{
  "type": "Feature",
  "properties": {
    "addr:full": "11149 Dowlin Dr Cincinnati OH 45241",
    "addr:postcode": "11149;45241",
    "addr:street": "Dowlin Dr",
    "iso:country": "US",
    "sg:address": "11149 Dowlin Dr",
    "sg:city": "Cincinnati",
    "sg:classifiers": [
      {
        "category": "Travel",
        "subcategory": "Hotels \u0026 Motels",
        "type": "Entertainment"
      }
    ],
    "sg:phone": "+1 513 772 2837",
    "sg:postcode": "45241",
    "sg:province": "OH",
    "sg:website": "www.cincinnatisharonville.gardeninn.com",
    "wof:name": "Hilton Garden Inn",
    "wof:placetype": "venue"
  },
  "geometry": {"coordinates":[-84.438316,39.271271],"type":"Point"}
}
