{
  "type": "Feature",
  "properties": {
    "iso:country":"US",
    "sg:address":"11149 Dowlin Dr",
    "sg:city":"Cincinnati",
    "sg:classifiers":[
        {
            "category":"Travel",
            "subcategory":"Hotels & Motels",
            "type":"Entertainment"
        }
    ],
    "sg:phone":"+1 513 772 2837",
    "sg:postcode":"45241",
    "sg:province":"OH",
    "sg:website":"www.cincinnatisharonville.gardeninn.com",
    "wof:name":"Hilton Garden Inn",
    "wof:placetype":"venue"
},
  "geometry": {"coordinates":[-84.438316,39.271271],"type":"Point"}
}