{
  "type": "Feature",
  "properties": {
    "addr:full": "285 Lloyd Rd West Union OH 45693",
    "addr:housenumber": "285",
    "addr:postcode": "45693",
    "addr:street": "Lloyd Rd",
    "iso:country": "US",
    "sg:address": "285 Lloyd Rd",
    "sg:city": "West Union",
    "sg:classifiers": [
      {
        "category": "Education",
        "subcategory": "School",
        "type": "Public Place"
      }
    ],
    "sg:phone": "+1 937 544 1665",
    "sg:postcode": "45693",
    "sg:province": "OH",
    "wof:name": "Adams County Special Education",
    "wof:placetype": "venue"
  },
  "geometry": {"coordinates":[-83.581786,38.81263],"type":"Point"}
}
