{
  "type": "Feature",
  "properties": {
    "iso:country":"US",
    "sg:address":"6027 State Rte 3",
    "sg:city":"Wilmington",
    "sg:classifiers":[
        {
            "category":"Building & Trades",
            "subcategory":"Plumbing",
            "type":"Services"
        }
    ],
    "sg:phone":"+1 937 584 4493",
    "sg:postcode":"45177",
    "sg:province":"OH",
    "sg:tags":[
        "plumbing",
        "contractor"
    ],
    "wof:name":"Hilderbrant Plumbing & Svc",
    "wof:placetype":"venue"
},
  "geometry": {"coordinates":[-83.935192,39.438587],"type":"Point"}
}