{
  "type": "Feature",
  "properties": {
    "addr:full": "6027 State Rte 3 Wilmington OH 45177",
    "addr:housenumber": "6027",
    "addr:postcode": "45177",
    "addr:street": "State Rte 3",
    "iso:country": "US",
    "sg:address": "6027 State Rte 3",
    "sg:city": "Wilmington",
    "sg:classifiers": [
      {
        "category": "Building \u0026 Trades",
        "subcategory": "Plumbing",
        "type": "Services"
      }
    ],
    "sg:phone": "+1 937 584 4493",
    "sg:postcode": "45177",
    "sg:province": "OH",
    "sg:tags": [
      "plumbing",
      "contractor"
    ],
    "wof:name": "Hilderbrant Plumbing \u0026 Svc",
    "wof:placetype": "venue"
  },
  "geometry": {"coordinates":[-83.935192,39.438587],"type":"Point"}
}
