{
  "type": "Feature",
  "properties": {
    "addr:full": "1685 Old Rushville Rd NE Rushville OH 43150",
    "addr:housenumber": "1685",
    "addr:postcode": "43150",
    "addr:street": "Old Rushville Rd Ne",
    "iso:country": "US",
    "sg:address": "1685 Old Rushville Rd NE",
    "sg:city": "Rushville",
    "sg:classifiers": [
      {
        "category": "Manufacturing",
        "subcategory": "Tools \u0026 Machinery",
        "type": "Manufacturing \u0026 Wholesale Goods"
      }
    ],
    "sg:phone": "+1 740 569 4633",
    "sg:postcode": "43150",
    "sg:province": "OH",
    "sg:tags": [
      "machine",
      "shop"
    ],
    "wof:name": "J Squared Machine",
    "wof:placetype": "venue"
  },
  "geometry": {"coordinates":[-82.410466,39.730702],"type":"Point"}
}
