{
  "type": "Feature",
  "properties": {
    "addr:full":"2734 E Main St Columbus OH 43209",
    "addr:housenumber":"2734",
    "addr:postcode":"43209",
    "addr:street":"E Main St",
    "iso:country":"US",
    "sg:address":"2734 E Main St",
    "sg:city":"Columbus",
    "sg:classifiers":[
        {
            "category":"Professional",
            "subcategory":"Business Services",
            "type":"Services"
        }
    ],
    "sg:phone":"+1 614 236 1917",
    "sg:postcode":"43209",
    "sg:province":"OH",
    "sg:tags":[
        "box",
        "mail"
    ],
    "wof:name":"Mail Box Main Street",
    "wof:placetype":"venue"
},
  "geometry": {"coordinates":[-82.925736,39.956948],"type":"Point"}
}