{
  "type": "Feature",
  "properties": {
    "iso:country":"US",
    "sg:address":"7515 Fawnmeadow Ln",
    "sg:city":"Cincinnati",
    "sg:classifiers":[
        {
            "category":"Building & Trades",
            "subcategory":"Construction",
            "type":"Services"
        }
    ],
    "sg:phone":"+1 513 321 7799",
    "sg:postcode":"45241",
    "sg:province":"OH",
    "sg:tags":[
        "painter"
    ],
    "wof:name":"Bentz Custom Painting",
    "wof:placetype":"venue"
},
  "geometry": {"coordinates":[-84.377937,39.303231],"type":"Point"}
}