{
  "type": "Feature",
  "properties": {
    "iso:country":"US",
    "sg:address":"3483 E Fulton St",
    "sg:city":"Columbus",
    "sg:classifiers":[
        {
            "category":"Utilities",
            "subcategory":"Refuse",
            "type":"Services"
        },
        {
            "category":"Wholesale",
            "subcategory":"Scrap",
            "type":"Manufacturing & Wholesale Goods"
        }
    ],
    "sg:phone":"+1 614 235 4886",
    "sg:postcode":"43227",
    "sg:province":"OH",
    "sg:tags":[
        "recycling",
        "material",
        "center",
        "system"
    ],
    "wof:name":"Buckeye Recycling Center",
    "wof:placetype":"venue"
},
  "geometry": {"coordinates":[-82.902946,39.952125],"type":"Point"}
}