{
  "type": "Feature",
  "properties": {
    "addr:full":"35200 Stevens Blvd Willoughby OH 44095",
    "addr:housenumber":"35200",
    "addr:postcode":"44095",
    "addr:street":"Stevens Blvd",
    "iso:country":"US",
    "sg:address":"35200 Stevens Blvd",
    "sg:city":"Willoughby",
    "sg:classifiers":[
        {
            "category":"Education",
            "subcategory":"School",
            "type":"Public Place"
        }
    ],
    "sg:phone":"+1 440 975 3720",
    "sg:postcode":"44095",
    "sg:province":"OH",
    "sg:tags":[
        "elementary",
        "educational",
        "facility"
    ],
    "wof:name":"Longfellow Elementary School",
    "wof:placetype":"venue"
},
  "geometry": {"coordinates":[-81.43770600000001,41.648889],"type":"Point"}
}