{
  "type": "Feature",
  "properties": {
    "addr:full": "38850 Center Ridge Rd North Ridgeville OH 44039",
    "addr:housenumber": "38850",
    "addr:postcode": "44039",
    "addr:street": "Center Ridge Rd",
    "iso:country": "US",
    "sg:address": "38850 Center Ridge Rd",
    "sg:city": "North Ridgeville",
    "sg:classifiers": [
      {
        "category": "Banks \u0026 Credit Unions",
        "subcategory": "Bank",
        "type": "Services"
      }
    ],
    "sg:phone": "+1 440 327 2533",
    "sg:postcode": "44039",
    "sg:province": "OH",
    "sg:tags": [
      "loan",
      "real estate"
    ],
    "wof:name": "First Financial Equities",
    "wof:placetype": "venue"
  },
  "geometry": {"coordinates":[-82.05319,41.383642],"type":"Point"}
}
