{
  "type": "Feature",
  "properties": {
    "addr:full":"5201 Northfield Rd Cleveland OH 44146",
    "addr:housenumber":"5201",
    "addr:postcode":"44146",
    "addr:street":"Northfield Rd",
    "iso:country":"US",
    "sg:address":"5201 Northfield Rd",
    "sg:city":"Cleveland",
    "sg:classifiers":[
        {
            "category":"Retail",
            "subcategory":"Auto Repair",
            "type":"Services"
        }
    ],
    "sg:phone":"+1 216 581 9349",
    "sg:postcode":"44146",
    "sg:province":"OH",
    "sg:tags":[
        "repairing",
        "automobile"
    ],
    "wof:name":"Maher Brothers Car Care",
    "wof:placetype":"venue"
},
  "geometry": {"coordinates":[-81.52729100000001,41.419621],"type":"Point"}
}