{
  "type": "Feature",
  "properties": {
    "addr:full": "1313 S Nickel Plate St Louisville OH 44641",
    "addr:housenumber": "1313",
    "addr:postcode": "44641",
    "addr:street": "S Nickel Plate St",
    "iso:country": "US",
    "sg:address": "1313 S Nickel Plate St",
    "sg:city": "Louisville",
    "sg:classifiers": [
      {
        "category": "Building \u0026 Trades",
        "subcategory": "Landscaping Services",
        "type": "Services"
      }
    ],
    "sg:phone": "+1 330 875 1191",
    "sg:postcode": "44641",
    "sg:province": "OH",
    "wof:name": "Victor Pandrea",
    "wof:placetype": "venue"
  },
  "geometry": {"coordinates":[-81.250685,40.828764],"type":"Point"}
}
