{
  "type": "Feature",
  "properties": {
    "addr:full": "265 Carpenter Rd Columbus OH 43230",
    "addr:housenumber": "265",
    "addr:postcode": "43230",
    "addr:street": "Carpenter Rd",
    "iso:country": "US",
    "sg:address": "265 Carpenter Rd",
    "sg:city": "Columbus",
    "sg:classifiers": [
      {
        "category": "Professional",
        "type": "Services"
      }
    ],
    "sg:phone": "+1 614 475 1411",
    "sg:postcode": "43230",
    "sg:province": "OH",
    "wof:name": "Grandmas Helper",
    "wof:placetype": "venue"
  },
  "geometry": {"coordinates":[-82.869556,40.021883],"type":"Point"}
}
