{
  "type": "Feature",
  "properties": {
    "addr:full":"1292 Delaware Ave Marion OH 43302",
    "addr:housenumber":"1292",
    "addr:postcode":"43302",
    "addr:street":"Delaware Ave",
    "iso:country":"US",
    "sg:address":"1292 Delaware Ave",
    "sg:city":"Marion",
    "sg:classifiers":[
        {
            "category":"Banks & Credit Unions",
            "subcategory":"Bank",
            "type":"Services"
        }
    ],
    "sg:phone":"+1 740 375 6818",
    "sg:postcode":"43302",
    "sg:province":"OH",
    "sg:tags":[
        "financing"
    ],
    "wof:name":"Citi Financial",
    "wof:placetype":"venue"
},
  "geometry": {"coordinates":[-83.12022399999999,40.565006],"type":"Point"}
}