{
  "type": "Feature",
  "properties": {
    "addr:full":"1490 Manning Pkwy Powell OH 43065",
    "addr:housenumber":"1490",
    "addr:postcode":"43065",
    "addr:street":"Manning Pkwy",
    "iso:country":"US",
    "sg:address":"1490 Manning Pkwy",
    "sg:city":"Powell",
    "sg:classifiers":[
        {
            "category":"Professional",
            "subcategory":"Employment Agencies",
            "type":"Services"
        }
    ],
    "sg:phone":"+1 614 318 8000",
    "sg:postcode":"43065",
    "sg:province":"OH",
    "sg:tags":[
        "executive",
        "placement"
    ],
    "wof:name":"Artemis",
    "wof:placetype":"venue"
},
  "geometry": {"coordinates":[-83.04269499999999,40.138415],"type":"Point"}
}