{
  "type": "Feature",
  "properties": {
    "iso:country":"US",
    "sg:address":"224 Maryland Ave",
    "sg:city":"Toledo",
    "sg:classifiers":[
        {
            "category":"Building & Trades",
            "subcategory":"Plumbing",
            "type":"Services"
        }
    ],
    "sg:phone":"+1 419 698 9568",
    "sg:postcode":"43605",
    "sg:province":"OH",
    "sg:tags":[
        "contractor",
        "system",
        "sewerage"
    ],
    "wof:name":"All Drains For Less",
    "wof:placetype":"venue"
},
  "geometry": {"coordinates":[-83.513141,41.649823],"type":"Point"}
}