{
  "type": "Feature",
  "properties": {
    "addr:full":"11206 Buckeye Rd Cleveland OH 44104",
    "addr:housenumber":"11206",
    "addr:postcode":"44104",
    "addr:street":"Buckeye Rd",
    "iso:country":"US",
    "sg:address":"11206 Buckeye Rd",
    "sg:city":"Cleveland",
    "sg:classifiers":[
        {
            "category":"Retail",
            "subcategory":"Repair Shop",
            "type":"Services"
        }
    ],
    "sg:phone":"+1 216 218 0156",
    "sg:postcode":"44104",
    "sg:province":"OH",
    "sg:tags":[
        "appliance"
    ],
    "wof:name":"A Appliance",
    "wof:placetype":"venue"
},
  "geometry": {"coordinates":[-81.60574,41.481243],"type":"Point"}
}