{
  "type": "Feature",
  "properties": {
    "addr:full": "91 Raymond Ave Shelby OH 44875",
    "addr:housenumber": "91",
    "addr:postcode": "44875",
    "addr:street": "Raymond Ave",
    "iso:country": "US",
    "sg:address": "91 Raymond Ave",
    "sg:city": "Shelby",
    "sg:classifiers": [
      {
        "category": "Health Services",
        "subcategory": "Clinic",
        "type": "Services"
      }
    ],
    "sg:phone": "+1 419 342 1752",
    "sg:postcode": "44875",
    "sg:province": "OH",
    "sg:tags": [
      "home"
    ],
    "wof:name": "Caring For You In-Home",
    "wof:placetype": "venue"
  },
  "geometry": {"coordinates":[-82.672665,40.88252],"type":"Point"}
}
