{
  "type": "Feature",
  "properties": {
    "iso:country":"US",
    "sg:address":"54 Mentor Ave",
    "sg:city":"Painesville",
    "sg:classifiers":[
        {
            "category":"Recreation",
            "type":"Entertainment"
        }
    ],
    "sg:phone":"+1 440 392 5912",
    "sg:postcode":"44077",
    "sg:province":"OH",
    "sg:tags":[
        "parks"
    ],
    "sg:website":"www.painesville.com",
    "wof:name":"Painesville Recreation Dept",
    "wof:placetype":"venue"
},
  "geometry": {"coordinates":[-81.246534,41.723628],"type":"Point"}
}