{
  "type": "Feature",
  "properties": {
    "iso:country":"US",
    "sg:address":"71480 Maynard Rd",
    "sg:city":"St Clairsville",
    "sg:classifiers":[
        {
            "category":"Organizations",
            "subcategory":"Religious Organization",
            "type":"Services"
        }
    ],
    "sg:phone":"+1 740 695 5280",
    "sg:postcode":"43950",
    "sg:province":"OH",
    "sg:tags":[
        "church"
    ],
    "wof:name":"Maynard United Methodist Chr",
    "wof:placetype":"venue"
},
  "geometry": {"coordinates":[-80.87989,40.122385],"type":"Point"}
}