{
  "type": "Feature",
  "properties": {
    "iso:country":"US",
    "sg:address":"2630 W 14th St",
    "sg:city":"Cleveland",
    "sg:classifiers":[
        {
            "category":"Food & Beverages",
            "subcategory":"Groceries & Convenience Stores",
            "type":"Retail Goods"
        }
    ],
    "sg:phone":"+1 216 241 9147",
    "sg:postcode":"44113",
    "sg:province":"OH",
    "wof:name":"Tremont Convenience Food Mart",
    "wof:placetype":"venue"
},
  "geometry": {"coordinates":[-81.69138,41.477077],"type":"Point"}
}