{
  "type": "Feature",
  "properties": {
    "addr:full": "5576 Forest Green Dr Toledo OH 43615",
    "addr:housenumber": "5576",
    "addr:postcode": "43615",
    "addr:street": "Forest Green Dr",
    "iso:country": "US",
    "sg:address": "5576 Forest Green Dr",
    "sg:city": "Toledo",
    "sg:classifiers": [
      {
        "category": "Professional",
        "type": "Services"
      }
    ],
    "sg:phone": "+1 419 865 2290",
    "sg:postcode": "43615",
    "sg:province": "OH",
    "wof:name": "Jab International Inc",
    "wof:placetype": "venue"
  },
  "geometry": {"coordinates":[-83.672436,41.62062],"type":"Point"}
}
