{
  "type": "Feature",
  "properties": {
    "iso:country":"US",
    "sg:address":"11756 Honeywell Dr",
    "sg:city":"Cincinnati",
    "sg:classifiers":[
        {
            "category":"Building & Trades",
            "subcategory":"Plumbing",
            "type":"Services"
        }
    ],
    "sg:phone":"+1 513 772 0050",
    "sg:postcode":"45241",
    "sg:province":"OH",
    "sg:tags":[
        "plumbing",
        "contractor"
    ],
    "wof:name":"Elliott and Bradley Plumbing",
    "wof:placetype":"venue"
},
  "geometry": {"coordinates":[-84.37229600000001,39.285108],"type":"Point"}
}