{
  "type": "Feature",
  "properties": {
    "addr:full": "455 Weavers-Fort Jefferson Rd Hollansburg OH 45332",
    "addr:housenumber": "455",
    "addr:postcode": "45332",
    "addr:street": "Weavers-Fort Jefferson Rd",
    "iso:country": "US",
    "sg:address": "455 Weavers-Fort Jefferson Rd",
    "sg:city": "Hollansburg",
    "sg:classifiers": [
      {
        "category": "Real Estate",
        "subcategory": "Real Estate Operator",
        "type": "Services"
      }
    ],
    "sg:phone": "+1 937 997 2115",
    "sg:postcode": "45332",
    "sg:province": "OH",
    "sg:tags": [
      "property",
      "lessor"
    ],
    "wof:name": "Kevin Denlinger",
    "wof:placetype": "venue"
  },
  "geometry": {"coordinates":[-84.789556,40.019231],"type":"Point"}
}
