{
  "type": "Feature",
  "properties": {
    "iso:country":"US",
    "sg:address":"869 Cedar Run Rd NE",
    "sg:city":"Newark",
    "sg:classifiers":[
        {
            "category":"Building & Trades",
            "subcategory":"Construction",
            "type":"Services"
        }
    ],
    "sg:phone":"+1 614 856 9218",
    "sg:postcode":"43055",
    "sg:province":"OH",
    "sg:tags":[
        "contractor"
    ],
    "sg:website":"www.mihomes.com",
    "wof:name":"M/I Homes",
    "wof:placetype":"venue"
},
  "geometry": {"coordinates":[-82.382929,40.080624],"type":"Point"}
}