{
  "type": "Feature",
  "properties": {
    "iso:country":"US",
    "sg:address":"19031 Lomond Blvd",
    "sg:city":"Cleveland",
    "sg:classifiers":[
        {
            "category":"Professional",
            "type":"Services"
        }
    ],
    "sg:phone":"+1 216 663 4708",
    "sg:postcode":"44122",
    "sg:province":"OH",
    "wof:name":"G L Svc Inc",
    "wof:placetype":"venue"
},
  "geometry": {"coordinates":[-81.544586,41.462088],"type":"Point"}
}