{
  "type": "Feature",
  "properties": {
    "addr:full": "55 W Main St Batavia OH 45103",
    "addr:housenumber": "55",
    "addr:postcode": "45103",
    "addr:street": "W Main St",
    "iso:country": "US",
    "sg:address": "55 W Main St",
    "sg:city": "Batavia",
    "sg:classifiers": [
      {
        "category": "Professional",
        "subcategory": "Lawyer \u0026 Legal Services",
        "type": "Services"
      }
    ],
    "sg:phone": "+1 513 732 2101",
    "sg:postcode": "45103",
    "sg:province": "OH",
    "sg:tags": [
      "attorney"
    ],
    "wof:name": "Michael J Riley",
    "wof:placetype": "venue"
  },
  "geometry": {"coordinates":[-84.179401,39.078438],"type":"Point"}
}
