{
  "type": "Feature",
  "properties": {
    "addr:full": "1110 E State St Fremont OH 43420",
    "addr:housenumber": "1110",
    "addr:postcode": "43420",
    "addr:street": "E State St",
    "iso:country": "US",
    "sg:address": "1110 E State St",
    "sg:city": "Fremont",
    "sg:classifiers": [
      {
        "category": "Health Services",
        "subcategory": "Chiropractor",
        "type": "Services"
      }
    ],
    "sg:phone": "+1 419 334 2671",
    "sg:postcode": "43420",
    "sg:province": "OH",
    "wof:name": "Darr Family Chiropractic",
    "wof:placetype": "venue"
  },
  "geometry": {"coordinates":[-83.097782,41.34328],"type":"Point"}
}
