{
  "type": "Feature",
  "properties": {
    "iso:country":"US",
    "sg:address":"1985 Zettler Center Dr",
    "sg:city":"Columbus",
    "sg:classifiers":[
        {
            "category":"Social Services",
            "type":"Services"
        }
    ],
    "sg:phone":"+1 614 275 3300",
    "sg:postcode":"43223",
    "sg:province":"OH",
    "wof:name":"Volunteers of America Inc",
    "wof:placetype":"venue"
},
  "geometry": {"coordinates":[-83.049935,39.930221],"type":"Point"}
}