{
  "type": "Feature",
  "properties": {
    "iso:country":"US",
    "sg:address":"700 Trenton Ave",
    "sg:city":"Findlay",
    "sg:classifiers":[
        {
            "category":"Restaurant",
            "type":"Food & Drink"
        }
    ],
    "sg:menulink":"http://www.allmenus.com/oh/findlay/200668-long-john-silvers/menu/",
    "sg:phone":"+1 419 423 7303",
    "sg:postcode":"45840",
    "sg:province":"OH",
    "sg:tags":[
        "seafood",
        "american"
    ],
    "wof:name":"Long John Silver's",
    "wof:placetype":"venue"
},
  "geometry": {"coordinates":[-83.659453,41.05876],"type":"Point"}
}