{
  "type": "Feature",
  "properties": {
    "iso:country":"US",
    "sg:address":"6 Madison St",
    "sg:city":"Norwalk",
    "sg:classifiers":[
        {
            "category":"Recreation",
            "type":"Entertainment"
        }
    ],
    "sg:phone":"+1 419 668 1320",
    "sg:postcode":"44857",
    "sg:province":"OH",
    "sg:tags":[
        "r",
        "alcoholic",
        "beverage"
    ],
    "wof:name":"Bill Dublos Inc",
    "wof:placetype":"venue"
},
  "geometry": {"coordinates":[-82.606939,41.243472],"type":"Point"}
}