{
  "type": "Feature",
  "properties": {
    "addr:full":"3875 King Ave Cleveland OH 44114",
    "addr:housenumber":"3875",
    "addr:postcode":"44114",
    "addr:street":"King Ave",
    "iso:country":"US",
    "sg:address":"3875 King Ave",
    "sg:city":"Cleveland",
    "sg:classifiers":[
        {
            "category":"Manufacturing",
            "subcategory":"Printing",
            "type":"Manufacturing & Wholesale Goods"
        }
    ],
    "sg:phone":"+1 216 426 5660",
    "sg:postcode":"44114",
    "sg:province":"OH",
    "sg:tags":[
        "printer",
        "commercial",
        "offset"
    ],
    "sg:website":"www.finelinelitho.com",
    "wof:name":"Fine Line Litho Inc",
    "wof:placetype":"venue"
},
  "geometry": {"coordinates":[-81.668108,41.518546],"type":"Point"}
}