{
  "type": "Feature",
  "properties": {
    "addr:full": "411 2nd St Portsmouth OH 45662",
    "addr:housenumber": "411",
    "addr:postcode": "45662",
    "addr:street": "2Nd St",
    "iso:country": "US",
    "sg:address": "411 2nd St",
    "sg:city": "Portsmouth",
    "sg:classifiers": [
      {
        "category": "Government",
        "subcategory": "Office",
        "type": "Public Place"
      }
    ],
    "sg:phone": "+1 740 353 3173",
    "sg:postcode": "45662",
    "sg:province": "OH",
    "sg:tags": [
      "county",
      "program",
      "health"
    ],
    "wof:name": "Scioto County Health Clinic",
    "wof:placetype": "venue"
  },
  "geometry": {"coordinates":[-83.004959,38.73179],"type":"Point"}
}
