{
  "type": "Feature",
  "properties": {
    "addr:full":"203 Main St Coshocton OH 43812",
    "addr:housenumber":"203",
    "addr:postcode":"43812",
    "addr:street":"Main St",
    "iso:country":"US",
    "sg:address":"203 Main St",
    "sg:city":"Coshocton",
    "sg:classifiers":[
        {
            "category":"Retail",
            "subcategory":"Auto Repair",
            "type":"Services"
        }
    ],
    "sg:phone":"+1 740 622 2092",
    "sg:postcode":"43812",
    "sg:province":"OH",
    "sg:tags":[
        "repairing",
        "automobile",
        "automotive",
        "general"
    ],
    "wof:name":"Hardestys Extended Auto Care",
    "wof:placetype":"venue"
},
  "geometry": {"coordinates":[-81.868769,40.273672],"type":"Point"}
}