{
  "type": "Feature",
  "properties": {
    "addr:full": "316 N Main St Columbiana OH 44408",
    "addr:housenumber": "316",
    "addr:postcode": "44408",
    "addr:street": "N Main St",
    "iso:country": "US",
    "sg:address": "316 N Main St",
    "sg:city": "Columbiana",
    "sg:classifiers": [
      {
        "category": "Autos \u0026 Motor Vehicles",
        "subcategory": "Automobile Sales",
        "type": "Retail Goods"
      }
    ],
    "sg:phone": "+1 330 482 3115",
    "sg:postcode": "44408",
    "sg:province": "OH",
    "sg:tags": [
      "dealers-used",
      "car",
      "used",
      "cars-wholesale"
    ],
    "wof:name": "Cornerstone Premium Motors",
    "wof:placetype": "venue"
  },
  "geometry": {"coordinates":[-80.693832,40.883049],"type":"Point"}
}
