{
  "type": "Feature",
  "properties": {
    "addr:full": "301 Greene St Marietta OH 45750",
    "addr:housenumber": "301",
    "addr:postcode": "45750",
    "addr:street": "Greene St",
    "iso:country": "US",
    "sg:address": "301 Greene St",
    "sg:city": "Marietta",
    "sg:classifiers": [
      {
        "category": "Shopping",
        "subcategory": "Pharmacy",
        "type": "Retail Goods"
      }
    ],
    "sg:phone": "+1 740 376 0769",
    "sg:postcode": "45750",
    "sg:province": "OH",
    "wof:name": "Rite Aid Pharmacy",
    "wof:placetype": "venue"
  },
  "geometry": {"coordinates":[-81.448847,39.412605],"type":"Point"}
}
