{
  "type": "Feature",
  "properties": {
    "iso:country":"US",
    "sg:address":"5317 Lake Rd E",
    "sg:city":"Geneva",
    "sg:classifiers":[
        {
            "category":"Travel",
            "subcategory":"Hotels & Motels",
            "type":"Entertainment"
        }
    ],
    "sg:phone":"+1 440 466 8747",
    "sg:postcode":"44041",
    "sg:province":"OH",
    "wof:name":"Allen Court Cottages",
    "wof:placetype":"venue"
},
  "geometry": {"coordinates":[-80.94637299999999,41.861063],"type":"Point"}
}