{
  "type": "Feature",
  "properties": {
    "addr:full": "5317 Lake Rd E Geneva OH 44041",
    "addr:housenumber": "5317",
    "addr:postcode": "44041",
    "addr:street": "Lake Rd E",
    "iso:country": "US",
    "sg:address": "5317 Lake Rd E",
    "sg:city": "Geneva",
    "sg:classifiers": [
      {
        "category": "Travel",
        "subcategory": "Hotels \u0026 Motels",
        "type": "Entertainment"
      }
    ],
    "sg:phone": "+1 440 466 8747",
    "sg:postcode": "44041",
    "sg:province": "OH",
    "wof:name": "Allen Court Cottages",
    "wof:placetype": "venue"
  },
  "geometry": {"coordinates":[-80.946373,41.861063],"type":"Point"}
}
