{
  "type": "Feature",
  "properties": {
    "addr:full": "97 Burns Ave Cincinnati OH 45215",
    "addr:housenumber": "97",
    "addr:postcode": "45215",
    "addr:street": "Burns Ave",
    "iso:country": "US",
    "sg:address": "97 Burns Ave",
    "sg:city": "Cincinnati",
    "sg:classifiers": [
      {
        "category": "Shopping",
        "subcategory": "Computers \u0026 Home Electronics",
        "type": "Retail Goods"
      }
    ],
    "sg:phone": "+1 513 821 5220",
    "sg:postcode": "45215",
    "sg:province": "OH",
    "sg:tags": [
      "software"
    ],
    "wof:name": "Finite Solutions Inc",
    "wof:placetype": "venue"
  },
  "geometry": {"coordinates":[-84.468779,39.220051],"type":"Point"}
}
