{
  "type": "Feature",
  "properties": {
    "iso:country":"US",
    "sg:address":"914 Quail Dr",
    "sg:city":"Fremont",
    "sg:classifiers":[
        {
            "category":"Real Estate",
            "subcategory":"Real Estate Operator",
            "type":"Services"
        }
    ],
    "sg:phone":"+1 419 334 9908",
    "sg:postcode":"43420",
    "sg:province":"OH",
    "sg:tags":[
        "apartment"
    ],
    "wof:name":"Little Bark Manor Apartments",
    "wof:placetype":"venue"
},
  "geometry": {"coordinates":[-83.10356899999999,41.33324],"type":"Point"}
}