{
  "type": "Feature",
  "properties": {
    "iso:country":"US",
    "sg:address":"3235 Manchester Rd",
    "sg:city":"Akron",
    "sg:classifiers":[
        {
            "category":"Personal",
            "subcategory":"Beauty Salon",
            "type":"Services"
        }
    ],
    "sg:phone":"+1 330 645 1915",
    "sg:postcode":"44319",
    "sg:province":"OH",
    "wof:name":"Famous Hair",
    "wof:placetype":"venue"
},
  "geometry": {"coordinates":[-81.55382400000001,41.012772],"type":"Point"}
}