{
  "type": "Feature",
  "properties": {
    "iso:country":"US",
    "sg:address":"3408 Clarksville Rd",
    "sg:city":"Waynesville",
    "sg:classifiers":[
        {
            "category":"Retail",
            "subcategory":"Repair Shop",
            "type":"Services"
        }
    ],
    "sg:phone":"+1 513 897 1888",
    "sg:postcode":"45068",
    "sg:province":"OH",
    "sg:tags":[
        "television",
        "radio"
    ],
    "wof:name":"Randy's TV",
    "wof:placetype":"venue"
},
  "geometry": {"coordinates":[-84.057666,39.481273],"type":"Point"}
}