{
  "type": "Feature",
  "properties": {
    "iso:country":"US",
    "sg:address":"5241 Southwyck Blvd",
    "sg:city":"Toledo",
    "sg:classifiers":[
        {
            "category":"Manufacturing",
            "subcategory":"Retail Goods",
            "type":"Manufacturing & Wholesale Goods"
        }
    ],
    "sg:phone":"+1 419 861 1467",
    "sg:postcode":"43614",
    "sg:province":"OH",
    "sg:tags":[
        "manufacturer"
    ],
    "wof:name":"Visionary Industries",
    "wof:placetype":"venue"
},
  "geometry": {"coordinates":[-83.667537,41.60009],"type":"Point"}
}