{
  "type": "Feature",
  "properties": {
    "addr:full": "16524 State Rte 568 Findlay OH 45840",
    "addr:housenumber": "16524",
    "addr:postcode": "45840",
    "addr:street": "State Rte 568",
    "iso:country": "US",
    "sg:address": "16524 State Rte 568",
    "sg:city": "Findlay",
    "sg:classifiers": [
      {
        "category": "Food \u0026 Beverages",
        "subcategory": "Fruits \u0026 Vegetables",
        "type": "Retail Goods"
      }
    ],
    "sg:phone": "+1 419 422 5541",
    "sg:postcode": "45840",
    "sg:province": "OH",
    "sg:tags": [
      "produce"
    ],
    "wof:name": "Shafer's Produce",
    "wof:placetype": "venue"
  },
  "geometry": {"coordinates":[-83.559874,41.03609],"type":"Point"}
}
