{
  "type": "Feature",
  "properties": {
    "iso:country":"US",
    "sg:address":"16524 State Rte 568",
    "sg:city":"Findlay",
    "sg:classifiers":[
        {
            "category":"Food & Beverages",
            "subcategory":"Fruits & Vegetables",
            "type":"Retail Goods"
        }
    ],
    "sg:phone":"+1 419 422 5541",
    "sg:postcode":"45840",
    "sg:province":"OH",
    "sg:tags":[
        "produce"
    ],
    "wof:name":"Shafer's Produce",
    "wof:placetype":"venue"
},
  "geometry": {"coordinates":[-83.55987399999999,41.03609],"type":"Point"}
}