{
  "type": "Feature",
  "properties": {
    "iso:country":"US",
    "sg:address":"46343 National Rd W",
    "sg:city":"Saint Clairsville",
    "sg:classifiers":[
        {
            "category":"Restaurant",
            "type":"Food & Drink"
        }
    ],
    "sg:phone":"+1 740 695 0125",
    "sg:postcode":"43950",
    "sg:province":"OH",
    "sg:tags":[
        "eating"
    ],
    "wof:name":"Gasbers",
    "wof:placetype":"venue"
},
  "geometry": {"coordinates":[-80.955529,40.072722],"type":"Point"}
}