{
  "type": "Feature",
  "properties": {
    "addr:full": "300 Marconi Blvd Columbus OH 43215",
    "addr:housenumber": "300",
    "addr:postcode": "43215",
    "addr:street": "Marconi Blvd",
    "iso:country": "US",
    "sg:address": "300 Marconi Blvd",
    "sg:city": "Columbus",
    "sg:classifiers": [
      {
        "category": "Real Estate",
        "subcategory": "Real Estate Agent",
        "type": "Services"
      }
    ],
    "sg:phone": "+1 614 228 4929",
    "sg:postcode": "43215",
    "sg:province": "OH",
    "sg:tags": [
      "management"
    ],
    "wof:name": "Putnam Hill Co",
    "wof:placetype": "venue"
  },
  "geometry": {"coordinates":[-83.005369,39.968374],"type":"Point"}
}
