{
  "type": "Feature",
  "properties": {
    "addr:full": "1104 Ohio Pike Cincinnati OH 45245",
    "addr:housenumber": "1104",
    "addr:postcode": "45245",
    "addr:street": "Ohio Pike",
    "iso:country": "US",
    "sg:address": "1104 Ohio Pike",
    "sg:city": "Cincinnati",
    "sg:classifiers": [
      {
        "category": "Retail",
        "subcategory": "Car Wash",
        "type": "Services"
      }
    ],
    "sg:phone": "+1 513 943 1520",
    "sg:postcode": "45245",
    "sg:province": "OH",
    "wof:name": "Water Works Car Wash",
    "wof:placetype": "venue"
  },
  "geometry": {"coordinates":[-84.2649,39.061401],"type":"Point"}
}
