{
  "type": "Feature",
  "properties": {
    "addr:full":"205 E Main St Russellville OH 45168",
    "addr:housenumber":"205",
    "addr:postcode":"45168",
    "addr:street":"E Main St",
    "iso:country":"US",
    "sg:address":"205 E Main St",
    "sg:city":"Russellville",
    "sg:classifiers":[
        {
            "category":"Personal",
            "subcategory":"Beauty Salon",
            "type":"Services"
        }
    ],
    "sg:phone":"+1 937 377 1163",
    "sg:postcode":"45168",
    "sg:province":"OH",
    "wof:name":"Connie's Hair Salon",
    "wof:placetype":"venue"
},
  "geometry": {"coordinates":[-83.78471,38.866778],"type":"Point"}
}