{
  "type": "Feature",
  "properties": {
    "iso:country":"US",
    "sg:address":"7030 Worthington Galena Rd",
    "sg:city":"Worthington",
    "sg:classifiers":[
        {
            "category":"Professional",
            "type":"Services"
        }
    ],
    "sg:phone":"+1 614 436 0392",
    "sg:postcode":"43085",
    "sg:province":"OH",
    "sg:tags":[
        "establishment"
    ],
    "wof:name":"Omega Performance",
    "wof:placetype":"venue"
},
  "geometry": {"coordinates":[-82.999106,40.108144],"type":"Point"}
}