{
  "type": "Feature",
  "properties": {
    "addr:full": "6185 Andora Rd NE Mechanicstown OH 44651",
    "addr:housenumber": "6185",
    "addr:postcode": "44651",
    "addr:street": "Andora Rd Ne",
    "iso:country": "US",
    "sg:address": "6185 Andora Rd NE",
    "sg:city": "Mechanicstown",
    "sg:classifiers": [
      {
        "category": "Manufacturing",
        "subcategory": "Wood Products",
        "type": "Manufacturing \u0026 Wholesale Goods"
      }
    ],
    "sg:phone": "+1 330 627 4385",
    "sg:postcode": "44651",
    "sg:province": "OH",
    "sg:tags": [
      "pallet",
      "mfg"
    ],
    "wof:name": "Hidden Valley Hardwood",
    "wof:placetype": "venue"
  },
  "geometry": {"coordinates":[-81.012952,40.660478],"type":"Point"}
}
