{
  "type": "Feature",
  "properties": {
    "addr:full":"1196 Gath Rd Sardinia OH 45171",
    "addr:housenumber":"1196",
    "addr:postcode":"45171",
    "addr:street":"Gath Rd",
    "iso:country":"US",
    "sg:address":"1196 Gath Rd",
    "sg:city":"Sardinia",
    "sg:classifiers":[
        {
            "category":"Wholesale",
            "subcategory":"Electrical",
            "type":"Manufacturing & Wholesale Goods"
        }
    ],
    "sg:phone":"+1 937 446 2779",
    "sg:postcode":"45171",
    "sg:province":"OH",
    "sg:tags":[
        "electronic"
    ],
    "wof:name":"Max Cone",
    "wof:placetype":"venue"
},
  "geometry": {"coordinates":[-83.82897800000001,39.04084],"type":"Point"}
}