{
  "type": "Feature",
  "properties": {
    "addr:full": "18900 Van Aken Blvd Cleveland OH 44122",
    "addr:housenumber": "18900",
    "addr:postcode": "44122",
    "addr:street": "Van Aken Blvd",
    "iso:country": "US",
    "sg:address": "18900 Van Aken Blvd",
    "sg:city": "Cleveland",
    "sg:classifiers": [
      {
        "category": "Personal",
        "type": "Services"
      }
    ],
    "sg:phone": "+1 216 268 5349",
    "sg:postcode": "44122",
    "sg:province": "OH",
    "sg:tags": [
      "therapist",
      "massage"
    ],
    "wof:name": "Human Touch",
    "wof:placetype": "venue"
  },
  "geometry": {"coordinates":[-81.551234,41.466347],"type":"Point"}
}
