{
  "type": "Feature",
  "properties": {
    "addr:full": "4562 Hinckley Industrial Pkwy Cleveland OH 44109",
    "addr:housenumber": "4562",
    "addr:postcode": "44109",
    "addr:street": "Hinckley Industrial Pkwy",
    "iso:country": "US",
    "sg:address": "4562 Hinckley Industrial Pkwy",
    "sg:city": "Cleveland",
    "sg:classifiers": [
      {
        "category": "Professional",
        "subcategory": "Detective \u0026 Security Services",
        "type": "Services"
      }
    ],
    "sg:phone": "+1 216 335 9121",
    "sg:postcode": "44109",
    "sg:province": "OH",
    "sg:tags": [
      "guard",
      "patrol"
    ],
    "wof:name": "Murray Management LLC",
    "wof:placetype": "venue"
  },
  "geometry": {"coordinates":[-81.67958,41.430075],"type":"Point"}
}
