{
  "type": "Feature",
  "properties": {
    "addr:full": "1150 Waycross Rd Cincinnati OH 45240",
    "addr:housenumber": "1150",
    "addr:postcode": "45240",
    "addr:street": "Waycross Rd",
    "iso:country": "US",
    "sg:address": "1150 Waycross Rd",
    "sg:city": "Cincinnati",
    "sg:classifiers": [
      {
        "category": "Real Estate",
        "subcategory": "Real Estate Agent",
        "type": "Services"
      }
    ],
    "sg:phone": "+1 513 825 5172",
    "sg:postcode": "45240",
    "sg:province": "OH",
    "wof:name": "Benchmark Management Corp",
    "wof:placetype": "venue"
  },
  "geometry": {"coordinates":[-84.522067,39.28352],"type":"Point"}
}
