{
  "type": "Feature",
  "properties": {
    "iso:country":"US",
    "sg:address":"1523 Meriline Ave",
    "sg:city":"Dayton",
    "sg:classifiers":[
        {
            "category":"Manufacturing",
            "subcategory":"Signs",
            "type":"Manufacturing & Wholesale Goods"
        }
    ],
    "sg:phone":"+1 937 253 0869",
    "sg:postcode":"45410",
    "sg:province":"OH",
    "sg:tags":[
        "specialty",
        "mfg"
    ],
    "sg:website":"www.flyingtricycle.com",
    "wof:name":"Flying Tricycle",
    "wof:placetype":"venue"
},
  "geometry": {"coordinates":[-84.134992,39.745766],"type":"Point"}
}