{
  "type": "Feature",
  "properties": {
    "addr:full": "4500 Rockside Rd Cleveland OH 44131",
    "addr:housenumber": "4500",
    "addr:postcode": "44131",
    "addr:street": "Rockside Rd",
    "iso:country": "US",
    "sg:address": "4500 Rockside Rd",
    "sg:city": "Cleveland",
    "sg:classifiers": [
      {
        "category": "Professional",
        "subcategory": "Research",
        "type": "Services"
      }
    ],
    "sg:phone": "+1 216 573 5550",
    "sg:postcode": "44131",
    "sg:province": "OH",
    "sg:tags": [
      "environmental",
      "ecological"
    ],
    "wof:name": "JDS Environmental Inc",
    "wof:placetype": "venue"
  },
  "geometry": {"coordinates":[-81.66064,41.398863],"type":"Point"}
}
