{
  "type": "Feature",
  "properties": {
    "addr:full": "548 W Central Ave Delaware OH 43015",
    "addr:housenumber": "548",
    "addr:postcode": "43015",
    "addr:street": "W Central Ave",
    "iso:country": "US",
    "sg:address": "548 W Central Ave",
    "sg:city": "Delaware",
    "sg:classifiers": [
      {
        "category": "Manufacturing",
        "subcategory": "Chemicals \u0026 Compounds",
        "type": "Manufacturing \u0026 Wholesale Goods"
      }
    ],
    "sg:phone": "+1 740 362 3071",
    "sg:postcode": "43015",
    "sg:province": "OH",
    "sg:tags": [
      "material",
      "technology"
    ],
    "wof:name": "Taasi Corporation",
    "wof:placetype": "venue"
  },
  "geometry": {"coordinates":[-83.088438,40.305989],"type":"Point"}
}
