{
  "type": "Feature",
  "properties": {
    "iso:country":"US",
    "sg:address":"548 W Central Ave",
    "sg:city":"Delaware",
    "sg:classifiers":[
        {
            "category":"Manufacturing",
            "subcategory":"Chemicals & Compounds",
            "type":"Manufacturing & Wholesale Goods"
        }
    ],
    "sg:phone":"+1 740 362 3071",
    "sg:postcode":"43015",
    "sg:province":"OH",
    "sg:tags":[
        "material",
        "technology"
    ],
    "wof:name":"Taasi Corporation",
    "wof:placetype":"venue"
},
  "geometry": {"coordinates":[-83.088438,40.305989],"type":"Point"}
}