{
  "type": "Feature",
  "properties": {
    "addr:full": "6010 Mahoning Ave Youngstown OH 44515",
    "addr:housenumber": "6010",
    "addr:postcode": "44515",
    "addr:street": "Mahoning Ave",
    "iso:country": "US",
    "sg:address": "6010 Mahoning Ave",
    "sg:city": "Youngstown",
    "sg:classifiers": [
      {
        "category": "Banks \u0026 Credit Unions",
        "subcategory": "Bank",
        "type": "Services"
      }
    ],
    "sg:phone": "+1 330 747 6686",
    "sg:postcode": "44515",
    "sg:province": "OH",
    "sg:tags": [
      "state",
      "commercial"
    ],
    "sg:website": "www.skyfi.com",
    "wof:name": "Sky Bank",
    "wof:placetype": "venue"
  },
  "geometry": {"coordinates":[-80.774989,41.099669],"type":"Point"}
}
