{
  "type": "Feature",
  "properties": {
    "iso:country":"US",
    "sg:address":"6010 Mahoning Ave",
    "sg:city":"Youngstown",
    "sg:classifiers":[
        {
            "category":"Banks & Credit Unions",
            "subcategory":"Bank",
            "type":"Services"
        }
    ],
    "sg:phone":"+1 330 747 6686",
    "sg:postcode":"44515",
    "sg:province":"OH",
    "sg:tags":[
        "state",
        "commercial"
    ],
    "sg:website":"www.skyfi.com",
    "wof:name":"Sky Bank",
    "wof:placetype":"venue"
},
  "geometry": {"coordinates":[-80.77498900000001,41.099669],"type":"Point"}
}