{
  "type": "Feature",
  "properties": {
    "iso:country":"US",
    "sg:address":"67695 Mall Rd",
    "sg:city":"St Clairsville",
    "sg:classifiers":[
        {
            "category":"Restaurant",
            "type":"Food & Drink"
        }
    ],
    "sg:phone":"+1 740 695 4585",
    "sg:postcode":"43950",
    "sg:province":"OH",
    "sg:website":"www.rax-online.com",
    "wof:name":"Rax Restaurant",
    "wof:placetype":"venue"
},
  "geometry": {"coordinates":[-80.862897,40.068397],"type":"Point"}
}