{
  "type": "Feature",
  "properties": {
    "addr:full":"12103 Union Ave Cleveland OH 44105",
    "addr:housenumber":"12103",
    "addr:postcode":"44105",
    "addr:street":"Union Ave",
    "iso:country":"US",
    "sg:address":"12103 Union Ave",
    "sg:city":"Cleveland",
    "sg:classifiers":[
        {
            "category":"Autos & Motor Vehicles",
            "subcategory":"Automobile Sales",
            "type":"Retail Goods"
        }
    ],
    "sg:phone":"+1 216 295 9473",
    "sg:postcode":"44105",
    "sg:province":"OH",
    "sg:tags":[
        "used"
    ],
    "wof:name":"Wise Choice",
    "wof:placetype":"venue"
},
  "geometry": {"coordinates":[-81.596892,41.463773],"type":"Point"}
}