{
  "type": "Feature",
  "properties": {
    "addr:full": "1123 E Main St Eaton OH 45320",
    "addr:housenumber": "1123",
    "addr:postcode": "45320",
    "addr:street": "E Main St",
    "iso:country": "US",
    "sg:address": "1123 E Main St",
    "sg:city": "Eaton",
    "sg:classifiers": [
      {
        "category": "Shopping",
        "type": "Retail Goods"
      },
      {
        "category": "Wholesale",
        "subcategory": "Electrical",
        "type": "Manufacturing \u0026 Wholesale Goods"
      }
    ],
    "sg:phone": "+1 937 472 1000",
    "sg:postcode": "45320",
    "sg:province": "OH",
    "sg:tags": [
      "electronic",
      "radiotelephone",
      "cellular",
      "telephone"
    ],
    "wof:name": "Complete Communications Inc",
    "wof:placetype": "venue"
  },
  "geometry": {"coordinates":[-84.617812,39.74379],"type":"Point"}
}
