{
  "type": "Feature",
  "properties": {
    "addr:full": "11475 Market St North Lima OH 44452",
    "addr:housenumber": "11475",
    "addr:postcode": "44452",
    "addr:street": "Market St",
    "iso:country": "US",
    "sg:address": "11475 Market St",
    "sg:city": "North Lima",
    "sg:classifiers": [
      {
        "category": "Autos \u0026 Motor Vehicles",
        "subcategory": "Auto Supplies",
        "type": "Retail Goods"
      }
    ],
    "sg:phone": "+1 330 549 2181",
    "sg:postcode": "44452",
    "sg:province": "OH",
    "wof:name": "NAPA Auto Parts",
    "wof:placetype": "venue"
  },
  "geometry": {"coordinates":[-80.659497,40.956806],"type":"Point"}
}
