{
  "type": "Feature",
  "properties": {
    "iso:country":"US",
    "sg:address":"1146 Sleeping Meadow Dr",
    "sg:city":"New Albany",
    "sg:classifiers":[
        {
            "category":"Building & Trades",
            "subcategory":"Construction",
            "type":"Services"
        }
    ],
    "sg:phone":"+1 614 822 6081",
    "sg:postcode":"43054",
    "sg:province":"OH",
    "sg:tags":[
        "house"
    ],
    "wof:name":"William Thorton Builders",
    "wof:placetype":"venue"
},
  "geometry": {"coordinates":[-82.83740899999999,40.051761],"type":"Point"}
}