{
  "type": "Feature",
  "properties": {
    "addr:full":"3996 Cloverdale Rd Medway OH 45341",
    "addr:housenumber":"3996",
    "addr:postcode":"45341",
    "addr:street":"Cloverdale Rd",
    "iso:country":"US",
    "sg:address":"3996 Cloverdale Rd",
    "sg:city":"Medway",
    "sg:classifiers":[
        {
            "category":"Wholesale",
            "subcategory":"Chemicals & Plastics",
            "type":"Manufacturing & Wholesale Goods"
        }
    ],
    "sg:phone":"+1 937 849 6618",
    "sg:postcode":"45341",
    "sg:province":"OH",
    "sg:tags":[
        "repair"
    ],
    "wof:name":"Expert Spa Service",
    "wof:placetype":"venue"
},
  "geometry": {"coordinates":[-84.025779,39.874738],"type":"Point"}
}