{
  "type": "Feature",
  "properties": {
    "addr:full":"4737 E Main St Columbus OH 43213",
    "addr:housenumber":"4737",
    "addr:postcode":"43213",
    "addr:street":"E Main St",
    "iso:country":"US",
    "sg:address":"4737 E Main St",
    "sg:city":"Columbus",
    "sg:classifiers":[
        {
            "category":"Shopping",
            "subcategory":"Beauty & Cosmetics",
            "type":"Retail Goods"
        }
    ],
    "sg:phone":"+1 614 864 1474",
    "sg:postcode":"43213",
    "sg:province":"OH",
    "sg:tags":[
        "e",
        "merchandise"
    ],
    "wof:name":"Sally Beauty Supply",
    "wof:placetype":"venue"
},
  "geometry": {"coordinates":[-82.87262800000001,39.955291],"type":"Point"}
}