{
  "type": "Feature",
  "properties": {
    "addr:full": "7599 W Chester Rd West Chester OH 45069",
    "addr:housenumber": "7599",
    "addr:postcode": "45069",
    "addr:street": "W Chester Rd",
    "iso:country": "US",
    "sg:address": "7599 W Chester Rd",
    "sg:city": "West Chester",
    "sg:classifiers": [
      {
        "category": "Professional",
        "type": "Services"
      }
    ],
    "sg:phone": "+1 513 779 6884",
    "sg:postcode": "45069",
    "sg:province": "OH",
    "sg:tags": [
      "establishment"
    ],
    "wof:name": "Youth Marketing Solutions",
    "wof:placetype": "venue"
  },
  "geometry": {"coordinates":[-84.372011,39.318535],"type":"Point"}
}
