{
  "type": "Feature",
  "properties": {
    "iso:country":"US",
    "sg:address":"120 N Enterprise St",
    "sg:city":"Celina",
    "sg:classifiers":[
        {
            "category":"Autos & Motor Vehicles",
            "subcategory":"Auto Supplies",
            "type":"Retail Goods"
        }
    ],
    "sg:phone":"+1 419 586 2331",
    "sg:postcode":"45822",
    "sg:province":"OH",
    "wof:name":"Lockwood Performance",
    "wof:placetype":"venue"
},
  "geometry": {"coordinates":[-84.556449,40.549317],"type":"Point"}
}