{
  "type": "Feature",
  "properties": {
    "addr:full":"2825 Briggston Ave Columbus OH 43204",
    "addr:housenumber":"2825",
    "addr:postcode":"43204",
    "addr:street":"Briggston Ave",
    "iso:country":"US",
    "sg:address":"2825 Briggston Ave",
    "sg:city":"Columbus",
    "sg:classifiers":[
        {
            "category":"Real Estate",
            "subcategory":"Real Estate Agent",
            "type":"Services"
        }
    ],
    "sg:phone":"+1 614 351 1443",
    "sg:postcode":"43204",
    "sg:province":"OH",
    "wof:name":"Germany Realty Co",
    "wof:placetype":"venue"
},
  "geometry": {"coordinates":[-83.071108,39.926592],"type":"Point"}
}