{
  "type": "Feature",
  "properties": {
    "addr:full": "3051 Delta Marine Dr Reynoldsburg OH 43068",
    "addr:housenumber": "3051",
    "addr:postcode": "43068",
    "addr:street": "Delta Marine Dr",
    "iso:country": "US",
    "sg:address": "3051 Delta Marine Dr",
    "sg:city": "Reynoldsburg",
    "sg:classifiers": [
      {
        "category": "Professional",
        "type": "Services"
      }
    ],
    "sg:phone": "+1 614 322 1469",
    "sg:postcode": "43068",
    "sg:province": "OH",
    "wof:name": "Ameritech Training Center",
    "wof:placetype": "venue"
  },
  "geometry": {"coordinates":[-82.825489,39.918615],"type":"Point"}
}
