{
  "type": "Feature",
  "properties": {
    "addr:full": "1792 Brice Rd Reynoldsburg OH 43068",
    "addr:housenumber": "1792",
    "addr:postcode": "43068",
    "addr:street": "Brice Rd",
    "iso:country": "US",
    "sg:address": "1792 Brice Rd",
    "sg:city": "Reynoldsburg",
    "sg:classifiers": [
      {
        "category": "Retail",
        "subcategory": "Self-service Laundry",
        "type": "Services"
      }
    ],
    "sg:phone": "+1 614 861 9475",
    "sg:postcode": "43068",
    "sg:province": "OH",
    "wof:name": "Reynoldsburg Sunshine Ctr",
    "wof:placetype": "venue"
  },
  "geometry": {"coordinates":[-82.829634,39.944138],"type":"Point"}
}
