{
  "type": "Feature",
  "properties": {
    "addr:full": "449 Howe St Akron OH 44307",
    "addr:housenumber": "449",
    "addr:postcode": "44307",
    "addr:street": "Howe St",
    "iso:country": "US",
    "sg:address": "449 Howe St",
    "sg:city": "Akron",
    "sg:classifiers": [
      {
        "category": "Retail",
        "subcategory": "Photofinishing",
        "type": "Services"
      }
    ],
    "sg:phone": "+1 330 945 7166",
    "sg:postcode": "44307",
    "sg:province": "OH",
    "sg:tags": [
      "photo",
      "finishing"
    ],
    "wof:name": "Target One Hour Photo",
    "wof:placetype": "venue"
  },
  "geometry": {"coordinates":[-81.542761,41.067172],"type":"Point"}
}
