{
  "type": "Feature",
  "properties": {
    "iso:country":"US",
    "sg:address":"2820 W Market St",
    "sg:city":"Fairlawn",
    "sg:classifiers":[
        {
            "category":"Health Services",
            "subcategory":"Optometrist",
            "type":"Services"
        }
    ],
    "sg:phone":"+1 330 253 2436",
    "sg:postcode":"44333",
    "sg:province":"OH",
    "wof:name":"Borodkin Eyecare",
    "wof:placetype":"venue"
},
  "geometry": {"coordinates":[-81.60522400000001,41.125814],"type":"Point"}
}