{
  "type": "Feature",
  "properties": {
    "addr:full":"2206 Grand Blvd Hamilton OH 45011",
    "addr:housenumber":"2206",
    "addr:postcode":"45011",
    "addr:street":"Grand Blvd",
    "iso:country":"US",
    "sg:address":"2206 Grand Blvd",
    "sg:city":"Hamilton",
    "sg:classifiers":[
        {
            "category":"Food & Beverages",
            "subcategory":"Groceries & Convenience Stores",
            "type":"Retail Goods"
        }
    ],
    "sg:phone":"+1 513 863 6680",
    "sg:postcode":"45011",
    "sg:province":"OH",
    "wof:name":"Mac's",
    "wof:placetype":"venue"
},
  "geometry": {"coordinates":[-84.53899800000001,39.381435],"type":"Point"}
}