{
  "type": "Feature",
  "properties": {
    "addr:full": "8340 N Gilmore Rd Hamilton OH 45015",
    "addr:housenumber": "8340",
    "addr:postcode": "45015",
    "addr:street": "N Gilmore Rd",
    "iso:country": "US",
    "sg:address": "8340 N Gilmore Rd",
    "sg:city": "Hamilton",
    "sg:classifiers": [
      {
        "category": "Home \u0026 Garden",
        "subcategory": "Garden Supply",
        "type": "Retail Goods"
      }
    ],
    "sg:phone": "+1 513 893 5296",
    "sg:postcode": "45015",
    "sg:province": "OH",
    "sg:tags": [
      "mulch"
    ],
    "wof:name": "For All Seasons Landscaping",
    "wof:placetype": "venue"
  },
  "geometry": {"coordinates":[-84.519812,39.349654],"type":"Point"}
}
