{
  "type": "Feature",
  "properties": {
    "addr:full": "8360 Rausch Dr Plain City OH 43064",
    "addr:housenumber": "8360",
    "addr:postcode": "43064",
    "addr:street": "Rausch Dr",
    "iso:country": "US",
    "sg:address": "8360 Rausch Dr",
    "sg:city": "Plain City",
    "sg:classifiers": [
      {
        "category": "Autos \u0026 Motor Vehicles",
        "subcategory": "Automobile Sales",
        "type": "Retail Goods"
      }
    ],
    "sg:phone": "+1 614 873 5536",
    "sg:postcode": "43064",
    "sg:province": "OH",
    "sg:tags": [
      "classic"
    ],
    "wof:name": "Driving Machines",
    "wof:placetype": "venue"
  },
  "geometry": {"coordinates":[-83.206081,40.129915],"type":"Point"}
}
