{
  "type": "Feature",
  "properties": {
    "addr:full": "1300 Park Dr Middletown OH 45044",
    "addr:housenumber": "1300",
    "addr:postcode": "45044",
    "addr:street": "Park Dr",
    "iso:country": "US",
    "sg:address": "1300 Park Dr",
    "sg:city": "Middletown",
    "sg:classifiers": [
      {
        "category": "Building \u0026 Trades",
        "subcategory": "Plumbing",
        "type": "Services"
      }
    ],
    "sg:phone": "+1 513 398 1053",
    "sg:postcode": "45044",
    "sg:province": "OH",
    "sg:tags": [
      "plumbing",
      "contractor"
    ],
    "wof:name": "Accurate Sewer \u0026 Drain Clean",
    "wof:placetype": "venue"
  },
  "geometry": {"coordinates":[-84.376208,39.500299],"type":"Point"}
}
