{
  "type": "Feature",
  "properties": {
    "addr:full": "3167 Creekside Pkwy Groveport OH 43137",
    "addr:housenumber": "3167",
    "addr:postcode": "43137",
    "addr:street": "Creekside Pkwy",
    "iso:country": "US",
    "sg:address": "3167 Creekside Pkwy",
    "sg:city": "Groveport",
    "sg:classifiers": [
      {
        "category": "Retail",
        "subcategory": "Auto Repair",
        "type": "Services"
      }
    ],
    "sg:phone": "+1 614 491 9713",
    "sg:postcode": "43137",
    "sg:province": "OH",
    "sg:tags": [
      "truck"
    ],
    "wof:name": "Duke's Garage",
    "wof:placetype": "venue"
  },
  "geometry": {"coordinates":[-82.94526,39.852655],"type":"Point"}
}
