{
  "type": "Feature",
  "properties": {
    "addr:full": "1134 Evergreen Rd Columbus OH 43207",
    "addr:housenumber": "1134",
    "addr:postcode": "43207",
    "addr:street": "Evergreen Rd",
    "iso:country": "US",
    "sg:address": "1134 Evergreen Rd",
    "sg:city": "Columbus",
    "sg:classifiers": [
      {
        "category": "Retail",
        "subcategory": "Auto Repair",
        "type": "Services"
      }
    ],
    "sg:phone": "+1 614 491 0184",
    "sg:postcode": "43207",
    "sg:province": "OH",
    "sg:tags": [
      "repairing",
      "automobile"
    ],
    "wof:name": "Hudson Auto Sales Inc",
    "wof:placetype": "venue"
  },
  "geometry": {"coordinates":[-82.962116,39.907312],"type":"Point"}
}
