{
  "type": "Feature",
  "properties": {
    "iso:country":"US",
    "sg:address":"1134 Evergreen Rd",
    "sg:city":"Columbus",
    "sg:classifiers":[
        {
            "category":"Retail",
            "subcategory":"Auto Repair",
            "type":"Services"
        }
    ],
    "sg:phone":"+1 614 491 0184",
    "sg:postcode":"43207",
    "sg:province":"OH",
    "sg:tags":[
        "repairing",
        "automobile"
    ],
    "wof:name":"Hudson Auto Sales Inc",
    "wof:placetype":"venue"
},
  "geometry": {"coordinates":[-82.96211599999999,39.907312],"type":"Point"}
}