{
  "type": "Feature",
  "properties": {
    "addr:full":"297 Center Rd Cleveland OH 44146",
    "addr:housenumber":"297",
    "addr:postcode":"44146",
    "addr:street":"Center Rd",
    "iso:country":"US",
    "sg:address":"297 Center Rd",
    "sg:city":"Cleveland",
    "sg:classifiers":[
        {
            "category":"Organizations",
            "subcategory":"Religious Organization",
            "type":"Services"
        }
    ],
    "sg:phone":"+1 440 439 4448",
    "sg:postcode":"44146",
    "sg:province":"OH",
    "wof:name":"Islam Ahmaddiya Mvmt Inc",
    "wof:placetype":"venue"
},
  "geometry": {"coordinates":[-81.537217,41.402128],"type":"Point"}
}