{
  "type": "Feature",
  "properties": {
    "iso:country":"US",
    "sg:address":"2944 Murray Rd",
    "sg:city":"New London",
    "sg:classifiers":[
        {
            "category":"Building & Trades",
            "subcategory":"Construction",
            "type":"Services"
        }
    ],
    "sg:phone":"+1 419 929 8831",
    "sg:postcode":"44851",
    "sg:province":"OH",
    "sg:tags":[
        "nonresidential"
    ],
    "wof:name":"Ultimate Storage & Access",
    "wof:placetype":"venue"
},
  "geometry": {"coordinates":[-82.476403,41.144072],"type":"Point"}
}