{
  "type": "Feature",
  "properties": {
    "addr:full": "12613 Larchmere Blvd Cleveland OH 44120",
    "addr:housenumber": "12613",
    "addr:postcode": "44120",
    "addr:street": "Larchmere Blvd",
    "iso:country": "US",
    "sg:address": "12613 Larchmere Blvd",
    "sg:city": "Cleveland",
    "sg:classifiers": [
      {
        "category": "Real Estate",
        "subcategory": "Real Estate Operator",
        "type": "Services"
      }
    ],
    "sg:phone": "+1 216 721 5093",
    "sg:postcode": "44120",
    "sg:province": "OH",
    "sg:tags": [
      "building",
      "apartment"
    ],
    "wof:name": "Moreland Building Inc",
    "wof:placetype": "venue"
  },
  "geometry": {"coordinates":[-81.594598,41.487755],"type":"Point"}
}
