{
  "type": "Feature",
  "properties": {
    "iso:country":"US",
    "sg:address":"7722 Union Schoolhouse Rd",
    "sg:city":"Dayton",
    "sg:classifiers":[
        {
            "category":"Building & Trades",
            "subcategory":"Landscaping Services",
            "type":"Services"
        }
    ],
    "sg:phone":"+1 937 235 5296",
    "sg:postcode":"45424",
    "sg:province":"OH",
    "wof:name":"Parascape Lawns & Lanscaping",
    "wof:placetype":"venue"
},
  "geometry": {"coordinates":[-84.103008,39.812417],"type":"Point"}
}