{
  "type": "Feature",
  "properties": {
    "addr:full": "7722 Union Schoolhouse Rd Dayton OH 45424",
    "addr:housenumber": "7722",
    "addr:postcode": "45424",
    "addr:street": "Union Schoolhouse Rd",
    "iso:country": "US",
    "sg:address": "7722 Union Schoolhouse Rd",
    "sg:city": "Dayton",
    "sg:classifiers": [
      {
        "category": "Building \u0026 Trades",
        "subcategory": "Landscaping Services",
        "type": "Services"
      }
    ],
    "sg:phone": "+1 937 235 5296",
    "sg:postcode": "45424",
    "sg:province": "OH",
    "wof:name": "Parascape Lawns \u0026 Lanscaping",
    "wof:placetype": "venue"
  },
  "geometry": {"coordinates":[-84.103008,39.812417],"type":"Point"}
}
