{
  "type": "Feature",
  "properties": {
    "addr:full":"660 Beaver Creek Cir Maumee OH 43537",
    "addr:housenumber":"660",
    "addr:postcode":"43537",
    "addr:street":"Beaver Creek Cir",
    "iso:country":"US",
    "sg:address":"660 Beaver Creek Cir",
    "sg:city":"Maumee",
    "sg:classifiers":[
        {
            "category":"Health Services",
            "subcategory":"Doctor",
            "type":"Services"
        }
    ],
    "sg:phone":"+1 419 891 6210",
    "sg:postcode":"43537",
    "sg:province":"OH",
    "sg:tags":[
        "physician",
        "surgeon"
    ],
    "wof:name":"Arrowhead Family Physicians",
    "wof:placetype":"venue"
},
  "geometry": {"coordinates":[-83.688942,41.575511],"type":"Point"}
}