{
  "type": "Feature",
  "properties": {
    "addr:full": "6450 Grafton Rd Valley City OH 44280",
    "addr:housenumber": "6450",
    "addr:postcode": "44280",
    "addr:street": "Grafton Rd",
    "iso:country": "US",
    "sg:address": "6450 Grafton Rd",
    "sg:city": "Valley City",
    "sg:classifiers": [
      {
        "category": "Manufacturing",
        "subcategory": "Furniture",
        "type": "Manufacturing \u0026 Wholesale Goods"
      },
      {
        "category": "Building \u0026 Trades",
        "subcategory": "Construction",
        "type": "Services"
      }
    ],
    "sg:phone": "+1 330 483 9020",
    "sg:postcode": "44280",
    "sg:province": "OH",
    "sg:tags": [
      "cabinet",
      "fixture",
      "maker",
      "store",
      "mfg"
    ],
    "sg:website": "www.customsurroundings.com",
    "wof:name": "Custom Surroundings Inc",
    "wof:placetype": "venue"
  },
  "geometry": {"coordinates":[-81.918602,41.260088],"type":"Point"}
}
