{
  "type": "Feature",
  "properties": {
    "iso:country":"US",
    "sg:address":"6450 Grafton Rd",
    "sg:city":"Valley City",
    "sg:classifiers":[
        {
            "category":"Manufacturing",
            "subcategory":"Furniture",
            "type":"Manufacturing & Wholesale Goods"
        },
        {
            "category":"Building & Trades",
            "subcategory":"Construction",
            "type":"Services"
        }
    ],
    "sg:phone":"+1 330 483 9020",
    "sg:postcode":"44280",
    "sg:province":"OH",
    "sg:tags":[
        "cabinet",
        "fixture",
        "maker",
        "store",
        "mfg"
    ],
    "sg:website":"www.customsurroundings.com",
    "wof:name":"Custom Surroundings Inc",
    "wof:placetype":"venue"
},
  "geometry": {"coordinates":[-81.91860200000001,41.260088],"type":"Point"}
}