{
  "type": "Feature",
  "properties": {
    "addr:full":"1967 Uniondale Dr Stow OH 44224",
    "addr:housenumber":"1967",
    "addr:postcode":"44224",
    "addr:street":"Uniondale Dr",
    "iso:country":"US",
    "sg:address":"1967 Uniondale Dr",
    "sg:city":"Stow",
    "sg:classifiers":[
        {
            "category":"Building & Trades",
            "subcategory":"Construction",
            "type":"Services"
        }
    ],
    "sg:phone":"+1 330 686 2092",
    "sg:postcode":"44224",
    "sg:province":"OH",
    "sg:tags":[
        "hanging",
        "contractor"
    ],
    "wof:name":"L&Z Painting",
    "wof:placetype":"venue"
},
  "geometry": {"coordinates":[-81.43178399999999,41.170172],"type":"Point"}
}