{
  "type": "Feature",
  "properties": {
    "addr:full": "10561 Chester Rd Cincinnati OH 45215",
    "addr:housenumber": "10561",
    "addr:postcode": "45215",
    "addr:street": "Chester Rd",
    "iso:country": "US",
    "sg:address": "10561 Chester Rd",
    "sg:city": "Cincinnati",
    "sg:classifiers": [
      {
        "category": "Coffee \u0026 Tea",
        "type": "Food \u0026 Drink"
      },
      {
        "category": "Wholesale",
        "subcategory": "Vending Machines",
        "type": "Manufacturing \u0026 Wholesale Goods"
      }
    ],
    "sg:phone": "+1 513 772 3324",
    "sg:postcode": "45215",
    "sg:province": "OH",
    "sg:tags": [
      "break",
      "supply"
    ],
    "sg:website": "http://www.ypad.com/business-profile.cfm/state/OH/city/Woodlawn/ppid/15662",
    "wof:name": "Premiere Vending",
    "wof:placetype": "venue"
  },
  "geometry": {"coordinates":[-84.453558,39.259839],"type":"Point"}
}
