{
  "type": "Feature",
  "properties": {
    "addr:full": "1571 N Central Dr Dayton OH 45432",
    "addr:housenumber": "1571",
    "addr:postcode": "45432",
    "addr:street": "N Central Dr",
    "iso:country": "US",
    "sg:address": "1571 N Central Dr",
    "sg:city": "Dayton",
    "sg:classifiers": [
      {
        "category": "Building \u0026 Trades",
        "subcategory": "Plumbing",
        "type": "Services"
      }
    ],
    "sg:phone": "+1 937 426 4622",
    "sg:postcode": "45432",
    "sg:province": "OH",
    "sg:tags": [
      "air",
      "heating",
      "conditioning",
      "contractor"
    ],
    "wof:name": "Hussong Shtmtl Htg \u0026 Coolg Co",
    "wof:placetype": "venue"
  },
  "geometry": {"coordinates":[-84.07618,39.736002],"type":"Point"}
}
