{
  "type": "Feature",
  "properties": {
    "iso:country":"US",
    "sg:address":"1571 N Central Dr",
    "sg:city":"Dayton",
    "sg:classifiers":[
        {
            "category":"Building & Trades",
            "subcategory":"Plumbing",
            "type":"Services"
        }
    ],
    "sg:phone":"+1 937 426 4622",
    "sg:postcode":"45432",
    "sg:province":"OH",
    "sg:tags":[
        "air",
        "heating",
        "conditioning",
        "contractor"
    ],
    "wof:name":"Hussong Shtmtl Htg & Coolg Co",
    "wof:placetype":"venue"
},
  "geometry": {"coordinates":[-84.07617999999999,39.736002],"type":"Point"}
}