{
  "type": "Feature",
  "properties": {
    "addr:full":"4004 Superior Ave Cincinnati OH 45236",
    "addr:housenumber":"4004",
    "addr:postcode":"45236",
    "addr:street":"Superior Ave",
    "iso:country":"US",
    "sg:address":"4004 Superior Ave",
    "sg:city":"Cincinnati",
    "sg:classifiers":[
        {
            "category":"Building & Trades",
            "subcategory":"Plumbing",
            "type":"Services"
        }
    ],
    "sg:phone":"+1 513 793 5162",
    "sg:postcode":"45236",
    "sg:province":"OH",
    "sg:tags":[
        "contractor"
    ],
    "wof:name":"M & S Heating & A & Appl Repr",
    "wof:placetype":"venue"
},
  "geometry": {"coordinates":[-84.400988,39.200707],"type":"Point"}
}