{
  "type": "Feature",
  "properties": {
    "addr:full":"3274 Beekman St Cincinnati OH 45223",
    "addr:housenumber":"3274",
    "addr:postcode":"45223",
    "addr:street":"Beekman St",
    "iso:country":"US",
    "sg:address":"3274 Beekman St",
    "sg:city":"Cincinnati",
    "sg:classifiers":[
        {
            "category":"Wholesale",
            "subcategory":"Home Furnishings",
            "type":"Manufacturing & Wholesale Goods"
        }
    ],
    "sg:phone":"+1 513 681 1774",
    "sg:postcode":"45223",
    "sg:province":"OH",
    "sg:tags":[
        "housewares"
    ],
    "wof:name":"M E Heuck Co",
    "wof:placetype":"venue"
},
  "geometry": {"coordinates":[-84.55133499999999,39.146524],"type":"Point"}
}