{
  "type": "Feature",
  "properties": {
    "iso:country":"US",
    "sg:address":"4924 Cashion Dr",
    "sg:city":"Hilliard",
    "sg:classifiers":[
        {
            "category":"Building & Trades",
            "subcategory":"Landscaping Services",
            "type":"Services"
        }
    ],
    "sg:phone":"+1 614 777 9328",
    "sg:postcode":"43026",
    "sg:province":"OH",
    "wof:name":"Racoon Creek",
    "wof:placetype":"venue"
},
  "geometry": {"coordinates":[-83.143253,40.015034],"type":"Point"}
}