{
  "type": "Feature",
  "properties": {
    "iso:country":"US",
    "sg:address":"4509 Renaissance Pkwy",
    "sg:city":"Cleveland",
    "sg:classifiers":[
        {
            "category":"Banks & Credit Unions",
            "subcategory":"Bank",
            "type":"Services"
        }
    ],
    "sg:phone":"+1 216 595 1135",
    "sg:postcode":"44128",
    "sg:province":"OH",
    "sg:tags":[
        "loan",
        "broker"
    ],
    "wof:name":"Town & Country Home Loans Inc",
    "wof:placetype":"venue"
},
  "geometry": {"coordinates":[-81.49191999999999,41.441338],"type":"Point"}
}