{
  "type": "Feature",
  "properties": {
    "addr:full": "4509 Renaissance Pkwy Cleveland OH 44128",
    "addr:housenumber": "4509",
    "addr:postcode": "44128",
    "addr:street": "Renaissance Pkwy",
    "iso:country": "US",
    "sg:address": "4509 Renaissance Pkwy",
    "sg:city": "Cleveland",
    "sg:classifiers": [
      {
        "category": "Banks \u0026 Credit Unions",
        "subcategory": "Bank",
        "type": "Services"
      }
    ],
    "sg:phone": "+1 216 595 1135",
    "sg:postcode": "44128",
    "sg:province": "OH",
    "sg:tags": [
      "loan",
      "broker"
    ],
    "wof:name": "Town \u0026 Country Home Loans Inc",
    "wof:placetype": "venue"
  },
  "geometry": {"coordinates":[-81.49192,41.441338],"type":"Point"}
}
