{
  "type": "Feature",
  "properties": {
    "addr:full": "1207 Broad St Conneaut OH 44030",
    "addr:housenumber": "1207",
    "addr:postcode": "44030",
    "addr:street": "Broad St",
    "iso:country": "US",
    "sg:address": "1207 Broad St",
    "sg:city": "Conneaut",
    "sg:classifiers": [
      {
        "category": "Social Services",
        "type": "Services"
      },
      {
        "category": "Professional",
        "subcategory": "Employment Agencies",
        "type": "Services"
      },
      {
        "category": "Sports \u0026 Exercise",
        "subcategory": "Sports Center",
        "type": "Entertainment"
      }
    ],
    "sg:phone": "+1 440 593 6330",
    "sg:postcode": "44030",
    "sg:province": "OH",
    "sg:tags": [
      "workers'",
      "placement",
      "volunteer"
    ],
    "wof:name": "Lake Erie Boat Club",
    "wof:placetype": "venue"
  },
  "geometry": {"coordinates":[-80.553166,41.965142],"type":"Point"}
}
