{
  "type": "Feature",
  "properties": {
    "addr:full": "4226 Tonsing Dr Ravenna OH 44266",
    "addr:housenumber": "4226",
    "addr:postcode": "44266",
    "addr:street": "Tonsing Dr",
    "iso:country": "US",
    "sg:address": "4226 Tonsing Dr",
    "sg:city": "Ravenna",
    "sg:classifiers": [
      {
        "category": "Autos \u0026 Motor Vehicles",
        "subcategory": "Automobile Sales",
        "type": "Retail Goods"
      }
    ],
    "sg:phone": "+1 330 325 8369",
    "sg:postcode": "44266",
    "sg:province": "OH",
    "sg:tags": [
      "used"
    ],
    "wof:name": "Gran Motor Cars LLC",
    "wof:placetype": "venue"
  },
  "geometry": {"coordinates":[-81.242131,41.113198],"type":"Point"}
}
