{
  "type": "Feature",
  "properties": {
    "addr:full":"1725 W State St Alliance OH 44601",
    "addr:housenumber":"1725",
    "addr:postcode":"44601",
    "addr:street":"W State St",
    "iso:country":"US",
    "sg:address":"1725 W State St",
    "sg:city":"Alliance",
    "sg:classifiers":[
        {
            "category":"Retail",
            "subcategory":"Car Wash",
            "type":"Services"
        }
    ],
    "sg:phone":"+1 330 823 1819",
    "sg:postcode":"44601",
    "sg:province":"OH",
    "sg:tags":[
        "polishing",
        "washing"
    ],
    "wof:name":"Carr Wash Of Alliance",
    "wof:placetype":"venue"
},
  "geometry": {"coordinates":[-81.13093600000001,40.901934],"type":"Point"}
}