{
  "type": "Feature",
  "properties": {
    "addr:full": "9114 Oak Valley Rd Holland OH 43528",
    "addr:housenumber": "9114",
    "addr:postcode": "43528",
    "addr:street": "Oak Valley Rd",
    "iso:country": "US",
    "sg:address": "9114 Oak Valley Rd",
    "sg:city": "Holland",
    "sg:classifiers": [
      {
        "category": "Insurance",
        "subcategory": "Hazard Insurance",
        "type": "Services"
      }
    ],
    "sg:phone": "+1 419 861 2052",
    "sg:postcode": "43528",
    "sg:province": "OH",
    "sg:tags": [
      "carrier"
    ],
    "wof:name": "Federated Insurance",
    "wof:placetype": "venue"
  },
  "geometry": {"coordinates":[-83.760708,41.635221],"type":"Point"}
}
