{
  "type": "Feature",
  "properties": {
    "addr:full":"2930 W Florence Campbellstown Rd Eaton OH 45320",
    "addr:housenumber":"2930",
    "addr:postcode":"45320",
    "addr:street":"W Florence Campbellstown Rd",
    "iso:country":"US",
    "sg:address":"2930 W Florence Campbellstown Rd",
    "sg:city":"Eaton",
    "sg:classifiers":[
        {
            "category":"Government",
            "subcategory":"Office",
            "type":"Public Place"
        }
    ],
    "sg:phone":"+1 937 456 5320",
    "sg:postcode":"45320",
    "sg:province":"OH",
    "sg:tags":[
        "village"
    ],
    "wof:name":"Jackson Twp Office",
    "wof:placetype":"venue"
},
  "geometry": {"coordinates":[-84.760234,39.785718],"type":"Point"}
}