{
  "type": "Feature",
  "properties": {
    "addr:full":"715 Lane St Ironton OH 45638",
    "addr:housenumber":"715",
    "addr:postcode":"45638",
    "addr:street":"Lane St",
    "iso:country":"US",
    "sg:address":"715 Lane St",
    "sg:city":"Ironton",
    "sg:classifiers":[
        {
            "category":"Shopping",
            "subcategory":"Used Merchandise",
            "type":"Retail Goods"
        },
        {
            "category":"Health Services",
            "subcategory":"Hospital",
            "type":"Services"
        }
    ],
    "sg:phone":"+1 740 533 6280",
    "sg:postcode":"45638",
    "sg:province":"OH",
    "sg:tags":[
        "mental"
    ],
    "wof:name":"Shawnee Mental Health Center",
    "wof:placetype":"venue"
},
  "geometry": {"coordinates":[-82.643463,38.492643],"type":"Point"}
}