{
  "type": "Feature",
  "properties": {
    "iso:country":"US",
    "sg:address":"6330 Frederick Pike",
    "sg:city":"Dayton",
    "sg:classifiers":[
        {
            "category":"Retail",
            "subcategory":"Animal Services",
            "type":"Services"
        }
    ],
    "sg:phone":"+1 937 890 0574",
    "sg:postcode":"45414",
    "sg:province":"OH",
    "sg:tags":[
        "pet",
        "grooming",
        "washing"
    ],
    "wof:name":"Pet Heaven Kennels & Pet",
    "wof:placetype":"venue"
},
  "geometry": {"coordinates":[-84.226799,39.836476],"type":"Point"}
}