{
  "type": "Feature",
  "properties": {
    "addr:full":"2643 Burridge Cir Twinsburg OH 44087",
    "addr:housenumber":"2643",
    "addr:postcode":"44087",
    "addr:street":"Burridge Cir",
    "iso:country":"US",
    "sg:address":"2643 Burridge Cir",
    "sg:city":"Twinsburg",
    "sg:classifiers":[
        {
            "category":"Autos & Motor Vehicles",
            "subcategory":"Automobile Sales",
            "type":"Retail Goods"
        }
    ],
    "sg:phone":"+1 330 405 6421",
    "sg:postcode":"44087",
    "sg:province":"OH",
    "sg:tags":[
        "used"
    ],
    "wof:name":"Fbs Auto Sales Inc",
    "wof:placetype":"venue"
},
  "geometry": {"coordinates":[-81.44553999999999,41.31438],"type":"Point"}
}