{
  "type": "Feature",
  "properties": {
    "addr:full": "7900 McKitrick Rd Plain City OH 43064",
    "addr:postcode": "7900;43064",
    "addr:street": "Mckitrick Rd",
    "iso:country": "US",
    "sg:address": "7900 McKitrick Rd",
    "sg:city": "Plain City",
    "sg:classifiers": [
      {
        "category": "Building \u0026 Trades",
        "subcategory": "Construction",
        "type": "Services"
      }
    ],
    "sg:phone": "+1 614 873 3579",
    "sg:postcode": "43064",
    "sg:province": "OH",
    "sg:tags": [
      "general",
      "contractor"
    ],
    "wof:name": "Leatherman Construction Co",
    "wof:placetype": "venue"
  },
  "geometry": {"coordinates":[-83.190426,40.14892],"type":"Point"}
}
