{
  "type": "Feature",
  "properties": {
    "addr:full":"401 Jefferson Ave Toledo OH 43604",
    "addr:housenumber":"401",
    "addr:postcode":"43604",
    "addr:street":"Jefferson Ave",
    "iso:country":"US",
    "sg:address":"401 Jefferson Ave",
    "sg:city":"Toledo",
    "sg:classifiers":[
        {
            "category":"Professional",
            "subcategory":"Business Services",
            "type":"Services"
        }
    ],
    "sg:phone":"+1 419 255 3300",
    "sg:postcode":"43604",
    "sg:province":"OH",
    "sg:tags":[
        "convention",
        "meeting",
        "facility"
    ],
    "sg:website":"www.toledo-seagate.com",
    "wof:name":"Seagate Convention Ctr",
    "wof:placetype":"venue"
},
  "geometry": {"coordinates":[-83.53691000000001,41.650524],"type":"Point"}
}