{
  "type": "Feature",
  "properties": {
    "iso:country":"US",
    "sg:address":"2100 E Dorothy Ln",
    "sg:city":"Dayton",
    "sg:classifiers":[
        {
            "category":"Shopping",
            "subcategory":"Gifts & Souvenirs",
            "type":"Retail Goods"
        }
    ],
    "sg:phone":"+1 937 294 2718",
    "sg:postcode":"45420",
    "sg:province":"OH",
    "sg:tags":[
        "shop"
    ],
    "wof:name":"M & R Hallmark House Of Cards",
    "wof:placetype":"venue"
},
  "geometry": {"coordinates":[-84.127241,39.70284],"type":"Point"}
}