{
  "type": "Feature",
  "properties": {
    "addr:full":"12049 Centron Pl Cincinnati OH 45246",
    "addr:housenumber":"12049",
    "addr:postcode":"45246",
    "addr:street":"Centron Pl",
    "iso:country":"US",
    "sg:address":"12049 Centron Pl",
    "sg:city":"Cincinnati",
    "sg:classifiers":[
        {
            "category":"Manufacturing",
            "subcategory":"Chemicals & Compounds",
            "type":"Manufacturing & Wholesale Goods"
        }
    ],
    "sg:phone":"+1 513 671 0400",
    "sg:postcode":"45246",
    "sg:province":"OH",
    "sg:tags":[
        "preparation",
        "printing",
        "ink",
        "lithographing",
        "mfg"
    ],
    "wof:name":"Sun Chemical Corporation",
    "wof:placetype":"venue"
},
  "geometry": {"coordinates":[-84.471856,39.299249],"type":"Point"}
}