{
  "type": "Feature",
  "properties": {
    "iso:country":"US",
    "sg:address":"465 College St",
    "sg:city":"Wadsworth",
    "sg:classifiers":[
        {
            "category":"Home & Garden",
            "subcategory":"Building Materials",
            "type":"Retail Goods"
        }
    ],
    "sg:phone":"+1 330 336 3528",
    "sg:postcode":"44281",
    "sg:province":"OH",
    "sg:tags":[
        "shutter"
    ],
    "wof:name":"Silver Shutter",
    "wof:placetype":"venue"
},
  "geometry": {"coordinates":[-81.742793,41.025336],"type":"Point"}
}