{
  "type": "Feature",
  "properties": {
    "addr:full":"3649 Pine Creek Rd Williamsburg OH 45176",
    "addr:housenumber":"3649",
    "addr:postcode":"45176",
    "addr:street":"Pine Creek Rd",
    "iso:country":"US",
    "sg:address":"3649 Pine Creek Rd",
    "sg:city":"Williamsburg",
    "sg:classifiers":[
        {
            "category":"Retail",
            "subcategory":"Repair Shop",
            "type":"Services"
        },
        {
            "category":"Building & Trades",
            "subcategory":"Construction",
            "type":"Services"
        }
    ],
    "sg:phone":"+1 513 724 3456",
    "sg:postcode":"45176",
    "sg:province":"OH",
    "sg:tags":[
        "sink",
        "bathtub",
        "refinishing",
        "business",
        "contractor"
    ],
    "wof:name":"Fitzgerald's Creative Coatings",
    "wof:placetype":"venue"
},
  "geometry": {"coordinates":[-84.030343,39.071443],"type":"Point"}
}