{
  "type": "Feature",
  "properties": {
    "addr:full":"7900 Exchange St Cleveland OH 44125",
    "addr:housenumber":"7900",
    "addr:postcode":"44125",
    "addr:street":"Exchange St",
    "iso:country":"US",
    "sg:address":"7900 Exchange St",
    "sg:city":"Cleveland",
    "sg:classifiers":[
        {
            "category":"Manufacturing",
            "subcategory":"Metals",
            "type":"Manufacturing & Wholesale Goods"
        },
        {
            "category":"Building & Trades",
            "subcategory":"Construction",
            "type":"Services"
        },
        {
            "category":"Manufacturing",
            "subcategory":"Building Materials",
            "type":"Manufacturing & Wholesale Goods"
        }
    ],
    "sg:phone":"+1 216 524 6110",
    "sg:postcode":"44125",
    "sg:province":"OH",
    "sg:tags":[
        "steel",
        "sheet",
        "distributor",
        "work",
        "warehouse",
        "metal-wholesale",
        "work-manufacturers",
        "fabricator",
        "mill",
        "welder",
        "manufacturer"
    ],
    "wof:name":"Precision Welding Corporation",
    "wof:placetype":"venue"
},
  "geometry": {"coordinates":[-81.628691,41.407872],"type":"Point"}
}