{
  "type": "Feature",
  "properties": {
    "iso:country":"US",
    "sg:address":"3710 Floral Ave",
    "sg:city":"Cincinnati",
    "sg:classifiers":[
        {
            "category":"Manufacturing",
            "subcategory":"Printing",
            "type":"Manufacturing & Wholesale Goods"
        }
    ],
    "sg:phone":"+1 513 351 2800",
    "sg:postcode":"45212",
    "sg:province":"OH",
    "sg:tags":[
        "commercial",
        "typesetting"
    ],
    "wof:name":"Koehler Graphics",
    "wof:placetype":"venue"
},
  "geometry": {"coordinates":[-84.457589,39.14672],"type":"Point"}
}