{
  "type": "Feature",
  "properties": {
    "addr:full":"2164 State Rte 125 Amelia OH 45102",
    "addr:housenumber":"2164",
    "addr:postcode":"45102",
    "addr:street":"State Rte 125",
    "iso:country":"US",
    "sg:address":"2164 State Rte 125",
    "sg:city":"Amelia",
    "sg:classifiers":[
        {
            "category":"Home & Garden",
            "subcategory":"Building Materials",
            "type":"Retail Goods"
        }
    ],
    "sg:phone":"+1 513 797 5567",
    "sg:postcode":"45102",
    "sg:province":"OH",
    "sg:tags":[
        "glass",
        "window",
        "plate"
    ],
    "wof:name":"Brad's Glass Shop",
    "wof:placetype":"venue"
},
  "geometry": {"coordinates":[-84.167849,39.007596],"type":"Point"}
}