{
  "type": "Feature",
  "properties": {
    "addr:full":"6650 Pearl Rd Cleveland OH 44130",
    "addr:housenumber":"6650",
    "addr:postcode":"44130",
    "addr:street":"Pearl Rd",
    "iso:country":"US",
    "sg:address":"6650 Pearl Rd",
    "sg:city":"Cleveland",
    "sg:classifiers":[
        {
            "category":"Travel",
            "subcategory":"Travel Agent",
            "type":"Entertainment"
        }
    ],
    "sg:phone":"+1 440 842 1994",
    "sg:postcode":"44130",
    "sg:province":"OH",
    "sg:tags":[
        "agency",
        "bureau"
    ],
    "sg:website":"www.sundancetvl.com",
    "wof:name":"Sundance Travel",
    "wof:placetype":"venue"
},
  "geometry": {"coordinates":[-81.78241199999999,41.381423],"type":"Point"}
}