{
  "type": "Feature",
  "properties": {
    "addr:full":"34158 Jade Cir North Ridgeville OH 44039",
    "addr:housenumber":"34158",
    "addr:postcode":"44039",
    "addr:street":"Jade Cir",
    "iso:country":"US",
    "sg:address":"34158 Jade Cir",
    "sg:city":"North Ridgeville",
    "sg:classifiers":[
        {
            "category":"Manufacturing",
            "subcategory":"Signs",
            "type":"Manufacturing & Wholesale Goods"
        }
    ],
    "sg:phone":"+1 440 327 5575",
    "sg:postcode":"44039",
    "sg:province":"OH",
    "wof:name":"Direct Image Signs",
    "wof:placetype":"venue"
},
  "geometry": {"coordinates":[-81.995332,41.412182],"type":"Point"}
}