{
  "type": "Feature",
  "properties": {
    "addr:full":"38711 Arbor Ct Grafton OH 44044",
    "addr:housenumber":"38711",
    "addr:postcode":"44044",
    "addr:street":"Arbor Ct",
    "iso:country":"US",
    "sg:address":"38711 Arbor Ct",
    "sg:city":"Grafton",
    "sg:classifiers":[
        {
            "category":"Shopping",
            "subcategory":"Department Store",
            "type":"Retail Goods"
        }
    ],
    "sg:phone":"+1 440 458 4707",
    "sg:postcode":"44044",
    "sg:province":"OH",
    "wof:name":"Larrys Food & Deli",
    "wof:placetype":"venue"
},
  "geometry": {"coordinates":[-82.078991,41.291066],"type":"Point"}
}