{
  "type": "Feature",
  "properties": {
    "addr:full": "9525 Twp Rd 50 Dola OH 45835",
    "addr:housenumber": "9525;50",
    "addr:postcode": "45835",
    "addr:street": "Twp Rd",
    "iso:country": "US",
    "sg:address": "9525 Twp Rd 50",
    "sg:city": "Dola",
    "sg:classifiers": [
      {
        "category": "Insurance",
        "subcategory": "Insurance Agent",
        "type": "Services"
      }
    ],
    "sg:phone": "+1 419 759 2100",
    "sg:postcode": "45835",
    "sg:province": "OH",
    "wof:name": "Combs \u0026 Assoc",
    "wof:placetype": "venue"
  },
  "geometry": {"coordinates":[-83.699979,40.761674],"type":"Point"}
}
