{
  "type": "Feature",
  "properties": {
    "iso:country":"US",
    "sg:address":"9525 Twp Rd 50",
    "sg:city":"Dola",
    "sg:classifiers":[
        {
            "category":"Insurance",
            "subcategory":"Insurance Agent",
            "type":"Services"
        }
    ],
    "sg:phone":"+1 419 759 2100",
    "sg:postcode":"45835",
    "sg:province":"OH",
    "wof:name":"Combs & Assoc",
    "wof:placetype":"venue"
},
  "geometry": {"coordinates":[-83.699979,40.761674],"type":"Point"}
}