{
  "type": "Feature",
  "properties": {
    "addr:full":"10612 Churchill Dr Powell OH 43065",
    "addr:housenumber":"10612",
    "addr:postcode":"43065",
    "addr:street":"Churchill Dr",
    "iso:country":"US",
    "sg:address":"10612 Churchill Dr",
    "sg:city":"Powell",
    "sg:classifiers":[
        {
            "category":"Building & Trades",
            "subcategory":"Construction",
            "type":"Services"
        }
    ],
    "sg:phone":"+1 614 895 1800",
    "sg:postcode":"43065",
    "sg:province":"OH",
    "sg:tags":[
        "home",
        "builder"
    ],
    "wof:name":"Compass Homes",
    "wof:placetype":"venue"
},
  "geometry": {"coordinates":[-83.056551,40.138667],"type":"Point"}
}