{
  "type": "Feature",
  "properties": {
    "addr:full": "11590 Century Blvd Cincinnati OH 45246",
    "addr:housenumber": "11590",
    "addr:postcode": "45246",
    "addr:street": "Century Blvd",
    "iso:country": "US",
    "sg:address": "11590 Century Blvd",
    "sg:city": "Cincinnati",
    "sg:classifiers": [
      {
        "category": "Health Services",
        "subcategory": "Doctor",
        "type": "Services"
      }
    ],
    "sg:phone": "+1 513 671 7246",
    "sg:postcode": "45246",
    "sg:province": "OH",
    "sg:tags": [
      "physician",
      "surgeon"
    ],
    "wof:name": "Pain Solutions Network LLC",
    "wof:placetype": "venue"
  },
  "geometry": {"coordinates":[-84.453407,39.28622],"type":"Point"}
}
