{
  "type": "Feature",
  "properties": {
    "addr:full": "1117 Woodward Ave Akron OH 44310",
    "addr:housenumber": "1117",
    "addr:postcode": "44310",
    "addr:street": "Woodward Ave",
    "iso:country": "US",
    "sg:address": "1117 Woodward Ave",
    "sg:city": "Akron",
    "sg:classifiers": [
      {
        "category": "Restaurant",
        "type": "Food \u0026 Drink"
      }
    ],
    "sg:phone": "+1 330 922 0110",
    "sg:postcode": "44310",
    "sg:province": "OH",
    "sg:tags": [
      "catering"
    ],
    "wof:name": "Rosemarys Catering Service",
    "wof:placetype": "venue"
  },
  "geometry": {"coordinates":[-81.507958,41.116255],"type":"Point"}
}
