{
  "type": "Feature",
  "properties": {
    "iso:country":"US",
    "sg:address":"1117 Woodward Ave",
    "sg:city":"Akron",
    "sg:classifiers":[
        {
            "category":"Restaurant",
            "type":"Food & Drink"
        }
    ],
    "sg:phone":"+1 330 922 0110",
    "sg:postcode":"44310",
    "sg:province":"OH",
    "sg:tags":[
        "catering"
    ],
    "wof:name":"Rosemarys Catering Service",
    "wof:placetype":"venue"
},
  "geometry": {"coordinates":[-81.507958,41.116255],"type":"Point"}
}