{
  "type": "Feature",
  "properties": {
    "addr:full": "2154 South Ave Toledo OH 43609",
    "addr:housenumber": "2154",
    "addr:postcode": "43609",
    "addr:street": "South Ave",
    "iso:country": "US",
    "sg:address": "2154 South Ave",
    "sg:city": "Toledo",
    "sg:classifiers": [
      {
        "category": "Food \u0026 Beverages",
        "subcategory": "Liquor \u0026 Beverages",
        "type": "Retail Goods"
      }
    ],
    "sg:phone": "+1 419 385 5566",
    "sg:postcode": "43609",
    "sg:province": "OH",
    "sg:tags": [
      "beer",
      "ale"
    ],
    "wof:name": "South Port Carryout",
    "wof:placetype": "venue"
  },
  "geometry": {"coordinates":[-83.596433,41.630755],"type":"Point"}
}
