{
  "type": "Feature",
  "properties": {
    "addr:full":"7591 Town Line Rd Shiloh OH 44878",
    "addr:housenumber":"7591",
    "addr:postcode":"44878",
    "addr:street":"Town Line Rd",
    "iso:country":"US",
    "sg:address":"7591 Town Line Rd",
    "sg:city":"Shiloh",
    "sg:classifiers":[
        {
            "category":"Professional",
            "subcategory":"Business Services",
            "type":"Services"
        }
    ],
    "sg:phone":"+1 419 895 2393",
    "sg:postcode":"44878",
    "sg:province":"OH",
    "sg:tags":[
        "interior",
        "consultant",
        "design",
        "decorator"
    ],
    "wof:name":"Mickie Mc William's Interiors",
    "wof:placetype":"venue"
},
  "geometry": {"coordinates":[-82.43171599999999,40.965024],"type":"Point"}
}