{
  "type": "Feature",
  "properties": {
    "addr:full":"336 Elm St London OH 43140",
    "addr:housenumber":"336",
    "addr:postcode":"43140",
    "addr:street":"Elm St",
    "iso:country":"US",
    "sg:address":"336 Elm St",
    "sg:city":"London",
    "sg:classifiers":[
        {
            "category":"Education",
            "subcategory":"School",
            "type":"Public Place"
        }
    ],
    "sg:phone":"+1 740 852 5705",
    "sg:postcode":"43140",
    "sg:province":"OH",
    "wof:name":"London High School",
    "wof:placetype":"venue"
},
  "geometry": {"coordinates":[-83.448076,39.901112],"type":"Point"}
}