{
  "type": "Feature",
  "properties": {
    "addr:full": "3620 Wilmington Pike Kettering OH 45429",
    "addr:housenumber": "3620",
    "addr:postcode": "45429",
    "addr:street": "Wilmington Pike",
    "iso:country": "US",
    "sg:address": "3620 Wilmington Pike",
    "sg:city": "Kettering",
    "sg:classifiers": [
      {
        "category": "Banks \u0026 Credit Unions",
        "subcategory": "Bank",
        "type": "Services"
      }
    ],
    "sg:phone": "+1 937 293 9511",
    "sg:postcode": "45429",
    "sg:province": "OH",
    "sg:tags": [
      "loan"
    ],
    "wof:name": "Jericho Mortgage Of Dayton",
    "wof:placetype": "venue"
  },
  "geometry": {"coordinates":[-84.138494,39.694852],"type":"Point"}
}
