{
  "type": "Feature",
  "properties": {
    "addr:full": "108 E Greene St Piqua OH 45356",
    "addr:housenumber": "108",
    "addr:postcode": "45356",
    "addr:street": "E Greene St",
    "iso:country": "US",
    "sg:address": "108 E Greene St",
    "sg:city": "Piqua",
    "sg:classifiers": [
      {
        "category": "Personal",
        "subcategory": "Barber",
        "type": "Services"
      }
    ],
    "sg:phone": "+1 937 615 0765",
    "sg:postcode": "45356",
    "sg:province": "OH",
    "wof:name": "Barber Shoppe",
    "wof:placetype": "venue"
  },
  "geometry": {"coordinates":[-84.239181,40.150882],"type":"Point"}
}
