{
  "type": "Feature",
  "properties": {
    "addr:full":"1758 Westbelt Dr Columbus OH 43228",
    "addr:housenumber":"1758",
    "addr:postcode":"43228",
    "addr:street":"Westbelt Dr",
    "iso:country":"US",
    "sg:address":"1758 Westbelt Dr",
    "sg:city":"Columbus",
    "sg:classifiers":[
        {
            "category":"Professional",
            "subcategory":"Advertising",
            "type":"Services"
        }
    ],
    "sg:phone":"+1 614 529 2200",
    "sg:postcode":"43228",
    "sg:province":"OH",
    "sg:tags":[
        "distributing",
        "sample"
    ],
    "wof:name":"SCP Distributors",
    "wof:placetype":"venue"
},
  "geometry": {"coordinates":[-83.125001,39.986913],"type":"Point"}
}