{
  "type": "Feature",
  "properties": {
    "iso:country":"US",
    "sg:address":"24551 Detroit Rd",
    "sg:city":"Cleveland",
    "sg:classifiers":[
        {
            "category":"Social Services",
            "type":"Services"
        }
    ],
    "sg:phone":"+1 440 248 5454",
    "sg:postcode":"44145",
    "sg:province":"OH",
    "sg:tags":[
        "counselor",
        "marriage",
        "family"
    ],
    "wof:name":"James E Kaplar Phd & Assoc",
    "wof:placetype":"venue"
},
  "geometry": {"coordinates":[-81.890518,41.47086],"type":"Point"}
}