{
  "type": "Feature",
  "properties": {
    "addr:full": "1359 Meadows Dr Lancaster OH 43130",
    "addr:housenumber": "1359",
    "addr:postcode": "43130",
    "addr:street": "Meadows Dr",
    "iso:country": "US",
    "sg:address": "1359 Meadows Dr",
    "sg:city": "Lancaster",
    "sg:classifiers": [
      {
        "category": "Restaurant",
        "type": "Food \u0026 Drink"
      }
    ],
    "sg:phone": "+1 740 654 7821",
    "sg:postcode": "43130",
    "sg:province": "OH",
    "sg:tags": [
      "eating"
    ],
    "wof:name": "Bairs Concessions Inc",
    "wof:placetype": "venue"
  },
  "geometry": {"coordinates":[-82.555486,39.729797],"type":"Point"}
}
