{
  "type": "Feature",
  "properties": {
    "addr:full": "2718 Lyons Rd Miamisburg OH 45342",
    "addr:housenumber": "2718",
    "addr:postcode": "45342",
    "addr:street": "Lyons Rd",
    "iso:country": "US",
    "sg:address": "2718 Lyons Rd",
    "sg:city": "Miamisburg",
    "sg:classifiers": [
      {
        "category": "Education",
        "subcategory": "Library",
        "type": "Public Place"
      }
    ],
    "sg:phone": "+1 937 227 9567",
    "sg:postcode": "45342",
    "sg:province": "OH",
    "wof:name": "Miami Township Branch Library",
    "wof:placetype": "venue"
  },
  "geometry": {"coordinates":[-84.223144,39.62797],"type":"Point"}
}
