{
  "type": "Feature",
  "properties": {
    "addr:full":"6811 National Rd SE Jacksontown OH 43076",
    "addr:housenumber":"6811",
    "addr:postcode":"43076",
    "addr:street":"National Rd Se",
    "iso:country":"US",
    "sg:address":"6811 National Rd SE",
    "sg:city":"Jacksontown",
    "sg:classifiers":[
        {
            "category":"Restaurant",
            "type":"Food & Drink"
        }
    ],
    "sg:phone":"+1 740 323 3874",
    "sg:postcode":"43076",
    "sg:province":"OH",
    "wof:name":"Clark's Dining Room",
    "wof:placetype":"venue"
},
  "geometry": {"coordinates":[-82.41507799999999,39.959474],"type":"Point"}
}