{
  "type": "Feature",
  "properties": {
    "addr:full": "163 7th St Columbiana OH 44408",
    "addr:housenumber": "163",
    "addr:postcode": "44408",
    "addr:street": "7Th St",
    "iso:country": "US",
    "sg:address": "163 7th St",
    "sg:city": "Columbiana",
    "sg:classifiers": [
      {
        "category": "Personal",
        "subcategory": "Beauty Salon",
        "type": "Services"
      }
    ],
    "sg:phone": "+1 330 482 4653",
    "sg:postcode": "44408",
    "sg:province": "OH",
    "wof:name": "Becky's Beauty Salon",
    "wof:placetype": "venue"
  },
  "geometry": {"coordinates":[-80.692721,40.898098],"type":"Point"}
}
