{
  "type": "Feature",
  "properties": {
    "addr:full":"4392 State Rte 140 Wheelersburg OH 45694",
    "addr:housenumber":"4392",
    "addr:postcode":"45694",
    "addr:street":"State Rte 140",
    "iso:country":"US",
    "sg:address":"4392 State Rte 140",
    "sg:city":"Wheelersburg",
    "sg:classifiers":[
        {
            "category":"Food & Beverages",
            "subcategory":"Groceries & Convenience Stores",
            "type":"Retail Goods"
        }
    ],
    "sg:phone":"+1 740 776 6715",
    "sg:postcode":"45694",
    "sg:province":"OH",
    "wof:name":"Montys 23",
    "wof:placetype":"venue"
},
  "geometry": {"coordinates":[-82.811578,38.76265],"type":"Point"}
}