{
  "type": "Feature",
  "properties": {
    "addr:full":"39 Walnut Rd Medway OH 45341",
    "addr:housenumber":"39",
    "addr:postcode":"45341",
    "addr:street":"Walnut Rd",
    "iso:country":"US",
    "sg:address":"39 Walnut Rd",
    "sg:city":"Medway",
    "sg:classifiers":[
        {
            "category":"Organizations",
            "subcategory":"Religious Organization",
            "type":"Services"
        }
    ],
    "sg:phone":"+1 937 849 0885",
    "sg:postcode":"45341",
    "sg:province":"OH",
    "sg:tags":[
        "clergy"
    ],
    "wof:name":"Crystal Lakes Spiritual Church",
    "wof:placetype":"venue"
},
  "geometry": {"coordinates":[-84.021624,39.895069],"type":"Point"}
}