{
  "type": "Feature",
  "properties": {
    "addr:full": "94 W Church St Pickerington OH 43147",
    "addr:housenumber": "94",
    "addr:postcode": "43147",
    "addr:street": "W Church St",
    "iso:country": "US",
    "sg:address": "94 W Church St",
    "sg:city": "Pickerington",
    "sg:classifiers": [
      {
        "category": "Communications",
        "subcategory": "Film \u0026 Video Production",
        "type": "Services"
      }
    ],
    "sg:phone": "+1 614 837 8273",
    "sg:postcode": "43147",
    "sg:province": "OH",
    "sg:tags": [
      "taping"
    ],
    "wof:name": "Video Data Svc",
    "wof:placetype": "venue"
  },
  "geometry": {"coordinates":[-82.753752,39.885087],"type":"Point"}
}
