{
  "type": "Feature",
  "properties": {
    "iso:country":"US",
    "sg:address":"3350 Clark-Shaw Rd",
    "sg:city":"Powell",
    "sg:classifiers":[
        {
            "category":"Communications",
            "type":"Services"
        }
    ],
    "sg:phone":"+1 740 369 7129",
    "sg:postcode":"43065",
    "sg:province":"OH",
    "sg:tags":[
        "communication"
    ],
    "wof:name":"Montague Communications LLC",
    "wof:placetype":"venue"
},
  "geometry": {"coordinates":[-83.1074,40.228574],"type":"Point"}
}