{
  "type": "Feature",
  "properties": {
    "addr:full": "419 W River St Antwerp OH 45813",
    "addr:housenumber": "419",
    "addr:postcode": "45813",
    "addr:street": "W River St",
    "iso:country": "US",
    "sg:address": "419 W River St",
    "sg:city": "Antwerp",
    "sg:classifiers": [
      {
        "category": "Autos \u0026 Motor Vehicles",
        "subcategory": "Auto Supplies",
        "type": "Retail Goods"
      }
    ],
    "sg:phone": "+1 419 258 8895",
    "sg:postcode": "45813",
    "sg:province": "OH",
    "sg:tags": [
      "tire"
    ],
    "wof:name": "Chuck's Tires",
    "wof:placetype": "venue"
  },
  "geometry": {"coordinates":[-84.747137,41.179204],"type":"Point"}
}
