{
  "type": "Feature",
  "properties": {
    "iso:country":"US",
    "sg:address":"4807 Rockside Rd",
    "sg:city":"Cleveland",
    "sg:classifiers":[
        {
            "category":"Banks & Credit Unions",
            "subcategory":"Bank",
            "type":"Services"
        }
    ],
    "sg:phone":"+1 216 520 1730",
    "sg:postcode":"44131",
    "sg:province":"OH",
    "sg:tags":[
        "mortgage",
        "loan",
        "broker",
        "real estate"
    ],
    "wof:name":"Ohio Financial Group LLC",
    "wof:placetype":"venue"
},
  "geometry": {"coordinates":[-81.65456399999999,41.397191],"type":"Point"}
}