{
  "type": "Feature",
  "properties": {
    "iso:country":"US",
    "sg:address":"760 N Bridge St",
    "sg:city":"Chillicothe",
    "sg:classifiers":[
        {
            "category":"Autos & Motor Vehicles",
            "subcategory":"Fuel & Gas Station",
            "type":"Retail Goods"
        }
    ],
    "sg:phone":"+1 740 773 4482",
    "sg:postcode":"45601",
    "sg:province":"OH",
    "sg:tags":[
        "oil"
    ],
    "wof:name":"BP Oil Co",
    "wof:placetype":"venue"
},
  "geometry": {"coordinates":[-82.976043,39.342552],"type":"Point"}
}