{
  "type": "Feature",
  "properties": {
    "addr:full": "760 N Bridge St Chillicothe OH 45601",
    "addr:housenumber": "760",
    "addr:postcode": "45601",
    "addr:street": "N Bridge St",
    "iso:country": "US",
    "sg:address": "760 N Bridge St",
    "sg:city": "Chillicothe",
    "sg:classifiers": [
      {
        "category": "Autos \u0026 Motor Vehicles",
        "subcategory": "Fuel \u0026 Gas Station",
        "type": "Retail Goods"
      }
    ],
    "sg:phone": "+1 740 773 4482",
    "sg:postcode": "45601",
    "sg:province": "OH",
    "sg:tags": [
      "oil"
    ],
    "wof:name": "BP Oil Co",
    "wof:placetype": "venue"
  },
  "geometry": {"coordinates":[-82.976043,39.342552],"type":"Point"}
}
