{
  "type": "Feature",
  "properties": {
    "iso:country":"US",
    "sg:address":"589 W Riverview Ave",
    "sg:city":"Napoleon",
    "sg:classifiers":[
        {
            "category":"Health Services",
            "subcategory":"Hospital",
            "type":"Services"
        }
    ],
    "sg:phone":"+1 419 592 0500",
    "sg:postcode":"43545",
    "sg:province":"OH",
    "sg:tags":[
        "mental"
    ],
    "sg:website":"www.henrycountyhospital.org",
    "wof:name":"Help Center",
    "wof:placetype":"venue"
},
  "geometry": {"coordinates":[-84.132827,41.384357],"type":"Point"}
}