{
  "type": "Feature",
  "properties": {
    "addr:full":"486 SE Catawba Rd Port Clinton OH 43452",
    "addr:housenumber":"486",
    "addr:postcode":"43452",
    "addr:street":"Se Catawba Rd",
    "iso:country":"US",
    "sg:address":"486 SE Catawba Rd",
    "sg:city":"Port Clinton",
    "sg:classifiers":[
        {
            "category":"Marine",
            "type":"Transportation"
        }
    ],
    "sg:phone":"+1 419 732 0777",
    "sg:postcode":"43452",
    "sg:province":"OH",
    "sg:tags":[
        "cleaning",
        "boat"
    ],
    "wof:name":"Mirror Image Detailing Inc",
    "wof:placetype":"venue"
},
  "geometry": {"coordinates":[-82.858951,41.52089],"type":"Point"}
}