{
  "type": "Feature",
  "properties": {
    "addr:full": "212 Cook Rd Lebanon OH 45036",
    "addr:housenumber": "212",
    "addr:postcode": "45036",
    "addr:street": "Cook Rd",
    "iso:country": "US",
    "sg:address": "212 Cook Rd",
    "sg:city": "Lebanon",
    "sg:classifiers": [
      {
        "category": "Government",
        "subcategory": "Office",
        "type": "Public Place"
      }
    ],
    "sg:phone": "+1 513 933 1572",
    "sg:postcode": "45036",
    "sg:province": "OH",
    "wof:name": "Warren County Crisis Ctr",
    "wof:placetype": "venue"
  },
  "geometry": {"coordinates":[-84.200236,39.419359],"type":"Point"}
}
