{
  "type": "Feature",
  "properties": {
    "addr:full":"803 Bethel Rd Columbus OH 43214",
    "addr:housenumber":"803",
    "addr:postcode":"43214",
    "addr:street":"Bethel Rd",
    "iso:country":"US",
    "sg:address":"803 Bethel Rd",
    "sg:city":"Columbus",
    "sg:classifiers":[
        {
            "category":"Food & Beverages",
            "subcategory":"Specialty",
            "type":"Retail Goods"
        }
    ],
    "sg:phone":"+1 614 459 2378",
    "sg:postcode":"43214",
    "sg:province":"OH",
    "sg:tags":[
        "herb"
    ],
    "wof:name":"Fitness & Nutrition Center",
    "wof:placetype":"venue"
},
  "geometry": {"coordinates":[-83.043656,40.063275],"type":"Point"}
}