{
  "type": "Feature",
  "properties": {
    "addr:full": "3709 Wilmington Pike Dayton OH 45429",
    "addr:housenumber": "3709",
    "addr:postcode": "45429",
    "addr:street": "Wilmington Pike",
    "iso:country": "US",
    "sg:address": "3709 Wilmington Pike",
    "sg:city": "Dayton",
    "sg:classifiers": [
      {
        "category": "Retail",
        "subcategory": "Repair Shop",
        "type": "Services"
      }
    ],
    "sg:phone": "+1 937 298 6630",
    "sg:postcode": "45429",
    "sg:province": "OH",
    "sg:tags": [
      "television",
      "radio"
    ],
    "wof:name": "A V Specialist",
    "wof:placetype": "venue"
  },
  "geometry": {"coordinates":[-84.137371,39.693649],"type":"Point"}
}
