{
  "type": "Feature",
  "properties": {
    "addr:full": "9400 Friendsville Rd Seville OH 44273",
    "addr:postcode": "9400;44273",
    "addr:street": "Friendsville Rd",
    "iso:country": "US",
    "sg:address": "9400 Friendsville Rd",
    "sg:city": "Seville",
    "sg:classifiers": [
      {
        "category": "Building \u0026 Trades",
        "subcategory": "Construction",
        "type": "Services"
      }
    ],
    "sg:phone": "+1 330 948 2257",
    "sg:postcode": "44273",
    "sg:province": "OH",
    "sg:tags": [
      "hanging",
      "contractor"
    ],
    "wof:name": "Seaboards Restorations Co",
    "wof:placetype": "venue"
  },
  "geometry": {"coordinates":[-81.96663,41.022443],"type":"Point"}
}
