{
  "type": "Feature",
  "properties": {
    "addr:full":"17200 Wood Acre Trl Chagrin Falls OH 44023",
    "addr:housenumber":"17200",
    "addr:postcode":"44023",
    "addr:street":"Wood Acre Trl",
    "iso:country":"US",
    "sg:address":"17200 Wood Acre Trl",
    "sg:city":"Chagrin Falls",
    "sg:classifiers":[
        {
            "category":"Professional",
            "subcategory":"Computer Services",
            "type":"Services"
        }
    ],
    "sg:phone":"+1 440 708 0138",
    "sg:postcode":"44023",
    "sg:province":"OH",
    "sg:tags":[
        "consultant",
        "designer",
        "datum",
        "system"
    ],
    "wof:name":"Eagle Vision Systems Inc",
    "wof:placetype":"venue"
},
  "geometry": {"coordinates":[-81.29404700000001,41.400858],"type":"Point"}
}