{
  "type": "Feature",
  "properties": {
    "addr:full":"174 Hunt Club Dr Copley OH 44321",
    "addr:housenumber":"174",
    "addr:postcode":"44321",
    "addr:street":"Hunt Club Dr",
    "iso:country":"US",
    "sg:address":"174 Hunt Club Dr",
    "sg:city":"Copley",
    "sg:classifiers":[
        {
            "category":"Shopping",
            "subcategory":"Jewelry",
            "type":"Retail Goods"
        }
    ],
    "sg:phone":"+1 330 666 1807",
    "sg:postcode":"44321",
    "sg:province":"OH",
    "sg:tags":[
        "jeweler"
    ],
    "wof:name":"Sterling Jewelers",
    "wof:placetype":"venue"
},
  "geometry": {"coordinates":[-81.655461,41.130343],"type":"Point"}
}