{
  "type": "Feature",
  "properties": {
    "iso:country":"US",
    "sg:address":"9610 Co Rd 14",
    "sg:city":"Wauseon",
    "sg:classifiers":[
        {
            "category":"Building & Trades",
            "subcategory":"Construction",
            "type":"Services"
        }
    ],
    "sg:phone":"+1 419 335 3200",
    "sg:postcode":"43567",
    "sg:province":"OH",
    "sg:tags":[
        "roofing",
        "contractor"
    ],
    "wof:name":"Jensen Bridge & Roofing LLC",
    "wof:placetype":"venue"
},
  "geometry": {"coordinates":[-84.134311,41.615475],"type":"Point"}
}