{
  "type": "Feature",
  "properties": {
    "iso:country":"US",
    "sg:address":"166 Park Ave W",
    "sg:city":"Mansfield",
    "sg:classifiers":[
        {
            "category":"Taxi",
            "type":"Transportation"
        }
    ],
    "sg:phone":"+1 419 526 0300",
    "sg:postcode":"44902",
    "sg:province":"OH",
    "sg:tags":[
        "taxicab"
    ],
    "wof:name":"Skylite Taxi",
    "wof:placetype":"venue"
},
  "geometry": {"coordinates":[-82.522881,40.758948],"type":"Point"}
}