{
  "type": "Feature",
  "properties": {
    "addr:full":"520 Franklin Ave Newark OH 43056",
    "addr:housenumber":"520",
    "addr:postcode":"43056",
    "addr:street":"Franklin Ave",
    "iso:country":"US",
    "sg:address":"520 Franklin Ave",
    "sg:city":"Newark",
    "sg:classifiers":[
        {
            "category":"Health Services",
            "subcategory":"Doctor",
            "type":"Services"
        }
    ],
    "sg:phone":"+1 740 323 1232",
    "sg:postcode":"43056",
    "sg:province":"OH",
    "sg:tags":[
        "dentist"
    ],
    "wof:name":"Kenneth J Stovcik Inc",
    "wof:placetype":"venue"
},
  "geometry": {"coordinates":[-82.408441,40.038219],"type":"Point"}
}