{
  "type": "Feature",
  "properties": {
    "iso:country":"US",
    "sg:address":"424 W Plane St",
    "sg:city":"Bethel",
    "sg:classifiers":[
        {
            "category":"Professional",
            "subcategory":"Lawyer & Legal Services",
            "type":"Services"
        }
    ],
    "sg:phone":"+1 513 734 2888",
    "sg:postcode":"45106",
    "sg:province":"OH",
    "sg:tags":[
        "attorney"
    ],
    "wof:name":"Jeffry D Ferguson",
    "wof:placetype":"venue"
},
  "geometry": {"coordinates":[-84.082725,38.963767],"type":"Point"}
}