{
  "type": "Feature",
  "properties": {
    "addr:full":"326 W Main St Conneaut OH 44030",
    "addr:housenumber":"326",
    "addr:postcode":"44030",
    "addr:street":"W Main St",
    "iso:country":"US",
    "sg:address":"326 W Main St",
    "sg:city":"Conneaut",
    "sg:classifiers":[
        {
            "category":"Personal",
            "subcategory":"Barber",
            "type":"Services"
        }
    ],
    "sg:phone":"+1 440 593 6135",
    "sg:postcode":"44030",
    "sg:province":"OH",
    "wof:name":"Broad St Hairport",
    "wof:placetype":"venue"
},
  "geometry": {"coordinates":[-80.600337,41.934436],"type":"Point"}
}