{
  "type": "Feature",
  "properties": {
    "iso:country":"US",
    "sg:address":"604 S 30th St",
    "sg:city":"Newark",
    "sg:classifiers":[
        {
            "category":"Health Services",
            "subcategory":"Optometrist",
            "type":"Services"
        }
    ],
    "sg:phone":"+1 740 522 8444",
    "sg:postcode":"43056",
    "sg:province":"OH",
    "wof:name":"Indian Mound Eye Clinic",
    "wof:placetype":"venue"
},
  "geometry": {"coordinates":[-82.44271000000001,40.035471],"type":"Point"}
}