{
  "type": "Feature",
  "properties": {
    "iso:country":"US",
    "sg:address":"324 Noble Ave",
    "sg:city":"Akron",
    "sg:classifiers":[
        {
            "category":"Professional",
            "type":"Services"
        }
    ],
    "sg:phone":"+1 330 384 1557",
    "sg:postcode":"44320",
    "sg:province":"OH",
    "sg:tags":[
        "technical",
        "preparation",
        "manual"
    ],
    "wof:name":"M & G Polymers Technology",
    "wof:placetype":"venue"
},
  "geometry": {"coordinates":[-81.55398599999999,41.087766],"type":"Point"}
}