{
  "type": "Feature",
  "properties": {
    "addr:full": "324 Noble Ave Akron OH 44320",
    "addr:housenumber": "324",
    "addr:postcode": "44320",
    "addr:street": "Noble Ave",
    "iso:country": "US",
    "sg:address": "324 Noble Ave",
    "sg:city": "Akron",
    "sg:classifiers": [
      {
        "category": "Professional",
        "type": "Services"
      }
    ],
    "sg:phone": "+1 330 384 1557",
    "sg:postcode": "44320",
    "sg:province": "OH",
    "sg:tags": [
      "technical",
      "preparation",
      "manual"
    ],
    "wof:name": "M \u0026 G Polymers Technology",
    "wof:placetype": "venue"
  },
  "geometry": {"coordinates":[-81.553986,41.087766],"type":"Point"}
}
