{
  "type": "Feature",
  "properties": {
    "iso:country":"US",
    "sg:address":"42 Arnold Pl",
    "sg:city":"Dayton",
    "sg:classifiers":[
        {
            "category":"Social Services",
            "type":"Services"
        }
    ],
    "sg:phone":"+1 937 278 8219",
    "sg:postcode":"45402",
    "sg:province":"OH",
    "sg:tags":[
        "organization",
        "welfare"
    ],
    "wof:name":"Alvis House-Cope",
    "wof:placetype":"venue"
},
  "geometry": {"coordinates":[-84.210808,39.766487],"type":"Point"}
}