{
  "type": "Feature",
  "properties": {
    "iso:country":"US",
    "sg:address":"4381 Walnut St",
    "sg:city":"Buckeye Lake",
    "sg:classifiers":[
        {
            "category":"Organizations",
            "subcategory":"Religious Organization",
            "type":"Services"
        }
    ],
    "sg:phone":"+1 740 928 4976",
    "sg:postcode":"43008",
    "sg:province":"OH",
    "sg:tags":[
        "church"
    ],
    "wof:name":"First Community Church",
    "wof:placetype":"venue"
},
  "geometry": {"coordinates":[-82.496062,39.929031],"type":"Point"}
}