{
  "type": "Feature",
  "properties": {
    "iso:country":"US",
    "sg:address":"4700 Reed Rd",
    "sg:city":"Columbus",
    "sg:classifiers":[
        {
            "category":"Organizations",
            "subcategory":"Non-profit Organization",
            "type":"Services"
        }
    ],
    "sg:phone":"+1 614 451 3232",
    "sg:postcode":"43220",
    "sg:province":"OH",
    "wof:name":"Council On American Islm Rltns",
    "wof:placetype":"venue"
},
  "geometry": {"coordinates":[-83.066864,40.052975],"type":"Point"}
}