{
  "type": "Feature",
  "properties": {
    "iso:country":"US",
    "sg:address":"5384 Wilson Mills Rd",
    "sg:city":"Cleveland",
    "sg:classifiers":[
        {
            "category":"Organizations",
            "subcategory":"Religious Organization",
            "type":"Services"
        }
    ],
    "sg:phone":"+1 440 442 6725",
    "sg:postcode":"44143",
    "sg:province":"OH",
    "sg:tags":[
        "catholic"
    ],
    "wof:name":"Blessed Sacrament Fathers",
    "wof:placetype":"venue"
},
  "geometry": {"coordinates":[-81.485958,41.538935],"type":"Point"}
}