{
  "type": "Feature",
  "properties": {
    "iso:country":"US",
    "sg:address":"322 2nd Ave",
    "sg:city":"Gallipolis",
    "sg:classifiers":[
        {
            "category":"Insurance",
            "subcategory":"Insurance Agent",
            "type":"Services"
        }
    ],
    "sg:phone":"+1 740 446 8235",
    "sg:postcode":"45631",
    "sg:province":"OH",
    "wof:name":"Lynch Agency",
    "wof:placetype":"venue"
},
  "geometry": {"coordinates":[-82.205719,38.807678],"type":"Point"}
}