{
  "type": "Feature",
  "properties": {
    "iso:country":"US",
    "sg:address":"6004 Cleveland Ave",
    "sg:city":"Columbus",
    "sg:classifiers":[
        {
            "category":"Health Services",
            "subcategory":"Podiatrist",
            "type":"Services"
        }
    ],
    "sg:phone":"+1 614 901 0000",
    "sg:postcode":"43231",
    "sg:province":"OH",
    "wof:name":"Ohio Foot Care Inc",
    "wof:placetype":"venue"
},
  "geometry": {"coordinates":[-82.950292,40.094085],"type":"Point"}
}