{
  "type": "Feature",
  "properties": {
    "iso:country":"US",
    "sg:address":"7395 East Pike",
    "sg:city":"Zanesville",
    "sg:classifiers":[
        {
            "category":"Home & Garden",
            "subcategory":"Home Furnishings",
            "type":"Retail Goods"
        }
    ],
    "sg:phone":"+1 740 872 3345",
    "sg:postcode":"43701",
    "sg:province":"OH",
    "sg:tags":[
        "pottery"
    ],
    "sg:website":"www.zanesvillepottery.com",
    "wof:name":"Zanesville Pottery & China",
    "wof:placetype":"venue"
},
  "geometry": {"coordinates":[-81.855493,39.971631],"type":"Point"}
}