{
  "type": "Feature",
  "properties": {
    "addr:full": "7395 East Pike Zanesville OH 43701",
    "addr:housenumber": "7395",
    "addr:postcode": "43701",
    "addr:street": "East Pike",
    "iso:country": "US",
    "sg:address": "7395 East Pike",
    "sg:city": "Zanesville",
    "sg:classifiers": [
      {
        "category": "Home \u0026 Garden",
        "subcategory": "Home Furnishings",
        "type": "Retail Goods"
      }
    ],
    "sg:phone": "+1 740 872 3345",
    "sg:postcode": "43701",
    "sg:province": "OH",
    "sg:tags": [
      "pottery"
    ],
    "sg:website": "www.zanesvillepottery.com",
    "wof:name": "Zanesville Pottery \u0026 China",
    "wof:placetype": "venue"
  },
  "geometry": {"coordinates":[-81.855493,39.971631],"type":"Point"}
}
