{
  "type": "Feature",
  "properties": {
    "addr:full": "1644 Sawyer St Mogadore OH 44260",
    "addr:housenumber": "1644",
    "addr:postcode": "44260",
    "addr:street": "Sawyer St",
    "iso:country": "US",
    "sg:address": "1644 Sawyer St",
    "sg:city": "Mogadore",
    "sg:classifiers": [
      {
        "category": "Freight",
        "type": "Transportation"
      }
    ],
    "sg:phone": "+1 330 628 5075",
    "sg:postcode": "44260",
    "sg:province": "OH",
    "sg:tags": [
      "arrangement",
      "broker",
      "trucking"
    ],
    "wof:name": "P \u0026 D Consultants Inc",
    "wof:placetype": "venue"
  },
  "geometry": {"coordinates":[-81.381725,41.032266],"type":"Point"}
}
