{
  "type": "Feature",
  "properties": {
    "addr:full": "1030 Ross Ave Cincinnati OH 45205",
    "addr:housenumber": "1030",
    "addr:postcode": "45205",
    "addr:street": "Ross Ave",
    "iso:country": "US",
    "sg:address": "1030 Ross Ave",
    "sg:city": "Cincinnati",
    "sg:classifiers": [
      {
        "category": "Home \u0026 Garden",
        "subcategory": "Carpets \u0026 Floor Coverings",
        "type": "Retail Goods"
      }
    ],
    "sg:phone": "+1 513 471 8500",
    "sg:postcode": "45205",
    "sg:province": "OH",
    "sg:tags": [
      "material"
    ],
    "wof:name": "Valvano Flooring",
    "wof:placetype": "venue"
  },
  "geometry": {"coordinates":[-84.574256,39.113949],"type":"Point"}
}
