{
  "type": "Feature",
  "properties": {
    "addr:full": "734 Garden Rd Columbus OH 43214",
    "addr:housenumber": "734",
    "addr:postcode": "43214",
    "addr:street": "Garden Rd",
    "iso:country": "US",
    "sg:address": "734 Garden Rd",
    "sg:city": "Columbus",
    "sg:classifiers": [
      {
        "category": "Retail",
        "subcategory": "Auto Repair",
        "type": "Services"
      }
    ],
    "sg:phone": "+1 614 268 3500",
    "sg:postcode": "43214",
    "sg:province": "OH",
    "sg:tags": [
      "sun",
      "installation",
      "automotive",
      "roof",
      "customizing"
    ],
    "wof:name": "Auto Options Inc",
    "wof:placetype": "venue"
  },
  "geometry": {"coordinates":[-82.999899,40.055588],"type":"Point"}
}
