{
  "type": "Feature",
  "properties": {
    "addr:full": "11482 State Rte 93 Pedro OH 45659",
    "addr:housenumber": "11482",
    "addr:postcode": "45659",
    "addr:street": "State Rte 93 Pedro",
    "iso:country": "US",
    "sg:address": "11482 State Rte 93",
    "sg:city": "Pedro",
    "sg:classifiers": [
      {
        "category": "Wholesale",
        "subcategory": "Furniture",
        "type": "Manufacturing \u0026 Wholesale Goods"
      }
    ],
    "sg:phone": "+1 740 533 3718",
    "sg:postcode": "45659",
    "sg:province": "OH",
    "wof:name": "Lucilles Furniture",
    "wof:placetype": "venue"
  },
  "geometry": {"coordinates":[-82.659202,38.662804],"type":"Point"}
}
