{
  "type": "Feature",
  "properties": {
    "addr:full": "416 N Henry St Crestline OH 44827",
    "addr:housenumber": "416",
    "addr:postcode": "44827",
    "addr:street": "N Henry St",
    "iso:country": "US",
    "sg:address": "416 N Henry St",
    "sg:city": "Crestline",
    "sg:classifiers": [
      {
        "category": "Organizations",
        "subcategory": "Professional Association",
        "type": "Services"
      }
    ],
    "sg:phone": "+1 419 683 1047",
    "sg:postcode": "44827",
    "sg:province": "OH",
    "wof:name": "Delta Kappa Gamma Chapter",
    "wof:placetype": "venue"
  },
  "geometry": {"coordinates":[-82.7409,40.789192],"type":"Point"}
}
