{
  "type": "Feature",
  "properties": {
    "iso:country":"US",
    "sg:address":"1737 Georgetown Rd",
    "sg:city":"Hudson",
    "sg:classifiers":[
        {
            "category":"Professional",
            "type":"Services"
        }
    ],
    "sg:phone":"+1 330 342 9388",
    "sg:postcode":"44236",
    "sg:province":"OH",
    "sg:tags":[
        "establishment"
    ],
    "wof:name":"Ohio School Facilities Cmmssn",
    "wof:placetype":"venue"
},
  "geometry": {"coordinates":[-81.431409,41.208305],"type":"Point"}
}