{
  "type": "Feature",
  "properties": {
    "iso:country":"US",
    "sg:address":"114 N West St",
    "sg:city":"Lima",
    "sg:classifiers":[
        {
            "category":"Banks & Credit Unions",
            "subcategory":"Bank",
            "type":"Services"
        }
    ],
    "sg:phone":"+1 419 224 6887",
    "sg:postcode":"45801",
    "sg:province":"OH",
    "sg:tags":[
        "mortgage"
    ],
    "wof:name":"Roebuck Mortgage Services LLC",
    "wof:placetype":"venue"
},
  "geometry": {"coordinates":[-84.107708,40.741161],"type":"Point"}
}