{
  "type": "Feature",
  "properties": {
    "addr:full": "114 N West St Lima OH 45801",
    "addr:housenumber": "114",
    "addr:postcode": "45801",
    "addr:street": "N West St",
    "iso:country": "US",
    "sg:address": "114 N West St",
    "sg:city": "Lima",
    "sg:classifiers": [
      {
        "category": "Banks \u0026 Credit Unions",
        "subcategory": "Bank",
        "type": "Services"
      }
    ],
    "sg:phone": "+1 419 224 6887",
    "sg:postcode": "45801",
    "sg:province": "OH",
    "sg:tags": [
      "mortgage"
    ],
    "wof:name": "Roebuck Mortgage Services LLC",
    "wof:placetype": "venue"
  },
  "geometry": {"coordinates":[-84.107708,40.741161],"type":"Point"}
}
