{
  "type": "Feature",
  "properties": {
    "iso:country":"US",
    "sg:address":"7308 Southpointe Dr",
    "sg:city":"Cincinnati",
    "sg:classifiers":[
        {
            "category":"Recreation",
            "type":"Entertainment"
        }
    ],
    "sg:phone":"+1 513 941 7408",
    "sg:postcode":"45233",
    "sg:province":"OH",
    "sg:tags":[
        "astrologer"
    ],
    "wof:name":"Star Quest",
    "wof:placetype":"venue"
},
  "geometry": {"coordinates":[-84.691619,39.131161],"type":"Point"}
}