{
  "type": "Feature",
  "properties": {
    "iso:country":"US",
    "sg:address":"10403 Harrison Ave",
    "sg:city":"Harrison",
    "sg:classifiers":[
        {
            "category":"Professional",
            "subcategory":"Management & Consulting",
            "type":"Services"
        }
    ],
    "sg:phone":"+1 513 367 1113",
    "sg:postcode":"45030",
    "sg:province":"IN",
    "sg:tags":[
        "consultant",
        "financial"
    ],
    "wof:name":"Conservative Fincl Solutions",
    "wof:placetype":"venue"
},
  "geometry": {"coordinates":[-84.787446,39.248522],"type":"Point"}
}