{
  "type": "Feature",
  "properties": {
    "addr:full": "999 E Market St Celina OH 45822",
    "addr:housenumber": "999",
    "addr:postcode": "45822",
    "addr:street": "E Market St",
    "iso:country": "US",
    "sg:address": "999 E Market St",
    "sg:city": "Celina",
    "sg:classifiers": [
      {
        "category": "Home \u0026 Garden",
        "subcategory": "Carpets \u0026 Floor Coverings",
        "type": "Retail Goods"
      }
    ],
    "sg:phone": "+1 419 586 2492",
    "sg:postcode": "45822",
    "sg:province": "OH",
    "sg:tags": [
      "furniture"
    ],
    "wof:name": "B \u0026 B House Of Carpet",
    "wof:placetype": "venue"
  },
  "geometry": {"coordinates":[-84.556523,40.549102],"type":"Point"}
}
