{
  "type": "Feature",
  "properties": {
    "addr:full":"800 Raider Dr Mc Connelsville OH 43756",
    "addr:housenumber":"800",
    "addr:postcode":"43756",
    "addr:street":"Raider Dr",
    "iso:country":"US",
    "sg:address":"800 Raider Dr",
    "sg:city":"Mc Connelsville",
    "sg:classifiers":[
        {
            "category":"Education",
            "subcategory":"School",
            "type":"Public Place"
        }
    ],
    "sg:phone":"+1 740 962 2944",
    "sg:postcode":"43756",
    "sg:province":"OH",
    "sg:website":"www.mlsd.k12.oh.us",
    "wof:name":"Morgan High School",
    "wof:placetype":"venue"
},
  "geometry": {"coordinates":[-81.816546,39.611743],"type":"Point"}
}