{
  "type": "Feature",
  "properties": {
    "addr:full": "4531 Schinkal Rd Cincinnati OH 45248",
    "addr:housenumber": "4531",
    "addr:postcode": "45248",
    "addr:street": "Schinkal Rd",
    "iso:country": "US",
    "sg:address": "4531 Schinkal Rd",
    "sg:city": "Cincinnati",
    "sg:classifiers": [
      {
        "category": "Building \u0026 Trades",
        "subcategory": "Landscaping Services",
        "type": "Services"
      }
    ],
    "sg:phone": "+1 513 467 0040",
    "sg:postcode": "45248",
    "sg:province": "OH",
    "sg:tags": [
      "mowing"
    ],
    "wof:name": "Wood Groundskeeping",
    "wof:placetype": "venue"
  },
  "geometry": {"coordinates":[-84.689551,39.17449],"type":"Point"}
}
