{
  "type": "Feature",
  "properties": {
    "addr:full": "615 W Main St Blanchester OH 45107",
    "addr:housenumber": "615",
    "addr:postcode": "45107",
    "addr:street": "W Main St",
    "iso:country": "US",
    "sg:address": "615 W Main St",
    "sg:city": "Blanchester",
    "sg:classifiers": [
      {
        "category": "Health Services",
        "subcategory": "Doctor",
        "type": "Services"
      }
    ],
    "sg:phone": "+1 937 783 5505",
    "sg:postcode": "45107",
    "sg:province": "OH",
    "wof:name": "Gundler Jody DDS",
    "wof:placetype": "venue"
  },
  "geometry": {"coordinates":[-83.996499,39.290497],"type":"Point"}
}
