{
  "type": "Feature",
  "properties": {
    "iso:country":"US",
    "sg:address":"4419 Talcott Trl",
    "sg:city":"Dayton",
    "sg:classifiers":[
        {
            "category":"Shopping",
            "subcategory":"Discount & Variety Stores",
            "type":"Retail Goods"
        }
    ],
    "sg:phone":"+1 937 837 2549",
    "sg:postcode":"45426",
    "sg:province":"OH",
    "sg:tags":[
        "merchandise",
        "general"
    ],
    "wof:name":"C E Specialty Merchandise",
    "wof:placetype":"venue"
},
  "geometry": {"coordinates":[-84.327164,39.808151],"type":"Point"}
}