{
  "type": "Feature",
  "properties": {
    "iso:country":"US",
    "sg:address":"6262 Hamilton Middletown Rd",
    "sg:city":"Middletown",
    "sg:classifiers":[
        {
            "category":"Government",
            "subcategory":"Fire Station",
            "type":"Public Place"
        }
    ],
    "sg:phone":"+1 513 539 8380",
    "sg:postcode":"45044",
    "sg:province":"OH",
    "sg:tags":[
        "department"
    ],
    "wof:name":"Monroe Fire Dept",
    "wof:placetype":"venue"
},
  "geometry": {"coordinates":[-84.42074100000001,39.452953],"type":"Point"}
}