{
  "type": "Feature",
  "properties": {
    "addr:full": "6262 Hamilton Middletown Rd Middletown OH 45044",
    "addr:housenumber": "6262",
    "addr:postcode": "45044",
    "addr:street": "Hamilton Middletown Rd",
    "iso:country": "US",
    "sg:address": "6262 Hamilton Middletown Rd",
    "sg:city": "Middletown",
    "sg:classifiers": [
      {
        "category": "Government",
        "subcategory": "Fire Station",
        "type": "Public Place"
      }
    ],
    "sg:phone": "+1 513 539 8380",
    "sg:postcode": "45044",
    "sg:province": "OH",
    "sg:tags": [
      "department"
    ],
    "wof:name": "Monroe Fire Dept",
    "wof:placetype": "venue"
  },
  "geometry": {"coordinates":[-84.420741,39.452953],"type":"Point"}
}
