{
  "type": "Feature",
  "properties": {
    "addr:full":"2144 Broadview Rd Cleveland OH 44109",
    "addr:housenumber":"2144",
    "addr:postcode":"44109",
    "addr:street":"Broadview Rd",
    "iso:country":"US",
    "sg:address":"2144 Broadview Rd",
    "sg:city":"Cleveland",
    "sg:classifiers":[
        {
            "category":"Fast Food",
            "type":"Food & Drink"
        },
        {
            "category":"Deli",
            "type":"Food & Drink"
        },
        {
            "category":"Restaurant",
            "type":"Food & Drink"
        },
        {
            "category":"Food & Beverages",
            "subcategory":"Groceries & Convenience Stores",
            "type":"Retail Goods"
        }
    ],
    "sg:phone":"+1 216 351 7282",
    "sg:postcode":"44109",
    "sg:province":"OH",
    "sg:tags":[
        "shop",
        "delicatessen",
        "sandwich",
        "health",
        "take"
    ],
    "sg:website":"http://www.subway.com",
    "wof:name":"Subway Shop",
    "wof:placetype":"venue"
},
  "geometry": {"coordinates":[-81.699315,41.437984],"type":"Point"}
}