{
  "type": "Feature",
  "properties": {
    "addr:full":"7503 Mudbrook St NW Massillon OH 44646",
    "addr:housenumber":"7503",
    "addr:postcode":"44646",
    "addr:street":"Mudbrook St Nw",
    "iso:country":"US",
    "sg:address":"7503 Mudbrook St NW",
    "sg:city":"Massillon",
    "sg:classifiers":[
        {
            "category":"Education",
            "subcategory":"School",
            "type":"Public Place"
        }
    ],
    "sg:phone":"+1 330 830 8028",
    "sg:postcode":"44646",
    "sg:province":"OH",
    "sg:tags":[
        "elementary",
        "secondary"
    ],
    "wof:name":"Sauder Elementary School",
    "wof:placetype":"venue"
},
  "geometry": {"coordinates":[-81.49012,40.867426],"type":"Point"}
}