{
  "type": "Feature",
  "properties": {
    "addr:full": "7011 S Palmer Rd New Carlisle OH 45344",
    "addr:housenumber": "7011",
    "addr:postcode": "45344",
    "addr:street": "S Palmer Rd",
    "iso:country": "US",
    "sg:address": "7011 S Palmer Rd",
    "sg:city": "New Carlisle",
    "sg:phone": "+1 937 845 8896",
    "sg:postcode": "45344",
    "sg:province": "OH",
    "sg:tags": [
      "farm",
      "corn",
      "soybean"
    ],
    "wof:name": "Whispering Pine Farm",
    "wof:placetype": "venue"
  },
  "geometry": {"coordinates":[-84.066524,39.916898],"type":"Point"}
}
