{
  "type": "Feature",
  "properties": {
    "addr:full": "501 2nd St Marietta OH 45750",
    "addr:housenumber": "501",
    "addr:postcode": "45750",
    "addr:street": "2Nd St",
    "iso:country": "US",
    "sg:address": "501 2nd St",
    "sg:city": "Marietta",
    "sg:classifiers": [
      {
        "category": "Personal",
        "subcategory": "Beauty Salon",
        "type": "Services"
      }
    ],
    "sg:phone": "+1 740 373 3698",
    "sg:postcode": "45750",
    "sg:province": "OH",
    "wof:name": "Cuts N Curls",
    "wof:placetype": "venue"
  },
  "geometry": {"coordinates":[-81.459983,39.42059],"type":"Point"}
}
