{
  "type": "Feature",
  "properties": {
    "iso:country":"US",
    "sg:address":"7457 Oakmeadows Dr",
    "sg:city":"Columbus",
    "sg:phone":"+1 614 888 7410",
    "sg:postcode":"43085",
    "sg:province":"OH",
    "sg:tags":[
        "equipment",
        "commercial"
    ],
    "wof:name":"Skyline Displays-So Ohio",
    "wof:placetype":"venue"
},
  "geometry": {"coordinates":[-82.980666,40.118393],"type":"Point"}
}