{
  "type": "Feature",
  "properties": {
    "iso:country":"US",
    "sg:address":"1738 State Rte 202",
    "sg:city":"Troy",
    "sg:classifiers":[
        {
            "category":"Farming",
            "subcategory":"Fish & Marine Products",
            "type":"Manufacturing & Wholesale Goods"
        }
    ],
    "sg:phone":"+1 937 335 4182",
    "sg:postcode":"45373",
    "sg:province":"OH",
    "sg:tags":[
        "management"
    ],
    "wof:name":"Lower Lost Creek Reserve Inc",
    "wof:placetype":"venue"
},
  "geometry": {"coordinates":[-84.176592,40.018857],"type":"Point"}
}