{
  "type": "Feature",
  "properties": {
    "addr:full": "1738 State Rte 202 Troy OH 45373",
    "addr:housenumber": "1738",
    "addr:postcode": "45373",
    "addr:street": "State Rte 202",
    "iso:country": "US",
    "sg:address": "1738 State Rte 202",
    "sg:city": "Troy",
    "sg:classifiers": [
      {
        "category": "Farming",
        "subcategory": "Fish \u0026 Marine Products",
        "type": "Manufacturing \u0026 Wholesale Goods"
      }
    ],
    "sg:phone": "+1 937 335 4182",
    "sg:postcode": "45373",
    "sg:province": "OH",
    "sg:tags": [
      "management"
    ],
    "wof:name": "Lower Lost Creek Reserve Inc",
    "wof:placetype": "venue"
  },
  "geometry": {"coordinates":[-84.176592,40.018857],"type":"Point"}
}
