{
  "type": "Feature",
  "properties": {
    "addr:full": "5102 Pleasant Ave Fairfield OH 45014",
    "addr:housenumber": "5102",
    "addr:postcode": "45014",
    "addr:street": "Pleasant Ave",
    "iso:country": "US",
    "sg:address": "5102 Pleasant Ave",
    "sg:city": "Fairfield",
    "sg:classifiers": [
      {
        "category": "Shopping",
        "subcategory": "Gifts \u0026 Souvenirs",
        "type": "Retail Goods"
      }
    ],
    "sg:phone": "+1 513 737 9772",
    "sg:postcode": "45014",
    "sg:province": "OH",
    "wof:name": "Hooterville Sports Cards",
    "wof:placetype": "venue"
  },
  "geometry": {"coordinates":[-84.559795,39.340566],"type":"Point"}
}
