{
  "type": "Feature",
  "properties": {
    "addr:full":"503 W High St Hicksville OH 43526",
    "addr:housenumber":"503",
    "addr:postcode":"43526",
    "addr:street":"W High St",
    "iso:country":"US",
    "sg:address":"503 W High St",
    "sg:city":"Hicksville",
    "sg:classifiers":[
        {
            "category":"Shopping",
            "subcategory":"Computers & Home Electronics",
            "type":"Retail Goods"
        }
    ],
    "sg:phone":"+1 419 542 9729",
    "sg:postcode":"43526",
    "sg:province":"OH",
    "sg:tags":[
        "equipment",
        "electronic",
        "supply"
    ],
    "wof:name":"SDH Marketing",
    "wof:placetype":"venue"
},
  "geometry": {"coordinates":[-84.773303,41.287811],"type":"Point"}
}