{
  "type": "Feature",
  "properties": {
    "addr:full":"1637 E US Hwy 36 Urbana OH 43078",
    "addr:housenumber":"1637",
    "addr:postcode":"43078",
    "addr:street":"E Us Hwy 36",
    "iso:country":"US",
    "sg:address":"1637 E US Hwy 36",
    "sg:city":"Urbana",
    "sg:classifiers":[
        {
            "category":"Shopping",
            "subcategory":"Beauty & Cosmetics",
            "type":"Retail Goods"
        }
    ],
    "sg:phone":"+1 937 653 6611",
    "sg:postcode":"43078",
    "sg:province":"OH",
    "sg:tags":[
        "equipment",
        "supply"
    ],
    "wof:name":"Sally Beauty Supply 1953",
    "wof:placetype":"venue"
},
  "geometry": {"coordinates":[-83.721406,40.106148],"type":"Point"}
}