{
  "type": "Feature",
  "properties": {
    "iso:country":"US",
    "sg:address":"1400 Oakhill Ave NE",
    "sg:city":"Youngstown",
    "sg:classifiers":[
        {
            "category":"Education",
            "subcategory":"School",
            "type":"Public Place"
        }
    ],
    "sg:phone":"+1 330 750 0100",
    "sg:postcode":"44507",
    "sg:province":"OH",
    "wof:name":"Summit Academy Of Youngstown",
    "wof:placetype":"venue"
},
  "geometry": {"coordinates":[-80.659719,41.085955],"type":"Point"}
}