{
  "type": "Feature",
  "properties": {
    "addr:full":"253 W Aurora Rd Northfield OH 44067",
    "addr:housenumber":"253",
    "addr:postcode":"44067",
    "addr:street":"W Aurora Rd",
    "iso:country":"US",
    "sg:address":"253 W Aurora Rd",
    "sg:city":"Northfield",
    "sg:classifiers":[
        {
            "category":"Professional",
            "type":"Services"
        }
    ],
    "sg:phone":"+1 330 467 9600",
    "sg:postcode":"44067",
    "sg:province":"OH",
    "wof:name":"Paul Jackson Family Ltd Partnr",
    "wof:placetype":"venue"
},
  "geometry": {"coordinates":[-81.54579699999999,41.314348],"type":"Point"}
}