{
  "type": "Feature",
  "properties": {
    "addr:full": "940 Red Oak Cir Medina OH 44256",
    "addr:housenumber": "940",
    "addr:postcode": "44256",
    "addr:street": "Red Oak Cir",
    "iso:country": "US",
    "sg:address": "940 Red Oak Cir",
    "sg:city": "Medina",
    "sg:classifiers": [
      {
        "category": "Manufacturing",
        "subcategory": "Printing",
        "type": "Manufacturing \u0026 Wholesale Goods"
      }
    ],
    "sg:phone": "+1 330 723 9098",
    "sg:postcode": "44256",
    "sg:province": "OH",
    "sg:tags": [
      "commercial"
    ],
    "wof:name": "Mark Ashleys",
    "wof:placetype": "venue"
  },
  "geometry": {"coordinates":[-81.849218,41.122993],"type":"Point"}
}
