{
  "type": "Feature",
  "properties": {
    "iso:country":"US",
    "sg:address":"940 Red Oak Cir",
    "sg:city":"Medina",
    "sg:classifiers":[
        {
            "category":"Manufacturing",
            "subcategory":"Printing",
            "type":"Manufacturing & Wholesale Goods"
        }
    ],
    "sg:phone":"+1 330 723 9098",
    "sg:postcode":"44256",
    "sg:province":"OH",
    "sg:tags":[
        "commercial"
    ],
    "wof:name":"Mark Ashleys",
    "wof:placetype":"venue"
},
  "geometry": {"coordinates":[-81.84921799999999,41.122993],"type":"Point"}
}