{
  "type": "Feature",
  "properties": {
    "addr:full": "7963 Morgan Rd Cleves OH 45002",
    "addr:housenumber": "7963",
    "addr:postcode": "45002",
    "addr:street": "Morgan Rd",
    "iso:country": "US",
    "sg:address": "7963 Morgan Rd",
    "sg:city": "Cleves",
    "sg:classifiers": [
      {
        "category": "Manufacturing",
        "subcategory": "Tools \u0026 Machinery",
        "type": "Manufacturing \u0026 Wholesale Goods"
      }
    ],
    "sg:phone": "+1 513 353 2100",
    "sg:postcode": "45002",
    "sg:province": "OH",
    "sg:tags": [
      "model",
      "maker"
    ],
    "wof:name": "J-Co",
    "wof:placetype": "venue"
  },
  "geometry": {"coordinates":[-84.752544,39.228197],"type":"Point"}
}
