{
  "type": "Feature",
  "properties": {
    "iso:country":"US",
    "sg:address":"284 N Washington St",
    "sg:city":"Tiffin",
    "sg:classifiers":[
        {
            "category":"Shopping",
            "subcategory":"Pharmacy",
            "type":"Retail Goods"
        }
    ],
    "sg:phone":"+1 419 443 0189",
    "sg:postcode":"44883",
    "sg:province":"OH",
    "wof:name":"CVS Pharmacy",
    "wof:placetype":"venue"
},
  "geometry": {"coordinates":[-83.178122,41.124584],"type":"Point"}
}