{
  "type": "Feature",
  "properties": {
    "addr:full":"421 Anderson Ferry Rd Cincinnati OH 45238",
    "addr:housenumber":"421",
    "addr:postcode":"45238",
    "addr:street":"Anderson Ferry Rd",
    "iso:country":"US",
    "sg:address":"421 Anderson Ferry Rd",
    "sg:city":"Cincinnati",
    "sg:classifiers":[
        {
            "category":"Banks & Credit Unions",
            "subcategory":"Investment Brokerage",
            "type":"Services"
        },
        {
            "category":"Professional",
            "subcategory":"Business Services",
            "type":"Services"
        }
    ],
    "sg:phone":"+1 513 244 8900",
    "sg:postcode":"45238",
    "sg:province":"OH",
    "sg:tags":[
        "broker",
        "commodity"
    ],
    "wof:name":"Stevens Business Group",
    "wof:placetype":"venue"
},
  "geometry": {"coordinates":[-84.618103,39.094978],"type":"Point"}
}