{
  "type": "Feature",
  "properties": {
    "iso:country":"US",
    "sg:address":"2211 W Laskey Rd",
    "sg:city":"Toledo",
    "sg:classifiers":[
        {
            "category":"Retail",
            "subcategory":"Auto Repair",
            "type":"Services"
        }
    ],
    "sg:phone":"+1 419 472 2221",
    "sg:postcode":"43613",
    "sg:province":"OH",
    "sg:tags":[
        "wheel",
        "axle",
        "alignment"
    ],
    "wof:name":"Voll Frame & Alignment",
    "wof:placetype":"venue"
},
  "geometry": {"coordinates":[-83.597568,41.706767],"type":"Point"}
}