{
  "type": "Feature",
  "properties": {
    "addr:full": "9652 Murray Ridge Rd Elyria OH 44035",
    "addr:housenumber": "9652",
    "addr:postcode": "44035",
    "addr:street": "Murray Ridge Rd",
    "iso:country": "US",
    "sg:address": "9652 Murray Ridge Rd",
    "sg:city": "Elyria",
    "sg:classifiers": [
      {
        "category": "Organizations",
        "subcategory": "Religious Organization",
        "type": "Services"
      }
    ],
    "sg:phone": "+1 440 355 8333",
    "sg:postcode": "44035",
    "sg:province": "OH",
    "sg:tags": [
      "church"
    ],
    "wof:name": "LA Grange SDA Church",
    "wof:placetype": "venue"
  },
  "geometry": {"coordinates":[-82.135991,41.349036],"type":"Point"}
}
