{
  "type": "Feature",
  "properties": {
    "addr:full":"407 Vine St Cincinnati OH 45202",
    "addr:housenumber":"407",
    "addr:postcode":"45202",
    "addr:street":"Vine St",
    "iso:country":"US",
    "sg:address":"407 Vine St",
    "sg:city":"Cincinnati",
    "sg:classifiers":[
        {
            "category":"Professional",
            "subcategory":"Research",
            "type":"Services"
        }
    ],
    "sg:phone":"+1 513 256 8495",
    "sg:postcode":"45202",
    "sg:province":"OH",
    "sg:tags":[
        "marketing",
        "nonphysical"
    ],
    "wof:name":"Samplesaint",
    "wof:placetype":"venue"
},
  "geometry": {"coordinates":[-84.512826,39.100241],"type":"Point"}
}