{
  "type": "Feature",
  "properties": {
    "addr:full":"4027 Eastern Ave Cincinnati OH 45226",
    "addr:housenumber":"4027",
    "addr:postcode":"45226",
    "addr:street":"Eastern Ave",
    "iso:country":"US",
    "sg:address":"4027 Eastern Ave",
    "sg:city":"Cincinnati",
    "sg:classifiers":[
        {
            "category":"Government",
            "subcategory":"Office",
            "type":"Public Place"
        }
    ],
    "sg:phone":"+1 513 321 1395",
    "sg:postcode":"45226",
    "sg:province":"OH",
    "sg:tags":[
        "city",
        "resource",
        "human"
    ],
    "wof:name":"Cincinnati WIC",
    "wof:placetype":"venue"
},
  "geometry": {"coordinates":[-84.432249,39.108682],"type":"Point"}
}