{
  "type": "Feature",
  "properties": {
    "addr:full":"19 N Pearl St Covington OH 45318",
    "addr:housenumber":"19",
    "addr:postcode":"45318",
    "addr:street":"N Pearl St",
    "iso:country":"US",
    "sg:address":"19 N Pearl St",
    "sg:city":"Covington",
    "sg:classifiers":[
        {
            "category":"Professional",
            "type":"Services"
        }
    ],
    "sg:phone":"+1 937 473 2150",
    "sg:postcode":"45318",
    "sg:province":"OH",
    "wof:name":"Agpro Inc",
    "wof:placetype":"venue"
},
  "geometry": {"coordinates":[-84.353611,40.117563],"type":"Point"}
}