{
  "type": "Feature",
  "properties": {
    "iso:country":"US",
    "sg:address":"11234 Hackett Rd",
    "sg:city":"Apple Creek",
    "sg:classifiers":[
        {
            "category":"Autos & Motor Vehicles",
            "subcategory":"Automobile Sales",
            "type":"Retail Goods"
        }
    ],
    "sg:phone":"+1 330 698 0280",
    "sg:postcode":"44606",
    "sg:province":"OH",
    "sg:tags":[
        "equipment",
        "aircraft",
        "parts",
        "supply"
    ],
    "sg:website":"www.preferredairparts.com",
    "wof:name":"Preferred Airparts",
    "wof:placetype":"venue"
},
  "geometry": {"coordinates":[-81.779245,40.755925],"type":"Point"}
}