{
  "type": "Feature",
  "properties": {
    "iso:country":"US",
    "sg:address":"219 N River Rd NW",
    "sg:city":"Warren",
    "sg:classifiers":[
        {
            "category":"Wholesale",
            "subcategory":"Machinery & Supplies",
            "type":"Manufacturing & Wholesale Goods"
        }
    ],
    "sg:phone":"+1 330 372 5427",
    "sg:postcode":"44483",
    "sg:province":"OH",
    "sg:tags":[
        "equipment",
        "industrial"
    ],
    "wof:name":"Gas Radiant Systems Inc",
    "wof:placetype":"venue"
},
  "geometry": {"coordinates":[-80.815763,41.265454],"type":"Point"}
}