{
  "type": "Feature",
  "properties": {
    "addr:full": "219 N River Rd NW Warren OH 44483",
    "addr:housenumber": "219",
    "addr:postcode": "44483",
    "addr:street": "N River Rd Nw",
    "iso:country": "US",
    "sg:address": "219 N River Rd NW",
    "sg:city": "Warren",
    "sg:classifiers": [
      {
        "category": "Wholesale",
        "subcategory": "Machinery \u0026 Supplies",
        "type": "Manufacturing \u0026 Wholesale Goods"
      }
    ],
    "sg:phone": "+1 330 372 5427",
    "sg:postcode": "44483",
    "sg:province": "OH",
    "sg:tags": [
      "equipment",
      "industrial"
    ],
    "wof:name": "Gas Radiant Systems Inc",
    "wof:placetype": "venue"
  },
  "geometry": {"coordinates":[-80.815763,41.265454],"type":"Point"}
}
