{
  "type": "Feature",
  "properties": {
    "addr:full": "3811 Venice Rd Sandusky OH 44870",
    "addr:housenumber": "3811",
    "addr:postcode": "44870",
    "addr:street": "Venice Rd",
    "iso:country": "US",
    "sg:address": "3811 Venice Rd",
    "sg:city": "Sandusky",
    "sg:classifiers": [
      {
        "category": "Building \u0026 Trades",
        "subcategory": "Landscaping Services",
        "type": "Services"
      }
    ],
    "sg:phone": "+1 419 625 2352",
    "sg:postcode": "44870",
    "sg:province": "OH",
    "sg:tags": [
      "tree",
      "landscape",
      "contractor"
    ],
    "wof:name": "Baileys Tree \u0026 Landscaping Svc",
    "wof:placetype": "venue"
  },
  "geometry": {"coordinates":[-82.751656,41.441568],"type":"Point"}
}
