{
  "type": "Feature",
  "properties": {
    "addr:full":"35860 Detroit Rd Avon OH 44011",
    "addr:housenumber":"35860",
    "addr:postcode":"44011",
    "addr:street":"Detroit Rd",
    "iso:country":"US",
    "sg:address":"35860 Detroit Rd",
    "sg:city":"Avon",
    "sg:classifiers":[
        {
            "category":"Restaurant",
            "type":"Food & Drink"
        }
    ],
    "sg:phone":"+1 440 937 4646",
    "sg:postcode":"44011",
    "sg:province":"OH",
    "wof:name":"Panera Bread",
    "wof:placetype":"venue"
},
  "geometry": {"coordinates":[-82.013245,41.457574],"type":"Point"}
}