{
  "type": "Feature",
  "properties": {
    "addr:full":"390 Seneca Ct Avon Lake OH 44012",
    "addr:housenumber":"390",
    "addr:postcode":"44012",
    "addr:street":"Seneca Ct",
    "iso:country":"US",
    "sg:address":"390 Seneca Ct",
    "sg:city":"Avon Lake",
    "sg:classifiers":[
        {
            "category":"Shopping",
            "subcategory":"Clothing, Apparel, & Fashions",
            "type":"Retail Goods"
        }
    ],
    "sg:phone":"+1 440 930 5473",
    "sg:postcode":"44012",
    "sg:province":"OH",
    "sg:tags":[
        "accessory"
    ],
    "wof:name":"IWC Accessories",
    "wof:placetype":"venue"
},
  "geometry": {"coordinates":[-81.98988799999999,41.495735],"type":"Point"}
}