{
  "type": "Feature",
  "properties": {
    "addr:full":"10102 Lorain Ave Cleveland OH 44111",
    "addr:housenumber":"10102",
    "addr:postcode":"44111",
    "addr:street":"Lorain Ave",
    "iso:country":"US",
    "sg:address":"10102 Lorain Ave",
    "sg:city":"Cleveland",
    "sg:classifiers":[
        {
            "category":"Shopping",
            "subcategory":"Used Merchandise",
            "type":"Retail Goods"
        }
    ],
    "sg:phone":"+1 216 334 1860",
    "sg:postcode":"44111",
    "sg:province":"OH",
    "sg:tags":[
        "shop",
        "consignment"
    ],
    "wof:name":"Old Firehouse",
    "wof:placetype":"venue"
},
  "geometry": {"coordinates":[-81.754893,41.466568],"type":"Point"}
}