{
  "type": "Feature",
  "properties": {
    "iso:country":"US",
    "sg:address":"7537 Mentor Ave",
    "sg:city":"Mentor",
    "sg:classifiers":[
        {
            "category":"Wholesale",
            "subcategory":"Computers",
            "type":"Manufacturing & Wholesale Goods"
        },
        {
            "category":"Shopping",
            "subcategory":"Computers & Home Electronics",
            "type":"Retail Goods"
        }
    ],
    "sg:phone":"+1 440 975 0686",
    "sg:postcode":"44060",
    "sg:province":"OH",
    "sg:tags":[
        "software"
    ],
    "wof:name":"E-Power Solutions Inc",
    "wof:placetype":"venue"
},
  "geometry": {"coordinates":[-81.37150699999999,41.656443],"type":"Point"}
}