{
  "type": "Feature",
  "properties": {
    "addr:full": "1514 16th St West Portsmouth OH 45663",
    "addr:housenumber": "1514",
    "addr:postcode": "45663",
    "addr:street": "16Th St",
    "iso:country": "US",
    "sg:address": "1514 16th St",
    "sg:city": "West Portsmouth",
    "sg:classifiers": [
      {
        "category": "Social Services",
        "type": "Services"
      }
    ],
    "sg:phone": "+1 740 858 3663",
    "sg:postcode": "45663",
    "sg:province": "OH",
    "sg:tags": [
      "organization",
      "welfare"
    ],
    "wof:name": "Mt Zion Food Pantry",
    "wof:placetype": "venue"
  },
  "geometry": {"coordinates":[-83.038539,38.76377],"type":"Point"}
}
