{
  "type": "Feature",
  "properties": {
    "addr:full": "2039 E Western Reserve Rd Youngstown OH 44514",
    "addr:housenumber": "2039",
    "addr:postcode": "44514",
    "addr:street": "E Western Reserve Rd",
    "iso:country": "US",
    "sg:address": "2039 E Western Reserve Rd",
    "sg:city": "Youngstown",
    "sg:classifiers": [
      {
        "category": "Building \u0026 Trades",
        "subcategory": "Cleaning \u0026 Sanitation",
        "type": "Services"
      }
    ],
    "sg:phone": "+1 330 779 3474",
    "sg:postcode": "44514",
    "sg:province": "OH",
    "sg:tags": [
      "window"
    ],
    "wof:name": "Fish Window Cleaning",
    "wof:placetype": "venue"
  },
  "geometry": {"coordinates":[-80.611419,40.987813],"type":"Point"}
}
