{
  "type": "Feature",
  "properties": {
    "iso:country":"US",
    "sg:address":"2039 E Western Reserve Rd",
    "sg:city":"Youngstown",
    "sg:classifiers":[
        {
            "category":"Building & Trades",
            "subcategory":"Cleaning & Sanitation",
            "type":"Services"
        }
    ],
    "sg:phone":"+1 330 779 3474",
    "sg:postcode":"44514",
    "sg:province":"OH",
    "sg:tags":[
        "window"
    ],
    "wof:name":"Fish Window Cleaning",
    "wof:placetype":"venue"
},
  "geometry": {"coordinates":[-80.611419,40.987813],"type":"Point"}
}