{
  "type": "Feature",
  "properties": {
    "addr:full": "445 Hutchinson Ave Columbus OH 43235",
    "addr:housenumber": "445",
    "addr:postcode": "43235",
    "addr:street": "Hutchinson Ave",
    "iso:country": "US",
    "sg:address": "445 Hutchinson Ave",
    "sg:city": "Columbus",
    "sg:classifiers": [
      {
        "category": "Food \u0026 Beverages",
        "subcategory": "Groceries \u0026 Convenience Stores",
        "type": "Retail Goods"
      }
    ],
    "sg:phone": "+1 614 785 6486",
    "sg:postcode": "43235",
    "sg:province": "OH",
    "sg:tags": [
      "market"
    ],
    "wof:name": "Open Market Inc",
    "wof:placetype": "venue"
  },
  "geometry": {"coordinates":[-83.011924,40.113883],"type":"Point"}
}
