{
  "type": "Feature",
  "properties": {
    "addr:full":"1730 Mears Ave Cincinnati OH 45230",
    "addr:housenumber":"1730",
    "addr:postcode":"45230",
    "addr:street":"Mears Ave",
    "iso:country":"US",
    "sg:address":"1730 Mears Ave",
    "sg:city":"Cincinnati",
    "sg:classifiers":[
        {
            "category":"Education",
            "subcategory":"School",
            "type":"Public Place"
        }
    ],
    "sg:phone":"+1 513 533 6340",
    "sg:postcode":"45230",
    "sg:province":"OH",
    "wof:name":"Cincinnati Public Sch Mt",
    "wof:placetype":"venue"
},
  "geometry": {"coordinates":[-84.38638899999999,39.086403],"type":"Point"}
}