{
  "type": "Feature",
  "properties": {
    "iso:country":"US",
    "sg:address":"50 W Broad St",
    "sg:city":"Columbus",
    "sg:classifiers":[
        {
            "category":"Professional",
            "subcategory":"Management & Consulting",
            "type":"Services"
        }
    ],
    "sg:phone":"+1 614 461 4014",
    "sg:postcode":"43215",
    "sg:province":"OH",
    "sg:tags":[
        "political",
        "lobbyist"
    ],
    "wof:name":"Ohio Cable Telecom Assn",
    "wof:placetype":"venue"
},
  "geometry": {"coordinates":[-83.001973,39.962163],"type":"Point"}
}