{
  "type": "Feature",
  "properties": {
    "addr:full": "34305 Solon Rd Ste 60 Solon OH 44139",
    "addr:postcode": "34305;44139",
    "addr:street": "Solon Rd Ste 60",
    "iso:country": "US",
    "sg:address": "34305 Solon Rd Ste 60",
    "sg:city": "Solon",
    "sg:classifiers": [
      {
        "category": "Education",
        "subcategory": "Special Training",
        "type": "Public Place"
      }
    ],
    "sg:phone": "+1 440 349 4153",
    "sg:postcode": "44139",
    "sg:province": "OH",
    "sg:tags": [
      "tutoring"
    ],
    "sg:website": "tutoring.sylvanlearning.com",
    "wof:name": "Sylvan Learning Center",
    "wof:placetype": "venue"
  },
  "geometry": {"coordinates":[-81.434303,41.394199],"type":"Point"}
}
