{
  "type": "Feature",
  "properties": {
    "addr:full":"5587 Greenfield Dr Galena OH 43021",
    "addr:housenumber":"5587",
    "addr:postcode":"43021",
    "addr:street":"Greenfield Dr",
    "iso:country":"US",
    "sg:address":"5587 Greenfield Dr",
    "sg:city":"Galena",
    "sg:classifiers":[
        {
            "category":"Professional",
            "type":"Services"
        }
    ],
    "sg:phone":"+1 740 549 1438",
    "sg:postcode":"43021",
    "sg:province":"OH",
    "wof:name":"Motter Jannel or Chris",
    "wof:placetype":"venue"
},
  "geometry": {"coordinates":[-82.956192,40.236346],"type":"Point"}
}