{
  "type": "Feature",
  "properties": {
    "addr:full": "230 Twp Hwy 300 Waverly OH 45694",
    "addr:housenumber": "230",
    "addr:postcode": "45694",
    "addr:street": "Twp Hwy 300",
    "iso:country": "US",
    "sg:address": "230 Twp Hwy 300",
    "sg:city": "Waverly",
    "sg:classifiers": [
      {
        "category": "Government",
        "subcategory": "Office",
        "type": "Public Place"
      }
    ],
    "sg:phone": "+1 740 947 2472",
    "sg:postcode": "45694",
    "sg:province": "OH",
    "sg:tags": [
      "policy"
    ],
    "wof:name": "Pike County Treasurer's Office",
    "wof:placetype": "venue"
  },
  "geometry": {"coordinates":[-82.797057,38.757394],"type":"Point"}
}
