{
  "type": "Feature",
  "properties": {
    "addr:full": "30 S Limestone St Jamestown OH 45335",
    "addr:housenumber": "30",
    "addr:postcode": "45335",
    "addr:street": "S Limestone St",
    "iso:country": "US",
    "sg:address": "30 S Limestone St",
    "sg:city": "Jamestown",
    "sg:classifiers": [
      {
        "category": "Freight",
        "type": "Transportation"
      }
    ],
    "sg:phone": "+1 937 675 7051",
    "sg:postcode": "45335",
    "sg:province": "OH",
    "sg:tags": [
      "trucking"
    ],
    "wof:name": "Fanning Trucking",
    "wof:placetype": "venue"
  },
  "geometry": {"coordinates":[-83.734958,39.656818],"type":"Point"}
}
