{
  "type": "Feature",
  "properties": {
    "iso:country":"US",
    "sg:address":"30 S Limestone St",
    "sg:city":"Jamestown",
    "sg:classifiers":[
        {
            "category":"Freight",
            "type":"Transportation"
        }
    ],
    "sg:phone":"+1 937 675 7051",
    "sg:postcode":"45335",
    "sg:province":"OH",
    "sg:tags":[
        "trucking"
    ],
    "wof:name":"Fanning Trucking",
    "wof:placetype":"venue"
},
  "geometry": {"coordinates":[-83.73495800000001,39.656818],"type":"Point"}
}