{
  "type": "Feature",
  "properties": {
    "iso:country":"US",
    "sg:address":"601 Massillon Rd",
    "sg:city":"Akron",
    "sg:classifiers":[
        {
            "category":"Organizations",
            "subcategory":"Community Association",
            "type":"Services"
        }
    ],
    "sg:phone":"+1 330 784 1026",
    "sg:postcode":"44306",
    "sg:province":"OH",
    "wof:name":"Army & Navy Union Garrison",
    "wof:placetype":"venue"
},
  "geometry": {"coordinates":[-81.46298899999999,41.043402],"type":"Point"}
}