{
  "type": "Feature",
  "properties": {
    "addr:full": "601 Massillon Rd Akron OH 44306",
    "addr:housenumber": "601",
    "addr:postcode": "44306",
    "addr:street": "Massillon Rd",
    "iso:country": "US",
    "sg:address": "601 Massillon Rd",
    "sg:city": "Akron",
    "sg:classifiers": [
      {
        "category": "Organizations",
        "subcategory": "Community Association",
        "type": "Services"
      }
    ],
    "sg:phone": "+1 330 784 1026",
    "sg:postcode": "44306",
    "sg:province": "OH",
    "wof:name": "Army \u0026 Navy Union Garrison",
    "wof:placetype": "venue"
  },
  "geometry": {"coordinates":[-81.462989,41.043402],"type":"Point"}
}
