{
  "type": "Feature",
  "properties": {
    "addr:full": "235 Marion Ave Mansfield OH 44903",
    "addr:housenumber": "235",
    "addr:postcode": "44903",
    "addr:street": "Marion Ave",
    "iso:country": "US",
    "sg:address": "235 Marion Ave",
    "sg:city": "Mansfield",
    "sg:classifiers": [
      {
        "category": "Shopping",
        "subcategory": "Florist",
        "type": "Retail Goods"
      }
    ],
    "sg:phone": "+1 419 522 7673",
    "sg:postcode": "44903",
    "sg:province": "OH",
    "wof:name": "Antique Rose Florist",
    "wof:placetype": "venue"
  },
  "geometry": {"coordinates":[-82.530572,40.756547],"type":"Point"}
}
