{
  "type": "Feature",
  "properties": {
    "addr:full":"217 S Hempstead Rd Westerville OH 43081",
    "addr:housenumber":"217",
    "addr:postcode":"43081",
    "addr:street":"S Hempstead Rd",
    "iso:country":"US",
    "sg:address":"217 S Hempstead Rd",
    "sg:city":"Westerville",
    "sg:classifiers":[
        {
            "category":"Shopping",
            "subcategory":"Crafts & Fabrics",
            "type":"Retail Goods"
        }
    ],
    "sg:phone":"+1 614 882 7013",
    "sg:postcode":"43081",
    "sg:province":"OH",
    "sg:tags":[
        "sewing"
    ],
    "wof:name":"Betty J Simms Sewing",
    "wof:placetype":"venue"
},
  "geometry": {"coordinates":[-82.893574,40.118613],"type":"Point"}
}