{
  "type": "Feature",
  "properties": {
    "addr:full":"19 S Franklin St Delaware OH 43015",
    "addr:housenumber":"19",
    "addr:postcode":"43015",
    "addr:street":"S Franklin St",
    "iso:country":"US",
    "sg:address":"19 S Franklin St",
    "sg:city":"Delaware",
    "sg:classifiers":[
        {
            "category":"Professional",
            "type":"Services"
        },
        {
            "category":"Restaurant",
            "type":"Food & Drink"
        }
    ],
    "sg:phone":"+1 740 363 6554",
    "sg:postcode":"43015",
    "sg:province":"OH",
    "sg:tags":[
        "caterer"
    ],
    "wof:name":"Ollie's Fine Ice Cream",
    "wof:placetype":"venue"
},
  "geometry": {"coordinates":[-83.069542,40.298472],"type":"Point"}
}