{
  "type": "Feature",
  "properties": {
    "addr:full": "950 Windham Ct Youngstown OH 44512",
    "addr:housenumber": "950",
    "addr:postcode": "44512",
    "addr:street": "Windham Ct",
    "iso:country": "US",
    "sg:address": "950 Windham Ct",
    "sg:city": "Youngstown",
    "sg:classifiers": [
      {
        "category": "Professional",
        "type": "Services"
      }
    ],
    "sg:phone": "+1 330 629 2761",
    "sg:postcode": "44512",
    "sg:province": "OH",
    "sg:tags": [
      "establishment"
    ],
    "wof:name": "WFG Dan Bradaick",
    "wof:placetype": "venue"
  },
  "geometry": {"coordinates":[-80.636285,41.028514],"type":"Point"}
}
