{
  "type": "Feature",
  "properties": {
    "addr:full": "1351 E 351st St Willoughby OH 44095",
    "addr:housenumber": "1351",
    "addr:postcode": "44095",
    "addr:street": "E 351St St",
    "iso:country": "US",
    "sg:address": "1351 E 351st St",
    "sg:city": "Willoughby",
    "sg:classifiers": [
      {
        "category": "Professional",
        "subcategory": "Accounting \u0026 Tax Preparation",
        "type": "Services"
      }
    ],
    "sg:phone": "+1 440 953 5835",
    "sg:postcode": "44095",
    "sg:province": "OH",
    "sg:tags": [
      "consultant"
    ],
    "wof:name": "Pyramid Accounting Partners",
    "wof:placetype": "venue"
  },
  "geometry": {"coordinates":[-81.438471,41.646101],"type":"Point"}
}
