{
  "type": "Feature",
  "properties": {
    "iso:country":"US",
    "sg:address":"137 Noran Cir",
    "sg:city":"Cleveland",
    "sg:classifiers":[
        {
            "category":"Communications",
            "subcategory":"Film & Video Production",
            "type":"Services"
        }
    ],
    "sg:phone":"+1 440 786 9398",
    "sg:postcode":"44146",
    "sg:province":"OH",
    "sg:tags":[
        "taping"
    ],
    "wof:name":"We'Re Forever Yours Video",
    "wof:placetype":"venue"
},
  "geometry": {"coordinates":[-81.54101199999999,41.403931],"type":"Point"}
}