{
  "type": "Feature",
  "properties": {
    "addr:full": "7850 Mentor Ave Mentor OH 44060",
    "addr:housenumber": "7850",
    "addr:postcode": "44060",
    "addr:street": "Mentor Ave",
    "iso:country": "US",
    "sg:address": "7850 Mentor Ave",
    "sg:city": "Mentor",
    "sg:classifiers": [
      {
        "category": "Wholesale",
        "subcategory": "Groceries",
        "type": "Manufacturing \u0026 Wholesale Goods"
      }
    ],
    "sg:phone": "+1 440 205 0989",
    "sg:postcode": "44060",
    "sg:province": "OH",
    "sg:tags": [
      "pretzel"
    ],
    "wof:name": "Auntie Anne's Hand Rolled Soft",
    "wof:placetype": "venue"
  },
  "geometry": {"coordinates":[-81.362095,41.660627],"type":"Point"}
}
