{
  "type": "Feature",
  "properties": {
    "addr:full": "385 Woodside Northfield OH 44067",
    "addr:housenumber": "385",
    "addr:postcode": "44067",
    "addr:street": "Woodside",
    "iso:country": "US",
    "sg:address": "385 Woodside",
    "sg:city": "Northfield",
    "sg:classifiers": [
      {
        "category": "Professional",
        "type": "Services"
      }
    ],
    "sg:phone": "+1 330 468 0825",
    "sg:postcode": "44067",
    "sg:province": "OH",
    "wof:name": "Ancon Ind Inc",
    "wof:placetype": "venue"
  },
  "geometry": {"coordinates":[-81.546644,41.337238],"type":"Point"}
}
