{
  "type": "Feature",
  "properties": {
    "addr:full":"1501 Commerce Dr Stow OH 44224",
    "addr:housenumber":"1501",
    "addr:postcode":"44224",
    "addr:street":"Commerce Dr",
    "iso:country":"US",
    "sg:address":"1501 Commerce Dr",
    "sg:city":"Stow",
    "sg:classifiers":[
        {
            "category":"Professional",
            "type":"Services"
        }
    ],
    "sg:phone":"+1 330 761 4350",
    "sg:postcode":"44224",
    "sg:province":"OH",
    "wof:name":"Semc",
    "wof:placetype":"venue"
},
  "geometry": {"coordinates":[-81.460386,41.192231],"type":"Point"}
}