{
  "type": "Feature",
  "properties": {
    "addr:full": "711 Forest Hills Rd Newark OH 43056",
    "addr:housenumber": "711",
    "addr:postcode": "43056",
    "addr:street": "Forest Hills Rd",
    "iso:country": "US",
    "sg:address": "711 Forest Hills Rd",
    "sg:city": "Newark",
    "sg:classifiers": [
      {
        "category": "Building \u0026 Trades",
        "subcategory": "Construction",
        "type": "Services"
      }
    ],
    "sg:phone": "+1 740 323 2127",
    "sg:postcode": "43056",
    "sg:province": "OH",
    "sg:tags": [
      "home",
      "builder",
      "contract",
      "family"
    ],
    "wof:name": "Mark Builders Inc",
    "wof:placetype": "venue"
  },
  "geometry": {"coordinates":[-82.380186,40.030432],"type":"Point"}
}
