{
  "type": "Feature",
  "properties": {
    "iso:country":"US",
    "sg:address":"711 Forest Hills Rd",
    "sg:city":"Newark",
    "sg:classifiers":[
        {
            "category":"Building & Trades",
            "subcategory":"Construction",
            "type":"Services"
        }
    ],
    "sg:phone":"+1 740 323 2127",
    "sg:postcode":"43056",
    "sg:province":"OH",
    "sg:tags":[
        "home",
        "builder",
        "contract",
        "family"
    ],
    "wof:name":"Mark Builders Inc",
    "wof:placetype":"venue"
},
  "geometry": {"coordinates":[-82.38018599999999,40.030432],"type":"Point"}
}