{
  "type": "Feature",
  "properties": {
    "addr:full": "3070 Mayfield Rd Cleveland OH 44118",
    "addr:housenumber": "3070",
    "addr:postcode": "44118",
    "addr:street": "Mayfield Rd",
    "iso:country": "US",
    "sg:address": "3070 Mayfield Rd",
    "sg:city": "Cleveland",
    "sg:classifiers": [
      {
        "category": "Personal",
        "subcategory": "Beauty Salon",
        "type": "Services"
      }
    ],
    "sg:phone": "+1 216 932 4440",
    "sg:postcode": "44118",
    "sg:province": "OH",
    "wof:name": "Salon 201",
    "wof:placetype": "venue"
  },
  "geometry": {"coordinates":[-81.569615,41.515479],"type":"Point"}
}
