{
  "type": "Feature",
  "properties": {
    "addr:full":"23 Chicago Ave Columbus OH 43222",
    "addr:housenumber":"23",
    "addr:postcode":"43222",
    "addr:street":"Chicago Ave",
    "iso:country":"US",
    "sg:address":"23 Chicago Ave",
    "sg:city":"Columbus",
    "sg:classifiers":[
        {
            "category":"Organizations",
            "subcategory":"Religious Organization",
            "type":"Services"
        }
    ],
    "sg:phone":"+1 614 351 3076",
    "sg:postcode":"43222",
    "sg:province":"OH",
    "sg:tags":[
        "clergy"
    ],
    "wof:name":"Robert S Cowden",
    "wof:placetype":"venue"
},
  "geometry": {"coordinates":[-83.03461799999999,39.959839],"type":"Point"}
}