{
  "type": "Feature",
  "properties": {
    "iso:country":"US",
    "sg:address":"5267 N Detroit Ave",
    "sg:city":"Toledo",
    "sg:classifiers":[
        {
            "category":"Organizations",
            "subcategory":"Community Association",
            "type":"Services"
        }
    ],
    "sg:phone":"+1 419 470 9724",
    "sg:postcode":"43612",
    "sg:province":"OH",
    "sg:tags":[
        "military"
    ],
    "wof:name":"American Legion",
    "wof:placetype":"venue"
},
  "geometry": {"coordinates":[-83.541927,41.711504],"type":"Point"}
}