{
  "type": "Feature",
  "properties": {
    "iso:country":"US",
    "sg:address":"1275 Smith Ave SW",
    "sg:city":"Canton",
    "sg:classifiers":[
        {
            "category":"Personal",
            "type":"Services"
        }
    ],
    "sg:phone":"+1 330 866 5194",
    "sg:postcode":"44706",
    "sg:province":"OH",
    "sg:tags":[
        "consultant",
        "wedding"
    ],
    "wof:name":"Weddings By Aimee & Kaylene",
    "wof:placetype":"venue"
},
  "geometry": {"coordinates":[-81.400111,40.788391],"type":"Point"}
}