{
  "type": "Feature",
  "properties": {
    "addr:full": "540 Moody St Akron OH 44305",
    "addr:housenumber": "540",
    "addr:postcode": "44305",
    "addr:street": "Moody St",
    "iso:country": "US",
    "sg:address": "540 Moody St",
    "sg:city": "Akron",
    "sg:classifiers": [
      {
        "category": "Professional",
        "subcategory": "Business Services",
        "type": "Services"
      }
    ],
    "sg:phone": "+1 330 784 9943",
    "sg:postcode": "44305",
    "sg:province": "OH",
    "wof:name": "Refrigration Svc Engineers Soc",
    "wof:placetype": "venue"
  },
  "geometry": {"coordinates":[-81.435112,41.078334],"type":"Point"}
}
