{
  "type": "Feature",
  "properties": {
    "iso:country":"US",
    "sg:address":"4387 School Section Rd",
    "sg:city":"Cincinnati",
    "sg:classifiers":[
        {
            "category":"Food & Beverages",
            "subcategory":"Specialty",
            "type":"Retail Goods"
        }
    ],
    "sg:phone":"+1 513 574 0447",
    "sg:postcode":"45211",
    "sg:province":"OH",
    "wof:name":"T Daniel Ntrtional Supplements",
    "wof:placetype":"venue"
},
  "geometry": {"coordinates":[-84.620167,39.170037],"type":"Point"}
}