{
  "type": "Feature",
  "properties": {
    "addr:full": "7171 Greenville Falls-Clayton Rd Bradford OH 45308",
    "addr:housenumber": "7171",
    "addr:postcode": "45308",
    "addr:street": "Greenville Falls-Clayton Rd",
    "iso:country": "US",
    "sg:address": "7171 Greenville Falls-Clayton Rd",
    "sg:city": "Bradford",
    "sg:phone": "+1 937 448 2580",
    "sg:postcode": "45308",
    "sg:province": "OH",
    "sg:tags": [
      "farm",
      "soybean"
    ],
    "wof:name": "Jack Miller",
    "wof:placetype": "venue"
  },
  "geometry": {"coordinates":[-84.393211,40.139134],"type":"Point"}
}
