{
  "type": "Feature",
  "properties": {
    "iso:country":"US",
    "sg:address":"1582 Evansport Rd",
    "sg:city":"Defiance",
    "sg:classifiers":[
        {
            "category":"Restaurant",
            "type":"Food & Drink"
        }
    ],
    "sg:phone":"+1 419 428 4100",
    "sg:postcode":"43512",
    "sg:province":"OH",
    "sg:tags":[
        "eating"
    ],
    "wof:name":"Evansport Carryout",
    "wof:placetype":"venue"
},
  "geometry": {"coordinates":[-84.396248,41.416564],"type":"Point"}
}