{
  "type": "Feature",
  "properties": {
    "addr:full": "1582 Evansport Rd Defiance OH 43512",
    "addr:housenumber": "1582",
    "addr:postcode": "43512",
    "addr:street": "Evansport Rd",
    "iso:country": "US",
    "sg:address": "1582 Evansport Rd",
    "sg:city": "Defiance",
    "sg:classifiers": [
      {
        "category": "Restaurant",
        "type": "Food \u0026 Drink"
      }
    ],
    "sg:phone": "+1 419 428 4100",
    "sg:postcode": "43512",
    "sg:province": "OH",
    "sg:tags": [
      "eating"
    ],
    "wof:name": "Evansport Carryout",
    "wof:placetype": "venue"
  },
  "geometry": {"coordinates":[-84.396248,41.416564],"type":"Point"}
}
