{
  "type": "Feature",
  "properties": {
    "iso:country":"US",
    "sg:address":"4962 State Rte 93",
    "sg:city":"Ironton",
    "sg:classifiers":[
        {
            "category":"Manufacturing",
            "subcategory":"Glass & Minerals",
            "type":"Manufacturing & Wholesale Goods"
        }
    ],
    "sg:phone":"+1 740 532 2089",
    "sg:postcode":"45638",
    "sg:province":"OH",
    "sg:tags":[
        "concrete",
        "brick",
        "prod",
        "block"
    ],
    "wof:name":"Miller-Smith Concrete Products",
    "wof:placetype":"venue"
},
  "geometry": {"coordinates":[-82.638881,38.58643],"type":"Point"}
}