{
  "type": "Feature",
  "properties": {
    "addr:full":"250 Crestview Rd Columbus OH 43202",
    "addr:housenumber":"250",
    "addr:postcode":"43202",
    "addr:street":"Crestview Rd",
    "iso:country":"US",
    "sg:address":"250 Crestview Rd",
    "sg:city":"Columbus",
    "sg:classifiers":[
        {
            "category":"Retail",
            "subcategory":"Animal Services",
            "type":"Services"
        }
    ],
    "sg:phone":"+1 614 262 8333",
    "sg:postcode":"43202",
    "sg:province":"OH",
    "sg:tags":[
        "pet",
        "boarding",
        "sitting"
    ],
    "wof:name":"Toni Sits Pets",
    "wof:placetype":"venue"
},
  "geometry": {"coordinates":[-83.007133,40.02232],"type":"Point"}
}