{
  "type": "Feature",
  "properties": {
    "addr:full":"6909 N State Rte 66 Defiance OH 43512",
    "addr:housenumber":"6909",
    "addr:postcode":"43512",
    "addr:street":"N State Rte 66",
    "iso:country":"US",
    "sg:address":"6909 N State Rte 66",
    "sg:city":"Defiance",
    "sg:classifiers":[
        {
            "category":"Real Estate",
            "subcategory":"Real Estate Operator",
            "type":"Services"
        }
    ],
    "sg:phone":"+1 419 784 5179",
    "sg:postcode":"43512",
    "sg:province":"OH",
    "sg:tags":[
        "mobile",
        "home",
        "community"
    ],
    "wof:name":"Green Acres Mobile Home Court",
    "wof:placetype":"venue"
},
  "geometry": {"coordinates":[-84.36077,41.342282],"type":"Point"}
}