{
  "type": "Feature",
  "properties": {
    "addr:full": "34 E National Rd Vandalia OH 45377",
    "addr:housenumber": "34",
    "addr:postcode": "45377",
    "addr:street": "E National Rd",
    "iso:country": "US",
    "sg:address": "34 E National Rd",
    "sg:city": "Vandalia",
    "sg:classifiers": [
      {
        "category": "Professional",
        "subcategory": "Engineering",
        "type": "Services"
      }
    ],
    "sg:phone": "+1 937 898 5862",
    "sg:postcode": "45377",
    "sg:province": "OH",
    "sg:tags": [
      "surveying",
      "engineer"
    ],
    "wof:name": "Thomas Winemiller \u0026 Associates",
    "wof:placetype": "venue"
  },
  "geometry": {"coordinates":[-84.197649,39.890814],"type":"Point"}
}
