{
  "type": "Feature",
  "properties": {
    "addr:full":"515 S State St Westerville OH 43081",
    "addr:housenumber":"515",
    "addr:postcode":"43081",
    "addr:street":"S State St",
    "iso:country":"US",
    "sg:address":"515 S State St",
    "sg:city":"Westerville",
    "sg:classifiers":[
        {
            "category":"Professional",
            "type":"Services"
        }
    ],
    "sg:phone":"+1 614 899 0076",
    "sg:postcode":"43081",
    "sg:province":"OH",
    "sg:tags":[
        "establishment"
    ],
    "wof:name":"Westerville Med-Ohio",
    "wof:placetype":"venue"
},
  "geometry": {"coordinates":[-82.927423,40.114456],"type":"Point"}
}