{
  "type": "Feature",
  "properties": {
    "addr:full": "144 S 30th St Newark OH 43055",
    "addr:housenumber": "144",
    "addr:postcode": "43055",
    "addr:street": "S 30Th St",
    "iso:country": "US",
    "sg:address": "144 S 30th St",
    "sg:city": "Newark",
    "sg:classifiers": [
      {
        "category": "Wholesale",
        "subcategory": "Medical Equipment \u0026 Supplies",
        "type": "Manufacturing \u0026 Wholesale Goods"
      },
      {
        "category": "Shopping",
        "type": "Retail Goods"
      }
    ],
    "sg:phone": "+1 740 344 4925",
    "sg:postcode": "43055",
    "sg:province": "OH",
    "sg:tags": [
      "orthopedic",
      "appliance"
    ],
    "wof:name": "Custom Care Orthotics Inc",
    "wof:placetype": "venue"
  },
  "geometry": {"coordinates":[-82.441871,40.045618],"type":"Point"}
}
