{
  "type": "Feature",
  "properties": {
    "addr:full":"1454 Eastwood Ave Columbus OH 43203",
    "addr:housenumber":"1454",
    "addr:postcode":"43203",
    "addr:street":"Eastwood Ave",
    "iso:country":"US",
    "sg:address":"1454 Eastwood Ave",
    "sg:city":"Columbus",
    "sg:classifiers":[
        {
            "category":"Professional",
            "subcategory":"Business Services",
            "type":"Services"
        }
    ],
    "sg:phone":"+1 614 885 3694",
    "sg:postcode":"43203",
    "sg:province":"OH",
    "wof:name":"Flosmo Productions Inc",
    "wof:placetype":"venue"
},
  "geometry": {"coordinates":[-82.962594,39.967883],"type":"Point"}
}