{
  "type": "Feature",
  "properties": {
    "addr:full": "4450 Eastgate Blvd Cincinnati OH 45245",
    "addr:housenumber": "4450",
    "addr:postcode": "45245",
    "addr:street": "Eastgate Blvd",
    "iso:country": "US",
    "sg:address": "4450 Eastgate Blvd",
    "sg:city": "Cincinnati",
    "sg:classifiers": [
      {
        "category": "Real Estate",
        "subcategory": "Real Estate Agent",
        "type": "Services"
      }
    ],
    "sg:phone": "+1 513 753 7222",
    "sg:postcode": "45245",
    "sg:province": "OH",
    "wof:name": "Amerishop Real Estate Svcs LP",
    "wof:placetype": "venue"
  },
  "geometry": {"coordinates":[-84.274509,39.098168],"type":"Point"}
}
