{
  "type": "Feature",
  "properties": {
    "addr:full":"5140 E Harbor Rd Port Clinton OH 43452",
    "addr:housenumber":"5140 e",
    "addr:postcode":"43452",
    "addr:street":"Harbor Rd",
    "iso:country":"US",
    "sg:address":"5140 E Harbor Rd",
    "sg:city":"Port Clinton",
    "sg:classifiers":[
        {
            "category":"Recreation",
            "subcategory":"Marina",
            "type":"Entertainment"
        }
    ],
    "sg:phone":"+1 419 734 5408",
    "sg:postcode":"43452",
    "sg:province":"OH",
    "sg:tags":[
        "repairing",
        "boat"
    ],
    "wof:name":"Right Way Marine",
    "wof:placetype":"venue"
},
  "geometry": {"coordinates":[-82.833449,41.531466],"type":"Point"}
}