{
  "type": "Feature",
  "properties": {
    "iso:country":"US",
    "sg:address":"8225 E Washington St",
    "sg:city":"Chagrin Falls",
    "sg:classifiers":[
        {
            "category":"Sports & Exercise",
            "subcategory":"Playing Field",
            "type":"Entertainment"
        },
        {
            "category":"Arts & Performance",
            "subcategory":"Dance",
            "type":"Entertainment"
        }
    ],
    "sg:phone":"+1 440 543 1559",
    "sg:postcode":"44023",
    "sg:province":"OH",
    "sg:tags":[
        "school",
        "instruction",
        "fitness"
    ],
    "sg:website":"www.chagrinballroom.com",
    "wof:name":"Elegance in Ballroom",
    "wof:placetype":"venue"
},
  "geometry": {"coordinates":[-81.348248,41.41546],"type":"Point"}
}