{
  "type": "Feature",
  "properties": {
    "iso:country":"US",
    "sg:address":"5939 Broadway Ave",
    "sg:city":"Cleveland",
    "sg:classifiers":[
        {
            "category":"Shopping",
            "type":"Retail Goods"
        }
    ],
    "sg:phone":"+1 216 441 8590",
    "sg:postcode":"44127",
    "sg:province":"OH",
    "sg:tags":[
        "burial",
        "casket",
        "merchandise",
        "mfg"
    ],
    "wof:name":"Casket Store",
    "wof:placetype":"venue"
},
  "geometry": {"coordinates":[-81.648713,41.465038],"type":"Point"}
}