{
  "type": "Feature",
  "properties": {
    "iso:country":"US",
    "sg:address":"875 S Sandusky Ave",
    "sg:city":"Bucyrus",
    "sg:classifiers":[
        {
            "category":"Banks & Credit Unions",
            "subcategory":"Bank",
            "type":"Services"
        }
    ],
    "sg:phone":"+1 419 562 7167",
    "sg:postcode":"44820",
    "sg:province":"OH",
    "sg:website":"www.ffcb.com",
    "wof:name":"First Federal Community Bank",
    "wof:placetype":"venue"
},
  "geometry": {"coordinates":[-82.975543,40.799644],"type":"Point"}
}