{
  "type": "Feature",
  "properties": {
    "addr:full": "299 Vine Ave Sharon OH 16146",
    "addr:housenumber": "299",
    "addr:postcode": "16146",
    "addr:street": "Vine Ave",
    "iso:country": "US",
    "sg:address": "299 Vine Ave",
    "sg:city": "Sharon",
    "sg:classifiers": [
      {
        "category": "Recreation",
        "type": "Entertainment"
      }
    ],
    "sg:phone": "+1   ",
    "sg:postcode": "16146",
    "sg:province": "OH",
    "sg:tags": [
      "club",
      "membership"
    ],
    "wof:name": "Sons of Italy Shenango Valley",
    "wof:placetype": "venue"
  },
  "geometry": {"coordinates":[-80.507487,41.236008],"type":"Point"}
}
