{
  "type": "Feature",
  "properties": {
    "addr:full": "1567 Rombach Ave Wilmington OH 45177",
    "addr:housenumber": "1567",
    "addr:postcode": "45177",
    "addr:street": "Rombach Ave",
    "iso:country": "US",
    "sg:address": "1567 Rombach Ave",
    "sg:city": "Wilmington",
    "sg:classifiers": [
      {
        "category": "Retail",
        "subcategory": "Photofinishing",
        "type": "Services"
      }
    ],
    "sg:phone": "+1 937 382 6080",
    "sg:postcode": "45177",
    "sg:province": "OH",
    "sg:tags": [
      "photo",
      "finishing"
    ],
    "wof:name": "Fotos Etc",
    "wof:placetype": "venue"
  },
  "geometry": {"coordinates":[-83.801572,39.449605],"type":"Point"}
}
