{
  "type": "Feature",
  "properties": {
    "addr:full": "398 Damascus Rd Marysville OH 43040",
    "addr:housenumber": "398",
    "addr:postcode": "43040",
    "addr:street": "Damascus Rd",
    "iso:country": "US",
    "sg:address": "398 Damascus Rd",
    "sg:city": "Marysville",
    "sg:classifiers": [
      {
        "category": "Social Services",
        "subcategory": "Child Care",
        "type": "Services"
      }
    ],
    "sg:phone": "+1 937 642 4300",
    "sg:postcode": "43040",
    "sg:province": "OH",
    "sg:tags": [
      "day"
    ],
    "wof:name": "A Plus Child Care \u0026 Learning",
    "wof:placetype": "venue"
  },
  "geometry": {"coordinates":[-83.39124,40.235893],"type":"Point"}
}
