{
  "type": "Feature",
  "properties": {
    "addr:full": "11871 Akron Canfield Rd North Jackson OH 44451",
    "addr:housenumber": "11871",
    "addr:postcode": "44451",
    "addr:street": "Akron Canfield Rd",
    "iso:country": "US",
    "sg:address": "11871 Akron Canfield Rd",
    "sg:city": "North Jackson",
    "sg:classifiers": [
      {
        "category": "Retail",
        "subcategory": "Repair Shop",
        "type": "Services"
      },
      {
        "category": "Manufacturing",
        "subcategory": "Tools \u0026 Machinery",
        "type": "Manufacturing \u0026 Wholesale Goods"
      }
    ],
    "sg:phone": "+1 330 547 5155",
    "sg:postcode": "44451",
    "sg:province": "OH",
    "sg:tags": [
      "machine",
      "job",
      "welding"
    ],
    "wof:name": "E L Machine \u0026 Welding Co Inc",
    "wof:placetype": "venue"
  },
  "geometry": {"coordinates":[-80.876132,41.024242],"type":"Point"}
}
