{
  "type": "Feature",
  "properties": {
    "iso:country":"US",
    "sg:address":"11871 Akron Canfield Rd",
    "sg:city":"North Jackson",
    "sg:classifiers":[
        {
            "category":"Retail",
            "subcategory":"Repair Shop",
            "type":"Services"
        },
        {
            "category":"Manufacturing",
            "subcategory":"Tools & Machinery",
            "type":"Manufacturing & Wholesale Goods"
        }
    ],
    "sg:phone":"+1 330 547 5155",
    "sg:postcode":"44451",
    "sg:province":"OH",
    "sg:tags":[
        "machine",
        "job",
        "welding"
    ],
    "wof:name":"E L Machine & Welding Co Inc",
    "wof:placetype":"venue"
},
  "geometry": {"coordinates":[-80.876132,41.024242],"type":"Point"}
}