{
  "type": "Feature",
  "properties": {
    "addr:full":"458 Windsor Park Dr Dayton OH 45459",
    "addr:housenumber":"458",
    "addr:postcode":"45459",
    "addr:street":"Windsor Park Dr",
    "iso:country":"US",
    "sg:address":"458 Windsor Park Dr",
    "sg:city":"Dayton",
    "sg:classifiers":[
        {
            "category":"Manufacturing",
            "subcategory":"Printing",
            "type":"Manufacturing & Wholesale Goods"
        }
    ],
    "sg:phone":"+1 937 438 4981",
    "sg:postcode":"45459",
    "sg:province":"OH",
    "sg:tags":[
        "newspaper"
    ],
    "wof:name":"Dayton Newspapers Inc",
    "wof:placetype":"venue"
},
  "geometry": {"coordinates":[-84.175724,39.630478],"type":"Point"}
}