{
  "type": "Feature",
  "properties": {
    "addr:full": "17744 N Dixie Hwy Bowling Green OH 43402",
    "addr:housenumber": "17744",
    "addr:postcode": "43402",
    "addr:street": "N Dixie Hwy",
    "iso:country": "US",
    "sg:address": "17744 N Dixie Hwy",
    "sg:city": "Bowling Green",
    "sg:classifiers": [
      {
        "category": "Wholesale",
        "subcategory": "Wine \u0026 Distilled Alcoholic Beverages",
        "type": "Manufacturing \u0026 Wholesale Goods"
      }
    ],
    "sg:phone": "+1 419 353 2337",
    "sg:postcode": "43402",
    "sg:province": "OH",
    "wof:name": "Bowling Green Beverage Inc",
    "wof:placetype": "venue"
  },
  "geometry": {"coordinates":[-83.650629,41.408572],"type":"Point"}
}
