{
  "type": "Feature",
  "properties": {
    "iso:country":"US",
    "sg:address":"50 Superior St",
    "sg:city":"Youngstown",
    "sg:classifiers":[
        {
            "category":"Home & Garden",
            "subcategory":"Building Materials",
            "type":"Retail Goods"
        },
        {
            "category":"Manufacturing",
            "subcategory":"Furniture",
            "type":"Manufacturing & Wholesale Goods"
        }
    ],
    "sg:phone":"+1 330 743 1050",
    "sg:postcode":"44510",
    "sg:province":"OH",
    "sg:tags":[
        "mfg"
    ],
    "wof:name":"Angles Shapes and Surfaces",
    "wof:placetype":"venue"
},
  "geometry": {"coordinates":[-80.668318,41.118013],"type":"Point"}
}