{
  "type": "Feature",
  "properties": {
    "addr:full": "22925 W Sprague Rd Strongsville OH 44149",
    "addr:housenumber": "22925",
    "addr:postcode": "44149",
    "addr:street": "W Sprague Rd",
    "iso:country": "US",
    "sg:address": "22925 W Sprague Rd",
    "sg:city": "Strongsville",
    "sg:classifiers": [
      {
        "category": "Personal",
        "subcategory": "Beauty Salon",
        "type": "Services"
      }
    ],
    "sg:phone": "+1 440 243 6299",
    "sg:postcode": "44149",
    "sg:province": "OH",
    "wof:name": "Ladonna's Coiffures",
    "wof:placetype": "venue"
  },
  "geometry": {"coordinates":[-81.876546,41.350606],"type":"Point"}
}
