{
  "type": "Feature",
  "properties": {
    "addr:full": "2695 Barnes Rd Shiloh OH 44878",
    "addr:housenumber": "2695",
    "addr:postcode": "44878",
    "addr:street": "Barnes Rd",
    "iso:country": "US",
    "sg:address": "2695 Barnes Rd",
    "sg:city": "Shiloh",
    "sg:classifiers": [
      {
        "category": "Home \u0026 Garden",
        "subcategory": "Garden Supply",
        "type": "Retail Goods"
      }
    ],
    "sg:phone": "+1 419 896 3816",
    "sg:postcode": "44878",
    "sg:province": "OH",
    "sg:tags": [
      "lawn"
    ],
    "wof:name": "Four Seasons Lawn \u0026 Garden",
    "wof:placetype": "venue"
  },
  "geometry": {"coordinates":[-82.607029,40.98094],"type":"Point"}
}
