{
  "type": "Feature",
  "properties": {
    "iso:country":"US",
    "sg:address":"2695 Barnes Rd",
    "sg:city":"Shiloh",
    "sg:classifiers":[
        {
            "category":"Home & Garden",
            "subcategory":"Garden Supply",
            "type":"Retail Goods"
        }
    ],
    "sg:phone":"+1 419 896 3816",
    "sg:postcode":"44878",
    "sg:province":"OH",
    "sg:tags":[
        "lawn"
    ],
    "wof:name":"Four Seasons Lawn & Garden",
    "wof:placetype":"venue"
},
  "geometry": {"coordinates":[-82.607029,40.98094],"type":"Point"}
}