{
  "type": "Feature",
  "properties": {
    "iso:country":"US",
    "sg:address":"12507 Corlett Ave",
    "sg:city":"Cleveland",
    "sg:classifiers":[
        {
            "category":"Organizations",
            "subcategory":"Religious Organization",
            "type":"Services"
        }
    ],
    "sg:phone":"+1 216 441 1744",
    "sg:postcode":"44105",
    "sg:province":"OH",
    "sg:tags":[
        "clergy"
    ],
    "wof:name":"Seth Thomas",
    "wof:placetype":"venue"
},
  "geometry": {"coordinates":[-81.595809,41.455742],"type":"Point"}
}