{
  "type": "Feature",
  "properties": {
    "addr:full": "117 W Maple St Bryan OH 43506",
    "addr:housenumber": "117",
    "addr:postcode": "43506",
    "addr:street": "W Maple St",
    "iso:country": "US",
    "sg:address": "117 W Maple St",
    "sg:city": "Bryan",
    "sg:classifiers": [
      {
        "category": "Professional",
        "subcategory": "Lawyer \u0026 Legal Services",
        "type": "Services"
      }
    ],
    "sg:phone": "+1 419 636 3196",
    "sg:postcode": "43506",
    "sg:province": "OH",
    "sg:tags": [
      "attorney"
    ],
    "sg:website": "www.nsslawoffice.com",
    "wof:name": "Newcomer Schaeffer \u0026 Spangler",
    "wof:placetype": "venue"
  },
  "geometry": {"coordinates":[-84.551565,41.471938],"type":"Point"}
}
