{
  "type": "Feature",
  "properties": {
    "iso:country":"US",
    "sg:address":"117 W Maple St",
    "sg:city":"Bryan",
    "sg:classifiers":[
        {
            "category":"Professional",
            "subcategory":"Lawyer & Legal Services",
            "type":"Services"
        }
    ],
    "sg:phone":"+1 419 636 3196",
    "sg:postcode":"43506",
    "sg:province":"OH",
    "sg:tags":[
        "attorney"
    ],
    "sg:website":"www.nsslawoffice.com",
    "wof:name":"Newcomer Schaeffer & Spangler",
    "wof:placetype":"venue"
},
  "geometry": {"coordinates":[-84.551565,41.471938],"type":"Point"}
}