{
  "type": "Feature",
  "properties": {
    "addr:full":"1531 S Hawkins Ave Akron OH 44320",
    "addr:housenumber":"1531",
    "addr:postcode":"44320",
    "addr:street":"S Hawkins Ave",
    "iso:country":"US",
    "sg:address":"1531 S Hawkins Ave",
    "sg:city":"Akron",
    "sg:classifiers":[
        {
            "category":"Shopping",
            "subcategory":"Tobacco",
            "type":"Retail Goods"
        }
    ],
    "sg:phone":"+1 330 836 7427",
    "sg:postcode":"44320",
    "sg:province":"OH",
    "sg:tags":[
        "cigarette",
        "cigar",
        "dealer"
    ],
    "wof:name":"Smoke N Joe's",
    "wof:placetype":"venue"
},
  "geometry": {"coordinates":[-81.56963,41.065586],"type":"Point"}
}