{
  "type": "Feature",
  "properties": {
    "addr:full": "1148 Main Ave Cleveland OH 44113",
    "addr:housenumber": "1148",
    "addr:postcode": "44113",
    "addr:street": "Main Ave",
    "iso:country": "US",
    "sg:address": "1148 Main Ave",
    "sg:city": "Cleveland",
    "sg:classifiers": [
      {
        "category": "Restaurant",
        "type": "Food \u0026 Drink"
      }
    ],
    "sg:phone": "+1 216 241 2700",
    "sg:postcode": "44113",
    "sg:province": "OH",
    "wof:name": "Paninis In Flats",
    "wof:placetype": "venue"
  },
  "geometry": {"coordinates":[-81.706325,41.49716],"type":"Point"}
}
