{
  "type": "Feature",
  "properties": {
    "iso:country":"US",
    "sg:address":"1148 Main Ave",
    "sg:city":"Cleveland",
    "sg:classifiers":[
        {
            "category":"Restaurant",
            "type":"Food & Drink"
        }
    ],
    "sg:phone":"+1 216 241 2700",
    "sg:postcode":"44113",
    "sg:province":"OH",
    "wof:name":"Paninis In Flats",
    "wof:placetype":"venue"
},
  "geometry": {"coordinates":[-81.70632500000001,41.49716],"type":"Point"}
}