{
  "type": "Feature",
  "properties": {
    "addr:full": "43502 Oberlin Elyria Rd Oberlin OH 44074",
    "addr:housenumber": "43502",
    "addr:postcode": "44074",
    "addr:street": "Oberlin Elyria Rd",
    "iso:country": "US",
    "sg:address": "43502 Oberlin Elyria Rd",
    "sg:city": "Oberlin",
    "sg:classifiers": [
      {
        "category": "Building \u0026 Trades",
        "subcategory": "Construction",
        "type": "Services"
      }
    ],
    "sg:phone": "+1 440 774 3946",
    "sg:postcode": "44074",
    "sg:province": "OH",
    "sg:tags": [
      "general",
      "contractor"
    ],
    "wof:name": "New Dominion Construction",
    "wof:placetype": "venue"
  },
  "geometry": {"coordinates":[-82.165725,41.296897],"type":"Point"}
}
