{
  "type": "Feature",
  "properties": {
    "addr:full": "1399 N Main St Amherst OH 44001",
    "addr:housenumber": "1399",
    "addr:postcode": "44001",
    "addr:street": "N Main St",
    "iso:country": "US",
    "sg:address": "1399 N Main St",
    "sg:city": "Amherst",
    "sg:classifiers": [
      {
        "category": "Manufacturing",
        "subcategory": "Lumber",
        "type": "Manufacturing \u0026 Wholesale Goods"
      }
    ],
    "sg:phone": "+1 440 988 4808",
    "sg:postcode": "44001",
    "sg:province": "OH",
    "sg:tags": [
      "operation",
      "timber",
      "tract"
    ],
    "wof:name": "McGough Farms",
    "wof:placetype": "venue"
  },
  "geometry": {"coordinates":[-82.227905,41.425678],"type":"Point"}
}
