{
  "type": "Feature",
  "properties": {
    "iso:country":"US",
    "sg:address":"1399 N Main St",
    "sg:city":"Amherst",
    "sg:classifiers":[
        {
            "category":"Manufacturing",
            "subcategory":"Lumber",
            "type":"Manufacturing & Wholesale Goods"
        }
    ],
    "sg:phone":"+1 440 988 4808",
    "sg:postcode":"44001",
    "sg:province":"OH",
    "sg:tags":[
        "operation",
        "timber",
        "tract"
    ],
    "wof:name":"McGough Farms",
    "wof:placetype":"venue"
},
  "geometry": {"coordinates":[-82.22790500000001,41.425678],"type":"Point"}
}