{
  "type": "Feature",
  "properties": {
    "iso:country":"US",
    "sg:address":"4867 Mahoning Ave NW",
    "sg:city":"Warren",
    "sg:classifiers":[
        {
            "category":"Autos & Motor Vehicles",
            "subcategory":"Motorcycle Sales",
            "type":"Retail Goods"
        }
    ],
    "sg:phone":"+1 330 847 7644",
    "sg:postcode":"44483",
    "sg:province":"OH",
    "sg:tags":[
        "scooter"
    ],
    "sg:website":"www.yamahaofwarren.com",
    "wof:name":"Yamaha Of Warren Inc",
    "wof:placetype":"venue"
},
  "geometry": {"coordinates":[-80.847067,41.287739],"type":"Point"}
}