{
  "type": "Feature",
  "properties": {
    "iso:country":"US",
    "sg:address":"5454 Alger Dr",
    "sg:city":"Sylvania",
    "sg:classifiers":[
        {
            "category":"Building & Trades",
            "subcategory":"Electrical",
            "type":"Services"
        }
    ],
    "sg:phone":"+1 419 861 3666",
    "sg:postcode":"43560",
    "sg:province":"OH",
    "sg:tags":[
        "electric",
        "contractor"
    ],
    "wof:name":"Professional Electrical Svc",
    "wof:placetype":"venue"
},
  "geometry": {"coordinates":[-83.679441,41.713737],"type":"Point"}
}