{
  "type": "Feature",
  "properties": {
    "addr:full":"9388 Limeridge Rd Mantua OH 44255",
    "addr:housenumber":"9388",
    "addr:postcode":"44255",
    "addr:street":"Limeridge Rd",
    "iso:country":"US",
    "sg:address":"9388 Limeridge Rd",
    "sg:city":"Mantua",
    "sg:classifiers":[
        {
            "category":"Wholesale",
            "subcategory":"Electrical",
            "type":"Manufacturing & Wholesale Goods"
        }
    ],
    "sg:phone":"+1 330 274 2770",
    "sg:postcode":"44255",
    "sg:province":"OH",
    "sg:tags":[
        "equipment"
    ],
    "wof:name":"Electrical Harness & Loom",
    "wof:placetype":"venue"
},
  "geometry": {"coordinates":[-81.18275,41.250351],"type":"Point"}
}