{
  "type": "Feature",
  "properties": {
    "addr:full":"518 E Town St Columbus OH 43215",
    "addr:housenumber":"518",
    "addr:postcode":"43215",
    "addr:street":"E Town St",
    "iso:country":"US",
    "sg:address":"518 E Town St",
    "sg:city":"Columbus",
    "sg:classifiers":[
        {
            "category":"Real Estate",
            "subcategory":"Real Estate Operator",
            "type":"Services"
        }
    ],
    "sg:phone":"+1 614 224 5584",
    "sg:postcode":"43215",
    "sg:province":"OH",
    "sg:tags":[
        "building",
        "apartment"
    ],
    "wof:name":"Washington Apartments",
    "wof:placetype":"venue"
},
  "geometry": {"coordinates":[-82.985877,39.960502],"type":"Point"}
}