{
  "type": "Feature",
  "properties": {
    "addr:full":"36085 Salem Grange Rd Salem OH 44460",
    "addr:housenumber":"36085",
    "addr:postcode":"44460",
    "addr:street":"Salem Grange Rd",
    "iso:country":"US",
    "sg:address":"36085 Salem Grange Rd",
    "sg:city":"Salem",
    "sg:classifiers":[
        {
            "category":"Building & Trades",
            "subcategory":"Plumbing",
            "type":"Services"
        }
    ],
    "sg:phone":"+1 330 332 1828",
    "sg:postcode":"44460",
    "sg:province":"OH",
    "sg:tags":[
        "product",
        "management",
        "energy",
        "system"
    ],
    "wof:name":"Great Lakes Energy Partners",
    "wof:placetype":"venue"
},
  "geometry": {"coordinates":[-80.817555,40.857109],"type":"Point"}
}