{
  "type": "Feature",
  "properties": {
    "addr:full": "320 E Silver St Lebanon OH 45036",
    "addr:housenumber": "320",
    "addr:postcode": "45036",
    "addr:street": "E Silver St",
    "iso:country": "US",
    "sg:address": "320 E Silver St",
    "sg:city": "Lebanon",
    "sg:classifiers": [
      {
        "category": "Government",
        "subcategory": "Office",
        "type": "Public Place"
      }
    ],
    "sg:phone": "+1 513 420 4311",
    "sg:postcode": "45036",
    "sg:province": "OH",
    "wof:name": "Ohio State University Ext",
    "wof:placetype": "venue"
  },
  "geometry": {"coordinates":[-84.202524,39.435211],"type":"Point"}
}
