{
  "type": "Feature",
  "properties": {
    "iso:country":"US",
    "sg:address":"5657 Turnberry Dr",
    "sg:city":"Westerville",
    "sg:classifiers":[
        {
            "category":"Real Estate",
            "subcategory":"Real Estate Agent",
            "type":"Services"
        }
    ],
    "sg:phone":"+1 614 890 5019",
    "sg:postcode":"43082",
    "sg:province":"OH",
    "sg:tags":[
        "management"
    ],
    "wof:name":"Katsco Properties",
    "wof:placetype":"venue"
},
  "geometry": {"coordinates":[-82.932681,40.158119],"type":"Point"}
}