{
  "type": "Feature",
  "properties": {
    "iso:country":"US",
    "sg:address":"3252 E Main St",
    "sg:city":"Columbus",
    "sg:classifiers":[
        {
            "category":"Health Services",
            "subcategory":"Chiropractor",
            "type":"Services"
        }
    ],
    "sg:phone":"+1 614 237 2225",
    "sg:postcode":"43213",
    "sg:province":"OH",
    "wof:name":"Paul J Shannon DC",
    "wof:placetype":"venue"
},
  "geometry": {"coordinates":[-82.912691,39.956601],"type":"Point"}
}