{
  "type": "Feature",
  "properties": {
    "addr:full":"14100 Cedar Rd Cleveland OH 44121",
    "addr:housenumber":"14100",
    "addr:postcode":"44121",
    "addr:street":"Cedar Rd",
    "iso:country":"US",
    "sg:address":"14100 Cedar Rd",
    "sg:city":"Cleveland",
    "sg:classifiers":[
        {
            "category":"Health Services",
            "subcategory":"Doctor",
            "type":"Services"
        }
    ],
    "sg:phone":"+1 216 381 1400",
    "sg:postcode":"44121",
    "sg:province":"OH",
    "sg:tags":[
        "physician",
        "surgeon"
    ],
    "wof:name":"Heights Wound Care Clinic",
    "wof:placetype":"venue"
},
  "geometry": {"coordinates":[-81.53628399999999,41.501349],"type":"Point"}
}