{
  "type": "Feature",
  "properties": {
    "addr:full": "779 S 2nd St Coshocton OH 43812",
    "addr:housenumber": "779",
    "addr:postcode": "43812",
    "addr:street": "S 2Nd St",
    "iso:country": "US",
    "sg:address": "779 S 2nd St",
    "sg:city": "Coshocton",
    "sg:classifiers": [
      {
        "category": "Shopping",
        "subcategory": "Department Store",
        "type": "Retail Goods"
      }
    ],
    "sg:phone": "+1 740 622 1278",
    "sg:postcode": "43812",
    "sg:province": "OH",
    "sg:tags": [
      "discount"
    ],
    "wof:name": "Wal-Mart",
    "wof:placetype": "venue"
  },
  "geometry": {"coordinates":[-81.869367,40.265525],"type":"Point"}
}
