{
  "type": "Feature",
  "properties": {
    "iso:country":"US",
    "sg:address":"5486 Cedar Breaks Ct",
    "sg:city":"Fairfield",
    "sg:classifiers":[
        {
            "category":"Building & Trades",
            "subcategory":"Pest Control",
            "type":"Services"
        }
    ],
    "sg:phone":"+1 513 829 2686",
    "sg:postcode":"45014",
    "sg:province":"OH",
    "sg:tags":[
        "industrial",
        "services-commercial"
    ],
    "wof:name":"Pinnacle Exterminating Co",
    "wof:placetype":"venue"
},
  "geometry": {"coordinates":[-84.54625799999999,39.330072],"type":"Point"}
}