{
  "type": "Feature",
  "properties": {
    "addr:full":"623 High St Hamilton OH 45011",
    "addr:housenumber":"623",
    "addr:postcode":"45011",
    "addr:street":"High St",
    "iso:country":"US",
    "sg:address":"623 High St",
    "sg:city":"Hamilton",
    "sg:classifiers":[
        {
            "category":"Autos & Motor Vehicles",
            "subcategory":"Automobile Sales",
            "type":"Retail Goods"
        }
    ],
    "sg:phone":"+1 513 894 3686",
    "sg:postcode":"45011",
    "sg:province":"OH",
    "sg:tags":[
        "car",
        "dealer"
    ],
    "wof:name":"AKR Auto Sales",
    "wof:placetype":"venue"
},
  "geometry": {"coordinates":[-84.554885,39.397624],"type":"Point"}
}