{
  "type": "Feature",
  "properties": {
    "addr:full": "402 Main St Tiro OH 44887",
    "addr:housenumber": "402",
    "addr:postcode": "44887",
    "addr:street": "Main St",
    "iso:country": "US",
    "sg:address": "402 Main St",
    "sg:city": "Tiro",
    "sg:classifiers": [
      {
        "category": "Organizations",
        "subcategory": "Religious Organization",
        "type": "Services"
      }
    ],
    "sg:phone": "+1 419 342 2561",
    "sg:postcode": "44887",
    "sg:province": "OH",
    "sg:tags": [
      "church"
    ],
    "wof:name": "Crouse Memorial Lutheran Chr",
    "wof:placetype": "venue"
  },
  "geometry": {"coordinates":[-82.772348,40.909292],"type":"Point"}
}
