{
  "type": "Feature",
  "properties": {
    "addr:full":"60696 Hope Ave Byesville OH 43723",
    "addr:housenumber":"60696",
    "addr:postcode":"43723",
    "addr:street":"Hope Ave",
    "iso:country":"US",
    "sg:address":"60696 Hope Ave",
    "sg:city":"Byesville",
    "sg:classifiers":[
        {
            "category":"Organizations",
            "subcategory":"Labor Organization",
            "type":"Services"
        }
    ],
    "sg:phone":"+1 740 685 3018",
    "sg:postcode":"43723",
    "sg:province":"OH",
    "wof:name":"Uaw Local 2024",
    "wof:placetype":"venue"
},
  "geometry": {"coordinates":[-81.548405,39.979708],"type":"Point"}
}