{
  "type": "Feature",
  "properties": {
    "iso:country":"US",
    "sg:address":"26440 Bradner Rd",
    "sg:city":"Genoa",
    "sg:classifiers":[
        {
            "category":"Farming",
            "subcategory":"Farm",
            "type":"Manufacturing & Wholesale Goods"
        }
    ],
    "sg:phone":"+1 419 837 6311",
    "sg:postcode":"43430",
    "sg:province":"OH",
    "sg:tags":[
        "crop",
        "general"
    ],
    "wof:name":"Welling Farms",
    "wof:placetype":"venue"
},
  "geometry": {"coordinates":[-83.433967,41.531209],"type":"Point"}
}