{
  "type": "Feature",
  "properties": {
    "addr:full": "26440 Bradner Rd Genoa OH 43430",
    "addr:postcode": "26440;43430",
    "addr:street": "Bradner Rd",
    "iso:country": "US",
    "sg:address": "26440 Bradner Rd",
    "sg:city": "Genoa",
    "sg:classifiers": [
      {
        "category": "Farming",
        "subcategory": "Farm",
        "type": "Manufacturing \u0026 Wholesale Goods"
      }
    ],
    "sg:phone": "+1 419 837 6311",
    "sg:postcode": "43430",
    "sg:province": "OH",
    "sg:tags": [
      "crop",
      "general"
    ],
    "wof:name": "Welling Farms",
    "wof:placetype": "venue"
  },
  "geometry": {"coordinates":[-83.433967,41.531209],"type":"Point"}
}
