{
  "type": "Feature",
  "properties": {
    "addr:full":"1571 W Lane Ave Columbus OH 43221",
    "addr:housenumber":"1571",
    "addr:postcode":"43221",
    "addr:street":"W Lane Ave",
    "iso:country":"US",
    "sg:address":"1571 W Lane Ave",
    "sg:city":"Columbus",
    "sg:classifiers":[
        {
            "category":"Personal",
            "subcategory":"Beauty Salon",
            "type":"Services"
        }
    ],
    "sg:phone":"+1 614 488 0628",
    "sg:postcode":"43221",
    "sg:province":"OH",
    "sg:website":"http://www.regiscorp.com",
    "wof:name":"Saturday's Hair Salon",
    "wof:placetype":"venue"
},
  "geometry": {"coordinates":[-83.052406,40.007099],"type":"Point"}
}