{
  "type": "Feature",
  "properties": {
    "iso:country":"US",
    "sg:address":"3705 Lonsdale St",
    "sg:city":"Cincinnati",
    "sg:classifiers":[
        {
            "category":"Organizations",
            "subcategory":"Religious Organization",
            "type":"Services"
        }
    ],
    "sg:phone":"+1 513 271 3605",
    "sg:postcode":"45227",
    "sg:province":"OH",
    "sg:tags":[
        "church"
    ],
    "wof:name":"Fairfax Church Of God",
    "wof:placetype":"venue"
},
  "geometry": {"coordinates":[-84.391079,39.143974],"type":"Point"}
}