{
  "type": "Feature",
  "properties": {
    "addr:full":"8444 Glennridge Ave NW Clinton OH 44216",
    "addr:housenumber":"8444",
    "addr:postcode":"44216",
    "addr:street":"Glennridge Ave Nw",
    "iso:country":"US",
    "sg:address":"8444 Glennridge Ave NW",
    "sg:city":"Clinton",
    "sg:classifiers":[
        {
            "category":"Manufacturing",
            "subcategory":"Toys & Sporting Goods",
            "type":"Manufacturing & Wholesale Goods"
        }
    ],
    "sg:phone":"+1 330 854 0554",
    "sg:postcode":"44216",
    "sg:province":"OH",
    "sg:tags":[
        "craft",
        "mfg"
    ],
    "wof:name":"Designs From The Heart",
    "wof:placetype":"venue"
},
  "geometry": {"coordinates":[-81.520527,40.905695],"type":"Point"}
}