{
  "type": "Feature",
  "properties": {
    "iso:country":"US",
    "sg:address":"1952 W Broad St",
    "sg:city":"Columbus",
    "sg:classifiers":[
        {
            "category":"Local Transit",
            "type":"Transportation"
        }
    ],
    "sg:phone":"+1 614 466 9451",
    "sg:postcode":"43223",
    "sg:province":"OH",
    "sg:tags":[
        "passenger"
    ],
    "wof:name":"Ambulance Licensing Board Ohio",
    "wof:placetype":"venue"
},
  "geometry": {"coordinates":[-83.04748499999999,39.956658],"type":"Point"}
}