{
  "type": "Feature",
  "properties": {
    "addr:full":"9779 Morrow-Woodville Rd Pleasant Plain OH 45162",
    "addr:housenumber":"9779",
    "addr:postcode":"45162",
    "addr:street":"Morrow-Woodville Rd",
    "iso:country":"US",
    "sg:address":"9779 Morrow-Woodville Rd",
    "sg:city":"Pleasant Plain",
    "sg:classifiers":[
        {
            "category":"Retail",
            "subcategory":"Portrait Studio",
            "type":"Services"
        }
    ],
    "sg:phone":"+1 513 877 2287",
    "sg:postcode":"45162",
    "sg:province":"OH",
    "sg:tags":[
        "photo"
    ],
    "wof:name":"Fugett Photography",
    "wof:placetype":"venue"
},
  "geometry": {"coordinates":[-84.042823,39.280995],"type":"Point"}
}