{
  "type": "Feature",
  "properties": {
    "addr:full": "4030 E 131st St Cleveland OH 44105",
    "addr:housenumber": "4030",
    "addr:postcode": "44105",
    "addr:street": "E 131St St",
    "iso:country": "US",
    "sg:address": "4030 E 131st St",
    "sg:city": "Cleveland",
    "sg:classifiers": [
      {
        "category": "Food \u0026 Beverages",
        "subcategory": "Specialty",
        "type": "Retail Goods"
      }
    ],
    "sg:phone": "+1 216 921 6812",
    "sg:postcode": "44105",
    "sg:province": "OH",
    "sg:tags": [
      "health",
      "diet"
    ],
    "wof:name": "HFA",
    "wof:placetype": "venue"
  },
  "geometry": {"coordinates":[-81.591203,41.449752],"type":"Point"}
}
