{
  "type": "Feature",
  "properties": {
    "iso:country":"US",
    "sg:address":"4882 Pearl Rd",
    "sg:city":"Cleveland",
    "sg:classifiers":[
        {
            "category":"Food & Beverages",
            "subcategory":"Groceries & Convenience Stores",
            "type":"Retail Goods"
        },
        {
            "category":"Wholesale",
            "subcategory":"Durable Goods & Equipment",
            "type":"Manufacturing & Wholesale Goods"
        }
    ],
    "sg:phone":"+1 216 398 1548",
    "sg:postcode":"44109",
    "sg:province":"OH",
    "sg:tags":[
        "importer"
    ],
    "sg:website":"www.gaelicimports.com",
    "wof:name":"Gaelic Imports",
    "wof:placetype":"venue"
},
  "geometry": {"coordinates":[-81.721143,41.424869],"type":"Point"}
}