{
  "type": "Feature",
  "properties": {
    "addr:full": "4882 Pearl Rd Cleveland OH 44109",
    "addr:housenumber": "4882",
    "addr:postcode": "44109",
    "addr:street": "Pearl Rd",
    "iso:country": "US",
    "sg:address": "4882 Pearl Rd",
    "sg:city": "Cleveland",
    "sg:classifiers": [
      {
        "category": "Food \u0026 Beverages",
        "subcategory": "Groceries \u0026 Convenience Stores",
        "type": "Retail Goods"
      },
      {
        "category": "Wholesale",
        "subcategory": "Durable Goods \u0026 Equipment",
        "type": "Manufacturing \u0026 Wholesale Goods"
      }
    ],
    "sg:phone": "+1 216 398 1548",
    "sg:postcode": "44109",
    "sg:province": "OH",
    "sg:tags": [
      "importer"
    ],
    "sg:website": "www.gaelicimports.com",
    "wof:name": "Gaelic Imports",
    "wof:placetype": "venue"
  },
  "geometry": {"coordinates":[-81.721143,41.424869],"type":"Point"}
}
