{
  "type": "Feature",
  "properties": {
    "addr:full": "3547 Cleveland Ave Columbus OH 43224",
    "addr:housenumber": "3547",
    "addr:postcode": "43224",
    "addr:street": "Cleveland Ave",
    "iso:country": "US",
    "sg:address": "3547 Cleveland Ave",
    "sg:city": "Columbus",
    "sg:classifiers": [
      {
        "category": "Shopping",
        "subcategory": "Computers \u0026 Home Electronics",
        "type": "Retail Goods"
      }
    ],
    "sg:phone": "+1 614 267 4482",
    "sg:postcode": "43224",
    "sg:province": "OH",
    "wof:name": "Radio Shack",
    "wof:placetype": "venue"
  },
  "geometry": {"coordinates":[-82.962482,40.03741],"type":"Point"}
}
