{
  "type": "Feature",
  "properties": {
    "addr:full":"2306 Locust St S Canal Fulton OH 44614",
    "addr:housenumber":"2306",
    "addr:postcode":"44614",
    "addr:street":"Locust St S",
    "iso:country":"US",
    "sg:address":"2306 Locust St S",
    "sg:city":"Canal Fulton",
    "sg:classifiers":[
        {
            "category":"Personal",
            "type":"Services"
        }
    ],
    "sg:phone":"+1 330 854 4900",
    "sg:postcode":"44614",
    "sg:province":"OH",
    "sg:tags":[
        "towing"
    ],
    "wof:name":"Skipco Financial Adjusters Inc",
    "wof:placetype":"venue"
},
  "geometry": {"coordinates":[-81.57109800000001,40.882198],"type":"Point"}
}