{
  "type": "Feature",
  "properties": {
    "iso:country":"US",
    "sg:address":"14860 Chillicothe Rd",
    "sg:city":"Novelty",
    "sg:classifiers":[
        {
            "category":"Professional",
            "type":"Services"
        }
    ],
    "sg:phone":"+1 440 338 3074",
    "sg:postcode":"44072",
    "sg:province":"OH",
    "wof:name":"Elegant Impressions LLC",
    "wof:placetype":"venue"
},
  "geometry": {"coordinates":[-81.34023,41.469098],"type":"Point"}
}