{
  "type": "Feature",
  "properties": {
    "iso:country":"US",
    "sg:address":"1301 W Sandusky Ave",
    "sg:city":"Bellefontaine",
    "sg:classifiers":[
        {
            "category":"Wholesale",
            "subcategory":"Machinery & Supplies",
            "type":"Manufacturing & Wholesale Goods"
        }
    ],
    "sg:phone":"+1 937 593 5010",
    "sg:postcode":"43311",
    "sg:province":"OH",
    "sg:tags":[
        "hardware",
        "equipment",
        "industrial",
        "mfg"
    ],
    "sg:website":"www.hbdthermoid.com",
    "wof:name":"Hbd Industries Inc",
    "wof:placetype":"venue"
},
  "geometry": {"coordinates":[-83.782264,40.363115],"type":"Point"}
}