{
  "type": "Feature",
  "properties": {
    "addr:full": "1301 W Sandusky Ave Bellefontaine OH 43311",
    "addr:housenumber": "1301",
    "addr:postcode": "43311",
    "addr:street": "W Sandusky Ave",
    "iso:country": "US",
    "sg:address": "1301 W Sandusky Ave",
    "sg:city": "Bellefontaine",
    "sg:classifiers": [
      {
        "category": "Wholesale",
        "subcategory": "Machinery \u0026 Supplies",
        "type": "Manufacturing \u0026 Wholesale Goods"
      }
    ],
    "sg:phone": "+1 937 593 5010",
    "sg:postcode": "43311",
    "sg:province": "OH",
    "sg:tags": [
      "hardware",
      "equipment",
      "industrial",
      "mfg"
    ],
    "sg:website": "www.hbdthermoid.com",
    "wof:name": "Hbd Industries Inc",
    "wof:placetype": "venue"
  },
  "geometry": {"coordinates":[-83.782264,40.363115],"type":"Point"}
}
