{
  "type": "Feature",
  "properties": {
    "addr:full":"8351 Macthomas Ave NW North Canton OH 44720",
    "addr:housenumber":"8351",
    "addr:postcode":"44720",
    "addr:street":"Macthomas Ave Nw",
    "iso:country":"US",
    "sg:address":"8351 Macthomas Ave NW",
    "sg:city":"North Canton",
    "sg:classifiers":[
        {
            "category":"Manufacturing",
            "subcategory":"Printing",
            "type":"Manufacturing & Wholesale Goods"
        }
    ],
    "sg:phone":"+1 330 966 8104",
    "sg:postcode":"44720",
    "sg:province":"OH",
    "sg:tags":[
        "equipment",
        "loose",
        "leaf"
    ],
    "wof:name":"Terry Jarvis",
    "wof:placetype":"venue"
},
  "geometry": {"coordinates":[-81.383747,40.910869],"type":"Point"}
}