{
  "type": "Feature",
  "properties": {
    "addr:full":"647 Parkway Blvd Norton OH 44203",
    "addr:housenumber":"647",
    "addr:postcode":"44203",
    "addr:street":"Parkway Blvd",
    "iso:country":"US",
    "sg:address":"647 Parkway Blvd",
    "sg:city":"Norton",
    "sg:classifiers":[
        {
            "category":"Organizations",
            "subcategory":"Religious Organization",
            "type":"Services"
        }
    ],
    "sg:phone":"+1 330 825 8966",
    "sg:postcode":"44203",
    "sg:province":"OH",
    "sg:tags":[
        "clergy"
    ],
    "wof:name":"Robert Combs",
    "wof:placetype":"venue"
},
  "geometry": {"coordinates":[-81.633279,41.025126],"type":"Point"}
}