{
  "type": "Feature",
  "properties": {
    "addr:full": "806 Bethel Rd Columbus OH 43214",
    "addr:housenumber": "806",
    "addr:postcode": "43214",
    "addr:street": "Bethel Rd",
    "iso:country": "US",
    "sg:address": "806 Bethel Rd",
    "sg:city": "Columbus",
    "sg:classifiers": [
      {
        "category": "Wholesale",
        "subcategory": "Electrical",
        "type": "Manufacturing \u0026 Wholesale Goods"
      }
    ],
    "sg:phone": "+1 614 326 0274",
    "sg:postcode": "43214",
    "sg:province": "OH",
    "sg:tags": [
      "record"
    ],
    "sg:website": "www.imarnet.com",
    "wof:name": "Imar Corp",
    "wof:placetype": "venue"
  },
  "geometry": {"coordinates":[-83.043656,40.063275],"type":"Point"}
}
