{
  "type": "Feature",
  "properties": {
    "iso:country":"US",
    "sg:address":"3910 Old Riverside Dr",
    "sg:city":"Dayton",
    "sg:classifiers":[
        {
            "category":"Professional",
            "subcategory":"Computer Services",
            "type":"Services"
        }
    ],
    "sg:phone":"+1 937 279 9309",
    "sg:postcode":"45405",
    "sg:province":"OH",
    "sg:tags":[
        "repair"
    ],
    "wof:name":"Home Computer Doctors",
    "wof:placetype":"venue"
},
  "geometry": {"coordinates":[-84.209936,39.804202],"type":"Point"}
}