{
  "type": "Feature",
  "properties": {
    "addr:full": "311 E Columbus St Columbus OH 43206",
    "addr:housenumber": "311",
    "addr:postcode": "43206",
    "addr:street": "E Columbus St",
    "iso:country": "US",
    "sg:address": "311 E Columbus St",
    "sg:city": "Columbus",
    "sg:classifiers": [
      {
        "category": "Professional",
        "type": "Services"
      }
    ],
    "sg:phone": "+1 614 542 9029",
    "sg:postcode": "43206",
    "sg:province": "OH",
    "wof:name": "P Trent Taylor",
    "wof:placetype": "venue"
  },
  "geometry": {"coordinates":[-82.989426,39.946839],"type":"Point"}
}
