{
  "type": "Feature",
  "properties": {
    "iso:country":"US",
    "sg:address":"202 W Poplar St",
    "sg:city":"Sidney",
    "sg:classifiers":[
        {
            "category":"Government",
            "subcategory":"Office",
            "type":"Public Place"
        }
    ],
    "sg:phone":"+1 937 498 2185",
    "sg:postcode":"45365",
    "sg:province":"OH",
    "sg:tags":[
        "administrative",
        "program",
        "health"
    ],
    "sg:website":"www.helpmegrow.com",
    "wof:name":"Help Me Grow",
    "wof:placetype":"venue"
},
  "geometry": {"coordinates":[-84.158237,40.285662],"type":"Point"}
}