{
  "type": "Feature",
  "properties": {
    "addr:full":"2798 Westerville Rd Columbus OH 43224",
    "addr:housenumber":"2798",
    "addr:postcode":"43224",
    "addr:street":"Westerville Rd",
    "iso:country":"US",
    "sg:address":"2798 Westerville Rd",
    "sg:city":"Columbus",
    "sg:classifiers":[
        {
            "category":"Wholesale",
            "subcategory":"Auto Parts",
            "type":"Manufacturing & Wholesale Goods"
        }
    ],
    "sg:phone":"+1 614 261 0832",
    "sg:postcode":"43224",
    "sg:province":"OH",
    "sg:tags":[
        "body",
        "automobile",
        "shop"
    ],
    "wof:name":"Shad Used Tires",
    "wof:placetype":"venue"
},
  "geometry": {"coordinates":[-82.96183600000001,40.024611],"type":"Point"}
}