{
  "type": "Feature",
  "properties": {
    "addr:full": "9124 State Rte 49 Ansonia OH 45303",
    "addr:housenumber": "9124",
    "addr:postcode": "45303",
    "addr:street": "State Rte 49",
    "iso:country": "US",
    "sg:address": "9124 State Rte 49",
    "sg:city": "Ansonia",
    "sg:classifiers": [
      {
        "category": "Shopping",
        "subcategory": "Used Merchandise",
        "type": "Retail Goods"
      }
    ],
    "sg:phone": "+1 937 548 5340",
    "sg:postcode": "45303",
    "sg:province": "OH",
    "wof:name": "Kenworthys Auction",
    "wof:placetype": "venue"
  },
  "geometry": {"coordinates":[-84.678305,40.180701],"type":"Point"}
}
