{
  "type": "Feature",
  "properties": {
    "addr:full":"518 2nd Ave Gallipolis OH 45631",
    "addr:housenumber":"518",
    "addr:postcode":"45631",
    "addr:street":"2Nd Ave",
    "iso:country":"US",
    "sg:address":"518 2nd Ave",
    "sg:city":"Gallipolis",
    "sg:classifiers":[
        {
            "category":"Organizations",
            "subcategory":"Non-profit Organization",
            "type":"Services"
        }
    ],
    "sg:phone":"+1 740 446 7933",
    "sg:postcode":"45631",
    "sg:province":"OH",
    "sg:tags":[
        "human"
    ],
    "wof:name":"Victim Assistance Program",
    "wof:placetype":"venue"
},
  "geometry": {"coordinates":[-82.20153000000001,38.810404],"type":"Point"}
}