{
  "type": "Feature",
  "properties": {
    "iso:country":"US",
    "sg:address":"751 Forest Ave",
    "sg:city":"Zanesville",
    "sg:classifiers":[
        {
            "category":"Health Services",
            "subcategory":"Doctor",
            "type":"Services"
        }
    ],
    "sg:phone":"+1 740 454 0804",
    "sg:postcode":"43701",
    "sg:province":"OH",
    "sg:tags":[
        "physician",
        "surgeon"
    ],
    "wof:name":"Cardiology Associates-Se Ohio",
    "wof:placetype":"venue"
},
  "geometry": {"coordinates":[-82.012997,39.955437],"type":"Point"}
}