{
  "type": "Feature",
  "properties": {
    "addr:full":"10 W Park Pl Oxford OH 45056",
    "addr:housenumber":"10",
    "addr:postcode":"45056",
    "addr:street":"W Park Pl",
    "iso:country":"US",
    "sg:address":"10 W Park Pl",
    "sg:city":"Oxford",
    "sg:classifiers":[
        {
            "category":"Building & Trades",
            "subcategory":"Construction",
            "type":"Services"
        },
        {
            "category":"Home & Garden",
            "subcategory":"Carpets & Floor Coverings",
            "type":"Retail Goods"
        }
    ],
    "sg:phone":"+1 513 523 9585",
    "sg:postcode":"45056",
    "sg:province":"OH",
    "sg:tags":[
        "installs",
        "rug",
        "dealer"
    ],
    "wof:name":"Austin's Floor Store",
    "wof:placetype":"venue"
},
  "geometry": {"coordinates":[-84.742475,39.511047],"type":"Point"}
}