{
  "type": "Feature",
  "properties": {
    "addr:full":"611 Sherman St Akron OH 44311",
    "addr:housenumber":"611",
    "addr:postcode":"44311",
    "addr:street":"Sherman St",
    "iso:country":"US",
    "sg:address":"611 Sherman St",
    "sg:city":"Akron",
    "sg:classifiers":[
        {
            "category":"Building & Trades",
            "subcategory":"Construction",
            "type":"Services"
        }
    ],
    "sg:phone":"+1 330 376 1063",
    "sg:postcode":"44311",
    "sg:province":"OH",
    "sg:tags":[
        "residential"
    ],
    "wof:name":"Jnk Construction",
    "wof:placetype":"venue"
},
  "geometry": {"coordinates":[-81.516352,41.06699],"type":"Point"}
}