{
  "type": "Feature",
  "properties": {
    "addr:full": "14 Triangle Park Dr Cincinnati OH 45246",
    "addr:housenumber": "14",
    "addr:postcode": "45246",
    "addr:street": "Triangle Park Dr",
    "iso:country": "US",
    "sg:address": "14 Triangle Park Dr",
    "sg:city": "Cincinnati",
    "sg:classifiers": [
      {
        "category": "Professional",
        "subcategory": "Business Services",
        "type": "Services"
      }
    ],
    "sg:phone": "+1 513 772 5990",
    "sg:postcode": "45246",
    "sg:province": "OH",
    "sg:tags": [
      "inventory"
    ],
    "sg:website": "www.rgisinv.com",
    "wof:name": "R G I S Inventory Specialists",
    "wof:placetype": "venue"
  },
  "geometry": {"coordinates":[-84.447402,39.290839],"type":"Point"}
}
