{
  "type": "Feature",
  "properties": {
    "iso:country":"US",
    "sg:address":"122 N Washington St",
    "sg:city":"Van Wert",
    "sg:classifiers":[
        {
            "category":"Real Estate",
            "subcategory":"Real Estate Agent",
            "type":"Services"
        }
    ],
    "sg:phone":"+1 419 238 5555",
    "sg:postcode":"45891",
    "sg:province":"OH",
    "sg:tags":[
        "business"
    ],
    "wof:name":"Robert D Gamble",
    "wof:placetype":"venue"
},
  "geometry": {"coordinates":[-84.582938,40.870285],"type":"Point"}
}