{
  "type": "Feature",
  "properties": {
    "addr:full": "73 Rainbow Dr Bidwell OH 45614",
    "addr:housenumber": "73",
    "addr:postcode": "45614",
    "addr:street": "Rainbow Dr",
    "iso:country": "US",
    "sg:address": "73 Rainbow Dr",
    "sg:city": "Bidwell",
    "sg:classifiers": [
      {
        "category": "Farming",
        "subcategory": "Livestock Farm",
        "type": "Manufacturing \u0026 Wholesale Goods"
      }
    ],
    "sg:phone": "+1 740 446 2921",
    "sg:postcode": "45614",
    "sg:province": "OH",
    "sg:tags": [
      "beef",
      "feedlot",
      "cattle"
    ],
    "wof:name": "Burleson Kail",
    "wof:placetype": "venue"
  },
  "geometry": {"coordinates":[-82.252422,38.864651],"type":"Point"}
}
