{
  "type": "Feature",
  "properties": {
    "iso:country":"US",
    "sg:address":"1147 Miami St",
    "sg:city":"Toledo",
    "sg:classifiers":[
        {
            "category":"Wholesale",
            "subcategory":"Machinery & Supplies",
            "type":"Manufacturing & Wholesale Goods"
        }
    ],
    "sg:phone":"+1 419 698 3223",
    "sg:postcode":"43605",
    "sg:province":"OH",
    "sg:tags":[
        "janitor"
    ],
    "wof:name":"Hyco Supply Inc",
    "wof:placetype":"venue"
},
  "geometry": {"coordinates":[-83.529311,41.629798],"type":"Point"}
}