{
  "type": "Feature",
  "properties": {
    "iso:country":"US",
    "sg:address":"821 E Findlay St",
    "sg:city":"Carey",
    "sg:classifiers":[
        {
            "category":"Health Services",
            "subcategory":"Nursing And Care Facility",
            "type":"Services"
        }
    ],
    "sg:phone":"+1 419 396 6344",
    "sg:postcode":"43316",
    "sg:province":"OH",
    "sg:tags":[
        "home",
        "convalescent"
    ],
    "wof:name":"Caring Nursing Rehab",
    "wof:placetype":"venue"
},
  "geometry": {"coordinates":[-83.36739300000001,40.949811],"type":"Point"}
}