{
  "type": "Feature",
  "properties": {
    "addr:full": "6778 Lexington Park Blvd Mason OH 45040",
    "addr:housenumber": "6778",
    "addr:postcode": "45040",
    "addr:street": "Lexington Park Blvd",
    "iso:country": "US",
    "sg:address": "6778 Lexington Park Blvd",
    "sg:city": "Mason",
    "sg:classifiers": [
      {
        "category": "Building \u0026 Trades",
        "subcategory": "Construction",
        "type": "Services"
      }
    ],
    "sg:phone": "+1 513 459 9518",
    "sg:postcode": "45040",
    "sg:province": "OH",
    "sg:tags": [
      "home",
      "builder"
    ],
    "wof:name": "M/I Homes",
    "wof:placetype": "venue"
  },
  "geometry": {"coordinates":[-84.312538,39.341405],"type":"Point"}
}
