{
  "type": "Feature",
  "properties": {
    "addr:full": "6658 Eagleville Rd Bloomdale OH 44817",
    "addr:postcode": "6658;44817",
    "addr:street": "Eagleville Rd",
    "iso:country": "US",
    "sg:address": "6658 Eagleville Rd",
    "sg:city": "Bloomdale",
    "sg:classifiers": [
      {
        "category": "Freight",
        "type": "Transportation"
      }
    ],
    "sg:phone": "+1 419 454 5701",
    "sg:postcode": "44817",
    "sg:province": "OH",
    "sg:tags": [
      "operator",
      "trucking"
    ],
    "wof:name": "High Hopes Transportation Inc",
    "wof:placetype": "venue"
  },
  "geometry": {"coordinates":[-83.526531,41.200695],"type":"Point"}
}
