{
  "type": "Feature",
  "properties": {
    "iso:country":"US",
    "sg:address":"6658 Eagleville Rd",
    "sg:city":"Bloomdale",
    "sg:classifiers":[
        {
            "category":"Freight",
            "type":"Transportation"
        }
    ],
    "sg:phone":"+1 419 454 5701",
    "sg:postcode":"44817",
    "sg:province":"OH",
    "sg:tags":[
        "operator",
        "trucking"
    ],
    "wof:name":"High Hopes Transportation Inc",
    "wof:placetype":"venue"
},
  "geometry": {"coordinates":[-83.52653100000001,41.200695],"type":"Point"}
}