{
  "type": "Feature",
  "properties": {
    "addr:full":"203 W Franklin St Dayton OH 45459",
    "addr:housenumber":"203",
    "addr:postcode":"45459",
    "addr:street":"W Franklin St",
    "iso:country":"US",
    "sg:address":"203 W Franklin St",
    "sg:city":"Dayton",
    "sg:classifiers":[
        {
            "category":"Banks & Credit Unions",
            "subcategory":"Investment Brokerage",
            "type":"Services"
        }
    ],
    "sg:phone":"+1 937 434 5697",
    "sg:postcode":"45459",
    "sg:province":"OH",
    "sg:tags":[
        "advisory"
    ],
    "wof:name":"401 Advisor",
    "wof:placetype":"venue"
},
  "geometry": {"coordinates":[-84.167436,39.628179],"type":"Point"}
}