{
  "type": "Feature",
  "properties": {
    "addr:full": "2215 Batavia-Williamsburg Pike Batavia OH 45103",
    "addr:housenumber": "2215",
    "addr:postcode": "45103",
    "addr:street": "Batavia-Williamsburg Pike",
    "iso:country": "US",
    "sg:address": "2215 Batavia-Williamsburg Pike",
    "sg:city": "Batavia",
    "sg:classifiers": [
      {
        "category": "Real Estate",
        "subcategory": "Real Estate Operator",
        "type": "Services"
      },
      {
        "category": "Organizations",
        "subcategory": "Community Association",
        "type": "Services"
      }
    ],
    "sg:phone": "+1 513 732 2428",
    "sg:postcode": "45103",
    "sg:province": "OH",
    "sg:tags": [
      "building",
      "military",
      "nonresidential"
    ],
    "wof:name": "American Legion",
    "wof:placetype": "venue"
  },
  "geometry": {"coordinates":[-84.15669,39.077841],"type":"Point"}
}
