{
  "type": "Feature",
  "properties": {
    "addr:full":"7911 Euclid Ave Cincinnati OH 45243",
    "addr:housenumber":"7911",
    "addr:postcode":"45243",
    "addr:street":"Euclid Ave",
    "iso:country":"US",
    "sg:address":"7911 Euclid Ave",
    "sg:city":"Cincinnati",
    "sg:classifiers":[
        {
            "category":"Health Services",
            "subcategory":"Doctor",
            "type":"Services"
        }
    ],
    "sg:phone":"+1 513 561 5958",
    "sg:postcode":"45243",
    "sg:province":"OH",
    "sg:tags":[
        "physician",
        "surgeon"
    ],
    "wof:name":"Madeira Center-Healing & Acupn",
    "wof:placetype":"venue"
},
  "geometry": {"coordinates":[-84.356131,39.190625],"type":"Point"}
}