{
  "type": "Feature",
  "properties": {
    "addr:full": "6811 Corinth Court Rd Farmdale OH 44417",
    "addr:housenumber": "6811",
    "addr:postcode": "44417",
    "addr:street": "Corinth Court Rd",
    "iso:country": "US",
    "sg:address": "6811 Corinth Court Rd",
    "sg:city": "Farmdale",
    "sg:classifiers": [
      {
        "category": "Farming",
        "subcategory": "Farm \u0026 Veterinary Services",
        "type": "Manufacturing \u0026 Wholesale Goods"
      }
    ],
    "sg:phone": "+1 330 924 2394",
    "sg:postcode": "44417",
    "sg:province": "OH",
    "wof:name": "Neil Kohlmorgan Inc",
    "wof:placetype": "venue"
  },
  "geometry": {"coordinates":[-80.618574,41.424454],"type":"Point"}
}
