{
  "type": "Feature",
  "properties": {
    "iso:country":"US",
    "sg:address":"6811 Corinth Court Rd",
    "sg:city":"Farmdale",
    "sg:classifiers":[
        {
            "category":"Farming",
            "subcategory":"Farm & Veterinary Services",
            "type":"Manufacturing & Wholesale Goods"
        }
    ],
    "sg:phone":"+1 330 924 2394",
    "sg:postcode":"44417",
    "sg:province":"OH",
    "wof:name":"Neil Kohlmorgan Inc",
    "wof:placetype":"venue"
},
  "geometry": {"coordinates":[-80.618574,41.424454],"type":"Point"}
}