{
  "type": "Feature",
  "properties": {
    "addr:full": "399 N Main St Mansfield OH 44902",
    "addr:housenumber": "399",
    "addr:postcode": "44902",
    "addr:street": "N Main St",
    "iso:country": "US",
    "sg:address": "399 N Main St",
    "sg:city": "Mansfield",
    "sg:classifiers": [
      {
        "category": "Building \u0026 Trades",
        "subcategory": "Construction",
        "type": "Services"
      }
    ],
    "sg:phone": "+1 419 589 8441",
    "sg:postcode": "44902",
    "sg:province": "OH",
    "sg:tags": [
      "contractor"
    ],
    "wof:name": "Advanced Masonry Repair",
    "wof:placetype": "venue"
  },
  "geometry": {"coordinates":[-82.514822,40.769985],"type":"Point"}
}
