{
  "type": "Feature",
  "properties": {
    "addr:full": "140 Public Sq Cleveland OH 44114",
    "addr:housenumber": "140",
    "addr:postcode": "44114",
    "addr:street": "Public Sq",
    "iso:country": "US",
    "sg:address": "140 Public Sq",
    "sg:city": "Cleveland",
    "sg:classifiers": [
      {
        "category": "Professional",
        "subcategory": "Accounting \u0026 Tax Preparation",
        "type": "Services"
      }
    ],
    "sg:phone": "+1 216 696 6699",
    "sg:postcode": "44114",
    "sg:province": "OH",
    "wof:name": "Ran Associates of Cleveland",
    "wof:placetype": "venue"
  },
  "geometry": {"coordinates":[-81.693012,41.500179],"type":"Point"}
}
