{
  "type": "Feature",
  "properties": {
    "addr:full": "34900 Lake Shore Blvd Willoughby OH 44095",
    "addr:housenumber": "34900",
    "addr:postcode": "44095",
    "addr:street": "Lake Shore Blvd",
    "iso:country": "US",
    "sg:address": "34900 Lake Shore Blvd",
    "sg:city": "Willoughby",
    "sg:classifiers": [
      {
        "category": "Food \u0026 Beverages",
        "subcategory": "Meat \u0026 Fish",
        "type": "Retail Goods"
      }
    ],
    "sg:phone": "+1 440 953 3758",
    "sg:postcode": "44095",
    "sg:province": "OH",
    "wof:name": "Mirof's Meat Market",
    "wof:placetype": "venue"
  },
  "geometry": {"coordinates":[-81.442692,41.663403],"type":"Point"}
}
