{
  "type": "Feature",
  "properties": {
    "iso:country":"US",
    "sg:address":"614 W Superior Ave",
    "sg:city":"Cleveland",
    "sg:classifiers":[
        {
            "category":"Restaurant",
            "type":"Food & Drink"
        }
    ],
    "sg:phone":"+1 216 566 7717",
    "sg:postcode":"44113",
    "sg:province":"OH",
    "sg:tags":[
        "delicatessen"
    ],
    "wof:name":"Rockfeller Cafe",
    "wof:placetype":"venue"
},
  "geometry": {"coordinates":[-81.698537,41.497304],"type":"Point"}
}