{
  "type": "Feature",
  "properties": {
    "addr:full":"38 N State St Westerville OH 43081",
    "addr:housenumber":"38",
    "addr:postcode":"43081",
    "addr:street":"N State St",
    "iso:country":"US",
    "sg:address":"38 N State St",
    "sg:city":"Westerville",
    "sg:classifiers":[
        {
            "category":"Shopping",
            "type":"Retail Goods"
        }
    ],
    "sg:phone":"+1 614 890 8202",
    "sg:postcode":"43081",
    "sg:province":"OH",
    "sg:tags":[
        "art",
        "gallery",
        "dealer"
    ],
    "wof:name":"Gallery 202",
    "wof:placetype":"venue"
},
  "geometry": {"coordinates":[-82.932039,40.127231],"type":"Point"}
}