{
  "type": "Feature",
  "properties": {
    "addr:full": "1100 Wayne St Troy OH 45373",
    "addr:housenumber": "1100",
    "addr:postcode": "45373",
    "addr:street": "Wayne St",
    "iso:country": "US",
    "sg:address": "1100 Wayne St",
    "sg:city": "Troy",
    "sg:classifiers": [
      {
        "category": "Education",
        "subcategory": "Vocational School",
        "type": "Public Place"
      }
    ],
    "sg:phone": "+1 937 440 0550",
    "sg:postcode": "45373",
    "sg:province": "OH",
    "sg:tags": [
      "nurse"
    ],
    "wof:name": "Upper Valley JVS School",
    "wof:placetype": "venue"
  },
  "geometry": {"coordinates":[-84.217534,40.034352],"type":"Point"}
}
