{
  "type": "Feature",
  "properties": {
    "addr:full": "419 Superior St Rossford OH 43460",
    "addr:housenumber": "419",
    "addr:postcode": "43460",
    "addr:street": "Superior St",
    "iso:country": "US",
    "sg:address": "419 Superior St",
    "sg:city": "Rossford",
    "sg:classifiers": [
      {
        "category": "Personal",
        "subcategory": "Barber",
        "type": "Services"
      }
    ],
    "sg:phone": "+1 419 666 5522",
    "sg:postcode": "43460",
    "sg:province": "OH",
    "wof:name": "Village Squire Barber Salon",
    "wof:placetype": "venue"
  },
  "geometry": {"coordinates":[-83.556856,41.611343],"type":"Point"}
}
