{
  "type": "Feature",
  "properties": {
    "addr:full":"114 W Main St Cardington OH 43315",
    "addr:housenumber":"114",
    "addr:postcode":"43315",
    "addr:street":"W Main St",
    "iso:country":"US",
    "sg:address":"114 W Main St",
    "sg:city":"Cardington",
    "sg:classifiers":[
        {
            "category":"Personal",
            "subcategory":"Barber",
            "type":"Services"
        }
    ],
    "sg:phone":"+1 419 864 4576",
    "sg:postcode":"43315",
    "sg:province":"OH",
    "wof:name":"Other Half Barber Shop",
    "wof:placetype":"venue"
},
  "geometry": {"coordinates":[-82.89478699999999,40.500471],"type":"Point"}
}