{
  "type": "Feature",
  "properties": {
    "addr:full": "306 Hillwood Dr Toledo OH 43608",
    "addr:housenumber": "306",
    "addr:postcode": "43608",
    "addr:street": "Hillwood Dr",
    "iso:country": "US",
    "sg:address": "306 Hillwood Dr",
    "sg:city": "Toledo",
    "sg:classifiers": [
      {
        "category": "Real Estate",
        "subcategory": "Real Estate Agent",
        "type": "Services"
      }
    ],
    "sg:phone": "+1 419 255 7331",
    "sg:postcode": "43608",
    "sg:province": "OH",
    "wof:name": "Jan Harris",
    "wof:placetype": "venue"
  },
  "geometry": {"coordinates":[-83.552427,41.681169],"type":"Point"}
}
