{
  "type": "Feature",
  "properties": {
    "iso:country":"US",
    "sg:address":"306 Hillwood Dr",
    "sg:city":"Toledo",
    "sg:classifiers":[
        {
            "category":"Real Estate",
            "subcategory":"Real Estate Agent",
            "type":"Services"
        }
    ],
    "sg:phone":"+1 419 255 7331",
    "sg:postcode":"43608",
    "sg:province":"OH",
    "wof:name":"Jan Harris",
    "wof:placetype":"venue"
},
  "geometry": {"coordinates":[-83.55242699999999,41.681169],"type":"Point"}
}