{
  "type": "Feature",
  "properties": {
    "addr:full": "543 White Oak Pl Worthington OH 43085",
    "addr:housenumber": "543",
    "addr:postcode": "43085",
    "addr:street": "White Oak Pl",
    "iso:country": "US",
    "sg:address": "543 White Oak Pl",
    "sg:city": "Worthington",
    "sg:classifiers": [
      {
        "category": "Professional",
        "subcategory": "Computer Services",
        "type": "Services"
      }
    ],
    "sg:phone": "+1 614 848 4465",
    "sg:postcode": "43085",
    "sg:province": "OH",
    "sg:tags": [
      "consultant",
      "designer",
      "datum",
      "system"
    ],
    "wof:name": "White Oak Resources Inc",
    "wof:placetype": "venue"
  },
  "geometry": {"coordinates":[-83.007526,40.084811],"type":"Point"}
}
