{
  "type": "Feature",
  "properties": {
    "addr:full":"1535 Babbitt Rd Cleveland OH 44132",
    "addr:housenumber":"1535",
    "addr:postcode":"44132",
    "addr:street":"Babbitt Rd",
    "iso:country":"US",
    "sg:address":"1535 Babbitt Rd",
    "sg:city":"Cleveland",
    "sg:classifiers":[
        {
            "category":"Organizations",
            "subcategory":"Professional Association",
            "type":"Services"
        }
    ],
    "sg:phone":"+1 216 556 3633",
    "sg:postcode":"44132",
    "sg:province":"OH",
    "wof:name":"National Black MBA Assoc Inc",
    "wof:placetype":"venue"
},
  "geometry": {"coordinates":[-81.505937,41.586823],"type":"Point"}
}