{
  "type": "Feature",
  "properties": {
    "addr:full": "3839 Royal Oak Dr Brunswick OH 44212",
    "addr:housenumber": "3839",
    "addr:postcode": "44212",
    "addr:street": "Royal Oak Dr",
    "iso:country": "US",
    "sg:address": "3839 Royal Oak Dr",
    "sg:city": "Brunswick",
    "sg:classifiers": [
      {
        "category": "Insurance",
        "subcategory": "Hazard Insurance",
        "type": "Services"
      }
    ],
    "sg:phone": "+1 330 220 6420",
    "sg:postcode": "44212",
    "sg:province": "OH",
    "sg:tags": [
      "carrier",
      "surety"
    ],
    "wof:name": "International Fidelty Insur Co",
    "wof:placetype": "venue"
  },
  "geometry": {"coordinates":[-81.824396,41.233896],"type":"Point"}
}
