{
  "type": "Feature",
  "properties": {
    "addr:full":"3967 State Rte 303 Mantua OH 44255",
    "addr:housenumber":"3967",
    "addr:postcode":"44255",
    "addr:street":"State Rte 303",
    "iso:country":"US",
    "sg:address":"3967 State Rte 303",
    "sg:city":"Mantua",
    "sg:classifiers":[
        {
            "category":"Farming",
            "subcategory":"Farm & Veterinary Services",
            "type":"Manufacturing & Wholesale Goods"
        }
    ],
    "sg:phone":"+1 330 296 2666",
    "sg:postcode":"44255",
    "sg:province":"OH",
    "sg:tags":[
        "liquid",
        "pet",
        "marketing",
        "crop",
        "prep",
        "merchandise"
    ],
    "wof:name":"Valley Brook Farm & Feed",
    "wof:placetype":"venue"
},
  "geometry": {"coordinates":[-81.250984,41.241364],"type":"Point"}
}