{
  "type": "Feature",
  "properties": {
    "addr:full": "3137 Jay St Ravenna OH 44266",
    "addr:housenumber": "3137",
    "addr:postcode": "44266",
    "addr:street": "Jay St",
    "iso:country": "US",
    "sg:address": "3137 Jay St",
    "sg:city": "Ravenna",
    "sg:classifiers": [
      {
        "category": "Retail",
        "subcategory": "Repair Shop",
        "type": "Services"
      }
    ],
    "sg:phone": "+1 330 296 8545",
    "sg:postcode": "44266",
    "sg:province": "OH",
    "sg:tags": [
      "instrument",
      "musical"
    ],
    "wof:name": "Edward James Piano Svc",
    "wof:placetype": "venue"
  },
  "geometry": {"coordinates":[-81.2774,41.125],"type":"Point"}
}
