{
  "type": "Feature",
  "properties": {
    "addr:full":"786 Britton Ave Dayton OH 45429",
    "addr:housenumber":"786",
    "addr:postcode":"45429",
    "addr:street":"Britton Ave",
    "iso:country":"US",
    "sg:address":"786 Britton Ave",
    "sg:city":"Dayton",
    "sg:classifiers":[
        {
            "category":"Shopping",
            "subcategory":"Clothing, Apparel, & Fashions",
            "type":"Retail Goods"
        }
    ],
    "sg:phone":"+1 937 434 3762",
    "sg:postcode":"45429",
    "sg:province":"OH",
    "wof:name":"Shirts N Things",
    "wof:placetype":"venue"
},
  "geometry": {"coordinates":[-84.151717,39.671991],"type":"Point"}
}