{
  "type": "Feature",
  "properties": {
    "addr:full":"824 E 237th St Euclid OH 44123",
    "addr:housenumber":"824",
    "addr:postcode":"44123",
    "addr:street":"E 237Th St",
    "iso:country":"US",
    "sg:address":"824 E 237th St",
    "sg:city":"Euclid",
    "sg:classifiers":[
        {
            "category":"Professional",
            "subcategory":"Accounting & Tax Preparation",
            "type":"Services"
        }
    ],
    "sg:phone":"+1 216 289 8643",
    "sg:postcode":"44123",
    "sg:province":"OH",
    "wof:name":"Bellegoni Inc",
    "wof:placetype":"venue"
},
  "geometry": {"coordinates":[-81.51720899999999,41.597831],"type":"Point"}
}