{
  "type": "Feature",
  "properties": {
    "iso:country":"US",
    "sg:address":"2297 Edmund Ave",
    "sg:city":"Akron",
    "sg:classifiers":[
        {
            "category":"Professional",
            "subcategory":"Business Services",
            "type":"Services"
        }
    ],
    "sg:phone":"+1 330 733 6707",
    "sg:postcode":"44312",
    "sg:province":"OH",
    "sg:tags":[
        "inspection"
    ],
    "sg:website":"www.dchome1.com",
    "wof:name":"D C Home Iinspection Svc",
    "wof:placetype":"venue"
},
  "geometry": {"coordinates":[-81.44669399999999,41.048714],"type":"Point"}
}