{
  "type": "Feature",
  "properties": {
    "iso:country":"US",
    "sg:address":"4101 Harrison Ave",
    "sg:city":"Cincinnati",
    "sg:classifiers":[
        {
            "category":"Shopping",
            "subcategory":"Pharmacy",
            "type":"Retail Goods"
        }
    ],
    "sg:phone":"+1 513 574 3535",
    "sg:postcode":"45211",
    "sg:province":"OH",
    "wof:name":"CVS Pharmacy",
    "wof:placetype":"venue"
},
  "geometry": {"coordinates":[-84.618263,39.158467],"type":"Point"}
}