{
  "type": "Feature",
  "properties": {
    "addr:full": "228 Cypress St Louisville OH 44641",
    "addr:housenumber": "228",
    "addr:postcode": "44641",
    "addr:street": "Cypress St",
    "iso:country": "US",
    "sg:address": "228 Cypress St",
    "sg:city": "Louisville",
    "sg:classifiers": [
      {
        "category": "Professional",
        "type": "Services"
      }
    ],
    "sg:phone": "+1 330 875 9732",
    "sg:postcode": "44641",
    "sg:province": "OH",
    "wof:name": "Union Land Company",
    "wof:placetype": "venue"
  },
  "geometry": {"coordinates":[-81.240347,40.837168],"type":"Point"}
}
