{
  "type": "Feature",
  "properties": {
    "addr:full": "25460 US Hwy 23 Circleville OH 43113",
    "addr:postcode": "25460;43113",
    "addr:street": "Us Hwy 23",
    "iso:country": "US",
    "sg:address": "25460 US Hwy 23",
    "sg:city": "Circleville",
    "sg:classifiers": [
      {
        "category": "Autos \u0026 Motor Vehicles",
        "subcategory": "Recreational Vehicle Sales",
        "type": "Retail Goods"
      }
    ],
    "sg:phone": "+1 740 474 8544",
    "sg:postcode": "43113",
    "sg:province": "OH",
    "wof:name": "Countrytime Sales",
    "wof:placetype": "venue"
  },
  "geometry": {"coordinates":[-82.957484,39.559989],"type":"Point"}
}
