{
  "type": "Feature",
  "properties": {
    "addr:full": "240 Kurtz St Wooster OH 44691",
    "addr:housenumber": "240",
    "addr:postcode": "44691",
    "addr:street": "Kurtz St",
    "iso:country": "US",
    "sg:address": "240 Kurtz St",
    "sg:city": "Wooster",
    "sg:classifiers": [
      {
        "category": "Building \u0026 Trades",
        "subcategory": "Landscaping Services",
        "type": "Services"
      }
    ],
    "sg:phone": "+1 330 264 6410",
    "sg:postcode": "44691",
    "sg:province": "OH",
    "sg:tags": [
      "landscape",
      "contractor"
    ],
    "wof:name": "Burdette's Green Acres",
    "wof:placetype": "venue"
  },
  "geometry": {"coordinates":[-81.937974,40.82138],"type":"Point"}
}
