{
  "type": "Feature",
  "properties": {
    "iso:country":"US",
    "sg:address":"240 Kurtz St",
    "sg:city":"Wooster",
    "sg:classifiers":[
        {
            "category":"Building & Trades",
            "subcategory":"Landscaping Services",
            "type":"Services"
        }
    ],
    "sg:phone":"+1 330 264 6410",
    "sg:postcode":"44691",
    "sg:province":"OH",
    "sg:tags":[
        "landscape",
        "contractor"
    ],
    "wof:name":"Burdette's Green Acres",
    "wof:placetype":"venue"
},
  "geometry": {"coordinates":[-81.937974,40.82138],"type":"Point"}
}