{
  "type": "Feature",
  "properties": {
    "addr:full": "4141 Burrville Rd Coldwater OH 45828",
    "addr:housenumber": "4141",
    "addr:postcode": "45828",
    "addr:street": "Burrville Rd",
    "iso:country": "US",
    "sg:address": "4141 Burrville Rd",
    "sg:city": "Coldwater",
    "sg:classifiers": [
      {
        "category": "Retail",
        "subcategory": "Auto Repair",
        "type": "Services"
      }
    ],
    "sg:phone": "+1 419 375 1141",
    "sg:postcode": "45828",
    "sg:province": "OH",
    "sg:tags": [
      "truck"
    ],
    "wof:name": "J B Truck Svc \u0026 Parts",
    "wof:placetype": "venue"
  },
  "geometry": {"coordinates":[-84.727095,40.469718],"type":"Point"}
}
