{
  "type": "Feature",
  "properties": {
    "iso:country":"US",
    "sg:address":"4141 Burrville Rd",
    "sg:city":"Coldwater",
    "sg:classifiers":[
        {
            "category":"Retail",
            "subcategory":"Auto Repair",
            "type":"Services"
        }
    ],
    "sg:phone":"+1 419 375 1141",
    "sg:postcode":"45828",
    "sg:province":"OH",
    "sg:tags":[
        "truck"
    ],
    "wof:name":"J B Truck Svc & Parts",
    "wof:placetype":"venue"
},
  "geometry": {"coordinates":[-84.72709500000001,40.469718],"type":"Point"}
}