{
  "type": "Feature",
  "properties": {
    "addr:full":"8688 Simpson Ct Mason OH 45040",
    "addr:housenumber":"8688",
    "addr:postcode":"45040",
    "addr:street":"Simpson Ct",
    "iso:country":"US",
    "sg:address":"8688 Simpson Ct",
    "sg:city":"Mason",
    "sg:classifiers":[
        {
            "category":"Professional",
            "subcategory":"Engineering",
            "type":"Services"
        }
    ],
    "sg:phone":"+1 513 459 9650",
    "sg:postcode":"45040",
    "sg:province":"OH",
    "sg:tags":[
        "engineer"
    ],
    "wof:name":"Infrared Engineering",
    "wof:placetype":"venue"
},
  "geometry": {"coordinates":[-84.29216099999999,39.310462],"type":"Point"}
}