{
  "type": "Feature",
  "properties": {
    "addr:full":"2903 Bennington Ave Columbus OH 43231",
    "addr:housenumber":"2903",
    "addr:postcode":"43231",
    "addr:street":"Bennington Ave",
    "iso:country":"US",
    "sg:address":"2903 Bennington Ave",
    "sg:city":"Columbus",
    "sg:classifiers":[
        {
            "category":"Wholesale",
            "subcategory":"Farm Supplies",
            "type":"Manufacturing & Wholesale Goods"
        }
    ],
    "sg:phone":"+1 614 471 3456",
    "sg:postcode":"43231",
    "sg:province":"OH",
    "wof:name":"Reeb Brothers Farms",
    "wof:placetype":"venue"
},
  "geometry": {"coordinates":[-82.935954,40.061019],"type":"Point"}
}