{
  "type": "Feature",
  "properties": {
    "addr:full":"2103 E 100th St Cleveland OH 44106",
    "addr:housenumber":"2103",
    "addr:postcode":"44106",
    "addr:street":"E 100Th St",
    "iso:country":"US",
    "sg:address":"2103 E 100th St",
    "sg:city":"Cleveland",
    "sg:classifiers":[
        {
            "category":"Building & Trades",
            "subcategory":"Construction",
            "type":"Services"
        }
    ],
    "sg:phone":"+1 216 795 6442",
    "sg:postcode":"44106",
    "sg:province":"OH",
    "sg:tags":[
        "company"
    ],
    "wof:name":"Turner Construction Co",
    "wof:placetype":"venue"
},
  "geometry": {"coordinates":[-81.618256,41.500444],"type":"Point"}
}