{
  "type": "Feature",
  "properties": {
    "addr:full":"32708 Lake Rd Avon Lake OH 44012",
    "addr:housenumber":"32708",
    "addr:postcode":"44012",
    "addr:street":"Lake Rd",
    "iso:country":"US",
    "sg:address":"32708 Lake Rd",
    "sg:city":"Avon Lake",
    "sg:classifiers":[
        {
            "category":"Travel",
            "subcategory":"Hotels & Motels",
            "type":"Entertainment"
        }
    ],
    "sg:phone":"+1 440 933 6393",
    "sg:postcode":"44012",
    "sg:province":"OH",
    "sg:tags":[
        "breakfast",
        "accommodation",
        "bed"
    ],
    "wof:name":"Potonic's Bed & Breakfast",
    "wof:placetype":"venue"
},
  "geometry": {"coordinates":[-82.01643199999999,41.513198],"type":"Point"}
}