{
  "type": "Feature",
  "properties": {
    "addr:full": "9880 Freeway Dr Macedonia OH 44056",
    "addr:housenumber": "9880",
    "addr:postcode": "44056",
    "addr:street": "Freeway Dr",
    "iso:country": "US",
    "sg:address": "9880 Freeway Dr",
    "sg:city": "Macedonia",
    "sg:classifiers": [
      {
        "category": "Social Services",
        "type": "Services"
      }
    ],
    "sg:phone": "+1 330 467 4888",
    "sg:postcode": "44056",
    "sg:province": "OH",
    "sg:tags": [
      "counseling"
    ],
    "wof:name": "Catholic Charities",
    "wof:placetype": "venue"
  },
  "geometry": {"coordinates":[-81.51355,41.335896],"type":"Point"}
}
