{
  "type": "Feature",
  "properties": {
    "iso:country":"US",
    "sg:address":"1797 US Hwy 52",
    "sg:city":"Moscow",
    "sg:classifiers":[
        {
            "category":"Building & Trades",
            "subcategory":"Construction",
            "type":"Services"
        }
    ],
    "sg:phone":"+1 513 553 1829",
    "sg:postcode":"45153",
    "sg:province":"OH",
    "sg:tags":[
        "contractor"
    ],
    "wof:name":"Hayward Buildwright Co",
    "wof:placetype":"venue"
},
  "geometry": {"coordinates":[-84.223995,38.853222],"type":"Point"}
}