{
  "type": "Feature",
  "properties": {
    "iso:country":"US",
    "sg:address":"378 Walhalla Rd",
    "sg:city":"Columbus",
    "sg:classifiers":[
        {
            "category":"Professional",
            "subcategory":"Management & Consulting",
            "type":"Services"
        }
    ],
    "sg:phone":"+1 614 261 6419",
    "sg:postcode":"43202",
    "sg:province":"OH",
    "sg:tags":[
        "consultant",
        "business"
    ],
    "wof:name":"Business Management Group Inc",
    "wof:placetype":"venue"
},
  "geometry": {"coordinates":[-83.004884,40.028075],"type":"Point"}
}