{
  "type": "Feature",
  "properties": {
    "addr:full": "378 Walhalla Rd Columbus OH 43202",
    "addr:housenumber": "378",
    "addr:postcode": "43202",
    "addr:street": "Walhalla Rd",
    "iso:country": "US",
    "sg:address": "378 Walhalla Rd",
    "sg:city": "Columbus",
    "sg:classifiers": [
      {
        "category": "Professional",
        "subcategory": "Management \u0026 Consulting",
        "type": "Services"
      }
    ],
    "sg:phone": "+1 614 261 6419",
    "sg:postcode": "43202",
    "sg:province": "OH",
    "sg:tags": [
      "consultant",
      "business"
    ],
    "wof:name": "Business Management Group Inc",
    "wof:placetype": "venue"
  },
  "geometry": {"coordinates":[-83.004884,40.028075],"type":"Point"}
}
