{
  "type": "Feature",
  "properties": {
    "addr:full": "2969 Co Rd 234 Hicksville OH 43526",
    "addr:housenumber": "2969",
    "addr:postcode": "43526",
    "addr:street": "Co Rd 234",
    "iso:country": "US",
    "sg:address": "2969 Co Rd 234",
    "sg:city": "Hicksville",
    "sg:classifiers": [
      {
        "category": "Retail",
        "subcategory": "Repair Shop",
        "type": "Services"
      }
    ],
    "sg:phone": "+1 419 542 7372",
    "sg:postcode": "43526",
    "sg:province": "OH",
    "sg:tags": [
      "repairing",
      "piano",
      "refinishing"
    ],
    "wof:name": "Coplin Piano Svc",
    "wof:placetype": "venue"
  },
  "geometry": {"coordinates":[-84.770356,41.24463],"type":"Point"}
}
