{
  "type": "Feature",
  "properties": {
    "iso:country":"US",
    "sg:address":"2969 Co Rd 234",
    "sg:city":"Hicksville",
    "sg:classifiers":[
        {
            "category":"Retail",
            "subcategory":"Repair Shop",
            "type":"Services"
        }
    ],
    "sg:phone":"+1 419 542 7372",
    "sg:postcode":"43526",
    "sg:province":"OH",
    "sg:tags":[
        "repairing",
        "piano",
        "refinishing"
    ],
    "wof:name":"Coplin Piano Svc",
    "wof:placetype":"venue"
},
  "geometry": {"coordinates":[-84.770356,41.24463],"type":"Point"}
}