{
  "type": "Feature",
  "properties": {
    "addr:full":"7 Hide Away Dr Cridersville OH 45806",
    "addr:housenumber":"7",
    "addr:postcode":"45806",
    "addr:street":"Hide Away Dr",
    "iso:country":"US",
    "sg:address":"7 Hide Away Dr",
    "sg:city":"Cridersville",
    "sg:classifiers":[
        {
            "category":"Real Estate",
            "subcategory":"Real Estate Operator",
            "type":"Services"
        }
    ],
    "sg:phone":"+1 419 645 5828",
    "sg:postcode":"45806",
    "sg:province":"OH",
    "sg:tags":[
        "mobile",
        "home",
        "community"
    ],
    "wof:name":"Rosewood Mobile Home Park",
    "wof:placetype":"venue"
},
  "geometry": {"coordinates":[-84.141881,40.656889],"type":"Point"}
}