{
  "type": "Feature",
  "properties": {
    "addr:full":"8026 Garnet Ave NE Canton OH 44721",
    "addr:housenumber":"8026",
    "addr:postcode":"44721",
    "addr:street":"Garnet Ave Ne",
    "iso:country":"US",
    "sg:address":"8026 Garnet Ave NE",
    "sg:city":"Canton",
    "sg:classifiers":[
        {
            "category":"Building & Trades",
            "subcategory":"Construction",
            "type":"Services"
        }
    ],
    "sg:phone":"+1 330 305 0228",
    "sg:postcode":"44721",
    "sg:province":"OH",
    "sg:tags":[
        "house",
        "general",
        "contractor"
    ],
    "wof:name":"Mount Corrick Construction Inc",
    "wof:placetype":"venue"
},
  "geometry": {"coordinates":[-81.341804,40.900043],"type":"Point"}
}