{
  "type": "Feature",
  "properties": {
    "addr:full": "410 Forest Lake Dr Wilmington OH 45177",
    "addr:housenumber": "410",
    "addr:postcode": "45177",
    "addr:street": "Forest Lake Dr",
    "iso:country": "US",
    "sg:address": "410 Forest Lake Dr",
    "sg:city": "Wilmington",
    "sg:classifiers": [
      {
        "category": "Building \u0026 Trades",
        "subcategory": "Electrical",
        "type": "Services"
      }
    ],
    "sg:phone": "+1 937 382 0254",
    "sg:postcode": "45177",
    "sg:province": "OH",
    "sg:tags": [
      "electrical",
      "contractor"
    ],
    "wof:name": "Barker Electric",
    "wof:placetype": "venue"
  },
  "geometry": {"coordinates":[-83.861418,39.450314],"type":"Point"}
}
