{
  "type": "Feature",
  "properties": {
    "iso:country":"US",
    "sg:address":"2450 Brixton Rd",
    "sg:city":"Columbus",
    "sg:classifiers":[
        {
            "category":"Organizations",
            "subcategory":"Community Association",
            "type":"Services"
        }
    ],
    "sg:phone":"+1 614 488 1456",
    "sg:postcode":"43221",
    "sg:province":"OH",
    "wof:name":"Arlington Securities Inc",
    "wof:placetype":"venue"
},
  "geometry": {"coordinates":[-83.079956,40.012055],"type":"Point"}
}