{
  "type": "Feature",
  "properties": {
    "iso:country":"US",
    "sg:address":"337 W Exchange St",
    "sg:city":"Akron",
    "sg:classifiers":[
        {
            "category":"Shopping",
            "subcategory":"Florist",
            "type":"Retail Goods"
        }
    ],
    "sg:phone":"+1 330 535 6125",
    "sg:postcode":"44302",
    "sg:province":"OH",
    "wof:name":"C K Constantine",
    "wof:placetype":"venue"
},
  "geometry": {"coordinates":[-81.531036,41.081233],"type":"Point"}
}