{
  "type": "Feature",
  "properties": {
    "addr:full": "240 Main St Hamilton OH 45013",
    "addr:housenumber": "240",
    "addr:postcode": "45013",
    "addr:street": "Main St",
    "iso:country": "US",
    "sg:address": "240 Main St",
    "sg:city": "Hamilton",
    "sg:classifiers": [
      {
        "category": "Professional",
        "subcategory": "Employment Agencies",
        "type": "Services"
      }
    ],
    "sg:phone": "+1 513 868 3933",
    "sg:postcode": "45013",
    "sg:province": "OH",
    "sg:tags": [
      "opportunity"
    ],
    "sg:website": "www.laborready.com",
    "wof:name": "Labor Ready Inc",
    "wof:placetype": "venue"
  },
  "geometry": {"coordinates":[-84.568678,39.403639],"type":"Point"}
}
