{
  "type": "Feature",
  "properties": {
    "addr:full":"677 Miami St Akron OH 44311",
    "addr:housenumber":"677",
    "addr:postcode":"44311",
    "addr:street":"Miami St",
    "iso:country":"US",
    "sg:address":"677 Miami St",
    "sg:city":"Akron",
    "sg:classifiers":[
        {
            "category":"Wholesale",
            "subcategory":"Scrap",
            "type":"Manufacturing & Wholesale Goods"
        }
    ],
    "sg:phone":"+1 330 996 4631",
    "sg:postcode":"44311",
    "sg:province":"OH",
    "sg:tags":[
        "oil"
    ],
    "sg:website":"www.nofriction.com",
    "wof:name":"Rice Oil Environmental Svc",
    "wof:placetype":"venue"
},
  "geometry": {"coordinates":[-81.52266,41.064216],"type":"Point"}
}