{
  "type": "Feature",
  "properties": {
    "addr:full": "70 W Olentangy St Powell OH 43065",
    "addr:housenumber": "70",
    "addr:postcode": "43065",
    "addr:street": "W Olentangy St",
    "iso:country": "US",
    "sg:address": "70 W Olentangy St",
    "sg:city": "Powell",
    "sg:classifiers": [
      {
        "category": "Building \u0026 Trades",
        "subcategory": "Construction",
        "type": "Services"
      }
    ],
    "sg:phone": "+1 614 885 2400",
    "sg:postcode": "43065",
    "sg:province": "OH",
    "sg:tags": [
      "family",
      "residential",
      "builder",
      "general",
      "home",
      "contractor"
    ],
    "wof:name": "Kevin Knight \u0026 Company",
    "wof:placetype": "venue"
  },
  "geometry": {"coordinates":[-83.076876,40.158161],"type":"Point"}
}
