{
  "type": "Feature",
  "properties": {
    "addr:full":"7365 Brakeman Rd Painesville OH 44077",
    "addr:housenumber":"7365",
    "addr:postcode":"44077",
    "addr:street":"Brakeman Rd",
    "iso:country":"US",
    "sg:address":"7365 Brakeman Rd",
    "sg:city":"Painesville",
    "sg:classifiers":[
        {
            "category":"Building & Trades",
            "subcategory":"Construction",
            "type":"Services"
        }
    ],
    "sg:phone":"+1 440 254 4017",
    "sg:postcode":"44077",
    "sg:province":"OH",
    "sg:tags":[
        "house"
    ],
    "wof:name":"Vermont Colony Builders Inc",
    "wof:placetype":"venue"
},
  "geometry": {"coordinates":[-81.146264,41.666898],"type":"Point"}
}