{
  "type": "Feature",
  "properties": {
    "iso:country":"US",
    "sg:address":"548 Parkside Dr",
    "sg:city":"Akron",
    "sg:classifiers":[
        {
            "category":"Professional",
            "subcategory":"Management & Consulting",
            "type":"Services"
        }
    ],
    "sg:phone":"+1 330 388 0662",
    "sg:postcode":"44313",
    "sg:province":"OH",
    "sg:tags":[
        "marketing",
        "program"
    ],
    "wof:name":"Tango Connect",
    "wof:placetype":"venue"
},
  "geometry": {"coordinates":[-81.584895,41.130526],"type":"Point"}
}