{
  "type": "Feature",
  "properties": {
    "iso:country":"US",
    "sg:address":"1201 Nebraska Ave",
    "sg:city":"Lorain",
    "sg:classifiers":[
        {
            "category":"Education",
            "subcategory":"School",
            "type":"Public Place"
        }
    ],
    "sg:phone":"+1 440 288 3203",
    "sg:postcode":"44052",
    "sg:province":"OH",
    "wof:name":"Larkmoor Elementary School",
    "wof:placetype":"venue"
},
  "geometry": {"coordinates":[-82.143895,41.472583],"type":"Point"}
}