{
  "type": "Feature",
  "properties": {
    "addr:full": "2000 Canfield Rd Youngstown OH 44511",
    "addr:housenumber": "2000",
    "addr:postcode": "44511",
    "addr:street": "Canfield Rd",
    "iso:country": "US",
    "sg:address": "2000 Canfield Rd",
    "sg:city": "Youngstown",
    "sg:classifiers": [
      {
        "category": "Building \u0026 Trades",
        "subcategory": "Pest Control",
        "type": "Services"
      }
    ],
    "sg:phone": "+1 330 792 7927",
    "sg:postcode": "44511",
    "sg:province": "OH",
    "sg:tags": [
      "removal",
      "industrial",
      "services-commercial",
      "termite",
      "bee"
    ],
    "wof:name": "Sunny Pest Control",
    "wof:placetype": "venue"
  },
  "geometry": {"coordinates":[-80.690598,41.064861],"type":"Point"}
}
