{
  "type": "Feature",
  "properties": {
    "addr:full": "908 Dayton St Chillicothe OH 45601",
    "addr:housenumber": "908",
    "addr:postcode": "45601",
    "addr:street": "Dayton St",
    "iso:country": "US",
    "sg:address": "908 Dayton St",
    "sg:city": "Chillicothe",
    "sg:classifiers": [
      {
        "category": "Organizations",
        "subcategory": "Religious Organization",
        "type": "Services"
      }
    ],
    "sg:phone": "+1 740 773 2407",
    "sg:postcode": "45601",
    "sg:province": "OH",
    "sg:tags": [
      "church"
    ],
    "wof:name": "Landmark Church Fellowship",
    "wof:placetype": "venue"
  },
  "geometry": {"coordinates":[-82.952339,39.332782],"type":"Point"}
}
