{
  "type": "Feature",
  "properties": {
    "addr:full":"431 Charletta Dr Mansfield OH 44903",
    "addr:housenumber":"431",
    "addr:postcode":"44903",
    "addr:street":"Charletta Dr",
    "iso:country":"US",
    "sg:address":"431 Charletta Dr",
    "sg:city":"Mansfield",
    "sg:classifiers":[
        {
            "category":"Building & Trades",
            "subcategory":"Construction",
            "type":"Services"
        }
    ],
    "sg:phone":"+1 419 522 2998",
    "sg:postcode":"44903",
    "sg:province":"OH",
    "sg:tags":[
        "contractor"
    ],
    "wof:name":"Myers Mechanical Insulation",
    "wof:placetype":"venue"
},
  "geometry": {"coordinates":[-82.527709,40.865005],"type":"Point"}
}