{
  "type": "Feature",
  "properties": {
    "addr:full": "137 S Main St Bryan OH 43506",
    "addr:housenumber": "137",
    "addr:postcode": "43506",
    "addr:street": "S Main St",
    "iso:country": "US",
    "sg:address": "137 S Main St",
    "sg:city": "Bryan",
    "sg:classifiers": [
      {
        "category": "Shopping",
        "subcategory": "Clothing, Apparel, \u0026 Fashions",
        "type": "Retail Goods"
      }
    ],
    "sg:phone": "+1 419 633 7375",
    "sg:postcode": "43506",
    "sg:province": "OH",
    "wof:name": "Bridal Gallery",
    "wof:placetype": "venue"
  },
  "geometry": {"coordinates":[-84.550985,41.474118],"type":"Point"}
}
