{
  "type": "Feature",
  "properties": {
    "addr:full":"1392 High St Wadsworth OH 44281",
    "addr:housenumber":"1392",
    "addr:postcode":"44281",
    "addr:street":"High St",
    "iso:country":"US",
    "sg:address":"1392 High St",
    "sg:city":"Wadsworth",
    "sg:classifiers":[
        {
            "category":"Insurance",
            "subcategory":"Title Insurance",
            "type":"Services"
        },
        {
            "category":"Real Estate",
            "subcategory":"Real Estate Services",
            "type":"Services"
        }
    ],
    "sg:phone":"+1 330 334 5115",
    "sg:postcode":"44281",
    "sg:province":"OH",
    "sg:tags":[
        "company"
    ],
    "wof:name":"Midland Title Security Inc",
    "wof:placetype":"venue"
},
  "geometry": {"coordinates":[-81.73584099999999,41.056792],"type":"Point"}
}