{
  "type": "Feature",
  "properties": {
    "addr:full": "8224 Mentor Ave Mentor OH 44060",
    "addr:housenumber": "8224",
    "addr:postcode": "44060",
    "addr:street": "Mentor Ave",
    "iso:country": "US",
    "sg:address": "8224 Mentor Ave",
    "sg:city": "Mentor",
    "sg:classifiers": [
      {
        "category": "Government",
        "subcategory": "Office",
        "type": "Public Place"
      },
      {
        "category": "Health Services",
        "subcategory": "Doctor",
        "type": "Services"
      }
    ],
    "sg:phone": "+1 440 255 7202",
    "sg:postcode": "44060",
    "sg:province": "OH",
    "sg:tags": [
      "county",
      "pediatrics"
    ],
    "wof:name": "Lake County Pediatrics Inc",
    "wof:placetype": "venue"
  },
  "geometry": {"coordinates":[-81.345218,41.665016],"type":"Point"}
}
