{
  "type": "Feature",
  "properties": {
    "iso:country":"US",
    "sg:address":"160 W Main St",
    "sg:city":"Batavia",
    "sg:classifiers":[
        {
            "category":"Health Services",
            "subcategory":"Chiropractor",
            "type":"Services"
        }
    ],
    "sg:phone":"+1 513 732 2701",
    "sg:postcode":"45103",
    "sg:province":"OH",
    "wof:name":"Clermont Chiropractic Ctr",
    "wof:placetype":"venue"
},
  "geometry": {"coordinates":[-84.179886,39.079044],"type":"Point"}
}