{
  "type": "Feature",
  "properties": {
    "addr:full":"1 E Main St New Concord OH 43762",
    "addr:housenumber":"1",
    "addr:postcode":"43762",
    "addr:street":"E Main St",
    "iso:country":"US",
    "sg:address":"1 E Main St",
    "sg:city":"New Concord",
    "sg:classifiers":[
        {
            "category":"Social Services",
            "subcategory":"Job Training",
            "type":"Services"
        }
    ],
    "sg:phone":"+1 740 826 7155",
    "sg:postcode":"43762",
    "sg:province":"OH",
    "sg:tags":[
        "rehabilitation"
    ],
    "wof:name":"Genesis Rehab & Radiology",
    "wof:placetype":"venue"
},
  "geometry": {"coordinates":[-81.731922,39.993822],"type":"Point"}
}