{
  "type": "Feature",
  "properties": {
    "addr:full": "5355 State Rte 110 Napoleon OH 43545",
    "addr:housenumber": "5355",
    "addr:postcode": "43545",
    "addr:street": "State Rte 110",
    "iso:country": "US",
    "sg:address": "5355 State Rte 110",
    "sg:city": "Napoleon",
    "sg:phone": "+1 419 748 8380",
    "sg:postcode": "43545",
    "sg:province": "OH",
    "sg:tags": [
      "farm",
      "corn",
      "soybean"
    ],
    "wof:name": "William Smith",
    "wof:placetype": "venue"
  },
  "geometry": {"coordinates":[-83.965484,41.415057],"type":"Point"}
}
