{
  "type": "Feature",
  "properties": {
    "iso:country":"US",
    "sg:address":"4037 Washington Blvd",
    "sg:city":"Cleveland",
    "sg:classifiers":[
        {
            "category":"Shopping",
            "type":"Retail Goods"
        }
    ],
    "sg:phone":"+1 216 932 3559",
    "sg:postcode":"44118",
    "sg:province":"OH",
    "sg:tags":[
        "merchandise"
    ],
    "wof:name":"Gallery At Cain Park Village",
    "wof:placetype":"venue"
},
  "geometry": {"coordinates":[-81.53469,41.496674],"type":"Point"}
}