{
  "type": "Feature",
  "properties": {
    "addr:full": "7725 Commerce Park Oval Cleveland OH 44131",
    "addr:housenumber": "7725",
    "addr:postcode": "44131",
    "addr:street": "Commerce Park Oval",
    "iso:country": "US",
    "sg:address": "7725 Commerce Park Oval",
    "sg:city": "Cleveland",
    "sg:classifiers": [
      {
        "category": "Building \u0026 Trades",
        "subcategory": "Construction",
        "type": "Services"
      }
    ],
    "sg:phone": "+1 216 328 9322",
    "sg:postcode": "44131",
    "sg:province": "OH",
    "sg:tags": [
      "concrete",
      "contractor"
    ],
    "wof:name": "F P Allega Concrete Constr Co",
    "wof:placetype": "venue"
  },
  "geometry": {"coordinates":[-81.634774,41.395979],"type":"Point"}
}
