{
  "type": "Feature",
  "properties": {
    "iso:country":"US",
    "sg:address":"503 E Lytle-Five Points Rd",
    "sg:city":"Centerville",
    "sg:classifiers":[
        {
            "category":"Recreation",
            "type":"Entertainment"
        }
    ],
    "sg:phone":"+1 937 885 2264",
    "sg:postcode":"45458",
    "sg:province":"OH",
    "sg:tags":[
        "stable"
    ],
    "wof:name":"Clearcreek Farms",
    "wof:placetype":"venue"
},
  "geometry": {"coordinates":[-84.181659,39.568173],"type":"Point"}
}