{
  "type": "Feature",
  "properties": {
    "iso:country":"US",
    "sg:address":"927 State Rte 28",
    "sg:city":"Milford",
    "sg:classifiers":[
        {
            "category":"Food & Beverages",
            "subcategory":"Groceries & Convenience Stores",
            "type":"Retail Goods"
        }
    ],
    "sg:phone":"+1 513 831 0432",
    "sg:postcode":"45150",
    "sg:province":"OH",
    "wof:name":"Ameristop Food Mart",
    "wof:placetype":"venue"
},
  "geometry": {"coordinates":[-84.248955,39.192115],"type":"Point"}
}