{
  "type": "Feature",
  "properties": {
    "addr:full": "927 State Rte 28 Milford OH 45150",
    "addr:housenumber": "927",
    "addr:postcode": "45150",
    "addr:street": "State Rte 28",
    "iso:country": "US",
    "sg:address": "927 State Rte 28",
    "sg:city": "Milford",
    "sg:classifiers": [
      {
        "category": "Food \u0026 Beverages",
        "subcategory": "Groceries \u0026 Convenience Stores",
        "type": "Retail Goods"
      }
    ],
    "sg:phone": "+1 513 831 0432",
    "sg:postcode": "45150",
    "sg:province": "OH",
    "wof:name": "Ameristop Food Mart",
    "wof:placetype": "venue"
  },
  "geometry": {"coordinates":[-84.248955,39.192115],"type":"Point"}
}
