{
  "type": "Feature",
  "properties": {
    "iso:country":"US",
    "sg:address":"1313 Sharon Ave",
    "sg:city":"Zanesville",
    "sg:classifiers":[
        {
            "category":"Restaurant",
            "type":"Food & Drink"
        }
    ],
    "sg:phone":"+1 740 588 0571",
    "sg:postcode":"43701",
    "sg:province":"OH",
    "sg:tags":[
        "eating"
    ],
    "wof:name":"Champs Bar & Grill",
    "wof:placetype":"venue"
},
  "geometry": {"coordinates":[-81.991789,39.93503],"type":"Point"}
}