{
  "type": "Feature",
  "properties": {
    "addr:full":"1730 Hayden Ave Cleveland OH 44112",
    "addr:housenumber":"1730",
    "addr:postcode":"44112",
    "addr:street":"Hayden Ave",
    "iso:country":"US",
    "sg:address":"1730 Hayden Ave",
    "sg:city":"Cleveland",
    "sg:classifiers":[
        {
            "category":"Food & Beverages",
            "subcategory":"Groceries & Convenience Stores",
            "type":"Retail Goods"
        }
    ],
    "sg:phone":"+1 216 541 5960",
    "sg:postcode":"44112",
    "sg:province":"OH",
    "sg:tags":[
        "grocer"
    ],
    "wof:name":"Hayden Food Plus Inc",
    "wof:placetype":"venue"
},
  "geometry": {"coordinates":[-81.587604,41.53213],"type":"Point"}
}