{
  "type": "Feature",
  "properties": {
    "addr:full": "294 US Hwy 224 W Greenwich OH 44837",
    "addr:housenumber": "294",
    "addr:postcode": "44837",
    "addr:street": "Us Hwy 224 W",
    "iso:country": "US",
    "sg:address": "294 US Hwy 224 W",
    "sg:city": "Greenwich",
    "sg:classifiers": [
      {
        "category": "Building \u0026 Trades",
        "subcategory": "Electrical",
        "type": "Services"
      }
    ],
    "sg:phone": "+1 419 752 5011",
    "sg:postcode": "44837",
    "sg:province": "OH",
    "sg:tags": [
      "electrical",
      "contractor"
    ],
    "wof:name": "Stewart Electric Inc",
    "wof:placetype": "venue"
  },
  "geometry": {"coordinates":[-82.596559,41.031093],"type":"Point"}
}
