{
  "type": "Feature",
  "properties": {
    "addr:full": "517 Leeson Ave Van Wert OH 45891",
    "addr:housenumber": "517",
    "addr:postcode": "45891",
    "addr:street": "Leeson Ave",
    "iso:country": "US",
    "sg:address": "517 Leeson Ave",
    "sg:city": "Van Wert",
    "sg:classifiers": [
      {
        "category": "Building \u0026 Trades",
        "subcategory": "Plumbing",
        "type": "Services"
      }
    ],
    "sg:phone": "+1 419 238 4994",
    "sg:postcode": "45891",
    "sg:province": "OH",
    "sg:tags": [
      "plumbing",
      "heating",
      "contractor"
    ],
    "wof:name": "Schumm Plumbing \u0026 Heating Inc",
    "wof:placetype": "venue"
  },
  "geometry": {"coordinates":[-84.590788,40.866233],"type":"Point"}
}
