{
  "type": "Feature",
  "properties": {
    "addr:full": "6234 Engle Rd Cleveland OH 44142",
    "addr:housenumber": "6234",
    "addr:postcode": "44142",
    "addr:street": "Engle Rd",
    "iso:country": "US",
    "sg:address": "6234 Engle Rd",
    "sg:city": "Cleveland",
    "sg:classifiers": [
      {
        "category": "Retail",
        "subcategory": "Portrait Studio",
        "type": "Services"
      }
    ],
    "sg:phone": "+1 216 267 4600",
    "sg:postcode": "44142",
    "sg:province": "OH",
    "sg:tags": [
      "photographer"
    ],
    "wof:name": "Neldon Photographers",
    "wof:placetype": "venue"
  },
  "geometry": {"coordinates":[-81.823254,41.396894],"type":"Point"}
}
