{
  "type": "Feature",
  "properties": {
    "iso:country":"US",
    "sg:address":"1100 Gest St",
    "sg:city":"Cincinnati",
    "sg:classifiers":[
        {
            "category":"Railroad",
            "type":"Transportation"
        }
    ],
    "sg:phone":"+1 513 621 6111",
    "sg:postcode":"45203",
    "sg:province":"OH",
    "sg:website":"www.parsecinc.com",
    "wof:name":"Parsec Inc",
    "wof:placetype":"venue"
},
  "geometry": {"coordinates":[-84.53420699999999,39.106714],"type":"Point"}
}