{
  "type": "Feature",
  "properties": {
    "addr:full":"1830 Sherman Ave Cincinnati OH 45212",
    "addr:housenumber":"1830",
    "addr:postcode":"45212",
    "addr:street":"Sherman Ave",
    "iso:country":"US",
    "sg:address":"1830 Sherman Ave",
    "sg:city":"Cincinnati",
    "sg:classifiers":[
        {
            "category":"Personal",
            "type":"Services"
        },
        {
            "category":"Building & Trades",
            "subcategory":"Cleaning & Sanitation",
            "type":"Services"
        }
    ],
    "sg:phone":"+1 513 297 7714",
    "sg:postcode":"45212",
    "sg:province":"OH",
    "sg:tags":[
        "house",
        "butlers'",
        "maids'"
    ],
    "sg:website":"http://www.maids.com",
    "wof:name":"Maids Home Services",
    "wof:placetype":"venue"
},
  "geometry": {"coordinates":[-84.463538,39.161024],"type":"Point"}
}