{
  "type": "Feature",
  "properties": {
    "addr:full": "1 W Sugar St Leipsic OH 45856",
    "addr:housenumber": "1",
    "addr:postcode": "45856",
    "addr:street": "W Sugar St",
    "iso:country": "US",
    "sg:address": "1 W Sugar St",
    "sg:city": "Leipsic",
    "sg:classifiers": [
      {
        "category": "Shopping",
        "type": "Retail Goods"
      }
    ],
    "sg:phone": "+1 419 943 3870",
    "sg:postcode": "45856",
    "sg:province": "OH",
    "sg:tags": [
      "merchandise"
    ],
    "wof:name": "Shmily Gifts",
    "wof:placetype": "venue"
  },
  "geometry": {"coordinates":[-83.986475,41.103181],"type":"Point"}
}
