{
  "type": "Feature",
  "properties": {
    "addr:full": "3163 Abrams Dr Twinsburg OH 44087",
    "addr:housenumber": "3163",
    "addr:postcode": "44087",
    "addr:street": "Abrams Dr",
    "iso:country": "US",
    "sg:address": "3163 Abrams Dr",
    "sg:city": "Twinsburg",
    "sg:classifiers": [
      {
        "category": "Freight",
        "type": "Transportation"
      }
    ],
    "sg:phone": "+1 330 405 1414",
    "sg:postcode": "44087",
    "sg:province": "OH",
    "sg:tags": [
      "delivery"
    ],
    "wof:name": "S \u0026 R Services Inc",
    "wof:placetype": "venue"
  },
  "geometry": {"coordinates":[-81.422712,41.322678],"type":"Point"}
}
