{
  "type": "Feature",
  "properties": {
    "addr:full":"2037 Ontario Ave Springfield OH 45505",
    "addr:housenumber":"2037",
    "addr:postcode":"45505",
    "addr:street":"Ontario Ave",
    "iso:country":"US",
    "sg:address":"2037 Ontario Ave",
    "sg:city":"Springfield",
    "sg:classifiers":[
        {
            "category":"Retail",
            "subcategory":"Auto Repair",
            "type":"Services"
        }
    ],
    "sg:phone":"+1 937 324 3421",
    "sg:postcode":"45505",
    "sg:province":"OH",
    "sg:tags":[
        "body",
        "automobile",
        "painting"
    ],
    "wof:name":"R L Smith Body Shop",
    "wof:placetype":"venue"
},
  "geometry": {"coordinates":[-83.807614,39.898568],"type":"Point"}
}