{
  "type": "Feature",
  "properties": {
    "iso:country":"US",
    "sg:address":"8721 Colerain Ave",
    "sg:city":"Cincinnati",
    "sg:classifiers":[
        {
            "category":"Government",
            "subcategory":"Post Office",
            "type":"Public Place"
        }
    ],
    "sg:phone":"+1 513 741 8396",
    "sg:postcode":"45251",
    "sg:province":"OH",
    "sg:tags":[
        "postal",
        "us"
    ],
    "wof:name":"United States Postal Service",
    "wof:placetype":"venue"
},
  "geometry": {"coordinates":[-84.590203,39.230796],"type":"Point"}
}