{
  "type": "Feature",
  "properties": {
    "addr:full": "555 Independence Dr Medina OH 44256",
    "addr:housenumber": "555",
    "addr:postcode": "44256",
    "addr:street": "Independence Dr",
    "iso:country": "US",
    "sg:address": "555 Independence Dr",
    "sg:city": "Medina",
    "sg:classifiers": [
      {
        "category": "Government",
        "subcategory": "Police Station",
        "type": "Public Place"
      }
    ],
    "sg:phone": "+1 330 725 0028",
    "sg:postcode": "44256",
    "sg:province": "OH",
    "sg:tags": [
      "department",
      "school",
      "executive"
    ],
    "sg:website": "www.medinasheriff.com",
    "wof:name": "Medina County Sheriff's Office",
    "wof:placetype": "venue"
  },
  "geometry": {"coordinates":[-81.888281,41.126841],"type":"Point"}
}
