{
  "type": "Feature",
  "properties": {
    "addr:full":"560 Tioga Trl Willoughby OH 44094",
    "addr:housenumber":"560",
    "addr:postcode":"44094",
    "addr:street":"Tioga Trl",
    "iso:country":"US",
    "sg:address":"560 Tioga Trl",
    "sg:city":"Willoughby",
    "sg:classifiers":[
        {
            "category":"Building & Trades",
            "subcategory":"Construction",
            "type":"Services"
        }
    ],
    "sg:phone":"+1 440 946 6418",
    "sg:postcode":"44094",
    "sg:province":"OH",
    "sg:tags":[
        "concrete",
        "contractor"
    ],
    "wof:name":"Wheeler & Son Cement Contrs",
    "wof:placetype":"venue"
},
  "geometry": {"coordinates":[-81.39085900000001,41.704533],"type":"Point"}
}