{
  "type": "Feature",
  "properties": {
    "iso:country":"US",
    "sg:address":"8245 Vore Ridge Rd",
    "sg:city":"Athens",
    "sg:classifiers":[
        {
            "category":"Arts & Performance",
            "subcategory":"Theater",
            "type":"Entertainment"
        }
    ],
    "sg:phone":"+1 740 594 7160",
    "sg:postcode":"45701",
    "sg:province":"OH",
    "sg:tags":[
        "live",
        "music"
    ],
    "wof:name":"Derek Shoemaker Disc Jockey",
    "wof:placetype":"venue"
},
  "geometry": {"coordinates":[-82.136912,39.33664],"type":"Point"}
}