{
  "type": "Feature",
  "properties": {
    "addr:full": "2704 W 40th St Lorain OH 44053",
    "addr:housenumber": "2704",
    "addr:postcode": "44053",
    "addr:street": "W 40Th St",
    "iso:country": "US",
    "sg:address": "2704 W 40th St",
    "sg:city": "Lorain",
    "sg:classifiers": [
      {
        "category": "Freight",
        "type": "Transportation"
      }
    ],
    "sg:phone": "+1 440 282 1734",
    "sg:postcode": "44053",
    "sg:province": "OH",
    "sg:tags": [
      "delivery"
    ],
    "wof:name": "Aarruns To Run",
    "wof:placetype": "venue"
  },
  "geometry": {"coordinates":[-82.21163,41.434365],"type":"Point"}
}
