{
  "type": "Feature",
  "properties": {
    "iso:country":"US",
    "sg:address":"3250 Barber Rd",
    "sg:city":"Norton",
    "sg:classifiers":[
        {
            "category":"Manufacturing",
            "subcategory":"Tools & Machinery",
            "type":"Manufacturing & Wholesale Goods"
        }
    ],
    "sg:phone":"+1 330 745 6000",
    "sg:postcode":"44203",
    "sg:province":"OH",
    "sg:tags":[
        "pump"
    ],
    "sg:website":"www.nelsencorp.com",
    "wof:name":"Nelsen Corp",
    "wof:placetype":"venue"
},
  "geometry": {"coordinates":[-81.60886499999999,41.036718],"type":"Point"}
}