{
  "type": "Feature",
  "properties": {
    "addr:full": "3250 Barber Rd Norton OH 44203",
    "addr:housenumber": "3250",
    "addr:postcode": "44203",
    "addr:street": "Barber Rd",
    "iso:country": "US",
    "sg:address": "3250 Barber Rd",
    "sg:city": "Norton",
    "sg:classifiers": [
      {
        "category": "Manufacturing",
        "subcategory": "Tools \u0026 Machinery",
        "type": "Manufacturing \u0026 Wholesale Goods"
      }
    ],
    "sg:phone": "+1 330 745 6000",
    "sg:postcode": "44203",
    "sg:province": "OH",
    "sg:tags": [
      "pump"
    ],
    "sg:website": "www.nelsencorp.com",
    "wof:name": "Nelsen Corp",
    "wof:placetype": "venue"
  },
  "geometry": {"coordinates":[-81.608865,41.036718],"type":"Point"}
}
