{
  "type": "Feature",
  "properties": {
    "addr:full":"3923 Beechgrove Rd Bucyrus OH 44820",
    "addr:housenumber":"3923",
    "addr:postcode":"44820",
    "addr:street":"Beechgrove Rd",
    "iso:country":"US",
    "sg:address":"3923 Beechgrove Rd",
    "sg:city":"Bucyrus",
    "sg:classifiers":[
        {
            "category":"Food & Beverages",
            "subcategory":"Specialty",
            "type":"Retail Goods"
        }
    ],
    "sg:phone":"+1 419 562 0383",
    "sg:postcode":"44820",
    "sg:province":"OH",
    "wof:name":"Watkins Products",
    "wof:placetype":"venue"
},
  "geometry": {"coordinates":[-82.940172,40.848802],"type":"Point"}
}