{
  "type": "Feature",
  "properties": {
    "addr:full": "9415 Auburn Rd Chardon OH 44024",
    "addr:housenumber": "9415",
    "addr:postcode": "44024",
    "addr:street": "Auburn Rd",
    "iso:country": "US",
    "sg:address": "9415 Auburn Rd",
    "sg:city": "Chardon",
    "sg:classifiers": [
      {
        "category": "Professional",
        "subcategory": "Management \u0026 Consulting",
        "type": "Services"
      }
    ],
    "sg:phone": "+1 440 286 1876",
    "sg:postcode": "44024",
    "sg:province": "OH",
    "sg:tags": [
      "consultant",
      "energy",
      "conservation"
    ],
    "wof:name": "Energy First Group Inc",
    "wof:placetype": "venue"
  },
  "geometry": {"coordinates":[-81.242833,41.615781],"type":"Point"}
}
