{
  "type": "Feature",
  "properties": {
    "addr:full":"4684 Industry Dr Fairfield OH 45014",
    "addr:housenumber":"4684",
    "addr:postcode":"45014",
    "addr:street":"Industry Dr",
    "iso:country":"US",
    "sg:address":"4684 Industry Dr",
    "sg:city":"Fairfield",
    "sg:classifiers":[
        {
            "category":"Professional",
            "subcategory":"Management & Consulting",
            "type":"Services"
        }
    ],
    "sg:phone":"+1 513 939 0146",
    "sg:postcode":"45014",
    "sg:province":"OH",
    "sg:tags":[
        "party",
        "planning"
    ],
    "wof:name":"Creative 3-D",
    "wof:placetype":"venue"
},
  "geometry": {"coordinates":[-84.531156,39.348867],"type":"Point"}
}