{
  "type": "Feature",
  "properties": {
    "iso:country":"US",
    "sg:address":"552 Treadway Blvd",
    "sg:city":"Sheffield Lake",
    "sg:classifiers":[
        {
            "category":"Manufacturing",
            "subcategory":"Tools & Machinery",
            "type":"Manufacturing & Wholesale Goods"
        }
    ],
    "sg:phone":"+1 440 949 6796",
    "sg:postcode":"44054",
    "sg:province":"OH",
    "sg:tags":[
        "mfg"
    ],
    "wof:name":"Schuller Electric Co",
    "wof:placetype":"venue"
},
  "geometry": {"coordinates":[-82.090938,41.490623],"type":"Point"}
}