{
  "type": "Feature",
  "properties": {
    "iso:country":"US",
    "sg:address":"1080 N Bridge St",
    "sg:city":"Chillicothe",
    "sg:classifiers":[
        {
            "category":"Retail",
            "subcategory":"Self-service Laundry",
            "type":"Services"
        }
    ],
    "sg:phone":"+1 740 775 9582",
    "sg:postcode":"45601",
    "sg:province":"OH",
    "wof:name":"Quick Clean Laundry",
    "wof:placetype":"venue"
},
  "geometry": {"coordinates":[-82.97675,39.348247],"type":"Point"}
}