{
  "type": "Feature",
  "properties": {
    "iso:country":"US",
    "sg:address":"13458 Twp Rd 115",
    "sg:city":"Kenton",
    "sg:classifiers":[
        {
            "category":"Real Estate",
            "subcategory":"Real Estate Operator",
            "type":"Services"
        }
    ],
    "sg:phone":"+1 419 675 1021",
    "sg:postcode":"43326",
    "sg:province":"OH",
    "sg:tags":[
        "property",
        "lessor"
    ],
    "wof:name":"Justin Curl",
    "wof:placetype":"venue"
},
  "geometry": {"coordinates":[-83.681693,40.623397],"type":"Point"}
}