{
  "type": "Feature",
  "properties": {
    "iso:country":"US",
    "sg:address":"6173 Mount Gilead Waterford Rd",
    "sg:city":"Mt Gilead",
    "sg:classifiers":[
        {
            "category":"Autos & Motor Vehicles",
            "subcategory":"Fuel & Gas Station",
            "type":"Retail Goods"
        }
    ],
    "sg:phone":"+1 419 768 3359",
    "sg:postcode":"43338",
    "sg:province":"OH",
    "sg:tags":[
        "oil"
    ],
    "wof:name":"Duke Travel Plaza",
    "wof:placetype":"venue"
},
  "geometry": {"coordinates":[-82.716852,40.562792],"type":"Point"}
}