{
  "type": "Feature",
  "properties": {
    "addr:full": "6173 Mount Gilead Waterford Rd Mt Gilead OH 43338",
    "addr:housenumber": "6173",
    "addr:postcode": "43338",
    "addr:street": "Mount Gilead Waterford Rd",
    "iso:country": "US",
    "sg:address": "6173 Mount Gilead Waterford Rd",
    "sg:city": "Mt Gilead",
    "sg:classifiers": [
      {
        "category": "Autos \u0026 Motor Vehicles",
        "subcategory": "Fuel \u0026 Gas Station",
        "type": "Retail Goods"
      }
    ],
    "sg:phone": "+1 419 768 3359",
    "sg:postcode": "43338",
    "sg:province": "OH",
    "sg:tags": [
      "oil"
    ],
    "wof:name": "Duke Travel Plaza",
    "wof:placetype": "venue"
  },
  "geometry": {"coordinates":[-82.716852,40.562792],"type":"Point"}
}
