{
  "type": "Feature",
  "properties": {
    "addr:full": "859 State Rte 83 Beverly OH 45715",
    "addr:housenumber": "859",
    "addr:postcode": "45715",
    "addr:street": "State Rte 83",
    "iso:country": "US",
    "sg:address": "859 State Rte 83",
    "sg:city": "Beverly",
    "sg:classifiers": [
      {
        "category": "Building \u0026 Trades",
        "subcategory": "Plumbing",
        "type": "Services"
      }
    ],
    "sg:phone": "+1 740 984 3100",
    "sg:postcode": "45715",
    "sg:province": "OH",
    "sg:tags": [
      "product",
      "management",
      "energy",
      "system"
    ],
    "wof:name": "Duke Energy North America",
    "wof:placetype": "venue"
  },
  "geometry": {"coordinates":[-81.654559,39.614781],"type":"Point"}
}
