{
  "type": "Feature",
  "properties": {
    "iso:country":"US",
    "sg:address":"859 State Rte 83",
    "sg:city":"Beverly",
    "sg:classifiers":[
        {
            "category":"Building & Trades",
            "subcategory":"Plumbing",
            "type":"Services"
        }
    ],
    "sg:phone":"+1 740 984 3100",
    "sg:postcode":"45715",
    "sg:province":"OH",
    "sg:tags":[
        "product",
        "management",
        "energy",
        "system"
    ],
    "wof:name":"Duke Energy North America",
    "wof:placetype":"venue"
},
  "geometry": {"coordinates":[-81.65455900000001,39.614781],"type":"Point"}
}