{
  "type": "Feature",
  "properties": {
    "addr:full": "1224 Alton Darby Creek Rd Columbus OH 43228",
    "addr:housenumber": "1224",
    "addr:postcode": "43228",
    "addr:street": "Alton Darby Creek Rd",
    "iso:country": "US",
    "sg:address": "1224 Alton Darby Creek Rd",
    "sg:city": "Columbus",
    "sg:classifiers": [
      {
        "category": "Farming",
        "subcategory": "Farm \u0026 Veterinary Services",
        "type": "Manufacturing \u0026 Wholesale Goods"
      }
    ],
    "sg:phone": "+1 614 335 0020",
    "sg:postcode": "43228",
    "sg:province": "OH",
    "sg:tags": [
      "breeder",
      "livestock"
    ],
    "wof:name": "Ayrshire Breeders' Assn",
    "wof:placetype": "venue"
  },
  "geometry": {"coordinates":[-83.177128,39.977924],"type":"Point"}
}
