{
  "type": "Feature",
  "properties": {
    "addr:full": "3630 Washington Blvd Cleveland OH 44118",
    "addr:housenumber": "3630",
    "addr:postcode": "44118",
    "addr:street": "Washington Blvd",
    "iso:country": "US",
    "sg:address": "3630 Washington Blvd",
    "sg:city": "Cleveland",
    "sg:classifiers": [
      {
        "category": "Building \u0026 Trades",
        "subcategory": "Pest Control",
        "type": "Services"
      }
    ],
    "sg:phone": "+1 216 381 5329",
    "sg:postcode": "44118",
    "sg:province": "OH",
    "wof:name": "Critter Gitter",
    "wof:placetype": "venue"
  },
  "geometry": {"coordinates":[-81.54882,41.502576],"type":"Point"}
}
