{
  "type": "Feature",
  "properties": {
    "iso:country":"US",
    "sg:address":"3630 Washington Blvd",
    "sg:city":"Cleveland",
    "sg:classifiers":[
        {
            "category":"Building & Trades",
            "subcategory":"Pest Control",
            "type":"Services"
        }
    ],
    "sg:phone":"+1 216 381 5329",
    "sg:postcode":"44118",
    "sg:province":"OH",
    "wof:name":"Critter Gitter",
    "wof:placetype":"venue"
},
  "geometry": {"coordinates":[-81.54882000000001,41.502576],"type":"Point"}
}