{
  "type": "Feature",
  "properties": {
    "addr:full": "5094 Co Rd 120 Millersburg OH 44654",
    "addr:housenumber": "5094",
    "addr:postcode": "44654",
    "addr:street": "Co Rd 120",
    "iso:country": "US",
    "sg:address": "5094 Co Rd 120",
    "sg:city": "Millersburg",
    "sg:classifiers": [
      {
        "category": "Wholesale",
        "subcategory": "Painting Supplies",
        "type": "Manufacturing \u0026 Wholesale Goods"
      }
    ],
    "sg:phone": "+1 330 893 2725",
    "sg:postcode": "44654",
    "sg:province": "OH",
    "wof:name": "Paints \u0026 Solvents",
    "wof:placetype": "venue"
  },
  "geometry": {"coordinates":[-81.799524,40.552287],"type":"Point"}
}
