{
  "type": "Feature",
  "properties": {
    "iso:country":"US",
    "sg:address":"5094 Co Rd 120",
    "sg:city":"Millersburg",
    "sg:classifiers":[
        {
            "category":"Wholesale",
            "subcategory":"Painting Supplies",
            "type":"Manufacturing & Wholesale Goods"
        }
    ],
    "sg:phone":"+1 330 893 2725",
    "sg:postcode":"44654",
    "sg:province":"OH",
    "wof:name":"Paints & Solvents",
    "wof:placetype":"venue"
},
  "geometry": {"coordinates":[-81.79952400000001,40.552287],"type":"Point"}
}