{
  "type": "Feature",
  "properties": {
    "addr:full": "100 Mall Dr Steubenville OH 43952",
    "addr:housenumber": "100",
    "addr:postcode": "43952",
    "addr:street": "Mall Dr",
    "iso:country": "US",
    "sg:address": "100 Mall Dr",
    "sg:city": "Steubenville",
    "sg:classifiers": [
      {
        "category": "Building \u0026 Trades",
        "subcategory": "Construction",
        "type": "Services"
      }
    ],
    "sg:phone": "+1 740 266 2377",
    "sg:postcode": "43952",
    "sg:province": "OH",
    "sg:tags": [
      "house"
    ],
    "wof:name": "Rycon Construction Inc",
    "wof:placetype": "venue"
  },
  "geometry": {"coordinates":[-80.670645,40.371089],"type":"Point"}
}
