{
  "type": "Feature",
  "properties": {
    "iso:country":"US",
    "sg:address":"275 Springside Dr",
    "sg:city":"Akron",
    "sg:classifiers":[
        {
            "category":"Insurance",
            "subcategory":"Insurance Agent",
            "type":"Services"
        }
    ],
    "sg:phone":"+1 330 666 2199",
    "sg:postcode":"44333",
    "sg:province":"OH",
    "sg:website":"www.libertymutual.com",
    "wof:name":"Liberty Mutual Insurance",
    "wof:placetype":"venue"
},
  "geometry": {"coordinates":[-81.641983,41.142006],"type":"Point"}
}