{
  "type": "Feature",
  "properties": {
    "addr:full": "6100 Beechcroft Rd Columbus OH 43229",
    "addr:postcode": "6100;43229",
    "addr:street": "Beechcroft Rd",
    "iso:country": "US",
    "sg:address": "6100 Beechcroft Rd",
    "sg:city": "Columbus",
    "sg:classifiers": [
      {
        "category": "Education",
        "subcategory": "School",
        "type": "Public Place"
      }
    ],
    "sg:phone": "+1 614 365 5364",
    "sg:postcode": "43229",
    "sg:province": "OH",
    "sg:tags": [
      "high"
    ],
    "sg:website": "www.columbus.k12.oh.us",
    "wof:name": "Beechcroft High School",
    "wof:placetype": "venue"
  },
  "geometry": {"coordinates":[-82.964147,40.091277],"type":"Point"}
}
