{
  "type": "Feature",
  "properties": {
    "addr:full": "30 Public Sq Mt Vernon OH 43050",
    "addr:housenumber": "30",
    "addr:postcode": "43050",
    "addr:street": "Public Sq",
    "iso:country": "US",
    "sg:address": "30 Public Sq",
    "sg:city": "Mt Vernon",
    "sg:classifiers": [
      {
        "category": "Personal",
        "subcategory": "Barber",
        "type": "Services"
      }
    ],
    "sg:phone": "+1 740 392 2096",
    "sg:postcode": "43050",
    "sg:province": "OH",
    "wof:name": "Family Barber Shop",
    "wof:placetype": "venue"
  },
  "geometry": {"coordinates":[-82.485566,40.394079],"type":"Point"}
}
