{
  "type": "Feature",
  "properties": {
    "iso:country":"US",
    "sg:address":"30 Public Sq",
    "sg:city":"Mt Vernon",
    "sg:classifiers":[
        {
            "category":"Personal",
            "subcategory":"Barber",
            "type":"Services"
        }
    ],
    "sg:phone":"+1 740 392 2096",
    "sg:postcode":"43050",
    "sg:province":"OH",
    "wof:name":"Family Barber Shop",
    "wof:placetype":"venue"
},
  "geometry": {"coordinates":[-82.48556600000001,40.394079],"type":"Point"}
}