{
  "type": "Feature",
  "properties": {
    "addr:full":"12 N 3rd St Waterville OH 43566",
    "addr:housenumber":"12",
    "addr:postcode":"43566",
    "addr:street":"N 3Rd St",
    "iso:country":"US",
    "sg:address":"12 N 3rd St",
    "sg:city":"Waterville",
    "sg:classifiers":[
        {
            "category":"Restaurant",
            "type":"Food & Drink"
        }
    ],
    "sg:phone":"+1 419 878 7007",
    "sg:postcode":"43566",
    "sg:province":"OH",
    "wof:name":"Koral Hamburger",
    "wof:placetype":"venue"
},
  "geometry": {"coordinates":[-83.719632,41.500513],"type":"Point"}
}