{
  "type": "Feature",
  "properties": {
    "iso:country":"US",
    "sg:address":"90 Hidden Ravines Dr",
    "sg:city":"Powell",
    "sg:classifiers":[
        {
            "category":"Organizations",
            "subcategory":"Religious Organization",
            "type":"Services"
        }
    ],
    "sg:phone":"+1 740 548 5323",
    "sg:postcode":"43065",
    "sg:province":"OH",
    "sg:tags":[
        "church"
    ],
    "wof:name":"Cornerstone Community Church",
    "wof:placetype":"venue"
},
  "geometry": {"coordinates":[-83.021111,40.170563],"type":"Point"}
}