{
  "type": "Feature",
  "properties": {
    "addr:full":"2272 Romig Rd Akron OH 44320",
    "addr:housenumber":"2272",
    "addr:postcode":"44320",
    "addr:street":"Romig Rd",
    "iso:country":"US",
    "sg:address":"2272 Romig Rd",
    "sg:city":"Akron",
    "sg:classifiers":[
        {
            "category":"Home & Garden",
            "subcategory":"Furniture",
            "type":"Retail Goods"
        }
    ],
    "sg:phone":"+1 330 848 7600",
    "sg:postcode":"44320",
    "sg:province":"OH",
    "wof:name":"Furniture & Mattress Lqdtrs",
    "wof:placetype":"venue"
},
  "geometry": {"coordinates":[-81.58156700000001,41.059276],"type":"Point"}
}