{
  "type": "Feature",
  "properties": {
    "addr:full":"205 N Wheeler St Mt Victory OH 43340",
    "addr:housenumber":"205",
    "addr:postcode":"43340",
    "addr:street":"N Wheeler St",
    "iso:country":"US",
    "sg:address":"205 N Wheeler St",
    "sg:city":"Mt Victory",
    "sg:classifiers":[
        {
            "category":"Shopping",
            "subcategory":"Used Merchandise",
            "type":"Retail Goods"
        }
    ],
    "sg:phone":"+1 937 354 4000",
    "sg:postcode":"43340",
    "sg:province":"OH",
    "sg:tags":[
        "antique"
    ],
    "wof:name":"Tiffany's",
    "wof:placetype":"venue"
},
  "geometry": {"coordinates":[-83.515766,40.53752],"type":"Point"}
}