{
  "type": "Feature",
  "properties": {
    "addr:full": "3156 Country Club Dr Medina OH 44256",
    "addr:housenumber": "3156",
    "addr:postcode": "44256",
    "addr:street": "Country Club Dr",
    "iso:country": "US",
    "sg:address": "3156 Country Club Dr",
    "sg:city": "Medina",
    "sg:classifiers": [
      {
        "category": "Professional",
        "subcategory": "Computer Services",
        "type": "Services"
      }
    ],
    "sg:phone": "+1 330 723 7072",
    "sg:postcode": "44256",
    "sg:province": "OH",
    "sg:tags": [
      "consultant",
      "designer"
    ],
    "wof:name": "Wormwhole Productions",
    "wof:placetype": "venue"
  },
  "geometry": {"coordinates":[-81.809702,41.125043],"type":"Point"}
}
