{
  "type": "Feature",
  "properties": {
    "iso:country":"US",
    "sg:address":"644 Woodland Ave",
    "sg:city":"Toledo",
    "sg:classifiers":[
        {
            "category":"Social Services",
            "subcategory":"Child Care",
            "type":"Services"
        }
    ],
    "sg:phone":"+1 419 244 8266",
    "sg:postcode":"43604",
    "sg:province":"OH",
    "wof:name":"Tracy's Day Care",
    "wof:placetype":"venue"
},
  "geometry": {"coordinates":[-83.561662,41.652121],"type":"Point"}
}