{
  "type": "Feature",
  "properties": {
    "iso:country":"US",
    "sg:address":"4130 Bradley Rd",
    "sg:city":"Cleveland",
    "sg:classifiers":[
        {
            "category":"Autos & Motor Vehicles",
            "subcategory":"Auto Supplies",
            "type":"Retail Goods"
        }
    ],
    "sg:phone":"+1 216 749 4336",
    "sg:postcode":"44109",
    "sg:province":"OH",
    "sg:tags":[
        "filter",
        "gas"
    ],
    "wof:name":"Multi Tec Filters",
    "wof:placetype":"venue"
},
  "geometry": {"coordinates":[-81.67839600000001,41.440752],"type":"Point"}
}