{
  "type": "Feature",
  "properties": {
    "addr:full":"4850 E Main St Columbus OH 43213",
    "addr:housenumber":"4850",
    "addr:postcode":"43213",
    "addr:street":"E Main St",
    "iso:country":"US",
    "sg:address":"4850 E Main St",
    "sg:city":"Columbus",
    "sg:classifiers":[
        {
            "category":"Health Services",
            "subcategory":"Doctor",
            "type":"Services"
        }
    ],
    "sg:phone":"+1 614 566 0950",
    "sg:postcode":"43213",
    "sg:province":"OH",
    "sg:tags":[
        "physician",
        "family",
        "practice",
        "surgeons",
        "medicine",
        "surgeon"
    ],
    "wof:name":"Grant Family Practice",
    "wof:placetype":"venue"
},
  "geometry": {"coordinates":[-82.869079,39.955243],"type":"Point"}
}