{
  "type": "Feature",
  "properties": {
    "addr:full":"8877 Kings Orchard Trail Chagrin Falls OH 44023",
    "addr:housenumber":"8877",
    "addr:postcode":"44023",
    "addr:street":"Kings Orchard Trail",
    "iso:country":"US",
    "sg:address":"8877 Kings Orchard Trail",
    "sg:city":"Chagrin Falls",
    "sg:classifiers":[
        {
            "category":"Shopping",
            "subcategory":"Pets & Pet Supplies",
            "type":"Retail Goods"
        }
    ],
    "sg:phone":"+1 440 724 0531",
    "sg:postcode":"44023",
    "sg:province":"OH",
    "sg:tags":[
        "training"
    ],
    "sg:website":"www.bfftrainer.com",
    "wof:name":"B.F.F. Best Friends Forever",
    "wof:placetype":"venue"
},
  "geometry": {"coordinates":[-81.32382,41.401453],"type":"Point"}
}