{
  "type": "Feature",
  "properties": {
    "addr:full":"15051 White Rd Middlefield OH 44062",
    "addr:housenumber":"15051",
    "addr:postcode":"44062",
    "addr:street":"White Rd",
    "iso:country":"US",
    "sg:address":"15051 White Rd",
    "sg:city":"Middlefield",
    "sg:classifiers":[
        {
            "category":"Freight",
            "type":"Transportation"
        }
    ],
    "sg:phone":"+1 440 834 8588",
    "sg:postcode":"44062",
    "sg:province":"OH",
    "sg:tags":[
        "hauling",
        "trucking"
    ],
    "wof:name":"Diversified Carriers",
    "wof:placetype":"venue"
},
  "geometry": {"coordinates":[-81.108625,41.458239],"type":"Point"}
}