{
  "type": "Feature",
  "properties": {
    "addr:full": "23114 Mermill Rd Custar OH 43511",
    "addr:postcode": "23114;43511",
    "addr:street": "Mermill Rd",
    "iso:country": "US",
    "sg:address": "23114 Mermill Rd",
    "sg:city": "Custar",
    "sg:phone": "+1 419 669 2385",
    "sg:postcode": "43511",
    "sg:province": "OH",
    "sg:tags": [
      "farm",
      "corn",
      "wheat",
      "soybean"
    ],
    "wof:name": "Tim Fintel",
    "wof:placetype": "venue"
  },
  "geometry": {"coordinates":[-83.85292,41.299345],"type":"Point"}
}
