{
  "type": "Feature",
  "properties": {
    "addr:full": "1176 Milan Ave Amherst OH 44001",
    "addr:housenumber": "1176",
    "addr:postcode": "44001",
    "addr:street": "Milan Ave",
    "iso:country": "US",
    "sg:address": "1176 Milan Ave",
    "sg:city": "Amherst",
    "sg:classifiers": [
      {
        "category": "Personal",
        "subcategory": "Beauty Salon",
        "type": "Services"
      }
    ],
    "sg:phone": "+1 440 988 5603",
    "sg:postcode": "44001",
    "sg:province": "OH",
    "wof:name": "A Beau Monde Salon",
    "wof:placetype": "venue"
  },
  "geometry": {"coordinates":[-82.251008,41.398555],"type":"Point"}
}
