{
  "type": "Feature",
  "properties": {
    "iso:country":"US",
    "sg:address":"280 E 320th St",
    "sg:city":"Willoughby",
    "sg:classifiers":[
        {
            "category":"Organizations",
            "subcategory":"Non-profit Organization",
            "type":"Services"
        }
    ],
    "sg:phone":"+1 440 585 5950",
    "sg:postcode":"44095",
    "sg:province":"OH",
    "sg:tags":[
        "social"
    ],
    "wof:name":"Ohio Assoc of Deaf Inc",
    "wof:placetype":"venue"
},
  "geometry": {"coordinates":[-81.463869,41.644144],"type":"Point"}
}