{
  "type": "Feature",
  "properties": {
    "addr:full": "3819 State Rte 39 Millersburg OH 44654",
    "addr:housenumber": "3819",
    "addr:postcode": "44654",
    "addr:street": "State Rte 39",
    "iso:country": "US",
    "sg:address": "3819 State Rte 39",
    "sg:city": "Millersburg",
    "sg:classifiers": [
      {
        "category": "Shopping",
        "subcategory": "Discount \u0026 Variety Stores",
        "type": "Retail Goods"
      }
    ],
    "sg:phone": "+1 330 893 2624",
    "sg:postcode": "44654",
    "sg:province": "OH",
    "wof:name": "Henry R Miller",
    "wof:placetype": "venue"
  },
  "geometry": {"coordinates":[-81.760802,40.546126],"type":"Point"}
}
