{
  "type": "Feature",
  "properties": {
    "iso:country":"US",
    "sg:address":"2230 Heller Dr",
    "sg:city":"Dayton",
    "sg:classifiers":[
        {
            "category":"Wholesale",
            "subcategory":"Auto Parts",
            "type":"Manufacturing & Wholesale Goods"
        }
    ],
    "sg:phone":"+1 937 427 7661",
    "sg:postcode":"45434",
    "sg:province":"OH",
    "sg:tags":[
        "automobile",
        "supply"
    ],
    "wof:name":"One Stop Auto Dealer Supply",
    "wof:placetype":"venue"
},
  "geometry": {"coordinates":[-84.0107,39.705098],"type":"Point"}
}