{
  "type": "Feature",
  "properties": {
    "addr:full":"995 E Lincoln Ave Columbus OH 43229",
    "addr:housenumber":"995",
    "addr:postcode":"43229",
    "addr:street":"E Lincoln Ave",
    "iso:country":"US",
    "sg:address":"995 E Lincoln Ave",
    "sg:city":"Columbus",
    "sg:classifiers":[
        {
            "category":"Home & Garden",
            "subcategory":"Building Materials",
            "type":"Retail Goods"
        }
    ],
    "sg:phone":"+1 614 846 8396",
    "sg:postcode":"43229",
    "sg:province":"OH",
    "sg:tags":[
        "house"
    ],
    "wof:name":"D & J Cement Contrs",
    "wof:placetype":"venue"
},
  "geometry": {"coordinates":[-82.993132,40.075469],"type":"Point"}
}