{
  "type": "Feature",
  "properties": {
    "addr:full": "5515 Scioto Darby Rd Hilliard OH 43026",
    "addr:housenumber": "5515",
    "addr:postcode": "43026",
    "addr:street": "Scioto Darby Rd",
    "iso:country": "US",
    "sg:address": "5515 Scioto Darby Rd",
    "sg:city": "Hilliard",
    "sg:classifiers": [
      {
        "category": "Health Services",
        "subcategory": "Doctor",
        "type": "Services"
      }
    ],
    "sg:phone": "+1 614 876 4224",
    "sg:postcode": "43026",
    "sg:province": "OH",
    "sg:tags": [
      "dentist"
    ],
    "wof:name": "Daniel L Rankin DDS",
    "wof:placetype": "venue"
  },
  "geometry": {"coordinates":[-83.16283,40.029681],"type":"Point"}
}
