{
  "type": "Feature",
  "properties": {
    "addr:full": "26 Erie St S Massillon OH 44646",
    "addr:housenumber": "26",
    "addr:postcode": "44646",
    "addr:street": "Erie St S",
    "iso:country": "US",
    "sg:address": "26 Erie St S",
    "sg:city": "Massillon",
    "sg:classifiers": [
      {
        "category": "Professional",
        "subcategory": "Lawyer \u0026 Legal Services",
        "type": "Services"
      }
    ],
    "sg:phone": "+1 330 832 5999",
    "sg:postcode": "44646",
    "sg:province": "OH",
    "sg:tags": [
      "attorney"
    ],
    "wof:name": "Christoff \u0026 Christoff Law Ofcs",
    "wof:placetype": "venue"
  },
  "geometry": {"coordinates":[-81.523051,40.796401],"type":"Point"}
}
