{
  "type": "Feature",
  "properties": {
    "addr:full":"1523 Lafayette Ave Middletown OH 45044",
    "addr:housenumber":"1523",
    "addr:postcode":"45044",
    "addr:street":"Lafayette Ave",
    "iso:country":"US",
    "sg:address":"1523 Lafayette Ave",
    "sg:city":"Middletown",
    "sg:classifiers":[
        {
            "category":"Organizations",
            "subcategory":"Community Association",
            "type":"Services"
        }
    ],
    "sg:phone":"+1 513 424 9371",
    "sg:postcode":"45044",
    "sg:province":"OH",
    "sg:tags":[
        "club"
    ],
    "wof:name":"Meadowlawn Social Club",
    "wof:placetype":"venue"
},
  "geometry": {"coordinates":[-84.40007,39.493103],"type":"Point"}
}