{
  "type": "Feature",
  "properties": {
    "iso:country":"US",
    "sg:address":"19675 Sheldon Rd",
    "sg:city":"Cleveland",
    "sg:classifiers":[
        {
            "category":"Mining & Drilling",
            "type":"Manufacturing & Wholesale Goods"
        }
    ],
    "sg:phone":"+1 216 676 5949",
    "sg:postcode":"44130",
    "sg:province":"OH",
    "sg:tags":[
        "consulting",
        "nonmetallic",
        "business",
        "mineral"
    ],
    "wof:name":"Dans Dry Dock & Storage",
    "wof:placetype":"venue"
},
  "geometry": {"coordinates":[-81.83890700000001,41.389203],"type":"Point"}
}