{
  "type": "Feature",
  "properties": {
    "addr:full": "19675 Sheldon Rd Cleveland OH 44130",
    "addr:housenumber": "19675",
    "addr:postcode": "44130",
    "addr:street": "Sheldon Rd",
    "iso:country": "US",
    "sg:address": "19675 Sheldon Rd",
    "sg:city": "Cleveland",
    "sg:classifiers": [
      {
        "category": "Mining \u0026 Drilling",
        "type": "Manufacturing \u0026 Wholesale Goods"
      }
    ],
    "sg:phone": "+1 216 676 5949",
    "sg:postcode": "44130",
    "sg:province": "OH",
    "sg:tags": [
      "consulting",
      "nonmetallic",
      "business",
      "mineral"
    ],
    "wof:name": "Dans Dry Dock \u0026 Storage",
    "wof:placetype": "venue"
  },
  "geometry": {"coordinates":[-81.838907,41.389203],"type":"Point"}
}
