{
  "type": "Feature",
  "properties": {
    "iso:country":"US",
    "sg:address":"7150 Ragland Rd",
    "sg:city":"Cincinnati",
    "sg:classifiers":[
        {
            "category":"Insurance",
            "subcategory":"Insurance Agent",
            "type":"Services"
        }
    ],
    "sg:phone":"+1 513 561 9489",
    "sg:postcode":"45244",
    "sg:province":"OH",
    "sg:tags":[
        "agency"
    ],
    "wof:name":"Agency Development Corp",
    "wof:placetype":"venue"
},
  "geometry": {"coordinates":[-84.353955,39.114802],"type":"Point"}
}