{
  "type": "Feature",
  "properties": {
    "addr:full": "552 N Lake St Madison OH 44057",
    "addr:housenumber": "552",
    "addr:postcode": "44057",
    "addr:street": "N Lake St",
    "iso:country": "US",
    "sg:address": "552 N Lake St",
    "sg:city": "Madison",
    "sg:classifiers": [
      {
        "category": "Shopping",
        "subcategory": "Hobbies, Toys, \u0026 Games",
        "type": "Retail Goods"
      }
    ],
    "sg:phone": "+1 440 428 0042",
    "sg:postcode": "44057",
    "sg:province": "OH",
    "sg:tags": [
      "shop"
    ],
    "wof:name": "Rivendell",
    "wof:placetype": "venue"
  },
  "geometry": {"coordinates":[-81.047293,41.780818],"type":"Point"}
}
