{
  "type": "Feature",
  "properties": {
    "addr:full": "1065 Rosedale Rd Irwin OH 43029",
    "addr:housenumber": "1065",
    "addr:postcode": "43029",
    "addr:street": "Rosedale Rd",
    "iso:country": "US",
    "sg:address": "1065 Rosedale Rd",
    "sg:city": "Irwin",
    "sg:classifiers": [
      {
        "category": "Farming",
        "subcategory": "Farm",
        "type": "Manufacturing \u0026 Wholesale Goods"
      }
    ],
    "sg:phone": "+1 740 857 1128",
    "sg:postcode": "43029",
    "sg:province": "OH",
    "sg:tags": [
      "crop",
      "general"
    ],
    "wof:name": "James Stewart",
    "wof:placetype": "venue"
  },
  "geometry": {"coordinates":[-83.425963,40.098698],"type":"Point"}
}
