{
  "type": "Feature",
  "properties": {
    "addr:full": "9170 Muirkirk Dr Dublin OH 43017",
    "addr:housenumber": "9170",
    "addr:postcode": "43017",
    "addr:street": "Muirkirk Dr",
    "iso:country": "US",
    "sg:address": "9170 Muirkirk Dr",
    "sg:city": "Dublin",
    "sg:classifiers": [
      {
        "category": "Building \u0026 Trades",
        "subcategory": "Construction",
        "type": "Services"
      }
    ],
    "sg:phone": "+1 614 792 1133",
    "sg:postcode": "43017",
    "sg:province": "OH",
    "sg:tags": [
      "house"
    ],
    "wof:name": "Pfister Homes",
    "wof:placetype": "venue"
  },
  "geometry": {"coordinates":[-83.135502,40.155473],"type":"Point"}
}
