{
  "type": "Feature",
  "properties": {
    "addr:full":"3812 Fishinger Blvd Hilliard OH 43026",
    "addr:housenumber":"3812",
    "addr:postcode":"43026",
    "addr:street":"Fishinger Blvd",
    "iso:country":"US",
    "sg:address":"3812 Fishinger Blvd",
    "sg:city":"Hilliard",
    "sg:classifiers":[
        {
            "category":"Insurance",
            "subcategory":"Title Insurance",
            "type":"Services"
        }
    ],
    "sg:phone":"+1 614 529 1880",
    "sg:postcode":"43026",
    "sg:province":"OH",
    "sg:tags":[
        "carrier"
    ],
    "wof:name":"Amerititle Agency",
    "wof:placetype":"venue"
},
  "geometry": {"coordinates":[-83.116108,40.032172],"type":"Point"}
}