{
  "type": "Feature",
  "properties": {
    "addr:full":"129 W State St Newcomerstown OH 43832",
    "addr:housenumber":"129",
    "addr:postcode":"43832",
    "addr:street":"W State St",
    "iso:country":"US",
    "sg:address":"129 W State St",
    "sg:city":"Newcomerstown",
    "sg:classifiers":[
        {
            "category":"Autos & Motor Vehicles",
            "subcategory":"Fuel & Gas Station",
            "type":"Retail Goods"
        }
    ],
    "sg:phone":"+1 740 498 6541",
    "sg:postcode":"43832",
    "sg:province":"OH",
    "sg:tags":[
        "oil"
    ],
    "wof:name":"Newcomerstown Shell",
    "wof:placetype":"venue"
},
  "geometry": {"coordinates":[-81.606353,40.271268],"type":"Point"}
}