{
  "type": "Feature",
  "properties": {
    "iso:country":"US",
    "sg:address":"2597 S Hamilton Rd",
    "sg:city":"Columbus",
    "sg:classifiers":[
        {
            "category":"Shopping",
            "subcategory":"Jewelry",
            "type":"Retail Goods"
        }
    ],
    "sg:phone":"+1 614 861 7777",
    "sg:postcode":"43232",
    "sg:province":"OH",
    "sg:tags":[
        "store"
    ],
    "wof:name":"Idg Jewelers",
    "wof:placetype":"venue"
},
  "geometry": {"coordinates":[-82.880318,39.920063],"type":"Point"}
}