{
  "type": "Feature",
  "properties": {
    "addr:full": "8423 Colerain Ave Cincinnati OH 45239",
    "addr:housenumber": "8423",
    "addr:postcode": "45239",
    "addr:street": "Colerain Ave",
    "iso:country": "US",
    "sg:address": "8423 Colerain Ave",
    "sg:city": "Cincinnati",
    "sg:classifiers": [
      {
        "category": "Food \u0026 Beverages",
        "subcategory": "Bakery",
        "type": "Retail Goods"
      }
    ],
    "sg:phone": "+1 513 385 5080",
    "sg:postcode": "45239",
    "sg:province": "OH",
    "wof:name": "Interstate Brands Corporation",
    "wof:placetype": "venue"
  },
  "geometry": {"coordinates":[-84.586762,39.221478],"type":"Point"}
}
