{
  "type": "Feature",
  "properties": {
    "iso:country":"US",
    "sg:address":"8423 Colerain Ave",
    "sg:city":"Cincinnati",
    "sg:classifiers":[
        {
            "category":"Food & Beverages",
            "subcategory":"Bakery",
            "type":"Retail Goods"
        }
    ],
    "sg:phone":"+1 513 385 5080",
    "sg:postcode":"45239",
    "sg:province":"OH",
    "wof:name":"Interstate Brands Corporation",
    "wof:placetype":"venue"
},
  "geometry": {"coordinates":[-84.58676199999999,39.221478],"type":"Point"}
}