{
  "type": "Feature",
  "properties": {
    "addr:full":"1228 N Monroe Dr Xenia OH 45385",
    "addr:housenumber":"1228",
    "addr:postcode":"45385",
    "addr:street":"N Monroe Dr",
    "iso:country":"US",
    "sg:address":"1228 N Monroe Dr",
    "sg:city":"Xenia",
    "sg:classifiers":[
        {
            "category":"Insurance",
            "subcategory":"Insurance Agent",
            "type":"Services"
        }
    ],
    "sg:phone":"+1 937 372 3559",
    "sg:postcode":"45385",
    "sg:province":"OH",
    "wof:name":"Lesourd & Co",
    "wof:placetype":"venue"
},
  "geometry": {"coordinates":[-83.92895900000001,39.700904],"type":"Point"}
}