{
  "type": "Feature",
  "properties": {
    "addr:full": "5295 Franklin Church Rd Greenwich OH 44837",
    "addr:housenumber": "5295",
    "addr:postcode": "44837",
    "addr:street": "Franklin Church Rd",
    "iso:country": "US",
    "sg:address": "5295 Franklin Church Rd",
    "sg:city": "Greenwich",
    "sg:classifiers": [
      {
        "category": "Professional",
        "subcategory": "Management \u0026 Consulting",
        "type": "Services"
      }
    ],
    "sg:phone": "+1 419 895 3143",
    "sg:postcode": "44837",
    "sg:province": "OH",
    "sg:tags": [
      "retail",
      "direct",
      "sales"
    ],
    "wof:name": "John W Clark",
    "wof:placetype": "venue"
  },
  "geometry": {"coordinates":[-82.474577,40.901126],"type":"Point"}
}
