{
  "type": "Feature",
  "properties": {
    "addr:full":"4424 Milan Rd Sandusky OH 44870",
    "addr:housenumber":"4424",
    "addr:postcode":"44870",
    "addr:street":"Milan Rd",
    "iso:country":"US",
    "sg:address":"4424 Milan Rd",
    "sg:city":"Sandusky",
    "sg:classifiers":[
        {
            "category":"Shopping",
            "subcategory":"Jewelry",
            "type":"Retail Goods"
        }
    ],
    "sg:phone":"+1 419 625 4000",
    "sg:postcode":"44870",
    "sg:province":"OH",
    "sg:tags":[
        "jeweler"
    ],
    "wof:name":"Crider Quality Jewelers",
    "wof:placetype":"venue"
},
  "geometry": {"coordinates":[-82.66928799999999,41.413531],"type":"Point"}
}