{
  "type": "Feature",
  "properties": {
    "addr:full":"1043 Brown St Dayton OH 45409",
    "addr:housenumber":"1043",
    "addr:postcode":"45409",
    "addr:street":"Brown St",
    "iso:country":"US",
    "sg:address":"1043 Brown St",
    "sg:city":"Dayton",
    "sg:classifiers":[
        {
            "category":"Restaurant",
            "type":"Food & Drink"
        }
    ],
    "sg:phone":"+1 937 294 5464",
    "sg:postcode":"45409",
    "sg:province":"OH",
    "sg:website":"www.cassanos.com",
    "wof:name":"Cassano's Pizza King",
    "wof:placetype":"venue"
},
  "geometry": {"coordinates":[-84.182726,39.74404],"type":"Point"}
}