{
  "type": "Feature",
  "properties": {
    "iso:country":"US",
    "sg:address":"3114 National Rd",
    "sg:city":"Clayton",
    "sg:classifiers":[
        {
            "category":"Professional",
            "type":"Services"
        }
    ],
    "sg:phone":"+1 937 836 5336",
    "sg:postcode":"45315",
    "sg:province":"OH",
    "sg:tags":[
        "establishment"
    ],
    "wof:name":"Herr Ohmer U",
    "wof:placetype":"venue"
},
  "geometry": {"coordinates":[-84.32893199999999,39.87526],"type":"Point"}
}