{
  "type": "Feature",
  "properties": {
    "addr:full": "13019 Shanley Rd Quincy OH 43343",
    "addr:postcode": "13019;43343",
    "addr:street": "Shanley Rd",
    "iso:country": "US",
    "sg:address": "13019 Shanley Rd",
    "sg:city": "Quincy",
    "sg:classifiers": [
      {
        "category": "Manufacturing",
        "subcategory": "Metals",
        "type": "Manufacturing \u0026 Wholesale Goods"
      }
    ],
    "sg:phone": "+1 937 362 4357",
    "sg:postcode": "43343",
    "sg:province": "OH",
    "sg:tags": [
      "sheet",
      "fabrication"
    ],
    "wof:name": "F M Sheet Metal Fabrication",
    "wof:placetype": "venue"
  },
  "geometry": {"coordinates":[-83.996725,40.243046],"type":"Point"}
}
