{
  "type": "Feature",
  "properties": {
    "iso:country":"US",
    "sg:address":"11017 Mahoning Ave",
    "sg:city":"North Jackson",
    "sg:classifiers":[
        {
            "category":"Local Transit",
            "type":"Transportation"
        }
    ],
    "sg:phone":"+1 330 654 2288",
    "sg:postcode":"44451",
    "sg:province":"OH",
    "sg:tags":[
        "ambulance"
    ],
    "wof:name":"Pellin Ambulance Svc",
    "wof:placetype":"venue"
},
  "geometry": {"coordinates":[-80.857436,41.100044],"type":"Point"}
}