{
  "type": "Feature",
  "properties": {
    "iso:country":"US",
    "sg:address":"259 E State St",
    "sg:city":"Alliance",
    "sg:classifiers":[
        {
            "category":"Banks & Credit Unions",
            "subcategory":"Bank",
            "type":"Services"
        }
    ],
    "sg:phone":"+1 330 829 9008",
    "sg:postcode":"44601",
    "sg:province":"OH",
    "sg:tags":[
        "mortgage"
    ],
    "wof:name":"Statewide Home Mortgage",
    "wof:placetype":"venue"
},
  "geometry": {"coordinates":[-81.101828,40.901612],"type":"Point"}
}