{
  "type": "Feature",
  "properties": {
    "iso:country":"US",
    "sg:address":"2390 Parkman Rd NW",
    "sg:city":"Warren",
    "sg:classifiers":[
        {
            "category":"Health Services",
            "subcategory":"Doctor",
            "type":"Services"
        }
    ],
    "sg:phone":"+1 330 373 1414",
    "sg:postcode":"44485",
    "sg:province":"OH",
    "sg:tags":[
        "medical"
    ],
    "wof:name":"Mehta Paresh G MD",
    "wof:placetype":"venue"
},
  "geometry": {"coordinates":[-80.85572000000001,41.252251],"type":"Point"}
}