{
  "type": "Feature",
  "properties": {
    "addr:full":"301 Walnut St Coshocton OH 43812",
    "addr:housenumber":"301",
    "addr:postcode":"43812",
    "addr:street":"Walnut St",
    "iso:country":"US",
    "sg:address":"301 Walnut St",
    "sg:city":"Coshocton",
    "sg:classifiers":[
        {
            "category":"Restaurant",
            "type":"Food & Drink"
        }
    ],
    "sg:phone":"+1 740 622 3157",
    "sg:postcode":"43812",
    "sg:province":"OH",
    "wof:name":"Pizza Point",
    "wof:placetype":"venue"
},
  "geometry": {"coordinates":[-81.867127,40.272324],"type":"Point"}
}