{
  "type": "Feature",
  "properties": {
    "addr:full": "6660 N High St Worthington OH 43085",
    "addr:housenumber": "6660",
    "addr:postcode": "43085",
    "addr:street": "N High St",
    "iso:country": "US",
    "sg:address": "6660 N High St",
    "sg:city": "Worthington",
    "sg:classifiers": [
      {
        "category": "Professional",
        "subcategory": "Computer Services",
        "type": "Services"
      }
    ],
    "sg:phone": "+1 614 781 1948",
    "sg:postcode": "43085",
    "sg:province": "OH",
    "sg:tags": [
      "software"
    ],
    "sg:website": "www.ansys.com",
    "wof:name": "Ansys Inc",
    "wof:placetype": "venue"
  },
  "geometry": {"coordinates":[-83.017162,40.101948],"type":"Point"}
}
