{
  "type": "Feature",
  "properties": {
    "iso:country":"US",
    "sg:address":"4665 Turney Rd",
    "sg:city":"Cleveland",
    "sg:classifiers":[
        {
            "category":"Personal",
            "subcategory":"Beauty Salon",
            "type":"Services"
        }
    ],
    "sg:phone":"+1 216 271 2711",
    "sg:postcode":"44125",
    "sg:province":"OH",
    "wof:name":"Dee-Jean's Hair LTD",
    "wof:placetype":"venue"
},
  "geometry": {"coordinates":[-81.61785399999999,41.433094],"type":"Point"}
}