{
  "type": "Feature",
  "properties": {
    "addr:full": "1089 W Broad St Columbus OH 43222",
    "addr:housenumber": "1089",
    "addr:postcode": "43222",
    "addr:street": "W Broad St",
    "iso:country": "US",
    "sg:address": "1089 W Broad St",
    "sg:city": "Columbus",
    "sg:classifiers": [
      {
        "category": "Health Services",
        "subcategory": "Doctor",
        "type": "Services"
      }
    ],
    "sg:phone": "+1 614 224 4541",
    "sg:postcode": "43222",
    "sg:province": "OH",
    "wof:name": "American Home Healthcare",
    "wof:placetype": "venue"
  },
  "geometry": {"coordinates":[-83.030055,39.958577],"type":"Point"}
}
