{
  "type": "Feature",
  "properties": {
    "iso:country":"US",
    "sg:address":"715 E Main St",
    "sg:city":"Batavia",
    "sg:classifiers":[
        {
            "category":"Recreation",
            "type":"Entertainment"
        }
    ],
    "sg:phone":"+1 513 732 6393",
    "sg:postcode":"45103",
    "sg:province":"OH",
    "sg:tags":[
        "club",
        "tennis",
        "swimming"
    ],
    "wof:name":"Ridge Swim & Tennis Club",
    "wof:placetype":"venue"
},
  "geometry": {"coordinates":[-84.17246900000001,39.073273],"type":"Point"}
}