{
  "type": "Feature",
  "properties": {
    "addr:full": "715 E Main St Batavia OH 45103",
    "addr:housenumber": "715",
    "addr:postcode": "45103",
    "addr:street": "E Main St",
    "iso:country": "US",
    "sg:address": "715 E Main St",
    "sg:city": "Batavia",
    "sg:classifiers": [
      {
        "category": "Recreation",
        "type": "Entertainment"
      }
    ],
    "sg:phone": "+1 513 732 6393",
    "sg:postcode": "45103",
    "sg:province": "OH",
    "sg:tags": [
      "club",
      "tennis",
      "swimming"
    ],
    "wof:name": "Ridge Swim \u0026 Tennis Club",
    "wof:placetype": "venue"
  },
  "geometry": {"coordinates":[-84.172469,39.073273],"type":"Point"}
}
