{
  "type": "Feature",
  "properties": {
    "addr:full":"1243 Meadow Bridge Dr Dayton OH 45434",
    "addr:housenumber":"1243",
    "addr:postcode":"45434",
    "addr:street":"Meadow Bridge Dr",
    "iso:country":"US",
    "sg:address":"1243 Meadow Bridge Dr",
    "sg:city":"Dayton",
    "sg:classifiers":[
        {
            "category":"Restaurant",
            "type":"Food & Drink"
        }
    ],
    "sg:menulink":"http://www.allmenus.com/oh/beavercreek/83270-papa-johns-pizza/menu/",
    "sg:phone":"+1 937 320 7272",
    "sg:postcode":"45434",
    "sg:province":"OH",
    "sg:tags":[
        "american",
        "pizza"
    ],
    "wof:name":"Papa John's Pizza",
    "wof:placetype":"venue"
},
  "geometry": {"coordinates":[-84.052728,39.724674],"type":"Point"}
}