{
  "type": "Feature",
  "properties": {
    "addr:full": "1801 Saint Paris Pike Springfield OH 45504",
    "addr:housenumber": "1801",
    "addr:postcode": "45504",
    "addr:street": "Saint Paris Pike",
    "iso:country": "US",
    "sg:address": "1801 Saint Paris Pike",
    "sg:city": "Springfield",
    "sg:classifiers": [
      {
        "category": "Organizations",
        "subcategory": "Religious Organization",
        "type": "Services"
      }
    ],
    "sg:phone": "+1 937 399 6257",
    "sg:postcode": "45504",
    "sg:province": "OH",
    "sg:tags": [
      "lutheran",
      "church"
    ],
    "wof:name": "Grace Lutheran Church",
    "wof:placetype": "venue"
  },
  "geometry": {"coordinates":[-83.822578,39.94986],"type":"Point"}
}
