{
  "type": "Feature",
  "properties": {
    "iso:country":"US",
    "sg:address":"11923 Twp Rd 245",
    "sg:city":"Kenton",
    "sg:classifiers":[
        {
            "category":"Farming",
            "subcategory":"Farm",
            "type":"Manufacturing & Wholesale Goods"
        }
    ],
    "sg:phone":"+1 419 674 4720",
    "sg:postcode":"43326",
    "sg:province":"OH",
    "sg:tags":[
        "crop",
        "general"
    ],
    "wof:name":"Mike Hughes",
    "wof:placetype":"venue"
},
  "geometry": {"coordinates":[-83.438997,40.645],"type":"Point"}
}