{
  "type": "Feature",
  "properties": {
    "addr:full": "11923 Twp Rd 245 Kenton OH 43326",
    "addr:housenumber": "11923;245",
    "addr:postcode": "43326",
    "addr:street": "Twp Rd",
    "iso:country": "US",
    "sg:address": "11923 Twp Rd 245",
    "sg:city": "Kenton",
    "sg:classifiers": [
      {
        "category": "Farming",
        "subcategory": "Farm",
        "type": "Manufacturing \u0026 Wholesale Goods"
      }
    ],
    "sg:phone": "+1 419 674 4720",
    "sg:postcode": "43326",
    "sg:province": "OH",
    "sg:tags": [
      "crop",
      "general"
    ],
    "wof:name": "Mike Hughes",
    "wof:placetype": "venue"
  },
  "geometry": {"coordinates":[-83.438997,40.645],"type":"Point"}
}
