{
  "type": "Feature",
  "properties": {
    "addr:full": "728 Market St Zanesville OH 43701",
    "addr:housenumber": "728",
    "addr:postcode": "43701",
    "addr:street": "Market St",
    "iso:country": "US",
    "sg:address": "728 Market St",
    "sg:city": "Zanesville",
    "sg:classifiers": [
      {
        "category": "Education",
        "subcategory": "Dance Studio",
        "type": "Public Place"
      }
    ],
    "sg:phone": "+1 740 452 5504",
    "sg:postcode": "43701",
    "sg:province": "OH",
    "sg:tags": [
      "instruction",
      "dancing"
    ],
    "wof:name": "Barbara Ann Black Dance Acad",
    "wof:placetype": "venue"
  },
  "geometry": {"coordinates":[-82.003589,39.941595],"type":"Point"}
}
