{
  "type": "Feature",
  "properties": {
    "addr:full":"1320 Nagel Rd Cincinnati OH 45255",
    "addr:housenumber":"1320",
    "addr:postcode":"45255",
    "addr:street":"Nagel Rd",
    "iso:country":"US",
    "sg:address":"1320 Nagel Rd",
    "sg:city":"Cincinnati",
    "sg:classifiers":[
        {
            "category":"Government",
            "subcategory":"Post Office",
            "type":"Public Place"
        }
    ],
    "sg:phone":"+1 513 474 3262",
    "sg:postcode":"45255",
    "sg:province":"OH",
    "sg:tags":[
        "postal",
        "us"
    ],
    "wof:name":"United States Postal Service",
    "wof:placetype":"venue"
},
  "geometry": {"coordinates":[-84.332264,39.07371],"type":"Point"}
}