{
  "type": "Feature",
  "properties": {
    "iso:country":"US",
    "sg:address":"3944 Greenwich Rd",
    "sg:city":"Seville",
    "sg:classifiers":[
        {
            "category":"Professional",
            "subcategory":"Business Services",
            "type":"Services"
        }
    ],
    "sg:phone":"+1 330 336 5335",
    "sg:postcode":"44273",
    "sg:province":"OH",
    "sg:tags":[
        "water",
        "treatment"
    ],
    "wof:name":"WIL Lo Water Conditioning",
    "wof:placetype":"venue"
},
  "geometry": {"coordinates":[-81.827549,41.025073],"type":"Point"}
}