{
  "type": "Feature",
  "properties": {
    "iso:country":"US",
    "sg:address":"668 E Main St",
    "sg:city":"Jackson",
    "sg:classifiers":[
        {
            "category":"Autos & Motor Vehicles",
            "subcategory":"Auto Supplies",
            "type":"Retail Goods"
        }
    ],
    "sg:phone":"+1 740 286 1415",
    "sg:postcode":"45640",
    "sg:province":"OH",
    "sg:tags":[
        "automobile",
        "parts"
    ],
    "sg:website":"www.autozone.com",
    "wof:name":"Autozone",
    "wof:placetype":"venue"
},
  "geometry": {"coordinates":[-82.629623,39.04403],"type":"Point"}
}