{
  "type": "Feature",
  "properties": {
    "addr:full": "668 E Main St Jackson OH 45640",
    "addr:housenumber": "668",
    "addr:postcode": "45640",
    "addr:street": "E Main St",
    "iso:country": "US",
    "sg:address": "668 E Main St",
    "sg:city": "Jackson",
    "sg:classifiers": [
      {
        "category": "Autos \u0026 Motor Vehicles",
        "subcategory": "Auto Supplies",
        "type": "Retail Goods"
      }
    ],
    "sg:phone": "+1 740 286 1415",
    "sg:postcode": "45640",
    "sg:province": "OH",
    "sg:tags": [
      "automobile",
      "parts"
    ],
    "sg:website": "www.autozone.com",
    "wof:name": "Autozone",
    "wof:placetype": "venue"
  },
  "geometry": {"coordinates":[-82.629623,39.04403],"type":"Point"}
}
