{
  "type": "Feature",
  "properties": {
    "addr:full": "1228 Moonkist Ct Cincinnati OH 45230",
    "addr:housenumber": "1228",
    "addr:postcode": "45230",
    "addr:street": "Moonkist Ct",
    "iso:country": "US",
    "sg:address": "1228 Moonkist Ct",
    "sg:city": "Cincinnati",
    "sg:classifiers": [
      {
        "category": "Building \u0026 Trades",
        "subcategory": "Construction",
        "type": "Services"
      }
    ],
    "sg:phone": "+1 513 233 2316",
    "sg:postcode": "45230",
    "sg:province": "OH",
    "sg:tags": [
      "home",
      "improvement"
    ],
    "wof:name": "A 24 Hour Door",
    "wof:placetype": "venue"
  },
  "geometry": {"coordinates":[-84.393072,39.093277],"type":"Point"}
}
