{
  "type": "Feature",
  "properties": {
    "iso:country":"US",
    "sg:address":"1228 Moonkist Ct",
    "sg:city":"Cincinnati",
    "sg:classifiers":[
        {
            "category":"Building & Trades",
            "subcategory":"Construction",
            "type":"Services"
        }
    ],
    "sg:phone":"+1 513 233 2316",
    "sg:postcode":"45230",
    "sg:province":"OH",
    "sg:tags":[
        "home",
        "improvement"
    ],
    "wof:name":"A 24 Hour Door",
    "wof:placetype":"venue"
},
  "geometry": {"coordinates":[-84.393072,39.093277],"type":"Point"}
}