{
  "type": "Feature",
  "properties": {
    "addr:full":"120 Marconi Blvd Columbus OH 43215",
    "addr:housenumber":"120",
    "addr:postcode":"43215",
    "addr:street":"Marconi Blvd",
    "iso:country":"US",
    "sg:address":"120 Marconi Blvd",
    "sg:city":"Columbus",
    "sg:classifiers":[
        {
            "category":"Government",
            "subcategory":"Police Station",
            "type":"Public Place"
        }
    ],
    "sg:phone":"+1 614 645 4670",
    "sg:postcode":"43215",
    "sg:province":"OH",
    "sg:tags":[
        "department"
    ],
    "wof:name":"Columbus Police-Juvenile Bur",
    "wof:placetype":"venue"
},
  "geometry": {"coordinates":[-83.00442700000001,39.963421],"type":"Point"}
}