{
  "type": "Feature",
  "properties": {
    "addr:full":"11000 Cedar Ave Cleveland OH 44106",
    "addr:housenumber":"11000",
    "addr:postcode":"44106",
    "addr:street":"Cedar Ave",
    "iso:country":"US",
    "sg:address":"11000 Cedar Ave",
    "sg:city":"Cleveland",
    "sg:classifiers":[
        {
            "category":"Professional",
            "subcategory":"Detective & Security Services",
            "type":"Services"
        }
    ],
    "sg:phone":"+1 216 421 3653",
    "sg:postcode":"44106",
    "sg:province":"OH",
    "wof:name":"Akoura Biometrics",
    "wof:placetype":"venue"
},
  "geometry": {"coordinates":[-81.60672,41.499904],"type":"Point"}
}