{
  "type": "Feature",
  "properties": {
    "addr:full":"837 Boardman Canfield Rd Youngstown OH 44512",
    "addr:housenumber":"837",
    "addr:postcode":"44512",
    "addr:street":"Boardman Canfield Rd",
    "iso:country":"US",
    "sg:address":"837 Boardman Canfield Rd",
    "sg:city":"Youngstown",
    "sg:classifiers":[
        {
            "category":"Personal",
            "subcategory":"Beauty Salon",
            "type":"Services"
        },
        {
            "category":"Personal",
            "subcategory":"Nail Salon",
            "type":"Services"
        }
    ],
    "sg:phone":"+1 330 629 9595",
    "sg:postcode":"44512",
    "sg:province":"OH",
    "wof:name":"Nails on File",
    "wof:placetype":"venue"
},
  "geometry": {"coordinates":[-80.686904,41.024529],"type":"Point"}
}