{
  "type": "Feature",
  "properties": {
    "addr:full": "18489 Pearl Rd Cleveland OH 44136",
    "addr:housenumber": "18489",
    "addr:postcode": "44136",
    "addr:street": "Pearl Rd",
    "iso:country": "US",
    "sg:address": "18489 Pearl Rd",
    "sg:city": "Cleveland",
    "sg:classifiers": [
      {
        "category": "Local Transit",
        "type": "Transportation"
      }
    ],
    "sg:phone": "+1 440 846 9291",
    "sg:postcode": "44136",
    "sg:province": "OH",
    "sg:tags": [
      "handicapped",
      "passenger"
    ],
    "wof:name": "Suburban Transportation",
    "wof:placetype": "venue"
  },
  "geometry": {"coordinates":[-81.835174,41.284572],"type":"Point"}
}
