{
  "type": "Feature",
  "properties": {
    "addr:full": "10720 Makro Dr Cincinnati OH 45241",
    "addr:postcode": "10720;45241",
    "addr:street": "Makro Dr",
    "iso:country": "US",
    "sg:address": "10720 Makro Dr",
    "sg:city": "Cincinnati",
    "sg:classifiers": [
      {
        "category": "Autos \u0026 Motor Vehicles",
        "subcategory": "Auto Supplies",
        "type": "Retail Goods"
      }
    ],
    "sg:phone": "+1 513 554 1777",
    "sg:postcode": "45241",
    "sg:province": "OH",
    "sg:tags": [
      "equipment",
      "racing",
      "car",
      "automobile"
    ],
    "wof:name": "M D Motorsports",
    "wof:placetype": "venue"
  },
  "geometry": {"coordinates":[-84.418698,39.260706],"type":"Point"}
}
