{
  "type": "Feature",
  "properties": {
    "iso:country":"US",
    "sg:address":"135 Euclid Ave",
    "sg:city":"Bellevue",
    "sg:classifiers":[
        {
            "category":"Food & Beverages",
            "subcategory":"Specialty",
            "type":"Retail Goods"
        }
    ],
    "sg:phone":"+1 419 483 0879",
    "sg:postcode":"44811",
    "sg:province":"OH",
    "wof:name":"Hozvicka Natural Health Servic",
    "wof:placetype":"venue"
},
  "geometry": {"coordinates":[-82.843529,41.275503],"type":"Point"}
}