{
  "type": "Feature",
  "properties": {
    "addr:full": "135 Euclid Ave Bellevue OH 44811",
    "addr:housenumber": "135",
    "addr:postcode": "44811",
    "addr:street": "Euclid Ave",
    "iso:country": "US",
    "sg:address": "135 Euclid Ave",
    "sg:city": "Bellevue",
    "sg:classifiers": [
      {
        "category": "Food \u0026 Beverages",
        "subcategory": "Specialty",
        "type": "Retail Goods"
      }
    ],
    "sg:phone": "+1 419 483 0879",
    "sg:postcode": "44811",
    "sg:province": "OH",
    "wof:name": "Hozvicka Natural Health Servic",
    "wof:placetype": "venue"
  },
  "geometry": {"coordinates":[-82.843529,41.275503],"type":"Point"}
}
