{
  "type": "Feature",
  "properties": {
    "addr:full": "1440 Snow Rd Cleveland OH 44134",
    "addr:housenumber": "1440",
    "addr:postcode": "44134",
    "addr:street": "Snow Rd",
    "iso:country": "US",
    "sg:address": "1440 Snow Rd",
    "sg:city": "Cleveland",
    "sg:classifiers": [
      {
        "category": "Communications",
        "subcategory": "Film \u0026 Video Production",
        "type": "Services"
      }
    ],
    "sg:phone": "+1 216 741 2080",
    "sg:postcode": "44134",
    "sg:province": "OH",
    "sg:tags": [
      "taping"
    ],
    "wof:name": "Lasting Impressions Video",
    "wof:placetype": "venue"
  },
  "geometry": {"coordinates":[-81.690604,41.405327],"type":"Point"}
}
