{
  "type": "Feature",
  "properties": {
    "addr:full": "411 W Loveland Ave Loveland OH 45140",
    "addr:housenumber": "411",
    "addr:postcode": "45140",
    "addr:street": "W Loveland Ave",
    "iso:country": "US",
    "sg:address": "411 W Loveland Ave",
    "sg:city": "Loveland",
    "sg:classifiers": [
      {
        "category": "Building \u0026 Trades",
        "subcategory": "Construction",
        "type": "Services"
      }
    ],
    "sg:phone": "+1 513 965 0455",
    "sg:postcode": "45140",
    "sg:province": "OH",
    "sg:tags": [
      "home",
      "builder",
      "family",
      "contractor"
    ],
    "sg:website": "www.eaglecustomhomes.com",
    "wof:name": "Eagle Custom Homes Inc",
    "wof:placetype": "venue"
  },
  "geometry": {"coordinates":[-84.262224,39.268763],"type":"Point"}
}
