{
  "type": "Feature",
  "properties": {
    "addr:full": "4090 River Rd Cincinnati OH 45204",
    "addr:housenumber": "4090",
    "addr:postcode": "45204",
    "addr:street": "River Rd",
    "iso:country": "US",
    "sg:address": "4090 River Rd",
    "sg:city": "Cincinnati",
    "sg:classifiers": [
      {
        "category": "Home \u0026 Garden",
        "subcategory": "Furniture",
        "type": "Retail Goods"
      }
    ],
    "sg:phone": "+1 513 451 1285",
    "sg:postcode": "45204",
    "sg:province": "OH",
    "wof:name": "19 C Furniture",
    "wof:placetype": "venue"
  },
  "geometry": {"coordinates":[-84.6233,39.077269],"type":"Point"}
}
