{
  "type": "Feature",
  "properties": {
    "addr:full": "211 Franklin Ave Kent OH 44240",
    "addr:housenumber": "211",
    "addr:postcode": "44240",
    "addr:street": "Franklin Ave",
    "iso:country": "US",
    "sg:address": "211 Franklin Ave",
    "sg:city": "Kent",
    "sg:classifiers": [
      {
        "category": "Bars \u0026 Pubs",
        "type": "Food \u0026 Drink"
      }
    ],
    "sg:phone": "+1 330 673 7822",
    "sg:postcode": "44240",
    "sg:province": "OH",
    "wof:name": "Mugs Brew Pub Inc",
    "wof:placetype": "venue"
  },
  "geometry": {"coordinates":[-81.359245,41.152221],"type":"Point"}
}
