{
  "type": "Feature",
  "properties": {
    "iso:country":"US",
    "sg:address":"211 Franklin Ave",
    "sg:city":"Kent",
    "sg:classifiers":[
        {
            "category":"Bars & Pubs",
            "type":"Food & Drink"
        }
    ],
    "sg:phone":"+1 330 673 7822",
    "sg:postcode":"44240",
    "sg:province":"OH",
    "wof:name":"Mugs Brew Pub Inc",
    "wof:placetype":"venue"
},
  "geometry": {"coordinates":[-81.359245,41.152221],"type":"Point"}
}