{
  "type": "Feature",
  "properties": {
    "iso:country":"US",
    "sg:address":"72 N Main St",
    "sg:city":"Hudson",
    "sg:classifiers":[
        {
            "category":"Organizations",
            "subcategory":"Religious Organization",
            "type":"Services"
        }
    ],
    "sg:phone":"+1 330 656 1800",
    "sg:postcode":"44236",
    "sg:province":"OH",
    "sg:tags":[
        "synagogue"
    ],
    "wof:name":"Temple Beth Shalom",
    "wof:placetype":"venue"
},
  "geometry": {"coordinates":[-81.440506,41.240111],"type":"Point"}
}