{
  "type": "Feature",
  "properties": {
    "addr:full":"2246 Canary Ln Fairfield OH 45014",
    "addr:housenumber":"2246",
    "addr:postcode":"45014",
    "addr:street":"Canary Ln",
    "iso:country":"US",
    "sg:address":"2246 Canary Ln",
    "sg:city":"Fairfield",
    "sg:classifiers":[
        {
            "category":"Building & Trades",
            "subcategory":"Construction",
            "type":"Services"
        }
    ],
    "sg:phone":"+1 513 738 4065",
    "sg:postcode":"45014",
    "sg:province":"OH",
    "sg:tags":[
        "concrete",
        "contractor"
    ],
    "wof:name":"James E Holbert",
    "wof:placetype":"venue"
},
  "geometry": {"coordinates":[-84.64187800000001,39.313265],"type":"Point"}
}