{
  "type": "Feature",
  "properties": {
    "addr:full": "101 Meadowland Dr Chardon OH 44024",
    "addr:housenumber": "101",
    "addr:postcode": "44024",
    "addr:street": "Meadowland Dr",
    "iso:country": "US",
    "sg:address": "101 Meadowland Dr",
    "sg:city": "Chardon",
    "sg:classifiers": [
      {
        "category": "Real Estate",
        "subcategory": "Real Estate Operator",
        "type": "Services"
      }
    ],
    "sg:phone": "+1 440 286 3653",
    "sg:postcode": "44024",
    "sg:province": "OH",
    "sg:tags": [
      "building",
      "apartment"
    ],
    "wof:name": "Meadow Apts",
    "wof:placetype": "venue"
  },
  "geometry": {"coordinates":[-81.223847,41.583521],"type":"Point"}
}
