{
  "type": "Feature",
  "properties": {
    "addr:full": "6195 Delcrest Dr Fairfield OH 45014",
    "addr:housenumber": "6195",
    "addr:postcode": "45014",
    "addr:street": "Delcrest Dr",
    "iso:country": "US",
    "sg:address": "6195 Delcrest Dr",
    "sg:city": "Fairfield",
    "sg:classifiers": [
      {
        "category": "Building \u0026 Trades",
        "subcategory": "Construction",
        "type": "Services"
      }
    ],
    "sg:phone": "+1 513 874 0101",
    "sg:postcode": "45014",
    "sg:province": "OH",
    "sg:tags": [
      "patio",
      "deck"
    ],
    "wof:name": "Archadeck",
    "wof:placetype": "venue"
  },
  "geometry": {"coordinates":[-84.508487,39.311807],"type":"Point"}
}
