{
  "type": "Feature",
  "properties": {
    "iso:country":"US",
    "sg:address":"775 Lafayette Rd",
    "sg:city":"Medina",
    "sg:classifiers":[
        {
            "category":"Retail",
            "subcategory":"Auto Repair",
            "type":"Services"
        }
    ],
    "sg:phone":"+1 330 725 6330",
    "sg:postcode":"44256",
    "sg:province":"OH",
    "sg:tags":[
        "wrecker"
    ],
    "wof:name":"Lloyd's Towing Svc",
    "wof:placetype":"venue"
},
  "geometry": {"coordinates":[-81.881997,41.128245],"type":"Point"}
}