{
  "type": "Feature",
  "properties": {
    "addr:full": "525 Rockglen Dr Wadsworth OH 44281",
    "addr:housenumber": "525",
    "addr:postcode": "44281",
    "addr:street": "Rockglen Dr",
    "iso:country": "US",
    "sg:address": "525 Rockglen Dr",
    "sg:city": "Wadsworth",
    "sg:classifiers": [
      {
        "category": "Wholesale",
        "subcategory": "Toys \u0026 Hobbies",
        "type": "Manufacturing \u0026 Wholesale Goods"
      }
    ],
    "sg:phone": "+1 330 321 6382",
    "sg:postcode": "44281",
    "sg:province": "OH",
    "sg:tags": [
      "bingo",
      "supply"
    ],
    "wof:name": "Youngson Bingo Supply",
    "wof:placetype": "venue"
  },
  "geometry": {"coordinates":[-81.743833,41.057652],"type":"Point"}
}
