{
  "type": "Feature",
  "properties": {
    "iso:country":"US",
    "sg:address":"525 Rockglen Dr",
    "sg:city":"Wadsworth",
    "sg:classifiers":[
        {
            "category":"Wholesale",
            "subcategory":"Toys & Hobbies",
            "type":"Manufacturing & Wholesale Goods"
        }
    ],
    "sg:phone":"+1 330 321 6382",
    "sg:postcode":"44281",
    "sg:province":"OH",
    "sg:tags":[
        "bingo",
        "supply"
    ],
    "wof:name":"Youngson Bingo Supply",
    "wof:placetype":"venue"
},
  "geometry": {"coordinates":[-81.743833,41.057652],"type":"Point"}
}