{
  "type": "Feature",
  "properties": {
    "iso:country":"US",
    "sg:address":"225 W Columbus St",
    "sg:city":"Kenton",
    "sg:classifiers":[
        {
            "category":"Utilities",
            "subcategory":"Telephone",
            "type":"Services"
        }
    ],
    "sg:phone":"+1 419 674 1100",
    "sg:postcode":"43326",
    "sg:province":"OH",
    "wof:name":"Alltel",
    "wof:placetype":"venue"
},
  "geometry": {"coordinates":[-83.610266,40.648139],"type":"Point"}
}