{
  "type": "Feature",
  "properties": {
    "addr:full": "16281 E Twp Rd 126 Attica OH 44811",
    "addr:housenumber": "16281",
    "addr:postcode": "44811",
    "addr:street": "E Twp Rd 126",
    "iso:country": "US",
    "sg:address": "16281 E Twp Rd 126",
    "sg:city": "Attica",
    "sg:phone": "+1 419 426 4141",
    "sg:postcode": "44811",
    "sg:province": "OH",
    "sg:tags": [
      "farm",
      "corn",
      "wheat",
      "soybean"
    ],
    "wof:name": "Weidinger Brothers",
    "wof:placetype": "venue"
  },
  "geometry": {"coordinates":[-82.858333,41.153554],"type":"Point"}
}
