{
  "type": "Feature",
  "properties": {
    "iso:country":"US",
    "sg:address":"5360 Salem Ave",
    "sg:city":"Dayton",
    "sg:classifiers":[
        {
            "category":"Restaurant",
            "type":"Food & Drink"
        }
    ],
    "sg:menulink":"http://www.allmenus.com/oh/trotwood/195332-mcdonalds/menu/",
    "sg:postcode":"45426",
    "sg:province":"OH",
    "sg:tags":[
        "burger",
        "american"
    ],
    "wof:name":"McDonald's",
    "wof:placetype":"venue"
},
  "geometry": {"coordinates":[-84.288707,39.82217],"type":"Point"}
}