{
  "type": "Feature",
  "properties": {
    "iso:country":"US",
    "sg:address":"17 Granger Rd",
    "sg:city":"Medina",
    "sg:classifiers":[
        {
            "category":"Building & Trades",
            "subcategory":"Construction",
            "type":"Services"
        }
    ],
    "sg:phone":"+1 330 666 4274",
    "sg:postcode":"44256",
    "sg:province":"OH",
    "sg:tags":[
        "home",
        "house",
        "improvement"
    ],
    "wof:name":"Klippel Construction LLC",
    "wof:placetype":"venue"
},
  "geometry": {"coordinates":[-81.68697899999999,41.155752],"type":"Point"}
}