{
  "type": "Feature",
  "properties": {
    "addr:full": "17 Granger Rd Medina OH 44256",
    "addr:housenumber": "17",
    "addr:postcode": "44256",
    "addr:street": "Granger Rd",
    "iso:country": "US",
    "sg:address": "17 Granger Rd",
    "sg:city": "Medina",
    "sg:classifiers": [
      {
        "category": "Building \u0026 Trades",
        "subcategory": "Construction",
        "type": "Services"
      }
    ],
    "sg:phone": "+1 330 666 4274",
    "sg:postcode": "44256",
    "sg:province": "OH",
    "sg:tags": [
      "home",
      "house",
      "improvement"
    ],
    "wof:name": "Klippel Construction LLC",
    "wof:placetype": "venue"
  },
  "geometry": {"coordinates":[-81.686979,41.155752],"type":"Point"}
}
