{
  "type": "Feature",
  "properties": {
    "iso:country":"US",
    "sg:address":"10960 Reading Rd",
    "sg:city":"Cincinnati",
    "sg:classifiers":[
        {
            "category":"Retail",
            "subcategory":"Repair Shop",
            "type":"Services"
        }
    ],
    "sg:phone":"+1 513 563 4737",
    "sg:postcode":"45241",
    "sg:province":"OH",
    "sg:tags":[
        "upholsterer"
    ],
    "wof:name":"Jim Morris Upholstering",
    "wof:placetype":"venue"
},
  "geometry": {"coordinates":[-84.413617,39.266508],"type":"Point"}
}