{
  "type": "Feature",
  "properties": {
    "iso:country":"US",
    "sg:address":"3895 Homestead Rd",
    "sg:city":"Ravenna",
    "sg:classifiers":[
        {
            "category":"Manufacturing",
            "subcategory":"Tools & Machinery",
            "type":"Manufacturing & Wholesale Goods"
        }
    ],
    "sg:phone":"+1 330 325 7022",
    "sg:postcode":"44266",
    "sg:province":"OH",
    "sg:tags":[
        "jobbing",
        "machining",
        "general"
    ],
    "wof:name":"Gs Machine",
    "wof:placetype":"venue"
},
  "geometry": {"coordinates":[-81.299202,41.09867],"type":"Point"}
}