{
  "type": "Feature",
  "properties": {
    "addr:full":"3895 Homestead Rd Ravenna OH 44266",
    "addr:housenumber":"3895",
    "addr:postcode":"44266",
    "addr:street":"Homestead Rd",
    "iso:country":"US",
    "sg:address":"3895 Homestead Rd",
    "sg:city":"Ravenna",
    "sg:classifiers":[
        {
            "category":"Manufacturing",
            "subcategory":"Tools & Machinery",
            "type":"Manufacturing & Wholesale Goods"
        }
    ],
    "sg:phone":"+1 330 325 7022",
    "sg:postcode":"44266",
    "sg:province":"OH",
    "sg:tags":[
        "jobbing",
        "machining",
        "general"
    ],
    "wof:name":"Gs Machine",
    "wof:placetype":"venue"
},
  "geometry": {"coordinates":[-81.29920199999999,41.09867],"type":"Point"}
}