{
  "type": "Feature",
  "properties": {
    "iso:country":"US",
    "sg:address":"10586 State Rte 800 SE",
    "sg:city":"Uhrichsville",
    "sg:classifiers":[
        {
            "category":"Autos & Motor Vehicles",
            "subcategory":"Fuel & Gas Station",
            "type":"Retail Goods"
        }
    ],
    "sg:phone":"+1 740 922 3349",
    "sg:postcode":"44683",
    "sg:province":"OH",
    "sg:tags":[
        "oil"
    ],
    "wof:name":"Tatsmans Sunoco & Restaurant",
    "wof:placetype":"venue"
},
  "geometry": {"coordinates":[-81.308888,40.323431],"type":"Point"}
}