{
  "type": "Feature",
  "properties": {
    "addr:full": "10586 State Rte 800 SE Uhrichsville OH 44683",
    "addr:housenumber": "10586",
    "addr:postcode": "44683",
    "addr:street": "State Rte 800 Se",
    "iso:country": "US",
    "sg:address": "10586 State Rte 800 SE",
    "sg:city": "Uhrichsville",
    "sg:classifiers": [
      {
        "category": "Autos \u0026 Motor Vehicles",
        "subcategory": "Fuel \u0026 Gas Station",
        "type": "Retail Goods"
      }
    ],
    "sg:phone": "+1 740 922 3349",
    "sg:postcode": "44683",
    "sg:province": "OH",
    "sg:tags": [
      "oil"
    ],
    "wof:name": "Tatsmans Sunoco \u0026 Restaurant",
    "wof:placetype": "venue"
  },
  "geometry": {"coordinates":[-81.308888,40.323431],"type":"Point"}
}
