{
  "type": "Feature",
  "properties": {
    "iso:country":"US",
    "sg:address":"10815 Clark Rd",
    "sg:city":"Chardon",
    "sg:classifiers":[
        {
            "category":"Wholesale",
            "subcategory":"Auto Parts",
            "type":"Manufacturing & Wholesale Goods"
        }
    ],
    "sg:phone":"+1 440 285 2340",
    "sg:postcode":"44024",
    "sg:province":"OH",
    "sg:tags":[
        "automobile",
        "rebuilt"
    ],
    "wof:name":"Geauga Rebuilders & Supply",
    "wof:placetype":"venue"
},
  "geometry": {"coordinates":[-81.24420600000001,41.626401],"type":"Point"}
}