{
  "type": "Feature",
  "properties": {
    "addr:full": "10815 Clark Rd Chardon OH 44024",
    "addr:housenumber": "10815",
    "addr:postcode": "44024",
    "addr:street": "Clark Rd",
    "iso:country": "US",
    "sg:address": "10815 Clark Rd",
    "sg:city": "Chardon",
    "sg:classifiers": [
      {
        "category": "Wholesale",
        "subcategory": "Auto Parts",
        "type": "Manufacturing \u0026 Wholesale Goods"
      }
    ],
    "sg:phone": "+1 440 285 2340",
    "sg:postcode": "44024",
    "sg:province": "OH",
    "sg:tags": [
      "automobile",
      "rebuilt"
    ],
    "wof:name": "Geauga Rebuilders \u0026 Supply",
    "wof:placetype": "venue"
  },
  "geometry": {"coordinates":[-81.244206,41.626401],"type":"Point"}
}
