{
  "type": "Feature",
  "properties": {
    "addr:full": "13173 Main St Weston OH 43569",
    "addr:housenumber": "13173",
    "addr:postcode": "43569",
    "addr:street": "Main St",
    "iso:country": "US",
    "sg:address": "13173 Main St",
    "sg:city": "Weston",
    "sg:classifiers": [
      {
        "category": "Real Estate",
        "subcategory": "Real Estate Agent",
        "type": "Services"
      }
    ],
    "sg:phone": "+1 419 669 4538",
    "sg:postcode": "43569",
    "sg:province": "OH",
    "wof:name": "John Newlove Real Estate Inc",
    "wof:placetype": "venue"
  },
  "geometry": {"coordinates":[-83.796033,41.344419],"type":"Point"}
}
