{
  "type": "Feature",
  "properties": {
    "addr:full": "3710 Eastern Ave Cincinnati OH 45226",
    "addr:housenumber": "3710",
    "addr:postcode": "45226",
    "addr:street": "Eastern Ave",
    "iso:country": "US",
    "sg:address": "3710 Eastern Ave",
    "sg:city": "Cincinnati",
    "sg:classifiers": [
      {
        "category": "Place Of Worship",
        "subcategory": "Church",
        "type": "Public Place"
      },
      {
        "category": "Place Of Worship",
        "type": "Public Place"
      }
    ],
    "sg:phone": "+1 513 871 8611",
    "sg:postcode": "45226",
    "sg:province": "OH",
    "sg:tags": [
      "churches-interdenominational",
      "churches-various",
      "denomination"
    ],
    "wof:name": "Christian Parkside Church",
    "wof:placetype": "venue"
  },
  "geometry": {"coordinates":[-84.436619,39.112402],"type":"Point"}
}
