{
  "type": "Feature",
  "properties": {
    "addr:full": "62 W Main St New Concord OH 43762",
    "addr:housenumber": "62",
    "addr:postcode": "43762",
    "addr:street": "W Main St",
    "iso:country": "US",
    "sg:address": "62 W Main St",
    "sg:city": "New Concord",
    "sg:classifiers": [
      {
        "category": "Travel",
        "subcategory": "Hotels \u0026 Motels",
        "type": "Entertainment"
      }
    ],
    "sg:phone": "+1 740 826 7397",
    "sg:postcode": "43762",
    "sg:province": "OH",
    "sg:tags": [
      "breakfast",
      "accommodation",
      "bed"
    ],
    "sg:website": "www.bedandbreakfastohio.com",
    "wof:name": "Friendship House Bed \u0026 Brkfst",
    "wof:placetype": "venue"
  },
  "geometry": {"coordinates":[-81.735245,39.993518],"type":"Point"}
}
