{
  "type": "Feature",
  "properties": {
    "addr:full":"114 N Main St Baltimore OH 43105",
    "addr:housenumber":"114",
    "addr:postcode":"43105",
    "addr:street":"N Main St",
    "iso:country":"US",
    "sg:address":"114 N Main St",
    "sg:city":"Baltimore",
    "sg:classifiers":[
        {
            "category":"Shopping",
            "subcategory":"Pharmacy",
            "type":"Retail Goods"
        }
    ],
    "sg:phone":"+1 740 862 4240",
    "sg:postcode":"43105",
    "sg:province":"OH",
    "sg:tags":[
        "drug"
    ],
    "wof:name":"Village Pharmacy Inc",
    "wof:placetype":"venue"
},
  "geometry": {"coordinates":[-82.60127199999999,39.846131],"type":"Point"}
}