{
  "type": "Feature",
  "properties": {
    "addr:full": "16930 Detroit Ave Lakewood OH 44107",
    "addr:housenumber": "16930",
    "addr:postcode": "44107",
    "addr:street": "Detroit Ave",
    "iso:country": "US",
    "sg:address": "16930 Detroit Ave",
    "sg:city": "Lakewood",
    "sg:classifiers": [
      {
        "category": "Professional",
        "type": "Services"
      }
    ],
    "sg:phone": "+1 216 227 1213",
    "sg:postcode": "44107",
    "sg:province": "OH",
    "wof:name": "Sean Devins",
    "wof:placetype": "venue"
  },
  "geometry": {"coordinates":[-81.815487,41.485454],"type":"Point"}
}
