{
  "type": "Feature",
  "properties": {
    "addr:full":"1875 Millikin Rd Fl 3 Columbus OH 43210",
    "addr:housenumber":"1875;3",
    "addr:postcode":"43210",
    "addr:street":"Millikin Rd",
    "iso:country":"US",
    "sg:address":"1875 Millikin Rd Fl 3",
    "sg:city":"Columbus",
    "sg:classifiers":[
        {
            "category":"Health Services",
            "subcategory":"Clinic",
            "type":"Services"
        }
    ],
    "sg:phone":"+1 614 292 0110",
    "sg:postcode":"43210",
    "sg:province":"OH",
    "sg:tags":[
        "welfare"
    ],
    "sg:website":"http://www.ohio-state.edu",
    "wof:name":"Student Wilce Health Center",
    "wof:placetype":"venue"
},
  "geometry": {"coordinates":[-83.016445,40.002186],"type":"Point"}
}