{
  "type": "Feature",
  "properties": {
    "addr:full":"1856 Lewiston Ct Cincinnati OH 45240",
    "addr:housenumber":"1856",
    "addr:postcode":"45240",
    "addr:street":"Lewiston Ct",
    "iso:country":"US",
    "sg:address":"1856 Lewiston Ct",
    "sg:city":"Cincinnati",
    "sg:classifiers":[
        {
            "category":"Building & Trades",
            "subcategory":"Landscaping Services",
            "type":"Services"
        }
    ],
    "sg:phone":"+1 513 674 0627",
    "sg:postcode":"45240",
    "sg:province":"OH",
    "wof:name":"Stanley L McGhee",
    "wof:placetype":"venue"
},
  "geometry": {"coordinates":[-84.550867,39.295079],"type":"Point"}
}