{
  "type": "Feature",
  "properties": {
    "iso:country":"US",
    "sg:address":"913 E Main St",
    "sg:city":"Chillicothe",
    "sg:classifiers":[
        {
            "category":"Shopping",
            "subcategory":"Clothing, Apparel, & Fashions",
            "type":"Retail Goods"
        }
    ],
    "sg:phone":"+1 740 775 9447",
    "sg:postcode":"45601",
    "sg:province":"OH",
    "sg:tags":[
        "shop",
        "beauty"
    ],
    "wof:name":"Wig Studio",
    "wof:placetype":"venue"
},
  "geometry": {"coordinates":[-82.957925,39.336947],"type":"Point"}
}