{
  "type": "Feature",
  "properties": {
    "addr:full":"430 Richmond St Painesville OH 44077",
    "addr:housenumber":"430",
    "addr:postcode":"44077",
    "addr:street":"Richmond St",
    "iso:country":"US",
    "sg:address":"430 Richmond St",
    "sg:city":"Painesville",
    "sg:classifiers":[
        {
            "category":"Restaurant",
            "type":"Food & Drink"
        }
    ],
    "sg:phone":"+1 440 354 9081",
    "sg:postcode":"44077",
    "sg:province":"OH",
    "sg:tags":[
        "eating"
    ],
    "wof:name":"Latin Corner",
    "wof:placetype":"venue"
},
  "geometry": {"coordinates":[-81.254498,41.727413],"type":"Point"}
}