{
  "type": "Feature",
  "properties": {
    "iso:country":"US",
    "sg:address":"795 Union Ave SE",
    "sg:city":"Minerva",
    "sg:classifiers":[
        {
            "category":"Insurance",
            "subcategory":"Insurance Agent",
            "type":"Services"
        }
    ],
    "sg:phone":"+1 330 868 5542",
    "sg:postcode":"44657",
    "sg:province":"OH",
    "wof:name":"Jfc Insurance Agency Inc",
    "wof:placetype":"venue"
},
  "geometry": {"coordinates":[-81.091836,40.785672],"type":"Point"}
}