{
  "type": "Feature",
  "properties": {
    "addr:full":"10 Blymyer Ave Mansfield OH 44903",
    "addr:housenumber":"10",
    "addr:postcode":"44903",
    "addr:street":"Blymyer Ave",
    "iso:country":"US",
    "sg:address":"10 Blymyer Ave",
    "sg:city":"Mansfield",
    "sg:classifiers":[
        {
            "category":"Real Estate",
            "subcategory":"Real Estate Operator",
            "type":"Services"
        }
    ],
    "sg:phone":"+1 419 526 3522",
    "sg:postcode":"44903",
    "sg:province":"OH",
    "sg:tags":[
        "building",
        "apartment"
    ],
    "wof:name":"Mansfield Apartment",
    "wof:placetype":"venue"
},
  "geometry": {"coordinates":[-82.524986,40.757803],"type":"Point"}
}