{
  "type": "Feature",
  "properties": {
    "addr:full": "620 Alum Creek Dr Columbus OH 43205",
    "addr:housenumber": "620",
    "addr:postcode": "43205",
    "addr:street": "Alum Creek Dr",
    "iso:country": "US",
    "sg:address": "620 Alum Creek Dr",
    "sg:city": "Columbus",
    "sg:classifiers": [
      {
        "category": "Health Services",
        "subcategory": "Doctor",
        "type": "Services"
      }
    ],
    "sg:phone": "+1 614 253 7977",
    "sg:postcode": "43205",
    "sg:province": "OH",
    "sg:tags": [
      "dentist"
    ],
    "wof:name": "Alum Creek Dental Ctr",
    "wof:placetype": "venue"
  },
  "geometry": {"coordinates":[-82.944454,39.955249],"type":"Point"}
}
