{
  "type": "Feature",
  "properties": {
    "iso:country":"US",
    "sg:address":"7196 Muirfield Dr",
    "sg:city":"Dublin",
    "sg:classifiers":[
        {
            "category":"Shopping",
            "type":"Retail Goods"
        }
    ],
    "sg:phone":"+1 614 799 5100",
    "sg:postcode":"43017",
    "sg:province":"OH",
    "sg:tags":[
        "cosmetic",
        "perfume"
    ],
    "wof:name":"Mukha Custom Cosmetics",
    "wof:placetype":"venue"
},
  "geometry": {"coordinates":[-83.154865,40.112631],"type":"Point"}
}