{
  "type": "Feature",
  "properties": {
    "addr:full": "934 E Legendary Run Cincinnati OH 45245",
    "addr:housenumber": "934",
    "addr:postcode": "45245",
    "addr:street": "E Legendary Run",
    "iso:country": "US",
    "sg:address": "934 E Legendary Run",
    "sg:city": "Cincinnati",
    "sg:classifiers": [
      {
        "category": "Wholesale",
        "subcategory": "Non-durable Goods",
        "type": "Manufacturing \u0026 Wholesale Goods"
      }
    ],
    "sg:phone": "+1 513 947 9648",
    "sg:postcode": "45245",
    "sg:province": "OH",
    "wof:name": "Oriental Intl Trdg LLC",
    "wof:placetype": "venue"
  },
  "geometry": {"coordinates":[-84.274908,39.030764],"type":"Point"}
}
