{
  "type": "Feature",
  "properties": {
    "iso:country":"US",
    "sg:address":"1116 Grange Hall Rd",
    "sg:city":"Dayton",
    "sg:classifiers":[
        {
            "category":"Personal",
            "subcategory":"Beauty Salon",
            "type":"Services"
        }
    ],
    "sg:phone":"+1 937 426 9149",
    "sg:postcode":"45430",
    "sg:province":"OH",
    "wof:name":"Unique Hair Design",
    "wof:placetype":"venue"
},
  "geometry": {"coordinates":[-84.084678,39.722899],"type":"Point"}
}