{
  "type": "Feature",
  "properties": {
    "iso:country":"US",
    "sg:address":"8034 Clay St",
    "sg:city":"Thompson",
    "sg:classifiers":[
        {
            "category":"Building & Trades",
            "subcategory":"Construction",
            "type":"Services"
        },
        {
            "category":"Manufacturing",
            "subcategory":"Buildings",
            "type":"Manufacturing & Wholesale Goods"
        }
    ],
    "sg:phone":"+1 440 298 1335",
    "sg:postcode":"44086",
    "sg:province":"OH",
    "sg:tags":[
        "ma",
        "deck",
        "builder",
        "mfg",
        "prefabricated",
        "wood",
        "patio"
    ],
    "wof:name":"Bob O Barns",
    "wof:placetype":"venue"
},
  "geometry": {"coordinates":[-81.085097,41.665577],"type":"Point"}
}