{
  "type": "Feature",
  "properties": {
    "addr:full": "8034 Clay St Thompson OH 44086",
    "addr:housenumber": "8034",
    "addr:postcode": "44086",
    "addr:street": "Clay St",
    "iso:country": "US",
    "sg:address": "8034 Clay St",
    "sg:city": "Thompson",
    "sg:classifiers": [
      {
        "category": "Building \u0026 Trades",
        "subcategory": "Construction",
        "type": "Services"
      },
      {
        "category": "Manufacturing",
        "subcategory": "Buildings",
        "type": "Manufacturing \u0026 Wholesale Goods"
      }
    ],
    "sg:phone": "+1 440 298 1335",
    "sg:postcode": "44086",
    "sg:province": "OH",
    "sg:tags": [
      "ma",
      "deck",
      "builder",
      "mfg",
      "prefabricated",
      "wood",
      "patio"
    ],
    "wof:name": "Bob O Barns",
    "wof:placetype": "venue"
  },
  "geometry": {"coordinates":[-81.085097,41.665577],"type":"Point"}
}
