{
  "type": "Feature",
  "properties": {
    "addr:full": "1854 Ebenezer Rd Cincinnati OH 45233",
    "addr:housenumber": "1854",
    "addr:postcode": "45233",
    "addr:street": "Ebenezer Rd",
    "iso:country": "US",
    "sg:address": "1854 Ebenezer Rd",
    "sg:city": "Cincinnati",
    "sg:classifiers": [
      {
        "category": "Building \u0026 Trades",
        "subcategory": "Electrical",
        "type": "Services"
      }
    ],
    "sg:phone": "+1 513 941 3268",
    "sg:postcode": "45233",
    "sg:province": "OH",
    "sg:tags": [
      "electrical",
      "contractor"
    ],
    "wof:name": "Holthaus Electric",
    "wof:placetype": "venue"
  },
  "geometry": {"coordinates":[-84.651714,39.126262],"type":"Point"}
}
