{
  "type": "Feature",
  "properties": {
    "iso:country":"US",
    "sg:address":"8511 State Rte 703",
    "sg:city":"Celina",
    "sg:classifiers":[
        {
            "category":"Freight",
            "type":"Transportation"
        }
    ],
    "sg:phone":"+1 419 394 3828",
    "sg:postcode":"45822",
    "sg:province":"OH",
    "sg:tags":[
        "operator",
        "trucking"
    ],
    "wof:name":"J & G Repair",
    "wof:placetype":"venue"
},
  "geometry": {"coordinates":[-84.479252,40.551058],"type":"Point"}
}