{
  "type": "Feature",
  "properties": {
    "addr:full": "1711 Lincoln Way W Massillon OH 44647",
    "addr:housenumber": "1711",
    "addr:postcode": "44647",
    "addr:street": "Lincoln Way W",
    "iso:country": "US",
    "sg:address": "1711 Lincoln Way W",
    "sg:city": "Massillon",
    "sg:classifiers": [
      {
        "category": "Home \u0026 Garden",
        "subcategory": "Furniture",
        "type": "Retail Goods"
      }
    ],
    "sg:phone": "+1 330 832 8729",
    "sg:postcode": "44647",
    "sg:province": "OH",
    "wof:name": "Kellers Office Furniture LLC",
    "wof:placetype": "venue"
  },
  "geometry": {"coordinates":[-81.54507,40.794668],"type":"Point"}
}
