{
  "type": "Feature",
  "properties": {
    "iso:country":"US",
    "sg:address":"29 E 5th Ave",
    "sg:city":"Columbus",
    "sg:classifiers":[
        {
            "category":"Social Services",
            "type":"Services"
        }
    ],
    "sg:phone":"+1 614 258 5690",
    "sg:postcode":"43201",
    "sg:province":"OH",
    "sg:tags":[
        "organization",
        "welfare"
    ],
    "wof:name":"Camcao Transportation",
    "wof:placetype":"venue"
},
  "geometry": {"coordinates":[-83.004486,39.986995],"type":"Point"}
}