{
  "type": "Feature",
  "properties": {
    "addr:full": "12916 State Rte 664 Scn Logan OH 43138",
    "addr:housenumber": "12916",
    "addr:postcode": "43138",
    "addr:street": "State Rte 664 Scn",
    "iso:country": "US",
    "sg:address": "12916 State Rte 664 Scn",
    "sg:city": "Logan",
    "sg:classifiers": [
      {
        "category": "Autos \u0026 Motor Vehicles",
        "subcategory": "Automobile Sales",
        "type": "Retail Goods"
      }
    ],
    "sg:phone": "+1 740 385 5624",
    "sg:postcode": "43138",
    "sg:province": "OH",
    "sg:website": "www.donwood.com",
    "wof:name": "Don Wood Automotive LTD",
    "wof:placetype": "venue"
  },
  "geometry": {"coordinates":[-82.439017,39.540982],"type":"Point"}
}
