{
  "type": "Feature",
  "properties": {
    "addr:full": "69216 Boden Rd New Concord OH 43762",
    "addr:postcode": "69216;43762",
    "addr:street": "Boden Rd",
    "iso:country": "US",
    "sg:address": "69216 Boden Rd",
    "sg:city": "New Concord",
    "sg:classifiers": [
      {
        "category": "Government",
        "subcategory": "Office",
        "type": "Public Place"
      }
    ],
    "sg:phone": "+1 740 432 4152",
    "sg:postcode": "43762",
    "sg:province": "OH",
    "sg:tags": [
      "executive"
    ],
    "wof:name": "Knox Township",
    "wof:placetype": "venue"
  },
  "geometry": {"coordinates":[-81.703037,40.114695],"type":"Point"}
}
