{
  "type": "Feature",
  "properties": {
    "iso:country":"US",
    "sg:address":"6233 Smith Rd",
    "sg:city":"Cleveland",
    "sg:classifiers":[
        {
            "category":"Social Services",
            "subcategory":"Child Care",
            "type":"Services"
        }
    ],
    "sg:phone":"+1 216 676 4043",
    "sg:postcode":"44142",
    "sg:province":"OH",
    "sg:tags":[
        "day"
    ],
    "wof:name":"Childtime Childrens Ctr 522",
    "wof:placetype":"venue"
},
  "geometry": {"coordinates":[-81.804382,41.396669],"type":"Point"}
}