{
  "type": "Feature",
  "properties": {
    "addr:full": "3408 Marvin Ave Cleveland OH 44109",
    "addr:housenumber": "3408",
    "addr:postcode": "44109",
    "addr:street": "Marvin Ave",
    "iso:country": "US",
    "sg:address": "3408 Marvin Ave",
    "sg:city": "Cleveland",
    "sg:classifiers": [
      {
        "category": "Banks \u0026 Credit Unions",
        "subcategory": "Investment Brokerage",
        "type": "Services"
      }
    ],
    "sg:phone": "+1 216 739 0609",
    "sg:postcode": "44109",
    "sg:province": "OH",
    "sg:tags": [
      "advisory"
    ],
    "wof:name": "SOS Financial Services LLC",
    "wof:placetype": "venue"
  },
  "geometry": {"coordinates":[-81.705626,41.46004],"type":"Point"}
}
