{
  "type": "Feature",
  "properties": {
    "iso:country":"US",
    "sg:address":"3408 Marvin Ave",
    "sg:city":"Cleveland",
    "sg:classifiers":[
        {
            "category":"Banks & Credit Unions",
            "subcategory":"Investment Brokerage",
            "type":"Services"
        }
    ],
    "sg:phone":"+1 216 739 0609",
    "sg:postcode":"44109",
    "sg:province":"OH",
    "sg:tags":[
        "advisory"
    ],
    "wof:name":"SOS Financial Services LLC",
    "wof:placetype":"venue"
},
  "geometry": {"coordinates":[-81.705626,41.46004],"type":"Point"}
}