{
  "type": "Feature",
  "properties": {
    "addr:full": "19895 Ringgold Southern Rd Circleville OH 43113",
    "addr:housenumber": "19895",
    "addr:postcode": "43113",
    "addr:street": "Ringgold Southern Rd",
    "iso:country": "US",
    "sg:address": "19895 Ringgold Southern Rd",
    "sg:city": "Circleville",
    "sg:classifiers": [
      {
        "category": "Building \u0026 Trades",
        "subcategory": "Construction",
        "type": "Services"
      }
    ],
    "sg:phone": "+1 740 474 8848",
    "sg:postcode": "43113",
    "sg:province": "OH",
    "sg:tags": [
      "barn"
    ],
    "wof:name": "Clear Span Builders",
    "wof:placetype": "venue"
  },
  "geometry": {"coordinates":[-82.864864,39.639676],"type":"Point"}
}
