{
  "type": "Feature",
  "properties": {
    "iso:country":"US",
    "sg:address":"14661 Robinson Rd",
    "sg:city":"Plain City",
    "sg:classifiers":[
        {
            "category":"Building & Trades",
            "subcategory":"Construction",
            "type":"Services"
        }
    ],
    "sg:phone":"+1 614 873 3078",
    "sg:postcode":"43064",
    "sg:province":"OH",
    "sg:tags":[
        "carpentry",
        "contractor"
    ],
    "wof:name":"Vernon Headings",
    "wof:placetype":"venue"
},
  "geometry": {"coordinates":[-83.31626799999999,40.133409],"type":"Point"}
}