{
  "type": "Feature",
  "properties": {
    "addr:full": "14661 Robinson Rd Plain City OH 43064",
    "addr:housenumber": "14661",
    "addr:postcode": "43064",
    "addr:street": "Robinson Rd",
    "iso:country": "US",
    "sg:address": "14661 Robinson Rd",
    "sg:city": "Plain City",
    "sg:classifiers": [
      {
        "category": "Building \u0026 Trades",
        "subcategory": "Construction",
        "type": "Services"
      }
    ],
    "sg:phone": "+1 614 873 3078",
    "sg:postcode": "43064",
    "sg:province": "OH",
    "sg:tags": [
      "carpentry",
      "contractor"
    ],
    "wof:name": "Vernon Headings",
    "wof:placetype": "venue"
  },
  "geometry": {"coordinates":[-83.316268,40.133409],"type":"Point"}
}
