{
  "type": "Feature",
  "properties": {
    "addr:full": "19185 N Benton Rd W North Benton OH 44449",
    "addr:housenumber": "19185",
    "addr:postcode": "44449",
    "addr:street": "N Benton Rd W North",
    "iso:country": "US",
    "sg:address": "19185 N Benton Rd W",
    "sg:city": "North Benton",
    "sg:classifiers": [
      {
        "category": "Farming",
        "subcategory": "Dairy Farm",
        "type": "Manufacturing \u0026 Wholesale Goods"
      }
    ],
    "sg:phone": "+1 330 584 3683",
    "sg:postcode": "44449",
    "sg:province": "OH",
    "sg:tags": [
      "corn",
      "wheat"
    ],
    "wof:name": "Carl Lenore",
    "wof:placetype": "venue"
  },
  "geometry": {"coordinates":[-81.01554,40.982388],"type":"Point"}
}
