{
  "type": "Feature",
  "properties": {
    "addr:full":"7621 Euclid Ave Cleveland OH 44103",
    "addr:housenumber":"7621",
    "addr:postcode":"44103",
    "addr:street":"Euclid Ave",
    "iso:country":"US",
    "sg:address":"7621 Euclid Ave",
    "sg:city":"Cleveland",
    "sg:classifiers":[
        {
            "category":"Real Estate",
            "subcategory":"Real Estate Agent",
            "type":"Services"
        }
    ],
    "sg:phone":"+1 216 458 0224",
    "sg:postcode":"44103",
    "sg:province":"OH",
    "sg:tags":[
        "authorities",
        "housing"
    ],
    "wof:name":"Cleveland Housing & Erie",
    "wof:placetype":"venue"
},
  "geometry": {"coordinates":[-81.635739,41.503994],"type":"Point"}
}