{
  "type": "Feature",
  "properties": {
    "iso:country":"US",
    "sg:address":"654 South St",
    "sg:city":"Wheelersburg",
    "sg:classifiers":[
        {
            "category":"Retail",
            "subcategory":"Repair Shop",
            "type":"Services"
        }
    ],
    "sg:phone":"+1 740 574 6177",
    "sg:postcode":"45694",
    "sg:province":"OH",
    "sg:tags":[
        "appliance"
    ],
    "wof:name":"Paul's Appliance Svc",
    "wof:placetype":"venue"
},
  "geometry": {"coordinates":[-82.854821,38.729192],"type":"Point"}
}