{
  "type": "Feature",
  "properties": {
    "iso:country":"US",
    "sg:address":"2781 Shakercrest Blvd",
    "sg:city":"Cleveland",
    "sg:classifiers":[
        {
            "category":"Manufacturing",
            "subcategory":"Printing",
            "type":"Manufacturing & Wholesale Goods"
        }
    ],
    "sg:phone":"+1 216 831 5620",
    "sg:postcode":"44122",
    "sg:province":"OH",
    "sg:tags":[
        "commercial"
    ],
    "wof:name":"Judith R & Brad H Swimmer",
    "wof:placetype":"venue"
},
  "geometry": {"coordinates":[-81.50325599999999,41.480806],"type":"Point"}
}