{
  "type": "Feature",
  "properties": {
    "addr:full": "2781 Shakercrest Blvd Cleveland OH 44122",
    "addr:housenumber": "2781",
    "addr:postcode": "44122",
    "addr:street": "Shakercrest Blvd",
    "iso:country": "US",
    "sg:address": "2781 Shakercrest Blvd",
    "sg:city": "Cleveland",
    "sg:classifiers": [
      {
        "category": "Manufacturing",
        "subcategory": "Printing",
        "type": "Manufacturing \u0026 Wholesale Goods"
      }
    ],
    "sg:phone": "+1 216 831 5620",
    "sg:postcode": "44122",
    "sg:province": "OH",
    "sg:tags": [
      "commercial"
    ],
    "wof:name": "Judith R \u0026 Brad H Swimmer",
    "wof:placetype": "venue"
  },
  "geometry": {"coordinates":[-81.503256,41.480806],"type":"Point"}
}
