{
  "type": "Feature",
  "properties": {
    "addr:full": "4433 Mahoning Ave NW Warren OH 44483",
    "addr:housenumber": "4433",
    "addr:postcode": "44483",
    "addr:street": "Mahoning Ave Nw",
    "iso:country": "US",
    "sg:address": "4433 Mahoning Ave NW",
    "sg:city": "Warren",
    "sg:classifiers": [
      {
        "category": "Cinema",
        "subcategory": "Movie Rental",
        "type": "Entertainment"
      }
    ],
    "sg:phone": "+1 330 847 8144",
    "sg:postcode": "44483",
    "sg:province": "OH",
    "sg:tags": [
      "video",
      "tape"
    ],
    "wof:name": "Champions Movie Gallery",
    "wof:placetype": "venue"
  },
  "geometry": {"coordinates":[-80.844558,41.281711],"type":"Point"}
}
