{
  "type": "Feature",
  "properties": {
    "iso:country":"US",
    "sg:address":"621 Richmond Rd",
    "sg:city":"Cleveland",
    "sg:classifiers":[
        {
            "category":"Shopping",
            "subcategory":"Clothing, Apparel, & Fashions",
            "type":"Retail Goods"
        }
    ],
    "sg:phone":"+1 440 461 2926",
    "sg:postcode":"44143",
    "sg:province":"OH",
    "sg:tags":[
        "shop",
        "specialty"
    ],
    "wof:name":"Afterthoughts",
    "wof:placetype":"venue"
},
  "geometry": {"coordinates":[-81.4971,41.54218],"type":"Point"}
}