{
  "type": "Feature",
  "properties": {
    "iso:country":"US",
    "sg:address":"8950 Rossash Rd",
    "sg:city":"Cincinnati",
    "sg:classifiers":[
        {
            "category":"Shopping",
            "subcategory":"Florist",
            "type":"Retail Goods"
        }
    ],
    "sg:phone":"+1 513 242 3111",
    "sg:postcode":"45236",
    "sg:province":"OH",
    "sg:website":"www.jonestheflorist.com",
    "wof:name":"Jones The Florist",
    "wof:placetype":"venue"
},
  "geometry": {"coordinates":[-84.390777,39.221199],"type":"Point"}
}