{
  "type": "Feature",
  "properties": {
    "iso:country":"US",
    "sg:address":"6623 Hitchingpost Ln",
    "sg:city":"Cincinnati",
    "sg:classifiers":[
        {
            "category":"Manufacturing",
            "subcategory":"Signs",
            "type":"Manufacturing & Wholesale Goods"
        }
    ],
    "sg:phone":"+1 513 233 9444",
    "sg:postcode":"45230",
    "sg:province":"OH",
    "sg:tags":[
        "advertising",
        "specialty"
    ],
    "wof:name":"Signs On Site",
    "wof:placetype":"venue"
},
  "geometry": {"coordinates":[-84.37894,39.069312],"type":"Point"}
}