{
  "type": "Feature",
  "properties": {
    "iso:country":"US",
    "sg:address":"5311 Northfield Rd",
    "sg:city":"Cleveland",
    "sg:classifiers":[
        {
            "category":"Professional",
            "subcategory":"Engineering",
            "type":"Services"
        }
    ],
    "sg:phone":"+1 216 581 9262",
    "sg:postcode":"44146",
    "sg:province":"OH",
    "sg:tags":[
        "engineer"
    ],
    "wof:name":"Intelligent Building Syst Inc",
    "wof:placetype":"venue"
},
  "geometry": {"coordinates":[-81.52729100000001,41.415161],"type":"Point"}
}