{
  "type": "Feature",
  "properties": {
    "addr:full": "623 E Main St Kent OH 44240",
    "addr:housenumber": "623",
    "addr:postcode": "44240",
    "addr:street": "E Main St",
    "iso:country": "US",
    "sg:address": "623 E Main St",
    "sg:city": "Kent",
    "sg:classifiers": [
      {
        "category": "Food \u0026 Beverages",
        "subcategory": "Specialty",
        "type": "Retail Goods"
      },
      {
        "category": "Wholesale",
        "subcategory": "Groceries",
        "type": "Manufacturing \u0026 Wholesale Goods"
      }
    ],
    "sg:phone": "+1 330 677 0101",
    "sg:postcode": "44240",
    "sg:province": "OH",
    "sg:tags": [
      "tea",
      "coffee"
    ],
    "wof:name": "Susan's Coffee \u0026 Tea",
    "wof:placetype": "venue"
  },
  "geometry": {"coordinates":[-81.348686,41.153865],"type":"Point"}
}
