{
  "type": "Feature",
  "properties": {
    "iso:country":"US",
    "sg:address":"623 E Main St",
    "sg:city":"Kent",
    "sg:classifiers":[
        {
            "category":"Food & Beverages",
            "subcategory":"Specialty",
            "type":"Retail Goods"
        },
        {
            "category":"Wholesale",
            "subcategory":"Groceries",
            "type":"Manufacturing & Wholesale Goods"
        }
    ],
    "sg:phone":"+1 330 677 0101",
    "sg:postcode":"44240",
    "sg:province":"OH",
    "sg:tags":[
        "tea",
        "coffee"
    ],
    "wof:name":"Susan's Coffee & Tea",
    "wof:placetype":"venue"
},
  "geometry": {"coordinates":[-81.348686,41.153865],"type":"Point"}
}