{
  "type": "Feature",
  "properties": {
    "iso:country":"US",
    "sg:address":"2745 Northland Plaza Dr",
    "sg:city":"Columbus",
    "sg:classifiers":[
        {
            "category":"Home & Garden",
            "subcategory":"Furniture",
            "type":"Retail Goods"
        }
    ],
    "sg:phone":"+1 614 776 5535",
    "sg:postcode":"43231",
    "sg:province":"OH",
    "wof:name":"Furniture Decor Cym Inc",
    "wof:placetype":"venue"
},
  "geometry": {"coordinates":[-82.94842,40.083619],"type":"Point"}
}