{
  "type": "Feature",
  "properties": {
    "addr:full": "2745 Northland Plaza Dr Columbus OH 43231",
    "addr:housenumber": "2745",
    "addr:postcode": "43231",
    "addr:street": "Northland Plaza Dr",
    "iso:country": "US",
    "sg:address": "2745 Northland Plaza Dr",
    "sg:city": "Columbus",
    "sg:classifiers": [
      {
        "category": "Home \u0026 Garden",
        "subcategory": "Furniture",
        "type": "Retail Goods"
      }
    ],
    "sg:phone": "+1 614 776 5535",
    "sg:postcode": "43231",
    "sg:province": "OH",
    "wof:name": "Furniture Decor Cym Inc",
    "wof:placetype": "venue"
  },
  "geometry": {"coordinates":[-82.94842,40.083619],"type":"Point"}
}
