{
  "type": "Feature",
  "properties": {
    "iso:country":"US",
    "sg:address":"7623 W Chester Rd",
    "sg:city":"West Chester",
    "sg:classifiers":[
        {
            "category":"Professional",
            "type":"Services"
        }
    ],
    "sg:phone":"+1 513 777 1897",
    "sg:postcode":"45069",
    "sg:province":"OH",
    "wof:name":"Richard W & Billie R Whit",
    "wof:placetype":"venue"
},
  "geometry": {"coordinates":[-84.37255500000001,39.318658],"type":"Point"}
}