{
  "type": "Feature",
  "properties": {
    "addr:full":"3032 Center Rd Poland OH 44514",
    "addr:housenumber":"3032",
    "addr:postcode":"44514",
    "addr:street":"Center Rd",
    "iso:country":"US",
    "sg:address":"3032 Center Rd",
    "sg:city":"Poland",
    "sg:classifiers":[
        {
            "category":"Restaurant",
            "type":"Food & Drink"
        }
    ],
    "sg:phone":"+1 330 757 0738",
    "sg:postcode":"44514",
    "sg:province":"OH",
    "wof:name":"Ezio's Banquet Room & Catering",
    "wof:placetype":"venue"
},
  "geometry": {"coordinates":[-80.591847,41.023806],"type":"Point"}
}