{
  "type": "Feature",
  "properties": {
    "iso:country":"US",
    "sg:address":"5800 Monroe St",
    "sg:city":"Sylvania",
    "sg:classifiers":[
        {
            "category":"Wholesale",
            "subcategory":"Durable Goods & Equipment",
            "type":"Manufacturing & Wholesale Goods"
        }
    ],
    "sg:phone":"+1 419 882 5412",
    "sg:postcode":"43560",
    "sg:province":"OH",
    "sg:tags":[
        "representative",
        "manufacturer"
    ],
    "wof:name":"Specialty Construction Product",
    "wof:placetype":"venue"
},
  "geometry": {"coordinates":[-83.684654,41.714327],"type":"Point"}
}