{
  "type": "Feature",
  "properties": {
    "iso:country":"US",
    "sg:address":"6025 Cork County Dr",
    "sg:city":"Galloway",
    "sg:classifiers":[
        {
            "category":"Retail",
            "subcategory":"Car Wash",
            "type":"Services"
        }
    ],
    "sg:phone":"+1 614 539 1322",
    "sg:postcode":"43119",
    "sg:province":"OH",
    "sg:tags":[
        "automobile",
        "detail",
        "clean"
    ],
    "wof:name":"Poorboy's Tire & Auto Detail",
    "wof:placetype":"venue"
},
  "geometry": {"coordinates":[-83.156676,39.937444],"type":"Point"}
}