{
  "type": "Feature",
  "properties": {
    "iso:country":"US",
    "sg:address":"14357 Kramer Rd",
    "sg:city":"Bowling Green",
    "sg:classifiers":[
        {
            "category":"Building & Trades",
            "subcategory":"Landscaping Services",
            "type":"Services"
        }
    ],
    "sg:phone":"+1 419 353 4400",
    "sg:postcode":"43402",
    "sg:province":"OH",
    "wof:name":"Andersons Technologies Inc",
    "wof:placetype":"venue"
},
  "geometry": {"coordinates":[-83.680809,41.342572],"type":"Point"}
}