{
  "type": "Feature",
  "properties": {
    "addr:full":"918 S Front St Columbus OH 43206",
    "addr:housenumber":"918",
    "addr:postcode":"43206",
    "addr:street":"S Front St",
    "iso:country":"US",
    "sg:address":"918 S Front St",
    "sg:city":"Columbus",
    "sg:classifiers":[
        {
            "category":"Health Services",
            "subcategory":"Health Practitioner",
            "type":"Services"
        }
    ],
    "sg:phone":"+1 614 445 8277",
    "sg:postcode":"43206",
    "sg:province":"OH",
    "sg:tags":[
        "psychologist"
    ],
    "wof:name":"Affirmations",
    "wof:placetype":"venue"
},
  "geometry": {"coordinates":[-82.998544,39.942724],"type":"Point"}
}