{
  "type": "Feature",
  "properties": {
    "addr:full":"105 Woodland Ave Swanton OH 43558",
    "addr:housenumber":"105",
    "addr:postcode":"43558",
    "addr:street":"Woodland Ave",
    "iso:country":"US",
    "sg:address":"105 Woodland Ave",
    "sg:city":"Swanton",
    "sg:classifiers":[
        {
            "category":"Professional",
            "subcategory":"Research",
            "type":"Services"
        }
    ],
    "sg:phone":"+1 419 826 2880",
    "sg:postcode":"43558",
    "sg:province":"OH",
    "sg:tags":[
        "development",
        "laboratory"
    ],
    "wof:name":"Energystics Technolgies",
    "wof:placetype":"venue"
},
  "geometry": {"coordinates":[-83.890067,41.591259],"type":"Point"}
}