{
  "type": "Feature",
  "properties": {
    "addr:full": "32505 Center Ridge Rd North Ridgeville OH 44039",
    "addr:housenumber": "32505",
    "addr:postcode": "44039",
    "addr:street": "Center Ridge Rd",
    "iso:country": "US",
    "sg:address": "32505 Center Ridge Rd",
    "sg:city": "North Ridgeville",
    "sg:classifiers": [
      {
        "category": "Food \u0026 Beverages",
        "subcategory": "Groceries \u0026 Convenience Stores",
        "type": "Retail Goods"
      }
    ],
    "sg:phone": "+1 440 327 7093",
    "sg:postcode": "44039",
    "sg:province": "OH",
    "sg:website": "www.convenientfoodmart.com",
    "wof:name": "Convenient Food Mart",
    "wof:placetype": "venue"
  },
  "geometry": {"coordinates":[-81.978594,41.408218],"type":"Point"}
}
