{
  "type": "Feature",
  "properties": {
    "iso:country":"US",
    "sg:address":"32505 Center Ridge Rd",
    "sg:city":"North Ridgeville",
    "sg:classifiers":[
        {
            "category":"Food & Beverages",
            "subcategory":"Groceries & Convenience Stores",
            "type":"Retail Goods"
        }
    ],
    "sg:phone":"+1 440 327 7093",
    "sg:postcode":"44039",
    "sg:province":"OH",
    "sg:website":"www.convenientfoodmart.com",
    "wof:name":"Convenient Food Mart",
    "wof:placetype":"venue"
},
  "geometry": {"coordinates":[-81.978594,41.408218],"type":"Point"}
}