{
  "type": "Feature",
  "properties": {
    "addr:full": "4685 Morse Rd Gahanna OH 43230",
    "addr:housenumber": "4685",
    "addr:postcode": "43230",
    "addr:street": "Morse Rd",
    "iso:country": "US",
    "sg:address": "4685 Morse Rd",
    "sg:city": "Gahanna",
    "sg:classifiers": [
      {
        "category": "Shopping",
        "type": "Retail Goods"
      }
    ],
    "sg:phone": "+1 614 478 1678",
    "sg:postcode": "43230",
    "sg:province": "OH",
    "sg:tags": [
      "cosmetic",
      "perfume"
    ],
    "wof:name": "Merle Norman Cosmetics",
    "wof:placetype": "venue"
  },
  "geometry": {"coordinates":[-82.866928,40.055507],"type":"Point"}
}
