{
  "type": "Feature",
  "properties": {
    "iso:country":"US",
    "sg:address":"4685 Morse Rd",
    "sg:city":"Gahanna",
    "sg:classifiers":[
        {
            "category":"Shopping",
            "type":"Retail Goods"
        }
    ],
    "sg:phone":"+1 614 478 1678",
    "sg:postcode":"43230",
    "sg:province":"OH",
    "sg:tags":[
        "cosmetic",
        "perfume"
    ],
    "wof:name":"Merle Norman Cosmetics",
    "wof:placetype":"venue"
},
  "geometry": {"coordinates":[-82.866928,40.055507],"type":"Point"}
}