{
  "type": "Feature",
  "properties": {
    "iso:country":"US",
    "sg:address":"121 Harrison St",
    "sg:city":"Sherwood",
    "sg:classifiers":[
        {
            "category":"Personal",
            "type":"Services"
        }
    ],
    "sg:phone":"+1 419 899 3513",
    "sg:postcode":"43512",
    "sg:province":"OH",
    "sg:tags":[
        "therapist",
        "massage"
    ],
    "wof:name":"Sherwood Massotherapy",
    "wof:placetype":"venue"
},
  "geometry": {"coordinates":[-84.553359,41.291858],"type":"Point"}
}