{
  "type": "Feature",
  "properties": {
    "addr:full": "1371 Beech St Zanesville OH 43701",
    "addr:housenumber": "1371",
    "addr:postcode": "43701",
    "addr:street": "Beech St",
    "iso:country": "US",
    "sg:address": "1371 Beech St",
    "sg:city": "Zanesville",
    "sg:classifiers": [
      {
        "category": "Wholesale",
        "subcategory": "Chemicals \u0026 Plastics",
        "type": "Manufacturing \u0026 Wholesale Goods"
      }
    ],
    "sg:phone": "+1 330 966 2700",
    "sg:postcode": "43701",
    "sg:province": "OH",
    "sg:tags": [
      "recycled",
      "glass"
    ],
    "wof:name": "Ensley Corporation",
    "wof:placetype": "venue"
  },
  "geometry": {"coordinates":[-82.04222,39.906286],"type":"Point"}
}
