{
  "type": "Feature",
  "properties": {
    "addr:full": "425 Central Ave Springfield OH 45505",
    "addr:housenumber": "425",
    "addr:postcode": "45505",
    "addr:street": "Central Ave",
    "iso:country": "US",
    "sg:address": "425 Central Ave",
    "sg:city": "Springfield",
    "sg:classifiers": [
      {
        "category": "Wholesale",
        "subcategory": "Machinery \u0026 Supplies",
        "type": "Manufacturing \u0026 Wholesale Goods"
      }
    ],
    "sg:phone": "+1 937 525 0903",
    "sg:postcode": "45505",
    "sg:province": "OH",
    "sg:tags": [
      "equipment",
      "industrial"
    ],
    "wof:name": "Blessing Pump \u0026 Water Systems",
    "wof:placetype": "venue"
  },
  "geometry": {"coordinates":[-83.797371,39.91741],"type":"Point"}
}
