{
  "type": "Feature",
  "properties": {
    "addr:full": "4541 Tuscarawas St W Canton OH 44708",
    "addr:housenumber": "4541",
    "addr:postcode": "44708",
    "addr:street": "Tuscarawas St W",
    "iso:country": "US",
    "sg:address": "4541 Tuscarawas St W",
    "sg:city": "Canton",
    "sg:classifiers": [
      {
        "category": "Shopping",
        "subcategory": "Bicycles \u0026 Sporting Goods",
        "type": "Retail Goods"
      }
    ],
    "sg:phone": "+1 330 477 9693",
    "sg:postcode": "44708",
    "sg:province": "OH",
    "sg:tags": [
      "repair"
    ],
    "wof:name": "Dell's Cyclery",
    "wof:placetype": "venue"
  },
  "geometry": {"coordinates":[-81.429397,40.796056],"type":"Point"}
}
