{
  "type": "Feature",
  "properties": {
    "iso:country":"US",
    "sg:address":"4285 Broadway",
    "sg:city":"Grove City",
    "sg:classifiers":[
        {
            "category":"Wholesale",
            "subcategory":"Farm Supplies",
            "type":"Manufacturing & Wholesale Goods"
        }
    ],
    "sg:phone":"+1 740 788 9688",
    "sg:postcode":"43123",
    "sg:province":"OH",
    "sg:tags":[
        "horse",
        "dealer"
    ],
    "wof:name":"United Equine Marketing Svc",
    "wof:placetype":"venue"
},
  "geometry": {"coordinates":[-83.098129,39.877038],"type":"Point"}
}