{
  "type": "Feature",
  "properties": {
    "iso:country":"US",
    "sg:address":"1965 W 44th St",
    "sg:city":"Cleveland",
    "sg:classifiers":[
        {
            "category":"Organizations",
            "subcategory":"Religious Organization",
            "type":"Services"
        }
    ],
    "sg:phone":"+1 216 631 8075",
    "sg:postcode":"44113",
    "sg:province":"OH",
    "sg:tags":[
        "church"
    ],
    "wof:name":"First Hispanic United Meth Chr",
    "wof:placetype":"venue"
},
  "geometry": {"coordinates":[-81.716403,41.480017],"type":"Point"}
}