{
  "type": "Feature",
  "properties": {
    "addr:full": "206 Landemere Ct Delaware OH 43015",
    "addr:housenumber": "206",
    "addr:postcode": "43015",
    "addr:street": "Landemere Ct",
    "iso:country": "US",
    "sg:address": "206 Landemere Ct",
    "sg:city": "Delaware",
    "sg:classifiers": [
      {
        "category": "Farming",
        "subcategory": "Nursery",
        "type": "Manufacturing \u0026 Wholesale Goods"
      }
    ],
    "sg:phone": "+1 740 369 8613",
    "sg:postcode": "43015",
    "sg:province": "OH",
    "sg:tags": [
      "ornamental"
    ],
    "wof:name": "Package Plant Professional",
    "wof:placetype": "venue"
  },
  "geometry": {"coordinates":[-83.102041,40.311691],"type":"Point"}
}
