{
  "type": "Feature",
  "properties": {
    "iso:country":"US",
    "sg:address":"206 Landemere Ct",
    "sg:city":"Delaware",
    "sg:classifiers":[
        {
            "category":"Farming",
            "subcategory":"Nursery",
            "type":"Manufacturing & Wholesale Goods"
        }
    ],
    "sg:phone":"+1 740 369 8613",
    "sg:postcode":"43015",
    "sg:province":"OH",
    "sg:tags":[
        "ornamental"
    ],
    "wof:name":"Package Plant Professional",
    "wof:placetype":"venue"
},
  "geometry": {"coordinates":[-83.102041,40.311691],"type":"Point"}
}