{
  "type": "Feature",
  "properties": {
    "addr:full": "6371 Sawmill Rd Dublin OH 43017",
    "addr:housenumber": "6371",
    "addr:postcode": "43017",
    "addr:street": "Sawmill Rd",
    "iso:country": "US",
    "sg:address": "6371 Sawmill Rd",
    "sg:city": "Dublin",
    "sg:classifiers": [
      {
        "category": "Shopping",
        "subcategory": "Clothing, Apparel, \u0026 Fashions",
        "type": "Retail Goods"
      }
    ],
    "sg:phone": "+1 614 764 0033",
    "sg:postcode": "43017",
    "sg:province": "OH",
    "wof:name": "Opening Night",
    "wof:placetype": "venue"
  },
  "geometry": {"coordinates":[-83.091628,40.095583],"type":"Point"}
}
