{
  "type": "Feature",
  "properties": {
    "iso:country":"US",
    "sg:address":"14167 Rd K",
    "sg:city":"Ottawa",
    "sg:classifiers":[
        {
            "category":"Farming",
            "subcategory":"Dairy Farm",
            "type":"Manufacturing & Wholesale Goods"
        }
    ],
    "sg:phone":"+1 419 538 6371",
    "sg:postcode":"45875",
    "sg:province":"OH",
    "wof:name":"Jim Meyerhoffer",
    "wof:placetype":"venue"
},
  "geometry": {"coordinates":[-84.133861,41.02103],"type":"Point"}
}