{
  "type": "Feature",
  "properties": {
    "addr:full": "14167 Rd K Ottawa OH 45875",
    "addr:postcode": "14167;45875",
    "addr:street": "Rd",
    "iso:country": "US",
    "sg:address": "14167 Rd K",
    "sg:city": "Ottawa",
    "sg:classifiers": [
      {
        "category": "Farming",
        "subcategory": "Dairy Farm",
        "type": "Manufacturing \u0026 Wholesale Goods"
      }
    ],
    "sg:phone": "+1 419 538 6371",
    "sg:postcode": "45875",
    "sg:province": "OH",
    "wof:name": "Jim Meyerhoffer",
    "wof:placetype": "venue"
  },
  "geometry": {"coordinates":[-84.133861,41.02103],"type":"Point"}
}
