{
  "type": "Feature",
  "properties": {
    "addr:full":"886 Bexley Dr Perrysburg OH 43551",
    "addr:housenumber":"886",
    "addr:postcode":"43551",
    "addr:street":"Bexley Dr",
    "iso:country":"US",
    "sg:address":"886 Bexley Dr",
    "sg:city":"Perrysburg",
    "sg:classifiers":[
        {
            "category":"Travel",
            "subcategory":"Travel Agent",
            "type":"Entertainment"
        }
    ],
    "sg:phone":"+1 419 872 0088",
    "sg:postcode":"43551",
    "sg:province":"OH",
    "sg:tags":[
        "agency"
    ],
    "wof:name":"Fragile Ocean",
    "wof:placetype":"venue"
},
  "geometry": {"coordinates":[-83.60896700000001,41.554647],"type":"Point"}
}