{
  "type": "Feature",
  "properties": {
    "iso:country":"US",
    "sg:address":"9675 Cincinnati Columbus Rd",
    "sg:city":"Cincinnati",
    "sg:classifiers":[
        {
            "category":"Food & Beverages",
            "subcategory":"Specialty",
            "type":"Retail Goods"
        },
        {
            "category":"Restaurant",
            "type":"Food & Drink"
        }
    ],
    "sg:phone":"+1 513 777 7422",
    "sg:postcode":"45241",
    "sg:province":"OH",
    "sg:tags":[
        "tea",
        "coffee",
        "eating"
    ],
    "wof:name":"Caruso Coffee Co LLC",
    "wof:placetype":"venue"
},
  "geometry": {"coordinates":[-84.382813,39.308981],"type":"Point"}
}