{
  "type": "Feature",
  "properties": {
    "addr:full":"1668 Merriman Rd Akron OH 44313",
    "addr:housenumber":"1668",
    "addr:postcode":"44313",
    "addr:street":"Merriman Rd",
    "iso:country":"US",
    "sg:address":"1668 Merriman Rd",
    "sg:city":"Akron",
    "sg:classifiers":[
        {
            "category":"Personal",
            "subcategory":"Beauty Salon",
            "type":"Services"
        }
    ],
    "sg:phone":"+1 330 865 0800",
    "sg:postcode":"44313",
    "sg:province":"OH",
    "wof:name":"Jacqui Davis",
    "wof:placetype":"venue"
},
  "geometry": {"coordinates":[-81.55188,41.1343],"type":"Point"}
}