{
  "type": "Feature",
  "properties": {
    "addr:full":"2827 Columbus Ave Ashtabula OH 44004",
    "addr:housenumber":"2827",
    "addr:postcode":"44004",
    "addr:street":"Columbus Ave",
    "iso:country":"US",
    "sg:address":"2827 Columbus Ave",
    "sg:city":"Ashtabula",
    "sg:classifiers":[
        {
            "category":"Building & Trades",
            "subcategory":"Construction",
            "type":"Services"
        }
    ],
    "sg:phone":"+1 440 992 3905",
    "sg:postcode":"44004",
    "sg:province":"OH",
    "sg:tags":[
        "contractor"
    ],
    "wof:name":"Farr Marvin Jr Plst & Drywall",
    "wof:placetype":"venue"
},
  "geometry": {"coordinates":[-80.78332899999999,41.881234],"type":"Point"}
}