{
  "type": "Feature",
  "properties": {
    "addr:full": "12005 Prospect Rd Strongsville OH 44149",
    "addr:housenumber": "12005",
    "addr:postcode": "44149",
    "addr:street": "Prospect Rd",
    "iso:country": "US",
    "sg:address": "12005 Prospect Rd",
    "sg:city": "Strongsville",
    "sg:classifiers": [
      {
        "category": "Home \u0026 Garden",
        "subcategory": "Furniture",
        "type": "Retail Goods"
      }
    ],
    "sg:phone": "+1 440 878 4284",
    "sg:postcode": "44149",
    "sg:province": "OH",
    "wof:name": "DRK Custom Woodworks",
    "wof:placetype": "venue"
  },
  "geometry": {"coordinates":[-81.857692,41.320767],"type":"Point"}
}
