{
  "type": "Feature",
  "properties": {
    "addr:full": "1046 Canton Rd Akron OH 44312",
    "addr:housenumber": "1046",
    "addr:postcode": "44312",
    "addr:street": "Canton Rd",
    "iso:country": "US",
    "sg:address": "1046 Canton Rd",
    "sg:city": "Akron",
    "sg:classifiers": [
      {
        "category": "Personal",
        "subcategory": "Barber",
        "type": "Services"
      }
    ],
    "sg:phone": "+1 330 733 5633",
    "sg:postcode": "44312",
    "sg:province": "OH",
    "wof:name": "George's Barber Shop \u0026 Hair",
    "wof:placetype": "venue"
  },
  "geometry": {"coordinates":[-81.43141,41.036285],"type":"Point"}
}
