{
  "type": "Feature",
  "properties": {
    "addr:full": "14433 Cedar Rd Cleveland OH 44121",
    "addr:housenumber": "14433",
    "addr:postcode": "44121",
    "addr:street": "Cedar Rd",
    "iso:country": "US",
    "sg:address": "14433 Cedar Rd",
    "sg:city": "Cleveland",
    "sg:classifiers": [
      {
        "category": "Shopping",
        "subcategory": "Optical Goods",
        "type": "Retail Goods"
      },
      {
        "category": "Health Services",
        "subcategory": "Optometrist",
        "type": "Services"
      }
    ],
    "sg:phone": "+1 216 291 1255",
    "sg:postcode": "44121",
    "sg:province": "OH",
    "sg:tags": [
      "medical"
    ],
    "wof:name": "Michael Schloss Od Inc",
    "wof:placetype": "venue"
  },
  "geometry": {"coordinates":[-81.520083,41.501432],"type":"Point"}
}
