{
  "type": "Feature",
  "properties": {
    "addr:full": "1 Allen Bradley Dr Cleveland OH 44124",
    "addr:housenumber": "1",
    "addr:postcode": "44124",
    "addr:street": "Allen Bradley Dr",
    "iso:country": "US",
    "sg:address": "1 Allen Bradley Dr",
    "sg:city": "Cleveland",
    "sg:classifiers": [
      {
        "category": "Manufacturing",
        "subcategory": "Tools \u0026 Machinery",
        "type": "Manufacturing \u0026 Wholesale Goods"
      }
    ],
    "sg:phone": "+1 440 646 4507",
    "sg:postcode": "44124",
    "sg:province": "OH",
    "sg:tags": [
      "equipment",
      "mfg",
      "system",
      "automation"
    ],
    "sg:website": "www.ab.com",
    "wof:name": "Rockwell Automation  Inc",
    "wof:placetype": "venue"
  },
  "geometry": {"coordinates":[-81.453527,41.505793],"type":"Point"}
}
