{
  "type": "Feature",
  "properties": {
    "addr:full": "2774 Parkman Rd NW Warren OH 44485",
    "addr:housenumber": "2774",
    "addr:postcode": "44485",
    "addr:street": "Parkman Rd Nw",
    "iso:country": "US",
    "sg:address": "2774 Parkman Rd NW",
    "sg:city": "Warren",
    "sg:classifiers": [
      {
        "category": "Food \u0026 Beverages",
        "subcategory": "Groceries \u0026 Convenience Stores",
        "type": "Retail Goods"
      }
    ],
    "sg:phone": "+1 630 879 8100",
    "sg:postcode": "44485",
    "sg:province": "OH",
    "wof:name": "Aldi Inc (illinois)",
    "wof:placetype": "venue"
  },
  "geometry": {"coordinates":[-80.860256,41.254604],"type":"Point"}
}
