{
  "type": "Feature",
  "properties": {
    "iso:country":"US",
    "sg:address":"2774 Parkman Rd NW",
    "sg:city":"Warren",
    "sg:classifiers":[
        {
            "category":"Food & Beverages",
            "subcategory":"Groceries & Convenience Stores",
            "type":"Retail Goods"
        }
    ],
    "sg:phone":"+1 630 879 8100",
    "sg:postcode":"44485",
    "sg:province":"OH",
    "wof:name":"Aldi Inc (illinois)",
    "wof:placetype":"venue"
},
  "geometry": {"coordinates":[-80.860256,41.254604],"type":"Point"}
}