{
  "type": "Feature",
  "properties": {
    "iso:country":"US",
    "sg:address":"5886 State Rte 132",
    "sg:city":"Morrow",
    "sg:classifiers":[
        {
            "category":"Organizations",
            "subcategory":"Religious Organization",
            "type":"Services"
        }
    ],
    "sg:phone":"+1 513 899 3471",
    "sg:postcode":"45152",
    "sg:province":"OH",
    "sg:tags":[
        "church"
    ],
    "wof:name":"Sugar Run Valley Baptist Chr",
    "wof:placetype":"venue"
},
  "geometry": {"coordinates":[-84.05611,39.341408],"type":"Point"}
}