{
  "type": "Feature",
  "properties": {
    "iso:country":"US",
    "sg:address":"600 N Aurora Rd",
    "sg:city":"Aurora",
    "sg:classifiers":[
        {
            "category":"Travel",
            "subcategory":"Hotels & Motels",
            "type":"Entertainment"
        }
    ],
    "sg:phone":"+1 330 995 0200",
    "sg:postcode":"44202",
    "sg:province":"OH",
    "sg:tags":[
        "operation",
        "physical",
        "drinking",
        "fitness"
    ],
    "wof:name":"Bertram Inn",
    "wof:placetype":"venue"
},
  "geometry": {"coordinates":[-81.361492,41.33038],"type":"Point"}
}