{
  "type": "Feature",
  "properties": {
    "addr:full": "210 E Boundary St Perrysburg OH 43551",
    "addr:housenumber": "210",
    "addr:postcode": "43551",
    "addr:street": "E Boundary St",
    "iso:country": "US",
    "sg:address": "210 E Boundary St",
    "sg:city": "Perrysburg",
    "sg:classifiers": [
      {
        "category": "Organizations",
        "subcategory": "Religious Organization",
        "type": "Services"
      }
    ],
    "sg:phone": "+1 419 874 5896",
    "sg:postcode": "43551",
    "sg:province": "OH",
    "sg:tags": [
      "church"
    ],
    "sg:website": "www.bridgewaynaz.com",
    "wof:name": "Perrysburg Church-The Nazarene",
    "wof:placetype": "venue"
  },
  "geometry": {"coordinates":[-83.61724,41.563044],"type":"Point"}
}
