{
  "type": "Feature",
  "properties": {
    "addr:full": "972 Beechwood Rd Columbus OH 43227",
    "addr:housenumber": "972",
    "addr:postcode": "43227",
    "addr:street": "Beechwood Rd",
    "iso:country": "US",
    "sg:address": "972 Beechwood Rd",
    "sg:city": "Columbus",
    "sg:classifiers": [
      {
        "category": "Organizations",
        "subcategory": "Religious Organization",
        "type": "Services"
      }
    ],
    "sg:phone": "+1 614 235 0670",
    "sg:postcode": "43227",
    "sg:province": "OH",
    "sg:tags": [
      "church"
    ],
    "sg:website": "www.ccceast.org",
    "wof:name": "Christian Community Church",
    "wof:placetype": "venue"
  },
  "geometry": {"coordinates":[-82.894456,39.952637],"type":"Point"}
}
