{
  "type": "Feature",
  "properties": {
    "addr:full": "56 Elm St Shelby OH 44875",
    "addr:housenumber": "56",
    "addr:postcode": "44875",
    "addr:street": "Elm St",
    "iso:country": "US",
    "sg:address": "56 Elm St",
    "sg:city": "Shelby",
    "sg:classifiers": [
      {
        "category": "Professional",
        "type": "Services"
      },
      {
        "category": "Professional",
        "subcategory": "Business Services",
        "type": "Services"
      }
    ],
    "sg:phone": "+1 419 342 2300",
    "sg:postcode": "44875",
    "sg:province": "OH",
    "sg:tags": [
      "notary"
    ],
    "wof:name": "C C Notary",
    "wof:placetype": "venue"
  },
  "geometry": {"coordinates":[-82.65301,40.89452],"type":"Point"}
}
