{
  "type": "Feature",
  "properties": {
    "addr:full": "1446 S Main St Akron OH 44301",
    "addr:housenumber": "1446",
    "addr:postcode": "44301",
    "addr:street": "S Main St",
    "iso:country": "US",
    "sg:address": "1446 S Main St",
    "sg:city": "Akron",
    "sg:classifiers": [
      {
        "category": "Retail",
        "subcategory": "Funeral Services",
        "type": "Services"
      }
    ],
    "sg:phone": "+1 330 724 9351",
    "sg:postcode": "44301",
    "sg:province": "OH",
    "sg:tags": [
      "director"
    ],
    "wof:name": "Schermesser Funeral Home Inc",
    "wof:placetype": "venue"
  },
  "geometry": {"coordinates":[-81.527558,41.047441],"type":"Point"}
}
