{
  "type": "Feature",
  "properties": {
    "iso:country":"US",
    "sg:address":"24 Brown St",
    "sg:city":"Barberton",
    "sg:classifiers":[
        {
            "category":"Wholesale",
            "subcategory":"Non-durable Goods",
            "type":"Manufacturing & Wholesale Goods"
        }
    ],
    "sg:phone":"+1 330 745 9400",
    "sg:postcode":"44203",
    "sg:province":"OH",
    "sg:tags":[
        "wholesaler",
        "imported"
    ],
    "wof:name":"24 Brown Street Inc",
    "wof:placetype":"venue"
},
  "geometry": {"coordinates":[-81.602084,41.019442],"type":"Point"}
}