{
  "type": "Feature",
  "properties": {
    "addr:full": "2023 Lawrence Ave Cincinnati OH 45212",
    "addr:housenumber": "2023",
    "addr:postcode": "45212",
    "addr:street": "Lawrence Ave",
    "iso:country": "US",
    "sg:address": "2023 Lawrence Ave",
    "sg:city": "Cincinnati",
    "sg:classifiers": [
      {
        "category": "Building \u0026 Trades",
        "subcategory": "Plumbing",
        "type": "Services"
      }
    ],
    "sg:phone": "+1 513 271 4328",
    "sg:postcode": "45212",
    "sg:province": "OH",
    "sg:tags": [
      "heating",
      "contractor"
    ],
    "wof:name": "Pendrex Heating Cooling",
    "wof:placetype": "venue"
  },
  "geometry": {"coordinates":[-84.459633,39.160004],"type":"Point"}
}
