{
  "type": "Feature",
  "properties": {
    "iso:country":"US",
    "sg:address":"30 Inter Meadows Way",
    "sg:city":"Powell",
    "sg:classifiers":[
        {
            "category":"Insurance",
            "subcategory":"Insurance Agent",
            "type":"Services"
        }
    ],
    "sg:phone":"+1 740 548 9991",
    "sg:postcode":"43065",
    "sg:province":"OH",
    "wof:name":"Frank CHI",
    "wof:placetype":"venue"
},
  "geometry": {"coordinates":[-83.032297,40.161836],"type":"Point"}
}