{
  "type": "Feature",
  "properties": {
    "iso:country":"US",
    "sg:address":"2000 Auburn Dr",
    "sg:city":"Cleveland",
    "sg:classifiers":[
        {
            "category":"Building & Trades",
            "subcategory":"Plumbing",
            "type":"Services"
        }
    ],
    "sg:phone":"+1 216 896 1400",
    "sg:postcode":"44122",
    "sg:province":"OH",
    "sg:tags":[
        "contractor"
    ],
    "wof:name":"Simplexgrinnell LP",
    "wof:placetype":"venue"
},
  "geometry": {"coordinates":[-81.494076,41.457198],"type":"Point"}
}