{
  "type": "Feature",
  "properties": {
    "addr:full": "5317 Frank Ave NW North Canton OH 44720",
    "addr:housenumber": "5317",
    "addr:postcode": "44720",
    "addr:street": "Frank Ave Nw",
    "iso:country": "US",
    "sg:address": "5317 Frank Ave NW",
    "sg:city": "North Canton",
    "sg:classifiers": [
      {
        "category": "Recreation",
        "type": "Entertainment"
      }
    ],
    "sg:phone": "+1 330 499 7980",
    "sg:postcode": "44720",
    "sg:province": "OH",
    "sg:tags": [
      "concessionaire"
    ],
    "wof:name": "Earl H Kline Inc",
    "wof:placetype": "venue"
  },
  "geometry": {"coordinates":[-81.442205,40.861153],"type":"Point"}
}
