{
  "type": "Feature",
  "properties": {
    "addr:full": "2350 Brookpark Rd Cleveland OH 44134",
    "addr:housenumber": "2350",
    "addr:postcode": "44134",
    "addr:street": "Brookpark Rd",
    "iso:country": "US",
    "sg:address": "2350 Brookpark Rd",
    "sg:city": "Cleveland",
    "sg:classifiers": [
      {
        "category": "Restaurant",
        "type": "Food \u0026 Drink"
      }
    ],
    "sg:menulink": "http://www.allmenus.com/oh/cleveland/67457-east-of-chicago-pizza/menu/",
    "sg:phone": "+1 216 658 3278",
    "sg:postcode": "44134",
    "sg:province": "OH",
    "sg:tags": [
      "sandwich",
      "salad",
      "soup",
      "american",
      "wrap",
      "pizza"
    ],
    "wof:name": "East of Chicago Pizza",
    "wof:placetype": "venue"
  },
  "geometry": {"coordinates":[-81.69797,41.419148],"type":"Point"}
}
