{
  "type": "Feature",
  "properties": {
    "iso:country":"US",
    "sg:address":"1727 E Long St",
    "sg:city":"Columbus",
    "sg:classifiers":[
        {
            "category":"Shopping",
            "type":"Retail Goods"
        },
        {
            "category":"Wholesale",
            "subcategory":"Electrical",
            "type":"Manufacturing & Wholesale Goods"
        }
    ],
    "sg:phone":"+1 614 253 3319",
    "sg:postcode":"43203",
    "sg:province":"OH",
    "sg:tags":[
        "fire",
        "alarm",
        "burglar",
        "system"
    ],
    "wof:name":"Shield Security Systems Inc",
    "wof:placetype":"venue"
},
  "geometry": {"coordinates":[-82.954226,39.968639],"type":"Point"}
}