{
  "type": "Feature",
  "properties": {
    "iso:country":"US",
    "sg:address":"680 E Dayton Yellow Springs Rd",
    "sg:city":"Fairborn",
    "sg:classifiers":[
        {
            "category":"Health Services",
            "subcategory":"Health Practitioner",
            "type":"Services"
        }
    ],
    "sg:phone":"+1 937 390 3800",
    "sg:postcode":"45324",
    "sg:province":"OH",
    "sg:tags":[
        "psychologist"
    ],
    "wof:name":"Positive Perspectives Inc",
    "wof:placetype":"venue"
},
  "geometry": {"coordinates":[-83.949071,39.792223],"type":"Point"}
}