{
  "type": "Feature",
  "properties": {
    "addr:full": "187 Park Ave Conneaut OH 44030",
    "addr:housenumber": "187",
    "addr:postcode": "44030",
    "addr:street": "Park Ave",
    "iso:country": "US",
    "sg:address": "187 Park Ave",
    "sg:city": "Conneaut",
    "sg:classifiers": [
      {
        "category": "Bars \u0026 Pubs",
        "type": "Food \u0026 Drink"
      }
    ],
    "sg:phone": "+1 440 593 1603",
    "sg:postcode": "44030",
    "sg:province": "OH",
    "wof:name": "Bottomline Sports Lounge",
    "wof:placetype": "venue"
  },
  "geometry": {"coordinates":[-80.551093,41.965515],"type":"Point"}
}
