{
  "type": "Feature",
  "properties": {
    "addr:full": "359 E Pike St Morrow OH 45152",
    "addr:housenumber": "359",
    "addr:postcode": "45152",
    "addr:street": "E Pike St",
    "iso:country": "US",
    "sg:address": "359 E Pike St",
    "sg:city": "Morrow",
    "sg:classifiers": [
      {
        "category": "Restaurant",
        "type": "Food \u0026 Drink"
      }
    ],
    "sg:phone": "+1 513 899 4100",
    "sg:postcode": "45152",
    "sg:province": "OH",
    "wof:name": "Chubby's Pizza Of Morrow",
    "wof:placetype": "venue"
  },
  "geometry": {"coordinates":[-84.123021,39.35503],"type":"Point"}
}
