{
  "type": "Feature",
  "properties": {
    "iso:country":"US",
    "sg:address":"359 E Pike St",
    "sg:city":"Morrow",
    "sg:classifiers":[
        {
            "category":"Restaurant",
            "type":"Food & Drink"
        }
    ],
    "sg:phone":"+1 513 899 4100",
    "sg:postcode":"45152",
    "sg:province":"OH",
    "wof:name":"Chubby's Pizza Of Morrow",
    "wof:placetype":"venue"
},
  "geometry": {"coordinates":[-84.12302099999999,39.35503],"type":"Point"}
}