{
  "type": "Feature",
  "properties": {
    "iso:country":"US",
    "sg:address":"8060 South Ave",
    "sg:city":"Youngstown",
    "sg:classifiers":[
        {
            "category":"Health Services",
            "subcategory":"Nursing And Care Facility",
            "type":"Services"
        }
    ],
    "sg:phone":"+1 330 758 8855",
    "sg:postcode":"44512",
    "sg:province":"OH",
    "sg:tags":[
        "home"
    ],
    "wof:name":"Commons At The Greenbrier The",
    "wof:placetype":"venue"
},
  "geometry": {"coordinates":[-80.634035,41.003379],"type":"Point"}
}