{
  "type": "Feature",
  "properties": {
    "iso:country":"US",
    "sg:address":"2960 Pleasant Home Rd",
    "sg:city":"Burbank",
    "sg:classifiers":[
        {
            "category":"Shopping",
            "subcategory":"Gifts & Souvenirs",
            "type":"Retail Goods"
        }
    ],
    "sg:phone":"+1 419 846 1311",
    "sg:postcode":"44214",
    "sg:province":"OH",
    "wof:name":"Guys Wise Sports Cards",
    "wof:placetype":"venue"
},
  "geometry": {"coordinates":[-81.99436799999999,40.911685],"type":"Point"}
}