{
  "type": "Feature",
  "properties": {
    "addr:full": "2960 Pleasant Home Rd Burbank OH 44214",
    "addr:housenumber": "2960",
    "addr:postcode": "44214",
    "addr:street": "Pleasant Home Rd",
    "iso:country": "US",
    "sg:address": "2960 Pleasant Home Rd",
    "sg:city": "Burbank",
    "sg:classifiers": [
      {
        "category": "Shopping",
        "subcategory": "Gifts \u0026 Souvenirs",
        "type": "Retail Goods"
      }
    ],
    "sg:phone": "+1 419 846 1311",
    "sg:postcode": "44214",
    "sg:province": "OH",
    "wof:name": "Guys Wise Sports Cards",
    "wof:placetype": "venue"
  },
  "geometry": {"coordinates":[-81.994368,40.911685],"type":"Point"}
}
