{
  "type": "Feature",
  "properties": {
    "iso:country":"US",
    "sg:address":"6856 N Clubside Dr",
    "sg:city":"Andover",
    "sg:classifiers":[
        {
            "category":"Travel",
            "subcategory":"Travel Agent",
            "type":"Entertainment"
        }
    ],
    "sg:phone":"+1 440 293 4112",
    "sg:postcode":"44003",
    "sg:province":"OH",
    "sg:tags":[
        "agency",
        "bureau"
    ],
    "wof:name":"Palange's Travel",
    "wof:placetype":"venue"
},
  "geometry": {"coordinates":[-80.536896,41.568177],"type":"Point"}
}