{
  "type": "Feature",
  "properties": {
    "addr:full":"8190 Beechmont Ave Cincinnati OH 45255",
    "addr:housenumber":"8190",
    "addr:postcode":"45255",
    "addr:street":"Beechmont Ave",
    "iso:country":"US",
    "sg:address":"8190 Beechmont Ave",
    "sg:city":"Cincinnati",
    "sg:classifiers":[
        {
            "category":"Professional",
            "subcategory":"Computer Services",
            "type":"Services"
        }
    ],
    "sg:phone":"+1 513 233 3370",
    "sg:postcode":"45255",
    "sg:province":"OH",
    "sg:tags":[
        "graphics"
    ],
    "wof:name":"Imaging Solutions",
    "wof:placetype":"venue"
},
  "geometry": {"coordinates":[-84.32760399999999,39.072906],"type":"Point"}
}