{
  "type": "Feature",
  "properties": {
    "iso:country":"US",
    "sg:address":"12 N Walnut St",
    "sg:city":"Englewood",
    "sg:classifiers":[
        {
            "category":"Building & Trades",
            "subcategory":"Construction",
            "type":"Services"
        }
    ],
    "sg:phone":"+1 937 832 3440",
    "sg:postcode":"45322",
    "sg:province":"OH",
    "sg:tags":[
        "restoration",
        "cleaning",
        "patio",
        "deck"
    ],
    "wof:name":"FACILITEC-USA Inc",
    "wof:placetype":"venue"
},
  "geometry": {"coordinates":[-84.30334000000001,39.878111],"type":"Point"}
}