{
  "type": "Feature",
  "properties": {
    "iso:country":"US",
    "sg:address":"602 W High Ave",
    "sg:city":"New Philadelphia",
    "sg:classifiers":[
        {
            "category":"Autos & Motor Vehicles",
            "subcategory":"Auto Supplies",
            "type":"Retail Goods"
        }
    ],
    "sg:phone":"+1 330 339 6323",
    "sg:postcode":"44663",
    "sg:province":"OH",
    "sg:tags":[
        "tire"
    ],
    "wof:name":"B & F Tire Inc",
    "wof:placetype":"venue"
},
  "geometry": {"coordinates":[-81.45755800000001,40.491493],"type":"Point"}
}