{
  "type": "Feature",
  "properties": {
    "addr:full": "602 W High Ave New Philadelphia OH 44663",
    "addr:housenumber": "602",
    "addr:postcode": "44663",
    "addr:street": "W High Ave",
    "iso:country": "US",
    "sg:address": "602 W High Ave",
    "sg:city": "New Philadelphia",
    "sg:classifiers": [
      {
        "category": "Autos \u0026 Motor Vehicles",
        "subcategory": "Auto Supplies",
        "type": "Retail Goods"
      }
    ],
    "sg:phone": "+1 330 339 6323",
    "sg:postcode": "44663",
    "sg:province": "OH",
    "sg:tags": [
      "tire"
    ],
    "wof:name": "B \u0026 F Tire Inc",
    "wof:placetype": "venue"
  },
  "geometry": {"coordinates":[-81.457558,40.491493],"type":"Point"}
}
