{
  "type": "Feature",
  "properties": {
    "addr:full":"2234 Emerson Rd Bloomdale OH 44817",
    "addr:housenumber":"2234",
    "addr:postcode":"44817",
    "addr:street":"Emerson Rd",
    "iso:country":"US",
    "sg:address":"2234 Emerson Rd",
    "sg:city":"Bloomdale",
    "sg:phone":"+1 419 454 4968",
    "sg:postcode":"44817",
    "sg:province":"OH",
    "sg:tags":[
        "farm",
        "corn",
        "wheat",
        "soybean"
    ],
    "wof:name":"Dennis Nye",
    "wof:placetype":"venue"
},
  "geometry": {"coordinates":[-83.535079,41.180808],"type":"Point"}
}