{
  "type": "Feature",
  "properties": {
    "iso:country":"US",
    "sg:address":"500 Main St",
    "sg:city":"Morrow",
    "sg:classifiers":[
        {
            "category":"Recreation",
            "type":"Entertainment"
        }
    ],
    "sg:phone":"+1 513 518 0882",
    "sg:postcode":"45152",
    "sg:province":"OH",
    "sg:tags":[
        "charter",
        "canoe"
    ],
    "wof:name":"Rivertime Canoe Rental",
    "wof:placetype":"venue"
},
  "geometry": {"coordinates":[-84.134894,39.355195],"type":"Point"}
}