{
  "type": "Feature",
  "properties": {
    "addr:full": "500 Main St Morrow OH 45152",
    "addr:housenumber": "500",
    "addr:postcode": "45152",
    "addr:street": "Main St",
    "iso:country": "US",
    "sg:address": "500 Main St",
    "sg:city": "Morrow",
    "sg:classifiers": [
      {
        "category": "Recreation",
        "type": "Entertainment"
      }
    ],
    "sg:phone": "+1 513 518 0882",
    "sg:postcode": "45152",
    "sg:province": "OH",
    "sg:tags": [
      "charter",
      "canoe"
    ],
    "wof:name": "Rivertime Canoe Rental",
    "wof:placetype": "venue"
  },
  "geometry": {"coordinates":[-84.134894,39.355195],"type":"Point"}
}
