{
  "type": "Feature",
  "properties": {
    "iso:country":"US",
    "sg:address":"4750 E Galbraith Rd",
    "sg:city":"Cincinnati",
    "sg:classifiers":[
        {
            "category":"Health Services",
            "subcategory":"Doctor",
            "type":"Services"
        }
    ],
    "sg:phone":"+1 513 686 4840",
    "sg:postcode":"45236",
    "sg:province":"OH",
    "sg:tags":[
        "physician",
        "surgeon"
    ],
    "wof:name":"Alliance Primary Care",
    "wof:placetype":"venue"
},
  "geometry": {"coordinates":[-84.379626,39.206717],"type":"Point"}
}