{
  "type": "Feature",
  "properties": {
    "addr:full":"4900 Boggs Rd Zanesville OH 43701",
    "addr:postcode":"4900;43701",
    "addr:street":"Boggs Rd",
    "iso:country":"US",
    "sg:address":"4900 Boggs Rd",
    "sg:city":"Zanesville",
    "sg:classifiers":[
        {
            "category":"Mining & Drilling",
            "type":"Manufacturing & Wholesale Goods"
        }
    ],
    "sg:phone":"+1 740 452 4503",
    "sg:postcode":"43701",
    "sg:province":"OH",
    "sg:tags":[
        "oil",
        "gas",
        "producer"
    ],
    "wof:name":"Oxford Oil Co",
    "wof:placetype":"venue"
},
  "geometry": {"coordinates":[-81.904853,39.970077],"type":"Point"}
}