{
  "type": "Feature",
  "properties": {
    "iso:country":"US",
    "sg:address":"294 Regatta Dr",
    "sg:city":"Avon Lake",
    "sg:classifiers":[
        {
            "category":"Social Services",
            "subcategory":"Child Care",
            "type":"Services"
        }
    ],
    "sg:phone":"+1 440 930 5399",
    "sg:postcode":"44012",
    "sg:province":"OH",
    "wof:name":"Monday Morning Moms",
    "wof:placetype":"venue"
},
  "geometry": {"coordinates":[-81.973448,41.499731],"type":"Point"}
}