{
  "type": "Feature",
  "properties": {
    "iso:country":"US",
    "sg:address":"5720 Westbourne Ave",
    "sg:city":"Columbus",
    "sg:classifiers":[
        {
            "category":"Building & Trades",
            "subcategory":"Construction",
            "type":"Services"
        }
    ],
    "sg:phone":"+1 614 751 5777",
    "sg:postcode":"43213",
    "sg:province":"OH",
    "sg:tags":[
        "repair",
        "window",
        "door",
        "patio"
    ],
    "wof:name":"National Patio Rooms Inc",
    "wof:placetype":"venue"
},
  "geometry": {"coordinates":[-82.849434,39.984446],"type":"Point"}
}