{
  "type": "Feature",
  "properties": {
    "addr:full": "4696 Dixie Hwy Fairfield OH 45014",
    "addr:housenumber": "4696",
    "addr:postcode": "45014",
    "addr:street": "Dixie Hwy",
    "iso:country": "US",
    "sg:address": "4696 Dixie Hwy",
    "sg:city": "Fairfield",
    "sg:classifiers": [
      {
        "category": "Restaurant",
        "type": "Food \u0026 Drink"
      }
    ],
    "sg:phone": "+1 513 829 7013",
    "sg:postcode": "45014",
    "sg:province": "OH",
    "sg:tags": [
      "diner"
    ],
    "wof:name": "Pearls Diner",
    "wof:placetype": "venue"
  },
  "geometry": {"coordinates":[-84.541951,39.348895],"type":"Point"}
}
