{
  "type": "Feature",
  "properties": {
    "addr:full": "600 W Superior Ave Cleveland OH 44113",
    "addr:housenumber": "600",
    "addr:postcode": "44113",
    "addr:street": "W Superior Ave",
    "iso:country": "US",
    "sg:address": "600 W Superior Ave",
    "sg:city": "Cleveland",
    "sg:classifiers": [
      {
        "category": "Real Estate",
        "subcategory": "Real Estate Agent",
        "type": "Services"
      }
    ],
    "sg:phone": "+1 216 522 1927",
    "sg:postcode": "44113",
    "sg:province": "OH",
    "wof:name": "Re Max Transaction Realty",
    "wof:placetype": "venue"
  },
  "geometry": {"coordinates":[-81.69859,41.497269],"type":"Point"}
}
