{
  "type": "Feature",
  "properties": {
    "addr:full": "77 S High St Columbus OH 43215",
    "addr:housenumber": "77",
    "addr:postcode": "43215",
    "addr:street": "S High St",
    "iso:country": "US",
    "sg:address": "77 S High St",
    "sg:city": "Columbus",
    "sg:classifiers": [
      {
        "category": "Government",
        "subcategory": "Office",
        "type": "Public Place"
      }
    ],
    "sg:phone": "+1 614 466 4433",
    "sg:postcode": "43215",
    "sg:province": "OH",
    "sg:tags": [
      "funds",
      "unclaimed"
    ],
    "wof:name": "Division of Unclaimed Funds",
    "wof:placetype": "venue"
  },
  "geometry": {"coordinates":[-83.000456,39.961082],"type":"Point"}
}
