{
  "type": "Feature",
  "properties": {
    "iso:country":"US",
    "sg:address":"417 Commerce St",
    "sg:city":"Tallmadge",
    "sg:classifiers":[
        {
            "category":"Real Estate",
            "subcategory":"Architect",
            "type":"Services"
        }
    ],
    "sg:phone":"+1 330 633 9225",
    "sg:postcode":"44278",
    "sg:province":"OH",
    "wof:name":"James Douglas Evans Architect",
    "wof:placetype":"venue"
},
  "geometry": {"coordinates":[-81.456311,41.099675],"type":"Point"}
}