{
  "type": "Feature",
  "properties": {
    "addr:full": "7340 Taylorsville Rd Dayton OH 45424",
    "addr:housenumber": "7340",
    "addr:postcode": "45424",
    "addr:street": "Taylorsville Rd",
    "iso:country": "US",
    "sg:address": "7340 Taylorsville Rd",
    "sg:city": "Dayton",
    "sg:classifiers": [
      {
        "category": "Shopping",
        "subcategory": "Crafts \u0026 Fabrics",
        "type": "Retail Goods"
      },
      {
        "category": "Shopping",
        "subcategory": "Gifts \u0026 Souvenirs",
        "type": "Retail Goods"
      }
    ],
    "sg:phone": "+1 937 233 7021",
    "sg:postcode": "45424",
    "sg:province": "OH",
    "sg:tags": [
      "shop"
    ],
    "wof:name": "Kittie's Country Accents",
    "wof:placetype": "venue"
  },
  "geometry": {"coordinates":[-84.087169,39.859983],"type":"Point"}
}
