{
  "type": "Feature",
  "properties": {
    "iso:country":"US",
    "sg:address":"7340 Taylorsville Rd",
    "sg:city":"Dayton",
    "sg:classifiers":[
        {
            "category":"Shopping",
            "subcategory":"Crafts & Fabrics",
            "type":"Retail Goods"
        },
        {
            "category":"Shopping",
            "subcategory":"Gifts & Souvenirs",
            "type":"Retail Goods"
        }
    ],
    "sg:phone":"+1 937 233 7021",
    "sg:postcode":"45424",
    "sg:province":"OH",
    "sg:tags":[
        "shop"
    ],
    "wof:name":"Kittie's Country Accents",
    "wof:placetype":"venue"
},
  "geometry": {"coordinates":[-84.087169,39.859983],"type":"Point"}
}