{
  "type": "Feature",
  "properties": {
    "iso:country":"US",
    "sg:address":"13069 Cleveland Ave NW",
    "sg:city":"Uniontown",
    "sg:classifiers":[
        {
            "category":"Shopping",
            "subcategory":"Computers & Home Electronics",
            "type":"Retail Goods"
        }
    ],
    "sg:phone":"+1 330 848 9311",
    "sg:postcode":"44685",
    "sg:province":"OH",
    "sg:tags":[
        "equipment",
        "dealer"
    ],
    "wof:name":"Electronic Technology Ctr",
    "wof:placetype":"venue"
},
  "geometry": {"coordinates":[-81.40810399999999,40.967175],"type":"Point"}
}