{
  "type": "Feature",
  "properties": {
    "addr:full": "13069 Cleveland Ave NW Uniontown OH 44685",
    "addr:housenumber": "13069",
    "addr:postcode": "44685",
    "addr:street": "Cleveland Ave Nw",
    "iso:country": "US",
    "sg:address": "13069 Cleveland Ave NW",
    "sg:city": "Uniontown",
    "sg:classifiers": [
      {
        "category": "Shopping",
        "subcategory": "Computers \u0026 Home Electronics",
        "type": "Retail Goods"
      }
    ],
    "sg:phone": "+1 330 848 9311",
    "sg:postcode": "44685",
    "sg:province": "OH",
    "sg:tags": [
      "equipment",
      "dealer"
    ],
    "wof:name": "Electronic Technology Ctr",
    "wof:placetype": "venue"
  },
  "geometry": {"coordinates":[-81.408104,40.967175],"type":"Point"}
}
