{
  "type": "Feature",
  "properties": {
    "addr:full": "1176 Ashland Ave Dayton OH 45420",
    "addr:housenumber": "1176",
    "addr:postcode": "45420",
    "addr:street": "Ashland Ave",
    "iso:country": "US",
    "sg:address": "1176 Ashland Ave",
    "sg:city": "Dayton",
    "sg:classifiers": [
      {
        "category": "Real Estate",
        "subcategory": "Real Estate Agent",
        "type": "Services"
      }
    ],
    "sg:phone": "+1 937 256 1512",
    "sg:postcode": "45420",
    "sg:province": "OH",
    "wof:name": "Ej Realty",
    "wof:placetype": "venue"
  },
  "geometry": {"coordinates":[-84.148159,39.721721],"type":"Point"}
}
