{
  "type": "Feature",
  "properties": {
    "iso:country":"US",
    "sg:address":"1176 Ashland Ave",
    "sg:city":"Dayton",
    "sg:classifiers":[
        {
            "category":"Real Estate",
            "subcategory":"Real Estate Agent",
            "type":"Services"
        }
    ],
    "sg:phone":"+1 937 256 1512",
    "sg:postcode":"45420",
    "sg:province":"OH",
    "wof:name":"Ej Realty",
    "wof:placetype":"venue"
},
  "geometry": {"coordinates":[-84.14815900000001,39.721721],"type":"Point"}
}