{
  "type": "Feature",
  "properties": {
    "addr:full": "325 Main St Bridgeport OH 43912",
    "addr:housenumber": "325",
    "addr:postcode": "43912",
    "addr:street": "Main St",
    "iso:country": "US",
    "sg:address": "325 Main St",
    "sg:city": "Bridgeport",
    "sg:classifiers": [
      {
        "category": "Banks \u0026 Credit Unions",
        "subcategory": "Bank",
        "type": "Services"
      }
    ],
    "sg:phone": "+1 740 695 3323",
    "sg:postcode": "43912",
    "sg:province": "OH",
    "sg:tags": [
      "national"
    ],
    "wof:name": "Belmont Bancorp",
    "wof:placetype": "venue"
  },
  "geometry": {"coordinates":[-80.743964,40.072364],"type":"Point"}
}
