{
  "type": "Feature",
  "properties": {
    "iso:country":"US",
    "sg:address":"325 Main St",
    "sg:city":"Bridgeport",
    "sg:classifiers":[
        {
            "category":"Banks & Credit Unions",
            "subcategory":"Bank",
            "type":"Services"
        }
    ],
    "sg:phone":"+1 740 695 3323",
    "sg:postcode":"43912",
    "sg:province":"OH",
    "sg:tags":[
        "national"
    ],
    "wof:name":"Belmont Bancorp",
    "wof:placetype":"venue"
},
  "geometry": {"coordinates":[-80.74396400000001,40.072364],"type":"Point"}
}