{
  "type": "Feature",
  "properties": {
    "addr:full": "121 E Main St Bainbridge OH 45612",
    "addr:housenumber": "121",
    "addr:postcode": "45612",
    "addr:street": "E Main St",
    "iso:country": "US",
    "sg:address": "121 E Main St",
    "sg:city": "Bainbridge",
    "sg:classifiers": [
      {
        "category": "Government",
        "subcategory": "Post Office",
        "type": "Public Place"
      }
    ],
    "sg:phone": "+1 740 634 2222",
    "sg:postcode": "45612",
    "sg:province": "OH",
    "wof:name": "US Post Office",
    "wof:placetype": "venue"
  },
  "geometry": {"coordinates":[-83.268553,39.227851],"type":"Point"}
}
