{
  "type": "Feature",
  "properties": {
    "iso:country":"US",
    "sg:address":"706 Napoleon Rd",
    "sg:city":"Bowling Green",
    "sg:classifiers":[
        {
            "category":"Travel",
            "subcategory":"Bed & Breakfast",
            "type":"Entertainment"
        }
    ],
    "sg:phone":"+1 419 353 5100",
    "sg:postcode":"43402",
    "sg:province":"OH",
    "sg:tags":[
        "housing",
        "student"
    ],
    "sg:website":"www.collegepark.org",
    "wof:name":"Enclave",
    "wof:placetype":"venue"
},
  "geometry": {"coordinates":[-83.642337,41.36371],"type":"Point"}
}