{
  "type": "Feature",
  "properties": {
    "iso:country":"US",
    "sg:address":"511 Solon Rd",
    "sg:city":"Chagrin Falls",
    "sg:classifiers":[
        {
            "category":"Building & Trades",
            "subcategory":"Construction",
            "type":"Services"
        }
    ],
    "sg:phone":"+1 440 247 6962",
    "sg:postcode":"44022",
    "sg:province":"OH",
    "sg:tags":[
        "general",
        "remodeling",
        "contractor"
    ],
    "wof:name":"Minglewood Bldrs & Restoration",
    "wof:placetype":"venue"
},
  "geometry": {"coordinates":[-81.403244,41.416684],"type":"Point"}
}