{
  "type": "Feature",
  "properties": {
    "addr:full": "511 Solon Rd Chagrin Falls OH 44022",
    "addr:housenumber": "511",
    "addr:postcode": "44022",
    "addr:street": "Solon Rd",
    "iso:country": "US",
    "sg:address": "511 Solon Rd",
    "sg:city": "Chagrin Falls",
    "sg:classifiers": [
      {
        "category": "Building \u0026 Trades",
        "subcategory": "Construction",
        "type": "Services"
      }
    ],
    "sg:phone": "+1 440 247 6962",
    "sg:postcode": "44022",
    "sg:province": "OH",
    "sg:tags": [
      "general",
      "remodeling",
      "contractor"
    ],
    "wof:name": "Minglewood Bldrs \u0026 Restoration",
    "wof:placetype": "venue"
  },
  "geometry": {"coordinates":[-81.403244,41.416684],"type":"Point"}
}
