{
  "type": "Feature",
  "properties": {
    "addr:full":"6900 Brandt Pike Dayton OH 45424",
    "addr:housenumber":"6900",
    "addr:postcode":"45424",
    "addr:street":"Brandt Pike",
    "iso:country":"US",
    "sg:address":"6900 Brandt Pike",
    "sg:city":"Dayton",
    "sg:classifiers":[
        {
            "category":"Organizations",
            "subcategory":"Religious Organization",
            "type":"Services"
        }
    ],
    "sg:phone":"+1 937 233 3137",
    "sg:postcode":"45424",
    "sg:province":"OH",
    "sg:tags":[
        "church"
    ],
    "sg:website":"www.hhchog.org",
    "wof:name":"Huber Heights Church Of God",
    "wof:placetype":"venue"
},
  "geometry": {"coordinates":[-84.110798,39.851509],"type":"Point"}
}