{
  "type": "Feature",
  "properties": {
    "iso:country":"US",
    "sg:address":"335 E 3rd St",
    "sg:city":"Ashland",
    "sg:classifiers":[
        {
            "category":"Real Estate",
            "subcategory":"Real Estate Agent",
            "type":"Services"
        }
    ],
    "sg:phone":"+1 419 207 8803",
    "sg:postcode":"44805",
    "sg:province":"OH",
    "wof:name":"Woodfield Group",
    "wof:placetype":"venue"
},
  "geometry": {"coordinates":[-82.30947399999999,40.869527],"type":"Point"}
}