{
  "type": "Feature",
  "properties": {
    "iso:country":"US",
    "sg:address":"2708 Akron Rd",
    "sg:city":"Wooster",
    "sg:classifiers":[
        {
            "category":"Wholesale",
            "subcategory":"Machinery & Supplies",
            "type":"Manufacturing & Wholesale Goods"
        }
    ],
    "sg:phone":"+1 330 263 1065",
    "sg:postcode":"44691",
    "sg:province":"OH",
    "sg:tags":[
        "fastener",
        "industrial",
        "threaded"
    ],
    "wof:name":"Fastenal Company",
    "wof:placetype":"venue"
},
  "geometry": {"coordinates":[-81.90839200000001,40.831219],"type":"Point"}
}