{
  "type": "Feature",
  "properties": {
    "iso:country":"US",
    "sg:address":"9731 Montgomery Rd",
    "sg:city":"Cincinnati",
    "sg:classifiers":[
        {
            "category":"Food & Beverages",
            "subcategory":"Groceries & Convenience Stores",
            "type":"Retail Goods"
        }
    ],
    "sg:phone":"+1 513 891 9280",
    "sg:postcode":"45242",
    "sg:province":"OH",
    "sg:tags":[
        "grocer"
    ],
    "wof:name":"Asiana",
    "wof:placetype":"venue"
},
  "geometry": {"coordinates":[-84.352386,39.23159],"type":"Point"}
}