{
  "type": "Feature",
  "properties": {
    "addr:full":"5779 Scarborough Blvd Columbus OH 43232",
    "addr:housenumber":"5779",
    "addr:postcode":"43232",
    "addr:street":"Scarborough Blvd",
    "iso:country":"US",
    "sg:address":"5779 Scarborough Blvd",
    "sg:city":"Columbus",
    "sg:classifiers":[
        {
            "category":"Shopping",
            "subcategory":"Clothing, Apparel, & Fashions",
            "type":"Retail Goods"
        }
    ],
    "sg:phone":"+1 614 861 2872",
    "sg:postcode":"43232",
    "sg:province":"OH",
    "sg:tags":[
        "printing",
        "screen",
        "silk",
        "design"
    ],
    "wof:name":"T-Shirt Alert",
    "wof:placetype":"venue"
},
  "geometry": {"coordinates":[-82.83768600000001,39.932507],"type":"Point"}
}