{
  "type": "Feature",
  "properties": {
    "addr:full": "866 Sherwood Dr Elyria OH 44035",
    "addr:housenumber": "866",
    "addr:postcode": "44035",
    "addr:street": "Sherwood Dr",
    "iso:country": "US",
    "sg:address": "866 Sherwood Dr",
    "sg:city": "Elyria",
    "sg:classifiers": [
      {
        "category": "Professional",
        "subcategory": "Business Services",
        "type": "Services"
      }
    ],
    "sg:phone": "+1 440 453 5576",
    "sg:postcode": "44035",
    "sg:province": "OH",
    "sg:tags": [
      "broker",
      "merchandise"
    ],
    "wof:name": "Diakinos",
    "wof:placetype": "venue"
  },
  "geometry": {"coordinates":[-82.07443,41.394856],"type":"Point"}
}
