{
  "type": "Feature",
  "properties": {
    "iso:country":"US",
    "sg:address":"39 Northview Pl",
    "sg:city":"Huron",
    "sg:classifiers":[
        {
            "category":"Retail",
            "subcategory":"Animal Services",
            "type":"Services"
        }
    ],
    "sg:phone":"+1 419 433 5046",
    "sg:postcode":"44839",
    "sg:province":"OH",
    "wof:name":"All Four Paws Pet Sitting",
    "wof:placetype":"venue"
},
  "geometry": {"coordinates":[-82.589382,41.412672],"type":"Point"}
}