{
  "type": "Feature",
  "properties": {
    "addr:full": "6435 W Chester Rd West Chester OH 45069",
    "addr:housenumber": "6435",
    "addr:postcode": "45069",
    "addr:street": "W Chester Rd",
    "iso:country": "US",
    "sg:address": "6435 W Chester Rd",
    "sg:city": "West Chester",
    "sg:classifiers": [
      {
        "category": "Organizations",
        "subcategory": "Professional Association",
        "type": "Services"
      }
    ],
    "sg:phone": "+1 513 326 7100",
    "sg:postcode": "45069",
    "sg:province": "OH",
    "sg:tags": [
      "warehouse",
      "co",
      "purchasing"
    ],
    "wof:name": "Greater Cincinnati Automobile",
    "wof:placetype": "venue"
  },
  "geometry": {"coordinates":[-84.412685,39.325785],"type":"Point"}
}
