{
  "type": "Feature",
  "properties": {
    "addr:full": "26001 Miles Rd Cleveland OH 44128",
    "addr:housenumber": "26001",
    "addr:postcode": "44128",
    "addr:street": "Miles Rd",
    "iso:country": "US",
    "sg:address": "26001 Miles Rd",
    "sg:city": "Cleveland",
    "sg:classifiers": [
      {
        "category": "Wholesale",
        "subcategory": "Electrical",
        "type": "Manufacturing \u0026 Wholesale Goods"
      }
    ],
    "sg:phone": "+1 440 248 8383",
    "sg:postcode": "44128",
    "sg:province": "OH",
    "sg:tags": [
      "equipment",
      "electronic",
      "supply"
    ],
    "wof:name": "Reh Electronics",
    "wof:placetype": "venue"
  },
  "geometry": {"coordinates":[-81.494479,41.424333],"type":"Point"}
}
