{
  "type": "Feature",
  "properties": {
    "addr:full": "2698 Eastman Ave Columbus OH 43207",
    "addr:housenumber": "2698",
    "addr:postcode": "43207",
    "addr:street": "Eastman Ave",
    "iso:country": "US",
    "sg:address": "2698 Eastman Ave",
    "sg:city": "Columbus",
    "sg:classifiers": [
      {
        "category": "Building \u0026 Trades",
        "subcategory": "Construction",
        "type": "Services"
      }
    ],
    "sg:phone": "+1 614 497 9648",
    "sg:postcode": "43207",
    "sg:province": "OH",
    "sg:tags": [
      "hanging",
      "contractor"
    ],
    "wof:name": "Jenkins Jl Painting",
    "wof:placetype": "venue"
  },
  "geometry": {"coordinates":[-82.991086,39.906462],"type":"Point"}
}
