{
  "type": "Feature",
  "properties": {
    "addr:full": "520 Cleveland Rd W Huron OH 44839",
    "addr:housenumber": "520",
    "addr:postcode": "44839",
    "addr:street": "Cleveland Rd W",
    "iso:country": "US",
    "sg:address": "520 Cleveland Rd W",
    "sg:city": "Huron",
    "sg:classifiers": [
      {
        "category": "Building \u0026 Trades",
        "subcategory": "Construction",
        "type": "Services"
      }
    ],
    "sg:phone": "+1 419 433 3090",
    "sg:postcode": "44839",
    "sg:province": "OH",
    "sg:tags": [
      "general",
      "contractor"
    ],
    "wof:name": "Peridia Inc",
    "wof:placetype": "venue"
  },
  "geometry": {"coordinates":[-82.561143,41.398336],"type":"Point"}
}
