{
  "type": "Feature",
  "properties": {
    "iso:country":"US",
    "sg:address":"7043 Strout Rd",
    "sg:city":"Morrow",
    "sg:classifiers":[
        {
            "category":"Building & Trades",
            "subcategory":"Construction",
            "type":"Services"
        }
    ],
    "sg:phone":"+1 513 899 9000",
    "sg:postcode":"45152",
    "sg:province":"OH",
    "sg:tags":[
        "roofing",
        "contractor"
    ],
    "wof:name":"A Ray Roofing",
    "wof:placetype":"venue"
},
  "geometry": {"coordinates":[-84.06947099999999,39.386428],"type":"Point"}
}