{
  "type": "Feature",
  "properties": {
    "addr:full": "7043 Strout Rd Morrow OH 45152",
    "addr:postcode": "7043;45152",
    "addr:street": "Strout Rd",
    "iso:country": "US",
    "sg:address": "7043 Strout Rd",
    "sg:city": "Morrow",
    "sg:classifiers": [
      {
        "category": "Building \u0026 Trades",
        "subcategory": "Construction",
        "type": "Services"
      }
    ],
    "sg:phone": "+1 513 899 9000",
    "sg:postcode": "45152",
    "sg:province": "OH",
    "sg:tags": [
      "roofing",
      "contractor"
    ],
    "wof:name": "A Ray Roofing",
    "wof:placetype": "venue"
  },
  "geometry": {"coordinates":[-84.069471,39.386428],"type":"Point"}
}
