{
  "type": "Feature",
  "properties": {
    "iso:country":"US",
    "sg:address":"956 Belvedere Ave SE",
    "sg:city":"Warren",
    "sg:classifiers":[
        {
            "category":"Building & Trades",
            "subcategory":"Construction",
            "type":"Services"
        }
    ],
    "sg:phone":"+1 330 307 1584",
    "sg:postcode":"44484",
    "sg:province":"OH",
    "sg:tags":[
        "general",
        "contractor"
    ],
    "wof:name":"Placer Construction",
    "wof:placetype":"venue"
},
  "geometry": {"coordinates":[-80.791673,41.228523],"type":"Point"}
}