{
  "type": "Feature",
  "properties": {
    "addr:full":"218 E 9th St Genoa OH 43430",
    "addr:housenumber":"218",
    "addr:postcode":"43430",
    "addr:street":"E 9Th St",
    "iso:country":"US",
    "sg:address":"218 E 9th St",
    "sg:city":"Genoa",
    "sg:classifiers":[
        {
            "category":"Building & Trades",
            "subcategory":"Construction",
            "type":"Services"
        }
    ],
    "sg:phone":"+1 419 855 4757",
    "sg:postcode":"43430",
    "sg:province":"OH",
    "sg:tags":[
        "general",
        "highway",
        "contractor"
    ],
    "wof:name":"Henry W Bergman Inc",
    "wof:placetype":"venue"
},
  "geometry": {"coordinates":[-83.35618100000001,41.521147],"type":"Point"}
}