{
  "type": "Feature",
  "properties": {
    "addr:full": "987 Co Rd 175 Polk OH 44866",
    "addr:housenumber": "987;175",
    "addr:postcode": "44866",
    "addr:street": "Co Rd",
    "iso:country": "US",
    "sg:address": "987 Co Rd 175",
    "sg:city": "Polk",
    "sg:classifiers": [
      {
        "category": "Food \u0026 Beverages",
        "subcategory": "Liquor \u0026 Beverages",
        "type": "Retail Goods"
      }
    ],
    "sg:phone": "+1 419 869 7227",
    "sg:postcode": "44866",
    "sg:province": "OH",
    "sg:tags": [
      "alcoholic"
    ],
    "wof:name": "Village Drive Thru",
    "wof:placetype": "venue"
  },
  "geometry": {"coordinates":[-82.163074,40.91777],"type":"Point"}
}
