{
  "type": "Feature",
  "properties": {
    "iso:country":"US",
    "sg:address":"6190 Shamrock Ct",
    "sg:city":"Dublin",
    "sg:classifiers":[
        {
            "category":"Banks & Credit Unions",
            "subcategory":"Bank",
            "type":"Services"
        }
    ],
    "sg:phone":"+1 614 766 4101",
    "sg:postcode":"43016",
    "sg:province":"OH",
    "sg:tags":[
        "term",
        "short",
        "institution"
    ],
    "wof:name":"Wells Fargo",
    "wof:placetype":"venue"
},
  "geometry": {"coordinates":[-83.13883800000001,40.09388],"type":"Point"}
}