{
  "type": "Feature",
  "properties": {
    "addr:full": "13800 Shaker Blvd Cleveland OH 44120",
    "addr:housenumber": "13800",
    "addr:postcode": "44120",
    "addr:street": "Shaker Blvd",
    "iso:country": "US",
    "sg:address": "13800 Shaker Blvd",
    "sg:city": "Cleveland",
    "sg:classifiers": [
      {
        "category": "Professional",
        "subcategory": "Business Services",
        "type": "Services"
      }
    ],
    "sg:phone": "+1 216 752 1116",
    "sg:postcode": "44120",
    "sg:province": "OH",
    "sg:tags": [
      "interior",
      "consultant",
      "design",
      "decorator"
    ],
    "wof:name": "Ed Simon Interiors ASID",
    "wof:placetype": "venue"
  },
  "geometry": {"coordinates":[-81.58757,41.483752],"type":"Point"}
}
