{
  "type": "Feature",
  "properties": {
    "addr:full": "79 N Trine St Canal Winchester OH 43110",
    "addr:housenumber": "79",
    "addr:postcode": "43110",
    "addr:street": "N Trine St",
    "iso:country": "US",
    "sg:address": "79 N Trine St",
    "sg:city": "Canal Winchester",
    "sg:classifiers": [
      {
        "category": "Professional",
        "subcategory": "Business Services",
        "type": "Services"
      }
    ],
    "sg:phone": "+1 614 833 6302",
    "sg:postcode": "43110",
    "sg:province": "OH",
    "sg:tags": [
      "auctioneer"
    ],
    "wof:name": "John B Auctions",
    "wof:placetype": "venue"
  },
  "geometry": {"coordinates":[-82.802729,39.841751],"type":"Point"}
}
