{
  "type": "Feature",
  "properties": {
    "iso:country":"US",
    "sg:address":"923 5th St NE",
    "sg:city":"Canton",
    "sg:classifiers":[
        {
            "category":"Shopping",
            "subcategory":"Used Merchandise",
            "type":"Retail Goods"
        },
        {
            "category":"Social Services",
            "type":"Services"
        }
    ],
    "sg:phone":"+1 330 454 4071",
    "sg:postcode":"44704",
    "sg:province":"OH",
    "sg:tags":[
        "shop",
        "thrift"
    ],
    "wof:name":"American Rescue Workers Inc",
    "wof:placetype":"venue"
},
  "geometry": {"coordinates":[-81.36578299999999,40.79972],"type":"Point"}
}