{
  "type": "Feature",
  "properties": {
    "addr:full":"31 Ranch Ct Bowling Green OH 43402",
    "addr:housenumber":"31",
    "addr:postcode":"43402",
    "addr:street":"Ranch Ct",
    "iso:country":"US",
    "sg:address":"31 Ranch Ct",
    "sg:city":"Bowling Green",
    "sg:phone":"+1 419 352 5783",
    "sg:postcode":"43402",
    "sg:province":"OH",
    "sg:tags":[
        "farm",
        "corn",
        "wheat",
        "soybean"
    ],
    "wof:name":"Herbert Kinder",
    "wof:placetype":"venue"
},
  "geometry": {"coordinates":[-83.663397,41.383493],"type":"Point"}
}