{
  "type": "Feature",
  "properties": {
    "addr:full":"1410 Silver Pine Ln Findlay OH 45840",
    "addr:housenumber":"1410",
    "addr:postcode":"45840",
    "addr:street":"Silver Pine Ln",
    "iso:country":"US",
    "sg:address":"1410 Silver Pine Ln",
    "sg:city":"Findlay",
    "sg:classifiers":[
        {
            "category":"Social Services",
            "type":"Services"
        }
    ],
    "sg:phone":"+1 419 421 0133",
    "sg:postcode":"45840",
    "sg:province":"OH",
    "sg:tags":[
        "instruction",
        "health",
        "care"
    ],
    "wof:name":"Teamhealth",
    "wof:placetype":"venue"
},
  "geometry": {"coordinates":[-83.676681,41.081282],"type":"Point"}
}