{
  "type": "Feature",
  "properties": {
    "addr:full": "550 W Chalmers Ave Youngstown OH 44511",
    "addr:housenumber": "550",
    "addr:postcode": "44511",
    "addr:street": "W Chalmers Ave",
    "iso:country": "US",
    "sg:address": "550 W Chalmers Ave",
    "sg:city": "Youngstown",
    "sg:classifiers": [
      {
        "category": "Health Services",
        "subcategory": "Doctor",
        "type": "Services"
      }
    ],
    "sg:phone": "+1 330 746 5600",
    "sg:postcode": "44511",
    "sg:province": "OH",
    "sg:tags": [
      "medical"
    ],
    "wof:name": "Meridian Health Care",
    "wof:placetype": "venue"
  },
  "geometry": {"coordinates":[-80.672858,41.085111],"type":"Point"}
}
