{
  "type": "Feature",
  "properties": {
    "iso:country":"US",
    "sg:address":"8285 Sharp Ln",
    "sg:city":"Chesterland",
    "sg:classifiers":[
        {
            "category":"Professional",
            "subcategory":"Engineering",
            "type":"Services"
        }
    ],
    "sg:phone":"+1 440 729 1740",
    "sg:postcode":"44026",
    "sg:province":"OH",
    "sg:tags":[
        "engineer"
    ],
    "wof:name":"F Calo Consulting Inc",
    "wof:placetype":"venue"
},
  "geometry": {"coordinates":[-81.33715100000001,41.569159],"type":"Point"}
}