{
  "type": "Feature",
  "properties": {
    "iso:country":"US",
    "sg:address":"3506 Co Rd 30",
    "sg:city":"Kitts Hill",
    "sg:classifiers":[
        {
            "category":"Farming",
            "subcategory":"Livestock Farm",
            "type":"Manufacturing & Wholesale Goods"
        }
    ],
    "sg:phone":"+1 740 532 9432",
    "sg:postcode":"45645",
    "sg:province":"OH",
    "sg:tags":[
        "equine"
    ],
    "wof:name":"Williams Horse Farm",
    "wof:placetype":"venue"
},
  "geometry": {"coordinates":[-82.525457,38.527595],"type":"Point"}
}