{
  "type": "Feature",
  "properties": {
    "addr:full": "404 S Francis St Kent OH 44240",
    "addr:housenumber": "404",
    "addr:postcode": "44240",
    "addr:street": "S Francis St",
    "iso:country": "US",
    "sg:address": "404 S Francis St",
    "sg:city": "Kent",
    "sg:classifiers": [
      {
        "category": "Freight",
        "type": "Transportation"
      }
    ],
    "sg:phone": "+1 330 677 0381",
    "sg:postcode": "44240",
    "sg:province": "OH",
    "sg:tags": [
      "mover"
    ],
    "wof:name": "Mr Mover Inc",
    "wof:placetype": "venue"
  },
  "geometry": {"coordinates":[-81.385686,41.150993],"type":"Point"}
}
