{
  "type": "Feature",
  "properties": {
    "addr:full":"555 E 88th St Cleveland OH 44108",
    "addr:housenumber":"555",
    "addr:postcode":"44108",
    "addr:street":"E 88Th St",
    "iso:country":"US",
    "sg:address":"555 E 88th St",
    "sg:city":"Cleveland",
    "sg:classifiers":[
        {
            "category":"Government",
            "subcategory":"Office",
            "type":"Public Place"
        }
    ],
    "sg:phone":"+1 216 522 5623",
    "sg:postcode":"44108",
    "sg:province":"OH",
    "sg:tags":[
        "security",
        "government-united",
        "homeland",
        "state"
    ],
    "wof:name":"Us Defense Dept",
    "wof:placetype":"venue"
},
  "geometry": {"coordinates":[-81.62758100000001,41.538271],"type":"Point"}
}