{
  "type": "Feature",
  "properties": {
    "addr:full": "950 Valley St Minerva OH 44657",
    "addr:housenumber": "950",
    "addr:postcode": "44657",
    "addr:street": "Valley St",
    "iso:country": "US",
    "sg:address": "950 Valley St",
    "sg:city": "Minerva",
    "sg:classifiers": [
      {
        "category": "Shopping",
        "subcategory": "Pharmacy",
        "type": "Retail Goods"
      }
    ],
    "sg:phone": "+1 330 868 4172",
    "sg:postcode": "44657",
    "sg:province": "OH",
    "sg:tags": [
      "drug",
      "store"
    ],
    "wof:name": "Rite Aid",
    "wof:placetype": "venue"
  },
  "geometry": {"coordinates":[-81.110507,40.719959],"type":"Point"}
}
