{
  "type": "Feature",
  "properties": {
    "addr:full":"15325 Edgecliff Ave Cleveland OH 44111",
    "addr:postcode":"15325;44111",
    "addr:street":"Edgecliff Ave",
    "iso:country":"US",
    "sg:address":"15325 Edgecliff Ave",
    "sg:city":"Cleveland",
    "sg:classifiers":[
        {
            "category":"Banks & Credit Unions",
            "subcategory":"Bank",
            "type":"Services"
        }
    ],
    "sg:phone":"+1 216 671 1377",
    "sg:postcode":"44111",
    "sg:province":"OH",
    "sg:tags":[
        "national",
        "commercial"
    ],
    "wof:name":"National City Bank",
    "wof:placetype":"venue"
},
  "geometry": {"coordinates":[-81.804874,41.464074],"type":"Point"}
}