{
  "type": "Feature",
  "properties": {
    "addr:full": "5172 Windorf Dr Westerville OH 43081",
    "addr:postcode": "5172;43081",
    "addr:street": "Windorf Dr",
    "iso:country": "US",
    "sg:address": "5172 Windorf Dr",
    "sg:city": "Westerville",
    "sg:classifiers": [
      {
        "category": "Banks \u0026 Credit Unions",
        "subcategory": "Financial Services",
        "type": "Services"
      }
    ],
    "sg:phone": "+1 614 523 2566",
    "sg:postcode": "43081",
    "sg:province": "OH",
    "sg:tags": [
      "company",
      "holding"
    ],
    "wof:name": "Meikle's Memories",
    "wof:placetype": "venue"
  },
  "geometry": {"coordinates":[-82.870828,40.081722],"type":"Point"}
}
