{
  "type": "Feature",
  "properties": {
    "addr:full":"1520 Marsetta Dr Dayton OH 45432",
    "addr:housenumber":"1520",
    "addr:postcode":"45432",
    "addr:street":"Marsetta Dr",
    "iso:country":"US",
    "sg:address":"1520 Marsetta Dr",
    "sg:city":"Dayton",
    "sg:classifiers":[
        {
            "category":"Wholesale",
            "subcategory":"Photographic Equipment",
            "type":"Manufacturing & Wholesale Goods"
        },
        {
            "category":"Professional",
            "subcategory":"Computer Services",
            "type":"Services"
        }
    ],
    "sg:phone":"+1 937 427 7770",
    "sg:postcode":"45432",
    "sg:province":"OH",
    "sg:tags":[
        "audio",
        "video",
        "it"
    ],
    "wof:name":"Techease Solutions LLC",
    "wof:placetype":"venue"
},
  "geometry": {"coordinates":[-84.066737,39.733864],"type":"Point"}
}