{
  "type": "Feature",
  "properties": {
    "iso:country":"US",
    "sg:address":"27484 Oregon Rd",
    "sg:city":"Perrysburg",
    "sg:classifiers":[
        {
            "category":"Building & Trades",
            "subcategory":"Construction",
            "type":"Services"
        }
    ],
    "sg:phone":"+1 419 666 6779",
    "sg:postcode":"43551",
    "sg:province":"OH",
    "sg:tags":[
        "concrete",
        "contractor"
    ],
    "wof:name":"R&L Concrete",
    "wof:placetype":"venue"
},
  "geometry": {"coordinates":[-83.538082,41.552772],"type":"Point"}
}