{
  "type": "Feature",
  "properties": {
    "iso:country":"US",
    "sg:address":"9447 Monroe Central Rd",
    "sg:city":"West Manchester",
    "sg:phone":"+1 937 678 5699",
    "sg:postcode":"45382",
    "sg:province":"OH",
    "sg:tags":[
        "farm",
        "soybean"
    ],
    "wof:name":"Bruno Jurgens",
    "wof:placetype":"venue"
},
  "geometry": {"coordinates":[-84.65209900000001,39.876932],"type":"Point"}
}