{
  "type": "Feature",
  "properties": {
    "addr:full":"1100 Maple Ct Cambridge OH 43725",
    "addr:housenumber":"1100",
    "addr:postcode":"43725",
    "addr:street":"Maple Ct",
    "iso:country":"US",
    "sg:address":"1100 Maple Ct",
    "sg:city":"Cambridge",
    "sg:classifiers":[
        {
            "category":"Government",
            "subcategory":"Office",
            "type":"Public Place"
        }
    ],
    "sg:phone":"+1 740 439 6651",
    "sg:postcode":"43725",
    "sg:province":"OH",
    "sg:tags":[
        "village"
    ],
    "wof:name":"Cambridge Metropolitan Housing",
    "wof:placetype":"venue"
},
  "geometry": {"coordinates":[-81.57446899999999,40.03752],"type":"Point"}
}