{
  "type": "Feature",
  "properties": {
    "addr:full": "7369 Hamilton Rd Mendon OH 45862",
    "addr:housenumber": "7369",
    "addr:postcode": "45862",
    "addr:street": "Hamilton Rd",
    "iso:country": "US",
    "sg:address": "7369 Hamilton Rd",
    "sg:city": "Mendon",
    "sg:classifiers": [
      {
        "category": "Building \u0026 Trades",
        "subcategory": "Construction",
        "type": "Services"
      }
    ],
    "sg:phone": "+1 419 795 5481",
    "sg:postcode": "45862",
    "sg:province": "OH",
    "sg:tags": [
      "excavation",
      "general",
      "contractor"
    ],
    "wof:name": "Bennie Young Construction Co",
    "wof:placetype": "venue"
  },
  "geometry": {"coordinates":[-84.518474,40.691661],"type":"Point"}
}
