{
  "type": "Feature",
  "properties": {
    "addr:full":"1215 E 79th St Cleveland OH 44103",
    "addr:housenumber":"1215",
    "addr:postcode":"44103",
    "addr:street":"E 79Th St",
    "iso:country":"US",
    "sg:address":"1215 E 79th St",
    "sg:city":"Cleveland",
    "sg:classifiers":[
        {
            "category":"Professional",
            "subcategory":"Business Services",
            "type":"Services"
        }
    ],
    "sg:phone":"+1 216 441 9599",
    "sg:postcode":"44103",
    "sg:province":"OH",
    "sg:tags":[
        "working",
        "to",
        "strengthen",
        "create",
        "reunite",
        "s"
    ],
    "wof:name":"Family Dream Center Inc",
    "wof:placetype":"venue"
},
  "geometry": {"coordinates":[-81.633515,41.521857],"type":"Point"}
}