{
  "type": "Feature",
  "properties": {
    "addr:full": "1041 Schlater Rd Fort Loramie OH 45845",
    "addr:housenumber": "1041",
    "addr:postcode": "45845",
    "addr:street": "Schlater Rd",
    "iso:country": "US",
    "sg:address": "1041 Schlater Rd",
    "sg:city": "Fort Loramie",
    "sg:classifiers": [
      {
        "category": "Farming",
        "subcategory": "Farm",
        "type": "Manufacturing \u0026 Wholesale Goods"
      }
    ],
    "sg:phone": "+1 937 295 2499",
    "sg:postcode": "45845",
    "sg:province": "OH",
    "sg:tags": [
      "crop",
      "general"
    ],
    "wof:name": "James B Albers",
    "wof:placetype": "venue"
  },
  "geometry": {"coordinates":[-84.413907,40.332882],"type":"Point"}
}
