{
  "type": "Feature",
  "properties": {
    "iso:country":"US",
    "sg:address":"14367 Bennington Dr",
    "sg:city":"Cleveland",
    "sg:classifiers":[
        {
            "category":"Organizations",
            "subcategory":"Religious Organization",
            "type":"Services"
        }
    ],
    "sg:phone":"+1 440 572 1318",
    "sg:postcode":"44136",
    "sg:province":"OH",
    "sg:tags":[
        "clergy"
    ],
    "wof:name":"David P Anderson",
    "wof:placetype":"venue"
},
  "geometry": {"coordinates":[-81.801104,41.28314],"type":"Point"}
}