{
  "type": "Feature",
  "properties": {
    "addr:full":"5134 Gale Rd Granville OH 43023",
    "addr:housenumber":"5134",
    "addr:postcode":"43023",
    "addr:street":"Gale Rd",
    "iso:country":"US",
    "sg:address":"5134 Gale Rd",
    "sg:city":"Granville",
    "sg:phone":"+1 740 587 1734",
    "sg:postcode":"43023",
    "sg:province":"OH",
    "sg:tags":[
        "beef",
        "farm",
        "corn",
        "soybean",
        "cattle",
        "feedlot"
    ],
    "wof:name":"Sunnybank Farm",
    "wof:placetype":"venue"
},
  "geometry": {"coordinates":[-82.576481,40.011341],"type":"Point"}
}