{
  "type": "Feature",
  "properties": {
    "addr:full": "5984 Youngstown Hubbard Rd Hubbard OH 44425",
    "addr:housenumber": "5984",
    "addr:postcode": "44425",
    "addr:street": "Hubbard Rd",
    "iso:country": "US",
    "sg:address": "5984 Youngstown Hubbard Rd",
    "sg:city": "Hubbard",
    "sg:classifiers": [
      {
        "category": "Professional",
        "subcategory": "Business Services",
        "type": "Services"
      },
      {
        "category": "Shopping",
        "subcategory": "Shoes",
        "type": "Retail Goods"
      }
    ],
    "sg:phone": "+1 330 534 8345",
    "sg:postcode": "44425",
    "sg:province": "OH",
    "sg:tags": [
      "made"
    ],
    "wof:name": "Eli S Custom Shoes Co",
    "wof:placetype": "venue"
  },
  "geometry": {"coordinates":[-80.601681,41.148365],"type":"Point"}
}
