{
  "type": "Feature",
  "properties": {
    "addr:full": "10 N Breiel Blvd Middletown OH 45044",
    "addr:housenumber": "10",
    "addr:postcode": "45044",
    "addr:street": "N Breiel Blvd",
    "iso:country": "US",
    "sg:address": "10 N Breiel Blvd",
    "sg:city": "Middletown",
    "sg:classifiers": [
      {
        "category": "Organizations",
        "subcategory": "Religious Organization",
        "type": "Services"
      }
    ],
    "sg:phone": "+1 513 423 8745",
    "sg:postcode": "45044",
    "sg:province": "OH",
    "sg:tags": [
      "lutheran",
      "church"
    ],
    "sg:website": "www.zionluthchurch.org",
    "wof:name": "Zion Evang Lutheran Church",
    "wof:placetype": "venue"
  },
  "geometry": {"coordinates":[-84.354621,39.510636],"type":"Point"}
}
