{
  "type": "Feature",
  "properties": {
    "addr:full": "201 Westview Dr Jefferson OH 44047",
    "addr:housenumber": "201",
    "addr:postcode": "44047",
    "addr:street": "Westview Dr",
    "iso:country": "US",
    "sg:address": "201 Westview Dr",
    "sg:city": "Jefferson",
    "sg:classifiers": [
      {
        "category": "Wholesale",
        "subcategory": "Machinery \u0026 Supplies",
        "type": "Manufacturing \u0026 Wholesale Goods"
      },
      {
        "category": "Building \u0026 Trades",
        "subcategory": "Cleaning \u0026 Sanitation",
        "type": "Services"
      }
    ],
    "sg:phone": "+1 440 576 1441",
    "sg:postcode": "44047",
    "sg:province": "OH",
    "sg:tags": [
      "janitor",
      "establishment",
      "equipment"
    ],
    "wof:name": "D Team Cleaning Inc",
    "wof:placetype": "venue"
  },
  "geometry": {"coordinates":[-80.779038,41.734746],"type":"Point"}
}
