{
  "type": "Feature",
  "properties": {
    "iso:country":"US",
    "sg:address":"432 Fremont Rd",
    "sg:city":"Port Clinton",
    "sg:classifiers":[
        {
            "category":"Professional",
            "type":"Services"
        }
    ],
    "sg:phone":"+1 419 732 8162",
    "sg:postcode":"43452",
    "sg:province":"OH",
    "sg:tags":[
        "establishment"
    ],
    "wof:name":"River Ridge Creations LLC",
    "wof:placetype":"venue"
},
  "geometry": {"coordinates":[-82.947907,41.509382],"type":"Point"}
}