{
  "type": "Feature",
  "properties": {
    "addr:full": "5361 Kennedy Ave Cincinnati OH 45213",
    "addr:housenumber": "5361",
    "addr:postcode": "45213",
    "addr:street": "Kennedy Ave",
    "iso:country": "US",
    "sg:address": "5361 Kennedy Ave",
    "sg:city": "Cincinnati",
    "sg:classifiers": [
      {
        "category": "Autos \u0026 Motor Vehicles",
        "subcategory": "Fuel \u0026 Gas Station",
        "type": "Retail Goods"
      }
    ],
    "sg:phone": "+1 513 351 2025",
    "sg:postcode": "45213",
    "sg:province": "OH",
    "sg:tags": [
      "oil"
    ],
    "wof:name": "Kennedy Avenue Marathon",
    "wof:placetype": "venue"
  },
  "geometry": {"coordinates":[-84.420088,39.169841],"type":"Point"}
}
