{
  "type": "Feature",
  "properties": {
    "iso:country":"US",
    "sg:address":"619 W Fair Ave",
    "sg:city":"Lancaster",
    "sg:classifiers":[
        {
            "category":"Restaurant",
            "type":"Food & Drink"
        }
    ],
    "sg:phone":"+1 740 653 9571",
    "sg:postcode":"43130",
    "sg:province":"OH",
    "wof:name":"Thimmes Fish Shack",
    "wof:placetype":"venue"
},
  "geometry": {"coordinates":[-82.612944,39.724369],"type":"Point"}
}