{
  "type": "Feature",
  "properties": {
    "iso:country":"US",
    "sg:address":"2311 Baton Rouge Ave",
    "sg:city":"Lima",
    "sg:classifiers":[
        {
            "category":"Health Services",
            "subcategory":"Doctor",
            "type":"Services"
        }
    ],
    "sg:phone":"+1 419 331 9307",
    "sg:postcode":"45805",
    "sg:province":"OH",
    "sg:tags":[
        "physician",
        "surgeon"
    ],
    "wof:name":"Lima Pain & Rehab Ctr",
    "wof:placetype":"venue"
},
  "geometry": {"coordinates":[-84.145483,40.771498],"type":"Point"}
}