{
  "type": "Feature",
  "properties": {
    "addr:full":"301 S Main St Monroe OH 45050",
    "addr:housenumber":"301",
    "addr:postcode":"45050",
    "addr:street":"S Main St",
    "iso:country":"US",
    "sg:address":"301 S Main St",
    "sg:city":"Monroe",
    "sg:classifiers":[
        {
            "category":"Government",
            "subcategory":"Post Office",
            "type":"Public Place"
        }
    ],
    "sg:phone":"+1 513 539 9243",
    "sg:postcode":"45050",
    "sg:province":"OH",
    "wof:name":"US Post Office",
    "wof:placetype":"venue"
},
  "geometry": {"coordinates":[-84.364875,39.438002],"type":"Point"}
}