{
  "type": "Feature",
  "properties": {
    "iso:country":"US",
    "sg:address":"215 Woodman Dr",
    "sg:city":"Dayton",
    "sg:classifiers":[
        {
            "category":"Retail",
            "subcategory":"Auto Repair",
            "type":"Services"
        }
    ],
    "sg:phone":"+1 937 252 5310",
    "sg:postcode":"45431",
    "sg:province":"OH",
    "sg:tags":[
        "repairing",
        "automobile"
    ],
    "sg:website":"www.carx.com",
    "wof:name":"Car-X Auto Svc",
    "wof:placetype":"venue"
},
  "geometry": {"coordinates":[-84.12340500000001,39.768138],"type":"Point"}
}