{
  "type": "Feature",
  "properties": {
    "addr:full":"10460 State Rte 45 Salem OH 44460",
    "addr:housenumber":"10460",
    "addr:postcode":"44460",
    "addr:street":"State Rte 45",
    "iso:country":"US",
    "sg:address":"10460 State Rte 45",
    "sg:city":"Salem",
    "sg:classifiers":[
        {
            "category":"Home & Garden",
            "subcategory":"Home Furnishings",
            "type":"Retail Goods"
        }
    ],
    "sg:phone":"+1 330 332 0359",
    "sg:postcode":"44460",
    "sg:province":"OH",
    "sg:tags":[
        "equipment",
        "fireplace"
    ],
    "sg:website":"www.brunks.com",
    "wof:name":"Brunk's RV Sales",
    "wof:placetype":"venue"
},
  "geometry": {"coordinates":[-80.856127,40.960514],"type":"Point"}
}