{
  "type": "Feature",
  "properties": {
    "addr:full":"317 Woodside Ave Jefferson OH 44047",
    "addr:housenumber":"317",
    "addr:postcode":"44047",
    "addr:street":"Woodside Ave",
    "iso:country":"US",
    "sg:address":"317 Woodside Ave",
    "sg:city":"Jefferson",
    "sg:classifiers":[
        {
            "category":"Retail",
            "subcategory":"Animal Services",
            "type":"Services"
        }
    ],
    "sg:phone":"+1 440 576 7387",
    "sg:postcode":"44047",
    "sg:province":"OH",
    "sg:tags":[
        "pet",
        "boarding",
        "sitting"
    ],
    "wof:name":"Castlewood Kennels Inc",
    "wof:placetype":"venue"
},
  "geometry": {"coordinates":[-80.788611,41.733452],"type":"Point"}
}