{
  "type": "Feature",
  "properties": {
    "addr:full": "5001 Enterprise Dr NW Warren OH 44481",
    "addr:housenumber": "5001",
    "addr:postcode": "44481",
    "addr:street": "Enterprise Dr Nw",
    "iso:country": "US",
    "sg:address": "5001 Enterprise Dr NW",
    "sg:city": "Warren",
    "sg:classifiers": [
      {
        "category": "Professional",
        "type": "Services"
      }
    ],
    "sg:phone": "+1 330 898 9087",
    "sg:postcode": "44481",
    "sg:province": "OH",
    "sg:tags": [
      "establishment"
    ],
    "wof:name": "ALC",
    "wof:placetype": "venue"
  },
  "geometry": {"coordinates":[-80.879117,41.258409],"type":"Point"}
}
