{
  "type": "Feature",
  "properties": {
    "iso:country":"US",
    "sg:address":"5001 Enterprise Dr NW",
    "sg:city":"Warren",
    "sg:classifiers":[
        {
            "category":"Professional",
            "type":"Services"
        }
    ],
    "sg:phone":"+1 330 898 9087",
    "sg:postcode":"44481",
    "sg:province":"OH",
    "sg:tags":[
        "establishment"
    ],
    "wof:name":"ALC",
    "wof:placetype":"venue"
},
  "geometry": {"coordinates":[-80.87911699999999,41.258409],"type":"Point"}
}