{
  "type": "Feature",
  "properties": {
    "addr:full": "1635 Columbiana Lisbon Rd Columbiana OH 44408",
    "addr:housenumber": "1635",
    "addr:postcode": "44408",
    "addr:street": "Lisbon Rd",
    "iso:country": "US",
    "sg:address": "1635 Columbiana Lisbon Rd",
    "sg:city": "Columbiana",
    "sg:classifiers": [
      {
        "category": "Food \u0026 Beverages",
        "subcategory": "Groceries \u0026 Convenience Stores",
        "type": "Retail Goods"
      }
    ],
    "sg:phone": "+1 330 482 9583",
    "sg:postcode": "44408",
    "sg:province": "OH",
    "sg:tags": [
      "grocer"
    ],
    "wof:name": "Nemenz Little Village Shopper",
    "wof:placetype": "venue"
  },
  "geometry": {"coordinates":[-80.71429,40.876416],"type":"Point"}
}
