{
  "type": "Feature",
  "properties": {
    "iso:country":"US",
    "sg:address":"1635 Columbiana Lisbon Rd",
    "sg:city":"Columbiana",
    "sg:classifiers":[
        {
            "category":"Food & Beverages",
            "subcategory":"Groceries & Convenience Stores",
            "type":"Retail Goods"
        }
    ],
    "sg:phone":"+1 330 482 9583",
    "sg:postcode":"44408",
    "sg:province":"OH",
    "sg:tags":[
        "grocer"
    ],
    "wof:name":"Nemenz Little Village Shopper",
    "wof:placetype":"venue"
},
  "geometry": {"coordinates":[-80.71429000000001,40.876416],"type":"Point"}
}