{
  "type": "Feature",
  "properties": {
    "iso:country":"US",
    "sg:address":"3333 Harding Hwy E",
    "sg:city":"Marion",
    "sg:classifiers":[
        {
            "category":"Autos & Motor Vehicles",
            "subcategory":"Auto Supplies",
            "type":"Retail Goods"
        }
    ],
    "sg:phone":"+1 740 382 3989",
    "sg:postcode":"43302",
    "sg:province":"OH",
    "sg:tags":[
        "parts"
    ],
    "wof:name":"Advance Auto Parts",
    "wof:placetype":"venue"
},
  "geometry": {"coordinates":[-83.0369,40.612789],"type":"Point"}
}