{
  "type": "Feature",
  "properties": {
    "addr:full":"6711 Karen Dr Cleveland OH 44131",
    "addr:housenumber":"6711",
    "addr:postcode":"44131",
    "addr:street":"Karen Dr",
    "iso:country":"US",
    "sg:address":"6711 Karen Dr",
    "sg:city":"Cleveland",
    "sg:classifiers":[
        {
            "category":"Professional",
            "subcategory":"Management & Consulting",
            "type":"Services"
        }
    ],
    "sg:phone":"+1 216 901 1351",
    "sg:postcode":"44131",
    "sg:province":"OH",
    "sg:tags":[
        "public",
        "relations"
    ],
    "wof:name":"Rat Pac Marketing Inc",
    "wof:placetype":"venue"
},
  "geometry": {"coordinates":[-81.664529,41.383123],"type":"Point"}
}