{
  "type": "Feature",
  "properties": {
    "addr:full": "26250 Euclid Ave Cleveland OH 44132",
    "addr:housenumber": "26250",
    "addr:postcode": "44132",
    "addr:street": "Euclid Ave",
    "iso:country": "US",
    "sg:address": "26250 Euclid Ave",
    "sg:city": "Cleveland",
    "sg:classifiers": [
      {
        "category": "Health Services",
        "subcategory": "Doctor",
        "type": "Services"
      }
    ],
    "sg:phone": "+1 216 289 8149",
    "sg:postcode": "44132",
    "sg:province": "OH",
    "sg:tags": [
      "physician",
      "surgeon",
      "medical"
    ],
    "wof:name": "David J Fishman MD Inc",
    "wof:placetype": "venue"
  },
  "geometry": {"coordinates":[-81.495954,41.591388],"type":"Point"}
}
