{
  "type": "Feature",
  "properties": {
    "iso:country":"US",
    "sg:address":"10178 International Blvd",
    "sg:city":"Cincinnati",
    "sg:classifiers":[
        {
            "category":"Professional",
            "subcategory":"Engineering",
            "type":"Services"
        }
    ],
    "sg:phone":"+1 513 874 9494",
    "sg:postcode":"45246",
    "sg:province":"OH",
    "wof:name":"Alt & Witzig Engineering Inc",
    "wof:placetype":"venue"
},
  "geometry": {"coordinates":[-84.44336699999999,39.301721],"type":"Point"}
}