{
  "type": "Feature",
  "properties": {
    "addr:full": "10178 International Blvd Cincinnati OH 45246",
    "addr:housenumber": "10178",
    "addr:postcode": "45246",
    "addr:street": "International Blvd",
    "iso:country": "US",
    "sg:address": "10178 International Blvd",
    "sg:city": "Cincinnati",
    "sg:classifiers": [
      {
        "category": "Professional",
        "subcategory": "Engineering",
        "type": "Services"
      }
    ],
    "sg:phone": "+1 513 874 9494",
    "sg:postcode": "45246",
    "sg:province": "OH",
    "wof:name": "Alt \u0026 Witzig Engineering Inc",
    "wof:placetype": "venue"
  },
  "geometry": {"coordinates":[-84.443367,39.301721],"type":"Point"}
}
