{
  "type": "Feature",
  "properties": {
    "addr:full":"544 E Pershing St Salem OH 44460",
    "addr:housenumber":"544",
    "addr:postcode":"44460",
    "addr:street":"E Pershing St",
    "iso:country":"US",
    "sg:address":"544 E Pershing St",
    "sg:city":"Salem",
    "sg:classifiers":[
        {
            "category":"Restaurant",
            "type":"Food & Drink"
        }
    ],
    "sg:phone":"+1 330 337 8135",
    "sg:postcode":"44460",
    "sg:province":"OH",
    "sg:tags":[
        "eating"
    ],
    "wof:name":"Wallaby's Grille",
    "wof:placetype":"venue"
},
  "geometry": {"coordinates":[-80.853431,40.899858],"type":"Point"}
}