{
  "type": "Feature",
  "properties": {
    "addr:full": "8215 Vine St Cincinnati OH 45216",
    "addr:housenumber": "8215",
    "addr:postcode": "45216",
    "addr:street": "Vine St",
    "iso:country": "US",
    "sg:address": "8215 Vine St",
    "sg:city": "Cincinnati",
    "sg:classifiers": [
      {
        "category": "Retail",
        "subcategory": "Auto Repair",
        "type": "Services"
      }
    ],
    "sg:phone": "+1 513 821 2320",
    "sg:postcode": "45216",
    "sg:province": "OH",
    "sg:tags": [
      "repairing",
      "automobile"
    ],
    "wof:name": "Frank's Frame \u0026 Axle Svc",
    "wof:placetype": "venue"
  },
  "geometry": {"coordinates":[-84.474468,39.20979],"type":"Point"}
}
