{
  "type": "Feature",
  "properties": {
    "addr:full": "6906 Gillen Ln Miamisburg OH 45342",
    "addr:housenumber": "6906",
    "addr:postcode": "45342",
    "addr:street": "Gillen Ln",
    "iso:country": "US",
    "sg:address": "6906 Gillen Ln",
    "sg:city": "Miamisburg",
    "sg:classifiers": [
      {
        "category": "Building \u0026 Trades",
        "subcategory": "Landscaping Services",
        "type": "Services"
      }
    ],
    "sg:phone": "+1 937 866 6317",
    "sg:postcode": "45342",
    "sg:province": "OH",
    "sg:tags": [
      "lawn"
    ],
    "wof:name": "Scotts Lawn Service",
    "wof:placetype": "venue"
  },
  "geometry": {"coordinates":[-84.315353,39.64856],"type":"Point"}
}
