{
  "type": "Feature",
  "properties": {
    "iso:country":"US",
    "sg:address":"29001 Cedar Rd",
    "sg:city":"Cleveland",
    "sg:classifiers":[
        {
            "category":"Health Services",
            "subcategory":"Doctor",
            "type":"Services"
        }
    ],
    "sg:phone":"+1 440 461 8200",
    "sg:postcode":"44124",
    "sg:province":"OH",
    "sg:tags":[
        "surgeon",
        "oral"
    ],
    "wof:name":"Tetelman Evan D DDS",
    "wof:placetype":"venue"
},
  "geometry": {"coordinates":[-81.474701,41.501202],"type":"Point"}
}