{
  "type": "Feature",
  "properties": {
    "iso:country":"US",
    "sg:address":"118 E Main St",
    "sg:city":"Mason",
    "sg:classifiers":[
        {
            "category":"Real Estate",
            "subcategory":"Real Estate Agent",
            "type":"Services"
        }
    ],
    "sg:phone":"+1 513 398 2888",
    "sg:postcode":"45040",
    "sg:province":"OH",
    "wof:name":"Malhotra Real Estate",
    "wof:placetype":"venue"
},
  "geometry": {"coordinates":[-84.308624,39.360475],"type":"Point"}
}