{
  "type": "Feature",
  "properties": {
    "iso:country":"US",
    "sg:address":"20 E Vorhees St",
    "sg:city":"Cincinnati",
    "sg:classifiers":[
        {
            "category":"Real Estate",
            "subcategory":"Real Estate Agent",
            "type":"Services"
        }
    ],
    "sg:phone":"+1 513 351 3355",
    "sg:postcode":"45215",
    "sg:province":"OH",
    "sg:tags":[
        "inspection"
    ],
    "wof:name":"Robert Becker Engineering Grp",
    "wof:placetype":"venue"
},
  "geometry": {"coordinates":[-84.44143800000001,39.220551],"type":"Point"}
}