{
  "type": "Feature",
  "properties": {
    "addr:full": "5920 Fettro Rd Hillsboro OH 45133",
    "addr:housenumber": "5920",
    "addr:postcode": "45133",
    "addr:street": "Fettro Rd",
    "iso:country": "US",
    "sg:address": "5920 Fettro Rd",
    "sg:city": "Hillsboro",
    "sg:classifiers": [
      {
        "category": "Farming",
        "subcategory": "Farm",
        "type": "Manufacturing \u0026 Wholesale Goods"
      }
    ],
    "sg:phone": "+1 937 393 2603",
    "sg:postcode": "45133",
    "sg:province": "OH",
    "sg:tags": [
      "crop",
      "general"
    ],
    "wof:name": "Fettro Farms",
    "wof:placetype": "venue"
  },
  "geometry": {"coordinates":[-83.557949,39.170196],"type":"Point"}
}
