{
  "type": "Feature",
  "properties": {
    "iso:country":"US",
    "sg:address":"5920 Fettro Rd",
    "sg:city":"Hillsboro",
    "sg:classifiers":[
        {
            "category":"Farming",
            "subcategory":"Farm",
            "type":"Manufacturing & Wholesale Goods"
        }
    ],
    "sg:phone":"+1 937 393 2603",
    "sg:postcode":"45133",
    "sg:province":"OH",
    "sg:tags":[
        "crop",
        "general"
    ],
    "wof:name":"Fettro Farms",
    "wof:placetype":"venue"
},
  "geometry": {"coordinates":[-83.55794899999999,39.170196],"type":"Point"}
}