{
  "type": "Feature",
  "properties": {
    "iso:country":"US",
    "sg:address":"292 Glenworth Ct",
    "sg:city":"Powell",
    "sg:classifiers":[
        {
            "category":"Professional",
            "type":"Services"
        }
    ],
    "sg:phone":"+1 614 760 5843",
    "sg:postcode":"43065",
    "sg:province":"OH",
    "sg:tags":[
        "establishment"
    ],
    "wof:name":"Andrew J Beal Co",
    "wof:placetype":"venue"
},
  "geometry": {"coordinates":[-83.068136,40.15421],"type":"Point"}
}