{
  "type": "Feature",
  "properties": {
    "addr:full": "3315 N Ridge Rd W Ashtabula OH 44004",
    "addr:housenumber": "3315",
    "addr:postcode": "44004",
    "addr:street": "N Ridge Rd W",
    "iso:country": "US",
    "sg:address": "3315 N Ridge Rd W",
    "sg:city": "Ashtabula",
    "sg:classifiers": [
      {
        "category": "Home \u0026 Garden",
        "subcategory": "Home Furnishings",
        "type": "Retail Goods"
      }
    ],
    "sg:phone": "+1 440 998 0991",
    "sg:postcode": "44004",
    "sg:province": "OH",
    "sg:tags": [
      "housewares",
      "specialty"
    ],
    "wof:name": "Kitchen Collection 125",
    "wof:placetype": "venue"
  },
  "geometry": {"coordinates":[-80.82767,41.848698],"type":"Point"}
}
