{
  "type": "Feature",
  "properties": {
    "addr:full":"6070 Richmond Rd Bedford OH 44146",
    "addr:housenumber":"6070",
    "addr:postcode":"44146",
    "addr:street":"Richmond Rd",
    "iso:country":"US",
    "sg:address":"6070 Richmond Rd",
    "sg:city":"Bedford",
    "sg:classifiers":[
        {
            "category":"Professional",
            "type":"Services"
        }
    ],
    "sg:phone":"+1 440 232 8516",
    "sg:postcode":"44146",
    "sg:province":"OH",
    "wof:name":"Godstow Sanctuary & Herb Garde",
    "wof:placetype":"venue"
},
  "geometry": {"coordinates":[-81.48894799999999,41.39971],"type":"Point"}
}