{
  "type": "Feature",
  "properties": {
    "addr:full":"36445 Biltmore Pl Willoughby OH 44094",
    "addr:housenumber":"36445",
    "addr:postcode":"44094",
    "addr:street":"Biltmore Pl",
    "iso:country":"US",
    "sg:address":"36445 Biltmore Pl",
    "sg:city":"Willoughby",
    "sg:classifiers":[
        {
            "category":"Banks & Credit Unions",
            "subcategory":"Bank",
            "type":"Services"
        }
    ],
    "sg:phone":"+1 440 951 1122",
    "sg:postcode":"44094",
    "sg:province":"OH",
    "sg:tags":[
        "loan",
        "real estate"
    ],
    "wof:name":"First Liberty",
    "wof:placetype":"venue"
},
  "geometry": {"coordinates":[-81.425299,41.632649],"type":"Point"}
}