{
  "type": "Feature",
  "properties": {
    "addr:full":"10790 Zion Church Rd Spencerville OH 45887",
    "addr:housenumber":"10790",
    "addr:postcode":"45887",
    "addr:street":"Zion Church Rd",
    "iso:country":"US",
    "sg:address":"10790 Zion Church Rd",
    "sg:city":"Spencerville",
    "sg:classifiers":[
        {
            "category":"Farming",
            "subcategory":"Livestock Farm",
            "type":"Manufacturing & Wholesale Goods"
        }
    ],
    "sg:phone":"+1 419 339 1312",
    "sg:postcode":"45887",
    "sg:province":"OH",
    "sg:tags":[
        "animal",
        "general"
    ],
    "wof:name":"Kevin Bockey",
    "wof:placetype":"venue"
},
  "geometry": {"coordinates":[-84.305611,40.765116],"type":"Point"}
}