{
  "type": "Feature",
  "properties": {
    "iso:country":"US",
    "sg:address":"4197 Dawn Cliff Dr",
    "sg:city":"Cleveland",
    "sg:classifiers":[
        {
            "category":"Retail",
            "subcategory":"Repair Shop",
            "type":"Services"
        }
    ],
    "sg:phone":"+1 216 398 8144",
    "sg:postcode":"44144",
    "sg:province":"OH",
    "sg:tags":[
        "upholsterer"
    ],
    "wof:name":"A & B Upholstery",
    "wof:placetype":"venue"
},
  "geometry": {"coordinates":[-81.748124,41.444885],"type":"Point"}
}