{
  "type": "Feature",
  "properties": {
    "iso:country":"US",
    "sg:address":"3936 N Dixie Dr",
    "sg:city":"Dayton",
    "sg:classifiers":[
        {
            "category":"Personal",
            "subcategory":"Barber",
            "type":"Services"
        }
    ],
    "sg:phone":"+1 937 278 6612",
    "sg:postcode":"45414",
    "sg:province":"OH",
    "wof:name":"Dixie Barbers",
    "wof:placetype":"venue"
},
  "geometry": {"coordinates":[-84.194902,39.802751],"type":"Point"}
}