{
  "type": "Feature",
  "properties": {
    "iso:country":"US",
    "sg:address":"4765 Briar Rd",
    "sg:city":"Cleveland",
    "sg:classifiers":[
        {
            "category":"Wholesale",
            "subcategory":"Auto Parts",
            "type":"Manufacturing & Wholesale Goods"
        }
    ],
    "sg:phone":"+1 216 362 1422",
    "sg:postcode":"44135",
    "sg:province":"OH",
    "sg:tags":[
        "foot",
        "automobile",
        "control",
        "hand"
    ],
    "wof:name":"Truckin Vantastiks",
    "wof:placetype":"venue"
},
  "geometry": {"coordinates":[-81.791557,41.423799],"type":"Point"}
}