{
  "type": "Feature",
  "properties": {
    "addr:full":"9990 International Blvd Cincinnati OH 45246",
    "addr:housenumber":"9990",
    "addr:postcode":"45246",
    "addr:street":"International Blvd",
    "iso:country":"US",
    "sg:address":"9990 International Blvd",
    "sg:city":"Cincinnati",
    "sg:classifiers":[
        {
            "category":"Wholesale",
            "subcategory":"Medical Equipment & Supplies",
            "type":"Manufacturing & Wholesale Goods"
        }
    ],
    "sg:phone":"+1 513 874 2990",
    "sg:postcode":"45246",
    "sg:province":"OH",
    "wof:name":"Benco Dental Supply",
    "wof:placetype":"venue"
},
  "geometry": {"coordinates":[-84.44265,39.305488],"type":"Point"}
}