{
  "type": "Feature",
  "properties": {
    "addr:full":"6770 Mayfield Rd Cleveland OH 44124",
    "addr:housenumber":"6770",
    "addr:postcode":"44124",
    "addr:street":"Mayfield Rd",
    "iso:country":"US",
    "sg:address":"6770 Mayfield Rd",
    "sg:city":"Cleveland",
    "sg:classifiers":[
        {
            "category":"Personal",
            "type":"Services"
        }
    ],
    "sg:phone":"+1 440 338 6009",
    "sg:postcode":"44124",
    "sg:province":"OH",
    "sg:tags":[
        "control",
        "weight"
    ],
    "wof:name":"Weight Management Partners Inc",
    "wof:placetype":"venue"
},
  "geometry": {"coordinates":[-81.434549,41.52003],"type":"Point"}
}