{
  "type": "Feature",
  "properties": {
    "addr:full": "8208 S Kohler Rd Apple Creek OH 44606",
    "addr:housenumber": "8208",
    "addr:postcode": "44606",
    "addr:street": "S Kohler Rd",
    "iso:country": "US",
    "sg:address": "8208 S Kohler Rd",
    "sg:city": "Apple Creek",
    "sg:classifiers": [
      {
        "category": "Manufacturing",
        "subcategory": "Wood Products",
        "type": "Manufacturing \u0026 Wholesale Goods"
      }
    ],
    "sg:phone": "+1 330 857 3075",
    "sg:postcode": "44606",
    "sg:province": "OH",
    "sg:tags": [
      "mfg"
    ],
    "wof:name": "Litco Wood Products",
    "wof:placetype": "venue"
  },
  "geometry": {"coordinates":[-81.755591,40.699114],"type":"Point"}
}
