{
  "type": "Feature",
  "properties": {
    "iso:country":"US",
    "sg:address":"8208 S Kohler Rd",
    "sg:city":"Apple Creek",
    "sg:classifiers":[
        {
            "category":"Manufacturing",
            "subcategory":"Wood Products",
            "type":"Manufacturing & Wholesale Goods"
        }
    ],
    "sg:phone":"+1 330 857 3075",
    "sg:postcode":"44606",
    "sg:province":"OH",
    "sg:tags":[
        "mfg"
    ],
    "wof:name":"Litco Wood Products",
    "wof:placetype":"venue"
},
  "geometry": {"coordinates":[-81.755591,40.699114],"type":"Point"}
}