{
  "type": "Feature",
  "properties": {
    "addr:full": "5080 Sunbury Rd Westerville OH 43082",
    "addr:housenumber": "5080",
    "addr:postcode": "43082",
    "addr:street": "Sunbury Rd",
    "iso:country": "US",
    "sg:address": "5080 Sunbury Rd",
    "sg:city": "Westerville",
    "sg:classifiers": [
      {
        "category": "Professional",
        "subcategory": "Management \u0026 Consulting",
        "type": "Services"
      }
    ],
    "sg:phone": "+1 614 891 4090",
    "sg:postcode": "43082",
    "sg:province": "OH",
    "sg:tags": [
      "business"
    ],
    "wof:name": "Pringle Asscctes Cnslting Fing",
    "wof:placetype": "venue"
  },
  "geometry": {"coordinates":[-82.879657,40.171755],"type":"Point"}
}
