{
  "type": "Feature",
  "properties": {
    "iso:country":"US",
    "sg:address":"5080 Sunbury Rd",
    "sg:city":"Westerville",
    "sg:classifiers":[
        {
            "category":"Professional",
            "subcategory":"Management & Consulting",
            "type":"Services"
        }
    ],
    "sg:phone":"+1 614 891 4090",
    "sg:postcode":"43082",
    "sg:province":"OH",
    "sg:tags":[
        "business"
    ],
    "wof:name":"Pringle Asscctes Cnslting Fing",
    "wof:placetype":"venue"
},
  "geometry": {"coordinates":[-82.879657,40.171755],"type":"Point"}
}