{
  "type": "Feature",
  "properties": {
    "addr:full":"13535 Detroit Ave Cleveland OH 44107",
    "addr:housenumber":"13535",
    "addr:postcode":"44107",
    "addr:street":"Detroit Ave",
    "iso:country":"US",
    "sg:address":"13535 Detroit Ave",
    "sg:city":"Cleveland",
    "sg:classifiers":[
        {
            "category":"Health Services",
            "subcategory":"Doctor",
            "type":"Services"
        }
    ],
    "sg:phone":"+1 216 221 7070",
    "sg:postcode":"44107",
    "sg:province":"OH",
    "sg:tags":[
        "physician",
        "surgeon"
    ],
    "wof:name":"Mary A Kraft MD",
    "wof:placetype":"venue"
},
  "geometry": {"coordinates":[-81.785127,41.485002],"type":"Point"}
}