{
  "type": "Feature",
  "properties": {
    "addr:full": "54 Westchester Dr Youngstown OH 44515",
    "addr:housenumber": "54",
    "addr:postcode": "44515",
    "addr:street": "Westchester Dr",
    "iso:country": "US",
    "sg:address": "54 Westchester Dr",
    "sg:city": "Youngstown",
    "sg:classifiers": [
      {
        "category": "Insurance",
        "subcategory": "Insurance Agent",
        "type": "Services"
      }
    ],
    "sg:phone": "+1 330 270 0080",
    "sg:postcode": "44515",
    "sg:province": "OH",
    "wof:name": "Kimberly A Vargo",
    "wof:placetype": "venue"
  },
  "geometry": {"coordinates":[-80.748633,41.098077],"type":"Point"}
}
