{
  "type": "Feature",
  "properties": {
    "addr:full": "3905 Neff Rd Grove City OH 43123",
    "addr:housenumber": "3905",
    "addr:postcode": "43123",
    "addr:street": "Neff Rd",
    "iso:country": "US",
    "sg:address": "3905 Neff Rd",
    "sg:city": "Grove City",
    "sg:classifiers": [
      {
        "category": "Wholesale",
        "subcategory": "Plants",
        "type": "Manufacturing \u0026 Wholesale Goods"
      }
    ],
    "sg:phone": "+1 614 871 4444",
    "sg:postcode": "43123",
    "sg:province": "OH",
    "sg:tags": [
      "supply"
    ],
    "wof:name": "Holiday Acres",
    "wof:placetype": "venue"
  },
  "geometry": {"coordinates":[-83.146003,39.860552],"type":"Point"}
}
