{
  "type": "Feature",
  "properties": {
    "addr:full":"184 Springbrook Dr Columbus OH 43230",
    "addr:housenumber":"184",
    "addr:postcode":"43230",
    "addr:street":"Springbrook Dr",
    "iso:country":"US",
    "sg:address":"184 Springbrook Dr",
    "sg:city":"Columbus",
    "sg:classifiers":[
        {
            "category":"Building & Trades",
            "subcategory":"Landscaping Services",
            "type":"Services"
        }
    ],
    "sg:phone":"+1 614 418 5046",
    "sg:postcode":"43230",
    "sg:province":"OH",
    "sg:tags":[
        "gardener"
    ],
    "wof:name":"P T Buckley Co",
    "wof:placetype":"venue"
},
  "geometry": {"coordinates":[-82.87447400000001,40.032391],"type":"Point"}
}