{
  "type": "Feature",
  "properties": {
    "addr:full": "227 Tanglewood Dr Dalton OH 44618",
    "addr:housenumber": "227",
    "addr:postcode": "44618",
    "addr:street": "Tanglewood Dr",
    "iso:country": "US",
    "sg:address": "227 Tanglewood Dr",
    "sg:city": "Dalton",
    "sg:classifiers": [
      {
        "category": "Building \u0026 Trades",
        "subcategory": "Construction",
        "type": "Services"
      }
    ],
    "sg:phone": "+1 330 828 0726",
    "sg:postcode": "44618",
    "sg:province": "OH",
    "sg:tags": [
      "house"
    ],
    "wof:name": "Heritage Homes Inc",
    "wof:placetype": "venue"
  },
  "geometry": {"coordinates":[-81.706908,40.80291],"type":"Point"}
}
