{
  "type": "Feature",
  "properties": {
    "iso:country":"US",
    "sg:address":"20475 Bunker Hill Dr",
    "sg:city":"Cleveland",
    "sg:classifiers":[
        {
            "category":"Professional",
            "subcategory":"Art Services",
            "type":"Services"
        }
    ],
    "sg:phone":"+1 440 333 9988",
    "sg:postcode":"44126",
    "sg:province":"OH",
    "sg:tags":[
        "commercial",
        "design"
    ],
    "wof:name":"Graphics International",
    "wof:placetype":"venue"
},
  "geometry": {"coordinates":[-81.84619499999999,41.445439],"type":"Point"}
}