{
  "type": "Feature",
  "properties": {
    "addr:full": "20475 Bunker Hill Dr Cleveland OH 44126",
    "addr:housenumber": "20475",
    "addr:postcode": "44126",
    "addr:street": "Bunker Hill Dr",
    "iso:country": "US",
    "sg:address": "20475 Bunker Hill Dr",
    "sg:city": "Cleveland",
    "sg:classifiers": [
      {
        "category": "Professional",
        "subcategory": "Art Services",
        "type": "Services"
      }
    ],
    "sg:phone": "+1 440 333 9988",
    "sg:postcode": "44126",
    "sg:province": "OH",
    "sg:tags": [
      "commercial",
      "design"
    ],
    "wof:name": "Graphics International",
    "wof:placetype": "venue"
  },
  "geometry": {"coordinates":[-81.846195,41.445439],"type":"Point"}
}
