{
  "type": "Feature",
  "properties": {
    "addr:full": "4485 Refugee Rd Columbus OH 43232",
    "addr:housenumber": "4485",
    "addr:postcode": "43232",
    "addr:street": "Refugee Rd",
    "iso:country": "US",
    "sg:address": "4485 Refugee Rd",
    "sg:city": "Columbus",
    "sg:classifiers": [
      {
        "category": "Food \u0026 Beverages",
        "subcategory": "Groceries \u0026 Convenience Stores",
        "type": "Retail Goods"
      }
    ],
    "sg:phone": "+1 614 861 4578",
    "sg:postcode": "43232",
    "sg:province": "OH",
    "sg:tags": [
      "grocer"
    ],
    "wof:name": "Kroger",
    "wof:placetype": "venue"
  },
  "geometry": {"coordinates":[-82.877127,39.915422],"type":"Point"}
}
