{
  "type": "Feature",
  "properties": {
    "iso:country":"US",
    "sg:address":"3380 E Main St",
    "sg:city":"Columbus",
    "sg:classifiers":[
        {
            "category":"Retail",
            "subcategory":"Auto Repair",
            "type":"Services"
        }
    ],
    "sg:phone":"+1 614 231 5292",
    "sg:postcode":"43213",
    "sg:province":"OH",
    "sg:tags":[
        "body",
        "automobile",
        "painting"
    ],
    "sg:website":"www.xpertautocenter.com",
    "wof:name":"A-1 Xpert Auto Ctr",
    "wof:placetype":"venue"
},
  "geometry": {"coordinates":[-82.90748,39.956434],"type":"Point"}
}