{
  "type": "Feature",
  "properties": {
    "addr:full": "341 State Rte 250 Jeromesville OH 44840",
    "addr:housenumber": "341",
    "addr:postcode": "44840",
    "addr:street": "State Rte 250",
    "iso:country": "US",
    "sg:address": "341 State Rte 250",
    "sg:city": "Jeromesville",
    "sg:classifiers": [
      {
        "category": "Wholesale",
        "subcategory": "Durable Goods \u0026 Equipment",
        "type": "Manufacturing \u0026 Wholesale Goods"
      }
    ],
    "sg:phone": "+1 419 869 7908",
    "sg:postcode": "44840",
    "sg:province": "OH",
    "sg:tags": [
      "representative",
      "manufacturer"
    ],
    "wof:name": "Harpster \u0026 Co",
    "wof:placetype": "venue"
  },
  "geometry": {"coordinates":[-82.193399,40.856502],"type":"Point"}
}
