{
  "type": "Feature",
  "properties": {
    "iso:country":"US",
    "sg:address":"341 State Rte 250",
    "sg:city":"Jeromesville",
    "sg:classifiers":[
        {
            "category":"Wholesale",
            "subcategory":"Durable Goods & Equipment",
            "type":"Manufacturing & Wholesale Goods"
        }
    ],
    "sg:phone":"+1 419 869 7908",
    "sg:postcode":"44840",
    "sg:province":"OH",
    "sg:tags":[
        "representative",
        "manufacturer"
    ],
    "wof:name":"Harpster & Co",
    "wof:placetype":"venue"
},
  "geometry": {"coordinates":[-82.193399,40.856502],"type":"Point"}
}