{
  "type": "Feature",
  "properties": {
    "addr:full": "7100 Blue Ash Rd Cincinnati OH 45236",
    "addr:housenumber": "7100",
    "addr:postcode": "45236",
    "addr:street": "Blue Ash Rd",
    "iso:country": "US",
    "sg:address": "7100 Blue Ash Rd",
    "sg:city": "Cincinnati",
    "sg:classifiers": [
      {
        "category": "Professional",
        "type": "Services"
      }
    ],
    "sg:phone": "+1 513 791 5533",
    "sg:postcode": "45236",
    "sg:province": "OH",
    "wof:name": "Safety Matters",
    "wof:placetype": "venue"
  },
  "geometry": {"coordinates":[-84.399186,39.19829],"type":"Point"}
}
