{
  "type": "Feature",
  "properties": {
    "iso:country":"US",
    "sg:address":"59 Hitchcock Ln",
    "sg:city":"Amelia",
    "sg:classifiers":[
        {
            "category":"Building & Trades",
            "subcategory":"Pest Control",
            "type":"Services"
        }
    ],
    "sg:phone":"+1 513 753 5945",
    "sg:postcode":"45102",
    "sg:province":"OH",
    "wof:name":"First Choice Pest Control",
    "wof:placetype":"venue"
},
  "geometry": {"coordinates":[-84.219759,39.034087],"type":"Point"}
}