{
  "type": "Feature",
  "properties": {
    "iso:country":"US",
    "sg:address":"1201 Industrial Dr",
    "sg:city":"Fort Recovery",
    "sg:classifiers":[
        {
            "category":"Wholesale",
            "subcategory":"Machinery & Supplies",
            "type":"Manufacturing & Wholesale Goods"
        }
    ],
    "sg:phone":"+1 419 375 4104",
    "sg:postcode":"45846",
    "sg:province":"OH",
    "sg:tags":[
        "poultry",
        "equipment"
    ],
    "sg:website":"www.fortrecoveryequipment.com",
    "wof:name":"Ft Recovery Equipment Co",
    "wof:placetype":"venue"
},
  "geometry": {"coordinates":[-84.773606,40.40096],"type":"Point"}
}