{
  "type": "Feature",
  "properties": {
    "addr:full": "1201 Industrial Dr Fort Recovery OH 45846",
    "addr:housenumber": "1201",
    "addr:postcode": "45846",
    "addr:street": "Industrial Dr",
    "iso:country": "US",
    "sg:address": "1201 Industrial Dr",
    "sg:city": "Fort Recovery",
    "sg:classifiers": [
      {
        "category": "Wholesale",
        "subcategory": "Machinery \u0026 Supplies",
        "type": "Manufacturing \u0026 Wholesale Goods"
      }
    ],
    "sg:phone": "+1 419 375 4104",
    "sg:postcode": "45846",
    "sg:province": "OH",
    "sg:tags": [
      "poultry",
      "equipment"
    ],
    "sg:website": "www.fortrecoveryequipment.com",
    "wof:name": "Ft Recovery Equipment Co",
    "wof:placetype": "venue"
  },
  "geometry": {"coordinates":[-84.773606,40.40096],"type":"Point"}
}
