{
  "type": "Feature",
  "properties": {
    "addr:full": "621 Hebron Rd Newark OH 43056",
    "addr:housenumber": "621",
    "addr:postcode": "43056",
    "addr:street": "Hebron Rd",
    "iso:country": "US",
    "sg:address": "621 Hebron Rd",
    "sg:city": "Newark",
    "sg:classifiers": [
      {
        "category": "Professional",
        "subcategory": "Accounting \u0026 Tax Preparation",
        "type": "Services"
      }
    ],
    "sg:phone": "+1 740 522 5196",
    "sg:postcode": "43056",
    "sg:province": "OH",
    "sg:tags": [
      "return"
    ],
    "wof:name": "H \u0026 R Block",
    "wof:placetype": "venue"
  },
  "geometry": {"coordinates":[-82.432945,40.035077],"type":"Point"}
}
