{
  "type": "Feature",
  "properties": {
    "addr:full": "375 Northpointe Dr Fairfield OH 45014",
    "addr:housenumber": "375",
    "addr:postcode": "45014",
    "addr:street": "Northpointe Dr",
    "iso:country": "US",
    "sg:address": "375 Northpointe Dr",
    "sg:city": "Fairfield",
    "sg:classifiers": [
      {
        "category": "Shopping",
        "subcategory": "Clothing, Apparel, \u0026 Fashions",
        "type": "Retail Goods"
      }
    ],
    "sg:phone": "+1 513 874 1729",
    "sg:postcode": "45014",
    "sg:province": "OH",
    "sg:tags": [
      "sportswear"
    ],
    "wof:name": "Stardust Corp",
    "wof:placetype": "venue"
  },
  "geometry": {"coordinates":[-84.483338,39.320613],"type":"Point"}
}
