{
  "type": "Feature",
  "properties": {
    "iso:country":"US",
    "sg:address":"375 Northpointe Dr",
    "sg:city":"Fairfield",
    "sg:classifiers":[
        {
            "category":"Shopping",
            "subcategory":"Clothing, Apparel, & Fashions",
            "type":"Retail Goods"
        }
    ],
    "sg:phone":"+1 513 874 1729",
    "sg:postcode":"45014",
    "sg:province":"OH",
    "sg:tags":[
        "sportswear"
    ],
    "wof:name":"Stardust Corp",
    "wof:placetype":"venue"
},
  "geometry": {"coordinates":[-84.483338,39.320613],"type":"Point"}
}