{
  "type": "Feature",
  "properties": {
    "addr:full":"122 S Main St Marysville OH 43040",
    "addr:housenumber":"122",
    "addr:postcode":"43040",
    "addr:street":"S Main St",
    "iso:country":"US",
    "sg:address":"122 S Main St",
    "sg:city":"Marysville",
    "sg:classifiers":[
        {
            "category":"Personal",
            "subcategory":"Beauty Salon",
            "type":"Services"
        }
    ],
    "sg:phone":"+1 937 644 0804",
    "sg:postcode":"43040",
    "sg:province":"OH",
    "wof:name":"Off The Five Gallory & Salon",
    "wof:placetype":"venue"
},
  "geometry": {"coordinates":[-83.366871,40.236161],"type":"Point"}
}