{
  "type": "Feature",
  "properties": {
    "addr:full": "134 E 4th St Minster OH 45865",
    "addr:housenumber": "134",
    "addr:postcode": "45865",
    "addr:street": "E 4Th St",
    "iso:country": "US",
    "sg:address": "134 E 4th St",
    "sg:city": "Minster",
    "sg:classifiers": [
      {
        "category": "Wholesale",
        "subcategory": "Auto Parts",
        "type": "Manufacturing \u0026 Wholesale Goods"
      }
    ],
    "sg:phone": "+1 419 628 3376",
    "sg:postcode": "45865",
    "sg:province": "OH",
    "wof:name": "Carquest Of Minster",
    "wof:placetype": "venue"
  },
  "geometry": {"coordinates":[-84.377076,40.393079],"type":"Point"}
}
