{
  "type": "Feature",
  "properties": {
    "addr:full": "18945 Co Rd 155 Ridgeway OH 43345",
    "addr:housenumber": "18945;155",
    "addr:postcode": "43345",
    "addr:street": "Co Rd",
    "iso:country": "US",
    "sg:address": "18945 Co Rd 155",
    "sg:city": "Ridgeway",
    "sg:phone": "+1 419 675 2234",
    "sg:postcode": "43345",
    "sg:province": "OH",
    "sg:tags": [
      "farm",
      "wheat"
    ],
    "wof:name": "Rex G Sullinger",
    "wof:placetype": "venue"
  },
  "geometry": {"coordinates":[-83.634419,40.54528],"type":"Point"}
}
