{
  "type": "Feature",
  "properties": {
    "addr:full":"3700 Oberlin Ave Lorain OH 44053",
    "addr:housenumber":"3700",
    "addr:postcode":"44053",
    "addr:street":"Oberlin Ave",
    "iso:country":"US",
    "sg:address":"3700 Oberlin Ave",
    "sg:city":"Lorain",
    "sg:classifiers":[
        {
            "category":"Bars & Pubs",
            "type":"Food & Drink"
        },
        {
            "category":"Restaurant",
            "type":"Food & Drink"
        }
    ],
    "sg:phone":"+1 440 282 4080",
    "sg:postcode":"44053",
    "sg:province":"OH",
    "sg:tags":[
        "club",
        "drinking",
        "eating",
        "night"
    ],
    "wof:name":"Mutt & Jeff's",
    "wof:placetype":"venue"
},
  "geometry": {"coordinates":[-82.18542600000001,41.436045],"type":"Point"}
}