{
  "type": "Feature",
  "properties": {
    "addr:full": "200 Northland Blvd Cincinnati OH 45246",
    "addr:housenumber": "200",
    "addr:postcode": "45246",
    "addr:street": "Northland Blvd",
    "iso:country": "US",
    "sg:address": "200 Northland Blvd",
    "sg:city": "Cincinnati",
    "sg:classifiers": [
      {
        "category": "Health Services",
        "subcategory": "Doctor",
        "type": "Services"
      }
    ],
    "sg:phone": "+1 513 771 1644",
    "sg:postcode": "45246",
    "sg:province": "OH",
    "sg:tags": [
      "physician",
      "surgeon"
    ],
    "wof:name": "Anesthesia Group Practice Inc",
    "wof:placetype": "venue"
  },
  "geometry": {"coordinates":[-84.476025,39.284052],"type":"Point"}
}
