{
  "type": "Feature",
  "properties": {
    "addr:full": "2163 Claremont Ave Ashland OH 44805",
    "addr:housenumber": "2163",
    "addr:postcode": "44805",
    "addr:street": "Claremont Ave",
    "iso:country": "US",
    "sg:address": "2163 Claremont Ave",
    "sg:city": "Ashland",
    "sg:classifiers": [
      {
        "category": "Health Services",
        "subcategory": "Hospital",
        "type": "Services"
      }
    ],
    "sg:phone": "+1 419 281 1330",
    "sg:postcode": "44805",
    "sg:province": "OH",
    "sg:tags": [
      "general"
    ],
    "sg:website": "www.samaritanhospital.org",
    "wof:name": "Samaritan Health \u0026 Rehab Ctr",
    "wof:placetype": "venue"
  },
  "geometry": {"coordinates":[-82.341702,40.850964],"type":"Point"}
}
