{
  "type": "Feature",
  "properties": {
    "iso:country":"US",
    "sg:address":"2163 Claremont Ave",
    "sg:city":"Ashland",
    "sg:classifiers":[
        {
            "category":"Health Services",
            "subcategory":"Hospital",
            "type":"Services"
        }
    ],
    "sg:phone":"+1 419 281 1330",
    "sg:postcode":"44805",
    "sg:province":"OH",
    "sg:tags":[
        "general"
    ],
    "sg:website":"www.samaritanhospital.org",
    "wof:name":"Samaritan Health & Rehab Ctr",
    "wof:placetype":"venue"
},
  "geometry": {"coordinates":[-82.341702,40.850964],"type":"Point"}
}