{
  "type": "Feature",
  "properties": {
    "iso:country":"US",
    "sg:address":"5235 Morning Sun Rd",
    "sg:city":"Oxford",
    "sg:classifiers":[
        {
            "category":"Health Services",
            "subcategory":"Doctor",
            "type":"Services"
        }
    ],
    "sg:phone":"+1 513 524 9555",
    "sg:postcode":"45056",
    "sg:province":"OH",
    "sg:tags":[
        "physician",
        "surgeon"
    ],
    "wof:name":"Jetmore Bawa & Hirons",
    "wof:placetype":"venue"
},
  "geometry": {"coordinates":[-84.741394,39.517865],"type":"Point"}
}