{
  "type": "Feature",
  "properties": {
    "addr:full":"11 W Dayton Yellow Springs Rd Fairborn OH 45324",
    "addr:housenumber":"11",
    "addr:postcode":"45324",
    "addr:street":"W Dayton Yellow Springs Rd",
    "iso:country":"US",
    "sg:address":"11 W Dayton Yellow Springs Rd",
    "sg:city":"Fairborn",
    "sg:classifiers":[
        {
            "category":"Restaurant",
            "type":"Food & Drink"
        }
    ],
    "sg:phone":"+1 937 878 7585",
    "sg:postcode":"45324",
    "sg:province":"OH",
    "sg:tags":[
        "eating"
    ],
    "sg:website":"www.twinsgroup.com",
    "wof:name":"Pizza Hut",
    "wof:placetype":"venue"
},
  "geometry": {"coordinates":[-84.029369,39.794711],"type":"Point"}
}