{
  "type": "Feature",
  "properties": {
    "iso:country":"US",
    "sg:address":"2171 S Green Rd",
    "sg:city":"Cleveland",
    "sg:classifiers":[
        {
            "category":"Shopping",
            "type":"Retail Goods"
        }
    ],
    "sg:phone":"+1 216 691 4500",
    "sg:postcode":"44121",
    "sg:province":"OH",
    "sg:tags":[
        "merchandise"
    ],
    "wof:name":"Just Frames & Art",
    "wof:placetype":"venue"
},
  "geometry": {"coordinates":[-81.517765,41.499375],"type":"Point"}
}