{
  "type": "Feature",
  "properties": {
    "addr:full": "2171 S Green Rd Cleveland OH 44121",
    "addr:housenumber": "2171",
    "addr:postcode": "44121",
    "addr:street": "S Green Rd",
    "iso:country": "US",
    "sg:address": "2171 S Green Rd",
    "sg:city": "Cleveland",
    "sg:classifiers": [
      {
        "category": "Shopping",
        "type": "Retail Goods"
      }
    ],
    "sg:phone": "+1 216 691 4500",
    "sg:postcode": "44121",
    "sg:province": "OH",
    "sg:tags": [
      "merchandise"
    ],
    "wof:name": "Just Frames \u0026 Art",
    "wof:placetype": "venue"
  },
  "geometry": {"coordinates":[-81.517765,41.499375],"type":"Point"}
}
