{
  "type": "Feature",
  "properties": {
    "iso:country":"US",
    "sg:address":"2749 North St",
    "sg:city":"Clinton",
    "sg:classifiers":[
        {
            "category":"Government",
            "subcategory":"Office",
            "type":"Public Place"
        }
    ],
    "sg:phone":"+1 330 882 4782",
    "sg:postcode":"44216",
    "sg:province":"OH",
    "sg:tags":[
        "village"
    ],
    "wof:name":"Clinton Village Office",
    "wof:placetype":"venue"
},
  "geometry": {"coordinates":[-81.628084,40.927904],"type":"Point"}
}