{
  "type": "Feature",
  "properties": {
    "addr:full": "9986 Thrush Pl Dayton OH 45458",
    "addr:housenumber": "9986",
    "addr:postcode": "45458",
    "addr:street": "Thrush Pl",
    "iso:country": "US",
    "sg:address": "9986 Thrush Pl",
    "sg:city": "Dayton",
    "sg:classifiers": [
      {
        "category": "Banks \u0026 Credit Unions",
        "subcategory": "Financial Services",
        "type": "Services"
      }
    ],
    "sg:phone": "+1 937 885 9847",
    "sg:postcode": "45458",
    "sg:province": "OH",
    "sg:tags": [
      "investor"
    ],
    "wof:name": "Greentree Properties LLC",
    "wof:placetype": "venue"
  },
  "geometry": {"coordinates":[-84.16855,39.599362],"type":"Point"}
}
