{
  "type": "Feature",
  "properties": {
    "iso:country":"US",
    "sg:address":"42 W Center St",
    "sg:city":"Germantown",
    "sg:classifiers":[
        {
            "category":"Personal",
            "subcategory":"Beauty Salon",
            "type":"Services"
        }
    ],
    "sg:phone":"+1 937 855 6803",
    "sg:postcode":"45327",
    "sg:province":"OH",
    "wof:name":"Images",
    "wof:placetype":"venue"
},
  "geometry": {"coordinates":[-84.371477,39.626065],"type":"Point"}
}