{
  "type": "Feature",
  "properties": {
    "addr:full":"2295 Palmleaf Ct Columbus OH 43235",
    "addr:housenumber":"2295",
    "addr:postcode":"43235",
    "addr:street":"Palmleaf Ct",
    "iso:country":"US",
    "sg:address":"2295 Palmleaf Ct",
    "sg:city":"Columbus",
    "sg:classifiers":[
        {
            "category":"Shopping",
            "subcategory":"Computers & Home Electronics",
            "type":"Retail Goods"
        }
    ],
    "sg:phone":"+1 614 761 1766",
    "sg:postcode":"43235",
    "sg:province":"OH",
    "wof:name":"Custom Made Computers",
    "wof:placetype":"venue"
},
  "geometry": {"coordinates":[-83.07735099999999,40.106533],"type":"Point"}
}