{
  "type": "Feature",
  "properties": {
    "iso:country":"US",
    "sg:address":"2295 Palmleaf Ct",
    "sg:city":"Columbus",
    "sg:classifiers":[
        {
            "category":"Shopping",
            "subcategory":"Computers & Home Electronics",
            "type":"Retail Goods"
        }
    ],
    "sg:phone":"+1 614 761 1766",
    "sg:postcode":"43235",
    "sg:province":"OH",
    "wof:name":"Custom Made Computers",
    "wof:placetype":"venue"
},
  "geometry": {"coordinates":[-83.077351,40.106533],"type":"Point"}
}