{
  "type": "Feature",
  "properties": {
    "addr:full":"2246 Kipling Ave Cincinnati OH 45239",
    "addr:housenumber":"2246",
    "addr:postcode":"45239",
    "addr:street":"Kipling Ave",
    "iso:country":"US",
    "sg:address":"2246 Kipling Ave",
    "sg:city":"Cincinnati",
    "sg:classifiers":[
        {
            "category":"Professional",
            "type":"Services"
        }
    ],
    "sg:phone":"+1 513 591 0119",
    "sg:postcode":"45239",
    "sg:province":"OH",
    "wof:name":"Silver Dyme",
    "wof:placetype":"venue"
},
  "geometry": {"coordinates":[-84.567176,39.202112],"type":"Point"}
}