{
  "type": "Feature",
  "properties": {
    "addr:full": "909 E Ross Ave Cincinnati OH 45217",
    "addr:housenumber": "909",
    "addr:postcode": "45217",
    "addr:street": "E Ross Ave",
    "iso:country": "US",
    "sg:address": "909 E Ross Ave",
    "sg:city": "Cincinnati",
    "sg:classifiers": [
      {
        "category": "Wholesale",
        "subcategory": "Machinery \u0026 Supplies",
        "type": "Manufacturing \u0026 Wholesale Goods"
      }
    ],
    "sg:phone": "+1 513 641 1010",
    "sg:postcode": "45217",
    "sg:province": "OH",
    "sg:tags": [
      "equipment",
      "mfg",
      "establishment",
      "concrete"
    ],
    "wof:name": "Baxter-Wilbert Burial Vault",
    "wof:placetype": "venue"
  },
  "geometry": {"coordinates":[-84.482633,39.168709],"type":"Point"}
}
