{
  "type": "Feature",
  "properties": {
    "addr:full": "840 S Diamond St Mansfield OH 44907",
    "addr:housenumber": "840",
    "addr:postcode": "44907",
    "addr:street": "S Diamond St",
    "iso:country": "US",
    "sg:address": "840 S Diamond St",
    "sg:city": "Mansfield",
    "sg:classifiers": [
      {
        "category": "Organizations",
        "subcategory": "Community Association",
        "type": "Services"
      }
    ],
    "sg:phone": "+1 419 522 7588",
    "sg:postcode": "44907",
    "sg:province": "OH",
    "wof:name": "Optimist International",
    "wof:placetype": "venue"
  },
  "geometry": {"coordinates":[-82.49754,40.74136],"type":"Point"}
}
