{
  "type": "Feature",
  "properties": {
    "addr:full": "2070 Sullivant Ave Columbus OH 43223",
    "addr:postcode": "2070;43223",
    "addr:street": "Sullivant Ave",
    "iso:country": "US",
    "sg:address": "2070 Sullivant Ave",
    "sg:city": "Columbus",
    "sg:classifiers": [
      {
        "category": "Government",
        "subcategory": "Police Station",
        "type": "Public Place"
      }
    ],
    "sg:phone": "+1 614 645 4597",
    "sg:postcode": "43223",
    "sg:province": "OH",
    "sg:tags": [
      "protection"
    ],
    "wof:name": "Police-Precinct-8",
    "wof:placetype": "venue"
  },
  "geometry": {"coordinates":[-83.053502,39.947356],"type":"Point"}
}
