{
  "type": "Feature",
  "properties": {
    "addr:full": "9536 Broadview Rd Cleveland OH 44147",
    "addr:housenumber": "9536",
    "addr:postcode": "44147",
    "addr:street": "Broadview Rd",
    "iso:country": "US",
    "sg:address": "9536 Broadview Rd",
    "sg:city": "Cleveland",
    "sg:classifiers": [
      {
        "category": "Retail",
        "subcategory": "Auto Rental",
        "type": "Services"
      }
    ],
    "sg:phone": "+1 440 526 9057",
    "sg:postcode": "44147",
    "sg:province": "OH",
    "sg:tags": [
      "renting",
      "truck",
      "leasing"
    ],
    "sg:website": "www.taylorrental.com",
    "wof:name": "Budget Truck Rental",
    "wof:placetype": "venue"
  },
  "geometry": {"coordinates":[-81.684794,41.301754],"type":"Point"}
}
