{
  "type": "Feature",
  "properties": {
    "iso:country":"US",
    "sg:address":"1350 W 3rd St",
    "sg:city":"Cleveland",
    "sg:classifiers":[
        {
            "category":"Local Transit",
            "type":"Transportation"
        }
    ],
    "sg:phone":"+1 216 623 8800",
    "sg:postcode":"44113",
    "sg:province":"OH",
    "sg:tags":[
        "limousine"
    ],
    "wof:name":"Best Price Limousine Svc",
    "wof:placetype":"venue"
},
  "geometry": {"coordinates":[-81.696707,41.500143],"type":"Point"}
}