{
  "type": "Feature",
  "properties": {
    "addr:full":"250 Ledge Rd Macedonia OH 44056",
    "addr:housenumber":"250",
    "addr:postcode":"44056",
    "addr:street":"Ledge Rd",
    "iso:country":"US",
    "sg:address":"250 Ledge Rd",
    "sg:city":"Macedonia",
    "sg:classifiers":[
        {
            "category":"Professional",
            "type":"Services"
        }
    ],
    "sg:phone":"+1 330 659 3035",
    "sg:postcode":"44056",
    "sg:province":"OH",
    "sg:tags":[
        "establishment"
    ],
    "wof:name":"Green Valley Inc",
    "wof:placetype":"venue"
},
  "geometry": {"coordinates":[-81.519221,41.335645],"type":"Point"}
}