{
  "type": "Feature",
  "properties": {
    "iso:country":"US",
    "sg:address":"204 E Sycamore St",
    "sg:city":"Columbus Grove",
    "sg:classifiers":[
        {
            "category":"Health Services",
            "subcategory":"Doctor",
            "type":"Services"
        }
    ],
    "sg:phone":"+1 419 659 2134",
    "sg:postcode":"45830",
    "sg:province":"OH",
    "sg:tags":[
        "physician",
        "surgeon"
    ],
    "wof:name":"Lima Group Family Physicians",
    "wof:placetype":"venue"
},
  "geometry": {"coordinates":[-84.056091,40.918783],"type":"Point"}
}