{
  "type": "Feature",
  "properties": {
    "iso:country":"US",
    "sg:address":"10858 Ravenna Rd",
    "sg:city":"Twinsburg",
    "sg:classifiers":[
        {
            "category":"Home & Garden",
            "subcategory":"Home Furnishings",
            "type":"Retail Goods"
        }
    ],
    "sg:phone":"+1 330 425 1277",
    "sg:postcode":"44087",
    "sg:province":"OH",
    "sg:tags":[
        "contractor"
    ],
    "wof:name":"Twinsburg Fireplace Shop",
    "wof:placetype":"venue"
},
  "geometry": {"coordinates":[-81.467408,41.332108],"type":"Point"}
}