{
  "type": "Feature",
  "properties": {
    "addr:full": "4045 E US Rte 36 Fletcher OH 45326",
    "addr:housenumber": "4045",
    "addr:postcode": "45326",
    "addr:street": "E Us Rte 36",
    "iso:country": "US",
    "sg:address": "4045 E US Rte 36",
    "sg:city": "Fletcher",
    "sg:classifiers": [
      {
        "category": "Education",
        "subcategory": "School",
        "type": "Public Place"
      }
    ],
    "sg:phone": "+1 937 368 2332",
    "sg:postcode": "45326",
    "sg:province": "OH",
    "wof:name": "Miami East N Elementary Schl",
    "wof:placetype": "venue"
  },
  "geometry": {"coordinates":[-84.126223,40.145881],"type":"Point"}
}
