{
  "type": "Feature",
  "properties": {
    "addr:full":"225 N Sandusky Ave Bucyrus OH 44820",
    "addr:housenumber":"225",
    "addr:postcode":"44820",
    "addr:street":"N Sandusky Ave",
    "iso:country":"US",
    "sg:address":"225 N Sandusky Ave",
    "sg:city":"Bucyrus",
    "sg:classifiers":[
        {
            "category":"Shopping",
            "subcategory":"Jewelry",
            "type":"Retail Goods"
        }
    ],
    "sg:phone":"+1 419 562 2736",
    "sg:postcode":"44820",
    "sg:province":"OH",
    "sg:tags":[
        "repair",
        "jeweler"
    ],
    "wof:name":"Ley's Jewelry",
    "wof:placetype":"venue"
},
  "geometry": {"coordinates":[-82.97566999999999,40.810575],"type":"Point"}
}