{
  "type": "Feature",
  "properties": {
    "iso:country":"US",
    "sg:address":"3333 Detroit Ave",
    "sg:city":"Cleveland",
    "sg:classifiers":[
        {
            "category":"Retail",
            "subcategory":"Auto Repair",
            "type":"Services"
        }
    ],
    "sg:phone":"+1 216 651 8181",
    "sg:postcode":"44113",
    "sg:province":"OH",
    "sg:tags":[
        "repairing",
        "automobile"
    ],
    "wof:name":"Jnc Auto Svc",
    "wof:placetype":"venue"
},
  "geometry": {"coordinates":[-81.714764,41.488165],"type":"Point"}
}