{
  "type": "Feature",
  "properties": {
    "iso:country":"US",
    "sg:address":"1404 South St",
    "sg:city":"Piqua",
    "sg:classifiers":[
        {
            "category":"Retail",
            "subcategory":"Auto Repair",
            "type":"Services"
        }
    ],
    "sg:phone":"+1 937 778 8468",
    "sg:postcode":"45356",
    "sg:province":"OH",
    "sg:tags":[
        "repairing",
        "automobile"
    ],
    "wof:name":"Piqua Muffler Shop",
    "wof:placetype":"venue"
},
  "geometry": {"coordinates":[-84.25962699999999,40.137205],"type":"Point"}
}