{
  "type": "Feature",
  "properties": {
    "addr:full":"2159 Harrisburg Pike Grove City OH 43123",
    "addr:housenumber":"2159",
    "addr:postcode":"43123",
    "addr:street":"Harrisburg Pike",
    "iso:country":"US",
    "sg:address":"2159 Harrisburg Pike",
    "sg:city":"Grove City",
    "sg:classifiers":[
        {
            "category":"Autos & Motor Vehicles",
            "subcategory":"Automobile Sales",
            "type":"Retail Goods"
        }
    ],
    "sg:phone":"+1 614 277 3265",
    "sg:postcode":"43123",
    "sg:province":"OH",
    "sg:tags":[
        "car",
        "dealer"
    ],
    "wof:name":"Brown's Motor Sales & Svc",
    "wof:placetype":"venue"
},
  "geometry": {"coordinates":[-83.066208,39.914821],"type":"Point"}
}