{
  "type": "Feature",
  "properties": {
    "addr:full":"1500 S Green Rd Cleveland OH 44121",
    "addr:housenumber":"1500",
    "addr:postcode":"44121",
    "addr:street":"S Green Rd",
    "iso:country":"US",
    "sg:address":"1500 S Green Rd",
    "sg:city":"Cleveland",
    "sg:classifiers":[
        {
            "category":"Professional",
            "type":"Services"
        }
    ],
    "sg:phone":"+1 216 691 0648",
    "sg:postcode":"44121",
    "sg:province":"OH",
    "wof:name":"Howard B Abramoff",
    "wof:placetype":"venue"
},
  "geometry": {"coordinates":[-81.519492,41.51949],"type":"Point"}
}