{
  "type": "Feature",
  "properties": {
    "iso:country":"US",
    "sg:address":"1407 Stanley Ave",
    "sg:city":"Dayton",
    "sg:classifiers":[
        {
            "category":"Manufacturing",
            "subcategory":"Tools & Machinery",
            "type":"Manufacturing & Wholesale Goods"
        }
    ],
    "sg:phone":"+1 937 228 0900",
    "sg:postcode":"45404",
    "sg:province":"OH",
    "sg:tags":[
        "machine",
        "shop"
    ],
    "wof:name":"Magnum Tool Corp",
    "wof:placetype":"venue"
},
  "geometry": {"coordinates":[-84.19619899999999,39.783493],"type":"Point"}
}