{
  "type": "Feature",
  "properties": {
    "iso:country":"US",
    "sg:address":"830 Walnut St",
    "sg:city":"Elyria",
    "sg:classifiers":[
        {
            "category":"Building & Trades",
            "subcategory":"Plumbing",
            "type":"Services"
        }
    ],
    "sg:phone":"+1 440 324 2018",
    "sg:postcode":"44035",
    "sg:province":"OH",
    "sg:tags":[
        "plumbing",
        "fire",
        "contractor",
        "sprinkler",
        "heating"
    ],
    "wof:name":"Ray Esser & Sons Inc",
    "wof:placetype":"venue"
},
  "geometry": {"coordinates":[-82.124685,41.381667],"type":"Point"}
}