{
  "type": "Feature",
  "properties": {
    "iso:country":"US",
    "sg:address":"864 Southpark Ctr",
    "sg:city":"Strongsville",
    "sg:classifiers":[
        {
            "category":"Restaurant",
            "type":"Food & Drink"
        }
    ],
    "sg:menulink":"http://www.allmenus.com/oh/strongsville/122432-quiznos-sub/menu/",
    "sg:phone":"+1 440 846 2260",
    "sg:postcode":"44136",
    "sg:province":"OH",
    "sg:tags":[
        "wrap",
        "american",
        "sandwich"
    ],
    "wof:name":"Quiznos Sub",
    "wof:placetype":"venue"
},
  "geometry": {"coordinates":[-81.824246,41.311121],"type":"Point"}
}