{
  "type": "Feature",
  "properties": {
    "addr:full":"7664 W Chester Rd West Chester OH 45069",
    "addr:housenumber":"7664",
    "addr:postcode":"45069",
    "addr:street":"W Chester Rd",
    "iso:country":"US",
    "sg:address":"7664 W Chester Rd",
    "sg:city":"West Chester",
    "sg:classifiers":[
        {
            "category":"Home & Garden",
            "subcategory":"Home Furnishings",
            "type":"Retail Goods"
        }
    ],
    "sg:phone":"+1 513 755 9804",
    "sg:postcode":"45069",
    "sg:province":"OH",
    "sg:tags":[
        "linen"
    ],
    "wof:name":"Linens 'n Things",
    "wof:placetype":"venue"
},
  "geometry": {"coordinates":[-84.373622,39.319],"type":"Point"}
}