{
  "type": "Feature",
  "properties": {
    "iso:country":"US",
    "sg:address":"2685 W 14th St",
    "sg:city":"Cleveland",
    "sg:classifiers":[
        {
            "category":"Utilities",
            "subcategory":"Mobile Phone",
            "type":"Services"
        }
    ],
    "sg:phone":"+1 216 749 3161",
    "sg:postcode":"44113",
    "sg:province":"OH",
    "sg:tags":[
        "equipment",
        "paging",
        "signaling",
        "system"
    ],
    "wof:name":"Mega Pagers Plus",
    "wof:placetype":"venue"
},
  "geometry": {"coordinates":[-81.69121199999999,41.475913],"type":"Point"}
}