{
  "type": "Feature",
  "properties": {
    "addr:full": "2685 W 14th St Cleveland OH 44113",
    "addr:housenumber": "2685",
    "addr:postcode": "44113",
    "addr:street": "W 14Th St",
    "iso:country": "US",
    "sg:address": "2685 W 14th St",
    "sg:city": "Cleveland",
    "sg:classifiers": [
      {
        "category": "Utilities",
        "subcategory": "Mobile Phone",
        "type": "Services"
      }
    ],
    "sg:phone": "+1 216 749 3161",
    "sg:postcode": "44113",
    "sg:province": "OH",
    "sg:tags": [
      "equipment",
      "paging",
      "signaling",
      "system"
    ],
    "wof:name": "Mega Pagers Plus",
    "wof:placetype": "venue"
  },
  "geometry": {"coordinates":[-81.691212,41.475913],"type":"Point"}
}
