{
  "type": "Feature",
  "properties": {
    "iso:country":"US",
    "sg:address":"2642 Bethel Rd",
    "sg:city":"Columbus",
    "sg:classifiers":[
        {
            "category":"Shopping",
            "type":"Retail Goods"
        }
    ],
    "sg:phone":"+1 614 459 5989",
    "sg:postcode":"43220",
    "sg:province":"OH",
    "sg:tags":[
        "pet",
        "shop"
    ],
    "wof:name":"Petland",
    "wof:placetype":"venue"
},
  "geometry": {"coordinates":[-83.092939,40.065019],"type":"Point"}
}