{
  "type": "Feature",
  "properties": {
    "iso:country":"US",
    "sg:address":"280 Bates Rd",
    "sg:city":"Madison",
    "sg:classifiers":[
        {
            "category":"Building & Trades",
            "subcategory":"Construction",
            "type":"Services"
        }
    ],
    "sg:phone":"+1 440 428 6436",
    "sg:postcode":"44057",
    "sg:province":"OH",
    "sg:tags":[
        "house"
    ],
    "wof:name":"Jim Molner Carpentry",
    "wof:placetype":"venue"
},
  "geometry": {"coordinates":[-81.030288,41.786592],"type":"Point"}
}