{
  "type": "Feature",
  "properties": {
    "addr:full":"3484 Towne Blvd Franklin OH 45005",
    "addr:housenumber":"3484",
    "addr:postcode":"45005",
    "addr:street":"Towne Blvd",
    "iso:country":"US",
    "sg:address":"3484 Towne Blvd",
    "sg:city":"Franklin",
    "sg:classifiers":[
        {
            "category":"Food & Beverages",
            "subcategory":"Groceries & Convenience Stores",
            "type":"Retail Goods"
        }
    ],
    "sg:phone":"+1 513 422 3393",
    "sg:postcode":"45005",
    "sg:province":"OH",
    "wof:name":"Kroger",
    "wof:placetype":"venue"
},
  "geometry": {"coordinates":[-84.33044599999999,39.501445],"type":"Point"}
}