{
  "type": "Feature",
  "properties": {
    "iso:country":"US",
    "sg:address":"231 Springside Dr",
    "sg:city":"Akron",
    "sg:classifiers":[
        {
            "category":"Professional",
            "subcategory":"Management & Consulting",
            "type":"Services"
        }
    ],
    "sg:phone":"+1 330 666 4402",
    "sg:postcode":"44333",
    "sg:province":"OH",
    "sg:tags":[
        "consultant",
        "educational"
    ],
    "wof:name":"Pearson Professional Ctr",
    "wof:placetype":"venue"
},
  "geometry": {"coordinates":[-81.643365,41.141796],"type":"Point"}
}