{
  "type": "Feature",
  "properties": {
    "addr:full":"384 Twp Rd 35 Ada OH 45810",
    "addr:housenumber":"384;35",
    "addr:postcode":"45810",
    "addr:street":"Twp Rd",
    "iso:country":"US",
    "sg:address":"384 Twp Rd 35",
    "sg:city":"Ada",
    "sg:phone":"+1 419 634 3907",
    "sg:postcode":"45810",
    "sg:province":"OH",
    "sg:tags":[
        "farm",
        "soybean"
    ],
    "wof:name":"Jerry Wolber",
    "wof:placetype":"venue"
},
  "geometry": {"coordinates":[-83.842376,40.814406],"type":"Point"}
}