{
  "type": "Feature",
  "properties": {
    "iso:country":"US",
    "sg:address":"50 Shopping Plz",
    "sg:city":"Chagrin Falls",
    "sg:classifiers":[
        {
            "category":"Shopping",
            "subcategory":"Bicycles & Sporting Goods",
            "type":"Retail Goods"
        }
    ],
    "sg:phone":"+1 440 247 4900",
    "sg:postcode":"44022",
    "sg:province":"OH",
    "wof:name":"Geiger's Ski & Sport Haus",
    "wof:placetype":"venue"
},
  "geometry": {"coordinates":[-81.391289,41.430713],"type":"Point"}
}