{
  "type": "Feature",
  "properties": {
    "addr:full": "50 Shopping Plz Chagrin Falls OH 44022",
    "addr:postcode": "44022",
    "addr:street": "Shopping Plz",
    "iso:country": "US",
    "sg:address": "50 Shopping Plz",
    "sg:city": "Chagrin Falls",
    "sg:classifiers": [
      {
        "category": "Shopping",
        "subcategory": "Bicycles \u0026 Sporting Goods",
        "type": "Retail Goods"
      }
    ],
    "sg:phone": "+1 440 247 4900",
    "sg:postcode": "44022",
    "sg:province": "OH",
    "wof:name": "Geiger's Ski \u0026 Sport Haus",
    "wof:placetype": "venue"
  },
  "geometry": {"coordinates":[-81.391289,41.430713],"type":"Point"}
}
