{
  "type": "Feature",
  "properties": {
    "addr:full": "2575 Hayes Ave Fremont OH 43420",
    "addr:housenumber": "2575",
    "addr:postcode": "43420",
    "addr:street": "Hayes Ave",
    "iso:country": "US",
    "sg:address": "2575 Hayes Ave",
    "sg:city": "Fremont",
    "sg:classifiers": [
      {
        "category": "Health Services",
        "subcategory": "Doctor",
        "type": "Services"
      }
    ],
    "sg:phone": "+1 419 332 4215",
    "sg:postcode": "43420",
    "sg:province": "OH",
    "sg:tags": [
      "physician",
      "surgeon"
    ],
    "wof:name": "Dr Winder \u0026 Assoc",
    "wof:placetype": "venue"
  },
  "geometry": {"coordinates":[-83.151131,41.342031],"type":"Point"}
}
