{
  "type": "Feature",
  "properties": {
    "addr:full": "333 Sherbourne Dr Columbus OH 43219",
    "addr:housenumber": "333",
    "addr:postcode": "43219",
    "addr:street": "Sherbourne Dr",
    "iso:country": "US",
    "sg:address": "333 Sherbourne Dr",
    "sg:city": "Columbus",
    "sg:classifiers": [
      {
        "category": "Building \u0026 Trades",
        "subcategory": "Construction",
        "type": "Services"
      }
    ],
    "sg:phone": "+1 614 258 7986",
    "sg:postcode": "43219",
    "sg:province": "OH",
    "sg:tags": [
      "residential",
      "nonresidential"
    ],
    "wof:name": "Rl Sessley Construction",
    "wof:placetype": "venue"
  },
  "geometry": {"coordinates":[-82.94852,39.974969],"type":"Point"}
}
