{
  "type": "Feature",
  "properties": {
    "addr:full":"3202 Cliftmont Ave NE Canton OH 44705",
    "addr:housenumber":"3202",
    "addr:postcode":"44705",
    "addr:street":"Cliftmont Ave Ne",
    "iso:country":"US",
    "sg:address":"3202 Cliftmont Ave NE",
    "sg:city":"Canton",
    "sg:classifiers":[
        {
            "category":"Organizations",
            "subcategory":"Religious Organization",
            "type":"Services"
        }
    ],
    "sg:phone":"+1 330 456 4563",
    "sg:postcode":"44705",
    "sg:province":"OH",
    "sg:tags":[
        "church"
    ],
    "wof:name":"Church Canton Freewill Baptist",
    "wof:placetype":"venue"
},
  "geometry": {"coordinates":[-81.315403,40.830729],"type":"Point"}
}