{
  "type": "Feature",
  "properties": {
    "iso:country":"US",
    "sg:address":"612 Harding Way W",
    "sg:city":"Galion",
    "sg:classifiers":[
        {
            "category":"Cinema",
            "subcategory":"Movie Rental",
            "type":"Entertainment"
        }
    ],
    "sg:phone":"+1 419 462 8580",
    "sg:postcode":"44833",
    "sg:province":"OH",
    "sg:tags":[
        "leasing",
        "video",
        "disc",
        "tape"
    ],
    "wof:name":"Harris Video Svc",
    "wof:placetype":"venue"
},
  "geometry": {"coordinates":[-82.798478,40.734092],"type":"Point"}
}