{
  "type": "Feature",
  "properties": {
    "addr:full":"2749 Co Rd 174 Fremont OH 43420",
    "addr:housenumber":"2749;174",
    "addr:postcode":"43420",
    "addr:street":"Co Rd",
    "iso:country":"US",
    "sg:address":"2749 Co Rd 174",
    "sg:city":"Fremont",
    "sg:classifiers":[
        {
            "category":"Farming",
            "subcategory":"Livestock Farm",
            "type":"Manufacturing & Wholesale Goods"
        }
    ],
    "sg:phone":"+1 419 332 9596",
    "sg:postcode":"43420",
    "sg:province":"OH",
    "sg:tags":[
        "feedlot",
        "cattle",
        "crop",
        "beef",
        "general"
    ],
    "wof:name":"King Farm",
    "wof:placetype":"venue"
},
  "geometry": {"coordinates":[-83.097041,41.420269],"type":"Point"}
}