{
  "type": "Feature",
  "properties": {
    "addr:full":"973 Eastward Cir Zanesville OH 43701",
    "addr:housenumber":"973",
    "addr:postcode":"43701",
    "addr:street":"Eastward Cir",
    "iso:country":"US",
    "sg:address":"973 Eastward Cir",
    "sg:city":"Zanesville",
    "sg:classifiers":[
        {
            "category":"Home & Garden",
            "subcategory":"Hardware",
            "type":"Retail Goods"
        }
    ],
    "sg:phone":"+1 740 452 7679",
    "sg:postcode":"43701",
    "sg:province":"OH",
    "wof:name":"Barnett's Hardware Inc",
    "wof:placetype":"venue"
},
  "geometry": {"coordinates":[-82.01168199999999,39.985184],"type":"Point"}
}