{
  "type": "Feature",
  "properties": {
    "addr:full": "3950 Chester Ave Cleveland OH 44114",
    "addr:housenumber": "3950",
    "addr:postcode": "44114",
    "addr:street": "Chester Ave",
    "iso:country": "US",
    "sg:address": "3950 Chester Ave",
    "sg:city": "Cleveland",
    "sg:classifiers": [
      {
        "category": "Organizations",
        "subcategory": "Non-profit Organization",
        "type": "Services"
      }
    ],
    "sg:phone": "+1 216 431 4140",
    "sg:postcode": "44114",
    "sg:province": "OH",
    "sg:tags": [
      "information",
      "alcoholism",
      "treatment"
    ],
    "wof:name": "Employee Assistance Program",
    "wof:placetype": "venue"
  },
  "geometry": {"coordinates":[-81.662231,41.504725],"type":"Point"}
}
