{
  "type": "Feature",
  "properties": {
    "addr:full": "100 Worthington Mall Worthington OH 43085",
    "addr:housenumber": "100",
    "addr:postcode": "43085",
    "addr:street": "Worthington Mall",
    "iso:country": "US",
    "sg:address": "100 Worthington Mall",
    "sg:city": "Worthington",
    "sg:classifiers": [
      {
        "category": "Home \u0026 Garden",
        "subcategory": "Home Furnishings",
        "type": "Retail Goods"
      }
    ],
    "sg:phone": "+1 614 985 4740",
    "sg:postcode": "43085",
    "sg:province": "OH",
    "sg:tags": [
      "utensil",
      "cooking"
    ],
    "wof:name": "Cook's Cabinet",
    "wof:placetype": "venue"
  },
  "geometry": {"coordinates":[-83.017239,40.107903],"type":"Point"}
}
