{
  "type": "Feature",
  "properties": {
    "iso:country":"US",
    "sg:address":"21 W Market St",
    "sg:city":"Germantown",
    "sg:classifiers":[
        {
            "category":"Restaurant",
            "type":"Food & Drink"
        }
    ],
    "sg:phone":"+1 937 855 7759",
    "sg:postcode":"45327",
    "sg:province":"OH",
    "wof:name":"Florentine Restaurant",
    "wof:placetype":"venue"
},
  "geometry": {"coordinates":[-84.37163700000001,39.624835],"type":"Point"}
}