{
  "type": "Feature",
  "properties": {
    "addr:full": "21 W Market St Germantown OH 45327",
    "addr:housenumber": "21",
    "addr:postcode": "45327",
    "addr:street": "W Market St",
    "iso:country": "US",
    "sg:address": "21 W Market St",
    "sg:city": "Germantown",
    "sg:classifiers": [
      {
        "category": "Restaurant",
        "type": "Food \u0026 Drink"
      }
    ],
    "sg:phone": "+1 937 855 7759",
    "sg:postcode": "45327",
    "sg:province": "OH",
    "wof:name": "Florentine Restaurant",
    "wof:placetype": "venue"
  },
  "geometry": {"coordinates":[-84.371637,39.624835],"type":"Point"}
}
