{
  "type": "Feature",
  "properties": {
    "iso:country":"US",
    "sg:address":"3103 Executive Pkwy",
    "sg:city":"Toledo",
    "sg:classifiers":[
        {
            "category":"Freight",
            "type":"Transportation"
        }
    ],
    "sg:phone":"+1 419 531 6643",
    "sg:postcode":"43606",
    "sg:province":"OH",
    "sg:tags":[
        "distributor",
        "transporter",
        "fruit",
        "vegetable",
        "fresh"
    ],
    "wof:name":"CH Robinson Company Inc",
    "wof:placetype":"venue"
},
  "geometry": {"coordinates":[-83.62856499999999,41.682276],"type":"Point"}
}