{
  "type": "Feature",
  "properties": {
    "addr:full": "10575 State Rte 56 E Circleville OH 43113",
    "addr:housenumber": "10575",
    "addr:postcode": "43113",
    "addr:street": "State Rte 56 E",
    "iso:country": "US",
    "sg:address": "10575 State Rte 56 E",
    "sg:city": "Circleville",
    "sg:classifiers": [
      {
        "category": "Building \u0026 Trades",
        "subcategory": "Construction",
        "type": "Services"
      }
    ],
    "sg:phone": "+1 740 474 8308",
    "sg:postcode": "43113",
    "sg:province": "OH",
    "sg:tags": [
      "concrete",
      "contractor"
    ],
    "wof:name": "Adams Masonry \u0026 Poured Walls",
    "wof:placetype": "venue"
  },
  "geometry": {"coordinates":[-82.838348,39.529536],"type":"Point"}
}
