{
  "type": "Feature",
  "properties": {
    "addr:full": "7606 Mc Quaid Rd Wooster OH 44691",
    "addr:housenumber": "7606",
    "addr:postcode": "44691",
    "addr:street": "Mc Quaid Rd",
    "iso:country": "US",
    "sg:address": "7606 Mc Quaid Rd",
    "sg:city": "Wooster",
    "sg:phone": "+1 330 264 0817",
    "sg:postcode": "44691",
    "sg:province": "OH",
    "sg:tags": [
      "farm",
      "grain",
      "cash"
    ],
    "wof:name": "Farms Ken Weekley",
    "wof:placetype": "venue"
  },
  "geometry": {"coordinates":[-81.840054,40.801038],"type":"Point"}
}
