{
  "type": "Feature",
  "properties": {
    "addr:full": "673 Loveland Madeira Rd Loveland OH 45140",
    "addr:housenumber": "673",
    "addr:postcode": "45140",
    "addr:street": "Loveland Madeira Rd",
    "iso:country": "US",
    "sg:address": "673 Loveland Madeira Rd",
    "sg:city": "Loveland",
    "sg:classifiers": [
      {
        "category": "Shopping",
        "type": "Retail Goods"
      }
    ],
    "sg:phone": "+1 513 677 8922",
    "sg:postcode": "45140",
    "sg:province": "OH",
    "sg:tags": [
      "factory",
      "outlet"
    ],
    "wof:name": "Cotton Mill Store",
    "wof:placetype": "venue"
  },
  "geometry": {"coordinates":[-84.268003,39.265009],"type":"Point"}
}
