{
  "type": "Feature",
  "properties": {
    "addr:full": "106 Perry St Pemberville OH 43450",
    "addr:housenumber": "106",
    "addr:postcode": "43450",
    "addr:street": "Perry St",
    "iso:country": "US",
    "sg:address": "106 Perry St",
    "sg:city": "Pemberville",
    "sg:classifiers": [
      {
        "category": "Organizations",
        "subcategory": "Religious Organization",
        "type": "Services"
      }
    ],
    "sg:phone": "+1 419 287 3366",
    "sg:postcode": "43450",
    "sg:province": "OH",
    "sg:tags": [
      "church"
    ],
    "wof:name": "First Presbyterian Church",
    "wof:placetype": "venue"
  },
  "geometry": {"coordinates":[-83.46192,41.410787],"type":"Point"}
}
