{
  "type": "Feature",
  "properties": {
    "iso:country":"US",
    "sg:address":"106 Perry St",
    "sg:city":"Pemberville",
    "sg:classifiers":[
        {
            "category":"Organizations",
            "subcategory":"Religious Organization",
            "type":"Services"
        }
    ],
    "sg:phone":"+1 419 287 3366",
    "sg:postcode":"43450",
    "sg:province":"OH",
    "sg:tags":[
        "church"
    ],
    "wof:name":"First Presbyterian Church",
    "wof:placetype":"venue"
},
  "geometry": {"coordinates":[-83.46192000000001,41.410787],"type":"Point"}
}