{
  "type": "Feature",
  "properties": {
    "iso:country":"US",
    "sg:address":"590 E Boundary St",
    "sg:city":"Perrysburg",
    "sg:classifiers":[
        {
            "category":"Organizations",
            "subcategory":"Community Association",
            "type":"Services"
        }
    ],
    "sg:phone":"+1 419 874 4577",
    "sg:postcode":"43551",
    "sg:province":"OH",
    "sg:tags":[
        "fraternal"
    ],
    "wof:name":"Masonic Lodge",
    "wof:placetype":"venue"
},
  "geometry": {"coordinates":[-83.615233,41.560251],"type":"Point"}
}