{
  "type": "Feature",
  "properties": {
    "addr:full": "6427 State Rte 95 Mount Gilead OH 43338",
    "addr:housenumber": "6427;95",
    "addr:postcode": "43338",
    "addr:street": "State Rte;Mount",
    "iso:country": "US",
    "sg:address": "6427 State Rte 95",
    "sg:city": "Mount Gilead",
    "sg:classifiers": [
      {
        "category": "Food \u0026 Beverages",
        "subcategory": "Liquor \u0026 Beverages",
        "type": "Retail Goods"
      }
    ],
    "sg:phone": "+1 419 768 3553",
    "sg:postcode": "43338",
    "sg:province": "OH",
    "sg:tags": [
      "eating",
      "alcoholic"
    ],
    "wof:name": "Bills Cruise Thru \u0026 Cntry Mkt",
    "wof:placetype": "venue"
  },
  "geometry": {"coordinates":[-82.700758,40.488032],"type":"Point"}
}
