{
  "type": "Feature",
  "properties": {
    "iso:country":"US",
    "sg:address":"6427 State Rte 95",
    "sg:city":"Mount Gilead",
    "sg:classifiers":[
        {
            "category":"Food & Beverages",
            "subcategory":"Liquor & Beverages",
            "type":"Retail Goods"
        }
    ],
    "sg:phone":"+1 419 768 3553",
    "sg:postcode":"43338",
    "sg:province":"OH",
    "sg:tags":[
        "eating",
        "alcoholic"
    ],
    "wof:name":"Bills Cruise Thru & Cntry Mkt",
    "wof:placetype":"venue"
},
  "geometry": {"coordinates":[-82.700758,40.488032],"type":"Point"}
}