{
  "type": "Feature",
  "properties": {
    "addr:full":"225 Fairway Blvd Columbus OH 43213",
    "addr:housenumber":"225",
    "addr:postcode":"43213",
    "addr:street":"Fairway Blvd",
    "iso:country":"US",
    "sg:address":"225 Fairway Blvd",
    "sg:city":"Columbus",
    "sg:classifiers":[
        {
            "category":"Health Services",
            "subcategory":"Clinic",
            "type":"Services"
        }
    ],
    "sg:phone":"+1 614 751 9780",
    "sg:postcode":"43213",
    "sg:province":"OH",
    "sg:tags":[
        "home"
    ],
    "wof:name":"Mid Ohio Home Health Care LLC",
    "wof:placetype":"venue"
},
  "geometry": {"coordinates":[-82.874357,39.972892],"type":"Point"}
}