{
  "type": "Feature",
  "properties": {
    "addr:full":"5700 Monroe St Sylvania OH 43560",
    "addr:housenumber":"5700",
    "addr:postcode":"43560",
    "addr:street":"Monroe St",
    "iso:country":"US",
    "sg:address":"5700 Monroe St",
    "sg:city":"Sylvania",
    "sg:classifiers":[
        {
            "category":"Personal",
            "subcategory":"Beauty Salon",
            "type":"Services"
        }
    ],
    "sg:phone":"+1 419 882 1369",
    "sg:postcode":"43560",
    "sg:province":"OH",
    "wof:name":"Mane Attraction",
    "wof:placetype":"venue"
},
  "geometry": {"coordinates":[-83.674661,41.709137],"type":"Point"}
}