{
  "type": "Feature",
  "properties": {
    "iso:country":"US",
    "sg:address":"5242 Angola Rd",
    "sg:city":"Toledo",
    "sg:classifiers":[
        {
            "category":"Wholesale",
            "subcategory":"Machinery & Supplies",
            "type":"Manufacturing & Wholesale Goods"
        }
    ],
    "sg:phone":"+1 419 536 8359",
    "sg:postcode":"43615",
    "sg:province":"OH",
    "sg:tags":[
        "equipment",
        "industrial",
        "repair"
    ],
    "wof:name":"Otis Elevator Company",
    "wof:placetype":"venue"
},
  "geometry": {"coordinates":[-83.669764,41.62435],"type":"Point"}
}