{
  "type": "Feature",
  "properties": {
    "addr:full": "5242 Angola Rd Toledo OH 43615",
    "addr:housenumber": "5242",
    "addr:postcode": "43615",
    "addr:street": "Angola Rd",
    "iso:country": "US",
    "sg:address": "5242 Angola Rd",
    "sg:city": "Toledo",
    "sg:classifiers": [
      {
        "category": "Wholesale",
        "subcategory": "Machinery \u0026 Supplies",
        "type": "Manufacturing \u0026 Wholesale Goods"
      }
    ],
    "sg:phone": "+1 419 536 8359",
    "sg:postcode": "43615",
    "sg:province": "OH",
    "sg:tags": [
      "equipment",
      "industrial",
      "repair"
    ],
    "wof:name": "Otis Elevator Company",
    "wof:placetype": "venue"
  },
  "geometry": {"coordinates":[-83.669764,41.62435],"type":"Point"}
}
