{
  "type": "Feature",
  "properties": {
    "iso:country":"US",
    "sg:address":"3793 Stucky Valley Rd SW",
    "sg:city":"Stone Creek",
    "sg:classifiers":[
        {
            "category":"Farming",
            "subcategory":"Farm & Veterinary Services",
            "type":"Manufacturing & Wholesale Goods"
        }
    ],
    "sg:phone":"+1 330 897 7891",
    "sg:postcode":"43840",
    "sg:province":"OH",
    "sg:tags":[
        "management"
    ],
    "wof:name":"Dale Krebs",
    "wof:placetype":"venue"
},
  "geometry": {"coordinates":[-81.61922,40.434985],"type":"Point"}
}