{
  "type": "Feature",
  "properties": {
    "addr:full": "3793 Stucky Valley Rd SW Stone Creek OH 43840",
    "addr:housenumber": "3793",
    "addr:postcode": "43840",
    "addr:street": "Stucky Valley Rd Sw Stone Creek",
    "iso:country": "US",
    "sg:address": "3793 Stucky Valley Rd SW",
    "sg:city": "Stone Creek",
    "sg:classifiers": [
      {
        "category": "Farming",
        "subcategory": "Farm \u0026 Veterinary Services",
        "type": "Manufacturing \u0026 Wholesale Goods"
      }
    ],
    "sg:phone": "+1 330 897 7891",
    "sg:postcode": "43840",
    "sg:province": "OH",
    "sg:tags": [
      "management"
    ],
    "wof:name": "Dale Krebs",
    "wof:placetype": "venue"
  },
  "geometry": {"coordinates":[-81.61922,40.434985],"type":"Point"}
}
