{
  "type": "Feature",
  "properties": {
    "iso:country":"US",
    "sg:address":"4043 Larchmere Dr",
    "sg:city":"Grove City",
    "sg:classifiers":[
        {
            "category":"Building & Trades",
            "subcategory":"Construction",
            "type":"Services"
        }
    ],
    "sg:phone":"+1 614 871 3192",
    "sg:postcode":"43123",
    "sg:province":"OH",
    "sg:tags":[
        "contractor"
    ],
    "wof:name":"Mar Bill Construction",
    "wof:placetype":"venue"
},
  "geometry": {"coordinates":[-83.114862,39.883217],"type":"Point"}
}