{
  "type": "Feature",
  "properties": {
    "addr:full":"1635 Watkins Rd Columbus OH 43207",
    "addr:housenumber":"1635",
    "addr:postcode":"43207",
    "addr:street":"Watkins Rd",
    "iso:country":"US",
    "sg:address":"1635 Watkins Rd",
    "sg:city":"Columbus",
    "sg:classifiers":[
        {
            "category":"Professional",
            "subcategory":"Business Services",
            "type":"Services"
        }
    ],
    "sg:phone":"+1 614 409 2876",
    "sg:postcode":"43207",
    "sg:province":"OH",
    "sg:tags":[
        "packaging"
    ],
    "wof:name":"Faro",
    "wof:placetype":"venue"
},
  "geometry": {"coordinates":[-82.950744,39.904436],"type":"Point"}
}