{
  "type": "Feature",
  "properties": {
    "addr:full": "5956 Glenway Ave Cincinnati OH 45238",
    "addr:housenumber": "5956",
    "addr:postcode": "45238",
    "addr:street": "Glenway Ave",
    "iso:country": "US",
    "sg:address": "5956 Glenway Ave",
    "sg:city": "Cincinnati",
    "sg:classifiers": [
      {
        "category": "Insurance",
        "subcategory": "Hazard Insurance",
        "type": "Services"
      }
    ],
    "sg:phone": "+1 513 922 1442",
    "sg:postcode": "45238",
    "sg:province": "OH",
    "sg:website": "http://statefarm.mqgroup.com/url.asp?usr=352935",
    "wof:name": "State Farm Insurance Agent-Mike Schweppe",
    "wof:placetype": "venue"
  },
  "geometry": {"coordinates":[-84.617302,39.140331],"type":"Point"}
}
