{
  "type": "Feature",
  "properties": {
    "iso:country":"US",
    "sg:address":"16595 Tavern Rd",
    "sg:city":"Burton",
    "sg:classifiers":[
        {
            "category":"Wholesale",
            "subcategory":"Construction Materials",
            "type":"Manufacturing & Wholesale Goods"
        }
    ],
    "sg:phone":"+1 440 834 1006",
    "sg:postcode":"44021",
    "sg:province":"OH",
    "wof:name":"Tri-County Insulated Building",
    "wof:placetype":"venue"
},
  "geometry": {"coordinates":[-81.102412,41.418522],"type":"Point"}
}