{
  "type": "Feature",
  "properties": {
    "addr:full": "16595 Tavern Rd Burton OH 44021",
    "addr:housenumber": "16595",
    "addr:postcode": "44021",
    "addr:street": "Tavern Rd",
    "iso:country": "US",
    "sg:address": "16595 Tavern Rd",
    "sg:city": "Burton",
    "sg:classifiers": [
      {
        "category": "Wholesale",
        "subcategory": "Construction Materials",
        "type": "Manufacturing \u0026 Wholesale Goods"
      }
    ],
    "sg:phone": "+1 440 834 1006",
    "sg:postcode": "44021",
    "sg:province": "OH",
    "wof:name": "Tri-County Insulated Building",
    "wof:placetype": "venue"
  },
  "geometry": {"coordinates":[-81.102412,41.418522],"type":"Point"}
}
