{
  "type": "Feature",
  "properties": {
    "addr:full": "3040 Madison Rd Cincinnati OH 45209",
    "addr:housenumber": "3040",
    "addr:postcode": "45209",
    "addr:street": "Madison Rd",
    "iso:country": "US",
    "sg:address": "3040 Madison Rd",
    "sg:city": "Cincinnati",
    "sg:classifiers": [
      {
        "category": "Shopping",
        "subcategory": "Hobbies, Toys, \u0026 Games",
        "type": "Retail Goods"
      }
    ],
    "sg:phone": "+1 513 531 4600",
    "sg:postcode": "45209",
    "sg:province": "OH",
    "sg:tags": [
      "store"
    ],
    "sg:website": "www.kingarthurstoys.com",
    "wof:name": "King Arthur's Court",
    "wof:placetype": "venue"
  },
  "geometry": {"coordinates":[-84.432258,39.151902],"type":"Point"}
}
