{
  "type": "Feature",
  "properties": {
    "addr:full":"319 W Main St Montpelier OH 43543",
    "addr:housenumber":"319",
    "addr:postcode":"43543",
    "addr:street":"W Main St",
    "iso:country":"US",
    "sg:address":"319 W Main St",
    "sg:city":"Montpelier",
    "sg:classifiers":[
        {
            "category":"Manufacturing",
            "subcategory":"Printing",
            "type":"Manufacturing & Wholesale Goods"
        }
    ],
    "sg:phone":"+1 419 485 3113",
    "sg:postcode":"43543",
    "sg:province":"OH",
    "sg:tags":[
        "newspaper"
    ],
    "wof:name":"Leader Enterprise",
    "wof:placetype":"venue"
},
  "geometry": {"coordinates":[-84.61051999999999,41.586538],"type":"Point"}
}