{
  "type": "Feature",
  "properties": {
    "addr:full":"10584 New Biddinger Rd Harrison OH 45030",
    "addr:housenumber":"10584",
    "addr:postcode":"45030",
    "addr:street":"New Biddinger Rd",
    "iso:country":"US",
    "sg:address":"10584 New Biddinger Rd",
    "sg:city":"Harrison",
    "sg:classifiers":[
        {
            "category":"Building & Trades",
            "subcategory":"Construction",
            "type":"Services"
        }
    ],
    "sg:phone":"+1 513 367 2923",
    "sg:postcode":"45030",
    "sg:province":"OH",
    "sg:tags":[
        "house"
    ],
    "wof:name":"TT Const",
    "wof:placetype":"venue"
},
  "geometry": {"coordinates":[-84.804276,39.274665],"type":"Point"}
}