{
  "type": "Feature",
  "properties": {
    "addr:full": "16370 Wenger Rd Anna OH 45302",
    "addr:postcode": "16370;45302",
    "addr:street": "Wenger Rd",
    "iso:country": "US",
    "sg:address": "16370 Wenger Rd",
    "sg:city": "Anna",
    "sg:classifiers": [
      {
        "category": "Building \u0026 Trades",
        "subcategory": "Construction",
        "type": "Services"
      }
    ],
    "sg:phone": "+1 937 693 2224",
    "sg:postcode": "45302",
    "sg:province": "OH",
    "sg:tags": [
      "carpentry",
      "contractor"
    ],
    "wof:name": "Trimworks",
    "wof:placetype": "venue"
  },
  "geometry": {"coordinates":[-84.201926,40.428196],"type":"Point"}
}
