{
  "type": "Feature",
  "properties": {
    "iso:country":"US",
    "sg:address":"218 E Smith Rd",
    "sg:city":"Medina",
    "sg:classifiers":[
        {
            "category":"Wholesale",
            "subcategory":"Machinery & Supplies",
            "type":"Manufacturing & Wholesale Goods"
        }
    ],
    "sg:phone":"+1 330 721 7985",
    "sg:postcode":"44256",
    "sg:province":"OH",
    "sg:tags":[
        "industrial"
    ],
    "wof:name":"B Snyder Abrasives",
    "wof:placetype":"venue"
},
  "geometry": {"coordinates":[-81.862326,41.136181],"type":"Point"}
}