{
  "type": "Feature",
  "properties": {
    "addr:full": "4176 W 145th St Cleveland OH 44135",
    "addr:housenumber": "4176",
    "addr:postcode": "44135",
    "addr:street": "W 145Th St",
    "iso:country": "US",
    "sg:address": "4176 W 145th St",
    "sg:city": "Cleveland",
    "sg:classifiers": [
      {
        "category": "Building \u0026 Trades",
        "subcategory": "Construction",
        "type": "Services"
      }
    ],
    "sg:phone": "+1 440 891 1752",
    "sg:postcode": "44135",
    "sg:province": "OH",
    "sg:tags": [
      "contractor"
    ],
    "wof:name": "McCrae Inc",
    "wof:placetype": "venue"
  },
  "geometry": {"coordinates":[-81.796111,41.440727],"type":"Point"}
}
