{
  "type": "Feature",
  "properties": {
    "addr:full":"9443 Lakewood Dr NE Mineral City OH 44656",
    "addr:housenumber":"9443",
    "addr:postcode":"44656",
    "addr:street":"Lakewood Dr Ne",
    "iso:country":"US",
    "sg:address":"9443 Lakewood Dr NE",
    "sg:city":"Mineral City",
    "sg:classifiers":[
        {
            "category":"Professional",
            "subcategory":"Management & Consulting",
            "type":"Services"
        }
    ],
    "sg:phone":"+1 330 343 5608",
    "sg:postcode":"44656",
    "sg:province":"OH",
    "wof:name":"Entrepreneur Inc",
    "wof:placetype":"venue"
},
  "geometry": {"coordinates":[-81.27019199999999,40.523307],"type":"Point"}
}