{
  "type": "Feature",
  "properties": {
    "addr:full":"12982 Emerson Ave Cleveland OH 44107",
    "addr:housenumber":"12982",
    "addr:postcode":"44107",
    "addr:street":"Emerson Ave",
    "iso:country":"US",
    "sg:address":"12982 Emerson Ave",
    "sg:city":"Cleveland",
    "sg:classifiers":[
        {
            "category":"Building & Trades",
            "subcategory":"Landscaping Services",
            "type":"Services"
        }
    ],
    "sg:phone":"+1 216 228 8862",
    "sg:postcode":"44107",
    "sg:province":"OH",
    "sg:tags":[
        "landscape",
        "contractor"
    ],
    "wof:name":"Shelman Yardworks",
    "wof:placetype":"venue"
},
  "geometry": {"coordinates":[-81.782498,41.489441],"type":"Point"}
}