{
  "type": "Feature",
  "properties": {
    "addr:full": "28914 Lake Shore Blvd Willowick OH 44095",
    "addr:housenumber": "28914",
    "addr:postcode": "44095",
    "addr:street": "Lake Shore Blvd",
    "iso:country": "US",
    "sg:address": "28914 Lake Shore Blvd",
    "sg:city": "Willowick",
    "sg:classifiers": [
      {
        "category": "Wholesale",
        "subcategory": "Machinery \u0026 Supplies",
        "type": "Manufacturing \u0026 Wholesale Goods"
      }
    ],
    "sg:phone": "+1 440 943 5515",
    "sg:postcode": "44095",
    "sg:province": "OH",
    "sg:tags": [
      "cleaners",
      "vacuum"
    ],
    "wof:name": "Miehle Authorized Sales \u0026 Svc",
    "wof:placetype": "venue"
  },
  "geometry": {"coordinates":[-81.483143,41.629835],"type":"Point"}
}
