{
  "type": "Feature",
  "properties": {
    "addr:full": "1920 Indian Wood Cir Maumee OH 43537",
    "addr:housenumber": "1920",
    "addr:postcode": "43537",
    "addr:street": "Indian Wood Cir",
    "iso:country": "US",
    "sg:address": "1920 Indian Wood Cir",
    "sg:city": "Maumee",
    "sg:classifiers": [
      {
        "category": "Organizations",
        "subcategory": "Membership Organization",
        "type": "Services"
      }
    ],
    "sg:phone": "+1 419 891 0705",
    "sg:postcode": "43537",
    "sg:province": "OH",
    "sg:tags": [
      "veterinary"
    ],
    "wof:name": "Toledo Area Humane Society",
    "wof:placetype": "venue"
  },
  "geometry": {"coordinates":[-83.678652,41.584213],"type":"Point"}
}
