{
  "type": "Feature",
  "properties": {
    "addr:full": "5830 National Rd Zanesville OH 43701",
    "addr:housenumber": "5830",
    "addr:postcode": "43701",
    "addr:street": "National Rd",
    "iso:country": "US",
    "sg:address": "5830 National Rd",
    "sg:city": "Zanesville",
    "sg:classifiers": [
      {
        "category": "Shopping",
        "subcategory": "Pharmacy",
        "type": "Retail Goods"
      }
    ],
    "sg:phone": "+1 740 452 9008",
    "sg:postcode": "43701",
    "sg:province": "OH",
    "sg:tags": [
      "aid",
      "first",
      "supply"
    ],
    "wof:name": "T \u0026 T First Aid",
    "wof:placetype": "venue"
  },
  "geometry": {"coordinates":[-82.101536,39.952048],"type":"Point"}
}
