{
  "type": "Feature",
  "properties": {
    "addr:full": "2015 Penn Pl NE Canton OH 44704",
    "addr:housenumber": "2015",
    "addr:postcode": "44704",
    "addr:street": "Penn Pl Ne",
    "iso:country": "US",
    "sg:address": "2015 Penn Pl NE",
    "sg:city": "Canton",
    "sg:classifiers": [
      {
        "category": "Freight",
        "type": "Transportation"
      }
    ],
    "sg:phone": "+1 330 452 0227",
    "sg:postcode": "44704",
    "sg:province": "OH",
    "wof:name": "Thompson Transport",
    "wof:placetype": "venue"
  },
  "geometry": {"coordinates":[-81.349026,40.800194],"type":"Point"}
}
