{
  "type": "Feature",
  "properties": {
    "iso:country":"US",
    "sg:address":"2015 Penn Pl NE",
    "sg:city":"Canton",
    "sg:classifiers":[
        {
            "category":"Freight",
            "type":"Transportation"
        }
    ],
    "sg:phone":"+1 330 452 0227",
    "sg:postcode":"44704",
    "sg:province":"OH",
    "wof:name":"Thompson Transport",
    "wof:placetype":"venue"
},
  "geometry": {"coordinates":[-81.34902599999999,40.800194],"type":"Point"}
}