{
  "type": "Feature",
  "properties": {
    "addr:full": "1150 Morse Rd Columbus OH 43229",
    "addr:housenumber": "1150",
    "addr:postcode": "43229",
    "addr:street": "Morse Rd",
    "iso:country": "US",
    "sg:address": "1150 Morse Rd",
    "sg:city": "Columbus",
    "sg:classifiers": [
      {
        "category": "Sports \u0026 Exercise",
        "subcategory": "Bowling",
        "type": "Entertainment"
      }
    ],
    "sg:phone": "+1 614 840 9955",
    "sg:postcode": "43229",
    "sg:province": "OH",
    "wof:name": "Charlie Allen",
    "wof:placetype": "venue"
  },
  "geometry": {"coordinates":[-82.988264,40.061508],"type":"Point"}
}
