{
  "type": "Feature",
  "properties": {
    "iso:country":"US",
    "sg:address":"1150 Morse Rd",
    "sg:city":"Columbus",
    "sg:classifiers":[
        {
            "category":"Sports & Exercise",
            "subcategory":"Bowling",
            "type":"Entertainment"
        }
    ],
    "sg:phone":"+1 614 840 9955",
    "sg:postcode":"43229",
    "sg:province":"OH",
    "wof:name":"Charlie Allen",
    "wof:placetype":"venue"
},
  "geometry": {"coordinates":[-82.988264,40.061508],"type":"Point"}
}