{
  "type": "Feature",
  "properties": {
    "addr:full": "5151 Reed Rd Columbus OH 43220",
    "addr:housenumber": "5151",
    "addr:postcode": "43220",
    "addr:street": "Reed Rd",
    "iso:country": "US",
    "sg:address": "5151 Reed Rd",
    "sg:city": "Columbus",
    "sg:classifiers": [
      {
        "category": "Professional",
        "type": "Services"
      },
      {
        "category": "Professional",
        "subcategory": "Accounting \u0026 Tax Preparation",
        "type": "Services"
      }
    ],
    "sg:phone": "+1 614 273 0889",
    "sg:postcode": "43220",
    "sg:province": "OH",
    "sg:tags": [
      "bookkeeping",
      "general"
    ],
    "wof:name": "Doug Miller Cma",
    "wof:placetype": "venue"
  },
  "geometry": {"coordinates":[-83.06662,40.063745],"type":"Point"}
}
