{
  "type": "Feature",
  "properties": {
    "iso:country":"US",
    "sg:address":"1955 Newark Granville Rd",
    "sg:city":"Granville",
    "sg:classifiers":[
        {
            "category":"Health Services",
            "subcategory":"Clinic",
            "type":"Services"
        }
    ],
    "sg:phone":"+1 740 587 7440",
    "sg:postcode":"43023",
    "sg:province":"OH",
    "wof:name":"Wendt Bristol Diagnostic",
    "wof:placetype":"venue"
},
  "geometry": {"coordinates":[-82.48831800000001,40.062116],"type":"Point"}
}