{
  "type": "Feature",
  "properties": {
    "iso:country":"US",
    "sg:address":"1611 Plymouth Ridge Rd",
    "sg:city":"Ashtabula",
    "sg:classifiers":[
        {
            "category":"Retail",
            "subcategory":"Auto Repair",
            "type":"Services"
        }
    ],
    "sg:phone":"+1 440 998 1968",
    "sg:postcode":"44004",
    "sg:province":"OH",
    "sg:tags":[
        "automobile",
        "restoration",
        "classic"
    ],
    "wof:name":"Micky Hale Restoration",
    "wof:placetype":"venue"
},
  "geometry": {"coordinates":[-80.73148999999999,41.855392],"type":"Point"}
}