{
  "type": "Feature",
  "properties": {
    "addr:full":"1258 E Central Ave Miamisburg OH 45342",
    "addr:housenumber":"1258",
    "addr:postcode":"45342",
    "addr:street":"E Central Ave",
    "iso:country":"US",
    "sg:address":"1258 E Central Ave",
    "sg:city":"Miamisburg",
    "sg:classifiers":[
        {
            "category":"Shopping",
            "subcategory":"Used Merchandise",
            "type":"Retail Goods"
        }
    ],
    "sg:phone":"+1 937 866 9340",
    "sg:postcode":"45342",
    "sg:province":"OH",
    "sg:tags":[
        "shop",
        "thrift"
    ],
    "wof:name":"Goodwill Industries",
    "wof:placetype":"venue"
},
  "geometry": {"coordinates":[-84.264894,39.63997],"type":"Point"}
}