{
  "type": "Feature",
  "properties": {
    "iso:country":"US",
    "sg:address":"30330 Euclid Ave",
    "sg:city":"Wickliffe",
    "sg:classifiers":[
        {
            "category":"Restaurant",
            "type":"Food & Drink"
        }
    ],
    "sg:phone":"+1 440 943 2935",
    "sg:postcode":"44092",
    "sg:province":"OH",
    "sg:tags":[
        "eating"
    ],
    "wof:name":"Anna Lynn",
    "wof:placetype":"venue"
},
  "geometry": {"coordinates":[-81.458733,41.617631],"type":"Point"}
}