{
  "type": "Feature",
  "properties": {
    "iso:country":"US",
    "sg:address":"3645 Warrensville Center Rd",
    "sg:city":"Cleveland",
    "sg:classifiers":[
        {
            "category":"Social Services",
            "subcategory":"Adult Care",
            "type":"Services"
        }
    ],
    "sg:phone":"+1 216 295 7239",
    "sg:postcode":"44122",
    "sg:province":"OH",
    "sg:tags":[
        "foster"
    ],
    "wof:name":"Specialized Alternative-Family",
    "wof:placetype":"venue"
},
  "geometry": {"coordinates":[-81.535596,41.458352],"type":"Point"}
}