{
  "type": "Feature",
  "properties": {
    "addr:full":"1215 Marseilles-Galion Rd E Marion OH 43302",
    "addr:housenumber":"1215",
    "addr:postcode":"43302",
    "addr:street":"Marseilles-Galion Rd E",
    "iso:country":"US",
    "sg:address":"1215 Marseilles-Galion Rd E",
    "sg:city":"Marion",
    "sg:classifiers":[
        {
            "category":"Real Estate",
            "subcategory":"Real Estate Operator",
            "type":"Services"
        }
    ],
    "sg:phone":"+1 740 383 1479",
    "sg:postcode":"43302",
    "sg:province":"OH",
    "sg:tags":[
        "building",
        "nonresidential"
    ],
    "wof:name":"Marion County Fish & Game Inc",
    "wof:placetype":"venue"
},
  "geometry": {"coordinates":[-83.106623,40.673775],"type":"Point"}
}