{
  "type": "Feature",
  "properties": {
    "addr:full": "2621 Dryden Rd Dayton OH 45439",
    "addr:housenumber": "2621",
    "addr:postcode": "45439",
    "addr:street": "Dryden Rd",
    "iso:country": "US",
    "sg:address": "2621 Dryden Rd",
    "sg:city": "Dayton",
    "sg:classifiers": [
      {
        "category": "Building \u0026 Trades",
        "subcategory": "Construction",
        "type": "Services"
      }
    ],
    "sg:phone": "+1 937 294 1201",
    "sg:postcode": "45439",
    "sg:province": "OH",
    "sg:tags": [
      "house"
    ],
    "wof:name": "Messer Construction Co",
    "wof:placetype": "venue"
  },
  "geometry": {"coordinates":[-84.219249,39.7161],"type":"Point"}
}
