{
  "type": "Feature",
  "properties": {
    "addr:full": "281 E Main St Jackson OH 45640",
    "addr:housenumber": "281",
    "addr:postcode": "45640",
    "addr:street": "E Main St",
    "iso:country": "US",
    "sg:address": "281 E Main St",
    "sg:city": "Jackson",
    "sg:classifiers": [
      {
        "category": "Professional",
        "subcategory": "Management \u0026 Consulting",
        "type": "Services"
      }
    ],
    "sg:phone": "+1 740 288 1089",
    "sg:postcode": "45640",
    "sg:province": "OH",
    "wof:name": "Clever Invstgations Securities",
    "wof:placetype": "venue"
  },
  "geometry": {"coordinates":[-82.631527,39.047038],"type":"Point"}
}
