{
  "type": "Feature",
  "properties": {
    "iso:country":"US",
    "sg:address":"281 E Main St",
    "sg:city":"Jackson",
    "sg:classifiers":[
        {
            "category":"Professional",
            "subcategory":"Management & Consulting",
            "type":"Services"
        }
    ],
    "sg:phone":"+1 740 288 1089",
    "sg:postcode":"45640",
    "sg:province":"OH",
    "wof:name":"Clever Invstgations Securities",
    "wof:placetype":"venue"
},
  "geometry": {"coordinates":[-82.63152700000001,39.047038],"type":"Point"}
}