{
  "type": "Feature",
  "properties": {
    "addr:full":"9200 Miles Ave Cleveland OH 44105",
    "addr:housenumber":"9200",
    "addr:postcode":"44105",
    "addr:street":"Miles Ave",
    "iso:country":"US",
    "sg:address":"9200 Miles Ave",
    "sg:city":"Cleveland",
    "sg:classifiers":[
        {
            "category":"Organizations",
            "subcategory":"Religious Organization",
            "type":"Services"
        }
    ],
    "sg:phone":"+1 216 883 5254",
    "sg:postcode":"44105",
    "sg:province":"OH",
    "sg:tags":[
        "church"
    ],
    "wof:name":"Triumph Church",
    "wof:placetype":"venue"
},
  "geometry": {"coordinates":[-81.62224999999999,41.445067],"type":"Point"}
}