{
  "type": "Feature",
  "properties": {
    "iso:country":"US",
    "sg:address":"8000 Plaza Blvd",
    "sg:city":"Mentor",
    "sg:classifiers":[
        {
            "category":"Shopping",
            "subcategory":"Clothing, Apparel, & Fashions",
            "type":"Retail Goods"
        }
    ],
    "sg:phone":"+1 440 255 7000",
    "sg:postcode":"44060",
    "sg:province":"OH",
    "wof:name":"Catherines",
    "wof:placetype":"venue"
},
  "geometry": {"coordinates":[-81.36476500000001,41.657921],"type":"Point"}
}