{
  "type": "Feature",
  "properties": {
    "addr:full":"11939 Rausch Rd Marysville OH 43040",
    "addr:housenumber":"11939",
    "addr:postcode":"43040",
    "addr:street":"Rausch Rd",
    "iso:country":"US",
    "sg:address":"11939 Rausch Rd",
    "sg:city":"Marysville",
    "sg:classifiers":[
        {
            "category":"Freight",
            "type":"Transportation"
        }
    ],
    "sg:phone":"+1 937 642 3262",
    "sg:postcode":"43040",
    "sg:province":"OH",
    "sg:tags":[
        "operator",
        "local",
        "trucking"
    ],
    "wof:name":"W S Trucking",
    "wof:placetype":"venue"
},
  "geometry": {"coordinates":[-83.370439,40.170692],"type":"Point"}
}