{
  "type": "Feature",
  "properties": {
    "addr:full":"897 Wooster Rd W Barberton OH 44203",
    "addr:housenumber":"897",
    "addr:postcode":"44203",
    "addr:street":"Wooster Rd W",
    "iso:country":"US",
    "sg:address":"897 Wooster Rd W",
    "sg:city":"Barberton",
    "sg:classifiers":[
        {
            "category":"Bars & Pubs",
            "type":"Food & Drink"
        }
    ],
    "sg:phone":"+1 330 825 6073",
    "sg:postcode":"44203",
    "sg:province":"OH",
    "sg:tags":[
        "drinking",
        "eating"
    ],
    "wof:name":"Hodge's Cafe",
    "wof:placetype":"venue"
},
  "geometry": {"coordinates":[-81.623127,41.010822],"type":"Point"}
}