{
  "type": "Feature",
  "properties": {
    "iso:country":"US",
    "sg:address":"367 E Blagrove St",
    "sg:city":"Richwood",
    "sg:classifiers":[
        {
            "category":"Wholesale",
            "subcategory":"Farm Supplies",
            "type":"Manufacturing & Wholesale Goods"
        },
        {
            "category":"Wholesale",
            "subcategory":"Non-durable Goods",
            "type":"Manufacturing & Wholesale Goods"
        }
    ],
    "sg:phone":"+1 740 943 2335",
    "sg:postcode":"43344",
    "sg:province":"OH",
    "sg:tags":[
        "shop",
        "beef",
        "crop",
        "general",
        "cattle",
        "blacksmith"
    ],
    "wof:name":"Ken Davis & Sons Inc",
    "wof:placetype":"venue"
},
  "geometry": {"coordinates":[-83.284398,40.430333],"type":"Point"}
}