{
  "type": "Feature",
  "properties": {
    "addr:full": "367 E Blagrove St Richwood OH 43344",
    "addr:housenumber": "367",
    "addr:postcode": "43344",
    "addr:street": "E Blagrove St",
    "iso:country": "US",
    "sg:address": "367 E Blagrove St",
    "sg:city": "Richwood",
    "sg:classifiers": [
      {
        "category": "Wholesale",
        "subcategory": "Farm Supplies",
        "type": "Manufacturing \u0026 Wholesale Goods"
      },
      {
        "category": "Wholesale",
        "subcategory": "Non-durable Goods",
        "type": "Manufacturing \u0026 Wholesale Goods"
      }
    ],
    "sg:phone": "+1 740 943 2335",
    "sg:postcode": "43344",
    "sg:province": "OH",
    "sg:tags": [
      "shop",
      "beef",
      "crop",
      "general",
      "cattle",
      "blacksmith"
    ],
    "wof:name": "Ken Davis \u0026 Sons Inc",
    "wof:placetype": "venue"
  },
  "geometry": {"coordinates":[-83.284398,40.430333],"type":"Point"}
}
