{
  "type": "Feature",
  "properties": {
    "addr:full":"1230 Durbin Ter Maineville OH 45039",
    "addr:housenumber":"1230",
    "addr:postcode":"45039",
    "addr:street":"Durbin Ter",
    "iso:country":"US",
    "sg:address":"1230 Durbin Ter",
    "sg:city":"Maineville",
    "sg:classifiers":[
        {
            "category":"Building & Trades",
            "subcategory":"Construction",
            "type":"Services"
        }
    ],
    "sg:phone":"+1 513 683 2419",
    "sg:postcode":"45039",
    "sg:province":"OH",
    "sg:tags":[
        "house"
    ],
    "wof:name":"Atlantic Homes Inc",
    "wof:placetype":"venue"
},
  "geometry": {"coordinates":[-84.24250000000001,39.306333],"type":"Point"}
}