{
  "type": "Feature",
  "properties": {
    "iso:country":"US",
    "sg:address":"1208 Meadow Knoll Ct",
    "sg:city":"Batavia",
    "sg:classifiers":[
        {
            "category":"Farming",
            "subcategory":"Farm",
            "type":"Manufacturing & Wholesale Goods"
        }
    ],
    "sg:phone":"+1 513 753 3393",
    "sg:postcode":"45103",
    "sg:province":"OH",
    "sg:tags":[
        "crop",
        "general"
    ],
    "wof:name":"Bohl John",
    "wof:placetype":"venue"
},
  "geometry": {"coordinates":[-84.243138,39.080111],"type":"Point"}
}