{
  "type": "Feature",
  "properties": {
    "iso:country":"US",
    "sg:address":"9107 Ohio River Rd",
    "sg:city":"Wheelersburg",
    "sg:classifiers":[
        {
            "category":"Professional",
            "type":"Services"
        }
    ],
    "sg:phone":"+1 740 574 9119",
    "sg:postcode":"45694",
    "sg:province":"OH",
    "wof:name":"Xact",
    "wof:placetype":"venue"
},
  "geometry": {"coordinates":[-82.856086,38.713561],"type":"Point"}
}