{
  "type": "Feature",
  "properties": {
    "iso:country":"US",
    "sg:address":"4600 Midpine Ave",
    "sg:city":"Louisville",
    "sg:classifiers":[
        {
            "category":"Professional",
            "subcategory":"Secretarial Services",
            "type":"Services"
        }
    ],
    "sg:phone":"+1 330 332 3376",
    "sg:postcode":"44641",
    "sg:province":"OH",
    "sg:tags":[
        "convention",
        "court",
        "reporter"
    ],
    "wof:name":"Independent Reporting Svc",
    "wof:placetype":"venue"
},
  "geometry": {"coordinates":[-81.22996500000001,40.837839],"type":"Point"}
}