{
  "type": "Feature",
  "properties": {
    "addr:full": "15180 Bagley Rd Cleveland OH 44130",
    "addr:housenumber": "15180",
    "addr:postcode": "44130",
    "addr:street": "Bagley Rd",
    "iso:country": "US",
    "sg:address": "15180 Bagley Rd",
    "sg:city": "Cleveland",
    "sg:classifiers": [
      {
        "category": "Restaurant",
        "type": "Food \u0026 Drink"
      }
    ],
    "sg:phone": "+1 440 884 5100",
    "sg:postcode": "44130",
    "sg:province": "OH",
    "sg:tags": [
      "drinking",
      "eating",
      "pizza"
    ],
    "wof:name": "Jerome's Pizza",
    "wof:placetype": "venue"
  },
  "geometry": {"coordinates":[-81.806656,41.36991],"type":"Point"}
}
