{
  "type": "Feature",
  "properties": {
    "addr:full": "26 N Sandusky St Delaware OH 43015",
    "addr:housenumber": "26",
    "addr:postcode": "43015",
    "addr:street": "N Sandusky St",
    "iso:country": "US",
    "sg:address": "26 N Sandusky St",
    "sg:city": "Delaware",
    "sg:classifiers": [
      {
        "category": "Restaurant",
        "type": "Food \u0026 Drink"
      }
    ],
    "sg:phone": "+1 740 362 5910",
    "sg:postcode": "43015",
    "sg:province": "OH",
    "sg:tags": [
      "eating"
    ],
    "wof:name": "Alachboco Restaurant",
    "wof:placetype": "venue"
  },
  "geometry": {"coordinates":[-83.067638,40.299253],"type":"Point"}
}
