{
  "type": "Feature",
  "properties": {
    "addr:full": "2300 Navarre Ave Oregon OH 43616",
    "addr:housenumber": "2300",
    "addr:postcode": "43616",
    "addr:street": "Navarre Ave",
    "iso:country": "US",
    "sg:address": "2300 Navarre Ave",
    "sg:city": "Oregon",
    "sg:classifiers": [
      {
        "category": "Banks \u0026 Credit Unions",
        "subcategory": "Bank",
        "type": "Services"
      }
    ],
    "sg:phone": "+1 419 693 3400",
    "sg:postcode": "43616",
    "sg:province": "OH",
    "sg:tags": [
      "loan",
      "broker"
    ],
    "wof:name": "Sunset Mortgage",
    "wof:placetype": "venue"
  },
  "geometry": {"coordinates":[-83.492238,41.636596],"type":"Point"}
}
