{
  "type": "Feature",
  "properties": {
    "addr:full":"1030 Delta Ave Cincinnati OH 45208",
    "addr:housenumber":"1030",
    "addr:postcode":"45208",
    "addr:street":"Delta Ave",
    "iso:country":"US",
    "sg:address":"1030 Delta Ave",
    "sg:city":"Cincinnati",
    "sg:classifiers":[
        {
            "category":"Shopping",
            "subcategory":"Clothing, Apparel, & Fashions",
            "type":"Retail Goods"
        }
    ],
    "sg:phone":"+1 513 321 7525",
    "sg:postcode":"45208",
    "sg:province":"OH",
    "sg:tags":[
        "costume"
    ],
    "wof:name":"Second Hand Rose",
    "wof:placetype":"venue"
},
  "geometry": {"coordinates":[-84.42970800000001,39.129681],"type":"Point"}
}