{
  "type": "Feature",
  "properties": {
    "addr:full": "2950 Sferra Ave NW Warren OH 44483",
    "addr:housenumber": "2950",
    "addr:postcode": "44483",
    "addr:street": "Sferra Ave Nw",
    "iso:country": "US",
    "sg:address": "2950 Sferra Ave NW",
    "sg:city": "Warren",
    "sg:classifiers": [
      {
        "category": "Professional",
        "subcategory": "Accounting \u0026 Tax Preparation",
        "type": "Services"
      }
    ],
    "sg:phone": "+1 330 394 5005",
    "sg:postcode": "44483",
    "sg:province": "OH",
    "sg:tags": [
      "accountant"
    ],
    "wof:name": "V George Burson CPA",
    "wof:placetype": "venue"
  },
  "geometry": {"coordinates":[-80.823991,41.265422],"type":"Point"}
}
