{
  "type": "Feature",
  "properties": {
    "iso:country":"US",
    "sg:address":"2950 Sferra Ave NW",
    "sg:city":"Warren",
    "sg:classifiers":[
        {
            "category":"Professional",
            "subcategory":"Accounting & Tax Preparation",
            "type":"Services"
        }
    ],
    "sg:phone":"+1 330 394 5005",
    "sg:postcode":"44483",
    "sg:province":"OH",
    "sg:tags":[
        "accountant"
    ],
    "wof:name":"V George Burson CPA",
    "wof:placetype":"venue"
},
  "geometry": {"coordinates":[-80.82399100000001,41.265422],"type":"Point"}
}