{
  "type": "Feature",
  "properties": {
    "addr:full": "9243 Old Stage Rd Waynesville OH 45068",
    "addr:housenumber": "9243",
    "addr:postcode": "45068",
    "addr:street": "Old Stage Rd",
    "iso:country": "US",
    "sg:address": "9243 Old Stage Rd",
    "sg:city": "Waynesville",
    "sg:classifiers": [
      {
        "category": "Shopping",
        "type": "Retail Goods"
      }
    ],
    "sg:phone": "+1 937 862 4543",
    "sg:postcode": "45068",
    "sg:province": "OH",
    "sg:tags": [
      "plant",
      "flower",
      "tree",
      "artificial"
    ],
    "wof:name": "Rose Of Sharon Enterprises",
    "wof:placetype": "venue"
  },
  "geometry": {"coordinates":[-84.058736,39.565276],"type":"Point"}
}
