{
  "type": "Feature",
  "properties": {
    "addr:full":"9321 Seward Rd Fairfield OH 45014",
    "addr:housenumber":"9321",
    "addr:postcode":"45014",
    "addr:street":"Seward Rd",
    "iso:country":"US",
    "sg:address":"9321 Seward Rd",
    "sg:city":"Fairfield",
    "sg:classifiers":[
        {
            "category":"Retail",
            "subcategory":"Auto Repair",
            "type":"Services"
        }
    ],
    "sg:phone":"+1 513 738 5666",
    "sg:postcode":"45014",
    "sg:province":"OH",
    "sg:tags":[
        "repairing",
        "automobile"
    ],
    "wof:name":"Sheppard's Service",
    "wof:placetype":"venue"
},
  "geometry": {"coordinates":[-84.493297,39.325218],"type":"Point"}
}