{
  "type": "Feature",
  "properties": {
    "addr:full":"5956 W Central Ave Toledo OH 43615",
    "addr:housenumber":"5956",
    "addr:postcode":"43615",
    "addr:street":"W Central Ave",
    "iso:country":"US",
    "sg:address":"5956 W Central Ave",
    "sg:city":"Toledo",
    "sg:classifiers":[
        {
            "category":"Food & Beverages",
            "subcategory":"Groceries & Convenience Stores",
            "type":"Retail Goods"
        }
    ],
    "sg:phone":"+1 419 841 2861",
    "sg:postcode":"43615",
    "sg:province":"OH",
    "wof:name":"Centre Supermarkets Inc",
    "wof:placetype":"venue"
},
  "geometry": {"coordinates":[-83.684129,41.676317],"type":"Point"}
}