{
  "type": "Feature",
  "properties": {
    "addr:full": "612 2nd St Portsmouth OH 45662",
    "addr:housenumber": "612",
    "addr:postcode": "45662",
    "addr:street": "2Nd St",
    "iso:country": "US",
    "sg:address": "612 2nd St",
    "sg:city": "Portsmouth",
    "sg:classifiers": [
      {
        "category": "Organizations",
        "subcategory": "Religious Organization",
        "type": "Services"
      }
    ],
    "sg:phone": "+1 740 353 8558",
    "sg:postcode": "45662",
    "sg:province": "OH",
    "sg:tags": [
      "church"
    ],
    "wof:name": "House Of God Inc",
    "wof:placetype": "venue"
  },
  "geometry": {"coordinates":[-83.000615,38.73151],"type":"Point"}
}
