{
  "type": "Feature",
  "properties": {
    "iso:country":"US",
    "sg:address":"523 J St",
    "sg:city":"Perrysburg",
    "sg:classifiers":[
        {
            "category":"Manufacturing",
            "subcategory":"Printing",
            "type":"Manufacturing & Wholesale Goods"
        }
    ],
    "sg:phone":"+1 419 666 8250",
    "sg:postcode":"43551",
    "sg:province":"OH",
    "sg:tags":[
        "commercial",
        "lithographic"
    ],
    "wof:name":"Moore Business Solutions",
    "wof:placetype":"venue"
},
  "geometry": {"coordinates":[-83.553431,41.578332],"type":"Point"}
}