{
  "type": "Feature",
  "properties": {
    "addr:full": "523 J St Perrysburg OH 43551",
    "addr:housenumber": "523",
    "addr:postcode": "43551",
    "addr:street": "J St",
    "iso:country": "US",
    "sg:address": "523 J St",
    "sg:city": "Perrysburg",
    "sg:classifiers": [
      {
        "category": "Manufacturing",
        "subcategory": "Printing",
        "type": "Manufacturing \u0026 Wholesale Goods"
      }
    ],
    "sg:phone": "+1 419 666 8250",
    "sg:postcode": "43551",
    "sg:province": "OH",
    "sg:tags": [
      "commercial",
      "lithographic"
    ],
    "wof:name": "Moore Business Solutions",
    "wof:placetype": "venue"
  },
  "geometry": {"coordinates":[-83.553431,41.578332],"type":"Point"}
}
