{
  "type": "Feature",
  "properties": {
    "iso:country":"US",
    "sg:address":"8324 Seward Rd",
    "sg:city":"Fairfield",
    "sg:classifiers":[
        {
            "category":"Retail",
            "subcategory":"Auto Repair",
            "type":"Services"
        }
    ],
    "sg:phone":"+1 513 860 4080",
    "sg:postcode":"45011",
    "sg:province":"OH",
    "sg:tags":[
        "truck"
    ],
    "wof:name":"J B Diesel Svc",
    "wof:placetype":"venue"
},
  "geometry": {"coordinates":[-84.491148,39.348926],"type":"Point"}
}