{
  "type": "Feature",
  "properties": {
    "iso:country":"US",
    "sg:address":"157 W Cedar St",
    "sg:city":"Akron",
    "sg:classifiers":[
        {
            "category":"Health Services",
            "subcategory":"Doctor",
            "type":"Services"
        }
    ],
    "sg:phone":"+1 330 762 5046",
    "sg:postcode":"44307",
    "sg:province":"OH",
    "sg:tags":[
        "medical"
    ],
    "wof:name":"Hazra Dr Sandra V Md Inc",
    "wof:placetype":"venue"
},
  "geometry": {"coordinates":[-81.527976,41.077608],"type":"Point"}
}