{
  "type": "Feature",
  "properties": {
    "addr:full": "4317 West Ave Ashtabula OH 44004",
    "addr:housenumber": "4317",
    "addr:postcode": "44004",
    "addr:street": "West Ave",
    "iso:country": "US",
    "sg:address": "4317 West Ave",
    "sg:city": "Ashtabula",
    "sg:classifiers": [
      {
        "category": "Organizations",
        "subcategory": "Religious Organization",
        "type": "Services"
      }
    ],
    "sg:phone": "+1 440 992 0330",
    "sg:postcode": "44004",
    "sg:province": "OH",
    "sg:tags": [
      "church"
    ],
    "wof:name": "St Joseph Mission-Our Lady Of",
    "wof:placetype": "venue"
  },
  "geometry": {"coordinates":[-80.797574,41.866242],"type":"Point"}
}
