{
  "type": "Feature",
  "properties": {
    "addr:full": "861 North High Street Columbus OH 43201",
    "addr:housenumber": "861",
    "addr:postcode": "43201",
    "addr:street": "North High Street",
    "iso:country": "US",
    "sg:address": "861 North High Street",
    "sg:city": "Columbus",
    "sg:classifiers": [
      {
        "category": "Professional",
        "subcategory": "Computer Services",
        "type": "Services"
      }
    ],
    "sg:phone": "+1 614 580 4648",
    "sg:postcode": "43201",
    "sg:province": "OH",
    "sg:tags": [
      "iphone",
      "android",
      "mobile-applications",
      "healthcare",
      "mobile",
      "columbus",
      "doctors",
      "patients"
    ],
    "sg:website": "http://eproximiti.com/",
    "wof:name": "eproximiti",
    "wof:placetype": "venue"
  },
  "geometry": {"coordinates":[-83.00446,39.981767],"type":"Point"}
}
