{
  "type": "Feature",
  "properties": {
    "addr:full":"128 Cherry Ridge Run Ottawa OH 45875",
    "addr:housenumber":"128",
    "addr:postcode":"45875",
    "addr:street":"Cherry Ridge Run",
    "iso:country":"US",
    "sg:address":"128 Cherry Ridge Run",
    "sg:city":"Ottawa",
    "sg:classifiers":[
        {
            "category":"Building & Trades",
            "subcategory":"Construction",
            "type":"Services"
        }
    ],
    "sg:phone":"+1 419 523 9377",
    "sg:postcode":"45875",
    "sg:province":"OH",
    "sg:tags":[
        "general",
        "contractor"
    ],
    "wof:name":"TAC Construction LTD",
    "wof:placetype":"venue"
},
  "geometry": {"coordinates":[-84.03554800000001,41.042157],"type":"Point"}
}