{
  "type": "Feature",
  "properties": {
    "iso:country":"US",
    "sg:address":"9114 Lake Shore Blvd",
    "sg:city":"Mentor",
    "sg:classifiers":[
        {
            "category":"Organizations",
            "subcategory":"Religious Organization",
            "type":"Services"
        }
    ],
    "sg:phone":"+1 440 257 5544",
    "sg:postcode":"44060",
    "sg:province":"OH",
    "sg:tags":[
        "church"
    ],
    "wof:name":"St Bede The Venerable Church",
    "wof:placetype":"venue"
},
  "geometry": {"coordinates":[-81.312822,41.720431],"type":"Point"}
}