{
  "type": "Feature",
  "properties": {
    "iso:country":"US",
    "sg:address":"9980 Hewins Rd",
    "sg:city":"Garrettsville",
    "sg:classifiers":[
        {
            "category":"Farming",
            "subcategory":"Nursery",
            "type":"Manufacturing & Wholesale Goods"
        }
    ],
    "sg:phone":"+1 330 527 2906",
    "sg:postcode":"44231",
    "sg:province":"OH",
    "sg:tags":[
        "ornamental",
        "greenhouse"
    ],
    "wof:name":"Ruffing's Greenhouse",
    "wof:placetype":"venue"
},
  "geometry": {"coordinates":[-81.098474,41.270083],"type":"Point"}
}