{
  "type": "Feature",
  "properties": {
    "iso:country":"US",
    "sg:address":"3280 Babbs Rd",
    "sg:city":"Nashport",
    "sg:classifiers":[
        {
            "category":"Home & Garden",
            "subcategory":"Carpets & Floor Coverings",
            "type":"Retail Goods"
        }
    ],
    "sg:phone":"+1 740 454 1109",
    "sg:postcode":"43830",
    "sg:province":"OH",
    "sg:tags":[
        "install"
    ],
    "wof:name":"Integrity Flooring",
    "wof:placetype":"venue"
},
  "geometry": {"coordinates":[-82.04591000000001,40.034845],"type":"Point"}
}