{
  "type": "Feature",
  "properties": {
    "addr:full": "3280 Babbs Rd Nashport OH 43830",
    "addr:postcode": "3280;43830",
    "addr:street": "Babbs Rd",
    "iso:country": "US",
    "sg:address": "3280 Babbs Rd",
    "sg:city": "Nashport",
    "sg:classifiers": [
      {
        "category": "Home \u0026 Garden",
        "subcategory": "Carpets \u0026 Floor Coverings",
        "type": "Retail Goods"
      }
    ],
    "sg:phone": "+1 740 454 1109",
    "sg:postcode": "43830",
    "sg:province": "OH",
    "sg:tags": [
      "install"
    ],
    "wof:name": "Integrity Flooring",
    "wof:placetype": "venue"
  },
  "geometry": {"coordinates":[-82.04591,40.034845],"type":"Point"}
}
