{
  "type": "Feature",
  "properties": {
    "addr:full": "26 Cook Dr Attica OH 44807",
    "addr:housenumber": "26",
    "addr:postcode": "44807",
    "addr:street": "Cook Dr",
    "iso:country": "US",
    "sg:address": "26 Cook Dr",
    "sg:city": "Attica",
    "sg:classifiers": [
      {
        "category": "Health Services",
        "subcategory": "Doctor",
        "type": "Services"
      }
    ],
    "sg:phone": "+1 419 426 4892",
    "sg:postcode": "44807",
    "sg:province": "OH",
    "sg:tags": [
      "dentist"
    ],
    "wof:name": "David M Kagy DDS",
    "wof:placetype": "venue"
  },
  "geometry": {"coordinates":[-82.879776,41.061765],"type":"Point"}
}
