{
  "type": "Feature",
  "properties": {
    "iso:country":"US",
    "sg:address":"26 Cook Dr",
    "sg:city":"Attica",
    "sg:classifiers":[
        {
            "category":"Health Services",
            "subcategory":"Doctor",
            "type":"Services"
        }
    ],
    "sg:phone":"+1 419 426 4892",
    "sg:postcode":"44807",
    "sg:province":"OH",
    "sg:tags":[
        "dentist"
    ],
    "wof:name":"David M Kagy DDS",
    "wof:placetype":"venue"
},
  "geometry": {"coordinates":[-82.87977600000001,41.061765],"type":"Point"}
}