{
  "type": "Feature",
  "properties": {
    "iso:country":"US",
    "sg:address":"211 Whipple Ave NW",
    "sg:city":"Canton",
    "sg:classifiers":[
        {
            "category":"Insurance",
            "subcategory":"Insurance Agent",
            "type":"Services"
        }
    ],
    "sg:phone":"+1 330 477 3800",
    "sg:postcode":"44708",
    "sg:province":"OH",
    "wof:name":"Don Motz Insurance",
    "wof:placetype":"venue"
},
  "geometry": {"coordinates":[-81.426155,40.800487],"type":"Point"}
}