{
  "type": "Feature",
  "properties": {
    "addr:full": "921 Rush Ave Bellefontaine OH 43311",
    "addr:housenumber": "921",
    "addr:postcode": "43311",
    "addr:street": "Rush Ave",
    "iso:country": "US",
    "sg:address": "921 Rush Ave",
    "sg:city": "Bellefontaine",
    "sg:classifiers": [
      {
        "category": "Health Services",
        "subcategory": "Doctor",
        "type": "Services"
      }
    ],
    "sg:phone": "+1 937 592 2626",
    "sg:postcode": "43311",
    "sg:province": "OH",
    "sg:tags": [
      "physician",
      "surgeon"
    ],
    "sg:website": "www.goeyesurgeons.com",
    "wof:name": "Greater Ohio Eye Surgeons Inc",
    "wof:placetype": "venue"
  },
  "geometry": {"coordinates":[-83.754413,40.373477],"type":"Point"}
}
