{
  "type": "Feature",
  "properties": {
    "addr:full": "820 Kelly Dr Wapakoneta OH 45895",
    "addr:housenumber": "820",
    "addr:postcode": "45895",
    "addr:street": "Kelly Dr",
    "iso:country": "US",
    "sg:address": "820 Kelly Dr",
    "sg:city": "Wapakoneta",
    "sg:classifiers": [
      {
        "category": "Retail",
        "subcategory": "Animal Services",
        "type": "Services"
      }
    ],
    "sg:phone": "+1 419 738 3666",
    "sg:postcode": "45895",
    "sg:province": "OH",
    "sg:tags": [
      "pet"
    ],
    "wof:name": "Critter Sitter",
    "wof:placetype": "venue"
  },
  "geometry": {"coordinates":[-84.208335,40.571211],"type":"Point"}
}
