{
  "type": "Feature",
  "properties": {
    "iso:country":"US",
    "sg:address":"4778 Glengate Dr",
    "sg:city":"Columbus",
    "sg:classifiers":[
        {
            "category":"Insurance",
            "subcategory":"Insurance Agent",
            "type":"Services"
        }
    ],
    "sg:phone":"+1 614 837 0370",
    "sg:postcode":"43232",
    "sg:province":"OH",
    "wof:name":"Boughner Insurance Services",
    "wof:placetype":"venue"
},
  "geometry": {"coordinates":[-82.87527799999999,39.905194],"type":"Point"}
}