{
  "type": "Feature",
  "properties": {
    "iso:country":"US",
    "sg:address":"2745 Fairlane Dr",
    "sg:city":"Wheelersburg",
    "sg:classifiers":[
        {
            "category":"Organizations",
            "subcategory":"Community Association",
            "type":"Services"
        }
    ],
    "sg:phone":"+1 740 574 2314",
    "sg:postcode":"45694",
    "sg:province":"OH",
    "wof:name":"Kiwanis International Inc",
    "wof:placetype":"venue"
},
  "geometry": {"coordinates":[-82.826031,38.755185],"type":"Point"}
}