{
  "type": "Feature",
  "properties": {
    "addr:full":"1715 Newell St Findlay OH 45840",
    "addr:housenumber":"1715",
    "addr:postcode":"45840",
    "addr:street":"Newell St",
    "iso:country":"US",
    "sg:address":"1715 Newell St",
    "sg:city":"Findlay",
    "sg:classifiers":[
        {
            "category":"Building & Trades",
            "subcategory":"Electrical",
            "type":"Services"
        }
    ],
    "sg:phone":"+1 419 425 0055",
    "sg:postcode":"45840",
    "sg:province":"OH",
    "sg:tags":[
        "electric",
        "contractor"
    ],
    "wof:name":"Flag City Electric",
    "wof:placetype":"venue"
},
  "geometry": {"coordinates":[-83.673086,41.019185],"type":"Point"}
}