{
  "type": "Feature",
  "properties": {
    "addr:full": "7980 State Rte 221 Georgetown OH 45121",
    "addr:housenumber": "7980",
    "addr:postcode": "45121",
    "addr:street": "State Rte 221",
    "iso:country": "US",
    "sg:address": "7980 State Rte 221",
    "sg:city": "Georgetown",
    "sg:classifiers": [
      {
        "category": "Building \u0026 Trades",
        "subcategory": "Construction",
        "type": "Services"
      }
    ],
    "sg:phone": "+1 937 378 6056",
    "sg:postcode": "45121",
    "sg:province": "OH",
    "sg:tags": [
      "contractor"
    ],
    "wof:name": "M \u0026 R Construction",
    "wof:placetype": "venue"
  },
  "geometry": {"coordinates":[-83.924357,38.860994],"type":"Point"}
}
