{
  "type": "Feature",
  "properties": {
    "addr:full":"412 Girard Dr Berea OH 44017",
    "addr:housenumber":"412",
    "addr:postcode":"44017",
    "addr:street":"Girard Dr",
    "iso:country":"US",
    "sg:address":"412 Girard Dr",
    "sg:city":"Berea",
    "sg:classifiers":[
        {
            "category":"Education",
            "subcategory":"Special Training",
            "type":"Public Place"
        }
    ],
    "sg:phone":"+1 440 234 6021",
    "sg:postcode":"44017",
    "sg:province":"OH",
    "sg:tags":[
        "instruction",
        "music"
    ],
    "wof:name":"Constance Mehrling Music Std",
    "wof:placetype":"venue"
},
  "geometry": {"coordinates":[-81.87520600000001,41.359724],"type":"Point"}
}