{
  "type": "Feature",
  "properties": {
    "addr:full":"17604 Coshocton Rd Mount Vernon OH 43050",
    "addr:postcode":"17604;43050",
    "addr:street":"Coshocton Rd",
    "iso:country":"US",
    "sg:address":"17604 Coshocton Rd",
    "sg:city":"Mount Vernon",
    "sg:classifiers":[
        {
            "category":"Utilities",
            "subcategory":"Water",
            "type":"Services"
        }
    ],
    "sg:phone":"+1 740 397 7041",
    "sg:postcode":"43050",
    "sg:province":"OH",
    "sg:tags":[
        "executive",
        "supply"
    ],
    "wof:name":"Knox Cnty Dept Wtr Waste Waste",
    "wof:placetype":"venue"
},
  "geometry": {"coordinates":[-82.43399700000001,40.404542],"type":"Point"}
}