{
  "type": "Feature",
  "properties": {
    "iso:country":"US",
    "sg:address":"195 W Market St",
    "sg:city":"Tiffin",
    "sg:classifiers":[
        {
            "category":"Retail",
            "subcategory":"Auto Repair",
            "type":"Services"
        }
    ],
    "sg:phone":"+1 419 447 2774",
    "sg:postcode":"44883",
    "sg:province":"OH",
    "sg:tags":[
        "automobile",
        "lubrication",
        "automotive"
    ],
    "wof:name":"Pioneer Quick Lubes Inc",
    "wof:placetype":"venue"
},
  "geometry": {"coordinates":[-83.186948,41.11358],"type":"Point"}
}