{
  "type": "Feature",
  "properties": {
    "addr:full": "6219 Quincy Ave Cleveland OH 44104",
    "addr:housenumber": "6219",
    "addr:postcode": "44104",
    "addr:street": "Quincy Ave",
    "iso:country": "US",
    "sg:address": "6219 Quincy Ave",
    "sg:city": "Cleveland",
    "sg:classifiers": [
      {
        "category": "Shopping",
        "subcategory": "Discount \u0026 Variety Stores",
        "type": "Retail Goods"
      }
    ],
    "sg:phone": "+1 216 432 3470",
    "sg:postcode": "44104",
    "sg:province": "OH",
    "sg:tags": [
      "merchandise",
      "general"
    ],
    "wof:name": "Ernestines Store",
    "wof:placetype": "venue"
  },
  "geometry": {"coordinates":[-81.647874,41.493452],"type":"Point"}
}
