{
  "type": "Feature",
  "properties": {
    "iso:country":"US",
    "sg:address":"6219 Quincy Ave",
    "sg:city":"Cleveland",
    "sg:classifiers":[
        {
            "category":"Shopping",
            "subcategory":"Discount & Variety Stores",
            "type":"Retail Goods"
        }
    ],
    "sg:phone":"+1 216 432 3470",
    "sg:postcode":"44104",
    "sg:province":"OH",
    "sg:tags":[
        "merchandise",
        "general"
    ],
    "wof:name":"Ernestines Store",
    "wof:placetype":"venue"
},
  "geometry": {"coordinates":[-81.647874,41.493452],"type":"Point"}
}