{
  "type": "Feature",
  "properties": {
    "iso:country":"US",
    "sg:address":"1751 Keith Dr",
    "sg:city":"Cincinnati",
    "sg:classifiers":[
        {
            "category":"Wholesale",
            "subcategory":"Construction Materials",
            "type":"Manufacturing & Wholesale Goods"
        }
    ],
    "sg:phone":"+1 513 769 3494",
    "sg:postcode":"45215",
    "sg:province":"OH",
    "wof:name":"Concrete Lady",
    "wof:placetype":"venue"
},
  "geometry": {"coordinates":[-84.431797,39.228807],"type":"Point"}
}