{
  "type": "Feature",
  "properties": {
    "addr:full":"8070 Lucas Rd Plain City OH 43064",
    "addr:housenumber":"8070",
    "addr:postcode":"43064",
    "addr:street":"Lucas Rd",
    "iso:country":"US",
    "sg:address":"8070 Lucas Rd",
    "sg:city":"Plain City",
    "sg:classifiers":[
        {
            "category":"Farming",
            "subcategory":"Farm",
            "type":"Manufacturing & Wholesale Goods"
        }
    ],
    "sg:phone":"+1 614 879 9585",
    "sg:postcode":"43064",
    "sg:province":"OH",
    "sg:tags":[
        "crop",
        "general"
    ],
    "wof:name":"Detweiler Farm LLC",
    "wof:placetype":"venue"
},
  "geometry": {"coordinates":[-83.287661,40.014656],"type":"Point"}
}