{
  "type": "Feature",
  "properties": {
    "addr:full": "6184 Linworth Rd Worthington OH 43085",
    "addr:housenumber": "6184",
    "addr:postcode": "43085",
    "addr:street": "Linworth Rd",
    "iso:country": "US",
    "sg:address": "6184 Linworth Rd",
    "sg:city": "Worthington",
    "sg:classifiers": [
      {
        "category": "Health Services",
        "subcategory": "Clinic",
        "type": "Services"
      }
    ],
    "sg:phone": "+1 614 985 1435",
    "sg:postcode": "43085",
    "sg:province": "OH",
    "wof:name": "Elements Of Health",
    "wof:placetype": "venue"
  },
  "geometry": {"coordinates":[-83.049614,40.092609],"type":"Point"}
}
