{
  "type": "Feature",
  "properties": {
    "addr:full":"294 Breezewood Dr Bay Village OH 44140",
    "addr:housenumber":"294",
    "addr:postcode":"44140",
    "addr:street":"Breezewood Dr",
    "iso:country":"US",
    "sg:address":"294 Breezewood Dr",
    "sg:city":"Bay Village",
    "sg:classifiers":[
        {
            "category":"Building & Trades",
            "subcategory":"Construction",
            "type":"Services"
        }
    ],
    "sg:phone":"+1 440 899 9399",
    "sg:postcode":"44140",
    "sg:province":"OH",
    "sg:tags":[
        "hanging",
        "painter",
        "contractor"
    ],
    "wof:name":"Fix-N-Finish",
    "wof:placetype":"venue"
},
  "geometry": {"coordinates":[-81.952412,41.49177],"type":"Point"}
}