{
  "type": "Feature",
  "properties": {
    "addr:full":"2500 Ada Rd Lima OH 45801",
    "addr:housenumber":"2500",
    "addr:postcode":"45801",
    "addr:street":"Ada Rd",
    "iso:country":"US",
    "sg:address":"2500 Ada Rd",
    "sg:city":"Lima",
    "sg:classifiers":[
        {
            "category":"Social Services",
            "type":"Services"
        }
    ],
    "sg:phone":"+1 419 221 1385",
    "sg:postcode":"45801",
    "sg:province":"OH",
    "wof:name":"Allen County Board of Mr/Dd",
    "wof:placetype":"venue"
},
  "geometry": {"coordinates":[-84.054749,40.758756],"type":"Point"}
}