{
  "type": "Feature",
  "properties": {
    "iso:country":"US",
    "sg:address":"3283 Harding Hwy",
    "sg:city":"Lima",
    "sg:classifiers":[
        {
            "category":"Autos & Motor Vehicles",
            "subcategory":"Auto Supplies",
            "type":"Retail Goods"
        }
    ],
    "sg:phone":"+1 419 225 9054",
    "sg:postcode":"45804",
    "sg:province":"OH",
    "sg:tags":[
        "tire"
    ],
    "wof:name":"Allen Tire Service",
    "wof:placetype":"venue"
},
  "geometry": {"coordinates":[-84.044704,40.731077],"type":"Point"}
}