{
  "type": "Feature",
  "properties": {
    "addr:full": "3283 Harding Hwy Lima OH 45804",
    "addr:housenumber": "3283",
    "addr:postcode": "45804",
    "addr:street": "Harding Hwy",
    "iso:country": "US",
    "sg:address": "3283 Harding Hwy",
    "sg:city": "Lima",
    "sg:classifiers": [
      {
        "category": "Autos \u0026 Motor Vehicles",
        "subcategory": "Auto Supplies",
        "type": "Retail Goods"
      }
    ],
    "sg:phone": "+1 419 225 9054",
    "sg:postcode": "45804",
    "sg:province": "OH",
    "sg:tags": [
      "tire"
    ],
    "wof:name": "Allen Tire Service",
    "wof:placetype": "venue"
  },
  "geometry": {"coordinates":[-84.044704,40.731077],"type":"Point"}
}
