{
  "type": "Feature",
  "properties": {
    "addr:full": "1108 McArthur Rd Jeffersonville OH 43128",
    "addr:housenumber": "1108",
    "addr:postcode": "43128",
    "addr:street": "Mcarthur Rd",
    "iso:country": "US",
    "sg:address": "1108 McArthur Rd",
    "sg:city": "Jeffersonville",
    "sg:classifiers": [
      {
        "category": "Shopping",
        "subcategory": "Used Merchandise",
        "type": "Retail Goods"
      }
    ],
    "sg:phone": "+1 740 426 6169",
    "sg:postcode": "43128",
    "sg:province": "OH",
    "sg:tags": [
      "antique"
    ],
    "wof:name": "Forever Treasurers",
    "wof:placetype": "venue"
  },
  "geometry": {"coordinates":[-83.537798,39.651136],"type":"Point"}
}
