{
  "type": "Feature",
  "properties": {
    "iso:country":"US",
    "sg:address":"10394 Pioneer Rd",
    "sg:city":"Byesville",
    "sg:classifiers":[
        {
            "category":"Manufacturing",
            "subcategory":"Glass & Minerals",
            "type":"Manufacturing & Wholesale Goods"
        }
    ],
    "sg:phone":"+1 740 685 6554",
    "sg:postcode":"43723",
    "sg:province":"OH",
    "sg:tags":[
        "ready"
    ],
    "wof:name":"Caldwell Redi-Mix Concrete",
    "wof:placetype":"venue"
},
  "geometry": {"coordinates":[-81.55145,39.969359],"type":"Point"}
}