{
  "type": "Feature",
  "properties": {
    "addr:full":"325 W Wyandot Ave Upper Sandusky OH 43351",
    "addr:housenumber":"325",
    "addr:postcode":"43351",
    "addr:street":"W Wyandot Ave",
    "iso:country":"US",
    "sg:address":"325 W Wyandot Ave",
    "sg:city":"Upper Sandusky",
    "sg:classifiers":[
        {
            "category":"Professional",
            "subcategory":"Accounting & Tax Preparation",
            "type":"Services"
        }
    ],
    "sg:phone":"+1 419 294 0233",
    "sg:postcode":"43351",
    "sg:province":"OH",
    "sg:tags":[
        "bookkeeping",
        "general"
    ],
    "wof:name":"Jageman & Assoc Business Svc",
    "wof:placetype":"venue"
},
  "geometry": {"coordinates":[-83.28726899999999,40.827426],"type":"Point"}
}