{
  "type": "Feature",
  "properties": {
    "iso:country":"US",
    "sg:address":"1231 Glen Haven Ln",
    "sg:city":"Batavia",
    "sg:classifiers":[
        {
            "category":"Building & Trades",
            "subcategory":"Cleaning & Sanitation",
            "type":"Services"
        }
    ],
    "sg:phone":"+1 513 753 1520",
    "sg:postcode":"45103",
    "sg:province":"OH",
    "sg:tags":[
        "window"
    ],
    "wof:name":"Blair Window Cleaning Svc",
    "wof:placetype":"venue"
},
  "geometry": {"coordinates":[-84.234421,39.100279],"type":"Point"}
}