{
  "type": "Feature",
  "properties": {
    "addr:full": "1925 Millville Oxford Rd Hamilton OH 45013",
    "addr:housenumber": "1925",
    "addr:postcode": "45013",
    "addr:street": "Millville Oxford Rd",
    "iso:country": "US",
    "sg:address": "1925 Millville Oxford Rd",
    "sg:city": "Hamilton",
    "sg:classifiers": [
      {
        "category": "Farming",
        "subcategory": "Nursery",
        "type": "Manufacturing \u0026 Wholesale Goods"
      }
    ],
    "sg:phone": "+1 513 887 6606",
    "sg:postcode": "45013",
    "sg:province": "OH",
    "sg:tags": [
      "ornamental"
    ],
    "wof:name": "Oxford Greenhouse",
    "wof:placetype": "venue"
  },
  "geometry": {"coordinates":[-84.68032,39.437916],"type":"Point"}
}
