{
  "type": "Feature",
  "properties": {
    "iso:country":"US",
    "sg:address":"1925 Millville Oxford Rd",
    "sg:city":"Hamilton",
    "sg:classifiers":[
        {
            "category":"Farming",
            "subcategory":"Nursery",
            "type":"Manufacturing & Wholesale Goods"
        }
    ],
    "sg:phone":"+1 513 887 6606",
    "sg:postcode":"45013",
    "sg:province":"OH",
    "sg:tags":[
        "ornamental"
    ],
    "wof:name":"Oxford Greenhouse",
    "wof:placetype":"venue"
},
  "geometry": {"coordinates":[-84.68031999999999,39.437916],"type":"Point"}
}