{
  "type": "Feature",
  "properties": {
    "addr:full":"101 Harrison St Sherwood OH 43512",
    "addr:housenumber":"101",
    "addr:postcode":"43512",
    "addr:street":"Harrison St",
    "iso:country":"US",
    "sg:address":"101 Harrison St",
    "sg:city":"Sherwood",
    "sg:classifiers":[
        {
            "category":"Autos & Motor Vehicles",
            "subcategory":"Automobile Sales",
            "type":"Retail Goods"
        }
    ],
    "sg:phone":"+1 419 899 2165",
    "sg:postcode":"43512",
    "sg:province":"OH",
    "sg:tags":[
        "car",
        "dealer"
    ],
    "wof:name":"Moats Ford Sales Inc",
    "wof:placetype":"venue"
},
  "geometry": {"coordinates":[-84.553359,41.291896],"type":"Point"}
}