{
  "type": "Feature",
  "properties": {
    "addr:full": "893 Hamlet St Columbus OH 43201",
    "addr:housenumber": "893",
    "addr:postcode": "43201",
    "addr:street": "Hamlet St",
    "iso:country": "US",
    "sg:address": "893 Hamlet St",
    "sg:city": "Columbus",
    "sg:classifiers": [
      {
        "category": "Organizations",
        "subcategory": "Religious Organization",
        "type": "Services"
      }
    ],
    "sg:phone": "+1 614 299 0508",
    "sg:postcode": "43201",
    "sg:province": "OH",
    "wof:name": "St Vincent Depaul Sacred Heart",
    "wof:placetype": "venue"
  },
  "geometry": {"coordinates":[-82.999969,39.98215],"type":"Point"}
}
