{
  "type": "Feature",
  "properties": {
    "addr:full":"3249 Wales Ave NW Massillon OH 44646",
    "addr:housenumber":"3249",
    "addr:postcode":"44646",
    "addr:street":"Wales Ave Nw",
    "iso:country":"US",
    "sg:address":"3249 Wales Ave NW",
    "sg:city":"Massillon",
    "sg:classifiers":[
        {
            "category":"Insurance",
            "subcategory":"Insurance Agent",
            "type":"Services"
        }
    ],
    "sg:phone":"+1 330 833 1026",
    "sg:postcode":"44646",
    "sg:province":"OH",
    "wof:name":"Buell Bryon & OBrien",
    "wof:placetype":"venue"
},
  "geometry": {"coordinates":[-81.50271499999999,40.82799],"type":"Point"}
}