{
  "type": "Feature",
  "properties": {
    "addr:full":"6000 S Mason Montgomery Rd Mason OH 45040",
    "addr:housenumber":"6000",
    "addr:postcode":"45040",
    "addr:street":"S Mason Montgomery Rd",
    "iso:country":"US",
    "sg:address":"6000 S Mason Montgomery Rd",
    "sg:city":"Mason",
    "sg:classifiers":[
        {
            "category":"Government",
            "subcategory":"Court House",
            "type":"Public Place"
        }
    ],
    "sg:phone":"+1 513 398 7901",
    "sg:postcode":"45040",
    "sg:province":"OH",
    "sg:tags":[
        "city"
    ],
    "wof:name":"Mason City Municipal Court",
    "wof:placetype":"venue"
},
  "geometry": {"coordinates":[-84.309569,39.354385],"type":"Point"}
}