{
  "type": "Feature",
  "properties": {
    "iso:country":"US",
    "sg:address":"6962 Arlington St",
    "sg:city":"Brecksville",
    "sg:classifiers":[
        {
            "category":"Building & Trades",
            "subcategory":"Construction",
            "type":"Services"
        }
    ],
    "sg:phone":"+1 440 526 4590",
    "sg:postcode":"44141",
    "sg:province":"OH",
    "sg:tags":[
        "contractor"
    ],
    "wof:name":"Kenfab Welding",
    "wof:placetype":"venue"
},
  "geometry": {"coordinates":[-81.629658,41.318319],"type":"Point"}
}