{
  "type": "Feature",
  "properties": {
    "addr:full": "6962 Arlington St Brecksville OH 44141",
    "addr:housenumber": "6962",
    "addr:postcode": "44141",
    "addr:street": "Arlington St",
    "iso:country": "US",
    "sg:address": "6962 Arlington St",
    "sg:city": "Brecksville",
    "sg:classifiers": [
      {
        "category": "Building \u0026 Trades",
        "subcategory": "Construction",
        "type": "Services"
      }
    ],
    "sg:phone": "+1 440 526 4590",
    "sg:postcode": "44141",
    "sg:province": "OH",
    "sg:tags": [
      "contractor"
    ],
    "wof:name": "Kenfab Welding",
    "wof:placetype": "venue"
  },
  "geometry": {"coordinates":[-81.629658,41.318319],"type":"Point"}
}
