{
  "type": "Feature",
  "properties": {
    "iso:country":"US",
    "sg:address":"8142 Twp Rd 574",
    "sg:city":"Holmesville",
    "sg:classifiers":[
        {
            "category":"Building & Trades",
            "subcategory":"Construction",
            "type":"Services"
        }
    ],
    "sg:phone":"+1 330 674 0907",
    "sg:postcode":"44633",
    "sg:province":"OH",
    "sg:tags":[
        "gen"
    ],
    "wof:name":"D & D Construction",
    "wof:placetype":"venue"
},
  "geometry": {"coordinates":[-81.912349,40.608969],"type":"Point"}
}