{
  "type": "Feature",
  "properties": {
    "iso:country":"US",
    "sg:address":"515 Bandy Rd",
    "sg:city":"Bidwell",
    "sg:classifiers":[
        {
            "category":"Freight",
            "type":"Transportation"
        }
    ],
    "sg:phone":"+1 740 245 9247",
    "sg:postcode":"45614",
    "sg:province":"OH",
    "sg:tags":[
        "operator",
        "local",
        "trucking"
    ],
    "wof:name":"Sandy Roberts",
    "wof:placetype":"venue"
},
  "geometry": {"coordinates":[-82.377786,38.91807],"type":"Point"}
}