{
  "type": "Feature",
  "properties": {
    "addr:full":"11534 Mangen Rd Versailles OH 45380",
    "addr:postcode":"11534;45380",
    "addr:street":"Mangen Rd",
    "iso:country":"US",
    "sg:address":"11534 Mangen Rd",
    "sg:city":"Versailles",
    "sg:phone":"+1 937 526 4593",
    "sg:postcode":"45380",
    "sg:province":"OH",
    "sg:tags":[
        "farm",
        "wheat"
    ],
    "wof:name":"Dale Petitjean",
    "wof:placetype":"venue"
},
  "geometry": {"coordinates":[-84.523808,40.261674],"type":"Point"}
}