{
  "type": "Feature",
  "properties": {
    "iso:country":"US",
    "sg:address":"1147 Distel Ln",
    "sg:city":"Portsmouth",
    "sg:classifiers":[
        {
            "category":"Wholesale",
            "subcategory":"Auto Parts",
            "type":"Manufacturing & Wholesale Goods"
        }
    ],
    "sg:phone":"+1 740 353 4027",
    "sg:postcode":"45662",
    "sg:province":"OH",
    "sg:tags":[
        "tire"
    ],
    "wof:name":"Duncan's Wholesale Tires",
    "wof:placetype":"venue"
},
  "geometry": {"coordinates":[-82.982788,38.788845],"type":"Point"}
}