{
  "type": "Feature",
  "properties": {
    "iso:country":"US",
    "sg:address":"11013 Airport Hwy",
    "sg:city":"Swanton",
    "sg:classifiers":[
        {
            "category":"Airline",
            "type":"Transportation"
        }
    ],
    "sg:phone":"+1 419 865 2369",
    "sg:postcode":"43558",
    "sg:province":"OH",
    "sg:tags":[
        "scheduled",
        "air"
    ],
    "wof:name":"Delta Airlines",
    "wof:placetype":"venue"
},
  "geometry": {"coordinates":[-83.804923,41.595977],"type":"Point"}
}