{
  "type": "Feature",
  "properties": {
    "iso:country":"US",
    "sg:address":"8054 Hetz Dr",
    "sg:city":"Cincinnati",
    "sg:classifiers":[
        {
            "category":"Restaurant",
            "type":"Food & Drink"
        }
    ],
    "sg:phone":"+1 513 469 8787",
    "sg:postcode":"45242",
    "sg:province":"OH",
    "wof:name":"Shan Shan Kitchen",
    "wof:placetype":"venue"
},
  "geometry": {"coordinates":[-84.345699,39.263067],"type":"Point"}
}