{
  "type": "Feature",
  "properties": {
    "iso:country":"US",
    "sg:address":"1031 Cincinnati Ave",
    "sg:city":"Xenia",
    "sg:classifiers":[
        {
            "category":"Retail",
            "subcategory":"Auto Repair",
            "type":"Services"
        }
    ],
    "sg:phone":"+1 937 374 4157",
    "sg:postcode":"45385",
    "sg:province":"OH",
    "sg:tags":[
        "body",
        "general"
    ],
    "sg:website":"www.hidyhonda.com",
    "wof:name":"Hidy Honda",
    "wof:placetype":"venue"
},
  "geometry": {"coordinates":[-83.945149,39.667297],"type":"Point"}
}