{
  "type": "Feature",
  "properties": {
    "addr:full":"4410 Straight Arrow Rd Dayton OH 45430",
    "addr:housenumber":"4410",
    "addr:postcode":"45430",
    "addr:street":"Straight Arrow Rd",
    "iso:country":"US",
    "sg:address":"4410 Straight Arrow Rd",
    "sg:city":"Dayton",
    "sg:classifiers":[
        {
            "category":"Freight",
            "type":"Transportation"
        }
    ],
    "sg:phone":"+1 937 427 9322",
    "sg:postcode":"45430",
    "sg:province":"OH",
    "sg:tags":[
        "building",
        "house",
        "mover"
    ],
    "wof:name":"Charles Simms Development",
    "wof:placetype":"venue"
},
  "geometry": {"coordinates":[-84.10395200000001,39.709977],"type":"Point"}
}