{
  "type": "Feature",
  "properties": {
    "iso:country":"US",
    "sg:address":"6729 Main St",
    "sg:city":"Cincinnati",
    "sg:classifiers":[
        {
            "category":"Building & Trades",
            "subcategory":"Plumbing",
            "type":"Services"
        }
    ],
    "sg:phone":"+1 513 561 7460",
    "sg:postcode":"45244",
    "sg:province":"OH",
    "sg:tags":[
        "tank",
        "septic"
    ],
    "wof:name":"Muhlberger Sanitation",
    "wof:placetype":"venue"
},
  "geometry": {"coordinates":[-84.36782599999999,39.124338],"type":"Point"}
}