{
  "type": "Feature",
  "properties": {
    "addr:full":"2473 E Dublin Granville Rd Columbus OH 43229",
    "addr:housenumber":"2473",
    "addr:postcode":"43229",
    "addr:street":"E Dublin Granville Rd",
    "iso:country":"US",
    "sg:address":"2473 E Dublin Granville Rd",
    "sg:city":"Columbus",
    "sg:classifiers":[
        {
            "category":"Banks & Credit Unions",
            "subcategory":"Bank",
            "type":"Services"
        }
    ],
    "sg:phone":"+1 614 899 2330",
    "sg:postcode":"43229",
    "sg:province":"OH",
    "sg:tags":[
        "cashing",
        "check"
    ],
    "wof:name":"Check Into Cash",
    "wof:placetype":"venue"
},
  "geometry": {"coordinates":[-82.951564,40.085065],"type":"Point"}
}