{
  "type": "Feature",
  "properties": {
    "addr:full": "515 Springfield St Dayton OH 45403",
    "addr:housenumber": "515",
    "addr:postcode": "45403",
    "addr:street": "Springfield St",
    "iso:country": "US",
    "sg:address": "515 Springfield St",
    "sg:city": "Dayton",
    "sg:classifiers": [
      {
        "category": "Manufacturing",
        "subcategory": "Tools \u0026 Machinery",
        "type": "Manufacturing \u0026 Wholesale Goods"
      }
    ],
    "sg:phone": "+1 937 254 8898",
    "sg:postcode": "45403",
    "sg:province": "OH",
    "sg:tags": [
      "machine",
      "shop"
    ],
    "wof:name": "C G Egli Inc",
    "wof:placetype": "venue"
  },
  "geometry": {"coordinates":[-84.155763,39.768658],"type":"Point"}
}
