{
  "type": "Feature",
  "properties": {
    "addr:full":"7668 Sawmill Rd Dublin OH 43016",
    "addr:housenumber":"7668",
    "addr:postcode":"43016",
    "addr:street":"Sawmill Rd",
    "iso:country":"US",
    "sg:address":"7668 Sawmill Rd",
    "sg:city":"Dublin",
    "sg:classifiers":[
        {
            "category":"Cinema",
            "subcategory":"Movie Rental",
            "type":"Entertainment"
        }
    ],
    "sg:phone":"+1 614 792 2013",
    "sg:postcode":"43016",
    "sg:province":"OH",
    "sg:tags":[
        "leasing",
        "video",
        "disc",
        "tape"
    ],
    "wof:name":"Blockbuster Video",
    "wof:placetype":"venue"
},
  "geometry": {"coordinates":[-83.09016099999999,40.123134],"type":"Point"}
}