{
  "type": "Feature",
  "properties": {
    "addr:full":"4515 Laser Rd Shelby OH 44875",
    "addr:housenumber":"4515",
    "addr:postcode":"44875",
    "addr:street":"Laser Rd",
    "iso:country":"US",
    "sg:address":"4515 Laser Rd",
    "sg:city":"Shelby",
    "sg:classifiers":[
        {
            "category":"Real Estate",
            "subcategory":"Real Estate Operator",
            "type":"Services"
        }
    ],
    "sg:phone":"+1 419 347 9957",
    "sg:postcode":"44875",
    "sg:province":"OH",
    "sg:tags":[
        "country",
        "store"
    ],
    "wof:name":"Ault Country Tyme Shop",
    "wof:placetype":"venue"
},
  "geometry": {"coordinates":[-82.59567,40.872942],"type":"Point"}
}