{
  "type": "Feature",
  "properties": {
    "iso:country":"US",
    "sg:address":"9984 Brewster Ln",
    "sg:city":"Powell",
    "sg:classifiers":[
        {
            "category":"Health Services",
            "subcategory":"Doctor",
            "type":"Services"
        }
    ],
    "sg:phone":"+1 614 761 3853",
    "sg:postcode":"43065",
    "sg:province":"OH",
    "wof:name":"Duke M Rakich DDS",
    "wof:placetype":"venue"
},
  "geometry": {"coordinates":[-83.094094,40.15349],"type":"Point"}
}