{
  "type": "Feature",
  "properties": {
    "iso:country":"US",
    "sg:address":"4738 Henley-Deemer Rd",
    "sg:city":"Mc Dermott",
    "sg:classifiers":[
        {
            "category":"Education",
            "subcategory":"School",
            "type":"Public Place"
        }
    ],
    "sg:phone":"+1 740 259 2250",
    "sg:postcode":"45648",
    "sg:province":"OH",
    "sg:website":"www.northwest.k12.oh.us",
    "wof:name":"Northwest Elementary School",
    "wof:placetype":"venue"
},
  "geometry": {"coordinates":[-83.085415,38.876335],"type":"Point"}
}