{
  "type": "Feature",
  "properties": {
    "addr:full": "4583 Lee Rd Cleveland OH 44128",
    "addr:housenumber": "4583",
    "addr:postcode": "44128",
    "addr:street": "Lee Rd",
    "iso:country": "US",
    "sg:address": "4583 Lee Rd",
    "sg:city": "Cleveland",
    "sg:classifiers": [
      {
        "category": "Building \u0026 Trades",
        "subcategory": "Landscaping Services",
        "type": "Services"
      }
    ],
    "sg:phone": "+1 216 581 2150",
    "sg:postcode": "44128",
    "sg:province": "OH",
    "sg:tags": [
      "landscape",
      "contractor"
    ],
    "wof:name": "Wake Forest Garden Ctr",
    "wof:placetype": "venue"
  },
  "geometry": {"coordinates":[-81.564709,41.433954],"type":"Point"}
}
