{
  "type": "Feature",
  "properties": {
    "addr:full": "209 W 21st St Lorain OH 44052",
    "addr:housenumber": "209",
    "addr:postcode": "44052",
    "addr:street": "W 21St St",
    "iso:country": "US",
    "sg:address": "209 W 21st St",
    "sg:city": "Lorain",
    "sg:classifiers": [
      {
        "category": "Health Services",
        "subcategory": "Doctor",
        "type": "Services"
      }
    ],
    "sg:phone": "+1 440 244 5309",
    "sg:postcode": "44052",
    "sg:province": "OH",
    "sg:tags": [
      "dentist"
    ],
    "wof:name": "Mazorow Henry B DDS Ms Inc",
    "wof:placetype": "venue"
  },
  "geometry": {"coordinates":[-82.167709,41.451379],"type":"Point"}
}
