{
  "type": "Feature",
  "properties": {
    "addr:full": "215 E Herrick Ave Wellington OH 44090",
    "addr:housenumber": "215",
    "addr:postcode": "44090",
    "addr:street": "E Herrick Ave",
    "iso:country": "US",
    "sg:address": "215 E Herrick Ave",
    "sg:city": "Wellington",
    "sg:classifiers": [
      {
        "category": "Restaurant",
        "type": "Food \u0026 Drink"
      }
    ],
    "sg:menulink": "http://www.allmenus.com/oh/wellington/134308-subway/menu/",
    "sg:phone": "+1 440 647 6402",
    "sg:postcode": "44090",
    "sg:province": "OH",
    "sg:tags": [
      "american",
      "sandwich"
    ],
    "wof:name": "Subway",
    "wof:placetype": "venue"
  },
  "geometry": {"coordinates":[-82.214872,41.168552],"type":"Point"}
}
