{
  "type": "Feature",
  "properties": {
    "addr:full":"78 W Columbus St Canal Winchester OH 43110",
    "addr:housenumber":"78",
    "addr:postcode":"43110",
    "addr:street":"W Columbus St",
    "iso:country":"US",
    "sg:address":"78 W Columbus St",
    "sg:city":"Canal Winchester",
    "sg:classifiers":[
        {
            "category":"Personal",
            "subcategory":"Barber",
            "type":"Services"
        }
    ],
    "sg:phone":"+1 614 920 4257",
    "sg:postcode":"43110",
    "sg:province":"OH",
    "wof:name":"Design Team",
    "wof:placetype":"venue"
},
  "geometry": {"coordinates":[-82.808313,39.84162],"type":"Point"}
}