{
  "type": "Feature",
  "properties": {
    "addr:full": "201 W Jefferson St Montpelier OH 43543",
    "addr:housenumber": "201",
    "addr:postcode": "43543",
    "addr:street": "W Jefferson St",
    "iso:country": "US",
    "sg:address": "201 W Jefferson St",
    "sg:city": "Montpelier",
    "sg:classifiers": [
      {
        "category": "Wholesale",
        "subcategory": "Machinery \u0026 Supplies",
        "type": "Manufacturing \u0026 Wholesale Goods"
      }
    ],
    "sg:phone": "+1 419 485 3796",
    "sg:postcode": "43543",
    "sg:province": "OH",
    "sg:tags": [
      "equipment",
      "establishment"
    ],
    "wof:name": "Jerry E Teats Jr",
    "wof:placetype": "venue"
  },
  "geometry": {"coordinates":[-84.609882,41.584606],"type":"Point"}
}
