{
  "type": "Feature",
  "properties": {
    "iso:country":"US",
    "sg:address":"201 W Jefferson St",
    "sg:city":"Montpelier",
    "sg:classifiers":[
        {
            "category":"Wholesale",
            "subcategory":"Machinery & Supplies",
            "type":"Manufacturing & Wholesale Goods"
        }
    ],
    "sg:phone":"+1 419 485 3796",
    "sg:postcode":"43543",
    "sg:province":"OH",
    "sg:tags":[
        "equipment",
        "establishment"
    ],
    "wof:name":"Jerry E Teats Jr",
    "wof:placetype":"venue"
},
  "geometry": {"coordinates":[-84.609882,41.584606],"type":"Point"}
}