{
  "type": "Feature",
  "properties": {
    "addr:full": "3015 Scioto Darby Executive Ct Hilliard OH 43026",
    "addr:housenumber": "3015",
    "addr:postcode": "43026",
    "addr:street": "Scioto Darby Executive Ct",
    "iso:country": "US",
    "sg:address": "3015 Scioto Darby Executive Ct",
    "sg:city": "Hilliard",
    "sg:classifiers": [
      {
        "category": "Organizations",
        "subcategory": "Membership Organization",
        "type": "Services"
      }
    ],
    "sg:phone": "+1 614 777 7387",
    "sg:postcode": "43026",
    "sg:province": "OH",
    "sg:tags": [
      "society",
      "humane"
    ],
    "sg:website": "www.cahs-pets.org",
    "wof:name": "Humane Society-Capital Area",
    "wof:placetype": "venue"
  },
  "geometry": {"coordinates":[-83.116112,40.015609],"type":"Point"}
}
