{
  "type": "Feature",
  "properties": {
    "addr:full":"931 Brandt Rd Geneva OH 44041",
    "addr:housenumber":"931",
    "addr:postcode":"44041",
    "addr:street":"Brandt Rd",
    "iso:country":"US",
    "sg:address":"931 Brandt Rd",
    "sg:city":"Geneva",
    "sg:classifiers":[
        {
            "category":"Building & Trades",
            "subcategory":"Construction",
            "type":"Services"
        }
    ],
    "sg:phone":"+1 440 466 0966",
    "sg:postcode":"44041",
    "sg:province":"OH",
    "sg:tags":[
        "contractor"
    ],
    "wof:name":"Dun Rite Woodworks",
    "wof:placetype":"venue"
},
  "geometry": {"coordinates":[-80.96985599999999,41.755138],"type":"Point"}
}