{
  "type": "Feature",
  "properties": {
    "iso:country":"US",
    "sg:address":"770 S Riverside Dr",
    "sg:city":"Batavia",
    "sg:classifiers":[
        {
            "category":"Organizations",
            "subcategory":"Religious Organization",
            "type":"Services"
        }
    ],
    "sg:phone":"+1 513 732 2739",
    "sg:postcode":"45103",
    "sg:province":"OH",
    "sg:tags":[
        "church"
    ],
    "sg:website":"www.bataviabaptisttemple.org",
    "wof:name":"Batavia Baptist Temple",
    "wof:placetype":"venue"
},
  "geometry": {"coordinates":[-84.185901,39.071188],"type":"Point"}
}