{
  "type": "Feature",
  "properties": {
    "iso:country":"US",
    "sg:address":"2765 Miamisburg Centerville Rd",
    "sg:city":"Dayton",
    "sg:classifiers":[
        {
            "category":"Restaurant",
            "type":"Food & Drink"
        }
    ],
    "sg:phone":"+1 937 291 4153",
    "sg:postcode":"45459",
    "sg:province":"OH",
    "sg:tags":[
        "shop",
        "coffee"
    ],
    "sg:website":"www.starbucks.com",
    "wof:name":"Starbucks",
    "wof:placetype":"venue"
},
  "geometry": {"coordinates":[-84.220851,39.637163],"type":"Point"}
}