{
  "type": "Feature",
  "properties": {
    "addr:full": "27679 Royalton Rd Columbia Station OH 44028",
    "addr:housenumber": "27679",
    "addr:postcode": "44028",
    "addr:street": "Royalton Rd",
    "iso:country": "US",
    "sg:address": "27679 Royalton Rd",
    "sg:city": "Columbia Station",
    "sg:classifiers": [
      {
        "category": "Farming",
        "subcategory": "Dairy Farm",
        "type": "Manufacturing \u0026 Wholesale Goods"
      }
    ],
    "sg:phone": "+1 440 236 8286",
    "sg:postcode": "44028",
    "sg:province": "OH",
    "wof:name": "Jeffrey Trammell",
    "wof:placetype": "venue"
  },
  "geometry": {"coordinates":[-81.939194,41.31283],"type":"Point"}
}
