{
  "type": "Feature",
  "properties": {
    "iso:country":"US",
    "sg:address":"27679 Royalton Rd",
    "sg:city":"Columbia Station",
    "sg:classifiers":[
        {
            "category":"Farming",
            "subcategory":"Dairy Farm",
            "type":"Manufacturing & Wholesale Goods"
        }
    ],
    "sg:phone":"+1 440 236 8286",
    "sg:postcode":"44028",
    "sg:province":"OH",
    "wof:name":"Jeffrey Trammell",
    "wof:placetype":"venue"
},
  "geometry": {"coordinates":[-81.939194,41.31283],"type":"Point"}
}