{
  "type": "Feature",
  "properties": {
    "addr:full": "4330 Navarre Ave Oregon OH 43616",
    "addr:housenumber": "4330",
    "addr:postcode": "43616",
    "addr:street": "Navarre Ave",
    "iso:country": "US",
    "sg:address": "4330 Navarre Ave",
    "sg:city": "Oregon",
    "sg:classifiers": [
      {
        "category": "Health Services",
        "subcategory": "Health Practitioner",
        "type": "Services"
      },
      {
        "category": "Health Services",
        "subcategory": "Doctor",
        "type": "Services"
      }
    ],
    "sg:phone": "+1 419 691 7820",
    "sg:postcode": "43616",
    "sg:province": "OH",
    "sg:tags": [
      "physician",
      "surgeon"
    ],
    "wof:name": "Maumee Bay Family Practice",
    "wof:placetype": "venue"
  },
  "geometry": {"coordinates":[-83.439677,41.637503],"type":"Point"}
}
