{
  "type": "Feature",
  "properties": {
    "addr:full":"56 Lansdowne Blvd Youngstown OH 44506",
    "addr:housenumber":"56",
    "addr:postcode":"44506",
    "addr:street":"Lansdowne Blvd",
    "iso:country":"US",
    "sg:address":"56 Lansdowne Blvd",
    "sg:city":"Youngstown",
    "sg:classifiers":[
        {
            "category":"Wholesale",
            "subcategory":"Electrical",
            "type":"Manufacturing & Wholesale Goods"
        }
    ],
    "sg:phone":"+1 330 746 0188",
    "sg:postcode":"44506",
    "sg:province":"OH",
    "sg:tags":[
        "equipment"
    ],
    "wof:name":"Royal Electric",
    "wof:placetype":"venue"
},
  "geometry": {"coordinates":[-80.61619,41.098064],"type":"Point"}
}