{
  "type": "Feature",
  "properties": {
    "addr:full": "7623 Old 3c Hwy Maineville OH 45039",
    "addr:housenumber": "7623",
    "addr:postcode": "45039",
    "addr:street": "Old 3C Hwy",
    "iso:country": "US",
    "sg:address": "7623 Old 3c Hwy",
    "sg:city": "Maineville",
    "sg:classifiers": [
      {
        "category": "Education",
        "subcategory": "Dance Studio",
        "type": "Public Place"
      }
    ],
    "sg:phone": "+1 513 683 6860",
    "sg:postcode": "45039",
    "sg:province": "OH",
    "sg:tags": [
      "instruction",
      "dancing"
    ],
    "wof:name": "Ballet Tech",
    "wof:placetype": "venue"
  },
  "geometry": {"coordinates":[-84.250382,39.322451],"type":"Point"}
}
