{
  "type": "Feature",
  "properties": {
    "iso:country":"US",
    "sg:address":"10127 Co Rd 255",
    "sg:city":"Kenton",
    "sg:classifiers":[
        {
            "category":"Farming",
            "subcategory":"Dairy Farm",
            "type":"Manufacturing & Wholesale Goods"
        }
    ],
    "sg:phone":"+1 419 673 0212",
    "sg:postcode":"43326",
    "sg:province":"OH",
    "sg:tags":[
        "field",
        "corn",
        "grain",
        "cash",
        "crop"
    ],
    "wof:name":"Candilane Farm",
    "wof:placetype":"venue"
},
  "geometry": {"coordinates":[-83.419799,40.672725],"type":"Point"}
}