{
  "type": "Feature",
  "properties": {
    "addr:full":"20444 Raymond Rd Marysville OH 43040",
    "addr:housenumber":"20444",
    "addr:postcode":"43040",
    "addr:street":"Raymond Rd",
    "iso:country":"US",
    "sg:address":"20444 Raymond Rd",
    "sg:city":"Marysville",
    "sg:classifiers":[
        {
            "category":"Building & Trades",
            "subcategory":"Plumbing",
            "type":"Services"
        }
    ],
    "sg:phone":"+1 937 644 3191",
    "sg:postcode":"43040",
    "sg:province":"OH",
    "sg:tags":[
        "tank",
        "septic"
    ],
    "wof:name":"Clarridge's Discount Septic",
    "wof:placetype":"venue"
},
  "geometry": {"coordinates":[-83.410972,40.293209],"type":"Point"}
}