{
  "type": "Feature",
  "properties": {
    "iso:country":"US",
    "sg:address":"7413 Vine St",
    "sg:city":"Cincinnati",
    "sg:classifiers":[
        {
            "category":"Wholesale",
            "subcategory":"Auto Parts",
            "type":"Manufacturing & Wholesale Goods"
        }
    ],
    "sg:phone":"+1 513 679 4700",
    "sg:postcode":"45216",
    "sg:province":"OH",
    "wof:name":"Smyth Automotive Inc",
    "wof:placetype":"venue"
},
  "geometry": {"coordinates":[-84.476387,39.197929],"type":"Point"}
}