{
  "type": "Feature",
  "properties": {
    "addr:full": "3356 Valley Pkwy Cleveland OH 44133",
    "addr:housenumber": "3356",
    "addr:postcode": "44133",
    "addr:street": "Valley Pkwy",
    "iso:country": "US",
    "sg:address": "3356 Valley Pkwy",
    "sg:city": "Cleveland",
    "sg:classifiers": [
      {
        "category": "Building \u0026 Trades",
        "subcategory": "Construction",
        "type": "Services"
      }
    ],
    "sg:phone": "+1 440 877 0792",
    "sg:postcode": "44133",
    "sg:province": "OH",
    "sg:tags": [
      "repairing",
      "remodeling",
      "contractor"
    ],
    "wof:name": "ROD Remodeling",
    "wof:placetype": "venue"
  },
  "geometry": {"coordinates":[-81.724119,41.301375],"type":"Point"}
}
