{
  "type": "Feature",
  "properties": {
    "iso:country":"US",
    "sg:address":"3700 Northfield Rd",
    "sg:city":"Cleveland",
    "sg:classifiers":[
        {
            "category":"Professional",
            "subcategory":"Lawyer & Legal Services",
            "type":"Services"
        }
    ],
    "sg:phone":"+1 216 283 4225",
    "sg:postcode":"44122",
    "sg:province":"OH",
    "sg:tags":[
        "attorney"
    ],
    "wof:name":"Thomas P O'Donnell Co",
    "wof:placetype":"venue"
},
  "geometry": {"coordinates":[-81.533096,41.459901],"type":"Point"}
}