{
  "type": "Feature",
  "properties": {
    "iso:country":"US",
    "sg:address":"1401 Haft Dr",
    "sg:city":"Reynoldsburg",
    "sg:classifiers":[
        {
            "category":"Insurance",
            "subcategory":"Insurance Agent",
            "type":"Services"
        }
    ],
    "sg:phone":"+1 614 866 4776",
    "sg:postcode":"43068",
    "sg:province":"OH",
    "wof:name":"Boa",
    "wof:placetype":"venue"
},
  "geometry": {"coordinates":[-82.806811,39.954597],"type":"Point"}
}