{
  "type": "Feature",
  "properties": {
    "iso:country":"US",
    "sg:address":"343 16th St SE",
    "sg:city":"Massillon",
    "sg:classifiers":[
        {
            "category":"Building & Trades",
            "subcategory":"Construction",
            "type":"Services"
        }
    ],
    "sg:phone":"+1 330 832 3604",
    "sg:postcode":"44646",
    "sg:province":"OH",
    "sg:tags":[
        "general",
        "contractor"
    ],
    "wof:name":"Gerstenslager Hardwood Prods",
    "wof:placetype":"venue"
},
  "geometry": {"coordinates":[-81.50483,40.79259],"type":"Point"}
}