{
  "type": "Feature",
  "properties": {
    "addr:full": "343 16th St SE Massillon OH 44646",
    "addr:housenumber": "343",
    "addr:postcode": "44646",
    "addr:street": "16Th St Se",
    "iso:country": "US",
    "sg:address": "343 16th St SE",
    "sg:city": "Massillon",
    "sg:classifiers": [
      {
        "category": "Building \u0026 Trades",
        "subcategory": "Construction",
        "type": "Services"
      }
    ],
    "sg:phone": "+1 330 832 3604",
    "sg:postcode": "44646",
    "sg:province": "OH",
    "sg:tags": [
      "general",
      "contractor"
    ],
    "wof:name": "Gerstenslager Hardwood Prods",
    "wof:placetype": "venue"
  },
  "geometry": {"coordinates":[-81.50483,40.79259],"type":"Point"}
}
