{
  "type": "Feature",
  "properties": {
    "addr:full":"6602 Brown Rd Oregon OH 43618",
    "addr:housenumber":"6602",
    "addr:postcode":"43618",
    "addr:street":"Brown Rd",
    "iso:country":"US",
    "sg:address":"6602 Brown Rd",
    "sg:city":"Oregon",
    "sg:classifiers":[
        {
            "category":"Retail",
            "subcategory":"Repair Shop",
            "type":"Services"
        }
    ],
    "sg:phone":"+1 419 836 8820",
    "sg:postcode":"43618",
    "sg:province":"OH",
    "sg:tags":[
        "nursery",
        "garden",
        "supply"
    ],
    "wof:name":"Goulet Lawnmower Service",
    "wof:placetype":"venue"
},
  "geometry": {"coordinates":[-83.394612,41.623656],"type":"Point"}
}