{
  "type": "Feature",
  "properties": {
    "iso:country":"US",
    "sg:address":"5508 Wales Ave NW",
    "sg:city":"Massillon",
    "sg:classifiers":[
        {
            "category":"Restaurant",
            "type":"Food & Drink"
        }
    ],
    "sg:menulink":"http://www.allmenus.com/oh/canton/134674-subway/menu/",
    "sg:phone":"+1 330 834 2789",
    "sg:postcode":"44646",
    "sg:province":"OH",
    "sg:tags":[
        "american",
        "sandwich"
    ],
    "wof:name":"Subway",
    "wof:placetype":"venue"
},
  "geometry": {"coordinates":[-81.485255,40.858225],"type":"Point"}
}