{
  "type": "Feature",
  "properties": {
    "addr:full": "500 Southpark Center Cleveland OH 44136",
    "addr:housenumber": "500",
    "addr:postcode": "44136",
    "addr:street": "Southpark Center",
    "iso:country": "US",
    "sg:address": "500 Southpark Center",
    "sg:city": "Cleveland",
    "sg:classifiers": [
      {
        "category": "Shopping",
        "type": "Retail Goods"
      },
      {
        "category": "Shopping",
        "subcategory": "Gifts \u0026 Souvenirs",
        "type": "Retail Goods"
      }
    ],
    "sg:phone": "+1 440 238 8191",
    "sg:postcode": "44136",
    "sg:province": "OH",
    "sg:tags": [
      "shop",
      "merchandise"
    ],
    "wof:name": "New England Home Direct",
    "wof:placetype": "venue"
  },
  "geometry": {"coordinates":[-81.820449,41.310925],"type":"Point"}
}
