{
  "type": "Feature",
  "properties": {
    "addr:full": "2175 Coventry Rd Cleveland OH 44118",
    "addr:housenumber": "2175",
    "addr:postcode": "44118",
    "addr:street": "Coventry Rd",
    "iso:country": "US",
    "sg:address": "2175 Coventry Rd",
    "sg:city": "Cleveland",
    "sg:classifiers": [
      {
        "category": "Organizations",
        "subcategory": "Religious Organization",
        "type": "Services"
      }
    ],
    "sg:phone": "+1 216 321 3178",
    "sg:postcode": "44118",
    "sg:province": "OH",
    "sg:tags": [
      "church"
    ],
    "wof:name": "St Anns Parish",
    "wof:placetype": "venue"
  },
  "geometry": {"coordinates":[-81.57989,41.499231],"type":"Point"}
}
