{
  "type": "Feature",
  "properties": {
    "iso:country":"US",
    "sg:address":"128 W Perkins Ave",
    "sg:city":"Sandusky",
    "sg:classifiers":[
        {
            "category":"Personal",
            "subcategory":"Beauty Salon",
            "type":"Services"
        }
    ],
    "sg:phone":"+1 419 625 3080",
    "sg:postcode":"44870",
    "sg:province":"OH",
    "sg:tags":[
        "hair"
    ],
    "wof:name":"Oliver's Hair Salon",
    "wof:placetype":"venue"
},
  "geometry": {"coordinates":[-82.69941300000001,41.432763],"type":"Point"}
}