{
  "type": "Feature",
  "properties": {
    "iso:country":"US",
    "sg:address":"3624 W Market St",
    "sg:city":"Fairlawn",
    "sg:classifiers":[
        {
            "category":"Health Services",
            "subcategory":"Medical Lab",
            "type":"Services"
        }
    ],
    "sg:phone":"+1 330 665 2563",
    "sg:postcode":"44333",
    "sg:province":"OH",
    "sg:tags":[
        "laboratory"
    ],
    "wof:name":"Quest Diagnostics Inc",
    "wof:placetype":"venue"
},
  "geometry": {"coordinates":[-81.630656,41.13575],"type":"Point"}
}