{
  "type": "Feature",
  "properties": {
    "addr:full": "14450 Co Rd B Wauseon OH 43567",
    "addr:housenumber": "14450",
    "addr:postcode": "43567",
    "addr:street": "Co Rd",
    "iso:country": "US",
    "sg:address": "14450 Co Rd B",
    "sg:city": "Wauseon",
    "sg:classifiers": [
      {
        "category": "Shopping",
        "subcategory": "Beauty \u0026 Cosmetics",
        "type": "Retail Goods"
      }
    ],
    "sg:phone": "+1 419 337 0994",
    "sg:postcode": "43567",
    "sg:province": "OH",
    "sg:tags": [
      "merchandise"
    ],
    "wof:name": "Sue Andrews",
    "wof:placetype": "venue"
  },
  "geometry": {"coordinates":[-84.142766,41.50072],"type":"Point"}
}
