{
  "type": "Feature",
  "properties": {
    "iso:country":"US",
    "sg:address":"2943 Eastern Ave",
    "sg:city":"Cincinnati",
    "sg:classifiers":[
        {
            "category":"Health Services",
            "subcategory":"Doctor",
            "type":"Services"
        }
    ],
    "sg:phone":"+1 513 533 9990",
    "sg:postcode":"45226",
    "sg:province":"OH",
    "sg:tags":[
        "medical"
    ],
    "wof:name":"Hehman & Bramlage MD Inc",
    "wof:placetype":"venue"
},
  "geometry": {"coordinates":[-84.448342,39.120683],"type":"Point"}
}