{
  "type": "Feature",
  "properties": {
    "addr:full":"519 Avon Belden Rd Avon Lake OH 44012",
    "addr:housenumber":"519",
    "addr:postcode":"44012",
    "addr:street":"Avon Belden Rd",
    "iso:country":"US",
    "sg:address":"519 Avon Belden Rd",
    "sg:city":"Avon Lake",
    "sg:classifiers":[
        {
            "category":"Restaurant",
            "type":"Food & Drink"
        }
    ],
    "sg:menulink":"http://www.allmenus.com/oh/avon-lake/170139-burger-king/menu/",
    "sg:phone":"+1 440 933 6668",
    "sg:postcode":"44012",
    "sg:province":"OH",
    "sg:tags":[
        "burger",
        "american"
    ],
    "wof:name":"Burger King",
    "wof:placetype":"venue"
},
  "geometry": {"coordinates":[-82.01898300000001,41.492155],"type":"Point"}
}