{
  "type": "Feature",
  "properties": {
    "addr:full": "6717 Deer Ct Cleveland OH 44146",
    "addr:housenumber": "6717",
    "addr:postcode": "44146",
    "addr:street": "Deer Ct",
    "iso:country": "US",
    "sg:address": "6717 Deer Ct",
    "sg:city": "Cleveland",
    "sg:classifiers": [
      {
        "category": "Personal",
        "subcategory": "Barber",
        "type": "Services"
      }
    ],
    "sg:phone": "+1 216 752 3066",
    "sg:postcode": "44146",
    "sg:province": "OH",
    "wof:name": "Lawrence N Crump",
    "wof:placetype": "venue"
  },
  "geometry": {"coordinates":[-81.497566,41.375646],"type":"Point"}
}
