{
  "type": "Feature",
  "properties": {
    "addr:full":"47 E Lincoln St Columbus OH 43215",
    "addr:housenumber":"47",
    "addr:postcode":"43215",
    "addr:street":"E Lincoln St",
    "iso:country":"US",
    "sg:address":"47 E Lincoln St",
    "sg:city":"Columbus",
    "sg:classifiers":[
        {
            "category":"Building & Trades",
            "subcategory":"Construction",
            "type":"Services"
        }
    ],
    "sg:phone":"+1 614 280 8900",
    "sg:postcode":"43215",
    "sg:province":"OH",
    "sg:tags":[
        "home",
        "remodeling",
        "family",
        "contractor"
    ],
    "sg:website":"www.bakerhenning.com",
    "wof:name":"Baker Henning Productions Inc",
    "wof:placetype":"venue"
},
  "geometry": {"coordinates":[-83.002691,39.976943],"type":"Point"}
}