{
  "type": "Feature",
  "properties": {
    "iso:country":"US",
    "sg:address":"1257 Poth Rd",
    "sg:city":"Mansfield",
    "sg:classifiers":[
        {
            "category":"Organizations",
            "subcategory":"Religious Organization",
            "type":"Services"
        }
    ],
    "sg:phone":"+1 419 747 9818",
    "sg:postcode":"44906",
    "sg:province":"OH",
    "sg:tags":[
        "clergy"
    ],
    "wof:name":"Glenn M Phillips",
    "wof:placetype":"venue"
},
  "geometry": {"coordinates":[-82.560242,40.79434],"type":"Point"}
}