{
  "type": "Feature",
  "properties": {
    "iso:country":"US",
    "sg:address":"8303 Shadyside Ln",
    "sg:city":"Cincinnati",
    "sg:classifiers":[
        {
            "category":"Professional",
            "subcategory":"Computer Services",
            "type":"Services"
        }
    ],
    "sg:phone":"+1 513 779 2801",
    "sg:postcode":"45241",
    "sg:province":"OH",
    "wof:name":"Bull Worldwide Information",
    "wof:placetype":"venue"
},
  "geometry": {"coordinates":[-84.35420999999999,39.300228],"type":"Point"}
}