{
  "type": "Feature",
  "properties": {
    "addr:full": "421 Hampshire Rd Akron OH 44313",
    "addr:housenumber": "421",
    "addr:postcode": "44313",
    "addr:street": "Hampshire Rd",
    "iso:country": "US",
    "sg:address": "421 Hampshire Rd",
    "sg:city": "Akron",
    "sg:classifiers": [
      {
        "category": "Building \u0026 Trades",
        "subcategory": "Plumbing",
        "type": "Services"
      }
    ],
    "sg:phone": "+1 330 322 8694",
    "sg:postcode": "44313",
    "sg:province": "OH",
    "sg:tags": [
      "contractor"
    ],
    "wof:name": "Pro Temp Refrigeration",
    "wof:placetype": "venue"
  },
  "geometry": {"coordinates":[-81.602819,41.117572],"type":"Point"}
}
