{
  "type": "Feature",
  "properties": {
    "addr:full": "1543 Niles Cortland Rd SE Warren OH 44484",
    "addr:housenumber": "1543",
    "addr:postcode": "44484",
    "addr:street": "Niles Cortland Rd Se",
    "iso:country": "US",
    "sg:address": "1543 Niles Cortland Rd SE",
    "sg:city": "Warren",
    "sg:classifiers": [
      {
        "category": "Education",
        "subcategory": "Dance Studio",
        "type": "Public Place"
      }
    ],
    "sg:phone": "+1 330 505 4187",
    "sg:postcode": "44484",
    "sg:province": "OH",
    "sg:tags": [
      "instruction",
      "dancing"
    ],
    "wof:name": "Krysti's Dance Academy",
    "wof:placetype": "venue"
  },
  "geometry": {"coordinates":[-80.740384,41.223285],"type":"Point"}
}
