{
  "type": "Feature",
  "properties": {
    "iso:country":"US",
    "sg:address":"200 E 2nd St",
    "sg:city":"Salem",
    "sg:classifiers":[
        {
            "category":"Professional",
            "subcategory":"Accounting & Tax Preparation",
            "type":"Services"
        }
    ],
    "sg:phone":"+1 330 337 3158",
    "sg:postcode":"44460",
    "sg:province":"OH",
    "sg:tags":[
        "accountant"
    ],
    "wof:name":"Lee Palmer CPA",
    "wof:placetype":"venue"
},
  "geometry": {"coordinates":[-80.855357,40.902103],"type":"Point"}
}