{
  "type": "Feature",
  "properties": {
    "iso:country":"US",
    "sg:address":"42 W Water St",
    "sg:city":"Chillicothe",
    "sg:classifiers":[
        {
            "category":"Food & Beverages",
            "subcategory":"Specialty",
            "type":"Retail Goods"
        }
    ],
    "sg:phone":"+1 740 775 7776",
    "sg:postcode":"45601",
    "sg:province":"OH",
    "wof:name":"Olde Canal Health Foods",
    "wof:placetype":"venue"
},
  "geometry": {"coordinates":[-82.983891,39.335565],"type":"Point"}
}