{
  "type": "Feature",
  "properties": {
    "addr:full": "42 W Water St Chillicothe OH 45601",
    "addr:housenumber": "42",
    "addr:postcode": "45601",
    "addr:street": "W Water St",
    "iso:country": "US",
    "sg:address": "42 W Water St",
    "sg:city": "Chillicothe",
    "sg:classifiers": [
      {
        "category": "Food \u0026 Beverages",
        "subcategory": "Specialty",
        "type": "Retail Goods"
      }
    ],
    "sg:phone": "+1 740 775 7776",
    "sg:postcode": "45601",
    "sg:province": "OH",
    "wof:name": "Olde Canal Health Foods",
    "wof:placetype": "venue"
  },
  "geometry": {"coordinates":[-82.983891,39.335565],"type":"Point"}
}
