{
  "type": "Feature",
  "properties": {
    "addr:full":"1469 State Rte 28 Loveland OH 45140",
    "addr:housenumber":"1469",
    "addr:postcode":"45140",
    "addr:street":"State Rte 28",
    "iso:country":"US",
    "sg:address":"1469 State Rte 28",
    "sg:city":"Loveland",
    "sg:classifiers":[
        {
            "category":"Retail",
            "subcategory":"Repair Shop",
            "type":"Services"
        }
    ],
    "sg:phone":"+1 513 722 8229",
    "sg:postcode":"45140",
    "sg:province":"OH",
    "sg:tags":[
        "welding"
    ],
    "wof:name":"T & T Welding",
    "wof:placetype":"venue"
},
  "geometry": {"coordinates":[-84.197886,39.216487],"type":"Point"}
}