{
  "type": "Feature",
  "properties": {
    "iso:country":"US",
    "sg:address":"645 Nordyke Rd",
    "sg:city":"Cincinnati",
    "sg:classifiers":[
        {
            "category":"Education",
            "subcategory":"University",
            "type":"Public Place"
        }
    ],
    "sg:phone":"+1 513 761 2020",
    "sg:postcode":"45255",
    "sg:province":"OH",
    "sg:tags":[
        "college"
    ],
    "wof:name":"Cinti College of Mortuary Science",
    "wof:placetype":"venue"
},
  "geometry": {"coordinates":[-84.31880200000001,39.0494],"type":"Point"}
}