{
  "type": "Feature",
  "properties": {
    "addr:full": "122 Maple Ave Woodsfield OH 43793",
    "addr:housenumber": "122",
    "addr:postcode": "43793",
    "addr:street": "Maple Ave",
    "iso:country": "US",
    "sg:address": "122 Maple Ave",
    "sg:city": "Woodsfield",
    "sg:classifiers": [
      {
        "category": "Home \u0026 Garden",
        "subcategory": "Carpets \u0026 Floor Coverings",
        "type": "Retail Goods"
      }
    ],
    "sg:phone": "+1 740 472 0520",
    "sg:postcode": "43793",
    "sg:province": "OH",
    "wof:name": "Fetzers Carpet \u0026 Floor",
    "wof:placetype": "venue"
  },
  "geometry": {"coordinates":[-81.110931,39.766732],"type":"Point"}
}
