{
  "type": "Feature",
  "properties": {
    "iso:country":"US",
    "sg:address":"122 Maple Ave",
    "sg:city":"Woodsfield",
    "sg:classifiers":[
        {
            "category":"Home & Garden",
            "subcategory":"Carpets & Floor Coverings",
            "type":"Retail Goods"
        }
    ],
    "sg:phone":"+1 740 472 0520",
    "sg:postcode":"43793",
    "sg:province":"OH",
    "wof:name":"Fetzers Carpet & Floor",
    "wof:placetype":"venue"
},
  "geometry": {"coordinates":[-81.11093099999999,39.766732],"type":"Point"}
}