{
  "type": "Feature",
  "properties": {
    "iso:country":"US",
    "sg:address":"1314 Sill Rd",
    "sg:city":"Ashtabula",
    "sg:classifiers":[
        {
            "category":"Wholesale",
            "subcategory":"Scrap",
            "type":"Manufacturing & Wholesale Goods"
        }
    ],
    "sg:phone":"+1 440 998 2123",
    "sg:postcode":"44004",
    "sg:province":"OH",
    "sg:tags":[
        "material"
    ],
    "wof:name":"Sill Road Auto Wrecking",
    "wof:placetype":"venue"
},
  "geometry": {"coordinates":[-80.72318300000001,41.894659],"type":"Point"}
}