{
  "type": "Feature",
  "properties": {
    "addr:full": "5367 Co Rd 177 Bellevue OH 44811",
    "addr:housenumber": "5367;177",
    "addr:postcode": "44811",
    "addr:street": "Co Rd",
    "iso:country": "US",
    "sg:address": "5367 Co Rd 177",
    "sg:city": "Bellevue",
    "sg:phone": "+1 419 483 6194",
    "sg:postcode": "44811",
    "sg:province": "OH",
    "sg:tags": [
      "farm",
      "corn"
    ],
    "wof:name": "Vickery Farms",
    "wof:placetype": "venue"
  },
  "geometry": {"coordinates":[-82.919469,41.277464],"type":"Point"}
}
