{
  "type": "Feature",
  "properties": {
    "iso:country":"US",
    "sg:address":"4357 Alexander Rd",
    "sg:city":"Atwater",
    "sg:classifiers":[
        {
            "category":"Farming",
            "subcategory":"Farm",
            "type":"Manufacturing & Wholesale Goods"
        }
    ],
    "sg:phone":"+1 330 325 7796",
    "sg:postcode":"44201",
    "sg:province":"OH",
    "sg:tags":[
        "crop",
        "general"
    ],
    "wof:name":"Mays Farm",
    "wof:placetype":"venue"
},
  "geometry": {"coordinates":[-81.24301800000001,41.025724],"type":"Point"}
}