{
  "type": "Feature",
  "properties": {
    "addr:full":"5353 Dixie Hwy Fairfield OH 45014",
    "addr:housenumber":"5353",
    "addr:postcode":"45014",
    "addr:street":"Dixie Hwy",
    "iso:country":"US",
    "sg:address":"5353 Dixie Hwy",
    "sg:city":"Fairfield",
    "sg:classifiers":[
        {
            "category":"Recreation",
            "subcategory":"Picnic Area",
            "type":"Entertainment"
        },
        {
            "category":"Organizations",
            "subcategory":"Professional Association",
            "type":"Services"
        }
    ],
    "sg:phone":"+1 513 829 6666",
    "sg:postcode":"45014",
    "sg:province":"OH",
    "sg:tags":[
        "bureau",
        "agency",
        "place",
        "amusement",
        "arcade"
    ],
    "wof:name":"Dd Dolls",
    "wof:placetype":"venue"
},
  "geometry": {"coordinates":[-84.528391,39.336227],"type":"Point"}
}