{
  "type": "Feature",
  "properties": {
    "addr:full": "307 Clark St Cambridge OH 43725",
    "addr:housenumber": "307",
    "addr:postcode": "43725",
    "addr:street": "Clark St",
    "iso:country": "US",
    "sg:address": "307 Clark St",
    "sg:city": "Cambridge",
    "sg:classifiers": [
      {
        "category": "Food \u0026 Beverages",
        "subcategory": "Groceries \u0026 Convenience Stores",
        "type": "Retail Goods"
      }
    ],
    "sg:phone": "+1 740 432 1789",
    "sg:postcode": "43725",
    "sg:province": "OH",
    "wof:name": "Dairy Mart Convenience Store",
    "wof:placetype": "venue"
  },
  "geometry": {"coordinates":[-81.583816,40.027844],"type":"Point"}
}
