{
  "type": "Feature",
  "properties": {
    "iso:country":"US",
    "sg:address":"10603 Detroit Ave",
    "sg:city":"Cleveland",
    "sg:classifiers":[
        {
            "category":"Social Services",
            "type":"Services"
        }
    ],
    "sg:phone":"+1 216 226 6090",
    "sg:postcode":"44102",
    "sg:province":"OH",
    "sg:tags":[
        "senior",
        "citizen"
    ],
    "wof:name":"Acacia Place Adult Day Ctr",
    "wof:placetype":"venue"
},
  "geometry": {"coordinates":[-81.760828,41.481509],"type":"Point"}
}