{
  "type": "Feature",
  "properties": {
    "iso:country":"US",
    "sg:address":"1279 Pineview Trl",
    "sg:city":"Newark",
    "sg:classifiers":[
        {
            "category":"Shopping",
            "subcategory":"Shoes",
            "type":"Retail Goods"
        }
    ],
    "sg:phone":"+1 740 366 8129",
    "sg:postcode":"43055",
    "sg:province":"OH",
    "sg:tags":[
        "athletic"
    ],
    "wof:name":"Second Sole",
    "wof:placetype":"venue"
},
  "geometry": {"coordinates":[-82.454067,40.079134],"type":"Point"}
}