{
  "type": "Feature",
  "properties": {
    "addr:full":"401 W Boundary St Perrysburg OH 43551",
    "addr:housenumber":"401",
    "addr:postcode":"43551",
    "addr:street":"W Boundary St",
    "iso:country":"US",
    "sg:address":"401 W Boundary St",
    "sg:city":"Perrysburg",
    "sg:classifiers":[
        {
            "category":"Education",
            "subcategory":"School",
            "type":"Public Place"
        }
    ],
    "sg:phone":"+1 419 874 8721",
    "sg:postcode":"43551",
    "sg:province":"OH",
    "wof:name":"Frank Elementary School",
    "wof:placetype":"venue"
},
  "geometry": {"coordinates":[-83.638852,41.551641],"type":"Point"}
}