{
  "type": "Feature",
  "properties": {
    "addr:full": "54760 Twp Rd 90 Fresno OH 43824",
    "addr:housenumber": "90",
    "addr:postcode": "54760;43824",
    "addr:street": "Twp Rd",
    "iso:country": "US",
    "sg:address": "54760 Twp Rd 90",
    "sg:city": "Fresno",
    "sg:classifiers": [
      {
        "category": "Manufacturing",
        "subcategory": "Food",
        "type": "Manufacturing \u0026 Wholesale Goods"
      }
    ],
    "sg:phone": "+1 740 545 6002",
    "sg:postcode": "43824",
    "sg:province": "OH",
    "sg:tags": [
      "cheese",
      "processor",
      "mfg"
    ],
    "sg:website": "www.pearlvalleycheese.com",
    "wof:name": "Pearl Valley Cheese Inc",
    "wof:placetype": "venue"
  },
  "geometry": {"coordinates":[-81.729478,40.369217],"type":"Point"}
}
