{
  "type": "Feature",
  "properties": {
    "iso:country":"US",
    "sg:address":"54760 Twp Rd 90",
    "sg:city":"Fresno",
    "sg:classifiers":[
        {
            "category":"Manufacturing",
            "subcategory":"Food",
            "type":"Manufacturing & Wholesale Goods"
        }
    ],
    "sg:phone":"+1 740 545 6002",
    "sg:postcode":"43824",
    "sg:province":"OH",
    "sg:tags":[
        "cheese",
        "processor",
        "mfg"
    ],
    "sg:website":"www.pearlvalleycheese.com",
    "wof:name":"Pearl Valley Cheese Inc",
    "wof:placetype":"venue"
},
  "geometry": {"coordinates":[-81.729478,40.369217],"type":"Point"}
}