{
  "type": "Feature",
  "properties": {
    "iso:country":"US",
    "sg:address":"73 W Royal Forest Blvd",
    "sg:city":"Columbus",
    "sg:classifiers":[
        {
            "category":"Insurance",
            "subcategory":"Insurance Agent",
            "type":"Services"
        }
    ],
    "sg:phone":"+1 614 268 7721",
    "sg:postcode":"43214",
    "sg:province":"OH",
    "wof:name":"Wahistrom Group",
    "wof:placetype":"venue"
},
  "geometry": {"coordinates":[-83.020436,40.060463],"type":"Point"}
}