{
  "type": "Feature",
  "properties": {
    "addr:full":"29101 Health Campus Dr Cleveland OH 44145",
    "addr:postcode":"44145",
    "addr:street":"Campus Dr",
    "iso:country":"US",
    "sg:address":"29101 Health Campus Dr",
    "sg:city":"Cleveland",
    "sg:classifiers":[
        {
            "category":"Health Services",
            "subcategory":"Doctor",
            "type":"Services"
        }
    ],
    "sg:phone":"+1 440 835 6186",
    "sg:postcode":"44145",
    "sg:province":"OH",
    "sg:tags":[
        "physician",
        "surgeon"
    ],
    "wof:name":"E W Hilton MD",
    "wof:placetype":"venue"
},
  "geometry": {"coordinates":[-81.945255,41.436987],"type":"Point"}
}