{
  "type": "Feature",
  "properties": {
    "iso:country":"US",
    "sg:address":"24202 Front St",
    "sg:city":"Grand Rapids",
    "sg:classifiers":[
        {
            "category":"Professional",
            "subcategory":"Business Services",
            "type":"Services"
        }
    ],
    "sg:phone":"+1 419 832 0902",
    "sg:postcode":"43522",
    "sg:province":"OH",
    "sg:tags":[
        "interior",
        "consultant",
        "design",
        "decorator"
    ],
    "wof:name":"Cottage On The River",
    "wof:placetype":"venue"
},
  "geometry": {"coordinates":[-83.865165,41.412881],"type":"Point"}
}