{
  "type": "Feature",
  "properties": {
    "iso:country":"US",
    "sg:address":"672 W Liberty St",
    "sg:city":"Medina",
    "sg:classifiers":[
        {
            "category":"Banks & Credit Unions",
            "subcategory":"Investment Brokerage",
            "type":"Services"
        }
    ],
    "sg:phone":"+1 330 721 0100",
    "sg:postcode":"44256",
    "sg:province":"OH",
    "sg:tags":[
        "security"
    ],
    "sg:website":"www.lauxco.com",
    "wof:name":"Laux & Co",
    "wof:placetype":"venue"
},
  "geometry": {"coordinates":[-81.874375,41.139051],"type":"Point"}
}