{
  "type": "Feature",
  "properties": {
    "addr:full": "672 W Liberty St Medina OH 44256",
    "addr:housenumber": "672",
    "addr:postcode": "44256",
    "addr:street": "W Liberty St",
    "iso:country": "US",
    "sg:address": "672 W Liberty St",
    "sg:city": "Medina",
    "sg:classifiers": [
      {
        "category": "Banks \u0026 Credit Unions",
        "subcategory": "Investment Brokerage",
        "type": "Services"
      }
    ],
    "sg:phone": "+1 330 721 0100",
    "sg:postcode": "44256",
    "sg:province": "OH",
    "sg:tags": [
      "security"
    ],
    "sg:website": "www.lauxco.com",
    "wof:name": "Laux \u0026 Co",
    "wof:placetype": "venue"
  },
  "geometry": {"coordinates":[-81.874375,41.139051],"type":"Point"}
}
