{
  "type": "Feature",
  "properties": {
    "addr:full": "433 5th St Portsmouth OH 45662",
    "addr:housenumber": "433",
    "addr:postcode": "45662",
    "addr:street": "5Th St",
    "iso:country": "US",
    "sg:address": "433 5th St",
    "sg:city": "Portsmouth",
    "sg:classifiers": [
      {
        "category": "Autos \u0026 Motor Vehicles",
        "subcategory": "Fuel \u0026 Gas Station",
        "type": "Retail Goods"
      }
    ],
    "sg:phone": "+1 740 353 5235",
    "sg:postcode": "45662",
    "sg:province": "OH",
    "sg:tags": [
      "station",
      "construction",
      "gasoline"
    ],
    "wof:name": "Thompsons Petroleum Services",
    "wof:placetype": "venue"
  },
  "geometry": {"coordinates":[-83.003509,38.73427],"type":"Point"}
}
