{
  "type": "Feature",
  "properties": {
    "iso:country":"US",
    "sg:address":"2303 Gilbert Ave",
    "sg:city":"Cincinnati",
    "sg:classifiers":[
        {
            "category":"Real Estate",
            "subcategory":"Real Estate Agent",
            "type":"Services"
        }
    ],
    "sg:phone":"+1 513 861 9999",
    "sg:postcode":"45206",
    "sg:province":"OH",
    "sg:tags":[
        "residential",
        "commercial",
        "broker"
    ],
    "wof:name":"Pilot Realty",
    "wof:placetype":"venue"
},
  "geometry": {"coordinates":[-84.491688,39.123649],"type":"Point"}
}