{
  "type": "Feature",
  "properties": {
    "iso:country":"US",
    "sg:address":"23215 Commerce Park",
    "sg:city":"Cleveland",
    "sg:classifiers":[
        {
            "category":"Health Services",
            "subcategory":"Health Practitioner",
            "type":"Services"
        }
    ],
    "sg:phone":"+1 216 292 1400",
    "sg:postcode":"44122",
    "sg:province":"OH",
    "sg:tags":[
        "info",
        "eating",
        "disorder",
        "treatment"
    ],
    "wof:name":"Hull Institute LLC",
    "wof:placetype":"venue"
},
  "geometry": {"coordinates":[-81.50519799999999,41.46211],"type":"Point"}
}