{
  "type": "Feature",
  "properties": {
    "addr:full": "340 E Lincoln Way Lisbon OH 44432",
    "addr:housenumber": "340",
    "addr:postcode": "44432",
    "addr:street": "E Lincoln Way",
    "iso:country": "US",
    "sg:address": "340 E Lincoln Way",
    "sg:city": "Lisbon",
    "sg:classifiers": [
      {
        "category": "Retail",
        "subcategory": "Funeral Services",
        "type": "Services"
      }
    ],
    "sg:phone": "+1 330 424 7011",
    "sg:postcode": "44432",
    "sg:province": "OH",
    "sg:tags": [
      "director"
    ],
    "wof:name": "Weber Funeral Home",
    "wof:placetype": "venue"
  },
  "geometry": {"coordinates":[-80.763297,40.772055],"type":"Point"}
}
