{
  "type": "Feature",
  "properties": {
    "addr:full": "2306 N Ridge Rd Elyria OH 44035",
    "addr:housenumber": "2306",
    "addr:postcode": "44035",
    "addr:street": "N Ridge Rd",
    "iso:country": "US",
    "sg:address": "2306 N Ridge Rd",
    "sg:city": "Elyria",
    "sg:classifiers": [
      {
        "category": "Shopping",
        "subcategory": "Used Merchandise",
        "type": "Retail Goods"
      }
    ],
    "sg:phone": "+1 440 323 9837",
    "sg:postcode": "44035",
    "sg:province": "OH",
    "sg:tags": [
      "second",
      "store",
      "hand"
    ],
    "wof:name": "Second Hand Store",
    "wof:placetype": "venue"
  },
  "geometry": {"coordinates":[-82.116272,41.419033],"type":"Point"}
}
