{
  "type": "Feature",
  "properties": {
    "addr:full":"1146 Lawrence Dr Columbus OH 43207",
    "addr:housenumber":"1146",
    "addr:postcode":"43207",
    "addr:street":"Lawrence Dr",
    "iso:country":"US",
    "sg:address":"1146 Lawrence Dr",
    "sg:city":"Columbus",
    "sg:classifiers":[
        {
            "category":"Building & Trades",
            "subcategory":"Electrical",
            "type":"Services"
        }
    ],
    "sg:phone":"+1 614 989 3159",
    "sg:postcode":"43207",
    "sg:province":"OH",
    "sg:tags":[
        "electric",
        "contractor"
    ],
    "wof:name":"Gates Electric",
    "wof:placetype":"venue"
},
  "geometry": {"coordinates":[-82.96245500000001,39.92572],"type":"Point"}
}