{
  "type": "Feature",
  "properties": {
    "addr:full": "749 Brown Rd Columbus OH 43223",
    "addr:housenumber": "749",
    "addr:postcode": "43223",
    "addr:street": "Brown Rd",
    "iso:country": "US",
    "sg:address": "749 Brown Rd",
    "sg:city": "Columbus",
    "sg:classifiers": [
      {
        "category": "Building \u0026 Trades",
        "subcategory": "Plumbing",
        "type": "Services"
      }
    ],
    "sg:phone": "+1 614 279 4400",
    "sg:postcode": "43223",
    "sg:province": "OH",
    "sg:tags": [
      "air",
      "heating",
      "conditioning",
      "contractor"
    ],
    "wof:name": "Weaver Heating and Cooling",
    "wof:placetype": "venue"
  },
  "geometry": {"coordinates":[-83.037197,39.943085],"type":"Point"}
}
