{
  "type": "Feature",
  "properties": {
    "addr:full":"255 Altamont Rd Vermilion OH 44089",
    "addr:housenumber":"255",
    "addr:postcode":"44089",
    "addr:street":"Altamont Rd",
    "iso:country":"US",
    "sg:address":"255 Altamont Rd",
    "sg:city":"Vermilion",
    "sg:classifiers":[
        {
            "category":"Retail",
            "subcategory":"Laundry & Dry Cleaning",
            "type":"Services"
        }
    ],
    "sg:phone":"+1 440 985 1729",
    "sg:postcode":"44089",
    "sg:province":"OH",
    "sg:tags":[
        "cleaners",
        "rug",
        "carpet"
    ],
    "wof:name":"Lorain County Carpet Care",
    "wof:placetype":"venue"
},
  "geometry": {"coordinates":[-82.321512,41.427235],"type":"Point"}
}