{
  "type": "Feature",
  "properties": {
    "addr:full": "83 Duncan Ln Youngstown OH 44505",
    "addr:housenumber": "83",
    "addr:postcode": "44505",
    "addr:street": "Duncan Ln",
    "iso:country": "US",
    "sg:address": "83 Duncan Ln",
    "sg:city": "Youngstown",
    "sg:classifiers": [
      {
        "category": "Organizations",
        "subcategory": "Religious Organization",
        "type": "Services"
      }
    ],
    "sg:phone": "+1 330 743 0475",
    "sg:postcode": "44505",
    "sg:province": "OH",
    "sg:tags": [
      "clergy"
    ],
    "wof:name": "F P Walker",
    "wof:placetype": "venue"
  },
  "geometry": {"coordinates":[-80.595678,41.093673],"type":"Point"}
}
