{
  "type": "Feature",
  "properties": {
    "addr:full": "28637 Euclid Ave Wickliffe OH 44092",
    "addr:housenumber": "28637",
    "addr:postcode": "44092",
    "addr:street": "Euclid Ave",
    "iso:country": "US",
    "sg:address": "28637 Euclid Ave",
    "sg:city": "Wickliffe",
    "sg:classifiers": [
      {
        "category": "Professional",
        "type": "Services"
      }
    ],
    "sg:phone": "+1 440 516 5379",
    "sg:postcode": "44092",
    "sg:province": "OH",
    "sg:tags": [
      "establishment"
    ],
    "wof:name": "Ventus Networks LLC",
    "wof:placetype": "venue"
  },
  "geometry": {"coordinates":[-81.484014,41.599122],"type":"Point"}
}
