{
  "type": "Feature",
  "properties": {
    "addr:full":"398 S Shoop Ave Wauseon OH 43567",
    "addr:housenumber":"398",
    "addr:postcode":"43567",
    "addr:street":"S Shoop Ave",
    "iso:country":"US",
    "sg:address":"398 S Shoop Ave",
    "sg:city":"Wauseon",
    "sg:classifiers":[
        {
            "category":"Social Services",
            "subcategory":"Child Care",
            "type":"Services"
        }
    ],
    "sg:phone":"+1 419 335 6970",
    "sg:postcode":"43567",
    "sg:province":"OH",
    "sg:tags":[
        "day"
    ],
    "wof:name":"TLC Childcare",
    "wof:placetype":"venue"
},
  "geometry": {"coordinates":[-84.134326,41.544292],"type":"Point"}
}