{
  "type": "Feature",
  "properties": {
    "addr:full":"370 Cline Ave Mansfield OH 44907",
    "addr:housenumber":"370",
    "addr:postcode":"44907",
    "addr:street":"Cline Ave",
    "iso:country":"US",
    "sg:address":"370 Cline Ave",
    "sg:city":"Mansfield",
    "sg:classifiers":[
        {
            "category":"Health Services",
            "subcategory":"Dentist",
            "type":"Services"
        }
    ],
    "sg:phone":"+1 419 989 4568",
    "sg:postcode":"44907",
    "sg:province":"OH",
    "sg:tags":[
        "dentists-cosmetic",
        "dentistry"
    ],
    "wof:name":"Saltzgiver James L Jr DDS",
    "wof:placetype":"venue"
},
  "geometry": {"coordinates":[-82.52948000000001,40.747421],"type":"Point"}
}