{
  "type": "Feature",
  "properties": {
    "addr:full":"828 Oakwood Ave Napoleon OH 43545",
    "addr:housenumber":"828",
    "addr:postcode":"43545",
    "addr:street":"Oakwood Ave",
    "iso:country":"US",
    "sg:address":"828 Oakwood Ave",
    "sg:city":"Napoleon",
    "sg:classifiers":[
        {
            "category":"Shopping",
            "subcategory":"Florist",
            "type":"Retail Goods"
        }
    ],
    "sg:phone":"+1 419 592 0941",
    "sg:postcode":"43545",
    "sg:province":"OH",
    "wof:name":"LA Villa Florist",
    "wof:placetype":"venue"
},
  "geometry": {"coordinates":[-84.125377,41.39392],"type":"Point"}
}