{
  "type": "Feature",
  "properties": {
    "addr:full": "3924 Banks Rd Cincinnati OH 45245",
    "addr:housenumber": "3924",
    "addr:postcode": "45245",
    "addr:street": "Banks Rd",
    "iso:country": "US",
    "sg:address": "3924 Banks Rd",
    "sg:city": "Cincinnati",
    "sg:classifiers": [
      {
        "category": "Building \u0026 Trades",
        "subcategory": "Construction",
        "type": "Services"
      }
    ],
    "sg:phone": "+1 513 227 1761",
    "sg:postcode": "45245",
    "sg:province": "OH",
    "sg:tags": [
      "house"
    ],
    "wof:name": "Ya Construction LLC",
    "wof:placetype": "venue"
  },
  "geometry": {"coordinates":[-84.279482,39.059416],"type":"Point"}
}
