{
  "type": "Feature",
  "properties": {
    "addr:full":"3222 Hill Ave Toledo OH 43607",
    "addr:housenumber":"3222",
    "addr:postcode":"43607",
    "addr:street":"Hill Ave",
    "iso:country":"US",
    "sg:address":"3222 Hill Ave",
    "sg:city":"Toledo",
    "sg:classifiers":[
        {
            "category":"Professional",
            "type":"Services"
        }
    ],
    "sg:phone":"+1 419 531 0616",
    "sg:postcode":"43607",
    "sg:province":"OH",
    "sg:tags":[
        "establishment"
    ],
    "wof:name":"Efmark Serv Co",
    "wof:placetype":"venue"
},
  "geometry": {"coordinates":[-83.621217,41.638176],"type":"Point"}
}