{
  "type": "Feature",
  "properties": {
    "iso:country":"US",
    "sg:address":"130 W 2nd St",
    "sg:city":"Dayton",
    "sg:classifiers":[
        {
            "category":"Real Estate",
            "subcategory":"Real Estate Agent",
            "type":"Services"
        }
    ],
    "sg:phone":"+1 937 223 0388",
    "sg:postcode":"45402",
    "sg:province":"OH",
    "wof:name":"One Eleven Building Management",
    "wof:placetype":"venue"
},
  "geometry": {"coordinates":[-84.19518100000001,39.760428],"type":"Point"}
}