{
  "type": "Feature",
  "properties": {
    "iso:country":"US",
    "sg:address":"10298 Clipper Cove",
    "sg:city":"Aurora",
    "sg:classifiers":[
        {
            "category":"Building & Trades",
            "subcategory":"Construction",
            "type":"Services"
        }
    ],
    "sg:phone":"+1 330 562 7888",
    "sg:postcode":"44202",
    "sg:province":"OH",
    "sg:tags":[
        "house"
    ],
    "wof:name":"Yardmans Home Services Inc",
    "wof:placetype":"venue"
},
  "geometry": {"coordinates":[-81.399922,41.340239],"type":"Point"}
}