{
  "type": "Feature",
  "properties": {
    "addr:full": "10298 Clipper Cove Aurora OH 44202",
    "addr:housenumber": "10298",
    "addr:postcode": "44202",
    "addr:street": "Clipper Cove",
    "iso:country": "US",
    "sg:address": "10298 Clipper Cove",
    "sg:city": "Aurora",
    "sg:classifiers": [
      {
        "category": "Building \u0026 Trades",
        "subcategory": "Construction",
        "type": "Services"
      }
    ],
    "sg:phone": "+1 330 562 7888",
    "sg:postcode": "44202",
    "sg:province": "OH",
    "sg:tags": [
      "house"
    ],
    "wof:name": "Yardmans Home Services Inc",
    "wof:placetype": "venue"
  },
  "geometry": {"coordinates":[-81.399922,41.340239],"type":"Point"}
}
