{
  "type": "Feature",
  "properties": {
    "addr:full":"6640 Silica Rd Youngstown OH 44515",
    "addr:housenumber":"6640",
    "addr:postcode":"44515",
    "addr:street":"Silica Rd",
    "iso:country":"US",
    "sg:address":"6640 Silica Rd",
    "sg:city":"Youngstown",
    "sg:classifiers":[
        {
            "category":"Building & Trades",
            "subcategory":"Construction",
            "type":"Services"
        }
    ],
    "sg:phone":"+1 330 544 3816",
    "sg:postcode":"44515",
    "sg:province":"OH",
    "sg:tags":[
        "excavating",
        "contractor"
    ],
    "wof:name":"D H Excavating",
    "wof:placetype":"venue"
},
  "geometry": {"coordinates":[-80.79057299999999,41.116825],"type":"Point"}
}