{
  "type": "Feature",
  "properties": {
    "addr:full": "1010 Lincoln Hwy Wapakoneta OH 45895",
    "addr:housenumber": "1010",
    "addr:postcode": "45895",
    "addr:street": "Lincoln Hwy",
    "iso:country": "US",
    "sg:address": "1010 Lincoln Hwy",
    "sg:city": "Wapakoneta",
    "sg:classifiers": [
      {
        "category": "Health Services",
        "subcategory": "Nursing And Care Facility",
        "type": "Services"
      }
    ],
    "sg:phone": "+1 419 738 3711",
    "sg:postcode": "45895",
    "sg:province": "OH",
    "sg:tags": [
      "skilled"
    ],
    "wof:name": "Wapakoneta Manor",
    "wof:placetype": "venue"
  },
  "geometry": {"coordinates":[-84.202706,40.580948],"type":"Point"}
}
