{
  "type": "Feature",
  "properties": {
    "addr:full":"338 Marie Ct Harrison OH 45030",
    "addr:housenumber":"338",
    "addr:postcode":"45030",
    "addr:street":"Marie Ct",
    "iso:country":"US",
    "sg:address":"338 Marie Ct",
    "sg:city":"Harrison",
    "sg:classifiers":[
        {
            "category":"Banks & Credit Unions",
            "subcategory":"Financial Services",
            "type":"Services"
        }
    ],
    "sg:phone":"+1 513 367 7999",
    "sg:postcode":"45030",
    "sg:province":"OH",
    "sg:tags":[
        "investor"
    ],
    "wof:name":"Impressive Investment Group Lt",
    "wof:placetype":"venue"
},
  "geometry": {"coordinates":[-84.811415,39.257066],"type":"Point"}
}