{
  "type": "Feature",
  "properties": {
    "addr:full":"4035 Douglas Rd Toledo OH 43613",
    "addr:housenumber":"4035",
    "addr:postcode":"43613",
    "addr:street":"Douglas Rd",
    "iso:country":"US",
    "sg:address":"4035 Douglas Rd",
    "sg:city":"Toledo",
    "sg:classifiers":[
        {
            "category":"Banks & Credit Unions",
            "subcategory":"Bank",
            "type":"Services"
        }
    ],
    "sg:phone":"+1 419 473 0528",
    "sg:postcode":"43613",
    "sg:province":"OH",
    "wof:name":"Fifth Third Bank",
    "wof:placetype":"venue"
},
  "geometry": {"coordinates":[-83.60390099999999,41.692981],"type":"Point"}
}