{
  "type": "Feature",
  "properties": {
    "addr:full":"661 E Perry St Salem OH 44460",
    "addr:housenumber":"661",
    "addr:postcode":"44460",
    "addr:street":"E Perry St",
    "iso:country":"US",
    "sg:address":"661 E Perry St",
    "sg:city":"Salem",
    "sg:classifiers":[
        {
            "category":"Freight",
            "type":"Transportation"
        }
    ],
    "sg:phone":"+1 330 332 5618",
    "sg:postcode":"44460",
    "sg:province":"OH",
    "sg:tags":[
        "operator",
        "local",
        "trucking"
    ],
    "wof:name":"G & D Trucking",
    "wof:placetype":"venue"
},
  "geometry": {"coordinates":[-80.84981000000001,40.89283],"type":"Point"}
}