{
  "type": "Feature",
  "properties": {
    "addr:full":"5017 Cemetery Rd Hilliard OH 43026",
    "addr:housenumber":"5017",
    "addr:postcode":"43026",
    "addr:street":"Cemetery Rd",
    "iso:country":"US",
    "sg:address":"5017 Cemetery Rd",
    "sg:city":"Hilliard",
    "sg:classifiers":[
        {
            "category":"Wholesale",
            "subcategory":"Machinery & Supplies",
            "type":"Manufacturing & Wholesale Goods"
        }
    ],
    "sg:phone":"+1 614 876 9048",
    "sg:postcode":"43026",
    "sg:province":"OH",
    "wof:name":"Officelink Interiors LLC",
    "wof:placetype":"venue"
},
  "geometry": {"coordinates":[-83.149506,40.030731],"type":"Point"}
}