{
  "type": "Feature",
  "properties": {
    "addr:full": "5568 Twp Rd 84 Findlay OH 45840",
    "addr:housenumber": "84",
    "addr:postcode": "5568;45840",
    "addr:street": "Twp Rd",
    "iso:country": "US",
    "sg:address": "5568 Twp Rd 84",
    "sg:city": "Findlay",
    "sg:phone": "+1 419 859 2016",
    "sg:postcode": "45840",
    "sg:province": "OH",
    "sg:tags": [
      "farm",
      "corn",
      "wheat",
      "soybean"
    ],
    "wof:name": "Robert Burner",
    "wof:placetype": "venue"
  },
  "geometry": {"coordinates":[-83.772976,41.009815],"type":"Point"}
}
