{
  "type": "Feature",
  "properties": {
    "addr:full":"5977 Steiner Rd Sterling OH 44276",
    "addr:housenumber":"5977",
    "addr:postcode":"44276",
    "addr:street":"Steiner Rd",
    "iso:country":"US",
    "sg:address":"5977 Steiner Rd",
    "sg:city":"Sterling",
    "sg:phone":"+1 330 939 4961",
    "sg:postcode":"44276",
    "sg:province":"OH",
    "sg:tags":[
        "farm",
        "field",
        "corn",
        "soybean",
        "crop"
    ],
    "wof:name":"James Widmer",
    "wof:placetype":"venue"
},
  "geometry": {"coordinates":[-81.860821,40.931079],"type":"Point"}
}