{
  "type": "Feature",
  "properties": {
    "iso:country":"US",
    "sg:address":"9082 Long Rd",
    "sg:city":"Ostrander",
    "sg:classifiers":[
        {
            "category":"Building & Trades",
            "subcategory":"Construction",
            "type":"Services"
        }
    ],
    "sg:phone":"+1 740 666 1237",
    "sg:postcode":"43061",
    "sg:province":"OH",
    "sg:tags":[
        "excavation",
        "contractor"
    ],
    "wof:name":"Case Excavating",
    "wof:placetype":"venue"
},
  "geometry": {"coordinates":[-83.22223200000001,40.224612],"type":"Point"}
}