{
  "type": "Feature",
  "properties": {
    "addr:full": "9082 Long Rd Ostrander OH 43061",
    "addr:housenumber": "9082",
    "addr:postcode": "43061",
    "addr:street": "Long Rd",
    "iso:country": "US",
    "sg:address": "9082 Long Rd",
    "sg:city": "Ostrander",
    "sg:classifiers": [
      {
        "category": "Building \u0026 Trades",
        "subcategory": "Construction",
        "type": "Services"
      }
    ],
    "sg:phone": "+1 740 666 1237",
    "sg:postcode": "43061",
    "sg:province": "OH",
    "sg:tags": [
      "excavation",
      "contractor"
    ],
    "wof:name": "Case Excavating",
    "wof:placetype": "venue"
  },
  "geometry": {"coordinates":[-83.222232,40.224612],"type":"Point"}
}
