{
  "type": "Feature",
  "properties": {
    "iso:country":"US",
    "sg:address":"4550 Warrensville Center Rd",
    "sg:city":"Cleveland",
    "sg:classifiers":[
        {
            "category":"Restaurant",
            "type":"Food & Drink"
        }
    ],
    "sg:phone":"+1 216 518 9622",
    "sg:postcode":"44128",
    "sg:province":"OH",
    "sg:tags":[
        "eating"
    ],
    "wof:name":"Cinnamon Twist Cafe",
    "wof:placetype":"venue"
},
  "geometry": {"coordinates":[-81.53613,41.436171],"type":"Point"}
}