{
  "type": "Feature",
  "properties": {
    "addr:full": "4550 Warrensville Center Rd Cleveland OH 44128",
    "addr:housenumber": "4550",
    "addr:postcode": "44128",
    "addr:street": "Warrensville Center Rd",
    "iso:country": "US",
    "sg:address": "4550 Warrensville Center Rd",
    "sg:city": "Cleveland",
    "sg:classifiers": [
      {
        "category": "Restaurant",
        "type": "Food \u0026 Drink"
      }
    ],
    "sg:phone": "+1 216 518 9622",
    "sg:postcode": "44128",
    "sg:province": "OH",
    "sg:tags": [
      "eating"
    ],
    "wof:name": "Cinnamon Twist Cafe",
    "wof:placetype": "venue"
  },
  "geometry": {"coordinates":[-81.53613,41.436171],"type":"Point"}
}
