{
  "type": "Feature",
  "properties": {
    "addr:full":"2155 Parkway Blvd Alliance OH 44601",
    "addr:housenumber":"2155",
    "addr:postcode":"44601",
    "addr:street":"Parkway Blvd",
    "iso:country":"US",
    "sg:address":"2155 Parkway Blvd",
    "sg:city":"Alliance",
    "sg:classifiers":[
        {
            "category":"Health Services",
            "subcategory":"Doctor",
            "type":"Services"
        }
    ],
    "sg:phone":"+1 330 823 5830",
    "sg:postcode":"44601",
    "sg:province":"OH",
    "sg:tags":[
        "dentist"
    ],
    "wof:name":"Edward A Lohnes Inc",
    "wof:placetype":"venue"
},
  "geometry": {"coordinates":[-81.118071,40.901323],"type":"Point"}
}