{
  "type": "Feature",
  "properties": {
    "iso:country":"US",
    "sg:address":"1485 Kenny Rd",
    "sg:city":"Columbus",
    "sg:classifiers":[
        {
            "category":"Manufacturing",
            "subcategory":"Printing",
            "type":"Manufacturing & Wholesale Goods"
        }
    ],
    "sg:phone":"+1 614 299 8401",
    "sg:postcode":"43212",
    "sg:province":"OH",
    "sg:tags":[
        "book"
    ],
    "wof:name":"Educational Activities",
    "wof:placetype":"venue"
},
  "geometry": {"coordinates":[-83.035504,39.988343],"type":"Point"}
}