{
  "type": "Feature",
  "properties": {
    "iso:country":"US",
    "sg:address":"6736 Strip Ave NW",
    "sg:city":"North Canton",
    "sg:classifiers":[
        {
            "category":"Professional",
            "type":"Services"
        }
    ],
    "sg:phone":"+1 330 497 8442",
    "sg:postcode":"44720",
    "sg:province":"OH",
    "sg:tags":[
        "establishment"
    ],
    "wof:name":"Robert L Stark Inc",
    "wof:placetype":"venue"
},
  "geometry": {"coordinates":[-81.43203,40.87305],"type":"Point"}
}