{
  "type": "Feature",
  "properties": {
    "addr:full": "15060 W Sprague Rd Cleveland OH 44130",
    "addr:housenumber": "15060",
    "addr:postcode": "44130",
    "addr:street": "W Sprague Rd",
    "iso:country": "US",
    "sg:address": "15060 W Sprague Rd",
    "sg:city": "Cleveland",
    "sg:classifiers": [
      {
        "category": "Food \u0026 Beverages",
        "subcategory": "Groceries \u0026 Convenience Stores",
        "type": "Retail Goods"
      }
    ],
    "sg:phone": "+1 440 826 9042",
    "sg:postcode": "44130",
    "sg:province": "OH",
    "wof:name": "New Speedy Mart",
    "wof:placetype": "venue"
  },
  "geometry": {"coordinates":[-81.809215,41.350805],"type":"Point"}
}
