{
  "type": "Feature",
  "properties": {
    "iso:country":"US",
    "sg:address":"15060 W Sprague Rd",
    "sg:city":"Cleveland",
    "sg:classifiers":[
        {
            "category":"Food & Beverages",
            "subcategory":"Groceries & Convenience Stores",
            "type":"Retail Goods"
        }
    ],
    "sg:phone":"+1 440 826 9042",
    "sg:postcode":"44130",
    "sg:province":"OH",
    "wof:name":"New Speedy Mart",
    "wof:placetype":"venue"
},
  "geometry": {"coordinates":[-81.809215,41.350805],"type":"Point"}
}