{
  "type": "Feature",
  "properties": {
    "addr:full": "4025 Market St Youngstown OH 44512",
    "addr:housenumber": "4025",
    "addr:postcode": "44512",
    "addr:street": "Market St",
    "iso:country": "US",
    "sg:address": "4025 Market St",
    "sg:city": "Youngstown",
    "sg:classifiers": [
      {
        "category": "Health Services",
        "subcategory": "Clinic",
        "type": "Services"
      }
    ],
    "sg:phone": "+1 330 782 2218",
    "sg:postcode": "44512",
    "sg:province": "OH",
    "sg:tags": [
      "abortion"
    ],
    "wof:name": "Abortion Asssting In Yungstown",
    "wof:placetype": "venue"
  },
  "geometry": {"coordinates":[-80.662555,41.059207],"type":"Point"}
}
