{
  "type": "Feature",
  "properties": {
    "addr:full":"7545 Pingue Dr Columbus OH 43085",
    "addr:housenumber":"7545",
    "addr:postcode":"43085",
    "addr:street":"Pingue Dr",
    "iso:country":"US",
    "sg:address":"7545 Pingue Dr",
    "sg:city":"Columbus",
    "sg:classifiers":[
        {
            "category":"Manufacturing",
            "subcategory":"Tools & Machinery",
            "type":"Manufacturing & Wholesale Goods"
        },
        {
            "category":"Wholesale",
            "subcategory":"Electrical",
            "type":"Manufacturing & Wholesale Goods"
        }
    ],
    "sg:phone":"+1 614 888 3331",
    "sg:postcode":"43085",
    "sg:province":"OH",
    "sg:tags":[
        "equipment",
        "electric",
        "supply"
    ],
    "wof:name":"Kleinhuis North American Inc",
    "wof:placetype":"venue"
},
  "geometry": {"coordinates":[-82.98298,40.116315],"type":"Point"}
}