{
  "type": "Feature",
  "properties": {
    "addr:full": "853 Eastgate North Dr Cincinnati OH 45245",
    "addr:housenumber": "853",
    "addr:postcode": "45245",
    "addr:street": "Eastgate North Dr",
    "iso:country": "US",
    "sg:address": "853 Eastgate North Dr",
    "sg:city": "Cincinnati",
    "sg:classifiers": [
      {
        "category": "Restaurant",
        "type": "Food \u0026 Drink"
      }
    ],
    "sg:menulink": "http://www.allmenus.com/oh/union/98653-longhorn-steakhouse/menu/",
    "sg:phone": "+1 513 947 8882",
    "sg:postcode": "45245",
    "sg:province": "OH",
    "sg:tags": [
      "american",
      "steakhouse"
    ],
    "wof:name": "LongHorn Steakhouse",
    "wof:placetype": "venue"
  },
  "geometry": {"coordinates":[-84.271714,39.099085],"type":"Point"}
}
