{
  "type": "Feature",
  "properties": {
    "addr:full":"300 S Breiel Blvd Middletown OH 45044",
    "addr:housenumber":"300",
    "addr:postcode":"45044",
    "addr:street":"S Breiel Blvd",
    "iso:country":"US",
    "sg:address":"300 S Breiel Blvd",
    "sg:city":"Middletown",
    "sg:classifiers":[
        {
            "category":"Insurance",
            "subcategory":"Insurance Agent",
            "type":"Services"
        }
    ],
    "sg:phone":"+1 513 424 1102",
    "sg:postcode":"45044",
    "sg:province":"OH",
    "wof:name":"State Farm Insurance",
    "wof:placetype":"venue"
},
  "geometry": {"coordinates":[-84.35479599999999,39.509565],"type":"Point"}
}