{
  "type": "Feature",
  "properties": {
    "addr:full": "2645 Cleveland Ave NW Canton OH 44709",
    "addr:housenumber": "2645",
    "addr:postcode": "44709",
    "addr:street": "Cleveland Ave Nw",
    "iso:country": "US",
    "sg:address": "2645 Cleveland Ave NW",
    "sg:city": "Canton",
    "sg:classifiers": [
      {
        "category": "Health Services",
        "subcategory": "Clinic",
        "type": "Services"
      }
    ],
    "sg:phone": "+1 330 437 2910",
    "sg:postcode": "44709",
    "sg:province": "OH",
    "sg:tags": [
      "home"
    ],
    "sg:website": "www.cantonsummithomehealth.org",
    "wof:name": "Canton Summit Home Health Care",
    "wof:placetype": "venue"
  },
  "geometry": {"coordinates":[-81.385454,40.827147],"type":"Point"}
}
