{
  "type": "Feature",
  "properties": {
    "addr:full": "800 E Market St Akron OH 44305",
    "addr:housenumber": "800",
    "addr:postcode": "44305",
    "addr:street": "E Market St",
    "iso:country": "US",
    "sg:address": "800 E Market St",
    "sg:city": "Akron",
    "sg:classifiers": [
      {
        "category": "Social Services",
        "subcategory": "Child Care",
        "type": "Services"
      }
    ],
    "sg:phone": "+1 330 253 5031",
    "sg:postcode": "44305",
    "sg:province": "OH",
    "wof:name": "East Market Day Nursery",
    "wof:placetype": "venue"
  },
  "geometry": {"coordinates":[-81.493406,41.074659],"type":"Point"}
}
