{
  "type": "Feature",
  "properties": {
    "iso:country":"US",
    "sg:address":"304 W Main St",
    "sg:city":"Delta",
    "sg:classifiers":[
        {
            "category":"Manufacturing",
            "subcategory":"Printing",
            "type":"Manufacturing & Wholesale Goods"
        }
    ],
    "sg:phone":"+1 419 822 3187",
    "sg:postcode":"43515",
    "sg:province":"OH",
    "sg:tags":[
        "commercial"
    ],
    "wof:name":"Shipman Advertising Co",
    "wof:placetype":"venue"
},
  "geometry": {"coordinates":[-84.014281,41.573392],"type":"Point"}
}