{
  "type": "Feature",
  "properties": {
    "addr:full": "304 W Main St Delta OH 43515",
    "addr:housenumber": "304",
    "addr:postcode": "43515",
    "addr:street": "W Main St",
    "iso:country": "US",
    "sg:address": "304 W Main St",
    "sg:city": "Delta",
    "sg:classifiers": [
      {
        "category": "Manufacturing",
        "subcategory": "Printing",
        "type": "Manufacturing \u0026 Wholesale Goods"
      }
    ],
    "sg:phone": "+1 419 822 3187",
    "sg:postcode": "43515",
    "sg:province": "OH",
    "sg:tags": [
      "commercial"
    ],
    "wof:name": "Shipman Advertising Co",
    "wof:placetype": "venue"
  },
  "geometry": {"coordinates":[-84.014281,41.573392],"type":"Point"}
}
