{
  "type": "Feature",
  "properties": {
    "addr:full":"240 N Adams St Akron OH 44304",
    "addr:housenumber":"240",
    "addr:postcode":"44304",
    "addr:street":"N Adams St",
    "iso:country":"US",
    "sg:address":"240 N Adams St",
    "sg:city":"Akron",
    "sg:classifiers":[
        {
            "category":"Professional",
            "type":"Services"
        }
    ],
    "sg:phone":"+1 330 253 1523",
    "sg:postcode":"44304",
    "sg:province":"OH",
    "wof:name":"Guy Nathanial Cusma",
    "wof:placetype":"venue"
},
  "geometry": {"coordinates":[-81.499967,41.085259],"type":"Point"}
}