{
  "type": "Feature",
  "properties": {
    "iso:country":"US",
    "sg:address":"101 Akins Ct",
    "sg:city":"Springboro",
    "sg:classifiers":[
        {
            "category":"Manufacturing",
            "subcategory":"Toys & Sporting Goods",
            "type":"Manufacturing & Wholesale Goods"
        }
    ],
    "sg:phone":"+1 937 748 5199",
    "sg:postcode":"45066",
    "sg:province":"OH",
    "sg:tags":[
        "mfg"
    ],
    "wof:name":"Golfers Play Books",
    "wof:placetype":"venue"
},
  "geometry": {"coordinates":[-84.194929,39.560768],"type":"Point"}
}