{
  "type": "Feature",
  "properties": {
    "addr:full": "101 Akins Ct Springboro OH 45066",
    "addr:housenumber": "101",
    "addr:postcode": "45066",
    "addr:street": "Akins Ct",
    "iso:country": "US",
    "sg:address": "101 Akins Ct",
    "sg:city": "Springboro",
    "sg:classifiers": [
      {
        "category": "Manufacturing",
        "subcategory": "Toys \u0026 Sporting Goods",
        "type": "Manufacturing \u0026 Wholesale Goods"
      }
    ],
    "sg:phone": "+1 937 748 5199",
    "sg:postcode": "45066",
    "sg:province": "OH",
    "sg:tags": [
      "mfg"
    ],
    "wof:name": "Golfers Play Books",
    "wof:placetype": "venue"
  },
  "geometry": {"coordinates":[-84.194929,39.560768],"type":"Point"}
}
