{
  "type": "Feature",
  "properties": {
    "addr:full": "2135 E Central Ave Miamisburg OH 45342",
    "addr:housenumber": "2135",
    "addr:postcode": "45342",
    "addr:street": "E Central Ave",
    "iso:country": "US",
    "sg:address": "2135 E Central Ave",
    "sg:city": "Miamisburg",
    "sg:classifiers": [
      {
        "category": "Professional",
        "type": "Services"
      }
    ],
    "sg:phone": "+1 937 866 8017",
    "sg:postcode": "45342",
    "sg:province": "OH",
    "sg:tags": [
      "establishment"
    ],
    "wof:name": "Ardis",
    "wof:placetype": "venue"
  },
  "geometry": {"coordinates":[-84.252007,39.641993],"type":"Point"}
}
