{
  "type": "Feature",
  "properties": {
    "addr:full":"3055 W Sylvania Ave Toledo OH 43613",
    "addr:housenumber":"3055",
    "addr:postcode":"43613",
    "addr:street":"W Sylvania Ave",
    "iso:country":"US",
    "sg:address":"3055 W Sylvania Ave",
    "sg:city":"Toledo",
    "sg:classifiers":[
        {
            "category":"Health Services",
            "subcategory":"Podiatrist",
            "type":"Services"
        }
    ],
    "sg:phone":"+1 419 473 0125",
    "sg:postcode":"43613",
    "sg:province":"OH",
    "sg:website":"www.brentlrubinassoc.com",
    "wof:name":"Brent L Rubin & Assoc",
    "wof:placetype":"venue"
},
  "geometry": {"coordinates":[-83.617597,41.691832],"type":"Point"}
}