{
  "type": "Feature",
  "properties": {
    "addr:full": "220 N High St La Rue OH 43332",
    "addr:housenumber": "220",
    "addr:postcode": "43332",
    "addr:street": "N High St La Rue Oh",
    "iso:country": "US",
    "sg:address": "220 N High St",
    "sg:city": "La Rue",
    "sg:classifiers": [
      {
        "category": "Local Transit",
        "type": "Transportation"
      }
    ],
    "sg:phone": "+1 740 499 2022",
    "sg:postcode": "43332",
    "sg:province": "OH",
    "sg:tags": [
      "passenger",
      "ambulance"
    ],
    "wof:name": "Stofcheck Ambulance Service",
    "wof:placetype": "venue"
  },
  "geometry": {"coordinates":[-83.384262,40.579567],"type":"Point"}
}
