{
  "type": "Feature",
  "properties": {
    "addr:full":"903 Jean Ct Newark OH 43055",
    "addr:housenumber":"903",
    "addr:postcode":"43055",
    "addr:street":"Jean Ct",
    "iso:country":"US",
    "sg:address":"903 Jean Ct",
    "sg:city":"Newark",
    "sg:classifiers":[
        {
            "category":"Restaurant",
            "type":"Food & Drink"
        }
    ],
    "sg:phone":"+1 740 344 7101",
    "sg:postcode":"43055",
    "sg:province":"OH",
    "sg:tags":[
        "beverage"
    ],
    "wof:name":"Beverage Source",
    "wof:placetype":"venue"
},
  "geometry": {"coordinates":[-82.43353999999999,40.060376],"type":"Point"}
}