{
  "type": "Feature",
  "properties": {
    "iso:country":"US",
    "sg:address":"935 Shadyside Dr",
    "sg:city":"New Concord",
    "sg:classifiers":[
        {
            "category":"Farming",
            "subcategory":"Farm",
            "type":"Manufacturing & Wholesale Goods"
        }
    ],
    "sg:phone":"+1 740 826 4365",
    "sg:postcode":"43762",
    "sg:province":"OH",
    "wof:name":"White Farms",
    "wof:placetype":"venue"
},
  "geometry": {"coordinates":[-81.755332,40.005483],"type":"Point"}
}