{
  "type": "Feature",
  "properties": {
    "addr:full": "935 Shadyside Dr New Concord OH 43762",
    "addr:housenumber": "935",
    "addr:postcode": "43762",
    "addr:street": "Shadyside Dr",
    "iso:country": "US",
    "sg:address": "935 Shadyside Dr",
    "sg:city": "New Concord",
    "sg:classifiers": [
      {
        "category": "Farming",
        "subcategory": "Farm",
        "type": "Manufacturing \u0026 Wholesale Goods"
      }
    ],
    "sg:phone": "+1 740 826 4365",
    "sg:postcode": "43762",
    "sg:province": "OH",
    "wof:name": "White Farms",
    "wof:placetype": "venue"
  },
  "geometry": {"coordinates":[-81.755332,40.005483],"type":"Point"}
}
