{
  "type": "Feature",
  "properties": {
    "iso:country":"US",
    "sg:address":"709 W Perkins Ave",
    "sg:city":"Sandusky",
    "sg:classifiers":[
        {
            "category":"Personal",
            "subcategory":"Beauty Salon",
            "type":"Services"
        }
    ],
    "sg:phone":"+1 419 627 9427",
    "sg:postcode":"44870",
    "sg:province":"OH",
    "sg:tags":[
        "shop"
    ],
    "wof:name":"Fiesta Hair & Tanning",
    "wof:placetype":"venue"
},
  "geometry": {"coordinates":[-82.711253,41.433149],"type":"Point"}
}