{
  "type": "Feature",
  "properties": {
    "addr:full": "5860 Lewis Ave Toledo OH 43612",
    "addr:housenumber": "5860",
    "addr:postcode": "43612",
    "addr:street": "Lewis Ave",
    "iso:country": "US",
    "sg:address": "5860 Lewis Ave",
    "sg:city": "Toledo",
    "sg:classifiers": [
      {
        "category": "Shopping",
        "subcategory": "Used Merchandise",
        "type": "Retail Goods"
      }
    ],
    "sg:phone": "+1 419 476 0658",
    "sg:postcode": "43612",
    "sg:province": "OH",
    "sg:tags": [
      "antique"
    ],
    "wof:name": "Rocky's Antique Mall",
    "wof:placetype": "venue"
  },
  "geometry": {"coordinates":[-83.566511,41.723276],"type":"Point"}
}
