{
  "type": "Feature",
  "properties": {
    "addr:full": "111 S Nelson Ave Wilmington OH 45177",
    "addr:housenumber": "111",
    "addr:postcode": "45177",
    "addr:street": "S Nelson Ave",
    "iso:country": "US",
    "sg:address": "111 S Nelson Ave",
    "sg:city": "Wilmington",
    "sg:classifiers": [
      {
        "category": "Education",
        "subcategory": "College",
        "type": "Public Place"
      }
    ],
    "sg:phone": "+1 937 382 0901",
    "sg:postcode": "45177",
    "sg:province": "OH",
    "wof:name": "Ohio State Unvrsity EXT Clnton",
    "wof:placetype": "venue"
  },
  "geometry": {"coordinates":[-83.851884,39.443803],"type":"Point"}
}
