{
  "type": "Feature",
  "properties": {
    "addr:full":"1400 Hart Rd Lebanon OH 45036",
    "addr:housenumber":"1400",
    "addr:postcode":"45036",
    "addr:street":"Hart Rd",
    "iso:country":"US",
    "sg:address":"1400 Hart Rd",
    "sg:city":"Lebanon",
    "sg:classifiers":[
        {
            "category":"Manufacturing",
            "subcategory":"Furniture",
            "type":"Manufacturing & Wholesale Goods"
        }
    ],
    "sg:phone":"+1 513 932 1610",
    "sg:postcode":"45036",
    "sg:province":"OH",
    "sg:tags":[
        "household",
        "wood",
        "mfg"
    ],
    "wof:name":"Fister Enterprises",
    "wof:placetype":"venue"
},
  "geometry": {"coordinates":[-84.228168,39.456483],"type":"Point"}
}