{
  "type": "Feature",
  "properties": {
    "addr:full":"1020 W Fair Ave Lancaster OH 43130",
    "addr:housenumber":"1020",
    "addr:postcode":"43130",
    "addr:street":"W Fair Ave",
    "iso:country":"US",
    "sg:address":"1020 W Fair Ave",
    "sg:city":"Lancaster",
    "sg:classifiers":[
        {
            "category":"Shopping",
            "subcategory":"Tobacco",
            "type":"Retail Goods"
        }
    ],
    "sg:phone":"+1 740 653 6330",
    "sg:postcode":"43130",
    "sg:province":"OH",
    "sg:tags":[
        "cigarette",
        "cigar",
        "dealer"
    ],
    "wof:name":"Exquisite Tobacco",
    "wof:placetype":"venue"
},
  "geometry": {"coordinates":[-82.617501,39.724424],"type":"Point"}
}