{
  "type": "Feature",
  "properties": {
    "iso:country":"US",
    "sg:address":"901 Evans St",
    "sg:city":"Cincinnati",
    "sg:classifiers":[
        {
            "category":"Professional",
            "subcategory":"Accounting & Tax Preparation",
            "type":"Services"
        }
    ],
    "sg:phone":"+1 859 344 8887",
    "sg:postcode":"45204",
    "sg:province":"OH",
    "wof:name":"Burke & Shindler Pll",
    "wof:placetype":"venue"
},
  "geometry": {"coordinates":[-84.548012,39.107638],"type":"Point"}
}