{
  "type": "Feature",
  "properties": {
    "addr:full": "2757 Old Columbus Rd Granville OH 43023",
    "addr:housenumber": "2757",
    "addr:postcode": "43023",
    "addr:street": "Old Columbus Rd",
    "iso:country": "US",
    "sg:address": "2757 Old Columbus Rd",
    "sg:city": "Granville",
    "sg:classifiers": [
      {
        "category": "Social Services",
        "type": "Services"
      }
    ],
    "sg:phone": "+1 740 587 1553",
    "sg:postcode": "43023",
    "sg:province": "OH",
    "sg:tags": [
      "counseling"
    ],
    "wof:name": "Rolfing By Austin Mc Elroy",
    "wof:placetype": "venue"
  },
  "geometry": {"coordinates":[-82.547784,40.053089],"type":"Point"}
}
