{
  "type": "Feature",
  "properties": {
    "addr:full": "140 W 19th Ave Columbus OH 43210",
    "addr:housenumber": "140",
    "addr:postcode": "43210",
    "addr:street": "W 19Th Ave",
    "iso:country": "US",
    "sg:address": "140 W 19th Ave",
    "sg:city": "Columbus",
    "sg:classifiers": [
      {
        "category": "Education",
        "subcategory": "College",
        "type": "Public Place"
      }
    ],
    "sg:phone": "+1 614 292 2408",
    "sg:postcode": "43210",
    "sg:province": "OH",
    "wof:name": "Chemical Engineering Dept",
    "wof:placetype": "venue"
  },
  "geometry": {"coordinates":[-83.012359,40.003164],"type":"Point"}
}
