{
  "type": "Feature",
  "properties": {
    "addr:full": "2915 Stony Hollow Rd Dayton OH 45418",
    "addr:housenumber": "2915",
    "addr:postcode": "45418",
    "addr:street": "Stony Hollow Rd",
    "iso:country": "US",
    "sg:address": "2915 Stony Hollow Rd",
    "sg:city": "Dayton",
    "sg:classifiers": [
      {
        "category": "Utilities",
        "subcategory": "Refuse",
        "type": "Services"
      }
    ],
    "sg:phone": "+1 937 268 6336",
    "sg:postcode": "45418",
    "sg:province": "OH",
    "sg:tags": [
      "landfill",
      "waste"
    ],
    "wof:name": "Stony Hollow Hardfield",
    "wof:placetype": "venue"
  },
  "geometry": {"coordinates":[-84.235979,39.710553],"type":"Point"}
}
