{
  "type": "Feature",
  "properties": {
    "addr:full": "4011 Fenn Rd Medina OH 44256",
    "addr:housenumber": "4011",
    "addr:postcode": "44256",
    "addr:street": "Fenn Rd",
    "iso:country": "US",
    "sg:address": "4011 Fenn Rd",
    "sg:city": "Medina",
    "sg:classifiers": [
      {
        "category": "Professional",
        "type": "Services"
      }
    ],
    "sg:phone": "+1 330 225 8649",
    "sg:postcode": "44256",
    "sg:province": "OH",
    "wof:name": "Felix \u0026 Ann Mischak",
    "wof:placetype": "venue"
  },
  "geometry": {"coordinates":[-81.829376,41.170975],"type":"Point"}
}
