{
  "type": "Feature",
  "properties": {
    "addr:full":"8198 Twp Rd 669 Dundee OH 44624",
    "addr:housenumber":"8198;669",
    "addr:postcode":"44624",
    "addr:street":"Twp Rd",
    "iso:country":"US",
    "sg:address":"8198 Twp Rd 669",
    "sg:city":"Dundee",
    "sg:classifiers":[
        {
            "category":"Building & Trades",
            "subcategory":"Construction",
            "type":"Services"
        }
    ],
    "sg:phone":"+1 330 340 2192",
    "sg:postcode":"44624",
    "sg:province":"OH",
    "wof:name":"Triple M Construction Ltd",
    "wof:placetype":"venue"
},
  "geometry": {"coordinates":[-81.721332,40.630746],"type":"Point"}
}