{
  "type": "Feature",
  "properties": {
    "addr:full":"44 Monique Cir Marshallville OH 44645",
    "addr:housenumber":"44",
    "addr:postcode":"44645",
    "addr:street":"Monique Cir",
    "iso:country":"US",
    "sg:address":"44 Monique Cir",
    "sg:city":"Marshallville",
    "sg:classifiers":[
        {
            "category":"Professional",
            "type":"Services"
        }
    ],
    "sg:phone":"+1 330 855 8707",
    "sg:postcode":"44645",
    "sg:province":"OH",
    "wof:name":"Connie Hughes",
    "wof:placetype":"venue"
},
  "geometry": {"coordinates":[-81.736171,40.903964],"type":"Point"}
}