{
  "type": "Feature",
  "properties": {
    "iso:country":"US",
    "sg:address":"5317 Loe Rd",
    "sg:city":"Cygnet",
    "sg:classifiers":[
        {
            "category":"Building & Trades",
            "subcategory":"Electrical",
            "type":"Services"
        }
    ],
    "sg:phone":"+1 419 655 2519",
    "sg:postcode":"43413",
    "sg:province":"OH",
    "sg:tags":[
        "electrical",
        "contractor"
    ],
    "wof:name":"Mc Grain Electric",
    "wof:placetype":"venue"
},
  "geometry": {"coordinates":[-83.621183,41.225976],"type":"Point"}
}