{
  "type": "Feature",
  "properties": {
    "addr:full": "7474 Twin Lakes Trl Chagrin Falls OH 44022",
    "addr:housenumber": "7474",
    "addr:postcode": "44022",
    "addr:street": "Twin Lakes Trl",
    "iso:country": "US",
    "sg:address": "7474 Twin Lakes Trl",
    "sg:city": "Chagrin Falls",
    "sg:classifiers": [
      {
        "category": "Building \u0026 Trades",
        "subcategory": "Construction",
        "type": "Services"
      }
    ],
    "sg:phone": "+1 216 283 1552",
    "sg:postcode": "44022",
    "sg:province": "OH",
    "sg:tags": [
      "contractor"
    ],
    "wof:name": "Ace Builders",
    "wof:placetype": "venue"
  },
  "geometry": {"coordinates":[-81.374046,41.440737],"type":"Point"}
}
