{
  "type": "Feature",
  "properties": {
    "iso:country":"US",
    "sg:address":"7474 Twin Lakes Trl",
    "sg:city":"Chagrin Falls",
    "sg:classifiers":[
        {
            "category":"Building & Trades",
            "subcategory":"Construction",
            "type":"Services"
        }
    ],
    "sg:phone":"+1 216 283 1552",
    "sg:postcode":"44022",
    "sg:province":"OH",
    "sg:tags":[
        "contractor"
    ],
    "wof:name":"Ace Builders",
    "wof:placetype":"venue"
},
  "geometry": {"coordinates":[-81.37404600000001,41.440737],"type":"Point"}
}