{
  "type": "Feature",
  "properties": {
    "addr:full": "6223 Knollwood Rd Springfield OH 45502",
    "addr:housenumber": "6223",
    "addr:postcode": "45502",
    "addr:street": "Knollwood Rd",
    "iso:country": "US",
    "sg:address": "6223 Knollwood Rd",
    "sg:city": "Springfield",
    "sg:classifiers": [
      {
        "category": "Building \u0026 Trades",
        "subcategory": "Construction",
        "type": "Services"
      }
    ],
    "sg:phone": "+1 937 969 8138",
    "sg:postcode": "45502",
    "sg:province": "OH",
    "sg:tags": [
      "contractor"
    ],
    "wof:name": "Richard Snouse",
    "wof:placetype": "venue"
  },
  "geometry": {"coordinates":[-83.874796,40.020119],"type":"Point"}
}
