{
  "type": "Feature",
  "properties": {
    "addr:full": "215 Broad St Jackson OH 45640",
    "addr:housenumber": "215",
    "addr:postcode": "45640",
    "addr:street": "Broad St",
    "iso:country": "US",
    "sg:address": "215 Broad St",
    "sg:city": "Jackson",
    "sg:classifiers": [
      {
        "category": "Retail",
        "subcategory": "Funeral Services",
        "type": "Services"
      }
    ],
    "sg:phone": "+1 740 286 3522",
    "sg:postcode": "45640",
    "sg:province": "OH",
    "sg:tags": [
      "director"
    ],
    "wof:name": "Mayhew \u0026 Mayhew",
    "wof:placetype": "venue"
  },
  "geometry": {"coordinates":[-82.638263,39.04903],"type":"Point"}
}
