{
  "type": "Feature",
  "properties": {
    "iso:country":"US",
    "sg:address":"215 Broad St",
    "sg:city":"Jackson",
    "sg:classifiers":[
        {
            "category":"Retail",
            "subcategory":"Funeral Services",
            "type":"Services"
        }
    ],
    "sg:phone":"+1 740 286 3522",
    "sg:postcode":"45640",
    "sg:province":"OH",
    "sg:tags":[
        "director"
    ],
    "wof:name":"Mayhew & Mayhew",
    "wof:placetype":"venue"
},
  "geometry": {"coordinates":[-82.63826299999999,39.04903],"type":"Point"}
}