{
  "type": "Feature",
  "properties": {
    "addr:full":"243 E Livingston Ave Columbus OH 43215",
    "addr:housenumber":"243",
    "addr:postcode":"43215",
    "addr:street":"E Livingston Ave",
    "iso:country":"US",
    "sg:address":"243 E Livingston Ave",
    "sg:city":"Columbus",
    "sg:classifiers":[
        {
            "category":"Real Estate",
            "subcategory":"Architect",
            "type":"Services"
        }
    ],
    "sg:phone":"+1 614 461 0243",
    "sg:postcode":"43215",
    "sg:province":"OH",
    "sg:tags":[
        "architectural"
    ],
    "wof:name":"Rogers Darryl G AIA Architect",
    "wof:placetype":"venue"
},
  "geometry": {"coordinates":[-82.991527,39.952495],"type":"Point"}
}