{
  "type": "Feature",
  "properties": {
    "addr:full": "600 E Smith Rd Medina OH 44256",
    "addr:housenumber": "600",
    "addr:postcode": "44256",
    "addr:street": "E Smith Rd",
    "iso:country": "US",
    "sg:address": "600 E Smith Rd",
    "sg:city": "Medina",
    "sg:classifiers": [
      {
        "category": "Health Services",
        "subcategory": "Chiropractor",
        "type": "Services"
      }
    ],
    "sg:phone": "+1 330 725 4500",
    "sg:postcode": "44256",
    "sg:province": "OH",
    "wof:name": "Brunello Chiropractic Clinic",
    "wof:placetype": "venue"
  },
  "geometry": {"coordinates":[-81.84695,41.134398],"type":"Point"}
}
