{
  "type": "Feature",
  "properties": {
    "addr:full": "1030 King Ave Columbus OH 43212",
    "addr:housenumber": "1030",
    "addr:postcode": "43212",
    "addr:street": "King Ave",
    "iso:country": "US",
    "sg:address": "1030 King Ave",
    "sg:city": "Columbus",
    "sg:classifiers": [
      {
        "category": "Social Services",
        "subcategory": "Child Care",
        "type": "Services"
      }
    ],
    "sg:phone": "+1 614 298 8933",
    "sg:postcode": "43212",
    "sg:province": "OH",
    "sg:tags": [
      "day"
    ],
    "wof:name": "Kare A Lot",
    "wof:placetype": "venue"
  },
  "geometry": {"coordinates":[-83.034363,39.991275],"type":"Point"}
}
