{
  "type": "Feature",
  "properties": {
    "iso:country":"US",
    "sg:address":"7007 Engle Rd",
    "sg:city":"Cleveland",
    "sg:classifiers":[
        {
            "category":"Building & Trades",
            "subcategory":"Equipment Rental",
            "type":"Services"
        }
    ],
    "sg:phone":"+1 440 234 3090",
    "sg:postcode":"44130",
    "sg:province":"OH",
    "sg:tags":[
        "yard"
    ],
    "wof:name":"Electrical Solutions Of Ohio",
    "wof:placetype":"venue"
},
  "geometry": {"coordinates":[-81.824654,41.373538],"type":"Point"}
}