{
  "type": "Feature",
  "properties": {
    "addr:full": "7007 Engle Rd Cleveland OH 44130",
    "addr:housenumber": "7007",
    "addr:postcode": "44130",
    "addr:street": "Engle Rd",
    "iso:country": "US",
    "sg:address": "7007 Engle Rd",
    "sg:city": "Cleveland",
    "sg:classifiers": [
      {
        "category": "Building \u0026 Trades",
        "subcategory": "Equipment Rental",
        "type": "Services"
      }
    ],
    "sg:phone": "+1 440 234 3090",
    "sg:postcode": "44130",
    "sg:province": "OH",
    "sg:tags": [
      "yard"
    ],
    "wof:name": "Electrical Solutions Of Ohio",
    "wof:placetype": "venue"
  },
  "geometry": {"coordinates":[-81.824654,41.373538],"type":"Point"}
}
