{
  "type": "Feature",
  "properties": {
    "addr:full": "1413 S Main St Bellefontaine OH 43311",
    "addr:housenumber": "1413",
    "addr:postcode": "43311",
    "addr:street": "S Main St",
    "iso:country": "US",
    "sg:address": "1413 S Main St",
    "sg:city": "Bellefontaine",
    "sg:classifiers": [
      {
        "category": "Government",
        "subcategory": "Office",
        "type": "Public Place"
      }
    ],
    "sg:phone": "+1 937 592 2233",
    "sg:postcode": "43311",
    "sg:province": "OH",
    "sg:tags": [
      "federal",
      "program"
    ],
    "sg:website": "www.usda.gov",
    "wof:name": "US Agricultural Dept",
    "wof:placetype": "venue"
  },
  "geometry": {"coordinates":[-83.76181,40.341344],"type":"Point"}
}
