{
  "type": "Feature",
  "properties": {
    "addr:full":"3804 Euclid Ave Cleveland OH 44115",
    "addr:housenumber":"3804",
    "addr:postcode":"44115",
    "addr:street":"Euclid Ave",
    "iso:country":"US",
    "sg:address":"3804 Euclid Ave",
    "sg:city":"Cleveland",
    "sg:classifiers":[
        {
            "category":"Manufacturing",
            "subcategory":"Printing",
            "type":"Manufacturing & Wholesale Goods"
        }
    ],
    "sg:phone":"+1 216 391 3272",
    "sg:postcode":"44115",
    "sg:province":"OH",
    "sg:tags":[
        "printer"
    ],
    "wof:name":"DCS Graphic Design",
    "wof:placetype":"venue"
},
  "geometry": {"coordinates":[-81.65974799999999,41.503224],"type":"Point"}
}