{
  "type": "Feature",
  "properties": {
    "addr:full": "135 E Ascot Ln Cuyahoga Falls OH 44223",
    "addr:housenumber": "135",
    "addr:postcode": "44223",
    "addr:street": "E Ascot Ln",
    "iso:country": "US",
    "sg:address": "135 E Ascot Ln",
    "sg:city": "Cuyahoga Falls",
    "sg:classifiers": [
      {
        "category": "Wholesale",
        "subcategory": "Machinery \u0026 Supplies",
        "type": "Manufacturing \u0026 Wholesale Goods"
      }
    ],
    "sg:phone": "+1 330 923 4853",
    "sg:postcode": "44223",
    "sg:province": "OH",
    "sg:tags": [
      "equipment",
      "hydraulic"
    ],
    "sg:website": "www.atlasfluid.com",
    "wof:name": "Atlas Fluid Components",
    "wof:placetype": "venue"
  },
  "geometry": {"coordinates":[-81.519352,41.163749],"type":"Point"}
}
