{
  "type": "Feature",
  "properties": {
    "iso:country":"US",
    "sg:address":"9282 Loralinda Dr",
    "sg:city":"Cincinnati",
    "sg:classifiers":[
        {
            "category":"Insurance",
            "subcategory":"Insurance Agent",
            "type":"Services"
        }
    ],
    "sg:phone":"+1 513 741 2925",
    "sg:postcode":"45251",
    "sg:province":"OH",
    "wof:name":"Pesion Plus",
    "wof:placetype":"venue"
},
  "geometry": {"coordinates":[-84.58439,39.239935],"type":"Point"}
}