{
  "type": "Feature",
  "properties": {
    "addr:full":"3260 W Henderson Rd Columbus OH 43220",
    "addr:housenumber":"3260",
    "addr:postcode":"43220",
    "addr:street":"W Henderson Rd",
    "iso:country":"US",
    "sg:address":"3260 W Henderson Rd",
    "sg:city":"Columbus",
    "sg:classifiers":[
        {
            "category":"Insurance",
            "subcategory":"Insurance Agent",
            "type":"Services"
        },
        {
            "category":"Insurance",
            "subcategory":"Life Insurance",
            "type":"Services"
        }
    ],
    "sg:phone":"+1 614 442 9090",
    "sg:postcode":"43220",
    "sg:province":"OH",
    "sg:tags":[
        "consultant",
        "carrier"
    ],
    "wof:name":"Annuity Marketing Group",
    "wof:placetype":"venue"
},
  "geometry": {"coordinates":[-83.081397,40.059611],"type":"Point"}
}