{
  "type": "Feature",
  "properties": {
    "iso:country":"US",
    "sg:address":"25931 Euclid Ave",
    "sg:city":"Euclid",
    "sg:classifiers":[
        {
            "category":"Insurance",
            "subcategory":"Insurance Agent",
            "type":"Services"
        }
    ],
    "sg:phone":"+1 216 751 6702",
    "sg:postcode":"44132",
    "sg:province":"OH",
    "sg:tags":[
        "consultant",
        "fin"
    ],
    "wof:name":"Global Consultants Inc",
    "wof:placetype":"venue"
},
  "geometry": {"coordinates":[-81.504245,41.586095],"type":"Point"}
}