{
  "type": "Feature",
  "properties": {
    "iso:country":"US",
    "sg:address":"1818 W Lane Ave",
    "sg:city":"Columbus",
    "sg:classifiers":[
        {
            "category":"Banks & Credit Unions",
            "subcategory":"Bank",
            "type":"Services"
        }
    ],
    "sg:phone":"+1 614 487 8383",
    "sg:postcode":"43221",
    "sg:province":"OH",
    "wof:name":"Ohio Savings Bank",
    "wof:placetype":"venue"
},
  "geometry": {"coordinates":[-83.058768,40.007464],"type":"Point"}
}