{
  "type": "Feature",
  "properties": {
    "addr:full": "25941 Euclid Ave Cleveland OH 44132",
    "addr:housenumber": "25941",
    "addr:postcode": "44132",
    "addr:street": "Euclid Ave",
    "iso:country": "US",
    "sg:address": "25941 Euclid Ave",
    "sg:city": "Cleveland",
    "sg:classifiers": [
      {
        "category": "Health Services",
        "subcategory": "Chiropractor",
        "type": "Services"
      }
    ],
    "sg:phone": "+1 216 261 2055",
    "sg:postcode": "44132",
    "sg:province": "OH",
    "wof:name": "Euclid Chiropractic \u0026 Therapy",
    "wof:placetype": "venue"
  },
  "geometry": {"coordinates":[-81.504292,41.586052],"type":"Point"}
}
