{
  "type": "Feature",
  "properties": {
    "iso:country":"US",
    "sg:address":"25941 Euclid Ave",
    "sg:city":"Cleveland",
    "sg:classifiers":[
        {
            "category":"Health Services",
            "subcategory":"Chiropractor",
            "type":"Services"
        }
    ],
    "sg:phone":"+1 216 261 2055",
    "sg:postcode":"44132",
    "sg:province":"OH",
    "wof:name":"Euclid Chiropractic & Therapy",
    "wof:placetype":"venue"
},
  "geometry": {"coordinates":[-81.50429200000001,41.586052],"type":"Point"}
}