{
  "type": "Feature",
  "properties": {
    "iso:country":"US",
    "sg:address":"1764 Polk Hollow Rd",
    "sg:city":"Chillicothe",
    "sg:classifiers":[
        {
            "category":"Building & Trades",
            "subcategory":"Construction",
            "type":"Services"
        }
    ],
    "sg:phone":"+1 740 775 0901",
    "sg:postcode":"45601",
    "sg:province":"OH",
    "sg:tags":[
        "house"
    ],
    "wof:name":"C & M Construction",
    "wof:placetype":"venue"
},
  "geometry": {"coordinates":[-83.056558,39.327323],"type":"Point"}
}