{
  "type": "Feature",
  "properties": {
    "iso:country":"US",
    "sg:address":"550 S Main St",
    "sg:city":"Oberlin",
    "sg:classifiers":[
        {
            "category":"Freight",
            "type":"Transportation"
        }
    ],
    "sg:phone":"+1 440 775 7009",
    "sg:postcode":"44074",
    "sg:province":"OH",
    "sg:tags":[
        "commercial",
        "storage"
    ],
    "wof:name":"58 Storage",
    "wof:placetype":"venue"
},
  "geometry": {"coordinates":[-82.21773899999999,41.279591],"type":"Point"}
}