{
  "type": "Feature",
  "properties": {
    "addr:full":"44 Holmes St Galena OH 43021",
    "addr:housenumber":"44",
    "addr:postcode":"43021",
    "addr:street":"Holmes St",
    "iso:country":"US",
    "sg:address":"44 Holmes St",
    "sg:city":"Galena",
    "sg:classifiers":[
        {
            "category":"Autos & Motor Vehicles",
            "subcategory":"Auto Supplies",
            "type":"Retail Goods"
        }
    ],
    "sg:phone":"+1 740 965 4566",
    "sg:postcode":"43021",
    "sg:province":"OH",
    "sg:tags":[
        "equipment",
        "air",
        "conditioning",
        "automobile"
    ],
    "wof:name":"Your Neighborhood Mechanic Inc",
    "wof:placetype":"venue"
},
  "geometry": {"coordinates":[-82.88126699999999,40.221737],"type":"Point"}
}