{
  "type": "Feature",
  "properties": {
    "addr:full": "304 Mill St New Lexington OH 43764",
    "addr:housenumber": "304",
    "addr:postcode": "43764",
    "addr:street": "Mill St",
    "iso:country": "US",
    "sg:address": "304 Mill St",
    "sg:city": "New Lexington",
    "sg:classifiers": [
      {
        "category": "Retail",
        "subcategory": "Funeral Services",
        "type": "Services"
      }
    ],
    "sg:phone": "+1 740 342 1951",
    "sg:postcode": "43764",
    "sg:province": "OH",
    "sg:tags": [
      "director"
    ],
    "wof:name": "Roberts Funeral Home",
    "wof:placetype": "venue"
  },
  "geometry": {"coordinates":[-82.202847,39.711434],"type":"Point"}
}
