{
  "type": "Feature",
  "properties": {
    "iso:country":"US",
    "sg:address":"304 Mill St",
    "sg:city":"New Lexington",
    "sg:classifiers":[
        {
            "category":"Retail",
            "subcategory":"Funeral Services",
            "type":"Services"
        }
    ],
    "sg:phone":"+1 740 342 1951",
    "sg:postcode":"43764",
    "sg:province":"OH",
    "sg:tags":[
        "director"
    ],
    "wof:name":"Roberts Funeral Home",
    "wof:placetype":"venue"
},
  "geometry": {"coordinates":[-82.20284700000001,39.711434],"type":"Point"}
}