{
  "type": "Feature",
  "properties": {
    "addr:full": "9082 Eversole Run Dr Powell OH 43065",
    "addr:housenumber": "9082",
    "addr:postcode": "43065",
    "addr:street": "Eversole Run Dr",
    "iso:country": "US",
    "sg:address": "9082 Eversole Run Dr",
    "sg:city": "Powell",
    "sg:classifiers": [
      {
        "category": "Professional",
        "subcategory": "Business Services",
        "type": "Services"
      }
    ],
    "sg:phone": "+1 614 761 9040",
    "sg:postcode": "43065",
    "sg:province": "OH",
    "sg:tags": [
      "interior",
      "consultant",
      "design",
      "decorator"
    ],
    "wof:name": "Accessory Market",
    "wof:placetype": "venue"
  },
  "geometry": {"coordinates":[-83.16788,40.177368],"type":"Point"}
}
