{
  "type": "Feature",
  "properties": {
    "iso:country":"US",
    "sg:address":"590 Dussel Dr",
    "sg:city":"Maumee",
    "sg:classifiers":[
        {
            "category":"Restaurant",
            "type":"Food & Drink"
        }
    ],
    "sg:phone":"+1 419 893 1112",
    "sg:postcode":"43537",
    "sg:province":"OH",
    "wof:name":"Wendys",
    "wof:placetype":"venue"
},
  "geometry": {"coordinates":[-83.650178,41.585535],"type":"Point"}
}