{
  "type": "Feature",
  "properties": {
    "iso:country":"US",
    "sg:address":"226 N 4th St",
    "sg:city":"Steubenville",
    "sg:classifiers":[
        {
            "category":"Social Services",
            "type":"Services"
        }
    ],
    "sg:phone":"+1 740 282 6034",
    "sg:postcode":"43952",
    "sg:province":"OH",
    "sg:tags":[
        "senior",
        "citizen"
    ],
    "wof:name":"Retired Senior Volunteer Prgm",
    "wof:placetype":"venue"
},
  "geometry": {"coordinates":[-80.613525,40.362924],"type":"Point"}
}