{
  "type": "Feature",
  "properties": {
    "addr:full":"6504 Glenway Ave Cincinnati OH 45211",
    "addr:housenumber":"6504",
    "addr:postcode":"45211",
    "addr:street":"Glenway Ave",
    "iso:country":"US",
    "sg:address":"6504 Glenway Ave",
    "sg:city":"Cincinnati",
    "sg:classifiers":[
        {
            "category":"Education",
            "subcategory":"School",
            "type":"Public Place"
        }
    ],
    "sg:phone":"+1 513 598 4922",
    "sg:postcode":"45211",
    "sg:province":"OH",
    "sg:website":"www.chauffeurtraining.com",
    "wof:name":"Executive Chaffeuring School",
    "wof:placetype":"venue"
},
  "geometry": {"coordinates":[-84.62934300000001,39.156248],"type":"Point"}
}