{
  "type": "Feature",
  "properties": {
    "iso:country":"US",
    "sg:address":"4180 Greenvale Rd",
    "sg:city":"Cleveland",
    "sg:classifiers":[
        {
            "category":"Retail",
            "subcategory":"Repair Shop",
            "type":"Services"
        }
    ],
    "sg:phone":"+1 216 381 1221",
    "sg:postcode":"44121",
    "sg:province":"OH",
    "sg:tags":[
        "instrument",
        "musical"
    ],
    "sg:website":"www.borodimusic.com",
    "wof:name":"Borodi Music",
    "wof:placetype":"venue"
},
  "geometry": {"coordinates":[-81.529656,41.538878],"type":"Point"}
}