{
  "type": "Feature",
  "properties": {
    "addr:full":"6000 Townvista Dr Cincinnati OH 45224",
    "addr:housenumber":"6000",
    "addr:postcode":"45224",
    "addr:street":"Townvista Dr",
    "iso:country":"US",
    "sg:address":"6000 Townvista Dr",
    "sg:city":"Cincinnati",
    "sg:classifiers":[
        {
            "category":"Real Estate",
            "subcategory":"Real Estate Operator",
            "type":"Services"
        }
    ],
    "sg:phone":"+1 513 242 4482",
    "sg:postcode":"45224",
    "sg:province":"OH",
    "sg:tags":[
        "building",
        "apartment"
    ],
    "wof:name":"Salvation Army",
    "wof:placetype":"venue"
},
  "geometry": {"coordinates":[-84.51503700000001,39.19891],"type":"Point"}
}