{
  "type": "Feature",
  "properties": {
    "addr:full":"204 W Perkins Ave Sandusky OH 44870",
    "addr:housenumber":"204",
    "addr:postcode":"44870",
    "addr:street":"W Perkins Ave",
    "iso:country":"US",
    "sg:address":"204 W Perkins Ave",
    "sg:city":"Sandusky",
    "sg:classifiers":[
        {
            "category":"Personal",
            "subcategory":"Beauty Salon",
            "type":"Services"
        }
    ],
    "sg:phone":"+1 419 624 9948",
    "sg:postcode":"44870",
    "sg:province":"OH",
    "sg:tags":[
        "manicuring"
    ],
    "wof:name":"Sandusky Modern Nail",
    "wof:placetype":"venue"
},
  "geometry": {"coordinates":[-82.701205,41.432787],"type":"Point"}
}