{
  "type": "Feature",
  "properties": {
    "addr:full": "2849 Fischer Pl Cincinnati OH 45211",
    "addr:housenumber": "2849",
    "addr:postcode": "45211",
    "addr:street": "Fischer Pl",
    "iso:country": "US",
    "sg:address": "2849 Fischer Pl",
    "sg:city": "Cincinnati",
    "sg:classifiers": [
      {
        "category": "Organizations",
        "subcategory": "Religious Organization",
        "type": "Services"
      }
    ],
    "sg:phone": "+1 513 481 0431",
    "sg:postcode": "45211",
    "sg:province": "OH",
    "sg:tags": [
      "monastery",
      "convent"
    ],
    "sg:website": "www.ohsnd.org",
    "wof:name": "Sisters Of Notre Dame De Namur",
    "wof:placetype": "venue"
  },
  "geometry": {"coordinates":[-84.592137,39.146085],"type":"Point"}
}
