{
  "type": "Feature",
  "properties": {
    "addr:full":"7749 Webster Rd Cleveland OH 44130",
    "addr:housenumber":"7749",
    "addr:postcode":"44130",
    "addr:street":"Webster Rd",
    "iso:country":"US",
    "sg:address":"7749 Webster Rd",
    "sg:city":"Cleveland",
    "sg:classifiers":[
        {
            "category":"Organizations",
            "subcategory":"Professional Association",
            "type":"Services"
        }
    ],
    "sg:phone":"+1 440 826 3930",
    "sg:postcode":"44130",
    "sg:province":"OH",
    "sg:website":"www.bmm.org",
    "wof:name":"Baptist Mid-Missions",
    "wof:placetype":"venue"
},
  "geometry": {"coordinates":[-81.80125099999999,41.352384],"type":"Point"}
}