{
  "type": "Feature",
  "properties": {
    "iso:country":"US",
    "sg:address":"10176 Lisbon Rd",
    "sg:city":"Canfield",
    "sg:classifiers":[
        {
            "category":"Building & Trades",
            "subcategory":"Plumbing",
            "type":"Services"
        }
    ],
    "sg:phone":"+1 330 533 5748",
    "sg:postcode":"44406",
    "sg:province":"OH",
    "sg:tags":[
        "contractor"
    ],
    "wof:name":"Jerry Ewing Plumbing Company",
    "wof:placetype":"venue"
},
  "geometry": {"coordinates":[-80.79533600000001,40.965959],"type":"Point"}
}