{
  "type": "Feature",
  "properties": {
    "addr:full":"2600 6th St SW Canton OH 44710",
    "addr:housenumber":"2600",
    "addr:postcode":"44710",
    "addr:street":"6Th St Sw",
    "iso:country":"US",
    "sg:address":"2600 6th St SW",
    "sg:city":"Canton",
    "sg:classifiers":[
        {
            "category":"Health Services",
            "subcategory":"Medical Lab",
            "type":"Services"
        }
    ],
    "sg:phone":"+1 330 438 6274",
    "sg:postcode":"44710",
    "sg:province":"OH",
    "sg:tags":[
        "laboratory"
    ],
    "wof:name":"Gyneclgic Onclgists of Ne Ohio",
    "wof:placetype":"venue"
},
  "geometry": {"coordinates":[-81.402901,40.796753],"type":"Point"}
}