{
  "type": "Feature",
  "properties": {
    "iso:country":"US",
    "sg:address":"8648 Waynesburg Dr SE",
    "sg:city":"Waynesburg",
    "sg:classifiers":[
        {
            "category":"Restaurant",
            "type":"Food & Drink"
        }
    ],
    "sg:phone":"+1 330 866 3538",
    "sg:postcode":"44688",
    "sg:province":"OH",
    "sg:website":"www.subway.com",
    "wof:name":"Subway Sandwiches & Salads",
    "wof:placetype":"venue"
},
  "geometry": {"coordinates":[-81.260952,40.676794],"type":"Point"}
}