{
  "type": "Feature",
  "properties": {
    "addr:full": "1735 Cleveland Ave NW Canton OH 44703",
    "addr:housenumber": "1735",
    "addr:postcode": "44703",
    "addr:street": "Cleveland Ave Nw",
    "iso:country": "US",
    "sg:address": "1735 Cleveland Ave NW",
    "sg:city": "Canton",
    "sg:classifiers": [
      {
        "category": "Food \u0026 Beverages",
        "subcategory": "Groceries \u0026 Convenience Stores",
        "type": "Retail Goods"
      }
    ],
    "sg:phone": "+1 330 452 5021",
    "sg:postcode": "44703",
    "sg:province": "OH",
    "wof:name": "Spee-D-Foods Inc",
    "wof:placetype": "venue"
  },
  "geometry": {"coordinates":[-81.380263,40.816935],"type":"Point"}
}
