{
  "type": "Feature",
  "properties": {
    "iso:country":"US",
    "sg:address":"1735 Cleveland Ave NW",
    "sg:city":"Canton",
    "sg:classifiers":[
        {
            "category":"Food & Beverages",
            "subcategory":"Groceries & Convenience Stores",
            "type":"Retail Goods"
        }
    ],
    "sg:phone":"+1 330 452 5021",
    "sg:postcode":"44703",
    "sg:province":"OH",
    "wof:name":"Spee-D-Foods Inc",
    "wof:placetype":"venue"
},
  "geometry": {"coordinates":[-81.380263,40.816935],"type":"Point"}
}