{
  "type": "Feature",
  "properties": {
    "iso:country":"US",
    "sg:address":"1505 Delashmut Ave",
    "sg:city":"Columbus",
    "sg:classifiers":[
        {
            "category":"Professional",
            "subcategory":"Business Services",
            "type":"Services"
        }
    ],
    "sg:phone":"+1 614 294 8326",
    "sg:postcode":"43212",
    "sg:province":"OH",
    "sg:tags":[
        "fund",
        "raising"
    ],
    "wof:name":"Teamwork Fundraising",
    "wof:placetype":"venue"
},
  "geometry": {"coordinates":[-83.03025,39.990448],"type":"Point"}
}