{
  "type": "Feature",
  "properties": {
    "iso:country":"US",
    "sg:address":"615 E Bigelow Ave",
    "sg:city":"Findlay",
    "sg:classifiers":[
        {
            "category":"Utilities",
            "subcategory":"Mobile Phone",
            "type":"Services"
        }
    ],
    "sg:phone":"+1 419 425 5304",
    "sg:postcode":"45840",
    "sg:province":"OH",
    "sg:tags":[
        "communication",
        "radiotelephone"
    ],
    "wof:name":"I H S Wireless",
    "wof:placetype":"venue"
},
  "geometry": {"coordinates":[-83.64086399999999,41.07291],"type":"Point"}
}