{
  "type": "Feature",
  "properties": {
    "addr:full":"438 5th St NE Barberton OH 44203",
    "addr:housenumber":"438",
    "addr:postcode":"44203",
    "addr:street":"5Th St Ne",
    "iso:country":"US",
    "sg:address":"438 5th St NE",
    "sg:city":"Barberton",
    "sg:classifiers":[
        {
            "category":"Restaurant",
            "type":"Food & Drink"
        }
    ],
    "sg:phone":"+1 330 753 8137",
    "sg:postcode":"44203",
    "sg:province":"OH",
    "sg:tags":[
        "parlor",
        "ice",
        "cream"
    ],
    "wof:name":"Scoops",
    "wof:placetype":"venue"
},
  "geometry": {"coordinates":[-81.58963199999999,41.02185],"type":"Point"}
}