{
  "type": "Feature",
  "properties": {
    "addr:full": "101 Northwood Dr Delta OH 43515",
    "addr:housenumber": "101",
    "addr:postcode": "43515",
    "addr:street": "Northwood Dr",
    "iso:country": "US",
    "sg:address": "101 Northwood Dr",
    "sg:city": "Delta",
    "sg:classifiers": [
      {
        "category": "Social Services",
        "subcategory": "Child Care",
        "type": "Services"
      }
    ],
    "sg:phone": "+1 419 822 4976",
    "sg:postcode": "43515",
    "sg:province": "OH",
    "wof:name": "Sunny Day Preschool",
    "wof:placetype": "venue"
  },
  "geometry": {"coordinates":[-84.005118,41.58255],"type":"Point"}
}
