{
  "type": "Feature",
  "properties": {
    "addr:full": "314 Shelby St Sidney OH 45365",
    "addr:housenumber": "314",
    "addr:postcode": "45365",
    "addr:street": "Shelby St",
    "iso:country": "US",
    "sg:address": "314 Shelby St",
    "sg:city": "Sidney",
    "sg:classifiers": [
      {
        "category": "Manufacturing",
        "subcategory": "Tools \u0026 Machinery",
        "type": "Manufacturing \u0026 Wholesale Goods"
      }
    ],
    "sg:phone": "+1 937 492 8133",
    "sg:postcode": "45365",
    "sg:province": "OH",
    "sg:tags": [
      "machine",
      "shop"
    ],
    "wof:name": "Sidney Design Svc Inc",
    "wof:placetype": "venue"
  },
  "geometry": {"coordinates":[-84.152557,40.290395],"type":"Point"}
}
