{
  "type": "Feature",
  "properties": {
    "iso:country":"US",
    "sg:address":"15875 W High St",
    "sg:city":"Middlefield",
    "sg:classifiers":[
        {
            "category":"Health Services",
            "subcategory":"Doctor",
            "type":"Services"
        }
    ],
    "sg:phone":"+1 440 632 0389",
    "sg:postcode":"44062",
    "sg:province":"OH",
    "sg:tags":[
        "dentist"
    ],
    "wof:name":"Middlefield Dental",
    "wof:placetype":"venue"
},
  "geometry": {"coordinates":[-81.076866,41.462246],"type":"Point"}
}