{
  "type": "Feature",
  "properties": {
    "iso:country":"US",
    "sg:address":"22521 State St",
    "sg:city":"Amesville",
    "sg:classifiers":[
        {
            "category":"Retail",
            "subcategory":"Auto Repair",
            "type":"Services"
        }
    ],
    "sg:phone":"+1 330 821 5488",
    "sg:postcode":"45711",
    "sg:province":"OH",
    "sg:tags":[
        "wrecker"
    ],
    "wof:name":"Gandee's Towing LLC",
    "wof:placetype":"venue"
},
  "geometry": {"coordinates":[-81.854862,39.429924],"type":"Point"}
}