{
  "type": "Feature",
  "properties": {
    "addr:full":"7582 Pearl Rd Cleveland OH 44130",
    "addr:housenumber":"7582",
    "addr:postcode":"44130",
    "addr:street":"Pearl Rd",
    "iso:country":"US",
    "sg:address":"7582 Pearl Rd",
    "sg:city":"Cleveland",
    "sg:classifiers":[
        {
            "category":"Recreation",
            "type":"Entertainment"
        }
    ],
    "sg:phone":"+1 216 702 6186",
    "sg:postcode":"44130",
    "sg:province":"OH",
    "sg:tags":[
        "psychic",
        "medium"
    ],
    "wof:name":"Leeza's Psychic Boutique",
    "wof:placetype":"venue"
},
  "geometry": {"coordinates":[-81.814753,41.360054],"type":"Point"}
}