{
  "type": "Feature",
  "properties": {
    "addr:full": "14105 Shaffer Rd Swanton OH 43558",
    "addr:housenumber": "14105",
    "addr:postcode": "43558",
    "addr:street": "Shaffer Rd",
    "iso:country": "US",
    "sg:address": "14105 Shaffer Rd",
    "sg:city": "Swanton",
    "sg:classifiers": [
      {
        "category": "Recreation",
        "type": "Entertainment"
      }
    ],
    "sg:phone": "+1 419 826 4678",
    "sg:postcode": "43558",
    "sg:province": "OH",
    "sg:tags": [
      "concessionaire"
    ],
    "wof:name": "HMS Host",
    "wof:placetype": "venue"
  },
  "geometry": {"coordinates":[-83.878428,41.603241],"type":"Point"}
}
