{
  "type": "Feature",
  "properties": {
    "addr:full":"715 S Lincoln Ave Bridgeport OH 43912",
    "addr:housenumber":"715",
    "addr:postcode":"43912",
    "addr:street":"S Lincoln Ave",
    "iso:country":"US",
    "sg:address":"715 S Lincoln Ave",
    "sg:city":"Bridgeport",
    "sg:classifiers":[
        {
            "category":"Freight",
            "type":"Transportation"
        }
    ],
    "sg:phone":"+1 740 635 8000",
    "sg:postcode":"43912",
    "sg:province":"OH",
    "sg:tags":[
        "commercial",
        "storage"
    ],
    "wof:name":"PJS Mini Storage",
    "wof:placetype":"venue"
},
  "geometry": {"coordinates":[-80.740574,40.066831],"type":"Point"}
}