{
  "type": "Feature",
  "properties": {
    "addr:full": "8341 Tyler Blvd Mentor OH 44060",
    "addr:housenumber": "8341",
    "addr:postcode": "44060",
    "addr:street": "Tyler Blvd",
    "iso:country": "US",
    "sg:address": "8341 Tyler Blvd",
    "sg:city": "Mentor",
    "sg:classifiers": [
      {
        "category": "Wholesale",
        "subcategory": "Construction Materials",
        "type": "Manufacturing \u0026 Wholesale Goods"
      }
    ],
    "sg:phone": "+1 440 974 7381",
    "sg:postcode": "44060",
    "sg:province": "OH",
    "sg:tags": [
      "molding"
    ],
    "sg:website": "www.moldmastersintl.com",
    "wof:name": "Mold Masters Intl",
    "wof:placetype": "venue"
  },
  "geometry": {"coordinates":[-81.340731,41.68294],"type":"Point"}
}
