{
  "type": "Feature",
  "properties": {
    "addr:full":"2229 Broadway Lorain OH 44052",
    "addr:housenumber":"2229",
    "addr:postcode":"44052",
    "addr:street":"Broadway",
    "iso:country":"US",
    "sg:address":"2229 Broadway",
    "sg:city":"Lorain",
    "sg:classifiers":[
        {
            "category":"Retail",
            "subcategory":"Repair Shop",
            "type":"Services"
        }
    ],
    "sg:phone":"+1 440 244 3221",
    "sg:postcode":"44052",
    "sg:province":"OH",
    "sg:tags":[
        "alarm",
        "burglar",
        "system",
        "locksmith"
    ],
    "wof:name":"Ganobcik Security Locksmiths",
    "wof:placetype":"venue"
},
  "geometry": {"coordinates":[-82.165695,41.449801],"type":"Point"}
}