{
  "type": "Feature",
  "properties": {
    "addr:full": "10168 Columbia Rd Harrison IN 45030",
    "addr:housenumber": "10168",
    "addr:postcode": "45030",
    "addr:street": "Columbia Rd",
    "iso:country": "US",
    "sg:address": "10168 Columbia Rd",
    "sg:city": "Harrison",
    "sg:classifiers": [
      {
        "category": "Shopping",
        "subcategory": "Florist",
        "type": "Retail Goods"
      }
    ],
    "sg:phone": "+1 513 385 8274",
    "sg:postcode": "45030",
    "sg:province": "IN",
    "sg:tags": [
      "herb",
      "flower"
    ],
    "wof:name": "Margarets Garden",
    "wof:placetype": "venue"
  },
  "geometry": {"coordinates":[-84.665083,39.264292],"type":"Point"}
}
