{
  "type": "Feature",
  "properties": {
    "iso:country":"US",
    "sg:address":"36 W Interstate St",
    "sg:city":"Cleveland",
    "sg:classifiers":[
        {
            "category":"Freight",
            "type":"Transportation"
        }
    ],
    "sg:phone":"+1 440 232 3880",
    "sg:postcode":"44146",
    "sg:province":"OH",
    "sg:tags":[
        "warehouse",
        "public"
    ],
    "wof:name":"S E Mighton Co",
    "wof:placetype":"venue"
},
  "geometry": {"coordinates":[-81.52745400000001,41.37924],"type":"Point"}
}