{
  "type": "Feature",
  "properties": {
    "addr:full": "36 W Interstate St Cleveland OH 44146",
    "addr:housenumber": "36",
    "addr:postcode": "44146",
    "addr:street": "W Interstate St",
    "iso:country": "US",
    "sg:address": "36 W Interstate St",
    "sg:city": "Cleveland",
    "sg:classifiers": [
      {
        "category": "Freight",
        "type": "Transportation"
      }
    ],
    "sg:phone": "+1 440 232 3880",
    "sg:postcode": "44146",
    "sg:province": "OH",
    "sg:tags": [
      "warehouse",
      "public"
    ],
    "wof:name": "S E Mighton Co",
    "wof:placetype": "venue"
  },
  "geometry": {"coordinates":[-81.527454,41.37924],"type":"Point"}
}
