{
  "type": "Feature",
  "properties": {
    "iso:country":"US",
    "sg:address":"11109 Hebron Rd",
    "sg:city":"Hebron",
    "sg:classifiers":[
        {
            "category":"Autos & Motor Vehicles",
            "subcategory":"Boat Sales",
            "type":"Retail Goods"
        }
    ],
    "sg:phone":"+1 740 928 6614",
    "sg:postcode":"43025",
    "sg:province":"OH",
    "sg:tags":[
        "dealer",
        "sales"
    ],
    "wof:name":"Buckeye Lake Water Sports",
    "wof:placetype":"venue"
},
  "geometry": {"coordinates":[-82.48027,39.934311],"type":"Point"}
}