{
  "type": "Feature",
  "properties": {
    "iso:country":"US",
    "sg:address":"27 S 6th St",
    "sg:city":"Zanesville",
    "sg:classifiers":[
        {
            "category":"Real Estate",
            "subcategory":"Surveying",
            "type":"Services"
        }
    ],
    "sg:phone":"+1 740 453 8448",
    "sg:postcode":"43701",
    "sg:province":"OH",
    "sg:tags":[
        "surveyor"
    ],
    "wof:name":"L Peter Dinan & Assoc",
    "wof:placetype":"venue"
},
  "geometry": {"coordinates":[-82.00530500000001,39.939596],"type":"Point"}
}