{
  "type": "Feature",
  "properties": {
    "iso:country":"US",
    "sg:address":"29512 Lisaview Dr",
    "sg:city":"Bay Village",
    "sg:classifiers":[
        {
            "category":"Wholesale",
            "subcategory":"Hardware",
            "type":"Manufacturing & Wholesale Goods"
        }
    ],
    "sg:phone":"+1 440 871 5205",
    "sg:postcode":"44140",
    "sg:province":"OH",
    "sg:tags":[
        "dust",
        "collecting",
        "system"
    ],
    "wof:name":"Thomas C Keyes Inc",
    "wof:placetype":"venue"
},
  "geometry": {"coordinates":[-81.947,41.479304],"type":"Point"}
}