{
  "type": "Feature",
  "properties": {
    "addr:full": "3560 W Market St Fairlawn OH 44333",
    "addr:housenumber": "3560",
    "addr:postcode": "44333",
    "addr:street": "W Market St",
    "iso:country": "US",
    "sg:address": "3560 W Market St",
    "sg:city": "Fairlawn",
    "sg:classifiers": [
      {
        "category": "Manufacturing",
        "subcategory": "Rubber \u0026 Plastics",
        "type": "Manufacturing \u0026 Wholesale Goods"
      }
    ],
    "sg:phone": "+1 330 664 2940",
    "sg:postcode": "44333",
    "sg:province": "OH",
    "sg:tags": [
      "product"
    ],
    "sg:website": "www.cepcarlisle.com",
    "wof:name": "Cep Products",
    "wof:placetype": "venue"
  },
  "geometry": {"coordinates":[-81.626471,41.135457],"type":"Point"}
}
