{
  "type": "Feature",
  "properties": {
    "addr:full": "2868 Northwest Blvd NW Warren OH 44485",
    "addr:housenumber": "2868",
    "addr:postcode": "44485",
    "addr:street": "Northwest Blvd Nw",
    "iso:country": "US",
    "sg:address": "2868 Northwest Blvd NW",
    "sg:city": "Warren",
    "sg:classifiers": [
      {
        "category": "Building \u0026 Trades",
        "subcategory": "Pest Control",
        "type": "Services"
      }
    ],
    "sg:phone": "+1 330 898 4756",
    "sg:postcode": "44485",
    "sg:province": "OH",
    "wof:name": "Ohio's 1st Choice Pest Control",
    "wof:placetype": "venue"
  },
  "geometry": {"coordinates":[-80.856707,41.245017],"type":"Point"}
}
