{
  "type": "Feature",
  "properties": {
    "iso:country":"US",
    "sg:address":"349 Rice St",
    "sg:city":"Elmore",
    "sg:classifiers":[
        {
            "category":"Wholesale",
            "subcategory":"Machinery & Supplies",
            "type":"Manufacturing & Wholesale Goods"
        }
    ],
    "sg:phone":"+1 419 862 0800",
    "sg:postcode":"43416",
    "sg:province":"OH",
    "wof:name":"Midwest Machinery Sales",
    "wof:placetype":"venue"
},
  "geometry": {"coordinates":[-83.29509899999999,41.475569],"type":"Point"}
}