{
  "type": "Feature",
  "properties": {
    "addr:full": "349 Rice St Elmore OH 43416",
    "addr:housenumber": "349",
    "addr:postcode": "43416",
    "addr:street": "Rice St",
    "iso:country": "US",
    "sg:address": "349 Rice St",
    "sg:city": "Elmore",
    "sg:classifiers": [
      {
        "category": "Wholesale",
        "subcategory": "Machinery \u0026 Supplies",
        "type": "Manufacturing \u0026 Wholesale Goods"
      }
    ],
    "sg:phone": "+1 419 862 0800",
    "sg:postcode": "43416",
    "sg:province": "OH",
    "wof:name": "Midwest Machinery Sales",
    "wof:placetype": "venue"
  },
  "geometry": {"coordinates":[-83.295099,41.475569],"type":"Point"}
}
