{
  "type": "Feature",
  "properties": {
    "iso:country":"US",
    "sg:address":"3301 Westbourne Dr",
    "sg:city":"Cincinnati",
    "sg:classifiers":[
        {
            "category":"Health Services",
            "subcategory":"Doctor",
            "type":"Services"
        }
    ],
    "sg:phone":"+1 513 794 5600",
    "sg:postcode":"45248",
    "sg:province":"OH",
    "sg:tags":[
        "physician",
        "surgeon"
    ],
    "wof:name":"Michel Ghastine MD",
    "wof:placetype":"venue"
},
  "geometry": {"coordinates":[-84.629009,39.146307],"type":"Point"}
}