{
  "type": "Feature",
  "properties": {
    "iso:country":"US",
    "sg:address":"2031 W 25th St",
    "sg:city":"Cleveland",
    "sg:classifiers":[
        {
            "category":"Restaurant",
            "type":"Food & Drink"
        }
    ],
    "sg:menulink":"http://www.allmenus.com/oh/cleveland/134281-subway/menu/",
    "sg:phone":"+1 216 771 7827",
    "sg:postcode":"44113",
    "sg:province":"OH",
    "sg:tags":[
        "american",
        "sandwich"
    ],
    "wof:name":"Subway",
    "wof:placetype":"venue"
},
  "geometry": {"coordinates":[-81.703064,41.483808],"type":"Point"}
}