{
  "type": "Feature",
  "properties": {
    "addr:full":"111 S 3rd St Columbus OH 43215",
    "addr:housenumber":"111",
    "addr:postcode":"43215",
    "addr:street":"S 3Rd St",
    "iso:country":"US",
    "sg:address":"111 S 3rd St",
    "sg:city":"Columbus",
    "sg:classifiers":[
        {
            "category":"Food & Beverages",
            "subcategory":"Specialty",
            "type":"Retail Goods"
        }
    ],
    "sg:phone":"+1 614 221 4611",
    "sg:postcode":"43215",
    "sg:province":"OH",
    "sg:tags":[
        "herb"
    ],
    "sg:website":"http://www.gnc.com",
    "wof:name":"GNC",
    "wof:placetype":"venue"
},
  "geometry": {"coordinates":[-82.997524,39.960298],"type":"Point"}
}