{
  "type": "Feature",
  "properties": {
    "iso:country":"US",
    "sg:address":"447 Nilles Rd",
    "sg:city":"Fairfield",
    "sg:classifiers":[
        {
            "category":"Health Services",
            "subcategory":"Doctor",
            "type":"Services"
        }
    ],
    "sg:phone":"+1 513 829 7611",
    "sg:postcode":"45014",
    "sg:province":"OH",
    "sg:tags":[
        "physician",
        "surgeon"
    ],
    "wof:name":"Colon & Rectal Disease Ctr",
    "wof:placetype":"venue"
},
  "geometry": {"coordinates":[-84.560649,39.337669],"type":"Point"}
}