{
  "type": "Feature",
  "properties": {
    "addr:full":"830 E State St Athens OH 45701",
    "addr:housenumber":"830",
    "addr:postcode":"45701",
    "addr:street":"E State St",
    "iso:country":"US",
    "sg:address":"830 E State St",
    "sg:city":"Athens",
    "sg:classifiers":[
        {
            "category":"Autos & Motor Vehicles",
            "subcategory":"Automobile Sales",
            "type":"Retail Goods"
        }
    ],
    "sg:phone":"+1 740 594 2906",
    "sg:postcode":"45701",
    "sg:province":"OH",
    "sg:tags":[
        "car",
        "dealer"
    ],
    "sg:website":"www.donwoodtoyota.com",
    "wof:name":"Don Wood Ford-Lincoln-Mercury",
    "wof:placetype":"venue"
},
  "geometry": {"coordinates":[-82.074028,39.337413],"type":"Point"}
}