{
  "type": "Feature",
  "properties": {
    "addr:full": "805 Pearl Rd Brunswick OH 44212",
    "addr:housenumber": "805",
    "addr:postcode": "44212",
    "addr:street": "Pearl Rd",
    "iso:country": "US",
    "sg:address": "805 Pearl Rd",
    "sg:city": "Brunswick",
    "sg:classifiers": [
      {
        "category": "Restaurant",
        "type": "Food \u0026 Drink"
      }
    ],
    "sg:phone": "+1 330 220 6166",
    "sg:postcode": "44212",
    "sg:province": "OH",
    "wof:name": "Gioninos Pizzeria",
    "wof:placetype": "venue"
  },
  "geometry": {"coordinates":[-81.841112,41.25362],"type":"Point"}
}
