{
  "type": "Feature",
  "properties": {
    "iso:country":"US",
    "sg:address":"805 Pearl Rd",
    "sg:city":"Brunswick",
    "sg:classifiers":[
        {
            "category":"Restaurant",
            "type":"Food & Drink"
        }
    ],
    "sg:phone":"+1 330 220 6166",
    "sg:postcode":"44212",
    "sg:province":"OH",
    "wof:name":"Gioninos Pizzeria",
    "wof:placetype":"venue"
},
  "geometry": {"coordinates":[-81.841112,41.25362],"type":"Point"}
}