{
  "type": "Feature",
  "properties": {
    "iso:country":"US",
    "sg:address":"3642 Pigeon Run Ave SW",
    "sg:city":"Massillon",
    "sg:classifiers":[
        {
            "category":"Professional",
            "subcategory":"Engineering",
            "type":"Services"
        }
    ],
    "sg:phone":"+1 330 833 7980",
    "sg:postcode":"44647",
    "sg:province":"OH",
    "sg:tags":[
        "engineer"
    ],
    "wof:name":"Fritz Brothers Engineering",
    "wof:placetype":"venue"
},
  "geometry": {"coordinates":[-81.560106,40.75738],"type":"Point"}
}