{
  "type": "Feature",
  "properties": {
    "addr:full": "3642 Pigeon Run Ave SW Massillon OH 44647",
    "addr:housenumber": "3642",
    "addr:postcode": "44647",
    "addr:street": "Pigeon Run Ave Sw",
    "iso:country": "US",
    "sg:address": "3642 Pigeon Run Ave SW",
    "sg:city": "Massillon",
    "sg:classifiers": [
      {
        "category": "Professional",
        "subcategory": "Engineering",
        "type": "Services"
      }
    ],
    "sg:phone": "+1 330 833 7980",
    "sg:postcode": "44647",
    "sg:province": "OH",
    "sg:tags": [
      "engineer"
    ],
    "wof:name": "Fritz Brothers Engineering",
    "wof:placetype": "venue"
  },
  "geometry": {"coordinates":[-81.560106,40.75738],"type":"Point"}
}
