{
  "type": "Feature",
  "properties": {
    "iso:country":"US",
    "sg:address":"4402 Redfern Rd",
    "sg:city":"Cleveland",
    "sg:classifiers":[
        {
            "category":"Shopping",
            "subcategory":"Bicycles & Sporting Goods",
            "type":"Retail Goods"
        }
    ],
    "sg:phone":"+1 440 884 2991",
    "sg:postcode":"44134",
    "sg:province":"OH",
    "wof:name":"Fairbanks Firearms",
    "wof:placetype":"venue"
},
  "geometry": {"coordinates":[-81.71865699999999,41.399684],"type":"Point"}
}