{
  "type": "Feature",
  "properties": {
    "addr:full": "1221 Marion Rd Columbus OH 43207",
    "addr:housenumber": "1221",
    "addr:postcode": "43207",
    "addr:street": "Marion Rd",
    "iso:country": "US",
    "sg:address": "1221 Marion Rd",
    "sg:city": "Columbus",
    "sg:classifiers": [
      {
        "category": "Building \u0026 Trades",
        "subcategory": "Construction",
        "type": "Services"
      }
    ],
    "sg:phone": "+1 614 884 0404",
    "sg:postcode": "43207",
    "sg:province": "OH",
    "sg:tags": [
      "roofing",
      "contractor"
    ],
    "wof:name": "Columbus Roofing \u0026 Sheet Metal",
    "wof:placetype": "venue"
  },
  "geometry": {"coordinates":[-82.963089,39.922433],"type":"Point"}
}
