{
  "type": "Feature",
  "properties": {
    "iso:country":"US",
    "sg:address":"5333 Northfield Rd",
    "sg:city":"Cleveland",
    "sg:classifiers":[
        {
            "category":"Social Services",
            "subcategory":"Job Training",
            "type":"Services"
        }
    ],
    "sg:phone":"+1 216 587 1836",
    "sg:postcode":"44146",
    "sg:province":"OH",
    "sg:tags":[
        "rehabilitation"
    ],
    "wof:name":"Young's Rehab",
    "wof:placetype":"venue"
},
  "geometry": {"coordinates":[-81.527366,41.416928],"type":"Point"}
}