{
  "type": "Feature",
  "properties": {
    "iso:country":"US",
    "sg:address":"102 W Poe Rd",
    "sg:city":"Bowling Green",
    "sg:classifiers":[
        {
            "category":"Home & Garden",
            "subcategory":"Garden Supply",
            "type":"Retail Goods"
        }
    ],
    "sg:phone":"+1 419 353 8323",
    "sg:postcode":"43402",
    "sg:province":"OH",
    "sg:tags":[
        "lawn",
        "mower"
    ],
    "wof:name":"Book's Lawn Equipment",
    "wof:placetype":"venue"
},
  "geometry": {"coordinates":[-83.650476,41.385705],"type":"Point"}
}