{
  "type": "Feature",
  "properties": {
    "iso:country":"US",
    "sg:address":"1196 Tibbetts Wick Rd",
    "sg:city":"Girard",
    "sg:classifiers":[
        {
            "category":"Building & Trades",
            "subcategory":"Plumbing",
            "type":"Services"
        }
    ],
    "sg:phone":"+1 330 539 6070",
    "sg:postcode":"44420",
    "sg:province":"OH",
    "sg:tags":[
        "plumbing",
        "contractor"
    ],
    "wof:name":"Adam & Eve Plumbing",
    "wof:placetype":"venue"
},
  "geometry": {"coordinates":[-80.685093,41.184465],"type":"Point"}
}