{
  "type": "Feature",
  "properties": {
    "addr:full": "2074 Miles Rd Cincinnati OH 45231",
    "addr:housenumber": "2074",
    "addr:postcode": "45231",
    "addr:street": "Miles Rd",
    "iso:country": "US",
    "sg:address": "2074 Miles Rd",
    "sg:city": "Cincinnati",
    "sg:classifiers": [
      {
        "category": "Home \u0026 Garden",
        "subcategory": "Building Materials",
        "type": "Retail Goods"
      }
    ],
    "sg:phone": "+1 513 674 0400",
    "sg:postcode": "45231",
    "sg:province": "OH",
    "sg:tags": [
      "windows"
    ],
    "wof:name": "Anderson Home Improvement",
    "wof:placetype": "venue"
  },
  "geometry": {"coordinates":[-84.556263,39.251653],"type":"Point"}
}
