{
  "type": "Feature",
  "properties": {
    "addr:full":"8473 State Rte 41 NW Washington Court House OH 43160",
    "addr:housenumber":"8473",
    "addr:postcode":"43160",
    "addr:street":"State Rte 41 Nw",
    "iso:country":"US",
    "sg:address":"8473 State Rte 41 NW",
    "sg:city":"Washington Court House",
    "sg:phone":"+1 740 426 6454",
    "sg:postcode":"43160",
    "sg:province":"OH",
    "sg:tags":[
        "farm",
        "corn",
        "soybean"
    ],
    "wof:name":"Maple Hill Farms",
    "wof:placetype":"venue"
},
  "geometry": {"coordinates":[-83.530496,39.628014],"type":"Point"}
}