{
  "type": "Feature",
  "properties": {
    "iso:country":"US",
    "sg:address":"343 Ashwood Dr",
    "sg:city":"Elyria",
    "sg:classifiers":[
        {
            "category":"Shopping",
            "subcategory":"Computers & Home Electronics",
            "type":"Retail Goods"
        }
    ],
    "sg:phone":"+1 440 323 3423",
    "sg:postcode":"44035",
    "sg:province":"OH",
    "sg:tags":[
        "software"
    ],
    "wof:name":"Computer Custom Programs",
    "wof:placetype":"venue"
},
  "geometry": {"coordinates":[-82.151395,41.354182],"type":"Point"}
}