{
  "type": "Feature",
  "properties": {
    "addr:full": "16 W Washington St Athens OH 45701",
    "addr:housenumber": "16",
    "addr:postcode": "45701",
    "addr:street": "W Washington St",
    "iso:country": "US",
    "sg:address": "16 W Washington St",
    "sg:city": "Athens",
    "sg:classifiers": [
      {
        "category": "Professional",
        "type": "Services"
      }
    ],
    "sg:phone": "+1 740 592 9922",
    "sg:postcode": "45701",
    "sg:province": "OH",
    "wof:name": "Mcfadden Insurance Svc",
    "wof:placetype": "venue"
  },
  "geometry": {"coordinates":[-82.101866,39.329304],"type":"Point"}
}
