{
  "type": "Feature",
  "properties": {
    "addr:full":"4591 Orr Rd New Washington OH 44854",
    "addr:housenumber":"4591",
    "addr:postcode":"44854",
    "addr:street":"Orr Rd",
    "iso:country":"US",
    "sg:address":"4591 Orr Rd",
    "sg:city":"New Washington",
    "sg:classifiers":[
        {
            "category":"Real Estate",
            "subcategory":"Real Estate Operator",
            "type":"Services"
        }
    ],
    "sg:phone":"+1 419 492 2761",
    "sg:postcode":"44854",
    "sg:province":"OH",
    "sg:tags":[
        "property",
        "lessor"
    ],
    "wof:name":"Donald Shealy",
    "wof:placetype":"venue"
},
  "geometry": {"coordinates":[-82.897301,40.935945],"type":"Point"}
}