{
  "type": "Feature",
  "properties": {
    "iso:country":"US",
    "sg:address":"11201 Detroit Ave",
    "sg:city":"Cleveland",
    "sg:classifiers":[
        {
            "category":"Restaurant",
            "type":"Food & Drink"
        }
    ],
    "sg:phone":"+1 216 227 5474",
    "sg:postcode":"44102",
    "sg:province":"OH",
    "sg:tags":[
        "caterer"
    ],
    "sg:website":"www.kishculinary.com",
    "wof:name":"Kish Culinary Co",
    "wof:placetype":"venue"
},
  "geometry": {"coordinates":[-81.76613999999999,41.482945],"type":"Point"}
}