{
  "type": "Feature",
  "properties": {
    "addr:full": "11201 Detroit Ave Cleveland OH 44102",
    "addr:housenumber": "11201",
    "addr:postcode": "44102",
    "addr:street": "Detroit Ave",
    "iso:country": "US",
    "sg:address": "11201 Detroit Ave",
    "sg:city": "Cleveland",
    "sg:classifiers": [
      {
        "category": "Restaurant",
        "type": "Food \u0026 Drink"
      }
    ],
    "sg:phone": "+1 216 227 5474",
    "sg:postcode": "44102",
    "sg:province": "OH",
    "sg:tags": [
      "caterer"
    ],
    "sg:website": "www.kishculinary.com",
    "wof:name": "Kish Culinary Co",
    "wof:placetype": "venue"
  },
  "geometry": {"coordinates":[-81.76614,41.482945],"type":"Point"}
}
