{
  "type": "Feature",
  "properties": {
    "iso:country":"US",
    "sg:address":"4426 Boston Rd",
    "sg:city":"Strongsville",
    "sg:classifiers":[
        {
            "category":"Building & Trades",
            "subcategory":"Construction",
            "type":"Services"
        }
    ],
    "sg:phone":"+1 440 823 6459",
    "sg:postcode":"44149",
    "sg:province":"OH",
    "sg:tags":[
        "general"
    ],
    "wof:name":"Level One Construction",
    "wof:placetype":"venue"
},
  "geometry": {"coordinates":[-81.85270199999999,41.275339],"type":"Point"}
}