{
  "type": "Feature",
  "properties": {
    "iso:country":"US",
    "sg:address":"13800 Ulery Rd",
    "sg:city":"Sunbury",
    "sg:classifiers":[
        {
            "category":"Freight",
            "type":"Transportation"
        }
    ],
    "sg:phone":"+1 740 524 0225",
    "sg:postcode":"43074",
    "sg:province":"OH",
    "sg:tags":[
        "operator",
        "local",
        "trucking"
    ],
    "wof:name":"Old Shinies Hauling",
    "wof:placetype":"venue"
},
  "geometry": {"coordinates":[-82.796125,40.324959],"type":"Point"}
}