{
  "type": "Feature",
  "properties": {
    "addr:full":"3650 Chitty Rd Sabina OH 45169",
    "addr:postcode":"3650;45169",
    "addr:street":"Chitty Rd",
    "iso:country":"US",
    "sg:address":"3650 Chitty Rd",
    "sg:city":"Sabina",
    "sg:classifiers":[
        {
            "category":"Real Estate",
            "subcategory":"Real Estate Operator",
            "type":"Services"
        }
    ],
    "sg:phone":"+1 937 453 2252",
    "sg:postcode":"45169",
    "sg:province":"OH",
    "sg:tags":[
        "property",
        "lessor"
    ],
    "wof:name":"Lewis Chitty",
    "wof:placetype":"venue"
},
  "geometry": {"coordinates":[-83.68591499999999,39.569061],"type":"Point"}
}