{
  "type": "Feature",
  "properties": {
    "addr:full":"20 High St Hamilton OH 45011",
    "addr:housenumber":"20",
    "addr:postcode":"45011",
    "addr:street":"High St",
    "iso:country":"US",
    "sg:address":"20 High St",
    "sg:city":"Hamilton",
    "sg:classifiers":[
        {
            "category":"Professional",
            "subcategory":"Computer Services",
            "type":"Services"
        }
    ],
    "sg:phone":"+1 513 737 8500",
    "sg:postcode":"45011",
    "sg:province":"OH",
    "sg:tags":[
        "repair"
    ],
    "wof:name":"Computer Troubleshooters",
    "wof:placetype":"venue"
},
  "geometry": {"coordinates":[-84.563603,39.400388],"type":"Point"}
}