{
  "type": "Feature",
  "properties": {
    "iso:country":"US",
    "sg:address":"17702 Nottingham Rd",
    "sg:city":"Cleveland",
    "sg:classifiers":[
        {
            "category":"Social Services",
            "subcategory":"Adult Care",
            "type":"Services"
        }
    ],
    "sg:phone":"+1 216 486 5258",
    "sg:postcode":"44119",
    "sg:province":"OH",
    "sg:tags":[
        "residential"
    ],
    "wof:name":"Nottingham Home",
    "wof:placetype":"venue"
},
  "geometry": {"coordinates":[-81.554986,41.579388],"type":"Point"}
}