{
  "type": "Feature",
  "properties": {
    "addr:full":"10600 Chester Rd Cincinnati OH 45215",
    "addr:housenumber":"10600",
    "addr:postcode":"45215",
    "addr:street":"Chester Rd",
    "iso:country":"US",
    "sg:address":"10600 Chester Rd",
    "sg:city":"Cincinnati",
    "sg:classifiers":[
        {
            "category":"Manufacturing",
            "subcategory":"Printing",
            "type":"Manufacturing & Wholesale Goods"
        }
    ],
    "sg:phone":"+1 513 542 1522",
    "sg:postcode":"45215",
    "sg:province":"OH",
    "sg:tags":[
        "printer"
    ],
    "wof:name":"T L Krieg Offset Inc",
    "wof:placetype":"venue"
},
  "geometry": {"coordinates":[-84.45071799999999,39.262353],"type":"Point"}
}