{
  "type": "Feature",
  "properties": {
    "addr:full":"5643 Cheviot Rd Cincinnati OH 45247",
    "addr:housenumber":"5643",
    "addr:postcode":"45247",
    "addr:street":"Cheviot Rd",
    "iso:country":"US",
    "sg:address":"5643 Cheviot Rd",
    "sg:city":"Cincinnati",
    "sg:classifiers":[
        {
            "category":"Utilities",
            "subcategory":"Telephone",
            "type":"Services"
        }
    ],
    "sg:phone":"+1 513 923 9003",
    "sg:postcode":"45247",
    "sg:province":"OH",
    "sg:tags":[
        "telecommunication"
    ],
    "wof:name":"Sienna Communications Group",
    "wof:placetype":"venue"
},
  "geometry": {"coordinates":[-84.59929700000001,39.191429],"type":"Point"}
}