{
  "type": "Feature",
  "properties": {
    "iso:country":"US",
    "sg:address":"75 Locust Dr",
    "sg:city":"Springboro",
    "sg:classifiers":[
        {
            "category":"Building & Trades",
            "subcategory":"Construction",
            "type":"Services"
        }
    ],
    "sg:phone":"+1 937 748 6315",
    "sg:postcode":"45066",
    "sg:province":"OH",
    "sg:tags":[
        "house"
    ],
    "wof:name":"Handyman Can Home Improvers",
    "wof:placetype":"venue"
},
  "geometry": {"coordinates":[-84.23775000000001,39.548624],"type":"Point"}
}