{
  "type": "Feature",
  "properties": {
    "addr:full":"8400 Sadie Thomas Rd Johnstown OH 43031",
    "addr:housenumber":"8400",
    "addr:postcode":"43031",
    "addr:street":"Sadie Thomas Rd",
    "iso:country":"US",
    "sg:address":"8400 Sadie Thomas Rd",
    "sg:city":"Johnstown",
    "sg:classifiers":[
        {
            "category":"Manufacturing",
            "subcategory":"Wood Products",
            "type":"Manufacturing & Wholesale Goods"
        },
        {
            "category":"Building & Trades",
            "subcategory":"Construction",
            "type":"Services"
        }
    ],
    "sg:phone":"+1 740 967 2224",
    "sg:postcode":"43031",
    "sg:province":"OH",
    "sg:tags":[
        "mfg",
        "woodworker"
    ],
    "wof:name":"Anderson Bomlitz Custom Design",
    "wof:placetype":"venue"
},
  "geometry": {"coordinates":[-82.649237,40.121144],"type":"Point"}
}