{
  "type": "Feature",
  "properties": {
    "addr:full": "7777 Exchange Rd Cleveland OH 44125",
    "addr:housenumber": "7777",
    "addr:postcode": "44125",
    "addr:street": "Exchange Rd",
    "iso:country": "US",
    "sg:address": "7777 Exchange Rd",
    "sg:city": "Cleveland",
    "sg:classifiers": [
      {
        "category": "Wholesale",
        "subcategory": "Office Equipment",
        "type": "Manufacturing \u0026 Wholesale Goods"
      }
    ],
    "sg:phone": "+1 216 901 1786",
    "sg:postcode": "44125",
    "sg:province": "OH",
    "sg:tags": [
      "machine",
      "addressing",
      "supply"
    ],
    "wof:name": "Addressograph Products",
    "wof:placetype": "venue"
  },
  "geometry": {"coordinates":[-81.630175,41.407928],"type":"Point"}
}
