{
  "type": "Feature",
  "properties": {
    "addr:full": "3363 Rocky Point Rd Springfield OH 45502",
    "addr:housenumber": "3363",
    "addr:postcode": "45502",
    "addr:street": "Rocky Point Rd",
    "iso:country": "US",
    "sg:address": "3363 Rocky Point Rd",
    "sg:city": "Springfield",
    "sg:classifiers": [
      {
        "category": "Building \u0026 Trades",
        "subcategory": "Construction",
        "type": "Services"
      }
    ],
    "sg:phone": "+1 937 322 1223",
    "sg:postcode": "45502",
    "sg:province": "OH",
    "sg:tags": [
      "carpentry",
      "contractor"
    ],
    "wof:name": "Modern Renovations",
    "wof:placetype": "venue"
  },
  "geometry": {"coordinates":[-83.871442,39.869044],"type":"Point"}
}
