{
  "type": "Feature",
  "properties": {
    "addr:full":"120 N 4th St Coshocton OH 43812",
    "addr:housenumber":"120",
    "addr:postcode":"43812",
    "addr:street":"N 4Th St",
    "iso:country":"US",
    "sg:address":"120 N 4th St",
    "sg:city":"Coshocton",
    "sg:classifiers":[
        {
            "category":"Social Services",
            "type":"Services"
        }
    ],
    "sg:phone":"+1 740 622 2829",
    "sg:postcode":"43812",
    "sg:province":"OH",
    "sg:tags":[
        "information",
        "planning",
        "center",
        "family"
    ],
    "wof:name":"Family Planning",
    "wof:placetype":"venue"
},
  "geometry": {"coordinates":[-81.86512999999999,40.274722],"type":"Point"}
}