{
  "type": "Feature",
  "properties": {
    "iso:country":"US",
    "sg:address":"6753 Lakeside Cir W",
    "sg:city":"Columbus",
    "sg:classifiers":[
        {
            "category":"Food & Beverages",
            "subcategory":"Groceries & Convenience Stores",
            "type":"Retail Goods"
        }
    ],
    "sg:phone":"+1 614 985 0169",
    "sg:postcode":"43085",
    "sg:province":"OH",
    "wof:name":"Marion Marathon Corporation",
    "wof:placetype":"venue"
},
  "geometry": {"coordinates":[-83.051272,40.095852],"type":"Point"}
}