{
  "type": "Feature",
  "properties": {
    "iso:country":"US",
    "sg:address":"7001 Mayfield Ave",
    "sg:city":"Cincinnati",
    "sg:classifiers":[
        {
            "category":"Shopping",
            "subcategory":"Gifts & Souvenirs",
            "type":"Retail Goods"
        }
    ],
    "sg:phone":"+1 513 791 5516",
    "sg:postcode":"45243",
    "sg:province":"OH",
    "wof:name":"Wreaths N Things By Jackie",
    "wof:placetype":"venue"
},
  "geometry": {"coordinates":[-84.369243,39.189356],"type":"Point"}
}