{
  "type": "Feature",
  "properties": {
    "addr:full":"2455 Billingsley Rd Columbus OH 43235",
    "addr:housenumber":"2455",
    "addr:postcode":"43235",
    "addr:street":"Billingsley Rd",
    "iso:country":"US",
    "sg:address":"2455 Billingsley Rd",
    "sg:city":"Columbus",
    "sg:classifiers":[
        {
            "category":"Autos & Motor Vehicles",
            "subcategory":"Automobile Sales",
            "type":"Retail Goods"
        }
    ],
    "sg:phone":"+1 614 792 2455",
    "sg:postcode":"43235",
    "sg:province":"OH",
    "sg:tags":[
        "car",
        "used",
        "dealer"
    ],
    "sg:website":"www.byersmazdasubaru.com",
    "wof:name":"Byers Mazda Subaru",
    "wof:placetype":"venue"
},
  "geometry": {"coordinates":[-83.08119000000001,40.112239],"type":"Point"}
}