{
  "type": "Feature",
  "properties": {
    "addr:full": "1850 Franklin Ave Toronto OH 43964",
    "addr:housenumber": "1850",
    "addr:postcode": "43964",
    "addr:street": "Franklin Ave",
    "iso:country": "US",
    "sg:address": "1850 Franklin Ave",
    "sg:city": "Toronto",
    "sg:classifiers": [
      {
        "category": "Restaurant",
        "type": "Food \u0026 Drink"
      }
    ],
    "sg:phone": "+1 740 537 5370",
    "sg:postcode": "43964",
    "sg:province": "OH",
    "wof:name": "Mc Donald's",
    "wof:placetype": "venue"
  },
  "geometry": {"coordinates":[-80.616849,40.450179],"type":"Point"}
}
