{
  "type": "Feature",
  "properties": {
    "iso:country":"US",
    "sg:address":"17312 Long Meadow Trl",
    "sg:city":"Chagrin Falls",
    "sg:classifiers":[
        {
            "category":"Wholesale",
            "subcategory":"Electrical",
            "type":"Manufacturing & Wholesale Goods"
        }
    ],
    "sg:phone":"+1 440 543 2543",
    "sg:postcode":"44023",
    "sg:province":"OH",
    "sg:tags":[
        "equipment",
        "legal"
    ],
    "sg:website":"www.patriotsecurity.net",
    "wof:name":"Patriot Security Systems Inc",
    "wof:placetype":"venue"
},
  "geometry": {"coordinates":[-81.32564600000001,41.396538],"type":"Point"}
}