{
  "type": "Feature",
  "properties": {
    "addr:full": "17312 Long Meadow Trl Chagrin Falls OH 44023",
    "addr:housenumber": "17312",
    "addr:postcode": "44023",
    "addr:street": "Long Meadow Trl",
    "iso:country": "US",
    "sg:address": "17312 Long Meadow Trl",
    "sg:city": "Chagrin Falls",
    "sg:classifiers": [
      {
        "category": "Wholesale",
        "subcategory": "Electrical",
        "type": "Manufacturing \u0026 Wholesale Goods"
      }
    ],
    "sg:phone": "+1 440 543 2543",
    "sg:postcode": "44023",
    "sg:province": "OH",
    "sg:tags": [
      "equipment",
      "legal"
    ],
    "sg:website": "www.patriotsecurity.net",
    "wof:name": "Patriot Security Systems Inc",
    "wof:placetype": "venue"
  },
  "geometry": {"coordinates":[-81.325646,41.396538],"type":"Point"}
}
