{
  "type": "Feature",
  "properties": {
    "addr:full":"4777 Farnhurst Rd Cleveland OH 44124",
    "addr:housenumber":"4777",
    "addr:postcode":"44124",
    "addr:street":"Farnhurst Rd",
    "iso:country":"US",
    "sg:address":"4777 Farnhurst Rd",
    "sg:city":"Cleveland",
    "sg:classifiers":[
        {
            "category":"Professional",
            "type":"Services"
        }
    ],
    "sg:phone":"+1 216 691 2221",
    "sg:postcode":"44124",
    "sg:province":"OH",
    "sg:tags":[
        "establishment"
    ],
    "wof:name":"South Euclid Lyndhurst Board",
    "wof:placetype":"venue"
},
  "geometry": {"coordinates":[-81.50909,41.523307],"type":"Point"}
}