{
  "type": "Feature",
  "properties": {
    "addr:full": "1306 S Pennsylvania Ave Wellston OH 45692",
    "addr:housenumber": "1306",
    "addr:postcode": "45692",
    "addr:street": "S Pennsylvania Ave",
    "iso:country": "US",
    "sg:address": "1306 S Pennsylvania Ave",
    "sg:city": "Wellston",
    "sg:classifiers": [
      {
        "category": "Home \u0026 Garden",
        "subcategory": "Furniture",
        "type": "Retail Goods"
      }
    ],
    "sg:phone": "+1 740 384 3895",
    "sg:postcode": "45692",
    "sg:province": "OH",
    "sg:tags": [
      "household"
    ],
    "wof:name": "Open Sofa \u0026 Mattress Outlet",
    "wof:placetype": "venue"
  },
  "geometry": {"coordinates":[-82.534538,39.111206],"type":"Point"}
}
