{
  "type": "Feature",
  "properties": {
    "addr:full": "4547 Vista Dr NW Canal Winchester OH 43110",
    "addr:housenumber": "4547",
    "addr:postcode": "43110",
    "addr:street": "Vista Dr Nw",
    "iso:country": "US",
    "sg:address": "4547 Vista Dr NW",
    "sg:city": "Canal Winchester",
    "sg:classifiers": [
      {
        "category": "Professional",
        "type": "Services"
      }
    ],
    "sg:phone": "+1 614 833 4518",
    "sg:postcode": "43110",
    "sg:province": "OH",
    "wof:name": "Reed M Baily",
    "wof:placetype": "venue"
  },
  "geometry": {"coordinates":[-82.791446,39.802818],"type":"Point"}
}
