{
  "type": "Feature",
  "properties": {
    "iso:country":"US",
    "sg:address":"3269 Rockyhill Dr",
    "sg:city":"Hamilton",
    "sg:classifiers":[
        {
            "category":"Professional",
            "type":"Services"
        }
    ],
    "sg:phone":"+1 513 856 7770",
    "sg:postcode":"45013",
    "sg:province":"IN",
    "wof:name":"Wendy Bridge",
    "wof:placetype":"venue"
},
  "geometry": {"coordinates":[-84.658247,39.336135],"type":"Point"}
}