{
  "type": "Feature",
  "properties": {
    "iso:country":"US",
    "sg:address":"4633 Northfield Rd",
    "sg:city":"Cleveland",
    "sg:classifiers":[
        {
            "category":"Social Services",
            "type":"Services"
        }
    ],
    "sg:phone":"+1 216 475 6878",
    "sg:postcode":"44128",
    "sg:province":"OH",
    "sg:tags":[
        "organization",
        "welfare"
    ],
    "wof:name":"Salvation Army Thrift Store",
    "wof:placetype":"venue"
},
  "geometry": {"coordinates":[-81.525642,41.428171],"type":"Point"}
}