{
  "type": "Feature",
  "properties": {
    "addr:full":"345 Allen Ave Chillicothe OH 45601",
    "addr:housenumber":"345",
    "addr:postcode":"45601",
    "addr:street":"Allen Ave",
    "iso:country":"US",
    "sg:address":"345 Allen Ave",
    "sg:city":"Chillicothe",
    "sg:classifiers":[
        {
            "category":"Government",
            "subcategory":"Office",
            "type":"Public Place"
        }
    ],
    "sg:phone":"+1 740 773 1574",
    "sg:postcode":"45601",
    "sg:province":"OH",
    "wof:name":"Federal Express Property Prgrm",
    "wof:placetype":"venue"
},
  "geometry": {"coordinates":[-82.992339,39.341347],"type":"Point"}
}