{
  "type": "Feature",
  "properties": {
    "addr:full":"9515 Greystone Pkwy Brecksville OH 44141",
    "addr:housenumber":"9515",
    "addr:postcode":"44141",
    "addr:street":"Greystone Pkwy",
    "iso:country":"US",
    "sg:address":"9515 Greystone Pkwy",
    "sg:city":"Brecksville",
    "sg:classifiers":[
        {
            "category":"Freight",
            "type":"Transportation"
        }
    ],
    "sg:phone":"+1 440 717 0760",
    "sg:postcode":"44141",
    "sg:province":"OH",
    "sg:tags":[
        "hauling",
        "trucking"
    ],
    "wof:name":"J P Logistics",
    "wof:placetype":"venue"
},
  "geometry": {"coordinates":[-81.631733,41.300626],"type":"Point"}
}