{
  "type": "Feature",
  "properties": {
    "iso:country":"US",
    "sg:address":"10820 State Rte 347",
    "sg:city":"East Liberty",
    "sg:classifiers":[
        {
            "category":"Professional",
            "subcategory":"Research",
            "type":"Services"
        }
    ],
    "sg:phone":"+1 937 666 2011",
    "sg:postcode":"43319",
    "sg:province":"OH",
    "wof:name":"Transportation Research Ctr",
    "wof:placetype":"venue"
},
  "geometry": {"coordinates":[-83.565043,40.339506],"type":"Point"}
}