{
  "type": "Feature",
  "properties": {
    "addr:full": "4126 N Main St Findlay OH 45840",
    "addr:housenumber": "4126",
    "addr:postcode": "45840",
    "addr:street": "N Main St",
    "iso:country": "US",
    "sg:address": "4126 N Main St",
    "sg:city": "Findlay",
    "sg:classifiers": [
      {
        "category": "Building \u0026 Trades",
        "subcategory": "Electrical",
        "type": "Services"
      }
    ],
    "sg:phone": "+1 419 422 0118",
    "sg:postcode": "45840",
    "sg:province": "OH",
    "sg:tags": [
      "electrical",
      "contractor"
    ],
    "wof:name": "Girdler \u0026 Co",
    "wof:placetype": "venue"
  },
  "geometry": {"coordinates":[-83.649987,41.089597],"type":"Point"}
}
