{
  "type": "Feature",
  "properties": {
    "addr:full":"3893 Market St Youngstown OH 44507",
    "addr:housenumber":"3893",
    "addr:postcode":"44507",
    "addr:street":"Market St",
    "iso:country":"US",
    "sg:address":"3893 Market St",
    "sg:city":"Youngstown",
    "sg:classifiers":[
        {
            "category":"Health Services",
            "subcategory":"Doctor",
            "type":"Services"
        }
    ],
    "sg:phone":"+1 330 743 4058",
    "sg:postcode":"44507",
    "sg:province":"OH",
    "sg:tags":[
        "physician",
        "surgeon"
    ],
    "sg:website":"www.lippygroup.com",
    "wof:name":"Lippy Group Of ENT",
    "wof:placetype":"venue"
},
  "geometry": {"coordinates":[-80.661715,41.061647],"type":"Point"}
}