{
  "type": "Feature",
  "properties": {
    "iso:country":"US",
    "sg:address":"7371 Dixie Hwy",
    "sg:city":"Fairfield",
    "sg:classifiers":[
        {
            "category":"Home & Garden",
            "subcategory":"Carpets & Floor Coverings",
            "type":"Retail Goods"
        }
    ],
    "sg:phone":"+1 513 874 7800",
    "sg:postcode":"45014",
    "sg:province":"OH",
    "sg:tags":[
        "dealer",
        "rug"
    ],
    "wof:name":"Dalton Georgia Carpets",
    "wof:placetype":"venue"
},
  "geometry": {"coordinates":[-84.486627,39.306172],"type":"Point"}
}