{
  "type": "Feature",
  "properties": {
    "addr:full":"3261 W Siebenthaler Ave Dayton OH 45406",
    "addr:housenumber":"3261",
    "addr:postcode":"45406",
    "addr:street":"W Siebenthaler Ave",
    "iso:country":"US",
    "sg:address":"3261 W Siebenthaler Ave",
    "sg:city":"Dayton",
    "sg:classifiers":[
        {
            "category":"Restaurant",
            "type":"Food & Drink"
        }
    ],
    "sg:phone":"+1 937 275 2859",
    "sg:postcode":"45406",
    "sg:province":"OH",
    "sg:tags":[
        "chinese"
    ],
    "wof:name":"Szechuan Taste",
    "wof:placetype":"venue"
},
  "geometry": {"coordinates":[-84.244668,39.798207],"type":"Point"}
}