{
  "type": "Feature",
  "properties": {
    "iso:country":"US",
    "sg:address":"3204 Johnson Rd",
    "sg:city":"Steubenville",
    "sg:classifiers":[
        {
            "category":"Health Services",
            "subcategory":"Hospital",
            "type":"Services"
        },
        {
            "category":"Health Services",
            "subcategory":"Clinic",
            "type":"Services"
        }
    ],
    "sg:phone":"+1 740 264 8700",
    "sg:postcode":"43952",
    "sg:province":"OH",
    "wof:name":"Teramana Cancer Center",
    "wof:placetype":"venue"
},
  "geometry": {"coordinates":[-80.65861599999999,40.366735],"type":"Point"}
}