{
  "type": "Feature",
  "properties": {
    "addr:full": "3204 Johnson Rd Steubenville OH 43952",
    "addr:housenumber": "3204",
    "addr:postcode": "43952",
    "addr:street": "Johnson Rd",
    "iso:country": "US",
    "sg:address": "3204 Johnson Rd",
    "sg:city": "Steubenville",
    "sg:classifiers": [
      {
        "category": "Health Services",
        "subcategory": "Hospital",
        "type": "Services"
      },
      {
        "category": "Health Services",
        "subcategory": "Clinic",
        "type": "Services"
      }
    ],
    "sg:phone": "+1 740 264 8700",
    "sg:postcode": "43952",
    "sg:province": "OH",
    "wof:name": "Teramana Cancer Center",
    "wof:placetype": "venue"
  },
  "geometry": {"coordinates":[-80.658616,40.366735],"type":"Point"}
}
