{
  "type": "Feature",
  "properties": {
    "addr:full": "3582 Caleb Ave Cuyahoga Falls OH 44221",
    "addr:housenumber": "3582",
    "addr:postcode": "44221",
    "addr:street": "Caleb Ave",
    "iso:country": "US",
    "sg:address": "3582 Caleb Ave",
    "sg:city": "Cuyahoga Falls",
    "sg:classifiers": [
      {
        "category": "Insurance",
        "subcategory": "Hazard Insurance",
        "type": "Services"
      }
    ],
    "sg:phone": "+1 330 920 9576",
    "sg:postcode": "44221",
    "sg:province": "OH",
    "sg:tags": [
      "bond"
    ],
    "wof:name": "A Second Chance Bail Bonds",
    "wof:placetype": "venue"
  },
  "geometry": {"coordinates":[-81.485157,41.164555],"type":"Point"}
}
