{
  "type": "Feature",
  "properties": {
    "addr:full":"11121 Western Ave Cleveland OH 44111",
    "addr:housenumber":"11121",
    "addr:postcode":"44111",
    "addr:street":"Western Ave",
    "iso:country":"US",
    "sg:address":"11121 Western Ave",
    "sg:city":"Cleveland",
    "sg:classifiers":[
        {
            "category":"Bars & Pubs",
            "type":"Food & Drink"
        }
    ],
    "sg:phone":"+1 216 688 0076",
    "sg:postcode":"44111",
    "sg:province":"OH",
    "wof:name":"Kickstand Smitty's Saloon",
    "wof:placetype":"venue"
},
  "geometry": {"coordinates":[-81.764618,41.470314],"type":"Point"}
}