{
  "type": "Feature",
  "properties": {
    "addr:full":"806 Shannon Ave Cuyahoga Falls OH 44221",
    "addr:housenumber":"806",
    "addr:postcode":"44221",
    "addr:street":"Shannon Ave",
    "iso:country":"US",
    "sg:address":"806 Shannon Ave",
    "sg:city":"Cuyahoga Falls",
    "sg:classifiers":[
        {
            "category":"Professional",
            "subcategory":"Accounting & Tax Preparation",
            "type":"Services"
        }
    ],
    "sg:phone":"+1 330 928 1598",
    "sg:postcode":"44221",
    "sg:province":"OH",
    "sg:tags":[
        "consultant"
    ],
    "wof:name":"Richard J Culp Tax Cnsltnt",
    "wof:placetype":"venue"
},
  "geometry": {"coordinates":[-81.471253,41.123003],"type":"Point"}
}