{
  "type": "Feature",
  "properties": {
    "iso:country":"US",
    "sg:address":"1601 Bethel Rd",
    "sg:city":"Columbus",
    "sg:classifiers":[
        {
            "category":"Shopping",
            "type":"Retail Goods"
        }
    ],
    "sg:phone":"+1 614 457 5410",
    "sg:postcode":"43220",
    "sg:province":"OH",
    "sg:tags":[
        "merchandise"
    ],
    "wof:name":"Telephony Concepts",
    "wof:placetype":"venue"
},
  "geometry": {"coordinates":[-83.06317199999999,40.06393],"type":"Point"}
}