{
  "type": "Feature",
  "properties": {
    "addr:full": "5200 Westpoint Plaza Dr Columbus OH 43228",
    "addr:housenumber": "5200",
    "addr:postcode": "43228",
    "addr:street": "Westpoint Plaza Dr",
    "iso:country": "US",
    "sg:address": "5200 Westpoint Plaza Dr",
    "sg:city": "Columbus",
    "sg:classifiers": [
      {
        "category": "Restaurant",
        "type": "Food \u0026 Drink"
      }
    ],
    "sg:phone": "+1 614 529 8500",
    "sg:postcode": "43228",
    "sg:province": "OH",
    "sg:website": "www.subway.com",
    "wof:name": "Subway Sandwiches \u0026 Salads",
    "wof:placetype": "venue"
  },
  "geometry": {"coordinates":[-83.147922,39.982918],"type":"Point"}
}
