{
  "type": "Feature",
  "properties": {
    "iso:country":"US",
    "sg:address":"838 N Lexington-Springmill Rd",
    "sg:city":"Mansfield",
    "sg:classifiers":[
        {
            "category":"Shopping",
            "subcategory":"Optical Goods",
            "type":"Retail Goods"
        }
    ],
    "sg:phone":"+1 419 747 4384",
    "sg:postcode":"44906",
    "sg:province":"OH",
    "wof:name":"Pearle Vision",
    "wof:placetype":"venue"
},
  "geometry": {"coordinates":[-82.590254,40.774156],"type":"Point"}
}