{
  "type": "Feature",
  "properties": {
    "iso:country":"US",
    "sg:address":"10215 Twp Hwy 49",
    "sg:city":"Mount Perry",
    "sg:classifiers":[
        {
            "category":"Building & Trades",
            "subcategory":"Pest Control",
            "type":"Services"
        }
    ],
    "sg:phone":"+1 740 454 3370",
    "sg:postcode":"43760",
    "sg:province":"OH",
    "wof:name":"Xterminator Total Pest Control",
    "wof:placetype":"venue"
},
  "geometry": {"coordinates":[-82.205986,39.838302],"type":"Point"}
}