{
  "type": "Feature",
  "properties": {
    "iso:country":"US",
    "sg:address":"6229 1st St",
    "sg:city":"Lewis Center",
    "sg:classifiers":[
        {
            "category":"Building & Trades",
            "subcategory":"Construction",
            "type":"Services"
        }
    ],
    "sg:phone":"+1 740 548 7501",
    "sg:postcode":"43015",
    "sg:province":"OH",
    "sg:tags":[
        "house",
        "pain",
        "business"
    ],
    "wof:name":"Masters Painting",
    "wof:placetype":"venue"
},
  "geometry": {"coordinates":[-83.01094500000001,40.199338],"type":"Point"}
}