{
  "type": "Feature",
  "properties": {
    "addr:full": "6229 1st St Lewis Center OH 43015",
    "addr:housenumber": "6229",
    "addr:postcode": "43015",
    "addr:street": "1St St",
    "iso:country": "US",
    "sg:address": "6229 1st St",
    "sg:city": "Lewis Center",
    "sg:classifiers": [
      {
        "category": "Building \u0026 Trades",
        "subcategory": "Construction",
        "type": "Services"
      }
    ],
    "sg:phone": "+1 740 548 7501",
    "sg:postcode": "43015",
    "sg:province": "OH",
    "sg:tags": [
      "house",
      "pain",
      "business"
    ],
    "wof:name": "Masters Painting",
    "wof:placetype": "venue"
  },
  "geometry": {"coordinates":[-83.010945,40.199338],"type":"Point"}
}
