{
  "type": "Feature",
  "properties": {
    "iso:country":"US",
    "sg:address":"10925 New Haven Rd",
    "sg:city":"Harrison",
    "sg:classifiers":[
        {
            "category":"Retail",
            "subcategory":"Auto Repair",
            "type":"Services"
        }
    ],
    "sg:phone":"+1 513 367 5533",
    "sg:postcode":"45030",
    "sg:province":"IN",
    "wof:name":"Harrison Automotive Inc",
    "wof:placetype":"venue"
},
  "geometry": {"coordinates":[-84.80287,39.257927],"type":"Point"}
}