{
  "type": "Feature",
  "properties": {
    "addr:full":"4407 Lorain Ave Cleveland OH 44113",
    "addr:housenumber":"4407",
    "addr:postcode":"44113",
    "addr:street":"Lorain Ave",
    "iso:country":"US",
    "sg:address":"4407 Lorain Ave",
    "sg:city":"Cleveland",
    "sg:classifiers":[
        {
            "category":"Personal",
            "type":"Services"
        }
    ],
    "sg:phone":"+1 216 231 5322",
    "sg:postcode":"44113",
    "sg:province":"OH",
    "sg:tags":[
        "credit",
        "debt",
        "counseling"
    ],
    "wof:name":"Consumer Credit Counseling Svc",
    "wof:placetype":"venue"
},
  "geometry": {"coordinates":[-81.717626,41.47878],"type":"Point"}
}