{
  "type": "Feature",
  "properties": {
    "iso:country":"US",
    "sg:address":"2815 Tremainsville Rd",
    "sg:city":"Toledo",
    "sg:classifiers":[
        {
            "category":"Building & Trades",
            "subcategory":"Plumbing",
            "type":"Services"
        }
    ],
    "sg:phone":"+1 419 472 0899",
    "sg:postcode":"43613",
    "sg:province":"OH",
    "sg:tags":[
        "contractor"
    ],
    "wof:name":"Mr Plumber Emer West Main Off",
    "wof:placetype":"venue"
},
  "geometry": {"coordinates":[-83.611847,41.712698],"type":"Point"}
}