{
  "type": "Feature",
  "properties": {
    "addr:full": "2840 Nash Rd Toledo OH 43613",
    "addr:housenumber": "2840",
    "addr:postcode": "43613",
    "addr:street": "Nash Rd",
    "iso:country": "US",
    "sg:address": "2840 Nash Rd",
    "sg:city": "Toledo",
    "sg:classifiers": [
      {
        "category": "Insurance",
        "subcategory": "Insurance Agent",
        "type": "Services"
      }
    ],
    "sg:phone": "+1 419 472 2999",
    "sg:postcode": "43613",
    "sg:province": "OH",
    "wof:name": "Sh Medical Claims Consultant",
    "wof:placetype": "venue"
  },
  "geometry": {"coordinates":[-83.613551,41.705722],"type":"Point"}
}
