{
  "type": "Feature",
  "properties": {
    "addr:full": "228 Orchard Dr Dayton OH 45419",
    "addr:housenumber": "228",
    "addr:postcode": "45419",
    "addr:street": "Orchard Dr",
    "iso:country": "US",
    "sg:address": "228 Orchard Dr",
    "sg:city": "Dayton",
    "sg:classifiers": [
      {
        "category": "Shopping",
        "subcategory": "Hobbies, Toys, \u0026 Games",
        "type": "Retail Goods"
      }
    ],
    "sg:phone": "+1 937 296 9528",
    "sg:postcode": "45419",
    "sg:province": "OH",
    "wof:name": "Creations By Renee",
    "wof:placetype": "venue"
  },
  "geometry": {"coordinates":[-84.16737,39.708549],"type":"Point"}
}
