{
  "type": "Feature",
  "properties": {
    "iso:country":"US",
    "sg:address":"228 Orchard Dr",
    "sg:city":"Dayton",
    "sg:classifiers":[
        {
            "category":"Shopping",
            "subcategory":"Hobbies, Toys, & Games",
            "type":"Retail Goods"
        }
    ],
    "sg:phone":"+1 937 296 9528",
    "sg:postcode":"45419",
    "sg:province":"OH",
    "wof:name":"Creations By Renee",
    "wof:placetype":"venue"
},
  "geometry": {"coordinates":[-84.16737,39.708549],"type":"Point"}
}