{
  "type": "Feature",
  "properties": {
    "addr:full":"2913 Cedar Hill Rd Cuyahoga Falls OH 44223",
    "addr:housenumber":"2913",
    "addr:postcode":"44223",
    "addr:street":"Cedar Hill Rd",
    "iso:country":"US",
    "sg:address":"2913 Cedar Hill Rd",
    "sg:city":"Cuyahoga Falls",
    "sg:classifiers":[
        {
            "category":"Organizations",
            "subcategory":"Professional Association",
            "type":"Services"
        }
    ],
    "sg:phone":"+1 330 945 7740",
    "sg:postcode":"44223",
    "sg:province":"OH",
    "sg:tags":[
        "business",
        "trade"
    ],
    "wof:name":"Sales & Marketing Executive",
    "wof:placetype":"venue"
},
  "geometry": {"coordinates":[-81.513935,41.149851],"type":"Point"}
}