{
  "type": "Feature",
  "properties": {
    "addr:full": "541 Santa Monica Dr Youngstown OH 44505",
    "addr:housenumber": "541",
    "addr:postcode": "44505",
    "addr:street": "Santa Monica Dr",
    "iso:country": "US",
    "sg:address": "541 Santa Monica Dr",
    "sg:city": "Youngstown",
    "sg:classifiers": [
      {
        "category": "Building \u0026 Trades",
        "subcategory": "Construction",
        "type": "Services"
      }
    ],
    "sg:phone": "+1 330 759 8822",
    "sg:postcode": "44505",
    "sg:province": "OH",
    "sg:tags": [
      "house"
    ],
    "wof:name": "Hasija Construction",
    "wof:placetype": "venue"
  },
  "geometry": {"coordinates":[-80.656919,41.170293],"type":"Point"}
}
