{
  "type": "Feature",
  "properties": {
    "iso:country":"US",
    "sg:address":"3870 Security Dr",
    "sg:city":"Grove City",
    "sg:classifiers":[
        {
            "category":"Building & Trades",
            "subcategory":"Construction",
            "type":"Services"
        }
    ],
    "sg:phone":"+1 614 871 1526",
    "sg:postcode":"43123",
    "sg:province":"OH",
    "sg:tags":[
        "contractor"
    ],
    "wof:name":"Ward Thompson",
    "wof:placetype":"venue"
},
  "geometry": {"coordinates":[-83.075715,39.885058],"type":"Point"}
}