{
  "type": "Feature",
  "properties": {
    "addr:full": "3870 Security Dr Grove City OH 43123",
    "addr:housenumber": "3870",
    "addr:postcode": "43123",
    "addr:street": "Security Dr",
    "iso:country": "US",
    "sg:address": "3870 Security Dr",
    "sg:city": "Grove City",
    "sg:classifiers": [
      {
        "category": "Building \u0026 Trades",
        "subcategory": "Construction",
        "type": "Services"
      }
    ],
    "sg:phone": "+1 614 871 1526",
    "sg:postcode": "43123",
    "sg:province": "OH",
    "sg:tags": [
      "contractor"
    ],
    "wof:name": "Ward Thompson",
    "wof:placetype": "venue"
  },
  "geometry": {"coordinates":[-83.075715,39.885058],"type":"Point"}
}
