{
  "type": "Feature",
  "properties": {
    "addr:full": "822 Franklin St Hamilton IN 45013",
    "addr:housenumber": "822",
    "addr:postcode": "45013",
    "addr:street": "Franklin St",
    "iso:country": "US",
    "sg:address": "822 Franklin St",
    "sg:city": "Hamilton",
    "sg:classifiers": [
      {
        "category": "Building \u0026 Trades",
        "subcategory": "Construction",
        "type": "Services"
      }
    ],
    "sg:phone": "+1 513 887 8888",
    "sg:postcode": "45013",
    "sg:province": "IN",
    "sg:tags": [
      "painter"
    ],
    "wof:name": "Five Star Painting",
    "wof:placetype": "venue"
  },
  "geometry": {"coordinates":[-84.581118,39.409747],"type":"Point"}
}
