{
  "type": "Feature",
  "properties": {
    "addr:full": "5277 Co Rd 78 Mt Gilead OH 43338",
    "addr:housenumber": "5277;78",
    "addr:postcode": "43338",
    "addr:street": "Co Rd;Mt Gilead",
    "iso:country": "US",
    "sg:address": "5277 Co Rd 78",
    "sg:city": "Mt Gilead",
    "sg:classifiers": [
      {
        "category": "Freight",
        "type": "Transportation"
      }
    ],
    "sg:phone": "+1 419 947 2204",
    "sg:postcode": "43338",
    "sg:province": "OH",
    "sg:tags": [
      "operator",
      "local",
      "trucking"
    ],
    "wof:name": "Mitchells Trucking",
    "wof:placetype": "venue"
  },
  "geometry": {"coordinates":[-82.753502,40.607448],"type":"Point"}
}
