{
  "type": "Feature",
  "properties": {
    "addr:full":"15 E Gambier St Mount Vernon OH 43050",
    "addr:housenumber":"15",
    "addr:postcode":"43050",
    "addr:street":"E Gambier St",
    "iso:country":"US",
    "sg:address":"15 E Gambier St",
    "sg:city":"Mount Vernon",
    "sg:classifiers":[
        {
            "category":"Building & Trades",
            "subcategory":"Construction",
            "type":"Services"
        }
    ],
    "sg:phone":"+1 740 392 8561",
    "sg:postcode":"43050",
    "sg:province":"OH",
    "sg:tags":[
        "water",
        "plumbing",
        "well",
        "drilling",
        "supply"
    ],
    "wof:name":"Jamison Well Drilling Inc",
    "wof:placetype":"venue"
},
  "geometry": {"coordinates":[-82.48546399999999,40.391806],"type":"Point"}
}