{
  "type": "Feature",
  "properties": {
    "addr:full":"633 Scioto St Urbana OH 43078",
    "addr:housenumber":"633",
    "addr:postcode":"43078",
    "addr:street":"Scioto St",
    "iso:country":"US",
    "sg:address":"633 Scioto St",
    "sg:city":"Urbana",
    "sg:classifiers":[
        {
            "category":"Restaurant",
            "type":"Food & Drink"
        }
    ],
    "sg:menulink":"http://www.allmenus.com/oh/urbana/214819-ponderosa-steak-house/menu/",
    "sg:phone":"+1 937 652 2404",
    "sg:postcode":"43078",
    "sg:province":"OH",
    "sg:tags":[
        "american",
        "steakhouse"
    ],
    "wof:name":"Ponderosa Steak House",
    "wof:placetype":"venue"
},
  "geometry": {"coordinates":[-83.740148,40.107335],"type":"Point"}
}