{
  "type": "Feature",
  "properties": {
    "iso:country":"US",
    "sg:address":"523 Vienna Ave",
    "sg:city":"Niles",
    "sg:classifiers":[
        {
            "category":"Shopping",
            "type":"Retail Goods"
        }
    ],
    "sg:phone":"+1 330 544 1111",
    "sg:postcode":"44446",
    "sg:province":"OH",
    "sg:tags":[
        "medal",
        "plaque",
        "merchandise",
        "trophies"
    ],
    "wof:name":"Hangware Trophies & Plaques",
    "wof:placetype":"venue"
},
  "geometry": {"coordinates":[-80.75484899999999,41.187996],"type":"Point"}
}