{
  "type": "Feature",
  "properties": {
    "addr:full": "523 Vienna Ave Niles OH 44446",
    "addr:housenumber": "523",
    "addr:postcode": "44446",
    "addr:street": "Vienna Ave",
    "iso:country": "US",
    "sg:address": "523 Vienna Ave",
    "sg:city": "Niles",
    "sg:classifiers": [
      {
        "category": "Shopping",
        "type": "Retail Goods"
      }
    ],
    "sg:phone": "+1 330 544 1111",
    "sg:postcode": "44446",
    "sg:province": "OH",
    "sg:tags": [
      "medal",
      "plaque",
      "merchandise",
      "trophies"
    ],
    "wof:name": "Hangware Trophies \u0026 Plaques",
    "wof:placetype": "venue"
  },
  "geometry": {"coordinates":[-80.754849,41.187996],"type":"Point"}
}
