{
  "type": "Feature",
  "properties": {
    "addr:full":"6433 Kimberly Dr Cleveland OH 44125",
    "addr:housenumber":"6433",
    "addr:postcode":"44125",
    "addr:street":"Kimberly Dr",
    "iso:country":"US",
    "sg:address":"6433 Kimberly Dr",
    "sg:city":"Cleveland",
    "sg:classifiers":[
        {
            "category":"Building & Trades",
            "subcategory":"Landscaping Services",
            "type":"Services"
        }
    ],
    "sg:phone":"+1 216 662 0762",
    "sg:postcode":"44125",
    "sg:province":"OH",
    "sg:tags":[
        "landscape"
    ],
    "wof:name":"Lloyd Jones Landscaping",
    "wof:placetype":"venue"
},
  "geometry": {"coordinates":[-81.58904800000001,41.392371],"type":"Point"}
}