{
  "type": "Feature",
  "properties": {
    "addr:full": "3636 Creed St Hubbard OH 44425",
    "addr:housenumber": "3636",
    "addr:postcode": "44425",
    "addr:street": "Creed St",
    "iso:country": "US",
    "sg:address": "3636 Creed St",
    "sg:city": "Hubbard",
    "sg:classifiers": [
      {
        "category": "Food \u0026 Beverages",
        "subcategory": "Groceries \u0026 Convenience Stores",
        "type": "Retail Goods"
      }
    ],
    "sg:phone": "+1 330 534 0418",
    "sg:postcode": "44425",
    "sg:province": "OH",
    "wof:name": "One Stop Superette",
    "wof:placetype": "venue"
  },
  "geometry": {"coordinates":[-80.557611,41.153727],"type":"Point"}
}
