{
  "type": "Feature",
  "properties": {
    "iso:country":"US",
    "sg:address":"5201 Delhi Ave",
    "sg:city":"Cincinnati",
    "sg:classifiers":[
        {
            "category":"Wholesale",
            "subcategory":"Electrical",
            "type":"Manufacturing & Wholesale Goods"
        }
    ],
    "sg:phone":"+1 513 922 7166",
    "sg:postcode":"45238",
    "sg:province":"OH",
    "sg:tags":[
        "mobile",
        "telephone"
    ],
    "wof:name":"Alpha Communications",
    "wof:placetype":"venue"
},
  "geometry": {"coordinates":[-84.618206,39.09388],"type":"Point"}
}