{
  "type": "Feature",
  "properties": {
    "iso:country":"US",
    "sg:address":"21761 Gate House Ln",
    "sg:city":"Cleveland",
    "sg:classifiers":[
        {
            "category":"Professional",
            "subcategory":"Lawyer & Legal Services",
            "type":"Services"
        }
    ],
    "sg:phone":"+1 440 333 2211",
    "sg:postcode":"44116",
    "sg:province":"OH",
    "sg:tags":[
        "attorney"
    ],
    "wof:name":"Paul C Wagner Jr",
    "wof:placetype":"venue"
},
  "geometry": {"coordinates":[-81.861987,41.474649],"type":"Point"}
}