{
  "type": "Feature",
  "properties": {
    "iso:country":"US",
    "sg:address":"49 Pinehurst Rd",
    "sg:city":"Munroe Falls",
    "sg:classifiers":[
        {
            "category":"Freight",
            "type":"Transportation"
        }
    ],
    "sg:phone":"+1 330 351 4726",
    "sg:postcode":"44262",
    "sg:province":"OH",
    "sg:tags":[
        "preparation",
        "document"
    ],
    "wof:name":"Larr & Associates",
    "wof:placetype":"venue"
},
  "geometry": {"coordinates":[-81.43667499999999,41.151599],"type":"Point"}
}