{
  "type": "Feature",
  "properties": {
    "addr:full": "49 Pinehurst Rd Munroe Falls OH 44262",
    "addr:housenumber": "49",
    "addr:postcode": "44262",
    "addr:street": "Pinehurst Rd",
    "iso:country": "US",
    "sg:address": "49 Pinehurst Rd",
    "sg:city": "Munroe Falls",
    "sg:classifiers": [
      {
        "category": "Freight",
        "type": "Transportation"
      }
    ],
    "sg:phone": "+1 330 351 4726",
    "sg:postcode": "44262",
    "sg:province": "OH",
    "sg:tags": [
      "preparation",
      "document"
    ],
    "wof:name": "Larr \u0026 Associates",
    "wof:placetype": "venue"
  },
  "geometry": {"coordinates":[-81.436675,41.151599],"type":"Point"}
}
