{
  "type": "Feature",
  "properties": {
    "iso:country":"US",
    "sg:address":"11080 W Toussaint East Rd",
    "sg:city":"Oak Harbor",
    "sg:classifiers":[
        {
            "category":"Government",
            "subcategory":"Police Station",
            "type":"Public Place"
        }
    ],
    "sg:phone":"+1 419 898 4906",
    "sg:postcode":"43449",
    "sg:province":"OH",
    "sg:tags":[
        "department"
    ],
    "wof:name":"Carroll Twp Police",
    "wof:placetype":"venue"
},
  "geometry": {"coordinates":[-83.146305,41.566975],"type":"Point"}
}