{
  "type": "Feature",
  "properties": {
    "iso:country":"US",
    "sg:address":"66 S Miller Rd",
    "sg:city":"Fairlawn",
    "sg:classifiers":[
        {
            "category":"Real Estate",
            "subcategory":"Real Estate Services",
            "type":"Services"
        }
    ],
    "sg:phone":"+1 330 865 8110",
    "sg:postcode":"44333",
    "sg:province":"OH",
    "sg:tags":[
        "company",
        "title"
    ],
    "wof:name":"Arlinton Title Agency",
    "wof:placetype":"venue"
},
  "geometry": {"coordinates":[-81.609852,41.126218],"type":"Point"}
}