{
  "type": "Feature",
  "properties": {
    "addr:full":"2654 Henville Rd Xenia OH 45385",
    "addr:housenumber":"2654",
    "addr:postcode":"45385",
    "addr:street":"Henville Rd",
    "iso:country":"US",
    "sg:address":"2654 Henville Rd",
    "sg:city":"Xenia",
    "sg:classifiers":[
        {
            "category":"Shopping",
            "subcategory":"Crafts & Fabrics",
            "type":"Retail Goods"
        }
    ],
    "sg:phone":"+1 937 376 1306",
    "sg:postcode":"45385",
    "sg:province":"OH",
    "sg:tags":[
        "sewing"
    ],
    "wof:name":"Kathryn Elaine Kramer Design",
    "wof:placetype":"venue"
},
  "geometry": {"coordinates":[-83.92201900000001,39.614082],"type":"Point"}
}