{
  "type": "Feature",
  "properties": {
    "addr:full": "40601 Ashton Hill Rd Caldwell OH 43724",
    "addr:housenumber": "40601",
    "addr:postcode": "43724",
    "addr:street": "Ashton Hill Rd",
    "iso:country": "US",
    "sg:address": "40601 Ashton Hill Rd",
    "sg:city": "Caldwell",
    "sg:classifiers": [
      {
        "category": "Utilities",
        "subcategory": "Telephone",
        "type": "Services"
      }
    ],
    "sg:phone": "+1 740 783 4208",
    "sg:postcode": "43724",
    "sg:province": "OH",
    "sg:tags": [
      "communications"
    ],
    "wof:name": "American Telephone Technology",
    "wof:placetype": "venue"
  },
  "geometry": {"coordinates":[-81.469552,39.685756],"type":"Point"}
}
