{
  "type": "Feature",
  "properties": {
    "addr:full": "2101 Hill Ave Toledo OH 43607",
    "addr:housenumber": "2101",
    "addr:postcode": "43607",
    "addr:street": "Hill Ave",
    "iso:country": "US",
    "sg:address": "2101 Hill Ave",
    "sg:city": "Toledo",
    "sg:classifiers": [
      {
        "category": "Railroad",
        "type": "Transportation"
      }
    ],
    "sg:phone": "+1 419 661 4705",
    "sg:postcode": "43607",
    "sg:province": "OH",
    "sg:tags": [
      "operator",
      "line"
    ],
    "wof:name": "Conrail",
    "wof:placetype": "venue"
  },
  "geometry": {"coordinates":[-83.599994,41.638011],"type":"Point"}
}
