{
  "type": "Feature",
  "properties": {
    "addr:full":"4038 Talmadge Rd Toledo OH 43623",
    "addr:housenumber":"4038",
    "addr:postcode":"43623",
    "addr:street":"Talmadge Rd",
    "iso:country":"US",
    "sg:address":"4038 Talmadge Rd",
    "sg:city":"Toledo",
    "sg:classifiers":[
        {
            "category":"Restaurant",
            "type":"Food & Drink"
        }
    ],
    "sg:phone":"+1 419 474 9700",
    "sg:postcode":"43623",
    "sg:province":"OH",
    "wof:name":"KOKO Pelli Grill",
    "wof:placetype":"venue"
},
  "geometry": {"coordinates":[-83.64454600000001,41.69177],"type":"Point"}
}