{
  "type": "Feature",
  "properties": {
    "iso:country":"US",
    "sg:address":"1232 W Kemper Rd",
    "sg:city":"Cincinnati",
    "sg:classifiers":[
        {
            "category":"Wholesale",
            "subcategory":"Office Equipment",
            "type":"Manufacturing & Wholesale Goods"
        }
    ],
    "sg:phone":"+1 513 245 1421",
    "sg:postcode":"45240",
    "sg:province":"OH",
    "sg:tags":[
        "machine",
        "duplicating",
        "copying"
    ],
    "wof:name":"Onesource Imaging Products",
    "wof:placetype":"venue"
},
  "geometry": {"coordinates":[-84.525298,39.288838],"type":"Point"}
}