{
  "type": "Feature",
  "properties": {
    "addr:full": "1232 W Kemper Rd Cincinnati OH 45240",
    "addr:housenumber": "1232",
    "addr:postcode": "45240",
    "addr:street": "W Kemper Rd",
    "iso:country": "US",
    "sg:address": "1232 W Kemper Rd",
    "sg:city": "Cincinnati",
    "sg:classifiers": [
      {
        "category": "Wholesale",
        "subcategory": "Office Equipment",
        "type": "Manufacturing \u0026 Wholesale Goods"
      }
    ],
    "sg:phone": "+1 513 245 1421",
    "sg:postcode": "45240",
    "sg:province": "OH",
    "sg:tags": [
      "machine",
      "duplicating",
      "copying"
    ],
    "wof:name": "Onesource Imaging Products",
    "wof:placetype": "venue"
  },
  "geometry": {"coordinates":[-84.525298,39.288838],"type":"Point"}
}
