{
  "type": "Feature",
  "properties": {
    "iso:country":"US",
    "sg:address":"7875 Murray Ridge Rd",
    "sg:city":"Elyria",
    "sg:classifiers":[
        {
            "category":"Personal",
            "subcategory":"Beauty Salon",
            "type":"Services"
        }
    ],
    "sg:phone":"+1 440 323 1946",
    "sg:postcode":"44035",
    "sg:province":"OH",
    "wof:name":"Cabas Hair Systems",
    "wof:placetype":"venue"
},
  "geometry": {"coordinates":[-82.150051,41.37796],"type":"Point"}
}