{
  "type": "Feature",
  "properties": {
    "addr:full": "520 S Main St Akron OH 44311",
    "addr:housenumber": "520",
    "addr:postcode": "44311",
    "addr:street": "S Main St",
    "iso:country": "US",
    "sg:address": "520 S Main St",
    "sg:city": "Akron",
    "sg:classifiers": [
      {
        "category": "Local Transit",
        "type": "Transportation"
      }
    ],
    "sg:phone": "+1 330 733 7551",
    "sg:postcode": "44311",
    "sg:province": "OH",
    "sg:tags": [
      "ambulance"
    ],
    "wof:name": "Physicians \u0026 Surgeon Ambulance",
    "wof:placetype": "venue"
  },
  "geometry": {"coordinates":[-81.524431,41.073244],"type":"Point"}
}
