{
  "type": "Feature",
  "properties": {
    "iso:country":"US",
    "sg:address":"520 S Main St",
    "sg:city":"Akron",
    "sg:classifiers":[
        {
            "category":"Local Transit",
            "type":"Transportation"
        }
    ],
    "sg:phone":"+1 330 733 7551",
    "sg:postcode":"44311",
    "sg:province":"OH",
    "sg:tags":[
        "ambulance"
    ],
    "wof:name":"Physicians & Surgeon Ambulance",
    "wof:placetype":"venue"
},
  "geometry": {"coordinates":[-81.52443100000001,41.073244],"type":"Point"}
}