{
  "type": "Feature",
  "properties": {
    "addr:full": "1983 Palmyra Rd SW Warren OH 44485",
    "addr:housenumber": "1983",
    "addr:postcode": "44485",
    "addr:street": "Palmyra Rd Sw",
    "iso:country": "US",
    "sg:address": "1983 Palmyra Rd SW",
    "sg:city": "Warren",
    "sg:classifiers": [
      {
        "category": "Professional",
        "type": "Services"
      }
    ],
    "sg:phone": "+1 330 399 1138",
    "sg:postcode": "44485",
    "sg:province": "OH",
    "sg:tags": [
      "establishment"
    ],
    "wof:name": "E 93rd",
    "wof:placetype": "venue"
  },
  "geometry": {"coordinates":[-80.843769,41.223945],"type":"Point"}
}
