{
  "type": "Feature",
  "properties": {
    "iso:country":"US",
    "sg:address":"2910 Bryden Rd",
    "sg:city":"Columbus",
    "sg:classifiers":[
        {
            "category":"Communications",
            "subcategory":"Film & Video Production",
            "type":"Services"
        }
    ],
    "sg:phone":"+1 614 238 0518",
    "sg:postcode":"43209",
    "sg:province":"OH",
    "sg:tags":[
        "audio"
    ],
    "wof:name":"Pagetech Productions",
    "wof:placetype":"venue"
},
  "geometry": {"coordinates":[-82.92289700000001,39.958897],"type":"Point"}
}