{
  "type": "Feature",
  "properties": {
    "addr:full": "2910 Bryden Rd Columbus OH 43209",
    "addr:housenumber": "2910",
    "addr:postcode": "43209",
    "addr:street": "Bryden Rd",
    "iso:country": "US",
    "sg:address": "2910 Bryden Rd",
    "sg:city": "Columbus",
    "sg:classifiers": [
      {
        "category": "Communications",
        "subcategory": "Film \u0026 Video Production",
        "type": "Services"
      }
    ],
    "sg:phone": "+1 614 238 0518",
    "sg:postcode": "43209",
    "sg:province": "OH",
    "sg:tags": [
      "audio"
    ],
    "wof:name": "Pagetech Productions",
    "wof:placetype": "venue"
  },
  "geometry": {"coordinates":[-82.922897,39.958897],"type":"Point"}
}
