{
  "type": "Feature",
  "properties": {
    "addr:full": "1920 Stringtown Rd Grove City OH 43123",
    "addr:housenumber": "1920",
    "addr:postcode": "43123",
    "addr:street": "Stringtown Rd",
    "iso:country": "US",
    "sg:address": "1920 Stringtown Rd",
    "sg:city": "Grove City",
    "sg:classifiers": [
      {
        "category": "Restaurant",
        "type": "Food \u0026 Drink"
      }
    ],
    "sg:phone": "+1 614 875 1818",
    "sg:postcode": "43123",
    "sg:province": "OH",
    "wof:name": "Wendy's",
    "wof:placetype": "venue"
  },
  "geometry": {"coordinates":[-83.055764,39.878327],"type":"Point"}
}
