{
  "type": "Feature",
  "properties": {
    "addr:full":"239 Elas Ct Tipp City OH 45371",
    "addr:housenumber":"239",
    "addr:postcode":"45371",
    "addr:street":"Elas Ct",
    "iso:country":"US",
    "sg:address":"239 Elas Ct",
    "sg:city":"Tipp City",
    "sg:classifiers":[
        {
            "category":"Wholesale",
            "subcategory":"Jewelry",
            "type":"Manufacturing & Wholesale Goods"
        }
    ],
    "sg:phone":"+1 937 335 8425",
    "sg:postcode":"45371",
    "sg:province":"OH",
    "sg:tags":[
        "stone"
    ],
    "wof:name":"Schultz Caryn",
    "wof:placetype":"venue"
},
  "geometry": {"coordinates":[-84.20313299999999,39.984989],"type":"Point"}
}