{
  "type": "Feature",
  "properties": {
    "addr:full": "1539 Millerstown Rd Urbana OH 43078",
    "addr:housenumber": "1539",
    "addr:postcode": "43078",
    "addr:street": "Millerstown Rd",
    "iso:country": "US",
    "sg:address": "1539 Millerstown Rd",
    "sg:city": "Urbana",
    "sg:classifiers": [
      {
        "category": "Farming",
        "subcategory": "Farm",
        "type": "Manufacturing \u0026 Wholesale Goods"
      }
    ],
    "sg:phone": "+1 937 653 7960",
    "sg:postcode": "43078",
    "sg:province": "OH",
    "sg:tags": [
      "crop",
      "general"
    ],
    "wof:name": "George Craig",
    "wof:placetype": "venue"
  },
  "geometry": {"coordinates":[-83.77901,40.12778],"type":"Point"}
}
