{
  "type": "Feature",
  "properties": {
    "iso:country":"US",
    "sg:address":"3747 S Mahoning Ave",
    "sg:city":"Alliance",
    "sg:classifiers":[
        {
            "category":"Shopping",
            "type":"Retail Goods"
        }
    ],
    "sg:phone":"+1 330 823 4464",
    "sg:postcode":"44601",
    "sg:province":"OH",
    "sg:tags":[
        "awning",
        "canopy"
    ],
    "wof:name":"Don Steepleton Construction",
    "wof:placetype":"venue"
},
  "geometry": {"coordinates":[-81.086813,40.875892],"type":"Point"}
}