{
  "type": "Feature",
  "properties": {
    "addr:full": "3747 S Mahoning Ave Alliance OH 44601",
    "addr:housenumber": "3747",
    "addr:postcode": "44601",
    "addr:street": "S Mahoning Ave",
    "iso:country": "US",
    "sg:address": "3747 S Mahoning Ave",
    "sg:city": "Alliance",
    "sg:classifiers": [
      {
        "category": "Shopping",
        "type": "Retail Goods"
      }
    ],
    "sg:phone": "+1 330 823 4464",
    "sg:postcode": "44601",
    "sg:province": "OH",
    "sg:tags": [
      "awning",
      "canopy"
    ],
    "wof:name": "Don Steepleton Construction",
    "wof:placetype": "venue"
  },
  "geometry": {"coordinates":[-81.086813,40.875892],"type":"Point"}
}
