{
  "type": "Feature",
  "properties": {
    "addr:full":"1641 Roseview Dr Columbus OH 43209",
    "addr:housenumber":"1641",
    "addr:postcode":"43209",
    "addr:street":"Roseview Dr",
    "iso:country":"US",
    "sg:address":"1641 Roseview Dr",
    "sg:city":"Columbus",
    "sg:classifiers":[
        {
            "category":"Restaurant",
            "type":"Food & Drink"
        }
    ],
    "sg:phone":"+1 614 239 7434",
    "sg:postcode":"43209",
    "sg:province":"OH",
    "sg:tags":[
        "caterer"
    ],
    "wof:name":"Sweet Manna",
    "wof:placetype":"venue"
},
  "geometry": {"coordinates":[-82.928729,39.936628],"type":"Point"}
}