{
  "type": "Feature",
  "properties": {
    "addr:full":"1500 N Clinton St Defiance OH 43512",
    "addr:housenumber":"1500",
    "addr:postcode":"43512",
    "addr:street":"N Clinton St",
    "iso:country":"US",
    "sg:address":"1500 N Clinton St",
    "sg:city":"Defiance",
    "sg:classifiers":[
        {
            "category":"Shopping",
            "subcategory":"Clothing, Apparel, & Fashions",
            "type":"Retail Goods"
        }
    ],
    "sg:phone":"+1 419 782 4949",
    "sg:postcode":"43512",
    "sg:province":"OH",
    "wof:name":"Deb",
    "wof:placetype":"venue"
},
  "geometry": {"coordinates":[-84.36094900000001,41.300984],"type":"Point"}
}