{
  "type": "Feature",
  "properties": {
    "addr:full": "331 Cove Rd Jackson OH 45640",
    "addr:housenumber": "331",
    "addr:postcode": "45640",
    "addr:street": "Cove Rd",
    "iso:country": "US",
    "sg:address": "331 Cove Rd",
    "sg:city": "Jackson",
    "sg:classifiers": [
      {
        "category": "Manufacturing",
        "subcategory": "Apparel",
        "type": "Manufacturing \u0026 Wholesale Goods"
      }
    ],
    "sg:phone": "+1 740 988 2143",
    "sg:postcode": "45640",
    "sg:province": "OH",
    "wof:name": "Linmar Designs",
    "wof:placetype": "venue"
  },
  "geometry": {"coordinates":[-82.750331,39.020883],"type":"Point"}
}
