{
  "type": "Feature",
  "properties": {
    "iso:country":"US",
    "sg:address":"10908 State Rte 269",
    "sg:city":"Bellevue",
    "sg:classifiers":[
        {
            "category":"Building & Trades",
            "subcategory":"Construction",
            "type":"Services"
        }
    ],
    "sg:phone":"+1 419 483 6977",
    "sg:postcode":"44811",
    "sg:province":"OH",
    "sg:tags":[
        "house",
        "remodeling"
    ],
    "wof:name":"Beckman Construction",
    "wof:placetype":"venue"
},
  "geometry": {"coordinates":[-82.830252,41.300916],"type":"Point"}
}