{
  "type": "Feature",
  "properties": {
    "addr:full":"1324 Chase Ave Cincinnati OH 45223",
    "addr:housenumber":"1324",
    "addr:postcode":"45223",
    "addr:street":"Chase Ave",
    "iso:country":"US",
    "sg:address":"1324 Chase Ave",
    "sg:city":"Cincinnati",
    "sg:classifiers":[
        {
            "category":"Organizations",
            "subcategory":"Religious Organization",
            "type":"Services"
        }
    ],
    "sg:phone":"+1 513 542 3854",
    "sg:postcode":"45223",
    "sg:province":"OH",
    "sg:tags":[
        "church"
    ],
    "wof:name":"Chase Ave Church Of-Nazarene",
    "wof:placetype":"venue"
},
  "geometry": {"coordinates":[-84.533783,39.16326],"type":"Point"}
}