{
  "type": "Feature",
  "properties": {
    "iso:country":"US",
    "sg:address":"3375 N Dayton Xenia Rd",
    "sg:city":"Dayton",
    "sg:classifiers":[
        {
            "category":"Home & Garden",
            "subcategory":"Hardware",
            "type":"Retail Goods"
        }
    ],
    "sg:phone":"+1 937 426 5070",
    "sg:postcode":"45432",
    "sg:province":"OH",
    "sg:tags":[
        "repair"
    ],
    "wof:name":"Barney's True Value Hardware",
    "wof:placetype":"venue"
},
  "geometry": {"coordinates":[-84.062456,39.730872],"type":"Point"}
}