{
  "type": "Feature",
  "properties": {
    "iso:country":"US",
    "sg:address":"1706 E Broad St",
    "sg:city":"Columbus",
    "sg:classifiers":[
        {
            "category":"Social Services",
            "type":"Services"
        }
    ],
    "sg:phone":"+1 614 251 6000",
    "sg:postcode":"43203",
    "sg:province":"OH",
    "sg:tags":[
        "counselor",
        "marriage",
        "family"
    ],
    "sg:website":"www.ihs-trainet.com",
    "wof:name":"Institute For Human Svc",
    "wof:placetype":"venue"
},
  "geometry": {"coordinates":[-82.95640299999999,39.967312],"type":"Point"}
}