{
  "type": "Feature",
  "properties": {
    "addr:full": "1706 E Broad St Columbus OH 43203",
    "addr:housenumber": "1706",
    "addr:postcode": "43203",
    "addr:street": "E Broad St",
    "iso:country": "US",
    "sg:address": "1706 E Broad St",
    "sg:city": "Columbus",
    "sg:classifiers": [
      {
        "category": "Social Services",
        "type": "Services"
      }
    ],
    "sg:phone": "+1 614 251 6000",
    "sg:postcode": "43203",
    "sg:province": "OH",
    "sg:tags": [
      "counselor",
      "marriage",
      "family"
    ],
    "sg:website": "www.ihs-trainet.com",
    "wof:name": "Institute For Human Svc",
    "wof:placetype": "venue"
  },
  "geometry": {"coordinates":[-82.956403,39.967312],"type":"Point"}
}
