{
  "type": "Feature",
  "properties": {
    "addr:full": "1627 Pyro Rd Oak Hill OH 45656",
    "addr:housenumber": "1627",
    "addr:postcode": "45656",
    "addr:street": "Pyro Rd",
    "iso:country": "US",
    "sg:address": "1627 Pyro Rd",
    "sg:city": "Oak Hill",
    "sg:classifiers": [
      {
        "category": "Manufacturing",
        "subcategory": "Glass \u0026 Minerals",
        "type": "Manufacturing \u0026 Wholesale Goods"
      }
    ],
    "sg:phone": "+1 740 682 7711",
    "sg:postcode": "45656",
    "sg:province": "OH",
    "sg:tags": [
      "refractory",
      "mfg",
      "clay"
    ],
    "wof:name": "Oak Hill Plant",
    "wof:placetype": "venue"
  },
  "geometry": {"coordinates":[-82.543593,38.927373],"type":"Point"}
}
