{
  "type": "Feature",
  "properties": {
    "addr:full":"29134 Euclid Ave Wickliffe OH 44092",
    "addr:housenumber":"29134",
    "addr:postcode":"44092",
    "addr:street":"Euclid Ave",
    "iso:country":"US",
    "sg:address":"29134 Euclid Ave",
    "sg:city":"Wickliffe",
    "sg:classifiers":[
        {
            "category":"Health Services",
            "subcategory":"Doctor",
            "type":"Services"
        }
    ],
    "sg:phone":"+1 440 943 3003",
    "sg:postcode":"44092",
    "sg:province":"OH",
    "sg:tags":[
        "dentist"
    ],
    "wof:name":"Cary N Goldstein Inc",
    "wof:placetype":"venue"
},
  "geometry": {"coordinates":[-81.477704,41.603434],"type":"Point"}
}