{
  "type": "Feature",
  "properties": {
    "iso:country":"US",
    "sg:address":"265 S Elm St",
    "sg:city":"Columbiana",
    "sg:classifiers":[
        {
            "category":"Manufacturing",
            "subcategory":"Furniture",
            "type":"Manufacturing & Wholesale Goods"
        }
    ],
    "sg:phone":"+1 330 482 0805",
    "sg:postcode":"44408",
    "sg:province":"OH",
    "sg:tags":[
        "wood",
        "mfg"
    ],
    "wof:name":"Creative Counters",
    "wof:placetype":"venue"
},
  "geometry": {"coordinates":[-80.69226,40.884442],"type":"Point"}
}