{
  "type": "Feature",
  "properties": {
    "addr:full":"12000 Middleton Pike Bowling Green OH 43402",
    "addr:housenumber":"12000",
    "addr:postcode":"43402",
    "addr:street":"Middleton Pike",
    "iso:country":"US",
    "sg:address":"12000 Middleton Pike",
    "sg:city":"Bowling Green",
    "sg:classifiers":[
        {
            "category":"Professional",
            "subcategory":"Research",
            "type":"Services"
        }
    ],
    "sg:phone":"+1 419 353 1330",
    "sg:postcode":"43402",
    "sg:province":"OH",
    "sg:tags":[
        "environmental",
        "ecological"
    ],
    "sg:website":"www.eq.com",
    "wof:name":"E Q Ind Svc",
    "wof:placetype":"venue"
},
  "geometry": {"coordinates":[-83.628967,41.45809],"type":"Point"}
}