{
  "type": "Feature",
  "properties": {
    "iso:country":"US",
    "sg:address":"270 Main St",
    "sg:city":"Painesville",
    "sg:classifiers":[
        {
            "category":"Education",
            "subcategory":"Special Training",
            "type":"Public Place"
        }
    ],
    "sg:phone":"+1 440 357 9030",
    "sg:postcode":"44077",
    "sg:province":"OH",
    "sg:tags":[
        "instruction",
        "driving"
    ],
    "wof:name":"Lake Erie Education Inc",
    "wof:placetype":"venue"
},
  "geometry": {"coordinates":[-81.239592,41.726454],"type":"Point"}
}