{
  "type": "Feature",
  "properties": {
    "addr:full":"5306 E 100th St Cleveland OH 44125",
    "addr:housenumber":"5306",
    "addr:postcode":"44125",
    "addr:street":"E 100Th St",
    "iso:country":"US",
    "sg:address":"5306 E 100th St",
    "sg:city":"Cleveland",
    "sg:classifiers":[
        {
            "category":"Real Estate",
            "subcategory":"Real Estate Agent",
            "type":"Services"
        }
    ],
    "sg:phone":"+1 216 581 7558",
    "sg:postcode":"44125",
    "sg:province":"OH",
    "wof:name":"D Basel",
    "wof:placetype":"venue"
},
  "geometry": {"coordinates":[-81.61501800000001,41.419327],"type":"Point"}
}