{
  "type": "Feature",
  "properties": {
    "addr:full": "496 Arch St Salem OH 44460",
    "addr:housenumber": "496",
    "addr:postcode": "44460",
    "addr:street": "Arch St",
    "iso:country": "US",
    "sg:address": "496 Arch St",
    "sg:city": "Salem",
    "sg:classifiers": [
      {
        "category": "Organizations",
        "subcategory": "Community Association",
        "type": "Services"
      }
    ],
    "sg:phone": "+1 330 337 8015",
    "sg:postcode": "44460",
    "sg:province": "OH",
    "sg:tags": [
      "military"
    ],
    "sg:website": "www.vfw.org",
    "wof:name": "Veterans Of Foreign Wars",
    "wof:placetype": "venue"
  },
  "geometry": {"coordinates":[-80.863558,40.895212],"type":"Point"}
}
