{
  "type": "Feature",
  "properties": {
    "addr:full": "709 Milton Blvd Newton Falls OH 44444",
    "addr:housenumber": "709",
    "addr:postcode": "44444",
    "addr:street": "Milton Blvd",
    "iso:country": "US",
    "sg:address": "709 Milton Blvd",
    "sg:city": "Newton Falls",
    "sg:classifiers": [
      {
        "category": "Education",
        "subcategory": "School",
        "type": "Public Place"
      }
    ],
    "sg:phone": "+1 330 872 7676",
    "sg:postcode": "44444",
    "sg:province": "OH",
    "sg:tags": [
      "religious"
    ],
    "sg:website": "www.ssmj.org",
    "wof:name": "St Mary \u0026 Joseph School",
    "wof:placetype": "venue"
  },
  "geometry": {"coordinates":[-80.969336,41.183929],"type":"Point"}
}
