{
  "type": "Feature",
  "properties": {
    "addr:full": "6411 Saint Clair Ave Cleveland OH 44103",
    "addr:housenumber": "6411",
    "addr:postcode": "44103",
    "addr:street": "Saint Clair Ave",
    "iso:country": "US",
    "sg:address": "6411 Saint Clair Ave",
    "sg:city": "Cleveland",
    "sg:classifiers": [
      {
        "category": "Health Services",
        "subcategory": "Chiropractor",
        "type": "Services"
      }
    ],
    "sg:phone": "+1 216 391 4779",
    "sg:postcode": "44103",
    "sg:province": "OH",
    "wof:name": "Cyril Von Savage DC",
    "wof:placetype": "venue"
  },
  "geometry": {"coordinates":[-81.645477,41.525299],"type":"Point"}
}
