{
  "type": "Feature",
  "properties": {
    "addr:full":"22840 Lake Shore Blvd Euclid OH 44123",
    "addr:housenumber":"22840",
    "addr:postcode":"44123",
    "addr:street":"Lake Shore Blvd",
    "iso:country":"US",
    "sg:address":"22840 Lake Shore Blvd",
    "sg:city":"Euclid",
    "sg:classifiers":[
        {
            "category":"Shopping",
            "subcategory":"Discount & Variety Stores",
            "type":"Retail Goods"
        }
    ],
    "sg:phone":"+1 216 731 9000",
    "sg:postcode":"44123",
    "sg:province":"OH",
    "sg:tags":[
        "deep"
    ],
    "wof:name":"Marcs",
    "wof:placetype":"venue"
},
  "geometry": {"coordinates":[-81.52061,41.613388],"type":"Point"}
}