{
  "type": "Feature",
  "properties": {
    "addr:full": "4924 Para Dr Cincinnati OH 45237",
    "addr:housenumber": "4924",
    "addr:postcode": "45237",
    "addr:street": "Para Dr",
    "iso:country": "US",
    "sg:address": "4924 Para Dr",
    "sg:city": "Cincinnati",
    "sg:classifiers": [
      {
        "category": "Professional",
        "subcategory": "Computer Services",
        "type": "Services"
      }
    ],
    "sg:phone": "+1 513 242 7300",
    "sg:postcode": "45237",
    "sg:province": "OH",
    "sg:tags": [
      "cd-rom",
      "software"
    ],
    "sg:website": "http://www.emcv2.com",
    "wof:name": "Ccdi",
    "wof:placetype": "venue"
  },
  "geometry": {"coordinates":[-84.483352,39.175673],"type":"Point"}
}
