{
  "type": "Feature",
  "properties": {
    "iso:country":"US",
    "sg:address":"5040 W Eastwood Cir",
    "sg:city":"Cincinnati",
    "sg:classifiers":[
        {
            "category":"Wholesale",
            "subcategory":"Computers",
            "type":"Manufacturing & Wholesale Goods"
        }
    ],
    "sg:phone":"+1 513 271 4425",
    "sg:postcode":"45227",
    "sg:province":"OH",
    "sg:tags":[
        "computer-wholesale",
        "manufacturer"
    ],
    "sg:website":"http://www.decisionpointmediainsights.com",
    "wof:name":"Decisionpoint Media Insights",
    "wof:placetype":"venue"
},
  "geometry": {"coordinates":[-84.41083,39.162969],"type":"Point"}
}