{
  "type": "Feature",
  "properties": {
    "addr:full": "5040 W Eastwood Cir Cincinnati OH 45227",
    "addr:housenumber": "5040",
    "addr:postcode": "45227",
    "addr:street": "W Eastwood Cir",
    "iso:country": "US",
    "sg:address": "5040 W Eastwood Cir",
    "sg:city": "Cincinnati",
    "sg:classifiers": [
      {
        "category": "Wholesale",
        "subcategory": "Computers",
        "type": "Manufacturing \u0026 Wholesale Goods"
      }
    ],
    "sg:phone": "+1 513 271 4425",
    "sg:postcode": "45227",
    "sg:province": "OH",
    "sg:tags": [
      "computer-wholesale",
      "manufacturer"
    ],
    "sg:website": "http://www.decisionpointmediainsights.com",
    "wof:name": "Decisionpoint Media Insights",
    "wof:placetype": "venue"
  },
  "geometry": {"coordinates":[-84.41083,39.162969],"type":"Point"}
}
