{
  "type": "Feature",
  "properties": {
    "addr:full":"403 E Main St Lancaster OH 43130",
    "addr:housenumber":"403",
    "addr:postcode":"43130",
    "addr:street":"E Main St",
    "iso:country":"US",
    "sg:address":"403 E Main St",
    "sg:city":"Lancaster",
    "sg:classifiers":[
        {
            "category":"Insurance",
            "subcategory":"Insurance Agent",
            "type":"Services"
        }
    ],
    "sg:phone":"+1 740 653 3352",
    "sg:postcode":"43130",
    "sg:province":"OH",
    "wof:name":"American Family Insurance",
    "wof:placetype":"venue"
},
  "geometry": {"coordinates":[-82.595541,39.71361],"type":"Point"}
}