{
  "type": "Feature",
  "properties": {
    "addr:full": "222 Sharon Woods Rd Wadsworth OH 44281",
    "addr:housenumber": "222",
    "addr:postcode": "44281",
    "addr:street": "Sharon Woods Rd",
    "iso:country": "US",
    "sg:address": "222 Sharon Woods Rd",
    "sg:city": "Wadsworth",
    "sg:classifiers": [
      {
        "category": "Professional",
        "subcategory": "Management \u0026 Consulting",
        "type": "Services"
      }
    ],
    "sg:phone": "+1 330 666 3758",
    "sg:postcode": "44281",
    "sg:province": "OH",
    "sg:tags": [
      "consultant",
      "business"
    ],
    "wof:name": "Don Harbert Enterprises Inc",
    "wof:placetype": "venue"
  },
  "geometry": {"coordinates":[-81.693326,41.11367],"type":"Point"}
}
