{
  "type": "Feature",
  "properties": {
    "addr:full":"1530 King Ave Columbus OH 43212",
    "addr:housenumber":"1530",
    "addr:postcode":"43212",
    "addr:street":"King Ave",
    "iso:country":"US",
    "sg:address":"1530 King Ave",
    "sg:city":"Columbus",
    "sg:classifiers":[
        {
            "category":"Professional",
            "type":"Services"
        }
    ],
    "sg:phone":"+1 614 486 6545",
    "sg:postcode":"43212",
    "sg:province":"OH",
    "wof:name":"Katie M Kronenberg",
    "wof:placetype":"venue"
},
  "geometry": {"coordinates":[-83.04750300000001,39.991759],"type":"Point"}
}