{
  "type": "Feature",
  "properties": {
    "addr:full": "1246 N Main St Urbana OH 43078",
    "addr:housenumber": "1246",
    "addr:postcode": "43078",
    "addr:street": "N Main St",
    "iso:country": "US",
    "sg:address": "1246 N Main St",
    "sg:city": "Urbana",
    "sg:classifiers": [
      {
        "category": "Autos \u0026 Motor Vehicles",
        "subcategory": "Automobile Sales",
        "type": "Retail Goods"
      }
    ],
    "sg:phone": "+1 937 322 2269",
    "sg:postcode": "43078",
    "sg:province": "OH",
    "sg:tags": [
      "truck"
    ],
    "wof:name": "White's Service Ctr",
    "wof:placetype": "venue"
  },
  "geometry": {"coordinates":[-83.749352,40.124525],"type":"Point"}
}
