{
  "type": "Feature",
  "properties": {
    "addr:full": "14 W 4th St Dayton OH 45402",
    "addr:housenumber": "14",
    "addr:postcode": "45402",
    "addr:street": "W 4Th St",
    "iso:country": "US",
    "sg:address": "14 W 4th St",
    "sg:city": "Dayton",
    "sg:classifiers": [
      {
        "category": "Government",
        "subcategory": "Office",
        "type": "Public Place"
      }
    ],
    "sg:phone": "+1 937 225 4547",
    "sg:postcode": "45402",
    "sg:province": "OH",
    "wof:name": "Sexually Transmitted DISEASE",
    "wof:placetype": "venue"
  },
  "geometry": {"coordinates":[-84.193066,39.757787],"type":"Point"}
}
