{
  "type": "Feature",
  "properties": {
    "addr:full":"401 Matthew St Marietta OH 45750",
    "addr:housenumber":"401",
    "addr:postcode":"45750",
    "addr:street":"Matthew St",
    "iso:country":"US",
    "sg:address":"401 Matthew St",
    "sg:city":"Marietta",
    "sg:classifiers":[
        {
            "category":"Social Services",
            "subcategory":"Job Training",
            "type":"Services"
        }
    ],
    "sg:phone":"+1 740 374 1407",
    "sg:postcode":"45750",
    "sg:province":"OH",
    "sg:tags":[
        "rehabilitation"
    ],
    "sg:website":"www.mmhospital.org",
    "wof:name":"Rehabilitation Center",
    "wof:placetype":"venue"
},
  "geometry": {"coordinates":[-81.462362,39.434847],"type":"Point"}
}