{
  "type": "Feature",
  "properties": {
    "addr:full":"982 N High St Columbus OH 43201",
    "addr:housenumber":"982",
    "addr:postcode":"43201",
    "addr:street":"N High St",
    "iso:country":"US",
    "sg:address":"982 N High St",
    "sg:city":"Columbus",
    "sg:classifiers":[
        {
            "category":"Restaurant",
            "type":"Food & Drink"
        }
    ],
    "sg:phone":"+1 614 421 2140",
    "sg:postcode":"43201",
    "sg:province":"OH",
    "sg:tags":[
        "tea",
        "rooms"
    ],
    "wof:name":"Zencha Tea Salon",
    "wof:placetype":"venue"
},
  "geometry": {"coordinates":[-83.00444400000001,39.981925],"type":"Point"}
}