{
  "type": "Feature",
  "properties": {
    "addr:full": "11049 Prince Ln Cincinnati OH 45241",
    "addr:housenumber": "11049",
    "addr:postcode": "45241",
    "addr:street": "Prince Ln",
    "iso:country": "US",
    "sg:address": "11049 Prince Ln",
    "sg:city": "Cincinnati",
    "sg:classifiers": [
      {
        "category": "Communications",
        "type": "Services"
      }
    ],
    "sg:phone": "+1 513 771 8863",
    "sg:postcode": "45241",
    "sg:province": "OH",
    "sg:tags": [
      "communication"
    ],
    "wof:name": "Digital Music Express",
    "wof:placetype": "venue"
  },
  "geometry": {"coordinates":[-84.437432,39.270536],"type":"Point"}
}
