{
  "type": "Feature",
  "properties": {
    "addr:full":"771 N Freedom St Ravenna OH 44266",
    "addr:housenumber":"771",
    "addr:postcode":"44266",
    "addr:street":"N Freedom St",
    "iso:country":"US",
    "sg:address":"771 N Freedom St",
    "sg:city":"Ravenna",
    "sg:classifiers":[
        {
            "category":"Professional",
            "subcategory":"Business Services",
            "type":"Services"
        }
    ],
    "sg:phone":"+1 330 297 4919",
    "sg:postcode":"44266",
    "sg:province":"OH",
    "sg:tags":[
        "telemarketing"
    ],
    "wof:name":"Pasco Telemarketing",
    "wof:placetype":"venue"
},
  "geometry": {"coordinates":[-81.23260000000001,41.168233],"type":"Point"}
}