{
  "type": "Feature",
  "properties": {
    "addr:full": "5125 Cemetery Rd Hilliard OH 43026",
    "addr:housenumber": "5125",
    "addr:postcode": "43026",
    "addr:street": "Cemetery Rd",
    "iso:country": "US",
    "sg:address": "5125 Cemetery Rd",
    "sg:city": "Hilliard",
    "sg:classifiers": [
      {
        "category": "Retail",
        "subcategory": "Veterinary Services",
        "type": "Services"
      }
    ],
    "sg:phone": "+1 614 876 5125",
    "sg:postcode": "43026",
    "sg:province": "OH",
    "sg:tags": [
      "veterinarian"
    ],
    "wof:name": "Hilliard Veterinary Hospital",
    "wof:placetype": "venue"
  },
  "geometry": {"coordinates":[-83.151801,40.030508],"type":"Point"}
}
