{
  "type": "Feature",
  "properties": {
    "iso:country":"US",
    "sg:address":"5125 Cemetery Rd",
    "sg:city":"Hilliard",
    "sg:classifiers":[
        {
            "category":"Retail",
            "subcategory":"Veterinary Services",
            "type":"Services"
        }
    ],
    "sg:phone":"+1 614 876 5125",
    "sg:postcode":"43026",
    "sg:province":"OH",
    "sg:tags":[
        "veterinarian"
    ],
    "wof:name":"Hilliard Veterinary Hospital",
    "wof:placetype":"venue"
},
  "geometry": {"coordinates":[-83.15180100000001,40.030508],"type":"Point"}
}