{
  "type": "Feature",
  "properties": {
    "addr:full": "1850 E Wyandot Ave Upper Sandusky OH 43351",
    "addr:housenumber": "1850 e",
    "addr:postcode": "43351",
    "addr:street": "Wyandot Ave",
    "iso:country": "US",
    "sg:address": "1850 E Wyandot Ave",
    "sg:city": "Upper Sandusky",
    "sg:classifiers": [
      {
        "category": "Freight",
        "type": "Transportation"
      }
    ],
    "sg:phone": "+1 419 294 5728",
    "sg:postcode": "43351",
    "sg:province": "OH",
    "sg:tags": [
      "trucking"
    ],
    "wof:name": "Con-Way Central Express",
    "wof:placetype": "venue"
  },
  "geometry": {"coordinates":[-83.245475,40.83356],"type":"Point"}
}
