{
  "type": "Feature",
  "properties": {
    "iso:country":"US",
    "sg:address":"2857 Blue Jacket Ct",
    "sg:city":"Lima",
    "sg:classifiers":[
        {
            "category":"Banks & Credit Unions",
            "subcategory":"Bank",
            "type":"Services"
        }
    ],
    "sg:phone":"+1 419 223 9746",
    "sg:postcode":"45806",
    "sg:province":"OH",
    "sg:tags":[
        "federal",
        "loan",
        "real estate"
    ],
    "wof:name":"Lima Superior Federal Cr Un",
    "wof:placetype":"venue"
},
  "geometry": {"coordinates":[-84.149559,40.698051],"type":"Point"}
}