{
  "type": "Feature",
  "properties": {
    "addr:full": "1429 Brookfield Rd Hubbard OH 44425",
    "addr:housenumber": "1429",
    "addr:postcode": "44425",
    "addr:street": "Brookfield Rd",
    "iso:country": "US",
    "sg:address": "1429 Brookfield Rd",
    "sg:city": "Hubbard",
    "sg:classifiers": [
      {
        "category": "Wholesale",
        "subcategory": "Construction Materials",
        "type": "Manufacturing \u0026 Wholesale Goods"
      }
    ],
    "sg:phone": "+1 330 448 8005",
    "sg:postcode": "44425",
    "sg:province": "OH",
    "sg:tags": [
      "building"
    ],
    "wof:name": "City Stone LLC",
    "wof:placetype": "venue"
  },
  "geometry": {"coordinates":[-80.568529,41.20403],"type":"Point"}
}
