{
  "type": "Feature",
  "properties": {
    "addr:full": "7527 East Pike Norwich OH 43767",
    "addr:housenumber": "7527",
    "addr:postcode": "43767",
    "addr:street": "East Pike",
    "iso:country": "US",
    "sg:address": "7527 East Pike",
    "sg:city": "Norwich",
    "sg:classifiers": [
      {
        "category": "Wholesale",
        "subcategory": "Durable Goods \u0026 Equipment",
        "type": "Manufacturing \u0026 Wholesale Goods"
      }
    ],
    "sg:phone": "+1 740 826 7439",
    "sg:postcode": "43767",
    "sg:province": "OH",
    "sg:tags": [
      "used",
      "merchandise"
    ],
    "wof:name": "Bogarts Antique Mall",
    "wof:placetype": "venue"
  },
  "geometry": {"coordinates":[-81.847666,39.973534],"type":"Point"}
}
