{
  "type": "Feature",
  "properties": {
    "iso:country":"US",
    "sg:address":"4975 Meyers Ln",
    "sg:city":"Cincinnati",
    "sg:classifiers":[
        {
            "category":"Building & Trades",
            "subcategory":"Construction",
            "type":"Services"
        }
    ],
    "sg:phone":"+1 513 793 8329",
    "sg:postcode":"45242",
    "sg:province":"OH",
    "sg:tags":[
        "carpentry",
        "contractor"
    ],
    "wof:name":"Meyer & Meyer Remodeling",
    "wof:placetype":"venue"
},
  "geometry": {"coordinates":[-84.372145,39.254727],"type":"Point"}
}