{
  "type": "Feature",
  "properties": {
    "addr:full": "4975 Meyers Ln Cincinnati OH 45242",
    "addr:housenumber": "4975",
    "addr:postcode": "45242",
    "addr:street": "Meyers Ln",
    "iso:country": "US",
    "sg:address": "4975 Meyers Ln",
    "sg:city": "Cincinnati",
    "sg:classifiers": [
      {
        "category": "Building \u0026 Trades",
        "subcategory": "Construction",
        "type": "Services"
      }
    ],
    "sg:phone": "+1 513 793 8329",
    "sg:postcode": "45242",
    "sg:province": "OH",
    "sg:tags": [
      "carpentry",
      "contractor"
    ],
    "wof:name": "Meyer \u0026 Meyer Remodeling",
    "wof:placetype": "venue"
  },
  "geometry": {"coordinates":[-84.372145,39.254727],"type":"Point"}
}
