{
  "type": "Feature",
  "properties": {
    "iso:country":"US",
    "sg:address":"13150 Wenger Rd",
    "sg:city":"Anna",
    "sg:phone":"+1 937 394 7698",
    "sg:postcode":"45302",
    "sg:province":"OH",
    "sg:tags":[
        "farm",
        "corn"
    ],
    "wof:name":"Fred Berning",
    "wof:placetype":"venue"
},
  "geometry": {"coordinates":[-84.201864,40.385647],"type":"Point"}
}