{
  "type": "Feature",
  "properties": {
    "addr:full": "5218 Youngstown Poland Rd Youngstown OH 44514",
    "addr:housenumber": "5218",
    "addr:postcode": "44514",
    "addr:street": "Poland Rd",
    "iso:country": "US",
    "sg:address": "5218 Youngstown Poland Rd",
    "sg:city": "Youngstown",
    "sg:classifiers": [
      {
        "category": "Autos \u0026 Motor Vehicles",
        "subcategory": "Auto Supplies",
        "type": "Retail Goods"
      },
      {
        "category": "Wholesale",
        "subcategory": "Auto Parts",
        "type": "Manufacturing \u0026 Wholesale Goods"
      }
    ],
    "sg:phone": "+1 330 757 9839",
    "sg:postcode": "44514",
    "sg:province": "OH",
    "sg:tags": [
      "automobile"
    ],
    "wof:name": "M V G Auto Supply",
    "wof:placetype": "venue"
  },
  "geometry": {"coordinates":[-80.615699,41.046224],"type":"Point"}
}
