{
  "type": "Feature",
  "properties": {
    "iso:country":"US",
    "sg:address":"7300 Vine St",
    "sg:city":"Cincinnati",
    "sg:classifiers":[
        {
            "category":"Wholesale",
            "subcategory":"Auto Parts",
            "type":"Manufacturing & Wholesale Goods"
        }
    ],
    "sg:phone":"+1 513 821 0444",
    "sg:postcode":"45216",
    "sg:province":"OH",
    "sg:tags":[
        "automobile",
        "supply"
    ],
    "wof:name":"Top Gun Engine Parts Warehouse",
    "wof:placetype":"venue"
},
  "geometry": {"coordinates":[-84.477694,39.19663],"type":"Point"}
}