{
  "type": "Feature",
  "properties": {
    "addr:full": "299 W Main St Alliance OH 44601",
    "addr:housenumber": "299",
    "addr:postcode": "44601",
    "addr:street": "W Main St",
    "iso:country": "US",
    "sg:address": "299 W Main St",
    "sg:city": "Alliance",
    "sg:classifiers": [
      {
        "category": "Food \u0026 Beverages",
        "subcategory": "Groceries \u0026 Convenience Stores",
        "type": "Retail Goods"
      }
    ],
    "sg:phone": "+1 330 821 2860",
    "sg:postcode": "44601",
    "sg:province": "OH",
    "sg:tags": [
      "grocer"
    ],
    "wof:name": "Korosy's Korner",
    "wof:placetype": "venue"
  },
  "geometry": {"coordinates":[-81.109918,40.92179],"type":"Point"}
}
