{
  "type": "Feature",
  "properties": {
    "addr:full": "923 Findlay St Portsmouth OH 45662",
    "addr:housenumber": "923",
    "addr:postcode": "45662",
    "addr:street": "Findlay St",
    "iso:country": "US",
    "sg:address": "923 Findlay St",
    "sg:city": "Portsmouth",
    "sg:classifiers": [
      {
        "category": "Wholesale",
        "subcategory": "Electrical",
        "type": "Manufacturing \u0026 Wholesale Goods"
      }
    ],
    "sg:phone": "+1 740 354 3163",
    "sg:postcode": "45662",
    "sg:province": "OH",
    "sg:tags": [
      "control",
      "security",
      "system"
    ],
    "wof:name": "Social Security Adminstration",
    "wof:placetype": "venue"
  },
  "geometry": {"coordinates":[-82.992883,38.737969],"type":"Point"}
}
