{
  "type": "Feature",
  "properties": {
    "addr:full": "30799 Pinetree Rd Cleveland OH 44124",
    "addr:housenumber": "30799",
    "addr:postcode": "44124",
    "addr:street": "Pinetree Rd",
    "iso:country": "US",
    "sg:address": "30799 Pinetree Rd",
    "sg:city": "Cleveland",
    "sg:classifiers": [
      {
        "category": "Wholesale",
        "subcategory": "Hardware",
        "type": "Manufacturing \u0026 Wholesale Goods"
      }
    ],
    "sg:phone": "+1 440 542 1289",
    "sg:postcode": "44124",
    "sg:province": "OH",
    "wof:name": "J V Industrial Sales",
    "wof:placetype": "venue"
  },
  "geometry": {"coordinates":[-81.46014,41.462399],"type":"Point"}
}
