{
  "type": "Feature",
  "properties": {
    "addr:full": "912 E State St Sharon OH 16146",
    "addr:housenumber": "912",
    "addr:postcode": "16146",
    "addr:street": "E State St",
    "iso:country": "US",
    "sg:address": "912 E State St",
    "sg:city": "Sharon",
    "sg:classifiers": [
      {
        "category": "Health Services",
        "subcategory": "Doctor",
        "type": "Services"
      }
    ],
    "sg:phone": "+1 724 346 6500",
    "sg:postcode": "16146",
    "sg:province": "OH",
    "sg:tags": [
      "physician",
      "surgeon"
    ],
    "wof:name": "Preventative Medicine Ctr",
    "wof:placetype": "venue"
  },
  "geometry": {"coordinates":[-80.492353,41.232958],"type":"Point"}
}
