{
  "type": "Feature",
  "properties": {
    "iso:country":"US",
    "sg:address":"912 E State St",
    "sg:city":"Sharon",
    "sg:classifiers":[
        {
            "category":"Health Services",
            "subcategory":"Doctor",
            "type":"Services"
        }
    ],
    "sg:phone":"+1 724 346 6500",
    "sg:postcode":"16146",
    "sg:province":"OH",
    "sg:tags":[
        "physician",
        "surgeon"
    ],
    "wof:name":"Preventative Medicine Ctr",
    "wof:placetype":"venue"
},
  "geometry": {"coordinates":[-80.49235299999999,41.232958],"type":"Point"}
}