{
  "type": "Feature",
  "properties": {
    "iso:country":"US",
    "sg:address":"25111 Miles Rd",
    "sg:city":"Cleveland",
    "sg:classifiers":[
        {
            "category":"Professional",
            "subcategory":"Accounting & Tax Preparation",
            "type":"Services"
        }
    ],
    "sg:phone":"+1 216 595 1000",
    "sg:postcode":"44128",
    "sg:province":"OH",
    "sg:tags":[
        "payroll"
    ],
    "wof:name":"Check Mate Payroll Svc",
    "wof:placetype":"venue"
},
  "geometry": {"coordinates":[-81.501598,41.424187],"type":"Point"}
}