{
  "type": "Feature",
  "properties": {
    "iso:country":"US",
    "sg:address":"842 4th St",
    "sg:city":"Portsmouth",
    "sg:classifiers":[
        {
            "category":"Manufacturing",
            "subcategory":"Printing",
            "type":"Manufacturing & Wholesale Goods"
        }
    ],
    "sg:phone":"+1 740 354 6542",
    "sg:postcode":"45662",
    "sg:province":"OH",
    "sg:tags":[
        "commercial"
    ],
    "wof:name":"Keystone Printing Co/Copy Cat",
    "wof:placetype":"venue"
},
  "geometry": {"coordinates":[-82.995748,38.733073],"type":"Point"}
}