{
  "type": "Feature",
  "properties": {
    "addr:full": "842 4th St Portsmouth OH 45662",
    "addr:housenumber": "842",
    "addr:postcode": "45662",
    "addr:street": "4Th St",
    "iso:country": "US",
    "sg:address": "842 4th St",
    "sg:city": "Portsmouth",
    "sg:classifiers": [
      {
        "category": "Manufacturing",
        "subcategory": "Printing",
        "type": "Manufacturing \u0026 Wholesale Goods"
      }
    ],
    "sg:phone": "+1 740 354 6542",
    "sg:postcode": "45662",
    "sg:province": "OH",
    "sg:tags": [
      "commercial"
    ],
    "wof:name": "Keystone Printing Co/Copy Cat",
    "wof:placetype": "venue"
  },
  "geometry": {"coordinates":[-82.995748,38.733073],"type":"Point"}
}
