{
  "type": "Feature",
  "properties": {
    "iso:country":"US",
    "sg:address":"66252 2nd Ave",
    "sg:city":"Reedsville",
    "sg:classifiers":[
        {
            "category":"Retail",
            "subcategory":"Laundry & Dry Cleaning",
            "type":"Services"
        }
    ],
    "sg:phone":"+1 740 378 6224",
    "sg:postcode":"45772",
    "sg:province":"OH",
    "sg:tags":[
        "shop",
        "sewing"
    ],
    "wof:name":"Custom Sewing By Bobbie Reed",
    "wof:placetype":"venue"
},
  "geometry": {"coordinates":[-81.74854999999999,39.122749],"type":"Point"}
}