{
  "type": "Feature",
  "properties": {
    "addr:full": "500 E Starr Ave Columbus OH 43201",
    "addr:housenumber": "500",
    "addr:postcode": "43201",
    "addr:street": "E Starr Ave",
    "iso:country": "US",
    "sg:address": "500 E Starr Ave",
    "sg:city": "Columbus",
    "sg:classifiers": [
      {
        "category": "Retail",
        "subcategory": "Auto Repair",
        "type": "Services"
      }
    ],
    "sg:phone": "+1 614 291 2378",
    "sg:postcode": "43201",
    "sg:province": "OH",
    "sg:tags": [
      "repairing",
      "automobile"
    ],
    "wof:name": "Best Price Auto Sales \u0026 Svc",
    "wof:placetype": "venue"
  },
  "geometry": {"coordinates":[-82.989683,39.982745],"type":"Point"}
}
