{
  "type": "Feature",
  "properties": {
    "addr:full": "4220 Dane Ave Cincinnati OH 45223",
    "addr:housenumber": "4220",
    "addr:postcode": "45223",
    "addr:street": "Dane Ave",
    "iso:country": "US",
    "sg:address": "4220 Dane Ave",
    "sg:city": "Cincinnati",
    "sg:classifiers": [
      {
        "category": "Social Services",
        "type": "Services"
      },
      {
        "category": "Place Of Worship",
        "type": "Public Place"
      },
      {
        "category": "Shopping",
        "subcategory": "Thrift Store",
        "type": "Retail Goods"
      },
      {
        "category": "Banks \u0026 Credit Unions",
        "subcategory": "Bank",
        "type": "Services"
      }
    ],
    "sg:phone": "+1 513 681 5938",
    "sg:postcode": "45223",
    "sg:province": "OH",
    "sg:tags": [
      "shop",
      "second",
      "church",
      "hand"
    ],
    "sg:website": "http://www.salvationarmysouth.org",
    "wof:name": "Salvation Army",
    "wof:placetype": "venue"
  },
  "geometry": {"coordinates":[-84.532661,39.164162],"type":"Point"}
}
