{
  "type": "Feature",
  "properties": {
    "iso:country":"US",
    "sg:address":"4165 Olentangy Blvd",
    "sg:city":"Columbus",
    "sg:classifiers":[
        {
            "category":"Health Services",
            "subcategory":"Doctor",
            "type":"Services"
        }
    ],
    "sg:phone":"+1 614 221 5647",
    "sg:postcode":"43214",
    "sg:province":"OH",
    "sg:tags":[
        "medical"
    ],
    "wof:name":"Victor Vermeulen MD Inc",
    "wof:placetype":"venue"
},
  "geometry": {"coordinates":[-83.028065,40.044327],"type":"Point"}
}