{
  "type": "Feature",
  "properties": {
    "iso:country":"US",
    "sg:address":"6356 Market Ave N",
    "sg:city":"Canton",
    "sg:classifiers":[
        {
            "category":"Autos & Motor Vehicles",
            "subcategory":"Fuel & Gas Station",
            "type":"Retail Goods"
        }
    ],
    "sg:phone":"+1 330 497 1782",
    "sg:postcode":"44721",
    "sg:province":"OH",
    "sg:tags":[
        "oil"
    ],
    "wof:name":"Bell Stores Citgo",
    "wof:placetype":"venue"
},
  "geometry": {"coordinates":[-81.363785,40.874278],"type":"Point"}
}