{
  "type": "Feature",
  "properties": {
    "addr:full": "6356 Market Ave N Canton OH 44721",
    "addr:housenumber": "6356",
    "addr:postcode": "44721",
    "addr:street": "Market Ave N",
    "iso:country": "US",
    "sg:address": "6356 Market Ave N",
    "sg:city": "Canton",
    "sg:classifiers": [
      {
        "category": "Autos \u0026 Motor Vehicles",
        "subcategory": "Fuel \u0026 Gas Station",
        "type": "Retail Goods"
      }
    ],
    "sg:phone": "+1 330 497 1782",
    "sg:postcode": "44721",
    "sg:province": "OH",
    "sg:tags": [
      "oil"
    ],
    "wof:name": "Bell Stores Citgo",
    "wof:placetype": "venue"
  },
  "geometry": {"coordinates":[-81.363785,40.874278],"type":"Point"}
}
