{
  "type": "Feature",
  "properties": {
    "addr:full": "2078 S Taylor Rd Cleveland OH 44118",
    "addr:housenumber": "2078",
    "addr:postcode": "44118",
    "addr:street": "S Taylor Rd",
    "iso:country": "US",
    "sg:address": "2078 S Taylor Rd",
    "sg:city": "Cleveland",
    "sg:classifiers": [
      {
        "category": "Food \u0026 Beverages",
        "subcategory": "Groceries \u0026 Convenience Stores",
        "type": "Retail Goods"
      }
    ],
    "sg:phone": "+1 216 932 5000",
    "sg:postcode": "44118",
    "sg:province": "OH",
    "wof:name": "International Foods",
    "wof:placetype": "venue"
  },
  "geometry": {"coordinates":[-81.556065,41.501931],"type":"Point"}
}
