{
  "type": "Feature",
  "properties": {
    "iso:country":"US",
    "sg:address":"1769 Elmore St",
    "sg:city":"Cincinnati",
    "sg:classifiers":[
        {
            "category":"Building & Trades",
            "subcategory":"Electrical",
            "type":"Services"
        }
    ],
    "sg:phone":"+1 513 271 5000",
    "sg:postcode":"45223",
    "sg:province":"OH",
    "sg:tags":[
        "electric",
        "contractor"
    ],
    "sg:website":"www.cooper-electric.net",
    "wof:name":"Cooper Electric",
    "wof:placetype":"venue"
},
  "geometry": {"coordinates":[-84.548341,39.15576],"type":"Point"}
}