{
  "type": "Feature",
  "properties": {
    "addr:full": "419 E Main St Canfield OH 44406",
    "addr:housenumber": "419",
    "addr:postcode": "44406",
    "addr:street": "E Main St",
    "iso:country": "US",
    "sg:address": "419 E Main St",
    "sg:city": "Canfield",
    "sg:classifiers": [
      {
        "category": "Shopping",
        "subcategory": "Pharmacy",
        "type": "Retail Goods"
      }
    ],
    "sg:phone": "+1 330 533 3972",
    "sg:postcode": "44406",
    "sg:province": "OH",
    "sg:tags": [
      "drug",
      "store"
    ],
    "wof:name": "Eckerd",
    "wof:placetype": "venue"
  },
  "geometry": {"coordinates":[-80.745972,41.024661],"type":"Point"}
}
