{
  "type": "Feature",
  "properties": {
    "iso:country":"US",
    "sg:address":"502 N Front St",
    "sg:city":"Oak Hill",
    "sg:classifiers":[
        {
            "category":"Autos & Motor Vehicles",
            "subcategory":"Automobile Sales",
            "type":"Retail Goods"
        }
    ],
    "sg:phone":"+1 740 682 9206",
    "sg:postcode":"45656",
    "sg:province":"OH",
    "sg:tags":[
        "car",
        "used",
        "dealer"
    ],
    "wof:name":"C M Auto Sales",
    "wof:placetype":"venue"
},
  "geometry": {"coordinates":[-82.568668,38.899913],"type":"Point"}
}