{
  "type": "Feature",
  "properties": {
    "addr:full": "502 N Front St Oak Hill OH 45656",
    "addr:housenumber": "502",
    "addr:postcode": "45656",
    "addr:street": "N Front St",
    "iso:country": "US",
    "sg:address": "502 N Front St",
    "sg:city": "Oak Hill",
    "sg:classifiers": [
      {
        "category": "Autos \u0026 Motor Vehicles",
        "subcategory": "Automobile Sales",
        "type": "Retail Goods"
      }
    ],
    "sg:phone": "+1 740 682 9206",
    "sg:postcode": "45656",
    "sg:province": "OH",
    "sg:tags": [
      "car",
      "used",
      "dealer"
    ],
    "wof:name": "C M Auto Sales",
    "wof:placetype": "venue"
  },
  "geometry": {"coordinates":[-82.568668,38.899913],"type":"Point"}
}
