{
  "type": "Feature",
  "properties": {
    "addr:full": "884 Center Dr Vandalia OH 45377",
    "addr:housenumber": "884",
    "addr:postcode": "45377",
    "addr:street": "Center Dr",
    "iso:country": "US",
    "sg:address": "884 Center Dr",
    "sg:city": "Vandalia",
    "sg:classifiers": [
      {
        "category": "Manufacturing",
        "subcategory": "Tools \u0026 Machinery",
        "type": "Manufacturing \u0026 Wholesale Goods"
      }
    ],
    "sg:phone": "+1 937 890 3335",
    "sg:postcode": "45377",
    "sg:province": "OH",
    "sg:tags": [
      "machine",
      "shop"
    ],
    "wof:name": "Metwood Industries",
    "wof:placetype": "venue"
  },
  "geometry": {"coordinates":[-84.185052,39.884277],"type":"Point"}
}
