{
  "type": "Feature",
  "properties": {
    "addr:full": "15636 Grove Rd Garrettsville OH 44231",
    "addr:housenumber": "15636",
    "addr:postcode": "44231",
    "addr:street": "Grove Rd",
    "iso:country": "US",
    "sg:address": "15636 Grove Rd",
    "sg:city": "Garrettsville",
    "sg:classifiers": [
      {
        "category": "Home \u0026 Garden",
        "subcategory": "Hardware",
        "type": "Retail Goods"
      }
    ],
    "sg:phone": "+1 440 548 2714",
    "sg:postcode": "44231",
    "sg:province": "OH",
    "sg:tags": [
      "store"
    ],
    "wof:name": "C \u0026 S Hardware",
    "wof:placetype": "venue"
  },
  "geometry": {"coordinates":[-81.087182,41.35564],"type":"Point"}
}
