{
  "type": "Feature",
  "properties": {
    "addr:full": "2009 Michigan St Sidney OH 45365",
    "addr:housenumber": "2009",
    "addr:postcode": "45365",
    "addr:street": "Michigan St",
    "iso:country": "US",
    "sg:address": "2009 Michigan St",
    "sg:city": "Sidney",
    "sg:classifiers": [
      {
        "category": "Bars \u0026 Pubs",
        "type": "Food \u0026 Drink"
      }
    ],
    "sg:phone": "+1 937 492 3299",
    "sg:postcode": "45365",
    "sg:province": "OH",
    "sg:tags": [
      "lounge",
      "cocktail"
    ],
    "wof:name": "Dawg Pound Lounge",
    "wof:placetype": "venue"
  },
  "geometry": {"coordinates":[-84.184238,40.287751],"type":"Point"}
}
