{
  "type": "Feature",
  "properties": {
    "addr:full":"2009 Michigan St Sidney OH 45365",
    "addr:housenumber":"2009",
    "addr:postcode":"45365",
    "addr:street":"Michigan St",
    "iso:country":"US",
    "sg:address":"2009 Michigan St",
    "sg:city":"Sidney",
    "sg:classifiers":[
        {
            "category":"Bars & Pubs",
            "type":"Food & Drink"
        }
    ],
    "sg:phone":"+1 937 492 3299",
    "sg:postcode":"45365",
    "sg:province":"OH",
    "sg:tags":[
        "lounge",
        "cocktail"
    ],
    "wof:name":"Dawg Pound Lounge",
    "wof:placetype":"venue"
},
  "geometry": {"coordinates":[-84.18423799999999,40.287751],"type":"Point"}
}