{
  "type": "Feature",
  "properties": {
    "addr:full": "10142 Dowling Rd Bowling Green OH 43402",
    "addr:housenumber": "10142",
    "addr:postcode": "43402",
    "addr:street": "Dowling Rd",
    "iso:country": "US",
    "sg:address": "10142 Dowling Rd",
    "sg:city": "Bowling Green",
    "sg:classifiers": [
      {
        "category": "Education",
        "subcategory": "School",
        "type": "Public Place"
      }
    ],
    "sg:phone": "+1 419 833 6771",
    "sg:postcode": "43402",
    "sg:province": "OH",
    "sg:tags": [
      "educational",
      "administrative"
    ],
    "wof:name": "Northwest Ohio Serrc Center",
    "wof:placetype": "venue"
  },
  "geometry": {"coordinates":[-83.594849,41.478004],"type":"Point"}
}
