{
  "type": "Feature",
  "properties": {
    "addr:full":"7112 Duluth Ave Cleveland OH 44103",
    "addr:housenumber":"7112",
    "addr:postcode":"44103",
    "addr:street":"Duluth Ave",
    "iso:country":"US",
    "sg:address":"7112 Duluth Ave",
    "sg:city":"Cleveland",
    "sg:classifiers":[
        {
            "category":"Building & Trades",
            "subcategory":"Construction",
            "type":"Services"
        }
    ],
    "sg:phone":"+1 216 431 8049",
    "sg:postcode":"44103",
    "sg:province":"OH",
    "sg:tags":[
        "carpentry",
        "contractor"
    ],
    "wof:name":"Williams Construction",
    "wof:placetype":"venue"
},
  "geometry": {"coordinates":[-81.63951,41.518602],"type":"Point"}
}