{
  "type": "Feature",
  "properties": {
    "iso:country":"US",
    "sg:address":"846 State Rte 46 N",
    "sg:city":"Jefferson",
    "sg:classifiers":[
        {
            "category":"Personal",
            "subcategory":"Barber",
            "type":"Services"
        }
    ],
    "sg:phone":"+1 440 992 9283",
    "sg:postcode":"44047",
    "sg:province":"OH",
    "wof:name":"Barber In The Harbor",
    "wof:placetype":"venue"
},
  "geometry": {"coordinates":[-80.769351,41.747851],"type":"Point"}
}