{
  "type": "Feature",
  "properties": {
    "iso:country":"US",
    "sg:address":"7900 Eagle Rd",
    "sg:city":"Willoughby",
    "sg:classifiers":[
        {
            "category":"Building & Trades",
            "subcategory":"Landscaping Services",
            "type":"Services"
        }
    ],
    "sg:phone":"+1 440 256 7001",
    "sg:postcode":"44094",
    "sg:province":"OH",
    "sg:tags":[
        "landscape",
        "contractor"
    ],
    "wof:name":"A J Nowac Landscaping Inc",
    "wof:placetype":"venue"
},
  "geometry": {"coordinates":[-81.360686,41.604569],"type":"Point"}
}