{
  "type": "Feature",
  "properties": {
    "addr:full": "7900 Eagle Rd Willoughby OH 44094",
    "addr:housenumber": "7900",
    "addr:postcode": "44094",
    "addr:street": "Eagle Rd",
    "iso:country": "US",
    "sg:address": "7900 Eagle Rd",
    "sg:city": "Willoughby",
    "sg:classifiers": [
      {
        "category": "Building \u0026 Trades",
        "subcategory": "Landscaping Services",
        "type": "Services"
      }
    ],
    "sg:phone": "+1 440 256 7001",
    "sg:postcode": "44094",
    "sg:province": "OH",
    "sg:tags": [
      "landscape",
      "contractor"
    ],
    "wof:name": "A J Nowac Landscaping Inc",
    "wof:placetype": "venue"
  },
  "geometry": {"coordinates":[-81.360686,41.604569],"type":"Point"}
}
