{
  "type": "Feature",
  "properties": {
    "iso:country":"US",
    "sg:address":"437 E Center St",
    "sg:city":"Marion",
    "sg:classifiers":[
        {
            "category":"Freight",
            "type":"Transportation"
        }
    ],
    "sg:phone":"+1 740 383 1107",
    "sg:postcode":"43302",
    "sg:province":"OH",
    "sg:tags":[
        "general"
    ],
    "wof:name":"Johnston Supply Inc",
    "wof:placetype":"venue"
},
  "geometry": {"coordinates":[-83.11872099999999,40.588975],"type":"Point"}
}