{
  "type": "Feature",
  "properties": {
    "addr:full":"3420 Hopkins Rd Youngstown OH 44511",
    "addr:housenumber":"3420",
    "addr:postcode":"44511",
    "addr:street":"Hopkins Rd",
    "iso:country":"US",
    "sg:address":"3420 Hopkins Rd",
    "sg:city":"Youngstown",
    "sg:classifiers":[
        {
            "category":"Building & Trades",
            "subcategory":"Cleaning & Sanitation",
            "type":"Services"
        }
    ],
    "sg:phone":"+1 330 758 5611",
    "sg:postcode":"44511",
    "sg:province":"OH",
    "sg:tags":[
        "window"
    ],
    "wof:name":"Marty Stock Spotless Window",
    "wof:placetype":"venue"
},
  "geometry": {"coordinates":[-80.690663,41.063043],"type":"Point"}
}