{
  "type": "Feature",
  "properties": {
    "iso:country":"US",
    "sg:address":"1425 Tiffin Ave",
    "sg:city":"Sandusky",
    "sg:classifiers":[
        {
            "category":"Manufacturing",
            "subcategory":"Metals",
            "type":"Manufacturing & Wholesale Goods"
        }
    ],
    "sg:phone":"+1 419 625 8543",
    "sg:postcode":"44870",
    "sg:province":"OH",
    "sg:tags":[
        "steel",
        "nut",
        "mfg"
    ],
    "sg:website":"www.industrialnut.com",
    "wof:name":"Industrial Nut Corp",
    "wof:placetype":"venue"
},
  "geometry": {"coordinates":[-82.730318,41.443477],"type":"Point"}
}