{
  "type": "Feature",
  "properties": {
    "addr:full": "1425 Tiffin Ave Sandusky OH 44870",
    "addr:housenumber": "1425",
    "addr:postcode": "44870",
    "addr:street": "Tiffin Ave",
    "iso:country": "US",
    "sg:address": "1425 Tiffin Ave",
    "sg:city": "Sandusky",
    "sg:classifiers": [
      {
        "category": "Manufacturing",
        "subcategory": "Metals",
        "type": "Manufacturing \u0026 Wholesale Goods"
      }
    ],
    "sg:phone": "+1 419 625 8543",
    "sg:postcode": "44870",
    "sg:province": "OH",
    "sg:tags": [
      "steel",
      "nut",
      "mfg"
    ],
    "sg:website": "www.industrialnut.com",
    "wof:name": "Industrial Nut Corp",
    "wof:placetype": "venue"
  },
  "geometry": {"coordinates":[-82.730318,41.443477],"type":"Point"}
}
