{
  "type": "Feature",
  "properties": {
    "addr:full":"6800 Eastland Rd Cleveland OH 44130",
    "addr:housenumber":"6800",
    "addr:postcode":"44130",
    "addr:street":"Eastland Rd",
    "iso:country":"US",
    "sg:address":"6800 Eastland Rd",
    "sg:city":"Cleveland",
    "sg:classifiers":[
        {
            "category":"Building & Trades",
            "subcategory":"Plumbing",
            "type":"Services"
        }
    ],
    "sg:phone":"+1 440 243 3535",
    "sg:postcode":"44130",
    "sg:province":"OH",
    "sg:tags":[
        "engineering",
        "contractor"
    ],
    "sg:website":"www.brewer-garrett.com",
    "wof:name":"Brewer-Garrett Co",
    "wof:placetype":"venue"
},
  "geometry": {"coordinates":[-81.843192,41.385196],"type":"Point"}
}