{
  "type": "Feature",
  "properties": {
    "iso:country":"US",
    "sg:address":"4252 Archwood Ave",
    "sg:city":"Cleveland",
    "sg:classifiers":[
        {
            "category":"Freight",
            "type":"Transportation"
        }
    ],
    "sg:phone":"+1 216 883 8510",
    "sg:postcode":"44109",
    "sg:province":"OH",
    "sg:tags":[
        "operator",
        "local",
        "trucking"
    ],
    "wof:name":"D&W Enterprises",
    "wof:placetype":"venue"
},
  "geometry": {"coordinates":[-81.714939,41.453443],"type":"Point"}
}