{
  "type": "Feature",
  "properties": {
    "addr:full": "4252 Archwood Ave Cleveland OH 44109",
    "addr:housenumber": "4252",
    "addr:postcode": "44109",
    "addr:street": "Archwood Ave",
    "iso:country": "US",
    "sg:address": "4252 Archwood Ave",
    "sg:city": "Cleveland",
    "sg:classifiers": [
      {
        "category": "Freight",
        "type": "Transportation"
      }
    ],
    "sg:phone": "+1 216 883 8510",
    "sg:postcode": "44109",
    "sg:province": "OH",
    "sg:tags": [
      "operator",
      "local",
      "trucking"
    ],
    "wof:name": "D\u0026W Enterprises",
    "wof:placetype": "venue"
  },
  "geometry": {"coordinates":[-81.714939,41.453443],"type":"Point"}
}
