{
  "type": "Feature",
  "properties": {
    "iso:country":"US",
    "sg:address":"2703 Fulton Dr NW",
    "sg:city":"Canton",
    "sg:classifiers":[
        {
            "category":"Retail",
            "subcategory":"Veterinary Services",
            "type":"Services"
        }
    ],
    "sg:phone":"+1 330 452 5116",
    "sg:postcode":"44718",
    "sg:province":"OH",
    "sg:tags":[
        "merchandise"
    ],
    "wof:name":"Aquapet",
    "wof:placetype":"venue"
},
  "geometry": {"coordinates":[-81.401295,40.826401],"type":"Point"}
}