{
  "type": "Feature",
  "properties": {
    "iso:country":"US",
    "sg:address":"2676 Carmont Ave SW",
    "sg:city":"Massillon",
    "sg:classifiers":[
        {
            "category":"Arts & Performance",
            "subcategory":"Theater",
            "type":"Entertainment"
        }
    ],
    "sg:phone":"+1 330 833 3820",
    "sg:postcode":"44647",
    "sg:province":"OH",
    "sg:tags":[
        "live",
        "music"
    ],
    "wof:name":"Hoss's DJ Svc",
    "wof:placetype":"venue"
},
  "geometry": {"coordinates":[-81.545565,40.770401],"type":"Point"}
}