{
  "type": "Feature",
  "properties": {
    "addr:full":"1335 Park Ave W Mansfield OH 44906",
    "addr:housenumber":"1335",
    "addr:postcode":"44906",
    "addr:street":"Park Ave W",
    "iso:country":"US",
    "sg:address":"1335 Park Ave W",
    "sg:city":"Mansfield",
    "sg:classifiers":[
        {
            "category":"Personal",
            "subcategory":"Beauty Salon",
            "type":"Services"
        }
    ],
    "sg:phone":"+1 419 522 1335",
    "sg:postcode":"44906",
    "sg:province":"OH",
    "sg:website":"http://lestudiocheveux.com",
    "wof:name":"Studio Cheveaux",
    "wof:placetype":"venue"
},
  "geometry": {"coordinates":[-82.56386000000001,40.759393],"type":"Point"}
}