{
  "type": "Feature",
  "properties": {
    "addr:full": "1206 Lake Ave Ashtabula OH 44004",
    "addr:housenumber": "1206",
    "addr:postcode": "44004",
    "addr:street": "Lake Ave",
    "iso:country": "US",
    "sg:address": "1206 Lake Ave",
    "sg:city": "Ashtabula",
    "sg:classifiers": [
      {
        "category": "Professional",
        "subcategory": "Management \u0026 Consulting",
        "type": "Services"
      }
    ],
    "sg:phone": "+1 440 964 7400",
    "sg:postcode": "44004",
    "sg:province": "OH",
    "sg:tags": [
      "coffee",
      "brewing",
      "devices"
    ],
    "wof:name": "Espresso Zone",
    "wof:placetype": "venue"
  },
  "geometry": {"coordinates":[-80.804859,41.888598],"type":"Point"}
}
