{
  "type": "Feature",
  "properties": {
    "iso:country":"US",
    "sg:address":"1206 Lake Ave",
    "sg:city":"Ashtabula",
    "sg:classifiers":[
        {
            "category":"Professional",
            "subcategory":"Management & Consulting",
            "type":"Services"
        }
    ],
    "sg:phone":"+1 440 964 7400",
    "sg:postcode":"44004",
    "sg:province":"OH",
    "sg:tags":[
        "coffee",
        "brewing",
        "devices"
    ],
    "wof:name":"Espresso Zone",
    "wof:placetype":"venue"
},
  "geometry": {"coordinates":[-80.80485899999999,41.888598],"type":"Point"}
}