{
  "type": "Feature",
  "properties": {
    "iso:country":"US",
    "sg:address":"3615 Brotherton Rd",
    "sg:city":"Cincinnati",
    "sg:classifiers":[
        {
            "category":"Professional",
            "subcategory":"Computer Services",
            "type":"Services"
        }
    ],
    "sg:phone":"+1 513 321 0304",
    "sg:postcode":"45209",
    "sg:province":"OH",
    "sg:tags":[
        "consultant",
        "designer"
    ],
    "wof:name":"Jaybirds Computer Systems",
    "wof:placetype":"venue"
},
  "geometry": {"coordinates":[-84.414186,39.154379],"type":"Point"}
}