{
  "type": "Feature",
  "properties": {
    "iso:country":"US",
    "sg:address":"234 Mount Vernon Rd",
    "sg:city":"Newark",
    "sg:classifiers":[
        {
            "category":"Autos & Motor Vehicles",
            "subcategory":"Recreational Vehicle Sales",
            "type":"Retail Goods"
        },
        {
            "category":"Wholesale",
            "subcategory":"Auto Parts",
            "type":"Manufacturing & Wholesale Goods"
        }
    ],
    "sg:phone":"+1 740 349 7038",
    "sg:postcode":"43055",
    "sg:province":"OH",
    "sg:tags":[
        "trailer",
        "supply"
    ],
    "wof:name":"Ohio Transport Inc",
    "wof:placetype":"venue"
},
  "geometry": {"coordinates":[-82.40713100000001,40.063419],"type":"Point"}
}