{
  "type": "Feature",
  "properties": {
    "addr:full": "234 Mount Vernon Rd Newark OH 43055",
    "addr:housenumber": "234",
    "addr:postcode": "43055",
    "addr:street": "Mount Vernon Rd",
    "iso:country": "US",
    "sg:address": "234 Mount Vernon Rd",
    "sg:city": "Newark",
    "sg:classifiers": [
      {
        "category": "Autos \u0026 Motor Vehicles",
        "subcategory": "Recreational Vehicle Sales",
        "type": "Retail Goods"
      },
      {
        "category": "Wholesale",
        "subcategory": "Auto Parts",
        "type": "Manufacturing \u0026 Wholesale Goods"
      }
    ],
    "sg:phone": "+1 740 349 7038",
    "sg:postcode": "43055",
    "sg:province": "OH",
    "sg:tags": [
      "trailer",
      "supply"
    ],
    "wof:name": "Ohio Transport Inc",
    "wof:placetype": "venue"
  },
  "geometry": {"coordinates":[-82.407131,40.063419],"type":"Point"}
}
