{
  "type": "Feature",
  "properties": {
    "addr:full":"401 Echo Dr NE Newark OH 43055",
    "addr:housenumber":"401",
    "addr:postcode":"43055",
    "addr:street":"Echo Dr Ne",
    "iso:country":"US",
    "sg:address":"401 Echo Dr NE",
    "sg:city":"Newark",
    "sg:classifiers":[
        {
            "category":"Professional",
            "subcategory":"Business Services",
            "type":"Services"
        }
    ],
    "sg:phone":"+1 740 763 0190",
    "sg:postcode":"43055",
    "sg:province":"OH",
    "sg:tags":[
        "inspection"
    ],
    "wof:name":"Federal Building Inspections",
    "wof:placetype":"venue"
},
  "geometry": {"coordinates":[-82.275037,40.084132],"type":"Point"}
}