{
  "type": "Feature",
  "properties": {
    "addr:full": "10800 Brower Rd North Bend OH 45052",
    "addr:postcode": "10800;45052",
    "addr:street": "Brower Rd",
    "iso:country": "US",
    "sg:address": "10800 Brower Rd",
    "sg:city": "North Bend",
    "sg:classifiers": [
      {
        "category": "Professional",
        "type": "Services"
      }
    ],
    "sg:phone": "+1 513 467 0615",
    "sg:postcode": "45052",
    "sg:province": "OH",
    "sg:tags": [
      "establishment"
    ],
    "wof:name": "Enerfab",
    "wof:placetype": "venue"
  },
  "geometry": {"coordinates":[-84.795546,39.135886],"type":"Point"}
}
