{
  "type": "Feature",
  "properties": {
    "addr:full": "860 Sandalwood Rd W Perrysburg OH 43551",
    "addr:housenumber": "860",
    "addr:postcode": "43551",
    "addr:street": "Sandalwood Rd W",
    "iso:country": "US",
    "sg:address": "860 Sandalwood Rd W",
    "sg:city": "Perrysburg",
    "sg:classifiers": [
      {
        "category": "Professional",
        "subcategory": "Engineering",
        "type": "Services"
      }
    ],
    "sg:phone": "+1 419 872 9999",
    "sg:postcode": "43551",
    "sg:province": "OH",
    "sg:tags": [
      "engineer"
    ],
    "wof:name": "L A Grime \u0026 Assoc",
    "wof:placetype": "venue"
  },
  "geometry": {"coordinates":[-83.595329,41.560316],"type":"Point"}
}
