{
  "type": "Feature",
  "properties": {
    "iso:country":"US",
    "sg:address":"860 Sandalwood Rd W",
    "sg:city":"Perrysburg",
    "sg:classifiers":[
        {
            "category":"Professional",
            "subcategory":"Engineering",
            "type":"Services"
        }
    ],
    "sg:phone":"+1 419 872 9999",
    "sg:postcode":"43551",
    "sg:province":"OH",
    "sg:tags":[
        "engineer"
    ],
    "wof:name":"L A Grime & Assoc",
    "wof:placetype":"venue"
},
  "geometry": {"coordinates":[-83.59532900000001,41.560316],"type":"Point"}
}