{
  "type": "Feature",
  "properties": {
    "addr:full": "17714 Twp Hwy 49 Wharton OH 43359",
    "addr:housenumber": "17714",
    "addr:postcode": "43359",
    "addr:street": "Twp Hwy 49",
    "iso:country": "US",
    "sg:address": "17714 Twp Hwy 49",
    "sg:city": "Wharton",
    "sg:phone": "+1 419 458 3195",
    "sg:postcode": "43359",
    "sg:province": "OH",
    "sg:tags": [
      "farm",
      "corn",
      "soybean"
    ],
    "wof:name": "Lawrence Passet",
    "wof:placetype": "venue"
  },
  "geometry": {"coordinates":[-83.43836,40.846976],"type":"Point"}
}
