{
  "type": "Feature",
  "properties": {
    "addr:full": "619 Oak St Cincinnati OH 45206",
    "addr:housenumber": "619",
    "addr:postcode": "45206",
    "addr:street": "Oak St",
    "iso:country": "US",
    "sg:address": "619 Oak St",
    "sg:city": "Cincinnati",
    "sg:classifiers": [
      {
        "category": "Health Services",
        "subcategory": "Clinic",
        "type": "Services"
      }
    ],
    "sg:phone": "+1 513 475 4500",
    "sg:postcode": "45206",
    "sg:province": "OH",
    "sg:tags": [
      "physician",
      "surgeon",
      "bureau",
      "information"
    ],
    "wof:name": "Tri Health Spirit Of Women",
    "wof:placetype": "venue"
  },
  "geometry": {"coordinates":[-84.495807,39.129661],"type":"Point"}
}
