{
  "type": "Feature",
  "properties": {
    "iso:country":"US",
    "sg:address":"24 S Hampton Cir",
    "sg:city":"Rocky River",
    "sg:classifiers":[
        {
            "category":"Professional",
            "type":"Services"
        }
    ],
    "sg:phone":"+1 440 331 7117",
    "sg:postcode":"44116",
    "sg:province":"OH",
    "wof:name":"Alvin F Delau",
    "wof:placetype":"venue"
},
  "geometry": {"coordinates":[-81.859493,41.468853],"type":"Point"}
}