{
  "type": "Feature",
  "properties": {
    "addr:full": "4145 E State Rte 296 Urbana OH 43078",
    "addr:housenumber": "4145",
    "addr:postcode": "43078",
    "addr:street": "E State Rte 296",
    "iso:country": "US",
    "sg:address": "4145 E State Rte 296",
    "sg:city": "Urbana",
    "sg:classifiers": [
      {
        "category": "Farming",
        "subcategory": "Livestock Farm",
        "type": "Manufacturing \u0026 Wholesale Goods"
      }
    ],
    "sg:phone": "+1 937 652 1728",
    "sg:postcode": "43078",
    "sg:province": "OH",
    "sg:tags": [
      "animal",
      "general"
    ],
    "wof:name": "Cable Acres Farm",
    "wof:placetype": "venue"
  },
  "geometry": {"coordinates":[-83.668285,40.164689],"type":"Point"}
}
