{
  "type": "Feature",
  "properties": {
    "iso:country":"US",
    "sg:address":"4145 E State Rte 296",
    "sg:city":"Urbana",
    "sg:classifiers":[
        {
            "category":"Farming",
            "subcategory":"Livestock Farm",
            "type":"Manufacturing & Wholesale Goods"
        }
    ],
    "sg:phone":"+1 937 652 1728",
    "sg:postcode":"43078",
    "sg:province":"OH",
    "sg:tags":[
        "animal",
        "general"
    ],
    "wof:name":"Cable Acres Farm",
    "wof:placetype":"venue"
},
  "geometry": {"coordinates":[-83.668285,40.164689],"type":"Point"}
}