{
  "type": "Feature",
  "properties": {
    "iso:country":"US",
    "sg:address":"8550 Berk Blvd",
    "sg:city":"Hamilton",
    "sg:classifiers":[
        {
            "category":"Wholesale",
            "subcategory":"Office Equipment",
            "type":"Manufacturing & Wholesale Goods"
        }
    ],
    "sg:phone":"+1 513 874 8844",
    "sg:postcode":"45015",
    "sg:province":"OH",
    "wof:name":"Advanced Fastener Corp",
    "wof:placetype":"venue"
},
  "geometry": {"coordinates":[-84.512378,39.343883],"type":"Point"}
}