{
  "type": "Feature",
  "properties": {
    "addr:full":"3431 Cleveland Ave Columbus OH 43224",
    "addr:housenumber":"3431",
    "addr:postcode":"43224",
    "addr:street":"Cleveland Ave",
    "iso:country":"US",
    "sg:address":"3431 Cleveland Ave",
    "sg:city":"Columbus",
    "sg:classifiers":[
        {
            "category":"Health Services",
            "subcategory":"Clinic",
            "type":"Services"
        }
    ],
    "sg:phone":"+1 614 263 3769",
    "sg:postcode":"43224",
    "sg:province":"OH",
    "wof:name":"Health Assistance",
    "wof:placetype":"venue"
},
  "geometry": {"coordinates":[-82.963183,40.035948],"type":"Point"}
}