{
  "type": "Feature",
  "properties": {
    "addr:full": "9981 Co Rd F Hamler OH 43524",
    "addr:housenumber": "9981",
    "addr:postcode": "43524",
    "addr:street": "Co Rd",
    "iso:country": "US",
    "sg:address": "9981 Co Rd F",
    "sg:city": "Hamler",
    "sg:classifiers": [
      {
        "category": "Organizations",
        "subcategory": "Religious Organization",
        "type": "Services"
      }
    ],
    "sg:phone": "+1 419 335 3181",
    "sg:postcode": "43524",
    "sg:province": "OH",
    "sg:tags": [
      "church"
    ],
    "wof:name": "Church Of The Brethren",
    "wof:placetype": "venue"
  },
  "geometry": {"coordinates":[-84.054987,41.239386],"type":"Point"}
}
