{
  "type": "Feature",
  "properties": {
    "iso:country":"US",
    "sg:address":"311 E 13th St",
    "sg:city":"Cincinnati",
    "sg:classifiers":[
        {
            "category":"Building & Trades",
            "subcategory":"Construction",
            "type":"Services"
        }
    ],
    "sg:phone":"+1 513 684 0419",
    "sg:postcode":"45202",
    "sg:province":"OH",
    "sg:tags":[
        "general",
        "contractor"
    ],
    "wof:name":"Speedy Maintenance Svc",
    "wof:placetype":"venue"
},
  "geometry": {"coordinates":[-84.509863,39.110027],"type":"Point"}
}