{
  "type": "Feature",
  "properties": {
    "addr:full": "311 E 13th St Cincinnati OH 45202",
    "addr:housenumber": "311",
    "addr:postcode": "45202",
    "addr:street": "E 13Th St",
    "iso:country": "US",
    "sg:address": "311 E 13th St",
    "sg:city": "Cincinnati",
    "sg:classifiers": [
      {
        "category": "Building \u0026 Trades",
        "subcategory": "Construction",
        "type": "Services"
      }
    ],
    "sg:phone": "+1 513 684 0419",
    "sg:postcode": "45202",
    "sg:province": "OH",
    "sg:tags": [
      "general",
      "contractor"
    ],
    "wof:name": "Speedy Maintenance Svc",
    "wof:placetype": "venue"
  },
  "geometry": {"coordinates":[-84.509863,39.110027],"type":"Point"}
}
