{
  "type": "Feature",
  "properties": {
    "addr:full": "4541 Rosemarie Rd Franklin OH 45005",
    "addr:housenumber": "4541",
    "addr:postcode": "45005",
    "addr:street": "Rosemarie Rd",
    "iso:country": "US",
    "sg:address": "4541 Rosemarie Rd",
    "sg:city": "Franklin",
    "sg:classifiers": [
      {
        "category": "Organizations",
        "subcategory": "Religious Organization",
        "type": "Services"
      }
    ],
    "sg:phone": "+1 937 746 0866",
    "sg:postcode": "45005",
    "sg:province": "OH",
    "sg:tags": [
      "clergy"
    ],
    "wof:name": "Gerald Green",
    "wof:placetype": "venue"
  },
  "geometry": {"coordinates":[-84.289954,39.486275],"type":"Point"}
}
