{
  "type": "Feature",
  "properties": {
    "addr:full":"1268 E Ash St Piqua OH 45356",
    "addr:housenumber":"1268",
    "addr:postcode":"45356",
    "addr:street":"E Ash St",
    "iso:country":"US",
    "sg:address":"1268 E Ash St",
    "sg:city":"Piqua",
    "sg:classifiers":[
        {
            "category":"Professional",
            "subcategory":"Employment Agencies",
            "type":"Services"
        }
    ],
    "sg:phone":"+1 937 778 8445",
    "sg:postcode":"45356",
    "sg:province":"OH",
    "wof:name":"Patrick Staffing Inc",
    "wof:placetype":"venue"
},
  "geometry": {"coordinates":[-84.20903,40.150675],"type":"Point"}
}