{
  "type": "Feature",
  "properties": {
    "addr:full": "227 W Crawford St Findlay OH 45840",
    "addr:housenumber": "227",
    "addr:postcode": "45840",
    "addr:street": "W Crawford St",
    "iso:country": "US",
    "sg:address": "227 W Crawford St",
    "sg:city": "Findlay",
    "sg:classifiers": [
      {
        "category": "Personal",
        "subcategory": "Barber",
        "type": "Services"
      }
    ],
    "sg:phone": "+1 419 423 7177",
    "sg:postcode": "45840",
    "sg:province": "OH",
    "wof:name": "Rustic Razor",
    "wof:placetype": "venue"
  },
  "geometry": {"coordinates":[-83.652341,41.037722],"type":"Point"}
}
