{
  "type": "Feature",
  "properties": {
    "addr:full":"3003 Hospital Dr Batavia OH 45103",
    "addr:housenumber":"3003",
    "addr:postcode":"45103",
    "addr:street":"Hospital Dr",
    "iso:country":"US",
    "sg:address":"3003 Hospital Dr",
    "sg:city":"Batavia",
    "sg:classifiers":[
        {
            "category":"Building & Trades",
            "subcategory":"Construction",
            "type":"Services"
        }
    ],
    "sg:phone":"+1 513 735 0469",
    "sg:postcode":"45103",
    "sg:province":"OH",
    "sg:tags":[
        "general",
        "contractor"
    ],
    "wof:name":"Gordon Construction",
    "wof:placetype":"venue"
},
  "geometry": {"coordinates":[-84.146101,39.078913],"type":"Point"}
}