{
  "type": "Feature",
  "properties": {
    "iso:country":"US",
    "sg:address":"36244 Edwina Rd",
    "sg:city":"Woodsfield",
    "sg:classifiers":[
        {
            "category":"Building & Trades",
            "subcategory":"Plumbing",
            "type":"Services"
        }
    ],
    "sg:phone":"+1 740 567 9304",
    "sg:postcode":"43793",
    "sg:province":"OH",
    "sg:tags":[
        "septic"
    ],
    "wof:name":"Sparky's Septic Svc",
    "wof:placetype":"venue"
},
  "geometry": {"coordinates":[-81.154971,39.707108],"type":"Point"}
}