{
  "type": "Feature",
  "properties": {
    "iso:country":"US",
    "sg:address":"7815 Harvard Ave",
    "sg:city":"Cleveland",
    "sg:classifiers":[
        {
            "category":"Professional",
            "subcategory":"Testing Lab",
            "type":"Services"
        }
    ],
    "sg:phone":"+1 216 641 3290",
    "sg:postcode":"44105",
    "sg:province":"OH",
    "sg:tags":[
        "laboratory",
        "metallurgical"
    ],
    "wof:name":"Tensile Testing",
    "wof:placetype":"venue"
},
  "geometry": {"coordinates":[-81.632695,41.448876],"type":"Point"}
}