{
  "type": "Feature",
  "properties": {
    "addr:full": "12870 Neapolis Waterville Rd Neapolis OH 43571",
    "addr:housenumber": "12870",
    "addr:postcode": "43571",
    "addr:street": "Neapolis Waterville Rd",
    "iso:country": "US",
    "sg:address": "12870 Neapolis Waterville Rd",
    "sg:city": "Neapolis",
    "sg:classifiers": [
      {
        "category": "Farming",
        "subcategory": "Farm \u0026 Veterinary Services",
        "type": "Manufacturing \u0026 Wholesale Goods"
      }
    ],
    "sg:phone": "+1 419 875 5616",
    "sg:postcode": "43571",
    "sg:province": "OH",
    "sg:tags": [
      "breeder",
      "livestock"
    ],
    "wof:name": "Forrest Meadow Llamas",
    "wof:placetype": "venue"
  },
  "geometry": {"coordinates":[-83.8501,41.495345],"type":"Point"}
}
