{
  "type": "Feature",
  "properties": {
    "iso:country":"US",
    "sg:address":"127 Beech St",
    "sg:city":"Wauseon",
    "sg:classifiers":[
        {
            "category":"Wholesale",
            "subcategory":"Electrical",
            "type":"Manufacturing & Wholesale Goods"
        }
    ],
    "sg:phone":"+1 419 335 9010",
    "sg:postcode":"43567",
    "sg:province":"OH",
    "sg:tags":[
        "equipment",
        "electric",
        "supply"
    ],
    "wof:name":"Dyer & Mc Dermott Inc",
    "wof:placetype":"venue"
},
  "geometry": {"coordinates":[-84.138226,41.54856],"type":"Point"}
}