{
  "type": "Feature",
  "properties": {
    "addr:full": "127 Beech St Wauseon OH 43567",
    "addr:housenumber": "127",
    "addr:postcode": "43567",
    "addr:street": "Beech St",
    "iso:country": "US",
    "sg:address": "127 Beech St",
    "sg:city": "Wauseon",
    "sg:classifiers": [
      {
        "category": "Wholesale",
        "subcategory": "Electrical",
        "type": "Manufacturing \u0026 Wholesale Goods"
      }
    ],
    "sg:phone": "+1 419 335 9010",
    "sg:postcode": "43567",
    "sg:province": "OH",
    "sg:tags": [
      "equipment",
      "electric",
      "supply"
    ],
    "wof:name": "Dyer \u0026 Mc Dermott Inc",
    "wof:placetype": "venue"
  },
  "geometry": {"coordinates":[-84.138226,41.54856],"type":"Point"}
}
