{
  "type": "Feature",
  "properties": {
    "iso:country":"US",
    "sg:address":"1974 Wakefield Ave",
    "sg:city":"Youngstown",
    "sg:classifiers":[
        {
            "category":"Building & Trades",
            "subcategory":"Construction",
            "type":"Services"
        }
    ],
    "sg:phone":"+1 330 782 6427",
    "sg:postcode":"44514",
    "sg:province":"OH",
    "sg:tags":[
        "home",
        "improvement"
    ],
    "wof:name":"Comprehensive Carpentry",
    "wof:placetype":"venue"
},
  "geometry": {"coordinates":[-80.621501,41.05578],"type":"Point"}
}