{
  "type": "Feature",
  "properties": {
    "addr:full": "3328 Euclid Ave Cleveland OH 44115",
    "addr:housenumber": "3328",
    "addr:postcode": "44115",
    "addr:street": "Euclid Ave",
    "iso:country": "US",
    "sg:address": "3328 Euclid Ave",
    "sg:city": "Cleveland",
    "sg:classifiers": [
      {
        "category": "Real Estate",
        "subcategory": "Real Estate Operator",
        "type": "Services"
      }
    ],
    "sg:phone": "+1 216 881 2700",
    "sg:postcode": "44115",
    "sg:province": "OH",
    "sg:tags": [
      "owner",
      "apartment"
    ],
    "wof:name": "Stockbridge Apartments",
    "wof:placetype": "venue"
  },
  "geometry": {"coordinates":[-81.66453,41.502749],"type":"Point"}
}
