{
  "type": "Feature",
  "properties": {
    "addr:full":"950 S Main St Celina OH 45822",
    "addr:housenumber":"950",
    "addr:postcode":"45822",
    "addr:street":"S Main St",
    "iso:country":"US",
    "sg:address":"950 S Main St",
    "sg:city":"Celina",
    "sg:classifiers":[
        {
            "category":"Health Services",
            "subcategory":"Doctor",
            "type":"Services"
        }
    ],
    "sg:phone":"+1 419 586 3113",
    "sg:postcode":"45822",
    "sg:province":"OH",
    "sg:tags":[
        "physician",
        "surgeon"
    ],
    "wof:name":"Celina Family Practice",
    "wof:placetype":"venue"
},
  "geometry": {"coordinates":[-84.57387799999999,40.540492],"type":"Point"}
}