{
  "type": "Feature",
  "properties": {
    "addr:full": "272 Benedict Ave Norwalk OH 44857",
    "addr:housenumber": "272",
    "addr:postcode": "44857",
    "addr:street": "Benedict Ave",
    "iso:country": "US",
    "sg:address": "272 Benedict Ave",
    "sg:city": "Norwalk",
    "sg:classifiers": [
      {
        "category": "Restaurant",
        "type": "Food \u0026 Drink"
      }
    ],
    "sg:phone": "+1 419 663 5283",
    "sg:postcode": "44857",
    "sg:province": "OH",
    "sg:tags": [
      "shop",
      "coffee"
    ],
    "wof:name": "Sheri's Coffee House",
    "wof:placetype": "venue"
  },
  "geometry": {"coordinates":[-82.602138,41.2262],"type":"Point"}
}
