{
  "type": "Feature",
  "properties": {
    "addr:full":"536 Prairie Run Dr Sunbury OH 43074",
    "addr:housenumber":"536",
    "addr:postcode":"sunbury;43074",
    "addr:street":"Prairie Run Dr",
    "iso:country":"US",
    "sg:address":"536 Prairie Run Dr",
    "sg:city":"Sunbury",
    "sg:classifiers":[
        {
            "category":"Manufacturing",
            "subcategory":"Musical Instruments",
            "type":"Manufacturing & Wholesale Goods"
        }
    ],
    "sg:phone":"+1 740 965 2094",
    "sg:postcode":"43074",
    "sg:province":"OH",
    "sg:tags":[
        "mfg"
    ],
    "wof:name":"Asoma Instruments",
    "wof:placetype":"venue"
},
  "geometry": {"coordinates":[-82.86421900000001,40.253131],"type":"Point"}
}