{
  "type": "Feature",
  "properties": {
    "addr:full": "2056 McClaren Ln Broadview Heights OH 44147",
    "addr:housenumber": "2056",
    "addr:postcode": "44147",
    "addr:street": "Mcclaren Ln",
    "iso:country": "US",
    "sg:address": "2056 McClaren Ln",
    "sg:city": "Broadview Heights",
    "sg:classifiers": [
      {
        "category": "Building \u0026 Trades",
        "subcategory": "Plumbing",
        "type": "Services"
      }
    ],
    "sg:phone": "+1 440 546 0039",
    "sg:postcode": "44147",
    "sg:province": "OH",
    "sg:tags": [
      "conditioning",
      "air",
      "system",
      "contractor"
    ],
    "wof:name": "Keystone Heating \u0026 Cooling",
    "wof:placetype": "venue"
  },
  "geometry": {"coordinates":[-81.698056,41.281689],"type":"Point"}
}
