{
  "type": "Feature",
  "properties": {
    "iso:country":"US",
    "sg:address":"2056 McClaren Ln",
    "sg:city":"Broadview Heights",
    "sg:classifiers":[
        {
            "category":"Building & Trades",
            "subcategory":"Plumbing",
            "type":"Services"
        }
    ],
    "sg:phone":"+1 440 546 0039",
    "sg:postcode":"44147",
    "sg:province":"OH",
    "sg:tags":[
        "conditioning",
        "air",
        "system",
        "contractor"
    ],
    "wof:name":"Keystone Heating & Cooling",
    "wof:placetype":"venue"
},
  "geometry": {"coordinates":[-81.698056,41.281689],"type":"Point"}
}