{
  "type": "Feature",
  "properties": {
    "iso:country":"US",
    "sg:address":"1374 Som Center Rd",
    "sg:city":"Cleveland",
    "sg:classifiers":[
        {
            "category":"Restaurant",
            "type":"Food & Drink"
        }
    ],
    "sg:phone":"+1 440 461 7718",
    "sg:postcode":"44124",
    "sg:province":"OH",
    "wof:name":"Wendy's",
    "wof:placetype":"venue"
},
  "geometry": {"coordinates":[-81.43876,41.521481],"type":"Point"}
}