{
  "type": "Feature",
  "properties": {
    "addr:full": "1021 W High St Piqua OH 45356",
    "addr:housenumber": "1021",
    "addr:postcode": "45356",
    "addr:street": "W High St",
    "iso:country": "US",
    "sg:address": "1021 W High St",
    "sg:city": "Piqua",
    "sg:classifiers": [
      {
        "category": "Personal",
        "subcategory": "Piercing",
        "type": "Services"
      }
    ],
    "sg:phone": "+1 937 773 0466",
    "sg:postcode": "45356",
    "sg:province": "OH",
    "sg:tags": [
      "body"
    ],
    "wof:name": "Dark Angel Dermagraphics",
    "wof:placetype": "venue"
  },
  "geometry": {"coordinates":[-84.253823,40.148287],"type":"Point"}
}
