{
  "type": "Feature",
  "properties": {
    "iso:country":"US",
    "sg:address":"8056 W Chester Rd",
    "sg:city":"West Chester",
    "sg:classifiers":[
        {
            "category":"Wholesale",
            "subcategory":"Photographic Equipment",
            "type":"Manufacturing & Wholesale Goods"
        }
    ],
    "sg:phone":"+1 513 755 6652",
    "sg:postcode":"45069",
    "sg:province":"OH",
    "sg:tags":[
        "audio"
    ],
    "wof:name":"Electronic Presentations Systs",
    "wof:placetype":"venue"
},
  "geometry": {"coordinates":[-84.360636,39.317776],"type":"Point"}
}