{
  "type": "Feature",
  "properties": {
    "addr:full": "1370 N Fairfield Rd Dayton OH 45432",
    "addr:housenumber": "1370",
    "addr:postcode": "45432",
    "addr:street": "N Fairfield Rd",
    "iso:country": "US",
    "sg:address": "1370 N Fairfield Rd",
    "sg:city": "Dayton",
    "sg:classifiers": [
      {
        "category": "Banks \u0026 Credit Unions",
        "subcategory": "Bank",
        "type": "Services"
      }
    ],
    "sg:phone": "+1 937 458 0067",
    "sg:postcode": "45432",
    "sg:province": "OH",
    "sg:tags": [
      "loan",
      "real estate"
    ],
    "wof:name": "Legacy Mortgage",
    "wof:placetype": "venue"
  },
  "geometry": {"coordinates":[-84.057297,39.728742],"type":"Point"}
}
