{
  "type": "Feature",
  "properties": {
    "iso:country":"US",
    "sg:address":"1370 N Fairfield Rd",
    "sg:city":"Dayton",
    "sg:classifiers":[
        {
            "category":"Banks & Credit Unions",
            "subcategory":"Bank",
            "type":"Services"
        }
    ],
    "sg:phone":"+1 937 458 0067",
    "sg:postcode":"45432",
    "sg:province":"OH",
    "sg:tags":[
        "loan",
        "real estate"
    ],
    "wof:name":"Legacy Mortgage",
    "wof:placetype":"venue"
},
  "geometry": {"coordinates":[-84.05729700000001,39.728742],"type":"Point"}
}