{
  "type": "Feature",
  "properties": {
    "iso:country":"US",
    "sg:address":"109 S Dixie Hwy",
    "sg:city":"Cridersville",
    "sg:classifiers":[
        {
            "category":"Retail",
            "subcategory":"Veterinary Services",
            "type":"Services"
        }
    ],
    "sg:phone":"+1 419 645 5130",
    "sg:postcode":"45806",
    "sg:province":"OH",
    "sg:tags":[
        "hospital",
        "animal"
    ],
    "wof:name":"Baker Animal Hospital",
    "wof:placetype":"venue"
},
  "geometry": {"coordinates":[-84.134092,40.65347],"type":"Point"}
}