{
  "type": "Feature",
  "properties": {
    "addr:full":"83 Bridgeport Way Delaware OH 43015",
    "addr:housenumber":"83",
    "addr:postcode":"43015",
    "addr:street":"Bridgeport Way",
    "iso:country":"US",
    "sg:address":"83 Bridgeport Way",
    "sg:city":"Delaware",
    "sg:classifiers":[
        {
            "category":"Building & Trades",
            "subcategory":"Construction",
            "type":"Services"
        }
    ],
    "sg:phone":"+1 740 369 5421",
    "sg:postcode":"43015",
    "sg:province":"OH",
    "sg:tags":[
        "house"
    ],
    "wof:name":"Bolton S Const",
    "wof:placetype":"venue"
},
  "geometry": {"coordinates":[-83.10072099999999,40.31316],"type":"Point"}
}