{
  "type": "Feature",
  "properties": {
    "addr:full": "1622 Broadway Lorain OH 44052",
    "addr:housenumber": "1622",
    "addr:postcode": "44052",
    "addr:street": "Broadway",
    "iso:country": "US",
    "sg:address": "1622 Broadway",
    "sg:city": "Lorain",
    "sg:classifiers": [
      {
        "category": "Autos \u0026 Motor Vehicles",
        "subcategory": "Boat Sales",
        "type": "Retail Goods"
      }
    ],
    "sg:phone": "+1 440 245 7632",
    "sg:postcode": "44052",
    "sg:province": "OH",
    "wof:name": "Alliance Upholstery",
    "wof:placetype": "venue"
  },
  "geometry": {"coordinates":[-82.167172,41.456618],"type":"Point"}
}
