{
  "type": "Feature",
  "properties": {
    "iso:country":"US",
    "sg:address":"227 E Market St",
    "sg:city":"Alliance",
    "sg:classifiers":[
        {
            "category":"Building & Trades",
            "subcategory":"Construction",
            "type":"Services"
        }
    ],
    "sg:phone":"+1 330 821 0036",
    "sg:postcode":"44601",
    "sg:province":"OH",
    "sg:tags":[
        "carpentry",
        "contractor"
    ],
    "wof:name":"J & J Custom Woods",
    "wof:placetype":"venue"
},
  "geometry": {"coordinates":[-81.101584,40.920867],"type":"Point"}
}