{
  "type": "Feature",
  "properties": {
    "iso:country":"US",
    "sg:address":"576 Magnolia Dr",
    "sg:city":"Painesville",
    "sg:classifiers":[
        {
            "category":"Manufacturing",
            "subcategory":"Printing",
            "type":"Manufacturing & Wholesale Goods"
        }
    ],
    "sg:phone":"+1 440 639 1385",
    "sg:postcode":"44077",
    "sg:province":"OH",
    "sg:tags":[
        "printer"
    ],
    "wof:name":"Kovatch Press",
    "wof:placetype":"venue"
},
  "geometry": {"coordinates":[-81.255397,41.714763],"type":"Point"}
}