{
  "type": "Feature",
  "properties": {
    "addr:full": "576 Magnolia Dr Painesville OH 44077",
    "addr:housenumber": "576",
    "addr:postcode": "44077",
    "addr:street": "Magnolia Dr",
    "iso:country": "US",
    "sg:address": "576 Magnolia Dr",
    "sg:city": "Painesville",
    "sg:classifiers": [
      {
        "category": "Manufacturing",
        "subcategory": "Printing",
        "type": "Manufacturing \u0026 Wholesale Goods"
      }
    ],
    "sg:phone": "+1 440 639 1385",
    "sg:postcode": "44077",
    "sg:province": "OH",
    "sg:tags": [
      "printer"
    ],
    "wof:name": "Kovatch Press",
    "wof:placetype": "venue"
  },
  "geometry": {"coordinates":[-81.255397,41.714763],"type":"Point"}
}
