{
  "type": "Feature",
  "properties": {
    "addr:full": "5805 Monroe St Sylvania OH 43560",
    "addr:housenumber": "5805",
    "addr:postcode": "43560",
    "addr:street": "Monroe St",
    "iso:country": "US",
    "sg:address": "5805 Monroe St",
    "sg:city": "Sylvania",
    "sg:classifiers": [
      {
        "category": "Shopping",
        "subcategory": "Gifts \u0026 Souvenirs",
        "type": "Retail Goods"
      }
    ],
    "sg:phone": "+1 419 885 3472",
    "sg:postcode": "43560",
    "sg:province": "OH",
    "wof:name": "Buckeye \u0026 Wolverine Shop",
    "wof:placetype": "venue"
  },
  "geometry": {"coordinates":[-83.684093,41.713738],"type":"Point"}
}
