{
  "type": "Feature",
  "properties": {
    "addr:full":"1472 N Main St Canton OH 44720",
    "addr:housenumber":"1472",
    "addr:postcode":"44720",
    "addr:street":"N Main St",
    "iso:country":"US",
    "sg:address":"1472 N Main St",
    "sg:city":"Canton",
    "sg:classifiers":[
        {
            "category":"Shopping",
            "subcategory":"Hobbies, Toys, & Games",
            "type":"Retail Goods"
        }
    ],
    "sg:phone":"+1 330 494 5503",
    "sg:postcode":"44720",
    "sg:province":"OH",
    "wof:name":"Treehouse Toys Inc",
    "wof:placetype":"venue"
},
  "geometry": {"coordinates":[-81.406279,40.894778],"type":"Point"}
}