{
  "type": "Feature",
  "properties": {
    "addr:full":"2719 Alpine Trl Huron OH 44839",
    "addr:housenumber":"2719",
    "addr:postcode":"44839",
    "addr:street":"Alpine Trl",
    "iso:country":"US",
    "sg:address":"2719 Alpine Trl",
    "sg:city":"Huron",
    "sg:classifiers":[
        {
            "category":"Real Estate",
            "subcategory":"Real Estate Agent",
            "type":"Services"
        }
    ],
    "sg:phone":"+1 419 433 8909",
    "sg:postcode":"44839",
    "sg:province":"OH",
    "wof:name":"Alpine Trail Rental Homes",
    "wof:placetype":"venue"
},
  "geometry": {"coordinates":[-82.579122,41.343427],"type":"Point"}
}