{
  "type": "Feature",
  "properties": {
    "addr:full":"214 E 2nd St Dover OH 44622",
    "addr:housenumber":"214",
    "addr:postcode":"44622",
    "addr:street":"E 2Nd St",
    "iso:country":"US",
    "sg:address":"214 E 2nd St",
    "sg:city":"Dover",
    "sg:classifiers":[
        {
            "category":"Retail",
            "subcategory":"Auto Repair",
            "type":"Services"
        }
    ],
    "sg:phone":"+1 330 343 7213",
    "sg:postcode":"44622",
    "sg:province":"OH",
    "sg:tags":[
        "repairing",
        "automobile"
    ],
    "wof:name":"Mc Bride's Auto Svc Co",
    "wof:placetype":"venue"
},
  "geometry": {"coordinates":[-81.473428,40.522675],"type":"Point"}
}