{
  "type": "Feature",
  "properties": {
    "iso:country":"US",
    "sg:address":"565 Lawnwood Ct",
    "sg:city":"Circleville",
    "sg:phone":"+1 740 474 6149",
    "sg:postcode":"43113",
    "sg:province":"OH",
    "sg:tags":[
        "farm",
        "wheat"
    ],
    "wof:name":"John & Jean Fissell",
    "wof:placetype":"venue"
},
  "geometry": {"coordinates":[-82.934682,39.610327],"type":"Point"}
}