{
  "type": "Feature",
  "properties": {
    "iso:country":"US",
    "sg:address":"965 Poplar St",
    "sg:city":"Nelsonville",
    "sg:classifiers":[
        {
            "category":"Food & Beverages",
            "subcategory":"Groceries & Convenience Stores",
            "type":"Retail Goods"
        }
    ],
    "sg:phone":"+1 740 753 2362",
    "sg:postcode":"45764",
    "sg:province":"OH",
    "wof:name":"Kroger",
    "wof:placetype":"venue"
},
  "geometry": {"coordinates":[-82.220375,39.451376],"type":"Point"}
}