{
  "type": "Feature",
  "properties": {
    "iso:country":"US",
    "sg:address":"8142 Beechmont Ave",
    "sg:city":"Cincinnati",
    "sg:classifiers":[
        {
            "category":"Restaurant",
            "type":"Food & Drink"
        }
    ],
    "sg:menulink":"http://www.allmenus.com/oh/anderson/69674-donatos-pizza/menu/",
    "sg:phone":"+1 513 474 4600",
    "sg:postcode":"45255",
    "sg:province":"OH",
    "sg:tags":[
        "sandwich",
        "salad",
        "soup",
        "american",
        "wrap",
        "pizza"
    ],
    "wof:name":"Donatos Pizza",
    "wof:placetype":"venue"
},
  "geometry": {"coordinates":[-84.329437,39.073336],"type":"Point"}
}