{
  "type": "Feature",
  "properties": {
    "addr:full": "1825 E 28th St Lorain OH 44055",
    "addr:housenumber": "1825",
    "addr:postcode": "44055",
    "addr:street": "E 28Th St",
    "iso:country": "US",
    "sg:address": "1825 E 28th St",
    "sg:city": "Lorain",
    "sg:classifiers": [
      {
        "category": "Banks \u0026 Credit Unions",
        "subcategory": "Bank",
        "type": "Services"
      }
    ],
    "sg:phone": "+1 440 277 8265",
    "sg:postcode": "44055",
    "sg:province": "OH",
    "sg:website": "www.lormet.com",
    "wof:name": "Lormet Community Federal C/U",
    "wof:placetype": "venue"
  },
  "geometry": {"coordinates":[-82.132923,41.445619],"type":"Point"}
}
