{
  "type": "Feature",
  "properties": {
    "addr:full":"4019 W Dublin Granville Rd Dublin OH 43017",
    "addr:housenumber":"4019",
    "addr:postcode":"43017",
    "addr:street":"W Dublin Granville Rd",
    "iso:country":"US",
    "sg:address":"4019 W Dublin Granville Rd",
    "sg:city":"Dublin",
    "sg:classifiers":[
        {
            "category":"Health Services",
            "subcategory":"Doctor",
            "type":"Services"
        }
    ],
    "sg:phone":"+1 614 293 0080",
    "sg:postcode":"43017",
    "sg:province":"OH",
    "sg:tags":[
        "clinic"
    ],
    "wof:name":"James Care In Dublin",
    "wof:placetype":"venue"
},
  "geometry": {"coordinates":[-83.099075,40.099221],"type":"Point"}
}