{
  "type": "Feature",
  "properties": {
    "addr:full": "1938 Apple Rd St Paris OH 43072",
    "addr:housenumber": "1938",
    "addr:postcode": "43072",
    "addr:street": "Apple Rd St",
    "iso:country": "US",
    "sg:address": "1938 Apple Rd",
    "sg:city": "St Paris",
    "sg:classifiers": [
      {
        "category": "Government",
        "subcategory": "Office",
        "type": "Public Place"
      }
    ],
    "sg:phone": "+1 937 663 4863",
    "sg:postcode": "43072",
    "sg:province": "OH",
    "sg:tags": [
      "village"
    ],
    "wof:name": "Johnson Township Garage",
    "wof:placetype": "venue"
  },
  "geometry": {"coordinates":[-83.981222,40.154303],"type":"Point"}
}
