{
  "type": "Feature",
  "properties": {
    "addr:full": "7103 E Aracoma Dr Cincinnati OH 45237",
    "addr:housenumber": "7103",
    "addr:postcode": "45237",
    "addr:street": "E Aracoma Dr",
    "iso:country": "US",
    "sg:address": "7103 E Aracoma Dr",
    "sg:city": "Cincinnati",
    "sg:classifiers": [
      {
        "category": "Shopping",
        "subcategory": "Clothing, Apparel, \u0026 Fashions",
        "type": "Retail Goods"
      }
    ],
    "sg:phone": "+1 513 531 1876",
    "sg:postcode": "45237",
    "sg:province": "OH",
    "sg:tags": [
      "sport",
      "store"
    ],
    "wof:name": "Bens Department Store",
    "wof:placetype": "venue"
  },
  "geometry": {"coordinates":[-84.434243,39.198856],"type":"Point"}
}
