{
  "type": "Feature",
  "properties": {
    "addr:full":"1259 Carlyon Rd Cleveland OH 44112",
    "addr:housenumber":"1259",
    "addr:postcode":"44112",
    "addr:street":"Carlyon Rd",
    "iso:country":"US",
    "sg:address":"1259 Carlyon Rd",
    "sg:city":"Cleveland",
    "sg:classifiers":[
        {
            "category":"Banks & Credit Unions",
            "subcategory":"Bank",
            "type":"Services"
        }
    ],
    "sg:phone":"+1 216 761 5639",
    "sg:postcode":"44112",
    "sg:province":"OH",
    "sg:tags":[
        "loan",
        "broker"
    ],
    "wof:name":"Tuesdaynotescom",
    "wof:placetype":"venue"
},
  "geometry": {"coordinates":[-81.59692200000001,41.523514],"type":"Point"}
}