{
  "type": "Feature",
  "properties": {
    "addr:full":"410 E Sandusky St Findlay OH 45840",
    "addr:housenumber":"410",
    "addr:postcode":"45840",
    "addr:street":"E Sandusky St",
    "iso:country":"US",
    "sg:address":"410 E Sandusky St",
    "sg:city":"Findlay",
    "sg:classifiers":[
        {
            "category":"Building & Trades",
            "subcategory":"Construction",
            "type":"Services"
        }
    ],
    "sg:phone":"+1 419 424 9445",
    "sg:postcode":"45840",
    "sg:province":"OH",
    "sg:tags":[
        "nonresidential"
    ],
    "sg:website":"www.clearybuilding.com",
    "wof:name":"Cleary Building Corp",
    "wof:placetype":"venue"
},
  "geometry": {"coordinates":[-83.643852,41.037018],"type":"Point"}
}