{
  "type": "Feature",
  "properties": {
    "addr:full": "43022 Six Points Rd Laings OH 43793",
    "addr:housenumber": "43022",
    "addr:postcode": "43793",
    "addr:street": "Six Points Rd",
    "iso:country": "US",
    "sg:address": "43022 Six Points Rd",
    "sg:city": "Laings",
    "sg:classifiers": [
      {
        "category": "Utilities",
        "subcategory": "Water",
        "type": "Services"
      }
    ],
    "sg:phone": "+1 740 472 1030",
    "sg:postcode": "43793",
    "sg:province": "OH",
    "sg:tags": [
      "company",
      "sewage"
    ],
    "wof:name": "Monroe Water System",
    "wof:placetype": "venue"
  },
  "geometry": {"coordinates":[-81.011724,39.716959],"type":"Point"}
}
