{
  "type": "Feature",
  "properties": {
    "addr:full": "209 Lexington Ave Findlay OH 45840",
    "addr:housenumber": "209",
    "addr:postcode": "45840",
    "addr:street": "Lexington Ave",
    "iso:country": "US",
    "sg:address": "209 Lexington Ave",
    "sg:city": "Findlay",
    "sg:classifiers": [
      {
        "category": "Organizations",
        "subcategory": "Religious Organization",
        "type": "Services"
      }
    ],
    "sg:phone": "+1 419 422 8148",
    "sg:postcode": "45840",
    "sg:province": "OH",
    "sg:tags": [
      "church"
    ],
    "wof:name": "Findlay Grace Brethren Church",
    "wof:placetype": "venue"
  },
  "geometry": {"coordinates":[-83.652392,41.067793],"type":"Point"}
}
