{
  "type": "Feature",
  "properties": {
    "iso:country":"US",
    "sg:address":"1220 E Mall Dr",
    "sg:city":"Holland",
    "sg:classifiers":[
        {
            "category":"Home & Garden",
            "subcategory":"Furniture",
            "type":"Retail Goods"
        }
    ],
    "sg:phone":"+1 419 861 2204",
    "sg:postcode":"43528",
    "sg:province":"OH",
    "wof:name":"Denver Mattress Co",
    "wof:placetype":"venue"
},
  "geometry": {"coordinates":[-83.69463399999999,41.618732],"type":"Point"}
}