{
  "type": "Feature",
  "properties": {
    "addr:full": "5225 N Wooster Ave Extended NW Dover OH 44622",
    "addr:housenumber": "5225",
    "addr:postcode": "44622",
    "addr:street": "N Wooster Ave Extended Nw",
    "iso:country": "US",
    "sg:address": "5225 N Wooster Ave Extended NW",
    "sg:city": "Dover",
    "sg:classifiers": [
      {
        "category": "Home \u0026 Garden",
        "subcategory": "Building Materials",
        "type": "Retail Goods"
      }
    ],
    "sg:phone": "+1 330 343 5125",
    "sg:postcode": "44622",
    "sg:province": "OH",
    "sg:tags": [
      "glass",
      "window",
      "plate"
    ],
    "wof:name": "Star Auto Glass",
    "wof:placetype": "venue"
  },
  "geometry": {"coordinates":[-81.497332,40.56155],"type":"Point"}
}
