{
  "type": "Feature",
  "properties": {
    "addr:full": "8484 Mentor Ave Mentor OH 44060",
    "addr:housenumber": "8484",
    "addr:postcode": "44060",
    "addr:street": "Mentor Ave",
    "iso:country": "US",
    "sg:address": "8484 Mentor Ave",
    "sg:city": "Mentor",
    "sg:classifiers": [
      {
        "category": "Restaurant",
        "type": "Food \u0026 Drink"
      }
    ],
    "sg:phone": "+1 440 255 1813",
    "sg:postcode": "44060",
    "sg:province": "OH",
    "sg:tags": [
      "eating"
    ],
    "wof:name": "Safe Crackers Bar N Gr Lmt Prt",
    "wof:placetype": "venue"
  },
  "geometry": {"coordinates":[-81.338329,41.666788],"type":"Point"}
}
