{
  "type": "Feature",
  "properties": {
    "iso:country":"US",
    "sg:address":"8484 Mentor Ave",
    "sg:city":"Mentor",
    "sg:classifiers":[
        {
            "category":"Restaurant",
            "type":"Food & Drink"
        }
    ],
    "sg:phone":"+1 440 255 1813",
    "sg:postcode":"44060",
    "sg:province":"OH",
    "sg:tags":[
        "eating"
    ],
    "wof:name":"Safe Crackers Bar N Gr Lmt Prt",
    "wof:placetype":"venue"
},
  "geometry": {"coordinates":[-81.338329,41.666788],"type":"Point"}
}