{
  "type": "Feature",
  "properties": {
    "addr:full":"300 Commercial Dr Fairfield OH 45014",
    "addr:housenumber":"300",
    "addr:postcode":"45014",
    "addr:street":"Commercial Dr",
    "iso:country":"US",
    "sg:address":"300 Commercial Dr",
    "sg:city":"Fairfield",
    "sg:classifiers":[
        {
            "category":"Professional",
            "subcategory":"Business Services",
            "type":"Services"
        }
    ],
    "sg:phone":"+1 513 942 2000",
    "sg:postcode":"45014",
    "sg:province":"OH",
    "sg:tags":[
        "plant",
        "design",
        "maintenance"
    ],
    "wof:name":"Cincinnati Plant Svc",
    "wof:placetype":"venue"
},
  "geometry": {"coordinates":[-84.484382,39.309951],"type":"Point"}
}