{
  "type": "Feature",
  "properties": {
    "addr:full": "11 S Main St Mechanicsburg OH 43044",
    "addr:housenumber": "11",
    "addr:postcode": "43044",
    "addr:street": "S Main St",
    "iso:country": "US",
    "sg:address": "11 S Main St",
    "sg:city": "Mechanicsburg",
    "sg:classifiers": [
      {
        "category": "Shopping",
        "subcategory": "Florist",
        "type": "Retail Goods"
      }
    ],
    "sg:phone": "+1 937 834 2025",
    "sg:postcode": "43044",
    "sg:province": "OH",
    "wof:name": "Spangler's Flowerland",
    "wof:placetype": "venue"
  },
  "geometry": {"coordinates":[-83.555197,40.071254],"type":"Point"}
}
