{
  "type": "Feature",
  "properties": {
    "addr:full": "2585 State Rte 100 Tiffin OH 44883",
    "addr:housenumber": "2585",
    "addr:postcode": "44883",
    "addr:street": "State Rte 100",
    "iso:country": "US",
    "sg:address": "2585 State Rte 100",
    "sg:city": "Tiffin",
    "sg:classifiers": [
      {
        "category": "Building \u0026 Trades",
        "subcategory": "Plumbing",
        "type": "Services"
      }
    ],
    "sg:phone": "+1 419 447 1035",
    "sg:postcode": "44883",
    "sg:province": "OH",
    "sg:tags": [
      "contractor"
    ],
    "wof:name": "Terry Bogard Bldg Htg AC",
    "wof:placetype": "venue"
  },
  "geometry": {"coordinates":[-83.157541,41.086759],"type":"Point"}
}
