{
  "type": "Feature",
  "properties": {
    "iso:country":"US",
    "sg:address":"2585 State Rte 100",
    "sg:city":"Tiffin",
    "sg:classifiers":[
        {
            "category":"Building & Trades",
            "subcategory":"Plumbing",
            "type":"Services"
        }
    ],
    "sg:phone":"+1 419 447 1035",
    "sg:postcode":"44883",
    "sg:province":"OH",
    "sg:tags":[
        "contractor"
    ],
    "wof:name":"Terry Bogard Bldg Htg AC",
    "wof:placetype":"venue"
},
  "geometry": {"coordinates":[-83.15754099999999,41.086759],"type":"Point"}
}