{
  "type": "Feature",
  "properties": {
    "addr:full":"280 Wakefield Pl Oregon OH 43616",
    "addr:housenumber":"280",
    "addr:postcode":"43616",
    "addr:street":"Wakefield Pl",
    "iso:country":"US",
    "sg:address":"280 Wakefield Pl",
    "sg:city":"Oregon",
    "sg:classifiers":[
        {
            "category":"Arts & Performance",
            "subcategory":"Theater",
            "type":"Entertainment"
        }
    ],
    "sg:phone":"+1 419 691 1398",
    "sg:postcode":"43616",
    "sg:province":"OH",
    "wof:name":"Oregon Community Theatre",
    "wof:placetype":"venue"
},
  "geometry": {"coordinates":[-83.473832,41.646152],"type":"Point"}
}