{
  "type": "Feature",
  "properties": {
    "iso:country":"US",
    "sg:address":"321 Rice St",
    "sg:city":"Elmore",
    "sg:classifiers":[
        {
            "category":"Government",
            "subcategory":"Office",
            "type":"Public Place"
        }
    ],
    "sg:phone":"+1 419 862 3332",
    "sg:postcode":"43416",
    "sg:province":"OH",
    "sg:tags":[
        "executive"
    ],
    "wof:name":"Harris Township Board of",
    "wof:placetype":"venue"
},
  "geometry": {"coordinates":[-83.294813,41.475861],"type":"Point"}
}