{
  "type": "Feature",
  "properties": {
    "addr:full":"230 Shawnee Ln Gallipolis OH 45631",
    "addr:housenumber":"230",
    "addr:postcode":"45631",
    "addr:street":"Shawnee Ln",
    "iso:country":"US",
    "sg:address":"230 Shawnee Ln",
    "sg:city":"Gallipolis",
    "sg:classifiers":[
        {
            "category":"Education",
            "subcategory":"School",
            "type":"Public Place"
        }
    ],
    "sg:phone":"+1 740 446 7917",
    "sg:postcode":"45631",
    "sg:province":"OH",
    "wof:name":"Gallia County School Supt",
    "wof:placetype":"venue"
},
  "geometry": {"coordinates":[-82.23523,38.853885],"type":"Point"}
}