{
  "type": "Feature",
  "properties": {
    "addr:full": "14207 Eldon Dr Mount Vernon OH 43050",
    "addr:housenumber": "14207",
    "addr:postcode": "43050",
    "addr:street": "Eldon Dr",
    "iso:country": "US",
    "sg:address": "14207 Eldon Dr",
    "sg:city": "Mount Vernon",
    "sg:classifiers": [
      {
        "category": "Freight",
        "type": "Transportation"
      }
    ],
    "sg:phone": "+1 740 397 3996",
    "sg:postcode": "43050",
    "sg:province": "OH",
    "sg:tags": [
      "local",
      "without",
      "storage",
      "trucking"
    ],
    "wof:name": "Bud William Price",
    "wof:placetype": "venue"
  },
  "geometry": {"coordinates":[-82.490661,40.437286],"type":"Point"}
}
