{
  "type": "Feature",
  "properties": {
    "addr:full": "270 Regency Ridge Dr Dayton OH 45459",
    "addr:housenumber": "270",
    "addr:postcode": "45459",
    "addr:street": "Regency Ridge Dr",
    "iso:country": "US",
    "sg:address": "270 Regency Ridge Dr",
    "sg:city": "Dayton",
    "sg:classifiers": [
      {
        "category": "Wholesale",
        "subcategory": "Metals \u0026 Minerals",
        "type": "Manufacturing \u0026 Wholesale Goods"
      }
    ],
    "sg:phone": "+1 937 433 7500",
    "sg:postcode": "45459",
    "sg:province": "OH",
    "sg:tags": [
      "wire"
    ],
    "wof:name": "Engineered Wire Products",
    "wof:placetype": "venue"
  },
  "geometry": {"coordinates":[-84.163368,39.641937],"type":"Point"}
}
