{
  "type": "Feature",
  "properties": {
    "iso:country":"US",
    "sg:address":"12900 Superior Ave",
    "sg:city":"Cleveland",
    "sg:classifiers":[
        {
            "category":"Real Estate",
            "subcategory":"Real Estate Operator",
            "type":"Services"
        }
    ],
    "sg:phone":"+1 216 795 9010",
    "sg:postcode":"44112",
    "sg:province":"OH",
    "sg:tags":[
        "building",
        "apartment"
    ],
    "wof:name":"Apthorp Tower",
    "wof:placetype":"venue"
},
  "geometry": {"coordinates":[-81.593506,41.522996],"type":"Point"}
}