{
  "type": "Feature",
  "properties": {
    "addr:full":"251 E 211th St Cleveland OH 44123",
    "addr:housenumber":"251",
    "addr:postcode":"44123",
    "addr:street":"E 211Th St",
    "iso:country":"US",
    "sg:address":"251 E 211th St",
    "sg:city":"Cleveland",
    "sg:classifiers":[
        {
            "category":"Professional",
            "subcategory":"Management & Consulting",
            "type":"Services"
        }
    ],
    "sg:phone":"+1 216 731 2847",
    "sg:postcode":"44123",
    "sg:province":"OH",
    "sg:tags":[
        "consultant",
        "educational"
    ],
    "wof:name":"Principal Support Svc",
    "wof:placetype":"venue"
},
  "geometry": {"coordinates":[-81.532836,41.604136],"type":"Point"}
}