{
  "type": "Feature",
  "properties": {
    "addr:full": "15 Pembrook Dr Springboro OH 45066",
    "addr:housenumber": "15",
    "addr:postcode": "45066",
    "addr:street": "Pembrook Dr",
    "iso:country": "US",
    "sg:address": "15 Pembrook Dr",
    "sg:city": "Springboro",
    "sg:classifiers": [
      {
        "category": "Insurance",
        "subcategory": "Insurance Agent",
        "type": "Services"
      }
    ],
    "sg:phone": "+1 937 223 4236",
    "sg:postcode": "45066",
    "sg:province": "OH",
    "wof:name": "American Premier Insur Group",
    "wof:placetype": "venue"
  },
  "geometry": {"coordinates":[-84.198442,39.575175],"type":"Point"}
}
