{
  "type": "Feature",
  "properties": {
    "iso:country":"US",
    "sg:address":"42 S Main St",
    "sg:city":"Johnstown",
    "sg:classifiers":[
        {
            "category":"Manufacturing",
            "subcategory":"Printing",
            "type":"Manufacturing & Wholesale Goods"
        }
    ],
    "sg:phone":"+1 740 967 5646",
    "sg:postcode":"43031",
    "sg:province":"OH",
    "sg:tags":[
        "commercial"
    ],
    "wof:name":"Digital Impressions",
    "wof:placetype":"venue"
},
  "geometry": {"coordinates":[-82.68416,40.153249],"type":"Point"}
}