{
  "type": "Feature",
  "properties": {
    "addr:full": "121 Fyffe St Urbana OH 43078",
    "addr:housenumber": "121",
    "addr:postcode": "43078",
    "addr:street": "Fyffe St",
    "iso:country": "US",
    "sg:address": "121 Fyffe St",
    "sg:city": "Urbana",
    "sg:classifiers": [
      {
        "category": "Manufacturing",
        "subcategory": "Wood Products",
        "type": "Manufacturing \u0026 Wholesale Goods"
      }
    ],
    "sg:phone": "+1 937 653 7666",
    "sg:postcode": "43078",
    "sg:province": "OH",
    "sg:tags": [
      "mfg"
    ],
    "wof:name": "Carriage House Woodworking",
    "wof:placetype": "venue"
  },
  "geometry": {"coordinates":[-83.752463,40.115828],"type":"Point"}
}
