{
  "type": "Feature",
  "properties": {
    "addr:full":"15170 Middleton Pike Bowling Green OH 43402",
    "addr:housenumber":"15170",
    "addr:postcode":"43402",
    "addr:street":"Middleton Pike",
    "iso:country":"US",
    "sg:address":"15170 Middleton Pike",
    "sg:city":"Bowling Green",
    "sg:classifiers":[
        {
            "category":"Professional",
            "type":"Services"
        }
    ],
    "sg:phone":"+1 419 823 1515",
    "sg:postcode":"43402",
    "sg:province":"OH",
    "wof:name":"James W Archietect",
    "wof:placetype":"venue"
},
  "geometry": {"coordinates":[-83.694568,41.459257],"type":"Point"}
}