{
  "type": "Feature",
  "properties": {
    "iso:country":"US",
    "sg:address":"8 N State St",
    "sg:city":"Painesville",
    "sg:classifiers":[
        {
            "category":"Professional",
            "subcategory":"Lawyer & Legal Services",
            "type":"Services"
        }
    ],
    "sg:phone":"+1 440 354 2212",
    "sg:postcode":"44077",
    "sg:province":"OH",
    "sg:tags":[
        "attorney"
    ],
    "wof:name":"Linda G Silakoski Law Office",
    "wof:placetype":"venue"
},
  "geometry": {"coordinates":[-81.242317,41.727773],"type":"Point"}
}