{
  "type": "Feature",
  "properties": {
    "addr:full":"2205 S Smithville Rd Kettering OH 45420",
    "addr:housenumber":"2205",
    "addr:postcode":"45420",
    "addr:street":"S Smithville Rd",
    "iso:country":"US",
    "sg:address":"2205 S Smithville Rd",
    "sg:city":"Kettering",
    "sg:classifiers":[
        {
            "category":"Home & Garden",
            "subcategory":"Household Appliances",
            "type":"Retail Goods"
        }
    ],
    "sg:phone":"+1 937 252 5000",
    "sg:postcode":"45420",
    "sg:province":"OH",
    "wof:name":"Logan Master Appliance Sales",
    "wof:placetype":"venue"
},
  "geometry": {"coordinates":[-84.140899,39.733969],"type":"Point"}
}