{
  "type": "Feature",
  "properties": {
    "iso:country":"US",
    "sg:address":"4620 Navarre Rd SW",
    "sg:city":"Canton",
    "sg:classifiers":[
        {
            "category":"Retail",
            "subcategory":"Auto Repair",
            "type":"Services"
        }
    ],
    "sg:phone":"+1 330 479 3147",
    "sg:postcode":"44706",
    "sg:province":"OH",
    "sg:tags":[
        "repairing",
        "automobile"
    ],
    "wof:name":"Integrity Auto & Mobility Rpr",
    "wof:placetype":"venue"
},
  "geometry": {"coordinates":[-81.437995,40.770292],"type":"Point"}
}