{
  "type": "Feature",
  "properties": {
    "addr:full": "4620 Navarre Rd SW Canton OH 44706",
    "addr:housenumber": "4620",
    "addr:postcode": "44706",
    "addr:street": "Navarre Rd Sw",
    "iso:country": "US",
    "sg:address": "4620 Navarre Rd SW",
    "sg:city": "Canton",
    "sg:classifiers": [
      {
        "category": "Retail",
        "subcategory": "Auto Repair",
        "type": "Services"
      }
    ],
    "sg:phone": "+1 330 479 3147",
    "sg:postcode": "44706",
    "sg:province": "OH",
    "sg:tags": [
      "repairing",
      "automobile"
    ],
    "wof:name": "Integrity Auto \u0026 Mobility Rpr",
    "wof:placetype": "venue"
  },
  "geometry": {"coordinates":[-81.437995,40.770292],"type":"Point"}
}
