{
  "type": "Feature",
  "properties": {
    "addr:full": "4 W State St  Athens OH 45701",
    "addr:housenumber": "4",
    "addr:postcode": "45701",
    "addr:street": "W State St",
    "iso:country": "US",
    "sg:address": "4 W State St ",
    "sg:city": "Athens",
    "sg:classifiers": [
      {
        "category": "Restaurant",
        "type": "Food \u0026 Drink"
      }
    ],
    "sg:menulink": "http://www.allmenus.com/oh/athens/282258-casa-nueva/menu/",
    "sg:phone": "+1 740 592 2016",
    "sg:postcode": "45701",
    "sg:province": "OH",
    "sg:tags": [
      "mexican"
    ],
    "wof:name": "Casa Nueva",
    "wof:placetype": "venue"
  },
  "geometry": {"coordinates":[-82.101122,39.33057],"type":"Point"}
}
