{
  "type": "Feature",
  "properties": {
    "iso:country":"US",
    "sg:address":"3808 Highlawn Ave SE",
    "sg:city":"Warren",
    "sg:classifiers":[
        {
            "category":"Real Estate",
            "subcategory":"Real Estate Agent",
            "type":"Services"
        }
    ],
    "sg:phone":"+1 330 369 4571",
    "sg:postcode":"44484",
    "sg:province":"OH",
    "wof:name":"Lojo Corp",
    "wof:placetype":"venue"
},
  "geometry": {"coordinates":[-80.778649,41.206111],"type":"Point"}
}