{
  "type": "Feature",
  "properties": {
    "addr:full":"6944 W Snowville Rd Cleveland OH 44141",
    "addr:housenumber":"6944",
    "addr:postcode":"44141",
    "addr:street":"W Snowville Rd",
    "iso:country":"US",
    "sg:address":"6944 W Snowville Rd",
    "sg:city":"Cleveland",
    "sg:classifiers":[
        {
            "category":"Professional",
            "subcategory":"Business Services",
            "type":"Services"
        }
    ],
    "sg:phone":"+1 440 526 1010",
    "sg:postcode":"44141",
    "sg:province":"OH",
    "wof:name":"Gallucci Business Svc",
    "wof:placetype":"venue"
},
  "geometry": {"coordinates":[-81.631891,41.283025],"type":"Point"}
}