{
  "type": "Feature",
  "properties": {
    "addr:full": "800 W Hardin St Findlay OH 45840",
    "addr:housenumber": "800",
    "addr:postcode": "45840",
    "addr:street": "W Hardin St",
    "iso:country": "US",
    "sg:address": "800 W Hardin St",
    "sg:city": "Findlay",
    "sg:classifiers": [
      {
        "category": "Freight",
        "type": "Transportation"
      },
      {
        "category": "Building \u0026 Trades",
        "subcategory": "Construction",
        "type": "Services"
      }
    ],
    "sg:phone": "+1 419 425 4656",
    "sg:postcode": "45840",
    "sg:province": "OH",
    "sg:tags": [
      "heavy",
      "dock"
    ],
    "wof:name": "O'Neill Marine Products",
    "wof:placetype": "venue"
  },
  "geometry": {"coordinates":[-83.661075,41.035726],"type":"Point"}
}
