{
  "type": "Feature",
  "properties": {
    "addr:full":"4729 Logan Arms Dr Youngstown OH 44505",
    "addr:housenumber":"4729",
    "addr:postcode":"44505",
    "addr:street":"Logan Arms Dr",
    "iso:country":"US",
    "sg:address":"4729 Logan Arms Dr",
    "sg:city":"Youngstown",
    "sg:classifiers":[
        {
            "category":"Organizations",
            "subcategory":"Religious Organization",
            "type":"Services"
        }
    ],
    "sg:phone":"+1 330 759 3941",
    "sg:postcode":"44505",
    "sg:province":"OH",
    "sg:tags":[
        "clergy"
    ],
    "wof:name":"Jeffrey Dennis",
    "wof:placetype":"venue"
},
  "geometry": {"coordinates":[-80.65200400000001,41.164737],"type":"Point"}
}