{
  "type": "Feature",
  "properties": {
    "iso:country":"US",
    "sg:address":"327 N Wooster Ave",
    "sg:city":"Dover",
    "sg:classifiers":[
        {
            "category":"Autos & Motor Vehicles",
            "subcategory":"Fuel & Gas Station",
            "type":"Retail Goods"
        }
    ],
    "sg:phone":"+1 330 364 3813",
    "sg:postcode":"44622",
    "sg:province":"OH",
    "sg:tags":[
        "oil"
    ],
    "wof:name":"4 Street Car Wash",
    "wof:placetype":"venue"
},
  "geometry": {"coordinates":[-81.476848,40.522706],"type":"Point"}
}