{
  "type": "Feature",
  "properties": {
    "iso:country":"US",
    "sg:address":"2036 Coon Rd",
    "sg:city":"Copley",
    "sg:classifiers":[
        {
            "category":"Wholesale",
            "subcategory":"Durable Goods & Equipment",
            "type":"Manufacturing & Wholesale Goods"
        }
    ],
    "sg:phone":"+1 330 665 3384",
    "sg:postcode":"44321",
    "sg:province":"OH",
    "sg:tags":[
        "representative",
        "manufacturer"
    ],
    "sg:website":"www.millikencarpet.com",
    "wof:name":"Milliken & Co",
    "wof:placetype":"venue"
},
  "geometry": {"coordinates":[-81.658383,41.071158],"type":"Point"}
}