{
  "type": "Feature",
  "properties": {
    "addr:full": "2036 Coon Rd Copley OH 44321",
    "addr:housenumber": "2036",
    "addr:postcode": "44321",
    "addr:street": "Coon Rd",
    "iso:country": "US",
    "sg:address": "2036 Coon Rd",
    "sg:city": "Copley",
    "sg:classifiers": [
      {
        "category": "Wholesale",
        "subcategory": "Durable Goods \u0026 Equipment",
        "type": "Manufacturing \u0026 Wholesale Goods"
      }
    ],
    "sg:phone": "+1 330 665 3384",
    "sg:postcode": "44321",
    "sg:province": "OH",
    "sg:tags": [
      "representative",
      "manufacturer"
    ],
    "sg:website": "www.millikencarpet.com",
    "wof:name": "Milliken \u0026 Co",
    "wof:placetype": "venue"
  },
  "geometry": {"coordinates":[-81.658383,41.071158],"type":"Point"}
}
