{
  "type": "Feature",
  "properties": {
    "addr:full":"917 Andrews Rd Medina OH 44256",
    "addr:housenumber":"917",
    "addr:postcode":"44256",
    "addr:street":"Andrews Rd",
    "iso:country":"US",
    "sg:address":"917 Andrews Rd",
    "sg:city":"Medina",
    "sg:classifiers":[
        {
            "category":"Autos & Motor Vehicles",
            "subcategory":"Auto Supplies",
            "type":"Retail Goods"
        }
    ],
    "sg:phone":"+1 330 723 1412",
    "sg:postcode":"44256",
    "sg:province":"OH",
    "sg:tags":[
        "tire"
    ],
    "wof:name":"Goodyear Tire & Rubber Co",
    "wof:placetype":"venue"
},
  "geometry": {"coordinates":[-81.843639,41.141193],"type":"Point"}
}