{
  "type": "Feature",
  "properties": {
    "addr:full": "480 S High St Columbus OH 43215",
    "addr:housenumber": "480",
    "addr:postcode": "43215",
    "addr:street": "S High St",
    "iso:country": "US",
    "sg:address": "480 S High St",
    "sg:city": "Columbus",
    "sg:classifiers": [
      {
        "category": "Government",
        "subcategory": "Office",
        "type": "Public Place"
      }
    ],
    "sg:phone": "+1 614 466 5822",
    "sg:postcode": "43215",
    "sg:province": "OH",
    "sg:tags": [
      "management"
    ],
    "sg:website": "www.owda.org",
    "wof:name": "Ohio Water Development Auth",
    "wof:placetype": "venue"
  },
  "geometry": {"coordinates":[-82.998604,39.951685],"type":"Point"}
}
