{
  "type": "Feature",
  "properties": {
    "addr:full":"416 S Wayne St Mendon OH 45862",
    "addr:housenumber":"416",
    "addr:postcode":"45862",
    "addr:street":"S Wayne St",
    "iso:country":"US",
    "sg:address":"416 S Wayne St",
    "sg:city":"Mendon",
    "sg:classifiers":[
        {
            "category":"Organizations",
            "subcategory":"Religious Organization",
            "type":"Services"
        }
    ],
    "sg:phone":"+1 419 795 4405",
    "sg:postcode":"45862",
    "sg:province":"OH",
    "sg:tags":[
        "clergy"
    ],
    "wof:name":"Paul Bunnell",
    "wof:placetype":"venue"
},
  "geometry": {"coordinates":[-84.519847,40.668799],"type":"Point"}
}