{
  "type": "Feature",
  "properties": {
    "iso:country":"US",
    "sg:address":"9458 Rd M",
    "sg:city":"Ottawa",
    "sg:phone":"+1 419 523 0031",
    "sg:postcode":"45875",
    "sg:province":"OH",
    "sg:tags":[
        "farm",
        "soybean"
    ],
    "wof:name":"Bernard Utendorf",
    "wof:placetype":"venue"
},
  "geometry": {"coordinates":[-84.043447,40.9925],"type":"Point"}
}