{
  "type": "Feature",
  "properties": {
    "addr:full":"2213 Demi Dr Twinsburg OH 44087",
    "addr:housenumber":"2213",
    "addr:postcode":"44087",
    "addr:street":"Demi Dr",
    "iso:country":"US",
    "sg:address":"2213 Demi Dr",
    "sg:city":"Twinsburg",
    "sg:classifiers":[
        {
            "category":"Building & Trades",
            "subcategory":"Construction",
            "type":"Services"
        }
    ],
    "sg:phone":"+1 330 963 3740",
    "sg:postcode":"44087",
    "sg:province":"OH",
    "sg:tags":[
        "contractor"
    ],
    "wof:name":"Trees Leaves/Gutters",
    "wof:placetype":"venue"
},
  "geometry": {"coordinates":[-81.445185,41.344995],"type":"Point"}
}