{
  "type": "Feature",
  "properties": {
    "iso:country":"US",
    "sg:address":"200 W Main St",
    "sg:city":"Delta",
    "sg:classifiers":[
        {
            "category":"Building & Trades",
            "subcategory":"Landscaping Services",
            "type":"Services"
        }
    ],
    "sg:phone":"+1 419 822 3369",
    "sg:postcode":"43515",
    "sg:province":"OH",
    "sg:tags":[
        "tree"
    ],
    "wof:name":"New Century Tree & Shrub",
    "wof:placetype":"venue"
},
  "geometry": {"coordinates":[-84.01352900000001,41.57346],"type":"Point"}
}