{
  "type": "Feature",
  "properties": {
    "addr:full": "200 W Main St Delta OH 43515",
    "addr:housenumber": "200",
    "addr:postcode": "43515",
    "addr:street": "W Main St",
    "iso:country": "US",
    "sg:address": "200 W Main St",
    "sg:city": "Delta",
    "sg:classifiers": [
      {
        "category": "Building \u0026 Trades",
        "subcategory": "Landscaping Services",
        "type": "Services"
      }
    ],
    "sg:phone": "+1 419 822 3369",
    "sg:postcode": "43515",
    "sg:province": "OH",
    "sg:tags": [
      "tree"
    ],
    "wof:name": "New Century Tree \u0026 Shrub",
    "wof:placetype": "venue"
  },
  "geometry": {"coordinates":[-84.013529,41.57346],"type":"Point"}
}
