{
  "type": "Feature",
  "properties": {
    "addr:full":"1280 W Alexis Rd Toledo OH 43612",
    "addr:housenumber":"1280",
    "addr:postcode":"43612",
    "addr:street":"W Alexis Rd",
    "iso:country":"US",
    "sg:address":"1280 W Alexis Rd",
    "sg:city":"Toledo",
    "sg:classifiers":[
        {
            "category":"Restaurant",
            "type":"Food & Drink"
        }
    ],
    "sg:menulink":"http://www.allmenus.com/oh/toledo/3154-ginos/menu/",
    "sg:phone":"+1 419 269 4466",
    "sg:postcode":"43612",
    "sg:province":"OH",
    "sg:tags":[
        "american",
        "pizza"
    ],
    "wof:name":"Gino's",
    "wof:placetype":"venue"
},
  "geometry": {"coordinates":[-83.574161,41.721483],"type":"Point"}
}