{
  "type": "Feature",
  "properties": {
    "addr:full": "4746 Hayden Blvd Columbus OH 43221",
    "addr:housenumber": "4746",
    "addr:postcode": "43221",
    "addr:street": "Hayden Blvd",
    "iso:country": "US",
    "sg:address": "4746 Hayden Blvd",
    "sg:city": "Columbus",
    "sg:classifiers": [
      {
        "category": "Professional",
        "type": "Services"
      }
    ],
    "sg:phone": "+1 614 529 8100",
    "sg:postcode": "43221",
    "sg:province": "OH",
    "sg:tags": [
      "establishment"
    ],
    "wof:name": "Pat Ahl Lpc",
    "wof:placetype": "venue"
  },
  "geometry": {"coordinates":[-83.111386,40.06491],"type":"Point"}
}
