{
  "type": "Feature",
  "properties": {
    "iso:country":"US",
    "sg:address":"4614 Prospect Ave",
    "sg:city":"Cleveland",
    "sg:classifiers":[
        {
            "category":"Professional",
            "subcategory":"Management & Consulting",
            "type":"Services"
        }
    ],
    "sg:phone":"+1 216 881 9376",
    "sg:postcode":"44103",
    "sg:province":"OH",
    "sg:tags":[
        "counselor",
        "public",
        "relations"
    ],
    "wof:name":"Gibson Network",
    "wof:placetype":"venue"
},
  "geometry": {"coordinates":[-81.651808,41.502827],"type":"Point"}
}