{
  "type": "Feature",
  "properties": {
    "addr:full": "815 Wilson Ave Youngstown OH 44506",
    "addr:housenumber": "815",
    "addr:postcode": "44506",
    "addr:street": "Wilson Ave",
    "iso:country": "US",
    "sg:address": "815 Wilson Ave",
    "sg:city": "Youngstown",
    "sg:classifiers": [
      {
        "category": "Organizations",
        "subcategory": "Religious Organization",
        "type": "Services"
      }
    ],
    "sg:phone": "+1 330 744 3172",
    "sg:postcode": "44506",
    "sg:province": "OH",
    "sg:tags": [
      "church"
    ],
    "wof:name": "Everlife Worship Ctr",
    "wof:placetype": "venue"
  },
  "geometry": {"coordinates":[-80.634199,41.092601],"type":"Point"}
}
