{
  "type": "Feature",
  "properties": {
    "addr:full":"801 Bellefontaine Ave Lima OH 45801",
    "addr:housenumber":"801",
    "addr:postcode":"45801",
    "addr:street":"Bellefontaine Ave",
    "iso:country":"US",
    "sg:address":"801 Bellefontaine Ave",
    "sg:city":"Lima",
    "sg:classifiers":[
        {
            "category":"Education",
            "subcategory":"School",
            "type":"Public Place"
        }
    ],
    "sg:phone":"+1 419 229 6266",
    "sg:postcode":"45801",
    "sg:province":"OH",
    "sg:tags":[
        "religious"
    ],
    "wof:name":"Liberty Christian School Inc",
    "wof:placetype":"venue"
},
  "geometry": {"coordinates":[-84.091313,40.737915],"type":"Point"}
}