{
  "type": "Feature",
  "properties": {
    "addr:full":"4964 Prairie Rd Bellevue OH 44811",
    "addr:housenumber":"4964",
    "addr:postcode":"44811",
    "addr:street":"Prairie Rd",
    "iso:country":"US",
    "sg:address":"4964 Prairie Rd",
    "sg:city":"Bellevue",
    "sg:classifiers":[
        {
            "category":"Manufacturing",
            "subcategory":"Chemicals & Compounds",
            "type":"Manufacturing & Wholesale Goods"
        }
    ],
    "sg:phone":"+1 419 483 7625",
    "sg:postcode":"44811",
    "sg:province":"OH",
    "sg:tags":[
        "fertilizer",
        "mixing",
        "only"
    ],
    "wof:name":"Royster-Clark Inc",
    "wof:placetype":"venue"
},
  "geometry": {"coordinates":[-82.81334,41.277768],"type":"Point"}
}