{
  "type": "Feature",
  "properties": {
    "addr:full":"2030 Harcourt Estates Dr Cincinnati OH 45244",
    "addr:housenumber":"2030",
    "addr:postcode":"45244",
    "addr:street":"Harcourt Estates Dr",
    "iso:country":"US",
    "sg:address":"2030 Harcourt Estates Dr",
    "sg:city":"Cincinnati",
    "sg:classifiers":[
        {
            "category":"Professional",
            "subcategory":"Management & Consulting",
            "type":"Services"
        }
    ],
    "sg:phone":"+1 513 474 7191",
    "sg:postcode":"45244",
    "sg:province":"OH",
    "sg:tags":[
        "marketing",
        "consultant"
    ],
    "sg:website":"www.omaley.com",
    "wof:name":"John O'Maley & Assoc",
    "wof:placetype":"venue"
},
  "geometry": {"coordinates":[-84.313458,39.090311],"type":"Point"}
}