{
  "type": "Feature",
  "properties": {
    "addr:full": "7232 Thompson Clark Rd Bristolville OH 44402",
    "addr:housenumber": "7232",
    "addr:postcode": "44402",
    "addr:street": "Thompson Clark Rd",
    "iso:country": "US",
    "sg:address": "7232 Thompson Clark Rd",
    "sg:city": "Bristolville",
    "sg:phone": "+1 330 889 2480",
    "sg:postcode": "44402",
    "sg:province": "OH",
    "sg:tags": [
      "farm",
      "corn",
      "soybean"
    ],
    "wof:name": "Wildmans Wallow",
    "wof:placetype": "venue"
  },
  "geometry": {"coordinates":[-80.833605,41.416859],"type":"Point"}
}
