{
  "type": "Feature",
  "properties": {
    "iso:country":"US",
    "sg:address":"1360 S Cleveland Massillon Rd",
    "sg:city":"Akron",
    "sg:classifiers":[
        {
            "category":"Restaurant",
            "type":"Food & Drink"
        }
    ],
    "sg:menulink":"http://www.allmenus.com/oh/copley/134133-subway/menu/",
    "sg:phone":"+1 330 666 8783",
    "sg:postcode":"44321",
    "sg:province":"OH",
    "sg:tags":[
        "american",
        "sandwich"
    ],
    "wof:name":"Subway",
    "wof:placetype":"venue"
},
  "geometry": {"coordinates":[-81.644859,41.101164],"type":"Point"}
}