{
  "type": "Feature",
  "properties": {
    "iso:country":"US",
    "sg:address":"16630 State Rte 103",
    "sg:city":"Mt Blanchard",
    "sg:classifiers":[
        {
            "category":"Food & Beverages",
            "subcategory":"Meat & Fish",
            "type":"Retail Goods"
        },
        {
            "category":"Farming",
            "subcategory":"Farm & Veterinary Services",
            "type":"Manufacturing & Wholesale Goods"
        }
    ],
    "sg:phone":"+1 419 694 8575",
    "sg:postcode":"45867",
    "sg:province":"OH",
    "sg:tags":[
        "extract",
        "custom",
        "livestock",
        "slaughtering",
        "mfg"
    ],
    "wof:name":"Kimmel's Mountain Man Meats",
    "wof:placetype":"venue"
},
  "geometry": {"coordinates":[-83.564131,40.891166],"type":"Point"}
}