{
  "type": "Feature",
  "properties": {
    "addr:full": "16630 State Rte 103 Mt Blanchard OH 45867",
    "addr:housenumber": "16630",
    "addr:postcode": "45867",
    "addr:street": "State Rte 103",
    "iso:country": "US",
    "sg:address": "16630 State Rte 103",
    "sg:city": "Mt Blanchard",
    "sg:classifiers": [
      {
        "category": "Food \u0026 Beverages",
        "subcategory": "Meat \u0026 Fish",
        "type": "Retail Goods"
      },
      {
        "category": "Farming",
        "subcategory": "Farm \u0026 Veterinary Services",
        "type": "Manufacturing \u0026 Wholesale Goods"
      }
    ],
    "sg:phone": "+1 419 694 8575",
    "sg:postcode": "45867",
    "sg:province": "OH",
    "sg:tags": [
      "extract",
      "custom",
      "livestock",
      "slaughtering",
      "mfg"
    ],
    "wof:name": "Kimmel's Mountain Man Meats",
    "wof:placetype": "venue"
  },
  "geometry": {"coordinates":[-83.564131,40.891166],"type":"Point"}
}
