{
  "type": "Feature",
  "properties": {
    "iso:country":"US",
    "sg:address":"1510 Germantown Rd",
    "sg:city":"Middletown",
    "sg:classifiers":[
        {
            "category":"Food & Beverages",
            "subcategory":"Groceries & Convenience Stores",
            "type":"Retail Goods"
        }
    ],
    "sg:phone":"+1 513 422 0710",
    "sg:postcode":"45042",
    "sg:province":"OH",
    "sg:tags":[
        "grocer"
    ],
    "wof:name":"Davey's Super Carry-Out",
    "wof:placetype":"venue"
},
  "geometry": {"coordinates":[-84.383636,39.528864],"type":"Point"}
}