{
  "type": "Feature",
  "properties": {
    "iso:country":"US",
    "sg:address":"783 Catawba Ave",
    "sg:city":"Put In Bay",
    "sg:classifiers":[
        {
            "category":"Shopping",
            "type":"Retail Goods"
        }
    ],
    "sg:phone":"+1 419 285 8313",
    "sg:postcode":"43456",
    "sg:province":"OH",
    "sg:tags":[
        "ice"
    ],
    "wof:name":"Island Ice Co",
    "wof:placetype":"venue"
},
  "geometry": {"coordinates":[-82.824032,41.649235],"type":"Point"}
}