{
  "type": "Feature",
  "properties": {
    "addr:full": "900 Superior Ave E Cleveland OH 44114",
    "addr:housenumber": "900",
    "addr:postcode": "44114",
    "addr:street": "Superior Ave E",
    "iso:country": "US",
    "sg:address": "900 Superior Ave E",
    "sg:city": "Cleveland",
    "sg:classifiers": [
      {
        "category": "Professional",
        "subcategory": "Lawyer \u0026 Legal Services",
        "type": "Services"
      }
    ],
    "sg:phone": "+1 440 331 1313",
    "sg:postcode": "44114",
    "sg:province": "OH",
    "sg:tags": [
      "attorney"
    ],
    "wof:name": "Theodore A Gullia Jr",
    "wof:placetype": "venue"
  },
  "geometry": {"coordinates":[-81.686152,41.50345],"type":"Point"}
}
