{
  "type": "Feature",
  "properties": {
    "iso:country":"US",
    "sg:address":"900 Superior Ave E",
    "sg:city":"Cleveland",
    "sg:classifiers":[
        {
            "category":"Professional",
            "subcategory":"Lawyer & Legal Services",
            "type":"Services"
        }
    ],
    "sg:phone":"+1 440 331 1313",
    "sg:postcode":"44114",
    "sg:province":"OH",
    "sg:tags":[
        "attorney"
    ],
    "wof:name":"Theodore A Gullia Jr",
    "wof:placetype":"venue"
},
  "geometry": {"coordinates":[-81.68615200000001,41.50345],"type":"Point"}
}