{
  "type": "Feature",
  "properties": {
    "iso:country":"US",
    "sg:address":"1251 Essex Ave",
    "sg:city":"Columbus",
    "sg:classifiers":[
        {
            "category":"Wholesale",
            "subcategory":"Machinery & Supplies",
            "type":"Manufacturing & Wholesale Goods"
        }
    ],
    "sg:phone":"+1 614 294 5501",
    "sg:postcode":"43201",
    "sg:province":"OH",
    "sg:tags":[
        "industrial",
        "equipment",
        "material",
        "handling"
    ],
    "wof:name":"R E Condit Co Inc",
    "wof:placetype":"venue"
},
  "geometry": {"coordinates":[-82.9877,39.989721],"type":"Point"}
}