{
  "type": "Feature",
  "properties": {
    "iso:country":"US",
    "sg:address":"3718 Cook Rd",
    "sg:city":"Medina",
    "sg:classifiers":[
        {
            "category":"Health Services",
            "subcategory":"Clinic",
            "type":"Services"
        }
    ],
    "sg:phone":"+1 330 725 1298",
    "sg:postcode":"44256",
    "sg:province":"OH",
    "sg:tags":[
        "home",
        "care"
    ],
    "wof:name":"Peace Foundation",
    "wof:placetype":"venue"
},
  "geometry": {"coordinates":[-81.80404799999999,41.171617],"type":"Point"}
}