{
  "type": "Feature",
  "properties": {
    "iso:country":"US",
    "sg:address":"4345 E Balliette Dr",
    "sg:city":"Port Clinton",
    "sg:classifiers":[
        {
            "category":"Shopping",
            "subcategory":"Jewelry",
            "type":"Retail Goods"
        }
    ],
    "sg:phone":"+1 419 797 6821",
    "sg:postcode":"43452",
    "sg:province":"OH",
    "sg:tags":[
        "jeweler"
    ],
    "wof:name":"Jostens Inc",
    "wof:placetype":"venue"
},
  "geometry": {"coordinates":[-82.851737,41.577595],"type":"Point"}
}