{
  "type": "Feature",
  "properties": {
    "addr:full":"4688 Gerland Cir Rootstown OH 44272",
    "addr:housenumber":"4688",
    "addr:postcode":"44272",
    "addr:street":"Gerland Cir",
    "iso:country":"US",
    "sg:address":"4688 Gerland Cir",
    "sg:city":"Rootstown",
    "sg:classifiers":[
        {
            "category":"Shopping",
            "subcategory":"Used Merchandise",
            "type":"Retail Goods"
        }
    ],
    "sg:phone":"+1 330 325 8734",
    "sg:postcode":"44272",
    "sg:province":"OH",
    "sg:tags":[
        "sell",
        "antique",
        "buy"
    ],
    "wof:name":"Eagle Baskets",
    "wof:placetype":"venue"
},
  "geometry": {"coordinates":[-81.221842,41.11593],"type":"Point"}
}