{
  "type": "Feature",
  "properties": {
    "addr:full":"1081 State Rte 28 Milford OH 45150",
    "addr:housenumber":"1081",
    "addr:postcode":"45150",
    "addr:street":"State Rte 28",
    "iso:country":"US",
    "sg:address":"1081 State Rte 28",
    "sg:city":"Milford",
    "sg:classifiers":[
        {
            "category":"Manufacturing",
            "subcategory":"Printing",
            "type":"Manufacturing & Wholesale Goods"
        }
    ],
    "sg:phone":"+1 513 677 5254",
    "sg:postcode":"45150",
    "sg:province":"OH",
    "sg:tags":[
        "publishing"
    ],
    "wof:name":"Chilidog Press",
    "wof:placetype":"venue"
},
  "geometry": {"coordinates":[-84.237522,39.194097],"type":"Point"}
}