{
  "type": "Feature",
  "properties": {
    "addr:full":"5177 N Bend Rd Cincinnati OH 45211",
    "addr:housenumber":"5177",
    "addr:postcode":"45211",
    "addr:street":"N Bend Rd",
    "iso:country":"US",
    "sg:address":"5177 N Bend Rd",
    "sg:city":"Cincinnati",
    "sg:classifiers":[
        {
            "category":"Health Services",
            "subcategory":"Doctor",
            "type":"Services"
        }
    ],
    "sg:phone":"+1 513 662 3111",
    "sg:postcode":"45211",
    "sg:province":"OH",
    "sg:tags":[
        "physician",
        "surgeon"
    ],
    "wof:name":"Monfort Hts Ped & Adlt Med",
    "wof:placetype":"venue"
},
  "geometry": {"coordinates":[-84.604107,39.179355],"type":"Point"}
}