{
  "type": "Feature",
  "properties": {
    "addr:full":"107 South St Chardon OH 44024",
    "addr:housenumber":"107",
    "addr:postcode":"44024",
    "addr:street":"South St",
    "iso:country":"US",
    "sg:address":"107 South St",
    "sg:city":"Chardon",
    "sg:classifiers":[
        {
            "category":"Organizations",
            "subcategory":"Non-profit Organization",
            "type":"Services"
        }
    ],
    "sg:phone":"+1 440 286 8115",
    "sg:postcode":"44024",
    "sg:province":"OH",
    "sg:tags":[
        "social"
    ],
    "wof:name":"Leadership Geauga",
    "wof:placetype":"venue"
},
  "geometry": {"coordinates":[-81.20338599999999,41.579727],"type":"Point"}
}