{
  "type": "Feature",
  "properties": {
    "addr:full": "526 S Chillicothe Rd Aurora OH 44202",
    "addr:housenumber": "526",
    "addr:postcode": "44202",
    "addr:street": "S Chillicothe Rd",
    "iso:country": "US",
    "sg:address": "526 S Chillicothe Rd",
    "sg:city": "Aurora",
    "sg:classifiers": [
      {
        "category": "Wholesale",
        "subcategory": "Farm Supplies",
        "type": "Manufacturing \u0026 Wholesale Goods"
      }
    ],
    "sg:phone": "+1 330 562 4646",
    "sg:postcode": "44202",
    "sg:province": "OH",
    "wof:name": "Thr Mantua Grain \u0026 Supply",
    "wof:placetype": "venue"
  },
  "geometry": {"coordinates":[-81.34568,41.300715],"type":"Point"}
}
