{
  "type": "Feature",
  "properties": {
    "addr:full": "26241 Detroit Rd Cleveland OH 44145",
    "addr:housenumber": "26241",
    "addr:postcode": "44145",
    "addr:street": "Detroit Rd",
    "iso:country": "US",
    "sg:address": "26241 Detroit Rd",
    "sg:city": "Cleveland",
    "sg:classifiers": [
      {
        "category": "Shopping",
        "type": "Retail Goods"
      }
    ],
    "sg:phone": "+1 440 871 5683",
    "sg:postcode": "44145",
    "sg:province": "OH",
    "sg:tags": [
      "art",
      "gallery",
      "dealer"
    ],
    "wof:name": "Love Photography \u0026 Custom Frmg",
    "wof:placetype": "venue"
  },
  "geometry": {"coordinates":[-81.909602,41.469135],"type":"Point"}
}
