{
  "type": "Feature",
  "properties": {
    "addr:full": "78 W Main St New Concord OH 43762",
    "addr:housenumber": "78",
    "addr:postcode": "43762",
    "addr:street": "W Main St",
    "iso:country": "US",
    "sg:address": "78 W Main St",
    "sg:city": "New Concord",
    "sg:classifiers": [
      {
        "category": "Health Services",
        "subcategory": "Doctor",
        "type": "Services"
      }
    ],
    "sg:phone": "+1 740 826 7657",
    "sg:postcode": "43762",
    "sg:province": "OH",
    "sg:tags": [
      "medical"
    ],
    "wof:name": "Richard G Day",
    "wof:placetype": "venue"
  },
  "geometry": {"coordinates":[-81.737614,39.993432],"type":"Point"}
}
