{
  "type": "Feature",
  "properties": {
    "iso:country":"US",
    "sg:address":"4625 Far Hills Ave",
    "sg:city":"Dayton",
    "sg:classifiers":[
        {
            "category":"Professional",
            "subcategory":"Lawyer & Legal Services",
            "type":"Services"
        }
    ],
    "sg:phone":"+1 937 432 9300",
    "sg:postcode":"45429",
    "sg:province":"OH",
    "sg:tags":[
        "attorney"
    ],
    "wof:name":"Melinda Wilson & Assoc",
    "wof:placetype":"venue"
},
  "geometry": {"coordinates":[-84.166618,39.680844],"type":"Point"}
}