{
  "type": "Feature",
  "properties": {
    "iso:country":"US",
    "sg:address":"5380 Monroe St",
    "sg:city":"Toledo",
    "sg:classifiers":[
        {
            "category":"Banks & Credit Unions",
            "subcategory":"Bank",
            "type":"Services"
        }
    ],
    "sg:phone":"+1 419 885 3984",
    "sg:postcode":"43623",
    "sg:province":"OH",
    "sg:tags":[
        "financing"
    ],
    "wof:name":"Wells Fargo Financial Accptnce",
    "wof:placetype":"venue"
},
  "geometry": {"coordinates":[-83.660134,41.704545],"type":"Point"}
}