{
  "type": "Feature",
  "properties": {
    "addr:full":"201 Melbourne Dr Brunswick OH 44212",
    "addr:housenumber":"201",
    "addr:postcode":"44212",
    "addr:street":"Melbourne Dr",
    "iso:country":"US",
    "sg:address":"201 Melbourne Dr",
    "sg:city":"Brunswick",
    "sg:classifiers":[
        {
            "category":"Building & Trades",
            "subcategory":"Construction",
            "type":"Services"
        }
    ],
    "sg:phone":"+1 330 225 8401",
    "sg:postcode":"44212",
    "sg:province":"OH",
    "sg:tags":[
        "house"
    ],
    "wof:name":"Royalcrest Builders Inc",
    "wof:placetype":"venue"
},
  "geometry": {"coordinates":[-81.818421,41.27017],"type":"Point"}
}