{
  "type": "Feature",
  "properties": {
    "addr:full": "216 South St Caledonia OH 43314",
    "addr:housenumber": "216",
    "addr:postcode": "43314",
    "addr:street": "South St",
    "iso:country": "US",
    "sg:address": "216 South St",
    "sg:city": "Caledonia",
    "sg:classifiers": [
      {
        "category": "Building \u0026 Trades",
        "subcategory": "Plumbing",
        "type": "Services"
      }
    ],
    "sg:phone": "+1 419 845 3549",
    "sg:postcode": "43314",
    "sg:province": "OH",
    "sg:tags": [
      "septic"
    ],
    "wof:name": "Hanes Environmental",
    "wof:placetype": "venue"
  },
  "geometry": {"coordinates":[-82.970631,40.635571],"type":"Point"}
}
