{
  "type": "Feature",
  "properties": {
    "iso:country":"US",
    "sg:address":"7778 Reynolds Rd",
    "sg:city":"Mentor",
    "sg:classifiers":[
        {
            "category":"Professional",
            "subcategory":"Accounting & Tax Preparation",
            "type":"Services"
        }
    ],
    "sg:phone":"+1 440 946 0400",
    "sg:postcode":"44060",
    "sg:province":"OH",
    "sg:tags":[
        "accountant"
    ],
    "wof:name":"Mc Intosh & Co",
    "wof:placetype":"venue"
},
  "geometry": {"coordinates":[-81.37764300000001,41.658186],"type":"Point"}
}