{
  "type": "Feature",
  "properties": {
    "addr:full": "7778 Reynolds Rd Mentor OH 44060",
    "addr:housenumber": "7778",
    "addr:postcode": "44060",
    "addr:street": "Reynolds Rd",
    "iso:country": "US",
    "sg:address": "7778 Reynolds Rd",
    "sg:city": "Mentor",
    "sg:classifiers": [
      {
        "category": "Professional",
        "subcategory": "Accounting \u0026 Tax Preparation",
        "type": "Services"
      }
    ],
    "sg:phone": "+1 440 946 0400",
    "sg:postcode": "44060",
    "sg:province": "OH",
    "sg:tags": [
      "accountant"
    ],
    "wof:name": "Mc Intosh \u0026 Co",
    "wof:placetype": "venue"
  },
  "geometry": {"coordinates":[-81.377643,41.658186],"type":"Point"}
}
