{
  "type": "Feature",
  "properties": {
    "addr:full":"2938 Lagrange St Toledo OH 43608",
    "addr:housenumber":"2938",
    "addr:postcode":"43608",
    "addr:street":"Lagrange St",
    "iso:country":"US",
    "sg:address":"2938 Lagrange St",
    "sg:city":"Toledo",
    "sg:classifiers":[
        {
            "category":"Professional",
            "subcategory":"Accounting & Tax Preparation",
            "type":"Services"
        }
    ],
    "sg:phone":"+1 419 729 3001",
    "sg:postcode":"43608",
    "sg:province":"OH",
    "sg:tags":[
        "return"
    ],
    "wof:name":"H & R Block",
    "wof:placetype":"venue"
},
  "geometry": {"coordinates":[-83.54017899999999,41.678166],"type":"Point"}
}