{
  "type": "Feature",
  "properties": {
    "addr:full":"6576 N State Rte 66 Defiance OH 43512",
    "addr:housenumber":"6576",
    "addr:postcode":"43512",
    "addr:street":"N State Rte 66",
    "iso:country":"US",
    "sg:address":"6576 N State Rte 66",
    "sg:city":"Defiance",
    "sg:phone":"+1 419 784 2104",
    "sg:postcode":"43512",
    "sg:province":"OH",
    "sg:tags":[
        "farm",
        "corn",
        "grain",
        "cash"
    ],
    "wof:name":"Russell Cramer",
    "wof:placetype":"venue"
},
  "geometry": {"coordinates":[-84.360899,41.347452],"type":"Point"}
}