{
  "type": "Feature",
  "properties": {
    "addr:full":"11888 Pleasant Valley Rd Chillicothe OH 45601",
    "addr:housenumber":"11888",
    "addr:postcode":"45601",
    "addr:street":"Pleasant Valley Rd",
    "iso:country":"US",
    "sg:address":"11888 Pleasant Valley Rd",
    "sg:city":"Chillicothe",
    "sg:classifiers":[
        {
            "category":"Building & Trades",
            "subcategory":"Construction",
            "type":"Services"
        }
    ],
    "sg:phone":"+1 740 773 4729",
    "sg:postcode":"45601",
    "sg:province":"OH",
    "sg:tags":[
        "concrete",
        "contractor"
    ],
    "wof:name":"Smith Concrete Construction",
    "wof:placetype":"venue"
},
  "geometry": {"coordinates":[-83.05449400000001,39.373096],"type":"Point"}
}