{
  "type": "Feature",
  "properties": {
    "addr:full":"6920 Plainfield Rd Cincinnati OH 45236",
    "addr:housenumber":"6920",
    "addr:postcode":"45236",
    "addr:street":"Plainfield Rd",
    "iso:country":"US",
    "sg:address":"6920 Plainfield Rd",
    "sg:city":"Cincinnati",
    "sg:classifiers":[
        {
            "category":"Real Estate",
            "subcategory":"Architect",
            "type":"Services"
        }
    ],
    "sg:phone":"+1 513 793 9055",
    "sg:postcode":"45236",
    "sg:province":"OH",
    "wof:name":"Dellinger Architects",
    "wof:placetype":"venue"
},
  "geometry": {"coordinates":[-84.400306,39.195418],"type":"Point"}
}