{
  "type": "Feature",
  "properties": {
    "addr:full": "2345 Millville Ave Hamilton IN 45013",
    "addr:housenumber": "2345",
    "addr:postcode": "45013",
    "addr:street": "Millville Ave",
    "iso:country": "US",
    "sg:address": "2345 Millville Ave",
    "sg:city": "Hamilton",
    "sg:classifiers": [
      {
        "category": "Wholesale",
        "subcategory": "Stationery",
        "type": "Manufacturing \u0026 Wholesale Goods"
      }
    ],
    "sg:phone": "+1 513 737 8444",
    "sg:postcode": "45013",
    "sg:province": "IN",
    "sg:tags": [
      "packaging",
      "material"
    ],
    "wof:name": "Packing Supplies Direct Inc",
    "wof:placetype": "venue"
  },
  "geometry": {"coordinates":[-84.636661,39.398458],"type":"Point"}
}
