{
  "type": "Feature",
  "properties": {
    "iso:country":"US",
    "sg:address":"2345 Millville Ave",
    "sg:city":"Hamilton",
    "sg:classifiers":[
        {
            "category":"Wholesale",
            "subcategory":"Stationery",
            "type":"Manufacturing & Wholesale Goods"
        }
    ],
    "sg:phone":"+1 513 737 8444",
    "sg:postcode":"45013",
    "sg:province":"IN",
    "sg:tags":[
        "packaging",
        "material"
    ],
    "wof:name":"Packing Supplies Direct Inc",
    "wof:placetype":"venue"
},
  "geometry": {"coordinates":[-84.636661,39.398458],"type":"Point"}
}