{
  "type": "Feature",
  "properties": {
    "addr:full":"13462 York Rd Cleveland OH 44133",
    "addr:housenumber":"13462",
    "addr:postcode":"44133",
    "addr:street":"York Rd",
    "iso:country":"US",
    "sg:address":"13462 York Rd",
    "sg:city":"Cleveland",
    "sg:classifiers":[
        {
            "category":"Farming",
            "subcategory":"Farm",
            "type":"Manufacturing & Wholesale Goods"
        },
        {
            "category":"Farming",
            "subcategory":"Nursery",
            "type":"Manufacturing & Wholesale Goods"
        }
    ],
    "sg:phone":"+1 440 237 7595",
    "sg:postcode":"44133",
    "sg:province":"OH",
    "sg:tags":[
        "food",
        "covered",
        "greenhouse",
        "crop"
    ],
    "wof:name":"L Ross Florists & Greenhouses",
    "wof:placetype":"venue"
},
  "geometry": {"coordinates":[-81.755591,41.313208],"type":"Point"}
}