{
  "type": "Feature",
  "properties": {
    "iso:country":"US",
    "sg:address":"7292 W Chester Rd",
    "sg:city":"West Chester",
    "sg:classifiers":[
        {
            "category":"Building & Trades",
            "subcategory":"Construction",
            "type":"Services"
        }
    ],
    "sg:phone":"+1 513 759 0184",
    "sg:postcode":"45069",
    "sg:province":"OH",
    "sg:tags":[
        "concrete",
        "contractor"
    ],
    "wof:name":"Ln Concrete Specialist",
    "wof:placetype":"venue"
},
  "geometry": {"coordinates":[-84.38511699999999,39.321165],"type":"Point"}
}