{
  "type": "Feature",
  "properties": {
    "addr:full": "7292 W Chester Rd West Chester OH 45069",
    "addr:housenumber": "7292",
    "addr:postcode": "45069",
    "addr:street": "W Chester Rd",
    "iso:country": "US",
    "sg:address": "7292 W Chester Rd",
    "sg:city": "West Chester",
    "sg:classifiers": [
      {
        "category": "Building \u0026 Trades",
        "subcategory": "Construction",
        "type": "Services"
      }
    ],
    "sg:phone": "+1 513 759 0184",
    "sg:postcode": "45069",
    "sg:province": "OH",
    "sg:tags": [
      "concrete",
      "contractor"
    ],
    "wof:name": "Ln Concrete Specialist",
    "wof:placetype": "venue"
  },
  "geometry": {"coordinates":[-84.385117,39.321165],"type":"Point"}
}
