{
  "type": "Feature",
  "properties": {
    "addr:full": "1135 Warren St Sandusky OH 44870",
    "addr:housenumber": "1135",
    "addr:postcode": "44870",
    "addr:street": "Warren St",
    "iso:country": "US",
    "sg:address": "1135 Warren St",
    "sg:city": "Sandusky",
    "sg:classifiers": [
      {
        "category": "Organizations",
        "subcategory": "Religious Organization",
        "type": "Services"
      }
    ],
    "sg:phone": "+1 419 626 8730",
    "sg:postcode": "44870",
    "sg:province": "OH",
    "sg:tags": [
      "church"
    ],
    "sg:website": "www.sanduskycma.org",
    "wof:name": "Sandusky Alliance Church",
    "wof:placetype": "venue"
  },
  "geometry": {"coordinates":[-82.69967,41.448327],"type":"Point"}
}
