{
  "type": "Feature",
  "properties": {
    "addr:full": "9074 Ohio River Rd Wheelersburg OH 45694",
    "addr:housenumber": "9074",
    "addr:postcode": "45694",
    "addr:street": "Ohio River Rd",
    "iso:country": "US",
    "sg:address": "9074 Ohio River Rd",
    "sg:city": "Wheelersburg",
    "sg:classifiers": [
      {
        "category": "Insurance",
        "subcategory": "Insurance Agent",
        "type": "Services"
      }
    ],
    "sg:phone": "+1 740 574 2155",
    "sg:postcode": "45694",
    "sg:province": "OH",
    "wof:name": "Monumental Life",
    "wof:placetype": "venue"
  },
  "geometry": {"coordinates":[-82.85645,38.714022],"type":"Point"}
}
