{
  "type": "Feature",
  "properties": {
    "addr:full":"1922 6th St SW Akron OH 44314",
    "addr:housenumber":"1922",
    "addr:postcode":"44314",
    "addr:street":"6Th St Sw",
    "iso:country":"US",
    "sg:address":"1922 6th St SW",
    "sg:city":"Akron",
    "sg:classifiers":[
        {
            "category":"Building & Trades",
            "subcategory":"Construction",
            "type":"Services"
        }
    ],
    "sg:phone":"+1 330 753 0165",
    "sg:postcode":"44314",
    "sg:province":"OH",
    "sg:tags":[
        "house"
    ],
    "wof:name":"G & S Construction",
    "wof:placetype":"venue"
},
  "geometry": {"coordinates":[-81.551626,41.05321],"type":"Point"}
}