{
  "type": "Feature",
  "properties": {
    "addr:full":"8212 Lois Dr Cincinnati OH 45241",
    "addr:housenumber":"8212",
    "addr:postcode":"45241",
    "addr:street":"Lois Dr",
    "iso:country":"US",
    "sg:address":"8212 Lois Dr",
    "sg:city":"Cincinnati",
    "sg:classifiers":[
        {
            "category":"Wholesale",
            "subcategory":"Machinery & Supplies",
            "type":"Manufacturing & Wholesale Goods"
        }
    ],
    "sg:phone":"+1 513 777 2600",
    "sg:postcode":"45241",
    "sg:province":"OH",
    "sg:tags":[
        "packaging"
    ],
    "wof:name":"Automated Packaging Systems",
    "wof:placetype":"venue"
},
  "geometry": {"coordinates":[-84.360995,39.301162],"type":"Point"}
}