{
  "type": "Feature",
  "properties": {
    "addr:full": "29370 Lake Logan Rd Logan OH 43138",
    "addr:housenumber": "29370",
    "addr:postcode": "43138",
    "addr:street": "Lake Logan Rd",
    "iso:country": "US",
    "sg:address": "29370 Lake Logan Rd",
    "sg:city": "Logan",
    "sg:classifiers": [
      {
        "category": "Shopping",
        "subcategory": "Pharmacy",
        "type": "Retail Goods"
      }
    ],
    "sg:phone": "+1 740 385 5969",
    "sg:postcode": "43138",
    "sg:province": "OH",
    "sg:tags": [
      "mfg"
    ],
    "wof:name": "Jerry Carper",
    "wof:placetype": "venue"
  },
  "geometry": {"coordinates":[-82.47562,39.549179],"type":"Point"}
}
