{
  "type": "Feature",
  "properties": {
    "iso:country":"US",
    "sg:address":"855 E Franklin St",
    "sg:city":"Dayton",
    "sg:classifiers":[
        {
            "category":"Professional",
            "subcategory":"Business Services",
            "type":"Services"
        }
    ],
    "sg:phone":"+1 937 436 1419",
    "sg:postcode":"45459",
    "sg:province":"OH",
    "sg:tags":[
        "printing",
        "commercial",
        "g"
    ],
    "wof:name":"Creative Cutups",
    "wof:placetype":"venue"
},
  "geometry": {"coordinates":[-84.141295,39.628496],"type":"Point"}
}