{
  "type": "Feature",
  "properties": {
    "iso:country":"US",
    "sg:address":"17830 Englewood Dr",
    "sg:city":"Cleveland",
    "sg:classifiers":[
        {
            "category":"Freight",
            "type":"Transportation"
        }
    ],
    "sg:phone":"+1 440 260 0957",
    "sg:postcode":"44130",
    "sg:province":"OH",
    "sg:tags":[
        "hauling",
        "trucking"
    ],
    "wof:name":"ACDC Logistics Inc",
    "wof:placetype":"venue"
},
  "geometry": {"coordinates":[-81.824926,41.381149],"type":"Point"}
}