{
  "type": "Feature",
  "properties": {
    "addr:full": "1623 Harmony Ln SW North Canton OH 44709",
    "addr:housenumber": "1623",
    "addr:postcode": "44709",
    "addr:street": "Harmony Ln Sw North",
    "iso:country": "US",
    "sg:address": "1623 Harmony Ln SW",
    "sg:city": "North Canton",
    "sg:classifiers": [
      {
        "category": "Professional",
        "subcategory": "Testing Lab",
        "type": "Services"
      }
    ],
    "sg:phone": "+1 330 305 9229",
    "sg:postcode": "44709",
    "sg:province": "OH",
    "sg:tags": [
      "correction",
      "radon"
    ],
    "wof:name": "Detective Homes Radon LTD",
    "wof:placetype": "venue"
  },
  "geometry": {"coordinates":[-81.402955,40.854546],"type":"Point"}
}
