{
  "type": "Feature",
  "properties": {
    "addr:full": "7533 Easy St Mason OH 45040",
    "addr:housenumber": "7533",
    "addr:postcode": "45040",
    "addr:street": "Easy St",
    "iso:country": "US",
    "sg:address": "7533 Easy St",
    "sg:city": "Mason",
    "sg:classifiers": [
      {
        "category": "Health Services",
        "subcategory": "Doctor",
        "type": "Services"
      }
    ],
    "sg:phone": "+1 513 573 9625",
    "sg:postcode": "45040",
    "sg:province": "OH",
    "sg:tags": [
      "testing"
    ],
    "wof:name": "Accu Med Systems of Cincinnati",
    "wof:placetype": "venue"
  },
  "geometry": {"coordinates":[-84.339209,39.328378],"type":"Point"}
}
