{
  "type": "Feature",
  "properties": {
    "addr:full":"9150 S Hills Blvd Cleveland OH 44147",
    "addr:housenumber":"9150",
    "addr:postcode":"44147",
    "addr:street":"S Hills Blvd",
    "iso:country":"US",
    "sg:address":"9150 S Hills Blvd",
    "sg:city":"Cleveland",
    "sg:classifiers":[
        {
            "category":"Professional",
            "subcategory":"Lawyer & Legal Services",
            "type":"Services"
        }
    ],
    "sg:phone":"+1 440 838 8800",
    "sg:postcode":"44147",
    "sg:province":"OH",
    "sg:tags":[
        "attorney"
    ],
    "sg:website":"www.millisor.com",
    "wof:name":"Millisor & Nobil",
    "wof:placetype":"venue"
},
  "geometry": {"coordinates":[-81.64452900000001,41.317399],"type":"Point"}
}