{
  "type": "Feature",
  "properties": {
    "iso:country":"US",
    "sg:address":"280 E Broad St",
    "sg:city":"Columbus",
    "sg:classifiers":[
        {
            "category":"Social Services",
            "subcategory":"Adult Care",
            "type":"Services"
        }
    ],
    "sg:phone":"+1 614 462 6200",
    "sg:postcode":"43215",
    "sg:province":"OH",
    "sg:tags":[
        "residential"
    ],
    "wof:name":"Options For Elders",
    "wof:placetype":"venue"
},
  "geometry": {"coordinates":[-82.993346,39.963108],"type":"Point"}
}