{
  "type": "Feature",
  "properties": {
    "addr:full": "280 E Broad St Columbus OH 43215",
    "addr:housenumber": "280",
    "addr:postcode": "43215",
    "addr:street": "E Broad St",
    "iso:country": "US",
    "sg:address": "280 E Broad St",
    "sg:city": "Columbus",
    "sg:classifiers": [
      {
        "category": "Social Services",
        "subcategory": "Adult Care",
        "type": "Services"
      }
    ],
    "sg:phone": "+1 614 462 6200",
    "sg:postcode": "43215",
    "sg:province": "OH",
    "sg:tags": [
      "residential"
    ],
    "wof:name": "Options For Elders",
    "wof:placetype": "venue"
  },
  "geometry": {"coordinates":[-82.993346,39.963108],"type":"Point"}
}
