{
  "type": "Feature",
  "properties": {
    "iso:country":"US",
    "sg:address":"2527 US Hwy 68 N",
    "sg:city":"Bellefontaine",
    "sg:classifiers":[
        {
            "category":"Sports & Exercise",
            "subcategory":"Gym",
            "type":"Entertainment"
        }
    ],
    "sg:phone":"+1 937 592 9222",
    "sg:postcode":"43311",
    "sg:province":"OH",
    "sg:tags":[
        "club",
        "health",
        "studio",
        "gymnasium"
    ],
    "wof:name":"Curves",
    "wof:placetype":"venue"
},
  "geometry": {"coordinates":[-83.761386,40.330867],"type":"Point"}
}