{
  "type": "Feature",
  "properties": {
    "iso:country":"US",
    "sg:address":"2951 Sidney Ave",
    "sg:city":"Cincinnati",
    "sg:classifiers":[
        {
            "category":"Social Services",
            "type":"Services"
        }
    ],
    "sg:phone":"+1 513 542 1637",
    "sg:postcode":"45225",
    "sg:province":"OH",
    "sg:tags":[
        "organization",
        "welfare"
    ],
    "wof:name":"Camp Washington Neighborhood",
    "wof:placetype":"venue"
},
  "geometry": {"coordinates":[-84.535664,39.137409],"type":"Point"}
}