{
  "type": "Feature",
  "properties": {
    "iso:country":"US",
    "sg:address":"160 W Main St",
    "sg:city":"Hillsboro",
    "sg:classifiers":[
        {
            "category":"Wholesale",
            "subcategory":"Hardware",
            "type":"Manufacturing & Wholesale Goods"
        },
        {
            "category":"Wholesale",
            "subcategory":"Durable Goods & Equipment",
            "type":"Manufacturing & Wholesale Goods"
        }
    ],
    "sg:phone":"+1 937 393 9276",
    "sg:postcode":"45133",
    "sg:province":"OH",
    "sg:tags":[
        "heating"
    ],
    "wof:name":"Throck Supply Co LLC",
    "wof:placetype":"venue"
},
  "geometry": {"coordinates":[-83.612957,39.202477],"type":"Point"}
}