{
  "type": "Feature",
  "properties": {
    "addr:full": "160 W Main St Hillsboro OH 45133",
    "addr:housenumber": "160",
    "addr:postcode": "45133",
    "addr:street": "W Main St",
    "iso:country": "US",
    "sg:address": "160 W Main St",
    "sg:city": "Hillsboro",
    "sg:classifiers": [
      {
        "category": "Wholesale",
        "subcategory": "Hardware",
        "type": "Manufacturing \u0026 Wholesale Goods"
      },
      {
        "category": "Wholesale",
        "subcategory": "Durable Goods \u0026 Equipment",
        "type": "Manufacturing \u0026 Wholesale Goods"
      }
    ],
    "sg:phone": "+1 937 393 9276",
    "sg:postcode": "45133",
    "sg:province": "OH",
    "sg:tags": [
      "heating"
    ],
    "wof:name": "Throck Supply Co LLC",
    "wof:placetype": "venue"
  },
  "geometry": {"coordinates":[-83.612957,39.202477],"type":"Point"}
}
