{
  "type": "Feature",
  "properties": {
    "iso:country":"US",
    "sg:address":"116 N 7th St",
    "sg:city":"Zanesville",
    "sg:classifiers":[
        {
            "category":"Organizations",
            "subcategory":"Religious Organization",
            "type":"Services"
        }
    ],
    "sg:phone":"+1 740 452 7569",
    "sg:postcode":"43701",
    "sg:province":"OH",
    "sg:tags":[
        "lutheran",
        "church"
    ],
    "wof:name":"St John's Lutheran Church",
    "wof:placetype":"venue"
},
  "geometry": {"coordinates":[-82.003742,39.942253],"type":"Point"}
}