{
  "type": "Feature",
  "properties": {
    "iso:country":"US",
    "sg:address":"616 Harrisburg Pike",
    "sg:city":"Columbus",
    "sg:classifiers":[
        {
            "category":"Restaurant",
            "type":"Food & Drink"
        }
    ],
    "sg:phone":"+1 614 228 4044",
    "sg:postcode":"43223",
    "sg:province":"OH",
    "sg:tags":[
        "eating"
    ],
    "wof:name":"Little Caesars",
    "wof:placetype":"venue"
},
  "geometry": {"coordinates":[-83.03691000000001,39.944205],"type":"Point"}
}