{
  "type": "Feature",
  "properties": {
    "addr:full":"38160 Western Pkwy Willoughby OH 44094",
    "addr:housenumber":"38160",
    "addr:postcode":"44094",
    "addr:street":"Western Pkwy",
    "iso:country":"US",
    "sg:address":"38160 Western Pkwy",
    "sg:city":"Willoughby",
    "sg:classifiers":[
        {
            "category":"Manufacturing",
            "subcategory":"Tools & Machinery",
            "type":"Manufacturing & Wholesale Goods"
        }
    ],
    "sg:phone":"+1 440 918 9040",
    "sg:postcode":"44094",
    "sg:province":"OH",
    "sg:tags":[
        "chiller"
    ],
    "wof:name":"Northeastern Cabinetry",
    "wof:placetype":"venue"
},
  "geometry": {"coordinates":[-81.40163,41.680986],"type":"Point"}
}