{
  "type": "Feature",
  "properties": {
    "addr:full": "12271 Barrs St SW Massillon OH 44647",
    "addr:housenumber": "12271",
    "addr:postcode": "44647",
    "addr:street": "Barrs St Sw",
    "iso:country": "US",
    "sg:address": "12271 Barrs St SW",
    "sg:city": "Massillon",
    "sg:classifiers": [
      {
        "category": "Building \u0026 Trades",
        "subcategory": "Construction",
        "type": "Services"
      }
    ],
    "sg:phone": "+1 330 837 2008",
    "sg:postcode": "44647",
    "sg:province": "OH",
    "sg:tags": [
      "excavating",
      "contractor"
    ],
    "wof:name": "Burkett Trucking \u0026 Excavating",
    "wof:placetype": "venue"
  },
  "geometry": {"coordinates":[-81.58721,40.764297],"type":"Point"}
}
