{
  "type": "Feature",
  "properties": {
    "addr:full": "1102 Columbus Ave Sandusky OH 44870",
    "addr:housenumber": "1102",
    "addr:postcode": "44870",
    "addr:street": "Columbus Ave",
    "iso:country": "US",
    "sg:address": "1102 Columbus Ave",
    "sg:city": "Sandusky",
    "sg:classifiers": [
      {
        "category": "Insurance",
        "subcategory": "Hazard Insurance",
        "type": "Services"
      }
    ],
    "sg:phone": "+1 419 660 1200",
    "sg:postcode": "44870",
    "sg:province": "OH",
    "sg:tags": [
      "fidelity",
      "bond"
    ],
    "wof:name": "Mayo Bail Bond \u0026 Surety",
    "wof:placetype": "venue"
  },
  "geometry": {"coordinates":[-82.706046,41.44663],"type":"Point"}
}
