{
  "type": "Feature",
  "properties": {
    "addr:full": "5581 Tayside Cir Dublin OH 43016",
    "addr:housenumber": "5581",
    "addr:postcode": "43016",
    "addr:street": "Tayside Cir",
    "iso:country": "US",
    "sg:address": "5581 Tayside Cir",
    "sg:city": "Dublin",
    "sg:classifiers": [
      {
        "category": "Shopping",
        "subcategory": "Computers \u0026 Home Electronics",
        "type": "Retail Goods"
      }
    ],
    "sg:phone": "+1 614 459 4493",
    "sg:postcode": "43016",
    "sg:province": "OH",
    "wof:name": "Tel America Corp",
    "wof:placetype": "venue"
  },
  "geometry": {"coordinates":[-83.167287,40.07939],"type":"Point"}
}
