{
  "type": "Feature",
  "properties": {
    "iso:country":"US",
    "sg:address":"5581 Tayside Cir",
    "sg:city":"Dublin",
    "sg:classifiers":[
        {
            "category":"Shopping",
            "subcategory":"Computers & Home Electronics",
            "type":"Retail Goods"
        }
    ],
    "sg:phone":"+1 614 459 4493",
    "sg:postcode":"43016",
    "sg:province":"OH",
    "wof:name":"Tel America Corp",
    "wof:placetype":"venue"
},
  "geometry": {"coordinates":[-83.167287,40.07939],"type":"Point"}
}