{
  "type": "Feature",
  "properties": {
    "iso:country":"US",
    "sg:address":"1253 Lower Elkton Rd",
    "sg:city":"Columbiana",
    "sg:classifiers":[
        {
            "category":"Shopping",
            "type":"Retail Goods"
        }
    ],
    "sg:phone":"+1 330 482 3888",
    "sg:postcode":"44408",
    "sg:province":"OH",
    "sg:tags":[
        "chemical"
    ],
    "wof:name":"Eagle Enterprises",
    "wof:placetype":"venue"
},
  "geometry": {"coordinates":[-80.707834,40.878942],"type":"Point"}
}