{
  "type": "Feature",
  "properties": {
    "addr:full": "7081 Darcie Dr Hamilton OH 45011",
    "addr:housenumber": "7081",
    "addr:postcode": "45011",
    "addr:street": "Darcie Dr",
    "iso:country": "US",
    "sg:address": "7081 Darcie Dr",
    "sg:city": "Hamilton",
    "sg:classifiers": [
      {
        "category": "Shopping",
        "subcategory": "Gifts \u0026 Souvenirs",
        "type": "Retail Goods"
      }
    ],
    "sg:phone": "+1 513 477 2903",
    "sg:postcode": "45011",
    "sg:province": "OH",
    "wof:name": "Key Baskets LLC",
    "wof:placetype": "venue"
  },
  "geometry": {"coordinates":[-84.443381,39.378133],"type":"Point"}
}
