{
  "type": "Feature",
  "properties": {
    "addr:full": "37381 Davis Chapel Rd Logan OH 43138",
    "addr:housenumber": "37381",
    "addr:postcode": "43138",
    "addr:street": "Davis Chapel Rd",
    "iso:country": "US",
    "sg:address": "37381 Davis Chapel Rd",
    "sg:city": "Logan",
    "sg:classifiers": [
      {
        "category": "Real Estate",
        "subcategory": "Surveying",
        "type": "Services"
      }
    ],
    "sg:phone": "+1 740 380 3884",
    "sg:postcode": "43138",
    "sg:province": "OH",
    "sg:tags": [
      "surveyor"
    ],
    "wof:name": "SVE Surveying",
    "wof:placetype": "venue"
  },
  "geometry": {"coordinates":[-82.322636,39.52254],"type":"Point"}
}
