{
  "type": "Feature",
  "properties": {
    "addr:full":"4733 Cornell Rd Cincinnati OH 45241",
    "addr:housenumber":"4733",
    "addr:postcode":"45241",
    "addr:street":"Cornell Rd",
    "iso:country":"US",
    "sg:address":"4733 Cornell Rd",
    "sg:city":"Cincinnati",
    "sg:classifiers":[
        {
            "category":"Professional",
            "subcategory":"Engineering",
            "type":"Services"
        }
    ],
    "sg:phone":"+1 513 530 5595",
    "sg:postcode":"45241",
    "sg:province":"OH",
    "sg:tags":[
        "consulting",
        "engineer"
    ],
    "wof:name":"Integrated Engineering Svcs",
    "wof:placetype":"venue"
},
  "geometry": {"coordinates":[-84.377984,39.270485],"type":"Point"}
}