{
  "type": "Feature",
  "properties": {
    "iso:country":"US",
    "sg:address":"229 W Perkins Ave",
    "sg:city":"Sandusky",
    "sg:classifiers":[
        {
            "category":"Food & Beverages",
            "subcategory":"Groceries & Convenience Stores",
            "type":"Retail Goods"
        }
    ],
    "sg:phone":"+1 419 000 1111",
    "sg:postcode":"44870",
    "sg:province":"OH",
    "sg:tags":[
        "grocer"
    ],
    "wof:name":"Aldi",
    "wof:placetype":"venue"
},
  "geometry": {"coordinates":[-82.700799,41.432928],"type":"Point"}
}