{
  "type": "Feature",
  "properties": {
    "addr:full": "229 W Perkins Ave Sandusky OH 44870",
    "addr:housenumber": "229",
    "addr:postcode": "44870",
    "addr:street": "W Perkins Ave",
    "iso:country": "US",
    "sg:address": "229 W Perkins Ave",
    "sg:city": "Sandusky",
    "sg:classifiers": [
      {
        "category": "Food \u0026 Beverages",
        "subcategory": "Groceries \u0026 Convenience Stores",
        "type": "Retail Goods"
      }
    ],
    "sg:phone": "+1 419 000 1111",
    "sg:postcode": "44870",
    "sg:province": "OH",
    "sg:tags": [
      "grocer"
    ],
    "wof:name": "Aldi",
    "wof:placetype": "venue"
  },
  "geometry": {"coordinates":[-82.700799,41.432928],"type":"Point"}
}
