{
  "type": "Feature",
  "properties": {
    "iso:country":"US",
    "sg:address":"2047 S Rockhill Ave",
    "sg:city":"Alliance",
    "sg:classifiers":[
        {
            "category":"Health Services",
            "subcategory":"Doctor",
            "type":"Services"
        }
    ],
    "sg:phone":"+1 330 821 9336",
    "sg:postcode":"44601",
    "sg:province":"OH",
    "sg:tags":[
        "dentist"
    ],
    "wof:name":"Warren B Brocklehurst Inc",
    "wof:placetype":"venue"
},
  "geometry": {"coordinates":[-81.11590200000001,40.900085],"type":"Point"}
}