{
  "type": "Feature",
  "properties": {
    "addr:full": "344 Cramer Creek Ct Dublin OH 43017",
    "addr:housenumber": "344",
    "addr:postcode": "43017",
    "addr:street": "Cramer Creek Ct",
    "iso:country": "US",
    "sg:address": "344 Cramer Creek Ct",
    "sg:city": "Dublin",
    "sg:classifiers": [
      {
        "category": "Professional",
        "subcategory": "Computer Services",
        "type": "Services"
      }
    ],
    "sg:phone": "+1 614 761 8394",
    "sg:postcode": "43017",
    "sg:province": "OH",
    "sg:tags": [
      "related"
    ],
    "wof:name": "3sg Corporation",
    "wof:placetype": "venue"
  },
  "geometry": {"coordinates":[-83.120939,40.083878],"type":"Point"}
}
