{
  "type": "Feature",
  "properties": {
    "iso:country":"US",
    "sg:address":"545 Odlin Ave",
    "sg:city":"Dayton",
    "sg:classifiers":[
        {
            "category":"Professional",
            "subcategory":"Management & Consulting",
            "type":"Services"
        }
    ],
    "sg:phone":"+1 937 277 4257",
    "sg:postcode":"45405",
    "sg:province":"OH",
    "sg:tags":[
        "consultant",
        "educational"
    ],
    "wof:name":"READS Inc",
    "wof:placetype":"venue"
},
  "geometry": {"coordinates":[-84.219671,39.797654],"type":"Point"}
}