{
  "type": "Feature",
  "properties": {
    "addr:full":"27600 Chagrin Blvd Cleveland OH 44122",
    "addr:housenumber":"27600",
    "addr:postcode":"44122",
    "addr:street":"Chagrin Blvd",
    "iso:country":"US",
    "sg:address":"27600 Chagrin Blvd",
    "sg:city":"Cleveland",
    "sg:classifiers":[
        {
            "category":"Professional",
            "subcategory":"Management & Consulting",
            "type":"Services"
        }
    ],
    "sg:phone":"+1 216 595 1283",
    "sg:postcode":"44122",
    "sg:province":"OH",
    "sg:tags":[
        "consultant",
        "business"
    ],
    "wof:name":"A Z Management",
    "wof:placetype":"venue"
},
  "geometry": {"coordinates":[-81.48431600000001,41.462259],"type":"Point"}
}