{
  "type": "Feature",
  "properties": {
    "iso:country":"US",
    "sg:address":"107 N High St",
    "sg:city":"Columbus Grove",
    "sg:classifiers":[
        {
            "category":"Insurance",
            "subcategory":"Insurance Agent",
            "type":"Services"
        }
    ],
    "sg:phone":"+1 419 659 2703",
    "sg:postcode":"45830",
    "sg:province":"OH",
    "wof:name":"Mason Philip Insur Investments",
    "wof:placetype":"venue"
},
  "geometry": {"coordinates":[-84.057028,40.91975],"type":"Point"}
}