{
  "type": "Feature",
  "properties": {
    "iso:country":"US",
    "sg:address":"30 W Park Pl",
    "sg:city":"Oxford",
    "sg:classifiers":[
        {
            "category":"Organizations",
            "subcategory":"Professional Association",
            "type":"Services"
        }
    ],
    "sg:phone":"+1 513 523 8687",
    "sg:postcode":"45056",
    "sg:province":"OH",
    "sg:tags":[
        "chambers",
        "commerce"
    ],
    "sg:website":"www.enjoyoxford.org",
    "wof:name":"Oxford Visitor's Bureau Inc",
    "wof:placetype":"venue"
},
  "geometry": {"coordinates":[-84.742744,39.511048],"type":"Point"}
}