{
  "type": "Feature",
  "properties": {
    "iso:country":"US",
    "sg:address":"175 9th St SW",
    "sg:city":"Strasburg",
    "sg:classifiers":[
        {
            "category":"Wholesale",
            "subcategory":"Machinery & Supplies",
            "type":"Manufacturing & Wholesale Goods"
        }
    ],
    "sg:phone":"+1 330 878 5121",
    "sg:postcode":"44680",
    "sg:province":"OH",
    "sg:tags":[
        "equipment",
        "transportation"
    ],
    "wof:name":"Dunkirk Railroad Service",
    "wof:placetype":"venue"
},
  "geometry": {"coordinates":[-81.527393,40.587671],"type":"Point"}
}