{
  "type": "Feature",
  "properties": {
    "iso:country":"US",
    "sg:address":"426 E Perry St",
    "sg:city":"Port Clinton",
    "sg:classifiers":[
        {
            "category":"Travel",
            "subcategory":"Hotels & Motels",
            "type":"Entertainment"
        }
    ],
    "sg:phone":"+1 419 734 2064",
    "sg:postcode":"43452",
    "sg:province":"OH",
    "sg:tags":[
        "breakfast",
        "accommodation",
        "bed"
    ],
    "wof:name":"Bay Haven Inn Bed Breakfast",
    "wof:placetype":"venue"
},
  "geometry": {"coordinates":[-82.935283,41.51354],"type":"Point"}
}