{
  "type": "Feature",
  "properties": {
    "addr:full": "35835 Vine St Willowick OH 44095",
    "addr:housenumber": "35835",
    "addr:postcode": "44095",
    "addr:street": "Vine St",
    "iso:country": "US",
    "sg:address": "35835 Vine St",
    "sg:city": "Willowick",
    "sg:classifiers": [
      {
        "category": "Real Estate",
        "subcategory": "Real Estate Agent",
        "type": "Services"
      }
    ],
    "sg:phone": "+1 440 942 2870",
    "sg:postcode": "44095",
    "sg:province": "OH",
    "sg:tags": [
      "management"
    ],
    "wof:name": "Condo Management Co Of America",
    "wof:placetype": "venue"
  },
  "geometry": {"coordinates":[-81.43277,41.64264],"type":"Point"}
}
