{
  "type": "Feature",
  "properties": {
    "addr:full": "754 1st St NE Massillon OH 44646",
    "addr:housenumber": "754",
    "addr:postcode": "44646",
    "addr:street": "1St St Ne",
    "iso:country": "US",
    "sg:address": "754 1st St NE",
    "sg:city": "Massillon",
    "sg:classifiers": [
      {
        "category": "Retail",
        "subcategory": "Auto Repair",
        "type": "Services"
      }
    ],
    "sg:phone": "+1 330 837 2049",
    "sg:postcode": "44646",
    "sg:province": "OH",
    "sg:tags": [
      "exchanging",
      "engine"
    ],
    "wof:name": "Story Motors",
    "wof:placetype": "venue"
  },
  "geometry": {"coordinates":[-81.523485,40.804347],"type":"Point"}
}
