{
  "type": "Feature",
  "properties": {
    "iso:country":"US",
    "sg:address":"2327 E High St",
    "sg:city":"Springfield",
    "sg:classifiers":[
        {
            "category":"Organizations",
            "subcategory":"Religious Organization",
            "type":"Services"
        }
    ],
    "sg:phone":"+1 937 323 5474",
    "sg:postcode":"45505",
    "sg:province":"OH",
    "wof:name":"Oakland Presbyterian Church",
    "wof:placetype":"venue"
},
  "geometry": {"coordinates":[-83.774935,39.921541],"type":"Point"}
}