{
  "type": "Feature",
  "properties": {
    "addr:full": "796 Twp Rd 851 Savannah OH 44805",
    "addr:housenumber": "796;851",
    "addr:postcode": "44805",
    "addr:street": "Twp Rd",
    "iso:country": "US",
    "sg:address": "796 Twp Rd 851",
    "sg:city": "Savannah",
    "sg:classifiers": [
      {
        "category": "Restaurant",
        "type": "Food \u0026 Drink"
      }
    ],
    "sg:phone": "+1 419 962 4628",
    "sg:postcode": "44805",
    "sg:province": "OH",
    "sg:tags": [
      "caterer"
    ],
    "wof:name": "Sallie",
    "wof:placetype": "venue"
  },
  "geometry": {"coordinates":[-82.291462,40.949245],"type":"Point"}
}
