{
  "type": "Feature",
  "properties": {
    "iso:country":"US",
    "sg:address":"700 E Exchange St",
    "sg:city":"Akron",
    "sg:classifiers":[
        {
            "category":"Recreation",
            "type":"Entertainment"
        }
    ],
    "sg:phone":"+1 330 375 2821",
    "sg:postcode":"44306",
    "sg:province":"OH",
    "wof:name":"Mason Park Community Center",
    "wof:placetype":"venue"
},
  "geometry": {"coordinates":[-81.49922,41.071074],"type":"Point"}
}