{
  "type": "Feature",
  "properties": {
    "addr:full":"3544 W Henderson Rd Columbus OH 43220",
    "addr:housenumber":"3544",
    "addr:postcode":"43220",
    "addr:street":"W Henderson Rd",
    "iso:country":"US",
    "sg:address":"3544 W Henderson Rd",
    "sg:city":"Columbus",
    "sg:classifiers":[
        {
            "category":"Shopping",
            "subcategory":"Computers & Home Electronics",
            "type":"Retail Goods"
        }
    ],
    "sg:phone":"+1 614 442 1370",
    "sg:postcode":"43220",
    "sg:province":"OH",
    "sg:tags":[
        "software"
    ],
    "wof:name":"Global Soft Svc",
    "wof:placetype":"venue"
},
  "geometry": {"coordinates":[-83.09779,40.061002],"type":"Point"}
}