{
  "type": "Feature",
  "properties": {
    "addr:full":"745 W State St Columbus OH 43222",
    "addr:housenumber":"745",
    "addr:postcode":"43222",
    "addr:street":"W State St",
    "iso:country":"US",
    "sg:address":"745 W State St",
    "sg:city":"Columbus",
    "sg:classifiers":[
        {
            "category":"Health Services",
            "subcategory":"Clinic",
            "type":"Services"
        }
    ],
    "sg:phone":"+1 614 224 2344",
    "sg:postcode":"43222",
    "sg:province":"OH",
    "sg:tags":[
        "outpatient"
    ],
    "sg:website":"www.renalcaregroup.com",
    "wof:name":"Renal Care Group",
    "wof:placetype":"venue"
},
  "geometry": {"coordinates":[-83.02109900000001,39.957653],"type":"Point"}
}