{
  "type": "Feature",
  "properties": {
    "addr:full":"8420 Reading Rd Cincinnati OH 45215",
    "addr:housenumber":"8420",
    "addr:postcode":"45215",
    "addr:street":"Reading Rd",
    "iso:country":"US",
    "sg:address":"8420 Reading Rd",
    "sg:city":"Cincinnati",
    "sg:classifiers":[
        {
            "category":"Banks & Credit Unions",
            "subcategory":"Bank",
            "type":"Services"
        }
    ],
    "sg:phone":"+1 513 761 7100",
    "sg:postcode":"45215",
    "sg:province":"OH",
    "sg:tags":[
        "loan",
        "real estate"
    ],
    "wof:name":"Premier Mortgage Funding",
    "wof:placetype":"venue"
},
  "geometry": {"coordinates":[-84.44745399999999,39.211911],"type":"Point"}
}