{
  "type": "Feature",
  "properties": {
    "addr:full": "821 Ogden Ave Toledo OH 43609",
    "addr:housenumber": "821",
    "addr:postcode": "43609",
    "addr:street": "Ogden Ave",
    "iso:country": "US",
    "sg:address": "821 Ogden Ave",
    "sg:city": "Toledo",
    "sg:classifiers": [
      {
        "category": "Retail",
        "subcategory": "Laundry \u0026 Dry Cleaning",
        "type": "Services"
      }
    ],
    "sg:phone": "+1 419 389 9094",
    "sg:postcode": "43609",
    "sg:province": "OH",
    "sg:tags": [
      "cleaners",
      "rug",
      "carpet"
    ],
    "wof:name": "First Class Janitorial Svc",
    "wof:placetype": "venue"
  },
  "geometry": {"coordinates":[-83.583655,41.623866],"type":"Point"}
}
