{
  "type": "Feature",
  "properties": {
    "addr:full":"823 W 23rd St Lorain OH 44052",
    "addr:housenumber":"823",
    "addr:postcode":"44052",
    "addr:street":"W 23Rd St",
    "iso:country":"US",
    "sg:address":"823 W 23rd St",
    "sg:city":"Lorain",
    "sg:classifiers":[
        {
            "category":"Personal",
            "subcategory":"Beauty Salon",
            "type":"Services"
        }
    ],
    "sg:phone":"+1 440 282 1666",
    "sg:postcode":"44052",
    "sg:province":"OH",
    "wof:name":"J Anthony's Hair Studio",
    "wof:placetype":"venue"
},
  "geometry": {"coordinates":[-82.173754,41.448653],"type":"Point"}
}