{
  "type": "Feature",
  "properties": {
    "addr:full": "2577 Noble Rd Cleveland OH 44121",
    "addr:housenumber": "2577",
    "addr:postcode": "44121",
    "addr:street": "Noble Rd",
    "iso:country": "US",
    "sg:address": "2577 Noble Rd",
    "sg:city": "Cleveland",
    "sg:classifiers": [
      {
        "category": "Food \u0026 Beverages",
        "subcategory": "Groceries \u0026 Convenience Stores",
        "type": "Retail Goods"
      }
    ],
    "sg:phone": "+1 216 291 1673",
    "sg:postcode": "44121",
    "sg:province": "OH",
    "wof:name": "Chesapeake Sea Food",
    "wof:placetype": "venue"
  },
  "geometry": {"coordinates":[-81.542709,41.531861],"type":"Point"}
}
