{
  "type": "Feature",
  "properties": {
    "iso:country":"US",
    "sg:address":"2577 Noble Rd",
    "sg:city":"Cleveland",
    "sg:classifiers":[
        {
            "category":"Food & Beverages",
            "subcategory":"Groceries & Convenience Stores",
            "type":"Retail Goods"
        }
    ],
    "sg:phone":"+1 216 291 1673",
    "sg:postcode":"44121",
    "sg:province":"OH",
    "wof:name":"Chesapeake Sea Food",
    "wof:placetype":"venue"
},
  "geometry": {"coordinates":[-81.542709,41.531861],"type":"Point"}
}