{
  "type": "Feature",
  "properties": {
    "addr:full": "1 Cascade Plz Akron OH 44308",
    "addr:housenumber": "1",
    "addr:postcode": "44308",
    "addr:street": "Cascade Plz",
    "iso:country": "US",
    "sg:address": "1 Cascade Plz",
    "sg:city": "Akron",
    "sg:classifiers": [
      {
        "category": "Professional",
        "subcategory": "Lawyer \u0026 Legal Services",
        "type": "Services"
      }
    ],
    "sg:phone": "+1 330 535 0124",
    "sg:postcode": "44308",
    "sg:province": "OH",
    "sg:tags": [
      "attorney"
    ],
    "wof:name": "Semple \u0026 Eicher",
    "wof:placetype": "venue"
  },
  "geometry": {"coordinates":[-81.519515,41.081554],"type":"Point"}
}
