{
  "type": "Feature",
  "properties": {
    "addr:full":"135 S Washington St Tiffin OH 44883",
    "addr:housenumber":"135",
    "addr:postcode":"44883",
    "addr:street":"S Washington St",
    "iso:country":"US",
    "sg:address":"135 S Washington St",
    "sg:city":"Tiffin",
    "sg:classifiers":[
        {
            "category":"Shopping",
            "type":"Retail Goods"
        }
    ],
    "sg:phone":"+1 419 447 2866",
    "sg:postcode":"44883",
    "sg:province":"OH",
    "sg:tags":[
        "cosmetic",
        "perfume"
    ],
    "wof:name":"Avon Products",
    "wof:placetype":"venue"
},
  "geometry": {"coordinates":[-83.1764,41.113811],"type":"Point"}
}