{
  "type": "Feature",
  "properties": {
    "addr:full":"14429 Cedar Rd Cleveland OH 44121",
    "addr:housenumber":"14429",
    "addr:postcode":"44121",
    "addr:street":"Cedar Rd",
    "iso:country":"US",
    "sg:address":"14429 Cedar Rd",
    "sg:city":"Cleveland",
    "sg:classifiers":[
        {
            "category":"Professional",
            "subcategory":"Accounting & Tax Preparation",
            "type":"Services"
        }
    ],
    "sg:phone":"+1 216 291 9638",
    "sg:postcode":"44121",
    "sg:province":"OH",
    "sg:tags":[
        "return",
        "filing"
    ],
    "wof:name":"Glass Block 2000",
    "wof:placetype":"venue"
},
  "geometry": {"coordinates":[-81.520003,41.501432],"type":"Point"}
}