{
  "type": "Feature",
  "properties": {
    "addr:full": "5568 Hibernia Dr Columbus OH 43232",
    "addr:postcode": "5568;43232",
    "addr:street": "Hibernia Dr",
    "iso:country": "US",
    "sg:address": "5568 Hibernia Dr",
    "sg:city": "Columbus",
    "sg:classifiers": [
      {
        "category": "Utilities",
        "subcategory": "Telephone",
        "type": "Services"
      }
    ],
    "sg:phone": "+1 614 986 1430",
    "sg:postcode": "43232",
    "sg:province": "OH",
    "sg:tags": [
      "communications"
    ],
    "wof:name": "614 Enterprises",
    "wof:placetype": "venue"
  },
  "geometry": {"coordinates":[-82.852193,39.952677],"type":"Point"}
}
