{
  "type": "Feature",
  "properties": {
    "iso:country":"US",
    "sg:address":"764 Wourms Rd",
    "sg:city":"Fort Recovery",
    "sg:classifiers":[
        {
            "category":"Farming",
            "subcategory":"Farm & Veterinary Services",
            "type":"Manufacturing & Wholesale Goods"
        }
    ],
    "sg:phone":"+1 419 375 2701",
    "sg:postcode":"45846",
    "sg:province":"OH",
    "sg:tags":[
        "livestock"
    ],
    "wof:name":"Stammen Poultry",
    "wof:placetype":"venue"
},
  "geometry": {"coordinates":[-84.71940499999999,40.380374],"type":"Point"}
}