{
  "type": "Feature",
  "properties": {
    "addr:full": "2560 Erie Ave Cincinnati OH 45208",
    "addr:housenumber": "2560",
    "addr:postcode": "45208",
    "addr:street": "Erie Ave",
    "iso:country": "US",
    "sg:address": "2560 Erie Ave",
    "sg:city": "Cincinnati",
    "sg:classifiers": [
      {
        "category": "Real Estate",
        "subcategory": "Real Estate Operator",
        "type": "Services"
      }
    ],
    "sg:phone": "+1 513 321 3593",
    "sg:postcode": "45208",
    "sg:province": "OH",
    "sg:tags": [
      "building",
      "apartment",
      "commercial"
    ],
    "wof:name": "Plum Street Properties",
    "wof:placetype": "venue"
  },
  "geometry": {"coordinates":[-84.446027,39.140057],"type":"Point"}
}
