{
  "type": "Feature",
  "properties": {
    "iso:country":"US",
    "sg:address":"123 N Main St",
    "sg:city":"North Canton",
    "sg:classifiers":[
        {
            "category":"Restaurant",
            "type":"Food & Drink"
        }
    ],
    "sg:phone":"+1 330 498 4994",
    "sg:postcode":"44720",
    "sg:province":"OH",
    "wof:name":"Smokin' Joes Rib Schack",
    "wof:placetype":"venue"
},
  "geometry": {"coordinates":[-81.40250899999999,40.876896],"type":"Point"}
}