{
  "type": "Feature",
  "properties": {
    "addr:full": "2395 W State Rte 122 Lebanon OH 45036",
    "addr:housenumber": "2395",
    "addr:postcode": "45036",
    "addr:street": "W State Rte 122",
    "iso:country": "US",
    "sg:address": "2395 W State Rte 122",
    "sg:city": "Lebanon",
    "sg:phone": "+1 513 932 8966",
    "sg:postcode": "45036",
    "sg:province": "OH",
    "sg:tags": [
      "beef",
      "farm",
      "corn",
      "soybean",
      "cattle",
      "feedlot"
    ],
    "wof:name": "Clover Hill Farm Inc",
    "wof:placetype": "venue"
  },
  "geometry": {"coordinates":[-84.246995,39.491033],"type":"Point"}
}
