{
  "type": "Feature",
  "properties": {
    "addr:full": "1746 Ballentine Pike Springfield OH 45502",
    "addr:housenumber": "1746",
    "addr:postcode": "45502",
    "addr:street": "Ballentine Pike",
    "iso:country": "US",
    "sg:address": "1746 Ballentine Pike",
    "sg:city": "Springfield",
    "sg:classifiers": [
      {
        "category": "Building \u0026 Trades",
        "subcategory": "Plumbing",
        "type": "Services"
      }
    ],
    "sg:phone": "+1 937 323 0211",
    "sg:postcode": "45502",
    "sg:province": "OH",
    "sg:tags": [
      "septic"
    ],
    "wof:name": "A-1 Sanitary Svc",
    "wof:placetype": "venue"
  },
  "geometry": {"coordinates":[-83.882166,39.954071],"type":"Point"}
}
