{
  "type": "Feature",
  "properties": {
    "iso:country":"US",
    "sg:address":"2999 Payne Ave",
    "sg:city":"Cleveland",
    "sg:classifiers":[
        {
            "category":"Personal",
            "subcategory":"Beauty Salon",
            "type":"Services"
        }
    ],
    "sg:phone":"+1 216 241 5530",
    "sg:postcode":"44114",
    "sg:province":"OH",
    "wof:name":"Hair 2000",
    "wof:placetype":"venue"
},
  "geometry": {"coordinates":[-81.669877,41.507588],"type":"Point"}
}