{
  "type": "Feature",
  "properties": {
    "iso:country":"US",
    "sg:address":"8598 Sunlight Dr",
    "sg:city":"Cincinnati",
    "sg:classifiers":[
        {
            "category":"Building & Trades",
            "subcategory":"Construction",
            "type":"Services"
        }
    ],
    "sg:phone":"+1 513 931 0451",
    "sg:postcode":"45231",
    "sg:province":"OH",
    "sg:tags":[
        "contractor"
    ],
    "wof:name":"Opportunity Remodeling",
    "wof:placetype":"venue"
},
  "geometry": {"coordinates":[-84.56912699999999,39.22614],"type":"Point"}
}