{
  "type": "Feature",
  "properties": {
    "addr:full": "36100 Euclid Ave Willoughby OH 44094",
    "addr:housenumber": "36100",
    "addr:postcode": "44094",
    "addr:street": "Euclid Ave",
    "iso:country": "US",
    "sg:address": "36100 Euclid Ave",
    "sg:city": "Willoughby",
    "sg:classifiers": [
      {
        "category": "Health Services",
        "subcategory": "Podiatrist",
        "type": "Services"
      }
    ],
    "sg:phone": "+1 440 269 1488",
    "sg:postcode": "44094",
    "sg:province": "OH",
    "wof:name": "Buckeye Foot Care",
    "wof:placetype": "venue"
  },
  "geometry": {"coordinates":[-81.429576,41.626987],"type":"Point"}
}
