{
  "type": "Feature",
  "properties": {
    "addr:full": "414 N 2nd St Ironton OH 45638",
    "addr:housenumber": "414",
    "addr:postcode": "45638",
    "addr:street": "N 2Nd St",
    "iso:country": "US",
    "sg:address": "414 N 2nd St",
    "sg:city": "Ironton",
    "sg:classifiers": [
      {
        "category": "Retail",
        "subcategory": "Auto Repair",
        "type": "Services"
      }
    ],
    "sg:phone": "+1 740 534 9262",
    "sg:postcode": "45638",
    "sg:province": "OH",
    "sg:tags": [
      "repairing",
      "automobile"
    ],
    "wof:name": "Johnny's Auto Repair",
    "wof:placetype": "venue"
  },
  "geometry": {"coordinates":[-82.688418,38.53758],"type":"Point"}
}
