{
  "type": "Feature",
  "properties": {
    "addr:full":"479 Dussel Dr Maumee OH 43537",
    "addr:housenumber":"479",
    "addr:postcode":"43537",
    "addr:street":"Dussel Dr",
    "iso:country":"US",
    "sg:address":"479 Dussel Dr",
    "sg:city":"Maumee",
    "sg:classifiers":[
        {
            "category":"Restaurant",
            "type":"Food & Drink"
        }
    ],
    "sg:phone":"+1 419 482 6610",
    "sg:postcode":"43537",
    "sg:province":"OH",
    "sg:tags":[
        "parlor",
        "ice",
        "cream"
    ],
    "sg:website":"www.coldstonecreamery.com",
    "wof:name":"Cold Stone Creamery",
    "wof:placetype":"venue"
},
  "geometry": {"coordinates":[-83.657461,41.585758],"type":"Point"}
}