{
  "type": "Feature",
  "properties": {
    "iso:country":"US",
    "sg:address":"5742 State Rte 5",
    "sg:city":"Ravenna",
    "sg:classifiers":[
        {
            "category":"Utilities",
            "subcategory":"Fuel Oil & Lpg",
            "type":"Services"
        }
    ],
    "sg:phone":"+1 330 297 6649",
    "sg:postcode":"44266",
    "sg:province":"OH",
    "sg:tags":[
        "liquefied",
        "gas",
        "petroleum"
    ],
    "wof:name":"Level Propane",
    "wof:placetype":"venue"
},
  "geometry": {"coordinates":[-81.183175,41.151835],"type":"Point"}
}