{
  "type": "Feature",
  "properties": {
    "addr:full":"106 W Ash St Piqua OH 45356",
    "addr:housenumber":"106",
    "addr:postcode":"45356",
    "addr:street":"W Ash St",
    "iso:country":"US",
    "sg:address":"106 W Ash St",
    "sg:city":"Piqua",
    "sg:classifiers":[
        {
            "category":"Social Services",
            "type":"Services"
        }
    ],
    "sg:phone":"+1 937 773 6153",
    "sg:postcode":"45356",
    "sg:province":"OH",
    "sg:tags":[
        "deaf",
        "facility"
    ],
    "wof:name":"Community Services For-Deaf",
    "wof:placetype":"venue"
},
  "geometry": {"coordinates":[-84.24099099999999,40.149793],"type":"Point"}
}