{
  "type": "Feature",
  "properties": {
    "addr:full": "211 Spring St Flushing OH 43977",
    "addr:housenumber": "211",
    "addr:postcode": "43977",
    "addr:street": "Spring St",
    "iso:country": "US",
    "sg:address": "211 Spring St",
    "sg:city": "Flushing",
    "sg:classifiers": [
      {
        "category": "Building \u0026 Trades",
        "subcategory": "Construction",
        "type": "Services"
      }
    ],
    "sg:phone": "+1 740 968 3144",
    "sg:postcode": "43977",
    "sg:province": "OH",
    "sg:tags": [
      "steel",
      "stainless",
      "fabrication"
    ],
    "wof:name": "Edwards Stnless Stl Fbrication",
    "wof:placetype": "venue"
  },
  "geometry": {"coordinates":[-81.065789,40.148332],"type":"Point"}
}
