{
  "type": "Feature",
  "properties": {
    "addr:full": "1420 Finger Lakes Dayton OH 45458",
    "addr:housenumber": "1420",
    "addr:postcode": "45458",
    "addr:street": "Finger Lakes",
    "iso:country": "US",
    "sg:address": "1420 Finger Lakes",
    "sg:city": "Dayton",
    "sg:classifiers": [
      {
        "category": "Professional",
        "subcategory": "Computer Services",
        "type": "Services"
      }
    ],
    "sg:phone": "+1 937 281 4700",
    "sg:postcode": "45458",
    "sg:province": "OH",
    "sg:tags": [
      "internet"
    ],
    "sg:website": "www.phintec.com",
    "wof:name": "Phintec",
    "wof:placetype": "venue"
  },
  "geometry": {"coordinates":[-84.196948,39.621791],"type":"Point"}
}
