{
  "type": "Feature",
  "properties": {
    "addr:full": "111 E Columbus St Kenton OH 43326",
    "addr:housenumber": "111",
    "addr:postcode": "43326",
    "addr:street": "E Columbus St",
    "iso:country": "US",
    "sg:address": "111 E Columbus St",
    "sg:city": "Kenton",
    "sg:classifiers": [
      {
        "category": "Banks \u0026 Credit Unions",
        "subcategory": "Bank",
        "type": "Services"
      }
    ],
    "sg:phone": "+1 419 673 1201",
    "sg:postcode": "43326",
    "sg:province": "OH",
    "wof:name": "US Bank",
    "wof:placetype": "venue"
  },
  "geometry": {"coordinates":[-83.607835,40.648223],"type":"Point"}
}
