{
  "type": "Feature",
  "properties": {
    "iso:country":"US",
    "sg:address":"111 E Columbus St",
    "sg:city":"Kenton",
    "sg:classifiers":[
        {
            "category":"Banks & Credit Unions",
            "subcategory":"Bank",
            "type":"Services"
        }
    ],
    "sg:phone":"+1 419 673 1201",
    "sg:postcode":"43326",
    "sg:province":"OH",
    "wof:name":"US Bank",
    "wof:placetype":"venue"
},
  "geometry": {"coordinates":[-83.60783499999999,40.648223],"type":"Point"}
}