{
  "type": "Feature",
  "properties": {
    "iso:country":"US",
    "sg:address":"4681 Mahoning Ave NW",
    "sg:city":"Warren",
    "sg:classifiers":[
        {
            "category":"Health Services",
            "subcategory":"Doctor",
            "type":"Services"
        },
        {
            "category":"Health Services",
            "subcategory":"Clinic",
            "type":"Services"
        }
    ],
    "sg:phone":"+1 330 847 7778",
    "sg:postcode":"44483",
    "sg:province":"OH",
    "sg:tags":[
        "physician",
        "family",
        "practice",
        "surgeons",
        "osteopathic",
        "medicine",
        "surgeon"
    ],
    "wof:name":"Frank G Veres Do",
    "wof:placetype":"venue"
},
  "geometry": {"coordinates":[-80.84585300000001,41.284578],"type":"Point"}
}