{
  "type": "Feature",
  "properties": {
    "iso:country":"US",
    "sg:address":"2689 Commons Blvd",
    "sg:city":"Dayton",
    "sg:classifiers":[
        {
            "category":"Building & Trades",
            "subcategory":"Construction",
            "type":"Services"
        }
    ],
    "sg:phone":"+1 937 427 0607",
    "sg:postcode":"45431",
    "sg:province":"OH",
    "sg:tags":[
        "maintenance",
        "contractor"
    ],
    "wof:name":"Chain Commercial Maintenance",
    "wof:placetype":"venue"
},
  "geometry": {"coordinates":[-84.05952499999999,39.770665],"type":"Point"}
}