{
  "type": "Feature",
  "properties": {
    "addr:full":"809 Hebron Rd Newark OH 43056",
    "addr:housenumber":"809",
    "addr:postcode":"43056",
    "addr:street":"Hebron Rd",
    "iso:country":"US",
    "sg:address":"809 Hebron Rd",
    "sg:city":"Newark",
    "sg:classifiers":[
        {
            "category":"Shopping",
            "subcategory":"Stationery & Office Supplies",
            "type":"Retail Goods"
        }
    ],
    "sg:phone":"+1 740 522 5230",
    "sg:postcode":"43056",
    "sg:province":"OH",
    "wof:name":"Staples",
    "wof:placetype":"venue"
},
  "geometry": {"coordinates":[-82.441481,40.029183],"type":"Point"}
}