{
  "type": "Feature",
  "properties": {
    "addr:full":"3063 E 14th Ave Columbus OH 43219",
    "addr:housenumber":"3063",
    "addr:postcode":"43219",
    "addr:street":"E 14Th Ave",
    "iso:country":"US",
    "sg:address":"3063 E 14th Ave",
    "sg:city":"Columbus",
    "sg:classifiers":[
        {
            "category":"Social Services",
            "type":"Services"
        }
    ],
    "sg:phone":"+1 614 258 2545",
    "sg:postcode":"43219",
    "sg:province":"OH",
    "wof:name":"Lifecare Medical Services",
    "wof:placetype":"venue"
},
  "geometry": {"coordinates":[-82.929129,39.993918],"type":"Point"}
}