{
  "type": "Feature",
  "properties": {
    "addr:full": "229 Northland Blvd Cincinnati OH 45246",
    "addr:housenumber": "229",
    "addr:postcode": "45246",
    "addr:street": "Northland Blvd",
    "iso:country": "US",
    "sg:address": "229 Northland Blvd",
    "sg:city": "Cincinnati",
    "sg:classifiers": [
      {
        "category": "Manufacturing",
        "subcategory": "Rubber \u0026 Plastics",
        "type": "Manufacturing \u0026 Wholesale Goods"
      }
    ],
    "sg:phone": "+1 513 772 6635",
    "sg:postcode": "45246",
    "sg:province": "OH",
    "sg:tags": [
      "insulation",
      "mfg"
    ],
    "wof:name": "Surface Dynamics Inc",
    "wof:placetype": "venue"
  },
  "geometry": {"coordinates":[-84.481281,39.282584],"type":"Point"}
}
