{
  "type": "Feature",
  "properties": {
    "iso:country":"US",
    "sg:address":"1939 Baum St SE",
    "sg:city":"Canton",
    "sg:phone":"+1 330 484 4643",
    "sg:postcode":"44707",
    "sg:province":"OH",
    "sg:tags":[
        "wheat",
        "farm",
        "corn",
        "cash",
        "grain",
        "soybean"
    ],
    "wof:name":"D & L Farms",
    "wof:placetype":"venue"
},
  "geometry": {"coordinates":[-81.363519,40.741536],"type":"Point"}
}