{
  "type": "Feature",
  "properties": {
    "addr:full":"117 N Scioto St Circleville OH 43113",
    "addr:housenumber":"117",
    "addr:postcode":"43113",
    "addr:street":"N Scioto St",
    "iso:country":"US",
    "sg:address":"117 N Scioto St",
    "sg:city":"Circleville",
    "sg:classifiers":[
        {
            "category":"Banks & Credit Unions",
            "subcategory":"Investment Brokerage",
            "type":"Services"
        }
    ],
    "sg:phone":"+1 740 420 9886",
    "sg:postcode":"43113",
    "sg:province":"OH",
    "sg:tags":[
        "security"
    ],
    "wof:name":"Edward Jones 14310",
    "wof:placetype":"venue"
},
  "geometry": {"coordinates":[-82.94738099999999,39.603458],"type":"Point"}
}