{
  "type": "Feature",
  "properties": {
    "iso:country":"US",
    "sg:address":"5980 Wilcox Place",
    "sg:city":"Dublin",
    "sg:classifiers":[
        {
            "category":"Professional",
            "subcategory":"Computer Services",
            "type":"Services"
        }
    ],
    "sg:phone":"+1 614 547 9635",
    "sg:postcode":"43016",
    "sg:province":"OH",
    "sg:tags":[
        "ehr",
        "emr",
        "patient-portal",
        "integrated-electronic-fax",
        "hipaa-compliant-secure-email",
        "hipaa-compliant-secure-messaging"
    ],
    "sg:website":"http://www.updox.com",
    "wof:name":"Updox",
    "wof:placetype":"venue"
},
  "geometry": {"coordinates":[-83.15168799999999,40.094107],"type":"Point"}
}