{
  "type": "Feature",
  "properties": {
    "iso:country":"US",
    "sg:address":"3293 Massillon Rd",
    "sg:city":"Akron",
    "sg:classifiers":[
        {
            "category":"Autos & Motor Vehicles",
            "subcategory":"Auto Supplies",
            "type":"Retail Goods"
        }
    ],
    "sg:phone":"+1 330 899 1023",
    "sg:postcode":"44312",
    "sg:province":"OH",
    "sg:tags":[
        "automobile",
        "parts"
    ],
    "wof:name":"Keystone Automotive Ind Inc",
    "wof:placetype":"venue"
},
  "geometry": {"coordinates":[-81.464634,40.973359],"type":"Point"}
}