{
  "type": "Feature",
  "properties": {
    "addr:full": "1874 16th St SW Akron OH 44314",
    "addr:housenumber": "1874",
    "addr:postcode": "44314",
    "addr:street": "16Th St Sw",
    "iso:country": "US",
    "sg:address": "1874 16th St SW",
    "sg:city": "Akron",
    "sg:classifiers": [
      {
        "category": "Building \u0026 Trades",
        "subcategory": "Construction",
        "type": "Services"
      }
    ],
    "sg:phone": "+1 330 745 0998",
    "sg:postcode": "44314",
    "sg:province": "OH",
    "sg:tags": [
      "home",
      "improvement"
    ],
    "wof:name": "Handy Man Specialists Inc",
    "wof:placetype": "venue"
  },
  "geometry": {"coordinates":[-81.560332,41.053331],"type":"Point"}
}
