{
  "type": "Feature",
  "properties": {
    "iso:country":"US",
    "sg:address":"68 S Shore Dr",
    "sg:city":"Youngstown",
    "sg:classifiers":[
        {
            "category":"Building & Trades",
            "subcategory":"Construction",
            "type":"Services"
        }
    ],
    "sg:phone":"+1 330 629 9067",
    "sg:postcode":"44512",
    "sg:province":"OH",
    "sg:tags":[
        "detection",
        "gas"
    ],
    "wof:name":"S L Technologies Inc",
    "wof:placetype":"venue"
},
  "geometry": {"coordinates":[-80.666628,41.007221],"type":"Point"}
}