{
  "type": "Feature",
  "properties": {
    "addr:full":"10220 Greenville St Marys Rd Versailles OH 45380",
    "addr:housenumber":"10220",
    "addr:postcode":"45380",
    "addr:street":"Greenville St Marys Rd",
    "iso:country":"US",
    "sg:address":"10220 Greenville St Marys Rd",
    "sg:city":"Versailles",
    "sg:classifiers":[
        {
            "category":"Freight",
            "type":"Transportation"
        }
    ],
    "sg:phone":"+1 937 337 5044",
    "sg:postcode":"45380",
    "sg:province":"OH",
    "sg:tags":[
        "operator",
        "trucking"
    ],
    "wof:name":"Ronald and Nancy Brewer",
    "wof:placetype":"venue"
},
  "geometry": {"coordinates":[-84.581052,40.20954],"type":"Point"}
}