{
  "type": "Feature",
  "properties": {
    "addr:full":"1966 Fairport Nursery Rd Painesville OH 44077",
    "addr:housenumber":"1966",
    "addr:postcode":"44077",
    "addr:street":"Fairport Nursery Rd",
    "iso:country":"US",
    "sg:address":"1966 Fairport Nursery Rd",
    "sg:city":"Painesville",
    "sg:classifiers":[
        {
            "category":"Manufacturing",
            "subcategory":"Chemicals & Compounds",
            "type":"Manufacturing & Wholesale Goods"
        }
    ],
    "sg:phone":"+1 440 357 1020",
    "sg:postcode":"44077",
    "sg:province":"OH",
    "sg:tags":[
        "inorganic",
        "industrial",
        "mfg"
    ],
    "wof:name":"Bower Ammonia & Chemical",
    "wof:placetype":"venue"
},
  "geometry": {"coordinates":[-81.26856100000001,41.750788],"type":"Point"}
}