{
  "type": "Feature",
  "properties": {
    "addr:full": "37 N High St Columbus OH 43215",
    "addr:housenumber": "37",
    "addr:postcode": "43215",
    "addr:street": "N High St",
    "iso:country": "US",
    "sg:address": "37 N High St",
    "sg:city": "Columbus",
    "sg:classifiers": [
      {
        "category": "Professional",
        "subcategory": "Research",
        "type": "Services"
      }
    ],
    "sg:phone": "+1 614 225 6923",
    "sg:postcode": "43215",
    "sg:province": "OH",
    "wof:name": "Research Services",
    "wof:placetype": "venue"
  },
  "geometry": {"coordinates":[-83.000963,39.963441],"type":"Point"}
}
