{
  "type": "Feature",
  "properties": {
    "iso:country":"US",
    "sg:address":"2827 Gilbert Ave",
    "sg:city":"Cincinnati",
    "sg:classifiers":[
        {
            "category":"Professional",
            "subcategory":"Art Services",
            "type":"Services"
        }
    ],
    "sg:phone":"+1 513 961 1454",
    "sg:postcode":"45206",
    "sg:province":"OH",
    "sg:tags":[
        "photographer"
    ],
    "wof:name":"Mc Hale Studios Inc",
    "wof:placetype":"venue"
},
  "geometry": {"coordinates":[-84.488405,39.13059],"type":"Point"}
}