{
  "type": "Feature",
  "properties": {
    "iso:country":"US",
    "sg:address":"3091 E 14th Ave",
    "sg:city":"Columbus",
    "sg:classifiers":[
        {
            "category":"Home & Garden",
            "subcategory":"Building Materials",
            "type":"Retail Goods"
        }
    ],
    "sg:phone":"+1 614 257 1776",
    "sg:postcode":"43219",
    "sg:province":"OH",
    "sg:tags":[
        "door"
    ],
    "wof:name":"Screen Systems Of America",
    "wof:placetype":"venue"
},
  "geometry": {"coordinates":[-82.92152299999999,39.993718],"type":"Point"}
}