{
  "type": "Feature",
  "properties": {
    "addr:full": "23546 US Hwy 224 Alvada OH 44802",
    "addr:housenumber": "23546",
    "addr:postcode": "44802",
    "addr:street": "Us Hwy 224",
    "iso:country": "US",
    "sg:address": "23546 US Hwy 224",
    "sg:city": "Alvada",
    "sg:classifiers": [
      {
        "category": "Shopping",
        "type": "Retail Goods"
      }
    ],
    "sg:phone": "+1 419 894 6901",
    "sg:postcode": "44802",
    "sg:province": "OH",
    "sg:tags": [
      "product",
      "wood"
    ],
    "wof:name": "NWP Mfg",
    "wof:placetype": "venue"
  },
  "geometry": {"coordinates":[-83.421399,41.07947],"type":"Point"}
}
