{
  "type": "Feature",
  "properties": {
    "iso:country":"US",
    "sg:address":"3983 Gallia St",
    "sg:city":"New Boston",
    "sg:classifiers":[
        {
            "category":"Real Estate",
            "subcategory":"Real Estate Operator",
            "type":"Services"
        },
        {
            "category":"Government",
            "subcategory":"Office",
            "type":"Public Place"
        }
    ],
    "sg:phone":"+1 740 456 4243",
    "sg:postcode":"45662",
    "sg:province":"OH",
    "sg:tags":[
        "executive",
        "apartment"
    ],
    "wof:name":"Cliffside House",
    "wof:placetype":"venue"
},
  "geometry": {"coordinates":[-82.936182,38.753015],"type":"Point"}
}