{
  "type": "Feature",
  "properties": {
    "addr:full":"365 Steubenville Rd SE Carrollton OH 44615",
    "addr:housenumber":"365",
    "addr:postcode":"44615",
    "addr:street":"Steubenville Rd Se",
    "iso:country":"US",
    "sg:address":"365 Steubenville Rd SE",
    "sg:city":"Carrollton",
    "sg:classifiers":[
        {
            "category":"Organizations",
            "subcategory":"Religious Organization",
            "type":"Services"
        }
    ],
    "sg:phone":"+1 330 627 7376",
    "sg:postcode":"44615",
    "sg:province":"OH",
    "sg:tags":[
        "church"
    ],
    "wof:name":"Carrollton Bible Chapel",
    "wof:placetype":"venue"
},
  "geometry": {"coordinates":[-81.07085499999999,40.566072],"type":"Point"}
}