{
  "type": "Feature",
  "properties": {
    "addr:full": "1370 Fay Rd Loveland OH 45140",
    "addr:housenumber": "1370",
    "addr:postcode": "45140",
    "addr:street": "Fay Rd",
    "iso:country": "US",
    "sg:address": "1370 Fay Rd",
    "sg:city": "Loveland",
    "sg:classifiers": [
      {
        "category": "Retail",
        "subcategory": "Repair Shop",
        "type": "Services"
      }
    ],
    "sg:phone": "+1 513 575 1113",
    "sg:postcode": "45140",
    "sg:province": "OH",
    "sg:tags": [
      "welding"
    ],
    "wof:name": "T \u0026 T Welding",
    "wof:placetype": "venue"
  },
  "geometry": {"coordinates":[-84.209749,39.218209],"type":"Point"}
}
