{
  "type": "Feature",
  "properties": {
    "addr:full":"1700 Portsmouth Rd Peebles OH 45660",
    "addr:housenumber":"1700",
    "addr:postcode":"45660",
    "addr:street":"Portsmouth Rd",
    "iso:country":"US",
    "sg:address":"1700 Portsmouth Rd",
    "sg:city":"Peebles",
    "sg:classifiers":[
        {
            "category":"Food & Beverages",
            "subcategory":"Meat & Fish",
            "type":"Retail Goods"
        },
        {
            "category":"Wholesale",
            "subcategory":"Meat",
            "type":"Manufacturing & Wholesale Goods"
        }
    ],
    "sg:phone":"+1 937 587 2930",
    "sg:postcode":"45660",
    "sg:province":"OH",
    "sg:tags":[
        "packer"
    ],
    "wof:name":"White's Meat Processing",
    "wof:placetype":"venue"
},
  "geometry": {"coordinates":[-83.37513800000001,38.961622],"type":"Point"}
}