{
  "type": "Feature",
  "properties": {
    "iso:country":"US",
    "sg:address":"5780 Troy Rd",
    "sg:city":"Springfield",
    "sg:classifiers":[
        {
            "category":"Education",
            "subcategory":"School",
            "type":"Public Place"
        }
    ],
    "sg:phone":"+1 937 964 1351",
    "sg:postcode":"45502",
    "sg:province":"OH",
    "sg:website":"www.northwestern.k12.oh.us",
    "wof:name":"Northwestern Elementary School",
    "wof:placetype":"venue"
},
  "geometry": {"coordinates":[-83.915207,39.98897],"type":"Point"}
}