{
  "type": "Feature",
  "properties": {
    "addr:full":"5200 N Hamilton Rd Columbus OH 43230",
    "addr:housenumber":"5200",
    "addr:postcode":"43230",
    "addr:street":"N Hamilton Rd",
    "iso:country":"US",
    "sg:address":"5200 N Hamilton Rd",
    "sg:city":"Columbus",
    "sg:classifiers":[
        {
            "category":"Home & Garden",
            "subcategory":"Building Materials",
            "type":"Retail Goods"
        }
    ],
    "sg:phone":"+1 614 939 5036",
    "sg:postcode":"43230",
    "sg:province":"OH",
    "sg:website":"www.homedepot.com",
    "wof:name":"Home Depot",
    "wof:placetype":"venue"
},
  "geometry": {"coordinates":[-82.86297399999999,40.064184],"type":"Point"}
}