{
  "type": "Feature",
  "properties": {
    "addr:full":"1278 W Broad St Columbus OH 43222",
    "addr:housenumber":"1278",
    "addr:postcode":"43222",
    "addr:street":"W Broad St",
    "iso:country":"US",
    "sg:address":"1278 W Broad St",
    "sg:city":"Columbus",
    "sg:classifiers":[
        {
            "category":"Retail",
            "subcategory":"Funeral Services",
            "type":"Services"
        }
    ],
    "sg:phone":"+1 614 274 1161",
    "sg:postcode":"43222",
    "sg:province":"OH",
    "sg:tags":[
        "director"
    ],
    "wof:name":"Rutherford-Shroyer Funeral Hm",
    "wof:placetype":"venue"
},
  "geometry": {"coordinates":[-83.034189,39.958146],"type":"Point"}
}