{
  "type": "Feature",
  "properties": {
    "iso:country":"US",
    "sg:address":"4127 Bridgewater Pkwy",
    "sg:city":"Stow",
    "sg:classifiers":[
        {
            "category":"Restaurant",
            "type":"Food & Drink"
        }
    ],
    "sg:menulink":"http://www.allmenus.com/oh/stow/163792-skyline-chili/menu/",
    "sg:phone":"+1 330 940 3929",
    "sg:postcode":"44224",
    "sg:province":"OH",
    "sg:tags":[
        "mexican"
    ],
    "wof:name":"Skyline Chili",
    "wof:placetype":"venue"
},
  "geometry": {"coordinates":[-81.481258,41.179961],"type":"Point"}
}