{
  "type": "Feature",
  "properties": {
    "iso:country":"US",
    "sg:address":"2122 Saint Clair Ave NE",
    "sg:city":"Cleveland",
    "sg:classifiers":[
        {
            "category":"Wholesale",
            "subcategory":"Non-durable Goods",
            "type":"Manufacturing & Wholesale Goods"
        },
        {
            "category":"Shopping",
            "subcategory":"Department Store",
            "type":"Retail Goods"
        },
        {
            "category":"Building & Trades",
            "subcategory":"Cleaning & Sanitation",
            "type":"Services"
        },
        {
            "category":"Home & Garden",
            "subcategory":"Hardware",
            "type":"Retail Goods"
        }
    ],
    "sg:phone":"+1 216 771 0110",
    "sg:postcode":"44114",
    "sg:province":"OH",
    "sg:tags":[
        "cleaner",
        "supply",
        "supplies-wholesale",
        "equipment",
        "house",
        "janitor",
        "manufacturer"
    ],
    "wof:name":"Ohio Valley Supply",
    "wof:placetype":"venue"
},
  "geometry": {"coordinates":[-81.67965,41.50913],"type":"Point"}
}