{
  "type": "Feature",
  "properties": {
    "iso:country":"US",
    "sg:address":"1200 Gay St",
    "sg:city":"Portsmouth",
    "sg:classifiers":[
        {
            "category":"Building & Trades",
            "subcategory":"Plumbing",
            "type":"Services"
        }
    ],
    "sg:phone":"+1 740 353 6993",
    "sg:postcode":"45662",
    "sg:province":"OH",
    "sg:tags":[
        "product",
        "management",
        "energy",
        "system"
    ],
    "wof:name":"Energy Employees Compensation",
    "wof:placetype":"venue"
},
  "geometry": {"coordinates":[-82.994183,38.740881],"type":"Point"}
}