{
  "type": "Feature",
  "properties": {
    "addr:full": "4648 Saint Peter Rd Coldwater OH 45828",
    "addr:housenumber": "4648",
    "addr:postcode": "45828",
    "addr:street": "Saint Peter Rd",
    "iso:country": "US",
    "sg:address": "4648 Saint Peter Rd",
    "sg:city": "Coldwater",
    "sg:phone": "+1 419 942 1505",
    "sg:postcode": "45828",
    "sg:province": "OH",
    "sg:tags": [
      "farm",
      "hog",
      "corn",
      "or",
      "feedlot"
    ],
    "wof:name": "Dale Boeckman",
    "wof:placetype": "venue"
  },
  "geometry": {"coordinates":[-84.746134,40.483267],"type":"Point"}
}
