{
  "type": "Feature",
  "properties": {
    "addr:full": "950 Sharon Valley Rd Newark OH 43055",
    "addr:housenumber": "950",
    "addr:postcode": "43055",
    "addr:street": "Sharon Valley Rd",
    "iso:country": "US",
    "sg:address": "950 Sharon Valley Rd",
    "sg:city": "Newark",
    "sg:classifiers": [
      {
        "category": "Professional",
        "subcategory": "Management \u0026 Consulting",
        "type": "Services"
      }
    ],
    "sg:phone": "+1 740 345 7458",
    "sg:postcode": "43055",
    "sg:province": "OH",
    "sg:tags": [
      "consultant",
      "business"
    ],
    "wof:name": "SCORE Svc Corp Of Retired",
    "wof:placetype": "venue"
  },
  "geometry": {"coordinates":[-82.436775,40.071518],"type":"Point"}
}
