{
  "type": "Feature",
  "properties": {
    "addr:full": "852 W Main St Kent OH 44240",
    "addr:housenumber": "852",
    "addr:postcode": "44240",
    "addr:street": "W Main St",
    "iso:country": "US",
    "sg:address": "852 W Main St",
    "sg:city": "Kent",
    "sg:classifiers": [
      {
        "category": "Building \u0026 Trades",
        "subcategory": "Construction",
        "type": "Services"
      }
    ],
    "sg:phone": "+1 330 677 4551",
    "sg:postcode": "44240",
    "sg:province": "OH",
    "sg:tags": [
      "paint",
      "varnish",
      "removal"
    ],
    "wof:name": "Dnj Refinishing",
    "wof:placetype": "venue"
  },
  "geometry": {"coordinates":[-81.376088,41.151936],"type":"Point"}
}
