{
  "type": "Feature",
  "properties": {
    "iso:country":"US",
    "sg:address":"1655 Johnsville Brookville Rd",
    "sg:city":"Brookville",
    "sg:classifiers":[
        {
            "category":"Building & Trades",
            "subcategory":"Construction",
            "type":"Services"
        }
    ],
    "sg:phone":"+1 937 687 2612",
    "sg:postcode":"45309",
    "sg:province":"OH",
    "sg:tags":[
        "insulation",
        "heat",
        "contractor"
    ],
    "wof:name":"Dayton Western Home Imprvmt",
    "wof:placetype":"venue"
},
  "geometry": {"coordinates":[-84.423249,39.772261],"type":"Point"}
}