{
  "type": "Feature",
  "properties": {
    "addr:full":"3114 Alling Dr Twinsburg OH 44087",
    "addr:postcode":"3114;44087",
    "addr:street":"Alling Dr",
    "iso:country":"US",
    "sg:address":"3114 Alling Dr",
    "sg:city":"Twinsburg",
    "sg:classifiers":[
        {
            "category":"Professional",
            "subcategory":"Management & Consulting",
            "type":"Services"
        }
    ],
    "sg:phone":"+1 330 425 1310",
    "sg:postcode":"44087",
    "sg:province":"OH",
    "sg:tags":[
        "marketing",
        "consultant"
    ],
    "wof:name":"Trilogy Marketing Group",
    "wof:placetype":"venue"
},
  "geometry": {"coordinates":[-81.42464,41.33561],"type":"Point"}
}