{
  "type": "Feature",
  "properties": {
    "iso:country":"US",
    "sg:address":"300 Columbus Ave",
    "sg:city":"Sandusky",
    "sg:classifiers":[
        {
            "category":"Restaurant",
            "type":"Food & Drink"
        }
    ],
    "sg:menulink":"http://www.allmenus.com/oh/sandusky/63946-cabana-jacks/menu/",
    "sg:phone":"+1 419 625 4008",
    "sg:postcode":"44870",
    "sg:province":"OH",
    "sg:tags":[
        "american"
    ],
    "wof:name":"Cabana Jacks",
    "wof:placetype":"venue"
},
  "geometry": {"coordinates":[-82.710949,41.45494],"type":"Point"}
}