{
  "type": "Feature",
  "properties": {
    "iso:country":"US",
    "sg:address":"13375 Snow Rd",
    "sg:city":"Cleveland",
    "sg:classifiers":[
        {
            "category":"Banks & Credit Unions",
            "subcategory":"Bank",
            "type":"Services"
        }
    ],
    "sg:phone":"+1 216 362 1006",
    "sg:postcode":"44142",
    "sg:province":"OH",
    "sg:tags":[
        "loan"
    ],
    "sg:website":"www.checksmart.com",
    "wof:name":"Check Smart",
    "wof:placetype":"venue"
},
  "geometry": {"coordinates":[-81.787678,41.405086],"type":"Point"}
}