{
  "type": "Feature",
  "properties": {
    "addr:full":"3485 Commerce Dr Franklin OH 45005",
    "addr:housenumber":"3485",
    "addr:postcode":"45005",
    "addr:street":"Commerce Dr",
    "iso:country":"US",
    "sg:address":"3485 Commerce Dr",
    "sg:city":"Franklin",
    "sg:classifiers":[
        {
            "category":"Autos & Motor Vehicles",
            "subcategory":"Automobile Sales",
            "type":"Retail Goods"
        }
    ],
    "sg:phone":"+1 513 420 9333",
    "sg:postcode":"45005",
    "sg:province":"OH",
    "sg:tags":[
        "car",
        "dealer"
    ],
    "sg:website":"www.croninmotors.com",
    "wof:name":"Cronin Motors",
    "wof:placetype":"venue"
},
  "geometry": {"coordinates":[-84.320691,39.493881],"type":"Point"}
}