{
  "type": "Feature",
  "properties": {
    "iso:country":"US",
    "sg:address":"23 N Detroit St",
    "sg:city":"Kenton",
    "sg:classifiers":[
        {
            "category":"Restaurant",
            "type":"Food & Drink"
        }
    ],
    "sg:phone":"+1 419 675 0901",
    "sg:postcode":"43326",
    "sg:province":"OH",
    "sg:tags":[
        "shop",
        "coffee",
        "eating"
    ],
    "wof:name":"Jitterz Coffee Company",
    "wof:placetype":"venue"
},
  "geometry": {"coordinates":[-83.609318,40.647967],"type":"Point"}
}