{
  "type": "Feature",
  "properties": {
    "iso:country":"US",
    "sg:address":"3907 Nora Ave",
    "sg:city":"Middletown",
    "sg:classifiers":[
        {
            "category":"Retail",
            "subcategory":"Laundry & Dry Cleaning",
            "type":"Services"
        }
    ],
    "sg:phone":"+1 513 423 8259",
    "sg:postcode":"45044",
    "sg:province":"OH",
    "sg:tags":[
        "cleaners",
        "rug",
        "carpet"
    ],
    "wof:name":"Page's Carpet Cleaning",
    "wof:placetype":"venue"
},
  "geometry": {"coordinates":[-84.361256,39.5067],"type":"Point"}
}