{
  "type": "Feature",
  "properties": {
    "addr:full": "3907 Nora Ave Middletown OH 45044",
    "addr:housenumber": "3907",
    "addr:postcode": "45044",
    "addr:street": "Nora Ave",
    "iso:country": "US",
    "sg:address": "3907 Nora Ave",
    "sg:city": "Middletown",
    "sg:classifiers": [
      {
        "category": "Retail",
        "subcategory": "Laundry \u0026 Dry Cleaning",
        "type": "Services"
      }
    ],
    "sg:phone": "+1 513 423 8259",
    "sg:postcode": "45044",
    "sg:province": "OH",
    "sg:tags": [
      "cleaners",
      "rug",
      "carpet"
    ],
    "wof:name": "Page's Carpet Cleaning",
    "wof:placetype": "venue"
  },
  "geometry": {"coordinates":[-84.361256,39.5067],"type":"Point"}
}
