{
  "type": "Feature",
  "properties": {
    "addr:full": "3997 W Bancroft St Ottawa Hills OH 43606",
    "addr:housenumber": "3997",
    "addr:postcode": "43606",
    "addr:street": "W Bancroft St",
    "iso:country": "US",
    "sg:address": "3997 W Bancroft St",
    "sg:city": "Ottawa Hills",
    "sg:classifiers": [
      {
        "category": "Wholesale",
        "subcategory": "Non-durable Goods",
        "type": "Manufacturing \u0026 Wholesale Goods"
      }
    ],
    "sg:phone": "+1 419 535 6800",
    "sg:postcode": "43606",
    "sg:province": "OH",
    "sg:tags": [
      "advertising"
    ],
    "wof:name": "Golden Eagle Gifts",
    "wof:placetype": "venue"
  },
  "geometry": {"coordinates":[-83.63773,41.662447],"type":"Point"}
}
