{
  "type": "Feature",
  "properties": {
    "iso:country":"US",
    "sg:address":"3997 W Bancroft St",
    "sg:city":"Ottawa Hills",
    "sg:classifiers":[
        {
            "category":"Wholesale",
            "subcategory":"Non-durable Goods",
            "type":"Manufacturing & Wholesale Goods"
        }
    ],
    "sg:phone":"+1 419 535 6800",
    "sg:postcode":"43606",
    "sg:province":"OH",
    "sg:tags":[
        "advertising"
    ],
    "wof:name":"Golden Eagle Gifts",
    "wof:placetype":"venue"
},
  "geometry": {"coordinates":[-83.63773,41.662447],"type":"Point"}
}