{
  "type": "Feature",
  "properties": {
    "addr:full": "3358 Manchester Rd Akron OH 44319",
    "addr:housenumber": "3358",
    "addr:postcode": "44319",
    "addr:street": "Manchester Rd",
    "iso:country": "US",
    "sg:address": "3358 Manchester Rd",
    "sg:city": "Akron",
    "sg:classifiers": [
      {
        "category": "Shopping",
        "subcategory": "Used Merchandise",
        "type": "Retail Goods"
      }
    ],
    "sg:phone": "+1 330 644 7474",
    "sg:postcode": "44319",
    "sg:province": "OH",
    "wof:name": "Coventry Antiques \u0026 Crafts",
    "wof:placetype": "venue"
  },
  "geometry": {"coordinates":[-81.555585,41.007165],"type":"Point"}
}
