{
  "type": "Feature",
  "properties": {
    "iso:country":"US",
    "sg:address":"3358 Manchester Rd",
    "sg:city":"Akron",
    "sg:classifiers":[
        {
            "category":"Shopping",
            "subcategory":"Used Merchandise",
            "type":"Retail Goods"
        }
    ],
    "sg:phone":"+1 330 644 7474",
    "sg:postcode":"44319",
    "sg:province":"OH",
    "wof:name":"Coventry Antiques & Crafts",
    "wof:placetype":"venue"
},
  "geometry": {"coordinates":[-81.555585,41.007165],"type":"Point"}
}