{
  "type": "Feature",
  "properties": {
    "addr:full":"1172 Oak St Columbus OH 43205",
    "addr:housenumber":"1172",
    "addr:postcode":"43205",
    "addr:street":"Oak St",
    "iso:country":"US",
    "sg:address":"1172 Oak St",
    "sg:city":"Columbus",
    "sg:classifiers":[
        {
            "category":"Personal",
            "subcategory":"Barber",
            "type":"Services"
        }
    ],
    "sg:phone":"+1 614 258 3508",
    "sg:postcode":"43205",
    "sg:province":"OH",
    "wof:name":"Pure Platinum Cuts",
    "wof:placetype":"venue"
},
  "geometry": {"coordinates":[-82.967709,39.962672],"type":"Point"}
}