{
  "type": "Feature",
  "properties": {
    "addr:full": "717 Twp Hwy 350 Sullivan OH 44880",
    "addr:housenumber": "717",
    "addr:postcode": "44880",
    "addr:street": "Twp Hwy 350",
    "iso:country": "US",
    "sg:address": "717 Twp Hwy 350",
    "sg:city": "Sullivan",
    "sg:classifiers": [
      {
        "category": "Building \u0026 Trades",
        "subcategory": "Electrical",
        "type": "Services"
      }
    ],
    "sg:phone": "+1 419 736 2428",
    "sg:postcode": "44880",
    "sg:province": "OH",
    "sg:tags": [
      "electrical",
      "contractor"
    ],
    "wof:name": "Meyers Electric LLC",
    "wof:placetype": "venue"
  },
  "geometry": {"coordinates":[-82.266485,41.012915],"type":"Point"}
}
