{
  "type": "Feature",
  "properties": {
    "iso:country":"US",
    "sg:address":"500 Portage Lakes Dr",
    "sg:city":"Akron",
    "sg:classifiers":[
        {
            "category":"Social Services",
            "type":"Services"
        }
    ],
    "sg:phone":"+1 330 697 7403",
    "sg:postcode":"44319",
    "sg:province":"OH",
    "sg:tags":[
        "counselor",
        "marriage",
        "family"
    ],
    "wof:name":"Denise Deperro",
    "wof:placetype":"venue"
},
  "geometry": {"coordinates":[-81.536744,40.99629],"type":"Point"}
}