{
  "type": "Feature",
  "properties": {
    "addr:full": "1260 Keller Dr Troy OH 45373",
    "addr:housenumber": "1260",
    "addr:postcode": "45373",
    "addr:street": "Keller Dr",
    "iso:country": "US",
    "sg:address": "1260 Keller Dr",
    "sg:city": "Troy",
    "sg:classifiers": [
      {
        "category": "Real Estate",
        "subcategory": "Real Estate Agent",
        "type": "Services"
      }
    ],
    "sg:phone": "+1 937 335 3130",
    "sg:postcode": "45373",
    "sg:province": "OH",
    "wof:name": "Braun Appraisal Svc",
    "wof:placetype": "venue"
  },
  "geometry": {"coordinates":[-84.23014,40.064951],"type":"Point"}
}
