{
  "type": "Feature",
  "properties": {
    "iso:country":"US",
    "sg:address":"38 W Church St",
    "sg:city":"Newark",
    "sg:classifiers":[
        {
            "category":"Home & Garden",
            "subcategory":"Building Materials",
            "type":"Retail Goods"
        }
    ],
    "sg:phone":"+1 740 349 7970",
    "sg:postcode":"43055",
    "sg:province":"OH",
    "sg:tags":[
        "paint"
    ],
    "wof:name":"PPG Porter Paints",
    "wof:placetype":"venue"
},
  "geometry": {"coordinates":[-82.404465,40.058865],"type":"Point"}
}