{
  "type": "Feature",
  "properties": {
    "iso:country":"US",
    "sg:address":"3262 Center Rd",
    "sg:city":"Youngstown",
    "sg:classifiers":[
        {
            "category":"Health Services",
            "subcategory":"Podiatrist",
            "type":"Services"
        }
    ],
    "sg:phone":"+1 330 707 1220",
    "sg:postcode":"44514",
    "sg:province":"OH",
    "wof:name":"Ankle & Foot Care Ctr",
    "wof:placetype":"venue"
},
  "geometry": {"coordinates":[-80.588949,41.023815],"type":"Point"}
}