{
  "type": "Feature",
  "properties": {
    "iso:country":"US",
    "sg:address":"481 King Beach Dr",
    "sg:city":"Howard",
    "sg:classifiers":[
        {
            "category":"Freight",
            "type":"Transportation"
        }
    ],
    "sg:phone":"+1 740 397 8253",
    "sg:postcode":"43028",
    "sg:province":"OH",
    "sg:tags":[
        "commercial",
        "storage"
    ],
    "wof:name":"Centerburg Pack & Stack",
    "wof:placetype":"venue"
},
  "geometry": {"coordinates":[-82.337459,40.432276],"type":"Point"}
}