{
  "type": "Feature",
  "properties": {
    "addr:full": "481 King Beach Dr Howard OH 43028",
    "addr:housenumber": "481",
    "addr:postcode": "43028",
    "addr:street": "King Beach Dr",
    "iso:country": "US",
    "sg:address": "481 King Beach Dr",
    "sg:city": "Howard",
    "sg:classifiers": [
      {
        "category": "Freight",
        "type": "Transportation"
      }
    ],
    "sg:phone": "+1 740 397 8253",
    "sg:postcode": "43028",
    "sg:province": "OH",
    "sg:tags": [
      "commercial",
      "storage"
    ],
    "wof:name": "Centerburg Pack \u0026 Stack",
    "wof:placetype": "venue"
  },
  "geometry": {"coordinates":[-82.337459,40.432276],"type":"Point"}
}
