{
  "type": "Feature",
  "properties": {
    "addr:full": "123 S 3rd St Steubenville OH 43952",
    "addr:housenumber": "123",
    "addr:postcode": "43952",
    "addr:street": "S 3Rd St",
    "iso:country": "US",
    "sg:address": "123 S 3rd St",
    "sg:city": "Steubenville",
    "sg:classifiers": [
      {
        "category": "Government",
        "subcategory": "Office",
        "type": "Public Place"
      }
    ],
    "sg:phone": "+1 740 283 6026",
    "sg:postcode": "43952",
    "sg:province": "OH",
    "sg:tags": [
      "township",
      "government-city",
      "village"
    ],
    "sg:website": "http://www.uov.net",
    "wof:name": "Probation Officer",
    "wof:placetype": "venue"
  },
  "geometry": {"coordinates":[-80.613916,40.359039],"type":"Point"}
}
