{
  "type": "Feature",
  "properties": {
    "addr:full": "2487 Diamond Mill Rd Brookville OH 45309",
    "addr:housenumber": "2487",
    "addr:postcode": "45309",
    "addr:street": "Diamond Mill Rd",
    "iso:country": "US",
    "sg:address": "2487 Diamond Mill Rd",
    "sg:city": "Brookville",
    "sg:classifiers": [
      {
        "category": "Shopping",
        "subcategory": "Hobbies, Toys, \u0026 Games",
        "type": "Retail Goods"
      }
    ],
    "sg:phone": "+1 937 854 1809",
    "sg:postcode": "45309",
    "sg:province": "OH",
    "wof:name": "Just Horsen Around",
    "wof:placetype": "venue"
  },
  "geometry": {"coordinates":[-84.366782,39.781813],"type":"Point"}
}
