{
  "type": "Feature",
  "properties": {
    "addr:full": "5159 W Broad St Columbus OH 43228",
    "addr:housenumber": "5159",
    "addr:postcode": "43228",
    "addr:street": "W Broad St",
    "iso:country": "US",
    "sg:address": "5159 W Broad St",
    "sg:city": "Columbus",
    "sg:classifiers": [
      {
        "category": "Personal",
        "subcategory": "Beauty Salon",
        "type": "Services"
      }
    ],
    "sg:phone": "+1 614 870 8300",
    "sg:postcode": "43228",
    "sg:province": "OH",
    "wof:name": "D K Das Beauty Salon",
    "wof:placetype": "venue"
  },
  "geometry": {"coordinates":[-83.138433,39.951737],"type":"Point"}
}
