{
  "type": "Feature",
  "properties": {
    "addr:full": "21894 Lorain Rd Cleveland OH 44126",
    "addr:housenumber": "21894",
    "addr:postcode": "44126",
    "addr:street": "Lorain Rd",
    "iso:country": "US",
    "sg:address": "21894 Lorain Rd",
    "sg:city": "Cleveland",
    "sg:classifiers": [
      {
        "category": "Personal",
        "subcategory": "Beauty Salon",
        "type": "Services"
      }
    ],
    "sg:phone": "+1 440 331 4540",
    "sg:postcode": "44126",
    "sg:province": "OH",
    "wof:name": "Charles \u0026 John Hair Design",
    "wof:placetype": "venue"
  },
  "geometry": {"coordinates":[-81.86148,41.442812],"type":"Point"}
}
