{
  "type": "Feature",
  "properties": {
    "iso:country":"US",
    "sg:address":"21894 Lorain Rd",
    "sg:city":"Cleveland",
    "sg:classifiers":[
        {
            "category":"Personal",
            "subcategory":"Beauty Salon",
            "type":"Services"
        }
    ],
    "sg:phone":"+1 440 331 4540",
    "sg:postcode":"44126",
    "sg:province":"OH",
    "wof:name":"Charles & John Hair Design",
    "wof:placetype":"venue"
},
  "geometry": {"coordinates":[-81.86148,41.442812],"type":"Point"}
}