{
  "type": "Feature",
  "properties": {
    "iso:country":"US",
    "sg:address":"4857 Turney Rd",
    "sg:city":"Cleveland",
    "sg:classifiers":[
        {
            "category":"Retail",
            "subcategory":"Repair Shop",
            "type":"Services"
        }
    ],
    "sg:phone":"+1 216 641 9470",
    "sg:postcode":"44125",
    "sg:province":"OH",
    "sg:tags":[
        "television",
        "radio"
    ],
    "wof:name":"J & R TV Svc",
    "wof:placetype":"venue"
},
  "geometry": {"coordinates":[-81.614043,41.428205],"type":"Point"}
}