{
  "type": "Feature",
  "properties": {
    "iso:country":"US",
    "sg:address":"1911 N Fairfield Rd",
    "sg:city":"Dayton",
    "sg:classifiers":[
        {
            "category":"Health Services",
            "subcategory":"Doctor",
            "type":"Services"
        }
    ],
    "sg:phone":"+1 937 320 3888",
    "sg:postcode":"45432",
    "sg:province":"OH",
    "sg:tags":[
        "physician",
        "surgeon"
    ],
    "wof:name":"Primed Physicians",
    "wof:placetype":"venue"
},
  "geometry": {"coordinates":[-84.056247,39.744793],"type":"Point"}
}