{
  "type": "Feature",
  "properties": {
    "addr:full": "3360 New Germany Trebein Rd Dayton OH 45431",
    "addr:housenumber": "3360",
    "addr:postcode": "45431",
    "addr:street": "New Germany Trebein Rd",
    "iso:country": "US",
    "sg:address": "3360 New Germany Trebein Rd",
    "sg:city": "Dayton",
    "sg:classifiers": [
      {
        "category": "Shopping",
        "subcategory": "Department Store",
        "type": "Retail Goods"
      }
    ],
    "sg:phone": "+1 937 426 8227",
    "sg:postcode": "45431",
    "sg:province": "OH",
    "sg:tags": [
      "discount"
    ],
    "sg:website": "www.walmart.com",
    "wof:name": "Wal-Mart",
    "wof:placetype": "venue"
  },
  "geometry": {"coordinates":[-84.059234,39.771482],"type":"Point"}
}
