{
  "type": "Feature",
  "properties": {
    "addr:full": "3116 Kriner Rd Gallipolis OH 45631",
    "addr:housenumber": "3116",
    "addr:postcode": "45631",
    "addr:street": "Kriner Rd",
    "iso:country": "US",
    "sg:address": "3116 Kriner Rd",
    "sg:city": "Gallipolis",
    "sg:classifiers": [
      {
        "category": "Building \u0026 Trades",
        "subcategory": "Construction",
        "type": "Services"
      }
    ],
    "sg:phone": "+1 740 446 2156",
    "sg:postcode": "45631",
    "sg:province": "OH",
    "sg:tags": [
      "house"
    ],
    "wof:name": "Franklin Construction",
    "wof:placetype": "venue"
  },
  "geometry": {"coordinates":[-82.239652,38.758725],"type":"Point"}
}
