{
  "type": "Feature",
  "properties": {
    "iso:country":"US",
    "sg:address":"3116 Kriner Rd",
    "sg:city":"Gallipolis",
    "sg:classifiers":[
        {
            "category":"Building & Trades",
            "subcategory":"Construction",
            "type":"Services"
        }
    ],
    "sg:phone":"+1 740 446 2156",
    "sg:postcode":"45631",
    "sg:province":"OH",
    "sg:tags":[
        "house"
    ],
    "wof:name":"Franklin Construction",
    "wof:placetype":"venue"
},
  "geometry": {"coordinates":[-82.23965200000001,38.758725],"type":"Point"}
}