{
  "type": "Feature",
  "properties": {
    "addr:full": "6570 Rugosa Ave Reynoldsburg OH 43068",
    "addr:housenumber": "6570",
    "addr:postcode": "43068",
    "addr:street": "Rugosa Ave",
    "iso:country": "US",
    "sg:address": "6570 Rugosa Ave",
    "sg:city": "Reynoldsburg",
    "sg:classifiers": [
      {
        "category": "Wholesale",
        "subcategory": "Electrical",
        "type": "Manufacturing \u0026 Wholesale Goods"
      }
    ],
    "sg:phone": "+1 614 863 1199",
    "sg:postcode": "43068",
    "sg:province": "OH",
    "sg:tags": [
      "electronic"
    ],
    "wof:name": "Koebel Distribution",
    "wof:placetype": "venue"
  },
  "geometry": {"coordinates":[-82.824382,39.973308],"type":"Point"}
}
