{
  "type": "Feature",
  "properties": {
    "addr:full": "31711 Tower Rd Salem OH 44460",
    "addr:housenumber": "31711",
    "addr:postcode": "44460",
    "addr:street": "Tower Rd",
    "iso:country": "US",
    "sg:address": "31711 Tower Rd",
    "sg:city": "Salem",
    "sg:classifiers": [
      {
        "category": "Professional",
        "type": "Services"
      }
    ],
    "sg:phone": "+1 330 222 2131",
    "sg:postcode": "44460",
    "sg:province": "OH",
    "wof:name": "Michel A Voytek",
    "wof:placetype": "venue"
  },
  "geometry": {"coordinates":[-80.899825,40.849673],"type":"Point"}
}
