{
  "type": "Feature",
  "properties": {
    "iso:country":"US",
    "sg:address":"200 Broadway St",
    "sg:city":"Jackson",
    "sg:classifiers":[
        {
            "category":"Government",
            "subcategory":"Office",
            "type":"Public Place"
        }
    ],
    "sg:phone":"+1 740 286 2838",
    "sg:postcode":"45640",
    "sg:province":"OH",
    "sg:tags":[
        "program",
        "state",
        "adm"
    ],
    "wof:name":"Economic Development",
    "wof:placetype":"venue"
},
  "geometry": {"coordinates":[-82.636961,39.051975],"type":"Point"}
}