{
  "type": "Feature",
  "properties": {
    "addr:full": "1015 Illinois Ave Maumee OH 43537",
    "addr:housenumber": "1015",
    "addr:postcode": "43537",
    "addr:street": "Illinois Ave",
    "iso:country": "US",
    "sg:address": "1015 Illinois Ave",
    "sg:city": "Maumee",
    "sg:classifiers": [
      {
        "category": "Wholesale",
        "subcategory": "Petroleum",
        "type": "Manufacturing \u0026 Wholesale Goods"
      }
    ],
    "sg:phone": "+1 419 893 3358",
    "sg:postcode": "43537",
    "sg:province": "OH",
    "sg:tags": [
      "pipe",
      "line",
      "company"
    ],
    "wof:name": "Panhandle Eastern Pipeline Co",
    "wof:placetype": "venue"
  },
  "geometry": {"coordinates":[-83.686633,41.570979],"type":"Point"}
}
