{
  "type": "Feature",
  "properties": {
    "addr:full":"1556 E 105th St Cleveland OH 44106",
    "addr:housenumber":"1556",
    "addr:postcode":"44106",
    "addr:street":"E 105Th St",
    "iso:country":"US",
    "sg:address":"1556 E 105th St",
    "sg:city":"Cleveland",
    "sg:classifiers":[
        {
            "category":"Personal",
            "subcategory":"Barber",
            "type":"Services"
        }
    ],
    "sg:phone":"+1 216 721 5869",
    "sg:postcode":"44106",
    "sg:province":"OH",
    "wof:name":"Wills Barber Shop",
    "wof:placetype":"venue"
},
  "geometry": {"coordinates":[-81.61547899999999,41.513112],"type":"Point"}
}