{
  "type": "Feature",
  "properties": {
    "addr:full":"8208 Erie St Sylvania OH 43560",
    "addr:housenumber":"8208",
    "addr:postcode":"43560",
    "addr:street":"Erie St",
    "iso:country":"US",
    "sg:address":"8208 Erie St",
    "sg:city":"Sylvania",
    "sg:classifiers":[
        {
            "category":"Professional",
            "type":"Services"
        }
    ],
    "sg:phone":"+1 419 824 8422",
    "sg:postcode":"43560",
    "sg:province":"OH",
    "wof:name":"Jcj Motorsports Inc",
    "wof:placetype":"venue"
},
  "geometry": {"coordinates":[-83.742351,41.717292],"type":"Point"}
}