{
  "type": "Feature",
  "properties": {
    "addr:full": "223 W Main St Ravenna OH 44266",
    "addr:housenumber": "223",
    "addr:postcode": "44266",
    "addr:street": "W Main St",
    "iso:country": "US",
    "sg:address": "223 W Main St",
    "sg:city": "Ravenna",
    "sg:classifiers": [
      {
        "category": "Social Services",
        "type": "Services"
      }
    ],
    "sg:phone": "+1 330 296 3255",
    "sg:postcode": "44266",
    "sg:province": "OH",
    "wof:name": "Townhall II Inc",
    "wof:placetype": "venue"
  },
  "geometry": {"coordinates":[-81.244614,41.157657],"type":"Point"}
}
