{
  "type": "Feature",
  "properties": {
    "addr:full":"5457 Timbercreek Ln Stow OH 44224",
    "addr:housenumber":"5457",
    "addr:postcode":"44224",
    "addr:street":"Timbercreek Ln",
    "iso:country":"US",
    "sg:address":"5457 Timbercreek Ln",
    "sg:city":"Stow",
    "sg:classifiers":[
        {
            "category":"Building & Trades",
            "subcategory":"Construction",
            "type":"Services"
        }
    ],
    "sg:phone":"+1 330 650 5959",
    "sg:postcode":"44224",
    "sg:province":"OH",
    "sg:tags":[
        "house"
    ],
    "wof:name":"Timber Creek",
    "wof:placetype":"venue"
},
  "geometry": {"coordinates":[-81.395803,41.200699],"type":"Point"}
}