{
  "type": "Feature",
  "properties": {
    "addr:full": "1224 Elm St Middletown OH 45044",
    "addr:housenumber": "1224",
    "addr:postcode": "45044",
    "addr:street": "Elm St",
    "iso:country": "US",
    "sg:address": "1224 Elm St",
    "sg:city": "Middletown",
    "sg:classifiers": [
      {
        "category": "Food \u0026 Beverages",
        "subcategory": "Groceries \u0026 Convenience Stores",
        "type": "Retail Goods"
      }
    ],
    "sg:phone": "+1 513 420 0711",
    "sg:postcode": "45044",
    "sg:province": "OH",
    "wof:name": "Ticos Food For All Occasions",
    "wof:placetype": "venue"
  },
  "geometry": {"coordinates":[-84.408245,39.502712],"type":"Point"}
}
