{
  "type": "Feature",
  "properties": {
    "addr:full":"525 N Erie St Toledo OH 43604",
    "addr:housenumber":"525",
    "addr:postcode":"43604",
    "addr:street":"N Erie St",
    "iso:country":"US",
    "sg:address":"525 N Erie St",
    "sg:city":"Toledo",
    "sg:classifiers":[
        {
            "category":"Government",
            "subcategory":"Police Station",
            "type":"Public Place"
        }
    ],
    "sg:phone":"+1 419 245 3226",
    "sg:postcode":"43604",
    "sg:province":"OH",
    "sg:tags":[
        "department"
    ],
    "sg:website":"www.toledopolice.com",
    "wof:name":"Police Div-Internal Affairs",
    "wof:placetype":"venue"
},
  "geometry": {"coordinates":[-83.535284,41.655761],"type":"Point"}
}