{
  "type": "Feature",
  "properties": {
    "iso:country":"US",
    "sg:address":"13960 Rock Creek Rd",
    "sg:city":"Chardon",
    "sg:classifiers":[
        {
            "category":"Restaurant",
            "type":"Food & Drink"
        }
    ],
    "sg:phone":"+1 440 286 6661",
    "sg:postcode":"44024",
    "sg:province":"OH",
    "wof:name":"Hambden Country Inn",
    "wof:placetype":"venue"
},
  "geometry": {"coordinates":[-81.13666499999999,41.612285],"type":"Point"}
}