{
  "type": "Feature",
  "properties": {
    "addr:full": "13960 Rock Creek Rd Chardon OH 44024",
    "addr:housenumber": "13960",
    "addr:postcode": "44024",
    "addr:street": "Rock Creek Rd",
    "iso:country": "US",
    "sg:address": "13960 Rock Creek Rd",
    "sg:city": "Chardon",
    "sg:classifiers": [
      {
        "category": "Restaurant",
        "type": "Food \u0026 Drink"
      }
    ],
    "sg:phone": "+1 440 286 6661",
    "sg:postcode": "44024",
    "sg:province": "OH",
    "wof:name": "Hambden Country Inn",
    "wof:placetype": "venue"
  },
  "geometry": {"coordinates":[-81.136665,41.612285],"type":"Point"}
}
