{
  "type": "Feature",
  "properties": {
    "addr:full": "1772 Lyndhurst Rd Cleveland OH 44124",
    "addr:housenumber": "1772",
    "addr:postcode": "44124",
    "addr:street": "Lyndhurst Rd",
    "iso:country": "US",
    "sg:address": "1772 Lyndhurst Rd",
    "sg:city": "Cleveland",
    "sg:classifiers": [
      {
        "category": "Building \u0026 Trades",
        "subcategory": "Electrical",
        "type": "Services"
      }
    ],
    "sg:phone": "+1 440 449 3043",
    "sg:postcode": "44124",
    "sg:province": "OH",
    "sg:tags": [
      "electrical",
      "contractor"
    ],
    "wof:name": "Angie Electric Inc",
    "wof:placetype": "venue"
  },
  "geometry": {"coordinates":[-81.478219,41.514411],"type":"Point"}
}
