{
  "type": "Feature",
  "properties": {
    "iso:country":"US",
    "sg:address":"312 N Wayne St",
    "sg:city":"Piqua",
    "sg:classifiers":[
        {
            "category":"Professional",
            "subcategory":"Secretarial Services",
            "type":"Services"
        }
    ],
    "sg:phone":"+1 937 615 0039",
    "sg:postcode":"45356",
    "sg:province":"OH",
    "sg:tags":[
        "reporting",
        "court"
    ],
    "wof:name":"Excel Medical Data Svc",
    "wof:placetype":"venue"
},
  "geometry": {"coordinates":[-84.241081,40.14878],"type":"Point"}
}