{
  "type": "Feature",
  "properties": {
    "addr:full": "18581 Divelbiss Rd Fredericktown OH 43019",
    "addr:postcode": "18581;43019",
    "addr:street": "Divelbiss Rd",
    "iso:country": "US",
    "sg:address": "18581 Divelbiss Rd",
    "sg:city": "Fredericktown",
    "sg:classifiers": [
      {
        "category": "Retail",
        "subcategory": "Repair Shop",
        "type": "Services"
      }
    ],
    "sg:phone": "+1 740 694 0000",
    "sg:postcode": "43019",
    "sg:province": "OH",
    "sg:tags": [
      "welding"
    ],
    "wof:name": "Complete Metal Svc Inc",
    "wof:placetype": "venue"
  },
  "geometry": {"coordinates":[-82.446423,40.50663],"type":"Point"}
}
