{
  "type": "Feature",
  "properties": {
    "addr:full": "3031 Yorkshire Rd Cleveland OH 44118",
    "addr:housenumber": "3031",
    "addr:postcode": "44118",
    "addr:street": "Yorkshire Rd",
    "iso:country": "US",
    "sg:address": "3031 Yorkshire Rd",
    "sg:city": "Cleveland",
    "sg:classifiers": [
      {
        "category": "Building \u0026 Trades",
        "subcategory": "Construction",
        "type": "Services"
      }
    ],
    "sg:phone": "+1 216 321 5031",
    "sg:postcode": "44118",
    "sg:province": "OH",
    "sg:tags": [
      "house"
    ],
    "wof:name": "Yorkshire Builders Inc",
    "wof:placetype": "venue"
  },
  "geometry": {"coordinates":[-81.573625,41.504138],"type":"Point"}
}
