{
  "type": "Feature",
  "properties": {
    "iso:country":"US",
    "sg:address":"5790 Co Hwy 30",
    "sg:city":"Upper Sandusky",
    "sg:classifiers":[
        {
            "category":"Home & Garden",
            "subcategory":"Furniture",
            "type":"Retail Goods"
        }
    ],
    "sg:phone":"+1 419 294 2471",
    "sg:postcode":"43338",
    "sg:province":"OH",
    "wof:name":"Fine Furniture Gallery",
    "wof:placetype":"venue"
},
  "geometry": {"coordinates":[-82.843123,40.564577],"type":"Point"}
}