{
  "type": "Feature",
  "properties": {
    "addr:full":"19200 Roseland Ave Cleveland OH 44117",
    "addr:housenumber":"19200",
    "addr:postcode":"44117",
    "addr:street":"Roseland Ave",
    "iso:country":"US",
    "sg:address":"19200 Roseland Ave",
    "sg:city":"Cleveland",
    "sg:classifiers":[
        {
            "category":"Personal",
            "subcategory":"Beauty Salon",
            "type":"Services"
        }
    ],
    "sg:phone":"+1 216 481 3621",
    "sg:postcode":"44117",
    "sg:province":"OH",
    "wof:name":"Driven To You Barber/Stylist",
    "wof:placetype":"venue"
},
  "geometry": {"coordinates":[-81.55037299999999,41.56322],"type":"Point"}
}