{
  "type": "Feature",
  "properties": {
    "iso:country":"US",
    "sg:address":"1030 Cutter St",
    "sg:city":"Cincinnati",
    "sg:classifiers":[
        {
            "category":"Education",
            "subcategory":"School",
            "type":"Public Place"
        }
    ],
    "sg:phone":"+1 513 357 8550",
    "sg:postcode":"45203",
    "sg:province":"OH",
    "wof:name":"Porter Middle School",
    "wof:placetype":"venue"
},
  "geometry": {"coordinates":[-84.525671,39.105953],"type":"Point"}
}