{
  "type": "Feature",
  "properties": {
    "iso:country":"US",
    "sg:address":"1481 Warrensville Center Rd",
    "sg:city":"Cleveland",
    "sg:classifiers":[
        {
            "category":"Professional",
            "subcategory":"Accounting & Tax Preparation",
            "type":"Services"
        }
    ],
    "sg:phone":"+1 216 381 8319",
    "sg:postcode":"44121",
    "sg:province":"OH",
    "sg:tags":[
        "accountant"
    ],
    "wof:name":"N Trifon Poparad CPA",
    "wof:placetype":"venue"
},
  "geometry": {"coordinates":[-81.536379,41.519267],"type":"Point"}
}