{
  "type": "Feature",
  "properties": {
    "iso:country":"US",
    "sg:address":"332 S Preston St",
    "sg:city":"Centerburg",
    "sg:phone":"+1 740 625 6066",
    "sg:postcode":"43011",
    "sg:province":"OH",
    "sg:tags":[
        "farm",
        "grain",
        "cash"
    ],
    "wof:name":"Scott Jeffrey",
    "wof:placetype":"venue"
},
  "geometry": {"coordinates":[-82.69444300000001,40.298267],"type":"Point"}
}