{
  "type": "Feature",
  "properties": {
    "addr:full": "332 S Preston St Centerburg OH 43011",
    "addr:housenumber": "332",
    "addr:postcode": "43011",
    "addr:street": "S Preston St",
    "iso:country": "US",
    "sg:address": "332 S Preston St",
    "sg:city": "Centerburg",
    "sg:phone": "+1 740 625 6066",
    "sg:postcode": "43011",
    "sg:province": "OH",
    "sg:tags": [
      "farm",
      "grain",
      "cash"
    ],
    "wof:name": "Scott Jeffrey",
    "wof:placetype": "venue"
  },
  "geometry": {"coordinates":[-82.694443,40.298267],"type":"Point"}
}
