{
  "type": "Feature",
  "properties": {
    "iso:country":"US",
    "sg:address":"6100 Oak Tree Blvd",
    "sg:city":"Cleveland",
    "sg:classifiers":[
        {
            "category":"Insurance",
            "subcategory":"Health Insurance",
            "type":"Services"
        }
    ],
    "sg:phone":"+1 216 447 5040",
    "sg:postcode":"44131",
    "sg:province":"OH",
    "sg:tags":[
        "annuity",
        "life",
        "accident",
        "group",
        "provider"
    ],
    "wof:name":"Great-West Healthcare",
    "wof:placetype":"venue"
},
  "geometry": {"coordinates":[-81.661233,41.398296],"type":"Point"}
}