{
  "type": "Feature",
  "properties": {
    "addr:full":"246 High St Hamilton OH 45011",
    "addr:housenumber":"246",
    "addr:postcode":"45011",
    "addr:street":"High St",
    "iso:country":"US",
    "sg:address":"246 High St",
    "sg:city":"Hamilton",
    "sg:classifiers":[
        {
            "category":"Banks & Credit Unions",
            "subcategory":"Investment Brokerage",
            "type":"Services"
        }
    ],
    "sg:phone":"+1 513 863 0886",
    "sg:postcode":"45011",
    "sg:province":"OH",
    "sg:tags":[
        "stock",
        "bond"
    ],
    "wof:name":"Smith Barney",
    "wof:placetype":"venue"
},
  "geometry": {"coordinates":[-84.5609,39.399644],"type":"Point"}
}