{
  "type": "Feature",
  "properties": {
    "iso:country":"US",
    "sg:address":"4073 Silver Springs Ln",
    "sg:city":"Columbus",
    "sg:classifiers":[
        {
            "category":"Sports & Exercise",
            "subcategory":"Golf",
            "type":"Entertainment"
        }
    ],
    "sg:phone":"+1 614 472 3586",
    "sg:postcode":"43230",
    "sg:province":"OH",
    "sg:tags":[
        "course"
    ],
    "wof:name":"Golf 4A Cause",
    "wof:placetype":"venue"
},
  "geometry": {"coordinates":[-82.91250100000001,40.063221],"type":"Point"}
}