{
  "type": "Feature",
  "properties": {
    "iso:country":"US",
    "sg:address":"601 S 30th St",
    "sg:city":"Newark",
    "sg:classifiers":[
        {
            "category":"Retail",
            "subcategory":"Repair Shop",
            "type":"Services"
        }
    ],
    "sg:phone":"+1 740 366 7587",
    "sg:postcode":"43056",
    "sg:province":"OH",
    "sg:tags":[
        "appliance"
    ],
    "wof:name":"Beish Services",
    "wof:placetype":"venue"
},
  "geometry": {"coordinates":[-82.44289499999999,40.034974],"type":"Point"}
}