{
  "type": "Feature",
  "properties": {
    "iso:country":"US",
    "sg:address":"576 Pamlico St",
    "sg:city":"Columbus",
    "sg:classifiers":[
        {
            "category":"Organizations",
            "subcategory":"Religious Organization",
            "type":"Services"
        }
    ],
    "sg:phone":"+1 614 851 3157",
    "sg:postcode":"43228",
    "sg:province":"OH",
    "sg:tags":[
        "reach",
        "ministry"
    ],
    "wof:name":"Hanna Ministries",
    "wof:placetype":"venue"
},
  "geometry": {"coordinates":[-83.14851,39.936351],"type":"Point"}
}