{
  "type": "Feature",
  "properties": {
    "addr:full": "576 Pamlico St Columbus OH 43228",
    "addr:housenumber": "576",
    "addr:postcode": "43228",
    "addr:street": "Pamlico St",
    "iso:country": "US",
    "sg:address": "576 Pamlico St",
    "sg:city": "Columbus",
    "sg:classifiers": [
      {
        "category": "Organizations",
        "subcategory": "Religious Organization",
        "type": "Services"
      }
    ],
    "sg:phone": "+1 614 851 3157",
    "sg:postcode": "43228",
    "sg:province": "OH",
    "sg:tags": [
      "reach",
      "ministry"
    ],
    "wof:name": "Hanna Ministries",
    "wof:placetype": "venue"
  },
  "geometry": {"coordinates":[-83.14851,39.936351],"type":"Point"}
}
