{
  "type": "Feature",
  "properties": {
    "iso:country":"US",
    "sg:address":"2755 Snouffer Rd",
    "sg:city":"Columbus",
    "sg:classifiers":[
        {
            "category":"Building & Trades",
            "subcategory":"Construction",
            "type":"Services"
        }
    ],
    "sg:phone":"+1 614 734 9619",
    "sg:postcode":"43235",
    "sg:province":"OH",
    "sg:tags":[
        "builder",
        "patio",
        "deck"
    ],
    "wof:name":"Imperial Pavers",
    "wof:placetype":"venue"
},
  "geometry": {"coordinates":[-83.06367,40.103818],"type":"Point"}
}