{
  "type": "Feature",
  "properties": {
    "addr:full": "3740 Euclid Ave Cleveland OH 44115",
    "addr:housenumber": "3740",
    "addr:postcode": "44115",
    "addr:street": "Euclid Ave",
    "iso:country": "US",
    "sg:address": "3740 Euclid Ave",
    "sg:city": "Cleveland",
    "sg:classifiers": [
      {
        "category": "Banks \u0026 Credit Unions",
        "subcategory": "Bank",
        "type": "Services"
      }
    ],
    "sg:phone": "+1 216 881 6800",
    "sg:postcode": "44115",
    "sg:province": "OH",
    "sg:tags": [
      "company",
      "finance",
      "lease"
    ],
    "wof:name": "Citicapital Coml Lsg Corp",
    "wof:placetype": "venue"
  },
  "geometry": {"coordinates":[-81.659189,41.50331],"type":"Point"}
}
