{
  "type": "Feature",
  "properties": {
    "addr:full": "9758 State Rte 774 Hamersville OH 45130",
    "addr:housenumber": "9758",
    "addr:postcode": "45130",
    "addr:street": "State Rte 774",
    "iso:country": "US",
    "sg:address": "9758 State Rte 774",
    "sg:city": "Hamersville",
    "sg:classifiers": [
      {
        "category": "Professional",
        "subcategory": "Computer Services",
        "type": "Services"
      }
    ],
    "sg:phone": "+1 937 379 0307",
    "sg:postcode": "45130",
    "sg:province": "OH",
    "wof:name": "I T Solutions Inc",
    "wof:placetype": "venue"
  },
  "geometry": {"coordinates":[-84.028199,38.906929],"type":"Point"}
}
