{
  "type": "Feature",
  "properties": {
    "iso:country":"US",
    "sg:address":"74 West St",
    "sg:city":"Akron",
    "sg:classifiers":[
        {
            "category":"Personal",
            "subcategory":"Beauty Salon",
            "type":"Services"
        }
    ],
    "sg:phone":"+1 330 633 0877",
    "sg:postcode":"44303",
    "sg:province":"OH",
    "sg:tags":[
        "manicuring"
    ],
    "wof:name":"Bello Zazzera Hair & Nail",
    "wof:placetype":"venue"
},
  "geometry": {"coordinates":[-81.524378,41.090852],"type":"Point"}
}