{
  "type": "Feature",
  "properties": {
    "iso:country":"US",
    "sg:address":"2678 Westbreeze Dr",
    "sg:city":"Hilliard",
    "sg:classifiers":[
        {
            "category":"Professional",
            "type":"Services"
        }
    ],
    "sg:phone":"+1 614 527 1015",
    "sg:postcode":"43026",
    "sg:province":"OH",
    "wof:name":"Christinas Designs",
    "wof:placetype":"venue"
},
  "geometry": {"coordinates":[-83.149191,40.005407],"type":"Point"}
}