{
  "type": "Feature",
  "properties": {
    "addr:full": "908 Raymond St Akron OH 44307",
    "addr:housenumber": "908",
    "addr:postcode": "44307",
    "addr:street": "Raymond St",
    "iso:country": "US",
    "sg:address": "908 Raymond St",
    "sg:city": "Akron",
    "sg:classifiers": [
      {
        "category": "Food \u0026 Beverages",
        "subcategory": "Groceries \u0026 Convenience Stores",
        "type": "Retail Goods"
      }
    ],
    "sg:phone": "+1 330 253 0911",
    "sg:postcode": "44307",
    "sg:province": "OH",
    "wof:name": "No Limit Food Mart",
    "wof:placetype": "venue"
  },
  "geometry": {"coordinates":[-81.541073,41.069757],"type":"Point"}
}
