{
  "type": "Feature",
  "properties": {
    "iso:country":"US",
    "sg:address":"204 N Apple St",
    "sg:city":"Georgetown",
    "sg:classifiers":[
        {
            "category":"Manufacturing",
            "subcategory":"Furniture",
            "type":"Manufacturing & Wholesale Goods"
        }
    ],
    "sg:phone":"+1 937 378 4472",
    "sg:postcode":"45121",
    "sg:province":"OH",
    "sg:tags":[
        "manufacture",
        "custom",
        "casework",
        "commercial",
        "cabinet"
    ],
    "wof:name":"Case Design",
    "wof:placetype":"venue"
},
  "geometry": {"coordinates":[-83.90325900000001,38.867503],"type":"Point"}
}