{
  "type": "Feature",
  "properties": {
    "addr:full": "204 N Apple St Georgetown OH 45121",
    "addr:housenumber": "204",
    "addr:postcode": "45121",
    "addr:street": "N Apple St",
    "iso:country": "US",
    "sg:address": "204 N Apple St",
    "sg:city": "Georgetown",
    "sg:classifiers": [
      {
        "category": "Manufacturing",
        "subcategory": "Furniture",
        "type": "Manufacturing \u0026 Wholesale Goods"
      }
    ],
    "sg:phone": "+1 937 378 4472",
    "sg:postcode": "45121",
    "sg:province": "OH",
    "sg:tags": [
      "manufacture",
      "custom",
      "casework",
      "commercial",
      "cabinet"
    ],
    "wof:name": "Case Design",
    "wof:placetype": "venue"
  },
  "geometry": {"coordinates":[-83.903259,38.867503],"type":"Point"}
}
