{
  "type": "Feature",
  "properties": {
    "addr:full": "7454 W Chester Rd West Chester OH 45069",
    "addr:housenumber": "7454",
    "addr:postcode": "45069",
    "addr:street": "W Chester Rd",
    "iso:country": "US",
    "sg:address": "7454 W Chester Rd",
    "sg:city": "West Chester",
    "sg:classifiers": [
      {
        "category": "Freight",
        "type": "Transportation"
      }
    ],
    "sg:phone": "+1 513 755 3555",
    "sg:postcode": "45069",
    "sg:province": "OH",
    "sg:tags": [
      "storage"
    ],
    "wof:name": "West Chester-Mason Store-Lock",
    "wof:placetype": "venue"
  },
  "geometry": {"coordinates":[-84.381017,39.320212],"type":"Point"}
}
