{
  "type": "Feature",
  "properties": {
    "addr:full":"11008 Kinsman Rd Newbury OH 44065",
    "addr:housenumber":"11008",
    "addr:postcode":"44065",
    "addr:street":"Kinsman Rd",
    "iso:country":"US",
    "sg:address":"11008 Kinsman Rd",
    "sg:city":"Newbury",
    "sg:classifiers":[
        {
            "category":"Organizations",
            "subcategory":"Community Association",
            "type":"Services"
        }
    ],
    "sg:phone":"+1 440 564 5565",
    "sg:postcode":"44065",
    "sg:province":"OH",
    "sg:tags":[
        "club"
    ],
    "wof:name":"Newbury Legion Post",
    "wof:placetype":"venue"
},
  "geometry": {"coordinates":[-81.261875,41.463256],"type":"Point"}
}