{
  "type": "Feature",
  "properties": {
    "iso:country":"US",
    "sg:address":"35459 Salem Grange Rd",
    "sg:city":"Salem",
    "sg:classifiers":[
        {
            "category":"Organizations",
            "subcategory":"Religious Organization",
            "type":"Services"
        }
    ],
    "sg:phone":"+1 330 332 4467",
    "sg:postcode":"44460",
    "sg:province":"OH",
    "sg:tags":[
        "church"
    ],
    "wof:name":"Phillips Christian Church",
    "wof:placetype":"venue"
},
  "geometry": {"coordinates":[-80.834379,40.856958],"type":"Point"}
}