{
  "type": "Feature",
  "properties": {
    "addr:full":"4345 Secor Rd Toledo OH 43623",
    "addr:housenumber":"4345",
    "addr:postcode":"43623",
    "addr:street":"Secor Rd",
    "iso:country":"US",
    "sg:address":"4345 Secor Rd",
    "sg:city":"Toledo",
    "sg:classifiers":[
        {
            "category":"Social Services",
            "type":"Services"
        }
    ],
    "sg:phone":"+1 419 868 0290",
    "sg:postcode":"43623",
    "sg:province":"OH",
    "sg:tags":[
        "instruction",
        "health",
        "care"
    ],
    "wof:name":"Caring SERVICE-Dme",
    "wof:placetype":"venue"
},
  "geometry": {"coordinates":[-83.623473,41.697733],"type":"Point"}
}