{
  "type": "Feature",
  "properties": {
    "addr:full": "30609 Ronald Dr Willowick OH 44095",
    "addr:postcode": "30609;44095",
    "addr:street": "Ronald Dr",
    "iso:country": "US",
    "sg:address": "30609 Ronald Dr",
    "sg:city": "Willowick",
    "sg:classifiers": [
      {
        "category": "Shopping",
        "subcategory": "Computers \u0026 Home Electronics",
        "type": "Retail Goods"
      }
    ],
    "sg:phone": "+1 440 944 8631",
    "sg:postcode": "44095",
    "sg:province": "OH",
    "sg:tags": [
      "software"
    ],
    "wof:name": "Integrated Systems Development",
    "wof:placetype": "venue"
  },
  "geometry": {"coordinates":[-81.462102,41.630121],"type":"Point"}
}
