{
  "type": "Feature",
  "properties": {
    "addr:full": "7510 Slate Ridge Blvd Reynoldsburg OH 43068",
    "addr:housenumber": "7510",
    "addr:postcode": "43068",
    "addr:street": "Slate Ridge Blvd",
    "iso:country": "US",
    "sg:address": "7510 Slate Ridge Blvd",
    "sg:city": "Reynoldsburg",
    "sg:classifiers": [
      {
        "category": "Banks \u0026 Credit Unions",
        "subcategory": "Bank",
        "type": "Services"
      }
    ],
    "sg:phone": "+1 614 575 2599",
    "sg:postcode": "43068",
    "sg:province": "OH",
    "sg:tags": [
      "mortgage",
      "loan",
      "broker",
      "real estate"
    ],
    "wof:name": "Amerimac Mortgage Inc",
    "wof:placetype": "venue"
  },
  "geometry": {"coordinates":[-82.791238,39.944861],"type":"Point"}
}
