{
  "type": "Feature",
  "properties": {
    "addr:full": "30143 Lake Rd Bay Village OH 44140",
    "addr:housenumber": "30143",
    "addr:postcode": "44140",
    "addr:street": "Lake Rd",
    "iso:country": "US",
    "sg:address": "30143 Lake Rd",
    "sg:city": "Bay Village",
    "sg:classifiers": [
      {
        "category": "Building \u0026 Trades",
        "subcategory": "Plumbing",
        "type": "Services"
      }
    ],
    "sg:phone": "+1 440 871 1112",
    "sg:postcode": "44140",
    "sg:province": "OH",
    "sg:tags": [
      "plumbing",
      "contractor"
    ],
    "wof:name": "Killeen Plumbing",
    "wof:placetype": "venue"
  },
  "geometry": {"coordinates":[-81.953762,41.494695],"type":"Point"}
}
