{
  "type": "Feature",
  "properties": {
    "iso:country":"US",
    "sg:address":"30143 Lake Rd",
    "sg:city":"Bay Village",
    "sg:classifiers":[
        {
            "category":"Building & Trades",
            "subcategory":"Plumbing",
            "type":"Services"
        }
    ],
    "sg:phone":"+1 440 871 1112",
    "sg:postcode":"44140",
    "sg:province":"OH",
    "sg:tags":[
        "plumbing",
        "contractor"
    ],
    "wof:name":"Killeen Plumbing",
    "wof:placetype":"venue"
},
  "geometry": {"coordinates":[-81.953762,41.494695],"type":"Point"}
}