{
  "type": "Feature",
  "properties": {
    "addr:full": "10924 Smoky Row Rd Georgetown OH 45121",
    "addr:housenumber": "10924",
    "addr:postcode": "45121",
    "addr:street": "Smoky Row Rd",
    "iso:country": "US",
    "sg:address": "10924 Smoky Row Rd",
    "sg:city": "Georgetown",
    "sg:classifiers": [
      {
        "category": "Manufacturing",
        "subcategory": "Tools \u0026 Machinery",
        "type": "Manufacturing \u0026 Wholesale Goods"
      }
    ],
    "sg:phone": "+1 937 379 2145",
    "sg:postcode": "45121",
    "sg:province": "OH",
    "sg:tags": [
      "industrial",
      "mfg"
    ],
    "wof:name": "Truitt Custom Machine",
    "wof:placetype": "venue"
  },
  "geometry": {"coordinates":[-83.93855,38.93529],"type":"Point"}
}
