{
  "type": "Feature",
  "properties": {
    "iso:country":"US",
    "sg:address":"5300 Majestic Pkwy",
    "sg:city":"Bedford",
    "sg:classifiers":[
        {
            "category":"Wholesale",
            "subcategory":"Metals & Minerals",
            "type":"Manufacturing & Wholesale Goods"
        }
    ],
    "sg:phone":"+1 440 786 2666",
    "sg:postcode":"44146",
    "sg:province":"OH",
    "sg:tags":[
        "center"
    ],
    "wof:name":"Majestic Steel Usa Inc",
    "wof:placetype":"venue"
},
  "geometry": {"coordinates":[-81.50536700000001,41.412557],"type":"Point"}
}