{
  "type": "Feature",
  "properties": {
    "addr:full":"6678 Jackson Pike Lockbourne OH 43137",
    "addr:housenumber":"6678",
    "addr:postcode":"43137",
    "addr:street":"Jackson Pike",
    "iso:country":"US",
    "sg:address":"6678 Jackson Pike",
    "sg:city":"Lockbourne",
    "sg:classifiers":[
        {
            "category":"Freight",
            "type":"Transportation"
        }
    ],
    "sg:phone":"+1 614 871 9970",
    "sg:postcode":"43137",
    "sg:province":"OH",
    "sg:tags":[
        "operator",
        "trucking"
    ],
    "wof:name":"Reeves Trucking Inc",
    "wof:placetype":"venue"
},
  "geometry": {"coordinates":[-83.03257499999999,39.82537],"type":"Point"}
}