{
  "type": "Feature",
  "properties": {
    "addr:full": "7869 Mentor Ave Mentor OH 44060",
    "addr:housenumber": "7869",
    "addr:postcode": "44060",
    "addr:street": "Mentor Ave",
    "iso:country": "US",
    "sg:address": "7869 Mentor Ave",
    "sg:city": "Mentor",
    "sg:classifiers": [
      {
        "category": "Professional",
        "subcategory": "Employment Agencies",
        "type": "Services"
      }
    ],
    "sg:phone": "+1 440 205 8384",
    "sg:postcode": "44060",
    "sg:province": "OH",
    "sg:tags": [
      "help",
      "contractor"
    ],
    "wof:name": "Champion Personnel Systems Inc",
    "wof:placetype": "venue"
  },
  "geometry": {"coordinates":[-81.362536,41.660686],"type":"Point"}
}
