{
  "type": "Feature",
  "properties": {
    "addr:full":"3937 Beulah Rd Columbus OH 43224",
    "addr:housenumber":"3937",
    "addr:postcode":"43224",
    "addr:street":"Beulah Rd",
    "iso:country":"US",
    "sg:address":"3937 Beulah Rd",
    "sg:city":"Columbus",
    "sg:classifiers":[
        {
            "category":"Building & Trades",
            "subcategory":"Construction",
            "type":"Services"
        }
    ],
    "sg:phone":"+1 614 262 2934",
    "sg:postcode":"43224",
    "sg:province":"OH",
    "sg:tags":[
        "house",
        "nonresidential"
    ],
    "wof:name":"Mdg Builders Co",
    "wof:placetype":"venue"
},
  "geometry": {"coordinates":[-82.99606300000001,40.044956],"type":"Point"}
}