{
  "type": "Feature",
  "properties": {
    "addr:full": "25938 Highland Rd Cleveland OH 44143",
    "addr:housenumber": "25938",
    "addr:postcode": "44143",
    "addr:street": "Highland Rd",
    "iso:country": "US",
    "sg:address": "25938 Highland Rd",
    "sg:city": "Cleveland",
    "sg:classifiers": [
      {
        "category": "Retail",
        "subcategory": "Animal Services",
        "type": "Services"
      }
    ],
    "sg:phone": "+1 216 481 3889",
    "sg:postcode": "44143",
    "sg:province": "OH",
    "sg:tags": [
      "pet",
      "grooming",
      "washing"
    ],
    "wof:name": "Elmo's All Breeds Grooming",
    "wof:placetype": "venue"
  },
  "geometry": {"coordinates":[-81.503862,41.552688],"type":"Point"}
}
