{
  "type": "Feature",
  "properties": {
    "addr:full":"16511 Hilliard Rd Cleveland OH 44107",
    "addr:housenumber":"16511",
    "addr:postcode":"44107",
    "addr:street":"Hilliard Rd",
    "iso:country":"US",
    "sg:address":"16511 Hilliard Rd",
    "sg:city":"Cleveland",
    "sg:classifiers":[
        {
            "category":"Organizations",
            "subcategory":"Religious Organization",
            "type":"Services"
        }
    ],
    "sg:phone":"+1 216 226 6500",
    "sg:postcode":"44107",
    "sg:province":"OH",
    "sg:tags":[
        "church"
    ],
    "wof:name":"Faith Lutheran Church",
    "wof:placetype":"venue"
},
  "geometry": {"coordinates":[-81.813132,41.475438],"type":"Point"}
}