{
  "type": "Feature",
  "properties": {
    "iso:country":"US",
    "sg:address":"219 Aukerman St",
    "sg:city":"Eaton",
    "sg:classifiers":[
        {
            "category":"Shopping",
            "subcategory":"Discount & Variety Stores",
            "type":"Retail Goods"
        }
    ],
    "sg:phone":"+1 937 456 9923",
    "sg:postcode":"45320",
    "sg:province":"OH",
    "wof:name":"Dollar General",
    "wof:placetype":"venue"
},
  "geometry": {"coordinates":[-84.62943300000001,39.745572],"type":"Point"}
}