{
  "type": "Feature",
  "properties": {
    "iso:country":"US",
    "sg:address":"213 Walnut St",
    "sg:city":"Greenville",
    "sg:classifiers":[
        {
            "category":"Professional",
            "subcategory":"Lawyer & Legal Services",
            "type":"Services"
        }
    ],
    "sg:phone":"+1 937 548 0010",
    "sg:postcode":"45331",
    "sg:province":"OH",
    "sg:tags":[
        "attorney"
    ],
    "wof:name":"David A Rohrer",
    "wof:placetype":"venue"
},
  "geometry": {"coordinates":[-84.632919,40.104107],"type":"Point"}
}