{
  "type": "Feature",
  "properties": {
    "iso:country":"US",
    "sg:address":"10287 Pleasant Renner Rd",
    "sg:city":"Goshen",
    "sg:classifiers":[
        {
            "category":"Retail",
            "subcategory":"Animal Services",
            "type":"Services"
        }
    ],
    "sg:phone":"+1 513 877 2327",
    "sg:postcode":"45122",
    "sg:province":"OH",
    "wof:name":"Brillwood Stables",
    "wof:placetype":"venue"
},
  "geometry": {"coordinates":[-84.142571,39.276301],"type":"Point"}
}