{
  "type": "Feature",
  "properties": {
    "addr:full": "16630 State Rte 3 Loudonville OH 44842",
    "addr:housenumber": "16630",
    "addr:postcode": "44842",
    "addr:street": "State Rte 3",
    "iso:country": "US",
    "sg:address": "16630 State Rte 3",
    "sg:city": "Loudonville",
    "sg:classifiers": [
      {
        "category": "Shopping",
        "subcategory": "Used Merchandise",
        "type": "Retail Goods"
      }
    ],
    "sg:phone": "+1 419 994 2323",
    "sg:postcode": "44842",
    "sg:province": "OH",
    "sg:tags": [
      "shop",
      "thrift"
    ],
    "wof:name": "Goodwill Industries",
    "wof:placetype": "venue"
  },
  "geometry": {"coordinates":[-82.218539,40.641076],"type":"Point"}
}
