{
  "type": "Feature",
  "properties": {
    "iso:country":"US",
    "sg:address":"16630 State Rte 3",
    "sg:city":"Loudonville",
    "sg:classifiers":[
        {
            "category":"Shopping",
            "subcategory":"Used Merchandise",
            "type":"Retail Goods"
        }
    ],
    "sg:phone":"+1 419 994 2323",
    "sg:postcode":"44842",
    "sg:province":"OH",
    "sg:tags":[
        "shop",
        "thrift"
    ],
    "wof:name":"Goodwill Industries",
    "wof:placetype":"venue"
},
  "geometry": {"coordinates":[-82.21853900000001,40.641076],"type":"Point"}
}