{
  "type": "Feature",
  "properties": {
    "iso:country":"US",
    "sg:address":"4211 Venice Rd",
    "sg:city":"Sandusky",
    "sg:classifiers":[
        {
            "category":"Manufacturing",
            "subcategory":"Tools & Machinery",
            "type":"Manufacturing & Wholesale Goods"
        }
    ],
    "sg:phone":"+1 419 626 9559",
    "sg:postcode":"44870",
    "sg:province":"OH",
    "sg:tags":[
        "machine",
        "shop",
        "job"
    ],
    "wof:name":"Blue Chip Machine & Tool Ltd",
    "wof:placetype":"venue"
},
  "geometry": {"coordinates":[-82.761224,41.442451],"type":"Point"}
}