{
  "type": "Feature",
  "properties": {
    "addr:full": "4211 Venice Rd Sandusky OH 44870",
    "addr:housenumber": "4211",
    "addr:postcode": "44870",
    "addr:street": "Venice Rd",
    "iso:country": "US",
    "sg:address": "4211 Venice Rd",
    "sg:city": "Sandusky",
    "sg:classifiers": [
      {
        "category": "Manufacturing",
        "subcategory": "Tools \u0026 Machinery",
        "type": "Manufacturing \u0026 Wholesale Goods"
      }
    ],
    "sg:phone": "+1 419 626 9559",
    "sg:postcode": "44870",
    "sg:province": "OH",
    "sg:tags": [
      "machine",
      "shop",
      "job"
    ],
    "wof:name": "Blue Chip Machine \u0026 Tool Ltd",
    "wof:placetype": "venue"
  },
  "geometry": {"coordinates":[-82.761224,41.442451],"type":"Point"}
}
