{
  "type": "Feature",
  "properties": {
    "addr:full": "2253 Bruce Rd Delaware OH 43015",
    "addr:housenumber": "2253",
    "addr:postcode": "43015",
    "addr:street": "Bruce Rd",
    "iso:country": "US",
    "sg:address": "2253 Bruce Rd",
    "sg:city": "Delaware",
    "sg:classifiers": [
      {
        "category": "Building \u0026 Trades",
        "subcategory": "Electrical",
        "type": "Services"
      }
    ],
    "sg:phone": "+1 740 363 0439",
    "sg:postcode": "43015",
    "sg:province": "OH",
    "sg:tags": [
      "electric",
      "contractor"
    ],
    "sg:website": "www.mrelectric.com",
    "wof:name": "Ace Electric",
    "wof:placetype": "venue"
  },
  "geometry": {"coordinates":[-83.077096,40.331078],"type":"Point"}
}
