{
  "type": "Feature",
  "properties": {
    "iso:country":"US",
    "sg:address":"6440 Euclid Ave",
    "sg:city":"Cincinnati",
    "sg:classifiers":[
        {
            "category":"Banks & Credit Unions",
            "subcategory":"Bank",
            "type":"Services"
        }
    ],
    "sg:phone":"+1 513 891 2335",
    "sg:postcode":"45243",
    "sg:province":"OH",
    "sg:tags":[
        "mortgage"
    ],
    "wof:name":"GMAC",
    "wof:placetype":"venue"
},
  "geometry": {"coordinates":[-84.379832,39.192132],"type":"Point"}
}