{
  "type": "Feature",
  "properties": {
    "addr:full": "5754 Eastview Dr Clinton OH 44216",
    "addr:housenumber": "5754",
    "addr:postcode": "44216",
    "addr:street": "Eastview Dr",
    "iso:country": "US",
    "sg:address": "5754 Eastview Dr",
    "sg:city": "Clinton",
    "sg:classifiers": [
      {
        "category": "Professional",
        "subcategory": "Engineering",
        "type": "Services"
      }
    ],
    "sg:phone": "+1 330 882 6119",
    "sg:postcode": "44216",
    "sg:province": "OH",
    "sg:tags": [
      "general",
      "contractor"
    ],
    "wof:name": "Vetter Engineering Inc",
    "wof:placetype": "venue"
  },
  "geometry": {"coordinates":[-81.583718,40.95445],"type":"Point"}
}
