{
  "type": "Feature",
  "properties": {
    "addr:full":"1 E Main St Norwalk OH 44857",
    "addr:housenumber":"1",
    "addr:postcode":"44857",
    "addr:street":"E Main St",
    "iso:country":"US",
    "sg:address":"1 E Main St",
    "sg:city":"Norwalk",
    "sg:classifiers":[
        {
            "category":"Shopping",
            "subcategory":"Jewelry",
            "type":"Retail Goods"
        }
    ],
    "sg:phone":"+1 419 663 4653",
    "sg:postcode":"44857",
    "sg:province":"OH",
    "sg:tags":[
        "jeweler"
    ],
    "wof:name":"Diamond Collection Inc",
    "wof:placetype":"venue"
},
  "geometry": {"coordinates":[-82.614586,41.242813],"type":"Point"}
}