{
  "type": "Feature",
  "properties": {
    "addr:full": "236 Minster Egypt Pike Minster OH 45865",
    "addr:housenumber": "236",
    "addr:postcode": "45865",
    "addr:street": "Minster Egypt Pike",
    "iso:country": "US",
    "sg:address": "236 Minster Egypt Pike",
    "sg:city": "Minster",
    "sg:classifiers": [
      {
        "category": "Farming",
        "subcategory": "Livestock Farm",
        "type": "Manufacturing \u0026 Wholesale Goods"
      }
    ],
    "sg:phone": "+1 419 628 2108",
    "sg:postcode": "45865",
    "sg:province": "OH",
    "sg:tags": [
      "hog",
      "corn",
      "or",
      "feedlot"
    ],
    "wof:name": "Luke Dahlinghaus",
    "wof:placetype": "venue"
  },
  "geometry": {"coordinates":[-84.452439,40.385542],"type":"Point"}
}
