{
  "type": "Feature",
  "properties": {
    "addr:full": "6747 Daleview Rd Cincinnati OH 45247",
    "addr:housenumber": "6747",
    "addr:postcode": "45247",
    "addr:street": "Daleview Rd",
    "iso:country": "US",
    "sg:address": "6747 Daleview Rd",
    "sg:city": "Cincinnati",
    "sg:classifiers": [
      {
        "category": "Building \u0026 Trades",
        "subcategory": "Construction",
        "type": "Services"
      }
    ],
    "sg:phone": "+1 513 923 2743",
    "sg:postcode": "45247",
    "sg:province": "OH",
    "sg:tags": [
      "house"
    ],
    "wof:name": "Byrum Home Improvement",
    "wof:placetype": "venue"
  },
  "geometry": {"coordinates":[-84.651642,39.213234],"type":"Point"}
}
