{
  "type": "Feature",
  "properties": {
    "iso:country":"US",
    "sg:address":"68 N High St",
    "sg:city":"New Albany",
    "sg:classifiers":[
        {
            "category":"Professional",
            "subcategory":"Advertising",
            "type":"Services"
        }
    ],
    "sg:phone":"+1 614 939 5005",
    "sg:postcode":"43054",
    "sg:province":"OH",
    "sg:tags":[
        "agency"
    ],
    "wof:name":"Rmd Marketing Advertising",
    "wof:placetype":"venue"
},
  "geometry": {"coordinates":[-82.808661,40.082812],"type":"Point"}
}