{
  "type": "Feature",
  "properties": {
    "addr:full":"497 W Main St Batavia OH 45103",
    "addr:housenumber":"497",
    "addr:postcode":"45103",
    "addr:street":"W Main St",
    "iso:country":"US",
    "sg:address":"497 W Main St",
    "sg:city":"Batavia",
    "sg:classifiers":[
        {
            "category":"Health Services",
            "subcategory":"Doctor",
            "type":"Services"
        }
    ],
    "sg:phone":"+1 513 735 9111",
    "sg:postcode":"45103",
    "sg:province":"OH",
    "wof:name":"Clermont 4 Kids Dental Care",
    "wof:placetype":"venue"
},
  "geometry": {"coordinates":[-84.18537999999999,39.081459],"type":"Point"}
}