{
  "type": "Feature",
  "properties": {
    "iso:country":"US",
    "sg:address":"4104 Wyndwood Dr",
    "sg:city":"Toledo",
    "sg:classifiers":[
        {
            "category":"Real Estate",
            "subcategory":"Real Estate Operator",
            "type":"Services"
        }
    ],
    "sg:phone":"+1 419 841 3274",
    "sg:postcode":"43623",
    "sg:province":"OH",
    "sg:tags":[
        "building",
        "nonresidential"
    ],
    "wof:name":"Stacy Properties LLC",
    "wof:placetype":"venue"
},
  "geometry": {"coordinates":[-83.653768,41.693249],"type":"Point"}
}