{
  "type": "Feature",
  "properties": {
    "addr:full": "9203 Kinsman Rd Cleveland OH 44104",
    "addr:housenumber": "9203",
    "addr:postcode": "44104",
    "addr:street": "Kinsman Rd",
    "iso:country": "US",
    "sg:address": "9203 Kinsman Rd",
    "sg:city": "Cleveland",
    "sg:classifiers": [
      {
        "category": "Real Estate",
        "subcategory": "Real Estate Operator",
        "type": "Services"
      }
    ],
    "sg:phone": "+1 216 431 0061",
    "sg:postcode": "44104",
    "sg:province": "OH",
    "sg:tags": [
      "building",
      "nonresidential"
    ],
    "wof:name": "Tarrify Properties LLC",
    "wof:placetype": "venue"
  },
  "geometry": {"coordinates":[-81.622052,41.472245],"type":"Point"}
}
