{
  "type": "Feature",
  "properties": {
    "iso:country":"US",
    "sg:address":"1200 S Waggoner Rd",
    "sg:city":"Reynoldsburg",
    "sg:classifiers":[
        {
            "category":"Social Services",
            "subcategory":"Child Care",
            "type":"Services"
        }
    ],
    "sg:phone":"+1 614 864 3506",
    "sg:postcode":"43068",
    "sg:province":"OH",
    "sg:tags":[
        "school",
        "kindergarten",
        "academic",
        "organization",
        "religious",
        "day"
    ],
    "sg:website":"www.messiahlutheran.net",
    "wof:name":"Christian Messiah School",
    "wof:placetype":"venue"
},
  "geometry": {"coordinates":[-82.79382,39.957632],"type":"Point"}
}