{
  "type": "Feature",
  "properties": {
    "addr:full": "111 Shillito Pl Cincinnati OH 45202",
    "addr:housenumber": "111",
    "addr:postcode": "45202",
    "addr:street": "Shillito Pl",
    "iso:country": "US",
    "sg:address": "111 Shillito Pl",
    "sg:city": "Cincinnati",
    "sg:classifiers": [
      {
        "category": "Restaurant",
        "type": "Food \u0026 Drink"
      }
    ],
    "sg:phone": "+1 513 241 8799",
    "sg:postcode": "45202",
    "sg:province": "OH",
    "sg:tags": [
      "caterer"
    ],
    "wof:name": "Culinary Productions LTD",
    "wof:placetype": "venue"
  },
  "geometry": {"coordinates":[-84.515887,39.102626],"type":"Point"}
}
