{
  "type": "Feature",
  "properties": {
    "iso:country":"US",
    "sg:address":"305 Elm St",
    "sg:city":"Bellevue",
    "sg:classifiers":[
        {
            "category":"Manufacturing",
            "subcategory":"Metals",
            "type":"Manufacturing & Wholesale Goods"
        }
    ],
    "sg:phone":"+1 419 483 7540",
    "sg:postcode":"44811",
    "sg:province":"OH",
    "sg:tags":[
        "fabricated",
        "structural"
    ],
    "sg:website":"www.tsifab.com",
    "wof:name":"Thomas Steel Inc",
    "wof:placetype":"venue"
},
  "geometry": {"coordinates":[-82.82823399999999,41.276609],"type":"Point"}
}