{
  "type": "Feature",
  "properties": {
    "iso:country":"US",
    "sg:address":"97 River Dr",
    "sg:city":"Willoughby",
    "sg:classifiers":[
        {
            "category":"Home & Garden",
            "subcategory":"Household Appliances",
            "type":"Retail Goods"
        }
    ],
    "sg:phone":"+1 440 942 0252",
    "sg:postcode":"44095",
    "sg:province":"OH",
    "wof:name":"A-1 Shore Appliance",
    "wof:placetype":"venue"
},
  "geometry": {"coordinates":[-81.43246499999999,41.677627],"type":"Point"}
}