{
  "type": "Feature",
  "properties": {
    "addr:full": "478 W Turkeyfoot Lake Rd Akron OH 44319",
    "addr:housenumber": "478",
    "addr:postcode": "44319",
    "addr:street": "W Turkeyfoot Lake Rd",
    "iso:country": "US",
    "sg:address": "478 W Turkeyfoot Lake Rd",
    "sg:city": "Akron",
    "sg:classifiers": [
      {
        "category": "Personal",
        "subcategory": "Beauty Salon",
        "type": "Services"
      }
    ],
    "sg:phone": "+1 330 644 3744",
    "sg:postcode": "44319",
    "sg:province": "OH",
    "sg:tags": [
      "shop"
    ],
    "wof:name": "Creative Designers \u0026 Co",
    "wof:placetype": "venue"
  },
  "geometry": {"coordinates":[-81.536564,40.980772],"type":"Point"}
}
