{
  "type": "Feature",
  "properties": {
    "iso:country":"US",
    "sg:address":"41542 State Rte 517",
    "sg:city":"Lisbon",
    "sg:classifiers":[
        {
            "category":"Health Services",
            "subcategory":"Nursing And Care Facility",
            "type":"Services"
        },
        {
            "category":"Social Services",
            "type":"Services"
        }
    ],
    "sg:phone":"+1 330 420 0516",
    "sg:postcode":"44432",
    "sg:province":"OH",
    "sg:tags":[
        "instruction"
    ],
    "wof:name":"American Health Care Inc",
    "wof:placetype":"venue"
},
  "geometry": {"coordinates":[-80.715265,40.812599],"type":"Point"}
}