{
  "type": "Feature",
  "properties": {
    "addr:full": "1546 N High St Columbus OH 43201",
    "addr:housenumber": "1546",
    "addr:postcode": "43201",
    "addr:street": "N High St",
    "iso:country": "US",
    "sg:address": "1546 N High St",
    "sg:city": "Columbus",
    "sg:classifiers": [
      {
        "category": "Restaurant",
        "type": "Food \u0026 Drink"
      }
    ],
    "sg:menulink": "http://www.allmenus.com/oh/columbus/250550-ugly-tuna-saloona/menu/",
    "sg:phone": "+1 614 297 8862",
    "sg:postcode": "43201",
    "sg:province": "OH",
    "sg:tags": [
      "seafood",
      "american"
    ],
    "wof:name": "Ugly Tuna Saloona",
    "wof:placetype": "venue"
  },
  "geometry": {"coordinates":[-83.006868,39.994059],"type":"Point"}
}
