{
  "type": "Feature",
  "properties": {
    "iso:country":"US",
    "sg:address":"422 Washington St",
    "sg:city":"Steubenville",
    "sg:classifiers":[
        {
            "category":"Organizations",
            "subcategory":"Religious Organization",
            "type":"Services"
        },
        {
            "category":"Education",
            "subcategory":"School",
            "type":"Public Place"
        }
    ],
    "sg:phone":"+1 740 282 3631",
    "sg:postcode":"43952",
    "sg:province":"OH",
    "sg:tags":[
        "church"
    ],
    "sg:website":"www.diosteub.org",
    "wof:name":"Diocese Of Steubenville School",
    "wof:placetype":"venue"
},
  "geometry": {"coordinates":[-80.61559699999999,40.362104],"type":"Point"}
}