{
  "type": "Feature",
  "properties": {
    "addr:full": "1445 N Vandemark Rd Sidney OH 45365",
    "addr:housenumber": "1445",
    "addr:postcode": "45365",
    "addr:street": "N Vandemark Rd",
    "iso:country": "US",
    "sg:address": "1445 N Vandemark Rd",
    "sg:city": "Sidney",
    "sg:classifiers": [
      {
        "category": "Home \u0026 Garden",
        "subcategory": "Carpets \u0026 Floor Coverings",
        "type": "Retail Goods"
      }
    ],
    "sg:phone": "+1 937 497 0309",
    "sg:postcode": "45365",
    "sg:province": "OH",
    "sg:tags": [
      "material"
    ],
    "wof:name": "R \u0026 S Flooring Inc",
    "wof:placetype": "venue"
  },
  "geometry": {"coordinates":[-84.187774,40.295786],"type":"Point"}
}
