{
  "type": "Feature",
  "properties": {
    "addr:full":"2533 Onandaga Dr Columbus OH 43221",
    "addr:housenumber":"2533",
    "addr:postcode":"43221",
    "addr:street":"Onandaga Dr",
    "iso:country":"US",
    "sg:address":"2533 Onandaga Dr",
    "sg:city":"Columbus",
    "sg:classifiers":[
        {
            "category":"Building & Trades",
            "subcategory":"Construction",
            "type":"Services"
        }
    ],
    "sg:phone":"+1 614 481 4077",
    "sg:postcode":"43221",
    "sg:province":"OH",
    "sg:tags":[
        "industrial",
        "contractor"
    ],
    "wof:name":"Jonathan W Furash",
    "wof:placetype":"venue"
},
  "geometry": {"coordinates":[-83.07835900000001,40.008503],"type":"Point"}
}