{
  "type": "Feature",
  "properties": {
    "addr:full":"2603 Vine St Cincinnati OH 45219",
    "addr:housenumber":"2603",
    "addr:postcode":"45219",
    "addr:street":"Vine St",
    "iso:country":"US",
    "sg:address":"2603 Vine St",
    "sg:city":"Cincinnati",
    "sg:classifiers":[
        {
            "category":"Retail",
            "subcategory":"Repair Shop",
            "type":"Services"
        }
    ],
    "sg:phone":"+1 513 559 9400",
    "sg:postcode":"45219",
    "sg:province":"OH",
    "sg:tags":[
        "equipment",
        "telephone",
        "system"
    ],
    "wof:name":"Vine Co",
    "wof:placetype":"venue"
},
  "geometry": {"coordinates":[-84.50956600000001,39.130351],"type":"Point"}
}