{
  "type": "Feature",
  "properties": {
    "addr:full": "5918 Price Rd Milford OH 45150",
    "addr:housenumber": "5918",
    "addr:postcode": "45150",
    "addr:street": "Price Rd",
    "iso:country": "US",
    "sg:address": "5918 Price Rd",
    "sg:city": "Milford",
    "sg:classifiers": [
      {
        "category": "Real Estate",
        "subcategory": "Real Estate Agent",
        "type": "Services"
      }
    ],
    "sg:phone": "+1 513 831 2773",
    "sg:postcode": "45150",
    "sg:province": "OH",
    "wof:name": "Sky Top Properties Ltd",
    "wof:placetype": "venue"
  },
  "geometry": {"coordinates":[-84.266297,39.199557],"type":"Point"}
}
