{
  "type": "Feature",
  "properties": {
    "addr:full":"7360 Blacklick-Eastern Rd NW Pickerington OH 43147",
    "addr:housenumber":"7360",
    "addr:postcode":"43147",
    "addr:street":"Blacklick-Eastern Rd Nw",
    "iso:country":"US",
    "sg:address":"7360 Blacklick-Eastern Rd NW",
    "sg:city":"Pickerington",
    "sg:classifiers":[
        {
            "category":"Building & Trades",
            "subcategory":"Construction",
            "type":"Services"
        }
    ],
    "sg:phone":"+1 614 837 1588",
    "sg:postcode":"43147",
    "sg:province":"OH",
    "sg:tags":[
        "concrete",
        "contractor"
    ],
    "wof:name":"Genaro Concrete Foundations",
    "wof:placetype":"venue"
},
  "geometry": {"coordinates":[-82.723266,39.92928],"type":"Point"}
}