{
  "type": "Feature",
  "properties": {
    "iso:country":"US",
    "sg:address":"3355 Revere Ct",
    "sg:city":"Brunswick",
    "sg:classifiers":[
        {
            "category":"Recreation",
            "type":"Entertainment"
        }
    ],
    "sg:phone":"+1 330 558 0216",
    "sg:postcode":"44212",
    "sg:province":"OH",
    "sg:tags":[
        "amusement"
    ],
    "wof:name":"Heritage Park Recreation",
    "wof:placetype":"venue"
},
  "geometry": {"coordinates":[-81.80582099999999,41.243412],"type":"Point"}
}