{
  "type": "Feature",
  "properties": {
    "iso:country":"US",
    "sg:address":"14132 State Rte 327",
    "sg:city":"Wellston",
    "sg:classifiers":[
        {
            "category":"Professional",
            "type":"Services"
        }
    ],
    "sg:phone":"+1 740 384 3171",
    "sg:postcode":"45692",
    "sg:province":"OH",
    "wof:name":"James Blankenship",
    "wof:placetype":"venue"
},
  "geometry": {"coordinates":[-82.590808,39.151155],"type":"Point"}
}