{
  "type": "Feature",
  "properties": {
    "addr:full": "713 Woodlawn Rd Steubenville OH 43952",
    "addr:housenumber": "713",
    "addr:postcode": "43952",
    "addr:street": "Woodlawn Rd",
    "iso:country": "US",
    "sg:address": "713 Woodlawn Rd",
    "sg:city": "Steubenville",
    "sg:classifiers": [
      {
        "category": "Real Estate",
        "subcategory": "Real Estate Operator",
        "type": "Services"
      }
    ],
    "sg:phone": "+1 740 282 1392",
    "sg:postcode": "43952",
    "sg:province": "OH",
    "sg:tags": [
      "dwelling"
    ],
    "wof:name": "Kittle Investments",
    "wof:placetype": "venue"
  },
  "geometry": {"coordinates":[-80.629487,40.372086],"type":"Point"}
}
