{
  "type": "Feature",
  "properties": {
    "addr:full": "1917 Newark Granville Rd Granville OH 43023",
    "addr:housenumber": "1917",
    "addr:postcode": "43023",
    "addr:street": "Newark Granville Rd",
    "iso:country": "US",
    "sg:address": "1917 Newark Granville Rd",
    "sg:city": "Granville",
    "sg:classifiers": [
      {
        "category": "Insurance",
        "subcategory": "Insurance Agent",
        "type": "Services"
      }
    ],
    "sg:phone": "+1 740 587 2746",
    "sg:postcode": "43023",
    "sg:province": "OH",
    "wof:name": "Northwestern Mutual Financial",
    "wof:placetype": "venue"
  },
  "geometry": {"coordinates":[-82.488778,40.062265],"type":"Point"}
}
