{
  "type": "Feature",
  "properties": {
    "iso:country":"US",
    "sg:address":"6042 Fairway Dr",
    "sg:city":"Mason",
    "sg:classifiers":[
        {
            "category":"Restaurant",
            "type":"Food & Drink"
        }
    ],
    "sg:phone":"+1 513 573 3321",
    "sg:postcode":"45040",
    "sg:province":"OH",
    "sg:tags":[
        "lounge",
        "eating",
        "cocktail"
    ],
    "wof:name":"Courseview Restaurant & Patio",
    "wof:placetype":"venue"
},
  "geometry": {"coordinates":[-84.293243,39.348803],"type":"Point"}
}