{
  "type": "Feature",
  "properties": {
    "addr:full": "6042 Fairway Dr Mason OH 45040",
    "addr:housenumber": "6042",
    "addr:postcode": "45040",
    "addr:street": "Fairway Dr",
    "iso:country": "US",
    "sg:address": "6042 Fairway Dr",
    "sg:city": "Mason",
    "sg:classifiers": [
      {
        "category": "Restaurant",
        "type": "Food \u0026 Drink"
      }
    ],
    "sg:phone": "+1 513 573 3321",
    "sg:postcode": "45040",
    "sg:province": "OH",
    "sg:tags": [
      "lounge",
      "eating",
      "cocktail"
    ],
    "wof:name": "Courseview Restaurant \u0026 Patio",
    "wof:placetype": "venue"
  },
  "geometry": {"coordinates":[-84.293243,39.348803],"type":"Point"}
}
