{
  "type": "Feature",
  "properties": {
    "iso:country":"US",
    "sg:address":"1016 Morse St",
    "sg:city":"Akron",
    "sg:classifiers":[
        {
            "category":"Building & Trades",
            "subcategory":"Construction",
            "type":"Services"
        }
    ],
    "sg:phone":"+1 330 686 8632",
    "sg:postcode":"44320",
    "sg:province":"OH",
    "sg:tags":[
        "concrete",
        "contractor"
    ],
    "wof:name":"Affordable Concrete Leveling",
    "wof:placetype":"venue"
},
  "geometry": {"coordinates":[-81.569579,41.058671],"type":"Point"}
}