{
  "type": "Feature",
  "properties": {
    "addr:full": "8635 Ravenna Ave NE Louisville OH 44641",
    "addr:housenumber": "8635",
    "addr:postcode": "44641",
    "addr:street": "Ravenna Ave Ne",
    "iso:country": "US",
    "sg:address": "8635 Ravenna Ave NE",
    "sg:city": "Louisville",
    "sg:classifiers": [
      {
        "category": "Restaurant",
        "type": "Food \u0026 Drink"
      }
    ],
    "sg:phone": "+1 330 875 9214",
    "sg:postcode": "44641",
    "sg:province": "OH",
    "sg:tags": [
      "eating"
    ],
    "wof:name": "Main Street Family Restaurant",
    "wof:placetype": "venue"
  },
  "geometry": {"coordinates":[-81.256459,40.895311],"type":"Point"}
}
