{
  "type": "Feature",
  "properties": {
    "iso:country":"US",
    "sg:address":"8635 Ravenna Ave NE",
    "sg:city":"Louisville",
    "sg:classifiers":[
        {
            "category":"Restaurant",
            "type":"Food & Drink"
        }
    ],
    "sg:phone":"+1 330 875 9214",
    "sg:postcode":"44641",
    "sg:province":"OH",
    "sg:tags":[
        "eating"
    ],
    "wof:name":"Main Street Family Restaurant",
    "wof:placetype":"venue"
},
  "geometry": {"coordinates":[-81.25645900000001,40.895311],"type":"Point"}
}