{
  "type": "Feature",
  "properties": {
    "iso:country":"US",
    "sg:address":"616 Northfield Rd",
    "sg:city":"Cleveland",
    "sg:classifiers":[
        {
            "category":"Personal",
            "subcategory":"Beauty Salon",
            "type":"Services"
        }
    ],
    "sg:phone":"+1 440 735 9605",
    "sg:postcode":"44146",
    "sg:province":"OH",
    "wof:name":"Hair Cuts & Color",
    "wof:placetype":"venue"
},
  "geometry": {"coordinates":[-81.52655799999999,41.39844],"type":"Point"}
}