{
  "type": "Feature",
  "properties": {
    "addr:full": "616 Northfield Rd Cleveland OH 44146",
    "addr:housenumber": "616",
    "addr:postcode": "44146",
    "addr:street": "Northfield Rd",
    "iso:country": "US",
    "sg:address": "616 Northfield Rd",
    "sg:city": "Cleveland",
    "sg:classifiers": [
      {
        "category": "Personal",
        "subcategory": "Beauty Salon",
        "type": "Services"
      }
    ],
    "sg:phone": "+1 440 735 9605",
    "sg:postcode": "44146",
    "sg:province": "OH",
    "wof:name": "Hair Cuts \u0026 Color",
    "wof:placetype": "venue"
  },
  "geometry": {"coordinates":[-81.526558,41.39844],"type":"Point"}
}
