{
  "type": "Feature",
  "properties": {
    "addr:full":"137 E High St Hicksville OH 43526",
    "addr:housenumber":"137",
    "addr:postcode":"43526",
    "addr:street":"E High St",
    "iso:country":"US",
    "sg:address":"137 E High St",
    "sg:city":"Hicksville",
    "sg:classifiers":[
        {
            "category":"Organizations",
            "subcategory":"Religious Organization",
            "type":"Services"
        }
    ],
    "sg:phone":"+1 419 542 7124",
    "sg:postcode":"43526",
    "sg:province":"OH",
    "sg:tags":[
        "church"
    ],
    "wof:name":"Trinity United Methodist Chr",
    "wof:placetype":"venue"
},
  "geometry": {"coordinates":[-84.761168,41.294138],"type":"Point"}
}