{
  "type": "Feature",
  "properties": {
    "addr:full": "1376 Anderson Ferry Rd Cincinnati OH 45238",
    "addr:housenumber": "1376",
    "addr:postcode": "45238",
    "addr:street": "Anderson Ferry Rd",
    "iso:country": "US",
    "sg:address": "1376 Anderson Ferry Rd",
    "sg:city": "Cincinnati",
    "sg:classifiers": [
      {
        "category": "Building \u0026 Trades",
        "subcategory": "Construction",
        "type": "Services"
      }
    ],
    "sg:phone": "+1 513 922 0439",
    "sg:postcode": "45238",
    "sg:province": "OH",
    "sg:tags": [
      "home",
      "builder"
    ],
    "wof:name": "Bridgestone Homes",
    "wof:placetype": "venue"
  },
  "geometry": {"coordinates":[-84.616898,39.122411],"type":"Point"}
}
