{
  "type": "Feature",
  "properties": {
    "addr:full": "4022 Channel Rd NE Carrollton OH 44615",
    "addr:housenumber": "4022",
    "addr:postcode": "44615",
    "addr:street": "Channel Rd Ne",
    "iso:country": "US",
    "sg:address": "4022 Channel Rd NE",
    "sg:city": "Carrollton",
    "sg:classifiers": [
      {
        "category": "Home \u0026 Garden",
        "subcategory": "Garden Supply",
        "type": "Retail Goods"
      }
    ],
    "sg:phone": "+1 330 627 8095",
    "sg:postcode": "44615",
    "sg:province": "OH",
    "wof:name": "Fords Green Valley Tree Farms",
    "wof:placetype": "venue"
  },
  "geometry": {"coordinates":[-81.013246,40.631704],"type":"Point"}
}
