{
  "type": "Feature",
  "properties": {
    "iso:country":"US",
    "sg:address":"2034 Allandale Dr",
    "sg:city":"Wooster",
    "sg:classifiers":[
        {
            "category":"Organizations",
            "subcategory":"Religious Organization",
            "type":"Services"
        }
    ],
    "sg:phone":"+1 330 262 1306",
    "sg:postcode":"44691",
    "sg:province":"OH",
    "sg:tags":[
        "clergy"
    ],
    "wof:name":"Sanford Oyer",
    "wof:placetype":"venue"
},
  "geometry": {"coordinates":[-81.926379,40.825675],"type":"Point"}
}