{
  "type": "Feature",
  "properties": {
    "addr:full":"4711 E 355th St Willoughby OH 44094",
    "addr:housenumber":"4711",
    "addr:postcode":"44094",
    "addr:street":"E 355Th St",
    "iso:country":"US",
    "sg:address":"4711 E 355th St",
    "sg:city":"Willoughby",
    "sg:classifiers":[
        {
            "category":"Manufacturing",
            "subcategory":"Retail Goods",
            "type":"Manufacturing & Wholesale Goods"
        }
    ],
    "sg:phone":"+1 440 954 3500",
    "sg:postcode":"44094",
    "sg:province":"OH",
    "sg:tags":[
        "manufacturer"
    ],
    "sg:website":"www.bevcorp.com",
    "wof:name":"Bebcorp Industries",
    "wof:placetype":"venue"
},
  "geometry": {"coordinates":[-81.434895,41.630337],"type":"Point"}
}