{
  "type": "Feature",
  "properties": {
    "addr:full": "1722 Cedar Ave Cincinnati OH 45224",
    "addr:housenumber": "1722",
    "addr:postcode": "45224",
    "addr:street": "Cedar Ave",
    "iso:country": "US",
    "sg:address": "1722 Cedar Ave",
    "sg:city": "Cincinnati",
    "sg:classifiers": [
      {
        "category": "Shopping",
        "subcategory": "Jewelry",
        "type": "Retail Goods"
      }
    ],
    "sg:phone": "+1 513 542 8226",
    "sg:postcode": "45224",
    "sg:province": "OH",
    "wof:name": "Nice Lady Jewelry",
    "wof:placetype": "venue"
  },
  "geometry": {"coordinates":[-84.550831,39.198999],"type":"Point"}
}
