{
  "type": "Feature",
  "properties": {
    "addr:full":"807 Brookfield Dr New Carlisle OH 45344",
    "addr:housenumber":"807",
    "addr:postcode":"45344",
    "addr:street":"Brookfield Dr",
    "iso:country":"US",
    "sg:address":"807 Brookfield Dr",
    "sg:city":"New Carlisle",
    "sg:classifiers":[
        {
            "category":"Banks & Credit Unions",
            "subcategory":"Bank",
            "type":"Services"
        }
    ],
    "sg:phone":"+1 937 845 7308",
    "sg:postcode":"45344",
    "sg:province":"OH",
    "sg:tags":[
        "motion",
        "state",
        "production",
        "commercial"
    ],
    "wof:name":"Gantt Enterprises",
    "wof:placetype":"venue"
},
  "geometry": {"coordinates":[-84.03544599999999,39.946088],"type":"Point"}
}