{
  "type": "Feature",
  "properties": {
    "iso:country":"US",
    "sg:address":"147 James Way",
    "sg:city":"Marion",
    "sg:classifiers":[
        {
            "category":"Autos & Motor Vehicles",
            "subcategory":"Auto Supplies",
            "type":"Retail Goods"
        },
        {
            "category":"Wholesale",
            "subcategory":"Auto Parts",
            "type":"Manufacturing & Wholesale Goods"
        }
    ],
    "sg:phone":"+1 740 389 6359",
    "sg:postcode":"43302",
    "sg:province":"OH",
    "sg:tags":[
        "automobile"
    ],
    "wof:name":"Walsh Big A Auto Parts",
    "wof:placetype":"venue"
},
  "geometry": {"coordinates":[-83.079178,40.580514],"type":"Point"}
}