{
  "type": "Feature",
  "properties": {
    "iso:country":"US",
    "sg:address":"2754 Berlin Station Rd",
    "sg:city":"Delaware",
    "sg:classifiers":[
        {
            "category":"Building & Trades",
            "subcategory":"Construction",
            "type":"Services"
        }
    ],
    "sg:phone":"+1 740 363 2533",
    "sg:postcode":"43015",
    "sg:province":"OH",
    "sg:tags":[
        "house"
    ],
    "wof:name":"Ad Builders",
    "wof:placetype":"venue"
},
  "geometry": {"coordinates":[-83.01515000000001,40.256195],"type":"Point"}
}