{
  "type": "Feature",
  "properties": {
    "addr:full": "2754 Berlin Station Rd Delaware OH 43015",
    "addr:housenumber": "2754",
    "addr:postcode": "43015",
    "addr:street": "Berlin Station Rd",
    "iso:country": "US",
    "sg:address": "2754 Berlin Station Rd",
    "sg:city": "Delaware",
    "sg:classifiers": [
      {
        "category": "Building \u0026 Trades",
        "subcategory": "Construction",
        "type": "Services"
      }
    ],
    "sg:phone": "+1 740 363 2533",
    "sg:postcode": "43015",
    "sg:province": "OH",
    "sg:tags": [
      "house"
    ],
    "wof:name": "Ad Builders",
    "wof:placetype": "venue"
  },
  "geometry": {"coordinates":[-83.01515,40.256195],"type":"Point"}
}
