{
  "type": "Feature",
  "properties": {
    "addr:full": "1443 S Hamilton Rd Columbus OH 43227",
    "addr:housenumber": "1443",
    "addr:postcode": "43227",
    "addr:street": "S Hamilton Rd",
    "iso:country": "US",
    "sg:address": "1443 S Hamilton Rd",
    "sg:city": "Columbus",
    "sg:classifiers": [
      {
        "category": "Professional",
        "subcategory": "Employment Agencies",
        "type": "Services"
      }
    ],
    "sg:phone": "+1 614 277 0159",
    "sg:postcode": "43227",
    "sg:province": "OH",
    "sg:tags": [
      "opportunity"
    ],
    "wof:name": "Ameritemps Inc",
    "wof:placetype": "venue"
  },
  "geometry": {"coordinates":[-82.87776,39.946671],"type":"Point"}
}
