{
  "type": "Feature",
  "properties": {
    "iso:country":"US",
    "sg:address":"12 S Main St",
    "sg:city":"Mount Gilead",
    "sg:classifiers":[
        {
            "category":"Shopping",
            "subcategory":"Gifts & Souvenirs",
            "type":"Retail Goods"
        }
    ],
    "sg:phone":"+1 419 946 1929",
    "sg:postcode":"43338",
    "sg:province":"OH",
    "wof:name":"Emmas Attic Treasures",
    "wof:placetype":"venue"
},
  "geometry": {"coordinates":[-82.828445,40.548939],"type":"Point"}
}