{
  "type": "Feature",
  "properties": {
    "addr:full": "273 Allen Dr Kent OH 44240",
    "addr:housenumber": "273",
    "addr:postcode": "44240",
    "addr:street": "Allen Dr",
    "iso:country": "US",
    "sg:address": "273 Allen Dr",
    "sg:city": "Kent",
    "sg:classifiers": [
      {
        "category": "Personal",
        "subcategory": "Beauty Salon",
        "type": "Services"
      }
    ],
    "sg:phone": "+1 330 673 3666",
    "sg:postcode": "44240",
    "sg:province": "OH",
    "sg:tags": [
      "manicuring"
    ],
    "wof:name": "Nails By Lisa",
    "wof:placetype": "venue"
  },
  "geometry": {"coordinates":[-81.364167,41.167315],"type":"Point"}
}
