{
  "type": "Feature",
  "properties": {
    "iso:country":"US",
    "sg:address":"273 Allen Dr",
    "sg:city":"Kent",
    "sg:classifiers":[
        {
            "category":"Personal",
            "subcategory":"Beauty Salon",
            "type":"Services"
        }
    ],
    "sg:phone":"+1 330 673 3666",
    "sg:postcode":"44240",
    "sg:province":"OH",
    "sg:tags":[
        "manicuring"
    ],
    "wof:name":"Nails By Lisa",
    "wof:placetype":"venue"
},
  "geometry": {"coordinates":[-81.364167,41.167315],"type":"Point"}
}