{
  "type": "Feature",
  "properties": {
    "addr:full":"3530 Belmont Ave Youngstown OH 44505",
    "addr:housenumber":"3530",
    "addr:postcode":"44505",
    "addr:street":"Belmont Ave",
    "iso:country":"US",
    "sg:address":"3530 Belmont Ave",
    "sg:city":"Youngstown",
    "sg:classifiers":[
        {
            "category":"Banks & Credit Unions",
            "subcategory":"Investment Brokerage",
            "type":"Services"
        }
    ],
    "sg:phone":"+1 330 759 7822",
    "sg:postcode":"44505",
    "sg:province":"OH",
    "sg:tags":[
        "security"
    ],
    "wof:name":"Edward Jones 08196",
    "wof:placetype":"venue"
},
  "geometry": {"coordinates":[-80.66531500000001,41.147379],"type":"Point"}
}