{
  "type": "Feature",
  "properties": {
    "iso:country":"US",
    "sg:address":"322 W High St",
    "sg:city":"Bryan",
    "sg:classifiers":[
        {
            "category":"Banks & Credit Unions",
            "subcategory":"Bank",
            "type":"Services"
        }
    ],
    "sg:phone":"+1 419 636 6792",
    "sg:postcode":"43506",
    "sg:province":"OH",
    "sg:tags":[
        "state",
        "commercial"
    ],
    "sg:website":"www.skyfi.com",
    "wof:name":"Sky Bank",
    "wof:placetype":"venue"
},
  "geometry": {"coordinates":[-84.55432500000001,41.474674],"type":"Point"}
}