{
  "type": "Feature",
  "properties": {
    "addr:full":"2521 12th St NW Canton OH 44708",
    "addr:housenumber":"2521",
    "addr:postcode":"44708",
    "addr:street":"12Th St Nw",
    "iso:country":"US",
    "sg:address":"2521 12th St NW",
    "sg:city":"Canton",
    "sg:classifiers":[
        {
            "category":"Social Services",
            "subcategory":"Child Care",
            "type":"Services"
        }
    ],
    "sg:phone":"+1 330 456 4797",
    "sg:postcode":"44708",
    "sg:province":"OH",
    "sg:tags":[
        "kindergarten",
        "academic",
        "school"
    ],
    "sg:website":"www.westbrookparkumc.org",
    "wof:name":"Westbrook Park Nursery School",
    "wof:placetype":"venue"
},
  "geometry": {"coordinates":[-81.402809,40.810177],"type":"Point"}
}