{
  "type": "Feature",
  "properties": {
    "addr:full": "5741 Westbourne Ave Columbus OH 43213",
    "addr:housenumber": "5741",
    "addr:postcode": "43213",
    "addr:street": "Westbourne Ave",
    "iso:country": "US",
    "sg:address": "5741 Westbourne Ave",
    "sg:city": "Columbus",
    "sg:classifiers": [
      {
        "category": "Wholesale",
        "subcategory": "Computers",
        "type": "Manufacturing \u0026 Wholesale Goods"
      }
    ],
    "sg:phone": "+1 614 575 1261",
    "sg:postcode": "43213",
    "sg:province": "OH",
    "sg:tags": [
      "equipment",
      "processing",
      "datum"
    ],
    "wof:name": "Storage Technology Corp",
    "wof:placetype": "venue"
  },
  "geometry": {"coordinates":[-82.850579,39.984335],"type":"Point"}
}
