{
  "type": "Feature",
  "properties": {
    "iso:country":"US",
    "sg:address":"7555 Dickey Rd",
    "sg:city":"Middletown",
    "sg:classifiers":[
        {
            "category":"Building & Trades",
            "subcategory":"Landscaping Services",
            "type":"Services"
        }
    ],
    "sg:phone":"+1 513 424 6826",
    "sg:postcode":"45042",
    "sg:province":"OH",
    "wof:name":"Parkers Bobcat & Lawn Service",
    "wof:placetype":"venue"
},
  "geometry": {"coordinates":[-84.451312,39.576715],"type":"Point"}
}