{
  "type": "Feature",
  "properties": {
    "addr:full": "7555 Dickey Rd Middletown OH 45042",
    "addr:housenumber": "7555",
    "addr:postcode": "45042",
    "addr:street": "Dickey Rd",
    "iso:country": "US",
    "sg:address": "7555 Dickey Rd",
    "sg:city": "Middletown",
    "sg:classifiers": [
      {
        "category": "Building \u0026 Trades",
        "subcategory": "Landscaping Services",
        "type": "Services"
      }
    ],
    "sg:phone": "+1 513 424 6826",
    "sg:postcode": "45042",
    "sg:province": "OH",
    "wof:name": "Parkers Bobcat \u0026 Lawn Service",
    "wof:placetype": "venue"
  },
  "geometry": {"coordinates":[-84.451312,39.576715],"type":"Point"}
}
