{
  "type": "Feature",
  "properties": {
    "addr:full":"42842 Co Rd 10A Woodsfield OH 43793",
    "addr:housenumber":"42842;10a",
    "addr:postcode":"43793",
    "addr:street":"Co Rd",
    "iso:country":"US",
    "sg:address":"42842 Co Rd 10A",
    "sg:city":"Woodsfield",
    "sg:classifiers":[
        {
            "category":"Farming",
            "subcategory":"Livestock Farm",
            "type":"Manufacturing & Wholesale Goods"
        }
    ],
    "sg:phone":"+1 740 472 1958",
    "sg:postcode":"43793",
    "sg:province":"OH",
    "sg:tags":[
        "feedlot",
        "field",
        "crop",
        "beef",
        "cattle"
    ],
    "wof:name":"Kenneth Roth",
    "wof:placetype":"venue"
},
  "geometry": {"coordinates":[-81.04696199999999,39.709126],"type":"Point"}
}