{
  "type": "Feature",
  "properties": {
    "addr:full": "10911 Briggs Rd Cleveland OH 44111",
    "addr:housenumber": "10911",
    "addr:postcode": "44111",
    "addr:street": "Briggs Rd",
    "iso:country": "US",
    "sg:address": "10911 Briggs Rd",
    "sg:city": "Cleveland",
    "sg:classifiers": [
      {
        "category": "Manufacturing",
        "subcategory": "Metals",
        "type": "Manufacturing \u0026 Wholesale Goods"
      }
    ],
    "sg:phone": "+1 216 252 0080",
    "sg:postcode": "44111",
    "sg:province": "OH",
    "sg:tags": [
      "fabricator",
      "sheet",
      "fabricating"
    ],
    "wof:name": "Prototype Fabricators Co Inc",
    "wof:placetype": "venue"
  },
  "geometry": {"coordinates":[-81.760814,41.448401],"type":"Point"}
}
