{
  "type": "Feature",
  "properties": {
    "iso:country":"US",
    "sg:address":"10911 Briggs Rd",
    "sg:city":"Cleveland",
    "sg:classifiers":[
        {
            "category":"Manufacturing",
            "subcategory":"Metals",
            "type":"Manufacturing & Wholesale Goods"
        }
    ],
    "sg:phone":"+1 216 252 0080",
    "sg:postcode":"44111",
    "sg:province":"OH",
    "sg:tags":[
        "fabricator",
        "sheet",
        "fabricating"
    ],
    "wof:name":"Prototype Fabricators Co Inc",
    "wof:placetype":"venue"
},
  "geometry": {"coordinates":[-81.760814,41.448401],"type":"Point"}
}