{
  "type": "Feature",
  "properties": {
    "iso:country":"US",
    "sg:address":"6306 Home Rd",
    "sg:city":"Delaware",
    "sg:classifiers":[
        {
            "category":"Retail",
            "subcategory":"Animal Services",
            "type":"Services"
        }
    ],
    "sg:phone":"+1 740 881 2000",
    "sg:postcode":"43015",
    "sg:province":"OH",
    "sg:tags":[
        "breeder",
        "dog"
    ],
    "wof:name":"Canine Companion Club LLC",
    "wof:placetype":"venue"
},
  "geometry": {"coordinates":[-83.148438,40.195589],"type":"Point"}
}