{
  "type": "Feature",
  "properties": {
    "iso:country":"US",
    "sg:address":"621 Bright Rd",
    "sg:city":"Findlay",
    "sg:classifiers":[
        {
            "category":"Organizations",
            "subcategory":"Religious Organization",
            "type":"Services"
        }
    ],
    "sg:phone":"+1 419 423 3664",
    "sg:postcode":"45840",
    "sg:province":"OH",
    "sg:tags":[
        "church"
    ],
    "sg:website":"www.nwos-elca.org",
    "wof:name":"Northwestern Ohio Synod Elca",
    "wof:placetype":"venue"
},
  "geometry": {"coordinates":[-83.606373,41.047907],"type":"Point"}
}