{
  "type": "Feature",
  "properties": {
    "addr:full": "1764 Wadsworth Rd Akron OH 44320",
    "addr:housenumber": "1764",
    "addr:postcode": "44320",
    "addr:street": "Wadsworth Rd",
    "iso:country": "US",
    "sg:address": "1764 Wadsworth Rd",
    "sg:city": "Akron",
    "sg:classifiers": [
      {
        "category": "Shopping",
        "subcategory": "Computers \u0026 Home Electronics",
        "type": "Retail Goods"
      }
    ],
    "sg:phone": "+1 330 753 5542",
    "sg:postcode": "44320",
    "sg:province": "OH",
    "sg:tags": [
      "television",
      "radio"
    ],
    "wof:name": "Wdli TV 17",
    "wof:placetype": "venue"
  },
  "geometry": {"coordinates":[-81.591915,41.059022],"type":"Point"}
}
