{
  "type": "Feature",
  "properties": {
    "iso:country":"US",
    "sg:address":"375 Dixmyth Ave",
    "sg:city":"Cincinnati",
    "sg:classifiers":[
        {
            "category":"Health Services",
            "subcategory":"Health Practitioner",
            "type":"Services"
        }
    ],
    "sg:phone":"+1 513 872 4000",
    "sg:postcode":"45220",
    "sg:province":"OH",
    "sg:tags":[
        "psychologist"
    ],
    "sg:website":"www.trihealth.com",
    "wof:name":"Trihealth Sleep & Alertness",
    "wof:placetype":"venue"
},
  "geometry": {"coordinates":[-84.523129,39.140122],"type":"Point"}
}