{
  "type": "Feature",
  "properties": {
    "iso:country":"US",
    "sg:address":"1561 Hopkins Ave",
    "sg:city":"Columbus",
    "sg:classifiers":[
        {
            "category":"Building & Trades",
            "subcategory":"Plumbing",
            "type":"Services"
        }
    ],
    "sg:phone":"+1 614 279 7301",
    "sg:postcode":"43223",
    "sg:province":"OH",
    "sg:tags":[
        "plumbing",
        "contractor"
    ],
    "wof:name":"A Sterling Plumbing & Drains",
    "wof:placetype":"venue"
},
  "geometry": {"coordinates":[-83.036963,39.930208],"type":"Point"}
}