{
  "type": "Feature",
  "properties": {
    "iso:country":"US",
    "sg:address":"7191 Euclid Ave",
    "sg:city":"Cincinnati",
    "sg:classifiers":[
        {
            "category":"Shopping",
            "subcategory":"Hobbies, Toys, & Games",
            "type":"Retail Goods"
        },
        {
            "category":"Professional",
            "subcategory":"Management & Consulting",
            "type":"Services"
        }
    ],
    "sg:phone":"+1 513 793 6412",
    "sg:postcode":"45243",
    "sg:province":"OH",
    "sg:tags":[
        "specializing",
        "craft",
        "show"
    ],
    "wof:name":"Kristin's Kreations",
    "wof:placetype":"venue"
},
  "geometry": {"coordinates":[-84.37218,39.191578],"type":"Point"}
}