{
  "type": "Feature",
  "properties": {
    "iso:country":"US",
    "sg:address":"550 Main St",
    "sg:city":"Cincinnati",
    "sg:classifiers":[
        {
            "category":"Government",
            "subcategory":"Office",
            "type":"Public Place"
        }
    ],
    "sg:phone":"+1 513 357 5462",
    "sg:postcode":"45202",
    "sg:province":"OH",
    "wof:name":"Us Assn-Retired Fed Employees",
    "wof:placetype":"venue"
},
  "geometry": {"coordinates":[-84.51009500000001,39.102944],"type":"Point"}
}