{
  "type": "Feature",
  "properties": {
    "iso:country":"US",
    "sg:address":"11211 Burr Oak Rd",
    "sg:city":"Wapakoneta",
    "sg:classifiers":[
        {
            "category":"Wholesale",
            "subcategory":"Durable Goods & Equipment",
            "type":"Manufacturing & Wholesale Goods"
        }
    ],
    "sg:phone":"+1 419 738 8998",
    "sg:postcode":"45895",
    "sg:province":"OH",
    "sg:tags":[
        "professional",
        "scientific",
        "apparatus",
        "instrument"
    ],
    "wof:name":"Coherent Laser Group Services",
    "wof:placetype":"venue"
},
  "geometry": {"coordinates":[-84.237415,40.518693],"type":"Point"}
}