{
  "type": "Feature",
  "properties": {
    "addr:full": "3098 State Rte 5 Cortland OH 44410",
    "addr:housenumber": "3098",
    "addr:postcode": "44410",
    "addr:street": "State Rte 5",
    "iso:country": "US",
    "sg:address": "3098 State Rte 5",
    "sg:city": "Cortland",
    "sg:classifiers": [
      {
        "category": "Autos \u0026 Motor Vehicles",
        "subcategory": "Automobile Sales",
        "type": "Retail Goods"
      }
    ],
    "sg:phone": "+1 330 638 1010",
    "sg:postcode": "44410",
    "sg:province": "OH",
    "sg:tags": [
      "body",
      "repair",
      "dealer",
      "car",
      "general"
    ],
    "sg:website": "www.mrlowpayment.com",
    "wof:name": "Mark Thomas Ford Inc",
    "wof:placetype": "venue"
  },
  "geometry": {"coordinates":[-80.743084,41.307332],"type":"Point"}
}
