{
  "type": "Feature",
  "properties": {
    "addr:full": "2100 Reynoldsburg New Albany Rd Blacklick OH 43004",
    "addr:postcode": "2100;43004",
    "addr:street": "New Albany Rd",
    "iso:country": "US",
    "sg:address": "2100 Reynoldsburg New Albany Rd",
    "sg:city": "Blacklick",
    "sg:classifiers": [
      {
        "category": "Organizations",
        "subcategory": "Religious Organization",
        "type": "Services"
      }
    ],
    "sg:phone": "+1 614 855 3075",
    "sg:postcode": "43004",
    "sg:province": "OH",
    "sg:tags": [
      "church"
    ],
    "sg:website": "www.newhorizonscommunity.com",
    "wof:name": "New Horizons Community Church",
    "wof:placetype": "venue"
  },
  "geometry": {"coordinates":[-82.814777,40.022719],"type":"Point"}
}
