{
  "type": "Feature",
  "properties": {
    "addr:full": "305 Nantucket Pl Vermilion OH 44089",
    "addr:housenumber": "305",
    "addr:postcode": "44089",
    "addr:street": "Nantucket Pl",
    "iso:country": "US",
    "sg:address": "305 Nantucket Pl",
    "sg:city": "Vermilion",
    "sg:classifiers": [
      {
        "category": "Professional",
        "type": "Services"
      }
    ],
    "sg:phone": "+1 440 967 9337",
    "sg:postcode": "44089",
    "sg:province": "OH",
    "wof:name": "Roy Zimmer",
    "wof:placetype": "venue"
  },
  "geometry": {"coordinates":[-82.349584,41.425024],"type":"Point"}
}
