{
  "type": "Feature",
  "properties": {
    "addr:full":"622 Central Center Chillicothe OH 45601",
    "addr:housenumber":"622",
    "addr:postcode":"45601",
    "addr:street":"Central Center",
    "iso:country":"US",
    "sg:address":"622 Central Center",
    "sg:city":"Chillicothe",
    "sg:classifiers":[
        {
            "category":"Health Services",
            "subcategory":"Doctor",
            "type":"Services"
        }
    ],
    "sg:phone":"+1 740 775 4222",
    "sg:postcode":"45601",
    "sg:province":"OH",
    "sg:tags":[
        "dentist"
    ],
    "wof:name":"Priority Dental",
    "wof:placetype":"venue"
},
  "geometry": {"coordinates":[-83.00198,39.337319],"type":"Point"}
}