{
  "type": "Feature",
  "properties": {
    "iso:country":"US",
    "sg:address":"180 Victoria Rd",
    "sg:city":"Youngstown",
    "sg:classifiers":[
        {
            "category":"Wholesale",
            "subcategory":"Farm Supplies",
            "type":"Manufacturing & Wholesale Goods"
        }
    ],
    "sg:phone":"+1 330 270 0685",
    "sg:postcode":"44515",
    "sg:province":"OH",
    "sg:tags":[
        "fertilizer"
    ],
    "wof:name":"Lesco Service Ctr",
    "wof:placetype":"venue"
},
  "geometry": {"coordinates":[-80.784609,41.111184],"type":"Point"}
}