{
  "type": "Feature",
  "properties": {
    "iso:country":"US",
    "sg:address":"12145 Whitman Rd",
    "sg:city":"Doylestown",
    "sg:classifiers":[
        {
            "category":"Retail",
            "subcategory":"Auto Repair",
            "type":"Services"
        }
    ],
    "sg:phone":"+1 330 658 2748",
    "sg:postcode":"44230",
    "sg:province":"OH",
    "sg:tags":[
        "body",
        "automobile",
        "painting",
        "shop"
    ],
    "sg:website":"www.nagys.com",
    "wof:name":"Nagy's Body Shop",
    "wof:placetype":"venue"
},
  "geometry": {"coordinates":[-81.71503800000001,40.952828],"type":"Point"}
}