{
  "type": "Feature",
  "properties": {
    "addr:full":"10884 State Rte 212 NE Bolivar OH 44612",
    "addr:housenumber":"10884",
    "addr:postcode":"44612",
    "addr:street":"State Rte 212 Ne Bolivar",
    "iso:country":"US",
    "sg:address":"10884 State Rte 212 NE",
    "sg:city":"Bolivar",
    "sg:classifiers":[
        {
            "category":"Retail",
            "subcategory":"Laundry & Dry Cleaning",
            "type":"Services"
        }
    ],
    "sg:phone":"+1 330 874 3425",
    "sg:postcode":"44612",
    "sg:province":"OH",
    "sg:tags":[
        "cleaners"
    ],
    "wof:name":"Wilkshire Dry Cleaning",
    "wof:placetype":"venue"
},
  "geometry": {"coordinates":[-81.440763,40.638848],"type":"Point"}
}