{
  "type": "Feature",
  "properties": {
    "addr:full":"4807 Evanswood Dr Columbus OH 43229",
    "addr:housenumber":"4807",
    "addr:postcode":"43229",
    "addr:street":"Evanswood Dr",
    "iso:country":"US",
    "sg:address":"4807 Evanswood Dr",
    "sg:city":"Columbus",
    "sg:classifiers":[
        {
            "category":"Education",
            "subcategory":"College",
            "type":"Public Place"
        }
    ],
    "sg:phone":"+1 614 785 1801",
    "sg:postcode":"43229",
    "sg:province":"OH",
    "sg:tags":[
        "academic",
        "school"
    ],
    "wof:name":"University Of Dayton",
    "wof:placetype":"venue"
},
  "geometry": {"coordinates":[-82.994507,40.063288],"type":"Point"}
}