{
  "type": "Feature",
  "properties": {
    "addr:full":"860 Boardman Canfield Rd Youngstown OH 44512",
    "addr:housenumber":"860",
    "addr:postcode":"44512",
    "addr:street":"Boardman Canfield Rd",
    "iso:country":"US",
    "sg:address":"860 Boardman Canfield Rd",
    "sg:city":"Youngstown",
    "sg:classifiers":[
        {
            "category":"Building & Trades",
            "subcategory":"Cleaning & Sanitation",
            "type":"Services"
        }
    ],
    "sg:phone":"+1 330 758 4000",
    "sg:postcode":"44512",
    "sg:province":"OH",
    "sg:tags":[
        "janitor"
    ],
    "wof:name":"Oasis Commercial Cleaning Svc",
    "wof:placetype":"venue"
},
  "geometry": {"coordinates":[-80.688287,41.024618],"type":"Point"}
}