{
  "type": "Feature",
  "properties": {
    "addr:full":"500 Thomas Ln Columbus OH 43214",
    "addr:housenumber":"500",
    "addr:postcode":"43214",
    "addr:street":"Thomas Ln",
    "iso:country":"US",
    "sg:address":"500 Thomas Ln",
    "sg:city":"Columbus",
    "sg:classifiers":[
        {
            "category":"Health Services",
            "subcategory":"Doctor",
            "type":"Services"
        }
    ],
    "sg:phone":"+1 614 538 2424",
    "sg:postcode":"43214",
    "sg:province":"OH",
    "sg:tags":[
        "physician",
        "surgeon"
    ],
    "wof:name":"Ohio ENT Surgeons Inc",
    "wof:placetype":"venue"
},
  "geometry": {"coordinates":[-83.03446700000001,40.032543],"type":"Point"}
}