{
  "type": "Feature",
  "properties": {
    "iso:country":"US",
    "sg:address":"4401 W 130th St",
    "sg:city":"Cleveland",
    "sg:classifiers":[
        {
            "category":"Wholesale",
            "subcategory":"Scrap",
            "type":"Manufacturing & Wholesale Goods"
        }
    ],
    "sg:phone":"+1 216 251 2277",
    "sg:postcode":"44135",
    "sg:province":"OH",
    "sg:tags":[
        "material"
    ],
    "wof:name":"Manson & Son",
    "wof:placetype":"venue"
},
  "geometry": {"coordinates":[-81.77996,41.43365],"type":"Point"}
}