{
  "type": "Feature",
  "properties": {
    "addr:full": "4401 W 130th St Cleveland OH 44135",
    "addr:housenumber": "4401",
    "addr:postcode": "44135",
    "addr:street": "W 130Th St",
    "iso:country": "US",
    "sg:address": "4401 W 130th St",
    "sg:city": "Cleveland",
    "sg:classifiers": [
      {
        "category": "Wholesale",
        "subcategory": "Scrap",
        "type": "Manufacturing \u0026 Wholesale Goods"
      }
    ],
    "sg:phone": "+1 216 251 2277",
    "sg:postcode": "44135",
    "sg:province": "OH",
    "sg:tags": [
      "material"
    ],
    "wof:name": "Manson \u0026 Son",
    "wof:placetype": "venue"
  },
  "geometry": {"coordinates":[-81.77996,41.43365],"type":"Point"}
}
