{
  "type": "Feature",
  "properties": {
    "iso:country":"US",
    "sg:address":"1933 Cole Rd",
    "sg:city":"Ashley",
    "sg:classifiers":[
        {
            "category":"Communications",
            "type":"Services"
        }
    ],
    "sg:phone":"+1 740 747 8503",
    "sg:postcode":"43003",
    "sg:province":"OH",
    "sg:tags":[
        "communication"
    ],
    "wof:name":"Cashman Communication",
    "wof:placetype":"venue"
},
  "geometry": {"coordinates":[-83.02488099999999,40.408641],"type":"Point"}
}