{
  "type": "Feature",
  "properties": {
    "iso:country":"US",
    "sg:address":"2579 Shawnee Rd",
    "sg:city":"Lima",
    "sg:classifiers":[
        {
            "category":"Wholesale",
            "subcategory":"Office Equipment",
            "type":"Manufacturing & Wholesale Goods"
        }
    ],
    "sg:phone":"+1 419 221 2679",
    "sg:postcode":"45806",
    "sg:province":"OH",
    "sg:tags":[
        "machine",
        "duplicating",
        "copying"
    ],
    "wof:name":"Office Concepts Ohio",
    "wof:placetype":"venue"
},
  "geometry": {"coordinates":[-84.151358,40.703598],"type":"Point"}
}