{
  "type": "Feature",
  "properties": {
    "iso:country":"US",
    "sg:address":"64 Oak Meadow Dr",
    "sg:city":"Pataskala",
    "sg:classifiers":[
        {
            "category":"Restaurant",
            "type":"Food & Drink"
        }
    ],
    "sg:phone":"+1 740 927 0088",
    "sg:postcode":"43062",
    "sg:province":"OH",
    "sg:tags":[
        "eating",
        "pizza"
    ],
    "wof:name":"Domino's Pizza",
    "wof:placetype":"venue"
},
  "geometry": {"coordinates":[-82.67828799999999,40.004298],"type":"Point"}
}