{
  "type": "Feature",
  "properties": {
    "addr:full": "64 Oak Meadow Dr Pataskala OH 43062",
    "addr:housenumber": "64",
    "addr:postcode": "43062",
    "addr:street": "Oak Meadow Dr",
    "iso:country": "US",
    "sg:address": "64 Oak Meadow Dr",
    "sg:city": "Pataskala",
    "sg:classifiers": [
      {
        "category": "Restaurant",
        "type": "Food \u0026 Drink"
      }
    ],
    "sg:phone": "+1 740 927 0088",
    "sg:postcode": "43062",
    "sg:province": "OH",
    "sg:tags": [
      "eating",
      "pizza"
    ],
    "wof:name": "Domino's Pizza",
    "wof:placetype": "venue"
  },
  "geometry": {"coordinates":[-82.678288,40.004298],"type":"Point"}
}
