{
  "type": "Feature",
  "properties": {
    "addr:full": "725 Wessor Ave Willard OH 44890",
    "addr:housenumber": "725",
    "addr:postcode": "44890",
    "addr:street": "Wessor Ave",
    "iso:country": "US",
    "sg:address": "725 Wessor Ave",
    "sg:city": "Willard",
    "sg:classifiers": [
      {
        "category": "Social Services",
        "subcategory": "Job Training",
        "type": "Services"
      }
    ],
    "sg:phone": "+1 419 933 6245",
    "sg:postcode": "44890",
    "sg:province": "OH",
    "sg:tags": [
      "rehabilitation"
    ],
    "sg:website": "www.rehabcare.com",
    "wof:name": "Rehab Care Group",
    "wof:placetype": "venue"
  },
  "geometry": {"coordinates":[-82.714896,41.056189],"type":"Point"}
}
