{
  "type": "Feature",
  "properties": {
    "iso:country":"US",
    "sg:address":"725 Wessor Ave",
    "sg:city":"Willard",
    "sg:classifiers":[
        {
            "category":"Social Services",
            "subcategory":"Job Training",
            "type":"Services"
        }
    ],
    "sg:phone":"+1 419 933 6245",
    "sg:postcode":"44890",
    "sg:province":"OH",
    "sg:tags":[
        "rehabilitation"
    ],
    "sg:website":"www.rehabcare.com",
    "wof:name":"Rehab Care Group",
    "wof:placetype":"venue"
},
  "geometry": {"coordinates":[-82.714896,41.056189],"type":"Point"}
}