{
  "type": "Feature",
  "properties": {
    "iso:country":"US",
    "sg:address":"5140 Mayfield Rd",
    "sg:city":"Cleveland",
    "sg:classifiers":[
        {
            "category":"Shopping",
            "subcategory":"Books",
            "type":"Retail Goods"
        }
    ],
    "sg:phone":"+1 440 442 1986",
    "sg:postcode":"44124",
    "sg:province":"OH",
    "wof:name":"North Coast Nostalgia",
    "wof:placetype":"venue"
},
  "geometry": {"coordinates":[-81.49095,41.519844],"type":"Point"}
}