{
  "type": "Feature",
  "properties": {
    "addr:full":"2463 W Rookwood Ct Cincinnati OH 45208",
    "addr:housenumber":"2463",
    "addr:postcode":"45208",
    "addr:street":"W Rookwood Ct",
    "iso:country":"US",
    "sg:address":"2463 W Rookwood Ct",
    "sg:city":"Cincinnati",
    "sg:classifiers":[
        {
            "category":"Professional",
            "subcategory":"Business Services",
            "type":"Services"
        }
    ],
    "sg:phone":"+1 513 871 1328",
    "sg:postcode":"45208",
    "sg:province":"OH",
    "sg:tags":[
        "interior",
        "consultant",
        "design",
        "decorator"
    ],
    "wof:name":"Mark L Kiddie",
    "wof:placetype":"venue"
},
  "geometry": {"coordinates":[-84.448666,39.132075],"type":"Point"}
}