{
  "type": "Feature",
  "properties": {
    "iso:country":"US",
    "sg:address":"111 E Washington St",
    "sg:city":"Painesville",
    "sg:classifiers":[
        {
            "category":"Professional",
            "subcategory":"Lawyer & Legal Services",
            "type":"Services"
        }
    ],
    "sg:phone":"+1 440 946 2322",
    "sg:postcode":"44077",
    "sg:province":"OH",
    "sg:tags":[
        "attorney"
    ],
    "wof:name":"David E Kerner Law Offices",
    "wof:placetype":"venue"
},
  "geometry": {"coordinates":[-81.24312,41.723047],"type":"Point"}
}