{
  "type": "Feature",
  "properties": {
    "addr:full": "7550 Lucerne Dr Cleveland OH 44130",
    "addr:housenumber": "7550",
    "addr:postcode": "44130",
    "addr:street": "Lucerne Dr",
    "iso:country": "US",
    "sg:address": "7550 Lucerne Dr",
    "sg:city": "Cleveland",
    "sg:classifiers": [
      {
        "category": "Professional",
        "subcategory": "Management \u0026 Consulting",
        "type": "Services"
      }
    ],
    "sg:phone": "+1 440 826 4900",
    "sg:postcode": "44130",
    "sg:province": "OH",
    "wof:name": "Brown and Caldwell Ohio",
    "wof:placetype": "venue"
  },
  "geometry": {"coordinates":[-81.817138,41.357746],"type":"Point"}
}
