{
  "type": "Feature",
  "properties": {
    "iso:country":"US",
    "sg:address":"2537 Glenmawr Ave",
    "sg:city":"Columbus",
    "sg:classifiers":[
        {
            "category":"Wholesale",
            "subcategory":"Electrical",
            "type":"Manufacturing & Wholesale Goods"
        }
    ],
    "sg:phone":"+1 614 263 6560",
    "sg:postcode":"43202",
    "sg:province":"OH",
    "sg:tags":[
        "control",
        "security",
        "system"
    ],
    "wof:name":"DSS Constr & Contracting LLC",
    "wof:placetype":"venue"
},
  "geometry": {"coordinates":[-82.99882700000001,40.016545],"type":"Point"}
}