{
  "type": "Feature",
  "properties": {
    "addr:full":"545 Glenrose Ave Cincinnati OH 45215",
    "addr:housenumber":"545",
    "addr:postcode":"45215",
    "addr:street":"Glenrose Ave",
    "iso:country":"US",
    "sg:address":"545 Glenrose Ave",
    "sg:city":"Cincinnati",
    "sg:classifiers":[
        {
            "category":"Professional",
            "type":"Services"
        }
    ],
    "sg:phone":"+1 513 948 4102",
    "sg:postcode":"45215",
    "sg:province":"OH",
    "wof:name":"Sandy McClemore",
    "wof:placetype":"venue"
},
  "geometry": {"coordinates":[-84.456548,39.216015],"type":"Point"}
}