{
  "type": "Feature",
  "properties": {
    "iso:country":"US",
    "sg:address":"1826 Lakeview Ave",
    "sg:city":"Dayton",
    "sg:classifiers":[
        {
            "category":"Personal",
            "subcategory":"Beauty Salon",
            "type":"Services"
        }
    ],
    "sg:phone":"+1 937 263 5648",
    "sg:postcode":"45408",
    "sg:province":"OH",
    "wof:name":"Mary's Hair Reflexions",
    "wof:placetype":"venue"
},
  "geometry": {"coordinates":[-84.225893,39.744901],"type":"Point"}
}