{
  "type": "Feature",
  "properties": {
    "addr:full": "180 Country Club Dr NE Warren OH 44484",
    "addr:housenumber": "180",
    "addr:postcode": "44484",
    "addr:street": "Country Club Dr Ne",
    "iso:country": "US",
    "sg:address": "180 Country Club Dr NE",
    "sg:city": "Warren",
    "sg:classifiers": [
      {
        "category": "Health Services",
        "subcategory": "Doctor",
        "type": "Services"
      }
    ],
    "sg:phone": "+1 330 856 4670",
    "sg:postcode": "44484",
    "sg:province": "OH",
    "sg:tags": [
      "physician",
      "surgeon"
    ],
    "wof:name": "Joseph N Cavalier DO",
    "wof:placetype": "venue"
  },
  "geometry": {"coordinates":[-80.772863,41.239294],"type":"Point"}
}
