{
  "type": "Feature",
  "properties": {
    "addr:full": "1830 W Market St Orrville OH 44667",
    "addr:housenumber": "1830",
    "addr:postcode": "44667",
    "addr:street": "W Market St",
    "iso:country": "US",
    "sg:address": "1830 W Market St",
    "sg:city": "Orrville",
    "sg:classifiers": [
      {
        "category": "Organizations",
        "subcategory": "Religious Organization",
        "type": "Services"
      }
    ],
    "sg:phone": "+1 330 682 6601",
    "sg:postcode": "44667",
    "sg:province": "OH",
    "sg:tags": [
      "church"
    ],
    "wof:name": "First Presbyterian Church",
    "wof:placetype": "venue"
  },
  "geometry": {"coordinates":[-81.789027,40.840685],"type":"Point"}
}
