{
  "type": "Feature",
  "properties": {
    "iso:country":"US",
    "sg:address":"4745 Shaunee Creek Dr",
    "sg:city":"Dayton",
    "sg:classifiers":[
        {
            "category":"Shopping",
            "subcategory":"Jewelry",
            "type":"Retail Goods"
        }
    ],
    "sg:phone":"+1 937 274 6984",
    "sg:postcode":"45415",
    "sg:province":"OH",
    "wof:name":"Goins Jewelry & Designs",
    "wof:placetype":"venue"
},
  "geometry": {"coordinates":[-84.238596,39.815665],"type":"Point"}
}