{
  "type": "Feature",
  "properties": {
    "addr:full": "8728 N High St Mineral City OH 44656",
    "addr:housenumber": "8728",
    "addr:postcode": "44656",
    "addr:street": "N High St",
    "iso:country": "US",
    "sg:address": "8728 N High St",
    "sg:city": "Mineral City",
    "sg:classifiers": [
      {
        "category": "Government",
        "subcategory": "Office",
        "type": "Public Place"
      }
    ],
    "sg:phone": "+1 330 859 2222",
    "sg:postcode": "44656",
    "sg:province": "OH",
    "sg:tags": [
      "city"
    ],
    "wof:name": "Mineral City Village Mayor",
    "wof:placetype": "venue"
  },
  "geometry": {"coordinates":[-81.363176,40.604066],"type":"Point"}
}
