{
  "type": "Feature",
  "properties": {
    "addr:full": "375 N Front St Columbus OH 43215",
    "addr:housenumber": "375",
    "addr:postcode": "43215",
    "addr:street": "N Front St",
    "iso:country": "US",
    "sg:address": "375 N Front St",
    "sg:city": "Columbus",
    "sg:classifiers": [
      {
        "category": "Banks \u0026 Credit Unions",
        "subcategory": "Financial Services",
        "type": "Services"
      }
    ],
    "sg:phone": "+1 614 857 2337",
    "sg:postcode": "43215",
    "sg:province": "OH",
    "sg:tags": [
      "investor"
    ],
    "wof:name": "Ad Investments LLC",
    "wof:placetype": "venue"
  },
  "geometry": {"coordinates":[-83.004041,39.970041],"type":"Point"}
}
