{
  "type": "Feature",
  "properties": {
    "addr:full": "1863 State Rte 590 Burgoon OH 43407",
    "addr:housenumber": "1863",
    "addr:postcode": "43407",
    "addr:street": "State Rte 590",
    "iso:country": "US",
    "sg:address": "1863 State Rte 590",
    "sg:city": "Burgoon",
    "sg:classifiers": [
      {
        "category": "Building \u0026 Trades",
        "subcategory": "Construction",
        "type": "Services"
      }
    ],
    "sg:phone": "+1 419 986 5621",
    "sg:postcode": "43407",
    "sg:province": "OH",
    "sg:tags": [
      "excavation",
      "contractor"
    ],
    "wof:name": "Aces Digging",
    "wof:placetype": "venue"
  },
  "geometry": {"coordinates":[-83.235442,41.28897],"type":"Point"}
}
