{
  "type": "Feature",
  "properties": {
    "iso:country":"US",
    "sg:address":"1863 State Rte 590",
    "sg:city":"Burgoon",
    "sg:classifiers":[
        {
            "category":"Building & Trades",
            "subcategory":"Construction",
            "type":"Services"
        }
    ],
    "sg:phone":"+1 419 986 5621",
    "sg:postcode":"43407",
    "sg:province":"OH",
    "sg:tags":[
        "excavation",
        "contractor"
    ],
    "wof:name":"Aces Digging",
    "wof:placetype":"venue"
},
  "geometry": {"coordinates":[-83.23544200000001,41.28897],"type":"Point"}
}