{
  "type": "Feature",
  "properties": {
    "iso:country":"US",
    "sg:address":"1237 Weathervane Ln",
    "sg:city":"Akron",
    "sg:classifiers":[
        {
            "category":"Insurance",
            "subcategory":"Insurance Agent",
            "type":"Services"
        }
    ],
    "sg:phone":"+1 330 867 4650",
    "sg:postcode":"44313",
    "sg:province":"OH",
    "wof:name":"Brokers of Northern Ohio",
    "wof:placetype":"venue"
},
  "geometry": {"coordinates":[-81.553027,41.134949],"type":"Point"}
}