{
  "type": "Feature",
  "properties": {
    "addr:full": "1308 Parkway Ct Fairfield OH 45014",
    "addr:housenumber": "1308",
    "addr:postcode": "45014",
    "addr:street": "Parkway Ct",
    "iso:country": "US",
    "sg:address": "1308 Parkway Ct",
    "sg:city": "Fairfield",
    "sg:classifiers": [
      {
        "category": "Professional",
        "subcategory": "Computer Services",
        "type": "Services"
      }
    ],
    "sg:phone": "+1 513 858 2016",
    "sg:postcode": "45014",
    "sg:province": "OH",
    "sg:tags": [
      "consultant",
      "designer"
    ],
    "wof:name": "Five Star Svc",
    "wof:placetype": "venue"
  },
  "geometry": {"coordinates":[-84.571124,39.318931],"type":"Point"}
}
