{
  "type": "Feature",
  "properties": {
    "addr:full": "1920 Forest Elm Ct Columbus OH 43229",
    "addr:housenumber": "1920",
    "addr:postcode": "43229",
    "addr:street": "Forest Elm Ct",
    "iso:country": "US",
    "sg:address": "1920 Forest Elm Ct",
    "sg:city": "Columbus",
    "sg:classifiers": [
      {
        "category": "Building \u0026 Trades",
        "subcategory": "Construction",
        "type": "Services"
      }
    ],
    "sg:phone": "+1 614 638 4286",
    "sg:postcode": "43229",
    "sg:province": "OH",
    "sg:tags": [
      "house"
    ],
    "wof:name": "Yeichner Construction",
    "wof:placetype": "venue"
  },
  "geometry": {"coordinates":[-82.965839,40.085508],"type":"Point"}
}
