{
  "type": "Feature",
  "properties": {
    "iso:country":"US",
    "sg:address":"1920 Forest Elm Ct",
    "sg:city":"Columbus",
    "sg:classifiers":[
        {
            "category":"Building & Trades",
            "subcategory":"Construction",
            "type":"Services"
        }
    ],
    "sg:phone":"+1 614 638 4286",
    "sg:postcode":"43229",
    "sg:province":"OH",
    "sg:tags":[
        "house"
    ],
    "wof:name":"Yeichner Construction",
    "wof:placetype":"venue"
},
  "geometry": {"coordinates":[-82.965839,40.085508],"type":"Point"}
}