{
  "type": "Feature",
  "properties": {
    "addr:full":"5986 King Rd SW Stone Creek OH 43840",
    "addr:housenumber":"5986",
    "addr:postcode":"43840",
    "addr:street":"King Rd Sw Stone Creek",
    "iso:country":"US",
    "sg:address":"5986 King Rd SW",
    "sg:city":"Stone Creek",
    "sg:classifiers":[
        {
            "category":"Professional",
            "subcategory":"Management & Consulting",
            "type":"Services"
        }
    ],
    "sg:phone":"+1 330 897 8660",
    "sg:postcode":"43840",
    "sg:province":"OH",
    "sg:tags":[
        "organization",
        "selling",
        "direct"
    ],
    "wof:name":"King Enterprises",
    "wof:placetype":"venue"
},
  "geometry": {"coordinates":[-81.622688,40.402176],"type":"Point"}
}