{
  "type": "Feature",
  "properties": {
    "addr:full": "56209 Wilson Rd Quaker City OH 43773",
    "addr:housenumber": "56209",
    "addr:postcode": "43773",
    "addr:street": "Wilson Rd",
    "iso:country": "US",
    "sg:address": "56209 Wilson Rd",
    "sg:city": "Quaker City",
    "sg:classifiers": [
      {
        "category": "Government",
        "subcategory": "Office",
        "type": "Public Place"
      }
    ],
    "sg:phone": "+1 740 679 2551",
    "sg:postcode": "43773",
    "sg:province": "OH",
    "sg:tags": [
      "village"
    ],
    "wof:name": "Wayne Twp Offices",
    "wof:placetype": "venue"
  },
  "geometry": {"coordinates":[-81.364714,39.912396],"type":"Point"}
}
