{
  "type": "Feature",
  "properties": {
    "iso:country":"US",
    "sg:address":"4998 Gurneyville Rd",
    "sg:city":"Wilmington",
    "sg:phone":"+1 937 382 5175",
    "sg:postcode":"45177",
    "sg:province":"OH",
    "sg:tags":[
        "farm",
        "corn"
    ],
    "wof:name":"John Mothersole Farm",
    "wof:placetype":"venue"
},
  "geometry": {"coordinates":[-83.916602,39.537818],"type":"Point"}
}