{
  "type": "Feature",
  "properties": {
    "iso:country":"US",
    "sg:address":"260 Avon Belden Rd",
    "sg:city":"Avon Lake",
    "sg:classifiers":[
        {
            "category":"Building & Trades",
            "subcategory":"Construction",
            "type":"Services"
        }
    ],
    "sg:phone":"+1 440 930 8922",
    "sg:postcode":"44012",
    "sg:province":"OH",
    "sg:tags":[
        "home",
        "builder"
    ],
    "wof:name":"Ryan Homes Waver",
    "wof:placetype":"venue"
},
  "geometry": {"coordinates":[-82.018805,41.503483],"type":"Point"}
}