{
  "type": "Feature",
  "properties": {
    "iso:country":"US",
    "sg:address":"10868 Portage St NW",
    "sg:city":"Canal Fulton",
    "sg:classifiers":[
        {
            "category":"Shopping",
            "type":"Retail Goods"
        },
        {
            "category":"Shopping",
            "subcategory":"Pharmacy",
            "type":"Retail Goods"
        }
    ],
    "sg:phone":"+1 330 494 5121",
    "sg:postcode":"44614",
    "sg:province":"OH",
    "sg:tags":[
        "aid",
        "first",
        "merchandise",
        "supply"
    ],
    "wof:name":"Affirmed First Aid & Safety",
    "wof:placetype":"venue"
},
  "geometry": {"coordinates":[-81.552708,40.881491],"type":"Point"}
}