{
  "type": "Feature",
  "properties": {
    "addr:full": "10868 Portage St NW Canal Fulton OH 44614",
    "addr:housenumber": "10868",
    "addr:postcode": "44614",
    "addr:street": "Portage St Nw",
    "iso:country": "US",
    "sg:address": "10868 Portage St NW",
    "sg:city": "Canal Fulton",
    "sg:classifiers": [
      {
        "category": "Shopping",
        "type": "Retail Goods"
      },
      {
        "category": "Shopping",
        "subcategory": "Pharmacy",
        "type": "Retail Goods"
      }
    ],
    "sg:phone": "+1 330 494 5121",
    "sg:postcode": "44614",
    "sg:province": "OH",
    "sg:tags": [
      "aid",
      "first",
      "merchandise",
      "supply"
    ],
    "wof:name": "Affirmed First Aid \u0026 Safety",
    "wof:placetype": "venue"
  },
  "geometry": {"coordinates":[-81.552708,40.881491],"type":"Point"}
}
