{
  "type": "Feature",
  "properties": {
    "addr:full":"17669 Pioneer Rd Middlefield OH 44062",
    "addr:housenumber":"17669",
    "addr:postcode":"44062",
    "addr:street":"Pioneer Rd",
    "iso:country":"US",
    "sg:address":"17669 Pioneer Rd",
    "sg:city":"Middlefield",
    "sg:classifiers":[
        {
            "category":"Freight",
            "type":"Transportation"
        }
    ],
    "sg:phone":"+1 440 636 5303",
    "sg:postcode":"44062",
    "sg:province":"OH",
    "sg:tags":[
        "operator",
        "refuse",
        "local",
        "system",
        "trucking"
    ],
    "wof:name":"A & G Trucking",
    "wof:placetype":"venue"
},
  "geometry": {"coordinates":[-81.02037,41.521275],"type":"Point"}
}