{
  "type": "Feature",
  "properties": {
    "iso:country":"US",
    "sg:address":"29260 Starr Route Rd",
    "sg:city":"Logan",
    "sg:classifiers":[
        {
            "category":"Farming",
            "subcategory":"Livestock Farm",
            "type":"Manufacturing & Wholesale Goods"
        }
    ],
    "sg:phone":"+1 740 385 2986",
    "sg:postcode":"43138",
    "sg:province":"OH",
    "wof:name":"Krinn Farm",
    "wof:placetype":"venue"
},
  "geometry": {"coordinates":[-82.47965499999999,39.520009],"type":"Point"}
}