{
  "type": "Feature",
  "properties": {
    "addr:full": "29260 Starr Route Rd Logan OH 43138",
    "addr:postcode": "29260;43138",
    "addr:street": "Route Rd",
    "iso:country": "US",
    "sg:address": "29260 Starr Route Rd",
    "sg:city": "Logan",
    "sg:classifiers": [
      {
        "category": "Farming",
        "subcategory": "Livestock Farm",
        "type": "Manufacturing \u0026 Wholesale Goods"
      }
    ],
    "sg:phone": "+1 740 385 2986",
    "sg:postcode": "43138",
    "sg:province": "OH",
    "wof:name": "Krinn Farm",
    "wof:placetype": "venue"
  },
  "geometry": {"coordinates":[-82.479655,39.520009],"type":"Point"}
}
