{
  "type": "Feature",
  "properties": {
    "iso:country":"US",
    "sg:address":"3637 S High St",
    "sg:city":"Columbus",
    "sg:classifiers":[
        {
            "category":"Food & Beverages",
            "subcategory":"Groceries & Convenience Stores",
            "type":"Retail Goods"
        }
    ],
    "sg:phone":"+1 614 492 1077",
    "sg:postcode":"43207",
    "sg:province":"OH",
    "sg:tags":[
        "grocer"
    ],
    "wof:name":"Kroger",
    "wof:placetype":"venue"
},
  "geometry": {"coordinates":[-82.99956,39.885514],"type":"Point"}
}