{
  "type": "Feature",
  "properties": {
    "addr:full": "513 W Main St Lakeside Marblhd OH 43440",
    "addr:housenumber": "513",
    "addr:postcode": "43440",
    "addr:street": "W Main St",
    "iso:country": "US",
    "sg:address": "513 W Main St",
    "sg:city": "Lakeside Marblhd",
    "sg:classifiers": [
      {
        "category": "Government",
        "subcategory": "Office",
        "type": "Public Place"
      }
    ],
    "sg:phone": "+1 419 798 9229",
    "sg:postcode": "43440",
    "sg:province": "OH",
    "sg:tags": [
      "village"
    ],
    "wof:name": "Marblehead Vlg Maintenance",
    "wof:placetype": "venue"
  },
  "geometry": {"coordinates":[-82.731809,41.540314],"type":"Point"}
}
