{
  "type": "Feature",
  "properties": {
    "iso:country":"US",
    "sg:address":"1879 S Limestone St",
    "sg:city":"Springfield",
    "sg:classifiers":[
        {
            "category":"Cinema",
            "subcategory":"Movie Rental",
            "type":"Entertainment"
        }
    ],
    "sg:phone":"+1 937 324 0685",
    "sg:postcode":"45505",
    "sg:province":"OH",
    "sg:tags":[
        "personal",
        "video",
        "tape"
    ],
    "wof:name":"Videotan Etc LLC",
    "wof:placetype":"venue"
},
  "geometry": {"coordinates":[-83.810904,39.900969],"type":"Point"}
}