{
  "type": "Feature",
  "properties": {
    "iso:country":"US",
    "sg:address":"3555 Hanley Rd",
    "sg:city":"Perrysburg",
    "sg:classifiers":[
        {
            "category":"Travel",
            "subcategory":"Hotels & Motels",
            "type":"Entertainment"
        }
    ],
    "sg:phone":"+1 419 837 5245",
    "sg:postcode":"43551",
    "sg:province":"OH",
    "wof:name":"Howard Johnson",
    "wof:placetype":"venue"
},
  "geometry": {"coordinates":[-83.464044,41.529411],"type":"Point"}
}