{
  "type": "Feature",
  "properties": {
    "addr:full": "3555 Hanley Rd Perrysburg OH 43551",
    "addr:housenumber": "3555",
    "addr:postcode": "43551",
    "addr:street": "Hanley Rd",
    "iso:country": "US",
    "sg:address": "3555 Hanley Rd",
    "sg:city": "Perrysburg",
    "sg:classifiers": [
      {
        "category": "Travel",
        "subcategory": "Hotels \u0026 Motels",
        "type": "Entertainment"
      }
    ],
    "sg:phone": "+1 419 837 5245",
    "sg:postcode": "43551",
    "sg:province": "OH",
    "wof:name": "Howard Johnson",
    "wof:placetype": "venue"
  },
  "geometry": {"coordinates":[-83.464044,41.529411],"type":"Point"}
}
