{
  "type": "Feature",
  "properties": {
    "addr:full":"1165 Harwood Dr Mansfield OH 44906",
    "addr:housenumber":"1165",
    "addr:postcode":"44906",
    "addr:street":"Harwood Dr",
    "iso:country":"US",
    "sg:address":"1165 Harwood Dr",
    "sg:city":"Mansfield",
    "sg:classifiers":[
        {
            "category":"Organizations",
            "subcategory":"Religious Organization",
            "type":"Services"
        }
    ],
    "sg:phone":"+1 419 529 4319",
    "sg:postcode":"44906",
    "sg:province":"OH",
    "sg:tags":[
        "clergy"
    ],
    "wof:name":"Porter Richards",
    "wof:placetype":"venue"
},
  "geometry": {"coordinates":[-82.561915,40.756848],"type":"Point"}
}