{
  "type": "Feature",
  "properties": {
    "addr:full":"6681 Ridge Rd Cleveland OH 44129",
    "addr:housenumber":"6681",
    "addr:postcode":"44129",
    "addr:street":"Ridge Rd",
    "iso:country":"US",
    "sg:address":"6681 Ridge Rd",
    "sg:city":"Cleveland",
    "sg:classifiers":[
        {
            "category":"Professional",
            "type":"Services"
        }
    ],
    "sg:phone":"+1 440 887 9645",
    "sg:postcode":"44129",
    "sg:province":"OH",
    "wof:name":"Westside Heart Inc",
    "wof:placetype":"venue"
},
  "geometry": {"coordinates":[-81.73462499999999,41.380706],"type":"Point"}
}