{
  "type": "Feature",
  "properties": {
    "addr:full": "4597 Dixie Hwy Fairfield OH 45014",
    "addr:housenumber": "4597",
    "addr:postcode": "45014",
    "addr:street": "Dixie Hwy",
    "iso:country": "US",
    "sg:address": "4597 Dixie Hwy",
    "sg:city": "Fairfield",
    "sg:classifiers": [
      {
        "category": "Social Services",
        "type": "Services"
      }
    ],
    "sg:phone": "+1 513 821 6190",
    "sg:postcode": "45014",
    "sg:province": "OH",
    "sg:tags": [
      "organization",
      "welfare"
    ],
    "wof:name": "Moving Causes",
    "wof:placetype": "venue"
  },
  "geometry": {"coordinates":[-84.542426,39.353978],"type":"Point"}
}
