{
  "type": "Feature",
  "properties": {
    "addr:full":"370 2nd St Morrow OH 45152",
    "addr:housenumber":"370",
    "addr:postcode":"45152",
    "addr:street":"2Nd St",
    "iso:country":"US",
    "sg:address":"370 2nd St",
    "sg:city":"Morrow",
    "sg:classifiers":[
        {
            "category":"Real Estate",
            "subcategory":"Real Estate Agent",
            "type":"Services"
        }
    ],
    "sg:phone":"+1 513 899 4841",
    "sg:postcode":"45152",
    "sg:province":"OH",
    "wof:name":"Salem Township Cemetery",
    "wof:placetype":"venue"
},
  "geometry": {"coordinates":[-84.125793,39.350805],"type":"Point"}
}