{
  "type": "Feature",
  "properties": {
    "iso:country":"US",
    "sg:address":"2705 Fulton Dr NW",
    "sg:city":"Canton",
    "sg:classifiers":[
        {
            "category":"Retail",
            "subcategory":"Animal Services",
            "type":"Services"
        }
    ],
    "sg:phone":"+1 330 588 8660",
    "sg:postcode":"44718",
    "sg:province":"OH",
    "sg:tags":[
        "pet",
        "grooming",
        "washing"
    ],
    "wof:name":"Classic Pets",
    "wof:placetype":"venue"
},
  "geometry": {"coordinates":[-81.40125,40.826378],"type":"Point"}
}