{
  "type": "Feature",
  "properties": {
    "iso:country":"US",
    "sg:address":"723 Bacon Ave",
    "sg:city":"East Palestine",
    "sg:classifiers":[
        {
            "category":"Retail",
            "subcategory":"Auto Repair",
            "type":"Services"
        }
    ],
    "sg:phone":"+1 330 426 1818",
    "sg:postcode":"44413",
    "sg:province":"OH",
    "sg:tags":[
        "repairing",
        "automobile"
    ],
    "wof:name":"Leake Service Ctr",
    "wof:placetype":"venue"
},
  "geometry": {"coordinates":[-80.55235999999999,40.833321],"type":"Point"}
}