{
  "type": "Feature",
  "properties": {
    "addr:full":"9412 Buckeye Rd Cleveland OH 44104",
    "addr:housenumber":"9412",
    "addr:postcode":"44104",
    "addr:street":"Buckeye Rd",
    "iso:country":"US",
    "sg:address":"9412 Buckeye Rd",
    "sg:city":"Cleveland",
    "sg:classifiers":[
        {
            "category":"Education",
            "subcategory":"College",
            "type":"Public Place"
        }
    ],
    "sg:phone":"+1 216 421 2585",
    "sg:postcode":"44104",
    "sg:province":"OH",
    "wof:name":"Hope Alliance Church",
    "wof:placetype":"venue"
},
  "geometry": {"coordinates":[-81.620167,41.483998],"type":"Point"}
}