{
  "type": "Feature",
  "properties": {
    "addr:full": "2286 Nayland Rd Columbus OH 43220",
    "addr:housenumber": "2286",
    "addr:postcode": "43220",
    "addr:street": "Nayland Rd",
    "iso:country": "US",
    "sg:address": "2286 Nayland Rd",
    "sg:city": "Columbus",
    "sg:classifiers": [
      {
        "category": "Real Estate",
        "subcategory": "Real Estate Agent",
        "type": "Services"
      }
    ],
    "sg:phone": "+1 614 451 8956",
    "sg:postcode": "43220",
    "sg:province": "OH",
    "wof:name": "Joseph W Webber Jr",
    "wof:placetype": "venue"
  },
  "geometry": {"coordinates":[-83.077961,40.038264],"type":"Point"}
}
