{
  "type": "Feature",
  "properties": {
    "addr:full": "4136 Colonel Glenn Hwy Beavercreek OH 45431",
    "addr:housenumber": "4136",
    "addr:postcode": "45431",
    "addr:street": "Colonel Glenn Hwy",
    "iso:country": "US",
    "sg:address": "4136 Colonel Glenn Hwy",
    "sg:city": "Beavercreek",
    "sg:classifiers": [
      {
        "category": "Real Estate",
        "subcategory": "Real Estate Agent",
        "type": "Services"
      }
    ],
    "sg:phone": "+1 937 429 0167",
    "sg:postcode": "45431",
    "sg:province": "OH",
    "wof:name": "Jim Sisk Realty Inc",
    "wof:placetype": "venue"
  },
  "geometry": {"coordinates":[-84.087621,39.773494],"type":"Point"}
}
