{
  "type": "Feature",
  "properties": {
    "addr:full":"643 Henry St SE Niles OH 44446",
    "addr:housenumber":"643",
    "addr:postcode":"44446",
    "addr:street":"Henry St Se",
    "iso:country":"US",
    "sg:address":"643 Henry St SE",
    "sg:city":"Niles",
    "sg:classifiers":[
        {
            "category":"Manufacturing",
            "subcategory":"Metals",
            "type":"Manufacturing & Wholesale Goods"
        }
    ],
    "sg:phone":"+1 330 652 4165",
    "sg:postcode":"44446",
    "sg:province":"OH",
    "sg:tags":[
        "extruded",
        "product",
        "aluminum",
        "mfg"
    ],
    "wof:name":"Indalex Inc",
    "wof:placetype":"venue"
},
  "geometry": {"coordinates":[-80.751052,41.176552],"type":"Point"}
}