{
  "type": "Feature",
  "properties": {
    "addr:full": "1989 W 5th Ave Columbus OH 43212",
    "addr:housenumber": "1989",
    "addr:postcode": "43212",
    "addr:street": "W 5Th Ave",
    "iso:country": "US",
    "sg:address": "1989 W 5th Ave",
    "sg:city": "Columbus",
    "sg:classifiers": [
      {
        "category": "Professional",
        "subcategory": "Accounting \u0026 Tax Preparation",
        "type": "Services"
      }
    ],
    "sg:phone": "+1 614 488 0061",
    "sg:postcode": "43212",
    "sg:province": "OH",
    "sg:tags": [
      "accountant"
    ],
    "wof:name": "Warner \u0026 Harper",
    "wof:placetype": "venue"
  },
  "geometry": {"coordinates":[-83.059634,39.989345],"type":"Point"}
}
