{
  "type": "Feature",
  "properties": {
    "iso:country":"US",
    "sg:address":"1989 W 5th Ave",
    "sg:city":"Columbus",
    "sg:classifiers":[
        {
            "category":"Professional",
            "subcategory":"Accounting & Tax Preparation",
            "type":"Services"
        }
    ],
    "sg:phone":"+1 614 488 0061",
    "sg:postcode":"43212",
    "sg:province":"OH",
    "sg:tags":[
        "accountant"
    ],
    "wof:name":"Warner & Harper",
    "wof:placetype":"venue"
},
  "geometry": {"coordinates":[-83.059634,39.989345],"type":"Point"}
}