{
  "type": "Feature",
  "properties": {
    "addr:full": "1037 Parsons Ave Columbus OH 43206",
    "addr:housenumber": "1037",
    "addr:postcode": "43206",
    "addr:street": "Parsons Ave",
    "iso:country": "US",
    "sg:address": "1037 Parsons Ave",
    "sg:city": "Columbus",
    "sg:classifiers": [
      {
        "category": "Manufacturing",
        "subcategory": "Printing",
        "type": "Manufacturing \u0026 Wholesale Goods"
      }
    ],
    "sg:phone": "+1 614 443 0701",
    "sg:postcode": "43206",
    "sg:province": "OH",
    "sg:tags": [
      "bookbinder"
    ],
    "wof:name": "Book Color Bindery",
    "wof:placetype": "venue"
  },
  "geometry": {"coordinates":[-82.983165,39.942576],"type":"Point"}
}
