{
  "type": "Feature",
  "properties": {
    "iso:country":"US",
    "sg:address":"9039 Springboro Pike",
    "sg:city":"Miamisburg",
    "sg:classifiers":[
        {
            "category":"Professional",
            "subcategory":"Engineering",
            "type":"Services"
        }
    ],
    "sg:phone":"+1 937 384 9940",
    "sg:postcode":"45342",
    "sg:province":"OH",
    "sg:tags":[
        "consulting",
        "business",
        "engineer"
    ],
    "sg:website":"www.haleyaldrich.com",
    "wof:name":"Haley & Aldrich Inc",
    "wof:placetype":"venue"
},
  "geometry": {"coordinates":[-84.22735299999999,39.615774],"type":"Point"}
}