{
  "type": "Feature",
  "properties": {
    "addr:full": "9039 Springboro Pike Miamisburg OH 45342",
    "addr:housenumber": "9039",
    "addr:postcode": "45342",
    "addr:street": "Springboro Pike",
    "iso:country": "US",
    "sg:address": "9039 Springboro Pike",
    "sg:city": "Miamisburg",
    "sg:classifiers": [
      {
        "category": "Professional",
        "subcategory": "Engineering",
        "type": "Services"
      }
    ],
    "sg:phone": "+1 937 384 9940",
    "sg:postcode": "45342",
    "sg:province": "OH",
    "sg:tags": [
      "consulting",
      "business",
      "engineer"
    ],
    "sg:website": "www.haleyaldrich.com",
    "wof:name": "Haley \u0026 Aldrich Inc",
    "wof:placetype": "venue"
  },
  "geometry": {"coordinates":[-84.227353,39.615774],"type":"Point"}
}
