{
  "type": "Feature",
  "properties": {
    "addr:full":"5201 Denison Ave Cleveland OH 44102",
    "addr:housenumber":"5201",
    "addr:postcode":"44102",
    "addr:street":"Denison Ave",
    "iso:country":"US",
    "sg:address":"5201 Denison Ave",
    "sg:city":"Cleveland",
    "sg:classifiers":[
        {
            "category":"Building & Trades",
            "subcategory":"Equipment Rental",
            "type":"Services"
        }
    ],
    "sg:phone":"+1 216 651 3750",
    "sg:postcode":"44102",
    "sg:province":"OH",
    "sg:tags":[
        "machine",
        "vending"
    ],
    "wof:name":"Quality Refreshments",
    "wof:placetype":"venue"
},
  "geometry": {"coordinates":[-81.72555199999999,41.456317],"type":"Point"}
}