{
  "type": "Feature",
  "properties": {
    "iso:country":"US",
    "sg:address":"4075 Port Union Rd",
    "sg:city":"Fairfield",
    "sg:classifiers":[
        {
            "category":"Freight",
            "type":"Transportation"
        }
    ],
    "sg:phone":"+1 513 942 7500",
    "sg:postcode":"45014",
    "sg:province":"OH",
    "sg:tags":[
        "operator",
        "local",
        "mover",
        "storage",
        "trucking"
    ],
    "sg:website":"www.bellmoving.com",
    "wof:name":"Bell Moving & Storage Inc",
    "wof:placetype":"venue"
},
  "geometry": {"coordinates":[-84.484454,39.331324],"type":"Point"}
}