{
  "type": "Feature",
  "properties": {
    "addr:full":"1450 Courtright Rd Columbus OH 43227",
    "addr:housenumber":"1450",
    "addr:postcode":"43227",
    "addr:street":"Courtright Rd",
    "iso:country":"US",
    "sg:address":"1450 Courtright Rd",
    "sg:city":"Columbus",
    "sg:classifiers":[
        {
            "category":"Restaurant",
            "type":"Food & Drink"
        }
    ],
    "sg:phone":"+1 614 238 3600",
    "sg:postcode":"43227",
    "sg:province":"OH",
    "wof:name":"Queens Pizza",
    "wof:placetype":"venue"
},
  "geometry": {"coordinates":[-82.89710100000001,39.942485],"type":"Point"}
}