{
  "type": "Feature",
  "properties": {
    "addr:full": "1223 Brookfield Rd Hubbard OH 44425",
    "addr:housenumber": "1223",
    "addr:postcode": "44425",
    "addr:street": "Brookfield Rd",
    "iso:country": "US",
    "sg:address": "1223 Brookfield Rd",
    "sg:city": "Hubbard",
    "sg:classifiers": [
      {
        "category": "Health Services",
        "subcategory": "Chiropractor",
        "type": "Services"
      }
    ],
    "sg:phone": "+1 330 448 8672",
    "sg:postcode": "44425",
    "sg:province": "OH",
    "sg:tags": [
      "chiropractic"
    ],
    "wof:name": "Jones Chiropractic Clinic Inc",
    "wof:placetype": "venue"
  },
  "geometry": {"coordinates":[-80.5678,41.209332],"type":"Point"}
}
