{
  "type": "Feature",
  "properties": {
    "iso:country":"US",
    "sg:address":"1223 Brookfield Rd",
    "sg:city":"Hubbard",
    "sg:classifiers":[
        {
            "category":"Health Services",
            "subcategory":"Chiropractor",
            "type":"Services"
        }
    ],
    "sg:phone":"+1 330 448 8672",
    "sg:postcode":"44425",
    "sg:province":"OH",
    "sg:tags":[
        "chiropractic"
    ],
    "wof:name":"Jones Chiropractic Clinic Inc",
    "wof:placetype":"venue"
},
  "geometry": {"coordinates":[-80.56780000000001,41.209332],"type":"Point"}
}