{
  "type": "Feature",
  "properties": {
    "iso:country":"US",
    "sg:address":"5746 Lawrence Rd",
    "sg:city":"Cincinnati",
    "sg:classifiers":[
        {
            "category":"Building & Trades",
            "subcategory":"Construction",
            "type":"Services"
        }
    ],
    "sg:phone":"+1 513 574 0008",
    "sg:postcode":"45248",
    "sg:province":"OH",
    "sg:tags":[
        "handyman",
        "contractor"
    ],
    "wof:name":"A West Side Home Repair Svc",
    "wof:placetype":"venue"
},
  "geometry": {"coordinates":[-84.64285099999999,39.150298],"type":"Point"}
}