{
  "type": "Feature",
  "properties": {
    "addr:full":"11970 Apollo Dr Cleveland OH 44133",
    "addr:housenumber":"11970",
    "addr:postcode":"44133",
    "addr:street":"Apollo Dr",
    "iso:country":"US",
    "sg:address":"11970 Apollo Dr",
    "sg:city":"Cleveland",
    "sg:classifiers":[
        {
            "category":"Professional",
            "subcategory":"Management & Consulting",
            "type":"Services"
        }
    ],
    "sg:phone":"+1 440 230 0283",
    "sg:postcode":"44133",
    "sg:province":"OH",
    "sg:tags":[
        "marketing",
        "program"
    ],
    "wof:name":"Ultra Marketing",
    "wof:placetype":"venue"
},
  "geometry": {"coordinates":[-81.705592,41.327513],"type":"Point"}
}