{
  "type": "Feature",
  "properties": {
    "iso:country":"US",
    "sg:address":"25 Aqueduct St",
    "sg:city":"Akron",
    "sg:classifiers":[
        {
            "category":"Building & Trades",
            "subcategory":"Construction",
            "type":"Services"
        }
    ],
    "sg:phone":"+1 330 434 2266",
    "sg:postcode":"44303",
    "sg:province":"OH",
    "sg:tags":[
        "real",
        "e",
        "residential",
        "commercial",
        "contractor",
        "remodeling"
    ],
    "wof:name":"Biasella Company Home Imprv",
    "wof:placetype":"venue"
},
  "geometry": {"coordinates":[-81.530568,41.091562],"type":"Point"}
}