{
  "type": "Feature",
  "properties": {
    "addr:full": "14320 Ridge Rd Cleveland OH 44133",
    "addr:housenumber": "14320",
    "addr:postcode": "44133",
    "addr:street": "Ridge Rd",
    "iso:country": "US",
    "sg:address": "14320 Ridge Rd",
    "sg:city": "Cleveland",
    "sg:classifiers": [
      {
        "category": "Health Services",
        "subcategory": "Doctor",
        "type": "Services"
      }
    ],
    "sg:phone": "+1 440 230 2400",
    "sg:postcode": "44133",
    "sg:province": "OH",
    "sg:tags": [
      "physician",
      "surgeon"
    ],
    "wof:name": "Michael E Debs Inc",
    "wof:placetype": "venue"
  },
  "geometry": {"coordinates":[-81.734648,41.313144],"type":"Point"}
}
