{
  "type": "Feature",
  "properties": {
    "iso:country":"US",
    "sg:address":"142 N Main St",
    "sg:city":"Marion",
    "sg:classifiers":[
        {
            "category":"Restaurant",
            "type":"Food & Drink"
        }
    ],
    "sg:phone":"+1 740 387 3764",
    "sg:postcode":"43302",
    "sg:province":"OH",
    "sg:tags":[
        "cafe"
    ],
    "wof:name":"Old Town Cafe",
    "wof:placetype":"venue"
},
  "geometry": {"coordinates":[-83.128827,40.58961],"type":"Point"}
}