{
  "type": "Feature",
  "properties": {
    "addr:full": "1608 Druid Dr Copley OH 44321",
    "addr:housenumber": "1608",
    "addr:postcode": "44321",
    "addr:street": "Druid Dr",
    "iso:country": "US",
    "sg:address": "1608 Druid Dr",
    "sg:city": "Copley",
    "sg:classifiers": [
      {
        "category": "Professional",
        "subcategory": "Art Services",
        "type": "Services"
      }
    ],
    "sg:phone": "+1 330 666 8070",
    "sg:postcode": "44321",
    "sg:province": "OH",
    "sg:tags": [
      "graphic",
      "designer"
    ],
    "wof:name": "Creative Images",
    "wof:placetype": "venue"
  },
  "geometry": {"coordinates":[-81.635704,41.0927],"type":"Point"}
}
