{
  "type": "Feature",
  "properties": {
    "iso:country":"US",
    "sg:address":"1608 Druid Dr",
    "sg:city":"Copley",
    "sg:classifiers":[
        {
            "category":"Professional",
            "subcategory":"Art Services",
            "type":"Services"
        }
    ],
    "sg:phone":"+1 330 666 8070",
    "sg:postcode":"44321",
    "sg:province":"OH",
    "sg:tags":[
        "graphic",
        "designer"
    ],
    "wof:name":"Creative Images",
    "wof:placetype":"venue"
},
  "geometry": {"coordinates":[-81.635704,41.0927],"type":"Point"}
}