{
  "type": "Feature",
  "properties": {
    "addr:full":"9909 Avon Lake Rd Burbank OH 44214",
    "addr:housenumber":"9909",
    "addr:postcode":"44214",
    "addr:street":"Avon Lake Rd",
    "iso:country":"US",
    "sg:address":"9909 Avon Lake Rd",
    "sg:city":"Burbank",
    "sg:classifiers":[
        {
            "category":"Food & Beverages",
            "subcategory":"Candy",
            "type":"Retail Goods"
        }
    ],
    "sg:phone":"+1 330 948 9953",
    "sg:postcode":"44214",
    "sg:province":"OH",
    "sg:tags":[
        "confectionery"
    ],
    "sg:website":"www.rmcf.com",
    "wof:name":"Rocky Mountain Chocolate Fctry",
    "wof:placetype":"venue"
},
  "geometry": {"coordinates":[-81.996174,41.003022],"type":"Point"}
}