{
  "type": "Feature",
  "properties": {
    "addr:full":"12914 US Hwy 68 Kenton OH 43326",
    "addr:housenumber":"12914",
    "addr:postcode":"43326",
    "addr:street":"Us Hwy 68",
    "iso:country":"US",
    "sg:address":"12914 US Hwy 68",
    "sg:city":"Kenton",
    "sg:classifiers":[
        {
            "category":"Food & Beverages",
            "subcategory":"Groceries & Convenience Stores",
            "type":"Retail Goods"
        }
    ],
    "sg:phone":"+1 419 673 9248",
    "sg:postcode":"43326",
    "sg:province":"OH",
    "wof:name":"Lambs Corner Market",
    "wof:placetype":"venue"
},
  "geometry": {"coordinates":[-83.614745,40.632417],"type":"Point"}
}