{
  "type": "Feature",
  "properties": {
    "iso:country":"US",
    "sg:address":"2137 Shyville Rd",
    "sg:city":"Piketon",
    "sg:classifiers":[
        {
            "category":"Organizations",
            "subcategory":"Non-profit Organization",
            "type":"Services"
        }
    ],
    "sg:phone":"+1 740 289 4944",
    "sg:postcode":"45661",
    "sg:province":"OH",
    "sg:tags":[
        "alternative",
        "abortion"
    ],
    "wof:name":"Pregnancy Care Ctr",
    "wof:placetype":"venue"
},
  "geometry": {"coordinates":[-82.99836000000001,39.057444],"type":"Point"}
}