{
  "type": "Feature",
  "properties": {
    "addr:full": "2137 Shyville Rd Piketon OH 45661",
    "addr:housenumber": "2137",
    "addr:postcode": "45661",
    "addr:street": "Shyville Rd",
    "iso:country": "US",
    "sg:address": "2137 Shyville Rd",
    "sg:city": "Piketon",
    "sg:classifiers": [
      {
        "category": "Organizations",
        "subcategory": "Non-profit Organization",
        "type": "Services"
      }
    ],
    "sg:phone": "+1 740 289 4944",
    "sg:postcode": "45661",
    "sg:province": "OH",
    "sg:tags": [
      "alternative",
      "abortion"
    ],
    "wof:name": "Pregnancy Care Ctr",
    "wof:placetype": "venue"
  },
  "geometry": {"coordinates":[-82.99836,39.057444],"type":"Point"}
}
