{
  "type": "Feature",
  "properties": {
    "addr:full":"11336 Pelican Cove Painesville OH 44077",
    "addr:housenumber":"11336",
    "addr:postcode":"44077",
    "addr:street":"Pelican Cove",
    "iso:country":"US",
    "sg:address":"11336 Pelican Cove",
    "sg:city":"Painesville",
    "sg:classifiers":[
        {
            "category":"Sports & Exercise",
            "subcategory":"Golf",
            "type":"Entertainment"
        }
    ],
    "sg:phone":"+1 440 357 6258",
    "sg:postcode":"44077",
    "sg:province":"OH",
    "sg:tags":[
        "course"
    ],
    "sg:website":"www.ncjt.org",
    "wof:name":"North Coast Junior Golf Tour",
    "wof:placetype":"venue"
},
  "geometry": {"coordinates":[-81.232158,41.673839],"type":"Point"}
}