{
  "type": "Feature",
  "properties": {
    "addr:full": "5641 Ridge Rd Cleveland OH 44129",
    "addr:housenumber": "5641",
    "addr:postcode": "44129",
    "addr:street": "Ridge Rd",
    "iso:country": "US",
    "sg:address": "5641 Ridge Rd",
    "sg:city": "Cleveland",
    "sg:classifiers": [
      {
        "category": "Retail",
        "subcategory": "Repair Shop",
        "type": "Services"
      }
    ],
    "sg:phone": "+1 440 845 7940",
    "sg:postcode": "44129",
    "sg:province": "OH",
    "sg:tags": [
      "lock",
      "locksmith"
    ],
    "wof:name": "Fort Worth Lock \u0026 Key",
    "wof:placetype": "venue"
  },
  "geometry": {"coordinates":[-81.734552,41.408082],"type":"Point"}
}
