{
  "type": "Feature",
  "properties": {
    "addr:full": "314 N 7th St Upper Sandusky OH 43351",
    "addr:housenumber": "314",
    "addr:postcode": "43351",
    "addr:street": "N 7Th St",
    "iso:country": "US",
    "sg:address": "314 N 7th St",
    "sg:city": "Upper Sandusky",
    "sg:classifiers": [
      {
        "category": "Building \u0026 Trades",
        "subcategory": "Construction",
        "type": "Services"
      }
    ],
    "sg:phone": "+1 419 294 4411",
    "sg:postcode": "43351",
    "sg:province": "OH",
    "sg:tags": [
      "residential"
    ],
    "wof:name": "Kennedy Construction",
    "wof:placetype": "venue"
  },
  "geometry": {"coordinates":[-83.283037,40.831431],"type":"Point"}
}
