{
  "type": "Feature",
  "properties": {
    "addr:full": "4599 State Rte 235 Ada OH 45810",
    "addr:housenumber": "4599",
    "addr:postcode": "45810",
    "addr:street": "State Rte 235",
    "iso:country": "US",
    "sg:address": "4599 State Rte 235",
    "sg:city": "Ada",
    "sg:classifiers": [
      {
        "category": "Restaurant",
        "type": "Food \u0026 Drink"
      }
    ],
    "sg:phone": "+1 419 273 2996",
    "sg:postcode": "45810",
    "sg:province": "OH",
    "wof:name": "Victoria's Sweet Shop",
    "wof:placetype": "venue"
  },
  "geometry": {"coordinates":[-83.823274,40.752908],"type":"Point"}
}
