{
  "type": "Feature",
  "properties": {
    "iso:country":"US",
    "sg:address":"4599 State Rte 235",
    "sg:city":"Ada",
    "sg:classifiers":[
        {
            "category":"Restaurant",
            "type":"Food & Drink"
        }
    ],
    "sg:phone":"+1 419 273 2996",
    "sg:postcode":"45810",
    "sg:province":"OH",
    "wof:name":"Victoria's Sweet Shop",
    "wof:placetype":"venue"
},
  "geometry": {"coordinates":[-83.823274,40.752908],"type":"Point"}
}