{
  "type": "Feature",
  "properties": {
    "addr:full": "9916 Broadway Ave Cleveland OH 44125",
    "addr:housenumber": "9916",
    "addr:postcode": "44125",
    "addr:street": "Broadway Ave",
    "iso:country": "US",
    "sg:address": "9916 Broadway Ave",
    "sg:city": "Cleveland",
    "sg:classifiers": [
      {
        "category": "Building \u0026 Trades",
        "subcategory": "Construction",
        "type": "Services"
      },
      {
        "category": "Building \u0026 Trades",
        "subcategory": "Plumbing",
        "type": "Services"
      }
    ],
    "sg:phone": "+1 440 546 1164",
    "sg:postcode": "44125",
    "sg:province": "OH",
    "sg:tags": [
      "sheet",
      "work",
      "metal",
      "contractor"
    ],
    "wof:name": "P \u0026 L Industries Inc",
    "wof:placetype": "venue"
  },
  "geometry": {"coordinates":[-81.613168,41.437991],"type":"Point"}
}
