{
  "type": "Feature",
  "properties": {
    "iso:country":"US",
    "sg:address":"9916 Broadway Ave",
    "sg:city":"Cleveland",
    "sg:classifiers":[
        {
            "category":"Building & Trades",
            "subcategory":"Construction",
            "type":"Services"
        },
        {
            "category":"Building & Trades",
            "subcategory":"Plumbing",
            "type":"Services"
        }
    ],
    "sg:phone":"+1 440 546 1164",
    "sg:postcode":"44125",
    "sg:province":"OH",
    "sg:tags":[
        "sheet",
        "work",
        "metal",
        "contractor"
    ],
    "wof:name":"P & L Industries Inc",
    "wof:placetype":"venue"
},
  "geometry": {"coordinates":[-81.613168,41.437991],"type":"Point"}
}