{
  "type": "Feature",
  "properties": {
    "iso:country":"US",
    "sg:address":"100 Lincoln Way E",
    "sg:city":"Massillon",
    "sg:classifiers":[
        {
            "category":"Government",
            "subcategory":"Office",
            "type":"Public Place"
        }
    ],
    "sg:phone":"+1 330 830 1710",
    "sg:postcode":"44646",
    "sg:province":"OH",
    "sg:tags":[
        "administrative",
        "program",
        "health",
        "business"
    ],
    "wof:name":"Health Department",
    "wof:placetype":"venue"
},
  "geometry": {"coordinates":[-81.521253,40.797008],"type":"Point"}
}