{
  "type": "Feature",
  "properties": {
    "addr:full": "400 Independence Dr Napoleon OH 43545",
    "addr:housenumber": "400",
    "addr:postcode": "43545",
    "addr:street": "Independence Dr",
    "iso:country": "US",
    "sg:address": "400 Independence Dr",
    "sg:city": "Napoleon",
    "sg:classifiers": [
      {
        "category": "Health Services",
        "subcategory": "Optometrist",
        "type": "Services"
      }
    ],
    "sg:phone": "+1 419 599 4541",
    "sg:postcode": "43545",
    "sg:province": "OH",
    "wof:name": "Napoleon Family Vision \u0026 Cntrt",
    "wof:placetype": "venue"
  },
  "geometry": {"coordinates":[-84.111315,41.410289],"type":"Point"}
}
