{
  "type": "Feature",
  "properties": {
    "addr:full":"1831 Austinburg Rd Austinburg OH 44010",
    "addr:housenumber":"1831",
    "addr:postcode":"44010",
    "addr:street":"Austinburg Rd",
    "iso:country":"US",
    "sg:address":"1831 Austinburg Rd",
    "sg:city":"Austinburg",
    "sg:classifiers":[
        {
            "category":"Travel",
            "subcategory":"Hotels & Motels",
            "type":"Entertainment"
        }
    ],
    "sg:phone":"+1 440 275 2020",
    "sg:postcode":"44010",
    "sg:province":"OH",
    "sg:tags":[
        "operation"
    ],
    "wof:name":"Holiday Inn",
    "wof:placetype":"venue"
},
  "geometry": {"coordinates":[-80.809467,41.817642],"type":"Point"}
}