{
  "type": "Feature",
  "properties": {
    "addr:full": "3855 Ravenna Ave SE Canton OH 44730",
    "addr:housenumber": "3855",
    "addr:postcode": "44730",
    "addr:street": "Ravenna Ave Se",
    "iso:country": "US",
    "sg:address": "3855 Ravenna Ave SE",
    "sg:city": "Canton",
    "sg:classifiers": [
      {
        "category": "Food \u0026 Beverages",
        "subcategory": "Bakery",
        "type": "Retail Goods"
      }
    ],
    "sg:phone": "+1 330 488 3060",
    "sg:postcode": "44730",
    "sg:province": "OH",
    "sg:tags": [
      "baker"
    ],
    "wof:name": "Metzger's Muffins \u0026 Such",
    "wof:placetype": "venue"
  },
  "geometry": {"coordinates":[-81.246391,40.735325],"type":"Point"}
}
