{
  "type": "Feature",
  "properties": {
    "addr:full": "110 Novner Dr Cincinnati OH 45215",
    "addr:housenumber": "110",
    "addr:postcode": "45215",
    "addr:street": "Novner Dr",
    "iso:country": "US",
    "sg:address": "110 Novner Dr",
    "sg:city": "Cincinnati",
    "sg:classifiers": [
      {
        "category": "Wholesale",
        "subcategory": "Electrical",
        "type": "Manufacturing \u0026 Wholesale Goods"
      }
    ],
    "sg:phone": "+1 513 771 5335",
    "sg:postcode": "45215",
    "sg:province": "OH",
    "sg:tags": [
      "control"
    ],
    "wof:name": "Unosource Controls Inc",
    "wof:placetype": "venue"
  },
  "geometry": {"coordinates":[-84.475256,39.245557],"type":"Point"}
}
