{
  "type": "Feature",
  "properties": {
    "addr:full": "10901 State Rte 39 Millersburg OH 44654",
    "addr:housenumber": "10901",
    "addr:postcode": "44654",
    "addr:street": "State Rte 39",
    "iso:country": "US",
    "sg:address": "10901 State Rte 39",
    "sg:city": "Millersburg",
    "sg:classifiers": [
      {
        "category": "Education",
        "subcategory": "School",
        "type": "Public Place"
      }
    ],
    "sg:phone": "+1 330 674 4761",
    "sg:postcode": "44654",
    "sg:province": "OH",
    "wof:name": "West Holmes Middle School",
    "wof:placetype": "venue"
  },
  "geometry": {"coordinates":[-82.019235,40.57614],"type":"Point"}
}
