{
  "type": "Feature",
  "properties": {
    "iso:country":"US",
    "sg:address":"10901 State Rte 39",
    "sg:city":"Millersburg",
    "sg:classifiers":[
        {
            "category":"Education",
            "subcategory":"School",
            "type":"Public Place"
        }
    ],
    "sg:phone":"+1 330 674 4761",
    "sg:postcode":"44654",
    "sg:province":"OH",
    "wof:name":"West Holmes Middle School",
    "wof:placetype":"venue"
},
  "geometry": {"coordinates":[-82.01923499999999,40.57614],"type":"Point"}
}