{
  "type": "Feature",
  "properties": {
    "iso:country":"US",
    "sg:address":"1855 Snow Rd",
    "sg:city":"Cleveland",
    "sg:classifiers":[
        {
            "category":"Professional",
            "type":"Services"
        }
    ],
    "sg:phone":"+1 216 351 7584",
    "sg:postcode":"44134",
    "sg:province":"OH",
    "sg:tags":[
        "establishment"
    ],
    "wof:name":"Snowview Limited",
    "wof:placetype":"venue"
},
  "geometry": {"coordinates":[-81.697498,41.40501],"type":"Point"}
}