{
  "type": "Feature",
  "properties": {
    "iso:country":"US",
    "sg:address":"3651 Massillon Rd",
    "sg:city":"Uniontown",
    "sg:classifiers":[
        {
            "category":"Restaurant",
            "type":"Food & Drink"
        }
    ],
    "sg:menulink":"http://www.allmenus.com/oh/green/122441-quiznos-sub/menu/",
    "sg:phone":"+1 330 899 0194",
    "sg:postcode":"44685",
    "sg:province":"OH",
    "sg:tags":[
        "wrap",
        "american",
        "sandwich"
    ],
    "wof:name":"Quiznos Sub",
    "wof:placetype":"venue"
},
  "geometry": {"coordinates":[-81.46498699999999,40.962037],"type":"Point"}
}