{
  "type": "Feature",
  "properties": {
    "addr:full": "3651 Massillon Rd Uniontown OH 44685",
    "addr:housenumber": "3651",
    "addr:postcode": "44685",
    "addr:street": "Massillon Rd",
    "iso:country": "US",
    "sg:address": "3651 Massillon Rd",
    "sg:city": "Uniontown",
    "sg:classifiers": [
      {
        "category": "Restaurant",
        "type": "Food \u0026 Drink"
      }
    ],
    "sg:menulink": "http://www.allmenus.com/oh/green/122441-quiznos-sub/menu/",
    "sg:phone": "+1 330 899 0194",
    "sg:postcode": "44685",
    "sg:province": "OH",
    "sg:tags": [
      "wrap",
      "american",
      "sandwich"
    ],
    "wof:name": "Quiznos Sub",
    "wof:placetype": "venue"
  },
  "geometry": {"coordinates":[-81.464987,40.962037],"type":"Point"}
}
