{
  "type": "Feature",
  "properties": {
    "addr:full":"6225 Benore Rd Toledo OH 43612",
    "addr:housenumber":"6225",
    "addr:postcode":"43612",
    "addr:street":"Benore Rd",
    "iso:country":"US",
    "sg:address":"6225 Benore Rd",
    "sg:city":"Toledo",
    "sg:classifiers":[
        {
            "category":"Building & Trades",
            "subcategory":"Construction",
            "type":"Services"
        }
    ],
    "sg:phone":"+1 419 654 3411",
    "sg:postcode":"43612",
    "sg:province":"OH",
    "sg:tags":[
        "demolition",
        "contractor"
    ],
    "wof:name":"Paxton Demolition",
    "wof:placetype":"venue"
},
  "geometry": {"coordinates":[-83.524475,41.727223],"type":"Point"}
}