{
  "type": "Feature",
  "properties": {
    "iso:country":"US",
    "sg:address":"4730 Airport Rd",
    "sg:city":"Cincinnati",
    "sg:classifiers":[
        {
            "category":"Airport",
            "type":"Transportation"
        }
    ],
    "sg:phone":"+1 513 871 8235",
    "sg:postcode":"45226",
    "sg:province":"OH",
    "wof:name":"Air Tolin Inc",
    "wof:placetype":"venue"
},
  "geometry": {"coordinates":[-84.427487,39.101518],"type":"Point"}
}