{
  "type": "Feature",
  "properties": {
    "addr:full": "900 E Western Reserve Rd Youngstown OH 44514",
    "addr:housenumber": "900",
    "addr:postcode": "44514",
    "addr:street": "E Western Reserve Rd",
    "iso:country": "US",
    "sg:address": "900 E Western Reserve Rd",
    "sg:city": "Youngstown",
    "sg:classifiers": [
      {
        "category": "Restaurant",
        "type": "Food \u0026 Drink"
      }
    ],
    "sg:menulink": "http://www.allmenus.com/oh/boardman/195501-mcdonalds/menu/",
    "sg:postcode": "44514",
    "sg:province": "OH",
    "sg:tags": [
      "burger",
      "american"
    ],
    "wof:name": "McDonald's",
    "wof:placetype": "venue"
  },
  "geometry": {"coordinates":[-80.63602,40.98792],"type":"Point"}
}
