{
  "type": "Feature",
  "properties": {
    "addr:full":"810 Sycamore Street - Third Floor Cincinnati OH 45202",
    "addr:housenumber":"810",
    "addr:postcode":"45202",
    "addr:street":"Sycamore Street Third Floor",
    "iso:country":"US",
    "sg:address":"810 Sycamore Street - Third Floor",
    "sg:city":"Cincinnati",
    "sg:classifiers":[
        {
            "category":"Professional",
            "subcategory":"Lawyer & Legal Services",
            "type":"Services"
        }
    ],
    "sg:phone":"+1 513 338 1910",
    "sg:postcode":"45202",
    "sg:province":"OH",
    "sg:tags":[
        "attorney",
        "law",
        "business",
        "collection",
        "bankruptcy"
    ],
    "sg:website":"http://www.zingarellilaw.com",
    "wof:name":"Zingarelli Law Office",
    "wof:placetype":"venue"
},
  "geometry": {"coordinates":[-84.50907100000001,39.105652],"type":"Point"}
}