{
  "type": "Feature",
  "properties": {
    "addr:full": "345 E Main St Jackson OH 45640",
    "addr:housenumber": "345",
    "addr:postcode": "45640",
    "addr:street": "E Main St",
    "iso:country": "US",
    "sg:address": "345 E Main St",
    "sg:city": "Jackson",
    "sg:classifiers": [
      {
        "category": "Professional",
        "subcategory": "Accounting \u0026 Tax Preparation",
        "type": "Services"
      }
    ],
    "sg:phone": "+1 740 286 1131",
    "sg:postcode": "45640",
    "sg:province": "OH",
    "sg:tags": [
      "accountant"
    ],
    "wof:name": "Brackman \u0026 Co",
    "wof:placetype": "venue"
  },
  "geometry": {"coordinates":[-82.631324,39.046586],"type":"Point"}
}
