{
  "type": "Feature",
  "properties": {
    "iso:country":"US",
    "sg:address":"6279 Tri Ridge Blvd",
    "sg:city":"Loveland",
    "sg:classifiers":[
        {
            "category":"Building & Trades",
            "subcategory":"Construction",
            "type":"Services"
        }
    ],
    "sg:phone":"+1 513 248 5400",
    "sg:postcode":"45140",
    "sg:province":"OH",
    "sg:tags":[
        "home",
        "builder"
    ],
    "sg:website":"www.mihomes.com",
    "wof:name":"M/I Homes",
    "wof:placetype":"venue"
},
  "geometry": {"coordinates":[-84.28318400000001,39.225262],"type":"Point"}
}