{
  "type": "Feature",
  "properties": {
    "addr:full": "6279 Tri Ridge Blvd Loveland OH 45140",
    "addr:housenumber": "6279",
    "addr:postcode": "45140",
    "addr:street": "Tri Ridge Blvd",
    "iso:country": "US",
    "sg:address": "6279 Tri Ridge Blvd",
    "sg:city": "Loveland",
    "sg:classifiers": [
      {
        "category": "Building \u0026 Trades",
        "subcategory": "Construction",
        "type": "Services"
      }
    ],
    "sg:phone": "+1 513 248 5400",
    "sg:postcode": "45140",
    "sg:province": "OH",
    "sg:tags": [
      "home",
      "builder"
    ],
    "sg:website": "www.mihomes.com",
    "wof:name": "M/I Homes",
    "wof:placetype": "venue"
  },
  "geometry": {"coordinates":[-84.283184,39.225262],"type":"Point"}
}
