{
  "type": "Feature",
  "properties": {
    "iso:country":"US",
    "sg:address":"2630 Coppersmith Ave",
    "sg:city":"Dayton",
    "sg:classifiers":[
        {
            "category":"Professional",
            "subcategory":"Testing Lab",
            "type":"Services"
        }
    ],
    "sg:phone":"+1 937 264 0441",
    "sg:postcode":"45414",
    "sg:province":"OH",
    "sg:tags":[
        "laboratory"
    ],
    "wof:name":"Long Beach Genetics",
    "wof:placetype":"venue"
},
  "geometry": {"coordinates":[-84.21337699999999,39.849159],"type":"Point"}
}