{
  "type": "Feature",
  "properties": {
    "addr:full": "2630 Coppersmith Ave Dayton OH 45414",
    "addr:postcode": "2630;45414",
    "addr:street": "Coppersmith Ave",
    "iso:country": "US",
    "sg:address": "2630 Coppersmith Ave",
    "sg:city": "Dayton",
    "sg:classifiers": [
      {
        "category": "Professional",
        "subcategory": "Testing Lab",
        "type": "Services"
      }
    ],
    "sg:phone": "+1 937 264 0441",
    "sg:postcode": "45414",
    "sg:province": "OH",
    "sg:tags": [
      "laboratory"
    ],
    "wof:name": "Long Beach Genetics",
    "wof:placetype": "venue"
  },
  "geometry": {"coordinates":[-84.213377,39.849159],"type":"Point"}
}
