{
  "type": "Feature",
  "properties": {
    "iso:country":"US",
    "sg:address":"3690 Orange Pl Ste 525",
    "sg:city":"Beachwood",
    "sg:classifiers":[
        {
            "category":"Health Services",
            "subcategory":"Doctor",
            "type":"Services"
        }
    ],
    "sg:phone":"+1 216 595 1420",
    "sg:postcode":"44122",
    "sg:province":"OH",
    "sg:tags":[
        "surgeon",
        "oral"
    ],
    "wof:name":"Stickney Trudy DDS",
    "wof:placetype":"venue"
},
  "geometry": {"coordinates":[-81.487999,41.458801],"type":"Point"}
}