{
  "type": "Feature",
  "properties": {
    "addr:full":"120 N Center St Springfield OH 45502",
    "addr:housenumber":"120",
    "addr:postcode":"45502",
    "addr:street":"N Center St",
    "iso:country":"US",
    "sg:address":"120 N Center St",
    "sg:city":"Springfield",
    "sg:classifiers":[
        {
            "category":"Government",
            "subcategory":"Office",
            "type":"Public Place"
        }
    ],
    "sg:phone":"+1 937 328 2482",
    "sg:postcode":"45502",
    "sg:province":"OH",
    "sg:tags":[
        "county",
        "affairs",
        "veteran",
        "administration"
    ],
    "wof:name":"Clark County Veterans Service",
    "wof:placetype":"venue"
},
  "geometry": {"coordinates":[-83.811584,39.926966],"type":"Point"}
}