{
  "type": "Feature",
  "properties": {
    "addr:full":"102 N Main St Columbus Grove OH 45830",
    "addr:housenumber":"102",
    "addr:postcode":"45830",
    "addr:street":"N Main St",
    "iso:country":"US",
    "sg:address":"102 N Main St",
    "sg:city":"Columbus Grove",
    "sg:classifiers":[
        {
            "category":"Restaurant",
            "type":"Food & Drink"
        }
    ],
    "sg:phone":"+1 419 659 5241",
    "sg:postcode":"45830",
    "sg:province":"OH",
    "wof:name":"Dairy Whip",
    "wof:placetype":"venue"
},
  "geometry": {"coordinates":[-84.05852400000001,40.920914],"type":"Point"}
}