{
  "type": "Feature",
  "properties": {
    "iso:country":"US",
    "sg:address":"2423 Woodward Pl NW",
    "sg:city":"Canton",
    "sg:classifiers":[
        {
            "category":"Building & Trades",
            "subcategory":"Cleaning & Sanitation",
            "type":"Services"
        }
    ],
    "sg:phone":"+1 330 454 1081",
    "sg:postcode":"44708",
    "sg:province":"OH",
    "sg:tags":[
        "butler",
        "maid"
    ],
    "wof:name":"Har-Di Cleaning Svc",
    "wof:placetype":"venue"
},
  "geometry": {"coordinates":[-81.400468,40.823271],"type":"Point"}
}