{
  "type": "Feature",
  "properties": {
    "addr:full": "2423 Woodward Pl NW Canton OH 44708",
    "addr:housenumber": "2423",
    "addr:postcode": "44708",
    "addr:street": "Woodward Pl Nw",
    "iso:country": "US",
    "sg:address": "2423 Woodward Pl NW",
    "sg:city": "Canton",
    "sg:classifiers": [
      {
        "category": "Building \u0026 Trades",
        "subcategory": "Cleaning \u0026 Sanitation",
        "type": "Services"
      }
    ],
    "sg:phone": "+1 330 454 1081",
    "sg:postcode": "44708",
    "sg:province": "OH",
    "sg:tags": [
      "butler",
      "maid"
    ],
    "wof:name": "Har-Di Cleaning Svc",
    "wof:placetype": "venue"
  },
  "geometry": {"coordinates":[-81.400468,40.823271],"type":"Point"}
}
