{
  "type": "Feature",
  "properties": {
    "addr:full": "360 Fairlawn Ave Mansfield OH 44903",
    "addr:housenumber": "360",
    "addr:postcode": "44903",
    "addr:street": "Fairlawn Ave",
    "iso:country": "US",
    "sg:address": "360 Fairlawn Ave",
    "sg:city": "Mansfield",
    "sg:classifiers": [
      {
        "category": "Shopping",
        "subcategory": "Discount \u0026 Variety Stores",
        "type": "Retail Goods"
      }
    ],
    "sg:phone": "+1 419 756 5409",
    "sg:postcode": "44903",
    "sg:province": "OH",
    "sg:tags": [
      "merchandise",
      "general"
    ],
    "wof:name": "Memories From The Heart",
    "wof:placetype": "venue"
  },
  "geometry": {"coordinates":[-82.544079,40.749306],"type":"Point"}
}
