{
  "type": "Feature",
  "properties": {
    "addr:full":"228 Byers Rd Miamisburg OH 45342",
    "addr:housenumber":"228",
    "addr:postcode":"45342",
    "addr:street":"Byers Rd",
    "iso:country":"US",
    "sg:address":"228 Byers Rd",
    "sg:city":"Miamisburg",
    "sg:classifiers":[
        {
            "category":"Real Estate",
            "subcategory":"Real Estate Agent",
            "type":"Services"
        }
    ],
    "sg:phone":"+1 937 847 6820",
    "sg:postcode":"45342",
    "sg:province":"OH",
    "sg:website":"www.coldwellbankerdayton.com",
    "wof:name":"Coldwell Banker",
    "wof:placetype":"venue"
},
  "geometry": {"coordinates":[-84.23441099999999,39.638734],"type":"Point"}
}