{
  "type": "Feature",
  "properties": {
    "iso:country":"US",
    "sg:address":"409 Park Ave W",
    "sg:city":"Mansfield",
    "sg:classifiers":[
        {
            "category":"Insurance",
            "subcategory":"Insurance Agent",
            "type":"Services"
        }
    ],
    "sg:phone":"+1 419 526 1213",
    "sg:postcode":"44906",
    "sg:province":"OH",
    "wof:name":"Jordan Insurance Agency",
    "wof:placetype":"venue"
},
  "geometry": {"coordinates":[-82.530928,40.758845],"type":"Point"}
}