{
  "type": "Feature",
  "properties": {
    "iso:country":"US",
    "sg:address":"4885 Aspen Pine Blvd",
    "sg:city":"Dublin",
    "sg:classifiers":[
        {
            "category":"Professional",
            "type":"Services"
        }
    ],
    "sg:phone":"+1 614 850 9670",
    "sg:postcode":"43016",
    "sg:province":"OH",
    "sg:tags":[
        "establishment"
    ],
    "wof:name":"Pines At Tuttle Crossing",
    "wof:placetype":"venue"
},
  "geometry": {"coordinates":[-83.14989,40.070679],"type":"Point"}
}