{
  "type": "Feature",
  "properties": {
    "addr:full":"500 Swiss Dr Marion OH 43302",
    "addr:housenumber":"500",
    "addr:postcode":"43302",
    "addr:street":"Swiss Dr",
    "iso:country":"US",
    "sg:address":"500 Swiss Dr",
    "sg:city":"Marion",
    "sg:classifiers":[
        {
            "category":"Professional",
            "type":"Services"
        }
    ],
    "sg:phone":"+1 740 383 5202",
    "sg:postcode":"43302",
    "sg:province":"OH",
    "wof:name":"Bianca Mead",
    "wof:placetype":"venue"
},
  "geometry": {"coordinates":[-83.15272299999999,40.580201],"type":"Point"}
}