{
  "type": "Feature",
  "properties": {
    "addr:full": "1394 McKaig Rd Troy OH 45373",
    "addr:housenumber": "1394",
    "addr:postcode": "45373",
    "addr:street": "Mckaig Rd",
    "iso:country": "US",
    "sg:address": "1394 McKaig Rd",
    "sg:city": "Troy",
    "sg:classifiers": [
      {
        "category": "Freight",
        "type": "Transportation"
      }
    ],
    "sg:phone": "+1 937 335 8870",
    "sg:postcode": "45373",
    "sg:province": "OH",
    "sg:tags": [
      "operator",
      "local",
      "trucking"
    ],
    "wof:name": "Trimble Trucking",
    "wof:placetype": "venue"
  },
  "geometry": {"coordinates":[-84.223656,40.039665],"type":"Point"}
}
