{
  "type": "Feature",
  "properties": {
    "iso:country":"US",
    "sg:address":"6320 Wiehe Rd",
    "sg:city":"Cincinnati",
    "sg:classifiers":[
        {
            "category":"Manufacturing",
            "subcategory":"Tools & Machinery",
            "type":"Manufacturing & Wholesale Goods"
        }
    ],
    "sg:phone":"+1 513 841 0600",
    "sg:postcode":"45237",
    "sg:province":"OH",
    "sg:tags":[
        "equipment",
        "conveyor",
        "conveying"
    ],
    "wof:name":"Midwest Drives Inc",
    "wof:placetype":"venue"
},
  "geometry": {"coordinates":[-84.452422,39.186329],"type":"Point"}
}