{
  "type": "Feature",
  "properties": {
    "addr:full": "719 Coshocton Rd Mount Vernon OH 43050",
    "addr:housenumber": "719",
    "addr:postcode": "43050",
    "addr:street": "Coshocton Rd",
    "iso:country": "US",
    "sg:address": "719 Coshocton Rd",
    "sg:city": "Mount Vernon",
    "sg:classifiers": [
      {
        "category": "Wholesale",
        "subcategory": "Electrical",
        "type": "Manufacturing \u0026 Wholesale Goods"
      }
    ],
    "sg:phone": "+1 740 393 7971",
    "sg:postcode": "43050",
    "sg:province": "OH",
    "sg:tags": [
      "electronic"
    ],
    "wof:name": "S/R Marketing Inc",
    "wof:placetype": "venue"
  },
  "geometry": {"coordinates":[-82.46425,40.398039],"type":"Point"}
}
