{
  "type": "Feature",
  "properties": {
    "addr:full": "9705 Valley Rd Shreve OH 44676",
    "addr:housenumber": "9705",
    "addr:postcode": "44676",
    "addr:street": "Valley Rd",
    "iso:country": "US",
    "sg:address": "9705 Valley Rd",
    "sg:city": "Shreve",
    "sg:classifiers": [
      {
        "category": "Building \u0026 Trades",
        "subcategory": "Construction",
        "type": "Services"
      }
    ],
    "sg:phone": "+1 330 567 3580",
    "sg:postcode": "44676",
    "sg:province": "OH",
    "sg:tags": [
      "residential"
    ],
    "wof:name": "Tb Landscape",
    "wof:placetype": "venue"
  },
  "geometry": {"coordinates":[-81.980875,40.682062],"type":"Point"}
}
