{
  "type": "Feature",
  "properties": {
    "addr:full": "866 Plymouth Brick Rd Ashtabula OH 44004",
    "addr:housenumber": "866",
    "addr:postcode": "44004",
    "addr:street": "Plymouth Brick Rd",
    "iso:country": "US",
    "sg:address": "866 Plymouth Brick Rd",
    "sg:city": "Ashtabula",
    "sg:classifiers": [
      {
        "category": "Building \u0026 Trades",
        "subcategory": "Construction",
        "type": "Services"
      }
    ],
    "sg:phone": "+1 440 992 2302",
    "sg:postcode": "44004",
    "sg:province": "OH",
    "sg:tags": [
      "roofing",
      "contractor"
    ],
    "wof:name": "Ralston Roofing",
    "wof:placetype": "venue"
  },
  "geometry": {"coordinates":[-80.760756,41.836781],"type":"Point"}
}
