{
  "type": "Feature",
  "properties": {
    "addr:full": "4 E Main St Versailles OH 45380",
    "addr:housenumber": "4",
    "addr:postcode": "45380",
    "addr:street": "E Main St",
    "iso:country": "US",
    "sg:address": "4 E Main St",
    "sg:city": "Versailles",
    "sg:classifiers": [
      {
        "category": "Home \u0026 Garden",
        "subcategory": "Carpets \u0026 Floor Coverings",
        "type": "Retail Goods"
      }
    ],
    "sg:phone": "+1 937 526 3321",
    "sg:postcode": "45380",
    "sg:province": "OH",
    "sg:tags": [
      "dealer",
      "rug"
    ],
    "wof:name": "Floor Store \u0026 More",
    "wof:placetype": "venue"
  },
  "geometry": {"coordinates":[-84.483466,40.222584],"type":"Point"}
}
