{
  "type": "Feature",
  "properties": {
    "addr:full":"4 E Main St Versailles OH 45380",
    "addr:housenumber":"4",
    "addr:postcode":"45380",
    "addr:street":"E Main St",
    "iso:country":"US",
    "sg:address":"4 E Main St",
    "sg:city":"Versailles",
    "sg:classifiers":[
        {
            "category":"Home & Garden",
            "subcategory":"Carpets & Floor Coverings",
            "type":"Retail Goods"
        }
    ],
    "sg:phone":"+1 937 526 3321",
    "sg:postcode":"45380",
    "sg:province":"OH",
    "sg:tags":[
        "dealer",
        "rug"
    ],
    "wof:name":"Floor Store & More",
    "wof:placetype":"venue"
},
  "geometry": {"coordinates":[-84.48346600000001,40.222584],"type":"Point"}
}