{
  "type": "Feature",
  "properties": {
    "iso:country":"US",
    "sg:address":"371 Robert St",
    "sg:city":"Akron",
    "sg:classifiers":[
        {
            "category":"Organizations",
            "subcategory":"Religious Organization",
            "type":"Services"
        }
    ],
    "sg:phone":"+1 330 773 1913",
    "sg:postcode":"44306",
    "sg:province":"OH",
    "sg:tags":[
        "church"
    ],
    "wof:name":"True Vine Church Of God",
    "wof:placetype":"venue"
},
  "geometry": {"coordinates":[-81.486794,41.058609],"type":"Point"}
}