{
  "type": "Feature",
  "properties": {
    "addr:full": "519 W River St Antwerp OH 45813",
    "addr:housenumber": "519",
    "addr:postcode": "45813",
    "addr:street": "W River St",
    "iso:country": "US",
    "sg:address": "519 W River St",
    "sg:city": "Antwerp",
    "sg:classifiers": [
      {
        "category": "Restaurant",
        "type": "Food \u0026 Drink"
      }
    ],
    "sg:phone": "+1 419 258 4311",
    "sg:postcode": "45813",
    "sg:province": "OH",
    "wof:name": "A \u0026 W All-American Food",
    "wof:placetype": "venue"
  },
  "geometry": {"coordinates":[-84.752308,41.177773],"type":"Point"}
}
