{
  "type": "Feature",
  "properties": {
    "addr:full":"308 Louisiana Ave Elyria OH 44035",
    "addr:housenumber":"308",
    "addr:postcode":"44035",
    "addr:street":"Louisiana Ave",
    "iso:country":"US",
    "sg:address":"308 Louisiana Ave",
    "sg:city":"Elyria",
    "sg:classifiers":[
        {
            "category":"Building & Trades",
            "subcategory":"Equipment Rental",
            "type":"Services"
        }
    ],
    "sg:phone":"+1 440 323 5855",
    "sg:postcode":"44035",
    "sg:province":"OH",
    "sg:tags":[
        "camping"
    ],
    "wof:name":"PDQ Camping Ctr",
    "wof:placetype":"venue"
},
  "geometry": {"coordinates":[-82.116511,41.38207],"type":"Point"}
}