{
  "type": "Feature",
  "properties": {
    "addr:full":"9911 Avon Lake Rd Burbank OH 44214",
    "addr:housenumber":"9911",
    "addr:postcode":"44214",
    "addr:street":"Avon Lake Rd",
    "iso:country":"US",
    "sg:address":"9911 Avon Lake Rd",
    "sg:city":"Burbank",
    "sg:classifiers":[
        {
            "category":"Bakery",
            "type":"Food & Drink"
        }
    ],
    "sg:menulink":"http://www.allmenus.com/oh/harrisville/220124-auntie-annes-pretzels/menu/",
    "sg:phone":"+1 330 948 5153",
    "sg:postcode":"44214",
    "sg:province":"OH",
    "sg:tags":[
        "american",
        "pastry"
    ],
    "wof:name":"Auntie Anne's Pretzels",
    "wof:placetype":"venue"
},
  "geometry": {"coordinates":[-81.996088,41.006402],"type":"Point"}
}