{
  "type": "Feature",
  "properties": {
    "iso:country":"US",
    "sg:address":"1321 Carpenter Rd N",
    "sg:city":"Brunswick",
    "sg:classifiers":[
        {
            "category":"Shopping",
            "subcategory":"Music",
            "type":"Retail Goods"
        }
    ],
    "sg:phone":"+1 330 225 4141",
    "sg:postcode":"44212",
    "sg:province":"OH",
    "sg:tags":[
        "compact",
        "record",
        "disc",
        "tape"
    ],
    "wof:name":"Slipped Discs",
    "wof:placetype":"venue"
},
  "geometry": {"coordinates":[-81.807996,41.240415],"type":"Point"}
}