{
  "type": "Feature",
  "properties": {
    "iso:country":"US",
    "sg:address":"30 W Main St",
    "sg:city":"East Palestine",
    "sg:classifiers":[
        {
            "category":"Banks & Credit Unions",
            "subcategory":"Bank",
            "type":"Services"
        }
    ],
    "sg:phone":"+1 330 426 9393",
    "sg:postcode":"44413",
    "sg:province":"OH",
    "sg:tags":[
        "financing"
    ],
    "wof:name":"Victorian Finance LLC",
    "wof:placetype":"venue"
},
  "geometry": {"coordinates":[-80.54081,40.832738],"type":"Point"}
}