{
  "type": "Feature",
  "properties": {
    "iso:country":"US",
    "sg:address":"10690 Lincoln Hwy",
    "sg:city":"Van Wert",
    "sg:classifiers":[
        {
            "category":"Home & Garden",
            "subcategory":"Carpets & Floor Coverings",
            "type":"Retail Goods"
        }
    ],
    "sg:phone":"+1 419 232 4681",
    "sg:postcode":"45891",
    "sg:province":"OH",
    "sg:tags":[
        "dealer",
        "rug"
    ],
    "wof:name":"Carpet Wholesalers",
    "wof:placetype":"venue"
},
  "geometry": {"coordinates":[-84.61728599999999,40.875454],"type":"Point"}
}