{
  "type": "Feature",
  "properties": {
    "addr:full": "10690 Lincoln Hwy Van Wert OH 45891",
    "addr:housenumber": "10690",
    "addr:postcode": "45891",
    "addr:street": "Lincoln Hwy",
    "iso:country": "US",
    "sg:address": "10690 Lincoln Hwy",
    "sg:city": "Van Wert",
    "sg:classifiers": [
      {
        "category": "Home \u0026 Garden",
        "subcategory": "Carpets \u0026 Floor Coverings",
        "type": "Retail Goods"
      }
    ],
    "sg:phone": "+1 419 232 4681",
    "sg:postcode": "45891",
    "sg:province": "OH",
    "sg:tags": [
      "dealer",
      "rug"
    ],
    "wof:name": "Carpet Wholesalers",
    "wof:placetype": "venue"
  },
  "geometry": {"coordinates":[-84.617286,40.875454],"type":"Point"}
}
