{
  "type": "Feature",
  "properties": {
    "addr:full": "817 Main St Cincinnati OH 45202",
    "addr:housenumber": "817",
    "addr:postcode": "45202",
    "addr:street": "Main St",
    "iso:country": "US",
    "sg:address": "817 Main St",
    "sg:city": "Cincinnati",
    "sg:classifiers": [
      {
        "category": "Professional",
        "subcategory": "Business Services",
        "type": "Services"
      }
    ],
    "sg:phone": "+1 513 651 5679",
    "sg:postcode": "45202",
    "sg:province": "OH",
    "sg:tags": [
      "translator",
      "interpreter"
    ],
    "sg:website": "www.conversa1.com",
    "wof:name": "Conversa Language Ctr",
    "wof:placetype": "venue"
  },
  "geometry": {"coordinates":[-84.510714,39.105042],"type":"Point"}
}
