{
  "type": "Feature",
  "properties": {
    "iso:country":"US",
    "sg:address":"3320 Cleveland Ave NW",
    "sg:city":"Canton",
    "sg:classifiers":[
        {
            "category":"Autos & Motor Vehicles",
            "subcategory":"Automobile Sales",
            "type":"Retail Goods"
        }
    ],
    "sg:phone":"+1 330 493 1197",
    "sg:postcode":"44709",
    "sg:province":"OH",
    "sg:tags":[
        "used"
    ],
    "wof:name":"Millers Used Cars",
    "wof:placetype":"venue"
},
  "geometry": {"coordinates":[-81.38854,40.833675],"type":"Point"}
}