{
  "type": "Feature",
  "properties": {
    "addr:full":"200 Washington Jackson Rd Eaton OH 45320",
    "addr:housenumber":"200",
    "addr:postcode":"45320",
    "addr:street":"Washington Jackson Rd",
    "iso:country":"US",
    "sg:address":"200 Washington Jackson Rd",
    "sg:city":"Eaton",
    "sg:classifiers":[
        {
            "category":"Organizations",
            "subcategory":"Professional Association",
            "type":"Services"
        }
    ],
    "sg:phone":"+1 937 456 5511",
    "sg:postcode":"45320",
    "sg:province":"OH",
    "wof:name":"American Cancer Society",
    "wof:placetype":"venue"
},
  "geometry": {"coordinates":[-84.639533,39.765827],"type":"Point"}
}