{
  "type": "Feature",
  "properties": {
    "iso:country":"US",
    "sg:address":"2550 Harrison Rd",
    "sg:city":"Columbus",
    "sg:classifiers":[
        {
            "category":"Building & Trades",
            "subcategory":"Construction",
            "type":"Services"
        }
    ],
    "sg:phone":"+1 614 274 6810",
    "sg:postcode":"43204",
    "sg:province":"OH",
    "sg:tags":[
        "general",
        "contractor"
    ],
    "wof:name":"Fenstermaker Commercial Constr",
    "wof:placetype":"venue"
},
  "geometry": {"coordinates":[-83.064345,39.970574],"type":"Point"}
}