{
  "type": "Feature",
  "properties": {
    "iso:country":"US",
    "sg:address":"527 Portage Trail Extended W",
    "sg:city":"Cuyahoga Falls",
    "sg:classifiers":[
        {
            "category":"Professional",
            "subcategory":"Lawyer & Legal Services",
            "type":"Services"
        }
    ],
    "sg:phone":"+1 330 929 4495",
    "sg:postcode":"44223",
    "sg:province":"OH",
    "sg:tags":[
        "attorney"
    ],
    "wof:name":"D Robert Dietz",
    "wof:placetype":"venue"
},
  "geometry": {"coordinates":[-81.526541,41.139906],"type":"Point"}
}