{
  "type": "Feature",
  "properties": {
    "addr:full": "3669 Co Hwy 59 Nevada OH 44849",
    "addr:housenumber": "3669",
    "addr:postcode": "44849",
    "addr:street": "Co Hwy 59",
    "iso:country": "US",
    "sg:address": "3669 Co Hwy 59",
    "sg:city": "Nevada",
    "sg:classifiers": [
      {
        "category": "Shopping",
        "subcategory": "Florist",
        "type": "Retail Goods"
      }
    ],
    "sg:phone": "+1 740 482 2203",
    "sg:postcode": "44849",
    "sg:province": "OH",
    "sg:tags": [
      "s",
      "supply"
    ],
    "wof:name": "Carmar Gardens",
    "wof:placetype": "venue"
  },
  "geometry": {"coordinates":[-83.186396,40.789192],"type":"Point"}
}
