{
  "type": "Feature",
  "properties": {
    "addr:full":"203 N Main St Hicksville OH 43526",
    "addr:housenumber":"203",
    "addr:postcode":"43526",
    "addr:street":"N Main St",
    "iso:country":"US",
    "sg:address":"203 N Main St",
    "sg:city":"Hicksville",
    "sg:classifiers":[
        {
            "category":"Health Services",
            "subcategory":"Doctor",
            "type":"Services"
        }
    ],
    "sg:phone":"+1 419 542 8716",
    "sg:postcode":"43526",
    "sg:province":"OH",
    "sg:tags":[
        "dentist"
    ],
    "wof:name":"Robert L Ramus DDS",
    "wof:placetype":"venue"
},
  "geometry": {"coordinates":[-84.764419,41.294699],"type":"Point"}
}