{
  "type": "Feature",
  "properties": {
    "addr:full": "14813 Madison Ave Lakewood OH 44107",
    "addr:housenumber": "14813",
    "addr:postcode": "44107",
    "addr:street": "Madison Ave",
    "iso:country": "US",
    "sg:address": "14813 Madison Ave",
    "sg:city": "Lakewood",
    "sg:classifiers": [
      {
        "category": "Shopping",
        "subcategory": "Bicycles \u0026 Sporting Goods",
        "type": "Retail Goods"
      }
    ],
    "sg:phone": "+1 216 521 4855",
    "sg:postcode": "44107",
    "sg:province": "OH",
    "wof:name": "Aqua Specialists",
    "wof:placetype": "venue"
  },
  "geometry": {"coordinates":[-81.801299,41.477195],"type":"Point"}
}
