{
  "type": "Feature",
  "properties": {
    "iso:country":"US",
    "sg:address":"14813 Madison Ave",
    "sg:city":"Lakewood",
    "sg:classifiers":[
        {
            "category":"Shopping",
            "subcategory":"Bicycles & Sporting Goods",
            "type":"Retail Goods"
        }
    ],
    "sg:phone":"+1 216 521 4855",
    "sg:postcode":"44107",
    "sg:province":"OH",
    "wof:name":"Aqua Specialists",
    "wof:placetype":"venue"
},
  "geometry": {"coordinates":[-81.801299,41.477195],"type":"Point"}
}