{
  "type": "Feature",
  "properties": {
    "addr:full": "603 Leo St Dayton OH 45404",
    "addr:housenumber": "603",
    "addr:postcode": "45404",
    "addr:street": "Leo St",
    "iso:country": "US",
    "sg:address": "603 Leo St",
    "sg:city": "Dayton",
    "sg:classifiers": [
      {
        "category": "Wholesale",
        "subcategory": "Machinery \u0026 Supplies",
        "type": "Manufacturing \u0026 Wholesale Goods"
      }
    ],
    "sg:phone": "+1 937 461 5460",
    "sg:postcode": "45404",
    "sg:province": "OH",
    "sg:tags": [
      "equipment",
      "industrial"
    ],
    "wof:name": "Doall Industrial Supply Corp",
    "wof:placetype": "venue"
  },
  "geometry": {"coordinates":[-84.185125,39.783052],"type":"Point"}
}
