{
  "type": "Feature",
  "properties": {
    "iso:country":"US",
    "sg:address":"603 Leo St",
    "sg:city":"Dayton",
    "sg:classifiers":[
        {
            "category":"Wholesale",
            "subcategory":"Machinery & Supplies",
            "type":"Manufacturing & Wholesale Goods"
        }
    ],
    "sg:phone":"+1 937 461 5460",
    "sg:postcode":"45404",
    "sg:province":"OH",
    "sg:tags":[
        "equipment",
        "industrial"
    ],
    "wof:name":"Doall Industrial Supply Corp",
    "wof:placetype":"venue"
},
  "geometry": {"coordinates":[-84.185125,39.783052],"type":"Point"}
}