{
  "type": "Feature",
  "properties": {
    "addr:full":"2011 Broadview Rd Cleveland OH 44109",
    "addr:housenumber":"2011",
    "addr:postcode":"44109",
    "addr:street":"Broadview Rd",
    "iso:country":"US",
    "sg:address":"2011 Broadview Rd",
    "sg:city":"Cleveland",
    "sg:classifiers":[
        {
            "category":"Bars & Pubs",
            "type":"Food & Drink"
        }
    ],
    "sg:phone":"+1 216 749 0977",
    "sg:postcode":"44109",
    "sg:province":"OH",
    "wof:name":"Wedge Inn",
    "wof:placetype":"venue"
},
  "geometry": {"coordinates":[-81.697631,41.435348],"type":"Point"}
}