{
  "type": "Feature",
  "properties": {
    "addr:full":"341 Sunset Dr South Lebanon OH 45065",
    "addr:housenumber":"341",
    "addr:postcode":"45065",
    "addr:street":"Sunset Dr South",
    "iso:country":"US",
    "sg:address":"341 Sunset Dr",
    "sg:city":"South Lebanon",
    "sg:classifiers":[
        {
            "category":"Building & Trades",
            "subcategory":"Construction",
            "type":"Services"
        }
    ],
    "sg:phone":"+1 513 494 2611",
    "sg:postcode":"45065",
    "sg:province":"OH",
    "sg:tags":[
        "contractor"
    ],
    "wof:name":"Fee Brothers Construction Co",
    "wof:placetype":"venue"
},
  "geometry": {"coordinates":[-84.208713,39.372905],"type":"Point"}
}