{
  "type": "Feature",
  "properties": {
    "iso:country":"US",
    "sg:address":"466 Weaver Way",
    "sg:city":"Sharon",
    "sg:classifiers":[
        {
            "category":"Food & Beverages",
            "subcategory":"Groceries & Convenience Stores",
            "type":"Retail Goods"
        }
    ],
    "sg:phone":"+1   ",
    "sg:postcode":"16146",
    "sg:province":"OH",
    "wof:name":"Paradise Food Market",
    "wof:placetype":"venue"
},
  "geometry": {"coordinates":[-80.517234,41.221082],"type":"Point"}
}