{
  "type": "Feature",
  "properties": {
    "addr:full":"4160 Greenvale Rd Cleveland OH 44121",
    "addr:housenumber":"4160",
    "addr:postcode":"44121",
    "addr:street":"Greenvale Rd",
    "iso:country":"US",
    "sg:address":"4160 Greenvale Rd",
    "sg:city":"Cleveland",
    "sg:classifiers":[
        {
            "category":"Retail",
            "subcategory":"Auto Repair",
            "type":"Services"
        }
    ],
    "sg:phone":"+1 216 291 5432",
    "sg:postcode":"44121",
    "sg:province":"OH",
    "sg:tags":[
        "repairing",
        "automobile"
    ],
    "wof:name":"Honda Hospital",
    "wof:placetype":"venue"
},
  "geometry": {"coordinates":[-81.528296,41.53926],"type":"Point"}
}