{
  "type": "Feature",
  "properties": {
    "addr:full": "112 W Pacemont Rd Columbus OH 43202",
    "addr:housenumber": "112",
    "addr:postcode": "43202",
    "addr:street": "W Pacemont Rd",
    "iso:country": "US",
    "sg:address": "112 W Pacemont Rd",
    "sg:city": "Columbus",
    "sg:classifiers": [
      {
        "category": "Professional",
        "type": "Services"
      }
    ],
    "sg:phone": "+1 614 262 8987",
    "sg:postcode": "43202",
    "sg:province": "OH",
    "sg:tags": [
      "establishment"
    ],
    "wof:name": "OH Aquatic Council",
    "wof:placetype": "venue"
  },
  "geometry": {"coordinates":[-83.020027,40.026934],"type":"Point"}
}
