{
  "type": "Feature",
  "properties": {
    "addr:full": "8135 N Dixie Dr Dayton OH 45414",
    "addr:housenumber": "8135",
    "addr:postcode": "45414",
    "addr:street": "N Dixie Dr",
    "iso:country": "US",
    "sg:address": "8135 N Dixie Dr",
    "sg:city": "Dayton",
    "sg:classifiers": [
      {
        "category": "Real Estate",
        "subcategory": "Developer",
        "type": "Services"
      }
    ],
    "sg:phone": "+1 937 890 1831",
    "sg:postcode": "45414",
    "sg:province": "OH",
    "sg:tags": [
      "cemetery"
    ],
    "wof:name": "Dayton Mem Pk Cmtry \u0026 Mausoleu",
    "wof:placetype": "venue"
  },
  "geometry": {"coordinates":[-84.198858,39.845496],"type":"Point"}
}
