{
  "type": "Feature",
  "properties": {
    "iso:country":"US",
    "sg:address":"231 N Walnut St",
    "sg:city":"Dover",
    "sg:classifiers":[
        {
            "category":"Real Estate",
            "subcategory":"Real Estate Services",
            "type":"Services"
        }
    ],
    "sg:phone":"+1 330 364 6424",
    "sg:postcode":"44622",
    "sg:province":"OH",
    "sg:tags":[
        "company",
        "title"
    ],
    "wof:name":"American Title Assoc Agency",
    "wof:placetype":"venue"
},
  "geometry": {"coordinates":[-81.476695,40.520675],"type":"Point"}
}