{
  "type": "Feature",
  "properties": {
    "iso:country":"US",
    "sg:address":"224 W Exchange St",
    "sg:city":"Akron",
    "sg:classifiers":[
        {
            "category":"Health Services",
            "subcategory":"Doctor",
            "type":"Services"
        }
    ],
    "sg:phone":"+1 330 344 1989",
    "sg:postcode":"44302",
    "sg:province":"OH",
    "sg:tags":[
        "physician",
        "surgeon"
    ],
    "wof:name":"Summitt Neurological Assoc",
    "wof:placetype":"venue"
},
  "geometry": {"coordinates":[-81.528502,41.079171],"type":"Point"}
}