{
  "type": "Feature",
  "properties": {
    "iso:country":"US",
    "sg:address":"3 Summit Park Dr",
    "sg:city":"Cleveland",
    "sg:classifiers":[
        {
            "category":"Wholesale",
            "subcategory":"Electrical",
            "type":"Manufacturing & Wholesale Goods"
        }
    ],
    "sg:phone":"+1 216 642 0033",
    "sg:postcode":"44131",
    "sg:province":"OH",
    "sg:tags":[
        "electronic"
    ],
    "wof:name":"N E C Solutions(america) Inc",
    "wof:placetype":"venue"
},
  "geometry": {"coordinates":[-81.655851,41.39571],"type":"Point"}
}