{
  "type": "Feature",
  "properties": {
    "addr:full":"14550 Watt Rd Novelty OH 44072",
    "addr:housenumber":"14550",
    "addr:postcode":"44072",
    "addr:street":"Watt Rd",
    "iso:country":"US",
    "sg:address":"14550 Watt Rd",
    "sg:city":"Novelty",
    "sg:classifiers":[
        {
            "category":"Shopping",
            "subcategory":"Books",
            "type":"Retail Goods"
        }
    ],
    "sg:phone":"+1 440 338 4811",
    "sg:postcode":"44072",
    "sg:province":"OH",
    "sg:tags":[
        "used",
        "merchandise"
    ],
    "wof:name":"Lloyds Literature",
    "wof:placetype":"venue"
},
  "geometry": {"coordinates":[-81.3121,41.465986],"type":"Point"}
}