{
  "type": "Feature",
  "properties": {
    "addr:full":"6000 Cornell Rd Cincinnati OH 45242",
    "addr:housenumber":"6000",
    "addr:postcode":"45242",
    "addr:street":"Cornell Rd",
    "iso:country":"US",
    "sg:address":"6000 Cornell Rd",
    "sg:city":"Cincinnati",
    "sg:classifiers":[
        {
            "category":"Wholesale",
            "subcategory":"Electrical",
            "type":"Manufacturing & Wholesale Goods"
        }
    ],
    "sg:phone":"+1 513 489 1441",
    "sg:postcode":"45242",
    "sg:province":"OH",
    "sg:tags":[
        "alarm",
        "burglar",
        "system"
    ],
    "wof:name":"Aritronix Inc",
    "wof:placetype":"venue"
},
  "geometry": {"coordinates":[-84.365336,39.268764],"type":"Point"}
}