{
  "type": "Feature",
  "properties": {
    "iso:country":"US",
    "sg:address":"1707 N Park Ave",
    "sg:city":"Warren",
    "sg:classifiers":[
        {
            "category":"Bars & Pubs",
            "type":"Food & Drink"
        }
    ],
    "sg:phone":"+1 330 394 3641",
    "sg:postcode":"44483",
    "sg:province":"OH",
    "sg:tags":[
        "drinking",
        "eating"
    ],
    "wof:name":"Kiefers Cafe",
    "wof:placetype":"venue"
},
  "geometry": {"coordinates":[-80.817155,41.253946],"type":"Point"}
}