{
  "type": "Feature",
  "properties": {
    "addr:full": "1003 N Clinton St Defiance OH 43512",
    "addr:housenumber": "1003",
    "addr:postcode": "43512",
    "addr:street": "N Clinton St",
    "iso:country": "US",
    "sg:address": "1003 N Clinton St",
    "sg:city": "Defiance",
    "sg:classifiers": [
      {
        "category": "Restaurant",
        "type": "Food \u0026 Drink"
      }
    ],
    "sg:menulink": "http://www.allmenus.com/oh/noble/88759-applebees/menu/",
    "sg:phone": "+1 419 784 2279",
    "sg:postcode": "43512",
    "sg:province": "OH",
    "sg:tags": [
      "burger",
      "american",
      "sandwich",
      "soup"
    ],
    "wof:name": "Applebee's",
    "wof:placetype": "venue"
  },
  "geometry": {"coordinates":[-84.360816,41.29999],"type":"Point"}
}
