{
  "type": "Feature",
  "properties": {
    "addr:full":"251 N West St Piketon OH 45661",
    "addr:housenumber":"251",
    "addr:postcode":"45661",
    "addr:street":"N West St",
    "iso:country":"US",
    "sg:address":"251 N West St",
    "sg:city":"Piketon",
    "sg:classifiers":[
        {
            "category":"Education",
            "subcategory":"School",
            "type":"Public Place"
        }
    ],
    "sg:phone":"+1 740 289 4194",
    "sg:postcode":"45661",
    "sg:province":"OH",
    "wof:name":"Zahns Corner Middle School",
    "wof:placetype":"venue"
},
  "geometry": {"coordinates":[-83.01699000000001,39.066283],"type":"Point"}
}