{
  "type": "Feature",
  "properties": {
    "addr:full": "2996 Derr Rd Springfield OH 45503",
    "addr:housenumber": "2996",
    "addr:postcode": "45503",
    "addr:street": "Derr Rd",
    "iso:country": "US",
    "sg:address": "2996 Derr Rd",
    "sg:city": "Springfield",
    "sg:classifiers": [
      {
        "category": "Autos \u0026 Motor Vehicles",
        "subcategory": "Fuel \u0026 Gas Station",
        "type": "Retail Goods"
      }
    ],
    "sg:phone": "+1 937 399 1896",
    "sg:postcode": "45503",
    "sg:province": "OH",
    "sg:tags": [
      "oil"
    ],
    "wof:name": "Speedway",
    "wof:placetype": "venue"
  },
  "geometry": {"coordinates":[-83.785328,39.963888],"type":"Point"}
}
