{
  "type": "Feature",
  "properties": {
    "iso:country":"US",
    "sg:address":"22613 State Rte 136",
    "sg:city":"Winchester",
    "sg:classifiers":[
        {
            "category":"Real Estate",
            "subcategory":"Real Estate Operator",
            "type":"Services"
        }
    ],
    "sg:phone":"+1 937 695 0640",
    "sg:postcode":"45697",
    "sg:province":"OH",
    "sg:tags":[
        "property",
        "lessor"
    ],
    "wof:name":"Kenneth E West",
    "wof:placetype":"venue"
},
  "geometry": {"coordinates":[-83.655778,38.993239],"type":"Point"}
}