{
  "type": "Feature",
  "properties": {
    "addr:full": "5387 Roberts Rd Hilliard OH 43026",
    "addr:housenumber": "5387",
    "addr:postcode": "43026",
    "addr:street": "Roberts Rd",
    "iso:country": "US",
    "sg:address": "5387 Roberts Rd",
    "sg:city": "Hilliard",
    "sg:classifiers": [
      {
        "category": "Restaurant",
        "type": "Food \u0026 Drink"
      }
    ],
    "sg:menulink": "http://www.allmenus.com/oh/columbus/19432-luckys-grille--billiards/menu/",
    "sg:phone": "+1 614 771 7766",
    "sg:postcode": "43026",
    "sg:province": "OH",
    "sg:tags": [
      "american"
    ],
    "wof:name": "Lucky's Grille \u0026 Billiards",
    "wof:placetype": "venue"
  },
  "geometry": {"coordinates":[-83.150968,40.002829],"type":"Point"}
}
