{
  "type": "Feature",
  "properties": {
    "addr:full": "3833 N Dayton Xenia Rd Dayton OH 45432",
    "addr:housenumber": "3833",
    "addr:postcode": "45432",
    "addr:street": "N Dayton Xenia Rd",
    "iso:country": "US",
    "sg:address": "3833 N Dayton Xenia Rd",
    "sg:city": "Dayton",
    "sg:classifiers": [
      {
        "category": "Bars \u0026 Pubs",
        "type": "Food \u0026 Drink"
      }
    ],
    "sg:phone": "+1 937 429 0186",
    "sg:postcode": "45432",
    "sg:province": "OH",
    "sg:tags": [
      "drinking"
    ],
    "wof:name": "Knollwood Tavern",
    "wof:placetype": "venue"
  },
  "geometry": {"coordinates":[-84.078959,39.736185],"type":"Point"}
}
