{
  "type": "Feature",
  "properties": {
    "iso:country":"US",
    "sg:address":"932 Holland Park Blvd",
    "sg:city":"Holland",
    "sg:classifiers":[
        {
            "category":"Banks & Credit Unions",
            "subcategory":"Bank",
            "type":"Services"
        }
    ],
    "sg:phone":"+1 419 865 4950",
    "sg:postcode":"43528",
    "sg:province":"OH",
    "sg:tags":[
        "machine",
        "teller",
        "automated"
    ],
    "wof:name":"ATM Solutions",
    "wof:placetype":"venue"
},
  "geometry": {"coordinates":[-83.701165,41.622509],"type":"Point"}
}