{
  "type": "Feature",
  "properties": {
    "addr:full": "932 Holland Park Blvd Holland OH 43528",
    "addr:housenumber": "932",
    "addr:postcode": "43528",
    "addr:street": "Holland Park Blvd",
    "iso:country": "US",
    "sg:address": "932 Holland Park Blvd",
    "sg:city": "Holland",
    "sg:classifiers": [
      {
        "category": "Banks \u0026 Credit Unions",
        "subcategory": "Bank",
        "type": "Services"
      }
    ],
    "sg:phone": "+1 419 865 4950",
    "sg:postcode": "43528",
    "sg:province": "OH",
    "sg:tags": [
      "machine",
      "teller",
      "automated"
    ],
    "wof:name": "ATM Solutions",
    "wof:placetype": "venue"
  },
  "geometry": {"coordinates":[-83.701165,41.622509],"type":"Point"}
}
