{
  "type": "Feature",
  "properties": {
    "iso:country":"US",
    "sg:address":"2970 W Broad St",
    "sg:city":"Columbus",
    "sg:classifiers":[
        {
            "category":"Health Services",
            "subcategory":"Doctor",
            "type":"Services"
        }
    ],
    "sg:phone":"+1 614 279 0808",
    "sg:postcode":"43204",
    "sg:province":"OH",
    "sg:tags":[
        "physician",
        "surgeon"
    ],
    "wof:name":"Herbert & Parsons Inc",
    "wof:placetype":"venue"
},
  "geometry": {"coordinates":[-83.07973699999999,39.954675],"type":"Point"}
}