{
  "type": "Feature",
  "properties": {
    "addr:full": "2970 W Broad St Columbus OH 43204",
    "addr:housenumber": "2970",
    "addr:postcode": "43204",
    "addr:street": "W Broad St",
    "iso:country": "US",
    "sg:address": "2970 W Broad St",
    "sg:city": "Columbus",
    "sg:classifiers": [
      {
        "category": "Health Services",
        "subcategory": "Doctor",
        "type": "Services"
      }
    ],
    "sg:phone": "+1 614 279 0808",
    "sg:postcode": "43204",
    "sg:province": "OH",
    "sg:tags": [
      "physician",
      "surgeon"
    ],
    "wof:name": "Herbert \u0026 Parsons Inc",
    "wof:placetype": "venue"
  },
  "geometry": {"coordinates":[-83.079737,39.954675],"type":"Point"}
}
