{
  "type": "Feature",
  "properties": {
    "addr:full":"140 Dixie Hwy Rossford OH 43460",
    "addr:housenumber":"140",
    "addr:postcode":"43460",
    "addr:street":"Dixie Hwy",
    "iso:country":"US",
    "sg:address":"140 Dixie Hwy",
    "sg:city":"Rossford",
    "sg:classifiers":[
        {
            "category":"Manufacturing",
            "subcategory":"Glass & Minerals",
            "type":"Manufacturing & Wholesale Goods"
        }
    ],
    "sg:phone":"+1 419 247 3211",
    "sg:postcode":"43460",
    "sg:province":"OH",
    "sg:tags":[
        "flat",
        "product",
        "mfg"
    ],
    "wof:name":"Pilington Libbey-Owens-Ford Co",
    "wof:placetype":"venue"
},
  "geometry": {"coordinates":[-83.55322,41.614382],"type":"Point"}
}