{
  "type": "Feature",
  "properties": {
    "iso:country":"US",
    "sg:address":"404 Elverne Ave",
    "sg:city":"Dayton",
    "sg:classifiers":[
        {
            "category":"Sports & Exercise",
            "subcategory":"Bowling",
            "type":"Entertainment"
        }
    ],
    "sg:phone":"+1 937 233 4178",
    "sg:postcode":"45404",
    "sg:province":"OH",
    "sg:tags":[
        "center"
    ],
    "wof:name":"Bowling Contracting Services",
    "wof:placetype":"venue"
},
  "geometry": {"coordinates":[-84.13681200000001,39.80204],"type":"Point"}
}