{
  "type": "Feature",
  "properties": {
    "addr:full":"496 Roney Ln Cincinnati OH 45244",
    "addr:housenumber":"496",
    "addr:postcode":"45244",
    "addr:street":"Roney Ln",
    "iso:country":"US",
    "sg:address":"496 Roney Ln",
    "sg:city":"Cincinnati",
    "sg:classifiers":[
        {
            "category":"Shopping",
            "subcategory":"Discount & Variety Stores",
            "type":"Retail Goods"
        }
    ],
    "sg:phone":"+1 513 528 7755",
    "sg:postcode":"45244",
    "sg:province":"OH",
    "wof:name":"Everythings 99 Cents",
    "wof:placetype":"venue"
},
  "geometry": {"coordinates":[-84.30209000000001,39.11003],"type":"Point"}
}