{
  "type": "Feature",
  "properties": {
    "addr:full":"331 S Roosevelt Ave Piqua OH 45356",
    "addr:housenumber":"331",
    "addr:postcode":"45356",
    "addr:street":"S Roosevelt Ave",
    "iso:country":"US",
    "sg:address":"331 S Roosevelt Ave",
    "sg:city":"Piqua",
    "sg:classifiers":[
        {
            "category":"Restaurant",
            "type":"Food & Drink"
        }
    ],
    "sg:phone":"+1 937 778 9314",
    "sg:postcode":"45356",
    "sg:province":"OH",
    "sg:tags":[
        "drinking",
        "eating"
    ],
    "wof:name":"Charles Caserta Restaurant",
    "wof:placetype":"venue"
},
  "geometry": {"coordinates":[-84.244359,40.14348],"type":"Point"}
}