{
  "type": "Feature",
  "properties": {
    "addr:full": "1262 Weathervane Ln Akron OH 44313",
    "addr:housenumber": "1262",
    "addr:postcode": "44313",
    "addr:street": "Weathervane Ln",
    "iso:country": "US",
    "sg:address": "1262 Weathervane Ln",
    "sg:city": "Akron",
    "sg:classifiers": [
      {
        "category": "Shopping",
        "subcategory": "Jewelry",
        "type": "Retail Goods"
      }
    ],
    "sg:phone": "+1 330 836 2446",
    "sg:postcode": "44313",
    "sg:province": "OH",
    "sg:tags": [
      "jeweler"
    ],
    "wof:name": "Mc Donnell \u0026 Bracken Jewelers",
    "wof:placetype": "venue"
  },
  "geometry": {"coordinates":[-81.553641,41.13737],"type":"Point"}
}
