{
  "type": "Feature",
  "properties": {
    "addr:full":"10999 Reed Hartman Hwy Cincinnati OH 45242",
    "addr:housenumber":"10999",
    "addr:postcode":"45242",
    "addr:street":"Reed Hartman Hwy",
    "iso:country":"US",
    "sg:address":"10999 Reed Hartman Hwy",
    "sg:city":"Cincinnati",
    "sg:classifiers":[
        {
            "category":"Building & Trades",
            "subcategory":"Construction",
            "type":"Services"
        }
    ],
    "sg:phone":"+1 513 793 0964",
    "sg:postcode":"45242",
    "sg:province":"OH",
    "sg:tags":[
        "home",
        "improvement"
    ],
    "wof:name":"R K Lawrence Home Improvement",
    "wof:placetype":"venue"
},
  "geometry": {"coordinates":[-84.37730000000001,39.267867],"type":"Point"}
}