{
  "type": "Feature",
  "properties": {
    "addr:full":"700 Western Ave Findlay OH 45840",
    "addr:housenumber":"700",
    "addr:postcode":"45840",
    "addr:street":"Western Ave",
    "iso:country":"US",
    "sg:address":"700 Western Ave",
    "sg:city":"Findlay",
    "sg:classifiers":[
        {
            "category":"Professional",
            "subcategory":"Advertising",
            "type":"Services"
        }
    ],
    "sg:phone":"+1 419 422 5585",
    "sg:postcode":"45840",
    "sg:province":"OH",
    "sg:tags":[
        "outdoor"
    ],
    "wof:name":"Lammers Outdoor Advertising",
    "wof:placetype":"venue"
},
  "geometry": {"coordinates":[-83.65981600000001,41.034354],"type":"Point"}
}