{
  "type": "Feature",
  "properties": {
    "addr:full":"2800 Archwood Ave Cleveland OH 44109",
    "addr:housenumber":"2800",
    "addr:postcode":"44109",
    "addr:street":"Archwood Ave",
    "iso:country":"US",
    "sg:address":"2800 Archwood Ave",
    "sg:city":"Cleveland",
    "sg:classifiers":[
        {
            "category":"Social Services",
            "type":"Services"
        }
    ],
    "sg:phone":"+1 216 661 5350",
    "sg:postcode":"44109",
    "sg:province":"OH",
    "wof:name":"Wsem Youth Services",
    "wof:placetype":"venue"
},
  "geometry": {"coordinates":[-81.70295299999999,41.452757],"type":"Point"}
}