{
  "type": "Feature",
  "properties": {
    "iso:country":"US",
    "sg:address":"579 Wedgewood Dr",
    "sg:city":"Columbus",
    "sg:classifiers":[
        {
            "category":"Food & Beverages",
            "subcategory":"Liquor & Beverages",
            "type":"Retail Goods"
        }
    ],
    "sg:phone":"+1 614 279 9100",
    "sg:postcode":"43228",
    "sg:province":"OH",
    "sg:tags":[
        "beer",
        "ale",
        "alcoholic"
    ],
    "wof:name":"Manor Carry Out",
    "wof:placetype":"venue"
},
  "geometry": {"coordinates":[-83.096498,39.939609],"type":"Point"}
}