{
  "type": "Feature",
  "properties": {
    "addr:full": "825 Richard Ln Kenton OH 43326",
    "addr:housenumber": "825",
    "addr:postcode": "43326",
    "addr:street": "Richard Ln",
    "iso:country": "US",
    "sg:address": "825 Richard Ln",
    "sg:city": "Kenton",
    "sg:classifiers": [
      {
        "category": "Health Services",
        "subcategory": "Nursing And Care Facility",
        "type": "Services"
      }
    ],
    "sg:phone": "+1 419 673 9821",
    "sg:postcode": "43326",
    "sg:province": "OH",
    "sg:tags": [
      "intermediate"
    ],
    "wof:name": "Blanchard House",
    "wof:placetype": "venue"
  },
  "geometry": {"coordinates":[-83.593498,40.655489],"type":"Point"}
}
