{
  "type": "Feature",
  "properties": {
    "iso:country":"US",
    "sg:address":"1474 Main St",
    "sg:city":"Hamilton",
    "sg:classifiers":[
        {
            "category":"Banks & Credit Unions",
            "subcategory":"Bank",
            "type":"Services"
        }
    ],
    "sg:phone":"+1 513 887 0770",
    "sg:postcode":"45013",
    "sg:province":"IN",
    "sg:tags":[
        "state",
        "commercial"
    ],
    "wof:name":"Fifth Third Bank",
    "wof:placetype":"venue"
},
  "geometry": {"coordinates":[-84.59409100000001,39.423867],"type":"Point"}
}