{
  "type": "Feature",
  "properties": {
    "addr:full": "1474 Main St Hamilton IN 45013",
    "addr:housenumber": "1474",
    "addr:postcode": "45013",
    "addr:street": "Main St",
    "iso:country": "US",
    "sg:address": "1474 Main St",
    "sg:city": "Hamilton",
    "sg:classifiers": [
      {
        "category": "Banks \u0026 Credit Unions",
        "subcategory": "Bank",
        "type": "Services"
      }
    ],
    "sg:phone": "+1 513 887 0770",
    "sg:postcode": "45013",
    "sg:province": "IN",
    "sg:tags": [
      "state",
      "commercial"
    ],
    "wof:name": "Fifth Third Bank",
    "wof:placetype": "venue"
  },
  "geometry": {"coordinates":[-84.594091,39.423867],"type":"Point"}
}
