{
  "type": "Feature",
  "properties": {
    "addr:full": "133 Bliss Rd Beaver OH 45613",
    "addr:housenumber": "133",
    "addr:postcode": "45613",
    "addr:street": "Bliss Rd",
    "iso:country": "US",
    "sg:address": "133 Bliss Rd",
    "sg:city": "Beaver",
    "sg:classifiers": [
      {
        "category": "Farming",
        "subcategory": "Farm",
        "type": "Manufacturing \u0026 Wholesale Goods"
      }
    ],
    "sg:phone": "+1 740 226 7541",
    "sg:postcode": "45613",
    "sg:province": "OH",
    "sg:tags": [
      "livestock",
      "crop",
      "general"
    ],
    "wof:name": "Richard Reffitt",
    "wof:placetype": "venue"
  },
  "geometry": {"coordinates":[-82.89737,38.985961],"type":"Point"}
}
