{
  "type": "Feature",
  "properties": {
    "addr:full":"839 Waterton Dr Westerville OH 43081",
    "addr:housenumber":"839",
    "addr:postcode":"43081",
    "addr:street":"Waterton Dr",
    "iso:country":"US",
    "sg:address":"839 Waterton Dr",
    "sg:city":"Westerville",
    "sg:classifiers":[
        {
            "category":"Wholesale",
            "subcategory":"Apparel",
            "type":"Manufacturing & Wholesale Goods"
        }
    ],
    "sg:phone":"+1 614 899 2553",
    "sg:postcode":"43081",
    "sg:province":"OH",
    "sg:tags":[
        "clothing"
    ],
    "wof:name":"Pts Closet Ltd",
    "wof:placetype":"venue"
},
  "geometry": {"coordinates":[-82.95816600000001,40.128229],"type":"Point"}
}