{
  "type": "Feature",
  "properties": {
    "iso:country":"US",
    "sg:address":"4357 Westland Mall",
    "sg:city":"Columbus",
    "sg:classifiers":[
        {
            "category":"Restaurant",
            "type":"Food & Drink"
        }
    ],
    "sg:phone":"+1 614 279 1999",
    "sg:postcode":"43228",
    "sg:province":"OH",
    "wof:name":"Xo Grill Bar & Nightclub",
    "wof:placetype":"venue"
},
  "geometry": {"coordinates":[-83.115121,39.952623],"type":"Point"}
}