{
  "type": "Feature",
  "properties": {
    "iso:country":"US",
    "sg:address":"4486 US Rte 127",
    "sg:city":"Van Wert",
    "sg:classifiers":[
        {
            "category":"Organizations",
            "subcategory":"Religious Organization",
            "type":"Services"
        }
    ],
    "sg:phone":"+1 419 238 1907",
    "sg:postcode":"45891",
    "sg:province":"OH",
    "sg:tags":[
        "church"
    ],
    "wof:name":"North Union United Methodist",
    "wof:placetype":"venue"
},
  "geometry": {"coordinates":[-84.57226799999999,40.939163],"type":"Point"}
}