{
  "type": "Feature",
  "properties": {
    "addr:full": "4486 US Rte 127 Van Wert OH 45891",
    "addr:housenumber": "4486",
    "addr:postcode": "45891",
    "addr:street": "Us Rte 127",
    "iso:country": "US",
    "sg:address": "4486 US Rte 127",
    "sg:city": "Van Wert",
    "sg:classifiers": [
      {
        "category": "Organizations",
        "subcategory": "Religious Organization",
        "type": "Services"
      }
    ],
    "sg:phone": "+1 419 238 1907",
    "sg:postcode": "45891",
    "sg:province": "OH",
    "sg:tags": [
      "church"
    ],
    "wof:name": "North Union United Methodist",
    "wof:placetype": "venue"
  },
  "geometry": {"coordinates":[-84.572268,40.939163],"type":"Point"}
}
