{
  "type": "Feature",
  "properties": {
    "iso:country":"US",
    "sg:address":"5400 Grant Ave",
    "sg:city":"Cleveland",
    "sg:classifiers":[
        {
            "category":"Local Transit",
            "type":"Transportation"
        }
    ],
    "sg:phone":"+1 216 566 5100",
    "sg:postcode":"44125",
    "sg:province":"OH",
    "sg:tags":[
        "public"
    ],
    "wof:name":"Greater Rgnl Trnst Athrty",
    "wof:placetype":"venue"
},
  "geometry": {"coordinates":[-81.652863,41.440374],"type":"Point"}
}