{
  "type": "Feature",
  "properties": {
    "addr:full":"8535 South Ave Youngstown OH 44514",
    "addr:housenumber":"8535",
    "addr:postcode":"44514",
    "addr:street":"South Ave",
    "iso:country":"US",
    "sg:address":"8535 South Ave",
    "sg:city":"Youngstown",
    "sg:classifiers":[
        {
            "category":"Restaurant",
            "type":"Food & Drink"
        }
    ],
    "sg:menulink":"http://www.allmenus.com/oh/boardman/79331-pizza-hut/menu/",
    "sg:phone":"+1 330 965 4000",
    "sg:postcode":"44514",
    "sg:province":"OH",
    "sg:tags":[
        "american",
        "pizza"
    ],
    "wof:name":"Pizza Hut",
    "wof:placetype":"venue"
},
  "geometry": {"coordinates":[-80.63365400000001,40.990174],"type":"Point"}
}