{
  "type": "Feature",
  "properties": {
    "addr:full": "369 E Chestnut St Lisbon OH 44432",
    "addr:housenumber": "369",
    "addr:postcode": "44432",
    "addr:street": "E Chestnut St",
    "iso:country": "US",
    "sg:address": "369 E Chestnut St",
    "sg:city": "Lisbon",
    "sg:classifiers": [
      {
        "category": "Building \u0026 Trades",
        "subcategory": "Construction",
        "type": "Services"
      }
    ],
    "sg:phone": "+1 330 420 9400",
    "sg:postcode": "44432",
    "sg:province": "OH",
    "sg:tags": [
      "roofing",
      "contractor"
    ],
    "wof:name": "High Efficient Heating",
    "wof:placetype": "venue"
  },
  "geometry": {"coordinates":[-80.762289,40.773354],"type":"Point"}
}
