{
  "type": "Feature",
  "properties": {
    "iso:country":"US",
    "sg:address":"369 E Chestnut St",
    "sg:city":"Lisbon",
    "sg:classifiers":[
        {
            "category":"Building & Trades",
            "subcategory":"Construction",
            "type":"Services"
        }
    ],
    "sg:phone":"+1 330 420 9400",
    "sg:postcode":"44432",
    "sg:province":"OH",
    "sg:tags":[
        "roofing",
        "contractor"
    ],
    "wof:name":"High Efficient Heating",
    "wof:placetype":"venue"
},
  "geometry": {"coordinates":[-80.762289,40.773354],"type":"Point"}
}