{
  "type": "Feature",
  "properties": {
    "iso:country":"US",
    "sg:address":"15705 Libby Rd",
    "sg:city":"Cleveland",
    "sg:classifiers":[
        {
            "category":"Shopping",
            "subcategory":"Florist",
            "type":"Retail Goods"
        }
    ],
    "sg:phone":"+1 216 581 7754",
    "sg:postcode":"44137",
    "sg:province":"OH",
    "wof:name":"T J's Wholesale",
    "wof:placetype":"venue"
},
  "geometry": {"coordinates":[-81.570528,41.417041],"type":"Point"}
}