{
  "type": "Feature",
  "properties": {
    "iso:country":"US",
    "sg:address":"2507 Summit St",
    "sg:city":"Columbus",
    "sg:classifiers":[
        {
            "category":"Bars & Pubs",
            "type":"Food & Drink"
        }
    ],
    "sg:phone":"+1 614 267 3480",
    "sg:postcode":"43202",
    "sg:province":"OH",
    "sg:tags":[
        "drinking"
    ],
    "wof:name":"Blondies Bar Patio",
    "wof:placetype":"venue"
},
  "geometry": {"coordinates":[-83.000197,40.014556],"type":"Point"}
}