{
  "type": "Feature",
  "properties": {
    "addr:full": "2507 Summit St Columbus OH 43202",
    "addr:housenumber": "2507",
    "addr:postcode": "43202",
    "addr:street": "Summit St",
    "iso:country": "US",
    "sg:address": "2507 Summit St",
    "sg:city": "Columbus",
    "sg:classifiers": [
      {
        "category": "Bars \u0026 Pubs",
        "type": "Food \u0026 Drink"
      }
    ],
    "sg:phone": "+1 614 267 3480",
    "sg:postcode": "43202",
    "sg:province": "OH",
    "sg:tags": [
      "drinking"
    ],
    "wof:name": "Blondies Bar Patio",
    "wof:placetype": "venue"
  },
  "geometry": {"coordinates":[-83.000197,40.014556],"type":"Point"}
}
