{
  "type": "Feature",
  "properties": {
    "addr:full": "2401 Scranton Rd Cleveland OH 44113",
    "addr:housenumber": "2401",
    "addr:postcode": "44113",
    "addr:street": "Scranton Rd",
    "iso:country": "US",
    "sg:address": "2401 Scranton Rd",
    "sg:city": "Cleveland",
    "sg:classifiers": [
      {
        "category": "Restaurant",
        "type": "Food \u0026 Drink"
      }
    ],
    "sg:phone": "+1 216 241 7774",
    "sg:postcode": "44113",
    "sg:province": "OH",
    "wof:name": "Pizza Pan",
    "wof:placetype": "venue"
  },
  "geometry": {"coordinates":[-81.694589,41.478792],"type":"Point"}
}
