{
  "type": "Feature",
  "properties": {
    "iso:country":"US",
    "sg:address":"2401 Scranton Rd",
    "sg:city":"Cleveland",
    "sg:classifiers":[
        {
            "category":"Restaurant",
            "type":"Food & Drink"
        }
    ],
    "sg:phone":"+1 216 241 7774",
    "sg:postcode":"44113",
    "sg:province":"OH",
    "wof:name":"Pizza Pan",
    "wof:placetype":"venue"
},
  "geometry": {"coordinates":[-81.69458899999999,41.478792],"type":"Point"}
}