{
  "type": "Feature",
  "properties": {
    "iso:country":"US",
    "sg:address":"25 Tarbell Ave",
    "sg:city":"Cleveland",
    "sg:classifiers":[
        {
            "category":"Health Services",
            "subcategory":"Doctor",
            "type":"Services"
        }
    ],
    "sg:phone":"+1 440 439 7766",
    "sg:postcode":"44146",
    "sg:province":"OH",
    "sg:tags":[
        "physician",
        "surgeon"
    ],
    "wof:name":"Mohan Bafna Inc",
    "wof:placetype":"venue"
},
  "geometry": {"coordinates":[-81.534674,41.392811],"type":"Point"}
}