{
  "type": "Feature",
  "properties": {
    "addr:full":"6147 Dorr St Toledo OH 43615",
    "addr:housenumber":"6147",
    "addr:postcode":"43615",
    "addr:street":"Dorr St",
    "iso:country":"US",
    "sg:address":"6147 Dorr St",
    "sg:city":"Toledo",
    "sg:classifiers":[
        {
            "category":"Education",
            "subcategory":"Special Training",
            "type":"Public Place"
        }
    ],
    "sg:phone":"+1 419 867 1606",
    "sg:postcode":"43615",
    "sg:province":"OH",
    "sg:tags":[
        "instruction",
        "music"
    ],
    "wof:name":"Wilson Guitar Studio",
    "wof:placetype":"venue"
},
  "geometry": {"coordinates":[-83.687517,41.653728],"type":"Point"}
}