{
  "type": "Feature",
  "properties": {
    "addr:full":"1401 Parkview Cir Steubenville OH 43952",
    "addr:housenumber":"1401",
    "addr:postcode":"43952",
    "addr:street":"Parkview Cir",
    "iso:country":"US",
    "sg:address":"1401 Parkview Cir",
    "sg:city":"Steubenville",
    "sg:classifiers":[
        {
            "category":"Real Estate",
            "subcategory":"Real Estate Agent",
            "type":"Services"
        }
    ],
    "sg:phone":"+1 740 283 7958",
    "sg:postcode":"43952",
    "sg:province":"OH",
    "sg:tags":[
        "authorities",
        "housing"
    ],
    "wof:name":"Jefferson Metro Housing",
    "wof:placetype":"venue"
},
  "geometry": {"coordinates":[-80.62555999999999,40.377315],"type":"Point"}
}