{
  "type": "Feature",
  "properties": {
    "addr:full":"9111 Marquis Ct Miamisburg OH 45342",
    "addr:housenumber":"9111",
    "addr:postcode":"45342",
    "addr:street":"Marquis Ct",
    "iso:country":"US",
    "sg:address":"9111 Marquis Ct",
    "sg:city":"Miamisburg",
    "sg:classifiers":[
        {
            "category":"Professional",
            "subcategory":"Management & Consulting",
            "type":"Services"
        }
    ],
    "sg:phone":"+1 937 312 1698",
    "sg:postcode":"45342",
    "sg:province":"OH",
    "sg:tags":[
        "consultant",
        "training"
    ],
    "wof:name":"Training Service & Solutions",
    "wof:placetype":"venue"
},
  "geometry": {"coordinates":[-84.215445,39.619051],"type":"Point"}
}