{
  "type": "Feature",
  "properties": {
    "addr:full":"4525 Burger Ave Cleveland OH 44109",
    "addr:housenumber":"4525",
    "addr:postcode":"44109",
    "addr:street":"Burger Ave",
    "iso:country":"US",
    "sg:address":"4525 Burger Ave",
    "sg:city":"Cleveland",
    "sg:classifiers":[
        {
            "category":"Professional",
            "subcategory":"Computer Services",
            "type":"Services"
        }
    ],
    "sg:phone":"+1 216 741 6065",
    "sg:postcode":"44109",
    "sg:province":"OH",
    "sg:tags":[
        "consultant",
        "designer"
    ],
    "wof:name":"Scientific Technologies",
    "wof:placetype":"venue"
},
  "geometry": {"coordinates":[-81.71807200000001,41.423657],"type":"Point"}
}