{
  "type": "Feature",
  "properties": {
    "addr:full": "3191 Princeton Rd Hamilton OH 45011",
    "addr:housenumber": "3191",
    "addr:postcode": "45011",
    "addr:street": "Princeton Rd",
    "iso:country": "US",
    "sg:address": "3191 Princeton Rd",
    "sg:city": "Hamilton",
    "sg:classifiers": [
      {
        "category": "Deli",
        "type": "Food \u0026 Drink"
      }
    ],
    "sg:menulink": "http://www.allmenus.com/oh/fairfield/235635-sarpinos-pizzeria/menu/",
    "sg:phone": "+1 513 895 2400",
    "sg:postcode": "45011",
    "sg:province": "OH",
    "sg:tags": [
      "american"
    ],
    "wof:name": "Sarpino's Pizzeria",
    "wof:placetype": "venue"
  },
  "geometry": {"coordinates":[-84.509036,39.390969],"type":"Point"}
}
