{
  "type": "Feature",
  "properties": {
    "addr:full":"215 Byers Rd Miamisburg OH 45342",
    "addr:housenumber":"215",
    "addr:postcode":"45342",
    "addr:street":"Byers Rd",
    "iso:country":"US",
    "sg:address":"215 Byers Rd",
    "sg:city":"Miamisburg",
    "sg:classifiers":[
        {
            "category":"Food & Beverages",
            "subcategory":"Groceries & Convenience Stores",
            "type":"Retail Goods"
        }
    ],
    "sg:phone":"+1 937 865 9123",
    "sg:postcode":"45342",
    "sg:province":"OH",
    "wof:name":"Tienda Mexicana",
    "wof:placetype":"venue"
},
  "geometry": {"coordinates":[-84.234573,39.638558],"type":"Point"}
}