{
  "type": "Feature",
  "properties": {
    "addr:full":"4480 Refugee Rd Columbus OH 43232",
    "addr:housenumber":"4480",
    "addr:postcode":"43232",
    "addr:street":"Refugee Rd",
    "iso:country":"US",
    "sg:address":"4480 Refugee Rd",
    "sg:city":"Columbus",
    "sg:classifiers":[
        {
            "category":"Social Services",
            "type":"Services"
        }
    ],
    "sg:phone":"+1 614 751 9112",
    "sg:postcode":"43232",
    "sg:province":"OH",
    "sg:tags":[
        "agency",
        "adoption"
    ],
    "wof:name":"Paranthesis Family Advocates",
    "wof:placetype":"venue"
},
  "geometry": {"coordinates":[-82.876985,39.915413],"type":"Point"}
}