{
  "type": "Feature",
  "properties": {
    "iso:country":"US",
    "sg:address":"1172 Tuscarawas Ave NW",
    "sg:city":"New Philadelphia",
    "sg:classifiers":[
        {
            "category":"Retail",
            "subcategory":"Auto Repair",
            "type":"Services"
        }
    ],
    "sg:phone":"+1 330 343 3013",
    "sg:postcode":"44663",
    "sg:province":"OH",
    "sg:tags":[
        "repairing",
        "automobile"
    ],
    "wof:name":"A & M Svc Ctr",
    "wof:placetype":"venue"
},
  "geometry": {"coordinates":[-81.467586,40.504831],"type":"Point"}
}