{
  "type": "Feature",
  "properties": {
    "addr:full": "8677 Emerson Rd Apple Creek OH 44606",
    "addr:housenumber": "8677",
    "addr:postcode": "44606",
    "addr:street": "Emerson Rd",
    "iso:country": "US",
    "sg:address": "8677 Emerson Rd",
    "sg:city": "Apple Creek",
    "sg:classifiers": [
      {
        "category": "Wholesale",
        "subcategory": "Machinery \u0026 Supplies",
        "type": "Manufacturing \u0026 Wholesale Goods"
      }
    ],
    "sg:phone": "+1 330 698 3003",
    "sg:postcode": "44606",
    "sg:province": "OH",
    "sg:tags": [
      "field",
      "oil"
    ],
    "wof:name": "Omega Cementing Co",
    "wof:placetype": "venue"
  },
  "geometry": {"coordinates":[-81.818613,40.740864],"type":"Point"}
}
