{
  "type": "Feature",
  "properties": {
    "addr:full": "3761 Fishcreek Rd Stow OH 44224",
    "addr:housenumber": "3761",
    "addr:postcode": "44224",
    "addr:street": "Fishcreek Rd",
    "iso:country": "US",
    "sg:address": "3761 Fishcreek Rd",
    "sg:city": "Stow",
    "sg:classifiers": [
      {
        "category": "Social Services",
        "type": "Services"
      }
    ],
    "sg:phone": "+1 330 686 0377",
    "sg:postcode": "44224",
    "sg:province": "OH",
    "sg:tags": [
      "counselor",
      "marriage",
      "family"
    ],
    "wof:name": "Humanistic Counseling Ctr",
    "wof:placetype": "venue"
  },
  "geometry": {"coordinates":[-81.401377,41.161548],"type":"Point"}
}
