{
  "type": "Feature",
  "properties": {
    "addr:full":"1300 Erie St S Massillon OH 44646",
    "addr:housenumber":"1300",
    "addr:postcode":"44646",
    "addr:street":"Erie St S",
    "iso:country":"US",
    "sg:address":"1300 Erie St S",
    "sg:city":"Massillon",
    "sg:classifiers":[
        {
            "category":"Manufacturing",
            "subcategory":"Tools & Machinery",
            "type":"Manufacturing & Wholesale Goods"
        },
        {
            "category":"Retail",
            "subcategory":"Auto Repair",
            "type":"Services"
        }
    ],
    "sg:phone":"+1 330 837 2254",
    "sg:postcode":"44646",
    "sg:province":"OH",
    "sg:tags":[
        "engine",
        "shop",
        "mfg",
        "automobile",
        "machine",
        "racing"
    ],
    "sg:website":"www.draime.com",
    "wof:name":"Draime Enterprises Inc",
    "wof:placetype":"venue"
},
  "geometry": {"coordinates":[-81.516203,40.782394],"type":"Point"}
}