{
  "type": "Feature",
  "properties": {
    "addr:full": "2580 State Rte 141 Gallipolis OH 45631",
    "addr:housenumber": "2580",
    "addr:postcode": "45631",
    "addr:street": "State Rte 141",
    "iso:country": "US",
    "sg:address": "2580 State Rte 141",
    "sg:city": "Gallipolis",
    "sg:classifiers": [
      {
        "category": "Retail",
        "subcategory": "Repair Shop",
        "type": "Services"
      }
    ],
    "sg:phone": "+1 740 446 7797",
    "sg:postcode": "45631",
    "sg:province": "OH",
    "sg:tags": [
      "cleaners",
      "parts",
      "vacuum"
    ],
    "wof:name": "Century Distributors",
    "wof:placetype": "venue"
  },
  "geometry": {"coordinates":[-82.255463,38.799598],"type":"Point"}
}
