{
  "type": "Feature",
  "properties": {
    "iso:country":"US",
    "sg:address":"4397 N Leavitt Rd",
    "sg:city":"Lorain",
    "sg:classifiers":[
        {
            "category":"Recreation",
            "type":"Entertainment"
        }
    ],
    "sg:phone":"+1 440 282 5663",
    "sg:postcode":"44053",
    "sg:province":"OH",
    "sg:tags":[
        "club",
        "membership"
    ],
    "wof:name":"Emerald Valley Country Club",
    "wof:placetype":"venue"
},
  "geometry": {"coordinates":[-82.204277,41.427645],"type":"Point"}
}