{
  "type": "Feature",
  "properties": {
    "iso:country":"US",
    "sg:address":"5611 Autumn Chase Dr",
    "sg:city":"Columbus",
    "sg:classifiers":[
        {
            "category":"Real Estate",
            "subcategory":"Real Estate Operator",
            "type":"Services"
        }
    ],
    "sg:phone":"+1 614 868 0211",
    "sg:postcode":"43232",
    "sg:province":"OH",
    "sg:tags":[
        "apartment"
    ],
    "wof:name":"Autumn Chase Town Homes",
    "wof:placetype":"venue"
},
  "geometry": {"coordinates":[-82.844134,39.942515],"type":"Point"}
}