{
  "type": "Feature",
  "properties": {
    "iso:country":"US",
    "sg:address":"865 Summit Ave",
    "sg:city":"Niles",
    "sg:classifiers":[
        {
            "category":"Taxi",
            "type":"Transportation"
        }
    ],
    "sg:phone":"+1 330 394 8294",
    "sg:postcode":"44446",
    "sg:province":"OH",
    "sg:tags":[
        "taxicab"
    ],
    "wof:name":"New Valley Taxi",
    "wof:placetype":"venue"
},
  "geometry": {"coordinates":[-80.741458,41.172276],"type":"Point"}
}