{
  "type": "Feature",
  "properties": {
    "iso:country":"US",
    "sg:address":"23811 Chagrin Blvd",
    "sg:city":"Cleveland",
    "sg:classifiers":[
        {
            "category":"Health Services",
            "subcategory":"Health Practitioner",
            "type":"Services"
        }
    ],
    "sg:phone":"+1 216 464 1277",
    "sg:postcode":"44122",
    "sg:province":"OH",
    "sg:tags":[
        "psychologist"
    ],
    "wof:name":"Mark Lovinger & Assoc Inc",
    "wof:placetype":"venue"
},
  "geometry": {"coordinates":[-81.498794,41.464509],"type":"Point"}
}