{
  "type": "Feature",
  "properties": {
    "iso:country":"US",
    "sg:address":"175 Marybill Dr",
    "sg:city":"Troy",
    "sg:classifiers":[
        {
            "category":"Manufacturing",
            "subcategory":"Tools & Machinery",
            "type":"Manufacturing & Wholesale Goods"
        }
    ],
    "sg:phone":"+1 937 335 9353",
    "sg:postcode":"45373",
    "sg:province":"OH",
    "sg:tags":[
        "machine",
        "shop"
    ],
    "wof:name":"Trackomatic Systems",
    "wof:placetype":"venue"
},
  "geometry": {"coordinates":[-84.243554,40.064928],"type":"Point"}
}