{
  "type": "Feature",
  "properties": {
    "addr:full": "175 Marybill Dr Troy OH 45373",
    "addr:housenumber": "175",
    "addr:postcode": "45373",
    "addr:street": "Marybill Dr",
    "iso:country": "US",
    "sg:address": "175 Marybill Dr",
    "sg:city": "Troy",
    "sg:classifiers": [
      {
        "category": "Manufacturing",
        "subcategory": "Tools \u0026 Machinery",
        "type": "Manufacturing \u0026 Wholesale Goods"
      }
    ],
    "sg:phone": "+1 937 335 9353",
    "sg:postcode": "45373",
    "sg:province": "OH",
    "sg:tags": [
      "machine",
      "shop"
    ],
    "wof:name": "Trackomatic Systems",
    "wof:placetype": "venue"
  },
  "geometry": {"coordinates":[-84.243554,40.064928],"type":"Point"}
}
