{
  "type": "Feature",
  "properties": {
    "iso:country":"US",
    "sg:address":"338 Wood St",
    "sg:city":"Piqua",
    "sg:classifiers":[
        {
            "category":"Shopping",
            "subcategory":"Clothing, Apparel, & Fashions",
            "type":"Retail Goods"
        }
    ],
    "sg:phone":"+1 937 773 9832",
    "sg:postcode":"45356",
    "sg:province":"OH",
    "wof:name":"Desmonds/Russells Formal Wear",
    "wof:placetype":"venue"
},
  "geometry": {"coordinates":[-84.243078,40.145284],"type":"Point"}
}