{
  "type": "Feature",
  "properties": {
    "addr:full": "67885 Friends Church Rd St Clairsville OH 43950",
    "addr:postcode": "67885;43950",
    "addr:street": "Church Rd",
    "iso:country": "US",
    "sg:address": "67885 Friends Church Rd",
    "sg:city": "St Clairsville",
    "sg:classifiers": [
      {
        "category": "Organizations",
        "subcategory": "Religious Organization",
        "type": "Services"
      }
    ],
    "sg:phone": "+1 740 695 0971",
    "sg:postcode": "43950",
    "sg:province": "OH",
    "sg:tags": [
      "church"
    ],
    "sg:website": "www.eastrichlandfriends.com",
    "wof:name": "East Richland Evangelical Chr",
    "wof:placetype": "venue"
  },
  "geometry": {"coordinates":[-80.954857,40.06671],"type":"Point"}
}
