{
  "type": "Feature",
  "properties": {
    "iso:country":"US",
    "sg:address":"7359 Maple St",
    "sg:city":"Mentor",
    "sg:classifiers":[
        {
            "category":"Banks & Credit Unions",
            "subcategory":"Bank",
            "type":"Services"
        }
    ],
    "sg:phone":"+1 440 255 2560",
    "sg:postcode":"44060",
    "sg:province":"OH",
    "sg:tags":[
        "state"
    ],
    "wof:name":"North East Ohio Federal Cr Un",
    "wof:placetype":"venue"
},
  "geometry": {"coordinates":[-81.332887,41.671726],"type":"Point"}
}