{
  "type": "Feature",
  "properties": {
    "iso:country":"US",
    "sg:address":"6079 Blazer Pkwy",
    "sg:city":"Dublin",
    "sg:classifiers":[
        {
            "category":"Banks & Credit Unions",
            "subcategory":"Bank",
            "type":"Services"
        }
    ],
    "sg:phone":"+1 614 717 7801",
    "sg:postcode":"43017",
    "sg:province":"OH",
    "sg:tags":[
        "national",
        "commercial"
    ],
    "wof:name":"Firstar Bank",
    "wof:placetype":"venue"
},
  "geometry": {"coordinates":[-83.130417,40.081758],"type":"Point"}
}