{
  "type": "Feature",
  "properties": {
    "addr:full":"2025 W Market St Warren OH 44485",
    "addr:housenumber":"2025",
    "addr:postcode":"44485",
    "addr:street":"W Market St",
    "iso:country":"US",
    "sg:address":"2025 W Market St",
    "sg:city":"Warren",
    "sg:classifiers":[
        {
            "category":"Organizations",
            "subcategory":"Religious Organization",
            "type":"Services"
        }
    ],
    "sg:phone":"+1 330 399 4400",
    "sg:postcode":"44485",
    "sg:province":"OH",
    "sg:tags":[
        "church"
    ],
    "wof:name":"Body Of Christ Church",
    "wof:placetype":"venue"
},
  "geometry": {"coordinates":[-80.845164,41.235655],"type":"Point"}
}