{
  "type": "Feature",
  "properties": {
    "addr:full": "3892 E Broad St Columbus OH 43213",
    "addr:housenumber": "3892",
    "addr:postcode": "43213",
    "addr:street": "E Broad St",
    "iso:country": "US",
    "sg:address": "3892 E Broad St",
    "sg:city": "Columbus",
    "sg:classifiers": [
      {
        "category": "Professional",
        "subcategory": "Business Services",
        "type": "Services"
      }
    ],
    "sg:phone": "+1 614 237 0480",
    "sg:postcode": "43213",
    "sg:province": "OH",
    "sg:tags": [
      "embroidery"
    ],
    "wof:name": "Quality Stitch Embroidery Inc",
    "wof:placetype": "venue"
  },
  "geometry": {"coordinates":[-82.900741,39.97323],"type":"Point"}
}
