{
  "type": "Feature",
  "properties": {
    "addr:full": "4452 Heatherdowns Blvd Toledo OH 43614",
    "addr:housenumber": "4452",
    "addr:postcode": "43614",
    "addr:street": "Heatherdowns Blvd",
    "iso:country": "US",
    "sg:address": "4452 Heatherdowns Blvd",
    "sg:city": "Toledo",
    "sg:classifiers": [
      {
        "category": "Building \u0026 Trades",
        "subcategory": "Construction",
        "type": "Services"
      }
    ],
    "sg:phone": "+1 419 867 2700",
    "sg:postcode": "43614",
    "sg:province": "OH",
    "sg:tags": [
      "general",
      "contractor"
    ],
    "wof:name": "Abdo Home Remodeling Inc",
    "wof:placetype": "venue"
  },
  "geometry": {"coordinates":[-83.648356,41.594391],"type":"Point"}
}
