{
  "type": "Feature",
  "properties": {
    "addr:full": "120 Haskell Dr Cleveland OH 44108",
    "addr:housenumber": "120",
    "addr:postcode": "44108",
    "addr:street": "Haskell Dr",
    "iso:country": "US",
    "sg:address": "120 Haskell Dr",
    "sg:city": "Cleveland",
    "sg:classifiers": [
      {
        "category": "Building \u0026 Trades",
        "subcategory": "Construction",
        "type": "Services"
      }
    ],
    "sg:phone": "+1 216 851 2580",
    "sg:postcode": "44108",
    "sg:province": "OH",
    "sg:tags": [
      "home",
      "builder"
    ],
    "wof:name": "Haskell Homes Inc",
    "wof:placetype": "venue"
  },
  "geometry": {"coordinates":[-81.60279,41.554692],"type":"Point"}
}
