{
  "type": "Feature",
  "properties": {
    "iso:country":"US",
    "sg:address":"300 N Main St",
    "sg:city":"Glandorf",
    "sg:classifiers":[
        {
            "category":"Wholesale",
            "subcategory":"Farm Supplies",
            "type":"Manufacturing & Wholesale Goods"
        }
    ],
    "sg:phone":"+1 419 538 6521",
    "sg:postcode":"45875",
    "sg:province":"OH",
    "sg:tags":[
        "feed"
    ],
    "wof:name":"Glandorf Feed Co",
    "wof:placetype":"venue"
},
  "geometry": {"coordinates":[-84.082206,41.032916],"type":"Point"}
}