{
  "type": "Feature",
  "properties": {
    "addr:full": "300 N Main St Glandorf OH 45875",
    "addr:housenumber": "300",
    "addr:postcode": "45875",
    "addr:street": "N Main St",
    "iso:country": "US",
    "sg:address": "300 N Main St",
    "sg:city": "Glandorf",
    "sg:classifiers": [
      {
        "category": "Wholesale",
        "subcategory": "Farm Supplies",
        "type": "Manufacturing \u0026 Wholesale Goods"
      }
    ],
    "sg:phone": "+1 419 538 6521",
    "sg:postcode": "45875",
    "sg:province": "OH",
    "sg:tags": [
      "feed"
    ],
    "wof:name": "Glandorf Feed Co",
    "wof:placetype": "venue"
  },
  "geometry": {"coordinates":[-84.082206,41.032916],"type":"Point"}
}
