{
  "type": "Feature",
  "properties": {
    "addr:full":"2089 Clague Rd Cleveland OH 44145",
    "addr:housenumber":"2089",
    "addr:postcode":"44145",
    "addr:street":"Clague Rd",
    "iso:country":"US",
    "sg:address":"2089 Clague Rd",
    "sg:city":"Cleveland",
    "sg:classifiers":[
        {
            "category":"Personal",
            "subcategory":"Beauty Salon",
            "type":"Services"
        }
    ],
    "sg:phone":"+1 440 356 0230",
    "sg:postcode":"44145",
    "sg:province":"OH",
    "wof:name":"Magic Shears",
    "wof:placetype":"venue"
},
  "geometry": {"coordinates":[-81.882887,41.458688],"type":"Point"}
}