{
  "type": "Feature",
  "properties": {
    "iso:country":"US",
    "sg:address":"86801 Eslick Rd",
    "sg:city":"Uhrichsville",
    "sg:classifiers":[
        {
            "category":"Government",
            "subcategory":"Office",
            "type":"Public Place"
        }
    ],
    "sg:phone":"+1 740 269 2681",
    "sg:postcode":"44683",
    "sg:province":"OH",
    "sg:tags":[
        "federal"
    ],
    "wof:name":"US Army Corps Of Engineers",
    "wof:placetype":"venue"
},
  "geometry": {"coordinates":[-81.230923,40.354497],"type":"Point"}
}