{
  "type": "Feature",
  "properties": {
    "addr:full": "4709 Interstate Dr Cincinnati OH 45246",
    "addr:housenumber": "4709",
    "addr:postcode": "45246",
    "addr:street": "Interstate Dr",
    "iso:country": "US",
    "sg:address": "4709 Interstate Dr",
    "sg:city": "Cincinnati",
    "sg:classifiers": [
      {
        "category": "Professional",
        "subcategory": "Business Services",
        "type": "Services"
      }
    ],
    "sg:phone": "+1 513 942 6805",
    "sg:postcode": "45246",
    "sg:province": "OH",
    "wof:name": "Charles Levy Transportation Co",
    "wof:placetype": "venue"
  },
  "geometry": {"coordinates":[-84.467637,39.308655],"type":"Point"}
}
