{
  "type": "Feature",
  "properties": {
    "addr:full": "624 Reineck Dr Toledo OH 43605",
    "addr:housenumber": "624",
    "addr:postcode": "43605",
    "addr:street": "Reineck Dr",
    "iso:country": "US",
    "sg:address": "624 Reineck Dr",
    "sg:city": "Toledo",
    "sg:classifiers": [
      {
        "category": "Recreation",
        "type": "Entertainment"
      }
    ],
    "sg:phone": "+1 419 693 1991",
    "sg:postcode": "43605",
    "sg:province": "OH",
    "sg:tags": [
      "club",
      "course",
      "membership",
      "golf",
      "public"
    ],
    "wof:name": "Collins Park Golf Course",
    "wof:placetype": "venue"
  },
  "geometry": {"coordinates":[-83.485044,41.664282],"type":"Point"}
}
