{
  "type": "Feature",
  "properties": {
    "addr:full": "314 Takisa Cir Dayton OH 45415",
    "addr:housenumber": "314",
    "addr:postcode": "45415",
    "addr:street": "Takisa Cir",
    "iso:country": "US",
    "sg:address": "314 Takisa Cir",
    "sg:city": "Dayton",
    "sg:classifiers": [
      {
        "category": "Professional",
        "type": "Services"
      }
    ],
    "sg:phone": "+1 937 454 2063",
    "sg:postcode": "45415",
    "sg:province": "OH",
    "wof:name": "Geoshack",
    "wof:placetype": "venue"
  },
  "geometry": {"coordinates":[-84.268151,39.839957],"type":"Point"}
}
