{
  "type": "Feature",
  "properties": {
    "iso:country":"US",
    "sg:address":"1591 E Market St",
    "sg:city":"Akron",
    "sg:classifiers":[
        {
            "category":"Retail",
            "subcategory":"Auto Repair",
            "type":"Services"
        }
    ],
    "sg:phone":"+1 330 784 8899",
    "sg:postcode":"44305",
    "sg:province":"OH",
    "sg:tags":[
        "muffler",
        "exhaust",
        "system"
    ],
    "wof:name":"Market Street Muffler",
    "wof:placetype":"venue"
},
  "geometry": {"coordinates":[-81.47105,41.062765],"type":"Point"}
}