{
  "type": "Feature",
  "properties": {
    "addr:full":"35 Sivon Dr Painesville OH 44077",
    "addr:housenumber":"35",
    "addr:postcode":"44077",
    "addr:street":"Sivon Dr",
    "iso:country":"US",
    "sg:address":"35 Sivon Dr",
    "sg:city":"Painesville",
    "sg:classifiers":[
        {
            "category":"Building & Trades",
            "subcategory":"Construction",
            "type":"Services"
        }
    ],
    "sg:phone":"+1 440 946 1495",
    "sg:postcode":"44077",
    "sg:province":"OH",
    "sg:tags":[
        "siding",
        "contractor"
    ],
    "wof:name":"Shoreline Window & Remodeling",
    "wof:placetype":"venue"
},
  "geometry": {"coordinates":[-81.19900699999999,41.753185],"type":"Point"}
}