{
  "type": "Feature",
  "properties": {
    "addr:full": "62 Pembroke Rd Fairlawn OH 44333",
    "addr:housenumber": "62",
    "addr:postcode": "44333",
    "addr:street": "Pembroke Rd",
    "iso:country": "US",
    "sg:address": "62 Pembroke Rd",
    "sg:city": "Fairlawn",
    "sg:classifiers": [
      {
        "category": "Organizations",
        "subcategory": "Religious Organization",
        "type": "Services"
      }
    ],
    "sg:phone": "+1 330 867 9427",
    "sg:postcode": "44333",
    "sg:province": "OH",
    "sg:tags": [
      "clergy"
    ],
    "wof:name": "J Michael Mancari",
    "wof:placetype": "venue"
  },
  "geometry": {"coordinates":[-81.599383,41.125325],"type":"Point"}
}
