{
  "type": "Feature",
  "properties": {
    "addr:full": "1498 Fortman Rd Fort Loramie OH 45845",
    "addr:housenumber": "1498",
    "addr:postcode": "45845",
    "addr:street": "Fortman Rd",
    "iso:country": "US",
    "sg:address": "1498 Fortman Rd",
    "sg:city": "Fort Loramie",
    "sg:classifiers": [
      {
        "category": "Building \u0026 Trades",
        "subcategory": "Construction",
        "type": "Services"
      }
    ],
    "sg:phone": "+1 937 295 2839",
    "sg:postcode": "45845",
    "sg:province": "OH",
    "sg:tags": [
      "contractor"
    ],
    "wof:name": "Tony Meyer Construction Co",
    "wof:placetype": "venue"
  },
  "geometry": {"coordinates":[-84.408076,40.356207],"type":"Point"}
}
