{
  "type": "Feature",
  "properties": {
    "iso:country":"US",
    "sg:address":"15 W Central Pkwy",
    "sg:city":"Cincinnati",
    "sg:classifiers":[
        {
            "category":"Travel",
            "subcategory":"Travel Agent",
            "type":"Entertainment"
        }
    ],
    "sg:phone":"+1 513 762 3100",
    "sg:postcode":"45202",
    "sg:province":"OH",
    "sg:tags":[
        "agency"
    ],
    "wof:name":"AAA Travel Centers-Hdqtrs.",
    "wof:placetype":"venue"
},
  "geometry": {"coordinates":[-84.514938,39.106988],"type":"Point"}
}