{
  "type": "Feature",
  "properties": {
    "addr:full": "15 W Central Pkwy Cincinnati OH 45202",
    "addr:housenumber": "15",
    "addr:postcode": "45202",
    "addr:street": "W Central Pkwy",
    "iso:country": "US",
    "sg:address": "15 W Central Pkwy",
    "sg:city": "Cincinnati",
    "sg:classifiers": [
      {
        "category": "Travel",
        "subcategory": "Travel Agent",
        "type": "Entertainment"
      }
    ],
    "sg:phone": "+1 513 762 3100",
    "sg:postcode": "45202",
    "sg:province": "OH",
    "sg:tags": [
      "agency"
    ],
    "wof:name": "AAA Travel Centers-Hdqtrs.",
    "wof:placetype": "venue"
  },
  "geometry": {"coordinates":[-84.514938,39.106988],"type":"Point"}
}
