{
  "type": "Feature",
  "properties": {
    "iso:country":"US",
    "sg:address":"4593 Belden Village St NW",
    "sg:city":"Canton",
    "sg:classifiers":[
        {
            "category":"Shopping",
            "subcategory":"Computers & Home Electronics",
            "type":"Retail Goods"
        }
    ],
    "sg:phone":"+1 330 493 3474",
    "sg:postcode":"44718",
    "sg:province":"OH",
    "sg:tags":[
        "system"
    ],
    "wof:name":"Satellite Center Inc",
    "wof:placetype":"venue"
},
  "geometry": {"coordinates":[-81.43458,40.85654],"type":"Point"}
}