{
  "type": "Feature",
  "properties": {
    "addr:full": "4593 Belden Village St NW Canton OH 44718",
    "addr:housenumber": "4593",
    "addr:postcode": "44718",
    "addr:street": "Belden Village St Nw",
    "iso:country": "US",
    "sg:address": "4593 Belden Village St NW",
    "sg:city": "Canton",
    "sg:classifiers": [
      {
        "category": "Shopping",
        "subcategory": "Computers \u0026 Home Electronics",
        "type": "Retail Goods"
      }
    ],
    "sg:phone": "+1 330 493 3474",
    "sg:postcode": "44718",
    "sg:province": "OH",
    "sg:tags": [
      "system"
    ],
    "wof:name": "Satellite Center Inc",
    "wof:placetype": "venue"
  },
  "geometry": {"coordinates":[-81.43458,40.85654],"type":"Point"}
}
