{
  "type": "Feature",
  "properties": {
    "iso:country":"US",
    "sg:address":"11828 Airport Hwy",
    "sg:city":"Swanton",
    "sg:classifiers":[
        {
            "category":"Restaurant",
            "type":"Food & Drink"
        }
    ],
    "sg:phone":"+1 419 826 0761",
    "sg:postcode":"43558",
    "sg:province":"OH",
    "sg:tags":[
        "beverage",
        "eating",
        "alcoholic"
    ],
    "wof:name":"Airport Carry Out Store",
    "wof:placetype":"venue"
},
  "geometry": {"coordinates":[-83.826072,41.588273],"type":"Point"}
}