{
  "type": "Feature",
  "properties": {
    "addr:full": "11828 Airport Hwy Swanton OH 43558",
    "addr:housenumber": "11828",
    "addr:postcode": "43558",
    "addr:street": "Airport Hwy",
    "iso:country": "US",
    "sg:address": "11828 Airport Hwy",
    "sg:city": "Swanton",
    "sg:classifiers": [
      {
        "category": "Restaurant",
        "type": "Food \u0026 Drink"
      }
    ],
    "sg:phone": "+1 419 826 0761",
    "sg:postcode": "43558",
    "sg:province": "OH",
    "sg:tags": [
      "beverage",
      "eating",
      "alcoholic"
    ],
    "wof:name": "Airport Carry Out Store",
    "wof:placetype": "venue"
  },
  "geometry": {"coordinates":[-83.826072,41.588273],"type":"Point"}
}
