{
  "type": "Feature",
  "properties": {
    "addr:full": "295 Harmon Ave NW Warren OH 44483",
    "addr:housenumber": "295",
    "addr:postcode": "44483",
    "addr:street": "Harmon Ave Nw",
    "iso:country": "US",
    "sg:address": "295 Harmon Ave NW",
    "sg:city": "Warren",
    "sg:classifiers": [
      {
        "category": "Professional",
        "subcategory": "Lawyer \u0026 Legal Services",
        "type": "Services"
      }
    ],
    "sg:phone": "+1 330 392 2571",
    "sg:postcode": "44483",
    "sg:province": "OH",
    "sg:tags": [
      "attorney"
    ],
    "wof:name": "James J Connelly",
    "wof:placetype": "venue"
  },
  "geometry": {"coordinates":[-80.819649,41.237482],"type":"Point"}
}
