{
  "type": "Feature",
  "properties": {
    "addr:full":"2812 W Erie Ave Lorain OH 44053",
    "addr:housenumber":"2812",
    "addr:postcode":"44053",
    "addr:street":"W Erie Ave",
    "iso:country":"US",
    "sg:address":"2812 W Erie Ave",
    "sg:city":"Lorain",
    "sg:classifiers":[
        {
            "category":"Restaurant",
            "type":"Food & Drink"
        }
    ],
    "sg:phone":"+1 440 245 5822",
    "sg:postcode":"44053",
    "sg:province":"OH",
    "wof:name":"Chris' Restaurant",
    "wof:placetype":"venue"
},
  "geometry": {"coordinates":[-82.20705599999999,41.456432],"type":"Point"}
}