{
  "type": "Feature",
  "properties": {
    "addr:full": "1144 Lloyd Rd Wickliffe OH 44092",
    "addr:housenumber": "1144",
    "addr:postcode": "44092",
    "addr:street": "Lloyd Rd",
    "iso:country": "US",
    "sg:address": "1144 Lloyd Rd",
    "sg:city": "Wickliffe",
    "sg:classifiers": [
      {
        "category": "Retail",
        "subcategory": "Auto Repair",
        "type": "Services"
      }
    ],
    "sg:phone": "+1 440 944 3724",
    "sg:postcode": "44092",
    "sg:province": "OH",
    "sg:tags": [
      "body",
      "automobile",
      "painting"
    ],
    "wof:name": "Ken's Garage",
    "wof:placetype": "venue"
  },
  "geometry": {"coordinates":[-81.48369,41.612047],"type":"Point"}
}
