{
  "type": "Feature",
  "properties": {
    "addr:full": "219 2nd St NW Barberton OH 44203",
    "addr:housenumber": "219",
    "addr:postcode": "44203",
    "addr:street": "2Nd St Nw",
    "iso:country": "US",
    "sg:address": "219 2nd St NW",
    "sg:city": "Barberton",
    "sg:classifiers": [
      {
        "category": "Insurance",
        "subcategory": "Insurance Agent",
        "type": "Services"
      }
    ],
    "sg:phone": "+1 330 753 3081",
    "sg:postcode": "44203",
    "sg:province": "OH",
    "wof:name": "Finnell \u0026 Smith",
    "wof:placetype": "venue"
  },
  "geometry": {"coordinates":[-81.60732,41.01744],"type":"Point"}
}
