{
  "type": "Feature",
  "properties": {
    "iso:country":"US",
    "sg:address":"219 2nd St NW",
    "sg:city":"Barberton",
    "sg:classifiers":[
        {
            "category":"Insurance",
            "subcategory":"Insurance Agent",
            "type":"Services"
        }
    ],
    "sg:phone":"+1 330 753 3081",
    "sg:postcode":"44203",
    "sg:province":"OH",
    "wof:name":"Finnell & Smith",
    "wof:placetype":"venue"
},
  "geometry": {"coordinates":[-81.60732,41.01744],"type":"Point"}
}