{
  "type": "Feature",
  "properties": {
    "iso:country":"US",
    "sg:address":"1855 E Rusk Rd",
    "sg:city":"Troy",
    "sg:classifiers":[
        {
            "category":"Wholesale",
            "subcategory":"Medical Equipment & Supplies",
            "type":"Manufacturing & Wholesale Goods"
        }
    ],
    "sg:phone":"+1 937 335 8333",
    "sg:postcode":"45373",
    "sg:province":"OH",
    "sg:tags":[
        "professional",
        "microscope"
    ],
    "wof:name":"Dayton Microscope Supply Inc",
    "wof:placetype":"venue"
},
  "geometry": {"coordinates":[-84.16422300000001,40.089877],"type":"Point"}
}