{
  "type": "Feature",
  "properties": {
    "addr:full":"5253 E Broad St Columbus OH 43213",
    "addr:housenumber":"5253",
    "addr:postcode":"43213",
    "addr:street":"E Broad St",
    "iso:country":"US",
    "sg:address":"5253 E Broad St",
    "sg:city":"Columbus",
    "sg:classifiers":[
        {
            "category":"Health Services",
            "subcategory":"Nursing And Care Facility",
            "type":"Services"
        }
    ],
    "sg:phone":"+1 614 856 9951",
    "sg:postcode":"43213",
    "sg:province":"OH",
    "sg:tags":[
        "home",
        "retirement",
        "community"
    ],
    "wof:name":"Villas At St Therese Indpndnt",
    "wof:placetype":"venue"
},
  "geometry": {"coordinates":[-82.86401499999999,39.977123],"type":"Point"}
}