{
  "type": "Feature",
  "properties": {
    "iso:country":"US",
    "sg:address":"757 Richmond Rd",
    "sg:city":"Cleveland",
    "sg:classifiers":[
        {
            "category":"Retail",
            "subcategory":"Auto Repair",
            "type":"Services"
        }
    ],
    "sg:phone":"+1 440 442 7505",
    "sg:postcode":"44143",
    "sg:province":"OH",
    "sg:tags":[
        "general"
    ],
    "wof:name":"The Standard Oil Company",
    "wof:placetype":"venue"
},
  "geometry": {"coordinates":[-81.497095,41.539578],"type":"Point"}
}