{
  "type": "Feature",
  "properties": {
    "iso:country":"US",
    "sg:address":"3700 Lacon Rd",
    "sg:city":"Hilliard",
    "sg:classifiers":[
        {
            "category":"Health Services",
            "subcategory":"Health Practitioner",
            "type":"Services"
        }
    ],
    "sg:phone":"+1 614 529 5608",
    "sg:postcode":"43026",
    "sg:province":"OH",
    "sg:tags":[
        "nutritionist"
    ],
    "wof:name":"Shayla Stitser",
    "wof:placetype":"venue"
},
  "geometry": {"coordinates":[-83.133758,40.029964],"type":"Point"}
}