{
  "type": "Feature",
  "properties": {
    "addr:full":"1821 E 290th St Wickliffe OH 44092",
    "addr:housenumber":"1821",
    "addr:postcode":"44092",
    "addr:street":"E 290Th St",
    "iso:country":"US",
    "sg:address":"1821 E 290th St",
    "sg:city":"Wickliffe",
    "sg:classifiers":[
        {
            "category":"Building & Trades",
            "subcategory":"Construction",
            "type":"Services"
        }
    ],
    "sg:phone":"+1 440 944 9223",
    "sg:postcode":"44092",
    "sg:province":"OH",
    "sg:tags":[
        "painter"
    ],
    "wof:name":"Perfect Touch Decorating",
    "wof:placetype":"venue"
},
  "geometry": {"coordinates":[-81.476069,41.600508],"type":"Point"}
}