{
  "type": "Feature",
  "properties": {
    "addr:full":"3632 Franklin Rd Stow OH 44224",
    "addr:housenumber":"3632",
    "addr:postcode":"44224",
    "addr:street":"Franklin Rd",
    "iso:country":"US",
    "sg:address":"3632 Franklin Rd",
    "sg:city":"Stow",
    "sg:classifiers":[
        {
            "category":"Professional",
            "type":"Services"
        }
    ],
    "sg:phone":"+1 330 686 3059",
    "sg:postcode":"44224",
    "sg:province":"OH",
    "wof:name":"Salley Music Company",
    "wof:placetype":"venue"
},
  "geometry": {"coordinates":[-81.43640499999999,41.160669],"type":"Point"}
}