{
  "type": "Feature",
  "properties": {
    "addr:full":"936 Harrisburg Pike Columbus OH 43223",
    "addr:housenumber":"936",
    "addr:postcode":"43223",
    "addr:street":"Harrisburg Pike",
    "iso:country":"US",
    "sg:address":"936 Harrisburg Pike",
    "sg:city":"Columbus",
    "sg:classifiers":[
        {
            "category":"Real Estate",
            "subcategory":"Real Estate Agent",
            "type":"Services"
        }
    ],
    "sg:phone":"+1 614 871 3393",
    "sg:postcode":"43223",
    "sg:province":"OH",
    "wof:name":"Rankin Real Estate Inc",
    "wof:placetype":"venue"
},
  "geometry": {"coordinates":[-83.04156999999999,39.938182],"type":"Point"}
}