{
  "type": "Feature",
  "properties": {
    "addr:full":"713 Fox Creek Ln Cincinnati OH 45245",
    "addr:housenumber":"713",
    "addr:postcode":"45245",
    "addr:street":"Fox Creek Ln",
    "iso:country":"US",
    "sg:address":"713 Fox Creek Ln",
    "sg:city":"Cincinnati",
    "sg:classifiers":[
        {
            "category":"Insurance",
            "subcategory":"Insurance Agent",
            "type":"Services"
        }
    ],
    "sg:phone":"+1 513 753 7318",
    "sg:postcode":"45245",
    "sg:province":"OH",
    "sg:tags":[
        "accident"
    ],
    "wof:name":"A 1 Affordable Health Insur",
    "wof:placetype":"venue"
},
  "geometry": {"coordinates":[-84.273787,39.108253],"type":"Point"}
}