{
  "type": "Feature",
  "properties": {
    "iso:country":"US",
    "sg:address":"3540 S Dixie Hwy",
    "sg:city":"Lima",
    "sg:classifiers":[
        {
            "category":"Wholesale",
            "subcategory":"Electrical",
            "type":"Manufacturing & Wholesale Goods"
        }
    ],
    "sg:phone":"+1 419 228 7194",
    "sg:postcode":"45804",
    "sg:province":"OH",
    "sg:tags":[
        "alarm",
        "burglar",
        "system"
    ],
    "sg:website":"www.satelliteconnections.com",
    "wof:name":"SCI Security",
    "wof:placetype":"venue"
},
  "geometry": {"coordinates":[-84.126503,40.691308],"type":"Point"}
}