{
  "type": "Feature",
  "properties": {
    "addr:full": "3540 S Dixie Hwy Lima OH 45804",
    "addr:housenumber": "3540",
    "addr:postcode": "45804",
    "addr:street": "S Dixie Hwy",
    "iso:country": "US",
    "sg:address": "3540 S Dixie Hwy",
    "sg:city": "Lima",
    "sg:classifiers": [
      {
        "category": "Wholesale",
        "subcategory": "Electrical",
        "type": "Manufacturing \u0026 Wholesale Goods"
      }
    ],
    "sg:phone": "+1 419 228 7194",
    "sg:postcode": "45804",
    "sg:province": "OH",
    "sg:tags": [
      "alarm",
      "burglar",
      "system"
    ],
    "sg:website": "www.satelliteconnections.com",
    "wof:name": "SCI Security",
    "wof:placetype": "venue"
  },
  "geometry": {"coordinates":[-84.126503,40.691308],"type":"Point"}
}
