{
  "type": "Feature",
  "properties": {
    "addr:full": "7397 Texas Ave Mentor OH 44060",
    "addr:housenumber": "7397",
    "addr:postcode": "44060",
    "addr:street": "Texas Ave",
    "iso:country": "US",
    "sg:address": "7397 Texas Ave",
    "sg:city": "Mentor",
    "sg:classifiers": [
      {
        "category": "Shopping",
        "subcategory": "Gifts \u0026 Souvenirs",
        "type": "Retail Goods"
      }
    ],
    "sg:phone": "+1 440 974 7942",
    "sg:postcode": "44060",
    "sg:province": "OH",
    "wof:name": "Attention Grabbers",
    "wof:placetype": "venue"
  },
  "geometry": {"coordinates":[-81.372043,41.682832],"type":"Point"}
}
