{
  "type": "Feature",
  "properties": {
    "addr:full":"20 Fox Harbor Dr Troy OH 45373",
    "addr:housenumber":"20",
    "addr:postcode":"45373",
    "addr:street":"Fox Harbor Dr",
    "iso:country":"US",
    "sg:address":"20 Fox Harbor Dr",
    "sg:city":"Troy",
    "sg:classifiers":[
        {
            "category":"Wholesale",
            "subcategory":"Electrical",
            "type":"Manufacturing & Wholesale Goods"
        }
    ],
    "sg:phone":"+1 937 440 1779",
    "sg:postcode":"45373",
    "sg:province":"OH",
    "sg:tags":[
        "equipment"
    ],
    "wof:name":"Phillips Lighting",
    "wof:placetype":"venue"
},
  "geometry": {"coordinates":[-84.25580600000001,40.059404],"type":"Point"}
}