{
  "type": "Feature",
  "properties": {
    "addr:full": "3492 Leap Rd Hilliard OH 43026",
    "addr:housenumber": "3492",
    "addr:postcode": "43026",
    "addr:street": "Leap Rd",
    "iso:country": "US",
    "sg:address": "3492 Leap Rd",
    "sg:city": "Hilliard",
    "sg:classifiers": [
      {
        "category": "Retail",
        "subcategory": "Laundry \u0026 Dry Cleaning",
        "type": "Services"
      }
    ],
    "sg:phone": "+1 614 361 2218",
    "sg:postcode": "43026",
    "sg:province": "OH",
    "sg:tags": [
      "cleaners",
      "rug",
      "carpet"
    ],
    "wof:name": "Jet-N-Steam",
    "wof:placetype": "venue"
  },
  "geometry": {"coordinates":[-83.138779,40.024996],"type":"Point"}
}
