{
  "type": "Feature",
  "properties": {
    "iso:country":"US",
    "sg:address":"1280 Som Center Rd",
    "sg:city":"Cleveland",
    "sg:classifiers":[
        {
            "category":"Building & Trades",
            "subcategory":"Electrical",
            "type":"Services"
        }
    ],
    "sg:phone":"+1 216 579 8865",
    "sg:postcode":"44124",
    "sg:province":"OH",
    "sg:tags":[
        "electrical",
        "contractor"
    ],
    "wof:name":"Tri-County Electric",
    "wof:placetype":"venue"
},
  "geometry": {"coordinates":[-81.43875,41.525079],"type":"Point"}
}