{
  "type": "Feature",
  "properties": {
    "iso:country":"US",
    "sg:address":"86665 Flaherty Rd",
    "sg:city":"Scio",
    "sg:classifiers":[
        {
            "category":"Farming",
            "subcategory":"Livestock Farm",
            "type":"Manufacturing & Wholesale Goods"
        }
    ],
    "sg:phone":"+1 740 945 0266",
    "sg:postcode":"43988",
    "sg:province":"OH",
    "sg:tags":[
        "beef",
        "feedlot",
        "cattle"
    ],
    "wof:name":"Thomas Albaugh",
    "wof:placetype":"venue"
},
  "geometry": {"coordinates":[-81.09728699999999,40.349466],"type":"Point"}
}