{
  "type": "Feature",
  "properties": {
    "addr:full": "86665 Flaherty Rd Scio OH 43988",
    "addr:postcode": "86665;43988",
    "addr:street": "Flaherty Rd",
    "iso:country": "US",
    "sg:address": "86665 Flaherty Rd",
    "sg:city": "Scio",
    "sg:classifiers": [
      {
        "category": "Farming",
        "subcategory": "Livestock Farm",
        "type": "Manufacturing \u0026 Wholesale Goods"
      }
    ],
    "sg:phone": "+1 740 945 0266",
    "sg:postcode": "43988",
    "sg:province": "OH",
    "sg:tags": [
      "beef",
      "feedlot",
      "cattle"
    ],
    "wof:name": "Thomas Albaugh",
    "wof:placetype": "venue"
  },
  "geometry": {"coordinates":[-81.097287,40.349466],"type":"Point"}
}
