{
  "type": "Feature",
  "properties": {
    "addr:full": "3240 Wold Ave Cincinnati OH 45207",
    "addr:postcode": "3240;45207",
    "addr:street": "Wold Ave",
    "iso:country": "US",
    "sg:address": "3240 Wold Ave",
    "sg:city": "Cincinnati",
    "sg:classifiers": [
      {
        "category": "Building \u0026 Trades",
        "subcategory": "Cleaning \u0026 Sanitation",
        "type": "Services"
      }
    ],
    "sg:phone": "+1 513 784 9300",
    "sg:postcode": "45207",
    "sg:province": "OH",
    "sg:tags": [
      "janitor"
    ],
    "wof:name": "Simply Cleaning Plus",
    "wof:placetype": "venue"
  },
  "geometry": {"coordinates":[-84.468048,39.13711],"type":"Point"}
}
