{
  "type": "Feature",
  "properties": {
    "addr:full": "581 Mikes Ln Newark OH 43055",
    "addr:housenumber": "581",
    "addr:postcode": "43055",
    "addr:street": "Mikes Ln",
    "iso:country": "US",
    "sg:address": "581 Mikes Ln",
    "sg:city": "Newark",
    "sg:classifiers": [
      {
        "category": "Building \u0026 Trades",
        "subcategory": "Construction",
        "type": "Services"
      }
    ],
    "sg:phone": "+1 740 366 5669",
    "sg:postcode": "43055",
    "sg:province": "OH",
    "sg:tags": [
      "house",
      "contractor"
    ],
    "wof:name": "Jim Maier Builders Inc",
    "wof:placetype": "venue"
  },
  "geometry": {"coordinates":[-82.419425,40.072308],"type":"Point"}
}
