{
  "type": "Feature",
  "properties": {
    "addr:full":"4641 N State Rte 66 Defiance OH 43512",
    "addr:housenumber":"4641",
    "addr:postcode":"43512",
    "addr:street":"N State Rte 66",
    "iso:country":"US",
    "sg:address":"4641 N State Rte 66",
    "sg:city":"Defiance",
    "sg:phone":"+1 419 428 3203",
    "sg:postcode":"43512",
    "sg:province":"OH",
    "sg:tags":[
        "farm",
        "corn"
    ],
    "wof:name":"Barry Clark",
    "wof:placetype":"venue"
},
  "geometry": {"coordinates":[-84.360766,41.375061],"type":"Point"}
}