{
  "type": "Feature",
  "properties": {
    "addr:full": "150 W Coshocton St Johnstown OH 43031",
    "addr:housenumber": "150",
    "addr:postcode": "43031",
    "addr:street": "W Coshocton St",
    "iso:country": "US",
    "sg:address": "150 W Coshocton St",
    "sg:city": "Johnstown",
    "sg:classifiers": [
      {
        "category": "Building \u0026 Trades",
        "subcategory": "Construction",
        "type": "Services"
      }
    ],
    "sg:phone": "+1 740 392 1224",
    "sg:postcode": "43031",
    "sg:province": "OH",
    "sg:tags": [
      "house"
    ],
    "wof:name": "Ryan Builders",
    "wof:placetype": "venue"
  },
  "geometry": {"coordinates":[-82.687893,40.15207],"type":"Point"}
}
