{
  "type": "Feature",
  "properties": {
    "addr:full": "38150 Stagecoach Dr Scio OH 43988",
    "addr:housenumber": "38150",
    "addr:postcode": "43988",
    "addr:street": "Stagecoach Dr",
    "iso:country": "US",
    "sg:address": "38150 Stagecoach Dr",
    "sg:city": "Scio",
    "sg:classifiers": [
      {
        "category": "Professional",
        "subcategory": "Business Services",
        "type": "Services"
      }
    ],
    "sg:phone": "+1 740 945 8014",
    "sg:postcode": "43988",
    "sg:province": "OH",
    "sg:tags": [
      "auctioneer"
    ],
    "wof:name": "Scio Auction \u0026 Livestock Sales",
    "wof:placetype": "venue"
  },
  "geometry": {"coordinates":[-81.094963,40.405675],"type":"Point"}
}
