{
  "type": "Feature",
  "properties": {
    "addr:full":"2253 Central Dr Fairfield OH 45014",
    "addr:housenumber":"2253",
    "addr:postcode":"45014",
    "addr:street":"Central Dr",
    "iso:country":"US",
    "sg:address":"2253 Central Dr",
    "sg:city":"Fairfield",
    "sg:classifiers":[
        {
            "category":"Building & Trades",
            "subcategory":"Construction",
            "type":"Services"
        }
    ],
    "sg:phone":"+1 513 738 4414",
    "sg:postcode":"45014",
    "sg:province":"OH",
    "sg:tags":[
        "house"
    ],
    "wof:name":"Luther and Meyer Homes",
    "wof:placetype":"venue"
},
  "geometry": {"coordinates":[-84.641153,39.313905],"type":"Point"}
}