{
  "type": "Feature",
  "properties": {
    "iso:country":"US",
    "sg:address":"15723 Madison Ave",
    "sg:city":"Cleveland",
    "sg:classifiers":[
        {
            "category":"Shopping",
            "type":"Retail Goods"
        }
    ],
    "sg:phone":"+1 216 221 1327",
    "sg:postcode":"44107",
    "sg:province":"OH",
    "sg:tags":[
        "picture",
        "frame"
    ],
    "wof:name":"Custom Picture Framing",
    "wof:placetype":"venue"
},
  "geometry": {"coordinates":[-81.808515,41.477091],"type":"Point"}
}