{
  "type": "Feature",
  "properties": {
    "iso:country":"US",
    "sg:address":"1600 Middle Ave",
    "sg:city":"Elyria",
    "sg:classifiers":[
        {
            "category":"Insurance",
            "subcategory":"Insurance Agent",
            "type":"Services"
        }
    ],
    "sg:phone":"+1 440 322 1268",
    "sg:postcode":"44035",
    "sg:province":"OH",
    "wof:name":"Creative Incntves Insur Netwrk",
    "wof:placetype":"venue"
},
  "geometry": {"coordinates":[-82.107466,41.351085],"type":"Point"}
}