{
  "type": "Feature",
  "properties": {
    "addr:full": "6724 Perimeter Loop Rd Dublin OH 43017",
    "addr:housenumber": "6724",
    "addr:postcode": "43017",
    "addr:street": "Perimeter Loop Rd",
    "iso:country": "US",
    "sg:address": "6724 Perimeter Loop Rd",
    "sg:city": "Dublin",
    "sg:classifiers": [
      {
        "category": "Professional",
        "subcategory": "Management \u0026 Consulting",
        "type": "Services"
      }
    ],
    "sg:phone": "+1 614 760 0190",
    "sg:postcode": "43017",
    "sg:province": "OH",
    "sg:tags": [
      "public",
      "relations"
    ],
    "wof:name": "Communication Consultants G",
    "wof:placetype": "venue"
  },
  "geometry": {"coordinates":[-83.157758,40.102314],"type":"Point"}
}
