{
  "type": "Feature",
  "properties": {
    "iso:country":"US",
    "sg:address":"6724 Perimeter Loop Rd",
    "sg:city":"Dublin",
    "sg:classifiers":[
        {
            "category":"Professional",
            "subcategory":"Management & Consulting",
            "type":"Services"
        }
    ],
    "sg:phone":"+1 614 760 0190",
    "sg:postcode":"43017",
    "sg:province":"OH",
    "sg:tags":[
        "public",
        "relations"
    ],
    "wof:name":"Communication Consultants G",
    "wof:placetype":"venue"
},
  "geometry": {"coordinates":[-83.157758,40.102314],"type":"Point"}
}