{
  "type": "Feature",
  "properties": {
    "iso:country":"US",
    "sg:address":"7447 Rd 87",
    "sg:city":"Paulding",
    "sg:phone":"+1 419 399 5867",
    "sg:postcode":"45879",
    "sg:province":"OH",
    "sg:tags":[
        "gas"
    ],
    "wof:name":"Briceton Gas Svc",
    "wof:placetype":"venue"
},
  "geometry": {"coordinates":[-84.631266,41.077637],"type":"Point"}
}