{
  "type": "Feature",
  "properties": {
    "addr:full":"317 S Locust St Edgerton OH 43517",
    "addr:housenumber":"317",
    "addr:postcode":"43517",
    "addr:street":"S Locust St",
    "iso:country":"US",
    "sg:address":"317 S Locust St",
    "sg:city":"Edgerton",
    "sg:classifiers":[
        {
            "category":"Organizations",
            "subcategory":"Religious Organization",
            "type":"Services"
        }
    ],
    "sg:phone":"+1 419 298 2540",
    "sg:postcode":"43517",
    "sg:province":"OH",
    "sg:tags":[
        "church"
    ],
    "wof:name":"St Mary's Catholic Church",
    "wof:placetype":"venue"
},
  "geometry": {"coordinates":[-84.749242,41.446207],"type":"Point"}
}