{
  "type": "Feature",
  "properties": {
    "addr:full":"2062 Integrity Dr S Columbus OH 43209",
    "addr:housenumber":"2062",
    "addr:postcode":"43209",
    "addr:street":"Integrity Dr S",
    "iso:country":"US",
    "sg:address":"2062 Integrity Dr S",
    "sg:city":"Columbus",
    "sg:classifiers":[
        {
            "category":"Manufacturing",
            "subcategory":"Textiles",
            "type":"Manufacturing & Wholesale Goods"
        }
    ],
    "sg:phone":"+1 614 443 6161",
    "sg:postcode":"43209",
    "sg:province":"OH",
    "sg:tags":[
        "mfg"
    ],
    "wof:name":"Carpet Arts Unlimited",
    "wof:placetype":"venue"
},
  "geometry": {"coordinates":[-82.94126199999999,39.933686],"type":"Point"}
}