{
  "type": "Feature",
  "properties": {
    "iso:country":"US",
    "sg:address":"104 S Lincoln St",
    "sg:city":"Kent",
    "sg:classifiers":[
        {
            "category":"Shopping",
            "subcategory":"Music",
            "type":"Retail Goods"
        }
    ],
    "sg:phone":"+1 330 673 4470",
    "sg:postcode":"44240",
    "sg:province":"OH",
    "sg:tags":[
        "compact",
        "record",
        "disc",
        "tape"
    ],
    "wof:name":"Exchange",
    "wof:placetype":"venue"
},
  "geometry": {"coordinates":[-81.35133399999999,41.152446],"type":"Point"}
}