{
  "type": "Feature",
  "properties": {
    "addr:full": "4368 Dressler Rd NW Canton OH 44718",
    "addr:housenumber": "4368",
    "addr:postcode": "44718",
    "addr:street": "Dressler Rd Nw",
    "iso:country": "US",
    "sg:address": "4368 Dressler Rd NW",
    "sg:city": "Canton",
    "sg:classifiers": [
      {
        "category": "Banks \u0026 Credit Unions",
        "subcategory": "Bank",
        "type": "Services"
      }
    ],
    "sg:phone": "+1 330 491 0101",
    "sg:postcode": "44718",
    "sg:province": "OH",
    "sg:tags": [
      "mortgage",
      "loan",
      "banker",
      "real estate"
    ],
    "sg:website": "www.fidelitycommercemortgage.com",
    "wof:name": "Fidelity Commerce Mortgage",
    "wof:placetype": "venue"
  },
  "geometry": {"coordinates":[-81.434764,40.844236],"type":"Point"}
}
