{
  "type": "Feature",
  "properties": {
    "addr:full": "37115 Code Ave Willoughby OH 44094",
    "addr:postcode": "37115;44094",
    "addr:street": "Code Ave",
    "iso:country": "US",
    "sg:address": "37115 Code Ave",
    "sg:city": "Willoughby",
    "sg:classifiers": [
      {
        "category": "Building \u0026 Trades",
        "subcategory": "Landscaping Services",
        "type": "Services"
      }
    ],
    "sg:phone": "+1 440 942 3444",
    "sg:postcode": "44094",
    "sg:province": "OH",
    "wof:name": "M J Lanese Landscaping Inc",
    "wof:placetype": "venue"
  },
  "geometry": {"coordinates":[-81.418351,41.644292],"type":"Point"}
}
