{
  "type": "Feature",
  "properties": {
    "addr:full":"5265 Leydorf Ln Westerville OH 43082",
    "addr:housenumber":"5265",
    "addr:postcode":"43082",
    "addr:street":"Leydorf Ln",
    "iso:country":"US",
    "sg:address":"5265 Leydorf Ln",
    "sg:city":"Westerville",
    "sg:classifiers":[
        {
            "category":"Home & Garden",
            "subcategory":"Furniture",
            "type":"Retail Goods"
        }
    ],
    "sg:phone":"+1 740 965 2322",
    "sg:postcode":"43082",
    "sg:province":"OH",
    "sg:tags":[
        "equipment",
        "kitchen",
        "cabinet"
    ],
    "wof:name":"Kitchen & Bath Specialist Inc",
    "wof:placetype":"venue"
},
  "geometry": {"coordinates":[-82.943056,40.181044],"type":"Point"}
}