{
  "type": "Feature",
  "properties": {
    "iso:country":"US",
    "sg:address":"430 W Ervin Rd",
    "sg:city":"Van Wert",
    "sg:classifiers":[
        {
            "category":"Sports & Exercise",
            "subcategory":"Bowling",
            "type":"Entertainment"
        }
    ],
    "sg:phone":"+1 419 232 2695",
    "sg:postcode":"45891",
    "sg:province":"OH",
    "sg:tags":[
        "center"
    ],
    "wof:name":"Olympic Lanes",
    "wof:placetype":"venue"
},
  "geometry": {"coordinates":[-84.589168,40.858815],"type":"Point"}
}