{
  "type": "Feature",
  "properties": {
    "addr:full": "430 W Ervin Rd Van Wert OH 45891",
    "addr:housenumber": "430",
    "addr:postcode": "45891",
    "addr:street": "W Ervin Rd",
    "iso:country": "US",
    "sg:address": "430 W Ervin Rd",
    "sg:city": "Van Wert",
    "sg:classifiers": [
      {
        "category": "Sports \u0026 Exercise",
        "subcategory": "Bowling",
        "type": "Entertainment"
      }
    ],
    "sg:phone": "+1 419 232 2695",
    "sg:postcode": "45891",
    "sg:province": "OH",
    "sg:tags": [
      "center"
    ],
    "wof:name": "Olympic Lanes",
    "wof:placetype": "venue"
  },
  "geometry": {"coordinates":[-84.589168,40.858815],"type":"Point"}
}
