{
  "type": "Feature",
  "properties": {
    "iso:country":"US",
    "sg:address":"1326 Michigan St",
    "sg:city":"Sidney",
    "sg:classifiers":[
        {
            "category":"Restaurant",
            "type":"Food & Drink"
        }
    ],
    "sg:phone":"+1 937 492 5696",
    "sg:postcode":"45365",
    "sg:province":"OH",
    "wof:name":"Wendy's",
    "wof:placetype":"venue"
},
  "geometry": {"coordinates":[-84.174875,40.287829],"type":"Point"}
}