{
  "type": "Feature",
  "properties": {
    "addr:full": "1326 Michigan St Sidney OH 45365",
    "addr:housenumber": "1326",
    "addr:postcode": "45365",
    "addr:street": "Michigan St",
    "iso:country": "US",
    "sg:address": "1326 Michigan St",
    "sg:city": "Sidney",
    "sg:classifiers": [
      {
        "category": "Restaurant",
        "type": "Food \u0026 Drink"
      }
    ],
    "sg:phone": "+1 937 492 5696",
    "sg:postcode": "45365",
    "sg:province": "OH",
    "wof:name": "Wendy's",
    "wof:placetype": "venue"
  },
  "geometry": {"coordinates":[-84.174875,40.287829],"type":"Point"}
}
