{
  "type": "Feature",
  "properties": {
    "addr:full":"5020 Whipple Ave NW Canton OH 44718",
    "addr:housenumber":"5020",
    "addr:postcode":"44718",
    "addr:street":"Whipple Ave Nw",
    "iso:country":"US",
    "sg:address":"5020 Whipple Ave NW",
    "sg:city":"Canton",
    "sg:classifiers":[
        {
            "category":"Autos & Motor Vehicles",
            "subcategory":"Automobile Sales",
            "type":"Retail Goods"
        }
    ],
    "sg:phone":"+1 330 493 2500",
    "sg:postcode":"44718",
    "sg:province":"OH",
    "sg:tags":[
        "car",
        "dealer"
    ],
    "wof:name":"Enterprise Car Sales",
    "wof:placetype":"venue"
},
  "geometry": {"coordinates":[-81.422865,40.854804],"type":"Point"}
}