{
  "type": "Feature",
  "properties": {
    "addr:full":"2536 Dixie Hwy Hamilton OH 45015",
    "addr:housenumber":"2536",
    "addr:postcode":"45015",
    "addr:street":"Dixie Hwy",
    "iso:country":"US",
    "sg:address":"2536 Dixie Hwy",
    "sg:city":"Hamilton",
    "sg:classifiers":[
        {
            "category":"Restaurant",
            "type":"Food & Drink"
        }
    ],
    "sg:phone":"+1 513 856 8555",
    "sg:postcode":"45015",
    "sg:province":"OH",
    "wof:name":"Happy Garden Buffet",
    "wof:placetype":"venue"
},
  "geometry": {"coordinates":[-84.547746,39.370339],"type":"Point"}
}