{
  "type": "Feature",
  "properties": {
    "iso:country":"US",
    "sg:address":"1131 State Rte 72",
    "sg:city":"Jamestown",
    "sg:classifiers":[
        {
            "category":"Freight",
            "type":"Transportation"
        }
    ],
    "sg:phone":"+1 937 675 7185",
    "sg:postcode":"45335",
    "sg:province":"OH",
    "sg:tags":[
        "consultant"
    ],
    "wof:name":"Debbie Clark",
    "wof:placetype":"venue"
},
  "geometry": {"coordinates":[-83.73024700000001,39.640594],"type":"Point"}
}