{
  "type": "Feature",
  "properties": {
    "addr:full":"11860 State Rte 56 SE Mount Sterling OH 43143",
    "addr:housenumber":"11860",
    "addr:postcode":"43143",
    "addr:street":"State Rte 56 Se",
    "iso:country":"US",
    "sg:address":"11860 State Rte 56 SE",
    "sg:city":"Mount Sterling",
    "sg:phone":"+1 740 869 4299",
    "sg:postcode":"43143",
    "sg:province":"OH",
    "sg:tags":[
        "farm",
        "corn",
        "wheat",
        "soybean"
    ],
    "wof:name":"Sam Junk",
    "wof:placetype":"venue"
},
  "geometry": {"coordinates":[-83.310433,39.764055],"type":"Point"}
}