{
  "type": "Feature",
  "properties": {
    "addr:full": "1245 Monroe St NW New Philadelphia OH 44663",
    "addr:housenumber": "1245",
    "addr:postcode": "44663",
    "addr:street": "Monroe St Nw New Philadelphia",
    "iso:country": "US",
    "sg:address": "1245 Monroe St NW",
    "sg:city": "New Philadelphia",
    "sg:classifiers": [
      {
        "category": "Restaurant",
        "type": "Food \u0026 Drink"
      }
    ],
    "sg:phone": "+1 330 364 9221",
    "sg:postcode": "44663",
    "sg:province": "OH",
    "sg:tags": [
      "eating"
    ],
    "wof:name": "Dee's Restaurant",
    "wof:placetype": "venue"
  },
  "geometry": {"coordinates":[-81.456696,40.505431],"type":"Point"}
}
