{
  "type": "Feature",
  "properties": {
    "addr:full": "9915 Springfield Pike Cincinnati OH 45215",
    "addr:housenumber": "9915",
    "addr:postcode": "45215",
    "addr:street": "Springfield Pike",
    "iso:country": "US",
    "sg:address": "9915 Springfield Pike",
    "sg:city": "Cincinnati",
    "sg:classifiers": [
      {
        "category": "Utilities",
        "subcategory": "Cable",
        "type": "Services"
      }
    ],
    "sg:phone": "+1 513 771 5844",
    "sg:postcode": "45215",
    "sg:province": "OH",
    "sg:tags": [
      "television"
    ],
    "wof:name": "Novner TV Satellite Systems",
    "wof:placetype": "venue"
  },
  "geometry": {"coordinates":[-84.470993,39.245168],"type":"Point"}
}
