{
  "type": "Feature",
  "properties": {
    "addr:full":"971 Homewood Ave SE Warren OH 44484",
    "addr:housenumber":"971",
    "addr:postcode":"44484",
    "addr:street":"Homewood Ave Se",
    "iso:country":"US",
    "sg:address":"971 Homewood Ave SE",
    "sg:city":"Warren",
    "sg:classifiers":[
        {
            "category":"Building & Trades",
            "subcategory":"Construction",
            "type":"Services"
        }
    ],
    "sg:phone":"+1 330 856 4729",
    "sg:postcode":"44484",
    "sg:province":"OH",
    "sg:tags":[
        "window",
        "siding",
        "deck"
    ],
    "wof:name":"Emerald Builders Inc",
    "wof:placetype":"venue"
},
  "geometry": {"coordinates":[-80.798811,41.226373],"type":"Point"}
}