{
  "type": "Feature",
  "properties": {
    "addr:full": "1971 Cedarville Rd Goshen OH 45122",
    "addr:housenumber": "1971",
    "addr:postcode": "45122",
    "addr:street": "Cedarville Rd",
    "iso:country": "US",
    "sg:address": "1971 Cedarville Rd",
    "sg:city": "Goshen",
    "sg:classifiers": [
      {
        "category": "Building \u0026 Trades",
        "subcategory": "Construction",
        "type": "Services"
      }
    ],
    "sg:phone": "+1 513 625 2700",
    "sg:postcode": "45122",
    "sg:province": "OH",
    "sg:tags": [
      "fence",
      "contractor"
    ],
    "wof:name": "Reliable Fence",
    "wof:placetype": "venue"
  },
  "geometry": {"coordinates":[-84.151521,39.187135],"type":"Point"}
}
