{
  "type": "Feature",
  "properties": {
    "iso:country":"US",
    "sg:address":"119 E Twp Rd 28",
    "sg:city":"Tiffin",
    "sg:classifiers":[
        {
            "category":"Building & Trades",
            "subcategory":"Landscaping Services",
            "type":"Services"
        }
    ],
    "sg:phone":"+1 419 397 2636",
    "sg:postcode":"44883",
    "sg:province":"OH",
    "sg:tags":[
        "seasonal",
        "store",
        "contractor"
    ],
    "wof:name":"OLD Seed Shed",
    "wof:placetype":"venue"
},
  "geometry": {"coordinates":[-83.167379,41.014981],"type":"Point"}
}