{
  "type": "Feature",
  "properties": {
    "addr:full": "15967 E High St Middlefield OH 44062",
    "addr:housenumber": "15967",
    "addr:postcode": "44062",
    "addr:street": "E High St",
    "iso:country": "US",
    "sg:address": "15967 E High St",
    "sg:city": "Middlefield",
    "sg:classifiers": [
      {
        "category": "Retail",
        "subcategory": "Veterinary Services",
        "type": "Services"
      }
    ],
    "sg:phone": "+1 440 632 9181",
    "sg:postcode": "44062",
    "sg:province": "OH",
    "sg:tags": [
      "veterinarian"
    ],
    "wof:name": "Middlefield Veterinary Clinic",
    "wof:placetype": "venue"
  },
  "geometry": {"coordinates":[-81.071476,41.461841],"type":"Point"}
}
