{
  "type": "Feature",
  "properties": {
    "iso:country":"US",
    "sg:address":"3584 Vine St",
    "sg:city":"Cincinnati",
    "sg:classifiers":[
        {
            "category":"Building & Trades",
            "subcategory":"Construction",
            "type":"Services"
        }
    ],
    "sg:phone":"+1 513 751 0220",
    "sg:postcode":"45220",
    "sg:province":"OH",
    "sg:tags":[
        "hanging",
        "contractor"
    ],
    "wof:name":"G L Christmon Custom Painting",
    "wof:placetype":"venue"
},
  "geometry": {"coordinates":[-84.512075,39.14836],"type":"Point"}
}