{
  "type": "Feature",
  "properties": {
    "addr:full": "3584 Vine St Cincinnati OH 45220",
    "addr:housenumber": "3584",
    "addr:postcode": "45220",
    "addr:street": "Vine St",
    "iso:country": "US",
    "sg:address": "3584 Vine St",
    "sg:city": "Cincinnati",
    "sg:classifiers": [
      {
        "category": "Building \u0026 Trades",
        "subcategory": "Construction",
        "type": "Services"
      }
    ],
    "sg:phone": "+1 513 751 0220",
    "sg:postcode": "45220",
    "sg:province": "OH",
    "sg:tags": [
      "hanging",
      "contractor"
    ],
    "wof:name": "G L Christmon Custom Painting",
    "wof:placetype": "venue"
  },
  "geometry": {"coordinates":[-84.512075,39.14836],"type":"Point"}
}
