{
  "type": "Feature",
  "properties": {
    "addr:full": "6780 Mayfield Rd Cleveland OH 44124",
    "addr:housenumber": "6780",
    "addr:postcode": "44124",
    "addr:street": "Mayfield Rd",
    "iso:country": "US",
    "sg:address": "6780 Mayfield Rd",
    "sg:city": "Cleveland",
    "sg:classifiers": [
      {
        "category": "Health Services",
        "subcategory": "Doctor",
        "type": "Services"
      }
    ],
    "sg:phone": "+1 440 312 8090",
    "sg:postcode": "44124",
    "sg:province": "OH",
    "sg:tags": [
      "physician",
      "surgeon"
    ],
    "wof:name": "Sleep Disorders Ctr-Hillcrest",
    "wof:placetype": "venue"
  },
  "geometry": {"coordinates":[-81.434881,41.520028],"type":"Point"}
}
