{
  "type": "Feature",
  "properties": {
    "addr:full": "228 Stonehaven Rd Kettering OH 45429",
    "addr:housenumber": "228",
    "addr:postcode": "45429",
    "addr:street": "Stonehaven Rd",
    "iso:country": "US",
    "sg:address": "228 Stonehaven Rd",
    "sg:city": "Kettering",
    "sg:classifiers": [
      {
        "category": "Professional",
        "subcategory": "Lawyer \u0026 Legal Services",
        "type": "Services"
      }
    ],
    "sg:phone": "+1 937 293 2200",
    "sg:postcode": "45429",
    "sg:province": "OH",
    "sg:tags": [
      "attorney"
    ],
    "wof:name": "William R Coen Co Lpa",
    "wof:placetype": "venue"
  },
  "geometry": {"coordinates":[-84.174922,39.690921],"type":"Point"}
}
