{
  "type": "Feature",
  "properties": {
    "addr:full": "119 W Washington St Ashland OH 44805",
    "addr:housenumber": "119",
    "addr:postcode": "44805",
    "addr:street": "W Washington St",
    "iso:country": "US",
    "sg:address": "119 W Washington St",
    "sg:city": "Ashland",
    "sg:classifiers": [
      {
        "category": "Insurance",
        "subcategory": "Insurance Agent",
        "type": "Services"
      }
    ],
    "sg:phone": "+1 419 289 8441",
    "sg:postcode": "44805",
    "sg:province": "OH",
    "wof:name": "Conklin-Hall Insurance Svcs",
    "wof:placetype": "venue"
  },
  "geometry": {"coordinates":[-82.314417,40.866334],"type":"Point"}
}
