{
  "type": "Feature",
  "properties": {
    "addr:full": "8045 Dawnwood Ave NE Middlebranch OH 44652",
    "addr:postcode": "8045;44652",
    "addr:street": "Dawnwood Ave Ne",
    "iso:country": "US",
    "sg:address": "8045 Dawnwood Ave NE",
    "sg:city": "Middlebranch",
    "sg:classifiers": [
      {
        "category": "Manufacturing",
        "subcategory": "Rubber \u0026 Plastics",
        "type": "Manufacturing \u0026 Wholesale Goods"
      }
    ],
    "sg:phone": "+1 330 966 7600",
    "sg:postcode": "44652",
    "sg:province": "OH",
    "sg:tags": [
      "producer"
    ],
    "wof:name": "Interface Laminating",
    "wof:placetype": "venue"
  },
  "geometry": {"coordinates":[-81.324543,40.896629],"type":"Point"}
}
