{
  "type": "Feature",
  "properties": {
    "iso:country":"US",
    "sg:address":"3300 Mount Carmel Rd",
    "sg:city":"Cincinnati",
    "sg:classifiers":[
        {
            "category":"Health Services",
            "subcategory":"Chiropractor",
            "type":"Services"
        }
    ],
    "sg:phone":"+1 513 474 5044",
    "sg:postcode":"45244",
    "sg:province":"OH",
    "wof:name":"Beechmont Chiropractic",
    "wof:placetype":"venue"
},
  "geometry": {"coordinates":[-84.30718400000001,39.115546],"type":"Point"}
}