{
  "type": "Feature",
  "properties": {
    "iso:country":"US",
    "sg:address":"82 Henry St",
    "sg:city":"Ostrander",
    "sg:classifiers":[
        {
            "category":"Retail",
            "subcategory":"Auto Repair",
            "type":"Services"
        }
    ],
    "sg:phone":"+1 740 666 1244",
    "sg:postcode":"43061",
    "sg:province":"OH",
    "sg:tags":[
        "exchanging",
        "engine"
    ],
    "wof:name":"Automotive Head Svc & Machine",
    "wof:placetype":"venue"
},
  "geometry": {"coordinates":[-83.214299,40.264423],"type":"Point"}
}