{
  "type": "Feature",
  "properties": {
    "addr:full":"555 N Hyatt St Tipp City OH 45371",
    "addr:housenumber":"555",
    "addr:postcode":"45371",
    "addr:street":"N Hyatt St",
    "iso:country":"US",
    "sg:address":"555 N Hyatt St",
    "sg:city":"Tipp City",
    "sg:classifiers":[
        {
            "category":"Government",
            "subcategory":"Office",
            "type":"Public Place"
        }
    ],
    "sg:phone":"+1 937 667 8115",
    "sg:postcode":"45371",
    "sg:province":"OH",
    "sg:tags":[
        "city"
    ],
    "wof:name":"Tipp City Schls Bus Garage",
    "wof:placetype":"venue"
},
  "geometry": {"coordinates":[-84.18194699999999,39.969136],"type":"Point"}
}