{
  "type": "Feature",
  "properties": {
    "iso:country":"US",
    "sg:address":"200 Stanford Pkwy",
    "sg:city":"Findlay",
    "sg:classifiers":[
        {
            "category":"Wholesale",
            "subcategory":"Beer",
            "type":"Manufacturing & Wholesale Goods"
        }
    ],
    "sg:phone":"+1 419 423 1013",
    "sg:postcode":"45840",
    "sg:province":"OH",
    "sg:tags":[
        "wholesaler"
    ],
    "wof:name":"Acme Beverage Inc",
    "wof:placetype":"venue"
},
  "geometry": {"coordinates":[-83.675619,41.050723],"type":"Point"}
}