{
  "type": "Feature",
  "properties": {
    "addr:full": "4530 Eastgate Blvd Cincinnati OH 45245",
    "addr:housenumber": "4530",
    "addr:postcode": "45245",
    "addr:street": "Eastgate Blvd",
    "iso:country": "US",
    "sg:address": "4530 Eastgate Blvd",
    "sg:city": "Cincinnati",
    "sg:classifiers": [
      {
        "category": "Banks \u0026 Credit Unions",
        "subcategory": "Bank",
        "type": "Services"
      }
    ],
    "sg:phone": "+1 513 753 2600",
    "sg:postcode": "45245",
    "sg:province": "OH",
    "sg:tags": [
      "state",
      "commercial"
    ],
    "wof:name": "Fifth Third Bank",
    "wof:placetype": "venue"
  },
  "geometry": {"coordinates":[-84.274215,39.098449],"type":"Point"}
}
