{
  "type": "Feature",
  "properties": {
    "iso:country":"US",
    "sg:address":"3314 South Ave",
    "sg:city":"Youngstown",
    "sg:classifiers":[
        {
            "category":"Shopping",
            "subcategory":"Used Merchandise",
            "type":"Retail Goods"
        }
    ],
    "sg:phone":"+1 330 788 5185",
    "sg:postcode":"44502",
    "sg:province":"OH",
    "wof:name":"AKD Pawn",
    "wof:placetype":"venue"
},
  "geometry": {"coordinates":[-80.646215,41.065381],"type":"Point"}
}