{
  "type": "Feature",
  "properties": {
    "addr:full": "3314 South Ave Youngstown OH 44502",
    "addr:housenumber": "3314",
    "addr:postcode": "44502",
    "addr:street": "South Ave",
    "iso:country": "US",
    "sg:address": "3314 South Ave",
    "sg:city": "Youngstown",
    "sg:classifiers": [
      {
        "category": "Shopping",
        "subcategory": "Used Merchandise",
        "type": "Retail Goods"
      }
    ],
    "sg:phone": "+1 330 788 5185",
    "sg:postcode": "44502",
    "sg:province": "OH",
    "wof:name": "AKD Pawn",
    "wof:placetype": "venue"
  },
  "geometry": {"coordinates":[-80.646215,41.065381],"type":"Point"}
}
