{
  "type": "Feature",
  "properties": {
    "iso:country":"US",
    "sg:address":"381 Wayne St",
    "sg:city":"Mansfield",
    "sg:classifiers":[
        {
            "category":"Shopping",
            "subcategory":"Computers & Home Electronics",
            "type":"Retail Goods"
        }
    ],
    "sg:phone":"+1 419 525 7272",
    "sg:postcode":"44902",
    "sg:province":"OH",
    "sg:tags":[
        "audio"
    ],
    "wof:name":"Spots Audio & Accessories",
    "wof:placetype":"venue"
},
  "geometry": {"coordinates":[-82.506546,40.768436],"type":"Point"}
}