{
  "type": "Feature",
  "properties": {
    "addr:full":"50 E Main St Salineville OH 43945",
    "addr:housenumber":"50",
    "addr:postcode":"43945",
    "addr:street":"E Main St",
    "iso:country":"US",
    "sg:address":"50 E Main St",
    "sg:city":"Salineville",
    "sg:classifiers":[
        {
            "category":"Real Estate",
            "subcategory":"Real Estate Services",
            "type":"Services"
        },
        {
            "category":"Banks & Credit Unions",
            "subcategory":"Bank",
            "type":"Services"
        },
        {
            "category":"Banks & Credit Unions",
            "subcategory":"Financial Services",
            "type":"Services"
        }
    ],
    "sg:phone":"+1 330 679 2311",
    "sg:postcode":"43945",
    "sg:province":"OH",
    "sg:tags":[
        "commercial",
        "loan",
        "saving",
        "mortgage"
    ],
    "wof:name":"Sky Bank",
    "wof:placetype":"venue"
},
  "geometry": {"coordinates":[-80.831339,40.623974],"type":"Point"}
}