{
  "type": "Feature",
  "properties": {
    "addr:full": "19 N Canal St Newton Falls OH 44444",
    "addr:housenumber": "19",
    "addr:postcode": "44444",
    "addr:street": "N Canal St",
    "iso:country": "US",
    "sg:address": "19 N Canal St",
    "sg:city": "Newton Falls",
    "sg:classifiers": [
      {
        "category": "Government",
        "subcategory": "Court House",
        "type": "Public Place"
      }
    ],
    "sg:phone": "+1 330 872 0302",
    "sg:postcode": "44444",
    "sg:province": "OH",
    "wof:name": "Newton Falls Muncpl Crt Trmbll",
    "wof:placetype": "venue"
  },
  "geometry": {"coordinates":[-80.977756,41.188474],"type":"Point"}
}
