{
  "type": "Feature",
  "properties": {
    "addr:full": "3001 Harris Ave Cincinnati OH 45212",
    "addr:housenumber": "3001",
    "addr:postcode": "45212",
    "addr:street": "Harris Ave",
    "iso:country": "US",
    "sg:address": "3001 Harris Ave",
    "sg:city": "Cincinnati",
    "sg:classifiers": [
      {
        "category": "Building \u0026 Trades",
        "subcategory": "Construction",
        "type": "Services"
      }
    ],
    "sg:phone": "+1 513 458 4615",
    "sg:postcode": "45212",
    "sg:province": "OH",
    "sg:tags": [
      "marking",
      "maintenance",
      "parking"
    ],
    "wof:name": "Norwood Public Works Dept",
    "wof:placetype": "venue"
  },
  "geometry": {"coordinates":[-84.437966,39.161598],"type":"Point"}
}
