{
  "type": "Feature",
  "properties": {
    "addr:full":"7331 Pleasant Plains Rd Clayton OH 45315",
    "addr:housenumber":"7331",
    "addr:postcode":"45315",
    "addr:street":"Pleasant Plains Rd",
    "iso:country":"US",
    "sg:address":"7331 Pleasant Plains Rd",
    "sg:city":"Clayton",
    "sg:classifiers":[
        {
            "category":"Recreation",
            "type":"Entertainment"
        }
    ],
    "sg:phone":"+1 937 836 1474",
    "sg:postcode":"45315",
    "sg:province":"OH",
    "sg:tags":[
        "pool",
        "swimming"
    ],
    "wof:name":"Melody Pool",
    "wof:placetype":"venue"
},
  "geometry": {"coordinates":[-84.38754400000001,39.860985],"type":"Point"}
}