{
  "type": "Feature",
  "properties": {
    "iso:country":"US",
    "sg:address":"1030 Marion Avenue Rd N",
    "sg:city":"Mansfield",
    "sg:classifiers":[
        {
            "category":"Farming",
            "subcategory":"Dairy Farm",
            "type":"Manufacturing & Wholesale Goods"
        }
    ],
    "sg:phone":"+1 419 756 2571",
    "sg:postcode":"44903",
    "sg:province":"OH",
    "wof:name":"Raemelton Dairy Farm",
    "wof:placetype":"venue"
},
  "geometry": {"coordinates":[-82.635369,40.728416],"type":"Point"}
}