{
  "type": "Feature",
  "properties": {
    "addr:full": "1030 Marion Avenue Rd N Mansfield OH 44903",
    "addr:housenumber": "1030",
    "addr:postcode": "44903",
    "addr:street": "Marion Avenue Rd N",
    "iso:country": "US",
    "sg:address": "1030 Marion Avenue Rd N",
    "sg:city": "Mansfield",
    "sg:classifiers": [
      {
        "category": "Farming",
        "subcategory": "Dairy Farm",
        "type": "Manufacturing \u0026 Wholesale Goods"
      }
    ],
    "sg:phone": "+1 419 756 2571",
    "sg:postcode": "44903",
    "sg:province": "OH",
    "wof:name": "Raemelton Dairy Farm",
    "wof:placetype": "venue"
  },
  "geometry": {"coordinates":[-82.635369,40.728416],"type":"Point"}
}
