{
  "type": "Feature",
  "properties": {
    "addr:full":"11318 Proctor Ct Cleveland OH 44105",
    "addr:housenumber":"11318",
    "addr:postcode":"44105",
    "addr:street":"Proctor Ct",
    "iso:country":"US",
    "sg:address":"11318 Proctor Ct",
    "sg:city":"Cleveland",
    "sg:classifiers":[
        {
            "category":"Social Services",
            "subcategory":"Child Care",
            "type":"Services"
        }
    ],
    "sg:phone":"+1 216 883 4078",
    "sg:postcode":"44105",
    "sg:province":"OH",
    "wof:name":"Callie's Kiddies",
    "wof:placetype":"venue"
},
  "geometry": {"coordinates":[-81.604102,41.444286],"type":"Point"}
}