{
  "type": "Feature",
  "properties": {
    "addr:full": "1738 11th St Portsmouth OH 45662",
    "addr:housenumber": "1738",
    "addr:postcode": "45662",
    "addr:street": "11Th St",
    "iso:country": "US",
    "sg:address": "1738 11th St",
    "sg:city": "Portsmouth",
    "sg:classifiers": [
      {
        "category": "Building \u0026 Trades",
        "subcategory": "Landscaping Services",
        "type": "Services"
      }
    ],
    "sg:phone": "+1 740 354 5296",
    "sg:postcode": "45662",
    "sg:province": "OH",
    "wof:name": "Lawn Barber",
    "wof:placetype": "venue"
  },
  "geometry": {"coordinates":[-82.980304,38.738749],"type":"Point"}
}
