{
  "type": "Feature",
  "properties": {
    "iso:country":"US",
    "sg:address":"775 Hedgerow Ave",
    "sg:city":"Cincinnati",
    "sg:classifiers":[
        {
            "category":"Home & Garden",
            "subcategory":"Furniture",
            "type":"Retail Goods"
        }
    ],
    "sg:phone":"+1 513 772 5805",
    "sg:postcode":"45246",
    "sg:province":"OH",
    "wof:name":"GK Associates Inc",
    "wof:placetype":"venue"
},
  "geometry": {"coordinates":[-84.45614,39.265357],"type":"Point"}
}