{
  "type": "Feature",
  "properties": {
    "addr:full": "775 Hedgerow Ave Cincinnati OH 45246",
    "addr:housenumber": "775",
    "addr:postcode": "45246",
    "addr:street": "Hedgerow Ave",
    "iso:country": "US",
    "sg:address": "775 Hedgerow Ave",
    "sg:city": "Cincinnati",
    "sg:classifiers": [
      {
        "category": "Home \u0026 Garden",
        "subcategory": "Furniture",
        "type": "Retail Goods"
      }
    ],
    "sg:phone": "+1 513 772 5805",
    "sg:postcode": "45246",
    "sg:province": "OH",
    "wof:name": "GK Associates Inc",
    "wof:placetype": "venue"
  },
  "geometry": {"coordinates":[-84.45614,39.265357],"type":"Point"}
}
