{
  "type": "Feature",
  "properties": {
    "iso:country":"US",
    "sg:address":"884 W Mehring Way",
    "sg:city":"Cincinnati",
    "sg:classifiers":[
        {
            "category":"Manufacturing",
            "subcategory":"Glass & Minerals",
            "type":"Manufacturing & Wholesale Goods"
        }
    ],
    "sg:phone":"+1 513 763 8210",
    "sg:postcode":"45203",
    "sg:province":"OH",
    "sg:tags":[
        "concrete",
        "product",
        "mfg"
    ],
    "wof:name":"Bridgetek",
    "wof:placetype":"venue"
},
  "geometry": {"coordinates":[-84.526859,39.095043],"type":"Point"}
}