{
  "type": "Feature",
  "properties": {
    "addr:full": "5267 Ford Rd Williamsfield OH 44057",
    "addr:housenumber": "5267",
    "addr:postcode": "44057",
    "addr:street": "Ford Rd",
    "iso:country": "US",
    "sg:address": "5267 Ford Rd",
    "sg:city": "Williamsfield",
    "sg:classifiers": [
      {
        "category": "Shopping",
        "type": "Retail Goods"
      }
    ],
    "sg:phone": "+1 440 293 8227",
    "sg:postcode": "44057",
    "sg:province": "OH",
    "sg:tags": [
      "merchandise"
    ],
    "wof:name": "Frame Shop \u0026 Gallery",
    "wof:placetype": "venue"
  },
  "geometry": {"coordinates":[-81.101069,41.722965],"type":"Point"}
}
