{
  "type": "Feature",
  "properties": {
    "iso:country":"US",
    "sg:address":"5267 Ford Rd",
    "sg:city":"Williamsfield",
    "sg:classifiers":[
        {
            "category":"Shopping",
            "type":"Retail Goods"
        }
    ],
    "sg:phone":"+1 440 293 8227",
    "sg:postcode":"44057",
    "sg:province":"OH",
    "sg:tags":[
        "merchandise"
    ],
    "wof:name":"Frame Shop & Gallery",
    "wof:placetype":"venue"
},
  "geometry": {"coordinates":[-81.101069,41.722965],"type":"Point"}
}