{
  "type": "Feature",
  "properties": {
    "addr:full": "212 Sandstone Ridge Way Berea OH 44017",
    "addr:housenumber": "212",
    "addr:postcode": "44017",
    "addr:street": "Sandstone Ridge Way",
    "iso:country": "US",
    "sg:address": "212 Sandstone Ridge Way",
    "sg:city": "Berea",
    "sg:classifiers": [
      {
        "category": "Restaurant",
        "type": "Food \u0026 Drink"
      },
      {
        "category": "Ice Cream",
        "type": "Food \u0026 Drink"
      }
    ],
    "sg:phone": "+1 440 260 0222",
    "sg:postcode": "44017",
    "sg:province": "OH",
    "sg:tags": [
      "frozen",
      "dessert"
    ],
    "sg:website": "http://www.mjscullyco.com",
    "wof:name": "Dairy Queen",
    "wof:placetype": "venue"
  },
  "geometry": {"coordinates":[-81.884198,41.383619],"type":"Point"}
}
