{
  "type": "Feature",
  "properties": {
    "iso:country":"US",
    "sg:address":"41063 State Rte 558",
    "sg:city":"Leetonia",
    "sg:classifiers":[
        {
            "category":"Freight",
            "type":"Transportation"
        }
    ],
    "sg:phone":"+1 330 482 3657",
    "sg:postcode":"44431",
    "sg:province":"OH",
    "sg:tags":[
        "operator",
        "local",
        "trucking"
    ],
    "wof:name":"Emelo Trucking",
    "wof:placetype":"venue"
},
  "geometry": {"coordinates":[-80.725517,40.839282],"type":"Point"}
}