{
  "type": "Feature",
  "properties": {
    "addr:full":"204 Kempton Dr Berea OH 44017",
    "addr:housenumber":"204",
    "addr:postcode":"44017",
    "addr:street":"Kempton Dr",
    "iso:country":"US",
    "sg:address":"204 Kempton Dr",
    "sg:city":"Berea",
    "sg:classifiers":[
        {
            "category":"Professional",
            "subcategory":"Business Services",
            "type":"Services"
        }
    ],
    "sg:phone":"+1 440 826 8266",
    "sg:postcode":"44017",
    "sg:province":"OH",
    "sg:tags":[
        "liquidator"
    ],
    "wof:name":"Anthem Auction & Liquidation",
    "wof:placetype":"venue"
},
  "geometry": {"coordinates":[-81.86804100000001,41.363099],"type":"Point"}
}