{
  "type": "Feature",
  "properties": {
    "iso:country":"US",
    "sg:address":"848 Scioto St",
    "sg:city":"Urbana",
    "sg:classifiers":[
        {
            "category":"Social Services",
            "type":"Services"
        }
    ],
    "sg:phone":"+1 937 653 3113",
    "sg:postcode":"43078",
    "sg:province":"OH",
    "sg:tags":[
        "counselor",
        "marriage",
        "family"
    ],
    "wof:name":"Professional Counseling Svc",
    "wof:placetype":"venue"
},
  "geometry": {"coordinates":[-83.73162000000001,40.106881],"type":"Point"}
}