{
  "type": "Feature",
  "properties": {
    "iso:country":"US",
    "sg:address":"23050 Louise Ln",
    "sg:city":"Columbia Station",
    "sg:classifiers":[
        {
            "category":"Professional",
            "type":"Services"
        }
    ],
    "sg:phone":"+1 440 236 8527",
    "sg:postcode":"44028",
    "sg:province":"OH",
    "wof:name":"Ray Bilecky",
    "wof:placetype":"venue"
},
  "geometry": {"coordinates":[-81.882732,41.296617],"type":"Point"}
}