{
  "type": "Feature",
  "properties": {
    "iso:country":"US",
    "sg:address":"2850 W 25th St",
    "sg:city":"Cleveland",
    "sg:classifiers":[
        {
            "category":"Food & Beverages",
            "subcategory":"Specialty",
            "type":"Retail Goods"
        }
    ],
    "sg:phone":"+1 216 241 4003",
    "sg:postcode":"44113",
    "sg:province":"OH",
    "wof:name":"I 90 Citgo",
    "wof:placetype":"venue"
},
  "geometry": {"coordinates":[-81.699507,41.472954],"type":"Point"}
}