{
  "type": "Feature",
  "properties": {
    "addr:full":"720 Eastgate South Dr Cincinnati OH 45245",
    "addr:housenumber":"720",
    "addr:postcode":"45245",
    "addr:street":"Eastgate South Dr",
    "iso:country":"US",
    "sg:address":"720 Eastgate South Dr",
    "sg:city":"Cincinnati",
    "sg:classifiers":[
        {
            "category":"Shopping",
            "type":"Retail Goods"
        }
    ],
    "sg:phone":"+1 513 752 7650",
    "sg:postcode":"45245",
    "sg:province":"OH",
    "sg:tags":[
        "merchandise"
    ],
    "wof:name":"Watsons Pool Accessory Outlets",
    "wof:placetype":"venue"
},
  "geometry": {"coordinates":[-84.271455,39.095806],"type":"Point"}
}