{
  "type": "Feature",
  "properties": {
    "addr:full": "15489 State Rte 18 Sherwood OH 43556",
    "addr:housenumber": "15489",
    "addr:postcode": "43556",
    "addr:street": "State Rte 18",
    "iso:country": "US",
    "sg:address": "15489 State Rte 18",
    "sg:city": "Sherwood",
    "sg:phone": "+1 419 899 2289",
    "sg:postcode": "43556",
    "sg:province": "OH",
    "sg:tags": [
      "a",
      "wheat",
      "farm",
      "corn",
      "real estate"
    ],
    "wof:name": "Dell John",
    "wof:placetype": "venue"
  },
  "geometry": {"coordinates":[-84.530094,41.296286],"type":"Point"}
}
