{
  "type": "Feature",
  "properties": {
    "addr:full": "39050 Center Ridge Rd North Ridgeville OH 44039",
    "addr:housenumber": "39050",
    "addr:postcode": "44039",
    "addr:street": "Center Ridge Rd",
    "iso:country": "US",
    "sg:address": "39050 Center Ridge Rd",
    "sg:city": "North Ridgeville",
    "sg:classifiers": [
      {
        "category": "Professional",
        "subcategory": "Accounting \u0026 Tax Preparation",
        "type": "Services"
      }
    ],
    "sg:phone": "+1 440 327 8299",
    "sg:postcode": "44039",
    "sg:province": "OH",
    "sg:tags": [
      "return",
      "filing"
    ],
    "wof:name": "Tax Professionals",
    "wof:placetype": "venue"
  },
  "geometry": {"coordinates":[-82.057312,41.383234],"type":"Point"}
}
