{
  "type": "Feature",
  "properties": {
    "addr:full":"1105 W 1st Ave Columbus OH 43212",
    "addr:housenumber":"1105",
    "addr:postcode":"43212",
    "addr:street":"W 1St Ave",
    "iso:country":"US",
    "sg:address":"1105 W 1st Ave",
    "sg:city":"Columbus",
    "sg:classifiers":[
        {
            "category":"Restaurant",
            "type":"Food & Drink"
        }
    ],
    "sg:menulink":"http://www.allmenus.com/oh/grandview-heights/244224-marshalls/menu/",
    "sg:phone":"+1 614 294 1105",
    "sg:postcode":"43212",
    "sg:province":"OH",
    "sg:tags":[
        "american"
    ],
    "wof:name":"Marshall's",
    "wof:placetype":"venue"
},
  "geometry": {"coordinates":[-83.034189,39.979659],"type":"Point"}
}