{
  "type": "Feature",
  "properties": {
    "addr:full": "4101 N King Rd Sylvania OH 43560",
    "addr:housenumber": "4101",
    "addr:postcode": "43560",
    "addr:street": "N King Rd",
    "iso:country": "US",
    "sg:address": "4101 N King Rd",
    "sg:city": "Sylvania",
    "sg:classifiers": [
      {
        "category": "Building \u0026 Trades",
        "subcategory": "Construction",
        "type": "Services"
      }
    ],
    "sg:phone": "+1 419 843 2288",
    "sg:postcode": "43560",
    "sg:province": "OH",
    "sg:tags": [
      "housing",
      "contractor"
    ],
    "wof:name": "Prestancia Building Company",
    "wof:placetype": "venue"
  },
  "geometry": {"coordinates":[-83.723344,41.690643],"type":"Point"}
}
