{
  "type": "Feature",
  "properties": {
    "iso:country":"US",
    "sg:address":"201 W Geneva St",
    "sg:city":"Dunkirk",
    "sg:classifiers":[
        {
            "category":"Government",
            "subcategory":"Office",
            "type":"Public Place"
        }
    ],
    "sg:phone":"+1 419 759 2102",
    "sg:postcode":"45836",
    "sg:province":"OH",
    "sg:tags":[
        "village"
    ],
    "wof:name":"Dunkirk Village Public Affairs",
    "wof:placetype":"venue"
},
  "geometry": {"coordinates":[-83.645689,40.78309],"type":"Point"}
}