{
  "type": "Feature",
  "properties": {
    "addr:full": "604 Walnut St Coshocton OH 43812",
    "addr:housenumber": "604",
    "addr:postcode": "43812",
    "addr:street": "Walnut St",
    "iso:country": "US",
    "sg:address": "604 Walnut St",
    "sg:city": "Coshocton",
    "sg:classifiers": [
      {
        "category": "Organizations",
        "subcategory": "Community Association",
        "type": "Services"
      },
      {
        "category": "Social Services",
        "type": "Services"
      }
    ],
    "sg:phone": "+1 740 622 8504",
    "sg:postcode": "43812",
    "sg:province": "OH",
    "sg:tags": [
      "information",
      "abuse",
      "domestic",
      "treatment"
    ],
    "wof:name": "First Step Family Violence Int",
    "wof:placetype": "venue"
  },
  "geometry": {"coordinates":[-81.861552,40.272179],"type":"Point"}
}
