{
  "type": "Feature",
  "properties": {
    "addr:full": "572 S Nelson Rd Columbus OH 43205",
    "addr:housenumber": "572",
    "addr:postcode": "43205",
    "addr:street": "S Nelson Rd",
    "iso:country": "US",
    "sg:address": "572 S Nelson Rd",
    "sg:city": "Columbus",
    "sg:classifiers": [
      {
        "category": "Retail",
        "subcategory": "Car Wash",
        "type": "Services"
      },
      {
        "category": "Building \u0026 Trades",
        "subcategory": "Construction",
        "type": "Services"
      }
    ],
    "sg:phone": "+1 614 252 8020",
    "sg:postcode": "43205",
    "sg:province": "OH",
    "sg:tags": [
      "pressure",
      "restoration",
      "cleaning",
      "patio",
      "deck"
    ],
    "wof:name": "Rite Way Pressure Wash Inc",
    "wof:placetype": "venue"
  },
  "geometry": {"coordinates":[-82.946903,39.955868],"type":"Point"}
}
