{
  "type": "Feature",
  "properties": {
    "iso:country":"US",
    "sg:address":"5685 Reier Rd",
    "sg:city":"Saint Henry",
    "sg:classifiers":[
        {
            "category":"Farming",
            "subcategory":"Poultry Farm",
            "type":"Manufacturing & Wholesale Goods"
        }
    ],
    "sg:phone":"+1 419 925 5119",
    "sg:postcode":"45883",
    "sg:province":"OH",
    "sg:tags":[
        "chicken",
        "egg"
    ],
    "wof:name":"Gerlach Poultry",
    "wof:placetype":"venue"
},
  "geometry": {"coordinates":[-84.586758,40.396114],"type":"Point"}
}