{
  "type": "Feature",
  "properties": {
    "iso:country":"US",
    "sg:address":"5440 Dixie Hwy",
    "sg:city":"Fairfield",
    "sg:classifiers":[
        {
            "category":"Coffee & Tea",
            "type":"Food & Drink"
        }
    ],
    "sg:menulink":"http://www.allmenus.com/oh/fairfield/124814-starbucks-coffee/menu/",
    "sg:phone":"+1 513 939 2999",
    "sg:postcode":"45014",
    "sg:province":"OH",
    "sg:tags":[
        "american"
    ],
    "wof:name":"Starbucks Coffee",
    "wof:placetype":"venue"
},
  "geometry": {"coordinates":[-84.523989,39.335857],"type":"Point"}
}