{
  "type": "Feature",
  "properties": {
    "iso:country":"US",
    "sg:address":"610 Long Rd",
    "sg:city":"Pickerington",
    "sg:classifiers":[
        {
            "category":"Organizations",
            "subcategory":"Community Association",
            "type":"Services"
        }
    ],
    "sg:phone":"+1 614 833 1505",
    "sg:postcode":"43147",
    "sg:province":"OH",
    "wof:name":"Delta Kppa Gmma Soc Intrntonal",
    "wof:placetype":"venue"
},
  "geometry": {"coordinates":[-82.77029400000001,39.886831],"type":"Point"}
}