{
  "type": "Feature",
  "properties": {
    "addr:full": "610 Long Rd Pickerington OH 43147",
    "addr:housenumber": "610",
    "addr:postcode": "43147",
    "addr:street": "Long Rd",
    "iso:country": "US",
    "sg:address": "610 Long Rd",
    "sg:city": "Pickerington",
    "sg:classifiers": [
      {
        "category": "Organizations",
        "subcategory": "Community Association",
        "type": "Services"
      }
    ],
    "sg:phone": "+1 614 833 1505",
    "sg:postcode": "43147",
    "sg:province": "OH",
    "wof:name": "Delta Kppa Gmma Soc Intrntonal",
    "wof:placetype": "venue"
  },
  "geometry": {"coordinates":[-82.770294,39.886831],"type":"Point"}
}
