{
  "type": "Feature",
  "properties": {
    "iso:country":"US",
    "sg:address":"15374 US Hwy 68",
    "sg:city":"Mount Orab",
    "sg:classifiers":[
        {
            "category":"Farming",
            "subcategory":"Farm",
            "type":"Manufacturing & Wholesale Goods"
        }
    ],
    "sg:phone":"+1 937 444 3061",
    "sg:postcode":"45154",
    "sg:province":"OH",
    "sg:tags":[
        "crop",
        "general"
    ],
    "wof:name":"Wells Mica",
    "wof:placetype":"venue"
},
  "geometry": {"coordinates":[-83.92446200000001,39.058398],"type":"Point"}
}