{
  "type": "Feature",
  "properties": {
    "addr:full": "5221 West Ave Ashtabula OH 44004",
    "addr:housenumber": "5221",
    "addr:postcode": "44004",
    "addr:street": "West Ave",
    "iso:country": "US",
    "sg:address": "5221 West Ave",
    "sg:city": "Ashtabula",
    "sg:classifiers": [
      {
        "category": "Autos \u0026 Motor Vehicles",
        "subcategory": "Automobile Sales",
        "type": "Retail Goods"
      }
    ],
    "sg:phone": "+1 440 992 2872",
    "sg:postcode": "44004",
    "sg:province": "OH",
    "sg:tags": [
      "car",
      "dealer"
    ],
    "wof:name": "Black Forest Motor Cars",
    "wof:placetype": "venue"
  },
  "geometry": {"coordinates":[-80.796173,41.860296],"type":"Point"}
}
