{
  "type": "Feature",
  "properties": {
    "iso:country":"US",
    "sg:address":"5246 Cleveland Rd",
    "sg:city":"Wooster",
    "sg:classifiers":[
        {
            "category":"Wholesale",
            "subcategory":"Medical Equipment & Supplies",
            "type":"Manufacturing & Wholesale Goods"
        }
    ],
    "sg:phone":"+1 330 345 5466",
    "sg:postcode":"44691",
    "sg:province":"OH",
    "sg:tags":[
        "physician",
        "surgeon"
    ],
    "wof:name":"Wheeler & Wheeler Inc",
    "wof:placetype":"venue"
},
  "geometry": {"coordinates":[-81.923002,40.864187],"type":"Point"}
}