{
  "type": "Feature",
  "properties": {
    "addr:full": "5246 Cleveland Rd Wooster OH 44691",
    "addr:housenumber": "5246",
    "addr:postcode": "44691",
    "addr:street": "Cleveland Rd",
    "iso:country": "US",
    "sg:address": "5246 Cleveland Rd",
    "sg:city": "Wooster",
    "sg:classifiers": [
      {
        "category": "Wholesale",
        "subcategory": "Medical Equipment \u0026 Supplies",
        "type": "Manufacturing \u0026 Wholesale Goods"
      }
    ],
    "sg:phone": "+1 330 345 5466",
    "sg:postcode": "44691",
    "sg:province": "OH",
    "sg:tags": [
      "physician",
      "surgeon"
    ],
    "wof:name": "Wheeler \u0026 Wheeler Inc",
    "wof:placetype": "venue"
  },
  "geometry": {"coordinates":[-81.923002,40.864187],"type":"Point"}
}
