{
  "type": "Feature",
  "properties": {
    "addr:full":"3294 Bradley Brownlee Rd Cortland OH 44410",
    "addr:housenumber":"3294",
    "addr:postcode":"44410",
    "addr:street":"Bradley Brownlee Rd",
    "iso:country":"US",
    "sg:address":"3294 Bradley Brownlee Rd",
    "sg:city":"Cortland",
    "sg:classifiers":[
        {
            "category":"Farming",
            "subcategory":"Nursery",
            "type":"Manufacturing & Wholesale Goods"
        }
    ],
    "sg:phone":"+1 330 638 1969",
    "sg:postcode":"44410",
    "sg:province":"OH",
    "sg:tags":[
        "greenhouse"
    ],
    "wof:name":"Blascaks Greenhouses",
    "wof:placetype":"venue"
},
  "geometry": {"coordinates":[-80.700625,41.349742],"type":"Point"}
}