{
  "type": "Feature",
  "properties": {
    "addr:full": "1400 Gay St Portsmouth OH 45662",
    "addr:housenumber": "1400",
    "addr:postcode": "45662",
    "addr:street": "Gay St",
    "iso:country": "US",
    "sg:address": "1400 Gay St",
    "sg:city": "Portsmouth",
    "sg:classifiers": [
      {
        "category": "Health Services",
        "subcategory": "Doctor",
        "type": "Services"
      }
    ],
    "sg:phone": "+1 740 351 0999",
    "sg:postcode": "45662",
    "sg:province": "OH",
    "sg:tags": [
      "physician",
      "surgeon"
    ],
    "sg:website": "www.eyespecialistsofohio.com",
    "wof:name": "Eye Specialists Inc",
    "wof:placetype": "venue"
  },
  "geometry": {"coordinates":[-82.99387,38.742754],"type":"Point"}
}
