{
  "type": "Feature",
  "properties": {
    "addr:full": "4341 Dana Dr Franklin OH 45005",
    "addr:housenumber": "4341",
    "addr:postcode": "45005",
    "addr:street": "Dana Dr",
    "iso:country": "US",
    "sg:address": "4341 Dana Dr",
    "sg:city": "Franklin",
    "sg:classifiers": [
      {
        "category": "Shopping",
        "subcategory": "Used Merchandise",
        "type": "Retail Goods"
      }
    ],
    "sg:phone": "+1 937 746 1150",
    "sg:postcode": "45005",
    "sg:province": "OH",
    "wof:name": "Daltons Antiques",
    "wof:placetype": "venue"
  },
  "geometry": {"coordinates":[-84.278198,39.562089],"type":"Point"}
}
