{
  "type": "Feature",
  "properties": {
    "iso:country":"US",
    "sg:address":"13201 Granger Rd",
    "sg:city":"Cleveland",
    "sg:classifiers":[
        {
            "category":"Health Services",
            "subcategory":"Health Practitioner",
            "type":"Services"
        }
    ],
    "sg:phone":"+1 216 663 8440",
    "sg:postcode":"44125",
    "sg:province":"OH",
    "sg:tags":[
        "psychologist"
    ],
    "wof:name":"Marymount Sleep Disorder Ctr",
    "wof:placetype":"venue"
},
  "geometry": {"coordinates":[-81.59102799999999,41.417088],"type":"Point"}
}