{
  "type": "Feature",
  "properties": {
    "addr:full":"61561 Wintergreen Rd Lore City OH 43755",
    "addr:housenumber":"61561",
    "addr:postcode":"43755",
    "addr:street":"Wintergreen Rd",
    "iso:country":"US",
    "sg:address":"61561 Wintergreen Rd",
    "sg:city":"Lore City",
    "sg:classifiers":[
        {
            "category":"Bars & Pubs",
            "type":"Food & Drink"
        }
    ],
    "sg:phone":"+1 740 685 2435",
    "sg:postcode":"43755",
    "sg:province":"OH",
    "sg:tags":[
        "drinking"
    ],
    "wof:name":"Airport Inn",
    "wof:placetype":"venue"
},
  "geometry": {"coordinates":[-81.459445,39.992056],"type":"Point"}
}