{
  "type": "Feature",
  "properties": {
    "addr:full":"5037 Southway St SW Canton OH 44646",
    "addr:housenumber":"5037",
    "addr:postcode":"44646",
    "addr:street":"Southway St Sw",
    "iso:country":"US",
    "sg:address":"5037 Southway St SW",
    "sg:city":"Canton",
    "sg:classifiers":[
        {
            "category":"Professional",
            "subcategory":"Business Services",
            "type":"Services"
        }
    ],
    "sg:phone":"+1 330 479 2720",
    "sg:postcode":"44646",
    "sg:province":"OH",
    "sg:tags":[
        "translator",
        "interpreter"
    ],
    "sg:website":"www.gemodisplays.com",
    "wof:name":"GEMO",
    "wof:placetype":"venue"
},
  "geometry": {"coordinates":[-81.44083999999999,40.781951],"type":"Point"}
}