{
  "type": "Feature",
  "properties": {
    "addr:full": "410 Gibbs Rd Norwalk OH 44857",
    "addr:housenumber": "410",
    "addr:postcode": "44857",
    "addr:street": "Gibbs Rd",
    "iso:country": "US",
    "sg:address": "410 Gibbs Rd",
    "sg:city": "Norwalk",
    "sg:classifiers": [
      {
        "category": "Utilities",
        "subcategory": "Telephone",
        "type": "Services"
      }
    ],
    "sg:phone": "+1 419 668 4336",
    "sg:postcode": "44857",
    "sg:province": "OH",
    "sg:tags": [
      "communications"
    ],
    "wof:name": "Alltel",
    "wof:placetype": "venue"
  },
  "geometry": {"coordinates":[-82.568424,41.256988],"type":"Point"}
}
