{
  "type": "Feature",
  "properties": {
    "addr:full": "575 Reading Rd Cincinnati OH 45202",
    "addr:housenumber": "575",
    "addr:postcode": "45202",
    "addr:street": "Reading Rd",
    "iso:country": "US",
    "sg:address": "575 Reading Rd",
    "sg:city": "Cincinnati",
    "sg:classifiers": [
      {
        "category": "Wholesale",
        "subcategory": "Machinery \u0026 Supplies",
        "type": "Manufacturing \u0026 Wholesale Goods"
      }
    ],
    "sg:phone": "+1 513 721 7170",
    "sg:postcode": "45202",
    "sg:province": "OH",
    "sg:tags": [
      "product",
      "industrial",
      "petroleum"
    ],
    "wof:name": "Mid-Valley Central Equipment",
    "wof:placetype": "venue"
  },
  "geometry": {"coordinates":[-84.505718,39.109347],"type":"Point"}
}
