{
  "type": "Feature",
  "properties": {
    "iso:country":"US",
    "sg:address":"575 Reading Rd",
    "sg:city":"Cincinnati",
    "sg:classifiers":[
        {
            "category":"Wholesale",
            "subcategory":"Machinery & Supplies",
            "type":"Manufacturing & Wholesale Goods"
        }
    ],
    "sg:phone":"+1 513 721 7170",
    "sg:postcode":"45202",
    "sg:province":"OH",
    "sg:tags":[
        "product",
        "industrial",
        "petroleum"
    ],
    "wof:name":"Mid-Valley Central Equipment",
    "wof:placetype":"venue"
},
  "geometry": {"coordinates":[-84.505718,39.109347],"type":"Point"}
}