{
  "type": "Feature",
  "properties": {
    "iso:country":"US",
    "sg:address":"1351 Oxford Middletown Rd",
    "sg:city":"Hamilton",
    "sg:classifiers":[
        {
            "category":"Building & Trades",
            "subcategory":"Construction",
            "type":"Services"
        }
    ],
    "sg:phone":"+1 513 726 6368",
    "sg:postcode":"45013",
    "sg:province":"OH",
    "sg:tags":[
        "house"
    ],
    "wof:name":"Charles W Olinger",
    "wof:placetype":"venue"
},
  "geometry": {"coordinates":[-84.605701,39.537829],"type":"Point"}
}