{
  "type": "Feature",
  "properties": {
    "iso:country":"US",
    "sg:address":"6575 Seville Dr",
    "sg:city":"Canfield",
    "sg:classifiers":[
        {
            "category":"Banks & Credit Unions",
            "subcategory":"Investment Brokerage",
            "type":"Services"
        }
    ],
    "sg:phone":"+1 330 702 2075",
    "sg:postcode":"44406",
    "sg:province":"OH",
    "sg:tags":[
        "stock",
        "bond"
    ],
    "wof:name":"Mc Donald Investments",
    "wof:placetype":"venue"
},
  "geometry": {"coordinates":[-80.71510499999999,41.024357],"type":"Point"}
}