{
  "type": "Feature",
  "properties": {
    "addr:full":"5845 Liberty Rd Cleveland OH 44139",
    "addr:housenumber":"5845",
    "addr:postcode":"44139",
    "addr:street":"Liberty Rd",
    "iso:country":"US",
    "sg:address":"5845 Liberty Rd",
    "sg:city":"Cleveland",
    "sg:classifiers":[
        {
            "category":"Professional",
            "subcategory":"Research",
            "type":"Services"
        }
    ],
    "sg:phone":"+1 440 542 1745",
    "sg:postcode":"44139",
    "sg:province":"OH",
    "sg:tags":[
        "medical"
    ],
    "wof:name":"G E Clinical Svc",
    "wof:placetype":"venue"
},
  "geometry": {"coordinates":[-81.413893,41.39916],"type":"Point"}
}