{
  "type": "Feature",
  "properties": {
    "addr:full": "1943 Martin Ave Fremont OH 43420",
    "addr:housenumber": "1943",
    "addr:postcode": "43420",
    "addr:street": "Martin Ave",
    "iso:country": "US",
    "sg:address": "1943 Martin Ave",
    "sg:city": "Fremont",
    "sg:classifiers": [
      {
        "category": "Building \u0026 Trades",
        "subcategory": "Construction",
        "type": "Services"
      }
    ],
    "sg:phone": "+1 419 333 0876",
    "sg:postcode": "43420",
    "sg:province": "OH",
    "sg:tags": [
      "clearing",
      "land",
      "leveling"
    ],
    "wof:name": "Axar Land Maintenance",
    "wof:placetype": "venue"
  },
  "geometry": {"coordinates":[-83.141908,41.33347],"type":"Point"}
}
