{
  "type": "Feature",
  "properties": {
    "addr:full": "2800 Shady Run Rd Youngstown OH 44502",
    "addr:housenumber": "2800",
    "addr:postcode": "44502",
    "addr:street": "Shady Run Rd",
    "iso:country": "US",
    "sg:address": "2800 Shady Run Rd",
    "sg:city": "Youngstown",
    "sg:classifiers": [
      {
        "category": "Education",
        "subcategory": "School",
        "type": "Public Place"
      }
    ],
    "sg:phone": "+1 330 788 9566",
    "sg:postcode": "44502",
    "sg:province": "OH",
    "wof:name": "St Matthias Parish School",
    "wof:placetype": "venue"
  },
  "geometry": {"coordinates":[-80.634194,41.071047],"type":"Point"}
}
