{
  "type": "Feature",
  "properties": {
    "addr:full":"17290 Twp Rd 199 Mount Victory OH 43340",
    "addr:housenumber":"199",
    "addr:postcode":"17290;43340",
    "addr:street":"Twp Rd;Mount",
    "iso:country":"US",
    "sg:address":"17290 Twp Rd 199",
    "sg:city":"Mount Victory",
    "sg:phone":"+1 937 354 3815",
    "sg:postcode":"43340",
    "sg:province":"OH",
    "sg:tags":[
        "farm",
        "field",
        "corn",
        "crop"
    ],
    "wof:name":"J Bar Farm",
    "wof:placetype":"venue"
},
  "geometry": {"coordinates":[-83.52672200000001,40.564186],"type":"Point"}
}