{
  "type": "Feature",
  "properties": {
    "addr:full": "965 S Children's Home Rd Troy OH 45373",
    "addr:housenumber": "965",
    "addr:postcode": "45373",
    "addr:street": "Rd",
    "iso:country": "US",
    "sg:address": "965 S Children's Home Rd",
    "sg:city": "Troy",
    "sg:phone": "+1 937 339 8828",
    "sg:postcode": "45373",
    "sg:province": "OH",
    "sg:tags": [
      "farm",
      "corn"
    ],
    "wof:name": "Mark Batdorf",
    "wof:placetype": "venue"
  },
  "geometry": {"coordinates":[-84.142286,40.017454],"type":"Point"}
}
