{
  "type": "Feature",
  "properties": {
    "addr:full": "4153 Bridgewater Pkwy Stow OH 44224",
    "addr:housenumber": "4153",
    "addr:postcode": "44224",
    "addr:street": "Bridgewater Pkwy",
    "iso:country": "US",
    "sg:address": "4153 Bridgewater Pkwy",
    "sg:city": "Stow",
    "sg:classifiers": [
      {
        "category": "Retail",
        "subcategory": "Laundry \u0026 Dry Cleaning",
        "type": "Services"
      }
    ],
    "sg:phone": "+1 330 922 9904",
    "sg:postcode": "44224",
    "sg:province": "OH",
    "sg:tags": [
      "cleaners"
    ],
    "wof:name": "Encore Dry Cleaners",
    "wof:placetype": "venue"
  },
  "geometry": {"coordinates":[-81.480625,41.179187],"type":"Point"}
}
