{
  "type": "Feature",
  "properties": {
    "iso:country":"US",
    "sg:address":"4684 Neway Dr",
    "sg:city":"Hamilton",
    "sg:classifiers":[
        {
            "category":"Manufacturing",
            "subcategory":"Tools & Machinery",
            "type":"Manufacturing & Wholesale Goods"
        }
    ],
    "sg:phone":"+1 513 870 9553",
    "sg:postcode":"45011",
    "sg:province":"OH",
    "sg:tags":[
        "machine",
        "shop"
    ],
    "wof:name":"R & K Machine Shop",
    "wof:placetype":"venue"
},
  "geometry": {"coordinates":[-84.468824,39.331262],"type":"Point"}
}