{
  "type": "Feature",
  "properties": {
    "addr:full": "950 Youngstown Warren Rd Niles OH 44446",
    "addr:housenumber": "950",
    "addr:postcode": "44446",
    "addr:street": "Youngstown Warren Rd",
    "iso:country": "US",
    "sg:address": "950 Youngstown Warren Rd",
    "sg:city": "Niles",
    "sg:classifiers": [
      {
        "category": "Health Services",
        "subcategory": "Doctor",
        "type": "Services"
      }
    ],
    "sg:phone": "+1 330 652 8044",
    "sg:postcode": "44446",
    "sg:province": "OH",
    "wof:name": "John Thomas Kalasky",
    "wof:placetype": "venue"
  },
  "geometry": {"coordinates":[-80.733993,41.201013],"type":"Point"}
}
