{
  "type": "Feature",
  "properties": {
    "addr:full": "3044 Old State Rte 32 Batavia OH 45103",
    "addr:housenumber": "3044",
    "addr:postcode": "45103",
    "addr:street": "Old State Rte 32",
    "iso:country": "US",
    "sg:address": "3044 Old State Rte 32",
    "sg:city": "Batavia",
    "sg:classifiers": [
      {
        "category": "Building \u0026 Trades",
        "subcategory": "Construction",
        "type": "Services"
      }
    ],
    "sg:phone": "+1 513 724 6400",
    "sg:postcode": "45103",
    "sg:province": "OH",
    "sg:tags": [
      "contractor"
    ],
    "wof:name": "Tower Construction",
    "wof:placetype": "venue"
  },
  "geometry": {"coordinates":[-84.081444,39.051753],"type":"Point"}
}
