{
  "type": "Feature",
  "properties": {
    "addr:full":"4270 Northampton Rd Cuyahoga Falls OH 44223",
    "addr:housenumber":"4270",
    "addr:postcode":"44223",
    "addr:street":"Northampton Rd",
    "iso:country":"US",
    "sg:address":"4270 Northampton Rd",
    "sg:city":"Cuyahoga Falls",
    "sg:classifiers":[
        {
            "category":"Home & Garden",
            "subcategory":"Building Materials",
            "type":"Retail Goods"
        }
    ],
    "sg:phone":"+1 330 922 0002",
    "sg:postcode":"44223",
    "sg:province":"OH",
    "sg:tags":[
        "windows"
    ],
    "wof:name":"Cuyahoga Falls Replacement",
    "wof:placetype":"venue"
},
  "geometry": {"coordinates":[-81.545243,41.197339],"type":"Point"}
}