{
  "type": "Feature",
  "properties": {
    "addr:full": "15 Lonsdale Ave Dayton OH 45419",
    "addr:housenumber": "15",
    "addr:postcode": "45419",
    "addr:street": "Lonsdale Ave",
    "iso:country": "US",
    "sg:address": "15 Lonsdale Ave",
    "sg:city": "Dayton",
    "sg:classifiers": [
      {
        "category": "Wholesale",
        "subcategory": "Electrical",
        "type": "Manufacturing \u0026 Wholesale Goods"
      }
    ],
    "sg:phone": "+1 937 424 8600",
    "sg:postcode": "45419",
    "sg:province": "OH",
    "sg:tags": [
      "electric",
      "motor"
    ],
    "wof:name": "Bureau Of Motor Vehicles",
    "wof:placetype": "venue"
  },
  "geometry": {"coordinates":[-84.1709,39.717972],"type":"Point"}
}
