{
  "type": "Feature",
  "properties": {
    "addr:full": "7464 Mentor Ave Mentor OH 44060",
    "addr:housenumber": "7464",
    "addr:postcode": "44060",
    "addr:street": "Mentor Ave",
    "iso:country": "US",
    "sg:address": "7464 Mentor Ave",
    "sg:city": "Mentor",
    "sg:classifiers": [
      {
        "category": "Real Estate",
        "subcategory": "Real Estate Agent",
        "type": "Services"
      }
    ],
    "sg:phone": "+1 440 942 8006",
    "sg:postcode": "44060",
    "sg:province": "OH",
    "sg:website": "www.sequoiarealty.com",
    "wof:name": "Sequoia Realty Corp",
    "wof:placetype": "venue"
  },
  "geometry": {"coordinates":[-81.375815,41.653741],"type":"Point"}
}
