{
  "type": "Feature",
  "properties": {
    "addr:full": "11180 Thwing Rd Chardon OH 44024",
    "addr:housenumber": "11180",
    "addr:postcode": "44024",
    "addr:street": "Thwing Rd",
    "iso:country": "US",
    "sg:address": "11180 Thwing Rd",
    "sg:city": "Chardon",
    "sg:classifiers": [
      {
        "category": "Home \u0026 Garden",
        "subcategory": "Carpets \u0026 Floor Coverings",
        "type": "Retail Goods"
      }
    ],
    "sg:phone": "+1 440 263 8153",
    "sg:postcode": "44024",
    "sg:province": "OH",
    "wof:name": "Carpet Science",
    "wof:placetype": "venue"
  },
  "geometry": {"coordinates":[-81.240147,41.570076],"type":"Point"}
}
