{
  "type": "Feature",
  "properties": {
    "addr:full":"4581 Pearl Rd Cleveland OH 44109",
    "addr:housenumber":"4581",
    "addr:postcode":"44109",
    "addr:street":"Pearl Rd",
    "iso:country":"US",
    "sg:address":"4581 Pearl Rd",
    "sg:city":"Cleveland",
    "sg:classifiers":[
        {
            "category":"Real Estate",
            "subcategory":"Real Estate Operator",
            "type":"Services"
        }
    ],
    "sg:phone":"+1 216 741 2439",
    "sg:postcode":"44109",
    "sg:province":"OH",
    "sg:tags":[
        "building",
        "apartment"
    ],
    "wof:name":"Cundiff Group LLC",
    "wof:placetype":"venue"
},
  "geometry": {"coordinates":[-81.713982,41.430872],"type":"Point"}
}