{
  "type": "Feature",
  "properties": {
    "addr:full": "7216 Beechmont Ave Cincinnati OH 45230",
    "addr:housenumber": "7216",
    "addr:postcode": "45230",
    "addr:street": "Beechmont Ave",
    "iso:country": "US",
    "sg:address": "7216 Beechmont Ave",
    "sg:city": "Cincinnati",
    "sg:classifiers": [
      {
        "category": "Building \u0026 Trades",
        "subcategory": "Construction",
        "type": "Services"
      }
    ],
    "sg:phone": "+1 513 232 1547",
    "sg:postcode": "45230",
    "sg:province": "OH",
    "sg:tags": [
      "acoustical",
      "contractor"
    ],
    "wof:name": "Cincinnati Interiors LTD",
    "wof:placetype": "venue"
  },
  "geometry": {"coordinates":[-84.358372,39.07288],"type":"Point"}
}
