{
  "type": "Feature",
  "properties": {
    "addr:full": "1385 E 23rd Ave Columbus OH 43211",
    "addr:housenumber": "1385",
    "addr:postcode": "43211",
    "addr:street": "E 23Rd Ave",
    "iso:country": "US",
    "sg:address": "1385 E 23rd Ave",
    "sg:city": "Columbus",
    "sg:classifiers": [
      {
        "category": "Insurance",
        "subcategory": "Insurance Agent",
        "type": "Services"
      }
    ],
    "sg:phone": "+1 614 294 4589",
    "sg:postcode": "43211",
    "sg:province": "OH",
    "sg:tags": [
      "financial"
    ],
    "wof:name": "A Primerica Financial Services",
    "wof:placetype": "venue"
  },
  "geometry": {"coordinates":[-82.970809,40.005319],"type":"Point"}
}
