{
  "type": "Feature",
  "properties": {
    "addr:full": "4221 Grand Ave Middletown OH 45044",
    "addr:housenumber": "4221",
    "addr:postcode": "45044",
    "addr:street": "Grand Ave",
    "iso:country": "US",
    "sg:address": "4221 Grand Ave",
    "sg:city": "Middletown",
    "sg:classifiers": [
      {
        "category": "Retail",
        "subcategory": "Laundry \u0026 Dry Cleaning",
        "type": "Services"
      }
    ],
    "sg:phone": "+1 513 423 0848",
    "sg:postcode": "45044",
    "sg:province": "OH",
    "sg:tags": [
      "cleaner",
      "commercial"
    ],
    "wof:name": "Watson's Dry Cleaners Inc",
    "wof:placetype": "venue"
  },
  "geometry": {"coordinates":[-84.358279,39.50372],"type":"Point"}
}
