{
  "type": "Feature",
  "properties": {
    "iso:country":"US",
    "sg:address":"4221 Grand Ave",
    "sg:city":"Middletown",
    "sg:classifiers":[
        {
            "category":"Retail",
            "subcategory":"Laundry & Dry Cleaning",
            "type":"Services"
        }
    ],
    "sg:phone":"+1 513 423 0848",
    "sg:postcode":"45044",
    "sg:province":"OH",
    "sg:tags":[
        "cleaner",
        "commercial"
    ],
    "wof:name":"Watson's Dry Cleaners Inc",
    "wof:placetype":"venue"
},
  "geometry": {"coordinates":[-84.358279,39.50372],"type":"Point"}
}