{
  "type": "Feature",
  "properties": {
    "iso:country":"US",
    "sg:address":"2181 Wadsworth Rd",
    "sg:city":"Barberton",
    "sg:classifiers":[
        {
            "category":"Insurance",
            "subcategory":"Insurance Agent",
            "type":"Services"
        }
    ],
    "sg:phone":"+1 330 745 6230",
    "sg:postcode":"44203",
    "sg:province":"OH",
    "wof:name":"Farmers Insurance Group",
    "wof:placetype":"venue"
},
  "geometry": {"coordinates":[-81.609173,41.055115],"type":"Point"}
}