{
  "type": "Feature",
  "properties": {
    "addr:full": "5270 Day Rd Cincinnati OH 45252",
    "addr:housenumber": "5270",
    "addr:postcode": "45252",
    "addr:street": "Day Rd",
    "iso:country": "US",
    "sg:address": "5270 Day Rd",
    "sg:city": "Cincinnati",
    "sg:classifiers": [
      {
        "category": "Travel",
        "subcategory": "Travel Agent",
        "type": "Entertainment"
      }
    ],
    "sg:phone": "+1 513 923 3108",
    "sg:postcode": "45252",
    "sg:province": "OH",
    "sg:tags": [
      "agency"
    ],
    "sg:website": "www.ohiotraveltreasures.com",
    "wof:name": "Ohio Travel Treasures",
    "wof:placetype": "venue"
  },
  "geometry": {"coordinates":[-84.614672,39.268338],"type":"Point"}
}
