{
  "type": "Feature",
  "properties": {
    "addr:full": "4119 State Rte 95 Mount Gilead OH 43338",
    "addr:housenumber": "4119;95",
    "addr:postcode": "43338",
    "addr:street": "State Rte;Mount",
    "iso:country": "US",
    "sg:address": "4119 State Rte 95",
    "sg:city": "Mount Gilead",
    "sg:classifiers": [
      {
        "category": "Government",
        "subcategory": "Office",
        "type": "Public Place"
      }
    ],
    "sg:phone": "+1 419 946 1961",
    "sg:postcode": "43338",
    "sg:province": "OH",
    "sg:tags": [
      "state",
      "park"
    ],
    "wof:name": "Mount Gilead State Park",
    "wof:placetype": "venue"
  },
  "geometry": {"coordinates":[-82.816502,40.547749],"type":"Point"}
}
