{
  "type": "Feature",
  "properties": {
    "iso:country":"US",
    "sg:address":"11681 State Rte 706",
    "sg:city":"De Graff",
    "sg:classifiers":[
        {
            "category":"Utilities",
            "subcategory":"Mobile Phone",
            "type":"Services"
        }
    ],
    "sg:phone":"+1 937 585 4118",
    "sg:postcode":"43343",
    "sg:province":"OH",
    "sg:tags":[
        "telephone",
        "cellular"
    ],
    "wof:name":"Cingular Wireless",
    "wof:placetype":"venue"
},
  "geometry": {"coordinates":[-83.982901,40.286551],"type":"Point"}
}