{
  "type": "Feature",
  "properties": {
    "addr:full":"1005 Woodward Pl NW Canton OH 44709",
    "addr:housenumber":"1005",
    "addr:postcode":"44709",
    "addr:street":"Woodward Pl Nw",
    "iso:country":"US",
    "sg:address":"1005 Woodward Pl NW",
    "sg:city":"Canton",
    "sg:classifiers":[
        {
            "category":"Shopping",
            "subcategory":"Gifts & Souvenirs",
            "type":"Retail Goods"
        }
    ],
    "sg:phone":"+1 330 452 2437",
    "sg:postcode":"44709",
    "sg:province":"OH",
    "wof:name":"Treasures In Attic",
    "wof:placetype":"venue"
},
  "geometry": {"coordinates":[-81.381754,40.825053],"type":"Point"}
}