{
  "type": "Feature",
  "properties": {
    "addr:full":"6077 Sharon Woods Blvd Columbus OH 43229",
    "addr:housenumber":"6077",
    "addr:postcode":"43229",
    "addr:street":"Sharon Woods Blvd",
    "iso:country":"US",
    "sg:address":"6077 Sharon Woods Blvd",
    "sg:city":"Columbus",
    "sg:classifiers":[
        {
            "category":"Organizations",
            "subcategory":"Religious Organization",
            "type":"Services"
        }
    ],
    "sg:phone":"+1 614 891 0150",
    "sg:postcode":"43229",
    "sg:province":"OH",
    "wof:name":"Rectory",
    "wof:placetype":"venue"
},
  "geometry": {"coordinates":[-82.970665,40.090968],"type":"Point"}
}