{
  "type": "Feature",
  "properties": {
    "iso:country":"US",
    "sg:address":"20340 Center Ridge Rd",
    "sg:city":"Cleveland",
    "sg:classifiers":[
        {
            "category":"Organizations",
            "subcategory":"Non-profit Organization",
            "type":"Services"
        }
    ],
    "sg:phone":"+1 440 356 5565",
    "sg:postcode":"44116",
    "sg:province":"OH",
    "sg:tags":[
        "alternative",
        "abortion"
    ],
    "wof:name":"Among Women Cornerstone",
    "wof:placetype":"venue"
},
  "geometry": {"coordinates":[-81.846461,41.46387],"type":"Point"}
}