{
  "type": "Feature",
  "properties": {
    "addr:full": "9999 W Ridgewood Dr Cleveland OH 44130",
    "addr:housenumber": "9999",
    "addr:postcode": "44130",
    "addr:street": "W Ridgewood Dr",
    "iso:country": "US",
    "sg:address": "9999 W Ridgewood Dr",
    "sg:city": "Cleveland",
    "sg:classifiers": [
      {
        "category": "Social Services",
        "subcategory": "Adult Care",
        "type": "Services"
      }
    ],
    "sg:phone": "+1 440 842 9616",
    "sg:postcode": "44130",
    "sg:province": "OH",
    "sg:tags": [
      "home",
      "group"
    ],
    "wof:name": "Phoenix Resident Ctr Ridgewood",
    "wof:placetype": "venue"
  },
  "geometry": {"coordinates":[-81.756765,41.384485],"type":"Point"}
}
