{
  "type": "Feature",
  "properties": {
    "addr:full": "1814 W Cordova Ave Cincinnati OH 45239",
    "addr:housenumber": "1814",
    "addr:postcode": "45239",
    "addr:street": "W Cordova Ave",
    "iso:country": "US",
    "sg:address": "1814 W Cordova Ave",
    "sg:city": "Cincinnati",
    "sg:classifiers": [
      {
        "category": "Freight",
        "type": "Transportation"
      }
    ],
    "sg:phone": "+1 513 931 5307",
    "sg:postcode": "45239",
    "sg:province": "OH",
    "sg:tags": [
      "operator",
      "local",
      "trucking"
    ],
    "wof:name": "Glenn Merritt Trucking",
    "wof:placetype": "venue"
  },
  "geometry": {"coordinates":[-84.554826,39.21074],"type":"Point"}
}
