{
  "type": "Feature",
  "properties": {
    "addr:full": "65 London Rd Delaware OH 43015",
    "addr:housenumber": "65",
    "addr:postcode": "43015",
    "addr:street": "London Rd",
    "iso:country": "US",
    "sg:address": "65 London Rd",
    "sg:city": "Delaware",
    "sg:classifiers": [
      {
        "category": "Wholesale",
        "subcategory": "Scrap",
        "type": "Manufacturing \u0026 Wholesale Goods"
      }
    ],
    "sg:phone": "+1 740 363 9192",
    "sg:postcode": "43015",
    "sg:province": "OH",
    "sg:tags": [
      "recycling",
      "center"
    ],
    "wof:name": "Sims Recycling Ctr",
    "wof:placetype": "venue"
  },
  "geometry": {"coordinates":[-83.073004,40.290379],"type":"Point"}
}
