{
  "type": "Feature",
  "properties": {
    "addr:full": "215 S Detroit St Kenton OH 43326",
    "addr:housenumber": "215",
    "addr:postcode": "43326",
    "addr:street": "S Detroit St",
    "iso:country": "US",
    "sg:address": "215 S Detroit St",
    "sg:city": "Kenton",
    "sg:classifiers": [
      {
        "category": "Restaurant",
        "type": "Food \u0026 Drink"
      }
    ],
    "sg:phone": "+1 419 673 7101",
    "sg:postcode": "43326",
    "sg:province": "OH",
    "sg:tags": [
      "pizza"
    ],
    "wof:name": "Michael Angelo's Pizza",
    "wof:placetype": "venue"
  },
  "geometry": {"coordinates":[-83.609268,40.645895],"type":"Point"}
}
