{
  "type": "Feature",
  "properties": {
    "addr:full": "1819 W State St Fremont OH 43420",
    "addr:housenumber": "1819",
    "addr:postcode": "43420",
    "addr:street": "W State St",
    "iso:country": "US",
    "sg:address": "1819 W State St",
    "sg:city": "Fremont",
    "sg:classifiers": [
      {
        "category": "Restaurant",
        "type": "Food \u0026 Drink"
      }
    ],
    "sg:menulink": "http://www.allmenus.com/oh/fremont/170265-burger-king/menu/",
    "sg:phone": "+1 419 334 8102",
    "sg:postcode": "43420",
    "sg:province": "OH",
    "sg:tags": [
      "burger",
      "american"
    ],
    "wof:name": "Burger King",
    "wof:placetype": "venue"
  },
  "geometry": {"coordinates":[-83.134544,41.35597],"type":"Point"}
}
