{
  "type": "Feature",
  "properties": {
    "addr:full":"639 Reed Rd Seaman OH 45679",
    "addr:housenumber":"639",
    "addr:postcode":"45679",
    "addr:street":"Reed Rd",
    "iso:country":"US",
    "sg:address":"639 Reed Rd",
    "sg:city":"Seaman",
    "sg:classifiers":[
        {
            "category":"Utilities",
            "subcategory":"Mobile Phone",
            "type":"Services"
        }
    ],
    "sg:phone":"+1 937 386 3253",
    "sg:postcode":"45679",
    "sg:province":"OH",
    "sg:tags":[
        "communication",
        "radiotelephone"
    ],
    "wof:name":"Cingular Wireless",
    "wof:placetype":"venue"
},
  "geometry": {"coordinates":[-83.618177,38.934406],"type":"Point"}
}