{
  "type": "Feature",
  "properties": {
    "addr:full":"7289 State Rte 43 Kent OH 44240",
    "addr:housenumber":"7289",
    "addr:postcode":"44240",
    "addr:street":"State Rte 43",
    "iso:country":"US",
    "sg:address":"7289 State Rte 43",
    "sg:city":"Kent",
    "sg:classifiers":[
        {
            "category":"Restaurant",
            "type":"Food & Drink"
        }
    ],
    "sg:phone":"+1 330 677 1618",
    "sg:postcode":"44240",
    "sg:province":"OH",
    "sg:tags":[
        "eating"
    ],
    "wof:name":"Twin Lakes Cuisine Inc",
    "wof:placetype":"venue"
},
  "geometry": {"coordinates":[-81.347618,41.179804],"type":"Point"}
}