{
  "type": "Feature",
  "properties": {
    "addr:full": "571 E 185th St Cleveland OH 44119",
    "addr:housenumber": "571",
    "addr:postcode": "44119",
    "addr:street": "E 185Th St",
    "iso:country": "US",
    "sg:address": "571 E 185th St",
    "sg:city": "Cleveland",
    "sg:classifiers": [
      {
        "category": "Bars \u0026 Pubs",
        "subcategory": "Nightclub",
        "type": "Food \u0026 Drink"
      }
    ],
    "sg:phone": "+1 216 531 0788",
    "sg:postcode": "44119",
    "sg:province": "OH",
    "sg:tags": [
      "club",
      "night"
    ],
    "wof:name": "Windermere 2726 Club K Of C",
    "wof:placetype": "venue"
  },
  "geometry": {"coordinates":[-81.549913,41.591698],"type":"Point"}
}
