{
  "type": "Feature",
  "properties": {
    "iso:country":"US",
    "sg:address":"2008 Broad Blvd",
    "sg:city":"Cuyahoga Falls",
    "sg:classifiers":[
        {
            "category":"Food & Beverages",
            "subcategory":"Groceries & Convenience Stores",
            "type":"Retail Goods"
        }
    ],
    "sg:phone":"+1 330 945 9492",
    "sg:postcode":"44223",
    "sg:province":"OH",
    "sg:tags":[
        "department",
        "publishing"
    ],
    "wof:name":"E Genesis Market Letter",
    "wof:placetype":"venue"
},
  "geometry": {"coordinates":[-81.507304,41.134428],"type":"Point"}
}