{
  "type": "Feature",
  "properties": {
    "addr:full":"5032 Glencrossing Way Cincinnati OH 45238",
    "addr:housenumber":"5032",
    "addr:postcode":"45238",
    "addr:street":"Glencrossing Way",
    "iso:country":"US",
    "sg:address":"5032 Glencrossing Way",
    "sg:city":"Cincinnati",
    "sg:classifiers":[
        {
            "category":"Restaurant",
            "type":"Food & Drink"
        }
    ],
    "sg:menulink":"http://www.allmenus.com/oh/cincinnati/228855-jersey-mikes/menu/",
    "sg:phone":"+1 513 451 9400",
    "sg:postcode":"45238",
    "sg:province":"OH",
    "sg:tags":[
        "american",
        "sandwich"
    ],
    "wof:name":"Jersey Mike's",
    "wof:placetype":"venue"
},
  "geometry": {"coordinates":[-84.61008,39.130176],"type":"Point"}
}