{
  "type": "Feature",
  "properties": {
    "iso:country":"US",
    "sg:address":"3244 Twp Rd 32 S",
    "sg:city":"Bellefontaine",
    "sg:phone":"+1 937 599 2582",
    "sg:postcode":"43311",
    "sg:province":"OH",
    "sg:tags":[
        "farm",
        "grain",
        "cash"
    ],
    "wof:name":"Arthur F Mast",
    "wof:placetype":"venue"
},
  "geometry": {"coordinates":[-83.787672,40.315986],"type":"Point"}
}