{
  "type": "Feature",
  "properties": {
    "addr:full": "5328 N Opfer-Lentz Rd Curtice OH 43412",
    "addr:housenumber": "5328",
    "addr:postcode": "43412",
    "addr:street": "N Opfer-Lentz Rd",
    "iso:country": "US",
    "sg:address": "5328 N Opfer-Lentz Rd",
    "sg:city": "Curtice",
    "sg:phone": "+1 419 836 7818",
    "sg:postcode": "43412",
    "sg:province": "OH",
    "sg:tags": [
      "farm",
      "grain",
      "cash"
    ],
    "wof:name": "Leroy Furstnau",
    "wof:placetype": "venue"
  },
  "geometry": {"coordinates":[-83.319943,41.596966],"type":"Point"}
}
