{
  "type": "Feature",
  "properties": {
    "addr:full":"14590 State Rte 93 Jackson OH 45640",
    "addr:housenumber":"14590",
    "addr:postcode":"45640",
    "addr:street":"State Rte 93",
    "iso:country":"US",
    "sg:address":"14590 State Rte 93",
    "sg:city":"Jackson",
    "sg:classifiers":[
        {
            "category":"Health Services",
            "subcategory":"Doctor",
            "type":"Services"
        }
    ],
    "sg:phone":"+1 740 286 2826",
    "sg:postcode":"45640",
    "sg:province":"OH",
    "sg:tags":[
        "clinic"
    ],
    "wof:name":"Jackson Family Health Ctr",
    "wof:placetype":"venue"
},
  "geometry": {"coordinates":[-82.624849,39.031876],"type":"Point"}
}