{
  "type": "Feature",
  "properties": {
    "addr:full": "2768 Drake Rd Columbus OH 43219",
    "addr:housenumber": "2768",
    "addr:postcode": "43219",
    "addr:street": "Drake Rd",
    "iso:country": "US",
    "sg:address": "2768 Drake Rd",
    "sg:city": "Columbus",
    "sg:classifiers": [
      {
        "category": "Building \u0026 Trades",
        "subcategory": "Construction",
        "type": "Services"
      }
    ],
    "sg:phone": "+1 614 475 2141",
    "sg:postcode": "43219",
    "sg:province": "OH",
    "sg:tags": [
      "restoration",
      "cleaning",
      "patio",
      "deck"
    ],
    "wof:name": "Mr Clean Pressure Washing",
    "wof:placetype": "venue"
  },
  "geometry": {"coordinates":[-82.920901,40.006543],"type":"Point"}
}
