{
  "type": "Feature",
  "properties": {
    "addr:full": "1900 W Stanfield Rd Troy OH 45373",
    "addr:housenumber": "1900",
    "addr:postcode": "45373",
    "addr:street": "W Stanfield Rd",
    "iso:country": "US",
    "sg:address": "1900 W Stanfield Rd",
    "sg:city": "Troy",
    "sg:classifiers": [
      {
        "category": "Building \u0026 Trades",
        "subcategory": "Construction",
        "type": "Services"
      }
    ],
    "sg:phone": "+1 937 339 9553",
    "sg:postcode": "45373",
    "sg:province": "OH",
    "sg:tags": [
      "general",
      "contractor"
    ],
    "wof:name": "Norwich Development",
    "wof:placetype": "venue"
  },
  "geometry": {"coordinates":[-84.242858,40.050259],"type":"Point"}
}
