{
  "type": "Feature",
  "properties": {
    "iso:country":"US",
    "sg:address":"11242 Co Rd 17",
    "sg:city":"Wauseon",
    "sg:classifiers":[
        {
            "category":"Farming",
            "subcategory":"Farm",
            "type":"Manufacturing & Wholesale Goods"
        }
    ],
    "sg:phone":"+1 419 335 6569",
    "sg:postcode":"43567",
    "sg:province":"OH",
    "sg:tags":[
        "crop",
        "general"
    ],
    "wof:name":"Bowman Family Farm",
    "wof:placetype":"venue"
},
  "geometry": {"coordinates":[-84.190054,41.637138],"type":"Point"}
}