{
  "type": "Feature",
  "properties": {
    "addr:full":"17100 Lorain Ave Cleveland OH 44111",
    "addr:housenumber":"17100",
    "addr:postcode":"44111",
    "addr:street":"Lorain Ave",
    "iso:country":"US",
    "sg:address":"17100 Lorain Ave",
    "sg:city":"Cleveland",
    "sg:classifiers":[
        {
            "category":"Wholesale",
            "subcategory":"Electrical",
            "type":"Manufacturing & Wholesale Goods"
        }
    ],
    "sg:phone":"+1 216 251 2955",
    "sg:postcode":"44111",
    "sg:province":"OH",
    "sg:tags":[
        "control",
        "security",
        "system"
    ],
    "wof:name":"C W Security & Tlcmmnctns",
    "wof:placetype":"venue"
},
  "geometry": {"coordinates":[-81.815425,41.450546],"type":"Point"}
}