{
  "type": "Feature",
  "properties": {
    "addr:full":"81 N Adams St Akron OH 44304",
    "addr:housenumber":"81",
    "addr:postcode":"44304",
    "addr:street":"N Adams St",
    "iso:country":"US",
    "sg:address":"81 N Adams St",
    "sg:city":"Akron",
    "sg:classifiers":[
        {
            "category":"Shopping",
            "subcategory":"Used Merchandise",
            "type":"Retail Goods"
        },
        {
            "category":"Home & Garden",
            "subcategory":"Household Appliances",
            "type":"Retail Goods"
        }
    ],
    "sg:phone":"+1 330 376 5985",
    "sg:postcode":"44304",
    "sg:province":"OH",
    "wof:name":"Sam's Appliance",
    "wof:placetype":"venue"
},
  "geometry": {"coordinates":[-81.498457,41.079031],"type":"Point"}
}