{
  "type": "Feature",
  "properties": {
    "iso:country":"US",
    "sg:address":"1711 Sawmill Pkwy",
    "sg:city":"Huron",
    "sg:classifiers":[
        {
            "category":"Freight",
            "type":"Transportation"
        }
    ],
    "sg:phone":"+1 419 433 9693",
    "sg:postcode":"44839",
    "sg:province":"OH",
    "wof:name":"TNT Logistics",
    "wof:placetype":"venue"
},
  "geometry": {"coordinates":[-82.584433,41.400103],"type":"Point"}
}