{
  "type": "Feature",
  "properties": {
    "iso:country":"US",
    "sg:address":"1818 W 3rd St",
    "sg:city":"Dayton",
    "sg:classifiers":[
        {
            "category":"Freight",
            "type":"Transportation"
        }
    ],
    "sg:phone":"+1 937 268 2303",
    "sg:postcode":"45417",
    "sg:province":"OH",
    "sg:tags":[
        "general"
    ],
    "wof:name":"Dudley Warehouse Distributing",
    "wof:placetype":"venue"
},
  "geometry": {"coordinates":[-84.224436,39.754084],"type":"Point"}
}