{
  "type": "Feature",
  "properties": {
    "iso:country":"US",
    "sg:address":"3520 Brecksville Rd",
    "sg:city":"Richfield",
    "sg:classifiers":[
        {
            "category":"Retail",
            "subcategory":"Auto Repair",
            "type":"Services"
        }
    ],
    "sg:phone":"+1 330 659 3306",
    "sg:postcode":"44286",
    "sg:province":"OH",
    "sg:tags":[
        "body",
        "automobile",
        "painting"
    ],
    "wof:name":"Nick's Automotive Shop Inc",
    "wof:placetype":"venue"
},
  "geometry": {"coordinates":[-81.63796600000001,41.235953],"type":"Point"}
}