{
  "type": "Feature",
  "properties": {
    "iso:country":"US",
    "sg:address":"128 Perry St",
    "sg:city":"Sandusky",
    "sg:classifiers":[
        {
            "category":"Real Estate",
            "subcategory":"Real Estate Operator",
            "type":"Services"
        }
    ],
    "sg:phone":"+1 419 625 3361",
    "sg:postcode":"44870",
    "sg:province":"OH",
    "sg:tags":[
        "apartment"
    ],
    "wof:name":"Bayshore Towers",
    "wof:placetype":"venue"
},
  "geometry": {"coordinates":[-82.70454599999999,41.460147],"type":"Point"}
}