{
  "type": "Feature",
  "properties": {
    "iso:country":"US",
    "sg:address":"1990 Grand Ave",
    "sg:city":"Cincinnati",
    "sg:classifiers":[
        {
            "category":"Manufacturing",
            "subcategory":"Metals",
            "type":"Manufacturing & Wholesale Goods"
        }
    ],
    "sg:phone":"+1 513 471 7010",
    "sg:postcode":"45214",
    "sg:province":"OH",
    "sg:tags":[
        "finisher"
    ],
    "wof:name":"A & B Deburring Co",
    "wof:placetype":"venue"
},
  "geometry": {"coordinates":[-84.556299,39.12071],"type":"Point"}
}