{
  "type": "Feature",
  "properties": {
    "addr:full": "1990 Grand Ave Cincinnati OH 45214",
    "addr:housenumber": "1990",
    "addr:postcode": "45214",
    "addr:street": "Grand Ave",
    "iso:country": "US",
    "sg:address": "1990 Grand Ave",
    "sg:city": "Cincinnati",
    "sg:classifiers": [
      {
        "category": "Manufacturing",
        "subcategory": "Metals",
        "type": "Manufacturing \u0026 Wholesale Goods"
      }
    ],
    "sg:phone": "+1 513 471 7010",
    "sg:postcode": "45214",
    "sg:province": "OH",
    "sg:tags": [
      "finisher"
    ],
    "wof:name": "A \u0026 B Deburring Co",
    "wof:placetype": "venue"
  },
  "geometry": {"coordinates":[-84.556299,39.12071],"type":"Point"}
}
