{
  "type": "Feature",
  "properties": {
    "iso:country":"US",
    "sg:address":"1351 Cunard Rd",
    "sg:city":"Columbus",
    "sg:classifiers":[
        {
            "category":"Professional",
            "subcategory":"Management & Consulting",
            "type":"Services"
        }
    ],
    "sg:phone":"+1 614 237 5541",
    "sg:postcode":"43227",
    "sg:province":"OH",
    "sg:tags":[
        "personnel",
        "consultant"
    ],
    "wof:name":"Medical Search Consultants",
    "wof:placetype":"venue"
},
  "geometry": {"coordinates":[-82.902483,39.944887],"type":"Point"}
}