{
  "type": "Feature",
  "properties": {
    "iso:country":"US",
    "sg:address":"6981 Southern Blvd",
    "sg:city":"Youngstown",
    "sg:classifiers":[
        {
            "category":"Professional",
            "subcategory":"Computer Services",
            "type":"Services"
        }
    ],
    "sg:phone":"+1 330 629 2691",
    "sg:postcode":"44512",
    "sg:province":"OH",
    "sg:tags":[
        "internet"
    ],
    "sg:website":"www.cisnet.com",
    "wof:name":"Comprehensive Internet Svc",
    "wof:placetype":"venue"
},
  "geometry": {"coordinates":[-80.65622,41.028766],"type":"Point"}
}