{
  "type": "Feature",
  "properties": {
    "addr:full": "180 High St Wadsworth OH 44281",
    "addr:housenumber": "180",
    "addr:postcode": "44281",
    "addr:street": "High St",
    "iso:country": "US",
    "sg:address": "180 High St",
    "sg:city": "Wadsworth",
    "sg:classifiers": [
      {
        "category": "Health Services",
        "subcategory": "Doctor",
        "type": "Services"
      }
    ],
    "sg:phone": "+1 330 334 1603",
    "sg:postcode": "44281",
    "sg:province": "OH",
    "sg:tags": [
      "physician",
      "surgeon"
    ],
    "wof:name": "Jyoti S Deoras MD",
    "wof:placetype": "venue"
  },
  "geometry": {"coordinates":[-81.729757,41.02752],"type":"Point"}
}
