{
  "type": "Feature",
  "properties": {
    "iso:country":"US",
    "sg:address":"180 High St",
    "sg:city":"Wadsworth",
    "sg:classifiers":[
        {
            "category":"Health Services",
            "subcategory":"Doctor",
            "type":"Services"
        }
    ],
    "sg:phone":"+1 330 334 1603",
    "sg:postcode":"44281",
    "sg:province":"OH",
    "sg:tags":[
        "physician",
        "surgeon"
    ],
    "wof:name":"Jyoti S Deoras MD",
    "wof:placetype":"venue"
},
  "geometry": {"coordinates":[-81.72975700000001,41.02752],"type":"Point"}
}