{
  "type": "Feature",
  "properties": {
    "iso:country":"US",
    "sg:address":"3956 Alvacardo Rd",
    "sg:city":"Canfield",
    "sg:classifiers":[
        {
            "category":"Shopping",
            "subcategory":"Bicycles & Sporting Goods",
            "type":"Retail Goods"
        }
    ],
    "sg:phone":"+1 330 793 0323",
    "sg:postcode":"44406",
    "sg:province":"OH",
    "wof:name":"Bobs Shop",
    "wof:placetype":"venue"
},
  "geometry": {"coordinates":[-80.719459,41.056168],"type":"Point"}
}