{
  "type": "Feature",
  "properties": {
    "addr:full": "26094 Royalton Rd Columbia Station OH 44028",
    "addr:housenumber": "26094",
    "addr:postcode": "44028",
    "addr:street": "Royalton Rd",
    "iso:country": "US",
    "sg:address": "26094 Royalton Rd",
    "sg:city": "Columbia Station",
    "sg:classifiers": [
      {
        "category": "Building \u0026 Trades",
        "subcategory": "Construction",
        "type": "Services"
      }
    ],
    "sg:phone": "+1 440 236 5594",
    "sg:postcode": "44028",
    "sg:province": "OH",
    "sg:tags": [
      "excavation",
      "operator",
      "contractor",
      "local",
      "trucking"
    ],
    "wof:name": "Edward A Smith Construction",
    "wof:placetype": "venue"
  },
  "geometry": {"coordinates":[-81.926145,41.312785],"type":"Point"}
}
