{
  "type": "Feature",
  "properties": {
    "iso:country":"US",
    "sg:address":"26094 Royalton Rd",
    "sg:city":"Columbia Station",
    "sg:classifiers":[
        {
            "category":"Building & Trades",
            "subcategory":"Construction",
            "type":"Services"
        }
    ],
    "sg:phone":"+1 440 236 5594",
    "sg:postcode":"44028",
    "sg:province":"OH",
    "sg:tags":[
        "excavation",
        "operator",
        "contractor",
        "local",
        "trucking"
    ],
    "wof:name":"Edward A Smith Construction",
    "wof:placetype":"venue"
},
  "geometry": {"coordinates":[-81.92614500000001,41.312785],"type":"Point"}
}