{
  "type": "Feature",
  "properties": {
    "addr:full": "7923 Munson Rd Mentor OH 44060",
    "addr:housenumber": "7923",
    "addr:postcode": "44060",
    "addr:street": "Munson Rd",
    "iso:country": "US",
    "sg:address": "7923 Munson Rd",
    "sg:city": "Mentor",
    "sg:classifiers": [
      {
        "category": "Banks \u0026 Credit Unions",
        "subcategory": "Bank",
        "type": "Services"
      }
    ],
    "sg:phone": "+1 440 257 6231",
    "sg:postcode": "44060",
    "sg:province": "OH",
    "sg:tags": [
      "national",
      "commercial"
    ],
    "wof:name": "Charter One",
    "wof:placetype": "venue"
  },
  "geometry": {"coordinates":[-81.356281,41.705131],"type":"Point"}
}
