{
  "type": "Feature",
  "properties": {
    "addr:full":"12 W Wenger Rd Englewood OH 45322",
    "addr:housenumber":"12",
    "addr:postcode":"45322",
    "addr:street":"W Wenger Rd",
    "iso:country":"US",
    "sg:address":"12 W Wenger Rd",
    "sg:city":"Englewood",
    "sg:classifiers":[
        {
            "category":"Professional",
            "type":"Services"
        }
    ],
    "sg:phone":"+1 937 832 4120",
    "sg:postcode":"45322",
    "sg:province":"OH",
    "sg:tags":[
        "establishment"
    ],
    "sg:website":"www.eastway.org",
    "wof:name":"Fiscal",
    "wof:placetype":"venue"
},
  "geometry": {"coordinates":[-84.287862,39.86217],"type":"Point"}
}