{
  "type": "Feature",
  "properties": {
    "iso:country":"US",
    "sg:address":"100 N Main St",
    "sg:city":"Chagrin Falls",
    "sg:classifiers":[
        {
            "category":"Professional",
            "subcategory":"Lawyer & Legal Services",
            "type":"Services"
        }
    ],
    "sg:phone":"+1 440 247 4765",
    "sg:postcode":"44022",
    "sg:province":"OH",
    "wof:name":"Fried Lorna J Atty",
    "wof:placetype":"venue"
},
  "geometry": {"coordinates":[-81.392155,41.432963],"type":"Point"}
}