{
  "type": "Feature",
  "properties": {
    "addr:full":"1646 Fairwood Ave Columbus OH 43206",
    "addr:housenumber":"1646",
    "addr:postcode":"43206",
    "addr:street":"Fairwood Ave",
    "iso:country":"US",
    "sg:address":"1646 Fairwood Ave",
    "sg:city":"Columbus",
    "sg:classifiers":[
        {
            "category":"Manufacturing",
            "subcategory":"Metals",
            "type":"Manufacturing & Wholesale Goods"
        }
    ],
    "sg:phone":"+1 614 443 7635",
    "sg:postcode":"43206",
    "sg:province":"OH",
    "sg:tags":[
        "machine",
        "screw",
        "product",
        "mfg"
    ],
    "wof:name":"H & E Machine Company",
    "wof:placetype":"venue"
},
  "geometry": {"coordinates":[-82.955004,39.932906],"type":"Point"}
}