{
  "type": "Feature",
  "properties": {
    "addr:full":"3611 Rocky River Dr Cleveland OH 44111",
    "addr:housenumber":"3611",
    "addr:postcode":"44111",
    "addr:street":"Rocky River Dr",
    "iso:country":"US",
    "sg:address":"3611 Rocky River Dr",
    "sg:city":"Cleveland",
    "sg:classifiers":[
        {
            "category":"Wholesale",
            "subcategory":"Scrap",
            "type":"Manufacturing & Wholesale Goods"
        }
    ],
    "sg:phone":"+1 216 671 1935",
    "sg:postcode":"44111",
    "sg:province":"OH",
    "sg:tags":[
        "recycling",
        "center"
    ],
    "wof:name":"Global Lake Enterprise",
    "wof:placetype":"venue"
},
  "geometry": {"coordinates":[-81.81572,41.454405],"type":"Point"}
}