{
  "type": "Feature",
  "properties": {
    "addr:full": "84 W Franklin St Centerville OH 45459",
    "addr:housenumber": "84",
    "addr:postcode": "45459",
    "addr:street": "W Franklin St",
    "iso:country": "US",
    "sg:address": "84 W Franklin St",
    "sg:city": "Centerville",
    "sg:classifiers": [
      {
        "category": "Retail",
        "subcategory": "Repair Shop",
        "type": "Services"
      }
    ],
    "sg:phone": "+1 937 433 4666",
    "sg:postcode": "45459",
    "sg:province": "OH",
    "sg:tags": [
      "lock",
      "alarm",
      "safety",
      "locksmith"
    ],
    "wof:name": "Centerville Lock \u0026 Safe",
    "wof:placetype": "venue"
  },
  "geometry": {"coordinates":[-84.163519,39.628195],"type":"Point"}
}
