{
  "type": "Feature",
  "properties": {
    "addr:full":"2804 Conestoga St Springfield OH 45503",
    "addr:housenumber":"2804",
    "addr:postcode":"45503",
    "addr:street":"Conestoga St",
    "iso:country":"US",
    "sg:address":"2804 Conestoga St",
    "sg:city":"Springfield",
    "sg:classifiers":[
        {
            "category":"Shopping",
            "subcategory":"Bicycles & Sporting Goods",
            "type":"Retail Goods"
        }
    ],
    "sg:phone":"+1 937 399 6986",
    "sg:postcode":"45503",
    "sg:province":"OH",
    "wof:name":"Altrntv Sports Sply",
    "wof:placetype":"venue"
},
  "geometry": {"coordinates":[-83.764651,39.961365],"type":"Point"}
}