{
  "type": "Feature",
  "properties": {
    "addr:full": "94 S Plains Rd The Plains OH 45780",
    "addr:housenumber": "94",
    "addr:postcode": "45780",
    "addr:street": "S Plains Rd",
    "iso:country": "US",
    "sg:address": "94 S Plains Rd",
    "sg:city": "The Plains",
    "sg:classifiers": [
      {
        "category": "Professional",
        "subcategory": "Lawyer \u0026 Legal Services",
        "type": "Services"
      }
    ],
    "sg:phone": "+1 740 797 2411",
    "sg:postcode": "45780",
    "sg:province": "OH",
    "sg:tags": [
      "attorney"
    ],
    "wof:name": "Robert J Dodd Jr Co",
    "wof:placetype": "venue"
  },
  "geometry": {"coordinates":[-82.130642,39.363777],"type":"Point"}
}
