{
  "type": "Feature",
  "properties": {
    "addr:full": "4539 Todd Rd Franklin OH 45005",
    "addr:housenumber": "4539",
    "addr:postcode": "45005",
    "addr:street": "Todd Rd",
    "iso:country": "US",
    "sg:address": "4539 Todd Rd",
    "sg:city": "Franklin",
    "sg:classifiers": [
      {
        "category": "Retail",
        "subcategory": "Laundry \u0026 Dry Cleaning",
        "type": "Services"
      }
    ],
    "sg:phone": "+1 937 743 5834",
    "sg:postcode": "45005",
    "sg:province": "OH",
    "sg:tags": [
      "cleaners",
      "rug",
      "carpet"
    ],
    "wof:name": "C \u0026 J Spotless Carpet Cleaning",
    "wof:placetype": "venue"
  },
  "geometry": {"coordinates":[-84.288794,39.495903],"type":"Point"}
}
