{
  "type": "Feature",
  "properties": {
    "iso:country":"US",
    "sg:address":"4512 Warren-Sharon Rd",
    "sg:city":"Vienna",
    "sg:classifiers":[
        {
            "category":"Home & Garden",
            "subcategory":"Garden Supply",
            "type":"Retail Goods"
        }
    ],
    "sg:phone":"+1 330 394 2400",
    "sg:postcode":"44473",
    "sg:province":"OH",
    "sg:tags":[
        "lawn",
        "mower"
    ],
    "wof:name":"Vienna Hardware Inc",
    "wof:placetype":"venue"
},
  "geometry": {"coordinates":[-80.653547,41.237687],"type":"Point"}
}