{
  "type": "Feature",
  "properties": {
    "addr:full":"3665 Villa Rosa Dr Canfield OH 44406",
    "addr:housenumber":"3665",
    "addr:postcode":"44406",
    "addr:street":"Villa Rosa Dr",
    "iso:country":"US",
    "sg:address":"3665 Villa Rosa Dr",
    "sg:city":"Canfield",
    "sg:classifiers":[
        {
            "category":"Building & Trades",
            "subcategory":"Construction",
            "type":"Services"
        }
    ],
    "sg:phone":"+1 330 533 7916",
    "sg:postcode":"44406",
    "sg:province":"OH",
    "sg:tags":[
        "house"
    ],
    "wof:name":"Ramunno Builders Inc",
    "wof:placetype":"venue"
},
  "geometry": {"coordinates":[-80.71294899999999,41.041031],"type":"Point"}
}