{
  "type": "Feature",
  "properties": {
    "addr:full": "1629 W Lane Ave Columbus OH 43221",
    "addr:housenumber": "1629",
    "addr:postcode": "43221",
    "addr:street": "W Lane Ave",
    "iso:country": "US",
    "sg:address": "1629 W Lane Ave",
    "sg:city": "Columbus",
    "sg:classifiers": [
      {
        "category": "Shopping",
        "subcategory": "Shoes",
        "type": "Retail Goods"
      }
    ],
    "sg:phone": "+1 614 481 8120",
    "sg:postcode": "43221",
    "sg:province": "OH",
    "wof:name": "Ecco Shoes",
    "wof:placetype": "venue"
  },
  "geometry": {"coordinates":[-83.05256,40.007044],"type":"Point"}
}
