{
  "type": "Feature",
  "properties": {
    "iso:country":"US",
    "sg:address":"320 Lincoln Way E",
    "sg:city":"Massillon",
    "sg:classifiers":[
        {
            "category":"Real Estate",
            "subcategory":"Real Estate Agent",
            "type":"Services"
        }
    ],
    "sg:phone":"+1 330 833 8847",
    "sg:postcode":"44646",
    "sg:province":"OH",
    "wof:name":"Matie Real Estate Inc",
    "wof:placetype":"venue"
},
  "geometry": {"coordinates":[-81.51831799999999,40.797904],"type":"Point"}
}