{
  "type": "Feature",
  "properties": {
    "iso:country":"US",
    "sg:address":"387 Medina Rd",
    "sg:city":"Medina",
    "sg:classifiers":[
        {
            "category":"Real Estate",
            "subcategory":"Real Estate Services",
            "type":"Services"
        }
    ],
    "sg:phone":"+1 330 725 3489",
    "sg:postcode":"44256",
    "sg:province":"OH",
    "sg:tags":[
        "company",
        "abstract",
        "title"
    ],
    "wof:name":"Title First Agency Inc",
    "wof:placetype":"venue"
},
  "geometry": {"coordinates":[-81.700022,41.136088],"type":"Point"}
}