{
  "type": "Feature",
  "properties": {
    "iso:country":"US",
    "sg:address":"765 Aldengate Dr",
    "sg:city":"Galloway",
    "sg:classifiers":[
        {
            "category":"Wholesale",
            "subcategory":"Machinery & Supplies",
            "type":"Manufacturing & Wholesale Goods"
        }
    ],
    "sg:phone":"+1 614 870 7474",
    "sg:postcode":"43119",
    "sg:province":"OH",
    "sg:tags":[
        "equipment",
        "industrial"
    ],
    "wof:name":"Professional Automation",
    "wof:placetype":"venue"
},
  "geometry": {"coordinates":[-83.16543900000001,39.965725],"type":"Point"}
}