{
  "type": "Feature",
  "properties": {
    "addr:full": "765 Aldengate Dr Galloway OH 43119",
    "addr:housenumber": "765",
    "addr:postcode": "43119",
    "addr:street": "Aldengate Dr",
    "iso:country": "US",
    "sg:address": "765 Aldengate Dr",
    "sg:city": "Galloway",
    "sg:classifiers": [
      {
        "category": "Wholesale",
        "subcategory": "Machinery \u0026 Supplies",
        "type": "Manufacturing \u0026 Wholesale Goods"
      }
    ],
    "sg:phone": "+1 614 870 7474",
    "sg:postcode": "43119",
    "sg:province": "OH",
    "sg:tags": [
      "equipment",
      "industrial"
    ],
    "wof:name": "Professional Automation",
    "wof:placetype": "venue"
  },
  "geometry": {"coordinates":[-83.165439,39.965725],"type":"Point"}
}
