{
  "type": "Feature",
  "properties": {
    "addr:full": "473 Brown St Akron OH 44311",
    "addr:housenumber": "473",
    "addr:postcode": "44311",
    "addr:street": "Brown St",
    "iso:country": "US",
    "sg:address": "473 Brown St",
    "sg:city": "Akron",
    "sg:classifiers": [
      {
        "category": "Real Estate",
        "subcategory": "Real Estate Agent",
        "type": "Services"
      }
    ],
    "sg:phone": "+1 330 376 5514",
    "sg:postcode": "44311",
    "sg:province": "OH",
    "sg:tags": [
      "manager",
      "industrial",
      "commercial"
    ],
    "wof:name": "Asw Properties Ltd",
    "wof:placetype": "venue"
  },
  "geometry": {"coordinates":[-81.509708,41.069837],"type":"Point"}
}
