{
  "type": "Feature",
  "properties": {
    "iso:country":"US",
    "sg:address":"4755 Laurel Rd",
    "sg:city":"Brunswick",
    "sg:classifiers":[
        {
            "category":"Building & Trades",
            "subcategory":"Construction",
            "type":"Services"
        }
    ],
    "sg:phone":"+1 330 225 6658",
    "sg:postcode":"44212",
    "sg:province":"OH",
    "sg:tags":[
        "residential"
    ],
    "wof:name":"ONeill & Sons Construction",
    "wof:placetype":"venue"
},
  "geometry": {"coordinates":[-81.856082,41.226703],"type":"Point"}
}