{
  "type": "Feature",
  "properties": {
    "addr:full": "4755 Laurel Rd Brunswick OH 44212",
    "addr:housenumber": "4755",
    "addr:postcode": "44212",
    "addr:street": "Laurel Rd",
    "iso:country": "US",
    "sg:address": "4755 Laurel Rd",
    "sg:city": "Brunswick",
    "sg:classifiers": [
      {
        "category": "Building \u0026 Trades",
        "subcategory": "Construction",
        "type": "Services"
      }
    ],
    "sg:phone": "+1 330 225 6658",
    "sg:postcode": "44212",
    "sg:province": "OH",
    "sg:tags": [
      "residential"
    ],
    "wof:name": "ONeill \u0026 Sons Construction",
    "wof:placetype": "venue"
  },
  "geometry": {"coordinates":[-81.856082,41.226703],"type":"Point"}
}
