{
  "type": "Feature",
  "properties": {
    "addr:full":"6513 Blickling Dr Dublin OH 43017",
    "addr:housenumber":"6513",
    "addr:postcode":"43017",
    "addr:street":"Blickling Dr",
    "iso:country":"US",
    "sg:address":"6513 Blickling Dr",
    "sg:city":"Dublin",
    "sg:classifiers":[
        {
            "category":"Insurance",
            "subcategory":"Insurance Agent",
            "type":"Services"
        }
    ],
    "sg:phone":"+1 614 336 7723",
    "sg:postcode":"43017",
    "sg:province":"OH",
    "sg:tags":[
        "processing"
    ],
    "wof:name":"FCCI Insurance Group",
    "wof:placetype":"venue"
},
  "geometry": {"coordinates":[-83.10767800000001,40.086931],"type":"Point"}
}