{
  "type": "Feature",
  "properties": {
    "addr:full":"3646 E 112th St Cleveland OH 44105",
    "addr:housenumber":"3646",
    "addr:postcode":"44105",
    "addr:street":"E 112Th St",
    "iso:country":"US",
    "sg:address":"3646 E 112th St",
    "sg:city":"Cleveland",
    "sg:classifiers":[
        {
            "category":"Professional",
            "subcategory":"Management & Consulting",
            "type":"Services"
        }
    ],
    "sg:phone":"+1 440 439 4167",
    "sg:postcode":"44105",
    "sg:province":"OH",
    "sg:tags":[
        "business"
    ],
    "wof:name":"New Beginnings",
    "wof:placetype":"venue"
},
  "geometry": {"coordinates":[-81.60609700000001,41.460405],"type":"Point"}
}