{
  "type": "Feature",
  "properties": {
    "addr:full": "2407 Gilbert Ave Cincinnati OH 45206",
    "addr:housenumber": "2407",
    "addr:postcode": "45206",
    "addr:street": "Gilbert Ave",
    "iso:country": "US",
    "sg:address": "2407 Gilbert Ave",
    "sg:city": "Cincinnati",
    "sg:classifiers": [
      {
        "category": "Personal",
        "subcategory": "Beauty Salon",
        "type": "Services"
      }
    ],
    "sg:phone": "+1 513 751 1300",
    "sg:postcode": "45206",
    "sg:province": "OH",
    "wof:name": "Right Cut",
    "wof:placetype": "venue"
  },
  "geometry": {"coordinates":[-84.491012,39.124867],"type":"Point"}
}
