{
  "type": "Feature",
  "properties": {
    "iso:country":"US",
    "sg:address":"519 Oakwood Ave",
    "sg:city":"Lancaster",
    "sg:classifiers":[
        {
            "category":"Shopping",
            "subcategory":"Bicycles & Sporting Goods",
            "type":"Retail Goods"
        }
    ],
    "sg:phone":"+1 740 689 1121",
    "sg:postcode":"43130",
    "sg:province":"OH",
    "sg:tags":[
        "equipment",
        "skateboard"
    ],
    "wof:name":"Project 21",
    "wof:placetype":"venue"
},
  "geometry": {"coordinates":[-82.584663,39.719165],"type":"Point"}
}