{
  "type": "Feature",
  "properties": {
    "iso:country":"US",
    "sg:address":"521 Tuscarawas St W",
    "sg:city":"Canton",
    "sg:classifiers":[
        {
            "category":"Education",
            "subcategory":"School",
            "type":"Public Place"
        }
    ],
    "sg:phone":"+1 330 438 2607",
    "sg:postcode":"44702",
    "sg:province":"OH",
    "sg:website":"www.ccsdistrict.org",
    "wof:name":"Timken Senior High School",
    "wof:placetype":"venue"
},
  "geometry": {"coordinates":[-81.379047,40.799386],"type":"Point"}
}