{
  "type": "Feature",
  "properties": {
    "iso:country":"US",
    "sg:address":"143 E Franklin St",
    "sg:city":"Dayton",
    "sg:classifiers":[
        {
            "category":"Shopping",
            "type":"Retail Goods"
        }
    ],
    "sg:phone":"+1 937 436 6093",
    "sg:postcode":"45459",
    "sg:province":"OH",
    "sg:tags":[
        "merchandise"
    ],
    "wof:name":"Hedge Systems",
    "wof:placetype":"venue"
},
  "geometry": {"coordinates":[-84.155784,39.628597],"type":"Point"}
}