{
  "type": "Feature",
  "properties": {
    "addr:full": "208 Locust St Cincinnati OH 45215",
    "addr:housenumber": "208",
    "addr:postcode": "45215",
    "addr:street": "Locust St",
    "iso:country": "US",
    "sg:address": "208 Locust St",
    "sg:city": "Cincinnati",
    "sg:classifiers": [
      {
        "category": "Organizations",
        "subcategory": "Religious Organization",
        "type": "Services"
      }
    ],
    "sg:phone": "+1 513 821 9337",
    "sg:postcode": "45215",
    "sg:province": "OH",
    "sg:tags": [
      "church"
    ],
    "wof:name": "Burress Temple Church Of God",
    "wof:placetype": "venue"
  },
  "geometry": {"coordinates":[-84.462608,39.228851],"type":"Point"}
}
