{
  "type": "Feature",
  "properties": {
    "iso:country":"US",
    "sg:address":"208 Locust St",
    "sg:city":"Cincinnati",
    "sg:classifiers":[
        {
            "category":"Organizations",
            "subcategory":"Religious Organization",
            "type":"Services"
        }
    ],
    "sg:phone":"+1 513 821 9337",
    "sg:postcode":"45215",
    "sg:province":"OH",
    "sg:tags":[
        "church"
    ],
    "wof:name":"Burress Temple Church Of God",
    "wof:placetype":"venue"
},
  "geometry": {"coordinates":[-84.462608,39.228851],"type":"Point"}
}