{
  "type": "Feature",
  "properties": {
    "addr:full": "4700 Rockside Rd Cleveland OH 44131",
    "addr:housenumber": "4700",
    "addr:postcode": "44131",
    "addr:street": "Rockside Rd",
    "iso:country": "US",
    "sg:address": "4700 Rockside Rd",
    "sg:city": "Cleveland",
    "sg:classifiers": [
      {
        "category": "Manufacturing",
        "subcategory": "Printing",
        "type": "Manufacturing \u0026 Wholesale Goods"
      }
    ],
    "sg:phone": "+1 216 901 1485",
    "sg:postcode": "44131",
    "sg:province": "OH",
    "sg:tags": [
      "multimedia"
    ],
    "wof:name": "Media Webcasters",
    "wof:placetype": "venue"
  },
  "geometry": {"coordinates":[-81.656622,41.397699],"type":"Point"}
}
