{
  "type": "Feature",
  "properties": {
    "iso:country":"US",
    "sg:address":"720 W Martindale Rd",
    "sg:city":"Englewood",
    "sg:classifiers":[
        {
            "category":"Real Estate",
            "subcategory":"Real Estate Agent",
            "type":"Services"
        }
    ],
    "sg:phone":"+1 937 836 7277",
    "sg:postcode":"45322",
    "sg:province":"OH",
    "wof:name":"William J Conners Realtor",
    "wof:placetype":"venue"
},
  "geometry": {"coordinates":[-84.329248,39.897331],"type":"Point"}
}