{
  "type": "Feature",
  "properties": {
    "addr:full":"2408 E 30th St Lorain OH 44055",
    "addr:housenumber":"2408",
    "addr:postcode":"44055",
    "addr:street":"E 30Th St",
    "iso:country":"US",
    "sg:address":"2408 E 30th St",
    "sg:city":"Lorain",
    "sg:classifiers":[
        {
            "category":"Building & Trades",
            "subcategory":"Construction",
            "type":"Services"
        }
    ],
    "sg:phone":"+1 440 240 1209",
    "sg:postcode":"44055",
    "sg:province":"OH",
    "sg:tags":[
        "house"
    ],
    "wof:name":"D & P Roofing Company",
    "wof:placetype":"venue"
},
  "geometry": {"coordinates":[-82.112824,41.443709],"type":"Point"}
}