{
  "type": "Feature",
  "properties": {
    "addr:full":"55 Atterbury Blvd Hudson OH 44236",
    "addr:housenumber":"55",
    "addr:postcode":"44236",
    "addr:street":"Atterbury Blvd",
    "iso:country":"US",
    "sg:address":"55 Atterbury Blvd",
    "sg:city":"Hudson",
    "sg:classifiers":[
        {
            "category":"Organizations",
            "subcategory":"Religious Organization",
            "type":"Services"
        }
    ],
    "sg:phone":"+1 330 342 0429",
    "sg:postcode":"44236",
    "sg:province":"OH",
    "sg:tags":[
        "church"
    ],
    "wof:name":"Holy Trinity Anglican Church",
    "wof:placetype":"venue"
},
  "geometry": {"coordinates":[-81.44584999999999,41.240174],"type":"Point"}
}