{
  "type": "Feature",
  "properties": {
    "addr:full": "1205 Virginia Ave Cleveland OH 44107",
    "addr:housenumber": "1205",
    "addr:postcode": "44107",
    "addr:street": "Virginia Ave",
    "iso:country": "US",
    "sg:address": "1205 Virginia Ave",
    "sg:city": "Cleveland",
    "sg:classifiers": [
      {
        "category": "Professional",
        "type": "Services"
      },
      {
        "category": "Health Services",
        "subcategory": "Clinic",
        "type": "Services"
      }
    ],
    "sg:phone": "+1 216 227 1323",
    "sg:postcode": "44107",
    "sg:province": "OH",
    "sg:tags": [
      "managing",
      "home"
    ],
    "wof:name": "Maureen's Helping Hands Inc",
    "wof:placetype": "venue"
  },
  "geometry": {"coordinates":[-81.804794,41.489068],"type":"Point"}
}
