{
  "type": "Feature",
  "properties": {
    "addr:full": "6105 Detroit Ave Cleveland OH 44102",
    "addr:housenumber": "6105",
    "addr:postcode": "44102",
    "addr:street": "Detroit Ave",
    "iso:country": "US",
    "sg:address": "6105 Detroit Ave",
    "sg:city": "Cleveland",
    "sg:classifiers": [
      {
        "category": "Wholesale",
        "subcategory": "Meat",
        "type": "Manufacturing \u0026 Wholesale Goods"
      }
    ],
    "sg:phone": "+1 216 631 1414",
    "sg:postcode": "44102",
    "sg:province": "OH",
    "wof:name": "Gor-May Enterprises Inc",
    "wof:placetype": "venue"
  },
  "geometry": {"coordinates":[-81.727608,41.484749],"type":"Point"}
}
