{
  "type": "Feature",
  "properties": {
    "addr:full": "14812 Hametown Rd Doylestown OH 44230",
    "addr:housenumber": "14812",
    "addr:postcode": "44230",
    "addr:street": "Hametown Rd",
    "iso:country": "US",
    "sg:address": "14812 Hametown Rd",
    "sg:city": "Doylestown",
    "sg:classifiers": [
      {
        "category": "Wholesale",
        "subcategory": "Auto Parts",
        "type": "Manufacturing \u0026 Wholesale Goods"
      }
    ],
    "sg:phone": "+1 330 658 5560",
    "sg:postcode": "44230",
    "sg:province": "OH",
    "wof:name": "After Market Co",
    "wof:placetype": "venue"
  },
  "geometry": {"coordinates":[-81.666773,40.979246],"type":"Point"}
}
