{
  "type": "Feature",
  "properties": {
    "addr:full": "3574 E Kemper Rd Cincinnati OH 45241",
    "addr:housenumber": "3574",
    "addr:postcode": "45241",
    "addr:street": "E Kemper Rd",
    "iso:country": "US",
    "sg:address": "3574 E Kemper Rd",
    "sg:city": "Cincinnati",
    "sg:classifiers": [
      {
        "category": "Wholesale",
        "subcategory": "Furniture",
        "type": "Manufacturing \u0026 Wholesale Goods"
      }
    ],
    "sg:phone": "+1 513 769 4070",
    "sg:postcode": "45241",
    "sg:province": "OH",
    "wof:name": "Office Furniture Cntr",
    "wof:placetype": "venue"
  },
  "geometry": {"coordinates":[-84.406573,39.283134],"type":"Point"}
}
