{
  "type": "Feature",
  "properties": {
    "addr:full": "6645 Colerain Ave Cincinnati OH 45239",
    "addr:housenumber": "6645",
    "addr:postcode": "45239",
    "addr:street": "Colerain Ave",
    "iso:country": "US",
    "sg:address": "6645 Colerain Ave",
    "sg:city": "Cincinnati",
    "sg:classifiers": [
      {
        "category": "Professional",
        "subcategory": "Lawyer \u0026 Legal Services",
        "type": "Services"
      }
    ],
    "sg:phone": "+1 513 741 7888",
    "sg:postcode": "45239",
    "sg:province": "OH",
    "sg:tags": [
      "attorney"
    ],
    "wof:name": "Ronald C Harris",
    "wof:placetype": "venue"
  },
  "geometry": {"coordinates":[-84.583747,39.208532],"type":"Point"}
}
