{
  "type": "Feature",
  "properties": {
    "iso:country":"US",
    "sg:address":"5404 Columbus Pike",
    "sg:city":"Lewis Center",
    "sg:phone":"+1 740 548 6685",
    "sg:postcode":"43035",
    "sg:province":"OH",
    "sg:tags":[
        "gas"
    ],
    "wof:name":"Capitol Propane",
    "wof:placetype":"venue"
},
  "geometry": {"coordinates":[-83.03418000000001,40.217475],"type":"Point"}
}