{
  "type": "Feature",
  "properties": {
    "iso:country":"US",
    "sg:address":"2768 Bainbridge Ave",
    "sg:city":"Youngstown",
    "sg:classifiers":[
        {
            "category":"Building & Trades",
            "subcategory":"Construction",
            "type":"Services"
        }
    ],
    "sg:phone":"+1 330 792 4661",
    "sg:postcode":"44511",
    "sg:province":"OH",
    "sg:tags":[
        "roofing",
        "industrial",
        "contractors-commercial",
        "contractor"
    ],
    "wof:name":"Dp Williams Roofing Co",
    "wof:placetype":"venue"
},
  "geometry": {"coordinates":[-80.71948999999999,41.073015],"type":"Point"}
}