{
  "type": "Feature",
  "properties": {
    "addr:full": "2768 Bainbridge Ave Youngstown OH 44511",
    "addr:housenumber": "2768",
    "addr:postcode": "44511",
    "addr:street": "Bainbridge Ave",
    "iso:country": "US",
    "sg:address": "2768 Bainbridge Ave",
    "sg:city": "Youngstown",
    "sg:classifiers": [
      {
        "category": "Building \u0026 Trades",
        "subcategory": "Construction",
        "type": "Services"
      }
    ],
    "sg:phone": "+1 330 792 4661",
    "sg:postcode": "44511",
    "sg:province": "OH",
    "sg:tags": [
      "roofing",
      "industrial",
      "contractors-commercial",
      "contractor"
    ],
    "wof:name": "Dp Williams Roofing Co",
    "wof:placetype": "venue"
  },
  "geometry": {"coordinates":[-80.71949,41.073015],"type":"Point"}
}
