{
  "type": "Feature",
  "properties": {
    "iso:country":"US",
    "sg:address":"705 Lime City Rd",
    "sg:city":"Rossford",
    "sg:classifiers":[
        {
            "category":"Organizations",
            "subcategory":"Labor Organization",
            "type":"Services"
        }
    ],
    "sg:phone":"+1 419 666 3350",
    "sg:postcode":"43460",
    "sg:province":"OH",
    "wof:name":"Local 245 IBEW",
    "wof:placetype":"venue"
},
  "geometry": {"coordinates":[-83.567438,41.590422],"type":"Point"}
}