{
  "type": "Feature",
  "properties": {
    "addr:full":"3182 Maple Ave Zanesville OH 43701",
    "addr:housenumber":"3182",
    "addr:postcode":"43701",
    "addr:street":"Maple Ave",
    "iso:country":"US",
    "sg:address":"3182 Maple Ave",
    "sg:city":"Zanesville",
    "sg:classifiers":[
        {
            "category":"Wholesale",
            "subcategory":"Electrical",
            "type":"Manufacturing & Wholesale Goods"
        }
    ],
    "sg:phone":"+1 740 588 0279",
    "sg:postcode":"43701",
    "sg:province":"OH",
    "sg:tags":[
        "battery"
    ],
    "wof:name":"Unlimited Batteries",
    "wof:placetype":"venue"
},
  "geometry": {"coordinates":[-82.01772099999999,39.980448],"type":"Point"}
}