{
  "type": "Feature",
  "properties": {
    "iso:country":"US",
    "sg:address":"1116 N Reynolds Rd",
    "sg:city":"Toledo",
    "sg:classifiers":[
        {
            "category":"Local Transit",
            "type":"Transportation"
        }
    ],
    "sg:phone":"+1 419 535 7019",
    "sg:postcode":"43615",
    "sg:province":"OH",
    "sg:tags":[
        "passenger"
    ],
    "wof:name":"Childers Limousine Service",
    "wof:placetype":"venue"
},
  "geometry": {"coordinates":[-83.664573,41.65105],"type":"Point"}
}