{
  "type": "Feature",
  "properties": {
    "iso:country":"US",
    "sg:address":"310 Portland St",
    "sg:city":"Celina",
    "sg:classifiers":[
        {
            "category":"Shopping",
            "type":"Retail Goods"
        }
    ],
    "sg:phone":"+1 419 586 2946",
    "sg:postcode":"45822",
    "sg:province":"OH",
    "sg:tags":[
        "merchandise"
    ],
    "wof:name":"Pets-N-More",
    "wof:placetype":"venue"
},
  "geometry": {"coordinates":[-84.585341,40.546765],"type":"Point"}
}