{
  "type": "Feature",
  "properties": {
    "addr:full": "2339 Clermont Center Dr Batavia OH 45103",
    "addr:housenumber": "2339",
    "addr:postcode": "45103",
    "addr:street": "Clermont Center Dr",
    "iso:country": "US",
    "sg:address": "2339 Clermont Center Dr",
    "sg:city": "Batavia",
    "sg:classifiers": [
      {
        "category": "Government",
        "subcategory": "Office",
        "type": "Public Place"
      }
    ],
    "sg:phone": "+1 513 732 8001",
    "sg:postcode": "45103",
    "sg:province": "OH",
    "wof:name": "Clermont County Juvenile Prbtn",
    "wof:placetype": "venue"
  },
  "geometry": {"coordinates":[-84.144594,39.084051],"type":"Point"}
}
