{
  "type": "Feature",
  "properties": {
    "addr:full":"269 W High Ave New Philadelphia OH 44663",
    "addr:housenumber":"269",
    "addr:postcode":"44663",
    "addr:street":"W High Ave",
    "iso:country":"US",
    "sg:address":"269 W High Ave",
    "sg:city":"New Philadelphia",
    "sg:classifiers":[
        {
            "category":"Personal",
            "subcategory":"Beauty Salon",
            "type":"Services"
        }
    ],
    "sg:phone":"+1 330 339 6619",
    "sg:postcode":"44663",
    "sg:province":"OH",
    "sg:tags":[
        "shop"
    ],
    "wof:name":"Wallick's Hairstyling",
    "wof:placetype":"venue"
},
  "geometry": {"coordinates":[-81.44952600000001,40.490318],"type":"Point"}
}