{
  "type": "Feature",
  "properties": {
    "addr:full":"101 Linden Ave Dayton OH 45403",
    "addr:housenumber":"101",
    "addr:postcode":"45403",
    "addr:street":"Linden Ave",
    "iso:country":"US",
    "sg:address":"101 Linden Ave",
    "sg:city":"Dayton",
    "sg:classifiers":[
        {
            "category":"Organizations",
            "subcategory":"Non-profit Organization",
            "type":"Services"
        }
    ],
    "sg:phone":"+1 937 254 3637",
    "sg:postcode":"45403",
    "sg:province":"OH",
    "wof:name":"Campfire",
    "wof:placetype":"venue"
},
  "geometry": {"coordinates":[-84.162751,39.761255],"type":"Point"}
}