{
  "type": "Feature",
  "properties": {
    "iso:country":"US",
    "sg:address":"8144 Rd B",
    "sg:city":"Leipsic",
    "sg:classifiers":[
        {
            "category":"Professional",
            "type":"Services"
        }
    ],
    "sg:phone":"+1 419 943 3499",
    "sg:postcode":"45856",
    "sg:province":"OH",
    "sg:tags":[
        "establishment"
    ],
    "wof:name":"Schumacher Basinger Prtnrshp",
    "wof:placetype":"venue"
},
  "geometry": {"coordinates":[-84.017258,41.152437],"type":"Point"}
}