{
  "type": "Feature",
  "properties": {
    "iso:country":"US",
    "sg:address":"5717 Glenway Ave",
    "sg:city":"Cincinnati",
    "sg:classifiers":[
        {
            "category":"Banks & Credit Unions",
            "subcategory":"Bank",
            "type":"Services"
        }
    ],
    "sg:phone":"+1 513 661 5400",
    "sg:postcode":"45238",
    "sg:province":"OH",
    "sg:tags":[
        "cashing",
        "alternative",
        "loan",
        "check"
    ],
    "sg:website":"http://www.acecashexpress.com",
    "wof:name":"ACE Cash Express",
    "wof:placetype":"venue"
},
  "geometry": {"coordinates":[-84.61220400000001,39.134949],"type":"Point"}
}