{
  "type": "Feature",
  "properties": {
    "addr:full": "10 Sunnybrook Dr Cincinnati OH 45237",
    "addr:housenumber": "10",
    "addr:postcode": "45237",
    "addr:street": "Sunnybrook Dr",
    "iso:country": "US",
    "sg:address": "10 Sunnybrook Dr",
    "sg:city": "Cincinnati",
    "sg:classifiers": [
      {
        "category": "Professional",
        "subcategory": "Management \u0026 Consulting",
        "type": "Services"
      }
    ],
    "sg:phone": "+1 513 761 5131",
    "sg:postcode": "45237",
    "sg:province": "OH",
    "sg:tags": [
      "fuel"
    ],
    "wof:name": "Homelink Management",
    "wof:placetype": "venue"
  },
  "geometry": {"coordinates":[-84.455422,39.207168],"type":"Point"}
}
