{
  "type": "Feature",
  "properties": {
    "addr:full": "4066 E Harbor Rd Port Clinton OH 43452",
    "addr:housenumber": "4066 e",
    "addr:postcode": "43452",
    "addr:street": "Harbor Rd",
    "iso:country": "US",
    "sg:address": "4066 E Harbor Rd",
    "sg:city": "Port Clinton",
    "sg:classifiers": [
      {
        "category": "Shopping",
        "subcategory": "Clothing, Apparel, \u0026 Fashions",
        "type": "Retail Goods"
      }
    ],
    "sg:phone": "+1 419 734 3090",
    "sg:postcode": "43452",
    "sg:province": "OH",
    "sg:tags": [
      "store"
    ],
    "wof:name": "Fashion Bug",
    "wof:placetype": "venue"
  },
  "geometry": {"coordinates":[-82.854019,41.525667],"type":"Point"}
}
