{
  "type": "Feature",
  "properties": {
    "addr:full":"2105 Superior St Sandusky OH 44870",
    "addr:housenumber":"2105",
    "addr:postcode":"44870",
    "addr:street":"Superior St",
    "iso:country":"US",
    "sg:address":"2105 Superior St",
    "sg:city":"Sandusky",
    "sg:classifiers":[
        {
            "category":"Restaurant",
            "type":"Food & Drink"
        }
    ],
    "sg:phone":"+1 419 626 5757",
    "sg:postcode":"44870",
    "sg:province":"OH",
    "wof:name":"Decko Products Inc",
    "wof:placetype":"venue"
},
  "geometry": {"coordinates":[-82.743202,41.438599],"type":"Point"}
}