{
  "type": "Feature",
  "properties": {
    "iso:country":"US",
    "sg:address":"2455 Civic Center Dr",
    "sg:city":"Cincinnati",
    "sg:classifiers":[
        {
            "category":"Organizations",
            "subcategory":"Community Association",
            "type":"Services"
        }
    ],
    "sg:phone":"+1 513 851 7910",
    "sg:postcode":"45231",
    "sg:province":"OH",
    "sg:tags":[
        "club"
    ],
    "wof:name":"Hilltop Athletic Club",
    "wof:placetype":"venue"
},
  "geometry": {"coordinates":[-84.571949,39.277449],"type":"Point"}
}