{
  "type": "Feature",
  "properties": {
    "addr:full": "2455 Civic Center Dr Cincinnati OH 45231",
    "addr:housenumber": "2455",
    "addr:postcode": "45231",
    "addr:street": "Civic Center Dr",
    "iso:country": "US",
    "sg:address": "2455 Civic Center Dr",
    "sg:city": "Cincinnati",
    "sg:classifiers": [
      {
        "category": "Organizations",
        "subcategory": "Community Association",
        "type": "Services"
      }
    ],
    "sg:phone": "+1 513 851 7910",
    "sg:postcode": "45231",
    "sg:province": "OH",
    "sg:tags": [
      "club"
    ],
    "wof:name": "Hilltop Athletic Club",
    "wof:placetype": "venue"
  },
  "geometry": {"coordinates":[-84.571949,39.277449],"type":"Point"}
}
