{
  "type": "Feature",
  "properties": {
    "addr:full":"750 Cross Pointe Rd Columbus OH 43230",
    "addr:housenumber":"750",
    "addr:postcode":"43230",
    "addr:street":"Cross Pointe Rd",
    "iso:country":"US",
    "sg:address":"750 Cross Pointe Rd",
    "sg:city":"Columbus",
    "sg:classifiers":[
        {
            "category":"Manufacturing",
            "subcategory":"Tools & Machinery",
            "type":"Manufacturing & Wholesale Goods"
        }
    ],
    "sg:phone":"+1 614 863 3144",
    "sg:postcode":"43230",
    "sg:province":"OH",
    "sg:tags":[
        "grinder",
        "meat",
        "chopper"
    ],
    "sg:website":"www.wolfkinginc.com",
    "wof:name":"Convenient Food Systems",
    "wof:placetype":"venue"
},
  "geometry": {"coordinates":[-82.832072,40.001101],"type":"Point"}
}