{
  "type": "Feature",
  "properties": {
    "addr:full": "4590 Montgomery Rd Cincinnati OH 45212",
    "addr:housenumber": "4590",
    "addr:postcode": "45212",
    "addr:street": "Montgomery Rd",
    "iso:country": "US",
    "sg:address": "4590 Montgomery Rd",
    "sg:city": "Cincinnati",
    "sg:classifiers": [
      {
        "category": "Cinema",
        "subcategory": "Movie Rental",
        "type": "Entertainment"
      }
    ],
    "sg:phone": "+1 513 631 3000",
    "sg:postcode": "45212",
    "sg:province": "OH",
    "sg:tags": [
      "video",
      "tape"
    ],
    "wof:name": "Hollywood Video",
    "wof:placetype": "venue"
  },
  "geometry": {"coordinates":[-84.456598,39.15959],"type":"Point"}
}
