{
  "type": "Feature",
  "properties": {
    "addr:full": "8376 Rd B Leipsic OH 45856",
    "addr:housenumber": "8376",
    "addr:postcode": "45856",
    "addr:street": "Rd B Leipsic",
    "iso:country": "US",
    "sg:address": "8376 Rd B",
    "sg:city": "Leipsic",
    "sg:classifiers": [
      {
        "category": "Real Estate",
        "subcategory": "Real Estate Agent",
        "type": "Services"
      }
    ],
    "sg:phone": "+1 419 943 2220",
    "sg:postcode": "45856",
    "sg:province": "OH",
    "wof:name": "Nancy \u0026 Tom Frankart",
    "wof:placetype": "venue"
  },
  "geometry": {"coordinates":[-84.033351,41.152288],"type":"Point"}
}
