{
  "type": "Feature",
  "properties": {
    "addr:full":"975 W Main St Bellevue OH 44811",
    "addr:housenumber":"975",
    "addr:postcode":"44811",
    "addr:street":"W Main St",
    "iso:country":"US",
    "sg:address":"975 W Main St",
    "sg:city":"Bellevue",
    "sg:classifiers":[
        {
            "category":"Manufacturing",
            "subcategory":"Paper Products",
            "type":"Manufacturing & Wholesale Goods"
        }
    ],
    "sg:phone":"+1 419 483 4343",
    "sg:postcode":"44811",
    "sg:province":"OH",
    "sg:tags":[
        "packaging",
        "material"
    ],
    "wof:name":"Alcan Packaging",
    "wof:placetype":"venue"
},
  "geometry": {"coordinates":[-82.866592,41.280657],"type":"Point"}
}