{
  "type": "Feature",
  "properties": {
    "addr:full": "412 Church St Amherst OH 44001",
    "addr:housenumber": "412",
    "addr:postcode": "44001",
    "addr:street": "Church St",
    "iso:country": "US",
    "sg:address": "412 Church St",
    "sg:city": "Amherst",
    "sg:classifiers": [
      {
        "category": "Real Estate",
        "subcategory": "Real Estate Operator",
        "type": "Services"
      }
    ],
    "sg:phone": "+1 440 985 1505",
    "sg:postcode": "44001",
    "sg:province": "OH",
    "sg:tags": [
      "building",
      "nonresidential"
    ],
    "wof:name": "Cherant Properties LLC",
    "wof:placetype": "venue"
  },
  "geometry": {"coordinates":[-82.254069,41.354876],"type":"Point"}
}
