{
  "type": "Feature",
  "properties": {
    "addr:full":"36409 Mills Rd North Ridgeville OH 44039",
    "addr:housenumber":"36409",
    "addr:postcode":"44039",
    "addr:street":"Mills Rd",
    "iso:country":"US",
    "sg:address":"36409 Mills Rd",
    "sg:city":"North Ridgeville",
    "sg:classifiers":[
        {
            "category":"Building & Trades",
            "subcategory":"Construction",
            "type":"Services"
        }
    ],
    "sg:phone":"+1 440 934 2236",
    "sg:postcode":"44039",
    "sg:province":"OH",
    "sg:tags":[
        "contractor"
    ],
    "wof:name":"F & T Roofing",
    "wof:placetype":"venue"
},
  "geometry": {"coordinates":[-82.018716,41.4188],"type":"Point"}
}