{
  "type": "Feature",
  "properties": {
    "iso:country":"US",
    "sg:address":"1583 Alum Creek Dr",
    "sg:city":"Columbus",
    "sg:classifiers":[
        {
            "category":"Professional",
            "subcategory":"Detective & Security Services",
            "type":"Services"
        }
    ],
    "sg:phone":"+1 614 466 4790",
    "sg:postcode":"43209",
    "sg:province":"OH",
    "sg:tags":[
        "car"
    ],
    "wof:name":"Ohio State Patrol Crime L",
    "wof:placetype":"venue"
},
  "geometry": {"coordinates":[-82.942378,39.937009],"type":"Point"}
}