{
  "type": "Feature",
  "properties": {
    "addr:full": "1583 Alum Creek Dr Columbus OH 43209",
    "addr:housenumber": "1583",
    "addr:postcode": "43209",
    "addr:street": "Alum Creek Dr",
    "iso:country": "US",
    "sg:address": "1583 Alum Creek Dr",
    "sg:city": "Columbus",
    "sg:classifiers": [
      {
        "category": "Professional",
        "subcategory": "Detective \u0026 Security Services",
        "type": "Services"
      }
    ],
    "sg:phone": "+1 614 466 4790",
    "sg:postcode": "43209",
    "sg:province": "OH",
    "sg:tags": [
      "car"
    ],
    "wof:name": "Ohio State Patrol Crime L",
    "wof:placetype": "venue"
  },
  "geometry": {"coordinates":[-82.942378,39.937009],"type":"Point"}
}
