{
  "type": "Feature",
  "properties": {
    "addr:full":"1716 Orleans Dr Toledo OH 43614",
    "addr:housenumber":"1716",
    "addr:postcode":"43614",
    "addr:street":"Orleans Dr",
    "iso:country":"US",
    "sg:address":"1716 Orleans Dr",
    "sg:city":"Toledo",
    "sg:classifiers":[
        {
            "category":"Organizations",
            "subcategory":"Religious Organization",
            "type":"Services"
        }
    ],
    "sg:phone":"+1 419 893 1860",
    "sg:postcode":"43614",
    "sg:province":"OH",
    "sg:tags":[
        "church"
    ],
    "wof:name":"Riverview Christian Church",
    "wof:placetype":"venue"
},
  "geometry": {"coordinates":[-83.606813,41.607604],"type":"Point"}
}