{
  "type": "Feature",
  "properties": {
    "addr:full": "26300 Cedar Rd Cleveland OH 44122",
    "addr:housenumber": "26300",
    "addr:postcode": "44122",
    "addr:street": "Cedar Rd",
    "iso:country": "US",
    "sg:address": "26300 Cedar Rd",
    "sg:city": "Cleveland",
    "sg:classifiers": [
      {
        "category": "Shopping",
        "subcategory": "Clothing, Apparel, \u0026 Fashions",
        "type": "Retail Goods"
      }
    ],
    "sg:phone": "+1 216 464 4000",
    "sg:postcode": "44122",
    "sg:province": "OH",
    "sg:tags": [
      "menswear"
    ],
    "wof:name": "The Galleries of Neiman Marcus",
    "wof:placetype": "venue"
  },
  "geometry": {"coordinates":[-81.493205,41.501129],"type":"Point"}
}
