{
  "type": "Feature",
  "properties": {
    "iso:country":"US",
    "sg:address":"131 W Center St",
    "sg:city":"Marion",
    "sg:classifiers":[
        {
            "category":"Shopping",
            "type":"Retail Goods"
        }
    ],
    "sg:phone":"+1 740 383 2454",
    "sg:postcode":"43302",
    "sg:province":"OH",
    "sg:tags":[
        "material",
        "artist",
        "supply"
    ],
    "wof:name":"Gallery 131",
    "wof:placetype":"venue"
},
  "geometry": {"coordinates":[-83.129599,40.588551],"type":"Point"}
}