{
  "type": "Feature",
  "properties": {
    "addr:full": "217 S B St Hamilton IN 45013",
    "addr:housenumber": "217",
    "addr:postcode": "45013",
    "addr:street": "S B",
    "iso:country": "US",
    "sg:address": "217 S B St",
    "sg:city": "Hamilton",
    "sg:classifiers": [
      {
        "category": "Shopping",
        "subcategory": "Crafts \u0026 Fabrics",
        "type": "Retail Goods"
      }
    ],
    "sg:phone": "+1 513 895 5648",
    "sg:postcode": "45013",
    "sg:province": "IN",
    "sg:tags": [
      "sewing",
      "yarn"
    ],
    "wof:name": "Lambikins Hideaway Yarn",
    "wof:placetype": "venue"
  },
  "geometry": {"coordinates":[-84.568934,39.40071],"type":"Point"}
}
