{
  "type": "Feature",
  "properties": {
    "iso:country":"US",
    "sg:address":"2063 Beechmont Ave",
    "sg:city":"Cincinnati",
    "sg:classifiers":[
        {
            "category":"Wholesale",
            "subcategory":"Durable Goods & Equipment",
            "type":"Manufacturing & Wholesale Goods"
        }
    ],
    "sg:phone":"+1 513 231 1494",
    "sg:postcode":"45230",
    "sg:province":"OH",
    "sg:tags":[
        "representative",
        "manufacturer"
    ],
    "wof:name":"Wilson Electrical Sales",
    "wof:placetype":"venue"
},
  "geometry": {"coordinates":[-84.38705,39.09244],"type":"Point"}
}