{
  "type": "Feature",
  "properties": {
    "addr:full": "2063 Beechmont Ave Cincinnati OH 45230",
    "addr:housenumber": "2063",
    "addr:postcode": "45230",
    "addr:street": "Beechmont Ave",
    "iso:country": "US",
    "sg:address": "2063 Beechmont Ave",
    "sg:city": "Cincinnati",
    "sg:classifiers": [
      {
        "category": "Wholesale",
        "subcategory": "Durable Goods \u0026 Equipment",
        "type": "Manufacturing \u0026 Wholesale Goods"
      }
    ],
    "sg:phone": "+1 513 231 1494",
    "sg:postcode": "45230",
    "sg:province": "OH",
    "sg:tags": [
      "representative",
      "manufacturer"
    ],
    "wof:name": "Wilson Electrical Sales",
    "wof:placetype": "venue"
  },
  "geometry": {"coordinates":[-84.38705,39.09244],"type":"Point"}
}
