{
  "type": "Feature",
  "properties": {
    "addr:full":"541 N Broadway St Lebanon OH 45036",
    "addr:housenumber":"541",
    "addr:postcode":"45036",
    "addr:street":"N Broadway St",
    "iso:country":"US",
    "sg:address":"541 N Broadway St",
    "sg:city":"Lebanon",
    "sg:classifiers":[
        {
            "category":"Retail",
            "subcategory":"Car Wash",
            "type":"Services"
        }
    ],
    "sg:phone":"+1 513 934 1288",
    "sg:postcode":"45036",
    "sg:province":"OH",
    "sg:tags":[
        "polishing",
        "washing"
    ],
    "wof:name":"Lebanon Car Wash",
    "wof:placetype":"venue"
},
  "geometry": {"coordinates":[-84.206444,39.442251],"type":"Point"}
}