{
  "type": "Feature",
  "properties": {
    "iso:country":"US",
    "sg:address":"893 Cheney Ave",
    "sg:city":"Marion",
    "sg:classifiers":[
        {
            "category":"Bars & Pubs",
            "type":"Food & Drink"
        }
    ],
    "sg:phone":"+1 740 387 6330",
    "sg:postcode":"43302",
    "sg:province":"OH",
    "wof:name":"Steel Horse Saloon",
    "wof:placetype":"venue"
},
  "geometry": {"coordinates":[-83.140914,40.570004],"type":"Point"}
}