{
  "type": "Feature",
  "properties": {
    "addr:full": "26565 Royalton Rd Columbia Station OH 44028",
    "addr:housenumber": "26565",
    "addr:postcode": "44028",
    "addr:street": "Royalton Rd",
    "iso:country": "US",
    "sg:address": "26565 Royalton Rd",
    "sg:city": "Columbia Station",
    "sg:classifiers": [
      {
        "category": "Retail",
        "subcategory": "Veterinary Services",
        "type": "Services"
      }
    ],
    "sg:phone": "+1 440 236 6100",
    "sg:postcode": "44028",
    "sg:province": "OH",
    "sg:tags": [
      "veterinarian"
    ],
    "wof:name": "Columbia Animal Clinic",
    "wof:placetype": "venue"
  },
  "geometry": {"coordinates":[-81.929024,41.312697],"type":"Point"}
}
