{
  "type": "Feature",
  "properties": {
    "addr:full": "117 W High St London OH 43140",
    "addr:housenumber": "117",
    "addr:postcode": "43140",
    "addr:street": "W High St",
    "iso:country": "US",
    "sg:address": "117 W High St",
    "sg:city": "London",
    "sg:classifiers": [
      {
        "category": "Health Services",
        "subcategory": "Doctor",
        "type": "Services"
      }
    ],
    "sg:phone": "+1 740 852 2612",
    "sg:postcode": "43140",
    "sg:province": "OH",
    "sg:tags": [
      "physician",
      "surgeon"
    ],
    "wof:name": "David Brock DO",
    "wof:placetype": "venue"
  },
  "geometry": {"coordinates":[-83.451317,39.884415],"type":"Point"}
}
