{
  "type": "Feature",
  "properties": {
    "iso:country":"US",
    "sg:address":"1375 Golden Ln",
    "sg:city":"Broadview Heights",
    "sg:classifiers":[
        {
            "category":"Real Estate",
            "subcategory":"Developer",
            "type":"Services"
        }
    ],
    "sg:phone":"+1 440 526 7068",
    "sg:postcode":"44147",
    "sg:province":"OH",
    "wof:name":"Comfort Green of Geneva LLC",
    "wof:placetype":"venue"
},
  "geometry": {"coordinates":[-81.692806,41.287344],"type":"Point"}
}