{
  "type": "Feature",
  "properties": {
    "addr:full": "1642 Norcross Dr Oregon OH 43616",
    "addr:housenumber": "1642",
    "addr:postcode": "43616",
    "addr:street": "Norcross Dr",
    "iso:country": "US",
    "sg:address": "1642 Norcross Dr",
    "sg:city": "Oregon",
    "sg:classifiers": [
      {
        "category": "Wholesale",
        "subcategory": "Non-durable Goods",
        "type": "Manufacturing \u0026 Wholesale Goods"
      }
    ],
    "sg:phone": "+1 419 697 0255",
    "sg:postcode": "43616",
    "sg:province": "OH",
    "wof:name": "Innovision Distribution",
    "wof:placetype": "venue"
  },
  "geometry": {"coordinates":[-83.487237,41.621998],"type":"Point"}
}
