{
  "type": "Feature",
  "properties": {
    "addr:full": "13149 State Rte 736 Marysville OH 43040",
    "addr:housenumber": "13149",
    "addr:postcode": "43040",
    "addr:street": "State Rte 736",
    "iso:country": "US",
    "sg:address": "13149 State Rte 736",
    "sg:city": "Marysville",
    "sg:classifiers": [
      {
        "category": "Building \u0026 Trades",
        "subcategory": "Landscaping Services",
        "type": "Services"
      }
    ],
    "sg:phone": "+1 937 642 3175",
    "sg:postcode": "43040",
    "sg:province": "OH",
    "wof:name": "Blumenschein Lawn Service Ltd",
    "wof:placetype": "venue"
  },
  "geometry": {"coordinates":[-83.361352,40.198316],"type":"Point"}
}
