{
  "type": "Feature",
  "properties": {
    "addr:full":"620 Griswold Rd Elyria OH 44035",
    "addr:housenumber":"620",
    "addr:postcode":"44035",
    "addr:street":"Griswold Rd",
    "iso:country":"US",
    "sg:address":"620 Griswold Rd",
    "sg:city":"Elyria",
    "sg:classifiers":[
        {
            "category":"Autos & Motor Vehicles",
            "subcategory":"Automobile Sales",
            "type":"Retail Goods"
        }
    ],
    "sg:phone":"+1 440 324 9561",
    "sg:postcode":"44035",
    "sg:province":"OH",
    "sg:tags":[
        "car",
        "dealer"
    ],
    "wof:name":"Melissa's Auto Sales",
    "wof:placetype":"venue"
},
  "geometry": {"coordinates":[-82.116979,41.400479],"type":"Point"}
}