{
  "type": "Feature",
  "properties": {
    "addr:full": "2399 Forman Rd Jefferson OH 44047",
    "addr:housenumber": "2399",
    "addr:postcode": "44047",
    "addr:street": "Forman Rd",
    "iso:country": "US",
    "sg:address": "2399 Forman Rd",
    "sg:city": "Jefferson",
    "sg:classifiers": [
      {
        "category": "Freight",
        "type": "Transportation"
      }
    ],
    "sg:phone": "+1 440 563 5506",
    "sg:postcode": "44047",
    "sg:province": "OH",
    "sg:tags": [
      "warehouse",
      "self",
      "storage"
    ],
    "wof:name": "J P Molding Warehouse",
    "wof:placetype": "venue"
  },
  "geometry": {"coordinates":[-80.835835,41.686962],"type":"Point"}
}
