{
  "type": "Feature",
  "properties": {
    "addr:full": "21 S State St Westerville OH 43081",
    "addr:housenumber": "21",
    "addr:postcode": "43081",
    "addr:street": "S State St",
    "iso:country": "US",
    "sg:address": "21 S State St",
    "sg:city": "Westerville",
    "sg:classifiers": [
      {
        "category": "Government",
        "subcategory": "Office",
        "type": "Public Place"
      }
    ],
    "sg:phone": "+1 614 901 6741",
    "sg:postcode": "43081",
    "sg:province": "OH",
    "sg:tags": [
      "village"
    ],
    "wof:name": "Pioneer Cemetery",
    "wof:placetype": "venue"
  },
  "geometry": {"coordinates":[-82.931624,40.125817],"type":"Point"}
}
