{
  "type": "Feature",
  "properties": {
    "addr:full": "3656 US Hwy 50 Bainbridge OH 45612",
    "addr:housenumber": "3656",
    "addr:postcode": "45612",
    "addr:street": "Us Hwy 50",
    "iso:country": "US",
    "sg:address": "3656 US Hwy 50",
    "sg:city": "Bainbridge",
    "sg:classifiers": [
      {
        "category": "Manufacturing",
        "subcategory": "Lumber",
        "type": "Manufacturing \u0026 Wholesale Goods"
      }
    ],
    "sg:phone": "+1 740 634 2286",
    "sg:postcode": "45612",
    "sg:province": "OH",
    "sg:tags": [
      "company",
      "logging"
    ],
    "wof:name": "Jeffrey Adams Logging Inc",
    "wof:placetype": "venue"
  },
  "geometry": {"coordinates":[-83.275398,39.226225],"type":"Point"}
}
