{
  "type": "Feature",
  "properties": {
    "addr:full": "832 Hargrove Way Cincinnati OH 45240",
    "addr:housenumber": "832",
    "addr:postcode": "45240",
    "addr:street": "Hargrove Way",
    "iso:country": "US",
    "sg:address": "832 Hargrove Way",
    "sg:city": "Cincinnati",
    "sg:classifiers": [
      {
        "category": "Professional",
        "subcategory": "Computer Services",
        "type": "Services"
      }
    ],
    "sg:phone": "+1 513 793 8263",
    "sg:postcode": "45240",
    "sg:province": "OH",
    "sg:tags": [
      "consultant"
    ],
    "wof:name": "Edu-Entertain Inc",
    "wof:placetype": "venue"
  },
  "geometry": {"coordinates":[-84.507898,39.295117],"type":"Point"}
}
