{
  "type": "Feature",
  "properties": {
    "iso:country":"US",
    "sg:address":"780 King Ave",
    "sg:city":"Columbus",
    "sg:classifiers":[
        {
            "category":"Professional",
            "subcategory":"Art Services",
            "type":"Services"
        }
    ],
    "sg:phone":"+1 614 299 2346",
    "sg:postcode":"43212",
    "sg:province":"OH",
    "sg:tags":[
        "photographer"
    ],
    "wof:name":"Jeff Tholt Photography",
    "wof:placetype":"venue"
},
  "geometry": {"coordinates":[-83.02614800000001,39.990953],"type":"Point"}
}