{
  "type": "Feature",
  "properties": {
    "addr:full":"100 W Locust St Newark OH 43055",
    "addr:housenumber":"100",
    "addr:postcode":"43055",
    "addr:street":"W Locust St",
    "iso:country":"US",
    "sg:address":"100 W Locust St",
    "sg:city":"Newark",
    "sg:classifiers":[
        {
            "category":"Personal",
            "subcategory":"Beauty Salon",
            "type":"Services"
        }
    ],
    "sg:phone":"+1 740 345 5244",
    "sg:postcode":"43055",
    "sg:province":"OH",
    "wof:name":"Mary J's Styling Ctr",
    "wof:placetype":"venue"
},
  "geometry": {"coordinates":[-82.408407,40.059161],"type":"Point"}
}