{
  "type": "Feature",
  "properties": {
    "addr:full": "52 Shopping Plz Chagrin Falls OH 44022",
    "addr:postcode": "44022",
    "addr:street": "Shopping Plz",
    "iso:country": "US",
    "sg:address": "52 Shopping Plz",
    "sg:city": "Chagrin Falls",
    "sg:classifiers": [
      {
        "category": "Personal",
        "subcategory": "Shoe Repair \u0026 Shine",
        "type": "Services"
      }
    ],
    "sg:phone": "+1 440 893 9669",
    "sg:postcode": "44022",
    "sg:province": "OH",
    "wof:name": "Chagrin Falls Shoe Repair",
    "wof:placetype": "venue"
  },
  "geometry": {"coordinates":[-81.391899,41.430801],"type":"Point"}
}
