{
  "type": "Feature",
  "properties": {
    "iso:country":"US",
    "sg:address":"205 E 5th St",
    "sg:city":"Cincinnati",
    "sg:classifiers":[
        {
            "category":"Banks & Credit Unions",
            "subcategory":"Investment Brokerage",
            "type":"Services"
        }
    ],
    "sg:phone":"+1 513 381 2282",
    "sg:postcode":"45202",
    "sg:province":"OH",
    "sg:tags":[
        "security",
        "stock",
        "bond"
    ],
    "wof:name":"Vocational Economics",
    "wof:placetype":"venue"
},
  "geometry": {"coordinates":[-84.50918799999999,39.101644],"type":"Point"}
}