{
  "type": "Feature",
  "properties": {
    "addr:full":"600 Jefferson Ave Toledo OH 43624",
    "addr:housenumber":"600",
    "addr:postcode":"43624",
    "addr:street":"Jefferson Ave",
    "iso:country":"US",
    "sg:address":"600 Jefferson Ave",
    "sg:city":"Toledo",
    "sg:classifiers":[
        {
            "category":"Professional",
            "type":"Services"
        }
    ],
    "sg:phone":"+1 419 244 7284",
    "sg:postcode":"43624",
    "sg:province":"OH",
    "sg:tags":[
        "establishment"
    ],
    "wof:name":"Zerox",
    "wof:placetype":"venue"
},
  "geometry": {"coordinates":[-83.53894099999999,41.6515],"type":"Point"}
}