{
  "type": "Feature",
  "properties": {
    "addr:full": "3 Summit Park Dr Cleveland OH 44131",
    "addr:housenumber": "3",
    "addr:postcode": "44131",
    "addr:street": "Summit Park Dr",
    "iso:country": "US",
    "sg:address": "3 Summit Park Dr",
    "sg:city": "Cleveland",
    "sg:classifiers": [
      {
        "category": "Utilities",
        "subcategory": "Mobile Phone",
        "type": "Services"
      }
    ],
    "sg:phone": "+1 216 870 5000",
    "sg:postcode": "44131",
    "sg:province": "OH",
    "sg:tags": [
      "telephone",
      "cellular"
    ],
    "sg:website": "www.verizon.com",
    "wof:name": "Verizon Wireless",
    "wof:placetype": "venue"
  },
  "geometry": {"coordinates":[-81.655851,41.39571],"type":"Point"}
}
