{
  "type": "Feature",
  "properties": {
    "iso:country":"US",
    "sg:address":"1660 E High St",
    "sg:city":"Springfield",
    "sg:classifiers":[
        {
            "category":"Retail",
            "subcategory":"Funeral Services",
            "type":"Services"
        }
    ],
    "sg:phone":"+1 937 324 4973",
    "sg:postcode":"45505",
    "sg:province":"OH",
    "sg:tags":[
        "director"
    ],
    "sg:website":"www.conroyfh.com",
    "wof:name":"Conroy Funeral Home",
    "wof:placetype":"venue"
},
  "geometry": {"coordinates":[-83.783931,39.921329],"type":"Point"}
}