{
  "type": "Feature",
  "properties": {
    "addr:full":"105 W Butler St Bryan OH 43506",
    "addr:housenumber":"105",
    "addr:postcode":"43506",
    "addr:street":"W Butler St",
    "iso:country":"US",
    "sg:address":"105 W Butler St",
    "sg:city":"Bryan",
    "sg:classifiers":[
        {
            "category":"Shopping",
            "subcategory":"Stationery & Office Supplies",
            "type":"Retail Goods"
        }
    ],
    "sg:phone":"+1 419 633 3838",
    "sg:postcode":"43506",
    "sg:province":"OH",
    "sg:tags":[
        "album",
        "scrapbook"
    ],
    "wof:name":"Nana's Girls Scrapbooking",
    "wof:placetype":"venue"
},
  "geometry": {"coordinates":[-84.55170200000001,41.473214],"type":"Point"}
}