{
  "type": "Feature",
  "properties": {
    "addr:full":"1000 E Washington St Medina OH 44256",
    "addr:housenumber":"1000",
    "addr:postcode":"44256",
    "addr:street":"E Washington St",
    "iso:country":"US",
    "sg:address":"1000 E Washington St",
    "sg:city":"Medina",
    "sg:classifiers":[
        {
            "category":"Health Services",
            "subcategory":"Doctor",
            "type":"Services"
        }
    ],
    "sg:phone":"+1 330 336 1000",
    "sg:postcode":"44256",
    "sg:province":"OH",
    "sg:tags":[
        "physician",
        "surgeon"
    ],
    "wof:name":"Eric L Brown MD",
    "wof:placetype":"venue"
},
  "geometry": {"coordinates":[-81.837075,41.138844],"type":"Point"}
}