{
  "type": "Feature",
  "properties": {
    "addr:full": "3162 Mount Hope Rd Otway OH 45657",
    "addr:housenumber": "3162",
    "addr:postcode": "45657",
    "addr:street": "Mount Hope Rd",
    "iso:country": "US",
    "sg:address": "3162 Mount Hope Rd",
    "sg:city": "Otway",
    "sg:classifiers": [
      {
        "category": "Travel",
        "subcategory": "Campground",
        "type": "Entertainment"
      }
    ],
    "sg:phone": "+1 740 372 6422",
    "sg:postcode": "45657",
    "sg:province": "OH",
    "sg:tags": [
      "camp"
    ],
    "wof:name": "Mt Hope Bible Camp",
    "wof:placetype": "venue"
  },
  "geometry": {"coordinates":[-83.166098,38.931016],"type":"Point"}
}
