{
  "type": "Feature",
  "properties": {
    "addr:full": "2580 Oakstone Dr Columbus OH 43231",
    "addr:housenumber": "2580",
    "addr:postcode": "43231",
    "addr:street": "Oakstone Dr",
    "iso:country": "US",
    "sg:address": "2580 Oakstone Dr",
    "sg:city": "Columbus",
    "sg:classifiers": [
      {
        "category": "Wholesale",
        "subcategory": "Seafood",
        "type": "Manufacturing \u0026 Wholesale Goods"
      }
    ],
    "sg:phone": "+1 614 891 8590",
    "sg:postcode": "43231",
    "sg:province": "OH",
    "wof:name": "Pier Fish Co",
    "wof:placetype": "venue"
  },
  "geometry": {"coordinates":[-82.949056,40.097932],"type":"Point"}
}
