{
  "type": "Feature",
  "properties": {
    "addr:full": "1306 Research Park Dr Dayton OH 45432",
    "addr:housenumber": "1306",
    "addr:postcode": "45432",
    "addr:street": "Research Park Dr",
    "iso:country": "US",
    "sg:address": "1306 Research Park Dr",
    "sg:city": "Dayton",
    "sg:classifiers": [
      {
        "category": "Professional",
        "subcategory": "Research",
        "type": "Services"
      }
    ],
    "sg:phone": "+1 937 320 5120",
    "sg:postcode": "45432",
    "sg:province": "OH",
    "sg:tags": [
      "development",
      "laboratory"
    ],
    "wof:name": "Spectral Energetics Inc",
    "wof:placetype": "venue"
  },
  "geometry": {"coordinates":[-84.065907,39.732529],"type":"Point"}
}
