{
  "type": "Feature",
  "properties": {
    "addr:full": "100 S Paint St Chillicothe OH 45601",
    "addr:housenumber": "100",
    "addr:postcode": "45601",
    "addr:street": "S Paint St",
    "iso:country": "US",
    "sg:address": "100 S Paint St",
    "sg:city": "Chillicothe",
    "sg:classifiers": [
      {
        "category": "Health Services",
        "subcategory": "Nursing And Care Facility",
        "type": "Services"
      }
    ],
    "sg:phone": "+1 740 772 6820",
    "sg:postcode": "45601",
    "sg:province": "OH",
    "wof:name": "Detillion Family Care Home",
    "wof:placetype": "venue"
  },
  "geometry": {"coordinates":[-82.981563,39.331047],"type":"Point"}
}
