{
  "type": "Feature",
  "properties": {
    "iso:country":"US",
    "sg:address":"100 S Paint St",
    "sg:city":"Chillicothe",
    "sg:classifiers":[
        {
            "category":"Health Services",
            "subcategory":"Nursing And Care Facility",
            "type":"Services"
        }
    ],
    "sg:phone":"+1 740 772 6820",
    "sg:postcode":"45601",
    "sg:province":"OH",
    "wof:name":"Detillion Family Care Home",
    "wof:placetype":"venue"
},
  "geometry": {"coordinates":[-82.98156299999999,39.331047],"type":"Point"}
}