{
  "type": "Feature",
  "properties": {
    "iso:country":"US",
    "sg:address":"526 South St",
    "sg:city":"Alliance",
    "sg:classifiers":[
        {
            "category":"Social Services",
            "subcategory":"Child Care",
            "type":"Services"
        }
    ],
    "sg:phone":"+1 330 821 2116",
    "sg:postcode":"44601",
    "sg:province":"OH",
    "wof:name":"Mark Jones Child Care",
    "wof:placetype":"venue"
},
  "geometry": {"coordinates":[-81.097516,40.909556],"type":"Point"}
}