{
  "type": "Feature",
  "properties": {
    "addr:full":"312 Airport Rd Gallipolis OH 45631",
    "addr:housenumber":"312",
    "addr:postcode":"45631",
    "addr:street":"Airport Rd",
    "iso:country":"US",
    "sg:address":"312 Airport Rd",
    "sg:city":"Gallipolis",
    "sg:classifiers":[
        {
            "category":"Airport",
            "type":"Transportation"
        }
    ],
    "sg:phone":"+1 740 446 9004",
    "sg:postcode":"45631",
    "sg:province":"OH",
    "wof:name":"Gallia-Meigs Regional Airport",
    "wof:placetype":"venue"
},
  "geometry": {"coordinates":[-82.162251,38.833336],"type":"Point"}
}