{
  "type": "Feature",
  "properties": {
    "addr:full":"2310 Superior Ave E Cleveland OH 44114",
    "addr:housenumber":"2310",
    "addr:postcode":"44114",
    "addr:street":"Superior Ave E",
    "iso:country":"US",
    "sg:address":"2310 Superior Ave E",
    "sg:city":"Cleveland",
    "sg:classifiers":[
        {
            "category":"Professional",
            "type":"Services"
        }
    ],
    "sg:phone":"+1 216 575 1065",
    "sg:postcode":"44114",
    "sg:province":"OH",
    "sg:tags":[
        "arts",
        "artist"
    ],
    "wof:name":"Kelly & Hammett Studios",
    "wof:placetype":"venue"
},
  "geometry": {"coordinates":[-81.67512000000001,41.508629],"type":"Point"}
}