{
  "type": "Feature",
  "properties": {
    "addr:full": "8168 Business Way Plain City OH 43064",
    "addr:housenumber": "8168",
    "addr:postcode": "43064",
    "addr:street": "Business Way",
    "iso:country": "US",
    "sg:address": "8168 Business Way",
    "sg:city": "Plain City",
    "sg:classifiers": [
      {
        "category": "Wholesale",
        "subcategory": "Machinery \u0026 Supplies",
        "type": "Manufacturing \u0026 Wholesale Goods"
      }
    ],
    "sg:phone": "+1 614 733 0505",
    "sg:postcode": "43064",
    "sg:province": "OH",
    "sg:tags": [
      "equipment",
      "material",
      "handling"
    ],
    "wof:name": "Midwest Material Handling",
    "wof:placetype": "venue"
  },
  "geometry": {"coordinates":[-83.197907,40.132605],"type":"Point"}
}
