{
  "type": "Feature",
  "properties": {
    "addr:full":"624 W Stroop Rd Dayton OH 45429",
    "addr:housenumber":"624",
    "addr:postcode":"45429",
    "addr:street":"W Stroop Rd",
    "iso:country":"US",
    "sg:address":"624 W Stroop Rd",
    "sg:city":"Dayton",
    "sg:classifiers":[
        {
            "category":"Real Estate",
            "subcategory":"Real Estate Agent",
            "type":"Services"
        }
    ],
    "sg:phone":"+1 937 294 4169",
    "sg:postcode":"45429",
    "sg:province":"OH",
    "sg:tags":[
        "manager"
    ],
    "wof:name":"Hobbs Commercial Investment",
    "wof:placetype":"venue"
},
  "geometry": {"coordinates":[-84.18549899999999,39.690392],"type":"Point"}
}