{
  "type": "Feature",
  "properties": {
    "addr:full":"3492 Central Ave Grove City OH 43123",
    "addr:housenumber":"3492",
    "addr:postcode":"43123",
    "addr:street":"Central Ave",
    "iso:country":"US",
    "sg:address":"3492 Central Ave",
    "sg:city":"Grove City",
    "sg:classifiers":[
        {
            "category":"Professional",
            "subcategory":"Management & Consulting",
            "type":"Services"
        }
    ],
    "sg:phone":"+1 614 875 9914",
    "sg:postcode":"43123",
    "sg:province":"OH",
    "sg:tags":[
        "town",
        "city",
        "regional",
        "planner"
    ],
    "wof:name":"Urbancrest Village Municipal",
    "wof:placetype":"venue"
},
  "geometry": {"coordinates":[-83.083624,39.897977],"type":"Point"}
}