{
  "type": "Feature",
  "properties": {
    "addr:full":"1601 Woodland Ave Columbus OH 43219",
    "addr:housenumber":"1601",
    "addr:postcode":"43219",
    "addr:street":"Woodland Ave",
    "iso:country":"US",
    "sg:address":"1601 Woodland Ave",
    "sg:city":"Columbus",
    "sg:classifiers":[
        {
            "category":"Professional",
            "subcategory":"Computer Services",
            "type":"Services"
        }
    ],
    "sg:phone":"+1 614 258 2580",
    "sg:postcode":"43219",
    "sg:province":"OH",
    "sg:tags":[
        "consultant",
        "designer"
    ],
    "wof:name":"Industrial Management Systems",
    "wof:placetype":"venue"
},
  "geometry": {"coordinates":[-82.95457,40.000432],"type":"Point"}
}