{
  "type": "Feature",
  "properties": {
    "addr:full": "274 Dehoff Dr Youngstown OH 44515",
    "addr:housenumber": "274",
    "addr:postcode": "44515",
    "addr:street": "Dehoff Dr",
    "iso:country": "US",
    "sg:address": "274 Dehoff Dr",
    "sg:city": "Youngstown",
    "sg:classifiers": [
      {
        "category": "Building \u0026 Trades",
        "subcategory": "Plumbing",
        "type": "Services"
      }
    ],
    "sg:phone": "+1 330 270 9802",
    "sg:postcode": "44515",
    "sg:province": "OH",
    "sg:tags": [
      "air",
      "heating",
      "conditioning",
      "contractor"
    ],
    "wof:name": "Star Heating \u0026 AC",
    "wof:placetype": "venue"
  },
  "geometry": {"coordinates":[-80.757754,41.090706],"type":"Point"}
}
