{
  "type": "Feature",
  "properties": {
    "addr:full": "137 Federal Ave NW Massillon OH 44647",
    "addr:housenumber": "137",
    "addr:postcode": "44647",
    "addr:street": "Federal Ave Nw",
    "iso:country": "US",
    "sg:address": "137 Federal Ave NW",
    "sg:city": "Massillon",
    "sg:classifiers": [
      {
        "category": "Retail",
        "subcategory": "Laundry \u0026 Dry Cleaning",
        "type": "Services"
      }
    ],
    "sg:phone": "+1 330 837 5856",
    "sg:postcode": "44647",
    "sg:province": "OH",
    "sg:tags": [
      "cleaners"
    ],
    "wof:name": "Champion 1 Hour Dry Cleaners",
    "wof:placetype": "venue"
  },
  "geometry": {"coordinates":[-81.525586,40.796621],"type":"Point"}
}
