{
  "type": "Feature",
  "properties": {
    "iso:country":"US",
    "sg:address":"137 Federal Ave NW",
    "sg:city":"Massillon",
    "sg:classifiers":[
        {
            "category":"Retail",
            "subcategory":"Laundry & Dry Cleaning",
            "type":"Services"
        }
    ],
    "sg:phone":"+1 330 837 5856",
    "sg:postcode":"44647",
    "sg:province":"OH",
    "sg:tags":[
        "cleaners"
    ],
    "wof:name":"Champion 1 Hour Dry Cleaners",
    "wof:placetype":"venue"
},
  "geometry": {"coordinates":[-81.525586,40.796621],"type":"Point"}
}