{
  "type": "Feature",
  "properties": {
    "addr:full":"1020 Taylor Station Rd Columbus OH 43230",
    "addr:housenumber":"1020",
    "addr:postcode":"43230",
    "addr:street":"Taylor Station Rd",
    "iso:country":"US",
    "sg:address":"1020 Taylor Station Rd",
    "sg:city":"Columbus",
    "sg:classifiers":[
        {
            "category":"Building & Trades",
            "subcategory":"Construction",
            "type":"Services"
        }
    ],
    "sg:phone":"+1 614 751 5055",
    "sg:postcode":"43230",
    "sg:province":"OH",
    "sg:tags":[
        "general",
        "contractor"
    ],
    "wof:name":"Navarro Construction Co",
    "wof:placetype":"venue"
},
  "geometry": {"coordinates":[-82.84153499999999,39.990328],"type":"Point"}
}