{
  "type": "Feature",
  "properties": {
    "iso:country":"US",
    "sg:address":"1065 Reading Rd",
    "sg:city":"Mason",
    "sg:classifiers":[
        {
            "category":"Home & Garden",
            "subcategory":"Home Furnishings",
            "type":"Retail Goods"
        }
    ],
    "sg:phone":"+1 513 398 8510",
    "sg:postcode":"45040",
    "sg:province":"OH",
    "sg:tags":[
        "venetian",
        "blind"
    ],
    "wof:name":"Blinds Plus",
    "wof:placetype":"venue"
},
  "geometry": {"coordinates":[-84.34343800000001,39.337157],"type":"Point"}
}