{
  "type": "Feature",
  "properties": {
    "addr:full": "1065 Reading Rd Mason OH 45040",
    "addr:housenumber": "1065",
    "addr:postcode": "45040",
    "addr:street": "Reading Rd",
    "iso:country": "US",
    "sg:address": "1065 Reading Rd",
    "sg:city": "Mason",
    "sg:classifiers": [
      {
        "category": "Home \u0026 Garden",
        "subcategory": "Home Furnishings",
        "type": "Retail Goods"
      }
    ],
    "sg:phone": "+1 513 398 8510",
    "sg:postcode": "45040",
    "sg:province": "OH",
    "sg:tags": [
      "venetian",
      "blind"
    ],
    "wof:name": "Blinds Plus",
    "wof:placetype": "venue"
  },
  "geometry": {"coordinates":[-84.343438,39.337157],"type":"Point"}
}
