{
  "type": "Feature",
  "properties": {
    "addr:full": "4808 Rean Meadow Dr Dayton OH 45440",
    "addr:housenumber": "4808",
    "addr:postcode": "45440",
    "addr:street": "Rean Meadow Dr",
    "iso:country": "US",
    "sg:address": "4808 Rean Meadow Dr",
    "sg:city": "Dayton",
    "sg:classifiers": [
      {
        "category": "Professional",
        "subcategory": "Secretarial Services",
        "type": "Services"
      }
    ],
    "sg:phone": "+1 937 435 2264",
    "sg:postcode": "45440",
    "sg:province": "OH",
    "sg:tags": [
      "convention",
      "court",
      "reporter"
    ],
    "wof:name": "Nancy C Sellars \u0026 Assoc Court",
    "wof:placetype": "venue"
  },
  "geometry": {"coordinates":[-84.117733,39.671367],"type":"Point"}
}
