{
  "type": "Feature",
  "properties": {
    "iso:country":"US",
    "sg:address":"456 E Overlook Dr",
    "sg:city":"Willoughby",
    "sg:classifiers":[
        {
            "category":"Professional",
            "subcategory":"Accounting & Tax Preparation",
            "type":"Services"
        }
    ],
    "sg:phone":"+1 440 946 6097",
    "sg:postcode":"44095",
    "sg:province":"OH",
    "sg:tags":[
        "accountant"
    ],
    "wof:name":"Michael C Di Cicco CPA",
    "wof:placetype":"venue"
},
  "geometry": {"coordinates":[-81.41063699999999,41.677286],"type":"Point"}
}