{
  "type": "Feature",
  "properties": {
    "addr:full": "456 E Overlook Dr Willoughby OH 44095",
    "addr:housenumber": "456",
    "addr:postcode": "44095",
    "addr:street": "E Overlook Dr",
    "iso:country": "US",
    "sg:address": "456 E Overlook Dr",
    "sg:city": "Willoughby",
    "sg:classifiers": [
      {
        "category": "Professional",
        "subcategory": "Accounting \u0026 Tax Preparation",
        "type": "Services"
      }
    ],
    "sg:phone": "+1 440 946 6097",
    "sg:postcode": "44095",
    "sg:province": "OH",
    "sg:tags": [
      "accountant"
    ],
    "wof:name": "Michael C Di Cicco CPA",
    "wof:placetype": "venue"
  },
  "geometry": {"coordinates":[-81.410637,41.677286],"type":"Point"}
}
