{
  "type": "Feature",
  "properties": {
    "iso:country":"US",
    "sg:address":"5288 Westpoint Plaza Dr",
    "sg:city":"Columbus",
    "sg:classifiers":[
        {
            "category":"Wholesale",
            "subcategory":"Machinery & Supplies",
            "type":"Manufacturing & Wholesale Goods"
        }
    ],
    "sg:phone":"+1 614 876 0465",
    "sg:postcode":"43228",
    "sg:province":"OH",
    "sg:tags":[
        "beauty"
    ],
    "wof:name":"Sally Beauty Supply",
    "wof:placetype":"venue"
},
  "geometry": {"coordinates":[-83.14762399999999,39.982597],"type":"Point"}
}