{
  "type": "Feature",
  "properties": {
    "addr:full":"1996 Harris Rd Sheffield Vlg OH 44054",
    "addr:housenumber":"1996",
    "addr:postcode":"44054",
    "addr:street":"Harris Rd",
    "iso:country":"US",
    "sg:address":"1996 Harris Rd",
    "sg:city":"Sheffield Vlg",
    "sg:classifiers":[
        {
            "category":"Building & Trades",
            "subcategory":"Construction",
            "type":"Services"
        },
        {
            "category":"Shopping",
            "subcategory":"Bicycles & Sporting Goods",
            "type":"Retail Goods"
        }
    ],
    "sg:phone":"+1 440 949 6749",
    "sg:postcode":"44054",
    "sg:province":"OH",
    "sg:tags":[
        "equipment",
        "camping",
        "house"
    ],
    "wof:name":"U Dezyn It",
    "wof:placetype":"venue"
},
  "geometry": {"coordinates":[-82.094863,41.4741],"type":"Point"}
}