{
  "type": "Feature",
  "properties": {
    "iso:country":"US",
    "sg:address":"1041 E Park Ave",
    "sg:city":"Columbiana",
    "sg:classifiers":[
        {
            "category":"Building & Trades",
            "subcategory":"Plumbing",
            "type":"Services"
        }
    ],
    "sg:phone":"+1 330 482 2713",
    "sg:postcode":"44408",
    "sg:province":"OH",
    "sg:tags":[
        "heating",
        "contractor"
    ],
    "wof:name":"Nick's Tin Shop",
    "wof:placetype":"venue"
},
  "geometry": {"coordinates":[-80.671353,40.887899],"type":"Point"}
}