{
  "type": "Feature",
  "properties": {
    "iso:country":"US",
    "sg:address":"34427 Union Ridge Rd",
    "sg:city":"Albany",
    "sg:classifiers":[
        {
            "category":"Building & Trades",
            "subcategory":"Construction",
            "type":"Services"
        }
    ],
    "sg:phone":"+1 740 596 0966",
    "sg:postcode":"45710",
    "sg:province":"OH",
    "sg:tags":[
        "home",
        "improvement"
    ],
    "wof:name":"Gary Holley",
    "wof:placetype":"venue"
},
  "geometry": {"coordinates":[-82.341466,39.21649],"type":"Point"}
}