{
  "type": "Feature",
  "properties": {
    "addr:full":"7260 Erie Ave SW Navarre OH 44662",
    "addr:housenumber":"7260",
    "addr:postcode":"44662",
    "addr:street":"Erie Ave Sw",
    "iso:country":"US",
    "sg:address":"7260 Erie Ave SW",
    "sg:city":"Navarre",
    "sg:classifiers":[
        {
            "category":"Manufacturing",
            "subcategory":"Tools & Machinery",
            "type":"Manufacturing & Wholesale Goods"
        }
    ],
    "sg:phone":"+1 330 879 2448",
    "sg:postcode":"44662",
    "sg:province":"OH",
    "sg:tags":[
        "equipment",
        "mfg",
        "custom"
    ],
    "wof:name":"Terydon Inc",
    "wof:placetype":"venue"
},
  "geometry": {"coordinates":[-81.523408,40.70689],"type":"Point"}
}