{
  "type": "Feature",
  "properties": {
    "addr:full":"1631 NW Professional Plz Columbus OH 43220",
    "addr:housenumber":"1631",
    "addr:postcode":"43220",
    "addr:street":"Nw Professional Plz",
    "iso:country":"US",
    "sg:address":"1631 NW Professional Plz",
    "sg:city":"Columbus",
    "sg:classifiers":[
        {
            "category":"Insurance",
            "subcategory":"Insurance Agent",
            "type":"Services"
        }
    ],
    "sg:phone":"+1 614 326 6401",
    "sg:postcode":"43220",
    "sg:province":"OH",
    "wof:name":"Scott Good Insurance",
    "wof:placetype":"venue"
},
  "geometry": {"coordinates":[-83.063911,40.052207],"type":"Point"}
}