{
  "type": "Feature",
  "properties": {
    "iso:country":"US",
    "sg:address":"1015 Superior St",
    "sg:city":"Sandusky",
    "sg:classifiers":[
        {
            "category":"Retail",
            "subcategory":"Animal Services",
            "type":"Services"
        }
    ],
    "sg:phone":"+1 419 627 1778",
    "sg:postcode":"44870",
    "sg:province":"OH",
    "wof:name":"Jasmins Dogsitting Service",
    "wof:placetype":"venue"
},
  "geometry": {"coordinates":[-82.743859,41.445598],"type":"Point"}
}