{
  "type": "Feature",
  "properties": {
    "addr:full": "4787 E Main St Berlin OH 44654",
    "addr:housenumber": "4787",
    "addr:postcode": "44654",
    "addr:street": "E Main St",
    "iso:country": "US",
    "sg:address": "4787 E Main St",
    "sg:city": "Berlin",
    "sg:classifiers": [
      {
        "category": "Shopping",
        "subcategory": "Gifts \u0026 Souvenirs",
        "type": "Retail Goods"
      }
    ],
    "sg:phone": "+1 330 893 3983",
    "sg:postcode": "44654",
    "sg:province": "OH",
    "sg:tags": [
      "shop"
    ],
    "wof:name": "Lena's House",
    "wof:placetype": "venue"
  },
  "geometry": {"coordinates":[-81.795388,40.561448],"type":"Point"}
}
