{
  "type": "Feature",
  "properties": {
    "addr:full":"1075 N Bridge St Chillicothe OH 45601",
    "addr:housenumber":"1075",
    "addr:postcode":"45601",
    "addr:street":"N Bridge St",
    "iso:country":"US",
    "sg:address":"1075 N Bridge St",
    "sg:city":"Chillicothe",
    "sg:classifiers":[
        {
            "category":"Shopping",
            "subcategory":"Bicycles & Sporting Goods",
            "type":"Retail Goods"
        }
    ],
    "sg:phone":"+1 740 779 6541",
    "sg:postcode":"45601",
    "sg:province":"OH",
    "sg:website":"www.champsports.com",
    "wof:name":"Champs",
    "wof:placetype":"venue"
},
  "geometry": {"coordinates":[-82.976603,39.3483],"type":"Point"}
}