{
  "type": "Feature",
  "properties": {
    "addr:full":"441 Vine St Cincinnati OH 45202",
    "addr:housenumber":"441",
    "addr:postcode":"45202",
    "addr:street":"Vine St",
    "iso:country":"US",
    "sg:address":"441 Vine St",
    "sg:city":"Cincinnati",
    "sg:classifiers":[
        {
            "category":"Shopping",
            "subcategory":"Clothing, Apparel, & Fashions",
            "type":"Retail Goods"
        }
    ],
    "sg:phone":"+1 513 333 0146",
    "sg:postcode":"45202",
    "sg:province":"OH",
    "sg:website":"www.nyandcompany.com",
    "wof:name":"New York & Co",
    "wof:placetype":"venue"
},
  "geometry": {"coordinates":[-84.512918,39.100542],"type":"Point"}
}