{
  "type": "Feature",
  "properties": {
    "iso:country":"US",
    "sg:address":"9501 Colerain Ave",
    "sg:city":"Cincinnati",
    "sg:classifiers":[
        {
            "category":"Restaurant",
            "type":"Food & Drink"
        }
    ],
    "sg:phone":"+1 513 741 1547",
    "sg:postcode":"45251",
    "sg:province":"OH",
    "sg:website":"www.arbys.com",
    "wof:name":"Arby's",
    "wof:placetype":"venue"
},
  "geometry": {"coordinates":[-84.59504699999999,39.243543],"type":"Point"}
}