{
  "type": "Feature",
  "properties": {
    "iso:country":"US",
    "sg:address":"2988 N High St",
    "sg:city":"Columbus",
    "sg:classifiers":[
        {
            "category":"Real Estate",
            "subcategory":"Real Estate Operator",
            "type":"Services"
        }
    ],
    "sg:phone":"+1 614 261 0333",
    "sg:postcode":"43202",
    "sg:province":"OH",
    "sg:tags":[
        "building",
        "nonresidential"
    ],
    "wof:name":"Fairfax Properties LLC",
    "wof:placetype":"venue"
},
  "geometry": {"coordinates":[-83.01349,40.022692],"type":"Point"}
}