{
  "type": "Feature",
  "properties": {
    "addr:full":"5640 Southwyck Blvd Toledo OH 43614",
    "addr:postcode":"5640;43614",
    "addr:street":"Southwyck Blvd",
    "iso:country":"US",
    "sg:address":"5640 Southwyck Blvd",
    "sg:city":"Toledo",
    "sg:classifiers":[
        {
            "category":"Health Services",
            "subcategory":"Medical Lab",
            "type":"Services"
        }
    ],
    "sg:phone":"+1 419 866 9200",
    "sg:postcode":"43614",
    "sg:province":"OH",
    "sg:tags":[
        "detection",
        "equipment",
        "drug"
    ],
    "wof:name":"Examination Management Svc",
    "wof:placetype":"venue"
},
  "geometry": {"coordinates":[-83.671103,41.601503],"type":"Point"}
}