{
  "type": "Feature",
  "properties": {
    "addr:full": "16570 Commerce Ct Cleveland OH 44130",
    "addr:housenumber": "16570",
    "addr:postcode": "44130",
    "addr:street": "Commerce Ct",
    "iso:country": "US",
    "sg:address": "16570 Commerce Ct",
    "sg:city": "Cleveland",
    "sg:classifiers": [
      {
        "category": "Insurance",
        "subcategory": "Insurance Agent",
        "type": "Services"
      }
    ],
    "sg:phone": "+1 440 243 6029",
    "sg:postcode": "44130",
    "sg:province": "OH",
    "wof:name": "Concepts For Life Insurance",
    "wof:placetype": "venue"
  },
  "geometry": {"coordinates":[-81.814232,41.350827],"type":"Point"}
}
