{
  "type": "Feature",
  "properties": {
    "addr:full": "45 N 4th St Columbus OH 43215",
    "addr:housenumber": "45",
    "addr:postcode": "43215",
    "addr:street": "N 4Th St",
    "iso:country": "US",
    "sg:address": "45 N 4th St",
    "sg:city": "Columbus",
    "sg:classifiers": [
      {
        "category": "Government",
        "subcategory": "Office",
        "type": "Public Place"
      }
    ],
    "sg:phone": "+1 614 221 5853",
    "sg:postcode": "43215",
    "sg:province": "OH",
    "sg:tags": [
      "state",
      "resource"
    ],
    "wof:name": "School Employees State Retrmnt",
    "wof:placetype": "venue"
  },
  "geometry": {"coordinates":[-82.99653,39.963697],"type":"Point"}
}
