{
  "type": "Feature",
  "properties": {
    "addr:full": "14040 Kolter Rd Spencerville OH 45887",
    "addr:postcode": "14040;45887",
    "addr:street": "Kolter Rd",
    "iso:country": "US",
    "sg:address": "14040 Kolter Rd",
    "sg:city": "Spencerville",
    "sg:phone": "+1 419 647 6004",
    "sg:postcode": "45887",
    "sg:province": "OH",
    "sg:tags": [
      "farm",
      "corn"
    ],
    "wof:name": "McSpen Farms",
    "wof:placetype": "venue"
  },
  "geometry": {"coordinates":[-84.368897,40.699688],"type":"Point"}
}
