{
  "type": "Feature",
  "properties": {
    "addr:full": "838 N Lincoln Ave Salem OH 44460",
    "addr:housenumber": "838",
    "addr:postcode": "44460",
    "addr:street": "N Lincoln Ave",
    "iso:country": "US",
    "sg:address": "838 N Lincoln Ave",
    "sg:city": "Salem",
    "sg:classifiers": [
      {
        "category": "Manufacturing",
        "subcategory": "Printing",
        "type": "Manufacturing \u0026 Wholesale Goods"
      }
    ],
    "sg:phone": "+1 330 337 3387",
    "sg:postcode": "44460",
    "sg:province": "OH",
    "sg:tags": [
      "commercial"
    ],
    "wof:name": "Invitation Gallery",
    "wof:placetype": "venue"
  },
  "geometry": {"coordinates":[-80.848525,40.908975],"type":"Point"}
}
