{
  "type": "Feature",
  "properties": {
    "iso:country":"US",
    "sg:address":"612 Harrisburg Pike",
    "sg:city":"Columbus",
    "sg:classifiers":[
        {
            "category":"Retail",
            "subcategory":"Auto Repair",
            "type":"Services"
        }
    ],
    "sg:phone":"+1 614 228 0641",
    "sg:postcode":"43223",
    "sg:province":"OH",
    "sg:tags":[
        "repairing",
        "automobile"
    ],
    "wof:name":"Gray's Auto Svc",
    "wof:placetype":"venue"
},
  "geometry": {"coordinates":[-83.036953,39.944133],"type":"Point"}
}