{
  "type": "Feature",
  "properties": {
    "iso:country":"US",
    "sg:address":"770 State Rte 72",
    "sg:city":"Jamestown",
    "sg:phone":"+1 937 675 2464",
    "sg:postcode":"45335",
    "sg:province":"OH",
    "sg:tags":[
        "farm"
    ],
    "wof:name":"Friendly Knoll Farms",
    "wof:placetype":"venue"
},
  "geometry": {"coordinates":[-83.749205,39.697282],"type":"Point"}
}