{
  "type": "Feature",
  "properties": {
    "addr:full": "5136 US Hwy 33 Athens OH 45701",
    "addr:housenumber": "5136",
    "addr:postcode": "45701",
    "addr:street": "Us Hwy 33",
    "iso:country": "US",
    "sg:address": "5136 US Hwy 33",
    "sg:city": "Athens",
    "sg:classifiers": [
      {
        "category": "Shopping",
        "subcategory": "Gifts \u0026 Souvenirs",
        "type": "Retail Goods"
      }
    ],
    "sg:phone": "+1 740 592 6067",
    "sg:postcode": "45701",
    "sg:province": "OH",
    "wof:name": "Everything Russian",
    "wof:placetype": "venue"
  },
  "geometry": {"coordinates":[-82.06973,39.271418],"type":"Point"}
}
