{
  "type": "Feature",
  "properties": {
    "addr:full":"5575 Coakley Rd NW Carroll OH 43112",
    "addr:housenumber":"5575",
    "addr:postcode":"43112",
    "addr:street":"Coakley Rd Nw",
    "iso:country":"US",
    "sg:address":"5575 Coakley Rd NW",
    "sg:city":"Carroll",
    "sg:phone":"+1 740 756 7030",
    "sg:postcode":"43112",
    "sg:province":"OH",
    "sg:tags":[
        "farm",
        "corn",
        "soybean"
    ],
    "wof:name":"Harley Crow",
    "wof:placetype":"venue"
},
  "geometry": {"coordinates":[-82.68501999999999,39.809016],"type":"Point"}
}