{
  "type": "Feature",
  "properties": {
    "iso:country":"US",
    "sg:address":"794 E 3rd St",
    "sg:city":"Salem",
    "sg:classifiers":[
        {
            "category":"Personal",
            "subcategory":"Beauty Salon",
            "type":"Services"
        }
    ],
    "sg:phone":"+1 330 332 3343",
    "sg:postcode":"44460",
    "sg:province":"OH",
    "wof:name":"Cutting Edge Styling Salon",
    "wof:placetype":"venue"
},
  "geometry": {"coordinates":[-80.850132,40.903234],"type":"Point"}
}