{
  "type": "Feature",
  "properties": {
    "iso:country":"US",
    "sg:address":"730 W Main Cross St",
    "sg:city":"Findlay",
    "sg:classifiers":[
        {
            "category":"Insurance",
            "subcategory":"Insurance Agent",
            "type":"Services"
        }
    ],
    "sg:phone":"+1 419 422 0691",
    "sg:postcode":"45840",
    "sg:province":"OH",
    "wof:name":"Denny Putnam Agency",
    "wof:placetype":"venue"
},
  "geometry": {"coordinates":[-83.660999,41.040178],"type":"Point"}
}