{
  "type": "Feature",
  "properties": {
    "iso:country":"US",
    "sg:address":"3979 Medina Rd",
    "sg:city":"Akron",
    "sg:classifiers":[
        {
            "category":"Banks & Credit Unions",
            "subcategory":"Bank",
            "type":"Services"
        }
    ],
    "sg:phone":"+1 330 665 4536",
    "sg:postcode":"44333",
    "sg:province":"OH",
    "wof:name":"Charter One Bank NA",
    "wof:placetype":"venue"
},
  "geometry": {"coordinates":[-81.64073399999999,41.135955],"type":"Point"}
}