{
  "type": "Feature",
  "properties": {
    "addr:full": "3979 Medina Rd Akron OH 44333",
    "addr:housenumber": "3979",
    "addr:postcode": "44333",
    "addr:street": "Medina Rd",
    "iso:country": "US",
    "sg:address": "3979 Medina Rd",
    "sg:city": "Akron",
    "sg:classifiers": [
      {
        "category": "Banks \u0026 Credit Unions",
        "subcategory": "Bank",
        "type": "Services"
      }
    ],
    "sg:phone": "+1 330 665 4536",
    "sg:postcode": "44333",
    "sg:province": "OH",
    "wof:name": "Charter One Bank NA",
    "wof:placetype": "venue"
  },
  "geometry": {"coordinates":[-81.640734,41.135955],"type":"Point"}
}
