{
  "type": "Feature",
  "properties": {
    "iso:country":"US",
    "sg:address":"6836 Cochran Rd",
    "sg:city":"Cleveland",
    "sg:classifiers":[
        {
            "category":"Professional",
            "subcategory":"Business Services",
            "type":"Services"
        }
    ],
    "sg:phone":"+1 440 349 4124",
    "sg:postcode":"44139",
    "sg:province":"OH",
    "sg:tags":[
        "painter",
        "sign"
    ],
    "wof:name":"First Neon Signs & Svc",
    "wof:placetype":"venue"
},
  "geometry": {"coordinates":[-81.46939399999999,41.377104],"type":"Point"}
}