{
  "type": "Feature",
  "properties": {
    "addr:full": "6001 Cochran Rd Solon OH 44139",
    "addr:housenumber": "6001",
    "addr:postcode": "44139",
    "addr:street": "Cochran Rd",
    "iso:country": "US",
    "sg:address": "6001 Cochran Rd",
    "sg:city": "Solon",
    "sg:classifiers": [
      {
        "category": "Real Estate",
        "subcategory": "Real Estate Services",
        "type": "Services"
      }
    ],
    "sg:phone": "+1 440 542 0900",
    "sg:postcode": "44139",
    "sg:province": "OH",
    "sg:tags": [
      "management",
      "property"
    ],
    "wof:name": "Rockside Corporate Woods Llc",
    "wof:placetype": "venue"
  },
  "geometry": {"coordinates":[-81.468903,41.398201],"type":"Point"}
}
