{
  "type": "Feature",
  "properties": {
    "iso:country":"US",
    "sg:address":"1040 Higgs Ave",
    "sg:city":"Columbus",
    "sg:classifiers":[
        {
            "category":"Wholesale",
            "subcategory":"Metals & Minerals",
            "type":"Manufacturing & Wholesale Goods"
        }
    ],
    "sg:phone":"+1 614 294 0333",
    "sg:postcode":"43212",
    "sg:province":"OH",
    "sg:tags":[
        "center",
        "aluminum"
    ],
    "wof:name":"Tri State Aluminum",
    "wof:placetype":"venue"
},
  "geometry": {"coordinates":[-83.027545,39.978918],"type":"Point"}
}