{
  "type": "Feature",
  "properties": {
    "addr:full": "1040 Higgs Ave Columbus OH 43212",
    "addr:housenumber": "1040",
    "addr:postcode": "43212",
    "addr:street": "Higgs Ave",
    "iso:country": "US",
    "sg:address": "1040 Higgs Ave",
    "sg:city": "Columbus",
    "sg:classifiers": [
      {
        "category": "Wholesale",
        "subcategory": "Metals \u0026 Minerals",
        "type": "Manufacturing \u0026 Wholesale Goods"
      }
    ],
    "sg:phone": "+1 614 294 0333",
    "sg:postcode": "43212",
    "sg:province": "OH",
    "sg:tags": [
      "center",
      "aluminum"
    ],
    "wof:name": "Tri State Aluminum",
    "wof:placetype": "venue"
  },
  "geometry": {"coordinates":[-83.027545,39.978918],"type":"Point"}
}
