{
  "type": "Feature",
  "properties": {
    "iso:country":"US",
    "sg:address":"6000 Mahoning Ave",
    "sg:city":"Youngstown",
    "sg:classifiers":[
        {
            "category":"Shopping",
            "subcategory":"Department Store",
            "type":"Retail Goods"
        }
    ],
    "sg:phone":"+1 330 799 7373",
    "sg:postcode":"44515",
    "sg:province":"OH",
    "wof:name":"JC Penney",
    "wof:placetype":"venue"
},
  "geometry": {"coordinates":[-80.775138,41.099669],"type":"Point"}
}