{
  "type": "Feature",
  "properties": {
    "addr:full": "2730 N Forest Hill Rd Troy OH 45373",
    "addr:housenumber": "2730",
    "addr:postcode": "45373",
    "addr:street": "N Forest Hill Rd",
    "iso:country": "US",
    "sg:address": "2730 N Forest Hill Rd",
    "sg:city": "Troy",
    "sg:classifiers": [
      {
        "category": "Home \u0026 Garden",
        "subcategory": "Garden Supply",
        "type": "Retail Goods"
      }
    ],
    "sg:phone": "+1 937 332 0031",
    "sg:postcode": "45373",
    "sg:province": "OH",
    "wof:name": "Bed and Breakfast",
    "wof:placetype": "venue"
  },
  "geometry": {"coordinates":[-84.280969,40.074069],"type":"Point"}
}
