{
  "type": "Feature",
  "properties": {
    "iso:country":"US",
    "sg:address":"2730 N Forest Hill Rd",
    "sg:city":"Troy",
    "sg:classifiers":[
        {
            "category":"Home & Garden",
            "subcategory":"Garden Supply",
            "type":"Retail Goods"
        }
    ],
    "sg:phone":"+1 937 332 0031",
    "sg:postcode":"45373",
    "sg:province":"OH",
    "wof:name":"Bed and Breakfast",
    "wof:placetype":"venue"
},
  "geometry": {"coordinates":[-84.280969,40.074069],"type":"Point"}
}