{
  "type": "Feature",
  "properties": {
    "addr:full": "4525 Este Ave Cincinnati OH 45232",
    "addr:housenumber": "4525",
    "addr:postcode": "45232",
    "addr:street": "Este Ave",
    "iso:country": "US",
    "sg:address": "4525 Este Ave",
    "sg:city": "Cincinnati",
    "sg:classifiers": [
      {
        "category": "Building \u0026 Trades",
        "subcategory": "Construction",
        "type": "Services"
      }
    ],
    "sg:phone": "+1 513 542 8822",
    "sg:postcode": "45232",
    "sg:province": "OH",
    "sg:tags": [
      "general",
      "contractor"
    ],
    "wof:name": "C R \u0026 R",
    "wof:placetype": "venue"
  },
  "geometry": {"coordinates":[-84.512004,39.172167],"type":"Point"}
}
