{
  "type": "Feature",
  "properties": {
    "addr:full": "11005 Saint Clair Ave Cleveland OH 44108",
    "addr:housenumber": "11005",
    "addr:postcode": "44108",
    "addr:street": "Saint Clair Ave",
    "iso:country": "US",
    "sg:address": "11005 Saint Clair Ave",
    "sg:city": "Cleveland",
    "sg:classifiers": [
      {
        "category": "Autos \u0026 Motor Vehicles",
        "subcategory": "Fuel \u0026 Gas Station",
        "type": "Retail Goods"
      }
    ],
    "sg:phone": "+1 216 268 5645",
    "sg:postcode": "44108",
    "sg:province": "OH",
    "sg:tags": [
      "oil"
    ],
    "wof:name": "HFA",
    "wof:placetype": "venue"
  },
  "geometry": {"coordinates":[-81.606514,41.540942],"type":"Point"}
}
