{
  "type": "Feature",
  "properties": {
    "iso:country":"US",
    "sg:address":"340 Ashland Rd",
    "sg:city":"Mansfield",
    "sg:classifiers":[
        {
            "category":"Autos & Motor Vehicles",
            "subcategory":"Automobile Sales",
            "type":"Retail Goods"
        },
        {
            "category":"Manufacturing",
            "subcategory":"Motor Vehicles & Parts",
            "type":"Manufacturing & Wholesale Goods"
        }
    ],
    "sg:phone":"+1 419 524 7223",
    "sg:postcode":"44905",
    "sg:province":"OH",
    "sg:tags":[
        "body",
        "performance",
        "race",
        "dealer",
        "mfg"
    ],
    "wof:name":"Crafts Racing Products Inc",
    "wof:placetype":"venue"
},
  "geometry": {"coordinates":[-82.49401400000001,40.763787],"type":"Point"}
}