{
  "type": "Feature",
  "properties": {
    "iso:country":"US",
    "sg:address":"818 Trenton St",
    "sg:city":"Toronto",
    "sg:classifiers":[
        {
            "category":"Building & Trades",
            "subcategory":"Construction",
            "type":"Services"
        }
    ],
    "sg:phone":"+1 740 537 4410",
    "sg:postcode":"43964",
    "sg:province":"OH",
    "sg:tags":[
        "general",
        "contractor"
    ],
    "wof:name":"Scotts Contracting & Concrete",
    "wof:placetype":"venue"
},
  "geometry": {"coordinates":[-80.607773,40.459807],"type":"Point"}
}