{
  "type": "Feature",
  "properties": {
    "addr:full": "818 Trenton St Toronto OH 43964",
    "addr:housenumber": "818",
    "addr:postcode": "43964",
    "addr:street": "Trenton St",
    "iso:country": "US",
    "sg:address": "818 Trenton St",
    "sg:city": "Toronto",
    "sg:classifiers": [
      {
        "category": "Building \u0026 Trades",
        "subcategory": "Construction",
        "type": "Services"
      }
    ],
    "sg:phone": "+1 740 537 4410",
    "sg:postcode": "43964",
    "sg:province": "OH",
    "sg:tags": [
      "general",
      "contractor"
    ],
    "wof:name": "Scotts Contracting \u0026 Concrete",
    "wof:placetype": "venue"
  },
  "geometry": {"coordinates":[-80.607773,40.459807],"type":"Point"}
}
