{
  "type": "Feature",
  "properties": {
    "addr:full":"1105 Maple Ave Zanesville OH 43701",
    "addr:housenumber":"1105",
    "addr:postcode":"43701",
    "addr:street":"Maple Ave",
    "iso:country":"US",
    "sg:address":"1105 Maple Ave",
    "sg:city":"Zanesville",
    "sg:classifiers":[
        {
            "category":"Insurance",
            "subcategory":"Insurance Agent",
            "type":"Services"
        }
    ],
    "sg:phone":"+1 740 454 8770",
    "sg:postcode":"43701",
    "sg:province":"OH",
    "wof:name":"Tom Montgomery Insurance",
    "wof:placetype":"venue"
},
  "geometry": {"coordinates":[-82.01075299999999,39.953041],"type":"Point"}
}