{
  "type": "Feature",
  "properties": {
    "iso:country":"US",
    "sg:address":"8401 Axe Handle Rd",
    "sg:city":"Milford Center",
    "sg:phone":"+1 937 349 4383",
    "sg:postcode":"43045",
    "sg:province":"OH",
    "sg:tags":[
        "farm",
        "grain",
        "cash"
    ],
    "wof:name":"Adams Bros Farms",
    "wof:placetype":"venue"
},
  "geometry": {"coordinates":[-83.42341500000001,40.124053],"type":"Point"}
}