{
  "type": "Feature",
  "properties": {
    "iso:country":"US",
    "sg:address":"111 Main St",
    "sg:city":"Steubenville",
    "sg:classifiers":[
        {
            "category":"Banks & Credit Unions",
            "subcategory":"Investment Brokerage",
            "type":"Services"
        }
    ],
    "sg:phone":"+1 740 264 3250",
    "sg:postcode":"43939",
    "sg:province":"OH",
    "sg:tags":[
        "security"
    ],
    "wof:name":"A G Edwards & Sons",
    "wof:placetype":"venue"
},
  "geometry": {"coordinates":[-80.79452499999999,40.17676],"type":"Point"}
}