{
  "type": "Feature",
  "properties": {
    "iso:country":"US",
    "sg:address":"16922 S Canaan Rd",
    "sg:city":"Athens",
    "sg:classifiers":[
        {
            "category":"Professional",
            "subcategory":"Engineering",
            "type":"Services"
        }
    ],
    "sg:phone":"+1 740 592 5166",
    "sg:postcode":"45701",
    "sg:province":"OH",
    "sg:tags":[
        "engineer"
    ],
    "wof:name":"Gedeon Associates",
    "wof:placetype":"venue"
},
  "geometry": {"coordinates":[-81.98430500000001,39.293655],"type":"Point"}
}