{
  "type": "Feature",
  "properties": {
    "iso:country":"US",
    "sg:address":"30219 Detroit Rd",
    "sg:city":"Cleveland",
    "sg:classifiers":[
        {
            "category":"Shopping",
            "subcategory":"Computers & Home Electronics",
            "type":"Retail Goods"
        }
    ],
    "sg:phone":"+1 440 617 9650",
    "sg:postcode":"44145",
    "sg:province":"OH",
    "sg:tags":[
        "audio"
    ],
    "wof:name":"Audio Visions",
    "wof:placetype":"venue"
},
  "geometry": {"coordinates":[-81.95548100000001,41.463035],"type":"Point"}
}