{
  "type": "Feature",
  "properties": {
    "addr:full": "30219 Detroit Rd Cleveland OH 44145",
    "addr:housenumber": "30219",
    "addr:postcode": "44145",
    "addr:street": "Detroit Rd",
    "iso:country": "US",
    "sg:address": "30219 Detroit Rd",
    "sg:city": "Cleveland",
    "sg:classifiers": [
      {
        "category": "Shopping",
        "subcategory": "Computers \u0026 Home Electronics",
        "type": "Retail Goods"
      }
    ],
    "sg:phone": "+1 440 617 9650",
    "sg:postcode": "44145",
    "sg:province": "OH",
    "sg:tags": [
      "audio"
    ],
    "wof:name": "Audio Visions",
    "wof:placetype": "venue"
  },
  "geometry": {"coordinates":[-81.955481,41.463035],"type":"Point"}
}
