{
  "type": "Feature",
  "properties": {
    "iso:country":"US",
    "sg:address":"832 Eastern Ave",
    "sg:city":"Woodsfield",
    "sg:classifiers":[
        {
            "category":"Health Services",
            "subcategory":"Podiatrist",
            "type":"Services"
        }
    ],
    "sg:phone":"+1 740 472 2259",
    "sg:postcode":"43793",
    "sg:province":"OH",
    "wof:name":"Swiss Valley Foot & Ankle Ctr",
    "wof:placetype":"venue"
},
  "geometry": {"coordinates":[-81.101083,39.758614],"type":"Point"}
}