{
  "type": "Feature",
  "properties": {
    "iso:country":"US",
    "sg:address":"6350 Promler Ave NW",
    "sg:city":"North Canton",
    "sg:classifiers":[
        {
            "category":"Personal",
            "subcategory":"Beauty Salon",
            "type":"Services"
        }
    ],
    "sg:phone":"+1 330 497 1665",
    "sg:postcode":"44720",
    "sg:province":"OH",
    "wof:name":"77 Sunset Strip Hair & Nail",
    "wof:placetype":"venue"
},
  "geometry": {"coordinates":[-81.42850300000001,40.873068],"type":"Point"}
}