{
  "type": "Feature",
  "properties": {
    "addr:full": "1639 Brice Rd Reynoldsburg OH 43068",
    "addr:housenumber": "1639",
    "addr:postcode": "43068",
    "addr:street": "Brice Rd",
    "iso:country": "US",
    "sg:address": "1639 Brice Rd",
    "sg:city": "Reynoldsburg",
    "sg:classifiers": [
      {
        "category": "Food \u0026 Beverages",
        "subcategory": "Specialty",
        "type": "Retail Goods"
      }
    ],
    "sg:phone": "+1 614 866 7834",
    "sg:postcode": "43068",
    "sg:province": "OH",
    "sg:tags": [
      "vitamin"
    ],
    "wof:name": "American Nutrition",
    "wof:placetype": "venue"
  },
  "geometry": {"coordinates":[-82.829436,39.947762],"type":"Point"}
}
