{
  "type": "Feature",
  "properties": {
    "iso:country":"US",
    "sg:address":"190 Chestnut St",
    "sg:city":"Coshocton",
    "sg:classifiers":[
        {
            "category":"Shopping",
            "subcategory":"Tobacco",
            "type":"Retail Goods"
        }
    ],
    "sg:phone":"+1 740 622 2737",
    "sg:postcode":"43812",
    "sg:province":"OH",
    "sg:tags":[
        "cigarette",
        "cigar",
        "dealer"
    ],
    "wof:name":"Chestnut News & Tobacco",
    "wof:placetype":"venue"
},
  "geometry": {"coordinates":[-81.86892,40.275201],"type":"Point"}
}