{
  "type": "Feature",
  "properties": {
    "addr:full": "190 Chestnut St Coshocton OH 43812",
    "addr:housenumber": "190",
    "addr:postcode": "43812",
    "addr:street": "Chestnut St",
    "iso:country": "US",
    "sg:address": "190 Chestnut St",
    "sg:city": "Coshocton",
    "sg:classifiers": [
      {
        "category": "Shopping",
        "subcategory": "Tobacco",
        "type": "Retail Goods"
      }
    ],
    "sg:phone": "+1 740 622 2737",
    "sg:postcode": "43812",
    "sg:province": "OH",
    "sg:tags": [
      "cigarette",
      "cigar",
      "dealer"
    ],
    "wof:name": "Chestnut News \u0026 Tobacco",
    "wof:placetype": "venue"
  },
  "geometry": {"coordinates":[-81.86892,40.275201],"type":"Point"}
}
