{
  "type": "Feature",
  "properties": {
    "addr:full":"1625 Albon Rd Holland OH 43528",
    "addr:housenumber":"1625",
    "addr:postcode":"43528",
    "addr:street":"Albon Rd",
    "iso:country":"US",
    "sg:address":"1625 Albon Rd",
    "sg:city":"Holland",
    "sg:classifiers":[
        {
            "category":"Building & Trades",
            "subcategory":"Equipment Rental",
            "type":"Services"
        }
    ],
    "sg:phone":"+1 419 865 0245",
    "sg:postcode":"43528",
    "sg:province":"OH",
    "sg:tags":[
        "contractor"
    ],
    "wof:name":"Busch Rental & Trucking",
    "wof:placetype":"venue"
},
  "geometry": {"coordinates":[-83.73731600000001,41.611906],"type":"Point"}
}