{
  "type": "Feature",
  "properties": {
    "iso:country":"US",
    "sg:address":"8585 Industry Park Dr",
    "sg:city":"Piqua",
    "sg:classifiers":[
        {
            "category":"Retail",
            "subcategory":"Repair Shop",
            "type":"Services"
        }
    ],
    "sg:phone":"+1 937 778 8242",
    "sg:postcode":"45356",
    "sg:province":"OH",
    "sg:tags":[
        "welding"
    ],
    "wof:name":"Corex Inc",
    "wof:placetype":"venue"
},
  "geometry": {"coordinates":[-84.232652,40.160865],"type":"Point"}
}