{
  "type": "Feature",
  "properties": {
    "addr:full":"6929 Miami Ave Cincinnati OH 45243",
    "addr:housenumber":"6929",
    "addr:postcode":"45243",
    "addr:street":"Miami Ave",
    "iso:country":"US",
    "sg:address":"6929 Miami Ave",
    "sg:city":"Cincinnati",
    "sg:classifiers":[
        {
            "category":"Retail",
            "subcategory":"Laundry & Dry Cleaning",
            "type":"Services"
        }
    ],
    "sg:phone":"+1 513 561 9380",
    "sg:postcode":"45243",
    "sg:province":"OH",
    "sg:tags":[
        "drycleaning",
        "plant"
    ],
    "wof:name":"Kelloggs Cleaners & Launderers",
    "wof:placetype":"venue"
},
  "geometry": {"coordinates":[-84.36340199999999,39.18808],"type":"Point"}
}