{
  "type": "Feature",
  "properties": {
    "addr:full": "6929 Miami Ave Cincinnati OH 45243",
    "addr:housenumber": "6929",
    "addr:postcode": "45243",
    "addr:street": "Miami Ave",
    "iso:country": "US",
    "sg:address": "6929 Miami Ave",
    "sg:city": "Cincinnati",
    "sg:classifiers": [
      {
        "category": "Retail",
        "subcategory": "Laundry \u0026 Dry Cleaning",
        "type": "Services"
      }
    ],
    "sg:phone": "+1 513 561 9380",
    "sg:postcode": "45243",
    "sg:province": "OH",
    "sg:tags": [
      "drycleaning",
      "plant"
    ],
    "wof:name": "Kelloggs Cleaners \u0026 Launderers",
    "wof:placetype": "venue"
  },
  "geometry": {"coordinates":[-84.363402,39.18808],"type":"Point"}
}
