{
  "type": "Feature",
  "properties": {
    "addr:full": "2614 Edington Rd Columbus OH 43221",
    "addr:housenumber": "2614",
    "addr:postcode": "43221",
    "addr:street": "Edington Rd",
    "iso:country": "US",
    "sg:address": "2614 Edington Rd",
    "sg:city": "Columbus",
    "sg:classifiers": [
      {
        "category": "Building \u0026 Trades",
        "subcategory": "Construction",
        "type": "Services"
      }
    ],
    "sg:phone": "+1 614 488 1680",
    "sg:postcode": "43221",
    "sg:province": "OH",
    "sg:tags": [
      "general",
      "contractor"
    ],
    "wof:name": "J L Will \u0026 Co",
    "wof:placetype": "venue"
  },
  "geometry": {"coordinates":[-83.080876,40.01488],"type":"Point"}
}
