{
  "type": "Feature",
  "properties": {
    "iso:country":"US",
    "sg:address":"2614 Edington Rd",
    "sg:city":"Columbus",
    "sg:classifiers":[
        {
            "category":"Building & Trades",
            "subcategory":"Construction",
            "type":"Services"
        }
    ],
    "sg:phone":"+1 614 488 1680",
    "sg:postcode":"43221",
    "sg:province":"OH",
    "sg:tags":[
        "general",
        "contractor"
    ],
    "wof:name":"J L Will & Co",
    "wof:placetype":"venue"
},
  "geometry": {"coordinates":[-83.080876,40.01488],"type":"Point"}
}