{
  "type": "Feature",
  "properties": {
    "addr:full":"783 N Main St Mansfield OH 44902",
    "addr:housenumber":"783",
    "addr:postcode":"44902",
    "addr:street":"N Main St",
    "iso:country":"US",
    "sg:address":"783 N Main St",
    "sg:city":"Mansfield",
    "sg:classifiers":[
        {
            "category":"Recreation",
            "type":"Entertainment"
        }
    ],
    "sg:phone":"+1 419 522 1400",
    "sg:postcode":"44902",
    "sg:province":"OH",
    "sg:tags":[
        "club",
        "membership"
    ],
    "wof:name":"Cyclops Ball Field",
    "wof:placetype":"venue"
},
  "geometry": {"coordinates":[-82.513908,40.779984],"type":"Point"}
}