{
  "type": "Feature",
  "properties": {
    "iso:country":"US",
    "sg:address":"15 N Park Ave",
    "sg:city":"Wellston",
    "sg:classifiers":[
        {
            "category":"Sports & Exercise",
            "subcategory":"Bowling",
            "type":"Entertainment"
        }
    ],
    "sg:phone":"+1 740 384 6670",
    "sg:postcode":"45692",
    "sg:province":"OH",
    "sg:tags":[
        "center"
    ],
    "wof:name":"Trio Lanes",
    "wof:placetype":"venue"
},
  "geometry": {"coordinates":[-82.53582900000001,39.124489],"type":"Point"}
}