{
  "type": "Feature",
  "properties": {
    "addr:full": "15 N Park Ave Wellston OH 45692",
    "addr:housenumber": "15",
    "addr:postcode": "45692",
    "addr:street": "N Park Ave",
    "iso:country": "US",
    "sg:address": "15 N Park Ave",
    "sg:city": "Wellston",
    "sg:classifiers": [
      {
        "category": "Sports \u0026 Exercise",
        "subcategory": "Bowling",
        "type": "Entertainment"
      }
    ],
    "sg:phone": "+1 740 384 6670",
    "sg:postcode": "45692",
    "sg:province": "OH",
    "sg:tags": [
      "center"
    ],
    "wof:name": "Trio Lanes",
    "wof:placetype": "venue"
  },
  "geometry": {"coordinates":[-82.535829,39.124489],"type":"Point"}
}
