{
  "type": "Feature",
  "properties": {
    "addr:full":"7826 State Rte 49 Arcanum OH 45304",
    "addr:housenumber":"7826",
    "addr:postcode":"45304",
    "addr:street":"State Rte 49",
    "iso:country":"US",
    "sg:address":"7826 State Rte 49",
    "sg:city":"Arcanum",
    "sg:classifiers":[
        {
            "category":"Building & Trades",
            "subcategory":"Construction",
            "type":"Services"
        }
    ],
    "sg:phone":"+1 937 692 6470",
    "sg:postcode":"45304",
    "sg:province":"OH",
    "sg:tags":[
        "paving",
        "contractor"
    ],
    "wof:name":"Mid-America Surfaces Inc",
    "wof:placetype":"venue"
},
  "geometry": {"coordinates":[-84.514788,39.990803],"type":"Point"}
}