{
  "type": "Feature",
  "properties": {
    "addr:full":"1580 Fruitland Ave Cleveland OH 44124",
    "addr:housenumber":"1580",
    "addr:postcode":"44124",
    "addr:street":"Fruitland Ave",
    "iso:country":"US",
    "sg:address":"1580 Fruitland Ave",
    "sg:city":"Cleveland",
    "sg:classifiers":[
        {
            "category":"Shopping",
            "subcategory":"Gifts & Souvenirs",
            "type":"Retail Goods"
        }
    ],
    "sg:phone":"+1 440 473 4197",
    "sg:postcode":"44124",
    "sg:province":"OH",
    "wof:name":"Great Ideas & Gifts",
    "wof:placetype":"venue"
},
  "geometry": {"coordinates":[-81.453447,41.516967],"type":"Point"}
}