{
  "type": "Feature",
  "properties": {
    "addr:full": "538 Notre Dame Ave Dayton OH 45404",
    "addr:housenumber": "538",
    "addr:postcode": "45404",
    "addr:street": "Notre Dame Ave",
    "iso:country": "US",
    "sg:address": "538 Notre Dame Ave",
    "sg:city": "Dayton",
    "sg:classifiers": [
      {
        "category": "Professional",
        "type": "Services"
      }
    ],
    "sg:phone": "+1 937 223 2072",
    "sg:postcode": "45404",
    "sg:province": "OH",
    "wof:name": "Eric \u0026 Kimberly Riesenbeck",
    "wof:placetype": "venue"
  },
  "geometry": {"coordinates":[-84.171323,39.783875],"type":"Point"}
}
