{
  "type": "Feature",
  "properties": {
    "iso:country":"US",
    "sg:address":"538 Notre Dame Ave",
    "sg:city":"Dayton",
    "sg:classifiers":[
        {
            "category":"Professional",
            "type":"Services"
        }
    ],
    "sg:phone":"+1 937 223 2072",
    "sg:postcode":"45404",
    "sg:province":"OH",
    "wof:name":"Eric & Kimberly Riesenbeck",
    "wof:placetype":"venue"
},
  "geometry": {"coordinates":[-84.171323,39.783875],"type":"Point"}
}