{
  "type": "Feature",
  "properties": {
    "iso:country":"US",
    "sg:address":"9115 Freeway Dr",
    "sg:city":"Macedonia",
    "sg:classifiers":[
        {
            "category":"Manufacturing",
            "subcategory":"Metals",
            "type":"Manufacturing & Wholesale Goods"
        },
        {
            "category":"Autos & Motor Vehicles",
            "subcategory":"Auto Supplies",
            "type":"Retail Goods"
        }
    ],
    "sg:phone":"+1 330 467 0236",
    "sg:postcode":"44056",
    "sg:province":"OH",
    "sg:tags":[
        "wheel",
        "hubcap",
        "cap",
        "hub",
        "automobile"
    ],
    "wof:name":"Blackburn Hubcaps & Wheels LLC",
    "wof:placetype":"venue"
},
  "geometry": {"coordinates":[-81.511259,41.313857],"type":"Point"}
}