{
  "type": "Feature",
  "properties": {
    "iso:country":"US",
    "sg:address":"14038 Saint Clair Ave",
    "sg:city":"Cleveland",
    "sg:classifiers":[
        {
            "category":"Personal",
            "subcategory":"Barber",
            "type":"Services"
        }
    ],
    "sg:phone":"+1 216 541 5646",
    "sg:postcode":"44110",
    "sg:province":"OH",
    "wof:name":"East 141 St Barber Shop",
    "wof:placetype":"venue"
},
  "geometry": {"coordinates":[-81.58467,41.549434],"type":"Point"}
}