{
  "type": "Feature",
  "properties": {
    "addr:full":"269 E Paige Ave Barberton OH 44203",
    "addr:housenumber":"269",
    "addr:postcode":"44203",
    "addr:street":"E Paige Ave",
    "iso:country":"US",
    "sg:address":"269 E Paige Ave",
    "sg:city":"Barberton",
    "sg:classifiers":[
        {
            "category":"Retail",
            "subcategory":"Auto Repair",
            "type":"Services"
        }
    ],
    "sg:phone":"+1 330 745 5640",
    "sg:postcode":"44203",
    "sg:province":"OH",
    "sg:tags":[
        "body",
        "automobile",
        "painting"
    ],
    "wof:name":"East Side Body Shop Inc",
    "wof:placetype":"venue"
},
  "geometry": {"coordinates":[-81.59481700000001,41.015575],"type":"Point"}
}