{
  "type": "Feature",
  "properties": {
    "addr:full": "14855 Lancelot Ln W Cleveland OH 44133",
    "addr:housenumber": "14855",
    "addr:postcode": "44133",
    "addr:street": "Lancelot Ln W",
    "iso:country": "US",
    "sg:address": "14855 Lancelot Ln W",
    "sg:city": "Cleveland",
    "sg:classifiers": [
      {
        "category": "Building \u0026 Trades",
        "subcategory": "Construction",
        "type": "Services"
      }
    ],
    "sg:phone": "+1 440 582 0573",
    "sg:postcode": "44133",
    "sg:province": "OH",
    "sg:tags": [
      "general",
      "contractor"
    ],
    "wof:name": "Cedar Valley Homes",
    "wof:placetype": "venue"
  },
  "geometry": {"coordinates":[-81.774023,41.308455],"type":"Point"}
}
