{
  "type": "Feature",
  "properties": {
    "addr:full": "1102 Union St Ashland OH 44805",
    "addr:housenumber": "1102",
    "addr:postcode": "44805",
    "addr:street": "Union St",
    "iso:country": "US",
    "sg:address": "1102 Union St",
    "sg:city": "Ashland",
    "sg:classifiers": [
      {
        "category": "Building \u0026 Trades",
        "subcategory": "Plumbing",
        "type": "Services"
      }
    ],
    "sg:phone": "+1 419 289 8907",
    "sg:postcode": "44805",
    "sg:province": "OH",
    "sg:tags": [
      "contractor"
    ],
    "wof:name": "Ken Cellar Plumbing",
    "wof:placetype": "venue"
  },
  "geometry": {"coordinates":[-82.312835,40.876937],"type":"Point"}
}
