{
  "type": "Feature",
  "properties": {
    "iso:country":"US",
    "sg:address":"1102 Union St",
    "sg:city":"Ashland",
    "sg:classifiers":[
        {
            "category":"Building & Trades",
            "subcategory":"Plumbing",
            "type":"Services"
        }
    ],
    "sg:phone":"+1 419 289 8907",
    "sg:postcode":"44805",
    "sg:province":"OH",
    "sg:tags":[
        "contractor"
    ],
    "wof:name":"Ken Cellar Plumbing",
    "wof:placetype":"venue"
},
  "geometry": {"coordinates":[-82.31283500000001,40.876937],"type":"Point"}
}