{
  "type": "Feature",
  "properties": {
    "iso:country":"US",
    "sg:address":"6735 Newark Rd",
    "sg:city":"Nashport",
    "sg:classifiers":[
        {
            "category":"Retail",
            "subcategory":"Auto Repair",
            "type":"Services"
        }
    ],
    "sg:phone":"+1 740 452 9691",
    "sg:postcode":"43830",
    "sg:province":"OH",
    "sg:tags":[
        "automotive"
    ],
    "wof:name":"Clevers Towing",
    "wof:placetype":"venue"
},
  "geometry": {"coordinates":[-82.115904,40.037763],"type":"Point"}
}