{
  "type": "Feature",
  "properties": {
    "iso:country":"US",
    "sg:address":"4189 Swinger Rd",
    "sg:city":"Arcanum",
    "sg:classifiers":[
        {
            "category":"Building & Trades",
            "subcategory":"Construction",
            "type":"Services"
        }
    ],
    "sg:phone":"+1 937 547 0258",
    "sg:postcode":"45304",
    "sg:province":"OH",
    "sg:tags":[
        "residential"
    ],
    "wof:name":"T-Built",
    "wof:placetype":"venue"
},
  "geometry": {"coordinates":[-84.474827,40.040901],"type":"Point"}
}