{
  "type": "Feature",
  "properties": {
    "iso:country":"US",
    "sg:address":"750 Gilmore Dr",
    "sg:city":"Reynoldsburg",
    "sg:classifiers":[
        {
            "category":"Building & Trades",
            "subcategory":"Construction",
            "type":"Services"
        }
    ],
    "sg:phone":"+1 614 861 0949",
    "sg:postcode":"43068",
    "sg:province":"OH",
    "sg:tags":[
        "floor",
        "laying",
        "contractor"
    ],
    "wof:name":"Pauls Carpet Service",
    "wof:placetype":"venue"
},
  "geometry": {"coordinates":[-82.80403699999999,39.968144],"type":"Point"}
}