{
  "type": "Feature",
  "properties": {
    "addr:full": "6839 E Broad St Columbus OH 43213",
    "addr:housenumber": "6839",
    "addr:postcode": "43213",
    "addr:street": "E Broad St",
    "iso:country": "US",
    "sg:address": "6839 E Broad St",
    "sg:city": "Columbus",
    "sg:classifiers": [
      {
        "category": "Manufacturing",
        "subcategory": "Pet Food",
        "type": "Manufacturing \u0026 Wholesale Goods"
      },
      {
        "category": "Home \u0026 Garden",
        "subcategory": "Garden Supply",
        "type": "Retail Goods"
      }
    ],
    "sg:phone": "+1 614 860 1133",
    "sg:postcode": "43213",
    "sg:province": "OH",
    "sg:tags": [
      "feed",
      "mfg",
      "house",
      "prepared",
      "feeder",
      "bird"
    ],
    "wof:name": "Wild Birds Unlimited Inc",
    "wof:placetype": "venue"
  },
  "geometry": {"coordinates":[-82.821964,39.981759],"type":"Point"}
}
