{
  "type": "Feature",
  "properties": {
    "iso:country":"US",
    "sg:address":"6839 E Broad St",
    "sg:city":"Columbus",
    "sg:classifiers":[
        {
            "category":"Manufacturing",
            "subcategory":"Pet Food",
            "type":"Manufacturing & Wholesale Goods"
        },
        {
            "category":"Home & Garden",
            "subcategory":"Garden Supply",
            "type":"Retail Goods"
        }
    ],
    "sg:phone":"+1 614 860 1133",
    "sg:postcode":"43213",
    "sg:province":"OH",
    "sg:tags":[
        "feed",
        "mfg",
        "house",
        "prepared",
        "feeder",
        "bird"
    ],
    "wof:name":"Wild Birds Unlimited Inc",
    "wof:placetype":"venue"
},
  "geometry": {"coordinates":[-82.82196399999999,39.981759],"type":"Point"}
}