{
  "type": "Feature",
  "properties": {
    "addr:full": "36255 Reading Ave Willoughby OH 44094",
    "addr:postcode": "36255;44094",
    "addr:street": "Reading Ave",
    "iso:country": "US",
    "sg:address": "36255 Reading Ave",
    "sg:city": "Willoughby",
    "sg:classifiers": [
      {
        "category": "Manufacturing",
        "subcategory": "Furniture",
        "type": "Manufacturing \u0026 Wholesale Goods"
      },
      {
        "category": "Building \u0026 Trades",
        "subcategory": "Construction",
        "type": "Services"
      }
    ],
    "sg:phone": "+1 440 953 1780",
    "sg:postcode": "44094",
    "sg:province": "OH",
    "sg:tags": [
      "cabinet",
      "wood",
      "maker",
      "mfg"
    ],
    "wof:name": "Hruska Cabinet Company",
    "wof:placetype": "venue"
  },
  "geometry": {"coordinates":[-81.426341,41.634772],"type":"Point"}
}
