{
  "type": "Feature",
  "properties": {
    "iso:country":"US",
    "sg:address":"36255 Reading Ave",
    "sg:city":"Willoughby",
    "sg:classifiers":[
        {
            "category":"Manufacturing",
            "subcategory":"Furniture",
            "type":"Manufacturing & Wholesale Goods"
        },
        {
            "category":"Building & Trades",
            "subcategory":"Construction",
            "type":"Services"
        }
    ],
    "sg:phone":"+1 440 953 1780",
    "sg:postcode":"44094",
    "sg:province":"OH",
    "sg:tags":[
        "cabinet",
        "wood",
        "maker",
        "mfg"
    ],
    "wof:name":"Hruska Cabinet Company",
    "wof:placetype":"venue"
},
  "geometry": {"coordinates":[-81.42634099999999,41.634772],"type":"Point"}
}