{
  "type": "Feature",
  "properties": {
    "addr:full":"118 E Findlay St Carey OH 43316",
    "addr:housenumber":"118",
    "addr:postcode":"43316",
    "addr:street":"E Findlay St",
    "iso:country":"US",
    "sg:address":"118 E Findlay St",
    "sg:city":"Carey",
    "sg:classifiers":[
        {
            "category":"Restaurant",
            "type":"Food & Drink"
        }
    ],
    "sg:phone":"+1 419 396 7828",
    "sg:postcode":"43316",
    "sg:province":"OH",
    "sg:tags":[
        "eating"
    ],
    "wof:name":"Hong Kong",
    "wof:placetype":"venue"
},
  "geometry": {"coordinates":[-83.382052,40.952512],"type":"Point"}
}