{
  "type": "Feature",
  "properties": {
    "addr:full": "731 State Rte 15 Bryan OH 43506",
    "addr:housenumber": "731",
    "addr:postcode": "43506",
    "addr:street": "State Rte 15",
    "iso:country": "US",
    "sg:address": "731 State Rte 15",
    "sg:city": "Bryan",
    "sg:classifiers": [
      {
        "category": "Social Services",
        "type": "Services"
      }
    ],
    "sg:phone": "+1 419 633 7351",
    "sg:postcode": "43506",
    "sg:province": "OH",
    "sg:tags": [
      "counseling"
    ],
    "wof:name": "A Quiet Place",
    "wof:placetype": "venue"
  },
  "geometry": {"coordinates":[-84.550876,41.466469],"type":"Point"}
}
