{
  "type": "Feature",
  "properties": {
    "addr:full":"201 N Cleveland Massillon Rd Akron OH 44333",
    "addr:housenumber":"201",
    "addr:postcode":"44333",
    "addr:street":"N Cleveland Massillon Rd",
    "iso:country":"US",
    "sg:address":"201 N Cleveland Massillon Rd",
    "sg:city":"Akron",
    "sg:classifiers":[
        {
            "category":"Professional",
            "subcategory":"Lawyer & Legal Services",
            "type":"Services"
        }
    ],
    "sg:phone":"+1 330 864 3377",
    "sg:postcode":"44333",
    "sg:province":"OH",
    "sg:tags":[
        "attorney"
    ],
    "wof:name":"Patrick J Neman Co",
    "wof:placetype":"venue"
},
  "geometry": {"coordinates":[-81.637283,41.142069],"type":"Point"}
}