{
  "type": "Feature",
  "properties": {
    "iso:country":"US",
    "sg:address":"2121 Saint Clair Ave NE",
    "sg:city":"Cleveland",
    "sg:classifiers":[
        {
            "category":"Manufacturing",
            "subcategory":"Wood Products",
            "type":"Manufacturing & Wholesale Goods"
        }
    ],
    "sg:phone":"+1 216 781 4747",
    "sg:postcode":"44114",
    "sg:province":"OH",
    "sg:tags":[
        "coating",
        "powder",
        "mfg"
    ],
    "wof:name":"Decorative Veneer Inc",
    "wof:placetype":"venue"
},
  "geometry": {"coordinates":[-81.67766899999999,41.510101],"type":"Point"}
}