{
  "type": "Feature",
  "properties": {
    "addr:full":"3995 Commercial Blvd Cincinnati OH 45245",
    "addr:housenumber":"3995",
    "addr:postcode":"45245",
    "addr:street":"Commercial Blvd",
    "iso:country":"US",
    "sg:address":"3995 Commercial Blvd",
    "sg:city":"Cincinnati",
    "sg:classifiers":[
        {
            "category":"Retail",
            "subcategory":"Auto Repair",
            "type":"Services"
        }
    ],
    "sg:phone":"+1 513 752 2720",
    "sg:postcode":"45245",
    "sg:province":"OH",
    "sg:tags":[
        "body",
        "shop"
    ],
    "wof:name":"Maaco Auto Painting & Bodyworks",
    "wof:placetype":"venue"
},
  "geometry": {"coordinates":[-84.295097,39.0676],"type":"Point"}
}