{
  "type": "Feature",
  "properties": {
    "addr:full": "1210 S Mulberry St Troy OH 45373",
    "addr:housenumber": "1210",
    "addr:postcode": "45373",
    "addr:street": "S Mulberry St",
    "iso:country": "US",
    "sg:address": "1210 S Mulberry St",
    "sg:city": "Troy",
    "sg:classifiers": [
      {
        "category": "Building \u0026 Trades",
        "subcategory": "Construction",
        "type": "Services"
      }
    ],
    "sg:phone": "+1 937 339 8689",
    "sg:postcode": "45373",
    "sg:province": "OH",
    "sg:tags": [
      "hanging",
      "contractor"
    ],
    "wof:name": "Johnson Painting Jim",
    "wof:placetype": "venue"
  },
  "geometry": {"coordinates":[-84.205733,40.02791],"type":"Point"}
}
