{
  "type": "Feature",
  "properties": {
    "iso:country":"US",
    "sg:address":"4129 Upton Ave",
    "sg:city":"Toledo",
    "sg:classifiers":[
        {
            "category":"Building & Trades",
            "subcategory":"Construction",
            "type":"Services"
        }
    ],
    "sg:phone":"+1 419 473 2554",
    "sg:postcode":"43613",
    "sg:province":"OH",
    "sg:tags":[
        "repairing",
        "remodeling",
        "contractor"
    ],
    "wof:name":"O & S Ostachnowicz Inc",
    "wof:placetype":"venue"
},
  "geometry": {"coordinates":[-83.58965,41.693331],"type":"Point"}
}