{
  "type": "Feature",
  "properties": {
    "iso:country":"US",
    "sg:address":"16775 W Park Circle Dr",
    "sg:city":"Chagrin Falls",
    "sg:classifiers":[
        {
            "category":"Manufacturing",
            "subcategory":"Tools & Machinery",
            "type":"Manufacturing & Wholesale Goods"
        }
    ],
    "sg:phone":"+1 440 543 2222",
    "sg:postcode":"44023",
    "sg:province":"OH",
    "sg:tags":[
        "equipment",
        "system",
        "automation"
    ],
    "sg:website":"www.agautomation.com",
    "wof:name":"A G Automation",
    "wof:placetype":"venue"
},
  "geometry": {"coordinates":[-81.34886,41.415838],"type":"Point"}
}