{
  "type": "Feature",
  "properties": {
    "addr:full": "1108 Park Pl Dayton OH 45449",
    "addr:housenumber": "1108",
    "addr:postcode": "45449",
    "addr:street": "Park Pl",
    "iso:country": "US",
    "sg:address": "1108 Park Pl",
    "sg:city": "Dayton",
    "sg:classifiers": [
      {
        "category": "Manufacturing",
        "subcategory": "Tools \u0026 Machinery",
        "type": "Manufacturing \u0026 Wholesale Goods"
      }
    ],
    "sg:phone": "+1 937 859 8327",
    "sg:postcode": "45449",
    "sg:province": "OH",
    "sg:tags": [
      "industrial",
      "mfg"
    ],
    "wof:name": "Phoenix Tl \u0026 Mold Randy Smith",
    "wof:placetype": "venue"
  },
  "geometry": {"coordinates":[-84.253494,39.657028],"type":"Point"}
}
