{
  "type": "Feature",
  "properties": {
    "addr:full": "3580 Needmore Rd Dayton OH 45414",
    "addr:housenumber": "3580",
    "addr:postcode": "45414",
    "addr:street": "Needmore Rd",
    "iso:country": "US",
    "sg:address": "3580 Needmore Rd",
    "sg:city": "Dayton",
    "sg:phone": "+1 937 236 0620",
    "sg:postcode": "45414",
    "sg:province": "OH",
    "sg:tags": [
      "hydrologist"
    ],
    "wof:name": "Praxair Inc",
    "wof:placetype": "venue"
  },
  "geometry": {"coordinates":[-84.15838,39.820056],"type":"Point"}
}
