{
  "type": "Feature",
  "properties": {
    "addr:full": "9200 US Hwy 42 S Plain City OH 43064",
    "addr:housenumber": "9200",
    "addr:postcode": "43064",
    "addr:street": "Us Hwy 42 S Plain",
    "iso:country": "US",
    "sg:address": "9200 US Hwy 42 S",
    "sg:city": "Plain City",
    "sg:classifiers": [
      {
        "category": "Education",
        "subcategory": "School",
        "type": "Public Place"
      }
    ],
    "sg:phone": "+1 614 873 4642",
    "sg:postcode": "43064",
    "sg:province": "OH",
    "sg:website": "www.alder.k12.oh.us",
    "wof:name": "Jonathan Alder School Supt Ofc",
    "wof:placetype": "venue"
  },
  "geometry": {"coordinates":[-83.287172,40.075904],"type":"Point"}
}
