{
  "type": "Feature",
  "properties": {
    "iso:country":"US",
    "sg:address":"2124 E Dorothy Ln",
    "sg:city":"Kettering",
    "sg:classifiers":[
        {
            "category":"Personal",
            "type":"Services"
        }
    ],
    "sg:phone":"+1 937 298 2298",
    "sg:postcode":"45420",
    "sg:province":"OH",
    "sg:tags":[
        "consultant",
        "program",
        "health",
        "fitness"
    ],
    "wof:name":"Jenny Craig Weight Loss Ctr",
    "wof:placetype":"venue"
},
  "geometry": {"coordinates":[-84.123458,39.702596],"type":"Point"}
}