{
  "type": "Feature",
  "properties": {
    "iso:country":"US",
    "sg:address":"3648 Springdale Rd",
    "sg:city":"Cincinnati",
    "sg:classifiers":[
        {
            "category":"Manufacturing",
            "subcategory":"Printing",
            "type":"Manufacturing & Wholesale Goods"
        }
    ],
    "sg:phone":"+1 513 741 9056",
    "sg:postcode":"45251",
    "sg:province":"OH",
    "sg:tags":[
        "lithographic",
        "b",
        "commercial",
        "typesetting"
    ],
    "wof:name":"Minuteman Press",
    "wof:placetype":"venue"
},
  "geometry": {"coordinates":[-84.599515,39.246732],"type":"Point"}
}