{
  "type": "Feature",
  "properties": {
    "addr:full":"3648 Springdale Rd Cincinnati OH 45251",
    "addr:housenumber":"3648",
    "addr:postcode":"45251",
    "addr:street":"Springdale Rd",
    "iso:country":"US",
    "sg:address":"3648 Springdale Rd",
    "sg:city":"Cincinnati",
    "sg:classifiers":[
        {
            "category":"Manufacturing",
            "subcategory":"Printing",
            "type":"Manufacturing & Wholesale Goods"
        }
    ],
    "sg:phone":"+1 513 741 9056",
    "sg:postcode":"45251",
    "sg:province":"OH",
    "sg:tags":[
        "lithographic",
        "b",
        "commercial",
        "typesetting"
    ],
    "wof:name":"Minuteman Press",
    "wof:placetype":"venue"
},
  "geometry": {"coordinates":[-84.599515,39.246732],"type":"Point"}
}