{
  "type": "Feature",
  "properties": {
    "iso:country":"US",
    "sg:address":"1600 S Raccoon Rd",
    "sg:city":"Youngstown",
    "sg:classifiers":[
        {
            "category":"Personal",
            "subcategory":"Tattoo Parlor",
            "type":"Services"
        }
    ],
    "sg:phone":"+1 330 779 0778",
    "sg:postcode":"44515",
    "sg:province":"OH",
    "sg:tags":[
        "tattooing"
    ],
    "wof:name":"L P Tattooing",
    "wof:placetype":"venue"
},
  "geometry": {"coordinates":[-80.732395,41.08604],"type":"Point"}
}