{
  "type": "Feature",
  "properties": {
    "addr:full": "384 Newell Ave Akron OH 44305",
    "addr:housenumber": "384",
    "addr:postcode": "44305",
    "addr:street": "Newell Ave",
    "iso:country": "US",
    "sg:address": "384 Newell Ave",
    "sg:city": "Akron",
    "sg:classifiers": [
      {
        "category": "Wholesale",
        "subcategory": "Vending Machines",
        "type": "Manufacturing \u0026 Wholesale Goods"
      }
    ],
    "sg:phone": "+1 330 753 1238",
    "sg:postcode": "44305",
    "sg:province": "OH",
    "sg:tags": [
      "operated",
      "phonograph"
    ],
    "wof:name": "Castle Music",
    "wof:placetype": "venue"
  },
  "geometry": {"coordinates":[-81.448515,41.06883],"type":"Point"}
}
