{
  "type": "Feature",
  "properties": {
    "addr:full": "4184 E 178th St Cleveland OH 44128",
    "addr:housenumber": "4184",
    "addr:postcode": "44128",
    "addr:street": "E 178Th St",
    "iso:country": "US",
    "sg:address": "4184 E 178th St",
    "sg:city": "Cleveland",
    "sg:classifiers": [
      {
        "category": "Building \u0026 Trades",
        "subcategory": "Electrical",
        "type": "Services"
      }
    ],
    "sg:phone": "+1 216 283 6119",
    "sg:postcode": "44128",
    "sg:province": "OH",
    "sg:tags": [
      "electrical",
      "contractor"
    ],
    "wof:name": "Ted Smith Electric Co",
    "wof:placetype": "venue"
  },
  "geometry": {"coordinates":[-81.553647,41.445285],"type":"Point"}
}
