{
  "type": "Feature",
  "properties": {
    "iso:country":"US",
    "sg:address":"3601 Ayers Rd",
    "sg:city":"Millbury",
    "sg:classifiers":[
        {
            "category":"Health Services",
            "subcategory":"Doctor",
            "type":"Services"
        }
    ],
    "sg:phone":"+1 419 836 8300",
    "sg:postcode":"43447",
    "sg:province":"OH",
    "sg:tags":[
        "physician",
        "surgeon",
        "practice",
        "family"
    ],
    "wof:name":"Millbury Health Center",
    "wof:placetype":"venue"
},
  "geometry": {"coordinates":[-83.466588,41.573228],"type":"Point"}
}