{
  "type": "Feature",
  "properties": {
    "iso:country":"US",
    "sg:address":"275 Yellowtown Rd",
    "sg:city":"Patriot",
    "sg:classifiers":[
        {
            "category":"Building & Trades",
            "subcategory":"Pest Control",
            "type":"Services"
        }
    ],
    "sg:phone":"+1 740 446 3246",
    "sg:postcode":"45658",
    "sg:province":"OH",
    "wof:name":"Abba Pest Control",
    "wof:placetype":"venue"
},
  "geometry": {"coordinates":[-82.281558,38.777326],"type":"Point"}
}