{
  "type": "Feature",
  "properties": {
    "iso:country":"US",
    "sg:address":"31314 Center Ridge Rd",
    "sg:city":"Cleveland",
    "sg:classifiers":[
        {
            "category":"Health Services",
            "subcategory":"Doctor",
            "type":"Services"
        }
    ],
    "sg:phone":"+1 440 835 3892",
    "sg:postcode":"44145",
    "sg:province":"OH",
    "sg:tags":[
        "physician",
        "surgeon"
    ],
    "wof:name":"Francis L Mc Cafferty Inc",
    "wof:placetype":"venue"
},
  "geometry": {"coordinates":[-81.965125,41.421227],"type":"Point"}
}