{
  "type": "Feature",
  "properties": {
    "iso:country":"US",
    "sg:address":"3216 Ferry Rd",
    "sg:city":"Bellbrook",
    "sg:classifiers":[
        {
            "category":"Home & Garden",
            "subcategory":"Furniture",
            "type":"Retail Goods"
        }
    ],
    "sg:phone":"+1 937 848 4883",
    "sg:postcode":"45305",
    "sg:province":"OH",
    "wof:name":"R E Wampler",
    "wof:placetype":"venue"
},
  "geometry": {"coordinates":[-84.08811799999999,39.60042],"type":"Point"}
}