{
  "type": "Feature",
  "properties": {
    "addr:full": "3216 Ferry Rd Bellbrook OH 45305",
    "addr:housenumber": "3216",
    "addr:postcode": "45305",
    "addr:street": "Ferry Rd",
    "iso:country": "US",
    "sg:address": "3216 Ferry Rd",
    "sg:city": "Bellbrook",
    "sg:classifiers": [
      {
        "category": "Home \u0026 Garden",
        "subcategory": "Furniture",
        "type": "Retail Goods"
      }
    ],
    "sg:phone": "+1 937 848 4883",
    "sg:postcode": "45305",
    "sg:province": "OH",
    "wof:name": "R E Wampler",
    "wof:placetype": "venue"
  },
  "geometry": {"coordinates":[-84.088118,39.60042],"type":"Point"}
}
