{
  "type": "Feature",
  "properties": {
    "addr:full": "7811 Laurel Ave Cincinnati OH 45243",
    "addr:housenumber": "7811",
    "addr:postcode": "45243",
    "addr:street": "Laurel Ave",
    "iso:country": "US",
    "sg:address": "7811 Laurel Ave",
    "sg:city": "Cincinnati",
    "sg:classifiers": [
      {
        "category": "Professional",
        "subcategory": "Management \u0026 Consulting",
        "type": "Services"
      }
    ],
    "sg:phone": "+1 513 381 0666",
    "sg:postcode": "45243",
    "sg:province": "OH",
    "sg:tags": [
      "consultant",
      "business"
    ],
    "sg:website": "www.smc-one.com",
    "wof:name": "Stadium Management Co",
    "wof:placetype": "venue"
  },
  "geometry": {"coordinates":[-84.357656,39.190493],"type":"Point"}
}
