{
  "type": "Feature",
  "properties": {
    "addr:full":"8724 Co Hwy 235 Fredericksburg OH 44627",
    "addr:housenumber":"8724",
    "addr:postcode":"44627",
    "addr:street":"Co Hwy 235",
    "iso:country":"US",
    "sg:address":"8724 Co Hwy 235",
    "sg:city":"Fredericksburg",
    "sg:classifiers":[
        {
            "category":"Manufacturing",
            "subcategory":"Metals",
            "type":"Manufacturing & Wholesale Goods"
        }
    ],
    "sg:phone":"+1 330 695 3491",
    "sg:postcode":"44627",
    "sg:province":"OH",
    "sg:tags":[
        "refuse",
        "container",
        "mfg"
    ],
    "wof:name":"E-Pak Inc",
    "wof:placetype":"venue"
},
  "geometry": {"coordinates":[-81.81277900000001,40.651642],"type":"Point"}
}