{
  "type": "Feature",
  "properties": {
    "addr:full": "3400 Twp Rd 124 Cardington OH 43315",
    "addr:housenumber": "124",
    "addr:postcode": "3400;43315",
    "addr:street": "Twp Rd",
    "iso:country": "US",
    "sg:address": "3400 Twp Rd 124",
    "sg:city": "Cardington",
    "sg:classifiers": [
      {
        "category": "Insurance",
        "subcategory": "Insurance Agent",
        "type": "Services"
      }
    ],
    "sg:phone": "+1 419 864 6222",
    "sg:postcode": "43315",
    "sg:province": "OH",
    "wof:name": "Linda S Shepard Insurance",
    "wof:placetype": "venue"
  },
  "geometry": {"coordinates":[-82.847156,40.496903],"type":"Point"}
}
