{
  "type": "Feature",
  "properties": {
    "addr:full": "7405 Memphis Ave Cleveland OH 44144",
    "addr:housenumber": "7405",
    "addr:postcode": "44144",
    "addr:street": "Memphis Ave",
    "iso:country": "US",
    "sg:address": "7405 Memphis Ave",
    "sg:city": "Cleveland",
    "sg:classifiers": [
      {
        "category": "Wholesale",
        "subcategory": "Machinery \u0026 Supplies",
        "type": "Manufacturing \u0026 Wholesale Goods"
      }
    ],
    "sg:phone": "+1 216 351 6780",
    "sg:postcode": "44144",
    "sg:province": "OH",
    "sg:tags": [
      "casket"
    ],
    "wof:name": "Casket Urn \u0026 Monument Gallery",
    "wof:placetype": "venue"
  },
  "geometry": {"coordinates":[-81.737362,41.439902],"type":"Point"}
}
