{
  "type": "Feature",
  "properties": {
    "addr:full":"4840 Northfield Rd Cleveland OH 44128",
    "addr:housenumber":"4840",
    "addr:postcode":"44128",
    "addr:street":"Northfield Rd",
    "iso:country":"US",
    "sg:address":"4840 Northfield Rd",
    "sg:city":"Cleveland",
    "sg:classifiers":[
        {
            "category":"Shopping",
            "subcategory":"Optical Goods",
            "type":"Retail Goods"
        }
    ],
    "sg:phone":"+1 216 581 0800",
    "sg:postcode":"44128",
    "sg:province":"OH",
    "wof:name":"DOC Optics Ctr",
    "wof:placetype":"venue"
},
  "geometry": {"coordinates":[-81.526436,41.433975],"type":"Point"}
}