{
  "type": "Feature",
  "properties": {
    "addr:full":"799 Tibbetts Wick Rd Girard OH 44420",
    "addr:housenumber":"799",
    "addr:postcode":"44420",
    "addr:street":"Tibbetts Wick Rd",
    "iso:country":"US",
    "sg:address":"799 Tibbetts Wick Rd",
    "sg:city":"Girard",
    "sg:classifiers":[
        {
            "category":"Building & Trades",
            "subcategory":"Construction",
            "type":"Services"
        }
    ],
    "sg:phone":"+1 330 539 4066",
    "sg:postcode":"44420",
    "sg:province":"OH",
    "sg:tags":[
        "contractor"
    ],
    "wof:name":"Faith Roofing Siding",
    "wof:placetype":"venue"
},
  "geometry": {"coordinates":[-80.698932,41.183786],"type":"Point"}
}