{
  "type": "Feature",
  "properties": {
    "addr:full": "3326 Broadview Rd Cleveland OH 44109",
    "addr:housenumber": "3326",
    "addr:postcode": "44109",
    "addr:street": "Broadview Rd",
    "iso:country": "US",
    "sg:address": "3326 Broadview Rd",
    "sg:city": "Cleveland",
    "sg:classifiers": [
      {
        "category": "Education",
        "subcategory": "School",
        "type": "Public Place"
      }
    ],
    "sg:phone": "+1 216 635 1881",
    "sg:postcode": "44109",
    "sg:province": "OH",
    "sg:website": "www.constellationschools.com",
    "wof:name": "Constellation Community School",
    "wof:placetype": "venue"
  },
  "geometry": {"coordinates":[-81.704473,41.441454],"type":"Point"}
}
