{
  "type": "Feature",
  "properties": {
    "iso:country":"US",
    "sg:address":"15404 E Liverpool Rd",
    "sg:city":"East Liverpool",
    "sg:classifiers":[
        {
            "category":"Personal",
            "subcategory":"Beauty Salon",
            "type":"Services"
        }
    ],
    "sg:phone":"+1 330 386 4274",
    "sg:postcode":"43920",
    "sg:province":"OH",
    "wof:name":"Sue's Styling Salon",
    "wof:placetype":"venue"
},
  "geometry": {"coordinates":[-80.606391,40.678902],"type":"Point"}
}