{
  "type": "Feature",
  "properties": {
    "addr:full":"215 Sunrise Center Dr Zanesville OH 43701",
    "addr:housenumber":"215",
    "addr:postcode":"43701",
    "addr:street":"Sunrise Center Dr",
    "iso:country":"US",
    "sg:address":"215 Sunrise Center Dr",
    "sg:city":"Zanesville",
    "sg:classifiers":[
        {
            "category":"Health Services",
            "subcategory":"Chiropractor",
            "type":"Services"
        }
    ],
    "sg:phone":"+1 740 450 2225",
    "sg:postcode":"43701",
    "sg:province":"OH",
    "wof:name":"Rsty L Myers Chrpractic Physcn",
    "wof:placetype":"venue"
},
  "geometry": {"coordinates":[-81.980448,39.944439],"type":"Point"}
}