{
  "type": "Feature",
  "properties": {
    "addr:full": "920 E Wilbeth Rd Akron OH 44306",
    "addr:housenumber": "920",
    "addr:postcode": "44306",
    "addr:street": "E Wilbeth Rd",
    "iso:country": "US",
    "sg:address": "920 E Wilbeth Rd",
    "sg:city": "Akron",
    "sg:classifiers": [
      {
        "category": "Personal",
        "subcategory": "Beauty Salon",
        "type": "Services"
      }
    ],
    "sg:phone": "+1 330 724 6867",
    "sg:postcode": "44306",
    "sg:province": "OH",
    "wof:name": "Park Hill Beauty \u0026 Tanning Sln",
    "wof:placetype": "venue"
  },
  "geometry": {"coordinates":[-81.491976,41.039717],"type":"Point"}
}
