{
  "type": "Feature",
  "properties": {
    "addr:full":"1100 Lindale Ct Cincinnati OH 45215",
    "addr:housenumber":"1100",
    "addr:postcode":"45215",
    "addr:street":"Lindale Ct",
    "iso:country":"US",
    "sg:address":"1100 Lindale Ct",
    "sg:city":"Cincinnati",
    "sg:classifiers":[
        {
            "category":"Wholesale",
            "subcategory":"Hardware",
            "type":"Manufacturing & Wholesale Goods"
        }
    ],
    "sg:phone":"+1 513 769 5789",
    "sg:postcode":"45215",
    "sg:province":"OH",
    "sg:tags":[
        "water",
        "purification"
    ],
    "wof:name":"Benjoro Inc",
    "wof:placetype":"venue"
},
  "geometry": {"coordinates":[-84.456524,39.236474],"type":"Point"}
}