{
  "type": "Feature",
  "properties": {
    "addr:full": "8885 Basil Western Rd Canal Winchester OH 43110",
    "addr:housenumber": "8885",
    "addr:postcode": "43110",
    "addr:street": "Basil Western Rd",
    "iso:country": "US",
    "sg:address": "8885 Basil Western Rd",
    "sg:city": "Canal Winchester",
    "sg:classifiers": [
      {
        "category": "Education",
        "subcategory": "Dance Studio",
        "type": "Public Place"
      }
    ],
    "sg:phone": "+1 614 920 0200",
    "sg:postcode": "43110",
    "sg:province": "OH",
    "sg:tags": [
      "instruction",
      "dancing"
    ],
    "wof:name": "Dance Works Productions Inc",
    "wof:placetype": "venue"
  },
  "geometry": {"coordinates":[-82.761452,39.842624],"type":"Point"}
}
