{
  "type": "Feature",
  "properties": {
    "addr:full": "4698 Rocky River Dr Cleveland OH 44135",
    "addr:housenumber": "4698",
    "addr:postcode": "44135",
    "addr:street": "Rocky River Dr",
    "iso:country": "US",
    "sg:address": "4698 Rocky River Dr",
    "sg:city": "Cleveland",
    "sg:classifiers": [
      {
        "category": "Personal",
        "subcategory": "Barber",
        "type": "Services"
      }
    ],
    "sg:phone": "+1 216 362 1260",
    "sg:postcode": "44135",
    "sg:province": "OH",
    "wof:name": "Smitty's Barber Shop",
    "wof:placetype": "venue"
  },
  "geometry": {"coordinates":[-81.826425,41.428119],"type":"Point"}
}
