{
  "type": "Feature",
  "properties": {
    "addr:full":"102 N Bridge St SW Stone Creek OH 43840",
    "addr:housenumber":"102",
    "addr:postcode":"43840",
    "addr:street":"N Bridge St Sw Stone Creek",
    "iso:country":"US",
    "sg:address":"102 N Bridge St SW",
    "sg:city":"Stone Creek",
    "sg:classifiers":[
        {
            "category":"Government",
            "subcategory":"Office",
            "type":"Public Place"
        }
    ],
    "sg:phone":"+1 330 339 9083",
    "sg:postcode":"43840",
    "sg:province":"OH",
    "sg:tags":[
        "village"
    ],
    "wof:name":"Jefferson Twp Trustees Board",
    "wof:placetype":"venue"
},
  "geometry": {"coordinates":[-81.55905,40.398594],"type":"Point"}
}