{
  "type": "Feature",
  "properties": {
    "addr:full": "5121 Mayfield Rd Cleveland OH 44124",
    "addr:housenumber": "5121",
    "addr:postcode": "44124",
    "addr:street": "Mayfield Rd",
    "iso:country": "US",
    "sg:address": "5121 Mayfield Rd",
    "sg:city": "Cleveland",
    "sg:classifiers": [
      {
        "category": "Food \u0026 Beverages",
        "subcategory": "Groceries \u0026 Convenience Stores",
        "type": "Retail Goods"
      }
    ],
    "sg:phone": "+1 440 461 2800",
    "sg:postcode": "44124",
    "sg:province": "OH",
    "sg:tags": [
      "product"
    ],
    "wof:name": "Hana Asian Food",
    "wof:placetype": "venue"
  },
  "geometry": {"coordinates":[-81.493348,41.51996],"type":"Point"}
}
