{
  "type": "Feature",
  "properties": {
    "iso:country":"US",
    "sg:address":"3160 Valerie Arms Dr",
    "sg:city":"Dayton",
    "sg:classifiers":[
        {
            "category":"Shopping",
            "type":"Retail Goods"
        }
    ],
    "sg:phone":"+1 937 275 0473",
    "sg:postcode":"45405",
    "sg:province":"OH",
    "sg:tags":[
        "picture",
        "frame",
        "e"
    ],
    "wof:name":"Spiritual Gifts",
    "wof:placetype":"venue"
},
  "geometry": {"coordinates":[-84.239351,39.801327],"type":"Point"}
}