{
  "type": "Feature",
  "properties": {
    "iso:country":"US",
    "sg:address":"400 E 5th St",
    "sg:city":"Dayton",
    "sg:classifiers":[
        {
            "category":"Health Services",
            "subcategory":"Clinic",
            "type":"Services"
        }
    ],
    "sg:phone":"+1 937 223 3131",
    "sg:postcode":"45402",
    "sg:province":"OH",
    "sg:tags":[
        "home",
        "care",
        "help",
        "supply"
    ],
    "wof:name":"Spherion Corporation",
    "wof:placetype":"venue"
},
  "geometry": {"coordinates":[-84.185362,39.757138],"type":"Point"}
}