{
  "type": "Feature",
  "properties": {
    "addr:full": "3154 Redwood Rd Cleveland OH 44118",
    "addr:housenumber": "3154",
    "addr:postcode": "44118",
    "addr:street": "Redwood Rd",
    "iso:country": "US",
    "sg:address": "3154 Redwood Rd",
    "sg:city": "Cleveland",
    "sg:classifiers": [
      {
        "category": "Building \u0026 Trades",
        "subcategory": "Landscaping Services",
        "type": "Services"
      }
    ],
    "sg:phone": "+1 216 321 3037",
    "sg:postcode": "44118",
    "sg:province": "OH",
    "sg:tags": [
      "architect"
    ],
    "wof:name": "M J M Design \u0026 Construction",
    "wof:placetype": "venue"
  },
  "geometry": {"coordinates":[-81.567462,41.507252],"type":"Point"}
}
