{
  "type": "Feature",
  "properties": {
    "iso:country":"US",
    "sg:address":"3154 Redwood Rd",
    "sg:city":"Cleveland",
    "sg:classifiers":[
        {
            "category":"Building & Trades",
            "subcategory":"Landscaping Services",
            "type":"Services"
        }
    ],
    "sg:phone":"+1 216 321 3037",
    "sg:postcode":"44118",
    "sg:province":"OH",
    "sg:tags":[
        "architect"
    ],
    "wof:name":"M J M Design & Construction",
    "wof:placetype":"venue"
},
  "geometry": {"coordinates":[-81.567462,41.507252],"type":"Point"}
}