{
  "type": "Feature",
  "properties": {
    "addr:full": "28557 Barton Rd Logan OH 43138",
    "addr:housenumber": "28557",
    "addr:postcode": "43138",
    "addr:street": "Barton Rd",
    "iso:country": "US",
    "sg:address": "28557 Barton Rd",
    "sg:city": "Logan",
    "sg:classifiers": [
      {
        "category": "Building \u0026 Trades",
        "subcategory": "Construction",
        "type": "Services"
      }
    ],
    "sg:phone": "+1 740 385 1123",
    "sg:postcode": "43138",
    "sg:province": "OH",
    "sg:tags": [
      "contractor"
    ],
    "wof:name": "Michael R Menrath",
    "wof:placetype": "venue"
  },
  "geometry": {"coordinates":[-82.500677,39.440817],"type":"Point"}
}
