{
  "type": "Feature",
  "properties": {
    "addr:full": "316 Chapple Hill Dr NE Canton OH 44720",
    "addr:housenumber": "316",
    "addr:postcode": "44720",
    "addr:street": "Chapple Hill Dr Ne",
    "iso:country": "US",
    "sg:address": "316 Chapple Hill Dr NE",
    "sg:city": "Canton",
    "sg:classifiers": [
      {
        "category": "Building \u0026 Trades",
        "subcategory": "Landscaping Services",
        "type": "Services"
      }
    ],
    "sg:phone": "+1 330 499 6197",
    "sg:postcode": "44720",
    "sg:province": "OH",
    "wof:name": "Seebach Lawnscape",
    "wof:placetype": "venue"
  },
  "geometry": {"coordinates":[-81.398353,40.889173],"type":"Point"}
}
