{
  "type": "Feature",
  "properties": {
    "addr:full": "8227 W Chester Rd West Chester OH 45069",
    "addr:housenumber": "8227",
    "addr:postcode": "45069",
    "addr:street": "W Chester Rd",
    "iso:country": "US",
    "sg:address": "8227 W Chester Rd",
    "sg:city": "West Chester",
    "sg:classifiers": [
      {
        "category": "Food \u0026 Beverages",
        "subcategory": "Specialty",
        "type": "Retail Goods"
      }
    ],
    "sg:phone": "+1 513 759 0070",
    "sg:postcode": "45069",
    "sg:province": "OH",
    "sg:tags": [
      "vitamin"
    ],
    "wof:name": "Areawide Wellness Assoc",
    "wof:placetype": "venue"
  },
  "geometry": {"coordinates":[-84.355677,39.31765],"type":"Point"}
}
