{
  "type": "Feature",
  "properties": {
    "addr:full":"616 Borcherding Rd Woodville OH 43469",
    "addr:housenumber":"616",
    "addr:postcode":"43469",
    "addr:street":"Borcherding Rd",
    "iso:country":"US",
    "sg:address":"616 Borcherding Rd",
    "sg:city":"Woodville",
    "sg:classifiers":[
        {
            "category":"Building & Trades",
            "subcategory":"Plumbing",
            "type":"Services"
        }
    ],
    "sg:phone":"+1 419 849 3935",
    "sg:postcode":"43469",
    "sg:province":"OH",
    "sg:tags":[
        "contractor"
    ],
    "wof:name":"William Bsdcker Son Plbg Hatng",
    "wof:placetype":"venue"
},
  "geometry": {"coordinates":[-83.37204699999999,41.439068],"type":"Point"}
}