{
  "type": "Feature",
  "properties": {
    "addr:full": "21 W College St Oberlin OH 44074",
    "addr:housenumber": "21",
    "addr:postcode": "44074",
    "addr:street": "W College St",
    "iso:country": "US",
    "sg:address": "21 W College St",
    "sg:city": "Oberlin",
    "sg:classifiers": [
      {
        "category": "Restaurant",
        "type": "Food \u0026 Drink"
      }
    ],
    "sg:phone": "+1 440 774 7744",
    "sg:postcode": "44074",
    "sg:province": "OH",
    "sg:tags": [
      "boutique",
      "lady"
    ],
    "wof:name": "Trendy Wendys",
    "wof:placetype": "venue"
  },
  "geometry": {"coordinates":[-82.218103,41.291584],"type":"Point"}
}
