{
  "type": "Feature",
  "properties": {
    "iso:country":"US",
    "sg:address":"21 W College St",
    "sg:city":"Oberlin",
    "sg:classifiers":[
        {
            "category":"Restaurant",
            "type":"Food & Drink"
        }
    ],
    "sg:phone":"+1 440 774 7744",
    "sg:postcode":"44074",
    "sg:province":"OH",
    "sg:tags":[
        "boutique",
        "lady"
    ],
    "wof:name":"Trendy Wendys",
    "wof:placetype":"venue"
},
  "geometry": {"coordinates":[-82.218103,41.291584],"type":"Point"}
}