{
  "type": "Feature",
  "properties": {
    "iso:country":"US",
    "sg:address":"18597 State Rte 49",
    "sg:city":"Edon",
    "sg:classifiers":[
        {
            "category":"Retail",
            "subcategory":"Auto Repair",
            "type":"Services"
        }
    ],
    "sg:phone":"+1 419 459 4593",
    "sg:postcode":"43518",
    "sg:province":"OH",
    "sg:tags":[
        "repairing",
        "automobile"
    ],
    "wof:name":"Slater's Auto Repair",
    "wof:placetype":"venue"
},
  "geometry": {"coordinates":[-84.74764500000001,41.690283],"type":"Point"}
}