{
  "type": "Feature",
  "properties": {
    "addr:full": "35095 Center Ridge Rd North Ridgeville OH 44039",
    "addr:housenumber": "35095",
    "addr:postcode": "44039",
    "addr:street": "Center Ridge Rd",
    "iso:country": "US",
    "sg:address": "35095 Center Ridge Rd",
    "sg:city": "North Ridgeville",
    "sg:classifiers": [
      {
        "category": "Real Estate",
        "subcategory": "Real Estate Services",
        "type": "Services"
      }
    ],
    "sg:phone": "+1 440 327 0888",
    "sg:postcode": "44039",
    "sg:province": "OH",
    "sg:tags": [
      "company",
      "title"
    ],
    "wof:name": "Real Living Title",
    "wof:placetype": "venue"
  },
  "geometry": {"coordinates":[-82.008011,41.393249],"type":"Point"}
}
