{
  "type": "Feature",
  "properties": {
    "iso:country":"US",
    "sg:address":"5632 Kirkland Rd",
    "sg:city":"Toledo",
    "sg:classifiers":[
        {
            "category":"Professional",
            "subcategory":"Management & Consulting",
            "type":"Services"
        }
    ],
    "sg:phone":"+1 419 536 6748",
    "sg:postcode":"43615",
    "sg:province":"OH",
    "sg:tags":[
        "consultant",
        "business"
    ],
    "wof:name":"Innovative Results Consulting",
    "wof:placetype":"venue"
},
  "geometry": {"coordinates":[-83.67730299999999,41.673628],"type":"Point"}
}