{
  "type": "Feature",
  "properties": {
    "addr:full": "5632 Kirkland Rd Toledo OH 43615",
    "addr:housenumber": "5632",
    "addr:postcode": "43615",
    "addr:street": "Kirkland Rd",
    "iso:country": "US",
    "sg:address": "5632 Kirkland Rd",
    "sg:city": "Toledo",
    "sg:classifiers": [
      {
        "category": "Professional",
        "subcategory": "Management \u0026 Consulting",
        "type": "Services"
      }
    ],
    "sg:phone": "+1 419 536 6748",
    "sg:postcode": "43615",
    "sg:province": "OH",
    "sg:tags": [
      "consultant",
      "business"
    ],
    "wof:name": "Innovative Results Consulting",
    "wof:placetype": "venue"
  },
  "geometry": {"coordinates":[-83.677303,41.673628],"type":"Point"}
}
