{
  "type": "Feature",
  "properties": {
    "addr:full":"2151 Losantiville Ave Cincinnati OH 45237",
    "addr:housenumber":"2151",
    "addr:postcode":"45237",
    "addr:street":"Losantiville Ave",
    "iso:country":"US",
    "sg:address":"2151 Losantiville Ave",
    "sg:city":"Cincinnati",
    "sg:classifiers":[
        {
            "category":"Food & Beverages",
            "subcategory":"Groceries & Convenience Stores",
            "type":"Retail Goods"
        }
    ],
    "sg:phone":"+1 513 531 5006",
    "sg:postcode":"45237",
    "sg:province":"OH",
    "sg:website":"www.udfinc.com",
    "wof:name":"United Dairy Farmers",
    "wof:placetype":"venue"
},
  "geometry": {"coordinates":[-84.453035,39.191164],"type":"Point"}
}