{
  "type": "Feature",
  "properties": {
    "iso:country":"US",
    "sg:address":"1609 E 36th St",
    "sg:city":"Cleveland",
    "sg:classifiers":[
        {
            "category":"Restaurant",
            "type":"Food & Drink"
        }
    ],
    "sg:phone":"+1 216 881 2210",
    "sg:postcode":"44114",
    "sg:province":"OH",
    "wof:name":"Minas Tsambounieris",
    "wof:placetype":"venue"
},
  "geometry": {"coordinates":[-81.664193,41.511125],"type":"Point"}
}