{
  "type": "Feature",
  "properties": {
    "addr:full":"1380 Pearl Rd Brunswick OH 44212",
    "addr:housenumber":"1380",
    "addr:postcode":"44212",
    "addr:street":"Pearl Rd",
    "iso:country":"US",
    "sg:address":"1380 Pearl Rd",
    "sg:city":"Brunswick",
    "sg:classifiers":[
        {
            "category":"Social Services",
            "type":"Services"
        }
    ],
    "sg:phone":"+1 330 220 3611",
    "sg:postcode":"44212",
    "sg:province":"OH",
    "sg:tags":[
        "counselor",
        "marriage",
        "family"
    ],
    "wof:name":"Susan L Snider",
    "wof:placetype":"venue"
},
  "geometry": {"coordinates":[-81.84141099999999,41.23876],"type":"Point"}
}