{
  "type": "Feature",
  "properties": {
    "addr:full":"179 Ohio Ave NW Warren OH 44485",
    "addr:housenumber":"179",
    "addr:postcode":"44485",
    "addr:street":"Ohio Ave Nw",
    "iso:country":"US",
    "sg:address":"179 Ohio Ave NW",
    "sg:city":"Warren",
    "sg:classifiers":[
        {
            "category":"Building & Trades",
            "subcategory":"Landscaping Services",
            "type":"Services"
        }
    ],
    "sg:phone":"+1 330 219 2327",
    "sg:postcode":"44485",
    "sg:province":"OH",
    "sg:tags":[
        "lawn",
        "maintenance",
        "grounds"
    ],
    "wof:name":"Panda Bear Lawn Care",
    "wof:placetype":"venue"
},
  "geometry": {"coordinates":[-80.838307,41.236701],"type":"Point"}
}