{
  "type": "Feature",
  "properties": {
    "addr:full":"17826 Canterbury Rd Cleveland OH 44119",
    "addr:housenumber":"17826",
    "addr:postcode":"44119",
    "addr:street":"Canterbury Rd",
    "iso:country":"US",
    "sg:address":"17826 Canterbury Rd",
    "sg:city":"Cleveland",
    "sg:classifiers":[
        {
            "category":"Professional",
            "subcategory":"Computer Services",
            "type":"Services"
        }
    ],
    "sg:phone":"+1 216 481 7500",
    "sg:postcode":"44119",
    "sg:province":"OH",
    "sg:tags":[
        "website",
        "design"
    ],
    "wof:name":"Mediazen",
    "wof:placetype":"venue"
},
  "geometry": {"coordinates":[-81.553951,41.592094],"type":"Point"}
}