{
  "type": "Feature",
  "properties": {
    "iso:country":"US",
    "sg:address":"6607 Wade Park Ave",
    "sg:city":"Cleveland",
    "sg:classifiers":[
        {
            "category":"Bars & Pubs",
            "type":"Food & Drink"
        }
    ],
    "sg:phone":"+1 216 881 9148",
    "sg:postcode":"44103",
    "sg:province":"OH",
    "sg:tags":[
        "bar"
    ],
    "wof:name":"Keystone Cafe Inc",
    "wof:placetype":"venue"
},
  "geometry": {"coordinates":[-81.64129,41.515813],"type":"Point"}
}