{
  "type": "Feature",
  "properties": {
    "iso:country":"US",
    "sg:address":"1738 Woodland Ave NW",
    "sg:city":"Canton",
    "sg:classifiers":[
        {
            "category":"Manufacturing",
            "subcategory":"Printing",
            "type":"Manufacturing & Wholesale Goods"
        }
    ],
    "sg:phone":"+1 330 453 2460",
    "sg:postcode":"44703",
    "sg:province":"OH",
    "sg:tags":[
        "publishing"
    ],
    "wof:name":"Creative Works Publishing",
    "wof:placetype":"venue"
},
  "geometry": {"coordinates":[-81.379087,40.818292],"type":"Point"}
}