{
  "type": "Feature",
  "properties": {
    "addr:full": "7313 W Chester Rd West Chester OH 45069",
    "addr:housenumber": "7313",
    "addr:postcode": "45069",
    "addr:street": "W Chester Rd",
    "iso:country": "US",
    "sg:address": "7313 W Chester Rd",
    "sg:city": "West Chester",
    "sg:classifiers": [
      {
        "category": "Wholesale",
        "subcategory": "Electrical",
        "type": "Manufacturing \u0026 Wholesale Goods"
      }
    ],
    "sg:phone": "+1 513 942 1287",
    "sg:postcode": "45069",
    "sg:province": "OH",
    "sg:tags": [
      "communications",
      "design",
      "system"
    ],
    "wof:name": "Quasonix LLC",
    "wof:placetype": "venue"
  },
  "geometry": {"coordinates":[-84.386021,39.321367],"type":"Point"}
}
