{
  "type": "Feature",
  "properties": {
    "iso:country":"US",
    "sg:address":"4756 W Bancroft St",
    "sg:city":"Toledo",
    "sg:classifiers":[
        {
            "category":"Professional",
            "subcategory":"Testing Lab",
            "type":"Services"
        }
    ],
    "sg:phone":"+1 419 855 7764",
    "sg:postcode":"43615",
    "sg:province":"OH",
    "sg:tags":[
        "construction",
        "material"
    ],
    "wof:name":"Craig Technologies",
    "wof:placetype":"venue"
},
  "geometry": {"coordinates":[-83.650402,41.6625],"type":"Point"}
}