{
  "type": "Feature",
  "properties": {
    "addr:full":"2296 Scott St Napoleon OH 43545",
    "addr:housenumber":"2296",
    "addr:postcode":"43545",
    "addr:street":"Scott St",
    "iso:country":"US",
    "sg:address":"2296 Scott St",
    "sg:city":"Napoleon",
    "sg:classifiers":[
        {
            "category":"Restaurant",
            "type":"Food & Drink"
        }
    ],
    "sg:menulink":"http://www.allmenus.com/oh/napoleon/170346-burger-king/menu/",
    "sg:phone":"+1 419 599 1700",
    "sg:postcode":"43545",
    "sg:province":"OH",
    "sg:tags":[
        "burger",
        "american"
    ],
    "wof:name":"Burger King",
    "wof:placetype":"venue"
},
  "geometry": {"coordinates":[-84.132003,41.409842],"type":"Point"}
}