{
  "type": "Feature",
  "properties": {
    "addr:full": "2219 Massachusetts Ave SE Massillon OH 44646",
    "addr:housenumber": "2219",
    "addr:postcode": "44646",
    "addr:street": "Massachusetts Ave Se",
    "iso:country": "US",
    "sg:address": "2219 Massachusetts Ave SE",
    "sg:city": "Massillon",
    "sg:classifiers": [
      {
        "category": "Education",
        "subcategory": "School",
        "type": "Public Place"
      }
    ],
    "sg:phone": "+1 330 830 1839",
    "sg:postcode": "44646",
    "sg:province": "OH",
    "wof:name": "York Elementary School",
    "wof:placetype": "venue"
  },
  "geometry": {"coordinates":[-81.492468,40.796443],"type":"Point"}
}
