{
  "type": "Feature",
  "properties": {
    "addr:full": "6140 US Rte 127 Celina OH 45822",
    "addr:housenumber": "6140",
    "addr:postcode": "45822",
    "addr:street": "Us Rte 127",
    "iso:country": "US",
    "sg:address": "6140 US Rte 127",
    "sg:city": "Celina",
    "sg:classifiers": [
      {
        "category": "Building \u0026 Trades",
        "subcategory": "Construction",
        "type": "Services"
      }
    ],
    "sg:phone": "+1 419 584 0157",
    "sg:postcode": "45822",
    "sg:province": "OH",
    "sg:tags": [
      "utility",
      "contractor"
    ],
    "wof:name": "Henkels \u0026 Mc Coy Inc",
    "wof:placetype": "venue"
  },
  "geometry": {"coordinates":[-84.577188,40.525532],"type":"Point"}
}
