{
  "type": "Feature",
  "properties": {
    "addr:full": "5265 Tractor Rd Toledo OH 43612",
    "addr:postcode": "5265;43612",
    "addr:street": "Tractor Rd",
    "iso:country": "US",
    "sg:address": "5265 Tractor Rd",
    "sg:city": "Toledo",
    "sg:classifiers": [
      {
        "category": "Professional",
        "subcategory": "Business Services",
        "type": "Services"
      }
    ],
    "sg:phone": "+1 419 478 8555",
    "sg:postcode": "43612",
    "sg:province": "OH",
    "sg:tags": [
      "packaging",
      "chemical",
      "contract",
      "labeling",
      "laboratory"
    ],
    "wof:name": "Nationwide Chemical \u0026 Products",
    "wof:placetype": "venue"
  },
  "geometry": {"coordinates":[-83.553005,41.707251],"type":"Point"}
}
