{
  "type": "Feature",
  "properties": {
    "addr:full":"5798 State Rte 109 Leipsic OH 45856",
    "addr:housenumber":"5798",
    "addr:postcode":"45856",
    "addr:street":"State Rte 109",
    "iso:country":"US",
    "sg:address":"5798 State Rte 109",
    "sg:city":"Leipsic",
    "sg:classifiers":[
        {
            "category":"Shopping",
            "subcategory":"Used Merchandise",
            "type":"Retail Goods"
        }
    ],
    "sg:phone":"+1 419 943 2759",
    "sg:postcode":"45856",
    "sg:province":"OH",
    "sg:tags":[
        "antique"
    ],
    "wof:name":"Jan & Mike's Keepsakes",
    "wof:placetype":"venue"
},
  "geometry": {"coordinates":[-84.042124,41.096691],"type":"Point"}
}