{
  "type": "Feature",
  "properties": {
    "iso:country":"US",
    "sg:address":"1612 Victoria Ave",
    "sg:city":"Cleveland",
    "sg:classifiers":[
        {
            "category":"Building & Trades",
            "subcategory":"Landscaping Services",
            "type":"Services"
        }
    ],
    "sg:phone":"+1 440 781 4549",
    "sg:postcode":"44107",
    "sg:province":"OH",
    "sg:tags":[
        "lawn",
        "maintenance",
        "grounds"
    ],
    "wof:name":"Traditional Lawn Care",
    "wof:placetype":"venue"
},
  "geometry": {"coordinates":[-81.801101,41.481006],"type":"Point"}
}