{
  "type": "Feature",
  "properties": {
    "addr:full": "1985 Bellbrook Ave Xenia OH 45385",
    "addr:housenumber": "1985",
    "addr:postcode": "45385",
    "addr:street": "Bellbrook Ave",
    "iso:country": "US",
    "sg:address": "1985 Bellbrook Ave",
    "sg:city": "Xenia",
    "sg:classifiers": [
      {
        "category": "Restaurant",
        "type": "Food \u0026 Drink"
      }
    ],
    "sg:phone": "+1 937 372 5881",
    "sg:postcode": "45385",
    "sg:province": "OH",
    "wof:name": "Between Buns Cafe",
    "wof:placetype": "venue"
  },
  "geometry": {"coordinates":[-83.957947,39.669485],"type":"Point"}
}
