{
  "type": "Feature",
  "properties": {
    "addr:full":"102 Harding Way W Galion OH 44833",
    "addr:housenumber":"102",
    "addr:postcode":"44833",
    "addr:street":"Harding Way W",
    "iso:country":"US",
    "sg:address":"102 Harding Way W",
    "sg:city":"Galion",
    "sg:classifiers":[
        {
            "category":"Shopping",
            "subcategory":"Department Store",
            "type":"Retail Goods"
        }
    ],
    "sg:phone":"+1 419 468 4444",
    "sg:postcode":"44833",
    "sg:province":"OH",
    "wof:name":"JC Penney",
    "wof:placetype":"venue"
},
  "geometry": {"coordinates":[-82.791173,40.734008],"type":"Point"}
}