{
  "type": "Feature",
  "properties": {
    "addr:full":"9275 James Rd Nashport OH 43830",
    "addr:housenumber":"9275",
    "addr:postcode":"43830",
    "addr:street":"James Rd",
    "iso:country":"US",
    "sg:address":"9275 James Rd",
    "sg:city":"Nashport",
    "sg:classifiers":[
        {
            "category":"Restaurant",
            "type":"Food & Drink"
        }
    ],
    "sg:phone":"+1 740 754 2066",
    "sg:postcode":"43830",
    "sg:province":"OH",
    "sg:tags":[
        "eating"
    ],
    "wof:name":"Crenos Pizza",
    "wof:placetype":"venue"
},
  "geometry": {"coordinates":[-82.161055,40.072473],"type":"Point"}
}