{
  "type": "Feature",
  "properties": {
    "addr:full":"402 Cleveland St Elyria OH 44035",
    "addr:housenumber":"402",
    "addr:postcode":"44035",
    "addr:street":"Cleveland St",
    "iso:country":"US",
    "sg:address":"402 Cleveland St",
    "sg:city":"Elyria",
    "sg:classifiers":[
        {
            "category":"Retail",
            "subcategory":"Animal Services",
            "type":"Services"
        }
    ],
    "sg:phone":"+1 440 322 0661",
    "sg:postcode":"44035",
    "sg:province":"OH",
    "sg:tags":[
        "pet",
        "grooming",
        "washing"
    ],
    "wof:name":"Precious Pup",
    "wof:placetype":"venue"
},
  "geometry": {"coordinates":[-82.08602500000001,41.374951],"type":"Point"}
}