{
  "type": "Feature",
  "properties": {
    "addr:full": "425 W Kemper Rd Cincinnati OH 45246",
    "addr:housenumber": "425",
    "addr:postcode": "45246",
    "addr:street": "W Kemper Rd",
    "iso:country": "US",
    "sg:address": "425 W Kemper Rd",
    "sg:city": "Cincinnati",
    "sg:classifiers": [
      {
        "category": "Organizations",
        "subcategory": "Religious Organization",
        "type": "Services"
      }
    ],
    "sg:phone": "+1 513 825 2358",
    "sg:postcode": "45246",
    "sg:province": "OH",
    "sg:tags": [
      "church"
    ],
    "wof:name": "Soul-Winning Church Of God",
    "wof:placetype": "venue"
  },
  "geometry": {"coordinates":[-84.488315,39.287385],"type":"Point"}
}
