{
  "type": "Feature",
  "properties": {
    "iso:country":"US",
    "sg:address":"425 W Kemper Rd",
    "sg:city":"Cincinnati",
    "sg:classifiers":[
        {
            "category":"Organizations",
            "subcategory":"Religious Organization",
            "type":"Services"
        }
    ],
    "sg:phone":"+1 513 825 2358",
    "sg:postcode":"45246",
    "sg:province":"OH",
    "sg:tags":[
        "church"
    ],
    "wof:name":"Soul-Winning Church Of God",
    "wof:placetype":"venue"
},
  "geometry": {"coordinates":[-84.488315,39.287385],"type":"Point"}
}