{
  "type": "Feature",
  "properties": {
    "addr:full":"611 Yarmouth Dr Bay Village OH 44140",
    "addr:housenumber":"611",
    "addr:postcode":"44140",
    "addr:street":"Yarmouth Dr",
    "iso:country":"US",
    "sg:address":"611 Yarmouth Dr",
    "sg:city":"Bay Village",
    "sg:classifiers":[
        {
            "category":"Building & Trades",
            "subcategory":"Construction",
            "type":"Services"
        }
    ],
    "sg:phone":"+1 440 892 9228",
    "sg:postcode":"44140",
    "sg:province":"OH",
    "sg:tags":[
        "house",
        "contractor"
    ],
    "wof:name":"Kelly Needles Inc",
    "wof:placetype":"venue"
},
  "geometry": {"coordinates":[-81.953225,41.480123],"type":"Point"}
}