{
  "type": "Feature",
  "properties": {
    "addr:full": "200 Buehler St Galion OH 44833",
    "addr:housenumber": "200",
    "addr:postcode": "44833",
    "addr:street": "Buehler St",
    "iso:country": "US",
    "sg:address": "200 Buehler St",
    "sg:city": "Galion",
    "sg:classifiers": [
      {
        "category": "Personal",
        "subcategory": "Beauty Salon",
        "type": "Services"
      }
    ],
    "sg:phone": "+1 419 468 4340",
    "sg:postcode": "44833",
    "sg:province": "OH",
    "wof:name": "A'Beaute'",
    "wof:placetype": "venue"
  },
  "geometry": {"coordinates":[-82.783203,40.74328],"type":"Point"}
}
