{
  "type": "Feature",
  "properties": {
    "addr:full": "3330 Erie Ave Cincinnati OH 45208",
    "addr:housenumber": "3330",
    "addr:postcode": "45208",
    "addr:street": "Erie Ave",
    "iso:country": "US",
    "sg:address": "3330 Erie Ave",
    "sg:city": "Cincinnati",
    "sg:classifiers": [
      {
        "category": "Professional",
        "subcategory": "Business Services",
        "type": "Services"
      }
    ],
    "sg:phone": "+1 513 871 8181",
    "sg:postcode": "45208",
    "sg:province": "OH",
    "sg:tags": [
      "interior",
      "consultant",
      "design",
      "decorator"
    ],
    "wof:name": "Leed Design Assoc",
    "wof:placetype": "venue"
  },
  "geometry": {"coordinates":[-84.422296,39.141304],"type":"Point"}
}
