{
  "type": "Feature",
  "properties": {
    "iso:country":"US",
    "sg:address":"1584 Patriot Rd",
    "sg:city":"Patriot",
    "sg:classifiers":[
        {
            "category":"Government",
            "subcategory":"Post Office",
            "type":"Public Place"
        }
    ],
    "sg:phone":"+1 740 379 2803",
    "sg:postcode":"45658",
    "sg:province":"OH",
    "wof:name":"US Post Office",
    "wof:placetype":"venue"
},
  "geometry": {"coordinates":[-82.38382,38.774383],"type":"Point"}
}