{
  "type": "Feature",
  "properties": {
    "addr:full":"435 Longview Ave Canal Fulton OH 44614",
    "addr:housenumber":"435",
    "addr:postcode":"44614",
    "addr:street":"Longview Ave",
    "iso:country":"US",
    "sg:address":"435 Longview Ave",
    "sg:city":"Canal Fulton",
    "sg:classifiers":[
        {
            "category":"Food & Beverages",
            "subcategory":"Specialty",
            "type":"Retail Goods"
        }
    ],
    "sg:phone":"+1 330 854 4841",
    "sg:postcode":"44614",
    "sg:province":"OH",
    "sg:tags":[
        "health",
        "diet"
    ],
    "wof:name":"Pro Health Solutions",
    "wof:placetype":"venue"
},
  "geometry": {"coordinates":[-81.585773,40.88931],"type":"Point"}
}