{
  "type": "Feature",
  "properties": {
    "iso:country":"US",
    "sg:address":"880 State Rte 46 N",
    "sg:city":"Jefferson",
    "sg:classifiers":[
        {
            "category":"Professional",
            "subcategory":"Computer Services",
            "type":"Services"
        }
    ],
    "sg:phone":"+1 440 576 3977",
    "sg:postcode":"44047",
    "sg:province":"OH",
    "sg:tags":[
        "repair"
    ],
    "wof:name":"Thayer Web Design",
    "wof:placetype":"venue"
},
  "geometry": {"coordinates":[-80.769335,41.74836],"type":"Point"}
}