{
  "type": "Feature",
  "properties": {
    "addr:full": "9048 State Rte 7 Kinsman OH 44428",
    "addr:housenumber": "9048",
    "addr:postcode": "44428",
    "addr:street": "State Rte 7",
    "iso:country": "US",
    "sg:address": "9048 State Rte 7",
    "sg:city": "Kinsman",
    "sg:classifiers": [
      {
        "category": "Professional",
        "subcategory": "Business Services",
        "type": "Services"
      }
    ],
    "sg:phone": "+1 330 876 4400",
    "sg:postcode": "44428",
    "sg:province": "OH",
    "sg:tags": [
      "auctioneer"
    ],
    "wof:name": "D K Auctions",
    "wof:placetype": "venue"
  },
  "geometry": {"coordinates":[-80.570396,41.466935],"type":"Point"}
}
