{
  "type": "Feature",
  "properties": {
    "addr:full":"180 S.Fair Ave Hamilton OH 45011",
    "addr:housenumber":"180",
    "addr:postcode":"45011",
    "addr:street":"S.Fair Ave",
    "iso:country":"US",
    "sg:address":"180 S.Fair Ave",
    "sg:city":"Hamilton",
    "sg:classifiers":[
        {
            "category":"Professional",
            "subcategory":"Advertising",
            "type":"Services"
        }
    ],
    "sg:phone":"+1 513 309 6397",
    "sg:postcode":"45011",
    "sg:province":"OH",
    "sg:tags":[
        "directory",
        "guide"
    ],
    "sg:website":"http://www.lindaroarkministries.org",
    "wof:name":"world commissioned church",
    "wof:placetype":"venue"
},
  "geometry": {"coordinates":[-84.544887,39.3902],"type":"Point"}
}