{
  "type": "Feature",
  "properties": {
    "iso:country":"US",
    "sg:address":"1281 Copley Rd",
    "sg:city":"Akron",
    "sg:classifiers":[
        {
            "category":"Autos & Motor Vehicles",
            "subcategory":"Fuel & Gas Station",
            "type":"Retail Goods"
        }
    ],
    "sg:phone":"+1 330 864 0116",
    "sg:postcode":"44320",
    "sg:province":"OH",
    "sg:tags":[
        "oil"
    ],
    "sg:website":"www.hollandoil.com",
    "wof:name":"Holland Oil Co",
    "wof:placetype":"venue"
},
  "geometry": {"coordinates":[-81.56748399999999,41.083911],"type":"Point"}
}