{
  "type": "Feature",
  "properties": {
    "addr:full": "1281 Copley Rd Akron OH 44320",
    "addr:housenumber": "1281",
    "addr:postcode": "44320",
    "addr:street": "Copley Rd",
    "iso:country": "US",
    "sg:address": "1281 Copley Rd",
    "sg:city": "Akron",
    "sg:classifiers": [
      {
        "category": "Autos \u0026 Motor Vehicles",
        "subcategory": "Fuel \u0026 Gas Station",
        "type": "Retail Goods"
      }
    ],
    "sg:phone": "+1 330 864 0116",
    "sg:postcode": "44320",
    "sg:province": "OH",
    "sg:tags": [
      "oil"
    ],
    "sg:website": "www.hollandoil.com",
    "wof:name": "Holland Oil Co",
    "wof:placetype": "venue"
  },
  "geometry": {"coordinates":[-81.567484,41.083911],"type":"Point"}
}
