{
  "type": "Feature",
  "properties": {
    "addr:full": "11607 Euclid Ave Cleveland OH 44106",
    "addr:housenumber": "11607",
    "addr:postcode": "44106",
    "addr:street": "Euclid Ave",
    "iso:country": "US",
    "sg:address": "11607 Euclid Ave",
    "sg:city": "Cleveland",
    "sg:classifiers": [
      {
        "category": "Social Services",
        "type": "Services"
      }
    ],
    "sg:phone": "+1 216 229 3029",
    "sg:postcode": "44106",
    "sg:province": "OH",
    "sg:tags": [
      "organization",
      "welfare"
    ],
    "wof:name": "Linking Employment Abilities",
    "wof:placetype": "venue"
  },
  "geometry": {"coordinates":[-81.601662,41.511903],"type":"Point"}
}
