{
  "type": "Feature",
  "properties": {
    "addr:full": "520 W Sophia St Maumee OH 43537",
    "addr:housenumber": "520",
    "addr:postcode": "43537",
    "addr:street": "W Sophia St",
    "iso:country": "US",
    "sg:address": "520 W Sophia St",
    "sg:city": "Maumee",
    "sg:classifiers": [
      {
        "category": "Health Services",
        "subcategory": "Doctor",
        "type": "Services"
      }
    ],
    "sg:phone": "+1 419 893 1880",
    "sg:postcode": "43537",
    "sg:province": "OH",
    "sg:tags": [
      "physician",
      "surgeon",
      "medical"
    ],
    "wof:name": "Maumee Pediatric Assoc LLC",
    "wof:placetype": "venue"
  },
  "geometry": {"coordinates":[-83.663018,41.563287],"type":"Point"}
}
