{
  "type": "Feature",
  "properties": {
    "addr:full":"61127 Bolar Rd Mc Arthur OH 45651",
    "addr:housenumber":"61127",
    "addr:postcode":"45651",
    "addr:street":"Bolar Rd",
    "iso:country":"US",
    "sg:address":"61127 Bolar Rd",
    "sg:city":"Mc Arthur",
    "sg:classifiers":[
        {
            "category":"Home & Garden",
            "subcategory":"Building Materials",
            "type":"Retail Goods"
        }
    ],
    "sg:phone":"+1 740 596 2094",
    "sg:postcode":"45651",
    "sg:province":"OH",
    "sg:tags":[
        "glass",
        "window",
        "plate"
    ],
    "wof:name":"Mc Arthur Glass Co",
    "wof:placetype":"venue"
},
  "geometry": {"coordinates":[-82.548244,39.261977],"type":"Point"}
}