{
  "type": "Feature",
  "properties": {
    "iso:country":"US",
    "sg:address":"1409 Barcelona Dr",
    "sg:city":"Akron",
    "sg:classifiers":[
        {
            "category":"Shopping",
            "subcategory":"Clothing, Apparel, & Fashions",
            "type":"Retail Goods"
        }
    ],
    "sg:phone":"+1 330 836 0364",
    "sg:postcode":"44313",
    "sg:province":"OH",
    "wof:name":"Alteration Technician",
    "wof:placetype":"venue"
},
  "geometry": {"coordinates":[-81.556016,41.134345],"type":"Point"}
}