{
  "type": "Feature",
  "properties": {
    "iso:country":"US",
    "sg:address":"420 W Oakland Ave",
    "sg:city":"Washington Ct Hs",
    "sg:classifiers":[
        {
            "category":"Professional",
            "subcategory":"Art Services",
            "type":"Services"
        },
        {
            "category":"Manufacturing",
            "subcategory":"Printing",
            "type":"Manufacturing & Wholesale Goods"
        }
    ],
    "sg:phone":"+1 740 333 8337",
    "sg:postcode":"43160",
    "sg:province":"OH",
    "sg:tags":[
        "design",
        "screen",
        "mi"
    ],
    "wof:name":"Qualitee Design Sportswear Co",
    "wof:placetype":"venue"
},
  "geometry": {"coordinates":[-83.447704,39.537797],"type":"Point"}
}