{
  "type": "Feature",
  "properties": {
    "iso:country":"US",
    "sg:address":"3731 Sulphur Springs Rd",
    "sg:city":"Ottawa Hills",
    "sg:classifiers":[
        {
            "category":"Wholesale",
            "subcategory":"Durable Goods & Equipment",
            "type":"Manufacturing & Wholesale Goods"
        }
    ],
    "sg:phone":"+1 419 531 5913",
    "sg:postcode":"43606",
    "sg:province":"OH",
    "sg:tags":[
        "representative",
        "manufacturer"
    ],
    "wof:name":"Davis Sales Inc",
    "wof:placetype":"venue"
},
  "geometry": {"coordinates":[-83.634784,41.665222],"type":"Point"}
}