{
  "type": "Feature",
  "properties": {
    "iso:country":"US",
    "sg:address":"8877 Lincoln St SE",
    "sg:city":"Canton",
    "sg:classifiers":[
        {
            "category":"Building & Trades",
            "subcategory":"Construction",
            "type":"Services"
        }
    ],
    "sg:phone":"+1 330 488 2848",
    "sg:postcode":"44730",
    "sg:province":"OH",
    "sg:tags":[
        "general",
        "contractor"
    ],
    "wof:name":"Reichard Construction",
    "wof:placetype":"venue"
},
  "geometry": {"coordinates":[-81.238575,40.775136],"type":"Point"}
}