{
  "type": "Feature",
  "properties": {
    "addr:full": "8877 Lincoln St SE Canton OH 44730",
    "addr:housenumber": "8877",
    "addr:postcode": "44730",
    "addr:street": "Lincoln St Se",
    "iso:country": "US",
    "sg:address": "8877 Lincoln St SE",
    "sg:city": "Canton",
    "sg:classifiers": [
      {
        "category": "Building \u0026 Trades",
        "subcategory": "Construction",
        "type": "Services"
      }
    ],
    "sg:phone": "+1 330 488 2848",
    "sg:postcode": "44730",
    "sg:province": "OH",
    "sg:tags": [
      "general",
      "contractor"
    ],
    "wof:name": "Reichard Construction",
    "wof:placetype": "venue"
  },
  "geometry": {"coordinates":[-81.238575,40.775136],"type":"Point"}
}
