{
  "type": "Feature",
  "properties": {
    "addr:full": "3190 Woodford Rd Cincinnati OH 45213",
    "addr:housenumber": "3190",
    "addr:postcode": "45213",
    "addr:street": "Woodford Rd",
    "iso:country": "US",
    "sg:address": "3190 Woodford Rd",
    "sg:city": "Cincinnati",
    "sg:classifiers": [
      {
        "category": "Food \u0026 Beverages",
        "subcategory": "Groceries \u0026 Convenience Stores",
        "type": "Retail Goods"
      }
    ],
    "sg:phone": "+1 513 731 7917",
    "sg:postcode": "45213",
    "sg:province": "OH",
    "sg:website": "www.udfinc.com",
    "wof:name": "United Dairy Farmers",
    "wof:placetype": "venue"
  },
  "geometry": {"coordinates":[-84.4287,39.181673],"type":"Point"}
}
