{
  "type": "Feature",
  "properties": {
    "iso:country":"US",
    "sg:address":"3190 Woodford Rd",
    "sg:city":"Cincinnati",
    "sg:classifiers":[
        {
            "category":"Food & Beverages",
            "subcategory":"Groceries & Convenience Stores",
            "type":"Retail Goods"
        }
    ],
    "sg:phone":"+1 513 731 7917",
    "sg:postcode":"45213",
    "sg:province":"OH",
    "sg:website":"www.udfinc.com",
    "wof:name":"United Dairy Farmers",
    "wof:placetype":"venue"
},
  "geometry": {"coordinates":[-84.42870000000001,39.181673],"type":"Point"}
}