{
  "type": "Feature",
  "properties": {
    "iso:country":"US",
    "sg:address":"20903 Twp Rd 68",
    "sg:city":"Arlington",
    "sg:classifiers":[
        {
            "category":"Real Estate",
            "subcategory":"Real Estate Operator",
            "type":"Services"
        }
    ],
    "sg:phone":"+1 419 365 5618",
    "sg:postcode":"45814",
    "sg:province":"OH",
    "sg:tags":[
        "property",
        "lessor"
    ],
    "wof:name":"Harley Wilch",
    "wof:placetype":"venue"
},
  "geometry": {"coordinates":[-83.670031,40.862513],"type":"Point"}
}