{
  "type": "Feature",
  "properties": {
    "addr:full":"5410 N Co Rd 25A Piqua OH 45356",
    "addr:housenumber":"5410;25a",
    "addr:postcode":"45356",
    "addr:street":"N Co Rd",
    "iso:country":"US",
    "sg:address":"5410 N Co Rd 25A",
    "sg:city":"Piqua",
    "sg:classifiers":[
        {
            "category":"Shopping",
            "type":"Retail Goods"
        }
    ],
    "sg:phone":"+1 937 773 0215",
    "sg:postcode":"45356",
    "sg:province":"OH",
    "sg:tags":[
        "feed",
        "farm",
        "seed",
        "supply"
    ],
    "wof:name":"Western Ohio Fence & Supply",
    "wof:placetype":"venue"
},
  "geometry": {"coordinates":[-84.23698400000001,40.119664],"type":"Point"}
}