{
  "type": "Feature",
  "properties": {
    "iso:country":"US",
    "sg:address":"796 Wainwright Dr",
    "sg:city":"Columbus",
    "sg:classifiers":[
        {
            "category":"Freight",
            "type":"Transportation"
        }
    ],
    "sg:phone":"+1 614 784 0934",
    "sg:postcode":"43224",
    "sg:province":"OH",
    "sg:tags":[
        "operator",
        "trucking"
    ],
    "wof:name":"Dld Trucking",
    "wof:placetype":"venue"
},
  "geometry": {"coordinates":[-82.99337199999999,40.026996],"type":"Point"}
}