{
  "type": "Feature",
  "properties": {
    "iso:country":"US",
    "sg:address":"3378 State Rte 5",
    "sg:city":"Cortland",
    "sg:classifiers":[
        {
            "category":"Real Estate",
            "subcategory":"Real Estate Agent",
            "type":"Services"
        }
    ],
    "sg:phone":"+1 330 638 3333",
    "sg:postcode":"44410",
    "sg:province":"OH",
    "wof:name":"Better Homes & Gardens",
    "wof:placetype":"venue"
},
  "geometry": {"coordinates":[-80.734438,41.314435],"type":"Point"}
}