{
  "type": "Feature",
  "properties": {
    "addr:full": "3378 State Rte 5 Cortland OH 44410",
    "addr:housenumber": "3378",
    "addr:postcode": "44410",
    "addr:street": "State Rte 5",
    "iso:country": "US",
    "sg:address": "3378 State Rte 5",
    "sg:city": "Cortland",
    "sg:classifiers": [
      {
        "category": "Real Estate",
        "subcategory": "Real Estate Agent",
        "type": "Services"
      }
    ],
    "sg:phone": "+1 330 638 3333",
    "sg:postcode": "44410",
    "sg:province": "OH",
    "wof:name": "Better Homes \u0026 Gardens",
    "wof:placetype": "venue"
  },
  "geometry": {"coordinates":[-80.734438,41.314435],"type":"Point"}
}
