{
  "type": "Feature",
  "properties": {
    "iso:country":"US",
    "sg:address":"1528 Westwood Ave",
    "sg:city":"Cleveland",
    "sg:classifiers":[
        {
            "category":"Professional",
            "type":"Services"
        }
    ],
    "sg:phone":"+1 216 226 4704",
    "sg:postcode":"44107",
    "sg:province":"OH",
    "sg:tags":[
        "establishment"
    ],
    "wof:name":"Baha'Ls Of Lakewood",
    "wof:placetype":"venue"
},
  "geometry": {"coordinates":[-81.807309,41.481438],"type":"Point"}
}