{
  "type": "Feature",
  "properties": {
    "iso:country":"US",
    "sg:address":"896 State Rte 613",
    "sg:city":"Mc Comb",
    "sg:classifiers":[
        {
            "category":"Building & Trades",
            "subcategory":"Construction",
            "type":"Services"
        }
    ],
    "sg:phone":"+1 419 293 2316",
    "sg:postcode":"45858",
    "sg:province":"OH",
    "sg:tags":[
        "erectors",
        "machinery"
    ],
    "wof:name":"Grubb Construction Inc",
    "wof:placetype":"venue"
},
  "geometry": {"coordinates":[-83.87223400000001,41.085471],"type":"Point"}
}