{
  "type": "Feature",
  "properties": {
    "addr:full": "896 State Rte 613 Mc Comb OH 45858",
    "addr:housenumber": "896",
    "addr:postcode": "45858",
    "addr:street": "State Rte 613",
    "iso:country": "US",
    "sg:address": "896 State Rte 613",
    "sg:city": "Mc Comb",
    "sg:classifiers": [
      {
        "category": "Building \u0026 Trades",
        "subcategory": "Construction",
        "type": "Services"
      }
    ],
    "sg:phone": "+1 419 293 2316",
    "sg:postcode": "45858",
    "sg:province": "OH",
    "sg:tags": [
      "erectors",
      "machinery"
    ],
    "wof:name": "Grubb Construction Inc",
    "wof:placetype": "venue"
  },
  "geometry": {"coordinates":[-83.872234,41.085471],"type":"Point"}
}
