{
  "type": "Feature",
  "properties": {
    "addr:full": "34 S Main St Chagrin Falls OH 44022",
    "addr:housenumber": "34",
    "addr:postcode": "44022",
    "addr:street": "S Main St",
    "iso:country": "US",
    "sg:address": "34 S Main St",
    "sg:city": "Chagrin Falls",
    "sg:classifiers": [
      {
        "category": "Manufacturing",
        "subcategory": "Metals",
        "type": "Manufacturing \u0026 Wholesale Goods"
      }
    ],
    "sg:phone": "+1 440 247 5292",
    "sg:postcode": "44022",
    "sg:province": "OH",
    "sg:tags": [
      "industrial",
      "container"
    ],
    "sg:website": "www.bwaycorp.com",
    "wof:name": "BWAY Corp",
    "wof:placetype": "venue"
  },
  "geometry": {"coordinates":[-81.390733,41.429292],"type":"Point"}
}
