{
  "type": "Feature",
  "properties": {
    "addr:full":"20837 State Rte 180 Laurelville OH 43135",
    "addr:housenumber":"20837",
    "addr:postcode":"43135",
    "addr:street":"State Rte 180",
    "iso:country":"US",
    "sg:address":"20837 State Rte 180",
    "sg:city":"Laurelville",
    "sg:classifiers":[
        {
            "category":"Building & Trades",
            "subcategory":"Construction",
            "type":"Services"
        }
    ],
    "sg:phone":"+1 740 332 6428",
    "sg:postcode":"43135",
    "sg:province":"OH",
    "sg:tags":[
        "resurfacing",
        "laying",
        "refinishing",
        "floor"
    ],
    "wof:name":"Michael J Messmer Flooring LTD",
    "wof:placetype":"venue"
},
  "geometry": {"coordinates":[-82.64617699999999,39.4977],"type":"Point"}
}