{
  "type": "Feature",
  "properties": {
    "iso:country":"US",
    "sg:address":"261 S Broadway St",
    "sg:city":"Lynchburg",
    "sg:classifiers":[
        {
            "category":"Shopping",
            "subcategory":"Bicycles & Sporting Goods",
            "type":"Retail Goods"
        }
    ],
    "sg:phone":"+1 937 364 8611",
    "sg:postcode":"45142",
    "sg:province":"OH",
    "wof:name":"Broken Arrow Archery",
    "wof:placetype":"venue"
},
  "geometry": {"coordinates":[-83.791112,39.241907],"type":"Point"}
}