{
  "type": "Feature",
  "properties": {
    "iso:country":"US",
    "sg:address":"155 McDonald Dr NW",
    "sg:city":"New Philadelphia",
    "sg:classifiers":[
        {
            "category":"Health Services",
            "subcategory":"Doctor",
            "type":"Services"
        }
    ],
    "sg:phone":"+1 330 308 8999",
    "sg:postcode":"44663",
    "sg:province":"OH",
    "sg:tags":[
        "physician",
        "surgeon"
    ],
    "wof:name":"Lakeland Family Medicine Inc",
    "wof:placetype":"venue"
},
  "geometry": {"coordinates":[-81.46730100000001,40.492085],"type":"Point"}
}