{
  "type": "Feature",
  "properties": {
    "addr:full": "155 McDonald Dr NW New Philadelphia OH 44663",
    "addr:housenumber": "155",
    "addr:postcode": "44663",
    "addr:street": "Mcdonald Dr Nw New Philadelphia",
    "iso:country": "US",
    "sg:address": "155 McDonald Dr NW",
    "sg:city": "New Philadelphia",
    "sg:classifiers": [
      {
        "category": "Health Services",
        "subcategory": "Doctor",
        "type": "Services"
      }
    ],
    "sg:phone": "+1 330 308 8999",
    "sg:postcode": "44663",
    "sg:province": "OH",
    "sg:tags": [
      "physician",
      "surgeon"
    ],
    "wof:name": "Lakeland Family Medicine Inc",
    "wof:placetype": "venue"
  },
  "geometry": {"coordinates":[-81.467301,40.492085],"type":"Point"}
}
