{
  "type": "Feature",
  "properties": {
    "addr:full":"23 Overlook St Englewood OH 45322",
    "addr:housenumber":"23",
    "addr:postcode":"45322",
    "addr:street":"Overlook St",
    "iso:country":"US",
    "sg:address":"23 Overlook St",
    "sg:city":"Englewood",
    "sg:classifiers":[
        {
            "category":"Building & Trades",
            "subcategory":"Plumbing",
            "type":"Services"
        }
    ],
    "sg:phone":"+1 937 832 2828",
    "sg:postcode":"45322",
    "sg:province":"OH",
    "sg:tags":[
        "plumbing",
        "contractor"
    ],
    "wof:name":"Free Flow",
    "wof:placetype":"venue"
},
  "geometry": {"coordinates":[-84.301286,39.875979],"type":"Point"}
}