{
  "type": "Feature",
  "properties": {
    "iso:country":"US",
    "sg:address":"140 N 3rd St",
    "sg:city":"Columbus",
    "sg:classifiers":[
        {
            "category":"Retail",
            "subcategory":"Auto Rental",
            "type":"Services"
        }
    ],
    "sg:phone":"+1 614 224 6113",
    "sg:postcode":"43215",
    "sg:province":"OH",
    "sg:tags":[
        "renting",
        "automobile"
    ],
    "wof:name":"Budget Rent A Car",
    "wof:placetype":"venue"
},
  "geometry": {"coordinates":[-82.998515,39.965635],"type":"Point"}
}