{
  "type": "Feature",
  "properties": {
    "addr:full":"4405 Toulouse Ct Dayton OH 45429",
    "addr:housenumber":"4405",
    "addr:postcode":"45429",
    "addr:street":"Toulouse Ct",
    "iso:country":"US",
    "sg:address":"4405 Toulouse Ct",
    "sg:city":"Dayton",
    "sg:classifiers":[
        {
            "category":"Wholesale",
            "subcategory":"Furniture",
            "type":"Manufacturing & Wholesale Goods"
        },
        {
            "category":"Wholesale",
            "subcategory":"Durable Goods & Equipment",
            "type":"Manufacturing & Wholesale Goods"
        }
    ],
    "sg:phone":"+1 937 299 9994",
    "sg:postcode":"45429",
    "sg:province":"OH",
    "sg:tags":[
        "representative",
        "manufacturer"
    ],
    "wof:name":"Sid Scher & Associates",
    "wof:placetype":"venue"
},
  "geometry": {"coordinates":[-84.17104399999999,39.682819],"type":"Point"}
}