{
  "type": "Feature",
  "properties": {
    "addr:full": "4405 Toulouse Ct Dayton OH 45429",
    "addr:housenumber": "4405",
    "addr:postcode": "45429",
    "addr:street": "Toulouse Ct",
    "iso:country": "US",
    "sg:address": "4405 Toulouse Ct",
    "sg:city": "Dayton",
    "sg:classifiers": [
      {
        "category": "Wholesale",
        "subcategory": "Furniture",
        "type": "Manufacturing \u0026 Wholesale Goods"
      },
      {
        "category": "Wholesale",
        "subcategory": "Durable Goods \u0026 Equipment",
        "type": "Manufacturing \u0026 Wholesale Goods"
      }
    ],
    "sg:phone": "+1 937 299 9994",
    "sg:postcode": "45429",
    "sg:province": "OH",
    "sg:tags": [
      "representative",
      "manufacturer"
    ],
    "wof:name": "Sid Scher \u0026 Associates",
    "wof:placetype": "venue"
  },
  "geometry": {"coordinates":[-84.171044,39.682819],"type":"Point"}
}
