{
  "type": "Feature",
  "properties": {
    "addr:full": "2748 US Hwy 42 Delaware OH 43015",
    "addr:housenumber": "2748",
    "addr:postcode": "43015",
    "addr:street": "Us Hwy 42",
    "iso:country": "US",
    "sg:address": "2748 US Hwy 42",
    "sg:city": "Delaware",
    "sg:classifiers": [
      {
        "category": "Farming",
        "subcategory": "Livestock Farm",
        "type": "Manufacturing \u0026 Wholesale Goods"
      }
    ],
    "sg:phone": "+1 740 369 2727",
    "sg:postcode": "43015",
    "sg:province": "OH",
    "wof:name": "David Shellhouse",
    "wof:placetype": "venue"
  },
  "geometry": {"coordinates":[-83.111523,40.269004],"type":"Point"}
}
