{
  "type": "Feature",
  "properties": {
    "iso:country":"US",
    "sg:address":"3646 Main St",
    "sg:city":"Hilliard",
    "sg:classifiers":[
        {
            "category":"Banks & Credit Unions",
            "subcategory":"Bank",
            "type":"Services"
        }
    ],
    "sg:phone":"+1 614 777 4778",
    "sg:postcode":"43026",
    "sg:province":"OH",
    "sg:tags":[
        "cashing",
        "check"
    ],
    "wof:name":"Check Exchange",
    "wof:placetype":"venue"
},
  "geometry": {"coordinates":[-83.16114399999999,40.028917],"type":"Point"}
}