{
  "type": "Feature",
  "properties": {
    "addr:full": "3646 Main St Hilliard OH 43026",
    "addr:housenumber": "3646",
    "addr:postcode": "43026",
    "addr:street": "Main St",
    "iso:country": "US",
    "sg:address": "3646 Main St",
    "sg:city": "Hilliard",
    "sg:classifiers": [
      {
        "category": "Banks \u0026 Credit Unions",
        "subcategory": "Bank",
        "type": "Services"
      }
    ],
    "sg:phone": "+1 614 777 4778",
    "sg:postcode": "43026",
    "sg:province": "OH",
    "sg:tags": [
      "cashing",
      "check"
    ],
    "wof:name": "Check Exchange",
    "wof:placetype": "venue"
  },
  "geometry": {"coordinates":[-83.161144,40.028917],"type":"Point"}
}
