{
  "type": "Feature",
  "properties": {
    "addr:full":"315 Tuscarawas St W Canton OH 44702",
    "addr:housenumber":"315",
    "addr:postcode":"44702",
    "addr:street":"Tuscarawas St W",
    "iso:country":"US",
    "sg:address":"315 Tuscarawas St W",
    "sg:city":"Canton",
    "sg:classifiers":[
        {
            "category":"Professional",
            "subcategory":"Lawyer & Legal Services",
            "type":"Services"
        }
    ],
    "sg:phone":"+1 330 453 4123",
    "sg:postcode":"44702",
    "sg:province":"OH",
    "sg:tags":[
        "attorney"
    ],
    "wof:name":"Craig E Chessler",
    "wof:placetype":"venue"
},
  "geometry": {"coordinates":[-81.37731700000001,40.799036],"type":"Point"}
}