{
  "type": "Feature",
  "properties": {
    "addr:full":"3603 Westerville Rd Columbus OH 43224",
    "addr:housenumber":"3603",
    "addr:postcode":"43224",
    "addr:street":"Westerville Rd",
    "iso:country":"US",
    "sg:address":"3603 Westerville Rd",
    "sg:city":"Columbus",
    "sg:classifiers":[
        {
            "category":"Building & Trades",
            "subcategory":"Landscaping Services",
            "type":"Services"
        }
    ],
    "sg:phone":"+1 614 471 4144",
    "sg:postcode":"43224",
    "sg:province":"OH",
    "sg:tags":[
        "landscape",
        "contractor"
    ],
    "sg:website":"www.davey.com",
    "wof:name":"Davey Commercial Grounds Mgmt",
    "wof:placetype":"venue"
},
  "geometry": {"coordinates":[-82.948697,40.043194],"type":"Point"}
}