{
  "type": "Feature",
  "properties": {
    "addr:full": "1515 S Byrne Rd Toledo OH 43614",
    "addr:housenumber": "1515",
    "addr:postcode": "43614",
    "addr:street": "S Byrne Rd",
    "iso:country": "US",
    "sg:address": "1515 S Byrne Rd",
    "sg:city": "Toledo",
    "sg:classifiers": [
      {
        "category": "Shopping",
        "subcategory": "Pharmacy",
        "type": "Retail Goods"
      }
    ],
    "sg:phone": "+1 419 382 3475",
    "sg:postcode": "43614",
    "sg:province": "OH",
    "wof:name": "Pharmacy Counter The",
    "wof:placetype": "venue"
  },
  "geometry": {"coordinates":[-83.625682,41.60906],"type":"Point"}
}
