{
  "type": "Feature",
  "properties": {
    "addr:full": "4009 Far Hills Ave Dayton OH 45429",
    "addr:housenumber": "4009",
    "addr:postcode": "45429",
    "addr:street": "Far Hills Ave",
    "iso:country": "US",
    "sg:address": "4009 Far Hills Ave",
    "sg:city": "Dayton",
    "sg:classifiers": [
      {
        "category": "Personal",
        "subcategory": "Barber",
        "type": "Services"
      }
    ],
    "sg:phone": "+1 937 299 3830",
    "sg:postcode": "45429",
    "sg:province": "OH",
    "wof:name": "Castle Hill Barbers",
    "wof:placetype": "venue"
  },
  "geometry": {"coordinates":[-84.168702,39.688761],"type":"Point"}
}
