{
  "type": "Feature",
  "properties": {
    "iso:country":"US",
    "sg:address":"761 Beta Dr",
    "sg:city":"Cleveland",
    "sg:classifiers":[
        {
            "category":"Autos & Motor Vehicles",
            "subcategory":"Auto Supplies",
            "type":"Retail Goods"
        }
    ],
    "sg:phone":"+1 440 473 0331",
    "sg:postcode":"44143",
    "sg:province":"OH",
    "sg:tags":[
        "automobile",
        "parts"
    ],
    "wof:name":"Great Lakes Imported Auto Inc",
    "wof:placetype":"venue"
},
  "geometry": {"coordinates":[-81.445021,41.542756],"type":"Point"}
}