{
  "type": "Feature",
  "properties": {
    "addr:full":"206 E Garfield Rd Aurora OH 44202",
    "addr:housenumber":"206",
    "addr:postcode":"44202",
    "addr:street":"E Garfield Rd",
    "iso:country":"US",
    "sg:address":"206 E Garfield Rd",
    "sg:city":"Aurora",
    "sg:classifiers":[
        {
            "category":"Real Estate",
            "subcategory":"Developer",
            "type":"Services"
        }
    ],
    "sg:phone":"+1 330 562 5294",
    "sg:postcode":"44202",
    "sg:province":"OH",
    "sg:tags":[
        "residential",
        "land"
    ],
    "wof:name":"Duneden Group Inc",
    "wof:placetype":"venue"
},
  "geometry": {"coordinates":[-81.33580600000001,41.317304],"type":"Point"}
}