{
  "type": "Feature",
  "properties": {
    "addr:full":"12920 Lorain Ave Cleveland OH 44111",
    "addr:housenumber":"12920",
    "addr:postcode":"44111",
    "addr:street":"Lorain Ave",
    "iso:country":"US",
    "sg:address":"12920 Lorain Ave",
    "sg:city":"Cleveland",
    "sg:classifiers":[
        {
            "category":"Shopping",
            "subcategory":"Jewelry",
            "type":"Retail Goods"
        }
    ],
    "sg:phone":"+1 216 252 7722",
    "sg:postcode":"44111",
    "sg:province":"OH",
    "wof:name":"Hashem Sadi Abu",
    "wof:placetype":"venue"
},
  "geometry": {"coordinates":[-81.778451,41.458899],"type":"Point"}
}