{
  "type": "Feature",
  "properties": {
    "iso:country":"US",
    "sg:address":"2947 Interstate Pkwy",
    "sg:city":"Brunswick",
    "sg:classifiers":[
        {
            "category":"Wholesale",
            "subcategory":"Machinery & Supplies",
            "type":"Manufacturing & Wholesale Goods"
        }
    ],
    "sg:phone":"+1 330 220 6585",
    "sg:postcode":"44212",
    "sg:province":"OH",
    "sg:tags":[
        "equipment",
        "trenching"
    ],
    "wof:name":"Ditch Witch of Central Ohio",
    "wof:placetype":"venue"
},
  "geometry": {"coordinates":[-81.79269,41.247186],"type":"Point"}
}