{
  "type": "Feature",
  "properties": {
    "addr:full":"5780 Brice Outlet Mall Columbus OH 43232",
    "addr:housenumber":"5780",
    "addr:postcode":"43232",
    "addr:street":"Brice Outlet Mall",
    "iso:country":"US",
    "sg:address":"5780 Brice Outlet Mall",
    "sg:city":"Columbus",
    "sg:classifiers":[
        {
            "category":"Home & Garden",
            "subcategory":"Furniture",
            "type":"Retail Goods"
        }
    ],
    "sg:phone":"+1 614 575 8550",
    "sg:postcode":"43232",
    "sg:province":"OH",
    "sg:tags":[
        "mattress"
    ],
    "wof:name":"Mattress Mart King KOIL",
    "wof:placetype":"venue"
},
  "geometry": {"coordinates":[-82.83521,39.928903],"type":"Point"}
}