{
  "type": "Feature",
  "properties": {
    "addr:full":"10 Burke Ct Springboro OH 45066",
    "addr:housenumber":"10",
    "addr:postcode":"45066",
    "addr:street":"Burke Ct",
    "iso:country":"US",
    "sg:address":"10 Burke Ct",
    "sg:city":"Springboro",
    "sg:classifiers":[
        {
            "category":"Professional",
            "type":"Services"
        }
    ],
    "sg:phone":"+1 937 885 0733",
    "sg:postcode":"45066",
    "sg:province":"OH",
    "wof:name":"Pushbutton Interactive LLC",
    "wof:placetype":"venue"
},
  "geometry": {"coordinates":[-84.215416,39.585007],"type":"Point"}
}