{
  "type": "Feature",
  "properties": {
    "addr:full": "24 W William St Delaware OH 43015",
    "addr:housenumber": "24",
    "addr:postcode": "43015",
    "addr:street": "W William St",
    "iso:country": "US",
    "sg:address": "24 W William St",
    "sg:city": "Delaware",
    "sg:classifiers": [
      {
        "category": "Professional",
        "subcategory": "Accounting \u0026 Tax Preparation",
        "type": "Services"
      }
    ],
    "sg:phone": "+1 740 369 9161",
    "sg:postcode": "43015",
    "sg:province": "OH",
    "sg:tags": [
      "return",
      "filing"
    ],
    "wof:name": "Senior Services Tax Advisory",
    "wof:placetype": "venue"
  },
  "geometry": {"coordinates":[-83.068709,40.298922],"type":"Point"}
}
