{
  "type": "Feature",
  "properties": {
    "iso:country":"US",
    "sg:address":"302 E Main St",
    "sg:city":"Junction City",
    "sg:classifiers":[
        {
            "category":"Government",
            "subcategory":"Office",
            "type":"Public Place"
        }
    ],
    "sg:phone":"+1 740 987 4747",
    "sg:postcode":"43748",
    "sg:province":"OH",
    "sg:tags":[
        "govt",
        "city"
    ],
    "wof:name":"Junction City Water Works",
    "wof:placetype":"venue"
},
  "geometry": {"coordinates":[-82.296521,39.721215],"type":"Point"}
}