{
  "type": "Feature",
  "properties": {
    "addr:full": "3348 US Rte 62 Millersburg OH 44654",
    "addr:housenumber": "3348",
    "addr:postcode": "44654",
    "addr:street": "Us Rte 62",
    "iso:country": "US",
    "sg:address": "3348 US Rte 62",
    "sg:city": "Millersburg",
    "sg:classifiers": [
      {
        "category": "Professional",
        "subcategory": "Business Services",
        "type": "Services"
      }
    ],
    "sg:phone": "+1 330 893 3858",
    "sg:postcode": "44654",
    "sg:province": "OH",
    "wof:name": "Coblentz Collar Shop",
    "wof:placetype": "venue"
  },
  "geometry": {"coordinates":[-81.742217,40.601868],"type":"Point"}
}
