{
  "type": "Feature",
  "properties": {
    "iso:country":"US",
    "sg:address":"3348 US Rte 62",
    "sg:city":"Millersburg",
    "sg:classifiers":[
        {
            "category":"Professional",
            "subcategory":"Business Services",
            "type":"Services"
        }
    ],
    "sg:phone":"+1 330 893 3858",
    "sg:postcode":"44654",
    "sg:province":"OH",
    "wof:name":"Coblentz Collar Shop",
    "wof:placetype":"venue"
},
  "geometry": {"coordinates":[-81.742217,40.601868],"type":"Point"}
}