{
  "type": "Feature",
  "properties": {
    "addr:full": "180 Parkview Dr Millersburg OH 44654",
    "addr:housenumber": "180",
    "addr:postcode": "44654",
    "addr:street": "Parkview Dr",
    "iso:country": "US",
    "sg:address": "180 Parkview Dr",
    "sg:city": "Millersburg",
    "sg:classifiers": [
      {
        "category": "Personal",
        "subcategory": "Beauty Salon",
        "type": "Services"
      }
    ],
    "sg:phone": "+1 330 674 2476",
    "sg:postcode": "44654",
    "sg:province": "OH",
    "wof:name": "S \u0026 S Mane Attraction",
    "wof:placetype": "venue"
  },
  "geometry": {"coordinates":[-81.91047,40.543743],"type":"Point"}
}
