{
  "type": "Feature",
  "properties": {
    "iso:country":"US",
    "sg:address":"502 S State St",
    "sg:city":"Westerville",
    "sg:classifiers":[
        {
            "category":"Retail",
            "subcategory":"Auto Repair",
            "type":"Services"
        }
    ],
    "sg:phone":"+1 614 891 7771",
    "sg:postcode":"43081",
    "sg:province":"OH",
    "sg:tags":[
        "automotive",
        "maintenance"
    ],
    "sg:website":"www.vioc.com",
    "wof:name":"Valvoline Instant Oil Change",
    "wof:placetype":"venue"
},
  "geometry": {"coordinates":[-82.92668500000001,40.112867],"type":"Point"}
}