{
  "type": "Feature",
  "properties": {
    "addr:full":"614 Wooster Pike Terrace Park OH 45174",
    "addr:housenumber":"614",
    "addr:postcode":"45174",
    "addr:street":"Wooster Pike",
    "iso:country":"US",
    "sg:address":"614 Wooster Pike",
    "sg:city":"Terrace Park",
    "sg:classifiers":[
        {
            "category":"Building & Trades",
            "subcategory":"Construction",
            "type":"Services"
        }
    ],
    "sg:phone":"+1 513 831 1111",
    "sg:postcode":"45174",
    "sg:province":"OH",
    "sg:tags":[
        "renovated",
        "family",
        "house",
        "general",
        "new",
        "contractor"
    ],
    "sg:website":"www.drackett-harth.com",
    "wof:name":"Drackett-Harth Construction",
    "wof:placetype":"venue"
},
  "geometry": {"coordinates":[-84.30882,39.165868],"type":"Point"}
}