{
  "type": "Feature",
  "properties": {
    "addr:full": "116 W Main St Coldwater OH 45828",
    "addr:housenumber": "116",
    "addr:postcode": "45828",
    "addr:street": "W Main St",
    "iso:country": "US",
    "sg:address": "116 W Main St",
    "sg:city": "Coldwater",
    "sg:classifiers": [
      {
        "category": "Manufacturing",
        "subcategory": "Printing",
        "type": "Manufacturing \u0026 Wholesale Goods"
      }
    ],
    "sg:phone": "+1 419 678 2324",
    "sg:postcode": "45828",
    "sg:province": "OH",
    "sg:tags": [
      "news",
      "publication"
    ],
    "wof:name": "Mercer County Chronicle",
    "wof:placetype": "venue"
  },
  "geometry": {"coordinates":[-84.628869,40.479841],"type":"Point"}
}
