{
  "type": "Feature",
  "properties": {
    "addr:full": "2319 W 11th St Cleveland OH 44113",
    "addr:housenumber": "2319",
    "addr:postcode": "44113",
    "addr:street": "W 11Th St",
    "iso:country": "US",
    "sg:address": "2319 W 11th St",
    "sg:city": "Cleveland",
    "sg:classifiers": [
      {
        "category": "Restaurant",
        "type": "Food \u0026 Drink"
      }
    ],
    "sg:phone": "+1 216 861 9914",
    "sg:postcode": "44113",
    "sg:province": "OH",
    "sg:tags": [
      "caterer",
      "catering"
    ],
    "wof:name": "Elan Catering Inc",
    "wof:placetype": "venue"
  },
  "geometry": {"coordinates":[-81.689252,41.481552],"type":"Point"}
}
