{
  "type": "Feature",
  "properties": {
    "iso:country":"US",
    "sg:address":"1007 E Lincoln Way",
    "sg:city":"Minerva",
    "sg:classifiers":[
        {
            "category":"Autos & Motor Vehicles",
            "subcategory":"Automobile Sales",
            "type":"Retail Goods"
        }
    ],
    "sg:phone":"+1 330 868 2277",
    "sg:postcode":"44657",
    "sg:province":"OH",
    "sg:tags":[
        "used"
    ],
    "wof:name":"Loudon Motors Inc",
    "wof:placetype":"venue"
},
  "geometry": {"coordinates":[-81.08804,40.738349],"type":"Point"}
}