{
  "type": "Feature",
  "properties": {
    "addr:full": "11260 Cornell Park Dr Cincinnati OH 45242",
    "addr:housenumber": "11260",
    "addr:postcode": "45242",
    "addr:street": "Cornell Park Dr",
    "iso:country": "US",
    "sg:address": "11260 Cornell Park Dr",
    "sg:city": "Cincinnati",
    "sg:classifiers": [
      {
        "category": "Wholesale",
        "subcategory": "Machinery \u0026 Supplies",
        "type": "Manufacturing \u0026 Wholesale Goods"
      }
    ],
    "sg:phone": "+1 513 469 1822",
    "sg:postcode": "45242",
    "sg:province": "OH",
    "wof:name": "Gordon Machine",
    "wof:placetype": "venue"
  },
  "geometry": {"coordinates":[-84.372968,39.27347],"type":"Point"}
}
