{
  "type": "Feature",
  "properties": {
    "iso:country":"US",
    "sg:address":"1575 Anderson Ferry Rd",
    "sg:city":"Cincinnati",
    "sg:classifiers":[
        {
            "category":"Retail",
            "subcategory":"Repair Shop",
            "type":"Services"
        }
    ],
    "sg:phone":"+1 513 922 4600",
    "sg:postcode":"45238",
    "sg:province":"OH",
    "sg:tags":[
        "television",
        "radio"
    ],
    "wof:name":"Western Hills TV",
    "wof:placetype":"venue"
},
  "geometry": {"coordinates":[-84.616466,39.120358],"type":"Point"}
}