{
  "type": "Feature",
  "properties": {
    "addr:full": "616 Rector Ave Findlay OH 45840",
    "addr:housenumber": "616",
    "addr:postcode": "45840",
    "addr:street": "Rector Ave",
    "iso:country": "US",
    "sg:address": "616 Rector Ave",
    "sg:city": "Findlay",
    "sg:classifiers": [
      {
        "category": "Organizations",
        "subcategory": "Religious Organization",
        "type": "Services"
      }
    ],
    "sg:phone": "+1 419 422 9398",
    "sg:postcode": "45840",
    "sg:province": "OH",
    "sg:tags": [
      "church"
    ],
    "wof:name": "First United Brethren Church",
    "wof:placetype": "venue"
  },
  "geometry": {"coordinates":[-83.66093,41.062443],"type":"Point"}
}
