{
  "type": "Feature",
  "properties": {
    "iso:country":"US",
    "sg:address":"616 Rector Ave",
    "sg:city":"Findlay",
    "sg:classifiers":[
        {
            "category":"Organizations",
            "subcategory":"Religious Organization",
            "type":"Services"
        }
    ],
    "sg:phone":"+1 419 422 9398",
    "sg:postcode":"45840",
    "sg:province":"OH",
    "sg:tags":[
        "church"
    ],
    "wof:name":"First United Brethren Church",
    "wof:placetype":"venue"
},
  "geometry": {"coordinates":[-83.66093,41.062443],"type":"Point"}
}