{
  "type": "Feature",
  "properties": {
    "iso:country":"US",
    "sg:address":"6200 Montgomery Rd",
    "sg:city":"Cincinnati",
    "sg:classifiers":[
        {
            "category":"Sports & Exercise",
            "subcategory":"Gym",
            "type":"Entertainment"
        }
    ],
    "sg:phone":"+1 513 351 0600",
    "sg:postcode":"45213",
    "sg:province":"OH",
    "sg:tags":[
        "club",
        "health"
    ],
    "wof:name":"Das Gym",
    "wof:placetype":"venue"
},
  "geometry": {"coordinates":[-84.42313300000001,39.184377],"type":"Point"}
}