{
  "type": "Feature",
  "properties": {
    "addr:full":"16 Greene St Fairborn OH 45324",
    "addr:housenumber":"16",
    "addr:postcode":"45324",
    "addr:street":"Greene St",
    "iso:country":"US",
    "sg:address":"16 Greene St",
    "sg:city":"Fairborn",
    "sg:classifiers":[
        {
            "category":"Manufacturing",
            "subcategory":"Tools & Machinery",
            "type":"Manufacturing & Wholesale Goods"
        }
    ],
    "sg:phone":"+1 937 878 1322",
    "sg:postcode":"45324",
    "sg:province":"OH",
    "sg:tags":[
        "measuring",
        "instrument",
        "electrical",
        "mfg"
    ],
    "wof:name":"Ganymede Corp",
    "wof:placetype":"venue"
},
  "geometry": {"coordinates":[-84.02401399999999,39.818441],"type":"Point"}
}