{
  "type": "Feature",
  "properties": {
    "addr:full":"1000 Scioto St Urbana OH 43078",
    "addr:housenumber":"1000",
    "addr:postcode":"43078",
    "addr:street":"Scioto St",
    "iso:country":"US",
    "sg:address":"1000 Scioto St",
    "sg:city":"Urbana",
    "sg:classifiers":[
        {
            "category":"Banks & Credit Unions",
            "subcategory":"Bank",
            "type":"Services"
        }
    ],
    "sg:phone":"+1 937 653 8900",
    "sg:postcode":"43078",
    "sg:province":"OH",
    "sg:tags":[
        "loan"
    ],
    "wof:name":"Fast Payday Loans Of Ohio",
    "wof:placetype":"venue"
},
  "geometry": {"coordinates":[-83.72598000000001,40.105204],"type":"Point"}
}