{
  "type": "Feature",
  "properties": {
    "addr:full":"1331 S Mccord Rd Holland OH 43528",
    "addr:housenumber":"1331",
    "addr:postcode":"43528",
    "addr:street":"S Mccord Rd",
    "iso:country":"US",
    "sg:address":"1331 S Mccord Rd",
    "sg:city":"Holland",
    "sg:classifiers":[
        {
            "category":"Restaurant",
            "type":"Food & Drink"
        }
    ],
    "sg:menulink":"http://www.allmenus.com/oh/holland/86329-little-caesars-pizza/menu/",
    "sg:phone":"+1 419 866 5300",
    "sg:postcode":"43528",
    "sg:province":"OH",
    "sg:tags":[
        "american",
        "pizza"
    ],
    "wof:name":"Little Caesar's Pizza",
    "wof:placetype":"venue"
},
  "geometry": {"coordinates":[-83.703396,41.617799],"type":"Point"}
}