{
  "type": "Feature",
  "properties": {
    "iso:country":"US",
    "sg:address":"4852 Broadview Rd",
    "sg:city":"Cleveland",
    "sg:classifiers":[
        {
            "category":"Food & Beverages",
            "subcategory":"Groceries & Convenience Stores",
            "type":"Retail Goods"
        }
    ],
    "sg:phone":"+1 216 635 5353",
    "sg:postcode":"44109",
    "sg:province":"OH",
    "wof:name":"Mini Mart Express",
    "wof:placetype":"venue"
},
  "geometry": {"coordinates":[-81.696827,41.424216],"type":"Point"}
}