{
  "type": "Feature",
  "properties": {
    "addr:full": "4852 Broadview Rd Cleveland OH 44109",
    "addr:housenumber": "4852",
    "addr:postcode": "44109",
    "addr:street": "Broadview Rd",
    "iso:country": "US",
    "sg:address": "4852 Broadview Rd",
    "sg:city": "Cleveland",
    "sg:classifiers": [
      {
        "category": "Food \u0026 Beverages",
        "subcategory": "Groceries \u0026 Convenience Stores",
        "type": "Retail Goods"
      }
    ],
    "sg:phone": "+1 216 635 5353",
    "sg:postcode": "44109",
    "sg:province": "OH",
    "wof:name": "Mini Mart Express",
    "wof:placetype": "venue"
  },
  "geometry": {"coordinates":[-81.696827,41.424216],"type":"Point"}
}
