{
  "type": "Feature",
  "properties": {
    "addr:full":"3212 Lakeside Ave E Cleveland OH 44114",
    "addr:housenumber":"3212",
    "addr:postcode":"44114",
    "addr:street":"Lakeside Ave E",
    "iso:country":"US",
    "sg:address":"3212 Lakeside Ave E",
    "sg:city":"Cleveland",
    "sg:classifiers":[
        {
            "category":"Wholesale",
            "subcategory":"Metals & Minerals",
            "type":"Manufacturing & Wholesale Goods"
        }
    ],
    "sg:phone":"+1 216 621 5505",
    "sg:postcode":"44114",
    "sg:province":"OH",
    "sg:tags":[
        "steel",
        "warehouse"
    ],
    "wof:name":"O'Donnell Steel Co",
    "wof:placetype":"venue"
},
  "geometry": {"coordinates":[-81.672659,41.515014],"type":"Point"}
}