{
  "type": "Feature",
  "properties": {
    "iso:country":"US",
    "sg:address":"1269 Clydesdale Ct",
    "sg:city":"Columbus",
    "sg:classifiers":[
        {
            "category":"Shopping",
            "subcategory":"Florist",
            "type":"Retail Goods"
        }
    ],
    "sg:phone":"+1 614 985 3123",
    "sg:postcode":"43229",
    "sg:province":"OH",
    "wof:name":"John Morris Flowers",
    "wof:placetype":"venue"
},
  "geometry": {"coordinates":[-82.9807,40.102077],"type":"Point"}
}