{
  "type": "Feature",
  "properties": {
    "iso:country":"US",
    "sg:address":"6417 Hio Dr",
    "sg:city":"Cleveland",
    "sg:classifiers":[
        {
            "category":"Professional",
            "subcategory":"Advertising",
            "type":"Services"
        }
    ],
    "sg:phone":"+1 216 267 6740",
    "sg:postcode":"44142",
    "sg:province":"OH",
    "wof:name":"ENVELOPES&Mailer.Com",
    "wof:placetype":"venue"
},
  "geometry": {"coordinates":[-81.829958,41.391974],"type":"Point"}
}