{
  "type": "Feature",
  "properties": {
    "iso:country":"US",
    "sg:address":"1093 Canton Rd",
    "sg:city":"Akron",
    "sg:classifiers":[
        {
            "category":"Restaurant",
            "type":"Food & Drink"
        }
    ],
    "sg:phone":"+1 330 733 9112",
    "sg:postcode":"44312",
    "sg:province":"OH",
    "sg:tags":[
        "chicken",
        "eating",
        "dinner"
    ],
    "wof:name":"Country Crisp Carry-Out",
    "wof:placetype":"venue"
},
  "geometry": {"coordinates":[-81.43066,41.035219],"type":"Point"}
}