{
  "type": "Feature",
  "properties": {
    "addr:full":"275 N Main St Germantown OH 45327",
    "addr:housenumber":"275",
    "addr:postcode":"45327",
    "addr:street":"N Main St",
    "iso:country":"US",
    "sg:address":"275 N Main St",
    "sg:city":"Germantown",
    "sg:classifiers":[
        {
            "category":"Professional",
            "type":"Services"
        }
    ],
    "sg:phone":"+1 937 855 6424",
    "sg:postcode":"45327",
    "sg:province":"OH",
    "sg:tags":[
        "establishment"
    ],
    "wof:name":"Lindsey Woolseys Of Ohio",
    "wof:placetype":"venue"
},
  "geometry": {"coordinates":[-84.370667,39.627428],"type":"Point"}
}