{
  "type": "Feature",
  "properties": {
    "iso:country":"US",
    "sg:address":"2709 Turnkey Ct",
    "sg:city":"Cincinnati",
    "sg:classifiers":[
        {
            "category":"Freight",
            "type":"Transportation"
        }
    ],
    "sg:phone":"+1 513 232 5883",
    "sg:postcode":"45244",
    "sg:province":"OH",
    "sg:tags":[
        "operator",
        "trucking"
    ],
    "wof:name":"J S & Associates",
    "wof:placetype":"venue"
},
  "geometry": {"coordinates":[-84.35136,39.106141],"type":"Point"}
}