{
  "type": "Feature",
  "properties": {
    "addr:full": "4238 Ellison Rd Cleveland OH 44121",
    "addr:housenumber": "4238",
    "addr:postcode": "44121",
    "addr:street": "Ellison Rd",
    "iso:country": "US",
    "sg:address": "4238 Ellison Rd",
    "sg:city": "Cleveland",
    "sg:classifiers": [
      {
        "category": "Freight",
        "type": "Transportation"
      }
    ],
    "sg:phone": "+1 216 291 4768",
    "sg:postcode": "44121",
    "sg:province": "OH",
    "sg:tags": [
      "local",
      "without",
      "storage",
      "trucking"
    ],
    "wof:name": "Predator Motor Carrier",
    "wof:placetype": "venue"
  },
  "geometry": {"coordinates":[-81.530015,41.512153],"type":"Point"}
}
