{
  "type": "Feature",
  "properties": {
    "iso:country":"US",
    "sg:address":"469 Wards Corner Rd",
    "sg:city":"Loveland",
    "sg:classifiers":[
        {
            "category":"Food & Beverages",
            "subcategory":"Groceries & Convenience Stores",
            "type":"Retail Goods"
        }
    ],
    "sg:phone":"+1 513 831 2829",
    "sg:postcode":"45140",
    "sg:province":"OH",
    "sg:tags":[
        "station",
        "gasoline"
    ],
    "sg:website":"www.udfinc.com",
    "wof:name":"United Dairy Farmers",
    "wof:placetype":"venue"
},
  "geometry": {"coordinates":[-84.283046,39.222414],"type":"Point"}
}