{
  "type": "Feature",
  "properties": {
    "iso:country":"US",
    "sg:address":"8166 Creekstone Ln",
    "sg:city":"Blacklick",
    "sg:classifiers":[
        {
            "category":"Building & Trades",
            "subcategory":"Construction",
            "type":"Services"
        }
    ],
    "sg:phone":"+1 614 367 1859",
    "sg:postcode":"43004",
    "sg:province":"OH",
    "sg:tags":[
        "house"
    ],
    "wof:name":"Joshua Homes",
    "wof:placetype":"venue"
},
  "geometry": {"coordinates":[-82.789001,40.001843],"type":"Point"}
}