{
  "type": "Feature",
  "properties": {
    "iso:country":"US",
    "sg:address":"14 Overlook Dr",
    "sg:city":"Chillicothe",
    "sg:classifiers":[
        {
            "category":"Professional",
            "type":"Services"
        }
    ],
    "sg:phone":"+1 740 773 9700",
    "sg:postcode":"45601",
    "sg:province":"OH",
    "sg:tags":[
        "establishment"
    ],
    "wof:name":"Secure Guard",
    "wof:placetype":"venue"
},
  "geometry": {"coordinates":[-83.02067099999999,39.320209],"type":"Point"}
}