{
  "type": "Feature",
  "properties": {
    "iso:country":"US",
    "sg:address":"128 E 4th St",
    "sg:city":"East Liverpool",
    "sg:classifiers":[
        {
            "category":"Personal",
            "subcategory":"Beauty Salon",
            "type":"Services"
        }
    ],
    "sg:phone":"+1 330 385 0027",
    "sg:postcode":"43920",
    "sg:province":"OH",
    "wof:name":"Lords & Ladies",
    "wof:placetype":"venue"
},
  "geometry": {"coordinates":[-80.57890999999999,40.617892],"type":"Point"}
}