{
  "type": "Feature",
  "properties": {
    "addr:full": "128 E 4th St East Liverpool OH 43920",
    "addr:housenumber": "128",
    "addr:postcode": "43920",
    "addr:street": "E 4Th St",
    "iso:country": "US",
    "sg:address": "128 E 4th St",
    "sg:city": "East Liverpool",
    "sg:classifiers": [
      {
        "category": "Personal",
        "subcategory": "Beauty Salon",
        "type": "Services"
      }
    ],
    "sg:phone": "+1 330 385 0027",
    "sg:postcode": "43920",
    "sg:province": "OH",
    "wof:name": "Lords \u0026 Ladies",
    "wof:placetype": "venue"
  },
  "geometry": {"coordinates":[-80.57891,40.617892],"type":"Point"}
}
