{
  "type": "Feature",
  "properties": {
    "addr:full":"757 Michigan Ave Waterville OH 43566",
    "addr:housenumber":"757",
    "addr:postcode":"43566",
    "addr:street":"Michigan Ave",
    "iso:country":"US",
    "sg:address":"757 Michigan Ave",
    "sg:city":"Waterville",
    "sg:classifiers":[
        {
            "category":"Shopping",
            "subcategory":"Music",
            "type":"Retail Goods"
        },
        {
            "category":"Cinema",
            "subcategory":"Movie Rental",
            "type":"Entertainment"
        }
    ],
    "sg:phone":"+1 419 878 4500",
    "sg:postcode":"43566",
    "sg:province":"OH",
    "sg:tags":[
        "video",
        "disc",
        "tape",
        "cassette"
    ],
    "wof:name":"Video Connection 762",
    "wof:placetype":"venue"
},
  "geometry": {"coordinates":[-83.725433,41.500358],"type":"Point"}
}