{
  "type": "Feature",
  "properties": {
    "addr:full":"223 Morse Rd Columbus OH 43214",
    "addr:housenumber":"223",
    "addr:postcode":"43214",
    "addr:street":"Morse Rd",
    "iso:country":"US",
    "sg:address":"223 Morse Rd",
    "sg:city":"Columbus",
    "sg:classifiers":[
        {
            "category":"Real Estate",
            "subcategory":"Real Estate Agent",
            "type":"Services"
        }
    ],
    "sg:phone":"+1 614 267 7872",
    "sg:postcode":"43214",
    "sg:province":"OH",
    "wof:name":"Beechwold Realty",
    "wof:placetype":"venue"
},
  "geometry": {"coordinates":[-83.01305600000001,40.06212],"type":"Point"}
}