{
  "type": "Feature",
  "properties": {
    "addr:full":"48 W 3rd St Frazeysburg OH 43822",
    "addr:housenumber":"48",
    "addr:postcode":"43822",
    "addr:street":"W 3Rd St",
    "iso:country":"US",
    "sg:address":"48 W 3rd St",
    "sg:city":"Frazeysburg",
    "sg:classifiers":[
        {
            "category":"Food & Beverages",
            "subcategory":"Groceries & Convenience Stores",
            "type":"Retail Goods"
        }
    ],
    "sg:phone":"+1 740 828 2481",
    "sg:postcode":"43822",
    "sg:province":"OH",
    "wof:name":"Frazeysburg Village Drive Thru",
    "wof:placetype":"venue"
},
  "geometry": {"coordinates":[-82.11889600000001,40.118788],"type":"Point"}
}