{
  "type": "Feature",
  "properties": {
    "iso:country":"US",
    "sg:address":"26054 Dixie Hwy",
    "sg:city":"Perrysburg",
    "sg:classifiers":[
        {
            "category":"Travel",
            "subcategory":"Hotels & Motels",
            "type":"Entertainment"
        }
    ],
    "sg:phone":"+1 419 872 2902",
    "sg:postcode":"43551",
    "sg:province":"OH",
    "wof:name":"Economy Inn",
    "wof:placetype":"venue"
},
  "geometry": {"coordinates":[-83.636376,41.529987],"type":"Point"}
}