{
  "type": "Feature",
  "properties": {
    "addr:full": "290 State St Jackson OH 45640",
    "addr:housenumber": "290",
    "addr:postcode": "45640",
    "addr:street": "State St",
    "iso:country": "US",
    "sg:address": "290 State St",
    "sg:city": "Jackson",
    "sg:classifiers": [
      {
        "category": "Shopping",
        "subcategory": "Department Store",
        "type": "Retail Goods"
      }
    ],
    "sg:phone": "+1 740 286 0974",
    "sg:postcode": "45640",
    "sg:province": "OH",
    "sg:tags": [
      "shop"
    ],
    "wof:name": "J \u0026 S Wholesale",
    "wof:placetype": "venue"
  },
  "geometry": {"coordinates":[-82.654569,39.054806],"type":"Point"}
}
