{
  "type": "Feature",
  "properties": {
    "iso:country":"US",
    "sg:address":"290 State St",
    "sg:city":"Jackson",
    "sg:classifiers":[
        {
            "category":"Shopping",
            "subcategory":"Department Store",
            "type":"Retail Goods"
        }
    ],
    "sg:phone":"+1 740 286 0974",
    "sg:postcode":"45640",
    "sg:province":"OH",
    "sg:tags":[
        "shop"
    ],
    "wof:name":"J & S Wholesale",
    "wof:placetype":"venue"
},
  "geometry": {"coordinates":[-82.654569,39.054806],"type":"Point"}
}