{
  "type": "Feature",
  "properties": {
    "addr:full":"2179 Yorkshire Rd Columbus OH 43221",
    "addr:housenumber":"2179",
    "addr:postcode":"43221",
    "addr:street":"Yorkshire Rd",
    "iso:country":"US",
    "sg:address":"2179 Yorkshire Rd",
    "sg:city":"Columbus",
    "sg:classifiers":[
        {
            "category":"Building & Trades",
            "subcategory":"Construction",
            "type":"Services"
        }
    ],
    "sg:phone":"+1 614 485 1170",
    "sg:postcode":"43221",
    "sg:province":"OH",
    "sg:tags":[
        "home",
        "improvement"
    ],
    "wof:name":"Structure & Space",
    "wof:placetype":"venue"
},
  "geometry": {"coordinates":[-83.068247,40.000831],"type":"Point"}
}