{
  "type": "Feature",
  "properties": {
    "iso:country":"US",
    "sg:address":"889 State Rte 58",
    "sg:city":"Ashland",
    "sg:classifiers":[
        {
            "category":"Professional",
            "type":"Services"
        }
    ],
    "sg:phone":"+1 419 289 8832",
    "sg:postcode":"44805",
    "sg:province":"OH",
    "wof:name":"Dennis C Bates",
    "wof:placetype":"venue"
},
  "geometry": {"coordinates":[-82.312792,40.874681],"type":"Point"}
}