{
  "type": "Feature",
  "properties": {
    "iso:country":"US",
    "sg:address":"13595 Congress Lake Rd",
    "sg:city":"Hartville",
    "sg:classifiers":[
        {
            "category":"Professional",
            "type":"Services"
        }
    ],
    "sg:phone":"+1 330 877 0857",
    "sg:postcode":"44632",
    "sg:province":"OH",
    "wof:name":"Federick E Berndt",
    "wof:placetype":"venue"
},
  "geometry": {"coordinates":[-81.319993,40.9757],"type":"Point"}
}