{
  "type": "Feature",
  "properties": {
    "addr:full": "13075 Deer Run Wauseon OH 43567",
    "addr:housenumber": "13075",
    "addr:postcode": "43567",
    "addr:street": "Deer Run",
    "iso:country": "US",
    "sg:address": "13075 Deer Run",
    "sg:city": "Wauseon",
    "sg:classifiers": [
      {
        "category": "Real Estate",
        "subcategory": "Real Estate Operator",
        "type": "Services"
      }
    ],
    "sg:phone": "+1 419 335 0708",
    "sg:postcode": "43567",
    "sg:province": "OH",
    "sg:tags": [
      "building",
      "nonresidential"
    ],
    "wof:name": "J\u0026T Properties of Toledo LLC",
    "wof:placetype": "venue"
  },
  "geometry": {"coordinates":[-84.117546,41.567305],"type":"Point"}
}
