{
  "type": "Feature",
  "properties": {
    "addr:full": "1541 Oakwood Dr Cleveland OH 44121",
    "addr:housenumber": "1541",
    "addr:postcode": "44121",
    "addr:street": "Oakwood Dr",
    "iso:country": "US",
    "sg:address": "1541 Oakwood Dr",
    "sg:city": "Cleveland",
    "sg:classifiers": [
      {
        "category": "Professional",
        "subcategory": "Business Services",
        "type": "Services"
      }
    ],
    "sg:phone": "+1 216 291 1200",
    "sg:postcode": "44121",
    "sg:province": "OH",
    "sg:tags": [
      "interior",
      "consultant",
      "design",
      "decorator"
    ],
    "wof:name": "Teri Johnson Interiors",
    "wof:placetype": "venue"
  },
  "geometry": {"coordinates":[-81.541838,41.513263],"type":"Point"}
}
