{
  "type": "Feature",
  "properties": {
    "iso:country":"US",
    "sg:address":"570 Warehouse St",
    "sg:city":"Alliance",
    "sg:classifiers":[
        {
            "category":"Recreation",
            "type":"Entertainment"
        }
    ],
    "sg:phone":"+1 330 823 8199",
    "sg:postcode":"44601",
    "sg:province":"OH",
    "sg:tags":[
        "club",
        "membership"
    ],
    "wof:name":"Roma Society",
    "wof:placetype":"venue"
},
  "geometry": {"coordinates":[-81.097148,40.921964],"type":"Point"}
}