{
  "type": "Feature",
  "properties": {
    "iso:country":"US",
    "sg:address":"992 Harrison Ave",
    "sg:city":"Columbus",
    "sg:classifiers":[
        {
            "category":"Shopping",
            "subcategory":"Musical Instruments",
            "type":"Retail Goods"
        }
    ],
    "sg:phone":"+1 614 299 3279",
    "sg:postcode":"43201",
    "sg:province":"OH",
    "wof:name":"Hudson Music Hut",
    "wof:placetype":"venue"
},
  "geometry": {"coordinates":[-83.014203,39.980993],"type":"Point"}
}