{
  "type": "Feature",
  "properties": {
    "addr:full":"2900 Newpark Dr Norton OH 44203",
    "addr:postcode":"2900;44203",
    "addr:street":"Newpark Dr",
    "iso:country":"US",
    "sg:address":"2900 Newpark Dr",
    "sg:city":"Norton",
    "sg:classifiers":[
        {
            "category":"Professional",
            "type":"Services"
        }
    ],
    "sg:phone":"+1 330 848 4901",
    "sg:postcode":"44203",
    "sg:province":"OH",
    "sg:tags":[
        "establishment"
    ],
    "wof:name":"Sprinkfab",
    "wof:placetype":"venue"
},
  "geometry": {"coordinates":[-81.60538099999999,41.044529],"type":"Point"}
}