{
  "type": "Feature",
  "properties": {
    "iso:country":"US",
    "sg:address":"137 S State St",
    "sg:city":"Marion",
    "sg:classifiers":[
        {
            "category":"Local Transit",
            "type":"Transportation"
        }
    ],
    "sg:phone":"+1 740 382 9188",
    "sg:postcode":"43302",
    "sg:province":"OH",
    "sg:tags":[
        "bus",
        "line",
        "executive",
        "public"
    ],
    "sg:website":"http://www.greyhound.com",
    "wof:name":"Greyhound Bus Lines",
    "wof:placetype":"venue"
},
  "geometry": {"coordinates":[-83.127275,40.588164],"type":"Point"}
}