{
  "type": "Feature",
  "properties": {
    "addr:full": "4858 W Broad St Columbus OH 43228",
    "addr:housenumber": "4858",
    "addr:postcode": "43228",
    "addr:street": "W Broad St",
    "iso:country": "US",
    "sg:address": "4858 W Broad St",
    "sg:city": "Columbus",
    "sg:classifiers": [
      {
        "category": "Personal",
        "subcategory": "Beauty Salon",
        "type": "Services"
      }
    ],
    "sg:phone": "+1 614 878 3532",
    "sg:postcode": "43228",
    "sg:province": "OH",
    "sg:website": "http://www.regiscorp.com",
    "wof:name": "Saturday's Hair Salon",
    "wof:placetype": "venue"
  },
  "geometry": {"coordinates":[-83.130801,39.952163],"type":"Point"}
}
