{
  "type": "Feature",
  "properties": {
    "iso:country":"US",
    "sg:address":"7362 W Cross Creek Trl",
    "sg:city":"Brecksville",
    "sg:classifiers":[
        {
            "category":"Professional",
            "subcategory":"Computer Services",
            "type":"Services"
        }
    ],
    "sg:phone":"+1 440 736 7151",
    "sg:postcode":"44141",
    "sg:province":"OH",
    "sg:tags":[
        "technical",
        "assistance",
        "support"
    ],
    "wof:name":"Visual Data Group North America",
    "wof:placetype":"venue"
},
  "geometry": {"coordinates":[-81.64711,41.293665],"type":"Point"}
}