{
  "type": "Feature",
  "properties": {
    "addr:full": "419 W Wyoming Ave Cincinnati OH 45215",
    "addr:housenumber": "419",
    "addr:postcode": "45215",
    "addr:street": "W Wyoming Ave",
    "iso:country": "US",
    "sg:address": "419 W Wyoming Ave",
    "sg:city": "Cincinnati",
    "sg:classifiers": [
      {
        "category": "Place Of Worship",
        "subcategory": "Church",
        "type": "Public Place"
      },
      {
        "category": "Place Of Worship",
        "type": "Public Place"
      }
    ],
    "sg:phone": "+1 513 821 0410",
    "sg:postcode": "45215",
    "sg:province": "OH",
    "sg:tags": [
      "testament",
      "christ-new",
      "churches-church",
      "christ"
    ],
    "wof:name": "Church Of Chirst, Lockland",
    "wof:placetype": "venue"
  },
  "geometry": {"coordinates":[-84.456722,39.227171],"type":"Point"}
}
