{
  "type": "Feature",
  "properties": {
    "iso:country":"US",
    "sg:address":"4772 Pearl Rd",
    "sg:city":"Cleveland",
    "sg:classifiers":[
        {
            "category":"Professional",
            "subcategory":"Lawyer & Legal Services",
            "type":"Services"
        }
    ],
    "sg:phone":"+1 216 749 7466",
    "sg:postcode":"44109",
    "sg:province":"OH",
    "sg:tags":[
        "attorney"
    ],
    "wof:name":"Bert R Tomon",
    "wof:placetype":"venue"
},
  "geometry": {"coordinates":[-81.718391,41.427241],"type":"Point"}
}