{
  "type": "Feature",
  "properties": {
    "addr:full": "3390 Maple Ave Zanesville OH 43701",
    "addr:housenumber": "3390",
    "addr:postcode": "43701",
    "addr:street": "Maple Ave",
    "iso:country": "US",
    "sg:address": "3390 Maple Ave",
    "sg:city": "Zanesville",
    "sg:classifiers": [
      {
        "category": "Restaurant",
        "type": "Food \u0026 Drink"
      }
    ],
    "sg:menulink": "http://www.allmenus.com/oh/zanesville/69765-donatos-pizza/menu/",
    "sg:phone": "+1 740 452 7900",
    "sg:postcode": "43701",
    "sg:province": "OH",
    "sg:tags": [
      "sandwich",
      "salad",
      "soup",
      "american",
      "wrap",
      "pizza"
    ],
    "wof:name": "Donatos Pizza",
    "wof:placetype": "venue"
  },
  "geometry": {"coordinates":[-82.021437,39.985156],"type":"Point"}
}
