{
  "type": "Feature",
  "properties": {
    "addr:full": "17427 State Rte 163 Graytown OH 43432",
    "addr:housenumber": "17427",
    "addr:postcode": "43432",
    "addr:street": "State Rte 163",
    "iso:country": "US",
    "sg:address": "17427 State Rte 163",
    "sg:city": "Graytown",
    "sg:phone": "+1 419 862 2330",
    "sg:postcode": "43432",
    "sg:province": "OH",
    "sg:tags": [
      "wheat",
      "farm",
      "corn",
      "cash",
      "grain",
      "soybean"
    ],
    "wof:name": "Glenn Klaustermeye",
    "wof:placetype": "venue"
  },
  "geometry": {"coordinates":[-83.276986,41.516344],"type":"Point"}
}
