{
  "type": "Feature",
  "properties": {
    "addr:full":"275 Conover Dr Franklin OH 45005",
    "addr:housenumber":"275",
    "addr:postcode":"45005",
    "addr:street":"Conover Dr",
    "iso:country":"US",
    "sg:address":"275 Conover Dr",
    "sg:city":"Franklin",
    "sg:classifiers":[
        {
            "category":"Building & Trades",
            "subcategory":"Electrical",
            "type":"Services"
        }
    ],
    "sg:phone":"+1 937 704 0102",
    "sg:postcode":"45005",
    "sg:province":"OH",
    "sg:tags":[
        "electric",
        "contractor"
    ],
    "wof:name":"W G Fairfield Co",
    "wof:placetype":"venue"
},
  "geometry": {"coordinates":[-84.275104,39.563075],"type":"Point"}
}