{
  "type": "Feature",
  "properties": {
    "addr:full": "215 E National Rd Vandalia OH 45377",
    "addr:housenumber": "215",
    "addr:postcode": "45377",
    "addr:street": "E National Rd",
    "iso:country": "US",
    "sg:address": "215 E National Rd",
    "sg:city": "Vandalia",
    "sg:classifiers": [
      {
        "category": "Education",
        "subcategory": "Special Training",
        "type": "Public Place"
      }
    ],
    "sg:phone": "+1 937 454 6140",
    "sg:postcode": "45377",
    "sg:province": "OH",
    "sg:tags": [
      "center"
    ],
    "wof:name": "Vandalia Butler Board - Edu",
    "wof:placetype": "venue"
  },
  "geometry": {"coordinates":[-84.19257,39.891384],"type":"Point"}
}
