{
  "type": "Feature",
  "properties": {
    "iso:country":"US",
    "sg:address":"5834 Heisley Rd",
    "sg:city":"Mentor",
    "sg:classifiers":[
        {
            "category":"Professional",
            "subcategory":"Business Services",
            "type":"Services"
        }
    ],
    "sg:phone":"+1 440 358 1216",
    "sg:postcode":"44060",
    "sg:province":"OH",
    "sg:tags":[
        "electrical",
        "system",
        "power"
    ],
    "wof:name":"Lake Effect Solution",
    "wof:placetype":"venue"
},
  "geometry": {"coordinates":[-81.304226,41.709234],"type":"Point"}
}