{
  "type": "Feature",
  "properties": {
    "addr:full": "228 E Cuyahoga Falls Ave Akron OH 44310",
    "addr:housenumber": "228",
    "addr:postcode": "44310",
    "addr:street": "E Cuyahoga Falls Ave",
    "iso:country": "US",
    "sg:address": "228 E Cuyahoga Falls Ave",
    "sg:city": "Akron",
    "sg:classifiers": [
      {
        "category": "Personal",
        "subcategory": "Beauty Salon",
        "type": "Services"
      }
    ],
    "sg:phone": "+1 330 253 2332",
    "sg:postcode": "44310",
    "sg:province": "OH",
    "wof:name": "Hair Time",
    "wof:placetype": "venue"
  },
  "geometry": {"coordinates":[-81.5083,41.108598],"type":"Point"}
}
