{
  "type": "Feature",
  "properties": {
    "iso:country":"US",
    "sg:address":"300 Allen Bradley Dr",
    "sg:city":"Cleveland",
    "sg:classifiers":[
        {
            "category":"Wholesale",
            "subcategory":"Scrap",
            "type":"Manufacturing & Wholesale Goods"
        }
    ],
    "sg:phone":"+1 216 861 4455",
    "sg:postcode":"44124",
    "sg:province":"OH",
    "sg:tags":[
        "ingot",
        "metal",
        "aluminum"
    ],
    "sg:website":"www.beckaluminum.com",
    "wof:name":"Beck Aluminum Corp",
    "wof:placetype":"venue"
},
  "geometry": {"coordinates":[-81.458801,41.506105],"type":"Point"}
}