{
  "type": "Feature",
  "properties": {
    "iso:country":"US",
    "sg:address":"2140 Grandview Ave",
    "sg:city":"Portsmouth",
    "sg:classifiers":[
        {
            "category":"Organizations",
            "subcategory":"Religious Organization",
            "type":"Services"
        }
    ],
    "sg:phone":"+1 740 355 6967",
    "sg:postcode":"45662",
    "sg:province":"OH",
    "sg:tags":[
        "church"
    ],
    "wof:name":"Church - Christ Grant & Summit",
    "wof:placetype":"venue"
},
  "geometry": {"coordinates":[-82.97478,38.749368],"type":"Point"}
}