{
  "type": "Feature",
  "properties": {
    "iso:country":"US",
    "sg:address":"879 Oakwood Blvd",
    "sg:city":"Painesville",
    "sg:classifiers":[
        {
            "category":"Banks & Credit Unions",
            "subcategory":"Financial Services",
            "type":"Services"
        }
    ],
    "sg:phone":"+1 440 354 4078",
    "sg:postcode":"44077",
    "sg:province":"OH",
    "sg:tags":[
        "trust",
        "management"
    ],
    "wof:name":"Save Our Shoreline Inc",
    "wof:placetype":"venue"
},
  "geometry": {"coordinates":[-81.225264,41.761327],"type":"Point"}
}