{
  "type": "Feature",
  "properties": {
    "addr:full":"334 E Wapakoneta St Waynesfield OH 45896",
    "addr:housenumber":"334",
    "addr:postcode":"45896",
    "addr:street":"E Wapakoneta St",
    "iso:country":"US",
    "sg:address":"334 E Wapakoneta St",
    "sg:city":"Waynesfield",
    "sg:classifiers":[
        {
            "category":"Autos & Motor Vehicles",
            "subcategory":"Fuel & Gas Station",
            "type":"Retail Goods"
        }
    ],
    "sg:phone":"+1 419 568 3477",
    "sg:postcode":"45896",
    "sg:province":"OH",
    "sg:tags":[
        "oil"
    ],
    "wof:name":"Waynesfield Marathon",
    "wof:placetype":"venue"
},
  "geometry": {"coordinates":[-83.970159,40.600545],"type":"Point"}
}