{
  "type": "Feature",
  "properties": {
    "iso:country":"US",
    "sg:address":"180 W 4th St",
    "sg:city":"Minster",
    "sg:classifiers":[
        {
            "category":"Building & Trades",
            "subcategory":"Construction",
            "type":"Services"
        }
    ],
    "sg:phone":"+1 419 628 3530",
    "sg:postcode":"45865",
    "sg:province":"OH",
    "sg:tags":[
        "sheet",
        "metal",
        "roofing",
        "contractor"
    ],
    "wof:name":"Wyen & Sons Inc",
    "wof:placetype":"venue"
},
  "geometry": {"coordinates":[-84.383706,40.393052],"type":"Point"}
}