{
  "type": "Feature",
  "properties": {
    "addr:full": "180 W 4th St Minster OH 45865",
    "addr:housenumber": "180",
    "addr:postcode": "45865",
    "addr:street": "W 4Th St",
    "iso:country": "US",
    "sg:address": "180 W 4th St",
    "sg:city": "Minster",
    "sg:classifiers": [
      {
        "category": "Building \u0026 Trades",
        "subcategory": "Construction",
        "type": "Services"
      }
    ],
    "sg:phone": "+1 419 628 3530",
    "sg:postcode": "45865",
    "sg:province": "OH",
    "sg:tags": [
      "sheet",
      "metal",
      "roofing",
      "contractor"
    ],
    "wof:name": "Wyen \u0026 Sons Inc",
    "wof:placetype": "venue"
  },
  "geometry": {"coordinates":[-84.383706,40.393052],"type":"Point"}
}
