{
  "type": "Feature",
  "properties": {
    "addr:full":"115 N Main St North Baltimore OH 45872",
    "addr:housenumber":"115",
    "addr:postcode":"45872",
    "addr:street":"N Main St",
    "iso:country":"US",
    "sg:address":"115 N Main St",
    "sg:city":"North Baltimore",
    "sg:classifiers":[
        {
            "category":"Insurance",
            "subcategory":"Insurance Agent",
            "type":"Services"
        }
    ],
    "sg:phone":"+1 419 257 2671",
    "sg:postcode":"45872",
    "sg:province":"OH",
    "wof:name":"Ankney Insurance",
    "wof:placetype":"venue"
},
  "geometry": {"coordinates":[-83.67845199999999,41.184126],"type":"Point"}
}