{
  "type": "Feature",
  "properties": {
    "addr:full": "9831 State Rte 138 Leesburg OH 45135",
    "addr:housenumber": "9831",
    "addr:postcode": "45135",
    "addr:street": "State Rte 138",
    "iso:country": "US",
    "sg:address": "9831 State Rte 138",
    "sg:city": "Leesburg",
    "sg:phone": "+1 937 981 7189",
    "sg:postcode": "45135",
    "sg:province": "OH",
    "sg:tags": [
      "farm",
      "field",
      "wheat",
      "crop"
    ],
    "wof:name": "Jerry Terrell",
    "wof:placetype": "venue"
  },
  "geometry": {"coordinates":[-83.46078,39.282149],"type":"Point"}
}
