{
  "type": "Feature",
  "properties": {
    "addr:full":"14584 State Rte 115 Columbus Grove OH 45830",
    "addr:housenumber":"14584",
    "addr:postcode":"45830",
    "addr:street":"State Rte 115 Columbus Grove",
    "iso:country":"US",
    "sg:address":"14584 State Rte 115",
    "sg:city":"Columbus Grove",
    "sg:classifiers":[
        {
            "category":"Retail",
            "subcategory":"Auto Repair",
            "type":"Services"
        }
    ],
    "sg:phone":"+1 419 532 3908",
    "sg:postcode":"45830",
    "sg:province":"OH",
    "sg:tags":[
        "repairing",
        "automobile"
    ],
    "wof:name":"Ron Miehles Garage",
    "wof:placetype":"venue"
},
  "geometry": {"coordinates":[-84.18469399999999,40.965249],"type":"Point"}
}