{
  "type": "Feature",
  "properties": {
    "addr:full": "133 Washington St Hamilton OH 45011",
    "addr:housenumber": "133",
    "addr:postcode": "45011",
    "addr:street": "Washington St",
    "iso:country": "US",
    "sg:address": "133 Washington St",
    "sg:city": "Hamilton",
    "sg:classifiers": [
      {
        "category": "Building \u0026 Trades",
        "subcategory": "Landscaping Services",
        "type": "Services"
      }
    ],
    "sg:phone": "+1 513 737 2596",
    "sg:postcode": "45011",
    "sg:province": "OH",
    "sg:tags": [
      "landscape",
      "contractor"
    ],
    "wof:name": "Marks Landscaping",
    "wof:placetype": "venue"
  },
  "geometry": {"coordinates":[-84.567723,39.391317],"type":"Point"}
}
