{
  "type": "Feature",
  "properties": {
    "addr:full": "7800 Reynolds Rd Mentor OH 44060",
    "addr:housenumber": "7800",
    "addr:postcode": "44060",
    "addr:street": "Reynolds Rd",
    "iso:country": "US",
    "sg:address": "7800 Reynolds Rd",
    "sg:city": "Mentor",
    "sg:classifiers": [
      {
        "category": "Banks \u0026 Credit Unions",
        "subcategory": "Bank",
        "type": "Services"
      }
    ],
    "sg:phone": "+1 440 953 3606",
    "sg:postcode": "44060",
    "sg:province": "OH",
    "sg:tags": [
      "national",
      "commercial"
    ],
    "wof:name": "Firstmerit Bank NA",
    "wof:placetype": "venue"
  },
  "geometry": {"coordinates":[-81.377777,41.659155],"type":"Point"}
}
