{
  "type": "Feature",
  "properties": {
    "iso:country":"US",
    "sg:address":"10032 Deerfield Ct",
    "sg:city":"Twinsburg",
    "sg:classifiers":[
        {
            "category":"Shopping",
            "subcategory":"Department Store",
            "type":"Retail Goods"
        }
    ],
    "sg:phone":"+1 330 487 4378",
    "sg:postcode":"44087",
    "sg:province":"OH",
    "sg:tags":[
        "discount"
    ],
    "wof:name":"Profitable Products Inc",
    "wof:placetype":"venue"
},
  "geometry": {"coordinates":[-81.47856,41.342584],"type":"Point"}
}