{
  "type": "Feature",
  "properties": {
    "addr:full": "500 Clinton St Defiance OH 43512",
    "addr:housenumber": "500",
    "addr:postcode": "43512",
    "addr:street": "Clinton St",
    "iso:country": "US",
    "sg:address": "500 Clinton St",
    "sg:city": "Defiance",
    "sg:classifiers": [
      {
        "category": "Personal",
        "subcategory": "Tanning Parlor",
        "type": "Services"
      }
    ],
    "sg:phone": "+1 419 782 0300",
    "sg:postcode": "43512",
    "sg:province": "OH",
    "sg:tags": [
      "salon"
    ],
    "wof:name": "Sun's Edge Tanning Salon Inc",
    "wof:placetype": "venue"
  },
  "geometry": {"coordinates":[-84.363289,41.284887],"type":"Point"}
}
