{
  "type": "Feature",
  "properties": {
    "iso:country":"US",
    "sg:address":"3503 Bates Rd",
    "sg:city":"Madison",
    "sg:classifiers":[
        {
            "category":"Wholesale",
            "subcategory":"Metals & Minerals",
            "type":"Manufacturing & Wholesale Goods"
        }
    ],
    "sg:phone":"+1 440 428 1642",
    "sg:postcode":"44057",
    "sg:province":"OH",
    "sg:tags":[
        "steel"
    ],
    "wof:name":"Madison Steel",
    "wof:placetype":"venue"
},
  "geometry": {"coordinates":[-81.030158,41.77852],"type":"Point"}
}