{
  "type": "Feature",
  "properties": {
    "addr:full": "3503 Bates Rd Madison OH 44057",
    "addr:housenumber": "3503",
    "addr:postcode": "44057",
    "addr:street": "Bates Rd",
    "iso:country": "US",
    "sg:address": "3503 Bates Rd",
    "sg:city": "Madison",
    "sg:classifiers": [
      {
        "category": "Wholesale",
        "subcategory": "Metals \u0026 Minerals",
        "type": "Manufacturing \u0026 Wholesale Goods"
      }
    ],
    "sg:phone": "+1 440 428 1642",
    "sg:postcode": "44057",
    "sg:province": "OH",
    "sg:tags": [
      "steel"
    ],
    "wof:name": "Madison Steel",
    "wof:placetype": "venue"
  },
  "geometry": {"coordinates":[-81.030158,41.77852],"type":"Point"}
}
