{
  "type": "Feature",
  "properties": {
    "addr:full":"842 Toby Rd Eaton OH 45320",
    "addr:housenumber":"842",
    "addr:postcode":"45320",
    "addr:street":"Toby Rd",
    "iso:country":"US",
    "sg:address":"842 Toby Rd",
    "sg:city":"Eaton",
    "sg:classifiers":[
        {
            "category":"Farming",
            "subcategory":"Farm",
            "type":"Manufacturing & Wholesale Goods"
        }
    ],
    "sg:phone":"+1 937 456 3860",
    "sg:postcode":"45320",
    "sg:province":"OH",
    "sg:tags":[
        "operator",
        "general"
    ],
    "wof:name":"Fred Haber",
    "wof:placetype":"venue"
},
  "geometry": {"coordinates":[-84.703579,39.754368],"type":"Point"}
}