{
  "type": "Feature",
  "properties": {
    "addr:full": "2060 Mogadore Rd Akron OH 44312",
    "addr:housenumber": "2060",
    "addr:postcode": "44312",
    "addr:street": "Mogadore Rd",
    "iso:country": "US",
    "sg:address": "2060 Mogadore Rd",
    "sg:city": "Akron",
    "sg:classifiers": [
      {
        "category": "Restaurant",
        "type": "Food \u0026 Drink"
      }
    ],
    "sg:menulink": "http://www.allmenus.com/oh/akron/164583-wendys/menu/",
    "sg:phone": "+1 330 784 4891",
    "sg:postcode": "44312",
    "sg:province": "OH",
    "sg:tags": [
      "burger",
      "american",
      "soup"
    ],
    "wof:name": "Wendy's",
    "wof:placetype": "venue"
  },
  "geometry": {"coordinates":[-81.454527,41.061627],"type":"Point"}
}
