{
  "type": "Feature",
  "properties": {
    "addr:full":"6999 State Rte 350 Clarksville OH 45113",
    "addr:housenumber":"6999",
    "addr:postcode":"45113",
    "addr:street":"State Rte 350",
    "iso:country":"US",
    "sg:address":"6999 State Rte 350",
    "sg:city":"Clarksville",
    "sg:classifiers":[
        {
            "category":"Utilities",
            "subcategory":"Cable",
            "type":"Services"
        }
    ],
    "sg:phone":"+1 937 289 3269",
    "sg:postcode":"45113",
    "sg:province":"OH",
    "sg:tags":[
        "television"
    ],
    "wof:name":"KAS Cable TV Inc",
    "wof:placetype":"venue"
},
  "geometry": {"coordinates":[-83.97591199999999,39.396213],"type":"Point"}
}