{
  "type": "Feature",
  "properties": {
    "iso:country":"US",
    "sg:address":"5220 Warrensville Center Rd",
    "sg:city":"Cleveland",
    "sg:classifiers":[
        {
            "category":"Retail",
            "subcategory":"Auto Repair",
            "type":"Services"
        }
    ],
    "sg:phone":"+1 216 662 3303",
    "sg:postcode":"44137",
    "sg:province":"OH",
    "sg:tags":[
        "repairing",
        "automobile"
    ],
    "wof:name":"Nationwide Brake & Tire",
    "wof:placetype":"venue"
},
  "geometry": {"coordinates":[-81.537413,41.418679],"type":"Point"}
}