{
  "type": "Feature",
  "properties": {
    "iso:country":"US",
    "sg:address":"88 Decrow Ave",
    "sg:city":"Newark",
    "sg:classifiers":[
        {
            "category":"Manufacturing",
            "subcategory":"Tools & Machinery",
            "type":"Manufacturing & Wholesale Goods"
        }
    ],
    "sg:phone":"+1 740 344 3111",
    "sg:postcode":"43055",
    "sg:province":"OH",
    "sg:tags":[
        "machine",
        "die",
        "shop"
    ],
    "wof:name":"Gemco Machine & Tool Inc",
    "wof:placetype":"venue"
},
  "geometry": {"coordinates":[-82.428622,40.049716],"type":"Point"}
}