{
  "type": "Feature",
  "properties": {
    "addr:full":"1575 Ritchie Rd Cuyahoga Falls OH 44224",
    "addr:housenumber":"1575",
    "addr:postcode":"44224",
    "addr:street":"Ritchie Rd",
    "iso:country":"US",
    "sg:address":"1575 Ritchie Rd",
    "sg:city":"Cuyahoga Falls",
    "sg:classifiers":[
        {
            "category":"Building & Trades",
            "subcategory":"Construction",
            "type":"Services"
        }
    ],
    "sg:phone":"+1 330 688 3276",
    "sg:postcode":"44224",
    "sg:province":"OH",
    "sg:tags":[
        "maker",
        "cabinet"
    ],
    "wof:name":"Dennis William Co",
    "wof:placetype":"venue"
},
  "geometry": {"coordinates":[-81.45410099999999,41.185504],"type":"Point"}
}