{
  "type": "Feature",
  "properties": {
    "addr:full":"5210 E Farnhurst Rd Cleveland OH 44124",
    "addr:housenumber":"5210",
    "addr:postcode":"44124",
    "addr:street":"E Farnhurst Rd",
    "iso:country":"US",
    "sg:address":"5210 E Farnhurst Rd",
    "sg:city":"Cleveland",
    "sg:classifiers":[
        {
            "category":"Taxi",
            "type":"Transportation"
        }
    ],
    "sg:phone":"+1 440 720 0770",
    "sg:postcode":"44124",
    "sg:province":"OH",
    "sg:tags":[
        "taxicab"
    ],
    "wof:name":"A & D Transportation Svc",
    "wof:placetype":"venue"
},
  "geometry": {"coordinates":[-81.49324300000001,41.523691],"type":"Point"}
}