{
  "type": "Feature",
  "properties": {
    "addr:full":"7353 Reading Rd Cincinnati OH 45237",
    "addr:housenumber":"7353",
    "addr:postcode":"45237",
    "addr:street":"Reading Rd",
    "iso:country":"US",
    "sg:address":"7353 Reading Rd",
    "sg:city":"Cincinnati",
    "sg:classifiers":[
        {
            "category":"Building & Trades",
            "subcategory":"Plumbing",
            "type":"Services"
        }
    ],
    "sg:phone":"+1 513 631 8488",
    "sg:postcode":"45237",
    "sg:province":"OH",
    "sg:tags":[
        "mechanical",
        "contractor"
    ],
    "wof:name":"R Kelly Inc",
    "wof:placetype":"venue"
},
  "geometry": {"coordinates":[-84.45957799999999,39.195793],"type":"Point"}
}