{
  "type": "Feature",
  "properties": {
    "addr:full":"4766 Dues Dr Cincinnati OH 45246",
    "addr:housenumber":"4766",
    "addr:postcode":"45246",
    "addr:street":"Dues Dr",
    "iso:country":"US",
    "sg:address":"4766 Dues Dr",
    "sg:city":"Cincinnati",
    "sg:classifiers":[
        {
            "category":"Manufacturing",
            "subcategory":"Retail Goods",
            "type":"Manufacturing & Wholesale Goods"
        }
    ],
    "sg:phone":"+1 513 942 8655",
    "sg:postcode":"45246",
    "sg:province":"OH",
    "sg:tags":[
        "manufacturer"
    ],
    "wof:name":"Techna Ndt",
    "wof:placetype":"venue"
},
  "geometry": {"coordinates":[-84.465546,39.313047],"type":"Point"}
}