{
  "type": "Feature",
  "properties": {
    "addr:full": "5618 Glenway Ave Cincinnati OH 45238",
    "addr:housenumber": "5618",
    "addr:postcode": "45238",
    "addr:street": "Glenway Ave",
    "iso:country": "US",
    "sg:address": "5618 Glenway Ave",
    "sg:city": "Cincinnati",
    "sg:classifiers": [
      {
        "category": "Insurance",
        "subcategory": "Insurance Agent",
        "type": "Services"
      }
    ],
    "sg:phone": "+1 513 574 4676",
    "sg:postcode": "45238",
    "sg:province": "OH",
    "wof:name": "Robert Huber Insurance Agency",
    "wof:placetype": "venue"
  },
  "geometry": {"coordinates":[-84.61166,39.134357],"type":"Point"}
}
