{
  "type": "Feature",
  "properties": {
    "iso:country":"US",
    "sg:address":"1504 US Rte 62",
    "sg:city":"Wilmot",
    "sg:classifiers":[
        {
            "category":"Restaurant",
            "type":"Food & Drink"
        }
    ],
    "sg:phone":"+1 330 359 5454",
    "sg:postcode":"44689",
    "sg:province":"OH",
    "sg:tags":[
        "country",
        "living"
    ],
    "wof:name":"Grandmas Alpine Homestead",
    "wof:placetype":"venue"
},
  "geometry": {"coordinates":[-81.675343,40.639813],"type":"Point"}
}