{
  "type": "Feature",
  "properties": {
    "addr:full":"33321 Lake Rd Avon Lake OH 44012",
    "addr:housenumber":"33321",
    "addr:postcode":"44012",
    "addr:street":"Lake Rd",
    "iso:country":"US",
    "sg:address":"33321 Lake Rd",
    "sg:city":"Avon Lake",
    "sg:classifiers":[
        {
            "category":"Freight",
            "type":"Transportation"
        }
    ],
    "sg:phone":"+1 440 933 5929",
    "sg:postcode":"44012",
    "sg:province":"OH",
    "sg:tags":[
        "mover"
    ],
    "wof:name":"Executive Relocation Svc",
    "wof:placetype":"venue"
},
  "geometry": {"coordinates":[-82.044027,41.505953],"type":"Point"}
}