{
  "type": "Feature",
  "properties": {
    "addr:full": "18621 Neff Rd Cleveland OH 44119",
    "addr:housenumber": "18621",
    "addr:postcode": "44119",
    "addr:street": "Neff Rd",
    "iso:country": "US",
    "sg:address": "18621 Neff Rd",
    "sg:city": "Cleveland",
    "sg:classifiers": [
      {
        "category": "Organizations",
        "subcategory": "Non-profit Organization",
        "type": "Services"
      },
      {
        "category": "Health Services",
        "subcategory": "Nursing And Care Facility",
        "type": "Services"
      }
    ],
    "sg:phone": "+1 216 486 0268",
    "sg:postcode": "44119",
    "sg:province": "OH",
    "sg:tags": [
      "intermediate",
      "skilled"
    ],
    "wof:name": "Slovene Home For The Aged",
    "wof:placetype": "venue"
  },
  "geometry": {"coordinates":[-81.548708,41.581592],"type":"Point"}
}
