{
  "type": "Feature",
  "properties": {
    "addr:full":"8310 W Chester Rd West Chester OH 45069",
    "addr:housenumber":"8310",
    "addr:postcode":"45069",
    "addr:street":"W Chester Rd",
    "iso:country":"US",
    "sg:address":"8310 W Chester Rd",
    "sg:city":"West Chester",
    "sg:classifiers":[
        {
            "category":"Professional",
            "subcategory":"Lawyer & Legal Services",
            "type":"Services"
        }
    ],
    "sg:phone":"+1 513 777 2222",
    "sg:postcode":"45069",
    "sg:province":"OH",
    "sg:tags":[
        "attorney"
    ],
    "sg:website":"www.lyonsandlyonslaw.com",
    "wof:name":"Lyons & Lyons Co Lpa",
    "wof:placetype":"venue"
},
  "geometry": {"coordinates":[-84.35343399999999,39.317707],"type":"Point"}
}