{
  "type": "Feature",
  "properties": {
    "addr:full": "1517 Golden Gate Plz Cleveland OH 44124",
    "addr:housenumber": "1517",
    "addr:postcode": "44124",
    "addr:street": "Golden Gate Plz",
    "iso:country": "US",
    "sg:address": "1517 Golden Gate Plz",
    "sg:city": "Cleveland",
    "sg:classifiers": [
      {
        "category": "Building \u0026 Trades",
        "subcategory": "Plumbing",
        "type": "Services"
      }
    ],
    "sg:phone": "+1 440 460 1777",
    "sg:postcode": "44124",
    "sg:province": "OH",
    "sg:tags": [
      "contractor"
    ],
    "wof:name": "Carpenter Coml Coolg \u0026 Htg",
    "wof:placetype": "venue"
  },
  "geometry": {"coordinates":[-81.449092,41.518957],"type":"Point"}
}
