{
  "type": "Feature",
  "properties": {
    "iso:country":"US",
    "sg:address":"1517 Golden Gate Plz",
    "sg:city":"Cleveland",
    "sg:classifiers":[
        {
            "category":"Building & Trades",
            "subcategory":"Plumbing",
            "type":"Services"
        }
    ],
    "sg:phone":"+1 440 460 1777",
    "sg:postcode":"44124",
    "sg:province":"OH",
    "sg:tags":[
        "contractor"
    ],
    "wof:name":"Carpenter Coml Coolg & Htg",
    "wof:placetype":"venue"
},
  "geometry": {"coordinates":[-81.449092,41.518957],"type":"Point"}
}