{
  "type": "Feature",
  "properties": {
    "addr:full":"1687 Sandy Knoll Dr Uniontown OH 44685",
    "addr:housenumber":"1687",
    "addr:postcode":"44685",
    "addr:street":"Sandy Knoll Dr",
    "iso:country":"US",
    "sg:address":"1687 Sandy Knoll Dr",
    "sg:city":"Uniontown",
    "sg:classifiers":[
        {
            "category":"Restaurant",
            "type":"Food & Drink"
        }
    ],
    "sg:menulink":"http://www.allmenus.com/oh/green/175188-arbys/menu/",
    "sg:phone":"+1 330 896 2525",
    "sg:postcode":"44685",
    "sg:province":"OH",
    "sg:tags":[
        "burger",
        "american"
    ],
    "wof:name":"Arby's",
    "wof:placetype":"venue"
},
  "geometry": {"coordinates":[-81.46627700000001,40.963022],"type":"Point"}
}