{
  "type": "Feature",
  "properties": {
    "addr:full":"4549 Mayfield Rd Cleveland OH 44121",
    "addr:housenumber":"4549",
    "addr:postcode":"44121",
    "addr:street":"Mayfield Rd",
    "iso:country":"US",
    "sg:address":"4549 Mayfield Rd",
    "sg:city":"Cleveland",
    "sg:classifiers":[
        {
            "category":"Autos & Motor Vehicles",
            "subcategory":"Fuel & Gas Station",
            "type":"Retail Goods"
        },
        {
            "category":"Food & Beverages",
            "subcategory":"Groceries & Convenience Stores",
            "type":"Retail Goods"
        }
    ],
    "sg:phone":"+1 216 382 4141",
    "sg:postcode":"44121",
    "sg:province":"OH",
    "sg:website":"http://www.speedway.com",
    "wof:name":"Speedway",
    "wof:placetype":"venue"
},
  "geometry": {"coordinates":[-81.5158,41.519761],"type":"Point"}
}