{
  "type": "Feature",
  "properties": {
    "iso:country":"US",
    "sg:address":"1387 W Hunter St",
    "sg:city":"Logan",
    "sg:classifiers":[
        {
            "category":"Health Services",
            "subcategory":"Health Practitioner",
            "type":"Services"
        }
    ],
    "sg:phone":"+1 740 380 2565",
    "sg:postcode":"43138",
    "sg:province":"OH",
    "sg:tags":[
        "therapist",
        "physical"
    ],
    "wof:name":"Ohio Rehab & Diagnostic Ctr",
    "wof:placetype":"venue"
},
  "geometry": {"coordinates":[-82.427488,39.543377],"type":"Point"}
}