{
  "type": "Feature",
  "properties": {
    "addr:full": "1387 W Hunter St Logan OH 43138",
    "addr:housenumber": "1387",
    "addr:postcode": "43138",
    "addr:street": "W Hunter St",
    "iso:country": "US",
    "sg:address": "1387 W Hunter St",
    "sg:city": "Logan",
    "sg:classifiers": [
      {
        "category": "Health Services",
        "subcategory": "Health Practitioner",
        "type": "Services"
      }
    ],
    "sg:phone": "+1 740 380 2565",
    "sg:postcode": "43138",
    "sg:province": "OH",
    "sg:tags": [
      "therapist",
      "physical"
    ],
    "wof:name": "Ohio Rehab \u0026 Diagnostic Ctr",
    "wof:placetype": "venue"
  },
  "geometry": {"coordinates":[-82.427488,39.543377],"type":"Point"}
}
