{
  "type": "Feature",
  "properties": {
    "iso:country":"US",
    "sg:address":"4545 Hidden Hollow Trl",
    "sg:city":"Tipp City",
    "sg:classifiers":[
        {
            "category":"Manufacturing",
            "subcategory":"Toys & Sporting Goods",
            "type":"Manufacturing & Wholesale Goods"
        }
    ],
    "sg:phone":"+1 937 667 4704",
    "sg:postcode":"45371",
    "sg:province":"OH",
    "sg:tags":[
        "mfg"
    ],
    "wof:name":"Hidden Hollow Bear Co",
    "wof:placetype":"venue"
},
  "geometry": {"coordinates":[-84.177952,39.922741],"type":"Point"}
}