{
  "type": "Feature",
  "properties": {
    "addr:full": "4545 Hidden Hollow Trl Tipp City OH 45371",
    "addr:housenumber": "4545",
    "addr:postcode": "45371",
    "addr:street": "Hidden Hollow Trl",
    "iso:country": "US",
    "sg:address": "4545 Hidden Hollow Trl",
    "sg:city": "Tipp City",
    "sg:classifiers": [
      {
        "category": "Manufacturing",
        "subcategory": "Toys \u0026 Sporting Goods",
        "type": "Manufacturing \u0026 Wholesale Goods"
      }
    ],
    "sg:phone": "+1 937 667 4704",
    "sg:postcode": "45371",
    "sg:province": "OH",
    "sg:tags": [
      "mfg"
    ],
    "wof:name": "Hidden Hollow Bear Co",
    "wof:placetype": "venue"
  },
  "geometry": {"coordinates":[-84.177952,39.922741],"type":"Point"}
}
