{
  "type": "Feature",
  "properties": {
    "iso:country":"US",
    "sg:address":"3883 Croydon Dr NW",
    "sg:city":"Canton",
    "sg:classifiers":[
        {
            "category":"Banks & Credit Unions",
            "subcategory":"Investment Brokerage",
            "type":"Services"
        }
    ],
    "sg:phone":"+1 330 493 6799",
    "sg:postcode":"44718",
    "sg:province":"OH",
    "sg:tags":[
        "book",
        "publishing"
    ],
    "wof:name":"Matthew Publishing Co",
    "wof:placetype":"venue"
},
  "geometry": {"coordinates":[-81.41698100000001,40.835314],"type":"Point"}
}