{
  "type": "Feature",
  "properties": {
    "addr:full": "2900 W US Hwy 22 and 3 Maineville OH 45039",
    "addr:housenumber": "2900",
    "addr:postcode": "45039",
    "addr:street": "W Us Hwy 22 And 3",
    "iso:country": "US",
    "sg:address": "2900 W US Hwy 22 and 3",
    "sg:city": "Maineville",
    "sg:classifiers": [
      {
        "category": "Food \u0026 Beverages",
        "subcategory": "Groceries \u0026 Convenience Stores",
        "type": "Retail Goods"
      }
    ],
    "sg:phone": "+1 513 683 4001",
    "sg:postcode": "45039",
    "sg:province": "OH",
    "sg:tags": [
      "florist",
      "grocer",
      "cookie",
      "mfg"
    ],
    "wof:name": "Kroger",
    "wof:placetype": "venue"
  },
  "geometry": {"coordinates":[-84.276822,39.308554],"type":"Point"}
}
