{
  "type": "Feature",
  "properties": {
    "addr:full": "351 W Church St Orrville OH 44667",
    "addr:housenumber": "351",
    "addr:postcode": "44667",
    "addr:street": "W Church St",
    "iso:country": "US",
    "sg:address": "351 W Church St",
    "sg:city": "Orrville",
    "sg:classifiers": [
      {
        "category": "Home \u0026 Garden",
        "subcategory": "Carpets \u0026 Floor Coverings",
        "type": "Retail Goods"
      }
    ],
    "sg:phone": "+1 330 683 4763",
    "sg:postcode": "44667",
    "sg:province": "OH",
    "sg:tags": [
      "material"
    ],
    "sg:website": "www.stollers.net",
    "wof:name": "Stoller Floors",
    "wof:placetype": "venue"
  },
  "geometry": {"coordinates":[-81.767417,40.842397],"type":"Point"}
}
