{
  "type": "Feature",
  "properties": {
    "iso:country":"US",
    "sg:address":"300 E Silver St",
    "sg:city":"Lebanon",
    "sg:classifiers":[
        {
            "category":"Government",
            "subcategory":"Office",
            "type":"Public Place"
        }
    ],
    "sg:phone":"+1 513 695 1130",
    "sg:postcode":"45036",
    "sg:province":"OH",
    "wof:name":"Warren County One-Stop",
    "wof:placetype":"venue"
},
  "geometry": {"coordinates":[-84.20230599999999,39.435117],"type":"Point"}
}