{
  "type": "Feature",
  "properties": {
    "addr:full": "2012 W 25th St Cleveland OH 44113",
    "addr:housenumber": "2012",
    "addr:postcode": "44113",
    "addr:street": "W 25Th St",
    "iso:country": "US",
    "sg:address": "2012 W 25th St",
    "sg:city": "Cleveland",
    "sg:classifiers": [
      {
        "category": "Health Services",
        "subcategory": "Doctor",
        "type": "Services"
      }
    ],
    "sg:phone": "+1 440 888 3030",
    "sg:postcode": "44113",
    "sg:province": "OH",
    "sg:tags": [
      "clinic"
    ],
    "wof:name": "West Side Industrial Clinic",
    "wof:placetype": "venue"
  },
  "geometry": {"coordinates":[-81.703196,41.483878],"type":"Point"}
}
