{
  "type": "Feature",
  "properties": {
    "addr:full":"16687 Hilltop Park Pl Chagrin Falls OH 44023",
    "addr:housenumber":"16687",
    "addr:postcode":"44023",
    "addr:street":"Hilltop Park Pl",
    "iso:country":"US",
    "sg:address":"16687 Hilltop Park Pl",
    "sg:city":"Chagrin Falls",
    "sg:classifiers":[
        {
            "category":"Professional",
            "subcategory":"Management & Consulting",
            "type":"Services"
        }
    ],
    "sg:phone":"+1 440 543 6063",
    "sg:postcode":"44023",
    "sg:province":"OH",
    "sg:tags":[
        "marketing",
        "program"
    ],
    "wof:name":"G & M Marketing Corp",
    "wof:placetype":"venue"
},
  "geometry": {"coordinates":[-81.350774,41.413451],"type":"Point"}
}