{
  "type": "Feature",
  "properties": {
    "addr:full":"9830 Valley View Rd Macedonia OH 44056",
    "addr:housenumber":"9830",
    "addr:postcode":"44056",
    "addr:street":"Valley View Rd",
    "iso:country":"US",
    "sg:address":"9830 Valley View Rd",
    "sg:city":"Macedonia",
    "sg:classifiers":[
        {
            "category":"Insurance",
            "subcategory":"Insurance Agent",
            "type":"Services"
        }
    ],
    "sg:phone":"+1 330 468 0918",
    "sg:postcode":"44056",
    "sg:province":"OH",
    "wof:name":"Nixon Laurianti Insurance Inc",
    "wof:placetype":"venue"
},
  "geometry": {"coordinates":[-81.50673399999999,41.312108],"type":"Point"}
}