{
  "type": "Feature",
  "properties": {
    "addr:full": "14205 Orinoco Ave Cleveland OH 44112",
    "addr:housenumber": "14205",
    "addr:postcode": "44112",
    "addr:street": "Orinoco Ave",
    "iso:country": "US",
    "sg:address": "14205 Orinoco Ave",
    "sg:city": "Cleveland",
    "sg:classifiers": [
      {
        "category": "Freight",
        "type": "Transportation"
      }
    ],
    "sg:phone": "+1 216 761 3850",
    "sg:postcode": "44112",
    "sg:province": "OH",
    "wof:name": "Fuller Transportation",
    "wof:placetype": "venue"
  },
  "geometry": {"coordinates":[-81.58487,41.538077],"type":"Point"}
}
