{
  "type": "Feature",
  "properties": {
    "addr:full":"1111 E Broad St Columbus OH 43205",
    "addr:housenumber":"1111",
    "addr:postcode":"43205",
    "addr:street":"E Broad St",
    "iso:country":"US",
    "sg:address":"1111 E Broad St",
    "sg:city":"Columbus",
    "sg:classifiers":[
        {
            "category":"Insurance",
            "subcategory":"Hazard Insurance",
            "type":"Services"
        }
    ],
    "sg:phone":"+1 614 251 5284",
    "sg:postcode":"43205",
    "sg:province":"OH",
    "sg:tags":[
        "carrier"
    ],
    "wof:name":"CNA Surety Corporation",
    "wof:placetype":"venue"
},
  "geometry": {"coordinates":[-82.970519,39.965617],"type":"Point"}
}