{
  "type": "Feature",
  "properties": {
    "iso:country":"US",
    "sg:address":"523 Jefferson Ave",
    "sg:city":"Cincinnati",
    "sg:classifiers":[
        {
            "category":"Restaurant",
            "type":"Food & Drink"
        }
    ],
    "sg:phone":"+1 513 821 6546",
    "sg:postcode":"45215",
    "sg:province":"OH",
    "wof:name":"Maloney Sports Bar",
    "wof:placetype":"venue"
},
  "geometry": {"coordinates":[-84.44527100000001,39.219155],"type":"Point"}
}