{
  "type": "Feature",
  "properties": {
    "addr:full":"2509 E Main St Columbus OH 43209",
    "addr:housenumber":"2509",
    "addr:postcode":"43209",
    "addr:street":"E Main St",
    "iso:country":"US",
    "sg:address":"2509 E Main St",
    "sg:city":"Columbus",
    "sg:classifiers":[
        {
            "category":"Personal",
            "subcategory":"Beauty Salon",
            "type":"Services"
        },
        {
            "category":"Personal",
            "subcategory":"Barber",
            "type":"Services"
        }
    ],
    "sg:phone":"+1 614 237 8721",
    "sg:postcode":"43209",
    "sg:province":"OH",
    "sg:tags":[
        "hair",
        "accessory",
        "stylist",
        "supply"
    ],
    "sg:website":"http://www.greatclips.com/",
    "wof:name":"Great Clips",
    "wof:placetype":"venue"
},
  "geometry": {"coordinates":[-82.931732,39.95703],"type":"Point"}
}