{
  "type": "Feature",
  "properties": {
    "iso:country":"US",
    "sg:address":"545 Market St",
    "sg:city":"Youngstown",
    "sg:classifiers":[
        {
            "category":"Retail",
            "subcategory":"Repair Shop",
            "type":"Services"
        }
    ],
    "sg:phone":"+1 330 743 6000",
    "sg:postcode":"44502",
    "sg:province":"OH",
    "sg:tags":[
        "related"
    ],
    "wof:name":"Murray's Used Cars",
    "wof:placetype":"venue"
},
  "geometry": {"coordinates":[-80.653622,41.094252],"type":"Point"}
}