{
  "type": "Feature",
  "properties": {
    "addr:full": "2727 Harding Hwy Lima OH 45804",
    "addr:housenumber": "2727",
    "addr:postcode": "45804",
    "addr:street": "Harding Hwy",
    "iso:country": "US",
    "sg:address": "2727 Harding Hwy",
    "sg:city": "Lima",
    "sg:classifiers": [
      {
        "category": "Professional",
        "subcategory": "Lawyer \u0026 Legal Services",
        "type": "Services"
      }
    ],
    "sg:phone": "+1 419 224 1011",
    "sg:postcode": "45804",
    "sg:province": "OH",
    "sg:tags": [
      "attorney"
    ],
    "wof:name": "Dan Martin \u0026 Assoc Inc",
    "wof:placetype": "venue"
  },
  "geometry": {"coordinates":[-84.056737,40.731006],"type":"Point"}
}
