{
  "type": "Feature",
  "properties": {
    "iso:country":"US",
    "sg:address":"2727 Harding Hwy",
    "sg:city":"Lima",
    "sg:classifiers":[
        {
            "category":"Professional",
            "subcategory":"Lawyer & Legal Services",
            "type":"Services"
        }
    ],
    "sg:phone":"+1 419 224 1011",
    "sg:postcode":"45804",
    "sg:province":"OH",
    "sg:tags":[
        "attorney"
    ],
    "wof:name":"Dan Martin & Assoc Inc",
    "wof:placetype":"venue"
},
  "geometry": {"coordinates":[-84.056737,40.731006],"type":"Point"}
}