{
  "type": "Feature",
  "properties": {
    "addr:full":"201 N Main Ave Sidney OH 45365",
    "addr:housenumber":"201",
    "addr:postcode":"45365",
    "addr:street":"N Main Ave",
    "iso:country":"US",
    "sg:address":"201 N Main Ave",
    "sg:city":"Sidney",
    "sg:classifiers":[
        {
            "category":"Museum",
            "type":"Entertainment"
        }
    ],
    "sg:phone":"+1 937 498 1653",
    "sg:postcode":"45365",
    "sg:province":"OH",
    "sg:website":"www.shelbycountyhistory.org",
    "wof:name":"Shelby County Historical Scty",
    "wof:placetype":"venue"
},
  "geometry": {"coordinates":[-84.15512699999999,40.288008],"type":"Point"}
}