{
  "type": "Feature",
  "properties": {
    "iso:country":"US",
    "sg:address":"27 E Russell St",
    "sg:city":"Columbus",
    "sg:classifiers":[
        {
            "category":"Professional",
            "subcategory":"Management & Consulting",
            "type":"Services"
        }
    ],
    "sg:phone":"+1 614 221 1474",
    "sg:postcode":"43215",
    "sg:province":"OH",
    "sg:tags":[
        "consultant"
    ],
    "wof:name":"Decision Support Svc",
    "wof:placetype":"venue"
},
  "geometry": {"coordinates":[-83.001219,39.975803],"type":"Point"}
}