{
  "type": "Feature",
  "properties": {
    "iso:country":"US",
    "sg:address":"210 East Ave",
    "sg:city":"Irondale",
    "sg:classifiers":[
        {
            "category":"Government",
            "subcategory":"Post Office",
            "type":"Public Place"
        }
    ],
    "sg:phone":"+1 330 532 4834",
    "sg:postcode":"43932",
    "sg:province":"OH",
    "wof:name":"US Post Office",
    "wof:placetype":"venue"
},
  "geometry": {"coordinates":[-80.727438,40.567494],"type":"Point"}
}