{
  "type": "Feature",
  "properties": {
    "addr:full":"8512 Market Place Ln Cincinnati OH 45242",
    "addr:housenumber":"8512",
    "addr:postcode":"45242",
    "addr:street":"Market Place Ln",
    "iso:country":"US",
    "sg:address":"8512 Market Place Ln",
    "sg:city":"Cincinnati",
    "sg:classifiers":[
        {
            "category":"Bars & Pubs",
            "type":"Food & Drink"
        }
    ],
    "sg:phone":"+1 513 793 1980",
    "sg:postcode":"45242",
    "sg:province":"OH",
    "sg:tags":[
        "brew"
    ],
    "wof:name":"Sneaky Pete's Montgomery",
    "wof:placetype":"venue"
},
  "geometry": {"coordinates":[-84.34817099999999,39.23742],"type":"Point"}
}