{
  "type": "Feature",
  "properties": {
    "addr:full": "70 N Main St Poland OH 44514",
    "addr:housenumber": "70",
    "addr:postcode": "44514",
    "addr:street": "N Main St",
    "iso:country": "US",
    "sg:address": "70 N Main St",
    "sg:city": "Poland",
    "sg:classifiers": [
      {
        "category": "Personal",
        "subcategory": "Beauty Salon",
        "type": "Services"
      }
    ],
    "sg:phone": "+1 330 757 0516",
    "sg:postcode": "44514",
    "sg:province": "OH",
    "wof:name": "Hair Designers Unlimited",
    "wof:placetype": "venue"
  },
  "geometry": {"coordinates":[-80.61548,41.025627],"type":"Point"}
}
