{
  "type": "Feature",
  "properties": {
    "addr:full":"571 E 185th St Cleveland OH 44119",
    "addr:housenumber":"571",
    "addr:postcode":"44119",
    "addr:street":"E 185Th St",
    "iso:country":"US",
    "sg:address":"571 E 185th St",
    "sg:city":"Cleveland",
    "sg:classifiers":[
        {
            "category":"Professional",
            "subcategory":"Lawyer & Legal Services",
            "type":"Services"
        }
    ],
    "sg:phone":"+1 216 481 4495",
    "sg:postcode":"44119",
    "sg:province":"OH",
    "sg:tags":[
        "attorney"
    ],
    "wof:name":"Jeffrey M Mc Gaffick",
    "wof:placetype":"venue"
},
  "geometry": {"coordinates":[-81.54983,41.591733],"type":"Point"}
}