{
  "type": "Feature",
  "properties": {
    "addr:full": "11335 Putnam Rd Englewood OH 45322",
    "addr:housenumber": "11335",
    "addr:postcode": "45322",
    "addr:street": "Putnam Rd",
    "iso:country": "US",
    "sg:address": "11335 Putnam Rd",
    "sg:city": "Englewood",
    "sg:classifiers": [
      {
        "category": "Restaurant",
        "type": "Food \u0026 Drink"
      }
    ],
    "sg:phone": "+1 937 884 7222",
    "sg:postcode": "45322",
    "sg:province": "OH",
    "wof:name": "Pizza Dairy Lane",
    "wof:placetype": "venue"
  },
  "geometry": {"coordinates":[-84.350655,39.910752],"type":"Point"}
}
