{
  "type": "Feature",
  "properties": {
    "iso:country":"US",
    "sg:address":"11335 Putnam Rd",
    "sg:city":"Englewood",
    "sg:classifiers":[
        {
            "category":"Restaurant",
            "type":"Food & Drink"
        }
    ],
    "sg:phone":"+1 937 884 7222",
    "sg:postcode":"45322",
    "sg:province":"OH",
    "wof:name":"Pizza Dairy Lane",
    "wof:placetype":"venue"
},
  "geometry": {"coordinates":[-84.350655,39.910752],"type":"Point"}
}