{
  "type": "Feature",
  "properties": {
    "addr:full": "6903 York Rd Cleveland OH 44130",
    "addr:housenumber": "6903",
    "addr:postcode": "44130",
    "addr:street": "York Rd",
    "iso:country": "US",
    "sg:address": "6903 York Rd",
    "sg:city": "Cleveland",
    "sg:classifiers": [
      {
        "category": "Restaurant",
        "type": "Food \u0026 Drink"
      }
    ],
    "sg:phone": "+1 440 845 7493",
    "sg:postcode": "44130",
    "sg:province": "OH",
    "sg:tags": [
      "eating"
    ],
    "wof:name": "Fast Trax Classic Pizza",
    "wof:placetype": "venue"
  },
  "geometry": {"coordinates":[-81.759572,41.375379],"type":"Point"}
}
