{
  "type": "Feature",
  "properties": {
    "iso:country":"US",
    "sg:address":"4435 Glenhaven Rd",
    "sg:city":"Cincinnati",
    "sg:classifiers":[
        {
            "category":"Real Estate",
            "subcategory":"Real Estate Operator",
            "type":"Services"
        }
    ],
    "sg:phone":"+1 513 251 5990",
    "sg:postcode":"45238",
    "sg:province":"OH",
    "sg:tags":[
        "apartment"
    ],
    "wof:name":"Delshire Apartments",
    "wof:placetype":"venue"
},
  "geometry": {"coordinates":[-84.59957799999999,39.089343],"type":"Point"}
}