{
  "type": "Feature",
  "properties": {
    "addr:full": "14449 Old State Rd Middlefield OH 44062",
    "addr:housenumber": "14449",
    "addr:postcode": "44062",
    "addr:street": "Old State Rd",
    "iso:country": "US",
    "sg:address": "14449 Old State Rd",
    "sg:city": "Middlefield",
    "sg:classifiers": [
      {
        "category": "Retail",
        "subcategory": "Repair Shop",
        "type": "Services"
      }
    ],
    "sg:phone": "+1 440 632 9626",
    "sg:postcode": "44062",
    "sg:province": "OH",
    "sg:tags": [
      "ironwork"
    ],
    "wof:name": "Middlefields Iron Works \u0026 Antq",
    "wof:placetype": "venue"
  },
  "geometry": {"coordinates":[-81.078522,41.478365],"type":"Point"}
}
