{
  "type": "Feature",
  "properties": {
    "iso:country":"US",
    "sg:address":"14449 Old State Rd",
    "sg:city":"Middlefield",
    "sg:classifiers":[
        {
            "category":"Retail",
            "subcategory":"Repair Shop",
            "type":"Services"
        }
    ],
    "sg:phone":"+1 440 632 9626",
    "sg:postcode":"44062",
    "sg:province":"OH",
    "sg:tags":[
        "ironwork"
    ],
    "wof:name":"Middlefields Iron Works & Antq",
    "wof:placetype":"venue"
},
  "geometry": {"coordinates":[-81.07852200000001,41.478365],"type":"Point"}
}