{
  "type": "Feature",
  "properties": {
    "iso:country":"US",
    "sg:address":"929 Elaine Rd",
    "sg:city":"Columbus",
    "sg:classifiers":[
        {
            "category":"Shopping",
            "type":"Retail Goods"
        },
        {
            "category":"Retail",
            "subcategory":"Animal Services",
            "type":"Services"
        }
    ],
    "sg:phone":"+1 614 235 7249",
    "sg:postcode":"43227",
    "sg:province":"OH",
    "sg:tags":[
        "pet",
        "grooming",
        "washing",
        "merchandise"
    ],
    "wof:name":"Tattletail Tail'Ers",
    "wof:placetype":"venue"
},
  "geometry": {"coordinates":[-82.885503,39.954611],"type":"Point"}
}