{
  "type": "Feature",
  "properties": {
    "addr:full":"1494 E Aurora Rd Macedonia OH 44056",
    "addr:housenumber":"1494",
    "addr:postcode":"44056",
    "addr:street":"E Aurora Rd",
    "iso:country":"US",
    "sg:address":"1494 E Aurora Rd",
    "sg:city":"Macedonia",
    "sg:classifiers":[
        {
            "category":"Professional",
            "subcategory":"Management & Consulting",
            "type":"Services"
        }
    ],
    "sg:phone":"+1 330 468 5005",
    "sg:postcode":"44056",
    "sg:province":"OH",
    "sg:tags":[
        "consultant",
        "energy",
        "conservation"
    ],
    "wof:name":"Macedonia Community Health Ctr",
    "wof:placetype":"venue"
},
  "geometry": {"coordinates":[-81.485891,41.311298],"type":"Point"}
}