{
  "type": "Feature",
  "properties": {
    "iso:country":"US",
    "sg:address":"5709 Chevrolet Blvd",
    "sg:city":"Cleveland",
    "sg:classifiers":[
        {
            "category":"Sports & Exercise",
            "subcategory":"Bowling",
            "type":"Entertainment"
        }
    ],
    "sg:phone":"+1 440 842 8407",
    "sg:postcode":"44130",
    "sg:province":"OH",
    "sg:tags":[
        "center"
    ],
    "wof:name":"Cleveland Women's Bowling Assn",
    "wof:placetype":"venue"
},
  "geometry": {"coordinates":[-81.76885,41.408482],"type":"Point"}
}