{
  "type": "Feature",
  "properties": {
    "addr:full": "13571 Spring St Burton OH 44021",
    "addr:housenumber": "13571",
    "addr:postcode": "44021",
    "addr:street": "Spring St",
    "iso:country": "US",
    "sg:address": "13571 Spring St",
    "sg:city": "Burton",
    "sg:classifiers": [
      {
        "category": "Local Transit",
        "type": "Transportation"
      }
    ],
    "sg:phone": "+1 440 834 1020",
    "sg:postcode": "44021",
    "sg:province": "OH",
    "sg:tags": [
      "suburban"
    ],
    "wof:name": "First Transit Inc",
    "wof:placetype": "venue"
  },
  "geometry": {"coordinates":[-81.149825,41.472581],"type":"Point"}
}
