{
  "type": "Feature",
  "properties": {
    "addr:full":"149 W Main St Ashland OH 44805",
    "addr:housenumber":"149",
    "addr:postcode":"44805",
    "addr:street":"W Main St",
    "iso:country":"US",
    "sg:address":"149 W Main St",
    "sg:city":"Ashland",
    "sg:classifiers":[
        {
            "category":"Home & Garden",
            "subcategory":"Home Furnishings",
            "type":"Retail Goods"
        }
    ],
    "sg:phone":"+1 419 281 2513",
    "sg:postcode":"44805",
    "sg:province":"OH",
    "sg:tags":[
        "fabric",
        "drapery"
    ],
    "wof:name":"Ludwig Fabrics",
    "wof:placetype":"venue"
},
  "geometry": {"coordinates":[-82.317182,40.868642],"type":"Point"}
}