{
  "type": "Feature",
  "properties": {
    "addr:full": "208 E State St Botkins OH 45306",
    "addr:housenumber": "208",
    "addr:postcode": "45306",
    "addr:street": "E State St",
    "iso:country": "US",
    "sg:address": "208 E State St",
    "sg:city": "Botkins",
    "sg:classifiers": [
      {
        "category": "Health Services",
        "subcategory": "Doctor",
        "type": "Services"
      }
    ],
    "sg:phone": "+1 937 693 8151",
    "sg:postcode": "45306",
    "sg:province": "OH",
    "sg:tags": [
      "dentist"
    ],
    "wof:name": "J R Frische DDS",
    "wof:placetype": "venue"
  },
  "geometry": {"coordinates":[-84.179887,40.467863],"type":"Point"}
}
