{
  "type": "Feature",
  "properties": {
    "iso:country":"US",
    "sg:address":"1082 E 98th St",
    "sg:city":"Cleveland",
    "sg:classifiers":[
        {
            "category":"Organizations",
            "subcategory":"Non-profit Organization",
            "type":"Services"
        }
    ],
    "sg:phone":"+1 216 451 4848",
    "sg:postcode":"44108",
    "sg:province":"OH",
    "sg:tags":[
        "faith",
        "based",
        "community",
        "dev"
    ],
    "wof:name":"City Community Dev Corp",
    "wof:placetype":"venue"
},
  "geometry": {"coordinates":[-81.622128,41.527952],"type":"Point"}
}