{
  "type": "Feature",
  "properties": {
    "addr:full": "13603 Rismiller Rd Rossburg OH 45362",
    "addr:housenumber": "13603",
    "addr:postcode": "45362",
    "addr:street": "Rismiller Rd",
    "iso:country": "US",
    "sg:address": "13603 Rismiller Rd",
    "sg:city": "Rossburg",
    "sg:classifiers": [
      {
        "category": "Farming",
        "subcategory": "Farm",
        "type": "Manufacturing \u0026 Wholesale Goods"
      }
    ],
    "sg:phone": "+1 419 336 6621",
    "sg:postcode": "45362",
    "sg:province": "OH",
    "sg:tags": [
      "crop",
      "general"
    ],
    "wof:name": "James Rismiller",
    "wof:placetype": "venue"
  },
  "geometry": {"coordinates":[-84.55202,40.320184],"type":"Point"}
}
