{
  "type": "Feature",
  "properties": {
    "iso:country":"US",
    "sg:address":"13603 Rismiller Rd",
    "sg:city":"Rossburg",
    "sg:classifiers":[
        {
            "category":"Farming",
            "subcategory":"Farm",
            "type":"Manufacturing & Wholesale Goods"
        }
    ],
    "sg:phone":"+1 419 336 6621",
    "sg:postcode":"45362",
    "sg:province":"OH",
    "sg:tags":[
        "crop",
        "general"
    ],
    "wof:name":"James Rismiller",
    "wof:placetype":"venue"
},
  "geometry": {"coordinates":[-84.55202,40.320184],"type":"Point"}
}