{
  "type": "Feature",
  "properties": {
    "iso:country":"US",
    "sg:address":"2490 Lee Blvd",
    "sg:city":"Cleveland",
    "sg:classifiers":[
        {
            "category":"Health Services",
            "subcategory":"Clinic",
            "type":"Services"
        }
    ],
    "sg:phone":"+1 216 371 2146",
    "sg:postcode":"44118",
    "sg:province":"OH",
    "sg:tags":[
        "home"
    ],
    "wof:name":"Caring People",
    "wof:placetype":"venue"
},
  "geometry": {"coordinates":[-81.569422,41.516575],"type":"Point"}
}