{
  "type": "Feature",
  "properties": {
    "addr:full":"120 4th St Fort Jennings OH 45844",
    "addr:housenumber":"120",
    "addr:postcode":"45844",
    "addr:street":"4Th St",
    "iso:country":"US",
    "sg:address":"120 4th St",
    "sg:city":"Fort Jennings",
    "sg:phone":"+1 419 286 2364",
    "sg:postcode":"45844",
    "sg:province":"OH",
    "sg:tags":[
        "farm",
        "corn",
        "soybean"
    ],
    "wof:name":"Vincent Kohls",
    "wof:placetype":"venue"
},
  "geometry": {"coordinates":[-84.298164,40.906715],"type":"Point"}
}