{
  "type": "Feature",
  "properties": {
    "addr:full": "15098 Wilmington Dr Strongsville OH 44136",
    "addr:housenumber": "15098",
    "addr:postcode": "44136",
    "addr:street": "Wilmington Dr",
    "iso:country": "US",
    "sg:address": "15098 Wilmington Dr",
    "sg:city": "Strongsville",
    "sg:classifiers": [
      {
        "category": "Manufacturing",
        "subcategory": "Tools \u0026 Machinery",
        "type": "Manufacturing \u0026 Wholesale Goods"
      }
    ],
    "sg:phone": "+1 440 846 1059",
    "sg:postcode": "44136",
    "sg:province": "OH",
    "sg:tags": [
      "computer",
      "storage",
      "devices",
      "mfg"
    ],
    "wof:name": "Cebulon",
    "wof:placetype": "venue"
  },
  "geometry": {"coordinates":[-81.832232,41.306291],"type":"Point"}
}
