{
  "type": "Feature",
  "properties": {
    "iso:country":"US",
    "sg:address":"1224 Robinair Way",
    "sg:city":"Montpelier",
    "sg:classifiers":[
        {
            "category":"Professional",
            "subcategory":"Management & Consulting",
            "type":"Services"
        }
    ],
    "sg:phone":"+1 419 485 5055",
    "sg:postcode":"43543",
    "sg:province":"OH",
    "sg:tags":[
        "construction"
    ],
    "wof:name":"BWR Bowen Washington Regency",
    "wof:placetype":"venue"
},
  "geometry": {"coordinates":[-84.603419,41.572695],"type":"Point"}
}