{
  "type": "Feature",
  "properties": {
    "iso:country":"US",
    "sg:address":"1971 Madison Rd",
    "sg:city":"Cincinnati",
    "sg:classifiers":[
        {
            "category":"Personal",
            "subcategory":"Beauty Salon",
            "type":"Services"
        }
    ],
    "sg:phone":"+1 513 871 8888",
    "sg:postcode":"45208",
    "sg:province":"OH",
    "sg:tags":[
        "treatment",
        "skin"
    ],
    "wof:name":"Neva Rogers Skin Care",
    "wof:placetype":"venue"
},
  "geometry": {"coordinates":[-84.46332700000001,39.131844],"type":"Point"}
}