{
  "type": "Feature",
  "properties": {
    "addr:full": "1971 Madison Rd Cincinnati OH 45208",
    "addr:housenumber": "1971",
    "addr:postcode": "45208",
    "addr:street": "Madison Rd",
    "iso:country": "US",
    "sg:address": "1971 Madison Rd",
    "sg:city": "Cincinnati",
    "sg:classifiers": [
      {
        "category": "Personal",
        "subcategory": "Beauty Salon",
        "type": "Services"
      }
    ],
    "sg:phone": "+1 513 871 8888",
    "sg:postcode": "45208",
    "sg:province": "OH",
    "sg:tags": [
      "treatment",
      "skin"
    ],
    "wof:name": "Neva Rogers Skin Care",
    "wof:placetype": "venue"
  },
  "geometry": {"coordinates":[-84.463327,39.131844],"type":"Point"}
}
