{
  "type": "Feature",
  "properties": {
    "addr:full":"120 E South St Lebanon OH 45036",
    "addr:housenumber":"120 e",
    "addr:postcode":"45036",
    "addr:street":"South St",
    "iso:country":"US",
    "sg:address":"120 E South St",
    "sg:city":"Lebanon",
    "sg:classifiers":[
        {
            "category":"Professional",
            "subcategory":"Business Services",
            "type":"Services"
        }
    ],
    "sg:phone":"+1 513 933 9930",
    "sg:postcode":"45036",
    "sg:province":"OH",
    "sg:tags":[
        "embroidery"
    ],
    "wof:name":"East Main Productions Inc",
    "wof:placetype":"venue"
},
  "geometry": {"coordinates":[-84.20677499999999,39.43223],"type":"Point"}
}