{
  "type": "Feature",
  "properties": {
    "addr:full": "140 W Indianola Ave Youngstown OH 44507",
    "addr:housenumber": "140",
    "addr:postcode": "44507",
    "addr:street": "W Indianola Ave",
    "iso:country": "US",
    "sg:address": "140 W Indianola Ave",
    "sg:city": "Youngstown",
    "sg:classifiers": [
      {
        "category": "Home \u0026 Garden",
        "subcategory": "Building Materials",
        "type": "Retail Goods"
      }
    ],
    "sg:phone": "+1 330 788 5978",
    "sg:postcode": "44507",
    "sg:province": "OH",
    "sg:tags": [
      "installs",
      "garage",
      "door"
    ],
    "sg:website": "www.murdochdoor.com",
    "wof:name": "J W Murdoch \u0026 Sons Inc",
    "wof:placetype": "venue"
  },
  "geometry": {"coordinates":[-80.663395,41.072602],"type":"Point"}
}
