{
  "type": "Feature",
  "properties": {
    "iso:country":"US",
    "sg:address":"140 W Indianola Ave",
    "sg:city":"Youngstown",
    "sg:classifiers":[
        {
            "category":"Home & Garden",
            "subcategory":"Building Materials",
            "type":"Retail Goods"
        }
    ],
    "sg:phone":"+1 330 788 5978",
    "sg:postcode":"44507",
    "sg:province":"OH",
    "sg:tags":[
        "installs",
        "garage",
        "door"
    ],
    "sg:website":"www.murdochdoor.com",
    "wof:name":"J W Murdoch & Sons Inc",
    "wof:placetype":"venue"
},
  "geometry": {"coordinates":[-80.66339499999999,41.072602],"type":"Point"}
}