{
  "type": "Feature",
  "properties": {
    "addr:full":"24775 Aurora Rd Cleveland OH 44146",
    "addr:housenumber":"24775",
    "addr:postcode":"44146",
    "addr:street":"Aurora Rd",
    "iso:country":"US",
    "sg:address":"24775 Aurora Rd",
    "sg:city":"Cleveland",
    "sg:classifiers":[
        {
            "category":"Sports & Exercise",
            "subcategory":"Gym",
            "type":"Entertainment"
        }
    ],
    "sg:phone":"+1 440 439 5464",
    "sg:postcode":"44146",
    "sg:province":"OH",
    "sg:tags":[
        "club",
        "health",
        "studio",
        "gymnasium"
    ],
    "wof:name":"Kings Gym",
    "wof:placetype":"venue"
},
  "geometry": {"coordinates":[-81.50295,41.411336],"type":"Point"}
}