{
  "type": "Feature",
  "properties": {
    "addr:full": "1001 W High St Bryan OH 43506",
    "addr:housenumber": "1001",
    "addr:postcode": "43506",
    "addr:street": "W High St",
    "iso:country": "US",
    "sg:address": "1001 W High St",
    "sg:city": "Bryan",
    "sg:classifiers": [
      {
        "category": "Shopping",
        "subcategory": "Hobbies, Toys, \u0026 Games",
        "type": "Retail Goods"
      }
    ],
    "sg:phone": "+1 419 636 7072",
    "sg:postcode": "43506",
    "sg:province": "OH",
    "wof:name": "Northwst Hobbies",
    "wof:placetype": "venue"
  },
  "geometry": {"coordinates":[-84.566329,41.474567],"type":"Point"}
}
