{
  "type": "Feature",
  "properties": {
    "iso:country":"US",
    "sg:address":"4194 Coe Ave",
    "sg:city":"North Olmsted",
    "sg:classifiers":[
        {
            "category":"Building & Trades",
            "subcategory":"Construction",
            "type":"Services"
        }
    ],
    "sg:phone":"+1 440 777 3382",
    "sg:postcode":"44070",
    "sg:province":"OH",
    "sg:tags":[
        "concrete",
        "contractor"
    ],
    "wof:name":"Concrete Resurfacing",
    "wof:placetype":"venue"
},
  "geometry": {"coordinates":[-81.887821,41.42548],"type":"Point"}
}