{
  "type": "Feature",
  "properties": {
    "addr:full": "1524 Joyce Ave Columbus OH 43219",
    "addr:housenumber": "1524",
    "addr:postcode": "43219",
    "addr:street": "Joyce Ave",
    "iso:country": "US",
    "sg:address": "1524 Joyce Ave",
    "sg:city": "Columbus",
    "sg:classifiers": [
      {
        "category": "Freight",
        "type": "Transportation"
      },
      {
        "category": "Professional",
        "subcategory": "Business Services",
        "type": "Services"
      }
    ],
    "sg:phone": "+1 614 294 0377",
    "sg:postcode": "43219",
    "sg:province": "OH",
    "sg:tags": [
      "trucking"
    ],
    "wof:name": "Mc Lean's Hauling \u0026 Recycling",
    "wof:placetype": "venue"
  },
  "geometry": {"coordinates":[-82.965839,39.99637],"type":"Point"}
}
