{
  "type": "Feature",
  "properties": {
    "addr:full": "122 High St Wadsworth OH 44281",
    "addr:housenumber": "122",
    "addr:postcode": "44281",
    "addr:street": "High St",
    "iso:country": "US",
    "sg:address": "122 High St",
    "sg:city": "Wadsworth",
    "sg:classifiers": [
      {
        "category": "Home \u0026 Garden",
        "subcategory": "Hardware",
        "type": "Retail Goods"
      }
    ],
    "sg:phone": "+1 330 336 3535",
    "sg:postcode": "44281",
    "sg:province": "OH",
    "wof:name": "Holmesbrook Ace Hardware",
    "wof:placetype": "venue"
  },
  "geometry": {"coordinates":[-81.729768,41.026108],"type":"Point"}
}
