{
  "type": "Feature",
  "properties": {
    "addr:full":"1649 Morse Rd Columbus OH 43229",
    "addr:housenumber":"1649",
    "addr:postcode":"43229",
    "addr:street":"Morse Rd",
    "iso:country":"US",
    "sg:address":"1649 Morse Rd",
    "sg:city":"Columbus",
    "sg:classifiers":[
        {
            "category":"Retail",
            "subcategory":"Portrait Studio",
            "type":"Services"
        }
    ],
    "sg:phone":"+1 614 262 1600",
    "sg:postcode":"43229",
    "sg:province":"OH",
    "sg:tags":[
        "family"
    ],
    "wof:name":"Wal-Mart Portrait Studio",
    "wof:placetype":"venue"
},
  "geometry": {"coordinates":[-82.97716,40.060493],"type":"Point"}
}