{
  "type": "Feature",
  "properties": {
    "iso:country":"US",
    "sg:address":"29110 Anderson Rd",
    "sg:city":"Wickliffe",
    "sg:classifiers":[
        {
            "category":"Manufacturing",
            "subcategory":"Motor Vehicles & Parts",
            "type":"Manufacturing & Wholesale Goods"
        }
    ],
    "sg:phone":"+1 440 585 2200",
    "sg:postcode":"44092",
    "sg:province":"OH",
    "sg:tags":[
        "chrome",
        "mfg",
        "motorcycle",
        "accessory"
    ],
    "wof:name":"Custom Cycle Acc Mfg & Distrg",
    "wof:placetype":"venue"
},
  "geometry": {"coordinates":[-81.480372,41.605455],"type":"Point"}
}