{
  "type": "Feature",
  "properties": {
    "addr:full": "29110 Anderson Rd Wickliffe OH 44092",
    "addr:housenumber": "29110",
    "addr:postcode": "44092",
    "addr:street": "Anderson Rd",
    "iso:country": "US",
    "sg:address": "29110 Anderson Rd",
    "sg:city": "Wickliffe",
    "sg:classifiers": [
      {
        "category": "Manufacturing",
        "subcategory": "Motor Vehicles \u0026 Parts",
        "type": "Manufacturing \u0026 Wholesale Goods"
      }
    ],
    "sg:phone": "+1 440 585 2200",
    "sg:postcode": "44092",
    "sg:province": "OH",
    "sg:tags": [
      "chrome",
      "mfg",
      "motorcycle",
      "accessory"
    ],
    "wof:name": "Custom Cycle Acc Mfg \u0026 Distrg",
    "wof:placetype": "venue"
  },
  "geometry": {"coordinates":[-81.480372,41.605455],"type":"Point"}
}
