{
  "type": "Feature",
  "properties": {
    "addr:full":"100 Willow Brook Way S Delaware OH 43015",
    "addr:housenumber":"100",
    "addr:postcode":"43015",
    "addr:street":"Willow Brook Way S",
    "iso:country":"US",
    "sg:address":"100 Willow Brook Way S",
    "sg:city":"Delaware",
    "sg:classifiers":[
        {
            "category":"Social Services",
            "subcategory":"Adult Care",
            "type":"Services"
        }
    ],
    "sg:phone":"+1 740 369 0048",
    "sg:postcode":"43015",
    "sg:province":"OH",
    "sg:tags":[
        "residential"
    ],
    "sg:website":"www.willow-brook.org",
    "wof:name":"Centrum At Willow Brook",
    "wof:placetype":"venue"
},
  "geometry": {"coordinates":[-83.074151,40.271003],"type":"Point"}
}