{
  "type": "Feature",
  "properties": {
    "addr:full":"8360 Shadowpoint Ct Cincinnati OH 45242",
    "addr:postcode":"8360;45242",
    "addr:street":"Shadowpoint Ct",
    "iso:country":"US",
    "sg:address":"8360 Shadowpoint Ct",
    "sg:city":"Cincinnati",
    "sg:classifiers":[
        {
            "category":"Wholesale",
            "subcategory":"Machinery & Supplies",
            "type":"Manufacturing & Wholesale Goods"
        }
    ],
    "sg:phone":"+1 513 530 9972",
    "sg:postcode":"45242",
    "sg:province":"OH",
    "sg:tags":[
        "industrial"
    ],
    "wof:name":"MII International",
    "wof:placetype":"venue"
},
  "geometry": {"coordinates":[-84.335341,39.258011],"type":"Point"}
}