{
  "type": "Feature",
  "properties": {
    "addr:full":"5425 Southwyck Blvd Toledo OH 43614",
    "addr:housenumber":"5425",
    "addr:postcode":"43614",
    "addr:street":"Southwyck Blvd",
    "iso:country":"US",
    "sg:address":"5425 Southwyck Blvd",
    "sg:city":"Toledo",
    "sg:classifiers":[
        {
            "category":"Home & Garden",
            "subcategory":"Home Furnishings",
            "type":"Retail Goods"
        }
    ],
    "sg:phone":"+1 419 861 3086",
    "sg:postcode":"43614",
    "sg:province":"OH",
    "sg:tags":[
        "cutlery"
    ],
    "wof:name":"Cutco-Vector Marketing",
    "wof:placetype":"venue"
},
  "geometry": {"coordinates":[-83.66998700000001,41.604887],"type":"Point"}
}