{
  "type": "Feature",
  "properties": {
    "addr:full": "4250 Dresden Rd Zanesville OH 43701",
    "addr:housenumber": "4250",
    "addr:postcode": "43701",
    "addr:street": "Dresden Rd",
    "iso:country": "US",
    "sg:address": "4250 Dresden Rd",
    "sg:city": "Zanesville",
    "sg:classifiers": [
      {
        "category": "Recreation",
        "type": "Entertainment"
      }
    ],
    "sg:phone": "+1 740 453 7190",
    "sg:postcode": "43701",
    "sg:province": "OH",
    "wof:name": "All Seasons Golf Center Inc",
    "wof:placetype": "venue"
  },
  "geometry": {"coordinates":[-82.00496,40.005789],"type":"Point"}
}
