{
  "type": "Feature",
  "properties": {
    "addr:full":"500 S 4th St Columbus OH 43206",
    "addr:housenumber":"500",
    "addr:postcode":"43206",
    "addr:street":"S 4Th St",
    "iso:country":"US",
    "sg:address":"500 S 4th St",
    "sg:city":"Columbus",
    "sg:classifiers":[
        {
            "category":"Professional",
            "subcategory":"Lawyer & Legal Services",
            "type":"Services"
        }
    ],
    "sg:phone":"+1 614 228 3566",
    "sg:postcode":"43206",
    "sg:province":"OH",
    "sg:tags":[
        "attorney"
    ],
    "wof:name":"Stephanie L Gibson",
    "wof:placetype":"venue"
},
  "geometry": {"coordinates":[-82.99449199999999,39.951736],"type":"Point"}
}