{
  "type": "Feature",
  "properties": {
    "addr:full":"357 Washington St Chardon OH 44024",
    "addr:housenumber":"357",
    "addr:postcode":"44024",
    "addr:street":"Washington St",
    "iso:country":"US",
    "sg:address":"357 Washington St",
    "sg:city":"Chardon",
    "sg:classifiers":[
        {
            "category":"Manufacturing",
            "subcategory":"Tools & Machinery",
            "type":"Manufacturing & Wholesale Goods"
        }
    ],
    "sg:phone":"+1 440 285 9181",
    "sg:postcode":"44024",
    "sg:province":"OH",
    "sg:tags":[
        "machine",
        "access",
        "industrial",
        "mfg"
    ],
    "wof:name":"Unova Inc",
    "wof:placetype":"venue"
},
  "geometry": {"coordinates":[-81.20899,41.584373],"type":"Point"}
}