{
  "type": "Feature",
  "properties": {
    "addr:full": "5805 Hough Ave Cleveland OH 44103",
    "addr:housenumber": "5805",
    "addr:postcode": "44103",
    "addr:street": "Hough Ave",
    "iso:country": "US",
    "sg:address": "5805 Hough Ave",
    "sg:city": "Cleveland",
    "sg:classifiers": [
      {
        "category": "Manufacturing",
        "subcategory": "Metals",
        "type": "Manufacturing \u0026 Wholesale Goods"
      }
    ],
    "sg:phone": "+1 216 881 2211",
    "sg:postcode": "44103",
    "sg:province": "OH",
    "sg:tags": [
      "product",
      "fabricated",
      "mfg"
    ],
    "wof:name": "Action Burglar Bars",
    "wof:placetype": "venue"
  },
  "geometry": {"coordinates":[-81.650048,41.508514],"type":"Point"}
}
