{
  "type": "Feature",
  "properties": {
    "addr:full":"5611 Hudson Dr Hudson OH 44236",
    "addr:housenumber":"5611",
    "addr:postcode":"44236",
    "addr:street":"Hudson Dr",
    "iso:country":"US",
    "sg:address":"5611 Hudson Dr",
    "sg:city":"Hudson",
    "sg:classifiers":[
        {
            "category":"Utilities",
            "subcategory":"Mobile Phone",
            "type":"Services"
        }
    ],
    "sg:phone":"+1 330 342 8443",
    "sg:postcode":"44236",
    "sg:province":"OH",
    "sg:tags":[
        "telephone",
        "cellular"
    ],
    "wof:name":"Verizon Wireless",
    "wof:placetype":"venue"
},
  "geometry": {"coordinates":[-81.441379,41.21925],"type":"Point"}
}