{
  "type": "Feature",
  "properties": {
    "iso:country":"US",
    "sg:address":"13 Crawford St",
    "sg:city":"Middletown",
    "sg:classifiers":[
        {
            "category":"Manufacturing",
            "subcategory":"Printing",
            "type":"Manufacturing & Wholesale Goods"
        }
    ],
    "sg:phone":"+1 513 420 9466",
    "sg:postcode":"45044",
    "sg:province":"OH",
    "sg:tags":[
        "commercial"
    ],
    "wof:name":"Digital Visuals",
    "wof:placetype":"venue"
},
  "geometry": {"coordinates":[-84.391674,39.511831],"type":"Point"}
}