{
  "type": "Feature",
  "properties": {
    "iso:country":"US",
    "sg:address":"10570 Clay Pike Rd",
    "sg:city":"Pleasant City",
    "sg:classifiers":[
        {
            "category":"Autos & Motor Vehicles",
            "subcategory":"Motorcycle Sales",
            "type":"Retail Goods"
        }
    ],
    "sg:phone":"+1 740 685 3773",
    "sg:postcode":"43772",
    "sg:province":"OH",
    "sg:tags":[
        "scooter"
    ],
    "wof:name":"Sim's Cycle Inc",
    "wof:placetype":"venue"
},
  "geometry": {"coordinates":[-81.547179,39.923328],"type":"Point"}
}