{
  "type": "Feature",
  "properties": {
    "iso:country":"US",
    "sg:address":"4088 Anson Dr",
    "sg:city":"Hilliard",
    "sg:classifiers":[
        {
            "category":"Building & Trades",
            "subcategory":"Construction",
            "type":"Services"
        }
    ],
    "sg:phone":"+1 614 873 2563",
    "sg:postcode":"43026",
    "sg:province":"OH",
    "sg:tags":[
        "painter"
    ],
    "wof:name":"B King Assoc Inc",
    "wof:placetype":"venue"
},
  "geometry": {"coordinates":[-83.127864,40.041839],"type":"Point"}
}