{
  "type": "Feature",
  "properties": {
    "iso:country":"US",
    "sg:address":"6495 Equestrian Trl",
    "sg:city":"Medina",
    "sg:classifiers":[
        {
            "category":"Professional",
            "subcategory":"Lawyer & Legal Services",
            "type":"Services"
        }
    ],
    "sg:phone":"+1 330 239 4290",
    "sg:postcode":"44256",
    "sg:province":"OH",
    "wof:name":"Zickefoose Legal Nurse Cnsltng",
    "wof:placetype":"venue"
},
  "geometry": {"coordinates":[-81.762199,41.099041],"type":"Point"}
}