{
  "type": "Feature",
  "properties": {
    "addr:full": "6495 Equestrian Trl Medina OH 44256",
    "addr:housenumber": "6495",
    "addr:postcode": "44256",
    "addr:street": "Equestrian Trl",
    "iso:country": "US",
    "sg:address": "6495 Equestrian Trl",
    "sg:city": "Medina",
    "sg:classifiers": [
      {
        "category": "Professional",
        "subcategory": "Lawyer \u0026 Legal Services",
        "type": "Services"
      }
    ],
    "sg:phone": "+1 330 239 4290",
    "sg:postcode": "44256",
    "sg:province": "OH",
    "wof:name": "Zickefoose Legal Nurse Cnsltng",
    "wof:placetype": "venue"
  },
  "geometry": {"coordinates":[-81.762199,41.099041],"type":"Point"}
}
