{
  "type": "Feature",
  "properties": {
    "iso:country":"US",
    "sg:address":"1301 Easton Rd",
    "sg:city":"Creston",
    "sg:classifiers":[
        {
            "category":"Professional",
            "type":"Services"
        }
    ],
    "sg:phone":"+1 330 435 4760",
    "sg:postcode":"44217",
    "sg:province":"OH",
    "wof:name":"Floyd I Bertschy",
    "wof:placetype":"venue"
},
  "geometry": {"coordinates":[-81.936137,40.944761],"type":"Point"}
}