{
  "type": "Feature",
  "properties": {
    "addr:full": "2806 State Rte 307 Austinburg OH 44010",
    "addr:housenumber": "2806",
    "addr:postcode": "44010",
    "addr:street": "State Rte 307",
    "iso:country": "US",
    "sg:address": "2806 State Rte 307",
    "sg:city": "Austinburg",
    "sg:classifiers": [
      {
        "category": "Manufacturing",
        "subcategory": "Printing",
        "type": "Manufacturing \u0026 Wholesale Goods"
      }
    ],
    "sg:phone": "+1 440 275 1133",
    "sg:postcode": "44010",
    "sg:province": "OH",
    "sg:tags": [
      "screen"
    ],
    "wof:name": "Ringer Screen Print Inc",
    "wof:placetype": "venue"
  },
  "geometry": {"coordinates":[-80.853733,41.771893],"type":"Point"}
}
