{
  "type": "Feature",
  "properties": {
    "iso:country":"US",
    "sg:address":"7642 Lower Miamisburg Rd",
    "sg:city":"Miamisburg",
    "sg:classifiers":[
        {
            "category":"Farming",
            "subcategory":"Livestock Farm",
            "type":"Manufacturing & Wholesale Goods"
        }
    ],
    "sg:phone":"+1 937 866 1225",
    "sg:postcode":"45342",
    "sg:province":"OH",
    "sg:tags":[
        "beef",
        "feedlot",
        "cattle"
    ],
    "wof:name":"Lonesome Acres",
    "wof:placetype":"venue"
},
  "geometry": {"coordinates":[-84.32684399999999,39.628694],"type":"Point"}
}