{
  "type": "Feature",
  "properties": {
    "addr:full":"4192 W 49th St Cleveland OH 44144",
    "addr:housenumber":"4192",
    "addr:postcode":"44144",
    "addr:street":"W 49Th St",
    "iso:country":"US",
    "sg:address":"4192 W 49th St",
    "sg:city":"Cleveland",
    "sg:classifiers":[
        {
            "category":"Wholesale",
            "subcategory":"Fruits & Vegetables",
            "type":"Manufacturing & Wholesale Goods"
        }
    ],
    "sg:phone":"+1 216 661 1523",
    "sg:postcode":"44144",
    "sg:province":"OH",
    "wof:name":"Golden Harvest Produce",
    "wof:placetype":"venue"
},
  "geometry": {"coordinates":[-81.720254,41.440714],"type":"Point"}
}