{
  "type": "Feature",
  "properties": {
    "addr:full": "2800 Wayne Ave Dayton OH 45420",
    "addr:housenumber": "2800",
    "addr:postcode": "45420",
    "addr:street": "Wayne Ave",
    "iso:country": "US",
    "sg:address": "2800 Wayne Ave",
    "sg:city": "Dayton",
    "sg:classifiers": [
      {
        "category": "Restaurant",
        "type": "Food \u0026 Drink"
      }
    ],
    "sg:menulink": "http://www.allmenus.com/oh/dayton/69697-donatos-pizza/menu/",
    "sg:phone": "+1 937 254 8800",
    "sg:postcode": "45420",
    "sg:province": "OH",
    "sg:tags": [
      "sandwich",
      "salad",
      "soup",
      "american",
      "wrap",
      "pizza"
    ],
    "wof:name": "Donatos Pizza",
    "wof:placetype": "venue"
  },
  "geometry": {"coordinates":[-84.153889,39.739402],"type":"Point"}
}
