{
  "type": "Feature",
  "properties": {
    "iso:country":"US",
    "sg:address":"314 W High St",
    "sg:city":"St Marys",
    "sg:classifiers":[
        {
            "category":"Retail",
            "subcategory":"Funeral Services",
            "type":"Services"
        }
    ],
    "sg:phone":"+1 419 394 2301",
    "sg:postcode":"45885",
    "sg:province":"OH",
    "sg:tags":[
        "director"
    ],
    "wof:name":"Miller-Long & Folk",
    "wof:placetype":"venue"
},
  "geometry": {"coordinates":[-84.391131,40.543247],"type":"Point"}
}