{
  "type": "Feature",
  "properties": {
    "iso:country":"US",
    "sg:address":"831 McKaig Rd",
    "sg:city":"Troy",
    "sg:classifiers":[
        {
            "category":"Organizations",
            "subcategory":"Religious Organization",
            "type":"Services"
        }
    ],
    "sg:phone":"+1 937 335 8814",
    "sg:postcode":"45373",
    "sg:province":"OH",
    "sg:tags":[
        "church"
    ],
    "wof:name":"Richards Chapel United Mthdst",
    "wof:placetype":"venue"
},
  "geometry": {"coordinates":[-84.213795,40.039986],"type":"Point"}
}