{
  "type": "Feature",
  "properties": {
    "addr:full": "1346 Easthill St SE North Canton OH 44720",
    "addr:housenumber": "1346",
    "addr:postcode": "44720",
    "addr:street": "Easthill St Se",
    "iso:country": "US",
    "sg:address": "1346 Easthill St SE",
    "sg:city": "North Canton",
    "sg:classifiers": [
      {
        "category": "Travel",
        "subcategory": "Hotels \u0026 Motels",
        "type": "Entertainment"
      }
    ],
    "sg:phone": "+1 330 966 2222",
    "sg:postcode": "44720",
    "sg:province": "OH",
    "sg:tags": [
      "breakfast",
      "accommodation",
      "bed"
    ],
    "wof:name": "Fieldcrest",
    "wof:placetype": "venue"
  },
  "geometry": {"coordinates":[-81.381907,40.860528],"type":"Point"}
}
