{
  "type": "Feature",
  "properties": {
    "iso:country":"US",
    "sg:address":"1346 Easthill St SE",
    "sg:city":"North Canton",
    "sg:classifiers":[
        {
            "category":"Travel",
            "subcategory":"Hotels & Motels",
            "type":"Entertainment"
        }
    ],
    "sg:phone":"+1 330 966 2222",
    "sg:postcode":"44720",
    "sg:province":"OH",
    "sg:tags":[
        "breakfast",
        "accommodation",
        "bed"
    ],
    "wof:name":"Fieldcrest",
    "wof:placetype":"venue"
},
  "geometry": {"coordinates":[-81.381907,40.860528],"type":"Point"}
}