{
  "type": "Feature",
  "properties": {
    "addr:full":"2813 W Poplar Ridge Rd Malta OH 43758",
    "addr:housenumber":"2813",
    "addr:postcode":"43758",
    "addr:street":"W Poplar Ridge Rd",
    "iso:country":"US",
    "sg:address":"2813 W Poplar Ridge Rd",
    "sg:city":"Malta",
    "sg:classifiers":[
        {
            "category":"Building & Trades",
            "subcategory":"Plumbing",
            "type":"Services"
        }
    ],
    "sg:phone":"+1 740 962 5887",
    "sg:postcode":"43758",
    "sg:province":"OH",
    "sg:tags":[
        "contractor"
    ],
    "wof:name":"T W Spears Plumbing",
    "wof:placetype":"venue"
},
  "geometry": {"coordinates":[-81.877229,39.66388],"type":"Point"}
}