{
  "type": "Feature",
  "properties": {
    "iso:country":"US",
    "sg:address":"21380 Lorain Rd",
    "sg:city":"Cleveland",
    "sg:classifiers":[
        {
            "category":"Real Estate",
            "subcategory":"Real Estate Services",
            "type":"Services"
        }
    ],
    "sg:phone":"+1 216 228 9441",
    "sg:postcode":"44126",
    "sg:province":"OH",
    "sg:tags":[
        "company",
        "title"
    ],
    "wof:name":"Juventus LLC",
    "wof:placetype":"venue"
},
  "geometry": {"coordinates":[-81.855788,41.44541],"type":"Point"}
}