{
  "type": "Feature",
  "properties": {
    "iso:country":"US",
    "sg:address":"812 E Aurora Rd",
    "sg:city":"Macedonia",
    "sg:classifiers":[
        {
            "category":"Government",
            "subcategory":"Post Office",
            "type":"Public Place"
        }
    ],
    "sg:phone":"+1 330 467 8446",
    "sg:postcode":"44056",
    "sg:province":"OH",
    "sg:tags":[
        "postal",
        "us"
    ],
    "wof:name":"United States Postal Service",
    "wof:placetype":"venue"
},
  "geometry": {"coordinates":[-81.51034300000001,41.313774],"type":"Point"}
}