{
  "type": "Feature",
  "properties": {
    "addr:full": "1106 Exchange Rd S New London OH 44851",
    "addr:housenumber": "1106",
    "addr:postcode": "44851",
    "addr:street": "Exchange Rd",
    "iso:country": "US",
    "sg:address": "1106 Exchange Rd S",
    "sg:city": "New London",
    "sg:phone": "+1 419 929 8002",
    "sg:postcode": "44851",
    "sg:province": "OH",
    "sg:tags": [
      "farm",
      "corn",
      "soybean"
    ],
    "wof:name": "Ganz Farms",
    "wof:placetype": "venue"
  },
  "geometry": {"coordinates":[-82.462601,41.105713],"type":"Point"}
}
