{
  "type": "Feature",
  "properties": {
    "addr:full":"33 W 65th St Cincinnati OH 45216",
    "addr:housenumber":"33",
    "addr:postcode":"45216",
    "addr:street":"W 65Th St",
    "iso:country":"US",
    "sg:address":"33 W 65th St",
    "sg:city":"Cincinnati",
    "sg:classifiers":[
        {
            "category":"Place Of Worship",
            "subcategory":"Church",
            "type":"Public Place"
        },
        {
            "category":"Place Of Worship",
            "type":"Public Place"
        }
    ],
    "sg:phone":"+1 513 242 2720",
    "sg:postcode":"45216",
    "sg:province":"OH",
    "sg:tags":[
        "nazarene",
        "churches-church",
        "churches-nazarene"
    ],
    "wof:name":"Carthage Church Of Nazarene",
    "wof:placetype":"venue"
},
  "geometry": {"coordinates":[-84.486239,39.189537],"type":"Point"}
}