{
  "type": "Feature",
  "properties": {
    "iso:country":"US",
    "sg:address":"2979 Park Ave W",
    "sg:city":"Mansfield",
    "sg:classifiers":[
        {
            "category":"Manufacturing",
            "subcategory":"Glass & Minerals",
            "type":"Manufacturing & Wholesale Goods"
        },
        {
            "category":"Mining & Drilling",
            "type":"Manufacturing & Wholesale Goods"
        }
    ],
    "sg:phone":"+1 419 529 6000",
    "sg:postcode":"44906",
    "sg:province":"OH",
    "sg:tags":[
        "stone",
        "cutting",
        "finishing"
    ],
    "wof:name":"Richland Cut Stone",
    "wof:placetype":"venue"
},
  "geometry": {"coordinates":[-82.623566,40.760055],"type":"Point"}
}