{
  "type": "Feature",
  "properties": {
    "addr:full": "2979 Park Ave W Mansfield OH 44906",
    "addr:housenumber": "2979",
    "addr:postcode": "44906",
    "addr:street": "Park Ave W",
    "iso:country": "US",
    "sg:address": "2979 Park Ave W",
    "sg:city": "Mansfield",
    "sg:classifiers": [
      {
        "category": "Manufacturing",
        "subcategory": "Glass \u0026 Minerals",
        "type": "Manufacturing \u0026 Wholesale Goods"
      },
      {
        "category": "Mining \u0026 Drilling",
        "type": "Manufacturing \u0026 Wholesale Goods"
      }
    ],
    "sg:phone": "+1 419 529 6000",
    "sg:postcode": "44906",
    "sg:province": "OH",
    "sg:tags": [
      "stone",
      "cutting",
      "finishing"
    ],
    "wof:name": "Richland Cut Stone",
    "wof:placetype": "venue"
  },
  "geometry": {"coordinates":[-82.623566,40.760055],"type":"Point"}
}
