{
  "type": "Feature",
  "properties": {
    "addr:full": "318 N 2nd Ave Middleport OH 45760",
    "addr:housenumber": "318",
    "addr:postcode": "45760",
    "addr:street": "N 2Nd Ave",
    "iso:country": "US",
    "sg:address": "318 N 2nd Ave",
    "sg:city": "Middleport",
    "sg:classifiers": [
      {
        "category": "Personal",
        "subcategory": "Beauty Salon",
        "type": "Services"
      }
    ],
    "sg:phone": "+1 740 992 3667",
    "sg:postcode": "45760",
    "sg:province": "OH",
    "wof:name": "Classic Cuts Hair Salon",
    "wof:placetype": "venue"
  },
  "geometry": {"coordinates":[-82.047305,39.004698],"type":"Point"}
}
