{
  "type": "Feature",
  "properties": {
    "addr:full": "3575 Maple Ave Zanesville OH 43701",
    "addr:housenumber": "3575",
    "addr:postcode": "43701",
    "addr:street": "Maple Ave",
    "iso:country": "US",
    "sg:address": "3575 Maple Ave",
    "sg:city": "Zanesville",
    "sg:classifiers": [
      {
        "category": "Personal",
        "subcategory": "Beauty Salon",
        "type": "Services"
      }
    ],
    "sg:phone": "+1 740 450 0045",
    "sg:postcode": "43701",
    "sg:province": "OH",
    "sg:tags": [
      "manicuring"
    ],
    "wof:name": "Nails 3000",
    "wof:placetype": "venue"
  },
  "geometry": {"coordinates":[-82.022252,39.986451],"type":"Point"}
}
