{
  "type": "Feature",
  "properties": {
    "addr:full":"3659 Green Rd Cleveland OH 44122",
    "addr:housenumber":"3659",
    "addr:postcode":"44122",
    "addr:street":"Green Rd",
    "iso:country":"US",
    "sg:address":"3659 Green Rd",
    "sg:city":"Cleveland",
    "sg:classifiers":[
        {
            "category":"Health Services",
            "subcategory":"Hospital",
            "type":"Services"
        }
    ],
    "sg:phone":"+1 216 595 0440",
    "sg:postcode":"44122",
    "sg:province":"OH",
    "sg:tags":[
        "mental"
    ],
    "wof:name":"Francoise Adan",
    "wof:placetype":"venue"
},
  "geometry": {"coordinates":[-81.51692199999999,41.463399],"type":"Point"}
}