{
  "type": "Feature",
  "properties": {
    "addr:full": "947 E Kensington Ln Streetsboro OH 44241",
    "addr:housenumber": "947",
    "addr:postcode": "44241",
    "addr:street": "E Kensington Ln",
    "iso:country": "US",
    "sg:address": "947 E Kensington Ln",
    "sg:city": "Streetsboro",
    "sg:classifiers": [
      {
        "category": "Utilities",
        "subcategory": "Telephone",
        "type": "Services"
      }
    ],
    "sg:phone": "+1 330 655 2803",
    "sg:postcode": "44241",
    "sg:province": "OH",
    "sg:tags": [
      "web",
      "hosting"
    ],
    "wof:name": "Insystel Inc",
    "wof:placetype": "venue"
  },
  "geometry": {"coordinates":[-81.358751,41.263002],"type":"Point"}
}
