{
  "type": "Feature",
  "properties": {
    "addr:full":"771 S 30th St Heath OH 43056",
    "addr:housenumber":"771",
    "addr:postcode":"43056",
    "addr:street":"S 30Th St",
    "iso:country":"US",
    "sg:address":"771 S 30th St",
    "sg:city":"Heath",
    "sg:classifiers":[
        {
            "category":"Wholesale",
            "subcategory":"Electrical",
            "type":"Manufacturing & Wholesale Goods"
        }
    ],
    "sg:phone":"+1 740 522 3546",
    "sg:postcode":"43056",
    "sg:province":"OH",
    "sg:tags":[
        "operated",
        "telephone",
        "card"
    ],
    "wof:name":"Telaleasing Enterprises Inc",
    "wof:placetype":"venue"
},
  "geometry": {"coordinates":[-82.443395,40.030931],"type":"Point"}
}