{
  "type": "Feature",
  "properties": {
    "addr:full":"1946 Edgewood Dr Twinsburg OH 44087",
    "addr:housenumber":"1946",
    "addr:postcode":"44087",
    "addr:street":"Edgewood Dr",
    "iso:country":"US",
    "sg:address":"1946 Edgewood Dr",
    "sg:city":"Twinsburg",
    "sg:classifiers":[
        {
            "category":"Building & Trades",
            "subcategory":"Construction",
            "type":"Services"
        }
    ],
    "sg:phone":"+1 330 425 2061",
    "sg:postcode":"44087",
    "sg:province":"OH",
    "sg:tags":[
        "contractor"
    ],
    "wof:name":"Turle Construction Inc",
    "wof:placetype":"venue"
},
  "geometry": {"coordinates":[-81.458792,41.333524],"type":"Point"}
}