{
  "type": "Feature",
  "properties": {
    "addr:full":"2227 Summit St Portsmouth OH 45662",
    "addr:housenumber":"2227",
    "addr:postcode":"45662",
    "addr:street":"Summit St",
    "iso:country":"US",
    "sg:address":"2227 Summit St",
    "sg:city":"Portsmouth",
    "sg:classifiers":[
        {
            "category":"Social Services",
            "type":"Services"
        }
    ],
    "sg:phone":"+1 740 351 3539",
    "sg:postcode":"45662",
    "sg:province":"OH",
    "sg:tags":[
        "counseling"
    ],
    "wof:name":"Michael Hughes",
    "wof:placetype":"venue"
},
  "geometry": {"coordinates":[-82.97387500000001,38.748379],"type":"Point"}
}