{
  "type": "Feature",
  "properties": {
    "iso:country":"US",
    "sg:address":"1560 Sheridan Dr",
    "sg:city":"Lancaster",
    "sg:classifiers":[
        {
            "category":"Social Services",
            "type":"Services"
        }
    ],
    "sg:phone":"+1 740 654 0829",
    "sg:postcode":"43130",
    "sg:province":"OH",
    "sg:tags":[
        "organization",
        "welfare"
    ],
    "sg:website":"www.ohiopps.org",
    "wof:name":"Fairfield County Mental Health",
    "wof:placetype":"venue"
},
  "geometry": {"coordinates":[-82.569626,39.738419],"type":"Point"}
}