{
  "type": "Feature",
  "properties": {
    "iso:country":"US",
    "sg:address":"1841 Rosemont Rd",
    "sg:city":"Cleveland",
    "sg:classifiers":[
        {
            "category":"Professional",
            "type":"Services"
        }
    ],
    "sg:phone":"+1 216 451 3980",
    "sg:postcode":"44112",
    "sg:province":"OH",
    "wof:name":"Norma Channels",
    "wof:placetype":"venue"
},
  "geometry": {"coordinates":[-81.578858,41.530879],"type":"Point"}
}