{
  "type": "Feature",
  "properties": {
    "addr:full": "2187 Shadmill Ct Dublin OH 43016",
    "addr:housenumber": "2187",
    "addr:postcode": "43016",
    "addr:street": "Shadmill Ct",
    "iso:country": "US",
    "sg:address": "2187 Shadmill Ct",
    "sg:city": "Dublin",
    "sg:classifiers": [
      {
        "category": "Building \u0026 Trades",
        "subcategory": "Cleaning \u0026 Sanitation",
        "type": "Services"
      }
    ],
    "sg:phone": "+1 614 717 9505",
    "sg:postcode": "43016",
    "sg:province": "OH",
    "sg:tags": [
      "polishing",
      "waxing",
      "floor"
    ],
    "wof:name": "Trimax Cleaning Systems",
    "wof:placetype": "venue"
  },
  "geometry": {"coordinates":[-83.074901,40.121506],"type":"Point"}
}
