{
  "type": "Feature",
  "properties": {
    "iso:country":"US",
    "sg:address":"4401 Brandt Pike",
    "sg:city":"Dayton",
    "sg:classifiers":[
        {
            "category":"Manufacturing",
            "subcategory":"Signs",
            "type":"Manufacturing & Wholesale Goods"
        }
    ],
    "sg:phone":"+1 937 233 7395",
    "sg:postcode":"45424",
    "sg:province":"OH",
    "wof:name":"A-1 Sign Rental & Svc",
    "wof:placetype":"venue"
},
  "geometry": {"coordinates":[-84.12911,39.817425],"type":"Point"}
}