{
  "type": "Feature",
  "properties": {
    "addr:full": "4401 Brandt Pike Dayton OH 45424",
    "addr:housenumber": "4401",
    "addr:postcode": "45424",
    "addr:street": "Brandt Pike",
    "iso:country": "US",
    "sg:address": "4401 Brandt Pike",
    "sg:city": "Dayton",
    "sg:classifiers": [
      {
        "category": "Manufacturing",
        "subcategory": "Signs",
        "type": "Manufacturing \u0026 Wholesale Goods"
      }
    ],
    "sg:phone": "+1 937 233 7395",
    "sg:postcode": "45424",
    "sg:province": "OH",
    "wof:name": "A-1 Sign Rental \u0026 Svc",
    "wof:placetype": "venue"
  },
  "geometry": {"coordinates":[-84.12911,39.817425],"type":"Point"}
}
