{
  "type": "Feature",
  "properties": {
    "addr:full":"727 Wye Rd Akron OH 44333",
    "addr:housenumber":"727",
    "addr:postcode":"44333",
    "addr:street":"Wye Rd",
    "iso:country":"US",
    "sg:address":"727 Wye Rd",
    "sg:city":"Akron",
    "sg:classifiers":[
        {
            "category":"Building & Trades",
            "subcategory":"Landscaping Services",
            "type":"Services"
        }
    ],
    "sg:phone":"+1 330 666 1832",
    "sg:postcode":"44333",
    "sg:province":"OH",
    "wof:name":"Michigan Wildflower Devel",
    "wof:placetype":"venue"
},
  "geometry": {"coordinates":[-81.637351,41.156153],"type":"Point"}
}