{
  "type": "Feature",
  "properties": {
    "addr:full":"471 Arbor Cir Youngstown OH 44505",
    "addr:housenumber":"471",
    "addr:postcode":"44505",
    "addr:street":"Arbor Cir",
    "iso:country":"US",
    "sg:address":"471 Arbor Cir",
    "sg:city":"Youngstown",
    "sg:classifiers":[
        {
            "category":"Building & Trades",
            "subcategory":"Construction",
            "type":"Services"
        }
    ],
    "sg:phone":"+1 330 759 9634",
    "sg:postcode":"44505",
    "sg:province":"OH",
    "sg:tags":[
        "home",
        "remodeling",
        "family",
        "contractor"
    ],
    "wof:name":"Bi-Rite Home Improvement Inc",
    "wof:placetype":"venue"
},
  "geometry": {"coordinates":[-80.657185,41.14727],"type":"Point"}
}