{
  "type": "Feature",
  "properties": {
    "iso:country":"US",
    "sg:address":"4666 Larwell Dr",
    "sg:city":"Columbus",
    "sg:classifiers":[
        {
            "category":"Health Services",
            "subcategory":"Health Practitioner",
            "type":"Services"
        }
    ],
    "sg:phone":"+1 614 566 1120",
    "sg:postcode":"43220",
    "sg:province":"OH",
    "sg:tags":[
        "pathologist",
        "speech"
    ],
    "sg:website":"www.ohiohealth.com",
    "wof:name":"Ohiohealth Speech & Language",
    "wof:placetype":"venue"
},
  "geometry": {"coordinates":[-83.06211,40.055258],"type":"Point"}
}