{
  "type": "Feature",
  "properties": {
    "addr:full": "1251 Whipple Ave SW Canton OH 44710",
    "addr:housenumber": "1251",
    "addr:postcode": "44710",
    "addr:street": "Whipple Ave Sw",
    "iso:country": "US",
    "sg:address": "1251 Whipple Ave SW",
    "sg:city": "Canton",
    "sg:classifiers": [
      {
        "category": "Organizations",
        "subcategory": "Religious Organization",
        "type": "Services"
      }
    ],
    "sg:phone": "+1 330 477 9306",
    "sg:postcode": "44710",
    "sg:province": "OH",
    "sg:tags": [
      "clergy"
    ],
    "wof:name": "I Crites",
    "wof:placetype": "venue"
  },
  "geometry": {"coordinates":[-81.426788,40.789756],"type":"Point"}
}
