{
  "type": "Feature",
  "properties": {
    "iso:country":"US",
    "sg:address":"9735 Maumee Western Rd",
    "sg:city":"Monclova",
    "sg:classifiers":[
        {
            "category":"Shopping",
            "subcategory":"Used Merchandise",
            "type":"Retail Goods"
        }
    ],
    "sg:phone":"+1 419 861 0161",
    "sg:postcode":"43542",
    "sg:province":"OH",
    "sg:tags":[
        "record",
        "secondhand"
    ],
    "wof:name":"Dens 45",
    "wof:placetype":"venue"
},
  "geometry": {"coordinates":[-83.771566,41.573807],"type":"Point"}
}