{
  "type": "Feature",
  "properties": {
    "addr:full": "1730 Moxahala Ave Zanesville OH 43701",
    "addr:housenumber": "1730",
    "addr:postcode": "43701",
    "addr:street": "Moxahala Ave",
    "iso:country": "US",
    "sg:address": "1730 Moxahala Ave",
    "sg:city": "Zanesville",
    "sg:classifiers": [
      {
        "category": "Government",
        "subcategory": "Office",
        "type": "Public Place"
      }
    ],
    "sg:phone": "+1 740 455 0662",
    "sg:postcode": "43701",
    "sg:province": "OH",
    "sg:tags": [
      "village"
    ],
    "wof:name": "Zanesville Sewer Div",
    "wof:placetype": "venue"
  },
  "geometry": {"coordinates":[-82.005209,39.909672],"type":"Point"}
}
