{
  "type": "Feature",
  "properties": {
    "iso:country":"US",
    "sg:address":"1730 Moxahala Ave",
    "sg:city":"Zanesville",
    "sg:classifiers":[
        {
            "category":"Government",
            "subcategory":"Office",
            "type":"Public Place"
        }
    ],
    "sg:phone":"+1 740 455 0662",
    "sg:postcode":"43701",
    "sg:province":"OH",
    "sg:tags":[
        "village"
    ],
    "wof:name":"Zanesville Sewer Div",
    "wof:placetype":"venue"
},
  "geometry": {"coordinates":[-82.00520899999999,39.909672],"type":"Point"}
}