{
  "type": "Feature",
  "properties": {
    "addr:full":"2829 E Dublin Granville Rd Columbus OH 43231",
    "addr:housenumber":"2829",
    "addr:postcode":"43231",
    "addr:street":"E Dublin Granville Rd",
    "iso:country":"US",
    "sg:address":"2829 E Dublin Granville Rd",
    "sg:city":"Columbus",
    "sg:classifiers":[
        {
            "category":"Mining & Drilling",
            "type":"Manufacturing & Wholesale Goods"
        }
    ],
    "sg:phone":"+1 614 882 8533",
    "sg:postcode":"43231",
    "sg:province":"OH",
    "sg:tags":[
        "production",
        "gas",
        "producer",
        "oil"
    ],
    "wof:name":"Hopco Resources Inc",
    "wof:placetype":"venue"
},
  "geometry": {"coordinates":[-82.94212400000001,40.083106],"type":"Point"}
}