{
  "type": "Feature",
  "properties": {
    "addr:full": "4008 N Dixie Dr Dayton OH 45414",
    "addr:housenumber": "4008",
    "addr:postcode": "45414",
    "addr:street": "N Dixie Dr",
    "iso:country": "US",
    "sg:address": "4008 N Dixie Dr",
    "sg:city": "Dayton",
    "sg:classifiers": [
      {
        "category": "Building \u0026 Trades",
        "subcategory": "Electrical",
        "type": "Services"
      }
    ],
    "sg:phone": "+1 937 274 7351",
    "sg:postcode": "45414",
    "sg:province": "OH",
    "sg:tags": [
      "electric",
      "contractor"
    ],
    "wof:name": "Wells Electric Svc",
    "wof:placetype": "venue"
  },
  "geometry": {"coordinates":[-84.195203,39.803539],"type":"Point"}
}
