{
  "type": "Feature",
  "properties": {
    "iso:country":"US",
    "sg:address":"3000 Fortuna Dr",
    "sg:city":"Akron",
    "sg:classifiers":[
        {
            "category":"Retail",
            "subcategory":"Auto Rental",
            "type":"Services"
        }
    ],
    "sg:phone":"+1 330 644 0305",
    "sg:postcode":"44312",
    "sg:province":"OH",
    "sg:tags":[
        "renting",
        "truck",
        "leasing"
    ],
    "sg:website":"www.pensketruckleasing.com",
    "wof:name":"Penske Truck Rental",
    "wof:placetype":"venue"
},
  "geometry": {"coordinates":[-81.48898699999999,40.981246],"type":"Point"}
}