{
  "type": "Feature",
  "properties": {
    "addr:full": "11878 US Hwy 24 Cecil OH 45821",
    "addr:housenumber": "11878",
    "addr:postcode": "45821",
    "addr:street": "Us Hwy 24",
    "iso:country": "US",
    "sg:address": "11878 US Hwy 24",
    "sg:city": "Cecil",
    "sg:classifiers": [
      {
        "category": "Building \u0026 Trades",
        "subcategory": "Construction",
        "type": "Services"
      }
    ],
    "sg:phone": "+1 419 399 3804",
    "sg:postcode": "45821",
    "sg:province": "OH",
    "sg:tags": [
      "water",
      "well",
      "drilling"
    ],
    "wof:name": "Layman Well Drilling",
    "wof:placetype": "venue"
  },
  "geometry": {"coordinates":[-84.599774,41.230621],"type":"Point"}
}
