{
  "type": "Feature",
  "properties": {
    "iso:country":"US",
    "sg:address":"11878 US Hwy 24",
    "sg:city":"Cecil",
    "sg:classifiers":[
        {
            "category":"Building & Trades",
            "subcategory":"Construction",
            "type":"Services"
        }
    ],
    "sg:phone":"+1 419 399 3804",
    "sg:postcode":"45821",
    "sg:province":"OH",
    "sg:tags":[
        "water",
        "well",
        "drilling"
    ],
    "wof:name":"Layman Well Drilling",
    "wof:placetype":"venue"
},
  "geometry": {"coordinates":[-84.599774,41.230621],"type":"Point"}
}