{
  "type": "Feature",
  "properties": {
    "addr:full":"222 Central Ave Cincinnati OH 45202",
    "addr:housenumber":"222",
    "addr:postcode":"45202",
    "addr:street":"Central Ave",
    "iso:country":"US",
    "sg:address":"222 Central Ave",
    "sg:city":"Cincinnati",
    "sg:classifiers":[
        {
            "category":"Government",
            "subcategory":"Office",
            "type":"Public Place"
        }
    ],
    "sg:phone":"+1 513 546 2205",
    "sg:postcode":"45202",
    "sg:province":"OH",
    "sg:tags":[
        "social",
        "program",
        "administration",
        "manpower"
    ],
    "wof:name":"Department of Job & Fmly Svcs",
    "wof:placetype":"venue"
},
  "geometry": {"coordinates":[-84.518435,39.096941],"type":"Point"}
}