{
  "type": "Feature",
  "properties": {
    "iso:country":"US",
    "sg:address":"81 Miller Ave",
    "sg:city":"Archbold",
    "sg:classifiers":[
        {
            "category":"Banks & Credit Unions",
            "subcategory":"Financial Services",
            "type":"Services"
        }
    ],
    "sg:phone":"+1 419 784 0030",
    "sg:postcode":"43502",
    "sg:province":"OH",
    "sg:tags":[
        "company",
        "holding"
    ],
    "wof:name":"Eclipse Great Lakes",
    "wof:placetype":"venue"
},
  "geometry": {"coordinates":[-84.302299,41.500187],"type":"Point"}
}