{
  "type": "Feature",
  "properties": {
    "addr:full": "1143 Neil Ave Columbus OH 43201",
    "addr:housenumber": "1143",
    "addr:postcode": "43201",
    "addr:street": "Neil Ave",
    "iso:country": "US",
    "sg:address": "1143 Neil Ave",
    "sg:city": "Columbus",
    "sg:classifiers": [
      {
        "category": "Education",
        "subcategory": "Special Training",
        "type": "Public Place"
      }
    ],
    "sg:phone": "+1 614 291 0155",
    "sg:postcode": "43201",
    "sg:province": "OH",
    "sg:tags": [
      "self",
      "motivational",
      "improvement"
    ],
    "wof:name": "Barbara J Brahm",
    "wof:placetype": "venue"
  },
  "geometry": {"coordinates":[-83.012637,39.984421],"type":"Point"}
}
