{
  "type": "Feature",
  "properties": {
    "addr:full":"76 S Riverside Dr Batavia OH 45103",
    "addr:housenumber":"76",
    "addr:postcode":"45103",
    "addr:street":"S Riverside Dr",
    "iso:country":"US",
    "sg:address":"76 S Riverside Dr",
    "sg:city":"Batavia",
    "sg:classifiers":[
        {
            "category":"Government",
            "subcategory":"Office",
            "type":"Public Place"
        }
    ],
    "sg:phone":"+1 513 732 7243",
    "sg:postcode":"45103",
    "sg:province":"OH",
    "wof:name":"Clermont Cnty Marriage License",
    "wof:placetype":"venue"
},
  "geometry": {"coordinates":[-84.179305,39.077372],"type":"Point"}
}