{
  "type": "Feature",
  "properties": {
    "addr:full":"161 Rittman Ave Rittman OH 44270",
    "addr:housenumber":"161",
    "addr:postcode":"44270",
    "addr:street":"Rittman Ave",
    "iso:country":"US",
    "sg:address":"161 Rittman Ave",
    "sg:city":"Rittman",
    "sg:classifiers":[
        {
            "category":"Farming",
            "subcategory":"Orchard",
            "type":"Manufacturing & Wholesale Goods"
        }
    ],
    "sg:phone":"+1 330 925 6861",
    "sg:postcode":"44270",
    "sg:province":"OH",
    "sg:tags":[
        "fruit",
        "egg",
        "retail"
    ],
    "sg:website":"www.baumanorchards.com",
    "wof:name":"Bauman Orchards Inc",
    "wof:placetype":"venue"
},
  "geometry": {"coordinates":[-81.797132,40.971423],"type":"Point"}
}