{
  "type": "Feature",
  "properties": {
    "iso:country":"US",
    "sg:address":"643 Brickel Rd",
    "sg:city":"Jamestown",
    "sg:phone":"+1 937 675 6636",
    "sg:postcode":"45335",
    "sg:province":"OH",
    "sg:tags":[
        "farm",
        "soybean"
    ],
    "wof:name":"Gordie Dwyer",
    "wof:placetype":"venue"
},
  "geometry": {"coordinates":[-83.752543,39.691216],"type":"Point"}
}