{
  "type": "Feature",
  "properties": {
    "iso:country":"US",
    "sg:address":"987 E Ash St",
    "sg:city":"Piqua",
    "sg:classifiers":[
        {
            "category":"Restaurant",
            "type":"Food & Drink"
        }
    ],
    "sg:phone":"+1 937 778 1771",
    "sg:postcode":"45356",
    "sg:province":"OH",
    "wof:name":"China Clipper",
    "wof:placetype":"venue"
},
  "geometry": {"coordinates":[-84.218711,40.150976],"type":"Point"}
}