{
  "type": "Feature",
  "properties": {
    "addr:full":"1724 Lorain Blvd Elyria OH 44035",
    "addr:housenumber":"1724",
    "addr:postcode":"44035",
    "addr:street":"Lorain Blvd",
    "iso:country":"US",
    "sg:address":"1724 Lorain Blvd",
    "sg:city":"Elyria",
    "sg:classifiers":[
        {
            "category":"Travel",
            "subcategory":"Hotels & Motels",
            "type":"Entertainment"
        }
    ],
    "sg:phone":"+1 440 323 1515",
    "sg:postcode":"44035",
    "sg:province":"OH",
    "wof:name":"Howard Johnson",
    "wof:placetype":"venue"
},
  "geometry": {"coordinates":[-82.116709,41.391348],"type":"Point"}
}