{
  "type": "Feature",
  "properties": {
    "iso:country":"US",
    "sg:address":"107 E Main St",
    "sg:city":"Ashland",
    "sg:classifiers":[
        {
            "category":"Professional",
            "subcategory":"Lawyer & Legal Services",
            "type":"Services"
        }
    ],
    "sg:phone":"+1 419 289 0509",
    "sg:postcode":"44805",
    "sg:province":"OH",
    "sg:tags":[
        "attorney"
    ],
    "wof:name":"David A Samsel",
    "wof:placetype":"venue"
},
  "geometry": {"coordinates":[-82.314064,40.868581],"type":"Point"}
}