{
  "type": "Feature",
  "properties": {
    "iso:country":"US",
    "sg:address":"2008 State Rte 199",
    "sg:city":"Carey",
    "sg:classifiers":[
        {
            "category":"Bars & Pubs",
            "type":"Food & Drink"
        }
    ],
    "sg:phone":"+1 419 396 7738",
    "sg:postcode":"43316",
    "sg:province":"OH",
    "sg:tags":[
        "drinking"
    ],
    "wof:name":"Hillzys",
    "wof:placetype":"venue"
},
  "geometry": {"coordinates":[-83.382048,40.963504],"type":"Point"}
}