{
  "type": "Feature",
  "properties": {
    "addr:full": "2008 State Rte 199 Carey OH 43316",
    "addr:housenumber": "2008",
    "addr:postcode": "43316",
    "addr:street": "State Rte 199",
    "iso:country": "US",
    "sg:address": "2008 State Rte 199",
    "sg:city": "Carey",
    "sg:classifiers": [
      {
        "category": "Bars \u0026 Pubs",
        "type": "Food \u0026 Drink"
      }
    ],
    "sg:phone": "+1 419 396 7738",
    "sg:postcode": "43316",
    "sg:province": "OH",
    "sg:tags": [
      "drinking"
    ],
    "wof:name": "Hillzys",
    "wof:placetype": "venue"
  },
  "geometry": {"coordinates":[-83.382048,40.963504],"type":"Point"}
}
