{
  "type": "Feature",
  "properties": {
    "iso:country":"US",
    "sg:address":"1367 E Main St",
    "sg:city":"Columbus",
    "sg:classifiers":[
        {
            "category":"Real Estate",
            "subcategory":"Real Estate Agent",
            "type":"Services"
        }
    ],
    "sg:phone":"+1 614 252 1728",
    "sg:postcode":"43205",
    "sg:province":"OH",
    "sg:website":"www.newworld.com",
    "wof:name":"New World Real Estate",
    "wof:placetype":"venue"
},
  "geometry": {"coordinates":[-82.962315,39.957619],"type":"Point"}
}