{
  "type": "Feature",
  "properties": {
    "addr:full": "14745 State Rte 93 S Logan OH 43138",
    "addr:housenumber": "14745",
    "addr:postcode": "43138",
    "addr:street": "State Rte 93 S",
    "iso:country": "US",
    "sg:address": "14745 State Rte 93 S",
    "sg:city": "Logan",
    "sg:classifiers": [
      {
        "category": "Manufacturing",
        "subcategory": "Retail Goods",
        "type": "Manufacturing \u0026 Wholesale Goods"
      }
    ],
    "sg:phone": "+1 740 380 3544",
    "sg:postcode": "43138",
    "sg:province": "OH",
    "sg:tags": [
      "lead",
      "mfg"
    ],
    "wof:name": "Robberts",
    "wof:placetype": "venue"
  },
  "geometry": {"coordinates":[-82.432387,39.513706],"type":"Point"}
}
