{
  "type": "Feature",
  "properties": {
    "iso:country":"US",
    "sg:address":"14745 State Rte 93 S",
    "sg:city":"Logan",
    "sg:classifiers":[
        {
            "category":"Manufacturing",
            "subcategory":"Retail Goods",
            "type":"Manufacturing & Wholesale Goods"
        }
    ],
    "sg:phone":"+1 740 380 3544",
    "sg:postcode":"43138",
    "sg:province":"OH",
    "sg:tags":[
        "lead",
        "mfg"
    ],
    "wof:name":"Robberts",
    "wof:placetype":"venue"
},
  "geometry": {"coordinates":[-82.432387,39.513706],"type":"Point"}
}