{
  "type": "Feature",
  "properties": {
    "addr:full": "677 Main St Bridgeport OH 43912",
    "addr:housenumber": "677",
    "addr:postcode": "43912",
    "addr:street": "Main St",
    "iso:country": "US",
    "sg:address": "677 Main St",
    "sg:city": "Bridgeport",
    "sg:classifiers": [
      {
        "category": "Restaurant",
        "type": "Food \u0026 Drink"
      }
    ],
    "sg:phone": "+1 740 635 1300",
    "sg:postcode": "43912",
    "sg:province": "OH",
    "sg:tags": [
      "eating"
    ],
    "sg:website": "www.pizzahut.com",
    "wof:name": "Pizza Hut",
    "wof:placetype": "venue"
  },
  "geometry": {"coordinates":[-80.75063,40.071911],"type":"Point"}
}
