{
  "type": "Feature",
  "properties": {
    "iso:country":"US",
    "sg:address":"225 N Main St",
    "sg:city":"Findlay",
    "sg:classifiers":[
        {
            "category":"Wholesale",
            "subcategory":"Office Equipment",
            "type":"Manufacturing & Wholesale Goods"
        }
    ],
    "sg:phone":"+1 419 422 1553",
    "sg:postcode":"45840",
    "sg:province":"OH",
    "sg:tags":[
        "machine",
        "duplicating",
        "copying"
    ],
    "wof:name":"Gordon Flesch Co Inc",
    "wof:placetype":"venue"
},
  "geometry": {"coordinates":[-83.650097,41.044026],"type":"Point"}
}