{
  "type": "Feature",
  "properties": {
    "addr:full":"242 Federal St NW Warren OH 44483",
    "addr:housenumber":"242",
    "addr:postcode":"44483",
    "addr:street":"Federal St Nw",
    "iso:country":"US",
    "sg:address":"242 Federal St NW",
    "sg:city":"Warren",
    "sg:classifiers":[
        {
            "category":"Government",
            "subcategory":"Office",
            "type":"Public Place"
        }
    ],
    "sg:phone":"+1 330 797 5550",
    "sg:postcode":"44483",
    "sg:province":"OH",
    "sg:tags":[
        "executive"
    ],
    "wof:name":"Regional Reinstatement Center",
    "wof:placetype":"venue"
},
  "geometry": {"coordinates":[-80.819609,41.255433],"type":"Point"}
}