{
  "type": "Feature",
  "properties": {
    "addr:full":"55 S Main St Rittman OH 44270",
    "addr:housenumber":"55",
    "addr:postcode":"44270",
    "addr:street":"S Main St",
    "iso:country":"US",
    "sg:address":"55 S Main St",
    "sg:city":"Rittman",
    "sg:classifiers":[
        {
            "category":"Professional",
            "type":"Services"
        }
    ],
    "sg:phone":"+1 330 927 5706",
    "sg:postcode":"44270",
    "sg:province":"OH",
    "wof:name":"Omni Essential",
    "wof:placetype":"venue"
},
  "geometry": {"coordinates":[-81.78167999999999,40.971389],"type":"Point"}
}