{
  "type": "Feature",
  "properties": {
    "addr:full": "4747 Turney Rd Cleveland OH 44125",
    "addr:housenumber": "4747",
    "addr:postcode": "44125",
    "addr:street": "Turney Rd",
    "iso:country": "US",
    "sg:address": "4747 Turney Rd",
    "sg:city": "Cleveland",
    "sg:classifiers": [
      {
        "category": "Professional",
        "subcategory": "Lawyer \u0026 Legal Services",
        "type": "Services"
      }
    ],
    "sg:phone": "+1 216 341 3413",
    "sg:postcode": "44125",
    "sg:province": "OH",
    "sg:tags": [
      "attorney"
    ],
    "wof:name": "Matthew D Deliberato",
    "wof:placetype": "venue"
  },
  "geometry": {"coordinates":[-81.616444,41.431314],"type":"Point"}
}
