{
  "type": "Feature",
  "properties": {
    "iso:country":"US",
    "sg:address":"4747 Turney Rd",
    "sg:city":"Cleveland",
    "sg:classifiers":[
        {
            "category":"Professional",
            "subcategory":"Lawyer & Legal Services",
            "type":"Services"
        }
    ],
    "sg:phone":"+1 216 341 3413",
    "sg:postcode":"44125",
    "sg:province":"OH",
    "sg:tags":[
        "attorney"
    ],
    "wof:name":"Matthew D Deliberato",
    "wof:placetype":"venue"
},
  "geometry": {"coordinates":[-81.616444,41.431314],"type":"Point"}
}