{
  "type": "Feature",
  "properties": {
    "addr:full": "1168 S Beachview Rd Willoughby OH 44094",
    "addr:housenumber": "1168",
    "addr:postcode": "44094",
    "addr:street": "S Beachview Rd",
    "iso:country": "US",
    "sg:address": "1168 S Beachview Rd",
    "sg:city": "Willoughby",
    "sg:classifiers": [
      {
        "category": "Manufacturing",
        "subcategory": "Printing",
        "type": "Manufacturing \u0026 Wholesale Goods"
      }
    ],
    "sg:phone": "+1 440 951 2468",
    "sg:postcode": "44094",
    "sg:province": "OH",
    "sg:tags": [
      "publisher"
    ],
    "wof:name": "50 Something Magazine",
    "wof:placetype": "venue"
  },
  "geometry": {"coordinates":[-81.403196,41.692603],"type":"Point"}
}
