{
  "type": "Feature",
  "properties": {
    "addr:full":"8050 Brandywine Rd Northfield OH 44067",
    "addr:housenumber":"8050",
    "addr:postcode":"44067",
    "addr:street":"Brandywine Rd",
    "iso:country":"US",
    "sg:address":"8050 Brandywine Rd",
    "sg:city":"Northfield",
    "sg:classifiers":[
        {
            "category":"Freight",
            "type":"Transportation"
        }
    ],
    "sg:phone":"+1 330 468 2845",
    "sg:postcode":"44067",
    "sg:province":"OH",
    "wof:name":"Brandywine Falls Tours",
    "wof:placetype":"venue"
},
  "geometry": {"coordinates":[-81.536524,41.275283],"type":"Point"}
}