{
  "type": "Feature",
  "properties": {
    "addr:full": "2018 Central Ave Middletown OH 45044",
    "addr:housenumber": "2018",
    "addr:postcode": "45044",
    "addr:street": "Central Ave",
    "iso:country": "US",
    "sg:address": "2018 Central Ave",
    "sg:city": "Middletown",
    "sg:classifiers": [
      {
        "category": "Shopping",
        "type": "Retail Goods"
      }
    ],
    "sg:phone": "+1 513 422 6659",
    "sg:postcode": "45044",
    "sg:province": "OH",
    "sg:tags": [
      "telephone",
      "cellular"
    ],
    "wof:name": "M T Wireless",
    "wof:placetype": "venue"
  },
  "geometry": {"coordinates":[-84.387892,39.512504],"type":"Point"}
}
