{
  "type": "Feature",
  "properties": {
    "iso:country":"US",
    "sg:address":"2727 N Fairfield Rd",
    "sg:city":"Dayton",
    "sg:classifiers":[
        {
            "category":"Restaurant",
            "type":"Food & Drink"
        }
    ],
    "sg:phone":"+1 937 427 8766",
    "sg:postcode":"45431",
    "sg:province":"OH",
    "sg:tags":[
        "parlor",
        "ice",
        "cream"
    ],
    "wof:name":"Beavercreek Ice Cream",
    "wof:placetype":"venue"
},
  "geometry": {"coordinates":[-84.05221899999999,39.768912],"type":"Point"}
}