{
  "type": "Feature",
  "properties": {
    "iso:country":"US",
    "sg:address":"6001 Woodland Ave",
    "sg:city":"Cleveland",
    "sg:classifiers":[
        {
            "category":"Organizations",
            "subcategory":"Non-profit Organization",
            "type":"Services"
        }
    ],
    "sg:phone":"+1 216 432 3424",
    "sg:postcode":"44104",
    "sg:province":"OH",
    "sg:tags":[
        "social"
    ],
    "wof:name":"Resident Empwrment Orgnization",
    "wof:placetype":"venue"
},
  "geometry": {"coordinates":[-81.64842,41.488099],"type":"Point"}
}