{
  "type": "Feature",
  "properties": {
    "addr:full":"711 Winkler Dr Wooster OH 44691",
    "addr:housenumber":"711",
    "addr:postcode":"44691",
    "addr:street":"Winkler Dr",
    "iso:country":"US",
    "sg:address":"711 Winkler Dr",
    "sg:city":"Wooster",
    "sg:classifiers":[
        {
            "category":"Professional",
            "type":"Services"
        }
    ],
    "sg:phone":"+1 330 345 8797",
    "sg:postcode":"44691",
    "sg:province":"OH",
    "sg:tags":[
        "consultant",
        "geological"
    ],
    "wof:name":"PCA Geologic Consultants",
    "wof:placetype":"venue"
},
  "geometry": {"coordinates":[-81.93181300000001,40.835948],"type":"Point"}
}