{
  "type": "Feature",
  "properties": {
    "iso:country":"US",
    "sg:address":"600 Clinton St",
    "sg:city":"Circleville",
    "sg:classifiers":[
        {
            "category":"Manufacturing",
            "subcategory":"Rubber & Plastics",
            "type":"Manufacturing & Wholesale Goods"
        }
    ],
    "sg:phone":"+1 740 474 6031",
    "sg:postcode":"43113",
    "sg:province":"OH",
    "sg:tags":[
        "product",
        "mfg",
        "motor",
        "vehicle"
    ],
    "wof:name":"Plastech Engineered Products",
    "wof:placetype":"venue"
},
  "geometry": {"coordinates":[-82.940565,39.593902],"type":"Point"}
}