{
  "type": "Feature",
  "properties": {
    "addr:full":"23401 Emery Rd Cleveland OH 44128",
    "addr:housenumber":"23401",
    "addr:postcode":"44128",
    "addr:street":"Emery Rd",
    "iso:country":"US",
    "sg:address":"23401 Emery Rd",
    "sg:city":"Cleveland",
    "sg:classifiers":[
        {
            "category":"Education",
            "subcategory":"School",
            "type":"Public Place"
        }
    ],
    "sg:phone":"+1 216 295 7792",
    "sg:postcode":"44128",
    "sg:province":"OH",
    "sg:website":"www.warrensville.k12.oh.us",
    "wof:name":"John Dewey Elementary School",
    "wof:placetype":"venue"
},
  "geometry": {"coordinates":[-81.515761,41.435185],"type":"Point"}
}