{
  "type": "Feature",
  "properties": {
    "iso:country":"US",
    "sg:address":"802 S Reynolds Rd",
    "sg:city":"Toledo",
    "sg:classifiers":[
        {
            "category":"Freight",
            "type":"Transportation"
        }
    ],
    "sg:phone":"+1 419 531 6868",
    "sg:postcode":"43615",
    "sg:province":"OH",
    "sg:tags":[
        "special"
    ],
    "wof:name":"Lock It Up Self Storage",
    "wof:placetype":"venue"
},
  "geometry": {"coordinates":[-83.66458799999999,41.626311],"type":"Point"}
}