{
  "type": "Feature",
  "properties": {
    "addr:full": "802 S Reynolds Rd Toledo OH 43615",
    "addr:housenumber": "802",
    "addr:postcode": "43615",
    "addr:street": "S Reynolds Rd",
    "iso:country": "US",
    "sg:address": "802 S Reynolds Rd",
    "sg:city": "Toledo",
    "sg:classifiers": [
      {
        "category": "Freight",
        "type": "Transportation"
      }
    ],
    "sg:phone": "+1 419 531 6868",
    "sg:postcode": "43615",
    "sg:province": "OH",
    "sg:tags": [
      "special"
    ],
    "wof:name": "Lock It Up Self Storage",
    "wof:placetype": "venue"
  },
  "geometry": {"coordinates":[-83.664588,41.626311],"type":"Point"}
}
