{
  "type": "Feature",
  "properties": {
    "addr:full": "875 Norwood Ave Logan OH 43138",
    "addr:housenumber": "875",
    "addr:postcode": "43138",
    "addr:street": "Norwood Ave",
    "iso:country": "US",
    "sg:address": "875 Norwood Ave",
    "sg:city": "Logan",
    "sg:classifiers": [
      {
        "category": "Utilities",
        "subcategory": "Refuse",
        "type": "Services"
      }
    ],
    "sg:phone": "+1 740 385 5045",
    "sg:postcode": "43138",
    "sg:province": "OH",
    "sg:tags": [
      "system"
    ],
    "wof:name": "Logan Sewage Disposal Plant",
    "wof:placetype": "venue"
  },
  "geometry": {"coordinates":[-82.393611,39.533455],"type":"Point"}
}
