{
  "type": "Feature",
  "properties": {
    "iso:country":"US",
    "sg:address":"772 Hardtack Ct",
    "sg:city":"Columbus",
    "sg:classifiers":[
        {
            "category":"Building & Trades",
            "subcategory":"Construction",
            "type":"Services"
        }
    ],
    "sg:phone":"+1 614 933 8540",
    "sg:postcode":"43230",
    "sg:province":"OH",
    "sg:tags":[
        "house"
    ],
    "wof:name":"Kc Linhart Homes Ltd",
    "wof:placetype":"venue"
},
  "geometry": {"coordinates":[-82.852628,40.041584],"type":"Point"}
}