{
  "type": "Feature",
  "properties": {
    "addr:full":"2216 Refugee Rd Columbus OH 43207",
    "addr:housenumber":"2216",
    "addr:postcode":"43207",
    "addr:street":"Refugee Rd",
    "iso:country":"US",
    "sg:address":"2216 Refugee Rd",
    "sg:city":"Columbus",
    "sg:classifiers":[
        {
            "category":"Building & Trades",
            "subcategory":"Construction",
            "type":"Services"
        }
    ],
    "sg:phone":"+1 614 444 0255",
    "sg:postcode":"43207",
    "sg:province":"OH",
    "sg:tags":[
        "tunnel"
    ],
    "wof:name":"Capitol Tunneling Inc",
    "wof:placetype":"venue"
},
  "geometry": {"coordinates":[-82.937482,39.91983],"type":"Point"}
}