{
  "type": "Feature",
  "properties": {
    "iso:country":"US",
    "sg:address":"331 Brookpoint Cir",
    "sg:city":"Wadsworth",
    "sg:classifiers":[
        {
            "category":"Real Estate",
            "subcategory":"Real Estate Operator",
            "type":"Services"
        }
    ],
    "sg:phone":"+1 330 336 4019",
    "sg:postcode":"44281",
    "sg:province":"OH",
    "sg:tags":[
        "building",
        "nonresidential"
    ],
    "wof:name":"Gormley Anna Dean LLC",
    "wof:placetype":"venue"
},
  "geometry": {"coordinates":[-81.737605,41.052135],"type":"Point"}
}