{
  "type": "Feature",
  "properties": {
    "iso:country":"US",
    "sg:address":"13690 E Twp Rd 104",
    "sg:city":"Attica",
    "sg:phone":"+1 419 426 0821",
    "sg:postcode":"44807",
    "sg:province":"OH",
    "sg:tags":[
        "farm",
        "corn",
        "soybean"
    ],
    "wof:name":"Chris Willman",
    "wof:placetype":"venue"
},
  "geometry": {"coordinates":[-82.906577,41.080733],"type":"Point"}
}