{
  "type": "Feature",
  "properties": {
    "iso:country":"US",
    "sg:address":"1721 Madison Rd",
    "sg:city":"Cincinnati",
    "sg:classifiers":[
        {
            "category":"Organizations",
            "subcategory":"Religious Organization",
            "type":"Services"
        }
    ],
    "sg:phone":"+1 513 751 8860",
    "sg:postcode":"45206",
    "sg:province":"OH",
    "sg:tags":[
        "church"
    ],
    "wof:name":"Seventh Presbyterian Church",
    "wof:placetype":"venue"
},
  "geometry": {"coordinates":[-84.472505,39.129802],"type":"Point"}
}