{
  "type": "Feature",
  "properties": {
    "iso:country":"US",
    "sg:address":"1251 Kemper Meadow Dr",
    "sg:city":"Cincinnati",
    "sg:classifiers":[
        {
            "category":"Wholesale",
            "subcategory":"Non-durable Goods",
            "type":"Manufacturing & Wholesale Goods"
        }
    ],
    "sg:phone":"+1 513 522 2013",
    "sg:postcode":"45240",
    "sg:province":"OH",
    "sg:tags":[
        "advertising"
    ],
    "sg:website":"www.dakotaandassoc.com",
    "wof:name":"Dakota & Assoc",
    "wof:placetype":"venue"
},
  "geometry": {"coordinates":[-84.53115699999999,39.292727],"type":"Point"}
}