{
  "type": "Feature",
  "properties": {
    "addr:full": "1040 Buena Vista Dr Akron OH 44319",
    "addr:housenumber": "1040",
    "addr:postcode": "44319",
    "addr:street": "Buena Vista Dr",
    "iso:country": "US",
    "sg:address": "1040 Buena Vista Dr",
    "sg:city": "Akron",
    "sg:classifiers": [
      {
        "category": "Building \u0026 Trades",
        "subcategory": "Electrical",
        "type": "Services"
      }
    ],
    "sg:phone": "+1 330 645 0240",
    "sg:postcode": "44319",
    "sg:province": "OH",
    "sg:tags": [
      "electrical",
      "contractor"
    ],
    "wof:name": "Dyson",
    "wof:placetype": "venue"
  },
  "geometry": {"coordinates":[-81.484896,41.002567],"type":"Point"}
}
