{
  "type": "Feature",
  "properties": {
    "iso:country":"US",
    "sg:address":"1040 Buena Vista Dr",
    "sg:city":"Akron",
    "sg:classifiers":[
        {
            "category":"Building & Trades",
            "subcategory":"Electrical",
            "type":"Services"
        }
    ],
    "sg:phone":"+1 330 645 0240",
    "sg:postcode":"44319",
    "sg:province":"OH",
    "sg:tags":[
        "electrical",
        "contractor"
    ],
    "wof:name":"Dyson",
    "wof:placetype":"venue"
},
  "geometry": {"coordinates":[-81.48489600000001,41.002567],"type":"Point"}
}