{
  "type": "Feature",
  "properties": {
    "iso:country":"US",
    "sg:address":"6 N Sandusky St",
    "sg:city":"Delaware",
    "sg:classifiers":[
        {
            "category":"Shopping",
            "subcategory":"Gifts & Souvenirs",
            "type":"Retail Goods"
        }
    ],
    "sg:phone":"+1 740 363 4804",
    "sg:postcode":"43015",
    "sg:province":"OH",
    "wof:name":"Bare Bowl LTD",
    "wof:placetype":"venue"
},
  "geometry": {"coordinates":[-83.067587,40.300014],"type":"Point"}
}