{
  "type": "Feature",
  "properties": {
    "addr:full": "3814 W 133rd St Cleveland OH 44111",
    "addr:housenumber": "3814",
    "addr:postcode": "44111",
    "addr:street": "W 133Rd St",
    "iso:country": "US",
    "sg:address": "3814 W 133rd St",
    "sg:city": "Cleveland",
    "sg:classifiers": [
      {
        "category": "Shopping",
        "type": "Retail Goods"
      }
    ],
    "sg:phone": "+1 216 476 4826",
    "sg:postcode": "44111",
    "sg:province": "OH",
    "sg:tags": [
      "merchandise"
    ],
    "wof:name": "Wobblefoot Ltd",
    "wof:placetype": "venue"
  },
  "geometry": {"coordinates":[-81.782322,41.449045],"type":"Point"}
}
