{
  "type": "Feature",
  "properties": {
    "addr:full":"8245 Dawson Rd Fort Loramie OH 45845",
    "addr:housenumber":"8245",
    "addr:postcode":"45845",
    "addr:street":"Dawson Rd",
    "iso:country":"US",
    "sg:address":"8245 Dawson Rd",
    "sg:city":"Fort Loramie",
    "sg:classifiers":[
        {
            "category":"Farming",
            "subcategory":"Dairy Farm",
            "type":"Manufacturing & Wholesale Goods"
        }
    ],
    "sg:phone":"+1 937 295 2501",
    "sg:postcode":"45845",
    "sg:province":"OH",
    "wof:name":"Hedge View Farms",
    "wof:placetype":"venue"
},
  "geometry": {"coordinates":[-84.330907,40.318527],"type":"Point"}
}