{
  "type": "Feature",
  "properties": {
    "iso:country":"US",
    "sg:address":"2395 Baty Rd",
    "sg:city":"Lima",
    "sg:classifiers":[
        {
            "category":"Real Estate",
            "subcategory":"Real Estate Services",
            "type":"Services"
        }
    ],
    "sg:phone":"+1 419 339 1525",
    "sg:postcode":"45807",
    "sg:province":"OH",
    "sg:tags":[
        "company",
        "title"
    ],
    "wof:name":"West Central Ohio Research",
    "wof:placetype":"venue"
},
  "geometry": {"coordinates":[-84.184488,40.770217],"type":"Point"}
}