{
  "type": "Feature",
  "properties": {
    "addr:full":"1255 Euclid Ave Cleveland OH 44115",
    "addr:housenumber":"1255",
    "addr:postcode":"44115",
    "addr:street":"Euclid Ave",
    "iso:country":"US",
    "sg:address":"1255 Euclid Ave",
    "sg:city":"Cleveland",
    "sg:classifiers":[
        {
            "category":"Professional",
            "subcategory":"Employment Agencies",
            "type":"Services"
        }
    ],
    "sg:phone":"+1 216 371 7430",
    "sg:postcode":"44115",
    "sg:province":"OH",
    "wof:name":"Cleveland Works Inc",
    "wof:placetype":"venue"
},
  "geometry": {"coordinates":[-81.682323,41.500893],"type":"Point"}
}