{
  "type": "Feature",
  "properties": {
    "addr:full":"110 E Morenci St Lyons OH 43533",
    "addr:housenumber":"110",
    "addr:postcode":"43533",
    "addr:street":"E Morenci St",
    "iso:country":"US",
    "sg:address":"110 E Morenci St",
    "sg:city":"Lyons",
    "sg:classifiers":[
        {
            "category":"Home & Garden",
            "subcategory":"Furniture",
            "type":"Retail Goods"
        }
    ],
    "sg:phone":"+1 419 923 0015",
    "sg:postcode":"43533",
    "sg:province":"OH",
    "wof:name":"American Oak Creations",
    "wof:placetype":"venue"
},
  "geometry": {"coordinates":[-84.06910999999999,41.699271],"type":"Point"}
}