{
  "type": "Feature",
  "properties": {
    "iso:country":"US",
    "sg:address":"85 Clarendon Ave",
    "sg:city":"Columbus",
    "sg:classifiers":[
        {
            "category":"Social Services",
            "type":"Services"
        }
    ],
    "sg:phone":"+1 614 279 0012",
    "sg:postcode":"43223",
    "sg:province":"OH",
    "wof:name":"Ashburn J Jnior Yuth Ctr O B C",
    "wof:placetype":"venue"
},
  "geometry": {"coordinates":[-83.05911,39.953967],"type":"Point"}
}