{
  "type": "Feature",
  "properties": {
    "addr:full":"7077 Glenn Hwy Cambridge OH 43725",
    "addr:housenumber":"7077",
    "addr:postcode":"43725",
    "addr:street":"Glenn Hwy",
    "iso:country":"US",
    "sg:address":"7077 Glenn Hwy",
    "sg:city":"Cambridge",
    "sg:classifiers":[
        {
            "category":"Professional",
            "subcategory":"Lawyer & Legal Services",
            "type":"Services"
        }
    ],
    "sg:phone":"+1 740 439 2842",
    "sg:postcode":"43725",
    "sg:province":"OH",
    "sg:tags":[
        "attorney"
    ],
    "wof:name":"Neal S Tostenson",
    "wof:placetype":"venue"
},
  "geometry": {"coordinates":[-81.608712,40.02301],"type":"Point"}
}