{
  "type": "Feature",
  "properties": {
    "addr:full":"455 W Highland Ave Ravenna OH 44266",
    "addr:housenumber":"455",
    "addr:postcode":"44266",
    "addr:street":"W Highland Ave",
    "iso:country":"US",
    "sg:address":"455 W Highland Ave",
    "sg:city":"Ravenna",
    "sg:classifiers":[
        {
            "category":"Restaurant",
            "type":"Food & Drink"
        }
    ],
    "sg:phone":"+1 330 296 6538",
    "sg:postcode":"44266",
    "sg:province":"OH",
    "wof:name":"Spano's Bar",
    "wof:placetype":"venue"
},
  "geometry": {"coordinates":[-81.249433,41.160379],"type":"Point"}
}