{
  "type": "Feature",
  "properties": {
    "iso:country":"US",
    "sg:address":"6011 Brandt Pike",
    "sg:city":"Dayton",
    "sg:classifiers":[
        {
            "category":"Utilities",
            "subcategory":"Mobile Phone",
            "type":"Services"
        }
    ],
    "sg:phone":"+1 937 235 3400",
    "sg:postcode":"45424",
    "sg:province":"OH",
    "sg:tags":[
        "telephone",
        "cellular"
    ],
    "sg:website":"www.t-mobile.com",
    "wof:name":"T-Mobile",
    "wof:placetype":"venue"
},
  "geometry": {"coordinates":[-84.115126,39.845266],"type":"Point"}
}