{
  "type": "Feature",
  "properties": {
    "iso:country":"US",
    "sg:address":"301 W North St",
    "sg:city":"Springfield",
    "sg:classifiers":[
        {
            "category":"Real Estate",
            "subcategory":"Real Estate Agent",
            "type":"Services"
        }
    ],
    "sg:phone":"+1 937 322 4996",
    "sg:postcode":"45504",
    "sg:province":"OH",
    "wof:name":"See & Associates Realty",
    "wof:placetype":"venue"
},
  "geometry": {"coordinates":[-83.81658299999999,39.927527],"type":"Point"}
}