{
  "type": "Feature",
  "properties": {
    "addr:full": "301 W North St Springfield OH 45504",
    "addr:housenumber": "301",
    "addr:postcode": "45504",
    "addr:street": "W North St",
    "iso:country": "US",
    "sg:address": "301 W North St",
    "sg:city": "Springfield",
    "sg:classifiers": [
      {
        "category": "Real Estate",
        "subcategory": "Real Estate Agent",
        "type": "Services"
      }
    ],
    "sg:phone": "+1 937 322 4996",
    "sg:postcode": "45504",
    "sg:province": "OH",
    "wof:name": "See \u0026 Associates Realty",
    "wof:placetype": "venue"
  },
  "geometry": {"coordinates":[-83.816583,39.927527],"type":"Point"}
}
