{
  "type": "Feature",
  "properties": {
    "addr:full": "206 N Church St New Carlisle OH 45344",
    "addr:housenumber": "206",
    "addr:postcode": "45344",
    "addr:street": "N Church St",
    "iso:country": "US",
    "sg:address": "206 N Church St",
    "sg:city": "New Carlisle",
    "sg:classifiers": [
      {
        "category": "Health Services",
        "subcategory": "Chiropractor",
        "type": "Services"
      }
    ],
    "sg:phone": "+1 937 846 1295",
    "sg:postcode": "45344",
    "sg:province": "OH",
    "wof:name": "Moritz Chiropractic",
    "wof:placetype": "venue"
  },
  "geometry": {"coordinates":[-84.026051,39.93831],"type":"Point"}
}
