{
  "type": "Feature",
  "properties": {
    "addr:full": "38800 Center Ridge Rd North Ridgeville OH 44039",
    "addr:housenumber": "38800",
    "addr:postcode": "44039",
    "addr:street": "Center Ridge Rd",
    "iso:country": "US",
    "sg:address": "38800 Center Ridge Rd",
    "sg:city": "North Ridgeville",
    "sg:classifiers": [
      {
        "category": "Retail",
        "subcategory": "Auto Repair",
        "type": "Services"
      }
    ],
    "sg:phone": "+1 440 327 0133",
    "sg:postcode": "44039",
    "sg:province": "OH",
    "sg:tags": [
      "repairing",
      "automobile"
    ],
    "wof:name": "Patriot Automotive",
    "wof:placetype": "venue"
  },
  "geometry": {"coordinates":[-82.053713,41.383615],"type":"Point"}
}
