{
  "type": "Feature",
  "properties": {
    "addr:full": "2209 Richland Mall Mansfield OH 44906",
    "addr:housenumber": "2209",
    "addr:postcode": "44906",
    "addr:street": "Richland Mall",
    "iso:country": "US",
    "sg:address": "2209 Richland Mall",
    "sg:city": "Mansfield",
    "sg:classifiers": [
      {
        "category": "Shopping",
        "subcategory": "Gifts \u0026 Souvenirs",
        "type": "Retail Goods"
      }
    ],
    "sg:phone": "+1 419 529 9735",
    "sg:postcode": "44906",
    "sg:province": "OH",
    "sg:tags": [
      "shop"
    ],
    "wof:name": "Spencer Gifts",
    "wof:placetype": "venue"
  },
  "geometry": {"coordinates":[-82.593734,40.772532],"type":"Point"}
}
