{
  "type": "Feature",
  "properties": {
    "addr:full":"809 W Main St Coldwater OH 45828",
    "addr:housenumber":"809",
    "addr:postcode":"45828",
    "addr:street":"W Main St",
    "iso:country":"US",
    "sg:address":"809 W Main St",
    "sg:city":"Coldwater",
    "sg:classifiers":[
        {
            "category":"Health Services",
            "subcategory":"Doctor",
            "type":"Services"
        }
    ],
    "sg:phone":"+1 419 678 4887",
    "sg:postcode":"45828",
    "sg:province":"OH",
    "sg:tags":[
        "medical"
    ],
    "wof:name":"St Marys Surgical Associates",
    "wof:placetype":"venue"
},
  "geometry": {"coordinates":[-84.64039099999999,40.479693],"type":"Point"}
}