{
  "type": "Feature",
  "properties": {
    "iso:country":"US",
    "sg:address":"344 E Main St",
    "sg:city":"Oak Harbor",
    "sg:classifiers":[
        {
            "category":"Real Estate",
            "subcategory":"Real Estate Agent",
            "type":"Services"
        }
    ],
    "sg:phone":"+1 419 836 1852",
    "sg:postcode":"43449",
    "sg:province":"OH",
    "wof:name":"McBain Real Estate",
    "wof:placetype":"venue"
},
  "geometry": {"coordinates":[-83.13776300000001,41.50882],"type":"Point"}
}