{
  "type": "Feature",
  "properties": {
    "addr:full": "344 E Main St Oak Harbor OH 43449",
    "addr:housenumber": "344",
    "addr:postcode": "43449",
    "addr:street": "E Main St",
    "iso:country": "US",
    "sg:address": "344 E Main St",
    "sg:city": "Oak Harbor",
    "sg:classifiers": [
      {
        "category": "Real Estate",
        "subcategory": "Real Estate Agent",
        "type": "Services"
      }
    ],
    "sg:phone": "+1 419 836 1852",
    "sg:postcode": "43449",
    "sg:province": "OH",
    "wof:name": "McBain Real Estate",
    "wof:placetype": "venue"
  },
  "geometry": {"coordinates":[-83.137763,41.50882],"type":"Point"}
}
