{
  "type": "Feature",
  "properties": {
    "addr:full":"3690 Orange Pl Beachwood OH 44122",
    "addr:housenumber":"3690",
    "addr:postcode":"44122",
    "addr:street":"Orange Pl",
    "iso:country":"US",
    "sg:address":"3690 Orange Pl",
    "sg:city":"Beachwood",
    "sg:classifiers":[
        {
            "category":"Health Services",
            "subcategory":"Doctor",
            "type":"Services"
        }
    ],
    "sg:phone":"+1 216 464 5330",
    "sg:postcode":"44122",
    "sg:province":"OH",
    "sg:tags":[
        "psychiatrist"
    ],
    "wof:name":"Mosen Judith MD",
    "wof:placetype":"venue"
},
  "geometry": {"coordinates":[-81.48818,41.458661],"type":"Point"}
}