{
  "type": "Feature",
  "properties": {
    "addr:full": "5779 S Winds Dr Mentor On Lake OH 44060",
    "addr:housenumber": "5779",
    "addr:postcode": "lake;44060",
    "addr:street": "S Winds Dr",
    "iso:country": "US",
    "sg:address": "5779 S Winds Dr",
    "sg:city": "Mentor On Lake",
    "sg:classifiers": [
      {
        "category": "Real Estate",
        "subcategory": "Real Estate Operator",
        "type": "Services"
      }
    ],
    "sg:phone": "+1 440 257 0222",
    "sg:postcode": "44060",
    "sg:province": "OH",
    "sg:tags": [
      "building",
      "apartment"
    ],
    "wof:name": "Windsor Place",
    "wof:placetype": "venue"
  },
  "geometry": {"coordinates":[-81.359867,41.71381],"type":"Point"}
}
