{
  "type": "Feature",
  "properties": {
    "addr:full": "7533 Tyler Blvd Mentor OH 44060",
    "addr:housenumber": "7533",
    "addr:postcode": "44060",
    "addr:street": "Tyler Blvd",
    "iso:country": "US",
    "sg:address": "7533 Tyler Blvd",
    "sg:city": "Mentor",
    "sg:classifiers": [
      {
        "category": "Manufacturing",
        "subcategory": "Printing",
        "type": "Manufacturing \u0026 Wholesale Goods"
      }
    ],
    "sg:phone": "+1 440 953 2200",
    "sg:postcode": "44060",
    "sg:province": "OH",
    "sg:tags": [
      "periodical"
    ],
    "wof:name": "Fifty Something Magazine",
    "wof:placetype": "venue"
  },
  "geometry": {"coordinates":[-81.371625,41.663069],"type":"Point"}
}
