{
  "type": "Feature",
  "properties": {
    "iso:country":"US",
    "sg:address":"307 E Hardin St",
    "sg:city":"Findlay",
    "sg:classifiers":[
        {
            "category":"Organizations",
            "subcategory":"Religious Organization",
            "type":"Services"
        }
    ],
    "sg:phone":"+1 419 422 3306",
    "sg:postcode":"45840",
    "sg:province":"OH",
    "sg:tags":[
        "church"
    ],
    "sg:website":"www.findlayccc.org",
    "wof:name":"Central Church Of Christ",
    "wof:placetype":"venue"
},
  "geometry": {"coordinates":[-83.646674,41.035605],"type":"Point"}
}