{
  "type": "Feature",
  "properties": {
    "iso:country":"US",
    "sg:address":"11640 S State Line Rd",
    "sg:city":"Petersburg",
    "sg:classifiers":[
        {
            "category":"Building & Trades",
            "subcategory":"Equipment Rental",
            "type":"Services"
        }
    ],
    "sg:phone":"+1 330 542 1175",
    "sg:postcode":"44454",
    "sg:province":"OH",
    "sg:tags":[
        "leasing"
    ],
    "wof:name":"ADS Leasing Corp",
    "wof:placetype":"venue"
},
  "geometry": {"coordinates":[-80.519085,40.949083],"type":"Point"}
}