{
  "type": "Feature",
  "properties": {
    "addr:full": "4353 E 71st St Cleveland OH 44105",
    "addr:housenumber": "4353",
    "addr:postcode": "44105",
    "addr:street": "E 71St St",
    "iso:country": "US",
    "sg:address": "4353 E 71st St",
    "sg:city": "Cleveland",
    "sg:classifiers": [
      {
        "category": "Personal",
        "subcategory": "Beauty Salon",
        "type": "Services"
      }
    ],
    "sg:phone": "+1 216 441 2029",
    "sg:postcode": "44105",
    "sg:province": "OH",
    "wof:name": "Dedicated To You Hair \u0026 Nail",
    "wof:placetype": "venue"
  },
  "geometry": {"coordinates":[-81.639613,41.440203],"type":"Point"}
}
