{
  "type": "Feature",
  "properties": {
    "addr:full": "180 Spring Valley Pike Dayton OH 45458",
    "addr:housenumber": "180",
    "addr:postcode": "45458",
    "addr:street": "Spring Valley Pike",
    "iso:country": "US",
    "sg:address": "180 Spring Valley Pike",
    "sg:city": "Dayton",
    "sg:classifiers": [
      {
        "category": "Health Services",
        "subcategory": "Hospital",
        "type": "Services"
      }
    ],
    "sg:phone": "+1 937 291 1351",
    "sg:postcode": "45458",
    "sg:province": "OH",
    "sg:tags": [
      "mental"
    ],
    "wof:name": "South Suburban Mental Health",
    "wof:placetype": "venue"
  },
  "geometry": {"coordinates":[-84.159833,39.61351],"type":"Point"}
}
