{
  "type": "Feature",
  "properties": {
    "iso:country":"US",
    "sg:address":"180 Spring Valley Pike",
    "sg:city":"Dayton",
    "sg:classifiers":[
        {
            "category":"Health Services",
            "subcategory":"Hospital",
            "type":"Services"
        }
    ],
    "sg:phone":"+1 937 291 1351",
    "sg:postcode":"45458",
    "sg:province":"OH",
    "sg:tags":[
        "mental"
    ],
    "wof:name":"South Suburban Mental Health",
    "wof:placetype":"venue"
},
  "geometry": {"coordinates":[-84.15983300000001,39.61351],"type":"Point"}
}