{
  "type": "Feature",
  "properties": {
    "iso:country":"US",
    "sg:address":"5707 Madison Rd",
    "sg:city":"Cincinnati",
    "sg:classifiers":[
        {
            "category":"Organizations",
            "subcategory":"Religious Organization",
            "type":"Services"
        }
    ],
    "sg:phone":"+1 513 271 9096",
    "sg:postcode":"45227",
    "sg:province":"OH",
    "sg:tags":[
        "a",
        "as",
        "operates",
        "methodist",
        "church"
    ],
    "wof:name":"Gaines United Methodist Church",
    "wof:placetype":"venue"
},
  "geometry": {"coordinates":[-84.39439299999999,39.160621],"type":"Point"}
}