{
  "type": "Feature",
  "properties": {
    "iso:country":"US",
    "sg:address":"5929 N Dixie Dr",
    "sg:city":"Dayton",
    "sg:classifiers":[
        {
            "category":"Building & Trades",
            "subcategory":"Landscaping Services",
            "type":"Services"
        }
    ],
    "sg:phone":"+1 937 898 2700",
    "sg:postcode":"45414",
    "sg:province":"OH",
    "sg:tags":[
        "lawn",
        "maintenance",
        "grounds"
    ],
    "sg:website":"www.superiorservices.cc",
    "wof:name":"Superior Services Of Dayton",
    "wof:placetype":"venue"
},
  "geometry": {"coordinates":[-84.198362,39.821413],"type":"Point"}
}