{
  "type": "Feature",
  "properties": {
    "addr:full":"2958 Blossom Ave Columbus OH 43231",
    "addr:housenumber":"2958",
    "addr:postcode":"43231",
    "addr:street":"Blossom Ave",
    "iso:country":"US",
    "sg:address":"2958 Blossom Ave",
    "sg:city":"Columbus",
    "sg:classifiers":[
        {
            "category":"Manufacturing",
            "subcategory":"Printing",
            "type":"Manufacturing & Wholesale Goods"
        }
    ],
    "sg:phone":"+1 614 890 5636",
    "sg:postcode":"43231",
    "sg:province":"OH",
    "sg:tags":[
        "commercial",
        "lithographic"
    ],
    "wof:name":"Columbus Square Quickprint",
    "wof:placetype":"venue"
},
  "geometry": {"coordinates":[-82.939773,40.091335],"type":"Point"}
}