{
  "type": "Feature",
  "properties": {
    "iso:country":"US",
    "sg:address":"3449 Annabelle Dr",
    "sg:city":"Dayton",
    "sg:classifiers":[
        {
            "category":"Building & Trades",
            "subcategory":"Construction",
            "type":"Services"
        }
    ],
    "sg:phone":"+1 937 293 6176",
    "sg:postcode":"45429",
    "sg:province":"OH",
    "sg:tags":[
        "house"
    ],
    "wof:name":"Strawser Management",
    "wof:placetype":"venue"
},
  "geometry": {"coordinates":[-84.132329,39.696585],"type":"Point"}
}