{
  "type": "Feature",
  "properties": {
    "iso:country":"US",
    "sg:address":"5439 Aqua St",
    "sg:city":"Columbus",
    "sg:classifiers":[
        {
            "category":"Building & Trades",
            "subcategory":"Construction",
            "type":"Services"
        }
    ],
    "sg:phone":"+1 330 744 4518",
    "sg:postcode":"43229",
    "sg:province":"OH",
    "wof:name":"Verrill Paving Co",
    "wof:placetype":"venue"
},
  "geometry": {"coordinates":[-82.958595,40.079643],"type":"Point"}
}