{
  "type": "Feature",
  "properties": {
    "addr:full":"221 Court St Portsmouth OH 45662",
    "addr:housenumber":"221",
    "addr:postcode":"45662",
    "addr:street":"Court St",
    "iso:country":"US",
    "sg:address":"221 Court St",
    "sg:city":"Portsmouth",
    "sg:classifiers":[
        {
            "category":"Organizations",
            "subcategory":"Non-profit Organization",
            "type":"Services"
        }
    ],
    "sg:phone":"+1 740 354 3137",
    "sg:postcode":"45662",
    "sg:province":"OH",
    "sg:tags":[
        "worker",
        "placement",
        "volunteer"
    ],
    "wof:name":"Retired Senior Volunteer Prgrm",
    "wof:placetype":"venue"
},
  "geometry": {"coordinates":[-83.000885,38.732282],"type":"Point"}
}