{
  "type": "Feature",
  "properties": {
    "iso:country":"US",
    "sg:address":"555 N 2nd St",
    "sg:city":"Coldwater",
    "sg:classifiers":[
        {
            "category":"Food & Beverages",
            "subcategory":"Groceries & Convenience Stores",
            "type":"Retail Goods"
        },
        {
            "category":"Autos & Motor Vehicles",
            "subcategory":"Fuel & Gas Station",
            "type":"Retail Goods"
        }
    ],
    "sg:phone":"+1 419 678 7050",
    "sg:postcode":"45828",
    "sg:province":"OH",
    "sg:tags":[
        "oil"
    ],
    "wof:name":"Northtown Marathon Inc",
    "wof:placetype":"venue"
},
  "geometry": {"coordinates":[-84.628666,40.484674],"type":"Point"}
}