{
  "type": "Feature",
  "properties": {
    "addr:full": "555 N 2nd St Coldwater OH 45828",
    "addr:housenumber": "555",
    "addr:postcode": "45828",
    "addr:street": "N 2Nd St",
    "iso:country": "US",
    "sg:address": "555 N 2nd St",
    "sg:city": "Coldwater",
    "sg:classifiers": [
      {
        "category": "Food \u0026 Beverages",
        "subcategory": "Groceries \u0026 Convenience Stores",
        "type": "Retail Goods"
      },
      {
        "category": "Autos \u0026 Motor Vehicles",
        "subcategory": "Fuel \u0026 Gas Station",
        "type": "Retail Goods"
      }
    ],
    "sg:phone": "+1 419 678 7050",
    "sg:postcode": "45828",
    "sg:province": "OH",
    "sg:tags": [
      "oil"
    ],
    "wof:name": "Northtown Marathon Inc",
    "wof:placetype": "venue"
  },
  "geometry": {"coordinates":[-84.628666,40.484674],"type":"Point"}
}
