{
  "type": "Feature",
  "properties": {
    "iso:country":"US",
    "sg:address":"4842 Dearth Rd",
    "sg:city":"Springboro",
    "sg:classifiers":[
        {
            "category":"Organizations",
            "subcategory":"Religious Organization",
            "type":"Services"
        }
    ],
    "sg:phone":"+1 937 746 5554",
    "sg:postcode":"45066",
    "sg:province":"OH",
    "sg:tags":[
        "church"
    ],
    "wof:name":"Zion Missionary Baptist Church",
    "wof:placetype":"venue"
},
  "geometry": {"coordinates":[-84.264307,39.513387],"type":"Point"}
}