{
  "type": "Feature",
  "properties": {
    "addr:full":"3766 E Broad St Columbus OH 43213",
    "addr:housenumber":"3766",
    "addr:postcode":"43213",
    "addr:street":"E Broad St",
    "iso:country":"US",
    "sg:address":"3766 E Broad St",
    "sg:city":"Columbus",
    "sg:classifiers":[
        {
            "category":"Shopping",
            "subcategory":"Clothing, Apparel, & Fashions",
            "type":"Retail Goods"
        }
    ],
    "sg:phone":"+1 614 239 8509",
    "sg:postcode":"43213",
    "sg:province":"OH",
    "sg:tags":[
        "woman"
    ],
    "wof:name":"Dots Inc",
    "wof:placetype":"venue"
},
  "geometry": {"coordinates":[-82.899716,39.97337],"type":"Point"}
}