{
  "type": "Feature",
  "properties": {
    "iso:country":"US",
    "sg:address":"3018 State Rte 82",
    "sg:city":"Aurora",
    "sg:classifiers":[
        {
            "category":"Autos & Motor Vehicles",
            "subcategory":"Boat Sales",
            "type":"Retail Goods"
        }
    ],
    "sg:phone":"+1 330 562 8638",
    "sg:postcode":"44202",
    "sg:province":"OH",
    "sg:tags":[
        "dealer",
        "sales"
    ],
    "wof:name":"D & D Marine Svc",
    "wof:placetype":"venue"
},
  "geometry": {"coordinates":[-81.28380199999999,41.308641],"type":"Point"}
}