{
  "type": "Feature",
  "properties": {
    "addr:full": "3018 State Rte 82 Aurora OH 44202",
    "addr:housenumber": "3018",
    "addr:postcode": "44202",
    "addr:street": "State Rte 82",
    "iso:country": "US",
    "sg:address": "3018 State Rte 82",
    "sg:city": "Aurora",
    "sg:classifiers": [
      {
        "category": "Autos \u0026 Motor Vehicles",
        "subcategory": "Boat Sales",
        "type": "Retail Goods"
      }
    ],
    "sg:phone": "+1 330 562 8638",
    "sg:postcode": "44202",
    "sg:province": "OH",
    "sg:tags": [
      "dealer",
      "sales"
    ],
    "wof:name": "D \u0026 D Marine Svc",
    "wof:placetype": "venue"
  },
  "geometry": {"coordinates":[-81.283802,41.308641],"type":"Point"}
}
