{
  "type": "Feature",
  "properties": {
    "addr:full":"8011 Richard Rd Broadview Heights OH 44147",
    "addr:housenumber":"8011",
    "addr:postcode":"44147",
    "addr:street":"Richard Rd",
    "iso:country":"US",
    "sg:address":"8011 Richard Rd",
    "sg:city":"Broadview Heights",
    "sg:classifiers":[
        {
            "category":"Freight",
            "type":"Transportation"
        }
    ],
    "sg:phone":"+1 440 526 8138",
    "sg:postcode":"44147",
    "sg:province":"OH",
    "sg:tags":[
        "operator",
        "local",
        "trucking"
    ],
    "wof:name":"John F McSweeney",
    "wof:placetype":"venue"
},
  "geometry": {"coordinates":[-81.691999,41.345707],"type":"Point"}
}