{
  "type": "Feature",
  "properties": {
    "addr:full":"8181 Camargo Rd Cincinnati OH 45243",
    "addr:housenumber":"8181",
    "addr:postcode":"45243",
    "addr:street":"Camargo Rd",
    "iso:country":"US",
    "sg:address":"8181 Camargo Rd",
    "sg:city":"Cincinnati",
    "sg:classifiers":[
        {
            "category":"Building & Trades",
            "subcategory":"Landscaping Services",
            "type":"Services"
        }
    ],
    "sg:phone":"+1 513 271 1300",
    "sg:postcode":"45243",
    "sg:province":"OH",
    "sg:tags":[
        "landscape",
        "contractor"
    ],
    "wof:name":"Fred J Hensley",
    "wof:placetype":"venue"
},
  "geometry": {"coordinates":[-84.343129,39.196819],"type":"Point"}
}