{
  "type": "Feature",
  "properties": {
    "iso:country":"US",
    "sg:address":"1441 E Dorothy Ln",
    "sg:city":"Dayton",
    "sg:classifiers":[
        {
            "category":"Cinema",
            "subcategory":"Movie Theater",
            "type":"Entertainment"
        }
    ],
    "sg:phone":"+1 937 298 1000",
    "sg:postcode":"45419",
    "sg:province":"OH",
    "sg:tags":[
        "motion",
        "picture"
    ],
    "wof:name":"Kettering Cinema 1 & 2",
    "wof:placetype":"venue"
},
  "geometry": {"coordinates":[-84.14020499999999,39.703731],"type":"Point"}
}