{
  "type": "Feature",
  "properties": {
    "addr:full": "1063 W Riddle Ave Ravenna OH 44266",
    "addr:housenumber": "1063",
    "addr:postcode": "44266",
    "addr:street": "W Riddle Ave",
    "iso:country": "US",
    "sg:address": "1063 W Riddle Ave",
    "sg:city": "Ravenna",
    "sg:classifiers": [
      {
        "category": "Building \u0026 Trades",
        "subcategory": "Construction",
        "type": "Services"
      }
    ],
    "sg:phone": "+1 330 297 6399",
    "sg:postcode": "44266",
    "sg:province": "OH",
    "sg:tags": [
      "hanging",
      "contractor"
    ],
    "wof:name": "Webb Painting",
    "wof:placetype": "venue"
  },
  "geometry": {"coordinates":[-81.263499,41.155931],"type":"Point"}
}
