{
  "type": "Feature",
  "properties": {
    "addr:full": "263 Deo Dr Newark OH 43055",
    "addr:housenumber": "263",
    "addr:postcode": "43055",
    "addr:street": "Deo Dr",
    "iso:country": "US",
    "sg:address": "263 Deo Dr",
    "sg:city": "Newark",
    "sg:classifiers": [
      {
        "category": "Real Estate",
        "subcategory": "Real Estate Agent",
        "type": "Services"
      }
    ],
    "sg:phone": "+1 740 364 0321",
    "sg:postcode": "43055",
    "sg:province": "OH",
    "sg:tags": [
      "business"
    ],
    "wof:name": "Shai Commercial",
    "wof:placetype": "venue"
  },
  "geometry": {"coordinates":[-82.421514,40.0861],"type":"Point"}
}
