{
  "type": "Feature",
  "properties": {
    "iso:country":"US",
    "sg:address":"1471 North Rd",
    "sg:city":"Troy",
    "sg:classifiers":[
        {
            "category":"Local Transit",
            "type":"Transportation"
        }
    ],
    "sg:phone":"+1 937 335 6272",
    "sg:postcode":"45373",
    "sg:province":"OH",
    "sg:tags":[
        "repair",
        "model",
        "supply",
        "railroad",
        "doe"
    ],
    "wof:name":"Erie Railway Depot",
    "wof:placetype":"venue"
},
  "geometry": {"coordinates":[-84.225516,40.053873],"type":"Point"}
}