{
  "type": "Feature",
  "properties": {
    "addr:full": "5489 Wolfpen Rd Milford OH 45150",
    "addr:housenumber": "5489",
    "addr:postcode": "45150",
    "addr:street": "Wolfpen Rd",
    "iso:country": "US",
    "sg:address": "5489 Wolfpen Rd",
    "sg:city": "Milford",
    "sg:classifiers": [
      {
        "category": "Professional",
        "subcategory": "Management \u0026 Consulting",
        "type": "Services"
      }
    ],
    "sg:phone": "+1 513 831 9725",
    "sg:postcode": "45150",
    "sg:province": "OH",
    "sg:tags": [
      "consultant",
      "business"
    ],
    "wof:name": "Kossel \u0026 Assoc Inc",
    "wof:placetype": "venue"
  },
  "geometry": {"coordinates":[-84.237611,39.165593],"type":"Point"}
}
