{
  "type": "Feature",
  "properties": {
    "addr:full": "100 S Church St Bowling Green OH 43402",
    "addr:housenumber": "100",
    "addr:postcode": "43402",
    "addr:street": "S Church St",
    "iso:country": "US",
    "sg:address": "100 S Church St",
    "sg:city": "Bowling Green",
    "sg:classifiers": [
      {
        "category": "Organizations",
        "subcategory": "Religious Organization",
        "type": "Services"
      }
    ],
    "sg:phone": "+1 419 293 3454",
    "sg:postcode": "43402",
    "sg:province": "OH",
    "sg:tags": [
      "church"
    ],
    "wof:name": "Mc Comb United Presbyterian",
    "wof:placetype": "venue"
  },
  "geometry": {"coordinates":[-83.652037,41.374941],"type":"Point"}
}
