{
  "type": "Feature",
  "properties": {
    "addr:full": "18699 High Pkwy Cleveland OH 44116",
    "addr:housenumber": "18699",
    "addr:postcode": "44116",
    "addr:street": "High Pkwy",
    "iso:country": "US",
    "sg:address": "18699 High Pkwy",
    "sg:city": "Cleveland",
    "sg:classifiers": [
      {
        "category": "Professional",
        "subcategory": "Lawyer \u0026 Legal Services",
        "type": "Services"
      }
    ],
    "sg:phone": "+1 440 333 5835",
    "sg:postcode": "44116",
    "sg:province": "OH",
    "sg:tags": [
      "attorney"
    ],
    "wof:name": "James F Shannon",
    "wof:placetype": "venue"
  },
  "geometry": {"coordinates":[-81.828371,41.476094],"type":"Point"}
}
