{
  "type": "Feature",
  "properties": {
    "addr:full": "5625 Hichitee Ct. Hamilton OH 45011",
    "addr:housenumber": "5625",
    "addr:postcode": "45011",
    "addr:street": "Hichitee Ct.",
    "iso:country": "US",
    "sg:address": "5625 Hichitee Ct.",
    "sg:city": "Hamilton",
    "sg:classifiers": [
      {
        "category": "Shopping",
        "subcategory": "Stationery \u0026 Office Supplies",
        "type": "Retail Goods"
      },
      {
        "category": "Communications",
        "subcategory": "Film \u0026 Video Production",
        "type": "Services"
      },
      {
        "category": "Professional",
        "subcategory": "Advertising",
        "type": "Services"
      },
      {
        "category": "Professional",
        "subcategory": "Printing \u0026 Photocopies",
        "type": "Services"
      },
      {
        "category": "Professional",
        "subcategory": "Computer Services",
        "type": "Services"
      }
    ],
    "sg:phone": "+1 513 759 4297",
    "sg:postcode": "45011",
    "sg:province": "OH",
    "sg:tags": [
      "printers-continuous",
      "form",
      "multimedia",
      "services-commercial",
      "product",
      "individual",
      "online",
      "advertising-promotional"
    ],
    "wof:name": "Proforma P.R.E.S.S. Solutions",
    "wof:placetype": "venue"
  },
  "geometry": {"coordinates":[-84.429018,39.411824],"type":"Point"}
}
