{
  "type": "Feature",
  "properties": {
    "addr:full": "869 State Rte 183 Atwater OH 44201",
    "addr:housenumber": "869",
    "addr:postcode": "44201",
    "addr:street": "State Rte 183",
    "iso:country": "US",
    "sg:address": "869 State Rte 183",
    "sg:city": "Atwater",
    "sg:classifiers": [
      {
        "category": "Farming",
        "subcategory": "Livestock Farm",
        "type": "Manufacturing \u0026 Wholesale Goods"
      }
    ],
    "sg:phone": "+1 330 947 2567",
    "sg:postcode": "44201",
    "sg:province": "OH",
    "sg:tags": [
      "beef",
      "feedlot",
      "cattle"
    ],
    "wof:name": "Dick Vence",
    "wof:placetype": "venue"
  },
  "geometry": {"coordinates":[-81.148089,41.014253],"type":"Point"}
}
