{
  "type": "Feature",
  "properties": {
    "addr:full":"1923 Cooper Foster Park Rd Amherst OH 44001",
    "addr:housenumber":"1923",
    "addr:postcode":"44001",
    "addr:street":"Cooper Foster Park Rd",
    "iso:country":"US",
    "sg:address":"1923 Cooper Foster Park Rd",
    "sg:city":"Amherst",
    "sg:classifiers":[
        {
            "category":"Personal",
            "subcategory":"Tanning Parlor",
            "type":"Services"
        }
    ],
    "sg:phone":"+1 440 989 2478",
    "sg:postcode":"44001",
    "sg:province":"OH",
    "sg:tags":[
        "salon"
    ],
    "wof:name":"Damon Nail",
    "wof:placetype":"venue"
},
  "geometry": {"coordinates":[-82.210449,41.418239],"type":"Point"}
}