{
  "type": "Feature",
  "properties": {
    "iso:country":"US",
    "sg:address":"300 Lytle St",
    "sg:city":"Cincinnati",
    "sg:classifiers":[
        {
            "category":"Social Services",
            "subcategory":"Child Care",
            "type":"Services"
        }
    ],
    "sg:phone":"+1 513 768 6907",
    "sg:postcode":"45202",
    "sg:province":"OH",
    "sg:tags":[
        "youth",
        "r",
        "center",
        "day"
    ],
    "sg:website":"www.cinunionbethel.org",
    "wof:name":"Cincinnati Union Bethel",
    "wof:placetype":"venue"
},
  "geometry": {"coordinates":[-84.503683,39.101157],"type":"Point"}
}