{
  "type": "Feature",
  "properties": {
    "addr:full": "1385 Conant St Maumee OH 43537",
    "addr:housenumber": "1385",
    "addr:postcode": "43537",
    "addr:street": "Conant St",
    "iso:country": "US",
    "sg:address": "1385 Conant St",
    "sg:city": "Maumee",
    "sg:classifiers": [
      {
        "category": "Personal",
        "subcategory": "Beauty Salon",
        "type": "Services"
      },
      {
        "category": "Personal",
        "subcategory": "Barber",
        "type": "Services"
      }
    ],
    "sg:phone": "+1 419 893 2166",
    "sg:postcode": "43537",
    "sg:province": "OH",
    "sg:tags": [
      "hair",
      "accessory",
      "stylist",
      "supply"
    ],
    "sg:website": "http://www.greatclips.com/",
    "wof:name": "Great Clips",
    "wof:placetype": "venue"
  },
  "geometry": {"coordinates":[-83.664734,41.580425],"type":"Point"}
}
