{
  "type": "Feature",
  "properties": {
    "addr:full": "2343 E 86th St Cleveland OH 44106",
    "addr:housenumber": "2343",
    "addr:postcode": "44106",
    "addr:street": "E 86Th St",
    "iso:country": "US",
    "sg:address": "2343 E 86th St",
    "sg:city": "Cleveland",
    "sg:classifiers": [
      {
        "category": "Building \u0026 Trades",
        "subcategory": "Pest Control",
        "type": "Services"
      }
    ],
    "sg:phone": "+1 216 229 9330",
    "sg:postcode": "44106",
    "sg:province": "OH",
    "wof:name": "Precise Exterminating",
    "wof:placetype": "venue"
  },
  "geometry": {"coordinates":[-81.626893,41.499622],"type":"Point"}
}
