{
  "type": "Feature",
  "properties": {
    "iso:country":"US",
    "sg:address":"11434 Mill Rd",
    "sg:city":"Cincinnati",
    "sg:classifiers":[
        {
            "category":"Organizations",
            "subcategory":"Religious Organization",
            "type":"Services"
        }
    ],
    "sg:phone":"+1 513 825 6876",
    "sg:postcode":"45240",
    "sg:province":"OH",
    "sg:tags":[
        "clergy"
    ],
    "wof:name":"Tim Booker",
    "wof:placetype":"venue"
},
  "geometry": {"coordinates":[-84.54366,39.287855],"type":"Point"}
}