{
  "type": "Feature",
  "properties": {
    "iso:country":"US",
    "sg:address":"619 Davidson St",
    "sg:city":"Defiance",
    "sg:classifiers":[
        {
            "category":"Retail",
            "subcategory":"Car Wash",
            "type":"Services"
        }
    ],
    "sg:phone":"+1 419 784 4200",
    "sg:postcode":"43512",
    "sg:province":"OH",
    "sg:tags":[
        "automobile",
        "detail",
        "clean"
    ],
    "wof:name":"Baldwin Automotive Detail",
    "wof:placetype":"venue"
},
  "geometry": {"coordinates":[-84.37069,41.279721],"type":"Point"}
}