{
  "type": "Feature",
  "properties": {
    "addr:full": "2159 Sharon-Copley Rd Medina OH 44256",
    "addr:housenumber": "2159",
    "addr:postcode": "44256",
    "addr:street": "Sharon-Copley Rd",
    "iso:country": "US",
    "sg:address": "2159 Sharon-Copley Rd",
    "sg:city": "Medina",
    "sg:classifiers": [
      {
        "category": "Retail",
        "subcategory": "Animal Services",
        "type": "Services"
      }
    ],
    "sg:phone": "+1 330 239 1007",
    "sg:postcode": "44256",
    "sg:province": "OH",
    "sg:tags": [
      "pet",
      "grooming",
      "washing"
    ],
    "wof:name": "Coat Room Linda's",
    "wof:placetype": "venue"
  },
  "geometry": {"coordinates":[-81.758893,41.099358],"type":"Point"}
}
