{
  "type": "Feature",
  "properties": {
    "iso:country":"US",
    "sg:address":"3761 Amberwood Ct",
    "sg:city":"Amelia",
    "sg:classifiers":[
        {
            "category":"Professional",
            "subcategory":"Computer Services",
            "type":"Services"
        }
    ],
    "sg:phone":"+1 513 891 8998",
    "sg:postcode":"45102",
    "sg:province":"OH",
    "sg:website":"www.cecinc20.com",
    "wof:name":"Computer Environmental Control",
    "wof:placetype":"venue"
},
  "geometry": {"coordinates":[-84.250985,39.046701],"type":"Point"}
}