{
  "type": "Feature",
  "properties": {
    "addr:full": "5422 Patriot Dr Toledo OH 43611",
    "addr:housenumber": "5422",
    "addr:postcode": "43611",
    "addr:street": "Patriot Dr",
    "iso:country": "US",
    "sg:address": "5422 Patriot Dr",
    "sg:city": "Toledo",
    "sg:classifiers": [
      {
        "category": "Manufacturing",
        "subcategory": "Tools \u0026 Machinery",
        "type": "Manufacturing \u0026 Wholesale Goods"
      }
    ],
    "sg:phone": "+1 419 875 4219",
    "sg:postcode": "43611",
    "sg:province": "OH",
    "sg:tags": [
      "machine",
      "shop"
    ],
    "wof:name": "Neapolis Tool \u0026 Die Inc",
    "wof:placetype": "venue"
  },
  "geometry": {"coordinates":[-83.490728,41.7224],"type":"Point"}
}
