{
  "type": "Feature",
  "properties": {
    "addr:full": "6610 Covington Cove Canfield OH 44406",
    "addr:housenumber": "6610",
    "addr:postcode": "44406",
    "addr:street": "Covington Cove",
    "iso:country": "US",
    "sg:address": "6610 Covington Cove",
    "sg:city": "Canfield",
    "sg:classifiers": [
      {
        "category": "Building \u0026 Trades",
        "subcategory": "Construction",
        "type": "Services"
      }
    ],
    "sg:phone": "+1 330 702 0055",
    "sg:postcode": "44406",
    "sg:province": "OH",
    "sg:tags": [
      "house"
    ],
    "wof:name": "Benson Builders",
    "wof:placetype": "venue"
  },
  "geometry": {"coordinates":[-80.773387,40.989777],"type":"Point"}
}
