{
  "type": "Feature",
  "properties": {
    "addr:full":"2409 Cherry St Toledo OH 43608",
    "addr:housenumber":"2409",
    "addr:postcode":"43608",
    "addr:street":"Cherry St",
    "iso:country":"US",
    "sg:address":"2409 Cherry St",
    "sg:city":"Toledo",
    "sg:classifiers":[
        {
            "category":"Health Services",
            "subcategory":"Doctor",
            "type":"Services"
        }
    ],
    "sg:phone":"+1 419 255 5000",
    "sg:postcode":"43608",
    "sg:province":"OH",
    "sg:tags":[
        "physician",
        "surgeon",
        "medical"
    ],
    "sg:website":"www.intermed-online.org",
    "wof:name":"Intermed Associates Inc",
    "wof:placetype":"venue"
},
  "geometry": {"coordinates":[-83.542919,41.669753],"type":"Point"}
}