{
  "type": "Feature",
  "properties": {
    "iso:country":"US",
    "sg:address":"1081 N University Blvd",
    "sg:city":"Middletown",
    "sg:classifiers":[
        {
            "category":"Banks & Credit Unions",
            "subcategory":"Bank",
            "type":"Services"
        }
    ],
    "sg:phone":"+1 513 705 6448",
    "sg:postcode":"45042",
    "sg:province":"OH",
    "sg:tags":[
        "loan",
        "real estate"
    ],
    "wof:name":"ACF Mortgage",
    "wof:placetype":"venue"
},
  "geometry": {"coordinates":[-84.371132,39.52329],"type":"Point"}
}