{
  "type": "Feature",
  "properties": {
    "iso:country":"US",
    "sg:address":"28479 Standley Rd",
    "sg:city":"Defiance",
    "sg:phone":"+1 419 395 1777",
    "sg:postcode":"43512",
    "sg:province":"OH",
    "sg:tags":[
        "wheat"
    ],
    "wof:name":"Charles Kruse Farm",
    "wof:placetype":"venue"
},
  "geometry": {"coordinates":[-84.274747,41.267932],"type":"Point"}
}