{
  "type": "Feature",
  "properties": {
    "addr:full":"9571 Colerain Ave Cincinnati OH 45251",
    "addr:housenumber":"9571",
    "addr:postcode":"45251",
    "addr:street":"Colerain Ave",
    "iso:country":"US",
    "sg:address":"9571 Colerain Ave",
    "sg:city":"Cincinnati",
    "sg:classifiers":[
        {
            "category":"Shopping",
            "subcategory":"Clothing, Apparel, & Fashions",
            "type":"Retail Goods"
        }
    ],
    "sg:phone":"+1 513 385 6817",
    "sg:postcode":"45251",
    "sg:province":"OH",
    "sg:tags":[
        "accessory"
    ],
    "wof:name":"Claires",
    "wof:placetype":"venue"
},
  "geometry": {"coordinates":[-84.59648900000001,39.247519],"type":"Point"}
}