{
  "type": "Feature",
  "properties": {
    "iso:country":"US",
    "sg:address":"6733 Ridge Rd",
    "sg:city":"Cleveland",
    "sg:classifiers":[
        {
            "category":"Personal",
            "subcategory":"Beauty Salon",
            "type":"Services"
        }
    ],
    "sg:phone":"+1 440 887 0674",
    "sg:postcode":"44129",
    "sg:province":"OH",
    "sg:tags":[
        "nail",
        "manicuring"
    ],
    "wof:name":"Bella Nails",
    "wof:placetype":"venue"
},
  "geometry": {"coordinates":[-81.734675,41.381325],"type":"Point"}
}