{
  "type": "Feature",
  "properties": {
    "iso:country":"US",
    "sg:address":"1327 E 187th St",
    "sg:city":"Cleveland",
    "sg:classifiers":[
        {
            "category":"Shopping",
            "type":"Retail Goods"
        }
    ],
    "sg:phone":"+1 216 531 9095",
    "sg:postcode":"44110",
    "sg:province":"OH",
    "sg:tags":[
        "merchandise"
    ],
    "wof:name":"Gallery Dejanout Fine Arg",
    "wof:placetype":"venue"
},
  "geometry": {"coordinates":[-81.548562,41.568826],"type":"Point"}
}