{
  "type": "Feature",
  "properties": {
    "iso:country":"US",
    "sg:address":"2700 Losantiville Ave",
    "sg:city":"Cincinnati",
    "sg:classifiers":[
        {
            "category":"Retail",
            "subcategory":"Car Wash",
            "type":"Services"
        }
    ],
    "sg:phone":"+1 513 731 0555",
    "sg:postcode":"45213",
    "sg:province":"OH",
    "sg:tags":[
        "polishing",
        "washing"
    ],
    "wof:name":"Total Blessing Auto Detailing",
    "wof:placetype":"venue"
},
  "geometry": {"coordinates":[-84.43866800000001,39.187762],"type":"Point"}
}