{
  "type": "Feature",
  "properties": {
    "addr:full": "7734 Sawmill Rd Dublin OH 43016",
    "addr:housenumber": "7734",
    "addr:postcode": "43016",
    "addr:street": "Sawmill Rd",
    "iso:country": "US",
    "sg:address": "7734 Sawmill Rd",
    "sg:city": "Dublin",
    "sg:classifiers": [
      {
        "category": "Retail",
        "subcategory": "Laundry \u0026 Dry Cleaning",
        "type": "Services"
      }
    ],
    "sg:phone": "+1 614 764 9959",
    "sg:postcode": "43016",
    "sg:province": "OH",
    "sg:tags": [
      "garment",
      "agent"
    ],
    "wof:name": "Swan Super Cleaners",
    "wof:placetype": "venue"
  },
  "geometry": {"coordinates":[-83.090161,40.123134],"type":"Point"}
}
