{
  "type": "Feature",
  "properties": {
    "iso:country":"US",
    "sg:address":"7734 Sawmill Rd",
    "sg:city":"Dublin",
    "sg:classifiers":[
        {
            "category":"Retail",
            "subcategory":"Laundry & Dry Cleaning",
            "type":"Services"
        }
    ],
    "sg:phone":"+1 614 764 9959",
    "sg:postcode":"43016",
    "sg:province":"OH",
    "sg:tags":[
        "garment",
        "agent"
    ],
    "wof:name":"Swan Super Cleaners",
    "wof:placetype":"venue"
},
  "geometry": {"coordinates":[-83.090161,40.123134],"type":"Point"}
}