{
  "type": "Feature",
  "properties": {
    "addr:full":"1201 Havemann Rd Celina OH 45822",
    "addr:housenumber":"1201",
    "addr:postcode":"45822",
    "addr:street":"Havemann Rd",
    "iso:country":"US",
    "sg:address":"1201 Havemann Rd",
    "sg:city":"Celina",
    "sg:classifiers":[
        {
            "category":"Manufacturing",
            "subcategory":"Tools & Machinery",
            "type":"Manufacturing & Wholesale Goods"
        }
    ],
    "sg:phone":"+1 419 586 9023",
    "sg:postcode":"45822",
    "sg:province":"OH",
    "sg:tags":[
        "mold"
    ],
    "wof:name":"Mold Medic",
    "wof:placetype":"venue"
},
  "geometry": {"coordinates":[-84.548524,40.55675],"type":"Point"}
}