{
  "type": "Feature",
  "properties": {
    "addr:full": "27809 State Rte 424 Defiance OH 43512",
    "addr:housenumber": "27809",
    "addr:postcode": "43512",
    "addr:street": "State Rte 424",
    "iso:country": "US",
    "sg:address": "27809 State Rte 424",
    "sg:city": "Defiance",
    "sg:classifiers": [
      {
        "category": "Wholesale",
        "subcategory": "Machinery \u0026 Supplies",
        "type": "Manufacturing \u0026 Wholesale Goods"
      }
    ],
    "sg:phone": "+1 419 782 9911",
    "sg:postcode": "43512",
    "sg:province": "OH",
    "sg:tags": [
      "engine"
    ],
    "sg:website": "www.martindiesel.com",
    "wof:name": "Martin Diesel Svc Inc",
    "wof:placetype": "venue"
  },
  "geometry": {"coordinates":[-84.287852,41.294693],"type":"Point"}
}
