{
  "type": "Feature",
  "properties": {
    "iso:country":"US",
    "sg:address":"27809 State Rte 424",
    "sg:city":"Defiance",
    "sg:classifiers":[
        {
            "category":"Wholesale",
            "subcategory":"Machinery & Supplies",
            "type":"Manufacturing & Wholesale Goods"
        }
    ],
    "sg:phone":"+1 419 782 9911",
    "sg:postcode":"43512",
    "sg:province":"OH",
    "sg:tags":[
        "engine"
    ],
    "sg:website":"www.martindiesel.com",
    "wof:name":"Martin Diesel Svc Inc",
    "wof:placetype":"venue"
},
  "geometry": {"coordinates":[-84.287852,41.294693],"type":"Point"}
}