{
  "type": "Feature",
  "properties": {
    "iso:country":"US",
    "sg:address":"601 Country Manor Dr",
    "sg:city":"North Lima",
    "sg:classifiers":[
        {
            "category":"Real Estate",
            "subcategory":"Real Estate Agent",
            "type":"Services"
        }
    ],
    "sg:phone":"+1 330 549 9981",
    "sg:postcode":"44452",
    "sg:province":"OH",
    "wof:name":"KDP Enterprises",
    "wof:placetype":"venue"
},
  "geometry": {"coordinates":[-80.66425,40.922977],"type":"Point"}
}