{
  "type": "Feature",
  "properties": {
    "addr:full": "2224 State Rte 232 New Richmond OH 45157",
    "addr:housenumber": "2224",
    "addr:postcode": "45157",
    "addr:street": "State Rte 232",
    "iso:country": "US",
    "sg:address": "2224 State Rte 232",
    "sg:city": "New Richmond",
    "sg:phone": "+1 513 553 3049",
    "sg:postcode": "45157",
    "sg:province": "OH",
    "sg:tags": [
      "tobacco",
      "farm",
      "corn",
      "crop",
      "field",
      "soybean"
    ],
    "wof:name": "David Stroub",
    "wof:placetype": "venue"
  },
  "geometry": {"coordinates":[-84.170262,38.933805],"type":"Point"}
}
