{
  "type": "Feature",
  "properties": {
    "addr:full": "2525 Hubbard Rd Madison OH 44057",
    "addr:housenumber": "2525",
    "addr:postcode": "44057",
    "addr:street": "Hubbard Rd",
    "iso:country": "US",
    "sg:address": "2525 Hubbard Rd",
    "sg:city": "Madison",
    "sg:classifiers": [
      {
        "category": "Organizations",
        "subcategory": "Religious Organization",
        "type": "Services"
      }
    ],
    "sg:phone": "+1 440 428 5846",
    "sg:postcode": "44057",
    "sg:province": "OH",
    "sg:tags": [
      "church"
    ],
    "wof:name": "Center Living Word Christian",
    "wof:placetype": "venue"
  },
  "geometry": {"coordinates":[-81.048462,41.806745],"type":"Point"}
}
