{
  "type": "Feature",
  "properties": {
    "iso:country":"US",
    "sg:address":"4333 Westland Mall",
    "sg:city":"Columbus",
    "sg:classifiers":[
        {
            "category":"Shopping",
            "subcategory":"Clothing, Apparel, & Fashions",
            "type":"Retail Goods"
        }
    ],
    "sg:phone":"+1 614 274 4244",
    "sg:postcode":"43228",
    "sg:province":"OH",
    "sg:tags":[
        "item",
        "boutique"
    ],
    "wof:name":"Ladies First",
    "wof:placetype":"venue"
},
  "geometry": {"coordinates":[-83.115155,39.952712],"type":"Point"}
}