{
  "type": "Feature",
  "properties": {
    "iso:country":"US",
    "sg:address":"2507 Mount Vernon Ave",
    "sg:city":"Youngstown",
    "sg:classifiers":[
        {
            "category":"Building & Trades",
            "subcategory":"Landscaping Services",
            "type":"Services"
        }
    ],
    "sg:phone":"+1 330 720 3875",
    "sg:postcode":"44502",
    "sg:province":"OH",
    "sg:tags":[
        "tree"
    ],
    "wof:name":"Affordable Tree Service",
    "wof:placetype":"venue"
},
  "geometry": {"coordinates":[-80.610854,41.061685],"type":"Point"}
}