{
  "type": "Feature",
  "properties": {
    "addr:full": "1055 US Hwy 52 Aberdeen OH 45101",
    "addr:housenumber": "1055",
    "addr:postcode": "45101",
    "addr:street": "Us Hwy 52",
    "iso:country": "US",
    "sg:address": "1055 US Hwy 52",
    "sg:city": "Aberdeen",
    "sg:classifiers": [
      {
        "category": "Travel",
        "subcategory": "Hotels \u0026 Motels",
        "type": "Entertainment"
      }
    ],
    "sg:phone": "+1 937 795 2231",
    "sg:postcode": "45101",
    "sg:province": "OH",
    "wof:name": "Brown's Motel",
    "wof:placetype": "venue"
  },
  "geometry": {"coordinates":[-83.765978,38.658767],"type":"Point"}
}
