{
  "type": "Feature",
  "properties": {
    "iso:country":"US",
    "sg:address":"1055 US Hwy 52",
    "sg:city":"Aberdeen",
    "sg:classifiers":[
        {
            "category":"Travel",
            "subcategory":"Hotels & Motels",
            "type":"Entertainment"
        }
    ],
    "sg:phone":"+1 937 795 2231",
    "sg:postcode":"45101",
    "sg:province":"OH",
    "wof:name":"Brown's Motel",
    "wof:placetype":"venue"
},
  "geometry": {"coordinates":[-83.765978,38.658767],"type":"Point"}
}