{
  "type": "Feature",
  "properties": {
    "addr:full": "14077 Cedar Rd Cleveland OH 44118",
    "addr:housenumber": "14077",
    "addr:postcode": "44118",
    "addr:street": "Cedar Rd",
    "iso:country": "US",
    "sg:address": "14077 Cedar Rd",
    "sg:city": "Cleveland",
    "sg:classifiers": [
      {
        "category": "Professional",
        "subcategory": "Accounting \u0026 Tax Preparation",
        "type": "Services"
      }
    ],
    "sg:phone": "+1 216 932 8400",
    "sg:postcode": "44118",
    "sg:province": "OH",
    "sg:tags": [
      "return",
      "filing"
    ],
    "wof:name": "James Hagerty",
    "wof:placetype": "venue"
  },
  "geometry": {"coordinates":[-81.531342,41.50138],"type":"Point"}
}
