{
  "type": "Feature",
  "properties": {
    "addr:full":"2830 Worrell Rd Willoughby OH 44094",
    "addr:postcode":"2830;44094",
    "addr:street":"Worrell Rd",
    "iso:country":"US",
    "sg:address":"2830 Worrell Rd",
    "sg:city":"Willoughby",
    "sg:classifiers":[
        {
            "category":"Building & Trades",
            "subcategory":"Landscaping Services",
            "type":"Services"
        }
    ],
    "sg:phone":"+1 440 951 8144",
    "sg:postcode":"44094",
    "sg:province":"OH",
    "sg:tags":[
        "landscape",
        "contractor"
    ],
    "wof:name":"Loreto Lafelice Landscaping",
    "wof:placetype":"venue"
},
  "geometry": {"coordinates":[-81.391542,41.580035],"type":"Point"}
}