{
  "type": "Feature",
  "properties": {
    "iso:country":"US",
    "sg:address":"17337 Co Rd 26",
    "sg:city":"Arlington",
    "sg:classifiers":[
        {
            "category":"Utilities",
            "subcategory":"Fuel Oil & Lpg",
            "type":"Services"
        }
    ],
    "sg:phone":"+1 419 423 5998",
    "sg:postcode":"45814",
    "sg:province":"OH",
    "sg:tags":[
        "firewood"
    ],
    "wof:name":"Craft's Tree Svc Inc",
    "wof:placetype":"venue"
},
  "geometry": {"coordinates":[-83.555131,40.935415],"type":"Point"}
}