{
  "type": "Feature",
  "properties": {
    "addr:full": "947 S East St Bucyrus OH 44820",
    "addr:housenumber": "947",
    "addr:postcode": "44820",
    "addr:street": "S East St",
    "iso:country": "US",
    "sg:address": "947 S East St",
    "sg:city": "Bucyrus",
    "sg:classifiers": [
      {
        "category": "Shopping",
        "type": "Retail Goods"
      }
    ],
    "sg:phone": "+1 419 562 5108",
    "sg:postcode": "44820",
    "sg:province": "OH",
    "sg:tags": [
      "merchandise",
      "monument"
    ],
    "wof:name": "Bucyrus Monuments",
    "wof:placetype": "venue"
  },
  "geometry": {"coordinates":[-82.970947,40.7981],"type":"Point"}
}
