{
  "type": "Feature",
  "properties": {
    "addr:full":"5914 Merrill Ave Cleveland OH 44102",
    "addr:housenumber":"5914",
    "addr:postcode":"44102",
    "addr:street":"Merrill Ave",
    "iso:country":"US",
    "sg:address":"5914 Merrill Ave",
    "sg:city":"Cleveland",
    "sg:classifiers":[
        {
            "category":"Manufacturing",
            "subcategory":"Tools & Machinery",
            "type":"Manufacturing & Wholesale Goods"
        },
        {
            "category":"Manufacturing",
            "subcategory":"Electronics",
            "type":"Manufacturing & Wholesale Goods"
        }
    ],
    "sg:phone":"+1 216 631 0912",
    "sg:postcode":"44102",
    "sg:province":"OH",
    "sg:tags":[
        "semiconductor",
        "transformer",
        "component",
        "devices",
        "mfg"
    ],
    "sg:website":"www.darrahelectric.com",
    "wof:name":"Darrah Electric Company",
    "wof:placetype":"venue"
},
  "geometry": {"coordinates":[-81.726562,41.468896],"type":"Point"}
}