{
  "type": "Feature",
  "properties": {
    "iso:country":"US",
    "sg:address":"38669 Mentor Ave",
    "sg:city":"Willoughby",
    "sg:classifiers":[
        {
            "category":"Food & Beverages",
            "subcategory":"Specialty",
            "type":"Retail Goods"
        }
    ],
    "sg:phone":"+1 440 954 8638",
    "sg:postcode":"44094",
    "sg:province":"OH",
    "wof:name":"Just Natural Health Foods",
    "wof:placetype":"venue"
},
  "geometry": {"coordinates":[-81.396168,41.643552],"type":"Point"}
}