{
  "type": "Feature",
  "properties": {
    "addr:full": "210 W Market St Celina OH 45822",
    "addr:housenumber": "210",
    "addr:postcode": "45822",
    "addr:street": "W Market St",
    "iso:country": "US",
    "sg:address": "210 W Market St",
    "sg:city": "Celina",
    "sg:classifiers": [
      {
        "category": "Utilities",
        "subcategory": "Mobile Phone",
        "type": "Services"
      }
    ],
    "sg:phone": "+1 419 584 2355",
    "sg:postcode": "45822",
    "sg:province": "OH",
    "sg:tags": [
      "telephone",
      "cellular"
    ],
    "wof:name": "Cingular Wireless",
    "wof:placetype": "venue"
  },
  "geometry": {"coordinates":[-84.572972,40.548941],"type":"Point"}
}
