{
  "type": "Feature",
  "properties": {
    "iso:country":"US",
    "sg:address":"6200 Pfeiffer Rd",
    "sg:city":"Cincinnati",
    "sg:classifiers":[
        {
            "category":"Health Services",
            "subcategory":"Clinic",
            "type":"Services"
        }
    ],
    "sg:phone":"+1 513 985 6736",
    "sg:postcode":"45242",
    "sg:province":"OH",
    "sg:tags":[
        "holistic",
        "practitioner"
    ],
    "wof:name":"Trihealth Integrative Health",
    "wof:placetype":"venue"
},
  "geometry": {"coordinates":[-84.36439900000001,39.249351],"type":"Point"}
}