{
  "type": "Feature",
  "properties": {
    "addr:full":"107 Columbus Ave Campbell OH 44405",
    "addr:housenumber":"107",
    "addr:postcode":"44405",
    "addr:street":"Columbus Ave",
    "iso:country":"US",
    "sg:address":"107 Columbus Ave",
    "sg:city":"Campbell",
    "sg:classifiers":[
        {
            "category":"Building & Trades",
            "subcategory":"Construction",
            "type":"Services"
        }
    ],
    "sg:phone":"+1 330 744 8227",
    "sg:postcode":"44405",
    "sg:province":"OH",
    "sg:tags":[
        "concrete",
        "contractor"
    ],
    "wof:name":"Advantage Form Concrete",
    "wof:placetype":"venue"
},
  "geometry": {"coordinates":[-80.608529,41.084279],"type":"Point"}
}