{
  "type": "Feature",
  "properties": {
    "addr:full": "134 Maple St Ashland OH 44805",
    "addr:housenumber": "134",
    "addr:postcode": "44805",
    "addr:street": "Maple St",
    "iso:country": "US",
    "sg:address": "134 Maple St",
    "sg:city": "Ashland",
    "sg:classifiers": [
      {
        "category": "Building \u0026 Trades",
        "subcategory": "Construction",
        "type": "Services"
      }
    ],
    "sg:phone": "+1 419 281 6029",
    "sg:postcode": "44805",
    "sg:province": "OH",
    "sg:tags": [
      "house"
    ],
    "wof:name": "Rhino Home Improvements",
    "wof:placetype": "venue"
  },
  "geometry": {"coordinates":[-82.311705,40.867805],"type":"Point"}
}
