{
  "type": "Feature",
  "properties": {
    "iso:country":"US",
    "sg:address":"1929 W 23rd St",
    "sg:city":"Lorain",
    "sg:classifiers":[
        {
            "category":"Organizations",
            "subcategory":"Religious Organization",
            "type":"Services"
        }
    ],
    "sg:phone":"+1 440 960 1021",
    "sg:postcode":"44052",
    "sg:province":"OH",
    "sg:tags":[
        "church"
    ],
    "wof:name":"West Side Baptist Church",
    "wof:placetype":"venue"
},
  "geometry": {"coordinates":[-82.19755499999999,41.448778],"type":"Point"}
}