{
  "type": "Feature",
  "properties": {
    "iso:country":"US",
    "sg:address":"9413 Mount Auburn Ave",
    "sg:city":"Cleveland",
    "sg:classifiers":[
        {
            "category":"Organizations",
            "subcategory":"Religious Organization",
            "type":"Services"
        }
    ],
    "sg:phone":"+1 216 441 4494",
    "sg:postcode":"44104",
    "sg:province":"OH",
    "sg:tags":[
        "church"
    ],
    "wof:name":"Tree Of Life Spiritual Temple",
    "wof:placetype":"venue"
},
  "geometry": {"coordinates":[-81.618272,41.47618],"type":"Point"}
}