{
  "type": "Feature",
  "properties": {
    "addr:full":"8625 W Horseshoe Bend Rd Ludlow Falls OH 45339",
    "addr:housenumber":"8625",
    "addr:postcode":"45339",
    "addr:street":"W Horseshoe Bend Rd",
    "iso:country":"US",
    "sg:address":"8625 W Horseshoe Bend Rd",
    "sg:city":"Ludlow Falls",
    "sg:classifiers":[
        {
            "category":"Professional",
            "type":"Services"
        }
    ],
    "sg:phone":"+1 937 698 4654",
    "sg:postcode":"45339",
    "sg:province":"OH",
    "wof:name":"Brent Kindell",
    "wof:placetype":"venue"
},
  "geometry": {"coordinates":[-84.363361,40.008065],"type":"Point"}
}