{
  "type": "Feature",
  "properties": {
    "iso:country":"US",
    "sg:address":"82 N Court St",
    "sg:city":"Athens",
    "sg:classifiers":[
        {
            "category":"Real Estate",
            "subcategory":"Real Estate Agent",
            "type":"Services"
        }
    ],
    "sg:phone":"+1 740 594 6637",
    "sg:postcode":"45701",
    "sg:province":"OH",
    "sg:website":"www.ohio-realty.com",
    "wof:name":"Ohio Realty",
    "wof:placetype":"venue"
},
  "geometry": {"coordinates":[-82.100841,39.332017],"type":"Point"}
}