{
  "type": "Feature",
  "properties": {
    "iso:country":"US",
    "sg:address":"3080 Alum Creek Dr",
    "sg:city":"Columbus",
    "sg:classifiers":[
        {
            "category":"Shopping",
            "subcategory":"Discount & Variety Stores",
            "type":"Retail Goods"
        }
    ],
    "sg:phone":"+1 614 478 3505",
    "sg:postcode":"43207",
    "sg:province":"OH",
    "sg:tags":[
        "warehouse",
        "distributor"
    ],
    "wof:name":"Value City",
    "wof:placetype":"venue"
},
  "geometry": {"coordinates":[-82.928812,39.904811],"type":"Point"}
}