{
  "type": "Feature",
  "properties": {
    "addr:full": "3250 W Market St Fairlawn OH 44333",
    "addr:housenumber": "3250",
    "addr:postcode": "44333",
    "addr:street": "W Market St",
    "iso:country": "US",
    "sg:address": "3250 W Market St",
    "sg:city": "Fairlawn",
    "sg:classifiers": [
      {
        "category": "Professional",
        "subcategory": "Management \u0026 Consulting",
        "type": "Services"
      }
    ],
    "sg:phone": "+1 330 835 3298",
    "sg:postcode": "44333",
    "sg:province": "OH",
    "sg:tags": [
      "consultant",
      "business"
    ],
    "wof:name": "Diane Denson",
    "wof:placetype": "venue"
  },
  "geometry": {"coordinates":[-81.619372,41.132607],"type":"Point"}
}
