{
  "type": "Feature",
  "properties": {
    "addr:full": "6087 Ashley Lynn Ct Dublin OH 43016",
    "addr:housenumber": "6087",
    "addr:postcode": "43016",
    "addr:street": "Ashley Lynn Ct",
    "iso:country": "US",
    "sg:address": "6087 Ashley Lynn Ct",
    "sg:city": "Dublin",
    "sg:classifiers": [
      {
        "category": "Wholesale",
        "subcategory": "Sporting Goods",
        "type": "Manufacturing \u0026 Wholesale Goods"
      }
    ],
    "sg:phone": "+1 614 799 0891",
    "sg:postcode": "43016",
    "sg:province": "OH",
    "sg:tags": [
      "equipment",
      "golf",
      "supply"
    ],
    "wof:name": "Golden Pacific Inc",
    "wof:placetype": "venue"
  },
  "geometry": {"coordinates":[-83.149892,40.091052],"type":"Point"}
}
