{
  "type": "Feature",
  "properties": {
    "iso:country":"US",
    "sg:address":"6087 Ashley Lynn Ct",
    "sg:city":"Dublin",
    "sg:classifiers":[
        {
            "category":"Wholesale",
            "subcategory":"Sporting Goods",
            "type":"Manufacturing & Wholesale Goods"
        }
    ],
    "sg:phone":"+1 614 799 0891",
    "sg:postcode":"43016",
    "sg:province":"OH",
    "sg:tags":[
        "equipment",
        "golf",
        "supply"
    ],
    "wof:name":"Golden Pacific Inc",
    "wof:placetype":"venue"
},
  "geometry": {"coordinates":[-83.14989199999999,40.091052],"type":"Point"}
}