{
  "type": "Feature",
  "properties": {
    "addr:full": "243 W High St Fostoria OH 44830",
    "addr:housenumber": "243",
    "addr:postcode": "44830",
    "addr:street": "W High St",
    "iso:country": "US",
    "sg:address": "243 W High St",
    "sg:city": "Fostoria",
    "sg:classifiers": [
      {
        "category": "Social Services",
        "type": "Services"
      }
    ],
    "sg:phone": "+1 419 436 9675",
    "sg:postcode": "44830",
    "sg:province": "OH",
    "sg:tags": [
      "organization",
      "welfare"
    ],
    "wof:name": "Fostoria Area Habitat-Humanity",
    "wof:placetype": "venue"
  },
  "geometry": {"coordinates":[-83.418075,41.161737],"type":"Point"}
}
