{
  "type": "Feature",
  "properties": {
    "iso:country":"US",
    "sg:address":"6376 Pearl Rd",
    "sg:city":"Cleveland",
    "sg:classifiers":[
        {
            "category":"Autos & Motor Vehicles",
            "subcategory":"Automobile Sales",
            "type":"Retail Goods"
        }
    ],
    "sg:phone":"+1 440 888 2121",
    "sg:postcode":"44130",
    "sg:province":"OH",
    "sg:tags":[
        "car",
        "dealer"
    ],
    "sg:website":"www.integritychevy.com",
    "wof:name":"Integrity Chevrolet",
    "wof:placetype":"venue"
},
  "geometry": {"coordinates":[-81.765874,41.387772],"type":"Point"}
}