{
  "type": "Feature",
  "properties": {
    "addr:full": "3330 W Elm St Lima OH 45807",
    "addr:housenumber": "3330",
    "addr:postcode": "45807",
    "addr:street": "W Elm St",
    "iso:country": "US",
    "sg:address": "3330 W Elm St",
    "sg:city": "Lima",
    "sg:classifiers": [
      {
        "category": "Shopping",
        "subcategory": "Gifts \u0026 Souvenirs",
        "type": "Retail Goods"
      }
    ],
    "sg:phone": "+1 419 999 3385",
    "sg:postcode": "45807",
    "sg:province": "OH",
    "sg:tags": [
      "shop"
    ],
    "wof:name": "Readmore's Hallmark",
    "wof:placetype": "venue"
  },
  "geometry": {"coordinates":[-84.16617,40.737034],"type":"Point"}
}
