{
  "type": "Feature",
  "properties": {
    "iso:country":"US",
    "sg:address":"3330 W Elm St",
    "sg:city":"Lima",
    "sg:classifiers":[
        {
            "category":"Shopping",
            "subcategory":"Gifts & Souvenirs",
            "type":"Retail Goods"
        }
    ],
    "sg:phone":"+1 419 999 3385",
    "sg:postcode":"45807",
    "sg:province":"OH",
    "sg:tags":[
        "shop"
    ],
    "wof:name":"Readmore's Hallmark",
    "wof:placetype":"venue"
},
  "geometry": {"coordinates":[-84.16616999999999,40.737034],"type":"Point"}
}