{
  "type": "Feature",
  "properties": {
    "iso:country":"US",
    "sg:address":"3117 W Elm St",
    "sg:city":"Lima",
    "sg:classifiers":[
        {
            "category":"Insurance",
            "subcategory":"Insurance Agent",
            "type":"Services"
        }
    ],
    "sg:phone":"+1 419 999 3010",
    "sg:postcode":"45805",
    "sg:province":"OH",
    "wof:name":"State Farm Insurance",
    "wof:placetype":"venue"
},
  "geometry": {"coordinates":[-84.16117,40.736915],"type":"Point"}
}