{
  "type": "Feature",
  "properties": {
    "addr:full":"15443 State Rte 309 Kenton OH 43326",
    "addr:housenumber":"15443",
    "addr:postcode":"43326",
    "addr:street":"State Rte 309",
    "iso:country":"US",
    "sg:address":"15443 State Rte 309",
    "sg:city":"Kenton",
    "sg:classifiers":[
        {
            "category":"Real Estate",
            "subcategory":"Developer",
            "type":"Services"
        }
    ],
    "sg:phone":"+1 419 673 3148",
    "sg:postcode":"43326",
    "sg:province":"OH",
    "sg:tags":[
        "cemetery"
    ],
    "wof:name":"Grove Cemetery",
    "wof:placetype":"venue"
},
  "geometry": {"coordinates":[-83.58680699999999,40.644674],"type":"Point"}
}