{
  "type": "Feature",
  "properties": {
    "addr:full":"6161 Busch Blvd Columbus OH 43229",
    "addr:housenumber":"6161",
    "addr:postcode":"43229",
    "addr:street":"Busch Blvd",
    "iso:country":"US",
    "sg:address":"6161 Busch Blvd",
    "sg:city":"Columbus",
    "sg:classifiers":[
        {
            "category":"Travel",
            "subcategory":"Travel Agent",
            "type":"Entertainment"
        }
    ],
    "sg:phone":"+1 614 885 0200",
    "sg:postcode":"43229",
    "sg:province":"OH",
    "sg:tags":[
        "agency",
        "bureau"
    ],
    "wof:name":"Premier Travel Svc LLC",
    "wof:placetype":"venue"
},
  "geometry": {"coordinates":[-82.99268499999999,40.090008],"type":"Point"}
}