{
  "type": "Feature",
  "properties": {
    "addr:full":"4979 W 130th St Cleveland OH 44135",
    "addr:housenumber":"4979",
    "addr:postcode":"44135",
    "addr:street":"W 130Th St",
    "iso:country":"US",
    "sg:address":"4979 W 130th St",
    "sg:city":"Cleveland",
    "sg:classifiers":[
        {
            "category":"Wholesale",
            "subcategory":"Non-durable Goods",
            "type":"Manufacturing & Wholesale Goods"
        }
    ],
    "sg:phone":"+1 216 433 0578",
    "sg:postcode":"44135",
    "sg:province":"OH",
    "wof:name":"Real Deal-S P Leathers",
    "wof:placetype":"venue"
},
  "geometry": {"coordinates":[-81.78024000000001,41.421687],"type":"Point"}
}