{
  "type": "Feature",
  "properties": {
    "addr:full": "1039 Wilson Ave Steubenville OH 43952",
    "addr:housenumber": "1039",
    "addr:postcode": "43952",
    "addr:street": "Wilson Ave",
    "iso:country": "US",
    "sg:address": "1039 Wilson Ave",
    "sg:city": "Steubenville",
    "sg:classifiers": [
      {
        "category": "Food \u0026 Beverages",
        "subcategory": "Bakery",
        "type": "Retail Goods"
      }
    ],
    "sg:phone": "+1 740 282 1335",
    "sg:postcode": "43952",
    "sg:province": "OH",
    "sg:tags": [
      "baker"
    ],
    "sg:website": "www.nicklesbakery.com",
    "wof:name": "Nickles Bakery Inc",
    "wof:placetype": "venue"
  },
  "geometry": {"coordinates":[-80.628504,40.34758],"type":"Point"}
}
