{
  "type": "Feature",
  "properties": {
    "iso:country":"US",
    "sg:address":"1039 Wilson Ave",
    "sg:city":"Steubenville",
    "sg:classifiers":[
        {
            "category":"Food & Beverages",
            "subcategory":"Bakery",
            "type":"Retail Goods"
        }
    ],
    "sg:phone":"+1 740 282 1335",
    "sg:postcode":"43952",
    "sg:province":"OH",
    "sg:tags":[
        "baker"
    ],
    "sg:website":"www.nicklesbakery.com",
    "wof:name":"Nickles Bakery Inc",
    "wof:placetype":"venue"
},
  "geometry": {"coordinates":[-80.62850400000001,40.34758],"type":"Point"}
}