{
  "type": "Feature",
  "properties": {
    "addr:full": "3024 Plano Rd Washington Court House OH 43160",
    "addr:housenumber": "3024",
    "addr:postcode": "43160",
    "addr:street": "Plano Rd",
    "iso:country": "US",
    "sg:address": "3024 Plano Rd",
    "sg:city": "Washington Court House",
    "sg:classifiers": [
      {
        "category": "Real Estate",
        "subcategory": "Real Estate Operator",
        "type": "Services"
      }
    ],
    "sg:phone": "+1 740 998 4516",
    "sg:postcode": "43160",
    "sg:province": "OH",
    "sg:tags": [
      "property",
      "lessor"
    ],
    "wof:name": "Dawson Carlon Farm",
    "wof:placetype": "venue"
  },
  "geometry": {"coordinates":[-83.233734,39.455313],"type":"Point"}
}
