{
  "type": "Feature",
  "properties": {
    "iso:country":"US",
    "sg:address":"3717 Venice Rd",
    "sg:city":"Sandusky",
    "sg:classifiers":[
        {
            "category":"Restaurant",
            "type":"Food & Drink"
        },
        {
            "category":"Ice Cream",
            "type":"Food & Drink"
        }
    ],
    "sg:phone":"+1 419 625 4376",
    "sg:postcode":"44870",
    "sg:province":"OH",
    "sg:tags":[
        "frozen",
        "traditional",
        "american",
        "yogurt",
        "flavor",
        "local"
    ],
    "sg:website":"www.toftdairy.com",
    "wof:name":"Toft Dairy",
    "wof:placetype":"venue"
},
  "geometry": {"coordinates":[-82.75129699999999,41.441601],"type":"Point"}
}