{
  "type": "Feature",
  "properties": {
    "addr:full": "3717 Venice Rd Sandusky OH 44870",
    "addr:housenumber": "3717",
    "addr:postcode": "44870",
    "addr:street": "Venice Rd",
    "iso:country": "US",
    "sg:address": "3717 Venice Rd",
    "sg:city": "Sandusky",
    "sg:classifiers": [
      {
        "category": "Restaurant",
        "type": "Food \u0026 Drink"
      },
      {
        "category": "Ice Cream",
        "type": "Food \u0026 Drink"
      }
    ],
    "sg:phone": "+1 419 625 4376",
    "sg:postcode": "44870",
    "sg:province": "OH",
    "sg:tags": [
      "frozen",
      "traditional",
      "american",
      "yogurt",
      "flavor",
      "local"
    ],
    "sg:website": "www.toftdairy.com",
    "wof:name": "Toft Dairy",
    "wof:placetype": "venue"
  },
  "geometry": {"coordinates":[-82.751297,41.441601],"type":"Point"}
}
