{
  "type": "Feature",
  "properties": {
    "iso:country":"US",
    "sg:address":"977 Co Rd 8",
    "sg:city":"Liberty Center",
    "sg:classifiers":[
        {
            "category":"Utilities",
            "subcategory":"Refuse",
            "type":"Services"
        }
    ],
    "sg:phone":"+1 419 533 2372",
    "sg:postcode":"43532",
    "sg:province":"OH",
    "sg:tags":[
        "garbage",
        "collection"
    ],
    "wof:name":"Select Sanitation",
    "wof:placetype":"venue"
},
  "geometry": {"coordinates":[-84.018479,41.479543],"type":"Point"}
}