{
  "type": "Feature",
  "properties": {
    "addr:full":"8165 Airport Hwy Holland OH 43528",
    "addr:housenumber":"8165",
    "addr:postcode":"43528",
    "addr:street":"Airport Hwy",
    "iso:country":"US",
    "sg:address":"8165 Airport Hwy",
    "sg:city":"Holland",
    "sg:classifiers":[
        {
            "category":"Restaurant",
            "type":"Food & Drink"
        }
    ],
    "sg:phone":"+1 419 865 8387",
    "sg:postcode":"43528",
    "sg:province":"OH",
    "wof:name":"Albon Inn Again",
    "wof:placetype":"venue"
},
  "geometry": {"coordinates":[-83.73155,41.610291],"type":"Point"}
}