{
  "type": "Feature",
  "properties": {
    "addr:full":"323 Myrtle Ave Newark OH 43055",
    "addr:housenumber":"323",
    "addr:postcode":"43055",
    "addr:street":"Myrtle Ave",
    "iso:country":"US",
    "sg:address":"323 Myrtle Ave",
    "sg:city":"Newark",
    "sg:classifiers":[
        {
            "category":"Wholesale",
            "subcategory":"Non-durable Goods",
            "type":"Manufacturing & Wholesale Goods"
        }
    ],
    "sg:phone":"+1 740 344 1500",
    "sg:postcode":"43055",
    "sg:province":"OH",
    "sg:tags":[
        "advertising"
    ],
    "wof:name":"LTL Maintenance Supply",
    "wof:placetype":"venue"
},
  "geometry": {"coordinates":[-82.43056,40.091864],"type":"Point"}
}