{
  "type": "Feature",
  "properties": {
    "addr:full":"4461 Bascule Bridge Dr Dayton OH 45440",
    "addr:housenumber":"4461",
    "addr:postcode":"45440",
    "addr:street":"Bascule Bridge Dr",
    "iso:country":"US",
    "sg:address":"4461 Bascule Bridge Dr",
    "sg:city":"Dayton",
    "sg:classifiers":[
        {
            "category":"Food & Beverages",
            "subcategory":"Specialty",
            "type":"Retail Goods"
        }
    ],
    "sg:phone":"+1 937 426 3623",
    "sg:postcode":"45440",
    "sg:province":"OH",
    "sg:tags":[
        "health",
        "diet"
    ],
    "wof:name":"Thomas Phillip LLC",
    "wof:placetype":"venue"
},
  "geometry": {"coordinates":[-84.100397,39.690844],"type":"Point"}
}