{
  "type": "Feature",
  "properties": {
    "addr:full": "18613 Rockland Ave Cleveland OH 44135",
    "addr:housenumber": "18613",
    "addr:postcode": "44135",
    "addr:street": "Rockland Ave",
    "iso:country": "US",
    "sg:address": "18613 Rockland Ave",
    "sg:city": "Cleveland",
    "sg:classifiers": [
      {
        "category": "Retail",
        "subcategory": "Animal Services",
        "type": "Services"
      }
    ],
    "sg:phone": "+1 216 898 9137",
    "sg:postcode": "44135",
    "sg:province": "OH",
    "wof:name": "Dog Gone Good Grooming",
    "wof:placetype": "venue"
  },
  "geometry": {"coordinates":[-81.83198,41.429111],"type":"Point"}
}
