{
  "type": "Feature",
  "properties": {
    "iso:country":"US",
    "sg:address":"2373 Venice Blvd",
    "sg:city":"Fairfield",
    "sg:classifiers":[
        {
            "category":"Building & Trades",
            "subcategory":"Construction",
            "type":"Services"
        }
    ],
    "sg:phone":"+1 513 738 4113",
    "sg:postcode":"45014",
    "sg:province":"OH",
    "sg:tags":[
        "concrete",
        "contractor"
    ],
    "wof:name":"Flat Rock Concrete Cnstr",
    "wof:placetype":"venue"
},
  "geometry": {"coordinates":[-84.645371,39.31412],"type":"Point"}
}