{
  "type": "Feature",
  "properties": {
    "addr:full": "3710 E 93rd St Cleveland OH 44105",
    "addr:housenumber": "3710",
    "addr:postcode": "44105",
    "addr:street": "E 93Rd St",
    "iso:country": "US",
    "sg:address": "3710 E 93rd St",
    "sg:city": "Cleveland",
    "sg:classifiers": [
      {
        "category": "Manufacturing",
        "subcategory": "Tools \u0026 Machinery",
        "type": "Manufacturing \u0026 Wholesale Goods"
      }
    ],
    "sg:phone": "+1 216 883 5800",
    "sg:postcode": "44105",
    "sg:province": "OH",
    "sg:tags": [
      "machine",
      "shop"
    ],
    "wof:name": "Dye Service",
    "wof:placetype": "venue"
  },
  "geometry": {"coordinates":[-81.621476,41.457874],"type":"Point"}
}
