{
  "type": "Feature",
  "properties": {
    "iso:country":"US",
    "sg:address":"3710 E 93rd St",
    "sg:city":"Cleveland",
    "sg:classifiers":[
        {
            "category":"Manufacturing",
            "subcategory":"Tools & Machinery",
            "type":"Manufacturing & Wholesale Goods"
        }
    ],
    "sg:phone":"+1 216 883 5800",
    "sg:postcode":"44105",
    "sg:province":"OH",
    "sg:tags":[
        "machine",
        "shop"
    ],
    "wof:name":"Dye Service",
    "wof:placetype":"venue"
},
  "geometry": {"coordinates":[-81.621476,41.457874],"type":"Point"}
}