{
  "type": "Feature",
  "properties": {
    "iso:country":"US",
    "sg:address":"4094 Klein Ave",
    "sg:city":"Stow",
    "sg:classifiers":[
        {
            "category":"Autos & Motor Vehicles",
            "subcategory":"Motorcycle Sales",
            "type":"Retail Goods"
        }
    ],
    "sg:phone":"+1 330 688 7738",
    "sg:postcode":"44224",
    "sg:province":"OH",
    "wof:name":"Wild Stallion Custom Cycle",
    "wof:placetype":"venue"
},
  "geometry": {"coordinates":[-81.43000600000001,41.173604],"type":"Point"}
}