{
  "type": "Feature",
  "properties": {
    "addr:full":"626 Broadway Ave Bedford OH 44146",
    "addr:housenumber":"626",
    "addr:postcode":"44146",
    "addr:street":"Broadway Ave",
    "iso:country":"US",
    "sg:address":"626 Broadway Ave",
    "sg:city":"Bedford",
    "sg:classifiers":[
        {
            "category":"Autos & Motor Vehicles",
            "subcategory":"Automobile Sales",
            "type":"Retail Goods"
        }
    ],
    "sg:phone":"+1 440 439 3399",
    "sg:postcode":"44146",
    "sg:province":"OH",
    "sg:tags":[
        "used"
    ],
    "wof:name":"Thomas Used Cars",
    "wof:placetype":"venue"
},
  "geometry": {"coordinates":[-81.53909400000001,41.394969],"type":"Point"}
}