{
  "type": "Feature",
  "properties": {
    "addr:full": "1542 Apgar Rd Milford OH 45150",
    "addr:housenumber": "1542",
    "addr:postcode": "45150",
    "addr:street": "Apgar Rd",
    "iso:country": "US",
    "sg:address": "1542 Apgar Rd",
    "sg:city": "Milford",
    "sg:classifiers": [
      {
        "category": "Professional",
        "subcategory": "Business Services",
        "type": "Services"
      }
    ],
    "sg:phone": "+1 513 575 3535",
    "sg:postcode": "45150",
    "sg:province": "OH",
    "sg:tags": [
      "painter",
      "sign"
    ],
    "wof:name": "Shaw Signs",
    "wof:placetype": "venue"
  },
  "geometry": {"coordinates":[-84.204517,39.154636],"type":"Point"}
}
