{
  "type": "Feature",
  "properties": {
    "addr:full":"2005 Columbus Ave Springfield OH 45503",
    "addr:housenumber":"2005",
    "addr:postcode":"45503",
    "addr:street":"Columbus Ave",
    "iso:country":"US",
    "sg:address":"2005 Columbus Ave",
    "sg:city":"Springfield",
    "sg:classifiers":[
        {
            "category":"Personal",
            "subcategory":"Barber",
            "type":"Services"
        }
    ],
    "sg:phone":"+1 937 324 1832",
    "sg:postcode":"45503",
    "sg:province":"OH",
    "wof:name":"Rite Cut",
    "wof:placetype":"venue"
},
  "geometry": {"coordinates":[-83.777215,39.932034],"type":"Point"}
}