{
  "type": "Feature",
  "properties": {
    "iso:country":"US",
    "sg:address":"200 W Broadway St",
    "sg:city":"Dover",
    "sg:classifiers":[
        {
            "category":"Manufacturing",
            "subcategory":"Metals",
            "type":"Manufacturing & Wholesale Goods"
        }
    ],
    "sg:phone":"+1 330 343 8841",
    "sg:postcode":"44622",
    "sg:province":"OH",
    "sg:tags":[
        "product",
        "wire",
        "fabricated"
    ],
    "wof:name":"GE Co",
    "wof:placetype":"venue"
},
  "geometry": {"coordinates":[-81.47368299999999,40.518005],"type":"Point"}
}