{
  "type": "Feature",
  "properties": {
    "addr:full": "200 W Broadway St Dover OH 44622",
    "addr:housenumber": "200",
    "addr:postcode": "44622",
    "addr:street": "W Broadway St",
    "iso:country": "US",
    "sg:address": "200 W Broadway St",
    "sg:city": "Dover",
    "sg:classifiers": [
      {
        "category": "Manufacturing",
        "subcategory": "Metals",
        "type": "Manufacturing \u0026 Wholesale Goods"
      }
    ],
    "sg:phone": "+1 330 343 8841",
    "sg:postcode": "44622",
    "sg:province": "OH",
    "sg:tags": [
      "product",
      "wire",
      "fabricated"
    ],
    "wof:name": "GE Co",
    "wof:placetype": "venue"
  },
  "geometry": {"coordinates":[-81.473683,40.518005],"type":"Point"}
}
