{
  "type": "Feature",
  "properties": {
    "addr:full":"10116 Stookesberry Rd Lisbon OH 44432",
    "addr:housenumber":"10116",
    "addr:postcode":"44432",
    "addr:street":"Stookesberry Rd",
    "iso:country":"US",
    "sg:address":"10116 Stookesberry Rd",
    "sg:city":"Lisbon",
    "sg:classifiers":[
        {
            "category":"Manufacturing",
            "subcategory":"Metals",
            "type":"Manufacturing & Wholesale Goods"
        }
    ],
    "sg:phone":"+1 330 424 9666",
    "sg:postcode":"44432",
    "sg:province":"OH",
    "sg:tags":[
        "steel",
        "fabricator"
    ],
    "wof:name":"Welding Improvement Company",
    "wof:placetype":"venue"
},
  "geometry": {"coordinates":[-80.74388,40.753852],"type":"Point"}
}