{
  "type": "Feature",
  "properties": {
    "addr:full": "30946 Hide Away Hills Rd Logan OH 43138",
    "addr:housenumber": "30946",
    "addr:postcode": "43138",
    "addr:street": "Hide Away Hills Rd",
    "iso:country": "US",
    "sg:address": "30946 Hide Away Hills Rd",
    "sg:city": "Logan",
    "sg:classifiers": [
      {
        "category": "Wholesale",
        "subcategory": "Auto Parts",
        "type": "Manufacturing \u0026 Wholesale Goods"
      }
    ],
    "sg:phone": "+1 740 569 4566",
    "sg:postcode": "43138",
    "sg:province": "OH",
    "sg:tags": [
      "used"
    ],
    "wof:name": "Daubenmire Used Auto Parts",
    "wof:placetype": "venue"
  },
  "geometry": {"coordinates":[-82.435027,39.642589],"type":"Point"}
}
