{
  "type": "Feature",
  "properties": {
    "iso:country":"US",
    "sg:address":"8724 Olde Worthington Rd",
    "sg:city":"Westerville",
    "sg:classifiers":[
        {
            "category":"Building & Trades",
            "subcategory":"Construction",
            "type":"Services"
        }
    ],
    "sg:phone":"+1 614 891 4900",
    "sg:postcode":"43082",
    "sg:province":"OH",
    "sg:tags":[
        "general",
        "contractor"
    ],
    "wof:name":"Rajan Inc",
    "wof:placetype":"venue"
},
  "geometry": {"coordinates":[-82.95948199999999,40.144703],"type":"Point"}
}