{
  "type": "Feature",
  "properties": {
    "addr:full": "8724 Olde Worthington Rd Westerville OH 43082",
    "addr:housenumber": "8724",
    "addr:postcode": "43082",
    "addr:street": "Olde Worthington Rd",
    "iso:country": "US",
    "sg:address": "8724 Olde Worthington Rd",
    "sg:city": "Westerville",
    "sg:classifiers": [
      {
        "category": "Building \u0026 Trades",
        "subcategory": "Construction",
        "type": "Services"
      }
    ],
    "sg:phone": "+1 614 891 4900",
    "sg:postcode": "43082",
    "sg:province": "OH",
    "sg:tags": [
      "general",
      "contractor"
    ],
    "wof:name": "Rajan Inc",
    "wof:placetype": "venue"
  },
  "geometry": {"coordinates":[-82.959482,40.144703],"type":"Point"}
}
