{
  "type": "Feature",
  "properties": {
    "addr:full": "2801 W Bancroft St Toledo OH 43606",
    "addr:housenumber": "2801",
    "addr:postcode": "43606",
    "addr:street": "W Bancroft St",
    "iso:country": "US",
    "sg:address": "2801 W Bancroft St",
    "sg:city": "Toledo",
    "sg:classifiers": [
      {
        "category": "Shopping",
        "subcategory": "Pharmacy",
        "type": "Retail Goods"
      }
    ],
    "sg:phone": "+1 419 530 1910",
    "sg:postcode": "43606",
    "sg:province": "OH",
    "wof:name": "UT Phar Clg Applid Phrmclgy CT",
    "wof:placetype": "venue"
  },
  "geometry": {"coordinates":[-83.611671,41.663033],"type":"Point"}
}
