{
  "type": "Feature",
  "properties": {
    "iso:country":"US",
    "sg:address":"6250 Shier Rings Rd",
    "sg:city":"Dublin",
    "sg:classifiers":[
        {
            "category":"Wholesale",
            "subcategory":"Medical Equipment & Supplies",
            "type":"Manufacturing & Wholesale Goods"
        }
    ],
    "sg:phone":"+1 614 889 2220",
    "sg:postcode":"43016",
    "sg:province":"OH",
    "sg:tags":[
        "distributor",
        "hospital"
    ],
    "wof:name":"Medex Medical Inc",
    "wof:placetype":"venue"
},
  "geometry": {"coordinates":[-83.154183,40.095929],"type":"Point"}
}