{
  "type": "Feature",
  "properties": {
    "addr:full": "342 Wabash Ave S Brewster OH 44613",
    "addr:housenumber": "342",
    "addr:postcode": "44613",
    "addr:street": "Wabash Ave S",
    "iso:country": "US",
    "sg:address": "342 Wabash Ave S",
    "sg:city": "Brewster",
    "sg:classifiers": [
      {
        "category": "Restaurant",
        "type": "Food \u0026 Drink"
      }
    ],
    "sg:phone": "+1 330 767 2024",
    "sg:postcode": "44613",
    "sg:province": "OH",
    "sg:tags": [
      "eating"
    ],
    "wof:name": "J B's Heavenly Treats",
    "wof:placetype": "venue"
  },
  "geometry": {"coordinates":[-81.597851,40.709559],"type":"Point"}
}
