{
  "type": "Feature",
  "properties": {
    "addr:full":"3713 Oakwood Ave Youngstown OH 44515",
    "addr:housenumber":"3713",
    "addr:postcode":"44515",
    "addr:street":"Oakwood Ave",
    "iso:country":"US",
    "sg:address":"3713 Oakwood Ave",
    "sg:city":"Youngstown",
    "sg:classifiers":[
        {
            "category":"Bars & Pubs",
            "type":"Food & Drink"
        }
    ],
    "sg:phone":"+1 330 799 0005",
    "sg:postcode":"44515",
    "sg:province":"OH",
    "sg:tags":[
        "drinking"
    ],
    "wof:name":"Nodays Hideaway Lounge",
    "wof:placetype":"venue"
},
  "geometry": {"coordinates":[-80.71807800000001,41.104835],"type":"Point"}
}