{
  "type": "Feature",
  "properties": {
    "addr:full":"214 N Main St Englewood OH 45322",
    "addr:housenumber":"214",
    "addr:postcode":"45322",
    "addr:street":"N Main St",
    "iso:country":"US",
    "sg:address":"214 N Main St",
    "sg:city":"Englewood",
    "sg:classifiers":[
        {
            "category":"Shopping",
            "subcategory":"Florist",
            "type":"Retail Goods"
        }
    ],
    "sg:phone":"+1 937 836 7576",
    "sg:postcode":"45322",
    "sg:province":"OH",
    "wof:name":"Dutch Heritage Florist",
    "wof:placetype":"venue"
},
  "geometry": {"coordinates":[-84.303049,39.881242],"type":"Point"}
}