{
  "type": "Feature",
  "properties": {
    "iso:country":"US",
    "sg:address":"18 Main St",
    "sg:city":"Kingston",
    "sg:classifiers":[
        {
            "category":"Personal",
            "subcategory":"Barber",
            "type":"Services"
        }
    ],
    "sg:phone":"+1 740 642 2000",
    "sg:postcode":"45644",
    "sg:province":"OH",
    "wof:name":"Kingston Barber Shop",
    "wof:placetype":"venue"
},
  "geometry": {"coordinates":[-82.911073,39.472377],"type":"Point"}
}