{
  "type": "Feature",
  "properties": {
    "iso:country":"US",
    "sg:address":"2285 Warren Rd",
    "sg:city":"Cleveland",
    "sg:classifiers":[
        {
            "category":"Retail",
            "subcategory":"Auto Rental",
            "type":"Services"
        }
    ],
    "sg:phone":"+1 216 529 1100",
    "sg:postcode":"44107",
    "sg:province":"OH",
    "sg:tags":[
        "renting",
        "automobile"
    ],
    "wof:name":"Enterprise Rent A Car",
    "wof:placetype":"venue"
},
  "geometry": {"coordinates":[-81.79764900000001,41.470953],"type":"Point"}
}