{
  "type": "Feature",
  "properties": {
    "addr:full": "900 Harcourt Rd Mount Vernon OH 43050",
    "addr:housenumber": "900",
    "addr:postcode": "43050",
    "addr:street": "Harcourt Rd",
    "iso:country": "US",
    "sg:address": "900 Harcourt Rd",
    "sg:city": "Mount Vernon",
    "sg:classifiers": [
      {
        "category": "Real Estate",
        "subcategory": "Real Estate Operator",
        "type": "Services"
      }
    ],
    "sg:phone": "+1 740 393 1621",
    "sg:postcode": "43050",
    "sg:province": "OH",
    "sg:tags": [
      "mobile",
      "home",
      "site"
    ],
    "wof:name": "Westgate Mobile Home Community",
    "wof:placetype": "venue"
  },
  "geometry": {"coordinates":[-82.508296,40.37582],"type":"Point"}
}
