{
  "type": "Feature",
  "properties": {
    "addr:full":"3805 E Livingston Ave Columbus OH 43227",
    "addr:housenumber":"3805",
    "addr:postcode":"43227",
    "addr:street":"E Livingston Ave",
    "iso:country":"US",
    "sg:address":"3805 E Livingston Ave",
    "sg:city":"Columbus",
    "sg:classifiers":[
        {
            "category":"Autos & Motor Vehicles",
            "subcategory":"Auto Supplies",
            "type":"Retail Goods"
        }
    ],
    "sg:phone":"+1 614 239 1111",
    "sg:postcode":"43227",
    "sg:province":"OH",
    "wof:name":"Advance Auto Parts",
    "wof:placetype":"venue"
},
  "geometry": {"coordinates":[-82.89501199999999,39.945704],"type":"Point"}
}