{
  "type": "Feature",
  "properties": {
    "iso:country":"US",
    "sg:address":"385 Rose Ave",
    "sg:city":"Galena",
    "sg:classifiers":[
        {
            "category":"Organizations",
            "subcategory":"Religious Organization",
            "type":"Services"
        }
    ],
    "sg:phone":"+1 740 965 2724",
    "sg:postcode":"43021",
    "sg:province":"OH",
    "sg:tags":[
        "clergy"
    ],
    "wof:name":"Robert Mazzie",
    "wof:placetype":"venue"
},
  "geometry": {"coordinates":[-82.881075,40.223274],"type":"Point"}
}