{
  "type": "Feature",
  "properties": {
    "addr:full": "1251 N Howard St Akron OH 44310",
    "addr:housenumber": "1251",
    "addr:postcode": "44310",
    "addr:street": "N Howard St",
    "iso:country": "US",
    "sg:address": "1251 N Howard St",
    "sg:city": "Akron",
    "sg:classifiers": [
      {
        "category": "Professional",
        "subcategory": "Lawyer \u0026 Legal Services",
        "type": "Services"
      }
    ],
    "sg:phone": "+1 330 922 8060",
    "sg:postcode": "44310",
    "sg:province": "OH",
    "sg:tags": [
      "attorney"
    ],
    "wof:name": "Robert L Mihiylov",
    "wof:placetype": "venue"
  },
  "geometry": {"coordinates":[-81.511374,41.119326],"type":"Point"}
}
