{
  "type": "Feature",
  "properties": {
    "iso:country":"US",
    "sg:address":"2714 Gibson Dr",
    "sg:city":"Cleveland",
    "sg:classifiers":[
        {
            "category":"Professional",
            "subcategory":"Employment Agencies",
            "type":"Services"
        }
    ],
    "sg:phone":"+1 440 895 9952",
    "sg:postcode":"44116",
    "sg:province":"OH",
    "sg:tags":[
        "help",
        "contractor"
    ],
    "wof:name":"Priority Resources LLC",
    "wof:placetype":"venue"
},
  "geometry": {"coordinates":[-81.872398,41.459912],"type":"Point"}
}