{
  "type": "Feature",
  "properties": {
    "addr:full":"15365 Co Rd R Napoleon OH 43545",
    "addr:housenumber":"15365",
    "addr:postcode":"43545",
    "addr:street":"Co Rd R Napoleon",
    "iso:country":"US",
    "sg:address":"15365 Co Rd R",
    "sg:city":"Napoleon",
    "sg:classifiers":[
        {
            "category":"Farming",
            "subcategory":"Farm",
            "type":"Manufacturing & Wholesale Goods"
        }
    ],
    "sg:phone":"+1 419 592 6132",
    "sg:postcode":"43545",
    "sg:province":"OH",
    "sg:tags":[
        "crop",
        "general"
    ],
    "wof:name":"Mike Vandenberghe",
    "wof:placetype":"venue"
},
  "geometry": {"coordinates":[-84.158176,41.413567],"type":"Point"}
}