{
  "type": "Feature",
  "properties": {
    "iso:country":"US",
    "sg:address":"217 Lela Dr",
    "sg:city":"Mason",
    "sg:classifiers":[
        {
            "category":"Building & Trades",
            "subcategory":"Construction",
            "type":"Services"
        }
    ],
    "sg:phone":"+1 513 398 4121",
    "sg:postcode":"45040",
    "sg:province":"OH",
    "sg:tags":[
        "painting",
        "contractor"
    ],
    "wof:name":"Progressive Painting",
    "wof:placetype":"venue"
},
  "geometry": {"coordinates":[-84.291004,39.359844],"type":"Point"}
}