{
  "type": "Feature",
  "properties": {
    "addr:full":"3281 N Dayton Xenia Rd Dayton OH 45434",
    "addr:housenumber":"3281",
    "addr:postcode":"45434",
    "addr:street":"N Dayton Xenia Rd",
    "iso:country":"US",
    "sg:address":"3281 N Dayton Xenia Rd",
    "sg:city":"Dayton",
    "sg:classifiers":[
        {
            "category":"Restaurant",
            "type":"Food & Drink"
        }
    ],
    "sg:phone":"+1 937 426 1166",
    "sg:postcode":"45434",
    "sg:province":"OH",
    "sg:tags":[
        "eating"
    ],
    "sg:website":"www.friendlys.com",
    "wof:name":"Friendly's",
    "wof:placetype":"venue"
},
  "geometry": {"coordinates":[-84.053977,39.726767],"type":"Point"}
}