{
  "type": "Feature",
  "properties": {
    "iso:country":"US",
    "sg:address":"3797 Morgan Rd",
    "sg:city":"Blanchester",
    "sg:classifiers":[
        {
            "category":"Building & Trades",
            "subcategory":"Landscaping Services",
            "type":"Services"
        }
    ],
    "sg:phone":"+1 937 783 4678",
    "sg:postcode":"45107",
    "sg:province":"OH",
    "sg:tags":[
        "landscape",
        "contractor"
    ],
    "wof:name":"Strong Lawn & Landscape Inc",
    "wof:placetype":"venue"
},
  "geometry": {"coordinates":[-83.926219,39.218348],"type":"Point"}
}