{
  "type": "Feature",
  "properties": {
    "addr:full": "3797 Morgan Rd Blanchester OH 45107",
    "addr:housenumber": "3797",
    "addr:postcode": "45107",
    "addr:street": "Morgan Rd",
    "iso:country": "US",
    "sg:address": "3797 Morgan Rd",
    "sg:city": "Blanchester",
    "sg:classifiers": [
      {
        "category": "Building \u0026 Trades",
        "subcategory": "Landscaping Services",
        "type": "Services"
      }
    ],
    "sg:phone": "+1 937 783 4678",
    "sg:postcode": "45107",
    "sg:province": "OH",
    "sg:tags": [
      "landscape",
      "contractor"
    ],
    "wof:name": "Strong Lawn \u0026 Landscape Inc",
    "wof:placetype": "venue"
  },
  "geometry": {"coordinates":[-83.926219,39.218348],"type":"Point"}
}
