{
  "type": "Feature",
  "properties": {
    "addr:full":"5432 Liberty Square Dr Hamilton OH 45011",
    "addr:housenumber":"5432",
    "addr:postcode":"45011",
    "addr:street":"Liberty Square Dr",
    "iso:country":"US",
    "sg:address":"5432 Liberty Square Dr",
    "sg:city":"Hamilton",
    "sg:classifiers":[
        {
            "category":"Restaurant",
            "type":"Food & Drink"
        }
    ],
    "sg:phone":"+1 513 895 7888",
    "sg:postcode":"45011",
    "sg:province":"OH",
    "sg:tags":[
        "eating"
    ],
    "wof:name":"Panda King",
    "wof:placetype":"venue"
},
  "geometry": {"coordinates":[-84.470935,39.418595],"type":"Point"}
}