{
  "type": "Feature",
  "properties": {
    "addr:full":"943 E Johnstown Rd Columbus OH 43230",
    "addr:housenumber":"943",
    "addr:postcode":"43230",
    "addr:street":"E Johnstown Rd",
    "iso:country":"US",
    "sg:address":"943 E Johnstown Rd",
    "sg:city":"Columbus",
    "sg:classifiers":[
        {
            "category":"Travel",
            "subcategory":"Travel Agent",
            "type":"Entertainment"
        }
    ],
    "sg:phone":"+1 614 939 2376",
    "sg:postcode":"43230",
    "sg:province":"OH",
    "sg:tags":[
        "agency",
        "services-commercial"
    ],
    "wof:name":"Sandel Travel",
    "wof:placetype":"venue"
},
  "geometry": {"coordinates":[-82.862476,40.041796],"type":"Point"}
}