{
  "type": "Feature",
  "properties": {
    "iso:country":"US",
    "sg:address":"23 S Park Pl",
    "sg:city":"Newark",
    "sg:classifiers":[
        {
            "category":"Insurance",
            "subcategory":"Title Insurance",
            "type":"Services"
        }
    ],
    "sg:phone":"+1 740 345 6789",
    "sg:postcode":"43055",
    "sg:province":"OH",
    "sg:tags":[
        "carrier"
    ],
    "wof:name":"Title First Agency Inc",
    "wof:placetype":"venue"
},
  "geometry": {"coordinates":[-82.400913,40.057559],"type":"Point"}
}