{
  "type": "Feature",
  "properties": {
    "addr:full": "33 S James Rd Columbus OH 43213",
    "addr:housenumber": "33",
    "addr:postcode": "43213",
    "addr:street": "S James Rd",
    "iso:country": "US",
    "sg:address": "33 S James Rd",
    "sg:city": "Columbus",
    "sg:classifiers": [
      {
        "category": "Personal",
        "subcategory": "Beauty Salon",
        "type": "Services"
      }
    ],
    "sg:phone": "+1 614 236 9108",
    "sg:postcode": "43213",
    "sg:province": "OH",
    "wof:name": "Unique Design Hair Studio",
    "wof:placetype": "venue"
  },
  "geometry": {"coordinates":[-82.913564,39.971836],"type":"Point"}
}
