{
  "type": "Feature",
  "properties": {
    "addr:full": "121 E Elm St Union City OH 45390",
    "addr:housenumber": "121",
    "addr:postcode": "45390",
    "addr:street": "E Elm St",
    "iso:country": "US",
    "sg:address": "121 E Elm St",
    "sg:city": "Union City",
    "sg:classifiers": [
      {
        "category": "Wholesale",
        "subcategory": "Machinery \u0026 Supplies",
        "type": "Manufacturing \u0026 Wholesale Goods"
      }
    ],
    "sg:phone": "+1 937 968 4858",
    "sg:postcode": "45390",
    "sg:province": "OH",
    "sg:tags": [
      "mop"
    ],
    "sg:website": "www.hastemops.com",
    "wof:name": "Ha Ste Mfg Co",
    "wof:placetype": "venue"
  },
  "geometry": {"coordinates":[-84.805087,40.199491],"type":"Point"}
}
