{
  "type": "Feature",
  "properties": {
    "addr:full": "2207 Kimball Rd SE Canton OH 44707",
    "addr:housenumber": "2207",
    "addr:postcode": "44707",
    "addr:street": "Kimball Rd Se",
    "iso:country": "US",
    "sg:address": "2207 Kimball Rd SE",
    "sg:city": "Canton",
    "sg:classifiers": [
      {
        "category": "Professional",
        "subcategory": "Management \u0026 Consulting",
        "type": "Services"
      }
    ],
    "sg:phone": "+1 330 453 5828",
    "sg:postcode": "44707",
    "sg:province": "OH",
    "sg:tags": [
      "marketing",
      "consultant"
    ],
    "sg:website": "www.rootblast.com",
    "wof:name": "Rootblast International Inc",
    "wof:placetype": "venue"
  },
  "geometry": {"coordinates":[-81.381198,40.774783],"type":"Point"}
}
