{
  "type": "Feature",
  "properties": {
    "addr:full":"70 Fairway Dr Wilmington OH 45177",
    "addr:housenumber":"70",
    "addr:postcode":"45177",
    "addr:street":"Fairway Dr",
    "iso:country":"US",
    "sg:address":"70 Fairway Dr",
    "sg:city":"Wilmington",
    "sg:classifiers":[
        {
            "category":"Professional",
            "subcategory":"Employment Agencies",
            "type":"Services"
        }
    ],
    "sg:phone":"+1 937 382 4900",
    "sg:postcode":"45177",
    "sg:province":"OH",
    "sg:tags":[
        "help",
        "contractor"
    ],
    "wof:name":"Manpower Temporary Svc",
    "wof:placetype":"venue"
},
  "geometry": {"coordinates":[-83.79109800000001,39.452972],"type":"Point"}
}