{
  "type": "Feature",
  "properties": {
    "addr:full":"903 Hunter Ridge Cir Akron OH 44333",
    "addr:housenumber":"903",
    "addr:postcode":"44333",
    "addr:street":"Hunter Ridge Cir",
    "iso:country":"US",
    "sg:address":"903 Hunter Ridge Cir",
    "sg:city":"Akron",
    "sg:classifiers":[
        {
            "category":"Organizations",
            "subcategory":"Community Association",
            "type":"Services"
        }
    ],
    "sg:phone":"+1 330 666 4458",
    "sg:postcode":"44333",
    "sg:province":"OH",
    "wof:name":"Toastmasters International",
    "wof:placetype":"venue"
},
  "geometry": {"coordinates":[-81.625286,41.111714],"type":"Point"}
}