{
  "type": "Feature",
  "properties": {
    "addr:full": "714 E Boundary St Perrysburg OH 43551",
    "addr:housenumber": "714",
    "addr:postcode": "43551",
    "addr:street": "E Boundary St",
    "iso:country": "US",
    "sg:address": "714 E Boundary St",
    "sg:city": "Perrysburg",
    "sg:classifiers": [
      {
        "category": "Real Estate",
        "subcategory": "Real Estate Agent",
        "type": "Services"
      }
    ],
    "sg:phone": "+1 419 874 5804",
    "sg:postcode": "43551",
    "sg:province": "OH",
    "wof:name": "Mnhk Ltd",
    "wof:placetype": "venue"
  },
  "geometry": {"coordinates":[-83.61329,41.55713],"type":"Point"}
}
