{
  "type": "Feature",
  "properties": {
    "addr:full": "664 E Moler St Columbus OH 43207",
    "addr:housenumber": "664",
    "addr:postcode": "43207",
    "addr:street": "E Moler St",
    "iso:country": "US",
    "sg:address": "664 E Moler St",
    "sg:city": "Columbus",
    "sg:classifiers": [
      {
        "category": "Building \u0026 Trades",
        "subcategory": "Construction",
        "type": "Services"
      }
    ],
    "sg:phone": "+1 614 444 1979",
    "sg:postcode": "43207",
    "sg:province": "OH",
    "sg:tags": [
      "contractor"
    ],
    "wof:name": "Robert L Marcum",
    "wof:placetype": "venue"
  },
  "geometry": {"coordinates":[-82.978173,39.934508],"type":"Point"}
}
