{
  "type": "Feature",
  "properties": {
    "addr:full":"144 E Carlton Rd Wintersville OH 43953",
    "addr:housenumber":"144",
    "addr:postcode":"43953",
    "addr:street":"E Carlton Rd",
    "iso:country":"US",
    "sg:address":"144 E Carlton Rd",
    "sg:city":"Wintersville",
    "sg:classifiers":[
        {
            "category":"Shopping",
            "type":"Retail Goods"
        }
    ],
    "sg:phone":"+1 740 264 4993",
    "sg:postcode":"43953",
    "sg:province":"OH",
    "sg:tags":[
        "regalia",
        "fraternal",
        "supply"
    ],
    "wof:name":"Fraternal Crafters",
    "wof:placetype":"venue"
},
  "geometry": {"coordinates":[-80.6788,40.370258],"type":"Point"}
}