{
  "type": "Feature",
  "properties": {
    "addr:full":"4302 Dressler Rd NW Canton OH 44718",
    "addr:housenumber":"4302",
    "addr:postcode":"44718",
    "addr:street":"Dressler Rd Nw",
    "iso:country":"US",
    "sg:address":"4302 Dressler Rd NW",
    "sg:city":"Canton",
    "sg:classifiers":[
        {
            "category":"Building & Trades",
            "subcategory":"Construction",
            "type":"Services"
        }
    ],
    "sg:phone":"+1 330 492 2977",
    "sg:postcode":"44718",
    "sg:province":"OH",
    "sg:tags":[
        "house"
    ],
    "wof:name":"Ww Brady Const Inc",
    "wof:placetype":"venue"
},
  "geometry": {"coordinates":[-81.4349,40.843137],"type":"Point"}
}