{
  "type": "Feature",
  "properties": {
    "addr:full": "18451 Thery Rd Fayetteville OH 45118",
    "addr:housenumber": "18451",
    "addr:postcode": "45118",
    "addr:street": "Thery Rd",
    "iso:country": "US",
    "sg:address": "18451 Thery Rd",
    "sg:city": "Fayetteville",
    "sg:classifiers": [
      {
        "category": "Manufacturing",
        "subcategory": "Tools \u0026 Machinery",
        "type": "Manufacturing \u0026 Wholesale Goods"
      }
    ],
    "sg:phone": "+1 513 875 3680",
    "sg:postcode": "45118",
    "sg:province": "OH",
    "sg:tags": [
      "farm",
      "mfg"
    ],
    "wof:name": "Henry Wall",
    "wof:placetype": "venue"
  },
  "geometry": {"coordinates":[-83.891273,39.133964],"type":"Point"}
}
