{
  "type": "Feature",
  "properties": {
    "addr:full": "4255 Twp Rd 491 Somerset OH 43783",
    "addr:housenumber": "4255",
    "addr:postcode": "43783",
    "addr:street": "Twp Rd 491",
    "iso:country": "US",
    "sg:address": "4255 Twp Rd 491",
    "sg:city": "Somerset",
    "sg:classifiers": [
      {
        "category": "Building \u0026 Trades",
        "subcategory": "Construction",
        "type": "Services"
      }
    ],
    "sg:phone": "+1 740 743 2339",
    "sg:postcode": "43783",
    "sg:province": "OH",
    "sg:tags": [
      "house",
      "nonresidential"
    ],
    "wof:name": "Troyer Builders",
    "wof:placetype": "venue"
  },
  "geometry": {"coordinates":[-82.23635,39.846267],"type":"Point"}
}
