{
  "type": "Feature",
  "properties": {
    "iso:country":"US",
    "sg:address":"4255 Twp Rd 491",
    "sg:city":"Somerset",
    "sg:classifiers":[
        {
            "category":"Building & Trades",
            "subcategory":"Construction",
            "type":"Services"
        }
    ],
    "sg:phone":"+1 740 743 2339",
    "sg:postcode":"43783",
    "sg:province":"OH",
    "sg:tags":[
        "house",
        "nonresidential"
    ],
    "wof:name":"Troyer Builders",
    "wof:placetype":"venue"
},
  "geometry": {"coordinates":[-82.23635,39.846267],"type":"Point"}
}