{
  "type": "Feature",
  "properties": {
    "addr:full": "525 Kennedy Rd Akron OH 44305",
    "addr:housenumber": "525",
    "addr:postcode": "44305",
    "addr:street": "Kennedy Rd",
    "iso:country": "US",
    "sg:address": "525 Kennedy Rd",
    "sg:city": "Akron",
    "sg:classifiers": [
      {
        "category": "Sports \u0026 Exercise",
        "subcategory": "Race Track",
        "type": "Entertainment"
      }
    ],
    "sg:phone": "+1 330 784 1209",
    "sg:postcode": "44305",
    "sg:province": "OH",
    "sg:tags": [
      "equipment",
      "supply"
    ],
    "wof:name": "Crossflags",
    "wof:placetype": "venue"
  },
  "geometry": {"coordinates":[-81.424338,41.06625],"type":"Point"}
}
