{
  "type": "Feature",
  "properties": {
    "iso:country":"US",
    "sg:address":"40 N Arch Ave",
    "sg:city":"Alliance",
    "sg:classifiers":[
        {
            "category":"Organizations",
            "subcategory":"Religious Organization",
            "type":"Services"
        }
    ],
    "sg:phone":"+1 330 821 6648",
    "sg:postcode":"44601",
    "sg:province":"OH",
    "wof:name":"Alliance of Churches Inc",
    "wof:placetype":"venue"
},
  "geometry": {"coordinates":[-81.101404,40.922334],"type":"Point"}
}