{
  "type": "Feature",
  "properties": {
    "addr:full":"12399 Kinsman Rd Newbury OH 44065",
    "addr:housenumber":"12399",
    "addr:postcode":"44065",
    "addr:street":"Kinsman Rd",
    "iso:country":"US",
    "sg:address":"12399 Kinsman Rd",
    "sg:city":"Newbury",
    "sg:classifiers":[
        {
            "category":"Restaurant",
            "type":"Food & Drink"
        }
    ],
    "sg:phone":"+1 440 564 5613",
    "sg:postcode":"44065",
    "sg:province":"OH",
    "sg:tags":[
        "parlor",
        "ice",
        "cream"
    ],
    "wof:name":"Dairy King",
    "wof:placetype":"venue"
},
  "geometry": {"coordinates":[-81.207016,41.465751],"type":"Point"}
}