{
  "type": "Feature",
  "properties": {
    "addr:full": "821 W Fair Ave Lancaster OH 43130",
    "addr:housenumber": "821",
    "addr:postcode": "43130",
    "addr:street": "W Fair Ave",
    "iso:country": "US",
    "sg:address": "821 W Fair Ave",
    "sg:city": "Lancaster",
    "sg:classifiers": [
      {
        "category": "Manufacturing",
        "subcategory": "Signs",
        "type": "Manufacturing \u0026 Wholesale Goods"
      }
    ],
    "sg:phone": "+1 614 834 2072",
    "sg:postcode": "43130",
    "sg:province": "OH",
    "sg:tags": [
      "advertising",
      "specialty"
    ],
    "wof:name": "Sign Co",
    "wof:placetype": "venue"
  },
  "geometry": {"coordinates":[-82.61521,39.72446],"type":"Point"}
}
