{
  "type": "Feature",
  "properties": {
    "iso:country":"US",
    "sg:address":"3574 Elm Rd",
    "sg:city":"Stow",
    "sg:classifiers":[
        {
            "category":"Wholesale",
            "subcategory":"Non-durable Goods",
            "type":"Manufacturing & Wholesale Goods"
        }
    ],
    "sg:phone":"+1 330 688 1506",
    "sg:postcode":"44224",
    "sg:province":"OH",
    "wof:name":"Jlf Worldwide Distributors",
    "wof:placetype":"venue"
},
  "geometry": {"coordinates":[-81.44241,41.16128],"type":"Point"}
}