{
  "type": "Feature",
  "properties": {
    "addr:full": "3574 Elm Rd Stow OH 44224",
    "addr:housenumber": "3574",
    "addr:postcode": "44224",
    "addr:street": "Elm Rd",
    "iso:country": "US",
    "sg:address": "3574 Elm Rd",
    "sg:city": "Stow",
    "sg:classifiers": [
      {
        "category": "Wholesale",
        "subcategory": "Non-durable Goods",
        "type": "Manufacturing \u0026 Wholesale Goods"
      }
    ],
    "sg:phone": "+1 330 688 1506",
    "sg:postcode": "44224",
    "sg:province": "OH",
    "wof:name": "Jlf Worldwide Distributors",
    "wof:placetype": "venue"
  },
  "geometry": {"coordinates":[-81.44241,41.16128],"type":"Point"}
}
