{
  "type": "Feature",
  "properties": {
    "addr:full": "280 Central Ave Mansfield OH 44905",
    "addr:housenumber": "280",
    "addr:postcode": "44905",
    "addr:street": "Central Ave",
    "iso:country": "US",
    "sg:address": "280 Central Ave",
    "sg:city": "Mansfield",
    "sg:classifiers": [
      {
        "category": "Retail",
        "subcategory": "Repair Shop",
        "type": "Services"
      }
    ],
    "sg:phone": "+1 419 522 0100",
    "sg:postcode": "44905",
    "sg:province": "OH",
    "sg:tags": [
      "related"
    ],
    "wof:name": "J R Auto Repair",
    "wof:placetype": "venue"
  },
  "geometry": {"coordinates":[-82.499857,40.766075],"type":"Point"}
}
