{
  "type": "Feature",
  "properties": {
    "iso:country":"US",
    "sg:address":"280 Central Ave",
    "sg:city":"Mansfield",
    "sg:classifiers":[
        {
            "category":"Retail",
            "subcategory":"Repair Shop",
            "type":"Services"
        }
    ],
    "sg:phone":"+1 419 522 0100",
    "sg:postcode":"44905",
    "sg:province":"OH",
    "sg:tags":[
        "related"
    ],
    "wof:name":"J R Auto Repair",
    "wof:placetype":"venue"
},
  "geometry": {"coordinates":[-82.49985700000001,40.766075],"type":"Point"}
}