{
  "type": "Feature",
  "properties": {
    "addr:full": "43 Shadybrook Dr Washington Twp OH 45459",
    "addr:housenumber": "43",
    "addr:postcode": "45459",
    "addr:street": "Shadybrook Dr",
    "iso:country": "US",
    "sg:address": "43 Shadybrook Dr",
    "sg:city": "Washington Twp",
    "sg:classifiers": [
      {
        "category": "Building \u0026 Trades",
        "subcategory": "Landscaping Services",
        "type": "Services"
      }
    ],
    "sg:phone": "+1 937 434 0800",
    "sg:postcode": "45459",
    "sg:province": "OH",
    "sg:tags": [
      "designer",
      "landscape"
    ],
    "wof:name": "Special Effects Landscape Dsgn",
    "wof:placetype": "venue"
  },
  "geometry": {"coordinates":[-84.15928,39.65475],"type":"Point"}
}
