{
  "type": "Feature",
  "properties": {
    "addr:full": "4260 Americana Dr Stow OH 44224",
    "addr:housenumber": "4260",
    "addr:postcode": "44224",
    "addr:street": "Americana Dr",
    "iso:country": "US",
    "sg:address": "4260 Americana Dr",
    "sg:city": "Stow",
    "sg:classifiers": [
      {
        "category": "Real Estate",
        "subcategory": "Real Estate Operator",
        "type": "Services"
      }
    ],
    "sg:phone": "+1 330 928 1974",
    "sg:postcode": "44224",
    "sg:province": "OH",
    "sg:tags": [
      "building",
      "apartment"
    ],
    "wof:name": "Wyoga Lake Towers",
    "wof:placetype": "venue"
  },
  "geometry": {"coordinates":[-81.49224,41.190918],"type":"Point"}
}
