{
  "type": "Feature",
  "properties": {
    "iso:country":"US",
    "sg:address":"3750 Sunburst Ridge Ln",
    "sg:city":"Cincinnati",
    "sg:classifiers":[
        {
            "category":"Professional",
            "type":"Services"
        }
    ],
    "sg:phone":"+1 513 574 0185",
    "sg:postcode":"45248",
    "sg:province":"OH",
    "sg:tags":[
        "establishment"
    ],
    "wof:name":"Bellissemo Limited",
    "wof:placetype":"venue"
},
  "geometry": {"coordinates":[-84.669586,39.162329],"type":"Point"}
}