{
  "type": "Feature",
  "properties": {
    "addr:full":"34960 Center Ridge Rd North Ridgeville OH 44039",
    "addr:housenumber":"34960",
    "addr:postcode":"44039",
    "addr:street":"Center Ridge Rd",
    "iso:country":"US",
    "sg:address":"34960 Center Ridge Rd",
    "sg:city":"North Ridgeville",
    "sg:classifiers":[
        {
            "category":"Health Services",
            "subcategory":"Doctor",
            "type":"Services"
        },
        {
            "category":"Health Services",
            "subcategory":"Medical Lab",
            "type":"Services"
        }
    ],
    "sg:phone":"+1 440 353 3433",
    "sg:postcode":"44039",
    "sg:province":"OH",
    "sg:tags":[
        "laboratory",
        "surgeon",
        "physician"
    ],
    "wof:name":"Westshore Primary Care Assoc",
    "wof:placetype":"venue"
},
  "geometry": {"coordinates":[-82.00182100000001,41.395824],"type":"Point"}
}