{
  "type": "Feature",
  "properties": {
    "addr:full": "11820 Kemper Springs Dr Cincinnati OH 45240",
    "addr:housenumber": "11820",
    "addr:postcode": "45240",
    "addr:street": "Kemper Springs Dr",
    "iso:country": "US",
    "sg:address": "11820 Kemper Springs Dr",
    "sg:city": "Cincinnati",
    "sg:classifiers": [
      {
        "category": "Shopping",
        "subcategory": "Computers \u0026 Home Electronics",
        "type": "Retail Goods"
      }
    ],
    "sg:phone": "+1 513 674 0005",
    "sg:postcode": "45240",
    "sg:province": "OH",
    "sg:tags": [
      "software"
    ],
    "sg:website": "www.sigmanest.com",
    "wof:name": "Sigma TEK Corp",
    "wof:placetype": "venue"
  },
  "geometry": {"coordinates":[-84.532379,39.295442],"type":"Point"}
}
