{
  "type": "Feature",
  "properties": {
    "iso:country":"US",
    "sg:address":"140 Fox Rd",
    "sg:city":"Van Wert",
    "sg:classifiers":[
        {
            "category":"Government",
            "subcategory":"Office",
            "type":"Public Place"
        }
    ],
    "sg:phone":"+1 419 238 0808",
    "sg:postcode":"45891",
    "sg:province":"OH",
    "sg:tags":[
        "county",
        "program",
        "health"
    ],
    "sg:website":"www.vanwertcountyhealth.org",
    "wof:name":"Van WERT County Health Dept",
    "wof:placetype":"venue"
},
  "geometry": {"coordinates":[-84.58508500000001,40.851597],"type":"Point"}
}