{
  "type": "Feature",
  "properties": {
    "addr:full": "19448 State Rte 114 Cloverdale OH 45827",
    "addr:housenumber": "19448",
    "addr:postcode": "45827",
    "addr:street": "State Rte 114",
    "iso:country": "US",
    "sg:address": "19448 State Rte 114",
    "sg:city": "Cloverdale",
    "sg:classifiers": [
      {
        "category": "Farming",
        "subcategory": "Farm",
        "type": "Manufacturing \u0026 Wholesale Goods"
      }
    ],
    "sg:phone": "+1 419 532 2550",
    "sg:postcode": "45827",
    "sg:province": "OH",
    "sg:tags": [
      "crop",
      "general"
    ],
    "wof:name": "Bill Maag Farm",
    "wof:placetype": "venue"
  },
  "geometry": {"coordinates":[-84.23446,40.998489],"type":"Point"}
}
