{
  "type": "Feature",
  "properties": {
    "addr:full": "575 S High St Columbus OH 43215",
    "addr:housenumber": "575",
    "addr:postcode": "43215",
    "addr:street": "S High St",
    "iso:country": "US",
    "sg:address": "575 S High St",
    "sg:city": "Columbus",
    "sg:classifiers": [
      {
        "category": "Professional",
        "subcategory": "Lawyer \u0026 Legal Services",
        "type": "Services"
      }
    ],
    "sg:phone": "+1 614 280 9122",
    "sg:postcode": "43215",
    "sg:province": "OH",
    "sg:tags": [
      "attorney",
      "criminal",
      "law"
    ],
    "sg:website": "http://www.adamgburke.com",
    "wof:name": "Adam G. Burke, Attorney at Law",
    "wof:placetype": "venue"
  },
  "geometry": {"coordinates":[-82.998292,39.950133],"type":"Point"}
}
