{
  "type": "Feature",
  "properties": {
    "iso:country":"US",
    "sg:address":"7240 Oak Dr",
    "sg:city":"Youngstown",
    "sg:classifiers":[
        {
            "category":"Retail",
            "subcategory":"Veterinary Services",
            "type":"Services"
        }
    ],
    "sg:phone":"+1 330 757 7490",
    "sg:postcode":"44514",
    "sg:province":"OH",
    "wof:name":"Denise Ann Igoe Dvm",
    "wof:placetype":"venue"
},
  "geometry": {"coordinates":[-80.607482,41.009627],"type":"Point"}
}