{
  "type": "Feature",
  "properties": {
    "addr:full": "3582 Lytle Rd Cleveland OH 44122",
    "addr:housenumber": "3582",
    "addr:postcode": "44122",
    "addr:street": "Lytle Rd",
    "iso:country": "US",
    "sg:address": "3582 Lytle Rd",
    "sg:city": "Cleveland",
    "sg:classifiers": [
      {
        "category": "Professional",
        "type": "Services"
      }
    ],
    "sg:phone": "+1 216 752 6842",
    "sg:postcode": "44122",
    "sg:province": "OH",
    "wof:name": "William M Toomajian",
    "wof:placetype": "venue"
  },
  "geometry": {"coordinates":[-81.537559,41.462282],"type":"Point"}
}
