{
  "type": "Feature",
  "properties": {
    "addr:full":"5111 State Rte 13 Corning OH 43730",
    "addr:housenumber":"5111",
    "addr:postcode":"43730",
    "addr:street":"State Rte 13",
    "iso:country":"US",
    "sg:address":"5111 State Rte 13",
    "sg:city":"Corning",
    "sg:classifiers":[
        {
            "category":"Shopping",
            "subcategory":"Florist",
            "type":"Retail Goods"
        }
    ],
    "sg:phone":"+1 740 347 4575",
    "sg:postcode":"43730",
    "sg:province":"OH",
    "sg:tags":[
        "greenhouse"
    ],
    "wof:name":"Marolt Florists & Greenhouses",
    "wof:placetype":"venue"
},
  "geometry": {"coordinates":[-82.099917,39.638654],"type":"Point"}
}