{
  "type": "Feature",
  "properties": {
    "addr:full": "423 Summit St NW Warren OH 44483",
    "addr:housenumber": "423",
    "addr:postcode": "44483",
    "addr:street": "Summit St Nw",
    "iso:country": "US",
    "sg:address": "423 Summit St NW",
    "sg:city": "Warren",
    "sg:classifiers": [
      {
        "category": "Building \u0026 Trades",
        "subcategory": "Cleaning \u0026 Sanitation",
        "type": "Services"
      }
    ],
    "sg:phone": "+1 330 394 3671",
    "sg:postcode": "44483",
    "sg:province": "OH",
    "sg:tags": [
      "janitor"
    ],
    "wof:name": "Greentip Landscape",
    "wof:placetype": "venue"
  },
  "geometry": {"coordinates":[-80.825373,41.243685],"type":"Point"}
}
