{
  "type": "Feature",
  "properties": {
    "iso:country":"US",
    "sg:address":"92 Walton Ave",
    "sg:city":"Struthers",
    "sg:classifiers":[
        {
            "category":"Building & Trades",
            "subcategory":"Plumbing",
            "type":"Services"
        },
        {
            "category":"Building & Trades",
            "subcategory":"Construction",
            "type":"Services"
        }
    ],
    "sg:phone":"+1 330 423 1103",
    "sg:postcode":"44471",
    "sg:province":"OH",
    "sg:tags":[
        "plumber",
        "excavation",
        "system",
        "specialty",
        "heating",
        "clean",
        "contractor",
        "air conditioning",
        "boilers-repair"
    ],
    "sg:website":"http://www.bc-contracting.com",
    "wof:name":"BC Contracting",
    "wof:placetype":"venue"
},
  "geometry": {"coordinates":[-80.602009,41.063456],"type":"Point"}
}