{
  "type": "Feature",
  "properties": {
    "iso:country":"US",
    "sg:address":"6690 Ironwood Blvd",
    "sg:city":"Canfield",
    "sg:classifiers":[
        {
            "category":"Travel",
            "subcategory":"Hotels & Motels",
            "type":"Entertainment"
        }
    ],
    "sg:phone":"+1 330 702 1900",
    "sg:postcode":"44406",
    "sg:province":"OH",
    "sg:tags":[
        "lodging"
    ],
    "sg:website":"http://www.youngstowncanfieldsuites.hamptoninn.com",
    "wof:name":"Hampton Inn and Suites",
    "wof:placetype":"venue"
},
  "geometry": {"coordinates":[-80.73687200000001,41.020969],"type":"Point"}
}