{
  "type": "Feature",
  "properties": {
    "addr:full": "7900 E Kemper Rd Cincinnati OH 45249",
    "addr:housenumber": "7900",
    "addr:postcode": "45249",
    "addr:street": "E Kemper Rd",
    "iso:country": "US",
    "sg:address": "7900 E Kemper Rd",
    "sg:city": "Cincinnati",
    "sg:classifiers": [
      {
        "category": "Shopping",
        "subcategory": "Bicycles \u0026 Sporting Goods",
        "type": "Retail Goods"
      }
    ],
    "sg:phone": "+1 513 469 1333",
    "sg:postcode": "45249",
    "sg:province": "OH",
    "sg:tags": [
      "equipment",
      "basketball",
      "playground"
    ],
    "wof:name": "Recreations Outlet",
    "wof:placetype": "venue"
  },
  "geometry": {"coordinates":[-84.347728,39.279572],"type":"Point"}
}
