{
  "type": "Feature",
  "properties": {
    "iso:country":"US",
    "sg:address":"7900 E Kemper Rd",
    "sg:city":"Cincinnati",
    "sg:classifiers":[
        {
            "category":"Shopping",
            "subcategory":"Bicycles & Sporting Goods",
            "type":"Retail Goods"
        }
    ],
    "sg:phone":"+1 513 469 1333",
    "sg:postcode":"45249",
    "sg:province":"OH",
    "sg:tags":[
        "equipment",
        "basketball",
        "playground"
    ],
    "wof:name":"Recreations Outlet",
    "wof:placetype":"venue"
},
  "geometry": {"coordinates":[-84.347728,39.279572],"type":"Point"}
}