{
  "type": "Feature",
  "properties": {
    "addr:full":"12397 Royalton Rd North Royalton OH 44133",
    "addr:housenumber":"12397",
    "addr:postcode":"44133",
    "addr:street":"Royalton Rd",
    "iso:country":"US",
    "sg:address":"12397 Royalton Rd",
    "sg:city":"North Royalton",
    "sg:classifiers":[
        {
            "category":"Shopping",
            "type":"Retail Goods"
        }
    ],
    "sg:phone":"+1 216 952 1403",
    "sg:postcode":"44133",
    "sg:province":"OH",
    "sg:tags":[
        "merchandise"
    ],
    "wof:name":"Zarzycki Audio",
    "wof:placetype":"venue"
},
  "geometry": {"coordinates":[-81.775981,41.316054],"type":"Point"}
}