{
  "type": "Feature",
  "properties": {
    "addr:full": "600 Jacqueline Ct Holland OH 43528",
    "addr:housenumber": "600",
    "addr:postcode": "43528",
    "addr:street": "Jacqueline Ct",
    "iso:country": "US",
    "sg:address": "600 Jacqueline Ct",
    "sg:city": "Holland",
    "sg:classifiers": [
      {
        "category": "Shopping",
        "subcategory": "Bicycles \u0026 Sporting Goods",
        "type": "Retail Goods"
      }
    ],
    "sg:phone": "+1 419 861 1494",
    "sg:postcode": "43528",
    "sg:province": "OH",
    "wof:name": "Carol L Huff",
    "wof:placetype": "venue"
  },
  "geometry": {"coordinates":[-83.739647,41.630942],"type":"Point"}
}
