{
  "type": "Feature",
  "properties": {
    "iso:country":"US",
    "sg:address":"504 S Main St",
    "sg:city":"Rockford",
    "sg:classifiers":[
        {
            "category":"Shopping",
            "subcategory":"Pharmacy",
            "type":"Retail Goods"
        }
    ],
    "sg:phone":"+1 419 363 3630",
    "sg:postcode":"45882",
    "sg:province":"OH",
    "sg:website":"www.schumms.com",
    "wof:name":"Schumm Collectibles",
    "wof:placetype":"venue"
},
  "geometry": {"coordinates":[-84.64634,40.687718],"type":"Point"}
}