{
  "type": "Feature",
  "properties": {
    "addr:full": "393 E Town St Columbus OH 43215",
    "addr:housenumber": "393",
    "addr:postcode": "43215",
    "addr:street": "E Town St",
    "iso:country": "US",
    "sg:address": "393 E Town St",
    "sg:city": "Columbus",
    "sg:classifiers": [
      {
        "category": "Health Services",
        "subcategory": "Doctor",
        "type": "Services"
      }
    ],
    "sg:phone": "+1 614 224 1027",
    "sg:postcode": "43215",
    "sg:province": "OH",
    "sg:tags": [
      "physician",
      "surgeon"
    ],
    "sg:website": "www.thehealthywomanobgyn.com",
    "wof:name": "Healthy Woman",
    "wof:placetype": "venue"
  },
  "geometry": {"coordinates":[-82.989202,39.959971],"type":"Point"}
}
