{
  "type": "Feature",
  "properties": {
    "iso:country":"US",
    "sg:address":"393 E Town St",
    "sg:city":"Columbus",
    "sg:classifiers":[
        {
            "category":"Health Services",
            "subcategory":"Doctor",
            "type":"Services"
        }
    ],
    "sg:phone":"+1 614 224 1027",
    "sg:postcode":"43215",
    "sg:province":"OH",
    "sg:tags":[
        "physician",
        "surgeon"
    ],
    "sg:website":"www.thehealthywomanobgyn.com",
    "wof:name":"Healthy Woman",
    "wof:placetype":"venue"
},
  "geometry": {"coordinates":[-82.98920200000001,39.959971],"type":"Point"}
}