{
  "type": "Feature",
  "properties": {
    "iso:country":"US",
    "sg:address":"500 N Twp Rd 165",
    "sg:city":"Tiffin",
    "sg:classifiers":[
        {
            "category":"Building & Trades",
            "subcategory":"Construction",
            "type":"Services"
        }
    ],
    "sg:phone":"+1 419 448 0600",
    "sg:postcode":"44883",
    "sg:province":"OH",
    "sg:tags":[
        "house"
    ],
    "wof:name":"Goshe Builder Ltd",
    "wof:placetype":"venue"
},
  "geometry": {"coordinates":[-83.093885,41.139212],"type":"Point"}
}