{
  "type": "Feature",
  "properties": {
    "addr:full": "46 Morgan St Oberlin OH 44074",
    "addr:housenumber": "46",
    "addr:postcode": "44074",
    "addr:street": "Morgan St",
    "iso:country": "US",
    "sg:address": "46 Morgan St",
    "sg:city": "Oberlin",
    "sg:classifiers": [
      {
        "category": "Travel",
        "subcategory": "Hotels \u0026 Motels",
        "type": "Entertainment"
      }
    ],
    "sg:phone": "+1 440 774 8033",
    "sg:postcode": "44074",
    "sg:province": "OH",
    "sg:tags": [
      "breakfast",
      "accommodation",
      "bed"
    ],
    "wof:name": "Shurtleff Cottage",
    "wof:placetype": "venue"
  },
  "geometry": {"coordinates":[-82.219475,41.287067],"type":"Point"}
}
