{
  "type": "Feature",
  "properties": {
    "addr:full":"4507 Le Saint Ct Fairfield OH 45014",
    "addr:housenumber":"4507",
    "addr:postcode":"45014",
    "addr:street":"Le Saint Ct",
    "iso:country":"US",
    "sg:address":"4507 Le Saint Ct",
    "sg:city":"Fairfield",
    "sg:classifiers":[
        {
            "category":"Manufacturing",
            "subcategory":"Metals",
            "type":"Manufacturing & Wholesale Goods"
        }
    ],
    "sg:phone":"+1 513 942 9910",
    "sg:postcode":"45014",
    "sg:province":"OH",
    "sg:tags":[
        "mfg",
        "fitting",
        "sewer",
        "plastic"
    ],
    "wof:name":"Lasaint Logistics",
    "wof:placetype":"venue"
},
  "geometry": {"coordinates":[-84.47389099999999,39.329358],"type":"Point"}
}