{
  "type": "Feature",
  "properties": {
    "addr:full": "195 Griswold St NE Warren OH 44483",
    "addr:housenumber": "195",
    "addr:postcode": "44483",
    "addr:street": "Griswold St Ne",
    "iso:country": "US",
    "sg:address": "195 Griswold St NE",
    "sg:city": "Warren",
    "sg:phone": "+1 330 399 2919",
    "sg:postcode": "44483",
    "sg:province": "OH",
    "wof:name": "Griswold Body Shop",
    "wof:placetype": "venue"
  },
  "geometry": {"coordinates":[-80.818006,41.249137],"type":"Point"}
}
