{
  "type": "Feature",
  "properties": {
    "addr:full":"3819 Plane Tree Dr W Columbus OH 43228",
    "addr:housenumber":"3819",
    "addr:postcode":"43228",
    "addr:street":"Plane Tree Dr W",
    "iso:country":"US",
    "sg:address":"3819 Plane Tree Dr W",
    "sg:city":"Columbus",
    "sg:classifiers":[
        {
            "category":"Real Estate",
            "subcategory":"Real Estate Operator",
            "type":"Services"
        }
    ],
    "sg:phone":"+1 614 279 8697",
    "sg:postcode":"43228",
    "sg:province":"OH",
    "sg:tags":[
        "building",
        "apartment"
    ],
    "wof:name":"Raccoon Creek Apartments",
    "wof:placetype":"venue"
},
  "geometry": {"coordinates":[-83.098569,39.928383],"type":"Point"}
}