{
  "type": "Feature",
  "properties": {
    "addr:full":"477 Melbourne Ave Youngstown OH 44512",
    "addr:housenumber":"477",
    "addr:postcode":"44512",
    "addr:street":"Melbourne Ave",
    "iso:country":"US",
    "sg:address":"477 Melbourne Ave",
    "sg:city":"Youngstown",
    "sg:classifiers":[
        {
            "category":"Food & Beverages",
            "subcategory":"Groceries & Convenience Stores",
            "type":"Retail Goods"
        }
    ],
    "sg:phone":"+1 330 726 6002",
    "sg:postcode":"44512",
    "sg:province":"OH",
    "wof:name":"Lucky Lotto",
    "wof:placetype":"venue"
},
  "geometry": {"coordinates":[-80.68164299999999,41.03038],"type":"Point"}
}