{
  "type": "Feature",
  "properties": {
    "iso:country":"US",
    "sg:address":"15318 Terrace Rd",
    "sg:city":"Cleveland",
    "sg:classifiers":[
        {
            "category":"Home & Garden",
            "subcategory":"Home Furnishings",
            "type":"Retail Goods"
        }
    ],
    "sg:phone":"+1 216 556 7715",
    "sg:postcode":"44112",
    "sg:province":"OH",
    "wof:name":"Jackson Black Tie",
    "wof:placetype":"venue"
},
  "geometry": {"coordinates":[-81.570866,41.536276],"type":"Point"}
}