{
  "type": "Feature",
  "properties": {
    "addr:full": "20600 Lakeland Blvd Cleveland OH 44119",
    "addr:housenumber": "20600",
    "addr:postcode": "44119",
    "addr:street": "Lakeland Blvd",
    "iso:country": "US",
    "sg:address": "20600 Lakeland Blvd",
    "sg:city": "Cleveland",
    "sg:classifiers": [
      {
        "category": "Retail",
        "subcategory": "Auto Repair",
        "type": "Services"
      }
    ],
    "sg:phone": "+1 216 486 6324",
    "sg:postcode": "44119",
    "sg:province": "OH",
    "sg:tags": [
      "body",
      "automobile",
      "painting"
    ],
    "wof:name": "Suburban Collision Svc",
    "wof:placetype": "venue"
  },
  "geometry": {"coordinates":[-81.533766,41.583601],"type":"Point"}
}
