{
  "type": "Feature",
  "properties": {
    "iso:country":"US",
    "sg:address":"16755 Chagrin Blvd",
    "sg:city":"Cleveland",
    "sg:classifiers":[
        {
            "category":"Cinema",
            "subcategory":"Movie Rental",
            "type":"Entertainment"
        }
    ],
    "sg:phone":"+1 216 295 9500",
    "sg:postcode":"44120",
    "sg:province":"OH",
    "sg:tags":[
        "video",
        "tape"
    ],
    "wof:name":"Blockbuster",
    "wof:placetype":"venue"
},
  "geometry": {"coordinates":[-81.56033600000001,41.464578],"type":"Point"}
}