{
  "type": "Feature",
  "properties": {
    "iso:country":"US",
    "sg:address":"3205 Shreve Rd",
    "sg:city":"Wooster",
    "sg:classifiers":[
        {
            "category":"Education",
            "subcategory":"School",
            "type":"Public Place"
        }
    ],
    "sg:phone":"+1 330 264 9491",
    "sg:postcode":"44691",
    "sg:province":"OH",
    "wof:name":"Triway Local School District",
    "wof:placetype":"venue"
},
  "geometry": {"coordinates":[-81.97495600000001,40.760843],"type":"Point"}
}