{
  "type": "Feature",
  "properties": {
    "addr:full": "3205 Shreve Rd Wooster OH 44691",
    "addr:housenumber": "3205",
    "addr:postcode": "44691",
    "addr:street": "Shreve Rd",
    "iso:country": "US",
    "sg:address": "3205 Shreve Rd",
    "sg:city": "Wooster",
    "sg:classifiers": [
      {
        "category": "Education",
        "subcategory": "School",
        "type": "Public Place"
      }
    ],
    "sg:phone": "+1 330 264 9491",
    "sg:postcode": "44691",
    "sg:province": "OH",
    "wof:name": "Triway Local School District",
    "wof:placetype": "venue"
  },
  "geometry": {"coordinates":[-81.974956,40.760843],"type":"Point"}
}
