{
  "type": "Feature",
  "properties": {
    "iso:country":"US",
    "sg:address":"11700 Pellston Ct",
    "sg:city":"Cincinnati",
    "sg:classifiers":[
        {
            "category":"Shopping",
            "subcategory":"Clothing, Apparel, & Fashions",
            "type":"Retail Goods"
        }
    ],
    "sg:phone":"+1 412 833 4805",
    "sg:postcode":"45240",
    "sg:province":"OH",
    "sg:tags":[
        "woman",
        "wear"
    ],
    "wof:name":"Anntaylor Inc",
    "wof:placetype":"venue"
},
  "geometry": {"coordinates":[-84.520647,39.294154],"type":"Point"}
}