{
  "type": "Feature",
  "properties": {
    "addr:full": "21992 Lorain Rd Cleveland OH 44126",
    "addr:housenumber": "21992",
    "addr:postcode": "44126",
    "addr:street": "Lorain Rd",
    "iso:country": "US",
    "sg:address": "21992 Lorain Rd",
    "sg:city": "Cleveland",
    "sg:classifiers": [
      {
        "category": "Health Services",
        "subcategory": "Podiatrist",
        "type": "Services"
      }
    ],
    "sg:phone": "+1 440 333 7300",
    "sg:postcode": "44126",
    "sg:province": "OH",
    "wof:name": "John M Cuffari DPM",
    "wof:placetype": "venue"
  },
  "geometry": {"coordinates":[-81.863071,41.442233],"type":"Point"}
}
