{
  "type": "Feature",
  "properties": {
    "addr:full": "427 5th St Marietta OH 45750",
    "addr:housenumber": "427",
    "addr:postcode": "45750",
    "addr:street": "5Th St",
    "iso:country": "US",
    "sg:address": "427 5th St",
    "sg:city": "Marietta",
    "sg:classifiers": [
      {
        "category": "Professional",
        "subcategory": "Lawyer \u0026 Legal Services",
        "type": "Services"
      }
    ],
    "sg:phone": "+1 740 373 2414",
    "sg:postcode": "45750",
    "sg:province": "OH",
    "sg:tags": [
      "attorney"
    ],
    "wof:name": "Jennifer D Garrison",
    "wof:placetype": "venue"
  },
  "geometry": {"coordinates":[-81.454746,39.421614],"type":"Point"}
}
