{
  "type": "Feature",
  "properties": {
    "addr:full":"4860 Brecksville Rd Richfield OH 44286",
    "addr:housenumber":"4860",
    "addr:postcode":"44286",
    "addr:street":"Brecksville Rd",
    "iso:country":"US",
    "sg:address":"4860 Brecksville Rd",
    "sg:city":"Richfield",
    "sg:classifiers":[
        {
            "category":"Building & Trades",
            "subcategory":"Construction",
            "type":"Services"
        }
    ],
    "sg:phone":"+1 330 659 9585",
    "sg:postcode":"44286",
    "sg:province":"OH",
    "sg:tags":[
        "general",
        "contractor"
    ],
    "wof:name":"Omega Construction",
    "wof:placetype":"venue"
},
  "geometry": {"coordinates":[-81.628618,41.265616],"type":"Point"}
}