{
  "type": "Feature",
  "properties": {
    "addr:full":"100 E Park Ave Fairfield OH 45036",
    "addr:housenumber":"100",
    "addr:postcode":"45036",
    "addr:street":"E Park Ave",
    "iso:country":"US",
    "sg:address":"100 E Park Ave",
    "sg:city":"Fairfield",
    "sg:classifiers":[
        {
            "category":"Building & Trades",
            "subcategory":"Plumbing",
            "type":"Services"
        }
    ],
    "sg:phone":"+1 513 874 6389",
    "sg:postcode":"45036",
    "sg:province":"OH",
    "sg:tags":[
        "balancing",
        "air"
    ],
    "sg:website":"www.approvedproducts.com",
    "wof:name":"Approved Products Inc",
    "wof:placetype":"venue"
},
  "geometry": {"coordinates":[-84.20649299999999,39.427062],"type":"Point"}
}