{
  "type": "Feature",
  "properties": {
    "addr:full": "10 W 3rd St Frazeysburg OH 43822",
    "addr:housenumber": "10",
    "addr:postcode": "43822",
    "addr:street": "W 3Rd St",
    "iso:country": "US",
    "sg:address": "10 W 3rd St",
    "sg:city": "Frazeysburg",
    "sg:classifiers": [
      {
        "category": "Banks \u0026 Credit Unions",
        "subcategory": "Bank",
        "type": "Services"
      }
    ],
    "sg:phone": "+1 740 828 3401",
    "sg:postcode": "43822",
    "sg:province": "OH",
    "wof:name": "Unizan Bank",
    "wof:placetype": "venue"
  },
  "geometry": {"coordinates":[-82.118896,40.118788],"type":"Point"}
}
