{
  "type": "Feature",
  "properties": {
    "iso:country":"US",
    "sg:address":"1343 S Ohio Ave",
    "sg:city":"Columbus",
    "sg:classifiers":[
        {
            "category":"Professional",
            "type":"Services"
        }
    ],
    "sg:phone":"+1 614 444 1377",
    "sg:postcode":"43206",
    "sg:province":"OH",
    "wof:name":"Roy A Bryant",
    "wof:placetype":"venue"
},
  "geometry": {"coordinates":[-82.972495,39.937342],"type":"Point"}
}