{
  "type": "Feature",
  "properties": {
    "addr:full":"737 Co Rd 30 Tiffin OH 44883",
    "addr:housenumber":"737;30",
    "addr:postcode":"44883",
    "addr:street":"Co Rd",
    "iso:country":"US",
    "sg:address":"737 Co Rd 30",
    "sg:city":"Tiffin",
    "sg:classifiers":[
        {
            "category":"Real Estate",
            "subcategory":"Real Estate Operator",
            "type":"Services"
        }
    ],
    "sg:phone":"+1 419 447 7496",
    "sg:postcode":"44883",
    "sg:province":"OH",
    "sg:tags":[
        "property",
        "lessor"
    ],
    "wof:name":"Harley Shaull",
    "wof:placetype":"venue"
},
  "geometry": {"coordinates":[-83.185751,41.211309],"type":"Point"}
}