{
  "type": "Feature",
  "properties": {
    "iso:country":"US",
    "sg:address":"580 Lincoln Park Blvd",
    "sg:city":"Dayton",
    "sg:classifiers":[
        {
            "category":"Health Services",
            "subcategory":"Doctor",
            "type":"Services"
        }
    ],
    "sg:phone":"+1 937 297 6800",
    "sg:postcode":"45429",
    "sg:province":"OH",
    "sg:tags":[
        "medical"
    ],
    "wof:name":"Zwart Hans M D & Associates",
    "wof:placetype":"venue"
},
  "geometry": {"coordinates":[-84.160168,39.696629],"type":"Point"}
}