{
  "type": "Feature",
  "properties": {
    "addr:full":"1002 Belt Line Ave Cleveland OH 44109",
    "addr:housenumber":"1002",
    "addr:postcode":"44109",
    "addr:street":"Belt Line Ave",
    "iso:country":"US",
    "sg:address":"1002 Belt Line Ave",
    "sg:city":"Cleveland",
    "sg:classifiers":[
        {
            "category":"Manufacturing",
            "subcategory":"Food",
            "type":"Manufacturing & Wholesale Goods"
        }
    ],
    "sg:phone":"+1 216 351 3440",
    "sg:postcode":"44109",
    "sg:province":"OH",
    "sg:tags":[
        "rendering",
        "company"
    ],
    "wof:name":"Ohio By Products",
    "wof:placetype":"venue"
},
  "geometry": {"coordinates":[-81.685715,41.453158],"type":"Point"}
}