{
  "type": "Feature",
  "properties": {
    "addr:full": "873 Williams Ave Columbus OH 43212",
    "addr:housenumber": "873",
    "addr:postcode": "43212",
    "addr:street": "Williams Ave",
    "iso:country": "US",
    "sg:address": "873 Williams Ave",
    "sg:city": "Columbus",
    "sg:classifiers": [
      {
        "category": "Manufacturing",
        "subcategory": "Wood Products",
        "type": "Manufacturing \u0026 Wholesale Goods"
      }
    ],
    "sg:phone": "+1 614 299 1465",
    "sg:postcode": "43212",
    "sg:province": "OH",
    "sg:website": "www.columbuswashboard.com",
    "wof:name": "Columbus Washboard Co",
    "wof:placetype": "venue"
  },
  "geometry": {"coordinates":[-83.029822,39.977985],"type":"Point"}
}
