{
  "type": "Feature",
  "properties": {
    "iso:country":"US",
    "sg:address":"873 Williams Ave",
    "sg:city":"Columbus",
    "sg:classifiers":[
        {
            "category":"Manufacturing",
            "subcategory":"Wood Products",
            "type":"Manufacturing & Wholesale Goods"
        }
    ],
    "sg:phone":"+1 614 299 1465",
    "sg:postcode":"43212",
    "sg:province":"OH",
    "sg:website":"www.columbuswashboard.com",
    "wof:name":"Columbus Washboard Co",
    "wof:placetype":"venue"
},
  "geometry": {"coordinates":[-83.029822,39.977985],"type":"Point"}
}