{
  "type": "Feature",
  "properties": {
    "iso:country":"US",
    "sg:address":"6135 Memorial Dr",
    "sg:city":"Dublin",
    "sg:classifiers":[
        {
            "category":"Professional",
            "subcategory":"Lawyer & Legal Services",
            "type":"Services"
        }
    ],
    "sg:phone":"+1 614 889 0234",
    "sg:postcode":"43017",
    "sg:province":"OH",
    "sg:tags":[
        "attorney"
    ],
    "wof:name":"Kenneth R Sechler",
    "wof:placetype":"venue"
},
  "geometry": {"coordinates":[-83.149503,40.134623],"type":"Point"}
}