{
  "type": "Feature",
  "properties": {
    "addr:full": "1996 Britains Ln Columbus OH 43224",
    "addr:housenumber": "1996",
    "addr:postcode": "43224",
    "addr:street": "Britains Ln",
    "iso:country": "US",
    "sg:address": "1996 Britains Ln",
    "sg:city": "Columbus",
    "sg:classifiers": [
      {
        "category": "Building \u0026 Trades",
        "subcategory": "Landscaping Services",
        "type": "Services"
      }
    ],
    "sg:phone": "+1 614 262 2627",
    "sg:postcode": "43224",
    "sg:province": "OH",
    "sg:tags": [
      "lawn",
      "maintenance",
      "grounds"
    ],
    "wof:name": "Sun Landscaping \u0026 Lawncare",
    "wof:placetype": "venue"
  },
  "geometry": {"coordinates":[-82.961777,40.034521],"type":"Point"}
}
