{
  "type": "Feature",
  "properties": {
    "iso:country":"US",
    "sg:address":"1996 Britains Ln",
    "sg:city":"Columbus",
    "sg:classifiers":[
        {
            "category":"Building & Trades",
            "subcategory":"Landscaping Services",
            "type":"Services"
        }
    ],
    "sg:phone":"+1 614 262 2627",
    "sg:postcode":"43224",
    "sg:province":"OH",
    "sg:tags":[
        "lawn",
        "maintenance",
        "grounds"
    ],
    "wof:name":"Sun Landscaping & Lawncare",
    "wof:placetype":"venue"
},
  "geometry": {"coordinates":[-82.961777,40.034521],"type":"Point"}
}