{
  "type": "Feature",
  "properties": {
    "addr:full": "139 Harmon Ave Lebanon OH 45036",
    "addr:housenumber": "139",
    "addr:postcode": "45036",
    "addr:street": "Harmon Ave",
    "iso:country": "US",
    "sg:address": "139 Harmon Ave",
    "sg:city": "Lebanon",
    "sg:classifiers": [
      {
        "category": "Manufacturing",
        "subcategory": "Rubber \u0026 Plastics",
        "type": "Manufacturing \u0026 Wholesale Goods"
      }
    ],
    "sg:phone": "+1 513 932 6923",
    "sg:postcode": "45036",
    "sg:province": "OH",
    "sg:website": "www.knaufusa.com",
    "wof:name": "Knauf Polystyrene",
    "wof:placetype": "venue"
  },
  "geometry": {"coordinates":[-84.222787,39.434981],"type":"Point"}
}
