{
  "type": "Feature",
  "properties": {
    "addr:full":"744 Southpark Center Cleveland OH 44136",
    "addr:housenumber":"744",
    "addr:postcode":"44136",
    "addr:street":"Southpark Center",
    "iso:country":"US",
    "sg:address":"744 Southpark Center",
    "sg:city":"Cleveland",
    "sg:classifiers":[
        {
            "category":"Utilities",
            "subcategory":"Mobile Phone",
            "type":"Services"
        }
    ],
    "sg:phone":"+1 440 268 9375",
    "sg:postcode":"44136",
    "sg:province":"OH",
    "sg:tags":[
        "telephone",
        "cellular"
    ],
    "wof:name":"T Mobile",
    "wof:placetype":"venue"
},
  "geometry": {"coordinates":[-81.820449,41.310925],"type":"Point"}
}