{
  "type": "Feature",
  "properties": {
    "iso:country":"US",
    "sg:address":"124 N Barron St",
    "sg:city":"Eaton",
    "sg:classifiers":[
        {
            "category":"Professional",
            "subcategory":"Accounting & Tax Preparation",
            "type":"Services"
        }
    ],
    "sg:phone":"+1 937 456 2593",
    "sg:postcode":"45320",
    "sg:province":"OH",
    "sg:tags":[
        "return"
    ],
    "wof:name":"H & R Block",
    "wof:placetype":"venue"
},
  "geometry": {"coordinates":[-84.63641200000001,39.744202],"type":"Point"}
}