{
  "type": "Feature",
  "properties": {
    "addr:full": "124 N Barron St Eaton OH 45320",
    "addr:housenumber": "124",
    "addr:postcode": "45320",
    "addr:street": "N Barron St",
    "iso:country": "US",
    "sg:address": "124 N Barron St",
    "sg:city": "Eaton",
    "sg:classifiers": [
      {
        "category": "Professional",
        "subcategory": "Accounting \u0026 Tax Preparation",
        "type": "Services"
      }
    ],
    "sg:phone": "+1 937 456 2593",
    "sg:postcode": "45320",
    "sg:province": "OH",
    "sg:tags": [
      "return"
    ],
    "wof:name": "H \u0026 R Block",
    "wof:placetype": "venue"
  },
  "geometry": {"coordinates":[-84.636412,39.744202],"type":"Point"}
}
