{
  "type": "Feature",
  "properties": {
    "addr:full":"206 Oak St Cincinnati OH 45219",
    "addr:housenumber":"206",
    "addr:postcode":"45219",
    "addr:street":"Oak St",
    "iso:country":"US",
    "sg:address":"206 Oak St",
    "sg:city":"Cincinnati",
    "sg:classifiers":[
        {
            "category":"Organizations",
            "subcategory":"Religious Organization",
            "type":"Services"
        }
    ],
    "sg:phone":"+1 513 751 4678",
    "sg:postcode":"45219",
    "sg:province":"OH",
    "sg:tags":[
        "clergy"
    ],
    "wof:name":"F M Henderson",
    "wof:placetype":"venue"
},
  "geometry": {"coordinates":[-84.50555,39.131286],"type":"Point"}
}