{
  "type": "Feature",
  "properties": {
    "addr:full":"10355 Pine Gate Dr Chardon OH 44024",
    "addr:housenumber":"10355",
    "addr:postcode":"44024",
    "addr:street":"Pine Gate Dr",
    "iso:country":"US",
    "sg:address":"10355 Pine Gate Dr",
    "sg:city":"Chardon",
    "sg:classifiers":[
        {
            "category":"Cinema",
            "subcategory":"Movie Rental",
            "type":"Entertainment"
        }
    ],
    "sg:phone":"+1 440 286 1900",
    "sg:postcode":"44024",
    "sg:province":"OH",
    "sg:tags":[
        "leasing",
        "video",
        "disc",
        "tape"
    ],
    "wof:name":"Video Innovations",
    "wof:placetype":"venue"
},
  "geometry": {"coordinates":[-81.265923,41.576713],"type":"Point"}
}