{
  "type": "Feature",
  "properties": {
    "iso:country":"US",
    "sg:address":"5640 Cleveland Rd",
    "sg:city":"Wooster",
    "sg:classifiers":[
        {
            "category":"Retail",
            "subcategory":"Auto Repair",
            "type":"Services"
        }
    ],
    "sg:phone":"+1 330 345 5936",
    "sg:postcode":"44691",
    "sg:province":"OH",
    "sg:tags":[
        "body",
        "automobile",
        "painting"
    ],
    "wof:name":"R & K Truck Reconditioning",
    "wof:placetype":"venue"
},
  "geometry": {"coordinates":[-81.92214199999999,40.867942],"type":"Point"}
}