{
  "type": "Feature",
  "properties": {
    "addr:full": "5640 Cleveland Rd Wooster OH 44691",
    "addr:housenumber": "5640",
    "addr:postcode": "44691",
    "addr:street": "Cleveland Rd",
    "iso:country": "US",
    "sg:address": "5640 Cleveland Rd",
    "sg:city": "Wooster",
    "sg:classifiers": [
      {
        "category": "Retail",
        "subcategory": "Auto Repair",
        "type": "Services"
      }
    ],
    "sg:phone": "+1 330 345 5936",
    "sg:postcode": "44691",
    "sg:province": "OH",
    "sg:tags": [
      "body",
      "automobile",
      "painting"
    ],
    "wof:name": "R \u0026 K Truck Reconditioning",
    "wof:placetype": "venue"
  },
  "geometry": {"coordinates":[-81.922142,40.867942],"type":"Point"}
}
