{
  "type": "Feature",
  "properties": {
    "addr:full":"5319 Lakeside Dr Fairfield OH 45014",
    "addr:housenumber":"5319",
    "addr:postcode":"45014",
    "addr:street":"Lakeside Dr",
    "iso:country":"US",
    "sg:address":"5319 Lakeside Dr",
    "sg:city":"Fairfield",
    "sg:classifiers":[
        {
            "category":"Building & Trades",
            "subcategory":"Electrical",
            "type":"Services"
        }
    ],
    "sg:phone":"+1 513 829 0859",
    "sg:postcode":"45014",
    "sg:province":"OH",
    "sg:tags":[
        "electrical",
        "contractor"
    ],
    "wof:name":"Dennys",
    "wof:placetype":"venue"
},
  "geometry": {"coordinates":[-84.587879,39.337347],"type":"Point"}
}