{
  "type": "Feature",
  "properties": {
    "addr:full":"212 Monroe St Port Clinton OH 43452",
    "addr:housenumber":"212",
    "addr:postcode":"43452",
    "addr:street":"Monroe St",
    "iso:country":"US",
    "sg:address":"212 Monroe St",
    "sg:city":"Port Clinton",
    "sg:classifiers":[
        {
            "category":"Retail",
            "subcategory":"Portrait Studio",
            "type":"Services"
        }
    ],
    "sg:phone":"+1 419 732 3412",
    "sg:postcode":"43452",
    "sg:province":"OH",
    "sg:tags":[
        "photographer"
    ],
    "sg:website":"www.focuspointoh.com",
    "wof:name":"Focus Point",
    "wof:placetype":"venue"
},
  "geometry": {"coordinates":[-82.943056,41.511223],"type":"Point"}
}