{
  "type": "Feature",
  "properties": {
    "iso:country":"US",
    "sg:address":"3800 Lorain Ave",
    "sg:city":"Cleveland",
    "sg:classifiers":[
        {
            "category":"Wholesale",
            "subcategory":"Sporting Goods",
            "type":"Manufacturing & Wholesale Goods"
        }
    ],
    "sg:phone":"+1 216 651 3800",
    "sg:postcode":"44113",
    "sg:province":"OH",
    "sg:tags":[
        "parts",
        "bicycle",
        "accessory"
    ],
    "sg:website":"www.fridrichs.com",
    "wof:name":"Fridrich Bicycle Inc",
    "wof:placetype":"venue"
},
  "geometry": {"coordinates":[-81.711848,41.48092],"type":"Point"}
}