{
  "type": "Feature",
  "properties": {
    "addr:full":"1390 Christopher Wren Dr Columbus OH 43230",
    "addr:housenumber":"1390",
    "addr:postcode":"43230",
    "addr:street":"Christopher Wren Dr",
    "iso:country":"US",
    "sg:address":"1390 Christopher Wren Dr",
    "sg:city":"Columbus",
    "sg:classifiers":[
        {
            "category":"Real Estate",
            "subcategory":"Real Estate Operator",
            "type":"Services"
        }
    ],
    "sg:phone":"+1 614 475 1100",
    "sg:postcode":"43230",
    "sg:province":"OH",
    "sg:tags":[
        "building",
        "apartment"
    ],
    "wof:name":"Residence At Christopher Wren",
    "wof:placetype":"venue"
},
  "geometry": {"coordinates":[-82.876212,40.055582],"type":"Point"}
}