{
  "type": "Feature",
  "properties": {
    "iso:country":"US",
    "sg:address":"1501 S Erie Hwy",
    "sg:city":"Hamilton",
    "sg:classifiers":[
        {
            "category":"Food & Beverages",
            "subcategory":"Groceries & Convenience Stores",
            "type":"Retail Goods"
        }
    ],
    "sg:phone":"+1 513 892 7800",
    "sg:postcode":"45011",
    "sg:province":"OH",
    "sg:tags":[
        "grocer"
    ],
    "wof:name":"Glory International Market",
    "wof:placetype":"venue"
},
  "geometry": {"coordinates":[-84.54980399999999,39.380327],"type":"Point"}
}