{
  "type": "Feature",
  "properties": {
    "addr:full": "602 E Center St Marion OH 43302",
    "addr:housenumber": "602",
    "addr:postcode": "43302",
    "addr:street": "E Center St",
    "iso:country": "US",
    "sg:address": "602 E Center St",
    "sg:city": "Marion",
    "sg:classifiers": [
      {
        "category": "Insurance",
        "subcategory": "Insurance Agent",
        "type": "Services"
      }
    ],
    "sg:phone": "+1 740 387 3296",
    "sg:postcode": "43302",
    "sg:province": "OH",
    "sg:tags": [
      "general"
    ],
    "wof:name": "Simpson Insurance Agency Inc",
    "wof:placetype": "venue"
  },
  "geometry": {"coordinates":[-83.114192,40.589274],"type":"Point"}
}
