{
  "type": "Feature",
  "properties": {
    "iso:country":"US",
    "sg:address":"3192 Bates Rd",
    "sg:city":"Madison",
    "sg:classifiers":[
        {
            "category":"Professional",
            "type":"Services"
        }
    ],
    "sg:phone":"+1 440 428 3782",
    "sg:postcode":"44057",
    "sg:province":"OH",
    "wof:name":"Sharon Wood Studio",
    "wof:placetype":"venue"
},
  "geometry": {"coordinates":[-81.030221,41.782854],"type":"Point"}
}