{
  "type": "Feature",
  "properties": {
    "iso:country":"US",
    "sg:address":"113 N Main St",
    "sg:city":"Jenera",
    "sg:classifiers":[
        {
            "category":"Government",
            "subcategory":"Post Office",
            "type":"Public Place"
        }
    ],
    "sg:phone":"+1 419 326 3991",
    "sg:postcode":"45840",
    "sg:province":"OH",
    "wof:name":"US Post Office",
    "wof:placetype":"venue"
},
  "geometry": {"coordinates":[-83.650198,41.041408],"type":"Point"}
}