{
  "type": "Feature",
  "properties": {
    "iso:country":"US",
    "sg:address":"1441 Northview Rd",
    "sg:city":"Cleveland",
    "sg:classifiers":[
        {
            "category":"Organizations",
            "subcategory":"Religious Organization",
            "type":"Services"
        }
    ],
    "sg:phone":"+1 440 331 7883",
    "sg:postcode":"44116",
    "sg:province":"OH",
    "sg:tags":[
        "monastery",
        "convent"
    ],
    "wof:name":"Sisters Of St Joseph CSJ",
    "wof:placetype":"venue"
},
  "geometry": {"coordinates":[-81.847212,41.472225],"type":"Point"}
}