{
  "type": "Feature",
  "properties": {
    "addr:full": "1056 S New Hampshire Ave Wellston OH 45692",
    "addr:housenumber": "1056",
    "addr:postcode": "45692",
    "addr:street": "S New Hampshire Ave",
    "iso:country": "US",
    "sg:address": "1056 S New Hampshire Ave",
    "sg:city": "Wellston",
    "sg:classifiers": [
      {
        "category": "Utilities",
        "subcategory": "Refuse",
        "type": "Services"
      }
    ],
    "sg:phone": "+1 740 384 2164",
    "sg:postcode": "45692",
    "sg:province": "OH",
    "sg:tags": [
      "system",
      "sewerage"
    ],
    "wof:name": "Gjmv",
    "wof:placetype": "venue"
  },
  "geometry": {"coordinates":[-82.527018,39.113639],"type":"Point"}
}
