{
  "type": "Feature",
  "properties": {
    "addr:full":"10621 Briggs Rd Cleveland OH 44111",
    "addr:housenumber":"10621",
    "addr:postcode":"44111",
    "addr:street":"Briggs Rd",
    "iso:country":"US",
    "sg:address":"10621 Briggs Rd",
    "sg:city":"Cleveland",
    "sg:classifiers":[
        {
            "category":"Building & Trades",
            "subcategory":"Construction",
            "type":"Services"
        }
    ],
    "sg:phone":"+1 216 941 0900",
    "sg:postcode":"44111",
    "sg:province":"OH",
    "sg:tags":[
        "general",
        "contractor"
    ],
    "wof:name":"Dobson Construction Inc",
    "wof:placetype":"venue"
},
  "geometry": {"coordinates":[-81.760094,41.448628],"type":"Point"}
}