{
  "type": "Feature",
  "properties": {
    "addr:full": "51 W Main St Richmond OH 43944",
    "addr:housenumber": "51",
    "addr:postcode": "43944",
    "addr:street": "W Main St",
    "iso:country": "US",
    "sg:address": "51 W Main St",
    "sg:city": "Richmond",
    "sg:classifiers": [
      {
        "category": "Food \u0026 Beverages",
        "subcategory": "Groceries \u0026 Convenience Stores",
        "type": "Retail Goods"
      }
    ],
    "sg:phone": "+1 740 765 5111",
    "sg:postcode": "43944",
    "sg:province": "OH",
    "wof:name": "Kenco Quik Mart",
    "wof:placetype": "venue"
  },
  "geometry": {"coordinates":[-80.772708,40.433563],"type":"Point"}
}
