{
  "type": "Feature",
  "properties": {
    "iso:country":"US",
    "sg:address":"51 W Main St",
    "sg:city":"Richmond",
    "sg:classifiers":[
        {
            "category":"Food & Beverages",
            "subcategory":"Groceries & Convenience Stores",
            "type":"Retail Goods"
        }
    ],
    "sg:phone":"+1 740 765 5111",
    "sg:postcode":"43944",
    "sg:province":"OH",
    "wof:name":"Kenco Quik Mart",
    "wof:placetype":"venue"
},
  "geometry": {"coordinates":[-80.77270799999999,40.433563],"type":"Point"}
}