{
  "type": "Feature",
  "properties": {
    "iso:country":"US",
    "sg:address":"3452 US Hwy 50",
    "sg:city":"Williamsburg",
    "sg:classifiers":[
        {
            "category":"Farming",
            "subcategory":"Farm",
            "type":"Manufacturing & Wholesale Goods"
        }
    ],
    "sg:phone":"+1 513 724 3857",
    "sg:postcode":"45176",
    "sg:province":"OH",
    "sg:tags":[
        "crop",
        "general"
    ],
    "wof:name":"Wolfer Farms",
    "wof:placetype":"venue"
},
  "geometry": {"coordinates":[-84.03641,39.138084],"type":"Point"}
}