{
  "type": "Feature",
  "properties": {
    "addr:full":"4141 Morse Xing Columbus OH 43219",
    "addr:housenumber":"4141",
    "addr:postcode":"43219",
    "addr:street":"Morse Xing",
    "iso:country":"US",
    "sg:address":"4141 Morse Xing",
    "sg:city":"Columbus",
    "sg:classifiers":[
        {
            "category":"Professional",
            "type":"Services"
        }
    ],
    "sg:phone":"+1 614 342 2044",
    "sg:postcode":"43219",
    "sg:province":"OH",
    "wof:name":"Huffy Service First Inc",
    "wof:placetype":"venue"
},
  "geometry": {"coordinates":[-82.91894600000001,40.053908],"type":"Point"}
}