{
  "type": "Feature",
  "properties": {
    "iso:country":"US",
    "sg:address":"808 Pro Dr",
    "sg:city":"Celina",
    "sg:classifiers":[
        {
            "category":"Real Estate",
            "subcategory":"Real Estate Operator",
            "type":"Services"
        }
    ],
    "sg:phone":"+1 419 586 7457",
    "sg:postcode":"45822",
    "sg:province":"OH",
    "sg:tags":[
        "apartment"
    ],
    "wof:name":"Villa Allegra Apartments",
    "wof:placetype":"venue"
},
  "geometry": {"coordinates":[-84.55525,40.555213],"type":"Point"}
}