{
  "type": "Feature",
  "properties": {
    "iso:country":"US",
    "sg:address":"1217 Crestwood Hills Dr",
    "sg:city":"Vandalia",
    "sg:classifiers":[
        {
            "category":"Shopping",
            "subcategory":"Hobbies, Toys, & Games",
            "type":"Retail Goods"
        }
    ],
    "sg:phone":"+1 937 890 4954",
    "sg:postcode":"45377",
    "sg:province":"OH",
    "sg:tags":[
        "other",
        "bear",
        "doll"
    ],
    "wof:name":"Antique Attic Dolls By Beth",
    "wof:placetype":"venue"
},
  "geometry": {"coordinates":[-84.19046299999999,39.876205],"type":"Point"}
}