{
  "type": "Feature",
  "properties": {
    "addr:full":"28 City View Dr Sherrodsville OH 44695",
    "addr:housenumber":"28",
    "addr:postcode":"44695",
    "addr:street":"City View Dr",
    "iso:country":"US",
    "sg:address":"28 City View Dr",
    "sg:city":"Sherrodsville",
    "sg:classifiers":[
        {
            "category":"Retail",
            "subcategory":"Auto Repair",
            "type":"Services"
        }
    ],
    "sg:phone":"+1 740 269 4294",
    "sg:postcode":"44695",
    "sg:province":"OH",
    "sg:tags":[
        "body",
        "automobile",
        "painting"
    ],
    "wof:name":"Wilkin's Body Shop",
    "wof:placetype":"venue"
},
  "geometry": {"coordinates":[-81.24150899999999,40.495853],"type":"Point"}
}