{
  "type": "Feature",
  "properties": {
    "iso:country":"US",
    "sg:address":"32135 Cook Rd",
    "sg:city":"North Ridgeville",
    "sg:phone":"+1 440 327 9770",
    "sg:postcode":"44039",
    "sg:province":"OH",
    "sg:tags":[
        "farm",
        "corn",
        "soybean"
    ],
    "wof:name":"Richard Sullinger",
    "wof:placetype":"venue"
},
  "geometry": {"coordinates":[-81.97408299999999,41.384733],"type":"Point"}
}