{
  "type": "Feature",
  "properties": {
    "addr:full": "32135 Cook Rd North Ridgeville OH 44039",
    "addr:housenumber": "32135",
    "addr:postcode": "44039",
    "addr:street": "Cook Rd",
    "iso:country": "US",
    "sg:address": "32135 Cook Rd",
    "sg:city": "North Ridgeville",
    "sg:phone": "+1 440 327 9770",
    "sg:postcode": "44039",
    "sg:province": "OH",
    "sg:tags": [
      "farm",
      "corn",
      "soybean"
    ],
    "wof:name": "Richard Sullinger",
    "wof:placetype": "venue"
  },
  "geometry": {"coordinates":[-81.974083,41.384733],"type":"Point"}
}
