{
  "type": "Feature",
  "properties": {
    "addr:full": "1494 Park Ave W Mansfield OH 44906",
    "addr:housenumber": "1494",
    "addr:postcode": "44906",
    "addr:street": "Park Ave W",
    "iso:country": "US",
    "sg:address": "1494 Park Ave W",
    "sg:city": "Mansfield",
    "sg:classifiers": [
      {
        "category": "Personal",
        "subcategory": "Barber",
        "type": "Services"
      }
    ],
    "sg:phone": "+1 419 529 3141",
    "sg:postcode": "44906",
    "sg:province": "OH",
    "sg:tags": [
      "shop"
    ],
    "wof:name": "Hair Systems 1",
    "wof:placetype": "venue"
  },
  "geometry": {"coordinates":[-82.564088,40.759513],"type":"Point"}
}
