{
  "type": "Feature",
  "properties": {
    "iso:country":"US",
    "sg:address":"633 Mc Clanahan Rd",
    "sg:city":"West Union",
    "sg:classifiers":[
        {
            "category":"Building & Trades",
            "subcategory":"Plumbing",
            "type":"Services"
        }
    ],
    "sg:phone":"+1 937 544 4096",
    "sg:postcode":"45693",
    "sg:province":"OH",
    "sg:tags":[
        "conditioning",
        "air",
        "system",
        "contractor"
    ],
    "wof:name":"Bayless Heating & Air",
    "wof:placetype":"venue"
},
  "geometry": {"coordinates":[-83.596681,38.788303],"type":"Point"}
}