{
  "type": "Feature",
  "properties": {
    "addr:full": "633 Mc Clanahan Rd West Union OH 45693",
    "addr:housenumber": "633",
    "addr:postcode": "45693",
    "addr:street": "Mc Clanahan Rd",
    "iso:country": "US",
    "sg:address": "633 Mc Clanahan Rd",
    "sg:city": "West Union",
    "sg:classifiers": [
      {
        "category": "Building \u0026 Trades",
        "subcategory": "Plumbing",
        "type": "Services"
      }
    ],
    "sg:phone": "+1 937 544 4096",
    "sg:postcode": "45693",
    "sg:province": "OH",
    "sg:tags": [
      "conditioning",
      "air",
      "system",
      "contractor"
    ],
    "wof:name": "Bayless Heating \u0026 Air",
    "wof:placetype": "venue"
  },
  "geometry": {"coordinates":[-83.596681,38.788303],"type":"Point"}
}
