{
  "type": "Feature",
  "properties": {
    "iso:country":"US",
    "sg:address":"6724 Ridgeview Blvd",
    "sg:city":"North Ridgeville",
    "sg:classifiers":[
        {
            "category":"Building & Trades",
            "subcategory":"Plumbing",
            "type":"Services"
        }
    ],
    "sg:phone":"+1 440 327 4820",
    "sg:postcode":"44039",
    "sg:province":"OH",
    "sg:tags":[
        "contractor"
    ],
    "wof:name":"Armaro Heating & Cooling Inc",
    "wof:placetype":"venue"
},
  "geometry": {"coordinates":[-82.01124299999999,41.393489],"type":"Point"}
}