{
  "type": "Feature",
  "properties": {
    "addr:full": "6724 Ridgeview Blvd North Ridgeville OH 44039",
    "addr:housenumber": "6724",
    "addr:postcode": "44039",
    "addr:street": "Ridgeview Blvd",
    "iso:country": "US",
    "sg:address": "6724 Ridgeview Blvd",
    "sg:city": "North Ridgeville",
    "sg:classifiers": [
      {
        "category": "Building \u0026 Trades",
        "subcategory": "Plumbing",
        "type": "Services"
      }
    ],
    "sg:phone": "+1 440 327 4820",
    "sg:postcode": "44039",
    "sg:province": "OH",
    "sg:tags": [
      "contractor"
    ],
    "wof:name": "Armaro Heating \u0026 Cooling Inc",
    "wof:placetype": "venue"
  },
  "geometry": {"coordinates":[-82.011243,41.393489],"type":"Point"}
}
