{
  "type": "Feature",
  "properties": {
    "addr:full": "8575 Clough Pike Cincinnati OH 45244",
    "addr:housenumber": "8575",
    "addr:postcode": "45244",
    "addr:street": "Clough Pike",
    "iso:country": "US",
    "sg:address": "8575 Clough Pike",
    "sg:city": "Cincinnati",
    "sg:classifiers": [
      {
        "category": "Organizations",
        "subcategory": "Membership Organization",
        "type": "Services"
      }
    ],
    "sg:phone": "+1 513 474 9115",
    "sg:postcode": "45244",
    "sg:province": "OH",
    "wof:name": "West Coast Swing Cincinnati",
    "wof:placetype": "venue"
  },
  "geometry": {"coordinates":[-84.314876,39.087372],"type":"Point"}
}
