{
  "type": "Feature",
  "properties": {
    "addr:full": "6096 Boardwalk St Columbus OH 43229",
    "addr:housenumber": "6096",
    "addr:postcode": "43229",
    "addr:street": "Boardwalk St",
    "iso:country": "US",
    "sg:address": "6096 Boardwalk St",
    "sg:city": "Columbus",
    "sg:classifiers": [
      {
        "category": "Restaurant",
        "type": "Food \u0026 Drink"
      }
    ],
    "sg:phone": "+1 614 436 4066",
    "sg:postcode": "43229",
    "sg:province": "OH",
    "sg:tags": [
      "eating"
    ],
    "wof:name": "Pasta Petite",
    "wof:placetype": "venue"
  },
  "geometry": {"coordinates":[-82.991674,40.091309],"type":"Point"}
}
