{
  "type": "Feature",
  "properties": {
    "iso:country":"US",
    "sg:address":"4140 E Smith Rd",
    "sg:city":"Medina",
    "sg:classifiers":[
        {
            "category":"Communications",
            "subcategory":"Film & Video Production",
            "type":"Services"
        }
    ],
    "sg:phone":"+1 330 721 8393",
    "sg:postcode":"44256",
    "sg:province":"OH",
    "sg:tags":[
        "taping"
    ],
    "wof:name":"C J Productions",
    "wof:placetype":"venue"
},
  "geometry": {"coordinates":[-81.834923,41.129564],"type":"Point"}
}