{
  "type": "Feature",
  "properties": {
    "iso:country":"US",
    "sg:address":"125 E Court St",
    "sg:city":"Bowling Green",
    "sg:classifiers":[
        {
            "category":"Restaurant",
            "type":"Food & Drink"
        }
    ],
    "sg:phone":"+1 419 352 7768",
    "sg:postcode":"43402",
    "sg:province":"OH",
    "sg:tags":[
        "grocery",
        "eating"
    ],
    "wof:name":"Mr Spot's",
    "wof:placetype":"venue"
},
  "geometry": {"coordinates":[-83.64904900000001,41.376057],"type":"Point"}
}