{
  "type": "Feature",
  "properties": {
    "addr:full": "125 E Court St Bowling Green OH 43402",
    "addr:housenumber": "125",
    "addr:postcode": "43402",
    "addr:street": "E Court St",
    "iso:country": "US",
    "sg:address": "125 E Court St",
    "sg:city": "Bowling Green",
    "sg:classifiers": [
      {
        "category": "Restaurant",
        "type": "Food \u0026 Drink"
      }
    ],
    "sg:phone": "+1 419 352 7768",
    "sg:postcode": "43402",
    "sg:province": "OH",
    "sg:tags": [
      "grocery",
      "eating"
    ],
    "wof:name": "Mr Spot's",
    "wof:placetype": "venue"
  },
  "geometry": {"coordinates":[-83.649049,41.376057],"type":"Point"}
}
