{
  "type": "Feature",
  "properties": {
    "iso:country":"US",
    "sg:address":"320 Front Ave SW",
    "sg:city":"New Philadelphia",
    "sg:classifiers":[
        {
            "category":"Shopping",
            "subcategory":"Crafts & Fabrics",
            "type":"Retail Goods"
        }
    ],
    "sg:phone":"+1 330 339 2286",
    "sg:postcode":"44663",
    "sg:province":"OH",
    "sg:tags":[
        "sewing"
    ],
    "wof:name":"Shirleys Quilt Fabric Shop",
    "wof:placetype":"venue"
},
  "geometry": {"coordinates":[-81.45089400000001,40.488587],"type":"Point"}
}