{
  "type": "Feature",
  "properties": {
    "addr:full": "320 Front Ave SW New Philadelphia OH 44663",
    "addr:housenumber": "320",
    "addr:postcode": "44663",
    "addr:street": "Front Ave Sw",
    "iso:country": "US",
    "sg:address": "320 Front Ave SW",
    "sg:city": "New Philadelphia",
    "sg:classifiers": [
      {
        "category": "Shopping",
        "subcategory": "Crafts \u0026 Fabrics",
        "type": "Retail Goods"
      }
    ],
    "sg:phone": "+1 330 339 2286",
    "sg:postcode": "44663",
    "sg:province": "OH",
    "sg:tags": [
      "sewing"
    ],
    "wof:name": "Shirleys Quilt Fabric Shop",
    "wof:placetype": "venue"
  },
  "geometry": {"coordinates":[-81.450894,40.488587],"type":"Point"}
}
