{
  "type": "Feature",
  "properties": {
    "iso:country":"US",
    "sg:address":"2929 Richmond Rd",
    "sg:city":"Cleveland",
    "sg:classifiers":[
        {
            "category":"Museum",
            "type":"Entertainment"
        }
    ],
    "sg:phone":"+1 216 593 0575",
    "sg:postcode":"44122",
    "sg:province":"OH",
    "wof:name":"Maltz Jewish Museum",
    "wof:placetype":"venue"
},
  "geometry": {"coordinates":[-81.497705,41.478017],"type":"Point"}
}