{
  "type": "Feature",
  "properties": {
    "addr:full": "1651 Greenville-Nashville Rd Greenville OH 45331",
    "addr:housenumber": "1651",
    "addr:postcode": "45331",
    "addr:street": "Greenville-Nashville Rd",
    "iso:country": "US",
    "sg:address": "1651 Greenville-Nashville Rd",
    "sg:city": "Greenville",
    "sg:classifiers": [
      {
        "category": "Organizations",
        "subcategory": "Religious Organization",
        "type": "Services"
      }
    ],
    "sg:phone": "+1 937 547 3157",
    "sg:postcode": "45331",
    "sg:province": "OH",
    "sg:tags": [
      "church"
    ],
    "wof:name": "Abbotsville United Methodist",
    "wof:placetype": "venue"
  },
  "geometry": {"coordinates":[-84.746688,40.091684],"type":"Point"}
}
