{
  "type": "Feature",
  "properties": {
    "iso:country":"US",
    "sg:address":"2806 State Rte 307",
    "sg:city":"Austinburg",
    "sg:classifiers":[
        {
            "category":"Professional",
            "subcategory":"Computer Services",
            "type":"Services"
        }
    ],
    "sg:phone":"+1 440 275 1400",
    "sg:postcode":"44010",
    "sg:province":"OH",
    "sg:tags":[
        "wiring"
    ],
    "wof:name":"Cable Tools Co",
    "wof:placetype":"venue"
},
  "geometry": {"coordinates":[-80.85373300000001,41.771893],"type":"Point"}
}