{
  "type": "Feature",
  "properties": {
    "addr:full": "6431 Bridgetown Rd Ste 2 Cincinnati OH 45248",
    "addr:housenumber": "6431",
    "addr:postcode": "45248",
    "addr:street": "Bridgetown Rd Ste 2",
    "iso:country": "US",
    "sg:address": "6431 Bridgetown Rd Ste 2",
    "sg:city": "Cincinnati",
    "sg:classifiers": [
      {
        "category": "Insurance",
        "subcategory": "Hazard Insurance",
        "type": "Services"
      }
    ],
    "sg:phone": "+1 513 347 7010",
    "sg:postcode": "45248",
    "sg:province": "OH",
    "sg:website": "http://statefarm.mqgroup.com/url.asp?usr=352200",
    "wof:name": "State Farm Insurance Agent-Paul Parks",
    "wof:placetype": "venue"
  },
  "geometry": {"coordinates":[-84.659552,39.153033],"type":"Point"}
}
