{
  "type": "Feature",
  "properties": {
    "addr:full": "13109 Cranwood Park Blvd Cleveland OH 44125",
    "addr:housenumber": "13109",
    "addr:postcode": "44125",
    "addr:street": "Cranwood Park Blvd",
    "iso:country": "US",
    "sg:address": "13109 Cranwood Park Blvd",
    "sg:city": "Cleveland",
    "sg:classifiers": [
      {
        "category": "Shopping",
        "subcategory": "Clothing, Apparel, \u0026 Fashions",
        "type": "Retail Goods"
      }
    ],
    "sg:phone": "+1 216 475 6655",
    "sg:postcode": "44125",
    "sg:province": "OH",
    "wof:name": "Lady J Designs",
    "wof:placetype": "venue"
  },
  "geometry": {"coordinates":[-81.587316,41.432939],"type":"Point"}
}
