{
  "type": "Feature",
  "properties": {
    "iso:country":"US",
    "sg:address":"2319 Quebec Rd",
    "sg:city":"Cincinnati",
    "sg:classifiers":[
        {
            "category":"Organizations",
            "subcategory":"Religious Organization",
            "type":"Services"
        }
    ],
    "sg:phone":"+1 513 471 3081",
    "sg:postcode":"45214",
    "sg:province":"OH",
    "sg:tags":[
        "church"
    ],
    "wof:name":"Bethel Apostolic Church",
    "wof:placetype":"venue"
},
  "geometry": {"coordinates":[-84.562635,39.125],"type":"Point"}
}