{
  "type": "Feature",
  "properties": {
    "addr:full":"5449 Ridge Rd Cleveland OH 44129",
    "addr:housenumber":"5449",
    "addr:postcode":"44129",
    "addr:street":"Ridge Rd",
    "iso:country":"US",
    "sg:address":"5449 Ridge Rd",
    "sg:city":"Cleveland",
    "sg:classifiers":[
        {
            "category":"Social Services",
            "subcategory":"Child Care",
            "type":"Services"
        }
    ],
    "sg:phone":"+1 440 886 4456",
    "sg:postcode":"44129",
    "sg:province":"OH",
    "sg:tags":[
        "day"
    ],
    "wof:name":"En Loving Care Inc",
    "wof:placetype":"venue"
},
  "geometry": {"coordinates":[-81.73440600000001,41.412251],"type":"Point"}
}