{
  "type": "Feature",
  "properties": {
    "iso:country":"US",
    "sg:address":"5455 N Marginal Rd",
    "sg:city":"Cleveland",
    "sg:classifiers":[
        {
            "category":"Restaurant",
            "type":"Food & Drink"
        }
    ],
    "sg:phone":"+1 216 432 9730",
    "sg:postcode":"44114",
    "sg:province":"OH",
    "wof:name":"Andrea's Boardwalk Cafe",
    "wof:placetype":"venue"
},
  "geometry": {"coordinates":[-81.651976,41.531024],"type":"Point"}
}