{
  "type": "Feature",
  "properties": {
    "iso:country":"US",
    "sg:address":"1801 Saint Clair Ave NE",
    "sg:city":"Cleveland",
    "sg:classifiers":[
        {
            "category":"Social Services",
            "type":"Services"
        },
        {
            "category":"Government",
            "subcategory":"Office",
            "type":"Public Place"
        }
    ],
    "sg:phone":"+1 216 443 3433",
    "sg:postcode":"44114",
    "sg:province":"OH",
    "sg:tags":[
        "parish",
        "government-county"
    ],
    "wof:name":"Cuyahoga County Probation Svc",
    "wof:placetype":"venue"
},
  "geometry": {"coordinates":[-81.68216700000001,41.507935],"type":"Point"}
}