{
  "type": "Feature",
  "properties": {
    "addr:full": "1801 Central Pkwy Cincinnati OH 45214",
    "addr:housenumber": "1801",
    "addr:postcode": "45214",
    "addr:street": "Central Pkwy",
    "iso:country": "US",
    "sg:address": "1801 Central Pkwy",
    "sg:city": "Cincinnati",
    "sg:classifiers": [
      {
        "category": "Shopping",
        "subcategory": "Department Store",
        "type": "Retail Goods"
      }
    ],
    "sg:phone": "+1 513 721 1786",
    "sg:postcode": "45214",
    "sg:province": "OH",
    "wof:name": "Family Dollar Store",
    "wof:placetype": "venue"
  },
  "geometry": {"coordinates":[-84.524177,39.119104],"type":"Point"}
}
