{
  "type": "Feature",
  "properties": {
    "iso:country":"US",
    "sg:address":"8325 W Chester Rd",
    "sg:city":"West Chester",
    "sg:classifiers":[
        {
            "category":"Real Estate",
            "subcategory":"Real Estate Agent",
            "type":"Services"
        }
    ],
    "sg:phone":"+1 513 417 6653",
    "sg:postcode":"45069",
    "sg:province":"OH",
    "wof:name":"Kristeen J Boaz",
    "wof:placetype":"venue"
},
  "geometry": {"coordinates":[-84.353156,39.317539],"type":"Point"}
}