{
  "type": "Feature",
  "properties": {
    "addr:full":"4225 Macsway Ave Columbus OH 43232",
    "addr:housenumber":"4225",
    "addr:postcode":"43232",
    "addr:street":"Macsway Ave",
    "iso:country":"US",
    "sg:address":"4225 Macsway Ave",
    "sg:city":"Columbus",
    "sg:classifiers":[
        {
            "category":"Health Services",
            "subcategory":"Nursing And Care Facility",
            "type":"Services"
        },
        {
            "category":"Real Estate",
            "subcategory":"Real Estate Operator",
            "type":"Services"
        }
    ],
    "sg:phone":"+1 614 861 7234",
    "sg:postcode":"43232",
    "sg:province":"OH",
    "sg:tags":[
        "owner",
        "retirement",
        "apartment",
        "community",
        "home"
    ],
    "wof:name":"Eastland Manor Inc",
    "wof:placetype":"venue"
},
  "geometry": {"coordinates":[-82.87988199999999,39.923552],"type":"Point"}
}