{
  "type": "Feature",
  "properties": {
    "iso:country":"US",
    "sg:address":"5280 W 161st St",
    "sg:city":"Cleveland",
    "sg:classifiers":[
        {
            "category":"Manufacturing",
            "subcategory":"Tools & Machinery",
            "type":"Manufacturing & Wholesale Goods"
        }
    ],
    "sg:phone":"+1 216 433 7070",
    "sg:postcode":"44142",
    "sg:province":"OH",
    "sg:tags":[
        "repair",
        "mfg",
        "welding"
    ],
    "wof:name":"Jarcon Industries Inc",
    "wof:placetype":"venue"
},
  "geometry": {"coordinates":[-81.811109,41.417085],"type":"Point"}
}