{
  "type": "Feature",
  "properties": {
    "addr:full": "5280 W 161st St Cleveland OH 44142",
    "addr:housenumber": "5280",
    "addr:postcode": "44142",
    "addr:street": "W 161St St",
    "iso:country": "US",
    "sg:address": "5280 W 161st St",
    "sg:city": "Cleveland",
    "sg:classifiers": [
      {
        "category": "Manufacturing",
        "subcategory": "Tools \u0026 Machinery",
        "type": "Manufacturing \u0026 Wholesale Goods"
      }
    ],
    "sg:phone": "+1 216 433 7070",
    "sg:postcode": "44142",
    "sg:province": "OH",
    "sg:tags": [
      "repair",
      "mfg",
      "welding"
    ],
    "wof:name": "Jarcon Industries Inc",
    "wof:placetype": "venue"
  },
  "geometry": {"coordinates":[-81.811109,41.417085],"type":"Point"}
}
