{
  "type": "Feature",
  "properties": {
    "iso:country":"US",
    "sg:address":"78 Wilson St",
    "sg:city":"Newark",
    "sg:classifiers":[
        {
            "category":"Restaurant",
            "type":"Food & Drink"
        }
    ],
    "sg:phone":"+1 740 349 8009",
    "sg:postcode":"43055",
    "sg:province":"OH",
    "wof:name":"Yesterday's Pub",
    "wof:placetype":"venue"
},
  "geometry": {"coordinates":[-82.408909,40.054088],"type":"Point"}
}