{
  "type": "Feature",
  "properties": {
    "addr:full": "14135 Pleasant Ridge Dr Marysville OH 43040",
    "addr:housenumber": "14135",
    "addr:postcode": "43040",
    "addr:street": "Pleasant Ridge Dr",
    "iso:country": "US",
    "sg:address": "14135 Pleasant Ridge Dr",
    "sg:city": "Marysville",
    "sg:classifiers": [
      {
        "category": "Professional",
        "type": "Services"
      }
    ],
    "sg:phone": "+1 937 246 2402",
    "sg:postcode": "43040",
    "sg:province": "OH",
    "wof:name": "Jed Kiss",
    "wof:placetype": "venue"
  },
  "geometry": {"coordinates":[-83.311922,40.23062],"type":"Point"}
}
