{
  "type": "Feature",
  "properties": {
    "iso:country":"US",
    "sg:address":"7194 Pippin Rd",
    "sg:city":"Cincinnati",
    "sg:classifiers":[
        {
            "category":"Real Estate",
            "subcategory":"Real Estate Agent",
            "type":"Services"
        }
    ],
    "sg:phone":"+1 513 522 8000",
    "sg:postcode":"45239",
    "sg:province":"OH",
    "wof:name":"Woodhouse & Assoc",
    "wof:placetype":"venue"
},
  "geometry": {"coordinates":[-84.57384399999999,39.211123],"type":"Point"}
}