{
  "type": "Feature",
  "properties": {
    "iso:country":"US",
    "sg:address":"402 Eagle St",
    "sg:city":"Fairport Harbor",
    "sg:classifiers":[
        {
            "category":"Travel",
            "subcategory":"Travel Agent",
            "type":"Entertainment"
        }
    ],
    "sg:phone":"+1 440 358 9294",
    "sg:postcode":"44077",
    "sg:province":"OH",
    "sg:tags":[
        "operator",
        "tour",
        "agency",
        "bureau"
    ],
    "wof:name":"Fairwinds Travel & Tours",
    "wof:placetype":"venue"
},
  "geometry": {"coordinates":[-81.275458,41.752317],"type":"Point"}
}