{
  "type": "Feature",
  "properties": {
    "iso:country":"US",
    "sg:address":"1731 W 13th St",
    "sg:city":"Ashtabula",
    "sg:classifiers":[
        {
            "category":"Shopping",
            "subcategory":"Used Merchandise",
            "type":"Retail Goods"
        }
    ],
    "sg:phone":"+1 440 964 5530",
    "sg:postcode":"44004",
    "sg:province":"OH",
    "wof:name":"Heavens Auctioneering Service",
    "wof:placetype":"venue"
},
  "geometry": {"coordinates":[-80.80791499999999,41.887913],"type":"Point"}
}