{
  "type": "Feature",
  "properties": {
    "iso:country":"US",
    "sg:address":"120 E Poplar St",
    "sg:city":"Sidney",
    "sg:classifiers":[
        {
            "category":"Home & Garden",
            "subcategory":"Furniture",
            "type":"Retail Goods"
        }
    ],
    "sg:phone":"+1 937 492 8006",
    "sg:postcode":"45365",
    "sg:province":"OH",
    "wof:name":"Furniture Express",
    "wof:placetype":"venue"
},
  "geometry": {"coordinates":[-84.156452,40.285668],"type":"Point"}
}