{
  "type": "Feature",
  "properties": {
    "iso:country":"US",
    "sg:address":"4063 Porter Rd",
    "sg:city":"Westlake",
    "sg:classifiers":[
        {
            "category":"Farming",
            "subcategory":"Farm",
            "type":"Manufacturing & Wholesale Goods"
        }
    ],
    "sg:phone":"+1 440 871 5584",
    "sg:postcode":"44145",
    "sg:province":"OH",
    "sg:tags":[
        "crop",
        "general"
    ],
    "wof:name":"Eugene L Widener",
    "wof:placetype":"venue"
},
  "geometry": {"coordinates":[-81.94035,41.43157],"type":"Point"}
}