{
  "type": "Feature",
  "properties": {
    "addr:full":"72895 Harkins Chapel Rd Albany OH 45710",
    "addr:housenumber":"72895",
    "addr:postcode":"45710",
    "addr:street":"Harkins Chapel Rd",
    "iso:country":"US",
    "sg:address":"72895 Harkins Chapel Rd",
    "sg:city":"Albany",
    "sg:classifiers":[
        {
            "category":"Building & Trades",
            "subcategory":"Construction",
            "type":"Services"
        }
    ],
    "sg:phone":"+1 740 596 2198",
    "sg:postcode":"45710",
    "sg:province":"OH",
    "sg:tags":[
        "house"
    ],
    "wof:name":"Dino Construction Services",
    "wof:placetype":"venue"
},
  "geometry": {"coordinates":[-82.32503699999999,39.225071],"type":"Point"}
}