{
  "type": "Feature",
  "properties": {
    "iso:country":"US",
    "sg:address":"103 College St",
    "sg:city":"Butler",
    "sg:classifiers":[
        {
            "category":"Building & Trades",
            "subcategory":"Construction",
            "type":"Services"
        }
    ],
    "sg:phone":"+1 419 883 3321",
    "sg:postcode":"44822",
    "sg:province":"OH",
    "sg:tags":[
        "painter"
    ],
    "wof:name":"Scott Young Painting",
    "wof:placetype":"venue"
},
  "geometry": {"coordinates":[-82.427987,40.589941],"type":"Point"}
}