{
  "type": "Feature",
  "properties": {
    "addr:full": "103 College St Butler OH 44822",
    "addr:housenumber": "103",
    "addr:postcode": "44822",
    "addr:street": "College St",
    "iso:country": "US",
    "sg:address": "103 College St",
    "sg:city": "Butler",
    "sg:classifiers": [
      {
        "category": "Building \u0026 Trades",
        "subcategory": "Construction",
        "type": "Services"
      }
    ],
    "sg:phone": "+1 419 883 3321",
    "sg:postcode": "44822",
    "sg:province": "OH",
    "sg:tags": [
      "painter"
    ],
    "wof:name": "Scott Young Painting",
    "wof:placetype": "venue"
  },
  "geometry": {"coordinates":[-82.427987,40.589941],"type":"Point"}
}
