{
  "type": "Feature",
  "properties": {
    "addr:full":"51492 Breezy Hill Rd St Clairsville OH 43950",
    "addr:housenumber":"51492",
    "addr:postcode":"43950",
    "addr:street":"Breezy Hill Rd",
    "iso:country":"US",
    "sg:address":"51492 Breezy Hill Rd",
    "sg:city":"St Clairsville",
    "sg:classifiers":[
        {
            "category":"Real Estate",
            "subcategory":"Real Estate Operator",
            "type":"Services"
        }
    ],
    "sg:phone":"+1 740 695 1989",
    "sg:postcode":"43950",
    "sg:province":"OH",
    "sg:tags":[
        "apartment"
    ],
    "wof:name":"Bel-Claire Garden Apartments",
    "wof:placetype":"venue"
},
  "geometry": {"coordinates":[-80.859838,40.06759],"type":"Point"}
}