{
  "type": "Feature",
  "properties": {
    "addr:full": "101 5th St SE Barberton OH 44203",
    "addr:housenumber": "101",
    "addr:postcode": "44203",
    "addr:street": "5Th St Se",
    "iso:country": "US",
    "sg:address": "101 5th St SE",
    "sg:city": "Barberton",
    "sg:classifiers": [
      {
        "category": "Wholesale",
        "subcategory": "Scrap",
        "type": "Manufacturing \u0026 Wholesale Goods"
      }
    ],
    "sg:phone": "+1 330 753 2901",
    "sg:postcode": "44203",
    "sg:province": "OH",
    "sg:tags": [
      "clinic",
      "specialty",
      "outpatient"
    ],
    "wof:name": "Rehab",
    "wof:placetype": "venue"
  },
  "geometry": {"coordinates":[-81.589928,41.009425],"type":"Point"}
}
