{
  "type": "Feature",
  "properties": {
    "addr:full":"1760 Oakwood Ave Youngstown OH 44509",
    "addr:housenumber":"1760",
    "addr:postcode":"44509",
    "addr:street":"Oakwood Ave",
    "iso:country":"US",
    "sg:address":"1760 Oakwood Ave",
    "sg:city":"Youngstown",
    "sg:classifiers":[
        {
            "category":"Manufacturing",
            "subcategory":"Signs",
            "type":"Manufacturing & Wholesale Goods"
        }
    ],
    "sg:phone":"+1 330 793 4565",
    "sg:postcode":"44509",
    "sg:province":"OH",
    "wof:name":"Commercial Neon & Lighting",
    "wof:placetype":"venue"
},
  "geometry": {"coordinates":[-80.687302,41.105068],"type":"Point"}
}