{
  "type": "Feature",
  "properties": {
    "iso:country":"US",
    "sg:address":"4610 N High St",
    "sg:city":"Columbus",
    "sg:classifiers":[
        {
            "category":"Shopping",
            "subcategory":"Discount & Variety Stores",
            "type":"Retail Goods"
        }
    ],
    "sg:phone":"+1 614 263 3888",
    "sg:postcode":"43214",
    "sg:province":"OH",
    "sg:tags":[
        "merchandise",
        "general"
    ],
    "wof:name":"Elegance Of India",
    "wof:placetype":"venue"
},
  "geometry": {"coordinates":[-83.019769,40.05613],"type":"Point"}
}