{
  "type": "Feature",
  "properties": {
    "iso:country":"US",
    "sg:address":"2449 Gilchrist Rd",
    "sg:city":"Akron",
    "sg:classifiers":[
        {
            "category":"Restaurant",
            "type":"Food & Drink"
        }
    ],
    "sg:menulink":"http://www.allmenus.com/oh/akron/42816-bob-evans/menu/",
    "sg:phone":"+1 330 784 4421",
    "sg:postcode":"44305",
    "sg:province":"OH",
    "sg:tags":[
        "american"
    ],
    "wof:name":"Bob Evans",
    "wof:placetype":"venue"
},
  "geometry": {"coordinates":[-81.436013,41.065822],"type":"Point"}
}