{
  "type": "Feature",
  "properties": {
    "addr:full": "2449 Gilchrist Rd Akron OH 44305",
    "addr:housenumber": "2449",
    "addr:postcode": "44305",
    "addr:street": "Gilchrist Rd",
    "iso:country": "US",
    "sg:address": "2449 Gilchrist Rd",
    "sg:city": "Akron",
    "sg:classifiers": [
      {
        "category": "Restaurant",
        "type": "Food \u0026 Drink"
      }
    ],
    "sg:menulink": "http://www.allmenus.com/oh/akron/42816-bob-evans/menu/",
    "sg:phone": "+1 330 784 4421",
    "sg:postcode": "44305",
    "sg:province": "OH",
    "sg:tags": [
      "american"
    ],
    "wof:name": "Bob Evans",
    "wof:placetype": "venue"
  },
  "geometry": {"coordinates":[-81.436013,41.065822],"type":"Point"}
}
