{
  "type": "Feature",
  "properties": {
    "iso:country":"US",
    "sg:address":"150 Main St",
    "sg:city":"Wadsworth",
    "sg:classifiers":[
        {
            "category":"Education",
            "subcategory":"Dance Studio",
            "type":"Public Place"
        }
    ],
    "sg:phone":"+1 330 336 6640",
    "sg:postcode":"44281",
    "sg:province":"OH",
    "wof:name":"Northeast Ohio Dance Academy",
    "wof:placetype":"venue"
},
  "geometry": {"coordinates":[-81.729692,41.024046],"type":"Point"}
}