{
  "type": "Feature",
  "properties": {
    "addr:full": "1146 Charwood Rd Mansfield OH 44907",
    "addr:housenumber": "1146",
    "addr:postcode": "44907",
    "addr:street": "Charwood Rd",
    "iso:country": "US",
    "sg:address": "1146 Charwood Rd",
    "sg:city": "Mansfield",
    "sg:classifiers": [
      {
        "category": "Organizations",
        "subcategory": "Religious Organization",
        "type": "Services"
      }
    ],
    "sg:phone": "+1 419 756 5284",
    "sg:postcode": "44907",
    "sg:province": "OH",
    "sg:tags": [
      "clergy"
    ],
    "wof:name": "Carl W Cunfer",
    "wof:placetype": "venue"
  },
  "geometry": {"coordinates":[-82.522784,40.727463],"type":"Point"}
}
