{
  "type": "Feature",
  "properties": {
    "iso:country":"US",
    "sg:address":"1771 E 30th St",
    "sg:city":"Cleveland",
    "sg:classifiers":[
        {
            "category":"Wholesale",
            "subcategory":"Medical Equipment & Supplies",
            "type":"Manufacturing & Wholesale Goods"
        }
    ],
    "sg:phone":"+1 216 502 0755",
    "sg:postcode":"44114",
    "sg:province":"OH",
    "sg:tags":[
        "imaging"
    ],
    "wof:name":"Imalux Corporation",
    "wof:placetype":"venue"
},
  "geometry": {"coordinates":[-81.668143,41.507101],"type":"Point"}
}