{
  "type": "Feature",
  "properties": {
    "iso:country":"US",
    "sg:address":"6390 York Rd",
    "sg:city":"Cleveland",
    "sg:classifiers":[
        {
            "category":"Food & Beverages",
            "subcategory":"Candy",
            "type":"Retail Goods"
        }
    ],
    "sg:phone":"+1 440 845 2022",
    "sg:postcode":"44130",
    "sg:province":"OH",
    "sg:tags":[
        "making",
        "supply"
    ],
    "wof:name":"Jan's Confectionary Supplies",
    "wof:placetype":"venue"
},
  "geometry": {"coordinates":[-81.7597,41.382445],"type":"Point"}
}