{
  "type": "Feature",
  "properties": {
    "addr:full":"15 S 5th St Martins Ferry OH 43935",
    "addr:housenumber":"15",
    "addr:postcode":"43935",
    "addr:street":"S 5Th St Martins Ferry",
    "iso:country":"US",
    "sg:address":"15 S 5th St",
    "sg:city":"Martins Ferry",
    "sg:classifiers":[
        {
            "category":"Shopping",
            "subcategory":"Computers & Home Electronics",
            "type":"Retail Goods"
        }
    ],
    "sg:phone":"+1 740 609 0080",
    "sg:postcode":"43935",
    "sg:province":"OH",
    "sg:tags":[
        "equipment",
        "dealer"
    ],
    "wof:name":"Digital Data Communications",
    "wof:placetype":"venue"
},
  "geometry": {"coordinates":[-80.725404,40.096119],"type":"Point"}
}