{
  "type": "Feature",
  "properties": {
    "addr:full":"129 Cleveland Ave Lancaster OH 43130",
    "addr:housenumber":"129",
    "addr:postcode":"43130",
    "addr:street":"Cleveland Ave",
    "iso:country":"US",
    "sg:address":"129 Cleveland Ave",
    "sg:city":"Lancaster",
    "sg:classifiers":[
        {
            "category":"Building & Trades",
            "subcategory":"Construction",
            "type":"Services"
        }
    ],
    "sg:phone":"+1 614 868 1891",
    "sg:postcode":"43130",
    "sg:province":"OH",
    "sg:tags":[
        "steam",
        "cleaning"
    ],
    "sg:website":"www.mpwindustrial.com",
    "wof:name":"MPW Industrial Svc",
    "wof:placetype":"venue"
},
  "geometry": {"coordinates":[-82.60314200000001,39.701365],"type":"Point"}
}