{
  "type": "Feature",
  "properties": {
    "addr:full": "28670 Cincinnati Ridge Rd Coolville OH 45723",
    "addr:housenumber": "28670",
    "addr:postcode": "45723",
    "addr:street": "Cincinnati Ridge Rd",
    "iso:country": "US",
    "sg:address": "28670 Cincinnati Ridge Rd",
    "sg:city": "Coolville",
    "sg:classifiers": [
      {
        "category": "Building \u0026 Trades",
        "subcategory": "Construction",
        "type": "Services"
      }
    ],
    "sg:phone": "+1 740 667 6118",
    "sg:postcode": "45723",
    "sg:province": "OH",
    "sg:tags": [
      "excavation",
      "contractor"
    ],
    "wof:name": "James Excavating",
    "wof:placetype": "venue"
  },
  "geometry": {"coordinates":[-81.751785,39.221404],"type":"Point"}
}
