{
  "type": "Feature",
  "properties": {
    "addr:full":"101 W Wabash St Liberty Center OH 43532",
    "addr:housenumber":"101",
    "addr:postcode":"43532",
    "addr:street":"W Wabash St",
    "iso:country":"US",
    "sg:address":"101 W Wabash St",
    "sg:city":"Liberty Center",
    "sg:classifiers":[
        {
            "category":"Real Estate",
            "subcategory":"Real Estate Agent",
            "type":"Services"
        }
    ],
    "sg:phone":"+1 419 533 5201",
    "sg:postcode":"43532",
    "sg:province":"OH",
    "wof:name":"Hefflinger Realty Insurance",
    "wof:placetype":"venue"
},
  "geometry": {"coordinates":[-84.00836,41.444053],"type":"Point"}
}