{
  "type": "Feature",
  "properties": {
    "addr:full": "4146 Mill Crest Dr Hamilton OH 45011",
    "addr:housenumber": "4146",
    "addr:postcode": "45011",
    "addr:street": "Mill Crest Dr",
    "iso:country": "US",
    "sg:address": "4146 Mill Crest Dr",
    "sg:city": "Hamilton",
    "sg:classifiers": [
      {
        "category": "Food \u0026 Beverages",
        "subcategory": "Bakery",
        "type": "Retail Goods"
      }
    ],
    "sg:phone": "+1 513 829 8790",
    "sg:postcode": "45011",
    "sg:province": "OH",
    "wof:name": "Freds Donut Shop",
    "wof:placetype": "venue"
  },
  "geometry": {"coordinates":[-84.479802,39.406368],"type":"Point"}
}
