{
  "type": "Feature",
  "properties": {
    "iso:country":"US",
    "sg:address":"4146 Mill Crest Dr",
    "sg:city":"Hamilton",
    "sg:classifiers":[
        {
            "category":"Food & Beverages",
            "subcategory":"Bakery",
            "type":"Retail Goods"
        }
    ],
    "sg:phone":"+1 513 829 8790",
    "sg:postcode":"45011",
    "sg:province":"OH",
    "wof:name":"Freds Donut Shop",
    "wof:placetype":"venue"
},
  "geometry": {"coordinates":[-84.47980200000001,39.406368],"type":"Point"}
}