{
  "type": "Feature",
  "properties": {
    "iso:country":"US",
    "sg:address":"171 N Hamilton Rd",
    "sg:city":"Columbus",
    "sg:classifiers":[
        {
            "category":"Building & Trades",
            "subcategory":"Construction",
            "type":"Services"
        }
    ],
    "sg:phone":"+1 614 864 6200",
    "sg:postcode":"43213",
    "sg:province":"OH",
    "sg:tags":[
        "garage",
        "door",
        "installation"
    ],
    "wof:name":"Mid States Door",
    "wof:placetype":"venue"
},
  "geometry": {"coordinates":[-82.873904,39.977744],"type":"Point"}
}