{
  "type": "Feature",
  "properties": {
    "addr:full": "49 S James Rd Columbus OH 43213",
    "addr:housenumber": "49",
    "addr:postcode": "43213",
    "addr:street": "S James Rd",
    "iso:country": "US",
    "sg:address": "49 S James Rd",
    "sg:city": "Columbus",
    "sg:classifiers": [
      {
        "category": "Organizations",
        "subcategory": "Non-profit Organization",
        "type": "Services"
      }
    ],
    "sg:phone": "+1 614 231 8897",
    "sg:postcode": "43213",
    "sg:province": "OH",
    "wof:name": "Congo New Century",
    "wof:placetype": "venue"
  },
  "geometry": {"coordinates":[-82.91357,39.971911],"type":"Point"}
}
