{
  "type": "Feature",
  "properties": {
    "iso:country":"US",
    "sg:address":"858 E 3rd Ave",
    "sg:city":"Columbus",
    "sg:classifiers":[
        {
            "category":"Organizations",
            "subcategory":"Religious Organization",
            "type":"Services"
        }
    ],
    "sg:phone":"+1 614 299 7069",
    "sg:postcode":"43201",
    "sg:province":"OH",
    "sg:tags":[
        "baptist",
        "church"
    ],
    "wof:name":"Triedstone Baptist Church",
    "wof:placetype":"venue"
},
  "geometry": {"coordinates":[-82.98067,39.983364],"type":"Point"}
}