{
  "type": "Feature",
  "properties": {
    "addr:full":"4561 E 131st St Cleveland OH 44105",
    "addr:housenumber":"4561",
    "addr:postcode":"44105",
    "addr:street":"E 131St St",
    "iso:country":"US",
    "sg:address":"4561 E 131st St",
    "sg:city":"Cleveland",
    "sg:classifiers":[
        {
            "category":"Autos & Motor Vehicles",
            "subcategory":"Fuel & Gas Station",
            "type":"Retail Goods"
        }
    ],
    "sg:phone":"+1 216 475 1469",
    "sg:postcode":"44105",
    "sg:province":"OH",
    "sg:tags":[
        "convenience",
        "station",
        "store"
    ],
    "wof:name":"Marathon Gas Station",
    "wof:placetype":"venue"
},
  "geometry": {"coordinates":[-81.591414,41.435927],"type":"Point"}
}