{
  "type": "Feature",
  "properties": {
    "addr:full": "275 Forward Pass Rd SW Pataskala OH 43062",
    "addr:housenumber": "275",
    "addr:postcode": "43062",
    "addr:street": "Forward Pass Rd Sw",
    "iso:country": "US",
    "sg:address": "275 Forward Pass Rd SW",
    "sg:city": "Pataskala",
    "sg:classifiers": [
      {
        "category": "Professional",
        "subcategory": "Secretarial Services",
        "type": "Services"
      }
    ],
    "sg:phone": "+1 740 927 8386",
    "sg:postcode": "43062",
    "sg:province": "OH",
    "sg:tags": [
      "typing"
    ],
    "wof:name": "Bennett's Typing",
    "wof:placetype": "venue"
  },
  "geometry": {"coordinates":[-82.647975,40.021625],"type":"Point"}
}
