{
  "type": "Feature",
  "properties": {
    "iso:country":"US",
    "sg:address":"104 Glendale St",
    "sg:city":"Cardington",
    "sg:classifiers":[
        {
            "category":"Retail",
            "subcategory":"Auto Repair",
            "type":"Services"
        }
    ],
    "sg:phone":"+1 419 864 7596",
    "sg:postcode":"43315",
    "sg:province":"OH",
    "sg:tags":[
        "wheel",
        "axle",
        "alignment"
    ],
    "wof:name":"Glendale Alignment",
    "wof:placetype":"venue"
},
  "geometry": {"coordinates":[-82.892669,40.503171],"type":"Point"}
}