{
  "type": "Feature",
  "properties": {
    "addr:full": "4352 Winchell Rd Mantua OH 44255",
    "addr:housenumber": "4352",
    "addr:postcode": "44255",
    "addr:street": "Winchell Rd",
    "iso:country": "US",
    "sg:address": "4352 Winchell Rd",
    "sg:city": "Mantua",
    "sg:classifiers": [
      {
        "category": "Building \u0026 Trades",
        "subcategory": "Construction",
        "type": "Services"
      }
    ],
    "sg:phone": "+1 330 562 4716",
    "sg:postcode": "44255",
    "sg:province": "OH",
    "sg:tags": [
      "contractor"
    ],
    "wof:name": "JM Maintenance Co",
    "wof:placetype": "venue"
  },
  "geometry": {"coordinates":[-81.234378,41.342705],"type":"Point"}
}
