{
  "type": "Feature",
  "properties": {
    "iso:country":"US",
    "sg:address":"4352 Winchell Rd",
    "sg:city":"Mantua",
    "sg:classifiers":[
        {
            "category":"Building & Trades",
            "subcategory":"Construction",
            "type":"Services"
        }
    ],
    "sg:phone":"+1 330 562 4716",
    "sg:postcode":"44255",
    "sg:province":"OH",
    "sg:tags":[
        "contractor"
    ],
    "wof:name":"JM Maintenance Co",
    "wof:placetype":"venue"
},
  "geometry": {"coordinates":[-81.234378,41.342705],"type":"Point"}
}