{
  "type": "Feature",
  "properties": {
    "iso:country":"US",
    "sg:address":"8055 Stitt Rd",
    "sg:city":"Monclova",
    "sg:classifiers":[
        {
            "category":"Insurance",
            "subcategory":"Insurance Agent",
            "type":"Services"
        }
    ],
    "sg:phone":"+1 419 878 3970",
    "sg:postcode":"43542",
    "sg:province":"OH",
    "wof:name":"Allstate Insurance Co",
    "wof:placetype":"venue"
},
  "geometry": {"coordinates":[-83.733974,41.536701],"type":"Point"}
}