{
  "type": "Feature",
  "properties": {
    "addr:full": "3603 Menlo Rd Cleveland OH 44120",
    "addr:housenumber": "3603",
    "addr:postcode": "44120",
    "addr:street": "Menlo Rd",
    "iso:country": "US",
    "sg:address": "3603 Menlo Rd",
    "sg:city": "Cleveland",
    "sg:classifiers": [
      {
        "category": "Wholesale",
        "subcategory": "Non-durable Goods",
        "type": "Manufacturing \u0026 Wholesale Goods"
      }
    ],
    "sg:phone": "+1 216 752 9011",
    "sg:postcode": "44120",
    "sg:province": "OH",
    "wof:name": "Jls Distributors",
    "wof:placetype": "venue"
  },
  "geometry": {"coordinates":[-81.57192,41.462623],"type":"Point"}
}
