{
  "type": "Feature",
  "properties": {
    "addr:full": "721 S Columbus St Lancaster OH 43130",
    "addr:housenumber": "721",
    "addr:postcode": "43130",
    "addr:street": "S Columbus St",
    "iso:country": "US",
    "sg:address": "721 S Columbus St",
    "sg:city": "Lancaster",
    "sg:classifiers": [
      {
        "category": "Recreation",
        "type": "Entertainment"
      },
      {
        "category": "Shopping",
        "subcategory": "Bicycles \u0026 Sporting Goods",
        "type": "Retail Goods"
      }
    ],
    "sg:phone": "+1 740 653 2697",
    "sg:postcode": "43130",
    "sg:province": "OH",
    "sg:tags": [
      "archery",
      "range"
    ],
    "wof:name": "Fairfield Outdoors Inc",
    "wof:placetype": "venue"
  },
  "geometry": {"coordinates":[-82.599018,39.704683],"type":"Point"}
}
