{
  "type": "Feature",
  "properties": {
    "addr:full": "4326 W 8th St Cincinnati OH 45205",
    "addr:housenumber": "4326",
    "addr:postcode": "45205",
    "addr:street": "W 8Th St",
    "iso:country": "US",
    "sg:address": "4326 W 8th St",
    "sg:city": "Cincinnati",
    "sg:classifiers": [
      {
        "category": "Professional",
        "type": "Services"
      }
    ],
    "sg:phone": "+1 513 251 0743",
    "sg:postcode": "45205",
    "sg:province": "OH",
    "wof:name": "Amy C Zstautberg",
    "wof:placetype": "venue"
  },
  "geometry": {"coordinates":[-84.594335,39.108699],"type":"Point"}
}
