{
  "type": "Feature",
  "properties": {
    "iso:country":"US",
    "sg:address":"40528 State Rte 18",
    "sg:city":"Wellington",
    "sg:classifiers":[
        {
            "category":"Professional",
            "subcategory":"Accounting & Tax Preparation",
            "type":"Services"
        }
    ],
    "sg:phone":"+1 440 647 1700",
    "sg:postcode":"44090",
    "sg:province":"OH",
    "sg:tags":[
        "bookkeeping",
        "general"
    ],
    "wof:name":"Office Solutions Unlimited",
    "wof:placetype":"venue"
},
  "geometry": {"coordinates":[-82.108148,41.168574],"type":"Point"}
}