{
  "type": "Feature",
  "properties": {
    "iso:country":"US",
    "sg:address":"120 Main St",
    "sg:city":"Ripley",
    "sg:classifiers":[
        {
            "category":"Education",
            "subcategory":"School",
            "type":"Public Place"
        }
    ],
    "sg:phone":"+1 937 392 4396",
    "sg:postcode":"45167",
    "sg:province":"OH",
    "wof:name":"Ripley-Union-Lewis Local Dist",
    "wof:placetype":"venue"
},
  "geometry": {"coordinates":[-83.84419800000001,38.746045],"type":"Point"}
}