{
  "type": "Feature",
  "properties": {
    "iso:country":"US",
    "sg:address":"545 S Drexel Ave",
    "sg:city":"Columbus",
    "sg:classifiers":[
        {
            "category":"Personal",
            "subcategory":"Barber",
            "type":"Services"
        }
    ],
    "sg:phone":"+1 614 235 6769",
    "sg:postcode":"43209",
    "sg:province":"OH",
    "wof:name":"Drexel Barber Shop",
    "wof:placetype":"venue"
},
  "geometry": {"coordinates":[-82.938029,39.958304],"type":"Point"}
}