{
  "type": "Feature",
  "properties": {
    "addr:full":"6805 Richville Dr SW Massillon OH 44646",
    "addr:housenumber":"6805",
    "addr:postcode":"44646",
    "addr:street":"Richville Dr Sw",
    "iso:country":"US",
    "sg:address":"6805 Richville Dr SW",
    "sg:city":"Massillon",
    "sg:classifiers":[
        {
            "category":"Education",
            "subcategory":"School",
            "type":"Public Place"
        }
    ],
    "sg:phone":"+1 330 832 9856",
    "sg:postcode":"44646",
    "sg:province":"OH",
    "sg:tags":[
        "high",
        "vocational"
    ],
    "wof:name":"Career Education",
    "wof:placetype":"venue"
},
  "geometry": {"coordinates":[-81.48140100000001,40.766317],"type":"Point"}
}