{
  "type": "Feature",
  "properties": {
    "addr:full":"827 Lexington Ave Mansfield OH 44907",
    "addr:housenumber":"827",
    "addr:postcode":"44907",
    "addr:street":"Lexington Ave",
    "iso:country":"US",
    "sg:address":"827 Lexington Ave",
    "sg:city":"Mansfield",
    "sg:classifiers":[
        {
            "category":"Restaurant",
            "type":"Food & Drink"
        }
    ],
    "sg:menulink":"http://www.allmenus.com/oh/mansfield/245131-m-j-mulligans-at-paisley-park/menu/",
    "sg:phone":"+1 419 756 3357",
    "sg:postcode":"44907",
    "sg:province":"OH",
    "sg:tags":[
        "american"
    ],
    "wof:name":"M J Mulligans At Paisley Park",
    "wof:placetype":"venue"
},
  "geometry": {"coordinates":[-82.532425,40.735467],"type":"Point"}
}