{
  "type": "Feature",
  "properties": {
    "addr:full": "11257 State Rte 47 W Quincy OH 43343",
    "addr:housenumber": "11257",
    "addr:postcode": "43343",
    "addr:street": "State Rte 47 W",
    "iso:country": "US",
    "sg:address": "11257 State Rte 47 W",
    "sg:city": "Quincy",
    "sg:classifiers": [
      {
        "category": "Freight",
        "type": "Transportation"
      }
    ],
    "sg:phone": "+1 937 585 4488",
    "sg:postcode": "43343",
    "sg:province": "OH",
    "wof:name": "MVC Inc",
    "wof:placetype": "venue"
  },
  "geometry": {"coordinates":[-83.962564,40.33896],"type":"Point"}
}
