{
  "type": "Feature",
  "properties": {
    "addr:full": "3001 State Rte 59 Ravenna OH 44266",
    "addr:housenumber": "3001",
    "addr:postcode": "44266",
    "addr:street": "State Rte 59",
    "iso:country": "US",
    "sg:address": "3001 State Rte 59",
    "sg:city": "Ravenna",
    "sg:classifiers": [
      {
        "category": "Autos \u0026 Motor Vehicles",
        "subcategory": "Automobile Sales",
        "type": "Retail Goods"
      }
    ],
    "sg:phone": "+1 330 297 6880",
    "sg:postcode": "44266",
    "sg:province": "OH",
    "sg:tags": [
      "used"
    ],
    "wof:name": "Globe Auto Sales",
    "wof:placetype": "venue"
  },
  "geometry": {"coordinates":[-81.286567,41.159261],"type":"Point"}
}
