{
  "type": "Feature",
  "properties": {
    "iso:country":"US",
    "sg:address":"125 Johns St",
    "sg:city":"Wellington",
    "sg:classifiers":[
        {
            "category":"Real Estate",
            "subcategory":"Real Estate Agent",
            "type":"Services"
        }
    ],
    "sg:phone":"+1 440 647 5888",
    "sg:postcode":"44090",
    "sg:province":"OH",
    "wof:name":"Heather Packett",
    "wof:placetype":"venue"
},
  "geometry": {"coordinates":[-82.220288,41.170675],"type":"Point"}
}