{
  "type": "Feature",
  "properties": {
    "iso:country":"US",
    "sg:address":"1490 N Ridge Rd",
    "sg:city":"Painesville",
    "sg:classifiers":[
        {
            "category":"Retail",
            "subcategory":"Auto Repair",
            "type":"Services"
        }
    ],
    "sg:phone":"+1 440 357 1010",
    "sg:postcode":"44077",
    "sg:province":"OH",
    "sg:tags":[
        "wrecker"
    ],
    "wof:name":"Messenger Enterprise Inc",
    "wof:placetype":"venue"
},
  "geometry": {"coordinates":[-81.22383000000001,41.740659],"type":"Point"}
}