{
  "type": "Feature",
  "properties": {
    "addr:full":"33 Standen Dr Hamilton OH 45015",
    "addr:housenumber":"33",
    "addr:postcode":"45015",
    "addr:street":"Standen Dr",
    "iso:country":"US",
    "sg:address":"33 Standen Dr",
    "sg:city":"Hamilton",
    "sg:classifiers":[
        {
            "category":"Manufacturing",
            "subcategory":"Electronics",
            "type":"Manufacturing & Wholesale Goods"
        }
    ],
    "sg:phone":"+1 513 874 1211",
    "sg:postcode":"45015",
    "sg:province":"OH",
    "sg:tags":[
        "engineering",
        "consulting",
        "analysis",
        "system"
    ],
    "wof:name":"Qlog Corp",
    "wof:placetype":"venue"
},
  "geometry": {"coordinates":[-84.512353,39.337394],"type":"Point"}
}