{
  "type": "Feature",
  "properties": {
    "iso:country":"US",
    "sg:address":"4 E Main St",
    "sg:city":"Logan",
    "sg:classifiers":[
        {
            "category":"Professional",
            "subcategory":"Lawyer & Legal Services",
            "type":"Services"
        }
    ],
    "sg:phone":"+1 740 653 8128",
    "sg:postcode":"43138",
    "sg:province":"OH",
    "sg:tags":[
        "attorney"
    ],
    "wof:name":"L Jackson Henninger & Assoc",
    "wof:placetype":"venue"
},
  "geometry": {"coordinates":[-82.408772,39.540194],"type":"Point"}
}