{
  "type": "Feature",
  "properties": {
    "iso:country":"US",
    "sg:address":"816 County Line Rd",
    "sg:city":"Westerville",
    "sg:classifiers":[
        {
            "category":"Education",
            "subcategory":"School",
            "type":"Public Place"
        }
    ],
    "sg:phone":"+1 614 797 7991",
    "sg:postcode":"43081",
    "sg:province":"OH",
    "wof:name":"Westerville City Schools",
    "wof:placetype":"venue"
},
  "geometry": {"coordinates":[-82.99447499999999,40.135949],"type":"Point"}
}