{
  "type": "Feature",
  "properties": {
    "addr:full": "816 County Line Rd Westerville OH 43081",
    "addr:housenumber": "816",
    "addr:postcode": "43081",
    "addr:street": "County Line Rd",
    "iso:country": "US",
    "sg:address": "816 County Line Rd",
    "sg:city": "Westerville",
    "sg:classifiers": [
      {
        "category": "Education",
        "subcategory": "School",
        "type": "Public Place"
      }
    ],
    "sg:phone": "+1 614 797 7991",
    "sg:postcode": "43081",
    "sg:province": "OH",
    "wof:name": "Westerville City Schools",
    "wof:placetype": "venue"
  },
  "geometry": {"coordinates":[-82.994475,40.135949],"type":"Point"}
}
