{
  "type": "Feature",
  "properties": {
    "iso:country":"US",
    "sg:address":"909 W McPherson Hwy",
    "sg:city":"Clyde",
    "sg:classifiers":[
        {
            "category":"Autos & Motor Vehicles",
            "subcategory":"Recreational Vehicle Sales",
            "type":"Retail Goods"
        }
    ],
    "sg:phone":"+1 419 547 0708",
    "sg:postcode":"43410",
    "sg:province":"OH",
    "sg:tags":[
        "equipment",
        "camping"
    ],
    "sg:website":"www.townandcountryrvcenter.com",
    "wof:name":"Town & Country Rv Center Inc",
    "wof:placetype":"venue"
},
  "geometry": {"coordinates":[-82.998623,41.316213],"type":"Point"}
}