{
  "type": "Feature",
  "properties": {
    "addr:full": "909 W McPherson Hwy Clyde OH 43410",
    "addr:housenumber": "909",
    "addr:postcode": "43410",
    "addr:street": "W Mcpherson Hwy",
    "iso:country": "US",
    "sg:address": "909 W McPherson Hwy",
    "sg:city": "Clyde",
    "sg:classifiers": [
      {
        "category": "Autos \u0026 Motor Vehicles",
        "subcategory": "Recreational Vehicle Sales",
        "type": "Retail Goods"
      }
    ],
    "sg:phone": "+1 419 547 0708",
    "sg:postcode": "43410",
    "sg:province": "OH",
    "sg:tags": [
      "equipment",
      "camping"
    ],
    "sg:website": "www.townandcountryrvcenter.com",
    "wof:name": "Town \u0026 Country Rv Center Inc",
    "wof:placetype": "venue"
  },
  "geometry": {"coordinates":[-82.998623,41.316213],"type":"Point"}
}
