{
  "type": "Feature",
  "properties": {
    "addr:full": "324 4th St Marietta OH 45750",
    "addr:housenumber": "324",
    "addr:postcode": "45750",
    "addr:street": "4Th St",
    "iso:country": "US",
    "sg:address": "324 4th St",
    "sg:city": "Marietta",
    "sg:classifiers": [
      {
        "category": "Utilities",
        "subcategory": "Natural Gas",
        "type": "Services"
      }
    ],
    "sg:phone": "+1 740 373 6545",
    "sg:postcode": "45750",
    "sg:province": "OH",
    "sg:tags": [
      "distribution"
    ],
    "wof:name": "Dominion East Ohio",
    "wof:placetype": "venue"
  },
  "geometry": {"coordinates":[-81.453566,39.418525],"type":"Point"}
}
