{
  "type": "Feature",
  "properties": {
    "iso:country":"US",
    "sg:address":"6200 Oak Tree Blvd",
    "sg:city":"Cleveland",
    "sg:classifiers":[
        {
            "category":"Real Estate",
            "subcategory":"Real Estate Agent",
            "type":"Services"
        }
    ],
    "sg:phone":"+1 216 525 0058",
    "sg:postcode":"44131",
    "sg:province":"OH",
    "sg:tags":[
        "management"
    ],
    "wof:name":"C B Richard Ellis",
    "wof:placetype":"venue"
},
  "geometry": {"coordinates":[-81.660327,41.39622],"type":"Point"}
}