{
  "type": "Feature",
  "properties": {
    "addr:full":"2847 Lagrange St Toledo OH 43608",
    "addr:housenumber":"2847",
    "addr:postcode":"43608",
    "addr:street":"Lagrange St",
    "iso:country":"US",
    "sg:address":"2847 Lagrange St",
    "sg:city":"Toledo",
    "sg:classifiers":[
        {
            "category":"Personal",
            "subcategory":"Beauty Salon",
            "type":"Services"
        }
    ],
    "sg:phone":"+1 419 241 8768",
    "sg:postcode":"43608",
    "sg:province":"OH",
    "wof:name":"Hair Connection",
    "wof:placetype":"venue"
},
  "geometry": {"coordinates":[-83.539726,41.676712],"type":"Point"}
}