{
  "type": "Feature",
  "properties": {
    "iso:country":"US",
    "sg:address":"1 Canal Square Plz",
    "sg:city":"Akron",
    "sg:classifiers":[
        {
            "category":"Real Estate",
            "subcategory":"Real Estate Operator",
            "type":"Services"
        }
    ],
    "sg:phone":"+1 330 434 5027",
    "sg:postcode":"44308",
    "sg:province":"OH",
    "sg:tags":[
        "apartment"
    ],
    "wof:name":"Warner Housing Partnership, Lp",
    "wof:placetype":"venue"
},
  "geometry": {"coordinates":[-81.52269699999999,41.080872],"type":"Point"}
}