{
  "type": "Feature",
  "properties": {
    "iso:country":"US",
    "sg:address":"2205 Puma Pl",
    "sg:city":"Hilliard",
    "sg:classifiers":[
        {
            "category":"Building & Trades",
            "subcategory":"Construction",
            "type":"Services"
        }
    ],
    "sg:phone":"+1 614 921 8653",
    "sg:postcode":"43026",
    "sg:province":"OH",
    "sg:tags":[
        "cleaning"
    ],
    "wof:name":"Whisk Away Cleaning",
    "wof:placetype":"venue"
},
  "geometry": {"coordinates":[-83.150834,39.996487],"type":"Point"}
}