{
  "type": "Feature",
  "properties": {
    "iso:country":"US",
    "sg:address":"1100 E Broad St",
    "sg:city":"Elyria",
    "sg:classifiers":[
        {
            "category":"Autos & Motor Vehicles",
            "subcategory":"Automobile Sales",
            "type":"Retail Goods"
        }
    ],
    "sg:phone":"+1 440 365 7311",
    "sg:postcode":"44035",
    "sg:province":"OH",
    "sg:tags":[
        "car",
        "dealer"
    ],
    "sg:website":"www.jackmatia.com",
    "wof:name":"Jack Matia Chevrolet Inc",
    "wof:placetype":"venue"
},
  "geometry": {"coordinates":[-82.07655800000001,41.364236],"type":"Point"}
}