{
  "type": "Feature",
  "properties": {
    "iso:country":"US",
    "sg:address":"9333 N Church Dr",
    "sg:city":"Cleveland",
    "sg:classifiers":[
        {
            "category":"Real Estate",
            "subcategory":"Real Estate Operator",
            "type":"Services"
        }
    ],
    "sg:phone":"+1 440 843 2392",
    "sg:postcode":"44130",
    "sg:province":"OH",
    "sg:tags":[
        "apartment"
    ],
    "wof:name":"Churchill Towers",
    "wof:placetype":"venue"
},
  "geometry": {"coordinates":[-81.754932,41.380476],"type":"Point"}
}