{
  "type": "Feature",
  "properties": {
    "addr:full":"2758 Eastcleft Dr Columbus OH 43221",
    "addr:housenumber":"2758",
    "addr:postcode":"43221",
    "addr:street":"Eastcleft Dr",
    "iso:country":"US",
    "sg:address":"2758 Eastcleft Dr",
    "sg:city":"Columbus",
    "sg:classifiers":[
        {
            "category":"Shopping",
            "type":"Retail Goods"
        }
    ],
    "sg:phone":"+1 614 457 2216",
    "sg:postcode":"43221",
    "sg:province":"OH",
    "sg:tags":[
        "picture",
        "frame"
    ],
    "wof:name":"Arlington Frames",
    "wof:placetype":"venue"
},
  "geometry": {"coordinates":[-83.090324,40.021202],"type":"Point"}
}