{
  "type": "Feature",
  "properties": {
    "addr:full":"898 Alhambra Rd Cleveland OH 44110",
    "addr:housenumber":"898",
    "addr:postcode":"44110",
    "addr:street":"Alhambra Rd",
    "iso:country":"US",
    "sg:address":"898 Alhambra Rd",
    "sg:city":"Cleveland",
    "sg:classifiers":[
        {
            "category":"Restaurant",
            "type":"Food & Drink"
        }
    ],
    "sg:phone":"+1 216 486 7900",
    "sg:postcode":"44110",
    "sg:province":"OH",
    "sg:tags":[
        "eating"
    ],
    "wof:name":"Carstarphens Soul Food",
    "wof:placetype":"venue"
},
  "geometry": {"coordinates":[-81.56376299999999,41.556124],"type":"Point"}
}