{
  "type": "Feature",
  "properties": {
    "addr:full":"1750 Thomas Rd SE Warren OH 44484",
    "addr:housenumber":"1750",
    "addr:postcode":"44484",
    "addr:street":"Thomas Rd Se",
    "iso:country":"US",
    "sg:address":"1750 Thomas Rd SE",
    "sg:city":"Warren",
    "sg:classifiers":[
        {
            "category":"Personal",
            "type":"Services"
        }
    ],
    "sg:phone":"+1 330 448 2347",
    "sg:postcode":"44484",
    "sg:province":"OH",
    "sg:tags":[
        "control",
        "weight"
    ],
    "wof:name":"Custom Counter Weight",
    "wof:placetype":"venue"
},
  "geometry": {"coordinates":[-80.80161,41.22381],"type":"Point"}
}