{
  "type": "Feature",
  "properties": {
    "iso:country":"US",
    "sg:address":"4300 Montgomery Rd",
    "sg:city":"Cincinnati",
    "sg:classifiers":[
        {
            "category":"Retail",
            "subcategory":"Auto Repair",
            "type":"Services"
        }
    ],
    "sg:phone":"+1 513 631 2406",
    "sg:postcode":"45212",
    "sg:province":"OH",
    "sg:tags":[
        "body",
        "automobile",
        "painting"
    ],
    "wof:name":"Center City Collision",
    "wof:placetype":"venue"
},
  "geometry": {"coordinates":[-84.45885199999999,39.156706],"type":"Point"}
}