{
  "type": "Feature",
  "properties": {
    "iso:country":"US",
    "sg:address":"1284 N Broad St",
    "sg:city":"Fairborn",
    "sg:classifiers":[
        {
            "category":"Restaurant",
            "type":"Food & Drink"
        }
    ],
    "sg:phone":"+1 937 878 4892",
    "sg:postcode":"45324",
    "sg:province":"OH",
    "wof:name":"Janya's Place",
    "wof:placetype":"venue"
},
  "geometry": {"coordinates":[-84.01240900000001,39.834838],"type":"Point"}
}