{
  "type": "Feature",
  "properties": {
    "addr:full":"7477 Nethersole Dr Cleveland OH 44130",
    "addr:housenumber":"7477",
    "addr:postcode":"44130",
    "addr:street":"Nethersole Dr",
    "iso:country":"US",
    "sg:address":"7477 Nethersole Dr",
    "sg:city":"Cleveland",
    "sg:classifiers":[
        {
            "category":"Building & Trades",
            "subcategory":"Construction",
            "type":"Services"
        }
    ],
    "sg:phone":"+1 440 234 8465",
    "sg:postcode":"44130",
    "sg:province":"OH",
    "sg:tags":[
        "residential"
    ],
    "wof:name":"McLellan Homes Inc",
    "wof:placetype":"venue"
},
  "geometry": {"coordinates":[-81.820139,41.362265],"type":"Point"}
}