{
  "type": "Feature",
  "properties": {
    "addr:full": "6389 Branch Hill-Miamiville Rd Loveland OH 45140",
    "addr:housenumber": "6389",
    "addr:postcode": "45140",
    "addr:street": "Branch Hill-Miamiville Rd",
    "iso:country": "US",
    "sg:address": "6389 Branch Hill-Miamiville Rd",
    "sg:city": "Loveland",
    "sg:classifiers": [
      {
        "category": "Building \u0026 Trades",
        "subcategory": "Construction",
        "type": "Services"
      }
    ],
    "sg:phone": "+1 513 248 1627",
    "sg:postcode": "45140",
    "sg:province": "OH",
    "sg:tags": [
      "contractor"
    ],
    "wof:name": "Mc Kay Roofing",
    "wof:placetype": "venue"
  },
  "geometry": {"coordinates":[-84.292625,39.23301],"type":"Point"}
}
