{
  "type": "Feature",
  "properties": {
    "addr:full": "270 N Main St Mansfield OH 44902",
    "addr:housenumber": "270",
    "addr:postcode": "44902",
    "addr:street": "N Main St",
    "iso:country": "US",
    "sg:address": "270 N Main St",
    "sg:city": "Mansfield",
    "sg:classifiers": [
      {
        "category": "Building \u0026 Trades",
        "subcategory": "Construction",
        "type": "Services"
      }
    ],
    "sg:phone": "+1 419 522 8766",
    "sg:postcode": "44902",
    "sg:province": "OH",
    "sg:tags": [
      "house"
    ],
    "wof:name": "Mike Kennedy",
    "wof:placetype": "venue"
  },
  "geometry": {"coordinates":[-82.515,40.765816],"type":"Point"}
}
