{
  "type": "Feature",
  "properties": {
    "iso:country":"US",
    "sg:address":"270 N Main St",
    "sg:city":"Mansfield",
    "sg:classifiers":[
        {
            "category":"Building & Trades",
            "subcategory":"Construction",
            "type":"Services"
        }
    ],
    "sg:phone":"+1 419 522 8766",
    "sg:postcode":"44902",
    "sg:province":"OH",
    "sg:tags":[
        "house"
    ],
    "wof:name":"Mike Kennedy",
    "wof:placetype":"venue"
},
  "geometry": {"coordinates":[-82.515,40.765816],"type":"Point"}
}