{
  "type": "Feature",
  "properties": {
    "addr:full":"19147 Eastlook Rd Cleveland OH 44116",
    "addr:housenumber":"19147",
    "addr:postcode":"44116",
    "addr:street":"Eastlook Rd",
    "iso:country":"US",
    "sg:address":"19147 Eastlook Rd",
    "sg:city":"Cleveland",
    "sg:classifiers":[
        {
            "category":"Organizations",
            "subcategory":"Religious Organization",
            "type":"Services"
        }
    ],
    "sg:phone":"+1 440 356 0056",
    "sg:postcode":"44116",
    "sg:province":"OH",
    "sg:tags":[
        "church"
    ],
    "wof:name":"Rocky River Baptist Church",
    "wof:placetype":"venue"
},
  "geometry": {"coordinates":[-81.835711,41.480218],"type":"Point"}
}