{
  "type": "Feature",
  "properties": {
    "addr:full":"106 W Main St Woodville OH 43469",
    "addr:housenumber":"106",
    "addr:postcode":"43469",
    "addr:street":"W Main St",
    "iso:country":"US",
    "sg:address":"106 W Main St",
    "sg:city":"Woodville",
    "sg:classifiers":[
        {
            "category":"Food & Beverages",
            "subcategory":"Groceries & Convenience Stores",
            "type":"Retail Goods"
        }
    ],
    "sg:phone":"+1 419 849 2333",
    "sg:postcode":"43469",
    "sg:province":"OH",
    "sg:tags":[
        "grocer"
    ],
    "wof:name":"Del's Super Market Inc",
    "wof:placetype":"venue"
},
  "geometry": {"coordinates":[-83.364177,41.450986],"type":"Point"}
}