{
  "type": "Feature",
  "properties": {
    "addr:full": "216 S Madison St Delta OH 43515",
    "addr:housenumber": "216",
    "addr:postcode": "43515",
    "addr:street": "S Madison St",
    "iso:country": "US",
    "sg:address": "216 S Madison St",
    "sg:city": "Delta",
    "sg:classifiers": [
      {
        "category": "Restaurant",
        "type": "Food \u0026 Drink"
      }
    ],
    "sg:phone": "+1 419 826 3493",
    "sg:postcode": "43515",
    "sg:province": "OH",
    "sg:tags": [
      "eating"
    ],
    "wof:name": "Rosabelle Krauss",
    "wof:placetype": "venue"
  },
  "geometry": {"coordinates":[-84.003665,41.571827],"type":"Point"}
}
