{
  "type": "Feature",
  "properties": {
    "addr:full":"104 Top St South Point OH 45680",
    "addr:housenumber":"104",
    "addr:postcode":"45680",
    "addr:street":"Top St",
    "iso:country":"US",
    "sg:address":"104 Top St",
    "sg:city":"South Point",
    "sg:classifiers":[
        {
            "category":"Shopping",
            "type":"Retail Goods"
        }
    ],
    "sg:phone":"+1 740 894 6311",
    "sg:postcode":"45680",
    "sg:province":"OH",
    "sg:tags":[
        "sales",
        "install",
        "accessory"
    ],
    "sg:website":"www.streetproducts.com",
    "wof:name":"Street Products Car Audio",
    "wof:placetype":"venue"
},
  "geometry": {"coordinates":[-82.566676,38.420682],"type":"Point"}
}