{
  "type": "Feature",
  "properties": {
    "addr:full": "771 Central Ave Franklin OH 45005",
    "addr:housenumber": "771",
    "addr:postcode": "45005",
    "addr:street": "Central Ave",
    "iso:country": "US",
    "sg:address": "771 Central Ave",
    "sg:city": "Franklin",
    "sg:classifiers": [
      {
        "category": "Personal",
        "subcategory": "Beauty Salon",
        "type": "Services"
      }
    ],
    "sg:phone": "+1 937 746 5300",
    "sg:postcode": "45005",
    "sg:province": "OH",
    "wof:name": "Village Hairstylist",
    "wof:placetype": "venue"
  },
  "geometry": {"coordinates":[-84.323704,39.584058],"type":"Point"}
}
