{
  "type": "Feature",
  "properties": {
    "addr:full": "520 Boardman Canfield Rd Youngstown OH 44512",
    "addr:housenumber": "520",
    "addr:postcode": "44512",
    "addr:street": "Boardman Canfield Rd",
    "iso:country": "US",
    "sg:address": "520 Boardman Canfield Rd",
    "sg:city": "Youngstown",
    "sg:classifiers": [
      {
        "category": "Shopping",
        "subcategory": "Clothing, Apparel, \u0026 Fashions",
        "type": "Retail Goods"
      }
    ],
    "sg:phone": "+1 330 726 8640",
    "sg:postcode": "44512",
    "sg:province": "OH",
    "wof:name": "United Clothing Inc",
    "wof:placetype": "venue"
  },
  "geometry": {"coordinates":[-80.67868,41.024548],"type":"Point"}
}
