{
  "type": "Feature",
  "properties": {
    "iso:country":"US",
    "sg:address":"6736 Erie Ave N",
    "sg:city":"Canal Fulton",
    "sg:classifiers":[
        {
            "category":"Building & Trades",
            "subcategory":"Plumbing",
            "type":"Services"
        }
    ],
    "sg:phone":"+1 330 854 4405",
    "sg:postcode":"44614",
    "sg:province":"OH",
    "sg:tags":[
        "septic"
    ],
    "wof:name":"Aeration Specialties Inc",
    "wof:placetype":"venue"
},
  "geometry": {"coordinates":[-81.586197,40.879799],"type":"Point"}
}