{
  "type": "Feature",
  "properties": {
    "iso:country":"US",
    "sg:address":"6067 Brandt Pike",
    "sg:city":"Dayton",
    "sg:classifiers":[
        {
            "category":"Shopping",
            "subcategory":"Tobacco",
            "type":"Retail Goods"
        }
    ],
    "sg:phone":"+1 937 233 8153",
    "sg:postcode":"45424",
    "sg:province":"OH",
    "sg:tags":[
        "product"
    ],
    "wof:name":"Smokers Outlet",
    "wof:placetype":"venue"
},
  "geometry": {"coordinates":[-84.115459,39.844502],"type":"Point"}
}