{
  "type": "Feature",
  "properties": {
    "addr:full": "4011 E Wallings Rd Broadview Heights OH 44147",
    "addr:housenumber": "4011",
    "addr:postcode": "44147",
    "addr:street": "E Wallings Rd",
    "iso:country": "US",
    "sg:address": "4011 E Wallings Rd",
    "sg:city": "Broadview Heights",
    "sg:classifiers": [
      {
        "category": "Building \u0026 Trades",
        "subcategory": "Landscaping Services",
        "type": "Services"
      }
    ],
    "sg:phone": "+1 440 838 5720",
    "sg:postcode": "44147",
    "sg:province": "OH",
    "wof:name": "Rices Seasons Landscaping",
    "wof:placetype": "venue"
  },
  "geometry": {"coordinates":[-81.658016,41.344897],"type":"Point"}
}
