{
  "type": "Feature",
  "properties": {
    "addr:full": "3312 Youngstown Kingsville Rd Cortland OH 44410",
    "addr:housenumber": "3312",
    "addr:postcode": "44410",
    "addr:street": "Youngstown Kingsville Rd",
    "iso:country": "US",
    "sg:address": "3312 Youngstown Kingsville Rd",
    "sg:city": "Cortland",
    "sg:classifiers": [
      {
        "category": "Fast Food",
        "type": "Food \u0026 Drink"
      },
      {
        "category": "Restaurant",
        "type": "Food \u0026 Drink"
      }
    ],
    "sg:phone": "+1 330 637 9552",
    "sg:postcode": "44410",
    "sg:province": "OH",
    "sg:tags": [
      "take"
    ],
    "wof:name": "Bullet Motorsports",
    "wof:placetype": "venue"
  },
  "geometry": {"coordinates":[-80.655632,41.306806],"type":"Point"}
}
