{
  "type": "Feature",
  "properties": {
    "iso:country":"US",
    "sg:address":"4950 Oxford Milford Rd",
    "sg:city":"Oxford",
    "sg:phone":"+1 513 523 7291",
    "sg:postcode":"45056",
    "sg:province":"OH",
    "sg:tags":[
        "farm",
        "corn"
    ],
    "wof:name":"Butterfield Farms",
    "wof:placetype":"venue"
},
  "geometry": {"coordinates":[-84.70277400000001,39.518824],"type":"Point"}
}