{
  "type": "Feature",
  "properties": {
    "addr:full": "328 Southpark Center Cleveland OH 44136",
    "addr:housenumber": "328",
    "addr:postcode": "44136",
    "addr:street": "Southpark Center",
    "iso:country": "US",
    "sg:address": "328 Southpark Center",
    "sg:city": "Cleveland",
    "sg:classifiers": [
      {
        "category": "Shopping",
        "subcategory": "Clothing, Apparel, \u0026 Fashions",
        "type": "Retail Goods"
      }
    ],
    "sg:phone": "+1 440 238 3959",
    "sg:postcode": "44136",
    "sg:province": "OH",
    "wof:name": "Weathervane",
    "wof:placetype": "venue"
  },
  "geometry": {"coordinates":[-81.820449,41.310925],"type":"Point"}
}
