{
  "type": "Feature",
  "properties": {
    "addr:full":"10104 Kenwood Rd Cincinnati OH 45242",
    "addr:housenumber":"10104",
    "addr:postcode":"45242",
    "addr:street":"Kenwood Rd",
    "iso:country":"US",
    "sg:address":"10104 Kenwood Rd",
    "sg:city":"Cincinnati",
    "sg:classifiers":[
        {
            "category":"Building & Trades",
            "subcategory":"Plumbing",
            "type":"Services"
        }
    ],
    "sg:phone":"+1 513 889 5755",
    "sg:postcode":"45242",
    "sg:province":"OH",
    "sg:tags":[
        "installation",
        "sprinkler",
        "system"
    ],
    "wof:name":"Cdfc Fire Sprnklr Systems LLC",
    "wof:placetype":"venue"
},
  "geometry": {"coordinates":[-84.37552599999999,39.245647],"type":"Point"}
}