{
  "type": "Feature",
  "properties": {
    "iso:country":"US",
    "sg:address":"135 W Dorothy Ln",
    "sg:city":"Dayton",
    "sg:classifiers":[
        {
            "category":"Personal",
            "type":"Services"
        }
    ],
    "sg:phone":"+1 937 395 1770",
    "sg:postcode":"45429",
    "sg:province":"OH",
    "sg:tags":[
        "electrolysis"
    ],
    "wof:name":"Oakwood Electrolysis",
    "wof:placetype":"venue"
},
  "geometry": {"coordinates":[-84.172481,39.704634],"type":"Point"}
}