{
  "type": "Feature",
  "properties": {
    "iso:country":"US",
    "sg:address":"1582 Westdale Rd",
    "sg:city":"Cleveland",
    "sg:classifiers":[
        {
            "category":"Wholesale",
            "subcategory":"Machinery & Supplies",
            "type":"Manufacturing & Wholesale Goods"
        }
    ],
    "sg:phone":"+1 440 942 9011",
    "sg:postcode":"44121",
    "sg:province":"OH",
    "sg:tags":[
        "equipment",
        "industrial",
        "representative",
        "mfg"
    ],
    "wof:name":"Trinity Machine Tool Company",
    "wof:placetype":"venue"
},
  "geometry": {"coordinates":[-81.528906,41.518735],"type":"Point"}
}