{
  "type": "Feature",
  "properties": {
    "addr:full": "1978 W 74th St Cleveland OH 44102",
    "addr:housenumber": "1978",
    "addr:postcode": "44102",
    "addr:street": "W 74Th St",
    "iso:country": "US",
    "sg:address": "1978 W 74th St",
    "sg:city": "Cleveland",
    "sg:classifiers": [
      {
        "category": "Manufacturing",
        "subcategory": "Tools \u0026 Machinery",
        "type": "Manufacturing \u0026 Wholesale Goods"
      }
    ],
    "sg:phone": "+1 216 961 4550",
    "sg:postcode": "44102",
    "sg:province": "OH",
    "sg:tags": [
      "mfg",
      "equipment",
      "feeding",
      "vibratory"
    ],
    "sg:website": "www.stainlessautomation.com",
    "wof:name": "Stainless Automation",
    "wof:placetype": "venue"
  },
  "geometry": {"coordinates":[-81.73579,41.478092],"type":"Point"}
}
