{
  "type": "Feature",
  "properties": {
    "iso:country":"US",
    "sg:address":"12568 Woodberry Ln",
    "sg:city":"Strongsville",
    "sg:classifiers":[
        {
            "category":"Banks & Credit Unions",
            "subcategory":"Financial Services",
            "type":"Services"
        }
    ],
    "sg:phone":"+1 440 238 9464",
    "sg:postcode":"44149",
    "sg:province":"OH",
    "sg:tags":[
        "trust",
        "management"
    ],
    "wof:name":"Redella Family Trust",
    "wof:placetype":"venue"
},
  "geometry": {"coordinates":[-81.870472,41.321177],"type":"Point"}
}