{
  "type": "Feature",
  "properties": {
    "addr:full": "12568 Woodberry Ln Strongsville OH 44149",
    "addr:housenumber": "12568",
    "addr:postcode": "44149",
    "addr:street": "Woodberry Ln",
    "iso:country": "US",
    "sg:address": "12568 Woodberry Ln",
    "sg:city": "Strongsville",
    "sg:classifiers": [
      {
        "category": "Banks \u0026 Credit Unions",
        "subcategory": "Financial Services",
        "type": "Services"
      }
    ],
    "sg:phone": "+1 440 238 9464",
    "sg:postcode": "44149",
    "sg:province": "OH",
    "sg:tags": [
      "trust",
      "management"
    ],
    "wof:name": "Redella Family Trust",
    "wof:placetype": "venue"
  },
  "geometry": {"coordinates":[-81.870472,41.321177],"type":"Point"}
}
