{
  "type": "Feature",
  "properties": {
    "addr:full": "98 Limestone Blvd Chillicothe OH 45601",
    "addr:housenumber": "98",
    "addr:postcode": "45601",
    "addr:street": "Limestone Blvd",
    "iso:country": "US",
    "sg:address": "98 Limestone Blvd",
    "sg:city": "Chillicothe",
    "sg:classifiers": [
      {
        "category": "Organizations",
        "subcategory": "Religious Organization",
        "type": "Services"
      }
    ],
    "sg:phone": "+1 740 775 6508",
    "sg:postcode": "45601",
    "sg:province": "OH",
    "sg:tags": [
      "clergy"
    ],
    "wof:name": "Steven J Schmidt",
    "wof:placetype": "venue"
  },
  "geometry": {"coordinates":[-83.019492,39.346169],"type":"Point"}
}
