{
  "type": "Feature",
  "properties": {
    "iso:country":"US",
    "sg:address":"2097 Irvin Rd",
    "sg:city":"Jamestown",
    "sg:classifiers":[
        {
            "category":"Freight",
            "type":"Transportation"
        }
    ],
    "sg:phone":"+1 937 675 2066",
    "sg:postcode":"45335",
    "sg:province":"OH",
    "sg:tags":[
        "operator",
        "local",
        "trucking"
    ],
    "wof:name":"Ryan Reed",
    "wof:placetype":"venue"
},
  "geometry": {"coordinates":[-83.75626200000001,39.609648],"type":"Point"}
}