{
  "type": "Feature",
  "properties": {
    "addr:full": "2097 Irvin Rd Jamestown OH 45335",
    "addr:housenumber": "2097",
    "addr:postcode": "45335",
    "addr:street": "Irvin Rd",
    "iso:country": "US",
    "sg:address": "2097 Irvin Rd",
    "sg:city": "Jamestown",
    "sg:classifiers": [
      {
        "category": "Freight",
        "type": "Transportation"
      }
    ],
    "sg:phone": "+1 937 675 2066",
    "sg:postcode": "45335",
    "sg:province": "OH",
    "sg:tags": [
      "operator",
      "local",
      "trucking"
    ],
    "wof:name": "Ryan Reed",
    "wof:placetype": "venue"
  },
  "geometry": {"coordinates":[-83.756262,39.609648],"type":"Point"}
}
