{
  "type": "Feature",
  "properties": {
    "addr:full": "1169 E Main St Newark OH 43055",
    "addr:housenumber": "1169",
    "addr:postcode": "43055",
    "addr:street": "E Main St",
    "iso:country": "US",
    "sg:address": "1169 E Main St",
    "sg:city": "Newark",
    "sg:classifiers": [
      {
        "category": "Wholesale",
        "subcategory": "Machinery \u0026 Supplies",
        "type": "Manufacturing \u0026 Wholesale Goods"
      },
      {
        "category": "Autos \u0026 Motor Vehicles",
        "subcategory": "Auto Supplies",
        "type": "Retail Goods"
      }
    ],
    "sg:phone": "+1 740 345 6202",
    "sg:postcode": "43055",
    "sg:province": "OH",
    "sg:tags": [
      "filter",
      "industrial",
      "gas"
    ],
    "wof:name": "Ohio Industrial Filter Product",
    "wof:placetype": "venue"
  },
  "geometry": {"coordinates":[-82.356926,40.06176],"type":"Point"}
}
