{
  "type": "Feature",
  "properties": {
    "addr:full":"6407 Warrick St Cincinnati OH 45227",
    "addr:housenumber":"6407",
    "addr:postcode":"45227",
    "addr:street":"Warrick St",
    "iso:country":"US",
    "sg:address":"6407 Warrick St",
    "sg:city":"Cincinnati",
    "sg:classifiers":[
        {
            "category":"Manufacturing",
            "subcategory":"Electronics",
            "type":"Manufacturing & Wholesale Goods"
        },
        {
            "category":"Manufacturing",
            "subcategory":"Tools & Machinery",
            "type":"Manufacturing & Wholesale Goods"
        }
    ],
    "sg:phone":"+1 513 271 8400",
    "sg:postcode":"45227",
    "sg:province":"OH",
    "sg:tags":[
        "mfg",
        "tube",
        "supply",
        "equipment",
        "electron",
        "electronic"
    ],
    "wof:name":"Frank Simpson Co Inc",
    "wof:placetype":"venue"
},
  "geometry": {"coordinates":[-84.38525300000001,39.159087],"type":"Point"}
}