{
  "type": "Feature",
  "properties": {
    "addr:full": "2533 Rondowa Ave Dayton OH 45404",
    "addr:housenumber": "2533",
    "addr:postcode": "45404",
    "addr:street": "Rondowa Ave",
    "iso:country": "US",
    "sg:address": "2533 Rondowa Ave",
    "sg:city": "Dayton",
    "sg:classifiers": [
      {
        "category": "Building \u0026 Trades",
        "subcategory": "Plumbing",
        "type": "Services"
      }
    ],
    "sg:phone": "+1 937 233 7983",
    "sg:postcode": "45404",
    "sg:province": "OH",
    "sg:tags": [
      "contractor"
    ],
    "wof:name": "Ayers Heating Cooling",
    "wof:placetype": "venue"
  },
  "geometry": {"coordinates":[-84.137503,39.79445],"type":"Point"}
}
