{
  "type": "Feature",
  "properties": {
    "addr:full": "30100 Chagrin Blvd Cleveland OH 44124",
    "addr:postcode": "30100;44124",
    "addr:street": "Chagrin Blvd",
    "iso:country": "US",
    "sg:address": "30100 Chagrin Blvd",
    "sg:city": "Cleveland",
    "sg:classifiers": [
      {
        "category": "Professional",
        "subcategory": "Lawyer \u0026 Legal Services",
        "type": "Services"
      }
    ],
    "sg:phone": "+1 216 831 8083",
    "sg:postcode": "44124",
    "sg:province": "OH",
    "sg:tags": [
      "attorney"
    ],
    "wof:name": "H Charles Thomey Esq LLC",
    "wof:placetype": "venue"
  },
  "geometry": {"coordinates":[-81.456519,41.459923],"type":"Point"}
}
