{
  "type": "Feature",
  "properties": {
    "iso:country":"US",
    "sg:address":"1020 S Detroit St",
    "sg:city":"Bellefontaine",
    "sg:phone":"+1 937 592 3906",
    "sg:postcode":"43311",
    "sg:province":"OH",
    "sg:tags":[
        "oil"
    ],
    "wof:name":"Heiby Oil Co",
    "wof:placetype":"venue"
},
  "geometry": {"coordinates":[-83.763065,40.347851],"type":"Point"}
}