{
  "type": "Feature",
  "properties": {
    "addr:full": "2335 W 11th St Cleveland OH 44113",
    "addr:housenumber": "2335",
    "addr:postcode": "44113",
    "addr:street": "W 11Th St",
    "iso:country": "US",
    "sg:address": "2335 W 11th St",
    "sg:city": "Cleveland",
    "sg:classifiers": [
      {
        "category": "Real Estate",
        "subcategory": "Architect",
        "type": "Services"
      }
    ],
    "sg:phone": "+1 216 621 3432",
    "sg:postcode": "44113",
    "sg:province": "OH",
    "wof:name": "Erbach Architects Inc",
    "wof:placetype": "venue"
  },
  "geometry": {"coordinates":[-81.689254,41.48178],"type":"Point"}
}
