{
  "type": "Feature",
  "properties": {
    "addr:full":"4803 N Myers Rd Geneva OH 44041",
    "addr:housenumber":"4803",
    "addr:postcode":"44041",
    "addr:street":"N Myers Rd",
    "iso:country":"US",
    "sg:address":"4803 N Myers Rd",
    "sg:city":"Geneva",
    "sg:classifiers":[
        {
            "category":"Retail",
            "subcategory":"Auto Repair",
            "type":"Services"
        }
    ],
    "sg:phone":"+1 440 466 3311",
    "sg:postcode":"44041",
    "sg:province":"OH",
    "sg:tags":[
        "repairing",
        "automobile"
    ],
    "wof:name":"Chapel Auto Svc Inc",
    "wof:placetype":"venue"
},
  "geometry": {"coordinates":[-80.916573,41.859184],"type":"Point"}
}