{
  "type": "Feature",
  "properties": {
    "addr:full": "7908 W Chester Rd West Chester OH 45069",
    "addr:housenumber": "7908",
    "addr:postcode": "45069",
    "addr:street": "W Chester Rd",
    "iso:country": "US",
    "sg:address": "7908 W Chester Rd",
    "sg:city": "West Chester",
    "sg:classifiers": [
      {
        "category": "Professional",
        "subcategory": "Research",
        "type": "Services"
      }
    ],
    "sg:phone": "+1 513 755 9842",
    "sg:postcode": "45069",
    "sg:province": "OH",
    "sg:tags": [
      "environmental",
      "ecological"
    ],
    "sg:website": "www.ats-water.com",
    "wof:name": "Advanced Treatment Science Inc",
    "wof:placetype": "venue"
  },
  "geometry": {"coordinates":[-84.365065,39.318022],"type":"Point"}
}
