{
  "type": "Feature",
  "properties": {
    "addr:full": "331 N Hillcrest Dr Wooster OH 44691",
    "addr:housenumber": "331",
    "addr:postcode": "44691",
    "addr:street": "N Hillcrest Dr",
    "iso:country": "US",
    "sg:address": "331 N Hillcrest Dr",
    "sg:city": "Wooster",
    "sg:classifiers": [
      {
        "category": "Wholesale",
        "subcategory": "Farm Supplies",
        "type": "Manufacturing \u0026 Wholesale Goods"
      }
    ],
    "sg:phone": "+1 330 264 3500",
    "sg:postcode": "44691",
    "sg:province": "OH",
    "wof:name": "Farmers Exchange",
    "wof:placetype": "venue"
  },
  "geometry": {"coordinates":[-81.905365,40.796607],"type":"Point"}
}
