{
  "type": "Feature",
  "properties": {
    "addr:full":"137 Leland Ave Columbus OH 43214",
    "addr:housenumber":"137",
    "addr:postcode":"43214",
    "addr:street":"Leland Ave",
    "iso:country":"US",
    "sg:address":"137 Leland Ave",
    "sg:city":"Columbus",
    "sg:classifiers":[
        {
            "category":"Manufacturing",
            "subcategory":"Printing",
            "type":"Manufacturing & Wholesale Goods"
        }
    ],
    "sg:phone":"+1 614 846 4126",
    "sg:postcode":"43214",
    "sg:province":"OH",
    "sg:tags":[
        "book"
    ],
    "wof:name":"Luna Bisonte Prods",
    "wof:placetype":"venue"
},
  "geometry": {"coordinates":[-83.02063200000001,40.063428],"type":"Point"}
}