{
  "type": "Feature",
  "properties": {
    "iso:country":"US",
    "sg:address":"3652 Round Bottom Rd",
    "sg:city":"Cincinnati",
    "sg:classifiers":[
        {
            "category":"Building & Trades",
            "subcategory":"Construction",
            "type":"Services"
        }
    ],
    "sg:phone":"+1 513 561 9970",
    "sg:postcode":"45244",
    "sg:province":"OH",
    "sg:tags":[
        "roofing",
        "contractor"
    ],
    "wof:name":"Forshee",
    "wof:placetype":"venue"
},
  "geometry": {"coordinates":[-84.35494300000001,39.126706],"type":"Point"}
}