{
  "type": "Feature",
  "properties": {
    "addr:full": "429 N Broadway St Green Springs OH 44836",
    "addr:housenumber": "429",
    "addr:postcode": "44836",
    "addr:street": "N Broadway St",
    "iso:country": "US",
    "sg:address": "429 N Broadway St",
    "sg:city": "Green Springs",
    "sg:classifiers": [
      {
        "category": "Organizations",
        "subcategory": "Religious Organization",
        "type": "Services"
      }
    ],
    "sg:phone": "+1 419 639 3140",
    "sg:postcode": "44836",
    "sg:province": "OH",
    "sg:tags": [
      "monastery",
      "convent"
    ],
    "wof:name": "Franciscan Sisters",
    "wof:placetype": "venue"
  },
  "geometry": {"coordinates":[-83.051956,41.264364],"type":"Point"}
}
