{
  "type": "Feature",
  "properties": {
    "addr:full":"909 W North Bend Rd Cincinnati OH 45224",
    "addr:housenumber":"909",
    "addr:postcode":"45224",
    "addr:street":"W North Bend Rd",
    "iso:country":"US",
    "sg:address":"909 W North Bend Rd",
    "sg:city":"Cincinnati",
    "sg:classifiers":[
        {
            "category":"Restaurant",
            "type":"Food & Drink"
        }
    ],
    "sg:phone":"+1 513 242 6731",
    "sg:postcode":"45224",
    "sg:province":"OH",
    "wof:name":"Finneytown Restaurant",
    "wof:placetype":"venue"
},
  "geometry": {"coordinates":[-84.51894,39.201137],"type":"Point"}
}