{
  "type": "Feature",
  "properties": {
    "addr:full": "2101 Aetna Rd Ashtabula OH 44004",
    "addr:housenumber": "2101",
    "addr:postcode": "44004",
    "addr:street": "Aetna Rd",
    "iso:country": "US",
    "sg:address": "2101 Aetna Rd",
    "sg:city": "Ashtabula",
    "sg:classifiers": [
      {
        "category": "Building \u0026 Trades",
        "subcategory": "Plumbing",
        "type": "Services"
      }
    ],
    "sg:phone": "+1 440 998 7252",
    "sg:postcode": "44004",
    "sg:province": "OH",
    "sg:tags": [
      "sheet",
      "work",
      "metal",
      "contractor"
    ],
    "wof:name": "Have Inc",
    "wof:placetype": "venue"
  },
  "geometry": {"coordinates":[-80.766618,41.863597],"type":"Point"}
}
