{
  "type": "Feature",
  "properties": {
    "iso:country":"US",
    "sg:address":"2101 Aetna Rd",
    "sg:city":"Ashtabula",
    "sg:classifiers":[
        {
            "category":"Building & Trades",
            "subcategory":"Plumbing",
            "type":"Services"
        }
    ],
    "sg:phone":"+1 440 998 7252",
    "sg:postcode":"44004",
    "sg:province":"OH",
    "sg:tags":[
        "sheet",
        "work",
        "metal",
        "contractor"
    ],
    "wof:name":"Have Inc",
    "wof:placetype":"venue"
},
  "geometry": {"coordinates":[-80.76661799999999,41.863597],"type":"Point"}
}