{
  "type": "Feature",
  "properties": {
    "iso:country":"US",
    "sg:address":"2460 Navarre Ave",
    "sg:city":"Oregon",
    "sg:classifiers":[
        {
            "category":"Real Estate",
            "subcategory":"Real Estate Services",
            "type":"Services"
        }
    ],
    "sg:phone":"+1 419 691 0999",
    "sg:postcode":"43616",
    "sg:province":"OH",
    "sg:tags":[
        "company",
        "title"
    ],
    "wof:name":"Chicago Title Co",
    "wof:placetype":"venue"
},
  "geometry": {"coordinates":[-83.4901,41.636538],"type":"Point"}
}