{
  "type": "Feature",
  "properties": {
    "addr:full": "200 Front St Marietta OH 45750",
    "addr:housenumber": "200",
    "addr:postcode": "45750",
    "addr:street": "Front St",
    "iso:country": "US",
    "sg:address": "200 Front St",
    "sg:city": "Marietta",
    "sg:classifiers": [
      {
        "category": "Home \u0026 Garden",
        "subcategory": "Furniture",
        "type": "Retail Goods"
      }
    ],
    "sg:phone": "+1 740 373 8444",
    "sg:postcode": "45750",
    "sg:province": "OH",
    "sg:website": "www.topdrawerfurniture.com",
    "wof:name": "Top Drawer Furniture \u0026 Design",
    "wof:placetype": "venue"
  },
  "geometry": {"coordinates":[-81.454265,39.412817],"type":"Point"}
}
