{
  "type": "Feature",
  "properties": {
    "iso:country":"US",
    "sg:address":"904 Northboro Dr",
    "sg:city":"Cleveland",
    "sg:classifiers":[
        {
            "category":"Real Estate",
            "subcategory":"Architect",
            "type":"Services"
        }
    ],
    "sg:phone":"+1 216 314 4586",
    "sg:postcode":"44143",
    "sg:province":"OH",
    "wof:name":"Cleveland Design & Constr",
    "wof:placetype":"venue"
},
  "geometry": {"coordinates":[-81.443226,41.535732],"type":"Point"}
}