{
  "type": "Feature",
  "properties": {
    "iso:country":"US",
    "sg:address":"301 3rd St",
    "sg:city":"Kalida",
    "sg:classifiers":[
        {
            "category":"Education",
            "subcategory":"School",
            "type":"Public Place"
        }
    ],
    "sg:phone":"+1 419 532 3534",
    "sg:postcode":"45853",
    "sg:province":"OH",
    "wof:name":"Kalida Local School District",
    "wof:placetype":"venue"
},
  "geometry": {"coordinates":[-84.202904,40.982046],"type":"Point"}
}