{
  "type": "Feature",
  "properties": {
    "addr:full": "301 3rd St Kalida OH 45853",
    "addr:housenumber": "301",
    "addr:postcode": "45853",
    "addr:street": "3Rd St",
    "iso:country": "US",
    "sg:address": "301 3rd St",
    "sg:city": "Kalida",
    "sg:classifiers": [
      {
        "category": "Education",
        "subcategory": "School",
        "type": "Public Place"
      }
    ],
    "sg:phone": "+1 419 532 3534",
    "sg:postcode": "45853",
    "sg:province": "OH",
    "wof:name": "Kalida Local School District",
    "wof:placetype": "venue"
  },
  "geometry": {"coordinates":[-84.202904,40.982046],"type":"Point"}
}
