{
  "type": "Feature",
  "properties": {
    "addr:full": "104 Robinson Ave Columbus Grove OH 45830",
    "addr:housenumber": "104",
    "addr:postcode": "45830",
    "addr:street": "Robinson Ave Columbus Grove",
    "iso:country": "US",
    "sg:address": "104 Robinson Ave",
    "sg:city": "Columbus Grove",
    "sg:classifiers": [
      {
        "category": "Organizations",
        "subcategory": "Religious Organization",
        "type": "Services"
      }
    ],
    "sg:phone": "+1 419 659 5980",
    "sg:postcode": "45830",
    "sg:province": "OH",
    "wof:name": "Ohio Conference of SDA (inc)",
    "wof:placetype": "venue"
  },
  "geometry": {"coordinates":[-84.054084,40.927986],"type":"Point"}
}
