{
  "type": "Feature",
  "properties": {
    "iso:country":"US",
    "sg:address":"586 Schocalog Rd",
    "sg:city":"Akron",
    "sg:classifiers":[
        {
            "category":"Organizations",
            "subcategory":"Religious Organization",
            "type":"Services"
        }
    ],
    "sg:phone":"+1 330 836 3148",
    "sg:postcode":"44320",
    "sg:province":"OH",
    "sg:tags":[
        "clergy"
    ],
    "wof:name":"Luther C Cooper",
    "wof:placetype":"venue"
},
  "geometry": {"coordinates":[-81.60413699999999,41.107811],"type":"Point"}
}