{
  "type": "Feature",
  "properties": {
    "iso:country":"US",
    "sg:address":"444 E 3rd St",
    "sg:city":"Dayton",
    "sg:classifiers":[
        {
            "category":"Organizations",
            "subcategory":"Professional Association",
            "type":"Services"
        }
    ],
    "sg:phone":"+1 937 222 4911",
    "sg:postcode":"45403",
    "sg:province":"OH",
    "wof:name":"Dayton Area Auto Dealers Assn",
    "wof:placetype":"venue"
},
  "geometry": {"coordinates":[-84.18583599999999,39.760408],"type":"Point"}
}