{
  "type": "Feature",
  "properties": {
    "addr:full": "444 E 3rd St Dayton OH 45403",
    "addr:housenumber": "444",
    "addr:postcode": "45403",
    "addr:street": "E 3Rd St",
    "iso:country": "US",
    "sg:address": "444 E 3rd St",
    "sg:city": "Dayton",
    "sg:classifiers": [
      {
        "category": "Organizations",
        "subcategory": "Professional Association",
        "type": "Services"
      }
    ],
    "sg:phone": "+1 937 222 4911",
    "sg:postcode": "45403",
    "sg:province": "OH",
    "wof:name": "Dayton Area Auto Dealers Assn",
    "wof:placetype": "venue"
  },
  "geometry": {"coordinates":[-84.185836,39.760408],"type":"Point"}
}
