{
  "type": "Feature",
  "properties": {
    "addr:full": "9310 Hamilton Dr Mentor OH 44060",
    "addr:postcode": "9310;44060",
    "addr:street": "Hamilton Dr",
    "iso:country": "US",
    "sg:address": "9310 Hamilton Dr",
    "sg:city": "Mentor",
    "sg:classifiers": [
      {
        "category": "Autos \u0026 Motor Vehicles",
        "subcategory": "Automobile Sales",
        "type": "Retail Goods"
      }
    ],
    "sg:phone": "+1 440 357 0251",
    "sg:postcode": "44060",
    "sg:province": "OH",
    "sg:tags": [
      "car",
      "dealer"
    ],
    "wof:name": "Pettifer \u0026 Sons Auto Recond",
    "wof:placetype": "venue"
  },
  "geometry": {"coordinates":[-81.306094,41.69429],"type":"Point"}
}
