{
  "type": "Feature",
  "properties": {
    "iso:country":"US",
    "sg:address":"305 9th St",
    "sg:city":"Wellsville",
    "sg:classifiers":[
        {
            "category":"Education",
            "subcategory":"School",
            "type":"Public Place"
        }
    ],
    "sg:phone":"+1 330 532 1370",
    "sg:postcode":"43968",
    "sg:province":"OH",
    "sg:website":"www.wellsville.k12.oh.us",
    "wof:name":"Mac Donald Elementary School",
    "wof:placetype":"venue"
},
  "geometry": {"coordinates":[-80.647434,40.604424],"type":"Point"}
}