{
  "type": "Feature",
  "properties": {
    "iso:country":"US",
    "sg:address":"160 E Broad St",
    "sg:city":"Pataskala",
    "sg:classifiers":[
        {
            "category":"Real Estate",
            "subcategory":"Real Estate Services",
            "type":"Services"
        }
    ],
    "sg:phone":"+1 740 964 6911",
    "sg:postcode":"43062",
    "sg:province":"OH",
    "sg:tags":[
        "company",
        "title"
    ],
    "wof:name":"Title First",
    "wof:placetype":"venue"
},
  "geometry": {"coordinates":[-82.67339200000001,40.003497],"type":"Point"}
}