{
  "type": "Feature",
  "properties": {
    "addr:full": "160 E Broad St Pataskala OH 43062",
    "addr:housenumber": "160",
    "addr:postcode": "43062",
    "addr:street": "E Broad St",
    "iso:country": "US",
    "sg:address": "160 E Broad St",
    "sg:city": "Pataskala",
    "sg:classifiers": [
      {
        "category": "Real Estate",
        "subcategory": "Real Estate Services",
        "type": "Services"
      }
    ],
    "sg:phone": "+1 740 964 6911",
    "sg:postcode": "43062",
    "sg:province": "OH",
    "sg:tags": [
      "company",
      "title"
    ],
    "wof:name": "Title First",
    "wof:placetype": "venue"
  },
  "geometry": {"coordinates":[-82.673392,40.003497],"type":"Point"}
}
