{
  "type": "Feature",
  "properties": {
    "addr:full":"1749 W Main St Troy OH 45373",
    "addr:housenumber":"1749",
    "addr:postcode":"45373",
    "addr:street":"W Main St",
    "iso:country":"US",
    "sg:address":"1749 W Main St",
    "sg:city":"Troy",
    "sg:classifiers":[
        {
            "category":"Restaurant",
            "type":"Food & Drink"
        }
    ],
    "sg:menulink":"http://www.allmenus.com/oh/concord/41877-bob-evans/menu/",
    "sg:phone":"+1 937 335 0800",
    "sg:postcode":"45373",
    "sg:province":"OH",
    "sg:tags":[
        "american"
    ],
    "wof:name":"Bob Evans",
    "wof:placetype":"venue"
},
  "geometry": {"coordinates":[-84.23611200000001,40.053812],"type":"Point"}
}