{
  "type": "Feature",
  "properties": {
    "addr:full":"1809 Freeman Ave Cincinnati OH 45214",
    "addr:housenumber":"1809",
    "addr:postcode":"45214",
    "addr:street":"Freeman Ave",
    "iso:country":"US",
    "sg:address":"1809 Freeman Ave",
    "sg:city":"Cincinnati",
    "sg:classifiers":[
        {
            "category":"Social Services",
            "type":"Services"
        }
    ],
    "sg:phone":"+1 513 632 7106",
    "sg:postcode":"45214",
    "sg:province":"OH",
    "wof:name":"Friendly Street Neighborhood",
    "wof:placetype":"venue"
},
  "geometry": {"coordinates":[-84.531521,39.116006],"type":"Point"}
}