{
  "type": "Feature",
  "properties": {
    "iso:country":"US",
    "sg:address":"175 Galloway Rd",
    "sg:city":"Galloway",
    "sg:classifiers":[
        {
            "category":"Retail",
            "subcategory":"Veterinary Services",
            "type":"Services"
        }
    ],
    "sg:phone":"+1 614 870 3900",
    "sg:postcode":"43119",
    "sg:province":"OH",
    "sg:tags":[
        "veterinarian"
    ],
    "wof:name":"Angel Animal Hospital Inc",
    "wof:placetype":"venue"
},
  "geometry": {"coordinates":[-83.154893,39.947489],"type":"Point"}
}