{
  "type": "Feature",
  "properties": {
    "iso:country":"US",
    "sg:address":"501 E Broad St",
    "sg:city":"Columbus",
    "sg:classifiers":[
        {
            "category":"Organizations",
            "subcategory":"Religious Organization",
            "type":"Services"
        }
    ],
    "sg:phone":"+1 614 221 4571",
    "sg:postcode":"43215",
    "sg:province":"OH",
    "wof:name":"Broad St Untd Methidist Church",
    "wof:placetype":"venue"
},
  "geometry": {"coordinates":[-82.988069,39.96355],"type":"Point"}
}