{
  "type": "Feature",
  "properties": {
    "iso:country":"US",
    "sg:address":"4576 Blainfield",
    "sg:city":"Batavia",
    "sg:classifiers":[
        {
            "category":"Professional",
            "type":"Services"
        }
    ],
    "sg:phone":"+1 513 943 4330",
    "sg:postcode":"45103",
    "sg:province":"OH",
    "sg:tags":[
        "establishment"
    ],
    "wof:name":"Schronet Concepts",
    "wof:placetype":"venue"
},
  "geometry": {"coordinates":[-84.23313400000001,39.104512],"type":"Point"}
}