{
  "type": "Feature",
  "properties": {
    "addr:full": "4576 Blainfield Batavia OH 45103",
    "addr:housenumber": "4576",
    "addr:postcode": "45103",
    "addr:street": "Blainfield",
    "iso:country": "US",
    "sg:address": "4576 Blainfield",
    "sg:city": "Batavia",
    "sg:classifiers": [
      {
        "category": "Professional",
        "type": "Services"
      }
    ],
    "sg:phone": "+1 513 943 4330",
    "sg:postcode": "45103",
    "sg:province": "OH",
    "sg:tags": [
      "establishment"
    ],
    "wof:name": "Schronet Concepts",
    "wof:placetype": "venue"
  },
  "geometry": {"coordinates":[-84.233134,39.104512],"type":"Point"}
}
