{
  "type": "Feature",
  "properties": {
    "iso:country":"US",
    "sg:address":"17808 E Park Dr",
    "sg:city":"Cleveland",
    "sg:classifiers":[
        {
            "category":"Freight",
            "type":"Transportation"
        }
    ],
    "sg:phone":"+1 216 531 2947",
    "sg:postcode":"44119",
    "sg:province":"OH",
    "wof:name":"Downing Transport",
    "wof:placetype":"venue"
},
  "geometry": {"coordinates":[-81.552818,41.586155],"type":"Point"}
}