{
  "type": "Feature",
  "properties": {
    "addr:full":"136 Deer Trail Dr Springboro OH 45066",
    "addr:housenumber":"136",
    "addr:postcode":"45066",
    "addr:street":"Deer Trail Dr",
    "iso:country":"US",
    "sg:address":"136 Deer Trail Dr",
    "sg:city":"Springboro",
    "sg:classifiers":[
        {
            "category":"Professional",
            "subcategory":"Computer Services",
            "type":"Services"
        }
    ],
    "sg:phone":"+1 937 748 0243",
    "sg:postcode":"45066",
    "sg:province":"OH",
    "sg:tags":[
        "design",
        "system",
        "programing",
        "custom"
    ],
    "wof:name":"Shaner Consultants Inc",
    "wof:placetype":"venue"
},
  "geometry": {"coordinates":[-84.236394,39.576243],"type":"Point"}
}