{
  "type": "Feature",
  "properties": {
    "addr:full": "695 Boardman Canfield Rd Youngstown OH 44512",
    "addr:housenumber": "695",
    "addr:postcode": "44512",
    "addr:street": "Boardman Canfield Rd",
    "iso:country": "US",
    "sg:address": "695 Boardman Canfield Rd",
    "sg:city": "Youngstown",
    "sg:classifiers": [
      {
        "category": "Autos \u0026 Motor Vehicles",
        "subcategory": "Fuel \u0026 Gas Station",
        "type": "Retail Goods"
      }
    ],
    "sg:phone": "+1 330 726 8037",
    "sg:postcode": "44512",
    "sg:province": "OH",
    "sg:tags": [
      "grocery",
      "station",
      "gasoline"
    ],
    "wof:name": "Speedway Superamerica LLC",
    "wof:placetype": "venue"
  },
  "geometry": {"coordinates":[-80.680337,41.02441],"type":"Point"}
}
