{
  "type": "Feature",
  "properties": {
    "addr:full": "2885 Detroit Ave Cleveland OH 44113",
    "addr:housenumber": "2885",
    "addr:postcode": "44113",
    "addr:street": "Detroit Ave",
    "iso:country": "US",
    "sg:address": "2885 Detroit Ave",
    "sg:city": "Cleveland",
    "sg:classifiers": [
      {
        "category": "Manufacturing",
        "subcategory": "Tools \u0026 Machinery",
        "type": "Manufacturing \u0026 Wholesale Goods"
      }
    ],
    "sg:phone": "+1 216 696 5307",
    "sg:postcode": "44113",
    "sg:province": "OH",
    "sg:tags": [
      "machine",
      "shop",
      "job",
      "custom"
    ],
    "wof:name": "Ro-Mon Corporation",
    "wof:placetype": "venue"
  },
  "geometry": {"coordinates":[-81.709931,41.490402],"type":"Point"}
}
