{
  "type": "Feature",
  "properties": {
    "iso:country":"US",
    "sg:address":"6500 Sylvian St NW",
    "sg:city":"North Canton",
    "sg:classifiers":[
        {
            "category":"Personal",
            "subcategory":"Hair Removal",
            "type":"Services"
        }
    ],
    "sg:phone":"+1 330 494 4200",
    "sg:postcode":"44720",
    "sg:province":"OH",
    "sg:tags":[
        "removing"
    ],
    "wof:name":"Barbara's Electrolysis Clinic",
    "wof:placetype":"venue"
},
  "geometry": {"coordinates":[-81.472764,40.881262],"type":"Point"}
}