{
  "type": "Feature",
  "properties": {
    "addr:full": "1394 S Cleveland Massillon Rd Copley OH 44321",
    "addr:housenumber": "1394",
    "addr:postcode": "44321",
    "addr:street": "S Cleveland Massillon Rd",
    "iso:country": "US",
    "sg:address": "1394 S Cleveland Massillon Rd",
    "sg:city": "Copley",
    "sg:classifiers": [
      {
        "category": "Banks \u0026 Credit Unions",
        "subcategory": "Bank",
        "type": "Services"
      }
    ],
    "sg:phone": "+1 330 666 4103",
    "sg:postcode": "44321",
    "sg:province": "OH",
    "wof:name": "First National Bank Of Ohio",
    "wof:placetype": "venue"
  },
  "geometry": {"coordinates":[-81.644689,41.102062],"type":"Point"}
}
