{
  "type": "Feature",
  "properties": {
    "iso:country":"US",
    "sg:address":"1394 S Cleveland Massillon Rd",
    "sg:city":"Copley",
    "sg:classifiers":[
        {
            "category":"Banks & Credit Unions",
            "subcategory":"Bank",
            "type":"Services"
        }
    ],
    "sg:phone":"+1 330 666 4103",
    "sg:postcode":"44321",
    "sg:province":"OH",
    "wof:name":"First National Bank Of Ohio",
    "wof:placetype":"venue"
},
  "geometry": {"coordinates":[-81.644689,41.102062],"type":"Point"}
}