{
  "type": "Feature",
  "properties": {
    "iso:country":"US",
    "sg:address":"670 Morrison Rd",
    "sg:city":"Gahanna",
    "sg:classifiers":[
        {
            "category":"Shopping",
            "subcategory":"Computers & Home Electronics",
            "type":"Retail Goods"
        }
    ],
    "sg:phone":"+1 614 413 4000",
    "sg:postcode":"43230",
    "sg:province":"OH",
    "sg:tags":[
        "software"
    ],
    "wof:name":"Now Software",
    "wof:placetype":"venue"
},
  "geometry": {"coordinates":[-82.859829,40.0024],"type":"Point"}
}