{
  "type": "Feature",
  "properties": {
    "addr:full":"4744 Corduroy Rd Mentor OH 44060",
    "addr:housenumber":"4744",
    "addr:postcode":"44060",
    "addr:street":"Corduroy Rd",
    "iso:country":"US",
    "sg:address":"4744 Corduroy Rd",
    "sg:city":"Mentor",
    "sg:classifiers":[
        {
            "category":"Retail",
            "subcategory":"Laundry & Dry Cleaning",
            "type":"Services"
        }
    ],
    "sg:phone":"+1 440 209 9565",
    "sg:postcode":"44060",
    "sg:province":"OH",
    "sg:tags":[
        "cleaners",
        "rug",
        "carpet"
    ],
    "wof:name":"Quality Carpet Care",
    "wof:placetype":"venue"
},
  "geometry": {"coordinates":[-81.311519,41.7398],"type":"Point"}
}