{
  "type": "Feature",
  "properties": {
    "addr:full": "3031 E 14th Ave Columbus OH 43219",
    "addr:housenumber": "3031",
    "addr:postcode": "43219",
    "addr:street": "E 14Th Ave",
    "iso:country": "US",
    "sg:address": "3031 E 14th Ave",
    "sg:city": "Columbus",
    "sg:classifiers": [
      {
        "category": "Wholesale",
        "subcategory": "Auto Parts",
        "type": "Manufacturing \u0026 Wholesale Goods"
      }
    ],
    "sg:phone": "+1 614 258 4611",
    "sg:postcode": "43219",
    "sg:province": "OH",
    "sg:tags": [
      "body",
      "automobile",
      "shop"
    ],
    "wof:name": "Grinstead Auto Paint \u0026 Supply",
    "wof:placetype": "venue"
  },
  "geometry": {"coordinates":[-82.928346,39.993865],"type":"Point"}
}
