{
  "type": "Feature",
  "properties": {
    "iso:country":"US",
    "sg:address":"3031 E 14th Ave",
    "sg:city":"Columbus",
    "sg:classifiers":[
        {
            "category":"Wholesale",
            "subcategory":"Auto Parts",
            "type":"Manufacturing & Wholesale Goods"
        }
    ],
    "sg:phone":"+1 614 258 4611",
    "sg:postcode":"43219",
    "sg:province":"OH",
    "sg:tags":[
        "body",
        "automobile",
        "shop"
    ],
    "wof:name":"Grinstead Auto Paint & Supply",
    "wof:placetype":"venue"
},
  "geometry": {"coordinates":[-82.928346,39.993865],"type":"Point"}
}