{
  "type": "Feature",
  "properties": {
    "iso:country":"US",
    "sg:address":"13836 Bellaire Rd",
    "sg:city":"Cleveland",
    "sg:classifiers":[
        {
            "category":"Wholesale",
            "subcategory":"Auto Parts",
            "type":"Manufacturing & Wholesale Goods"
        }
    ],
    "sg:phone":"+1 216 252 1994",
    "sg:postcode":"44135",
    "sg:province":"OH",
    "sg:tags":[
        "automobile",
        "rebuilt"
    ],
    "wof:name":"Hubcap Heaven & Wheels",
    "wof:placetype":"venue"
},
  "geometry": {"coordinates":[-81.78624600000001,41.434981],"type":"Point"}
}