{
  "type": "Feature",
  "properties": {
    "iso:country":"US",
    "sg:address":"35000 Curtis Blvd",
    "sg:city":"Willoughby",
    "sg:classifiers":[
        {
            "category":"Travel",
            "subcategory":"Hotels & Motels",
            "type":"Entertainment"
        }
    ],
    "sg:phone":"+1 440 953 8000",
    "sg:postcode":"44095",
    "sg:province":"OH",
    "sg:website":"www.radisson.com",
    "wof:name":"Radisson Hotel & Conference",
    "wof:placetype":"venue"
},
  "geometry": {"coordinates":[-81.447169,41.631387],"type":"Point"}
}