{
  "type": "Feature",
  "properties": {
    "addr:full":"816 Shedborne Ave Dayton OH 45403",
    "addr:housenumber":"816",
    "addr:postcode":"45403",
    "addr:street":"Shedborne Ave",
    "iso:country":"US",
    "sg:address":"816 Shedborne Ave",
    "sg:city":"Dayton",
    "sg:classifiers":[
        {
            "category":"Education",
            "subcategory":"School",
            "type":"Public Place"
        }
    ],
    "sg:phone":"+1 937 542 5090",
    "sg:postcode":"45403",
    "sg:province":"OH",
    "wof:name":"Kemp Elementary School",
    "wof:placetype":"venue"
},
  "geometry": {"coordinates":[-84.13197,39.75471],"type":"Point"}
}