{
  "type": "Feature",
  "properties": {
    "iso:country":"US",
    "sg:address":"23250 Broadway Ave",
    "sg:city":"Bedford",
    "sg:classifiers":[
        {
            "category":"Shopping",
            "subcategory":"Discount & Variety Stores",
            "type":"Retail Goods"
        }
    ],
    "sg:phone":"+1 440 786 8290",
    "sg:postcode":"44146",
    "sg:province":"OH",
    "wof:name":"Dollarama Plus",
    "wof:placetype":"venue"
},
  "geometry": {"coordinates":[-81.508388,41.365425],"type":"Point"}
}