{
  "type": "Feature",
  "properties": {
    "addr:full": "5705 E Walnut Grove Troy OH 45373",
    "addr:housenumber": "5705",
    "addr:postcode": "45373",
    "addr:street": "E Walnut Grove",
    "iso:country": "US",
    "sg:address": "5705 E Walnut Grove",
    "sg:city": "Troy",
    "sg:classifiers": [
      {
        "category": "Organizations",
        "subcategory": "Religious Organization",
        "type": "Services"
      }
    ],
    "sg:phone": "+1 937 335 8298",
    "sg:postcode": "45373",
    "sg:province": "OH",
    "sg:tags": [
      "church"
    ],
    "wof:name": "Cove Springs Church",
    "wof:placetype": "venue"
  },
  "geometry": {"coordinates":[-84.101184,39.999578],"type":"Point"}
}
