{
  "type": "Feature",
  "properties": {
    "addr:full": "1616 Covington St Youngstown OH 44510",
    "addr:housenumber": "1616",
    "addr:postcode": "44510",
    "addr:street": "Covington St",
    "iso:country": "US",
    "sg:address": "1616 Covington St",
    "sg:city": "Youngstown",
    "sg:classifiers": [
      {
        "category": "Professional",
        "subcategory": "Accounting \u0026 Tax Preparation",
        "type": "Services"
      }
    ],
    "sg:phone": "+1 330 747 0847",
    "sg:postcode": "44510",
    "sg:province": "OH",
    "sg:tags": [
      "accountant"
    ],
    "wof:name": "Barry Brocker",
    "wof:placetype": "venue"
  },
  "geometry": {"coordinates":[-80.660466,41.121593],"type":"Point"}
}
