{
  "type": "Feature",
  "properties": {
    "addr:full":"14381 E Twp Rd 8 Attica OH 44807",
    "addr:housenumber":"14381",
    "addr:postcode":"44807",
    "addr:street":"E Twp Rd 8",
    "iso:country":"US",
    "sg:address":"14381 E Twp Rd 8",
    "sg:city":"Attica",
    "sg:phone":"+1 419 426 2302",
    "sg:postcode":"44807",
    "sg:province":"OH",
    "sg:tags":[
        "farm",
        "grain",
        "cash"
    ],
    "wof:name":"George M Eisenhart",
    "wof:placetype":"venue"
},
  "geometry": {"coordinates":[-82.896896,41.110047],"type":"Point"}
}