{
  "type": "Feature",
  "properties": {
    "addr:full": "949 S Patterson Blvd Dayton OH 45409",
    "addr:housenumber": "949",
    "addr:postcode": "45409",
    "addr:street": "S Patterson Blvd",
    "iso:country": "US",
    "sg:address": "949 S Patterson Blvd",
    "sg:city": "Dayton",
    "sg:classifiers": [
      {
        "category": "Real Estate",
        "subcategory": "Real Estate Agent",
        "type": "Services"
      }
    ],
    "sg:phone": "+1 937 224 5556",
    "sg:postcode": "45409",
    "sg:province": "OH",
    "wof:name": "Updyke Properties",
    "wof:placetype": "venue"
  },
  "geometry": {"coordinates":[-84.190901,39.742463],"type":"Point"}
}
