{
  "type": "Feature",
  "properties": {
    "addr:full": "132 N Arch St Barnesville OH 43713",
    "addr:housenumber": "132",
    "addr:postcode": "43713",
    "addr:street": "N Arch St",
    "iso:country": "US",
    "sg:address": "132 N Arch St",
    "sg:city": "Barnesville",
    "sg:classifiers": [
      {
        "category": "Government",
        "subcategory": "Office",
        "type": "Public Place"
      }
    ],
    "sg:phone": "+1 740 425 3444",
    "sg:postcode": "43713",
    "sg:province": "OH",
    "sg:tags": [
      "village"
    ],
    "wof:name": "Barnesville Village Clerks Ofc",
    "wof:placetype": "venue"
  },
  "geometry": {"coordinates":[-81.175177,39.98795],"type":"Point"}
}
