{
  "type": "Feature",
  "properties": {
    "iso:country":"US",
    "sg:address":"132 N Arch St",
    "sg:city":"Barnesville",
    "sg:classifiers":[
        {
            "category":"Government",
            "subcategory":"Office",
            "type":"Public Place"
        }
    ],
    "sg:phone":"+1 740 425 3444",
    "sg:postcode":"43713",
    "sg:province":"OH",
    "sg:tags":[
        "village"
    ],
    "wof:name":"Barnesville Village Clerks Ofc",
    "wof:placetype":"venue"
},
  "geometry": {"coordinates":[-81.17517700000001,39.98795],"type":"Point"}
}