{
  "type": "Feature",
  "properties": {
    "iso:country":"US",
    "sg:address":"1790 Town Park Blvd",
    "sg:city":"Uniontown",
    "sg:classifiers":[
        {
            "category":"Building & Trades",
            "subcategory":"Construction",
            "type":"Services"
        }
    ],
    "sg:phone":"+1 330 899 0374",
    "sg:postcode":"44685",
    "sg:province":"OH",
    "sg:tags":[
        "house"
    ],
    "wof:name":"Testa Builders",
    "wof:placetype":"venue"
},
  "geometry": {"coordinates":[-81.46771,40.950563],"type":"Point"}
}