{
  "type": "Feature",
  "properties": {
    "addr:full": "318 N Main St Urbana OH 43078",
    "addr:housenumber": "318",
    "addr:postcode": "43078",
    "addr:street": "N Main St",
    "iso:country": "US",
    "sg:address": "318 N Main St",
    "sg:city": "Urbana",
    "sg:classifiers": [
      {
        "category": "Education",
        "subcategory": "Special Training",
        "type": "Public Place"
      }
    ],
    "sg:phone": "+1 937 652 4444",
    "sg:postcode": "43078",
    "sg:province": "OH",
    "sg:tags": [
      "instruction",
      "driving"
    ],
    "wof:name": "Urbana's School Of Driving",
    "wof:placetype": "venue"
  },
  "geometry": {"coordinates":[-83.75228,40.110615],"type":"Point"}
}
