{
  "type": "Feature",
  "properties": {
    "addr:full":"3150 Republic Blvd N Toledo OH 43615",
    "addr:housenumber":"3150",
    "addr:postcode":"43615",
    "addr:street":"Republic Blvd N",
    "iso:country":"US",
    "sg:address":"3150 Republic Blvd N",
    "sg:city":"Toledo",
    "sg:classifiers":[
        {
            "category":"Health Services",
            "subcategory":"Health Practitioner",
            "type":"Services"
        }
    ],
    "sg:phone":"+1 419 841 6256",
    "sg:postcode":"43615",
    "sg:province":"OH",
    "sg:tags":[
        "psychologist"
    ],
    "wof:name":"Michael Drewyor PHD",
    "wof:placetype":"venue"
},
  "geometry": {"coordinates":[-83.674798,41.677565],"type":"Point"}
}