{
  "type": "Feature",
  "properties": {
    "addr:full": "9449 Brookpark Rd Cleveland OH 44129",
    "addr:housenumber": "9449",
    "addr:postcode": "44129",
    "addr:street": "Brookpark Rd",
    "iso:country": "US",
    "sg:address": "9449 Brookpark Rd",
    "sg:city": "Cleveland",
    "sg:classifiers": [
      {
        "category": "Wholesale",
        "subcategory": "Construction Materials",
        "type": "Manufacturing \u0026 Wholesale Goods"
      }
    ],
    "sg:phone": "+1 216 398 0150",
    "sg:postcode": "44129",
    "sg:province": "OH",
    "sg:tags": [
      "item",
      "plaster",
      "wallboard",
      "related"
    ],
    "wof:name": "Big Creek Building Supply",
    "wof:placetype": "venue"
  },
  "geometry": {"coordinates":[-81.747216,41.418461],"type":"Point"}
}
