{
  "type": "Feature",
  "properties": {
    "iso:country":"US",
    "sg:address":"717 W Town St",
    "sg:city":"Columbus",
    "sg:classifiers":[
        {
            "category":"Health Services",
            "subcategory":"Doctor",
            "type":"Services"
        }
    ],
    "sg:phone":"+1 614 228 3874",
    "sg:postcode":"43222",
    "sg:province":"OH",
    "sg:tags":[
        "physician",
        "surgeon"
    ],
    "wof:name":"Richard H Clary MD",
    "wof:placetype":"venue"
},
  "geometry": {"coordinates":[-83.01933,39.956337],"type":"Point"}
}