{
  "type": "Feature",
  "properties": {
    "iso:country":"US",
    "sg:address":"2103 Robin St",
    "sg:city":"Lakewood",
    "sg:classifiers":[
        {
            "category":"Professional",
            "type":"Services"
        }
    ],
    "sg:phone":"+1 216 221 7729",
    "sg:postcode":"44107",
    "sg:province":"OH",
    "wof:name":"Donald J Mountain",
    "wof:placetype":"venue"
},
  "geometry": {"coordinates":[-81.775965,41.474236],"type":"Point"}
}