{
  "type": "Feature",
  "properties": {
    "iso:country":"US",
    "sg:address":"17455 Haskins Rd",
    "sg:city":"Bowling Green",
    "sg:classifiers":[
        {
            "category":"Real Estate",
            "subcategory":"Real Estate Agent",
            "type":"Services"
        }
    ],
    "sg:phone":"+1 419 352 8673",
    "sg:postcode":"43402",
    "sg:province":"OH",
    "sg:tags":[
        "commercial",
        "property",
        "rental"
    ],
    "wof:name":"Niemar Properties LLC",
    "wof:placetype":"venue"
},
  "geometry": {"coordinates":[-83.683471,41.407647],"type":"Point"}
}