{
  "type": "Feature",
  "properties": {
    "iso:country":"US",
    "sg:address":"9505 Pioneer Rd",
    "sg:city":"Byesville",
    "sg:classifiers":[
        {
            "category":"Building & Trades",
            "subcategory":"Plumbing",
            "type":"Services"
        }
    ],
    "sg:phone":"+1 740 685 3000",
    "sg:postcode":"43723",
    "sg:province":"OH",
    "sg:tags":[
        "tank",
        "septic"
    ],
    "wof:name":"Joseph Seresun Excavating",
    "wof:placetype":"venue"
},
  "geometry": {"coordinates":[-81.568479,39.964108],"type":"Point"}
}