{
  "type": "Feature",
  "properties": {
    "addr:full": "49 S Edgehill Ave Youngstown OH 44515",
    "addr:housenumber": "49",
    "addr:postcode": "44515",
    "addr:street": "S Edgehill Ave",
    "iso:country": "US",
    "sg:address": "49 S Edgehill Ave",
    "sg:city": "Youngstown",
    "sg:classifiers": [
      {
        "category": "Shopping",
        "subcategory": "Shoes",
        "type": "Retail Goods"
      }
    ],
    "sg:phone": "+1 330 799 6894",
    "sg:postcode": "44515",
    "sg:province": "OH",
    "wof:name": "Knapp Shoes",
    "wof:placetype": "venue"
  },
  "geometry": {"coordinates":[-80.725914,41.101312],"type":"Point"}
}
