{
  "type": "Feature",
  "properties": {
    "iso:country":"US",
    "sg:address":"250 Graceland Blvd",
    "sg:city":"Columbus",
    "sg:classifiers":[
        {
            "category":"Health Services",
            "subcategory":"Health Practitioner",
            "type":"Services"
        }
    ],
    "sg:phone":"+1 614 846 6573",
    "sg:postcode":"43214",
    "sg:province":"OH",
    "sg:tags":[
        "psychologist"
    ],
    "wof:name":"Psychological Corp",
    "wof:placetype":"venue"
},
  "geometry": {"coordinates":[-83.02575,40.066089],"type":"Point"}
}