{
  "type": "Feature",
  "properties": {
    "addr:full":"6655 Lakeview Dr Kinsman OH 44428",
    "addr:housenumber":"6655",
    "addr:postcode":"44428",
    "addr:street":"Lakeview Dr",
    "iso:country":"US",
    "sg:address":"6655 Lakeview Dr",
    "sg:city":"Kinsman",
    "sg:classifiers":[
        {
            "category":"Organizations",
            "subcategory":"Non-profit Organization",
            "type":"Services"
        },
        {
            "category":"Professional",
            "type":"Services"
        }
    ],
    "sg:phone":"+1 330 876 8663",
    "sg:postcode":"44428",
    "sg:province":"OH",
    "wof:name":"Mahoning Valley Jog Inc",
    "wof:placetype":"venue"
},
  "geometry": {"coordinates":[-80.581401,41.45119],"type":"Point"}
}