{
  "type": "Feature",
  "properties": {
    "addr:full": "953 Rogers St Toledo OH 43605",
    "addr:housenumber": "953",
    "addr:postcode": "43605",
    "addr:street": "Rogers St",
    "iso:country": "US",
    "sg:address": "953 Rogers St",
    "sg:city": "Toledo",
    "sg:phone": "+1 877 621 5469",
    "sg:postcode": "43605",
    "sg:province": "OH",
    "sg:tags": [
      "coffee",
      "supply"
    ],
    "wof:name": "Sunbelt Home and Off Cof Svc",
    "wof:placetype": "venue"
  },
  "geometry": {"coordinates":[-83.519146,41.635221],"type":"Point"}
}
