{
  "type": "Feature",
  "properties": {
    "iso:country":"US",
    "sg:address":"953 Rogers St",
    "sg:city":"Toledo",
    "sg:phone":"+1 877 621 5469",
    "sg:postcode":"43605",
    "sg:province":"OH",
    "sg:tags":[
        "coffee",
        "supply"
    ],
    "wof:name":"Sunbelt Home and Off Cof Svc",
    "wof:placetype":"venue"
},
  "geometry": {"coordinates":[-83.51914600000001,41.635221],"type":"Point"}
}