{
  "type": "Feature",
  "properties": {
    "iso:country":"US",
    "sg:address":"9 N Shafer St",
    "sg:city":"Athens",
    "sg:classifiers":[
        {
            "category":"Restaurant",
            "type":"Food & Drink"
        }
    ],
    "sg:menulink":"http://www.allmenus.com/oh/athens/258923-mistrettas-italian-market/menu/",
    "sg:phone":"+1 740 594 4949",
    "sg:postcode":"45701",
    "sg:province":"OH",
    "sg:tags":[
        "soup",
        "american",
        "sandwich",
        "salad",
        "dessert"
    ],
    "wof:name":"Mistretta's Italian Market",
    "wof:placetype":"venue"
},
  "geometry": {"coordinates":[-82.11060500000001,39.332545],"type":"Point"}
}