{
  "type": "Feature",
  "properties": {
    "addr:full": "25953 Forbes Rd Bedford OH 44146",
    "addr:housenumber": "25953",
    "addr:postcode": "44146",
    "addr:street": "Forbes Rd",
    "iso:country": "US",
    "sg:address": "25953 Forbes Rd",
    "sg:city": "Bedford",
    "sg:classifiers": [
      {
        "category": "Wholesale",
        "subcategory": "Vending Machines",
        "type": "Manufacturing \u0026 Wholesale Goods"
      }
    ],
    "sg:phone": "+1 440 439 4972",
    "sg:postcode": "44146",
    "sg:province": "OH",
    "sg:tags": [
      "operator"
    ],
    "wof:name": "Madison Vending",
    "wof:placetype": "venue"
  },
  "geometry": {"coordinates":[-81.495181,41.372536],"type":"Point"}
}
