{
  "type": "Feature",
  "properties": {
    "addr:full": "920 E Mansfield St Bucyrus OH 44820",
    "addr:housenumber": "920",
    "addr:postcode": "44820",
    "addr:street": "E Mansfield St",
    "iso:country": "US",
    "sg:address": "920 E Mansfield St",
    "sg:city": "Bucyrus",
    "sg:classifiers": [
      {
        "category": "Real Estate",
        "subcategory": "Real Estate Agent",
        "type": "Services"
      }
    ],
    "sg:phone": "+1 419 562 5051",
    "sg:postcode": "44820",
    "sg:province": "OH",
    "sg:tags": [
      "business"
    ],
    "wof:name": "Garberick Realty Co",
    "wof:placetype": "venue"
  },
  "geometry": {"coordinates":[-82.963071,40.810018],"type":"Point"}
}
