{
  "type": "Feature",
  "properties": {
    "addr:full": "2344 Limestone Way Columbus OH 43228",
    "addr:housenumber": "2344",
    "addr:postcode": "43228",
    "addr:street": "Limestone Way",
    "iso:country": "US",
    "sg:address": "2344 Limestone Way",
    "sg:city": "Columbus",
    "sg:classifiers": [
      {
        "category": "Building \u0026 Trades",
        "subcategory": "Construction",
        "type": "Services"
      }
    ],
    "sg:phone": "+1 614 844 6131",
    "sg:postcode": "43228",
    "sg:province": "OH",
    "sg:tags": [
      "house"
    ],
    "wof:name": "M/I Homes Inc",
    "wof:placetype": "venue"
  },
  "geometry": {"coordinates":[-83.098737,40.002005],"type":"Point"}
}
