{
  "type": "Feature",
  "properties": {
    "addr:full":"5602 Woodville Rd Northwood OH 43619",
    "addr:housenumber":"5602",
    "addr:postcode":"43619",
    "addr:street":"Woodville Rd",
    "iso:country":"US",
    "sg:address":"5602 Woodville Rd",
    "sg:city":"Northwood",
    "sg:classifiers":[
        {
            "category":"Insurance",
            "subcategory":"Insurance Agent",
            "type":"Services"
        }
    ],
    "sg:phone":"+1 419 698 1122",
    "sg:postcode":"43619",
    "sg:province":"OH",
    "wof:name":"Glemser Insurance Agency",
    "wof:placetype":"venue"
},
  "geometry": {"coordinates":[-83.440707,41.585814],"type":"Point"}
}