{
  "type": "Feature",
  "properties": {
    "addr:full": "26 W North Bend Rd Cincinnati OH 45216",
    "addr:housenumber": "26",
    "addr:postcode": "45216",
    "addr:street": "W North Bend Rd",
    "iso:country": "US",
    "sg:address": "26 W North Bend Rd",
    "sg:city": "Cincinnati",
    "sg:classifiers": [
      {
        "category": "Organizations",
        "subcategory": "Community Association",
        "type": "Services"
      }
    ],
    "sg:phone": "+1 513 821 0704",
    "sg:postcode": "45216",
    "sg:province": "OH",
    "wof:name": "Socially Involving Male Black African Inc",
    "wof:placetype": "venue"
  },
  "geometry": {"coordinates":[-84.477783,39.19738],"type":"Point"}
}
