{
  "type": "Feature",
  "properties": {
    "iso:country":"US",
    "sg:address":"4141 Colonel Glenn Hwy",
    "sg:city":"Dayton",
    "sg:classifiers":[
        {
            "category":"Wholesale",
            "subcategory":"Metals & Minerals",
            "type":"Manufacturing & Wholesale Goods"
        }
    ],
    "sg:phone":"+1 937 427 2505",
    "sg:postcode":"45431",
    "sg:province":"OH",
    "sg:tags":[
        "steel",
        "product"
    ],
    "wof:name":"Vulcraft Division Sales",
    "wof:placetype":"venue"
},
  "geometry": {"coordinates":[-84.087578,39.773348],"type":"Point"}
}