{
  "type": "Feature",
  "properties": {
    "addr:full":"1518 Gallia St Portsmouth OH 45662",
    "addr:housenumber":"1518",
    "addr:postcode":"45662",
    "addr:street":"Gallia St",
    "iso:country":"US",
    "sg:address":"1518 Gallia St",
    "sg:city":"Portsmouth",
    "sg:classifiers":[
        {
            "category":"Organizations",
            "subcategory":"Professional Association",
            "type":"Services"
        }
    ],
    "sg:phone":"+1 740 354 1190",
    "sg:postcode":"45662",
    "sg:province":"OH",
    "wof:name":"Knights Of Columbus",
    "wof:placetype":"venue"
},
  "geometry": {"coordinates":[-82.984351,38.736022],"type":"Point"}
}