{
  "type": "Feature",
  "properties": {
    "iso:country":"US",
    "sg:address":"501 W Liberty St",
    "sg:city":"Springfield",
    "sg:classifiers":[
        {
            "category":"Manufacturing",
            "subcategory":"Tools & Machinery",
            "type":"Manufacturing & Wholesale Goods"
        }
    ],
    "sg:phone":"+1 937 325 8701",
    "sg:postcode":"45506",
    "sg:province":"OH",
    "sg:tags":[
        "control",
        "mfg"
    ],
    "wof:name":"ITT Jabsco",
    "wof:placetype":"venue"
},
  "geometry": {"coordinates":[-83.823773,39.915075],"type":"Point"}
}