{
  "type": "Feature",
  "properties": {
    "addr:full":"3682 Hildana Rd Cleveland OH 44120",
    "addr:housenumber":"3682",
    "addr:postcode":"44120",
    "addr:street":"Hildana Rd",
    "iso:country":"US",
    "sg:address":"3682 Hildana Rd",
    "sg:city":"Cleveland",
    "sg:classifiers":[
        {
            "category":"Building & Trades",
            "subcategory":"Construction",
            "type":"Services"
        }
    ],
    "sg:phone":"+1 216 214 2223",
    "sg:postcode":"44120",
    "sg:province":"OH",
    "sg:tags":[
        "general",
        "contractor"
    ],
    "wof:name":"My Castle LLC",
    "wof:placetype":"venue"
},
  "geometry": {"coordinates":[-81.568625,41.45924],"type":"Point"}
}