{
  "type": "Feature",
  "properties": {
    "iso:country":"US",
    "sg:address":"285 E State St",
    "sg:city":"Columbus",
    "sg:classifiers":[
        {
            "category":"Health Services",
            "subcategory":"Doctor",
            "type":"Services"
        }
    ],
    "sg:phone":"+1 614 228 3056",
    "sg:postcode":"43215",
    "sg:province":"OH",
    "sg:tags":[
        "physician",
        "surgeon"
    ],
    "wof:name":"Jerry Mitchell MD",
    "wof:placetype":"venue"
},
  "geometry": {"coordinates":[-82.993427,39.960816],"type":"Point"}
}