{
  "type": "Feature",
  "properties": {
    "iso:country":"US",
    "sg:address":"760 Killian Rd",
    "sg:city":"Akron",
    "sg:classifiers":[
        {
            "category":"Wholesale",
            "subcategory":"Plants",
            "type":"Manufacturing & Wholesale Goods"
        },
        {
            "category":"Manufacturing",
            "subcategory":"Rubber & Plastics",
            "type":"Manufacturing & Wholesale Goods"
        }
    ],
    "sg:phone":"+1 330 644 9993",
    "sg:postcode":"44319",
    "sg:province":"OH",
    "sg:tags":[
        "florist",
        "product",
        "supply",
        "manufacturer"
    ],
    "wof:name":"Diamond Line Container Company",
    "wof:placetype":"venue"
},
  "geometry": {"coordinates":[-81.494362,40.997375],"type":"Point"}
}