{
  "type": "Feature",
  "properties": {
    "addr:full": "760 Killian Rd Akron OH 44319",
    "addr:housenumber": "760",
    "addr:postcode": "44319",
    "addr:street": "Killian Rd",
    "iso:country": "US",
    "sg:address": "760 Killian Rd",
    "sg:city": "Akron",
    "sg:classifiers": [
      {
        "category": "Wholesale",
        "subcategory": "Plants",
        "type": "Manufacturing \u0026 Wholesale Goods"
      },
      {
        "category": "Manufacturing",
        "subcategory": "Rubber \u0026 Plastics",
        "type": "Manufacturing \u0026 Wholesale Goods"
      }
    ],
    "sg:phone": "+1 330 644 9993",
    "sg:postcode": "44319",
    "sg:province": "OH",
    "sg:tags": [
      "florist",
      "product",
      "supply",
      "manufacturer"
    ],
    "wof:name": "Diamond Line Container Company",
    "wof:placetype": "venue"
  },
  "geometry": {"coordinates":[-81.494362,40.997375],"type":"Point"}
}
