{
  "type": "Feature",
  "properties": {
    "iso:country":"US",
    "sg:address":"4122 Melrose Dr",
    "sg:city":"Wooster",
    "sg:classifiers":[
        {
            "category":"Professional",
            "subcategory":"Computer Services",
            "type":"Services"
        }
    ],
    "sg:phone":"+1 330 345 7825",
    "sg:postcode":"44691",
    "sg:province":"OH",
    "wof:name":"PC Medic",
    "wof:placetype":"venue"
},
  "geometry": {"coordinates":[-81.915918,40.848238],"type":"Point"}
}