{
  "type": "Feature",
  "properties": {
    "addr:full":"2447 Mechanicsburg Rd Springfield OH 45503",
    "addr:housenumber":"2447",
    "addr:postcode":"45503",
    "addr:street":"Mechanicsburg Rd",
    "iso:country":"US",
    "sg:address":"2447 Mechanicsburg Rd",
    "sg:city":"Springfield",
    "sg:classifiers":[
        {
            "category":"Food & Beverages",
            "subcategory":"Groceries & Convenience Stores",
            "type":"Retail Goods"
        }
    ],
    "sg:phone":"+1 937 342 9102",
    "sg:postcode":"45503",
    "sg:province":"OH",
    "wof:name":"Leen's Carry Out & Bait",
    "wof:placetype":"venue"
},
  "geometry": {"coordinates":[-83.764585,39.952137],"type":"Point"}
}