{
  "type": "Feature",
  "properties": {
    "iso:country":"US",
    "sg:address":"75 Powhatton Dr",
    "sg:city":"Milford",
    "sg:classifiers":[
        {
            "category":"Health Services",
            "subcategory":"Doctor",
            "type":"Services"
        }
    ],
    "sg:phone":"+1 513 831 3310",
    "sg:postcode":"45150",
    "sg:province":"OH",
    "sg:tags":[
        "physician",
        "surgeon"
    ],
    "wof:name":"Sophia Petkov MD",
    "wof:placetype":"venue"
},
  "geometry": {"coordinates":[-84.27790400000001,39.172582],"type":"Point"}
}