{
  "type": "Feature",
  "properties": {
    "addr:full": "75 Powhatton Dr Milford OH 45150",
    "addr:housenumber": "75",
    "addr:postcode": "45150",
    "addr:street": "Powhatton Dr",
    "iso:country": "US",
    "sg:address": "75 Powhatton Dr",
    "sg:city": "Milford",
    "sg:classifiers": [
      {
        "category": "Health Services",
        "subcategory": "Doctor",
        "type": "Services"
      }
    ],
    "sg:phone": "+1 513 831 3310",
    "sg:postcode": "45150",
    "sg:province": "OH",
    "sg:tags": [
      "physician",
      "surgeon"
    ],
    "wof:name": "Sophia Petkov MD",
    "wof:placetype": "venue"
  },
  "geometry": {"coordinates":[-84.277904,39.172582],"type":"Point"}
}
