{
  "type": "Feature",
  "properties": {
    "addr:full":"639 N Detroit Ave Toledo OH 43607",
    "addr:housenumber":"639",
    "addr:postcode":"43607",
    "addr:street":"N Detroit Ave",
    "iso:country":"US",
    "sg:address":"639 N Detroit Ave",
    "sg:city":"Toledo",
    "sg:classifiers":[
        {
            "category":"Social Services",
            "subcategory":"Child Care",
            "type":"Services"
        }
    ],
    "sg:phone":"+1 419 244 7813",
    "sg:postcode":"43607",
    "sg:province":"OH",
    "wof:name":"Little Treasures Child Care",
    "wof:placetype":"venue"
},
  "geometry": {"coordinates":[-83.581992,41.646375],"type":"Point"}
}