{
  "type": "Feature",
  "properties": {
    "iso:country":"US",
    "sg:address":"2354 E Main St",
    "sg:city":"Columbus",
    "sg:classifiers":[
        {
            "category":"Professional",
            "subcategory":"Lawyer & Legal Services",
            "type":"Services"
        }
    ],
    "sg:phone":"+1 614 236 5122",
    "sg:postcode":"43209",
    "sg:province":"OH",
    "sg:tags":[
        "attorney"
    ],
    "wof:name":"Bilenco Law Office",
    "wof:placetype":"venue"
},
  "geometry": {"coordinates":[-82.93753,39.957255],"type":"Point"}
}