{
  "type": "Feature",
  "properties": {
    "iso:country":"US",
    "sg:address":"1118 Euclid Ave",
    "sg:city":"Cleveland",
    "sg:classifiers":[
        {
            "category":"Recreation",
            "type":"Entertainment"
        }
    ],
    "sg:phone":"+1 216 621 8900",
    "sg:postcode":"44115",
    "sg:province":"OH",
    "sg:tags":[
        "club",
        "fitness",
        "membership",
        "bowling",
        "sport",
        "physical"
    ],
    "sg:website":"www.clevelandathleticclub.com",
    "wof:name":"Cleveland Athletic Club",
    "wof:placetype":"venue"
},
  "geometry": {"coordinates":[-81.68563,41.500273],"type":"Point"}
}