{
  "type": "Feature",
  "properties": {
    "addr:full": "300 Garrison St Fremont OH 43420",
    "addr:housenumber": "300",
    "addr:postcode": "43420",
    "addr:street": "Garrison St",
    "iso:country": "US",
    "sg:address": "300 Garrison St",
    "sg:city": "Fremont",
    "sg:classifiers": [
      {
        "category": "Insurance",
        "subcategory": "Insurance Agent",
        "type": "Services"
      }
    ],
    "sg:phone": "+1 419 332 4201",
    "sg:postcode": "43420",
    "sg:province": "OH",
    "sg:tags": [
      "consulting",
      "management"
    ],
    "wof:name": "Danziger Rei",
    "wof:placetype": "venue"
  },
  "geometry": {"coordinates":[-83.113549,41.345408],"type":"Point"}
}
