{
  "type": "Feature",
  "properties": {
    "iso:country":"US",
    "sg:address":"2275 Scranton Rd",
    "sg:city":"Cleveland",
    "sg:classifiers":[
        {
            "category":"Wholesale",
            "subcategory":"Machinery & Supplies",
            "type":"Manufacturing & Wholesale Goods"
        },
        {
            "category":"Manufacturing",
            "subcategory":"Glass & Minerals",
            "type":"Manufacturing & Wholesale Goods"
        }
    ],
    "sg:phone":"+1 216 861 1975",
    "sg:postcode":"44113",
    "sg:province":"OH",
    "sg:tags":[
        "burial",
        "mfg",
        "funeral",
        "director",
        "concrete",
        "vault"
    ],
    "wof:name":"American Vault Co",
    "wof:placetype":"venue"
},
  "geometry": {"coordinates":[-81.694648,41.482834],"type":"Point"}
}