{
  "type": "Feature",
  "properties": {
    "addr:full": "2275 Scranton Rd Cleveland OH 44113",
    "addr:housenumber": "2275",
    "addr:postcode": "44113",
    "addr:street": "Scranton Rd",
    "iso:country": "US",
    "sg:address": "2275 Scranton Rd",
    "sg:city": "Cleveland",
    "sg:classifiers": [
      {
        "category": "Wholesale",
        "subcategory": "Machinery \u0026 Supplies",
        "type": "Manufacturing \u0026 Wholesale Goods"
      },
      {
        "category": "Manufacturing",
        "subcategory": "Glass \u0026 Minerals",
        "type": "Manufacturing \u0026 Wholesale Goods"
      }
    ],
    "sg:phone": "+1 216 861 1975",
    "sg:postcode": "44113",
    "sg:province": "OH",
    "sg:tags": [
      "burial",
      "mfg",
      "funeral",
      "director",
      "concrete",
      "vault"
    ],
    "wof:name": "American Vault Co",
    "wof:placetype": "venue"
  },
  "geometry": {"coordinates":[-81.694648,41.482834],"type":"Point"}
}
