{
  "type": "Feature",
  "properties": {
    "addr:full": "1338 N 5th St Columbus OH 43201",
    "addr:housenumber": "1338",
    "addr:postcode": "43201",
    "addr:street": "N 5Th St",
    "iso:country": "US",
    "sg:address": "1338 N 5th St",
    "sg:city": "Columbus",
    "sg:classifiers": [
      {
        "category": "Restaurant",
        "type": "Food \u0026 Drink"
      }
    ],
    "sg:phone": "+1 614 291 9449",
    "sg:postcode": "43201",
    "sg:province": "OH",
    "sg:tags": [
      "caterer"
    ],
    "wof:name": "UBU Catering By Charles",
    "wof:placetype": "venue"
  },
  "geometry": {"coordinates":[-82.998035,39.990861],"type":"Point"}
}
