{
  "type": "Feature",
  "properties": {
    "addr:full": "25 Buck Ct Fairfield OH 45014",
    "addr:housenumber": "25",
    "addr:postcode": "45014",
    "addr:street": "Buck Ct",
    "iso:country": "US",
    "sg:address": "25 Buck Ct",
    "sg:city": "Fairfield",
    "sg:classifiers": [
      {
        "category": "Building \u0026 Trades",
        "subcategory": "Construction",
        "type": "Services"
      }
    ],
    "sg:phone": "+1 513 829 1146",
    "sg:postcode": "45014",
    "sg:province": "OH",
    "sg:tags": [
      "house",
      "builder",
      "operative"
    ],
    "wof:name": "Michael Piatt Construction",
    "wof:placetype": "venue"
  },
  "geometry": {"coordinates":[-84.563354,39.315683],"type":"Point"}
}
