{
  "type": "Feature",
  "properties": {
    "addr:full":"8711 Marseilles-Galion Rd W La Rue OH 43332",
    "addr:housenumber":"8711",
    "addr:postcode":"43332",
    "addr:street":"Marseilles-Galion Rd W La Rue Oh",
    "iso:country":"US",
    "sg:address":"8711 Marseilles-Galion Rd W",
    "sg:city":"La Rue",
    "sg:classifiers":[
        {
            "category":"Farming",
            "subcategory":"Livestock Farm",
            "type":"Manufacturing & Wholesale Goods"
        }
    ],
    "sg:phone":"+1 740 499 3314",
    "sg:postcode":"43332",
    "sg:province":"OH",
    "sg:tags":[
        "corn",
        "soybean"
    ],
    "wof:name":"Sam Roszman",
    "wof:placetype":"venue"
},
  "geometry": {"coordinates":[-83.36216400000001,40.675758],"type":"Point"}
}