{
  "type": "Feature",
  "properties": {
    "addr:full":"404 N Byrne Rd Toledo OH 43607",
    "addr:housenumber":"404",
    "addr:postcode":"43607",
    "addr:street":"N Byrne Rd",
    "iso:country":"US",
    "sg:address":"404 N Byrne Rd",
    "sg:city":"Toledo",
    "sg:classifiers":[
        {
            "category":"Building & Trades",
            "subcategory":"Electrical",
            "type":"Services"
        }
    ],
    "sg:phone":"+1 419 531 4251",
    "sg:postcode":"43607",
    "sg:province":"OH",
    "sg:tags":[
        "electrical",
        "contractor"
    ],
    "sg:website":"www.laibe.com",
    "wof:name":"Laibe Electric Co",
    "wof:placetype":"venue"
},
  "geometry": {"coordinates":[-83.62589699999999,41.639075],"type":"Point"}
}