{
  "type": "Feature",
  "properties": {
    "addr:full":"49020 Ashland Pl East Liverpool OH 43920",
    "addr:housenumber":"49020",
    "addr:postcode":"43920",
    "addr:street":"Ashland Pl",
    "iso:country":"US",
    "sg:address":"49020 Ashland Pl",
    "sg:city":"East Liverpool",
    "sg:classifiers":[
        {
            "category":"Real Estate",
            "subcategory":"Real Estate Services",
            "type":"Services"
        }
    ],
    "sg:phone":"+1 440 285 8961",
    "sg:postcode":"43920",
    "sg:province":"OH",
    "sg:tags":[
        "abstract",
        "title"
    ],
    "wof:name":"Grimsley Title Agency Ltd",
    "wof:placetype":"venue"
},
  "geometry": {"coordinates":[-80.574636,40.656555],"type":"Point"}
}