{
  "type": "Feature",
  "properties": {
    "addr:full": "1100 W 3rd Ave Columbus OH 43212",
    "addr:housenumber": "1100",
    "addr:postcode": "43212",
    "addr:street": "W 3Rd Ave",
    "iso:country": "US",
    "sg:address": "1100 W 3rd Ave",
    "sg:city": "Columbus",
    "sg:classifiers": [
      {
        "category": "Wholesale",
        "subcategory": "Vending Machines",
        "type": "Manufacturing \u0026 Wholesale Goods"
      }
    ],
    "sg:phone": "+1 614 421 6800",
    "sg:postcode": "43212",
    "sg:province": "OH",
    "sg:website": "www.shafferdistributing.com",
    "wof:name": "Shaffer Distributing Co",
    "wof:placetype": "venue"
  },
  "geometry": {"coordinates":[-83.034278,39.98472],"type":"Point"}
}
