{
  "type": "Feature",
  "properties": {
    "addr:full":"837 S Hamilton Rd Columbus OH 43213",
    "addr:housenumber":"837",
    "addr:postcode":"43213",
    "addr:street":"S Hamilton Rd",
    "iso:country":"US",
    "sg:address":"837 S Hamilton Rd",
    "sg:city":"Columbus",
    "sg:classifiers":[
        {
            "category":"Restaurant",
            "type":"Food & Drink"
        }
    ],
    "sg:phone":"+1 614 235 7888",
    "sg:postcode":"43213",
    "sg:province":"OH",
    "sg:tags":[
        "eating"
    ],
    "wof:name":"Mc Yao China Buffet",
    "wof:placetype":"venue"
},
  "geometry": {"coordinates":[-82.876525,39.959969],"type":"Point"}
}