{
  "type": "Feature",
  "properties": {
    "addr:full":"256 Pinecrest Dr Gallipolis OH 45614",
    "addr:housenumber":"256",
    "addr:postcode":"45614",
    "addr:street":"Pinecrest Dr",
    "iso:country":"US",
    "sg:address":"256 Pinecrest Dr",
    "sg:city":"Gallipolis",
    "sg:classifiers":[
        {
            "category":"Health Services",
            "subcategory":"Doctor",
            "type":"Services"
        }
    ],
    "sg:phone":"+1 740 446 0021",
    "sg:postcode":"45614",
    "sg:province":"OH",
    "sg:tags":[
        "physician",
        "surgeon"
    ],
    "wof:name":"Hillcrest Urological Clinic",
    "wof:placetype":"venue"
},
  "geometry": {"coordinates":[-82.26397799999999,38.842865],"type":"Point"}
}