{
  "type": "Feature",
  "properties": {
    "iso:country":"US",
    "sg:address":"5922 State Rte 45",
    "sg:city":"Bristolville",
    "sg:classifiers":[
        {
            "category":"Personal",
            "subcategory":"Tattoo Parlor",
            "type":"Services"
        }
    ],
    "sg:phone":"+1 330 847 7560",
    "sg:postcode":"44402",
    "sg:province":"OH",
    "sg:tags":[
        "tattooing"
    ],
    "wof:name":"C & L Tattoos",
    "wof:placetype":"venue"
},
  "geometry": {"coordinates":[-80.866303,41.372035],"type":"Point"}
}