{
  "type": "Feature",
  "properties": {
    "iso:country":"US",
    "sg:address":"3504 W Lakeshore Dr",
    "sg:city":"Port Clinton",
    "sg:classifiers":[
        {
            "category":"Freight",
            "type":"Transportation"
        }
    ],
    "sg:phone":"+1 419 635 2206",
    "sg:postcode":"43452",
    "sg:province":"OH",
    "sg:tags":[
        "local",
        "except",
        "trucking"
    ],
    "wof:name":"Quality Cartage",
    "wof:placetype":"venue"
},
  "geometry": {"coordinates":[-83.001322,41.522886],"type":"Point"}
}