{
  "type": "Feature",
  "properties": {
    "addr:full":"46429 National Rd W Saint Clairsville OH 43950",
    "addr:housenumber":"46429",
    "addr:postcode":"43950",
    "addr:street":"National Rd W Saint Clairsville",
    "iso:country":"US",
    "sg:address":"46429 National Rd W",
    "sg:city":"Saint Clairsville",
    "sg:classifiers":[
        {
            "category":"Autos & Motor Vehicles",
            "subcategory":"Auto Supplies",
            "type":"Retail Goods"
        }
    ],
    "sg:phone":"+1 740 695 0604",
    "sg:postcode":"43950",
    "sg:province":"OH",
    "wof:name":"Rons Truck Parts",
    "wof:placetype":"venue"
},
  "geometry": {"coordinates":[-80.957577,40.072554],"type":"Point"}
}