{
  "type": "Feature",
  "properties": {
    "addr:full":"310 Glenwood Ave Napoleon OH 43545",
    "addr:housenumber":"310",
    "addr:postcode":"43545",
    "addr:street":"Glenwood Ave",
    "iso:country":"US",
    "sg:address":"310 Glenwood Ave",
    "sg:city":"Napoleon",
    "sg:classifiers":[
        {
            "category":"Government",
            "subcategory":"Police Station",
            "type":"Public Place"
        }
    ],
    "sg:phone":"+1 419 599 2810",
    "sg:postcode":"43545",
    "sg:province":"OH",
    "sg:tags":[
        "department",
        "local"
    ],
    "wof:name":"Police Department",
    "wof:placetype":"venue"
},
  "geometry": {"coordinates":[-84.141156,41.384337],"type":"Point"}
}