{
  "type": "Feature",
  "properties": {
    "addr:full": "114 S Main St Findlay OH 45840",
    "addr:housenumber": "114",
    "addr:postcode": "45840",
    "addr:street": "S Main St",
    "iso:country": "US",
    "sg:address": "114 S Main St",
    "sg:city": "Findlay",
    "sg:classifiers": [
      {
        "category": "Social Services",
        "subcategory": "Adult Care",
        "type": "Services"
      }
    ],
    "sg:phone": "+1 419 427 3320",
    "sg:postcode": "45840",
    "sg:province": "OH",
    "sg:tags": [
      "foster"
    ],
    "wof:name": "Specialized Alternatives-Youth",
    "wof:placetype": "venue"
  },
  "geometry": {"coordinates":[-83.650275,41.041276],"type":"Point"}
}
