{
  "type": "Feature",
  "properties": {
    "iso:country":"US",
    "sg:address":"6326 State Rte 95",
    "sg:city":"Butler",
    "sg:classifiers":[
        {
            "category":"Building & Trades",
            "subcategory":"Construction",
            "type":"Services"
        }
    ],
    "sg:phone":"+1 419 883 3327",
    "sg:postcode":"44822",
    "sg:province":"OH",
    "sg:tags":[
        "house"
    ],
    "wof:name":"John L Fletcher Home Imprv",
    "wof:placetype":"venue"
},
  "geometry": {"coordinates":[-82.41562399999999,40.598038],"type":"Point"}
}