{
  "type": "Feature",
  "properties": {
    "addr:full": "6326 State Rte 95 Butler OH 44822",
    "addr:housenumber": "6326",
    "addr:postcode": "44822",
    "addr:street": "State Rte 95",
    "iso:country": "US",
    "sg:address": "6326 State Rte 95",
    "sg:city": "Butler",
    "sg:classifiers": [
      {
        "category": "Building \u0026 Trades",
        "subcategory": "Construction",
        "type": "Services"
      }
    ],
    "sg:phone": "+1 419 883 3327",
    "sg:postcode": "44822",
    "sg:province": "OH",
    "sg:tags": [
      "house"
    ],
    "wof:name": "John L Fletcher Home Imprv",
    "wof:placetype": "venue"
  },
  "geometry": {"coordinates":[-82.415624,40.598038],"type":"Point"}
}
