{
  "type": "Feature",
  "properties": {
    "addr:full": "4401 Rockside Rd Cleveland OH 44131",
    "addr:housenumber": "4401",
    "addr:postcode": "44131",
    "addr:street": "Rockside Rd",
    "iso:country": "US",
    "sg:address": "4401 Rockside Rd",
    "sg:city": "Cleveland",
    "sg:classifiers": [
      {
        "category": "Professional",
        "subcategory": "Employment Agencies",
        "type": "Services"
      }
    ],
    "sg:phone": "+1 216 520 0309",
    "sg:postcode": "44131",
    "sg:province": "OH",
    "sg:tags": [
      "opportunity"
    ],
    "sg:website": "www.intelistaf.com",
    "wof:name": "Inteli Staf Healthcare",
    "wof:placetype": "venue"
  },
  "geometry": {"coordinates":[-81.661878,41.399581],"type":"Point"}
}
