{
  "type": "Feature",
  "properties": {
    "addr:full": "540 Trumbull Ave Cortland OH 44420",
    "addr:housenumber": "540",
    "addr:postcode": "44420",
    "addr:street": "Trumbull Ave",
    "iso:country": "US",
    "sg:address": "540 Trumbull Ave",
    "sg:city": "Cortland",
    "sg:classifiers": [
      {
        "category": "Insurance",
        "subcategory": "Insurance Agent",
        "type": "Services"
      }
    ],
    "sg:phone": "+1 330 638 4700",
    "sg:postcode": "44420",
    "sg:province": "OH",
    "sg:tags": [
      "agency"
    ],
    "wof:name": "Theresa Kowalczyk Insur Agcy",
    "wof:placetype": "venue"
  },
  "geometry": {"coordinates":[-80.679707,41.141226],"type":"Point"}
}
