{
  "type": "Feature",
  "properties": {
    "addr:full": "1866 Shela Blvd Portsmouth OH 45662",
    "addr:housenumber": "1866",
    "addr:postcode": "45662",
    "addr:street": "Shela Blvd",
    "iso:country": "US",
    "sg:address": "1866 Shela Blvd",
    "sg:city": "Portsmouth",
    "sg:classifiers": [
      {
        "category": "Organizations",
        "subcategory": "Religious Organization",
        "type": "Services"
      }
    ],
    "sg:phone": "+1 740 776 7411",
    "sg:postcode": "45662",
    "sg:province": "OH",
    "sg:tags": [
      "church"
    ],
    "wof:name": "Sciotodale Freewill Baptist Ch",
    "wof:placetype": "venue"
  },
  "geometry": {"coordinates":[-82.852101,38.74883],"type":"Point"}
}
