{
  "type": "Feature",
  "properties": {
    "addr:full": "3570 Cedarbrook Rd Cleveland OH 44118",
    "addr:housenumber": "3570",
    "addr:postcode": "44118",
    "addr:street": "Cedarbrook Rd",
    "iso:country": "US",
    "sg:address": "3570 Cedarbrook Rd",
    "sg:city": "Cleveland",
    "sg:classifiers": [
      {
        "category": "Real Estate",
        "subcategory": "Real Estate Agent",
        "type": "Services"
      }
    ],
    "sg:phone": "+1 216 371 1686",
    "sg:postcode": "44118",
    "sg:province": "OH",
    "wof:name": "Sampson Appraisals",
    "wof:placetype": "venue"
  },
  "geometry": {"coordinates":[-81.550936,41.50032],"type":"Point"}
}
