{
  "type": "Feature",
  "properties": {
    "addr:full": "24100 Palm Dr North Olmsted OH 44070",
    "addr:housenumber": "24100",
    "addr:postcode": "44070",
    "addr:street": "Palm Dr",
    "iso:country": "US",
    "sg:address": "24100 Palm Dr",
    "sg:city": "North Olmsted",
    "sg:classifiers": [
      {
        "category": "Education",
        "subcategory": "School",
        "type": "Public Place"
      }
    ],
    "sg:phone": "+1 440 779 3570",
    "sg:postcode": "44070",
    "sg:province": "OH",
    "wof:name": "Birch Kindergarten",
    "wof:placetype": "venue"
  },
  "geometry": {"coordinates":[-81.889029,41.423859],"type":"Point"}
}
