{
  "type": "Feature",
  "properties": {
    "iso:country":"US",
    "sg:address":"24100 Palm Dr",
    "sg:city":"North Olmsted",
    "sg:classifiers":[
        {
            "category":"Education",
            "subcategory":"School",
            "type":"Public Place"
        }
    ],
    "sg:phone":"+1 440 779 3570",
    "sg:postcode":"44070",
    "sg:province":"OH",
    "wof:name":"Birch Kindergarten",
    "wof:placetype":"venue"
},
  "geometry": {"coordinates":[-81.88902899999999,41.423859],"type":"Point"}
}