{
  "type": "Feature",
  "properties": {
    "addr:full":"1800 Coventry Rd Cleveland OH 44118",
    "addr:housenumber":"1800",
    "addr:postcode":"44118",
    "addr:street":"Coventry Rd",
    "iso:country":"US",
    "sg:address":"1800 Coventry Rd",
    "sg:city":"Cleveland",
    "sg:classifiers":[
        {
            "category":"Restaurant",
            "type":"Food & Drink"
        }
    ],
    "sg:menulink":"http://www.allmenus.com/oh/cleveland-heights/37618-hunan-coventry/menu/",
    "sg:phone":"+1 216 371 0777",
    "sg:postcode":"44118",
    "sg:province":"OH",
    "sg:tags":[
        "asian",
        "chinese"
    ],
    "wof:name":"Hunan Coventry",
    "wof:placetype":"venue"
},
  "geometry": {"coordinates":[-81.580219,41.50976],"type":"Point"}
}