{
  "type": "Feature",
  "properties": {
    "addr:full":"980 Springville Ave Fostoria OH 44830",
    "addr:housenumber":"980",
    "addr:postcode":"44830",
    "addr:street":"Springville Ave",
    "iso:country":"US",
    "sg:address":"980 Springville Ave",
    "sg:city":"Fostoria",
    "sg:classifiers":[
        {
            "category":"Retail",
            "subcategory":"Repair Shop",
            "type":"Services"
        }
    ],
    "sg:phone":"+1 419 435 8909",
    "sg:postcode":"44830",
    "sg:province":"OH",
    "sg:tags":[
        "refinishing",
        "furniture"
    ],
    "wof:name":"Custom Quality Finishing",
    "wof:placetype":"venue"
},
  "geometry": {"coordinates":[-83.40167,41.147137],"type":"Point"}
}