{
  "type": "Feature",
  "properties": {
    "addr:full":"500 Grant St Akron OH 44311",
    "addr:housenumber":"500",
    "addr:postcode":"44311",
    "addr:street":"Grant St",
    "iso:country":"US",
    "sg:address":"500 Grant St",
    "sg:city":"Akron",
    "sg:classifiers":[
        {
            "category":"Professional",
            "subcategory":"Advertising",
            "type":"Services"
        }
    ],
    "sg:phone":"+1 330 255 1115",
    "sg:postcode":"44311",
    "sg:province":"OH",
    "wof:name":"Ispod.Net LLC",
    "wof:placetype":"venue"
},
  "geometry": {"coordinates":[-81.51784600000001,41.070881],"type":"Point"}
}