{
  "type": "Feature",
  "properties": {
    "iso:country":"US",
    "sg:address":"2745 Dunkeith Dr NW",
    "sg:city":"Canton",
    "sg:classifiers":[
        {
            "category":"Shopping",
            "subcategory":"Pharmacy",
            "type":"Retail Goods"
        }
    ],
    "sg:phone":"+1 330 456 2476",
    "sg:postcode":"44708",
    "sg:province":"OH",
    "wof:name":"Fulton Road Pharmacy Inc",
    "wof:placetype":"venue"
},
  "geometry": {"coordinates":[-81.444782,40.831214],"type":"Point"}
}