{
  "type": "Feature",
  "properties": {
    "iso:country":"US",
    "sg:address":"1937 Stockton Dr",
    "sg:city":"Loveland",
    "sg:classifiers":[
        {
            "category":"Professional",
            "type":"Services"
        }
    ],
    "sg:phone":"+1 513 683 1864",
    "sg:postcode":"45140",
    "sg:province":"OH",
    "wof:name":"Walter J & Lois Wynne",
    "wof:placetype":"venue"
},
  "geometry": {"coordinates":[-84.29661299999999,39.273077],"type":"Point"}
}