{
  "type": "Feature",
  "properties": {
    "addr:full": "5140 Pearl Rd Cleveland OH 44129",
    "addr:housenumber": "5140",
    "addr:postcode": "44129",
    "addr:street": "Pearl Rd",
    "iso:country": "US",
    "sg:address": "5140 Pearl Rd",
    "sg:city": "Cleveland",
    "sg:classifiers": [
      {
        "category": "Home \u0026 Garden",
        "subcategory": "Furniture",
        "type": "Retail Goods"
      }
    ],
    "sg:phone": "+1 216 749 3923",
    "sg:postcode": "44129",
    "sg:province": "OH",
    "sg:tags": [
      "store"
    ],
    "wof:name": "Maric Express",
    "wof:placetype": "venue"
  },
  "geometry": {"coordinates":[-81.726875,41.41976],"type":"Point"}
}
