{
  "type": "Feature",
  "properties": {
    "iso:country":"US",
    "sg:address":"5140 Pearl Rd",
    "sg:city":"Cleveland",
    "sg:classifiers":[
        {
            "category":"Home & Garden",
            "subcategory":"Furniture",
            "type":"Retail Goods"
        }
    ],
    "sg:phone":"+1 216 749 3923",
    "sg:postcode":"44129",
    "sg:province":"OH",
    "sg:tags":[
        "store"
    ],
    "wof:name":"Maric Express",
    "wof:placetype":"venue"
},
  "geometry": {"coordinates":[-81.72687500000001,41.41976],"type":"Point"}
}