{
  "type": "Feature",
  "properties": {
    "addr:full": "13257 Prospect Rd Strongsville OH 44149",
    "addr:housenumber": "13257",
    "addr:postcode": "44149",
    "addr:street": "Prospect Rd",
    "iso:country": "US",
    "sg:address": "13257 Prospect Rd",
    "sg:city": "Strongsville",
    "sg:classifiers": [
      {
        "category": "Wholesale",
        "subcategory": "Office Equipment",
        "type": "Manufacturing \u0026 Wholesale Goods"
      }
    ],
    "sg:phone": "+1 440 238 6871",
    "sg:postcode": "44149",
    "sg:province": "OH",
    "sg:tags": [
      "machine",
      "duplicating",
      "copying"
    ],
    "wof:name": "Aatawba Business Systems",
    "wof:placetype": "venue"
  },
  "geometry": {"coordinates":[-81.857702,41.319663],"type":"Point"}
}
