{
  "type": "Feature",
  "properties": {
    "addr:full": "1416 Brick School Rd Gallipolis OH 45631",
    "addr:housenumber": "1416",
    "addr:postcode": "45631",
    "addr:street": "Brick School Rd",
    "iso:country": "US",
    "sg:address": "1416 Brick School Rd",
    "sg:city": "Gallipolis",
    "sg:classifiers": [
      {
        "category": "Building \u0026 Trades",
        "subcategory": "Construction",
        "type": "Services"
      }
    ],
    "sg:phone": "+1 740 367 7265",
    "sg:postcode": "45631",
    "sg:province": "OH",
    "sg:tags": [
      "house",
      "contractor"
    ],
    "wof:name": "Martins Home Improvement",
    "wof:placetype": "venue"
  },
  "geometry": {"coordinates":[-82.184491,38.907172],"type":"Point"}
}
