{
  "type": "Feature",
  "properties": {
    "iso:country":"US",
    "sg:address":"1416 Brick School Rd",
    "sg:city":"Gallipolis",
    "sg:classifiers":[
        {
            "category":"Building & Trades",
            "subcategory":"Construction",
            "type":"Services"
        }
    ],
    "sg:phone":"+1 740 367 7265",
    "sg:postcode":"45631",
    "sg:province":"OH",
    "sg:tags":[
        "house",
        "contractor"
    ],
    "wof:name":"Martins Home Improvement",
    "wof:placetype":"venue"
},
  "geometry": {"coordinates":[-82.18449099999999,38.907172],"type":"Point"}
}