{
  "type": "Feature",
  "properties": {
    "addr:full": "209 Eastern Ave Woodsfield OH 43793",
    "addr:housenumber": "209",
    "addr:postcode": "43793",
    "addr:street": "Eastern Ave",
    "iso:country": "US",
    "sg:address": "209 Eastern Ave",
    "sg:city": "Woodsfield",
    "sg:classifiers": [
      {
        "category": "Restaurant",
        "type": "Food \u0026 Drink"
      }
    ],
    "sg:phone": "+1 740 472 1721",
    "sg:postcode": "43793",
    "sg:province": "OH",
    "wof:name": "Pat's Corner Cafe",
    "wof:placetype": "venue"
  },
  "geometry": {"coordinates":[-81.112393,39.762164],"type":"Point"}
}
