{
  "type": "Feature",
  "properties": {
    "addr:full":"2291 Riverfront Pkwy Cuyahoga Falls OH 44221",
    "addr:housenumber":"2291",
    "addr:postcode":"44221",
    "addr:street":"Riverfront Pkwy",
    "iso:country":"US",
    "sg:address":"2291 Riverfront Pkwy",
    "sg:city":"Cuyahoga Falls",
    "sg:classifiers":[
        {
            "category":"Professional",
            "subcategory":"Advertising",
            "type":"Services"
        }
    ],
    "sg:phone":"+1 330 945 6232",
    "sg:postcode":"44221",
    "sg:province":"OH",
    "sg:tags":[
        "counselor"
    ],
    "sg:website":"www.maddoxmarketing.com",
    "wof:name":"Maddox Marketing Group Inc",
    "wof:placetype":"venue"
},
  "geometry": {"coordinates":[-81.48205,41.137232],"type":"Point"}
}