{
  "type": "Feature",
  "properties": {
    "addr:full": "208 Sunflower Dr Brunswick OH 44212",
    "addr:housenumber": "208",
    "addr:postcode": "44212",
    "addr:street": "Sunflower Dr",
    "iso:country": "US",
    "sg:address": "208 Sunflower Dr",
    "sg:city": "Brunswick",
    "sg:classifiers": [
      {
        "category": "Restaurant",
        "type": "Food \u0026 Drink"
      }
    ],
    "sg:phone": "+1 330 225 1897",
    "sg:postcode": "44212",
    "sg:province": "OH",
    "sg:tags": [
      "eating"
    ],
    "wof:name": "Sandra Snack",
    "wof:placetype": "venue"
  },
  "geometry": {"coordinates":[-81.826364,41.269718],"type":"Point"}
}
