{
  "type": "Feature",
  "properties": {
    "iso:country":"US",
    "sg:address":"5951 E Main St",
    "sg:city":"Columbus",
    "sg:classifiers":[
        {
            "category":"Professional",
            "subcategory":"Employment Agencies",
            "type":"Services"
        }
    ],
    "sg:phone":"+1 614 552 3285",
    "sg:postcode":"43213",
    "sg:province":"OH",
    "sg:tags":[
        "help",
        "contractor"
    ],
    "wof:name":"Interim Personnel",
    "wof:placetype":"venue"
},
  "geometry": {"coordinates":[-82.83867499999999,39.95463],"type":"Point"}
}