{
  "type": "Feature",
  "properties": {
    "addr:full": "5951 E Main St Columbus OH 43213",
    "addr:housenumber": "5951",
    "addr:postcode": "43213",
    "addr:street": "E Main St",
    "iso:country": "US",
    "sg:address": "5951 E Main St",
    "sg:city": "Columbus",
    "sg:classifiers": [
      {
        "category": "Professional",
        "subcategory": "Employment Agencies",
        "type": "Services"
      }
    ],
    "sg:phone": "+1 614 552 3285",
    "sg:postcode": "43213",
    "sg:province": "OH",
    "sg:tags": [
      "help",
      "contractor"
    ],
    "wof:name": "Interim Personnel",
    "wof:placetype": "venue"
  },
  "geometry": {"coordinates":[-82.838675,39.95463],"type":"Point"}
}
