{
  "type": "Feature",
  "properties": {
    "iso:country":"US",
    "sg:address":"644 Bridgeside Dr",
    "sg:city":"Avon Lake",
    "sg:classifiers":[
        {
            "category":"Professional",
            "subcategory":"Detective & Security Services",
            "type":"Services"
        }
    ],
    "sg:phone":"+1 440 331 4455",
    "sg:postcode":"44012",
    "sg:province":"OH",
    "sg:tags":[
        "investigation",
        "private"
    ],
    "wof:name":"Discovery Resources Inc",
    "wof:placetype":"venue"
},
  "geometry": {"coordinates":[-81.97860300000001,41.488342],"type":"Point"}
}