{
  "type": "Feature",
  "properties": {
    "addr:full":"610 Oxford Dr Bryan OH 43506",
    "addr:housenumber":"610",
    "addr:postcode":"43506",
    "addr:street":"Oxford Dr",
    "iso:country":"US",
    "sg:address":"610 Oxford Dr",
    "sg:city":"Bryan",
    "sg:classifiers":[
        {
            "category":"Shopping",
            "subcategory":"Gifts & Souvenirs",
            "type":"Retail Goods"
        }
    ],
    "sg:phone":"+1 419 636 1838",
    "sg:postcode":"43506",
    "sg:province":"OH",
    "wof:name":"C June Smith",
    "wof:placetype":"venue"
},
  "geometry": {"coordinates":[-84.560788,41.467516],"type":"Point"}
}