{
  "type": "Feature",
  "properties": {
    "iso:country":"US",
    "sg:address":"1203 Tuscarawas St W",
    "sg:city":"Canton",
    "sg:classifiers":[
        {
            "category":"Wholesale",
            "subcategory":"Auto Parts",
            "type":"Manufacturing & Wholesale Goods"
        }
    ],
    "sg:phone":"+1 330 454 8009",
    "sg:postcode":"44702",
    "sg:province":"OH",
    "sg:tags":[
        "supply"
    ],
    "wof:name":"Surefit Auto Care Center",
    "wof:placetype":"venue"
},
  "geometry": {"coordinates":[-81.386087,40.800674],"type":"Point"}
}