{
  "type": "Feature",
  "properties": {
    "addr:full": "4197 W 20th St Cleveland OH 44109",
    "addr:housenumber": "4197",
    "addr:postcode": "44109",
    "addr:street": "W 20Th St",
    "iso:country": "US",
    "sg:address": "4197 W 20th St",
    "sg:city": "Cleveland",
    "sg:classifiers": [
      {
        "category": "Real Estate",
        "subcategory": "Real Estate Operator",
        "type": "Services"
      }
    ],
    "sg:phone": "+1 216 459 8810",
    "sg:postcode": "44109",
    "sg:province": "OH",
    "sg:tags": [
      "building",
      "apartment"
    ],
    "wof:name": "G M Management Co",
    "wof:placetype": "venue"
  },
  "geometry": {"coordinates":[-81.697094,41.44204],"type":"Point"}
}
