{
  "type": "Feature",
  "properties": {
    "iso:country":"US",
    "sg:address":"4045 Valleyview Ave",
    "sg:city":"Steubenville",
    "sg:classifiers":[
        {
            "category":"Building & Trades",
            "subcategory":"Construction",
            "type":"Services"
        }
    ],
    "sg:phone":"+1 740 264 3541",
    "sg:postcode":"43952",
    "sg:province":"OH",
    "sg:tags":[
        "general",
        "contractor"
    ],
    "wof:name":"Fort Steuben Construction",
    "wof:placetype":"venue"
},
  "geometry": {"coordinates":[-80.670945,40.381257],"type":"Point"}
}