{
  "type": "Feature",
  "properties": {
    "addr:full": "3470 N Brock-Whitzel Rd Malta OH 43758",
    "addr:housenumber": "3470",
    "addr:postcode": "43758",
    "addr:street": "N Brock-Whitzel Rd",
    "iso:country": "US",
    "sg:address": "3470 N Brock-Whitzel Rd",
    "sg:city": "Malta",
    "sg:classifiers": [
      {
        "category": "Retail",
        "subcategory": "Repair Shop",
        "type": "Services"
      }
    ],
    "sg:phone": "+1 740 962 4643",
    "sg:postcode": "43758",
    "sg:province": "OH",
    "sg:tags": [
      "furniture"
    ],
    "wof:name": "Davis \u0026 Son Uphl \u0026 Refinishing",
    "wof:placetype": "venue"
  },
  "geometry": {"coordinates":[-81.926484,39.640384],"type":"Point"}
}
