{
  "type": "Feature",
  "properties": {
    "addr:full":"560 E Livingston Ave Columbus OH 43215",
    "addr:housenumber":"560",
    "addr:postcode":"43215",
    "addr:street":"E Livingston Ave",
    "iso:country":"US",
    "sg:address":"560 E Livingston Ave",
    "sg:city":"Columbus",
    "sg:classifiers":[
        {
            "category":"Food & Beverages",
            "subcategory":"Groceries & Convenience Stores",
            "type":"Retail Goods"
        }
    ],
    "sg:phone":"+1 614 221 8043",
    "sg:postcode":"43215",
    "sg:province":"OH",
    "sg:website":"www.krogers.com",
    "wof:name":"Kroger",
    "wof:placetype":"venue"
},
  "geometry": {"coordinates":[-82.98276300000001,39.952249],"type":"Point"}
}