{
  "type": "Feature",
  "properties": {
    "addr:full": "31008 Lake Shore Blvd Willoughby OH 44095",
    "addr:housenumber": "31008",
    "addr:postcode": "44095",
    "addr:street": "Lake Shore Blvd",
    "iso:country": "US",
    "sg:address": "31008 Lake Shore Blvd",
    "sg:city": "Willoughby",
    "sg:classifiers": [
      {
        "category": "Autos \u0026 Motor Vehicles",
        "subcategory": "Fuel \u0026 Gas Station",
        "type": "Retail Goods"
      }
    ],
    "sg:phone": "+1 440 943 9810",
    "sg:postcode": "44095",
    "sg:province": "OH",
    "sg:tags": [
      "general"
    ],
    "wof:name": "Yanos Automotive",
    "wof:placetype": "venue"
  },
  "geometry": {"coordinates":[-81.469566,41.644054],"type":"Point"}
}
