{
  "type": "Feature",
  "properties": {
    "addr:full":"241 16th St Toledo OH 43604",
    "addr:housenumber":"241",
    "addr:postcode":"43604",
    "addr:street":"16Th St",
    "iso:country":"US",
    "sg:address":"241 16th St",
    "sg:city":"Toledo",
    "sg:classifiers":[
        {
            "category":"Organizations",
            "subcategory":"Religious Organization",
            "type":"Services"
        }
    ],
    "sg:phone":"+1 419 243 3901",
    "sg:postcode":"43604",
    "sg:province":"OH",
    "sg:tags":[
        "church"
    ],
    "wof:name":"Church Of Jesus Christ Of Lds",
    "wof:placetype":"venue"
},
  "geometry": {"coordinates":[-83.545879,41.655954],"type":"Point"}
}