{
  "type": "Feature",
  "properties": {
    "addr:full":"19854 Idlewood Trl Strongsville OH 44149",
    "addr:housenumber":"19854",
    "addr:postcode":"44149",
    "addr:street":"Idlewood Trl",
    "iso:country":"US",
    "sg:address":"19854 Idlewood Trl",
    "sg:city":"Strongsville",
    "sg:classifiers":[
        {
            "category":"Building & Trades",
            "subcategory":"Electrical",
            "type":"Services"
        }
    ],
    "sg:phone":"+1 440 238 0234",
    "sg:postcode":"44149",
    "sg:province":"OH",
    "sg:tags":[
        "electrical",
        "contractor"
    ],
    "wof:name":"Anthony Labianca Electrician",
    "wof:placetype":"venue"
},
  "geometry": {"coordinates":[-81.84363999999999,41.328182],"type":"Point"}
}