{
  "type": "Feature",
  "properties": {
    "iso:country":"US",
    "sg:address":"641 Northland Blvd",
    "sg:city":"Cincinnati",
    "sg:classifiers":[
        {
            "category":"Professional",
            "subcategory":"Accounting & Tax Preparation",
            "type":"Services"
        }
    ],
    "sg:phone":"+1 513 851 3243",
    "sg:postcode":"45240",
    "sg:province":"OH",
    "sg:tags":[
        "return",
        "filing"
    ],
    "sg:website":"www.jacksonhewitt.com",
    "wof:name":"Jackson Hewitt Tax Svc",
    "wof:placetype":"venue"
},
  "geometry": {"coordinates":[-84.497212,39.281319],"type":"Point"}
}