{
  "type": "Feature",
  "properties": {
    "addr:full":"978 W Walnut St Canal Winchester OH 43110",
    "addr:housenumber":"978",
    "addr:postcode":"43110",
    "addr:street":"W Walnut St",
    "iso:country":"US",
    "sg:address":"978 W Walnut St",
    "sg:city":"Canal Winchester",
    "sg:classifiers":[
        {
            "category":"Autos & Motor Vehicles",
            "subcategory":"Automobile Sales",
            "type":"Retail Goods"
        }
    ],
    "sg:phone":"+1 614 837 8844",
    "sg:postcode":"43110",
    "sg:province":"OH",
    "sg:tags":[
        "used",
        "classic"
    ],
    "wof:name":"Wayne's World",
    "wof:placetype":"venue"
},
  "geometry": {"coordinates":[-82.831671,39.848244],"type":"Point"}
}