{
  "type": "Feature",
  "properties": {
    "addr:full": "107 E Dublin Granville Rd New Albany OH 43054",
    "addr:housenumber": "107",
    "addr:postcode": "43054",
    "addr:street": "E Dublin Granville Rd",
    "iso:country": "US",
    "sg:address": "107 E Dublin Granville Rd",
    "sg:city": "New Albany",
    "sg:classifiers": [
      {
        "category": "Professional",
        "type": "Services"
      }
    ],
    "sg:phone": "+1 614 855 9861",
    "sg:postcode": "43054",
    "sg:province": "OH",
    "sg:tags": [
      "establishment"
    ],
    "wof:name": "KERN-Harrington House",
    "wof:placetype": "venue"
  },
  "geometry": {"coordinates":[-82.817309,40.082983],"type":"Point"}
}
