{
  "type": "Feature",
  "properties": {
    "addr:full":"703 Tyler St Sandusky OH 44870",
    "addr:housenumber":"703",
    "addr:postcode":"44870",
    "addr:street":"Tyler St",
    "iso:country":"US",
    "sg:address":"703 Tyler St",
    "sg:city":"Sandusky",
    "sg:classifiers":[
        {
            "category":"Community Center",
            "type":"Public Place"
        }
    ],
    "sg:phone":"+1 419 626 3464",
    "sg:postcode":"44870",
    "sg:province":"OH",
    "sg:tags":[
        "medical"
    ],
    "sg:website":"www.fmc-ag.com",
    "wof:name":"Fresenius Medical Care",
    "wof:placetype":"venue"
},
  "geometry": {"coordinates":[-82.717598,41.427101],"type":"Point"}
}