{
  "type": "Feature",
  "properties": {
    "iso:country":"US",
    "sg:address":"4771 Fulton Dr NW",
    "sg:city":"Canton",
    "sg:classifiers":[
        {
            "category":"Building & Trades",
            "subcategory":"Landscaping Services",
            "type":"Services"
        }
    ],
    "sg:phone":"+1 330 493 6811",
    "sg:postcode":"44718",
    "sg:province":"OH",
    "sg:tags":[
        "snowplowing"
    ],
    "wof:name":"Proper Lawn Care and Landscape",
    "wof:placetype":"venue"
},
  "geometry": {"coordinates":[-81.443289,40.848783],"type":"Point"}
}