{
  "type": "Feature",
  "properties": {
    "iso:country":"US",
    "sg:address":"812 S Water St",
    "sg:city":"Kent",
    "sg:classifiers":[
        {
            "category":"Social Services",
            "type":"Services"
        }
    ],
    "sg:phone":"+1 330 673 3676",
    "sg:postcode":"44240",
    "sg:province":"OH",
    "sg:tags":[
        "counseling"
    ],
    "wof:name":"Joan D Rogers",
    "wof:placetype":"venue"
},
  "geometry": {"coordinates":[-81.35836500000001,41.146306],"type":"Point"}
}