{
  "type": "Feature",
  "properties": {
    "addr:full": "1216 Eastern Ave Gallipolis OH 45631",
    "addr:housenumber": "1216",
    "addr:postcode": "45631",
    "addr:street": "Eastern Ave",
    "iso:country": "US",
    "sg:address": "1216 Eastern Ave",
    "sg:city": "Gallipolis",
    "sg:classifiers": [
      {
        "category": "Retail",
        "subcategory": "Repair Shop",
        "type": "Services"
      }
    ],
    "sg:phone": "+1 740 446 7398",
    "sg:postcode": "45631",
    "sg:province": "OH",
    "sg:tags": [
      "appliance"
    ],
    "wof:name": "Skaggs Appliance Svc",
    "wof:placetype": "venue"
  },
  "geometry": {"coordinates":[-82.18985,38.816568],"type":"Point"}
}
