{
  "type": "Feature",
  "properties": {
    "addr:full": "233 Whiley Ave Lancaster OH 43130",
    "addr:housenumber": "233",
    "addr:postcode": "43130",
    "addr:street": "Whiley Ave",
    "iso:country": "US",
    "sg:address": "233 Whiley Ave",
    "sg:city": "Lancaster",
    "sg:classifiers": [
      {
        "category": "Professional",
        "subcategory": "Research",
        "type": "Services"
      }
    ],
    "sg:phone": "+1 740 687 1554",
    "sg:postcode": "43130",
    "sg:province": "OH",
    "sg:tags": [
      "environmental",
      "ecological"
    ],
    "wof:name": "Us T Environmental Contractor",
    "wof:placetype": "venue"
  },
  "geometry": {"coordinates":[-82.607498,39.711748],"type":"Point"}
}
