{
  "type": "Feature",
  "properties": {
    "addr:full":"647 Lawnhaven Dr Mogadore OH 44260",
    "addr:housenumber":"647",
    "addr:postcode":"44260",
    "addr:street":"Lawnhaven Dr",
    "iso:country":"US",
    "sg:address":"647 Lawnhaven Dr",
    "sg:city":"Mogadore",
    "sg:classifiers":[
        {
            "category":"Building & Trades",
            "subcategory":"Construction",
            "type":"Services"
        }
    ],
    "sg:phone":"+1 330 699 2512",
    "sg:postcode":"44260",
    "sg:province":"OH",
    "sg:tags":[
        "house",
        "contractor"
    ],
    "sg:website":"www.jamestowncustomhomes.com",
    "wof:name":"Jamestown Homes Inc",
    "wof:placetype":"venue"
},
  "geometry": {"coordinates":[-81.385638,41.006063],"type":"Point"}
}