{
  "type": "Feature",
  "properties": {
    "addr:full": "3219 Tremainsville Rd Toledo OH 43613",
    "addr:housenumber": "3219",
    "addr:postcode": "43613",
    "addr:street": "Tremainsville Rd",
    "iso:country": "US",
    "sg:address": "3219 Tremainsville Rd",
    "sg:city": "Toledo",
    "sg:classifiers": [
      {
        "category": "Retail",
        "subcategory": "Funeral Services",
        "type": "Services"
      }
    ],
    "sg:phone": "+1 419 473 1301",
    "sg:postcode": "43613",
    "sg:province": "OH",
    "wof:name": "H H Birkenkamp Funeral Home",
    "wof:placetype": "venue"
  },
  "geometry": {"coordinates":[-83.621232,41.720673],"type":"Point"}
}
