{
  "type": "Feature",
  "properties": {
    "addr:full":"106 E Main St Bellevue OH 44811",
    "addr:housenumber":"106",
    "addr:postcode":"44811",
    "addr:street":"E Main St",
    "iso:country":"US",
    "sg:address":"106 E Main St",
    "sg:city":"Bellevue",
    "sg:classifiers":[
        {
            "category":"Bars & Pubs",
            "type":"Food & Drink"
        }
    ],
    "sg:phone":"+1 419 483 2110",
    "sg:postcode":"44811",
    "sg:province":"OH",
    "sg:tags":[
        "drinking"
    ],
    "wof:name":"Tinas",
    "wof:placetype":"venue"
},
  "geometry": {"coordinates":[-82.840711,41.27358],"type":"Point"}
}