{
  "type": "Feature",
  "properties": {
    "iso:country":"US",
    "sg:address":"189 E Main St",
    "sg:city":"St Clairsville",
    "sg:classifiers":[
        {
            "category":"Professional",
            "subcategory":"Business Services",
            "type":"Services"
        },
        {
            "category":"Home & Garden",
            "subcategory":"Home Furnishings",
            "type":"Retail Goods"
        }
    ],
    "sg:phone":"+1 740 695 9903",
    "sg:postcode":"43950",
    "sg:province":"OH",
    "sg:tags":[
        "interior",
        "consultant",
        "design",
        "decorator"
    ],
    "wof:name":"Window Fashions By Beth",
    "wof:placetype":"venue"
},
  "geometry": {"coordinates":[-80.896688,40.081323],"type":"Point"}
}