{
  "type": "Feature",
  "properties": {
    "iso:country":"US",
    "sg:address":"7632 Hub Pkwy",
    "sg:city":"Cleveland",
    "sg:classifiers":[
        {
            "category":"Retail",
            "subcategory":"Repair Shop",
            "type":"Services"
        }
    ],
    "sg:phone":"+1 216 525 0050",
    "sg:postcode":"44125",
    "sg:province":"OH",
    "sg:tags":[
        "instrumentation",
        "industrial",
        "for",
        "supply",
        "equipment",
        "electronic"
    ],
    "sg:website":"www.calibrationservice.com",
    "wof:name":"Broadview Instrumentation Svcs",
    "wof:placetype":"venue"
},
  "geometry": {"coordinates":[-81.588565,41.364051],"type":"Point"}
}