{
  "type": "Feature",
  "properties": {
    "iso:country":"US",
    "sg:address":"755 Boardman Canfield Rd Suite N3",
    "sg:city":"Youngstown",
    "sg:classifiers":[
        {
            "category":"Real Estate",
            "subcategory":"Real Estate Services",
            "type":"Services"
        },
        {
            "category":"Real Estate",
            "subcategory":"Real Estate Agent",
            "type":"Services"
        }
    ],
    "sg:phone":"+1 330 965 6500",
    "sg:postcode":"44512",
    "sg:province":"OH",
    "sg:tags":[
        "commercial"
    ],
    "sg:website":"http://www.kutlickrealtyllc.com",
    "wof:name":"Kutlick Realty LLC",
    "wof:placetype":"venue"
},
  "geometry": {"coordinates":[-80.68534099999999,41.024509],"type":"Point"}
}