{
  "type": "Feature",
  "properties": {
    "addr:full": "8118 Montgomery Rd Cincinnati OH 45236",
    "addr:housenumber": "8118",
    "addr:postcode": "45236",
    "addr:street": "Montgomery Rd",
    "iso:country": "US",
    "sg:address": "8118 Montgomery Rd",
    "sg:city": "Cincinnati",
    "sg:classifiers": [
      {
        "category": "Professional",
        "subcategory": "Business Services",
        "type": "Services"
      }
    ],
    "sg:phone": "+1 513 791 3710",
    "sg:postcode": "45236",
    "sg:province": "OH",
    "sg:tags": [
      "interior",
      "consultant",
      "design",
      "decorator"
    ],
    "wof:name": "Rowe Show Place",
    "wof:placetype": "venue"
  },
  "geometry": {"coordinates":[-84.368748,39.204135],"type":"Point"}
}
