{
  "type": "Feature",
  "properties": {
    "addr:full": "7967 W Chester Rd West Chester OH 45069",
    "addr:housenumber": "7967",
    "addr:postcode": "45069",
    "addr:street": "W Chester Rd",
    "iso:country": "US",
    "sg:address": "7967 W Chester Rd",
    "sg:city": "West Chester",
    "sg:classifiers": [
      {
        "category": "Wholesale",
        "subcategory": "Machinery \u0026 Supplies",
        "type": "Manufacturing \u0026 Wholesale Goods"
      }
    ],
    "sg:phone": "+1 513 290 4042",
    "sg:postcode": "45069",
    "sg:province": "OH",
    "sg:tags": [
      "salon",
      "beauty"
    ],
    "wof:name": "Sals Beauty Care \u0026 Accessories",
    "wof:placetype": "venue"
  },
  "geometry": {"coordinates":[-84.362787,39.317742],"type":"Point"}
}
