{
  "type": "Feature",
  "properties": {
    "iso:country":"US",
    "sg:address":"222 S Union St",
    "sg:city":"Lima",
    "sg:classifiers":[
        {
            "category":"Building & Trades",
            "subcategory":"Cleaning & Sanitation",
            "type":"Services"
        }
    ],
    "sg:phone":"+1 419 224 5841",
    "sg:postcode":"45801",
    "sg:province":"OH",
    "sg:tags":[
        "window"
    ],
    "wof:name":"Clear View Window Cleaning",
    "wof:placetype":"venue"
},
  "geometry": {"coordinates":[-84.10324900000001,40.738584],"type":"Point"}
}