{
  "type": "Feature",
  "properties": {
    "addr:full": "222 S Union St Lima OH 45801",
    "addr:housenumber": "222",
    "addr:postcode": "45801",
    "addr:street": "S Union St",
    "iso:country": "US",
    "sg:address": "222 S Union St",
    "sg:city": "Lima",
    "sg:classifiers": [
      {
        "category": "Building \u0026 Trades",
        "subcategory": "Cleaning \u0026 Sanitation",
        "type": "Services"
      }
    ],
    "sg:phone": "+1 419 224 5841",
    "sg:postcode": "45801",
    "sg:province": "OH",
    "sg:tags": [
      "window"
    ],
    "wof:name": "Clear View Window Cleaning",
    "wof:placetype": "venue"
  },
  "geometry": {"coordinates":[-84.103249,40.738584],"type":"Point"}
}
