{
  "type": "Feature",
  "properties": {
    "iso:country":"US",
    "sg:address":"1825 Pleasantview Dr NE",
    "sg:city":"Lancaster",
    "sg:classifiers":[
        {
            "category":"Banks & Credit Unions",
            "subcategory":"Financial Services",
            "type":"Services"
        }
    ],
    "sg:phone":"+1 740 687 4446",
    "sg:postcode":"43130",
    "sg:province":"OH",
    "sg:tags":[
        "investor"
    ],
    "wof:name":"Overlook Quarry LLC",
    "wof:placetype":"venue"
},
  "geometry": {"coordinates":[-82.579787,39.752054],"type":"Point"}
}