{
  "type": "Feature",
  "properties": {
    "addr:full":"112 2nd St SW Carrollton OH 44615",
    "addr:housenumber":"112",
    "addr:postcode":"44615",
    "addr:street":"2Nd St Sw",
    "iso:country":"US",
    "sg:address":"112 2nd St SW",
    "sg:city":"Carrollton",
    "sg:classifiers":[
        {
            "category":"Home & Garden",
            "subcategory":"Building Materials",
            "type":"Retail Goods"
        }
    ],
    "sg:phone":"+1 330 627 6776",
    "sg:postcode":"44615",
    "sg:province":"OH",
    "sg:tags":[
        "door"
    ],
    "wof:name":"Wayne Garage Door & Svc Inc",
    "wof:placetype":"venue"
},
  "geometry": {"coordinates":[-81.08833799999999,40.572915],"type":"Point"}
}