{
  "type": "Feature",
  "properties": {
    "addr:full": "7590 Mentor Ave Mentor OH 44060",
    "addr:housenumber": "7590",
    "addr:postcode": "44060",
    "addr:street": "Mentor Ave",
    "iso:country": "US",
    "sg:address": "7590 Mentor Ave",
    "sg:city": "Mentor",
    "sg:classifiers": [
      {
        "category": "Home \u0026 Garden",
        "subcategory": "Furniture",
        "type": "Retail Goods"
      }
    ],
    "sg:phone": "+1 440 946 8400",
    "sg:postcode": "44060",
    "sg:province": "OH",
    "wof:name": "Kronheims Furniture Inc",
    "wof:placetype": "venue"
  },
  "geometry": {"coordinates":[-81.369654,41.657333],"type":"Point"}
}
