{
  "type": "Feature",
  "properties": {
    "iso:country":"US",
    "sg:address":"7590 Mentor Ave",
    "sg:city":"Mentor",
    "sg:classifiers":[
        {
            "category":"Home & Garden",
            "subcategory":"Furniture",
            "type":"Retail Goods"
        }
    ],
    "sg:phone":"+1 440 946 8400",
    "sg:postcode":"44060",
    "sg:province":"OH",
    "wof:name":"Kronheims Furniture Inc",
    "wof:placetype":"venue"
},
  "geometry": {"coordinates":[-81.369654,41.657333],"type":"Point"}
}