{
  "type": "Feature",
  "properties": {
    "addr:full":"821 Junction Ave Toledo OH 43607",
    "addr:housenumber":"821",
    "addr:postcode":"43607",
    "addr:street":"Junction Ave",
    "iso:country":"US",
    "sg:address":"821 Junction Ave",
    "sg:city":"Toledo",
    "sg:classifiers":[
        {
            "category":"Organizations",
            "subcategory":"Religious Organization",
            "type":"Services"
        }
    ],
    "sg:phone":"+1 419 244 6096",
    "sg:postcode":"43607",
    "sg:province":"OH",
    "sg:tags":[
        "church"
    ],
    "wof:name":"Central Baptist Missionary Chr",
    "wof:placetype":"venue"
},
  "geometry": {"coordinates":[-83.57724899999999,41.649057],"type":"Point"}
}