{
  "type": "Feature",
  "properties": {
    "addr:full": "1267 S Norwalk Rd W Norwalk OH 44857",
    "addr:housenumber": "1267",
    "addr:postcode": "44857",
    "addr:street": "S Norwalk Rd W",
    "iso:country": "US",
    "sg:address": "1267 S Norwalk Rd W",
    "sg:city": "Norwalk",
    "sg:classifiers": [
      {
        "category": "Building \u0026 Trades",
        "subcategory": "Construction",
        "type": "Services"
      }
    ],
    "sg:phone": "+1 419 663 2581",
    "sg:postcode": "44857",
    "sg:province": "OH",
    "sg:tags": [
      "excavation",
      "contractor"
    ],
    "wof:name": "Robin Schaffer",
    "wof:placetype": "venue"
  },
  "geometry": {"coordinates":[-82.634656,41.225597],"type":"Point"}
}
