{
  "type": "Feature",
  "properties": {
    "addr:full":"206 W Chicago St Eaton OH 45320",
    "addr:housenumber":"206",
    "addr:postcode":"45320",
    "addr:street":"W Chicago St",
    "iso:country":"US",
    "sg:address":"206 W Chicago St",
    "sg:city":"Eaton",
    "sg:classifiers":[
        {
            "category":"Shopping",
            "subcategory":"Hobbies, Toys, & Games",
            "type":"Retail Goods"
        }
    ],
    "sg:phone":"+1 937 456 2870",
    "sg:postcode":"45320",
    "sg:province":"OH",
    "wof:name":"Reynolds Brionne",
    "wof:placetype":"venue"
},
  "geometry": {"coordinates":[-84.63829699999999,39.75447],"type":"Point"}
}