{
  "type": "Feature",
  "properties": {
    "iso:country":"US",
    "sg:address":"1 Clark Pl",
    "sg:city":"Columbus",
    "sg:classifiers":[
        {
            "category":"Manufacturing",
            "subcategory":"Retail Goods",
            "type":"Manufacturing & Wholesale Goods"
        }
    ],
    "sg:phone":"+1 614 299 5226",
    "sg:postcode":"43201",
    "sg:province":"OH",
    "sg:tags":[
        "product",
        "mfg"
    ],
    "wof:name":"Upperman Industries",
    "wof:placetype":"venue"
},
  "geometry": {"coordinates":[-83.00681299999999,39.98917],"type":"Point"}
}