{
  "type": "Feature",
  "properties": {
    "addr:full":"512 High St Batavia OH 45101",
    "addr:housenumber":"512",
    "addr:postcode":"45101",
    "addr:street":"High St",
    "iso:country":"US",
    "sg:address":"512 High St",
    "sg:city":"Batavia",
    "sg:classifiers":[
        {
            "category":"Social Services",
            "type":"Services"
        }
    ],
    "sg:phone":"+1 513 947 7000",
    "sg:postcode":"45101",
    "sg:province":"OH",
    "sg:tags":[
        "executive",
        "specialty",
        "o"
    ],
    "wof:name":"Clermont Counseling Center",
    "wof:placetype":"venue"
},
  "geometry": {"coordinates":[-83.75510800000001,38.652078],"type":"Point"}
}