{
  "type": "Feature",
  "properties": {
    "addr:full":"1365 US Hwy 42 NE London OH 43140",
    "addr:housenumber":"1365",
    "addr:postcode":"43140",
    "addr:street":"Us Hwy 42 Ne",
    "iso:country":"US",
    "sg:address":"1365 US Hwy 42 NE",
    "sg:city":"London",
    "sg:classifiers":[
        {
            "category":"Restaurant",
            "type":"Food & Drink"
        }
    ],
    "sg:phone":"+1 614 879 5997",
    "sg:postcode":"43140",
    "sg:province":"OH",
    "wof:name":"TJ Cinnamons",
    "wof:placetype":"venue"
},
  "geometry": {"coordinates":[-83.36274299999999,39.966189],"type":"Point"}
}