{
  "type": "Feature",
  "properties": {
    "iso:country":"US",
    "sg:address":"212 S Glenwood Ave",
    "sg:city":"Columbus",
    "sg:classifiers":[
        {
            "category":"Autos & Motor Vehicles",
            "subcategory":"Boat Sales",
            "type":"Retail Goods"
        },
        {
            "category":"Retail",
            "subcategory":"Repair Shop",
            "type":"Services"
        },
        {
            "category":"Wholesale",
            "subcategory":"Machinery & Supplies",
            "type":"Manufacturing & Wholesale Goods"
        },
        {
            "category":"Autos & Motor Vehicles",
            "subcategory":"Auto Supplies",
            "type":"Retail Goods"
        },
        {
            "category":"Retail",
            "subcategory":"Auto Repair",
            "type":"Services"
        }
    ],
    "sg:phone":"+1 614 221 4750",
    "sg:postcode":"43223",
    "sg:province":"OH",
    "sg:tags":[
        "upholstery",
        "upholsterer",
        "classic",
        "automobile",
        "top",
        "covers",
        "seat",
        "restoration-antique"
    ],
    "sg:website":"http://www.jandjautoupholstery.com",
    "wof:name":"J & J Auto Upholstery Inc",
    "wof:placetype":"venue"
},
  "geometry": {"coordinates":[-83.029546,39.954213],"type":"Point"}
}