{
  "type": "Feature",
  "properties": {
    "addr:full": "212 S Glenwood Ave Columbus OH 43223",
    "addr:housenumber": "212",
    "addr:postcode": "43223",
    "addr:street": "S Glenwood Ave",
    "iso:country": "US",
    "sg:address": "212 S Glenwood Ave",
    "sg:city": "Columbus",
    "sg:classifiers": [
      {
        "category": "Autos \u0026 Motor Vehicles",
        "subcategory": "Boat Sales",
        "type": "Retail Goods"
      },
      {
        "category": "Retail",
        "subcategory": "Repair Shop",
        "type": "Services"
      },
      {
        "category": "Wholesale",
        "subcategory": "Machinery \u0026 Supplies",
        "type": "Manufacturing \u0026 Wholesale Goods"
      },
      {
        "category": "Autos \u0026 Motor Vehicles",
        "subcategory": "Auto Supplies",
        "type": "Retail Goods"
      },
      {
        "category": "Retail",
        "subcategory": "Auto Repair",
        "type": "Services"
      }
    ],
    "sg:phone": "+1 614 221 4750",
    "sg:postcode": "43223",
    "sg:province": "OH",
    "sg:tags": [
      "upholstery",
      "upholsterer",
      "classic",
      "automobile",
      "top",
      "covers",
      "seat",
      "restoration-antique"
    ],
    "sg:website": "http://www.jandjautoupholstery.com",
    "wof:name": "J \u0026 J Auto Upholstery Inc",
    "wof:placetype": "venue"
  },
  "geometry": {"coordinates":[-83.029546,39.954213],"type":"Point"}
}
