{
  "type": "Feature",
  "properties": {
    "addr:full":"11197 Wolf Ave NE Hartville OH 44632",
    "addr:housenumber":"11197",
    "addr:postcode":"44632",
    "addr:street":"Wolf Ave Ne",
    "iso:country":"US",
    "sg:address":"11197 Wolf Ave NE",
    "sg:city":"Hartville",
    "sg:classifiers":[
        {
            "category":"Building & Trades",
            "subcategory":"Construction",
            "type":"Services"
        }
    ],
    "sg:phone":"+1 330 877 3009",
    "sg:postcode":"44632",
    "sg:province":"OH",
    "sg:tags":[
        "home",
        "builder"
    ],
    "wof:name":"Millennium Homes",
    "wof:placetype":"venue"
},
  "geometry": {"coordinates":[-81.310327,40.926532],"type":"Point"}
}