{
  "type": "Feature",
  "properties": {
    "addr:full": "320 Benton Rd Salem OH 44460",
    "addr:housenumber": "320",
    "addr:postcode": "44460",
    "addr:street": "Benton Rd",
    "iso:country": "US",
    "sg:address": "320 Benton Rd",
    "sg:city": "Salem",
    "sg:classifiers": [
      {
        "category": "Organizations",
        "subcategory": "Non-profit Organization",
        "type": "Services"
      }
    ],
    "sg:phone": "+1 330 337 7501",
    "sg:postcode": "44460",
    "sg:province": "OH",
    "sg:tags": [
      "information",
      "alcoholism",
      "treatment"
    ],
    "wof:name": "Oxford House",
    "wof:placetype": "venue"
  },
  "geometry": {"coordinates":[-80.872798,40.903313],"type":"Point"}
}
