{
  "type": "Feature",
  "properties": {
    "addr:full": "8043 Ohio River Rd Wheelersburg OH 45694",
    "addr:housenumber": "8043",
    "addr:postcode": "45694",
    "addr:street": "Ohio River Rd",
    "iso:country": "US",
    "sg:address": "8043 Ohio River Rd",
    "sg:city": "Wheelersburg",
    "sg:classifiers": [
      {
        "category": "Restaurant",
        "type": "Food \u0026 Drink"
      }
    ],
    "sg:phone": "+1 740 574 6024",
    "sg:postcode": "45694",
    "sg:province": "OH",
    "wof:name": "Pop's Drive-Inn \u0026 Restaurant",
    "wof:placetype": "venue"
  },
  "geometry": {"coordinates":[-82.859646,38.731713],"type":"Point"}
}
