{
  "type": "Feature",
  "properties": {
    "addr:full": "12079 Greenwich Rd Homerville OH 44235",
    "addr:housenumber": "12079",
    "addr:postcode": "44235",
    "addr:street": "Greenwich Rd",
    "iso:country": "US",
    "sg:address": "12079 Greenwich Rd",
    "sg:city": "Homerville",
    "sg:classifiers": [
      {
        "category": "Government",
        "subcategory": "Post Office",
        "type": "Public Place"
      }
    ],
    "sg:phone": "+1 330 625 2043",
    "sg:postcode": "44235",
    "sg:province": "OH",
    "wof:name": "US Post Office",
    "wof:placetype": "venue"
  },
  "geometry": {"coordinates":[-82.108014,41.027],"type":"Point"}
}
