{
  "type": "Feature",
  "properties": {
    "addr:full":"16101 Elberta Ave Cleveland OH 44128",
    "addr:housenumber":"16101",
    "addr:postcode":"44128",
    "addr:street":"Elberta Ave",
    "iso:country":"US",
    "sg:address":"16101 Elberta Ave",
    "sg:city":"Cleveland",
    "sg:classifiers":[
        {
            "category":"Building & Trades",
            "subcategory":"Landscaping Services",
            "type":"Services"
        }
    ],
    "sg:phone":"+1 216 662 0059",
    "sg:postcode":"44128",
    "sg:province":"OH",
    "sg:tags":[
        "tree"
    ],
    "wof:name":"A A Tree Stump Removal",
    "wof:placetype":"venue"
},
  "geometry": {"coordinates":[-81.568978,41.434261],"type":"Point"}
}