{
  "type": "Feature",
  "properties": {
    "addr:full": "263 Liberty St Painesville OH 44077",
    "addr:housenumber": "263",
    "addr:postcode": "44077",
    "addr:street": "Liberty St",
    "iso:country": "US",
    "sg:address": "263 Liberty St",
    "sg:city": "Painesville",
    "sg:classifiers": [
      {
        "category": "Recreation",
        "type": "Entertainment"
      }
    ],
    "sg:phone": "+1 440 354 6042",
    "sg:postcode": "44077",
    "sg:province": "OH",
    "sg:tags": [
      "martial",
      "arts",
      "instruction"
    ],
    "wof:name": "Davis School Of Self Defense",
    "wof:placetype": "venue"
  },
  "geometry": {"coordinates":[-81.241766,41.718734],"type":"Point"}
}
