{
  "type": "Feature",
  "properties": {
    "addr:full": "4056 Mount Carmel Tobasco Rd Cincinnati OH 45255",
    "addr:housenumber": "4056",
    "addr:postcode": "45255",
    "addr:street": "Mount Carmel Tobasco Rd",
    "iso:country": "US",
    "sg:address": "4056 Mount Carmel Tobasco Rd",
    "sg:city": "Cincinnati",
    "sg:classifiers": [
      {
        "category": "Travel",
        "subcategory": "Hotels \u0026 Motels",
        "type": "Entertainment"
      }
    ],
    "sg:phone": "+1 513 528 3800",
    "sg:postcode": "45255",
    "sg:province": "OH",
    "wof:name": "Days Inn",
    "wof:placetype": "venue"
  },
  "geometry": {"coordinates":[-84.297966,39.075517],"type":"Point"}
}
