{
  "type": "Feature",
  "properties": {
    "iso:country":"US",
    "sg:address":"12456 Monkey Hollow Rd",
    "sg:city":"Sunbury",
    "sg:classifiers":[
        {
            "category":"Health Services",
            "subcategory":"Medical Lab",
            "type":"Services"
        }
    ],
    "sg:phone":"+1 740 965 1598",
    "sg:postcode":"43074",
    "sg:province":"OH",
    "sg:tags":[
        "laboratory",
        "dental"
    ],
    "wof:name":"Roderer Dental Lab Inc",
    "wof:placetype":"venue"
},
  "geometry": {"coordinates":[-82.844876,40.295766],"type":"Point"}
}