{
  "type": "Feature",
  "properties": {
    "iso:country":"US",
    "sg:address":"78 W Washington St",
    "sg:city":"Jamestown",
    "sg:classifiers":[
        {
            "category":"Real Estate",
            "subcategory":"Real Estate Operator",
            "type":"Services"
        }
    ],
    "sg:phone":"+1 937 675 3861",
    "sg:postcode":"45335",
    "sg:province":"OH",
    "sg:tags":[
        "apartment"
    ],
    "wof:name":"Jamestown Place",
    "wof:placetype":"venue"
},
  "geometry": {"coordinates":[-83.740555,39.658448],"type":"Point"}
}