{
  "type": "Feature",
  "properties": {
    "addr:full":"967 E McMillan St Cincinnati OH 45206",
    "addr:housenumber":"967",
    "addr:postcode":"45206",
    "addr:street":"E Mcmillan St",
    "iso:country":"US",
    "sg:address":"967 E McMillan St",
    "sg:city":"Cincinnati",
    "sg:classifiers":[
        {
            "category":"Freight",
            "type":"Transportation"
        }
    ],
    "sg:phone":"+1 513 961 1133",
    "sg:postcode":"45206",
    "sg:province":"OH",
    "sg:tags":[
        "mover"
    ],
    "wof:name":"A-1 Ace Moving & Storage",
    "wof:placetype":"venue"
},
  "geometry": {"coordinates":[-84.48923499999999,39.125822],"type":"Point"}
}