{
  "type": "Feature",
  "properties": {
    "addr:full":"11020 Tollgate Rd SW Pataskala OH 43062",
    "addr:housenumber":"11020",
    "addr:postcode":"43062",
    "addr:street":"Tollgate Rd Sw",
    "iso:country":"US",
    "sg:address":"11020 Tollgate Rd SW",
    "sg:city":"Pataskala",
    "sg:classifiers":[
        {
            "category":"Professional",
            "subcategory":"Lawyer & Legal Services",
            "type":"Services"
        }
    ],
    "sg:phone":"+1 740 927 4880",
    "sg:postcode":"43062",
    "sg:province":"OH",
    "sg:tags":[
        "attorney"
    ],
    "wof:name":"Richard E Lord & Assoc",
    "wof:placetype":"venue"
},
  "geometry": {"coordinates":[-82.706597,39.936716],"type":"Point"}
}