{
  "type": "Feature",
  "properties": {
    "addr:full": "27200 Cedar Rd Cleveland OH 44122",
    "addr:housenumber": "27200",
    "addr:postcode": "44122",
    "addr:street": "Cedar Rd",
    "iso:country": "US",
    "sg:address": "27200 Cedar Rd",
    "sg:city": "Cleveland",
    "sg:classifiers": [
      {
        "category": "Personal",
        "subcategory": "Beauty Salon",
        "type": "Services"
      }
    ],
    "sg:phone": "+1 216 831 3745",
    "sg:postcode": "44122",
    "sg:province": "OH",
    "wof:name": "High Rollers",
    "wof:placetype": "venue"
  },
  "geometry": {"coordinates":[-81.489504,41.501094],"type":"Point"}
}
