{
  "type": "Feature",
  "properties": {
    "addr:full":"4993 Twp Hwy 55 Upper Sandusky OH 43351",
    "addr:postcode":"4993;43351",
    "addr:street":"Twp Hwy 55",
    "iso:country":"US",
    "sg:address":"4993 Twp Hwy 55",
    "sg:city":"Upper Sandusky",
    "sg:classifiers":[
        {
            "category":"Mining & Drilling",
            "type":"Manufacturing & Wholesale Goods"
        }
    ],
    "sg:phone":"+1 419 294 8527",
    "sg:postcode":"43351",
    "sg:province":"OH",
    "sg:tags":[
        "limestone"
    ],
    "wof:name":"Micwin",
    "wof:placetype":"venue"
},
  "geometry": {"coordinates":[-83.210083,40.814587],"type":"Point"}
}