{
  "type": "Feature",
  "properties": {
    "iso:country":"US",
    "sg:address":"112 Swan St",
    "sg:city":"Geneva",
    "sg:classifiers":[
        {
            "category":"Professional",
            "type":"Services"
        }
    ],
    "sg:phone":"+1 440 466 0915",
    "sg:postcode":"44041",
    "sg:province":"OH",
    "wof:name":"Lisa Moroski",
    "wof:placetype":"venue"
},
  "geometry": {"coordinates":[-80.95198000000001,41.802013],"type":"Point"}
}