{
  "type": "Feature",
  "properties": {
    "addr:full": "319 Industrial Pkwy Sandusky OH 44870",
    "addr:housenumber": "319",
    "addr:postcode": "44870",
    "addr:street": "Industrial Pkwy",
    "iso:country": "US",
    "sg:address": "319 Industrial Pkwy",
    "sg:city": "Sandusky",
    "sg:classifiers": [
      {
        "category": "Retail",
        "subcategory": "Laundry \u0026 Dry Cleaning",
        "type": "Services"
      }
    ],
    "sg:phone": "+1 419 624 0198",
    "sg:postcode": "44870",
    "sg:province": "OH",
    "sg:tags": [
      "cleaners",
      "rug",
      "carpet"
    ],
    "wof:name": "Restorepro",
    "wof:placetype": "venue"
  },
  "geometry": {"coordinates":[-82.684031,41.402192],"type":"Point"}
}
