{
  "type": "Feature",
  "properties": {
    "addr:full":"969 N Court St Medina OH 44256",
    "addr:housenumber":"969",
    "addr:postcode":"44256",
    "addr:street":"N Court St",
    "iso:country":"US",
    "sg:address":"969 N Court St",
    "sg:city":"Medina",
    "sg:classifiers":[
        {
            "category":"Retail",
            "subcategory":"Car Wash",
            "type":"Services"
        }
    ],
    "sg:phone":"+1 330 722 0221",
    "sg:postcode":"44256",
    "sg:province":"OH",
    "sg:tags":[
        "polishing",
        "washing"
    ],
    "wof:name":"Ultimate Wash",
    "wof:placetype":"venue"
},
  "geometry": {"coordinates":[-81.86330700000001,41.151364],"type":"Point"}
}