{
  "type": "Feature",
  "properties": {
    "addr:full": "1838 Arlington Ave Columbus OH 43212",
    "addr:housenumber": "1838",
    "addr:postcode": "43212",
    "addr:street": "Arlington Ave",
    "iso:country": "US",
    "sg:address": "1838 Arlington Ave",
    "sg:city": "Columbus",
    "sg:classifiers": [
      {
        "category": "Social Services",
        "subcategory": "Child Care",
        "type": "Services"
      }
    ],
    "sg:phone": "+1 614 337 1664",
    "sg:postcode": "43212",
    "sg:province": "OH",
    "wof:name": "Candice's Day Care",
    "wof:placetype": "venue"
  },
  "geometry": {"coordinates":[-83.060355,39.992557],"type":"Point"}
}
