{
  "type": "Feature",
  "properties": {
    "addr:full": "2855 N Ridge Rd E Ashtabula OH 44004",
    "addr:housenumber": "2855",
    "addr:postcode": "44004",
    "addr:street": "N Ridge Rd E",
    "iso:country": "US",
    "sg:address": "2855 N Ridge Rd E",
    "sg:city": "Ashtabula",
    "sg:classifiers": [
      {
        "category": "Banks \u0026 Credit Unions",
        "subcategory": "Investment Brokerage",
        "type": "Services"
      },
      {
        "category": "Banks \u0026 Credit Unions",
        "subcategory": "Bank",
        "type": "Services"
      }
    ],
    "sg:phone": "+1 440 998 1024",
    "sg:postcode": "44004",
    "sg:province": "OH",
    "sg:tags": [
      "advisory",
      "financing",
      "financial"
    ],
    "wof:name": "Citi Financial",
    "wof:placetype": "venue"
  },
  "geometry": {"coordinates":[-80.758962,41.876745],"type":"Point"}
}
