{
  "type": "Feature",
  "properties": {
    "addr:full": "1120 By-The-Shores Dr Huron OH 44839",
    "addr:housenumber": "1120",
    "addr:postcode": "44839",
    "addr:street": "By-The-Shores Dr",
    "iso:country": "US",
    "sg:address": "1120 By-The-Shores Dr",
    "sg:city": "Huron",
    "sg:classifiers": [
      {
        "category": "Autos \u0026 Motor Vehicles",
        "subcategory": "Automobile Sales",
        "type": "Retail Goods"
      }
    ],
    "sg:phone": "+1 419 433 8280",
    "sg:postcode": "44839",
    "sg:province": "OH",
    "sg:tags": [
      "car",
      "dealer"
    ],
    "wof:name": "State Auto Welsh",
    "wof:placetype": "venue"
  },
  "geometry": {"coordinates":[-82.527023,41.387914],"type":"Point"}
}
