{
  "type": "Feature",
  "properties": {
    "addr:full": "3082 Sandywood Dr Dayton OH 45440",
    "addr:housenumber": "3082",
    "addr:postcode": "45440",
    "addr:street": "Sandywood Dr",
    "iso:country": "US",
    "sg:address": "3082 Sandywood Dr",
    "sg:city": "Dayton",
    "sg:classifiers": [
      {
        "category": "Real Estate",
        "subcategory": "Real Estate Agent",
        "type": "Services"
      }
    ],
    "sg:phone": "+1 937 299 1056",
    "sg:postcode": "45440",
    "sg:province": "OH",
    "sg:tags": [
      "appraiser"
    ],
    "wof:name": "Equity Appraisal Associates",
    "wof:placetype": "venue"
  },
  "geometry": {"coordinates":[-84.108283,39.676993],"type":"Point"}
}
