{
  "type": "Feature",
  "properties": {
    "addr:full": "50 Stonybrook Dr Georgetown OH 45121",
    "addr:housenumber": "50",
    "addr:postcode": "45121",
    "addr:street": "Stonybrook Dr",
    "iso:country": "US",
    "sg:address": "50 Stonybrook Dr",
    "sg:city": "Georgetown",
    "sg:classifiers": [
      {
        "category": "Wholesale",
        "subcategory": "Drugs",
        "type": "Manufacturing \u0026 Wholesale Goods"
      }
    ],
    "sg:phone": "+1 937 378 3243",
    "sg:postcode": "45121",
    "sg:province": "OH",
    "sg:tags": [
      "pharmaceutical",
      "product"
    ],
    "wof:name": "Top RX",
    "wof:placetype": "venue"
  },
  "geometry": {"coordinates":[-83.905547,38.844797],"type":"Point"}
}
