{
  "type": "Feature",
  "properties": {
    "iso:country":"US",
    "sg:address":"50 Stonybrook Dr",
    "sg:city":"Georgetown",
    "sg:classifiers":[
        {
            "category":"Wholesale",
            "subcategory":"Drugs",
            "type":"Manufacturing & Wholesale Goods"
        }
    ],
    "sg:phone":"+1 937 378 3243",
    "sg:postcode":"45121",
    "sg:province":"OH",
    "sg:tags":[
        "pharmaceutical",
        "product"
    ],
    "wof:name":"Top RX",
    "wof:placetype":"venue"
},
  "geometry": {"coordinates":[-83.905547,38.844797],"type":"Point"}
}