{
  "type": "Feature",
  "properties": {
    "iso:country":"US",
    "sg:address":"4640 Oberlin Ave",
    "sg:city":"Lorain",
    "sg:classifiers":[
        {
            "category":"Real Estate",
            "subcategory":"Real Estate Operator",
            "type":"Services"
        }
    ],
    "sg:phone":"+1 440 282 6103",
    "sg:postcode":"44053",
    "sg:province":"OH",
    "sg:tags":[
        "building",
        "apartment"
    ],
    "wof:name":"Property Technician Inc",
    "wof:placetype":"venue"
},
  "geometry": {"coordinates":[-82.185486,41.427773],"type":"Point"}
}