{
  "type": "Feature",
  "properties": {
    "iso:country":"US",
    "sg:address":"3526 Lenox Dr",
    "sg:city":"Dayton",
    "sg:classifiers":[
        {
            "category":"Wholesale",
            "subcategory":"Sporting Goods",
            "type":"Manufacturing & Wholesale Goods"
        }
    ],
    "sg:phone":"+1 937 643 1165",
    "sg:postcode":"45429",
    "sg:province":"OH",
    "sg:tags":[
        "equipment",
        "fitness",
        "supply"
    ],
    "wof:name":"Commercial Fitness Solutions",
    "wof:placetype":"venue"
},
  "geometry": {"coordinates":[-84.172845,39.694881],"type":"Point"}
}