{
  "type": "Feature",
  "properties": {
    "addr:full": "3526 Lenox Dr Dayton OH 45429",
    "addr:housenumber": "3526",
    "addr:postcode": "45429",
    "addr:street": "Lenox Dr",
    "iso:country": "US",
    "sg:address": "3526 Lenox Dr",
    "sg:city": "Dayton",
    "sg:classifiers": [
      {
        "category": "Wholesale",
        "subcategory": "Sporting Goods",
        "type": "Manufacturing \u0026 Wholesale Goods"
      }
    ],
    "sg:phone": "+1 937 643 1165",
    "sg:postcode": "45429",
    "sg:province": "OH",
    "sg:tags": [
      "equipment",
      "fitness",
      "supply"
    ],
    "wof:name": "Commercial Fitness Solutions",
    "wof:placetype": "venue"
  },
  "geometry": {"coordinates":[-84.172845,39.694881],"type":"Point"}
}
