{
  "type": "Feature",
  "properties": {
    "iso:country":"US",
    "sg:address":"343 N Front St",
    "sg:city":"Columbus",
    "sg:classifiers":[
        {
            "category":"Professional",
            "subcategory":"Computer Services",
            "type":"Services"
        }
    ],
    "sg:phone":"+1 614 827 7000",
    "sg:postcode":"43215",
    "sg:province":"OH",
    "sg:tags":[
        "internet",
        "provider"
    ],
    "wof:name":"Citynet Ohio LLC",
    "wof:placetype":"venue"
},
  "geometry": {"coordinates":[-83.003968,39.969657],"type":"Point"}
}