{
  "type": "Feature",
  "properties": {
    "iso:country":"US",
    "sg:address":"2417 Carlyle St NW",
    "sg:city":"Massillon",
    "sg:classifiers":[
        {
            "category":"Building & Trades",
            "subcategory":"Construction",
            "type":"Services"
        }
    ],
    "sg:phone":"+1 330 495 6217",
    "sg:postcode":"44646",
    "sg:province":"OH",
    "sg:tags":[
        "painter"
    ],
    "wof:name":"Priest Painting & Decorating",
    "wof:placetype":"venue"
},
  "geometry": {"coordinates":[-81.48518,40.817037],"type":"Point"}
}