{
  "type": "Feature",
  "properties": {
    "addr:full":"6535 Hearthstone Ave Columbus OH 43229",
    "addr:housenumber":"6535",
    "addr:postcode":"43229",
    "addr:street":"Hearthstone Ave",
    "iso:country":"US",
    "sg:address":"6535 Hearthstone Ave",
    "sg:city":"Columbus",
    "sg:classifiers":[
        {
            "category":"Building & Trades",
            "subcategory":"Construction",
            "type":"Services"
        }
    ],
    "sg:phone":"+1 614 890 1399",
    "sg:postcode":"43229",
    "sg:province":"OH",
    "sg:tags":[
        "contractor"
    ],
    "wof:name":"Aaron & Aaron Roofing",
    "wof:placetype":"venue"
},
  "geometry": {"coordinates":[-82.964702,40.101399],"type":"Point"}
}