{
  "type": "Feature",
  "properties": {
    "iso:country":"US",
    "sg:address":"308 E Main St",
    "sg:city":"Carrollton",
    "sg:classifiers":[
        {
            "category":"Manufacturing",
            "subcategory":"Tools & Machinery",
            "type":"Manufacturing & Wholesale Goods"
        }
    ],
    "sg:phone":"+1 330 627 1700",
    "sg:postcode":"44615",
    "sg:province":"OH",
    "sg:tags":[
        "machine",
        "shop"
    ],
    "wof:name":"Red Line Automotive Machine Sp",
    "wof:placetype":"venue"
},
  "geometry": {"coordinates":[-81.081965,40.570575],"type":"Point"}
}