{
  "type": "Feature",
  "properties": {
    "addr:full": "2945 Erich Dr Wickliffe OH 44092",
    "addr:housenumber": "2945",
    "addr:postcode": "44092",
    "addr:street": "Erich Dr",
    "iso:country": "US",
    "sg:address": "2945 Erich Dr",
    "sg:city": "Wickliffe",
    "sg:classifiers": [
      {
        "category": "Building \u0026 Trades",
        "subcategory": "Construction",
        "type": "Services"
      }
    ],
    "sg:phone": "+1 440 585 2731",
    "sg:postcode": "44092",
    "sg:province": "OH",
    "sg:tags": [
      "house"
    ],
    "wof:name": "Frank Conti Construction Inc",
    "wof:placetype": "venue"
  },
  "geometry": {"coordinates":[-81.463522,41.574774],"type":"Point"}
}
