{
  "type": "Feature",
  "properties": {
    "iso:country":"US",
    "sg:address":"2945 Erich Dr",
    "sg:city":"Wickliffe",
    "sg:classifiers":[
        {
            "category":"Building & Trades",
            "subcategory":"Construction",
            "type":"Services"
        }
    ],
    "sg:phone":"+1 440 585 2731",
    "sg:postcode":"44092",
    "sg:province":"OH",
    "sg:tags":[
        "house"
    ],
    "wof:name":"Frank Conti Construction Inc",
    "wof:placetype":"venue"
},
  "geometry": {"coordinates":[-81.463522,41.574774],"type":"Point"}
}