{
  "type": "Feature",
  "properties": {
    "iso:country":"US",
    "sg:address":"6551 Wales Rd",
    "sg:city":"Northwood",
    "sg:classifiers":[
        {
            "category":"Professional",
            "subcategory":"Advertising",
            "type":"Services"
        }
    ],
    "sg:phone":"+1 419 693 5000",
    "sg:postcode":"43619",
    "sg:province":"OH",
    "sg:tags":[
        "distribution"
    ],
    "wof:name":"Hall Industrial Co",
    "wof:placetype":"venue"
},
  "geometry": {"coordinates":[-83.50618900000001,41.608516],"type":"Point"}
}