{
  "type": "Feature",
  "properties": {
    "addr:full": "21640 Edgecliff Dr Euclid OH 44123",
    "addr:postcode": "21640;44123",
    "addr:street": "Edgecliff Dr",
    "iso:country": "US",
    "sg:address": "21640 Edgecliff Dr",
    "sg:city": "Euclid",
    "sg:classifiers": [
      {
        "category": "Restaurant",
        "type": "Food \u0026 Drink"
      }
    ],
    "sg:phone": "+1 216 830 3287",
    "sg:postcode": "44123",
    "sg:province": "OH",
    "sg:tags": [
      "eating"
    ],
    "wof:name": "Cole \u0026 Wong",
    "wof:placetype": "venue"
  },
  "geometry": {"coordinates":[-81.533165,41.611129],"type":"Point"}
}
