{
  "type": "Feature",
  "properties": {
    "iso:country":"US",
    "sg:address":"21640 Edgecliff Dr",
    "sg:city":"Euclid",
    "sg:classifiers":[
        {
            "category":"Restaurant",
            "type":"Food & Drink"
        }
    ],
    "sg:phone":"+1 216 830 3287",
    "sg:postcode":"44123",
    "sg:province":"OH",
    "sg:tags":[
        "eating"
    ],
    "wof:name":"Cole & Wong",
    "wof:placetype":"venue"
},
  "geometry": {"coordinates":[-81.533165,41.611129],"type":"Point"}
}