{
  "type": "Feature",
  "properties": {
    "addr:full":"1085 Dearborn Dr Worthington OH 43085",
    "addr:housenumber":"1085",
    "addr:postcode":"43085",
    "addr:street":"Dearborn Dr",
    "iso:country":"US",
    "sg:address":"1085 Dearborn Dr",
    "sg:city":"Worthington",
    "sg:classifiers":[
        {
            "category":"Manufacturing",
            "subcategory":"Metals",
            "type":"Manufacturing & Wholesale Goods"
        }
    ],
    "sg:phone":"+1 614 438 7900",
    "sg:postcode":"43085",
    "sg:province":"OH",
    "sg:tags":[
        "cylinder"
    ],
    "sg:website":"www.worthingtoncylinders.com",
    "wof:name":"Worthington Cylinder Corp",
    "wof:placetype":"venue"
},
  "geometry": {"coordinates":[-82.992435,40.114263],"type":"Point"}
}