{
  "type": "Feature",
  "properties": {
    "addr:full":"10247 Spinnaker Run Aurora OH 44202",
    "addr:housenumber":"10247",
    "addr:postcode":"44202",
    "addr:street":"Spinnaker Run",
    "iso:country":"US",
    "sg:address":"10247 Spinnaker Run",
    "sg:city":"Aurora",
    "sg:classifiers":[
        {
            "category":"Building & Trades",
            "subcategory":"Landscaping Services",
            "type":"Services"
        }
    ],
    "sg:phone":"+1 330 562 5680",
    "sg:postcode":"44202",
    "sg:province":"OH",
    "sg:tags":[
        "landscape"
    ],
    "wof:name":"George Hrizo",
    "wof:placetype":"venue"
},
  "geometry": {"coordinates":[-81.406324,41.339086],"type":"Point"}
}