{
  "type": "Feature",
  "properties": {
    "addr:full": "236 S Sandusky Ave Bucyrus OH 44820",
    "addr:housenumber": "236",
    "addr:postcode": "44820",
    "addr:street": "S Sandusky Ave",
    "iso:country": "US",
    "sg:address": "236 S Sandusky Ave",
    "sg:city": "Bucyrus",
    "sg:classifiers": [
      {
        "category": "Wholesale",
        "subcategory": "Machinery \u0026 Supplies",
        "type": "Manufacturing \u0026 Wholesale Goods"
      }
    ],
    "sg:phone": "+1 419 563 0090",
    "sg:postcode": "44820",
    "sg:province": "OH",
    "sg:tags": [
      "crane",
      "derrick"
    ],
    "wof:name": "E-Crane Intl Inc",
    "wof:placetype": "venue"
  },
  "geometry": {"coordinates":[-82.975514,40.807185],"type":"Point"}
}
