{
  "type": "Feature",
  "properties": {
    "addr:full": "1850 Jamestown Gunnersville Rd Jamestown OH 45335",
    "addr:housenumber": "1850",
    "addr:postcode": "45335",
    "addr:street": "Jamestown Gunnersville Rd",
    "iso:country": "US",
    "sg:address": "1850 Jamestown Gunnersville Rd",
    "sg:city": "Jamestown",
    "sg:classifiers": [
      {
        "category": "Building \u0026 Trades",
        "subcategory": "Construction",
        "type": "Services"
      }
    ],
    "sg:phone": "+1 937 453 2623",
    "sg:postcode": "45335",
    "sg:province": "OH",
    "sg:tags": [
      "concrete",
      "contractor"
    ],
    "wof:name": "Teynor Concrete Construction",
    "wof:placetype": "venue"
  },
  "geometry": {"coordinates":[-83.735224,39.620673],"type":"Point"}
}
