{
  "type": "Feature",
  "properties": {
    "addr:full": "194 Morgan Ave Elyria OH 44035",
    "addr:housenumber": "194",
    "addr:postcode": "44035",
    "addr:street": "Morgan Ave",
    "iso:country": "US",
    "sg:address": "194 Morgan Ave",
    "sg:city": "Elyria",
    "sg:classifiers": [
      {
        "category": "Manufacturing",
        "subcategory": "Tools \u0026 Machinery",
        "type": "Manufacturing \u0026 Wholesale Goods"
      }
    ],
    "sg:phone": "+1 440 324 6277",
    "sg:postcode": "44035",
    "sg:province": "OH",
    "sg:tags": [
      "shop",
      "mfg",
      "die",
      "machine",
      "job",
      "maker"
    ],
    "wof:name": "Feller Tool Co Inc",
    "wof:placetype": "venue"
  },
  "geometry": {"coordinates":[-82.127553,41.386561],"type":"Point"}
}
