{
  "type": "Feature",
  "properties": {
    "iso:country":"US",
    "sg:address":"194 Morgan Ave",
    "sg:city":"Elyria",
    "sg:classifiers":[
        {
            "category":"Manufacturing",
            "subcategory":"Tools & Machinery",
            "type":"Manufacturing & Wholesale Goods"
        }
    ],
    "sg:phone":"+1 440 324 6277",
    "sg:postcode":"44035",
    "sg:province":"OH",
    "sg:tags":[
        "shop",
        "mfg",
        "die",
        "machine",
        "job",
        "maker"
    ],
    "wof:name":"Feller Tool Co Inc",
    "wof:placetype":"venue"
},
  "geometry": {"coordinates":[-82.12755300000001,41.386561],"type":"Point"}
}