{
  "type": "Feature",
  "properties": {
    "addr:full": "11729 Twp Rd 71A Roseville OH 43777",
    "addr:housenumber": "71a",
    "addr:postcode": "11729;43777",
    "addr:street": "Twp Rd",
    "iso:country": "US",
    "sg:address": "11729 Twp Rd 71A",
    "sg:city": "Roseville",
    "sg:classifiers": [
      {
        "category": "Building \u0026 Trades",
        "subcategory": "Construction",
        "type": "Services"
      }
    ],
    "sg:phone": "+1 740 697 0756",
    "sg:postcode": "43777",
    "sg:province": "OH",
    "sg:tags": [
      "woodworker"
    ],
    "wof:name": "Wiseman's Custom Woodworking",
    "wof:placetype": "venue"
  },
  "geometry": {"coordinates":[-82.096254,39.812319],"type":"Point"}
}
