{
  "type": "Feature",
  "properties": {
    "addr:full": "4902 Golf Ave Geneva OH 44041",
    "addr:housenumber": "4902",
    "addr:postcode": "44041",
    "addr:street": "Golf Ave",
    "iso:country": "US",
    "sg:address": "4902 Golf Ave",
    "sg:city": "Geneva",
    "sg:classifiers": [
      {
        "category": "Sports \u0026 Exercise",
        "subcategory": "Golf",
        "type": "Entertainment"
      }
    ],
    "sg:phone": "+1 440 466 8797",
    "sg:postcode": "44041",
    "sg:province": "OH",
    "sg:tags": [
      "course"
    ],
    "wof:name": "Golf Shop",
    "wof:placetype": "venue"
  },
  "geometry": {"coordinates":[-80.951999,41.858398],"type":"Point"}
}
