{
  "type": "Feature",
  "properties": {
    "iso:country":"US",
    "sg:address":"4902 Golf Ave",
    "sg:city":"Geneva",
    "sg:classifiers":[
        {
            "category":"Sports & Exercise",
            "subcategory":"Golf",
            "type":"Entertainment"
        }
    ],
    "sg:phone":"+1 440 466 8797",
    "sg:postcode":"44041",
    "sg:province":"OH",
    "sg:tags":[
        "course"
    ],
    "wof:name":"Golf Shop",
    "wof:placetype":"venue"
},
  "geometry": {"coordinates":[-80.951999,41.858398],"type":"Point"}
}