{
  "type": "Feature",
  "properties": {
    "addr:full": "4904 N Holland Sylvania Ave Sylvania OH 43623",
    "addr:housenumber": "4904",
    "addr:postcode": "43623",
    "addr:street": "N Holland Sylvania Ave",
    "iso:country": "US",
    "sg:address": "4904 N Holland Sylvania Ave",
    "sg:city": "Sylvania",
    "sg:classifiers": [
      {
        "category": "Real Estate",
        "subcategory": "Real Estate Agent",
        "type": "Services"
      }
    ],
    "sg:phone": "+1 419 885 4475",
    "sg:postcode": "43623",
    "sg:province": "OH",
    "wof:name": "Di Salle Real Estate Co",
    "wof:placetype": "venue"
  },
  "geometry": {"coordinates":[-83.695883,41.703852],"type":"Point"}
}
