{
  "type": "Feature",
  "properties": {
    "addr:full":"1248 High St Fairport Harbor OH 44077",
    "addr:housenumber":"1248",
    "addr:postcode":"44077",
    "addr:street":"High St",
    "iso:country":"US",
    "sg:address":"1248 High St",
    "sg:city":"Fairport Harbor",
    "sg:classifiers":[
        {
            "category":"Personal",
            "subcategory":"Beauty Salon",
            "type":"Services"
        }
    ],
    "sg:phone":"+1 440 357 6996",
    "sg:postcode":"44077",
    "sg:province":"OH",
    "sg:tags":[
        "shop"
    ],
    "wof:name":"Masters Touch",
    "wof:placetype":"venue"
},
  "geometry": {"coordinates":[-81.273991,41.742585],"type":"Point"}
}