{
  "type": "Feature",
  "properties": {
    "addr:full": "32 Executive Dr Norwalk OH 44857",
    "addr:housenumber": "32",
    "addr:postcode": "44857",
    "addr:street": "Executive Dr",
    "iso:country": "US",
    "sg:address": "32 Executive Dr",
    "sg:city": "Norwalk",
    "sg:classifiers": [
      {
        "category": "Health Services",
        "subcategory": "Doctor",
        "type": "Services"
      }
    ],
    "sg:phone": "+1 419 663 8808",
    "sg:postcode": "44857",
    "sg:province": "OH",
    "sg:tags": [
      "osteopathic"
    ],
    "wof:name": "North Centl Internal Medicine",
    "wof:placetype": "venue"
  },
  "geometry": {"coordinates":[-82.599453,41.230211],"type":"Point"}
}
