{
  "type": "Feature",
  "properties": {
    "addr:full": "10397 State Rte 155 Corning OH 43730",
    "addr:housenumber": "10397",
    "addr:postcode": "43730",
    "addr:street": "State Rte 155",
    "iso:country": "US",
    "sg:address": "10397 State Rte 155",
    "sg:city": "Corning",
    "sg:classifiers": [
      {
        "category": "Education",
        "subcategory": "School",
        "type": "Public Place"
      }
    ],
    "sg:phone": "+1 740 394 2402",
    "sg:postcode": "43730",
    "sg:province": "OH",
    "sg:tags": [
      "elementary",
      "secondary"
    ],
    "wof:name": "Southern Local School District",
    "wof:placetype": "venue"
  },
  "geometry": {"coordinates":[-82.14881,39.590459],"type":"Point"}
}
