{
  "type": "Feature",
  "properties": {
    "iso:country":"US",
    "sg:address":"4440 Yellowhammer Dr",
    "sg:city":"Westerville",
    "sg:classifiers":[
        {
            "category":"Insurance",
            "subcategory":"Hazard Insurance",
            "type":"Services"
        }
    ],
    "sg:phone":"+1 614 890 7938",
    "sg:postcode":"43081",
    "sg:province":"OH",
    "sg:tags":[
        "carrier"
    ],
    "wof:name":"National Assoc For Self Emplyd",
    "wof:placetype":"venue"
},
  "geometry": {"coordinates":[-82.896356,40.0875],"type":"Point"}
}