{
  "type": "Feature",
  "properties": {
    "addr:full":"2525 Oakstone Dr Columbus OH 43231",
    "addr:housenumber":"2525",
    "addr:postcode":"43231",
    "addr:street":"Oakstone Dr",
    "iso:country":"US",
    "sg:address":"2525 Oakstone Dr",
    "sg:city":"Columbus",
    "sg:classifiers":[
        {
            "category":"Banks & Credit Unions",
            "subcategory":"Bank",
            "type":"Services"
        }
    ],
    "sg:phone":"+1 614 895 0155",
    "sg:postcode":"43231",
    "sg:province":"OH",
    "sg:tags":[
        "loan",
        "real estate"
    ],
    "wof:name":"Mortgagequest",
    "wof:placetype":"venue"
},
  "geometry": {"coordinates":[-82.949079,40.097783],"type":"Point"}
}