{
  "type": "Feature",
  "properties": {
    "iso:country":"US",
    "sg:address":"3032 Liberty Ave",
    "sg:city":"Vermilion",
    "sg:classifiers":[
        {
            "category":"Freight",
            "type":"Transportation"
        }
    ],
    "sg:phone":"+1 440 967 0553",
    "sg:postcode":"44089",
    "sg:province":"OH",
    "sg:tags":[
        "commercial",
        "storage"
    ],
    "wof:name":"Liberty Ave South Storage",
    "wof:placetype":"venue"
},
  "geometry": {"coordinates":[-82.307723,41.424855],"type":"Point"}
}