{
  "type": "Feature",
  "properties": {
    "addr:full": "62 W Clinton St Millersburg OH 44654",
    "addr:housenumber": "62",
    "addr:postcode": "44654",
    "addr:street": "W Clinton St",
    "iso:country": "US",
    "sg:address": "62 W Clinton St",
    "sg:city": "Millersburg",
    "sg:classifiers": [
      {
        "category": "Government",
        "subcategory": "Office",
        "type": "Public Place"
      }
    ],
    "sg:phone": "+1 330 674 7923",
    "sg:postcode": "44654",
    "sg:province": "OH",
    "wof:name": "Holmes County Soil \u0026 Water",
    "wof:placetype": "venue"
  },
  "geometry": {"coordinates":[-81.917838,40.555559],"type":"Point"}
}
