{
  "type": "Feature",
  "properties": {
    "iso:country":"US",
    "sg:address":"2747 Som Center Rd",
    "sg:city":"Willoughby",
    "sg:classifiers":[
        {
            "category":"Shopping",
            "subcategory":"Gifts & Souvenirs",
            "type":"Retail Goods"
        }
    ],
    "sg:phone":"+1 440 585 9644",
    "sg:postcode":"44094",
    "sg:province":"OH",
    "sg:tags":[
        "balloon",
        "artist"
    ],
    "wof:name":"Balloon Express",
    "wof:placetype":"venue"
},
  "geometry": {"coordinates":[-81.439444,41.584421],"type":"Point"}
}