{
  "type": "Feature",
  "properties": {
    "iso:country":"US",
    "sg:address":"100 Williamsburg Ln",
    "sg:city":"Dayton",
    "sg:classifiers":[
        {
            "category":"Education",
            "subcategory":"Special Training",
            "type":"Public Place"
        }
    ],
    "sg:phone":"+1 937 436 2167",
    "sg:postcode":"45459",
    "sg:province":"OH",
    "sg:tags":[
        "tutoring"
    ],
    "wof:name":"Kumon Math & Reading Ctrs",
    "wof:placetype":"venue"
},
  "geometry": {"coordinates":[-84.15873999999999,39.637719],"type":"Point"}
}