{
  "type": "Feature",
  "properties": {
    "addr:full": "100 Williamsburg Ln Dayton OH 45459",
    "addr:housenumber": "100",
    "addr:postcode": "45459",
    "addr:street": "Williamsburg Ln",
    "iso:country": "US",
    "sg:address": "100 Williamsburg Ln",
    "sg:city": "Dayton",
    "sg:classifiers": [
      {
        "category": "Education",
        "subcategory": "Special Training",
        "type": "Public Place"
      }
    ],
    "sg:phone": "+1 937 436 2167",
    "sg:postcode": "45459",
    "sg:province": "OH",
    "sg:tags": [
      "tutoring"
    ],
    "wof:name": "Kumon Math \u0026 Reading Ctrs",
    "wof:placetype": "venue"
  },
  "geometry": {"coordinates":[-84.15874,39.637719],"type":"Point"}
}
