{
  "type": "Feature",
  "properties": {
    "addr:full":"220 N Miami St Trenton OH 45067",
    "addr:housenumber":"220",
    "addr:postcode":"45067",
    "addr:street":"N Miami St",
    "iso:country":"US",
    "sg:address":"220 N Miami St",
    "sg:city":"Trenton",
    "sg:classifiers":[
        {
            "category":"Social Services",
            "subcategory":"Child Care",
            "type":"Services"
        }
    ],
    "sg:phone":"+1 513 988 6215",
    "sg:postcode":"45067",
    "sg:province":"OH",
    "sg:website":"www.trentonnazarene.org",
    "wof:name":"Trenton Learning Ctr",
    "wof:placetype":"venue"
},
  "geometry": {"coordinates":[-84.45854,39.484291],"type":"Point"}
}