{
  "type": "Feature",
  "properties": {
    "addr:full":"1745 Southgate Pkwy Cambridge OH 43725",
    "addr:housenumber":"1745",
    "addr:postcode":"43725",
    "addr:street":"Southgate Pkwy",
    "iso:country":"US",
    "sg:address":"1745 Southgate Pkwy",
    "sg:city":"Cambridge",
    "sg:classifiers":[
        {
            "category":"Cinema",
            "subcategory":"Movie Rental",
            "type":"Entertainment"
        }
    ],
    "sg:phone":"+1 740 439 0093",
    "sg:postcode":"43725",
    "sg:province":"OH",
    "sg:tags":[
        "video",
        "tape"
    ],
    "wof:name":"M G A Inc",
    "wof:placetype":"venue"
},
  "geometry": {"coordinates":[-81.581357,40.009689],"type":"Point"}
}