{
  "type": "Feature",
  "properties": {
    "addr:full": "1345 Twp Rd 206 Marengo OH 43334",
    "addr:housenumber": "1345",
    "addr:postcode": "43334",
    "addr:street": "Twp Rd 206",
    "iso:country": "US",
    "sg:address": "1345 Twp Rd 206",
    "sg:city": "Marengo",
    "sg:classifiers": [
      {
        "category": "Recreation",
        "type": "Entertainment"
      }
    ],
    "sg:phone": "+1 419 253 8320",
    "sg:postcode": "43334",
    "sg:province": "OH",
    "sg:tags": [
      "stable"
    ],
    "wof:name": "S \u0026 G Quarter Horses",
    "wof:placetype": "venue"
  },
  "geometry": {"coordinates":[-82.740474,40.399337],"type":"Point"}
}
