{
  "type": "Feature",
  "properties": {
    "iso:country":"US",
    "sg:address":"6106 Dublin Rd",
    "sg:city":"Delaware",
    "sg:classifiers":[
        {
            "category":"Government",
            "subcategory":"Office",
            "type":"Public Place"
        }
    ],
    "sg:phone":"+1 740 881 5624",
    "sg:postcode":"43015",
    "sg:province":"OH",
    "sg:tags":[
        "village"
    ],
    "wof:name":"Concord Township Trustees",
    "wof:placetype":"venue"
},
  "geometry": {"coordinates":[-83.14975200000001,40.22309],"type":"Point"}
}