{
  "type": "Feature",
  "properties": {
    "iso:country":"US",
    "sg:address":"4518 State Rte 775",
    "sg:city":"Patriot",
    "sg:classifiers":[
        {
            "category":"Farming",
            "subcategory":"Livestock Farm",
            "type":"Manufacturing & Wholesale Goods"
        }
    ],
    "sg:phone":"+1 740 379 2212",
    "sg:postcode":"45658",
    "sg:province":"OH",
    "sg:tags":[
        "beef",
        "feedlot",
        "cattle"
    ],
    "wof:name":"Barbara A Baker",
    "wof:placetype":"venue"
},
  "geometry": {"coordinates":[-82.36108900000001,38.753261],"type":"Point"}
}