{
  "type": "Feature",
  "properties": {
    "iso:country":"US",
    "sg:address":"5322 Garber Rd",
    "sg:city":"Mount Vernon",
    "sg:classifiers":[
        {
            "category":"Building & Trades",
            "subcategory":"Landscaping Services",
            "type":"Services"
        }
    ],
    "sg:phone":"+1 740 393 1562",
    "sg:postcode":"43050",
    "sg:province":"OH",
    "wof:name":"Doups Tree Service",
    "wof:placetype":"venue"
},
  "geometry": {"coordinates":[-82.552101,40.304576],"type":"Point"}
}