{
  "type": "Feature",
  "properties": {
    "addr:full": "15050 Fladt Rd Marysville OH 43040",
    "addr:housenumber": "15050",
    "addr:postcode": "43040",
    "addr:street": "Fladt Rd",
    "iso:country": "US",
    "sg:address": "15050 Fladt Rd",
    "sg:city": "Marysville",
    "sg:classifiers": [
      {
        "category": "Building \u0026 Trades",
        "subcategory": "Landscaping Services",
        "type": "Services"
      }
    ],
    "sg:phone": "+1 937 642 4148",
    "sg:postcode": "43040",
    "sg:province": "OH",
    "wof:name": "Michael J Truskoski",
    "wof:placetype": "venue"
  },
  "geometry": {"coordinates":[-83.322309,40.17457],"type":"Point"}
}
