{
  "type": "Feature",
  "properties": {
    "iso:country":"US",
    "sg:address":"5978 State Rte 93",
    "sg:city":"Dundee",
    "sg:classifiers":[
        {
            "category":"Freight",
            "type":"Transportation"
        }
    ],
    "sg:phone":"+1 330 852 7708",
    "sg:postcode":"44624",
    "sg:province":"OH",
    "sg:tags":[
        "operator",
        "local",
        "trucking"
    ],
    "wof:name":"Milltree Trucking Inc",
    "wof:placetype":"venue"
},
  "geometry": {"coordinates":[-81.624882,40.576161],"type":"Point"}
}