{
  "type": "Feature",
  "properties": {
    "iso:country":"US",
    "sg:address":"3383 Albrecht Ave",
    "sg:city":"Akron",
    "sg:classifiers":[
        {
            "category":"Manufacturing",
            "subcategory":"Signs",
            "type":"Manufacturing & Wholesale Goods"
        }
    ],
    "sg:phone":"+1 330 628 8650",
    "sg:postcode":"44312",
    "sg:province":"OH",
    "wof:name":"Exotik Graphix",
    "wof:placetype":"venue"
},
  "geometry": {"coordinates":[-81.41202,41.040828],"type":"Point"}
}