{
  "type": "Feature",
  "properties": {
    "addr:full":"1805 Airport Rd New Lexington OH 43764",
    "addr:housenumber":"1805",
    "addr:postcode":"43764",
    "addr:street":"Airport Rd",
    "iso:country":"US",
    "sg:address":"1805 Airport Rd",
    "sg:city":"New Lexington",
    "sg:classifiers":[
        {
            "category":"Banks & Credit Unions",
            "subcategory":"Financial Services",
            "type":"Services"
        }
    ],
    "sg:phone":"+1 740 342 2852",
    "sg:postcode":"43764",
    "sg:province":"OH",
    "sg:tags":[
        "trust",
        "management"
    ],
    "wof:name":"Foraker Heirs LLC",
    "wof:placetype":"venue"
},
  "geometry": {"coordinates":[-82.20808700000001,39.692583],"type":"Point"}
}