{
  "type": "Feature",
  "properties": {
    "iso:country":"US",
    "sg:address":"638 Old State Rte 74",
    "sg:city":"Cincinnati",
    "sg:classifiers":[
        {
            "category":"Organizations",
            "subcategory":"Religious Organization",
            "type":"Services"
        }
    ],
    "sg:phone":"+1 513 528 3052",
    "sg:postcode":"45245",
    "sg:province":"OH",
    "wof:name":"Summerside Untd Methdst Church",
    "wof:placetype":"venue"
},
  "geometry": {"coordinates":[-84.29106,39.104698],"type":"Point"}
}