{
  "type": "Feature",
  "properties": {
    "addr:full": "5687 Pearl Rd Cleveland OH 44129",
    "addr:housenumber": "5687",
    "addr:postcode": "44129",
    "addr:street": "Pearl Rd",
    "iso:country": "US",
    "sg:address": "5687 Pearl Rd",
    "sg:city": "Cleveland",
    "sg:classifiers": [
      {
        "category": "Travel",
        "subcategory": "Travel Agent",
        "type": "Entertainment"
      }
    ],
    "sg:phone": "+1 440 888 8747",
    "sg:postcode": "44129",
    "sg:province": "OH",
    "sg:tags": [
      "agency",
      "bureau"
    ],
    "wof:name": "Steve's Travel",
    "wof:placetype": "venue"
  },
  "geometry": {"coordinates":[-81.740774,41.407746],"type":"Point"}
}
