{
  "type": "Feature",
  "properties": {
    "addr:full":"13246 Doylestown Rd Rittman OH 44270",
    "addr:housenumber":"13246",
    "addr:postcode":"44270",
    "addr:street":"Doylestown Rd",
    "iso:country":"US",
    "sg:address":"13246 Doylestown Rd",
    "sg:city":"Rittman",
    "sg:classifiers":[
        {
            "category":"Building & Trades",
            "subcategory":"Construction",
            "type":"Services"
        }
    ],
    "sg:phone":"+1 330 658 3282",
    "sg:postcode":"44270",
    "sg:province":"OH",
    "sg:tags":[
        "water",
        "well",
        "drilling"
    ],
    "wof:name":"H & H Pump Service",
    "wof:placetype":"venue"
},
  "geometry": {"coordinates":[-81.73693299999999,40.97157],"type":"Point"}
}