{
  "type": "Feature",
  "properties": {
    "addr:full":"119 Madison St Port Clinton OH 43452",
    "addr:housenumber":"119",
    "addr:postcode":"43452",
    "addr:street":"Madison St",
    "iso:country":"US",
    "sg:address":"119 Madison St",
    "sg:city":"Port Clinton",
    "sg:classifiers":[
        {
            "category":"Professional",
            "subcategory":"Management & Consulting",
            "type":"Services"
        }
    ],
    "sg:phone":"+1 419 732 1770",
    "sg:postcode":"43452",
    "sg:province":"OH",
    "sg:tags":[
        "consultant",
        "political"
    ],
    "wof:name":"Cathy Allen",
    "wof:placetype":"venue"
},
  "geometry": {"coordinates":[-82.94107099999999,41.512177],"type":"Point"}
}