{
  "type": "Feature",
  "properties": {
    "iso:country":"US",
    "sg:address":"4660 Duke Dr",
    "sg:city":"Mason",
    "sg:classifiers":[
        {
            "category":"Building & Trades",
            "subcategory":"Construction",
            "type":"Services"
        }
    ],
    "sg:phone":"+1 513 339 2100",
    "sg:postcode":"45040",
    "sg:province":"OH",
    "sg:tags":[
        "house",
        "builder",
        "operative"
    ],
    "wof:name":"Ryland Homes",
    "wof:placetype":"venue"
},
  "geometry": {"coordinates":[-84.309916,39.301167],"type":"Point"}
}