{
  "type": "Feature",
  "properties": {
    "addr:full":"217 E Main St Kent OH 44240",
    "addr:housenumber":"217",
    "addr:postcode":"44240",
    "addr:street":"E Main St",
    "iso:country":"US",
    "sg:address":"217 E Main St",
    "sg:city":"Kent",
    "sg:classifiers":[
        {
            "category":"Professional",
            "subcategory":"Lawyer & Legal Services",
            "type":"Services"
        }
    ],
    "sg:phone":"+1 330 678 5525",
    "sg:postcode":"44240",
    "sg:province":"OH",
    "sg:tags":[
        "attorney"
    ],
    "wof:name":"Ralph L Oates",
    "wof:placetype":"venue"
},
  "geometry": {"coordinates":[-81.353224,41.153857],"type":"Point"}
}