{
  "type": "Feature",
  "properties": {
    "iso:country":"US",
    "sg:address":"8114 Springboro Pike",
    "sg:city":"Miamisburg",
    "sg:classifiers":[
        {
            "category":"Shopping",
            "subcategory":"Shoes",
            "type":"Retail Goods"
        }
    ],
    "sg:phone":"+1 937 439 3887",
    "sg:postcode":"45342",
    "sg:province":"OH",
    "sg:tags":[
        "durable"
    ],
    "sg:website":"www.redwingshoe.com",
    "wof:name":"Red Wing Shoe Store",
    "wof:placetype":"venue"
},
  "geometry": {"coordinates":[-84.225475,39.633794],"type":"Point"}
}