{
  "type": "Feature",
  "properties": {
    "addr:full": "5680 Meeker Rd Greenville OH 45331",
    "addr:postcode": "5680;45331",
    "addr:street": "Meeker Rd",
    "iso:country": "US",
    "sg:address": "5680 Meeker Rd",
    "sg:city": "Greenville",
    "sg:classifiers": [
      {
        "category": "Retail",
        "subcategory": "Auto Repair",
        "type": "Services"
      }
    ],
    "sg:phone": "+1 937 548 9041",
    "sg:postcode": "45331",
    "sg:province": "OH",
    "sg:tags": [
      "repairing",
      "automobile"
    ],
    "wof:name": "Keith's Wrecker Svc",
    "wof:placetype": "venue"
  },
  "geometry": {"coordinates":[-84.627672,40.082514],"type":"Point"}
}
