{
  "type": "Feature",
  "properties": {
    "addr:full":"452 W Jackson St Painesville OH 44077",
    "addr:housenumber":"452",
    "addr:postcode":"44077",
    "addr:street":"W Jackson St",
    "iso:country":"US",
    "sg:address":"452 W Jackson St",
    "sg:city":"Painesville",
    "sg:classifiers":[
        {
            "category":"Organizations",
            "subcategory":"Religious Organization",
            "type":"Services"
        }
    ],
    "sg:phone":"+1 440 354 8771",
    "sg:postcode":"44077",
    "sg:province":"OH",
    "sg:tags":[
        "clergy"
    ],
    "wof:name":"Vincent R Miller",
    "wof:placetype":"venue"
},
  "geometry": {"coordinates":[-81.257723,41.717611],"type":"Point"}
}