{
  "type": "Feature",
  "properties": {
    "addr:full": "3690 Orange Pl Ste 520 Beachwood OH 44122",
    "addr:housenumber": "3690",
    "addr:postcode": "44122",
    "addr:street": "Orange Pl Ste 520",
    "iso:country": "US",
    "sg:address": "3690 Orange Pl Ste 520",
    "sg:city": "Beachwood",
    "sg:classifiers": [
      {
        "category": "Health Services",
        "subcategory": "Dentist",
        "type": "Services"
      }
    ],
    "sg:phone": "+1 216 360 0090",
    "sg:postcode": "44122",
    "sg:province": "OH",
    "wof:name": "Katz Steven DDS Ms",
    "wof:placetype": "venue"
  },
  "geometry": {"coordinates":[-81.487999,41.458801],"type":"Point"}
}
