{
  "type": "Feature",
  "properties": {
    "iso:country":"US",
    "sg:address":"804 South St",
    "sg:city":"Galion",
    "sg:classifiers":[
        {
            "category":"Organizations",
            "subcategory":"Religious Organization",
            "type":"Services"
        },
        {
            "category":"Manufacturing",
            "subcategory":"Rubber & Plastics",
            "type":"Manufacturing & Wholesale Goods"
        }
    ],
    "sg:phone":"+1 419 468 6126",
    "sg:postcode":"44833",
    "sg:province":"OH",
    "sg:tags":[
        "mfg",
        "clergy",
        "mechanical"
    ],
    "wof:name":"Lanny E Candel Rev",
    "wof:placetype":"venue"
},
  "geometry": {"coordinates":[-82.783682,40.723083],"type":"Point"}
}