{
  "type": "Feature",
  "properties": {
    "iso:country":"US",
    "sg:address":"6000 Lombardo Center",
    "sg:city":"Cleveland",
    "sg:classifiers":[
        {
            "category":"Insurance",
            "subcategory":"Insurance Agent",
            "type":"Services"
        }
    ],
    "sg:phone":"+1 216 520 1345",
    "sg:postcode":"44131",
    "sg:province":"OH",
    "wof:name":"New York Life Insurance Co",
    "wof:placetype":"venue"
},
  "geometry": {"coordinates":[-81.66340599999999,41.404796],"type":"Point"}
}