{
  "type": "Feature",
  "properties": {
    "iso:country":"US",
    "sg:address":"717 N Main St",
    "sg:city":"North Canton",
    "sg:classifiers":[
        {
            "category":"Banks & Credit Unions",
            "subcategory":"Investment Brokerage",
            "type":"Services"
        }
    ],
    "sg:phone":"+1 330 497 9590",
    "sg:postcode":"44720",
    "sg:province":"OH",
    "sg:tags":[
        "advisory",
        "financial"
    ],
    "wof:name":"Creative Financial Svc",
    "wof:placetype":"venue"
},
  "geometry": {"coordinates":[-81.40391,40.884528],"type":"Point"}
}