{
  "type": "Feature",
  "properties": {
    "addr:full": "7830 Southern Blvd Youngstown OH 44512",
    "addr:housenumber": "7830",
    "addr:postcode": "44512",
    "addr:street": "Southern Blvd",
    "iso:country": "US",
    "sg:address": "7830 Southern Blvd",
    "sg:city": "Youngstown",
    "sg:classifiers": [
      {
        "category": "Shopping",
        "subcategory": "Hobbies, Toys, \u0026 Games",
        "type": "Retail Goods"
      }
    ],
    "sg:phone": "+1 330 726 1474",
    "sg:postcode": "44512",
    "sg:province": "OH",
    "sg:tags": [
      "equipment",
      "ceramic",
      "supply"
    ],
    "wof:name": "Marie's Shoppe",
    "wof:placetype": "venue"
  },
  "geometry": {"coordinates":[-80.65345,41.011485],"type":"Point"}
}
