{
  "type": "Feature",
  "properties": {
    "iso:country":"US",
    "sg:address":"7830 Southern Blvd",
    "sg:city":"Youngstown",
    "sg:classifiers":[
        {
            "category":"Shopping",
            "subcategory":"Hobbies, Toys, & Games",
            "type":"Retail Goods"
        }
    ],
    "sg:phone":"+1 330 726 1474",
    "sg:postcode":"44512",
    "sg:province":"OH",
    "sg:tags":[
        "equipment",
        "ceramic",
        "supply"
    ],
    "wof:name":"Marie's Shoppe",
    "wof:placetype":"venue"
},
  "geometry": {"coordinates":[-80.65345000000001,41.011485],"type":"Point"}
}