{
  "type": "Feature",
  "properties": {
    "iso:country":"US",
    "sg:address":"18745 Co Rd 109",
    "sg:city":"Arcadia",
    "sg:classifiers":[
        {
            "category":"Farming",
            "subcategory":"Farm",
            "type":"Manufacturing & Wholesale Goods"
        }
    ],
    "sg:phone":"+1 419 894 6137",
    "sg:postcode":"44804",
    "sg:province":"OH",
    "sg:tags":[
        "crop",
        "general"
    ],
    "wof:name":"Cunningham Farm",
    "wof:placetype":"venue"
},
  "geometry": {"coordinates":[-83.52114899999999,41.122846],"type":"Point"}
}