{
  "type": "Feature",
  "properties": {
    "addr:full": "18745 Co Rd 109 Arcadia OH 44804",
    "addr:housenumber": "18745;109",
    "addr:postcode": "44804",
    "addr:street": "Co Rd",
    "iso:country": "US",
    "sg:address": "18745 Co Rd 109",
    "sg:city": "Arcadia",
    "sg:classifiers": [
      {
        "category": "Farming",
        "subcategory": "Farm",
        "type": "Manufacturing \u0026 Wholesale Goods"
      }
    ],
    "sg:phone": "+1 419 894 6137",
    "sg:postcode": "44804",
    "sg:province": "OH",
    "sg:tags": [
      "crop",
      "general"
    ],
    "wof:name": "Cunningham Farm",
    "wof:placetype": "venue"
  },
  "geometry": {"coordinates":[-83.521149,41.122846],"type":"Point"}
}
