{
  "type": "Feature",
  "properties": {
    "addr:full":"539 W Schrock Rd Columbus OH 43229",
    "addr:housenumber":"539",
    "addr:postcode":"43229",
    "addr:street":"W Schrock Rd",
    "iso:country":"US",
    "sg:address":"539 W Schrock Rd",
    "sg:city":"Columbus",
    "sg:classifiers":[
        {
            "category":"Manufacturing",
            "subcategory":"Tools & Machinery",
            "type":"Manufacturing & Wholesale Goods"
        }
    ],
    "sg:phone":"+1 614 885 3304",
    "sg:postcode":"43229",
    "sg:province":"OH",
    "sg:tags":[
        "machine",
        "shop"
    ],
    "wof:name":"Wilson Machine Company Inc",
    "wof:placetype":"venue"
},
  "geometry": {"coordinates":[-83.000005,40.101404],"type":"Point"}
}