{
  "type": "Feature",
  "properties": {
    "addr:full": "109 N Sandusky St Delaware OH 43015",
    "addr:housenumber": "109",
    "addr:postcode": "43015",
    "addr:street": "N Sandusky St",
    "iso:country": "US",
    "sg:address": "109 N Sandusky St",
    "sg:city": "Delaware",
    "sg:classifiers": [
      {
        "category": "Government",
        "subcategory": "Office",
        "type": "Public Place"
      }
    ],
    "sg:phone": "+1 740 368 1700",
    "sg:postcode": "43015",
    "sg:province": "OH",
    "sg:tags": [
      "county",
      "program",
      "health"
    ],
    "wof:name": "Delaware General Health Dist",
    "wof:placetype": "venue"
  },
  "geometry": {"coordinates":[-83.067505,40.302712],"type":"Point"}
}
