{
  "type": "Feature",
  "properties": {
    "iso:country":"US",
    "sg:address":"2160 Berlin Station Rd",
    "sg:city":"Delaware",
    "sg:classifiers":[
        {
            "category":"Building & Trades",
            "subcategory":"Construction",
            "type":"Services"
        }
    ],
    "sg:phone":"+1 740 369 8372",
    "sg:postcode":"43015",
    "sg:province":"OH",
    "sg:tags":[
        "house"
    ],
    "wof:name":"Rossiter Builders",
    "wof:placetype":"venue"
},
  "geometry": {"coordinates":[-83.034949,40.25898],"type":"Point"}
}