{
  "type": "Feature",
  "properties": {
    "addr:full": "1221 N 5th St Toronto OH 43964",
    "addr:housenumber": "1221",
    "addr:postcode": "43964",
    "addr:street": "N 5Th St",
    "iso:country": "US",
    "sg:address": "1221 N 5th St",
    "sg:city": "Toronto",
    "sg:classifiers": [
      {
        "category": "Shopping",
        "subcategory": "Gifts \u0026 Souvenirs",
        "type": "Retail Goods"
      }
    ],
    "sg:phone": "+1 740 537 4105",
    "sg:postcode": "43964",
    "sg:province": "OH",
    "wof:name": "Just Friends Country Merc",
    "wof:placetype": "venue"
  },
  "geometry": {"coordinates":[-80.603284,40.477844],"type":"Point"}
}
