{
  "type": "Feature",
  "properties": {
    "addr:full":"2600 Carolyn Dr Lima OH 45807",
    "addr:housenumber":"2600",
    "addr:postcode":"45807",
    "addr:street":"Carolyn Dr",
    "iso:country":"US",
    "sg:address":"2600 Carolyn Dr",
    "sg:city":"Lima",
    "sg:classifiers":[
        {
            "category":"Organizations",
            "subcategory":"Professional Association",
            "type":"Services"
        }
    ],
    "sg:phone":"+1 419 225 9056",
    "sg:postcode":"45807",
    "sg:province":"OH",
    "wof:name":"Ohio State Assn",
    "wof:placetype":"venue"
},
  "geometry": {"coordinates":[-84.13266299999999,40.777263],"type":"Point"}
}