{
  "type": "Feature",
  "properties": {
    "addr:full":"13379 State Rte 66 Cloverdale OH 45827",
    "addr:housenumber":"13379",
    "addr:postcode":"45827",
    "addr:street":"State Rte 66",
    "iso:country":"US",
    "sg:address":"13379 State Rte 66",
    "sg:city":"Cloverdale",
    "sg:classifiers":[
        {
            "category":"Real Estate",
            "subcategory":"Real Estate Operator",
            "type":"Services"
        }
    ],
    "sg:phone":"+1 419 453 3247",
    "sg:postcode":"45827",
    "sg:province":"OH",
    "sg:tags":[
        "farm",
        "corn",
        "property",
        "soybean",
        "lessor"
    ],
    "wof:name":"Joe Kemper",
    "wof:placetype":"venue"
},
  "geometry": {"coordinates":[-84.361287,40.985122],"type":"Point"}
}