{
  "type": "Feature",
  "properties": {
    "iso:country":"US",
    "sg:address":"1310 Claremont Ave",
    "sg:city":"Ashland",
    "sg:classifiers":[
        {
            "category":"Health Services",
            "subcategory":"Medical Lab",
            "type":"Services"
        }
    ],
    "sg:phone":"+1 419 281 7100",
    "sg:postcode":"44805",
    "sg:province":"OH",
    "sg:tags":[
        "laboratory"
    ],
    "wof:name":"Laboratory Corporation America",
    "wof:placetype":"venue"
},
  "geometry": {"coordinates":[-82.33287,40.856267],"type":"Point"}
}