{
  "type": "Feature",
  "properties": {
    "addr:full": "25825 Science Park Dr Cleveland OH 44122",
    "addr:housenumber": "25825",
    "addr:postcode": "44122",
    "addr:street": "Science Park Dr",
    "iso:country": "US",
    "sg:address": "25825 Science Park Dr",
    "sg:city": "Cleveland",
    "sg:classifiers": [
      {
        "category": "Banks \u0026 Credit Unions",
        "subcategory": "Investment Brokerage",
        "type": "Services"
      }
    ],
    "sg:phone": "+1 216 765 8160",
    "sg:postcode": "44122",
    "sg:province": "OH",
    "wof:name": "Logix Investment Management",
    "wof:placetype": "venue"
  },
  "geometry": {"coordinates":[-81.491635,41.470832],"type":"Point"}
}
