{
  "type": "Feature",
  "properties": {
    "addr:full":"520 E Poe Rd Bowling Green OH 43402",
    "addr:housenumber":"520",
    "addr:postcode":"43402",
    "addr:street":"E Poe Rd",
    "iso:country":"US",
    "sg:address":"520 E Poe Rd",
    "sg:city":"Bowling Green",
    "sg:classifiers":[
        {
            "category":"Autos & Motor Vehicles",
            "subcategory":"Auto Supplies",
            "type":"Retail Goods"
        }
    ],
    "sg:phone":"+1 419 353 8473",
    "sg:postcode":"43402",
    "sg:province":"OH",
    "sg:tags":[
        "farm",
        "truck",
        "tire"
    ],
    "wof:name":"Northwest Tire Services",
    "wof:placetype":"venue"
},
  "geometry": {"coordinates":[-83.64272099999999,41.385462],"type":"Point"}
}