{
  "type": "Feature",
  "properties": {
    "addr:full": "66 E Lynn St Columbus OH 43215",
    "addr:housenumber": "66",
    "addr:postcode": "43215",
    "addr:street": "E Lynn St",
    "iso:country": "US",
    "sg:address": "66 E Lynn St",
    "sg:city": "Columbus",
    "sg:classifiers": [
      {
        "category": "Professional",
        "subcategory": "Management \u0026 Consulting",
        "type": "Services"
      }
    ],
    "sg:phone": "+1 614 221 5150",
    "sg:postcode": "43215",
    "sg:province": "OH",
    "sg:tags": [
      "consultant",
      "government"
    ],
    "wof:name": "Statecraft Inc",
    "wof:placetype": "venue"
  },
  "geometry": {"coordinates":[-82.999014,39.963186],"type":"Point"}
}
