{
  "type": "Feature",
  "properties": {
    "iso:country":"US",
    "sg:address":"5738 Middleby Dr",
    "sg:city":"Hilliard",
    "sg:classifiers":[
        {
            "category":"Utilities",
            "subcategory":"Refuse",
            "type":"Services"
        }
    ],
    "sg:phone":"+1 614 777 1149",
    "sg:postcode":"43026",
    "sg:province":"OH",
    "sg:tags":[
        "pet",
        "waste",
        "removal"
    ],
    "wof:name":"Happy Lawn Pet Waste Removal",
    "wof:placetype":"venue"
},
  "geometry": {"coordinates":[-83.165147,40.017212],"type":"Point"}
}