{
  "type": "Feature",
  "properties": {
    "iso:country":"US",
    "sg:address":"36330 State Rte 324",
    "sg:city":"Hamden",
    "sg:classifiers":[
        {
            "category":"Wholesale",
            "subcategory":"Auto Parts",
            "type":"Manufacturing & Wholesale Goods"
        }
    ],
    "sg:phone":"+1 740 596 9953",
    "sg:postcode":"45634",
    "sg:province":"OH",
    "sg:tags":[
        "used"
    ],
    "wof:name":"Waters Auto Repair & Salvage",
    "wof:placetype":"venue"
},
  "geometry": {"coordinates":[-82.477752,39.193825],"type":"Point"}
}