{
  "type": "Feature",
  "properties": {
    "addr:full": "2800 Fulton Dr NW Canton OH 44718",
    "addr:housenumber": "2800",
    "addr:postcode": "44718",
    "addr:street": "Fulton Dr Nw",
    "iso:country": "US",
    "sg:address": "2800 Fulton Dr NW",
    "sg:city": "Canton",
    "sg:classifiers": [
      {
        "category": "Restaurant",
        "type": "Food \u0026 Drink"
      }
    ],
    "sg:phone": "+1 330 452 6825",
    "sg:postcode": "44718",
    "sg:province": "OH",
    "sg:tags": [
      "caterer"
    ],
    "wof:name": "Mr Mike's Catering",
    "wof:placetype": "venue"
  },
  "geometry": {"coordinates":[-81.40469,40.827563],"type":"Point"}
}
