{
  "type": "Feature",
  "properties": {
    "addr:full":"4444 Market St Youngstown OH 44512",
    "addr:housenumber":"4444",
    "addr:postcode":"44512",
    "addr:street":"Market St",
    "iso:country":"US",
    "sg:address":"4444 Market St",
    "sg:city":"Youngstown",
    "sg:classifiers":[
        {
            "category":"Insurance",
            "subcategory":"Insurance Agent",
            "type":"Services"
        }
    ],
    "sg:phone":"+1 330 788 3075",
    "sg:postcode":"44512",
    "sg:province":"OH",
    "sg:tags":[
        "consultant",
        "agency",
        "analyst"
    ],
    "wof:name":"Colony Insurance Agency Inc.",
    "wof:placetype":"venue"
},
  "geometry": {"coordinates":[-80.662758,41.053938],"type":"Point"}
}