{
  "type": "Feature",
  "properties": {
    "iso:country":"US",
    "sg:address":"40 Front St",
    "sg:city":"Dayton",
    "sg:classifiers":[
        {
            "category":"Building & Trades",
            "subcategory":"Construction",
            "type":"Services"
        }
    ],
    "sg:phone":"+1 937 222 7960",
    "sg:postcode":"45402",
    "sg:province":"OH",
    "sg:tags":[
        "contractor"
    ],
    "wof:name":"Adams Industrial Welding LLC",
    "wof:placetype":"venue"
},
  "geometry": {"coordinates":[-84.175398,39.763482],"type":"Point"}
}