{
  "type": "Feature",
  "properties": {
    "iso:country":"US",
    "sg:address":"1214 Doral Dr",
    "sg:city":"Youngstown",
    "sg:classifiers":[
        {
            "category":"Personal",
            "subcategory":"Beauty Salon",
            "type":"Services"
        }
    ],
    "sg:phone":"+1 330 726 6470",
    "sg:postcode":"44514",
    "sg:province":"OH",
    "wof:name":"Hair Inc",
    "wof:placetype":"venue"
},
  "geometry": {"coordinates":[-80.632435,41.028386],"type":"Point"}
}