{
  "type": "Feature",
  "properties": {
    "addr:full":"5906 Glenway Ave Cincinnati OH 45238",
    "addr:housenumber":"5906",
    "addr:postcode":"45238",
    "addr:street":"Glenway Ave",
    "iso:country":"US",
    "sg:address":"5906 Glenway Ave",
    "sg:city":"Cincinnati",
    "sg:classifiers":[
        {
            "category":"Real Estate",
            "subcategory":"Real Estate Agent",
            "type":"Services"
        }
    ],
    "sg:phone":"+1 513 922 8988",
    "sg:postcode":"45238",
    "sg:province":"OH",
    "wof:name":"Joseph Fiorino",
    "wof:placetype":"venue"
},
  "geometry": {"coordinates":[-84.61719100000001,39.140258],"type":"Point"}
}