{
  "type": "Feature",
  "properties": {
    "iso:country":"US",
    "sg:address":"4025 Lincoln St E",
    "sg:city":"Canton",
    "sg:classifiers":[
        {
            "category":"Restaurant",
            "type":"Food & Drink"
        }
    ],
    "sg:menulink":"http://www.allmenus.com/oh/canton/195250-mcdonalds/menu/",
    "sg:postcode":"44707",
    "sg:province":"OH",
    "sg:tags":[
        "burger",
        "american"
    ],
    "wof:name":"McDonald's",
    "wof:placetype":"venue"
},
  "geometry": {"coordinates":[-81.321423,40.789272],"type":"Point"}
}