{
  "type": "Feature",
  "properties": {
    "iso:country":"US",
    "sg:address":"205 E 8th St",
    "sg:city":"Marysville",
    "sg:classifiers":[
        {
            "category":"Restaurant",
            "type":"Food & Drink"
        }
    ],
    "sg:phone":"+1 937 644 9319",
    "sg:postcode":"43040",
    "sg:province":"OH",
    "sg:tags":[
        "delicatessen"
    ],
    "wof:name":"Perk A Deli",
    "wof:placetype":"venue"
},
  "geometry": {"coordinates":[-83.366005,40.233001],"type":"Point"}
}