{
  "type": "Feature",
  "properties": {
    "addr:full":"3654 E 105th St Cleveland OH 44105",
    "addr:housenumber":"3654",
    "addr:postcode":"44105",
    "addr:street":"E 105Th St",
    "iso:country":"US",
    "sg:address":"3654 E 105th St",
    "sg:city":"Cleveland",
    "sg:classifiers":[
        {
            "category":"Food & Beverages",
            "subcategory":"Groceries & Convenience Stores",
            "type":"Retail Goods"
        }
    ],
    "sg:phone":"+1 216 271 0542",
    "sg:postcode":"44105",
    "sg:province":"OH",
    "wof:name":"Sana Foods & Beverage",
    "wof:placetype":"venue"
},
  "geometry": {"coordinates":[-81.61169,41.457303],"type":"Point"}
}