{
  "type": "Feature",
  "properties": {
    "addr:full": "427 Richmond Rd Cleveland OH 44143",
    "addr:housenumber": "427",
    "addr:postcode": "44143",
    "addr:street": "Richmond Rd",
    "iso:country": "US",
    "sg:address": "427 Richmond Rd",
    "sg:city": "Cleveland",
    "sg:classifiers": [
      {
        "category": "Social Services",
        "subcategory": "Adult Care",
        "type": "Services"
      }
    ],
    "sg:phone": "+1 216 692 3212",
    "sg:postcode": "44143",
    "sg:province": "OH",
    "sg:tags": [
      "residential"
    ],
    "wof:name": "Highland House",
    "wof:placetype": "venue"
  },
  "geometry": {"coordinates":[-81.496889,41.563888],"type":"Point"}
}
