{
  "type": "Feature",
  "properties": {
    "addr:full":"1348 Main St Dresden OH 43821",
    "addr:housenumber":"1348",
    "addr:postcode":"43821",
    "addr:street":"Main St",
    "iso:country":"US",
    "sg:address":"1348 Main St",
    "sg:city":"Dresden",
    "sg:classifiers":[
        {
            "category":"Social Services",
            "type":"Services"
        }
    ],
    "sg:phone":"+1 740 754 2633",
    "sg:postcode":"43821",
    "sg:province":"OH",
    "sg:tags":[
        "senior",
        "citizen"
    ],
    "wof:name":"Bonnie Longaberger Ctr",
    "wof:placetype":"venue"
},
  "geometry": {"coordinates":[-82.00680800000001,40.113667],"type":"Point"}
}