{
  "type": "Feature",
  "properties": {
    "iso:country":"US",
    "sg:address":"980 State Rte 93 N",
    "sg:city":"Logan",
    "sg:classifiers":[
        {
            "category":"Utilities",
            "subcategory":"Refuse",
            "type":"Services"
        }
    ],
    "sg:phone":"+1 740 385 8101",
    "sg:postcode":"43138",
    "sg:province":"OH",
    "sg:tags":[
        "dumps"
    ],
    "wof:name":"Southern Ohio Disposal",
    "wof:placetype":"venue"
},
  "geometry": {"coordinates":[-82.39511299999999,39.548858],"type":"Point"}
}