{
  "type": "Feature",
  "properties": {
    "addr:full": "980 State Rte 93 N Logan OH 43138",
    "addr:housenumber": "980",
    "addr:postcode": "43138",
    "addr:street": "State Rte 93 N",
    "iso:country": "US",
    "sg:address": "980 State Rte 93 N",
    "sg:city": "Logan",
    "sg:classifiers": [
      {
        "category": "Utilities",
        "subcategory": "Refuse",
        "type": "Services"
      }
    ],
    "sg:phone": "+1 740 385 8101",
    "sg:postcode": "43138",
    "sg:province": "OH",
    "sg:tags": [
      "dumps"
    ],
    "wof:name": "Southern Ohio Disposal",
    "wof:placetype": "venue"
  },
  "geometry": {"coordinates":[-82.395113,39.548858],"type":"Point"}
}
