{
  "type": "Feature",
  "properties": {
    "addr:full": "12366 Providence Rd Brookville OH 45309",
    "addr:housenumber": "12366",
    "addr:postcode": "45309",
    "addr:street": "Providence Rd",
    "iso:country": "US",
    "sg:address": "12366 Providence Rd",
    "sg:city": "Brookville",
    "sg:classifiers": [
      {
        "category": "Farming",
        "subcategory": "Dairy Farm",
        "type": "Manufacturing \u0026 Wholesale Goods"
      }
    ],
    "sg:phone": "+1 937 833 3747",
    "sg:postcode": "45309",
    "sg:province": "OH",
    "wof:name": "David Flora",
    "wof:placetype": "venue"
  },
  "geometry": {"coordinates":[-84.407351,39.803439],"type":"Point"}
}
