{
  "type": "Feature",
  "properties": {
    "addr:full": "743 E State St Athens OH 45701",
    "addr:housenumber": "743",
    "addr:postcode": "45701",
    "addr:street": "E State St",
    "iso:country": "US",
    "sg:address": "743 E State St",
    "sg:city": "Athens",
    "sg:classifiers": [
      {
        "category": "Government",
        "subcategory": "Office",
        "type": "Public Place"
      }
    ],
    "sg:phone": "+1 740 594 3300",
    "sg:postcode": "45701",
    "sg:province": "OH",
    "sg:tags": [
      "general"
    ],
    "wof:name": "Southeast Region",
    "wof:placetype": "venue"
  },
  "geometry": {"coordinates":[-82.076029,39.337443],"type":"Point"}
}
