{
  "type": "Feature",
  "properties": {
    "addr:full": "108 W Russell Ave West Lafayette OH 43845",
    "addr:housenumber": "108",
    "addr:postcode": "43845",
    "addr:street": "W Russell Ave",
    "iso:country": "US",
    "sg:address": "108 W Russell Ave",
    "sg:city": "West Lafayette",
    "sg:classifiers": [
      {
        "category": "Airport",
        "type": "Transportation"
      }
    ],
    "sg:phone": "+1 740 545 7309",
    "sg:postcode": "43845",
    "sg:province": "OH",
    "wof:name": "Tri City Airmen Inc",
    "wof:placetype": "venue"
  },
  "geometry": {"coordinates":[-81.752879,40.274861],"type":"Point"}
}
