{
  "type": "Feature",
  "properties": {
    "addr:full": "950 Claycraft Rd Columbus OH 43230",
    "addr:housenumber": "950",
    "addr:postcode": "43230",
    "addr:street": "Claycraft Rd",
    "iso:country": "US",
    "sg:address": "950 Claycraft Rd",
    "sg:city": "Columbus",
    "sg:classifiers": [
      {
        "category": "Professional",
        "type": "Services"
      }
    ],
    "sg:phone": "+1 614 864 3386",
    "sg:postcode": "43230",
    "sg:province": "OH",
    "wof:name": "Network Energy of Ohio",
    "wof:placetype": "venue"
  },
  "geometry": {"coordinates":[-82.847366,39.992924],"type":"Point"}
}
