{
  "type": "Feature",
  "properties": {
    "addr:full":"280 Pattonsville Rd Jackson OH 45640",
    "addr:housenumber":"280",
    "addr:postcode":"45640",
    "addr:street":"Pattonsville Rd",
    "iso:country":"US",
    "sg:address":"280 Pattonsville Rd",
    "sg:city":"Jackson",
    "sg:classifiers":[
        {
            "category":"Health Services",
            "subcategory":"Doctor",
            "type":"Services"
        }
    ],
    "sg:phone":"+1 740 395 8868",
    "sg:postcode":"45640",
    "sg:province":"OH",
    "sg:tags":[
        "clinic"
    ],
    "sg:website":"www.holzerclinic.com",
    "wof:name":"Holzer Clinic",
    "wof:placetype":"venue"
},
  "geometry": {"coordinates":[-82.613759,39.05154],"type":"Point"}
}