{
  "type": "Feature",
  "properties": {
    "iso:country":"US",
    "sg:address":"5438 Infinity Ct",
    "sg:city":"Grove City",
    "sg:classifiers":[
        {
            "category":"Wholesale",
            "subcategory":"Electrical",
            "type":"Manufacturing & Wholesale Goods"
        }
    ],
    "sg:phone":"+1 614 875 6632",
    "sg:postcode":"43123",
    "sg:province":"OH",
    "sg:tags":[
        "control",
        "security",
        "system"
    ],
    "wof:name":"Phil Secure Inc",
    "wof:placetype":"venue"
},
  "geometry": {"coordinates":[-83.147327,39.878348],"type":"Point"}
}