{
  "type": "Feature",
  "properties": {
    "addr:full": "5438 Infinity Ct Grove City OH 43123",
    "addr:housenumber": "5438",
    "addr:postcode": "43123",
    "addr:street": "Infinity Ct",
    "iso:country": "US",
    "sg:address": "5438 Infinity Ct",
    "sg:city": "Grove City",
    "sg:classifiers": [
      {
        "category": "Wholesale",
        "subcategory": "Electrical",
        "type": "Manufacturing \u0026 Wholesale Goods"
      }
    ],
    "sg:phone": "+1 614 875 6632",
    "sg:postcode": "43123",
    "sg:province": "OH",
    "sg:tags": [
      "control",
      "security",
      "system"
    ],
    "wof:name": "Phil Secure Inc",
    "wof:placetype": "venue"
  },
  "geometry": {"coordinates":[-83.147327,39.878348],"type":"Point"}
}
