{
  "type": "Feature",
  "properties": {
    "iso:country":"US",
    "sg:address":"122 N Main St",
    "sg:city":"Hudson",
    "sg:classifiers":[
        {
            "category":"Real Estate",
            "subcategory":"Real Estate Agent",
            "type":"Services"
        },
        {
            "category":"Insurance",
            "subcategory":"Insurance Agent",
            "type":"Services"
        }
    ],
    "sg:phone":"+1 330 656 3340",
    "sg:postcode":"44236",
    "sg:province":"OH",
    "wof:name":"Cramer Smythe Co",
    "wof:placetype":"venue"
},
  "geometry": {"coordinates":[-81.440509,41.241597],"type":"Point"}
}