{
  "type": "Feature",
  "properties": {
    "addr:full":"510 Steubenville Rd SE Carrollton OH 44615",
    "addr:housenumber":"510",
    "addr:postcode":"44615",
    "addr:street":"Steubenville Rd Se",
    "iso:country":"US",
    "sg:address":"510 Steubenville Rd SE",
    "sg:city":"Carrollton",
    "sg:classifiers":[
        {
            "category":"Farming",
            "subcategory":"Dairy Farm",
            "type":"Manufacturing & Wholesale Goods"
        }
    ],
    "sg:phone":"+1 330 627 2844",
    "sg:postcode":"44615",
    "sg:province":"OH",
    "wof:name":"Grover Farms",
    "wof:placetype":"venue"
},
  "geometry": {"coordinates":[-81.067936,40.564396],"type":"Point"}
}