{
  "type": "Feature",
  "properties": {
    "addr:full": "4173 Bair Rd NW Dover OH 44622",
    "addr:postcode": "4173;44622",
    "addr:street": "Bair Rd Nw",
    "iso:country": "US",
    "sg:address": "4173 Bair Rd NW",
    "sg:city": "Dover",
    "sg:classifiers": [
      {
        "category": "Building \u0026 Trades",
        "subcategory": "Construction",
        "type": "Services"
      }
    ],
    "sg:phone": "+1 330 343 8031",
    "sg:postcode": "44622",
    "sg:province": "OH",
    "sg:tags": [
      "maker",
      "cabinet"
    ],
    "wof:name": "Harmon Hardwoods",
    "wof:placetype": "venue"
  },
  "geometry": {"coordinates":[-81.513218,40.542196],"type":"Point"}
}
