{
  "type": "Feature",
  "properties": {
    "iso:country":"US",
    "sg:address":"4173 Bair Rd NW",
    "sg:city":"Dover",
    "sg:classifiers":[
        {
            "category":"Building & Trades",
            "subcategory":"Construction",
            "type":"Services"
        }
    ],
    "sg:phone":"+1 330 343 8031",
    "sg:postcode":"44622",
    "sg:province":"OH",
    "sg:tags":[
        "maker",
        "cabinet"
    ],
    "wof:name":"Harmon Hardwoods",
    "wof:placetype":"venue"
},
  "geometry": {"coordinates":[-81.51321799999999,40.542196],"type":"Point"}
}