{
  "type": "Feature",
  "properties": {
    "addr:full":"4225 Leedom Hollow Zanesville OH 43701",
    "addr:housenumber":"4225",
    "addr:postcode":"43701",
    "addr:street":"Leedom Hollow",
    "iso:country":"US",
    "sg:address":"4225 Leedom Hollow",
    "sg:city":"Zanesville",
    "sg:classifiers":[
        {
            "category":"Farming",
            "subcategory":"Livestock Farm",
            "type":"Manufacturing & Wholesale Goods"
        }
    ],
    "sg:phone":"+1 740 796 3388",
    "sg:postcode":"43701",
    "sg:province":"OH",
    "sg:tags":[
        "beef",
        "corn",
        "crop",
        "field",
        "cattle",
        "feedlot"
    ],
    "wof:name":"T Leedom Farm",
    "wof:placetype":"venue"
},
  "geometry": {"coordinates":[-81.87994500000001,40.009732],"type":"Point"}
}