{
  "type": "Feature",
  "properties": {
    "addr:full": "10500 Quincy Ave Cleveland OH 44106",
    "addr:housenumber": "10500",
    "addr:postcode": "44106",
    "addr:street": "Quincy Ave",
    "iso:country": "US",
    "sg:address": "10500 Quincy Ave",
    "sg:city": "Cleveland",
    "sg:classifiers": [
      {
        "category": "Retail",
        "subcategory": "Car Wash",
        "type": "Services"
      }
    ],
    "sg:phone": "+1 216 231 7866",
    "sg:postcode": "44106",
    "sg:province": "OH",
    "sg:tags": [
      "polishing",
      "washing"
    ],
    "wof:name": "Dinero's Carwash",
    "wof:placetype": "venue"
  },
  "geometry": {"coordinates":[-81.616185,41.493383],"type":"Point"}
}
