{
  "type": "Feature",
  "properties": {
    "addr:full":"200 S Hamilton Rd Columbus OH 43230",
    "addr:housenumber":"200",
    "addr:postcode":"43230",
    "addr:street":"S Hamilton Rd",
    "iso:country":"US",
    "sg:address":"200 S Hamilton Rd",
    "sg:city":"Columbus",
    "sg:classifiers":[
        {
            "category":"Utilities",
            "subcategory":"Water",
            "type":"Services"
        }
    ],
    "sg:phone":"+1 614 471 3827",
    "sg:postcode":"43230",
    "sg:province":"OH",
    "sg:tags":[
        "supply"
    ],
    "wof:name":"Water Dept",
    "wof:placetype":"venue"
},
  "geometry": {"coordinates":[-82.86687999999999,40.013595],"type":"Point"}
}