{
  "type": "Feature",
  "properties": {
    "iso:country":"US",
    "sg:address":"1426 Scott Rd",
    "sg:city":"Mansfield",
    "sg:classifiers":[
        {
            "category":"Social Services",
            "subcategory":"Job Training",
            "type":"Services"
        }
    ],
    "sg:phone":"+1 419 566 5601",
    "sg:postcode":"44903",
    "sg:province":"OH",
    "sg:tags":[
        "rehabilitation"
    ],
    "wof:name":"Pro Rehab",
    "wof:placetype":"venue"
},
  "geometry": {"coordinates":[-82.459868,40.659989],"type":"Point"}
}