{
  "type": "Feature",
  "properties": {
    "addr:full":"300 N Freedom St Ravenna OH 44266",
    "addr:housenumber":"300",
    "addr:postcode":"44266",
    "addr:street":"N Freedom St",
    "iso:country":"US",
    "sg:address":"300 N Freedom St",
    "sg:city":"Ravenna",
    "sg:classifiers":[
        {
            "category":"Professional",
            "subcategory":"Accounting & Tax Preparation",
            "type":"Services"
        }
    ],
    "sg:phone":"+1 330 296 8085",
    "sg:postcode":"44266",
    "sg:province":"OH",
    "sg:tags":[
        "return",
        "filing"
    ],
    "wof:name":"Tilden's Tax Svc",
    "wof:placetype":"venue"
},
  "geometry": {"coordinates":[-81.233108,41.160508],"type":"Point"}
}