{
  "type": "Feature",
  "properties": {
    "iso:country":"US",
    "sg:address":"28790 White Rd",
    "sg:city":"Perrysburg",
    "sg:classifiers":[
        {
            "category":"Building & Trades",
            "subcategory":"Construction",
            "type":"Services"
        }
    ],
    "sg:phone":"+1 419 873 8618",
    "sg:postcode":"43551",
    "sg:province":"OH",
    "sg:tags":[
        "house"
    ],
    "wof:name":"Skergan Construction",
    "wof:placetype":"venue"
},
  "geometry": {"coordinates":[-83.596433,41.569001],"type":"Point"}
}