{
  "type": "Feature",
  "properties": {
    "addr:full":"23880 Commerce Park Rd Cleveland OH 44122",
    "addr:housenumber":"23880",
    "addr:postcode":"44122",
    "addr:street":"Commerce Park Rd",
    "iso:country":"US",
    "sg:address":"23880 Commerce Park Rd",
    "sg:city":"Cleveland",
    "sg:classifiers":[
        {
            "category":"Professional",
            "subcategory":"Research",
            "type":"Services"
        }
    ],
    "sg:phone":"+1 216 831 4227",
    "sg:postcode":"44122",
    "sg:province":"OH",
    "sg:tags":[
        "development",
        "laboratory",
        "commercial",
        "physical"
    ],
    "wof:name":"Fibrateck Scientific",
    "wof:placetype":"venue"
},
  "geometry": {"coordinates":[-81.513902,41.461087],"type":"Point"}
}