{
  "type": "Feature",
  "properties": {
    "addr:full": "1195 Parsons Ave Columbus OH 43206",
    "addr:housenumber": "1195",
    "addr:postcode": "43206",
    "addr:street": "Parsons Ave",
    "iso:country": "US",
    "sg:address": "1195 Parsons Ave",
    "sg:city": "Columbus",
    "sg:classifiers": [
      {
        "category": "Retail",
        "subcategory": "Repair Shop",
        "type": "Services"
      }
    ],
    "sg:phone": "+1 614 449 0443",
    "sg:postcode": "43206",
    "sg:province": "OH",
    "sg:tags": [
      "antique",
      "restoring"
    ],
    "wof:name": "Quality Furniture Refinishing",
    "wof:placetype": "venue"
  },
  "geometry": {"coordinates":[-82.983482,39.938421],"type":"Point"}
}
