{
  "type": "Feature",
  "properties": {
    "iso:country":"US",
    "sg:address":"811 S Main St",
    "sg:city":"Lima",
    "sg:classifiers":[
        {
            "category":"Home & Garden",
            "subcategory":"Furniture",
            "type":"Retail Goods"
        }
    ],
    "sg:phone":"+1 419 222 1544",
    "sg:postcode":"45804",
    "sg:province":"OH",
    "wof:name":"Chris's New & Used Furniture",
    "wof:placetype":"venue"
},
  "geometry": {"coordinates":[-84.104957,40.727718],"type":"Point"}
}