{
  "type": "Feature",
  "properties": {
    "addr:full":"415 S Broadway St Medina OH 44256",
    "addr:housenumber":"415",
    "addr:postcode":"44256",
    "addr:street":"S Broadway St",
    "iso:country":"US",
    "sg:address":"415 S Broadway St",
    "sg:city":"Medina",
    "sg:classifiers":[
        {
            "category":"Personal",
            "subcategory":"Tattoo Parlor",
            "type":"Services"
        }
    ],
    "sg:phone":"+1 330 725 8282",
    "sg:postcode":"44256",
    "sg:province":"OH",
    "sg:tags":[
        "tattooing"
    ],
    "wof:name":"Art In Motion Tattoos",
    "wof:placetype":"venue"
},
  "geometry": {"coordinates":[-81.862683,41.134443],"type":"Point"}
}