{
  "type": "Feature",
  "properties": {
    "iso:country":"US",
    "sg:address":"13 S Main St",
    "sg:city":"Rittman",
    "sg:classifiers":[
        {
            "category":"Personal",
            "subcategory":"Tanning Parlor",
            "type":"Services"
        }
    ],
    "sg:phone":"+1 330 925 6245",
    "sg:postcode":"44270",
    "sg:province":"OH",
    "sg:tags":[
        "salon"
    ],
    "wof:name":"A New You Tanning Salon",
    "wof:placetype":"venue"
},
  "geometry": {"coordinates":[-81.781587,40.972471],"type":"Point"}
}