{
  "type": "Feature",
  "properties": {
    "addr:full": "4035 W Central Ave Toledo OH 43606",
    "addr:housenumber": "4035",
    "addr:postcode": "43606",
    "addr:street": "W Central Ave",
    "iso:country": "US",
    "sg:address": "4035 W Central Ave",
    "sg:city": "Toledo",
    "sg:classifiers": [
      {
        "category": "Health Services",
        "subcategory": "Health Practitioner",
        "type": "Services"
      }
    ],
    "sg:phone": "+1 419 531 3003",
    "sg:postcode": "43606",
    "sg:province": "OH",
    "sg:tags": [
      "therapist",
      "physical"
    ],
    "wof:name": "Spin Care \u0026 Rehabilitation Ctr",
    "wof:placetype": "venue"
  },
  "geometry": {"coordinates":[-83.639584,41.677016],"type":"Point"}
}
