{
  "type": "Feature",
  "properties": {
    "iso:country":"US",
    "sg:address":"4035 W Central Ave",
    "sg:city":"Toledo",
    "sg:classifiers":[
        {
            "category":"Health Services",
            "subcategory":"Health Practitioner",
            "type":"Services"
        }
    ],
    "sg:phone":"+1 419 531 3003",
    "sg:postcode":"43606",
    "sg:province":"OH",
    "sg:tags":[
        "therapist",
        "physical"
    ],
    "wof:name":"Spin Care & Rehabilitation Ctr",
    "wof:placetype":"venue"
},
  "geometry": {"coordinates":[-83.639584,41.677016],"type":"Point"}
}