{
  "type": "Feature",
  "properties": {
    "iso:country":"US",
    "sg:address":"6809 W Chester Rd",
    "sg:city":"West Chester",
    "sg:classifiers":[
        {
            "category":"Building & Trades",
            "subcategory":"Landscaping Services",
            "type":"Services"
        }
    ],
    "sg:phone":"+1 513 759 0541",
    "sg:postcode":"45069",
    "sg:province":"OH",
    "wof:name":"Greenstar Lawn Care Svc Inc",
    "wof:placetype":"venue"
},
  "geometry": {"coordinates":[-84.409942,39.325194],"type":"Point"}
}