{
  "type": "Feature",
  "properties": {
    "addr:full": "9005 Darrow Rd Twinsburg OH 44087",
    "addr:housenumber": "9005",
    "addr:postcode": "44087",
    "addr:street": "Darrow Rd",
    "iso:country": "US",
    "sg:address": "9005 Darrow Rd",
    "sg:city": "Twinsburg",
    "sg:classifiers": [
      {
        "category": "Real Estate",
        "subcategory": "Real Estate Agent",
        "type": "Services"
      }
    ],
    "sg:phone": "+1 330 425 4282",
    "sg:postcode": "44087",
    "sg:province": "OH",
    "wof:name": "Realty Executives Northstar Hm",
    "wof:placetype": "venue"
  },
  "geometry": {"coordinates":[-81.44018,41.308917],"type":"Point"}
}
