{
  "type": "Feature",
  "properties": {
    "addr:full":"3830 Skyview Dr Brunswick OH 44212",
    "addr:housenumber":"3830",
    "addr:postcode":"44212",
    "addr:street":"Skyview Dr",
    "iso:country":"US",
    "sg:address":"3830 Skyview Dr",
    "sg:city":"Brunswick",
    "sg:classifiers":[
        {
            "category":"Professional",
            "subcategory":"Business Services",
            "type":"Services"
        }
    ],
    "sg:phone":"+1 330 273 1282",
    "sg:postcode":"44212",
    "sg:province":"OH",
    "sg:tags":[
        "appraiser"
    ],
    "wof:name":"Wanner & Co Inc",
    "wof:placetype":"venue"
},
  "geometry": {"coordinates":[-81.82383,41.27326],"type":"Point"}
}