{
  "type": "Feature",
  "properties": {
    "addr:full": "7850 Mentor Ave Mentor OH 44060",
    "addr:housenumber": "7850",
    "addr:postcode": "44060",
    "addr:street": "Mentor Ave",
    "iso:country": "US",
    "sg:address": "7850 Mentor Ave",
    "sg:city": "Mentor",
    "sg:classifiers": [
      {
        "category": "Utilities",
        "subcategory": "Mobile Phone",
        "type": "Services"
      }
    ],
    "sg:phone": "+1 440 266 1707",
    "sg:postcode": "44060",
    "sg:province": "OH",
    "sg:tags": [
      "telephone",
      "cellular"
    ],
    "wof:name": "Always Cellular Inc",
    "wof:placetype": "venue"
  },
  "geometry": {"coordinates":[-81.362095,41.660627],"type":"Point"}
}
