{
  "type": "Feature",
  "properties": {
    "addr:full": "221 W Rosewood Ave Defiance OH 43512",
    "addr:housenumber": "221",
    "addr:postcode": "43512",
    "addr:street": "W Rosewood Ave",
    "iso:country": "US",
    "sg:address": "221 W Rosewood Ave",
    "sg:city": "Defiance",
    "sg:classifiers": [
      {
        "category": "Restaurant",
        "type": "Food \u0026 Drink"
      }
    ],
    "sg:phone": "+1 419 782 7880",
    "sg:postcode": "43512",
    "sg:province": "OH",
    "sg:tags": [
      "eating"
    ],
    "wof:name": "Pizzos Pizza",
    "wof:placetype": "venue"
  },
  "geometry": {"coordinates":[-84.363742,41.258423],"type":"Point"}
}
