{
  "type": "Feature",
  "properties": {
    "addr:full": "463 Tiffin Ave Findlay OH 45840",
    "addr:housenumber": "463",
    "addr:postcode": "45840",
    "addr:street": "Tiffin Ave",
    "iso:country": "US",
    "sg:address": "463 Tiffin Ave",
    "sg:city": "Findlay",
    "sg:classifiers": [
      {
        "category": "Shopping",
        "subcategory": "Pharmacy",
        "type": "Retail Goods"
      }
    ],
    "sg:phone": "+1 419 422 3192",
    "sg:postcode": "45840",
    "sg:province": "OH",
    "wof:name": "CVS Pharmacy Toledo",
    "wof:placetype": "venue"
  },
  "geometry": {"coordinates":[-83.642658,41.044651],"type":"Point"}
}
