{
  "type": "Feature",
  "properties": {
    "iso:country":"US",
    "sg:address":"463 Tiffin Ave",
    "sg:city":"Findlay",
    "sg:classifiers":[
        {
            "category":"Shopping",
            "subcategory":"Pharmacy",
            "type":"Retail Goods"
        }
    ],
    "sg:phone":"+1 419 422 3192",
    "sg:postcode":"45840",
    "sg:province":"OH",
    "wof:name":"CVS Pharmacy Toledo",
    "wof:placetype":"venue"
},
  "geometry": {"coordinates":[-83.642658,41.044651],"type":"Point"}
}