{
  "type": "Feature",
  "properties": {
    "addr:full": "68 Worthington Mall Columbus OH 43085",
    "addr:housenumber": "68",
    "addr:postcode": "43085",
    "addr:street": "Worthington Mall",
    "iso:country": "US",
    "sg:address": "68 Worthington Mall",
    "sg:city": "Columbus",
    "sg:classifiers": [
      {
        "category": "Food \u0026 Beverages",
        "subcategory": "Meat \u0026 Fish",
        "type": "Retail Goods"
      }
    ],
    "sg:phone": "+1 614 888 5190",
    "sg:postcode": "43085",
    "sg:province": "OH",
    "wof:name": "Omaha Steaks",
    "wof:placetype": "venue"
  },
  "geometry": {"coordinates":[-83.01728,40.10792],"type":"Point"}
}
