{
  "type": "Feature",
  "properties": {
    "iso:country":"US",
    "sg:address":"25336 Co Rd 10",
    "sg:city":"Coshocton",
    "sg:classifiers":[
        {
            "category":"Home & Garden",
            "subcategory":"Garden Supply",
            "type":"Retail Goods"
        }
    ],
    "sg:phone":"+1 740 622 6452",
    "sg:postcode":"43812",
    "sg:province":"OH",
    "sg:tags":[
        "center"
    ],
    "wof:name":"Garden Patch",
    "wof:placetype":"venue"
},
  "geometry": {"coordinates":[-81.808766,40.320149],"type":"Point"}
}