{
  "type": "Feature",
  "properties": {
    "addr:full": "25336 Co Rd 10 Coshocton OH 43812",
    "addr:housenumber": "25336;10",
    "addr:postcode": "43812",
    "addr:street": "Co Rd",
    "iso:country": "US",
    "sg:address": "25336 Co Rd 10",
    "sg:city": "Coshocton",
    "sg:classifiers": [
      {
        "category": "Home \u0026 Garden",
        "subcategory": "Garden Supply",
        "type": "Retail Goods"
      }
    ],
    "sg:phone": "+1 740 622 6452",
    "sg:postcode": "43812",
    "sg:province": "OH",
    "sg:tags": [
      "center"
    ],
    "wof:name": "Garden Patch",
    "wof:placetype": "venue"
  },
  "geometry": {"coordinates":[-81.808766,40.320149],"type":"Point"}
}
