{
  "type": "Feature",
  "properties": {
    "addr:full": "14370 Chapel Hill Rd SE Corning OH 43730",
    "addr:housenumber": "14370",
    "addr:postcode": "43730",
    "addr:street": "Chapel Hill Rd Se",
    "iso:country": "US",
    "sg:address": "14370 Chapel Hill Rd SE",
    "sg:city": "Corning",
    "sg:classifiers": [
      {
        "category": "Professional",
        "type": "Services"
      }
    ],
    "sg:phone": "+1 740 347 4217",
    "sg:postcode": "43730",
    "sg:province": "OH",
    "wof:name": "Pond Side Pottery",
    "wof:placetype": "venue"
  },
  "geometry": {"coordinates":[-82.059811,39.620984],"type":"Point"}
}
