{
  "type": "Feature",
  "properties": {
    "iso:country":"US",
    "sg:address":"2036 State Rte 725",
    "sg:city":"Spring Valley",
    "sg:classifiers":[
        {
            "category":"Professional",
            "subcategory":"Management & Consulting",
            "type":"Services"
        }
    ],
    "sg:phone":"+1 937 862 8663",
    "sg:postcode":"45370",
    "sg:province":"OH",
    "sg:tags":[
        "construction"
    ],
    "wof:name":"M J Coates Construction",
    "wof:placetype":"venue"
},
  "geometry": {"coordinates":[-84.013569,39.619421],"type":"Point"}
}