{
  "type": "Feature",
  "properties": {
    "addr:full": "2036 State Rte 725 Spring Valley OH 45370",
    "addr:housenumber": "2036",
    "addr:postcode": "45370",
    "addr:street": "State Rte 725",
    "iso:country": "US",
    "sg:address": "2036 State Rte 725",
    "sg:city": "Spring Valley",
    "sg:classifiers": [
      {
        "category": "Professional",
        "subcategory": "Management \u0026 Consulting",
        "type": "Services"
      }
    ],
    "sg:phone": "+1 937 862 8663",
    "sg:postcode": "45370",
    "sg:province": "OH",
    "sg:tags": [
      "construction"
    ],
    "wof:name": "M J Coates Construction",
    "wof:placetype": "venue"
  },
  "geometry": {"coordinates":[-84.013569,39.619421],"type":"Point"}
}
