{
  "type": "Feature",
  "properties": {
    "iso:country":"US",
    "sg:address":"18746 Gauche Rd",
    "sg:city":"Fayetteville",
    "sg:classifiers":[
        {
            "category":"Banks & Credit Unions",
            "subcategory":"Financial Services",
            "type":"Services"
        }
    ],
    "sg:phone":"+1 513 875 3206",
    "sg:postcode":"45118",
    "sg:province":"OH",
    "sg:tags":[
        "investor"
    ],
    "wof:name":"Rossaveel Investments Ltd",
    "wof:placetype":"venue"
},
  "geometry": {"coordinates":[-83.934735,39.155115],"type":"Point"}
}