{
  "type": "Feature",
  "properties": {
    "iso:country":"US",
    "sg:address":"8941 Weitz Rd",
    "sg:city":"Celina",
    "sg:classifiers":[
        {
            "category":"Freight",
            "type":"Transportation"
        }
    ],
    "sg:phone":"+1 419 363 3829",
    "sg:postcode":"45822",
    "sg:province":"OH",
    "sg:tags":[
        "operator",
        "local",
        "trucking"
    ],
    "wof:name":"Clifford & Sons Trucking",
    "wof:placetype":"venue"
},
  "geometry": {"coordinates":[-84.590309,40.601189],"type":"Point"}
}