{
  "type": "Feature",
  "properties": {
    "iso:country":"US",
    "sg:address":"720 Welker Dr",
    "sg:city":"West Lafayette",
    "sg:classifiers":[
        {
            "category":"Health Services",
            "subcategory":"Clinic",
            "type":"Services"
        }
    ],
    "sg:phone":"+1 740 545 7677",
    "sg:postcode":"43845",
    "sg:province":"OH",
    "sg:tags":[
        "home"
    ],
    "wof:name":"Heartfelt Homecare",
    "wof:placetype":"venue"
},
  "geometry": {"coordinates":[-81.742941,40.268374],"type":"Point"}
}