{
  "type": "Feature",
  "properties": {
    "iso:country":"US",
    "sg:address":"3528 E 131st St",
    "sg:city":"Cleveland",
    "sg:classifiers":[
        {
            "category":"Retail",
            "subcategory":"Laundry & Dry Cleaning",
            "type":"Services"
        }
    ],
    "sg:phone":"+1 216 491 8644",
    "sg:postcode":"44120",
    "sg:province":"OH",
    "sg:tags":[
        "cleaners"
    ],
    "wof:name":"Mayfair Satellite Dry Cleaners",
    "wof:placetype":"venue"
},
  "geometry": {"coordinates":[-81.591173,41.46374],"type":"Point"}
}