{
  "type": "Feature",
  "properties": {
    "addr:full": "155 Pierce Ave Cuyahoga Falls OH 44221",
    "addr:housenumber": "155",
    "addr:postcode": "44221",
    "addr:street": "Pierce Ave",
    "iso:country": "US",
    "sg:address": "155 Pierce Ave",
    "sg:city": "Cuyahoga Falls",
    "sg:classifiers": [
      {
        "category": "Building \u0026 Trades",
        "subcategory": "Plumbing",
        "type": "Services"
      }
    ],
    "sg:phone": "+1 330 929 0803",
    "sg:postcode": "44221",
    "sg:province": "OH",
    "sg:tags": [
      "contractor"
    ],
    "wof:name": "Thomas Plumbing \u0026 Backflow",
    "wof:placetype": "venue"
  },
  "geometry": {"coordinates":[-81.485151,41.152367],"type":"Point"}
}
