{
  "type": "Feature",
  "properties": {
    "iso:country":"US",
    "sg:address":"9509 Frank Rd",
    "sg:city":"Port Washington",
    "sg:classifiers":[
        {
            "category":"Manufacturing",
            "subcategory":"Apparel",
            "type":"Manufacturing & Wholesale Goods"
        }
    ],
    "sg:phone":"+1 740 498 7617",
    "sg:postcode":"43837",
    "sg:province":"OH",
    "wof:name":"Ginnys Embroidrey",
    "wof:placetype":"venue"
},
  "geometry": {"coordinates":[-81.54494800000001,40.345618],"type":"Point"}
}