{
  "type": "Feature",
  "properties": {
    "addr:full": "9509 Frank Rd Port Washington OH 43837",
    "addr:housenumber": "9509",
    "addr:postcode": "43837",
    "addr:street": "Frank Rd",
    "iso:country": "US",
    "sg:address": "9509 Frank Rd",
    "sg:city": "Port Washington",
    "sg:classifiers": [
      {
        "category": "Manufacturing",
        "subcategory": "Apparel",
        "type": "Manufacturing \u0026 Wholesale Goods"
      }
    ],
    "sg:phone": "+1 740 498 7617",
    "sg:postcode": "43837",
    "sg:province": "OH",
    "wof:name": "Ginnys Embroidrey",
    "wof:placetype": "venue"
  },
  "geometry": {"coordinates":[-81.544948,40.345618],"type":"Point"}
}
