{
  "type": "Feature",
  "properties": {
    "addr:full": "4250 W Alexis Rd Toledo OH 43623",
    "addr:housenumber": "4250",
    "addr:postcode": "43623",
    "addr:street": "W Alexis Rd",
    "iso:country": "US",
    "sg:address": "4250 W Alexis Rd",
    "sg:city": "Toledo",
    "sg:classifiers": [
      {
        "category": "Cinema",
        "subcategory": "Movie Rental",
        "type": "Entertainment"
      }
    ],
    "sg:phone": "+1 419 475 2490",
    "sg:postcode": "43623",
    "sg:province": "OH",
    "sg:tags": [
      "video",
      "game",
      "leasing"
    ],
    "sg:website": "www.familyvideo.net",
    "wof:name": "Family Video",
    "wof:placetype": "venue"
  },
  "geometry": {"coordinates":[-83.645443,41.720341],"type":"Point"}
}
