{
  "type": "Feature",
  "properties": {
    "addr:full":"2100 Morse Rd Columbus OH 43229",
    "addr:housenumber":"2100",
    "addr:postcode":"43229",
    "addr:street":"Morse Rd",
    "iso:country":"US",
    "sg:address":"2100 Morse Rd",
    "sg:city":"Columbus",
    "sg:classifiers":[
        {
            "category":"Building & Trades",
            "subcategory":"Equipment Rental",
            "type":"Services"
        }
    ],
    "sg:phone":"+1 614 436 0538",
    "sg:postcode":"43229",
    "sg:province":"OH",
    "sg:tags":[
        "leasing"
    ],
    "wof:name":"Showplace Lease Purchase",
    "wof:placetype":"venue"
},
  "geometry": {"coordinates":[-82.96249400000001,40.060112],"type":"Point"}
}