{
  "type": "Feature",
  "properties": {
    "iso:country":"US",
    "sg:address":"4251 Vilamoura Dr",
    "sg:city":"Avon",
    "sg:classifiers":[
        {
            "category":"Real Estate",
            "subcategory":"Architect",
            "type":"Services"
        }
    ],
    "sg:phone":"+1 440 937 7721",
    "sg:postcode":"44011",
    "sg:province":"OH",
    "wof:name":"Corna Architects-Architectural",
    "wof:placetype":"venue"
},
  "geometry": {"coordinates":[-81.99388999999999,41.421762],"type":"Point"}
}