{
  "type": "Feature",
  "properties": {
    "addr:full":"7393 W Western Reserve Rd Canfield OH 44406",
    "addr:housenumber":"7393",
    "addr:postcode":"44406",
    "addr:street":"W Western Reserve Rd",
    "iso:country":"US",
    "sg:address":"7393 W Western Reserve Rd",
    "sg:city":"Canfield",
    "sg:phone":"+1 330 533 5821",
    "sg:postcode":"44406",
    "sg:province":"OH",
    "sg:tags":[
        "farm",
        "corn"
    ],
    "wof:name":"Moore Farms",
    "wof:placetype":"venue"
},
  "geometry": {"coordinates":[-80.78833299999999,40.988196],"type":"Point"}
}