{
  "type": "Feature",
  "properties": {
    "iso:country":"US",
    "sg:address":"6503 Marion-Melmore Rd",
    "sg:city":"Sycamore",
    "sg:classifiers":[
        {
            "category":"Government",
            "subcategory":"Office",
            "type":"Public Place"
        }
    ],
    "sg:phone":"+1 419 927 4531",
    "sg:postcode":"44882",
    "sg:province":"OH",
    "sg:tags":[
        "executive"
    ],
    "wof:name":"Township of Texas",
    "wof:placetype":"venue"
},
  "geometry": {"coordinates":[-83.093358,40.941689],"type":"Point"}
}