{
  "type": "Feature",
  "properties": {
    "addr:full": "1316 Oak Harbor Rd Fremont OH 43420",
    "addr:housenumber": "1316",
    "addr:postcode": "43420",
    "addr:street": "Oak Harbor Rd",
    "iso:country": "US",
    "sg:address": "1316 Oak Harbor Rd",
    "sg:city": "Fremont",
    "sg:classifiers": [
      {
        "category": "Food \u0026 Beverages",
        "subcategory": "Groceries \u0026 Convenience Stores",
        "type": "Retail Goods"
      }
    ],
    "sg:phone": "+1 419 332 7985",
    "sg:postcode": "43420",
    "sg:province": "OH",
    "sg:website": "www.kroger.com",
    "wof:name": "Kroger",
    "wof:placetype": "venue"
  },
  "geometry": {"coordinates":[-83.136774,41.361306],"type":"Point"}
}
