{
  "type": "Feature",
  "properties": {
    "iso:country":"US",
    "sg:address":"1316 Oak Harbor Rd",
    "sg:city":"Fremont",
    "sg:classifiers":[
        {
            "category":"Food & Beverages",
            "subcategory":"Groceries & Convenience Stores",
            "type":"Retail Goods"
        }
    ],
    "sg:phone":"+1 419 332 7985",
    "sg:postcode":"43420",
    "sg:province":"OH",
    "sg:website":"www.kroger.com",
    "wof:name":"Kroger",
    "wof:placetype":"venue"
},
  "geometry": {"coordinates":[-83.136774,41.361306],"type":"Point"}
}