{
  "type": "Feature",
  "properties": {
    "addr:full": "12003 Abbey Rd Cleveland OH 44133",
    "addr:housenumber": "12003",
    "addr:postcode": "44133",
    "addr:street": "Abbey Rd",
    "iso:country": "US",
    "sg:address": "12003 Abbey Rd",
    "sg:city": "Cleveland",
    "sg:classifiers": [
      {
        "category": "Retail",
        "subcategory": "Repair Shop",
        "type": "Services"
      }
    ],
    "sg:phone": "+1 440 582 5950",
    "sg:postcode": "44133",
    "sg:province": "OH",
    "sg:tags": [
      "tool",
      "grinding"
    ],
    "wof:name": "D \u0026 J Tools Inc",
    "wof:placetype": "venue"
  },
  "geometry": {"coordinates":[-81.7747,41.319654],"type":"Point"}
}
