{
  "type": "Feature",
  "properties": {
    "iso:country":"US",
    "sg:address":"630 Dover Center Rd",
    "sg:city":"Cleveland",
    "sg:classifiers":[
        {
            "category":"Government",
            "subcategory":"Post Office",
            "type":"Public Place"
        }
    ],
    "sg:phone":"+1 440 000 1111",
    "sg:postcode":"44140",
    "sg:province":"OH",
    "wof:name":"US Post Office",
    "wof:placetype":"venue"
},
  "geometry": {"coordinates":[-81.921151,41.478629],"type":"Point"}
}