{
  "type": "Feature",
  "properties": {
    "addr:full": "2025 US Hwy 62 NE Washington Ct Hs OH 43160",
    "addr:housenumber": "2025",
    "addr:postcode": "43160",
    "addr:street": "Us Hwy 62 Ne",
    "iso:country": "US",
    "sg:address": "2025 US Hwy 62 NE",
    "sg:city": "Washington Ct Hs",
    "sg:classifiers": [
      {
        "category": "Retail",
        "subcategory": "Laundry \u0026 Dry Cleaning",
        "type": "Services"
      }
    ],
    "sg:phone": "+1 740 335 0550",
    "sg:postcode": "43160",
    "sg:province": "OH",
    "sg:tags": [
      "cleaners"
    ],
    "wof:name": "Bob's Dry Cleaning",
    "wof:placetype": "venue"
  },
  "geometry": {"coordinates":[-83.420184,39.553273],"type":"Point"}
}
