{
  "type": "Feature",
  "properties": {
    "addr:full":"2271 Lee Rd Cleveland OH 44118",
    "addr:housenumber":"2271",
    "addr:postcode":"44118",
    "addr:street":"Lee Rd",
    "iso:country":"US",
    "sg:address":"2271 Lee Rd",
    "sg:city":"Cleveland",
    "sg:classifiers":[
        {
            "category":"Home & Garden",
            "subcategory":"Hardware",
            "type":"Retail Goods"
        }
    ],
    "sg:phone":"+1 216 321 4630",
    "sg:postcode":"44118",
    "sg:province":"OH",
    "wof:name":"Seitz-Agin Hardware Co",
    "wof:placetype":"venue"
},
  "geometry": {"coordinates":[-81.565286,41.498702],"type":"Point"}
}