{
  "type": "Feature",
  "properties": {
    "addr:full": "1375 Chickasaw Dr London OH 43140",
    "addr:housenumber": "1375",
    "addr:postcode": "43140",
    "addr:street": "Chickasaw Dr",
    "iso:country": "US",
    "sg:address": "1375 Chickasaw Dr",
    "sg:city": "London",
    "sg:classifiers": [
      {
        "category": "Building \u0026 Trades",
        "subcategory": "Construction",
        "type": "Services"
      }
    ],
    "sg:phone": "+1 740 852 5958",
    "sg:postcode": "43140",
    "sg:province": "OH",
    "sg:tags": [
      "house"
    ],
    "wof:name": "D J Builders",
    "wof:placetype": "venue"
  },
  "geometry": {"coordinates":[-83.494745,39.951994],"type":"Point"}
}
