{
  "type": "Feature",
  "properties": {
    "addr:full":"323 High St Wadsworth OH 44281",
    "addr:housenumber":"323",
    "addr:postcode":"44281",
    "addr:street":"High St",
    "iso:country":"US",
    "sg:address":"323 High St",
    "sg:city":"Wadsworth",
    "sg:classifiers":[
        {
            "category":"Health Services",
            "subcategory":"Podiatrist",
            "type":"Services"
        }
    ],
    "sg:phone":"+1 330 336 7075",
    "sg:postcode":"44281",
    "sg:province":"OH",
    "wof:name":"Wadsworth Foot & Ankle",
    "wof:placetype":"venue"
},
  "geometry": {"coordinates":[-81.729612,41.031616],"type":"Point"}
}