{
  "type": "Feature",
  "properties": {
    "iso:country":"US",
    "sg:address":"244 9th St",
    "sg:city":"Elyria",
    "sg:classifiers":[
        {
            "category":"Organizations",
            "subcategory":"Religious Organization",
            "type":"Services"
        }
    ],
    "sg:phone":"+1 440 322 2703",
    "sg:postcode":"44035",
    "sg:province":"OH",
    "sg:tags":[
        "church"
    ],
    "wof:name":"Good Shepherd Baptist Church",
    "wof:placetype":"venue"
},
  "geometry": {"coordinates":[-82.107264,41.358624],"type":"Point"}
}