{
  "type": "Feature",
  "properties": {
    "iso:country":"US",
    "sg:address":"1600 Hunter Ave",
    "sg:city":"Niles",
    "sg:classifiers":[
        {
            "category":"Manufacturing",
            "subcategory":"Tools & Machinery",
            "type":"Manufacturing & Wholesale Goods"
        }
    ],
    "sg:phone":"+1 330 505 0296",
    "sg:postcode":"44446",
    "sg:province":"OH",
    "sg:tags":[
        "repair",
        "industrial",
        "fabrication",
        "mach",
        "custom"
    ],
    "wof:name":"Reichard Industries Inc",
    "wof:placetype":"venue"
},
  "geometry": {"coordinates":[-80.774869,41.186523],"type":"Point"}
}