{
  "type": "Feature",
  "properties": {
    "addr:full": "1600 Hunter Ave Niles OH 44446",
    "addr:housenumber": "1600",
    "addr:postcode": "44446",
    "addr:street": "Hunter Ave",
    "iso:country": "US",
    "sg:address": "1600 Hunter Ave",
    "sg:city": "Niles",
    "sg:classifiers": [
      {
        "category": "Manufacturing",
        "subcategory": "Tools \u0026 Machinery",
        "type": "Manufacturing \u0026 Wholesale Goods"
      }
    ],
    "sg:phone": "+1 330 505 0296",
    "sg:postcode": "44446",
    "sg:province": "OH",
    "sg:tags": [
      "repair",
      "industrial",
      "fabrication",
      "mach",
      "custom"
    ],
    "wof:name": "Reichard Industries Inc",
    "wof:placetype": "venue"
  },
  "geometry": {"coordinates":[-80.774869,41.186523],"type":"Point"}
}
