{
  "type": "Feature",
  "properties": {
    "iso:country":"US",
    "sg:address":"23 S Mulberry St",
    "sg:city":"Troy",
    "sg:classifiers":[
        {
            "category":"Professional",
            "subcategory":"Business Services",
            "type":"Services"
        }
    ],
    "sg:phone":"+1 937 335 7583",
    "sg:postcode":"45373",
    "sg:province":"OH",
    "sg:tags":[
        "interior",
        "consultant",
        "design",
        "decorator"
    ],
    "wof:name":"Troy Design Assoc",
    "wof:placetype":"venue"
},
  "geometry": {"coordinates":[-84.20194600000001,40.037971],"type":"Point"}
}