{
  "type": "Feature",
  "properties": {
    "addr:full": "2401 Vine St Cincinnati OH 45219",
    "addr:housenumber": "2401",
    "addr:postcode": "45219",
    "addr:street": "Vine St",
    "iso:country": "US",
    "sg:address": "2401 Vine St",
    "sg:city": "Cincinnati",
    "sg:classifiers": [
      {
        "category": "Bars \u0026 Pubs",
        "type": "Food \u0026 Drink"
      }
    ],
    "sg:phone": "+1 513 721 8484",
    "sg:postcode": "45219",
    "sg:province": "OH",
    "wof:name": "Little Bit Bar",
    "wof:placetype": "venue"
  },
  "geometry": {"coordinates":[-84.51263,39.126273],"type":"Point"}
}
