{
  "type": "Feature",
  "properties": {
    "iso:country":"US",
    "sg:address":"2401 Vine St",
    "sg:city":"Cincinnati",
    "sg:classifiers":[
        {
            "category":"Bars & Pubs",
            "type":"Food & Drink"
        }
    ],
    "sg:phone":"+1 513 721 8484",
    "sg:postcode":"45219",
    "sg:province":"OH",
    "wof:name":"Little Bit Bar",
    "wof:placetype":"venue"
},
  "geometry": {"coordinates":[-84.51263,39.126273],"type":"Point"}
}