{
  "type": "Feature",
  "properties": {
    "iso:country":"US",
    "sg:address":"376 E Beech St",
    "sg:city":"Jefferson",
    "sg:classifiers":[
        {
            "category":"Government",
            "subcategory":"Office",
            "type":"Public Place"
        },
        {
            "category":"Professional",
            "subcategory":"Computer Services",
            "type":"Services"
        }
    ],
    "sg:phone":"+1 440 576 1554",
    "sg:postcode":"44047",
    "sg:province":"OH",
    "sg:tags":[
        "website",
        "agricultural",
        "regulation",
        "design",
        "marketing"
    ],
    "wof:name":"Extension Express of Ohio LLC",
    "wof:placetype":"venue"
},
  "geometry": {"coordinates":[-80.760299,41.746379],"type":"Point"}
}