{
  "type": "Feature",
  "properties": {
    "iso:country":"US",
    "sg:address":"2744 Cleveland Ave NW",
    "sg:city":"Canton",
    "sg:classifiers":[
        {
            "category":"Wholesale",
            "subcategory":"Auto Parts",
            "type":"Manufacturing & Wholesale Goods"
        }
    ],
    "sg:phone":"+1 330 453 4525",
    "sg:postcode":"44709",
    "sg:province":"OH",
    "sg:tags":[
        "body",
        "automobile",
        "shop"
    ],
    "wof:name":"API",
    "wof:placetype":"venue"
},
  "geometry": {"coordinates":[-81.38662100000001,40.829691],"type":"Point"}
}