{
  "type": "Feature",
  "properties": {
    "iso:country":"US",
    "sg:address":"5597 Westerville Rd",
    "sg:city":"Westerville",
    "sg:classifiers":[
        {
            "category":"Autos & Motor Vehicles",
            "subcategory":"Automobile Sales",
            "type":"Retail Goods"
        }
    ],
    "sg:phone":"+1 614 895 7919",
    "sg:postcode":"43081",
    "sg:province":"OH",
    "sg:tags":[
        "car",
        "dealer"
    ],
    "wof:name":"Brandywine Auto Sales Too",
    "wof:placetype":"venue"
},
  "geometry": {"coordinates":[-82.926811,40.088009],"type":"Point"}
}