{
  "type": "Feature",
  "properties": {
    "iso:country":"US",
    "sg:address":"849 W Main St",
    "sg:city":"Kent",
    "sg:classifiers":[
        {
            "category":"Wholesale",
            "subcategory":"Machinery & Supplies",
            "type":"Manufacturing & Wholesale Goods"
        }
    ],
    "sg:phone":"+1 330 673 8886",
    "sg:postcode":"44240",
    "sg:province":"OH",
    "sg:tags":[
        "tool"
    ],
    "wof:name":"Components & Equipment Co",
    "wof:placetype":"venue"
},
  "geometry": {"coordinates":[-81.376274,41.152002],"type":"Point"}
}