{
  "type": "Feature",
  "properties": {
    "addr:full":"38238 Glenn Ave Willoughby OH 44094",
    "addr:housenumber":"38238",
    "addr:postcode":"44094",
    "addr:street":"Glenn Ave",
    "iso:country":"US",
    "sg:address":"38238 Glenn Ave",
    "sg:city":"Willoughby",
    "sg:classifiers":[
        {
            "category":"Real Estate",
            "subcategory":"Real Estate Agent",
            "type":"Services"
        },
        {
            "category":"Organizations",
            "subcategory":"Professional Association",
            "type":"Services"
        }
    ],
    "sg:phone":"+1 440 918 0047",
    "sg:postcode":"44094",
    "sg:province":"OH",
    "sg:tags":[
        "sales"
    ],
    "sg:website":"www.myhomesellingteam.com",
    "wof:name":"Home Selling Team Inc",
    "wof:placetype":"venue"
},
  "geometry": {"coordinates":[-81.40281400000001,41.641341],"type":"Point"}
}