{
  "type": "Feature",
  "properties": {
    "iso:country":"US",
    "sg:address":"2072 England Ave",
    "sg:city":"Dayton",
    "sg:classifiers":[
        {
            "category":"Professional",
            "subcategory":"Business Services",
            "type":"Services"
        }
    ],
    "sg:phone":"+1 937 274 2760",
    "sg:postcode":"45406",
    "sg:province":"OH",
    "sg:tags":[
        "recording",
        "studio"
    ],
    "wof:name":"Sod Entertainment Gemstone",
    "wof:placetype":"venue"
},
  "geometry": {"coordinates":[-84.25904,39.787283],"type":"Point"}
}