{
  "type": "Feature",
  "properties": {
    "addr:full":"207 W Jackson St West Unity OH 43570",
    "addr:housenumber":"207",
    "addr:postcode":"43570",
    "addr:street":"W Jackson St",
    "iso:country":"US",
    "sg:address":"207 W Jackson St",
    "sg:city":"West Unity",
    "sg:classifiers":[
        {
            "category":"Home & Garden",
            "subcategory":"Home Furnishings",
            "type":"Retail Goods"
        }
    ],
    "sg:phone":"+1 419 924 5864",
    "sg:postcode":"43570",
    "sg:province":"OH",
    "sg:tags":[
        "equipment",
        "fireplace"
    ],
    "wof:name":"Perry's Fireplaces",
    "wof:placetype":"venue"
},
  "geometry": {"coordinates":[-84.43499799999999,41.586421],"type":"Point"}
}