{
  "type": "Feature",
  "properties": {
    "addr:full": "1564 Logan Ave Youngstown OH 44505",
    "addr:housenumber": "1564",
    "addr:postcode": "44505",
    "addr:street": "Logan Ave",
    "iso:country": "US",
    "sg:address": "1564 Logan Ave",
    "sg:city": "Youngstown",
    "sg:classifiers": [
      {
        "category": "Bars \u0026 Pubs",
        "type": "Food \u0026 Drink"
      }
    ],
    "sg:phone": "+1 330 743 0052",
    "sg:postcode": "44505",
    "sg:province": "OH",
    "sg:tags": [
      "drinking",
      "restaurant"
    ],
    "wof:name": "Pit Stop Cafe",
    "wof:placetype": "venue"
  },
  "geometry": {"coordinates":[-80.637769,41.12194],"type":"Point"}
}
