{
  "type": "Feature",
  "properties": {
    "addr:full": "1212 E Dublin Granville Rd Columbus OH 43229",
    "addr:housenumber": "1212",
    "addr:postcode": "43229",
    "addr:street": "E Dublin Granville Rd",
    "iso:country": "US",
    "sg:address": "1212 E Dublin Granville Rd",
    "sg:city": "Columbus",
    "sg:classifiers": [
      {
        "category": "Recreation",
        "subcategory": "Amusement Park",
        "type": "Entertainment"
      }
    ],
    "sg:phone": "+1 614 785 1000",
    "sg:postcode": "43229",
    "sg:province": "OH",
    "wof:name": "Fantasy Golf \u0026 Funland",
    "wof:placetype": "venue"
  },
  "geometry": {"coordinates":[-82.986623,40.087653],"type":"Point"}
}
