{
  "type": "Feature",
  "properties": {
    "iso:country":"US",
    "sg:address":"1212 E Dublin Granville Rd",
    "sg:city":"Columbus",
    "sg:classifiers":[
        {
            "category":"Recreation",
            "subcategory":"Amusement Park",
            "type":"Entertainment"
        }
    ],
    "sg:phone":"+1 614 785 1000",
    "sg:postcode":"43229",
    "sg:province":"OH",
    "wof:name":"Fantasy Golf & Funland",
    "wof:placetype":"venue"
},
  "geometry": {"coordinates":[-82.98662299999999,40.087653],"type":"Point"}
}