{
  "type": "Feature",
  "properties": {
    "addr:full":"1316 Front St Toledo OH 43605",
    "addr:housenumber":"1316",
    "addr:postcode":"43605",
    "addr:street":"Front St",
    "iso:country":"US",
    "sg:address":"1316 Front St",
    "sg:city":"Toledo",
    "sg:classifiers":[
        {
            "category":"Restaurant",
            "type":"Food & Drink"
        }
    ],
    "sg:phone":"+1 419 697 4445",
    "sg:postcode":"43605",
    "sg:province":"OH",
    "sg:tags":[
        "eating"
    ],
    "wof:name":"River East Cafe",
    "wof:placetype":"venue"
},
  "geometry": {"coordinates":[-83.515716,41.653147],"type":"Point"}
}