{
  "type": "Feature",
  "properties": {
    "addr:full": "860 Elm Rd NE Warren OH 44483",
    "addr:housenumber": "860",
    "addr:postcode": "44483",
    "addr:street": "Elm Rd Ne",
    "iso:country": "US",
    "sg:address": "860 Elm Rd NE",
    "sg:city": "Warren",
    "sg:classifiers": [
      {
        "category": "Organizations",
        "subcategory": "Membership Organization",
        "type": "Services"
      }
    ],
    "sg:phone": "+1 330 373 6801",
    "sg:postcode": "44483",
    "sg:province": "OH",
    "sg:tags": [
      "athletic"
    ],
    "wof:name": "St Edwards Football Network",
    "wof:placetype": "venue"
  },
  "geometry": {"coordinates":[-80.805747,41.244508],"type":"Point"}
}
