{
  "type": "Feature",
  "properties": {
    "iso:country":"US",
    "sg:address":"3711 Whipple Ave NW",
    "sg:city":"Canton",
    "sg:classifiers":[
        {
            "category":"Professional",
            "subcategory":"Lawyer & Legal Services",
            "type":"Services"
        }
    ],
    "sg:phone":"+1 330 492 2225",
    "sg:postcode":"44718",
    "sg:province":"OH",
    "sg:tags":[
        "attorney"
    ],
    "wof:name":"Zink Zink & Zink",
    "wof:placetype":"venue"
},
  "geometry": {"coordinates":[-81.423877,40.841442],"type":"Point"}
}