{
  "type": "Feature",
  "properties": {
    "iso:country":"US",
    "sg:address":"26937 Schady Rd",
    "sg:city":"Cleveland",
    "sg:classifiers":[
        {
            "category":"Building & Trades",
            "subcategory":"Construction",
            "type":"Services"
        }
    ],
    "sg:phone":"+1 440 235 7057",
    "sg:postcode":"44138",
    "sg:province":"OH",
    "sg:tags":[
        "house",
        "restoration",
        "cleaning",
        "patio",
        "deck"
    ],
    "wof:name":"Deck King Restorations Inc",
    "wof:placetype":"venue"
},
  "geometry": {"coordinates":[-81.922307,41.362292],"type":"Point"}
}