{
  "type": "Feature",
  "properties": {
    "addr:full":"1625 W Springhill Ave Dayton OH 45409",
    "addr:housenumber":"1625",
    "addr:postcode":"45409",
    "addr:street":"W Springhill Ave",
    "iso:country":"US",
    "sg:address":"1625 W Springhill Ave",
    "sg:city":"Dayton",
    "sg:classifiers":[
        {
            "category":"Professional",
            "subcategory":"Accounting & Tax Preparation",
            "type":"Services"
        }
    ],
    "sg:phone":"+1 937 298 9804",
    "sg:postcode":"45409",
    "sg:province":"OH",
    "sg:tags":[
        "bookkeeping",
        "general"
    ],
    "wof:name":"Consul-Tax Financial Group",
    "wof:placetype":"venue"
},
  "geometry": {"coordinates":[-84.198965,39.719736],"type":"Point"}
}