{
  "type": "Feature",
  "properties": {
    "iso:country":"US",
    "sg:address":"495 Clark Rd",
    "sg:city":"Wooster",
    "sg:classifiers":[
        {
            "category":"Building & Trades",
            "subcategory":"Construction",
            "type":"Services"
        }
    ],
    "sg:phone":"+1 330 264 0106",
    "sg:postcode":"44691",
    "sg:province":"OH",
    "wof:name":"D & P Construction",
    "wof:placetype":"venue"
},
  "geometry": {"coordinates":[-81.943398,40.696829],"type":"Point"}
}