{
  "type": "Feature",
  "properties": {
    "addr:full": "495 Clark Rd Wooster OH 44691",
    "addr:housenumber": "495",
    "addr:postcode": "44691",
    "addr:street": "Clark Rd",
    "iso:country": "US",
    "sg:address": "495 Clark Rd",
    "sg:city": "Wooster",
    "sg:classifiers": [
      {
        "category": "Building \u0026 Trades",
        "subcategory": "Construction",
        "type": "Services"
      }
    ],
    "sg:phone": "+1 330 264 0106",
    "sg:postcode": "44691",
    "sg:province": "OH",
    "wof:name": "D \u0026 P Construction",
    "wof:placetype": "venue"
  },
  "geometry": {"coordinates":[-81.943398,40.696829],"type":"Point"}
}
