{
  "type": "Feature",
  "properties": {
    "iso:country":"US",
    "sg:address":"2509 Maple Ave NE",
    "sg:city":"Canton",
    "sg:classifiers":[
        {
            "category":"Local Transit",
            "type":"Transportation"
        }
    ],
    "sg:phone":"+1 330 452 1000",
    "sg:postcode":"44714",
    "sg:province":"OH",
    "sg:tags":[
        "passenger",
        "limousine"
    ],
    "wof:name":"Electrum Limousine Svc",
    "wof:placetype":"venue"
},
  "geometry": {"coordinates":[-81.353321,40.824975],"type":"Point"}
}