{
  "type": "Feature",
  "properties": {
    "addr:full": "9195 US Hwy 68 Rushsylvania OH 43347",
    "addr:housenumber": "9195",
    "addr:postcode": "43347",
    "addr:street": "Us Hwy 68",
    "iso:country": "US",
    "sg:address": "9195 US Hwy 68",
    "sg:city": "Rushsylvania",
    "sg:classifiers": [
      {
        "category": "Building \u0026 Trades",
        "subcategory": "Construction",
        "type": "Services"
      }
    ],
    "sg:phone": "+1 937 468 2458",
    "sg:postcode": "43347",
    "sg:province": "OH",
    "sg:tags": [
      "contractor"
    ],
    "wof:name": "Helmuth Builders",
    "wof:placetype": "venue"
  },
  "geometry": {"coordinates":[-83.704141,40.484252],"type":"Point"}
}
