{
  "type": "Feature",
  "properties": {
    "addr:full":"1664 Devils Backbone Rd Cincinnati OH 45233",
    "addr:housenumber":"1664",
    "addr:postcode":"45233",
    "addr:street":"Devils Backbone Rd",
    "iso:country":"US",
    "sg:address":"1664 Devils Backbone Rd",
    "sg:city":"Cincinnati",
    "sg:classifiers":[
        {
            "category":"Education",
            "subcategory":"Junior College",
            "type":"Public Place"
        }
    ],
    "sg:phone":"+1 513 941 3993",
    "sg:postcode":"45233",
    "sg:province":"OH",
    "sg:tags":[
        "technical",
        "institute"
    ],
    "wof:name":"Robertson's Schoolhouse-Dance",
    "wof:placetype":"venue"
},
  "geometry": {"coordinates":[-84.651347,39.125928],"type":"Point"}
}