{
  "type": "Feature",
  "properties": {
    "iso:country":"US",
    "sg:address":"5239 State Rte 199",
    "sg:city":"Carey",
    "sg:classifiers":[
        {
            "category":"Manufacturing",
            "subcategory":"Tools & Machinery",
            "type":"Manufacturing & Wholesale Goods"
        }
    ],
    "sg:phone":"+1 419 396 6078",
    "sg:postcode":"43316",
    "sg:province":"OH",
    "sg:tags":[
        "machine",
        "shop"
    ],
    "wof:name":"Stromberg-Hydramite Inc",
    "wof:placetype":"venue"
},
  "geometry": {"coordinates":[-83.342288,40.915903],"type":"Point"}
}