{
  "type": "Feature",
  "properties": {
    "addr:full": "14787 Pearl Rd Strongsville OH 44136",
    "addr:housenumber": "14787",
    "addr:postcode": "44136",
    "addr:street": "Pearl Rd",
    "iso:country": "US",
    "sg:address": "14787 Pearl Rd",
    "sg:city": "Strongsville",
    "sg:classifiers": [
      {
        "category": "Health Services",
        "subcategory": "Doctor",
        "type": "Services"
      }
    ],
    "sg:phone": "+1 440 846 6260",
    "sg:postcode": "44136",
    "sg:province": "OH",
    "sg:tags": [
      "physician",
      "surgeon"
    ],
    "wof:name": "John Schnell \u0026 Assoc",
    "wof:placetype": "venue"
  },
  "geometry": {"coordinates":[-81.835136,41.306096],"type":"Point"}
}
