{
  "type": "Feature",
  "properties": {
    "addr:full": "107 Millersburg St Nashville OH 44661",
    "addr:housenumber": "107",
    "addr:postcode": "44661",
    "addr:street": "Millersburg St",
    "iso:country": "US",
    "sg:address": "107 Millersburg St",
    "sg:city": "Nashville",
    "sg:classifiers": [
      {
        "category": "Health Services",
        "subcategory": "Doctor",
        "type": "Services"
      }
    ],
    "sg:phone": "+1 330 378 4951",
    "sg:postcode": "44661",
    "sg:province": "OH",
    "sg:tags": [
      "physician",
      "surgeon"
    ],
    "wof:name": "Nashville Medical Clinic",
    "wof:placetype": "venue"
  },
  "geometry": {"coordinates":[-82.112458,40.59639],"type":"Point"}
}
