{
  "type": "Feature",
  "properties": {
    "addr:full": "10938 State Rte 104 Lucasville OH 45648",
    "addr:housenumber": "10938",
    "addr:postcode": "45648",
    "addr:street": "State Rte 104",
    "iso:country": "US",
    "sg:address": "10938 State Rte 104",
    "sg:city": "Lucasville",
    "sg:classifiers": [
      {
        "category": "Food \u0026 Beverages",
        "subcategory": "Liquor \u0026 Beverages",
        "type": "Retail Goods"
      }
    ],
    "sg:phone": "+1 740 259 2453",
    "sg:postcode": "45648",
    "sg:province": "OH",
    "sg:tags": [
      "grocery",
      "alcoholic"
    ],
    "wof:name": "Pit Stop Convenient Mart",
    "wof:placetype": "venue"
  },
  "geometry": {"coordinates":[-83.015467,38.873668],"type":"Point"}
}
