{
  "type": "Feature",
  "properties": {
    "addr:full":"2717 S Arlington Rd Akron OH 44312",
    "addr:housenumber":"2717",
    "addr:postcode":"44312",
    "addr:street":"S Arlington Rd",
    "iso:country":"US",
    "sg:address":"2717 S Arlington Rd",
    "sg:city":"Akron",
    "sg:classifiers":[
        {
            "category":"Insurance",
            "subcategory":"Insurance Agent",
            "type":"Services"
        }
    ],
    "sg:phone":"+1 330 958 0725",
    "sg:postcode":"44312",
    "sg:province":"OH",
    "wof:name":"American Economy Insurance",
    "wof:placetype":"venue"
},
  "geometry": {"coordinates":[-81.492143,41.000183],"type":"Point"}
}