{
  "type": "Feature",
  "properties": {
    "addr:full":"1490 State Rte 63 Lebanon OH 45036",
    "addr:housenumber":"1490",
    "addr:postcode":"45036",
    "addr:street":"State Rte 63",
    "iso:country":"US",
    "sg:address":"1490 State Rte 63",
    "sg:city":"Lebanon",
    "sg:classifiers":[
        {
            "category":"Organizations",
            "subcategory":"Religious Organization",
            "type":"Services"
        }
    ],
    "sg:phone":"+1 513 932 0882",
    "sg:postcode":"45036",
    "sg:province":"OH",
    "sg:tags":[
        "church"
    ],
    "wof:name":"Wings As Eagles Ministries",
    "wof:placetype":"venue"
},
  "geometry": {"coordinates":[-84.234557,39.435119],"type":"Point"}
}