{
  "type": "Feature",
  "properties": {
    "addr:full":"227 S Washington St Tiffin OH 44883",
    "addr:housenumber":"227",
    "addr:postcode":"44883",
    "addr:street":"S Washington St",
    "iso:country":"US",
    "sg:address":"227 S Washington St",
    "sg:city":"Tiffin",
    "sg:classifiers":[
        {
            "category":"Wholesale",
            "subcategory":"Hardware",
            "type":"Manufacturing & Wholesale Goods"
        }
    ],
    "sg:phone":"+1 419 448 8885",
    "sg:postcode":"44883",
    "sg:province":"OH",
    "sg:tags":[
        "water",
        "cooler",
        "fountain",
        "filter"
    ],
    "wof:name":"Hempy Water LLC",
    "wof:placetype":"venue"
},
  "geometry": {"coordinates":[-83.176002,41.111094],"type":"Point"}
}