{
  "type": "Feature",
  "properties": {
    "iso:country":"US",
    "sg:address":"6910 Carriage Hill Dr",
    "sg:city":"Cleveland",
    "sg:classifiers":[
        {
            "category":"Wholesale",
            "subcategory":"Non-durable Goods",
            "type":"Manufacturing & Wholesale Goods"
        }
    ],
    "sg:phone":"+1 440 740 0830",
    "sg:postcode":"44141",
    "sg:province":"OH",
    "sg:tags":[
        "advertising"
    ],
    "sg:website":"www.gooeypromotions.com",
    "wof:name":"Gooey Promotions",
    "wof:placetype":"venue"
},
  "geometry": {"coordinates":[-81.62993299999999,41.337785],"type":"Point"}
}