{
  "type": "Feature",
  "properties": {
    "addr:full": "6910 Carriage Hill Dr Cleveland OH 44141",
    "addr:housenumber": "6910",
    "addr:postcode": "44141",
    "addr:street": "Carriage Hill Dr",
    "iso:country": "US",
    "sg:address": "6910 Carriage Hill Dr",
    "sg:city": "Cleveland",
    "sg:classifiers": [
      {
        "category": "Wholesale",
        "subcategory": "Non-durable Goods",
        "type": "Manufacturing \u0026 Wholesale Goods"
      }
    ],
    "sg:phone": "+1 440 740 0830",
    "sg:postcode": "44141",
    "sg:province": "OH",
    "sg:tags": [
      "advertising"
    ],
    "sg:website": "www.gooeypromotions.com",
    "wof:name": "Gooey Promotions",
    "wof:placetype": "venue"
  },
  "geometry": {"coordinates":[-81.629933,41.337785],"type":"Point"}
}
