{
  "type": "Feature",
  "properties": {
    "addr:full": "2239 East Pike Zanesville OH 43701",
    "addr:housenumber": "2239",
    "addr:postcode": "43701",
    "addr:street": "East Pike",
    "iso:country": "US",
    "sg:address": "2239 East Pike",
    "sg:city": "Zanesville",
    "sg:classifiers": [
      {
        "category": "Home \u0026 Garden",
        "subcategory": "Mobile Homes",
        "type": "Retail Goods"
      }
    ],
    "sg:phone": "+1 740 453 0358",
    "sg:postcode": "43701",
    "sg:province": "OH",
    "sg:tags": [
      "house",
      "construction"
    ],
    "wof:name": "Greenlawn Mobile Home Sales",
    "wof:placetype": "venue"
  },
  "geometry": {"coordinates":[-81.971158,39.946342],"type":"Point"}
}
