{
  "type": "Feature",
  "properties": {
    "iso:country":"US",
    "sg:address":"2239 East Pike",
    "sg:city":"Zanesville",
    "sg:classifiers":[
        {
            "category":"Home & Garden",
            "subcategory":"Mobile Homes",
            "type":"Retail Goods"
        }
    ],
    "sg:phone":"+1 740 453 0358",
    "sg:postcode":"43701",
    "sg:province":"OH",
    "sg:tags":[
        "house",
        "construction"
    ],
    "wof:name":"Greenlawn Mobile Home Sales",
    "wof:placetype":"venue"
},
  "geometry": {"coordinates":[-81.971158,39.946342],"type":"Point"}
}