{
  "type": "Feature",
  "properties": {
    "addr:full": "2938 Canton Rd Uniontown OH 44685",
    "addr:housenumber": "2938",
    "addr:postcode": "44685",
    "addr:street": "Canton Rd",
    "iso:country": "US",
    "sg:address": "2938 Canton Rd",
    "sg:city": "Uniontown",
    "sg:classifiers": [
      {
        "category": "Building \u0026 Trades",
        "subcategory": "Landscaping Services",
        "type": "Services"
      }
    ],
    "sg:phone": "+1 330 699 2818",
    "sg:postcode": "44685",
    "sg:province": "OH",
    "wof:name": "Morgan Cstm Dsign Landscpacing",
    "wof:placetype": "venue"
  },
  "geometry": {"coordinates":[-81.405645,40.990039],"type":"Point"}
}
