{
  "type": "Feature",
  "properties": {
    "iso:country":"US",
    "sg:address":"10045 Springfield Pike",
    "sg:city":"Cincinnati",
    "sg:classifiers":[
        {
            "category":"Insurance",
            "subcategory":"Insurance Agent",
            "type":"Services"
        }
    ],
    "sg:phone":"+1 513 771 8686",
    "sg:postcode":"45215",
    "sg:province":"OH",
    "wof:name":"W A Allen Assoc",
    "wof:placetype":"venue"
},
  "geometry": {"coordinates":[-84.470753,39.248057],"type":"Point"}
}