{
  "type": "Feature",
  "properties": {
    "addr:full": "58898 Claysville Rd Cambridge OH 43725",
    "addr:housenumber": "58898",
    "addr:postcode": "43725",
    "addr:street": "Claysville Rd",
    "iso:country": "US",
    "sg:address": "58898 Claysville Rd",
    "sg:city": "Cambridge",
    "sg:classifiers": [
      {
        "category": "Utilities",
        "subcategory": "Mobile Phone",
        "type": "Services"
      }
    ],
    "sg:phone": "+1 740 435 3253",
    "sg:postcode": "43725",
    "sg:province": "OH",
    "sg:tags": [
      "communication",
      "radiotelephone"
    ],
    "wof:name": "Zocar Wireless Ltd",
    "wof:placetype": "venue"
  },
  "geometry": {"coordinates":[-81.670494,39.956103],"type":"Point"}
}
