{
  "type": "Feature",
  "properties": {
    "addr:full":"12065 County Line Rd Chesterland OH 44026",
    "addr:housenumber":"12065",
    "addr:postcode":"44026",
    "addr:street":"County Line Rd",
    "iso:country":"US",
    "sg:address":"12065 County Line Rd",
    "sg:city":"Chesterland",
    "sg:classifiers":[
        {
            "category":"Building & Trades",
            "subcategory":"Plumbing",
            "type":"Services"
        }
    ],
    "sg:phone":"+1 440 423 4829",
    "sg:postcode":"44026",
    "sg:province":"OH",
    "sg:tags":[
        "plumbing",
        "heating",
        "contractor"
    ],
    "wof:name":"Osbourn Plumbing & Heating",
    "wof:placetype":"venue"
},
  "geometry": {"coordinates":[-81.39067799999999,41.542493],"type":"Point"}
}