{
  "type": "Feature",
  "properties": {
    "addr:full": "2427 Pearl Rd Medina OH 44256",
    "addr:housenumber": "2427",
    "addr:postcode": "44256",
    "addr:street": "Pearl Rd",
    "iso:country": "US",
    "sg:address": "2427 Pearl Rd",
    "sg:city": "Medina",
    "sg:classifiers": [
      {
        "category": "Autos \u0026 Motor Vehicles",
        "subcategory": "Automobile Sales",
        "type": "Retail Goods"
      }
    ],
    "sg:phone": "+1 330 273 2262",
    "sg:postcode": "44256",
    "sg:province": "OH",
    "sg:tags": [
      "car",
      "dealer"
    ],
    "wof:name": "Best Deals On Wheels",
    "wof:placetype": "venue"
  },
  "geometry": {"coordinates":[-81.841645,41.201673],"type":"Point"}
}
