{
  "type": "Feature",
  "properties": {
    "iso:country":"US",
    "sg:address":"34 N High St",
    "sg:city":"New Albany",
    "sg:classifiers":[
        {
            "category":"Health Services",
            "subcategory":"Health Practitioner",
            "type":"Services"
        }
    ],
    "sg:phone":"+1 614 895 1253",
    "sg:postcode":"43054",
    "sg:province":"OH",
    "sg:tags":[
        "dietitian"
    ],
    "sg:website":"www.eatrightohio.org",
    "wof:name":"Ohio Dietetis Assn",
    "wof:placetype":"venue"
},
  "geometry": {"coordinates":[-82.808604,40.083725],"type":"Point"}
}