{
  "type": "Feature",
  "properties": {
    "iso:country":"US",
    "sg:address":"509 College Ave",
    "sg:city":"Ashland",
    "sg:classifiers":[
        {
            "category":"Education",
            "subcategory":"Library",
            "type":"Public Place"
        }
    ],
    "sg:phone":"+1 419 289 5400",
    "sg:postcode":"44805",
    "sg:province":"OH",
    "sg:website":"www.ashland.edu",
    "wof:name":"Ashland University Library",
    "wof:placetype":"venue"
},
  "geometry": {"coordinates":[-82.32067600000001,40.862321],"type":"Point"}
}