{
  "type": "Feature",
  "properties": {
    "addr:full":"1810 Canova Ave Cleveland OH 44109",
    "addr:housenumber":"1810",
    "addr:postcode":"44109",
    "addr:street":"Canova Ave",
    "iso:country":"US",
    "sg:address":"1810 Canova Ave",
    "sg:city":"Cleveland",
    "sg:classifiers":[
        {
            "category":"Shopping",
            "subcategory":"Computers & Home Electronics",
            "type":"Retail Goods"
        }
    ],
    "sg:phone":"+1 216 398 0852",
    "sg:postcode":"44109",
    "sg:province":"OH",
    "wof:name":"Protech Computers",
    "wof:placetype":"venue"
},
  "geometry": {"coordinates":[-81.69477999999999,41.439448],"type":"Point"}
}