{
  "type": "Feature",
  "properties": {
    "addr:full": "2668 Heather Ln NW Warren OH 44485",
    "addr:housenumber": "2668",
    "addr:postcode": "44485",
    "addr:street": "Heather Ln Nw",
    "iso:country": "US",
    "sg:address": "2668 Heather Ln NW",
    "sg:city": "Warren",
    "sg:classifiers": [
      {
        "category": "Professional",
        "subcategory": "Secretarial Services",
        "type": "Services"
      }
    ],
    "sg:phone": "+1 330 898 7122",
    "sg:postcode": "44485",
    "sg:province": "OH",
    "sg:tags": [
      "reporting",
      "court"
    ],
    "wof:name": "Type Write Desktop Publishing",
    "wof:placetype": "venue"
  },
  "geometry": {"coordinates":[-80.851908,41.257164],"type":"Point"}
}
