{
  "type": "Feature",
  "properties": {
    "iso:country":"US",
    "sg:address":"2668 Heather Ln NW",
    "sg:city":"Warren",
    "sg:classifiers":[
        {
            "category":"Professional",
            "subcategory":"Secretarial Services",
            "type":"Services"
        }
    ],
    "sg:phone":"+1 330 898 7122",
    "sg:postcode":"44485",
    "sg:province":"OH",
    "sg:tags":[
        "reporting",
        "court"
    ],
    "wof:name":"Type Write Desktop Publishing",
    "wof:placetype":"venue"
},
  "geometry": {"coordinates":[-80.85190799999999,41.257164],"type":"Point"}
}