{
  "type": "Feature",
  "properties": {
    "addr:full":"1912 Hayes Ave Sandusky OH 44870",
    "addr:housenumber":"1912",
    "addr:postcode":"44870",
    "addr:street":"Hayes Ave",
    "iso:country":"US",
    "sg:address":"1912 Hayes Ave",
    "sg:city":"Sandusky",
    "sg:classifiers":[
        {
            "category":"Health Services",
            "subcategory":"Doctor",
            "type":"Services"
        }
    ],
    "sg:phone":"+1 419 626 1313",
    "sg:postcode":"44870",
    "sg:province":"OH",
    "sg:tags":[
        "physician",
        "surgeon"
    ],
    "wof:name":"Carter Becker MD",
    "wof:placetype":"venue"
},
  "geometry": {"coordinates":[-82.712748,41.437607],"type":"Point"}
}