{
  "type": "Feature",
  "properties": {
    "iso:country":"US",
    "sg:address":"8515 Freeway Dr",
    "sg:city":"Macedonia",
    "sg:classifiers":[
        {
            "category":"Freight",
            "type":"Transportation"
        }
    ],
    "sg:phone":"+1 330 467 9766",
    "sg:postcode":"44056",
    "sg:province":"OH",
    "sg:tags":[
        "mover"
    ],
    "wof:name":"Freedom Moving & Storage",
    "wof:placetype":"venue"
},
  "geometry": {"coordinates":[-81.514949,41.335099],"type":"Point"}
}