{
  "type": "Feature",
  "properties": {
    "addr:full": "340 Ridge Rd Newton Falls OH 44444",
    "addr:housenumber": "340",
    "addr:postcode": "44444",
    "addr:street": "Ridge Rd",
    "iso:country": "US",
    "sg:address": "340 Ridge Rd",
    "sg:city": "Newton Falls",
    "sg:classifiers": [
      {
        "category": "Health Services",
        "subcategory": "Doctor",
        "type": "Services"
      }
    ],
    "sg:phone": "+1 330 872 7083",
    "sg:postcode": "44444",
    "sg:province": "OH",
    "sg:tags": [
      "physician",
      "surgeon"
    ],
    "wof:name": "Trubull Internal Medicine Inc",
    "wof:placetype": "venue"
  },
  "geometry": {"coordinates":[-80.979202,41.192138],"type":"Point"}
}
