{
  "type": "Feature",
  "properties": {
    "addr:full": "2825 S Union Ave Alliance OH 44601",
    "addr:housenumber": "2825",
    "addr:postcode": "44601",
    "addr:street": "S Union Ave",
    "iso:country": "US",
    "sg:address": "2825 S Union Ave",
    "sg:city": "Alliance",
    "sg:classifiers": [
      {
        "category": "Health Services",
        "subcategory": "Doctor",
        "type": "Services"
      }
    ],
    "sg:phone": "+1 330 823 6189",
    "sg:postcode": "44601",
    "sg:province": "OH",
    "wof:name": "Rittner Melvin J J DDS Inc",
    "wof:placetype": "venue"
  },
  "geometry": {"coordinates":[-81.105789,40.893674],"type":"Point"}
}
