{
  "type": "Feature",
  "properties": {
    "iso:country":"US",
    "sg:address":"8000 Ravines Edge Ct",
    "sg:city":"Columbus",
    "sg:classifiers":[
        {
            "category":"Banks & Credit Unions",
            "subcategory":"Bank",
            "type":"Services"
        }
    ],
    "sg:phone":"+1 614 802 0400",
    "sg:postcode":"43235",
    "sg:province":"OH",
    "wof:name":"Cooper State Bank Corporate",
    "wof:placetype":"venue"
},
  "geometry": {"coordinates":[-83.019199,40.126449],"type":"Point"}
}