{
  "type": "Feature",
  "properties": {
    "addr:full": "8000 Ravines Edge Ct Columbus OH 43235",
    "addr:postcode": "8000;43235",
    "addr:street": "Ravines Edge Ct",
    "iso:country": "US",
    "sg:address": "8000 Ravines Edge Ct",
    "sg:city": "Columbus",
    "sg:classifiers": [
      {
        "category": "Banks \u0026 Credit Unions",
        "subcategory": "Bank",
        "type": "Services"
      }
    ],
    "sg:phone": "+1 614 802 0400",
    "sg:postcode": "43235",
    "sg:province": "OH",
    "wof:name": "Cooper State Bank Corporate",
    "wof:placetype": "venue"
  },
  "geometry": {"coordinates":[-83.019199,40.126449],"type":"Point"}
}
