{
  "type": "Feature",
  "properties": {
    "iso:country":"US",
    "sg:address":"10241 US Rte 68",
    "sg:city":"Georgetown",
    "sg:classifiers":[
        {
            "category":"Food & Beverages",
            "subcategory":"Groceries & Convenience Stores",
            "type":"Retail Goods"
        }
    ],
    "sg:phone":"+1 937 378 6573",
    "sg:postcode":"45121",
    "sg:province":"OH",
    "wof:name":"Wittmeyers Farm Market",
    "wof:placetype":"venue"
},
  "geometry": {"coordinates":[-83.903323,38.920522],"type":"Point"}
}