{
  "type": "Feature",
  "properties": {
    "addr:full": "131 W State St Alliance OH 44601",
    "addr:housenumber": "131",
    "addr:postcode": "44601",
    "addr:street": "W State St",
    "iso:country": "US",
    "sg:address": "131 W State St",
    "sg:city": "Alliance",
    "sg:classifiers": [
      {
        "category": "Health Services",
        "subcategory": "Doctor",
        "type": "Services"
      }
    ],
    "sg:phone": "+1 330 823 3166",
    "sg:postcode": "44601",
    "sg:province": "OH",
    "sg:tags": [
      "physician",
      "surgeon"
    ],
    "wof:name": "Teresita Marcelo Inc",
    "wof:placetype": "venue"
  },
  "geometry": {"coordinates":[-81.107973,40.901789],"type":"Point"}
}
