{
  "type": "Feature",
  "properties": {
    "addr:full": "5968 Glenway Ave Cincinnati OH 45238",
    "addr:housenumber": "5968",
    "addr:postcode": "45238",
    "addr:street": "Glenway Ave",
    "iso:country": "US",
    "sg:address": "5968 Glenway Ave",
    "sg:city": "Cincinnati",
    "sg:classifiers": [
      {
        "category": "Personal",
        "type": "Services"
      }
    ],
    "sg:phone": "+1 513 631 2255",
    "sg:postcode": "45238",
    "sg:province": "OH",
    "sg:tags": [
      "credit",
      "debt",
      "counseling"
    ],
    "wof:name": "Cincinnati Credit Counseling",
    "wof:placetype": "venue"
  },
  "geometry": {"coordinates":[-84.617864,39.140974],"type":"Point"}
}
