{
  "type": "Feature",
  "properties": {
    "iso:country":"US",
    "sg:address":"2001 Crocker Rd",
    "sg:city":"Cleveland",
    "sg:classifiers":[
        {
            "category":"Health Services",
            "subcategory":"Doctor",
            "type":"Services"
        }
    ],
    "sg:phone":"+1 440 835 6132",
    "sg:postcode":"44145",
    "sg:province":"OH",
    "sg:tags":[
        "physician",
        "surgeon"
    ],
    "wof:name":"Anthony E Bacevice Jr MD",
    "wof:placetype":"venue"
},
  "geometry": {"coordinates":[-81.950548,41.461477],"type":"Point"}
}