{
  "type": "Feature",
  "properties": {
    "iso:country":"US",
    "sg:address":"3828 Tuscarawas St W",
    "sg:city":"Canton",
    "sg:classifiers":[
        {
            "category":"Restaurant",
            "type":"Food & Drink"
        }
    ],
    "sg:phone":"+1 330 477 3888",
    "sg:postcode":"44708",
    "sg:province":"OH",
    "wof:name":"Chinatown Kitchen",
    "wof:placetype":"venue"
},
  "geometry": {"coordinates":[-81.419116,40.79714],"type":"Point"}
}