{
  "type": "Feature",
  "properties": {
    "addr:full": "3828 Tuscarawas St W Canton OH 44708",
    "addr:housenumber": "3828",
    "addr:postcode": "44708",
    "addr:street": "Tuscarawas St W",
    "iso:country": "US",
    "sg:address": "3828 Tuscarawas St W",
    "sg:city": "Canton",
    "sg:classifiers": [
      {
        "category": "Restaurant",
        "type": "Food \u0026 Drink"
      }
    ],
    "sg:phone": "+1 330 477 3888",
    "sg:postcode": "44708",
    "sg:province": "OH",
    "wof:name": "Chinatown Kitchen",
    "wof:placetype": "venue"
  },
  "geometry": {"coordinates":[-81.419116,40.79714],"type":"Point"}
}
