{
  "type": "Feature",
  "properties": {
    "addr:full": "1289 Marlowe Ave Cleveland OH 44107",
    "addr:housenumber": "1289",
    "addr:postcode": "44107",
    "addr:street": "Marlowe Ave",
    "iso:country": "US",
    "sg:address": "1289 Marlowe Ave",
    "sg:city": "Cleveland",
    "sg:classifiers": [
      {
        "category": "Building \u0026 Trades",
        "subcategory": "Construction",
        "type": "Services"
      }
    ],
    "sg:phone": "+1 216 226 8525",
    "sg:postcode": "44107",
    "sg:province": "OH",
    "sg:tags": [
      "painting",
      "painter",
      "contractor"
    ],
    "wof:name": "Larry's Painting Inc",
    "wof:placetype": "venue"
  },
  "geometry": {"coordinates":[-81.795397,41.49057],"type":"Point"}
}
