{
  "type": "Feature",
  "properties": {
    "addr:full":"5820 S Wright St Kingsville OH 44048",
    "addr:housenumber":"5820",
    "addr:postcode":"44048",
    "addr:street":"S Wright St",
    "iso:country":"US",
    "sg:address":"5820 S Wright St",
    "sg:city":"Kingsville",
    "sg:classifiers":[
        {
            "category":"Retail",
            "subcategory":"Repair Shop",
            "type":"Services"
        }
    ],
    "sg:phone":"+1 440 224 1951",
    "sg:postcode":"44048",
    "sg:province":"OH",
    "sg:tags":[
        "upholsterer"
    ],
    "wof:name":"Doan Upholstering Inc",
    "wof:placetype":"venue"
},
  "geometry": {"coordinates":[-80.680286,41.878533],"type":"Point"}
}