{
  "type": "Feature",
  "properties": {
    "addr:full": "22603 Rd 140 Oakwood OH 45873",
    "addr:postcode": "22603;45873",
    "addr:street": "Rd 140",
    "iso:country": "US",
    "sg:address": "22603 Rd 140",
    "sg:city": "Oakwood",
    "sg:classifiers": [
      {
        "category": "Wholesale",
        "subcategory": "Machinery \u0026 Supplies",
        "type": "Manufacturing \u0026 Wholesale Goods"
      }
    ],
    "sg:phone": "+1 419 594 2360",
    "sg:postcode": "45873",
    "sg:province": "OH",
    "sg:tags": [
      "equipment",
      "establishment"
    ],
    "wof:name": "Body Restoration",
    "wof:placetype": "venue"
  },
  "geometry": {"coordinates":[-84.39029,41.136114],"type":"Point"}
}
