{
  "type": "Feature",
  "properties": {
    "addr:full":"461 State Rte 61 Marengo OH 43334",
    "addr:housenumber":"461",
    "addr:postcode":"43334",
    "addr:street":"State Rte 61",
    "iso:country":"US",
    "sg:address":"461 State Rte 61",
    "sg:city":"Marengo",
    "sg:classifiers":[
        {
            "category":"Home & Garden",
            "subcategory":"Mobile Homes",
            "type":"Retail Goods"
        }
    ],
    "sg:phone":"+1 419 253 7421",
    "sg:postcode":"43334",
    "sg:province":"OH",
    "wof:name":"Green Lawn Homes Morrow Co LLC",
    "wof:placetype":"venue"
},
  "geometry": {"coordinates":[-82.829685,40.369054],"type":"Point"}
}