{
  "type": "Feature",
  "properties": {
    "iso:country":"US",
    "sg:address":"609 W Main St",
    "sg:city":"Williamsburg",
    "sg:classifiers":[
        {
            "category":"Autos & Motor Vehicles",
            "subcategory":"Fuel & Gas Station",
            "type":"Retail Goods"
        }
    ],
    "sg:phone":"+1 513 724 3211",
    "sg:postcode":"45176",
    "sg:province":"OH",
    "sg:tags":[
        "station",
        "gasoline"
    ],
    "wof:name":"Bp Williamsburg",
    "wof:placetype":"venue"
},
  "geometry": {"coordinates":[-84.057608,39.056524],"type":"Point"}
}