{
  "type": "Feature",
  "properties": {
    "addr:full": "609 W Main St Williamsburg OH 45176",
    "addr:housenumber": "609",
    "addr:postcode": "45176",
    "addr:street": "W Main St",
    "iso:country": "US",
    "sg:address": "609 W Main St",
    "sg:city": "Williamsburg",
    "sg:classifiers": [
      {
        "category": "Autos \u0026 Motor Vehicles",
        "subcategory": "Fuel \u0026 Gas Station",
        "type": "Retail Goods"
      }
    ],
    "sg:phone": "+1 513 724 3211",
    "sg:postcode": "45176",
    "sg:province": "OH",
    "sg:tags": [
      "station",
      "gasoline"
    ],
    "wof:name": "Bp Williamsburg",
    "wof:placetype": "venue"
  },
  "geometry": {"coordinates":[-84.057608,39.056524],"type":"Point"}
}
