{
  "type": "Feature",
  "properties": {
    "addr:full":"619 W Marion St Mount Gilead OH 43338",
    "addr:housenumber":"619",
    "addr:postcode":"43338",
    "addr:street":"W Marion St",
    "iso:country":"US",
    "sg:address":"619 W Marion St",
    "sg:city":"Mount Gilead",
    "sg:classifiers":[
        {
            "category":"Government",
            "subcategory":"Office",
            "type":"Public Place"
        }
    ],
    "sg:phone":"+1 419 946 4026",
    "sg:postcode":"43338",
    "sg:province":"OH",
    "sg:tags":[
        "general"
    ],
    "wof:name":"Board of Elections",
    "wof:placetype":"venue"
},
  "geometry": {"coordinates":[-82.84911099999999,40.54923],"type":"Point"}
}