{
  "type": "Feature",
  "properties": {
    "addr:full":"111 S Main St Mt Victory OH 43340",
    "addr:housenumber":"111",
    "addr:postcode":"43340",
    "addr:street":"S Main St",
    "iso:country":"US",
    "sg:address":"111 S Main St",
    "sg:city":"Mt Victory",
    "sg:classifiers":[
        {
            "category":"Shopping",
            "subcategory":"Used Merchandise",
            "type":"Retail Goods"
        }
    ],
    "sg:phone":"+1 937 354 4330",
    "sg:postcode":"43340",
    "sg:province":"OH",
    "sg:tags":[
        "antique"
    ],
    "wof:name":"Corbin Cottage",
    "wof:placetype":"venue"
},
  "geometry": {"coordinates":[-83.520882,40.534237],"type":"Point"}
}