{
  "type": "Feature",
  "properties": {
    "addr:full":"25 N Cedar St Newark OH 43055",
    "addr:housenumber":"25",
    "addr:postcode":"43055",
    "addr:street":"N Cedar St",
    "iso:country":"US",
    "sg:address":"25 N Cedar St",
    "sg:city":"Newark",
    "sg:classifiers":[
        {
            "category":"Real Estate",
            "subcategory":"Real Estate Operator",
            "type":"Services"
        }
    ],
    "sg:phone":"+1 740 345 9723",
    "sg:postcode":"43055",
    "sg:province":"OH",
    "sg:tags":[
        "building",
        "apartment"
    ],
    "wof:name":"Jobs Manor",
    "wof:placetype":"venue"
},
  "geometry": {"coordinates":[-82.386314,40.060475],"type":"Point"}
}