{
  "type": "Feature",
  "properties": {
    "iso:country":"US",
    "sg:address":"602 Elmhurst Rd",
    "sg:city":"Dayton",
    "sg:classifiers":[
        {
            "category":"Food & Beverages",
            "subcategory":"Groceries & Convenience Stores",
            "type":"Retail Goods"
        }
    ],
    "sg:phone":"+1 937 263 7172",
    "sg:postcode":"45417",
    "sg:province":"OH",
    "sg:tags":[
        "grocer"
    ],
    "wof:name":"Springfield Trade Inc",
    "wof:placetype":"venue"
},
  "geometry": {"coordinates":[-84.25914400000001,39.755556],"type":"Point"}
}