{
  "type": "Feature",
  "properties": {
    "iso:country":"US",
    "sg:address":"6500 E Main St",
    "sg:city":"Reynoldsburg",
    "sg:classifiers":[
        {
            "category":"Personal",
            "subcategory":"Barber",
            "type":"Services"
        }
    ],
    "sg:phone":"+1 614 866 1232",
    "sg:postcode":"43068",
    "sg:province":"OH",
    "wof:name":"Mike's Barber Shop",
    "wof:placetype":"venue"
},
  "geometry": {"coordinates":[-82.82029799999999,39.954941],"type":"Point"}
}