{
  "type": "Feature",
  "properties": {
    "addr:full": "7228 Keiler Ct Dublin OH 43017",
    "addr:housenumber": "7228",
    "addr:postcode": "43017",
    "addr:street": "Keiler Ct",
    "iso:country": "US",
    "sg:address": "7228 Keiler Ct",
    "sg:city": "Dublin",
    "sg:classifiers": [
      {
        "category": "Wholesale",
        "subcategory": "Non-durable Goods",
        "type": "Manufacturing \u0026 Wholesale Goods"
      }
    ],
    "sg:phone": "+1 614 764 1201",
    "sg:postcode": "43017",
    "sg:province": "OH",
    "wof:name": "Cardinal Trading LLC",
    "wof:placetype": "venue"
  },
  "geometry": {"coordinates":[-83.147479,40.11404],"type":"Point"}
}
