{
  "type": "Feature",
  "properties": {
    "iso:country":"US",
    "sg:address":"404 S Market St",
    "sg:city":"Wooster",
    "sg:classifiers":[
        {
            "category":"Restaurant",
            "type":"Food & Drink"
        }
    ],
    "sg:menulink":"http://www.allmenus.com/oh/wooster/134544-subway/menu/",
    "sg:phone":"+1 330 262 7827",
    "sg:postcode":"44691",
    "sg:province":"OH",
    "sg:tags":[
        "american",
        "sandwich"
    ],
    "wof:name":"Subway",
    "wof:placetype":"venue"
},
  "geometry": {"coordinates":[-81.939043,40.794649],"type":"Point"}
}