{
  "type": "Feature",
  "properties": {
    "iso:country":"US",
    "sg:address":"337 N High St",
    "sg:city":"Chillicothe",
    "sg:classifiers":[
        {
            "category":"Shopping",
            "subcategory":"Used Merchandise",
            "type":"Retail Goods"
        }
    ],
    "sg:phone":"+1 740 779 9528",
    "sg:postcode":"45601",
    "sg:province":"OH",
    "sg:tags":[
        "antique"
    ],
    "wof:name":"Apple Tree Antiques & Cllctbls",
    "wof:placetype":"venue"
},
  "geometry": {"coordinates":[-82.990414,39.341109],"type":"Point"}
}