{
  "type": "Feature",
  "properties": {
    "addr:full": "337 N High St Chillicothe OH 45601",
    "addr:housenumber": "337",
    "addr:postcode": "45601",
    "addr:street": "N High St",
    "iso:country": "US",
    "sg:address": "337 N High St",
    "sg:city": "Chillicothe",
    "sg:classifiers": [
      {
        "category": "Shopping",
        "subcategory": "Used Merchandise",
        "type": "Retail Goods"
      }
    ],
    "sg:phone": "+1 740 779 9528",
    "sg:postcode": "45601",
    "sg:province": "OH",
    "sg:tags": [
      "antique"
    ],
    "wof:name": "Apple Tree Antiques \u0026 Cllctbls",
    "wof:placetype": "venue"
  },
  "geometry": {"coordinates":[-82.990414,39.341109],"type":"Point"}
}
