{
  "type": "Feature",
  "properties": {
    "iso:country":"US",
    "sg:address":"11235 Williamson Rd",
    "sg:city":"Cincinnati",
    "sg:classifiers":[
        {
            "category":"Home & Garden",
            "subcategory":"Furniture",
            "type":"Retail Goods"
        }
    ],
    "sg:phone":"+1 513 530 5010",
    "sg:postcode":"45241",
    "sg:province":"OH",
    "sg:tags":[
        "mattress"
    ],
    "wof:name":"Mattress Firm",
    "wof:placetype":"venue"
},
  "geometry": {"coordinates":[-84.378794,39.27395],"type":"Point"}
}