{
  "type": "Feature",
  "properties": {
    "iso:country":"US",
    "sg:address":"8019 Keller Rd",
    "sg:city":"Cincinnati",
    "sg:classifiers":[
        {
            "category":"Health Services",
            "subcategory":"Doctor",
            "type":"Services"
        }
    ],
    "sg:phone":"+1 513 984 2236",
    "sg:postcode":"45243",
    "sg:province":"OH",
    "sg:tags":[
        "physician",
        "surgeon"
    ],
    "wof:name":"Foundation For OB-Gyn",
    "wof:placetype":"venue"
},
  "geometry": {"coordinates":[-84.355736,39.207515],"type":"Point"}
}