{
  "type": "Feature",
  "properties": {
    "addr:full": "2450 Reading Rd Cincinnati OH 45206",
    "addr:housenumber": "2450",
    "addr:postcode": "45206",
    "addr:street": "Reading Rd",
    "iso:country": "US",
    "sg:address": "2450 Reading Rd",
    "sg:city": "Cincinnati",
    "sg:classifiers": [
      {
        "category": "Home \u0026 Garden",
        "subcategory": "Building Materials",
        "type": "Retail Goods"
      }
    ],
    "sg:phone": "+1 740 743 1090",
    "sg:postcode": "45206",
    "sg:province": "OH",
    "sg:tags": [
      "glass",
      "window",
      "plate"
    ],
    "wof:name": "King's Auto Glass",
    "wof:placetype": "venue"
  },
  "geometry": {"coordinates":[-84.501837,39.125892],"type":"Point"}
}
