{
  "type": "Feature",
  "properties": {
    "iso:country":"US",
    "sg:address":"2450 Reading Rd",
    "sg:city":"Cincinnati",
    "sg:classifiers":[
        {
            "category":"Home & Garden",
            "subcategory":"Building Materials",
            "type":"Retail Goods"
        }
    ],
    "sg:phone":"+1 740 743 1090",
    "sg:postcode":"45206",
    "sg:province":"OH",
    "sg:tags":[
        "glass",
        "window",
        "plate"
    ],
    "wof:name":"King's Auto Glass",
    "wof:placetype":"venue"
},
  "geometry": {"coordinates":[-84.50183699999999,39.125892],"type":"Point"}
}