{
  "type": "Feature",
  "properties": {
    "iso:country":"US",
    "sg:address":"117 E Chestnut St",
    "sg:city":"Columbus",
    "sg:classifiers":[
        {
            "category":"Bars & Pubs",
            "type":"Food & Drink"
        }
    ],
    "sg:phone":"+1 614 461 4110",
    "sg:postcode":"43215",
    "sg:province":"OH",
    "sg:tags":[
        "bar"
    ],
    "wof:name":"Tradewinds",
    "wof:placetype":"venue"
},
  "geometry": {"coordinates":[-82.998626,39.96787],"type":"Point"}
}