{
  "type": "Feature",
  "properties": {
    "addr:full": "19259 State Rte 136 Winchester OH 45697",
    "addr:housenumber": "19259",
    "addr:postcode": "45697",
    "addr:street": "State Rte 136",
    "iso:country": "US",
    "sg:address": "19259 State Rte 136",
    "sg:city": "Winchester",
    "sg:classifiers": [
      {
        "category": "Insurance",
        "subcategory": "Insurance Agent",
        "type": "Services"
      }
    ],
    "sg:phone": "+1 937 695 0809",
    "sg:postcode": "45697",
    "sg:province": "OH",
    "wof:name": "Winchester Insurance",
    "wof:placetype": "venue"
  },
  "geometry": {"coordinates":[-83.65111,38.941944],"type":"Point"}
}
