{
  "type": "Feature",
  "properties": {
    "addr:full":"4530 N Holland Sylvania Ave Toledo OH 43623",
    "addr:housenumber":"4530",
    "addr:postcode":"43623",
    "addr:street":"N Holland Sylvania Ave",
    "iso:country":"US",
    "sg:address":"4530 N Holland Sylvania Ave",
    "sg:city":"Toledo",
    "sg:classifiers":[
        {
            "category":"Building & Trades",
            "subcategory":"Construction",
            "type":"Services"
        }
    ],
    "sg:phone":"+1 419 824 4201",
    "sg:postcode":"43623",
    "sg:province":"OH",
    "sg:tags":[
        "contractor"
    ],
    "wof:name":"Eagle Ridge Builders",
    "wof:placetype":"venue"
},
  "geometry": {"coordinates":[-83.69252899999999,41.700063],"type":"Point"}
}