{
  "type": "Feature",
  "properties": {
    "iso:country":"US",
    "sg:address":"376 Crandall Ave",
    "sg:city":"Youngstown",
    "sg:classifiers":[
        {
            "category":"Personal",
            "subcategory":"Barber",
            "type":"Services"
        }
    ],
    "sg:phone":"+1 330 743 2206",
    "sg:postcode":"44504",
    "sg:province":"OH",
    "wof:name":"Robert Wilson Barbershop",
    "wof:placetype":"venue"
},
  "geometry": {"coordinates":[-80.655531,41.121935],"type":"Point"}
}