{
  "type": "Feature",
  "properties": {
    "addr:full": "5646 Young Rd Bellevue OH 44811",
    "addr:housenumber": "5646",
    "addr:postcode": "44811",
    "addr:street": "Young Rd",
    "iso:country": "US",
    "sg:address": "5646 Young Rd",
    "sg:city": "Bellevue",
    "sg:classifiers": [
      {
        "category": "Government",
        "subcategory": "Office",
        "type": "Public Place"
      }
    ],
    "sg:phone": "+1 419 483 6373",
    "sg:postcode": "44811",
    "sg:province": "OH",
    "sg:tags": [
      "township"
    ],
    "wof:name": "Township of Lyme",
    "wof:placetype": "venue"
  },
  "geometry": {"coordinates":[-82.794432,41.252888],"type":"Point"}
}
