{
  "type": "Feature",
  "properties": {
    "iso:country":"US",
    "sg:address":"1277 E Schaaf Rd",
    "sg:city":"Cleveland",
    "sg:classifiers":[
        {
            "category":"Retail",
            "subcategory":"Auto Repair",
            "type":"Services"
        }
    ],
    "sg:phone":"+1 216 741 5200",
    "sg:postcode":"44131",
    "sg:province":"OH",
    "sg:tags":[
        "truck",
        "tractor"
    ],
    "wof:name":"AAA Truck Service Co",
    "wof:placetype":"venue"
},
  "geometry": {"coordinates":[-81.65554899999999,41.413598],"type":"Point"}
}