{
  "type": "Feature",
  "properties": {
    "addr:full": "4804 N Leavitt Rd Lorain OH 44053",
    "addr:housenumber": "4804",
    "addr:postcode": "44053",
    "addr:street": "N Leavitt Rd",
    "iso:country": "US",
    "sg:address": "4804 N Leavitt Rd",
    "sg:city": "Lorain",
    "sg:classifiers": [
      {
        "category": "Health Services",
        "subcategory": "Doctor",
        "type": "Services"
      }
    ],
    "sg:phone": "+1 440 324 5588",
    "sg:postcode": "44053",
    "sg:province": "OH",
    "sg:tags": [
      "physician",
      "surgeon"
    ],
    "wof:name": "Comprehensive Pain Care",
    "wof:placetype": "venue"
  },
  "geometry": {"coordinates":[-82.208722,41.423208],"type":"Point"}
}
