{
  "type": "Feature",
  "properties": {
    "addr:full":"10 W 2nd St Dayton OH 45402",
    "addr:housenumber":"10",
    "addr:postcode":"45402",
    "addr:street":"W 2Nd St",
    "iso:country":"US",
    "sg:address":"10 W 2nd St",
    "sg:city":"Dayton",
    "sg:classifiers":[
        {
            "category":"Real Estate",
            "subcategory":"Real Estate Agent",
            "type":"Services"
        }
    ],
    "sg:phone":"+1 937 495 3600",
    "sg:postcode":"45402",
    "sg:province":"OH",
    "wof:name":"Jones Lang Lasalle Americas",
    "wof:placetype":"venue"
},
  "geometry": {"coordinates":[-84.19385699999999,39.7606],"type":"Point"}
}