{
  "type": "Feature",
  "properties": {
    "addr:full":"863 E 185th St Cleveland OH 44119",
    "addr:housenumber":"863",
    "addr:postcode":"44119",
    "addr:street":"E 185Th St",
    "iso:country":"US",
    "sg:address":"863 E 185th St",
    "sg:city":"Cleveland",
    "sg:classifiers":[
        {
            "category":"Personal",
            "subcategory":"Beauty Salon",
            "type":"Services"
        }
    ],
    "sg:phone":"+1 216 481 4121",
    "sg:postcode":"44119",
    "sg:province":"OH",
    "wof:name":"Frederick & Co",
    "wof:placetype":"venue"
},
  "geometry": {"coordinates":[-81.54977100000001,41.584241],"type":"Point"}
}