{
  "type": "Feature",
  "properties": {
    "iso:country":"US",
    "sg:address":"9186 Indian Mound Ct NW",
    "sg:city":"Pickerington",
    "sg:classifiers":[
        {
            "category":"Wholesale",
            "subcategory":"Medical Equipment & Supplies",
            "type":"Manufacturing & Wholesale Goods"
        },
        {
            "category":"Professional",
            "type":"Services"
        }
    ],
    "sg:phone":"+1 740 927 6147",
    "sg:postcode":"43147",
    "sg:province":"OH",
    "sg:tags":[
        "establishment",
        "veterinary",
        "design"
    ],
    "wof:name":"Equine Systems Inc",
    "wof:placetype":"venue"
},
  "geometry": {"coordinates":[-82.758908,39.935479],"type":"Point"}
}