{
  "type": "Feature",
  "properties": {
    "addr:full": "9186 Indian Mound Ct NW Pickerington OH 43147",
    "addr:housenumber": "9186",
    "addr:postcode": "43147",
    "addr:street": "Indian Mound Ct Nw",
    "iso:country": "US",
    "sg:address": "9186 Indian Mound Ct NW",
    "sg:city": "Pickerington",
    "sg:classifiers": [
      {
        "category": "Wholesale",
        "subcategory": "Medical Equipment \u0026 Supplies",
        "type": "Manufacturing \u0026 Wholesale Goods"
      },
      {
        "category": "Professional",
        "type": "Services"
      }
    ],
    "sg:phone": "+1 740 927 6147",
    "sg:postcode": "43147",
    "sg:province": "OH",
    "sg:tags": [
      "establishment",
      "veterinary",
      "design"
    ],
    "wof:name": "Equine Systems Inc",
    "wof:placetype": "venue"
  },
  "geometry": {"coordinates":[-82.758908,39.935479],"type":"Point"}
}
