{
  "type": "Feature",
  "properties": {
    "addr:full":"6884 Blain Hwy Chillicothe OH 45601",
    "addr:housenumber":"6884",
    "addr:postcode":"45601",
    "addr:street":"Blain Hwy",
    "iso:country":"US",
    "sg:address":"6884 Blain Hwy",
    "sg:city":"Chillicothe",
    "sg:classifiers":[
        {
            "category":"Manufacturing",
            "subcategory":"Tools & Machinery",
            "type":"Manufacturing & Wholesale Goods"
        }
    ],
    "sg:phone":"+1 740 773 5294",
    "sg:postcode":"45601",
    "sg:province":"OH",
    "sg:tags":[
        "machine",
        "shop"
    ],
    "wof:name":"J & K Machine Shop",
    "wof:placetype":"venue"
},
  "geometry": {"coordinates":[-83.06744399999999,39.24563],"type":"Point"}
}