{
  "type": "Feature",
  "properties": {
    "addr:full": "10415 Kenwood Rd Cincinnati OH 45242",
    "addr:housenumber": "10415",
    "addr:postcode": "45242",
    "addr:street": "Kenwood Rd",
    "iso:country": "US",
    "sg:address": "10415 Kenwood Rd",
    "sg:city": "Cincinnati",
    "sg:classifiers": [
      {
        "category": "Autos \u0026 Motor Vehicles",
        "subcategory": "Fuel \u0026 Gas Station",
        "type": "Retail Goods"
      },
      {
        "category": "Retail",
        "subcategory": "Car Wash",
        "type": "Services"
      },
      {
        "category": "Retail",
        "subcategory": "Auto Repair",
        "type": "Services"
      },
      {
        "category": "Food \u0026 Beverages",
        "subcategory": "Groceries \u0026 Convenience Stores",
        "type": "Retail Goods"
      }
    ],
    "sg:phone": "+1 513 791 0549",
    "sg:postcode": "45242",
    "sg:province": "OH",
    "sg:website": "http://www.napaautocare.com/",
    "wof:name": "Blue Ash Shell",
    "wof:placetype": "venue"
  },
  "geometry": {"coordinates":[-84.375145,39.250702],"type":"Point"}
}
