{
  "type": "Feature",
  "properties": {
    "addr:full": "3227 Co Hwy 739 Loudonville OH 44842",
    "addr:housenumber": "3227",
    "addr:postcode": "44842",
    "addr:street": "Co Hwy 739",
    "iso:country": "US",
    "sg:address": "3227 Co Hwy 739",
    "sg:city": "Loudonville",
    "sg:classifiers": [
      {
        "category": "Travel",
        "subcategory": "Hotels \u0026 Motels",
        "type": "Entertainment"
      }
    ],
    "sg:phone": "+1 419 994 5361",
    "sg:postcode": "44842",
    "sg:province": "OH",
    "sg:tags": [
      "chalet",
      "rental",
      "cabin"
    ],
    "sg:website": "www.kandelightkabins.com",
    "wof:name": "Kandelight Kabins",
    "wof:placetype": "venue"
  },
  "geometry": {"coordinates":[-82.262684,40.587186],"type":"Point"}
}
