{
  "type": "Feature",
  "properties": {
    "addr:full": "2555 Co Rd 184 Cardington OH 43315",
    "addr:housenumber": "2555;184",
    "addr:postcode": "43315",
    "addr:street": "Co Rd",
    "iso:country": "US",
    "sg:address": "2555 Co Rd 184",
    "sg:city": "Cardington",
    "sg:classifiers": [
      {
        "category": "Building \u0026 Trades",
        "subcategory": "Construction",
        "type": "Services"
      }
    ],
    "sg:phone": "+1 419 768 7677",
    "sg:postcode": "43315",
    "sg:province": "OH",
    "sg:tags": [
      "contractor"
    ],
    "wof:name": "Terry Cox Masonry",
    "wof:placetype": "venue"
  },
  "geometry": {"coordinates":[-82.746562,40.441197],"type":"Point"}
}
