{
  "type": "Feature",
  "properties": {
    "addr:full": "104 N Marietta St St Clairsville OH 43950",
    "addr:housenumber": "104",
    "addr:postcode": "43950",
    "addr:street": "N Marietta St",
    "iso:country": "US",
    "sg:address": "104 N Marietta St",
    "sg:city": "St Clairsville",
    "sg:classifiers": [
      {
        "category": "Professional",
        "subcategory": "Business Services",
        "type": "Services"
      }
    ],
    "sg:phone": "+1 740 695 6404",
    "sg:postcode": "43950",
    "sg:province": "OH",
    "sg:tags": [
      "recording",
      "studio"
    ],
    "wof:name": "Blacksmith Recording",
    "wof:placetype": "venue"
  },
  "geometry": {"coordinates":[-80.903379,40.081148],"type":"Point"}
}
