{
  "type": "Feature",
  "properties": {
    "iso:country":"US",
    "sg:address":"915 Trumbull St",
    "sg:city":"Xenia",
    "sg:classifiers":[
        {
            "category":"Retail",
            "subcategory":"Auto Repair",
            "type":"Services"
        }
    ],
    "sg:phone":"+1 937 374 2424",
    "sg:postcode":"45385",
    "sg:province":"OH",
    "sg:tags":[
        "machine",
        "automobile",
        "shop"
    ],
    "wof:name":"Zajbel Machining & Welding",
    "wof:placetype":"venue"
},
  "geometry": {"coordinates":[-83.944902,39.681424],"type":"Point"}
}