{
  "type": "Feature",
  "properties": {
    "addr:full":"16400 Broadway Ave Cleveland OH 44137",
    "addr:housenumber":"16400",
    "addr:postcode":"44137",
    "addr:street":"Broadway Ave",
    "iso:country":"US",
    "sg:address":"16400 Broadway Ave",
    "sg:city":"Cleveland",
    "sg:classifiers":[
        {
            "category":"Recreation",
            "type":"Entertainment"
        }
    ],
    "sg:phone":"+1 216 587 4781",
    "sg:postcode":"44137",
    "sg:province":"OH",
    "sg:tags":[
        "psychic",
        "medium"
    ],
    "wof:name":"Egyptian Readings By Rhonda",
    "wof:placetype":"venue"
},
  "geometry": {"coordinates":[-81.566395,41.412812],"type":"Point"}
}