{
  "type": "Feature",
  "properties": {
    "iso:country":"US",
    "sg:address":"1710 Westwood Ave",
    "sg:city":"Cincinnati",
    "sg:classifiers":[
        {
            "category":"Building & Trades",
            "subcategory":"Construction",
            "type":"Services"
        }
    ],
    "sg:phone":"+1 513 557 2464",
    "sg:postcode":"45214",
    "sg:province":"OH",
    "sg:tags":[
        "contractor"
    ],
    "wof:name":"Complete Roofing Contractors",
    "wof:placetype":"venue"
},
  "geometry": {"coordinates":[-84.55615299999999,39.12529],"type":"Point"}
}