{
  "type": "Feature",
  "properties": {
    "addr:full": "1710 Westwood Ave Cincinnati OH 45214",
    "addr:housenumber": "1710",
    "addr:postcode": "45214",
    "addr:street": "Westwood Ave",
    "iso:country": "US",
    "sg:address": "1710 Westwood Ave",
    "sg:city": "Cincinnati",
    "sg:classifiers": [
      {
        "category": "Building \u0026 Trades",
        "subcategory": "Construction",
        "type": "Services"
      }
    ],
    "sg:phone": "+1 513 557 2464",
    "sg:postcode": "45214",
    "sg:province": "OH",
    "sg:tags": [
      "contractor"
    ],
    "wof:name": "Complete Roofing Contractors",
    "wof:placetype": "venue"
  },
  "geometry": {"coordinates":[-84.556153,39.12529],"type":"Point"}
}
