{
  "type": "Feature",
  "properties": {
    "iso:country":"US",
    "sg:address":"4685 Old Columbus Rd NW",
    "sg:city":"Carroll",
    "sg:classifiers":[
        {
            "category":"Building & Trades",
            "subcategory":"Construction",
            "type":"Services"
        }
    ],
    "sg:phone":"+1 740 756 2000",
    "sg:postcode":"43112",
    "sg:province":"OH",
    "sg:tags":[
        "new",
        "housing",
        "contractor"
    ],
    "wof:name":"American Heritage Homes Corp",
    "wof:placetype":"venue"
},
  "geometry": {"coordinates":[-82.686749,39.772487],"type":"Point"}
}