{
  "type": "Feature",
  "properties": {
    "iso:country":"US",
    "sg:address":"5702 Olive Ave",
    "sg:city":"Franklin",
    "sg:classifiers":[
        {
            "category":"Organizations",
            "subcategory":"Religious Organization",
            "type":"Services"
        }
    ],
    "sg:phone":"+1 937 746 4658",
    "sg:postcode":"45005",
    "sg:province":"OH",
    "sg:tags":[
        "church"
    ],
    "wof:name":"Faith Missionary Baptist Chr",
    "wof:placetype":"venue"
},
  "geometry": {"coordinates":[-84.306535,39.544749],"type":"Point"}
}