{
  "type": "Feature",
  "properties": {
    "iso:country":"US",
    "sg:address":"3950 Red Bud Ave",
    "sg:city":"Cincinnati",
    "sg:classifiers":[
        {
            "category":"Building & Trades",
            "subcategory":"Construction",
            "type":"Services"
        }
    ],
    "sg:phone":"+1 513 861 2266",
    "sg:postcode":"45229",
    "sg:province":"OH",
    "sg:tags":[
        "house"
    ],
    "wof:name":"Stuart Charles Homes LLC",
    "wof:placetype":"venue"
},
  "geometry": {"coordinates":[-84.487827,39.155865],"type":"Point"}
}