{
  "type": "Feature",
  "properties": {
    "iso:country":"US",
    "sg:address":"3930 Sunset Blvd",
    "sg:city":"Youngstown",
    "sg:classifiers":[
        {
            "category":"Communications",
            "subcategory":"Radio Station",
            "type":"Services"
        }
    ],
    "sg:phone":"+1 330 782 4062",
    "sg:postcode":"44512",
    "sg:province":"OH",
    "sg:tags":[
        "company",
        "broadcasting"
    ],
    "sg:website":"www.wyfx.com",
    "wof:name":"WYFX",
    "wof:placetype":"venue"
},
  "geometry": {"coordinates":[-80.646974,41.05875],"type":"Point"}
}