{
  "type": "Feature",
  "properties": {
    "addr:full": "1144 US Hwy 20 E Norwalk OH 44857",
    "addr:housenumber": "1144",
    "addr:postcode": "44857",
    "addr:street": "Us Hwy 20 E",
    "iso:country": "US",
    "sg:address": "1144 US Hwy 20 E",
    "sg:city": "Norwalk",
    "sg:classifiers": [
      {
        "category": "Manufacturing",
        "subcategory": "Tools \u0026 Machinery",
        "type": "Manufacturing \u0026 Wholesale Goods"
      }
    ],
    "sg:phone": "+1 419 668 0171",
    "sg:postcode": "44857",
    "sg:province": "OH",
    "sg:tags": [
      "operator",
      "construction",
      "trucking",
      "local",
      "mfg"
    ],
    "wof:name": "Moyers Excavating",
    "wof:placetype": "venue"
  },
  "geometry": {"coordinates":[-82.548206,41.249327],"type":"Point"}
}
