{
  "type": "Feature",
  "properties": {
    "iso:country":"US",
    "sg:address":"1144 US Hwy 20 E",
    "sg:city":"Norwalk",
    "sg:classifiers":[
        {
            "category":"Manufacturing",
            "subcategory":"Tools & Machinery",
            "type":"Manufacturing & Wholesale Goods"
        }
    ],
    "sg:phone":"+1 419 668 0171",
    "sg:postcode":"44857",
    "sg:province":"OH",
    "sg:tags":[
        "operator",
        "construction",
        "trucking",
        "local",
        "mfg"
    ],
    "wof:name":"Moyers Excavating",
    "wof:placetype":"venue"
},
  "geometry": {"coordinates":[-82.54820599999999,41.249327],"type":"Point"}
}