{
  "type": "Feature",
  "properties": {
    "addr:full": "29516 Blanchard Rd Defiance OH 43512",
    "addr:housenumber": "29516",
    "addr:postcode": "43512",
    "addr:street": "Blanchard Rd",
    "iso:country": "US",
    "sg:address": "29516 Blanchard Rd",
    "sg:city": "Defiance",
    "sg:phone": "+1 419 395 1700",
    "sg:postcode": "43512",
    "sg:province": "OH",
    "sg:tags": [
      "farm",
      "corn",
      "soybean"
    ],
    "wof:name": "Roth Duwayne",
    "wof:placetype": "venue"
  },
  "geometry": {"coordinates":[-84.254156,41.20924],"type":"Point"}
}
