{
  "type": "Feature",
  "properties": {
    "iso:country":"US",
    "sg:address":"29516 Blanchard Rd",
    "sg:city":"Defiance",
    "sg:phone":"+1 419 395 1700",
    "sg:postcode":"43512",
    "sg:province":"OH",
    "sg:tags":[
        "farm",
        "corn",
        "soybean"
    ],
    "wof:name":"Roth Duwayne",
    "wof:placetype":"venue"
},
  "geometry": {"coordinates":[-84.25415599999999,41.20924],"type":"Point"}
}