{
  "type": "Feature",
  "properties": {
    "addr:full": "4601 N High St Columbus OH 43214",
    "addr:housenumber": "4601",
    "addr:postcode": "43214",
    "addr:street": "N High St",
    "iso:country": "US",
    "sg:address": "4601 N High St",
    "sg:city": "Columbus",
    "sg:classifiers": [
      {
        "category": "Health Services",
        "subcategory": "Doctor",
        "type": "Services"
      }
    ],
    "sg:phone": "+1 614 263 1662",
    "sg:postcode": "43214",
    "sg:province": "OH",
    "sg:tags": [
      "dentist"
    ],
    "wof:name": "Kurt J Ayers DDS",
    "wof:placetype": "venue"
  },
  "geometry": {"coordinates":[-83.019913,40.056323],"type":"Point"}
}
