{
  "type": "Feature",
  "properties": {
    "iso:country":"US",
    "sg:address":"2040 Augusta Dr SE",
    "sg:city":"Massillon",
    "sg:classifiers":[
        {
            "category":"Wholesale",
            "subcategory":"Scrap",
            "type":"Manufacturing & Wholesale Goods"
        }
    ],
    "sg:phone":"+1 330 830 5335",
    "sg:postcode":"44646",
    "sg:province":"OH",
    "sg:tags":[
        "metal",
        "ferrous"
    ],
    "wof:name":"Ferrous Solutions Inc",
    "wof:placetype":"venue"
},
  "geometry": {"coordinates":[-81.496285,40.774186],"type":"Point"}
}