{
  "type": "Feature",
  "properties": {
    "iso:country":"US",
    "sg:address":"800 Compton Rd",
    "sg:city":"Cincinnati",
    "sg:classifiers":[
        {
            "category":"Banks & Credit Unions",
            "subcategory":"Investment Brokerage",
            "type":"Services"
        }
    ],
    "sg:phone":"+1 513 729 4430",
    "sg:postcode":"45231",
    "sg:province":"OH",
    "sg:tags":[
        "consultant",
        "planning",
        "financial"
    ],
    "wof:name":"Gary E Hollander & Assoc",
    "wof:placetype":"venue"
},
  "geometry": {"coordinates":[-84.511915,39.233935],"type":"Point"}
}