{
  "type": "Feature",
  "properties": {
    "addr:full":"5410 S State Rte 49 Greenville OH 45331",
    "addr:housenumber":"5410",
    "addr:postcode":"45331",
    "addr:street":"S State Rte 49",
    "iso:country":"US",
    "sg:address":"5410 S State Rte 49",
    "sg:city":"Greenville",
    "sg:classifiers":[
        {
            "category":"Manufacturing",
            "subcategory":"Glass & Minerals",
            "type":"Manufacturing & Wholesale Goods"
        }
    ],
    "sg:phone":"+1 937 548 1101",
    "sg:postcode":"45331",
    "sg:province":"OH",
    "sg:tags":[
        "concrete",
        "material",
        "mfg"
    ],
    "wof:name":"Wayne Builders Supply",
    "wof:placetype":"venue"
},
  "geometry": {"coordinates":[-84.632688,40.073498],"type":"Point"}
}