{
  "type": "Feature",
  "properties": {
    "addr:full":"1279 E Hudson St Columbus OH 43211",
    "addr:housenumber":"1279",
    "addr:postcode":"43211",
    "addr:street":"E Hudson St",
    "iso:country":"US",
    "sg:address":"1279 E Hudson St",
    "sg:city":"Columbus",
    "sg:classifiers":[
        {
            "category":"Home & Garden",
            "subcategory":"Building Materials",
            "type":"Retail Goods"
        },
        {
            "category":"Retail",
            "subcategory":"Auto Repair",
            "type":"Services"
        }
    ],
    "sg:phone":"+1 614 268 5055",
    "sg:postcode":"43211",
    "sg:province":"OH",
    "sg:tags":[
        "plate",
        "window",
        "replacement",
        "installation",
        "glass"
    ],
    "wof:name":"Mid Ohio Glass Co Inc",
    "wof:placetype":"venue"
},
  "geometry": {"coordinates":[-82.97643600000001,40.013992],"type":"Point"}
}