{
  "type": "Feature",
  "properties": {
    "iso:country":"US",
    "sg:address":"2156 Schappelle Ln",
    "sg:city":"Cincinnati",
    "sg:classifiers":[
        {
            "category":"Building & Trades",
            "subcategory":"Cleaning & Sanitation",
            "type":"Services"
        }
    ],
    "sg:phone":"+1 513 851 8778",
    "sg:postcode":"45240",
    "sg:province":"OH",
    "sg:tags":[
        "residential",
        "elderly",
        "working",
        "for"
    ],
    "wof:name":"House Mates Maid Services",
    "wof:placetype":"venue"
},
  "geometry": {"coordinates":[-84.557885,39.283396],"type":"Point"}
}