{
  "type": "Feature",
  "properties": {
    "addr:full": "2156 Schappelle Ln Cincinnati OH 45240",
    "addr:housenumber": "2156",
    "addr:postcode": "45240",
    "addr:street": "Schappelle Ln",
    "iso:country": "US",
    "sg:address": "2156 Schappelle Ln",
    "sg:city": "Cincinnati",
    "sg:classifiers": [
      {
        "category": "Building \u0026 Trades",
        "subcategory": "Cleaning \u0026 Sanitation",
        "type": "Services"
      }
    ],
    "sg:phone": "+1 513 851 8778",
    "sg:postcode": "45240",
    "sg:province": "OH",
    "sg:tags": [
      "residential",
      "elderly",
      "working",
      "for"
    ],
    "wof:name": "House Mates Maid Services",
    "wof:placetype": "venue"
  },
  "geometry": {"coordinates":[-84.557885,39.283396],"type":"Point"}
}
