{
  "type": "Feature",
  "properties": {
    "iso:country":"US",
    "sg:address":"1566 Brighton Ave NE",
    "sg:city":"Warren",
    "sg:classifiers":[
        {
            "category":"Retail",
            "subcategory":"Auto Repair",
            "type":"Services"
        }
    ],
    "sg:phone":"+1 330 372 5499",
    "sg:postcode":"44483",
    "sg:province":"OH",
    "sg:tags":[
        "automotive",
        "r",
        "general",
        "supply"
    ],
    "wof:name":"Koby Radiator Service",
    "wof:placetype":"venue"
},
  "geometry": {"coordinates":[-80.80358,41.250788],"type":"Point"}
}