{
  "type": "Feature",
  "properties": {
    "iso:country":"US",
    "sg:address":"1534 W Church St",
    "sg:city":"Newark",
    "sg:classifiers":[
        {
            "category":"Health Services",
            "subcategory":"Doctor",
            "type":"Services"
        }
    ],
    "sg:phone":"+1 740 344 4549",
    "sg:postcode":"43055",
    "sg:province":"OH",
    "sg:tags":[
        "dentist"
    ],
    "wof:name":"Jeffery P Guest DDS",
    "wof:placetype":"venue"
},
  "geometry": {"coordinates":[-82.448165,40.058181],"type":"Point"}
}