{
  "type": "Feature",
  "properties": {
    "iso:country":"US",
    "sg:address":"1030 Seville Rd",
    "sg:city":"Wadsworth",
    "sg:classifiers":[
        {
            "category":"Manufacturing",
            "subcategory":"Metals",
            "type":"Manufacturing & Wholesale Goods"
        }
    ],
    "sg:phone":"+1 330 336 7403",
    "sg:postcode":"44281",
    "sg:province":"OH",
    "sg:tags":[
        "foundry"
    ],
    "wof:name":"World Cast Technology",
    "wof:placetype":"venue"
},
  "geometry": {"coordinates":[-81.761135,41.01025],"type":"Point"}
}