{
  "type": "Feature",
  "properties": {
    "addr:full": "1030 Seville Rd Wadsworth OH 44281",
    "addr:housenumber": "1030",
    "addr:postcode": "44281",
    "addr:street": "Seville Rd",
    "iso:country": "US",
    "sg:address": "1030 Seville Rd",
    "sg:city": "Wadsworth",
    "sg:classifiers": [
      {
        "category": "Manufacturing",
        "subcategory": "Metals",
        "type": "Manufacturing \u0026 Wholesale Goods"
      }
    ],
    "sg:phone": "+1 330 336 7403",
    "sg:postcode": "44281",
    "sg:province": "OH",
    "sg:tags": [
      "foundry"
    ],
    "wof:name": "World Cast Technology",
    "wof:placetype": "venue"
  },
  "geometry": {"coordinates":[-81.761135,41.01025],"type":"Point"}
}
