{
  "type": "Feature",
  "properties": {
    "addr:full": "2920 Campbell St Sandusky OH 44870",
    "addr:housenumber": "2920",
    "addr:postcode": "44870",
    "addr:street": "Campbell St",
    "iso:country": "US",
    "sg:address": "2920 Campbell St",
    "sg:city": "Sandusky",
    "sg:classifiers": [
      {
        "category": "Real Estate",
        "subcategory": "Real Estate Agent",
        "type": "Services"
      }
    ],
    "sg:phone": "+1 419 627 1711",
    "sg:postcode": "44870",
    "sg:province": "OH",
    "wof:name": "Decker Realty Inc",
    "wof:placetype": "venue"
  },
  "geometry": {"coordinates":[-82.703582,41.424472],"type":"Point"}
}
