{
  "type": "Feature",
  "properties": {
    "iso:country":"US",
    "sg:address":"2561 Harding Hwy E",
    "sg:city":"Marion",
    "sg:classifiers":[
        {
            "category":"Government",
            "subcategory":"Office",
            "type":"Public Place"
        }
    ],
    "sg:phone":"+1 740 387 1029",
    "sg:postcode":"43302",
    "sg:province":"OH",
    "sg:tags":[
        "national",
        "security"
    ],
    "wof:name":"National Guard",
    "wof:placetype":"venue"
},
  "geometry": {"coordinates":[-83.06590199999999,40.602942],"type":"Point"}
}