{
  "type": "Feature",
  "properties": {
    "iso:country":"US",
    "sg:address":"2660 Fisher Rd",
    "sg:city":"Columbus",
    "sg:classifiers":[
        {
            "category":"Wholesale",
            "subcategory":"Home Furnishings",
            "type":"Manufacturing & Wholesale Goods"
        }
    ],
    "sg:phone":"+1 614 274 6285",
    "sg:postcode":"43204",
    "sg:province":"OH",
    "sg:tags":[
        "floor",
        "covering",
        "rug",
        "carpet"
    ],
    "wof:name":"Dealers Supply North Inc",
    "wof:placetype":"venue"
},
  "geometry": {"coordinates":[-83.074455,39.973613],"type":"Point"}
}