{
  "type": "Feature",
  "properties": {
    "addr:full": "5234 Southern Blvd Youngstown OH 44512",
    "addr:housenumber": "5234",
    "addr:postcode": "44512",
    "addr:street": "Southern Blvd",
    "iso:country": "US",
    "sg:address": "5234 Southern Blvd",
    "sg:city": "Youngstown",
    "sg:classifiers": [
      {
        "category": "Restaurant",
        "type": "Food \u0026 Drink"
      }
    ],
    "sg:phone": "+1 330 788 8204",
    "sg:postcode": "44512",
    "sg:province": "OH",
    "sg:tags": [
      "eating",
      "caterer"
    ],
    "wof:name": "Cathy's Custom Catering",
    "wof:placetype": "venue"
  },
  "geometry": {"coordinates":[-80.657851,41.046461],"type":"Point"}
}
