{
  "type": "Feature",
  "properties": {
    "addr:full":"1241 Industrial Pkwy N Brunswick OH 44212",
    "addr:housenumber":"1241",
    "addr:postcode":"44212",
    "addr:street":"Industrial Pkwy N",
    "iso:country":"US",
    "sg:address":"1241 Industrial Pkwy N",
    "sg:city":"Brunswick",
    "sg:classifiers":[
        {
            "category":"Building & Trades",
            "subcategory":"Electrical",
            "type":"Services"
        }
    ],
    "sg:phone":"+1 330 273 2878",
    "sg:postcode":"44212",
    "sg:province":"OH",
    "sg:tags":[
        "electrical",
        "contractor"
    ],
    "wof:name":"Coleman Electric",
    "wof:placetype":"venue"
},
  "geometry": {"coordinates":[-81.796396,41.241456],"type":"Point"}
}