{
  "type": "Feature",
  "properties": {
    "iso:country":"US",
    "sg:address":"5439 Salem Ave",
    "sg:city":"Dayton",
    "sg:classifiers":[
        {
            "category":"Shopping",
            "subcategory":"Department Store",
            "type":"Retail Goods"
        }
    ],
    "sg:phone":"+1 937 854 5462",
    "sg:postcode":"45426",
    "sg:province":"OH",
    "wof:name":"A J Wright",
    "wof:placetype":"venue"
},
  "geometry": {"coordinates":[-84.286732,39.821138],"type":"Point"}
}