{
  "type": "Feature",
  "properties": {
    "addr:full":"5552 Cheviot Rd Cincinnati OH 45247",
    "addr:housenumber":"5552",
    "addr:postcode":"45247",
    "addr:street":"Cheviot Rd",
    "iso:country":"US",
    "sg:address":"5552 Cheviot Rd",
    "sg:city":"Cincinnati",
    "sg:classifiers":[
        {
            "category":"Professional",
            "subcategory":"Accounting & Tax Preparation",
            "type":"Services"
        }
    ],
    "sg:phone":"+1 513 245 1000",
    "sg:postcode":"45247",
    "sg:province":"OH",
    "wof:name":"Grear & Company",
    "wof:placetype":"venue"
},
  "geometry": {"coordinates":[-84.599187,39.191044],"type":"Point"}
}