{
  "type": "Feature",
  "properties": {
    "addr:full":"9774 Trease Rd Wadsworth OH 44281",
    "addr:housenumber":"9774",
    "addr:postcode":"44281",
    "addr:street":"Trease Rd",
    "iso:country":"US",
    "sg:address":"9774 Trease Rd",
    "sg:city":"Wadsworth",
    "sg:classifiers":[
        {
            "category":"Retail",
            "subcategory":"Auto Repair",
            "type":"Services"
        }
    ],
    "sg:phone":"+1 330 336 8815",
    "sg:postcode":"44281",
    "sg:province":"OH",
    "sg:tags":[
        "truck"
    ],
    "wof:name":"Ameritruck",
    "wof:placetype":"venue"
},
  "geometry": {"coordinates":[-81.74854999999999,41.006657],"type":"Point"}
}