{
  "type": "Feature",
  "properties": {
    "addr:full":"11960 Lockage St NW Canal Fulton OH 44614",
    "addr:housenumber":"11960",
    "addr:postcode":"44614",
    "addr:street":"Lockage St Nw",
    "iso:country":"US",
    "sg:address":"11960 Lockage St NW",
    "sg:city":"Canal Fulton",
    "sg:phone":"+1 330 854 3124",
    "sg:postcode":"44614",
    "sg:province":"OH",
    "sg:tags":[
        "farm",
        "corn"
    ],
    "wof:name":"Robert Putman",
    "wof:placetype":"venue"
},
  "geometry": {"coordinates":[-81.575941,40.876275],"type":"Point"}
}