{
  "type": "Feature",
  "properties": {
    "addr:full":"8549 Indian Creek Dr Youngstown OH 44514",
    "addr:housenumber":"8549",
    "addr:postcode":"44514",
    "addr:street":"Indian Creek Dr",
    "iso:country":"US",
    "sg:address":"8549 Indian Creek Dr",
    "sg:city":"Youngstown",
    "sg:classifiers":[
        {
            "category":"Building & Trades",
            "subcategory":"Construction",
            "type":"Services"
        }
    ],
    "sg:phone":"+1 330 758 3885",
    "sg:postcode":"44514",
    "sg:province":"OH",
    "sg:tags":[
        "painter"
    ],
    "wof:name":"George Babyak Painting & Decor",
    "wof:placetype":"venue"
},
  "geometry": {"coordinates":[-80.64402800000001,40.989352],"type":"Point"}
}