{
  "type": "Feature",
  "properties": {
    "addr:full": "1465 S Reynolds Rd Toledo OH 43615",
    "addr:housenumber": "1465",
    "addr:postcode": "43615",
    "addr:street": "S Reynolds Rd",
    "iso:country": "US",
    "sg:address": "1465 S Reynolds Rd",
    "sg:city": "Toledo",
    "sg:classifiers": [
      {
        "category": "Shopping",
        "subcategory": "Optical Goods",
        "type": "Retail Goods"
      }
    ],
    "sg:phone": "+1 419 385 4011",
    "sg:postcode": "43615",
    "sg:province": "OH",
    "wof:name": "D O C Eyeworld",
    "wof:placetype": "venue"
  },
  "geometry": {"coordinates":[-83.664519,41.614216],"type":"Point"}
}
