{
  "type": "Feature",
  "properties": {
    "iso:country":"US",
    "sg:address":"313 Monroe St",
    "sg:city":"Eldorado",
    "sg:classifiers":[
        {
            "category":"Building & Trades",
            "subcategory":"Construction",
            "type":"Services"
        }
    ],
    "sg:phone":"+1 937 273 3003",
    "sg:postcode":"45321",
    "sg:province":"OH",
    "sg:tags":[
        "house"
    ],
    "wof:name":"Jo Painting & Remodeling",
    "wof:placetype":"venue"
},
  "geometry": {"coordinates":[-84.674245,39.90468],"type":"Point"}
}