{
  "type": "Feature",
  "properties": {
    "addr:full": "313 Monroe St Eldorado OH 45321",
    "addr:housenumber": "313",
    "addr:postcode": "45321",
    "addr:street": "Monroe St",
    "iso:country": "US",
    "sg:address": "313 Monroe St",
    "sg:city": "Eldorado",
    "sg:classifiers": [
      {
        "category": "Building \u0026 Trades",
        "subcategory": "Construction",
        "type": "Services"
      }
    ],
    "sg:phone": "+1 937 273 3003",
    "sg:postcode": "45321",
    "sg:province": "OH",
    "sg:tags": [
      "house"
    ],
    "wof:name": "Jo Painting \u0026 Remodeling",
    "wof:placetype": "venue"
  },
  "geometry": {"coordinates":[-84.674245,39.90468],"type":"Point"}
}
