{
  "type": "Feature",
  "properties": {
    "iso:country":"US",
    "sg:address":"17407 Lorain Ave",
    "sg:city":"Cleveland",
    "sg:classifiers":[
        {
            "category":"Building & Trades",
            "subcategory":"Construction",
            "type":"Services"
        }
    ],
    "sg:phone":"+1 216 252 7500",
    "sg:postcode":"44111",
    "sg:province":"OH",
    "sg:tags":[
        "masonry",
        "contractor"
    ],
    "wof:name":"Ash Masonry & Restoration",
    "wof:placetype":"venue"
},
  "geometry": {"coordinates":[-81.817586,41.450059],"type":"Point"}
}