{
  "type": "Feature",
  "properties": {
    "iso:country":"US",
    "sg:address":"8795 Edison St NE",
    "sg:city":"Louisville",
    "sg:classifiers":[
        {
            "category":"Freight",
            "type":"Transportation"
        }
    ],
    "sg:phone":"+1 330 935 0372",
    "sg:postcode":"44641",
    "sg:province":"OH",
    "sg:tags":[
        "local",
        "trucking"
    ],
    "wof:name":"Baker Truck Service",
    "wof:placetype":"venue"
},
  "geometry": {"coordinates":[-81.228072,40.951372],"type":"Point"}
}