{
  "type": "Feature",
  "properties": {
    "addr:full": "1333 W 7th St Cincinnati OH 45203",
    "addr:housenumber": "1333",
    "addr:postcode": "45203",
    "addr:street": "W 7Th St",
    "iso:country": "US",
    "sg:address": "1333 W 7th St",
    "sg:city": "Cincinnati",
    "sg:classifiers": [
      {
        "category": "Local Transit",
        "type": "Transportation"
      }
    ],
    "sg:phone": "+1 513 241 5466",
    "sg:postcode": "45203",
    "sg:province": "OH",
    "sg:tags": [
      "limousine"
    ],
    "wof:name": "D \u0026 T Limousine Svc Inc",
    "wof:placetype": "venue"
  },
  "geometry": {"coordinates":[-84.540618,39.103525],"type":"Point"}
}
