{
  "type": "Feature",
  "properties": {
    "iso:country":"US",
    "sg:address":"1333 W 7th St",
    "sg:city":"Cincinnati",
    "sg:classifiers":[
        {
            "category":"Local Transit",
            "type":"Transportation"
        }
    ],
    "sg:phone":"+1 513 241 5466",
    "sg:postcode":"45203",
    "sg:province":"OH",
    "sg:tags":[
        "limousine"
    ],
    "wof:name":"D & T Limousine Svc Inc",
    "wof:placetype":"venue"
},
  "geometry": {"coordinates":[-84.54061799999999,39.103525],"type":"Point"}
}