{
  "type": "Feature",
  "properties": {
    "iso:country":"US",
    "sg:address":"8606 Finlarig Dr",
    "sg:city":"Dublin",
    "sg:classifiers":[
        {
            "category":"Retail",
            "subcategory":"Animal Services",
            "type":"Services"
        }
    ],
    "sg:phone":"+1 614 764 2346",
    "sg:postcode":"43017",
    "sg:province":"OH",
    "wof:name":"J Claws Investments LLC",
    "wof:placetype":"venue"
},
  "geometry": {"coordinates":[-83.15807,40.144009],"type":"Point"}
}