{
  "type": "Feature",
  "properties": {
    "addr:full": "9816 Sherman Rd Chesterland OH 44026",
    "addr:housenumber": "9816",
    "addr:postcode": "44026",
    "addr:street": "Sherman Rd",
    "iso:country": "US",
    "sg:address": "9816 Sherman Rd",
    "sg:city": "Chesterland",
    "sg:classifiers": [
      {
        "category": "Building \u0026 Trades",
        "subcategory": "Plumbing",
        "type": "Services"
      }
    ],
    "sg:phone": "+1 440 729 0029",
    "sg:postcode": "44026",
    "sg:province": "OH",
    "sg:tags": [
      "air",
      "heating",
      "conditioning",
      "contractor"
    ],
    "wof:name": "Five Star Rfrgn AC \u0026 Htg Svcs",
    "wof:placetype": "venue"
  },
  "geometry": {"coordinates":[-81.293403,41.536536],"type":"Point"}
}
