{
  "type": "Feature",
  "properties": {
    "iso:country":"US",
    "sg:address":"621 Grafton Ave",
    "sg:city":"Dayton",
    "sg:classifiers":[
        {
            "category":"Building & Trades",
            "subcategory":"Cleaning & Sanitation",
            "type":"Services"
        }
    ],
    "sg:phone":"+1 937 274 1304",
    "sg:postcode":"45406",
    "sg:province":"OH",
    "sg:tags":[
        "janitorial",
        "contractor"
    ],
    "wof:name":"Rey-Lee Jantr & Bldg Maint Svc",
    "wof:placetype":"venue"
},
  "geometry": {"coordinates":[-84.20753499999999,39.773102],"type":"Point"}
}