{
  "type": "Feature",
  "properties": {
    "addr:full": "621 Grafton Ave Dayton OH 45406",
    "addr:housenumber": "621",
    "addr:postcode": "45406",
    "addr:street": "Grafton Ave",
    "iso:country": "US",
    "sg:address": "621 Grafton Ave",
    "sg:city": "Dayton",
    "sg:classifiers": [
      {
        "category": "Building \u0026 Trades",
        "subcategory": "Cleaning \u0026 Sanitation",
        "type": "Services"
      }
    ],
    "sg:phone": "+1 937 274 1304",
    "sg:postcode": "45406",
    "sg:province": "OH",
    "sg:tags": [
      "janitorial",
      "contractor"
    ],
    "wof:name": "Rey-Lee Jantr \u0026 Bldg Maint Svc",
    "wof:placetype": "venue"
  },
  "geometry": {"coordinates":[-84.207535,39.773102],"type":"Point"}
}
