{
  "type": "Feature",
  "properties": {
    "addr:full": "2806 Cincinnati Dayton Rd Middletown OH 45044",
    "addr:housenumber": "2806",
    "addr:postcode": "45044",
    "addr:street": "Cincinnati Dayton Rd",
    "iso:country": "US",
    "sg:address": "2806 Cincinnati Dayton Rd",
    "sg:city": "Middletown",
    "sg:classifiers": [
      {
        "category": "Retail",
        "subcategory": "Auto Repair",
        "type": "Services"
      }
    ],
    "sg:phone": "+1 513 539 7811",
    "sg:postcode": "45044",
    "sg:province": "OH",
    "sg:tags": [
      "truck"
    ],
    "wof:name": "B \u0026 W Truck \u0026 Trailer Svc",
    "wof:placetype": "venue"
  },
  "geometry": {"coordinates":[-84.342355,39.476551],"type":"Point"}
}
