{
  "type": "Feature",
  "properties": {
    "addr:full":"24367 Lorain Rd North Olmsted OH 44070",
    "addr:housenumber":"24367",
    "addr:postcode":"44070",
    "addr:street":"Lorain Rd",
    "iso:country":"US",
    "sg:address":"24367 Lorain Rd",
    "sg:city":"North Olmsted",
    "sg:classifiers":[
        {
            "category":"Restaurant",
            "type":"Food & Drink"
        }
    ],
    "sg:menulink":"http://www.allmenus.com/oh/north-olmsted/134354-subway/menu/",
    "sg:phone":"+1 440 777 9100",
    "sg:postcode":"44070",
    "sg:province":"OH",
    "sg:tags":[
        "american",
        "sandwich"
    ],
    "wof:name":"Subway",
    "wof:placetype":"venue"
},
  "geometry": {"coordinates":[-81.892928,41.427454],"type":"Point"}
}