{
  "type": "Feature",
  "properties": {
    "iso:country":"US",
    "sg:address":"2100 Neil Ave",
    "sg:city":"Columbus",
    "sg:classifiers":[
        {
            "category":"Education",
            "subcategory":"School",
            "type":"Public Place"
        }
    ],
    "sg:phone":"+1 614 292 8696",
    "sg:postcode":"43210",
    "sg:province":"OH",
    "wof:name":"Osu Public Policy & MGT Schl",
    "wof:placetype":"venue"
},
  "geometry": {"coordinates":[-83.014489,40.005381],"type":"Point"}
}