{
  "type": "Feature",
  "properties": {
    "addr:full": "2100 Neil Ave Columbus OH 43210",
    "addr:housenumber": "2100",
    "addr:postcode": "43210",
    "addr:street": "Neil Ave",
    "iso:country": "US",
    "sg:address": "2100 Neil Ave",
    "sg:city": "Columbus",
    "sg:classifiers": [
      {
        "category": "Education",
        "subcategory": "School",
        "type": "Public Place"
      }
    ],
    "sg:phone": "+1 614 292 8696",
    "sg:postcode": "43210",
    "sg:province": "OH",
    "wof:name": "Osu Public Policy \u0026 MGT Schl",
    "wof:placetype": "venue"
  },
  "geometry": {"coordinates":[-83.014489,40.005381],"type":"Point"}
}
