{
  "type": "Feature",
  "properties": {
    "addr:full": "48 Front St Berea OH 44017",
    "addr:housenumber": "48",
    "addr:postcode": "44017",
    "addr:street": "Front St",
    "iso:country": "US",
    "sg:address": "48 Front St",
    "sg:city": "Berea",
    "sg:classifiers": [
      {
        "category": "Education",
        "subcategory": "Special Training",
        "type": "Public Place"
      }
    ],
    "sg:phone": "+1 440 816 1600",
    "sg:postcode": "44017",
    "sg:province": "OH",
    "sg:tags": [
      "instruction",
      "music"
    ],
    "wof:name": "J J Haaz Guitar Science",
    "wof:placetype": "venue"
  },
  "geometry": {"coordinates":[-81.853064,41.366796],"type":"Point"}
}
