{
  "type": "Feature",
  "properties": {
    "iso:country":"US",
    "sg:address":"313 Jefferson Ave",
    "sg:city":"Toledo",
    "sg:classifiers":[
        {
            "category":"Health Services",
            "subcategory":"Doctor",
            "type":"Services"
        }
    ],
    "sg:phone":"+1 419 255 1782",
    "sg:postcode":"43604",
    "sg:province":"OH",
    "sg:tags":[
        "center"
    ],
    "wof:name":"Mildred Byer Clnic For Hmeless",
    "wof:placetype":"venue"
},
  "geometry": {"coordinates":[-83.535834,41.649941],"type":"Point"}
}