{
  "type": "Feature",
  "properties": {
    "addr:full":"97 S Main St Waynesville OH 45068",
    "addr:housenumber":"97",
    "addr:postcode":"45068",
    "addr:street":"S Main St",
    "iso:country":"US",
    "sg:address":"97 S Main St",
    "sg:city":"Waynesville",
    "sg:classifiers":[
        {
            "category":"Manufacturing",
            "subcategory":"Signs",
            "type":"Manufacturing & Wholesale Goods"
        }
    ],
    "sg:phone":"+1 513 897 1982",
    "sg:postcode":"45068",
    "sg:province":"OH",
    "wof:name":"Carlin Nostalgic Sign Co",
    "wof:placetype":"venue"
},
  "geometry": {"coordinates":[-84.086451,39.529934],"type":"Point"}
}