{
  "type": "Feature",
  "properties": {
    "addr:full": "36153 Kilarney Rd Willoughby OH 44094",
    "addr:housenumber": "36153",
    "addr:postcode": "44094",
    "addr:street": "Kilarney Rd",
    "iso:country": "US",
    "sg:address": "36153 Kilarney Rd",
    "sg:city": "Willoughby",
    "sg:classifiers": [
      {
        "category": "Arts \u0026 Performance",
        "subcategory": "Theater",
        "type": "Entertainment"
      }
    ],
    "sg:phone": "+1 440 953 0752",
    "sg:postcode": "44094",
    "sg:province": "OH",
    "sg:tags": [
      "live",
      "music"
    ],
    "wof:name": "Rob Shuss Now \u0026 Then",
    "wof:placetype": "venue"
  },
  "geometry": {"coordinates":[-81.429661,41.62337],"type":"Point"}
}
