{
  "type": "Feature",
  "properties": {
    "iso:country":"US",
    "sg:address":"36153 Kilarney Rd",
    "sg:city":"Willoughby",
    "sg:classifiers":[
        {
            "category":"Arts & Performance",
            "subcategory":"Theater",
            "type":"Entertainment"
        }
    ],
    "sg:phone":"+1 440 953 0752",
    "sg:postcode":"44094",
    "sg:province":"OH",
    "sg:tags":[
        "live",
        "music"
    ],
    "wof:name":"Rob Shuss Now & Then",
    "wof:placetype":"venue"
},
  "geometry": {"coordinates":[-81.429661,41.62337],"type":"Point"}
}