{
  "type": "Feature",
  "properties": {
    "iso:country":"US",
    "sg:address":"56755 White Oak Ln",
    "sg:city":"Senecaville",
    "sg:classifiers":[
        {
            "category":"Building & Trades",
            "subcategory":"Construction",
            "type":"Services"
        }
    ],
    "sg:phone":"+1 740 685 5142",
    "sg:postcode":"43780",
    "sg:province":"OH",
    "sg:tags":[
        "residential"
    ],
    "wof:name":"Keith Contracting",
    "wof:placetype":"venue"
},
  "geometry": {"coordinates":[-81.436835,39.917897],"type":"Point"}
}