{
  "type": "Feature",
  "properties": {
    "iso:country":"US",
    "sg:address":"1880 Shepherd Fork Rd",
    "sg:city":"Portsmouth",
    "sg:classifiers":[
        {
            "category":"Autos & Motor Vehicles",
            "subcategory":"Automobile Sales",
            "type":"Retail Goods"
        }
    ],
    "sg:phone":"+1 740 858 4356",
    "sg:postcode":"45663",
    "sg:province":"OH",
    "sg:tags":[
        "used"
    ],
    "wof:name":"Old Schoolhouse Used Cars",
    "wof:placetype":"venue"
},
  "geometry": {"coordinates":[-83.053574,38.774224],"type":"Point"}
}