{
  "type": "Feature",
  "properties": {
    "addr:full":"1171 W North St Lima OH 45805",
    "addr:housenumber":"1171",
    "addr:postcode":"45805",
    "addr:street":"W North St",
    "iso:country":"US",
    "sg:address":"1171 W North St",
    "sg:city":"Lima",
    "sg:classifiers":[
        {
            "category":"Shopping",
            "subcategory":"Musical Instruments",
            "type":"Retail Goods"
        }
    ],
    "sg:phone":"+1 419 224 6751",
    "sg:postcode":"45805",
    "sg:province":"OH",
    "wof:name":"Gromans Music Co Inc",
    "wof:placetype":"venue"
},
  "geometry": {"coordinates":[-84.12750200000001,40.743288],"type":"Point"}
}