{
  "type": "Feature",
  "properties": {
    "addr:full": "5008 Lorain Ave Cleveland OH 44102",
    "addr:housenumber": "5008",
    "addr:postcode": "44102",
    "addr:street": "Lorain Ave",
    "iso:country": "US",
    "sg:address": "5008 Lorain Ave",
    "sg:city": "Cleveland",
    "sg:classifiers": [
      {
        "category": "Wholesale",
        "subcategory": "Electrical",
        "type": "Manufacturing \u0026 Wholesale Goods"
      }
    ],
    "sg:phone": "+1 440 537 0589",
    "sg:postcode": "44102",
    "sg:province": "OH",
    "sg:tags": [
      "control",
      "security",
      "system"
    ],
    "wof:name": "K P Rolling Security",
    "wof:placetype": "venue"
  },
  "geometry": {"coordinates":[-81.722186,41.47733],"type":"Point"}
}
