{
  "type": "Feature",
  "properties": {
    "addr:full": "7975 Lake Rd Chippewa Lake OH 44215",
    "addr:housenumber": "7975",
    "addr:postcode": "44215",
    "addr:street": "Lake Rd",
    "iso:country": "US",
    "sg:address": "7975 Lake Rd",
    "sg:city": "Chippewa Lake",
    "sg:classifiers": [
      {
        "category": "Building \u0026 Trades",
        "subcategory": "Landscaping Services",
        "type": "Services"
      }
    ],
    "sg:phone": "+1 330 769 3015",
    "sg:postcode": "44215",
    "sg:province": "OH",
    "wof:name": "Chippewa Valley Tree Service",
    "wof:placetype": "venue"
  },
  "geometry": {"coordinates":[-81.897328,41.056387],"type":"Point"}
}
