{
  "type": "Feature",
  "properties": {
    "addr:full": "712 E 163rd St Cleveland OH 44110",
    "addr:housenumber": "712",
    "addr:postcode": "44110",
    "addr:street": "E 163Rd St",
    "iso:country": "US",
    "sg:address": "712 E 163rd St",
    "sg:city": "Cleveland",
    "sg:classifiers": [
      {
        "category": "Wholesale",
        "subcategory": "Machinery \u0026 Supplies",
        "type": "Manufacturing \u0026 Wholesale Goods"
      }
    ],
    "sg:phone": "+1 216 531 8300",
    "sg:postcode": "44110",
    "sg:province": "OH",
    "sg:tags": [
      "chemical",
      "industrial",
      "janitorial"
    ],
    "wof:name": "Craig Industrial Products Inc",
    "wof:placetype": "venue"
  },
  "geometry": {"coordinates":[-81.566409,41.560913],"type":"Point"}
}
