{
  "type": "Feature",
  "properties": {
    "iso:country":"US",
    "sg:address":"3846 Huffman Rd",
    "sg:city":"Medina",
    "sg:classifiers":[
        {
            "category":"Manufacturing",
            "subcategory":"Printing",
            "type":"Manufacturing & Wholesale Goods"
        }
    ],
    "sg:phone":"+1 330 721 8832",
    "sg:postcode":"44256",
    "sg:province":"OH",
    "sg:tags":[
        "printer"
    ],
    "wof:name":"Foil Tech",
    "wof:placetype":"venue"
},
  "geometry": {"coordinates":[-81.829099,41.165778],"type":"Point"}
}