{
  "type": "Feature",
  "properties": {
    "addr:full":"9200 Montgomery Rd Cincinnati OH 45242",
    "addr:housenumber":"9200",
    "addr:postcode":"45242",
    "addr:street":"Montgomery Rd",
    "iso:country":"US",
    "sg:address":"9200 Montgomery Rd",
    "sg:city":"Cincinnati",
    "sg:classifiers":[
        {
            "category":"Banks & Credit Unions",
            "subcategory":"Investment Brokerage",
            "type":"Services"
        }
    ],
    "sg:phone":"+1 513 936 5215",
    "sg:postcode":"45242",
    "sg:province":"OH",
    "sg:tags":[
        "advisory",
        "financial"
    ],
    "wof:name":"Beacon Financial Advisors",
    "wof:placetype":"venue"
},
  "geometry": {"coordinates":[-84.35668699999999,39.221578],"type":"Point"}
}