{
  "type": "Feature",
  "properties": {
    "iso:country":"US",
    "sg:address":"2385 Refugee Park",
    "sg:city":"Columbus",
    "sg:classifiers":[
        {
            "category":"Wholesale",
            "subcategory":"Auto Parts",
            "type":"Manufacturing & Wholesale Goods"
        }
    ],
    "sg:phone":"+1 614 444 0320",
    "sg:postcode":"43207",
    "sg:province":"OH",
    "sg:tags":[
        "supply"
    ],
    "wof:name":"Maxxion Tonneau Systems",
    "wof:placetype":"venue"
},
  "geometry": {"coordinates":[-82.952073,39.918462],"type":"Point"}
}