{
  "type": "Feature",
  "properties": {
    "addr:full": "2385 Refugee Park Columbus OH 43207",
    "addr:housenumber": "2385",
    "addr:postcode": "43207",
    "addr:street": "Refugee Park",
    "iso:country": "US",
    "sg:address": "2385 Refugee Park",
    "sg:city": "Columbus",
    "sg:classifiers": [
      {
        "category": "Wholesale",
        "subcategory": "Auto Parts",
        "type": "Manufacturing \u0026 Wholesale Goods"
      }
    ],
    "sg:phone": "+1 614 444 0320",
    "sg:postcode": "43207",
    "sg:province": "OH",
    "sg:tags": [
      "supply"
    ],
    "wof:name": "Maxxion Tonneau Systems",
    "wof:placetype": "venue"
  },
  "geometry": {"coordinates":[-82.952073,39.918462],"type":"Point"}
}
