{
  "type": "Feature",
  "properties": {
    "addr:full":"1539 Pro Dr Lima OH 45805",
    "addr:housenumber":"1539",
    "addr:postcode":"45805",
    "addr:street":"Pro Dr",
    "iso:country":"US",
    "sg:address":"1539 Pro Dr",
    "sg:city":"Lima",
    "sg:classifiers":[
        {
            "category":"Banks & Credit Unions",
            "subcategory":"Financial Services",
            "type":"Services"
        }
    ],
    "sg:phone":"+1 419 221 1835",
    "sg:postcode":"45805",
    "sg:province":"OH",
    "sg:tags":[
        "company",
        "holding"
    ],
    "wof:name":"Rosik Holding LLC",
    "wof:placetype":"venue"
},
  "geometry": {"coordinates":[-84.166212,40.711314],"type":"Point"}
}