{
  "type": "Feature",
  "properties": {
    "iso:country":"US",
    "sg:address":"5001 Fishburg Rd",
    "sg:city":"Dayton",
    "sg:classifiers":[
        {
            "category":"Organizations",
            "subcategory":"Religious Organization",
            "type":"Services"
        }
    ],
    "sg:phone":"+1 937 233 4324",
    "sg:postcode":"45424",
    "sg:province":"OH",
    "sg:tags":[
        "church"
    ],
    "sg:website":"www.hhgcc.org",
    "wof:name":"Grace Community Church",
    "wof:placetype":"venue"
},
  "geometry": {"coordinates":[-84.131131,39.840651],"type":"Point"}
}