{
  "type": "Feature",
  "properties": {
    "iso:country":"US",
    "sg:address":"3003 Venture Ln",
    "sg:city":"Zanesville",
    "sg:classifiers":[
        {
            "category":"Restaurant",
            "type":"Food & Drink"
        }
    ],
    "sg:phone":"+1 740 453 3360",
    "sg:postcode":"43701",
    "sg:province":"OH",
    "sg:tags":[
        "eating"
    ],
    "wof:name":"Airport Subway",
    "wof:placetype":"venue"
},
  "geometry": {"coordinates":[-81.995087,39.981063],"type":"Point"}
}