{
  "type": "Feature",
  "properties": {
    "addr:full": "1370 Washington St Stockport OH 43787",
    "addr:housenumber": "1370",
    "addr:postcode": "43787",
    "addr:street": "Washington St",
    "iso:country": "US",
    "sg:address": "1370 Washington St",
    "sg:city": "Stockport",
    "sg:classifiers": [
      {
        "category": "Government",
        "subcategory": "Fire Station",
        "type": "Public Place"
      }
    ],
    "sg:phone": "+1 740 557 3605",
    "sg:postcode": "43787",
    "sg:province": "OH",
    "sg:tags": [
      "department"
    ],
    "wof:name": "Pennsville Fire Dept",
    "wof:placetype": "venue"
  },
  "geometry": {"coordinates":[-81.854528,39.574642],"type":"Point"}
}
