{
  "type": "Feature",
  "properties": {
    "iso:country":"US",
    "sg:address":"1921 Alvin Ave",
    "sg:city":"Cleveland",
    "sg:classifiers":[
        {
            "category":"Building & Trades",
            "subcategory":"Electrical",
            "type":"Services"
        }
    ],
    "sg:phone":"+1 216 749 5034",
    "sg:postcode":"44109",
    "sg:province":"OH",
    "sg:tags":[
        "electrical",
        "contractor"
    ],
    "wof:name":"Halusker Electrical Systems",
    "wof:placetype":"venue"
},
  "geometry": {"coordinates":[-81.69412,41.426982],"type":"Point"}
}