{
  "type": "Feature",
  "properties": {
    "addr:full": "9531 Colerain Ave Cincinnati OH 45251",
    "addr:housenumber": "9531",
    "addr:postcode": "45251",
    "addr:street": "Colerain Ave",
    "iso:country": "US",
    "sg:address": "9531 Colerain Ave",
    "sg:city": "Cincinnati",
    "sg:classifiers": [
      {
        "category": "Shopping",
        "type": "Retail Goods"
      }
    ],
    "sg:phone": "+1 513 923 1383",
    "sg:postcode": "45251",
    "sg:province": "OH",
    "sg:tags": [
      "candle"
    ],
    "wof:name": "Candle Cottage",
    "wof:placetype": "venue"
  },
  "geometry": {"coordinates":[-84.596754,39.248248],"type":"Point"}
}
