{
  "type": "Feature",
  "properties": {
    "addr:full":"221 N Detroit Ave Toledo OH 43607",
    "addr:housenumber":"221",
    "addr:postcode":"43607",
    "addr:street":"N Detroit Ave",
    "iso:country":"US",
    "sg:address":"221 N Detroit Ave",
    "sg:city":"Toledo",
    "sg:classifiers":[
        {
            "category":"Building & Trades",
            "subcategory":"Construction",
            "type":"Services"
        }
    ],
    "sg:phone":"+1 419 241 6422",
    "sg:postcode":"43607",
    "sg:province":"OH",
    "sg:tags":[
        "elevator"
    ],
    "wof:name":"Toledo Elevator & Machine Co",
    "wof:placetype":"venue"
},
  "geometry": {"coordinates":[-83.584447,41.642544],"type":"Point"}
}