{
  "type": "Feature",
  "properties": {
    "addr:full":"5443 Dixie Hwy Fairfield OH 45014",
    "addr:housenumber":"5443",
    "addr:postcode":"45014",
    "addr:street":"Dixie Hwy",
    "iso:country":"US",
    "sg:address":"5443 Dixie Hwy",
    "sg:city":"Fairfield",
    "sg:classifiers":[
        {
            "category":"Retail",
            "subcategory":"Auto Repair",
            "type":"Services"
        }
    ],
    "sg:phone":"+1 513 275 4387",
    "sg:postcode":"45014",
    "sg:province":"OH",
    "sg:tags":[
        "repairing",
        "automobile",
        "brake"
    ],
    "sg:website":"http://www.tomtracker.com/redirect.cfm?bID=4837&hID=111353",
    "wof:name":"Meineke Car Care Center",
    "wof:placetype":"venue"
},
  "geometry": {"coordinates":[-84.524854,39.334295],"type":"Point"}
}