{
  "type": "Feature",
  "properties": {
    "addr:full": "1789 Tri County Hwy Williamsburg OH 45176",
    "addr:housenumber": "1789",
    "addr:postcode": "45176",
    "addr:street": "Tri County Hwy",
    "iso:country": "US",
    "sg:address": "1789 Tri County Hwy",
    "sg:city": "Williamsburg",
    "sg:classifiers": [
      {
        "category": "Organizations",
        "subcategory": "Religious Organization",
        "type": "Services"
      }
    ],
    "sg:phone": "+1 937 379 2851",
    "sg:postcode": "45176",
    "sg:province": "OH",
    "sg:tags": [
      "church"
    ],
    "wof:name": "Feesburg Worship Ctr",
    "wof:placetype": "venue"
  },
  "geometry": {"coordinates":[-83.996605,39.042885],"type":"Point"}
}
