{
  "type": "Feature",
  "properties": {
    "addr:full":"518 S High St Columbus OH 43215",
    "addr:housenumber":"518",
    "addr:postcode":"43215",
    "addr:street":"S High St",
    "iso:country":"US",
    "sg:address":"518 S High St",
    "sg:city":"Columbus",
    "sg:classifiers":[
        {
            "category":"Restaurant",
            "type":"Food & Drink"
        }
    ],
    "sg:menulink":"http://www.allmenus.com/oh/columbus/122346-quiznos-sub/menu/",
    "sg:phone":"+1 614 221 6962",
    "sg:postcode":"43215",
    "sg:province":"OH",
    "sg:tags":[
        "wrap",
        "american",
        "sandwich"
    ],
    "wof:name":"Quiznos Sub",
    "wof:placetype":"venue"
},
  "geometry": {"coordinates":[-82.998614,39.951551],"type":"Point"}
}