{
  "type": "Feature",
  "properties": {
    "iso:country":"US",
    "sg:address":"1 Financial Way",
    "sg:city":"Cincinnati",
    "sg:classifiers":[
        {
            "category":"Professional",
            "subcategory":"Employment Agencies",
            "type":"Services"
        }
    ],
    "sg:phone":"+1 513 791 7770",
    "sg:postcode":"45242",
    "sg:province":"OH",
    "sg:tags":[
        "opportunity"
    ],
    "sg:website":"www.aerotek.com",
    "wof:name":"Aerotek",
    "wof:placetype":"venue"
},
  "geometry": {"coordinates":[-84.364519,39.247493],"type":"Point"}
}