{
  "type": "Feature",
  "properties": {
    "iso:country":"US",
    "sg:address":"8765 Gratis Jacksonburg Rd",
    "sg:city":"Camden",
    "sg:classifiers":[
        {
            "category":"Building & Trades",
            "subcategory":"Plumbing",
            "type":"Services"
        }
    ],
    "sg:phone":"+1 937 787 9894",
    "sg:postcode":"45311",
    "sg:province":"OH",
    "sg:tags":[
        "contractor"
    ],
    "wof:name":"A A A Professional Htg & Co",
    "wof:placetype":"venue"
},
  "geometry": {"coordinates":[-84.536258,39.614438],"type":"Point"}
}