{
  "type": "Feature",
  "properties": {
    "iso:country":"US",
    "sg:address":"109 E Main St",
    "sg:city":"Woodville",
    "sg:classifiers":[
        {
            "category":"Shopping",
            "type":"Retail Goods"
        }
    ],
    "sg:phone":"+1 419 849 2300",
    "sg:postcode":"43469",
    "sg:province":"OH",
    "sg:tags":[
        "craft",
        "gallery",
        "dealer"
    ],
    "wof:name":"Crafts Mall Inc",
    "wof:placetype":"venue"
},
  "geometry": {"coordinates":[-83.363158,41.450409],"type":"Point"}
}