{
  "type": "Feature",
  "properties": {
    "addr:full": "10 N Main St Chagrin Falls OH 44022",
    "addr:housenumber": "10",
    "addr:postcode": "44022",
    "addr:street": "N Main St",
    "iso:country": "US",
    "sg:address": "10 N Main St",
    "sg:city": "Chagrin Falls",
    "sg:classifiers": [
      {
        "category": "Manufacturing",
        "subcategory": "Wood Products",
        "type": "Manufacturing \u0026 Wholesale Goods"
      }
    ],
    "sg:phone": "+1 440 247 3061",
    "sg:postcode": "44022",
    "sg:province": "OH",
    "sg:tags": [
      "mfg"
    ],
    "wof:name": "Wheeler \u0026 Associates",
    "wof:placetype": "venue"
  },
  "geometry": {"coordinates":[-81.391333,41.430313],"type":"Point"}
}
