{
  "type": "Feature",
  "properties": {
    "iso:country":"US",
    "sg:address":"10 N Main St",
    "sg:city":"Chagrin Falls",
    "sg:classifiers":[
        {
            "category":"Manufacturing",
            "subcategory":"Wood Products",
            "type":"Manufacturing & Wholesale Goods"
        }
    ],
    "sg:phone":"+1 440 247 3061",
    "sg:postcode":"44022",
    "sg:province":"OH",
    "sg:tags":[
        "mfg"
    ],
    "wof:name":"Wheeler & Associates",
    "wof:placetype":"venue"
},
  "geometry": {"coordinates":[-81.391333,41.430313],"type":"Point"}
}