{
  "type": "Feature",
  "properties": {
    "addr:full": "623 Highland Blvd Coshocton OH 43812",
    "addr:housenumber": "623",
    "addr:postcode": "43812",
    "addr:street": "Highland Blvd",
    "iso:country": "US",
    "sg:address": "623 Highland Blvd",
    "sg:city": "Coshocton",
    "sg:classifiers": [
      {
        "category": "Organizations",
        "subcategory": "Religious Organization",
        "type": "Services"
      }
    ],
    "sg:phone": "+1 740 622 0474",
    "sg:postcode": "43812",
    "sg:province": "OH",
    "sg:tags": [
      "clergy"
    ],
    "wof:name": "Stephen R Ward",
    "wof:placetype": "venue"
  },
  "geometry": {"coordinates":[-81.843667,40.269932],"type":"Point"}
}
