{
  "type": "Feature",
  "properties": {
    "addr:full":"2691 N Lipkey Rd North Jackson OH 44451",
    "addr:housenumber":"2691",
    "addr:postcode":"44451",
    "addr:street":"N Lipkey Rd",
    "iso:country":"US",
    "sg:address":"2691 N Lipkey Rd",
    "sg:city":"North Jackson",
    "sg:classifiers":[
        {
            "category":"Social Services",
            "subcategory":"Job Training",
            "type":"Services"
        }
    ],
    "sg:phone":"+1 330 480 3010",
    "sg:postcode":"44451",
    "sg:province":"OH",
    "sg:tags":[
        "rehabilitation"
    ],
    "wof:name":"St Elizabeth Health Ctr",
    "wof:placetype":"venue"
},
  "geometry": {"coordinates":[-80.823234,41.129078],"type":"Point"}
}