{
  "type": "Feature",
  "properties": {
    "addr:full":"641 Harris St Jackson OH 45640",
    "addr:housenumber":"641",
    "addr:postcode":"45640",
    "addr:street":"Harris St",
    "iso:country":"US",
    "sg:address":"641 Harris St",
    "sg:city":"Jackson",
    "sg:classifiers":[
        {
            "category":"Retail",
            "subcategory":"Animal Services",
            "type":"Services"
        }
    ],
    "sg:phone":"+1 740 286 6357",
    "sg:postcode":"45640",
    "sg:province":"OH",
    "wof:name":"R & S Grooming",
    "wof:placetype":"venue"
},
  "geometry": {"coordinates":[-82.63064799999999,39.043734],"type":"Point"}
}