{
  "type": "Feature",
  "properties": {
    "addr:full":"2030 Needmore Rd Dayton OH 45414",
    "addr:housenumber":"2030",
    "addr:postcode":"45414",
    "addr:street":"Needmore Rd",
    "iso:country":"US",
    "sg:address":"2030 Needmore Rd",
    "sg:city":"Dayton",
    "sg:classifiers":[
        {
            "category":"Retail",
            "subcategory":"Car Wash",
            "type":"Services"
        }
    ],
    "sg:phone":"+1 937 278 8710",
    "sg:postcode":"45414",
    "sg:province":"OH",
    "sg:tags":[
        "polishing",
        "washing"
    ],
    "wof:name":"Dayton Super Wash",
    "wof:placetype":"venue"
},
  "geometry": {"coordinates":[-84.196783,39.819583],"type":"Point"}
}