{
  "type": "Feature",
  "properties": {
    "iso:country":"US",
    "sg:address":"23 N Franklin St",
    "sg:city":"Chagrin Falls",
    "sg:classifiers":[
        {
            "category":"Professional",
            "subcategory":"Management & Consulting",
            "type":"Services"
        },
        {
            "category":"Social Services",
            "type":"Services"
        }
    ],
    "sg:phone":"+1 440 247 6622",
    "sg:postcode":"44022",
    "sg:province":"OH",
    "sg:tags":[
        "consultant",
        "counselor",
        "marriage",
        "family",
        "business"
    ],
    "wof:name":"Cardinal Family Counseling Ctr",
    "wof:placetype":"venue"
},
  "geometry": {"coordinates":[-81.391763,41.430342],"type":"Point"}
}