{
  "type": "Feature",
  "properties": {
    "iso:country":"US",
    "sg:address":"1003 Riverside Ave",
    "sg:city":"Wellsville",
    "sg:classifiers":[
        {
            "category":"Museum",
            "type":"Entertainment"
        }
    ],
    "sg:phone":"+1 330 532 1018",
    "sg:postcode":"43968",
    "sg:province":"OH",
    "wof:name":"Wellsville Historical Society",
    "wof:placetype":"venue"
},
  "geometry": {"coordinates":[-80.64731500000001,40.603054],"type":"Point"}
}