{
  "type": "Feature",
  "properties": {
    "addr:full":"820 Bank St Lodi OH 44254",
    "addr:housenumber":"820",
    "addr:postcode":"44254",
    "addr:street":"Bank St",
    "iso:country":"US",
    "sg:address":"820 Bank St",
    "sg:city":"Lodi",
    "sg:classifiers":[
        {
            "category":"Wholesale",
            "subcategory":"Stationery",
            "type":"Manufacturing & Wholesale Goods"
        }
    ],
    "sg:phone":"+1 330 948 5220",
    "sg:postcode":"44254",
    "sg:province":"OH",
    "sg:tags":[
        "packaging",
        "material"
    ],
    "wof:name":"Royal Products Intl Inc",
    "wof:placetype":"venue"
},
  "geometry": {"coordinates":[-82.028741,41.028334],"type":"Point"}
}