{
  "type": "Feature",
  "properties": {
    "iso:country":"US",
    "sg:address":"10427 Kenwood Rd",
    "sg:city":"Cincinnati",
    "sg:classifiers":[
        {
            "category":"Health Services",
            "subcategory":"Doctor",
            "type":"Services"
        }
    ],
    "sg:phone":"+1 513 984 3817",
    "sg:postcode":"45242",
    "sg:province":"OH",
    "sg:tags":[
        "dentist"
    ],
    "wof:name":"K A Guder DDS",
    "wof:placetype":"venue"
},
  "geometry": {"coordinates":[-84.375077,39.251813],"type":"Point"}
}