{
  "type": "Feature",
  "properties": {
    "addr:full":"75 E Broad St Newton Falls OH 44444",
    "addr:housenumber":"75",
    "addr:postcode":"44444",
    "addr:street":"E Broad St",
    "iso:country":"US",
    "sg:address":"75 E Broad St",
    "sg:city":"Newton Falls",
    "sg:classifiers":[
        {
            "category":"Personal",
            "subcategory":"Beauty Salon",
            "type":"Services"
        }
    ],
    "sg:phone":"+1 330 872 0820",
    "sg:postcode":"44444",
    "sg:province":"OH",
    "sg:tags":[
        "shop",
        "barber"
    ],
    "wof:name":"Marge & Bill's Beauty & Barber",
    "wof:placetype":"venue"
},
  "geometry": {"coordinates":[-80.97489,41.187672],"type":"Point"}
}