{
  "type": "Feature",
  "properties": {
    "addr:full": "4655 Stone Rd Sabina OH 45169",
    "addr:housenumber": "4655",
    "addr:postcode": "45169",
    "addr:street": "Stone Rd",
    "iso:country": "US",
    "sg:address": "4655 Stone Rd",
    "sg:city": "Sabina",
    "sg:classifiers": [
      {
        "category": "Farming",
        "subcategory": "Farm",
        "type": "Manufacturing \u0026 Wholesale Goods"
      }
    ],
    "sg:phone": "+1 937 584 2843",
    "sg:postcode": "45169",
    "sg:province": "OH",
    "sg:tags": [
      "crop",
      "general"
    ],
    "wof:name": "Beam Farms",
    "wof:placetype": "venue"
  },
  "geometry": {"coordinates":[-83.696843,39.503508],"type":"Point"}
}
