{
  "type": "Feature",
  "properties": {
    "addr:full": "552 W Broadway St New Lexington OH 43764",
    "addr:housenumber": "552",
    "addr:postcode": "43764",
    "addr:street": "W Broadway St",
    "iso:country": "US",
    "sg:address": "552 W Broadway St",
    "sg:city": "New Lexington",
    "sg:classifiers": [
      {
        "category": "Professional",
        "subcategory": "Business Services",
        "type": "Services"
      }
    ],
    "sg:phone": "+1 740 342 4460",
    "sg:postcode": "43764",
    "sg:province": "OH",
    "sg:tags": [
      "embroidery"
    ],
    "wof:name": "Kinsel Embroidery \u0026 Sports",
    "wof:placetype": "venue"
  },
  "geometry": {"coordinates":[-82.217224,39.72055],"type":"Point"}
}
