{
  "type": "Feature",
  "properties": {
    "iso:country":"US",
    "sg:address":"2500 W State St",
    "sg:city":"Alliance",
    "sg:classifiers":[
        {
            "category":"Shopping",
            "subcategory":"Department Store",
            "type":"Retail Goods"
        }
    ],
    "sg:phone":"+1 330 821 3019",
    "sg:postcode":"44601",
    "sg:province":"OH",
    "wof:name":"Kmart",
    "wof:placetype":"venue"
},
  "geometry": {"coordinates":[-81.157723,40.901955],"type":"Point"}
}