{
  "type": "Feature",
  "properties": {
    "addr:full":"145 Obetz Rd Columbus OH 43207",
    "addr:housenumber":"145",
    "addr:postcode":"43207",
    "addr:street":"Obetz Rd",
    "iso:country":"US",
    "sg:address":"145 Obetz Rd",
    "sg:city":"Columbus",
    "sg:classifiers":[
        {
            "category":"Organizations",
            "subcategory":"Religious Organization",
            "type":"Services"
        }
    ],
    "sg:phone":"+1 614 491 5253",
    "sg:postcode":"43207",
    "sg:province":"OH",
    "sg:tags":[
        "church"
    ],
    "wof:name":"Living Word Church",
    "wof:placetype":"venue"
},
  "geometry": {"coordinates":[-83.000192,39.882117],"type":"Point"}
}