{
  "type": "Feature",
  "properties": {
    "addr:full":"500 Southpark Center Strongsville OH 44136",
    "addr:housenumber":"500",
    "addr:postcode":"44136",
    "addr:street":"Southpark Center",
    "iso:country":"US",
    "sg:address":"500 Southpark Center",
    "sg:city":"Strongsville",
    "sg:classifiers":[
        {
            "category":"Restaurant",
            "type":"Food & Drink"
        }
    ],
    "sg:phone":"+1 440 238 6683",
    "sg:postcode":"44136",
    "sg:province":"OH",
    "sg:tags":[
        "eating"
    ],
    "wof:name":"Sarku Japan Restaurant",
    "wof:placetype":"venue"
},
  "geometry": {"coordinates":[-81.820449,41.310925],"type":"Point"}
}