{
  "type": "Feature",
  "properties": {
    "iso:country":"US",
    "sg:address":"3886 Lee Rd",
    "sg:city":"Cleveland",
    "sg:classifiers":[
        {
            "category":"Government",
            "subcategory":"Police Station",
            "type":"Public Place"
        }
    ],
    "sg:phone":"+1 216 348 7101",
    "sg:postcode":"44128",
    "sg:province":"OH",
    "sg:tags":[
        "protection"
    ],
    "wof:name":"Police Dept- Mini Station 1",
    "wof:placetype":"venue"
},
  "geometry": {"coordinates":[-81.56488299999999,41.454284],"type":"Point"}
}