{
  "type": "Feature",
  "properties": {
    "addr:full": "3104 W 25th St Cleveland OH 44109",
    "addr:housenumber": "3104",
    "addr:postcode": "44109",
    "addr:street": "W 25Th St",
    "iso:country": "US",
    "sg:address": "3104 W 25th St",
    "sg:city": "Cleveland",
    "sg:classifiers": [
      {
        "category": "Organizations",
        "subcategory": "Community Association",
        "type": "Services"
      }
    ],
    "sg:phone": "+1 216 661 3651",
    "sg:postcode": "44109",
    "sg:province": "OH",
    "wof:name": "Clark Metro Development Corp",
    "wof:placetype": "venue"
  },
  "geometry": {"coordinates":[-81.699865,41.469369],"type":"Point"}
}
