{
  "type": "Feature",
  "properties": {
    "addr:full": "7998 Mayfield Rd Chesterland OH 44026",
    "addr:housenumber": "7998",
    "addr:postcode": "44026",
    "addr:street": "Mayfield Rd",
    "iso:country": "US",
    "sg:address": "7998 Mayfield Rd",
    "sg:city": "Chesterland",
    "sg:classifiers": [
      {
        "category": "Wholesale",
        "subcategory": "Construction Materials",
        "type": "Manufacturing \u0026 Wholesale Goods"
      }
    ],
    "sg:phone": "+1 440 729 4261",
    "sg:postcode": "44026",
    "sg:province": "OH",
    "sg:tags": [
      "frame",
      "industrial",
      "door"
    ],
    "sg:website": "www.jldoor.com",
    "wof:name": "J \u0026 L Door Svc",
    "wof:placetype": "venue"
  },
  "geometry": {"coordinates":[-81.353969,41.52233],"type":"Point"}
}
