{
  "type": "Feature",
  "properties": {
    "iso:country":"US",
    "sg:address":"7998 Mayfield Rd",
    "sg:city":"Chesterland",
    "sg:classifiers":[
        {
            "category":"Wholesale",
            "subcategory":"Construction Materials",
            "type":"Manufacturing & Wholesale Goods"
        }
    ],
    "sg:phone":"+1 440 729 4261",
    "sg:postcode":"44026",
    "sg:province":"OH",
    "sg:tags":[
        "frame",
        "industrial",
        "door"
    ],
    "sg:website":"www.jldoor.com",
    "wof:name":"J & L Door Svc",
    "wof:placetype":"venue"
},
  "geometry": {"coordinates":[-81.35396900000001,41.52233],"type":"Point"}
}