{
  "type": "Feature",
  "properties": {
    "addr:full": "2690 Geraldine Dr Cincinnati OH 45239",
    "addr:housenumber": "2690",
    "addr:postcode": "45239",
    "addr:street": "Geraldine Dr",
    "iso:country": "US",
    "sg:address": "2690 Geraldine Dr",
    "sg:city": "Cincinnati",
    "sg:classifiers": [
      {
        "category": "Building \u0026 Trades",
        "subcategory": "Landscaping Services",
        "type": "Services"
      }
    ],
    "sg:phone": "+1 513 521 0339",
    "sg:postcode": "45239",
    "sg:province": "OH",
    "wof:name": "Top Notch Tree Service",
    "wof:placetype": "venue"
  },
  "geometry": {"coordinates":[-84.57868,39.207369],"type":"Point"}
}
