{
  "type": "Feature",
  "properties": {
    "addr:full":"21833 State Rte 93 S Logan OH 43138",
    "addr:housenumber":"21833",
    "addr:postcode":"43138",
    "addr:street":"State Rte 93 S",
    "iso:country":"US",
    "sg:address":"21833 State Rte 93 S",
    "sg:city":"Logan",
    "sg:classifiers":[
        {
            "category":"Building & Trades",
            "subcategory":"Landscaping Services",
            "type":"Services"
        }
    ],
    "sg:phone":"+1 740 385 1003",
    "sg:postcode":"43138",
    "sg:province":"OH",
    "sg:tags":[
        "landscape",
        "contractor"
    ],
    "wof:name":"Greenscene Landscaping",
    "wof:placetype":"venue"
},
  "geometry": {"coordinates":[-82.447515,39.422683],"type":"Point"}
}