{
  "type": "Feature",
  "properties": {
    "iso:country":"US",
    "sg:address":"2060 S Alex Rd",
    "sg:city":"West Carrollton",
    "sg:classifiers":[
        {
            "category":"Autos & Motor Vehicles",
            "subcategory":"Auto Supplies",
            "type":"Retail Goods"
        }
    ],
    "sg:phone":"+1 937 859 1131",
    "sg:postcode":"45449",
    "sg:province":"OH",
    "sg:tags":[
        "automobile",
        "accessory"
    ],
    "wof:name":"Automotive Reconditioning Inc",
    "wof:placetype":"venue"
},
  "geometry": {"coordinates":[-84.243129,39.645725],"type":"Point"}
}