{
  "type": "Feature",
  "properties": {
    "addr:full": "13947 Cedar Rd Cleveland OH 44118",
    "addr:housenumber": "13947",
    "addr:postcode": "44118",
    "addr:street": "Cedar Rd",
    "iso:country": "US",
    "sg:address": "13947 Cedar Rd",
    "sg:city": "Cleveland",
    "sg:classifiers": [
      {
        "category": "Education",
        "subcategory": "Dance Studio",
        "type": "Public Place"
      }
    ],
    "sg:phone": "+1 216 932 0222",
    "sg:postcode": "44118",
    "sg:province": "OH",
    "sg:tags": [
      "instruction",
      "dancing"
    ],
    "wof:name": "Cleveland City Dance",
    "wof:placetype": "venue"
  },
  "geometry": {"coordinates":[-81.537622,41.501427],"type":"Point"}
}
