{
  "type": "Feature",
  "properties": {
    "iso:country":"US",
    "sg:address":"105 E Mulberry St",
    "sg:city":"Lancaster",
    "sg:classifiers":[
        {
            "category":"Organizations",
            "subcategory":"Religious Organization",
            "type":"Services"
        }
    ],
    "sg:phone":"+1 740 653 1950",
    "sg:postcode":"43130",
    "sg:province":"OH",
    "wof:name":"Saint Peters Lutheran Church",
    "wof:placetype":"venue"
},
  "geometry": {"coordinates":[-82.60172,39.716267],"type":"Point"}
}