{
  "type": "Feature",
  "properties": {
    "addr:full":"4480 Darrow Rd Stow OH 44224",
    "addr:housenumber":"4480",
    "addr:postcode":"44224",
    "addr:street":"Darrow Rd",
    "iso:country":"US",
    "sg:address":"4480 Darrow Rd",
    "sg:city":"Stow",
    "sg:classifiers":[
        {
            "category":"Insurance",
            "subcategory":"Hazard Insurance",
            "type":"Services"
        }
    ],
    "sg:phone":"+1 330 686 1231",
    "sg:postcode":"44224",
    "sg:province":"OH",
    "wof:name":"Liberty Mutual",
    "wof:placetype":"venue"
},
  "geometry": {"coordinates":[-81.4405,41.188997],"type":"Point"}
}