{
  "type": "Feature",
  "properties": {
    "iso:country":"US",
    "sg:address":"37 Ridge Rd",
    "sg:city":"Newton Falls",
    "sg:classifiers":[
        {
            "category":"Banks & Credit Unions",
            "subcategory":"Bank",
            "type":"Services"
        }
    ],
    "sg:phone":"+1 330 872 7214",
    "sg:postcode":"44444",
    "sg:province":"OH",
    "wof:name":"US Bank",
    "wof:placetype":"venue"
},
  "geometry": {"coordinates":[-80.980051,41.189318],"type":"Point"}
}