{
  "type": "Feature",
  "properties": {
    "iso:country":"US",
    "sg:address":"1924 Dana Ave",
    "sg:city":"Cincinnati",
    "sg:classifiers":[
        {
            "category":"Organizations",
            "subcategory":"Non-profit Organization",
            "type":"Services"
        }
    ],
    "sg:phone":"+1 513 221 0033",
    "sg:postcode":"45207",
    "sg:province":"OH",
    "sg:website":"www.4c-cinci.org",
    "wof:name":"4 C",
    "wof:placetype":"venue"
},
  "geometry": {"coordinates":[-84.463911,39.145994],"type":"Point"}
}