{
  "type": "Feature",
  "properties": {
    "addr:full":"13800 Terrace Rd Cleveland OH 44112",
    "addr:housenumber":"13800",
    "addr:postcode":"44112",
    "addr:street":"Terrace Rd",
    "iso:country":"US",
    "sg:address":"13800 Terrace Rd",
    "sg:city":"Cleveland",
    "sg:classifiers":[
        {
            "category":"Real Estate",
            "subcategory":"Real Estate Operator",
            "type":"Services"
        }
    ],
    "sg:phone":"+1 216 851 5118",
    "sg:postcode":"44112",
    "sg:province":"OH",
    "sg:tags":[
        "building",
        "apartment"
    ],
    "wof:name":"Park Lane Apartments",
    "wof:placetype":"venue"
},
  "geometry": {"coordinates":[-81.582825,41.524533],"type":"Point"}
}