{
  "type": "Feature",
  "properties": {
    "addr:full":"501 E Robb Ave Lima OH 45801",
    "addr:housenumber":"501",
    "addr:postcode":"45801",
    "addr:street":"E Robb Ave",
    "iso:country":"US",
    "sg:address":"501 E Robb Ave",
    "sg:city":"Lima",
    "sg:classifiers":[
        {
            "category":"Autos & Motor Vehicles",
            "subcategory":"Automobile Sales",
            "type":"Retail Goods"
        }
    ],
    "sg:phone":"+1 419 224 4172",
    "sg:postcode":"45801",
    "sg:province":"OH",
    "sg:tags":[
        "used"
    ],
    "wof:name":"Robb Overpass Auto Sales",
    "wof:placetype":"venue"
},
  "geometry": {"coordinates":[-84.095984,40.759312],"type":"Point"}
}