{
  "type": "Feature",
  "properties": {
    "addr:full": "2444 S Arlington Rd Akron OH 44319",
    "addr:housenumber": "2444",
    "addr:postcode": "44319",
    "addr:street": "S Arlington Rd",
    "iso:country": "US",
    "sg:address": "2444 S Arlington Rd",
    "sg:city": "Akron",
    "sg:classifiers": [
      {
        "category": "Autos \u0026 Motor Vehicles",
        "subcategory": "Automobile Sales",
        "type": "Retail Goods"
      }
    ],
    "sg:phone": "+1 330 644 3538",
    "sg:postcode": "44319",
    "sg:province": "OH",
    "sg:tags": [
      "body",
      "repair",
      "used",
      "automotive"
    ],
    "wof:name": "Kuality KARS Inc",
    "wof:placetype": "venue"
  },
  "geometry": {"coordinates":[-81.492115,41.004606],"type":"Point"}
}
