{
  "type": "Feature",
  "properties": {
    "iso:country":"US",
    "sg:address":"227 W Wyandot Ave",
    "sg:city":"Upper Sandusky",
    "sg:classifiers":[
        {
            "category":"Autos & Motor Vehicles",
            "subcategory":"Automobile Sales",
            "type":"Retail Goods"
        }
    ],
    "sg:phone":"+1 419 209 0900",
    "sg:postcode":"43351",
    "sg:province":"OH",
    "sg:tags":[
        "car",
        "used",
        "dealer"
    ],
    "wof:name":"Eippert Motor Sales Inc",
    "wof:placetype":"venue"
},
  "geometry": {"coordinates":[-83.28419700000001,40.827435],"type":"Point"}
}