{
  "type": "Feature",
  "properties": {
    "addr:full":"1976 Warrensville Center Rd Cleveland OH 44121",
    "addr:housenumber":"1976",
    "addr:postcode":"44121",
    "addr:street":"Warrensville Center Rd",
    "iso:country":"US",
    "sg:address":"1976 Warrensville Center Rd",
    "sg:city":"Cleveland",
    "sg:classifiers":[
        {
            "category":"Food & Beverages",
            "subcategory":"Groceries & Convenience Stores",
            "type":"Retail Goods"
        }
    ],
    "sg:phone":"+1 216 382 7330",
    "sg:postcode":"44121",
    "sg:province":"OH",
    "wof:name":"Dairy Mart Convenience Store",
    "wof:placetype":"venue"
},
  "geometry": {"coordinates":[-81.536424,41.505376],"type":"Point"}
}