{
  "type": "Feature",
  "properties": {
    "addr:full": "780 Crestway Dr Columbus OH 43235",
    "addr:housenumber": "780",
    "addr:postcode": "43235",
    "addr:street": "Crestway Dr",
    "iso:country": "US",
    "sg:address": "780 Crestway Dr",
    "sg:city": "Columbus",
    "sg:classifiers": [
      {
        "category": "Real Estate",
        "subcategory": "Real Estate Agent",
        "type": "Services"
      }
    ],
    "sg:phone": "+1 614 890 5000",
    "sg:postcode": "43235",
    "sg:province": "OH",
    "wof:name": "J A Billiter",
    "wof:placetype": "venue"
  },
  "geometry": {"coordinates":[-83.040339,40.073324],"type":"Point"}
}
