{
  "type": "Feature",
  "properties": {
    "addr:full":"5379 W Erie Ave Lorain OH 44053",
    "addr:housenumber":"5379",
    "addr:postcode":"44053",
    "addr:street":"W Erie Ave",
    "iso:country":"US",
    "sg:address":"5379 W Erie Ave",
    "sg:city":"Lorain",
    "sg:classifiers":[
        {
            "category":"Restaurant",
            "type":"Food & Drink"
        }
    ],
    "sg:menulink":"http://www.allmenus.com/oh/lorain/134657-subway/menu/",
    "sg:phone":"+1 440 960 1555",
    "sg:postcode":"44053",
    "sg:province":"OH",
    "sg:tags":[
        "american",
        "sandwich"
    ],
    "wof:name":"Subway",
    "wof:placetype":"venue"
},
  "geometry": {"coordinates":[-82.231897,41.44268],"type":"Point"}
}