{
  "type": "Feature",
  "properties": {
    "iso:country":"US",
    "sg:address":"425 W 5th St",
    "sg:city":"East Liverpool",
    "sg:classifiers":[
        {
            "category":"Health Services",
            "subcategory":"Doctor",
            "type":"Services"
        }
    ],
    "sg:phone":"+1 330 385 2488",
    "sg:postcode":"43920",
    "sg:province":"OH",
    "sg:tags":[
        "physician",
        "surgeon"
    ],
    "wof:name":"Reddy Cardiovascular Assoc",
    "wof:placetype":"venue"
},
  "geometry": {"coordinates":[-80.58646,40.621525],"type":"Point"}
}