{
  "type": "Feature",
  "properties": {
    "iso:country":"US",
    "sg:address":"2400 Elida Rd",
    "sg:city":"Lima",
    "sg:classifiers":[
        {
            "category":"Shopping",
            "subcategory":"Clothing, Apparel, & Fashions",
            "type":"Retail Goods"
        }
    ],
    "sg:phone":"+1 419 331 1131",
    "sg:postcode":"45805",
    "sg:province":"OH",
    "sg:tags":[
        "family"
    ],
    "sg:website":"www.oldnavy.com",
    "wof:name":"Old Navy",
    "wof:placetype":"venue"
},
  "geometry": {"coordinates":[-84.148983,40.762762],"type":"Point"}
}