{
  "type": "Feature",
  "properties": {
    "iso:country":"US",
    "sg:address":"2321 2nd St",
    "sg:city":"Cuyahoga Falls",
    "sg:classifiers":[
        {
            "category":"Shopping",
            "subcategory":"Computers & Home Electronics",
            "type":"Retail Goods"
        }
    ],
    "sg:phone":"+1 330 929 2197",
    "sg:postcode":"44221",
    "sg:province":"OH",
    "sg:tags":[
        "software"
    ],
    "wof:name":"Keane Healthcare Solutions",
    "wof:placetype":"venue"
},
  "geometry": {"coordinates":[-81.483782,41.138215],"type":"Point"}
}