{
  "type": "Feature",
  "properties": {
    "addr:full": "2321 2nd St Cuyahoga Falls OH 44221",
    "addr:housenumber": "2321",
    "addr:postcode": "44221",
    "addr:street": "2Nd St",
    "iso:country": "US",
    "sg:address": "2321 2nd St",
    "sg:city": "Cuyahoga Falls",
    "sg:classifiers": [
      {
        "category": "Shopping",
        "subcategory": "Computers \u0026 Home Electronics",
        "type": "Retail Goods"
      }
    ],
    "sg:phone": "+1 330 929 2197",
    "sg:postcode": "44221",
    "sg:province": "OH",
    "sg:tags": [
      "software"
    ],
    "wof:name": "Keane Healthcare Solutions",
    "wof:placetype": "venue"
  },
  "geometry": {"coordinates":[-81.483782,41.138215],"type":"Point"}
}
