{
  "type": "Feature",
  "properties": {
    "iso:country":"US",
    "sg:address":"408 N Market St",
    "sg:city":"Galion",
    "sg:classifiers":[
        {
            "category":"Freight",
            "type":"Transportation"
        }
    ],
    "sg:phone":"+1 419 468 5333",
    "sg:postcode":"44833",
    "sg:province":"OH",
    "sg:tags":[
        "warehouse"
    ],
    "wof:name":"Galion Canvas Products Co",
    "wof:placetype":"venue"
},
  "geometry": {"coordinates":[-82.789127,40.739326],"type":"Point"}
}