{
  "type": "Feature",
  "properties": {
    "iso:country":"US",
    "sg:address":"4125 Payne Ave",
    "sg:city":"Cleveland",
    "sg:classifiers":[
        {
            "category":"Building & Trades",
            "subcategory":"Construction",
            "type":"Services"
        }
    ],
    "sg:phone":"+1 216 431 2334",
    "sg:postcode":"44103",
    "sg:province":"OH",
    "sg:tags":[
        "commercial",
        "flooring",
        "contractor"
    ],
    "wof:name":"Company Inc",
    "wof:placetype":"venue"
},
  "geometry": {"coordinates":[-81.657005,41.511274],"type":"Point"}
}