{
  "type": "Feature",
  "properties": {
    "iso:country":"US",
    "sg:address":"263 S Detroit St",
    "sg:city":"Xenia",
    "sg:classifiers":[
        {
            "category":"Autos & Motor Vehicles",
            "subcategory":"Auto Supplies",
            "type":"Retail Goods"
        }
    ],
    "sg:phone":"+1 937 374 0058",
    "sg:postcode":"45385",
    "sg:province":"OH",
    "sg:tags":[
        "parts"
    ],
    "sg:website":"www.autozone.com",
    "wof:name":"Autozone",
    "wof:placetype":"venue"
},
  "geometry": {"coordinates":[-83.928832,39.682118],"type":"Point"}
}