{
  "type": "Feature",
  "properties": {
    "addr:full": "144 Waterloo St Marion OH 43302",
    "addr:housenumber": "144",
    "addr:postcode": "43302",
    "addr:street": "Waterloo St",
    "iso:country": "US",
    "sg:address": "144 Waterloo St",
    "sg:city": "Marion",
    "sg:classifiers": [
      {
        "category": "Arts \u0026 Performance",
        "subcategory": "Theater",
        "type": "Entertainment"
      }
    ],
    "sg:phone": "+1 740 382 5300",
    "sg:postcode": "43302",
    "sg:province": "OH",
    "sg:tags": [
      "live",
      "music"
    ],
    "wof:name": "Good Vibrations Karaoke \u0026 DJ",
    "wof:placetype": "venue"
  },
  "geometry": {"coordinates":[-83.147515,40.588121],"type":"Point"}
}
