{
  "type": "Feature",
  "properties": {
    "iso:country":"US",
    "sg:address":"245 N Seltzer St",
    "sg:city":"Crestline",
    "sg:classifiers":[
        {
            "category":"Banks & Credit Unions",
            "subcategory":"Bank",
            "type":"Services"
        }
    ],
    "sg:phone":"+1 419 683 1010",
    "sg:postcode":"44827",
    "sg:province":"OH",
    "wof:name":"United Bank",
    "wof:placetype":"venue"
},
  "geometry": {"coordinates":[-82.736549,40.785644],"type":"Point"}
}