{
  "type": "Feature",
  "properties": {
    "addr:full":"107 N Prospect St Ravenna OH 44266",
    "addr:housenumber":"107",
    "addr:postcode":"44266",
    "addr:street":"N Prospect St",
    "iso:country":"US",
    "sg:address":"107 N Prospect St",
    "sg:city":"Ravenna",
    "sg:classifiers":[
        {
            "category":"Wholesale",
            "subcategory":"Scrap",
            "type":"Manufacturing & Wholesale Goods"
        }
    ],
    "sg:phone":"+1 330 298 1233",
    "sg:postcode":"44266",
    "sg:province":"OH",
    "sg:tags":[
        "material"
    ],
    "wof:name":"Scrap N Stamp Haven",
    "wof:placetype":"venue"
},
  "geometry": {"coordinates":[-81.241564,41.157886],"type":"Point"}
}