{
  "type": "Feature",
  "properties": {
    "addr:full":"2000 N Ridge Rd Painesville OH 44077",
    "addr:housenumber":"2000",
    "addr:postcode":"44077",
    "addr:street":"N Ridge Rd",
    "iso:country":"US",
    "sg:address":"2000 N Ridge Rd",
    "sg:city":"Painesville",
    "sg:classifiers":[
        {
            "category":"Restaurant",
            "type":"Food & Drink"
        }
    ],
    "sg:phone":"+1 440 354 2547",
    "sg:postcode":"44077",
    "sg:province":"OH",
    "wof:name":"Carlucci's Pizza",
    "wof:placetype":"venue"
},
  "geometry": {"coordinates":[-81.203817,41.751815],"type":"Point"}
}