{
  "type": "Feature",
  "properties": {
    "iso:country":"US",
    "sg:address":"9579 Venus Dr",
    "sg:city":"Chardon",
    "sg:classifiers":[
        {
            "category":"Building & Trades",
            "subcategory":"Landscaping Services",
            "type":"Services"
        }
    ],
    "sg:phone":"+1 440 285 1752",
    "sg:postcode":"44024",
    "sg:province":"OH",
    "sg:tags":[
        "landscape",
        "contractor"
    ],
    "wof:name":"Prime Estate Landscape",
    "wof:placetype":"venue"
},
  "geometry": {"coordinates":[-81.131816,41.610431],"type":"Point"}
}