{
  "type": "Feature",
  "properties": {
    "addr:full": "9579 Venus Dr Chardon OH 44024",
    "addr:housenumber": "9579",
    "addr:postcode": "44024",
    "addr:street": "Venus Dr",
    "iso:country": "US",
    "sg:address": "9579 Venus Dr",
    "sg:city": "Chardon",
    "sg:classifiers": [
      {
        "category": "Building \u0026 Trades",
        "subcategory": "Landscaping Services",
        "type": "Services"
      }
    ],
    "sg:phone": "+1 440 285 1752",
    "sg:postcode": "44024",
    "sg:province": "OH",
    "sg:tags": [
      "landscape",
      "contractor"
    ],
    "wof:name": "Prime Estate Landscape",
    "wof:placetype": "venue"
  },
  "geometry": {"coordinates":[-81.131816,41.610431],"type":"Point"}
}
