{
  "type": "Feature",
  "properties": {
    "addr:full": "320 Linwood St Dayton OH 45405",
    "addr:housenumber": "320",
    "addr:postcode": "45405",
    "addr:street": "Linwood St",
    "iso:country": "US",
    "sg:address": "320 Linwood St",
    "sg:city": "Dayton",
    "sg:classifiers": [
      {
        "category": "Health Services",
        "subcategory": "Clinic",
        "type": "Services"
      }
    ],
    "sg:phone": "+1 937 225 4068",
    "sg:postcode": "45405",
    "sg:province": "OH",
    "sg:tags": [
      "home",
      "agency",
      "employment",
      "care"
    ],
    "wof:name": "Visiting Home Care",
    "wof:placetype": "venue"
  },
  "geometry": {"coordinates":[-84.192055,39.769341],"type":"Point"}
}
