{
  "type": "Feature",
  "properties": {
    "iso:country":"US",
    "sg:address":"9941 Walford Ave",
    "sg:city":"Cleveland",
    "sg:classifiers":[
        {
            "category":"Manufacturing",
            "subcategory":"Metals",
            "type":"Manufacturing & Wholesale Goods"
        }
    ],
    "sg:phone":"+1 216 281 8415",
    "sg:postcode":"44102",
    "sg:province":"OH",
    "sg:tags":[
        "tool",
        "mfg"
    ],
    "wof:name":"Oxico Corporation",
    "wof:placetype":"venue"
},
  "geometry": {"coordinates":[-81.75308099999999,41.455735],"type":"Point"}
}