{
  "type": "Feature",
  "properties": {
    "iso:country":"US",
    "sg:address":"4190 Co Rd 2",
    "sg:city":"Swanton",
    "sg:classifiers":[
        {
            "category":"Wholesale",
            "subcategory":"Hardware",
            "type":"Manufacturing & Wholesale Goods"
        }
    ],
    "sg:phone":"+1 419 825 1616",
    "sg:postcode":"43558",
    "sg:province":"OH",
    "sg:tags":[
        "furnace"
    ],
    "wof:name":"Marlyn's Plumbing/Cooling",
    "wof:placetype":"venue"
},
  "geometry": {"coordinates":[-83.901954,41.53633],"type":"Point"}
}