{
  "type": "Feature",
  "properties": {
    "addr:full": "734 Kerr St Columbus OH 43215",
    "addr:housenumber": "734",
    "addr:postcode": "43215",
    "addr:street": "Kerr St",
    "iso:country": "US",
    "sg:address": "734 Kerr St",
    "sg:city": "Columbus",
    "sg:classifiers": [
      {
        "category": "Building \u0026 Trades",
        "subcategory": "Construction",
        "type": "Services"
      }
    ],
    "sg:phone": "+1 614 404 8901",
    "sg:postcode": "43215",
    "sg:province": "OH",
    "sg:tags": [
      "house"
    ],
    "wof:name": "Blue Sky Homes LLC",
    "wof:placetype": "venue"
  },
  "geometry": {"coordinates":[-83.001457,39.977281],"type":"Point"}
}
