{
  "type": "Feature",
  "properties": {
    "addr:full":"5760 Bonaly Ct Dublin OH 43016",
    "addr:housenumber":"5760",
    "addr:postcode":"43016",
    "addr:street":"Bonaly Ct",
    "iso:country":"US",
    "sg:address":"5760 Bonaly Ct",
    "sg:city":"Dublin",
    "sg:classifiers":[
        {
            "category":"Utilities",
            "subcategory":"Telephone",
            "type":"Services"
        }
    ],
    "sg:phone":"+1 614 793 1138",
    "sg:postcode":"43016",
    "sg:province":"OH",
    "sg:tags":[
        "communications"
    ],
    "wof:name":"Hostutopiacom",
    "wof:placetype":"venue"
},
  "geometry": {"coordinates":[-83.173423,40.08613],"type":"Point"}
}