{
  "type": "Feature",
  "properties": {
    "addr:full": "250 Mahoning Ave Cleveland OH 44113",
    "addr:housenumber": "250",
    "addr:postcode": "44113",
    "addr:street": "Mahoning Ave",
    "iso:country": "US",
    "sg:address": "250 Mahoning Ave",
    "sg:city": "Cleveland",
    "sg:classifiers": [
      {
        "category": "Manufacturing",
        "subcategory": "Petroleum Products",
        "type": "Manufacturing \u0026 Wholesale Goods"
      }
    ],
    "sg:phone": "+1 216 781 6155",
    "sg:postcode": "44113",
    "sg:province": "OH",
    "sg:tags": [
      "lubricating",
      "oil",
      "grease"
    ],
    "wof:name": "Northeast Lubricants",
    "wof:placetype": "venue"
  },
  "geometry": {"coordinates":[-81.682968,41.485836],"type":"Point"}
}
