{
  "type": "Feature",
  "properties": {
    "iso:country":"US",
    "sg:address":"16600 W Sprague Rd",
    "sg:city":"Cleveland",
    "sg:classifiers":[
        {
            "category":"Wholesale",
            "subcategory":"Machinery & Supplies",
            "type":"Manufacturing & Wholesale Goods"
        }
    ],
    "sg:phone":"+1 440 243 0133",
    "sg:postcode":"44130",
    "sg:province":"OH",
    "sg:tags":[
        "equipment",
        "aircraft",
        "industrial",
        "parts"
    ],
    "wof:name":"Sphere Industrial Group Sups",
    "wof:placetype":"venue"
},
  "geometry": {"coordinates":[-81.81778199999999,41.350794],"type":"Point"}
}