{
  "type": "Feature",
  "properties": {
    "addr:full": "1500 N Mantua St Kent OH 44240",
    "addr:housenumber": "1500",
    "addr:postcode": "44240",
    "addr:street": "N Mantua St",
    "iso:country": "US",
    "sg:address": "1500 N Mantua St",
    "sg:city": "Kent",
    "sg:classifiers": [
      {
        "category": "Building \u0026 Trades",
        "subcategory": "Landscaping Services",
        "type": "Services"
      }
    ],
    "sg:phone": "+1 330 673 9511",
    "sg:postcode": "44240",
    "sg:province": "OH",
    "sg:tags": [
      "horticultural",
      "consultant"
    ],
    "sg:website": "www.daveytreeco.com",
    "wof:name": "Davey Tree Expert Co",
    "wof:placetype": "venue"
  },
  "geometry": {"coordinates":[-81.353107,41.170988],"type":"Point"}
}
