{
  "type": "Feature",
  "properties": {
    "addr:full": "415 Milan Ave Norwalk OH 44857",
    "addr:housenumber": "415",
    "addr:postcode": "44857",
    "addr:street": "Milan Ave",
    "iso:country": "US",
    "sg:address": "415 Milan Ave",
    "sg:city": "Norwalk",
    "sg:classifiers": [
      {
        "category": "Travel",
        "subcategory": "Hotels \u0026 Motels",
        "type": "Entertainment"
      }
    ],
    "sg:phone": "+1 419 663 1922",
    "sg:postcode": "44857",
    "sg:province": "OH",
    "sg:tags": [
      "operation"
    ],
    "sg:website": "www.sanduskyhotels.com",
    "wof:name": "Ameri Host Inn",
    "wof:placetype": "venue"
  },
  "geometry": {"coordinates":[-82.611358,41.262589],"type":"Point"}
}
