{
  "type": "Feature",
  "properties": {
    "iso:country":"US",
    "sg:address":"415 Milan Ave",
    "sg:city":"Norwalk",
    "sg:classifiers":[
        {
            "category":"Travel",
            "subcategory":"Hotels & Motels",
            "type":"Entertainment"
        }
    ],
    "sg:phone":"+1 419 663 1922",
    "sg:postcode":"44857",
    "sg:province":"OH",
    "sg:tags":[
        "operation"
    ],
    "sg:website":"www.sanduskyhotels.com",
    "wof:name":"Ameri Host Inn",
    "wof:placetype":"venue"
},
  "geometry": {"coordinates":[-82.611358,41.262589],"type":"Point"}
}