{
  "type": "Feature",
  "properties": {
    "addr:full": "119 S Kenton St Urbana OH 43078",
    "addr:housenumber": "119",
    "addr:postcode": "43078",
    "addr:street": "S Kenton St",
    "iso:country": "US",
    "sg:address": "119 S Kenton St",
    "sg:city": "Urbana",
    "sg:classifiers": [
      {
        "category": "Retail",
        "subcategory": "Auto Repair",
        "type": "Services"
      }
    ],
    "sg:phone": "+1 937 653 5862",
    "sg:postcode": "43078",
    "sg:province": "OH",
    "sg:tags": [
      "body",
      "automobile",
      "painting"
    ],
    "wof:name": "Jim's Body \u0026 Collision Repair",
    "wof:placetype": "venue"
  },
  "geometry": {"coordinates":[-83.749326,40.107529],"type":"Point"}
}
