{
  "type": "Feature",
  "properties": {
    "addr:full": "178 E Market St Sandusky OH 44870",
    "addr:housenumber": "178",
    "addr:postcode": "44870",
    "addr:street": "E Market St",
    "iso:country": "US",
    "sg:address": "178 E Market St",
    "sg:city": "Sandusky",
    "sg:classifiers": [
      {
        "category": "Wholesale",
        "subcategory": "Stationery",
        "type": "Manufacturing \u0026 Wholesale Goods"
      }
    ],
    "sg:phone": "+1 419 624 0675",
    "sg:postcode": "44870",
    "sg:province": "OH",
    "sg:tags": [
      "supply"
    ],
    "wof:name": "Art In Heart",
    "wof:placetype": "venue"
  },
  "geometry": {"coordinates":[-82.711283,41.45622],"type":"Point"}
}
