{
  "type": "Feature",
  "properties": {
    "addr:full": "2420 Wedgewood Dr Akron OH 44312",
    "addr:housenumber": "2420",
    "addr:postcode": "44312",
    "addr:street": "Wedgewood Dr",
    "iso:country": "US",
    "sg:address": "2420 Wedgewood Dr",
    "sg:city": "Akron",
    "sg:classifiers": [
      {
        "category": "Banks \u0026 Credit Unions",
        "subcategory": "Bank",
        "type": "Services"
      }
    ],
    "sg:phone": "+1 330 784 0439",
    "sg:postcode": "44312",
    "sg:province": "OH",
    "sg:tags": [
      "national"
    ],
    "wof:name": "Star Bank NA Ellet",
    "wof:placetype": "venue"
  },
  "geometry": {"coordinates":[-81.441241,41.049716],"type":"Point"}
}
