{
  "type": "Feature",
  "properties": {
    "addr:full":"30610 E Broadway St Walbridge OH 43465",
    "addr:housenumber":"30610",
    "addr:postcode":"43465",
    "addr:street":"E Broadway St",
    "iso:country":"US",
    "sg:address":"30610 E Broadway St",
    "sg:city":"Walbridge",
    "sg:classifiers":[
        {
            "category":"Manufacturing",
            "subcategory":"Metals",
            "type":"Manufacturing & Wholesale Goods"
        }
    ],
    "sg:phone":"+1 419 666 6130",
    "sg:postcode":"43465",
    "sg:province":"OH",
    "sg:tags":[
        "steel",
        "cold",
        "processing",
        "shape",
        "mfg"
    ],
    "wof:name":"Walbridge Coatings Inc",
    "wof:placetype":"venue"
},
  "geometry": {"coordinates":[-83.512676,41.599113],"type":"Point"}
}