{
  "type": "Feature",
  "properties": {
    "addr:full": "10 Tiber Way Marietta OH 45750",
    "addr:housenumber": "10",
    "addr:postcode": "45750",
    "addr:street": "Tiber Way",
    "iso:country": "US",
    "sg:address": "10 Tiber Way",
    "sg:city": "Marietta",
    "sg:classifiers": [
      {
        "category": "Food \u0026 Beverages",
        "subcategory": "Specialty",
        "type": "Retail Goods"
      },
      {
        "category": "Restaurant",
        "type": "Food \u0026 Drink"
      }
    ],
    "sg:phone": "+1 740 374 2429",
    "sg:postcode": "45750",
    "sg:province": "OH",
    "wof:name": "Day Brighter Natural Foods",
    "wof:placetype": "venue"
  },
  "geometry": {"coordinates":[-81.453327,39.413384],"type":"Point"}
}
