{
  "type": "Feature",
  "properties": {
    "iso:country":"US",
    "sg:address":"5067 US Hwy 6",
    "sg:city":"Helena",
    "sg:classifiers":[
        {
            "category":"Farming",
            "subcategory":"Farm",
            "type":"Manufacturing & Wholesale Goods"
        }
    ],
    "sg:phone":"+1 419 638 2605",
    "sg:postcode":"43435",
    "sg:province":"OH",
    "sg:tags":[
        "crop",
        "general"
    ],
    "wof:name":"Sneiders TV Sales & Service",
    "wof:placetype":"venue"
},
  "geometry": {"coordinates":[-83.319485,41.341011],"type":"Point"}
}