{
  "type": "Feature",
  "properties": {
    "addr:full": "5067 US Hwy 6 Helena OH 43435",
    "addr:housenumber": "5067",
    "addr:postcode": "43435",
    "addr:street": "Us Hwy 6",
    "iso:country": "US",
    "sg:address": "5067 US Hwy 6",
    "sg:city": "Helena",
    "sg:classifiers": [
      {
        "category": "Farming",
        "subcategory": "Farm",
        "type": "Manufacturing \u0026 Wholesale Goods"
      }
    ],
    "sg:phone": "+1 419 638 2605",
    "sg:postcode": "43435",
    "sg:province": "OH",
    "sg:tags": [
      "crop",
      "general"
    ],
    "wof:name": "Sneiders TV Sales \u0026 Service",
    "wof:placetype": "venue"
  },
  "geometry": {"coordinates":[-83.319485,41.341011],"type":"Point"}
}
