{
  "type": "Feature",
  "properties": {
    "addr:full": "20800 Center Ridge Rd Rocky River OH 44116",
    "addr:housenumber": "20800",
    "addr:postcode": "44116",
    "addr:street": "Center Ridge Rd",
    "iso:country": "US",
    "sg:address": "20800 Center Ridge Rd",
    "sg:city": "Rocky River",
    "sg:classifiers": [
      {
        "category": "Professional",
        "subcategory": "Business Services",
        "type": "Services"
      }
    ],
    "sg:phone": "+1 440 356 5511",
    "sg:postcode": "44116",
    "sg:province": "OH",
    "sg:tags": [
      "answering"
    ],
    "wof:name": "Staphyl",
    "wof:placetype": "venue"
  },
  "geometry": {"coordinates":[-81.850559,41.462604],"type":"Point"}
}
