{
  "type": "Feature",
  "properties": {
    "iso:country":"US",
    "sg:address":"4930 Mahoning Ave NW",
    "sg:city":"Warren",
    "sg:classifiers":[
        {
            "category":"Building & Trades",
            "subcategory":"Plumbing",
            "type":"Services"
        }
    ],
    "sg:phone":"+1 330 847 8480",
    "sg:postcode":"44483",
    "sg:province":"OH",
    "sg:tags":[
        "conditioning",
        "air",
        "system",
        "contractor"
    ],
    "wof:name":"Best Furnace Co",
    "wof:placetype":"venue"
},
  "geometry": {"coordinates":[-80.847652,41.290804],"type":"Point"}
}