{
  "type": "Feature",
  "properties": {
    "addr:full": "7239 Pinehill Rd Painesville OH 44077",
    "addr:housenumber": "7239",
    "addr:postcode": "44077",
    "addr:street": "Pinehill Rd",
    "iso:country": "US",
    "sg:address": "7239 Pinehill Rd",
    "sg:city": "Painesville",
    "sg:classifiers": [
      {
        "category": "Professional",
        "subcategory": "Computer Services",
        "type": "Services"
      }
    ],
    "sg:phone": "+1 614 789 9106",
    "sg:postcode": "44077",
    "sg:province": "OH",
    "sg:tags": [
      "consultant",
      "designer",
      "datum",
      "system"
    ],
    "wof:name": "ENC Group Inc",
    "wof:placetype": "venue"
  },
  "geometry": {"coordinates":[-81.255996,41.676347],"type":"Point"}
}
