{
  "type": "Feature",
  "properties": {
    "addr:full": "8494 Lincoln Way Orrville OH 44667",
    "addr:housenumber": "8494",
    "addr:postcode": "44667",
    "addr:street": "Lincoln Way",
    "iso:country": "US",
    "sg:address": "8494 Lincoln Way",
    "sg:city": "Orrville",
    "sg:classifiers": [
      {
        "category": "Retail",
        "subcategory": "Auto Repair",
        "type": "Services"
      }
    ],
    "sg:phone": "+1 330 683 7223",
    "sg:postcode": "44667",
    "sg:province": "OH",
    "sg:tags": [
      "machine",
      "automobile",
      "shop"
    ],
    "wof:name": "Mc Clelland Engine \u0026 Machine",
    "wof:placetype": "venue"
  },
  "geometry": {"coordinates":[-81.821245,40.79627],"type":"Point"}
}
