{
  "type": "Feature",
  "properties": {
    "addr:full": "24840 Deal Rd Gambier OH 43022",
    "addr:postcode": "24840;43022",
    "addr:street": "Deal Rd",
    "iso:country": "US",
    "sg:address": "24840 Deal Rd",
    "sg:city": "Gambier",
    "sg:classifiers": [
      {
        "category": "Mining \u0026 Drilling",
        "type": "Manufacturing \u0026 Wholesale Goods"
      }
    ],
    "sg:phone": "+1 740 668 6510",
    "sg:postcode": "43022",
    "sg:province": "OH",
    "sg:tags": [
      "field"
    ],
    "wof:name": "Morans Well Service",
    "wof:placetype": "venue"
  },
  "geometry": {"coordinates":[-82.304469,40.290927],"type":"Point"}
}
