{
  "type": "Feature",
  "properties": {
    "addr:full": "7647 State Rte 139 Lucasville OH 45648",
    "addr:housenumber": "7647",
    "addr:postcode": "45648",
    "addr:street": "State Rte 139",
    "iso:country": "US",
    "sg:address": "7647 State Rte 139",
    "sg:city": "Lucasville",
    "sg:classifiers": [
      {
        "category": "Food \u0026 Beverages",
        "subcategory": "Groceries \u0026 Convenience Stores",
        "type": "Retail Goods"
      }
    ],
    "sg:phone": "+1 740 355 9320",
    "sg:postcode": "45648",
    "sg:province": "OH",
    "wof:name": "Evans Corner Market",
    "wof:placetype": "venue"
  },
  "geometry": {"coordinates":[-82.912093,38.849933],"type":"Point"}
}
