{
  "type": "Feature",
  "properties": {
    "iso:country":"US",
    "sg:address":"33 Hess St",
    "sg:city":"Dayton",
    "sg:classifiers":[
        {
            "category":"Real Estate",
            "subcategory":"Real Estate Operator",
            "type":"Services"
        }
    ],
    "sg:phone":"+1 937 461 3513",
    "sg:postcode":"45402",
    "sg:province":"OH",
    "sg:tags":[
        "building",
        "apartment"
    ],
    "wof:name":"Dodds Properties",
    "wof:placetype":"venue"
},
  "geometry": {"coordinates":[-84.183351,39.755609],"type":"Point"}
}