{
  "type": "Feature",
  "properties": {
    "addr:full":"24700 Center Ridge Rd Cleveland OH 44145",
    "addr:housenumber":"24700",
    "addr:postcode":"44145",
    "addr:street":"Center Ridge Rd",
    "iso:country":"US",
    "sg:address":"24700 Center Ridge Rd",
    "sg:city":"Cleveland",
    "sg:classifiers":[
        {
            "category":"Manufacturing",
            "subcategory":"Chemicals & Compounds",
            "type":"Manufacturing & Wholesale Goods"
        }
    ],
    "sg:phone":"+1 440 871 2232",
    "sg:postcode":"44145",
    "sg:province":"OH",
    "sg:tags":[
        "miller",
        "drug"
    ],
    "sg:website":"www.westlake-labs.com",
    "wof:name":"Westlake Laboratories Inc",
    "wof:placetype":"venue"
},
  "geometry": {"coordinates":[-81.89544600000001,41.457522],"type":"Point"}
}