{
  "type": "Feature",
  "properties": {
    "addr:full": "3050 Hillier Rd Norton OH 44203",
    "addr:postcode": "3050;44203",
    "addr:street": "Hillier Rd",
    "iso:country": "US",
    "sg:address": "3050 Hillier Rd",
    "sg:city": "Norton",
    "sg:classifiers": [
      {
        "category": "Retail",
        "subcategory": "Repair Shop",
        "type": "Services"
      }
    ],
    "sg:phone": "+1 330 334 0499",
    "sg:postcode": "44203",
    "sg:province": "OH",
    "sg:tags": [
      "appliance"
    ],
    "wof:name": "D \u0026 S Appliance Svc",
    "wof:placetype": "venue"
  },
  "geometry": {"coordinates":[-81.674781,41.047841],"type":"Point"}
}
