{
  "type": "Feature",
  "properties": {
    "addr:full": "1814 Washington Blvd Belpre OH 45714",
    "addr:housenumber": "1814",
    "addr:postcode": "45714",
    "addr:street": "Washington Blvd",
    "iso:country": "US",
    "sg:address": "1814 Washington Blvd",
    "sg:city": "Belpre",
    "sg:classifiers": [
      {
        "category": "Sports \u0026 Exercise",
        "subcategory": "Gym",
        "type": "Entertainment"
      }
    ],
    "sg:phone": "+1 740 401 0748",
    "sg:postcode": "45714",
    "sg:province": "OH",
    "sg:tags": [
      "club",
      "health",
      "studio",
      "gymnasium"
    ],
    "wof:name": "Curves",
    "wof:placetype": "venue"
  },
  "geometry": {"coordinates":[-81.599071,39.276409],"type":"Point"}
}
