{
  "type": "Feature",
  "properties": {
    "iso:country":"US",
    "sg:address":"1316 W 61st St",
    "sg:city":"Cleveland",
    "sg:classifiers":[
        {
            "category":"Building & Trades",
            "subcategory":"Construction",
            "type":"Services"
        }
    ],
    "sg:phone":"+1 216 961 0711",
    "sg:postcode":"44102",
    "sg:province":"OH",
    "sg:tags":[
        "hanging",
        "contractor"
    ],
    "wof:name":"Southwest Painting LLP",
    "wof:placetype":"venue"
},
  "geometry": {"coordinates":[-81.728353,41.484986],"type":"Point"}
}