{
  "type": "Feature",
  "properties": {
    "addr:full":"5052 Hamilton Mason Rd Hamilton OH 45011",
    "addr:housenumber":"5052",
    "addr:postcode":"45011",
    "addr:street":"Hamilton Mason Rd",
    "iso:country":"US",
    "sg:address":"5052 Hamilton Mason Rd",
    "sg:city":"Hamilton",
    "sg:classifiers":[
        {
            "category":"Social Services",
            "subcategory":"Child Care",
            "type":"Services"
        }
    ],
    "sg:phone":"+1 513 863 3814",
    "sg:postcode":"45011",
    "sg:province":"OH",
    "wof:name":"Program-Heritage Elemntry Schl",
    "wof:placetype":"venue"
},
  "geometry": {"coordinates":[-84.451447,39.373621],"type":"Point"}
}