{
  "type": "Feature",
  "properties": {
    "addr:full":"25 Tarbell Ave Bedford OH 44146",
    "addr:housenumber":"25",
    "addr:postcode":"44146",
    "addr:street":"Tarbell Ave",
    "iso:country":"US",
    "sg:address":"25 Tarbell Ave",
    "sg:city":"Bedford",
    "sg:classifiers":[
        {
            "category":"Real Estate",
            "subcategory":"Real Estate Operator",
            "type":"Services"
        }
    ],
    "sg:phone":"+1 440 439 4700",
    "sg:postcode":"44146",
    "sg:province":"OH",
    "sg:tags":[
        "owner",
        "building",
        "apartment"
    ],
    "wof:name":"F H P Investment Co",
    "wof:placetype":"venue"
},
  "geometry": {"coordinates":[-81.534674,41.392811],"type":"Point"}
}