{
  "type": "Feature",
  "properties": {
    "iso:country":"US",
    "sg:address":"3303 Hughes Blvd",
    "sg:city":"Toledo",
    "sg:classifiers":[
        {
            "category":"Professional",
            "type":"Services"
        }
    ],
    "sg:phone":"+1 419 531 5693",
    "sg:postcode":"43606",
    "sg:province":"OH",
    "wof:name":"Natural Scents",
    "wof:placetype":"venue"
},
  "geometry": {"coordinates":[-83.626477,41.674422],"type":"Point"}
}