{
  "type": "Feature",
  "properties": {
    "addr:full":"8500 Sleepy Hollow Dr Cincinnati OH 45243",
    "addr:housenumber":"8500",
    "addr:postcode":"45243",
    "addr:street":"Sleepy Hollow Dr",
    "iso:country":"US",
    "sg:address":"8500 Sleepy Hollow Dr",
    "sg:city":"Cincinnati",
    "sg:classifiers":[
        {
            "category":"Banks & Credit Unions",
            "subcategory":"Bank",
            "type":"Services"
        }
    ],
    "sg:phone":"+1 513 794 1360",
    "sg:postcode":"45243",
    "sg:province":"OH",
    "sg:tags":[
        "leasing"
    ],
    "wof:name":"Kite Leasing Company Inc",
    "wof:placetype":"venue"
},
  "geometry": {"coordinates":[-84.33324,39.217923],"type":"Point"}
}