{
  "type": "Feature",
  "properties": {
    "iso:country":"US",
    "sg:address":"2315 Stanley Ave",
    "sg:city":"Dayton",
    "sg:classifiers":[
        {
            "category":"Wholesale",
            "subcategory":"Office Equipment",
            "type":"Manufacturing & Wholesale Goods"
        }
    ],
    "sg:phone":"+1 937 224 0006",
    "sg:postcode":"45404",
    "sg:province":"OH",
    "sg:tags":[
        "blueprint",
        "printing",
        "trade",
        "m",
        "supply"
    ],
    "wof:name":"Xerox Engineering Systems",
    "wof:placetype":"venue"
},
  "geometry": {"coordinates":[-84.173478,39.787815],"type":"Point"}
}