{
  "type": "Feature",
  "properties": {
    "addr:full": "203 N Main St Niles OH 44446",
    "addr:housenumber": "203",
    "addr:postcode": "44446",
    "addr:street": "N Main St",
    "iso:country": "US",
    "sg:address": "203 N Main St",
    "sg:city": "Niles",
    "sg:classifiers": [
      {
        "category": "Autos \u0026 Motor Vehicles",
        "subcategory": "Automobile Sales",
        "type": "Retail Goods"
      }
    ],
    "sg:phone": "+1 330 544 2277",
    "sg:postcode": "44446",
    "sg:province": "OH",
    "sg:tags": [
      "car",
      "dealer"
    ],
    "wof:name": "Sophia's Auto Sales",
    "wof:placetype": "venue"
  },
  "geometry": {"coordinates":[-80.765022,41.1832],"type":"Point"}
}
