{
  "type": "Feature",
  "properties": {
    "addr:full": "7657 Green Meadows Dr Lewis Center OH 43035",
    "addr:housenumber": "7657",
    "addr:postcode": "43035",
    "addr:street": "Green Meadows Dr",
    "iso:country": "US",
    "sg:address": "7657 Green Meadows Dr",
    "sg:city": "Lewis Center",
    "sg:classifiers": [
      {
        "category": "Manufacturing",
        "subcategory": "Furniture",
        "type": "Manufacturing \u0026 Wholesale Goods"
      }
    ],
    "sg:phone": "+1 740 549 4700",
    "sg:postcode": "43035",
    "sg:province": "OH",
    "sg:tags": [
      "equipment",
      "supply"
    ],
    "sg:website": "www.hodco.com",
    "wof:name": "Hodco Food Systems",
    "wof:placetype": "venue"
  },
  "geometry": {"coordinates":[-83.010548,40.17694],"type":"Point"}
}
