{
  "type": "Feature",
  "properties": {
    "addr:full":"5232 Co Rd Hj Delta OH 43515",
    "addr:housenumber":"5232",
    "addr:postcode":"43515",
    "addr:street":"Co Rd",
    "iso:country":"US",
    "sg:address":"5232 Co Rd Hj",
    "sg:city":"Delta",
    "sg:classifiers":[
        {
            "category":"Organizations",
            "subcategory":"Religious Organization",
            "type":"Services"
        }
    ],
    "sg:phone":"+1 419 822 5607",
    "sg:postcode":"43515",
    "sg:province":"OH",
    "sg:tags":[
        "church"
    ],
    "wof:name":"Fulton Union Christian Church",
    "wof:placetype":"venue"
},
  "geometry": {"coordinates":[-83.961941,41.594254],"type":"Point"}
}