{
  "type": "Feature",
  "properties": {
    "iso:country":"US",
    "sg:address":"200 Chestnut Ave NE",
    "sg:city":"Warren",
    "sg:classifiers":[
        {
            "category":"Insurance",
            "subcategory":"Title Insurance",
            "type":"Services"
        }
    ],
    "sg:phone":"+1 330 393 3200",
    "sg:postcode":"44483",
    "sg:province":"OH",
    "sg:website":"http://www.title-company.net",
    "wof:name":"The Title Company Of Warren Agency Inc",
    "wof:placetype":"venue"
},
  "geometry": {"coordinates":[-80.809096,41.237567],"type":"Point"}
}