{
  "type": "Feature",
  "properties": {
    "iso:country":"US",
    "sg:address":"6233 Deerhaven Ln",
    "sg:city":"Loveland",
    "sg:classifiers":[
        {
            "category":"Building & Trades",
            "subcategory":"Construction",
            "type":"Services"
        }
    ],
    "sg:phone":"+1 513 722 3757",
    "sg:postcode":"45140",
    "sg:province":"OH",
    "sg:tags":[
        "restoration",
        "cleaning",
        "patio",
        "deck"
    ],
    "wof:name":"Power Clean Pressure Washing",
    "wof:placetype":"venue"
},
  "geometry": {"coordinates":[-84.226271,39.212681],"type":"Point"}
}