{
  "type": "Feature",
  "properties": {
    "addr:full": "7500 Innovation Way Mason OH 45040",
    "addr:housenumber": "7500",
    "addr:postcode": "45040",
    "addr:street": "Innovation Way",
    "iso:country": "US",
    "sg:address": "7500 Innovation Way",
    "sg:city": "Mason",
    "sg:classifiers": [
      {
        "category": "Banks \u0026 Credit Unions",
        "subcategory": "Bank",
        "type": "Services"
      }
    ],
    "sg:phone": "+1 513 573 6517",
    "sg:postcode": "45040",
    "sg:province": "OH",
    "sg:tags": [
      "federal"
    ],
    "wof:name": "Emery Federal Credit Union",
    "wof:placetype": "venue"
  },
  "geometry": {"coordinates":[-84.290216,39.326679],"type":"Point"}
}
