{
  "type": "Feature",
  "properties": {
    "iso:country":"US",
    "sg:address":"4547 Montgomery Rd",
    "sg:city":"Cincinnati",
    "sg:classifiers":[
        {
            "category":"Shopping",
            "subcategory":"Jewelry",
            "type":"Retail Goods"
        }
    ],
    "sg:phone":"+1 513 631 5346",
    "sg:postcode":"45212",
    "sg:province":"OH",
    "sg:tags":[
        "jeweler"
    ],
    "wof:name":"Aaa Diamond Buyers",
    "wof:placetype":"venue"
},
  "geometry": {"coordinates":[-84.456581,39.15995],"type":"Point"}
}