{
  "type": "Feature",
  "properties": {
    "addr:full": "10423 Stuart Dr Painesville OH 44077",
    "addr:housenumber": "10423",
    "addr:postcode": "44077",
    "addr:street": "Stuart Dr",
    "iso:country": "US",
    "sg:address": "10423 Stuart Dr",
    "sg:city": "Painesville",
    "sg:classifiers": [
      {
        "category": "Professional",
        "subcategory": "Computer Services",
        "type": "Services"
      }
    ],
    "sg:phone": "+1 440 352 8187",
    "sg:postcode": "44077",
    "sg:province": "OH",
    "sg:tags": [
      "consultant",
      "designer"
    ],
    "wof:name": "Paguar Informatics",
    "wof:placetype": "venue"
  },
  "geometry": {"coordinates":[-81.263413,41.681853],"type":"Point"}
}
