{
  "type": "Feature",
  "properties": {
    "addr:full":"8091 Village Dr Cincinnati OH 45242",
    "addr:housenumber":"8091",
    "addr:postcode":"45242",
    "addr:street":"Village Dr",
    "iso:country":"US",
    "sg:address":"8091 Village Dr",
    "sg:city":"Cincinnati",
    "sg:classifiers":[
        {
            "category":"Wholesale",
            "subcategory":"Durable Goods & Equipment",
            "type":"Manufacturing & Wholesale Goods"
        }
    ],
    "sg:phone":"+1 513 489 3567",
    "sg:postcode":"45242",
    "sg:province":"OH",
    "sg:tags":[
        "devices"
    ],
    "wof:name":"Thermo Electron Corporation",
    "wof:placetype":"venue"
},
  "geometry": {"coordinates":[-84.3449,39.259584],"type":"Point"}
}