{
  "type": "Feature",
  "properties": {
    "addr:full":"25360 Westwood Rd Cleveland OH 44145",
    "addr:housenumber":"25360",
    "addr:postcode":"44145",
    "addr:street":"Westwood Rd",
    "iso:country":"US",
    "sg:address":"25360 Westwood Rd",
    "sg:city":"Cleveland",
    "sg:classifiers":[
        {
            "category":"Professional",
            "subcategory":"Lawyer & Legal Services",
            "type":"Services"
        }
    ],
    "sg:phone":"+1 440 871 4858",
    "sg:postcode":"44145",
    "sg:province":"OH",
    "sg:tags":[
        "attorney"
    ],
    "wof:name":"Jeffrey Kocian",
    "wof:placetype":"venue"
},
  "geometry": {"coordinates":[-81.902187,41.449504],"type":"Point"}
}