{
  "type": "Feature",
  "properties": {
    "addr:full": "2474 Indian Path Dr Westlake OH 44145",
    "addr:housenumber": "2474",
    "addr:postcode": "44145",
    "addr:street": "Indian Path Dr",
    "iso:country": "US",
    "sg:address": "2474 Indian Path Dr",
    "sg:city": "Westlake",
    "sg:classifiers": [
      {
        "category": "Freight",
        "type": "Transportation"
      }
    ],
    "sg:phone": "+1 216 789 4789",
    "sg:postcode": "44145",
    "sg:province": "OH",
    "sg:tags": [
      "water"
    ],
    "wof:name": "Imex",
    "wof:placetype": "venue"
  },
  "geometry": {"coordinates":[-81.940767,41.453374],"type":"Point"}
}
