{
  "type": "Feature",
  "properties": {
    "iso:country":"US",
    "sg:address":"855 S Holland Sylvania Rd",
    "sg:city":"Toledo",
    "sg:classifiers":[
        {
            "category":"Food & Beverages",
            "subcategory":"Groceries & Convenience Stores",
            "type":"Retail Goods"
        }
    ],
    "sg:phone":"+1 419 865 4500",
    "sg:postcode":"43615",
    "sg:province":"OH",
    "wof:name":"Crosstown Carry Out",
    "wof:placetype":"venue"
},
  "geometry": {"coordinates":[-83.684107,41.625661],"type":"Point"}
}