{
  "type": "Feature",
  "properties": {
    "iso:country":"US",
    "sg:address":"6818 Bramblewood Ln",
    "sg:city":"Cleveland",
    "sg:classifiers":[
        {
            "category":"Wholesale",
            "subcategory":"Electrical",
            "type":"Manufacturing & Wholesale Goods"
        }
    ],
    "sg:phone":"+1 440 720 0050",
    "sg:postcode":"44143",
    "sg:province":"OH",
    "sg:tags":[
        "control"
    ],
    "wof:name":"Veritas Industrial Control LLC",
    "wof:placetype":"venue"
},
  "geometry": {"coordinates":[-81.433072,41.551403],"type":"Point"}
}