{
  "type": "Feature",
  "properties": {
    "addr:full": "5422 Lower Leesville Rd Crestline OH 44827",
    "addr:housenumber": "5422",
    "addr:postcode": "44827",
    "addr:street": "Lower Leesville Rd",
    "iso:country": "US",
    "sg:address": "5422 Lower Leesville Rd",
    "sg:city": "Crestline",
    "sg:classifiers": [
      {
        "category": "Organizations",
        "subcategory": "Religious Organization",
        "type": "Services"
      }
    ],
    "sg:phone": "+1 419 562 0769",
    "sg:postcode": "44827",
    "sg:province": "OH",
    "sg:tags": [
      "church"
    ],
    "wof:name": "North Robinson United",
    "wof:placetype": "venue"
  },
  "geometry": {"coordinates":[-82.855786,40.799424],"type":"Point"}
}
