{
  "type": "Feature",
  "properties": {
    "addr:full":"8615 Frazeysburg Rd Dresden OH 43821",
    "addr:housenumber":"8615",
    "addr:postcode":"43821",
    "addr:street":"Frazeysburg Rd",
    "iso:country":"US",
    "sg:address":"8615 Frazeysburg Rd",
    "sg:city":"Dresden",
    "sg:classifiers":[
        {
            "category":"Bars & Pubs",
            "type":"Food & Drink"
        }
    ],
    "sg:phone":"+1 740 828 2926",
    "sg:postcode":"43821",
    "sg:province":"OH",
    "sg:tags":[
        "drinking"
    ],
    "wof:name":"Green's Tea Room",
    "wof:placetype":"venue"
},
  "geometry": {"coordinates":[-82.06504,40.088122],"type":"Point"}
}