{
  "type": "Feature",
  "properties": {
    "addr:full":"338 W Johnson St Upper Sandusky OH 43351",
    "addr:housenumber":"338",
    "addr:postcode":"43351",
    "addr:street":"W Johnson St",
    "iso:country":"US",
    "sg:address":"338 W Johnson St",
    "sg:city":"Upper Sandusky",
    "sg:classifiers":[
        {
            "category":"Real Estate",
            "subcategory":"Real Estate Agent",
            "type":"Services"
        }
    ],
    "sg:phone":"+1 419 294 1014",
    "sg:postcode":"43351",
    "sg:province":"OH",
    "wof:name":"JFK Inc",
    "wof:placetype":"venue"
},
  "geometry": {"coordinates":[-83.285937,40.826201],"type":"Point"}
}