{
  "type": "Feature",
  "properties": {
    "addr:full":"415 Byers Rd Miamisburg OH 45342",
    "addr:housenumber":"415",
    "addr:postcode":"45342",
    "addr:street":"Byers Rd",
    "iso:country":"US",
    "sg:address":"415 Byers Rd",
    "sg:city":"Miamisburg",
    "sg:classifiers":[
        {
            "category":"Health Services",
            "subcategory":"Medical Lab",
            "type":"Services"
        }
    ],
    "sg:phone":"+1 937 866 8188",
    "sg:postcode":"45342",
    "sg:province":"OH",
    "sg:tags":[
        "laboratory"
    ],
    "wof:name":"Laboratory Corp Of America",
    "wof:placetype":"venue"
},
  "geometry": {"coordinates":[-84.234881,39.634742],"type":"Point"}
}