{
  "type": "Feature",
  "properties": {
    "addr:full": "3297 Panhandle Rd Delaware OH 43015",
    "addr:housenumber": "3297",
    "addr:postcode": "43015",
    "addr:street": "Panhandle Rd",
    "iso:country": "US",
    "sg:address": "3297 Panhandle Rd",
    "sg:city": "Delaware",
    "sg:classifiers": [
      {
        "category": "Wholesale",
        "subcategory": "Farm Supplies",
        "type": "Manufacturing \u0026 Wholesale Goods"
      }
    ],
    "sg:phone": "+1 740 363 5883",
    "sg:postcode": "43015",
    "sg:province": "OH",
    "sg:tags": [
      "bulb",
      "seed"
    ],
    "wof:name": "Case Farms",
    "wof:placetype": "venue"
  },
  "geometry": {"coordinates":[-83.054764,40.349657],"type":"Point"}
}
