{
  "type": "Feature",
  "properties": {
    "addr:full": "65 S Front St Columbus OH 43215",
    "addr:housenumber": "65",
    "addr:postcode": "43215",
    "addr:street": "S Front St",
    "iso:country": "US",
    "sg:address": "65 S Front St",
    "sg:city": "Columbus",
    "sg:classifiers": [
      {
        "category": "Government",
        "subcategory": "Office",
        "type": "Public Place"
      }
    ],
    "sg:phone": "+1 614 752 9573",
    "sg:postcode": "43215",
    "sg:province": "OH",
    "sg:tags": [
      "program",
      "education"
    ],
    "wof:name": "Curriclum Instruction Prof Dev",
    "wof:placetype": "venue"
  },
  "geometry": {"coordinates":[-83.002195,39.960705],"type":"Point"}
}
