{
  "type": "Feature",
  "properties": {
    "addr:full": "5074 Darrow Rd Hudson OH 44236",
    "addr:housenumber": "5074",
    "addr:postcode": "44236",
    "addr:street": "Darrow Rd",
    "iso:country": "US",
    "sg:address": "5074 Darrow Rd",
    "sg:city": "Hudson",
    "sg:classifiers": [
      {
        "category": "Recreation",
        "type": "Entertainment"
      }
    ],
    "sg:phone": "+1 330 650 6222",
    "sg:postcode": "44236",
    "sg:province": "OH",
    "sg:tags": [
      "miniature",
      "operation",
      "golf",
      "course"
    ],
    "wof:name": "Double Play Baseball School",
    "wof:placetype": "venue"
  },
  "geometry": {"coordinates":[-81.440484,41.207667],"type":"Point"}
}
