{
  "type": "Feature",
  "properties": {
    "addr:full": "9411 Ledge Acres Dr Macedonia OH 44056",
    "addr:housenumber": "9411",
    "addr:postcode": "44056",
    "addr:street": "Ledge Acres Dr",
    "iso:country": "US",
    "sg:address": "9411 Ledge Acres Dr",
    "sg:city": "Macedonia",
    "sg:classifiers": [
      {
        "category": "Professional",
        "type": "Services"
      }
    ],
    "sg:phone": "+1 330 468 5882",
    "sg:postcode": "44056",
    "sg:province": "OH",
    "sg:tags": [
      "establishment"
    ],
    "wof:name": "Dark Imp Studios",
    "wof:placetype": "venue"
  },
  "geometry": {"coordinates":[-81.505036,41.338474],"type":"Point"}
}
