{
  "type": "Feature",
  "properties": {
    "iso:country":"US",
    "sg:address":"5309 McCartney Rd",
    "sg:city":"Sandusky",
    "sg:classifiers":[
        {
            "category":"Building & Trades",
            "subcategory":"Construction",
            "type":"Services"
        }
    ],
    "sg:phone":"+1 419 626 2757",
    "sg:postcode":"44870",
    "sg:province":"OH",
    "sg:tags":[
        "contractor"
    ],
    "wof:name":"Thomas Contracting",
    "wof:placetype":"venue"
},
  "geometry": {"coordinates":[-82.779617,41.448502],"type":"Point"}
}