{
  "type": "Feature",
  "properties": {
    "addr:full": "2045 S Co Rd 25A Troy OH 45373",
    "addr:housenumber": "2045;25a",
    "addr:postcode": "45373",
    "addr:street": "S Co Rd",
    "iso:country": "US",
    "sg:address": "2045 S Co Rd 25A",
    "sg:city": "Troy",
    "sg:classifiers": [
      {
        "category": "Autos \u0026 Motor Vehicles",
        "subcategory": "Automobile Sales",
        "type": "Retail Goods"
      }
    ],
    "sg:phone": "+1 937 339 1409",
    "sg:postcode": "45373",
    "sg:province": "OH",
    "sg:tags": [
      "used"
    ],
    "wof:name": "Gerrys Auto Sales \u0026 Service",
    "wof:placetype": "venue"
  },
  "geometry": {"coordinates":[-84.200627,40.009785],"type":"Point"}
}
