{
  "type": "Feature",
  "properties": {
    "addr:full":"286 E State St Salem OH 44460",
    "addr:housenumber":"286",
    "addr:postcode":"44460",
    "addr:street":"E State St",
    "iso:country":"US",
    "sg:address":"286 E State St",
    "sg:city":"Salem",
    "sg:classifiers":[
        {
            "category":"Real Estate",
            "subcategory":"Real Estate Agent",
            "type":"Services"
        }
    ],
    "sg:phone":"+1 330 337 3000",
    "sg:postcode":"44460",
    "sg:province":"OH",
    "wof:name":"Hardcastle Realty",
    "wof:placetype":"venue"
},
  "geometry": {"coordinates":[-80.85664,40.901028],"type":"Point"}
}