{
  "type": "Feature",
  "properties": {
    "iso:country":"US",
    "sg:address":"2415 Woodland Ave",
    "sg:city":"Cleveland",
    "sg:classifiers":[
        {
            "category":"Education",
            "subcategory":"College",
            "type":"Public Place"
        }
    ],
    "sg:phone":"+1 216 987 3030",
    "sg:postcode":"44104",
    "sg:province":"OH",
    "sg:tags":[
        "academic",
        "school"
    ],
    "wof:name":"Cuyahoga Community College",
    "wof:placetype":"venue"
},
  "geometry": {"coordinates":[-81.673562,41.492744],"type":"Point"}
}