{
  "type": "Feature",
  "properties": {
    "addr:full": "1706 Canton Rd Akron OH 44312",
    "addr:housenumber": "1706",
    "addr:postcode": "44312",
    "addr:street": "Canton Rd",
    "iso:country": "US",
    "sg:address": "1706 Canton Rd",
    "sg:city": "Akron",
    "sg:classifiers": [
      {
        "category": "Manufacturing",
        "subcategory": "Pottery",
        "type": "Manufacturing \u0026 Wholesale Goods"
      }
    ],
    "sg:phone": "+1 330 733 3384",
    "sg:postcode": "44312",
    "sg:province": "OH",
    "sg:tags": [
      "product",
      "mfg"
    ],
    "sg:website": "www.ocepekpottery.com",
    "wof:name": "Ocepek Pottery",
    "wof:placetype": "venue"
  },
  "geometry": {"coordinates":[-81.416137,41.019716],"type":"Point"}
}
