{
  "type": "Feature",
  "properties": {
    "iso:country":"US",
    "sg:address":"116 N Front St",
    "sg:city":"Fremont",
    "sg:classifiers":[
        {
            "category":"Shopping",
            "subcategory":"Used Merchandise",
            "type":"Retail Goods"
        }
    ],
    "sg:phone":"+1 419 355 1100",
    "sg:postcode":"43420",
    "sg:province":"OH",
    "sg:tags":[
        "shop",
        "consignment"
    ],
    "wof:name":"Valerie's Wardrobe & Cnsgnmnt",
    "wof:placetype":"venue"
},
  "geometry": {"coordinates":[-83.113487,41.34709],"type":"Point"}
}