{
  "type": "Feature",
  "properties": {
    "addr:full":"420 W Walnut St Kenton OH 43326",
    "addr:housenumber":"420",
    "addr:postcode":"43326",
    "addr:street":"W Walnut St",
    "iso:country":"US",
    "sg:address":"420 W Walnut St",
    "sg:city":"Kenton",
    "sg:classifiers":[
        {
            "category":"Building & Trades",
            "subcategory":"Construction",
            "type":"Services"
        }
    ],
    "sg:phone":"+1 419 674 4712",
    "sg:postcode":"43326",
    "sg:province":"OH",
    "sg:tags":[
        "concrete",
        "contractor"
    ],
    "wof:name":"Tice Construction Co",
    "wof:placetype":"venue"
},
  "geometry": {"coordinates":[-83.614665,40.645418],"type":"Point"}
}