{
  "type": "Feature",
  "properties": {
    "addr:full": "227 E Main St Jefferson OH 44030",
    "addr:housenumber": "227",
    "addr:postcode": "44030",
    "addr:street": "E Main St",
    "iso:country": "US",
    "sg:address": "227 E Main St",
    "sg:city": "Jefferson",
    "sg:classifiers": [
      {
        "category": "Autos \u0026 Motor Vehicles",
        "subcategory": "Fuel \u0026 Gas Station",
        "type": "Retail Goods"
      }
    ],
    "sg:phone": "+1 614 879 9219",
    "sg:postcode": "44030",
    "sg:province": "OH",
    "sg:tags": [
      "station",
      "gasoline"
    ],
    "wof:name": "Midwest Transmissions",
    "wof:placetype": "venue"
  },
  "geometry": {"coordinates":[-80.554794,41.943096],"type":"Point"}
}
