{
  "type": "Feature",
  "properties": {
    "addr:full": "203 E Royalton Rd Cleveland OH 44147",
    "addr:housenumber": "203",
    "addr:postcode": "44147",
    "addr:street": "E Royalton Rd",
    "iso:country": "US",
    "sg:address": "203 E Royalton Rd",
    "sg:city": "Cleveland",
    "sg:classifiers": [
      {
        "category": "Restaurant",
        "type": "Food \u0026 Drink"
      }
    ],
    "sg:phone": "+1 440 526 0789",
    "sg:postcode": "44147",
    "sg:province": "OH",
    "wof:name": "Pazzo's",
    "wof:placetype": "venue"
  },
  "geometry": {"coordinates":[-81.681342,41.313923],"type":"Point"}
}
