{
  "type": "Feature",
  "properties": {
    "addr:full": "1593 Commerce Dr Stow OH 44224",
    "addr:housenumber": "1593",
    "addr:postcode": "44224",
    "addr:street": "Commerce Dr",
    "iso:country": "US",
    "sg:address": "1593 Commerce Dr",
    "sg:city": "Stow",
    "sg:classifiers": [
      {
        "category": "Manufacturing",
        "subcategory": "Aerospace",
        "type": "Manufacturing \u0026 Wholesale Goods"
      }
    ],
    "sg:phone": "+1 330 686 5300",
    "sg:postcode": "44224",
    "sg:province": "OH",
    "sg:tags": [
      "mfg",
      "parts",
      "for",
      "plastic"
    ],
    "wof:name": "Goodrich Corporation",
    "wof:placetype": "venue"
  },
  "geometry": {"coordinates":[-81.442803,41.190891],"type":"Point"}
}
