{
  "type": "Feature",
  "properties": {
    "addr:full": "27412 Rainbow Lane Cir Beloit OH 44609",
    "addr:housenumber": "27412",
    "addr:postcode": "44609",
    "addr:street": "Rainbow Lane Cir",
    "iso:country": "US",
    "sg:address": "27412 Rainbow Lane Cir",
    "sg:city": "Beloit",
    "sg:classifiers": [
      {
        "category": "Manufacturing",
        "subcategory": "Printing",
        "type": "Manufacturing \u0026 Wholesale Goods"
      }
    ],
    "sg:phone": "+1 330 537 3696",
    "sg:postcode": "44609",
    "sg:province": "OH",
    "sg:tags": [
      "commercial"
    ],
    "wof:name": "Family Place",
    "wof:placetype": "venue"
  },
  "geometry": {"coordinates":[-80.98772,40.898477],"type":"Point"}
}
