{
  "type": "Feature",
  "properties": {
    "addr:full": "61 E Main St Girard OH 44420",
    "addr:housenumber": "61",
    "addr:postcode": "44420",
    "addr:street": "E Main St",
    "iso:country": "US",
    "sg:address": "61 E Main St",
    "sg:city": "Girard",
    "sg:classifiers": [
      {
        "category": "Health Services",
        "subcategory": "Nursing And Care Facility",
        "type": "Services"
      },
      {
        "category": "Health Services",
        "subcategory": "Health Practitioner",
        "type": "Services"
      }
    ],
    "sg:phone": "+1 330 545 3751",
    "sg:postcode": "44420",
    "sg:province": "OH",
    "sg:tags": [
      "physician",
      "nurse",
      "assistant"
    ],
    "wof:name": "Strose Nurse Clinic",
    "wof:placetype": "venue"
  },
  "geometry": {"coordinates":[-80.699554,41.15501],"type":"Point"}
}
