{
  "type": "Feature",
  "properties": {
    "iso:country":"US",
    "sg:address":"61 E Main St",
    "sg:city":"Girard",
    "sg:classifiers":[
        {
            "category":"Health Services",
            "subcategory":"Nursing And Care Facility",
            "type":"Services"
        },
        {
            "category":"Health Services",
            "subcategory":"Health Practitioner",
            "type":"Services"
        }
    ],
    "sg:phone":"+1 330 545 3751",
    "sg:postcode":"44420",
    "sg:province":"OH",
    "sg:tags":[
        "physician",
        "nurse",
        "assistant"
    ],
    "wof:name":"Strose Nurse Clinic",
    "wof:placetype":"venue"
},
  "geometry": {"coordinates":[-80.69955400000001,41.15501],"type":"Point"}
}