{
  "type": "Feature",
  "properties": {
    "iso:country":"US",
    "sg:address":"340 E Hunter St",
    "sg:city":"Logan",
    "sg:classifiers":[
        {
            "category":"Restaurant",
            "type":"Food & Drink"
        }
    ],
    "sg:phone":"+1 740 852 1689",
    "sg:postcode":"43138",
    "sg:province":"OH",
    "sg:tags":[
        "eating"
    ],
    "wof:name":"Jerry Tedrow",
    "wof:placetype":"venue"
},
  "geometry": {"coordinates":[-82.403403,39.540895],"type":"Point"}
}