{
  "type": "Feature",
  "properties": {
    "addr:full": "8613 Mayfield Rd Chesterland OH 44026",
    "addr:housenumber": "8613",
    "addr:postcode": "44026",
    "addr:street": "Mayfield Rd",
    "iso:country": "US",
    "sg:address": "8613 Mayfield Rd",
    "sg:city": "Chesterland",
    "sg:classifiers": [
      {
        "category": "Education",
        "subcategory": "Special Training",
        "type": "Public Place"
      }
    ],
    "sg:phone": "+1 440 729 1110",
    "sg:postcode": "44026",
    "sg:province": "OH",
    "sg:tags": [
      "school",
      "cooking"
    ],
    "wof:name": "Paganini Loretta Schl Cooking",
    "wof:placetype": "venue"
  },
  "geometry": {"coordinates":[-81.331522,41.521963],"type":"Point"}
}
