{
  "type": "Feature",
  "properties": {
    "addr:full": "3394 Co Rd 16 Wauseon OH 43567",
    "addr:housenumber": "3394;16",
    "addr:postcode": "43567",
    "addr:street": "Co Rd",
    "iso:country": "US",
    "sg:address": "3394 Co Rd 16",
    "sg:city": "Wauseon",
    "sg:phone": "+1 419 337 8393",
    "sg:postcode": "43567",
    "sg:province": "OH",
    "sg:tags": [
      "farm",
      "corn",
      "soybean"
    ],
    "wof:name": "Jerry Aeschliman",
    "wof:placetype": "venue"
  },
  "geometry": {"coordinates":[-84.172587,41.529355],"type":"Point"}
}
