{
  "type": "Feature",
  "properties": {
    "addr:full": "1882 Highland Rd Twinsburg OH 44087",
    "addr:housenumber": "1882",
    "addr:postcode": "44087",
    "addr:street": "Highland Rd",
    "iso:country": "US",
    "sg:address": "1882 Highland Rd",
    "sg:city": "Twinsburg",
    "sg:classifiers": [
      {
        "category": "Wholesale",
        "subcategory": "Machinery \u0026 Supplies",
        "type": "Manufacturing \u0026 Wholesale Goods"
      }
    ],
    "sg:phone": "+1 330 405 9183",
    "sg:postcode": "44087",
    "sg:province": "OH",
    "sg:tags": [
      "industrial",
      "miscellaneous"
    ],
    "wof:name": "Stainless Equipment \u0026 Systems",
    "wof:placetype": "venue"
  },
  "geometry": {"coordinates":[-81.447247,41.297672],"type":"Point"}
}
