{
  "type": "Feature",
  "properties": {
    "iso:country":"US",
    "sg:address":"5427 Bradley Brownlee Rd",
    "sg:city":"Fowler",
    "sg:classifiers":[
        {
            "category":"Manufacturing",
            "subcategory":"Lumber",
            "type":"Manufacturing & Wholesale Goods"
        }
    ],
    "sg:phone":"+1 330 637 6654",
    "sg:postcode":"44418",
    "sg:province":"OH",
    "sg:tags":[
        "hardwood",
        "mill"
    ],
    "wof:name":"Latimer Station Hardwood",
    "wof:placetype":"venue"
},
  "geometry": {"coordinates":[-80.624273,41.350319],"type":"Point"}
}