{
  "type": "Feature",
  "properties": {
    "addr:full": "6990 Princeville Ct Blacklick OH 43004",
    "addr:postcode": "6990;43004",
    "addr:street": "Princeville Ct",
    "iso:country": "US",
    "sg:address": "6990 Princeville Ct",
    "sg:city": "Blacklick",
    "sg:classifiers": [
      {
        "category": "Building \u0026 Trades",
        "subcategory": "Plumbing",
        "type": "Services"
      }
    ],
    "sg:phone": "+1 614 501 6709",
    "sg:postcode": "43004",
    "sg:province": "OH",
    "sg:tags": [
      "contractor"
    ],
    "wof:name": "Heinmiller Plumbing",
    "wof:placetype": "venue"
  },
  "geometry": {"coordinates":[-82.822892,40.007828],"type":"Point"}
}
