{
  "type": "Feature",
  "properties": {
    "iso:country":"US",
    "sg:address":"6990 Princeville Ct",
    "sg:city":"Blacklick",
    "sg:classifiers":[
        {
            "category":"Building & Trades",
            "subcategory":"Plumbing",
            "type":"Services"
        }
    ],
    "sg:phone":"+1 614 501 6709",
    "sg:postcode":"43004",
    "sg:province":"OH",
    "sg:tags":[
        "contractor"
    ],
    "wof:name":"Heinmiller Plumbing",
    "wof:placetype":"venue"
},
  "geometry": {"coordinates":[-82.822892,40.007828],"type":"Point"}
}