{
  "type": "Feature",
  "properties": {
    "iso:country":"US",
    "sg:address":"4208 Seville Rd",
    "sg:city":"Seville",
    "sg:classifiers":[
        {
            "category":"Building & Trades",
            "subcategory":"Construction",
            "type":"Services"
        }
    ],
    "sg:phone":"+1 330 769 1314",
    "sg:postcode":"44273",
    "sg:province":"OH",
    "sg:tags":[
        "house"
    ],
    "wof:name":"Scheiman Bros Construction Co",
    "wof:placetype":"venue"
},
  "geometry": {"coordinates":[-81.837932,41.009897],"type":"Point"}
}