{
  "type": "Feature",
  "properties": {
    "addr:full": "6340 Lakeview Dr Ravenna OH 44266",
    "addr:housenumber": "6340",
    "addr:postcode": "44266",
    "addr:street": "Lakeview Dr",
    "iso:country": "US",
    "sg:address": "6340 Lakeview Dr",
    "sg:city": "Ravenna",
    "sg:classifiers": [
      {
        "category": "Building \u0026 Trades",
        "subcategory": "Construction",
        "type": "Services"
      }
    ],
    "sg:phone": "+1 330 678 5787",
    "sg:postcode": "44266",
    "sg:province": "OH",
    "sg:tags": [
      "home",
      "improvement",
      "contractor"
    ],
    "sg:website": "www.eranbuilding.com",
    "wof:name": "Eran Building \u0026 Remodeling Inc",
    "wof:placetype": "venue"
  },
  "geometry": {"coordinates":[-81.313639,41.163605],"type":"Point"}
}
