{
  "type": "Feature",
  "properties": {
    "iso:country":"US",
    "sg:address":"6340 Lakeview Dr",
    "sg:city":"Ravenna",
    "sg:classifiers":[
        {
            "category":"Building & Trades",
            "subcategory":"Construction",
            "type":"Services"
        }
    ],
    "sg:phone":"+1 330 678 5787",
    "sg:postcode":"44266",
    "sg:province":"OH",
    "sg:tags":[
        "home",
        "improvement",
        "contractor"
    ],
    "sg:website":"www.eranbuilding.com",
    "wof:name":"Eran Building & Remodeling Inc",
    "wof:placetype":"venue"
},
  "geometry": {"coordinates":[-81.31363899999999,41.163605],"type":"Point"}
}