{
  "type": "Feature",
  "properties": {
    "addr:full": "101 W Park Ave Columbiana OH 44408",
    "addr:housenumber": "101",
    "addr:postcode": "44408",
    "addr:street": "W Park Ave",
    "iso:country": "US",
    "sg:address": "101 W Park Ave",
    "sg:city": "Columbiana",
    "sg:classifiers": [
      {
        "category": "Manufacturing",
        "subcategory": "Apparel",
        "type": "Manufacturing \u0026 Wholesale Goods"
      }
    ],
    "sg:phone": "+1 330 482 6100",
    "sg:postcode": "44408",
    "sg:province": "OH",
    "sg:tags": [
      "printing",
      "commercial"
    ],
    "wof:name": "Flying Needles Inc",
    "wof:placetype": "venue"
  },
  "geometry": {"coordinates":[-80.69519,40.888681],"type":"Point"}
}
