{
  "type": "Feature",
  "properties": {
    "iso:country":"US",
    "sg:address":"859 E Center St",
    "sg:city":"Marion",
    "sg:classifiers":[
        {
            "category":"Home & Garden",
            "subcategory":"Garden Supply",
            "type":"Retail Goods"
        }
    ],
    "sg:phone":"+1 740 375 4541",
    "sg:postcode":"43302",
    "sg:province":"OH",
    "sg:tags":[
        "nurseryman"
    ],
    "wof:name":"MRF Nursery",
    "wof:placetype":"venue"
},
  "geometry": {"coordinates":[-83.108596,40.589354],"type":"Point"}
}