{
  "type": "Feature",
  "properties": {
    "addr:full": "1834 E High Ave New Philadelphia OH 44663",
    "addr:housenumber": "1834",
    "addr:postcode": "44663",
    "addr:street": "E High Ave",
    "iso:country": "US",
    "sg:address": "1834 E High Ave",
    "sg:city": "New Philadelphia",
    "sg:classifiers": [
      {
        "category": "Utilities",
        "subcategory": "Fuel Oil \u0026 Lpg",
        "type": "Services"
      }
    ],
    "sg:phone": "+1 330 339 6078",
    "sg:postcode": "44663",
    "sg:province": "OH",
    "sg:tags": [
      "consulting",
      "dealer"
    ],
    "wof:name": "Professnal AVI Municpl Mgmt GP",
    "wof:placetype": "venue"
  },
  "geometry": {"coordinates":[-81.4179,40.47141],"type":"Point"}
}
