{
  "type": "Feature",
  "properties": {
    "iso:country":"US",
    "sg:address":"55 E Main St",
    "sg:city":"Geneva",
    "sg:classifiers":[
        {
            "category":"Restaurant",
            "type":"Food & Drink"
        }
    ],
    "sg:phone":"+1 440 466 7500",
    "sg:postcode":"44041",
    "sg:province":"OH",
    "sg:tags":[
        "eating"
    ],
    "wof:name":"Culinary Wizards Inc",
    "wof:placetype":"venue"
},
  "geometry": {"coordinates":[-80.94686799999999,41.805548],"type":"Point"}
}