{
  "type": "Feature",
  "properties": {
    "iso:country":"US",
    "sg:address":"1950 Sand Hill Rd",
    "sg:city":"Monroeville",
    "sg:phone":"+1 419 465 2253",
    "sg:postcode":"44847",
    "sg:province":"OH",
    "sg:tags":[
        "farm",
        "corn",
        "wheat",
        "soybean"
    ],
    "wof:name":"Dale Scheid",
    "wof:placetype":"venue"
},
  "geometry": {"coordinates":[-82.732494,41.195134],"type":"Point"}
}