{
  "type": "Feature",
  "properties": {
    "iso:country":"US",
    "sg:address":"371 W 2nd St",
    "sg:city":"Dayton",
    "sg:classifiers":[
        {
            "category":"Government",
            "subcategory":"Office",
            "type":"Public Place"
        }
    ],
    "sg:phone":"+1 937 333 3883",
    "sg:postcode":"45402",
    "sg:province":"OH",
    "sg:tags":[
        "village"
    ],
    "wof:name":"Dayton Building Svc Dept",
    "wof:placetype":"venue"
},
  "geometry": {"coordinates":[-84.201179,39.75966],"type":"Point"}
}