{
  "type": "Feature",
  "properties": {
    "addr:full":"47 Broad St Lucas OH 44846",
    "addr:housenumber":"47",
    "addr:postcode":"44846",
    "addr:street":"Broad St",
    "iso:country":"US",
    "sg:address":"47 Broad St",
    "sg:city":"Lucas",
    "sg:classifiers":[
        {
            "category":"Government",
            "subcategory":"Office",
            "type":"Public Place"
        }
    ],
    "sg:phone":"+1 419 892 3456",
    "sg:postcode":"44846",
    "sg:province":"OH",
    "sg:tags":[
        "govt",
        "city"
    ],
    "wof:name":"Lucas Wastewater Treatment",
    "wof:placetype":"venue"
},
  "geometry": {"coordinates":[-82.599253,41.293151],"type":"Point"}
}