{
  "type": "Feature",
  "properties": {
    "addr:full": "3771 Woodbine Ave Hubbard OH 44425",
    "addr:housenumber": "3771",
    "addr:postcode": "44425",
    "addr:street": "Woodbine Ave",
    "iso:country": "US",
    "sg:address": "3771 Woodbine Ave",
    "sg:city": "Hubbard",
    "sg:classifiers": [
      {
        "category": "Building \u0026 Trades",
        "subcategory": "Construction",
        "type": "Services"
      }
    ],
    "sg:phone": "+1 330 534 1911",
    "sg:postcode": "44425",
    "sg:province": "OH",
    "sg:tags": [
      "contractor"
    ],
    "wof:name": "Rob Phibbs Roofing Co",
    "wof:placetype": "venue"
  },
  "geometry": {"coordinates":[-80.596084,41.138057],"type":"Point"}
}
