{
  "type": "Feature",
  "properties": {
    "iso:country":"US",
    "sg:address":"9565 Midwest Ave",
    "sg:city":"Cleveland",
    "sg:classifiers":[
        {
            "category":"Health Services",
            "subcategory":"Medical Lab",
            "type":"Services"
        }
    ],
    "sg:phone":"+1 216 663 2233",
    "sg:postcode":"44125",
    "sg:province":"OH",
    "sg:tags":[
        "laboratory"
    ],
    "sg:website":"www.roedentallab.com",
    "wof:name":"Roe Dental Lab",
    "wof:placetype":"venue"
},
  "geometry": {"coordinates":[-81.619625,41.41965],"type":"Point"}
}