{
  "type": "Feature",
  "properties": {
    "addr:full":"3389 Glenmore Ave Cincinnati OH 45211",
    "addr:housenumber":"3389",
    "addr:postcode":"45211",
    "addr:street":"Glenmore Ave",
    "iso:country":"US",
    "sg:address":"3389 Glenmore Ave",
    "sg:city":"Cincinnati",
    "sg:classifiers":[
        {
            "category":"Personal",
            "subcategory":"Beauty Salon",
            "type":"Services"
        }
    ],
    "sg:phone":"+1 513 481 2575",
    "sg:postcode":"45211",
    "sg:province":"OH",
    "wof:name":"Fran's Hair Styling",
    "wof:placetype":"venue"
},
  "geometry": {"coordinates":[-84.612832,39.14889],"type":"Point"}
}