{
  "type": "Feature",
  "properties": {
    "iso:country":"US",
    "sg:address":"2721 Wayne Ave",
    "sg:city":"Dayton",
    "sg:classifiers":[
        {
            "category":"Government",
            "subcategory":"Police Station",
            "type":"Public Place"
        }
    ],
    "sg:phone":"+1 937 333 7440",
    "sg:postcode":"45420",
    "sg:province":"OH",
    "sg:tags":[
        "department"
    ],
    "wof:name":"Dayton Police Dept-2nd Dist",
    "wof:placetype":"venue"
},
  "geometry": {"coordinates":[-84.15426100000001,39.739082],"type":"Point"}
}