{
  "type": "Feature",
  "properties": {
    "addr:full":"4190 Harrison Ave Cincinnati OH 45211",
    "addr:housenumber":"4190",
    "addr:postcode":"45211",
    "addr:street":"Harrison Ave",
    "iso:country":"US",
    "sg:address":"4190 Harrison Ave",
    "sg:city":"Cincinnati",
    "sg:classifiers":[
        {
            "category":"Banks & Credit Unions",
            "subcategory":"Financial Services",
            "type":"Services"
        },
        {
            "category":"Professional",
            "subcategory":"Credit Reporting & Collection",
            "type":"Services"
        }
    ],
    "sg:phone":"+1 513 481 7000",
    "sg:postcode":"45211",
    "sg:province":"OH",
    "sg:tags":[
        "debt",
        "adjuster",
        "agency"
    ],
    "wof:name":"Collection Management Services",
    "wof:placetype":"venue"
},
  "geometry": {"coordinates":[-84.62014000000001,39.159901],"type":"Point"}
}