{
  "type": "Feature",
  "properties": {
    "iso:country":"US",
    "sg:address":"7470 S Boyden Rd",
    "sg:city":"Northfield",
    "sg:classifiers":[
        {
            "category":"Building & Trades",
            "subcategory":"Construction",
            "type":"Services"
        }
    ],
    "sg:phone":"+1 330 467 9393",
    "sg:postcode":"44067",
    "sg:province":"OH",
    "sg:tags":[
        "house"
    ],
    "wof:name":"S & S Interiors",
    "wof:placetype":"venue"
},
  "geometry": {"coordinates":[-81.548653,41.304459],"type":"Point"}
}