{
  "type": "Feature",
  "properties": {
    "addr:full": "7470 S Boyden Rd Northfield OH 44067",
    "addr:housenumber": "7470",
    "addr:postcode": "44067",
    "addr:street": "S Boyden Rd",
    "iso:country": "US",
    "sg:address": "7470 S Boyden Rd",
    "sg:city": "Northfield",
    "sg:classifiers": [
      {
        "category": "Building \u0026 Trades",
        "subcategory": "Construction",
        "type": "Services"
      }
    ],
    "sg:phone": "+1 330 467 9393",
    "sg:postcode": "44067",
    "sg:province": "OH",
    "sg:tags": [
      "house"
    ],
    "wof:name": "S \u0026 S Interiors",
    "wof:placetype": "venue"
  },
  "geometry": {"coordinates":[-81.548653,41.304459],"type":"Point"}
}
