{
  "type": "Feature",
  "properties": {
    "addr:full":"2152 W Laskey Rd Toledo OH 43613",
    "addr:housenumber":"2152",
    "addr:postcode":"43613",
    "addr:street":"W Laskey Rd",
    "iso:country":"US",
    "sg:address":"2152 W Laskey Rd",
    "sg:city":"Toledo",
    "sg:classifiers":[
        {
            "category":"Shopping",
            "type":"Retail Goods"
        }
    ],
    "sg:phone":"+1 419 471 9394",
    "sg:postcode":"43613",
    "sg:province":"OH",
    "sg:tags":[
        "factory",
        "outlet"
    ],
    "wof:name":"A Lot 4 Less",
    "wof:placetype":"venue"
},
  "geometry": {"coordinates":[-83.597295,41.706852],"type":"Point"}
}