{
  "type": "Feature",
  "properties": {
    "iso:country":"US",
    "sg:address":"4117 E Livingston Ave",
    "sg:city":"Columbus",
    "sg:classifiers":[
        {
            "category":"Organizations",
            "subcategory":"Religious Organization",
            "type":"Services"
        }
    ],
    "sg:phone":"+1 614 239 7510",
    "sg:postcode":"43227",
    "sg:province":"OH",
    "sg:tags":[
        "church"
    ],
    "wof:name":"Shady Lane Presbyterian Church",
    "wof:placetype":"venue"
},
  "geometry": {"coordinates":[-82.886783,39.945299],"type":"Point"}
}