{
  "type": "Feature",
  "properties": {
    "iso:country":"US",
    "sg:address":"131 N Ludlow St",
    "sg:city":"Dayton",
    "sg:classifiers":[
        {
            "category":"Health Services",
            "subcategory":"Doctor",
            "type":"Services"
        }
    ],
    "sg:phone":"+1 937 461 5003",
    "sg:postcode":"45402",
    "sg:province":"OH",
    "sg:tags":[
        "medical"
    ],
    "wof:name":"Posevitz Laszlo Do Inc",
    "wof:placetype":"venue"
},
  "geometry": {"coordinates":[-84.19419,39.760903],"type":"Point"}
}