{
  "type": "Feature",
  "properties": {
    "addr:full": "1102 Crestview Ave Bryan OH 43506",
    "addr:housenumber": "1102",
    "addr:postcode": "43506",
    "addr:street": "Crestview Ave",
    "iso:country": "US",
    "sg:address": "1102 Crestview Ave",
    "sg:city": "Bryan",
    "sg:classifiers": [
      {
        "category": "Real Estate",
        "subcategory": "Real Estate Agent",
        "type": "Services"
      }
    ],
    "sg:phone": "+1 419 636 1857",
    "sg:postcode": "43506",
    "sg:province": "OH",
    "sg:tags": [
      "broker"
    ],
    "wof:name": "Oberlin Properties Ltd",
    "wof:placetype": "venue"
  },
  "geometry": {"coordinates":[-84.562292,41.461503],"type":"Point"}
}
