{
  "type": "Feature",
  "properties": {
    "iso:country":"US",
    "sg:address":"27031 Gary Ave",
    "sg:city":"Cleveland",
    "sg:classifiers":[
        {
            "category":"Retail",
            "subcategory":"Animal Services",
            "type":"Services"
        }
    ],
    "sg:phone":"+1 216 261 9573",
    "sg:postcode":"44132",
    "sg:province":"OH",
    "sg:tags":[
        "pet",
        "grooming",
        "washing"
    ],
    "wof:name":"Groomers Touch",
    "wof:placetype":"venue"
},
  "geometry": {"coordinates":[-81.49647,41.608981],"type":"Point"}
}