{
  "type": "Feature",
  "properties": {
    "addr:full":"34153 Topaz St North Ridgeville OH 44039",
    "addr:housenumber":"34153",
    "addr:postcode":"44039",
    "addr:street":"Topaz St",
    "iso:country":"US",
    "sg:address":"34153 Topaz St",
    "sg:city":"North Ridgeville",
    "sg:classifiers":[
        {
            "category":"Insurance",
            "subcategory":"Insurance Agent",
            "type":"Services"
        }
    ],
    "sg:phone":"+1 440 353 0450",
    "sg:postcode":"44039",
    "sg:province":"OH",
    "wof:name":"Hartford Steam Boiler Ins Co",
    "wof:placetype":"venue"
},
  "geometry": {"coordinates":[-81.99517400000001,41.413585],"type":"Point"}
}