{
  "type": "Feature",
  "properties": {
    "addr:full":"650 W Smith Rd Medina OH 44256",
    "addr:housenumber":"650",
    "addr:postcode":"44256",
    "addr:street":"W Smith Rd",
    "iso:country":"US",
    "sg:address":"650 W Smith Rd",
    "sg:city":"Medina",
    "sg:classifiers":[
        {
            "category":"Manufacturing",
            "subcategory":"Retail Goods",
            "type":"Manufacturing & Wholesale Goods"
        }
    ],
    "sg:phone":"+1 330 725 3003",
    "sg:postcode":"44256",
    "sg:province":"OH",
    "sg:tags":[
        "cards",
        "mfg",
        "stencil",
        "laminating",
        "label"
    ],
    "wof:name":"McKillip Industries Inc",
    "wof:placetype":"venue"
},
  "geometry": {"coordinates":[-81.87595,41.136135],"type":"Point"}
}