{
  "type": "Feature",
  "properties": {
    "iso:country":"US",
    "sg:address":"287 S Chestnut St",
    "sg:city":"Barnesville",
    "sg:classifiers":[
        {
            "category":"Food & Beverages",
            "subcategory":"Groceries & Convenience Stores",
            "type":"Retail Goods"
        }
    ],
    "sg:phone":"+1 740 425 3700",
    "sg:postcode":"43713",
    "sg:province":"OH",
    "sg:website":"www.convenientfoodmart.com",
    "wof:name":"Convenient Food Mart",
    "wof:placetype":"venue"
},
  "geometry": {"coordinates":[-81.17776600000001,39.98666],"type":"Point"}
}