{
  "type": "Feature",
  "properties": {
    "addr:full": "287 S Chestnut St Barnesville OH 43713",
    "addr:housenumber": "287",
    "addr:postcode": "43713",
    "addr:street": "S Chestnut St",
    "iso:country": "US",
    "sg:address": "287 S Chestnut St",
    "sg:city": "Barnesville",
    "sg:classifiers": [
      {
        "category": "Food \u0026 Beverages",
        "subcategory": "Groceries \u0026 Convenience Stores",
        "type": "Retail Goods"
      }
    ],
    "sg:phone": "+1 740 425 3700",
    "sg:postcode": "43713",
    "sg:province": "OH",
    "sg:website": "www.convenientfoodmart.com",
    "wof:name": "Convenient Food Mart",
    "wof:placetype": "venue"
  },
  "geometry": {"coordinates":[-81.177766,39.98666],"type":"Point"}
}
