{
  "type": "Feature",
  "properties": {
    "iso:country":"US",
    "sg:address":"235 Fairground Rd",
    "sg:city":"Lucasville",
    "sg:classifiers":[
        {
            "category":"Personal",
            "subcategory":"Beauty Salon",
            "type":"Services"
        }
    ],
    "sg:phone":"+1 740 259 3335",
    "sg:postcode":"45648",
    "sg:province":"OH",
    "wof:name":"Reflections",
    "wof:placetype":"venue"
},
  "geometry": {"coordinates":[-82.99661500000001,38.888256],"type":"Point"}
}