{
  "type": "Feature",
  "properties": {
    "iso:country":"US",
    "sg:address":"203 3rd St",
    "sg:city":"Lowell",
    "sg:classifiers":[
        {
            "category":"Government",
            "subcategory":"Post Office",
            "type":"Public Place"
        }
    ],
    "sg:phone":"+1 740 896 2659",
    "sg:postcode":"45744",
    "sg:province":"OH",
    "wof:name":"US Post Office",
    "wof:placetype":"venue"
},
  "geometry": {"coordinates":[-81.506688,39.529379],"type":"Point"}
}