{
  "type": "Feature",
  "properties": {
    "addr:full":"335 Smith Dr Clayton OH 45315",
    "addr:housenumber":"335",
    "addr:postcode":"45315",
    "addr:street":"Smith Dr",
    "iso:country":"US",
    "sg:address":"335 Smith Dr",
    "sg:city":"Clayton",
    "sg:classifiers":[
        {
            "category":"Wholesale",
            "subcategory":"Groceries",
            "type":"Manufacturing & Wholesale Goods"
        }
    ],
    "sg:phone":"+1 937 832 7768",
    "sg:postcode":"45315",
    "sg:province":"OH",
    "sg:tags":[
        "distributor",
        "drink",
        "soft"
    ],
    "wof:name":"Buckeye Distributing Inc",
    "wof:placetype":"venue"
},
  "geometry": {"coordinates":[-84.32432799999999,39.856834],"type":"Point"}
}