{
  "type": "Feature",
  "properties": {
    "iso:country":"US",
    "sg:address":"1402 Wayne Ave",
    "sg:city":"Dayton",
    "sg:classifiers":[
        {
            "category":"Building & Trades",
            "subcategory":"Plumbing",
            "type":"Services"
        }
    ],
    "sg:phone":"+1 937 258 8602",
    "sg:postcode":"45410",
    "sg:province":"OH",
    "sg:tags":[
        "mechanical",
        "contractor"
    ],
    "wof:name":"K Max",
    "wof:placetype":"venue"
},
  "geometry": {"coordinates":[-84.172633,39.748095],"type":"Point"}
}