{
  "type": "Feature",
  "properties": {
    "iso:country":"US",
    "sg:address":"2148 S Lake Ct",
    "sg:city":"Findlay",
    "sg:classifiers":[
        {
            "category":"Health Services",
            "subcategory":"Doctor",
            "type":"Services"
        }
    ],
    "sg:phone":"+1 419 423 8823",
    "sg:postcode":"45840",
    "sg:province":"OH",
    "sg:tags":[
        "physician",
        "surgeon"
    ],
    "wof:name":"Ernesto Y Dy MD",
    "wof:placetype":"venue"
},
  "geometry": {"coordinates":[-83.656256,41.013716],"type":"Point"}
}