{
  "type": "Feature",
  "properties": {
    "addr:full": "783 W Market St Akron OH 44303",
    "addr:housenumber": "783",
    "addr:postcode": "44303",
    "addr:street": "W Market St",
    "iso:country": "US",
    "sg:address": "783 W Market St",
    "sg:city": "Akron",
    "sg:classifiers": [
      {
        "category": "Organizations",
        "subcategory": "Community Association",
        "type": "Services"
      }
    ],
    "sg:phone": "+1 330 253 0022",
    "sg:postcode": "44303",
    "sg:province": "OH",
    "sg:tags": [
      "military"
    ],
    "wof:name": "American Legion",
    "wof:placetype": "venue"
  },
  "geometry": {"coordinates":[-81.54288,41.096351],"type":"Point"}
}
