{
  "type": "Feature",
  "properties": {
    "addr:full": "551 Corbett Rd Groveport OH 43125",
    "addr:housenumber": "551",
    "addr:postcode": "43125",
    "addr:street": "Corbett Rd",
    "iso:country": "US",
    "sg:address": "551 Corbett Rd",
    "sg:city": "Groveport",
    "sg:classifiers": [
      {
        "category": "Building \u0026 Trades",
        "subcategory": "Landscaping Services",
        "type": "Services"
      }
    ],
    "sg:phone": "+1 614 491 1140",
    "sg:postcode": "43125",
    "sg:province": "OH",
    "sg:tags": [
      "lawn",
      "landscape",
      "contractor"
    ],
    "wof:name": "Wilcox \u0026 Sons Lawn \u0026 Landscape Inc",
    "wof:placetype": "venue"
  },
  "geometry": {"coordinates":[-82.884725,39.857295],"type":"Point"}
}
