{
  "type": "Feature",
  "properties": {
    "addr:full": "8220 Industrial Pkwy Plain City OH 43064",
    "addr:housenumber": "8220",
    "addr:postcode": "43064",
    "addr:street": "Industrial Pkwy",
    "iso:country": "US",
    "sg:address": "8220 Industrial Pkwy",
    "sg:city": "Plain City",
    "sg:classifiers": [
      {
        "category": "Building \u0026 Trades",
        "subcategory": "Landscaping Services",
        "type": "Services"
      }
    ],
    "sg:phone": "+1 614 876 9988",
    "sg:postcode": "43064",
    "sg:province": "OH",
    "sg:tags": [
      "lawn",
      "maintenance",
      "grounds"
    ],
    "wof:name": "Environmental Management Svc",
    "wof:placetype": "venue"
  },
  "geometry": {"coordinates":[-83.207684,40.135643],"type":"Point"}
}
