{
  "type": "Feature",
  "properties": {
    "iso:country":"US",
    "sg:address":"825 Tanglewood Dr S",
    "sg:city":"Mansfield",
    "sg:classifiers":[
        {
            "category":"Professional",
            "type":"Services"
        }
    ],
    "sg:phone":"+1 419 747 6544",
    "sg:postcode":"44906",
    "sg:province":"OH",
    "wof:name":"In A Cash Flash",
    "wof:placetype":"venue"
},
  "geometry": {"coordinates":[-82.582177,40.774289],"type":"Point"}
}