{
  "type": "Feature",
  "properties": {
    "addr:full":"110 W Mulberry St Bryan OH 43506",
    "addr:housenumber":"110",
    "addr:postcode":"43506",
    "addr:street":"W Mulberry St",
    "iso:country":"US",
    "sg:address":"110 W Mulberry St",
    "sg:city":"Bryan",
    "sg:classifiers":[
        {
            "category":"Restaurant",
            "type":"Food & Drink"
        }
    ],
    "sg:phone":"+1 419 636 5097",
    "sg:postcode":"43506",
    "sg:province":"OH",
    "wof:name":"Fountain City Ice House Carry",
    "wof:placetype":"venue"
},
  "geometry": {"coordinates":[-84.55165599999999,41.477266],"type":"Point"}
}