{
  "type": "Feature",
  "properties": {
    "addr:full":"1774 Sudbury Dr Holland OH 43528",
    "addr:housenumber":"1774",
    "addr:postcode":"43528",
    "addr:street":"Sudbury Dr",
    "iso:country":"US",
    "sg:address":"1774 Sudbury Dr",
    "sg:city":"Holland",
    "sg:classifiers":[
        {
            "category":"Building & Trades",
            "subcategory":"Construction",
            "type":"Services"
        }
    ],
    "sg:phone":"+1 419 865 4520",
    "sg:postcode":"43528",
    "sg:province":"OH",
    "sg:tags":[
        "roofing",
        "contractor"
    ],
    "wof:name":"Gillette Roofing & Siding",
    "wof:placetype":"venue"
},
  "geometry": {"coordinates":[-83.72981799999999,41.608983],"type":"Point"}
}