{
  "type": "Feature",
  "properties": {
    "addr:full": "3040 Riverside Dr Columbus OH 43221",
    "addr:housenumber": "3040",
    "addr:postcode": "43221",
    "addr:street": "Riverside Dr",
    "iso:country": "US",
    "sg:address": "3040 Riverside Dr",
    "sg:city": "Columbus",
    "sg:classifiers": [
      {
        "category": "Insurance",
        "subcategory": "Insurance Agent",
        "type": "Services"
      },
      {
        "category": "Insurance",
        "subcategory": "Hazard Insurance",
        "type": "Services"
      },
      {
        "category": "Insurance",
        "subcategory": "Title Insurance",
        "type": "Services"
      }
    ],
    "sg:phone": "+1 614 488 9445",
    "sg:postcode": "43221",
    "sg:province": "OH",
    "sg:tags": [
      "auto",
      "homeowner"
    ],
    "sg:website": "http://apps.amfam.com/agentlocator/LDIEMER?sourceid=yp3",
    "wof:name": "American Family Insurance- Lisa Diemer",
    "wof:placetype": "venue"
  },
  "geometry": {"coordinates":[-83.090724,40.015479],"type":"Point"}
}
