{
  "type": "Feature",
  "properties": {
    "addr:full": "18620 Rd 7-Q Columbus Grove OH 45830",
    "addr:housenumber": "18620",
    "addr:postcode": "45830",
    "addr:street": "Rd;Columbus Grove",
    "iso:country": "US",
    "sg:address": "18620 Rd 7-Q",
    "sg:city": "Columbus Grove",
    "sg:phone": "+1 419 659 5514",
    "sg:postcode": "45830",
    "sg:province": "OH",
    "sg:tags": [
      "farm",
      "wheat",
      "soybean"
    ],
    "wof:name": "Richard Hitchcock",
    "wof:placetype": "venue"
  },
  "geometry": {"coordinates":[-84.004833,40.910514],"type":"Point"}
}
