{
  "type": "Feature",
  "properties": {
    "addr:full": "2744 E Kemper Rd Cincinnati OH 45241",
    "addr:housenumber": "2744",
    "addr:postcode": "45241",
    "addr:street": "E Kemper Rd",
    "iso:country": "US",
    "sg:address": "2744 E Kemper Rd",
    "sg:city": "Cincinnati",
    "sg:classifiers": [
      {
        "category": "Shopping",
        "type": "Retail Goods"
      }
    ],
    "sg:phone": "+1 513 325 0600",
    "sg:postcode": "45241",
    "sg:province": "OH",
    "sg:tags": [
      "chemical"
    ],
    "wof:name": "Pilot Chemical",
    "wof:placetype": "venue"
  },
  "geometry": {"coordinates":[-84.423899,39.283911],"type":"Point"}
}
