{
  "type": "Feature",
  "properties": {
    "addr:full": "7757 State Rte 73 Hillsboro OH 45133",
    "addr:housenumber": "7757",
    "addr:postcode": "45133",
    "addr:street": "State Rte 73",
    "iso:country": "US",
    "sg:address": "7757 State Rte 73",
    "sg:city": "Hillsboro",
    "sg:classifiers": [
      {
        "category": "Building \u0026 Trades",
        "subcategory": "Construction",
        "type": "Services"
      }
    ],
    "sg:phone": "+1 937 393 3139",
    "sg:postcode": "45133",
    "sg:province": "OH",
    "sg:tags": [
      "modular",
      "home"
    ],
    "wof:name": "Blair Homes Inc",
    "wof:placetype": "venue"
  },
  "geometry": {"coordinates":[-83.622859,39.223313],"type":"Point"}
}
