{
  "type": "Feature",
  "properties": {
    "iso:country":"US",
    "sg:address":"1709 Victoria Rd",
    "sg:city":"Cleveland",
    "sg:classifiers":[
        {
            "category":"Building & Trades",
            "subcategory":"Landscaping Services",
            "type":"Services"
        }
    ],
    "sg:phone":"+1 216 692 3530",
    "sg:postcode":"44112",
    "sg:province":"OH",
    "sg:tags":[
        "landscape",
        "contractor"
    ],
    "wof:name":"Rinaldi Landscape Co Inc",
    "wof:placetype":"venue"
},
  "geometry": {"coordinates":[-81.563624,41.547938],"type":"Point"}
}