{
  "type": "Feature",
  "properties": {
    "iso:country":"US",
    "sg:address":"3829 Woodley Rd",
    "sg:city":"Toledo",
    "sg:classifiers":[
        {
            "category":"Health Services",
            "subcategory":"Doctor",
            "type":"Services"
        }
    ],
    "sg:phone":"+1 419 474 9324",
    "sg:postcode":"43606",
    "sg:province":"OH",
    "sg:tags":[
        "physician",
        "surgeon"
    ],
    "wof:name":"Vincent Toma MD",
    "wof:placetype":"venue"
},
  "geometry": {"coordinates":[-83.635895,41.691221],"type":"Point"}
}