{
  "type": "Feature",
  "properties": {
    "iso:country":"US",
    "sg:address":"7021 Cleves Warsaw Pike",
    "sg:city":"Cincinnati",
    "sg:classifiers":[
        {
            "category":"Professional",
            "subcategory":"Business Services",
            "type":"Services"
        }
    ],
    "sg:phone":"+1 513 941 4500",
    "sg:postcode":"45233",
    "sg:province":"OH",
    "sg:tags":[
        "environmental",
        "ecological",
        "product"
    ],
    "sg:website":"http://www.tepeservices.com",
    "wof:name":"Tepe Environmental Svc Ltd",
    "wof:placetype":"venue"
},
  "geometry": {"coordinates":[-84.678905,39.123656],"type":"Point"}
}