{
  "type": "Feature",
  "properties": {
    "addr:full": "202 South St Republic OH 44867",
    "addr:housenumber": "202",
    "addr:postcode": "44867",
    "addr:street": "South St",
    "iso:country": "US",
    "sg:address": "202 South St",
    "sg:city": "Republic",
    "sg:classifiers": [
      {
        "category": "Professional",
        "type": "Services"
      }
    ],
    "sg:phone": "+1 419 585 3601",
    "sg:postcode": "44867",
    "sg:province": "OH",
    "wof:name": "Russell S Hays and Mary P Ha",
    "wof:placetype": "venue"
  },
  "geometry": {"coordinates":[-83.017108,41.119609],"type":"Point"}
}
