{
  "type": "Feature",
  "properties": {
    "iso:country":"US",
    "sg:address":"8868 Garland St",
    "sg:city":"Franklin",
    "sg:classifiers":[
        {
            "category":"Building & Trades",
            "subcategory":"Construction",
            "type":"Services"
        }
    ],
    "sg:phone":"+1 937 746 2827",
    "sg:postcode":"45005",
    "sg:province":"OH",
    "sg:tags":[
        "hanging",
        "contractor"
    ],
    "wof:name":"Freedom Painting Co",
    "wof:placetype":"venue"
},
  "geometry": {"coordinates":[-84.300274,39.58316],"type":"Point"}
}