{
  "type": "Feature",
  "properties": {
    "addr:full":"784 Boardman Canfield Rd Youngstown OH 44512",
    "addr:housenumber":"784",
    "addr:postcode":"44512",
    "addr:street":"Boardman Canfield Rd",
    "iso:country":"US",
    "sg:address":"784 Boardman Canfield Rd",
    "sg:city":"Youngstown",
    "sg:classifiers":[
        {
            "category":"Insurance",
            "subcategory":"Insurance Agent",
            "type":"Services"
        }
    ],
    "sg:phone":"+1 330 965 1226",
    "sg:postcode":"44512",
    "sg:province":"OH",
    "wof:name":"Douglas Conn Insurance Inc",
    "wof:placetype":"venue"
},
  "geometry": {"coordinates":[-80.683018,41.024579],"type":"Point"}
}