{
  "type": "Feature",
  "properties": {
    "addr:full": "175 W Market St Akron OH 44303",
    "addr:housenumber": "175",
    "addr:postcode": "44303",
    "addr:street": "W Market St",
    "iso:country": "US",
    "sg:address": "175 W Market St",
    "sg:city": "Akron",
    "sg:classifiers": [
      {
        "category": "Retail",
        "subcategory": "Auto Repair",
        "type": "Services"
      }
    ],
    "sg:phone": "+1 330 253 1808",
    "sg:postcode": "44303",
    "sg:province": "OH",
    "sg:tags": [
      "repairing",
      "automobile"
    ],
    "wof:name": "Dominic's Automotive Svc",
    "wof:placetype": "venue"
  },
  "geometry": {"coordinates":[-81.522503,41.087755],"type":"Point"}
}
