{
  "type": "Feature",
  "properties": {
    "iso:country":"US",
    "sg:address":"314 N Dixie Dr",
    "sg:city":"Vandalia",
    "sg:classifiers":[
        {
            "category":"Shopping",
            "type":"Retail Goods"
        }
    ],
    "sg:phone":"+1 937 890 5811",
    "sg:postcode":"45377",
    "sg:province":"OH",
    "sg:tags":[
        "trophy",
        "medal",
        "award"
    ],
    "wof:name":"Gauntlet Awards & Engraving",
    "wof:placetype":"venue"
},
  "geometry": {"coordinates":[-84.198505,39.897134],"type":"Point"}
}