{
  "type": "Feature",
  "properties": {
    "iso:country":"US",
    "sg:address":"2650 University Blvd",
    "sg:city":"Cleveland",
    "sg:classifiers":[
        {
            "category":"Professional",
            "type":"Services"
        }
    ],
    "sg:phone":"+1 216 321 7326",
    "sg:postcode":"44118",
    "sg:province":"OH",
    "wof:name":"Cyber Gate",
    "wof:placetype":"venue"
},
  "geometry": {"coordinates":[-81.538131,41.487735],"type":"Point"}
}