{
  "type": "Feature",
  "properties": {
    "addr:full": "330 Imperial Dr Columbus OH 43230",
    "addr:housenumber": "330",
    "addr:postcode": "43230",
    "addr:street": "Imperial Dr",
    "iso:country": "US",
    "sg:address": "330 Imperial Dr",
    "sg:city": "Columbus",
    "sg:classifiers": [
      {
        "category": "Building \u0026 Trades",
        "subcategory": "Construction",
        "type": "Services"
      }
    ],
    "sg:phone": "+1 614 471 3610",
    "sg:postcode": "43230",
    "sg:province": "OH",
    "sg:tags": [
      "house"
    ],
    "wof:name": "Hays Builders",
    "wof:placetype": "venue"
  },
  "geometry": {"coordinates":[-82.89401,40.027403],"type":"Point"}
}
