{
  "type": "Feature",
  "properties": {
    "addr:full":"1252 Youngstown Warren Rd Niles OH 44446",
    "addr:housenumber":"1252",
    "addr:postcode":"44446",
    "addr:street":"Youngstown Warren Rd",
    "iso:country":"US",
    "sg:address":"1252 Youngstown Warren Rd",
    "sg:city":"Niles",
    "sg:classifiers":[
        {
            "category":"Health Services",
            "subcategory":"Doctor",
            "type":"Services"
        }
    ],
    "sg:phone":"+1 330 544 3724",
    "sg:postcode":"44446",
    "sg:province":"OH",
    "sg:tags":[
        "physician",
        "surgeon"
    ],
    "wof:name":"Alloush Nabil MD",
    "wof:placetype":"venue"
},
  "geometry": {"coordinates":[-80.73760799999999,41.203474],"type":"Point"}
}