{
  "type": "Feature",
  "properties": {
    "iso:country":"US",
    "sg:address":"1252 Youngstown Warren Rd",
    "sg:city":"Niles",
    "sg:classifiers":[
        {
            "category":"Health Services",
            "subcategory":"Doctor",
            "type":"Services"
        }
    ],
    "sg:phone":"+1 330 544 3724",
    "sg:postcode":"44446",
    "sg:province":"OH",
    "sg:tags":[
        "physician",
        "surgeon"
    ],
    "wof:name":"Alloush Nabil MD",
    "wof:placetype":"venue"
},
  "geometry": {"coordinates":[-80.737608,41.203474],"type":"Point"}
}