{
  "type": "Feature",
  "properties": {
    "addr:full": "2724 E 55th St Cleveland OH 44104",
    "addr:housenumber": "2724",
    "addr:postcode": "44104",
    "addr:street": "E 55Th St",
    "iso:country": "US",
    "sg:address": "2724 E 55th St",
    "sg:city": "Cleveland",
    "sg:classifiers": [
      {
        "category": "Retail",
        "subcategory": "Auto Repair",
        "type": "Services"
      }
    ],
    "sg:phone": "+1 330 963 4464",
    "sg:postcode": "44104",
    "sg:province": "OH",
    "sg:tags": [
      "automotive"
    ],
    "wof:name": "Envirotest Systems Corp",
    "wof:placetype": "venue"
  },
  "geometry": {"coordinates":[-81.651624,41.484371],"type":"Point"}
}
