{
  "type": "Feature",
  "properties": {
    "iso:country":"US",
    "sg:address":"2724 E 55th St",
    "sg:city":"Cleveland",
    "sg:classifiers":[
        {
            "category":"Retail",
            "subcategory":"Auto Repair",
            "type":"Services"
        }
    ],
    "sg:phone":"+1 330 963 4464",
    "sg:postcode":"44104",
    "sg:province":"OH",
    "sg:tags":[
        "automotive"
    ],
    "wof:name":"Envirotest Systems Corp",
    "wof:placetype":"venue"
},
  "geometry": {"coordinates":[-81.651624,41.484371],"type":"Point"}
}