{
  "type": "Feature",
  "properties": {
    "iso:country":"US",
    "sg:address":"5583 Ridge Ave",
    "sg:city":"Cincinnati",
    "sg:classifiers":[
        {
            "category":"Real Estate",
            "subcategory":"Real Estate Agent",
            "type":"Services"
        }
    ],
    "sg:phone":"+1 513 631 5873",
    "sg:postcode":"45213",
    "sg:province":"OH",
    "sg:tags":[
        "management"
    ],
    "wof:name":"Ridge Management Co",
    "wof:placetype":"venue"
},
  "geometry": {"coordinates":[-84.426787,39.171602],"type":"Point"}
}