{
  "type": "Feature",
  "properties": {
    "iso:country":"US",
    "sg:address":"1080 Elmwood St",
    "sg:city":"East Liverpool",
    "sg:classifiers":[
        {
            "category":"Home & Garden",
            "subcategory":"Garden Supply",
            "type":"Retail Goods"
        }
    ],
    "sg:phone":"+1 330 386 7625",
    "sg:postcode":"43920",
    "sg:province":"OH",
    "sg:tags":[
        "fertilizer"
    ],
    "wof:name":"Royster-Clark Inc",
    "wof:placetype":"venue"
},
  "geometry": {"coordinates":[-80.55385200000001,40.631926],"type":"Point"}
}