{
  "type": "Feature",
  "properties": {
    "addr:full": "1080 Elmwood St East Liverpool OH 43920",
    "addr:housenumber": "1080",
    "addr:postcode": "43920",
    "addr:street": "Elmwood St",
    "iso:country": "US",
    "sg:address": "1080 Elmwood St",
    "sg:city": "East Liverpool",
    "sg:classifiers": [
      {
        "category": "Home \u0026 Garden",
        "subcategory": "Garden Supply",
        "type": "Retail Goods"
      }
    ],
    "sg:phone": "+1 330 386 7625",
    "sg:postcode": "43920",
    "sg:province": "OH",
    "sg:tags": [
      "fertilizer"
    ],
    "wof:name": "Royster-Clark Inc",
    "wof:placetype": "venue"
  },
  "geometry": {"coordinates":[-80.553852,40.631926],"type":"Point"}
}
