{
  "type": "Feature",
  "properties": {
    "iso:country":"US",
    "sg:address":"4099 Brookside Dr",
    "sg:city":"Warren",
    "sg:classifiers":[
        {
            "category":"Organizations",
            "subcategory":"Religious Organization",
            "type":"Services"
        }
    ],
    "sg:phone":"+1 330 847 7596",
    "sg:postcode":"44483",
    "sg:province":"OH",
    "sg:tags":[
        "clergy"
    ],
    "wof:name":"Grady Williams",
    "wof:placetype":"venue"
},
  "geometry": {"coordinates":[-80.835853,41.274984],"type":"Point"}
}