{
  "type": "Feature",
  "properties": {
    "addr:full": "1096 Ambridge Rd Dayton OH 45459",
    "addr:housenumber": "1096",
    "addr:postcode": "45459",
    "addr:street": "Ambridge Rd",
    "iso:country": "US",
    "sg:address": "1096 Ambridge Rd",
    "sg:city": "Dayton",
    "sg:classifiers": [
      {
        "category": "Organizations",
        "subcategory": "Religious Organization",
        "type": "Services"
      }
    ],
    "sg:phone": "+1 937 439 9919",
    "sg:postcode": "45459",
    "sg:province": "OH",
    "sg:tags": [
      "clergy"
    ],
    "wof:name": "Stephan E Becker",
    "wof:placetype": "venue"
  },
  "geometry": {"coordinates":[-84.138165,39.641594],"type":"Point"}
}
