{
  "type": "Feature",
  "properties": {
    "iso:country":"US",
    "sg:address":"6100 Executive Blvd",
    "sg:city":"Dayton",
    "sg:classifiers":[
        {
            "category":"Wholesale",
            "subcategory":"Chemicals & Plastics",
            "type":"Manufacturing & Wholesale Goods"
        }
    ],
    "sg:phone":"+1 937 237 8520",
    "sg:postcode":"45424",
    "sg:province":"OH",
    "sg:tags":[
        "product",
        "mfg"
    ],
    "wof:name":"Meyer Plastics Inc",
    "wof:placetype":"venue"
},
  "geometry": {"coordinates":[-84.113438,39.870588],"type":"Point"}
}