{
  "type": "Feature",
  "properties": {
    "addr:full": "6239 Germantown Rd Middletown OH 45042",
    "addr:housenumber": "6239",
    "addr:postcode": "45042",
    "addr:street": "Germantown Rd",
    "iso:country": "US",
    "sg:address": "6239 Germantown Rd",
    "sg:city": "Middletown",
    "sg:classifiers": [
      {
        "category": "Autos \u0026 Motor Vehicles",
        "subcategory": "Automobile Sales",
        "type": "Retail Goods"
      }
    ],
    "sg:phone": "+1 513 422 2500",
    "sg:postcode": "45042",
    "sg:province": "OH",
    "sg:tags": [
      "car",
      "used",
      "dealer"
    ],
    "sg:website": "www.scorechryslerdodge.com",
    "wof:name": "Score Chrysler Plymouth Dodge",
    "wof:placetype": "venue"
  },
  "geometry": {"coordinates":[-84.383454,39.545313],"type":"Point"}
}
