{
  "type": "Feature",
  "properties": {
    "addr:full":"1693 Salem Pkwy W Salem OH 44460",
    "addr:housenumber":"1693",
    "addr:postcode":"44460",
    "addr:street":"Salem Pkwy W",
    "iso:country":"US",
    "sg:address":"1693 Salem Pkwy W",
    "sg:city":"Salem",
    "sg:classifiers":[
        {
            "category":"Manufacturing",
            "subcategory":"Metals",
            "type":"Manufacturing & Wholesale Goods"
        }
    ],
    "sg:phone":"+1 330 332 9500",
    "sg:postcode":"44460",
    "sg:province":"OH",
    "sg:tags":[
        "hardware",
        "decorative",
        "brass"
    ],
    "sg:website":"www.brassaccents.com",
    "wof:name":"Brass Accents Inc",
    "wof:placetype":"venue"
},
  "geometry": {"coordinates":[-80.88176799999999,40.917737],"type":"Point"}
}