{
  "type": "Feature",
  "properties": {
    "addr:full":"5203 Monroe St Toledo OH 43606",
    "addr:housenumber":"5203",
    "addr:postcode":"43606",
    "addr:street":"Monroe St",
    "iso:country":"US",
    "sg:address":"5203 Monroe St",
    "sg:city":"Toledo",
    "sg:classifiers":[
        {
            "category":"Home & Garden",
            "subcategory":"Home Furnishings",
            "type":"Retail Goods"
        }
    ],
    "sg:phone":"+1 419 882 3581",
    "sg:postcode":"43606",
    "sg:province":"OH",
    "wof:name":"Pier 1",
    "wof:placetype":"venue"
},
  "geometry": {"coordinates":[-83.65136800000001,41.700891],"type":"Point"}
}