{
  "type": "Feature",
  "properties": {
    "addr:full": "86 Shawondassee Dr Willoughby OH 44095",
    "addr:housenumber": "86",
    "addr:postcode": "44095",
    "addr:street": "Shawondassee Dr",
    "iso:country": "US",
    "sg:address": "86 Shawondassee Dr",
    "sg:city": "Willoughby",
    "sg:classifiers": [
      {
        "category": "Building \u0026 Trades",
        "subcategory": "Construction",
        "type": "Services"
      }
    ],
    "sg:phone": "+1 440 946 3697",
    "sg:postcode": "44095",
    "sg:province": "OH",
    "sg:tags": [
      "repairing",
      "remodeling",
      "contractor"
    ],
    "wof:name": "Ameracraft Builders",
    "wof:placetype": "venue"
  },
  "geometry": {"coordinates":[-81.438581,41.66459],"type":"Point"}
}
