{
  "type": "Feature",
  "properties": {
    "addr:full": "5650 New Vienna Rd New Vienna OH 45159",
    "addr:housenumber": "5650",
    "addr:postcode": "45159",
    "addr:street": "New Vienna Rd",
    "iso:country": "US",
    "sg:address": "5650 New Vienna Rd",
    "sg:city": "New Vienna",
    "sg:phone": "+1 937 987 2596",
    "sg:postcode": "45159",
    "sg:province": "OH",
    "sg:tags": [
      "farm",
      "corn",
      "wheat",
      "soybean"
    ],
    "wof:name": "Donald McKamey",
    "wof:placetype": "venue"
  },
  "geometry": {"coordinates":[-83.677522,39.319422],"type":"Point"}
}
