{
  "type": "Feature",
  "properties": {
    "iso:country":"US",
    "sg:address":"1 S Cleveland Ave",
    "sg:city":"Mogadore",
    "sg:classifiers":[
        {
            "category":"Education",
            "subcategory":"School",
            "type":"Public Place"
        }
    ],
    "sg:phone":"+1 330 628 9946",
    "sg:postcode":"44260",
    "sg:province":"OH",
    "sg:website":"www.mogadore.summit.k12.oh.us",
    "wof:name":"Mogadore Local School District",
    "wof:placetype":"venue"
},
  "geometry": {"coordinates":[-81.39313199999999,41.048873],"type":"Point"}
}