{
  "type": "Feature",
  "properties": {
    "iso:country":"US",
    "sg:address":"116 E 2nd St",
    "sg:city":"Port Clinton",
    "sg:classifiers":[
        {
            "category":"Restaurant",
            "type":"Food & Drink"
        }
    ],
    "sg:phone":"+1 419 734 3118",
    "sg:postcode":"43452",
    "sg:province":"OH",
    "sg:tags":[
        "eating"
    ],
    "wof:name":"Underwood's Fine Foods",
    "wof:placetype":"venue"
},
  "geometry": {"coordinates":[-82.940909,41.511852],"type":"Point"}
}