{
  "type": "Feature",
  "properties": {
    "addr:full":"1286 N Hague Ave Columbus OH 43204",
    "addr:housenumber":"1286",
    "addr:postcode":"43204",
    "addr:street":"N Hague Ave",
    "iso:country":"US",
    "sg:address":"1286 N Hague Ave",
    "sg:city":"Columbus",
    "sg:phone":"+1 614 274 7861",
    "sg:postcode":"43204",
    "sg:province":"OH",
    "sg:tags":[
        "grain",
        "cash"
    ],
    "wof:name":"Dematteo Farms",
    "wof:placetype":"venue"
},
  "geometry": {"coordinates":[-83.085571,39.980235],"type":"Point"}
}