{
  "type": "Feature",
  "properties": {
    "iso:country":"US",
    "sg:address":"730 Riddle Rd",
    "sg:city":"Cincinnati",
    "sg:classifiers":[
        {
            "category":"Professional",
            "subcategory":"Research",
            "type":"Services"
        }
    ],
    "sg:phone":"+1 513 961 1999",
    "sg:postcode":"45220",
    "sg:province":"OH",
    "sg:tags":[
        "market",
        "analysis"
    ],
    "wof:name":"T M Smith & Assoc",
    "wof:placetype":"venue"
},
  "geometry": {"coordinates":[-84.52986199999999,39.137237],"type":"Point"}
}