{
  "type": "Feature",
  "properties": {
    "addr:full": "7979 Red Bank Rd Westerville OH 43082",
    "addr:housenumber": "7979",
    "addr:postcode": "43082",
    "addr:street": "Red Bank Rd",
    "iso:country": "US",
    "sg:address": "7979 Red Bank Rd",
    "sg:city": "Westerville",
    "sg:classifiers": [
      {
        "category": "Building \u0026 Trades",
        "subcategory": "Construction",
        "type": "Services"
      }
    ],
    "sg:phone": "+1 614 891 8876",
    "sg:postcode": "43082",
    "sg:province": "OH",
    "sg:tags": [
      "home",
      "contractor"
    ],
    "wof:name": "Dan Rako Builders Inc",
    "wof:placetype": "venue"
  },
  "geometry": {"coordinates":[-82.858111,40.13021],"type":"Point"}
}
