{
  "type": "Feature",
  "properties": {
    "iso:country":"US",
    "sg:address":"2939 Cincinnati Dayton Rd",
    "sg:city":"Middletown",
    "sg:classifiers":[
        {
            "category":"Autos & Motor Vehicles",
            "subcategory":"Automobile Sales",
            "type":"Retail Goods"
        }
    ],
    "sg:phone":"+1 513 423 4055",
    "sg:postcode":"45044",
    "sg:province":"OH",
    "sg:tags":[
        "car",
        "dealer"
    ],
    "wof:name":"Speedway Motors",
    "wof:placetype":"venue"
},
  "geometry": {"coordinates":[-84.341302,39.479832],"type":"Point"}
}