{
  "type": "Feature",
  "properties": {
    "addr:full":"5861 Cinema Dr Milford OH 45150",
    "addr:housenumber":"5861",
    "addr:postcode":"45150",
    "addr:street":"Cinema Dr",
    "iso:country":"US",
    "sg:address":"5861 Cinema Dr",
    "sg:city":"Milford",
    "sg:classifiers":[
        {
            "category":"Health Services",
            "subcategory":"Doctor",
            "type":"Services"
        }
    ],
    "sg:phone":"+1 513 794 5600",
    "sg:postcode":"45150",
    "sg:province":"OH",
    "sg:tags":[
        "physician",
        "surgeon"
    ],
    "wof:name":"Gastroenterology Consultants",
    "wof:placetype":"venue"
},
  "geometry": {"coordinates":[-84.254351,39.192248],"type":"Point"}
}