{
  "type": "Feature",
  "properties": {
    "addr:full":"5588 Wedgewood Rd Medina OH 44256",
    "addr:housenumber":"5588",
    "addr:postcode":"44256",
    "addr:street":"Wedgewood Rd",
    "iso:country":"US",
    "sg:address":"5588 Wedgewood Rd",
    "sg:city":"Medina",
    "sg:classifiers":[
        {
            "category":"Recreation",
            "type":"Entertainment"
        },
        {
            "category":"Organizations",
            "subcategory":"Community Association",
            "type":"Services"
        }
    ],
    "sg:phone":"+1 330 225 0677",
    "sg:postcode":"44256",
    "sg:province":"OH",
    "sg:tags":[
        "club",
        "country",
        "golf",
        "course"
    ],
    "wof:name":"Medina Country Club Ltd",
    "wof:placetype":"venue"
},
  "geometry": {"coordinates":[-81.88943,41.099255],"type":"Point"}
}