{
  "type": "Feature",
  "properties": {
    "iso:country":"US",
    "sg:address":"904 W Champlin Rd",
    "sg:city":"Wilmington",
    "sg:classifiers":[
        {
            "category":"Building & Trades",
            "subcategory":"Construction",
            "type":"Services"
        }
    ],
    "sg:phone":"+1 937 434 6029",
    "sg:postcode":"45177",
    "sg:province":"OH",
    "sg:tags":[
        "contractor"
    ],
    "wof:name":"Brooks Custom Paver Tech Inc",
    "wof:placetype":"venue"
},
  "geometry": {"coordinates":[-83.865807,39.388022],"type":"Point"}
}