{
  "type": "Feature",
  "properties": {
    "addr:full": "103 Steuben St Brilliant OH 43913",
    "addr:housenumber": "103",
    "addr:postcode": "43913",
    "addr:street": "Steuben St",
    "iso:country": "US",
    "sg:address": "103 Steuben St",
    "sg:city": "Brilliant",
    "sg:classifiers": [
      {
        "category": "Education",
        "subcategory": "Library",
        "type": "Public Place"
      }
    ],
    "sg:phone": "+1 740 598 4028",
    "sg:postcode": "43913",
    "sg:province": "OH",
    "sg:tags": [
      "executive"
    ],
    "wof:name": "Brilliant Branch Library",
    "wof:placetype": "venue"
  },
  "geometry": {"coordinates":[-80.626919,40.264952],"type":"Point"}
}
