{
  "type": "Feature",
  "properties": {
    "addr:full":"1147 State Rte 589 Sidney OH 45365",
    "addr:housenumber":"1147",
    "addr:postcode":"45365",
    "addr:street":"State Rte 589",
    "iso:country":"US",
    "sg:address":"1147 State Rte 589",
    "sg:city":"Sidney",
    "sg:classifiers":[
        {
            "category":"Farming",
            "subcategory":"Farm",
            "type":"Manufacturing & Wholesale Goods"
        }
    ],
    "sg:phone":"+1 937 498 4413",
    "sg:postcode":"45365",
    "sg:province":"OH",
    "sg:tags":[
        "crop",
        "general"
    ],
    "wof:name":"Bill Hageman",
    "wof:placetype":"venue"
},
  "geometry": {"coordinates":[-84.05977900000001,40.202311],"type":"Point"}
}