{
  "type": "Feature",
  "properties": {
    "addr:full":"1005 N Shoop Ave Wauseon OH 43567",
    "addr:housenumber":"1005",
    "addr:postcode":"43567",
    "addr:street":"N Shoop Ave",
    "iso:country":"US",
    "sg:address":"1005 N Shoop Ave",
    "sg:city":"Wauseon",
    "sg:classifiers":[
        {
            "category":"Retail",
            "subcategory":"Auto Repair",
            "type":"Services"
        }
    ],
    "sg:phone":"+1 419 335 9111",
    "sg:postcode":"43567",
    "sg:province":"OH",
    "sg:tags":[
        "repairing",
        "automobile"
    ],
    "wof:name":"Kolb Auto Repair",
    "wof:placetype":"venue"
},
  "geometry": {"coordinates":[-84.134539,41.560356],"type":"Point"}
}