{
  "type": "Feature",
  "properties": {
    "addr:full":"11377 Montgomery Rd Cincinnati OH 45249",
    "addr:housenumber":"11377",
    "addr:postcode":"45249",
    "addr:street":"Montgomery Rd",
    "iso:country":"US",
    "sg:address":"11377 Montgomery Rd",
    "sg:city":"Cincinnati",
    "sg:classifiers":[
        {
            "category":"Building & Trades",
            "subcategory":"Construction",
            "type":"Services"
        }
    ],
    "sg:phone":"+1 513 842 5516",
    "sg:postcode":"45249",
    "sg:province":"OH",
    "sg:tags":[
        "bathroom",
        "remodeling"
    ],
    "wof:name":"City-Wide Kitchens & Baths",
    "wof:placetype":"venue"
},
  "geometry": {"coordinates":[-84.328433,39.270706],"type":"Point"}
}