{
  "type": "Feature",
  "properties": {
    "iso:country":"US",
    "sg:address":"1016 Patricia Dr",
    "sg:city":"Girard",
    "sg:classifiers":[
        {
            "category":"Building & Trades",
            "subcategory":"Construction",
            "type":"Services"
        }
    ],
    "sg:phone":"+1 330 544 0405",
    "sg:postcode":"44420",
    "sg:province":"OH",
    "sg:tags":[
        "carpentry",
        "contractor"
    ],
    "wof:name":"Watson Carpentry",
    "wof:placetype":"venue"
},
  "geometry": {"coordinates":[-80.68437400000001,41.167542],"type":"Point"}
}