{
  "type": "Feature",
  "properties": {
    "addr:full": "1016 Patricia Dr Girard OH 44420",
    "addr:housenumber": "1016",
    "addr:postcode": "44420",
    "addr:street": "Patricia Dr",
    "iso:country": "US",
    "sg:address": "1016 Patricia Dr",
    "sg:city": "Girard",
    "sg:classifiers": [
      {
        "category": "Building \u0026 Trades",
        "subcategory": "Construction",
        "type": "Services"
      }
    ],
    "sg:phone": "+1 330 544 0405",
    "sg:postcode": "44420",
    "sg:province": "OH",
    "sg:tags": [
      "carpentry",
      "contractor"
    ],
    "wof:name": "Watson Carpentry",
    "wof:placetype": "venue"
  },
  "geometry": {"coordinates":[-80.684374,41.167542],"type":"Point"}
}
