{
  "type": "Feature",
  "properties": {
    "addr:full":"26410 Detroit Rd Cleveland OH 44145",
    "addr:housenumber":"26410",
    "addr:postcode":"44145",
    "addr:street":"Detroit Rd",
    "iso:country":"US",
    "sg:address":"26410 Detroit Rd",
    "sg:city":"Cleveland",
    "sg:classifiers":[
        {
            "category":"Wholesale",
            "subcategory":"Durable Goods & Equipment",
            "type":"Manufacturing & Wholesale Goods"
        }
    ],
    "sg:phone":"+1 440 250 3400",
    "sg:postcode":"44145",
    "sg:province":"OH",
    "sg:tags":[
        "representative",
        "manufacturer"
    ],
    "wof:name":"Loesch Associates Inc",
    "wof:placetype":"venue"
},
  "geometry": {"coordinates":[-81.913319,41.468711],"type":"Point"}
}