{
  "type": "Feature",
  "properties": {
    "addr:full": "4701 Beacon Hill Rd Columbus OH 43228",
    "addr:housenumber": "4701",
    "addr:postcode": "43228",
    "addr:street": "Beacon Hill Rd",
    "iso:country": "US",
    "sg:address": "4701 Beacon Hill Rd",
    "sg:city": "Columbus",
    "sg:classifiers": [
      {
        "category": "Real Estate",
        "subcategory": "Real Estate Operator",
        "type": "Services"
      }
    ],
    "sg:phone": "+1 614 870 1050",
    "sg:postcode": "43228",
    "sg:province": "OH",
    "sg:tags": [
      "condominium"
    ],
    "wof:name": "Glenford Village Condominium",
    "wof:placetype": "venue"
  },
  "geometry": {"coordinates":[-83.125152,39.956123],"type":"Point"}
}
