{
  "type": "Feature",
  "properties": {
    "addr:full": "1020 Estill Dr Lakewood OH 44107",
    "addr:housenumber": "1020",
    "addr:postcode": "44107",
    "addr:street": "Estill Dr",
    "iso:country": "US",
    "sg:address": "1020 Estill Dr",
    "sg:city": "Lakewood",
    "sg:classifiers": [
      {
        "category": "Building \u0026 Trades",
        "subcategory": "Construction",
        "type": "Services"
      }
    ],
    "sg:phone": "+1 216 789 7896",
    "sg:postcode": "44107",
    "sg:province": "OH",
    "sg:tags": [
      "house"
    ],
    "wof:name": "MJ Matousek Inc",
    "wof:placetype": "venue"
  },
  "geometry": {"coordinates":[-81.793551,41.494117],"type":"Point"}
}
