{
  "type": "Feature",
  "properties": {
    "iso:country":"US",
    "sg:address":"1020 Estill Dr",
    "sg:city":"Lakewood",
    "sg:classifiers":[
        {
            "category":"Building & Trades",
            "subcategory":"Construction",
            "type":"Services"
        }
    ],
    "sg:phone":"+1 216 789 7896",
    "sg:postcode":"44107",
    "sg:province":"OH",
    "sg:tags":[
        "house"
    ],
    "wof:name":"MJ Matousek Inc",
    "wof:placetype":"venue"
},
  "geometry": {"coordinates":[-81.79355099999999,41.494117],"type":"Point"}
}