{
  "type": "Feature",
  "properties": {
    "iso:country":"US",
    "sg:address":"15233 Green Rd",
    "sg:city":"Wakeman",
    "sg:classifiers":[
        {
            "category":"Farming",
            "subcategory":"Farm & Veterinary Services",
            "type":"Manufacturing & Wholesale Goods"
        }
    ],
    "sg:phone":"+1 440 839 2735",
    "sg:postcode":"44889",
    "sg:province":"OH",
    "sg:tags":[
        "livestock"
    ],
    "wof:name":"Lee Tansey",
    "wof:placetype":"venue"
},
  "geometry": {"coordinates":[-82.34159200000001,41.2574],"type":"Point"}
}