{
  "type": "Feature",
  "properties": {
    "addr:full": "15233 Green Rd Wakeman OH 44889",
    "addr:housenumber": "15233",
    "addr:postcode": "44889",
    "addr:street": "Green Rd",
    "iso:country": "US",
    "sg:address": "15233 Green Rd",
    "sg:city": "Wakeman",
    "sg:classifiers": [
      {
        "category": "Farming",
        "subcategory": "Farm \u0026 Veterinary Services",
        "type": "Manufacturing \u0026 Wholesale Goods"
      }
    ],
    "sg:phone": "+1 440 839 2735",
    "sg:postcode": "44889",
    "sg:province": "OH",
    "sg:tags": [
      "livestock"
    ],
    "wof:name": "Lee Tansey",
    "wof:placetype": "venue"
  },
  "geometry": {"coordinates":[-82.341592,41.2574],"type":"Point"}
}
