{
  "type": "Feature",
  "properties": {
    "addr:full":"645 Carey St Zanesville OH 43701",
    "addr:housenumber":"645",
    "addr:postcode":"43701",
    "addr:street":"Carey St",
    "iso:country":"US",
    "sg:address":"645 Carey St",
    "sg:city":"Zanesville",
    "sg:classifiers":[
        {
            "category":"Organizations",
            "subcategory":"Community Association",
            "type":"Services"
        }
    ],
    "sg:phone":"+1 740 452 1592",
    "sg:postcode":"43701",
    "sg:province":"OH",
    "sg:tags":[
        "fraternal"
    ],
    "wof:name":"Golden Rule Lodge",
    "wof:placetype":"venue"
},
  "geometry": {"coordinates":[-82.01477800000001,39.928757],"type":"Point"}
}