{
  "type": "Feature",
  "properties": {
    "addr:full":"2284 E Main St Columbus OH 43209",
    "addr:housenumber":"2284",
    "addr:postcode":"43209",
    "addr:street":"E Main St",
    "iso:country":"US",
    "sg:address":"2284 E Main St",
    "sg:city":"Columbus",
    "sg:classifiers":[
        {
            "category":"Insurance",
            "subcategory":"Insurance Agent",
            "type":"Services"
        }
    ],
    "sg:phone":"+1 614 884 2314",
    "sg:postcode":"43209",
    "sg:province":"OH",
    "wof:name":"State Farm Insurance",
    "wof:placetype":"venue"
},
  "geometry": {"coordinates":[-82.936207,39.957213],"type":"Point"}
}