{
  "type": "Feature",
  "properties": {
    "addr:full": "135 Pinewood St Elyria OH 44035",
    "addr:housenumber": "135",
    "addr:postcode": "44035",
    "addr:street": "Pinewood St",
    "iso:country": "US",
    "sg:address": "135 Pinewood St",
    "sg:city": "Elyria",
    "sg:classifiers": [
      {
        "category": "Professional",
        "subcategory": "Management \u0026 Consulting",
        "type": "Services"
      }
    ],
    "sg:phone": "+1 440 323 1167",
    "sg:postcode": "44035",
    "sg:province": "OH",
    "sg:tags": [
      "consultant",
      "business"
    ],
    "wof:name": "Inverted Pyramid Assoc",
    "wof:placetype": "venue"
  },
  "geometry": {"coordinates":[-82.100582,41.354628],"type":"Point"}
}
