{
  "type": "Feature",
  "properties": {
    "addr:full":"3810 Starr Centre Dr Canfield OH 44406",
    "addr:housenumber":"3810",
    "addr:postcode":"44406",
    "addr:street":"Starr Centre Dr",
    "iso:country":"US",
    "sg:address":"3810 Starr Centre Dr",
    "sg:city":"Canfield",
    "sg:classifiers":[
        {
            "category":"Banks & Credit Unions",
            "subcategory":"Bank",
            "type":"Services"
        }
    ],
    "sg:phone":"+1 330 702 8414",
    "sg:postcode":"44406",
    "sg:province":"OH",
    "sg:tags":[
        "loan",
        "real estate"
    ],
    "wof:name":"Society Mortgage Svc",
    "wof:placetype":"venue"
},
  "geometry": {"coordinates":[-80.717556,41.025503],"type":"Point"}
}