{
  "type": "Feature",
  "properties": {
    "addr:full":"21537 State Rte 751 West Lafayette OH 43845",
    "addr:housenumber":"21537",
    "addr:postcode":"43845",
    "addr:street":"State Rte 751",
    "iso:country":"US",
    "sg:address":"21537 State Rte 751",
    "sg:city":"West Lafayette",
    "sg:classifiers":[
        {
            "category":"Organizations",
            "subcategory":"Religious Organization",
            "type":"Services"
        }
    ],
    "sg:phone":"+1 740 545 6018",
    "sg:postcode":"43845",
    "sg:province":"OH",
    "sg:tags":[
        "church"
    ],
    "wof:name":"Village Baptist Church",
    "wof:placetype":"venue"
},
  "geometry": {"coordinates":[-81.732744,40.272123],"type":"Point"}
}