{
  "type": "Feature",
  "properties": {
    "addr:full":"1851 Wilson Ave Youngstown OH 44506",
    "addr:housenumber":"1851",
    "addr:postcode":"44506",
    "addr:street":"Wilson Ave",
    "iso:country":"US",
    "sg:address":"1851 Wilson Ave",
    "sg:city":"Youngstown",
    "sg:classifiers":[
        {
            "category":"Building & Trades",
            "subcategory":"Construction",
            "type":"Services"
        }
    ],
    "sg:phone":"+1 330 744 9928",
    "sg:postcode":"44506",
    "sg:province":"OH",
    "sg:tags":[
        "industrial",
        "painting",
        "painter",
        "contractor"
    ],
    "wof:name":"Sampson Maintenance Services",
    "wof:placetype":"venue"
},
  "geometry": {"coordinates":[-80.617058,41.083529],"type":"Point"}
}