{
  "type": "Feature",
  "properties": {
    "addr:full": "1734 Forest Hills Cir Zanesville OH 43701",
    "addr:housenumber": "1734",
    "addr:postcode": "43701",
    "addr:street": "Forest Hills Cir",
    "iso:country": "US",
    "sg:address": "1734 Forest Hills Cir",
    "sg:city": "Zanesville",
    "sg:classifiers": [
      {
        "category": "Real Estate",
        "subcategory": "Real Estate Agent",
        "type": "Services"
      }
    ],
    "sg:phone": "+1 740 588 9023",
    "sg:postcode": "43701",
    "sg:province": "OH",
    "sg:tags": [
      "inspection"
    ],
    "sg:website": "www.housemaster.com",
    "wof:name": "House Master Of America",
    "wof:placetype": "venue"
  },
  "geometry": {"coordinates":[-82.006172,39.990351],"type":"Point"}
}
