{
  "type": "Feature",
  "properties": {
    "iso:country":"US",
    "sg:address":"922 State Rte 28",
    "sg:city":"Milford",
    "sg:classifiers":[
        {
            "category":"Personal",
            "subcategory":"Beauty Salon",
            "type":"Services"
        }
    ],
    "sg:phone":"+1 513 831 9000",
    "sg:postcode":"45150",
    "sg:province":"OH",
    "wof:name":"New Attitudes Hair & Tnnng Sln",
    "wof:placetype":"venue"
},
  "geometry": {"coordinates":[-84.252518,39.191342],"type":"Point"}
}