{
  "type": "Feature",
  "properties": {
    "addr:full":"4666 Surmay Ave SW Canton OH 44706",
    "addr:housenumber":"4666",
    "addr:postcode":"44706",
    "addr:street":"Surmay Ave Sw",
    "iso:country":"US",
    "sg:address":"4666 Surmay Ave SW",
    "sg:city":"Canton",
    "sg:classifiers":[
        {
            "category":"Retail",
            "subcategory":"Repair Shop",
            "type":"Services"
        },
        {
            "category":"Health Services",
            "subcategory":"Clinic",
            "type":"Services"
        }
    ],
    "sg:phone":"+1 330 484 9800",
    "sg:postcode":"44706",
    "sg:province":"OH",
    "sg:tags":[
        "hospital",
        "refinishing"
    ],
    "wof:name":"Robert's Medical Refurb",
    "wof:placetype":"venue"
},
  "geometry": {"coordinates":[-81.442493,40.740845],"type":"Point"}
}