{
  "type": "Feature",
  "properties": {
    "iso:country":"US",
    "sg:address":"816 Clark Ave",
    "sg:city":"Ashland",
    "sg:classifiers":[
        {
            "category":"Professional",
            "subcategory":"Management & Consulting",
            "type":"Services"
        }
    ],
    "sg:phone":"+1 419 289 7518",
    "sg:postcode":"44805",
    "sg:province":"OH",
    "wof:name":"D-R Services",
    "wof:placetype":"venue"
},
  "geometry": {"coordinates":[-82.296177,40.874696],"type":"Point"}
}