{
  "type": "Feature",
  "properties": {
    "addr:full": "816 Clark Ave Ashland OH 44805",
    "addr:housenumber": "816",
    "addr:postcode": "44805",
    "addr:street": "Clark Ave",
    "iso:country": "US",
    "sg:address": "816 Clark Ave",
    "sg:city": "Ashland",
    "sg:classifiers": [
      {
        "category": "Professional",
        "subcategory": "Management \u0026 Consulting",
        "type": "Services"
      }
    ],
    "sg:phone": "+1 419 289 7518",
    "sg:postcode": "44805",
    "sg:province": "OH",
    "wof:name": "D-R Services",
    "wof:placetype": "venue"
  },
  "geometry": {"coordinates":[-82.296177,40.874696],"type":"Point"}
}
