{
  "type": "Feature",
  "properties": {
    "addr:full":"105 Cam Ct Lima OH 45805",
    "addr:housenumber":"105",
    "addr:postcode":"45805",
    "addr:street":"Cam Ct",
    "iso:country":"US",
    "sg:address":"105 Cam Ct",
    "sg:city":"Lima",
    "sg:classifiers":[
        {
            "category":"Insurance",
            "subcategory":"Insurance Agent",
            "type":"Services"
        }
    ],
    "sg:phone":"+1 419 998 3500",
    "sg:postcode":"45805",
    "sg:province":"OH",
    "sg:website":"www.statefarm.com",
    "wof:name":"State Farm Insurance",
    "wof:placetype":"venue"
},
  "geometry": {"coordinates":[-84.15194,40.707539],"type":"Point"}
}