{
  "type": "Feature",
  "properties": {
    "addr:full":"4353 E 49th St Cleveland OH 44125",
    "addr:housenumber":"4353",
    "addr:postcode":"44125",
    "addr:street":"E 49Th St",
    "iso:country":"US",
    "sg:address":"4353 E 49th St",
    "sg:city":"Cleveland",
    "sg:classifiers":[
        {
            "category":"Manufacturing",
            "subcategory":"Chemicals & Compounds",
            "type":"Manufacturing & Wholesale Goods"
        }
    ],
    "sg:phone":"+1 216 883 8025",
    "sg:postcode":"44125",
    "sg:province":"OH",
    "sg:tags":[
        "industrial",
        "organic",
        "mfg"
    ],
    "sg:website":"www.resorg.com",
    "wof:name":"Research Organics Inc",
    "wof:placetype":"venue"
},
  "geometry": {"coordinates":[-81.656576,41.432582],"type":"Point"}
}