{
  "type": "Feature",
  "properties": {
    "iso:country":"US",
    "sg:address":"1214 E 340th St",
    "sg:city":"Willoughby",
    "sg:classifiers":[
        {
            "category":"Building & Trades",
            "subcategory":"Plumbing",
            "type":"Services"
        }
    ],
    "sg:phone":"+1 440 975 0877",
    "sg:postcode":"44095",
    "sg:province":"OH",
    "sg:tags":[
        "heating",
        "contractor"
    ],
    "wof:name":"Artwell Heating & Cooling",
    "wof:placetype":"venue"
},
  "geometry": {"coordinates":[-81.446406,41.64452],"type":"Point"}
}