{
  "type": "Feature",
  "properties": {
    "addr:full": "1214 E 340th St Willoughby OH 44095",
    "addr:housenumber": "1214",
    "addr:postcode": "44095",
    "addr:street": "E 340Th St",
    "iso:country": "US",
    "sg:address": "1214 E 340th St",
    "sg:city": "Willoughby",
    "sg:classifiers": [
      {
        "category": "Building \u0026 Trades",
        "subcategory": "Plumbing",
        "type": "Services"
      }
    ],
    "sg:phone": "+1 440 975 0877",
    "sg:postcode": "44095",
    "sg:province": "OH",
    "sg:tags": [
      "heating",
      "contractor"
    ],
    "wof:name": "Artwell Heating \u0026 Cooling",
    "wof:placetype": "venue"
  },
  "geometry": {"coordinates":[-81.446406,41.64452],"type":"Point"}
}
