{
  "type": "Feature",
  "properties": {
    "addr:full": "33782 Lake Rd Avon Lake OH 44012",
    "addr:housenumber": "33782",
    "addr:postcode": "44012",
    "addr:street": "Lake Rd",
    "iso:country": "US",
    "sg:address": "33782 Lake Rd",
    "sg:city": "Avon Lake",
    "sg:classifiers": [
      {
        "category": "Building \u0026 Trades",
        "subcategory": "Construction",
        "type": "Services"
      }
    ],
    "sg:phone": "+1 440 930 5154",
    "sg:postcode": "44012",
    "sg:province": "OH",
    "sg:tags": [
      "remodeling"
    ],
    "wof:name": "Midway Construction",
    "wof:placetype": "venue"
  },
  "geometry": {"coordinates":[-82.060744,41.501912],"type":"Point"}
}
