{
  "type": "Feature",
  "properties": {
    "iso:country":"US",
    "sg:address":"33782 Lake Rd",
    "sg:city":"Avon Lake",
    "sg:classifiers":[
        {
            "category":"Building & Trades",
            "subcategory":"Construction",
            "type":"Services"
        }
    ],
    "sg:phone":"+1 440 930 5154",
    "sg:postcode":"44012",
    "sg:province":"OH",
    "sg:tags":[
        "remodeling"
    ],
    "wof:name":"Midway Construction",
    "wof:placetype":"venue"
},
  "geometry": {"coordinates":[-82.060744,41.501912],"type":"Point"}
}