{
  "type": "Feature",
  "properties": {
    "addr:full":"1430 Danner Dr Aurora OH 44202",
    "addr:housenumber":"1430",
    "addr:postcode":"44202",
    "addr:street":"Danner Dr",
    "iso:country":"US",
    "sg:address":"1430 Danner Dr",
    "sg:city":"Aurora",
    "sg:classifiers":[
        {
            "category":"Wholesale",
            "subcategory":"Hardware",
            "type":"Manufacturing & Wholesale Goods"
        }
    ],
    "sg:phone":"+1 330 562 4509",
    "sg:postcode":"44202",
    "sg:province":"OH",
    "sg:tags":[
        "tool"
    ],
    "sg:website":"www.worldwidechuck.com",
    "wof:name":"Worldwide Chuck Svc Inc",
    "wof:placetype":"venue"
},
  "geometry": {"coordinates":[-81.32987799999999,41.276331],"type":"Point"}
}