{
  "type": "Feature",
  "properties": {
    "addr:full": "395 Harding St Defiance OH 43512",
    "addr:housenumber": "395",
    "addr:postcode": "43512",
    "addr:street": "Harding St",
    "iso:country": "US",
    "sg:address": "395 Harding St",
    "sg:city": "Defiance",
    "sg:classifiers": [
      {
        "category": "Health Services",
        "subcategory": "Nursing And Care Facility",
        "type": "Services"
      }
    ],
    "sg:phone": "+1 419 784 2372",
    "sg:postcode": "43512",
    "sg:province": "OH",
    "sg:tags": [
      "home",
      "convalescent"
    ],
    "wof:name": "Harvorside Heathcare Defiance",
    "wof:placetype": "venue"
  },
  "geometry": {"coordinates":[-84.372203,41.297398],"type":"Point"}
}
