{
  "type": "Feature",
  "properties": {
    "iso:country":"US",
    "sg:address":"2621 W 14th St",
    "sg:city":"Cleveland",
    "sg:classifiers":[
        {
            "category":"Restaurant",
            "type":"Food & Drink"
        }
    ],
    "sg:phone":"+1 216 241 5025",
    "sg:postcode":"44113",
    "sg:province":"OH",
    "wof:name":"Grumpy's",
    "wof:placetype":"venue"
},
  "geometry": {"coordinates":[-81.691227,41.476907],"type":"Point"}
}