{
  "type": "Feature",
  "properties": {
    "iso:country":"US",
    "sg:address":"516 West St",
    "sg:city":"Caldwell",
    "sg:classifiers":[
        {
            "category":"Utilities",
            "subcategory":"Mobile Phone",
            "type":"Services"
        }
    ],
    "sg:phone":"+1 740 732 1770",
    "sg:postcode":"43724",
    "sg:province":"OH",
    "sg:tags":[
        "telephone",
        "cellular"
    ],
    "wof:name":"GAP Wireless Communication",
    "wof:placetype":"venue"
},
  "geometry": {"coordinates":[-81.51663600000001,39.748079],"type":"Point"}
}