{
  "type": "Feature",
  "properties": {
    "addr:full":"53 Marchmont Dr Fairborn OH 45324",
    "addr:housenumber":"53",
    "addr:postcode":"45324",
    "addr:street":"Marchmont Dr",
    "iso:country":"US",
    "sg:address":"53 Marchmont Dr",
    "sg:city":"Fairborn",
    "sg:classifiers":[
        {
            "category":"Organizations",
            "subcategory":"Religious Organization",
            "type":"Services"
        }
    ],
    "sg:phone":"+1 937 878 7224",
    "sg:postcode":"45324",
    "sg:province":"OH",
    "sg:tags":[
        "clergy"
    ],
    "wof:name":"Tooney Easterling",
    "wof:placetype":"venue"
},
  "geometry": {"coordinates":[-84.01246399999999,39.811073],"type":"Point"}
}