{
  "type": "Feature",
  "properties": {
    "addr:full": "8250 Rockwell Rd Mount Sterling OH 43143",
    "addr:housenumber": "8250",
    "addr:postcode": "43143",
    "addr:street": "Rockwell Rd",
    "iso:country": "US",
    "sg:address": "8250 Rockwell Rd",
    "sg:city": "Mount Sterling",
    "sg:classifiers": [
      {
        "category": "Farming",
        "subcategory": "Farm",
        "type": "Manufacturing \u0026 Wholesale Goods"
      }
    ],
    "sg:phone": "+1 740 869 2512",
    "sg:postcode": "43143",
    "sg:province": "OH",
    "sg:tags": [
      "crop",
      "general"
    ],
    "wof:name": "Dorn Mm",
    "wof:placetype": "venue"
  },
  "geometry": {"coordinates":[-83.339883,39.655132],"type":"Point"}
}
