{
  "type": "Feature",
  "properties": {
    "addr:full": "16282 Thompson Ridge Rd Laurelville OH 43135",
    "addr:housenumber": "16282",
    "addr:postcode": "43135",
    "addr:street": "Thompson Ridge Rd",
    "iso:country": "US",
    "sg:address": "16282 Thompson Ridge Rd",
    "sg:city": "Laurelville",
    "sg:classifiers": [
      {
        "category": "Manufacturing",
        "subcategory": "Lumber",
        "type": "Manufacturing \u0026 Wholesale Goods"
      }
    ],
    "sg:phone": "+1 740 332 6626",
    "sg:postcode": "43135",
    "sg:province": "OH",
    "sg:tags": [
      "logging"
    ],
    "wof:name": "Elkins Logging",
    "wof:placetype": "venue"
  },
  "geometry": {"coordinates":[-82.731423,39.471321],"type":"Point"}
}
