{
  "type": "Feature",
  "properties": {
    "iso:country":"US",
    "sg:address":"16282 Thompson Ridge Rd",
    "sg:city":"Laurelville",
    "sg:classifiers":[
        {
            "category":"Manufacturing",
            "subcategory":"Lumber",
            "type":"Manufacturing & Wholesale Goods"
        }
    ],
    "sg:phone":"+1 740 332 6626",
    "sg:postcode":"43135",
    "sg:province":"OH",
    "sg:tags":[
        "logging"
    ],
    "wof:name":"Elkins Logging",
    "wof:placetype":"venue"
},
  "geometry": {"coordinates":[-82.73142300000001,39.471321],"type":"Point"}
}