{
  "type": "Feature",
  "properties": {
    "iso:country":"US",
    "sg:address":"438 E Wilson Bridge Rd",
    "sg:city":"Worthington",
    "sg:classifiers":[
        {
            "category":"Utilities",
            "subcategory":"Mobile Phone",
            "type":"Services"
        }
    ],
    "sg:phone":"+1 614 436 2771",
    "sg:postcode":"43085",
    "sg:province":"OH",
    "sg:tags":[
        "telephone",
        "cellular"
    ],
    "wof:name":"Cellular One",
    "wof:placetype":"venue"
},
  "geometry": {"coordinates":[-82.998969,40.109154],"type":"Point"}
}