{
  "type": "Feature",
  "properties": {
    "addr:full":"29076 Fall River Dr Westlake OH 44145",
    "addr:housenumber":"29076",
    "addr:postcode":"44145",
    "addr:street":"Fall River Dr",
    "iso:country":"US",
    "sg:address":"29076 Fall River Dr",
    "sg:city":"Westlake",
    "sg:classifiers":[
        {
            "category":"Manufacturing",
            "subcategory":"Printing",
            "type":"Manufacturing & Wholesale Goods"
        }
    ],
    "sg:phone":"+1 440 892 0436",
    "sg:postcode":"44145",
    "sg:province":"OH",
    "sg:tags":[
        "typesetting"
    ],
    "wof:name":"HB Laser Communication Inc",
    "wof:placetype":"venue"
},
  "geometry": {"coordinates":[-81.938186,41.43327],"type":"Point"}
}