{
  "type": "Feature",
  "properties": {
    "iso:country":"US",
    "sg:address":"6370 S Co Rd 43",
    "sg:city":"Tiffin",
    "sg:phone":"+1 419 983 5995",
    "sg:postcode":"44883",
    "sg:province":"OH",
    "sg:tags":[
        "farm",
        "corn",
        "wheat",
        "soybean"
    ],
    "wof:name":"Don Geary",
    "wof:placetype":"venue"
},
  "geometry": {"coordinates":[-83.054614,41.032008],"type":"Point"}
}