{
  "type": "Feature",
  "properties": {
    "addr:full": "335 Glessner Ave Mansfield OH 44903",
    "addr:housenumber": "335",
    "addr:postcode": "44903",
    "addr:street": "Glessner Ave",
    "iso:country": "US",
    "sg:address": "335 Glessner Ave",
    "sg:city": "Mansfield",
    "sg:classifiers": [
      {
        "category": "Health Services",
        "subcategory": "Health Practitioner",
        "type": "Services"
      }
    ],
    "sg:phone": "+1 419 526 8551",
    "sg:postcode": "44903",
    "sg:province": "OH",
    "sg:tags": [
      "pathologist",
      "speech"
    ],
    "wof:name": "Mansfield Hospital",
    "wof:placetype": "venue"
  },
  "geometry": {"coordinates":[-82.52787,40.753425],"type":"Point"}
}
