{
  "type": "Feature",
  "properties": {
    "addr:full": "330 Southview Rd Dayton OH 45419",
    "addr:housenumber": "330",
    "addr:postcode": "45419",
    "addr:street": "Southview Rd",
    "iso:country": "US",
    "sg:address": "330 Southview Rd",
    "sg:city": "Dayton",
    "sg:classifiers": [
      {
        "category": "Banks \u0026 Credit Unions",
        "subcategory": "Bank",
        "type": "Services"
      }
    ],
    "sg:phone": "+1 937 298 1133",
    "sg:postcode": "45419",
    "sg:province": "OH",
    "sg:tags": [
      "company",
      "trust"
    ],
    "wof:name": "Preservation Trust For Oak",
    "wof:placetype": "venue"
  },
  "geometry": {"coordinates":[-84.183326,39.726454],"type":"Point"}
}
