{
  "type": "Feature",
  "properties": {
    "addr:full": "12008 Saint Clair Ave Cleveland OH 44108",
    "addr:housenumber": "12008",
    "addr:postcode": "44108",
    "addr:street": "Saint Clair Ave",
    "iso:country": "US",
    "sg:address": "12008 Saint Clair Ave",
    "sg:city": "Cleveland",
    "sg:classifiers": [
      {
        "category": "Food \u0026 Beverages",
        "subcategory": "Groceries \u0026 Convenience Stores",
        "type": "Retail Goods"
      }
    ],
    "sg:phone": "+1 216 451 0311",
    "sg:postcode": "44108",
    "sg:province": "OH",
    "sg:tags": [
      "grocer"
    ],
    "wof:name": "Mandingo's",
    "wof:placetype": "venue"
  },
  "geometry": {"coordinates":[-81.601049,41.54127],"type":"Point"}
}
