{
  "type": "Feature",
  "properties": {
    "iso:country":"US",
    "sg:address":"12008 Saint Clair Ave",
    "sg:city":"Cleveland",
    "sg:classifiers":[
        {
            "category":"Food & Beverages",
            "subcategory":"Groceries & Convenience Stores",
            "type":"Retail Goods"
        }
    ],
    "sg:phone":"+1 216 451 0311",
    "sg:postcode":"44108",
    "sg:province":"OH",
    "sg:tags":[
        "grocer"
    ],
    "wof:name":"Mandingo's",
    "wof:placetype":"venue"
},
  "geometry": {"coordinates":[-81.601049,41.54127],"type":"Point"}
}