{
  "type": "Feature",
  "properties": {
    "addr:full": "541 Adrian Ct Brookville OH 45309",
    "addr:housenumber": "541",
    "addr:postcode": "45309",
    "addr:street": "Adrian Ct",
    "iso:country": "US",
    "sg:address": "541 Adrian Ct",
    "sg:city": "Brookville",
    "sg:classifiers": [
      {
        "category": "Building \u0026 Trades",
        "subcategory": "Construction",
        "type": "Services"
      }
    ],
    "sg:phone": "+1 937 833 1488",
    "sg:postcode": "45309",
    "sg:province": "OH",
    "sg:tags": [
      "nonresidential"
    ],
    "wof:name": "Dayton Industries Group Inc",
    "wof:placetype": "venue"
  },
  "geometry": {"coordinates":[-84.427292,39.839936],"type":"Point"}
}
