{
  "type": "Feature",
  "properties": {
    "addr:full": "725 Glenwood Ave Fostoria OH 44830",
    "addr:housenumber": "725",
    "addr:postcode": "44830",
    "addr:street": "Glenwood Ave",
    "iso:country": "US",
    "sg:address": "725 Glenwood Ave",
    "sg:city": "Fostoria",
    "sg:classifiers": [
      {
        "category": "Home \u0026 Garden",
        "subcategory": "Carpets \u0026 Floor Coverings",
        "type": "Retail Goods"
      }
    ],
    "sg:phone": "+1 419 435 5016",
    "sg:postcode": "44830",
    "sg:province": "OH",
    "wof:name": "Clarks Carpet Installatio",
    "wof:placetype": "venue"
  },
  "geometry": {"coordinates":[-83.402322,41.167562],"type":"Point"}
}
