{
  "type": "Feature",
  "properties": {
    "addr:full": "1580 W Turkeyfoot Lake Rd Barberton OH 44203",
    "addr:housenumber": "1580",
    "addr:postcode": "44203",
    "addr:street": "W Turkeyfoot Lake Rd",
    "iso:country": "US",
    "sg:address": "1580 W Turkeyfoot Lake Rd",
    "sg:city": "Barberton",
    "sg:classifiers": [
      {
        "category": "Manufacturing",
        "subcategory": "Rubber \u0026 Plastics",
        "type": "Manufacturing \u0026 Wholesale Goods"
      }
    ],
    "sg:phone": "+1 330 753 0162",
    "sg:postcode": "44203",
    "sg:province": "OH",
    "sg:tags": [
      "process",
      "thermal"
    ],
    "wof:name": "G \u0026 J Extrusions Inc",
    "wof:placetype": "venue"
  },
  "geometry": {"coordinates":[-81.575737,40.986601],"type":"Point"}
}
