{
  "type": "Feature",
  "properties": {
    "addr:full":"4529 English Creek Dr Cincinnati OH 45245",
    "addr:housenumber":"4529",
    "addr:postcode":"45245",
    "addr:street":"English Creek Dr",
    "iso:country":"US",
    "sg:address":"4529 English Creek Dr",
    "sg:city":"Cincinnati",
    "sg:classifiers":[
        {
            "category":"Wholesale",
            "subcategory":"Hardware",
            "type":"Manufacturing & Wholesale Goods"
        },
        {
            "category":"Building & Trades",
            "subcategory":"Construction",
            "type":"Services"
        }
    ],
    "sg:phone":"+1 513 752 5743",
    "sg:postcode":"45245",
    "sg:province":"OH",
    "sg:tags":[
        "industrial",
        "wall",
        "commercial",
        "heating",
        "air",
        "conditioning",
        "distributor",
        "new",
        "unit"
    ],
    "sg:website":"www.gordonconst.com",
    "wof:name":"Gordon Construction Inc",
    "wof:placetype":"venue"
},
  "geometry": {"coordinates":[-84.26284200000001,39.10407],"type":"Point"}
}