{
  "type": "Feature",
  "properties": {
    "iso:country":"US",
    "sg:address":"458 Greenvale Rd",
    "sg:city":"Cleveland",
    "sg:classifiers":[
        {
            "category":"Freight",
            "type":"Transportation"
        }
    ],
    "sg:phone":"+1 216 254 1931",
    "sg:postcode":"44121",
    "sg:province":"OH",
    "sg:tags":[
        "operator",
        "local",
        "trucking"
    ],
    "wof:name":"T & MS Hauling and Moving",
    "wof:placetype":"venue"
},
  "geometry": {"coordinates":[-81.536856,41.542007],"type":"Point"}
}