{
  "type": "Feature",
  "properties": {
    "iso:country":"US",
    "sg:address":"1604 Pine St",
    "sg:city":"Zanesville",
    "sg:classifiers":[
        {
            "category":"Organizations",
            "subcategory":"Religious Organization",
            "type":"Services"
        }
    ],
    "sg:phone":"+1 740 452 6753",
    "sg:postcode":"43701",
    "sg:province":"OH",
    "sg:tags":[
        "church"
    ],
    "wof:name":"Southside Baptist Church",
    "wof:placetype":"venue"
},
  "geometry": {"coordinates":[-82.017029,39.91587],"type":"Point"}
}