{
  "type": "Feature",
  "properties": {
    "addr:full":"4500 Woodville Rd Northwood OH 43619",
    "addr:housenumber":"4500",
    "addr:postcode":"43619",
    "addr:street":"Woodville Rd",
    "iso:country":"US",
    "sg:address":"4500 Woodville Rd",
    "sg:city":"Northwood",
    "sg:classifiers":[
        {
            "category":"Building & Trades",
            "subcategory":"Construction",
            "type":"Services"
        }
    ],
    "sg:phone":"+1 419 691 6409",
    "sg:postcode":"43619",
    "sg:province":"OH",
    "sg:tags":[
        "contractor"
    ],
    "wof:name":"Jj Drywall",
    "wof:placetype":"venue"
},
  "geometry": {"coordinates":[-83.46737,41.603964],"type":"Point"}
}