{
  "type": "Feature",
  "properties": {
    "addr:full": "3309 Grinnell Rd Xenia OH 45385",
    "addr:housenumber": "3309",
    "addr:postcode": "45385",
    "addr:street": "Grinnell Rd",
    "iso:country": "US",
    "sg:address": "3309 Grinnell Rd",
    "sg:city": "Xenia",
    "sg:phone": "+1 937 767 9356",
    "sg:postcode": "45385",
    "sg:province": "OH",
    "sg:tags": [
      "farm",
      "corn"
    ],
    "wof:name": "Craig Corry",
    "wof:placetype": "venue"
  },
  "geometry": {"coordinates":[-83.867634,39.773923],"type":"Point"}
}
