{
  "type": "Feature",
  "properties": {
    "iso:country":"US",
    "sg:address":"5128 Grandin Ridge Dr",
    "sg:city":"Hamilton",
    "sg:classifiers":[
        {
            "category":"Building & Trades",
            "subcategory":"Construction",
            "type":"Services"
        }
    ],
    "sg:phone":"+1 513 314 8750",
    "sg:postcode":"45011",
    "sg:province":"OH",
    "sg:tags":[
        "hanging",
        "contractor"
    ],
    "wof:name":"Loncharte Painting",
    "wof:placetype":"venue"
},
  "geometry": {"coordinates":[-84.449352,39.38329],"type":"Point"}
}