{
  "type": "Feature",
  "properties": {
    "addr:full": "5128 Grandin Ridge Dr Hamilton OH 45011",
    "addr:housenumber": "5128",
    "addr:postcode": "45011",
    "addr:street": "Grandin Ridge Dr",
    "iso:country": "US",
    "sg:address": "5128 Grandin Ridge Dr",
    "sg:city": "Hamilton",
    "sg:classifiers": [
      {
        "category": "Building \u0026 Trades",
        "subcategory": "Construction",
        "type": "Services"
      }
    ],
    "sg:phone": "+1 513 314 8750",
    "sg:postcode": "45011",
    "sg:province": "OH",
    "sg:tags": [
      "hanging",
      "contractor"
    ],
    "wof:name": "Loncharte Painting",
    "wof:placetype": "venue"
  },
  "geometry": {"coordinates":[-84.449352,39.38329],"type":"Point"}
}
