{
  "type": "Feature",
  "properties": {
    "addr:full":"34851 Euclid Ave Willoughby OH 44094",
    "addr:housenumber":"34851",
    "addr:postcode":"44094",
    "addr:street":"Euclid Ave",
    "iso:country":"US",
    "sg:address":"34851 Euclid Ave",
    "sg:city":"Willoughby",
    "sg:classifiers":[
        {
            "category":"Restaurant",
            "type":"Food & Drink"
        }
    ],
    "sg:menulink":"http://www.allmenus.com/oh/willoughby/122451-quiznos-sub/menu/",
    "sg:phone":"+1 440 951 9641",
    "sg:postcode":"44094",
    "sg:province":"OH",
    "sg:tags":[
        "wrap",
        "american",
        "sandwich"
    ],
    "wof:name":"Quiznos Sub",
    "wof:placetype":"venue"
},
  "geometry": {"coordinates":[-81.439695,41.62495],"type":"Point"}
}