{
  "type": "Feature",
  "properties": {
    "addr:full": "19 N Main St New London OH 44851",
    "addr:housenumber": "19",
    "addr:postcode": "44851",
    "addr:street": "N Main St",
    "iso:country": "US",
    "sg:address": "19 N Main St",
    "sg:city": "New London",
    "sg:classifiers": [
      {
        "category": "Autos \u0026 Motor Vehicles",
        "subcategory": "Automobile Sales",
        "type": "Retail Goods"
      }
    ],
    "sg:phone": "+1 419 929 3911",
    "sg:postcode": "44851",
    "sg:province": "OH",
    "sg:tags": [
      "new",
      "used",
      "parts",
      "offer"
    ],
    "wof:name": "Baileys Pontiac",
    "wof:placetype": "venue"
  },
  "geometry": {"coordinates":[-82.399565,41.085761],"type":"Point"}
}
