{
  "type": "Feature",
  "properties": {
    "iso:country":"US",
    "sg:address":"680 Baxter Rd",
    "sg:city":"Loveland",
    "sg:classifiers":[
        {
            "category":"Building & Trades",
            "subcategory":"Landscaping Services",
            "type":"Services"
        }
    ],
    "sg:phone":"+1 513 683 6800",
    "sg:postcode":"45140",
    "sg:province":"OH",
    "sg:tags":[
        "landscape"
    ],
    "wof:name":"Surroundings Inc",
    "wof:placetype":"venue"
},
  "geometry": {"coordinates":[-84.241132,39.276337],"type":"Point"}
}