{
  "type": "Feature",
  "properties": {
    "addr:full":"914 E Indianola Ave Youngstown OH 44502",
    "addr:housenumber":"914",
    "addr:postcode":"44502",
    "addr:street":"E Indianola Ave",
    "iso:country":"US",
    "sg:address":"914 E Indianola Ave",
    "sg:city":"Youngstown",
    "sg:classifiers":[
        {
            "category":"Manufacturing",
            "subcategory":"Tools & Machinery",
            "type":"Manufacturing & Wholesale Goods"
        }
    ],
    "sg:phone":"+1 330 782 6731",
    "sg:postcode":"44502",
    "sg:province":"OH",
    "sg:tags":[
        "mfg"
    ],
    "wof:name":"Mor-X Plastics",
    "wof:placetype":"venue"
},
  "geometry": {"coordinates":[-80.637692,41.073119],"type":"Point"}
}