{
  "type": "Feature",
  "properties": {
    "iso:country":"US",
    "sg:address":"277 W Nationwide Blvd Suite 200",
    "sg:city":"Columbus",
    "sg:classifiers":[
        {
            "category":"Professional",
            "subcategory":"Employment Agencies",
            "type":"Services"
        }
    ],
    "sg:phone":"+1 888 400 7474",
    "sg:postcode":"43215",
    "sg:province":"OH",
    "sg:tags":[
        "contractor"
    ],
    "sg:website":"http://www.officeteam.com",
    "wof:name":"OfficeTeam",
    "wof:placetype":"venue"
},
  "geometry": {"coordinates":[-83.009083,39.968171],"type":"Point"}
}