{
  "type": "Feature",
  "properties": {
    "iso:country":"US",
    "sg:address":"125 Cutright Dr",
    "sg:city":"Chillicothe",
    "sg:classifiers":[
        {
            "category":"Education",
            "subcategory":"School",
            "type":"Public Place"
        }
    ],
    "sg:phone":"+1 740 773 1455",
    "sg:postcode":"45601",
    "sg:province":"OH",
    "wof:name":"Chillicothe City Schls Mctnc",
    "wof:placetype":"venue"
},
  "geometry": {"coordinates":[-82.959074,39.338788],"type":"Point"}
}