{
  "type": "Feature",
  "properties": {
    "iso:country":"US",
    "sg:address":"625 Davids St",
    "sg:city":"Marion",
    "sg:classifiers":[
        {
            "category":"Manufacturing",
            "subcategory":"Printing",
            "type":"Manufacturing & Wholesale Goods"
        }
    ],
    "sg:phone":"+1 740 375 2810",
    "sg:postcode":"43302",
    "sg:province":"OH",
    "sg:tags":[
        "commercial"
    ],
    "wof:name":"Jats Graphic & Printing",
    "wof:placetype":"venue"
},
  "geometry": {"coordinates":[-83.143412,40.577858],"type":"Point"}
}