{
  "type": "Feature",
  "properties": {
    "addr:full": "625 Davids St Marion OH 43302",
    "addr:housenumber": "625",
    "addr:postcode": "43302",
    "addr:street": "Davids St",
    "iso:country": "US",
    "sg:address": "625 Davids St",
    "sg:city": "Marion",
    "sg:classifiers": [
      {
        "category": "Manufacturing",
        "subcategory": "Printing",
        "type": "Manufacturing \u0026 Wholesale Goods"
      }
    ],
    "sg:phone": "+1 740 375 2810",
    "sg:postcode": "43302",
    "sg:province": "OH",
    "sg:tags": [
      "commercial"
    ],
    "wof:name": "Jats Graphic \u0026 Printing",
    "wof:placetype": "venue"
  },
  "geometry": {"coordinates":[-83.143412,40.577858],"type":"Point"}
}
