{
  "type": "Feature",
  "properties": {
    "addr:full":"4725 Greenbriar Ln Lorain OH 44053",
    "addr:housenumber":"4725",
    "addr:postcode":"44053",
    "addr:street":"Greenbriar Ln",
    "iso:country":"US",
    "sg:address":"4725 Greenbriar Ln",
    "sg:city":"Lorain",
    "sg:classifiers":[
        {
            "category":"Recreation",
            "type":"Entertainment"
        }
    ],
    "sg:phone":"+1 440 989 8199",
    "sg:postcode":"44053",
    "sg:province":"OH",
    "sg:tags":[
        "club",
        "membership"
    ],
    "wof:name":"Hurricane Soccer Club",
    "wof:placetype":"venue"
},
  "geometry": {"coordinates":[-82.238945,41.427986],"type":"Point"}
}