{
  "type": "Feature",
  "properties": {
    "addr:full": "601 E Main St West Lafayette OH 43845",
    "addr:housenumber": "601",
    "addr:postcode": "43845",
    "addr:street": "E Main St",
    "iso:country": "US",
    "sg:address": "601 E Main St",
    "sg:city": "West Lafayette",
    "sg:classifiers": [
      {
        "category": "Education",
        "subcategory": "Library",
        "type": "Public Place"
      }
    ],
    "sg:phone": "+1 740 545 6672",
    "sg:postcode": "43845",
    "sg:province": "OH",
    "wof:name": "West Lafayette Branch Library",
    "wof:placetype": "venue"
  },
  "geometry": {"coordinates":[-81.745521,40.27424],"type":"Point"}
}
