{
  "type": "Feature",
  "properties": {
    "iso:country":"US",
    "sg:address":"11780 State Rte 41",
    "sg:city":"West Union",
    "sg:classifiers":[
        {
            "category":"Wholesale",
            "subcategory":"Farm Supplies",
            "type":"Manufacturing & Wholesale Goods"
        }
    ],
    "sg:phone":"+1 937 544 3332",
    "sg:postcode":"45693",
    "sg:province":"OH",
    "sg:tags":[
        "feed"
    ],
    "wof:name":"West Union Farm Supply Inc",
    "wof:placetype":"venue"
},
  "geometry": {"coordinates":[-83.560238,38.784056],"type":"Point"}
}