{
  "type": "Feature",
  "properties": {
    "addr:full": "11780 State Rte 41 West Union OH 45693",
    "addr:housenumber": "11780",
    "addr:postcode": "45693",
    "addr:street": "State Rte 41 West",
    "iso:country": "US",
    "sg:address": "11780 State Rte 41",
    "sg:city": "West Union",
    "sg:classifiers": [
      {
        "category": "Wholesale",
        "subcategory": "Farm Supplies",
        "type": "Manufacturing \u0026 Wholesale Goods"
      }
    ],
    "sg:phone": "+1 937 544 3332",
    "sg:postcode": "45693",
    "sg:province": "OH",
    "sg:tags": [
      "feed"
    ],
    "wof:name": "West Union Farm Supply Inc",
    "wof:placetype": "venue"
  },
  "geometry": {"coordinates":[-83.560238,38.784056],"type":"Point"}
}
