{
  "type": "Feature",
  "properties": {
    "addr:full": "17928 State Rte 501 Wapakoneta OH 45895",
    "addr:housenumber": "17928",
    "addr:postcode": "45895",
    "addr:street": "State Rte 501",
    "iso:country": "US",
    "sg:address": "17928 State Rte 501",
    "sg:city": "Wapakoneta",
    "sg:classifiers": [
      {
        "category": "Farming",
        "subcategory": "Dairy Farm",
        "type": "Manufacturing \u0026 Wholesale Goods"
      }
    ],
    "sg:phone": "+1 419 657 6073",
    "sg:postcode": "45895",
    "sg:province": "OH",
    "sg:tags": [
      "corn",
      "soybean"
    ],
    "wof:name": "Rodney Davis",
    "wof:placetype": "venue"
  },
  "geometry": {"coordinates":[-84.203018,40.612157],"type":"Point"}
}
