{
  "type": "Feature",
  "properties": {
    "iso:country":"US",
    "sg:address":"17928 State Rte 501",
    "sg:city":"Wapakoneta",
    "sg:classifiers":[
        {
            "category":"Farming",
            "subcategory":"Dairy Farm",
            "type":"Manufacturing & Wholesale Goods"
        }
    ],
    "sg:phone":"+1 419 657 6073",
    "sg:postcode":"45895",
    "sg:province":"OH",
    "sg:tags":[
        "corn",
        "soybean"
    ],
    "wof:name":"Rodney Davis",
    "wof:placetype":"venue"
},
  "geometry": {"coordinates":[-84.203018,40.612157],"type":"Point"}
}