{
  "type": "Feature",
  "properties": {
    "iso:country":"US",
    "sg:address":"220 Springwood Rd",
    "sg:city":"Northfield",
    "sg:classifiers":[
        {
            "category":"Professional",
            "type":"Services"
        }
    ],
    "sg:phone":"+1 330 467 0454",
    "sg:postcode":"44067",
    "sg:province":"OH",
    "wof:name":"Craig T Poling",
    "wof:placetype":"venue"
},
  "geometry": {"coordinates":[-81.549488,41.320541],"type":"Point"}
}