{
  "type": "Feature",
  "properties": {
    "addr:full": "220 Springwood Rd Northfield OH 44067",
    "addr:housenumber": "220",
    "addr:postcode": "44067",
    "addr:street": "Springwood Rd",
    "iso:country": "US",
    "sg:address": "220 Springwood Rd",
    "sg:city": "Northfield",
    "sg:classifiers": [
      {
        "category": "Professional",
        "type": "Services"
      }
    ],
    "sg:phone": "+1 330 467 0454",
    "sg:postcode": "44067",
    "sg:province": "OH",
    "wof:name": "Craig T Poling",
    "wof:placetype": "venue"
  },
  "geometry": {"coordinates":[-81.549488,41.320541],"type":"Point"}
}
