{
  "type": "Feature",
  "properties": {
    "iso:country":"US",
    "sg:address":"227 Renick Ave",
    "sg:city":"Chillicothe",
    "sg:classifiers":[
        {
            "category":"Manufacturing",
            "subcategory":"Printing",
            "type":"Manufacturing & Wholesale Goods"
        }
    ],
    "sg:phone":"+1 740 774 3306",
    "sg:postcode":"45601",
    "sg:province":"OH",
    "sg:tags":[
        "screen"
    ],
    "wof:name":"Mile Tree Screen Printing",
    "wof:placetype":"venue"
},
  "geometry": {"coordinates":[-82.950075,39.335706],"type":"Point"}
}