{
  "type": "Feature",
  "properties": {
    "iso:country":"US",
    "sg:address":"1660 Waynesburg Dr SE",
    "sg:city":"Canton",
    "sg:classifiers":[
        {
            "category":"Food & Beverages",
            "subcategory":"Groceries & Convenience Stores",
            "type":"Retail Goods"
        }
    ],
    "sg:phone":"+1 330 453 6932",
    "sg:postcode":"44707",
    "sg:province":"OH",
    "sg:tags":[
        "vegetable",
        "fruit"
    ],
    "wof:name":"Smiths Waco Market",
    "wof:placetype":"venue"
},
  "geometry": {"coordinates":[-81.346841,40.77927],"type":"Point"}
}