{
  "type": "Feature",
  "properties": {
    "addr:full": "46 S Main St Mt Gilead OH 43338",
    "addr:housenumber": "46",
    "addr:postcode": "43338",
    "addr:street": "S Main St",
    "iso:country": "US",
    "sg:address": "46 S Main St",
    "sg:city": "Mt Gilead",
    "sg:classifiers": [
      {
        "category": "Insurance",
        "subcategory": "Insurance Agent",
        "type": "Services"
      }
    ],
    "sg:phone": "+1 419 947 4060",
    "sg:postcode": "43338",
    "sg:province": "OH",
    "wof:name": "Glenn Evans \u0026 Assoc",
    "wof:placetype": "venue"
  },
  "geometry": {"coordinates":[-82.828664,40.548046],"type":"Point"}
}
