{
  "type": "Feature",
  "properties": {
    "addr:full":"190 Richland Rd Xenia OH 45385",
    "addr:housenumber":"190",
    "addr:postcode":"45385",
    "addr:street":"Richland Rd",
    "iso:country":"US",
    "sg:address":"190 Richland Rd",
    "sg:city":"Xenia",
    "sg:classifiers":[
        {
            "category":"Wholesale",
            "subcategory":"Hardware",
            "type":"Manufacturing & Wholesale Goods"
        }
    ],
    "sg:phone":"+1 937 376 9655",
    "sg:postcode":"45385",
    "sg:province":"OH",
    "wof:name":"Meades Furnace & Air",
    "wof:placetype":"venue"
},
  "geometry": {"coordinates":[-83.957037,39.626937],"type":"Point"}
}