{
  "type": "Feature",
  "properties": {
    "addr:full": "6393 Oak Tree Blvd Cleveland OH 44131",
    "addr:housenumber": "6393",
    "addr:postcode": "44131",
    "addr:street": "Oak Tree Blvd",
    "iso:country": "US",
    "sg:address": "6393 Oak Tree Blvd",
    "sg:city": "Cleveland",
    "sg:classifiers": [
      {
        "category": "Insurance",
        "subcategory": "Insurance Agent",
        "type": "Services"
      }
    ],
    "sg:phone": "+1 216 520 0315",
    "sg:postcode": "44131",
    "sg:province": "OH",
    "wof:name": "Medical Mutual Of Ohio",
    "wof:placetype": "venue"
  },
  "geometry": {"coordinates":[-81.660056,41.392507],"type":"Point"}
}
