{
  "type": "Feature",
  "properties": {
    "addr:full": "1346 Chapel St Cincinnati OH 45206",
    "addr:housenumber": "1346",
    "addr:postcode": "45206",
    "addr:street": "Chapel St",
    "iso:country": "US",
    "sg:address": "1346 Chapel St",
    "sg:city": "Cincinnati",
    "sg:classifiers": [
      {
        "category": "Health Services",
        "subcategory": "Health Practitioner",
        "type": "Services"
      }
    ],
    "sg:phone": "+1 513 961 8400",
    "sg:postcode": "45206",
    "sg:province": "OH",
    "sg:tags": [
      "psychologist"
    ],
    "wof:name": "Barbara J Walker",
    "wof:placetype": "venue"
  },
  "geometry": {"coordinates":[-84.479959,39.130734],"type":"Point"}
}
