{
  "type": "Feature",
  "properties": {
    "iso:country":"US",
    "sg:address":"933 Bethel Rd",
    "sg:city":"Columbus",
    "sg:classifiers":[
        {
            "category":"Shopping",
            "subcategory":"Pharmacy",
            "type":"Retail Goods"
        }
    ],
    "sg:phone":"+1 614 459 9521",
    "sg:postcode":"43214",
    "sg:province":"OH",
    "wof:name":"CVS Pharmacy",
    "wof:placetype":"venue"
},
  "geometry": {"coordinates":[-83.043915,40.063206],"type":"Point"}
}