{
  "type": "Feature",
  "properties": {
    "addr:full": "107 N Sandusky Ave Bucyrus OH 44820",
    "addr:housenumber": "107",
    "addr:postcode": "44820",
    "addr:street": "N Sandusky Ave",
    "iso:country": "US",
    "sg:address": "107 N Sandusky Ave",
    "sg:city": "Bucyrus",
    "sg:classifiers": [
      {
        "category": "Shopping",
        "subcategory": "Hobbies, Toys, \u0026 Games",
        "type": "Retail Goods"
      }
    ],
    "sg:phone": "+1 419 563 1011",
    "sg:postcode": "44820",
    "sg:province": "OH",
    "wof:name": "C \u0026 R Hobbies",
    "wof:placetype": "venue"
  },
  "geometry": {"coordinates":[-82.975648,40.809669],"type":"Point"}
}
