{
  "type": "Feature",
  "properties": {
    "addr:full": "477 N Park St Columbus OH 43215",
    "addr:housenumber": "477",
    "addr:postcode": "43215",
    "addr:street": "N Park St",
    "iso:country": "US",
    "sg:address": "477 N Park St",
    "sg:city": "Columbus",
    "sg:classifiers": [
      {
        "category": "Restaurant",
        "type": "Food \u0026 Drink"
      }
    ],
    "sg:phone": "+1 614 221 0673",
    "sg:postcode": "43215",
    "sg:province": "OH",
    "wof:name": "Brothers Bar \u0026 Grill",
    "wof:placetype": "venue"
  },
  "geometry": {"coordinates":[-83.004707,39.971705],"type":"Point"}
}
