{
  "type": "Feature",
  "properties": {
    "iso:country":"US",
    "sg:address":"477 N Park St",
    "sg:city":"Columbus",
    "sg:classifiers":[
        {
            "category":"Restaurant",
            "type":"Food & Drink"
        }
    ],
    "sg:phone":"+1 614 221 0673",
    "sg:postcode":"43215",
    "sg:province":"OH",
    "wof:name":"Brothers Bar & Grill",
    "wof:placetype":"venue"
},
  "geometry": {"coordinates":[-83.004707,39.971705],"type":"Point"}
}