{
  "type": "Feature",
  "properties": {
    "addr:full": "336 Hilan Ave SW New Philadelphia OH 44663",
    "addr:housenumber": "336",
    "addr:postcode": "44663",
    "addr:street": "Hilan Ave Sw",
    "iso:country": "US",
    "sg:address": "336 Hilan Ave SW",
    "sg:city": "New Philadelphia",
    "sg:classifiers": [
      {
        "category": "Real Estate",
        "subcategory": "Real Estate Agent",
        "type": "Services"
      }
    ],
    "sg:phone": "+1 330 340 1861",
    "sg:postcode": "44663",
    "sg:province": "OH",
    "wof:name": "JBL Realty Investments",
    "wof:placetype": "venue"
  },
  "geometry": {"coordinates":[-81.454597,40.471826],"type":"Point"}
}
