{
  "type": "Feature",
  "properties": {
    "iso:country":"US",
    "sg:address":"27750 Price Ln",
    "sg:city":"West Harrison",
    "sg:classifiers":[
        {
            "category":"Building & Trades",
            "subcategory":"Construction",
            "type":"Services"
        }
    ],
    "sg:phone":"+1 812 637 2528",
    "sg:postcode":"47060",
    "sg:province":"OH",
    "sg:tags":[
        "general",
        "contractor"
    ],
    "wof:name":"Price Construction",
    "wof:placetype":"venue"
},
  "geometry": {"coordinates":[-84.900071,39.27092],"type":"Point"}
}