{
  "type": "Feature",
  "properties": {
    "addr:full":"5505 Milan Rd Sandusky OH 44870",
    "addr:housenumber":"5505",
    "addr:postcode":"44870",
    "addr:street":"Milan Rd",
    "iso:country":"US",
    "sg:address":"5505 Milan Rd",
    "sg:city":"Sandusky",
    "sg:classifiers":[
        {
            "category":"Building & Trades",
            "subcategory":"Construction",
            "type":"Services"
        }
    ],
    "sg:phone":"+1 419 626 1111",
    "sg:postcode":"44870",
    "sg:province":"OH",
    "sg:tags":[
        "general",
        "contractor"
    ],
    "wof:name":"Telamon Construction Inc",
    "wof:placetype":"venue"
},
  "geometry": {"coordinates":[-82.652835,41.396896],"type":"Point"}
}