{
  "type": "Feature",
  "properties": {
    "addr:full":"1900 N High St Columbus OH 43201",
    "addr:housenumber":"1900",
    "addr:postcode":"43201",
    "addr:street":"N High St",
    "iso:country":"US",
    "sg:address":"1900 N High St",
    "sg:city":"Columbus",
    "sg:classifiers":[
        {
            "category":"Professional",
            "type":"Services"
        },
        {
            "category":"Shopping",
            "subcategory":"Music",
            "type":"Retail Goods"
        }
    ],
    "sg:phone":"+1 614 291 6133",
    "sg:postcode":"43201",
    "sg:province":"OH",
    "sg:tags":[
        "compact",
        "record",
        "disc",
        "tape"
    ],
    "wof:name":"Johnny Go's House O' Music",
    "wof:placetype":"venue"
},
  "geometry": {"coordinates":[-83.008205,40.001176],"type":"Point"}
}