{
  "type": "Feature",
  "properties": {
    "iso:country":"US",
    "sg:address":"2319 Middletown Eaton Rd",
    "sg:city":"Middletown",
    "sg:classifiers":[
        {
            "category":"Building & Trades",
            "subcategory":"Construction",
            "type":"Services"
        }
    ],
    "sg:phone":"+1 513 422 9919",
    "sg:postcode":"45042",
    "sg:province":"OH",
    "sg:tags":[
        "concrete",
        "contractor"
    ],
    "wof:name":"Joe Back Construction",
    "wof:placetype":"venue"
},
  "geometry": {"coordinates":[-84.476177,39.54],"type":"Point"}
}