{
  "type": "Feature",
  "properties": {
    "iso:country":"US",
    "sg:address":"6280 Sawmill Rd",
    "sg:city":"Dublin",
    "sg:classifiers":[
        {
            "category":"Shopping",
            "subcategory":"Jewelry",
            "type":"Retail Goods"
        }
    ],
    "sg:phone":"+1 614 336 4545",
    "sg:postcode":"43017",
    "sg:province":"OH",
    "sg:tags":[
        "precious",
        "mfg",
        "metal",
        "jeweler"
    ],
    "sg:website":"www.diamondcellar.com",
    "wof:name":"Diamond Cellar The",
    "wof:placetype":"venue"
},
  "geometry": {"coordinates":[-83.091527,40.094826],"type":"Point"}
}