{
  "type": "Feature",
  "properties": {
    "addr:full": "1436 E 36th St Cleveland OH 44114",
    "addr:housenumber": "1436",
    "addr:postcode": "44114",
    "addr:street": "E 36Th St",
    "iso:country": "US",
    "sg:address": "1436 E 36th St",
    "sg:city": "Cleveland",
    "sg:classifiers": [
      {
        "category": "Wholesale",
        "subcategory": "Vending Machines",
        "type": "Manufacturing \u0026 Wholesale Goods"
      }
    ],
    "sg:phone": "+1 216 361 3333",
    "sg:postcode": "44114",
    "sg:province": "OH",
    "sg:tags": [
      "food",
      "snack",
      "candy"
    ],
    "wof:name": "Vending Services",
    "wof:placetype": "venue"
  },
  "geometry": {"coordinates":[-81.666817,41.514031],"type":"Point"}
}
