{
  "type": "Feature",
  "properties": {
    "addr:full": "304 Monroe St Conneaut OH 44030",
    "addr:housenumber": "304",
    "addr:postcode": "44030",
    "addr:street": "Monroe St",
    "iso:country": "US",
    "sg:address": "304 Monroe St",
    "sg:city": "Conneaut",
    "sg:classifiers": [
      {
        "category": "Shopping",
        "subcategory": "Florist",
        "type": "Retail Goods"
      }
    ],
    "sg:phone": "+1 440 593 2240",
    "sg:postcode": "44030",
    "sg:province": "OH",
    "wof:name": "Frew \u0026 Jackson Florists",
    "wof:placetype": "venue"
  },
  "geometry": {"coordinates":[-80.557514,41.943318],"type":"Point"}
}
