{
  "type": "Feature",
  "properties": {
    "iso:country":"US",
    "sg:address":"456 Main St",
    "sg:city":"Steubenville",
    "sg:classifiers":[
        {
            "category":"Shopping",
            "subcategory":"Gifts & Souvenirs",
            "type":"Retail Goods"
        }
    ],
    "sg:phone":"+1 740 266 7570",
    "sg:postcode":"43953",
    "sg:province":"OH",
    "wof:name":"Sweets N Treats & More",
    "wof:placetype":"venue"
},
  "geometry": {"coordinates":[-80.694862,40.374628],"type":"Point"}
}