{
  "type": "Feature",
  "properties": {
    "addr:full": "6392 Monroe St Sylvania OH 43560",
    "addr:housenumber": "6392",
    "addr:postcode": "43560",
    "addr:street": "Monroe St",
    "iso:country": "US",
    "sg:address": "6392 Monroe St",
    "sg:city": "Sylvania",
    "sg:classifiers": [
      {
        "category": "Banks \u0026 Credit Unions",
        "subcategory": "Bank",
        "type": "Services"
      }
    ],
    "sg:phone": "+1 419 882 1740",
    "sg:postcode": "43560",
    "sg:province": "OH",
    "sg:tags": [
      "national",
      "commercial"
    ],
    "wof:name": "National City Bank",
    "wof:placetype": "venue"
  },
  "geometry": {"coordinates":[-83.695151,41.715434],"type":"Point"}
}
