{
  "type": "Feature",
  "properties": {
    "addr:full": "438 Hickory St West Union OH 45693",
    "addr:housenumber": "438",
    "addr:postcode": "45693",
    "addr:street": "Hickory St",
    "iso:country": "US",
    "sg:address": "438 Hickory St",
    "sg:city": "West Union",
    "sg:classifiers": [
      {
        "category": "Building \u0026 Trades",
        "subcategory": "Landscaping Services",
        "type": "Services"
      }
    ],
    "sg:phone": "+1 937 544 5781",
    "sg:postcode": "45693",
    "sg:province": "OH",
    "sg:tags": [
      "landscape",
      "contractor"
    ],
    "wof:name": "Scenic Design Landscaping",
    "wof:placetype": "venue"
  },
  "geometry": {"coordinates":[-83.541411,38.797119],"type":"Point"}
}
