{
  "type": "Feature",
  "properties": {
    "iso:country":"US",
    "sg:address":"200 Industrial Pkwy",
    "sg:city":"Chagrin Falls",
    "sg:classifiers":[
        {
            "category":"Education",
            "subcategory":"School",
            "type":"Public Place"
        }
    ],
    "sg:phone":"+1 440 247 4639",
    "sg:postcode":"44022",
    "sg:province":"OH",
    "wof:name":"St Joan of ARC Special Servs",
    "wof:placetype":"venue"
},
  "geometry": {"coordinates":[-81.371363,41.424742],"type":"Point"}
}