{
  "type": "Feature",
  "properties": {
    "addr:full":"1619 Mardon Dr Dayton OH 45432",
    "addr:housenumber":"1619",
    "addr:postcode":"45432",
    "addr:street":"Mardon Dr",
    "iso:country":"US",
    "sg:address":"1619 Mardon Dr",
    "sg:city":"Dayton",
    "sg:classifiers":[
        {
            "category":"Building & Trades",
            "subcategory":"Construction",
            "type":"Services"
        }
    ],
    "sg:phone":"+1 937 320 6200",
    "sg:postcode":"45432",
    "sg:province":"OH",
    "sg:tags":[
        "fire",
        "restoration",
        "damage"
    ],
    "wof:name":"Finer Services Inc",
    "wof:placetype":"venue"
},
  "geometry": {"coordinates":[-84.088122,39.738962],"type":"Point"}
}