{
  "type": "Feature",
  "properties": {
    "addr:full": "3629 Hummingbird Hill Dr Youngstown OH 44514",
    "addr:housenumber": "3629",
    "addr:postcode": "44514",
    "addr:street": "Hummingbird Hill Dr",
    "iso:country": "US",
    "sg:address": "3629 Hummingbird Hill Dr",
    "sg:city": "Youngstown",
    "sg:classifiers": [
      {
        "category": "Professional",
        "subcategory": "Art Services",
        "type": "Services"
      }
    ],
    "sg:phone": "+1 330 757 9608",
    "sg:postcode": "44514",
    "sg:province": "OH",
    "sg:tags": [
      "artist"
    ],
    "wof:name": "Art Department",
    "wof:placetype": "venue"
  },
  "geometry": {"coordinates":[-80.589372,40.999266],"type":"Point"}
}
