{
  "type": "Feature",
  "properties": {
    "addr:full":"319 Pearl St Jackson OH 45640",
    "addr:housenumber":"319",
    "addr:postcode":"45640",
    "addr:street":"Pearl St",
    "iso:country":"US",
    "sg:address":"319 Pearl St",
    "sg:city":"Jackson",
    "sg:classifiers":[
        {
            "category":"Building & Trades",
            "subcategory":"Construction",
            "type":"Services"
        }
    ],
    "sg:phone":"+1 740 286 3782",
    "sg:postcode":"45640",
    "sg:province":"OH",
    "sg:tags":[
        "house"
    ],
    "wof:name":"Loomis Home Improvement",
    "wof:placetype":"venue"
},
  "geometry": {"coordinates":[-82.63664199999999,39.04989],"type":"Point"}
}