{
  "type": "Feature",
  "properties": {
    "addr:full": "809 Steubenville Ave Cambridge OH 43725",
    "addr:housenumber": "809",
    "addr:postcode": "43725",
    "addr:street": "Steubenville Ave",
    "iso:country": "US",
    "sg:address": "809 Steubenville Ave",
    "sg:city": "Cambridge",
    "sg:classifiers": [
      {
        "category": "Banks \u0026 Credit Unions",
        "subcategory": "Investment Brokerage",
        "type": "Services"
      }
    ],
    "sg:phone": "+1 740 439 6641",
    "sg:postcode": "43725",
    "sg:province": "OH",
    "sg:tags": [
      "stock",
      "bond"
    ],
    "wof:name": "Edward Jones Co",
    "wof:placetype": "venue"
  },
  "geometry": {"coordinates":[-81.589967,40.026206],"type":"Point"}
}
