{
  "type": "Feature",
  "properties": {
    "addr:full": "515 Main St Bowerston OH 44695",
    "addr:housenumber": "515",
    "addr:postcode": "44695",
    "addr:street": "Main St",
    "iso:country": "US",
    "sg:address": "515 Main St",
    "sg:city": "Bowerston",
    "sg:classifiers": [
      {
        "category": "Wholesale",
        "subcategory": "Construction Materials",
        "type": "Manufacturing \u0026 Wholesale Goods"
      }
    ],
    "sg:phone": "+1 740 269 2921",
    "sg:postcode": "44695",
    "sg:province": "OH",
    "sg:tags": [
      "brick",
      "common",
      "face"
    ],
    "wof:name": "Bowerston Shale Co",
    "wof:placetype": "venue"
  },
  "geometry": {"coordinates":[-81.180932,40.422417],"type":"Point"}
}
