{
  "type": "Feature",
  "properties": {
    "addr:full": "12 Monterey Dr Fort Loramie OH 45845",
    "addr:housenumber": "12",
    "addr:postcode": "45845",
    "addr:street": "Monterey Dr",
    "iso:country": "US",
    "sg:address": "12 Monterey Dr",
    "sg:city": "Fort Loramie",
    "sg:classifiers": [
      {
        "category": "Real Estate",
        "subcategory": "Real Estate Operator",
        "type": "Services"
      }
    ],
    "sg:phone": "+1 937 295 2634",
    "sg:postcode": "45845",
    "sg:province": "OH",
    "sg:tags": [
      "property",
      "lessor"
    ],
    "wof:name": "Richard Hilgefort",
    "wof:placetype": "venue"
  },
  "geometry": {"coordinates":[-84.367762,40.348507],"type":"Point"}
}
