{
  "type": "Feature",
  "properties": {
    "addr:full":"4007 Bach Buxton Rd Amelia OH 45102",
    "addr:postcode":"4007;45102",
    "addr:street":"Buxton Rd",
    "iso:country":"US",
    "sg:address":"4007 Bach Buxton Rd",
    "sg:city":"Amelia",
    "sg:classifiers":[
        {
            "category":"Professional",
            "subcategory":"Lawyer & Legal Services",
            "type":"Services"
        }
    ],
    "sg:phone":"+1 513 721 7522",
    "sg:postcode":"45102",
    "sg:province":"OH",
    "sg:tags":[
        "attorney"
    ],
    "wof:name":"Law Offices",
    "wof:placetype":"venue"
},
  "geometry": {"coordinates":[-84.245368,39.065789],"type":"Point"}
}