{
  "type": "Feature",
  "properties": {
    "addr:full": "136 S Keowee St Dayton OH 45410",
    "addr:housenumber": "136",
    "addr:postcode": "45410",
    "addr:street": "S Keowee St",
    "iso:country": "US",
    "sg:address": "136 S Keowee St",
    "sg:city": "Dayton",
    "sg:classifiers": [
      {
        "category": "Manufacturing",
        "subcategory": "Rubber \u0026 Plastics",
        "type": "Manufacturing \u0026 Wholesale Goods"
      },
      {
        "category": "Organizations",
        "subcategory": "Professional Association",
        "type": "Services"
      }
    ],
    "sg:phone": "+1 937 222 2462",
    "sg:postcode": "45410",
    "sg:province": "OH",
    "sg:tags": [
      "business"
    ],
    "sg:website": "www.cellulose.org",
    "wof:name": "Cellulose Insulation Mfrs Assn",
    "wof:placetype": "venue"
  },
  "geometry": {"coordinates":[-84.177581,39.76],"type":"Point"}
}
