{
  "type": "Feature",
  "properties": {
    "addr:full":"9500 Le Saint Dr Fairfield OH 45014",
    "addr:postcode":"9500;45014",
    "addr:street":"Le Saint Dr",
    "iso:country":"US",
    "sg:address":"9500 Le Saint Dr",
    "sg:city":"Fairfield",
    "sg:classifiers":[
        {
            "category":"Freight",
            "type":"Transportation"
        }
    ],
    "sg:phone":"+1 513 874 0034",
    "sg:postcode":"45014",
    "sg:province":"OH",
    "sg:tags":[
        "trucking"
    ],
    "wof:name":"Dollison Media Svc Inc",
    "wof:placetype":"venue"
},
  "geometry": {"coordinates":[-84.478486,39.320344],"type":"Point"}
}