{
  "type": "Feature",
  "properties": {
    "iso:country":"US",
    "sg:address":"6450 Poe Ave",
    "sg:city":"Dayton",
    "sg:classifiers":[
        {
            "category":"Insurance",
            "subcategory":"Insurance Agent",
            "type":"Services"
        }
    ],
    "sg:phone":"+1 937 898 4899",
    "sg:postcode":"45414",
    "sg:province":"OH",
    "wof:name":"Western Southern Life Insur",
    "wof:placetype":"venue"
},
  "geometry": {"coordinates":[-84.189172,39.836112],"type":"Point"}
}