{
  "type": "Feature",
  "properties": {
    "iso:country":"US",
    "sg:address":"2700 Columbus Ave",
    "sg:city":"Sandusky",
    "sg:classifiers":[
        {
            "category":"Government",
            "subcategory":"Office",
            "type":"Public Place"
        }
    ],
    "sg:phone":"+1 419 627 7717",
    "sg:postcode":"44870",
    "sg:province":"OH",
    "wof:name":"Equipment Superintendent",
    "wof:placetype":"venue"
},
  "geometry": {"coordinates":[-82.695741,41.429047],"type":"Point"}
}