{
  "type": "Feature",
  "properties": {
    "addr:full":"1480 Cederwood Dr Westlake OH 44145",
    "addr:housenumber":"1480",
    "addr:postcode":"44145",
    "addr:street":"Cederwood Dr",
    "iso:country":"US",
    "sg:address":"1480 Cederwood Dr",
    "sg:city":"Westlake",
    "sg:classifiers":[
        {
            "category":"Shopping",
            "subcategory":"Discount & Variety Stores",
            "type":"Retail Goods"
        }
    ],
    "sg:phone":"+1 440 871 6717",
    "sg:postcode":"44145",
    "sg:province":"OH",
    "wof:name":"Two Palms Company",
    "wof:placetype":"venue"
},
  "geometry": {"coordinates":[-81.95790599999999,41.467941],"type":"Point"}
}