{
  "type": "Feature",
  "properties": {
    "addr:full":"3266 S High St Columbus OH 43207",
    "addr:housenumber":"3266",
    "addr:postcode":"43207",
    "addr:street":"S High St",
    "iso:country":"US",
    "sg:address":"3266 S High St",
    "sg:city":"Columbus",
    "sg:classifiers":[
        {
            "category":"Restaurant",
            "type":"Food & Drink"
        }
    ],
    "sg:menulink":"http://www.allmenus.com/oh/columbus/19454-pjs-pizza/menu/",
    "sg:phone":"+1 614 497 2727",
    "sg:postcode":"43207",
    "sg:province":"OH",
    "sg:tags":[
        "italian"
    ],
    "wof:name":"PJ's Pizza",
    "wof:placetype":"venue"
},
  "geometry": {"coordinates":[-82.995368,39.895336],"type":"Point"}
}