{
  "type": "Feature",
  "properties": {
    "iso:country":"US",
    "sg:address":"2024 E Manhattan Blvd",
    "sg:city":"Toledo",
    "sg:classifiers":[
        {
            "category":"Retail",
            "subcategory":"Auto Rental",
            "type":"Services"
        }
    ],
    "sg:phone":"+1 419 729 9791",
    "sg:postcode":"43608",
    "sg:province":"OH",
    "sg:tags":[
        "renting",
        "truck",
        "leasing"
    ],
    "wof:name":"Ryder",
    "wof:placetype":"venue"
},
  "geometry": {"coordinates":[-83.51199200000001,41.687648],"type":"Point"}
}