{
  "type": "Feature",
  "properties": {
    "addr:full": "2024 E Manhattan Blvd Toledo OH 43608",
    "addr:housenumber": "2024",
    "addr:postcode": "43608",
    "addr:street": "E Manhattan Blvd",
    "iso:country": "US",
    "sg:address": "2024 E Manhattan Blvd",
    "sg:city": "Toledo",
    "sg:classifiers": [
      {
        "category": "Retail",
        "subcategory": "Auto Rental",
        "type": "Services"
      }
    ],
    "sg:phone": "+1 419 729 9791",
    "sg:postcode": "43608",
    "sg:province": "OH",
    "sg:tags": [
      "renting",
      "truck",
      "leasing"
    ],
    "wof:name": "Ryder",
    "wof:placetype": "venue"
  },
  "geometry": {"coordinates":[-83.511992,41.687648],"type":"Point"}
}
