{
  "type": "Feature",
  "properties": {
    "iso:country":"US",
    "sg:address":"17015 Lorain Ave",
    "sg:city":"Cleveland",
    "sg:classifiers":[
        {
            "category":"Shopping",
            "type":"Retail Goods"
        }
    ],
    "sg:phone":"+1 216 671 7500",
    "sg:postcode":"44111",
    "sg:province":"OH",
    "sg:tags":[
        "medical",
        "durable",
        "equipment",
        "therapy",
        "home",
        "support",
        "se"
    ],
    "wof:name":"Hastings Home Health Care Ctr",
    "wof:placetype":"venue"
},
  "geometry": {"coordinates":[-81.815825,41.450294],"type":"Point"}
}