{
  "type": "Feature",
  "properties": {
    "iso:country":"US",
    "sg:address":"250 W Court St",
    "sg:city":"Cincinnati",
    "sg:classifiers":[
        {
            "category":"Banks & Credit Unions",
            "subcategory":"Investment Brokerage",
            "type":"Services"
        }
    ],
    "sg:phone":"+1 513 784 1600",
    "sg:postcode":"45202",
    "sg:province":"OH",
    "sg:tags":[
        "consultant",
        "planning",
        "financial"
    ],
    "wof:name":"Joseph Wilson",
    "wof:placetype":"venue"
},
  "geometry": {"coordinates":[-84.518659,39.105705],"type":"Point"}
}