{
  "type": "Feature",
  "properties": {
    "addr:full": "990 S Sunbury Rd Westerville OH 43081",
    "addr:housenumber": "990",
    "addr:postcode": "43081",
    "addr:street": "S Sunbury Rd",
    "iso:country": "US",
    "sg:address": "990 S Sunbury Rd",
    "sg:city": "Westerville",
    "sg:classifiers": [
      {
        "category": "Restaurant",
        "type": "Food \u0026 Drink"
      }
    ],
    "sg:phone": "+1 614 899 1100",
    "sg:postcode": "43081",
    "sg:province": "OH",
    "wof:name": "Minico's Pizza Restaurant",
    "wof:placetype": "venue"
  },
  "geometry": {"coordinates":[-82.888764,40.100491],"type":"Point"}
}
