{
  "type": "Feature",
  "properties": {
    "iso:country":"US",
    "sg:address":"2941 Haverhill St",
    "sg:city":"Springfield",
    "sg:classifiers":[
        {
            "category":"Organizations",
            "subcategory":"Religious Organization",
            "type":"Services"
        }
    ],
    "sg:phone":"+1 937 399 0687",
    "sg:postcode":"45503",
    "sg:province":"OH",
    "sg:tags":[
        "clergy"
    ],
    "wof:name":"Dean A Elam",
    "wof:placetype":"venue"
},
  "geometry": {"coordinates":[-83.776746,39.96156],"type":"Point"}
}