{
  "type": "Feature",
  "properties": {
    "addr:full": "1931 Larrick Rd Sabina OH 45169",
    "addr:housenumber": "1931",
    "addr:postcode": "45169",
    "addr:street": "Larrick Rd",
    "iso:country": "US",
    "sg:address": "1931 Larrick Rd",
    "sg:city": "Sabina",
    "sg:classifiers": [
      {
        "category": "Restaurant",
        "type": "Food \u0026 Drink"
      }
    ],
    "sg:phone": "+1 937 584 2957",
    "sg:postcode": "45169",
    "sg:province": "OH",
    "sg:tags": [
      "eating"
    ],
    "wof:name": "ME \u0026 My Gang Catering",
    "wof:placetype": "venue"
  },
  "geometry": {"coordinates":[-83.625806,39.40246],"type":"Point"}
}
