{
  "type": "Feature",
  "properties": {
    "iso:country":"US",
    "sg:address":"1931 Larrick Rd",
    "sg:city":"Sabina",
    "sg:classifiers":[
        {
            "category":"Restaurant",
            "type":"Food & Drink"
        }
    ],
    "sg:phone":"+1 937 584 2957",
    "sg:postcode":"45169",
    "sg:province":"OH",
    "sg:tags":[
        "eating"
    ],
    "wof:name":"ME & My Gang Catering",
    "wof:placetype":"venue"
},
  "geometry": {"coordinates":[-83.625806,39.40246],"type":"Point"}
}