{
  "type": "Feature",
  "properties": {
    "addr:full": "105 W Butler St Bryan OH 43506",
    "addr:housenumber": "105",
    "addr:postcode": "43506",
    "addr:street": "W Butler St",
    "iso:country": "US",
    "sg:address": "105 W Butler St",
    "sg:city": "Bryan",
    "sg:classifiers": [
      {
        "category": "Home \u0026 Garden",
        "subcategory": "Household Appliances",
        "type": "Retail Goods"
      }
    ],
    "sg:phone": "+1 419 636 8778",
    "sg:postcode": "43506",
    "sg:province": "OH",
    "wof:name": "Towns Appliances LLC",
    "wof:placetype": "venue"
  },
  "geometry": {"coordinates":[-84.551702,41.473214],"type":"Point"}
}
