{
  "type": "Feature",
  "properties": {
    "addr:full": "24 E Main St Versailles OH 45380",
    "addr:housenumber": "24",
    "addr:postcode": "45380",
    "addr:street": "E Main St",
    "iso:country": "US",
    "sg:address": "24 E Main St",
    "sg:city": "Versailles",
    "sg:classifiers": [
      {
        "category": "Personal",
        "type": "Services"
      },
      {
        "category": "Personal",
        "subcategory": "Beauty Salon",
        "type": "Services"
      }
    ],
    "sg:phone": "+1 937 526 3125",
    "sg:postcode": "45380",
    "sg:province": "OH",
    "wof:name": "Total Image Tanning \u0026 Hair Co",
    "wof:placetype": "venue"
  },
  "geometry": {"coordinates":[-84.483676,40.22257],"type":"Point"}
}
