{
  "type": "Feature",
  "properties": {
    "addr:full": "1 East Ave Monroe OH 45050",
    "addr:housenumber": "1",
    "addr:postcode": "45050",
    "addr:street": "East Ave",
    "iso:country": "US",
    "sg:address": "1 East Ave",
    "sg:city": "Monroe",
    "sg:classifiers": [
      {
        "category": "Banks \u0026 Credit Unions",
        "subcategory": "Bank",
        "type": "Services"
      }
    ],
    "sg:phone": "+1 513 425 8506",
    "sg:postcode": "45050",
    "sg:province": "OH",
    "wof:name": "Chase",
    "wof:placetype": "venue"
  },
  "geometry": {"coordinates":[-84.359843,39.444022],"type":"Point"}
}
