{
  "type": "Feature",
  "properties": {
    "addr:full": "4672 Cemetery Rd Hilliard OH 43026",
    "addr:housenumber": "4672",
    "addr:postcode": "43026",
    "addr:street": "Cemetery Rd",
    "iso:country": "US",
    "sg:address": "4672 Cemetery Rd",
    "sg:city": "Hilliard",
    "sg:classifiers": [
      {
        "category": "Cinema",
        "subcategory": "Movie Rental",
        "type": "Entertainment"
      }
    ],
    "sg:phone": "+1 614 921 8894",
    "sg:postcode": "43026",
    "sg:province": "OH",
    "sg:tags": [
      "leasing",
      "video",
      "disc",
      "tape"
    ],
    "wof:name": "Blockbuster Video",
    "wof:placetype": "venue"
  },
  "geometry": {"coordinates":[-83.136923,40.03209],"type":"Point"}
}
