{
  "type": "Feature",
  "properties": {
    "addr:full": "10632 Loveland Madeira Rd Loveland OH 45140",
    "addr:housenumber": "10632",
    "addr:postcode": "45140",
    "addr:street": "Loveland Madeira Rd",
    "iso:country": "US",
    "sg:address": "10632 Loveland Madeira Rd",
    "sg:city": "Loveland",
    "sg:classifiers": [
      {
        "category": "Education",
        "subcategory": "School",
        "type": "Public Place"
      }
    ],
    "sg:phone": "+1 513 583 1181",
    "sg:postcode": "45140",
    "sg:province": "OH",
    "wof:name": "Youthland Academy",
    "wof:placetype": "venue"
  },
  "geometry": {"coordinates":[-84.296213,39.252105],"type":"Point"}
}
