{
  "type": "Feature",
  "properties": {
    "addr:full": "3020 N McCord Rd Toledo OH 43615",
    "addr:housenumber": "3020",
    "addr:postcode": "43615",
    "addr:street": "N Mccord Rd",
    "iso:country": "US",
    "sg:address": "3020 N McCord Rd",
    "sg:city": "Toledo",
    "sg:classifiers": [
      {
        "category": "Health Services",
        "subcategory": "Medical Lab",
        "type": "Services"
      }
    ],
    "sg:phone": "+1 419 841 3097",
    "sg:postcode": "43615",
    "sg:province": "OH",
    "sg:tags": [
      "laboratory"
    ],
    "wof:name": "Mercy Integrated Laboratories",
    "wof:placetype": "venue"
  },
  "geometry": {"coordinates":[-83.702862,41.671773],"type":"Point"}
}
