{
  "type": "Feature",
  "properties": {
    "iso:country":"US",
    "sg:address":"4700 W Broad St",
    "sg:city":"Columbus",
    "sg:classifiers":[
        {
            "category":"Personal",
            "subcategory":"Beauty Salon",
            "type":"Services"
        }
    ],
    "sg:phone":"+1 614 870 7295",
    "sg:postcode":"43228",
    "sg:province":"OH",
    "sg:tags":[
        "shop"
    ],
    "sg:website":"www.greatclips.com",
    "wof:name":"Great Clips",
    "wof:placetype":"venue"
},
  "geometry": {"coordinates":[-83.126895,39.952449],"type":"Point"}
}