{
  "type": "Feature",
  "properties": {
    "iso:country":"US",
    "sg:address":"1290 S High St",
    "sg:city":"Columbus",
    "sg:classifiers":[
        {
            "category":"Food & Beverages",
            "subcategory":"Groceries & Convenience Stores",
            "type":"Retail Goods"
        }
    ],
    "sg:phone":"+1 614 444 1422",
    "sg:postcode":"43206",
    "sg:province":"OH",
    "wof:name":"High Stop Food Mart",
    "wof:placetype":"venue"
},
  "geometry": {"coordinates":[-82.996004,39.936369],"type":"Point"}
}