{
  "type": "Feature",
  "properties": {
    "addr:full":"526 W Wayne St Maumee OH 43537",
    "addr:housenumber":"526",
    "addr:postcode":"43537",
    "addr:street":"W Wayne St",
    "iso:country":"US",
    "sg:address":"526 W Wayne St",
    "sg:city":"Maumee",
    "sg:classifiers":[
        {
            "category":"Building & Trades",
            "subcategory":"Construction",
            "type":"Services"
        }
    ],
    "sg:phone":"+1 419 893 0709",
    "sg:postcode":"43537",
    "sg:province":"OH",
    "sg:tags":[
        "lessor",
        "general",
        "real estate",
        "contractor",
        "remodeling"
    ],
    "wof:name":"Tara Construction & Remodeling",
    "wof:placetype":"venue"
},
  "geometry": {"coordinates":[-83.661714,41.559394],"type":"Point"}
}