{
  "type": "Feature",
  "properties": {
    "iso:country":"US",
    "sg:address":"1300 Mote Dr",
    "sg:city":"Covington",
    "sg:classifiers":[
        {
            "category":"Real Estate",
            "subcategory":"Developer",
            "type":"Services"
        }
    ],
    "sg:phone":"+1 937 473 3142",
    "sg:postcode":"45318",
    "sg:province":"OH",
    "wof:name":"Brookston/Channel Properties",
    "wof:placetype":"venue"
},
  "geometry": {"coordinates":[-84.35410899999999,40.109489],"type":"Point"}
}