{
  "type": "Feature",
  "properties": {
    "addr:full": "1300 Mote Dr Covington OH 45318",
    "addr:housenumber": "1300",
    "addr:postcode": "45318",
    "addr:street": "Mote Dr",
    "iso:country": "US",
    "sg:address": "1300 Mote Dr",
    "sg:city": "Covington",
    "sg:classifiers": [
      {
        "category": "Real Estate",
        "subcategory": "Developer",
        "type": "Services"
      }
    ],
    "sg:phone": "+1 937 473 3142",
    "sg:postcode": "45318",
    "sg:province": "OH",
    "wof:name": "Brookston/Channel Properties",
    "wof:placetype": "venue"
  },
  "geometry": {"coordinates":[-84.354109,40.109489],"type":"Point"}
}
