{
  "type": "Feature",
  "properties": {
    "iso:country":"US",
    "sg:address":"8 Ballard St",
    "sg:city":"Jackson",
    "sg:classifiers":[
        {
            "category":"Shopping",
            "subcategory":"Music",
            "type":"Retail Goods"
        }
    ],
    "sg:phone":"+1 740 286 7135",
    "sg:postcode":"45693",
    "sg:province":"OH",
    "wof:name":"Manchild Records LLC",
    "wof:placetype":"venue"
},
  "geometry": {"coordinates":[-83.526793,38.80477],"type":"Point"}
}