{
  "type": "Feature",
  "properties": {
    "addr:full": "9220 Portland Rd Castalia OH 44824",
    "addr:housenumber": "9220",
    "addr:postcode": "44824",
    "addr:street": "Portland Rd",
    "iso:country": "US",
    "sg:address": "9220 Portland Rd",
    "sg:city": "Castalia",
    "sg:classifiers": [
      {
        "category": "Mining \u0026 Drilling",
        "type": "Manufacturing \u0026 Wholesale Goods"
      }
    ],
    "sg:phone": "+1 419 483 4390",
    "sg:postcode": "44824",
    "sg:province": "OH",
    "sg:tags": [
      "mfg",
      "product",
      "limestone",
      "lime"
    ],
    "wof:name": "Sandusky Crushed Stone Co",
    "wof:placetype": "venue"
  },
  "geometry": {"coordinates":[-82.792413,41.342529],"type":"Point"}
}
