{
  "type": "Feature",
  "properties": {
    "addr:full": "3525 Centurion Dr Cincinnati OH 45211",
    "addr:housenumber": "3525",
    "addr:postcode": "45211",
    "addr:street": "Centurion Dr",
    "iso:country": "US",
    "sg:address": "3525 Centurion Dr",
    "sg:city": "Cincinnati",
    "sg:classifiers": [
      {
        "category": "Professional",
        "subcategory": "Management \u0026 Consulting",
        "type": "Services"
      }
    ],
    "sg:phone": "+1 513 922 3400",
    "sg:postcode": "45211",
    "sg:province": "OH",
    "sg:tags": [
      "retail",
      "direct",
      "sales"
    ],
    "wof:name": "Spring Water Distributors",
    "wof:placetype": "venue"
  },
  "geometry": {"coordinates":[-84.608294,39.171329],"type":"Point"}
}
