{
  "type": "Feature",
  "properties": {
    "addr:full":"2701 Dutch Hollow Rd Elida OH 45807",
    "addr:housenumber":"2701",
    "addr:postcode":"45807",
    "addr:street":"Dutch Hollow Rd",
    "iso:country":"US",
    "sg:address":"2701 Dutch Hollow Rd",
    "sg:city":"Elida",
    "sg:classifiers":[
        {
            "category":"Organizations",
            "subcategory":"Religious Organization",
            "type":"Services"
        }
    ],
    "sg:phone":"+1 419 339 3339",
    "sg:postcode":"45807",
    "sg:province":"OH",
    "sg:tags":[
        "church"
    ],
    "sg:website":"www.cornerstone.org",
    "wof:name":"Cornerstone Baptist Church",
    "wof:placetype":"venue"
},
  "geometry": {"coordinates":[-84.203542,40.77865],"type":"Point"}
}