{
  "type": "Feature",
  "properties": {
    "addr:full": "2901 Fishworm Rd Cedarville OH 45314",
    "addr:housenumber": "2901",
    "addr:postcode": "45314",
    "addr:street": "Fishworm Rd",
    "iso:country": "US",
    "sg:address": "2901 Fishworm Rd",
    "sg:city": "Cedarville",
    "sg:phone": "+1 937 766 9820",
    "sg:postcode": "45314",
    "sg:province": "OH",
    "sg:tags": [
      "farm",
      "wheat"
    ],
    "wof:name": "Andrew Conover",
    "wof:placetype": "venue"
  },
  "geometry": {"coordinates":[-83.791208,39.761782],"type":"Point"}
}
