{
  "type": "Feature",
  "properties": {
    "addr:full": "2529 Essex Pl Cincinnati OH 45206",
    "addr:housenumber": "2529",
    "addr:postcode": "45206",
    "addr:street": "Essex Pl",
    "iso:country": "US",
    "sg:address": "2529 Essex Pl",
    "sg:city": "Cincinnati",
    "sg:classifiers": [
      {
        "category": "Organizations",
        "subcategory": "Religious Organization",
        "type": "Services"
      }
    ],
    "sg:phone": "+1 513 281 1555",
    "sg:postcode": "45206",
    "sg:province": "OH",
    "sg:tags": [
      "church"
    ],
    "wof:name": "Church-God \u0026 Saints-Christ",
    "wof:placetype": "venue"
  },
  "geometry": {"coordinates":[-84.498351,39.127401],"type":"Point"}
}
