{
  "type": "Feature",
  "properties": {
    "iso:country":"US",
    "sg:address":"2846 Millbank Row",
    "sg:city":"Maineville",
    "sg:classifiers":[
        {
            "category":"Wholesale",
            "subcategory":"Toys & Hobbies",
            "type":"Manufacturing & Wholesale Goods"
        }
    ],
    "sg:phone":"+1 513 754 5630",
    "sg:postcode":"45039",
    "sg:province":"OH",
    "wof:name":"Monduce Inc",
    "wof:placetype":"venue"
},
  "geometry": {"coordinates":[-84.272701,39.309311],"type":"Point"}
}