{
  "type": "Feature",
  "properties": {
    "iso:country":"US",
    "sg:address":"1691 E 31st St",
    "sg:city":"Lorain",
    "sg:classifiers":[
        {
            "category":"Organizations",
            "subcategory":"Religious Organization",
            "type":"Services"
        }
    ],
    "sg:phone":"+1 440 277 1919",
    "sg:postcode":"44055",
    "sg:province":"OH",
    "sg:tags":[
        "clergy"
    ],
    "wof:name":"Zoltan D Szucs",
    "wof:placetype":"venue"
},
  "geometry": {"coordinates":[-82.14194000000001,41.442193],"type":"Point"}
}