{
  "type": "Feature",
  "properties": {
    "addr:full":"21628 Twp Rd 258 Newcomerstown OH 43832",
    "addr:postcode":"21628;43832",
    "addr:street":"Twp Rd 258",
    "iso:country":"US",
    "sg:address":"21628 Twp Rd 258",
    "sg:city":"Newcomerstown",
    "sg:classifiers":[
        {
            "category":"Real Estate",
            "subcategory":"Developer",
            "type":"Services"
        }
    ],
    "sg:phone":"+1 740 498 6943",
    "sg:postcode":"43832",
    "sg:province":"OH",
    "sg:tags":[
        "cemetery"
    ],
    "wof:name":"Newcomerstown Cemeteries",
    "wof:placetype":"venue"
},
  "geometry": {"coordinates":[-81.64214200000001,40.262307],"type":"Point"}
}