{
  "type": "Feature",
  "properties": {
    "iso:country":"US",
    "sg:address":"42994 Six Points Rd",
    "sg:city":"Laings",
    "sg:classifiers":[
        {
            "category":"Organizations",
            "subcategory":"Religious Organization",
            "type":"Services"
        }
    ],
    "sg:phone":"+1 740 472 5508",
    "sg:postcode":"43752",
    "sg:province":"OH",
    "sg:tags":[
        "church"
    ],
    "wof:name":"Church Of Christ",
    "wof:placetype":"venue"
},
  "geometry": {"coordinates":[-81.00868699999999,39.717015],"type":"Point"}
}