{
  "type": "Feature",
  "properties": {
    "addr:full":"5649 Rd C Leipsic OH 45856",
    "addr:housenumber":"5649",
    "addr:postcode":"45856",
    "addr:street":"Rd C Leipsic",
    "iso:country":"US",
    "sg:address":"5649 Rd C",
    "sg:city":"Leipsic",
    "sg:classifiers":[
        {
            "category":"Autos & Motor Vehicles",
            "subcategory":"Automobile Sales",
            "type":"Retail Goods"
        }
    ],
    "sg:phone":"+1 419 943 2960",
    "sg:postcode":"45856",
    "sg:province":"OH",
    "sg:tags":[
        "used"
    ],
    "wof:name":"Bobs Vehicle Sales",
    "wof:placetype":"venue"
},
  "geometry": {"coordinates":[-83.966266,41.138254],"type":"Point"}
}