{
  "type": "Feature",
  "properties": {
    "addr:full": "13690 Broad St SW Pataskala OH 43062",
    "addr:housenumber": "13690",
    "addr:postcode": "43062",
    "addr:street": "Broad St Sw",
    "iso:country": "US",
    "sg:address": "13690 Broad St SW",
    "sg:city": "Pataskala",
    "sg:classifiers": [
      {
        "category": "Shopping",
        "subcategory": "Discount \u0026 Variety Stores",
        "type": "Retail Goods"
      },
      {
        "category": "Professional",
        "subcategory": "Management \u0026 Consulting",
        "type": "Services"
      }
    ],
    "sg:phone": "+1 740 927 3586",
    "sg:postcode": "43062",
    "sg:province": "OH",
    "sg:tags": [
      "bid",
      "reporting",
      "merchandise",
      "business",
      "general"
    ],
    "wof:name": "Alpha-Omega Co",
    "wof:placetype": "venue"
  },
  "geometry": {"coordinates":[-82.744125,39.991631],"type":"Point"}
}
