{
  "type": "Feature",
  "properties": {
    "iso:country":"US",
    "sg:address":"277 Calhoun St",
    "sg:city":"Cincinnati",
    "sg:classifiers":[
        {
            "category":"Restaurant",
            "type":"Food & Drink"
        }
    ],
    "sg:phone":"+1 513 221 3044",
    "sg:postcode":"45219",
    "sg:province":"OH",
    "wof:name":"In The Woods Tavern",
    "wof:placetype":"venue"
},
  "geometry": {"coordinates":[-84.516486,39.128199],"type":"Point"}
}