{
  "type": "Feature",
  "properties": {
    "addr:full": "154 Garden St Cleveland OH 44146",
    "addr:housenumber": "154",
    "addr:postcode": "44146",
    "addr:street": "Garden St",
    "iso:country": "US",
    "sg:address": "154 Garden St",
    "sg:city": "Cleveland",
    "sg:classifiers": [
      {
        "category": "Shopping",
        "subcategory": "Gifts \u0026 Souvenirs",
        "type": "Retail Goods"
      }
    ],
    "sg:phone": "+1 440 232 1564",
    "sg:postcode": "44146",
    "sg:province": "OH",
    "sg:tags": [
      "basket",
      "parcel"
    ],
    "wof:name": "Annastacia S Kavanagh Gifts",
    "wof:placetype": "venue"
  },
  "geometry": {"coordinates":[-81.5344,41.396467],"type":"Point"}
}
