{
  "type": "Feature",
  "properties": {
    "iso:country":"US",
    "sg:address":"154 Garden St",
    "sg:city":"Cleveland",
    "sg:classifiers":[
        {
            "category":"Shopping",
            "subcategory":"Gifts & Souvenirs",
            "type":"Retail Goods"
        }
    ],
    "sg:phone":"+1 440 232 1564",
    "sg:postcode":"44146",
    "sg:province":"OH",
    "sg:tags":[
        "basket",
        "parcel"
    ],
    "wof:name":"Annastacia S Kavanagh Gifts",
    "wof:placetype":"venue"
},
  "geometry": {"coordinates":[-81.53440000000001,41.396467],"type":"Point"}
}