{
  "type": "Feature",
  "properties": {
    "addr:full": "112 Downs Ave Urbana OH 43078",
    "addr:housenumber": "112",
    "addr:postcode": "43078",
    "addr:street": "Downs Ave",
    "iso:country": "US",
    "sg:address": "112 Downs Ave",
    "sg:city": "Urbana",
    "sg:classifiers": [
      {
        "category": "Recreation",
        "type": "Entertainment"
      }
    ],
    "sg:phone": "+1 937 484 4840",
    "sg:postcode": "43078",
    "sg:province": "OH",
    "sg:tags": [
      "amusement"
    ],
    "wof:name": "MPG Motorsports LLC",
    "wof:placetype": "venue"
  },
  "geometry": {"coordinates":[-83.749826,40.121543],"type":"Point"}
}
