{
  "type": "Feature",
  "properties": {
    "iso:country":"US",
    "sg:address":"221 N Vandemark Rd",
    "sg:city":"Sidney",
    "sg:classifiers":[
        {
            "category":"Restaurant",
            "type":"Food & Drink"
        }
    ],
    "sg:menulink":"http://www.allmenus.com/oh/clinton/88795-applebees/menu/",
    "sg:phone":"+1 937 498 1833",
    "sg:postcode":"45365",
    "sg:province":"OH",
    "sg:tags":[
        "burger",
        "american",
        "sandwich",
        "soup"
    ],
    "wof:name":"Applebee's",
    "wof:placetype":"venue"
},
  "geometry": {"coordinates":[-84.187831,40.288259],"type":"Point"}
}