{
  "type": "Feature",
  "properties": {
    "addr:full":"3200 Linwood Ave Cincinnati OH 45226",
    "addr:housenumber":"3200",
    "addr:postcode":"45226",
    "addr:street":"Linwood Ave",
    "iso:country":"US",
    "sg:address":"3200 Linwood Ave",
    "sg:city":"Cincinnati",
    "sg:classifiers":[
        {
            "category":"Restaurant",
            "type":"Food & Drink"
        }
    ],
    "sg:phone":"+1 513 321 2540",
    "sg:postcode":"45226",
    "sg:province":"OH",
    "wof:name":"Lucy Blue",
    "wof:placetype":"venue"
},
  "geometry": {"coordinates":[-84.429979,39.127973],"type":"Point"}
}