{
  "type": "Feature",
  "properties": {
    "addr:full": "33 E North St Columbus OH 43085",
    "addr:housenumber": "33",
    "addr:postcode": "43085",
    "addr:street": "E North St",
    "iso:country": "US",
    "sg:address": "33 E North St",
    "sg:city": "Columbus",
    "sg:classifiers": [
      {
        "category": "Real Estate",
        "subcategory": "Real Estate Services",
        "type": "Services"
      }
    ],
    "sg:phone": "+1 614 841 2553",
    "sg:postcode": "43085",
    "sg:province": "OH",
    "sg:tags": [
      "company",
      "abstract",
      "title"
    ],
    "wof:name": "Pillar Title Agency",
    "wof:placetype": "venue"
  },
  "geometry": {"coordinates":[-83.016757,40.092821],"type":"Point"}
}
