{
  "type": "Feature",
  "properties": {
    "iso:country":"US",
    "sg:address":"581 E Market St",
    "sg:city":"Cadiz",
    "sg:classifiers":[
        {
            "category":"Personal",
            "subcategory":"Barber",
            "type":"Services"
        }
    ],
    "sg:phone":"+1 740 942 9001",
    "sg:postcode":"43907",
    "sg:province":"OH",
    "wof:name":"Hair Shack",
    "wof:placetype":"venue"
},
  "geometry": {"coordinates":[-80.989043,40.267309],"type":"Point"}
}