{
  "type": "Feature",
  "properties": {
    "addr:full": "855 W Main St Leipsic OH 45856",
    "addr:housenumber": "855",
    "addr:postcode": "45856",
    "addr:street": "W Main St",
    "iso:country": "US",
    "sg:address": "855 W Main St",
    "sg:city": "Leipsic",
    "sg:classifiers": [
      {
        "category": "Wholesale",
        "subcategory": "Hardware",
        "type": "Manufacturing \u0026 Wholesale Goods"
      }
    ],
    "sg:phone": "+1 419 423 2765",
    "sg:postcode": "45856",
    "sg:province": "OH",
    "sg:tags": [
      "fastener"
    ],
    "wof:name": "Village Incom Supply",
    "wof:placetype": "venue"
  },
  "geometry": {"coordinates":[-83.9966,41.101639],"type":"Point"}
}
