{
  "type": "Feature",
  "properties": {
    "iso:country":"US",
    "sg:address":"2894 E Main St",
    "sg:city":"Columbus",
    "sg:classifiers":[
        {
            "category":"Restaurant",
            "type":"Food & Drink"
        }
    ],
    "sg:phone":"+1 614 338 8800",
    "sg:postcode":"43209",
    "sg:province":"OH",
    "sg:website":"www.singlescolumbus.com",
    "wof:name":"Singles",
    "wof:placetype":"venue"
},
  "geometry": {"coordinates":[-82.92046499999999,39.956808],"type":"Point"}
}