{
  "type": "Feature",
  "properties": {
    "iso:country":"US",
    "sg:address":"2151 Colerain Ave",
    "sg:city":"Cincinnati",
    "sg:classifiers":[
        {
            "category":"Retail",
            "subcategory":"Laundry & Dry Cleaning",
            "type":"Services"
        }
    ],
    "sg:phone":"+1 513 241 5586",
    "sg:postcode":"45214",
    "sg:province":"OH",
    "sg:tags":[
        "cleaners"
    ],
    "wof:name":"Sam The Tailor",
    "wof:placetype":"venue"
},
  "geometry": {"coordinates":[-84.53274999999999,39.119933],"type":"Point"}
}