{
  "type": "Feature",
  "properties": {
    "addr:full": "2151 Colerain Ave Cincinnati OH 45214",
    "addr:housenumber": "2151",
    "addr:postcode": "45214",
    "addr:street": "Colerain Ave",
    "iso:country": "US",
    "sg:address": "2151 Colerain Ave",
    "sg:city": "Cincinnati",
    "sg:classifiers": [
      {
        "category": "Retail",
        "subcategory": "Laundry \u0026 Dry Cleaning",
        "type": "Services"
      }
    ],
    "sg:phone": "+1 513 241 5586",
    "sg:postcode": "45214",
    "sg:province": "OH",
    "sg:tags": [
      "cleaners"
    ],
    "wof:name": "Sam The Tailor",
    "wof:placetype": "venue"
  },
  "geometry": {"coordinates":[-84.53275,39.119933],"type":"Point"}
}
