{
  "type": "Feature",
  "properties": {
    "iso:country":"US",
    "sg:address":"705 Main St",
    "sg:city":"Dresden",
    "sg:classifiers":[
        {
            "category":"Shopping",
            "subcategory":"Gifts & Souvenirs",
            "type":"Retail Goods"
        }
    ],
    "sg:phone":"+1 740 754 4100",
    "sg:postcode":"43821",
    "sg:province":"OH",
    "sg:tags":[
        "shop"
    ],
    "wof:name":"Heart Of Dresden",
    "wof:placetype":"venue"
},
  "geometry": {"coordinates":[-82.011548,40.122245],"type":"Point"}
}