{
  "type": "Feature",
  "properties": {
    "addr:full":"2 S Main St Middletown OH 45044",
    "addr:housenumber":"2",
    "addr:postcode":"45044",
    "addr:street":"S Main St",
    "iso:country":"US",
    "sg:address":"2 S Main St",
    "sg:city":"Middletown",
    "sg:classifiers":[
        {
            "category":"Education",
            "subcategory":"School",
            "type":"Public Place"
        }
    ],
    "sg:phone":"+1 513 424 6110",
    "sg:postcode":"45044",
    "sg:province":"OH",
    "wof:name":"Middletown Preparatory An",
    "wof:placetype":"venue"
},
  "geometry": {"coordinates":[-84.405948,39.515815],"type":"Point"}
}