{
  "type": "Feature",
  "properties": {
    "addr:full": "3821 Blue Church Rd Sunbury OH 43074",
    "addr:housenumber": "3821",
    "addr:postcode": "43074",
    "addr:street": "Blue Church Rd",
    "iso:country": "US",
    "sg:address": "3821 Blue Church Rd",
    "sg:city": "Sunbury",
    "sg:classifiers": [
      {
        "category": "Wholesale",
        "subcategory": "Non-durable Goods",
        "type": "Manufacturing \u0026 Wholesale Goods"
      }
    ],
    "sg:phone": "+1 740 965 1444",
    "sg:postcode": "43074",
    "sg:province": "OH",
    "sg:tags": [
      "advertising"
    ],
    "wof:name": "Wizard Decal Installation",
    "wof:placetype": "venue"
  },
  "geometry": {"coordinates":[-82.866979,40.298863],"type":"Point"}
}
