{
  "type": "Feature",
  "properties": {
    "iso:country":"US",
    "sg:address":"1000 N High St",
    "sg:city":"Columbus",
    "sg:classifiers":[
        {
            "category":"Personal",
            "subcategory":"Beauty Salon",
            "type":"Services"
        }
    ],
    "sg:phone":"+1 614 781 1785",
    "sg:postcode":"43085",
    "sg:province":"OH",
    "sg:tags":[
        "shop"
    ],
    "wof:name":"Designs Of You",
    "wof:placetype":"venue"
},
  "geometry": {"coordinates":[-83.017718,40.094621],"type":"Point"}
}