{
  "type": "Feature",
  "properties": {
    "iso:country":"US",
    "sg:address":"106 Houston St SW",
    "sg:city":"Massillon",
    "sg:classifiers":[
        {
            "category":"Insurance",
            "subcategory":"Insurance Agent",
            "type":"Services"
        }
    ],
    "sg:phone":"+1 330 830 9167",
    "sg:postcode":"44647",
    "sg:province":"OH",
    "wof:name":"Primerica",
    "wof:placetype":"venue"
},
  "geometry": {"coordinates":[-81.530756,40.792969],"type":"Point"}
}