{
  "type": "Feature",
  "properties": {
    "addr:full":"15375 Brookpark Rd Cleveland OH 44142",
    "addr:housenumber":"15375",
    "addr:postcode":"44142",
    "addr:street":"Brookpark Rd",
    "iso:country":"US",
    "sg:address":"15375 Brookpark Rd",
    "sg:city":"Cleveland",
    "sg:classifiers":[
        {
            "category":"Retail",
            "subcategory":"Auto Repair",
            "type":"Services"
        }
    ],
    "sg:phone":"+1 216 267 3097",
    "sg:postcode":"44142",
    "sg:province":"OH",
    "sg:tags":[
        "body",
        "automobile",
        "painting"
    ],
    "wof:name":"George's Auto Body Shop",
    "wof:placetype":"venue"
},
  "geometry": {"coordinates":[-81.807784,41.418517],"type":"Point"}
}