{
  "type": "Feature",
  "properties": {
    "addr:full":"810 Burns St Mansfield OH 44903",
    "addr:housenumber":"810",
    "addr:postcode":"44903",
    "addr:street":"Burns St",
    "iso:country":"US",
    "sg:address":"810 Burns St",
    "sg:city":"Mansfield",
    "sg:classifiers":[
        {
            "category":"Wholesale",
            "subcategory":"Drugs",
            "type":"Manufacturing & Wholesale Goods"
        }
    ],
    "sg:phone":"+1 419 529 9729",
    "sg:postcode":"44903",
    "sg:province":"OH",
    "sg:tags":[
        "cosmetic"
    ],
    "wof:name":"Cheryl L Page Cosmetics",
    "wof:placetype":"venue"
},
  "geometry": {"coordinates":[-82.54621899999999,40.773473],"type":"Point"}
}