{
  "type": "Feature",
  "properties": {
    "iso:country":"US",
    "sg:address":"607 Northlawn Dr",
    "sg:city":"Youngstown",
    "sg:classifiers":[
        {
            "category":"Building & Trades",
            "subcategory":"Construction",
            "type":"Services"
        }
    ],
    "sg:phone":"+1 330 759 0254",
    "sg:postcode":"44505",
    "sg:province":"OH",
    "sg:tags":[
        "residential"
    ],
    "wof:name":"T Gutierrez Inc",
    "wof:placetype":"venue"
},
  "geometry": {"coordinates":[-80.650499,41.152867],"type":"Point"}
}