{
  "type": "Feature",
  "properties": {
    "iso:country":"US",
    "sg:address":"2023 W 87th St",
    "sg:city":"Cleveland",
    "sg:classifiers":[
        {
            "category":"Shopping",
            "subcategory":"Hobbies, Toys, & Games",
            "type":"Retail Goods"
        }
    ],
    "sg:phone":"+1 216 631 0683",
    "sg:postcode":"44102",
    "sg:province":"OH",
    "wof:name":"R P Toy",
    "wof:placetype":"venue"
},
  "geometry": {"coordinates":[-81.744123,41.474206],"type":"Point"}
}