{
  "type": "Feature",
  "properties": {
    "addr:full": "1066 Country Club Rd Columbus OH 43227",
    "addr:housenumber": "1066",
    "addr:postcode": "43227",
    "addr:street": "Country Club Rd",
    "iso:country": "US",
    "sg:address": "1066 Country Club Rd",
    "sg:city": "Columbus",
    "sg:classifiers": [
      {
        "category": "Organizations",
        "subcategory": "Religious Organization",
        "type": "Services"
      }
    ],
    "sg:phone": "+1 614 577 1227",
    "sg:postcode": "43227",
    "sg:province": "OH",
    "sg:tags": [
      "church"
    ],
    "wof:name": "Praise \u0026 Worship Deliverance",
    "wof:placetype": "venue"
  },
  "geometry": {"coordinates":[-82.867192,39.954645],"type":"Point"}
}
