{
  "type": "Feature",
  "properties": {
    "iso:country":"US",
    "sg:address":"3264 Cedarbrook Rd",
    "sg:city":"Cleveland",
    "sg:classifiers":[
        {
            "category":"Building & Trades",
            "subcategory":"Construction",
            "type":"Services"
        }
    ],
    "sg:phone":"+1 216 397 1460",
    "sg:postcode":"44118",
    "sg:province":"OH",
    "sg:tags":[
        "home"
    ],
    "wof:name":"Oxford Building & Restoration",
    "wof:placetype":"venue"
},
  "geometry": {"coordinates":[-81.562654,41.499534],"type":"Point"}
}