{
  "type": "Feature",
  "properties": {
    "addr:full":"409 Boardman Poland Rd Youngstown OH 44512",
    "addr:housenumber":"409",
    "addr:postcode":"44512",
    "addr:street":"Boardman Poland Rd",
    "iso:country":"US",
    "sg:address":"409 Boardman Poland Rd",
    "sg:city":"Youngstown",
    "sg:classifiers":[
        {
            "category":"Shopping",
            "subcategory":"Clothing, Apparel, & Fashions",
            "type":"Retail Goods"
        }
    ],
    "sg:phone":"+1 330 965 0087",
    "sg:postcode":"44512",
    "sg:province":"OH",
    "sg:tags":[
        "infant",
        "wear"
    ],
    "wof:name":"Zoodles Inc",
    "wof:placetype":"venue"
},
  "geometry": {"coordinates":[-80.64541199999999,41.024227],"type":"Point"}
}