{
  "type": "Feature",
  "properties": {
    "iso:country":"US",
    "sg:address":"457 S Reynolds Rd",
    "sg:city":"Toledo",
    "sg:classifiers":[
        {
            "category":"Personal",
            "subcategory":"Hair Removal",
            "type":"Services"
        },
        {
            "category":"Personal",
            "type":"Services"
        }
    ],
    "sg:phone":"+1 419 531 2227",
    "sg:postcode":"43615",
    "sg:province":"OH",
    "sg:tags":[
        "credit",
        "debt",
        "counseling"
    ],
    "wof:name":"Consumer Credit Counseling Svc",
    "wof:placetype":"venue"
},
  "geometry": {"coordinates":[-83.664428,41.631639],"type":"Point"}
}