{
  "type": "Feature",
  "properties": {
    "iso:country":"US",
    "sg:address":"22408 Twp Hwy 275",
    "sg:city":"Alvada",
    "sg:phone":"+1 419 894 6279",
    "sg:postcode":"44802",
    "sg:province":"OH",
    "sg:tags":[
        "farm",
        "corn",
        "soybean"
    ],
    "wof:name":"Tong Farms",
    "wof:placetype":"venue"
},
  "geometry": {"coordinates":[-83.439313,41.057466],"type":"Point"}
}