{
  "type": "Feature",
  "properties": {
    "iso:country":"US",
    "sg:address":"9254 Plainfield Rd",
    "sg:city":"Cincinnati",
    "sg:classifiers":[
        {
            "category":"Restaurant",
            "type":"Food & Drink"
        }
    ],
    "sg:menulink":"http://www.allmenus.com/oh/blue-ash/163741-skyline-chili/menu/",
    "sg:phone":"+1 513 793 3350",
    "sg:postcode":"45236",
    "sg:province":"OH",
    "sg:tags":[
        "mexican"
    ],
    "wof:name":"Skyline Chili",
    "wof:placetype":"venue"
},
  "geometry": {"coordinates":[-84.39429199999999,39.227608],"type":"Point"}
}