{
  "type": "Feature",
  "properties": {
    "addr:full": "795 W 5th Ave Columbus OH 43212",
    "addr:housenumber": "795",
    "addr:postcode": "43212",
    "addr:street": "W 5Th Ave",
    "iso:country": "US",
    "sg:address": "795 W 5th Ave",
    "sg:city": "Columbus",
    "sg:classifiers": [
      {
        "category": "Recreation",
        "type": "Entertainment"
      }
    ],
    "sg:phone": "+1 614 291 0049",
    "sg:postcode": "43212",
    "sg:province": "OH",
    "sg:tags": [
      "club",
      "private",
      "for",
      "man"
    ],
    "wof:name": "Club Columbus Inc",
    "wof:placetype": "venue"
  },
  "geometry": {"coordinates":[-83.025996,39.987776],"type":"Point"}
}
