{
  "type": "Feature",
  "properties": {
    "addr:full": "4465 State Rte 601 E Norwalk OH 44857",
    "addr:housenumber": "4465",
    "addr:postcode": "44857",
    "addr:street": "State Rte 601 E",
    "iso:country": "US",
    "sg:address": "4465 State Rte 601 E",
    "sg:city": "Norwalk",
    "sg:classifiers": [
      {
        "category": "Utilities",
        "subcategory": "Natural Gas",
        "type": "Services"
      }
    ],
    "sg:phone": "+1 419 660 0432",
    "sg:postcode": "44857",
    "sg:province": "OH",
    "sg:tags": [
      "company"
    ],
    "wof:name": "North Coast Gas Transmission",
    "wof:placetype": "venue"
  },
  "geometry": {"coordinates":[-82.553367,41.26318],"type":"Point"}
}
