{
  "type": "Feature",
  "properties": {
    "addr:full": "3029 N Wooster Ave Dover OH 44622",
    "addr:housenumber": "3029",
    "addr:postcode": "44622",
    "addr:street": "N Wooster Ave",
    "iso:country": "US",
    "sg:address": "3029 N Wooster Ave",
    "sg:city": "Dover",
    "sg:classifiers": [
      {
        "category": "Organizations",
        "subcategory": "Religious Organization",
        "type": "Services"
      }
    ],
    "sg:phone": "+1 330 364 3520",
    "sg:postcode": "44622",
    "sg:province": "OH",
    "sg:tags": [
      "church"
    ],
    "sg:website": "www.doverfcc.com",
    "wof:name": "First Christian Church",
    "wof:placetype": "venue"
  },
  "geometry": {"coordinates":[-81.49576,40.552408],"type":"Point"}
}
