{
  "type": "Feature",
  "properties": {
    "iso:country":"US",
    "sg:address":"13907 W Willard Rd",
    "sg:city":"Novelty",
    "sg:classifiers":[
        {
            "category":"Building & Trades",
            "subcategory":"Plumbing",
            "type":"Services"
        }
    ],
    "sg:phone":"+1 216 531 4238",
    "sg:postcode":"44072",
    "sg:province":"OH",
    "sg:tags":[
        "conditioning",
        "air",
        "system",
        "contractor"
    ],
    "wof:name":"Accell Air Systems",
    "wof:placetype":"venue"
},
  "geometry": {"coordinates":[-81.359533,41.485294],"type":"Point"}
}