{
  "type": "Feature",
  "properties": {
    "addr:full": "132 W North St Sidney OH 45365",
    "addr:housenumber": "132",
    "addr:postcode": "45365",
    "addr:street": "W North St",
    "iso:country": "US",
    "sg:address": "132 W North St",
    "sg:city": "Sidney",
    "sg:classifiers": [
      {
        "category": "Shopping",
        "type": "Retail Goods"
      }
    ],
    "sg:phone": "+1 937 492 5886",
    "sg:postcode": "45365",
    "sg:province": "OH",
    "sg:tags": [
      "merchandise"
    ],
    "wof:name": "Ginn Grain Co",
    "wof:placetype": "venue"
  },
  "geometry": {"coordinates":[-84.157839,40.28691],"type":"Point"}
}
