{
  "type": "Feature",
  "properties": {
    "iso:country":"US",
    "sg:address":"N Main St & E Washingt",
    "sg:city":"Chagrin Falls",
    "sg:classifiers":[
        {
            "category":"Autos & Motor Vehicles",
            "subcategory":"Fuel & Gas Station",
            "type":"Retail Goods"
        },
        {
            "category":"Retail",
            "subcategory":"Auto Repair",
            "type":"Services"
        }
    ],
    "sg:phone":"+1 440 247 6207",
    "sg:postcode":"44022",
    "sg:province":"OH",
    "wof:name":"Chagrin Bp",
    "wof:placetype":"venue"
},
  "geometry": {"coordinates":[-81.389397,41.434399],"type":"Point"}
}