{
  "type": "Feature",
  "properties": {
    "iso:country":"US",
    "sg:address":"3590 Cassandra Dr",
    "sg:city":"Tipp City",
    "sg:classifiers":[
        {
            "category":"Wholesale",
            "subcategory":"Machinery & Supplies",
            "type":"Manufacturing & Wholesale Goods"
        }
    ],
    "sg:phone":"+1 937 335 3501",
    "sg:postcode":"45371",
    "sg:province":"OH",
    "sg:tags":[
        "equipment",
        "safety",
        "clothing"
    ],
    "wof:name":"World Class Safety",
    "wof:placetype":"venue"
},
  "geometry": {"coordinates":[-84.209385,39.987507],"type":"Point"}
}