{
  "type": "Feature",
  "properties": {
    "addr:full": "2368 Victory Pkwy Cincinnati OH 45206",
    "addr:housenumber": "2368",
    "addr:postcode": "45206",
    "addr:street": "Victory Pkwy",
    "iso:country": "US",
    "sg:address": "2368 Victory Pkwy",
    "sg:city": "Cincinnati",
    "sg:classifiers": [
      {
        "category": "Organizations",
        "subcategory": "Membership Organization",
        "type": "Services"
      }
    ],
    "sg:phone": "+1 513 381 1959",
    "sg:postcode": "45206",
    "sg:province": "OH",
    "sg:tags": [
      "educational",
      "association"
    ],
    "wof:name": "Aqp",
    "wof:placetype": "venue"
  },
  "geometry": {"coordinates":[-84.48451,39.124525],"type":"Point"}
}
