{
  "type": "Feature",
  "properties": {
    "addr:full":"2215 Lawn Ave Cincinnati OH 45212",
    "addr:housenumber":"2215",
    "addr:postcode":"45212",
    "addr:street":"Lawn Ave",
    "iso:country":"US",
    "sg:address":"2215 Lawn Ave",
    "sg:city":"Cincinnati",
    "sg:classifiers":[
        {
            "category":"Building & Trades",
            "subcategory":"Construction",
            "type":"Services"
        }
    ],
    "sg:phone":"+1 513 631 5786",
    "sg:postcode":"45212",
    "sg:province":"OH",
    "sg:tags":[
        "residential",
        "contractor"
    ],
    "wof:name":"J & J Home Improvement",
    "wof:placetype":"venue"
},
  "geometry": {"coordinates":[-84.45154599999999,39.169376],"type":"Point"}
}