{
  "type": "Feature",
  "properties": {
    "addr:full": "17207 Westdale Ave Cleveland OH 44135",
    "addr:housenumber": "17207",
    "addr:postcode": "44135",
    "addr:street": "Westdale Ave",
    "iso:country": "US",
    "sg:address": "17207 Westdale Ave",
    "sg:city": "Cleveland",
    "sg:classifiers": [
      {
        "category": "Shopping",
        "subcategory": "Gifts \u0026 Souvenirs",
        "type": "Retail Goods"
      }
    ],
    "sg:phone": "+1 216 941 9129",
    "sg:postcode": "44135",
    "sg:province": "OH",
    "sg:tags": [
      "shop",
      "art"
    ],
    "wof:name": "Gimme Smiles",
    "wof:placetype": "venue"
  },
  "geometry": {"coordinates":[-81.818116,41.439046],"type":"Point"}
}
