{
  "type": "Feature",
  "properties": {
    "iso:country":"US",
    "sg:address":"17207 Westdale Ave",
    "sg:city":"Cleveland",
    "sg:classifiers":[
        {
            "category":"Shopping",
            "subcategory":"Gifts & Souvenirs",
            "type":"Retail Goods"
        }
    ],
    "sg:phone":"+1 216 941 9129",
    "sg:postcode":"44135",
    "sg:province":"OH",
    "sg:tags":[
        "shop",
        "art"
    ],
    "wof:name":"Gimme Smiles",
    "wof:placetype":"venue"
},
  "geometry": {"coordinates":[-81.818116,41.439046],"type":"Point"}
}