{
  "type": "Feature",
  "properties": {
    "addr:full": "1800 London Rd Cleveland OH 44112",
    "addr:housenumber": "1800",
    "addr:postcode": "44112",
    "addr:street": "London Rd",
    "iso:country": "US",
    "sg:address": "1800 London Rd",
    "sg:city": "Cleveland",
    "sg:classifiers": [
      {
        "category": "Retail",
        "subcategory": "Auto Repair",
        "type": "Services"
      }
    ],
    "sg:phone": "+1 216 481 4142",
    "sg:postcode": "44112",
    "sg:province": "OH",
    "sg:tags": [
      "repairing",
      "automobile"
    ],
    "wof:name": "Extreme Quality Car Care",
    "wof:placetype": "venue"
  },
  "geometry": {"coordinates":[-81.559122,41.553391],"type":"Point"}
}
