{
  "type": "Feature",
  "properties": {
    "addr:full":"891 Som Center Rd Cleveland OH 44143",
    "addr:housenumber":"891",
    "addr:postcode":"44143",
    "addr:street":"Som Center Rd",
    "iso:country":"US",
    "sg:address":"891 Som Center Rd",
    "sg:city":"Cleveland",
    "sg:classifiers":[
        {
            "category":"Professional",
            "subcategory":"Lawyer & Legal Services",
            "type":"Services"
        }
    ],
    "sg:phone":"+1 440 449 3266",
    "sg:postcode":"44143",
    "sg:province":"OH",
    "sg:tags":[
        "attorney"
    ],
    "wof:name":"Albert G Hehr Jr",
    "wof:placetype":"venue"
},
  "geometry": {"coordinates":[-81.438716,41.536474],"type":"Point"}
}