{
  "type": "Feature",
  "properties": {
    "iso:country":"US",
    "sg:address":"1934 Navarre Rd SW",
    "sg:city":"Canton",
    "sg:classifiers":[
        {
            "category":"Wholesale",
            "subcategory":"Home Furnishings",
            "type":"Manufacturing & Wholesale Goods"
        }
    ],
    "sg:phone":"+1 330 896 5634",
    "sg:postcode":"44706",
    "sg:province":"OH",
    "wof:name":"Epoxy Stone Inc",
    "wof:placetype":"venue"
},
  "geometry": {"coordinates":[-81.39608200000001,40.786264],"type":"Point"}
}