{
  "type": "Feature",
  "properties": {
    "addr:full": "1934 Navarre Rd SW Canton OH 44706",
    "addr:housenumber": "1934",
    "addr:postcode": "44706",
    "addr:street": "Navarre Rd Sw",
    "iso:country": "US",
    "sg:address": "1934 Navarre Rd SW",
    "sg:city": "Canton",
    "sg:classifiers": [
      {
        "category": "Wholesale",
        "subcategory": "Home Furnishings",
        "type": "Manufacturing \u0026 Wholesale Goods"
      }
    ],
    "sg:phone": "+1 330 896 5634",
    "sg:postcode": "44706",
    "sg:province": "OH",
    "wof:name": "Epoxy Stone Inc",
    "wof:placetype": "venue"
  },
  "geometry": {"coordinates":[-81.396082,40.786264],"type":"Point"}
}
