{
  "type": "Feature",
  "properties": {
    "iso:country":"US",
    "sg:address":"270 Broad St",
    "sg:city":"Westerville",
    "sg:classifiers":[
        {
            "category":"Manufacturing",
            "subcategory":"Retail Goods",
            "type":"Manufacturing & Wholesale Goods"
        },
        {
            "category":"Manufacturing",
            "subcategory":"Tools & Machinery",
            "type":"Manufacturing & Wholesale Goods"
        }
    ],
    "sg:phone":"+1 614 895 7181",
    "sg:postcode":"43055",
    "sg:province":"OH",
    "sg:tags":[
        "salon",
        "industrial",
        "beauty",
        "mfg",
        "supply",
        "accessory",
        "machine"
    ],
    "wof:name":"Advanced Technical Abrasives",
    "wof:placetype":"venue"
},
  "geometry": {"coordinates":[-82.425648,40.064514],"type":"Point"}
}