{
  "type": "Feature",
  "properties": {
    "addr:full":"21139 Lorain Rd Cleveland OH 44126",
    "addr:housenumber":"21139",
    "addr:postcode":"44126",
    "addr:street":"Lorain Rd",
    "iso:country":"US",
    "sg:address":"21139 Lorain Rd",
    "sg:city":"Cleveland",
    "sg:classifiers":[
        {
            "category":"Building & Trades",
            "subcategory":"Cleaning & Sanitation",
            "type":"Services"
        }
    ],
    "sg:phone":"+1 440 895 3000",
    "sg:postcode":"44126",
    "sg:province":"OH",
    "sg:tags":[
        "house"
    ],
    "sg:website":"www.merrymaids.com",
    "wof:name":"Merry Maids",
    "wof:placetype":"venue"
},
  "geometry": {"coordinates":[-81.8535,41.446178],"type":"Point"}
}