{
  "type": "Feature",
  "properties": {
    "addr:full":"390 Congress Park Dr Dayton OH 45459",
    "addr:housenumber":"390",
    "addr:postcode":"45459",
    "addr:street":"Congress Park Dr",
    "iso:country":"US",
    "sg:address":"390 Congress Park Dr",
    "sg:city":"Dayton",
    "sg:classifiers":[
        {
            "category":"Shopping",
            "subcategory":"Computers & Home Electronics",
            "type":"Retail Goods"
        }
    ],
    "sg:phone":"+1 937 428 0660",
    "sg:postcode":"45459",
    "sg:province":"OH",
    "sg:tags":[
        "software"
    ],
    "wof:name":"Ginko System",
    "wof:placetype":"venue"
},
  "geometry": {"coordinates":[-84.176376,39.630315],"type":"Point"}
}