{
  "type": "Feature",
  "properties": {
    "iso:country":"US",
    "sg:address":"2 Court St",
    "sg:city":"Millersburg",
    "sg:classifiers":[
        {
            "category":"Government",
            "subcategory":"Office",
            "type":"Public Place"
        }
    ],
    "sg:phone":"+1 330 674 5622",
    "sg:postcode":"44654",
    "sg:province":"OH",
    "sg:tags":[
        "policy"
    ],
    "wof:name":"Auditor State",
    "wof:placetype":"venue"
},
  "geometry": {"coordinates":[-81.916799,40.553528],"type":"Point"}
}