{
  "type": "Feature",
  "properties": {
    "addr:full":"18 Jackson St Struthers OH 44471",
    "addr:housenumber":"18",
    "addr:postcode":"44471",
    "addr:street":"Jackson St",
    "iso:country":"US",
    "sg:address":"18 Jackson St",
    "sg:city":"Struthers",
    "sg:classifiers":[
        {
            "category":"Manufacturing",
            "subcategory":"Metals",
            "type":"Manufacturing & Wholesale Goods"
        }
    ],
    "sg:phone":"+1 330 755 3323",
    "sg:postcode":"44471",
    "sg:province":"OH",
    "sg:tags":[
        "fabricator",
        "aluminum"
    ],
    "sg:website":"www.aluminumfencemfg.com",
    "wof:name":"Aluminum Fence & Mfg",
    "wof:placetype":"venue"
},
  "geometry": {"coordinates":[-80.583152,41.059879],"type":"Point"}
}