{
  "type": "Feature",
  "properties": {
    "iso:country":"US",
    "sg:address":"223 W Main St",
    "sg:city":"Crestline",
    "sg:classifiers":[
        {
            "category":"Retail",
            "subcategory":"Funeral Services",
            "type":"Services"
        }
    ],
    "sg:phone":"+1 419 683 2020",
    "sg:postcode":"44827",
    "sg:province":"OH",
    "wof:name":"Mark A Schneider Funeral Home",
    "wof:placetype":"venue"
},
  "geometry": {"coordinates":[-82.738223,40.788274],"type":"Point"}
}