{
  "type": "Feature",
  "properties": {
    "iso:country":"US",
    "sg:address":"149 N Maysville Ave",
    "sg:city":"Zanesville",
    "sg:classifiers":[
        {
            "category":"Shopping",
            "subcategory":"Clothing, Apparel, & Fashions",
            "type":"Retail Goods"
        }
    ],
    "sg:phone":"+1 740 450 0068",
    "sg:postcode":"43701",
    "sg:province":"OH",
    "sg:tags":[
        "riding",
        "equipment"
    ],
    "wof:name":"Saddles & Bridles Plus",
    "wof:placetype":"venue"
},
  "geometry": {"coordinates":[-82.019086,39.905536],"type":"Point"}
}