{
  "type": "Feature",
  "properties": {
    "addr:full": "149 N Maysville Ave Zanesville OH 43701",
    "addr:housenumber": "149",
    "addr:postcode": "43701",
    "addr:street": "N Maysville Ave",
    "iso:country": "US",
    "sg:address": "149 N Maysville Ave",
    "sg:city": "Zanesville",
    "sg:classifiers": [
      {
        "category": "Shopping",
        "subcategory": "Clothing, Apparel, \u0026 Fashions",
        "type": "Retail Goods"
      }
    ],
    "sg:phone": "+1 740 450 0068",
    "sg:postcode": "43701",
    "sg:province": "OH",
    "sg:tags": [
      "riding",
      "equipment"
    ],
    "wof:name": "Saddles \u0026 Bridles Plus",
    "wof:placetype": "venue"
  },
  "geometry": {"coordinates":[-82.019086,39.905536],"type":"Point"}
}
