{
  "type": "Feature",
  "properties": {
    "iso:country":"US",
    "sg:address":"3070 Mayfield Rd",
    "sg:city":"Cleveland",
    "sg:classifiers":[
        {
            "category":"Health Services",
            "subcategory":"Podiatrist",
            "type":"Services"
        }
    ],
    "sg:phone":"+1 216 397 0999",
    "sg:postcode":"44118",
    "sg:province":"OH",
    "wof:name":"Taj Malik Inc",
    "wof:placetype":"venue"
},
  "geometry": {"coordinates":[-81.569615,41.515479],"type":"Point"}
}