{
  "type": "Feature",
  "properties": {
    "iso:country":"US",
    "sg:address":"1952 E 6th St",
    "sg:city":"Cleveland",
    "sg:classifiers":[
        {
            "category":"Restaurant",
            "type":"Food & Drink"
        }
    ],
    "sg:phone":"+1 216 589 0051",
    "sg:postcode":"44114",
    "sg:province":"OH",
    "wof:name":"Marlin",
    "wof:placetype":"venue"
},
  "geometry": {"coordinates":[-81.68940600000001,41.500319],"type":"Point"}
}