{
  "type": "Feature",
  "properties": {
    "iso:country":"US",
    "sg:address":"7967 W Chester Rd",
    "sg:city":"West Chester",
    "sg:classifiers":[
        {
            "category":"Insurance",
            "subcategory":"Insurance Agent",
            "type":"Services"
        }
    ],
    "sg:phone":"+1 513 777 1041",
    "sg:postcode":"45069",
    "sg:province":"OH",
    "wof:name":"State Farm Insurance",
    "wof:placetype":"venue"
},
  "geometry": {"coordinates":[-84.362787,39.317742],"type":"Point"}
}