{
  "type": "Feature",
  "properties": {
    "addr:full":"5820 Wedgwood Dr Morrow OH 45152",
    "addr:housenumber":"5820",
    "addr:postcode":"45152",
    "addr:street":"Wedgwood Dr",
    "iso:country":"US",
    "sg:address":"5820 Wedgwood Dr",
    "sg:city":"Morrow",
    "sg:classifiers":[
        {
            "category":"Building & Trades",
            "subcategory":"Construction",
            "type":"Services"
        }
    ],
    "sg:phone":"+1 513 899 9144",
    "sg:postcode":"45152",
    "sg:province":"OH",
    "sg:tags":[
        "home",
        "builder"
    ],
    "wof:name":"Fischer Singer Family Homes",
    "wof:placetype":"venue"
},
  "geometry": {"coordinates":[-84.196759,39.34877],"type":"Point"}
}