{
  "type": "Feature",
  "properties": {
    "addr:full":"17932 Florence Chapel Pike Circleville OH 43113",
    "addr:housenumber":"17932",
    "addr:postcode":"43113",
    "addr:street":"Florence Chapel Pike",
    "iso:country":"US",
    "sg:address":"17932 Florence Chapel Pike",
    "sg:city":"Circleville",
    "sg:classifiers":[
        {
            "category":"Retail",
            "subcategory":"Auto Repair",
            "type":"Services"
        }
    ],
    "sg:phone":"+1 740 477 3932",
    "sg:postcode":"43113",
    "sg:province":"OH",
    "sg:tags":[
        "repairing",
        "automobile"
    ],
    "wof:name":"Spires & Sons Auto Repair",
    "wof:placetype":"venue"
},
  "geometry": {"coordinates":[-83.07652400000001,39.682694],"type":"Point"}
}