{
  "type": "Feature",
  "properties": {
    "addr:full":"5616 Mendocino Ct Dayton OH 45424",
    "addr:housenumber":"5616",
    "addr:postcode":"45424",
    "addr:street":"Mendocino Ct",
    "iso:country":"US",
    "sg:address":"5616 Mendocino Ct",
    "sg:city":"Dayton",
    "sg:classifiers":[
        {
            "category":"Building & Trades",
            "subcategory":"Construction",
            "type":"Services"
        }
    ],
    "sg:phone":"+1 937 237 3026",
    "sg:postcode":"45424",
    "sg:province":"OH",
    "sg:tags":[
        "house"
    ],
    "wof:name":"North Dayton Home Improvement",
    "wof:placetype":"venue"
},
  "geometry": {"coordinates":[-84.102682,39.810463],"type":"Point"}
}