{
  "type": "Feature",
  "properties": {
    "iso:country":"US",
    "sg:address":"1803 Wexford Ave",
    "sg:city":"Cleveland",
    "sg:classifiers":[
        {
            "category":"Building & Trades",
            "subcategory":"Construction",
            "type":"Services"
        }
    ],
    "sg:phone":"+1 216 351 8214",
    "sg:postcode":"44134",
    "sg:province":"OH",
    "sg:tags":[
        "contractor"
    ],
    "wof:name":"FCH Contractors",
    "wof:placetype":"venue"
},
  "geometry": {"coordinates":[-81.692351,41.415333],"type":"Point"}
}