{
  "type": "Feature",
  "properties": {
    "addr:full": "9520 Rainbow Ln North Royalton OH 44133",
    "addr:housenumber": "9520",
    "addr:postcode": "44133",
    "addr:street": "Rainbow Ln",
    "iso:country": "US",
    "sg:address": "9520 Rainbow Ln",
    "sg:city": "North Royalton",
    "sg:classifiers": [
      {
        "category": "Professional",
        "type": "Services"
      }
    ],
    "sg:phone": "+1 440 582 4576",
    "sg:postcode": "44133",
    "sg:province": "OH",
    "wof:name": "Saojml Ltd",
    "wof:placetype": "venue"
  },
  "geometry": {"coordinates":[-81.754967,41.348868],"type":"Point"}
}
