{
  "type": "Feature",
  "properties": {
    "iso:country":"US",
    "sg:address":"9520 Rainbow Ln",
    "sg:city":"North Royalton",
    "sg:classifiers":[
        {
            "category":"Professional",
            "type":"Services"
        }
    ],
    "sg:phone":"+1 440 582 4576",
    "sg:postcode":"44133",
    "sg:province":"OH",
    "wof:name":"Saojml Ltd",
    "wof:placetype":"venue"
},
  "geometry": {"coordinates":[-81.75496699999999,41.348868],"type":"Point"}
}