{
  "type": "Feature",
  "properties": {
    "iso:country":"US",
    "sg:address":"4062 Rushton Dr",
    "sg:city":"Beavercreek",
    "sg:classifiers":[
        {
            "category":"Professional",
            "subcategory":"Management & Consulting",
            "type":"Services"
        }
    ],
    "sg:phone":"+1 937 431 1564",
    "sg:postcode":"45431",
    "sg:province":"OH",
    "sg:tags":[
        "consultant",
        "business"
    ],
    "wof:name":"Executive Group",
    "wof:placetype":"venue"
},
  "geometry": {"coordinates":[-84.084993,39.765159],"type":"Point"}
}