{
  "type": "Feature",
  "properties": {
    "iso:country":"US",
    "sg:address":"6442 State Rte 81",
    "sg:city":"Ada",
    "sg:phone":"+1 419 634 4257",
    "sg:postcode":"45810",
    "sg:province":"OH",
    "sg:tags":[
        "farm",
        "corn",
        "wheat",
        "soybean"
    ],
    "wof:name":"Gary Wagners Farm",
    "wof:placetype":"venue"
},
  "geometry": {"coordinates":[-83.7486,40.776334],"type":"Point"}
}