{
  "type": "Feature",
  "properties": {
    "addr:full":"35 S Park Pl Newark OH 43055",
    "addr:housenumber":"35",
    "addr:postcode":"43055",
    "addr:street":"S Park Pl",
    "iso:country":"US",
    "sg:address":"35 S Park Pl",
    "sg:city":"Newark",
    "sg:classifiers":[
        {
            "category":"Professional",
            "subcategory":"Lawyer & Legal Services",
            "type":"Services"
        }
    ],
    "sg:phone":"+1 740 345 4550",
    "sg:postcode":"43055",
    "sg:province":"OH",
    "sg:tags":[
        "attorney"
    ],
    "wof:name":"Stephen B Wilson",
    "wof:placetype":"venue"
},
  "geometry": {"coordinates":[-82.40107399999999,40.057501],"type":"Point"}
}