{
  "type": "Feature",
  "properties": {
    "addr:full":"6513 Guthrie Ave Cleveland OH 44102",
    "addr:housenumber":"6513",
    "addr:postcode":"44102",
    "addr:street":"Guthrie Ave",
    "iso:country":"US",
    "sg:address":"6513 Guthrie Ave",
    "sg:city":"Cleveland",
    "sg:classifiers":[
        {
            "category":"Wholesale",
            "subcategory":"Stationery",
            "type":"Manufacturing & Wholesale Goods"
        }
    ],
    "sg:phone":"+1 216 651 8966",
    "sg:postcode":"44102",
    "sg:province":"OH",
    "sg:tags":[
        "core",
        "tube",
        "paper"
    ],
    "wof:name":"Dynamic Machine Concepts Inc",
    "wof:placetype":"venue"
},
  "geometry": {"coordinates":[-81.734769,41.47664],"type":"Point"}
}