{
  "type": "Feature",
  "properties": {
    "addr:full": "12408 Union Ave Cleveland OH 44105",
    "addr:housenumber": "12408",
    "addr:postcode": "44105",
    "addr:street": "Union Ave",
    "iso:country": "US",
    "sg:address": "12408 Union Ave",
    "sg:city": "Cleveland",
    "sg:classifiers": [
      {
        "category": "Shopping",
        "subcategory": "Discount \u0026 Variety Stores",
        "type": "Retail Goods"
      }
    ],
    "sg:phone": "+1 216 921 1813",
    "sg:postcode": "44105",
    "sg:province": "OH",
    "wof:name": "Family Dollar Store",
    "wof:placetype": "venue"
  },
  "geometry": {"coordinates":[-81.595651,41.463637],"type":"Point"}
}
