{
  "type": "Feature",
  "properties": {
    "addr:full": "4874 E 94th St Cleveland OH 44125",
    "addr:housenumber": "4874",
    "addr:postcode": "44125",
    "addr:street": "E 94Th St",
    "iso:country": "US",
    "sg:address": "4874 E 94th St",
    "sg:city": "Cleveland",
    "sg:classifiers": [
      {
        "category": "Organizations",
        "subcategory": "Religious Organization",
        "type": "Services"
      }
    ],
    "sg:phone": "+1 216 271 3672",
    "sg:postcode": "44125",
    "sg:province": "OH",
    "sg:tags": [
      "clergy"
    ],
    "wof:name": "James Burge",
    "wof:placetype": "venue"
  },
  "geometry": {"coordinates":[-81.620412,41.428235],"type":"Point"}
}
