{
  "type": "Feature",
  "properties": {
    "addr:full": "41600 Griswold Rd Elyria OH 44035",
    "addr:postcode": "41600;44035",
    "addr:street": "Griswold Rd",
    "iso:country": "US",
    "sg:address": "41600 Griswold Rd",
    "sg:city": "Elyria",
    "sg:classifiers": [
      {
        "category": "Building \u0026 Trades",
        "subcategory": "Landscaping Services",
        "type": "Services"
      }
    ],
    "sg:phone": "+1 440 324 4314",
    "sg:postcode": "44035",
    "sg:province": "OH",
    "sg:tags": [
      "landscape",
      "contractor"
    ],
    "wof:name": "Pandy's Garden Ctr Landscaping",
    "wof:placetype": "venue"
  },
  "geometry": {"coordinates":[-82.125431,41.400445],"type":"Point"}
}
