{
  "type": "Feature",
  "properties": {
    "iso:country":"US",
    "sg:address":"41600 Griswold Rd",
    "sg:city":"Elyria",
    "sg:classifiers":[
        {
            "category":"Building & Trades",
            "subcategory":"Landscaping Services",
            "type":"Services"
        }
    ],
    "sg:phone":"+1 440 324 4314",
    "sg:postcode":"44035",
    "sg:province":"OH",
    "sg:tags":[
        "landscape",
        "contractor"
    ],
    "wof:name":"Pandy's Garden Ctr Landscaping",
    "wof:placetype":"venue"
},
  "geometry": {"coordinates":[-82.12543100000001,41.400445],"type":"Point"}
}