{
  "type": "Feature",
  "properties": {
    "addr:full": "1465 W 3rd St Dayton OH 45402",
    "addr:housenumber": "1465",
    "addr:postcode": "45402",
    "addr:street": "W 3Rd St",
    "iso:country": "US",
    "sg:address": "1465 W 3rd St",
    "sg:city": "Dayton",
    "sg:classifiers": [
      {
        "category": "Real Estate",
        "subcategory": "Real Estate Operator",
        "type": "Services"
      }
    ],
    "sg:phone": "+1 937 461 6851",
    "sg:postcode": "45402",
    "sg:province": "OH",
    "sg:tags": [
      "apartment"
    ],
    "wof:name": "Enon Plaza Inc",
    "wof:placetype": "venue"
  },
  "geometry": {"coordinates":[-84.219049,39.755122],"type":"Point"}
}
