{
  "type": "Feature",
  "properties": {
    "iso:country":"US",
    "sg:address":"1406 Cadiz Rd",
    "sg:city":"Steubenville",
    "sg:classifiers":[
        {
            "category":"Wholesale",
            "subcategory":"Medical Equipment & Supplies",
            "type":"Manufacturing & Wholesale Goods"
        },
        {
            "category":"Health Services",
            "subcategory":"Clinic",
            "type":"Services"
        }
    ],
    "sg:phone":"+1 740 346 0737",
    "sg:postcode":"43953",
    "sg:province":"OH",
    "sg:tags":[
        "home"
    ],
    "wof:name":"Apria Healthcare Inc",
    "wof:placetype":"venue"
},
  "geometry": {"coordinates":[-80.730859,40.373824],"type":"Point"}
}