{
  "type": "Feature",
  "properties": {
    "addr:full": "6225 Lampton Pond Dr Hilliard OH 43026",
    "addr:housenumber": "6225",
    "addr:postcode": "43026",
    "addr:street": "Lampton Pond Dr",
    "iso:country": "US",
    "sg:address": "6225 Lampton Pond Dr",
    "sg:city": "Hilliard",
    "sg:classifiers": [
      {
        "category": "Freight",
        "type": "Transportation"
      }
    ],
    "sg:phone": "+1 614 210 0030",
    "sg:postcode": "43026",
    "sg:province": "OH",
    "sg:tags": [
      "operator",
      "trucking"
    ],
    "wof:name": "S M Donahue Trucking Inc",
    "wof:placetype": "venue"
  },
  "geometry": {"coordinates":[-83.183307,40.019385],"type":"Point"}
}
