{
  "type": "Feature",
  "properties": {
    "addr:full":"6805 E Sparta Ave East Sparta OH 44626",
    "addr:housenumber":"6805",
    "addr:postcode":"44626",
    "addr:street":"E Sparta Ave",
    "iso:country":"US",
    "sg:address":"6805 E Sparta Ave",
    "sg:city":"East Sparta",
    "sg:classifiers":[
        {
            "category":"Wholesale",
            "subcategory":"Electrical",
            "type":"Manufacturing & Wholesale Goods"
        }
    ],
    "sg:phone":"+1 330 484 0048",
    "sg:postcode":"44626",
    "sg:province":"OH",
    "sg:tags":[
        "electric",
        "motor"
    ],
    "wof:name":"Community Motors",
    "wof:placetype":"venue"
},
  "geometry": {"coordinates":[-81.346163,40.70585],"type":"Point"}
}