{
  "type": "Feature",
  "properties": {
    "iso:country":"US",
    "sg:address":"508 Central Ave",
    "sg:city":"Franklin",
    "sg:classifiers":[
        {
            "category":"Sports & Exercise",
            "subcategory":"Gym",
            "type":"Entertainment"
        }
    ],
    "sg:phone":"+1 937 743 0900",
    "sg:postcode":"45005",
    "sg:province":"OH",
    "sg:tags":[
        "club",
        "health",
        "studio",
        "gymnasium"
    ],
    "wof:name":"Curves For Women",
    "wof:placetype":"venue"
},
  "geometry": {"coordinates":[-84.312811,39.578536],"type":"Point"}
}