{
  "type": "Feature",
  "properties": {
    "addr:full": "401 Cherry St Galion OH 44833",
    "addr:housenumber": "401",
    "addr:postcode": "44833",
    "addr:street": "Cherry St",
    "iso:country": "US",
    "sg:address": "401 Cherry St",
    "sg:city": "Galion",
    "sg:classifiers": [
      {
        "category": "Building \u0026 Trades",
        "subcategory": "Construction",
        "type": "Services"
      }
    ],
    "sg:phone": "+1 419 468 1616",
    "sg:postcode": "44833",
    "sg:province": "OH",
    "sg:tags": [
      "downspouts",
      "gutter"
    ],
    "wof:name": "M \u0026 T Seamless Gutters",
    "wof:placetype": "venue"
  },
  "geometry": {"coordinates":[-82.796677,40.732319],"type":"Point"}
}
