{
  "type": "Feature",
  "properties": {
    "addr:full": "3304 Beech Rd NW Johnstown OH 43031",
    "addr:housenumber": "3304",
    "addr:postcode": "43031",
    "addr:street": "Beech Rd Nw",
    "iso:country": "US",
    "sg:address": "3304 Beech Rd NW",
    "sg:city": "Johnstown",
    "sg:classifiers": [
      {
        "category": "Manufacturing",
        "subcategory": "Metals",
        "type": "Manufacturing \u0026 Wholesale Goods"
      }
    ],
    "sg:phone": "+1 740 967 6147",
    "sg:postcode": "43031",
    "sg:province": "OH",
    "sg:tags": [
      "brass",
      "foundry",
      "bronze"
    ],
    "sg:website": "www.petkeep.com",
    "wof:name": "Shaw Prdctn Foundries",
    "wof:placetype": "venue"
  },
  "geometry": {"coordinates":[-82.753616,40.100256],"type":"Point"}
}
