{
  "type": "Feature",
  "properties": {
    "iso:country":"US",
    "sg:address":"140 S Bodmer Ave",
    "sg:city":"Strasburg",
    "sg:classifiers":[
        {
            "category":"Organizations",
            "subcategory":"Professional Association",
            "type":"Services"
        }
    ],
    "sg:phone":"+1 330 878 7080",
    "sg:postcode":"44680",
    "sg:province":"OH",
    "wof:name":"Cypress Masonic Temple",
    "wof:placetype":"venue"
},
  "geometry": {"coordinates":[-81.530244,40.595865],"type":"Point"}
}