{
  "type": "Feature",
  "properties": {
    "addr:full": "5991 Center St Mentor OH 44060",
    "addr:housenumber": "5991",
    "addr:postcode": "44060",
    "addr:street": "Center St",
    "iso:country": "US",
    "sg:address": "5991 Center St",
    "sg:city": "Mentor",
    "sg:classifiers": [
      {
        "category": "Professional",
        "subcategory": "Engineering",
        "type": "Services"
      }
    ],
    "sg:phone": "+1 440 209 1440",
    "sg:postcode": "44060",
    "sg:province": "OH",
    "sg:tags": [
      "engineer"
    ],
    "wof:name": "Alternative Inc",
    "wof:placetype": "venue"
  },
  "geometry": {"coordinates":[-81.341387,41.707427],"type":"Point"}
}
