{
  "type": "Feature",
  "properties": {
    "iso:country":"US",
    "sg:address":"1 Red Hollow Rd",
    "sg:city":"Beaver",
    "sg:classifiers":[
        {
            "category":"Farming",
            "subcategory":"Livestock Farm",
            "type":"Manufacturing & Wholesale Goods"
        }
    ],
    "sg:phone":"+1 740 820 8108",
    "sg:postcode":"45613",
    "sg:province":"OH",
    "sg:tags":[
        "animal",
        "general"
    ],
    "wof:name":"Teddy Oliver",
    "wof:placetype":"venue"
},
  "geometry": {"coordinates":[-82.85871299999999,38.956879],"type":"Point"}
}