{
  "type": "Feature",
  "properties": {
    "addr:full": "1 Red Hollow Rd Beaver OH 45613",
    "addr:housenumber": "1",
    "addr:postcode": "45613",
    "addr:street": "Red Hollow Rd",
    "iso:country": "US",
    "sg:address": "1 Red Hollow Rd",
    "sg:city": "Beaver",
    "sg:classifiers": [
      {
        "category": "Farming",
        "subcategory": "Livestock Farm",
        "type": "Manufacturing \u0026 Wholesale Goods"
      }
    ],
    "sg:phone": "+1 740 820 8108",
    "sg:postcode": "45613",
    "sg:province": "OH",
    "sg:tags": [
      "animal",
      "general"
    ],
    "wof:name": "Teddy Oliver",
    "wof:placetype": "venue"
  },
  "geometry": {"coordinates":[-82.858713,38.956879],"type":"Point"}
}
