{
  "type": "Feature",
  "properties": {
    "iso:country":"US",
    "sg:address":"9100 Chillicothe Rd",
    "sg:city":"Willoughby",
    "sg:classifiers":[
        {
            "category":"Autos & Motor Vehicles",
            "subcategory":"Fuel & Gas Station",
            "type":"Retail Goods"
        }
    ],
    "sg:phone":"+1 440 256 8700",
    "sg:postcode":"44094",
    "sg:province":"OH",
    "sg:tags":[
        "oil"
    ],
    "wof:name":"B & N Family Sunoco",
    "wof:placetype":"venue"
},
  "geometry": {"coordinates":[-81.359298,41.621138],"type":"Point"}
}