{
  "type": "Feature",
  "properties": {
    "addr:full": "9100 Chillicothe Rd Willoughby OH 44094",
    "addr:housenumber": "9100",
    "addr:postcode": "44094",
    "addr:street": "Chillicothe Rd",
    "iso:country": "US",
    "sg:address": "9100 Chillicothe Rd",
    "sg:city": "Willoughby",
    "sg:classifiers": [
      {
        "category": "Autos \u0026 Motor Vehicles",
        "subcategory": "Fuel \u0026 Gas Station",
        "type": "Retail Goods"
      }
    ],
    "sg:phone": "+1 440 256 8700",
    "sg:postcode": "44094",
    "sg:province": "OH",
    "sg:tags": [
      "oil"
    ],
    "wof:name": "B \u0026 N Family Sunoco",
    "wof:placetype": "venue"
  },
  "geometry": {"coordinates":[-81.359298,41.621138],"type":"Point"}
}
