{
  "type": "Feature",
  "properties": {
    "addr:full":"150 E Main St Columbus OH 43215",
    "addr:housenumber":"150",
    "addr:postcode":"43215",
    "addr:street":"E Main St",
    "iso:country":"US",
    "sg:address":"150 E Main St",
    "sg:city":"Columbus",
    "sg:classifiers":[
        {
            "category":"Real Estate",
            "subcategory":"Developer",
            "type":"Services"
        },
        {
            "category":"Real Estate",
            "subcategory":"Real Estate Agent",
            "type":"Services"
        }
    ],
    "sg:phone":"+1 614 224 0100",
    "sg:postcode":"43215",
    "sg:province":"OH",
    "sg:tags":[
        "manager"
    ],
    "wof:name":"David J Glimcher Co",
    "wof:placetype":"venue"
},
  "geometry": {"coordinates":[-82.99557299999999,39.956644],"type":"Point"}
}