{
  "type": "Feature",
  "properties": {
    "iso:country":"US",
    "sg:address":"4071 Cleveland Massillon Rd",
    "sg:city":"Barberton",
    "sg:classifiers":[
        {
            "category":"Professional",
            "subcategory":"Lawyer & Legal Services",
            "type":"Services"
        }
    ],
    "sg:phone":"+1 330 825 2477",
    "sg:postcode":"44203",
    "sg:province":"OH",
    "sg:tags":[
        "planning",
        "attorney",
        "criminal",
        "estate",
        "wills",
        "disability",
        "damage",
        "accident",
        "social",
        "trust",
        "security",
        "property",
        "law",
        "bankruptcy"
    ],
    "sg:website":"http://www.lawyerska.com",
    "wof:name":"Kennedy & Associates CO., L.P.A.",
    "wof:placetype":"venue"
},
  "geometry": {"coordinates":[-81.63815200000001,41.02839],"type":"Point"}
}