{
  "type": "Feature",
  "properties": {
    "addr:full": "4071 Cleveland Massillon Rd Barberton OH 44203",
    "addr:housenumber": "4071",
    "addr:postcode": "44203",
    "addr:street": "Cleveland Massillon Rd",
    "iso:country": "US",
    "sg:address": "4071 Cleveland Massillon Rd",
    "sg:city": "Barberton",
    "sg:classifiers": [
      {
        "category": "Professional",
        "subcategory": "Lawyer \u0026 Legal Services",
        "type": "Services"
      }
    ],
    "sg:phone": "+1 330 825 2477",
    "sg:postcode": "44203",
    "sg:province": "OH",
    "sg:tags": [
      "planning",
      "attorney",
      "criminal",
      "estate",
      "wills",
      "disability",
      "damage",
      "accident",
      "social",
      "trust",
      "security",
      "property",
      "law",
      "bankruptcy"
    ],
    "sg:website": "http://www.lawyerska.com",
    "wof:name": "Kennedy \u0026 Associates CO., L.P.A.",
    "wof:placetype": "venue"
  },
  "geometry": {"coordinates":[-81.638152,41.02839],"type":"Point"}
}
