{
  "type": "Feature",
  "properties": {
    "addr:full": "585 E Livingston St Celina OH 45822",
    "addr:housenumber": "585",
    "addr:postcode": "45822",
    "addr:street": "E Livingston St",
    "iso:country": "US",
    "sg:address": "585 E Livingston St",
    "sg:city": "Celina",
    "sg:classifiers": [
      {
        "category": "Communications",
        "subcategory": "Radio Station",
        "type": "Services"
      }
    ],
    "sg:phone": "+1 419 586 9151",
    "sg:postcode": "45822",
    "sg:province": "OH",
    "sg:tags": [
      "company",
      "broadcasting"
    ],
    "wof:name": "WKTN Radio",
    "wof:placetype": "venue"
  },
  "geometry": {"coordinates":[-84.560971,40.550523],"type":"Point"}
}
