{
  "type": "Feature",
  "properties": {
    "addr:full": "5850 Dry Fork Rd Cleves OH 45002",
    "addr:housenumber": "5850",
    "addr:postcode": "45002",
    "addr:street": "Dry Fork Rd",
    "iso:country": "US",
    "sg:address": "5850 Dry Fork Rd",
    "sg:city": "Cleves",
    "sg:classifiers": [
      {
        "category": "Wholesale",
        "subcategory": "Construction Materials",
        "type": "Manufacturing \u0026 Wholesale Goods"
      }
    ],
    "sg:phone": "+1 513 367 2177",
    "sg:postcode": "45002",
    "sg:province": "OH",
    "sg:tags": [
      "operator",
      "sand",
      "gravel",
      "local",
      "trucking"
    ],
    "wof:name": "Ashcraft Sand \u0026 Gravel Inc",
    "wof:placetype": "venue"
  },
  "geometry": {"coordinates":[-84.770359,39.22097],"type":"Point"}
}
