{
  "type": "Feature",
  "properties": {
    "iso:country":"US",
    "sg:address":"5850 Dry Fork Rd",
    "sg:city":"Cleves",
    "sg:classifiers":[
        {
            "category":"Wholesale",
            "subcategory":"Construction Materials",
            "type":"Manufacturing & Wholesale Goods"
        }
    ],
    "sg:phone":"+1 513 367 2177",
    "sg:postcode":"45002",
    "sg:province":"OH",
    "sg:tags":[
        "operator",
        "sand",
        "gravel",
        "local",
        "trucking"
    ],
    "wof:name":"Ashcraft Sand & Gravel Inc",
    "wof:placetype":"venue"
},
  "geometry": {"coordinates":[-84.770359,39.22097],"type":"Point"}
}