{
  "type": "Feature",
  "properties": {
    "addr:full":"7735 State Rte 45 Lisbon OH 44432",
    "addr:housenumber":"7735",
    "addr:postcode":"44432",
    "addr:street":"State Rte 45",
    "iso:country":"US",
    "sg:address":"7735 State Rte 45",
    "sg:city":"Lisbon",
    "sg:classifiers":[
        {
            "category":"Health Services",
            "subcategory":"Hospital",
            "type":"Services"
        }
    ],
    "sg:phone":"+1 330 424 0404",
    "sg:postcode":"44432",
    "sg:province":"OH",
    "sg:tags":[
        "mental"
    ],
    "wof:name":"Columbiana Co MRDD",
    "wof:placetype":"venue"
},
  "geometry": {"coordinates":[-80.774737,40.785933],"type":"Point"}
}