{
  "type": "Feature",
  "properties": {
    "addr:full":"5717 Erie Ave SW Navarre OH 44662",
    "addr:housenumber":"5717",
    "addr:postcode":"44662",
    "addr:street":"Erie Ave Sw",
    "iso:country":"US",
    "sg:address":"5717 Erie Ave SW",
    "sg:city":"Navarre",
    "sg:classifiers":[
        {
            "category":"Personal",
            "subcategory":"Beauty Salon",
            "type":"Services"
        }
    ],
    "sg:phone":"+1 330 879 5037",
    "sg:postcode":"44662",
    "sg:province":"OH",
    "wof:name":"Carlos' Beauty Salon",
    "wof:placetype":"venue"
},
  "geometry": {"coordinates":[-81.52195,40.72806],"type":"Point"}
}