{
  "type": "Feature",
  "properties": {
    "addr:full": "101 Stucky Dr Dover OH 44622",
    "addr:housenumber": "101",
    "addr:postcode": "44622",
    "addr:street": "Stucky Dr",
    "iso:country": "US",
    "sg:address": "101 Stucky Dr",
    "sg:city": "Dover",
    "sg:classifiers": [
      {
        "category": "Travel",
        "subcategory": "Travel Agent",
        "type": "Entertainment"
      }
    ],
    "sg:phone": "+1 330 343 1946",
    "sg:postcode": "44622",
    "sg:province": "OH",
    "sg:tags": [
      "agency",
      "bureau"
    ],
    "wof:name": "First Class Travel",
    "wof:placetype": "venue"
  },
  "geometry": {"coordinates":[-81.49584,40.54371],"type":"Point"}
}
