{
  "type": "Feature",
  "properties": {
    "addr:full": "118 N Findlay St Dayton OH 45403",
    "addr:housenumber": "118",
    "addr:postcode": "45403",
    "addr:street": "N Findlay St",
    "iso:country": "US",
    "sg:address": "118 N Findlay St",
    "sg:city": "Dayton",
    "sg:classifiers": [
      {
        "category": "Autos \u0026 Motor Vehicles",
        "subcategory": "Fuel \u0026 Gas Station",
        "type": "Retail Goods"
      }
    ],
    "sg:phone": "+1 937 353 8697",
    "sg:postcode": "45403",
    "sg:province": "OH",
    "sg:tags": [
      "oil"
    ],
    "wof:name": "Or's Sunoco Towing",
    "wof:placetype": "venue"
  },
  "geometry": {"coordinates":[-84.157635,39.766653],"type":"Point"}
}
