{
  "type": "Feature",
  "properties": {
    "iso:country":"US",
    "sg:address":"118 N Findlay St",
    "sg:city":"Dayton",
    "sg:classifiers":[
        {
            "category":"Autos & Motor Vehicles",
            "subcategory":"Fuel & Gas Station",
            "type":"Retail Goods"
        }
    ],
    "sg:phone":"+1 937 353 8697",
    "sg:postcode":"45403",
    "sg:province":"OH",
    "sg:tags":[
        "oil"
    ],
    "wof:name":"Or's Sunoco Towing",
    "wof:placetype":"venue"
},
  "geometry": {"coordinates":[-84.157635,39.766653],"type":"Point"}
}