{
  "type": "Feature",
  "properties": {
    "addr:full": "5595 Massillon Rd Canton OH 44720",
    "addr:housenumber": "5595",
    "addr:postcode": "44720",
    "addr:street": "Massillon Rd",
    "iso:country": "US",
    "sg:address": "5595 Massillon Rd",
    "sg:city": "Canton",
    "sg:classifiers": [
      {
        "category": "Building \u0026 Trades",
        "subcategory": "Construction",
        "type": "Services"
      }
    ],
    "sg:phone": "+1 330 456 8239",
    "sg:postcode": "44720",
    "sg:province": "OH",
    "sg:tags": [
      "new",
      "remodeling",
      "family",
      "home"
    ],
    "wof:name": "OBrien Lumber \u0026 Cnstr Co",
    "wof:placetype": "venue"
  },
  "geometry": {"coordinates":[-81.463934,40.908004],"type":"Point"}
}
