{
  "type": "Feature",
  "properties": {
    "iso:country":"US",
    "sg:address":"5595 Massillon Rd",
    "sg:city":"Canton",
    "sg:classifiers":[
        {
            "category":"Building & Trades",
            "subcategory":"Construction",
            "type":"Services"
        }
    ],
    "sg:phone":"+1 330 456 8239",
    "sg:postcode":"44720",
    "sg:province":"OH",
    "sg:tags":[
        "new",
        "remodeling",
        "family",
        "home"
    ],
    "wof:name":"OBrien Lumber & Cnstr Co",
    "wof:placetype":"venue"
},
  "geometry": {"coordinates":[-81.463934,40.908004],"type":"Point"}
}