{
  "type": "Feature",
  "properties": {
    "addr:full": "329 Southwood Ave Columbus OH 43207",
    "addr:housenumber": "329",
    "addr:postcode": "43207",
    "addr:street": "Southwood Ave",
    "iso:country": "US",
    "sg:address": "329 Southwood Ave",
    "sg:city": "Columbus",
    "sg:classifiers": [
      {
        "category": "Shopping",
        "subcategory": "Clothing, Apparel, \u0026 Fashions",
        "type": "Retail Goods"
      }
    ],
    "sg:phone": "+1 614 443 1860",
    "sg:postcode": "43207",
    "sg:province": "OH",
    "sg:website": "www.celticimports.com",
    "wof:name": "Celtic Imports",
    "wof:placetype": "venue"
  },
  "geometry": {"coordinates":[-82.985382,39.931895],"type":"Point"}
}
