{
  "type": "Feature",
  "properties": {
    "addr:full":"3560 W Market St Fairlawn OH 44333",
    "addr:housenumber":"3560",
    "addr:postcode":"44333",
    "addr:street":"W Market St",
    "iso:country":"US",
    "sg:address":"3560 W Market St",
    "sg:city":"Fairlawn",
    "sg:classifiers":[
        {
            "category":"Organizations",
            "subcategory":"Non-profit Organization",
            "type":"Services"
        }
    ],
    "sg:phone":"+1 330 665 4199",
    "sg:postcode":"44333",
    "sg:province":"OH",
    "sg:tags":[
        "medical",
        "management"
    ],
    "wof:name":"H F Medical Management Inc",
    "wof:placetype":"venue"
},
  "geometry": {"coordinates":[-81.626471,41.135457],"type":"Point"}
}