{
  "type": "Feature",
  "properties": {
    "iso:country":"US",
    "sg:address":"10495 Montgomery Rd",
    "sg:city":"Cincinnati",
    "sg:classifiers":[
        {
            "category":"Health Services",
            "subcategory":"Doctor",
            "type":"Services"
        }
    ],
    "sg:phone":"+1 513 791 6006",
    "sg:postcode":"45242",
    "sg:province":"OH",
    "sg:tags":[
        "medical"
    ],
    "wof:name":"Allergy & Asthma Center",
    "wof:placetype":"venue"
},
  "geometry": {"coordinates":[-84.343718,39.254028],"type":"Point"}
}