{
  "type": "Feature",
  "properties": {
    "addr:full": "2151 Crane Ave Cincinnati OH 45207",
    "addr:housenumber": "2151",
    "addr:postcode": "45207",
    "addr:street": "Crane Ave",
    "iso:country": "US",
    "sg:address": "2151 Crane Ave",
    "sg:city": "Cincinnati",
    "sg:classifiers": [
      {
        "category": "Shopping",
        "subcategory": "Clothing, Apparel, \u0026 Fashions",
        "type": "Retail Goods"
      }
    ],
    "sg:phone": "+1 513 241 5586",
    "sg:postcode": "45207",
    "sg:province": "OH",
    "wof:name": "Sam The Tailor",
    "wof:placetype": "venue"
  },
  "geometry": {"coordinates":[-84.461113,39.141851],"type":"Point"}
}
