{
  "type": "Feature",
  "properties": {
    "addr:full":"8749 Reading Rd Cincinnati OH 45215",
    "addr:housenumber":"8749",
    "addr:postcode":"45215",
    "addr:street":"Reading Rd",
    "iso:country":"US",
    "sg:address":"8749 Reading Rd",
    "sg:city":"Cincinnati",
    "sg:classifiers":[
        {
            "category":"Bars & Pubs",
            "type":"Food & Drink"
        }
    ],
    "sg:phone":"+1 513 821 3888",
    "sg:postcode":"45215",
    "sg:province":"OH",
    "sg:tags":[
        "drinking"
    ],
    "wof:name":"Our Place Tavern",
    "wof:placetype":"venue"
},
  "geometry": {"coordinates":[-84.44328,39.219096],"type":"Point"}
}