{
  "type": "Feature",
  "properties": {
    "iso:country":"US",
    "sg:address":"1523 Niles Cortland Rd",
    "sg:city":"Niles",
    "sg:classifiers":[
        {
            "category":"Home & Garden",
            "subcategory":"Furniture",
            "type":"Retail Goods"
        }
    ],
    "sg:phone":"+1 330 652 3838",
    "sg:postcode":"44446",
    "sg:province":"OH",
    "sg:tags":[
        "mattress"
    ],
    "wof:name":"Sleepy Hollow Sleep Shop",
    "wof:placetype":"venue"
},
  "geometry": {"coordinates":[-80.74306199999999,41.201592],"type":"Point"}
}