{
  "type": "Feature",
  "properties": {
    "addr:full": "1523 Niles Cortland Rd Niles OH 44446",
    "addr:housenumber": "1523",
    "addr:postcode": "44446",
    "addr:street": "Niles Cortland Rd",
    "iso:country": "US",
    "sg:address": "1523 Niles Cortland Rd",
    "sg:city": "Niles",
    "sg:classifiers": [
      {
        "category": "Home \u0026 Garden",
        "subcategory": "Furniture",
        "type": "Retail Goods"
      }
    ],
    "sg:phone": "+1 330 652 3838",
    "sg:postcode": "44446",
    "sg:province": "OH",
    "sg:tags": [
      "mattress"
    ],
    "wof:name": "Sleepy Hollow Sleep Shop",
    "wof:placetype": "venue"
  },
  "geometry": {"coordinates":[-80.743062,41.201592],"type":"Point"}
}
