{
  "type": "Feature",
  "properties": {
    "addr:full":"619 W Findlay St Carey OH 43316",
    "addr:housenumber":"619",
    "addr:postcode":"43316",
    "addr:street":"W Findlay St",
    "iso:country":"US",
    "sg:address":"619 W Findlay St",
    "sg:city":"Carey",
    "sg:classifiers":[
        {
            "category":"Building & Trades",
            "subcategory":"Cleaning & Sanitation",
            "type":"Services"
        }
    ],
    "sg:phone":"+1 419 396 9890",
    "sg:postcode":"43316",
    "sg:province":"OH",
    "sg:tags":[
        "janitor"
    ],
    "wof:name":"A Mop A Broom & A Bucket",
    "wof:placetype":"venue"
},
  "geometry": {"coordinates":[-83.391807,40.95368],"type":"Point"}
}