{
  "type": "Feature",
  "properties": {
    "iso:country":"US",
    "sg:address":"520 E 5th St",
    "sg:city":"Cincinnati",
    "sg:classifiers":[
        {
            "category":"Professional",
            "subcategory":"Lawyer & Legal Services",
            "type":"Services"
        }
    ],
    "sg:phone":"+1 513 421 4020",
    "sg:postcode":"45202",
    "sg:province":"OH",
    "sg:tags":[
        "attorney"
    ],
    "wof:name":"David M Scott",
    "wof:placetype":"venue"
},
  "geometry": {"coordinates":[-84.50275499999999,39.104142],"type":"Point"}
}