{
  "type": "Feature",
  "properties": {
    "addr:full": "520 E 5th St Cincinnati OH 45202",
    "addr:housenumber": "520",
    "addr:postcode": "45202",
    "addr:street": "E 5Th St",
    "iso:country": "US",
    "sg:address": "520 E 5th St",
    "sg:city": "Cincinnati",
    "sg:classifiers": [
      {
        "category": "Professional",
        "subcategory": "Lawyer \u0026 Legal Services",
        "type": "Services"
      }
    ],
    "sg:phone": "+1 513 421 4020",
    "sg:postcode": "45202",
    "sg:province": "OH",
    "sg:tags": [
      "attorney"
    ],
    "wof:name": "David M Scott",
    "wof:placetype": "venue"
  },
  "geometry": {"coordinates":[-84.502755,39.104142],"type":"Point"}
}
