{
  "type": "Feature",
  "properties": {
    "iso:country":"US",
    "sg:address":"9801 State Rte 66",
    "sg:city":"Fort Loramie",
    "sg:classifiers":[
        {
            "category":"Wholesale",
            "subcategory":"Construction Materials",
            "type":"Manufacturing & Wholesale Goods"
        }
    ],
    "sg:phone":"+1 937 295 2641",
    "sg:postcode":"45845",
    "sg:province":"OH",
    "sg:tags":[
        "concrete",
        "product"
    ],
    "wof:name":"Fort Loramic Cast Stone Prods",
    "wof:placetype":"venue"
},
  "geometry": {"coordinates":[-84.37432,40.336357],"type":"Point"}
}