{
  "type": "Feature",
  "properties": {
    "addr:full": "13300 Littleton Rd Cleveland OH 44125",
    "addr:housenumber": "13300",
    "addr:postcode": "44125",
    "addr:street": "Littleton Rd",
    "iso:country": "US",
    "sg:address": "13300 Littleton Rd",
    "sg:city": "Cleveland",
    "sg:classifiers": [
      {
        "category": "Building \u0026 Trades",
        "subcategory": "Landscaping Services",
        "type": "Services"
      }
    ],
    "sg:phone": "+1 216 587 2091",
    "sg:postcode": "44125",
    "sg:province": "OH",
    "sg:tags": [
      "landscape"
    ],
    "wof:name": "Planet Earth Landscape",
    "wof:placetype": "venue"
  },
  "geometry": {"coordinates":[-81.591006,41.402175],"type":"Point"}
}
