{
  "type": "Feature",
  "properties": {
    "iso:country":"US",
    "sg:address":"217 Hawkeye Ct",
    "sg:city":"Columbus",
    "sg:classifiers":[
        {
            "category":"Food & Beverages",
            "subcategory":"Specialty",
            "type":"Retail Goods"
        }
    ],
    "sg:phone":"+1 614 443 7473",
    "sg:postcode":"43235",
    "sg:province":"OH",
    "sg:tags":[
        "poultry"
    ],
    "wof:name":"Chicken Store & More",
    "wof:placetype":"venue"
},
  "geometry": {"coordinates":[-83.02266899999999,40.134606],"type":"Point"}
}