{
  "type": "Feature",
  "properties": {
    "addr:full": "217 Hawkeye Ct Columbus OH 43235",
    "addr:housenumber": "217",
    "addr:postcode": "43235",
    "addr:street": "Hawkeye Ct",
    "iso:country": "US",
    "sg:address": "217 Hawkeye Ct",
    "sg:city": "Columbus",
    "sg:classifiers": [
      {
        "category": "Food \u0026 Beverages",
        "subcategory": "Specialty",
        "type": "Retail Goods"
      }
    ],
    "sg:phone": "+1 614 443 7473",
    "sg:postcode": "43235",
    "sg:province": "OH",
    "sg:tags": [
      "poultry"
    ],
    "wof:name": "Chicken Store \u0026 More",
    "wof:placetype": "venue"
  },
  "geometry": {"coordinates":[-83.022669,40.134606],"type":"Point"}
}
