{
  "type": "Feature",
  "properties": {
    "addr:full":"126 Gnau Ave SW Massillon OH 44646",
    "addr:housenumber":"126",
    "addr:postcode":"44646",
    "addr:street":"Gnau Ave Sw",
    "iso:country":"US",
    "sg:address":"126 Gnau Ave SW",
    "sg:city":"Massillon",
    "sg:classifiers":[
        {
            "category":"Social Services",
            "type":"Services"
        }
    ],
    "sg:phone":"+1 330 834 9066",
    "sg:postcode":"44646",
    "sg:province":"OH",
    "sg:tags":[
        "organization",
        "welfare"
    ],
    "wof:name":"Ohio Chapter-Myasthenia Gravis",
    "wof:placetype":"venue"
},
  "geometry": {"coordinates":[-81.48119199999999,40.794292],"type":"Point"}
}