{
  "type": "Feature",
  "properties": {
    "addr:full":"4180 Chandlersville Rd Zanesville OH 43701",
    "addr:housenumber":"4180",
    "addr:postcode":"43701",
    "addr:street":"Chandlersville Rd",
    "iso:country":"US",
    "sg:address":"4180 Chandlersville Rd",
    "sg:city":"Zanesville",
    "sg:classifiers":[
        {
            "category":"Autos & Motor Vehicles",
            "subcategory":"Fuel & Gas Station",
            "type":"Retail Goods"
        }
    ],
    "sg:phone":"+1 740 454 9200",
    "sg:postcode":"43701",
    "sg:province":"OH",
    "sg:tags":[
        "oil"
    ],
    "wof:name":"Carlwick Service",
    "wof:placetype":"venue"
},
  "geometry": {"coordinates":[-81.918458,39.921742],"type":"Point"}
}