{
  "type": "Feature",
  "properties": {
    "addr:full":"13 Sycamore Dr Norwalk OH 44857",
    "addr:housenumber":"13",
    "addr:postcode":"44857",
    "addr:street":"Sycamore Dr",
    "iso:country":"US",
    "sg:address":"13 Sycamore Dr",
    "sg:city":"Norwalk",
    "sg:classifiers":[
        {
            "category":"Real Estate",
            "subcategory":"Real Estate Operator",
            "type":"Services"
        }
    ],
    "sg:phone":"+1 419 668 9250",
    "sg:postcode":"44857",
    "sg:province":"OH",
    "sg:tags":[
        "apartment"
    ],
    "wof:name":"Bluff's Apartments",
    "wof:placetype":"venue"
},
  "geometry": {"coordinates":[-82.64379099999999,41.233933],"type":"Point"}
}