{
  "type": "Feature",
  "properties": {
    "addr:full": "1667 Mosley Dr Hamilton IN 45013",
    "addr:housenumber": "1667",
    "addr:postcode": "45013",
    "addr:street": "Mosley Dr",
    "iso:country": "US",
    "sg:address": "1667 Mosley Dr",
    "sg:city": "Hamilton",
    "sg:classifiers": [
      {
        "category": "Building \u0026 Trades",
        "subcategory": "Construction",
        "type": "Services"
      }
    ],
    "sg:phone": "+1 513 738 0235",
    "sg:postcode": "45013",
    "sg:province": "IN",
    "sg:tags": [
      "designer",
      "dealer",
      "pool",
      "swimming"
    ],
    "wof:name": "Colegate Pools Inc",
    "wof:placetype": "venue"
  },
  "geometry": {"coordinates":[-84.727121,39.373265],"type":"Point"}
}
