{
  "type": "Feature",
  "properties": {
    "iso:country":"US",
    "sg:address":"1361 Marlyn Dr",
    "sg:city":"Columbus",
    "sg:classifiers":[
        {
            "category":"Building & Trades",
            "subcategory":"Electrical",
            "type":"Services"
        }
    ],
    "sg:phone":"+1 614 459 0098",
    "sg:postcode":"43220",
    "sg:province":"OH",
    "sg:tags":[
        "electrical",
        "contractor"
    ],
    "wof:name":"Snyder Electric",
    "wof:placetype":"venue"
},
  "geometry": {"coordinates":[-83.05589500000001,40.042992],"type":"Point"}
}