{
  "type": "Feature",
  "properties": {
    "iso:country":"US",
    "sg:address":"22450 Canterbury Ln",
    "sg:city":"Cleveland",
    "sg:classifiers":[
        {
            "category":"Shopping",
            "subcategory":"Catalog Store",
            "type":"Retail Goods"
        }
    ],
    "sg:phone":"+1 216 561 7822",
    "sg:postcode":"44122",
    "sg:province":"OH",
    "sg:tags":[
        "mail",
        "house"
    ],
    "wof:name":"Family Jewels",
    "wof:placetype":"venue"
},
  "geometry": {"coordinates":[-81.51823,41.472124],"type":"Point"}
}