{
  "type": "Feature",
  "properties": {
    "addr:full": "1660 Gateway Cir Grove City OH 43123",
    "addr:housenumber": "1660",
    "addr:postcode": "43123",
    "addr:street": "Gateway Cir",
    "iso:country": "US",
    "sg:address": "1660 Gateway Cir",
    "sg:city": "Grove City",
    "sg:classifiers": [
      {
        "category": "Real Estate",
        "subcategory": "Real Estate Agent",
        "type": "Services"
      }
    ],
    "sg:phone": "+1 614 875 1408",
    "sg:postcode": "43123",
    "sg:province": "OH",
    "sg:website": "www.countrytyme.com",
    "wof:name": "Country Tyme Realty Inc",
    "wof:placetype": "venue"
  },
  "geometry": {"coordinates":[-83.046198,39.887608],"type":"Point"}
}
