{
  "type": "Feature",
  "properties": {
    "iso:country":"US",
    "sg:address":"2612 Jefferson Estates Ct",
    "sg:city":"Blacklick",
    "sg:classifiers":[
        {
            "category":"Insurance",
            "subcategory":"Insurance Agent",
            "type":"Services"
        }
    ],
    "sg:phone":"+1 614 939 5294",
    "sg:postcode":"43004",
    "sg:province":"OH",
    "wof:name":"Rayron Associates Inc",
    "wof:placetype":"venue"
},
  "geometry": {"coordinates":[-82.798146,40.039204],"type":"Point"}
}