{
  "type": "Feature",
  "properties": {
    "iso:country":"US",
    "sg:address":"7841 Burrwood St",
    "sg:city":"Dublin",
    "sg:classifiers":[
        {
            "category":"Restaurant",
            "type":"Food & Drink"
        }
    ],
    "sg:phone":"+1 614 766 9951",
    "sg:postcode":"43016",
    "sg:province":"OH",
    "sg:tags":[
        "eating"
    ],
    "wof:name":"Cuyahoga Vly Tibetan Terrier",
    "wof:placetype":"venue"
},
  "geometry": {"coordinates":[-83.08526500000001,40.126659],"type":"Point"}
}