{
  "type": "Feature",
  "properties": {
    "iso:country":"US",
    "sg:address":"5067 Canterbury Dr",
    "sg:city":"Powell",
    "sg:classifiers":[
        {
            "category":"Shopping",
            "subcategory":"Clothing, Apparel, & Fashions",
            "type":"Retail Goods"
        }
    ],
    "sg:phone":"+1 614 351 1989",
    "sg:postcode":"43065",
    "sg:province":"OH",
    "sg:tags":[
        "couturier",
        "bridal"
    ],
    "sg:website":"www.tomjamesco.com",
    "wof:name":"Tom James Co",
    "wof:placetype":"venue"
},
  "geometry": {"coordinates":[-83.113471,40.145985],"type":"Point"}
}