{
  "type": "Feature",
  "properties": {
    "iso:country":"US",
    "sg:address":"3871 Broadview Rd",
    "sg:city":"Richfield",
    "sg:classifiers":[
        {
            "category":"Health Services",
            "subcategory":"Doctor",
            "type":"Services"
        }
    ],
    "sg:phone":"+1 330 659 4480",
    "sg:postcode":"44286",
    "sg:province":"OH",
    "sg:tags":[
        "physician",
        "surgeon"
    ],
    "wof:name":"Randolph M Heinle Inc",
    "wof:placetype":"venue"
},
  "geometry": {"coordinates":[-81.647958,41.229305],"type":"Point"}
}