{
  "type": "Feature",
  "properties": {
    "addr:full":"14080 Brookpark Rd Cleveland OH 44135",
    "addr:housenumber":"14080",
    "addr:postcode":"44135",
    "addr:street":"Brookpark Rd",
    "iso:country":"US",
    "sg:address":"14080 Brookpark Rd",
    "sg:city":"Cleveland",
    "sg:classifiers":[
        {
            "category":"Retail",
            "subcategory":"Auto Rental",
            "type":"Services"
        }
    ],
    "sg:phone":"+1 216 267 4900",
    "sg:postcode":"44135",
    "sg:province":"OH",
    "sg:tags":[
        "renting",
        "leasing",
        "trailer"
    ],
    "wof:name":"XTRA Lease Inc",
    "wof:placetype":"venue"
},
  "geometry": {"coordinates":[-81.794752,41.418486],"type":"Point"}
}