{
  "type": "Feature",
  "properties": {
    "iso:country":"US",
    "sg:address":"10671 Evendale Dr",
    "sg:city":"Cincinnati",
    "sg:classifiers":[
        {
            "category":"Retail",
            "subcategory":"Repair Shop",
            "type":"Services"
        }
    ],
    "sg:phone":"+1 513 554 1604",
    "sg:postcode":"45241",
    "sg:province":"OH",
    "sg:tags":[
        "tank",
        "cleaning"
    ],
    "sg:website":"www.contactpsc.com",
    "wof:name":"Allwaste Tank Cleaning Inc",
    "wof:placetype":"venue"
},
  "geometry": {"coordinates":[-84.44099799999999,39.2554],"type":"Point"}
}