{
  "type": "Feature",
  "properties": {
    "iso:country":"US",
    "sg:address":"391 Preston Rd",
    "sg:city":"Vinton",
    "sg:classifiers":[
        {
            "category":"Freight",
            "type":"Transportation"
        }
    ],
    "sg:phone":"+1 740 388 0124",
    "sg:postcode":"45686",
    "sg:province":"OH",
    "sg:tags":[
        "operator",
        "local",
        "trucking"
    ],
    "wof:name":"Angles Trucking Inc",
    "wof:placetype":"venue"
},
  "geometry": {"coordinates":[-82.392649,38.97862],"type":"Point"}
}