{
  "type": "Feature",
  "properties": {
    "iso:country":"US",
    "sg:address":"2900 Kingston Ave",
    "sg:city":"Dayton",
    "sg:classifiers":[
        {
            "category":"Freight",
            "type":"Transportation"
        }
    ],
    "sg:phone":"+1 937 253 7347",
    "sg:postcode":"45420",
    "sg:province":"OH",
    "sg:tags":[
        "operator",
        "local",
        "trucking"
    ],
    "wof:name":"Baker Express Trucking Inc",
    "wof:placetype":"venue"
},
  "geometry": {"coordinates":[-84.13745299999999,39.723392],"type":"Point"}
}