{
  "type": "Feature",
  "properties": {
    "addr:full": "2900 Kingston Ave Dayton OH 45420",
    "addr:housenumber": "2900",
    "addr:postcode": "45420",
    "addr:street": "Kingston Ave",
    "iso:country": "US",
    "sg:address": "2900 Kingston Ave",
    "sg:city": "Dayton",
    "sg:classifiers": [
      {
        "category": "Freight",
        "type": "Transportation"
      }
    ],
    "sg:phone": "+1 937 253 7347",
    "sg:postcode": "45420",
    "sg:province": "OH",
    "sg:tags": [
      "operator",
      "local",
      "trucking"
    ],
    "wof:name": "Baker Express Trucking Inc",
    "wof:placetype": "venue"
  },
  "geometry": {"coordinates":[-84.137453,39.723392],"type":"Point"}
}
