{
  "type": "Feature",
  "properties": {
    "iso:country":"US",
    "sg:address":"136 N Breiel Blvd",
    "sg:city":"Middletown",
    "sg:classifiers":[
        {
            "category":"Health Services",
            "subcategory":"Doctor",
            "type":"Services"
        }
    ],
    "sg:phone":"+1 513 423 6654",
    "sg:postcode":"45042",
    "sg:province":"OH",
    "sg:tags":[
        "physician",
        "surgeon"
    ],
    "wof:name":"Barry A Robertson MD",
    "wof:placetype":"venue"
},
  "geometry": {"coordinates":[-84.35462099999999,39.510636],"type":"Point"}
}