{
  "type": "Feature",
  "properties": {
    "iso:country":"US",
    "sg:address":"720 Junction Ave",
    "sg:city":"Toledo",
    "sg:classifiers":[
        {
            "category":"Organizations",
            "subcategory":"Religious Organization",
            "type":"Services"
        }
    ],
    "sg:phone":"+1 419 246 3571",
    "sg:postcode":"43607",
    "sg:province":"OH",
    "sg:tags":[
        "church"
    ],
    "wof:name":"Beulah Baptist Church",
    "wof:placetype":"venue"
},
  "geometry": {"coordinates":[-83.577079,41.647024],"type":"Point"}
}