{
  "type": "Feature",
  "properties": {
    "addr:full":"5393 Sinclair Rd Columbus OH 43229",
    "addr:housenumber":"5393",
    "addr:postcode":"43229",
    "addr:street":"Sinclair Rd",
    "iso:country":"US",
    "sg:address":"5393 Sinclair Rd",
    "sg:city":"Columbus",
    "sg:classifiers":[
        {
            "category":"Organizations",
            "subcategory":"Religious Organization",
            "type":"Services"
        }
    ],
    "sg:phone":"+1 614 781 0508",
    "sg:postcode":"43229",
    "sg:province":"OH",
    "sg:tags":[
        "church"
    ],
    "wof:name":"Christ Embassy Intl",
    "wof:placetype":"venue"
},
  "geometry": {"coordinates":[-82.997828,40.076862],"type":"Point"}
}