{
  "type": "Feature",
  "properties": {
    "iso:country":"US",
    "sg:address":"2102 Elm Rd",
    "sg:city":"Cortland",
    "sg:classifiers":[
        {
            "category":"Autos & Motor Vehicles",
            "subcategory":"Motorcycle Sales",
            "type":"Retail Goods"
        }
    ],
    "sg:phone":"+1 330 395 4700",
    "sg:postcode":"44410",
    "sg:province":"OH",
    "sg:tags":[
        "scooter"
    ],
    "sg:website":"www.warrenharleydavidson.com",
    "wof:name":"Harley-Davidson Sales",
    "wof:placetype":"venue"
},
  "geometry": {"coordinates":[-80.766999,41.286353],"type":"Point"}
}