{
  "type": "Feature",
  "properties": {
    "addr:full": "7766 Blue Juniper Dr Westerville OH 43082",
    "addr:housenumber": "7766",
    "addr:postcode": "43082",
    "addr:street": "Blue Juniper Dr",
    "iso:country": "US",
    "sg:address": "7766 Blue Juniper Dr",
    "sg:city": "Westerville",
    "sg:classifiers": [
      {
        "category": "Personal",
        "type": "Services"
      }
    ],
    "sg:phone": "+1 614 865 4497",
    "sg:postcode": "43082",
    "sg:province": "OH",
    "sg:tags": [
      "wedding",
      "chapel"
    ],
    "wof:name": "Coldwell Banker/King Thompson",
    "wof:placetype": "venue"
  },
  "geometry": {"coordinates":[-82.94552,40.150948],"type":"Point"}
}
