{
  "type": "Feature",
  "properties": {
    "addr:full":"4486 Kemp Rd Dayton OH 45431",
    "addr:housenumber":"4486",
    "addr:postcode":"45431",
    "addr:street":"Kemp Rd",
    "iso:country":"US",
    "sg:address":"4486 Kemp Rd",
    "sg:city":"Dayton",
    "sg:classifiers":[
        {
            "category":"Personal",
            "type":"Services"
        }
    ],
    "sg:phone":"+1 937 431 0665",
    "sg:postcode":"45431",
    "sg:province":"OH",
    "sg:tags":[
        "therapist",
        "massage"
    ],
    "wof:name":"Julie Desorcy",
    "wof:placetype":"venue"
},
  "geometry": {"coordinates":[-84.099773,39.758013],"type":"Point"}
}