{
  "type": "Feature",
  "properties": {
    "addr:full":"2703 Independence Village Center Reynoldsburg OH 43068",
    "addr:housenumber":"2703",
    "addr:postcode":"43068",
    "addr:street":"Independence Village",
    "iso:country":"US",
    "sg:address":"2703 Independence Village Center",
    "sg:city":"Reynoldsburg",
    "sg:classifiers":[
        {
            "category":"Manufacturing",
            "subcategory":"Signs",
            "type":"Manufacturing & Wholesale Goods"
        }
    ],
    "sg:phone":"+1 614 861 7700",
    "sg:postcode":"43068",
    "sg:province":"OH",
    "sg:tags":[
        "specialty",
        "mfg"
    ],
    "wof:name":"Rapid Signs Inc",
    "wof:placetype":"venue"
},
  "geometry": {"coordinates":[-82.82941599999999,39.926312],"type":"Point"}
}