{
  "type": "Feature",
  "properties": {
    "addr:full": "5001 Monroe St Toledo OH 43606",
    "addr:housenumber": "5001",
    "addr:postcode": "43606",
    "addr:street": "Monroe St",
    "iso:country": "US",
    "sg:address": "5001 Monroe St",
    "sg:city": "Toledo",
    "sg:classifiers": [
      {
        "category": "Retail",
        "subcategory": "Portrait Studio",
        "type": "Services"
      }
    ],
    "sg:phone": "+1 419 473 9619",
    "sg:postcode": "43606",
    "sg:province": "OH",
    "sg:tags": [
      "photographer"
    ],
    "wof:name": "J C Penney Portrait Studio",
    "wof:placetype": "venue"
  },
  "geometry": {"coordinates":[-83.642016,41.697742],"type":"Point"}
}
