{
  "type": "Feature",
  "properties": {
    "iso:country":"US",
    "sg:address":"1435 E 357th St",
    "sg:city":"Willoughby",
    "sg:classifiers":[
        {
            "category":"Building & Trades",
            "subcategory":"Construction",
            "type":"Services"
        }
    ],
    "sg:phone":"+1 440 942 6999",
    "sg:postcode":"44095",
    "sg:province":"OH",
    "sg:tags":[
        "contractor"
    ],
    "wof:name":"Sure Seal Roofing",
    "wof:placetype":"venue"
},
  "geometry": {"coordinates":[-81.433625,41.640784],"type":"Point"}
}