{
  "type": "Feature",
  "properties": {
    "addr:full": "6593 E Main St Reynoldsburg OH 43068",
    "addr:housenumber": "6593",
    "addr:postcode": "43068",
    "addr:street": "E Main St",
    "iso:country": "US",
    "sg:address": "6593 E Main St",
    "sg:city": "Reynoldsburg",
    "sg:classifiers": [
      {
        "category": "Retail",
        "subcategory": "Self-service Laundry",
        "type": "Services"
      }
    ],
    "sg:phone": "+1 614 863 0366",
    "sg:postcode": "43068",
    "sg:province": "OH",
    "wof:name": "All-Nite Coin Laundry",
    "wof:placetype": "venue"
  },
  "geometry": {"coordinates":[-82.820793,39.954858],"type":"Point"}
}
