{
  "type": "Feature",
  "properties": {
    "iso:country":"US",
    "sg:address":"5500 Frantz Rd",
    "sg:city":"Dublin",
    "sg:classifiers":[
        {
            "category":"Professional",
            "subcategory":"Accounting & Tax Preparation",
            "type":"Services"
        }
    ],
    "sg:phone":"+1 614 793 5300",
    "sg:postcode":"43017",
    "sg:province":"OH",
    "sg:tags":[
        "accountant"
    ],
    "wof:name":"Charles B Zehnder Co",
    "wof:placetype":"venue"
},
  "geometry": {"coordinates":[-83.12304399999999,40.079291],"type":"Point"}
}