{
  "type": "Feature",
  "properties": {
    "iso:country":"US",
    "sg:address":"7818 Sycamore St",
    "sg:city":"Maineville",
    "sg:classifiers":[
        {
            "category":"Manufacturing",
            "subcategory":"Apparel",
            "type":"Manufacturing & Wholesale Goods"
        }
    ],
    "sg:phone":"+1 513 583 9355",
    "sg:postcode":"45039",
    "sg:province":"OH",
    "wof:name":"A Stitch In Time",
    "wof:placetype":"venue"
},
  "geometry": {"coordinates":[-84.226834,39.318022],"type":"Point"}
}