{
  "type": "Feature",
  "properties": {
    "addr:full":"322 W Main St Mason OH 45040",
    "addr:housenumber":"322",
    "addr:postcode":"45040",
    "addr:street":"W Main St",
    "iso:country":"US",
    "sg:address":"322 W Main St",
    "sg:city":"Mason",
    "sg:classifiers":[
        {
            "category":"Insurance",
            "subcategory":"Insurance Agent",
            "type":"Services"
        }
    ],
    "sg:phone":"+1 513 459 6400",
    "sg:postcode":"45040",
    "sg:province":"OH",
    "wof:name":"Herb Shoufler Insurance",
    "wof:placetype":"venue"
},
  "geometry": {"coordinates":[-84.313467,39.360568],"type":"Point"}
}