{
  "type": "Feature",
  "properties": {
    "addr:full":"118 N Goodrich St Oregon OH 43616",
    "addr:housenumber":"118",
    "addr:postcode":"43616",
    "addr:street":"N Goodrich St",
    "iso:country":"US",
    "sg:address":"118 N Goodrich St",
    "sg:city":"Oregon",
    "sg:classifiers":[
        {
            "category":"Arts & Performance",
            "subcategory":"Theater",
            "type":"Entertainment"
        }
    ],
    "sg:phone":"+1 419 691 1398",
    "sg:postcode":"43616",
    "sg:province":"OH",
    "sg:tags":[
        "theatrical"
    ],
    "wof:name":"Oregon Community Theatre",
    "wof:placetype":"venue"
},
  "geometry": {"coordinates":[-83.471378,41.653711],"type":"Point"}
}