{
  "type": "Feature",
  "properties": {
    "addr:full":"3250 Refugee Rd Columbus OH 43232",
    "addr:housenumber":"3250",
    "addr:postcode":"43232",
    "addr:street":"Refugee Rd",
    "iso:country":"US",
    "sg:address":"3250 Refugee Rd",
    "sg:city":"Columbus",
    "sg:classifiers":[
        {
            "category":"Restaurant",
            "type":"Food & Drink"
        }
    ],
    "sg:phone":"+1 614 235 7100",
    "sg:postcode":"43232",
    "sg:province":"OH",
    "sg:tags":[
        "bar",
        "family"
    ],
    "wof:name":"Berwick Manor Party Hse & Rest",
    "wof:placetype":"venue"
},
  "geometry": {"coordinates":[-82.911975,39.917356],"type":"Point"}
}