{
  "type": "Feature",
  "properties": {
    "iso:country":"US",
    "sg:address":"5804 Hamilton Ave",
    "sg:city":"Cincinnati",
    "sg:classifiers":[
        {
            "category":"Food & Beverages",
            "subcategory":"Groceries & Convenience Stores",
            "type":"Retail Goods"
        }
    ],
    "sg:phone":"+1 513 681 5839",
    "sg:postcode":"45224",
    "sg:province":"OH",
    "wof:name":"Dairy Mart Convenience Store",
    "wof:placetype":"venue"
},
  "geometry": {"coordinates":[-84.54658000000001,39.198664],"type":"Point"}
}