{
  "type": "Feature",
  "properties": {
    "addr:full":"1615 S Alex Rd Dayton OH 45449",
    "addr:housenumber":"1615",
    "addr:postcode":"45449",
    "addr:street":"S Alex Rd",
    "iso:country":"US",
    "sg:address":"1615 S Alex Rd",
    "sg:city":"Dayton",
    "sg:classifiers":[
        {
            "category":"Health Services",
            "subcategory":"Chiropractor",
            "type":"Services"
        }
    ],
    "sg:phone":"+1 937 866 2114",
    "sg:postcode":"45449",
    "sg:province":"OH",
    "wof:name":"Gentle Chiropractic",
    "wof:placetype":"venue"
},
  "geometry": {"coordinates":[-84.242285,39.656628],"type":"Point"}
}