{
  "type": "Feature",
  "properties": {
    "iso:country":"US",
    "sg:address":"884 W Liberty St",
    "sg:city":"Hubbard",
    "sg:classifiers":[
        {
            "category":"Personal",
            "subcategory":"Beauty Salon",
            "type":"Services"
        }
    ],
    "sg:phone":"+1 330 534 0803",
    "sg:postcode":"44425",
    "sg:province":"OH",
    "sg:tags":[
        "hair",
        "stylist"
    ],
    "sg:website":"http://www.regiscorp.com",
    "wof:name":"Famous Hair",
    "wof:placetype":"venue"
},
  "geometry": {"coordinates":[-80.58396,41.156335],"type":"Point"}
}