{
  "type": "Feature",
  "properties": {
    "iso:country":"US",
    "sg:address":"900 Summit St NW",
    "sg:city":"Warren",
    "sg:classifiers":[
        {
            "category":"Shopping",
            "subcategory":"Bicycles & Sporting Goods",
            "type":"Retail Goods"
        }
    ],
    "sg:phone":"+1 330 373 6177",
    "sg:postcode":"44485",
    "sg:province":"OH",
    "wof:name":"Second Chance Goods",
    "wof:placetype":"venue"
},
  "geometry": {"coordinates":[-80.832115,41.242308],"type":"Point"}
}