{
  "type": "Feature",
  "properties": {
    "addr:full":"521 Beech Rd Mansfield OH 44906",
    "addr:housenumber":"521",
    "addr:postcode":"44906",
    "addr:street":"Beech Rd",
    "iso:country":"US",
    "sg:address":"521 Beech Rd",
    "sg:city":"Mansfield",
    "sg:classifiers":[
        {
            "category":"Insurance",
            "subcategory":"Insurance Agent",
            "type":"Services"
        }
    ],
    "sg:phone":"+1 419 529 9161",
    "sg:postcode":"44906",
    "sg:province":"OH",
    "wof:name":"Tom Clu Moloney Insurance",
    "wof:placetype":"venue"
},
  "geometry": {"coordinates":[-82.577821,40.745653],"type":"Point"}
}