{
  "type": "Feature",
  "properties": {
    "addr:full": "650 Sugar Ln Elyria OH 44035",
    "addr:housenumber": "650",
    "addr:postcode": "44035",
    "addr:street": "Sugar Ln",
    "iso:country": "US",
    "sg:address": "650 Sugar Ln",
    "sg:city": "Elyria",
    "sg:classifiers": [
      {
        "category": "Manufacturing",
        "subcategory": "Metals",
        "type": "Manufacturing \u0026 Wholesale Goods"
      }
    ],
    "sg:phone": "+1 440 365 0600",
    "sg:postcode": "44035",
    "sg:province": "OH",
    "sg:tags": [
      "steel",
      "mills"
    ],
    "sg:website": "www.denne.com",
    "wof:name": "Denne Industries",
    "wof:placetype": "venue"
  },
  "geometry": {"coordinates":[-82.072922,41.361589],"type":"Point"}
}
