{
  "type": "Feature",
  "properties": {
    "iso:country":"US",
    "sg:address":"650 Sugar Ln",
    "sg:city":"Elyria",
    "sg:classifiers":[
        {
            "category":"Manufacturing",
            "subcategory":"Metals",
            "type":"Manufacturing & Wholesale Goods"
        }
    ],
    "sg:phone":"+1 440 365 0600",
    "sg:postcode":"44035",
    "sg:province":"OH",
    "sg:tags":[
        "steel",
        "mills"
    ],
    "sg:website":"www.denne.com",
    "wof:name":"Denne Industries",
    "wof:placetype":"venue"
},
  "geometry": {"coordinates":[-82.072922,41.361589],"type":"Point"}
}