{
  "type": "Feature",
  "properties": {
    "addr:full": "17504 Saint Clair Ave Cleveland OH 44110",
    "addr:housenumber": "17504",
    "addr:postcode": "44110",
    "addr:street": "Saint Clair Ave",
    "iso:country": "US",
    "sg:address": "17504 Saint Clair Ave",
    "sg:city": "Cleveland",
    "sg:classifiers": [
      {
        "category": "Food \u0026 Beverages",
        "subcategory": "Bakery",
        "type": "Retail Goods"
      }
    ],
    "sg:phone": "+1 216 486 2402",
    "sg:postcode": "44110",
    "sg:province": "OH",
    "wof:name": "Bonnie Lynn Donuts",
    "wof:placetype": "venue"
  },
  "geometry": {"coordinates":[-81.556873,41.567313],"type":"Point"}
}
