{
  "type": "Feature",
  "properties": {
    "addr:full": "1149 Asbury Rd Cincinnati OH 45255",
    "addr:housenumber": "1149",
    "addr:postcode": "45255",
    "addr:street": "Asbury Rd",
    "iso:country": "US",
    "sg:address": "1149 Asbury Rd",
    "sg:city": "Cincinnati",
    "sg:classifiers": [
      {
        "category": "Real Estate",
        "subcategory": "Real Estate Operator",
        "type": "Services"
      }
    ],
    "sg:phone": "+1 513 231 1446",
    "sg:postcode": "45255",
    "sg:province": "OH",
    "sg:tags": [
      "building",
      "apartment"
    ],
    "wof:name": "Asbury Woods Seniors Apts",
    "wof:placetype": "venue"
  },
  "geometry": {"coordinates":[-84.341807,39.071585],"type":"Point"}
}
