{
  "type": "Feature",
  "properties": {
    "addr:full": "1784 S 4th St Columbus OH 43207",
    "addr:housenumber": "1784",
    "addr:postcode": "43207",
    "addr:street": "S 4Th St",
    "iso:country": "US",
    "sg:address": "1784 S 4th St",
    "sg:city": "Columbus",
    "sg:classifiers": [
      {
        "category": "Building \u0026 Trades",
        "subcategory": "Construction",
        "type": "Services"
      }
    ],
    "sg:phone": "+1 614 443 3415",
    "sg:postcode": "43207",
    "sg:province": "OH",
    "sg:tags": [
      "contractor"
    ],
    "wof:name": "Lula M Bailey",
    "wof:placetype": "venue"
  },
  "geometry": {"coordinates":[-82.993265,39.925666],"type":"Point"}
}
