{
  "type": "Feature",
  "properties": {
    "addr:full": "1781 Bechtle Ave Springfield OH 45504",
    "addr:housenumber": "1781",
    "addr:postcode": "45504",
    "addr:street": "Bechtle Ave",
    "iso:country": "US",
    "sg:address": "1781 Bechtle Ave",
    "sg:city": "Springfield",
    "sg:classifiers": [
      {
        "category": "Restaurant",
        "type": "Food \u0026 Drink"
      }
    ],
    "sg:phone": "+1 937 399 5888",
    "sg:postcode": "45504",
    "sg:province": "OH",
    "wof:name": "Golden Bowl",
    "wof:placetype": "venue"
  },
  "geometry": {"coordinates":[-83.835819,39.941841],"type":"Point"}
}
