{
  "type": "Feature",
  "properties": {
    "addr:full": "139 Pounder Ave Galion OH 44833",
    "addr:housenumber": "139",
    "addr:postcode": "44833",
    "addr:street": "Pounder Ave",
    "iso:country": "US",
    "sg:address": "139 Pounder Ave",
    "sg:city": "Galion",
    "sg:classifiers": [
      {
        "category": "Mining \u0026 Drilling",
        "type": "Manufacturing \u0026 Wholesale Goods"
      }
    ],
    "sg:phone": "+1 419 468 0177",
    "sg:postcode": "44833",
    "sg:province": "OH",
    "sg:tags": [
      "crude",
      "production",
      "gas"
    ],
    "wof:name": "M A P Crude Petroleum \u0026 Naturl",
    "wof:placetype": "venue"
  },
  "geometry": {"coordinates":[-82.767853,40.733045],"type":"Point"}
}
