{
  "type": "Feature",
  "properties": {
    "iso:country":"US",
    "sg:address":"139 Pounder Ave",
    "sg:city":"Galion",
    "sg:classifiers":[
        {
            "category":"Mining & Drilling",
            "type":"Manufacturing & Wholesale Goods"
        }
    ],
    "sg:phone":"+1 419 468 0177",
    "sg:postcode":"44833",
    "sg:province":"OH",
    "sg:tags":[
        "crude",
        "production",
        "gas"
    ],
    "wof:name":"M A P Crude Petroleum & Naturl",
    "wof:placetype":"venue"
},
  "geometry": {"coordinates":[-82.767853,40.733045],"type":"Point"}
}