{
  "type": "Feature",
  "properties": {
    "iso:country":"US",
    "sg:address":"446 Woodrow St",
    "sg:city":"Akron",
    "sg:classifiers":[
        {
            "category":"Building & Trades",
            "subcategory":"Construction",
            "type":"Services"
        }
    ],
    "sg:phone":"+1 330 376 8184",
    "sg:postcode":"44303",
    "sg:province":"OH",
    "sg:tags":[
        "contractor"
    ],
    "wof:name":"Davenport Productions",
    "wof:placetype":"venue"
},
  "geometry": {"coordinates":[-81.53567700000001,41.103213],"type":"Point"}
}