{
  "type": "Feature",
  "properties": {
    "addr:full": "446 Woodrow St Akron OH 44303",
    "addr:housenumber": "446",
    "addr:postcode": "44303",
    "addr:street": "Woodrow St",
    "iso:country": "US",
    "sg:address": "446 Woodrow St",
    "sg:city": "Akron",
    "sg:classifiers": [
      {
        "category": "Building \u0026 Trades",
        "subcategory": "Construction",
        "type": "Services"
      }
    ],
    "sg:phone": "+1 330 376 8184",
    "sg:postcode": "44303",
    "sg:province": "OH",
    "sg:tags": [
      "contractor"
    ],
    "wof:name": "Davenport Productions",
    "wof:placetype": "venue"
  },
  "geometry": {"coordinates":[-81.535677,41.103213],"type":"Point"}
}
