{
  "type": "Feature",
  "properties": {
    "addr:full":"7019 Roundelay Rd N Reynoldsburg OH 43068",
    "addr:housenumber":"7019",
    "addr:postcode":"43068",
    "addr:street":"Roundelay Rd N",
    "iso:country":"US",
    "sg:address":"7019 Roundelay Rd N",
    "sg:city":"Reynoldsburg",
    "sg:classifiers":[
        {
            "category":"Professional",
            "subcategory":"Advertising",
            "type":"Services"
        }
    ],
    "sg:phone":"+1 614 870 2539",
    "sg:postcode":"43068",
    "sg:province":"OH",
    "wof:name":"Balloon Masters",
    "wof:placetype":"venue"
},
  "geometry": {"coordinates":[-82.809628,39.962717],"type":"Point"}
}