{
  "type": "Feature",
  "properties": {
    "iso:country":"US",
    "sg:address":"130 S Chillicothe Rd",
    "sg:city":"Aurora",
    "sg:classifiers":[
        {
            "category":"Government",
            "subcategory":"Office",
            "type":"Public Place"
        }
    ],
    "sg:phone":"+1 330 562 6131",
    "sg:postcode":"44202",
    "sg:province":"OH",
    "sg:tags":[
        "city"
    ],
    "sg:website":"www.auroraoh.com",
    "wof:name":"Aurora City Hall",
    "wof:placetype":"venue"
},
  "geometry": {"coordinates":[-81.345592,41.313175],"type":"Point"}
}