{
  "type": "Feature",
  "properties": {
    "iso:country":"US",
    "sg:address":"180 E Main St",
    "sg:city":"Wilmington",
    "sg:classifiers":[
        {
            "category":"Organizations",
            "subcategory":"Non-profit Organization",
            "type":"Services"
        }
    ],
    "sg:phone":"+1 937 382 8359",
    "sg:postcode":"45177",
    "sg:province":"OH",
    "sg:tags":[
        "action",
        "agency",
        "community"
    ],
    "wof:name":"Joes Java House",
    "wof:placetype":"venue"
},
  "geometry": {"coordinates":[-83.823492,39.445255],"type":"Point"}
}