{
  "type": "Feature",
  "properties": {
    "addr:full":"133 Homeworth Rd Alliance OH 44601",
    "addr:housenumber":"133",
    "addr:postcode":"44601",
    "addr:street":"Homeworth Rd",
    "iso:country":"US",
    "sg:address":"133 Homeworth Rd",
    "sg:city":"Alliance",
    "sg:classifiers":[
        {
            "category":"Manufacturing",
            "subcategory":"Glass & Minerals",
            "type":"Manufacturing & Wholesale Goods"
        }
    ],
    "sg:phone":"+1 330 821 9244",
    "sg:postcode":"44601",
    "sg:province":"OH",
    "sg:tags":[
        "ready",
        "concrete",
        "mfg"
    ],
    "wof:name":"Alliance Redi Mix Inc",
    "wof:placetype":"venue"
},
  "geometry": {"coordinates":[-81.077742,40.899697],"type":"Point"}
}