{
  "type": "Feature",
  "properties": {
    "addr:full":"530 N Freedom St Ravenna OH 44266",
    "addr:housenumber":"530",
    "addr:postcode":"44266",
    "addr:street":"N Freedom St",
    "iso:country":"US",
    "sg:address":"530 N Freedom St",
    "sg:city":"Ravenna",
    "sg:classifiers":[
        {
            "category":"Government",
            "subcategory":"Office",
            "type":"Public Place"
        }
    ],
    "sg:phone":"+1 330 872 6012",
    "sg:postcode":"44266",
    "sg:province":"OH",
    "sg:tags":[
        "state",
        "security"
    ],
    "wof:name":"National Guard",
    "wof:placetype":"venue"
},
  "geometry": {"coordinates":[-81.23283600000001,41.164069],"type":"Point"}
}