{
  "type": "Feature",
  "properties": {
    "iso:country":"US",
    "sg:address":"233 W Bridge St",
    "sg:city":"Dublin",
    "sg:classifiers":[
        {
            "category":"Shopping",
            "subcategory":"Clothing, Apparel, & Fashions",
            "type":"Retail Goods"
        }
    ],
    "sg:phone":"+1 614 764 8508",
    "sg:postcode":"43017",
    "sg:province":"OH",
    "sg:tags":[
        "ready"
    ],
    "wof:name":"Britt & Jack Futures",
    "wof:placetype":"venue"
},
  "geometry": {"coordinates":[-83.120715,40.099117],"type":"Point"}
}