{
  "type": "Feature",
  "properties": {
    "addr:full":"134 Patton Ave Dayton OH 45427",
    "addr:housenumber":"134",
    "addr:postcode":"45427",
    "addr:street":"Patton Ave",
    "iso:country":"US",
    "sg:address":"134 Patton Ave",
    "sg:city":"Dayton",
    "sg:classifiers":[
        {
            "category":"Wholesale",
            "subcategory":"Dairy",
            "type":"Manufacturing & Wholesale Goods"
        }
    ],
    "sg:phone":"+1 937 461 4536",
    "sg:postcode":"45427",
    "sg:province":"OH",
    "sg:tags":[
        "product"
    ],
    "wof:name":"Southern Belle Tavern",
    "wof:placetype":"venue"
},
  "geometry": {"coordinates":[-84.270655,39.751273],"type":"Point"}
}