{
  "type": "Feature",
  "properties": {
    "addr:full": "2518 Oxford State Rd Middletown OH 45044",
    "addr:housenumber": "2518",
    "addr:postcode": "45044",
    "addr:street": "Oxford State Rd",
    "iso:country": "US",
    "sg:address": "2518 Oxford State Rd",
    "sg:city": "Middletown",
    "sg:classifiers": [
      {
        "category": "Freight",
        "type": "Transportation"
      }
    ],
    "sg:phone": "+1 513 424 6978",
    "sg:postcode": "45044",
    "sg:province": "OH",
    "sg:tags": [
      "terminal",
      "truck"
    ],
    "wof:name": "J P Transportation Co",
    "wof:placetype": "venue"
  },
  "geometry": {"coordinates":[-84.383752,39.475337],"type":"Point"}
}
