{
  "type": "Feature",
  "properties": {
    "addr:full":"744 Miller St Youngstown OH 44502",
    "addr:housenumber":"744",
    "addr:postcode":"44502",
    "addr:street":"Miller St",
    "iso:country":"US",
    "sg:address":"744 Miller St",
    "sg:city":"Youngstown",
    "sg:classifiers":[
        {
            "category":"Professional",
            "type":"Services"
        }
    ],
    "sg:phone":"+1 330 782 4867",
    "sg:postcode":"44502",
    "sg:province":"OH",
    "wof:name":"Joseph C Lewis",
    "wof:placetype":"venue"
},
  "geometry": {"coordinates":[-80.641231,41.073718],"type":"Point"}
}