{
  "type": "Feature",
  "properties": {
    "addr:full": "101 W 4th St Cincinnati OH 45202",
    "addr:housenumber": "101",
    "addr:postcode": "45202",
    "addr:street": "W 4Th St",
    "iso:country": "US",
    "sg:address": "101 W 4th St",
    "sg:city": "Cincinnati",
    "sg:classifiers": [
      {
        "category": "Bars \u0026 Pubs",
        "type": "Food \u0026 Drink"
      }
    ],
    "sg:phone": "+1 513 784 1999",
    "sg:postcode": "45202",
    "sg:province": "OH",
    "sg:tags": [
      "drinking"
    ],
    "wof:name": "Federal Reserve Piano Lounge",
    "wof:placetype": "venue"
  },
  "geometry": {"coordinates":[-84.515883,39.09946],"type":"Point"}
}
