{
  "type": "Feature",
  "properties": {
    "addr:full": "4770 Everhard Rd NW Canton OH 44718",
    "addr:postcode": "4770;44718",
    "addr:street": "Everhard Rd Nw",
    "iso:country": "US",
    "sg:address": "4770 Everhard Rd NW",
    "sg:city": "Canton",
    "sg:classifiers": [
      {
        "category": "Personal",
        "subcategory": "Beauty Salon",
        "type": "Services"
      }
    ],
    "sg:phone": "+1 330 966 1955",
    "sg:postcode": "44718",
    "sg:province": "OH",
    "wof:name": "Due Amicci Elite Salons \u0026 The",
    "wof:placetype": "venue"
  },
  "geometry": {"coordinates":[-81.437272,40.855172],"type":"Point"}
}
