{
  "type": "Feature",
  "properties": {
    "addr:full":"430 E Main Cross St Findlay OH 45840",
    "addr:housenumber":"430",
    "addr:postcode":"oh 45840",
    "addr:street":"E Main Cross St",
    "iso:country":"US",
    "sg:address":"430 E Main Cross St",
    "sg:city":"Findlay",
    "sg:classifiers":[
        {
            "category":"Autos & Motor Vehicles",
            "subcategory":"Automobile Sales",
            "type":"Retail Goods"
        }
    ],
    "sg:phone":"+1 419 422 1192",
    "sg:postcode":"45840",
    "sg:province":"OH",
    "sg:tags":[
        "car",
        "used",
        "dealer"
    ],
    "wof:name":"H & M Motor Sales",
    "wof:placetype":"venue"
},
  "geometry": {"coordinates":[-83.643871,41.039141],"type":"Point"}
}