{
  "type": "Feature",
  "properties": {
    "addr:full": "4955 Seaman St Oregon OH 43616",
    "addr:housenumber": "4955",
    "addr:postcode": "43616",
    "addr:street": "Seaman St",
    "iso:country": "US",
    "sg:address": "4955 Seaman St",
    "sg:city": "Oregon",
    "sg:classifiers": [
      {
        "category": "Government",
        "subcategory": "Office",
        "type": "Public Place"
      }
    ],
    "sg:phone": "+1 419 693 0761",
    "sg:postcode": "43616",
    "sg:province": "OH",
    "sg:tags": [
      "administrative",
      "program",
      "health"
    ],
    "wof:name": "Board of Mental Retardation",
    "wof:placetype": "venue"
  },
  "geometry": {"coordinates":[-83.437752,41.652173],"type":"Point"}
}
