{
  "type": "Feature",
  "properties": {
    "addr:full":"1729 Indian Wood Cir Maumee OH 43537",
    "addr:housenumber":"1729",
    "addr:postcode":"43537",
    "addr:street":"Indian Wood Cir",
    "iso:country":"US",
    "sg:address":"1729 Indian Wood Cir",
    "sg:city":"Maumee",
    "sg:classifiers":[
        {
            "category":"Organizations",
            "subcategory":"Religious Organization",
            "type":"Services"
        }
    ],
    "sg:phone":"+1 419 897 9770",
    "sg:postcode":"43537",
    "sg:province":"OH",
    "wof:name":"Toledo Dst Untd Methdst Church",
    "wof:placetype":"venue"
},
  "geometry": {"coordinates":[-83.68346099999999,41.589404],"type":"Point"}
}