{
  "type": "Feature",
  "properties": {
    "iso:country":"US",
    "sg:address":"510 Elmgrove Ter",
    "sg:city":"Middletown",
    "sg:classifiers":[
        {
            "category":"Real Estate",
            "subcategory":"Real Estate Operator",
            "type":"Services"
        }
    ],
    "sg:phone":"+1 513 424 2013",
    "sg:postcode":"45044",
    "sg:province":"OH",
    "sg:tags":[
        "building",
        "apartment"
    ],
    "wof:name":"Elmgrove Apartments",
    "wof:placetype":"venue"
},
  "geometry": {"coordinates":[-84.41816300000001,39.492345],"type":"Point"}
}