{
  "type": "Feature",
  "properties": {
    "iso:country":"US",
    "sg:address":"150 S Washington St",
    "sg:city":"Greenfield",
    "sg:classifiers":[
        {
            "category":"Manufacturing",
            "subcategory":"Apparel",
            "type":"Manufacturing & Wholesale Goods"
        }
    ],
    "sg:phone":"+1 937 981 3716",
    "sg:postcode":"45123",
    "sg:province":"OH",
    "sg:tags":[
        "embroidery"
    ],
    "wof:name":"Jetts Professional Embroidery",
    "wof:placetype":"venue"
},
  "geometry": {"coordinates":[-83.382865,39.350968],"type":"Point"}
}