{
  "type": "Feature",
  "properties": {
    "iso:country":"US",
    "sg:address":"784 Thurber Dr W",
    "sg:city":"Columbus",
    "sg:classifiers":[
        {
            "category":"Real Estate",
            "subcategory":"Real Estate Operator",
            "type":"Services"
        }
    ],
    "sg:phone":"+1 614 461 9017",
    "sg:postcode":"43215",
    "sg:province":"OH",
    "sg:tags":[
        "apartment"
    ],
    "wof:name":"Alexandria Colony",
    "wof:placetype":"venue"
},
  "geometry": {"coordinates":[-83.01634799999999,39.976959],"type":"Point"}
}