{
  "type": "Feature",
  "properties": {
    "iso:country":"US",
    "sg:address":"602 Broadway Ave",
    "sg:city":"Sidney",
    "sg:classifiers":[
        {
            "category":"Utilities",
            "subcategory":"Refuse",
            "type":"Services"
        }
    ],
    "sg:phone":"+1 937 492 9291",
    "sg:postcode":"45365",
    "sg:province":"OH",
    "sg:tags":[
        "system"
    ],
    "wof:name":"Recycling Haus",
    "wof:placetype":"venue"
},
  "geometry": {"coordinates":[-84.15018499999999,40.292453],"type":"Point"}
}