{
  "type": "Feature",
  "properties": {
    "addr:full": "52 Clairmont Dr Painesville OH 44077",
    "addr:housenumber": "52",
    "addr:postcode": "44077",
    "addr:street": "Clairmont Dr",
    "iso:country": "US",
    "sg:address": "52 Clairmont Dr",
    "sg:city": "Painesville",
    "sg:classifiers": [
      {
        "category": "Building \u0026 Trades",
        "subcategory": "Construction",
        "type": "Services"
      }
    ],
    "sg:phone": "+1 440 357 1758",
    "sg:postcode": "44077",
    "sg:province": "OH",
    "sg:tags": [
      "contractor"
    ],
    "wof:name": "Admiral Deck Cleaning \u0026 Svcs",
    "wof:placetype": "venue"
  },
  "geometry": {"coordinates":[-81.280648,41.700004],"type":"Point"}
}
