{
  "type": "Feature",
  "properties": {
    "addr:full": "6523 Bridgeton Manor Ct Hamilton OH 45011",
    "addr:housenumber": "6523",
    "addr:postcode": "45011",
    "addr:street": "Bridgeton Manor Ct",
    "iso:country": "US",
    "sg:address": "6523 Bridgeton Manor Ct",
    "sg:city": "Hamilton",
    "sg:classifiers": [
      {
        "category": "Professional",
        "subcategory": "Research",
        "type": "Services"
      }
    ],
    "sg:phone": "+1 513 759 5333",
    "sg:postcode": "45011",
    "sg:province": "OH",
    "sg:tags": [
      "environmental",
      "ecological"
    ],
    "wof:name": "Herlihy Enterprises Inc",
    "wof:placetype": "venue"
  },
  "geometry": {"coordinates":[-84.416133,39.389391],"type":"Point"}
}
