{
  "type": "Feature",
  "properties": {
    "iso:country":"US",
    "sg:address":"520 Slocum St",
    "sg:city":"Lancaster",
    "sg:classifiers":[
        {
            "category":"Manufacturing",
            "subcategory":"Tools & Machinery",
            "type":"Manufacturing & Wholesale Goods"
        }
    ],
    "sg:phone":"+1 740 653 3421",
    "sg:postcode":"43130",
    "sg:province":"OH",
    "sg:tags":[
        "shop",
        "jig",
        "mfg",
        "die",
        "fixture",
        "machine",
        "parts"
    ],
    "wof:name":"Lancaster Metal Products Inc",
    "wof:placetype":"venue"
},
  "geometry": {"coordinates":[-82.612855,39.719492],"type":"Point"}
}