{
  "type": "Feature",
  "properties": {
    "addr:full": "9 Main St Greenwich OH 44837",
    "addr:housenumber": "9",
    "addr:postcode": "44837",
    "addr:street": "Main St",
    "iso:country": "US",
    "sg:address": "9 Main St",
    "sg:city": "Greenwich",
    "sg:classifiers": [
      {
        "category": "Shopping",
        "subcategory": "Florist",
        "type": "Retail Goods"
      }
    ],
    "sg:phone": "+1 419 752 0405",
    "sg:postcode": "44837",
    "sg:province": "OH",
    "wof:name": "Old Glory Florist \u0026 Gifts",
    "wof:placetype": "venue"
  },
  "geometry": {"coordinates":[-82.518352,41.029899],"type":"Point"}
}
