{
  "type": "Feature",
  "properties": {
    "iso:country":"US",
    "sg:address":"8743 Leavitt Rd",
    "sg:city":"Elyria",
    "sg:classifiers":[
        {
            "category":"Wholesale",
            "subcategory":"Construction Materials",
            "type":"Manufacturing & Wholesale Goods"
        },
        {
            "category":"Building & Trades",
            "subcategory":"Construction",
            "type":"Services"
        }
    ],
    "sg:phone":"+1 440 986 2788",
    "sg:postcode":"44035",
    "sg:province":"OH",
    "sg:tags":[
        "shed",
        "general",
        "utility"
    ],
    "wof:name":"Heartland Sales Center",
    "wof:placetype":"venue"
},
  "geometry": {"coordinates":[-82.21036,41.366707],"type":"Point"}
}