{
  "type": "Feature",
  "properties": {
    "addr:full": "1118 Pierce Ave Sharpsville OH 16150",
    "addr:housenumber": "1118",
    "addr:postcode": "16150",
    "addr:street": "Pierce Ave",
    "iso:country": "US",
    "sg:address": "1118 Pierce Ave",
    "sg:city": "Sharpsville",
    "sg:classifiers": [
      {
        "category": "Health Services",
        "subcategory": "Doctor",
        "type": "Services"
      }
    ],
    "sg:phone": "+1   ",
    "sg:postcode": "16150",
    "sg:province": "OH",
    "wof:name": "Jackie Lous Dance Studio",
    "wof:placetype": "venue"
  },
  "geometry": {"coordinates":[-80.490197,41.258093],"type":"Point"}
}
