{
  "type": "Feature",
  "properties": {
    "addr:full":"109 Locust St Pleasant Hill OH 45359",
    "addr:housenumber":"109",
    "addr:postcode":"45359",
    "addr:street":"Locust St",
    "iso:country":"US",
    "sg:address":"109 Locust St",
    "sg:city":"Pleasant Hill",
    "sg:classifiers":[
        {
            "category":"Professional",
            "subcategory":"Management & Consulting",
            "type":"Services"
        }
    ],
    "sg:phone":"+1 937 676 2160",
    "sg:postcode":"45359",
    "sg:province":"OH",
    "sg:tags":[
        "construction"
    ],
    "wof:name":"Stern-Delcamp Construction",
    "wof:placetype":"venue"
},
  "geometry": {"coordinates":[-84.339461,40.053422],"type":"Point"}
}