{
  "type": "Feature",
  "properties": {
    "iso:country":"US",
    "sg:address":"2607 Woodville Pike",
    "sg:city":"Goshen",
    "sg:classifiers":[
        {
            "category":"Building & Trades",
            "subcategory":"Construction",
            "type":"Services"
        }
    ],
    "sg:phone":"+1 513 625 8930",
    "sg:postcode":"45122",
    "sg:province":"OH",
    "sg:tags":[
        "excavation"
    ],
    "wof:name":"Connie Knuckles Cnstr LLC",
    "wof:placetype":"venue"
},
  "geometry": {"coordinates":[-84.082115,39.223803],"type":"Point"}
}