{
  "type": "Feature",
  "properties": {
    "iso:country":"US",
    "sg:address":"216 Hartford Ave SE",
    "sg:city":"Canton",
    "sg:classifiers":[
        {
            "category":"Education",
            "subcategory":"Library",
            "type":"Public Place"
        }
    ],
    "sg:phone":"+1 330 452 9014",
    "sg:postcode":"44707",
    "sg:province":"OH",
    "wof:name":"Dehoff Library",
    "wof:placetype":"venue"
},
  "geometry": {"coordinates":[-81.354249,40.79294],"type":"Point"}
}