{
  "type": "Feature",
  "properties": {
    "addr:full": "2101 Sawbury Blvd Columbus OH 43235",
    "addr:housenumber": "2101",
    "addr:postcode": "43235",
    "addr:street": "Sawbury Blvd",
    "iso:country": "US",
    "sg:address": "2101 Sawbury Blvd",
    "sg:city": "Columbus",
    "sg:classifiers": [
      {
        "category": "Building \u0026 Trades",
        "subcategory": "Construction",
        "type": "Services"
      }
    ],
    "sg:phone": "+1 614 761 2782",
    "sg:postcode": "43235",
    "sg:province": "OH",
    "sg:tags": [
      "contractor"
    ],
    "wof:name": "A C O Restoration Co Inc",
    "wof:placetype": "venue"
  },
  "geometry": {"coordinates":[-83.072931,40.113425],"type":"Point"}
}
