{
  "type": "Feature",
  "properties": {
    "addr:full": "8230 Montgomery Rd Cincinnati OH 45236",
    "addr:housenumber": "8230",
    "addr:postcode": "45236",
    "addr:street": "Montgomery Rd",
    "iso:country": "US",
    "sg:address": "8230 Montgomery Rd",
    "sg:city": "Cincinnati",
    "sg:classifiers": [
      {
        "category": "Professional",
        "subcategory": "Management \u0026 Consulting",
        "type": "Services"
      },
      {
        "category": "Manufacturing",
        "subcategory": "Printing",
        "type": "Manufacturing \u0026 Wholesale Goods"
      }
    ],
    "sg:phone": "+1 513 984 8580",
    "sg:postcode": "45236",
    "sg:province": "OH",
    "sg:tags": [
      "marketing",
      "program",
      "multimedia"
    ],
    "wof:name": "On Target Media Inc",
    "wof:placetype": "venue"
  },
  "geometry": {"coordinates":[-84.366552,39.205933],"type":"Point"}
}
