{
  "type": "Feature",
  "properties": {
    "addr:full": "1616 E Wooster St Bowling Green OH 43402",
    "addr:housenumber": "1616",
    "addr:postcode": "43402",
    "addr:street": "E Wooster St",
    "iso:country": "US",
    "sg:address": "1616 E Wooster St",
    "sg:city": "Bowling Green",
    "sg:classifiers": [
      {
        "category": "Social Services",
        "type": "Services"
      }
    ],
    "sg:phone": "+1 419 352 2390",
    "sg:postcode": "43402",
    "sg:province": "OH",
    "sg:tags": [
      "organization",
      "welfare"
    ],
    "wof:name": "United Way",
    "wof:placetype": "venue"
  },
  "geometry": {"coordinates":[-83.622674,41.374443],"type":"Point"}
}
