{
  "type": "Feature",
  "properties": {
    "addr:full": "4040 Saint Paris Pike Springfield OH 45504",
    "addr:housenumber": "4040",
    "addr:postcode": "45504",
    "addr:street": "Saint Paris Pike",
    "iso:country": "US",
    "sg:address": "4040 Saint Paris Pike",
    "sg:city": "Springfield",
    "sg:classifiers": [
      {
        "category": "Retail",
        "subcategory": "Auto Repair",
        "type": "Services"
      }
    ],
    "sg:phone": "+1 937 399 2570",
    "sg:postcode": "45504",
    "sg:province": "OH",
    "sg:tags": [
      "repairing",
      "automobile",
      "general"
    ],
    "wof:name": "Rogers Garage",
    "wof:placetype": "venue"
  },
  "geometry": {"coordinates":[-83.848442,39.979498],"type":"Point"}
}
