{
  "type": "Feature",
  "properties": {
    "iso:country":"US",
    "sg:address":"4040 Saint Paris Pike",
    "sg:city":"Springfield",
    "sg:classifiers":[
        {
            "category":"Retail",
            "subcategory":"Auto Repair",
            "type":"Services"
        }
    ],
    "sg:phone":"+1 937 399 2570",
    "sg:postcode":"45504",
    "sg:province":"OH",
    "sg:tags":[
        "repairing",
        "automobile",
        "general"
    ],
    "wof:name":"Rogers Garage",
    "wof:placetype":"venue"
},
  "geometry": {"coordinates":[-83.84844200000001,39.979498],"type":"Point"}
}