{
  "type": "Feature",
  "properties": {
    "addr:full":"6300 Tussing Rd Reynoldsburg OH 43068",
    "addr:postcode":"6300;43068",
    "addr:street":"Tussing Rd",
    "iso:country":"US",
    "sg:address":"6300 Tussing Rd",
    "sg:city":"Reynoldsburg",
    "sg:classifiers":[
        {
            "category":"Shopping",
            "subcategory":"Department Store",
            "type":"Retail Goods"
        }
    ],
    "sg:phone":"+1 614 864 2569",
    "sg:postcode":"43068",
    "sg:province":"OH",
    "sg:tags":[
        "grocery"
    ],
    "wof:name":"Wal-Mart",
    "wof:placetype":"venue"
},
  "geometry": {"coordinates":[-82.825013,39.927094],"type":"Point"}
}