{
  "type": "Feature",
  "properties": {
    "iso:country":"US",
    "sg:address":"14050 Cedar Rd",
    "sg:city":"Cleveland",
    "sg:classifiers":[
        {
            "category":"Real Estate",
            "subcategory":"Real Estate Operator",
            "type":"Services"
        }
    ],
    "sg:phone":"+1 216 382 2514",
    "sg:postcode":"44118",
    "sg:province":"OH",
    "sg:tags":[
        "building",
        "apartment"
    ],
    "wof:name":"Cedar Center Apartments",
    "wof:placetype":"venue"
},
  "geometry": {"coordinates":[-81.531342,41.50138],"type":"Point"}
}