{
  "type": "Feature",
  "properties": {
    "addr:full":"12455 Quarry Rd Oberlin OH 44074",
    "addr:housenumber":"12455",
    "addr:postcode":"44074",
    "addr:street":"Quarry Rd",
    "iso:country":"US",
    "sg:address":"12455 Quarry Rd",
    "sg:city":"Oberlin",
    "sg:phone":"+1 440 774 7394",
    "sg:postcode":"44074",
    "sg:province":"OH",
    "sg:tags":[
        "farm",
        "corn",
        "soybean"
    ],
    "wof:name":"Paul Squires",
    "wof:placetype":"venue"
},
  "geometry": {"coordinates":[-82.25856400000001,41.29445],"type":"Point"}
}