{
  "type": "Feature",
  "properties": {
    "iso:country":"US",
    "sg:address":"1770 N Co Rd 25A",
    "sg:city":"Troy",
    "sg:classifiers":[
        {
            "category":"Home & Garden",
            "subcategory":"Garden Supply",
            "type":"Retail Goods"
        }
    ],
    "sg:phone":"+1 937 335 3375",
    "sg:postcode":"45373",
    "sg:province":"OH",
    "sg:tags":[
        "lawn",
        "mower"
    ],
    "wof:name":"Hines Commercial & Residential",
    "wof:placetype":"venue"
},
  "geometry": {"coordinates":[-84.21534200000001,40.06704],"type":"Point"}
}