{
  "type": "Feature",
  "properties": {
    "addr:full": "1770 N Co Rd 25A Troy OH 45373",
    "addr:housenumber": "1770;25a",
    "addr:postcode": "45373",
    "addr:street": "N Co Rd",
    "iso:country": "US",
    "sg:address": "1770 N Co Rd 25A",
    "sg:city": "Troy",
    "sg:classifiers": [
      {
        "category": "Home \u0026 Garden",
        "subcategory": "Garden Supply",
        "type": "Retail Goods"
      }
    ],
    "sg:phone": "+1 937 335 3375",
    "sg:postcode": "45373",
    "sg:province": "OH",
    "sg:tags": [
      "lawn",
      "mower"
    ],
    "wof:name": "Hines Commercial \u0026 Residential",
    "wof:placetype": "venue"
  },
  "geometry": {"coordinates":[-84.215342,40.06704],"type":"Point"}
}
