{
  "type": "Feature",
  "properties": {
    "addr:full":"2810 Custer Orangeville Rd Burghill OH 44404",
    "addr:housenumber":"2810",
    "addr:postcode":"44404",
    "addr:street":"Custer Orangeville Rd",
    "iso:country":"US",
    "sg:address":"2810 Custer Orangeville Rd",
    "sg:city":"Burghill",
    "sg:classifiers":[
        {
            "category":"Farming",
            "subcategory":"Nursery",
            "type":"Manufacturing & Wholesale Goods"
        }
    ],
    "sg:phone":"+1 330 772 5623",
    "sg:postcode":"44404",
    "sg:province":"OH",
    "sg:tags":[
        "ornamental"
    ],
    "wof:name":"Flint Farm Nursery",
    "wof:placetype":"venue"
},
  "geometry": {"coordinates":[-80.54795900000001,41.294285],"type":"Point"}
}