{
  "type": "Feature",
  "properties": {
    "addr:full":"2272 Petzinger Ct Columbus OH 43232",
    "addr:housenumber":"2272",
    "addr:postcode":"43232",
    "addr:street":"Petzinger Ct",
    "iso:country":"US",
    "sg:address":"2272 Petzinger Ct",
    "sg:city":"Columbus",
    "sg:classifiers":[
        {
            "category":"Real Estate",
            "subcategory":"Real Estate Operator",
            "type":"Services"
        }
    ],
    "sg:phone":"+1 614 864 6500",
    "sg:postcode":"43232",
    "sg:province":"OH",
    "sg:tags":[
        "building",
        "apartment"
    ],
    "wof:name":"Wynds Apartments",
    "wof:placetype":"venue"
},
  "geometry": {"coordinates":[-82.89629100000001,39.926226],"type":"Point"}
}