{
  "type": "Feature",
  "properties": {
    "iso:country":"US",
    "sg:address":"1211 Euclid Ave",
    "sg:city":"Cleveland",
    "sg:classifiers":[
        {
            "category":"Building & Trades",
            "subcategory":"Construction",
            "type":"Services"
        }
    ],
    "sg:phone":"+1 216 685 1666",
    "sg:postcode":"44115",
    "sg:province":"OH",
    "sg:tags":[
        "house"
    ],
    "wof:name":"Iilles Construction",
    "wof:placetype":"venue"
},
  "geometry": {"coordinates":[-81.682194,41.500912],"type":"Point"}
}