{
  "type": "Feature",
  "properties": {
    "iso:country":"US",
    "sg:address":"1 Griffin Gate",
    "sg:city":"Barberton",
    "sg:classifiers":[
        {
            "category":"Professional",
            "subcategory":"Business Services",
            "type":"Services"
        }
    ],
    "sg:phone":"+1 330 644 3534",
    "sg:postcode":"44203",
    "sg:province":"OH",
    "sg:tags":[
        "arbitration"
    ],
    "wof:name":"Stafford & Ward",
    "wof:placetype":"venue"
},
  "geometry": {"coordinates":[-81.569477,40.979015],"type":"Point"}
}