{
  "type": "Feature",
  "properties": {
    "addr:full":"6847 N Chestnut St Ravenna OH 44266",
    "addr:housenumber":"6847",
    "addr:postcode":"44266",
    "addr:street":"N Chestnut St",
    "iso:country":"US",
    "sg:address":"6847 N Chestnut St",
    "sg:city":"Ravenna",
    "sg:classifiers":[
        {
            "category":"Professional",
            "subcategory":"Testing Lab",
            "type":"Services"
        }
    ],
    "sg:phone":"+1 330 296 5019",
    "sg:postcode":"44266",
    "sg:province":"OH",
    "sg:tags":[
        "laboratory"
    ],
    "wof:name":"Robinson Radiation Oncology",
    "wof:placetype":"venue"
},
  "geometry": {"coordinates":[-81.24583800000001,41.176096],"type":"Point"}
}