{
  "type": "Feature",
  "properties": {
    "addr:full":"701 2nd Ave Gallipolis OH 45631",
    "addr:housenumber":"701",
    "addr:postcode":"45631",
    "addr:street":"2Nd Ave",
    "iso:country":"US",
    "sg:address":"701 2nd Ave",
    "sg:city":"Gallipolis",
    "sg:classifiers":[
        {
            "category":"Autos & Motor Vehicles",
            "subcategory":"Automobile Sales",
            "type":"Retail Goods"
        }
    ],
    "sg:phone":"+1 740 446 8554",
    "sg:postcode":"45631",
    "sg:province":"OH",
    "wof:name":"Southern Auto Sales",
    "wof:placetype":"venue"
},
  "geometry": {"coordinates":[-82.197085,38.813258],"type":"Point"}
}