{
  "type": "Feature",
  "properties": {
    "addr:full":"4431 South Ave Toledo OH 43615",
    "addr:housenumber":"4431",
    "addr:postcode":"43615",
    "addr:street":"South Ave",
    "iso:country":"US",
    "sg:address":"4431 South Ave",
    "sg:city":"Toledo",
    "sg:classifiers":[
        {
            "category":"Freight",
            "type":"Transportation"
        }
    ],
    "sg:phone":"+1 419 537 1011",
    "sg:postcode":"43615",
    "sg:province":"OH",
    "sg:tags":[
        "carrier",
        "motor"
    ],
    "wof:name":"Yellow Transportation Inc",
    "wof:placetype":"venue"
},
  "geometry": {"coordinates":[-83.648082,41.630901],"type":"Point"}
}