{
  "type": "Feature",
  "properties": {
    "addr:full": "7835 Ransbottom Rd Roseville OH 43777",
    "addr:housenumber": "7835",
    "addr:postcode": "43777",
    "addr:street": "Ransbottom Rd",
    "iso:country": "US",
    "sg:address": "7835 Ransbottom Rd",
    "sg:city": "Roseville",
    "sg:classifiers": [
      {
        "category": "Building \u0026 Trades",
        "subcategory": "Construction",
        "type": "Services"
      }
    ],
    "sg:phone": "+1 740 697 0420",
    "sg:postcode": "43777",
    "sg:province": "OH",
    "sg:tags": [
      "house"
    ],
    "wof:name": "R \u0026 J Construction",
    "wof:placetype": "venue"
  },
  "geometry": {"coordinates":[-82.064417,39.817236],"type":"Point"}
}
