{
  "type": "Feature",
  "properties": {
    "iso:country":"US",
    "sg:address":"7835 Ransbottom Rd",
    "sg:city":"Roseville",
    "sg:classifiers":[
        {
            "category":"Building & Trades",
            "subcategory":"Construction",
            "type":"Services"
        }
    ],
    "sg:phone":"+1 740 697 0420",
    "sg:postcode":"43777",
    "sg:province":"OH",
    "sg:tags":[
        "house"
    ],
    "wof:name":"R & J Construction",
    "wof:placetype":"venue"
},
  "geometry": {"coordinates":[-82.06441700000001,39.817236],"type":"Point"}
}