{
  "type": "Feature",
  "properties": {
    "addr:full": "1048 Discovery Dr Columbus OH 43085",
    "addr:housenumber": "1048",
    "addr:postcode": "43085",
    "addr:street": "Discovery Dr",
    "iso:country": "US",
    "sg:address": "1048 Discovery Dr",
    "sg:city": "Columbus",
    "sg:classifiers": [
      {
        "category": "Home \u0026 Garden",
        "subcategory": "Building Materials",
        "type": "Retail Goods"
      },
      {
        "category": "Building \u0026 Trades",
        "subcategory": "Construction",
        "type": "Services"
      }
    ],
    "sg:phone": "+1 614 888 1414",
    "sg:postcode": "43085",
    "sg:province": "OH",
    "sg:tags": [
      "wallpaper",
      "hanging"
    ],
    "wof:name": "Williamson Wallcovering",
    "wof:placetype": "venue"
  },
  "geometry": {"coordinates":[-82.98601,40.120999],"type":"Point"}
}
