{
  "type": "Feature",
  "properties": {
    "addr:full": "4800 Hall Rd Columbus OH 43228",
    "addr:housenumber": "4800",
    "addr:postcode": "43228",
    "addr:street": "Hall Rd",
    "iso:country": "US",
    "sg:address": "4800 Hall Rd",
    "sg:city": "Columbus",
    "sg:classifiers": [
      {
        "category": "Real Estate",
        "subcategory": "Real Estate Operator",
        "type": "Services"
      }
    ],
    "sg:phone": "+1 614 878 4610",
    "sg:postcode": "43228",
    "sg:province": "OH",
    "sg:tags": [
      "building",
      "apartment"
    ],
    "wof:name": "Westview Gardens Apartments",
    "wof:placetype": "venue"
  },
  "geometry": {"coordinates":[-83.1269,39.930223],"type":"Point"}
}
