{
  "type": "Feature",
  "properties": {
    "addr:full": "32600 Winter Green Dr Cleveland OH 44139",
    "addr:housenumber": "32600",
    "addr:postcode": "44139",
    "addr:street": "Winter Green Dr",
    "iso:country": "US",
    "sg:address": "32600 Winter Green Dr",
    "sg:city": "Cleveland",
    "sg:classifiers": [
      {
        "category": "Shopping",
        "subcategory": "Clothing, Apparel, \u0026 Fashions",
        "type": "Retail Goods"
      }
    ],
    "sg:phone": "+1 440 349 8930",
    "sg:postcode": "44139",
    "sg:province": "OH",
    "sg:tags": [
      "clothes"
    ],
    "wof:name": "Fibres Inc",
    "wof:placetype": "venue"
  },
  "geometry": {"coordinates":[-81.447913,41.420362],"type":"Point"}
}
