{
  "type": "Feature",
  "properties": {
    "addr:full":"3619 S Meridian Rd Youngstown OH 44511",
    "addr:housenumber":"3619",
    "addr:postcode":"44511",
    "addr:street":"S Meridian Rd",
    "iso:country":"US",
    "sg:address":"3619 S Meridian Rd",
    "sg:city":"Youngstown",
    "sg:classifiers":[
        {
            "category":"Banks & Credit Unions",
            "subcategory":"Bank",
            "type":"Services"
        }
    ],
    "sg:phone":"+1 330 793 3971",
    "sg:postcode":"44511",
    "sg:province":"OH",
    "sg:tags":[
        "national",
        "commercial"
    ],
    "wof:name":"Farmers National Bank",
    "wof:placetype":"venue"
},
  "geometry": {"coordinates":[-80.71100300000001,41.063096],"type":"Point"}
}