{
  "type": "Feature",
  "properties": {
    "addr:full": "412 E Wooster St Bowling Green OH 43402",
    "addr:housenumber": "412",
    "addr:postcode": "43402",
    "addr:street": "E Wooster St",
    "iso:country": "US",
    "sg:address": "412 E Wooster St",
    "sg:city": "Bowling Green",
    "sg:classifiers": [
      {
        "category": "Insurance",
        "subcategory": "Insurance Agent",
        "type": "Services"
      }
    ],
    "sg:phone": "+1 419 353 0405",
    "sg:postcode": "43402",
    "sg:province": "OH",
    "wof:name": "Le Galley Insurance",
    "wof:placetype": "venue"
  },
  "geometry": {"coordinates":[-83.645816,41.374703],"type":"Point"}
}
