{
  "type": "Feature",
  "properties": {
    "addr:full": "386 Dublin Ave Columbus OH 43215",
    "addr:housenumber": "386",
    "addr:postcode": "43215",
    "addr:street": "Dublin Ave",
    "iso:country": "US",
    "sg:address": "386 Dublin Ave",
    "sg:city": "Columbus",
    "sg:classifiers": [
      {
        "category": "Wholesale",
        "subcategory": "Groceries",
        "type": "Manufacturing \u0026 Wholesale Goods"
      }
    ],
    "sg:phone": "+1 614 224 4613",
    "sg:postcode": "43215",
    "sg:province": "OH",
    "sg:tags": [
      "food",
      "distributor"
    ],
    "wof:name": "Euro-USA",
    "wof:placetype": "venue"
  },
  "geometry": {"coordinates":[-83.013492,39.967653],"type":"Point"}
}
