{
  "type": "Feature",
  "properties": {
    "addr:full": "1350 Euclid Ave Cleveland OH 44115",
    "addr:housenumber": "1350",
    "addr:postcode": "44115",
    "addr:street": "Euclid Ave",
    "iso:country": "US",
    "sg:address": "1350 Euclid Ave",
    "sg:city": "Cleveland",
    "sg:classifiers": [
      {
        "category": "Restaurant",
        "type": "Food \u0026 Drink"
      }
    ],
    "sg:phone": "+1 216 579 0345",
    "sg:postcode": "44115",
    "sg:province": "OH",
    "sg:tags": [
      "eating"
    ],
    "wof:name": "A Cafe",
    "wof:placetype": "venue"
  },
  "geometry": {"coordinates":[-81.682228,41.500756],"type":"Point"}
}
