{
  "type": "Feature",
  "properties": {
    "addr:full":"19199 S Sagamore Rd Cleveland OH 44126",
    "addr:housenumber":"19199",
    "addr:postcode":"44126",
    "addr:street":"S Sagamore Rd",
    "iso:country":"US",
    "sg:address":"19199 S Sagamore Rd",
    "sg:city":"Cleveland",
    "sg:classifiers":[
        {
            "category":"Building & Trades",
            "subcategory":"Construction",
            "type":"Services"
        }
    ],
    "sg:phone":"+1 440 895 9948",
    "sg:postcode":"44126",
    "sg:province":"OH",
    "sg:tags":[
        "painting",
        "maintenance"
    ],
    "wof:name":"Tri-Crown Construction",
    "wof:placetype":"venue"
},
  "geometry": {"coordinates":[-81.83273699999999,41.456047],"type":"Point"}
}