{
  "type": "Feature",
  "properties": {
    "iso:country":"US",
    "sg:address":"901 York St",
    "sg:city":"Cincinnati",
    "sg:classifiers":[
        {
            "category":"Place Of Worship",
            "subcategory":"Church",
            "type":"Public Place"
        },
        {
            "category":"Place Of Worship",
            "type":"Public Place"
        }
    ],
    "sg:phone":"+1 513 721 2604",
    "sg:postcode":"45214",
    "sg:province":"OH",
    "sg:tags":[
        "churches-seventh-day",
        "adventist",
        "christian",
        "churches-advent"
    ],
    "sg:website":"http://www.adventist.org",
    "wof:name":"Marantha Svnth Day Advntist Ch",
    "wof:placetype":"venue"
},
  "geometry": {"coordinates":[-84.52916,39.117279],"type":"Point"}
}