{
  "type": "Feature",
  "properties": {
    "iso:country":"US",
    "sg:address":"4950 Wooden Shoe Hollow Dr",
    "sg:city":"Cincinnati",
    "sg:classifiers":[
        {
            "category":"Wholesale",
            "subcategory":"Plants",
            "type":"Manufacturing & Wholesale Goods"
        }
    ],
    "sg:phone":"+1 513 541 8666",
    "sg:postcode":"45232",
    "sg:province":"OH",
    "sg:tags":[
        "florist"
    ],
    "wof:name":"Vetter Wholesale Florist",
    "wof:placetype":"venue"
},
  "geometry": {"coordinates":[-84.516142,39.182242],"type":"Point"}
}