{
  "type": "Feature",
  "properties": {
    "addr:full": "4950 Wooden Shoe Hollow Dr Cincinnati OH 45232",
    "addr:housenumber": "4950",
    "addr:postcode": "45232",
    "addr:street": "Wooden Shoe Hollow Dr",
    "iso:country": "US",
    "sg:address": "4950 Wooden Shoe Hollow Dr",
    "sg:city": "Cincinnati",
    "sg:classifiers": [
      {
        "category": "Wholesale",
        "subcategory": "Plants",
        "type": "Manufacturing \u0026 Wholesale Goods"
      }
    ],
    "sg:phone": "+1 513 541 8666",
    "sg:postcode": "45232",
    "sg:province": "OH",
    "sg:tags": [
      "florist"
    ],
    "wof:name": "Vetter Wholesale Florist",
    "wof:placetype": "venue"
  },
  "geometry": {"coordinates":[-84.516142,39.182242],"type":"Point"}
}
