{
  "type": "Feature",
  "properties": {
    "addr:full": "520 Edgerton St Hamler OH 43524",
    "addr:housenumber": "520",
    "addr:postcode": "43524",
    "addr:street": "Edgerton St",
    "iso:country": "US",
    "sg:address": "520 Edgerton St",
    "sg:city": "Hamler",
    "sg:classifiers": [
      {
        "category": "Home \u0026 Garden",
        "subcategory": "Furniture",
        "type": "Retail Goods"
      }
    ],
    "sg:phone": "+1 419 274 6035",
    "sg:postcode": "43524",
    "sg:province": "OH",
    "sg:tags": [
      "equipment",
      "kitchen",
      "cabinet"
    ],
    "wof:name": "Hardwood Connection",
    "wof:placetype": "venue"
  },
  "geometry": {"coordinates":[-84.03022,41.230933],"type":"Point"}
}
