{
  "type": "Feature",
  "properties": {
    "iso:country":"US",
    "sg:address":"7070 Antoinette Dr",
    "sg:city":"Cleveland",
    "sg:classifiers":[
        {
            "category":"Professional",
            "subcategory":"Computer Services",
            "type":"Services"
        }
    ],
    "sg:phone":"+1 216 433 9668",
    "sg:postcode":"44129",
    "sg:province":"OH",
    "sg:tags":[
        "related"
    ],
    "wof:name":"Etg",
    "wof:placetype":"venue"
},
  "geometry": {"coordinates":[-81.728723,41.372417],"type":"Point"}
}