{
  "type": "Feature",
  "properties": {
    "addr:full": "7070 Antoinette Dr Cleveland OH 44129",
    "addr:housenumber": "7070",
    "addr:postcode": "44129",
    "addr:street": "Antoinette Dr",
    "iso:country": "US",
    "sg:address": "7070 Antoinette Dr",
    "sg:city": "Cleveland",
    "sg:classifiers": [
      {
        "category": "Professional",
        "subcategory": "Computer Services",
        "type": "Services"
      }
    ],
    "sg:phone": "+1 216 433 9668",
    "sg:postcode": "44129",
    "sg:province": "OH",
    "sg:tags": [
      "related"
    ],
    "wof:name": "Etg",
    "wof:placetype": "venue"
  },
  "geometry": {"coordinates":[-81.728723,41.372417],"type":"Point"}
}
