{
  "type": "Feature",
  "properties": {
    "iso:country":"US",
    "sg:address":"1210 Independence Ave",
    "sg:city":"Akron",
    "sg:classifiers":[
        {
            "category":"Cinema",
            "subcategory":"Movie Theater",
            "type":"Entertainment"
        }
    ],
    "sg:phone":"+1 330 633 7668",
    "sg:postcode":"44310",
    "sg:province":"OH",
    "wof:name":"Regal Cinemas",
    "wof:placetype":"venue"
},
  "geometry": {"coordinates":[-81.46660300000001,41.110693],"type":"Point"}
}