{
  "type": "Feature",
  "properties": {
    "iso:country":"US",
    "sg:address":"34 Park St",
    "sg:city":"Berea",
    "sg:classifiers":[
        {
            "category":"Personal",
            "subcategory":"Beauty Salon",
            "type":"Services"
        }
    ],
    "sg:phone":"+1 440 243 4392",
    "sg:postcode":"44017",
    "sg:province":"OH",
    "sg:tags":[
        "manicuring"
    ],
    "wof:name":"Nails For You",
    "wof:placetype":"venue"
},
  "geometry": {"coordinates":[-81.854697,41.367628],"type":"Point"}
}