{
  "type": "Feature",
  "properties": {
    "iso:country":"US",
    "sg:address":"863 Smithfield Dr",
    "sg:city":"Northfield",
    "sg:classifiers":[
        {
            "category":"Farming",
            "subcategory":"Nursery",
            "type":"Manufacturing & Wholesale Goods"
        }
    ],
    "sg:phone":"+1 330 467 8581",
    "sg:postcode":"44067",
    "sg:province":"OH",
    "sg:tags":[
        "turf"
    ],
    "wof:name":"Turf Talent",
    "wof:placetype":"venue"
},
  "geometry": {"coordinates":[-81.569799,41.313635],"type":"Point"}
}