{
  "type": "Feature",
  "properties": {
    "iso:country":"US",
    "sg:address":"1301 E 9th St",
    "sg:city":"Cleveland",
    "sg:classifiers":[
        {
            "category":"Personal",
            "type":"Services"
        }
    ],
    "sg:phone":"+1 216 771 7273",
    "sg:postcode":"44114",
    "sg:province":"OH",
    "sg:tags":[
        "therapist",
        "massage"
    ],
    "wof:name":"John E's Massage Works",
    "wof:placetype":"venue"
},
  "geometry": {"coordinates":[-81.689572,41.503429],"type":"Point"}
}