{
  "type": "Feature",
  "properties": {
    "addr:full": "5221 Salem Ave Trotwood OH 45426",
    "addr:housenumber": "5221",
    "addr:postcode": "45426",
    "addr:street": "Salem Ave",
    "iso:country": "US",
    "sg:address": "5221 Salem Ave",
    "sg:city": "Trotwood",
    "sg:classifiers": [
      {
        "category": "Autos \u0026 Motor Vehicles",
        "subcategory": "Auto Supplies",
        "type": "Retail Goods"
      }
    ],
    "sg:phone": "+1 937 854 7007",
    "sg:postcode": "45426",
    "sg:province": "OH",
    "sg:tags": [
      "automobile",
      "parts"
    ],
    "sg:website": "www.pepboys.com",
    "wof:name": "Pep Boys Supercenter",
    "wof:placetype": "venue"
  },
  "geometry": {"coordinates":[-84.285304,39.820624],"type":"Point"}
}
