{
  "type": "Feature",
  "properties": {
    "iso:country":"US",
    "sg:address":"5221 Salem Ave",
    "sg:city":"Trotwood",
    "sg:classifiers":[
        {
            "category":"Autos & Motor Vehicles",
            "subcategory":"Auto Supplies",
            "type":"Retail Goods"
        }
    ],
    "sg:phone":"+1 937 854 7007",
    "sg:postcode":"45426",
    "sg:province":"OH",
    "sg:tags":[
        "automobile",
        "parts"
    ],
    "sg:website":"www.pepboys.com",
    "wof:name":"Pep Boys Supercenter",
    "wof:placetype":"venue"
},
  "geometry": {"coordinates":[-84.285304,39.820624],"type":"Point"}
}