{
  "type": "Feature",
  "properties": {
    "addr:full": "1916 N Reynolds Rd Toledo OH 43615",
    "addr:housenumber": "1916",
    "addr:postcode": "43615",
    "addr:street": "N Reynolds Rd",
    "iso:country": "US",
    "sg:address": "1916 N Reynolds Rd",
    "sg:city": "Toledo",
    "sg:classifiers": [
      {
        "category": "Personal",
        "type": "Services"
      }
    ],
    "sg:phone": "+1 419 345 1225",
    "sg:postcode": "43615",
    "sg:province": "OH",
    "sg:tags": [
      "therapist",
      "massage"
    ],
    "wof:name": "Becky Davis",
    "wof:placetype": "venue"
  },
  "geometry": {"coordinates":[-83.66756,41.660301],"type":"Point"}
}
