{
  "type": "Feature",
  "properties": {
    "iso:country":"US",
    "sg:address":"100 S Poe Rd",
    "sg:city":"North Baltimore",
    "sg:classifiers":[
        {
            "category":"Building & Trades",
            "subcategory":"Cleaning & Sanitation",
            "type":"Services"
        }
    ],
    "sg:phone":"+1 419 257 4421",
    "sg:postcode":"45872",
    "sg:province":"OH",
    "sg:tags":[
        "chemical"
    ],
    "wof:name":"Omnichem LLC",
    "wof:placetype":"venue"
},
  "geometry": {"coordinates":[-83.663747,41.179956],"type":"Point"}
}