{
  "type": "Feature",
  "properties": {
    "iso:country":"US",
    "sg:address":"370 S Cleveland Ave",
    "sg:city":"Westerville",
    "sg:classifiers":[
        {
            "category":"Banks & Credit Unions",
            "subcategory":"Bank",
            "type":"Services"
        }
    ],
    "sg:phone":"+1 614 244 2277",
    "sg:postcode":"43081",
    "sg:province":"OH",
    "sg:tags":[
        "national",
        "commercial",
        "business"
    ],
    "wof:name":"Distribution Services",
    "wof:placetype":"venue"
},
  "geometry": {"coordinates":[-82.948307,40.1218],"type":"Point"}
}