{
  "type": "Feature",
  "properties": {
    "addr:full": "370 S Cleveland Ave Westerville OH 43081",
    "addr:housenumber": "370",
    "addr:postcode": "43081",
    "addr:street": "S Cleveland Ave",
    "iso:country": "US",
    "sg:address": "370 S Cleveland Ave",
    "sg:city": "Westerville",
    "sg:classifiers": [
      {
        "category": "Banks \u0026 Credit Unions",
        "subcategory": "Bank",
        "type": "Services"
      }
    ],
    "sg:phone": "+1 614 244 2277",
    "sg:postcode": "43081",
    "sg:province": "OH",
    "sg:tags": [
      "national",
      "commercial",
      "business"
    ],
    "wof:name": "Distribution Services",
    "wof:placetype": "venue"
  },
  "geometry": {"coordinates":[-82.948307,40.1218],"type":"Point"}
}
