{
  "type": "Feature",
  "properties": {
    "addr:full": "6288 Co Rd 20 West Mansfield OH 43358",
    "addr:housenumber": "6288;20",
    "addr:postcode": "43358",
    "addr:street": "Co Rd",
    "iso:country": "US",
    "sg:address": "6288 Co Rd 20",
    "sg:city": "West Mansfield",
    "sg:classifiers": [
      {
        "category": "Farming",
        "subcategory": "Dairy Farm",
        "type": "Manufacturing \u0026 Wholesale Goods"
      }
    ],
    "sg:phone": "+1 937 468 2028",
    "sg:postcode": "43358",
    "sg:province": "OH",
    "wof:name": "Maple Shade Farms",
    "wof:placetype": "venue"
  },
  "geometry": {"coordinates":[-83.612308,40.447883],"type":"Point"}
}
