{
  "type": "Feature",
  "properties": {
    "iso:country":"US",
    "sg:address":"6288 Co Rd 20",
    "sg:city":"West Mansfield",
    "sg:classifiers":[
        {
            "category":"Farming",
            "subcategory":"Dairy Farm",
            "type":"Manufacturing & Wholesale Goods"
        }
    ],
    "sg:phone":"+1 937 468 2028",
    "sg:postcode":"43358",
    "sg:province":"OH",
    "wof:name":"Maple Shade Farms",
    "wof:placetype":"venue"
},
  "geometry": {"coordinates":[-83.612308,40.447883],"type":"Point"}
}