{
  "type": "Feature",
  "properties": {
    "iso:country":"US",
    "sg:address":"2749 Arenac Rd",
    "sg:city":"Fairlawn",
    "sg:classifiers":[
        {
            "category":"Retail",
            "subcategory":"Portrait Studio",
            "type":"Services"
        }
    ],
    "sg:phone":"+1 330 836 3021",
    "sg:postcode":"44333",
    "sg:province":"OH",
    "sg:tags":[
        "photographer"
    ],
    "wof:name":"Giggle Graph Studio",
    "wof:placetype":"venue"
},
  "geometry": {"coordinates":[-81.608171,41.134971],"type":"Point"}
}