{
  "type": "Feature",
  "properties": {
    "addr:full":"1312 Farr Dr Dayton OH 45404",
    "addr:housenumber":"1312",
    "addr:postcode":"45404",
    "addr:street":"Farr Dr",
    "iso:country":"US",
    "sg:address":"1312 Farr Dr",
    "sg:city":"Dayton",
    "sg:classifiers":[
        {
            "category":"Real Estate",
            "subcategory":"Real Estate Agent",
            "type":"Services"
        }
    ],
    "sg:phone":"+1 937 461 2732",
    "sg:postcode":"45404",
    "sg:province":"OH",
    "sg:tags":[
        "management"
    ],
    "sg:website":"www.asdamerica.com",
    "wof:name":"ASD America Inc",
    "wof:placetype":"venue"
},
  "geometry": {"coordinates":[-84.166405,39.78355],"type":"Point"}
}