{
  "type": "Feature",
  "properties": {
    "addr:full": "1164 E Pidgeon Rd Salem OH 44460",
    "addr:housenumber": "1164",
    "addr:postcode": "44460",
    "addr:street": "E Pidgeon Rd",
    "iso:country": "US",
    "sg:address": "1164 E Pidgeon Rd",
    "sg:city": "Salem",
    "sg:classifiers": [
      {
        "category": "Restaurant",
        "type": "Food \u0026 Drink"
      }
    ],
    "sg:phone": "+1 330 337 9802",
    "sg:postcode": "44460",
    "sg:province": "OH",
    "sg:tags": [
      "eating",
      "product",
      "dairy"
    ],
    "wof:name": "Dairy King",
    "wof:placetype": "venue"
  },
  "geometry": {"coordinates":[-80.844412,40.87911],"type":"Point"}
}
