{
  "type": "Feature",
  "properties": {
    "addr:full": "4189 Mill Trace Rd Youngstown OH 44511",
    "addr:housenumber": "4189",
    "addr:postcode": "44511",
    "addr:street": "Mill Trace Rd",
    "iso:country": "US",
    "sg:address": "4189 Mill Trace Rd",
    "sg:city": "Youngstown",
    "sg:classifiers": [
      {
        "category": "Shopping",
        "subcategory": "Used Merchandise",
        "type": "Retail Goods"
      }
    ],
    "sg:phone": "+1 330 782 5861",
    "sg:postcode": "44511",
    "sg:province": "OH",
    "sg:tags": [
      "antique"
    ],
    "wof:name": "Robert R Davis Antique Shop",
    "wof:placetype": "venue"
  },
  "geometry": {"coordinates":[-80.688599,41.055324],"type":"Point"}
}
