{
  "type": "Feature",
  "properties": {
    "addr:full":"3115 W Elm St Lima OH 45805",
    "addr:housenumber":"3115",
    "addr:postcode":"45805",
    "addr:street":"W Elm St",
    "iso:country":"US",
    "sg:address":"3115 W Elm St",
    "sg:city":"Lima",
    "sg:classifiers":[
        {
            "category":"Personal",
            "subcategory":"Beauty Salon",
            "type":"Services"
        }
    ],
    "sg:phone":"+1 419 991 0728",
    "sg:postcode":"45805",
    "sg:province":"OH",
    "sg:tags":[
        "shop"
    ],
    "wof:name":"Steven Michael's Hair Studio",
    "wof:placetype":"venue"
},
  "geometry": {"coordinates":[-84.161198,40.736915],"type":"Point"}
}