{
  "type": "Feature",
  "properties": {
    "addr:full": "1653 Merriman Rd Akron OH 44313",
    "addr:housenumber": "1653",
    "addr:postcode": "44313",
    "addr:street": "Merriman Rd",
    "iso:country": "US",
    "sg:address": "1653 Merriman Rd",
    "sg:city": "Akron",
    "sg:classifiers": [
      {
        "category": "Professional",
        "type": "Services"
      }
    ],
    "sg:phone": "+1 330 237 2020",
    "sg:postcode": "44313",
    "sg:province": "OH",
    "sg:tags": [
      "establishment"
    ],
    "wof:name": "Collaborative Results Inc",
    "wof:placetype": "venue"
  },
  "geometry": {"coordinates":[-81.552183,41.134615],"type":"Point"}
}
