{
  "type": "Feature",
  "properties": {
    "addr:full": "405 N Main St Springboro OH 45066",
    "addr:housenumber": "405",
    "addr:postcode": "45066",
    "addr:street": "N Main St",
    "iso:country": "US",
    "sg:address": "405 N Main St",
    "sg:city": "Springboro",
    "sg:classifiers": [
      {
        "category": "Real Estate",
        "subcategory": "Real Estate Agent",
        "type": "Services"
      }
    ],
    "sg:phone": "+1 937 748 2399",
    "sg:postcode": "45066",
    "sg:province": "OH",
    "wof:name": "Big Valley Realty",
    "wof:placetype": "venue"
  },
  "geometry": {"coordinates":[-84.232077,39.565914],"type":"Point"}
}
