{
  "type": "Feature",
  "properties": {
    "addr:full":"9745 State Rte 14 Streetsboro OH 44241",
    "addr:housenumber":"9745",
    "addr:postcode":"44241",
    "addr:street":"State Rte 14",
    "iso:country":"US",
    "sg:address":"9745 State Rte 14",
    "sg:city":"Streetsboro",
    "sg:classifiers":[
        {
            "category":"Restaurant",
            "type":"Food & Drink"
        }
    ],
    "sg:phone":"+1 330 422 0165",
    "sg:postcode":"44241",
    "sg:province":"OH",
    "sg:website":"www.sheetz.com",
    "wof:name":"Sheetz Inc",
    "wof:placetype":"venue"
},
  "geometry": {"coordinates":[-81.36512999999999,41.251103],"type":"Point"}
}