{
  "type": "Feature",
  "properties": {
    "addr:full": "113 N Columbus St Lancaster OH 43130",
    "addr:housenumber": "113",
    "addr:postcode": "43130",
    "addr:street": "N Columbus St",
    "iso:country": "US",
    "sg:address": "113 N Columbus St",
    "sg:city": "Lancaster",
    "sg:classifiers": [
      {
        "category": "Shopping",
        "subcategory": "Clothing, Apparel, \u0026 Fashions",
        "type": "Retail Goods"
      }
    ],
    "sg:phone": "+1 740 687 0623",
    "sg:postcode": "43130",
    "sg:province": "OH",
    "sg:tags": [
      "wear",
      "formal"
    ],
    "sg:website": "www.tuxedojunction.com",
    "wof:name": "Tuxedo Junction",
    "wof:placetype": "venue"
  },
  "geometry": {"coordinates":[-82.604633,39.714295],"type":"Point"}
}
