{
  "type": "Feature",
  "properties": {
    "iso:country":"US",
    "sg:address":"5234 Yeatman Rd",
    "sg:city":"Cincinnati",
    "sg:classifiers":[
        {
            "category":"Building & Trades",
            "subcategory":"Construction",
            "type":"Services"
        }
    ],
    "sg:phone":"+1 513 741 9212",
    "sg:postcode":"45252",
    "sg:province":"OH",
    "sg:tags":[
        "hanging",
        "contractor"
    ],
    "wof:name":"DK Painting Services",
    "wof:placetype":"venue"
},
  "geometry": {"coordinates":[-84.613997,39.290325],"type":"Point"}
}