{
  "type": "Feature",
  "properties": {
    "iso:country":"US",
    "sg:address":"4450 Hamilton Ave",
    "sg:city":"Cleveland",
    "sg:classifiers":[
        {
            "category":"Professional",
            "type":"Services"
        }
    ],
    "sg:phone":"+1 216 361 9150",
    "sg:postcode":"44114",
    "sg:province":"OH",
    "sg:tags":[
        "establishment"
    ],
    "wof:name":"American Rebuilding & Relining",
    "wof:placetype":"venue"
},
  "geometry": {"coordinates":[-81.663917,41.517331],"type":"Point"}
}