{
  "type": "Feature",
  "properties": {
    "iso:country":"US",
    "sg:address":"1595 Main St",
    "sg:city":"Peninsula",
    "sg:classifiers":[
        {
            "category":"Shopping",
            "subcategory":"Used Merchandise",
            "type":"Retail Goods"
        }
    ],
    "sg:phone":"+1 330 657 2778",
    "sg:postcode":"44264",
    "sg:province":"OH",
    "wof:name":"Downtown Emporium",
    "wof:placetype":"venue"
},
  "geometry": {"coordinates":[-81.548816,41.241302],"type":"Point"}
}