{
  "type": "Feature",
  "properties": {
    "addr:full": "601 N Main St Alger OH 45812",
    "addr:housenumber": "601",
    "addr:postcode": "45812",
    "addr:street": "N Main St",
    "iso:country": "US",
    "sg:address": "601 N Main St",
    "sg:city": "Alger",
    "sg:classifiers": [
      {
        "category": "Organizations",
        "subcategory": "Religious Organization",
        "type": "Services"
      }
    ],
    "sg:phone": "+1 419 757 2861",
    "sg:postcode": "45812",
    "sg:province": "OH",
    "sg:tags": [
      "church"
    ],
    "wof:name": "Waugh Calvin \u0026 Patricia",
    "wof:placetype": "venue"
  },
  "geometry": {"coordinates":[-83.843899,40.710657],"type":"Point"}
}
