{
  "type": "Feature",
  "properties": {
    "addr:full": "65 E State St Columbus OH 43215",
    "addr:housenumber": "65",
    "addr:postcode": "43215",
    "addr:street": "E State St",
    "iso:country": "US",
    "sg:address": "65 E State St",
    "sg:city": "Columbus",
    "sg:classifiers": [
      {
        "category": "Manufacturing",
        "subcategory": "Printing",
        "type": "Manufacturing \u0026 Wholesale Goods"
      }
    ],
    "sg:phone": "+1 614 228 8200",
    "sg:postcode": "43215",
    "sg:province": "OH",
    "sg:tags": [
      "newspaper"
    ],
    "wof:name": "Plain Dealer",
    "wof:placetype": "venue"
  },
  "geometry": {"coordinates":[-82.998192,39.960327],"type":"Point"}
}
