{
  "type": "Feature",
  "properties": {
    "iso:country":"US",
    "sg:address":"3477 Fishinger Mill Dr",
    "sg:city":"Hilliard",
    "sg:classifiers":[
        {
            "category":"Real Estate",
            "subcategory":"Real Estate Operator",
            "type":"Services"
        }
    ],
    "sg:phone":"+1 614 527 9612",
    "sg:postcode":"43026",
    "sg:province":"OH",
    "sg:tags":[
        "apartment"
    ],
    "wof:name":"Millington Apartments",
    "wof:placetype":"venue"
},
  "geometry": {"coordinates":[-83.110727,40.023807],"type":"Point"}
}