{
  "type": "Feature",
  "properties": {
    "iso:country":"US",
    "sg:address":"1316 E High St",
    "sg:city":"Springfield",
    "sg:classifiers":[
        {
            "category":"Social Services",
            "type":"Services"
        }
    ],
    "sg:phone":"+1 937 325 3707",
    "sg:postcode":"45505",
    "sg:province":"OH",
    "sg:tags":[
        "organization",
        "legal",
        "welfare"
    ],
    "wof:name":"Battered Victim Crisis Center",
    "wof:placetype":"venue"
},
  "geometry": {"coordinates":[-83.789362,39.921092],"type":"Point"}
}