{
  "type": "Feature",
  "properties": {
    "addr:full": "1810 Rusticwood Ln Cincinnati OH 45255",
    "addr:housenumber": "1810",
    "addr:postcode": "45255",
    "addr:street": "Rusticwood Ln",
    "iso:country": "US",
    "sg:address": "1810 Rusticwood Ln",
    "sg:city": "Cincinnati",
    "sg:classifiers": [
      {
        "category": "Building \u0026 Trades",
        "subcategory": "Construction",
        "type": "Services"
      }
    ],
    "sg:phone": "+1 513 232 2493",
    "sg:postcode": "45255",
    "sg:province": "OH",
    "sg:tags": [
      "house"
    ],
    "wof:name": "Doyle Custom Construction Inc",
    "wof:placetype": "venue"
  },
  "geometry": {"coordinates":[-84.341672,39.085489],"type":"Point"}
}
