{
  "type": "Feature",
  "properties": {
    "iso:country":"US",
    "sg:address":"2803 Highland Ave",
    "sg:city":"Cincinnati",
    "sg:classifiers":[
        {
            "category":"Shopping",
            "subcategory":"Clothing, Apparel, & Fashions",
            "type":"Retail Goods"
        }
    ],
    "sg:phone":"+1 513 751 6250",
    "sg:postcode":"45219",
    "sg:province":"OH",
    "sg:tags":[
        "family"
    ],
    "wof:name":"We Got That",
    "wof:placetype":"venue"
},
  "geometry": {"coordinates":[-84.502976,39.131676],"type":"Point"}
}