{
  "type": "Feature",
  "properties": {
    "addr:full": "332 Gudrun Rd Columbus OH 43202",
    "addr:housenumber": "332",
    "addr:postcode": "43202",
    "addr:street": "Gudrun Rd",
    "iso:country": "US",
    "sg:address": "332 Gudrun Rd",
    "sg:city": "Columbus",
    "sg:classifiers": [
      {
        "category": "Professional",
        "type": "Services"
      }
    ],
    "sg:phone": "+1 614 586 0003",
    "sg:postcode": "43202",
    "sg:province": "OH",
    "wof:name": "Bierman Sj",
    "wof:placetype": "venue"
  },
  "geometry": {"coordinates":[-83.005128,40.026663],"type":"Point"}
}
