{
  "type": "Feature",
  "properties": {
    "addr:full": "170 S 3rd St Newark OH 43055",
    "addr:housenumber": "170",
    "addr:postcode": "43055",
    "addr:street": "S 3Rd St",
    "iso:country": "US",
    "sg:address": "170 S 3rd St",
    "sg:city": "Newark",
    "sg:classifiers": [
      {
        "category": "Building \u0026 Trades",
        "subcategory": "Plumbing",
        "type": "Services"
      }
    ],
    "sg:phone": "+1 740 349 8130",
    "sg:postcode": "43055",
    "sg:province": "OH",
    "sg:tags": [
      "plumbing",
      "contractor"
    ],
    "wof:name": "Cramer Plumbing \u0026 Heating",
    "wof:placetype": "venue"
  },
  "geometry": {"coordinates":[-82.400041,40.052685],"type":"Point"}
}
