{
  "type": "Feature",
  "properties": {
    "addr:full":"324 Dewey Ave Cambridge OH 43725",
    "addr:housenumber":"324",
    "addr:postcode":"43725",
    "addr:street":"Dewey Ave",
    "iso:country":"US",
    "sg:address":"324 Dewey Ave",
    "sg:city":"Cambridge",
    "sg:classifiers":[
        {
            "category":"Food & Beverages",
            "subcategory":"Groceries & Convenience Stores",
            "type":"Retail Goods"
        },
        {
            "category":"Autos & Motor Vehicles",
            "subcategory":"Fuel & Gas Station",
            "type":"Retail Goods"
        }
    ],
    "sg:phone":"+1 740 439 5445",
    "sg:postcode":"43725",
    "sg:province":"OH",
    "sg:tags":[
        "station",
        "gasoline"
    ],
    "wof:name":"Workingman's Friend",
    "wof:placetype":"venue"
},
  "geometry": {"coordinates":[-81.597735,40.022733],"type":"Point"}
}