{
  "type": "Feature",
  "properties": {
    "addr:full":"27 S 23rd St Newark OH 43055",
    "addr:housenumber":"27",
    "addr:postcode":"43055",
    "addr:street":"S 23Rd St",
    "iso:country":"US",
    "sg:address":"27 S 23rd St",
    "sg:city":"Newark",
    "sg:classifiers":[
        {
            "category":"Manufacturing",
            "subcategory":"Furniture",
            "type":"Manufacturing & Wholesale Goods"
        }
    ],
    "sg:phone":"+1 740 344 7648",
    "sg:postcode":"43055",
    "sg:province":"OH",
    "sg:tags":[
        "building",
        "public",
        "mfg"
    ],
    "wof:name":"Charles M Luke Rev",
    "wof:placetype":"venue"
},
  "geometry": {"coordinates":[-82.433267,40.048103],"type":"Point"}
}