{
  "type": "Feature",
  "properties": {
    "addr:full": "20589 State Rte 141 Pedro OH 45659",
    "addr:housenumber": "20589",
    "addr:postcode": "45659",
    "addr:street": "State Rte 141 Pedro",
    "iso:country": "US",
    "sg:address": "20589 State Rte 141",
    "sg:city": "Pedro",
    "sg:classifiers": [
      {
        "category": "Farming",
        "subcategory": "Livestock Farm",
        "type": "Manufacturing \u0026 Wholesale Goods"
      }
    ],
    "sg:phone": "+1 740 643 2259",
    "sg:postcode": "45659",
    "sg:province": "OH",
    "sg:tags": [
      "beef",
      "field",
      "corn",
      "crop",
      "to",
      "cattle",
      "feedlot"
    ],
    "wof:name": "Dale Brown",
    "wof:placetype": "venue"
  },
  "geometry": {"coordinates":[-82.474903,38.668593],"type":"Point"}
}
