{
  "type": "Feature",
  "properties": {
    "iso:country":"US",
    "sg:address":"10237 Chatham Woods Dr",
    "sg:city":"Loveland",
    "sg:classifiers":[
        {
            "category":"Insurance",
            "subcategory":"Insurance Agent",
            "type":"Services"
        }
    ],
    "sg:phone":"+1 513 583 9812",
    "sg:postcode":"45140",
    "sg:province":"OH",
    "wof:name":"Fidelity National Title Insur",
    "wof:placetype":"venue"
},
  "geometry": {"coordinates":[-84.274686,39.276591],"type":"Point"}
}