{
  "type": "Feature",
  "properties": {
    "addr:full": "420 Avon Belden Rd Avon Lake OH 44012",
    "addr:housenumber": "420",
    "addr:postcode": "44012",
    "addr:street": "Avon Belden Rd",
    "iso:country": "US",
    "sg:address": "420 Avon Belden Rd",
    "sg:city": "Avon Lake",
    "sg:classifiers": [
      {
        "category": "Organizations",
        "subcategory": "Religious Organization",
        "type": "Services"
      }
    ],
    "sg:phone": "+1 440 933 4854",
    "sg:postcode": "44012",
    "sg:province": "OH",
    "sg:tags": [
      "church"
    ],
    "wof:name": "St Joseph Church",
    "wof:placetype": "venue"
  },
  "geometry": {"coordinates":[-82.018904,41.495148],"type":"Point"}
}
