{
  "type": "Feature",
  "properties": {
    "addr:full": "219 Bingham St Oak Hill OH 45656",
    "addr:housenumber": "219",
    "addr:postcode": "45656",
    "addr:street": "Bingham St",
    "iso:country": "US",
    "sg:address": "219 Bingham St",
    "sg:city": "Oak Hill",
    "sg:classifiers": [
      {
        "category": "Wholesale",
        "subcategory": "Toys \u0026 Hobbies",
        "type": "Manufacturing \u0026 Wholesale Goods"
      }
    ],
    "sg:phone": "+1 740 682 6274",
    "sg:postcode": "45656",
    "sg:province": "OH",
    "sg:tags": [
      "mining",
      "construction",
      "machinery"
    ],
    "wof:name": "D \u0026 D Crafts",
    "wof:placetype": "venue"
  },
  "geometry": {"coordinates":[-82.560536,38.89417],"type":"Point"}
}
