{
  "type": "Feature",
  "properties": {
    "iso:country":"US",
    "sg:address":"219 Bingham St",
    "sg:city":"Oak Hill",
    "sg:classifiers":[
        {
            "category":"Wholesale",
            "subcategory":"Toys & Hobbies",
            "type":"Manufacturing & Wholesale Goods"
        }
    ],
    "sg:phone":"+1 740 682 6274",
    "sg:postcode":"45656",
    "sg:province":"OH",
    "sg:tags":[
        "mining",
        "construction",
        "machinery"
    ],
    "wof:name":"D & D Crafts",
    "wof:placetype":"venue"
},
  "geometry": {"coordinates":[-82.560536,38.89417],"type":"Point"}
}