{
  "type": "Feature",
  "properties": {
    "addr:full": "22201 State Route 51 W Genoa OH 43430",
    "addr:housenumber": "22201",
    "addr:postcode": "43430",
    "addr:street": "State Route 51 W",
    "iso:country": "US",
    "sg:address": "22201 State Route 51 W",
    "sg:city": "Genoa",
    "sg:classifiers": [
      {
        "category": "Restaurant",
        "type": "Food \u0026 Drink"
      }
    ],
    "sg:menulink": "http://www.allmenus.com/oh/clay/195074-mcdonalds/menu/",
    "sg:postcode": "43430",
    "sg:province": "OH",
    "sg:tags": [
      "burger",
      "american"
    ],
    "wof:name": "McDonald's",
    "wof:placetype": "venue"
  },
  "geometry": {"coordinates":[-83.359262,41.531625],"type":"Point"}
}
