{
  "type": "Feature",
  "properties": {
    "iso:country":"US",
    "sg:address":"22201 State Route 51 W",
    "sg:city":"Genoa",
    "sg:classifiers":[
        {
            "category":"Restaurant",
            "type":"Food & Drink"
        }
    ],
    "sg:menulink":"http://www.allmenus.com/oh/clay/195074-mcdonalds/menu/",
    "sg:postcode":"43430",
    "sg:province":"OH",
    "sg:tags":[
        "burger",
        "american"
    ],
    "wof:name":"McDonald's",
    "wof:placetype":"venue"
},
  "geometry": {"coordinates":[-83.359262,41.531625],"type":"Point"}
}