{
  "type": "Feature",
  "properties": {
    "addr:full":"5857 Smith Rd Brook Park OH 44142",
    "addr:housenumber":"5857",
    "addr:postcode":"44142",
    "addr:street":"Smith Rd",
    "iso:country":"US",
    "sg:address":"5857 Smith Rd",
    "sg:city":"Brook Park",
    "sg:classifiers":[
        {
            "category":"Restaurant",
            "type":"Food & Drink"
        }
    ],
    "sg:menulink":"http://www.allmenus.com/oh/brook-park/122314-quiznos-sub/menu/",
    "sg:phone":"+1 216 267 7893",
    "sg:postcode":"44142",
    "sg:province":"OH",
    "sg:tags":[
        "wrap",
        "american",
        "sandwich"
    ],
    "wof:name":"Quiznos Sub",
    "wof:placetype":"venue"
},
  "geometry": {"coordinates":[-81.804129,41.403425],"type":"Point"}
}