{
  "type": "Feature",
  "properties": {
    "addr:full":"4099 Easton Way Columbus OH 43219",
    "addr:housenumber":"4099",
    "addr:postcode":"43219",
    "addr:street":"Easton Way",
    "iso:country":"US",
    "sg:address":"4099 Easton Way",
    "sg:city":"Columbus",
    "sg:classifiers":[
        {
            "category":"Home & Garden",
            "subcategory":"Household Appliances",
            "type":"Retail Goods"
        }
    ],
    "sg:phone":"+1 614 478 4280",
    "sg:postcode":"43219",
    "sg:province":"OH",
    "sg:website":"www.hhgregg.com",
    "wof:name":"H H Gregg Appliances",
    "wof:placetype":"venue"
},
  "geometry": {"coordinates":[-82.91517899999999,40.047987],"type":"Point"}
}