{
  "type": "Feature",
  "properties": {
    "iso:country":"US",
    "sg:address":"4621 Wuebker Rd",
    "sg:city":"Minster",
    "sg:classifiers":[
        {
            "category":"Real Estate",
            "subcategory":"Real Estate Operator",
            "type":"Services"
        }
    ],
    "sg:phone":"+1 419 628 2764",
    "sg:postcode":"45865",
    "sg:province":"OH",
    "sg:tags":[
        "property",
        "lessor"
    ],
    "wof:name":"Bernard Stueve",
    "wof:placetype":"venue"
},
  "geometry": {"coordinates":[-84.365133,40.415186],"type":"Point"}
}