{
  "type": "Feature",
  "properties": {
    "addr:full": "4621 Wuebker Rd Minster OH 45865",
    "addr:housenumber": "4621",
    "addr:postcode": "45865",
    "addr:street": "Wuebker Rd",
    "iso:country": "US",
    "sg:address": "4621 Wuebker Rd",
    "sg:city": "Minster",
    "sg:classifiers": [
      {
        "category": "Real Estate",
        "subcategory": "Real Estate Operator",
        "type": "Services"
      }
    ],
    "sg:phone": "+1 419 628 2764",
    "sg:postcode": "45865",
    "sg:province": "OH",
    "sg:tags": [
      "property",
      "lessor"
    ],
    "wof:name": "Bernard Stueve",
    "wof:placetype": "venue"
  },
  "geometry": {"coordinates":[-84.365133,40.415186],"type":"Point"}
}
