{
  "type": "Feature",
  "properties": {
    "addr:full": "90 Grace Dr Powell OH 43065",
    "addr:housenumber": "90",
    "addr:postcode": "43065",
    "addr:street": "Grace Dr",
    "iso:country": "US",
    "sg:address": "90 Grace Dr",
    "sg:city": "Powell",
    "sg:classifiers": [
      {
        "category": "Building \u0026 Trades",
        "subcategory": "Electrical",
        "type": "Services"
      }
    ],
    "sg:phone": "+1 614 847 0035",
    "sg:postcode": "43065",
    "sg:province": "OH",
    "sg:tags": [
      "electrical",
      "contractor"
    ],
    "wof:name": "Cochran W R Industrial Elc",
    "wof:placetype": "venue"
  },
  "geometry": {"coordinates":[-83.073064,40.159605],"type":"Point"}
}
