{
  "type": "Feature",
  "properties": {
    "iso:country":"US",
    "sg:address":"26218 Thompson Rd",
    "sg:city":"Perrysburg",
    "sg:classifiers":[
        {
            "category":"Professional",
            "subcategory":"Advertising",
            "type":"Services"
        }
    ],
    "sg:phone":"+1 419 874 6870",
    "sg:postcode":"43551",
    "sg:province":"OH",
    "sg:tags":[
        "counselor"
    ],
    "wof:name":"Ad Ideas",
    "wof:placetype":"venue"
},
  "geometry": {"coordinates":[-83.586919,41.532605],"type":"Point"}
}