{
  "type": "Feature",
  "properties": {
    "iso:country":"US",
    "sg:address":"1115 Canton Rd NW",
    "sg:city":"Carrollton",
    "sg:classifiers":[
        {
            "category":"Restaurant",
            "type":"Food & Drink"
        }
    ],
    "sg:phone":"+1 330 627 7827",
    "sg:postcode":"44615",
    "sg:province":"OH",
    "sg:tags":[
        "eating"
    ],
    "wof:name":"Subway",
    "wof:placetype":"venue"
},
  "geometry": {"coordinates":[-81.09210400000001,40.587443],"type":"Point"}
}