{
  "type": "Feature",
  "properties": {
    "addr:full": "3936 Saddlehorn Dr Columbus OH 43221",
    "addr:housenumber": "3936",
    "addr:postcode": "43221",
    "addr:street": "Saddlehorn Dr",
    "iso:country": "US",
    "sg:address": "3936 Saddlehorn Dr",
    "sg:city": "Columbus",
    "sg:classifiers": [
      {
        "category": "Wholesale",
        "subcategory": "Medical Equipment \u0026 Supplies",
        "type": "Manufacturing \u0026 Wholesale Goods"
      }
    ],
    "sg:phone": "+1 614 529 1302",
    "sg:postcode": "43221",
    "sg:province": "OH",
    "wof:name": "Veterans Medical Supplies Inc",
    "wof:placetype": "venue"
  },
  "geometry": {"coordinates":[-83.121409,40.061835],"type":"Point"}
}
