{
  "type": "Feature",
  "properties": {
    "iso:country":"US",
    "sg:address":"407 N Depot St",
    "sg:city":"Sandusky",
    "sg:classifiers":[
        {
            "category":"Freight",
            "type":"Transportation"
        }
    ],
    "sg:phone":"+1 419 625 5238",
    "sg:postcode":"44870",
    "sg:province":"OH",
    "sg:tags":[
        "special"
    ],
    "wof:name":"S & J Warehousing Inc",
    "wof:placetype":"venue"
},
  "geometry": {"coordinates":[-82.707472,41.440016],"type":"Point"}
}