{
  "type": "Feature",
  "properties": {
    "addr:full": "407 N Depot St Sandusky OH 44870",
    "addr:housenumber": "407",
    "addr:postcode": "44870",
    "addr:street": "N Depot St",
    "iso:country": "US",
    "sg:address": "407 N Depot St",
    "sg:city": "Sandusky",
    "sg:classifiers": [
      {
        "category": "Freight",
        "type": "Transportation"
      }
    ],
    "sg:phone": "+1 419 625 5238",
    "sg:postcode": "44870",
    "sg:province": "OH",
    "sg:tags": [
      "special"
    ],
    "wof:name": "S \u0026 J Warehousing Inc",
    "wof:placetype": "venue"
  },
  "geometry": {"coordinates":[-82.707472,41.440016],"type":"Point"}
}
