{
  "type": "Feature",
  "properties": {
    "iso:country":"US",
    "sg:address":"1149 Stone Dr",
    "sg:city":"Harrison",
    "sg:classifiers":[
        {
            "category":"Professional",
            "subcategory":"Lawyer & Legal Services",
            "type":"Services"
        }
    ],
    "sg:phone":"+1 513 367 1999",
    "sg:postcode":"45030",
    "sg:province":"IN",
    "sg:tags":[
        "attorney"
    ],
    "wof:name":"Thomas J Kluener",
    "wof:placetype":"venue"
},
  "geometry": {"coordinates":[-84.795858,39.253676],"type":"Point"}
}