{
  "type": "Feature",
  "properties": {
    "addr:full": "1912 Edgewood Dr Defiance OH 43512",
    "addr:housenumber": "1912",
    "addr:postcode": "43512",
    "addr:street": "Edgewood Dr",
    "iso:country": "US",
    "sg:address": "1912 Edgewood Dr",
    "sg:city": "Defiance",
    "sg:classifiers": [
      {
        "category": "Professional",
        "subcategory": "Management \u0026 Consulting",
        "type": "Services"
      }
    ],
    "sg:phone": "+1 419 782 0578",
    "sg:postcode": "43512",
    "sg:province": "OH",
    "sg:tags": [
      "consultant",
      "business"
    ],
    "wof:name": "Signature Solutions",
    "wof:placetype": "venue"
  },
  "geometry": {"coordinates":[-84.328422,41.262476],"type":"Point"}
}
