{
  "type": "Feature",
  "properties": {
    "iso:country":"US",
    "sg:address":"7260 Smoky Row Rd",
    "sg:city":"Columbus",
    "sg:classifiers":[
        {
            "category":"Organizations",
            "subcategory":"Religious Organization",
            "type":"Services"
        }
    ],
    "sg:phone":"+1 614 889 5224",
    "sg:postcode":"43235",
    "sg:province":"OH",
    "sg:tags":[
        "church"
    ],
    "sg:website":"www.frbc.info",
    "wof:name":"Smoky Row Brethren Church",
    "wof:placetype":"venue"
},
  "geometry": {"coordinates":[-83.065718,40.111417],"type":"Point"}
}