{
  "type": "Feature",
  "properties": {
    "iso:country":"US",
    "sg:address":"11009 Edgewater Dr",
    "sg:city":"Cleveland",
    "sg:classifiers":[
        {
            "category":"Professional",
            "subcategory":"Lawyer & Legal Services",
            "type":"Services"
        }
    ],
    "sg:phone":"+1 216 631 4740",
    "sg:postcode":"44102",
    "sg:province":"OH",
    "sg:tags":[
        "attorney"
    ],
    "wof:name":"Feighan & Feighan",
    "wof:placetype":"venue"
},
  "geometry": {"coordinates":[-81.763881,41.489042],"type":"Point"}
}