{
  "type": "Feature",
  "properties": {
    "addr:full": "11511 Hopkins Ave Cleveland OH 44108",
    "addr:housenumber": "11511",
    "addr:postcode": "44108",
    "addr:street": "Hopkins Ave",
    "iso:country": "US",
    "sg:address": "11511 Hopkins Ave",
    "sg:city": "Cleveland",
    "sg:classifiers": [
      {
        "category": "Social Services",
        "subcategory": "Child Care",
        "type": "Services"
      }
    ],
    "sg:phone": "+1 216 761 4661",
    "sg:postcode": "44108",
    "sg:province": "OH",
    "wof:name": "R Miller Daycare",
    "wof:placetype": "venue"
  },
  "geometry": {"coordinates":[-81.605827,41.534588],"type":"Point"}
}
