{
  "type": "Feature",
  "properties": {
    "iso:country":"US",
    "sg:address":"11511 Hopkins Ave",
    "sg:city":"Cleveland",
    "sg:classifiers":[
        {
            "category":"Social Services",
            "subcategory":"Child Care",
            "type":"Services"
        }
    ],
    "sg:phone":"+1 216 761 4661",
    "sg:postcode":"44108",
    "sg:province":"OH",
    "wof:name":"R Miller Daycare",
    "wof:placetype":"venue"
},
  "geometry": {"coordinates":[-81.60582700000001,41.534588],"type":"Point"}
}