{
  "type": "Feature",
  "properties": {
    "addr:full":"1245 Mc Cook Ave Dayton OH 45404",
    "addr:housenumber":"1245",
    "addr:postcode":"45404",
    "addr:street":"Mc Cook Ave",
    "iso:country":"US",
    "sg:address":"1245 Mc Cook Ave",
    "sg:city":"Dayton",
    "sg:classifiers":[
        {
            "category":"Wholesale",
            "subcategory":"Machinery & Supplies",
            "type":"Manufacturing & Wholesale Goods"
        }
    ],
    "sg:phone":"+1 937 223 9902",
    "sg:postcode":"45404",
    "sg:province":"OH",
    "sg:tags":[
        "equipment",
        "industrial"
    ],
    "wof:name":"BOC Gases",
    "wof:placetype":"venue"
},
  "geometry": {"coordinates":[-84.191233,39.782562],"type":"Point"}
}