{
  "type": "Feature",
  "properties": {
    "addr:full": "1100 E Eureka St Lima OH 45804",
    "addr:housenumber": "1100",
    "addr:postcode": "45804",
    "addr:street": "E Eureka St",
    "iso:country": "US",
    "sg:address": "1100 E Eureka St",
    "sg:city": "Lima",
    "sg:classifiers": [
      {
        "category": "Building \u0026 Trades",
        "subcategory": "Construction",
        "type": "Services"
      }
    ],
    "sg:phone": "+1 419 224 2297",
    "sg:postcode": "45804",
    "sg:province": "OH",
    "sg:tags": [
      "fabricator",
      "metal"
    ],
    "wof:name": "B \u0026 E Fabrication",
    "wof:placetype": "venue"
  },
  "geometry": {"coordinates":[-84.088827,40.735016],"type":"Point"}
}
