{
  "type": "Feature",
  "properties": {
    "iso:country":"US",
    "sg:address":"1100 E Eureka St",
    "sg:city":"Lima",
    "sg:classifiers":[
        {
            "category":"Building & Trades",
            "subcategory":"Construction",
            "type":"Services"
        }
    ],
    "sg:phone":"+1 419 224 2297",
    "sg:postcode":"45804",
    "sg:province":"OH",
    "sg:tags":[
        "fabricator",
        "metal"
    ],
    "wof:name":"B & E Fabrication",
    "wof:placetype":"venue"
},
  "geometry": {"coordinates":[-84.08882699999999,40.735016],"type":"Point"}
}