{
  "type": "Feature",
  "properties": {
    "addr:full": "99 Ashwood Rd Tiffin OH 44883",
    "addr:housenumber": "99",
    "addr:postcode": "44883",
    "addr:street": "Ashwood Rd",
    "iso:country": "US",
    "sg:address": "99 Ashwood Rd",
    "sg:city": "Tiffin",
    "sg:classifiers": [
      {
        "category": "Insurance",
        "subcategory": "Insurance Agent",
        "type": "Services"
      }
    ],
    "sg:phone": "+1 419 447 3500",
    "sg:postcode": "44883",
    "sg:province": "OH",
    "wof:name": "Sky Insurance Inc",
    "wof:placetype": "venue"
  },
  "geometry": {"coordinates":[-83.201467,41.116455],"type":"Point"}
}
