{
  "type": "Feature",
  "properties": {
    "iso:country":"US",
    "sg:address":"2222 Warrensville Center Rd",
    "sg:city":"Cleveland",
    "sg:classifiers":[
        {
            "category":"Education",
            "subcategory":"Special Training",
            "type":"Public Place"
        }
    ],
    "sg:phone":"+1 440 526 9450",
    "sg:postcode":"44118",
    "sg:province":"OH",
    "sg:tags":[
        "reading",
        "instruction",
        "improvement"
    ],
    "sg:website":"www.huntingtonlearning.com",
    "wof:name":"Huntington Learning Centers",
    "wof:placetype":"venue"
},
  "geometry": {"coordinates":[-81.53632399999999,41.499145],"type":"Point"}
}