{
  "type": "Feature",
  "properties": {
    "addr:full":"1814 E 40th St Cleveland OH 44103",
    "addr:housenumber":"1814",
    "addr:postcode":"44103",
    "addr:street":"E 40Th St",
    "iso:country":"US",
    "sg:address":"1814 E 40th St",
    "sg:city":"Cleveland",
    "sg:classifiers":[
        {
            "category":"Professional",
            "subcategory":"Business Services",
            "type":"Services"
        },
        {
            "category":"Government",
            "subcategory":"Post Office",
            "type":"Public Place"
        }
    ],
    "sg:phone":"+1 216 391 1940",
    "sg:postcode":"44103",
    "sg:province":"OH",
    "sg:tags":[
        "mail",
        "list",
        "mailing",
        "shipping"
    ],
    "wof:name":"S J K Services",
    "wof:placetype":"venue"
},
  "geometry": {"coordinates":[-81.65891999999999,41.508461],"type":"Point"}
}