{
  "type": "Feature",
  "properties": {
    "iso:country":"US",
    "sg:address":"10955 Corduroy Rd",
    "sg:city":"Curtice",
    "sg:classifiers":[
        {
            "category":"Retail",
            "subcategory":"Auto Repair",
            "type":"Services"
        }
    ],
    "sg:phone":"+1 419 836 9123",
    "sg:postcode":"43412",
    "sg:province":"OH",
    "sg:tags":[
        "automotive"
    ],
    "wof:name":"South Shore Towing",
    "wof:placetype":"venue"
},
  "geometry": {"coordinates":[-83.287475,41.660877],"type":"Point"}
}