{
  "type": "Feature",
  "properties": {
    "iso:country":"US",
    "sg:address":"31150 Emery Rd",
    "sg:city":"Chagrin Falls",
    "sg:classifiers":[
        {
            "category":"Building & Trades",
            "subcategory":"Construction",
            "type":"Services"
        }
    ],
    "sg:phone":"+1 216 360 0907",
    "sg:postcode":"44022",
    "sg:province":"OH",
    "sg:tags":[
        "house"
    ],
    "wof:name":"Kensington Homes Inc",
    "wof:placetype":"venue"
},
  "geometry": {"coordinates":[-81.463574,41.437645],"type":"Point"}
}