{
  "type": "Feature",
  "properties": {
    "iso:country":"US",
    "sg:address":"1996 Noble Rd",
    "sg:city":"Cleveland",
    "sg:classifiers":[
        {
            "category":"Retail",
            "subcategory":"Animal Services",
            "type":"Services"
        }
    ],
    "sg:phone":"+1 216 249 1702",
    "sg:postcode":"44112",
    "sg:province":"OH",
    "wof:name":"Pretty Pooch Parlor",
    "wof:placetype":"venue"
},
  "geometry": {"coordinates":[-81.562462,41.54003],"type":"Point"}
}