{
  "type": "Feature",
  "properties": {
    "iso:country":"US",
    "sg:address":"153 W Main St",
    "sg:city":"Newcomerstown",
    "sg:classifiers":[
        {
            "category":"Shopping",
            "subcategory":"Bicycles & Sporting Goods",
            "type":"Retail Goods"
        }
    ],
    "sg:phone":"+1 740 492 0366",
    "sg:postcode":"43832",
    "sg:province":"OH",
    "sg:tags":[
        "equipment",
        "archery",
        "supply"
    ],
    "wof:name":"3D Archery",
    "wof:placetype":"venue"
},
  "geometry": {"coordinates":[-81.607337,40.275601],"type":"Point"}
}