{
  "type": "Feature",
  "properties": {
    "addr:full": "1 Caribou Ct Fairfield OH 45014",
    "addr:housenumber": "1",
    "addr:postcode": "45014",
    "addr:street": "Caribou Ct",
    "iso:country": "US",
    "sg:address": "1 Caribou Ct",
    "sg:city": "Fairfield",
    "sg:classifiers": [
      {
        "category": "Retail",
        "subcategory": "Repair Shop",
        "type": "Services"
      }
    ],
    "sg:phone": "+1 513 942 9622",
    "sg:postcode": "45014",
    "sg:province": "OH",
    "sg:tags": [
      "upholsterer"
    ],
    "wof:name": "Alberto Designs",
    "wof:placetype": "venue"
  },
  "geometry": {"coordinates":[-84.49799,39.310644],"type":"Point"}
}
