{
  "type": "Feature",
  "properties": {
    "addr:full":"10891 State Rte 212 NE Bolivar OH 44612",
    "addr:housenumber":"10891",
    "addr:postcode":"44612",
    "addr:street":"State Rte 212 Ne Bolivar",
    "iso:country":"US",
    "sg:address":"10891 State Rte 212 NE",
    "sg:city":"Bolivar",
    "sg:classifiers":[
        {
            "category":"Professional",
            "subcategory":"Advertising",
            "type":"Services"
        }
    ],
    "sg:phone":"+1 330 874 2396",
    "sg:postcode":"44612",
    "sg:province":"OH",
    "sg:tags":[
        "counselor"
    ],
    "sg:website":"www.phaseivmarketing.com",
    "wof:name":"Phase 4 Marketing Inc",
    "wof:placetype":"venue"
},
  "geometry": {"coordinates":[-81.440645,40.638943],"type":"Point"}
}