{
  "type": "Feature",
  "properties": {
    "iso:country":"US",
    "sg:address":"3820 E 52nd St",
    "sg:city":"Cleveland",
    "sg:classifiers":[
        {
            "category":"Home & Garden",
            "subcategory":"Home Furnishings",
            "type":"Retail Goods"
        }
    ],
    "sg:phone":"+1 216 441 0357",
    "sg:postcode":"44105",
    "sg:province":"OH",
    "sg:tags":[
        "lamp",
        "shades"
    ],
    "wof:name":"Burian Shades",
    "wof:placetype":"venue"
},
  "geometry": {"coordinates":[-81.65447399999999,41.455188],"type":"Point"}
}