{
  "type": "Feature",
  "properties": {
    "addr:full": "3820 E 52nd St Cleveland OH 44105",
    "addr:housenumber": "3820",
    "addr:postcode": "44105",
    "addr:street": "E 52Nd St",
    "iso:country": "US",
    "sg:address": "3820 E 52nd St",
    "sg:city": "Cleveland",
    "sg:classifiers": [
      {
        "category": "Home \u0026 Garden",
        "subcategory": "Home Furnishings",
        "type": "Retail Goods"
      }
    ],
    "sg:phone": "+1 216 441 0357",
    "sg:postcode": "44105",
    "sg:province": "OH",
    "sg:tags": [
      "lamp",
      "shades"
    ],
    "wof:name": "Burian Shades",
    "wof:placetype": "venue"
  },
  "geometry": {"coordinates":[-81.654474,41.455188],"type":"Point"}
}
