{
  "type": "Feature",
  "properties": {
    "addr:full": "7861 Reynolds Rd Mentor OH 44060",
    "addr:housenumber": "7861",
    "addr:postcode": "44060",
    "addr:street": "Reynolds Rd",
    "iso:country": "US",
    "sg:address": "7861 Reynolds Rd",
    "sg:city": "Mentor",
    "sg:classifiers": [
      {
        "category": "Restaurant",
        "type": "Food \u0026 Drink"
      }
    ],
    "sg:phone": "+1 440 946 5310",
    "sg:postcode": "44060",
    "sg:province": "OH",
    "sg:tags": [
      "eating"
    ],
    "sg:website": "www.ponderosasteakhouses.com",
    "wof:name": "Ponderosa Steakhouse",
    "wof:placetype": "venue"
  },
  "geometry": {"coordinates":[-81.377396,41.657374],"type":"Point"}
}
