{
  "type": "Feature",
  "properties": {
    "iso:country":"US",
    "sg:address":"104 Franklin St",
    "sg:city":"Gilboa",
    "sg:classifiers":[
        {
            "category":"Organizations",
            "subcategory":"Religious Organization",
            "type":"Services"
        }
    ],
    "sg:phone":"+1 419 456 3281",
    "sg:postcode":"45875",
    "sg:province":"OH",
    "sg:tags":[
        "church"
    ],
    "wof:name":"Gilboa United Methodist Church",
    "wof:placetype":"venue"
},
  "geometry": {"coordinates":[-83.923973,41.01739],"type":"Point"}
}