{
  "type": "Feature",
  "properties": {
    "addr:full":"2848 Springdale Rd Cincinnati OH 45251",
    "addr:housenumber":"2848",
    "addr:postcode":"45251",
    "addr:street":"Springdale Rd",
    "iso:country":"US",
    "sg:address":"2848 Springdale Rd",
    "sg:city":"Cincinnati",
    "sg:classifiers":[
        {
            "category":"Restaurant",
            "type":"Food & Drink"
        }
    ],
    "sg:phone":"+1 513 825 4000",
    "sg:postcode":"45251",
    "sg:province":"OH",
    "sg:tags":[
        "caterer"
    ],
    "wof:name":"Reuss Meats Produce & Bakery",
    "wof:placetype":"venue"
},
  "geometry": {"coordinates":[-84.577682,39.257148],"type":"Point"}
}