{
  "type": "Feature",
  "properties": {
    "addr:full": "8338 Hayes Rd Williamsfield OH 44093",
    "addr:housenumber": "8338",
    "addr:postcode": "44093",
    "addr:street": "Hayes Rd",
    "iso:country": "US",
    "sg:address": "8338 Hayes Rd",
    "sg:city": "Williamsfield",
    "sg:classifiers": [
      {
        "category": "Wholesale",
        "subcategory": "Construction Materials",
        "type": "Manufacturing \u0026 Wholesale Goods"
      }
    ],
    "sg:phone": "+1 440 293 5400",
    "sg:postcode": "44093",
    "sg:province": "OH",
    "sg:tags": [
      "sand",
      "gravel"
    ],
    "wof:name": "Kinsman Material Sand \u0026 Gravel",
    "wof:placetype": "venue"
  },
  "geometry": {"coordinates":[-80.647455,41.523509],"type":"Point"}
}
