{
  "type": "Feature",
  "properties": {
    "iso:country":"US",
    "sg:address":"8338 Hayes Rd",
    "sg:city":"Williamsfield",
    "sg:classifiers":[
        {
            "category":"Wholesale",
            "subcategory":"Construction Materials",
            "type":"Manufacturing & Wholesale Goods"
        }
    ],
    "sg:phone":"+1 440 293 5400",
    "sg:postcode":"44093",
    "sg:province":"OH",
    "sg:tags":[
        "sand",
        "gravel"
    ],
    "wof:name":"Kinsman Material Sand & Gravel",
    "wof:placetype":"venue"
},
  "geometry": {"coordinates":[-80.64745499999999,41.523509],"type":"Point"}
}