{
  "type": "Feature",
  "properties": {
    "addr:full":"171 S Sandusky St Delaware OH 43015",
    "addr:housenumber":"171",
    "addr:postcode":"43015",
    "addr:street":"S Sandusky St",
    "iso:country":"US",
    "sg:address":"171 S Sandusky St",
    "sg:city":"Delaware",
    "sg:classifiers":[
        {
            "category":"Shopping",
            "subcategory":"Used Merchandise",
            "type":"Retail Goods"
        }
    ],
    "sg:phone":"+1 740 369 6021",
    "sg:postcode":"43015",
    "sg:province":"OH",
    "sg:tags":[
        "general"
    ],
    "wof:name":"Goodwill Store",
    "wof:placetype":"venue"
},
  "geometry": {"coordinates":[-83.068229,40.29263],"type":"Point"}
}