{
  "type": "Feature",
  "properties": {
    "addr:full": "1692 E Kossuth St Columbus OH 43206",
    "addr:housenumber": "1692",
    "addr:postcode": "43206",
    "addr:street": "E Kossuth St",
    "iso:country": "US",
    "sg:address": "1692 E Kossuth St",
    "sg:city": "Columbus",
    "sg:classifiers": [
      {
        "category": "Professional",
        "subcategory": "Accounting \u0026 Tax Preparation",
        "type": "Services"
      }
    ],
    "sg:phone": "+1 614 253 8448",
    "sg:postcode": "43206",
    "sg:province": "OH",
    "sg:tags": [
      "return",
      "filing"
    ],
    "wof:name": "Coleman \u0026 Assoc Inc",
    "wof:placetype": "venue"
  },
  "geometry": {"coordinates":[-82.950134,39.943746],"type":"Point"}
}
