{
  "type": "Feature",
  "properties": {
    "addr:full": "525 N Crater Ave Dover OH 44622",
    "addr:housenumber": "525",
    "addr:postcode": "44622",
    "addr:street": "N Crater Ave",
    "iso:country": "US",
    "sg:address": "525 N Crater Ave",
    "sg:city": "Dover",
    "sg:classifiers": [
      {
        "category": "Banks \u0026 Credit Unions",
        "subcategory": "Bank",
        "type": "Services"
      }
    ],
    "sg:phone": "+1 330 343 6974",
    "sg:postcode": "44622",
    "sg:province": "OH",
    "sg:tags": [
      "loan",
      "broker",
      "mortgage"
    ],
    "wof:name": "TMK Mortgage",
    "wof:placetype": "venue"
  },
  "geometry": {"coordinates":[-81.473982,40.529016],"type":"Point"}
}
