{
  "type": "Feature",
  "properties": {
    "iso:country":"US",
    "sg:address":"525 N Crater Ave",
    "sg:city":"Dover",
    "sg:classifiers":[
        {
            "category":"Banks & Credit Unions",
            "subcategory":"Bank",
            "type":"Services"
        }
    ],
    "sg:phone":"+1 330 343 6974",
    "sg:postcode":"44622",
    "sg:province":"OH",
    "sg:tags":[
        "loan",
        "broker",
        "mortgage"
    ],
    "wof:name":"TMK Mortgage",
    "wof:placetype":"venue"
},
  "geometry": {"coordinates":[-81.47398200000001,40.529016],"type":"Point"}
}