{
  "type": "Feature",
  "properties": {
    "addr:full":"15450 Detroit Ave Cleveland OH 44107",
    "addr:housenumber":"15450",
    "addr:postcode":"44107",
    "addr:street":"Detroit Ave",
    "iso:country":"US",
    "sg:address":"15450 Detroit Ave",
    "sg:city":"Cleveland",
    "sg:classifiers":[
        {
            "category":"Sports & Exercise",
            "subcategory":"Golf",
            "type":"Entertainment"
        }
    ],
    "sg:phone":"+1 216 529 5900",
    "sg:postcode":"44107",
    "sg:province":"OH",
    "sg:tags":[
        "course"
    ],
    "wof:name":"Lakewood Little Links Golf Crs",
    "wof:placetype":"venue"
},
  "geometry": {"coordinates":[-81.802846,41.485101],"type":"Point"}
}