{
  "type": "Feature",
  "properties": {
    "iso:country":"US",
    "sg:address":"15387 Pearl Rd",
    "sg:city":"Cleveland",
    "sg:classifiers":[
        {
            "category":"Autos & Motor Vehicles",
            "subcategory":"Fuel & Gas Station",
            "type":"Retail Goods"
        }
    ],
    "sg:phone":"+1 440 878 1925",
    "sg:postcode":"44136",
    "sg:province":"OH",
    "sg:tags":[
        "oil"
    ],
    "wof:name":"Clark Gas Station",
    "wof:placetype":"venue"
},
  "geometry": {"coordinates":[-81.83512399999999,41.300684],"type":"Point"}
}