{
  "type": "Feature",
  "properties": {
    "addr:full": "15387 Pearl Rd Cleveland OH 44136",
    "addr:housenumber": "15387",
    "addr:postcode": "44136",
    "addr:street": "Pearl Rd",
    "iso:country": "US",
    "sg:address": "15387 Pearl Rd",
    "sg:city": "Cleveland",
    "sg:classifiers": [
      {
        "category": "Autos \u0026 Motor Vehicles",
        "subcategory": "Fuel \u0026 Gas Station",
        "type": "Retail Goods"
      }
    ],
    "sg:phone": "+1 440 878 1925",
    "sg:postcode": "44136",
    "sg:province": "OH",
    "sg:tags": [
      "oil"
    ],
    "wof:name": "Clark Gas Station",
    "wof:placetype": "venue"
  },
  "geometry": {"coordinates":[-81.835124,41.300684],"type":"Point"}
}
