{
  "type": "Feature",
  "properties": {
    "iso:country":"US",
    "sg:address":"4507 W 8th St",
    "sg:city":"Cincinnati",
    "sg:classifiers":[
        {
            "category":"Health Services",
            "subcategory":"Doctor",
            "type":"Services"
        }
    ],
    "sg:phone":"+1 513 381 0848",
    "sg:postcode":"45238",
    "sg:province":"OH",
    "sg:tags":[
        "physician",
        "surgeon"
    ],
    "wof:name":"Henry J Kenkel Sr MD",
    "wof:placetype":"venue"
},
  "geometry": {"coordinates":[-84.598551,39.108885],"type":"Point"}
}