{
  "type": "Feature",
  "properties": {
    "addr:full": "7601 Hamilton Ave Cincinnati OH 45231",
    "addr:housenumber": "7601",
    "addr:postcode": "45231",
    "addr:street": "Hamilton Ave",
    "iso:country": "US",
    "sg:address": "7601 Hamilton Ave",
    "sg:city": "Cincinnati",
    "sg:classifiers": [
      {
        "category": "Wholesale",
        "subcategory": "Machinery \u0026 Supplies",
        "type": "Manufacturing \u0026 Wholesale Goods"
      }
    ],
    "sg:phone": "+1 513 521 2370",
    "sg:postcode": "45231",
    "sg:province": "OH",
    "sg:tags": [
      "equipment",
      "salon",
      "establishment",
      "beauty"
    ],
    "wof:name": "Esther's Beauty Supplies",
    "wof:placetype": "venue"
  },
  "geometry": {"coordinates":[-84.548104,39.233531],"type":"Point"}
}
