{
  "type": "Feature",
  "properties": {
    "iso:country":"US",
    "sg:address":"315 Ken Mar Ind Pkwy",
    "sg:city":"Cleveland",
    "sg:classifiers":[
        {
            "category":"Wholesale",
            "subcategory":"Office Equipment",
            "type":"Manufacturing & Wholesale Goods"
        }
    ],
    "sg:phone":"+1 440 237 3636",
    "sg:postcode":"44147",
    "sg:province":"OH",
    "sg:tags":[
        "machine",
        "duplicating",
        "supply"
    ],
    "wof:name":"Wittco Standard",
    "wof:placetype":"venue"
},
  "geometry": {"coordinates":[-81.657049,41.315272],"type":"Point"}
}