{
  "type": "Feature",
  "properties": {
    "addr:full":"4470 Ridge Rd Cleveland OH 44144",
    "addr:housenumber":"4470",
    "addr:postcode":"44144",
    "addr:street":"Ridge Rd",
    "iso:country":"US",
    "sg:address":"4470 Ridge Rd",
    "sg:city":"Cleveland",
    "sg:classifiers":[
        {
            "category":"Organizations",
            "subcategory":"Religious Organization",
            "type":"Services"
        }
    ],
    "sg:phone":"+1 216 749 5585",
    "sg:postcode":"44144",
    "sg:province":"OH",
    "sg:tags":[
        "church"
    ],
    "sg:website":"www.lutheransonline.com/dmlchurch",
    "wof:name":"Dr Martin Luther Lutheran Chr",
    "wof:placetype":"venue"
},
  "geometry": {"coordinates":[-81.73539,41.435669],"type":"Point"}
}