{
  "type": "Feature",
  "properties": {
    "addr:full": "134 N 4th St Cambridge OH 43725",
    "addr:housenumber": "134",
    "addr:postcode": "43725",
    "addr:street": "N 4Th St",
    "iso:country": "US",
    "sg:address": "134 N 4th St",
    "sg:city": "Cambridge",
    "sg:classifiers": [
      {
        "category": "Restaurant",
        "type": "Food \u0026 Drink"
      }
    ],
    "sg:phone": "+1 740 432 7366",
    "sg:postcode": "43725",
    "sg:province": "OH",
    "sg:tags": [
      "eating"
    ],
    "wof:name": "Willie's Corner Restaurant",
    "wof:placetype": "venue"
  },
  "geometry": {"coordinates":[-81.596698,40.025629],"type":"Point"}
}
