{
  "type": "Feature",
  "properties": {
    "iso:country":"US",
    "sg:address":"134 N 4th St",
    "sg:city":"Cambridge",
    "sg:classifiers":[
        {
            "category":"Restaurant",
            "type":"Food & Drink"
        }
    ],
    "sg:phone":"+1 740 432 7366",
    "sg:postcode":"43725",
    "sg:province":"OH",
    "sg:tags":[
        "eating"
    ],
    "wof:name":"Willie's Corner Restaurant",
    "wof:placetype":"venue"
},
  "geometry": {"coordinates":[-81.596698,40.025629],"type":"Point"}
}