{
  "type": "Feature",
  "properties": {
    "addr:full": "2000 Brittain Rd Akron OH 44310",
    "addr:housenumber": "2000",
    "addr:postcode": "44310",
    "addr:street": "Brittain Rd",
    "iso:country": "US",
    "sg:address": "2000 Brittain Rd",
    "sg:city": "Akron",
    "sg:classifiers": [
      {
        "category": "Bakery",
        "type": "Food \u0026 Drink"
      }
    ],
    "sg:menulink": "http://www.allmenus.com/oh/akron/220121-auntie-annes-pretzels/menu/",
    "sg:phone": "+1 330 633 8650",
    "sg:postcode": "44310",
    "sg:province": "OH",
    "sg:tags": [
      "american",
      "pastry"
    ],
    "wof:name": "Auntie Anne's Pretzels",
    "wof:placetype": "venue"
  },
  "geometry": {"coordinates":[-81.470768,41.111578],"type":"Point"}
}
