{
  "type": "Feature",
  "properties": {
    "addr:full":"14375 Cleveland Rd SW Pataskala OH 43062",
    "addr:housenumber":"14375",
    "addr:postcode":"43062",
    "addr:street":"Cleveland Rd Sw",
    "iso:country":"US",
    "sg:address":"14375 Cleveland Rd SW",
    "sg:city":"Pataskala",
    "sg:classifiers":[
        {
            "category":"Building & Trades",
            "subcategory":"Construction",
            "type":"Services"
        }
    ],
    "sg:phone":"+1 740 927 1207",
    "sg:postcode":"43062",
    "sg:province":"OH",
    "sg:tags":[
        "housing"
    ],
    "wof:name":"Visintine Construction",
    "wof:placetype":"venue"
},
  "geometry": {"coordinates":[-82.761107,39.999023],"type":"Point"}
}