{
  "type": "Feature",
  "properties": {
    "addr:full":"771 S 30th St Newark OH 43056",
    "addr:housenumber":"771",
    "addr:postcode":"43056",
    "addr:street":"S 30Th St",
    "iso:country":"US",
    "sg:address":"771 S 30th St",
    "sg:city":"Newark",
    "sg:classifiers":[
        {
            "category":"Restaurant",
            "type":"Food & Drink"
        }
    ],
    "sg:phone":"+1 740 522 3587",
    "sg:postcode":"43056",
    "sg:province":"OH",
    "sg:tags":[
        "eating"
    ],
    "wof:name":"Arbys",
    "wof:placetype":"venue"
},
  "geometry": {"coordinates":[-82.443395,40.030931],"type":"Point"}
}