{
  "type": "Feature",
  "properties": {
    "iso:country":"US",
    "sg:address":"14023 State Rte 18",
    "sg:city":"Sherwood",
    "sg:classifiers":[
        {
            "category":"Food & Beverages",
            "subcategory":"Groceries & Convenience Stores",
            "type":"Retail Goods"
        }
    ],
    "sg:phone":"+1 419 899 2395",
    "sg:postcode":"43556",
    "sg:province":"OH",
    "sg:tags":[
        "grocer"
    ],
    "sg:website":"www.sherwoodsupercenter.com",
    "wof:name":"Village Food Emporium",
    "wof:placetype":"venue"
},
  "geometry": {"coordinates":[-84.553129,41.296422],"type":"Point"}
}