{
  "type": "Feature",
  "properties": {
    "addr:full":"1572 US Hwy 22 NW Washington Ct Hs OH 43160",
    "addr:housenumber":"1572",
    "addr:postcode":"43160",
    "addr:street":"Us Hwy 22 Nw",
    "iso:country":"US",
    "sg:address":"1572 US Hwy 22 NW",
    "sg:city":"Washington Ct Hs",
    "sg:classifiers":[
        {
            "category":"Autos & Motor Vehicles",
            "subcategory":"Automobile Sales",
            "type":"Retail Goods"
        }
    ],
    "sg:phone":"+1 740 333 6611",
    "sg:postcode":"43160",
    "sg:province":"OH",
    "sg:tags":[
        "car",
        "dealer"
    ],
    "wof:name":"D & M Auto Works",
    "wof:placetype":"venue"
},
  "geometry": {"coordinates":[-83.462322,39.529122],"type":"Point"}
}