{
  "type": "Feature",
  "properties": {
    "addr:full": "1708 Blue Rock St Cincinnati OH 45223",
    "addr:housenumber": "1708",
    "addr:postcode": "45223",
    "addr:street": "Blue Rock St",
    "iso:country": "US",
    "sg:address": "1708 Blue Rock St",
    "sg:city": "Cincinnati",
    "sg:classifiers": [
      {
        "category": "Retail",
        "subcategory": "Repair Shop",
        "type": "Services"
      }
    ],
    "sg:phone": "+1 513 681 5500",
    "sg:postcode": "45223",
    "sg:province": "OH",
    "sg:tags": [
      "welding"
    ],
    "wof:name": "Delhi Welding Co",
    "wof:placetype": "venue"
  },
  "geometry": {"coordinates":[-84.544503,39.160726],"type":"Point"}
}
