{
  "type": "Feature",
  "properties": {
    "addr:full":"483 Front St Berea OH 44017",
    "addr:housenumber":"483",
    "addr:postcode":"44017",
    "addr:street":"Front St",
    "iso:country":"US",
    "sg:address":"483 Front St",
    "sg:city":"Berea",
    "sg:classifiers":[
        {
            "category":"Shopping",
            "subcategory":"Gifts & Souvenirs",
            "type":"Retail Goods"
        }
    ],
    "sg:phone":"+1 440 243 7110",
    "sg:postcode":"44017",
    "sg:province":"OH",
    "sg:tags":[
        "personal"
    ],
    "wof:name":"Balloons By The Bunch",
    "wof:placetype":"venue"
},
  "geometry": {"coordinates":[-81.853148,41.379112],"type":"Point"}
}