{
  "type": "Feature",
  "properties": {
    "iso:country":"US",
    "sg:address":"3256 Midden Cir",
    "sg:city":"Cincinnati",
    "sg:classifiers":[
        {
            "category":"Restaurant",
            "type":"Food & Drink"
        }
    ],
    "sg:phone":"+1 513 389 1488",
    "sg:postcode":"45238",
    "sg:province":"OH",
    "wof:name":"Queen City Pizza",
    "wof:placetype":"venue"
},
  "geometry": {"coordinates":[-84.61309900000001,39.138601],"type":"Point"}
}