{
  "type": "Feature",
  "properties": {
    "addr:full": "3256 Midden Cir Cincinnati OH 45238",
    "addr:postcode": "3256;45238",
    "addr:street": "Midden Cir",
    "iso:country": "US",
    "sg:address": "3256 Midden Cir",
    "sg:city": "Cincinnati",
    "sg:classifiers": [
      {
        "category": "Restaurant",
        "type": "Food \u0026 Drink"
      }
    ],
    "sg:phone": "+1 513 389 1488",
    "sg:postcode": "45238",
    "sg:province": "OH",
    "wof:name": "Queen City Pizza",
    "wof:placetype": "venue"
  },
  "geometry": {"coordinates":[-84.613099,39.138601],"type":"Point"}
}
