{
  "type": "Feature",
  "properties": {
    "addr:full":"257 Delta Ave Cincinnati OH 45226",
    "addr:housenumber":"257",
    "addr:postcode":"45226",
    "addr:street":"Delta Ave",
    "iso:country":"US",
    "sg:address":"257 Delta Ave",
    "sg:city":"Cincinnati",
    "sg:classifiers":[
        {
            "category":"Building & Trades",
            "subcategory":"Construction",
            "type":"Services"
        }
    ],
    "sg:phone":"+1 513 871 6061",
    "sg:postcode":"45226",
    "sg:province":"OH",
    "sg:tags":[
        "handyman"
    ],
    "wof:name":"East Hills Handyman Svc",
    "wof:placetype":"venue"
},
  "geometry": {"coordinates":[-84.441462,39.11546],"type":"Point"}
}