{
  "type": "Feature",
  "properties": {
    "addr:full": "945 Safin Rd Columbus OH 43204",
    "addr:housenumber": "945",
    "addr:postcode": "43204",
    "addr:street": "Safin Rd",
    "iso:country": "US",
    "sg:address": "945 Safin Rd",
    "sg:city": "Columbus",
    "sg:classifiers": [
      {
        "category": "Wholesale",
        "subcategory": "Motor Vehicles",
        "type": "Manufacturing \u0026 Wholesale Goods"
      }
    ],
    "sg:phone": "+1 614 274 2400",
    "sg:postcode": "43204",
    "sg:province": "OH",
    "sg:tags": [
      "trailer"
    ],
    "wof:name": "Transportation Supply Depot",
    "wof:placetype": "venue"
  },
  "geometry": {"coordinates":[-83.073456,39.974936],"type":"Point"}
}
