{
  "type": "Feature",
  "properties": {
    "addr:full": "316 Grandview Ave NW Canton OH 44708",
    "addr:housenumber": "316",
    "addr:postcode": "44708",
    "addr:street": "Grandview Ave Nw",
    "iso:country": "US",
    "sg:address": "316 Grandview Ave NW",
    "sg:city": "Canton",
    "sg:classifiers": [
      {
        "category": "Professional",
        "subcategory": "Lawyer \u0026 Legal Services",
        "type": "Services"
      }
    ],
    "sg:phone": "+1 330 478 3833",
    "sg:postcode": "44708",
    "sg:province": "OH",
    "sg:tags": [
      "attorney"
    ],
    "wof:name": "Douglas T Fowler",
    "wof:placetype": "venue"
  },
  "geometry": {"coordinates":[-81.424483,40.803078],"type":"Point"}
}
