{
  "type": "Feature",
  "properties": {
    "addr:full":"15970 Salem Church St NE Alliance OH 44601",
    "addr:housenumber":"15970",
    "addr:postcode":"44601",
    "addr:street":"Salem Church St Ne",
    "iso:country":"US",
    "sg:address":"15970 Salem Church St NE",
    "sg:city":"Alliance",
    "sg:classifiers":[
        {
            "category":"Food & Beverages",
            "subcategory":"Bakery",
            "type":"Retail Goods"
        }
    ],
    "sg:phone":"+1 330 821 9490",
    "sg:postcode":"44601",
    "sg:province":"OH",
    "wof:name":"Jubilee Donuts Inc",
    "wof:placetype":"venue"
},
  "geometry": {"coordinates":[-81.0915,40.850056],"type":"Point"}
}