{
  "type": "Feature",
  "properties": {
    "iso:country":"US",
    "sg:address":"5399 Brandt Pike",
    "sg:city":"Dayton",
    "sg:classifiers":[
        {
            "category":"Health Services",
            "subcategory":"Doctor",
            "type":"Services"
        }
    ],
    "sg:phone":"+1 937 237 9396",
    "sg:postcode":"45424",
    "sg:province":"OH",
    "sg:tags":[
        "dentist"
    ],
    "wof:name":"Brandt Pike Dental Care",
    "wof:placetype":"venue"
},
  "geometry": {"coordinates":[-84.121739,39.832971],"type":"Point"}
}