{
  "type": "Feature",
  "properties": {
    "iso:country":"US",
    "sg:address":"2648 Whiton Rd",
    "sg:city":"Cleveland",
    "sg:classifiers":[
        {
            "category":"Real Estate",
            "subcategory":"Real Estate Agent",
            "type":"Services"
        }
    ],
    "sg:phone":"+1 216 932 7878",
    "sg:postcode":"44118",
    "sg:province":"OH",
    "wof:name":"Suki Schmelzer Realtor",
    "wof:placetype":"venue"
},
  "geometry": {"coordinates":[-81.519942,41.488298],"type":"Point"}
}