{
  "type": "Feature",
  "properties": {
    "addr:full": "2629 Water Park Dr Mason OH 45040",
    "addr:housenumber": "2629",
    "addr:postcode": "45040",
    "addr:street": "Water Park Dr",
    "iso:country": "US",
    "sg:address": "2629 Water Park Dr",
    "sg:city": "Mason",
    "sg:classifiers": [
      {
        "category": "Restaurant",
        "type": "Food \u0026 Drink"
      }
    ],
    "sg:menulink": "http://www.allmenus.com/oh/mason/44086-bob-evans/menu/",
    "sg:phone": "+1 513 459 7087",
    "sg:postcode": "45040",
    "sg:province": "OH",
    "sg:tags": [
      "american"
    ],
    "wof:name": "Bob Evans",
    "wof:placetype": "venue"
  },
  "geometry": {"coordinates":[-84.2647,39.359549],"type":"Point"}
}
