{
  "type": "Feature",
  "properties": {
    "addr:full":"120 Pine St Elyria OH 44035",
    "addr:housenumber":"120",
    "addr:postcode":"44035",
    "addr:street":"Pine St",
    "iso:country":"US",
    "sg:address":"120 Pine St",
    "sg:city":"Elyria",
    "sg:classifiers":[
        {
            "category":"Manufacturing",
            "subcategory":"Chemicals & Compounds",
            "type":"Manufacturing & Wholesale Goods"
        }
    ],
    "sg:phone":"+1 440 322 3741",
    "sg:postcode":"44035",
    "sg:province":"OH",
    "sg:tags":[
        "inorganic",
        "industrial"
    ],
    "wof:name":"Engelhard Corp",
    "wof:placetype":"venue"
},
  "geometry": {"coordinates":[-82.102206,41.369946],"type":"Point"}
}