{
  "type": "Feature",
  "properties": {
    "addr:full": "250 Glessner Ave Mansfield OH 44903",
    "addr:housenumber": "250",
    "addr:postcode": "44903",
    "addr:street": "Glessner Ave",
    "iso:country": "US",
    "sg:address": "250 Glessner Ave",
    "sg:city": "Mansfield",
    "sg:classifiers": [
      {
        "category": "Social Services",
        "subcategory": "Child Care",
        "type": "Services"
      }
    ],
    "sg:phone": "+1 419 522 6766",
    "sg:postcode": "44903",
    "sg:province": "OH",
    "sg:tags": [
      "day"
    ],
    "wof:name": "Little Blessings Preschool \u0026 D",
    "wof:placetype": "venue"
  },
  "geometry": {"coordinates":[-82.525281,40.753551],"type":"Point"}
}
