{
  "type": "Feature",
  "properties": {
    "iso:country":"US",
    "sg:address":"2144 W Alexis Rd",
    "sg:city":"Toledo",
    "sg:classifiers":[
        {
            "category":"Personal",
            "subcategory":"Barber",
            "type":"Services"
        }
    ],
    "sg:phone":"+1 419 474 7678",
    "sg:postcode":"43613",
    "sg:province":"OH",
    "wof:name":"Classic Barbers",
    "wof:placetype":"venue"
},
  "geometry": {"coordinates":[-83.596553,41.721292],"type":"Point"}
}