{
  "type": "Feature",
  "properties": {
    "iso:country":"US",
    "sg:address":"4315 Manchester Rd",
    "sg:city":"Akron",
    "sg:classifiers":[
        {
            "category":"Restaurant",
            "type":"Food & Drink"
        }
    ],
    "sg:phone":"+1 330 644 2239",
    "sg:postcode":"44319",
    "sg:province":"OH",
    "wof:name":"Anthe's",
    "wof:placetype":"venue"
},
  "geometry": {"coordinates":[-81.559079,40.98788],"type":"Point"}
}