{
  "type": "Feature",
  "properties": {
    "iso:country":"US",
    "sg:address":"3292 Maize Rd",
    "sg:city":"Columbus",
    "sg:classifiers":[
        {
            "category":"Professional",
            "subcategory":"Accounting & Tax Preparation",
            "type":"Services"
        }
    ],
    "sg:phone":"+1 614 447 8011",
    "sg:postcode":"43224",
    "sg:province":"OH",
    "sg:tags":[
        "return",
        "filing"
    ],
    "wof:name":"Rapid Tax Svc",
    "wof:placetype":"venue"
},
  "geometry": {"coordinates":[-82.98964700000001,40.030825],"type":"Point"}
}