{
  "type": "Feature",
  "properties": {
    "addr:full": "5750 W Alexis Rd Sylvania OH 43560",
    "addr:housenumber": "5750",
    "addr:postcode": "43560",
    "addr:street": "W Alexis Rd",
    "iso:country": "US",
    "sg:address": "5750 W Alexis Rd",
    "sg:city": "Sylvania",
    "sg:classifiers": [
      {
        "category": "Professional",
        "subcategory": "Accounting \u0026 Tax Preparation",
        "type": "Services"
      }
    ],
    "sg:phone": "+1 419 882 1886",
    "sg:postcode": "43560",
    "sg:province": "OH",
    "sg:tags": [
      "accountant"
    ],
    "wof:name": "Clendenin \u0026 Zbierajewski",
    "wof:placetype": "venue"
  },
  "geometry": {"coordinates":[-83.684261,41.715663],"type":"Point"}
}
