{
  "type": "Feature",
  "properties": {
    "iso:country":"US",
    "sg:address":"5750 W Alexis Rd",
    "sg:city":"Sylvania",
    "sg:classifiers":[
        {
            "category":"Professional",
            "subcategory":"Accounting & Tax Preparation",
            "type":"Services"
        }
    ],
    "sg:phone":"+1 419 882 1886",
    "sg:postcode":"43560",
    "sg:province":"OH",
    "sg:tags":[
        "accountant"
    ],
    "wof:name":"Clendenin & Zbierajewski",
    "wof:placetype":"venue"
},
  "geometry": {"coordinates":[-83.684261,41.715663],"type":"Point"}
}