{
  "type": "Feature",
  "properties": {
    "addr:full": "14068 Euclid Ave Cleveland OH 44112",
    "addr:housenumber": "14068",
    "addr:postcode": "44112",
    "addr:street": "Euclid Ave",
    "iso:country": "US",
    "sg:address": "14068 Euclid Ave",
    "sg:city": "Cleveland",
    "sg:classifiers": [
      {
        "category": "Social Services",
        "subcategory": "Child Care",
        "type": "Services"
      }
    ],
    "sg:phone": "+1 216 851 4100",
    "sg:postcode": "44112",
    "sg:province": "OH",
    "wof:name": "Angels In Heaven",
    "wof:placetype": "venue"
  },
  "geometry": {"coordinates":[-81.58441,41.527974],"type":"Point"}
}
