{
  "type": "Feature",
  "properties": {
    "iso:country":"US",
    "sg:address":"118 Hemlock Ave",
    "sg:city":"Dover",
    "sg:classifiers":[
        {
            "category":"Health Services",
            "subcategory":"Clinic",
            "type":"Services"
        }
    ],
    "sg:phone":"+1 330 343 6676",
    "sg:postcode":"44622",
    "sg:province":"OH",
    "wof:name":"Health & Hope",
    "wof:placetype":"venue"
},
  "geometry": {"coordinates":[-81.464468,40.528517],"type":"Point"}
}