{
  "type": "Feature",
  "properties": {
    "addr:full": "10835 Main St Clarksburg OH 43115",
    "addr:housenumber": "10835",
    "addr:postcode": "43115",
    "addr:street": "Main St",
    "iso:country": "US",
    "sg:address": "10835 Main St",
    "sg:city": "Clarksburg",
    "sg:classifiers": [
      {
        "category": "Insurance",
        "subcategory": "Insurance Agent",
        "type": "Services"
      }
    ],
    "sg:phone": "+1 740 993 4347",
    "sg:postcode": "43115",
    "sg:province": "OH",
    "wof:name": "Neil Coleman Insurance",
    "wof:placetype": "venue"
  },
  "geometry": {"coordinates":[-83.153785,39.506098],"type":"Point"}
}
