{
  "type": "Feature",
  "properties": {
    "addr:full": "1439 Settlement Rd Norwalk OH 44857",
    "addr:housenumber": "1439",
    "addr:postcode": "44857",
    "addr:street": "Settlement Rd",
    "iso:country": "US",
    "sg:address": "1439 Settlement Rd",
    "sg:city": "Norwalk",
    "sg:classifiers": [
      {
        "category": "Retail",
        "subcategory": "Repair Shop",
        "type": "Services"
      }
    ],
    "sg:phone": "+1 419 660 9293",
    "sg:postcode": "44857",
    "sg:province": "OH",
    "sg:tags": [
      "equipment",
      "hydraulic"
    ],
    "wof:name": "Newland Enterprises",
    "wof:placetype": "venue"
  },
  "geometry": {"coordinates":[-82.638233,41.202085],"type":"Point"}
}
