{
  "type": "Feature",
  "properties": {
    "addr:full": "8455 Beechmont Ave Cincinnati OH 45255",
    "addr:housenumber": "8455",
    "addr:postcode": "45255",
    "addr:street": "Beechmont Ave",
    "iso:country": "US",
    "sg:address": "8455 Beechmont Ave",
    "sg:city": "Cincinnati",
    "sg:classifiers": [
      {
        "category": "Building \u0026 Trades",
        "subcategory": "Construction",
        "type": "Services"
      },
      {
        "category": "Home \u0026 Garden",
        "subcategory": "Carpets \u0026 Floor Coverings",
        "type": "Retail Goods"
      }
    ],
    "sg:phone": "+1 513 232 8161",
    "sg:postcode": "45255",
    "sg:province": "OH",
    "sg:tags": [
      "hardwood",
      "material",
      "contractor"
    ],
    "wof:name": "Finishing Tuches Hardwood Flrg",
    "wof:placetype": "venue"
  },
  "geometry": {"coordinates":[-84.315643,39.071908],"type":"Point"}
}
