{
  "type": "Feature",
  "properties": {
    "addr:full": "2040 Burnt Pond Rd Ostrander OH 43061",
    "addr:housenumber": "2040",
    "addr:postcode": "43061",
    "addr:street": "Burnt Pond Rd",
    "iso:country": "US",
    "sg:address": "2040 Burnt Pond Rd",
    "sg:city": "Ostrander",
    "sg:classifiers": [
      {
        "category": "Real Estate",
        "subcategory": "Real Estate Operator",
        "type": "Services"
      }
    ],
    "sg:phone": "+1 740 666 2571",
    "sg:postcode": "43061",
    "sg:province": "OH",
    "sg:tags": [
      "property",
      "lessor"
    ],
    "wof:name": "Burnt Pond Farm",
    "wof:placetype": "venue"
  },
  "geometry": {"coordinates":[-83.232546,40.284267],"type":"Point"}
}
