{
  "type": "Feature",
  "properties": {
    "addr:full": "2884 E Waterloo Rd Akron OH 44312",
    "addr:housenumber": "2884",
    "addr:postcode": "44312",
    "addr:street": "E Waterloo Rd",
    "iso:country": "US",
    "sg:address": "2884 E Waterloo Rd",
    "sg:city": "Akron",
    "sg:classifiers": [
      {
        "category": "Travel",
        "subcategory": "Hotels \u0026 Motels",
        "type": "Entertainment"
      }
    ],
    "sg:phone": "+1 330 628 3531",
    "sg:postcode": "44312",
    "sg:province": "OH",
    "sg:tags": [
      "operation"
    ],
    "wof:name": "Motors Inn Motel",
    "wof:placetype": "venue"
  },
  "geometry": {"coordinates":[-81.424043,41.030972],"type":"Point"}
}
