{
  "type": "Feature",
  "properties": {
    "iso:country":"US",
    "sg:address":"2884 E Waterloo Rd",
    "sg:city":"Akron",
    "sg:classifiers":[
        {
            "category":"Travel",
            "subcategory":"Hotels & Motels",
            "type":"Entertainment"
        }
    ],
    "sg:phone":"+1 330 628 3531",
    "sg:postcode":"44312",
    "sg:province":"OH",
    "sg:tags":[
        "operation"
    ],
    "wof:name":"Motors Inn Motel",
    "wof:placetype":"venue"
},
  "geometry": {"coordinates":[-81.424043,41.030972],"type":"Point"}
}