{
  "type": "Feature",
  "properties": {
    "addr:full": "705 Oakwood St Ravenna OH 44266",
    "addr:housenumber": "705",
    "addr:postcode": "44266",
    "addr:street": "Oakwood St",
    "iso:country": "US",
    "sg:address": "705 Oakwood St",
    "sg:city": "Ravenna",
    "sg:classifiers": [
      {
        "category": "Education",
        "subcategory": "Library",
        "type": "Public Place"
      }
    ],
    "sg:phone": "+1 330 296 2827",
    "sg:postcode": "44266",
    "sg:province": "OH",
    "wof:name": "Reed Memorial Library",
    "wof:placetype": "venue"
  },
  "geometry": {"coordinates":[-81.255671,41.165439],"type":"Point"}
}
