{
  "type": "Feature",
  "properties": {
    "iso:country":"US",
    "sg:address":"705 Oakwood St",
    "sg:city":"Ravenna",
    "sg:classifiers":[
        {
            "category":"Education",
            "subcategory":"Library",
            "type":"Public Place"
        }
    ],
    "sg:phone":"+1 330 296 2827",
    "sg:postcode":"44266",
    "sg:province":"OH",
    "wof:name":"Reed Memorial Library",
    "wof:placetype":"venue"
},
  "geometry": {"coordinates":[-81.25567100000001,41.165439],"type":"Point"}
}