{
  "type": "Feature",
  "properties": {
    "addr:full":"5570 Fulton Dr NW Canton OH 44718",
    "addr:housenumber":"5570",
    "addr:postcode":"44718",
    "addr:street":"Fulton Dr Nw",
    "iso:country":"US",
    "sg:address":"5570 Fulton Dr NW",
    "sg:city":"Canton",
    "sg:classifiers":[
        {
            "category":"Restaurant",
            "type":"Food & Drink"
        }
    ],
    "sg:phone":"+1 330 497 9111",
    "sg:postcode":"44718",
    "sg:province":"OH",
    "sg:tags":[
        "eating"
    ],
    "wof:name":"91 Wood Fired Oven Inc",
    "wof:placetype":"venue"
},
  "geometry": {"coordinates":[-81.452366,40.855072],"type":"Point"}
}