{
  "type": "Feature",
  "properties": {
    "addr:full": "4930 Manchester Rd Middletown OH 45042",
    "addr:housenumber": "4930",
    "addr:postcode": "45042",
    "addr:street": "Manchester Rd",
    "iso:country": "US",
    "sg:address": "4930 Manchester Rd",
    "sg:city": "Middletown",
    "sg:classifiers": [
      {
        "category": "Professional",
        "type": "Services"
      }
    ],
    "sg:phone": "+1 513 422 6778",
    "sg:postcode": "45042",
    "sg:province": "OH",
    "wof:name": "First Natl SW Ohio",
    "wof:placetype": "venue"
  },
  "geometry": {"coordinates":[-84.335046,39.52483],"type":"Point"}
}
