{
  "type": "Feature",
  "properties": {
    "iso:country":"US",
    "sg:address":"3233 W Sylvania Ave",
    "sg:city":"Toledo",
    "sg:classifiers":[
        {
            "category":"Personal",
            "subcategory":"Barber",
            "type":"Services"
        }
    ],
    "sg:phone":"+1 419 475 5794",
    "sg:postcode":"43613",
    "sg:province":"OH",
    "wof:name":"Bob's Barber Shop",
    "wof:placetype":"venue"
},
  "geometry": {"coordinates":[-83.623138,41.691731],"type":"Point"}
}