{
  "type": "Feature",
  "properties": {
    "addr:full": "5799 Mariemont Ave Cincinnati OH 45227",
    "addr:housenumber": "5799",
    "addr:postcode": "45227",
    "addr:street": "Mariemont Ave",
    "iso:country": "US",
    "sg:address": "5799 Mariemont Ave",
    "sg:city": "Cincinnati",
    "sg:classifiers": [
      {
        "category": "Professional",
        "subcategory": "Engineering",
        "type": "Services"
      }
    ],
    "sg:phone": "+1 513 561 1900",
    "sg:postcode": "45227",
    "sg:province": "OH",
    "sg:tags": [
      "engineer"
    ],
    "wof:name": "KCB Capital Partners",
    "wof:placetype": "venue"
  },
  "geometry": {"coordinates":[-84.389617,39.139599],"type":"Point"}
}
