{
  "type": "Feature",
  "properties": {
    "iso:country":"US",
    "sg:address":"3230 W Broad St",
    "sg:city":"Columbus",
    "sg:classifiers":[
        {
            "category":"Professional",
            "subcategory":"Business Services",
            "type":"Services"
        }
    ],
    "sg:phone":"+1 614 274 8197",
    "sg:postcode":"43204",
    "sg:province":"OH",
    "sg:tags":[
        "paging",
        "answering"
    ],
    "wof:name":"Aries Answering Service Inc",
    "wof:placetype":"venue"
},
  "geometry": {"coordinates":[-83.08626,39.954445],"type":"Point"}
}