{
  "type": "Feature",
  "properties": {
    "addr:full": "307 Taylor Ave Amherst OH 44001",
    "addr:housenumber": "307",
    "addr:postcode": "44001",
    "addr:street": "Taylor Ave",
    "iso:country": "US",
    "sg:address": "307 Taylor Ave",
    "sg:city": "Amherst",
    "sg:classifiers": [
      {
        "category": "Building \u0026 Trades",
        "subcategory": "Construction",
        "type": "Services"
      }
    ],
    "sg:phone": "+1 440 988 8220",
    "sg:postcode": "44001",
    "sg:province": "OH",
    "sg:tags": [
      "house"
    ],
    "wof:name": "Empire Builders",
    "wof:placetype": "venue"
  },
  "geometry": {"coordinates":[-82.214025,41.394435],"type":"Point"}
}
