{
  "type": "Feature",
  "properties": {
    "iso:country":"US",
    "sg:address":"300 N High St",
    "sg:city":"La Rue",
    "sg:classifiers":[
        {
            "category":"Retail",
            "subcategory":"Repair Shop",
            "type":"Services"
        }
    ],
    "sg:phone":"+1 740 499 2565",
    "sg:postcode":"43332",
    "sg:province":"OH",
    "sg:tags":[
        "appliance"
    ],
    "wof:name":"Ford's Appliance & Svc Inc",
    "wof:placetype":"venue"
},
  "geometry": {"coordinates":[-83.3844,40.580546],"type":"Point"}
}