{
  "type": "Feature",
  "properties": {
    "addr:full":"946 Garfield Ave Lancaster OH 43130",
    "addr:housenumber":"946",
    "addr:postcode":"43130",
    "addr:street":"Garfield Ave",
    "iso:country":"US",
    "sg:address":"946 Garfield Ave",
    "sg:city":"Lancaster",
    "sg:classifiers":[
        {
            "category":"Manufacturing",
            "subcategory":"Toys & Sporting Goods",
            "type":"Manufacturing & Wholesale Goods"
        }
    ],
    "sg:phone":"+1 740 687 1232",
    "sg:postcode":"43130",
    "sg:province":"OH",
    "sg:tags":[
        "mfg"
    ],
    "wof:name":"David Whitaker",
    "wof:placetype":"venue"
},
  "geometry": {"coordinates":[-82.616899,39.725943],"type":"Point"}
}