{
  "type": "Feature",
  "properties": {
    "iso:country":"US",
    "sg:address":"8630 Flagler St",
    "sg:city":"Dayton",
    "sg:classifiers":[
        {
            "category":"Wholesale",
            "subcategory":"Electrical",
            "type":"Manufacturing & Wholesale Goods"
        }
    ],
    "sg:phone":"+1 937 890 6534",
    "sg:postcode":"45415",
    "sg:province":"OH",
    "sg:tags":[
        "machine",
        "industrial",
        "sewing"
    ],
    "wof:name":"WEBB & Son Sewing Machine Sls",
    "wof:placetype":"venue"
},
  "geometry": {"coordinates":[-84.269969,39.849413],"type":"Point"}
}