{
  "type": "Feature",
  "properties": {
    "addr:full": "8630 Flagler St Dayton OH 45415",
    "addr:housenumber": "8630",
    "addr:postcode": "45415",
    "addr:street": "Flagler St",
    "iso:country": "US",
    "sg:address": "8630 Flagler St",
    "sg:city": "Dayton",
    "sg:classifiers": [
      {
        "category": "Wholesale",
        "subcategory": "Electrical",
        "type": "Manufacturing \u0026 Wholesale Goods"
      }
    ],
    "sg:phone": "+1 937 890 6534",
    "sg:postcode": "45415",
    "sg:province": "OH",
    "sg:tags": [
      "machine",
      "industrial",
      "sewing"
    ],
    "wof:name": "WEBB \u0026 Son Sewing Machine Sls",
    "wof:placetype": "venue"
  },
  "geometry": {"coordinates":[-84.269969,39.849413],"type":"Point"}
}
