{
  "type": "Feature",
  "properties": {
    "addr:full": "15 W 5th Ave Columbus OH 43201",
    "addr:housenumber": "15",
    "addr:postcode": "43201",
    "addr:street": "W 5Th Ave",
    "iso:country": "US",
    "sg:address": "15 W 5th Ave",
    "sg:city": "Columbus",
    "sg:classifiers": [
      {
        "category": "Wholesale",
        "subcategory": "Medical Equipment \u0026 Supplies",
        "type": "Manufacturing \u0026 Wholesale Goods"
      }
    ],
    "sg:phone": "+1 614 846 5740",
    "sg:postcode": "43201",
    "sg:province": "OH",
    "sg:tags": [
      "physician",
      "surgeon"
    ],
    "wof:name": "Stevens Surgical Supply",
    "wof:placetype": "venue"
  },
  "geometry": {"coordinates":[-83.007965,39.987112],"type":"Point"}
}
