{
  "type": "Feature",
  "properties": {
    "addr:full": "5995 Harrison Ave Cincinnati OH 45248",
    "addr:housenumber": "5995",
    "addr:postcode": "45248",
    "addr:street": "Harrison Ave",
    "iso:country": "US",
    "sg:address": "5995 Harrison Ave",
    "sg:city": "Cincinnati",
    "sg:classifiers": [
      {
        "category": "Autos \u0026 Motor Vehicles",
        "subcategory": "Automobile Sales",
        "type": "Retail Goods"
      }
    ],
    "sg:phone": "+1 513 598 6678",
    "sg:postcode": "45248",
    "sg:province": "OH",
    "sg:tags": [
      "car",
      "dealer"
    ],
    "wof:name": "Lauderbacks Auto Sales",
    "wof:placetype": "venue"
  },
  "geometry": {"coordinates":[-84.645523,39.177688],"type":"Point"}
}
