{
  "type": "Feature",
  "properties": {
    "iso:country":"US",
    "sg:address":"5995 Harrison Ave",
    "sg:city":"Cincinnati",
    "sg:classifiers":[
        {
            "category":"Autos & Motor Vehicles",
            "subcategory":"Automobile Sales",
            "type":"Retail Goods"
        }
    ],
    "sg:phone":"+1 513 598 6678",
    "sg:postcode":"45248",
    "sg:province":"OH",
    "sg:tags":[
        "car",
        "dealer"
    ],
    "wof:name":"Lauderbacks Auto Sales",
    "wof:placetype":"venue"
},
  "geometry": {"coordinates":[-84.645523,39.177688],"type":"Point"}
}