{
  "type": "Feature",
  "properties": {
    "addr:full":"1325 Wagner Rd Greenville OH 45331",
    "addr:housenumber":"1325",
    "addr:postcode":"45331",
    "addr:street":"Wagner Rd",
    "iso:country":"US",
    "sg:address":"1325 Wagner Rd",
    "sg:city":"Greenville",
    "sg:classifiers":[
        {
            "category":"Food & Beverages",
            "subcategory":"Groceries & Convenience Stores",
            "type":"Retail Goods"
        }
    ],
    "sg:phone":"+1 937 548 5815",
    "sg:postcode":"45331",
    "sg:province":"OH",
    "sg:tags":[
        "grocer"
    ],
    "wof:name":"Eikenberry's Iga Foodliners",
    "wof:placetype":"venue"
},
  "geometry": {"coordinates":[-84.757261,40.135431],"type":"Point"}
}