{
  "type": "Feature",
  "properties": {
    "iso:country":"US",
    "sg:address":"1370 W 6th St",
    "sg:city":"Cleveland",
    "sg:classifiers":[
        {
            "category":"Organizations",
            "subcategory":"Labor Organization",
            "type":"Services"
        }
    ],
    "sg:phone":"+1 216 861 7676",
    "sg:postcode":"44113",
    "sg:province":"OH",
    "wof:name":"Cleveland Teachers Union",
    "wof:placetype":"venue"
},
  "geometry": {"coordinates":[-81.69822000000001,41.499254],"type":"Point"}
}