{
  "type": "Feature",
  "properties": {
    "iso:country":"US",
    "sg:address":"11083 Reading Rd",
    "sg:city":"Cincinnati",
    "sg:classifiers":[
        {
            "category":"Restaurant",
            "type":"Food & Drink"
        }
    ],
    "sg:phone":"+1 513 563 4550",
    "sg:postcode":"45241",
    "sg:province":"OH",
    "sg:tags":[
        "eating"
    ],
    "wof:name":"Kidd Coffee",
    "wof:placetype":"venue"
},
  "geometry": {"coordinates":[-84.41295,39.270701],"type":"Point"}
}