{
  "type": "Feature",
  "properties": {
    "addr:full":"9025 Ohio River Rd Wheelersburg OH 45694",
    "addr:housenumber":"9025",
    "addr:postcode":"45694",
    "addr:street":"Ohio River Rd",
    "iso:country":"US",
    "sg:address":"9025 Ohio River Rd",
    "sg:city":"Wheelersburg",
    "sg:classifiers":[
        {
            "category":"Shopping",
            "subcategory":"Discount & Variety Stores",
            "type":"Retail Goods"
        }
    ],
    "sg:phone":"+1 740 574 4734",
    "sg:postcode":"45694",
    "sg:province":"OH",
    "wof:name":"Big Lots",
    "wof:placetype":"venue"
},
  "geometry": {"coordinates":[-82.856525,38.714845],"type":"Point"}
}