{
  "type": "Feature",
  "properties": {
    "iso:country":"US",
    "sg:address":"1158 Green Valley Dr",
    "sg:city":"Bidwell",
    "sg:classifiers":[
        {
            "category":"Shopping",
            "subcategory":"Computers & Home Electronics",
            "type":"Retail Goods"
        }
    ],
    "sg:phone":"+1 740 446 2975",
    "sg:postcode":"45614",
    "sg:province":"OH",
    "wof:name":"J B Net",
    "wof:placetype":"venue"
},
  "geometry": {"coordinates":[-82.278599,38.887902],"type":"Point"}
}