{
  "type": "Feature",
  "properties": {
    "addr:full": "69 W Main St Mc Connelsville OH 43756",
    "addr:housenumber": "69",
    "addr:postcode": "43756",
    "addr:street": "W Main St",
    "iso:country": "US",
    "sg:address": "69 W Main St",
    "sg:city": "Mc Connelsville",
    "sg:classifiers": [
      {
        "category": "Food \u0026 Beverages",
        "subcategory": "Groceries \u0026 Convenience Stores",
        "type": "Retail Goods"
      }
    ],
    "sg:phone": "+1 740 962 6201",
    "sg:postcode": "43756",
    "sg:province": "OH",
    "wof:name": "R \u0026 JS Stop-N-Shop",
    "wof:placetype": "venue"
  },
  "geometry": {"coordinates":[-81.854358,39.648949],"type":"Point"}
}
