{
  "type": "Feature",
  "properties": {
    "iso:country":"US",
    "sg:address":"69 W Main St",
    "sg:city":"Mc Connelsville",
    "sg:classifiers":[
        {
            "category":"Food & Beverages",
            "subcategory":"Groceries & Convenience Stores",
            "type":"Retail Goods"
        }
    ],
    "sg:phone":"+1 740 962 6201",
    "sg:postcode":"43756",
    "sg:province":"OH",
    "wof:name":"R & JS Stop-N-Shop",
    "wof:placetype":"venue"
},
  "geometry": {"coordinates":[-81.854358,39.648949],"type":"Point"}
}