{
  "type": "Feature",
  "properties": {
    "addr:full": "5110 Whipple Ave NW Canton OH 44718",
    "addr:housenumber": "5110",
    "addr:postcode": "44718",
    "addr:street": "Whipple Ave Nw",
    "iso:country": "US",
    "sg:address": "5110 Whipple Ave NW",
    "sg:city": "Canton",
    "sg:classifiers": [
      {
        "category": "Shopping",
        "type": "Retail Goods"
      }
    ],
    "sg:phone": "+1 330 493 0079",
    "sg:postcode": "44718",
    "sg:province": "OH",
    "sg:tags": [
      "church",
      "supply"
    ],
    "wof:name": "Cokesbury Book \u0026 Church Supls",
    "wof:placetype": "venue"
  },
  "geometry": {"coordinates":[-81.42282,40.855577],"type":"Point"}
}
