{
  "type": "Feature",
  "properties": {
    "addr:full":"1791 Elm Rd NE Warren OH 44483",
    "addr:housenumber":"1791",
    "addr:postcode":"44483",
    "addr:street":"Elm Rd Ne",
    "iso:country":"US",
    "sg:address":"1791 Elm Rd NE",
    "sg:city":"Warren",
    "sg:classifiers":[
        {
            "category":"Retail",
            "subcategory":"Animal Services",
            "type":"Services"
        }
    ],
    "sg:phone":"+1 330 372 6629",
    "sg:postcode":"44483",
    "sg:province":"OH",
    "sg:tags":[
        "pet",
        "grooming",
        "washing"
    ],
    "wof:name":"Dar's Dog Parlour",
    "wof:placetype":"venue"
},
  "geometry": {"coordinates":[-80.793964,41.252889],"type":"Point"}
}