{
  "type": "Feature",
  "properties": {
    "iso:country":"US",
    "sg:address":"5472 Mahoning Ave",
    "sg:city":"Youngstown",
    "sg:classifiers":[
        {
            "category":"Home & Garden",
            "subcategory":"Furniture",
            "type":"Retail Goods"
        }
    ],
    "sg:phone":"+1 330 270 8671",
    "sg:postcode":"44515",
    "sg:province":"OH",
    "sg:tags":[
        "mattress"
    ],
    "wof:name":"Quality Mattress Outlet",
    "wof:placetype":"venue"
},
  "geometry": {"coordinates":[-80.76212099999999,41.099688],"type":"Point"}
}