{
  "type": "Feature",
  "properties": {
    "addr:full": "635 E 115th St Cleveland OH 44108",
    "addr:housenumber": "635",
    "addr:postcode": "44108",
    "addr:street": "E 115Th St",
    "iso:country": "US",
    "sg:address": "635 E 115th St",
    "sg:city": "Cleveland",
    "sg:classifiers": [
      {
        "category": "Building \u0026 Trades",
        "subcategory": "Construction",
        "type": "Services"
      }
    ],
    "sg:phone": "+1 216 851 1561",
    "sg:postcode": "44108",
    "sg:province": "OH",
    "sg:tags": [
      "contractor"
    ],
    "wof:name": "B \u0026 K Demolition \u0026 Constr",
    "wof:placetype": "venue"
  },
  "geometry": {"coordinates":[-81.604758,41.538638],"type":"Point"}
}
