{
  "type": "Feature",
  "properties": {
    "addr:full":"6795 W Sugar Grove Rd Covington OH 45318",
    "addr:housenumber":"6795",
    "addr:postcode":"45318",
    "addr:street":"W Sugar Grove Rd",
    "iso:country":"US",
    "sg:address":"6795 W Sugar Grove Rd",
    "sg:city":"Covington",
    "sg:phone":"+1 937 473 5579",
    "sg:postcode":"45318",
    "sg:province":"OH",
    "sg:tags":[
        "farm",
        "grain",
        "cash"
    ],
    "wof:name":"Angle Farms",
    "wof:placetype":"venue"
},
  "geometry": {"coordinates":[-84.33009300000001,40.077429],"type":"Point"}
}