{
  "type": "Feature",
  "properties": {
    "addr:full": "15375 Brookpark Rd Cleveland OH 44142",
    "addr:housenumber": "15375",
    "addr:postcode": "44142",
    "addr:street": "Brookpark Rd",
    "iso:country": "US",
    "sg:address": "15375 Brookpark Rd",
    "sg:city": "Cleveland",
    "sg:classifiers": [
      {
        "category": "Retail",
        "subcategory": "Car Wash",
        "type": "Services"
      }
    ],
    "sg:phone": "+1 216 898 5674",
    "sg:postcode": "44142",
    "sg:province": "OH",
    "sg:tags": [
      "automobile",
      "detail",
      "clean"
    ],
    "wof:name": "Direct Detail",
    "wof:placetype": "venue"
  },
  "geometry": {"coordinates":[-81.807784,41.418517],"type":"Point"}
}
