{
  "type": "Feature",
  "properties": {
    "iso:country":"US",
    "sg:address":"150 E 4th St Fl 6",
    "sg:city":"Cincinnati",
    "sg:classifiers":[
        {
            "category":"Real Estate",
            "subcategory":"Architect",
            "type":"Services"
        }
    ],
    "sg:phone":"+1 513 421 2265",
    "sg:postcode":"45202",
    "sg:province":"OH",
    "sg:tags":[
        "architects'",
        "specification",
        "construction",
        "builders'",
        "architectural"
    ],
    "sg:website":"http://www.amkassociates.com",
    "wof:name":"A M Kinney Associates",
    "wof:placetype":"venue"
},
  "geometry": {"coordinates":[-84.510113,39.100313],"type":"Point"}
}