{
  "type": "Feature",
  "properties": {
    "iso:country":"US",
    "sg:address":"3025 E Manhattan Blvd",
    "sg:city":"Toledo",
    "sg:classifiers":[
        {
            "category":"Manufacturing",
            "subcategory":"Tools & Machinery",
            "type":"Manufacturing & Wholesale Goods"
        }
    ],
    "sg:phone":"+1 419 726 0970",
    "sg:postcode":"43608",
    "sg:province":"OH",
    "sg:tags":[
        "machine",
        "shop",
        "industrial",
        "mfg"
    ],
    "wof:name":"Salv-Pro Enterprises Inc",
    "wof:placetype":"venue"
},
  "geometry": {"coordinates":[-83.50314400000001,41.688412],"type":"Point"}
}