{
  "type": "Feature",
  "properties": {
    "iso:country":"US",
    "sg:address":"100 Indian Ridge Dr",
    "sg:city":"Piketon",
    "sg:classifiers":[
        {
            "category":"Health Services",
            "subcategory":"Doctor",
            "type":"Services"
        }
    ],
    "sg:phone":"+1 740 289 1900",
    "sg:postcode":"45661",
    "sg:province":"OH",
    "sg:tags":[
        "physician",
        "surgeon"
    ],
    "wof:name":"George P Pettit Inc",
    "wof:placetype":"venue"
},
  "geometry": {"coordinates":[-83.018976,39.059319],"type":"Point"}
}