{
  "type": "Feature",
  "properties": {
    "addr:full": "684 N Park Ave Warren OH 44483",
    "addr:housenumber": "684",
    "addr:postcode": "44483",
    "addr:street": "N Park Ave",
    "iso:country": "US",
    "sg:address": "684 N Park Ave",
    "sg:city": "Warren",
    "sg:classifiers": [
      {
        "category": "Professional",
        "subcategory": "Employment Agencies",
        "type": "Services"
      }
    ],
    "sg:phone": "+1 330 392 9223",
    "sg:postcode": "44483",
    "sg:province": "OH",
    "sg:tags": [
      "opportunity"
    ],
    "wof:name": "Senior Workers Action Program",
    "wof:placetype": "venue"
  },
  "geometry": {"coordinates":[-80.818128,41.243053],"type":"Point"}
}
