{
  "type": "Feature",
  "properties": {
    "addr:full":"8915 Brecksville Rd Brecksville OH 44141",
    "addr:housenumber":"8915",
    "addr:postcode":"44141",
    "addr:street":"Brecksville Rd",
    "iso:country":"US",
    "sg:address":"8915 Brecksville Rd",
    "sg:city":"Brecksville",
    "sg:classifiers":[
        {
            "category":"Real Estate",
            "subcategory":"Real Estate Agent",
            "type":"Services"
        }
    ],
    "sg:phone":"+1 440 526 1555",
    "sg:postcode":"44141",
    "sg:province":"OH",
    "sg:tags":[
        "agency"
    ],
    "wof:name":"Century 21",
    "wof:placetype":"venue"
},
  "geometry": {"coordinates":[-81.626778,41.319382],"type":"Point"}
}