{
  "type": "Feature",
  "properties": {
    "addr:full":"343 Chapin St Toledo OH 43609",
    "addr:housenumber":"343",
    "addr:postcode":"43609",
    "addr:street":"Chapin St",
    "iso:country":"US",
    "sg:address":"343 Chapin St",
    "sg:city":"Toledo",
    "sg:classifiers":[
        {
            "category":"Manufacturing",
            "subcategory":"Printing",
            "type":"Manufacturing & Wholesale Goods"
        }
    ],
    "sg:phone":"+1 419 255 8117",
    "sg:postcode":"43609",
    "sg:province":"OH",
    "sg:tags":[
        "commercial"
    ],
    "wof:name":"Transfer Connection",
    "wof:placetype":"venue"
},
  "geometry": {"coordinates":[-83.55927,41.63327],"type":"Point"}
}