{
  "type": "Feature",
  "properties": {
    "addr:full": "4294 Warren-Sharon Rd Vienna OH 44473",
    "addr:housenumber": "4294",
    "addr:postcode": "44473",
    "addr:street": "Warren-Sharon Rd",
    "iso:country": "US",
    "sg:address": "4294 Warren-Sharon Rd",
    "sg:city": "Vienna",
    "sg:classifiers": [
      {
        "category": "Sports \u0026 Exercise",
        "subcategory": "Race Track",
        "type": "Entertainment"
      },
      {
        "category": "Retail",
        "subcategory": "Auto Repair",
        "type": "Services"
      }
    ],
    "sg:phone": "+1 330 898 3300",
    "sg:postcode": "44473",
    "sg:province": "OH",
    "sg:tags": [
      "repairing",
      "automobile"
    ],
    "wof:name": "G \u0026 G Racing Products",
    "wof:placetype": "venue"
  },
  "geometry": {"coordinates":[-80.666875,41.237716],"type":"Point"}
}
