{
  "type": "Feature",
  "properties": {
    "addr:full": "13808 York Blvd Cleveland OH 44125",
    "addr:housenumber": "13808",
    "addr:postcode": "44125",
    "addr:street": "York Blvd",
    "iso:country": "US",
    "sg:address": "13808 York Blvd",
    "sg:city": "Cleveland",
    "sg:classifiers": [
      {
        "category": "Building \u0026 Trades",
        "subcategory": "Construction",
        "type": "Services"
      }
    ],
    "sg:phone": "+1 216 581 8193",
    "sg:postcode": "44125",
    "sg:province": "OH",
    "sg:tags": [
      "house"
    ],
    "wof:name": "Kozelka Home Improve",
    "wof:placetype": "venue"
  },
  "geometry": {"coordinates":[-81.586398,41.406367],"type":"Point"}
}
