{
  "type": "Feature",
  "properties": {
    "iso:country":"US",
    "sg:address":"922 Eastport Ave",
    "sg:city":"Uhrichsville",
    "sg:classifiers":[
        {
            "category":"Real Estate",
            "subcategory":"Real Estate Agent",
            "type":"Services"
        }
    ],
    "sg:phone":"+1 740 922 0505",
    "sg:postcode":"44683",
    "sg:province":"OH",
    "sg:tags":[
        "insurance"
    ],
    "wof:name":"Bob Spring & Associates Ltd",
    "wof:placetype":"venue"
},
  "geometry": {"coordinates":[-81.343733,40.398219],"type":"Point"}
}