{
  "type": "Feature",
  "properties": {
    "addr:full":"103 E Mcpherson Hwy Clyde OH 43410",
    "addr:housenumber":"103",
    "addr:postcode":"43410",
    "addr:street":"E Mcpherson Hwy",
    "iso:country":"US",
    "sg:address":"103 E Mcpherson Hwy",
    "sg:city":"Clyde",
    "sg:classifiers":[
        {
            "category":"Restaurant",
            "type":"Food & Drink"
        }
    ],
    "sg:menulink":"http://www.allmenus.com/oh/clyde/134008-subway/menu/",
    "sg:phone":"+1 419 547 0055",
    "sg:postcode":"43410",
    "sg:province":"OH",
    "sg:tags":[
        "american",
        "sandwich"
    ],
    "wof:name":"Subway",
    "wof:placetype":"venue"
},
  "geometry": {"coordinates":[-82.974765,41.309874],"type":"Point"}
}