{
  "type": "Feature",
  "properties": {
    "addr:full":"777 Bible Rd Lima OH 45801",
    "addr:housenumber":"777",
    "addr:postcode":"45801",
    "addr:street":"Bible Rd",
    "iso:country":"US",
    "sg:address":"777 Bible Rd",
    "sg:city":"Lima",
    "sg:classifiers":[
        {
            "category":"Organizations",
            "subcategory":"Labor Organization",
            "type":"Services"
        }
    ],
    "sg:phone":"+1 419 229 7947",
    "sg:postcode":"45801",
    "sg:province":"OH",
    "wof:name":"UAW Local",
    "wof:placetype":"venue"
},
  "geometry": {"coordinates":[-84.092067,40.774052],"type":"Point"}
}