{
  "type": "Feature",
  "properties": {
    "iso:country":"US",
    "sg:address":"300 S Main St",
    "sg:city":"Findlay",
    "sg:classifiers":[
        {
            "category":"Government",
            "subcategory":"Office",
            "type":"Public Place"
        }
    ],
    "sg:phone":"+1 419 424 7466",
    "sg:postcode":"45840",
    "sg:province":"OH",
    "sg:tags":[
        "village"
    ],
    "wof:name":"Neat Municipal Building",
    "wof:placetype":"venue"
},
  "geometry": {"coordinates":[-83.650243,41.039144],"type":"Point"}
}