{
  "type": "Feature",
  "properties": {
    "addr:full":"27701 Chardon Rd Wickliffe OH 44092",
    "addr:housenumber":"27701",
    "addr:postcode":"44092",
    "addr:street":"Chardon Rd",
    "iso:country":"US",
    "sg:address":"27701 Chardon Rd",
    "sg:city":"Wickliffe",
    "sg:classifiers":[
        {
            "category":"Banks & Credit Unions",
            "subcategory":"Bank",
            "type":"Services"
        }
    ],
    "sg:phone":"+1 440 943 5464",
    "sg:postcode":"44092",
    "sg:province":"OH",
    "wof:name":"Firstmerrit",
    "wof:placetype":"venue"
},
  "geometry": {"coordinates":[-81.483571,41.583165],"type":"Point"}
}