{
  "type": "Feature",
  "properties": {
    "iso:country":"US",
    "sg:address":"2007 Starr Ave",
    "sg:city":"Toledo",
    "sg:classifiers":[
        {
            "category":"Professional",
            "subcategory":"Computer Services",
            "type":"Services"
        }
    ],
    "sg:phone":"+1 419 693 1172",
    "sg:postcode":"43605",
    "sg:province":"OH",
    "sg:tags":[
        "repair"
    ],
    "wof:name":"P C Horsepower",
    "wof:placetype":"venue"
},
  "geometry": {"coordinates":[-83.501977,41.643783],"type":"Point"}
}