{
  "type": "Feature",
  "properties": {
    "iso:country":"US",
    "sg:address":"9564 Circle Dr S",
    "sg:city":"Pickerington",
    "sg:classifiers":[
        {
            "category":"Freight",
            "type":"Transportation"
        }
    ],
    "sg:phone":"+1 614 866 5141",
    "sg:postcode":"43147",
    "sg:province":"OH",
    "sg:tags":[
        "hauling",
        "trucking"
    ],
    "wof:name":"H J Horse Hauling",
    "wof:placetype":"venue"
},
  "geometry": {"coordinates":[-82.76913500000001,39.904646],"type":"Point"}
}