{
  "type": "Feature",
  "properties": {
    "addr:full": "9564 Circle Dr S Pickerington OH 43147",
    "addr:housenumber": "9564",
    "addr:postcode": "43147",
    "addr:street": "Circle Dr S",
    "iso:country": "US",
    "sg:address": "9564 Circle Dr S",
    "sg:city": "Pickerington",
    "sg:classifiers": [
      {
        "category": "Freight",
        "type": "Transportation"
      }
    ],
    "sg:phone": "+1 614 866 5141",
    "sg:postcode": "43147",
    "sg:province": "OH",
    "sg:tags": [
      "hauling",
      "trucking"
    ],
    "wof:name": "H J Horse Hauling",
    "wof:placetype": "venue"
  },
  "geometry": {"coordinates":[-82.769135,39.904646],"type":"Point"}
}
