{
  "type": "Feature",
  "properties": {
    "addr:full": "4038 White St Cincinnati OH 45255",
    "addr:housenumber": "4038",
    "addr:postcode": "45255",
    "addr:street": "White St",
    "iso:country": "US",
    "sg:address": "4038 White St",
    "sg:city": "Cincinnati",
    "sg:classifiers": [
      {
        "category": "Building \u0026 Trades",
        "subcategory": "Construction",
        "type": "Services"
      }
    ],
    "sg:phone": "+1 513 688 1333",
    "sg:postcode": "45255",
    "sg:province": "OH",
    "sg:tags": [
      "painter"
    ],
    "wof:name": "Bill's Painting \u0026 Carpentry",
    "wof:placetype": "venue"
  },
  "geometry": {"coordinates":[-84.299615,39.07086],"type":"Point"}
}
