{
  "type": "Feature",
  "properties": {
    "addr:full": "16 Belgrade Ave Youngstown OH 44505",
    "addr:housenumber": "16",
    "addr:postcode": "44505",
    "addr:street": "Belgrade Ave",
    "iso:country": "US",
    "sg:address": "16 Belgrade Ave",
    "sg:city": "Youngstown",
    "sg:classifiers": [
      {
        "category": "Professional",
        "subcategory": "Art Services",
        "type": "Services"
      },
      {
        "category": "Manufacturing",
        "subcategory": "Printing",
        "type": "Manufacturing \u0026 Wholesale Goods"
      }
    ],
    "sg:phone": "+1 330 759 9099",
    "sg:postcode": "44505",
    "sg:province": "OH",
    "sg:tags": [
      "plate",
      "graphic",
      "metal",
      "lithographic",
      "negative",
      "design"
    ],
    "wof:name": "Meridian Arts and Graphics",
    "wof:placetype": "venue"
  },
  "geometry": {"coordinates":[-80.667745,41.135889],"type":"Point"}
}
