{
  "type": "Feature",
  "properties": {
    "iso:country":"US",
    "sg:address":"130 Tiller Dr",
    "sg:city":"Powell",
    "sg:classifiers":[
        {
            "category":"Professional",
            "type":"Services"
        }
    ],
    "sg:phone":"+1 614 948 0043",
    "sg:postcode":"43065",
    "sg:province":"OH",
    "sg:tags":[
        "gift"
    ],
    "wof:name":"Rococo Limited",
    "wof:placetype":"venue"
},
  "geometry": {"coordinates":[-83.079369,40.144637],"type":"Point"}
}