{
  "type": "Feature",
  "properties": {
    "addr:full": "7411 Vantage Dr Columbus OH 43235",
    "addr:housenumber": "7411",
    "addr:postcode": "43235",
    "addr:street": "Vantage Dr",
    "iso:country": "US",
    "sg:address": "7411 Vantage Dr",
    "sg:city": "Columbus",
    "sg:classifiers": [
      {
        "category": "Travel",
        "subcategory": "Hotels \u0026 Motels",
        "type": "Entertainment"
      }
    ],
    "sg:phone": "+1 614 436 7070",
    "sg:postcode": "43235",
    "sg:province": "OH",
    "sg:tags": [
      "operation"
    ],
    "wof:name": "Courtyard By Marriott",
    "wof:placetype": "venue"
  },
  "geometry": {"coordinates":[-83.014458,40.116782],"type":"Point"}
}
