{
  "type": "Feature",
  "properties": {
    "addr:full":"1550 Cree Ct Grove City OH 43123",
    "addr:housenumber":"1550",
    "addr:postcode":"43123",
    "addr:street":"Cree Ct",
    "iso:country":"US",
    "sg:address":"1550 Cree Ct",
    "sg:city":"Grove City",
    "sg:classifiers":[
        {
            "category":"Building & Trades",
            "subcategory":"Landscaping Services",
            "type":"Services"
        }
    ],
    "sg:phone":"+1 614 871 8058",
    "sg:postcode":"43123",
    "sg:province":"OH",
    "sg:tags":[
        "lawn",
        "maintenance",
        "grounds"
    ],
    "wof:name":"Grasshopper Lawn & Yard",
    "wof:placetype":"venue"
},
  "geometry": {"coordinates":[-83.047954,39.831558],"type":"Point"}
}