{
  "type": "Feature",
  "properties": {
    "iso:country":"US",
    "sg:address":"4889 Sinclair Rd",
    "sg:city":"Columbus",
    "sg:classifiers":[
        {
            "category":"Organizations",
            "subcategory":"Religious Organization",
            "type":"Services"
        }
    ],
    "sg:phone":"+1 614 848 5587",
    "sg:postcode":"43229",
    "sg:province":"OH",
    "sg:tags":[
        "church"
    ],
    "wof:name":"New Covenant Believers Church",
    "wof:placetype":"venue"
},
  "geometry": {"coordinates":[-82.998823,40.062287],"type":"Point"}
}