{
  "type": "Feature",
  "properties": {
    "addr:full":"1321 Buena Vista St NE Canton OH 44714",
    "addr:housenumber":"1321",
    "addr:postcode":"44714",
    "addr:street":"Buena Vista St Ne",
    "iso:country":"US",
    "sg:address":"1321 Buena Vista St NE",
    "sg:city":"Canton",
    "sg:classifiers":[
        {
            "category":"Wholesale",
            "subcategory":"Machinery & Supplies",
            "type":"Manufacturing & Wholesale Goods"
        },
        {
            "category":"Professional",
            "subcategory":"Engineering",
            "type":"Services"
        }
    ],
    "sg:phone":"+1 330 494 2480",
    "sg:postcode":"44714",
    "sg:province":"OH",
    "sg:tags":[
        "equipment",
        "product",
        "industrial",
        "petroleum"
    ],
    "wof:name":"Jacket Industrial Sales Inc",
    "wof:placetype":"venue"
},
  "geometry": {"coordinates":[-81.35635000000001,40.858777],"type":"Point"}
}