{
  "type": "Feature",
  "properties": {
    "iso:country":"US",
    "sg:address":"1289 Yellowwood Dr",
    "sg:city":"Columbus",
    "sg:classifiers":[
        {
            "category":"Real Estate",
            "subcategory":"Real Estate Agent",
            "type":"Services"
        }
    ],
    "sg:phone":"+1 614 888 0340",
    "sg:postcode":"43229",
    "sg:province":"OH",
    "wof:name":"RDZ Investment Inc",
    "wof:placetype":"venue"
},
  "geometry": {"coordinates":[-82.98409599999999,40.077833],"type":"Point"}
}