{
  "type": "Feature",
  "properties": {
    "addr:full": "111 Liberty St West Liberty OH 43357",
    "addr:housenumber": "111",
    "addr:postcode": "43357",
    "addr:street": "Liberty St",
    "iso:country": "US",
    "sg:address": "111 Liberty St",
    "sg:city": "West Liberty",
    "sg:classifiers": [
      {
        "category": "Restaurant",
        "type": "Food \u0026 Drink"
      }
    ],
    "sg:phone": "+1 937 465 3081",
    "sg:postcode": "43357",
    "sg:province": "OH",
    "wof:name": "Liberty Gathering Place",
    "wof:placetype": "venue"
  },
  "geometry": {"coordinates":[-83.751918,40.252643],"type":"Point"}
}
