{
  "type": "Feature",
  "properties": {
    "iso:country":"US",
    "sg:address":"111 Liberty St",
    "sg:city":"West Liberty",
    "sg:classifiers":[
        {
            "category":"Restaurant",
            "type":"Food & Drink"
        }
    ],
    "sg:phone":"+1 937 465 3081",
    "sg:postcode":"43357",
    "sg:province":"OH",
    "wof:name":"Liberty Gathering Place",
    "wof:placetype":"venue"
},
  "geometry": {"coordinates":[-83.751918,40.252643],"type":"Point"}
}