{
  "type": "Feature",
  "properties": {
    "addr:full":"4158 State Rte 587 New Riegel OH 44853",
    "addr:housenumber":"4158",
    "addr:postcode":"44853",
    "addr:street":"State Rte 587",
    "iso:country":"US",
    "sg:address":"4158 State Rte 587",
    "sg:city":"New Riegel",
    "sg:classifiers":[
        {
            "category":"Farming",
            "subcategory":"Farm",
            "type":"Manufacturing & Wholesale Goods"
        }
    ],
    "sg:phone":"+1 419 595 3027",
    "sg:postcode":"44853",
    "sg:province":"OH",
    "sg:tags":[
        "crop",
        "general"
    ],
    "wof:name":"Bouillon Robert",
    "wof:placetype":"venue"
},
  "geometry": {"coordinates":[-83.32889,41.062688],"type":"Point"}
}