{
  "type": "Feature",
  "properties": {
    "addr:full": "37225 Aurora Rd Cleveland OH 44139",
    "addr:housenumber": "37225",
    "addr:postcode": "44139",
    "addr:street": "Aurora Rd",
    "iso:country": "US",
    "sg:address": "37225 Aurora Rd",
    "sg:city": "Cleveland",
    "sg:classifiers": [
      {
        "category": "Manufacturing",
        "subcategory": "Printing",
        "type": "Manufacturing \u0026 Wholesale Goods"
      }
    ],
    "sg:phone": "+1 440 248 2876",
    "sg:postcode": "44139",
    "sg:province": "OH",
    "sg:tags": [
      "publisher"
    ],
    "wof:name": "Drives \u0026 Controls Magazine",
    "wof:placetype": "venue"
  },
  "geometry": {"coordinates":[-81.414141,41.371777],"type":"Point"}
}
