{
  "type": "Feature",
  "properties": {
    "addr:full": "2280 W Henderson Rd Columbus OH 43220",
    "addr:housenumber": "2280",
    "addr:postcode": "43220",
    "addr:street": "W Henderson Rd",
    "iso:country": "US",
    "sg:address": "2280 W Henderson Rd",
    "sg:city": "Columbus",
    "sg:classifiers": [
      {
        "category": "Communications",
        "subcategory": "Film \u0026 Video Production",
        "type": "Services"
      }
    ],
    "sg:phone": "+1 614 326 1255",
    "sg:postcode": "43220",
    "sg:province": "OH",
    "sg:tags": [
      "audio"
    ],
    "sg:website": "www.avmproductions.com",
    "wof:name": "AVM Productions",
    "wof:placetype": "venue"
  },
  "geometry": {"coordinates":[-83.080232,40.05914],"type":"Point"}
}
