{
  "type": "Feature",
  "properties": {
    "iso:country":"US",
    "sg:address":"2280 W Henderson Rd",
    "sg:city":"Columbus",
    "sg:classifiers":[
        {
            "category":"Communications",
            "subcategory":"Film & Video Production",
            "type":"Services"
        }
    ],
    "sg:phone":"+1 614 326 1255",
    "sg:postcode":"43220",
    "sg:province":"OH",
    "sg:tags":[
        "audio"
    ],
    "sg:website":"www.avmproductions.com",
    "wof:name":"AVM Productions",
    "wof:placetype":"venue"
},
  "geometry": {"coordinates":[-83.080232,40.05914],"type":"Point"}
}