{
  "type": "Feature",
  "properties": {
    "addr:full":"401 Matthew St Marietta OH 45750",
    "addr:housenumber":"401",
    "addr:postcode":"45750",
    "addr:street":"Matthew St",
    "iso:country":"US",
    "sg:address":"401 Matthew St",
    "sg:city":"Marietta",
    "sg:classifiers":[
        {
            "category":"Health Services",
            "subcategory":"Hospital",
            "type":"Services"
        }
    ],
    "sg:phone":"+1 740 376 5000",
    "sg:postcode":"45750",
    "sg:province":"OH",
    "sg:tags":[
        "medical",
        "specialty"
    ],
    "wof:name":"Strecker Cancer Center",
    "wof:placetype":"venue"
},
  "geometry": {"coordinates":[-81.462362,39.434847],"type":"Point"}
}