{
  "type": "Feature",
  "properties": {
    "iso:country":"US",
    "sg:address":"6600 Highland Lakes Pl",
    "sg:city":"Westerville",
    "sg:classifiers":[
        {
            "category":"Professional",
            "type":"Services"
        }
    ],
    "sg:phone":"+1 614 823 4918",
    "sg:postcode":"43082",
    "sg:province":"OH",
    "wof:name":"Anthony R Mampieri",
    "wof:placetype":"venue"
},
  "geometry": {"coordinates":[-82.933725,40.163571],"type":"Point"}
}