{
  "type": "Feature",
  "properties": {
    "addr:full": "621 Broad St SW Pataskala OH 43062",
    "addr:housenumber": "621",
    "addr:postcode": "43062",
    "addr:street": "Broad St Sw",
    "iso:country": "US",
    "sg:address": "621 Broad St SW",
    "sg:city": "Pataskala",
    "sg:classifiers": [
      {
        "category": "Health Services",
        "subcategory": "Doctor",
        "type": "Services"
      }
    ],
    "sg:phone": "+1 740 927 5044",
    "sg:postcode": "43062",
    "sg:province": "OH",
    "sg:tags": [
      "physician",
      "surgeon"
    ],
    "wof:name": "Mid-Oh Medical Assoc",
    "wof:placetype": "venue"
  },
  "geometry": {"coordinates":[-82.689838,40.000669],"type":"Point"}
}
