{
  "type": "Feature",
  "properties": {
    "addr:full": "971 Kelenard Ave Columbus OH 43219",
    "addr:housenumber": "971",
    "addr:postcode": "43219",
    "addr:street": "Kelenard Ave",
    "iso:country": "US",
    "sg:address": "971 Kelenard Ave",
    "sg:city": "Columbus",
    "sg:classifiers": [
      {
        "category": "Building \u0026 Trades",
        "subcategory": "Landscaping Services",
        "type": "Services"
      }
    ],
    "sg:phone": "+1 614 679 2390",
    "sg:postcode": "43219",
    "sg:province": "OH",
    "sg:tags": [
      "landscape"
    ],
    "wof:name": "Schmidt Landscape",
    "wof:placetype": "venue"
  },
  "geometry": {"coordinates":[-82.939047,39.98969],"type":"Point"}
}
