{
  "type": "Feature",
  "properties": {
    "addr:full": "790 Wright St Yellow Springs OH 45387",
    "addr:housenumber": "790",
    "addr:postcode": "45387",
    "addr:street": "Wright St",
    "iso:country": "US",
    "sg:address": "790 Wright St",
    "sg:city": "Yellow Springs",
    "sg:classifiers": [
      {
        "category": "Manufacturing",
        "subcategory": "Pottery",
        "type": "Manufacturing \u0026 Wholesale Goods"
      }
    ],
    "sg:phone": "+1 937 767 1004",
    "sg:postcode": "45387",
    "sg:province": "OH",
    "sg:tags": [
      "stoneware",
      "mfr"
    ],
    "wof:name": "Michael Jones Ceramics",
    "wof:placetype": "venue"
  },
  "geometry": {"coordinates":[-83.901412,39.80018],"type":"Point"}
}
