{
  "type": "Feature",
  "properties": {
    "iso:country":"US",
    "sg:address":"790 Wright St",
    "sg:city":"Yellow Springs",
    "sg:classifiers":[
        {
            "category":"Manufacturing",
            "subcategory":"Pottery",
            "type":"Manufacturing & Wholesale Goods"
        }
    ],
    "sg:phone":"+1 937 767 1004",
    "sg:postcode":"45387",
    "sg:province":"OH",
    "sg:tags":[
        "stoneware",
        "mfr"
    ],
    "wof:name":"Michael Jones Ceramics",
    "wof:placetype":"venue"
},
  "geometry": {"coordinates":[-83.90141199999999,39.80018],"type":"Point"}
}