{
  "type": "Feature",
  "properties": {
    "addr:full": "32668 Center Ridge Rd North Ridgeville OH 44039",
    "addr:housenumber": "32668",
    "addr:postcode": "44039",
    "addr:street": "Center Ridge Rd",
    "iso:country": "US",
    "sg:address": "32668 Center Ridge Rd",
    "sg:city": "North Ridgeville",
    "sg:classifiers": [
      {
        "category": "Shopping",
        "type": "Retail Goods"
      }
    ],
    "sg:phone": "+1 440 327 7795",
    "sg:postcode": "44039",
    "sg:province": "OH",
    "sg:tags": [
      "art",
      "gallery",
      "dealer"
    ],
    "wof:name": "Franklin Express Art Craft Co",
    "wof:placetype": "venue"
  },
  "geometry": {"coordinates":[-81.977205,41.409424],"type":"Point"}
}
