{
  "type": "Feature",
  "properties": {
    "iso:country":"US",
    "sg:address":"1516 US Hwy 22 NW",
    "sg:city":"Washington Ct Hs",
    "sg:classifiers":[
        {
            "category":"Home & Garden",
            "subcategory":"Building Materials",
            "type":"Retail Goods"
        }
    ],
    "sg:phone":"+1 740 335 3373",
    "sg:postcode":"43160",
    "sg:province":"OH",
    "sg:tags":[
        "windows"
    ],
    "wof:name":"Builders Supply Co",
    "wof:placetype":"venue"
},
  "geometry": {"coordinates":[-83.461185,39.52935],"type":"Point"}
}