{
  "type": "Feature",
  "properties": {
    "addr:full": "15460 Justamere Rd Centerburg OH 43011",
    "addr:postcode": "15460;43011",
    "addr:street": "Justamere Rd",
    "iso:country": "US",
    "sg:address": "15460 Justamere Rd",
    "sg:city": "Centerburg",
    "sg:phone": "+1 740 625 7396",
    "sg:postcode": "43011",
    "sg:province": "OH",
    "sg:tags": [
      "farm",
      "corn"
    ],
    "wof:name": "Ellie Donohue",
    "wof:placetype": "venue"
  },
  "geometry": {"coordinates":[-82.775973,40.308963],"type":"Point"}
}
