{
  "type": "Feature",
  "properties": {
    "iso:country":"US",
    "sg:address":"15460 Justamere Rd",
    "sg:city":"Centerburg",
    "sg:phone":"+1 740 625 7396",
    "sg:postcode":"43011",
    "sg:province":"OH",
    "sg:tags":[
        "farm",
        "corn"
    ],
    "wof:name":"Ellie Donohue",
    "wof:placetype":"venue"
},
  "geometry": {"coordinates":[-82.77597299999999,40.308963],"type":"Point"}
}