{
  "type": "Feature",
  "properties": {
    "iso:country":"US",
    "sg:address":"11179 W Market St",
    "sg:city":"Germantown",
    "sg:classifiers":[
        {
            "category":"Real Estate",
            "subcategory":"Developer",
            "type":"Services"
        }
    ],
    "sg:phone":"+1 937 855 3011",
    "sg:postcode":"45327",
    "sg:province":"OH",
    "sg:tags":[
        "cemetery"
    ],
    "wof:name":"Germantown Cemetery Assn",
    "wof:placetype":"venue"
},
  "geometry": {"coordinates":[-84.389062,39.622756],"type":"Point"}
}