{
  "type": "Feature",
  "properties": {
    "addr:full": "8300 Tyler Blvd Mentor OH 44060",
    "addr:housenumber": "8300",
    "addr:postcode": "44060",
    "addr:street": "Tyler Blvd",
    "iso:country": "US",
    "sg:address": "8300 Tyler Blvd",
    "sg:city": "Mentor",
    "sg:classifiers": [
      {
        "category": "Health Services",
        "subcategory": "Doctor",
        "type": "Services"
      }
    ],
    "sg:phone": "+1 440 266 5002",
    "sg:postcode": "44060",
    "sg:province": "OH",
    "sg:tags": [
      "physician",
      "surgeon"
    ],
    "wof:name": "Your Diabetes Endocrine Nutri",
    "wof:placetype": "venue"
  },
  "geometry": {"coordinates":[-81.348857,41.682769],"type":"Point"}
}
