{
  "type": "Feature",
  "properties": {
    "addr:full": "7375 Industrial Pkwy Dr Lorain OH 44053",
    "addr:housenumber": "7375",
    "addr:postcode": "44053",
    "addr:street": "Industrial Pkwy Dr",
    "iso:country": "US",
    "sg:address": "7375 Industrial Pkwy Dr",
    "sg:city": "Lorain",
    "sg:classifiers": [
      {
        "category": "Manufacturing",
        "subcategory": "Metals",
        "type": "Manufacturing \u0026 Wholesale Goods"
      },
      {
        "category": "Manufacturing",
        "subcategory": "Chemicals \u0026 Compounds",
        "type": "Manufacturing \u0026 Wholesale Goods"
      }
    ],
    "sg:phone": "+1 440 960 5660",
    "sg:postcode": "44053",
    "sg:province": "OH",
    "sg:tags": [
      "mfg",
      "center",
      "beryllium",
      "plastic"
    ],
    "sg:website": "www.brushwellman.com",
    "wof:name": "Brush Wellman Inc",
    "wof:placetype": "venue"
  },
  "geometry": {"coordinates":[-82.27852,41.409143],"type":"Point"}
}
