{
  "type": "Feature",
  "properties": {
    "iso:country":"US",
    "sg:address":"7375 Industrial Pkwy Dr",
    "sg:city":"Lorain",
    "sg:classifiers":[
        {
            "category":"Manufacturing",
            "subcategory":"Metals",
            "type":"Manufacturing & Wholesale Goods"
        },
        {
            "category":"Manufacturing",
            "subcategory":"Chemicals & Compounds",
            "type":"Manufacturing & Wholesale Goods"
        }
    ],
    "sg:phone":"+1 440 960 5660",
    "sg:postcode":"44053",
    "sg:province":"OH",
    "sg:tags":[
        "mfg",
        "center",
        "beryllium",
        "plastic"
    ],
    "sg:website":"www.brushwellman.com",
    "wof:name":"Brush Wellman Inc",
    "wof:placetype":"venue"
},
  "geometry": {"coordinates":[-82.27852,41.409143],"type":"Point"}
}