{
  "type": "Feature",
  "properties": {
    "iso:country":"US",
    "sg:address":"13020 Miles Ave",
    "sg:city":"Cleveland",
    "sg:classifiers":[
        {
            "category":"Restaurant",
            "type":"Food & Drink"
        }
    ],
    "sg:menulink":"http://www.allmenus.com/oh/cleveland/233248-mr-hero/menu/",
    "sg:phone":"+1 216 883 7300",
    "sg:postcode":"44105",
    "sg:province":"OH",
    "sg:tags":[
        "wrap",
        "american",
        "sandwich"
    ],
    "wof:name":"Mr. Hero",
    "wof:placetype":"venue"
},
  "geometry": {"coordinates":[-81.591865,41.445373],"type":"Point"}
}