{
  "type": "Feature",
  "properties": {
    "addr:full": "101 Walnut St Mechanicsburg OH 43044",
    "addr:housenumber": "101",
    "addr:postcode": "43044",
    "addr:street": "Walnut St",
    "iso:country": "US",
    "sg:address": "101 Walnut St",
    "sg:city": "Mechanicsburg",
    "sg:classifiers": [
      {
        "category": "Building \u0026 Trades",
        "subcategory": "Construction",
        "type": "Services"
      }
    ],
    "sg:phone": "+1 937 834 2998",
    "sg:postcode": "43044",
    "sg:province": "OH",
    "sg:tags": [
      "contractor"
    ],
    "wof:name": "Regency Contractors Inc",
    "wof:placetype": "venue"
  },
  "geometry": {"coordinates":[-83.558732,40.072559],"type":"Point"}
}
