{
  "type": "Feature",
  "properties": {
    "iso:country":"US",
    "sg:address":"101 Walnut St",
    "sg:city":"Mechanicsburg",
    "sg:classifiers":[
        {
            "category":"Building & Trades",
            "subcategory":"Construction",
            "type":"Services"
        }
    ],
    "sg:phone":"+1 937 834 2998",
    "sg:postcode":"43044",
    "sg:province":"OH",
    "sg:tags":[
        "contractor"
    ],
    "wof:name":"Regency Contractors Inc",
    "wof:placetype":"venue"
},
  "geometry": {"coordinates":[-83.55873200000001,40.072559],"type":"Point"}
}