{
  "type": "Feature",
  "properties": {
    "addr:full": "14757 Walnut Creek Pike Ashville OH 43103",
    "addr:housenumber": "14757",
    "addr:postcode": "43103",
    "addr:street": "Walnut Creek Pike",
    "iso:country": "US",
    "sg:address": "14757 Walnut Creek Pike",
    "sg:city": "Ashville",
    "sg:classifiers": [
      {
        "category": "Building \u0026 Trades",
        "subcategory": "Equipment Rental",
        "type": "Services"
      }
    ],
    "sg:phone": "+1 740 983 8217",
    "sg:postcode": "43103",
    "sg:province": "OH",
    "sg:tags": [
      "camping"
    ],
    "wof:name": "TNT Party Tent Rental",
    "wof:placetype": "venue"
  },
  "geometry": {"coordinates":[-82.920712,39.714696],"type":"Point"}
}
