{
  "type": "Feature",
  "properties": {
    "addr:full":"23 College St Youngstown OH 44514",
    "addr:housenumber":"23",
    "addr:postcode":"44514",
    "addr:street":"College St",
    "iso:country":"US",
    "sg:address":"23 College St",
    "sg:city":"Youngstown",
    "sg:classifiers":[
        {
            "category":"Restaurant",
            "type":"Food & Drink"
        }
    ],
    "sg:phone":"+1 330 757 3298",
    "sg:postcode":"44514",
    "sg:province":"OH",
    "sg:tags":[
        "eating"
    ],
    "wof:name":"Pacificos Family Dining",
    "wof:placetype":"venue"
},
  "geometry": {"coordinates":[-80.613727,41.022242],"type":"Point"}
}