{
  "type": "Feature",
  "properties": {
    "addr:full":"266 Martinel Dr Kent OH 44240",
    "addr:housenumber":"266",
    "addr:postcode":"44240",
    "addr:street":"Martinel Dr",
    "iso:country":"US",
    "sg:address":"266 Martinel Dr",
    "sg:city":"Kent",
    "sg:classifiers":[
        {
            "category":"Retail",
            "subcategory":"Repair Shop",
            "type":"Services"
        },
        {
            "category":"Manufacturing",
            "subcategory":"Tools & Machinery",
            "type":"Manufacturing & Wholesale Goods"
        }
    ],
    "sg:phone":"+1 330 673 2411",
    "sg:postcode":"44240",
    "sg:province":"OH",
    "sg:tags":[
        "mfg",
        "contractor",
        "welding",
        "apparatus",
        "trade"
    ],
    "wof:name":"Dennis Corso Co Inc",
    "wof:placetype":"venue"
},
  "geometry": {"coordinates":[-81.36241200000001,41.138082],"type":"Point"}
}