{
  "type": "Feature",
  "properties": {
    "iso:country":"US",
    "sg:address":"5783 Settlers Pl",
    "sg:city":"Dublin",
    "sg:classifiers":[
        {
            "category":"Restaurant",
            "type":"Food & Drink"
        }
    ],
    "sg:phone":"+1 614 798 9408",
    "sg:postcode":"43017",
    "sg:province":"OH",
    "sg:tags":[
        "eating"
    ],
    "wof:name":"Susan Marriot",
    "wof:placetype":"venue"
},
  "geometry": {"coordinates":[-83.118296,40.084448],"type":"Point"}
}