{
  "type": "Feature",
  "properties": {
    "iso:country":"US",
    "sg:address":"1254 Maryland Ave SW",
    "sg:city":"Canton",
    "sg:classifiers":[
        {
            "category":"Personal",
            "subcategory":"Beauty Salon",
            "type":"Services"
        }
    ],
    "sg:phone":"+1 330 453 5079",
    "sg:postcode":"44710",
    "sg:province":"OH",
    "wof:name":"Linda's Beauty Shop",
    "wof:placetype":"venue"
},
  "geometry": {"coordinates":[-81.410352,40.789261],"type":"Point"}
}