{
  "type": "Feature",
  "properties": {
    "iso:country":"US",
    "sg:address":"3870 Kemp Rd",
    "sg:city":"Dayton",
    "sg:classifiers":[
        {
            "category":"Retail",
            "subcategory":"Auto Repair",
            "type":"Services"
        }
    ],
    "sg:phone":"+1 937 426 8209",
    "sg:postcode":"45431",
    "sg:province":"OH",
    "sg:tags":[
        "repairing",
        "automobile"
    ],
    "wof:name":"Beavercreek Auto Svc",
    "wof:placetype":"venue"
},
  "geometry": {"coordinates":[-84.074765,39.756575],"type":"Point"}
}