{
  "type": "Feature",
  "properties": {
    "addr:full": "3870 Kemp Rd Dayton OH 45431",
    "addr:housenumber": "3870",
    "addr:postcode": "45431",
    "addr:street": "Kemp Rd",
    "iso:country": "US",
    "sg:address": "3870 Kemp Rd",
    "sg:city": "Dayton",
    "sg:classifiers": [
      {
        "category": "Retail",
        "subcategory": "Auto Repair",
        "type": "Services"
      }
    ],
    "sg:phone": "+1 937 426 8209",
    "sg:postcode": "45431",
    "sg:province": "OH",
    "sg:tags": [
      "repairing",
      "automobile"
    ],
    "wof:name": "Beavercreek Auto Svc",
    "wof:placetype": "venue"
  },
  "geometry": {"coordinates":[-84.074765,39.756575],"type":"Point"}
}
