{
  "type": "Feature",
  "properties": {
    "addr:full":"4231 Co Hwy 35 De Graff OH 43318",
    "addr:housenumber":"4231",
    "addr:postcode":"43318",
    "addr:street":"Co Hwy 35 De",
    "iso:country":"US",
    "sg:address":"4231 Co Hwy 35",
    "sg:city":"De Graff",
    "sg:classifiers":[
        {
            "category":"Farming",
            "subcategory":"Farm",
            "type":"Manufacturing & Wholesale Goods"
        }
    ],
    "sg:phone":"+1 937 585 5711",
    "sg:postcode":"43318",
    "sg:province":"OH",
    "sg:tags":[
        "crop",
        "general"
    ],
    "wof:name":"Robert Detrick",
    "wof:placetype":"venue"
},
  "geometry": {"coordinates":[-83.97426400000001,40.395272],"type":"Point"}
}