{
  "type": "Feature",
  "properties": {
    "iso:country":"US",
    "sg:address":"8820 Echo Dr",
    "sg:city":"Mentor",
    "sg:classifiers":[
        {
            "category":"Social Services",
            "subcategory":"Child Care",
            "type":"Services"
        }
    ],
    "sg:phone":"+1 440 255 6011",
    "sg:postcode":"44060",
    "sg:province":"OH",
    "wof:name":"Kids Land",
    "wof:placetype":"venue"
},
  "geometry": {"coordinates":[-81.322344,41.680452],"type":"Point"}
}