{
  "type": "Feature",
  "properties": {
    "iso:country":"US",
    "sg:address":"907 Loveland Madeira Rd",
    "sg:city":"Loveland",
    "sg:phone":"+1 513 583 0671",
    "sg:postcode":"45140",
    "sg:province":"OH",
    "sg:tags":[
        "gas"
    ],
    "wof:name":"Loveland Rent-A Tool Rental",
    "wof:placetype":"venue"
},
  "geometry": {"coordinates":[-84.27588299999999,39.258356],"type":"Point"}
}