{
  "type": "Feature",
  "properties": {
    "iso:country":"US",
    "sg:address":"11959 Tramway Dr",
    "sg:city":"Cincinnati",
    "sg:classifiers":[
        {
            "category":"Manufacturing",
            "subcategory":"Tools & Machinery",
            "type":"Manufacturing & Wholesale Goods"
        }
    ],
    "sg:phone":"+1 513 563 8211",
    "sg:postcode":"45241",
    "sg:province":"OH",
    "sg:tags":[
        "machine",
        "mfg",
        "accessory"
    ],
    "wof:name":"Re-Machine",
    "wof:placetype":"venue"
},
  "geometry": {"coordinates":[-84.405632,39.290714],"type":"Point"}
}