{
  "type": "Feature",
  "properties": {
    "addr:full": "535 W Fair Ave Lancaster OH 43130",
    "addr:housenumber": "535",
    "addr:postcode": "43130",
    "addr:street": "W Fair Ave",
    "iso:country": "US",
    "sg:address": "535 W Fair Ave",
    "sg:city": "Lancaster",
    "sg:classifiers": [
      {
        "category": "Building \u0026 Trades",
        "subcategory": "Plumbing",
        "type": "Services"
      }
    ],
    "sg:phone": "+1 740 654 2958",
    "sg:postcode": "43130",
    "sg:province": "OH",
    "sg:tags": [
      "conditioning",
      "air",
      "system",
      "contractor"
    ],
    "wof:name": "Garretson's Heating \u0026 Cooling",
    "wof:placetype": "venue"
  },
  "geometry": {"coordinates":[-82.608425,39.724198],"type":"Point"}
}
