{
  "type": "Feature",
  "properties": {
    "addr:full": "4120 Oxford Gettysburg Rd Eaton OH 45320",
    "addr:housenumber": "4120",
    "addr:postcode": "45320",
    "addr:street": "Oxford Gettysburg Rd",
    "iso:country": "US",
    "sg:address": "4120 Oxford Gettysburg Rd",
    "sg:city": "Eaton",
    "sg:classifiers": [
      {
        "category": "Building \u0026 Trades",
        "subcategory": "Landscaping Services",
        "type": "Services"
      }
    ],
    "sg:phone": "+1 937 456 3933",
    "sg:postcode": "45320",
    "sg:province": "OH",
    "sg:tags": [
      "landscape",
      "contractor"
    ],
    "wof:name": "Rick Foust Landscape",
    "wof:placetype": "venue"
  },
  "geometry": {"coordinates":[-84.722885,39.799004],"type":"Point"}
}
