{
  "type": "Feature",
  "properties": {
    "addr:full": "20660 Hammersmith Rd Defiance OH 43512",
    "addr:housenumber": "20660",
    "addr:postcode": "43512",
    "addr:street": "Hammersmith Rd",
    "iso:country": "US",
    "sg:address": "20660 Hammersmith Rd",
    "sg:city": "Defiance",
    "sg:classifiers": [
      {
        "category": "Professional",
        "type": "Services"
      }
    ],
    "sg:phone": "+1 419 393 2247",
    "sg:postcode": "43512",
    "sg:province": "OH",
    "wof:name": "J D De Spain",
    "wof:placetype": "venue"
  },
  "geometry": {"coordinates":[-84.42517,41.238376],"type":"Point"}
}
