{
  "type": "Feature",
  "properties": {
    "addr:full":"170 Muffin Ln Cuyahoga Falls OH 44223",
    "addr:housenumber":"170",
    "addr:postcode":"44223",
    "addr:street":"Muffin Ln",
    "iso:country":"US",
    "sg:address":"170 Muffin Ln",
    "sg:city":"Cuyahoga Falls",
    "sg:classifiers":[
        {
            "category":"Manufacturing",
            "subcategory":"Food",
            "type":"Manufacturing & Wholesale Goods"
        }
    ],
    "sg:phone":"+1 330 929 0000",
    "sg:postcode":"44223",
    "sg:province":"OH",
    "sg:tags":[
        "frozen",
        "preparation",
        "bakery",
        "mfg"
    ],
    "wof:name":"Main Street Cambritt Cookies",
    "wof:placetype":"venue"
},
  "geometry": {"coordinates":[-81.51561700000001,41.165441],"type":"Point"}
}