{
  "type": "Feature",
  "properties": {
    "addr:full": "1830 Freeman Ave Cincinnati OH 45214",
    "addr:housenumber": "1830",
    "addr:postcode": "45214",
    "addr:street": "Freeman Ave",
    "iso:country": "US",
    "sg:address": "1830 Freeman Ave",
    "sg:city": "Cincinnati",
    "sg:classifiers": [
      {
        "category": "Building \u0026 Trades",
        "subcategory": "Construction",
        "type": "Services"
      }
    ],
    "sg:phone": "+1 513 621 6640",
    "sg:postcode": "45214",
    "sg:province": "OH",
    "sg:tags": [
      "repairing",
      "remodeling",
      "contractor"
    ],
    "wof:name": "Jackson's Electric \u0026 Rmldng",
    "wof:placetype": "venue"
  },
  "geometry": {"coordinates":[-84.531277,39.117348],"type":"Point"}
}
