{
  "type": "Feature",
  "properties": {
    "addr:full": "2300 Commercial Ave Mingo Junction OH 43938",
    "addr:housenumber": "2300",
    "addr:postcode": "43938",
    "addr:street": "Commercial Ave",
    "iso:country": "US",
    "sg:address": "2300 Commercial Ave",
    "sg:city": "Mingo Junction",
    "sg:classifiers": [
      {
        "category": "Railroad",
        "type": "Transportation"
      }
    ],
    "sg:phone": "+1 740 535 0573",
    "sg:postcode": "43938",
    "sg:province": "OH",
    "wof:name": "Consolidated Rail Corp",
    "wof:placetype": "venue"
  },
  "geometry": {"coordinates":[-80.617616,40.304117],"type":"Point"}
}
