{
  "type": "Feature",
  "properties": {
    "iso:country":"US",
    "sg:address":"214 12th St NE",
    "sg:city":"Canton",
    "sg:classifiers":[
        {
            "category":"Bars & Pubs",
            "type":"Food & Drink"
        }
    ],
    "sg:phone":"+1 330 452 3077",
    "sg:postcode":"44704",
    "sg:province":"OH",
    "wof:name":"Mac Roc Inc",
    "wof:placetype":"venue"
},
  "geometry": {"coordinates":[-81.369758,40.809015],"type":"Point"}
}