{
  "type": "Feature",
  "properties": {
    "addr:full": "214 12th St NE Canton OH 44704",
    "addr:housenumber": "214",
    "addr:postcode": "44704",
    "addr:street": "12Th St Ne",
    "iso:country": "US",
    "sg:address": "214 12th St NE",
    "sg:city": "Canton",
    "sg:classifiers": [
      {
        "category": "Bars \u0026 Pubs",
        "type": "Food \u0026 Drink"
      }
    ],
    "sg:phone": "+1 330 452 3077",
    "sg:postcode": "44704",
    "sg:province": "OH",
    "wof:name": "Mac Roc Inc",
    "wof:placetype": "venue"
  },
  "geometry": {"coordinates":[-81.369758,40.809015],"type":"Point"}
}
