{
  "type": "Feature",
  "properties": {
    "addr:full": "4009 Columbus Rd Granville OH 43023",
    "addr:housenumber": "4009",
    "addr:postcode": "43023",
    "addr:street": "Columbus Rd",
    "iso:country": "US",
    "sg:address": "4009 Columbus Rd",
    "sg:city": "Granville",
    "sg:classifiers": [
      {
        "category": "Real Estate",
        "subcategory": "Real Estate Agent",
        "type": "Services"
      }
    ],
    "sg:phone": "+1 740 587 7074",
    "sg:postcode": "43023",
    "sg:province": "OH",
    "sg:tags": [
      "management"
    ],
    "wof:name": "Protech Management Co Inc",
    "wof:placetype": "venue"
  },
  "geometry": {"coordinates":[-82.572544,40.042161],"type":"Point"}
}
