{
  "type": "Feature",
  "properties": {
    "iso:country":"US",
    "sg:address":"123 S Shoop Ave",
    "sg:city":"Wauseon",
    "sg:classifiers":[
        {
            "category":"Wholesale",
            "subcategory":"Stationery",
            "type":"Manufacturing & Wholesale Goods"
        }
    ],
    "sg:phone":"+1 419 335 4850",
    "sg:postcode":"43567",
    "sg:province":"OH",
    "sg:tags":[
        "packaging",
        "material"
    ],
    "sg:website":"www.nofp.com",
    "wof:name":"Northwestern Ohio Foam Pkging",
    "wof:placetype":"venue"
},
  "geometry": {"coordinates":[-84.13426699999999,41.54758],"type":"Point"}
}