{
  "type": "Feature",
  "properties": {
    "addr:full": "123 S Shoop Ave Wauseon OH 43567",
    "addr:housenumber": "123",
    "addr:postcode": "43567",
    "addr:street": "S Shoop Ave",
    "iso:country": "US",
    "sg:address": "123 S Shoop Ave",
    "sg:city": "Wauseon",
    "sg:classifiers": [
      {
        "category": "Wholesale",
        "subcategory": "Stationery",
        "type": "Manufacturing \u0026 Wholesale Goods"
      }
    ],
    "sg:phone": "+1 419 335 4850",
    "sg:postcode": "43567",
    "sg:province": "OH",
    "sg:tags": [
      "packaging",
      "material"
    ],
    "sg:website": "www.nofp.com",
    "wof:name": "Northwestern Ohio Foam Pkging",
    "wof:placetype": "venue"
  },
  "geometry": {"coordinates":[-84.134267,41.54758],"type":"Point"}
}
