{
  "type": "Feature",
  "properties": {
    "addr:full":"1130 Pine Valley Ln Toledo OH 43615",
    "addr:housenumber":"1130",
    "addr:postcode":"43615",
    "addr:street":"Pine Valley Ln",
    "iso:country":"US",
    "sg:address":"1130 Pine Valley Ln",
    "sg:city":"Toledo",
    "sg:classifiers":[
        {
            "category":"Real Estate",
            "subcategory":"Real Estate Operator",
            "type":"Services"
        }
    ],
    "sg:phone":"+1 419 535 5525",
    "sg:postcode":"43615",
    "sg:province":"OH",
    "sg:tags":[
        "building",
        "apartment"
    ],
    "wof:name":"Country Club Apartments",
    "wof:placetype":"venue"
},
  "geometry": {"coordinates":[-83.654195,41.649909],"type":"Point"}
}