{
  "type": "Feature",
  "properties": {
    "addr:full": "1681 Alton Rd Galloway OH 43119",
    "addr:housenumber": "1681",
    "addr:postcode": "43119",
    "addr:street": "Alton Rd",
    "iso:country": "US",
    "sg:address": "1681 Alton Rd",
    "sg:city": "Galloway",
    "sg:classifiers": [
      {
        "category": "Wholesale",
        "subcategory": "Machinery \u0026 Supplies",
        "type": "Manufacturing \u0026 Wholesale Goods"
      }
    ],
    "sg:phone": "+1 614 262 0652",
    "sg:postcode": "43119",
    "sg:province": "OH",
    "sg:tags": [
      "sprinkler"
    ],
    "wof:name": "Sprinkler Systems Svc",
    "wof:placetype": "venue"
  },
  "geometry": {"coordinates":[-83.177918,39.90675],"type":"Point"}
}
