{
  "type": "Feature",
  "properties": {
    "iso:country":"US",
    "sg:address":"1681 Alton Rd",
    "sg:city":"Galloway",
    "sg:classifiers":[
        {
            "category":"Wholesale",
            "subcategory":"Machinery & Supplies",
            "type":"Manufacturing & Wholesale Goods"
        }
    ],
    "sg:phone":"+1 614 262 0652",
    "sg:postcode":"43119",
    "sg:province":"OH",
    "sg:tags":[
        "sprinkler"
    ],
    "wof:name":"Sprinkler Systems Svc",
    "wof:placetype":"venue"
},
  "geometry": {"coordinates":[-83.17791800000001,39.90675],"type":"Point"}
}