{
  "type": "Feature",
  "properties": {
    "addr:full": "2012 Mahoning Rd NE Canton OH 44705",
    "addr:housenumber": "2012",
    "addr:postcode": "44705",
    "addr:street": "Mahoning Rd Ne",
    "iso:country": "US",
    "sg:address": "2012 Mahoning Rd NE",
    "sg:city": "Canton",
    "sg:classifiers": [
      {
        "category": "Autos \u0026 Motor Vehicles",
        "subcategory": "Automobile Sales",
        "type": "Retail Goods"
      }
    ],
    "sg:phone": "+1 330 456 3330",
    "sg:postcode": "44705",
    "sg:province": "OH",
    "sg:tags": [
      "car",
      "dealer"
    ],
    "wof:name": "Kerry's Motor World Inc",
    "wof:placetype": "venue"
  },
  "geometry": {"coordinates":[-81.34867,40.809502],"type":"Point"}
}
