{
  "type": "Feature",
  "properties": {
    "addr:full":"9870 Basil Rd NW Baltimore OH 43105",
    "addr:housenumber":"9870",
    "addr:postcode":"43105",
    "addr:street":"Basil Rd Nw",
    "iso:country":"US",
    "sg:address":"9870 Basil Rd NW",
    "sg:city":"Baltimore",
    "sg:classifiers":[
        {
            "category":"Building & Trades",
            "subcategory":"Construction",
            "type":"Services"
        }
    ],
    "sg:phone":"+1 740 862 3737",
    "sg:postcode":"43105",
    "sg:province":"OH",
    "sg:tags":[
        "hanging",
        "contractor"
    ],
    "wof:name":"Wright Painting & Cleaning Svc",
    "wof:placetype":"venue"
},
  "geometry": {"coordinates":[-82.617007,39.863733],"type":"Point"}
}