{
  "type": "Feature",
  "properties": {
    "addr:full":"325 Lake Ave Elyria OH 44035",
    "addr:housenumber":"325",
    "addr:postcode":"44035",
    "addr:street":"Lake Ave",
    "iso:country":"US",
    "sg:address":"325 Lake Ave",
    "sg:city":"Elyria",
    "sg:classifiers":[
        {
            "category":"Manufacturing",
            "subcategory":"Printing",
            "type":"Manufacturing & Wholesale Goods"
        }
    ],
    "sg:phone":"+1 440 323 4145",
    "sg:postcode":"44035",
    "sg:province":"OH",
    "sg:tags":[
        "printer"
    ],
    "wof:name":"Elyria Print & Copy Ctr Inc",
    "wof:placetype":"venue"
},
  "geometry": {"coordinates":[-82.116496,41.374056],"type":"Point"}
}