{
  "type": "Feature",
  "properties": {
    "addr:full":"3199 Morley Rd Cleveland OH 44122",
    "addr:housenumber":"3199",
    "addr:postcode":"44122",
    "addr:street":"Morley Rd",
    "iso:country":"US",
    "sg:address":"3199 Morley Rd",
    "sg:city":"Cleveland",
    "sg:classifiers":[
        {
            "category":"Building & Trades",
            "subcategory":"Construction",
            "type":"Services"
        }
    ],
    "sg:phone":"+1 216 991 1160",
    "sg:postcode":"44122",
    "sg:province":"OH",
    "sg:tags":[
        "painter"
    ],
    "wof:name":"Cleveland Robinson Jr Painting",
    "wof:placetype":"venue"
},
  "geometry": {"coordinates":[-81.53777100000001,41.473819],"type":"Point"}
}