{
  "type": "Feature",
  "properties": {
    "iso:country":"US",
    "sg:address":"5331 Commerce Pkwy W",
    "sg:city":"Cleveland",
    "sg:classifiers":[
        {
            "category":"Wholesale",
            "subcategory":"Construction Materials",
            "type":"Manufacturing & Wholesale Goods"
        },
        {
            "category":"Manufacturing",
            "subcategory":"Building Materials",
            "type":"Manufacturing & Wholesale Goods"
        }
    ],
    "sg:phone":"+1 216 433 4244",
    "sg:postcode":"44130",
    "sg:province":"OH",
    "wof:name":"Bee Gee Building Supply WHOL",
    "wof:placetype":"venue"
},
  "geometry": {"coordinates":[-81.76103999999999,41.417397],"type":"Point"}
}