{
  "type": "Feature",
  "properties": {
    "iso:country":"US",
    "sg:address":"1404 Jackson Ave SW",
    "sg:city":"Massillon",
    "sg:classifiers":[
        {
            "category":"Building & Trades",
            "subcategory":"Construction",
            "type":"Services"
        }
    ],
    "sg:phone":"+1 330 833 9667",
    "sg:postcode":"44646",
    "sg:province":"OH",
    "sg:tags":[
        "house"
    ],
    "wof:name":"R D Gibbons Home Improvement",
    "wof:placetype":"venue"
},
  "geometry": {"coordinates":[-81.485573,40.78057],"type":"Point"}
}