{
  "type": "Feature",
  "properties": {
    "addr:full": "1404 Jackson Ave SW Massillon OH 44646",
    "addr:housenumber": "1404",
    "addr:postcode": "44646",
    "addr:street": "Jackson Ave Sw",
    "iso:country": "US",
    "sg:address": "1404 Jackson Ave SW",
    "sg:city": "Massillon",
    "sg:classifiers": [
      {
        "category": "Building \u0026 Trades",
        "subcategory": "Construction",
        "type": "Services"
      }
    ],
    "sg:phone": "+1 330 833 9667",
    "sg:postcode": "44646",
    "sg:province": "OH",
    "sg:tags": [
      "house"
    ],
    "wof:name": "R D Gibbons Home Improvement",
    "wof:placetype": "venue"
  },
  "geometry": {"coordinates":[-81.485573,40.78057],"type":"Point"}
}
