{
  "type": "Feature",
  "properties": {
    "addr:full": "10401 Sawmill Rd Powell OH 43065",
    "addr:housenumber": "10401",
    "addr:postcode": "43065",
    "addr:street": "Sawmill Rd",
    "iso:country": "US",
    "sg:address": "10401 Sawmill Rd",
    "sg:city": "Powell",
    "sg:classifiers": [
      {
        "category": "Health Services",
        "subcategory": "Doctor",
        "type": "Services"
      }
    ],
    "sg:phone": "+1 614 791 1211",
    "sg:postcode": "43065",
    "sg:province": "OH",
    "sg:tags": [
      "osteopathic"
    ],
    "wof:name": "William Mitchell Do",
    "wof:placetype": "venue"
  },
  "geometry": {"coordinates":[-83.088894,40.147285],"type":"Point"}
}
