{
  "type": "Feature",
  "properties": {
    "addr:full":"4781 Dixie Hwy Fairfield OH 45014",
    "addr:housenumber":"4781",
    "addr:postcode":"45014",
    "addr:street":"Dixie Hwy",
    "iso:country":"US",
    "sg:address":"4781 Dixie Hwy",
    "sg:city":"Fairfield",
    "sg:classifiers":[
        {
            "category":"Shopping",
            "subcategory":"Pharmacy",
            "type":"Retail Goods"
        }
    ],
    "sg:phone":"+1 513 829 8050",
    "sg:postcode":"45014",
    "sg:province":"OH",
    "sg:tags":[
        "drug",
        "store"
    ],
    "wof:name":"Cvs",
    "wof:placetype":"venue"
},
  "geometry": {"coordinates":[-84.54251600000001,39.350523],"type":"Point"}
}