{
  "type": "Feature",
  "properties": {
    "iso:country":"US",
    "sg:address":"7247 Twp Rd 664",
    "sg:city":"Dundee",
    "sg:classifiers":[
        {
            "category":"Mining & Drilling",
            "type":"Manufacturing & Wholesale Goods"
        }
    ],
    "sg:phone":"+1 330 359 5843",
    "sg:postcode":"44624",
    "sg:province":"OH",
    "sg:tags":[
        "field"
    ],
    "wof:name":"Ray Miller Welding Inc",
    "wof:placetype":"venue"
},
  "geometry": {"coordinates":[-81.69796599999999,40.604602],"type":"Point"}
}