{
  "type": "Feature",
  "properties": {
    "addr:full": "7247 Twp Rd 664 Dundee OH 44624",
    "addr:housenumber": "7247;664",
    "addr:postcode": "44624",
    "addr:street": "Twp Rd",
    "iso:country": "US",
    "sg:address": "7247 Twp Rd 664",
    "sg:city": "Dundee",
    "sg:classifiers": [
      {
        "category": "Mining \u0026 Drilling",
        "type": "Manufacturing \u0026 Wholesale Goods"
      }
    ],
    "sg:phone": "+1 330 359 5843",
    "sg:postcode": "44624",
    "sg:province": "OH",
    "sg:tags": [
      "field"
    ],
    "wof:name": "Ray Miller Welding Inc",
    "wof:placetype": "venue"
  },
  "geometry": {"coordinates":[-81.697966,40.604602],"type":"Point"}
}
