{
  "type": "Feature",
  "properties": {
    "addr:full": "13505 Carnation Ave NW Hartville OH 44632",
    "addr:housenumber": "13505",
    "addr:postcode": "hartville;44632",
    "addr:street": "Carnation Ave Nw",
    "iso:country": "US",
    "sg:address": "13505 Carnation Ave NW",
    "sg:city": "Hartville",
    "sg:classifiers": [
      {
        "category": "Manufacturing",
        "subcategory": "Glass \u0026 Minerals",
        "type": "Manufacturing \u0026 Wholesale Goods"
      }
    ],
    "sg:phone": "+1 330 877 4442",
    "sg:postcode": "44632",
    "sg:province": "OH",
    "sg:tags": [
      "hydraulic",
      "cement",
      "mfg"
    ],
    "wof:name": "C and M Construction",
    "wof:placetype": "venue"
  },
  "geometry": {"coordinates":[-81.361504,40.981188],"type":"Point"}
}
