{
  "type": "Feature",
  "properties": {
    "addr:full": "700 Edenroc Dr Xenia OH 45385",
    "addr:housenumber": "700",
    "addr:postcode": "45385",
    "addr:street": "Edenroc Dr",
    "iso:country": "US",
    "sg:address": "700 Edenroc Dr",
    "sg:city": "Xenia",
    "sg:classifiers": [
      {
        "category": "Building \u0026 Trades",
        "subcategory": "Construction",
        "type": "Services"
      }
    ],
    "sg:phone": "+1 937 372 2983",
    "sg:postcode": "45385",
    "sg:province": "OH",
    "sg:tags": [
      "fence",
      "contractor"
    ],
    "wof:name": "Falvey Custom Fencing \u0026 Dckng",
    "wof:placetype": "venue"
  },
  "geometry": {"coordinates":[-83.918979,39.696537],"type":"Point"}
}
