{
  "type": "Feature",
  "properties": {
    "iso:country":"US",
    "sg:address":"700 Edenroc Dr",
    "sg:city":"Xenia",
    "sg:classifiers":[
        {
            "category":"Building & Trades",
            "subcategory":"Construction",
            "type":"Services"
        }
    ],
    "sg:phone":"+1 937 372 2983",
    "sg:postcode":"45385",
    "sg:province":"OH",
    "sg:tags":[
        "fence",
        "contractor"
    ],
    "wof:name":"Falvey Custom Fencing & Dckng",
    "wof:placetype":"venue"
},
  "geometry": {"coordinates":[-83.91897899999999,39.696537],"type":"Point"}
}