{
  "type": "Feature",
  "properties": {
    "addr:full":"453 W McConkey St Shreve OH 44676",
    "addr:housenumber":"453",
    "addr:postcode":"44676",
    "addr:street":"W Mcconkey St",
    "iso:country":"US",
    "sg:address":"453 W McConkey St",
    "sg:city":"Shreve",
    "sg:classifiers":[
        {
            "category":"Manufacturing",
            "subcategory":"Pottery",
            "type":"Manufacturing & Wholesale Goods"
        }
    ],
    "sg:phone":"+1 330 567 2145",
    "sg:postcode":"44676",
    "sg:province":"OH",
    "sg:tags":[
        "product",
        "ceramic"
    ],
    "sg:website":"www.cercollc.com",
    "wof:name":"Cerco LLC",
    "wof:placetype":"venue"
},
  "geometry": {"coordinates":[-82.02847300000001,40.681645],"type":"Point"}
}