{
  "type": "Feature",
  "properties": {
    "iso:country":"US",
    "sg:address":"530 Portage Lakes Dr",
    "sg:city":"Akron",
    "sg:classifiers":[
        {
            "category":"Food & Beverages",
            "subcategory":"Specialty",
            "type":"Retail Goods"
        }
    ],
    "sg:phone":"+1 330 633 8440",
    "sg:postcode":"44319",
    "sg:province":"OH",
    "sg:tags":[
        "health",
        "diet"
    ],
    "wof:name":"Nexagen USA",
    "wof:placetype":"venue"
},
  "geometry": {"coordinates":[-81.536985,40.996437],"type":"Point"}
}