{
  "type": "Feature",
  "properties": {
    "addr:full": "5038 Will Dr Akron OH 44319",
    "addr:housenumber": "5038",
    "addr:postcode": "44319",
    "addr:street": "Will Dr",
    "iso:country": "US",
    "sg:address": "5038 Will Dr",
    "sg:city": "Akron",
    "sg:classifiers": [
      {
        "category": "Organizations",
        "subcategory": "Religious Organization",
        "type": "Services"
      }
    ],
    "sg:phone": "+1 330 882 4194",
    "sg:postcode": "44319",
    "sg:province": "OH",
    "sg:tags": [
      "clergy"
    ],
    "wof:name": "Zvonimir Kotorcevic",
    "wof:placetype": "venue"
  },
  "geometry": {"coordinates":[-81.535454,40.953699],"type":"Point"}
}
