{
  "type": "Feature",
  "properties": {
    "iso:country":"US",
    "sg:address":"3052 US Rte 20",
    "sg:city":"North Kingsville",
    "sg:classifiers":[
        {
            "category":"Mining & Drilling",
            "type":"Manufacturing & Wholesale Goods"
        }
    ],
    "sg:phone":"+1 440 224 1992",
    "sg:postcode":"44081",
    "sg:province":"OH",
    "sg:tags":[
        "limestone"
    ],
    "wof:name":"Simak Trucking Inc",
    "wof:placetype":"venue"
},
  "geometry": {"coordinates":[-81.17264,41.770423],"type":"Point"}
}