{
  "type": "Feature",
  "properties": {
    "addr:full": "64774 Siverly Creek Rd Mc Arthur OH 45651",
    "addr:housenumber": "64774",
    "addr:postcode": "45651",
    "addr:street": "Siverly Creek Rd",
    "iso:country": "US",
    "sg:address": "64774 Siverly Creek Rd",
    "sg:city": "Mc Arthur",
    "sg:classifiers": [
      {
        "category": "Food \u0026 Beverages",
        "subcategory": "Groceries \u0026 Convenience Stores",
        "type": "Retail Goods"
      }
    ],
    "sg:phone": "+1 740 596 5649",
    "sg:postcode": "45651",
    "sg:province": "OH",
    "wof:name": "Eldon Reedy",
    "wof:placetype": "venue"
  },
  "geometry": {"coordinates":[-82.466113,39.329154],"type":"Point"}
}
