{
  "type": "Feature",
  "properties": {
    "addr:full":"3700 Ridge Mill Dr Hilliard OH 43026",
    "addr:housenumber":"3700",
    "addr:postcode":"43026",
    "addr:street":"Ridge Mill Dr",
    "iso:country":"US",
    "sg:address":"3700 Ridge Mill Dr",
    "sg:city":"Hilliard",
    "sg:classifiers":[
        {
            "category":"Social Services",
            "subcategory":"Child Care",
            "type":"Services"
        }
    ],
    "sg:phone":"+1 614 771 8909",
    "sg:postcode":"43026",
    "sg:province":"OH",
    "sg:website":"www.knowledgelearning.com",
    "wof:name":"Childrens World",
    "wof:placetype":"venue"
},
  "geometry": {"coordinates":[-83.11197799999999,40.029544],"type":"Point"}
}