{
  "type": "Feature",
  "properties": {
    "addr:full": "11206 Euclid Ave Cleveland OH 44106",
    "addr:housenumber": "11206",
    "addr:postcode": "44106",
    "addr:street": "Euclid Ave",
    "iso:country": "US",
    "sg:address": "11206 Euclid Ave",
    "sg:city": "Cleveland",
    "sg:classifiers": [
      {
        "category": "Health Services",
        "subcategory": "Health Practitioner",
        "type": "Services"
      }
    ],
    "sg:phone": "+1 216 231 8787",
    "sg:postcode": "44106",
    "sg:province": "OH",
    "sg:tags": [
      "pathologist",
      "speech"
    ],
    "sg:website": "www.chsc.org",
    "wof:name": "Cleveland Hearing \u0026 Speech Ctr",
    "wof:placetype": "venue"
  },
  "geometry": {"coordinates":[-81.606197,41.508084],"type":"Point"}
}
