{
  "type": "Feature",
  "properties": {
    "iso:country":"US",
    "sg:address":"9651 Colerain Ave",
    "sg:city":"Cincinnati",
    "sg:classifiers":[
        {
            "category":"Personal",
            "subcategory":"Beauty Salon",
            "type":"Services"
        }
    ],
    "sg:phone":"+1 513 385 1151",
    "sg:postcode":"45251",
    "sg:province":"OH",
    "sg:tags":[
        "manicurist",
        "manicuring"
    ],
    "wof:name":"Cincinnati Nails Inc",
    "wof:placetype":"venue"
},
  "geometry": {"coordinates":[-84.59598699999999,39.246066],"type":"Point"}
}