{
  "type": "Feature",
  "properties": {
    "addr:full":"860 NW Washington Blvd Hamilton OH 45013",
    "addr:housenumber":"860",
    "addr:postcode":"45013",
    "addr:street":"Nw Washington Blvd",
    "iso:country":"US",
    "sg:address":"860 NW Washington Blvd",
    "sg:city":"Hamilton",
    "sg:classifiers":[
        {
            "category":"Health Services",
            "subcategory":"Doctor",
            "type":"Services"
        }
    ],
    "sg:phone":"+1 513 896 6940",
    "sg:postcode":"45013",
    "sg:province":"OH",
    "sg:tags":[
        "physician",
        "surgeon"
    ],
    "sg:website":"www.oncologyhematologycare.com",
    "wof:name":"Oncology Hematology Care Inc",
    "wof:placetype":"venue"
},
  "geometry": {"coordinates":[-84.59089400000001,39.426666],"type":"Point"}
}