{
  "type": "Feature",
  "properties": {
    "addr:full": "2804 Archwood Ave Cleveland OH 44109",
    "addr:housenumber": "2804",
    "addr:postcode": "44109",
    "addr:street": "Archwood Ave",
    "iso:country": "US",
    "sg:address": "2804 Archwood Ave",
    "sg:city": "Cleveland",
    "sg:classifiers": [
      {
        "category": "Professional",
        "type": "Services"
      }
    ],
    "sg:phone": "+1 216 351 9351",
    "sg:postcode": "44109",
    "sg:province": "OH",
    "wof:name": "Bargainer Co LLC",
    "wof:placetype": "venue"
  },
  "geometry": {"coordinates":[-81.70294,41.452757],"type":"Point"}
}
