{
  "type": "Feature",
  "properties": {
    "addr:full": "652 Main St Fl 6 Cincinnati OH 45202",
    "addr:housenumber": "652;6",
    "addr:postcode": "45202",
    "addr:street": "Main St",
    "iso:country": "US",
    "sg:address": "652 Main St Fl 6",
    "sg:city": "Cincinnati",
    "sg:classifiers": [
      {
        "category": "Professional",
        "subcategory": "Computer Services",
        "type": "Services"
      },
      {
        "category": "Wholesale",
        "subcategory": "Computers",
        "type": "Manufacturing \u0026 Wholesale Goods"
      }
    ],
    "sg:phone": "+1 513 651 4108",
    "sg:postcode": "45202",
    "sg:province": "OH",
    "sg:tags": [
      "equipment",
      "software"
    ],
    "sg:website": "http://www.image-edit.com",
    "wof:name": "Digitalcustom",
    "wof:placetype": "venue"
  },
  "geometry": {"coordinates":[-84.510141,39.103085],"type":"Point"}
}
