{
  "type": "Feature",
  "properties": {
    "addr:full": "3482 Higby Rd Chillicothe OH 45601",
    "addr:housenumber": "3482",
    "addr:postcode": "45601",
    "addr:street": "Higby Rd",
    "iso:country": "US",
    "sg:address": "3482 Higby Rd",
    "sg:city": "Chillicothe",
    "sg:classifiers": [
      {
        "category": "Farming",
        "subcategory": "Farm",
        "type": "Manufacturing \u0026 Wholesale Goods"
      }
    ],
    "sg:phone": "+1 740 884 4989",
    "sg:postcode": "45601",
    "sg:province": "OH",
    "sg:tags": [
      "corn",
      "wheat",
      "soybean",
      "crop",
      "general"
    ],
    "wof:name": "David S Carroll",
    "wof:placetype": "venue"
  },
  "geometry": {"coordinates":[-82.866668,39.191868],"type":"Point"}
}
