{
  "type": "Feature",
  "properties": {
    "addr:full": "90 N Nelson Rd Columbus OH 43219",
    "addr:housenumber": "90",
    "addr:postcode": "43219",
    "addr:street": "N Nelson Rd",
    "iso:country": "US",
    "sg:address": "90 N Nelson Rd",
    "sg:city": "Columbus",
    "sg:classifiers": [
      {
        "category": "Professional",
        "subcategory": "Lawyer \u0026 Legal Services",
        "type": "Services"
      }
    ],
    "sg:phone": "+1 614 252 2026",
    "sg:postcode": "43219",
    "sg:province": "OH",
    "sg:tags": [
      "attorney"
    ],
    "wof:name": "Stanlee Culbreath \u0026 Assoc",
    "wof:placetype": "venue"
  },
  "geometry": {"coordinates":[-82.949867,39.96995],"type":"Point"}
}
