{
  "type": "Feature",
  "properties": {
    "addr:full": "6740 Perimeter Loop Rd Dublin OH 43017",
    "addr:housenumber": "6740",
    "addr:postcode": "43017",
    "addr:street": "Perimeter Loop Rd",
    "iso:country": "US",
    "sg:address": "6740 Perimeter Loop Rd",
    "sg:city": "Dublin",
    "sg:classifiers": [
      {
        "category": "Retail",
        "subcategory": "Laundry \u0026 Dry Cleaning",
        "type": "Services"
      }
    ],
    "sg:phone": "+1 614 760 0260",
    "sg:postcode": "43017",
    "sg:province": "OH",
    "sg:tags": [
      "cleaners"
    ],
    "wof:name": "Dry Cleaning Ctr",
    "wof:placetype": "venue"
  },
  "geometry": {"coordinates":[-83.157968,40.102741],"type":"Point"}
}
