{
  "type": "Feature",
  "properties": {
    "addr:full": "1717 S High St Columbus OH 43207",
    "addr:housenumber": "1717",
    "addr:postcode": "43207",
    "addr:street": "S High St",
    "iso:country": "US",
    "sg:address": "1717 S High St",
    "sg:city": "Columbus",
    "sg:classifiers": [
      {
        "category": "Retail",
        "subcategory": "Auto Repair",
        "type": "Services"
      }
    ],
    "sg:phone": "+1 614 443 6547",
    "sg:postcode": "43207",
    "sg:province": "OH",
    "sg:tags": [
      "body",
      "automobile",
      "painting"
    ],
    "wof:name": "Columbus Auto Repair Svc",
    "wof:placetype": "venue"
  },
  "geometry": {"coordinates":[-82.995678,39.926525],"type":"Point"}
}
