{
  "type": "Feature",
  "properties": {
    "addr:full": "11750 Shaker Blvd Cleveland OH 44120",
    "addr:housenumber": "11750",
    "addr:postcode": "44120",
    "addr:street": "Shaker Blvd",
    "iso:country": "US",
    "sg:address": "11750 Shaker Blvd",
    "sg:city": "Cleveland",
    "sg:classifiers": [
      {
        "category": "Freight",
        "type": "Transportation"
      }
    ],
    "sg:phone": "+1 216 751 9550",
    "sg:postcode": "44120",
    "sg:province": "OH",
    "sg:tags": [
      "hauling",
      "trucking"
    ],
    "wof:name": "Thompson Ground Development",
    "wof:placetype": "venue"
  },
  "geometry": {"coordinates":[-81.599343,41.484144],"type":"Point"}
}
