{
  "type": "Feature",
  "properties": {
    "addr:full": "614 Superior Ave E Cleveland OH 44114",
    "addr:housenumber": "614",
    "addr:postcode": "44114",
    "addr:street": "Superior Ave E",
    "iso:country": "US",
    "sg:address": "614 Superior Ave E",
    "sg:city": "Cleveland",
    "sg:classifiers": [
      {
        "category": "Professional",
        "subcategory": "Lawyer \u0026 Legal Services",
        "type": "Services"
      }
    ],
    "sg:phone": "+1 216 263 6203",
    "sg:postcode": "44114",
    "sg:province": "OH",
    "sg:tags": [
      "attorney"
    ],
    "wof:name": "Rauser \u0026 Associates",
    "wof:placetype": "venue"
  },
  "geometry": {"coordinates":[-81.688602,41.502161],"type":"Point"}
}
