{
  "type": "Feature",
  "properties": {
    "iso:country":"US",
    "sg:address":"1221 E 99th St",
    "sg:city":"Cleveland",
    "sg:classifiers":[
        {
            "category":"Organizations",
            "subcategory":"Religious Organization",
            "type":"Services"
        }
    ],
    "sg:phone":"+1 216 791 8394",
    "sg:postcode":"44108",
    "sg:province":"OH",
    "sg:tags":[
        "church"
    ],
    "wof:name":"Mount Olivet Church Of God",
    "wof:placetype":"venue"
},
  "geometry": {"coordinates":[-81.620914,41.523041],"type":"Point"}
}