{
  "type": "Feature",
  "properties": {
    "addr:full": "203 W Main St New Paris OH 45347",
    "addr:housenumber": "203",
    "addr:postcode": "45347",
    "addr:street": "W Main St",
    "iso:country": "US",
    "sg:address": "203 W Main St",
    "sg:city": "New Paris",
    "sg:classifiers": [
      {
        "category": "Freight",
        "type": "Transportation"
      }
    ],
    "sg:phone": "+1 937 437 5317",
    "sg:postcode": "45347",
    "sg:province": "OH",
    "sg:tags": [
      "trucking"
    ],
    "wof:name": "D L Anderson Trucking Inc",
    "wof:placetype": "venue"
  },
  "geometry": {"coordinates":[-84.795953,39.857331],"type":"Point"}
}
