{
  "type": "Feature",
  "properties": {
    "iso:country":"US",
    "sg:address":"32320 Redwood Blvd",
    "sg:city":"Avon Lake",
    "sg:classifiers":[
        {
            "category":"Marine",
            "type":"Transportation"
        }
    ],
    "sg:phone":"+1 440 933 4488",
    "sg:postcode":"44012",
    "sg:province":"OH",
    "sg:tags":[
        "water",
        "surveyor",
        "transport"
    ],
    "wof:name":"Universal Marine Surveying Inc",
    "wof:placetype":"venue"
},
  "geometry": {"coordinates":[-82.00036,41.502203],"type":"Point"}
}