{
  "type": "Feature",
  "properties": {
    "addr:full": "1505 Meriline Ave Dayton OH 45410",
    "addr:housenumber": "1505",
    "addr:postcode": "45410",
    "addr:street": "Meriline Ave",
    "iso:country": "US",
    "sg:address": "1505 Meriline Ave",
    "sg:city": "Dayton",
    "sg:classifiers": [
      {
        "category": "Retail",
        "subcategory": "Laundry \u0026 Dry Cleaning",
        "type": "Services"
      }
    ],
    "sg:phone": "+1 937 781 9005",
    "sg:postcode": "45410",
    "sg:province": "OH",
    "sg:tags": [
      "cleaners",
      "rug",
      "carpet"
    ],
    "wof:name": "Fiber Dry",
    "wof:placetype": "venue"
  },
  "geometry": {"coordinates":[-84.134913,39.745498],"type":"Point"}
}
