{
  "type": "Feature",
  "properties": {
    "addr:full":"2110 State Rd Ashtabula OH 44004",
    "addr:housenumber":"2110",
    "addr:postcode":"44004",
    "addr:street":"State Rd",
    "iso:country":"US",
    "sg:address":"2110 State Rd",
    "sg:city":"Ashtabula",
    "sg:classifiers":[
        {
            "category":"Building & Trades",
            "subcategory":"Construction",
            "type":"Services"
        }
    ],
    "sg:phone":"+1 440 998 1445",
    "sg:postcode":"44004",
    "sg:province":"OH",
    "sg:tags":[
        "concrete",
        "contractor"
    ],
    "sg:website":"www.velottareadymixconcrete.com",
    "wof:name":"M F Velotta & Son Inc",
    "wof:placetype":"venue"
},
  "geometry": {"coordinates":[-80.772401,41.889123],"type":"Point"}
}