{
  "type": "Feature",
  "properties": {
    "iso:country":"US",
    "sg:address":"5295 Springboro Pike",
    "sg:city":"Dayton",
    "sg:classifiers":[
        {
            "category":"Autos & Motor Vehicles",
            "subcategory":"Fuel & Gas Station",
            "type":"Retail Goods"
        }
    ],
    "sg:phone":"+1 937 439 1934",
    "sg:postcode":"45449",
    "sg:province":"OH",
    "sg:tags":[
        "automotive",
        "station"
    ],
    "wof:name":"Denver & Sons Marathon",
    "wof:placetype":"venue"
},
  "geometry": {"coordinates":[-84.221081,39.682874],"type":"Point"}
}