{
  "type": "Feature",
  "properties": {
    "iso:country":"US",
    "sg:address":"8373 Squirrelridge Dr",
    "sg:city":"Cincinnati",
    "sg:classifiers":[
        {
            "category":"Professional",
            "subcategory":"Research",
            "type":"Services"
        }
    ],
    "sg:phone":"+1 513 242 5290",
    "sg:postcode":"45243",
    "sg:province":"OH",
    "sg:tags":[
        "nonphysical",
        "consulting",
        "management",
        "commercial",
        "s"
    ],
    "wof:name":"Chemical Venture",
    "wof:placetype":"venue"
},
  "geometry": {"coordinates":[-84.36297999999999,39.207713],"type":"Point"}
}