{
  "type": "Feature",
  "properties": {
    "addr:full": "6740 State Rd Cleveland OH 44134",
    "addr:housenumber": "6740",
    "addr:postcode": "44134",
    "addr:street": "State Rd",
    "iso:country": "US",
    "sg:address": "6740 State Rd",
    "sg:city": "Cleveland",
    "sg:phone": "+1 440 845 2444",
    "sg:postcode": "44134",
    "sg:province": "OH",
    "sg:website": "http://www.paduafranciscan.com",
    "wof:name": "Padua Franciscan High School",
    "wof:placetype": "venue"
  },
  "geometry": {"coordinates":[-81.71215,41.381084],"type":"Point"}
}
