{
  "type": "Feature",
  "properties": {
    "iso:country":"US",
    "sg:address":"6740 State Rd",
    "sg:city":"Cleveland",
    "sg:phone":"+1 440 845 2444",
    "sg:postcode":"44134",
    "sg:province":"OH",
    "sg:website":"http://www.paduafranciscan.com",
    "wof:name":"Padua Franciscan High School",
    "wof:placetype":"venue"
},
  "geometry": {"coordinates":[-81.71214999999999,41.381084],"type":"Point"}
}