{
  "type": "Feature",
  "properties": {
    "addr:full": "108 E Wapakoneta St Waynesfield OH 45896",
    "addr:housenumber": "108",
    "addr:postcode": "45896",
    "addr:street": "E Wapakoneta St",
    "iso:country": "US",
    "sg:address": "108 E Wapakoneta St",
    "sg:city": "Waynesfield",
    "sg:classifiers": [
      {
        "category": "Education",
        "subcategory": "Library",
        "type": "Public Place"
      }
    ],
    "sg:phone": "+1 419 568 5851",
    "sg:postcode": "45896",
    "sg:province": "OH",
    "wof:name": "Waynesfield Public Library",
    "wof:placetype": "venue"
  },
  "geometry": {"coordinates":[-83.975137,40.600516],"type":"Point"}
}
