{
  "type": "Feature",
  "properties": {
    "addr:full": "1819 N Curry Rd Wilmington OH 45177",
    "addr:housenumber": "1819",
    "addr:postcode": "45177",
    "addr:street": "N Curry Rd",
    "iso:country": "US",
    "sg:address": "1819 N Curry Rd",
    "sg:city": "Wilmington",
    "sg:classifiers": [
      {
        "category": "Professional",
        "type": "Services"
      }
    ],
    "sg:phone": "+1 937 382 2271",
    "sg:postcode": "45177",
    "sg:province": "OH",
    "wof:name": "Clinton Aviation Organiza",
    "wof:placetype": "venue"
  },
  "geometry": {"coordinates":[-83.85962,39.505239],"type":"Point"}
}
