{
  "type": "Feature",
  "properties": {
    "iso:country":"US",
    "sg:address":"31481 Beech Grove Rd",
    "sg:city":"Londonderry",
    "sg:classifiers":[
        {
            "category":"Freight",
            "type":"Transportation"
        }
    ],
    "sg:phone":"+1 740 887 4100",
    "sg:postcode":"45647",
    "sg:province":"OH",
    "sg:tags":[
        "operator",
        "trucking"
    ],
    "wof:name":"Rick Puckett Trucking",
    "wof:placetype":"venue"
},
  "geometry": {"coordinates":[-82.661901,39.282784],"type":"Point"}
}