{
  "type": "Feature",
  "properties": {
    "iso:country":"US",
    "sg:address":"515 Hopkins St",
    "sg:city":"Defiance",
    "sg:classifiers":[
        {
            "category":"Wholesale",
            "subcategory":"Stationery",
            "type":"Manufacturing & Wholesale Goods"
        }
    ],
    "sg:phone":"+1 419 782 3826",
    "sg:postcode":"43512",
    "sg:province":"OH",
    "sg:tags":[
        "cards",
        "greeting"
    ],
    "wof:name":"Scott Card Co",
    "wof:placetype":"venue"
},
  "geometry": {"coordinates":[-84.35209500000001,41.281158],"type":"Point"}
}