{
  "type": "Feature",
  "properties": {
    "addr:full": "515 Hopkins St Defiance OH 43512",
    "addr:housenumber": "515",
    "addr:postcode": "43512",
    "addr:street": "Hopkins St",
    "iso:country": "US",
    "sg:address": "515 Hopkins St",
    "sg:city": "Defiance",
    "sg:classifiers": [
      {
        "category": "Wholesale",
        "subcategory": "Stationery",
        "type": "Manufacturing \u0026 Wholesale Goods"
      }
    ],
    "sg:phone": "+1 419 782 3826",
    "sg:postcode": "43512",
    "sg:province": "OH",
    "sg:tags": [
      "cards",
      "greeting"
    ],
    "wof:name": "Scott Card Co",
    "wof:placetype": "venue"
  },
  "geometry": {"coordinates":[-84.352095,41.281158],"type":"Point"}
}
