{
  "type": "Feature",
  "properties": {
    "iso:country":"US",
    "sg:address":"318 Main St",
    "sg:city":"Byesville",
    "sg:classifiers":[
        {
            "category":"Insurance",
            "subcategory":"Insurance Agent",
            "type":"Services"
        }
    ],
    "sg:phone":"+1 740 685 7437",
    "sg:postcode":"43723",
    "sg:province":"OH",
    "wof:name":"Shepard Insurance",
    "wof:placetype":"venue"
},
  "geometry": {"coordinates":[-81.54289,39.97032],"type":"Point"}
}