{
  "type": "Feature",
  "properties": {
    "iso:country":"US",
    "sg:address":"5960 Meese Rd",
    "sg:city":"Louisville",
    "sg:classifiers":[
        {
            "category":"Building & Trades",
            "subcategory":"Construction",
            "type":"Services"
        }
    ],
    "sg:phone":"+1 330 875 4798",
    "sg:postcode":"44641",
    "sg:province":"OH",
    "sg:tags":[
        "heavy"
    ],
    "wof:name":"Construction of Benchmark",
    "wof:placetype":"venue"
},
  "geometry": {"coordinates":[-81.224608,40.852163],"type":"Point"}
}