{
  "type": "Feature",
  "properties": {
    "addr:full": "145 Rice Ave Ney OH 43549",
    "addr:housenumber": "145",
    "addr:postcode": "43549",
    "addr:street": "Rice Ave",
    "iso:country": "US",
    "sg:address": "145 Rice Ave",
    "sg:city": "Ney",
    "sg:classifiers": [
      {
        "category": "Organizations",
        "subcategory": "Religious Organization",
        "type": "Services"
      }
    ],
    "sg:phone": "+1 419 658 8212",
    "sg:postcode": "43549",
    "sg:province": "OH",
    "sg:tags": [
      "church"
    ],
    "wof:name": "Ney United Methodist",
    "wof:placetype": "venue"
  },
  "geometry": {"coordinates":[-84.522454,41.382611],"type":"Point"}
}
