{
  "type": "Feature",
  "properties": {
    "addr:full":"11260 Colerain Ave Cincinnati OH 45252",
    "addr:housenumber":"11260",
    "addr:postcode":"45252",
    "addr:street":"Colerain Ave",
    "iso:country":"US",
    "sg:address":"11260 Colerain Ave",
    "sg:city":"Cincinnati",
    "sg:classifiers":[
        {
            "category":"Retail",
            "subcategory":"Animal Services",
            "type":"Services"
        }
    ],
    "sg:phone":"+1 513 385 5074",
    "sg:postcode":"45252",
    "sg:province":"OH",
    "wof:name":"Jan Rich Kennels",
    "wof:placetype":"venue"
},
  "geometry": {"coordinates":[-84.61583299999999,39.288445],"type":"Point"}
}