{
  "type": "Feature",
  "properties": {
    "addr:full": "5533 Far Hills Ave Dayton OH 45429",
    "addr:housenumber": "5533",
    "addr:postcode": "45429",
    "addr:street": "Far Hills Ave",
    "iso:country": "US",
    "sg:address": "5533 Far Hills Ave",
    "sg:city": "Dayton",
    "sg:classifiers": [
      {
        "category": "Education",
        "subcategory": "Dance Studio",
        "type": "Public Place"
      }
    ],
    "sg:phone": "+1 937 439 9935",
    "sg:postcode": "45429",
    "sg:province": "OH",
    "sg:tags": [
      "instruction",
      "dancing"
    ],
    "wof:name": "Howard-Reboulet School-Dance",
    "wof:placetype": "venue"
  },
  "geometry": {"coordinates":[-84.162258,39.667822],"type":"Point"}
}
