{
  "type": "Feature",
  "properties": {
    "iso:country":"US",
    "sg:address":"3600 Pennington Rd",
    "sg:city":"Cleveland",
    "sg:classifiers":[
        {
            "category":"Organizations",
            "subcategory":"Religious Organization",
            "type":"Services"
        }
    ],
    "sg:phone":"+1 216 561 3817",
    "sg:postcode":"44120",
    "sg:province":"OH",
    "sg:tags":[
        "clergy"
    ],
    "wof:name":"John C Whitley",
    "wof:placetype":"venue"
},
  "geometry": {"coordinates":[-81.57104,41.462879],"type":"Point"}
}