{
  "type": "Feature",
  "properties": {
    "addr:full": "321 Canterbury Ct Sharpsville OH 16150",
    "addr:housenumber": "321",
    "addr:postcode": "16150",
    "addr:street": "Canterbury Ct",
    "iso:country": "US",
    "sg:address": "321 Canterbury Ct",
    "sg:city": "Sharpsville",
    "sg:classifiers": [
      {
        "category": "Professional",
        "type": "Services"
      }
    ],
    "sg:phone": "+1 724 962 5588",
    "sg:postcode": "16150",
    "sg:province": "OH",
    "sg:tags": [
      "establishment"
    ],
    "wof:name": "J L Campbell",
    "wof:placetype": "venue"
  },
  "geometry": {"coordinates":[-80.474256,41.256609],"type":"Point"}
}
