{
  "type": "Feature",
  "properties": {
    "addr:full":"1500 E 5th St Delphos OH 45833",
    "addr:housenumber":"1500",
    "addr:postcode":"45833",
    "addr:street":"E 5Th St",
    "iso:country":"US",
    "sg:address":"1500 E 5th St",
    "sg:city":"Delphos",
    "sg:classifiers":[
        {
            "category":"Home & Garden",
            "subcategory":"Building Materials",
            "type":"Retail Goods"
        }
    ],
    "sg:phone":"+1 419 695 8105",
    "sg:postcode":"45833",
    "sg:province":"OH",
    "sg:tags":[
        "equipment",
        "electric",
        "supply"
    ],
    "wof:name":"H E Power Supply",
    "wof:placetype":"venue"
},
  "geometry": {"coordinates":[-84.319997,40.846761],"type":"Point"}
}