{
  "type": "Feature",
  "properties": {
    "addr:full": "920 S Lickert-Harder Rd Oak Harbor OH 43449",
    "addr:housenumber": "920",
    "addr:postcode": "43449",
    "addr:street": "S Lickert-Harder Rd",
    "iso:country": "US",
    "sg:address": "920 S Lickert-Harder Rd",
    "sg:city": "Oak Harbor",
    "sg:classifiers": [
      {
        "category": "Building \u0026 Trades",
        "subcategory": "Construction",
        "type": "Services"
      }
    ],
    "sg:phone": "+1 419 898 0767",
    "sg:postcode": "43449",
    "sg:province": "OH",
    "sg:tags": [
      "general",
      "contractor"
    ],
    "wof:name": "Lee Harder Builders Inc",
    "wof:placetype": "venue"
  },
  "geometry": {"coordinates":[-83.202692,41.501969],"type":"Point"}
}
