{
  "type": "Feature",
  "properties": {
    "addr:full": "15320 Twp Rd K Napoleon OH 43545",
    "addr:postcode": "15320;43545",
    "addr:street": "Rd",
    "iso:country": "US",
    "sg:address": "15320 Twp Rd K",
    "sg:city": "Napoleon",
    "sg:classifiers": [
      {
        "category": "Farming",
        "subcategory": "Farm",
        "type": "Manufacturing \u0026 Wholesale Goods"
      }
    ],
    "sg:phone": "+1 419 762 5738",
    "sg:postcode": "43545",
    "sg:province": "OH",
    "sg:tags": [
      "crop",
      "general"
    ],
    "wof:name": "James A Durham",
    "wof:placetype": "venue"
  },
  "geometry": {"coordinates":[-84.158901,41.311534],"type":"Point"}
}
