{
  "type": "Feature",
  "properties": {
    "iso:country":"US",
    "sg:address":"315 Deer Creek Dr",
    "sg:city":"Struthers",
    "sg:classifiers":[
        {
            "category":"Shopping",
            "subcategory":"Catalog Store",
            "type":"Retail Goods"
        }
    ],
    "sg:phone":"+1 330 750 9968",
    "sg:postcode":"44471",
    "sg:province":"OH",
    "sg:tags":[
        "internet"
    ],
    "wof:name":"Affordable Rehab Products Inc",
    "wof:placetype":"venue"
},
  "geometry": {"coordinates":[-80.587114,41.035612],"type":"Point"}
}