{
  "type": "Feature",
  "properties": {
    "addr:full":"1064 Vacationland Dr Cincinnati OH 45231",
    "addr:housenumber":"1064",
    "addr:postcode":"45231",
    "addr:street":"Vacationland Dr",
    "iso:country":"US",
    "sg:address":"1064 Vacationland Dr",
    "sg:city":"Cincinnati",
    "sg:classifiers":[
        {
            "category":"Building & Trades",
            "subcategory":"Construction",
            "type":"Services"
        }
    ],
    "sg:phone":"+1 513 616 1010",
    "sg:postcode":"45231",
    "sg:province":"OH",
    "sg:tags":[
        "altering",
        "roofing",
        "contractor",
        "remodeling",
        "consultant"
    ],
    "wof:name":"Speedco Construction",
    "wof:placetype":"venue"
},
  "geometry": {"coordinates":[-84.523753,39.224279],"type":"Point"}
}