{
  "type": "Feature",
  "properties": {
    "addr:full": "11338 Princeton Pike Cincinnati OH 45246",
    "addr:housenumber": "11338",
    "addr:postcode": "45246",
    "addr:street": "Princeton Pike",
    "iso:country": "US",
    "sg:address": "11338 Princeton Pike",
    "sg:city": "Cincinnati",
    "sg:classifiers": [
      {
        "category": "Professional",
        "type": "Services"
      },
      {
        "category": "Professional",
        "subcategory": "Business Services",
        "type": "Services"
      },
      {
        "category": "Professional",
        "subcategory": "Printing \u0026 Photocopies",
        "type": "Services"
      },
      {
        "category": "Shopping",
        "subcategory": "Stationery \u0026 Office Supplies",
        "type": "Retail Goods"
      },
      {
        "category": "Manufacturing",
        "subcategory": "Printing",
        "type": "Manufacturing \u0026 Wholesale Goods"
      },
      {
        "category": "Manufacturing",
        "subcategory": "Signs",
        "type": "Manufacturing \u0026 Wholesale Goods"
      }
    ],
    "sg:phone": "+1 513 771 1017",
    "sg:postcode": "45246",
    "sg:province": "OH",
    "sg:tags": [
      "machine",
      "document",
      "duplicating",
      "shipping",
      "materials-shipping",
      "packaging",
      "packing",
      "imaging",
      "copying",
      "digital",
      "copy"
    ],
    "sg:website": "http://www.fedex.com/Dropoff/start?FY11-FXO-YELLOWPAGES",
    "wof:name": "FedEx Office Print \u0026 Ship Center",
    "wof:placetype": "venue"
  },
  "geometry": {"coordinates":[-84.467392,39.283193],"type":"Point"}
}
