{
  "type": "Feature",
  "properties": {
    "addr:full":"1776 W Breese Rd Lima OH 45806",
    "addr:housenumber":"1776",
    "addr:postcode":"45806",
    "addr:street":"W Breese Rd",
    "iso:country":"US",
    "sg:address":"1776 W Breese Rd",
    "sg:city":"Lima",
    "sg:classifiers":[
        {
            "category":"Shopping",
            "subcategory":"Gifts & Souvenirs",
            "type":"Retail Goods"
        }
    ],
    "sg:phone":"+1 419 228 0903",
    "sg:postcode":"45806",
    "sg:province":"OH",
    "sg:tags":[
        "shop"
    ],
    "wof:name":"Gathering Place",
    "wof:placetype":"venue"
},
  "geometry": {"coordinates":[-84.135949,40.686691],"type":"Point"}
}