{
  "type": "Feature",
  "properties": {
    "addr:full":"1822 Stahlwood Ave Toledo OH 43613",
    "addr:housenumber":"1822",
    "addr:postcode":"43613",
    "addr:street":"Stahlwood Ave",
    "iso:country":"US",
    "sg:address":"1822 Stahlwood Ave",
    "sg:city":"Toledo",
    "sg:classifiers":[
        {
            "category":"Organizations",
            "subcategory":"Community Association",
            "type":"Services"
        }
    ],
    "sg:phone":"+1 419 474 3770",
    "sg:postcode":"43613",
    "sg:province":"OH",
    "wof:name":"Mystic Ord of Veiled Profits",
    "wof:placetype":"venue"
},
  "geometry": {"coordinates":[-83.586995,41.680316],"type":"Point"}
}