{
  "type": "Feature",
  "properties": {
    "addr:full":"201 Walnut St Fremont OH 43420",
    "addr:housenumber":"201",
    "addr:postcode":"43420",
    "addr:street":"Walnut St",
    "iso:country":"US",
    "sg:address":"201 Walnut St",
    "sg:city":"Fremont",
    "sg:classifiers":[
        {
            "category":"Building & Trades",
            "subcategory":"Construction",
            "type":"Services"
        }
    ],
    "sg:phone":"+1 419 334 3059",
    "sg:postcode":"43420",
    "sg:province":"OH",
    "sg:tags":[
        "paving",
        "asphalt",
        "contractor"
    ],
    "wof:name":"Superior Seal Coating & Asphlt",
    "wof:placetype":"venue"
},
  "geometry": {"coordinates":[-83.10123299999999,41.35583],"type":"Point"}
}