{
  "type": "Feature",
  "properties": {
    "addr:full":"3373 W 117th St Cleveland OH 44111",
    "addr:housenumber":"3373",
    "addr:postcode":"44111",
    "addr:street":"W 117Th St",
    "iso:country":"US",
    "sg:address":"3373 W 117th St",
    "sg:city":"Cleveland",
    "sg:classifiers":[
        {
            "category":"Professional",
            "subcategory":"Computer Services",
            "type":"Services"
        }
    ],
    "sg:phone":"+1 216 287 5906",
    "sg:postcode":"44111",
    "sg:province":"OH",
    "sg:tags":[
        "repair"
    ],
    "wof:name":"Network Cable Co",
    "wof:placetype":"venue"
},
  "geometry": {"coordinates":[-81.768852,41.461417],"type":"Point"}
}