{
  "type": "Feature",
  "properties": {
    "addr:full": "2155 E 30th St Cleveland OH 44115",
    "addr:housenumber": "2155",
    "addr:postcode": "44115",
    "addr:street": "E 30Th St",
    "iso:country": "US",
    "sg:address": "2155 E 30th St",
    "sg:city": "Cleveland",
    "sg:classifiers": [
      {
        "category": "Restaurant",
        "type": "Food \u0026 Drink"
      }
    ],
    "sg:phone": "+1 216 432 2535",
    "sg:postcode": "44115",
    "sg:province": "OH",
    "sg:tags": [
      "out"
    ],
    "wof:name": "A-Dawgs",
    "wof:placetype": "venue"
  },
  "geometry": {"coordinates":[-81.666536,41.498602],"type":"Point"}
}
