{
  "type": "Feature",
  "properties": {
    "iso:country":"US",
    "sg:address":"2155 E 30th St",
    "sg:city":"Cleveland",
    "sg:classifiers":[
        {
            "category":"Restaurant",
            "type":"Food & Drink"
        }
    ],
    "sg:phone":"+1 216 432 2535",
    "sg:postcode":"44115",
    "sg:province":"OH",
    "sg:tags":[
        "out"
    ],
    "wof:name":"A-Dawgs",
    "wof:placetype":"venue"
},
  "geometry": {"coordinates":[-81.66653599999999,41.498602],"type":"Point"}
}