{
  "type": "Feature",
  "properties": {
    "addr:full": "306 E North St Waverly OH 45690",
    "addr:housenumber": "306",
    "addr:postcode": "45690",
    "addr:street": "E North St",
    "iso:country": "US",
    "sg:address": "306 E North St",
    "sg:city": "Waverly",
    "sg:classifiers": [
      {
        "category": "Home \u0026 Garden",
        "subcategory": "Furniture",
        "type": "Retail Goods"
      }
    ],
    "sg:phone": "+1 740 947 1527",
    "sg:postcode": "45690",
    "sg:province": "OH",
    "wof:name": "Quality Home Expressions Ltd",
    "wof:placetype": "venue"
  },
  "geometry": {"coordinates":[-82.982521,39.129893],"type":"Point"}
}
