{
  "type": "Feature",
  "properties": {
    "iso:country":"US",
    "sg:address":"306 E North St",
    "sg:city":"Waverly",
    "sg:classifiers":[
        {
            "category":"Home & Garden",
            "subcategory":"Furniture",
            "type":"Retail Goods"
        }
    ],
    "sg:phone":"+1 740 947 1527",
    "sg:postcode":"45690",
    "sg:province":"OH",
    "wof:name":"Quality Home Expressions Ltd",
    "wof:placetype":"venue"
},
  "geometry": {"coordinates":[-82.98252100000001,39.129893],"type":"Point"}
}