{
  "type": "Feature",
  "properties": {
    "addr:full": "190 E Tompkins St Columbus OH 43202",
    "addr:housenumber": "190",
    "addr:postcode": "43202",
    "addr:street": "E Tompkins St",
    "iso:country": "US",
    "sg:address": "190 E Tompkins St",
    "sg:city": "Columbus",
    "sg:classifiers": [
      {
        "category": "Real Estate",
        "subcategory": "Real Estate Agent",
        "type": "Services"
      }
    ],
    "sg:phone": "+1 614 205 1484",
    "sg:postcode": "43202",
    "sg:province": "OH",
    "sg:tags": [
      "management"
    ],
    "wof:name": "Wade Real Estate Svc",
    "wof:placetype": "venue"
  },
  "geometry": {"coordinates":[-83.005083,40.01437],"type":"Point"}
}
