{
  "type": "Feature",
  "properties": {
    "addr:full": "13402 State Rte 15 Montpelier OH 43543",
    "addr:housenumber": "13402",
    "addr:postcode": "43543",
    "addr:street": "State Rte 15",
    "iso:country": "US",
    "sg:address": "13402 State Rte 15",
    "sg:city": "Montpelier",
    "sg:classifiers": [
      {
        "category": "Travel",
        "subcategory": "Hotels \u0026 Motels",
        "type": "Entertainment"
      }
    ],
    "sg:phone": "+1 419 485 3432",
    "sg:postcode": "43543",
    "sg:province": "OH",
    "wof:name": "Rainbow Motel",
    "wof:placetype": "venue"
  },
  "geometry": {"coordinates":[-84.555621,41.607177],"type":"Point"}
}
