{
  "type": "Feature",
  "properties": {
    "iso:country":"US",
    "sg:address":"13402 State Rte 15",
    "sg:city":"Montpelier",
    "sg:classifiers":[
        {
            "category":"Travel",
            "subcategory":"Hotels & Motels",
            "type":"Entertainment"
        }
    ],
    "sg:phone":"+1 419 485 3432",
    "sg:postcode":"43543",
    "sg:province":"OH",
    "wof:name":"Rainbow Motel",
    "wof:placetype":"venue"
},
  "geometry": {"coordinates":[-84.555621,41.607177],"type":"Point"}
}