{
  "type": "Feature",
  "properties": {
    "addr:full":"91 Grandview Dr Hudson OH 44236",
    "addr:housenumber":"91",
    "addr:postcode":"44236",
    "addr:street":"Grandview Dr",
    "iso:country":"US",
    "sg:address":"91 Grandview Dr",
    "sg:city":"Hudson",
    "sg:classifiers":[
        {
            "category":"Building & Trades",
            "subcategory":"Landscaping Services",
            "type":"Services"
        }
    ],
    "sg:phone":"+1 330 232 4141",
    "sg:postcode":"44236",
    "sg:province":"OH",
    "sg:tags":[
        "tree"
    ],
    "wof:name":"Tree Guardians Inc",
    "wof:placetype":"venue"
},
  "geometry": {"coordinates":[-81.516867,41.270429],"type":"Point"}
}