{
  "type": "Feature",
  "properties": {
    "addr:full": "825 Hart Rd Lebanon OH 45036",
    "addr:housenumber": "825",
    "addr:postcode": "45036",
    "addr:street": "Hart Rd",
    "iso:country": "US",
    "sg:address": "825 Hart Rd",
    "sg:city": "Lebanon",
    "sg:classifiers": [
      {
        "category": "Building \u0026 Trades",
        "subcategory": "Construction",
        "type": "Services"
      }
    ],
    "sg:phone": "+1 513 932 7066",
    "sg:postcode": "45036",
    "sg:province": "OH",
    "sg:tags": [
      "general",
      "contractor"
    ],
    "wof:name": "Mardismeehan Construction",
    "wof:placetype": "venue"
  },
  "geometry": {"coordinates":[-84.224124,39.447695],"type":"Point"}
}
