{
  "type": "Feature",
  "properties": {
    "addr:full":"3606 Bridge Ave Cleveland OH 44113",
    "addr:housenumber":"3606",
    "addr:postcode":"44113",
    "addr:street":"Bridge Ave",
    "iso:country":"US",
    "sg:address":"3606 Bridge Ave",
    "sg:city":"Cleveland",
    "sg:classifiers":[
        {
            "category":"Organizations",
            "subcategory":"Religious Organization",
            "type":"Services"
        }
    ],
    "sg:phone":"+1 216 961 0001",
    "sg:postcode":"44113",
    "sg:province":"OH",
    "wof:name":"Inter-Religious Task Force",
    "wof:placetype":"venue"
},
  "geometry": {"coordinates":[-81.713689,41.481874],"type":"Point"}
}