{
  "type": "Feature",
  "properties": {
    "iso:country":"US",
    "sg:address":"28870 Mickley Rd",
    "sg:city":"Danville",
    "sg:classifiers":[
        {
            "category":"Building & Trades",
            "subcategory":"Plumbing",
            "type":"Services"
        }
    ],
    "sg:phone":"+1 740 599 7142",
    "sg:postcode":"43014",
    "sg:province":"OH",
    "sg:tags":[
        "electrical",
        "contractor"
    ],
    "wof:name":"Durbin Plumbing & Heating",
    "wof:placetype":"venue"
},
  "geometry": {"coordinates":[-82.222721,40.455593],"type":"Point"}
}