{
  "type": "Feature",
  "properties": {
    "addr:full": "1514 11th St Portsmouth OH 45662",
    "addr:housenumber": "1514",
    "addr:postcode": "45662",
    "addr:street": "11Th St",
    "iso:country": "US",
    "sg:address": "1514 11th St",
    "sg:city": "Portsmouth",
    "sg:classifiers": [
      {
        "category": "Building \u0026 Trades",
        "subcategory": "Plumbing",
        "type": "Services"
      }
    ],
    "sg:phone": "+1 740 353 0240",
    "sg:postcode": "45662",
    "sg:province": "OH",
    "sg:tags": [
      "conditioning",
      "air",
      "system",
      "contractor"
    ],
    "wof:name": "Campbell Heating \u0026 Air Cond",
    "wof:placetype": "venue"
  },
  "geometry": {"coordinates":[-82.985061,38.738885],"type":"Point"}
}
