{
  "type": "Feature",
  "properties": {
    "iso:country":"US",
    "sg:address":"1514 11th St",
    "sg:city":"Portsmouth",
    "sg:classifiers":[
        {
            "category":"Building & Trades",
            "subcategory":"Plumbing",
            "type":"Services"
        }
    ],
    "sg:phone":"+1 740 353 0240",
    "sg:postcode":"45662",
    "sg:province":"OH",
    "sg:tags":[
        "conditioning",
        "air",
        "system",
        "contractor"
    ],
    "wof:name":"Campbell Heating & Air Cond",
    "wof:placetype":"venue"
},
  "geometry": {"coordinates":[-82.985061,38.738885],"type":"Point"}
}