{
  "type": "Feature",
  "properties": {
    "addr:full": "8600 Glennridge Ave NW Clinton OH 44216",
    "addr:housenumber": "8600",
    "addr:postcode": "44216",
    "addr:street": "Glennridge Ave Nw",
    "iso:country": "US",
    "sg:address": "8600 Glennridge Ave NW",
    "sg:city": "Clinton",
    "sg:classifiers": [
      {
        "category": "Professional",
        "type": "Services"
      }
    ],
    "sg:phone": "+1 330 854 5301",
    "sg:postcode": "44216",
    "sg:province": "OH",
    "wof:name": "Donlen Corp",
    "wof:placetype": "venue"
  },
  "geometry": {"coordinates":[-81.5215,40.903538],"type":"Point"}
}
