{
  "type": "Feature",
  "properties": {
    "addr:full":"3805 E 91st St Cleveland OH 44105",
    "addr:housenumber":"3805",
    "addr:postcode":"44105",
    "addr:street":"E 91St St",
    "iso:country":"US",
    "sg:address":"3805 E 91st St",
    "sg:city":"Cleveland",
    "sg:classifiers":[
        {
            "category":"Manufacturing",
            "subcategory":"Metals",
            "type":"Manufacturing & Wholesale Goods"
        }
    ],
    "sg:phone":"+1 216 883 0326",
    "sg:postcode":"44105",
    "sg:province":"OH",
    "sg:tags":[
        "painting",
        "industrial",
        "finisher",
        "parts"
    ],
    "wof:name":"Austin Finishing Co Inc",
    "wof:placetype":"venue"
},
  "geometry": {"coordinates":[-81.623366,41.454252],"type":"Point"}
}