{
  "type": "Feature",
  "properties": {
    "addr:full": "1450 Troy Rd Delaware OH 43015",
    "addr:housenumber": "1450",
    "addr:postcode": "43015",
    "addr:street": "Troy Rd",
    "iso:country": "US",
    "sg:address": "1450 Troy Rd",
    "sg:city": "Delaware",
    "sg:classifiers": [
      {
        "category": "Organizations",
        "subcategory": "Religious Organization",
        "type": "Services"
      }
    ],
    "sg:phone": "+1 740 369 1188",
    "sg:postcode": "43015",
    "sg:province": "OH",
    "sg:tags": [
      "church"
    ],
    "wof:name": "Calvary Baptist Church",
    "wof:placetype": "venue"
  },
  "geometry": {"coordinates":[-83.100168,40.329304],"type":"Point"}
}
