{
  "type": "Feature",
  "properties": {
    "iso:country":"US",
    "sg:address":"4477 Rocky River Dr",
    "sg:city":"Cleveland",
    "sg:classifiers":[
        {
            "category":"Retail",
            "subcategory":"Laundry & Dry Cleaning",
            "type":"Services"
        }
    ],
    "sg:phone":"+1 216 267 7175",
    "sg:postcode":"44135",
    "sg:province":"OH",
    "sg:tags":[
        "cleaners"
    ],
    "wof:name":"Sunshine Cleaners",
    "wof:placetype":"venue"
},
  "geometry": {"coordinates":[-81.822883,41.433361],"type":"Point"}
}