{
  "type": "Feature",
  "properties": {
    "iso:country":"US",
    "sg:address":"8229 Tyler Blvd",
    "sg:city":"Mentor",
    "sg:classifiers":[
        {
            "category":"Manufacturing",
            "subcategory":"Retail Goods",
            "type":"Manufacturing & Wholesale Goods"
        }
    ],
    "sg:phone":"+1 440 205 6629",
    "sg:postcode":"44060",
    "sg:province":"OH",
    "sg:tags":[
        "product",
        "mfg"
    ],
    "wof:name":"Dean S Repar",
    "wof:placetype":"venue"
},
  "geometry": {"coordinates":[-81.34634699999999,41.682925],"type":"Point"}
}