{
  "type": "Feature",
  "properties": {
    "addr:full":"10577 Durham Pl Powell OH 43065",
    "addr:housenumber":"10577",
    "addr:postcode":"43065",
    "addr:street":"Durham Pl",
    "iso:country":"US",
    "sg:address":"10577 Durham Pl",
    "sg:city":"Powell",
    "sg:classifiers":[
        {
            "category":"Real Estate",
            "subcategory":"Real Estate Operator",
            "type":"Services"
        }
    ],
    "sg:phone":"+1 614 793 0706",
    "sg:postcode":"43065",
    "sg:province":"OH",
    "sg:tags":[
        "building",
        "nonresidential"
    ],
    "wof:name":"Sand & Sea Properties LLC",
    "wof:placetype":"venue"
},
  "geometry": {"coordinates":[-83.111729,40.145264],"type":"Point"}
}