{
  "type": "Feature",
  "properties": {
    "iso:country":"US",
    "sg:address":"21 E Main St",
    "sg:city":"Columbus",
    "sg:classifiers":[
        {
            "category":"Professional",
            "type":"Services"
        }
    ],
    "sg:phone":"+1 614 340 9698",
    "sg:postcode":"43215",
    "sg:province":"OH",
    "sg:tags":[
        "establishment"
    ],
    "wof:name":"C Apa Columbus Assoc For",
    "wof:placetype":"venue"
},
  "geometry": {"coordinates":[-82.998992,39.956104],"type":"Point"}
}