{
  "type": "Feature",
  "properties": {
    "addr:full": "435 N Elizabeth St Lima OH 45801",
    "addr:housenumber": "435",
    "addr:postcode": "45801",
    "addr:street": "N Elizabeth St",
    "iso:country": "US",
    "sg:address": "435 N Elizabeth St",
    "sg:city": "Lima",
    "sg:classifiers": [
      {
        "category": "Wholesale",
        "subcategory": "Non-durable Goods",
        "type": "Manufacturing \u0026 Wholesale Goods"
      }
    ],
    "sg:phone": "+1 419 224 5848",
    "sg:postcode": "45801",
    "sg:province": "OH",
    "sg:tags": [
      "specialty",
      "novelty",
      "t",
      "gift",
      "advertising"
    ],
    "wof:name": "Ohio Foam Novelties Inc",
    "wof:placetype": "venue"
  },
  "geometry": {"coordinates":[-84.106847,40.746319],"type":"Point"}
}
