{
  "type": "Feature",
  "properties": {
    "addr:full": "105 E Central Ave Springboro OH 45066",
    "addr:housenumber": "105",
    "addr:postcode": "45066",
    "addr:street": "E Central Ave",
    "iso:country": "US",
    "sg:address": "105 E Central Ave",
    "sg:city": "Springboro",
    "sg:classifiers": [
      {
        "category": "Real Estate",
        "subcategory": "Real Estate Agent",
        "type": "Services"
      }
    ],
    "sg:phone": "+1 937 748 2466",
    "sg:postcode": "45066",
    "sg:province": "OH",
    "wof:name": "Ohio Homestead Inc Realtors",
    "wof:placetype": "venue"
  },
  "geometry": {"coordinates":[-84.232403,39.556343],"type":"Point"}
}
