{
  "type": "Feature",
  "properties": {
    "addr:full": "125 N Main Ave Sidney OH 45365",
    "addr:housenumber": "125",
    "addr:postcode": "45365",
    "addr:street": "N Main Ave",
    "iso:country": "US",
    "sg:address": "125 N Main Ave",
    "sg:city": "Sidney",
    "sg:classifiers": [
      {
        "category": "Building \u0026 Trades",
        "subcategory": "Pest Control",
        "type": "Services"
      }
    ],
    "sg:phone": "+1 937 492 6004",
    "sg:postcode": "45365",
    "sg:province": "OH",
    "wof:name": "Aggressive Pest Control",
    "wof:placetype": "venue"
  },
  "geometry": {"coordinates":[-84.155192,40.28656],"type":"Point"}
}
