{
  "type": "Feature",
  "properties": {
    "addr:full": "326 E Payne Ave Galion OH 44833",
    "addr:housenumber": "326",
    "addr:postcode": "44833",
    "addr:street": "E Payne Ave",
    "iso:country": "US",
    "sg:address": "326 E Payne Ave",
    "sg:city": "Galion",
    "sg:classifiers": [
      {
        "category": "Shopping",
        "subcategory": "Books",
        "type": "Retail Goods"
      }
    ],
    "sg:phone": "+1 419 468 2027",
    "sg:postcode": "44833",
    "sg:province": "OH",
    "wof:name": "Past Times Shop",
    "wof:placetype": "venue"
  },
  "geometry": {"coordinates":[-82.78493,40.73643],"type":"Point"}
}
