{
  "type": "Feature",
  "properties": {
    "addr:full": "218 S 2nd St Greenfield OH 45123",
    "addr:housenumber": "218",
    "addr:postcode": "45123",
    "addr:street": "S 2Nd St",
    "iso:country": "US",
    "sg:address": "218 S 2nd St",
    "sg:city": "Greenfield",
    "sg:classifiers": [
      {
        "category": "Organizations",
        "subcategory": "Religious Organization",
        "type": "Services"
      }
    ],
    "sg:phone": "+1 937 981 2785",
    "sg:postcode": "45123",
    "sg:province": "OH",
    "sg:tags": [
      "church"
    ],
    "sg:website": "www.stbenignus.org",
    "wof:name": "St Benignus Catholic Church",
    "wof:placetype": "venue"
  },
  "geometry": {"coordinates":[-83.380636,39.350721],"type":"Point"}
}
