{
  "type": "Feature",
  "properties": {
    "addr:full": "2354 Apple Ridge Dr Columbus OH 43223",
    "addr:housenumber": "2354",
    "addr:postcode": "43223",
    "addr:street": "Apple Ridge Dr",
    "iso:country": "US",
    "sg:address": "2354 Apple Ridge Dr",
    "sg:city": "Columbus",
    "sg:classifiers": [
      {
        "category": "Shopping",
        "subcategory": "Used Merchandise",
        "type": "Retail Goods"
      }
    ],
    "sg:phone": "+1 614 351 0919",
    "sg:postcode": "43223",
    "sg:province": "OH",
    "wof:name": "Final Art",
    "wof:placetype": "venue"
  },
  "geometry": {"coordinates":[-83.057514,39.93287],"type":"Point"}
}
