{
  "type": "Feature",
  "properties": {
    "addr:full":"1520 Old Henderson Rd Columbus OH 43220",
    "addr:housenumber":"1520",
    "addr:postcode":"43220",
    "addr:street":"Old Henderson Rd",
    "iso:country":"US",
    "sg:address":"1520 Old Henderson Rd",
    "sg:city":"Columbus",
    "sg:classifiers":[
        {
            "category":"Organizations",
            "subcategory":"Religious Organization",
            "type":"Services"
        }
    ],
    "sg:phone":"+1 614 457 1774",
    "sg:postcode":"43220",
    "sg:province":"OH",
    "wof:name":"Church World Svc Crop",
    "wof:placetype":"venue"
},
  "geometry": {"coordinates":[-83.061244,40.051923],"type":"Point"}
}