{
  "type": "Feature",
  "properties": {
    "iso:country":"US",
    "sg:address":"2400 Harrison Ave",
    "sg:city":"Cincinnati",
    "sg:classifiers":[
        {
            "category":"Real Estate",
            "subcategory":"Real Estate Operator",
            "type":"Services"
        }
    ],
    "sg:phone":"+1 513 481 2400",
    "sg:postcode":"45211",
    "sg:province":"OH",
    "sg:tags":[
        "building",
        "apartment"
    ],
    "wof:name":"Candlewood Apartments",
    "wof:placetype":"venue"
},
  "geometry": {"coordinates":[-84.580267,39.140312],"type":"Point"}
}