{
  "type": "Feature",
  "properties": {
    "addr:full": "357 E Turkeyfoot Lake Rd Akron OH 44319",
    "addr:housenumber": "357",
    "addr:postcode": "44319",
    "addr:street": "E Turkeyfoot Lake Rd",
    "iso:country": "US",
    "sg:address": "357 E Turkeyfoot Lake Rd",
    "sg:city": "Akron",
    "sg:classifiers": [
      {
        "category": "Bars \u0026 Pubs",
        "type": "Food \u0026 Drink"
      }
    ],
    "sg:phone": "+1 330 644 2338",
    "sg:postcode": "44319",
    "sg:province": "OH",
    "sg:tags": [
      "drinking"
    ],
    "wof:name": "Upper Deck",
    "wof:placetype": "venue"
  },
  "geometry": {"coordinates":[-81.511327,40.975462],"type":"Point"}
}
