{
  "type": "Feature",
  "properties": {
    "iso:country":"US",
    "sg:address":"357 E Turkeyfoot Lake Rd",
    "sg:city":"Akron",
    "sg:classifiers":[
        {
            "category":"Bars & Pubs",
            "type":"Food & Drink"
        }
    ],
    "sg:phone":"+1 330 644 2338",
    "sg:postcode":"44319",
    "sg:province":"OH",
    "sg:tags":[
        "drinking"
    ],
    "wof:name":"Upper Deck",
    "wof:placetype":"venue"
},
  "geometry": {"coordinates":[-81.51132699999999,40.975462],"type":"Point"}
}