{
  "type": "Feature",
  "properties": {
    "addr:full": "501 Garfield Ave Lancaster OH 43130",
    "addr:housenumber": "501",
    "addr:postcode": "43130",
    "addr:street": "Garfield Ave",
    "iso:country": "US",
    "sg:address": "501 Garfield Ave",
    "sg:city": "Lancaster",
    "sg:classifiers": [
      {
        "category": "Recreation",
        "type": "Entertainment"
      }
    ],
    "sg:phone": "+1 740 654 3958",
    "sg:postcode": "43130",
    "sg:province": "OH",
    "sg:tags": [
      "parlor",
      "billiard"
    ],
    "wof:name": "Brigg's West Side Billiard",
    "wof:placetype": "venue"
  },
  "geometry": {"coordinates":[-82.617438,39.720358],"type":"Point"}
}
