{
  "type": "Feature",
  "properties": {
    "iso:country":"US",
    "sg:address":"501 Garfield Ave",
    "sg:city":"Lancaster",
    "sg:classifiers":[
        {
            "category":"Recreation",
            "type":"Entertainment"
        }
    ],
    "sg:phone":"+1 740 654 3958",
    "sg:postcode":"43130",
    "sg:province":"OH",
    "sg:tags":[
        "parlor",
        "billiard"
    ],
    "wof:name":"Brigg's West Side Billiard",
    "wof:placetype":"venue"
},
  "geometry": {"coordinates":[-82.61743800000001,39.720358],"type":"Point"}
}