{
  "type": "Feature",
  "properties": {
    "iso:country":"US",
    "sg:address":"326 Sullivan Rd",
    "sg:city":"Fremont",
    "sg:classifiers":[
        {
            "category":"Building & Trades",
            "subcategory":"Equipment Rental",
            "type":"Services"
        }
    ],
    "sg:phone":"+1 419 355 8329",
    "sg:postcode":"43420",
    "sg:province":"OH",
    "sg:tags":[
        "camping"
    ],
    "wof:name":"UNEW Tent Rental",
    "wof:placetype":"venue"
},
  "geometry": {"coordinates":[-83.15347,41.346256],"type":"Point"}
}