{
  "type": "Feature",
  "properties": {
    "addr:full": "1350 Roosevelt Ave Martins Ferry OH 43935",
    "addr:housenumber": "1350",
    "addr:postcode": "43935",
    "addr:street": "Roosevelt Ave Martins",
    "iso:country": "US",
    "sg:address": "1350 Roosevelt Ave",
    "sg:city": "Martins Ferry",
    "sg:classifiers": [
      {
        "category": "Professional",
        "type": "Services"
      }
    ],
    "sg:phone": "+1 740 633 5667",
    "sg:postcode": "43935",
    "sg:province": "OH",
    "wof:name": "Blankenship Inc",
    "wof:placetype": "venue"
  },
  "geometry": {"coordinates":[-80.746445,40.087143],"type":"Point"}
}
