{
  "type": "Feature",
  "properties": {
    "iso:country":"US",
    "sg:address":"14 East St",
    "sg:city":"Dellroy",
    "sg:classifiers":[
        {
            "category":"Real Estate",
            "subcategory":"Real Estate Agent",
            "type":"Services"
        }
    ],
    "sg:phone":"+1 330 735 2404",
    "sg:postcode":"44620",
    "sg:province":"OH",
    "wof:name":"Gary L Hall Real Estate Svc",
    "wof:placetype":"venue"
},
  "geometry": {"coordinates":[-81.19662,40.554782],"type":"Point"}
}