{
  "type": "Feature",
  "properties": {
    "addr:full":"3370 Co Rd 6 Kitts Hill OH 45645",
    "addr:housenumber":"3370",
    "addr:postcode":"45645",
    "addr:street":"Co Rd 6 Kitts Hill",
    "iso:country":"US",
    "sg:address":"3370 Co Rd 6",
    "sg:city":"Kitts Hill",
    "sg:classifiers":[
        {
            "category":"Building & Trades",
            "subcategory":"Electrical",
            "type":"Services"
        }
    ],
    "sg:phone":"+1 740 532 4287",
    "sg:postcode":"45645",
    "sg:province":"OH",
    "sg:tags":[
        "electrical",
        "contractor"
    ],
    "wof:name":"William S Electrical Srv",
    "wof:placetype":"venue"
},
  "geometry": {"coordinates":[-82.545596,38.534588],"type":"Point"}
}