{
  "type": "Feature",
  "properties": {
    "addr:full":"407 Vine St Cincinnati OH 45202",
    "addr:housenumber":"407",
    "addr:postcode":"45202",
    "addr:street":"Vine St",
    "iso:country":"US",
    "sg:address":"407 Vine St",
    "sg:city":"Cincinnati",
    "sg:classifiers":[
        {
            "category":"Manufacturing",
            "subcategory":"Tools & Machinery",
            "type":"Manufacturing & Wholesale Goods"
        }
    ],
    "sg:phone":"+1 513 352 0240",
    "sg:postcode":"45202",
    "sg:province":"OH",
    "sg:tags":[
        "physician",
        "surgeon"
    ],
    "wof:name":"Gyne Concepts Inc",
    "wof:placetype":"venue"
},
  "geometry": {"coordinates":[-84.512826,39.100241],"type":"Point"}
}