{
  "type": "Feature",
  "properties": {
    "addr:full": "494 W Main St Conneaut OH 44030",
    "addr:housenumber": "494",
    "addr:postcode": "44030",
    "addr:street": "W Main St",
    "iso:country": "US",
    "sg:address": "494 W Main St",
    "sg:city": "Conneaut",
    "sg:classifiers": [
      {
        "category": "Manufacturing",
        "subcategory": "Leather Goods",
        "type": "Manufacturing \u0026 Wholesale Goods"
      }
    ],
    "sg:phone": "+1 440 593 5205",
    "sg:postcode": "44030",
    "sg:province": "OH",
    "sg:website": "www.conneautleather.com",
    "wof:name": "Conneaut Leather Inc",
    "wof:placetype": "venue"
  },
  "geometry": {"coordinates":[-80.611282,41.928047],"type":"Point"}
}
