{
  "type": "Feature",
  "properties": {
    "addr:full": "4 Garden Pl Cincinnati OH 45208",
    "addr:housenumber": "4",
    "addr:postcode": "45208",
    "addr:street": "Garden Pl",
    "iso:country": "US",
    "sg:address": "4 Garden Pl",
    "sg:city": "Cincinnati",
    "sg:classifiers": [
      {
        "category": "Real Estate",
        "subcategory": "Real Estate Operator",
        "type": "Services"
      }
    ],
    "sg:phone": "+1 513 351 0100",
    "sg:postcode": "45208",
    "sg:province": "OH",
    "sg:tags": [
      "building",
      "nonresidential"
    ],
    "wof:name": "Franklyn S \u0026 Roslyn Hark",
    "wof:placetype": "venue"
  },
  "geometry": {"coordinates":[-84.457712,39.138643],"type":"Point"}
}
