{
  "type": "Feature",
  "properties": {
    "addr:full": "218 S Main St Monroe OH 45050",
    "addr:housenumber": "218",
    "addr:postcode": "45050",
    "addr:street": "S Main St",
    "iso:country": "US",
    "sg:address": "218 S Main St",
    "sg:city": "Monroe",
    "sg:classifiers": [
      {
        "category": "Professional",
        "subcategory": "Accounting \u0026 Tax Preparation",
        "type": "Services"
      }
    ],
    "sg:phone": "+1 513 539 4722",
    "sg:postcode": "45050",
    "sg:province": "OH",
    "sg:tags": [
      "bookkeeping",
      "general"
    ],
    "wof:name": "Miller Bookkeeping \u0026 Tax Svc",
    "wof:placetype": "venue"
  },
  "geometry": {"coordinates":[-84.362483,39.44056],"type":"Point"}
}
