{
  "type": "Feature",
  "properties": {
    "addr:full":"6255 Shier Rings Rd Dublin OH 43016",
    "addr:housenumber":"6255",
    "addr:postcode":"43016",
    "addr:street":"Shier Rings Rd",
    "iso:country":"US",
    "sg:address":"6255 Shier Rings Rd",
    "sg:city":"Dublin",
    "sg:classifiers":[
        {
            "category":"Government",
            "subcategory":"Fire Station",
            "type":"Public Place"
        }
    ],
    "sg:phone":"+1 614 798 2204",
    "sg:postcode":"43016",
    "sg:province":"OH",
    "sg:tags":[
        "protection"
    ],
    "wof:name":"Fire Dept",
    "wof:placetype":"venue"
},
  "geometry": {"coordinates":[-83.154087,40.095789],"type":"Point"}
}