{
  "type": "Feature",
  "properties": {
    "addr:full": "1325 Glendale Milford Rd Cincinnati OH 45215",
    "addr:housenumber": "1325",
    "addr:postcode": "45215",
    "addr:street": "Glendale Milford Rd",
    "iso:country": "US",
    "sg:address": "1325 Glendale Milford Rd",
    "sg:city": "Cincinnati",
    "sg:classifiers": [
      {
        "category": "Manufacturing",
        "subcategory": "Printing",
        "type": "Manufacturing \u0026 Wholesale Goods"
      }
    ],
    "sg:phone": "+1 513 772 5400",
    "sg:postcode": "45215",
    "sg:province": "OH",
    "sg:tags": [
      "commercial",
      "lithographic"
    ],
    "wof:name": "Cincinnati Tab \u0026 Print",
    "wof:placetype": "venue"
  },
  "geometry": {"coordinates":[-84.453983,39.256553],"type":"Point"}
}
