{
  "type": "Feature",
  "properties": {
    "iso:country":"US",
    "sg:address":"4210 W Sylvania Ave",
    "sg:city":"Toledo",
    "sg:classifiers":[
        {
            "category":"Health Services",
            "subcategory":"Health Practitioner",
            "type":"Services"
        }
    ],
    "sg:phone":"+1 419 475 7799",
    "sg:postcode":"43623",
    "sg:province":"OH",
    "sg:tags":[
        "therapist",
        "physical"
    ],
    "wof:name":"Franklin Park Physical Therapy",
    "wof:placetype":"venue"
},
  "geometry": {"coordinates":[-83.639596,41.691342],"type":"Point"}
}