{
  "type": "Feature",
  "properties": {
    "addr:full":"5957 State Rd Cleveland OH 44134",
    "addr:housenumber":"5957",
    "addr:postcode":"44134",
    "addr:street":"State Rd",
    "iso:country":"US",
    "sg:address":"5957 State Rd",
    "sg:city":"Cleveland",
    "sg:classifiers":[
        {
            "category":"Personal",
            "type":"Services"
        }
    ],
    "sg:phone":"+1 440 884 1556",
    "sg:postcode":"44134",
    "sg:province":"OH",
    "sg:tags":[
        "trainer",
        "consultant",
        "program",
        "health",
        "fitness"
    ],
    "wof:name":"Anello Body Fitness",
    "wof:placetype":"venue"
},
  "geometry": {"coordinates":[-81.710414,41.40082],"type":"Point"}
}