{
  "type": "Feature",
  "properties": {
    "addr:full":"818 S Arlington St Akron OH 44306",
    "addr:housenumber":"818",
    "addr:postcode":"44306",
    "addr:street":"S Arlington St",
    "iso:country":"US",
    "sg:address":"818 S Arlington St",
    "sg:city":"Akron",
    "sg:classifiers":[
        {
            "category":"Manufacturing",
            "subcategory":"Rubber & Plastics",
            "type":"Manufacturing & Wholesale Goods"
        }
    ],
    "sg:phone":"+1 330 773 8873",
    "sg:postcode":"44306",
    "sg:province":"OH",
    "sg:tags":[
        "product",
        "dist",
        "mfg"
    ],
    "wof:name":"Renaissance Rubber & Gasket",
    "wof:placetype":"venue"
},
  "geometry": {"coordinates":[-81.49108099999999,41.049405],"type":"Point"}
}