{
  "type": "Feature",
  "properties": {
    "addr:full": "436 Salem St Brookville OH 45309",
    "addr:housenumber": "436",
    "addr:postcode": "45309",
    "addr:street": "Salem St",
    "iso:country": "US",
    "sg:address": "436 Salem St",
    "sg:city": "Brookville",
    "sg:classifiers": [
      {
        "category": "Building \u0026 Trades",
        "subcategory": "Construction",
        "type": "Services"
      }
    ],
    "sg:phone": "+1 937 248 3175",
    "sg:postcode": "45309",
    "sg:province": "OH",
    "sg:tags": [
      "concrete",
      "contractor"
    ],
    "wof:name": "Milligan's Custom Concrete",
    "wof:placetype": "venue"
  },
  "geometry": {"coordinates":[-84.413116,39.838086],"type":"Point"}
}
