{
  "type": "Feature",
  "properties": {
    "iso:country":"US",
    "sg:address":"12831 Frysinger Rd",
    "sg:city":"Rockford",
    "sg:classifiers":[
        {
            "category":"Manufacturing",
            "subcategory":"Metals",
            "type":"Manufacturing & Wholesale Goods"
        }
    ],
    "sg:phone":"+1 419 305 6073",
    "sg:postcode":"45882",
    "sg:province":"OH",
    "sg:tags":[
        "plate",
        "work",
        "fabricated",
        "mfg"
    ],
    "wof:name":"Steven P Harner",
    "wof:placetype":"venue"
},
  "geometry": {"coordinates":[-84.609705,40.725197],"type":"Point"}
}