{
  "type": "Feature",
  "properties": {
    "iso:country":"US",
    "sg:address":"10021 W Triadelphia Rd",
    "sg:city":"Crooksville",
    "sg:classifiers":[
        {
            "category":"Retail",
            "subcategory":"Repair Shop",
            "type":"Services"
        },
        {
            "category":"Building & Trades",
            "subcategory":"Construction",
            "type":"Services"
        }
    ],
    "sg:phone":"+1 740 962 2252",
    "sg:postcode":"43731",
    "sg:province":"OH",
    "sg:tags":[
        "welding"
    ],
    "wof:name":"George's Welding & Repair",
    "wof:placetype":"venue"
},
  "geometry": {"coordinates":[-82.008292,39.71006],"type":"Point"}
}