{
  "type": "Feature",
  "properties": {
    "addr:full":"2350 Vega Rd Thurman OH 45685",
    "addr:housenumber":"2350",
    "addr:postcode":"45685",
    "addr:street":"Vega Rd",
    "iso:country":"US",
    "sg:address":"2350 Vega Rd",
    "sg:city":"Thurman",
    "sg:classifiers":[
        {
            "category":"Farming",
            "subcategory":"Livestock Farm",
            "type":"Manufacturing & Wholesale Goods"
        }
    ],
    "sg:phone":"+1 740 286 2394",
    "sg:postcode":"45685",
    "sg:province":"OH",
    "sg:tags":[
        "beef",
        "feedlot",
        "cattle"
    ],
    "wof:name":"Thomas Jones",
    "wof:placetype":"venue"
},
  "geometry": {"coordinates":[-82.497287,38.958572],"type":"Point"}
}