{
  "type": "Feature",
  "properties": {
    "iso:country":"US",
    "sg:address":"1735 Beaconwood Ave",
    "sg:city":"Cleveland",
    "sg:classifiers":[
        {
            "category":"Professional",
            "type":"Services"
        }
    ],
    "sg:phone":"+1 216 381 9265",
    "sg:postcode":"44121",
    "sg:province":"OH",
    "wof:name":"Wendy Swendell",
    "wof:placetype":"venue"
},
  "geometry": {"coordinates":[-81.524926,41.511705],"type":"Point"}
}