{
  "type": "Feature",
  "properties": {
    "iso:country":"US",
    "sg:address":"354 Co Rd 24",
    "sg:city":"Archbold",
    "sg:classifiers":[
        {
            "category":"Wholesale",
            "subcategory":"Meat",
            "type":"Manufacturing & Wholesale Goods"
        }
    ],
    "sg:phone":"+1 419 445 6366",
    "sg:postcode":"43502",
    "sg:province":"OH",
    "sg:tags":[
        "packer"
    ],
    "wof:name":"Brookview Farm Meats",
    "wof:placetype":"venue"
},
  "geometry": {"coordinates":[-84.32523399999999,41.475587],"type":"Point"}
}