{
  "type": "Feature",
  "properties": {
    "addr:full":"875 Haskins Rd Bowling Green OH 43402",
    "addr:housenumber":"875",
    "addr:postcode":"43402",
    "addr:street":"Haskins Rd",
    "iso:country":"US",
    "sg:address":"875 Haskins Rd",
    "sg:city":"Bowling Green",
    "sg:classifiers":[
        {
            "category":"Organizations",
            "subcategory":"Religious Organization",
            "type":"Services"
        }
    ],
    "sg:phone":"+1 419 354 3989",
    "sg:postcode":"43402",
    "sg:province":"OH",
    "sg:tags":[
        "church"
    ],
    "wof:name":"First Christian Church",
    "wof:placetype":"venue"
},
  "geometry": {"coordinates":[-83.66808,41.385719],"type":"Point"}
}