{
  "type": "Feature",
  "properties": {
    "addr:full": "608 Thornbury Dr Dayton OH 45459",
    "addr:housenumber": "608",
    "addr:postcode": "45459",
    "addr:street": "Thornbury Dr",
    "iso:country": "US",
    "sg:address": "608 Thornbury Dr",
    "sg:city": "Dayton",
    "sg:classifiers": [
      {
        "category": "Professional",
        "subcategory": "Management \u0026 Consulting",
        "type": "Services"
      }
    ],
    "sg:phone": "+1 937 434 7726",
    "sg:postcode": "45459",
    "sg:province": "OH",
    "sg:tags": [
      "home",
      "demonstration"
    ],
    "wof:name": "Amway Distributors",
    "wof:placetype": "venue"
  },
  "geometry": {"coordinates":[-84.176745,39.657109],"type":"Point"}
}
