{
  "type": "Feature",
  "properties": {
    "addr:full": "708 Northfield Rd Bedford OH 44146",
    "addr:housenumber": "708",
    "addr:postcode": "44146",
    "addr:street": "Northfield Rd",
    "iso:country": "US",
    "sg:address": "708 Northfield Rd",
    "sg:city": "Bedford",
    "sg:classifiers": [
      {
        "category": "Professional",
        "type": "Services"
      }
    ],
    "sg:phone": "+1 440 439 4564",
    "sg:postcode": "44146",
    "sg:province": "OH",
    "wof:name": "Robert J Steffens 3r",
    "wof:placetype": "venue"
  },
  "geometry": {"coordinates":[-81.526427,41.396833],"type":"Point"}
}
