{
  "type": "Feature",
  "properties": {
    "iso:country":"US",
    "sg:address":"9118 Dayton Lebanon Pike",
    "sg:city":"Dayton",
    "sg:classifiers":[
        {
            "category":"Home & Garden",
            "subcategory":"Building Materials",
            "type":"Retail Goods"
        }
    ],
    "sg:phone":"+1 937 428 6058",
    "sg:postcode":"45458",
    "sg:province":"OH",
    "sg:tags":[
        "glass",
        "leaded"
    ],
    "wof:name":"SGO Designer Glass",
    "wof:placetype":"venue"
},
  "geometry": {"coordinates":[-84.160375,39.611868],"type":"Point"}
}