{
  "type": "Feature",
  "properties": {
    "addr:full": "48 Curt Rd Seaman OH 45679",
    "addr:housenumber": "48",
    "addr:postcode": "45679",
    "addr:street": "Curt Rd",
    "iso:country": "US",
    "sg:address": "48 Curt Rd",
    "sg:city": "Seaman",
    "sg:classifiers": [
      {
        "category": "Farming",
        "subcategory": "Livestock Farm",
        "type": "Manufacturing \u0026 Wholesale Goods"
      }
    ],
    "sg:phone": "+1 937 386 2531",
    "sg:postcode": "45679",
    "sg:province": "OH",
    "sg:tags": [
      "beef",
      "feedlot",
      "cattle"
    ],
    "wof:name": "Triple Cross Cattle Co",
    "wof:placetype": "venue"
  },
  "geometry": {"coordinates":[-83.57402,38.949942],"type":"Point"}
}
