{
  "type": "Feature",
  "properties": {
    "addr:full":"714 Terrace Ct Trenton OH 45067",
    "addr:housenumber":"714",
    "addr:postcode":"45067",
    "addr:street":"Terrace Ct",
    "iso:country":"US",
    "sg:address":"714 Terrace Ct",
    "sg:city":"Trenton",
    "sg:classifiers":[
        {
            "category":"Professional",
            "subcategory":"Management & Consulting",
            "type":"Services"
        }
    ],
    "sg:phone":"+1 513 988 6607",
    "sg:postcode":"45067",
    "sg:province":"OH",
    "sg:tags":[
        "consultant",
        "educational"
    ],
    "wof:name":"Sons & Daughter Learning Ctr",
    "wof:placetype":"venue"
},
  "geometry": {"coordinates":[-84.470039,39.478152],"type":"Point"}
}