{
  "type": "Feature",
  "properties": {
    "addr:full":"626 Zenobia Rd Norwalk OH 44857",
    "addr:housenumber":"626",
    "addr:postcode":"44857",
    "addr:street":"Zenobia Rd",
    "iso:country":"US",
    "sg:address":"626 Zenobia Rd",
    "sg:city":"Norwalk",
    "sg:phone":"+1 419 668 4370",
    "sg:postcode":"44857",
    "sg:province":"OH",
    "sg:tags":[
        "farm",
        "corn",
        "soybean"
    ],
    "wof:name":"Ervin Linder",
    "wof:placetype":"venue"
},
  "geometry": {"coordinates":[-82.56739899999999,41.207301],"type":"Point"}
}