{
  "type": "Feature",
  "properties": {
    "addr:full": "7960 York Rd Cleveland OH 44133",
    "addr:housenumber": "7960",
    "addr:postcode": "44133",
    "addr:street": "York Rd",
    "iso:country": "US",
    "sg:address": "7960 York Rd",
    "sg:city": "Cleveland",
    "sg:classifiers": [
      {
        "category": "Insurance",
        "subcategory": "Insurance Agent",
        "type": "Services"
      }
    ],
    "sg:phone": "+1 440 842 5826",
    "sg:postcode": "44133",
    "sg:province": "OH",
    "wof:name": "Larry Werner Insurance Inc",
    "wof:placetype": "venue"
  },
  "geometry": {"coordinates":[-81.759386,41.346814],"type":"Point"}
}
