{
  "type": "Feature",
  "properties": {
    "iso:country":"US",
    "sg:address":"1572 Shiloh Springs Rd",
    "sg:city":"Dayton",
    "sg:classifiers":[
        {
            "category":"Shopping",
            "subcategory":"Clothing, Apparel, & Fashions",
            "type":"Retail Goods"
        }
    ],
    "sg:phone":"+1 937 837 8226",
    "sg:postcode":"45426",
    "sg:province":"OH",
    "wof:name":"Coming Attractions",
    "wof:placetype":"venue"
},
  "geometry": {"coordinates":[-84.264169,39.819467],"type":"Point"}
}