{
  "type": "Feature",
  "properties": {
    "addr:full": "263 Industrial Dr Franklin OH 45005",
    "addr:housenumber": "263",
    "addr:postcode": "45005",
    "addr:street": "Industrial Dr",
    "iso:country": "US",
    "sg:address": "263 Industrial Dr",
    "sg:city": "Franklin",
    "sg:classifiers": [
      {
        "category": "Manufacturing",
        "subcategory": "Rubber \u0026 Plastics",
        "type": "Manufacturing \u0026 Wholesale Goods"
      }
    ],
    "sg:phone": "+1 937 746 8388",
    "sg:postcode": "45005",
    "sg:province": "OH",
    "sg:tags": [
      "sanitary",
      "mfg",
      "wear",
      "cultured",
      "marble"
    ],
    "sg:website": "www.marblearchproducts.com",
    "wof:name": "Marble Arch Products Inc",
    "wof:placetype": "venue"
  },
  "geometry": {"coordinates":[-84.290554,39.537233],"type":"Point"}
}
