{
  "type": "Feature",
  "properties": {
    "iso:country":"US",
    "sg:address":"263 Industrial Dr",
    "sg:city":"Franklin",
    "sg:classifiers":[
        {
            "category":"Manufacturing",
            "subcategory":"Rubber & Plastics",
            "type":"Manufacturing & Wholesale Goods"
        }
    ],
    "sg:phone":"+1 937 746 8388",
    "sg:postcode":"45005",
    "sg:province":"OH",
    "sg:tags":[
        "sanitary",
        "mfg",
        "wear",
        "cultured",
        "marble"
    ],
    "sg:website":"www.marblearchproducts.com",
    "wof:name":"Marble Arch Products Inc",
    "wof:placetype":"venue"
},
  "geometry": {"coordinates":[-84.290554,39.537233],"type":"Point"}
}