{
  "type": "Feature",
  "properties": {
    "iso:country":"US",
    "sg:address":"216 N Main St",
    "sg:city":"Marion",
    "sg:classifiers":[
        {
            "category":"Manufacturing",
            "subcategory":"Printing",
            "type":"Manufacturing & Wholesale Goods"
        }
    ],
    "sg:phone":"+1 740 383 3781",
    "sg:postcode":"43302",
    "sg:province":"OH",
    "sg:tags":[
        "cards",
        "business"
    ],
    "wof:name":"Signs & Logos Inc",
    "wof:placetype":"venue"
},
  "geometry": {"coordinates":[-83.12900999999999,40.592336],"type":"Point"}
}