{
  "type": "Feature",
  "properties": {
    "addr:full": "216 N Main St Marion OH 43302",
    "addr:housenumber": "216",
    "addr:postcode": "43302",
    "addr:street": "N Main St",
    "iso:country": "US",
    "sg:address": "216 N Main St",
    "sg:city": "Marion",
    "sg:classifiers": [
      {
        "category": "Manufacturing",
        "subcategory": "Printing",
        "type": "Manufacturing \u0026 Wholesale Goods"
      }
    ],
    "sg:phone": "+1 740 383 3781",
    "sg:postcode": "43302",
    "sg:province": "OH",
    "sg:tags": [
      "cards",
      "business"
    ],
    "wof:name": "Signs \u0026 Logos Inc",
    "wof:placetype": "venue"
  },
  "geometry": {"coordinates":[-83.12901,40.592336],"type":"Point"}
}
