{
  "type": "Feature",
  "properties": {
    "addr:full":"6573 Cochran Rd Cleveland OH 44139",
    "addr:housenumber":"6573",
    "addr:postcode":"44139",
    "addr:street":"Cochran Rd",
    "iso:country":"US",
    "sg:address":"6573 Cochran Rd",
    "sg:city":"Cleveland",
    "sg:classifiers":[
        {
            "category":"Real Estate",
            "subcategory":"Real Estate Agent",
            "type":"Services"
        }
    ],
    "sg:phone":"+1 440 505 2200",
    "sg:postcode":"44139",
    "sg:province":"OH",
    "sg:tags":[
        "management"
    ],
    "wof:name":"Gemini Development Group Inc",
    "wof:placetype":"venue"
},
  "geometry": {"coordinates":[-81.46920299999999,41.378259],"type":"Point"}
}