{
  "type": "Feature",
  "properties": {
    "iso:country":"US",
    "sg:address":"34980 Lakeland Blvd",
    "sg:city":"Willoughby",
    "sg:classifiers":[
        {
            "category":"Building & Trades",
            "subcategory":"Construction",
            "type":"Services"
        }
    ],
    "sg:phone":"+1 440 946 1117",
    "sg:postcode":"44095",
    "sg:province":"OH",
    "sg:tags":[
        "excavating",
        "contractor"
    ],
    "wof:name":"D Farinacci Excavating",
    "wof:placetype":"venue"
},
  "geometry": {"coordinates":[-81.446519,41.630706],"type":"Point"}
}