{
  "type": "Feature",
  "properties": {
    "addr:full":"70 Rothrock Loop Copley OH 44321",
    "addr:housenumber":"70",
    "addr:postcode":"44321",
    "addr:street":"Rothrock Loop",
    "iso:country":"US",
    "sg:address":"70 Rothrock Loop",
    "sg:city":"Copley",
    "sg:classifiers":[
        {
            "category":"Travel",
            "subcategory":"Hotels & Motels",
            "type":"Entertainment"
        },
        {
            "category":"Travel",
            "subcategory":"Bed & Breakfast",
            "type":"Entertainment"
        }
    ],
    "sg:phone":"+1 330 668 2700",
    "sg:postcode":"44321",
    "sg:province":"OH",
    "sg:tags":[
        "inn",
        "lodging"
    ],
    "sg:website":"http://www.baymontinns.com/hotel/19396&cid=RASE",
    "wof:name":"Baymont Inn and Suites Copley",
    "wof:placetype":"venue"
},
  "geometry": {"coordinates":[-81.648006,41.133607],"type":"Point"}
}