{
  "type": "Feature",
  "properties": {
    "addr:full": "1964 N Lakeman Dr Bellbrook OH 45305",
    "addr:housenumber": "1964",
    "addr:postcode": "45305",
    "addr:street": "N Lakeman Dr",
    "iso:country": "US",
    "sg:address": "1964 N Lakeman Dr",
    "sg:city": "Bellbrook",
    "sg:classifiers": [
      {
        "category": "Health Services",
        "subcategory": "Doctor",
        "type": "Services"
      }
    ],
    "sg:phone": "+1 937 848 6388",
    "sg:postcode": "45305",
    "sg:province": "OH",
    "sg:tags": [
      "dentist"
    ],
    "wof:name": "Burton L Hagler DDS Ms",
    "wof:placetype": "venue"
  },
  "geometry": {"coordinates":[-84.102868,39.641191],"type":"Point"}
}
