{
  "type": "Feature",
  "properties": {
    "addr:full": "1500 N Clinton St Defiance OH 43512",
    "addr:housenumber": "1500",
    "addr:postcode": "43512",
    "addr:street": "N Clinton St",
    "iso:country": "US",
    "sg:address": "1500 N Clinton St",
    "sg:city": "Defiance",
    "sg:classifiers": [
      {
        "category": "Shopping",
        "subcategory": "Department Store",
        "type": "Retail Goods"
      }
    ],
    "sg:phone": "+1 419 783 2928",
    "sg:postcode": "43512",
    "sg:province": "OH",
    "wof:name": "Sears Roebuck \u0026 Co",
    "wof:placetype": "venue"
  },
  "geometry": {"coordinates":[-84.360949,41.300984],"type":"Point"}
}
