{
  "type": "Feature",
  "properties": {
    "iso:country":"US",
    "sg:address":"1500 N Clinton St",
    "sg:city":"Defiance",
    "sg:classifiers":[
        {
            "category":"Shopping",
            "subcategory":"Department Store",
            "type":"Retail Goods"
        }
    ],
    "sg:phone":"+1 419 783 2928",
    "sg:postcode":"43512",
    "sg:province":"OH",
    "wof:name":"Sears Roebuck & Co",
    "wof:placetype":"venue"
},
  "geometry": {"coordinates":[-84.36094900000001,41.300984],"type":"Point"}
}