{
  "type": "Feature",
  "properties": {
    "addr:full": "804 Warren Ave Niles OH 44446",
    "addr:housenumber": "804",
    "addr:postcode": "44446",
    "addr:street": "Warren Ave",
    "iso:country": "US",
    "sg:address": "804 Warren Ave",
    "sg:city": "Niles",
    "sg:classifiers": [
      {
        "category": "Banks \u0026 Credit Unions",
        "subcategory": "Bank",
        "type": "Services"
      }
    ],
    "sg:phone": "+1 330 652 3887",
    "sg:postcode": "44446",
    "sg:province": "OH",
    "sg:tags": [
      "state"
    ],
    "wof:name": "First Choice Community Cr Un",
    "wof:placetype": "venue"
  },
  "geometry": {"coordinates":[-80.776071,41.183414],"type":"Point"}
}
