{
  "type": "Feature",
  "properties": {
    "addr:full":"2930 Edison St NW Uniontown OH 44685",
    "addr:housenumber":"2930",
    "addr:postcode":"44685",
    "addr:street":"Edison St Nw",
    "iso:country":"US",
    "sg:address":"2930 Edison St NW",
    "sg:city":"Uniontown",
    "sg:classifiers":[
        {
            "category":"Insurance",
            "subcategory":"Insurance Agent",
            "type":"Services"
        }
    ],
    "sg:phone":"+1 330 699 8877",
    "sg:postcode":"44685",
    "sg:province":"OH",
    "wof:name":"Thrivent Financial-Lutherans",
    "wof:placetype":"venue"
},
  "geometry": {"coordinates":[-81.40039,40.97617],"type":"Point"}
}