{
  "type": "Feature",
  "properties": {
    "addr:full": "7561 Avon Lake Rd Lodi OH 44254",
    "addr:housenumber": "7561",
    "addr:postcode": "44254",
    "addr:street": "Avon Lake Rd",
    "iso:country": "US",
    "sg:address": "7561 Avon Lake Rd",
    "sg:city": "Lodi",
    "sg:classifiers": [
      {
        "category": "Building \u0026 Trades",
        "subcategory": "Construction",
        "type": "Services"
      }
    ],
    "sg:phone": "+1 330 667 2885",
    "sg:postcode": "44254",
    "sg:province": "OH",
    "sg:tags": [
      "house"
    ],
    "wof:name": "Christopher J Nespeca",
    "wof:placetype": "venue"
  },
  "geometry": {"coordinates":[-82.024477,41.066817],"type":"Point"}
}
