{
  "type": "Feature",
  "properties": {
    "iso:country":"US",
    "sg:address":"7561 Avon Lake Rd",
    "sg:city":"Lodi",
    "sg:classifiers":[
        {
            "category":"Building & Trades",
            "subcategory":"Construction",
            "type":"Services"
        }
    ],
    "sg:phone":"+1 330 667 2885",
    "sg:postcode":"44254",
    "sg:province":"OH",
    "sg:tags":[
        "house"
    ],
    "wof:name":"Christopher J Nespeca",
    "wof:placetype":"venue"
},
  "geometry": {"coordinates":[-82.024477,41.066817],"type":"Point"}
}