{
  "type": "Feature",
  "properties": {
    "iso:country":"US",
    "sg:address":"5001 Mayfield Rd",
    "sg:city":"Cleveland",
    "sg:classifiers":[
        {
            "category":"Manufacturing",
            "subcategory":"Tools & Machinery",
            "type":"Manufacturing & Wholesale Goods"
        }
    ],
    "sg:phone":"+1 216 381 6822",
    "sg:postcode":"44124",
    "sg:province":"OH",
    "sg:tags":[
        "electrical",
        "mfg"
    ],
    "wof:name":"Hinds Crouse Products",
    "wof:placetype":"venue"
},
  "geometry": {"coordinates":[-81.49796499999999,41.519913],"type":"Point"}
}