{
  "type": "Feature",
  "properties": {
    "addr:full": "6444 Gallia St Portsmouth OH 45662",
    "addr:postcode": "6444;45662",
    "addr:street": "Gallia St",
    "iso:country": "US",
    "sg:address": "6444 Gallia St",
    "sg:city": "Portsmouth",
    "sg:classifiers": [
      {
        "category": "Social Services",
        "subcategory": "Child Care",
        "type": "Services"
      }
    ],
    "sg:phone": "+1 740 776 7274",
    "sg:postcode": "45662",
    "sg:province": "OH",
    "wof:name": "Patty's Day Care",
    "wof:placetype": "venue"
  },
  "geometry": {"coordinates":[-82.879207,38.753981],"type":"Point"}
}
