{
  "type": "Feature",
  "properties": {
    "iso:country":"US",
    "sg:address":"27820 Chagrin Blvd",
    "sg:city":"Cleveland",
    "sg:classifiers":[
        {
            "category":"Home & Garden",
            "subcategory":"Furniture",
            "type":"Retail Goods"
        }
    ],
    "sg:phone":"+1 216 765 1015",
    "sg:postcode":"44122",
    "sg:province":"OH",
    "sg:tags":[
        "juvenile"
    ],
    "wof:name":"Bellini Juvenile Designer Furn",
    "wof:placetype":"venue"
},
  "geometry": {"coordinates":[-81.480727,41.46226],"type":"Point"}
}