{
  "type": "Feature",
  "properties": {
    "addr:full": "27820 Chagrin Blvd Cleveland OH 44122",
    "addr:housenumber": "27820",
    "addr:postcode": "44122",
    "addr:street": "Chagrin Blvd",
    "iso:country": "US",
    "sg:address": "27820 Chagrin Blvd",
    "sg:city": "Cleveland",
    "sg:classifiers": [
      {
        "category": "Home \u0026 Garden",
        "subcategory": "Furniture",
        "type": "Retail Goods"
      }
    ],
    "sg:phone": "+1 216 765 1015",
    "sg:postcode": "44122",
    "sg:province": "OH",
    "sg:tags": [
      "juvenile"
    ],
    "wof:name": "Bellini Juvenile Designer Furn",
    "wof:placetype": "venue"
  },
  "geometry": {"coordinates":[-81.480727,41.46226],"type":"Point"}
}
