{
  "type": "Feature",
  "properties": {
    "iso:country":"US",
    "sg:address":"1436 Elm St",
    "sg:city":"Youngstown",
    "sg:classifiers":[
        {
            "category":"Organizations",
            "subcategory":"Religious Organization",
            "type":"Services"
        }
    ],
    "sg:phone":"+1 330 744 5504",
    "sg:postcode":"44505",
    "sg:province":"OH",
    "sg:tags":[
        "clergy"
    ],
    "wof:name":"Greater Mt Calvary Baptist Chr",
    "wof:placetype":"venue"
},
  "geometry": {"coordinates":[-80.645449,41.119653],"type":"Point"}
}