{
  "type": "Feature",
  "properties": {
    "addr:full": "3014 Bancroft Rd Fairlawn OH 44333",
    "addr:housenumber": "3014",
    "addr:postcode": "44333",
    "addr:street": "Bancroft Rd",
    "iso:country": "US",
    "sg:address": "3014 Bancroft Rd",
    "sg:city": "Fairlawn",
    "sg:classifiers": [
      {
        "category": "Recreation",
        "type": "Entertainment"
      }
    ],
    "sg:phone": "+1 330 836 0850",
    "sg:postcode": "44333",
    "sg:province": "OH",
    "sg:tags": [
      "amusement"
    ],
    "wof:name": "Fencing Academy Kiraly",
    "wof:placetype": "venue"
  },
  "geometry": {"coordinates":[-81.619014,41.12197],"type":"Point"}
}
