{
  "type": "Feature",
  "properties": {
    "iso:country":"US",
    "sg:address":"3014 Bancroft Rd",
    "sg:city":"Fairlawn",
    "sg:classifiers":[
        {
            "category":"Recreation",
            "type":"Entertainment"
        }
    ],
    "sg:phone":"+1 330 836 0850",
    "sg:postcode":"44333",
    "sg:province":"OH",
    "sg:tags":[
        "amusement"
    ],
    "wof:name":"Fencing Academy Kiraly",
    "wof:placetype":"venue"
},
  "geometry": {"coordinates":[-81.61901400000001,41.12197],"type":"Point"}
}