{
  "type": "Feature",
  "properties": {
    "iso:country":"US",
    "sg:address":"234 Goodman St",
    "sg:city":"Cincinnati",
    "sg:classifiers":[
        {
            "category":"Education",
            "subcategory":"University",
            "type":"Public Place"
        }
    ],
    "sg:phone":"+1 513 584 2873",
    "sg:postcode":"45219",
    "sg:province":"OH",
    "sg:tags":[
        "college"
    ],
    "wof:name":"University of Cincinnati Pancreatic Disease Center",
    "wof:placetype":"venue"
},
  "geometry": {"coordinates":[-84.50112799999999,39.136627],"type":"Point"}
}