{
  "type": "Feature",
  "properties": {
    "addr:full": "234 Goodman St Cincinnati OH 45219",
    "addr:housenumber": "234",
    "addr:postcode": "45219",
    "addr:street": "Goodman St",
    "iso:country": "US",
    "sg:address": "234 Goodman St",
    "sg:city": "Cincinnati",
    "sg:classifiers": [
      {
        "category": "Education",
        "subcategory": "University",
        "type": "Public Place"
      }
    ],
    "sg:phone": "+1 513 584 2873",
    "sg:postcode": "45219",
    "sg:province": "OH",
    "sg:tags": [
      "college"
    ],
    "wof:name": "University of Cincinnati Pancreatic Disease Center",
    "wof:placetype": "venue"
  },
  "geometry": {"coordinates":[-84.501128,39.136627],"type":"Point"}
}
