{
  "type": "Feature",
  "properties": {
    "addr:full":"1939 Majestic Cir Steubenville OH 43952",
    "addr:housenumber":"1939",
    "addr:postcode":"43952",
    "addr:street":"Majestic Cir",
    "iso:country":"US",
    "sg:address":"1939 Majestic Cir",
    "sg:city":"Steubenville",
    "sg:classifiers":[
        {
            "category":"Shopping",
            "subcategory":"Used Merchandise",
            "type":"Retail Goods"
        }
    ],
    "sg:phone":"+1 740 282 3926",
    "sg:postcode":"43952",
    "sg:province":"OH",
    "sg:tags":[
        "antique"
    ],
    "wof:name":"Oldies But Goodies",
    "wof:placetype":"venue"
},
  "geometry": {"coordinates":[-80.63631599999999,40.374621],"type":"Point"}
}