{
  "type": "Feature",
  "properties": {
    "addr:full": "1055 Roosevelt Ave Cuyahoga Falls OH 44221",
    "addr:housenumber": "1055",
    "addr:postcode": "44221",
    "addr:street": "Roosevelt Ave",
    "iso:country": "US",
    "sg:address": "1055 Roosevelt Ave",
    "sg:city": "Cuyahoga Falls",
    "sg:classifiers": [
      {
        "category": "Building \u0026 Trades",
        "subcategory": "Plumbing",
        "type": "Services"
      }
    ],
    "sg:phone": "+1 330 923 1907",
    "sg:postcode": "44221",
    "sg:province": "OH",
    "sg:tags": [
      "contractor"
    ],
    "wof:name": "Plumbing Unlimited",
    "wof:placetype": "venue"
  },
  "geometry": {"coordinates":[-81.496411,41.14455],"type":"Point"}
}
