{
  "type": "Feature",
  "properties": {
    "iso:country":"US",
    "sg:address":"1055 Roosevelt Ave",
    "sg:city":"Cuyahoga Falls",
    "sg:classifiers":[
        {
            "category":"Building & Trades",
            "subcategory":"Plumbing",
            "type":"Services"
        }
    ],
    "sg:phone":"+1 330 923 1907",
    "sg:postcode":"44221",
    "sg:province":"OH",
    "sg:tags":[
        "contractor"
    ],
    "wof:name":"Plumbing Unlimited",
    "wof:placetype":"venue"
},
  "geometry": {"coordinates":[-81.49641099999999,41.14455],"type":"Point"}
}