{
  "type": "Feature",
  "properties": {
    "addr:full":"2360 Van Leunen Dr Cincinnati OH 45239",
    "addr:housenumber":"2360",
    "addr:postcode":"45239",
    "addr:street":"Van Leunen Dr",
    "iso:country":"US",
    "sg:address":"2360 Van Leunen Dr",
    "sg:city":"Cincinnati",
    "sg:classifiers":[
        {
            "category":"Professional",
            "type":"Services"
        }
    ],
    "sg:phone":"+1 513 542 4431",
    "sg:postcode":"45239",
    "sg:province":"OH",
    "wof:name":"Virginia E Wilker",
    "wof:placetype":"venue"
},
  "geometry": {"coordinates":[-84.568511,39.194825],"type":"Point"}
}