{
  "type": "Feature",
  "properties": {
    "iso:country":"US",
    "sg:address":"6157 Alliance Rd NW",
    "sg:city":"Malvern",
    "sg:classifiers":[
        {
            "category":"Restaurant",
            "type":"Food & Drink"
        }
    ],
    "sg:phone":"+1 330 863 9135",
    "sg:postcode":"44644",
    "sg:province":"OH",
    "wof:name":"Deb's Family Restaurant",
    "wof:placetype":"venue"
},
  "geometry": {"coordinates":[-81.203992,40.688607],"type":"Point"}
}