{
  "type": "Feature",
  "properties": {
    "addr:full": "6157 Alliance Rd NW Malvern OH 44644",
    "addr:housenumber": "6157",
    "addr:postcode": "44644",
    "addr:street": "Alliance Rd Nw",
    "iso:country": "US",
    "sg:address": "6157 Alliance Rd NW",
    "sg:city": "Malvern",
    "sg:classifiers": [
      {
        "category": "Restaurant",
        "type": "Food \u0026 Drink"
      }
    ],
    "sg:phone": "+1 330 863 9135",
    "sg:postcode": "44644",
    "sg:province": "OH",
    "wof:name": "Deb's Family Restaurant",
    "wof:placetype": "venue"
  },
  "geometry": {"coordinates":[-81.203992,40.688607],"type":"Point"}
}
