{
  "type": "Feature",
  "properties": {
    "iso:country":"US",
    "sg:address":"4220 W 130th St",
    "sg:city":"Cleveland",
    "sg:classifiers":[
        {
            "category":"Retail",
            "subcategory":"Auto Repair",
            "type":"Services"
        }
    ],
    "sg:phone":"+1 216 251 4200",
    "sg:postcode":"44135",
    "sg:province":"OH",
    "sg:tags":[
        "body",
        "automobile",
        "painting"
    ],
    "wof:name":"Dempsey's Auto Body",
    "wof:placetype":"venue"
},
  "geometry": {"coordinates":[-81.779831,41.440402],"type":"Point"}
}