{
  "type": "Feature",
  "properties": {
    "addr:full":"1807 O Brien Rd Columbus OH 43228",
    "addr:housenumber":"1807",
    "addr:postcode":"43228",
    "addr:street":"O Brien Rd",
    "iso:country":"US",
    "sg:address":"1807 O Brien Rd",
    "sg:city":"Columbus",
    "sg:classifiers":[
        {
            "category":"Wholesale",
            "subcategory":"Durable Goods & Equipment",
            "type":"Manufacturing & Wholesale Goods"
        }
    ],
    "sg:phone":"+1 614 771 7017",
    "sg:postcode":"43228",
    "sg:province":"OH",
    "sg:tags":[
        "professional",
        "electrical",
        "contractor"
    ],
    "wof:name":"Diebold Incorporated",
    "wof:placetype":"venue"
},
  "geometry": {"coordinates":[-83.14085300000001,39.951512],"type":"Point"}
}