{
  "type": "Feature",
  "properties": {
    "iso:country":"US",
    "sg:address":"1398 N Shoop Ave",
    "sg:city":"Wauseon",
    "sg:classifiers":[
        {
            "category":"Professional",
            "subcategory":"Business Services",
            "type":"Services"
        },
        {
            "category":"Shopping",
            "subcategory":"Computers & Home Electronics",
            "type":"Retail Goods"
        }
    ],
    "sg:phone":"+1 419 335 0399",
    "sg:postcode":"43567",
    "sg:province":"OH",
    "sg:tags":[
        "communication",
        "satellite",
        "system",
        "equipment"
    ],
    "wof:name":"Direct Communications Inc",
    "wof:placetype":"venue"
},
  "geometry": {"coordinates":[-84.134286,41.566512],"type":"Point"}
}