{
  "type": "Feature",
  "properties": {
    "addr:full": "14647 State Rte 511 Oberlin OH 44074",
    "addr:housenumber": "14647",
    "addr:postcode": "44074",
    "addr:street": "State Rte 511",
    "iso:country": "US",
    "sg:address": "14647 State Rte 511",
    "sg:city": "Oberlin",
    "sg:classifiers": [
      {
        "category": "Shopping",
        "subcategory": "Discount \u0026 Variety Stores",
        "type": "Retail Goods"
      }
    ],
    "sg:phone": "+1 440 774 1601",
    "sg:postcode": "44074",
    "sg:province": "OH",
    "sg:tags": [
      "merchandise",
      "general"
    ],
    "wof:name": "Johnson Stone Products Inc",
    "wof:placetype": "venue"
  },
  "geometry": {"coordinates":[-82.173656,41.293744],"type":"Point"}
}
