{
  "type": "Feature",
  "properties": {
    "addr:full":"108 Mansfield Ave Mount Vernon OH 43050",
    "addr:housenumber":"108",
    "addr:postcode":"43050",
    "addr:street":"Mansfield Ave",
    "iso:country":"US",
    "sg:address":"108 Mansfield Ave",
    "sg:city":"Mount Vernon",
    "sg:classifiers":[
        {
            "category":"Education",
            "subcategory":"School",
            "type":"Public Place"
        }
    ],
    "sg:phone":"+1 740 393 5950",
    "sg:postcode":"43050",
    "sg:province":"OH",
    "wof:name":"SC Mt Vernon Dan Emmett Elem",
    "wof:placetype":"venue"
},
  "geometry": {"coordinates":[-82.487117,40.407046],"type":"Point"}
}