{
  "type": "Feature",
  "properties": {
    "iso:country":"US",
    "sg:address":"2171 Delaware Dr",
    "sg:city":"Cleveland",
    "sg:classifiers":[
        {
            "category":"Retail",
            "subcategory":"Animal Services",
            "type":"Services"
        }
    ],
    "sg:phone":"+1 216 229 8336",
    "sg:postcode":"44106",
    "sg:province":"OH",
    "sg:tags":[
        "pet",
        "breeder"
    ],
    "sg:website":"www.boabasement.com",
    "wof:name":"Boa Basement",
    "wof:placetype":"venue"
},
  "geometry": {"coordinates":[-81.595879,41.499821],"type":"Point"}
}