{
  "type": "Feature",
  "properties": {
    "iso:country":"US",
    "sg:address":"6630 Estate View Dr N",
    "sg:city":"Blacklick",
    "sg:classifiers":[
        {
            "category":"Real Estate",
            "subcategory":"Real Estate Agent",
            "type":"Services"
        }
    ],
    "sg:phone":"+1 614 322 9756",
    "sg:postcode":"43004",
    "sg:province":"OH",
    "wof:name":"Upscale Properties-Columbus",
    "wof:placetype":"venue"
},
  "geometry": {"coordinates":[-82.830547,40.005266],"type":"Point"}
}