{
  "type": "Feature",
  "properties": {
    "addr:full": "1501 E Central Ave Miamisburg OH 45342",
    "addr:housenumber": "1501",
    "addr:postcode": "45342",
    "addr:street": "E Central Ave",
    "iso:country": "US",
    "sg:address": "1501 E Central Ave",
    "sg:city": "Miamisburg",
    "sg:classifiers": [
      {
        "category": "Recreation",
        "type": "Entertainment"
      }
    ],
    "sg:phone": "+1 937 866 9320",
    "sg:postcode": "45342",
    "sg:province": "OH",
    "sg:tags": [
      "club",
      "membership"
    ],
    "wof:name": "Sycamore Creek Country Club",
    "wof:placetype": "venue"
  },
  "geometry": {"coordinates":[-84.264776,39.640606],"type":"Point"}
}
