{
  "type": "Feature",
  "properties": {
    "addr:full":"7910 Monclova Rd Monclova OH 43542",
    "addr:housenumber":"7910",
    "addr:postcode":"43542",
    "addr:street":"Monclova Rd",
    "iso:country":"US",
    "sg:address":"7910 Monclova Rd",
    "sg:city":"Monclova",
    "sg:classifiers":[
        {
            "category":"Professional",
            "type":"Services"
        }
    ],
    "sg:phone":"+1 419 867 8673",
    "sg:postcode":"43542",
    "sg:province":"OH",
    "sg:tags":[
        "establishment"
    ],
    "wof:name":"J Tucker Trades Co",
    "wof:placetype":"venue"
},
  "geometry": {"coordinates":[-83.72747200000001,41.558877],"type":"Point"}
}