{
  "type": "Feature",
  "properties": {
    "addr:full":"5700 Reigart Rd Hamilton OH 45011",
    "addr:postcode":"5700;45011",
    "addr:street":"Reigart Rd",
    "iso:country":"US",
    "sg:address":"5700 Reigart Rd",
    "sg:city":"Hamilton",
    "sg:classifiers":[
        {
            "category":"Recreation",
            "subcategory":"Marina",
            "type":"Entertainment"
        }
    ],
    "sg:phone":"+1 513 863 9635",
    "sg:postcode":"45011",
    "sg:province":"OH",
    "wof:name":"Hamilton Boat Club",
    "wof:placetype":"venue"
},
  "geometry": {"coordinates":[-84.501323,39.421807],"type":"Point"}
}