{
  "type": "Feature",
  "properties": {
    "addr:full": "7201 Quincy Ave Cleveland OH 44104",
    "addr:housenumber": "7201",
    "addr:postcode": "44104",
    "addr:street": "Quincy Ave",
    "iso:country": "US",
    "sg:address": "7201 Quincy Ave",
    "sg:city": "Cleveland",
    "sg:classifiers": [
      {
        "category": "Organizations",
        "subcategory": "Religious Organization",
        "type": "Services"
      }
    ],
    "sg:phone": "+1 216 391 7289",
    "sg:postcode": "44104",
    "sg:province": "OH",
    "sg:tags": [
      "church"
    ],
    "wof:name": "Deliverance Overcoming Church",
    "wof:placetype": "venue"
  },
  "geometry": {"coordinates":[-81.637282,41.493448],"type":"Point"}
}
