{
  "type": "Feature",
  "properties": {
    "addr:full": "192 S Eureka Ave Columbus OH 43204",
    "addr:housenumber": "192",
    "addr:postcode": "43204",
    "addr:street": "S Eureka Ave",
    "iso:country": "US",
    "sg:address": "192 S Eureka Ave",
    "sg:city": "Columbus",
    "sg:classifiers": [
      {
        "category": "Food \u0026 Beverages",
        "subcategory": "Groceries \u0026 Convenience Stores",
        "type": "Retail Goods"
      }
    ],
    "sg:phone": "+1 614 274 6485",
    "sg:postcode": "43204",
    "sg:province": "OH",
    "sg:tags": [
      "grocer"
    ],
    "wof:name": "Lemandand Stop",
    "wof:placetype": "venue"
  },
  "geometry": {"coordinates":[-83.065192,39.952742],"type":"Point"}
}
