{
  "type": "Feature",
  "properties": {
    "iso:country":"US",
    "sg:address":"192 S Eureka Ave",
    "sg:city":"Columbus",
    "sg:classifiers":[
        {
            "category":"Food & Beverages",
            "subcategory":"Groceries & Convenience Stores",
            "type":"Retail Goods"
        }
    ],
    "sg:phone":"+1 614 274 6485",
    "sg:postcode":"43204",
    "sg:province":"OH",
    "sg:tags":[
        "grocer"
    ],
    "wof:name":"Lemandand Stop",
    "wof:placetype":"venue"
},
  "geometry": {"coordinates":[-83.065192,39.952742],"type":"Point"}
}