{
  "type": "Feature",
  "properties": {
    "addr:full": "1626 Parkwood Rd Cleveland OH 44107",
    "addr:housenumber": "1626",
    "addr:postcode": "44107",
    "addr:street": "Parkwood Rd",
    "iso:country": "US",
    "sg:address": "1626 Parkwood Rd",
    "sg:city": "Cleveland",
    "sg:classifiers": [
      {
        "category": "Building \u0026 Trades",
        "subcategory": "Plumbing",
        "type": "Services"
      }
    ],
    "sg:phone": "+1 216 521 2338",
    "sg:postcode": "44107",
    "sg:province": "OH",
    "sg:tags": [
      "plumbing",
      "contractor",
      "remodeling",
      "general"
    ],
    "wof:name": "Keil Plumbing \u0026 Contracting",
    "wof:placetype": "venue"
  },
  "geometry": {"coordinates":[-81.788634,41.479239],"type":"Point"}
}
