{
  "type": "Feature",
  "properties": {
    "addr:full": "650 W Resource Dr Cleveland OH 44131",
    "addr:housenumber": "650",
    "addr:postcode": "44131",
    "addr:street": "W Resource Dr",
    "iso:country": "US",
    "sg:address": "650 W Resource Dr",
    "sg:city": "Cleveland",
    "sg:classifiers": [
      {
        "category": "Real Estate",
        "subcategory": "Real Estate Agent",
        "type": "Services"
      },
      {
        "category": "Building \u0026 Trades",
        "subcategory": "Landscaping Services",
        "type": "Services"
      }
    ],
    "sg:phone": "+1 216 739 2900",
    "sg:postcode": "44131",
    "sg:province": "OH",
    "sg:tags": [
      "carpentry",
      "special",
      "contractor"
    ],
    "sg:website": "www.safeguardproperties.com",
    "wof:name": "Safeguard Properties Inc",
    "wof:placetype": "venue"
  },
  "geometry": {"coordinates":[-81.668401,41.413618],"type":"Point"}
}
