{
  "type": "Feature",
  "properties": {
    "iso:country":"US",
    "sg:address":"81 Flax Dr",
    "sg:city":"London",
    "sg:classifiers":[
        {
            "category":"Organizations",
            "subcategory":"Religious Organization",
            "type":"Services"
        }
    ],
    "sg:phone":"+1 740 852 5966",
    "sg:postcode":"43140",
    "sg:province":"OH",
    "sg:tags":[
        "clergy"
    ],
    "wof:name":"Grace Baptist Church",
    "wof:placetype":"venue"
},
  "geometry": {"coordinates":[-83.463033,39.879466],"type":"Point"}
}