{
  "type": "Feature",
  "properties": {
    "addr:full":"552 Compton Rd Cincinnati OH 45231",
    "addr:housenumber":"552",
    "addr:postcode":"45231",
    "addr:street":"Compton Rd",
    "iso:country":"US",
    "sg:address":"552 Compton Rd",
    "sg:city":"Cincinnati",
    "sg:classifiers":[
        {
            "category":"Organizations",
            "subcategory":"Religious Organization",
            "type":"Services"
        }
    ],
    "sg:phone":"+1 513 522 2966",
    "sg:postcode":"45231",
    "sg:province":"OH",
    "sg:tags":[
        "clergy"
    ],
    "wof:name":"Jeffrey A Hosmer",
    "wof:placetype":"venue"
},
  "geometry": {"coordinates":[-84.500719,39.228227],"type":"Point"}
}