{
  "type": "Feature",
  "properties": {
    "addr:full":"2176 Donald Rd Bethel OH 45106",
    "addr:housenumber":"2176",
    "addr:postcode":"45106",
    "addr:street":"Donald Rd",
    "iso:country":"US",
    "sg:address":"2176 Donald Rd",
    "sg:city":"Bethel",
    "sg:classifiers":[
        {
            "category":"Professional",
            "subcategory":"Engineering",
            "type":"Services"
        }
    ],
    "sg:phone":"+1 513 734 3532",
    "sg:postcode":"45106",
    "sg:province":"OH",
    "sg:tags":[
        "engineer"
    ],
    "wof:name":"Pid Engineering",
    "wof:placetype":"venue"
},
  "geometry": {"coordinates":[-84.07571,38.925711],"type":"Point"}
}