{
  "type": "Feature",
  "properties": {
    "addr:full": "2876 S Arlington Rd Akron OH 44312",
    "addr:housenumber": "2876",
    "addr:postcode": "44312",
    "addr:street": "S Arlington Rd",
    "iso:country": "US",
    "sg:address": "2876 S Arlington Rd",
    "sg:city": "Akron",
    "sg:classifiers": [
      {
        "category": "Insurance",
        "subcategory": "Insurance Agent",
        "type": "Services"
      }
    ],
    "sg:phone": "+1 330 645 6338",
    "sg:postcode": "44312",
    "sg:province": "OH",
    "sg:website": "www.auiinc.com",
    "wof:name": "Associated Underwriters Ins",
    "wof:placetype": "venue"
  },
  "geometry": {"coordinates":[-81.492377,40.991985],"type":"Point"}
}
