{
  "type": "Feature",
  "properties": {
    "iso:country":"US",
    "sg:address":"814 Shanahan Rd",
    "sg:city":"Lewis Center",
    "sg:classifiers":[
        {
            "category":"Organizations",
            "subcategory":"Religious Organization",
            "type":"Services"
        }
    ],
    "sg:phone":"+1 740 549 2511",
    "sg:postcode":"43035",
    "sg:province":"OH",
    "sg:tags":[
        "church"
    ],
    "sg:website":"www.northmetrochurch.com",
    "wof:name":"North Metro Church",
    "wof:placetype":"venue"
},
  "geometry": {"coordinates":[-83.02857299999999,40.213565],"type":"Point"}
}