{
  "type": "Feature",
  "properties": {
    "iso:country":"US",
    "sg:address":"131 N Main St",
    "sg:city":"North Canton",
    "sg:classifiers":[
        {
            "category":"Personal",
            "subcategory":"Beauty Salon",
            "type":"Services"
        }
    ],
    "sg:phone":"+1 330 244 1704",
    "sg:postcode":"44720",
    "sg:province":"OH",
    "wof:name":"Perry's Creation",
    "wof:placetype":"venue"
},
  "geometry": {"coordinates":[-81.402497,40.876786],"type":"Point"}
}