{
  "type": "Feature",
  "properties": {
    "addr:full":"137 Beaver Pike Waverly OH 45690",
    "addr:housenumber":"137",
    "addr:postcode":"45690",
    "addr:street":"Beaver Pike",
    "iso:country":"US",
    "sg:address":"137 Beaver Pike",
    "sg:city":"Waverly",
    "sg:classifiers":[
        {
            "category":"Shopping",
            "subcategory":"Department Store",
            "type":"Retail Goods"
        }
    ],
    "sg:phone":"+1 740 226 1952",
    "sg:postcode":"45690",
    "sg:province":"OH",
    "sg:tags":[
        "shop"
    ],
    "wof:name":"D D's Bargain House",
    "wof:placetype":"venue"
},
  "geometry": {"coordinates":[-82.923875,39.053144],"type":"Point"}
}