{
  "type": "Feature",
  "properties": {
    "iso:country":"US",
    "sg:address":"208 Jefferson St",
    "sg:city":"Germantown",
    "sg:classifiers":[
        {
            "category":"Food & Beverages",
            "subcategory":"Liquor & Beverages",
            "type":"Retail Goods"
        }
    ],
    "sg:phone":"+1 937 855 2230",
    "sg:postcode":"45327",
    "sg:province":"OH",
    "sg:tags":[
        "eating",
        "alcoholic"
    ],
    "wof:name":"Germantown Drive-Thru",
    "wof:placetype":"venue"
},
  "geometry": {"coordinates":[-84.36596299999999,39.622874],"type":"Point"}
}