{
  "type": "Feature",
  "properties": {
    "addr:full": "208 Jefferson St Germantown OH 45327",
    "addr:housenumber": "208",
    "addr:postcode": "45327",
    "addr:street": "Jefferson St",
    "iso:country": "US",
    "sg:address": "208 Jefferson St",
    "sg:city": "Germantown",
    "sg:classifiers": [
      {
        "category": "Food \u0026 Beverages",
        "subcategory": "Liquor \u0026 Beverages",
        "type": "Retail Goods"
      }
    ],
    "sg:phone": "+1 937 855 2230",
    "sg:postcode": "45327",
    "sg:province": "OH",
    "sg:tags": [
      "eating",
      "alcoholic"
    ],
    "wof:name": "Germantown Drive-Thru",
    "wof:placetype": "venue"
  },
  "geometry": {"coordinates":[-84.365963,39.622874],"type":"Point"}
}
