{
  "type": "Feature",
  "properties": {
    "iso:country":"US",
    "sg:address":"1155 Atwater Ave",
    "sg:city":"Circleville",
    "sg:classifiers":[
        {
            "category":"Health Services",
            "subcategory":"Health Practitioner",
            "type":"Services"
        }
    ],
    "sg:phone":"+1 614 837 5932",
    "sg:postcode":"43113",
    "sg:province":"OH",
    "sg:tags":[
        "nurse",
        "registry"
    ],
    "sg:website":"www.sunh.com",
    "wof:name":"Americare Circleville Nurse",
    "wof:placetype":"venue"
},
  "geometry": {"coordinates":[-82.936696,39.620466],"type":"Point"}
}