{
  "type": "Feature",
  "properties": {
    "addr:full": "6649 N High St Columbus OH 43085",
    "addr:housenumber": "6649",
    "addr:postcode": "43085",
    "addr:street": "N High St",
    "iso:country": "US",
    "sg:address": "6649 N High St",
    "sg:city": "Columbus",
    "sg:classifiers": [
      {
        "category": "Professional",
        "type": "Services"
      },
      {
        "category": "Health Services",
        "subcategory": "Doctor",
        "type": "Services"
      }
    ],
    "sg:phone": "+1 614 885 4754",
    "sg:postcode": "43085",
    "sg:province": "OH",
    "sg:tags": [
      "dentist"
    ],
    "wof:name": "Charles T Schindler DDS",
    "wof:placetype": "venue"
  },
  "geometry": {"coordinates":[-83.0173,40.10222],"type":"Point"}
}
