{
  "type": "Feature",
  "properties": {
    "iso:country":"US",
    "sg:address":"686 Grandview Ave",
    "sg:city":"Columbus",
    "sg:classifiers":[
        {
            "category":"Retail",
            "subcategory":"Auto Rental",
            "type":"Services"
        }
    ],
    "sg:phone":"+1 614 486 5988",
    "sg:postcode":"43215",
    "sg:province":"OH",
    "sg:tags":[
        "renting",
        "truck",
        "leasing"
    ],
    "sg:website":"www.economicleasing.com",
    "wof:name":"Economic Leasing",
    "wof:placetype":"venue"
},
  "geometry": {"coordinates":[-83.045843,39.97083],"type":"Point"}
}