{
  "type": "Feature",
  "properties": {
    "addr:full": "265 W Riverview Ave Napoleon OH 43545",
    "addr:housenumber": "265",
    "addr:postcode": "43545",
    "addr:street": "W Riverview Ave",
    "iso:country": "US",
    "sg:address": "265 W Riverview Ave",
    "sg:city": "Napoleon",
    "sg:classifiers": [
      {
        "category": "Government",
        "subcategory": "Fire Station",
        "type": "Public Place"
      }
    ],
    "sg:phone": "+1 419 592 0441",
    "sg:postcode": "43545",
    "sg:province": "OH",
    "sg:tags": [
      "department"
    ],
    "wof:name": "Napoleon City Rescue Squad",
    "wof:placetype": "venue"
  },
  "geometry": {"coordinates":[-84.127412,41.386897],"type":"Point"}
}
