{
  "type": "Feature",
  "properties": {
    "iso:country":"US",
    "sg:address":"8660 Twinbrook Rd",
    "sg:city":"Mentor",
    "sg:classifiers":[
        {
            "category":"Building & Trades",
            "subcategory":"Landscaping Services",
            "type":"Services"
        }
    ],
    "sg:phone":"+1 440 205 1325",
    "sg:postcode":"44060",
    "sg:province":"OH",
    "sg:tags":[
        "lawn",
        "maintenance",
        "grounds"
    ],
    "wof:name":"Dyna Green",
    "wof:placetype":"venue"
},
  "geometry": {"coordinates":[-81.327174,41.687181],"type":"Point"}
}