{
  "type": "Feature",
  "properties": {
    "iso:country":"US",
    "sg:address":"125 N Main St",
    "sg:city":"Marysville",
    "sg:classifiers":[
        {
            "category":"Shopping",
            "subcategory":"Clothing, Apparel, & Fashions",
            "type":"Retail Goods"
        }
    ],
    "sg:phone":"+1 937 642 4492",
    "sg:postcode":"43040",
    "sg:province":"OH",
    "sg:tags":[
        "shop",
        "bridal"
    ],
    "wof:name":"Wedding Designs & Tj Texedos",
    "wof:placetype":"venue"
},
  "geometry": {"coordinates":[-83.366908,40.237245],"type":"Point"}
}