{
  "type": "Feature",
  "properties": {
    "iso:country":"US",
    "sg:address":"2589 W Galbraith Rd",
    "sg:city":"Cincinnati",
    "sg:classifiers":[
        {
            "category":"Food & Beverages",
            "subcategory":"Bakery",
            "type":"Retail Goods"
        }
    ],
    "sg:phone":"+1 513 522 9122",
    "sg:postcode":"45239",
    "sg:province":"OH",
    "wof:name":"Butternut Bread",
    "wof:placetype":"venue"
},
  "geometry": {"coordinates":[-84.575335,39.219326],"type":"Point"}
}