{
  "type": "Feature",
  "properties": {
    "iso:country":"US",
    "sg:address":"343 S Main St",
    "sg:city":"Kenton",
    "sg:classifiers":[
        {
            "category":"Retail",
            "subcategory":"Auto Repair",
            "type":"Services"
        }
    ],
    "sg:phone":"+1 419 673 4197",
    "sg:postcode":"43326",
    "sg:province":"OH",
    "sg:tags":[
        "repairing",
        "automobile"
    ],
    "wof:name":"Stephens Auto Ctr",
    "wof:placetype":"venue"
},
  "geometry": {"coordinates":[-83.608045,40.644043],"type":"Point"}
}