{
  "type": "Feature",
  "properties": {
    "iso:country":"US",
    "sg:address":"27 Potowatomie Trl",
    "sg:city":"Milford",
    "sg:classifiers":[
        {
            "category":"Shopping",
            "subcategory":"Hobbies, Toys, & Games",
            "type":"Retail Goods"
        }
    ],
    "sg:phone":"+1 513 831 3528",
    "sg:postcode":"45150",
    "sg:province":"OH",
    "wof:name":"Beanie Expo",
    "wof:placetype":"venue"
},
  "geometry": {"coordinates":[-84.281431,39.171408],"type":"Point"}
}