{
  "type": "Feature",
  "properties": {
    "addr:full": "5615 Angola Rd Toledo OH 43615",
    "addr:housenumber": "5615",
    "addr:postcode": "43615",
    "addr:street": "Angola Rd",
    "iso:country": "US",
    "sg:address": "5615 Angola Rd",
    "sg:city": "Toledo",
    "sg:classifiers": [
      {
        "category": "Retail",
        "subcategory": "Auto Repair",
        "type": "Services"
      }
    ],
    "sg:phone": "+1 419 867 9807",
    "sg:postcode": "43615",
    "sg:province": "OH",
    "sg:tags": [
      "wrecker"
    ],
    "wof:name": "Ray Jeffers Svc Ctr \u0026 Towing",
    "wof:placetype": "venue"
  },
  "geometry": {"coordinates":[-83.679045,41.623817],"type":"Point"}
}
