{
  "type": "Feature",
  "properties": {
    "iso:country":"US",
    "sg:address":"35 W Columbus St",
    "sg:city":"Mount Sterling",
    "sg:classifiers":[
        {
            "category":"Autos & Motor Vehicles",
            "subcategory":"Fuel & Gas Station",
            "type":"Retail Goods"
        }
    ],
    "sg:phone":"+1 740 869 3555",
    "sg:postcode":"43143",
    "sg:province":"OH",
    "sg:tags":[
        "convenience",
        "store"
    ],
    "wof:name":"Sterling One Stop",
    "wof:placetype":"venue"
},
  "geometry": {"coordinates":[-83.26555500000001,39.718805],"type":"Point"}
}