{
  "type": "Feature",
  "properties": {
    "addr:full": "35 W Columbus St Mount Sterling OH 43143",
    "addr:housenumber": "35",
    "addr:postcode": "43143",
    "addr:street": "W Columbus St",
    "iso:country": "US",
    "sg:address": "35 W Columbus St",
    "sg:city": "Mount Sterling",
    "sg:classifiers": [
      {
        "category": "Autos \u0026 Motor Vehicles",
        "subcategory": "Fuel \u0026 Gas Station",
        "type": "Retail Goods"
      }
    ],
    "sg:phone": "+1 740 869 3555",
    "sg:postcode": "43143",
    "sg:province": "OH",
    "sg:tags": [
      "convenience",
      "store"
    ],
    "wof:name": "Sterling One Stop",
    "wof:placetype": "venue"
  },
  "geometry": {"coordinates":[-83.265555,39.718805],"type":"Point"}
}
