{
  "type": "Feature",
  "properties": {
    "iso:country":"US",
    "sg:address":"56490 S Winning St",
    "sg:city":"Bridgeport",
    "sg:classifiers":[
        {
            "category":"Insurance",
            "subcategory":"Life Insurance",
            "type":"Services"
        }
    ],
    "sg:phone":"+1 740 635 0643",
    "sg:postcode":"43912",
    "sg:province":"OH",
    "sg:tags":[
        "carrier"
    ],
    "wof:name":"Slovene National Benefit Soc",
    "wof:placetype":"venue"
},
  "geometry": {"coordinates":[-80.767589,40.064317],"type":"Point"}
}