{
  "type": "Feature",
  "properties": {
    "iso:country":"US",
    "sg:address":"11283 Fancher Rd",
    "sg:city":"Westerville",
    "sg:classifiers":[
        {
            "category":"Building & Trades",
            "subcategory":"Landscaping Services",
            "type":"Services"
        }
    ],
    "sg:phone":"+1 614 855 4500",
    "sg:postcode":"43082",
    "sg:province":"OH",
    "sg:tags":[
        "sanitary"
    ],
    "wof:name":"Agronomics Inc",
    "wof:placetype":"venue"
},
  "geometry": {"coordinates":[-82.832287,40.133347],"type":"Point"}
}