{
  "type": "Feature",
  "properties": {
    "iso:country":"US",
    "sg:address":"4498 Cemetery Rd",
    "sg:city":"Hilliard",
    "sg:classifiers":[
        {
            "category":"Insurance",
            "subcategory":"Insurance Agent",
            "type":"Services"
        }
    ],
    "sg:phone":"+1 614 771 9339",
    "sg:postcode":"43026",
    "sg:province":"OH",
    "wof:name":"State Farm Insurance",
    "wof:placetype":"venue"
},
  "geometry": {"coordinates":[-83.13606900000001,40.032148],"type":"Point"}
}