{
  "type": "Feature",
  "properties": {
    "iso:country":"US",
    "sg:address":"230 Harding St",
    "sg:city":"Medina",
    "sg:classifiers":[
        {
            "category":"Building & Trades",
            "subcategory":"Landscaping Services",
            "type":"Services"
        }
    ],
    "sg:phone":"+1 330 723 3312",
    "sg:postcode":"44256",
    "sg:province":"OH",
    "sg:tags":[
        "landscape"
    ],
    "wof:name":"Rustic Landscapes & Lawncare",
    "wof:placetype":"venue"
},
  "geometry": {"coordinates":[-81.860823,41.148886],"type":"Point"}
}