{
  "type": "Feature",
  "properties": {
    "addr:full": "2700 Weaver Rd Batavia OH 45103",
    "addr:housenumber": "2700",
    "addr:postcode": "45103",
    "addr:street": "Weaver Rd",
    "iso:country": "US",
    "sg:address": "2700 Weaver Rd",
    "sg:city": "Batavia",
    "sg:classifiers": [
      {
        "category": "Professional",
        "subcategory": "Business Services",
        "type": "Services"
      }
    ],
    "sg:phone": "+1 513 625 5200",
    "sg:postcode": "45103",
    "sg:province": "OH",
    "wof:name": "Cronenberg \u0026 Co Inc",
    "wof:placetype": "venue"
  },
  "geometry": {"coordinates":[-84.093997,39.163164],"type":"Point"}
}
