{
  "type": "Feature",
  "properties": {
    "iso:country":"US",
    "sg:address":"2700 Weaver Rd",
    "sg:city":"Batavia",
    "sg:classifiers":[
        {
            "category":"Professional",
            "subcategory":"Business Services",
            "type":"Services"
        }
    ],
    "sg:phone":"+1 513 625 5200",
    "sg:postcode":"45103",
    "sg:province":"OH",
    "wof:name":"Cronenberg & Co Inc",
    "wof:placetype":"venue"
},
  "geometry": {"coordinates":[-84.093997,39.163164],"type":"Point"}
}