{
  "type": "Feature",
  "properties": {
    "addr:full": "1520 Cutlip Rd Jackson OH 45640",
    "addr:housenumber": "1520",
    "addr:postcode": "45640",
    "addr:street": "Cutlip Rd",
    "iso:country": "US",
    "sg:address": "1520 Cutlip Rd",
    "sg:city": "Jackson",
    "sg:classifiers": [
      {
        "category": "Farming",
        "subcategory": "Farm",
        "type": "Manufacturing \u0026 Wholesale Goods"
      }
    ],
    "sg:phone": "+1 740 286 5464",
    "sg:postcode": "45640",
    "sg:province": "OH",
    "sg:tags": [
      "crop",
      "general"
    ],
    "wof:name": "Robert Sickles",
    "wof:placetype": "venue"
  },
  "geometry": {"coordinates":[-82.582152,39.043028],"type":"Point"}
}
