{
  "type": "Feature",
  "properties": {
    "addr:full":"512 Reading Rd Cincinnati OH 45202",
    "addr:housenumber":"512",
    "addr:postcode":"45202",
    "addr:street":"Reading Rd",
    "iso:country":"US",
    "sg:address":"512 Reading Rd",
    "sg:city":"Cincinnati",
    "sg:classifiers":[
        {
            "category":"Wholesale",
            "subcategory":"Construction Materials",
            "type":"Manufacturing & Wholesale Goods"
        }
    ],
    "sg:phone":"+1 513 621 4777",
    "sg:postcode":"45202",
    "sg:province":"OH",
    "sg:tags":[
        "tile",
        "stone",
        "wood",
        "natural",
        "cork"
    ],
    "wof:name":"Ray Carr & Associates Inc",
    "wof:placetype":"venue"
},
  "geometry": {"coordinates":[-84.504402,39.110021],"type":"Point"}
}