{
  "type": "Feature",
  "properties": {
    "addr:full": "625 Central Ave Franklin OH 45005",
    "addr:housenumber": "625",
    "addr:postcode": "45005",
    "addr:street": "Central Ave",
    "iso:country": "US",
    "sg:address": "625 Central Ave",
    "sg:city": "Franklin",
    "sg:classifiers": [
      {
        "category": "Retail",
        "subcategory": "Repair Shop",
        "type": "Services"
      }
    ],
    "sg:phone": "+1 937 746 4037",
    "sg:postcode": "45005",
    "sg:province": "OH",
    "sg:tags": [
      "appliance"
    ],
    "wof:name": "A-1 Appliance Svc",
    "wof:placetype": "venue"
  },
  "geometry": {"coordinates":[-84.318505,39.581424],"type":"Point"}
}
