{
  "type": "Feature",
  "properties": {
    "iso:country":"US",
    "sg:address":"6095 Meyer Rd",
    "sg:city":"Celina",
    "sg:classifiers":[
        {
            "category":"Building & Trades",
            "subcategory":"Landscaping Services",
            "type":"Services"
        }
    ],
    "sg:phone":"+1 419 586 1900",
    "sg:postcode":"45822",
    "sg:province":"OH",
    "sg:tags":[
        "landscape",
        "contractor"
    ],
    "wof:name":"Lovely Lawn Care Co",
    "wof:placetype":"venue"
},
  "geometry": {"coordinates":[-84.590459,40.525231],"type":"Point"}
}