{
  "type": "Feature",
  "properties": {
    "addr:full":"2639 Wooster Rd Cleveland OH 44116",
    "addr:housenumber":"2639",
    "addr:postcode":"44116",
    "addr:street":"Wooster Rd",
    "iso:country":"US",
    "sg:address":"2639 Wooster Rd",
    "sg:city":"Cleveland",
    "sg:classifiers":[
        {
            "category":"Professional",
            "subcategory":"Employment Agencies",
            "type":"Services"
        },
        {
            "category":"Health Services",
            "subcategory":"Doctor",
            "type":"Services"
        }
    ],
    "sg:phone":"+1 440 331 9520",
    "sg:postcode":"44116",
    "sg:province":"OH",
    "sg:tags":[
        "physician",
        "surgeon",
        "help",
        "supply"
    ],
    "sg:website":"www.lakelandemergency.com",
    "wof:name":"Lakeland Emergency Associates",
    "wof:placetype":"venue"
},
  "geometry": {"coordinates":[-81.836744,41.470459],"type":"Point"}
}