{
  "type": "Feature",
  "properties": {
    "addr:full": "2250 N High St Columbus OH 43201",
    "addr:housenumber": "2250",
    "addr:postcode": "43201",
    "addr:street": "N High St",
    "iso:country": "US",
    "sg:address": "2250 N High St",
    "sg:city": "Columbus",
    "sg:classifiers": [
      {
        "category": "Restaurant",
        "type": "Food \u0026 Drink"
      }
    ],
    "sg:phone": "+1 614 299 2672",
    "sg:postcode": "43201",
    "sg:province": "OH",
    "sg:tags": [
      "eating"
    ],
    "wof:name": "KAFE Kerouak",
    "wof:placetype": "venue"
  },
  "geometry": {"coordinates":[-83.009914,40.009102],"type":"Point"}
}
