{
  "type": "Feature",
  "properties": {
    "iso:country":"US",
    "sg:address":"2250 N High St",
    "sg:city":"Columbus",
    "sg:classifiers":[
        {
            "category":"Restaurant",
            "type":"Food & Drink"
        }
    ],
    "sg:phone":"+1 614 299 2672",
    "sg:postcode":"43201",
    "sg:province":"OH",
    "sg:tags":[
        "eating"
    ],
    "wof:name":"KAFE Kerouak",
    "wof:placetype":"venue"
},
  "geometry": {"coordinates":[-83.00991399999999,40.009102],"type":"Point"}
}