{
  "type": "Feature",
  "properties": {
    "addr:full":"4635 Bell Station Rd Circleville OH 43113",
    "addr:housenumber":"4635",
    "addr:postcode":"43113",
    "addr:street":"Bell Station Rd",
    "iso:country":"US",
    "sg:address":"4635 Bell Station Rd",
    "sg:city":"Circleville",
    "sg:classifiers":[
        {
            "category":"Building & Trades",
            "subcategory":"Construction",
            "type":"Services"
        }
    ],
    "sg:phone":"+1 740 474 5538",
    "sg:postcode":"43113",
    "sg:province":"OH",
    "sg:tags":[
        "house"
    ],
    "wof:name":"Webers Construction",
    "wof:placetype":"venue"
},
  "geometry": {"coordinates":[-82.938802,39.653673],"type":"Point"}
}