{
  "type": "Feature",
  "properties": {
    "iso:country":"US",
    "sg:address":"17985 Co Rd 60",
    "sg:city":"Grover Hill",
    "sg:classifiers":[
        {
            "category":"Real Estate",
            "subcategory":"Real Estate Agent",
            "type":"Services"
        }
    ],
    "sg:phone":"+1 419 587 3440",
    "sg:postcode":"45849",
    "sg:province":"OH",
    "wof:name":"Trinn",
    "wof:placetype":"venue"
},
  "geometry": {"coordinates":[-84.495317,41.048274],"type":"Point"}
}