{
  "type": "Feature",
  "properties": {
    "iso:country":"US",
    "sg:address":"882 N High St",
    "sg:city":"Worthington",
    "sg:classifiers":[
        {
            "category":"Building & Trades",
            "subcategory":"Construction",
            "type":"Services"
        }
    ],
    "sg:phone":"+1 614 846 2392",
    "sg:postcode":"43085",
    "sg:province":"OH",
    "sg:tags":[
        "repairing",
        "remodeling",
        "contractor"
    ],
    "wof:name":"Sexton Parsons Remodeling",
    "wof:placetype":"venue"
},
  "geometry": {"coordinates":[-83.017771,40.092766],"type":"Point"}
}