{
  "type": "Feature",
  "properties": {
    "addr:full":"1901b S Alex Rd Dayton OH 45449",
    "addr:housenumber":"1901b",
    "addr:postcode":"45449",
    "addr:street":"S Alex Rd",
    "iso:country":"US",
    "sg:address":"1901b S Alex Rd",
    "sg:city":"Dayton",
    "sg:classifiers":[
        {
            "category":"Restaurant",
            "type":"Food & Drink"
        }
    ],
    "sg:menulink":"http://www.allmenus.com/oh/west-carrollton-city/134258-subway/menu/",
    "sg:phone":"+1 937 866 0046",
    "sg:postcode":"45449",
    "sg:province":"OH",
    "sg:tags":[
        "american",
        "sandwich"
    ],
    "wof:name":"Subway",
    "wof:placetype":"venue"
},
  "geometry": {"coordinates":[-84.242952,39.64787],"type":"Point"}
}