{
  "type": "Feature",
  "properties": {
    "addr:full": "195 Saxe Rd Mogadore OH 44260",
    "addr:housenumber": "195",
    "addr:postcode": "44260",
    "addr:street": "Saxe Rd",
    "iso:country": "US",
    "sg:address": "195 Saxe Rd",
    "sg:city": "Mogadore",
    "sg:classifiers": [
      {
        "category": "Building \u0026 Trades",
        "subcategory": "Construction",
        "type": "Services"
      }
    ],
    "sg:phone": "+1 330 628 3165",
    "sg:postcode": "44260",
    "sg:province": "OH",
    "sg:tags": [
      "contractor"
    ],
    "wof:name": "Conleys Roofing",
    "wof:placetype": "venue"
  },
  "geometry": {"coordinates":[-81.382988,41.066127],"type":"Point"}
}
