{
  "type": "Feature",
  "properties": {
    "addr:full": "1549 Piketon Rd Lucasville OH 45648",
    "addr:housenumber": "1549",
    "addr:postcode": "45648",
    "addr:street": "Piketon Rd",
    "iso:country": "US",
    "sg:address": "1549 Piketon Rd",
    "sg:city": "Lucasville",
    "sg:phone": "+1 740 820 3629",
    "sg:postcode": "45648",
    "sg:province": "OH",
    "sg:tags": [
      "farm",
      "grain",
      "cash"
    ],
    "wof:name": "Charles Locher Farm",
    "wof:placetype": "venue"
  },
  "geometry": {"coordinates":[-82.8849,38.901406],"type":"Point"}
}
