{
  "type": "Feature",
  "properties": {
    "iso:country":"US",
    "sg:address":"14900 Kinsman Rd",
    "sg:city":"Cleveland",
    "sg:classifiers":[
        {
            "category":"Social Services",
            "subcategory":"Child Care",
            "type":"Services"
        }
    ],
    "sg:phone":"+1 216 752 6468",
    "sg:postcode":"44120",
    "sg:province":"OH",
    "wof:name":"Nicole's Child Care Ctr Inc",
    "wof:placetype":"venue"
},
  "geometry": {"coordinates":[-81.576247,41.464389],"type":"Point"}
}