{
  "type": "Feature",
  "properties": {
    "iso:country":"US",
    "sg:address":"1494 Compton Rd",
    "sg:city":"Cincinnati",
    "sg:classifiers":[
        {
            "category":"Building & Trades",
            "subcategory":"Plumbing",
            "type":"Services"
        }
    ],
    "sg:phone":"+1 513 521 8627",
    "sg:postcode":"45231",
    "sg:province":"OH",
    "sg:tags":[
        "plumbing",
        "contractor"
    ],
    "wof:name":"Plum Perfect Plumbing",
    "wof:placetype":"venue"
},
  "geometry": {"coordinates":[-84.54257800000001,39.231959],"type":"Point"}
}