{
  "type": "Feature",
  "properties": {
    "addr:full": "1047 Eaton Ave Hamilton IN 45013",
    "addr:housenumber": "1047",
    "addr:postcode": "45013",
    "addr:street": "Eaton Ave",
    "iso:country": "US",
    "sg:address": "1047 Eaton Ave",
    "sg:city": "Hamilton",
    "sg:classifiers": [
      {
        "category": "Shopping",
        "subcategory": "Clothing, Apparel, \u0026 Fashions",
        "type": "Retail Goods"
      }
    ],
    "sg:phone": "+1 513 868 7800",
    "sg:postcode": "45013",
    "sg:province": "IN",
    "sg:tags": [
      "dance",
      "accessory"
    ],
    "wof:name": "Backstage",
    "wof:placetype": "venue"
  },
  "geometry": {"coordinates":[-84.576793,39.423389],"type":"Point"}
}
