{
  "type": "Feature",
  "properties": {
    "addr:full": "26060 Hurlingham Rd Cleveland OH 44122",
    "addr:postcode": "26060;44122",
    "addr:street": "Hurlingham Rd",
    "iso:country": "US",
    "sg:address": "26060 Hurlingham Rd",
    "sg:city": "Cleveland",
    "sg:classifiers": [
      {
        "category": "Insurance",
        "subcategory": "Insurance Agent",
        "type": "Services"
      }
    ],
    "sg:phone": "+1 216 831 6280",
    "sg:postcode": "44122",
    "sg:province": "OH",
    "wof:name": "Eckley Insurance Agency",
    "wof:placetype": "venue"
  },
  "geometry": {"coordinates":[-81.495289,41.480529],"type":"Point"}
}
