{
  "type": "Feature",
  "properties": {
    "addr:full": "5475 Canyon Ridge Dr Painesville OH 44077",
    "addr:housenumber": "5475",
    "addr:postcode": "44077",
    "addr:street": "Canyon Ridge Dr",
    "iso:country": "US",
    "sg:address": "5475 Canyon Ridge Dr",
    "sg:city": "Painesville",
    "sg:classifiers": [
      {
        "category": "Professional",
        "type": "Services"
      }
    ],
    "sg:phone": "+1 440 357 4440",
    "sg:postcode": "44077",
    "sg:province": "OH",
    "wof:name": "Robert J Dawson",
    "wof:placetype": "venue"
  },
  "geometry": {"coordinates":[-81.189978,41.720514],"type":"Point"}
}
