{
  "type": "Feature",
  "properties": {
    "addr:full": "6170 N Summit St Toledo OH 43611",
    "addr:housenumber": "6170",
    "addr:postcode": "43611",
    "addr:street": "N Summit St",
    "iso:country": "US",
    "sg:address": "6170 N Summit St",
    "sg:city": "Toledo",
    "sg:classifiers": [
      {
        "category": "Health Services",
        "subcategory": "Doctor",
        "type": "Services"
      }
    ],
    "sg:phone": "+1 419 729 2462",
    "sg:postcode": "43611",
    "sg:province": "OH",
    "wof:name": "George F Osborne DDS",
    "wof:placetype": "venue"
  },
  "geometry": {"coordinates":[-83.479647,41.73149],"type":"Point"}
}
