{
  "type": "Feature",
  "properties": {
    "addr:full":"1177 S Main St Canton OH 44720",
    "addr:housenumber":"1177",
    "addr:postcode":"44720",
    "addr:street":"S Main St",
    "iso:country":"US",
    "sg:address":"1177 S Main St",
    "sg:city":"Canton",
    "sg:classifiers":[
        {
            "category":"Banks & Credit Unions",
            "subcategory":"Investment Brokerage",
            "type":"Services"
        }
    ],
    "sg:phone":"+1 330 494 0010",
    "sg:postcode":"44720",
    "sg:province":"OH",
    "sg:tags":[
        "security"
    ],
    "wof:name":"IDS Financial Services Inc",
    "wof:placetype":"venue"
},
  "geometry": {"coordinates":[-81.398094,40.866506],"type":"Point"}
}