{
  "type": "Feature",
  "properties": {
    "addr:full":"220 N Wayne St Van Wert OH 45891",
    "addr:housenumber":"220",
    "addr:postcode":"45891",
    "addr:street":"N Wayne St",
    "iso:country":"US",
    "sg:address":"220 N Wayne St",
    "sg:city":"Van Wert",
    "sg:classifiers":[
        {
            "category":"Retail",
            "subcategory":"Car Wash",
            "type":"Services"
        }
    ],
    "sg:phone":"+1 419 238 5652",
    "sg:postcode":"45891",
    "sg:province":"OH",
    "sg:tags":[
        "polishing",
        "washing"
    ],
    "wof:name":"Hegemier Car Wash",
    "wof:placetype":"venue"
},
  "geometry": {"coordinates":[-84.56944300000001,40.871966],"type":"Point"}
}