{
  "type": "Feature",
  "properties": {
    "iso:country":"US",
    "sg:address":"1784 State Rte 63",
    "sg:city":"Lebanon",
    "sg:classifiers":[
        {
            "category":"Retail",
            "subcategory":"Animal Services",
            "type":"Services"
        }
    ],
    "sg:phone":"+1 513 932 2885",
    "sg:postcode":"45036",
    "sg:province":"OH",
    "sg:tags":[
        "breeder",
        "horse"
    ],
    "wof:name":"Shaker Hill-Morgan Horse Farm",
    "wof:placetype":"venue"
},
  "geometry": {"coordinates":[-84.239936,39.435463],"type":"Point"}
}