{
  "type": "Feature",
  "properties": {
    "addr:full": "155 Montrose West Ave Copley OH 44321",
    "addr:housenumber": "155",
    "addr:postcode": "44321",
    "addr:street": "Montrose West Ave",
    "iso:country": "US",
    "sg:address": "155 Montrose West Ave",
    "sg:city": "Copley",
    "sg:classifiers": [
      {
        "category": "Professional",
        "type": "Services"
      }
    ],
    "sg:phone": "+1 330 668 2802",
    "sg:postcode": "44321",
    "sg:province": "OH",
    "wof:name": "Comdisco Disaster Recovery Svc",
    "wof:placetype": "venue"
  },
  "geometry": {"coordinates":[-81.653518,41.130649],"type":"Point"}
}
