{
  "type": "Feature",
  "properties": {
    "iso:country":"US",
    "sg:address":"1257 Wildwood Rd",
    "sg:city":"Toledo",
    "sg:classifiers":[
        {
            "category":"Professional",
            "type":"Services"
        }
    ],
    "sg:phone":"+1 419 381 2620",
    "sg:postcode":"43614",
    "sg:province":"OH",
    "wof:name":"Maumee Watersports LLC",
    "wof:placetype":"venue"
},
  "geometry": {"coordinates":[-83.59311099999999,41.614096],"type":"Point"}
}