{
  "type": "Feature",
  "properties": {
    "addr:full": "150 E Main St Fl 3 Columbus OH 43215",
    "addr:housenumber": "150;3",
    "addr:postcode": "43215",
    "addr:street": "E Main St",
    "iso:country": "US",
    "sg:address": "150 E Main St Fl 3",
    "sg:city": "Columbus",
    "sg:classifiers": [
      {
        "category": "Professional",
        "subcategory": "Employment Agencies",
        "type": "Services"
      }
    ],
    "sg:phone": "+1 614 586 1270",
    "sg:postcode": "43215",
    "sg:province": "OH",
    "sg:tags": [
      "opportunity"
    ],
    "wof:name": "Groovejob.Com, Inc",
    "wof:placetype": "venue"
  },
  "geometry": {"coordinates":[-82.995071,39.956661],"type":"Point"}
}
