{
  "type": "Feature",
  "properties": {
    "addr:full": "411 Center St Ironton OH 45638",
    "addr:housenumber": "411",
    "addr:postcode": "45638",
    "addr:street": "Center St",
    "iso:country": "US",
    "sg:address": "411 Center St",
    "sg:city": "Ironton",
    "sg:classifiers": [
      {
        "category": "Professional",
        "subcategory": "Lawyer \u0026 Legal Services",
        "type": "Services"
      }
    ],
    "sg:phone": "+1 740 532 9000",
    "sg:postcode": "45638",
    "sg:province": "OH",
    "sg:tags": [
      "attorney"
    ],
    "wof:name": "Jeffrey W Smith",
    "wof:placetype": "venue"
  },
  "geometry": {"coordinates":[-82.683633,38.536605],"type":"Point"}
}
