{
  "type": "Feature",
  "properties": {
    "addr:full":"1655 W Market St Akron OH 44313",
    "addr:housenumber":"1655",
    "addr:postcode":"44313",
    "addr:street":"W Market St",
    "iso:country":"US",
    "sg:address":"1655 W Market St",
    "sg:city":"Akron",
    "sg:classifiers":[
        {
            "category":"Organizations",
            "subcategory":"Non-profit Organization",
            "type":"Services"
        }
    ],
    "sg:phone":"+1 330 867 5388",
    "sg:postcode":"44313",
    "sg:province":"OH",
    "sg:tags":[
        "information",
        "alcoholism",
        "treatment"
    ],
    "wof:name":"Callahan Petrou & Assocs Inc",
    "wof:placetype":"venue"
},
  "geometry": {"coordinates":[-81.56874999999999,41.109338],"type":"Point"}
}