{
  "type": "Feature",
  "properties": {
    "addr:full": "3311 Rohrer Rd Wadsworth OH 44281",
    "addr:housenumber": "3311",
    "addr:postcode": "44281",
    "addr:street": "Rohrer Rd",
    "iso:country": "US",
    "sg:address": "3311 Rohrer Rd",
    "sg:city": "Wadsworth",
    "sg:classifiers": [
      {
        "category": "Freight",
        "type": "Transportation"
      }
    ],
    "sg:phone": "+1 330 336 5114",
    "sg:postcode": "44281",
    "sg:province": "OH",
    "sg:tags": [
      "operator",
      "local",
      "trucking"
    ],
    "wof:name": "Swain Express Inc",
    "wof:placetype": "venue"
  },
  "geometry": {"coordinates":[-81.806578,41.035802],"type":"Point"}
}
