{
  "type": "Feature",
  "properties": {
    "addr:full": "2970 Benchmark Dr Columbus OH 43219",
    "addr:housenumber": "2970",
    "addr:postcode": "43219",
    "addr:street": "Benchmark Dr",
    "iso:country": "US",
    "sg:address": "2970 Benchmark Dr",
    "sg:city": "Columbus",
    "sg:classifiers": [
      {
        "category": "Building \u0026 Trades",
        "subcategory": "Construction",
        "type": "Services"
      }
    ],
    "sg:phone": "+1 614 478 4608",
    "sg:postcode": "43219",
    "sg:province": "OH",
    "sg:tags": [
      "general",
      "contractor"
    ],
    "wof:name": "Rockford Homes",
    "wof:placetype": "venue"
  },
  "geometry": {"coordinates":[-82.93252,40.030646],"type":"Point"}
}
