{
  "type": "Feature",
  "properties": {
    "addr:full": "1131 Verona Ave Youngstown OH 44506",
    "addr:housenumber": "1131",
    "addr:postcode": "44506",
    "addr:street": "Verona Ave",
    "iso:country": "US",
    "sg:address": "1131 Verona Ave",
    "sg:city": "Youngstown",
    "sg:classifiers": [
      {
        "category": "Real Estate",
        "subcategory": "Real Estate Operator",
        "type": "Services"
      }
    ],
    "sg:phone": "+1 330 743 6767",
    "sg:postcode": "44506",
    "sg:province": "OH",
    "sg:tags": [
      "building",
      "apartment"
    ],
    "wof:name": "Maplewood Manor",
    "wof:placetype": "venue"
  },
  "geometry": {"coordinates":[-80.629275,41.107842],"type":"Point"}
}
