{
  "type": "Feature",
  "properties": {
    "addr:full": "360 N Broad St Fairborn OH 45324",
    "addr:housenumber": "360",
    "addr:postcode": "45324",
    "addr:street": "N Broad St",
    "iso:country": "US",
    "sg:address": "360 N Broad St",
    "sg:city": "Fairborn",
    "sg:classifiers": [
      {
        "category": "Restaurant",
        "type": "Food \u0026 Drink"
      }
    ],
    "sg:menulink": "http://www.allmenus.com/oh/bath/213177-taco-bell/menu/",
    "sg:phone": "+1 937 879 7690",
    "sg:postcode": "45324",
    "sg:province": "OH",
    "sg:tags": [
      "mexican"
    ],
    "wof:name": "Taco Bell",
    "wof:placetype": "venue"
  },
  "geometry": {"coordinates":[-84.026001,39.827987],"type":"Point"}
}
