{
  "type": "Feature",
  "properties": {
    "addr:full": "5929 Andrews Rd Mentor On Lake OH 44060",
    "addr:housenumber": "5929",
    "addr:postcode": "lake;44060",
    "addr:street": "Andrews Rd",
    "iso:country": "US",
    "sg:address": "5929 Andrews Rd",
    "sg:city": "Mentor On Lake",
    "sg:classifiers": [
      {
        "category": "Shopping",
        "subcategory": "Pharmacy",
        "type": "Retail Goods"
      }
    ],
    "sg:phone": "+1 440 257 5995",
    "sg:postcode": "44060",
    "sg:province": "OH",
    "wof:name": "Marc's Mentor On The Lake",
    "wof:placetype": "venue"
  },
  "geometry": {"coordinates":[-81.361313,41.707377],"type":"Point"}
}
