{
  "type": "Feature",
  "properties": {
    "iso:country":"US",
    "sg:address":"310 Churchill Hubbard Rd",
    "sg:city":"Youngstown",
    "sg:classifiers":[
        {
            "category":"Real Estate",
            "subcategory":"Real Estate Services",
            "type":"Services"
        },
        {
            "category":"Professional",
            "subcategory":"Business Services",
            "type":"Services"
        },
        {
            "category":"Real Estate",
            "subcategory":"Surveying",
            "type":"Services"
        }
    ],
    "sg:phone":"+1 330 759 5062",
    "sg:postcode":"44505",
    "sg:province":"OH",
    "sg:tags":[
        "industrial",
        "appraisers-commercial",
        "appraiser"
    ],
    "sg:website":"http://www.jwoodsappraisals.com",
    "wof:name":"Woods John Jr & Assoc",
    "wof:placetype":"venue"
},
  "geometry": {"coordinates":[-80.660662,41.162286],"type":"Point"}
}