{
  "type": "Feature",
  "properties": {
    "addr:full": "400 Main St Wellsville OH 43968",
    "addr:housenumber": "400",
    "addr:postcode": "43968",
    "addr:street": "Main St",
    "iso:country": "US",
    "sg:address": "400 Main St",
    "sg:city": "Wellsville",
    "sg:classifiers": [
      {
        "category": "Restaurant",
        "type": "Food \u0026 Drink"
      }
    ],
    "sg:menulink": "http://www.allmenus.com/oh/wellsville/94112-a-m-river-grill/menu/",
    "sg:phone": "+1 330 532 4000",
    "sg:postcode": "43968",
    "sg:province": "OH",
    "sg:tags": [
      "american"
    ],
    "wof:name": "A M River Grill",
    "wof:placetype": "venue"
  },
  "geometry": {"coordinates":[-80.642728,40.609243],"type":"Point"}
}
