{
  "type": "Feature",
  "properties": {
    "addr:full": "1600 McClure Ln Malta OH 43758",
    "addr:housenumber": "1600",
    "addr:postcode": "43758",
    "addr:street": "Mcclure Ln",
    "iso:country": "US",
    "sg:address": "1600 McClure Ln",
    "sg:city": "Malta",
    "sg:classifiers": [
      {
        "category": "Manufacturing",
        "subcategory": "Printing",
        "type": "Manufacturing \u0026 Wholesale Goods"
      }
    ],
    "sg:phone": "+1 740 962 4003",
    "sg:postcode": "43758",
    "sg:province": "OH",
    "sg:tags": [
      "screen"
    ],
    "wof:name": "Amy's Custom T's",
    "wof:placetype": "venue"
  },
  "geometry": {"coordinates":[-81.914696,39.627398],"type":"Point"}
}
