{
  "type": "Feature",
  "properties": {
    "addr:full": "124 Burkhart Ave Cincinnati OH 45215",
    "addr:housenumber": "124",
    "addr:postcode": "45215",
    "addr:street": "Burkhart Ave",
    "iso:country": "US",
    "sg:address": "124 Burkhart Ave",
    "sg:city": "Cincinnati",
    "sg:classifiers": [
      {
        "category": "Professional",
        "type": "Services"
      }
    ],
    "sg:phone": "+1 513 761 6645",
    "sg:postcode": "45215",
    "sg:province": "OH",
    "wof:name": "On-Site Service",
    "wof:placetype": "venue"
  },
  "geometry": {"coordinates":[-84.449074,39.211516],"type":"Point"}
}
