{
  "type": "Feature",
  "properties": {
    "addr:full": "2974 E Powell Dr Lewis Center OH 43035",
    "addr:housenumber": "2974",
    "addr:postcode": "43035",
    "addr:street": "E Powell Dr",
    "iso:country": "US",
    "sg:address": "2974 E Powell Dr",
    "sg:city": "Lewis Center",
    "sg:classifiers": [
      {
        "category": "Building \u0026 Trades",
        "subcategory": "Construction",
        "type": "Services"
      }
    ],
    "sg:phone": "+1 614 985 1777",
    "sg:postcode": "43035",
    "sg:province": "OH",
    "sg:tags": [
      "home",
      "builder"
    ],
    "sg:website": "www.dominionhomes.com",
    "wof:name": "Dominion Homes Inc",
    "wof:placetype": "venue"
  },
  "geometry": {"coordinates":[-82.969707,40.155619],"type":"Point"}
}
