{
  "type": "Feature",
  "properties": {
    "iso:country":"US",
    "sg:address":"6427 State Rd",
    "sg:city":"Wadsworth",
    "sg:classifiers":[
        {
            "category":"Farming",
            "subcategory":"Farm",
            "type":"Manufacturing & Wholesale Goods"
        }
    ],
    "sg:phone":"+1 330 239 2517",
    "sg:postcode":"44281",
    "sg:province":"OH",
    "wof:name":"Nanbob Farms",
    "wof:placetype":"venue"
},
  "geometry": {"coordinates":[-81.716244,41.099198],"type":"Point"}
}