{
  "type": "Feature",
  "properties": {
    "iso:country":"US",
    "sg:address":"539 Windsor Park Dr",
    "sg:city":"Dayton",
    "sg:classifiers":[
        {
            "category":"Banks & Credit Unions",
            "subcategory":"Bank",
            "type":"Services"
        }
    ],
    "sg:phone":"+1 937 436 1500",
    "sg:postcode":"45459",
    "sg:province":"OH",
    "sg:tags":[
        "loan",
        "real estate"
    ],
    "wof:name":"Montgomery Mortgage Corp",
    "wof:placetype":"venue"
},
  "geometry": {"coordinates":[-84.17438799999999,39.630571],"type":"Point"}
}