{
  "type": "Feature",
  "properties": {
    "addr:full":"952 E Main St Ravenna OH 44266",
    "addr:housenumber":"952",
    "addr:postcode":"44266",
    "addr:street":"E Main St",
    "iso:country":"US",
    "sg:address":"952 E Main St",
    "sg:city":"Ravenna",
    "sg:classifiers":[
        {
            "category":"Restaurant",
            "type":"Food & Drink"
        }
    ],
    "sg:menulink":"http://www.allmenus.com/oh/ravenna/205898-ming-chu/menu/",
    "sg:phone":"+1 330 297 9033",
    "sg:postcode":"44266",
    "sg:province":"OH",
    "sg:tags":[
        "asian",
        "chinese"
    ],
    "wof:name":"Ming Chu",
    "wof:placetype":"venue"
},
  "geometry": {"coordinates":[-81.227114,41.157185],"type":"Point"}
}