{
  "type": "Feature",
  "properties": {
    "addr:full":"3286 S Waynesville Rd Morrow OH 45152",
    "addr:housenumber":"3286",
    "addr:postcode":"45152",
    "addr:street":"S Waynesville Rd",
    "iso:country":"US",
    "sg:address":"3286 S Waynesville Rd",
    "sg:city":"Morrow",
    "sg:classifiers":[
        {
            "category":"Farming",
            "subcategory":"Farm",
            "type":"Manufacturing & Wholesale Goods"
        }
    ],
    "sg:phone":"+1 513 899 3000",
    "sg:postcode":"45152",
    "sg:province":"OH",
    "wof:name":"White Oak Farm Number One",
    "wof:placetype":"venue"
},
  "geometry": {"coordinates":[-84.137019,39.378167],"type":"Point"}
}