{
  "type": "Feature",
  "properties": {
    "iso:country":"US",
    "sg:address":"6630 E US Rte 36",
    "sg:city":"Fletcher",
    "sg:phone":"+1 937 368 2590",
    "sg:postcode":"45326",
    "sg:province":"OH",
    "sg:tags":[
        "farm",
        "grain",
        "corn",
        "wheat",
        "cash"
    ],
    "wof:name":"Doug Cron Farms",
    "wof:placetype":"venue"
},
  "geometry": {"coordinates":[-84.077923,40.14298],"type":"Point"}
}