{
  "type": "Feature",
  "properties": {
    "addr:full":"6545 Warren-Sharon Rd Brookfield OH 44403",
    "addr:housenumber":"6545",
    "addr:postcode":"44403",
    "addr:street":"Warren-Sharon Rd",
    "iso:country":"US",
    "sg:address":"6545 Warren-Sharon Rd",
    "sg:city":"Brookfield",
    "sg:classifiers":[
        {
            "category":"Real Estate",
            "subcategory":"Real Estate Agent",
            "type":"Services"
        }
    ],
    "sg:phone":"+1 330 770 7407",
    "sg:postcode":"44403",
    "sg:province":"OH",
    "sg:tags":[
        "inspection"
    ],
    "wof:name":"Certified Home Inspections",
    "wof:placetype":"venue"
},
  "geometry": {"coordinates":[-80.58366700000001,41.235857],"type":"Point"}
}