{
  "type": "Feature",
  "properties": {
    "addr:full":"1851 State Rte 47 W Bellefontaine OH 43311",
    "addr:housenumber":"1851",
    "addr:postcode":"43311",
    "addr:street":"State Rte 47 W",
    "iso:country":"US",
    "sg:address":"1851 State Rte 47 W",
    "sg:city":"Bellefontaine",
    "sg:classifiers":[
        {
            "category":"Social Services",
            "subcategory":"Child Care",
            "type":"Services"
        }
    ],
    "sg:phone":"+1 937 292 7095",
    "sg:postcode":"43311",
    "sg:province":"OH",
    "wof:name":"Bellefontaine Child Devmnt Ctr",
    "wof:placetype":"venue"
},
  "geometry": {"coordinates":[-83.79713700000001,40.363384],"type":"Point"}
}