{
  "type": "Feature",
  "properties": {
    "addr:full": "5828 Riverton Rd Columbus OH 43232",
    "addr:housenumber": "5828",
    "addr:postcode": "43232",
    "addr:street": "Riverton Rd",
    "iso:country": "US",
    "sg:address": "5828 Riverton Rd",
    "sg:city": "Columbus",
    "sg:classifiers": [
      {
        "category": "Professional",
        "subcategory": "Computer Services",
        "type": "Services"
      }
    ],
    "sg:phone": "+1 614 751 8191",
    "sg:postcode": "43232",
    "sg:province": "OH",
    "sg:tags": [
      "programing",
      "custom"
    ],
    "wof:name": "Computer Advisors Inc",
    "wof:placetype": "venue"
  },
  "geometry": {"coordinates":[-82.840119,39.949721],"type":"Point"}
}
