{
  "type": "Feature",
  "properties": {
    "addr:full":"7536 Blacks Rd SW Pataskala OH 43062",
    "addr:housenumber":"7536",
    "addr:postcode":"43062",
    "addr:street":"Blacks Rd Sw",
    "iso:country":"US",
    "sg:address":"7536 Blacks Rd SW",
    "sg:city":"Pataskala",
    "sg:classifiers":[
        {
            "category":"Building & Trades",
            "subcategory":"Construction",
            "type":"Services"
        }
    ],
    "sg:phone":"+1 740 927 2850",
    "sg:postcode":"43062",
    "sg:province":"OH",
    "sg:tags":[
        "carpentry",
        "contractor"
    ],
    "wof:name":"Atkins Custom Cabinets",
    "wof:placetype":"venue"
},
  "geometry": {"coordinates":[-82.634062,39.999303],"type":"Point"}
}