{
  "type": "Feature",
  "properties": {
    "addr:full": "4172 Picador Rd SE Carrollton OH 44615",
    "addr:postcode": "4172;44615",
    "addr:street": "Picador Rd Se",
    "iso:country": "US",
    "sg:address": "4172 Picador Rd SE",
    "sg:city": "Carrollton",
    "sg:classifiers": [
      {
        "category": "Building \u0026 Trades",
        "subcategory": "Construction",
        "type": "Services"
      }
    ],
    "sg:phone": "+1 330 627 5227",
    "sg:postcode": "44615",
    "sg:province": "OH",
    "sg:tags": [
      "contractor"
    ],
    "wof:name": "T\u0026B Vinyl Siding",
    "wof:placetype": "venue"
  },
  "geometry": {"coordinates":[-81.093675,40.511045],"type":"Point"}
}
