{
  "type": "Feature",
  "properties": {
    "iso:country":"US",
    "sg:address":"119 Sibley St",
    "sg:city":"Van Wert",
    "sg:classifiers":[
        {
            "category":"Autos & Motor Vehicles",
            "subcategory":"Automobile Sales",
            "type":"Retail Goods"
        }
    ],
    "sg:phone":"+1 419 232 4275",
    "sg:postcode":"45891",
    "sg:province":"OH",
    "sg:tags":[
        "car",
        "dealer"
    ],
    "wof:name":"WELS Motor Sales",
    "wof:placetype":"venue"
},
  "geometry": {"coordinates":[-84.595595,40.87259],"type":"Point"}
}