{
  "type": "Feature",
  "properties": {
    "addr:full": "2307 E Aurora Rd Twinsburg OH 44087",
    "addr:housenumber": "2307",
    "addr:postcode": "44087",
    "addr:street": "E Aurora Rd",
    "iso:country": "US",
    "sg:address": "2307 E Aurora Rd",
    "sg:city": "Twinsburg",
    "sg:classifiers": [
      {
        "category": "Wholesale",
        "subcategory": "Machinery \u0026 Supplies",
        "type": "Manufacturing \u0026 Wholesale Goods"
      }
    ],
    "sg:phone": "+1 330 487 0702",
    "sg:postcode": "44087",
    "sg:province": "OH",
    "sg:tags": [
      "machine",
      "tool"
    ],
    "wof:name": "USA Industrial Inc",
    "wof:placetype": "venue"
  },
  "geometry": {"coordinates":[-81.457912,41.311402],"type":"Point"}
}
