{
  "type": "Feature",
  "properties": {
    "addr:full":"1708 Commerce Rd Holland OH 43528",
    "addr:housenumber":"1708",
    "addr:postcode":"43528",
    "addr:street":"Commerce Rd",
    "iso:country":"US",
    "sg:address":"1708 Commerce Rd",
    "sg:city":"Holland",
    "sg:classifiers":[
        {
            "category":"Wholesale",
            "subcategory":"Hardware",
            "type":"Manufacturing & Wholesale Goods"
        },
        {
            "category":"Building & Trades",
            "subcategory":"Cleaning & Sanitation",
            "type":"Services"
        }
    ],
    "sg:phone":"+1 419 867 7400",
    "sg:postcode":"43528",
    "sg:province":"OH",
    "sg:tags":[
        "repair",
        "odor",
        "testing",
        "system",
        "air",
        "ventilating"
    ],
    "sg:website":"www.cleanairinc.com",
    "wof:name":"Clean Air Systems Inc",
    "wof:placetype":"venue"
},
  "geometry": {"coordinates":[-83.79329799999999,41.609867],"type":"Point"}
}