{
  "type": "Feature",
  "properties": {
    "addr:full": "2801 Martin Luther King Jr Dr Cleveland OH 44104",
    "addr:housenumber": "2801",
    "addr:postcode": "44104",
    "addr:street": "Martin Luther King Jr Dr",
    "iso:country": "US",
    "sg:address": "2801 Martin Luther King Jr Dr",
    "sg:city": "Cleveland",
    "sg:classifiers": [
      {
        "category": "Professional",
        "subcategory": "Research",
        "type": "Services"
      }
    ],
    "sg:phone": "+1 216 231 5209",
    "sg:postcode": "44104",
    "sg:province": "OH",
    "sg:tags": [
      "laboratory"
    ],
    "wof:name": "Spectra Laboratories",
    "wof:placetype": "venue"
  },
  "geometry": {"coordinates":[-81.609242,41.482788],"type":"Point"}
}
