{
  "type": "Feature",
  "properties": {
    "iso:country":"US",
    "sg:address":"555 N Yearling Rd",
    "sg:city":"Columbus",
    "sg:classifiers":[
        {
            "category":"Manufacturing",
            "subcategory":"Metals",
            "type":"Manufacturing & Wholesale Goods"
        }
    ],
    "sg:phone":"+1 614 235 9805",
    "sg:postcode":"43213",
    "sg:province":"OH",
    "sg:tags":[
        "fabrication",
        "structural"
    ],
    "wof:name":"Canam Steel Corp",
    "wof:placetype":"venue"
},
  "geometry": {"coordinates":[-82.886273,39.986788],"type":"Point"}
}