{
  "type": "Feature",
  "properties": {
    "addr:full":"1 Donham Plz Middletown OH 45042",
    "addr:housenumber":"1",
    "addr:postcode":"45042",
    "addr:street":"Donham Plz",
    "iso:country":"US",
    "sg:address":"1 Donham Plz",
    "sg:city":"Middletown",
    "sg:classifiers":[
        {
            "category":"Government",
            "subcategory":"Police Station",
            "type":"Public Place"
        }
    ],
    "sg:phone":"+1 513 425 7748",
    "sg:postcode":"45042",
    "sg:province":"OH",
    "sg:tags":[
        "department"
    ],
    "wof:name":"Middletown Police Jail",
    "wof:placetype":"venue"
},
  "geometry": {"coordinates":[-84.40083199999999,39.519307],"type":"Point"}
}