{
  "type": "Feature",
  "properties": {
    "addr:full": "4185 Ridge Rd Cleveland OH 44144",
    "addr:housenumber": "4185",
    "addr:postcode": "44144",
    "addr:street": "Ridge Rd",
    "iso:country": "US",
    "sg:address": "4185 Ridge Rd",
    "sg:city": "Cleveland",
    "sg:classifiers": [
      {
        "category": "Retail",
        "subcategory": "Veterinary Services",
        "type": "Services"
      }
    ],
    "sg:phone": "+1 216 749 7161",
    "sg:postcode": "44144",
    "sg:province": "OH",
    "sg:tags": [
      "veterinarian"
    ],
    "wof:name": "Emerald Animal Hospital Inc",
    "wof:placetype": "venue"
  },
  "geometry": {"coordinates":[-81.735197,41.442957],"type":"Point"}
}
