{
  "type": "Feature",
  "properties": {
    "addr:full": "11993 Chase Plz Cincinnati OH 45240",
    "addr:housenumber": "11993",
    "addr:postcode": "45240",
    "addr:street": "Chase Plz",
    "iso:country": "US",
    "sg:address": "11993 Chase Plz",
    "sg:city": "Cincinnati",
    "sg:classifiers": [
      {
        "category": "Bars \u0026 Pubs",
        "type": "Food \u0026 Drink"
      }
    ],
    "sg:menulink": "http://www.allmenus.com/oh/forest-park/34950-cracker-barrel-old-country-store/menu/",
    "sg:phone": "+1 513 648 9655",
    "sg:postcode": "45240",
    "sg:province": "OH",
    "sg:tags": [
      "american",
      "southern"
    ],
    "wof:name": "Cracker Barrel Old Country Store",
    "wof:placetype": "venue"
  },
  "geometry": {"coordinates":[-84.526371,39.296866],"type":"Point"}
}
