{
  "type": "Feature",
  "properties": {
    "addr:full": "5526 Airway Rd Dayton OH 45431",
    "addr:housenumber": "5526",
    "addr:postcode": "45431",
    "addr:street": "Airway Rd",
    "iso:country": "US",
    "sg:address": "5526 Airway Rd",
    "sg:city": "Dayton",
    "sg:classifiers": [
      {
        "category": "Food \u0026 Beverages",
        "subcategory": "Groceries \u0026 Convenience Stores",
        "type": "Retail Goods"
      }
    ],
    "sg:phone": "+1 937 252 8858",
    "sg:postcode": "45431",
    "sg:province": "OH",
    "wof:name": "Sairams",
    "wof:placetype": "venue"
  },
  "geometry": {"coordinates":[-84.114452,39.771768],"type":"Point"}
}
