{
  "type": "Feature",
  "properties": {
    "addr:full": "712 W Emmitt Ave Waverly OH 45690",
    "addr:housenumber": "712",
    "addr:postcode": "45690",
    "addr:street": "W Emmitt Ave",
    "iso:country": "US",
    "sg:address": "712 W Emmitt Ave",
    "sg:city": "Waverly",
    "sg:classifiers": [
      {
        "category": "Restaurant",
        "type": "Food \u0026 Drink"
      }
    ],
    "sg:phone": "+1 740 947 4621",
    "sg:postcode": "45690",
    "sg:province": "OH",
    "wof:name": "Dairy Queen",
    "wof:placetype": "venue"
  },
  "geometry": {"coordinates":[-82.989507,39.124377],"type":"Point"}
}
