{
  "type": "Feature",
  "properties": {
    "iso:country":"US",
    "sg:address":"712 W Emmitt Ave",
    "sg:city":"Waverly",
    "sg:classifiers":[
        {
            "category":"Restaurant",
            "type":"Food & Drink"
        }
    ],
    "sg:phone":"+1 740 947 4621",
    "sg:postcode":"45690",
    "sg:province":"OH",
    "wof:name":"Dairy Queen",
    "wof:placetype":"venue"
},
  "geometry": {"coordinates":[-82.989507,39.124377],"type":"Point"}
}