{
  "type": "Feature",
  "properties": {
    "addr:full": "1733 Washington Ave Findlay OH 45840",
    "addr:housenumber": "1733",
    "addr:postcode": "45840",
    "addr:street": "Washington Ave",
    "iso:country": "US",
    "sg:address": "1733 Washington Ave",
    "sg:city": "Findlay",
    "sg:classifiers": [
      {
        "category": "Arts \u0026 Performance",
        "subcategory": "Theater",
        "type": "Entertainment"
      }
    ],
    "sg:phone": "+1 419 425 2277",
    "sg:postcode": "45840",
    "sg:province": "OH",
    "sg:tags": [
      "clown"
    ],
    "wof:name": "Solomon's Folly",
    "wof:placetype": "venue"
  },
  "geometry": {"coordinates":[-83.645619,41.019646],"type":"Point"}
}
