{
  "type": "Feature",
  "properties": {
    "iso:country":"US",
    "sg:address":"7812 Country Ln",
    "sg:city":"Chagrin Falls",
    "sg:classifiers":[
        {
            "category":"Building & Trades",
            "subcategory":"Landscaping Services",
            "type":"Services"
        }
    ],
    "sg:phone":"+1 440 543 7716",
    "sg:postcode":"44023",
    "sg:province":"OH",
    "sg:tags":[
        "landscape",
        "contractor"
    ],
    "wof:name":"W Service",
    "wof:placetype":"venue"
},
  "geometry": {"coordinates":[-81.36492,41.401589],"type":"Point"}
}