{
  "type": "Feature",
  "properties": {
    "addr:full": "1500 N Superior St Toledo OH 43604",
    "addr:housenumber": "1500",
    "addr:postcode": "43604",
    "addr:street": "N Superior St",
    "iso:country": "US",
    "sg:address": "1500 N Superior St",
    "sg:city": "Toledo",
    "sg:classifiers": [
      {
        "category": "Manufacturing",
        "subcategory": "Printing",
        "type": "Manufacturing \u0026 Wholesale Goods"
      }
    ],
    "sg:phone": "+1 419 726 9326",
    "sg:postcode": "43604",
    "sg:province": "OH",
    "sg:tags": [
      "publisher"
    ],
    "wof:name": "Black Pages",
    "wof:placetype": "venue"
  },
  "geometry": {"coordinates":[-83.518839,41.661572],"type":"Point"}
}
