{
  "type": "Feature",
  "properties": {
    "addr:full":"7972 Day Dr Cleveland OH 44129",
    "addr:housenumber":"7972",
    "addr:postcode":"44129",
    "addr:street":"Day Dr",
    "iso:country":"US",
    "sg:address":"7972 Day Dr",
    "sg:city":"Cleveland",
    "sg:classifiers":[
        {
            "category":"Health Services",
            "subcategory":"Optometrist",
            "type":"Services"
        }
    ],
    "sg:phone":"+1 440 885 1529",
    "sg:postcode":"44129",
    "sg:province":"OH",
    "wof:name":"Eye Masters",
    "wof:placetype":"venue"
},
  "geometry": {"coordinates":[-81.74373199999999,41.380576],"type":"Point"}
}