{
  "type": "Feature",
  "properties": {
    "addr:full": "6926 Lee Rd Westerville OH 43081",
    "addr:housenumber": "6926",
    "addr:postcode": "43081",
    "addr:street": "Lee Rd",
    "iso:country": "US",
    "sg:address": "6926 Lee Rd",
    "sg:city": "Westerville",
    "sg:classifiers": [
      {
        "category": "Building \u0026 Trades",
        "subcategory": "Construction",
        "type": "Services"
      }
    ],
    "sg:phone": "+1 614 523 1460",
    "sg:postcode": "43081",
    "sg:province": "OH",
    "sg:tags": [
      "general",
      "contractor"
    ],
    "wof:name": "Integrated Construction Group",
    "wof:placetype": "venue"
  },
  "geometry": {"coordinates":[-82.872989,40.098451],"type":"Point"}
}
