{
  "type": "Feature",
  "properties": {
    "addr:full": "10686 Twp Rd 90 Kenton OH 43326",
    "addr:housenumber": "10686;90",
    "addr:postcode": "43326",
    "addr:street": "Twp Rd",
    "iso:country": "US",
    "sg:address": "10686 Twp Rd 90",
    "sg:city": "Kenton",
    "sg:phone": "+1 419 673 0352",
    "sg:postcode": "43326",
    "sg:province": "OH",
    "sg:tags": [
      "farm",
      "corn",
      "soybean"
    ],
    "wof:name": "Robert Kritzler",
    "wof:placetype": "venue"
  },
  "geometry": {"coordinates":[-83.678864,40.703268],"type":"Point"}
}
