{
  "type": "Feature",
  "properties": {
    "addr:full": "9050 Church St Twinsburg OH 44087",
    "addr:housenumber": "9050",
    "addr:postcode": "44087",
    "addr:street": "Church St",
    "iso:country": "US",
    "sg:address": "9050 Church St",
    "sg:city": "Twinsburg",
    "sg:classifiers": [
      {
        "category": "Organizations",
        "subcategory": "Religious Organization",
        "type": "Services"
      }
    ],
    "sg:phone": "+1 330 425 2181",
    "sg:postcode": "44087",
    "sg:province": "OH",
    "wof:name": "United Church of Christ",
    "wof:placetype": "venue"
  },
  "geometry": {"coordinates":[-81.441425,41.312819],"type":"Point"}
}
