{
  "type": "Feature",
  "properties": {
    "addr:full":"4582 US Hwy 40 Tipp City OH 45371",
    "addr:housenumber":"4582",
    "addr:postcode":"45371",
    "addr:street":"Us Hwy 40",
    "iso:country":"US",
    "sg:address":"4582 US Hwy 40",
    "sg:city":"Tipp City",
    "sg:classifiers":[
        {
            "category":"Building & Trades",
            "subcategory":"Cleaning & Sanitation",
            "type":"Services"
        }
    ],
    "sg:phone":"+1 937 667 4667",
    "sg:postcode":"45371",
    "sg:province":"OH",
    "sg:tags":[
        "window"
    ],
    "wof:name":"Ohio Window Cleaning Inc",
    "wof:placetype":"venue"
},
  "geometry": {"coordinates":[-84.132941,39.89728],"type":"Point"}
}