{
  "type": "Feature",
  "properties": {
    "addr:full": "16750 Lucky Bell Ln Chagrin Falls OH 44023",
    "addr:housenumber": "16750",
    "addr:postcode": "44023",
    "addr:street": "Lucky Bell Ln",
    "iso:country": "US",
    "sg:address": "16750 Lucky Bell Ln",
    "sg:city": "Chagrin Falls",
    "sg:classifiers": [
      {
        "category": "Building \u0026 Trades",
        "subcategory": "Construction",
        "type": "Services"
      }
    ],
    "sg:phone": "+1 440 543 6136",
    "sg:postcode": "44023",
    "sg:province": "OH",
    "sg:tags": [
      "excavation",
      "contractor"
    ],
    "wof:name": "Buckeye Excavating",
    "wof:placetype": "venue"
  },
  "geometry": {"coordinates":[-81.290808,41.420339],"type":"Point"}
}
