{
  "type": "Feature",
  "properties": {
    "addr:full": "653 Euclid Ave Newark OH 43055",
    "addr:housenumber": "653",
    "addr:postcode": "43055",
    "addr:street": "Euclid Ave",
    "iso:country": "US",
    "sg:address": "653 Euclid Ave",
    "sg:city": "Newark",
    "sg:classifiers": [
      {
        "category": "Building \u0026 Trades",
        "subcategory": "Construction",
        "type": "Services"
      }
    ],
    "sg:phone": "+1 740 344 1011",
    "sg:postcode": "43055",
    "sg:province": "OH",
    "sg:tags": [
      "hanging",
      "contractor"
    ],
    "wof:name": "Terry L Cotterman",
    "wof:placetype": "venue"
  },
  "geometry": {"coordinates":[-82.424687,40.067714],"type":"Point"}
}
