{
  "type": "Feature",
  "properties": {
    "addr:full":"5982 W 54th St Cleveland OH 44129",
    "addr:housenumber":"5982",
    "addr:postcode":"44129",
    "addr:street":"W 54Th St",
    "iso:country":"US",
    "sg:address":"5982 W 54th St",
    "sg:city":"Cleveland",
    "sg:classifiers":[
        {
            "category":"Wholesale",
            "subcategory":"Machinery & Supplies",
            "type":"Manufacturing & Wholesale Goods"
        }
    ],
    "sg:phone":"+1 440 842 2218",
    "sg:postcode":"44129",
    "sg:province":"OH",
    "sg:tags":[
        "instrument",
        "surveying"
    ],
    "wof:name":"Robert's Surveying Supplies",
    "wof:placetype":"venue"
},
  "geometry": {"coordinates":[-81.72286099999999,41.400106],"type":"Point"}
}