{
  "type": "Feature",
  "properties": {
    "addr:full":"419 Lehman Ave Bowling Green OH 43402",
    "addr:housenumber":"419",
    "addr:postcode":"43402",
    "addr:street":"Lehman Ave",
    "iso:country":"US",
    "sg:address":"419 Lehman Ave",
    "sg:city":"Bowling Green",
    "sg:classifiers":[
        {
            "category":"Banks & Credit Unions",
            "subcategory":"Bank",
            "type":"Services"
        }
    ],
    "sg:phone":"+1 419 353 8181",
    "sg:postcode":"43402",
    "sg:province":"OH",
    "sg:tags":[
        "mortgage"
    ],
    "wof:name":"Statewide Home Mortgage Inc",
    "wof:placetype":"venue"
},
  "geometry": {"coordinates":[-83.645866,41.370154],"type":"Point"}
}