{
  "type": "Feature",
  "properties": {
    "addr:full": "26805 Russell Rd Cleveland OH 44140",
    "addr:housenumber": "26805",
    "addr:postcode": "44140",
    "addr:street": "Russell Rd",
    "iso:country": "US",
    "sg:address": "26805 Russell Rd",
    "sg:city": "Cleveland",
    "sg:classifiers": [
      {
        "category": "Retail",
        "subcategory": "Repair Shop",
        "type": "Services"
      }
    ],
    "sg:phone": "+1 440 835 1229",
    "sg:postcode": "44140",
    "sg:province": "OH",
    "sg:tags": [
      "cleaners",
      "parts",
      "vacuum"
    ],
    "wof:name": "Filter Queen Sales \u0026 Svc",
    "wof:placetype": "venue"
  },
  "geometry": {"coordinates":[-81.913839,41.486748],"type":"Point"}
}
