{
  "type": "Feature",
  "properties": {
    "iso:country":"US",
    "sg:address":"1084 Walnut Blvd",
    "sg:city":"Ashtabula",
    "sg:classifiers":[
        {
            "category":"Travel",
            "subcategory":"Hotels & Motels",
            "type":"Entertainment"
        }
    ],
    "sg:phone":"+1 440 964 8449",
    "sg:postcode":"44004",
    "sg:province":"OH",
    "sg:tags":[
        "breakfast",
        "accommodation",
        "bed"
    ],
    "sg:website":"www.cahillbb.com",
    "wof:name":"Michael Cahill Bed & Breakfast",
    "wof:placetype":"venue"
},
  "geometry": {"coordinates":[-80.80018,41.901105],"type":"Point"}
}