{
  "type": "Feature",
  "properties": {
    "addr:full": "1084 Walnut Blvd Ashtabula OH 44004",
    "addr:housenumber": "1084",
    "addr:postcode": "44004",
    "addr:street": "Walnut Blvd",
    "iso:country": "US",
    "sg:address": "1084 Walnut Blvd",
    "sg:city": "Ashtabula",
    "sg:classifiers": [
      {
        "category": "Travel",
        "subcategory": "Hotels \u0026 Motels",
        "type": "Entertainment"
      }
    ],
    "sg:phone": "+1 440 964 8449",
    "sg:postcode": "44004",
    "sg:province": "OH",
    "sg:tags": [
      "breakfast",
      "accommodation",
      "bed"
    ],
    "sg:website": "www.cahillbb.com",
    "wof:name": "Michael Cahill Bed \u0026 Breakfast",
    "wof:placetype": "venue"
  },
  "geometry": {"coordinates":[-80.80018,41.901105],"type":"Point"}
}
