{
  "type": "Feature",
  "properties": {
    "iso:country":"US",
    "sg:address":"4428 E Royalton Rd",
    "sg:city":"Broadview Heights",
    "sg:classifiers":[
        {
            "category":"Wholesale",
            "subcategory":"Farm Supplies",
            "type":"Manufacturing & Wholesale Goods"
        }
    ],
    "sg:phone":"+1 440 526 4815",
    "sg:postcode":"44141",
    "sg:province":"OH",
    "sg:tags":[
        "polymer",
        "science"
    ],
    "wof:name":"America Waterworks Inc",
    "wof:placetype":"venue"
},
  "geometry": {"coordinates":[-81.65469299999999,41.314425],"type":"Point"}
}