{
  "type": "Feature",
  "properties": {
    "addr:full":"613 Hebron Rd Newark OH 43056",
    "addr:housenumber":"613",
    "addr:postcode":"43056",
    "addr:street":"Hebron Rd",
    "iso:country":"US",
    "sg:address":"613 Hebron Rd",
    "sg:city":"Newark",
    "sg:classifiers":[
        {
            "category":"Cinema",
            "subcategory":"Movie Rental",
            "type":"Entertainment"
        }
    ],
    "sg:phone":"+1 740 522 2233",
    "sg:postcode":"43056",
    "sg:province":"OH",
    "sg:tags":[
        "video",
        "tape"
    ],
    "wof:name":"Blockbuster",
    "wof:placetype":"venue"
},
  "geometry": {"coordinates":[-82.433266,40.034729],"type":"Point"}
}