{
  "type": "Feature",
  "properties": {
    "iso:country":"US",
    "sg:address":"5511 State Rd",
    "sg:city":"Cleveland",
    "sg:classifiers":[
        {
            "category":"Wholesale",
            "subcategory":"Durable Goods & Equipment",
            "type":"Manufacturing & Wholesale Goods"
        }
    ],
    "sg:phone":"+1 216 351 9002",
    "sg:postcode":"44134",
    "sg:province":"OH",
    "sg:tags":[
        "medical"
    ],
    "wof:name":"Venous Systems Inc",
    "wof:placetype":"venue"
},
  "geometry": {"coordinates":[-81.71037200000001,41.412058],"type":"Point"}
}