{
  "type": "Feature",
  "properties": {
    "addr:full": "5511 State Rd Cleveland OH 44134",
    "addr:housenumber": "5511",
    "addr:postcode": "44134",
    "addr:street": "State Rd",
    "iso:country": "US",
    "sg:address": "5511 State Rd",
    "sg:city": "Cleveland",
    "sg:classifiers": [
      {
        "category": "Wholesale",
        "subcategory": "Durable Goods \u0026 Equipment",
        "type": "Manufacturing \u0026 Wholesale Goods"
      }
    ],
    "sg:phone": "+1 216 351 9002",
    "sg:postcode": "44134",
    "sg:province": "OH",
    "sg:tags": [
      "medical"
    ],
    "wof:name": "Venous Systems Inc",
    "wof:placetype": "venue"
  },
  "geometry": {"coordinates":[-81.710372,41.412058],"type":"Point"}
}
