{
  "type": "Feature",
  "properties": {
    "iso:country":"US",
    "sg:address":"175 W Johnstown Rd",
    "sg:city":"Gahanna",
    "sg:classifiers":[
        {
            "category":"Professional",
            "subcategory":"Research",
            "type":"Services"
        }
    ],
    "sg:phone":"+1 614 428 4608",
    "sg:postcode":"43230",
    "sg:province":"OH",
    "sg:tags":[
        "development",
        "laboratory"
    ],
    "wof:name":"Quest Diagnostics Inc",
    "wof:placetype":"venue"
},
  "geometry": {"coordinates":[-82.88719500000001,40.017168],"type":"Point"}
}