{
  "type": "Feature",
  "properties": {
    "addr:full":"1122 5th Ave Akron OH 44306",
    "addr:housenumber":"1122",
    "addr:postcode":"44306",
    "addr:street":"5Th Ave",
    "iso:country":"US",
    "sg:address":"1122 5th Ave",
    "sg:city":"Akron",
    "sg:classifiers":[
        {
            "category":"Personal",
            "subcategory":"Beauty Salon",
            "type":"Services"
        }
    ],
    "sg:phone":"+1 330 773 1048",
    "sg:postcode":"44306",
    "sg:province":"OH",
    "wof:name":"Flawless Hair Design",
    "wof:placetype":"venue"
},
  "geometry": {"coordinates":[-81.488826,41.061331],"type":"Point"}
}