{
  "type": "Feature",
  "properties": {
    "addr:full":"222 32nd St NW Canton OH 44709",
    "addr:housenumber":"222",
    "addr:postcode":"44709",
    "addr:street":"32Nd St Nw",
    "iso:country":"US",
    "sg:address":"222 32nd St NW",
    "sg:city":"Canton",
    "sg:classifiers":[
        {
            "category":"Wholesale",
            "subcategory":"Drugs",
            "type":"Manufacturing & Wholesale Goods"
        }
    ],
    "sg:phone":"+1 330 493 1248",
    "sg:postcode":"44709",
    "sg:province":"OH",
    "sg:tags":[
        "support",
        "abdominal"
    ],
    "wof:name":"Signatures AR",
    "wof:placetype":"venue"
},
  "geometry": {"coordinates":[-81.368394,40.8331],"type":"Point"}
}