{
  "type": "Feature",
  "properties": {
    "addr:full":"119 S Lisbon St Carrollton OH 44615",
    "addr:housenumber":"119",
    "addr:postcode":"44615",
    "addr:street":"S Lisbon St",
    "iso:country":"US",
    "sg:address":"119 S Lisbon St",
    "sg:city":"Carrollton",
    "sg:classifiers":[
        {
            "category":"Government",
            "subcategory":"Court House",
            "type":"Public Place"
        }
    ],
    "sg:phone":"+1 330 627 2323",
    "sg:postcode":"44615",
    "sg:province":"OH",
    "sg:tags":[
        "county"
    ],
    "wof:name":"Carroll County Juvenille Court",
    "wof:placetype":"venue"
},
  "geometry": {"coordinates":[-81.08662099999999,40.572394],"type":"Point"}
}