{
  "type": "Feature",
  "properties": {
    "addr:full":"1507 State Rte 28 Loveland OH 45140",
    "addr:housenumber":"1507",
    "addr:postcode":"45140",
    "addr:street":"State Rte 28",
    "iso:country":"US",
    "sg:address":"1507 State Rte 28",
    "sg:city":"Loveland",
    "sg:classifiers":[
        {
            "category":"Health Services",
            "subcategory":"Doctor",
            "type":"Services"
        }
    ],
    "sg:phone":"+1 513 575 1444",
    "sg:postcode":"45140",
    "sg:province":"OH",
    "sg:tags":[
        "medical"
    ],
    "wof:name":"Goshen Family Practice",
    "wof:placetype":"venue"
},
  "geometry": {"coordinates":[-84.200498,39.21488],"type":"Point"}
}