{
  "type": "Feature",
  "properties": {
    "iso:country":"US",
    "sg:address":"117 N State St",
    "sg:city":"Kent",
    "sg:classifiers":[
        {
            "category":"Organizations",
            "subcategory":"Community Association",
            "type":"Services"
        }
    ],
    "sg:phone":"+1 330 672 2182",
    "sg:postcode":"44270",
    "sg:province":"OH",
    "wof:name":"R O T C",
    "wof:placetype":"venue"
},
  "geometry": {"coordinates":[-81.78020600000001,40.976132],"type":"Point"}
}