{
  "type": "Feature",
  "properties": {
    "addr:full":"1426 Ridgeview Rd Columbus OH 43221",
    "addr:housenumber":"1426",
    "addr:postcode":"43221",
    "addr:street":"Ridgeview Rd",
    "iso:country":"US",
    "sg:address":"1426 Ridgeview Rd",
    "sg:city":"Columbus",
    "sg:classifiers":[
        {
            "category":"Professional",
            "subcategory":"Business Services",
            "type":"Services"
        }
    ],
    "sg:phone":"+1 614 486 2014",
    "sg:postcode":"43221",
    "sg:province":"OH",
    "sg:tags":[
        "translator",
        "interpreter"
    ],
    "wof:name":"ALTCO Translations",
    "wof:placetype":"venue"
},
  "geometry": {"coordinates":[-83.048979,40.014092],"type":"Point"}
}