{
  "type": "Feature",
  "properties": {
    "addr:full": "5711 Grant Ave Cleveland OH 44105",
    "addr:housenumber": "5711",
    "addr:postcode": "44105",
    "addr:street": "Grant Ave",
    "iso:country": "US",
    "sg:address": "5711 Grant Ave",
    "sg:city": "Cleveland",
    "sg:classifiers": [
      {
        "category": "Utilities",
        "subcategory": "Telephone",
        "type": "Services"
      }
    ],
    "sg:phone": "+1 216 420 9700",
    "sg:postcode": "44105",
    "sg:province": "OH",
    "sg:tags": [
      "company"
    ],
    "wof:name": "Integrity Communications",
    "wof:placetype": "venue"
  },
  "geometry": {"coordinates":[-81.648943,41.438932],"type":"Point"}
}
