{
  "type": "Feature",
  "properties": {
    "addr:full": "822 Fair Rd Sidney OH 45365",
    "addr:housenumber": "822",
    "addr:postcode": "45365",
    "addr:street": "Fair Rd",
    "iso:country": "US",
    "sg:address": "822 Fair Rd",
    "sg:city": "Sidney",
    "sg:classifiers": [
      {
        "category": "Government",
        "subcategory": "Office",
        "type": "Public Place"
      }
    ],
    "sg:phone": "+1 937 492 4788",
    "sg:postcode": "45365",
    "sg:province": "OH",
    "sg:tags": [
      "agricultural"
    ],
    "wof:name": "Farm Service Agency",
    "wof:placetype": "venue"
  },
  "geometry": {"coordinates":[-84.166633,40.276409],"type":"Point"}
}
