{
  "type": "Feature",
  "properties": {
    "addr:full": "3235 Manchester Rd Akron OH 44319",
    "addr:housenumber": "3235",
    "addr:postcode": "44319",
    "addr:street": "Manchester Rd",
    "iso:country": "US",
    "sg:address": "3235 Manchester Rd",
    "sg:city": "Akron",
    "sg:classifiers": [
      {
        "category": "Health Services",
        "subcategory": "Doctor",
        "type": "Services"
      }
    ],
    "sg:phone": "+1 330 645 9180",
    "sg:postcode": "44319",
    "sg:province": "OH",
    "sg:tags": [
      "dentist"
    ],
    "wof:name": "Confident Smile",
    "wof:placetype": "venue"
  },
  "geometry": {"coordinates":[-81.553824,41.012772],"type":"Point"}
}
