{
  "type": "Feature",
  "properties": {
    "addr:full": "6470 Rosser Ave SE Hubbard OH 44425",
    "addr:postcode": "6470;44425",
    "addr:street": "Rosser Ave Se",
    "iso:country": "US",
    "sg:address": "6470 Rosser Ave SE",
    "sg:city": "Hubbard",
    "sg:classifiers": [
      {
        "category": "Manufacturing",
        "subcategory": "Printing",
        "type": "Manufacturing \u0026 Wholesale Goods"
      }
    ],
    "sg:phone": "+1 330 534 0072",
    "sg:postcode": "44425",
    "sg:province": "OH",
    "sg:tags": [
      "commercial",
      "business"
    ],
    "wof:name": "Magical Design",
    "wof:placetype": "venue"
  },
  "geometry": {"coordinates":[-80.583116,41.135505],"type":"Point"}
}
