{
  "type": "Feature",
  "properties": {
    "iso:country":"US",
    "sg:address":"615 5th St",
    "sg:city":"Marietta",
    "sg:classifiers":[
        {
            "category":"Education",
            "subcategory":"Library",
            "type":"Public Place"
        }
    ],
    "sg:phone":"+1 740 373 1057",
    "sg:postcode":"45750",
    "sg:province":"OH",
    "sg:website":"www.wcplib.lib.oh.us",
    "wof:name":"Washington County Public Lib",
    "wof:placetype":"venue"
},
  "geometry": {"coordinates":[-81.457201,39.423843],"type":"Point"}
}