{
  "type": "Feature",
  "properties": {
    "addr:full":"4451 Mahoning Ave NW Warren OH 44483",
    "addr:housenumber":"4451",
    "addr:postcode":"44483",
    "addr:street":"Mahoning Ave Nw",
    "iso:country":"US",
    "sg:address":"4451 Mahoning Ave NW",
    "sg:city":"Warren",
    "sg:classifiers":[
        {
            "category":"Personal",
            "type":"Services"
        }
    ],
    "sg:phone":"+1 330 847 6222",
    "sg:postcode":"44483",
    "sg:province":"OH",
    "sg:tags":[
        "program",
        "physical",
        "exercise",
        "fitness"
    ],
    "wof:name":"Contours Express",
    "wof:placetype":"venue"
},
  "geometry": {"coordinates":[-80.84450200000001,41.281559],"type":"Point"}
}