{
  "type": "Feature",
  "properties": {
    "addr:full": "5180 Taylorsville Rd Dayton OH 45424",
    "addr:housenumber": "5180",
    "addr:postcode": "45424",
    "addr:street": "Taylorsville Rd",
    "iso:country": "US",
    "sg:address": "5180 Taylorsville Rd",
    "sg:city": "Dayton",
    "sg:classifiers": [
      {
        "category": "Taxi",
        "type": "Transportation"
      }
    ],
    "sg:phone": "+1 937 233 2201",
    "sg:postcode": "45424",
    "sg:province": "OH",
    "sg:tags": [
      "taxicab"
    ],
    "wof:name": "Aero Wide Cab",
    "wof:placetype": "venue"
  },
  "geometry": {"coordinates":[-84.146143,39.863301],"type":"Point"}
}
