{
  "type": "Feature",
  "properties": {
    "iso:country":"US",
    "sg:address":"4412 Liberty Ave",
    "sg:city":"Vermilion",
    "sg:classifiers":[
        {
            "category":"Restaurant",
            "type":"Food & Drink"
        }
    ],
    "sg:phone":"+1 440 967 1114",
    "sg:postcode":"44089",
    "sg:province":"OH",
    "wof:name":"Dog House",
    "wof:placetype":"venue"
},
  "geometry": {"coordinates":[-82.343735,41.425048],"type":"Point"}
}