{
  "type": "Feature",
  "properties": {
    "addr:full": "4601 Wuertz Ct Dublin OH 43016",
    "addr:housenumber": "4601",
    "addr:postcode": "43016",
    "addr:street": "Wuertz Ct",
    "iso:country": "US",
    "sg:address": "4601 Wuertz Ct",
    "sg:city": "Dublin",
    "sg:classifiers": [
      {
        "category": "Organizations",
        "subcategory": "Community Association",
        "type": "Services"
      }
    ],
    "sg:phone": "+1 614 789 0476",
    "sg:postcode": "43016",
    "sg:province": "OH",
    "wof:name": "Counsel On Healthy Mothers",
    "wof:placetype": "venue"
  },
  "geometry": {"coordinates":[-83.1165,40.075983],"type":"Point"}
}
