{
  "type": "Feature",
  "properties": {
    "addr:full": "28600 Ridgehills Dr Wickliffe OH 44092",
    "addr:postcode": "28600;44092",
    "addr:street": "Ridgehills Dr",
    "iso:country": "US",
    "sg:address": "28600 Ridgehills Dr",
    "sg:city": "Wickliffe",
    "sg:classifiers": [
      {
        "category": "Travel",
        "subcategory": "Hotels \u0026 Motels",
        "type": "Entertainment"
      },
      {
        "category": "Retail",
        "subcategory": "Event Space",
        "type": "Services"
      }
    ],
    "sg:phone": "+1 440 585 0600",
    "sg:postcode": "44092",
    "sg:province": "OH",
    "sg:tags": [
      "hall",
      "lodging",
      "banquet",
      "reception",
      "facility"
    ],
    "sg:website": "http://www.ramada.com/hotel/26455\u0026cid=RANE",
    "wof:name": "Ramada Plaza, Cleveland East",
    "wof:placetype": "venue"
  },
  "geometry": {"coordinates":[-81.483029,41.58823],"type":"Point"}
}
