{
  "type": "Feature",
  "properties": {
    "addr:full": "301 Mill St Chillicothe OH 45601",
    "addr:housenumber": "301",
    "addr:postcode": "45601",
    "addr:street": "Mill St",
    "iso:country": "US",
    "sg:address": "301 Mill St",
    "sg:city": "Chillicothe",
    "sg:classifiers": [
      {
        "category": "Organizations",
        "subcategory": "Religious Organization",
        "type": "Services"
      }
    ],
    "sg:phone": "+1 740 772 2352",
    "sg:postcode": "45601",
    "sg:province": "OH",
    "sg:tags": [
      "clergy"
    ],
    "wof:name": "James A Groves",
    "wof:placetype": "venue"
  },
  "geometry": {"coordinates":[-82.992295,39.338347],"type":"Point"}
}
