{
  "type": "Feature",
  "properties": {
    "addr:full":"1602 Rockwell Ave Cleveland OH 44114",
    "addr:housenumber":"1602",
    "addr:postcode":"44114",
    "addr:street":"Rockwell Ave",
    "iso:country":"US",
    "sg:address":"1602 Rockwell Ave",
    "sg:city":"Cleveland",
    "sg:classifiers":[
        {
            "category":"Utilities",
            "subcategory":"Telephone",
            "type":"Services"
        }
    ],
    "sg:phone":"+1 216 621 5071",
    "sg:postcode":"44114",
    "sg:province":"OH",
    "sg:tags":[
        "communications"
    ],
    "wof:name":"McLeodusa Incorporated",
    "wof:placetype":"venue"
},
  "geometry": {"coordinates":[-81.683969,41.505503],"type":"Point"}
}