{
  "type": "Feature",
  "properties": {
    "iso:country":"US",
    "sg:address":"1525 Turnberry Village Dr",
    "sg:city":"Dayton",
    "sg:classifiers":[
        {
            "category":"Real Estate",
            "subcategory":"Real Estate Agent",
            "type":"Services"
        }
    ],
    "sg:phone":"+1 937 434 0803",
    "sg:postcode":"45458",
    "sg:province":"OH",
    "wof:name":"Town Properties",
    "wof:placetype":"venue"
},
  "geometry": {"coordinates":[-84.200963,39.620063],"type":"Point"}
}