{
  "type": "Feature",
  "properties": {
    "addr:full": "109 Mill St Columbus OH 43230",
    "addr:housenumber": "109",
    "addr:postcode": "43230",
    "addr:street": "Mill St",
    "iso:country": "US",
    "sg:address": "109 Mill St",
    "sg:city": "Columbus",
    "sg:classifiers": [
      {
        "category": "Government",
        "subcategory": "Post Office",
        "type": "Public Place"
      }
    ],
    "sg:phone": "+1 614 471 8289",
    "sg:postcode": "43230",
    "sg:province": "OH",
    "sg:tags": [
      "postal",
      "us"
    ],
    "wof:name": "US Post Office",
    "wof:placetype": "venue"
  },
  "geometry": {"coordinates":[-82.87962,40.020586],"type":"Point"}
}
