{
  "type": "Feature",
  "properties": {
    "addr:full":"15040 Lorain Ave Cleveland OH 44111",
    "addr:housenumber":"15040",
    "addr:postcode":"44111",
    "addr:street":"Lorain Ave",
    "iso:country":"US",
    "sg:address":"15040 Lorain Ave",
    "sg:city":"Cleveland",
    "sg:classifiers":[
        {
            "category":"Retail",
            "subcategory":"Auto Repair",
            "type":"Services"
        }
    ],
    "sg:phone":"+1 216 251 7157",
    "sg:postcode":"44111",
    "sg:province":"OH",
    "sg:tags":[
        "machine",
        "automobile",
        "shop"
    ],
    "sg:website":"www.victoryengines.com",
    "wof:name":"Victory Engines",
    "wof:placetype":"venue"
},
  "geometry": {"coordinates":[-81.803043,41.452769],"type":"Point"}
}