{
  "type": "Feature",
  "properties": {
    "iso:country":"US",
    "sg:address":"145 Wyndcrest Ct",
    "sg:city":"Monroe",
    "sg:classifiers":[
        {
            "category":"Insurance",
            "subcategory":"Insurance Agent",
            "type":"Services"
        }
    ],
    "sg:phone":"+1 513 539 7789",
    "sg:postcode":"45050",
    "sg:province":"OH",
    "wof:name":"A L Williams",
    "wof:placetype":"venue"
},
  "geometry": {"coordinates":[-84.348147,39.441338],"type":"Point"}
}