{
  "type": "Feature",
  "properties": {
    "iso:country":"US",
    "sg:address":"122 N Barron St",
    "sg:city":"Eaton",
    "sg:classifiers":[
        {
            "category":"Home & Garden",
            "subcategory":"Carpets & Floor Coverings",
            "type":"Retail Goods"
        },
        {
            "category":"Home & Garden",
            "subcategory":"Furniture",
            "type":"Retail Goods"
        }
    ],
    "sg:phone":"+1 937 456 6553",
    "sg:postcode":"45320",
    "sg:province":"OH",
    "sg:tags":[
        "rug",
        "dealer"
    ],
    "wof:name":"Rich-Land Interiors Inc",
    "wof:placetype":"venue"
},
  "geometry": {"coordinates":[-84.63641200000001,39.74418],"type":"Point"}
}