{
  "type": "Feature",
  "properties": {
    "addr:full": "122 N Barron St Eaton OH 45320",
    "addr:housenumber": "122",
    "addr:postcode": "45320",
    "addr:street": "N Barron St",
    "iso:country": "US",
    "sg:address": "122 N Barron St",
    "sg:city": "Eaton",
    "sg:classifiers": [
      {
        "category": "Home \u0026 Garden",
        "subcategory": "Carpets \u0026 Floor Coverings",
        "type": "Retail Goods"
      },
      {
        "category": "Home \u0026 Garden",
        "subcategory": "Furniture",
        "type": "Retail Goods"
      }
    ],
    "sg:phone": "+1 937 456 6553",
    "sg:postcode": "45320",
    "sg:province": "OH",
    "sg:tags": [
      "rug",
      "dealer"
    ],
    "wof:name": "Rich-Land Interiors Inc",
    "wof:placetype": "venue"
  },
  "geometry": {"coordinates":[-84.636412,39.74418],"type":"Point"}
}
