{
  "type": "Feature",
  "properties": {
    "iso:country":"US",
    "sg:address":"1731 Goodman Ave",
    "sg:city":"Cincinnati",
    "sg:classifiers":[
        {
            "category":"Education",
            "subcategory":"School",
            "type":"Public Place"
        }
    ],
    "sg:phone":"+1 513 728 2610",
    "sg:postcode":"45239",
    "sg:province":"OH",
    "wof:name":"Goodman Elementary School",
    "wof:placetype":"venue"
},
  "geometry": {"coordinates":[-84.55351400000001,39.216328],"type":"Point"}
}