{
  "type": "Feature",
  "properties": {
    "addr:full": "5410 State Rd Cleveland OH 44134",
    "addr:housenumber": "5410",
    "addr:postcode": "44134",
    "addr:street": "State Rd",
    "iso:country": "US",
    "sg:address": "5410 State Rd",
    "sg:city": "Cleveland",
    "sg:classifiers": [
      {
        "category": "Food \u0026 Beverages",
        "subcategory": "Groceries \u0026 Convenience Stores",
        "type": "Retail Goods"
      }
    ],
    "sg:phone": "+1 216 661 3232",
    "sg:postcode": "44134",
    "sg:province": "OH",
    "wof:name": "Lincoln Food Mart",
    "wof:placetype": "venue"
  },
  "geometry": {"coordinates":[-81.710486,41.413756],"type":"Point"}
}
