{
  "type": "Feature",
  "properties": {
    "iso:country":"US",
    "sg:address":"5410 State Rd",
    "sg:city":"Cleveland",
    "sg:classifiers":[
        {
            "category":"Food & Beverages",
            "subcategory":"Groceries & Convenience Stores",
            "type":"Retail Goods"
        }
    ],
    "sg:phone":"+1 216 661 3232",
    "sg:postcode":"44134",
    "sg:province":"OH",
    "wof:name":"Lincoln Food Mart",
    "wof:placetype":"venue"
},
  "geometry": {"coordinates":[-81.710486,41.413756],"type":"Point"}
}