{
  "type": "Feature",
  "properties": {
    "addr:full": "1729 Stringtown Rd Grove City OH 43123",
    "addr:housenumber": "1729",
    "addr:postcode": "43123",
    "addr:street": "Stringtown Rd",
    "iso:country": "US",
    "sg:address": "1729 Stringtown Rd",
    "sg:city": "Grove City",
    "sg:classifiers": [
      {
        "category": "Personal",
        "subcategory": "Beauty Salon",
        "type": "Services"
      }
    ],
    "sg:phone": "+1 614 539 4733",
    "sg:postcode": "43123",
    "sg:province": "OH",
    "sg:website": "www.greatclips.com",
    "wof:name": "Great Clips",
    "wof:placetype": "venue"
  },
  "geometry": {"coordinates":[-83.043737,39.878772],"type":"Point"}
}
