{
  "type": "Feature",
  "properties": {
    "addr:full": "6325 York Rd Cleveland OH 44130",
    "addr:housenumber": "6325",
    "addr:postcode": "44130",
    "addr:street": "York Rd",
    "iso:country": "US",
    "sg:address": "6325 York Rd",
    "sg:city": "Cleveland",
    "sg:classifiers": [
      {
        "category": "Personal",
        "type": "Services"
      }
    ],
    "sg:phone": "+1 440 887 9510",
    "sg:postcode": "44130",
    "sg:province": "OH",
    "sg:tags": [
      "therapist",
      "massage"
    ],
    "wof:name": "Backs Massage \u0026 Therapy",
    "wof:placetype": "venue"
  },
  "geometry": {"coordinates":[-81.759545,41.381934],"type":"Point"}
}
