{
  "type": "Feature",
  "properties": {
    "iso:country":"US",
    "sg:address":"173 S Chillicothe Rd",
    "sg:city":"Aurora",
    "sg:classifiers":[
        {
            "category":"Insurance",
            "subcategory":"Insurance Agent",
            "type":"Services"
        }
    ],
    "sg:phone":"+1 330 995 9001",
    "sg:postcode":"44202",
    "sg:province":"OH",
    "wof:name":"Skala Insurance",
    "wof:placetype":"venue"
},
  "geometry": {"coordinates":[-81.34544,41.312262],"type":"Point"}
}