{
  "type": "Feature",
  "properties": {
    "addr:full":"9536 Glades Dr Hamilton OH 45011",
    "addr:housenumber":"9536",
    "addr:postcode":"45011",
    "addr:street":"Glades Dr",
    "iso:country":"US",
    "sg:address":"9536 Glades Dr",
    "sg:city":"Hamilton",
    "sg:classifiers":[
        {
            "category":"Manufacturing",
            "subcategory":"Tools & Machinery",
            "type":"Manufacturing & Wholesale Goods"
        }
    ],
    "sg:phone":"+1 513 942 8111",
    "sg:postcode":"45011",
    "sg:province":"OH",
    "sg:tags":[
        "designed",
        "built"
    ],
    "sg:website":"www.on-pointpackagingmachinery.com",
    "wof:name":"On Point Packaging",
    "wof:placetype":"venue"
},
  "geometry": {"coordinates":[-84.470645,39.319129],"type":"Point"}
}