{
  "type": "Feature",
  "properties": {
    "iso:country":"US",
    "sg:address":"64 S Main St",
    "sg:city":"Johnstown",
    "sg:classifiers":[
        {
            "category":"Utilities",
            "subcategory":"Mobile Phone",
            "type":"Services"
        }
    ],
    "sg:phone":"+1 740 966 5888",
    "sg:postcode":"43031",
    "sg:province":"OH",
    "sg:tags":[
        "telephone",
        "cellular"
    ],
    "wof:name":"Only Need To Ask Inc",
    "wof:placetype":"venue"
},
  "geometry": {"coordinates":[-82.683828,40.152843],"type":"Point"}
}