{
  "type": "Feature",
  "properties": {
    "addr:full": "1511 Linwood Ave SW Canton OH 44710",
    "addr:housenumber": "1511",
    "addr:postcode": "44710",
    "addr:street": "Linwood Ave Sw",
    "iso:country": "US",
    "sg:address": "1511 Linwood Ave SW",
    "sg:city": "Canton",
    "sg:classifiers": [
      {
        "category": "Manufacturing",
        "subcategory": "Metals",
        "type": "Manufacturing \u0026 Wholesale Goods"
      }
    ],
    "sg:phone": "+1 330 478 1120",
    "sg:postcode": "44710",
    "sg:province": "OH",
    "sg:tags": [
      "fabrication",
      "structural"
    ],
    "wof:name": "Pjs Towing Inc",
    "wof:placetype": "venue"
  },
  "geometry": {"coordinates":[-81.416193,40.783008],"type":"Point"}
}
