{
  "type": "Feature",
  "properties": {
    "iso:country":"US",
    "sg:address":"1511 Linwood Ave SW",
    "sg:city":"Canton",
    "sg:classifiers":[
        {
            "category":"Manufacturing",
            "subcategory":"Metals",
            "type":"Manufacturing & Wholesale Goods"
        }
    ],
    "sg:phone":"+1 330 478 1120",
    "sg:postcode":"44710",
    "sg:province":"OH",
    "sg:tags":[
        "fabrication",
        "structural"
    ],
    "wof:name":"Pjs Towing Inc",
    "wof:placetype":"venue"
},
  "geometry": {"coordinates":[-81.41619300000001,40.783008],"type":"Point"}
}