{
  "type": "Feature",
  "properties": {
    "iso:country":"US",
    "sg:address":"1040 Elizabeth Ave",
    "sg:city":"Logan",
    "sg:classifiers":[
        {
            "category":"Professional",
            "subcategory":"Management & Consulting",
            "type":"Services"
        }
    ],
    "sg:phone":"+1 740 385 7049",
    "sg:postcode":"43138",
    "sg:province":"OH",
    "sg:tags":[
        "retail",
        "direct",
        "sales"
    ],
    "wof:name":"Edward L Richards",
    "wof:placetype":"venue"
},
  "geometry": {"coordinates":[-82.40047199999999,39.526664],"type":"Point"}
}