{
  "type": "Feature",
  "properties": {
    "addr:full": "1040 Elizabeth Ave Logan OH 43138",
    "addr:housenumber": "1040",
    "addr:postcode": "43138",
    "addr:street": "Elizabeth Ave",
    "iso:country": "US",
    "sg:address": "1040 Elizabeth Ave",
    "sg:city": "Logan",
    "sg:classifiers": [
      {
        "category": "Professional",
        "subcategory": "Management \u0026 Consulting",
        "type": "Services"
      }
    ],
    "sg:phone": "+1 740 385 7049",
    "sg:postcode": "43138",
    "sg:province": "OH",
    "sg:tags": [
      "retail",
      "direct",
      "sales"
    ],
    "wof:name": "Edward L Richards",
    "wof:placetype": "venue"
  },
  "geometry": {"coordinates":[-82.400472,39.526664],"type":"Point"}
}
