{
  "type": "Feature",
  "properties": {
    "iso:country":"US",
    "sg:address":"8609 Dayton Cincinnati Pike",
    "sg:city":"Miamisburg",
    "sg:classifiers":[
        {
            "category":"Wholesale",
            "subcategory":"Apparel",
            "type":"Manufacturing & Wholesale Goods"
        },
        {
            "category":"Shopping",
            "subcategory":"Clothing, Apparel, & Fashions",
            "type":"Retail Goods"
        }
    ],
    "sg:phone":"+1 937 859 6511",
    "sg:postcode":"45342",
    "sg:province":"OH",
    "wof:name":"Apparel For Dance",
    "wof:placetype":"venue"
},
  "geometry": {"coordinates":[-84.292856,39.626204],"type":"Point"}
}