{
  "type": "Feature",
  "properties": {
    "addr:full": "8609 Dayton Cincinnati Pike Miamisburg OH 45342",
    "addr:housenumber": "8609",
    "addr:postcode": "45342",
    "addr:street": "Dayton Cincinnati Pike",
    "iso:country": "US",
    "sg:address": "8609 Dayton Cincinnati Pike",
    "sg:city": "Miamisburg",
    "sg:classifiers": [
      {
        "category": "Wholesale",
        "subcategory": "Apparel",
        "type": "Manufacturing \u0026 Wholesale Goods"
      },
      {
        "category": "Shopping",
        "subcategory": "Clothing, Apparel, \u0026 Fashions",
        "type": "Retail Goods"
      }
    ],
    "sg:phone": "+1 937 859 6511",
    "sg:postcode": "45342",
    "sg:province": "OH",
    "wof:name": "Apparel For Dance",
    "wof:placetype": "venue"
  },
  "geometry": {"coordinates":[-84.292856,39.626204],"type":"Point"}
}
