{
  "type": "Feature",
  "properties": {
    "iso:country":"US",
    "sg:address":"575 Hebron St",
    "sg:city":"Millersburg",
    "sg:classifiers":[
        {
            "category":"Freight",
            "type":"Transportation"
        }
    ],
    "sg:phone":"+1 330 674 9532",
    "sg:postcode":"44654",
    "sg:province":"OH",
    "sg:tags":[
        "operator",
        "local",
        "trucking"
    ],
    "wof:name":"Jerry A Phillips Hauling",
    "wof:placetype":"venue"
},
  "geometry": {"coordinates":[-81.913076,40.557808],"type":"Point"}
}