{
  "type": "Feature",
  "properties": {
    "iso:country":"US",
    "sg:address":"2460 Sullivant Ave",
    "sg:city":"Columbus",
    "sg:classifiers":[
        {
            "category":"Personal",
            "subcategory":"Barber",
            "type":"Services"
        }
    ],
    "sg:phone":"+1 614 276 0747",
    "sg:postcode":"43204",
    "sg:province":"OH",
    "wof:name":"Phat Fades",
    "wof:placetype":"venue"
},
  "geometry": {"coordinates":[-83.06408,39.945393],"type":"Point"}
}