{
  "type": "Feature",
  "properties": {
    "addr:full":"4829 Superior Ave Cleveland OH 44103",
    "addr:housenumber":"4829",
    "addr:postcode":"44103",
    "addr:street":"Superior Ave",
    "iso:country":"US",
    "sg:address":"4829 Superior Ave",
    "sg:city":"Cleveland",
    "sg:classifiers":[
        {
            "category":"Restaurant",
            "type":"Food & Drink"
        }
    ],
    "sg:phone":"+1 216 426 8603",
    "sg:postcode":"44103",
    "sg:province":"OH",
    "sg:tags":[
        "eating"
    ],
    "wof:name":"Marbles Bar & Grill",
    "wof:placetype":"venue"
},
  "geometry": {"coordinates":[-81.65689,41.515961],"type":"Point"}
}