{
  "type": "Feature",
  "properties": {
    "iso:country":"US",
    "sg:address":"4821 Rockdale Rd",
    "sg:city":"Liberty Twp",
    "sg:classifiers":[
        {
            "category":"Wholesale",
            "subcategory":"Chemicals & Plastics",
            "type":"Manufacturing & Wholesale Goods"
        }
    ],
    "sg:phone":"+1 513 727 9900",
    "sg:postcode":"45011",
    "sg:province":"OH",
    "wof:name":"Meloy Chemical Corp",
    "wof:placetype":"venue"
},
  "geometry": {"coordinates":[-84.45565499999999,39.429161],"type":"Point"}
}