{
  "type": "Feature",
  "properties": {
    "addr:full": "4821 Rockdale Rd Liberty Twp OH 45011",
    "addr:housenumber": "4821",
    "addr:postcode": "45011",
    "addr:street": "Rockdale Rd",
    "iso:country": "US",
    "sg:address": "4821 Rockdale Rd",
    "sg:city": "Liberty Twp",
    "sg:classifiers": [
      {
        "category": "Wholesale",
        "subcategory": "Chemicals \u0026 Plastics",
        "type": "Manufacturing \u0026 Wholesale Goods"
      }
    ],
    "sg:phone": "+1 513 727 9900",
    "sg:postcode": "45011",
    "sg:province": "OH",
    "wof:name": "Meloy Chemical Corp",
    "wof:placetype": "venue"
  },
  "geometry": {"coordinates":[-84.455655,39.429161],"type":"Point"}
}
