{
  "type": "Feature",
  "properties": {
    "iso:country":"US",
    "sg:address":"1360 Cross Creek Dr",
    "sg:city":"Brunswick",
    "sg:classifiers":[
        {
            "category":"Building & Trades",
            "subcategory":"Construction",
            "type":"Services"
        }
    ],
    "sg:phone":"+1 330 220 0768",
    "sg:postcode":"44212",
    "sg:province":"OH",
    "sg:tags":[
        "contractor"
    ],
    "wof:name":"Foster Industrial Control Svcs",
    "wof:placetype":"venue"
},
  "geometry": {"coordinates":[-81.827634,41.239108],"type":"Point"}
}