{
  "type": "Feature",
  "properties": {
    "addr:full": "1360 Cross Creek Dr Brunswick OH 44212",
    "addr:housenumber": "1360",
    "addr:postcode": "44212",
    "addr:street": "Cross Creek Dr",
    "iso:country": "US",
    "sg:address": "1360 Cross Creek Dr",
    "sg:city": "Brunswick",
    "sg:classifiers": [
      {
        "category": "Building \u0026 Trades",
        "subcategory": "Construction",
        "type": "Services"
      }
    ],
    "sg:phone": "+1 330 220 0768",
    "sg:postcode": "44212",
    "sg:province": "OH",
    "sg:tags": [
      "contractor"
    ],
    "wof:name": "Foster Industrial Control Svcs",
    "wof:placetype": "venue"
  },
  "geometry": {"coordinates":[-81.827634,41.239108],"type":"Point"}
}
