{
  "type": "Feature",
  "properties": {
    "iso:country":"US",
    "sg:address":"2346 Gardendale Dr",
    "sg:city":"Columbus",
    "sg:classifiers":[
        {
            "category":"Professional",
            "subcategory":"Management & Consulting",
            "type":"Services"
        }
    ],
    "sg:phone":"+1 614 354 1578",
    "sg:postcode":"43219",
    "sg:province":"OH",
    "sg:tags":[
        "marketing",
        "direct",
        "sales",
        "real estate",
        "investment"
    ],
    "wof:name":"Homebuyerone Inc",
    "wof:placetype":"venue"
},
  "geometry": {"coordinates":[-82.943487,39.996654],"type":"Point"}
}