{
  "type": "Feature",
  "properties": {
    "addr:full": "91 N Main St Roseville OH 43777",
    "addr:housenumber": "91",
    "addr:postcode": "43777",
    "addr:street": "N Main St",
    "iso:country": "US",
    "sg:address": "91 N Main St",
    "sg:city": "Roseville",
    "sg:classifiers": [
      {
        "category": "Organizations",
        "subcategory": "Membership Organization",
        "type": "Services"
      }
    ],
    "sg:phone": "+1 740 697 7127",
    "sg:postcode": "43777",
    "sg:province": "OH",
    "sg:tags": [
      "historical"
    ],
    "wof:name": "Roseville Historical Society",
    "wof:placetype": "venue"
  },
  "geometry": {"coordinates":[-82.072673,39.806852],"type":"Point"}
}
