{
  "type": "Feature",
  "properties": {
    "iso:country":"US",
    "sg:address":"2709 Tanglewood Dr",
    "sg:city":"Wooster",
    "sg:classifiers":[
        {
            "category":"Building & Trades",
            "subcategory":"Electrical",
            "type":"Services"
        }
    ],
    "sg:phone":"+1 330 345 8033",
    "sg:postcode":"44691",
    "sg:province":"OH",
    "sg:tags":[
        "electrical",
        "contractor"
    ],
    "wof:name":"Silver State Inc",
    "wof:placetype":"venue"
},
  "geometry": {"coordinates":[-81.92138199999999,40.832482],"type":"Point"}
}