{
  "type": "Feature",
  "properties": {
    "addr:full": "2709 Tanglewood Dr Wooster OH 44691",
    "addr:housenumber": "2709",
    "addr:postcode": "44691",
    "addr:street": "Tanglewood Dr",
    "iso:country": "US",
    "sg:address": "2709 Tanglewood Dr",
    "sg:city": "Wooster",
    "sg:classifiers": [
      {
        "category": "Building \u0026 Trades",
        "subcategory": "Electrical",
        "type": "Services"
      }
    ],
    "sg:phone": "+1 330 345 8033",
    "sg:postcode": "44691",
    "sg:province": "OH",
    "sg:tags": [
      "electrical",
      "contractor"
    ],
    "wof:name": "Silver State Inc",
    "wof:placetype": "venue"
  },
  "geometry": {"coordinates":[-81.921382,40.832482],"type":"Point"}
}
