{
  "type": "Feature",
  "properties": {
    "iso:country":"US",
    "sg:address":"211 High St",
    "sg:city":"Cleveland",
    "sg:classifiers":[
        {
            "category":"Professional",
            "subcategory":"Art Services",
            "type":"Services"
        }
    ],
    "sg:phone":"+1 216 696 7926",
    "sg:postcode":"44115",
    "sg:province":"OH",
    "sg:tags":[
        "photographer"
    ],
    "wof:name":"Tim Ryan & Sons Inc",
    "wof:placetype":"venue"
},
  "geometry": {"coordinates":[-81.689736,41.497656],"type":"Point"}
}