{
  "type": "Feature",
  "properties": {
    "iso:country":"US",
    "sg:address":"2404 W State St",
    "sg:city":"Fremont",
    "sg:classifiers":[
        {
            "category":"Retail",
            "subcategory":"Animal Services",
            "type":"Services"
        }
    ],
    "sg:phone":"+1 419 332 8338",
    "sg:postcode":"43420",
    "sg:province":"OH",
    "sg:tags":[
        "shelter"
    ],
    "wof:name":"Humane Society-Sandusky County",
    "wof:placetype":"venue"
},
  "geometry": {"coordinates":[-83.146748,41.361174],"type":"Point"}
}