{
  "type": "Feature",
  "properties": {
    "addr:full": "7304 June Berry Ln Whitehouse OH 43571",
    "addr:housenumber": "7304",
    "addr:postcode": "43571",
    "addr:street": "June Berry Ln",
    "iso:country": "US",
    "sg:address": "7304 June Berry Ln",
    "sg:city": "Whitehouse",
    "sg:classifiers": [
      {
        "category": "Wholesale",
        "subcategory": "Non-durable Goods",
        "type": "Manufacturing \u0026 Wholesale Goods"
      }
    ],
    "sg:phone": "+1 419 877 5922",
    "sg:postcode": "43571",
    "sg:province": "OH",
    "wof:name": "A \u0026 V African Cichlids",
    "wof:placetype": "venue"
  },
  "geometry": {"coordinates":[-83.805334,41.508321],"type":"Point"}
}
