{
  "type": "Feature",
  "properties": {
    "addr:full": "250 W Old Wilson Bridge Rd Worthington OH 43085",
    "addr:housenumber": "250",
    "addr:postcode": "43085",
    "addr:street": "W Old Wilson Bridge Rd",
    "iso:country": "US",
    "sg:address": "250 W Old Wilson Bridge Rd",
    "sg:city": "Worthington",
    "sg:classifiers": [
      {
        "category": "Professional",
        "subcategory": "Accounting \u0026 Tax Preparation",
        "type": "Services"
      }
    ],
    "sg:phone": "+1 614 396 4200",
    "sg:postcode": "43085",
    "sg:province": "OH",
    "sg:tags": [
      "accountant"
    ],
    "sg:website": "www.whalencpa.com",
    "wof:name": "Whalen \u0026 Co",
    "wof:placetype": "venue"
  },
  "geometry": {"coordinates":[-83.017769,40.109885],"type":"Point"}
}
