{
  "type": "Feature",
  "properties": {
    "iso:country":"US",
    "sg:address":"1990 Ford Dr",
    "sg:city":"Cleveland",
    "sg:classifiers":[
        {
            "category":"Real Estate",
            "subcategory":"Real Estate Operator",
            "type":"Services"
        }
    ],
    "sg:phone":"+1 216 791 6828",
    "sg:postcode":"44106",
    "sg:province":"OH",
    "sg:tags":[
        "apartment"
    ],
    "wof:name":"University Circle",
    "wof:placetype":"venue"
},
  "geometry": {"coordinates":[-81.605921,41.509235],"type":"Point"}
}