{
  "type": "Feature",
  "properties": {
    "addr:full":"5420 Mahoning Ave Youngstown OH 44515",
    "addr:housenumber":"5420",
    "addr:postcode":"44515",
    "addr:street":"Mahoning Ave",
    "iso:country":"US",
    "sg:address":"5420 Mahoning Ave",
    "sg:city":"Youngstown",
    "sg:classifiers":[
        {
            "category":"Recreation",
            "type":"Entertainment"
        }
    ],
    "sg:phone":"+1 330 270 4386",
    "sg:postcode":"44515",
    "sg:province":"OH",
    "sg:tags":[
        "ride",
        "center",
        "amusement"
    ],
    "wof:name":"Laser Storm",
    "wof:placetype":"venue"
},
  "geometry": {"coordinates":[-80.760142,41.099684],"type":"Point"}
}