{
  "type": "Feature",
  "properties": {
    "iso:country":"US",
    "sg:address":"7055 Quarry Rd",
    "sg:city":"Amherst",
    "sg:classifiers":[
        {
            "category":"Home & Garden",
            "subcategory":"Mobile Homes",
            "type":"Retail Goods"
        }
    ],
    "sg:phone":"+1 440 988 4033",
    "sg:postcode":"44001",
    "sg:province":"OH",
    "wof:name":"Westwoods Mobile Home Park",
    "wof:placetype":"venue"
},
  "geometry": {"coordinates":[-82.250519,41.396498],"type":"Point"}
}