{
  "type": "Feature",
  "properties": {
    "addr:full": "1174 Kenny Centre Mall Columbus OH 43220",
    "addr:housenumber": "1174",
    "addr:postcode": "43220",
    "addr:street": "Kenny Centre Mall",
    "iso:country": "US",
    "sg:address": "1174 Kenny Centre Mall",
    "sg:city": "Columbus",
    "sg:classifiers": [
      {
        "category": "Food \u0026 Beverages",
        "subcategory": "Bakery",
        "type": "Retail Goods"
      }
    ],
    "sg:phone": "+1 614 457 4800",
    "sg:postcode": "43220",
    "sg:province": "OH",
    "sg:tags": [
      "baker"
    ],
    "wof:name": "Pepperidge Farm Thrift Store",
    "wof:placetype": "venue"
  },
  "geometry": {"coordinates":[-83.050003,40.05112],"type":"Point"}
}
