{
  "type": "Feature",
  "properties": {
    "iso:country":"US",
    "sg:address":"2603 State Rte 59",
    "sg:city":"Ravenna",
    "sg:classifiers":[
        {
            "category":"Building & Trades",
            "subcategory":"Construction",
            "type":"Services"
        }
    ],
    "sg:phone":"+1 330 296 2332",
    "sg:postcode":"44266",
    "sg:province":"OH",
    "wof:name":"IHS Home Sweet Homes",
    "wof:placetype":"venue"
},
  "geometry": {"coordinates":[-81.29813799999999,41.158138],"type":"Point"}
}