{
  "type": "Feature",
  "properties": {
    "addr:full": "4550 Este Ave Cincinnati OH 45232",
    "addr:postcode": "4550;45232",
    "addr:street": "Este Ave",
    "iso:country": "US",
    "sg:address": "4550 Este Ave",
    "sg:city": "Cincinnati",
    "sg:classifiers": [
      {
        "category": "Local Transit",
        "type": "Transportation"
      }
    ],
    "sg:phone": "+1 513 541 1782",
    "sg:postcode": "45232",
    "sg:province": "OH",
    "sg:tags": [
      "ambulance"
    ],
    "wof:name": "Medcorp",
    "wof:placetype": "venue"
  },
  "geometry": {"coordinates":[-84.512925,39.1715],"type":"Point"}
}
