{
  "type": "Feature",
  "properties": {
    "addr:full":"6569 Brandt Pike Dayton OH 45424",
    "addr:housenumber":"6569",
    "addr:postcode":"45424",
    "addr:street":"Brandt Pike",
    "iso:country":"US",
    "sg:address":"6569 Brandt Pike",
    "sg:city":"Dayton",
    "sg:classifiers":[
        {
            "category":"Government",
            "subcategory":"Office",
            "type":"Public Place"
        }
    ],
    "sg:phone":"+1 937 233 3292",
    "sg:postcode":"45424",
    "sg:province":"OH",
    "sg:tags":[
        "village"
    ],
    "wof:name":"Huber Heights Sewer Div",
    "wof:placetype":"venue"
},
  "geometry": {"coordinates":[-84.11274,39.848972],"type":"Point"}
}