{
  "type": "Feature",
  "properties": {
    "addr:full":"1954 Kenton St Springfield OH 45505",
    "addr:housenumber":"1954",
    "addr:postcode":"45505",
    "addr:street":"Kenton St",
    "iso:country":"US",
    "sg:address":"1954 Kenton St",
    "sg:city":"Springfield",
    "sg:classifiers":[
        {
            "category":"Organizations",
            "subcategory":"Community Association",
            "type":"Services"
        }
    ],
    "sg:phone":"+1 937 323 6602",
    "sg:postcode":"45505",
    "sg:province":"OH",
    "sg:tags":[
        "military"
    ],
    "wof:name":"Amvets Post 25",
    "wof:placetype":"venue"
},
  "geometry": {"coordinates":[-83.78084200000001,39.909829],"type":"Point"}
}