{
  "type": "Feature",
  "properties": {
    "addr:full":"5603 Elder Rd Canal Winchester OH 43110",
    "addr:housenumber":"5603",
    "addr:postcode":"43110",
    "addr:street":"Elder Rd",
    "iso:country":"US",
    "sg:address":"5603 Elder Rd",
    "sg:city":"Canal Winchester",
    "sg:classifiers":[
        {
            "category":"Building & Trades",
            "subcategory":"Electrical",
            "type":"Services"
        }
    ],
    "sg:phone":"+1 614 837 2000",
    "sg:postcode":"43110",
    "sg:province":"OH",
    "sg:tags":[
        "electrical",
        "contractor"
    ],
    "wof:name":"Sherman Electric",
    "wof:placetype":"venue"
},
  "geometry": {"coordinates":[-82.842609,39.802946],"type":"Point"}
}