{
  "type": "Feature",
  "properties": {
    "iso:country":"US",
    "sg:address":"3110 Kettering Blvd",
    "sg:city":"Dayton",
    "sg:classifiers":[
        {
            "category":"Banks & Credit Unions",
            "subcategory":"Financial Services",
            "type":"Services"
        }
    ],
    "sg:phone":"+1 937 294 7409",
    "sg:postcode":"45439",
    "sg:province":"OH",
    "sg:tags":[
        "investor",
        "investment",
        "closed"
    ],
    "wof:name":"Valuation Co",
    "wof:placetype":"venue"
},
  "geometry": {"coordinates":[-84.204787,39.704087],"type":"Point"}
}