{
  "type": "Feature",
  "properties": {
    "addr:full": "5113 Twp Rd 359 Berlin OH 44654",
    "addr:postcode": "5113;44654",
    "addr:street": "Twp Rd 359",
    "iso:country": "US",
    "sg:address": "5113 Twp Rd 359",
    "sg:city": "Berlin",
    "sg:classifiers": [
      {
        "category": "Travel",
        "subcategory": "Hotels \u0026 Motels",
        "type": "Entertainment"
      }
    ],
    "sg:phone": "+1 330 893 2767",
    "sg:postcode": "44654",
    "sg:province": "OH",
    "sg:tags": [
      "breakfast",
      "operation",
      "bed",
      "accommodation"
    ],
    "wof:name": "Water's Edge Cabins Of Berlin",
    "wof:placetype": "venue"
  },
  "geometry": {"coordinates":[-81.804114,40.562653],"type":"Point"}
}
