{
  "type": "Feature",
  "properties": {
    "addr:full":"5030 Linden Ave Dayton OH 45432",
    "addr:housenumber":"5030",
    "addr:postcode":"45432",
    "addr:street":"Linden Ave",
    "iso:country":"US",
    "sg:address":"5030 Linden Ave",
    "sg:city":"Dayton",
    "sg:classifiers":[
        {
            "category":"Organizations",
            "subcategory":"Labor Organization",
            "type":"Services"
        }
    ],
    "sg:phone":"+1 937 256 4322",
    "sg:postcode":"45432",
    "sg:province":"OH",
    "wof:name":"Communications Workers-America",
    "wof:placetype":"venue"
},
  "geometry": {"coordinates":[-84.10307299999999,39.739535],"type":"Point"}
}