{
  "type": "Feature",
  "properties": {
    "addr:full": "2800 Ontario Ave Dayton OH 45414",
    "addr:housenumber": "2800",
    "addr:postcode": "45414",
    "addr:street": "Ontario Ave",
    "iso:country": "US",
    "sg:address": "2800 Ontario Ave",
    "sg:city": "Dayton",
    "sg:classifiers": [
      {
        "category": "Professional",
        "subcategory": "Research",
        "type": "Services"
      }
    ],
    "sg:phone": "+1 937 274 9872",
    "sg:postcode": "45414",
    "sg:province": "OH",
    "sg:tags": [
      "environmental",
      "ecological"
    ],
    "wof:name": "Shaw E \u0026 I",
    "wof:placetype": "venue"
  },
  "geometry": {"coordinates":[-84.177596,39.798601],"type":"Point"}
}
