{
  "type": "Feature",
  "properties": {
    "iso:country":"US",
    "sg:address":"2800 Ontario Ave",
    "sg:city":"Dayton",
    "sg:classifiers":[
        {
            "category":"Professional",
            "subcategory":"Research",
            "type":"Services"
        }
    ],
    "sg:phone":"+1 937 274 9872",
    "sg:postcode":"45414",
    "sg:province":"OH",
    "sg:tags":[
        "environmental",
        "ecological"
    ],
    "wof:name":"Shaw E & I",
    "wof:placetype":"venue"
},
  "geometry": {"coordinates":[-84.17759599999999,39.798601],"type":"Point"}
}