{
  "type": "Feature",
  "properties": {
    "addr:full":"2 Gateway Cleveland OH 44119",
    "addr:housenumber":"2",
    "addr:postcode":"44119",
    "addr:street":"Gateway",
    "iso:country":"US",
    "sg:address":"2 Gateway",
    "sg:city":"Cleveland",
    "sg:classifiers":[
        {
            "category":"Professional",
            "type":"Services"
        }
    ],
    "sg:phone":"+1 216 589 9750",
    "sg:postcode":"44119",
    "sg:province":"OH",
    "sg:tags":[
        "establishment"
    ],
    "wof:name":"Klink & Co",
    "wof:placetype":"venue"
},
  "geometry": {"coordinates":[-81.536795,41.585114],"type":"Point"}
}