{
  "type": "Feature",
  "properties": {
    "iso:country":"US",
    "sg:address":"21520 Zion Rd",
    "sg:city":"Gambier",
    "sg:classifiers":[
        {
            "category":"Building & Trades",
            "subcategory":"Construction",
            "type":"Services"
        }
    ],
    "sg:phone":"+1 740 427 9450",
    "sg:postcode":"43022",
    "sg:province":"OH",
    "sg:tags":[
        "contractor"
    ],
    "wof:name":"Aabic Roofing",
    "wof:placetype":"venue"
},
  "geometry": {"coordinates":[-82.36636,40.375508],"type":"Point"}
}