{
  "type": "Feature",
  "properties": {
    "addr:full": "30610 Detroit Rd Cleveland OH 44145",
    "addr:housenumber": "30610",
    "addr:postcode": "44145",
    "addr:street": "Detroit Rd",
    "iso:country": "US",
    "sg:address": "30610 Detroit Rd",
    "sg:city": "Cleveland",
    "sg:classifiers": [
      {
        "category": "Sports \u0026 Exercise",
        "subcategory": "Gym",
        "type": "Entertainment"
      }
    ],
    "sg:phone": "+1 440 835 5239",
    "sg:postcode": "44145",
    "sg:province": "OH",
    "sg:tags": [
      "club",
      "health",
      "studio",
      "gymnasium"
    ],
    "wof:name": "Physique Boutique Inc",
    "wof:placetype": "venue"
  },
  "geometry": {"coordinates":[-81.959812,41.461414],"type":"Point"}
}
