{
  "type": "Feature",
  "properties": {
    "addr:full": "1900 Fairgrove Ave Hamilton OH 45011",
    "addr:housenumber": "1900",
    "addr:postcode": "45011",
    "addr:street": "Fairgrove Ave",
    "iso:country": "US",
    "sg:address": "1900 Fairgrove Ave",
    "sg:city": "Hamilton",
    "sg:classifiers": [
      {
        "category": "Organizations",
        "subcategory": "Non-profit Organization",
        "type": "Services"
      }
    ],
    "sg:phone": "+1 513 867 7545",
    "sg:postcode": "45011",
    "sg:province": "OH",
    "wof:name": "Life Span",
    "wof:placetype": "venue"
  },
  "geometry": {"coordinates":[-84.537074,39.402565],"type":"Point"}
}
