{
  "type": "Feature",
  "properties": {
    "addr:full":"8020 Broadmoor Rd Mentor OH 44060",
    "addr:housenumber":"8020",
    "addr:postcode":"44060",
    "addr:street":"Broadmoor Rd",
    "iso:country":"US",
    "sg:address":"8020 Broadmoor Rd",
    "sg:city":"Mentor",
    "sg:classifiers":[
        {
            "category":"Wholesale",
            "subcategory":"Construction Materials",
            "type":"Manufacturing & Wholesale Goods"
        }
    ],
    "sg:phone":"+1 216 831 2420",
    "sg:postcode":"44060",
    "sg:province":"OH",
    "wof:name":"Pella Window & Door Co",
    "wof:placetype":"venue"
},
  "geometry": {"coordinates":[-81.376707,41.652469],"type":"Point"}
}