{
  "type": "Feature",
  "properties": {
    "iso:country":"US",
    "sg:address":"8401 Almira Ave",
    "sg:city":"Cleveland",
    "sg:classifiers":[
        {
            "category":"Wholesale",
            "subcategory":"Construction Materials",
            "type":"Manufacturing & Wholesale Goods"
        }
    ],
    "sg:phone":"+1 216 281 4004",
    "sg:postcode":"44102",
    "sg:province":"OH",
    "sg:tags":[
        "pallet",
        "skid"
    ],
    "wof:name":"Aardvark Industries Inc",
    "wof:placetype":"venue"
},
  "geometry": {"coordinates":[-81.743706,41.462118],"type":"Point"}
}