{
  "type": "Feature",
  "properties": {
    "addr:full": "16445 Haskins Rd Chagrin Falls OH 44023",
    "addr:housenumber": "16445",
    "addr:postcode": "44023",
    "addr:street": "Haskins Rd",
    "iso:country": "US",
    "sg:address": "16445 Haskins Rd",
    "sg:city": "Chagrin Falls",
    "sg:classifiers": [
      {
        "category": "Building \u0026 Trades",
        "subcategory": "Electrical",
        "type": "Services"
      }
    ],
    "sg:phone": "+1 440 543 8936",
    "sg:postcode": "44023",
    "sg:province": "OH",
    "sg:tags": [
      "electrical",
      "contractor"
    ],
    "wof:name": "Semall Electric Inc",
    "wof:placetype": "venue"
  },
  "geometry": {"coordinates":[-81.323218,41.423033],"type":"Point"}
}
