{
  "type": "Feature",
  "properties": {
    "addr:full":"12 Public Sq Willoughby OH 44094",
    "addr:housenumber":"12",
    "addr:postcode":"44094",
    "addr:street":"Public Sq",
    "iso:country":"US",
    "sg:address":"12 Public Sq",
    "sg:city":"Willoughby",
    "sg:classifiers":[
        {
            "category":"Home & Garden",
            "subcategory":"Building Materials",
            "type":"Retail Goods"
        }
    ],
    "sg:phone":"+1 440 946 5955",
    "sg:postcode":"44094",
    "sg:province":"OH",
    "sg:tags":[
        "installs",
        "windows",
        "kitchen",
        "cabinet"
    ],
    "wof:name":"American Kitchen & Bath Rescue",
    "wof:placetype":"venue"
},
  "geometry": {"coordinates":[-81.405162,41.639771],"type":"Point"}
}