{
  "type": "Feature",
  "properties": {
    "iso:country":"US",
    "sg:address":"3618 W Market St",
    "sg:city":"Fairlawn",
    "sg:classifiers":[
        {
            "category":"Health Services",
            "subcategory":"Health Practitioner",
            "type":"Services"
        }
    ],
    "sg:phone":"+1 330 666 5004",
    "sg:postcode":"44333",
    "sg:province":"OH",
    "sg:tags":[
        "info",
        "eating",
        "disorder",
        "treatment"
    ],
    "wof:name":"New Beginnings Counseling",
    "wof:placetype":"venue"
},
  "geometry": {"coordinates":[-81.630701,41.13575],"type":"Point"}
}