{
  "type": "Feature",
  "properties": {
    "addr:full":"429 Woodcrest Dr Wadsworth OH 44281",
    "addr:housenumber":"429",
    "addr:postcode":"44281",
    "addr:street":"Woodcrest Dr",
    "iso:country":"US",
    "sg:address":"429 Woodcrest Dr",
    "sg:city":"Wadsworth",
    "sg:classifiers":[
        {
            "category":"Professional",
            "subcategory":"Advertising",
            "type":"Services"
        }
    ],
    "sg:phone":"+1 330 722 2836",
    "sg:postcode":"44281",
    "sg:province":"OH",
    "sg:tags":[
        "counselor"
    ],
    "wof:name":"Miska Design Group Inc",
    "wof:placetype":"venue"
},
  "geometry": {"coordinates":[-81.71120000000001,41.017497],"type":"Point"}
}