{
  "type": "Feature",
  "properties": {
    "addr:full": "1561 8th St Cuyahoga Falls OH 44221",
    "addr:housenumber": "1561",
    "addr:postcode": "44221",
    "addr:street": "8Th St",
    "iso:country": "US",
    "sg:address": "1561 8th St",
    "sg:city": "Cuyahoga Falls",
    "sg:classifiers": [
      {
        "category": "Banks \u0026 Credit Unions",
        "subcategory": "Investment Brokerage",
        "type": "Services"
      }
    ],
    "sg:phone": "+1 330 929 8289",
    "sg:postcode": "44221",
    "sg:province": "OH",
    "sg:tags": [
      "security"
    ],
    "wof:name": "Paul Dietzel",
    "wof:placetype": "venue"
  },
  "geometry": {"coordinates":[-81.492616,41.126526],"type":"Point"}
}
