{
  "type": "Feature",
  "properties": {
    "iso:country":"US",
    "sg:address":"1561 8th St",
    "sg:city":"Cuyahoga Falls",
    "sg:classifiers":[
        {
            "category":"Banks & Credit Unions",
            "subcategory":"Investment Brokerage",
            "type":"Services"
        }
    ],
    "sg:phone":"+1 330 929 8289",
    "sg:postcode":"44221",
    "sg:province":"OH",
    "sg:tags":[
        "security"
    ],
    "wof:name":"Paul Dietzel",
    "wof:placetype":"venue"
},
  "geometry": {"coordinates":[-81.492616,41.126526],"type":"Point"}
}