{
  "type": "Feature",
  "properties": {
    "iso:country":"US",
    "sg:address":"1130 Manning Ave",
    "sg:city":"Youngstown",
    "sg:classifiers":[
        {
            "category":"Farming",
            "subcategory":"Dairy Farm",
            "type":"Manufacturing & Wholesale Goods"
        }
    ],
    "sg:phone":"+1 330 746 1011",
    "sg:postcode":"44502",
    "sg:province":"OH",
    "wof:name":"Home Corp",
    "wof:placetype":"venue"
},
  "geometry": {"coordinates":[-80.67084699999999,41.107993],"type":"Point"}
}