{
  "type": "Feature",
  "properties": {
    "addr:full": "1130 Manning Ave Youngstown OH 44502",
    "addr:housenumber": "1130",
    "addr:postcode": "44502",
    "addr:street": "Manning Ave",
    "iso:country": "US",
    "sg:address": "1130 Manning Ave",
    "sg:city": "Youngstown",
    "sg:classifiers": [
      {
        "category": "Farming",
        "subcategory": "Dairy Farm",
        "type": "Manufacturing \u0026 Wholesale Goods"
      }
    ],
    "sg:phone": "+1 330 746 1011",
    "sg:postcode": "44502",
    "sg:province": "OH",
    "wof:name": "Home Corp",
    "wof:placetype": "venue"
  },
  "geometry": {"coordinates":[-80.670847,41.107993],"type":"Point"}
}
