{
  "type": "Feature",
  "properties": {
    "addr:full": "37220 Mound St Sardis OH 43946",
    "addr:housenumber": "37220",
    "addr:postcode": "43946",
    "addr:street": "Mound St",
    "iso:country": "US",
    "sg:address": "37220 Mound St",
    "sg:city": "Sardis",
    "sg:classifiers": [
      {
        "category": "Arts \u0026 Performance",
        "subcategory": "Theater",
        "type": "Entertainment"
      }
    ],
    "sg:phone": "+1 740 483 2533",
    "sg:postcode": "43946",
    "sg:province": "OH",
    "sg:tags": [
      "bureau"
    ],
    "wof:name": "3 D Entertainment",
    "wof:placetype": "venue"
  },
  "geometry": {"coordinates":[-80.912549,39.621922],"type":"Point"}
}
