{
  "type": "Feature",
  "properties": {
    "iso:country":"US",
    "sg:address":"37220 Mound St",
    "sg:city":"Sardis",
    "sg:classifiers":[
        {
            "category":"Arts & Performance",
            "subcategory":"Theater",
            "type":"Entertainment"
        }
    ],
    "sg:phone":"+1 740 483 2533",
    "sg:postcode":"43946",
    "sg:province":"OH",
    "sg:tags":[
        "bureau"
    ],
    "wof:name":"3 D Entertainment",
    "wof:placetype":"venue"
},
  "geometry": {"coordinates":[-80.912549,39.621922],"type":"Point"}
}