{
  "type": "Feature",
  "properties": {
    "addr:full": "1036 Bibich Ct Crestline OH 44827",
    "addr:housenumber": "1036",
    "addr:postcode": "44827",
    "addr:street": "Bibich Ct",
    "iso:country": "US",
    "sg:address": "1036 Bibich Ct",
    "sg:city": "Crestline",
    "sg:classifiers": [
      {
        "category": "Building \u0026 Trades",
        "subcategory": "Construction",
        "type": "Services"
      }
    ],
    "sg:phone": "+1 419 683 3262",
    "sg:postcode": "44827",
    "sg:province": "OH",
    "sg:tags": [
      "hanging",
      "contractor"
    ],
    "wof:name": "Country Decorating",
    "wof:placetype": "venue"
  },
  "geometry": {"coordinates":[-82.739302,40.774564],"type":"Point"}
}
