{
  "type": "Feature",
  "properties": {
    "addr:full": "239 Canal St S Canal Fulton OH 44614",
    "addr:housenumber": "239",
    "addr:postcode": "44614",
    "addr:street": "Canal St S",
    "iso:country": "US",
    "sg:address": "239 Canal St S",
    "sg:city": "Canal Fulton",
    "sg:classifiers": [
      {
        "category": "Professional",
        "type": "Services"
      },
      {
        "category": "Real Estate",
        "subcategory": "Real Estate Operator",
        "type": "Services"
      }
    ],
    "sg:phone": "+1 330 854 1833",
    "sg:postcode": "44614",
    "sg:province": "OH",
    "sg:tags": [
      "property",
      "management",
      "establishment"
    ],
    "wof:name": "K M Quality Management Inc",
    "wof:placetype": "venue"
  },
  "geometry": {"coordinates":[-81.596934,40.888694],"type":"Point"}
}
