{
  "type": "Feature",
  "properties": {
    "addr:full": "2154 Schappelle Ln Cincinnati OH 45240",
    "addr:housenumber": "2154",
    "addr:postcode": "45240",
    "addr:street": "Schappelle Ln",
    "iso:country": "US",
    "sg:address": "2154 Schappelle Ln",
    "sg:city": "Cincinnati",
    "sg:classifiers": [
      {
        "category": "Retail",
        "subcategory": "Repair Shop",
        "type": "Services"
      },
      {
        "category": "Professional",
        "subcategory": "Art Services",
        "type": "Services"
      },
      {
        "category": "Shopping",
        "subcategory": "Antiques",
        "type": "Retail Goods"
      },
      {
        "category": "Wholesale",
        "subcategory": "Construction Materials",
        "type": "Manufacturing \u0026 Wholesale Goods"
      }
    ],
    "sg:phone": "+1 513 851 0123",
    "sg:postcode": "45240",
    "sg:province": "OH",
    "sg:tags": [
      "supply",
      "refinish",
      "caning",
      "restoration",
      "reproduction",
      "furniture"
    ],
    "sg:website": "http://www.furnituremedic.com",
    "wof:name": "Furniture Medic",
    "wof:placetype": "venue"
  },
  "geometry": {"coordinates":[-84.559064,39.283381],"type":"Point"}
}
