{
  "type": "Feature",
  "properties": {
    "iso:country":"US",
    "sg:address":"32 Joyce Dr",
    "sg:city":"Fairborn",
    "sg:classifiers":[
        {
            "category":"Farming",
            "subcategory":"Farm",
            "type":"Manufacturing & Wholesale Goods"
        }
    ],
    "sg:phone":"+1 937 878 3500",
    "sg:postcode":"45324",
    "sg:province":"OH",
    "sg:tags":[
        "crop",
        "general"
    ],
    "wof:name":"Grannan Farms Inc",
    "wof:placetype":"venue"
},
  "geometry": {"coordinates":[-84.026222,39.789085],"type":"Point"}
}