{
  "type": "Feature",
  "properties": {
    "addr:full":"1900 S Davis Ave West Portsmouth OH 45663",
    "addr:housenumber":"1900",
    "addr:postcode":"45663",
    "addr:street":"S Davis Ave",
    "iso:country":"US",
    "sg:address":"1900 S Davis Ave",
    "sg:city":"West Portsmouth",
    "sg:classifiers":[
        {
            "category":"Government",
            "subcategory":"Office",
            "type":"Public Place"
        }
    ],
    "sg:phone":"+1 740 858 2993",
    "sg:postcode":"45663",
    "sg:province":"OH",
    "sg:tags":[
        "village"
    ],
    "wof:name":"Emergency Medical Svc",
    "wof:placetype":"venue"
},
  "geometry": {"coordinates":[-83.03033000000001,38.763511],"type":"Point"}
}