{
  "type": "Feature",
  "properties": {
    "addr:full":"345 N Sandusky Ave Bucyrus OH 44820",
    "addr:housenumber":"345",
    "addr:postcode":"44820",
    "addr:street":"N Sandusky Ave",
    "iso:country":"US",
    "sg:address":"345 N Sandusky Ave",
    "sg:city":"Bucyrus",
    "sg:classifiers":[
        {
            "category":"Shopping",
            "subcategory":"Pharmacy",
            "type":"Retail Goods"
        }
    ],
    "sg:phone":"+1 419 562 4222",
    "sg:postcode":"44820",
    "sg:province":"OH",
    "wof:name":"Medicine Shoppe",
    "wof:placetype":"venue"
},
  "geometry": {"coordinates":[-82.975702,40.811428],"type":"Point"}
}