{
  "type": "Feature",
  "properties": {
    "addr:full":"815 Michigan Ave Waterville OH 43566",
    "addr:housenumber":"815",
    "addr:postcode":"43566",
    "addr:street":"Michigan Ave",
    "iso:country":"US",
    "sg:address":"815 Michigan Ave",
    "sg:city":"Waterville",
    "sg:classifiers":[
        {
            "category":"Retail",
            "subcategory":"Auto Repair",
            "type":"Services"
        }
    ],
    "sg:phone":"+1 419 878 2521",
    "sg:postcode":"43566",
    "sg:province":"OH",
    "sg:tags":[
        "body",
        "shop",
        "painting",
        "automobile"
    ],
    "wof:name":"Waterville Bodyworks Inc",
    "wof:placetype":"venue"
},
  "geometry": {"coordinates":[-83.72582800000001,41.500514],"type":"Point"}
}