{
  "type": "Feature",
  "properties": {
    "addr:full":"127 S Davis Ave Columbus OH 43222",
    "addr:housenumber":"127",
    "addr:postcode":"43222",
    "addr:street":"S Davis Ave",
    "iso:country":"US",
    "sg:address":"127 S Davis Ave",
    "sg:city":"Columbus",
    "sg:classifiers":[
        {
            "category":"Education",
            "subcategory":"College",
            "type":"Public Place"
        },
        {
            "category":"Education",
            "subcategory":"Vocational School",
            "type":"Public Place"
        }
    ],
    "sg:phone":"+1 614 234 5800",
    "sg:postcode":"43222",
    "sg:province":"OH",
    "sg:tags":[
        "academic"
    ],
    "sg:website":"www.mccn.edu",
    "wof:name":"Mount Carmel College Nursing",
    "wof:placetype":"venue"
},
  "geometry": {"coordinates":[-83.021246,39.957133],"type":"Point"}
}