{
  "type": "Feature",
  "properties": {
    "iso:country":"US",
    "sg:address":"106 Pheasantlake Dr",
    "sg:city":"Loveland",
    "sg:classifiers":[
        {
            "category":"Professional",
            "type":"Services"
        }
    ],
    "sg:phone":"+1 513 677 8641",
    "sg:postcode":"45140",
    "sg:province":"OH",
    "wof:name":"Sbgc Inc",
    "wof:placetype":"venue"
},
  "geometry": {"coordinates":[-84.292453,39.267249],"type":"Point"}
}