{
  "type": "Feature",
  "properties": {
    "addr:full": "4845 W Harbor Rd Port Clinton OH 43452",
    "addr:housenumber": "4845",
    "addr:postcode": "43452",
    "addr:street": "W Harbor Rd",
    "iso:country": "US",
    "sg:address": "4845 W Harbor Rd",
    "sg:city": "Port Clinton",
    "sg:phone": "+1 419 635 2500",
    "sg:postcode": "43452",
    "sg:province": "OH",
    "sg:tags": [
      "farm",
      "soybean"
    ],
    "wof:name": "Robert Libben",
    "wof:placetype": "venue"
  },
  "geometry": {"coordinates":[-83.027147,41.517561],"type":"Point"}
}
