{
  "type": "Feature",
  "properties": {
    "addr:full":"5500 Stanley Steamer Pkwy Dublin OH 43016",
    "addr:housenumber":"5500",
    "addr:postcode":"43016",
    "addr:street":"Stanley Steamer Pkwy",
    "iso:country":"US",
    "sg:address":"5500 Stanley Steamer Pkwy",
    "sg:city":"Dublin",
    "sg:classifiers":[
        {
            "category":"Retail",
            "subcategory":"Laundry & Dry Cleaning",
            "type":"Services"
        }
    ],
    "sg:phone":"+1 614 764 2007",
    "sg:postcode":"43016",
    "sg:province":"OH",
    "sg:tags":[
        "cleaners",
        "rug",
        "carpet"
    ],
    "sg:website":"www.stanley-steemer.com",
    "wof:name":"Stanley Steemer Intl Inc",
    "wof:placetype":"venue"
},
  "geometry": {"coordinates":[-83.139217,40.096309],"type":"Point"}
}