{
  "type": "Feature",
  "properties": {
    "iso:country":"US",
    "sg:address":"400 E State Line Rd",
    "sg:city":"Toledo",
    "sg:classifiers":[
        {
            "category":"Manufacturing",
            "subcategory":"Printing",
            "type":"Manufacturing & Wholesale Goods"
        }
    ],
    "sg:phone":"+1 419 478 0695",
    "sg:postcode":"43612",
    "sg:province":"OH",
    "sg:tags":[
        "print",
        "lithographic",
        "typesetting"
    ],
    "sg:website":"www.homewoodpress.com",
    "wof:name":"Homewood Press Inc",
    "wof:placetype":"venue"
},
  "geometry": {"coordinates":[-83.53662,41.728884],"type":"Point"}
}