{
  "type": "Feature",
  "properties": {
    "iso:country":"US",
    "sg:address":"97 E Main St",
    "sg:city":"Batavia",
    "sg:classifiers":[
        {
            "category":"Professional",
            "subcategory":"Lawyer & Legal Services",
            "type":"Services"
        }
    ],
    "sg:phone":"+1 513 732 2212",
    "sg:postcode":"45103",
    "sg:province":"OH",
    "sg:tags":[
        "attorney"
    ],
    "wof:name":"Durkee & Uhle",
    "wof:placetype":"venue"
},
  "geometry": {"coordinates":[-84.178809,39.077962],"type":"Point"}
}