{
  "type": "Feature",
  "properties": {
    "iso:country":"US",
    "sg:address":"14409 Beloit Snodes Rd",
    "sg:city":"Beloit",
    "sg:classifiers":[
        {
            "category":"Education",
            "subcategory":"School",
            "type":"Public Place"
        }
    ],
    "sg:phone":"+1 330 938 6448",
    "sg:postcode":"44609",
    "sg:province":"OH",
    "wof:name":"West Branch Local Schools",
    "wof:placetype":"venue"
},
  "geometry": {"coordinates":[-80.994072,40.901959],"type":"Point"}
}