{
  "type": "Feature",
  "properties": {
    "iso:country":"US",
    "sg:address":"11342 Co Rd Rs",
    "sg:city":"Lyons",
    "sg:classifiers":[
        {
            "category":"Retail",
            "subcategory":"Animal Services",
            "type":"Services"
        }
    ],
    "sg:phone":"+1 419 923 8664",
    "sg:postcode":"43533",
    "sg:province":"OH",
    "wof:name":"Peerces Pet Parlor",
    "wof:placetype":"venue"
},
  "geometry": {"coordinates":[-84.080304,41.678676],"type":"Point"}
}