{
  "type": "Feature",
  "properties": {
    "addr:full": "48 E Hollister St Cincinnati OH 45219",
    "addr:housenumber": "48",
    "addr:postcode": "45219",
    "addr:street": "E Hollister St",
    "iso:country": "US",
    "sg:address": "48 E Hollister St",
    "sg:city": "Cincinnati",
    "sg:classifiers": [
      {
        "category": "Health Services",
        "subcategory": "Health Practitioner",
        "type": "Services"
      }
    ],
    "sg:phone": "+1 513 421 9739",
    "sg:postcode": "45219",
    "sg:province": "OH",
    "sg:tags": [
      "psychologist"
    ],
    "wof:name": "Paul Diamond",
    "wof:placetype": "venue"
  },
  "geometry": {"coordinates":[-84.510082,39.125753],"type":"Point"}
}
