{
  "type": "Feature",
  "properties": {
    "iso:country":"US",
    "sg:address":"1499 State Rte 522",
    "sg:city":"Wheelersburg",
    "sg:classifiers":[
        {
            "category":"Shopping",
            "subcategory":"Jewelry",
            "type":"Retail Goods"
        }
    ],
    "sg:phone":"+1 740 574 8266",
    "sg:postcode":"45694",
    "sg:province":"OH",
    "sg:tags":[
        "jeweler"
    ],
    "wof:name":"Little Treasures",
    "wof:placetype":"venue"
},
  "geometry": {"coordinates":[-82.834907,38.70251],"type":"Point"}
}