{
  "type": "Feature",
  "properties": {
    "addr:full":"6453 Woodlawn Ave Ravenna OH 44266",
    "addr:housenumber":"6453",
    "addr:postcode":"44266",
    "addr:street":"Woodlawn Ave",
    "iso:country":"US",
    "sg:address":"6453 Woodlawn Ave",
    "sg:city":"Ravenna",
    "sg:classifiers":[
        {
            "category":"Professional",
            "type":"Services"
        }
    ],
    "sg:phone":"+1 330 296 7424",
    "sg:postcode":"44266",
    "sg:province":"OH",
    "wof:name":"J D B Inc",
    "wof:placetype":"venue"
},
  "geometry": {"coordinates":[-81.275645,41.165537],"type":"Point"}
}