{
  "type": "Feature",
  "properties": {
    "addr:full":"5118 14th St SW Canton OH 44710",
    "addr:housenumber":"5118",
    "addr:postcode":"44710",
    "addr:street":"14Th St Sw",
    "iso:country":"US",
    "sg:address":"5118 14th St SW",
    "sg:city":"Canton",
    "sg:classifiers":[
        {
            "category":"Retail",
            "subcategory":"Car Wash",
            "type":"Services"
        }
    ],
    "sg:phone":"+1 330 479 0904",
    "sg:postcode":"44710",
    "sg:province":"OH",
    "sg:tags":[
        "automobile",
        "detail",
        "clean"
    ],
    "wof:name":"Auto Cosmetics",
    "wof:placetype":"venue"
},
  "geometry": {"coordinates":[-81.44835399999999,40.788522],"type":"Point"}
}