{
  "type": "Feature",
  "properties": {
    "addr:full": "6515 Revere Ave Cincinnati OH 45233",
    "addr:housenumber": "6515",
    "addr:postcode": "45233",
    "addr:street": "Revere Ave",
    "iso:country": "US",
    "sg:address": "6515 Revere Ave",
    "sg:city": "Cincinnati",
    "sg:classifiers": [
      {
        "category": "Organizations",
        "subcategory": "Religious Organization",
        "type": "Services"
      }
    ],
    "sg:phone": "+1 513 941 7912",
    "sg:postcode": "45233",
    "sg:province": "OH",
    "sg:tags": [
      "church"
    ],
    "wof:name": "First Baptist Church Of Delhi",
    "wof:placetype": "venue"
  },
  "geometry": {"coordinates":[-84.688687,39.110692],"type":"Point"}
}
