{
  "type": "Feature",
  "properties": {
    "iso:country":"US",
    "sg:address":"2150 Monroe-Concord Rd",
    "sg:city":"Troy",
    "sg:classifiers":[
        {
            "category":"Organizations",
            "subcategory":"Religious Organization",
            "type":"Services"
        }
    ],
    "sg:phone":"+1 937 335 7398",
    "sg:postcode":"45373",
    "sg:province":"OH",
    "wof:name":"Corporation of President of Th",
    "wof:placetype":"venue"
},
  "geometry": {"coordinates":[-84.241292,39.99509],"type":"Point"}
}