{
  "type": "Feature",
  "properties": {
    "iso:country":"US",
    "sg:address":"948 N Market St",
    "sg:city":"Troy",
    "sg:classifiers":[
        {
            "category":"Banks & Credit Unions",
            "subcategory":"Bank",
            "type":"Services"
        }
    ],
    "sg:phone":"+1 937 339 9762",
    "sg:postcode":"45373",
    "sg:province":"OH",
    "wof:name":"Fifth Third Bank",
    "wof:placetype":"venue"
},
  "geometry": {"coordinates":[-84.19361000000001,40.050432],"type":"Point"}
}