{
  "type": "Feature",
  "properties": {
    "addr:full": "16567 Johnson Hill Rd Newcomerstown OH 43832",
    "addr:housenumber": "16567",
    "addr:postcode": "43832",
    "addr:street": "Johnson Hill Rd",
    "iso:country": "US",
    "sg:address": "16567 Johnson Hill Rd",
    "sg:city": "Newcomerstown",
    "sg:classifiers": [
      {
        "category": "Building \u0026 Trades",
        "subcategory": "Landscaping Services",
        "type": "Services"
      }
    ],
    "sg:phone": "+1 740 498 6948",
    "sg:postcode": "43832",
    "sg:province": "OH",
    "sg:tags": [
      "landscape"
    ],
    "wof:name": "Frank D \u0026 Jean I Oldt",
    "wof:placetype": "venue"
  },
  "geometry": {"coordinates":[-81.6014,40.24277],"type":"Point"}
}
