{
  "type": "Feature",
  "properties": {
    "addr:full":"5329 Glenway Ave Cincinnati OH 45238",
    "addr:housenumber":"5329",
    "addr:postcode":"45238",
    "addr:street":"Glenway Ave",
    "iso:country":"US",
    "sg:address":"5329 Glenway Ave",
    "sg:city":"Cincinnati",
    "sg:classifiers":[
        {
            "category":"Building & Trades",
            "subcategory":"Construction",
            "type":"Services"
        }
    ],
    "sg:phone":"+1 513 922 8989",
    "sg:postcode":"45238",
    "sg:province":"OH",
    "sg:tags":[
        "roofing",
        "product",
        "door",
        "windows",
        "siding",
        "storm"
    ],
    "wof:name":"Murphy Home Improvement Inc",
    "wof:placetype":"venue"
},
  "geometry": {"coordinates":[-84.60480099999999,39.126355],"type":"Point"}
}