{
  "type": "Feature",
  "properties": {
    "addr:full":"227 Broad St Conneaut OH 44030",
    "addr:housenumber":"227",
    "addr:postcode":"44030",
    "addr:street":"Broad St",
    "iso:country":"US",
    "sg:address":"227 Broad St",
    "sg:city":"Conneaut",
    "sg:classifiers":[
        {
            "category":"Insurance",
            "subcategory":"Insurance Agent",
            "type":"Services"
        }
    ],
    "sg:phone":"+1 440 593 3562",
    "sg:postcode":"44030",
    "sg:province":"OH",
    "wof:name":"Hanson Insurance",
    "wof:placetype":"venue"
},
  "geometry": {"coordinates":[-80.556202,41.943396],"type":"Point"}
}