{
  "type": "Feature",
  "properties": {
    "iso:country":"US",
    "sg:address":"1041 W State St",
    "sg:city":"Alliance",
    "sg:classifiers":[
        {
            "category":"Bakery",
            "type":"Food & Drink"
        },
        {
            "category":"Coffee & Tea",
            "type":"Food & Drink"
        },
        {
            "category":"Bagels",
            "type":"Food & Drink"
        },
        {
            "category":"Donuts",
            "type":"Food & Drink"
        }
    ],
    "sg:menulink":"http://www.allmenus.com/oh/alliance/143932-dunkin-donuts/menu/",
    "sg:phone":"+1 330 823 7621",
    "sg:postcode":"44601",
    "sg:province":"OH",
    "sg:tags":[
        "american",
        "diner",
        "pastry"
    ],
    "wof:name":"Dunkin' Donuts",
    "wof:placetype":"venue"
},
  "geometry": {"coordinates":[-81.119883,40.901799],"type":"Point"}
}