{
  "type": "Feature",
  "properties": {
    "addr:full": "5530 State Rd Cleveland OH 44134",
    "addr:housenumber": "5530",
    "addr:postcode": "44134",
    "addr:street": "State Rd",
    "iso:country": "US",
    "sg:address": "5530 State Rd",
    "sg:city": "Cleveland",
    "sg:classifiers": [
      {
        "category": "Shopping",
        "subcategory": "Bicycles \u0026 Sporting Goods",
        "type": "Retail Goods"
      }
    ],
    "sg:phone": "+1 216 459 0186",
    "sg:postcode": "44134",
    "sg:province": "OH",
    "wof:name": "Car Gen Incorporated",
    "wof:placetype": "venue"
  },
  "geometry": {"coordinates":[-81.710522,41.410786],"type":"Point"}
}
