{
  "type": "Feature",
  "properties": {
    "addr:full": "4652 Warrensville Center Rd Cleveland OH 44128",
    "addr:housenumber": "4652",
    "addr:postcode": "44128",
    "addr:street": "Warrensville Center Rd",
    "iso:country": "US",
    "sg:address": "4652 Warrensville Center Rd",
    "sg:city": "Cleveland",
    "sg:classifiers": [
      {
        "category": "Professional",
        "subcategory": "Management \u0026 Consulting",
        "type": "Services"
      }
    ],
    "sg:phone": "+1 216 581 5900",
    "sg:postcode": "44128",
    "sg:province": "OH",
    "sg:tags": [
      "marketing",
      "consultant"
    ],
    "wof:name": "Singleton \u0026 Partners LTD",
    "wof:placetype": "venue"
  },
  "geometry": {"coordinates":[-81.536135,41.432189],"type":"Point"}
}
