{
  "type": "Feature",
  "properties": {
    "addr:full":"4988 W 150th St Cleveland OH 44135",
    "addr:housenumber":"4988",
    "addr:postcode":"44135",
    "addr:street":"W 150Th St",
    "iso:country":"US",
    "sg:address":"4988 W 150th St",
    "sg:city":"Cleveland",
    "sg:classifiers":[
        {
            "category":"Autos & Motor Vehicles",
            "subcategory":"Auto Supplies",
            "type":"Retail Goods"
        }
    ],
    "sg:phone":"+1 216 362 7059",
    "sg:postcode":"44135",
    "sg:province":"OH",
    "sg:tags":[
        "automobile",
        "stereo",
        "radio"
    ],
    "wof:name":"Audio Outlaws Inc",
    "wof:placetype":"venue"
},
  "geometry": {"coordinates":[-81.802852,41.419555],"type":"Point"}
}