{
  "type": "Feature",
  "properties": {
    "addr:full": "643 Canton Rd Akron OH 44312",
    "addr:housenumber": "643",
    "addr:postcode": "44312",
    "addr:street": "Canton Rd",
    "iso:country": "US",
    "sg:address": "643 Canton Rd",
    "sg:city": "Akron",
    "sg:classifiers": [
      {
        "category": "Personal",
        "subcategory": "Beauty Salon",
        "type": "Services"
      }
    ],
    "sg:phone": "+1 330 733 6128",
    "sg:postcode": "44312",
    "sg:province": "OH",
    "wof:name": "Connie's House Of Hair Fashion",
    "wof:placetype": "venue"
  },
  "geometry": {"coordinates":[-81.437031,41.04611],"type":"Point"}
}
