{
  "type": "Feature",
  "properties": {
    "iso:country":"US",
    "sg:address":"1833 Settlement Rd",
    "sg:city":"Norwalk",
    "sg:classifiers":[
        {
            "category":"Home & Garden",
            "subcategory":"Home Furnishings",
            "type":"Retail Goods"
        }
    ],
    "sg:phone":"+1 419 668 6388",
    "sg:postcode":"44857",
    "sg:province":"OH",
    "sg:tags":[
        "equipment",
        "fireplace"
    ],
    "wof:name":"Hillside Wood Heat",
    "wof:placetype":"venue"
},
  "geometry": {"coordinates":[-82.65633200000001,41.198196],"type":"Point"}
}