{
  "type": "Feature",
  "properties": {
    "addr:full":"723 Lincoln Way W Massillon OH 44647",
    "addr:housenumber":"723",
    "addr:postcode":"44647",
    "addr:street":"Lincoln Way W",
    "iso:country":"US",
    "sg:address":"723 Lincoln Way W",
    "sg:city":"Massillon",
    "sg:classifiers":[
        {
            "category":"Autos & Motor Vehicles",
            "subcategory":"Auto Supplies",
            "type":"Retail Goods"
        }
    ],
    "sg:phone":"+1 330 832 3100",
    "sg:postcode":"44647",
    "sg:province":"OH",
    "sg:tags":[
        "tire"
    ],
    "wof:name":"Hi Way Tire",
    "wof:placetype":"venue"
},
  "geometry": {"coordinates":[-81.532718,40.793741],"type":"Point"}
}