{
  "type": "Feature",
  "properties": {
    "iso:country":"US",
    "sg:address":"5200 Monroe St",
    "sg:city":"Toledo",
    "sg:classifiers":[
        {
            "category":"Cinema",
            "subcategory":"Movie Rental",
            "type":"Entertainment"
        }
    ],
    "sg:phone":"+1 419 843 2341",
    "sg:postcode":"43623",
    "sg:province":"OH",
    "sg:tags":[
        "leasing",
        "video",
        "disc",
        "tape"
    ],
    "wof:name":"Video Connection",
    "wof:placetype":"venue"
},
  "geometry": {"coordinates":[-83.651383,41.701064],"type":"Point"}
}