{
  "type": "Feature",
  "properties": {
    "iso:country":"US",
    "sg:address":"295 E State St",
    "sg:city":"Salem",
    "sg:classifiers":[
        {
            "category":"Banks & Credit Unions",
            "subcategory":"Investment Brokerage",
            "type":"Services"
        }
    ],
    "sg:phone":"+1 330 337 9949",
    "sg:postcode":"44460",
    "sg:province":"OH",
    "sg:tags":[
        "security"
    ],
    "wof:name":"AIG Royal Alliance",
    "wof:placetype":"venue"
},
  "geometry": {"coordinates":[-80.856684,40.900878],"type":"Point"}
}