{
  "type": "Feature",
  "properties": {
    "addr:full": "1005 Jill Ct Piqua OH 45356",
    "addr:housenumber": "1005",
    "addr:postcode": "45356",
    "addr:street": "Jill Ct",
    "iso:country": "US",
    "sg:address": "1005 Jill Ct",
    "sg:city": "Piqua",
    "sg:classifiers": [
      {
        "category": "Communications",
        "type": "Services"
      }
    ],
    "sg:phone": "+1 937 773 4044",
    "sg:postcode": "45356",
    "sg:province": "OH",
    "sg:tags": [
      "communication"
    ],
    "wof:name": "H\u0026H Communications",
    "wof:placetype": "venue"
  },
  "geometry": {"coordinates":[-84.216673,40.165087],"type":"Point"}
}
