{
  "type": "Feature",
  "properties": {
    "addr:full": "856 Campanula Ct Reynoldsburg OH 43068",
    "addr:housenumber": "856",
    "addr:postcode": "43068",
    "addr:street": "Campanula Ct",
    "iso:country": "US",
    "sg:address": "856 Campanula Ct",
    "sg:city": "Reynoldsburg",
    "sg:classifiers": [
      {
        "category": "Bars \u0026 Pubs",
        "type": "Food \u0026 Drink"
      }
    ],
    "sg:phone": "+1 614 860 1167",
    "sg:postcode": "43068",
    "sg:province": "OH",
    "sg:tags": [
      "drinking"
    ],
    "wof:name": "Solza Inc",
    "wof:placetype": "venue"
  },
  "geometry": {"coordinates":[-82.761391,39.9717],"type":"Point"}
}
