{
  "type": "Feature",
  "properties": {
    "iso:country":"US",
    "sg:address":"425 Prospect St",
    "sg:city":"Dover",
    "sg:classifiers":[
        {
            "category":"Social Services",
            "type":"Services"
        }
    ],
    "sg:phone":"+1 330 364 6611",
    "sg:postcode":"44622",
    "sg:province":"OH",
    "sg:tags":[
        "organization",
        "welfare"
    ],
    "wof:name":"Senior Center Of Tuscarawas",
    "wof:placetype":"venue"
},
  "geometry": {"coordinates":[-81.465418,40.510391],"type":"Point"}
}