{
  "type": "Feature",
  "properties": {
    "iso:country":"US",
    "sg:address":"9465 State Rte 202",
    "sg:city":"Tipp City",
    "sg:classifiers":[
        {
            "category":"Building & Trades",
            "subcategory":"Construction",
            "type":"Services"
        }
    ],
    "sg:phone":"+1 937 667 8713",
    "sg:postcode":"45371",
    "sg:province":"OH",
    "sg:tags":[
        "excavating",
        "contractor"
    ],
    "wof:name":"D & M Excavating Inc",
    "wof:placetype":"venue"
},
  "geometry": {"coordinates":[-84.13533200000001,39.892633],"type":"Point"}
}