{
  "type": "Feature",
  "properties": {
    "addr:full": "9465 State Rte 202 Tipp City OH 45371",
    "addr:housenumber": "9465",
    "addr:postcode": "45371",
    "addr:street": "State Rte 202",
    "iso:country": "US",
    "sg:address": "9465 State Rte 202",
    "sg:city": "Tipp City",
    "sg:classifiers": [
      {
        "category": "Building \u0026 Trades",
        "subcategory": "Construction",
        "type": "Services"
      }
    ],
    "sg:phone": "+1 937 667 8713",
    "sg:postcode": "45371",
    "sg:province": "OH",
    "sg:tags": [
      "excavating",
      "contractor"
    ],
    "wof:name": "D \u0026 M Excavating Inc",
    "wof:placetype": "venue"
  },
  "geometry": {"coordinates":[-84.135332,39.892633],"type":"Point"}
}
