{
  "type": "Feature",
  "properties": {
    "addr:full": "1235 Nottingham Rd Amelia OH 45102",
    "addr:housenumber": "1235",
    "addr:postcode": "45102",
    "addr:street": "Nottingham Rd",
    "iso:country": "US",
    "sg:address": "1235 Nottingham Rd",
    "sg:city": "Amelia",
    "sg:classifiers": [
      {
        "category": "Building \u0026 Trades",
        "subcategory": "Construction",
        "type": "Services"
      }
    ],
    "sg:phone": "+1 513 673 8473",
    "sg:postcode": "45102",
    "sg:province": "OH",
    "sg:tags": [
      "house"
    ],
    "wof:name": "Construx Building Services",
    "wof:placetype": "venue"
  },
  "geometry": {"coordinates":[-84.236145,39.054555],"type":"Point"}
}
