{
  "type": "Feature",
  "properties": {
    "iso:country":"US",
    "sg:address":"137 N Market St",
    "sg:city":"Wooster",
    "sg:classifiers":[
        {
            "category":"Shopping",
            "subcategory":"Jewelry",
            "type":"Retail Goods"
        }
    ],
    "sg:phone":"+1 330 264 5367",
    "sg:postcode":"44691",
    "sg:province":"OH",
    "sg:tags":[
        "jeweler"
    ],
    "wof:name":"Malcuit Jewelers",
    "wof:placetype":"venue"
},
  "geometry": {"coordinates":[-81.94008100000001,40.799001],"type":"Point"}
}