{
  "type": "Feature",
  "properties": {
    "addr:full":"14410 Cedar Rd Cleveland OH 44121",
    "addr:housenumber":"14410",
    "addr:postcode":"44121",
    "addr:street":"Cedar Rd",
    "iso:country":"US",
    "sg:address":"14410 Cedar Rd",
    "sg:city":"Cleveland",
    "sg:classifiers":[
        {
            "category":"Retail",
            "subcategory":"Laundry & Dry Cleaning",
            "type":"Services"
        }
    ],
    "sg:phone":"+1 216 381 3000",
    "sg:postcode":"44121",
    "sg:province":"OH",
    "sg:tags":[
        "cleaners"
    ],
    "wof:name":"Gate Cleaners Inc",
    "wof:placetype":"venue"
},
  "geometry": {"coordinates":[-81.519488,41.501282],"type":"Point"}
}