{
  "type": "Feature",
  "properties": {
    "iso:country":"US",
    "sg:address":"4285 Deepwood Ln",
    "sg:city":"Toledo",
    "sg:classifiers":[
        {
            "category":"Real Estate",
            "subcategory":"Real Estate Operator",
            "type":"Services"
        }
    ],
    "sg:phone":"+1 419 382 9701",
    "sg:postcode":"43614",
    "sg:province":"OH",
    "sg:tags":[
        "condominium"
    ],
    "wof:name":"Riverside Commons",
    "wof:placetype":"venue"
},
  "geometry": {"coordinates":[-83.60636700000001,41.590089],"type":"Point"}
}