{
  "type": "Feature",
  "properties": {
    "addr:full": "31 Jayne Ave Shelby OH 44875",
    "addr:housenumber": "31",
    "addr:postcode": "44875",
    "addr:street": "Jayne Ave",
    "iso:country": "US",
    "sg:address": "31 Jayne Ave",
    "sg:city": "Shelby",
    "sg:classifiers": [
      {
        "category": "Freight",
        "type": "Transportation"
      }
    ],
    "sg:phone": "+1 419 347 7656",
    "sg:postcode": "44875",
    "sg:province": "OH",
    "sg:tags": [
      "operator",
      "local",
      "trucking"
    ],
    "wof:name": "Mullins Stoney",
    "wof:placetype": "venue"
  },
  "geometry": {"coordinates":[-82.666472,40.865633],"type":"Point"}
}
