{
  "type": "Feature",
  "properties": {
    "addr:full": "415 Brewer Ave Akron OH 44305",
    "addr:housenumber": "415",
    "addr:postcode": "44305",
    "addr:street": "Brewer Ave",
    "iso:country": "US",
    "sg:address": "415 Brewer Ave",
    "sg:city": "Akron",
    "sg:classifiers": [
      {
        "category": "Building \u0026 Trades",
        "subcategory": "Construction",
        "type": "Services"
      }
    ],
    "sg:phone": "+1 330 784 7063",
    "sg:postcode": "44305",
    "sg:province": "OH",
    "sg:tags": [
      "contracting",
      "general"
    ],
    "wof:name": "Apex General Contracting LLC",
    "wof:placetype": "venue"
  },
  "geometry": {"coordinates":[-81.438361,41.073743],"type":"Point"}
}
