{
  "type": "Feature",
  "properties": {
    "iso:country":"US",
    "sg:address":"375 S High St",
    "sg:city":"Columbus",
    "sg:classifiers":[
        {
            "category":"Professional",
            "subcategory":"Lawyer & Legal Services",
            "type":"Services"
        }
    ],
    "sg:phone":"+1 614 645 6624",
    "sg:postcode":"43215",
    "sg:province":"OH",
    "wof:name":"City Attorney",
    "wof:placetype":"venue"
},
  "geometry": {"coordinates":[-82.99908600000001,39.953877],"type":"Point"}
}