{
  "type": "Feature",
  "properties": {
    "addr:full": "375 S High St Columbus OH 43215",
    "addr:housenumber": "375",
    "addr:postcode": "43215",
    "addr:street": "S High St",
    "iso:country": "US",
    "sg:address": "375 S High St",
    "sg:city": "Columbus",
    "sg:classifiers": [
      {
        "category": "Professional",
        "subcategory": "Lawyer \u0026 Legal Services",
        "type": "Services"
      }
    ],
    "sg:phone": "+1 614 645 6624",
    "sg:postcode": "43215",
    "sg:province": "OH",
    "wof:name": "City Attorney",
    "wof:placetype": "venue"
  },
  "geometry": {"coordinates":[-82.999086,39.953877],"type":"Point"}
}
