{
  "type": "Feature",
  "properties": {
    "addr:full":"5855 John Glenn Hwy Cambridge OH 43725",
    "addr:housenumber":"5855",
    "addr:postcode":"43725",
    "addr:street":"John Glenn Hwy",
    "iso:country":"US",
    "sg:address":"5855 John Glenn Hwy",
    "sg:city":"Cambridge",
    "sg:classifiers":[
        {
            "category":"Professional",
            "subcategory":"Business Services",
            "type":"Services"
        }
    ],
    "sg:phone":"+1 740 432 7400",
    "sg:postcode":"43725",
    "sg:province":"OH",
    "sg:tags":[
        "auctioneer"
    ],
    "sg:website":"www.mcmastersharris.com",
    "wof:name":"Mc Masters Harris Auction Co",
    "wof:placetype":"venue"
},
  "geometry": {"coordinates":[-81.634681,40.012057],"type":"Point"}
}