{
  "type": "Feature",
  "properties": {
    "addr:full":"444 Earl St Toledo OH 43605",
    "addr:housenumber":"444",
    "addr:postcode":"43605",
    "addr:street":"Earl St",
    "iso:country":"US",
    "sg:address":"444 Earl St",
    "sg:city":"Toledo",
    "sg:classifiers":[
        {
            "category":"Shopping",
            "subcategory":"Used Merchandise",
            "type":"Retail Goods"
        }
    ],
    "sg:phone":"+1 419 697 7283",
    "sg:postcode":"43605",
    "sg:province":"OH",
    "sg:tags":[
        "shop",
        "thrift"
    ],
    "wof:name":"Saving Station",
    "wof:placetype":"venue"
},
  "geometry": {"coordinates":[-83.52412699999999,41.631772],"type":"Point"}
}