{
  "type": "Feature",
  "properties": {
    "iso:country":"US",
    "sg:address":"17 S High St",
    "sg:city":"Columbus",
    "sg:classifiers":[
        {
            "category":"Communications",
            "subcategory":"News Services",
            "type":"Services"
        }
    ],
    "sg:phone":"+1 614 221 1992",
    "sg:postcode":"43215",
    "sg:province":"OH",
    "sg:website":"www.gongwer-oh.com",
    "wof:name":"Gongwer News Svc Inc",
    "wof:placetype":"venue"
},
  "geometry": {"coordinates":[-83.000658,39.961976],"type":"Point"}
}