{
  "type": "Feature",
  "properties": {
    "addr:full":"215 W Garfield Rd Aurora OH 44202",
    "addr:housenumber":"215",
    "addr:postcode":"44202",
    "addr:street":"W Garfield Rd",
    "iso:country":"US",
    "sg:address":"215 W Garfield Rd",
    "sg:city":"Aurora",
    "sg:classifiers":[
        {
            "category":"Personal",
            "subcategory":"Beauty Salon",
            "type":"Services"
        }
    ],
    "sg:phone":"+1 330 562 8090",
    "sg:postcode":"44202",
    "sg:province":"OH",
    "sg:website":"www.chamberlainshair.com",
    "wof:name":"Chamberlain's Hair & Day Spa",
    "wof:placetype":"venue"
},
  "geometry": {"coordinates":[-81.35067600000001,41.317337],"type":"Point"}
}