{
  "type": "Feature",
  "properties": {
    "addr:full":"4251 N Holland Sylvania Ave Toledo OH 43623",
    "addr:housenumber":"4251",
    "addr:postcode":"43623",
    "addr:street":"N Holland Sylvania Ave",
    "iso:country":"US",
    "sg:address":"4251 N Holland Sylvania Ave",
    "sg:city":"Toledo",
    "sg:classifiers":[
        {
            "category":"Retail",
            "subcategory":"Car Wash",
            "type":"Services"
        }
    ],
    "sg:phone":"+1 419 824 3200",
    "sg:postcode":"43623",
    "sg:province":"OH",
    "sg:tags":[
        "polishing",
        "washing"
    ],
    "wof:name":"Sylvania Car Wash",
    "wof:placetype":"venue"
},
  "geometry": {"coordinates":[-83.686645,41.692242],"type":"Point"}
}