{
  "type": "Feature",
  "properties": {
    "iso:country":"US",
    "sg:address":"6801 Fairfield Rd",
    "sg:city":"Oxford",
    "sg:classifiers":[
        {
            "category":"Recreation",
            "type":"Entertainment"
        }
    ],
    "sg:phone":"+1 513 523 0131",
    "sg:postcode":"45056",
    "sg:province":"OH",
    "sg:tags":[
        "parks"
    ],
    "wof:name":"Oxford Community Park",
    "wof:placetype":"venue"
},
  "geometry": {"coordinates":[-84.777101,39.508152],"type":"Point"}
}