{
  "type": "Feature",
  "properties": {
    "addr:full": "481 Lloyd Rd Euclid OH 44132",
    "addr:housenumber": "481",
    "addr:postcode": "44132",
    "addr:street": "Lloyd Rd",
    "iso:country": "US",
    "sg:address": "481 Lloyd Rd",
    "sg:city": "Euclid",
    "sg:classifiers": [
      {
        "category": "Professional",
        "type": "Services"
      }
    ],
    "sg:phone": "+1 216 731 3707",
    "sg:postcode": "44132",
    "sg:province": "OH",
    "wof:name": "JRC Systems \u0026 Prodecures",
    "wof:placetype": "venue"
  },
  "geometry": {"coordinates":[-81.488921,41.618693],"type":"Point"}
}
