{
  "type": "Feature",
  "properties": {
    "iso:country":"US",
    "sg:address":"481 Lloyd Rd",
    "sg:city":"Euclid",
    "sg:classifiers":[
        {
            "category":"Professional",
            "type":"Services"
        }
    ],
    "sg:phone":"+1 216 731 3707",
    "sg:postcode":"44132",
    "sg:province":"OH",
    "wof:name":"JRC Systems & Prodecures",
    "wof:placetype":"venue"
},
  "geometry": {"coordinates":[-81.488921,41.618693],"type":"Point"}
}