{
  "type": "Feature",
  "properties": {
    "addr:full":"1208 Lincoln Way E Massillon OH 44646",
    "addr:housenumber":"1208",
    "addr:postcode":"44646",
    "addr:street":"Lincoln Way E",
    "iso:country":"US",
    "sg:address":"1208 Lincoln Way E",
    "sg:city":"Massillon",
    "sg:classifiers":[
        {
            "category":"Restaurant",
            "type":"Food & Drink"
        }
    ],
    "sg:phone":"+1 330 833 0344",
    "sg:postcode":"44646",
    "sg:province":"OH",
    "wof:name":"Fazoli's",
    "wof:placetype":"venue"
},
  "geometry": {"coordinates":[-81.509193,40.800236],"type":"Point"}
}