{
  "type": "Feature",
  "properties": {
    "iso:country":"US",
    "sg:address":"6848 Loop Rd",
    "sg:city":"Dayton",
    "sg:classifiers":[
        {
            "category":"Health Services",
            "subcategory":"Medical Lab",
            "type":"Services"
        }
    ],
    "sg:phone":"+1 937 291 6400",
    "sg:postcode":"45459",
    "sg:province":"OH",
    "sg:tags":[
        "laboratory"
    ],
    "wof:name":"Isis Medical",
    "wof:placetype":"venue"
},
  "geometry": {"coordinates":[-84.148207,39.643775],"type":"Point"}
}