{
  "type": "Feature",
  "properties": {
    "iso:country":"US",
    "sg:address":"11 W Monument Ave",
    "sg:city":"Dayton",
    "sg:classifiers":[
        {
            "category":"Organizations",
            "subcategory":"Professional Association",
            "type":"Services"
        }
    ],
    "sg:phone":"+1 937 586 3727",
    "sg:postcode":"45402",
    "sg:province":"OH",
    "wof:name":"Association - Destination Mgmt",
    "wof:placetype":"venue"
},
  "geometry": {"coordinates":[-84.193158,39.763757],"type":"Point"}
}