{
  "type": "Feature",
  "properties": {
    "addr:full":"2026 E Harbor Rd Port Clinton OH 43452",
    "addr:housenumber":"2026 e",
    "addr:postcode":"43452",
    "addr:street":"Harbor Rd",
    "iso:country":"US",
    "sg:address":"2026 E Harbor Rd",
    "sg:city":"Port Clinton",
    "sg:classifiers":[
        {
            "category":"Cinema",
            "subcategory":"Movie Rental",
            "type":"Entertainment"
        }
    ],
    "sg:phone":"+1 419 734 4180",
    "sg:postcode":"43452",
    "sg:province":"OH",
    "sg:tags":[
        "leasing",
        "video",
        "disc",
        "tape"
    ],
    "sg:website":"www.moviegallery.com",
    "wof:name":"Movie Gallery",
    "wof:placetype":"venue"
},
  "geometry": {"coordinates":[-82.901725,41.516109],"type":"Point"}
}