{
  "type": "Feature",
  "properties": {
    "addr:full": "205 Beechpoint Dr Oxford IN 45056",
    "addr:housenumber": "205",
    "addr:postcode": "45056",
    "addr:street": "Beechpoint Dr",
    "iso:country": "US",
    "sg:address": "205 Beechpoint Dr",
    "sg:city": "Oxford",
    "sg:classifiers": [
      {
        "category": "Professional",
        "type": "Services"
      }
    ],
    "sg:phone": "+1 513 523 3188",
    "sg:postcode": "45056",
    "sg:province": "IN",
    "wof:name": "George Seltzer",
    "wof:placetype": "venue"
  },
  "geometry": {"coordinates":[-84.707227,39.505999],"type":"Point"}
}
