{
  "type": "Feature",
  "properties": {
    "addr:full":"940 N Cable Rd Lima OH 45805",
    "addr:housenumber":"940",
    "addr:postcode":"45805",
    "addr:street":"N Cable Rd",
    "iso:country":"US",
    "sg:address":"940 N Cable Rd",
    "sg:city":"Lima",
    "sg:classifiers":[
        {
            "category":"Health Services",
            "subcategory":"Health Practitioner",
            "type":"Services"
        }
    ],
    "sg:phone":"+1 419 222 1029",
    "sg:postcode":"45805",
    "sg:province":"OH",
    "sg:tags":[
        "psychologist"
    ],
    "wof:name":"Coping Strategies",
    "wof:placetype":"venue"
},
  "geometry": {"coordinates":[-84.146947,40.754431],"type":"Point"}
}