{
  "type": "Feature",
  "properties": {
    "addr:full": "10303 Scull Rd Cincinnati OH 45252",
    "addr:housenumber": "10303",
    "addr:postcode": "45252",
    "addr:street": "Scull Rd",
    "iso:country": "US",
    "sg:address": "10303 Scull Rd",
    "sg:city": "Cincinnati",
    "sg:classifiers": [
      {
        "category": "Professional",
        "subcategory": "Management \u0026 Consulting",
        "type": "Services"
      },
      {
        "category": "Professional",
        "subcategory": "Engineering",
        "type": "Services"
      }
    ],
    "sg:phone": "+1 513 290 8623",
    "sg:postcode": "45252",
    "sg:province": "OH",
    "sg:tags": [
      "environmental",
      "ecological",
      "engineer",
      "consultant"
    ],
    "wof:name": "Environmental Health Solutions",
    "wof:placetype": "venue"
  },
  "geometry": {"coordinates":[-84.647851,39.261637],"type":"Point"}
}
