{
  "type": "Feature",
  "properties": {
    "iso:country":"US",
    "sg:address":"8972 Albany Rd",
    "sg:city":"Athens",
    "sg:classifiers":[
        {
            "category":"Shopping",
            "subcategory":"Pharmacy",
            "type":"Retail Goods"
        }
    ],
    "sg:phone":"+1 740 594 3092",
    "sg:postcode":"45701",
    "sg:province":"OH",
    "wof:name":"Fruth Pharmacy 9",
    "wof:placetype":"venue"
},
  "geometry": {"coordinates":[-82.10565699999999,39.304434],"type":"Point"}
}