{
  "type": "Feature",
  "properties": {
    "addr:full":"2740 Shaftesbury Dr NW Canton OH 44708",
    "addr:housenumber":"2740",
    "addr:postcode":"44708",
    "addr:street":"Shaftesbury Dr Nw",
    "iso:country":"US",
    "sg:address":"2740 Shaftesbury Dr NW",
    "sg:city":"Canton",
    "sg:classifiers":[
        {
            "category":"Real Estate",
            "subcategory":"Real Estate Operator",
            "type":"Services"
        }
    ],
    "sg:phone":"+1 330 477 6717",
    "sg:postcode":"44708",
    "sg:province":"OH",
    "sg:tags":[
        "apartment"
    ],
    "wof:name":"London Square Apartments",
    "wof:placetype":"venue"
},
  "geometry": {"coordinates":[-81.426575,40.827653],"type":"Point"}
}