{
  "type": "Feature",
  "properties": {
    "iso:country":"US",
    "sg:address":"6250 Corporate Center Dr",
    "sg:city":"Dublin",
    "sg:classifiers":[
        {
            "category":"Building & Trades",
            "subcategory":"Construction",
            "type":"Services"
        }
    ],
    "sg:phone":"+1 614 659 9485",
    "sg:postcode":"43016",
    "sg:province":"OH",
    "sg:tags":[
        "concrete",
        "contractor"
    ],
    "wof:name":"Concrete & Plumbing Supplies",
    "wof:placetype":"venue"
},
  "geometry": {"coordinates":[-83.159448,40.082354],"type":"Point"}
}