{
  "type": "Feature",
  "properties": {
    "addr:full": "2000 Chestnut Hill Dr Youngstown OH 44511",
    "addr:housenumber": "2000",
    "addr:postcode": "44511",
    "addr:street": "Chestnut Hill Dr",
    "iso:country": "US",
    "sg:address": "2000 Chestnut Hill Dr",
    "sg:city": "Youngstown",
    "sg:classifiers": [
      {
        "category": "Professional",
        "type": "Services"
      }
    ],
    "sg:phone": "+1 330 799 0858",
    "sg:postcode": "44511",
    "sg:province": "OH",
    "sg:tags": [
      "establishment"
    ],
    "wof:name": "Chestnut Hill Pavillion",
    "wof:placetype": "venue"
  },
  "geometry": {"coordinates":[-80.70246,41.080334],"type":"Point"}
}
