{
  "type": "Feature",
  "properties": {
    "iso:country":"US",
    "sg:address":"16740 Peters Rd",
    "sg:city":"Middlefield",
    "sg:classifiers":[
        {
            "category":"Professional",
            "type":"Services"
        }
    ],
    "sg:phone":"+1 440 632 5541",
    "sg:postcode":"44062",
    "sg:province":"OH",
    "sg:tags":[
        "establishment"
    ],
    "wof:name":"S Squared Laboratory",
    "wof:placetype":"venue"
},
  "geometry": {"coordinates":[-81.046086,41.493979],"type":"Point"}
}