{
  "type": "Feature",
  "properties": {
    "iso:country":"US",
    "sg:address":"2704 Erie Ave",
    "sg:city":"Cincinnati",
    "sg:classifiers":[
        {
            "category":"Restaurant",
            "type":"Food & Drink"
        }
    ],
    "sg:phone":"+1 513 321 6221",
    "sg:postcode":"45208",
    "sg:province":"OH",
    "sg:tags":[
        "parlor",
        "ice",
        "cream"
    ],
    "sg:website":"www.graeters.com",
    "wof:name":"Graeter's",
    "wof:placetype":"venue"
},
  "geometry": {"coordinates":[-84.44175799999999,39.139591],"type":"Point"}
}