{
  "type": "Feature",
  "properties": {
    "addr:full": "2704 Erie Ave Cincinnati OH 45208",
    "addr:housenumber": "2704",
    "addr:postcode": "45208",
    "addr:street": "Erie Ave",
    "iso:country": "US",
    "sg:address": "2704 Erie Ave",
    "sg:city": "Cincinnati",
    "sg:classifiers": [
      {
        "category": "Restaurant",
        "type": "Food \u0026 Drink"
      }
    ],
    "sg:phone": "+1 513 321 6221",
    "sg:postcode": "45208",
    "sg:province": "OH",
    "sg:tags": [
      "parlor",
      "ice",
      "cream"
    ],
    "sg:website": "www.graeters.com",
    "wof:name": "Graeter's",
    "wof:placetype": "venue"
  },
  "geometry": {"coordinates":[-84.441758,39.139591],"type":"Point"}
}
