{
  "type": "Feature",
  "properties": {
    "addr:full": "4825 Old Logan Rd SE Lancaster OH 43130",
    "addr:housenumber": "4825",
    "addr:postcode": "43130",
    "addr:street": "Old Logan Rd Se",
    "iso:country": "US",
    "sg:address": "4825 Old Logan Rd SE",
    "sg:city": "Lancaster",
    "sg:classifiers": [
      {
        "category": "Building \u0026 Trades",
        "subcategory": "Construction",
        "type": "Services"
      }
    ],
    "sg:phone": "+1 740 653 3599",
    "sg:postcode": "43130",
    "sg:province": "OH",
    "sg:tags": [
      "general",
      "contractor"
    ],
    "wof:name": "Tobias Holdings Inc",
    "wof:placetype": "venue"
  },
  "geometry": {"coordinates":[-82.560086,39.652877],"type":"Point"}
}
