{
  "type": "Feature",
  "properties": {
    "addr:full":"1165 Swartz Rd Akron OH 44306",
    "addr:housenumber":"1165",
    "addr:postcode":"44306",
    "addr:street":"Swartz Rd",
    "iso:country":"US",
    "sg:address":"1165 Swartz Rd",
    "sg:city":"Akron",
    "sg:classifiers":[
        {
            "category":"Retail",
            "subcategory":"Animal Services",
            "type":"Services"
        }
    ],
    "sg:phone":"+1 330 724 8233",
    "sg:postcode":"44306",
    "sg:province":"OH",
    "wof:name":"Clippe Joint",
    "wof:placetype":"venue"
},
  "geometry": {"coordinates":[-81.48668499999999,41.017861],"type":"Point"}
}