{
  "type": "Feature",
  "properties": {
    "iso:country":"US",
    "sg:address":"4807 Cedar Ave",
    "sg:city":"Cleveland",
    "sg:classifiers":[
        {
            "category":"Social Services",
            "type":"Services"
        }
    ],
    "sg:phone":"+1 216 431 4979",
    "sg:postcode":"44103",
    "sg:province":"OH",
    "sg:tags":[
        "organization",
        "welfare"
    ],
    "wof:name":"Fresh Start Halfway-House Inc",
    "wof:placetype":"venue"
},
  "geometry": {"coordinates":[-81.65466000000001,41.50013],"type":"Point"}
}