{
  "type": "Feature",
  "properties": {
    "addr:full": "134 W Main St Circleville OH 43113",
    "addr:housenumber": "134",
    "addr:postcode": "43113",
    "addr:street": "W Main St",
    "iso:country": "US",
    "sg:address": "134 W Main St",
    "sg:city": "Circleville",
    "sg:classifiers": [
      {
        "category": "Personal",
        "type": "Services"
      }
    ],
    "sg:phone": "+1 740 420 9111",
    "sg:postcode": "43113",
    "sg:province": "OH",
    "sg:tags": [
      "wear",
      "formal"
    ],
    "wof:name": "Uniquely Yours",
    "wof:placetype": "venue"
  },
  "geometry": {"coordinates":[-82.946899,39.602491],"type":"Point"}
}
