{
  "type": "Feature",
  "properties": {
    "addr:full":"1105 Co Rd 30A Ashland OH 44805",
    "addr:housenumber":"1105;30a",
    "addr:postcode":"44805",
    "addr:street":"Co Rd",
    "iso:country":"US",
    "sg:address":"1105 Co Rd 30A",
    "sg:city":"Ashland",
    "sg:classifiers":[
        {
            "category":"Building & Trades",
            "subcategory":"Equipment Rental",
            "type":"Services"
        }
    ],
    "sg:phone":"+1 419 368 9061",
    "sg:postcode":"44805",
    "sg:province":"OH",
    "sg:tags":[
        "yard"
    ],
    "wof:name":"Cooler Solutions",
    "wof:placetype":"venue"
},
  "geometry": {"coordinates":[-82.34068499999999,40.773508],"type":"Point"}
}