{
  "type": "Feature",
  "properties": {
    "iso:country":"US",
    "sg:address":"3900 Euclid Ave",
    "sg:city":"Cleveland",
    "sg:classifiers":[
        {
            "category":"Government",
            "subcategory":"Office",
            "type":"Public Place"
        }
    ],
    "sg:phone":"+1 216 881 8247",
    "sg:postcode":"44115",
    "sg:province":"OH",
    "sg:tags":[
        "agency"
    ],
    "wof:name":"N E Ohio Regional Sewer Dist",
    "wof:placetype":"venue"
},
  "geometry": {"coordinates":[-81.660586,41.503095],"type":"Point"}
}