{
  "type": "Feature",
  "properties": {
    "addr:full":"1091 State Rte 133 Bethel OH 45106",
    "addr:housenumber":"1091",
    "addr:postcode":"45106",
    "addr:street":"State Rte 133",
    "iso:country":"US",
    "sg:address":"1091 State Rte 133",
    "sg:city":"Bethel",
    "sg:classifiers":[
        {
            "category":"Food & Beverages",
            "subcategory":"Liquor & Beverages",
            "type":"Retail Goods"
        }
    ],
    "sg:phone":"+1 513 876 0726",
    "sg:postcode":"45106",
    "sg:province":"OH",
    "sg:tags":[
        "beer",
        "ale"
    ],
    "wof:name":"Campbell's Carryout",
    "wof:placetype":"venue"
},
  "geometry": {"coordinates":[-84.095146,38.842161],"type":"Point"}
}