{
  "type": "Feature",
  "properties": {
    "addr:full":"2892 Beechwood Ave Paris OH 44669",
    "addr:housenumber":"2892",
    "addr:postcode":"44669",
    "addr:street":"Beechwood Ave",
    "iso:country":"US",
    "sg:address":"2892 Beechwood Ave",
    "sg:city":"Paris",
    "sg:classifiers":[
        {
            "category":"Wholesale",
            "subcategory":"Farm Supplies",
            "type":"Manufacturing & Wholesale Goods"
        }
    ],
    "sg:phone":"+1 330 862 2170",
    "sg:postcode":"44669",
    "sg:province":"OH",
    "wof:name":"Harry Beaber & Sons Inc",
    "wof:placetype":"venue"
},
  "geometry": {"coordinates":[-81.16256,40.802675],"type":"Point"}
}