{
  "type": "Feature",
  "properties": {
    "addr:full": "7619 State Rte 53 N Upper Sandusky OH 43351",
    "addr:housenumber": "7619",
    "addr:postcode": "43351",
    "addr:street": "State Rte 53 N",
    "iso:country": "US",
    "sg:address": "7619 State Rte 53 N",
    "sg:city": "Upper Sandusky",
    "sg:classifiers": [
      {
        "category": "Retail",
        "subcategory": "Veterinary Services",
        "type": "Services"
      }
    ],
    "sg:phone": "+1 419 294 1619",
    "sg:postcode": "43351",
    "sg:province": "OH",
    "sg:tags": [
      "animal"
    ],
    "wof:name": "Upper Sandusky Animal Clinic",
    "wof:placetype": "venue"
  },
  "geometry": {"coordinates":[-83.276999,40.881907],"type":"Point"}
}
