{
  "type": "Feature",
  "properties": {
    "iso:country":"US",
    "sg:address":"8916 Bloomfield Geneva Rd",
    "sg:city":"North Bloomfield",
    "sg:classifiers":[
        {
            "category":"Organizations",
            "subcategory":"Religious Organization",
            "type":"Services"
        }
    ],
    "sg:phone":"+1 330 583 2174",
    "sg:postcode":"44450",
    "sg:province":"OH",
    "sg:tags":[
        "church"
    ],
    "wof:name":"Greene Church Of The Nazarene",
    "wof:placetype":"venue"
},
  "geometry": {"coordinates":[-80.868414,41.464207],"type":"Point"}
}