{
  "type": "Feature",
  "properties": {
    "addr:full": "1605 N Limestone St Springfield OH 45503",
    "addr:housenumber": "1605",
    "addr:postcode": "45503",
    "addr:street": "N Limestone St",
    "iso:country": "US",
    "sg:address": "1605 N Limestone St",
    "sg:city": "Springfield",
    "sg:classifiers": [
      {
        "category": "Professional",
        "subcategory": "Accounting \u0026 Tax Preparation",
        "type": "Services"
      }
    ],
    "sg:phone": "+1 937 342 1040",
    "sg:postcode": "45503",
    "sg:province": "OH",
    "sg:tags": [
      "return",
      "filing"
    ],
    "wof:name": "Laird's Tax \u0026 Financial Svc",
    "wof:placetype": "venue"
  },
  "geometry": {"coordinates":[-83.804972,39.943808],"type":"Point"}
}
