{
  "type": "Feature",
  "properties": {
    "iso:country":"US",
    "sg:address":"1605 N Limestone St",
    "sg:city":"Springfield",
    "sg:classifiers":[
        {
            "category":"Professional",
            "subcategory":"Accounting & Tax Preparation",
            "type":"Services"
        }
    ],
    "sg:phone":"+1 937 342 1040",
    "sg:postcode":"45503",
    "sg:province":"OH",
    "sg:tags":[
        "return",
        "filing"
    ],
    "wof:name":"Laird's Tax & Financial Svc",
    "wof:placetype":"venue"
},
  "geometry": {"coordinates":[-83.80497200000001,39.943808],"type":"Point"}
}