{
  "type": "Feature",
  "properties": {
    "iso:country":"US",
    "sg:address":"6242 Pheasant Hill Rd",
    "sg:city":"Dayton",
    "sg:classifiers":[
        {
            "category":"Building & Trades",
            "subcategory":"Construction",
            "type":"Services"
        }
    ],
    "sg:phone":"+1 937 233 4040",
    "sg:postcode":"45424",
    "sg:province":"OH",
    "sg:tags":[
        "general",
        "contractor"
    ],
    "wof:name":"Christian-Moorer Construction",
    "wof:placetype":"venue"
},
  "geometry": {"coordinates":[-84.10791999999999,39.825803],"type":"Point"}
}