{
  "type": "Feature",
  "properties": {
    "addr:full":"240 Browns Ln Coshocton OH 43812",
    "addr:housenumber":"240",
    "addr:postcode":"43812",
    "addr:street":"Browns Ln",
    "iso:country":"US",
    "sg:address":"240 Browns Ln",
    "sg:city":"Coshocton",
    "sg:classifiers":[
        {
            "category":"Wholesale",
            "subcategory":"Non-durable Goods",
            "type":"Manufacturing & Wholesale Goods"
        }
    ],
    "sg:phone":"+1 740 622 0905",
    "sg:postcode":"43812",
    "sg:province":"OH",
    "sg:tags":[
        "calendar"
    ],
    "wof:name":"Beach Co",
    "wof:placetype":"venue"
},
  "geometry": {"coordinates":[-81.86958,40.258914],"type":"Point"}
}