{
  "type": "Feature",
  "properties": {
    "addr:full": "6400 W Snowville Rd Brecksville OH 44141",
    "addr:housenumber": "6400",
    "addr:postcode": "44141",
    "addr:street": "W Snowville Rd",
    "iso:country": "US",
    "sg:address": "6400 W Snowville Rd",
    "sg:city": "Brecksville",
    "sg:classifiers": [
      {
        "category": "Restaurant",
        "type": "Food \u0026 Drink"
      }
    ],
    "sg:phone": "+1 440 838 0900",
    "sg:postcode": "44141",
    "sg:province": "OH",
    "wof:name": "Canteen Corp",
    "wof:placetype": "venue"
  },
  "geometry": {"coordinates":[-81.639963,41.282994],"type":"Point"}
}
