{
  "type": "Feature",
  "properties": {
    "iso:country":"US",
    "sg:address":"6400 W Snowville Rd",
    "sg:city":"Brecksville",
    "sg:classifiers":[
        {
            "category":"Restaurant",
            "type":"Food & Drink"
        }
    ],
    "sg:phone":"+1 440 838 0900",
    "sg:postcode":"44141",
    "sg:province":"OH",
    "wof:name":"Canteen Corp",
    "wof:placetype":"venue"
},
  "geometry": {"coordinates":[-81.63996299999999,41.282994],"type":"Point"}
}