{
  "type": "Feature",
  "properties": {
    "iso:country":"US",
    "sg:address":"3944 Spring Grove Ave",
    "sg:city":"Cincinnati",
    "sg:classifiers":[
        {
            "category":"Shopping",
            "subcategory":"Used Merchandise",
            "type":"Retail Goods"
        }
    ],
    "sg:phone":"+1 513 541 6999",
    "sg:postcode":"45223",
    "sg:province":"OH",
    "sg:tags":[
        "vintage",
        "clothing",
        "store"
    ],
    "wof:name":"Casablanca Vintage Inc",
    "wof:placetype":"venue"
},
  "geometry": {"coordinates":[-84.539596,39.158017],"type":"Point"}
}