{
  "type": "Feature",
  "properties": {
    "iso:country":"US",
    "sg:address":"2210 Agler Rd",
    "sg:city":"Columbus",
    "sg:classifiers":[
        {
            "category":"Retail",
            "subcategory":"Repair Shop",
            "type":"Services"
        }
    ],
    "sg:phone":"+1 614 475 9755",
    "sg:postcode":"43224",
    "sg:province":"OH",
    "sg:tags":[
        "appliance"
    ],
    "wof:name":"Veteran's Appliance Repair Svc",
    "wof:placetype":"venue"
},
  "geometry": {"coordinates":[-82.952208,40.027073],"type":"Point"}
}