{
  "type": "Feature",
  "properties": {
    "iso:country":"US",
    "sg:address":"5330 Crest Hill Dr",
    "sg:city":"Cincinnati",
    "sg:classifiers":[
        {
            "category":"Government",
            "subcategory":"Office",
            "type":"Public Place"
        }
    ],
    "sg:phone":"+1 513 860 1181",
    "sg:postcode":"45246",
    "sg:province":"OH",
    "sg:tags":[
        "housing",
        "program"
    ],
    "wof:name":"Low Income Housing Tax Credit",
    "wof:placetype":"venue"
},
  "geometry": {"coordinates":[-84.447249,39.30137],"type":"Point"}
}