{
  "type": "Feature",
  "properties": {
    "addr:full": "104 E High St Mt Vernon OH 43050",
    "addr:housenumber": "104",
    "addr:postcode": "43050",
    "addr:street": "E High St",
    "iso:country": "US",
    "sg:address": "104 E High St",
    "sg:city": "Mt Vernon",
    "sg:classifiers": [
      {
        "category": "Health Services",
        "subcategory": "Doctor",
        "type": "Services"
      }
    ],
    "sg:phone": "+1 740 393 9740",
    "sg:postcode": "43050",
    "sg:province": "OH",
    "sg:tags": [
      "dentist"
    ],
    "wof:name": "Oral Facial Surgery Ctr",
    "wof:placetype": "venue"
  },
  "geometry": {"coordinates":[-82.484136,40.393425],"type":"Point"}
}
