{
  "type": "Feature",
  "properties": {
    "iso:country":"US",
    "sg:address":"4723 Edwardsville Rd",
    "sg:city":"Clarksville",
    "sg:classifiers":[
        {
            "category":"Building & Trades",
            "subcategory":"Electrical",
            "type":"Services"
        }
    ],
    "sg:phone":"+1 937 783 4753",
    "sg:postcode":"45113",
    "sg:province":"OH",
    "sg:tags":[
        "general",
        "electrical",
        "contractor"
    ],
    "wof:name":"Sidewinder Electric Company",
    "wof:placetype":"venue"
},
  "geometry": {"coordinates":[-83.998763,39.350687],"type":"Point"}
}