{
  "type": "Feature",
  "properties": {
    "addr:full":"2330 E 79th St Cleveland OH 44104",
    "addr:housenumber":"2330",
    "addr:postcode":"44104",
    "addr:street":"E 79Th St",
    "iso:country":"US",
    "sg:address":"2330 E 79th St",
    "sg:city":"Cleveland",
    "sg:classifiers":[
        {
            "category":"Freight",
            "type":"Transportation"
        }
    ],
    "sg:phone":"+1 216 881 1033",
    "sg:postcode":"44104",
    "sg:province":"OH",
    "sg:tags":[
        "delivery"
    ],
    "sg:website":"www.industrialtransport.com",
    "wof:name":"Intrans Package Express",
    "wof:placetype":"venue"
},
  "geometry": {"coordinates":[-81.63346199999999,41.496238],"type":"Point"}
}