{
  "type": "Feature",
  "properties": {
    "iso:country":"US",
    "sg:address":"2330 E 79th St",
    "sg:city":"Cleveland",
    "sg:classifiers":[
        {
            "category":"Freight",
            "type":"Transportation"
        }
    ],
    "sg:phone":"+1 216 881 1033",
    "sg:postcode":"44104",
    "sg:province":"OH",
    "sg:tags":[
        "delivery"
    ],
    "sg:website":"www.industrialtransport.com",
    "wof:name":"Intrans Package Express",
    "wof:placetype":"venue"
},
  "geometry": {"coordinates":[-81.633462,41.496238],"type":"Point"}
}