{
  "type": "Feature",
  "properties": {
    "addr:full": "902 8th St Portsmouth OH 45662",
    "addr:housenumber": "902",
    "addr:postcode": "45662",
    "addr:street": "8Th St",
    "iso:country": "US",
    "sg:address": "902 8th St",
    "sg:city": "Portsmouth",
    "sg:classifiers": [
      {
        "category": "Real Estate",
        "subcategory": "Real Estate Agent",
        "type": "Services"
      }
    ],
    "sg:phone": "+1 740 354 5654",
    "sg:postcode": "45662",
    "sg:province": "OH",
    "wof:name": "Neal Hatcher Real Estate",
    "wof:placetype": "venue"
  },
  "geometry": {"coordinates":[-82.994394,38.736283],"type":"Point"}
}
