{
  "type": "Feature",
  "properties": {
    "addr:full": "428 W Liberty St Wooster OH 44691",
    "addr:housenumber": "428",
    "addr:postcode": "44691",
    "addr:street": "W Liberty St",
    "iso:country": "US",
    "sg:address": "428 W Liberty St",
    "sg:city": "Wooster",
    "sg:classifiers": [
      {
        "category": "Government",
        "subcategory": "Office",
        "type": "Public Place"
      }
    ],
    "sg:phone": "+1 330 287 5640",
    "sg:postcode": "44691",
    "sg:province": "OH",
    "sg:tags": [
      "transportation"
    ],
    "wof:name": "Bureua Mtr Vhcl Dputy Rgistrar",
    "wof:placetype": "venue"
  },
  "geometry": {"coordinates":[-81.94843,40.79823],"type":"Point"}
}
