{
  "type": "Feature",
  "properties": {
    "addr:full": "3613 Michigan Ave Dayton OH 45416",
    "addr:housenumber": "3613",
    "addr:postcode": "45416",
    "addr:street": "Michigan Ave",
    "iso:country": "US",
    "sg:address": "3613 Michigan Ave",
    "sg:city": "Dayton",
    "sg:classifiers": [
      {
        "category": "Shopping",
        "type": "Retail Goods"
      }
    ],
    "sg:phone": "+1 937 278 5789",
    "sg:postcode": "45416",
    "sg:province": "OH",
    "sg:tags": [
      "mural"
    ],
    "wof:name": "Creative Endeavors Of Dayton",
    "wof:placetype": "venue"
  },
  "geometry": {"coordinates":[-84.249894,39.802765],"type":"Point"}
}
