{
  "type": "Feature",
  "properties": {
    "iso:country":"US",
    "sg:address":"176 Broadway St",
    "sg:city":"Seaman",
    "sg:classifiers":[
        {
            "category":"Organizations",
            "subcategory":"Religious Organization",
            "type":"Services"
        }
    ],
    "sg:phone":"+1 937 386 3251",
    "sg:postcode":"45679",
    "sg:province":"OH",
    "sg:tags":[
        "church"
    ],
    "wof:name":"Seaman Church Of Christ",
    "wof:placetype":"venue"
},
  "geometry": {"coordinates":[-83.572293,38.938864],"type":"Point"}
}