{
  "type": "Feature",
  "properties": {
    "iso:country":"US",
    "sg:address":"1032 Hollowcreek Ct",
    "sg:city":"Miamisburg",
    "sg:classifiers":[
        {
            "category":"Home & Garden",
            "subcategory":"Mobile Homes",
            "type":"Retail Goods"
        }
    ],
    "sg:phone":"+1 937 865 5308",
    "sg:postcode":"45342",
    "sg:province":"OH",
    "wof:name":"Worldwide Health Svc",
    "wof:placetype":"venue"
},
  "geometry": {"coordinates":[-84.251181,39.620153],"type":"Point"}
}