{
  "type": "Feature",
  "properties": {
    "iso:country":"US",
    "sg:address":"877 N Main St",
    "sg:city":"Akron",
    "sg:classifiers":[
        {
            "category":"Shopping",
            "type":"Retail Goods"
        }
    ],
    "sg:phone":"+1 330 253 2660",
    "sg:postcode":"44310",
    "sg:province":"OH",
    "sg:tags":[
        "trophy",
        "merchandise",
        "medal",
        "business",
        "award"
    ],
    "wof:name":"Smyth's Trophies",
    "wof:placetype":"venue"
},
  "geometry": {"coordinates":[-81.51034199999999,41.109017],"type":"Point"}
}