{
  "type": "Feature",
  "properties": {
    "iso:country":"US",
    "sg:address":"222 W Lake St",
    "sg:city":"Ravenna",
    "sg:classifiers":[
        {
            "category":"Manufacturing",
            "subcategory":"Tools & Machinery",
            "type":"Manufacturing & Wholesale Goods"
        }
    ],
    "sg:phone":"+1 330 297 9719",
    "sg:postcode":"44266",
    "sg:province":"OH",
    "sg:tags":[
        "mold",
        "mfg"
    ],
    "wof:name":"Nichols Mold Inc",
    "wof:placetype":"venue"
},
  "geometry": {"coordinates":[-81.24746500000001,41.147485],"type":"Point"}
}