{
  "type": "Feature",
  "properties": {
    "addr:full": "222 W Lake St Ravenna OH 44266",
    "addr:housenumber": "222",
    "addr:postcode": "44266",
    "addr:street": "W Lake St",
    "iso:country": "US",
    "sg:address": "222 W Lake St",
    "sg:city": "Ravenna",
    "sg:classifiers": [
      {
        "category": "Manufacturing",
        "subcategory": "Tools \u0026 Machinery",
        "type": "Manufacturing \u0026 Wholesale Goods"
      }
    ],
    "sg:phone": "+1 330 297 9719",
    "sg:postcode": "44266",
    "sg:province": "OH",
    "sg:tags": [
      "mold",
      "mfg"
    ],
    "wof:name": "Nichols Mold Inc",
    "wof:placetype": "venue"
  },
  "geometry": {"coordinates":[-81.247465,41.147485],"type":"Point"}
}
