{
  "type": "Feature",
  "properties": {
    "addr:full":"7616 Windy Knoll Dr Cincinnati OH 45241",
    "addr:housenumber":"7616",
    "addr:postcode":"45241",
    "addr:street":"Windy Knoll Dr",
    "iso:country":"US",
    "sg:address":"7616 Windy Knoll Dr",
    "sg:city":"Cincinnati",
    "sg:classifiers":[
        {
            "category":"Real Estate",
            "subcategory":"Real Estate Agent",
            "type":"Services"
        }
    ],
    "sg:phone":"+1 513 777 0980",
    "sg:postcode":"45241",
    "sg:province":"OH",
    "sg:tags":[
        "consultant"
    ],
    "wof:name":"PAB Financial",
    "wof:placetype":"venue"
},
  "geometry": {"coordinates":[-84.373805,39.304214],"type":"Point"}
}