{
  "type": "Feature",
  "properties": {
    "addr:full":"1414 S Green Rd Cleveland OH 44121",
    "addr:housenumber":"1414",
    "addr:postcode":"44121",
    "addr:street":"S Green Rd",
    "iso:country":"US",
    "sg:address":"1414 S Green Rd",
    "sg:city":"Cleveland",
    "sg:classifiers":[
        {
            "category":"Wholesale",
            "subcategory":"Non-durable Goods",
            "type":"Manufacturing & Wholesale Goods"
        }
    ],
    "sg:phone":"+1 440 442 4070",
    "sg:postcode":"44121",
    "sg:province":"OH",
    "wof:name":"VIP Promotions Inc",
    "wof:placetype":"venue"
},
  "geometry": {"coordinates":[-81.51944,41.522721],"type":"Point"}
}