{
  "type": "Feature",
  "properties": {
    "addr:full":"420 Market Ave N Canton OH 44702",
    "addr:housenumber":"420",
    "addr:postcode":"44702",
    "addr:street":"Market Ave N",
    "iso:country":"US",
    "sg:address":"420 Market Ave N",
    "sg:city":"Canton",
    "sg:classifiers":[
        {
            "category":"Government",
            "subcategory":"Office",
            "type":"Public Place"
        }
    ],
    "sg:phone":"+1 330 489 3231",
    "sg:postcode":"44702",
    "sg:province":"OH",
    "sg:tags":[
        "city",
        "program",
        "health"
    ],
    "sg:website":"www.cantonhealth.org",
    "wof:name":"Canton City Health Dept",
    "wof:placetype":"venue"
},
  "geometry": {"coordinates":[-81.373716,40.801077],"type":"Point"}
}