{
  "type": "Feature",
  "properties": {
    "addr:full":"45880 Butternut Ridge Rd Oberlin OH 44074",
    "addr:housenumber":"45880",
    "addr:postcode":"44074",
    "addr:street":"Butternut Ridge Rd",
    "iso:country":"US",
    "sg:address":"45880 Butternut Ridge Rd",
    "sg:city":"Oberlin",
    "sg:classifiers":[
        {
            "category":"Health Services",
            "subcategory":"Nursing And Care Facility",
            "type":"Services"
        }
    ],
    "sg:phone":"+1 440 774 1155",
    "sg:postcode":"44074",
    "sg:province":"OH",
    "sg:tags":[
        "home",
        "convalescent"
    ],
    "wof:name":"Echoing Lake",
    "wof:placetype":"venue"
},
  "geometry": {"coordinates":[-82.212931,41.308826],"type":"Point"}
}