{
  "type": "Feature",
  "properties": {
    "addr:full": "639 S Frank Blvd Akron OH 44320",
    "addr:housenumber": "639",
    "addr:postcode": "44320",
    "addr:street": "S Frank Blvd",
    "iso:country": "US",
    "sg:address": "639 S Frank Blvd",
    "sg:city": "Akron",
    "sg:classifiers": [
      {
        "category": "Shopping",
        "subcategory": "Discount \u0026 Variety Stores",
        "type": "Retail Goods"
      }
    ],
    "sg:phone": "+1 330 864 0129",
    "sg:postcode": "44320",
    "sg:province": "OH",
    "sg:tags": [
      "merchandise",
      "general"
    ],
    "wof:name": "Delia Sales",
    "wof:placetype": "venue"
  },
  "geometry": {"coordinates":[-81.603574,41.105302],"type":"Point"}
}
