{
  "type": "Feature",
  "properties": {
    "addr:full":"5442 Canyon Ct Willoughby OH 44094",
    "addr:housenumber":"5442",
    "addr:postcode":"44094",
    "addr:street":"Canyon Ct",
    "iso:country":"US",
    "sg:address":"5442 Canyon Ct",
    "sg:city":"Willoughby",
    "sg:classifiers":[
        {
            "category":"Professional",
            "type":"Services"
        }
    ],
    "sg:phone":"+1 440 946 6745",
    "sg:postcode":"44094",
    "sg:province":"OH",
    "wof:name":"Sellin Stuff To Gov",
    "wof:placetype":"venue"
},
  "geometry": {"coordinates":[-81.44344599999999,41.616582],"type":"Point"}
}