{
  "type": "Feature",
  "properties": {
    "addr:full":"207 N Hillcrest Dr Wooster OH 44691",
    "addr:housenumber":"207",
    "addr:postcode":"44691",
    "addr:street":"N Hillcrest Dr",
    "iso:country":"US",
    "sg:address":"207 N Hillcrest Dr",
    "sg:city":"Wooster",
    "sg:classifiers":[
        {
            "category":"Building & Trades",
            "subcategory":"Plumbing",
            "type":"Services"
        }
    ],
    "sg:phone":"+1 330 264 3633",
    "sg:postcode":"44691",
    "sg:province":"OH",
    "sg:tags":[
        "plumbing",
        "heating",
        "installation",
        "sprinkler",
        "contractor"
    ],
    "wof:name":"Schmid Mechanical Inc",
    "wof:placetype":"venue"
},
  "geometry": {"coordinates":[-81.905379,40.79788],"type":"Point"}
}