{
  "type": "Feature",
  "properties": {
    "iso:country":"US",
    "sg:address":"301 W 3rd St",
    "sg:city":"Dayton",
    "sg:classifiers":[
        {
            "category":"Government",
            "subcategory":"Office",
            "type":"Public Place"
        }
    ],
    "sg:phone":"+1 937 225 5623",
    "sg:postcode":"45402",
    "sg:province":"OH",
    "wof:name":"Montgomery Prosecutor Office",
    "wof:placetype":"venue"
},
  "geometry": {"coordinates":[-84.198777,39.758396],"type":"Point"}
}