{
  "type": "Feature",
  "properties": {
    "iso:country":"US",
    "sg:address":"240 W Church St",
    "sg:city":"Marion",
    "sg:classifiers":[
        {
            "category":"Organizations",
            "subcategory":"Community Association",
            "type":"Services"
        }
    ],
    "sg:phone":"+1 740 387 3733",
    "sg:postcode":"43302",
    "sg:province":"OH",
    "sg:tags":[
        "educational"
    ],
    "wof:name":"Jobs For Ohio Graduates",
    "wof:placetype":"venue"
},
  "geometry": {"coordinates":[-83.132423,40.58722],"type":"Point"}
}