{
  "type": "Feature",
  "properties": {
    "addr:full": "7 W State St Athens OH 45701",
    "addr:housenumber": "7",
    "addr:postcode": "45701",
    "addr:street": "W State St",
    "iso:country": "US",
    "sg:address": "7 W State St",
    "sg:city": "Athens",
    "sg:classifiers": [
      {
        "category": "Bars \u0026 Pubs",
        "type": "Food \u0026 Drink"
      }
    ],
    "sg:phone": "+1 740 592 9853",
    "sg:postcode": "45701",
    "sg:province": "OH",
    "sg:tags": [
      "drinking"
    ],
    "wof:name": "Tony's Tavern",
    "wof:placetype": "venue"
  },
  "geometry": {"coordinates":[-82.102225,39.330829],"type":"Point"}
}
