{
  "type": "Feature",
  "properties": {
    "iso:country":"US",
    "sg:address":"4247 Creek Rd",
    "sg:city":"Cincinnati",
    "sg:classifiers":[
        {
            "category":"Home & Garden",
            "subcategory":"Hardware",
            "type":"Retail Goods"
        }
    ],
    "sg:phone":"+1 513 791 2342",
    "sg:postcode":"45241",
    "sg:province":"OH",
    "sg:tags":[
        "saw"
    ],
    "wof:name":"C & S Ind Sales Inc",
    "wof:placetype":"venue"
},
  "geometry": {"coordinates":[-84.389785,39.260819],"type":"Point"}
}