{
  "type": "Feature",
  "properties": {
    "addr:full": "1015 S State St Pioneer OH 43554",
    "addr:housenumber": "1015",
    "addr:postcode": "43554",
    "addr:street": "S State St",
    "iso:country": "US",
    "sg:address": "1015 S State St",
    "sg:city": "Pioneer",
    "sg:classifiers": [
      {
        "category": "Restaurant",
        "type": "Food \u0026 Drink"
      }
    ],
    "sg:phone": "+1 419 737 2812",
    "sg:postcode": "43554",
    "sg:province": "OH",
    "sg:tags": [
      "eating"
    ],
    "wof:name": "Pioneer Pizza Barn",
    "wof:placetype": "venue"
  },
  "geometry": {"coordinates":[-84.553568,41.666196],"type":"Point"}
}
