{
  "type": "Feature",
  "properties": {
    "iso:country":"US",
    "sg:address":"106 4th St",
    "sg:city":"South Point",
    "sg:classifiers":[
        {
            "category":"Personal",
            "subcategory":"Beauty Salon",
            "type":"Services"
        }
    ],
    "sg:phone":"+1 740 377 9999",
    "sg:postcode":"45680",
    "sg:province":"OH",
    "wof:name":"Weedwackers",
    "wof:placetype":"venue"
},
  "geometry": {"coordinates":[-82.576994,38.412459],"type":"Point"}
}