{
  "type": "Feature",
  "properties": {
    "addr:full": "20571 Ellacott Pkwy Cleveland OH 44128",
    "addr:postcode": "20571;44128",
    "addr:street": "Ellacott Pkwy",
    "iso:country": "US",
    "sg:address": "20571 Ellacott Pkwy",
    "sg:city": "Cleveland",
    "sg:classifiers": [
      {
        "category": "Shopping",
        "subcategory": "Hobbies, Toys, \u0026 Games",
        "type": "Retail Goods"
      }
    ],
    "sg:phone": "+1 216 475 4736",
    "sg:postcode": "44128",
    "sg:province": "OH",
    "sg:tags": [
      "craft",
      "supply"
    ],
    "wof:name": "Curry's Art Town Creations Co",
    "wof:placetype": "venue"
  },
  "geometry": {"coordinates":[-81.527844,41.442049],"type":"Point"}
}
