{
  "type": "Feature",
  "properties": {
    "iso:country":"US",
    "sg:address":"20571 Ellacott Pkwy",
    "sg:city":"Cleveland",
    "sg:classifiers":[
        {
            "category":"Shopping",
            "subcategory":"Hobbies, Toys, & Games",
            "type":"Retail Goods"
        }
    ],
    "sg:phone":"+1 216 475 4736",
    "sg:postcode":"44128",
    "sg:province":"OH",
    "sg:tags":[
        "craft",
        "supply"
    ],
    "wof:name":"Curry's Art Town Creations Co",
    "wof:placetype":"venue"
},
  "geometry": {"coordinates":[-81.527844,41.442049],"type":"Point"}
}