{
  "type": "Feature",
  "properties": {
    "addr:full": "7205 Patten Tract Rd Sandusky OH 44870",
    "addr:housenumber": "7205",
    "addr:postcode": "44870",
    "addr:street": "Patten Tract Rd",
    "iso:country": "US",
    "sg:address": "7205 Patten Tract Rd",
    "sg:city": "Sandusky",
    "sg:classifiers": [
      {
        "category": "Farming",
        "subcategory": "Dairy Farm",
        "type": "Manufacturing \u0026 Wholesale Goods"
      }
    ],
    "sg:phone": "+1 419 359 1509",
    "sg:postcode": "44870",
    "sg:province": "OH",
    "sg:tags": [
      "corn",
      "grain",
      "cash",
      "soybean"
    ],
    "wof:name": "Hermes Brothers Dairy Farm",
    "wof:placetype": "venue"
  },
  "geometry": {"coordinates":[-82.726143,41.369061],"type":"Point"}
}
