{
  "type": "Feature",
  "properties": {
    "iso:country":"US",
    "sg:address":"7205 Patten Tract Rd",
    "sg:city":"Sandusky",
    "sg:classifiers":[
        {
            "category":"Farming",
            "subcategory":"Dairy Farm",
            "type":"Manufacturing & Wholesale Goods"
        }
    ],
    "sg:phone":"+1 419 359 1509",
    "sg:postcode":"44870",
    "sg:province":"OH",
    "sg:tags":[
        "corn",
        "grain",
        "cash",
        "soybean"
    ],
    "wof:name":"Hermes Brothers Dairy Farm",
    "wof:placetype":"venue"
},
  "geometry": {"coordinates":[-82.72614299999999,41.369061],"type":"Point"}
}