{
  "type": "Feature",
  "properties": {
    "addr:full":"6220 Mount Gilead Waterford Rd Mt Gilead OH 43338",
    "addr:housenumber":"6220",
    "addr:postcode":"43338",
    "addr:street":"Mount Gilead Waterford Rd",
    "iso:country":"US",
    "sg:address":"6220 Mount Gilead Waterford Rd",
    "sg:city":"Mt Gilead",
    "sg:classifiers":[
        {
            "category":"Restaurant",
            "type":"Food & Drink"
        }
    ],
    "sg:phone":"+1 419 768 2210",
    "sg:postcode":"43338",
    "sg:province":"OH",
    "wof:name":"Mc Donald's",
    "wof:placetype":"venue"
},
  "geometry": {"coordinates":[-82.71041200000001,40.565077],"type":"Point"}
}