{
  "type": "Feature",
  "properties": {
    "addr:full": "3646 Springdale Rd Cincinnati OH 45251",
    "addr:housenumber": "3646",
    "addr:postcode": "45251",
    "addr:street": "Springdale Rd",
    "iso:country": "US",
    "sg:address": "3646 Springdale Rd",
    "sg:city": "Cincinnati",
    "sg:classifiers": [
      {
        "category": "Professional",
        "subcategory": "Employment Agencies",
        "type": "Services"
      }
    ],
    "sg:phone": "+1 513 842 5490",
    "sg:postcode": "45251",
    "sg:province": "OH",
    "sg:tags": [
      "opportunity"
    ],
    "wof:name": "Staffing Innovations",
    "wof:placetype": "venue"
  },
  "geometry": {"coordinates":[-84.599573,39.246692],"type":"Point"}
}
