{
  "type": "Feature",
  "properties": {
    "iso:country":"US",
    "sg:address":"3646 Springdale Rd",
    "sg:city":"Cincinnati",
    "sg:classifiers":[
        {
            "category":"Professional",
            "subcategory":"Employment Agencies",
            "type":"Services"
        }
    ],
    "sg:phone":"+1 513 842 5490",
    "sg:postcode":"45251",
    "sg:province":"OH",
    "sg:tags":[
        "opportunity"
    ],
    "wof:name":"Staffing Innovations",
    "wof:placetype":"venue"
},
  "geometry": {"coordinates":[-84.59957300000001,39.246692],"type":"Point"}
}