{
  "type": "Feature",
  "properties": {
    "iso:country":"US",
    "sg:address":"2108 State Rte 113 E",
    "sg:city":"Milan",
    "sg:classifiers":[
        {
            "category":"Health Services",
            "subcategory":"Doctor",
            "type":"Services"
        }
    ],
    "sg:phone":"+1 419 499 2600",
    "sg:postcode":"44846",
    "sg:province":"OH",
    "sg:tags":[
        "physician",
        "surgeon"
    ],
    "wof:name":"Sharon L Dorman & Assocs",
    "wof:placetype":"venue"
},
  "geometry": {"coordinates":[-82.583316,41.298251],"type":"Point"}
}