{
  "type": "Feature",
  "properties": {
    "iso:country":"US",
    "sg:address":"100 Windsor Dr",
    "sg:city":"Hillsboro",
    "sg:classifiers":[
        {
            "category":"Real Estate",
            "subcategory":"Real Estate Operator",
            "type":"Services"
        }
    ],
    "sg:phone":"+1 937 393 9922",
    "sg:postcode":"45133",
    "sg:province":"OH",
    "sg:tags":[
        "apartment"
    ],
    "wof:name":"Windsor Apartments",
    "wof:placetype":"venue"
},
  "geometry": {"coordinates":[-83.62692800000001,39.206077],"type":"Point"}
}