{
  "type": "Feature",
  "properties": {
    "addr:full":"5120 Mumper Rd Springfield OH 45502",
    "addr:housenumber":"5120",
    "addr:postcode":"45502",
    "addr:street":"Mumper Rd",
    "iso:country":"US",
    "sg:address":"5120 Mumper Rd",
    "sg:city":"Springfield",
    "sg:classifiers":[
        {
            "category":"Government",
            "subcategory":"Office",
            "type":"Public Place"
        }
    ],
    "sg:phone":"+1 937 399 6842",
    "sg:postcode":"45502",
    "sg:province":"OH",
    "sg:tags":[
        "village"
    ],
    "wof:name":"Township Garage",
    "wof:placetype":"venue"
},
  "geometry": {"coordinates":[-83.70310499999999,40.013562],"type":"Point"}
}