{
  "type": "Feature",
  "properties": {
    "addr:full":"941 Jacobs Rd Youngstown OH 44505",
    "addr:housenumber":"941",
    "addr:postcode":"44505",
    "addr:street":"Jacobs Rd",
    "iso:country":"US",
    "sg:address":"941 Jacobs Rd",
    "sg:city":"Youngstown",
    "sg:classifiers":[
        {
            "category":"Autos & Motor Vehicles",
            "subcategory":"Motorcycle Sales",
            "type":"Retail Goods"
        }
    ],
    "sg:phone":"+1 330 743 8826",
    "sg:postcode":"44505",
    "sg:province":"OH",
    "sg:tags":[
        "repair"
    ],
    "wof:name":"Chop Shop",
    "wof:placetype":"venue"
},
  "geometry": {"coordinates":[-80.58648700000001,41.113804],"type":"Point"}
}