{
  "type": "Feature",
  "properties": {
    "addr:full": "26254 Chaplegate Ct Perrysburg OH 43551",
    "addr:postcode": "26254;43551",
    "addr:street": "Chaplegate Ct",
    "iso:country": "US",
    "sg:address": "26254 Chaplegate Ct",
    "sg:city": "Perrysburg",
    "sg:classifiers": [
      {
        "category": "Shopping",
        "subcategory": "Computers \u0026 Home Electronics",
        "type": "Retail Goods"
      }
    ],
    "sg:phone": "+1 419 872 6066",
    "sg:postcode": "43551",
    "sg:province": "OH",
    "sg:tags": [
      "software"
    ],
    "wof:name": "Sherson Technologies Inc",
    "wof:placetype": "venue"
  },
  "geometry": {"coordinates":[-83.689683,41.533932],"type":"Point"}
}
