{
  "type": "Feature",
  "properties": {
    "addr:full":"100 E Franklin St Dayton OH 45459",
    "addr:housenumber":"100",
    "addr:postcode":"45459",
    "addr:street":"E Franklin St",
    "iso:country":"US",
    "sg:address":"100 E Franklin St",
    "sg:city":"Dayton",
    "sg:classifiers":[
        {
            "category":"Building & Trades",
            "subcategory":"Construction",
            "type":"Services"
        }
    ],
    "sg:phone":"+1 937 608 7011",
    "sg:postcode":"45459",
    "sg:province":"OH",
    "sg:tags":[
        "repairing",
        "remodeling",
        "contractor"
    ],
    "wof:name":"South Dayton Remodeling",
    "wof:placetype":"venue"
},
  "geometry": {"coordinates":[-84.154178,39.628502],"type":"Point"}
}