{
  "type": "Feature",
  "properties": {
    "iso:country":"US",
    "sg:address":"70 Poland Manor",
    "sg:city":"Youngstown",
    "sg:classifiers":[
        {
            "category":"Manufacturing",
            "subcategory":"Metals",
            "type":"Manufacturing & Wholesale Goods"
        }
    ],
    "sg:phone":"+1 330 757 1241",
    "sg:postcode":"44514",
    "sg:province":"OH",
    "sg:tags":[
        "cover",
        "manhole"
    ],
    "wof:name":"Poland Concrete Products Inc",
    "wof:placetype":"venue"
},
  "geometry": {"coordinates":[-80.611198,41.016177],"type":"Point"}
}