{
  "type": "Feature",
  "properties": {
    "addr:full": "70 Poland Manor Youngstown OH 44514",
    "addr:housenumber": "70",
    "addr:postcode": "44514",
    "addr:street": "Poland Manor",
    "iso:country": "US",
    "sg:address": "70 Poland Manor",
    "sg:city": "Youngstown",
    "sg:classifiers": [
      {
        "category": "Manufacturing",
        "subcategory": "Metals",
        "type": "Manufacturing \u0026 Wholesale Goods"
      }
    ],
    "sg:phone": "+1 330 757 1241",
    "sg:postcode": "44514",
    "sg:province": "OH",
    "sg:tags": [
      "cover",
      "manhole"
    ],
    "wof:name": "Poland Concrete Products Inc",
    "wof:placetype": "venue"
  },
  "geometry": {"coordinates":[-80.611198,41.016177],"type":"Point"}
}
