{
  "type": "Feature",
  "properties": {
    "iso:country":"US",
    "sg:address":"5413 Youngstown Warren Rd",
    "sg:city":"Niles",
    "sg:classifiers":[
        {
            "category":"Restaurant",
            "type":"Food & Drink"
        }
    ],
    "sg:menulink":"http://www.allmenus.com/oh/howland/44168-bob-evans/menu/",
    "sg:phone":"+1 330 652 6600",
    "sg:postcode":"44446",
    "sg:province":"OH",
    "sg:tags":[
        "american"
    ],
    "wof:name":"Bob Evans",
    "wof:placetype":"venue"
},
  "geometry": {"coordinates":[-80.753615,41.211233],"type":"Point"}
}