{
  "type": "Feature",
  "properties": {
    "iso:country":"US",
    "sg:address":"109 N Sandusky Ave",
    "sg:city":"Bucyrus",
    "sg:classifiers":[
        {
            "category":"Shopping",
            "subcategory":"Computers & Home Electronics",
            "type":"Retail Goods"
        }
    ],
    "sg:phone":"+1 419 562 5574",
    "sg:postcode":"44820",
    "sg:province":"OH",
    "sg:tags":[
        "software"
    ],
    "wof:name":"Micro Medix",
    "wof:placetype":"venue"
},
  "geometry": {"coordinates":[-82.975648,40.809648],"type":"Point"}
}