{
  "type": "Feature",
  "properties": {
    "addr:full": "109 N Sandusky Ave Bucyrus OH 44820",
    "addr:housenumber": "109",
    "addr:postcode": "44820",
    "addr:street": "N Sandusky Ave",
    "iso:country": "US",
    "sg:address": "109 N Sandusky Ave",
    "sg:city": "Bucyrus",
    "sg:classifiers": [
      {
        "category": "Shopping",
        "subcategory": "Computers \u0026 Home Electronics",
        "type": "Retail Goods"
      }
    ],
    "sg:phone": "+1 419 562 5574",
    "sg:postcode": "44820",
    "sg:province": "OH",
    "sg:tags": [
      "software"
    ],
    "wof:name": "Micro Medix",
    "wof:placetype": "venue"
  },
  "geometry": {"coordinates":[-82.975648,40.809648],"type":"Point"}
}
