{
  "type": "Feature",
  "properties": {
    "iso:country":"US",
    "sg:address":"2021 Mahoning Rd NE",
    "sg:city":"Canton",
    "sg:classifiers":[
        {
            "category":"Banks & Credit Unions",
            "subcategory":"Bank",
            "type":"Services"
        }
    ],
    "sg:phone":"+1 330 438 1070",
    "sg:postcode":"44705",
    "sg:province":"OH",
    "wof:name":"Huntington National Bank",
    "wof:placetype":"venue"
},
  "geometry": {"coordinates":[-81.348831,40.809587],"type":"Point"}
}