{
  "type": "Feature",
  "properties": {
    "addr:full":"18198 Sloane Ave Cleveland OH 44107",
    "addr:postcode":"18198;44107",
    "addr:street":"Sloane Ave",
    "iso:country":"US",
    "sg:address":"18198 Sloane Ave",
    "sg:city":"Cleveland",
    "sg:classifiers":[
        {
            "category":"Restaurant",
            "type":"Food & Drink"
        }
    ],
    "sg:phone":"+1 216 226 7800",
    "sg:postcode":"44107",
    "sg:province":"OH",
    "wof:name":"Peking Restaurant",
    "wof:placetype":"venue"
},
  "geometry": {"coordinates":[-81.82389499999999,41.486194],"type":"Point"}
}