{
  "type": "Feature",
  "properties": {
    "iso:country":"US",
    "sg:address":"13920 Union Ave",
    "sg:city":"Cleveland",
    "sg:classifiers":[
        {
            "category":"Shopping",
            "subcategory":"Clothing, Apparel, & Fashions",
            "type":"Retail Goods"
        }
    ],
    "sg:phone":"+1 216 295 1345",
    "sg:postcode":"44120",
    "sg:province":"OH",
    "wof:name":"Just For Women Inc",
    "wof:placetype":"venue"
},
  "geometry": {"coordinates":[-81.58484,41.46423],"type":"Point"}
}