{
  "type": "Feature",
  "properties": {
    "addr:full":"1351 Brookline Rd Cleveland OH 44121",
    "addr:housenumber":"1351",
    "addr:postcode":"44121",
    "addr:street":"Brookline Rd",
    "iso:country":"US",
    "sg:address":"1351 Brookline Rd",
    "sg:city":"Cleveland",
    "sg:classifiers":[
        {
            "category":"Professional",
            "subcategory":"Advertising",
            "type":"Services"
        }
    ],
    "sg:phone":"+1 216 382 3737",
    "sg:postcode":"44121",
    "sg:province":"OH",
    "sg:tags":[
        "distributing",
        "sample"
    ],
    "sg:website":"www.companyexpress.com",
    "wof:name":"Company Express",
    "wof:placetype":"venue"
},
  "geometry": {"coordinates":[-81.535689,41.524064],"type":"Point"}
}