{
  "type": "Feature",
  "properties": {
    "iso:country":"US",
    "sg:address":"1200 Chester Industrial Pkwy",
    "sg:city":"Avon",
    "sg:classifiers":[
        {
            "category":"Freight",
            "type":"Transportation"
        }
    ],
    "sg:phone":"+1 440 934 2222",
    "sg:postcode":"44011",
    "sg:province":"OH",
    "sg:tags":[
        "distance",
        "cartage",
        "hauling",
        "long",
        "contract",
        "warehouse",
        "local"
    ],
    "wof:name":"All Pro Freight",
    "wof:placetype":"venue"
},
  "geometry": {"coordinates":[-82.053454,41.470327],"type":"Point"}
}