{
  "type": "Feature",
  "properties": {
    "addr:full": "12983 Stonecreek Dr Pickerington OH 43147",
    "addr:housenumber": "12983",
    "addr:postcode": "43147",
    "addr:street": "Stonecreek Dr",
    "iso:country": "US",
    "sg:address": "12983 Stonecreek Dr",
    "sg:city": "Pickerington",
    "sg:classifiers": [
      {
        "category": "Recreation",
        "type": "Entertainment"
      }
    ],
    "sg:phone": "+1 614 751 3488",
    "sg:postcode": "43147",
    "sg:province": "OH",
    "sg:tags": [
      "instruction",
      "gymnastic"
    ],
    "sg:website": "www.fitnessandfun.net",
    "wof:name": "Fitness \u0026 Fun",
    "wof:placetype": "venue"
  },
  "geometry": {"coordinates":[-82.784575,39.923562],"type":"Point"}
}
