{
  "type": "Feature",
  "properties": {
    "addr:full": "8766 Ballentine Pike New Carlisle OH 45344",
    "addr:postcode": "8766;45344",
    "addr:street": "Ballentine Pike",
    "iso:country": "US",
    "sg:address": "8766 Ballentine Pike",
    "sg:city": "New Carlisle",
    "sg:classifiers": [
      {
        "category": "Professional",
        "type": "Services"
      }
    ],
    "sg:phone": "+1 937 964 1542",
    "sg:postcode": "45344",
    "sg:province": "OH",
    "wof:name": "Joyce Thackery",
    "wof:placetype": "venue"
  },
  "geometry": {"coordinates":[-83.967065,40.029017],"type":"Point"}
}
