{
  "type": "Feature",
  "properties": {
    "iso:country":"US",
    "sg:address":"314 W 3rd St",
    "sg:city":"Dover",
    "sg:classifiers":[
        {
            "category":"Bars & Pubs",
            "type":"Food & Drink"
        }
    ],
    "sg:phone":"+1 330 364 5858",
    "sg:postcode":"44662",
    "sg:province":"OH",
    "sg:tags":[
        "drinking"
    ],
    "wof:name":"Krock's Tavern",
    "wof:placetype":"venue"
},
  "geometry": {"coordinates":[-81.479573,40.52],"type":"Point"}
}