{
  "type": "Feature",
  "properties": {
    "addr:full": "314 W 3rd St Dover OH 44662",
    "addr:housenumber": "314",
    "addr:postcode": "44662",
    "addr:street": "W 3Rd St",
    "iso:country": "US",
    "sg:address": "314 W 3rd St",
    "sg:city": "Dover",
    "sg:classifiers": [
      {
        "category": "Bars \u0026 Pubs",
        "type": "Food \u0026 Drink"
      }
    ],
    "sg:phone": "+1 330 364 5858",
    "sg:postcode": "44662",
    "sg:province": "OH",
    "sg:tags": [
      "drinking"
    ],
    "wof:name": "Krock's Tavern",
    "wof:placetype": "venue"
  },
  "geometry": {"coordinates":[-81.479573,40.52],"type":"Point"}
}
