{
  "type": "Feature",
  "properties": {
    "iso:country":"US",
    "sg:address":"401 Devon Pl",
    "sg:city":"Kent",
    "sg:classifiers":[
        {
            "category":"Health Services",
            "subcategory":"Doctor",
            "type":"Services"
        }
    ],
    "sg:phone":"+1 330 677 0645",
    "sg:postcode":"44240",
    "sg:province":"OH",
    "sg:tags":[
        "physician",
        "surgeon"
    ],
    "wof:name":"Diane E Smith & Assoc",
    "wof:placetype":"venue"
},
  "geometry": {"coordinates":[-81.35180099999999,41.13371],"type":"Point"}
}