{
  "type": "Feature",
  "properties": {
    "addr:full":"257 E Jefferson St New Lexington OH 43764",
    "addr:housenumber":"257",
    "addr:postcode":"43764",
    "addr:street":"E Jefferson St",
    "iso:country":"US",
    "sg:address":"257 E Jefferson St",
    "sg:city":"New Lexington",
    "sg:classifiers":[
        {
            "category":"Health Services",
            "subcategory":"Doctor",
            "type":"Services"
        }
    ],
    "sg:phone":"+1 740 342 4156",
    "sg:postcode":"43764",
    "sg:province":"OH",
    "sg:tags":[
        "dentist"
    ],
    "wof:name":"Lawrence E Nash DMD Inc",
    "wof:placetype":"venue"
},
  "geometry": {"coordinates":[-82.206895,39.719108],"type":"Point"}
}