{
  "type": "Feature",
  "properties": {
    "iso:country":"US",
    "sg:address":"456 W 10th Ave",
    "sg:city":"Columbus",
    "sg:classifiers":[
        {
            "category":"Health Services",
            "subcategory":"Doctor",
            "type":"Services"
        }
    ],
    "sg:phone":"+1 614 293 6255",
    "sg:postcode":"43201",
    "sg:province":"OH",
    "sg:tags":[
        "physician",
        "surgeon"
    ],
    "wof:name":"Ohio State University Medical",
    "wof:placetype":"venue"
},
  "geometry": {"coordinates":[-83.020754,39.993994],"type":"Point"}
}