{
  "type": "Feature",
  "properties": {
    "addr:full":"6524 Michael Dr Cincinnati OH 45243",
    "addr:housenumber":"6524",
    "addr:postcode":"45243",
    "addr:street":"Michael Dr",
    "iso:country":"US",
    "sg:address":"6524 Michael Dr",
    "sg:city":"Cincinnati",
    "sg:classifiers":[
        {
            "category":"Health Services",
            "subcategory":"Clinic",
            "type":"Services"
        }
    ],
    "sg:phone":"+1 513 891 7519",
    "sg:postcode":"45243",
    "sg:province":"OH",
    "sg:tags":[
        "information",
        "medical"
    ],
    "wof:name":"Family Advocate",
    "wof:placetype":"venue"
},
  "geometry": {"coordinates":[-84.379462,39.192588],"type":"Point"}
}