{
  "type": "Feature",
  "properties": {
    "addr:full":"414 E College St Granville OH 43023",
    "addr:housenumber":"414",
    "addr:postcode":"43023",
    "addr:street":"E College St",
    "iso:country":"US",
    "sg:address":"414 E College St",
    "sg:city":"Granville",
    "sg:classifiers":[
        {
            "category":"Social Services",
            "subcategory":"Child Care",
            "type":"Services"
        }
    ],
    "sg:phone":"+1 740 587 3076",
    "sg:postcode":"43023",
    "sg:province":"OH",
    "sg:website":"www.kidspaceinc.net",
    "wof:name":"Granville Child Care Ctr",
    "wof:placetype":"venue"
},
  "geometry": {"coordinates":[-82.513886,40.069004],"type":"Point"}
}