{
  "type": "Feature",
  "properties": {
    "iso:country":"US",
    "sg:address":"484 County Line Rd",
    "sg:city":"Westerville",
    "sg:classifiers":[
        {
            "category":"Health Services",
            "subcategory":"Doctor",
            "type":"Services"
        }
    ],
    "sg:phone":"+1 614 882 4914",
    "sg:postcode":"43081",
    "sg:province":"OH",
    "sg:tags":[
        "physician",
        "surgeon"
    ],
    "wof:name":"Scott Barkin MD",
    "wof:placetype":"venue"
},
  "geometry": {"coordinates":[-82.91812400000001,40.132716],"type":"Point"}
}