{
  "type": "Feature",
  "properties": {
    "iso:country":"US",
    "sg:address":"50 E Cherry St",
    "sg:city":"Sunbury",
    "sg:classifiers":[
        {
            "category":"Retail",
            "subcategory":"Repair Shop",
            "type":"Services"
        }
    ],
    "sg:phone":"+1 740 965 3283",
    "sg:postcode":"43074",
    "sg:province":"OH",
    "sg:tags":[
        "picture",
        "framing"
    ],
    "wof:name":"Lindas 3 Antiques Art & Custom",
    "wof:placetype":"venue"
},
  "geometry": {"coordinates":[-82.859283,40.243029],"type":"Point"}
}