{
  "type": "Feature",
  "properties": {
    "addr:full": "5331 S Gilmore Rd Fairfield OH 45014",
    "addr:housenumber": "5331",
    "addr:postcode": "45014",
    "addr:street": "S Gilmore Rd",
    "iso:country": "US",
    "sg:address": "5331 S Gilmore Rd",
    "sg:city": "Fairfield",
    "sg:classifiers": [
      {
        "category": "Health Services",
        "subcategory": "Doctor",
        "type": "Services"
      }
    ],
    "sg:phone": "+1 513 867 8119",
    "sg:postcode": "45014",
    "sg:province": "OH",
    "sg:tags": [
      "physician",
      "surgeon"
    ],
    "wof:name": "Hamilton Anesthesia Assoc Inc",
    "wof:placetype": "venue"
  },
  "geometry": {"coordinates":[-84.521926,39.329148],"type":"Point"}
}
