{
  "type": "Feature",
  "properties": {
    "iso:country":"US",
    "sg:address":"30 Home St",
    "sg:city":"Athens",
    "sg:classifiers":[
        {
            "category":"Education",
            "subcategory":"Library",
            "type":"Public Place"
        }
    ],
    "sg:phone":"+1 740 592 4272",
    "sg:postcode":"45701",
    "sg:province":"OH",
    "sg:tags":[
        "executive"
    ],
    "sg:website":"www.athenscounty.lib.oh.us",
    "wof:name":"Athens Public Library",
    "wof:placetype":"venue"
},
  "geometry": {"coordinates":[-82.08454399999999,39.337449],"type":"Point"}
}