{
  "type": "Feature",
  "properties": {
    "addr:full": "409 Solida Rd South Point OH 45680",
    "addr:housenumber": "409",
    "addr:postcode": "45680",
    "addr:street": "Solida Rd",
    "iso:country": "US",
    "sg:address": "409 Solida Rd",
    "sg:city": "South Point",
    "sg:classifiers": [
      {
        "category": "Food \u0026 Beverages",
        "subcategory": "Groceries \u0026 Convenience Stores",
        "type": "Retail Goods"
      }
    ],
    "sg:phone": "+1 740 867 4979",
    "sg:postcode": "45680",
    "sg:province": "OH",
    "sg:tags": [
      "grocer"
    ],
    "wof:name": "South Point Food Fair",
    "wof:placetype": "venue"
  },
  "geometry": {"coordinates":[-82.576481,38.420358],"type":"Point"}
}
