{
  "type": "Feature",
  "properties": {
    "iso:country":"US",
    "sg:address":"3641 Harrison Ave",
    "sg:city":"Cincinnati",
    "sg:classifiers":[
        {
            "category":"Cinema",
            "subcategory":"Movie Theater",
            "type":"Entertainment"
        }
    ],
    "sg:phone":"+1 513 662 4365",
    "sg:postcode":"45211",
    "sg:province":"OH",
    "wof:name":"Harrison Avenue Theater",
    "wof:placetype":"venue"
},
  "geometry": {"coordinates":[-84.609492,39.155852],"type":"Point"}
}