{
  "type": "Feature",
  "properties": {
    "addr:full": "7077 Pebblestone Ave NW North Canton OH 44720",
    "addr:housenumber": "7077",
    "addr:postcode": "44720",
    "addr:street": "Pebblestone Ave Nw",
    "iso:country": "US",
    "sg:address": "7077 Pebblestone Ave NW",
    "sg:city": "North Canton",
    "sg:classifiers": [
      {
        "category": "Organizations",
        "subcategory": "Religious Organization",
        "type": "Services"
      }
    ],
    "sg:phone": "+1 330 433 9070",
    "sg:postcode": "44720",
    "sg:province": "OH",
    "sg:tags": [
      "clergy"
    ],
    "wof:name": "Bruce Roth",
    "wof:placetype": "venue"
  },
  "geometry": {"coordinates":[-81.460717,40.883871],"type":"Point"}
}
