{
  "type": "Feature",
  "properties": {
    "addr:full":"1127 Beatty Ave Cambridge OH 43725",
    "addr:housenumber":"1127",
    "addr:postcode":"43725",
    "addr:street":"Beatty Ave",
    "iso:country":"US",
    "sg:address":"1127 Beatty Ave",
    "sg:city":"Cambridge",
    "sg:classifiers":[
        {
            "category":"Organizations",
            "subcategory":"Religious Organization",
            "type":"Services"
        }
    ],
    "sg:phone":"+1 740 432 5923",
    "sg:postcode":"43725",
    "sg:province":"OH",
    "wof:name":"First Christian Church",
    "wof:placetype":"venue"
},
  "geometry": {"coordinates":[-81.584337,40.028688],"type":"Point"}
}