{
  "type": "Feature",
  "properties": {
    "addr:full": "2976 State Rte 503 Greenville OH 45331",
    "addr:housenumber": "2976",
    "addr:postcode": "45331",
    "addr:street": "State Rte 503",
    "iso:country": "US",
    "sg:address": "2976 State Rte 503",
    "sg:city": "Greenville",
    "sg:classifiers": [
      {
        "category": "Farming",
        "subcategory": "Farm",
        "type": "Manufacturing \u0026 Wholesale Goods"
      }
    ],
    "sg:phone": "+1 937 548 7151",
    "sg:postcode": "45331",
    "sg:province": "OH",
    "sg:tags": [
      "crop",
      "general"
    ],
    "wof:name": "Emil Niswonger",
    "wof:placetype": "venue"
  },
  "geometry": {"coordinates":[-84.637602,40.003051],"type":"Point"}
}
