{
  "type": "Feature",
  "properties": {
    "iso:country":"US",
    "sg:address":"2976 State Rte 503",
    "sg:city":"Greenville",
    "sg:classifiers":[
        {
            "category":"Farming",
            "subcategory":"Farm",
            "type":"Manufacturing & Wholesale Goods"
        }
    ],
    "sg:phone":"+1 937 548 7151",
    "sg:postcode":"45331",
    "sg:province":"OH",
    "sg:tags":[
        "crop",
        "general"
    ],
    "wof:name":"Emil Niswonger",
    "wof:placetype":"venue"
},
  "geometry": {"coordinates":[-84.637602,40.003051],"type":"Point"}
}