{
  "type": "Feature",
  "properties": {
    "iso:country":"US",
    "sg:address":"31005 Solon Rd",
    "sg:city":"Cleveland",
    "sg:classifiers":[
        {
            "category":"Manufacturing",
            "subcategory":"Metals",
            "type":"Manufacturing & Wholesale Goods"
        },
        {
            "category":"Wholesale",
            "subcategory":"Durable Goods & Equipment",
            "type":"Manufacturing & Wholesale Goods"
        }
    ],
    "sg:phone":"+1 440 248 5456",
    "sg:postcode":"44139",
    "sg:province":"OH",
    "sg:tags":[
        "injection",
        "mold",
        "representative",
        "manufacturer"
    ],
    "wof:name":"Net Shape Technologies LLC",
    "wof:placetype":"venue"
},
  "geometry": {"coordinates":[-81.457416,41.387205],"type":"Point"}
}