{
  "type": "Feature",
  "properties": {
    "iso:country":"US",
    "sg:address":"1002 Buffalo Rd",
    "sg:city":"Bryan",
    "sg:classifiers":[
        {
            "category":"Wholesale",
            "subcategory":"Medical Equipment & Supplies",
            "type":"Manufacturing & Wholesale Goods"
        }
    ],
    "sg:phone":"+1 419 636 4189",
    "sg:postcode":"43506",
    "sg:province":"OH",
    "sg:tags":[
        "hospital"
    ],
    "wof:name":"Health Care Solutions",
    "wof:placetype":"venue"
},
  "geometry": {"coordinates":[-84.56711300000001,41.475106],"type":"Point"}
}