{
  "type": "Feature",
  "properties": {
    "addr:full": "1002 Buffalo Rd Bryan OH 43506",
    "addr:housenumber": "1002",
    "addr:postcode": "43506",
    "addr:street": "Buffalo Rd",
    "iso:country": "US",
    "sg:address": "1002 Buffalo Rd",
    "sg:city": "Bryan",
    "sg:classifiers": [
      {
        "category": "Wholesale",
        "subcategory": "Medical Equipment \u0026 Supplies",
        "type": "Manufacturing \u0026 Wholesale Goods"
      }
    ],
    "sg:phone": "+1 419 636 4189",
    "sg:postcode": "43506",
    "sg:province": "OH",
    "sg:tags": [
      "hospital"
    ],
    "wof:name": "Health Care Solutions",
    "wof:placetype": "venue"
  },
  "geometry": {"coordinates":[-84.567113,41.475106],"type":"Point"}
}
