{
  "type": "Feature",
  "properties": {
    "iso:country":"US",
    "sg:address":"406 Donbar Dr",
    "sg:city":"Bowling Green",
    "sg:classifiers":[
        {
            "category":"Professional",
            "subcategory":"Lawyer & Legal Services",
            "type":"Services"
        }
    ],
    "sg:phone":"+1 419 352 2614",
    "sg:postcode":"43402",
    "sg:province":"OH",
    "sg:tags":[
        "attorney"
    ],
    "wof:name":"Betty F Coggin",
    "wof:placetype":"venue"
},
  "geometry": {"coordinates":[-83.662046,41.370066],"type":"Point"}
}