{
  "type": "Feature",
  "properties": {
    "addr:full":"625 Cline Ave Mansfield OH 44907",
    "addr:housenumber":"625",
    "addr:postcode":"44907",
    "addr:street":"Cline Ave",
    "iso:country":"US",
    "sg:address":"625 Cline Ave",
    "sg:city":"Mansfield",
    "sg:classifiers":[
        {
            "category":"Health Services",
            "subcategory":"Doctor",
            "type":"Services"
        }
    ],
    "sg:phone":"+1 419 756 1001",
    "sg:postcode":"44907",
    "sg:province":"OH",
    "sg:tags":[
        "dentist"
    ],
    "wof:name":"Jeffrey A Schmunk DDS",
    "wof:placetype":"venue"
},
  "geometry": {"coordinates":[-82.539198,40.74722],"type":"Point"}
}