{
  "type": "Feature",
  "properties": {
    "addr:full": "2546 Commerce Blvd Cincinnati OH 45241",
    "addr:housenumber": "2546",
    "addr:postcode": "45241",
    "addr:street": "Commerce Blvd",
    "iso:country": "US",
    "sg:address": "2546 Commerce Blvd",
    "sg:city": "Cincinnati",
    "sg:classifiers": [
      {
        "category": "Manufacturing",
        "subcategory": "Signs",
        "type": "Manufacturing \u0026 Wholesale Goods"
      }
    ],
    "sg:phone": "+1 513 772 4122",
    "sg:postcode": "45241",
    "sg:province": "OH",
    "wof:name": "Bravo Signs",
    "wof:placetype": "venue"
  },
  "geometry": {"coordinates":[-84.424146,39.290057],"type":"Point"}
}
