{
  "type": "Feature",
  "properties": {
    "addr:full":"32 N Four Mile Run Rd Austintown OH 44515",
    "addr:housenumber":"32",
    "addr:postcode":"44515",
    "addr:street":"N Four Mile Run Rd",
    "iso:country":"US",
    "sg:address":"32 N Four Mile Run Rd",
    "sg:city":"Austintown",
    "sg:classifiers":[
        {
            "category":"Professional",
            "subcategory":"Detective & Security Services",
            "type":"Services"
        }
    ],
    "sg:phone":"+1 330 270 5922",
    "sg:postcode":"44515",
    "sg:province":"OH",
    "sg:tags":[
        "guard",
        "patrol"
    ],
    "sg:website":"www.smssi.com",
    "wof:name":"St Moritz Security Svc",
    "wof:placetype":"venue"
},
  "geometry": {"coordinates":[-80.71804899999999,41.103038],"type":"Point"}
}