{
  "type": "Feature",
  "properties": {
    "addr:full": "3336 Riverside Dr Upper Arlington OH 43221",
    "addr:housenumber": "3336",
    "addr:postcode": "43221",
    "addr:street": "Riverside Dr",
    "iso:country": "US",
    "sg:address": "3336 Riverside Dr",
    "sg:city": "Upper Arlington",
    "sg:classifiers": [
      {
        "category": "Real Estate",
        "subcategory": "Real Estate Services",
        "type": "Services"
      }
    ],
    "sg:phone": "+1 614 225 1996",
    "sg:postcode": "43221",
    "sg:province": "OH",
    "sg:tags": [
      "company",
      "title"
    ],
    "wof:name": "Lakeside Title",
    "wof:placetype": "venue"
  },
  "geometry": {"coordinates":[-83.092014,40.022339],"type":"Point"}
}
