{
  "type": "Feature",
  "properties": {
    "addr:full":"351 Lincolnshire Rd Columbus OH 43230",
    "addr:housenumber":"351",
    "addr:postcode":"43230",
    "addr:street":"Lincolnshire Rd",
    "iso:country":"US",
    "sg:address":"351 Lincolnshire Rd",
    "sg:city":"Columbus",
    "sg:classifiers":[
        {
            "category":"Building & Trades",
            "subcategory":"Construction",
            "type":"Services"
        }
    ],
    "sg:phone":"+1 614 418 0351",
    "sg:postcode":"43230",
    "sg:province":"OH",
    "sg:tags":[
        "house"
    ],
    "wof:name":"Aspen Remodeling LLC",
    "wof:placetype":"venue"
},
  "geometry": {"coordinates":[-82.90019100000001,40.027519],"type":"Point"}
}