{
  "type": "Feature",
  "properties": {
    "addr:full": "601 Chillicothe St Portsmouth OH 45662",
    "addr:housenumber": "601",
    "addr:postcode": "45662",
    "addr:street": "Chillicothe St",
    "iso:country": "US",
    "sg:address": "601 Chillicothe St",
    "sg:city": "Portsmouth",
    "sg:classifiers": [
      {
        "category": "Insurance",
        "subcategory": "Insurance Agent",
        "type": "Services"
      }
    ],
    "sg:phone": "+1 740 354 5635",
    "sg:postcode": "45662",
    "sg:province": "OH",
    "wof:name": "American General Life",
    "wof:placetype": "venue"
  },
  "geometry": {"coordinates":[-82.996483,38.735603],"type":"Point"}
}
