{
  "type": "Feature",
  "properties": {
    "iso:country":"US",
    "sg:address":"665 N Broadway St",
    "sg:city":"Lebanon",
    "sg:classifiers":[
        {
            "category":"Wholesale",
            "subcategory":"Electrical",
            "type":"Manufacturing & Wholesale Goods"
        }
    ],
    "sg:phone":"+1 513 932 9572",
    "sg:postcode":"45036",
    "sg:province":"OH",
    "sg:tags":[
        "mobile",
        "telephone"
    ],
    "wof:name":"Version Wirless",
    "wof:placetype":"venue"
},
  "geometry": {"coordinates":[-84.205296,39.445041],"type":"Point"}
}