{
  "type": "Feature",
  "properties": {
    "addr:full":"317 W Church St Marion OH 43302",
    "addr:housenumber":"317",
    "addr:postcode":"43302",
    "addr:street":"W Church St",
    "iso:country":"US",
    "sg:address":"317 W Church St",
    "sg:city":"Marion",
    "sg:classifiers":[
        {
            "category":"Social Services",
            "type":"Services"
        }
    ],
    "sg:phone":"+1 740 382 2156",
    "sg:postcode":"43302",
    "sg:province":"OH",
    "sg:tags":[
        "organization",
        "welfare"
    ],
    "wof:name":"Salvation Army",
    "wof:placetype":"venue"
},
  "geometry": {"coordinates":[-83.13437500000001,40.586993],"type":"Point"}
}