{
  "type": "Feature",
  "properties": {
    "addr:full": "1405 E 28th St Lorain OH 44055",
    "addr:housenumber": "1405",
    "addr:postcode": "44055",
    "addr:street": "E 28Th St",
    "iso:country": "US",
    "sg:address": "1405 E 28th St",
    "sg:city": "Lorain",
    "sg:classifiers": [
      {
        "category": "Organizations",
        "subcategory": "Religious Organization",
        "type": "Services"
      }
    ],
    "sg:phone": "+1 440 277 0077",
    "sg:postcode": "44055",
    "sg:province": "OH",
    "sg:tags": [
      "church"
    ],
    "wof:name": "Casa De Oracion",
    "wof:placetype": "venue"
  },
  "geometry": {"coordinates":[-82.149717,41.445206],"type":"Point"}
}
