{
  "type": "Feature",
  "properties": {
    "addr:full": "31 Carpenters Ridge Cincinnati OH 45241",
    "addr:housenumber": "31",
    "addr:postcode": "45241",
    "addr:street": "Carpenters Ridge",
    "iso:country": "US",
    "sg:address": "31 Carpenters Ridge",
    "sg:city": "Cincinnati",
    "sg:classifiers": [
      {
        "category": "Wholesale",
        "subcategory": "Sporting Goods",
        "type": "Manufacturing \u0026 Wholesale Goods"
      }
    ],
    "sg:phone": "+1 513 554 0333",
    "sg:postcode": "45241",
    "sg:province": "OH",
    "wof:name": "Active Sport Products",
    "wof:placetype": "venue"
  },
  "geometry": {"coordinates":[-84.409452,39.241754],"type":"Point"}
}
