{
  "type": "Feature",
  "properties": {
    "addr:full":"2520 Hamilton Ave Cleveland OH 44114",
    "addr:housenumber":"2520",
    "addr:postcode":"44114",
    "addr:street":"Hamilton Ave",
    "iso:country":"US",
    "sg:address":"2520 Hamilton Ave",
    "sg:city":"Cleveland",
    "sg:classifiers":[
        {
            "category":"Building & Trades",
            "subcategory":"Construction",
            "type":"Services"
        }
    ],
    "sg:phone":"+1 216 861 0077",
    "sg:postcode":"44114",
    "sg:province":"OH",
    "sg:tags":[
        "windows",
        "carpentry",
        "contractor"
    ],
    "wof:name":"Window Restoration Systems Inc",
    "wof:placetype":"venue"
},
  "geometry": {"coordinates":[-81.676733,41.511228],"type":"Point"}
}