{
  "type": "Feature",
  "properties": {
    "addr:full":"27 N 5th St Zanesville OH 43701",
    "addr:housenumber":"27",
    "addr:postcode":"43701",
    "addr:street":"N 5Th St",
    "iso:country":"US",
    "sg:address":"27 N 5th St",
    "sg:city":"Zanesville",
    "sg:classifiers":[
        {
            "category":"Government",
            "subcategory":"Office",
            "type":"Public Place"
        }
    ],
    "sg:phone":"+1 740 455 7123",
    "sg:postcode":"43701",
    "sg:province":"OH",
    "wof:name":"Muskingum Prosecuting Attys",
    "wof:placetype":"venue"
},
  "geometry": {"coordinates":[-82.00653800000001,39.940518],"type":"Point"}
}