{
  "type": "Feature",
  "properties": {
    "addr:full":"38802 Biggs Rd Grafton OH 44044",
    "addr:postcode":"38802;44044",
    "addr:street":"Biggs Rd",
    "iso:country":"US",
    "sg:address":"38802 Biggs Rd",
    "sg:city":"Grafton",
    "sg:classifiers":[
        {
            "category":"Shopping",
            "subcategory":"Florist",
            "type":"Retail Goods"
        }
    ],
    "sg:phone":"+1 440 926 3308",
    "sg:postcode":"44044",
    "sg:province":"OH",
    "wof:name":"Michael Hornby Florist",
    "wof:placetype":"venue"
},
  "geometry": {"coordinates":[-82.076656,41.252461],"type":"Point"}
}