{
  "type": "Feature",
  "properties": {
    "iso:country":"US",
    "sg:address":"355 E Campus View Blvd",
    "sg:city":"Columbus",
    "sg:classifiers":[
        {
            "category":"Banks & Credit Unions",
            "subcategory":"Investment Brokerage",
            "type":"Services"
        }
    ],
    "sg:phone":"+1 614 885 9734",
    "sg:postcode":"43235",
    "sg:province":"OH",
    "sg:tags":[
        "consultant",
        "planning",
        "financial"
    ],
    "wof:name":"Bueter & Assoc",
    "wof:placetype":"venue"
},
  "geometry": {"coordinates":[-83.00727500000001,40.118752],"type":"Point"}
}