{
  "type": "Feature",
  "properties": {
    "addr:full": "1405 Maplecrest Dr Youngstown OH 44515",
    "addr:housenumber": "1405",
    "addr:postcode": "44515",
    "addr:street": "Maplecrest Dr",
    "iso:country": "US",
    "sg:address": "1405 Maplecrest Dr",
    "sg:city": "Youngstown",
    "sg:classifiers": [
      {
        "category": "Retail",
        "subcategory": "Laundry \u0026 Dry Cleaning",
        "type": "Services"
      }
    ],
    "sg:phone": "+1 330 270 9321",
    "sg:postcode": "44515",
    "sg:province": "OH",
    "sg:tags": [
      "cleaners",
      "rug",
      "carpet"
    ],
    "wof:name": "Magic Carpet Steam Cleaning",
    "wof:placetype": "venue"
  },
  "geometry": {"coordinates":[-80.748141,41.087301],"type":"Point"}
}
