{
  "type": "Feature",
  "properties": {
    "addr:full":"3350 Germantown St Dayton OH 45408",
    "addr:housenumber":"3350",
    "addr:postcode":"45408",
    "addr:street":"Germantown St",
    "iso:country":"US",
    "sg:address":"3350 Germantown St",
    "sg:city":"Dayton",
    "sg:classifiers":[
        {
            "category":"Real Estate",
            "subcategory":"Real Estate Agent",
            "type":"Services"
        }
    ],
    "sg:phone":"+1 937 268 7368",
    "sg:postcode":"45408",
    "sg:province":"OH",
    "wof:name":"Francis Enterprise",
    "wof:placetype":"venue"
},
  "geometry": {"coordinates":[-84.247614,39.735959],"type":"Point"}
}