{
  "type": "Feature",
  "properties": {
    "addr:full": "26800 Amhearst Cir Cleveland OH 44122",
    "addr:postcode": "26800;44122",
    "addr:street": "Amhearst Cir",
    "iso:country": "US",
    "sg:address": "26800 Amhearst Cir",
    "sg:city": "Cleveland",
    "sg:classifiers": [
      {
        "category": "Real Estate",
        "subcategory": "Real Estate Operator",
        "type": "Services"
      }
    ],
    "sg:phone": "+1 216 292 6628",
    "sg:postcode": "44122",
    "sg:province": "OH",
    "sg:tags": [
      "building",
      "apartment"
    ],
    "wof:name": "Leading Apts",
    "wof:placetype": "venue"
  },
  "geometry": {"coordinates":[-81.492493,41.495116],"type":"Point"}
}
