{
  "type": "Feature",
  "properties": {
    "iso:country":"US",
    "sg:address":"26800 Amhearst Cir",
    "sg:city":"Cleveland",
    "sg:classifiers":[
        {
            "category":"Real Estate",
            "subcategory":"Real Estate Operator",
            "type":"Services"
        }
    ],
    "sg:phone":"+1 216 292 6628",
    "sg:postcode":"44122",
    "sg:province":"OH",
    "sg:tags":[
        "building",
        "apartment"
    ],
    "wof:name":"Leading Apts",
    "wof:placetype":"venue"
},
  "geometry": {"coordinates":[-81.492493,41.495116],"type":"Point"}
}