{
  "type": "Feature",
  "properties": {
    "iso:country":"US",
    "sg:address":"2612 Agosta-Meeker Rd N",
    "sg:city":"New Bloomington",
    "sg:classifiers":[
        {
            "category":"Government",
            "subcategory":"Police Station",
            "type":"Public Place"
        }
    ],
    "sg:phone":"+1 740 499 2725",
    "sg:postcode":"43341",
    "sg:province":"OH",
    "sg:tags":[
        "protection"
    ],
    "wof:name":"Norm Ratterman",
    "wof:placetype":"venue"
},
  "geometry": {"coordinates":[-83.304872,40.638958],"type":"Point"}
}