{
  "type": "Feature",
  "properties": {
    "addr:full": "11859 Royalton Rd Cleveland OH 44133",
    "addr:housenumber": "11859",
    "addr:postcode": "44133",
    "addr:street": "Royalton Rd",
    "iso:country": "US",
    "sg:address": "11859 Royalton Rd",
    "sg:city": "Cleveland",
    "sg:classifiers": [
      {
        "category": "Building \u0026 Trades",
        "subcategory": "Construction",
        "type": "Services"
      }
    ],
    "sg:phone": "+1 440 237 1160",
    "sg:postcode": "44133",
    "sg:province": "OH",
    "sg:tags": [
      "restoration",
      "cleaning",
      "patio",
      "deck"
    ],
    "wof:name": "Blast Technology Inc",
    "wof:placetype": "venue"
  },
  "geometry": {"coordinates":[-81.764193,41.314116],"type":"Point"}
}
