{
  "type": "Feature",
  "properties": {
    "addr:full":"4549 Warner Rd Cleveland OH 44105",
    "addr:housenumber":"4549",
    "addr:postcode":"44105",
    "addr:street":"Warner Rd",
    "iso:country":"US",
    "sg:address":"4549 Warner Rd",
    "sg:city":"Cleveland",
    "sg:classifiers":[
        {
            "category":"Retail",
            "subcategory":"Auto Repair",
            "type":"Services"
        }
    ],
    "sg:phone":"+1 216 883 3868",
    "sg:postcode":"44105",
    "sg:province":"OH",
    "sg:tags":[
        "repairing",
        "automobile"
    ],
    "wof:name":"Jerry's Automotive",
    "wof:placetype":"venue"
},
  "geometry": {"coordinates":[-81.629576,41.435951],"type":"Point"}
}