{
  "type": "Feature",
  "properties": {
    "addr:full": "637 Canton Rd Akron OH 44312",
    "addr:housenumber": "637",
    "addr:postcode": "44312",
    "addr:street": "Canton Rd",
    "iso:country": "US",
    "sg:address": "637 Canton Rd",
    "sg:city": "Akron",
    "sg:classifiers": [
      {
        "category": "Personal",
        "subcategory": "Tattoo Parlor",
        "type": "Services"
      }
    ],
    "sg:phone": "+1 330 733 8800",
    "sg:postcode": "44312",
    "sg:province": "OH",
    "sg:tags": [
      "tattooing"
    ],
    "wof:name": "Dragon's Lair Tattoo Piercing",
    "wof:placetype": "venue"
  },
  "geometry": {"coordinates":[-81.437014,41.045916],"type":"Point"}
}
