{
  "type": "Feature",
  "properties": {
    "addr:full":"2938 Hayden Run Plz Columbus OH 43235",
    "addr:housenumber":"2938",
    "addr:postcode":"43235",
    "addr:street":"Hayden Run",
    "iso:country":"US",
    "sg:address":"2938 Hayden Run Plz",
    "sg:city":"Columbus",
    "sg:classifiers":[
        {
            "category":"Retail",
            "subcategory":"Laundry & Dry Cleaning",
            "type":"Services"
        }
    ],
    "sg:phone":"+1 614 764 1841",
    "sg:postcode":"43235",
    "sg:province":"OH",
    "sg:tags":[
        "cleaners"
    ],
    "wof:name":"Dry Cleaning World",
    "wof:placetype":"venue"
},
  "geometry": {"coordinates":[-83.09603,40.065715],"type":"Point"}
}