{
  "type": "Feature",
  "properties": {
    "addr:full": "33335 Chatham Dr Avon Lake OH 44012",
    "addr:postcode": "33335;44012",
    "addr:street": "Chatham Dr",
    "iso:country": "US",
    "sg:address": "33335 Chatham Dr",
    "sg:city": "Avon Lake",
    "sg:classifiers": [
      {
        "category": "Personal",
        "subcategory": "Tattoo Parlor",
        "type": "Services"
      }
    ],
    "sg:phone": "+1 440 930 2414",
    "sg:postcode": "44012",
    "sg:province": "OH",
    "sg:tags": [
      "tattooing"
    ],
    "wof:name": "Always \u0026 Forever Beautiful",
    "wof:placetype": "venue"
  },
  "geometry": {"coordinates":[-82.046145,41.495098],"type":"Point"}
}
