{
  "type": "Feature",
  "properties": {
    "addr:full":"2904 Frost Rd Mantua OH 44255",
    "addr:housenumber":"2904",
    "addr:postcode":"44255",
    "addr:street":"Frost Rd",
    "iso:country":"US",
    "sg:address":"2904 Frost Rd",
    "sg:city":"Mantua",
    "sg:classifiers":[
        {
            "category":"Wholesale",
            "subcategory":"Durable Goods & Equipment",
            "type":"Manufacturing & Wholesale Goods"
        }
    ],
    "sg:phone":"+1 330 274 2281",
    "sg:postcode":"44255",
    "sg:province":"OH",
    "sg:tags":[
        "importer"
    ],
    "wof:name":"I E Solutions",
    "wof:placetype":"venue"
},
  "geometry": {"coordinates":[-81.283191,41.261007],"type":"Point"}
}