{
  "type": "Feature",
  "properties": {
    "addr:full":"275 N Hickory St Ottawa OH 45875",
    "addr:housenumber":"275",
    "addr:postcode":"45875",
    "addr:street":"N Hickory St",
    "iso:country":"US",
    "sg:address":"275 N Hickory St",
    "sg:city":"Ottawa",
    "sg:classifiers":[
        {
            "category":"Freight",
            "type":"Transportation"
        }
    ],
    "sg:phone":"+1 419 523 3061",
    "sg:postcode":"45875",
    "sg:province":"OH",
    "sg:tags":[
        "farm",
        "product",
        "bean",
        "warehousing"
    ],
    "wof:name":"Ottawa Feed & Grain Inc",
    "wof:placetype":"venue"
},
  "geometry": {"coordinates":[-84.045851,41.02123],"type":"Point"}
}