{
  "type": "Feature",
  "properties": {
    "addr:full": "960 Checkrein Ave Columbus OH 43229",
    "addr:housenumber": "960",
    "addr:postcode": "43229",
    "addr:street": "Checkrein Ave",
    "iso:country": "US",
    "sg:address": "960 Checkrein Ave",
    "sg:city": "Columbus",
    "sg:classifiers": [
      {
        "category": "Health Services",
        "subcategory": "Clinic",
        "type": "Services"
      },
      {
        "category": "Professional",
        "subcategory": "Management \u0026 Consulting",
        "type": "Services"
      }
    ],
    "sg:phone": "+1 614 436 9404",
    "sg:postcode": "43229",
    "sg:province": "OH",
    "sg:tags": [
      "fuel",
      "home",
      "care"
    ],
    "sg:website": "www.interimhealthcare.com",
    "wof:name": "Interim Health Care",
    "wof:placetype": "venue"
  },
  "geometry": {"coordinates":[-82.988124,40.101829],"type":"Point"}
}
