{
  "type": "Feature",
  "properties": {
    "iso:country":"US",
    "sg:address":"152 W Main St",
    "sg:city":"Hopedale",
    "sg:classifiers":[
        {
            "category":"Food & Beverages",
            "subcategory":"Liquor & Beverages",
            "type":"Retail Goods"
        }
    ],
    "sg:phone":"+1 740 937 2110",
    "sg:postcode":"43976",
    "sg:province":"OH",
    "wof:name":"Main Street Store",
    "wof:placetype":"venue"
},
  "geometry": {"coordinates":[-80.902524,40.323639],"type":"Point"}
}