{
  "type": "Feature",
  "properties": {
    "addr:full": "2673 Woodcutter Ave Columbus OH 43224",
    "addr:housenumber": "2673",
    "addr:postcode": "43224",
    "addr:street": "Woodcutter Ave",
    "iso:country": "US",
    "sg:address": "2673 Woodcutter Ave",
    "sg:city": "Columbus",
    "sg:classifiers": [
      {
        "category": "Freight",
        "type": "Transportation"
      }
    ],
    "sg:phone": "+1 614 475 3651",
    "sg:postcode": "43224",
    "sg:province": "OH",
    "sg:tags": [
      "operator",
      "trucking"
    ],
    "wof:name": "Paul W Dyer Sr",
    "wof:placetype": "venue"
  },
  "geometry": {"coordinates":[-82.941961,40.045993],"type":"Point"}
}
