{
  "type": "Feature",
  "properties": {
    "addr:full": "8467 Bunnell Hill Rd Springboro OH 45066",
    "addr:housenumber": "8467",
    "addr:postcode": "45066",
    "addr:street": "Bunnell Hill Rd",
    "iso:country": "US",
    "sg:address": "8467 Bunnell Hill Rd",
    "sg:city": "Springboro",
    "sg:classifiers": [
      {
        "category": "Building \u0026 Trades",
        "subcategory": "Plumbing",
        "type": "Services"
      }
    ],
    "sg:phone": "+1 937 748 0394",
    "sg:postcode": "45066",
    "sg:province": "OH",
    "sg:tags": [
      "specializing",
      "plumbing",
      "contractor"
    ],
    "wof:name": "ACT Plumbing",
    "wof:placetype": "venue"
  },
  "geometry": {"coordinates":[-84.193833,39.561134],"type":"Point"}
}
