{
  "type": "Feature",
  "properties": {
    "addr:full":"110 Debra Dr Botkins OH 45306",
    "addr:housenumber":"110",
    "addr:postcode":"45306",
    "addr:street":"Debra Dr",
    "iso:country":"US",
    "sg:address":"110 Debra Dr",
    "sg:city":"Botkins",
    "sg:classifiers":[
        {
            "category":"Manufacturing",
            "subcategory":"Retail Goods",
            "type":"Manufacturing & Wholesale Goods"
        }
    ],
    "sg:phone":"+1 937 693 4762",
    "sg:postcode":"45306",
    "sg:province":"OH",
    "sg:tags":[
        "product",
        "mfg"
    ],
    "wof:name":"Custom Mfg Equipment",
    "wof:placetype":"venue"
},
  "geometry": {"coordinates":[-84.18459199999999,40.471684],"type":"Point"}
}