{
  "type": "Feature",
  "properties": {
    "iso:country":"US",
    "sg:address":"55 N Chillicothe Rd",
    "sg:city":"Aurora",
    "sg:classifiers":[
        {
            "category":"Shopping",
            "subcategory":"Music",
            "type":"Retail Goods"
        }
    ],
    "sg:phone":"+1 330 995 4500",
    "sg:postcode":"44202",
    "sg:province":"OH",
    "sg:website":"www.hollywoodvideo.com",
    "wof:name":"Hollywood Video",
    "wof:placetype":"venue"
},
  "geometry": {"coordinates":[-81.34547000000001,41.318108],"type":"Point"}
}