{
  "type": "Feature",
  "properties": {
    "iso:country":"US",
    "sg:address":"745 W State St",
    "sg:city":"Columbus",
    "sg:classifiers":[
        {
            "category":"Social Services",
            "subcategory":"Job Training",
            "type":"Services"
        }
    ],
    "sg:phone":"+1 614 220 5317",
    "sg:postcode":"43222",
    "sg:province":"OH",
    "sg:tags":[
        "rehabilitation"
    ],
    "wof:name":"Meridian Healthcare Pulmonary",
    "wof:placetype":"venue"
},
  "geometry": {"coordinates":[-83.02109900000001,39.957653],"type":"Point"}
}