{
  "type": "Feature",
  "properties": {
    "addr:full":"340 Albert Rd Brookville OH 45309",
    "addr:housenumber":"340",
    "addr:postcode":"45309",
    "addr:street":"Albert Rd",
    "iso:country":"US",
    "sg:address":"340 Albert Rd",
    "sg:city":"Brookville",
    "sg:classifiers":[
        {
            "category":"Organizations",
            "subcategory":"Religious Organization",
            "type":"Services"
        }
    ],
    "sg:phone":"+1 937 833 5317",
    "sg:postcode":"45309",
    "sg:province":"OH",
    "sg:tags":[
        "church"
    ],
    "sg:website":"www.firstbaptistchurchbrookville.com",
    "wof:name":"First Baptist Church",
    "wof:placetype":"venue"
},
  "geometry": {"coordinates":[-84.40626399999999,39.832177],"type":"Point"}
}