{
  "type": "Feature",
  "properties": {
    "addr:full": "4138 Meadowbrook Ln Mason OH 45040",
    "addr:housenumber": "4138",
    "addr:postcode": "45040",
    "addr:street": "Meadowbrook Ln",
    "iso:country": "US",
    "sg:address": "4138 Meadowbrook Ln",
    "sg:city": "Mason",
    "sg:classifiers": [
      {
        "category": "Professional",
        "subcategory": "Management \u0026 Consulting",
        "type": "Services"
      }
    ],
    "sg:phone": "+1 513 336 8920",
    "sg:postcode": "45040",
    "sg:province": "OH",
    "sg:tags": [
      "consultant"
    ],
    "wof:name": "Horizon Co Inc",
    "wof:placetype": "venue"
  },
  "geometry": {"coordinates":[-84.32695,39.379009],"type":"Point"}
}
