{
  "type": "Feature",
  "properties": {
    "iso:country":"US",
    "sg:address":"1373 Stone Dr",
    "sg:city":"Harrison",
    "sg:classifiers":[
        {
            "category":"Food & Beverages",
            "subcategory":"Specialty",
            "type":"Retail Goods"
        }
    ],
    "sg:phone":"+1 513 367 1600",
    "sg:postcode":"45030",
    "sg:province":"IN",
    "sg:tags":[
        "salt"
    ],
    "wof:name":"Adams Water Conditioning",
    "wof:placetype":"venue"
},
  "geometry": {"coordinates":[-84.796222,39.252428],"type":"Point"}
}