{
  "type": "Feature",
  "properties": {
    "iso:country":"US",
    "sg:address":"246 N Court St",
    "sg:city":"Medina",
    "sg:classifiers":[
        {
            "category":"Banks & Credit Unions",
            "subcategory":"Bank",
            "type":"Services"
        }
    ],
    "sg:phone":"+1 330 764 3250",
    "sg:postcode":"44256",
    "sg:province":"OH",
    "sg:tags":[
        "state"
    ],
    "wof:name":"Sky Bank",
    "wof:placetype":"venue"
},
  "geometry": {"coordinates":[-81.86391999999999,41.141309],"type":"Point"}
}