{
  "type": "Feature",
  "properties": {
    "addr:full": "246 N Court St Medina OH 44256",
    "addr:housenumber": "246",
    "addr:postcode": "44256",
    "addr:street": "N Court St",
    "iso:country": "US",
    "sg:address": "246 N Court St",
    "sg:city": "Medina",
    "sg:classifiers": [
      {
        "category": "Banks \u0026 Credit Unions",
        "subcategory": "Bank",
        "type": "Services"
      }
    ],
    "sg:phone": "+1 330 764 3250",
    "sg:postcode": "44256",
    "sg:province": "OH",
    "sg:tags": [
      "state"
    ],
    "wof:name": "Sky Bank",
    "wof:placetype": "venue"
  },
  "geometry": {"coordinates":[-81.86392,41.141309],"type":"Point"}
}
