{
  "type": "Feature",
  "properties": {
    "iso:country":"US",
    "sg:address":"8440 Hitchcock Rd",
    "sg:city":"Youngstown",
    "sg:classifiers":[
        {
            "category":"Real Estate",
            "subcategory":"Real Estate Agent",
            "type":"Services"
        }
    ],
    "sg:phone":"+1 330 726 8377",
    "sg:postcode":"44512",
    "sg:province":"OH",
    "wof:name":"Escaja James Realtor",
    "wof:placetype":"venue"
},
  "geometry": {"coordinates":[-80.67677,40.993428],"type":"Point"}
}