{
  "type": "Feature",
  "properties": {
    "iso:country":"US",
    "sg:address":"3024 Center Rd",
    "sg:city":"Youngstown",
    "sg:classifiers":[
        {
            "category":"Organizations",
            "subcategory":"Non-profit Organization",
            "type":"Services"
        }
    ],
    "sg:phone":"+1 330 707 1134",
    "sg:postcode":"44514",
    "sg:province":"OH",
    "sg:tags":[
        "human"
    ],
    "wof:name":"Mahoning County Council",
    "wof:placetype":"venue"
},
  "geometry": {"coordinates":[-80.591742,41.023806],"type":"Point"}
}