{
  "type": "Feature",
  "properties": {
    "iso:country":"US",
    "sg:address":"580 S High St",
    "sg:city":"Columbus",
    "sg:classifiers":[
        {
            "category":"Professional",
            "subcategory":"Lawyer & Legal Services",
            "type":"Services"
        }
    ],
    "sg:phone":"+1 614 224 9223",
    "sg:postcode":"43215",
    "sg:province":"OH",
    "sg:tags":[
        "attorney"
    ],
    "wof:name":"Ward KAPS Bainbridge & Maurer",
    "wof:placetype":"venue"
},
  "geometry": {"coordinates":[-82.99821300000001,39.950138],"type":"Point"}
}