{
  "type": "Feature",
  "properties": {
    "addr:full": "19474 Center Ridge Rd Cleveland OH 44116",
    "addr:housenumber": "19474",
    "addr:postcode": "44116",
    "addr:street": "Center Ridge Rd",
    "iso:country": "US",
    "sg:address": "19474 Center Ridge Rd",
    "sg:city": "Cleveland",
    "sg:classifiers": [
      {
        "category": "Organizations",
        "subcategory": "Membership Organization",
        "type": "Services"
      }
    ],
    "sg:phone": "+1 440 333 4180",
    "sg:postcode": "44116",
    "sg:province": "OH",
    "wof:name": "Global Country Of World Peace",
    "wof:placetype": "venue"
  },
  "geometry": {"coordinates":[-81.83924,41.46562],"type":"Point"}
}
