{
  "type": "Feature",
  "properties": {
    "addr:full": "9485 Eastland Rd Strongsville OH 44149",
    "addr:housenumber": "9485",
    "addr:postcode": "44149",
    "addr:street": "Eastland Rd",
    "iso:country": "US",
    "sg:address": "9485 Eastland Rd",
    "sg:city": "Strongsville",
    "sg:classifiers": [
      {
        "category": "Recreation",
        "type": "Entertainment"
      }
    ],
    "sg:phone": "+1 440 572 9990",
    "sg:postcode": "44149",
    "sg:province": "OH",
    "sg:tags": [
      "hay",
      "ride"
    ],
    "wof:name": "Chalet-Toboggan Chutes",
    "wof:placetype": "venue"
  },
  "geometry": {"coordinates":[-81.843268,41.342311],"type":"Point"}
}
