{
  "type": "Feature",
  "properties": {
    "iso:country":"US",
    "sg:address":"9485 Eastland Rd",
    "sg:city":"Strongsville",
    "sg:classifiers":[
        {
            "category":"Recreation",
            "type":"Entertainment"
        }
    ],
    "sg:phone":"+1 440 572 9990",
    "sg:postcode":"44149",
    "sg:province":"OH",
    "sg:tags":[
        "hay",
        "ride"
    ],
    "wof:name":"Chalet-Toboggan Chutes",
    "wof:placetype":"venue"
},
  "geometry": {"coordinates":[-81.84326799999999,41.342311],"type":"Point"}
}