{
  "type": "Feature",
  "properties": {
    "addr:full": "5303 Amherst Dr Cleveland OH 44129",
    "addr:housenumber": "5303",
    "addr:postcode": "44129",
    "addr:street": "Amherst Dr",
    "iso:country": "US",
    "sg:address": "5303 Amherst Dr",
    "sg:city": "Cleveland",
    "sg:classifiers": [
      {
        "category": "Manufacturing",
        "subcategory": "Chemicals \u0026 Compounds",
        "type": "Manufacturing \u0026 Wholesale Goods"
      }
    ],
    "sg:phone": "+1 440 842 7441",
    "sg:postcode": "44129",
    "sg:province": "OH",
    "sg:tags": [
      "cleaning"
    ],
    "wof:name": "Pacas Chemical",
    "wof:placetype": "venue"
  },
  "geometry": {"coordinates":[-81.744627,41.415564],"type":"Point"}
}
