{
  "type": "Feature",
  "properties": {
    "iso:country":"US",
    "sg:address":"5303 Amherst Dr",
    "sg:city":"Cleveland",
    "sg:classifiers":[
        {
            "category":"Manufacturing",
            "subcategory":"Chemicals & Compounds",
            "type":"Manufacturing & Wholesale Goods"
        }
    ],
    "sg:phone":"+1 440 842 7441",
    "sg:postcode":"44129",
    "sg:province":"OH",
    "sg:tags":[
        "cleaning"
    ],
    "wof:name":"Pacas Chemical",
    "wof:placetype":"venue"
},
  "geometry": {"coordinates":[-81.74462699999999,41.415564],"type":"Point"}
}