{
  "type": "Feature",
  "properties": {
    "iso:country":"US",
    "sg:address":"405 4th St NE",
    "sg:city":"Massillon",
    "sg:classifiers":[
        {
            "category":"Professional",
            "type":"Services"
        }
    ],
    "sg:phone":"+1 330 833 2803",
    "sg:postcode":"44646",
    "sg:province":"OH",
    "wof:name":"E7n Corp",
    "wof:placetype":"venue"
},
  "geometry": {"coordinates":[-81.520008,40.801622],"type":"Point"}
}