{
  "type": "Feature",
  "properties": {
    "iso:country":"US",
    "sg:address":"497 Norwich Ave",
    "sg:city":"Franklin Furnace",
    "sg:classifiers":[
        {
            "category":"Professional",
            "type":"Services"
        }
    ],
    "sg:phone":"+1 740 354 9578",
    "sg:postcode":"45629",
    "sg:province":"OH",
    "wof:name":"Star Interactive Inc",
    "wof:placetype":"venue"
},
  "geometry": {"coordinates":[-82.846657,38.623357],"type":"Point"}
}