{
  "type": "Feature",
  "properties": {
    "addr:full":"17106 Detroit Ave Cleveland OH 44107",
    "addr:housenumber":"17106",
    "addr:postcode":"44107",
    "addr:street":"Detroit Ave",
    "iso:country":"US",
    "sg:address":"17106 Detroit Ave",
    "sg:city":"Cleveland",
    "sg:classifiers":[
        {
            "category":"Shopping",
            "subcategory":"Used Merchandise",
            "type":"Retail Goods"
        }
    ],
    "sg:phone":"+1 216 221 2149",
    "sg:postcode":"44107",
    "sg:province":"OH",
    "sg:tags":[
        "antique"
    ],
    "wof:name":"A Vintage Faire",
    "wof:placetype":"venue"
},
  "geometry": {"coordinates":[-81.81659500000001,41.485476],"type":"Point"}
}