{
  "type": "Feature",
  "properties": {
    "addr:full":"6000 Frank Ave NW Canton OH 44720",
    "addr:housenumber":"6000",
    "addr:postcode":"44720",
    "addr:street":"Frank Ave Nw",
    "iso:country":"US",
    "sg:address":"6000 Frank Ave NW",
    "sg:city":"Canton",
    "sg:classifiers":[
        {
            "category":"Organizations",
            "subcategory":"Religious Organization",
            "type":"Services"
        }
    ],
    "sg:phone":"+1 330 499 9935",
    "sg:postcode":"44720",
    "sg:province":"OH",
    "wof:name":"Interfaith Campus Ministry",
    "wof:placetype":"venue"
},
  "geometry": {"coordinates":[-81.441812,40.866644],"type":"Point"}
}