{
  "type": "Feature",
  "properties": {
    "iso:country":"US",
    "sg:address":"1501 Euclid Ave",
    "sg:city":"Cleveland",
    "sg:classifiers":[
        {
            "category":"Professional",
            "type":"Services"
        }
    ],
    "sg:phone":"+1 216 502 1050",
    "sg:postcode":"44115",
    "sg:province":"OH",
    "sg:tags":[
        "establishment"
    ],
    "wof:name":"Strategy Logic",
    "wof:placetype":"venue"
},
  "geometry": {"coordinates":[-81.681828,41.500885],"type":"Point"}
}