{
  "type": "Feature",
  "properties": {
    "iso:country":"US",
    "sg:address":"12904 Kinsman Rd",
    "sg:city":"Cleveland",
    "sg:classifiers":[
        {
            "category":"Building & Trades",
            "subcategory":"Plumbing",
            "type":"Services"
        }
    ],
    "sg:phone":"+1 216 561 8880",
    "sg:postcode":"44120",
    "sg:province":"OH",
    "sg:tags":[
        "contractor"
    ],
    "wof:name":"Terrance Kordiack Mstr Plumber",
    "wof:placetype":"venue"
},
  "geometry": {"coordinates":[-81.592421,41.465803],"type":"Point"}
}