{
  "type": "Feature",
  "properties": {
    "addr:full":"1906 Wick Campbell Rd Hubbard OH 44425",
    "addr:housenumber":"1906",
    "addr:postcode":"44425",
    "addr:street":"Wick Campbell Rd",
    "iso:country":"US",
    "sg:address":"1906 Wick Campbell Rd",
    "sg:city":"Hubbard",
    "sg:classifiers":[
        {
            "category":"Organizations",
            "subcategory":"Religious Organization",
            "type":"Services"
        }
    ],
    "sg:phone":"+1 330 568 7091",
    "sg:postcode":"44425",
    "sg:province":"OH",
    "sg:tags":[
        "church"
    ],
    "wof:name":"Coalburg United Methodist Chr",
    "wof:placetype":"venue"
},
  "geometry": {"coordinates":[-80.587641,41.19129],"type":"Point"}
}