{
  "type": "Feature",
  "properties": {
    "addr:full": "5633 Vine St Cincinnati OH 45216",
    "addr:housenumber": "5633",
    "addr:postcode": "45216",
    "addr:street": "Vine St",
    "iso:country": "US",
    "sg:address": "5633 Vine St",
    "sg:city": "Cincinnati",
    "sg:classifiers": [
      {
        "category": "Organizations",
        "subcategory": "Community Association",
        "type": "Services"
      }
    ],
    "sg:phone": "+1 513 242 7403",
    "sg:postcode": "45216",
    "sg:province": "OH",
    "sg:tags": [
      "fraternal"
    ],
    "sg:website": "http://www.foe.com/",
    "wof:name": "Fraternal Order of Eagles",
    "wof:placetype": "venue"
  },
  "geometry": {"coordinates":[-84.49167,39.183603],"type":"Point"}
}
