{
  "type": "Feature",
  "properties": {
    "addr:full": "1650 Berkshire Rd Gates Mills OH 44040",
    "addr:housenumber": "1650",
    "addr:postcode": "44040",
    "addr:street": "Berkshire Rd",
    "iso:country": "US",
    "sg:address": "1650 Berkshire Rd",
    "sg:city": "Gates Mills",
    "sg:classifiers": [
      {
        "category": "Professional",
        "type": "Services"
      }
    ],
    "sg:phone": "+1 440 423 4855",
    "sg:postcode": "44040",
    "sg:province": "OH",
    "wof:name": "William G Lantz",
    "wof:placetype": "venue"
  },
  "geometry": {"coordinates":[-81.417581,41.515771],"type":"Point"}
}
