{
  "type": "Feature",
  "properties": {
    "addr:full": "672 Springmill St Mansfield OH 44903",
    "addr:housenumber": "672",
    "addr:postcode": "44903",
    "addr:street": "Springmill St",
    "iso:country": "US",
    "sg:address": "672 Springmill St",
    "sg:city": "Mansfield",
    "sg:classifiers": [
      {
        "category": "Local Transit",
        "type": "Transportation"
      }
    ],
    "sg:phone": "+1 419 522 9904",
    "sg:postcode": "44903",
    "sg:province": "OH",
    "sg:tags": [
      "wheelchair",
      "ambulance"
    ],
    "wof:name": "Apple Lane Ambulette Service",
    "wof:placetype": "venue"
  },
  "geometry": {"coordinates":[-82.529189,40.772824],"type":"Point"}
}
