{
  "type": "Feature",
  "properties": {
    "addr:full":"412 E Linden Ave Miamisburg OH 45342",
    "addr:housenumber":"412",
    "addr:postcode":"45342",
    "addr:street":"E Linden Ave",
    "iso:country":"US",
    "sg:address":"412 E Linden Ave",
    "sg:city":"Miamisburg",
    "sg:classifiers":[
        {
            "category":"Building & Trades",
            "subcategory":"Plumbing",
            "type":"Services"
        }
    ],
    "sg:phone":"+1 937 866 8393",
    "sg:postcode":"45342",
    "sg:province":"OH",
    "sg:tags":[
        "plumbing",
        "contractor"
    ],
    "wof:name":"G & W Plumbing",
    "wof:placetype":"venue"
},
  "geometry": {"coordinates":[-84.28366699999999,39.638989],"type":"Point"}
}