{
  "type": "Feature",
  "properties": {
    "iso:country":"US",
    "sg:address":"12107 Chapin Rd",
    "sg:city":"Berlin Heights",
    "sg:classifiers":[
        {
            "category":"Wholesale",
            "subcategory":"Farm Supplies",
            "type":"Manufacturing & Wholesale Goods"
        }
    ],
    "sg:phone":"+1 419 588 2625",
    "sg:postcode":"44814",
    "sg:province":"OH",
    "sg:tags":[
        "equipment",
        "kennel"
    ],
    "wof:name":"Big Dog Kennel",
    "wof:placetype":"venue"
},
  "geometry": {"coordinates":[-82.520291,41.313804],"type":"Point"}
}