{
  "type": "Feature",
  "properties": {
    "addr:full": "141 S Main St Marion OH 43302",
    "addr:housenumber": "141",
    "addr:postcode": "43302",
    "addr:street": "S Main St",
    "iso:country": "US",
    "sg:address": "141 S Main St",
    "sg:city": "Marion",
    "sg:classifiers": [
      {
        "category": "Shopping",
        "subcategory": "Computers \u0026 Home Electronics",
        "type": "Retail Goods"
      }
    ],
    "sg:phone": "+1 740 382 9932",
    "sg:postcode": "43302",
    "sg:province": "OH",
    "sg:tags": [
      "high",
      "fidelity",
      "stereophonic"
    ],
    "wof:name": "Advanced Audio",
    "wof:placetype": "venue"
  },
  "geometry": {"coordinates":[-83.128882,40.588065],"type":"Point"}
}
