{
  "type": "Feature",
  "properties": {
    "addr:full": "1117 Park Ave Piqua OH 45356",
    "addr:housenumber": "1117",
    "addr:postcode": "45356",
    "addr:street": "Park Ave",
    "iso:country": "US",
    "sg:address": "1117 Park Ave",
    "sg:city": "Piqua",
    "sg:classifiers": [
      {
        "category": "Building \u0026 Trades",
        "subcategory": "Plumbing",
        "type": "Services"
      }
    ],
    "sg:phone": "+1 937 773 3709",
    "sg:postcode": "45356",
    "sg:province": "OH",
    "sg:tags": [
      "plumbing",
      "contractor"
    ],
    "wof:name": "Willis Allied Plumbing",
    "wof:placetype": "venue"
  },
  "geometry": {"coordinates":[-84.255726,40.153562],"type":"Point"}
}
