{
  "type": "Feature",
  "properties": {
    "iso:country":"US",
    "sg:address":"1200 Oakwood Ave",
    "sg:city":"Dayton",
    "sg:classifiers":[
        {
            "category":"Professional",
            "subcategory":"Business Services",
            "type":"Services"
        }
    ],
    "sg:phone":"+1 937 299 3769",
    "sg:postcode":"45419",
    "sg:province":"OH",
    "sg:tags":[
        "embroidery"
    ],
    "wof:name":"J P Design",
    "wof:placetype":"venue"
},
  "geometry": {"coordinates":[-84.179862,39.717655],"type":"Point"}
}