{
  "type": "Feature",
  "properties": {
    "iso:country":"US",
    "sg:address":"32730 Walker Rd",
    "sg:city":"Avon Lake",
    "sg:classifiers":[
        {
            "category":"Insurance",
            "subcategory":"Insurance Agent",
            "type":"Services"
        }
    ],
    "sg:phone":"+1 440 933 2720",
    "sg:postcode":"44012",
    "sg:province":"OH",
    "wof:name":"State Farm Insurance",
    "wof:placetype":"venue"
},
  "geometry": {"coordinates":[-82.021272,41.49324],"type":"Point"}
}