{
  "type": "Feature",
  "properties": {
    "addr:full": "116 N Gamble St Shelby OH 44875",
    "addr:housenumber": "116",
    "addr:postcode": "44875",
    "addr:street": "N Gamble St",
    "iso:country": "US",
    "sg:address": "116 N Gamble St",
    "sg:city": "Shelby",
    "sg:classifiers": [
      {
        "category": "Food \u0026 Beverages",
        "subcategory": "Liquor \u0026 Beverages",
        "type": "Retail Goods"
      }
    ],
    "sg:phone": "+1 419 347 5409",
    "sg:postcode": "44875",
    "sg:province": "OH",
    "sg:tags": [
      "beer",
      "ale"
    ],
    "wof:name": "Shelby Carry Out Inc",
    "wof:placetype": "venue"
  },
  "geometry": {"coordinates":[-82.662085,40.885724],"type":"Point"}
}
