{
  "type": "Feature",
  "properties": {
    "iso:country":"US",
    "sg:address":"116 N Gamble St",
    "sg:city":"Shelby",
    "sg:classifiers":[
        {
            "category":"Food & Beverages",
            "subcategory":"Liquor & Beverages",
            "type":"Retail Goods"
        }
    ],
    "sg:phone":"+1 419 347 5409",
    "sg:postcode":"44875",
    "sg:province":"OH",
    "sg:tags":[
        "beer",
        "ale"
    ],
    "wof:name":"Shelby Carry Out Inc",
    "wof:placetype":"venue"
},
  "geometry": {"coordinates":[-82.662085,40.885724],"type":"Point"}
}