{
  "type": "Feature",
  "properties": {
    "addr:full":"1860 Clarion Ave Cincinnati OH 45207",
    "addr:housenumber":"1860",
    "addr:postcode":"45207",
    "addr:street":"Clarion Ave",
    "iso:country":"US",
    "sg:address":"1860 Clarion Ave",
    "sg:city":"Cincinnati",
    "sg:classifiers":[
        {
            "category":"Organizations",
            "subcategory":"Religious Organization",
            "type":"Services"
        }
    ],
    "sg:phone":"+1 513 396 6119",
    "sg:postcode":"45207",
    "sg:province":"OH",
    "sg:tags":[
        "church"
    ],
    "wof:name":"United House Of Prayer For All",
    "wof:placetype":"venue"
},
  "geometry": {"coordinates":[-84.46769999999999,39.14464],"type":"Point"}
}