{
  "type": "Feature",
  "properties": {
    "iso:country":"US",
    "sg:address":"3915 Reading Rd",
    "sg:city":"Cincinnati",
    "sg:classifiers":[
        {
            "category":"Retail",
            "subcategory":"Auto Repair",
            "type":"Services"
        }
    ],
    "sg:phone":"+1 513 751 0457",
    "sg:postcode":"45229",
    "sg:province":"OH",
    "sg:tags":[
        "body",
        "repairing",
        "painting",
        "automobile"
    ],
    "wof:name":"Doug's Frame & Body",
    "wof:placetype":"venue"
},
  "geometry": {"coordinates":[-84.480621,39.155819],"type":"Point"}
}