{
  "type": "Feature",
  "properties": {
    "addr:full":"1650 Manchester Ave Columbus OH 43211",
    "addr:housenumber":"1650",
    "addr:postcode":"43211",
    "addr:street":"Manchester Ave",
    "iso:country":"US",
    "sg:address":"1650 Manchester Ave",
    "sg:city":"Columbus",
    "sg:classifiers":[
        {
            "category":"Professional",
            "subcategory":"Management & Consulting",
            "type":"Services"
        }
    ],
    "sg:phone":"+1 614 447 1224",
    "sg:postcode":"43211",
    "sg:province":"OH",
    "sg:tags":[
        "consultant",
        "business"
    ],
    "wof:name":"Mc Millon Enterprises",
    "wof:placetype":"venue"
},
  "geometry": {"coordinates":[-82.965655,40.021851],"type":"Point"}
}