{
  "type": "Feature",
  "properties": {
    "iso:country":"US",
    "sg:address":"2828 Highland Ave",
    "sg:city":"Cincinnati",
    "sg:classifiers":[
        {
            "category":"Building & Trades",
            "subcategory":"Cleaning & Sanitation",
            "type":"Services"
        }
    ],
    "sg:phone":"+1 513 731 3590",
    "sg:postcode":"45212",
    "sg:province":"OH",
    "sg:tags":[
        "industrial"
    ],
    "wof:name":"Premier Mfg Support Svcs",
    "wof:placetype":"venue"
},
  "geometry": {"coordinates":[-84.436953,39.166661],"type":"Point"}
}