{
  "type": "Feature",
  "properties": {
    "addr:full": "431 Ohio Pike Cincinnati OH 45255",
    "addr:housenumber": "431",
    "addr:postcode": "45255",
    "addr:street": "Ohio Pike",
    "iso:country": "US",
    "sg:address": "431 Ohio Pike",
    "sg:city": "Cincinnati",
    "sg:classifiers": [
      {
        "category": "Retail",
        "subcategory": "Portrait Studio",
        "type": "Services"
      },
      {
        "category": "Shopping",
        "subcategory": "Computers \u0026 Home Electronics",
        "type": "Retail Goods"
      }
    ],
    "sg:phone": "+1 513 528 5710",
    "sg:postcode": "45255",
    "sg:province": "OH",
    "sg:tags": [
      "software",
      "developer"
    ],
    "sg:website": "www.treck.com",
    "wof:name": "Treck Inc",
    "wof:placetype": "venue"
  },
  "geometry": {"coordinates":[-84.312439,39.071722],"type":"Point"}
}
