{
  "type": "Feature",
  "properties": {
    "addr:full": "1282 E Ash St Piqua OH 45356",
    "addr:housenumber": "1282",
    "addr:postcode": "45356",
    "addr:street": "E Ash St",
    "iso:country": "US",
    "sg:address": "1282 E Ash St",
    "sg:city": "Piqua",
    "sg:classifiers": [
      {
        "category": "Shopping",
        "subcategory": "Shoes",
        "type": "Retail Goods"
      }
    ],
    "sg:phone": "+1 937 615 1097",
    "sg:postcode": "45356",
    "sg:province": "OH",
    "sg:website": "www.shoeshow.com",
    "wof:name": "Shoe Show",
    "wof:placetype": "venue"
  },
  "geometry": {"coordinates":[-84.209934,40.150798],"type":"Point"}
}
