{
  "type": "Feature",
  "properties": {
    "addr:full":"3140 Wolf Run Ct Cincinnati OH 45244",
    "addr:housenumber":"3140",
    "addr:postcode":"45244",
    "addr:street":"Wolf Run Ct",
    "iso:country":"US",
    "sg:address":"3140 Wolf Run Ct",
    "sg:city":"Cincinnati",
    "sg:classifiers":[
        {
            "category":"Building & Trades",
            "subcategory":"Construction",
            "type":"Services"
        }
    ],
    "sg:phone":"+1 513 561 1124",
    "sg:postcode":"45244",
    "sg:province":"OH",
    "sg:tags":[
        "elevator"
    ],
    "wof:name":"Thyssen Krupp Elevator",
    "wof:placetype":"venue"
},
  "geometry": {"coordinates":[-84.325514,39.114437],"type":"Point"}
}