{
  "type": "Feature",
  "properties": {
    "addr:full": "4797 Kingshill Dr Columbus OH 43229",
    "addr:housenumber": "4797",
    "addr:postcode": "43229",
    "addr:street": "Kingshill Dr",
    "iso:country": "US",
    "sg:address": "4797 Kingshill Dr",
    "sg:city": "Columbus",
    "sg:classifiers": [
      {
        "category": "Real Estate",
        "subcategory": "Real Estate Services",
        "type": "Services"
      }
    ],
    "sg:phone": "+1 877 657 4447",
    "sg:postcode": "43229",
    "sg:province": "OH",
    "sg:tags": [
      "apartment",
      "management",
      "rental",
      "finder"
    ],
    "sg:website": "http://www.forrent.com/apartment-community-profile/1001865.php?cmp=CAC-CSearchProfile",
    "wof:name": "Kingshill Court",
    "wof:placetype": "venue"
  },
  "geometry": {"coordinates":[-82.990079,40.063892],"type":"Point"}
}
