{
  "type": "Feature",
  "properties": {
    "addr:full": "4043 Afton-Elklick Rd Batavia OH 45103",
    "addr:housenumber": "4043",
    "addr:postcode": "45103",
    "addr:street": "Afton-Elklick Rd",
    "iso:country": "US",
    "sg:address": "4043 Afton-Elklick Rd",
    "sg:city": "Batavia",
    "sg:classifiers": [
      {
        "category": "Freight",
        "type": "Transportation"
      }
    ],
    "sg:phone": "+1 513 724 2655",
    "sg:postcode": "45103",
    "sg:province": "OH",
    "sg:tags": [
      "operator",
      "local",
      "trucking"
    ],
    "wof:name": "Brete Trucking LLC",
    "wof:placetype": "venue"
  },
  "geometry": {"coordinates":[-84.111315,39.048847],"type":"Point"}
}
