{
  "type": "Feature",
  "properties": {
    "addr:full":"38029 3rd St Willoughby OH 44094",
    "addr:housenumber":"38029",
    "addr:postcode":"44094",
    "addr:street":"3Rd St",
    "iso:country":"US",
    "sg:address":"38029 3rd St",
    "sg:city":"Willoughby",
    "sg:classifiers":[
        {
            "category":"Insurance",
            "subcategory":"Insurance Agent",
            "type":"Services"
        }
    ],
    "sg:phone":"+1 440 951 6100",
    "sg:postcode":"44094",
    "sg:province":"OH",
    "wof:name":"Insurance Partners Agency",
    "wof:placetype":"venue"
},
  "geometry": {"coordinates":[-81.406806,41.641798],"type":"Point"}
}