{
  "type": "Feature",
  "properties": {
    "addr:full":"730 Thurber Dr W Columbus OH 43215",
    "addr:housenumber":"730",
    "addr:postcode":"43215",
    "addr:street":"Thurber Dr W",
    "iso:country":"US",
    "sg:address":"730 Thurber Dr W",
    "sg:city":"Columbus",
    "sg:classifiers":[
        {
            "category":"Real Estate",
            "subcategory":"Real Estate Operator",
            "type":"Services"
        }
    ],
    "sg:phone":"+1 614 221 5921",
    "sg:postcode":"43215",
    "sg:province":"OH",
    "sg:tags":[
        "apartment"
    ],
    "wof:name":"Sonnenblick Apartments",
    "wof:placetype":"venue"
},
  "geometry": {"coordinates":[-83.012809,39.975596],"type":"Point"}
}