{
  "type": "Feature",
  "properties": {
    "addr:full":"1168 Bethel-New Richmond Rd New Richmond OH 45157",
    "addr:housenumber":"1168",
    "addr:postcode":"45157",
    "addr:street":"Bethel-New Richmond Rd",
    "iso:country":"US",
    "sg:address":"1168 Bethel-New Richmond Rd",
    "sg:city":"New Richmond",
    "sg:classifiers":[
        {
            "category":"Organizations",
            "subcategory":"Religious Organization",
            "type":"Services"
        }
    ],
    "sg:phone":"+1 513 553 1999",
    "sg:postcode":"45157",
    "sg:province":"OH",
    "sg:tags":[
        "church"
    ],
    "wof:name":"First Baptist Chr-New Rchmnd",
    "wof:placetype":"venue"
},
  "geometry": {"coordinates":[-84.26297,38.955135],"type":"Point"}
}