{
  "type": "Feature",
  "properties": {
    "iso:country":"US",
    "sg:address":"2068 Stringtown Rd",
    "sg:city":"Grove City",
    "sg:classifiers":[
        {
            "category":"Professional",
            "subcategory":"Management & Consulting",
            "type":"Services"
        }
    ],
    "sg:phone":"+1 614 871 0837",
    "sg:postcode":"43123",
    "sg:province":"OH",
    "sg:tags":[
        "communications",
        "consultant"
    ],
    "wof:name":"Wireless One World",
    "wof:placetype":"venue"
},
  "geometry": {"coordinates":[-83.05777,39.878496],"type":"Point"}
}