{
  "type": "Feature",
  "properties": {
    "addr:full":"701 Larona Rd Dayton OH 45426",
    "addr:housenumber":"701",
    "addr:postcode":"45426",
    "addr:street":"Larona Rd",
    "iso:country":"US",
    "sg:address":"701 Larona Rd",
    "sg:city":"Dayton",
    "sg:classifiers":[
        {
            "category":"Shopping",
            "subcategory":"Clothing, Apparel, & Fashions",
            "type":"Retail Goods"
        }
    ],
    "sg:phone":"+1 937 837 7974",
    "sg:postcode":"45426",
    "sg:province":"OH",
    "wof:name":"Style of Excellence",
    "wof:placetype":"venue"
},
  "geometry": {"coordinates":[-84.298096,39.806692],"type":"Point"}
}