{
  "type": "Feature",
  "properties": {
    "addr:full":"6019 Brandt Pike Dayton OH 45424",
    "addr:housenumber":"6019",
    "addr:postcode":"45424",
    "addr:street":"Brandt Pike",
    "iso:country":"US",
    "sg:address":"6019 Brandt Pike",
    "sg:city":"Dayton",
    "sg:classifiers":[
        {
            "category":"Personal",
            "subcategory":"Beauty Salon",
            "type":"Services"
        }
    ],
    "sg:phone":"+1 937 233 0500",
    "sg:postcode":"45424",
    "sg:province":"OH",
    "sg:tags":[
        "manicuring"
    ],
    "wof:name":"T-Nails",
    "wof:placetype":"venue"
},
  "geometry": {"coordinates":[-84.115165,39.845156],"type":"Point"}
}