{
  "type": "Feature",
  "properties": {
    "addr:full":"901 Leona St Elyria OH 44035",
    "addr:housenumber":"901",
    "addr:postcode":"44035",
    "addr:street":"Leona St",
    "iso:country":"US",
    "sg:address":"901 Leona St",
    "sg:city":"Elyria",
    "sg:classifiers":[
        {
            "category":"Freight",
            "type":"Transportation"
        }
    ],
    "sg:phone":"+1 440 324 5518",
    "sg:postcode":"44035",
    "sg:province":"OH",
    "sg:tags":[
        "general"
    ],
    "wof:name":"Uncle Bobs Self Storage",
    "wof:placetype":"venue"
},
  "geometry": {"coordinates":[-82.119838,41.401883],"type":"Point"}
}