{
  "type": "Feature",
  "properties": {
    "addr:full":"48 W Bowery St Akron OH 44308",
    "addr:housenumber":"48",
    "addr:postcode":"44308",
    "addr:street":"W Bowery St",
    "iso:country":"US",
    "sg:address":"48 W Bowery St",
    "sg:city":"Akron",
    "sg:classifiers":[
        {
            "category":"Banks & Credit Unions",
            "subcategory":"Bank",
            "type":"Services"
        }
    ],
    "sg:phone":"+1 330 319 6001",
    "sg:postcode":"44308",
    "sg:province":"OH",
    "sg:tags":[
        "company",
        "trust"
    ],
    "wof:name":"Everyday Trust",
    "wof:placetype":"venue"
},
  "geometry": {"coordinates":[-81.51882999999999,41.081202],"type":"Point"}
}