{
  "type": "Feature",
  "properties": {
    "addr:full": "734 Main St Wintersville OH 43953",
    "addr:housenumber": "734",
    "addr:postcode": "43953",
    "addr:street": "Main St",
    "iso:country": "US",
    "sg:address": "734 Main St",
    "sg:city": "Wintersville",
    "sg:classifiers": [
      {
        "category": "Health Services",
        "subcategory": "Optometrist",
        "type": "Services"
      }
    ],
    "sg:phone": "+1 740 264 2223",
    "sg:postcode": "43953",
    "sg:province": "OH",
    "wof:name": "Eye Clinic",
    "wof:placetype": "venue"
  },
  "geometry": {"coordinates":[-80.698638,40.374322],"type":"Point"}
}
