{
  "type": "Feature",
  "properties": {
    "iso:country":"US",
    "sg:address":"1249 Sunset View Dr W",
    "sg:city":"Akron",
    "sg:classifiers":[
        {
            "category":"Building & Trades",
            "subcategory":"Plumbing",
            "type":"Services"
        }
    ],
    "sg:phone":"+1 330 836 3247",
    "sg:postcode":"44313",
    "sg:province":"OH",
    "sg:tags":[
        "plumbing",
        "contractor"
    ],
    "wof:name":"Lew's Plumbing & Drain Co",
    "wof:placetype":"venue"
},
  "geometry": {"coordinates":[-81.55795500000001,41.095863],"type":"Point"}
}