{
  "type": "Feature",
  "properties": {
    "addr:full": "1249 Sunset View Dr W Akron OH 44313",
    "addr:housenumber": "1249",
    "addr:postcode": "44313",
    "addr:street": "Sunset View Dr W",
    "iso:country": "US",
    "sg:address": "1249 Sunset View Dr W",
    "sg:city": "Akron",
    "sg:classifiers": [
      {
        "category": "Building \u0026 Trades",
        "subcategory": "Plumbing",
        "type": "Services"
      }
    ],
    "sg:phone": "+1 330 836 3247",
    "sg:postcode": "44313",
    "sg:province": "OH",
    "sg:tags": [
      "plumbing",
      "contractor"
    ],
    "wof:name": "Lew's Plumbing \u0026 Drain Co",
    "wof:placetype": "venue"
  },
  "geometry": {"coordinates":[-81.557955,41.095863],"type":"Point"}
}
