{
  "type": "Feature",
  "properties": {
    "addr:full":"18565 State Rte 301 Lagrange OH 44050",
    "addr:housenumber":"18565",
    "addr:postcode":"44050",
    "addr:street":"State Rte 301",
    "iso:country":"US",
    "sg:address":"18565 State Rte 301",
    "sg:city":"Lagrange",
    "sg:classifiers":[
        {
            "category":"Restaurant",
            "type":"Food & Drink"
        }
    ],
    "sg:phone":"+1 440 355 6971",
    "sg:postcode":"44050",
    "sg:province":"OH",
    "sg:tags":[
        "eating"
    ],
    "wof:name":"Crm Manufacturing Inc",
    "wof:placetype":"venue"
},
  "geometry": {"coordinates":[-82.119958,41.21639],"type":"Point"}
}