{
  "type": "Feature",
  "properties": {
    "addr:full": "201 Ditto St Archbold OH 43502",
    "addr:housenumber": "201",
    "addr:postcode": "43502",
    "addr:street": "Ditto St",
    "iso:country": "US",
    "sg:address": "201 Ditto St",
    "sg:city": "Archbold",
    "sg:classifiers": [
      {
        "category": "Wholesale",
        "subcategory": "Computers",
        "type": "Manufacturing \u0026 Wholesale Goods"
      }
    ],
    "sg:phone": "+1 419 445 4775",
    "sg:postcode": "43502",
    "sg:province": "OH",
    "wof:name": "Pro-Soft",
    "wof:placetype": "venue"
  },
  "geometry": {"coordinates":[-84.307577,41.523621],"type":"Point"}
}
