{
  "type": "Feature",
  "properties": {
    "addr:full": "805 W Church St Newark OH 43055",
    "addr:housenumber": "805",
    "addr:postcode": "43055",
    "addr:street": "W Church St",
    "iso:country": "US",
    "sg:address": "805 W Church St",
    "sg:city": "Newark",
    "sg:classifiers": [
      {
        "category": "Education",
        "subcategory": "School",
        "type": "Public Place"
      }
    ],
    "sg:phone": "+1 740 349 2315",
    "sg:postcode": "43055",
    "sg:province": "OH",
    "wof:name": "Wilson Middle School",
    "wof:placetype": "venue"
  },
  "geometry": {"coordinates":[-82.432012,40.058031],"type":"Point"}
}
