{
  "type": "Feature",
  "properties": {
    "addr:full":"5427 Schultz Dr Sylvania OH 43560",
    "addr:housenumber":"5427",
    "addr:postcode":"43560",
    "addr:street":"Schultz Dr",
    "iso:country":"US",
    "sg:address":"5427 Schultz Dr",
    "sg:city":"Sylvania",
    "sg:classifiers":[
        {
            "category":"Manufacturing",
            "subcategory":"Printing",
            "type":"Manufacturing & Wholesale Goods"
        }
    ],
    "sg:phone":"+1 419 882 3900",
    "sg:postcode":"43560",
    "sg:province":"OH",
    "sg:tags":[
        "printer"
    ],
    "wof:name":"Sylvania Quickprint",
    "wof:placetype":"venue"
},
  "geometry": {"coordinates":[-83.678529,41.714264],"type":"Point"}
}