{
  "type": "Feature",
  "properties": {
    "iso:country":"US",
    "sg:address":"11970 Sinclair St SW",
    "sg:city":"Massillon",
    "sg:classifiers":[
        {
            "category":"Shopping",
            "type":"Retail Goods"
        }
    ],
    "sg:phone":"+1 330 833 9915",
    "sg:postcode":"44647",
    "sg:province":"OH",
    "sg:tags":[
        "merchandise"
    ],
    "wof:name":"Lochs Rocks",
    "wof:placetype":"venue"
},
  "geometry": {"coordinates":[-81.583158,40.778608],"type":"Point"}
}