{
  "type": "Feature",
  "properties": {
    "addr:full":"9923 Hampden Ave Cleveland OH 44108",
    "addr:housenumber":"9923",
    "addr:postcode":"44108",
    "addr:street":"Hampden Ave",
    "iso:country":"US",
    "sg:address":"9923 Hampden Ave",
    "sg:city":"Cleveland",
    "sg:classifiers":[
        {
            "category":"Shopping",
            "subcategory":"Gifts & Souvenirs",
            "type":"Retail Goods"
        }
    ],
    "sg:phone":"+1 216 791 4174",
    "sg:postcode":"44108",
    "sg:province":"OH",
    "sg:tags":[
        "shop"
    ],
    "wof:name":"Michael S Gift Ideas",
    "wof:placetype":"venue"
},
  "geometry": {"coordinates":[-81.61803399999999,41.524234],"type":"Point"}
}