{
  "type": "Feature",
  "properties": {
    "addr:full": "185 Wadsworth Rd Wadsworth OH 44281",
    "addr:housenumber": "185",
    "addr:postcode": "44281",
    "addr:street": "Wadsworth Rd",
    "iso:country": "US",
    "sg:address": "185 Wadsworth Rd",
    "sg:city": "Wadsworth",
    "sg:classifiers": [
      {
        "category": "Personal",
        "subcategory": "Beauty Salon",
        "type": "Services"
      }
    ],
    "sg:phone": "+1 330 334 5674",
    "sg:postcode": "44281",
    "sg:province": "OH",
    "sg:tags": [
      "treatment",
      "skin"
    ],
    "wof:name": "Advanced Laser Cosmetics",
    "wof:placetype": "venue"
  },
  "geometry": {"coordinates":[-81.75413,41.026699],"type":"Point"}
}
