{
  "type": "Feature",
  "properties": {
    "iso:country":"US",
    "sg:address":"4161 Dublin Rd",
    "sg:city":"Hilliard",
    "sg:classifiers":[
        {
            "category":"Insurance",
            "subcategory":"Insurance Agent",
            "type":"Services"
        }
    ],
    "sg:phone":"+1 614 876 5984",
    "sg:postcode":"43026",
    "sg:province":"OH",
    "wof:name":"Donald J Bren",
    "wof:placetype":"venue"
},
  "geometry": {"coordinates":[-83.103673,40.04265],"type":"Point"}
}