{
  "type": "Feature",
  "properties": {
    "iso:country":"US",
    "sg:address":"2343 Dixie Hwy",
    "sg:city":"Hamilton",
    "sg:classifiers":[
        {
            "category":"Restaurant",
            "type":"Food & Drink"
        }
    ],
    "sg:phone":"+1 513 894 3217",
    "sg:postcode":"45015",
    "sg:province":"OH",
    "sg:tags":[
        "pizzeria"
    ],
    "wof:name":"Richards Plaza Pizza",
    "wof:placetype":"venue"
},
  "geometry": {"coordinates":[-84.548658,39.372876],"type":"Point"}
}