{
  "type": "Feature",
  "properties": {
    "addr:full":"2190 S Overlook Rd Cleveland OH 44106",
    "addr:housenumber":"2190",
    "addr:postcode":"44106",
    "addr:street":"S Overlook Rd",
    "iso:country":"US",
    "sg:address":"2190 S Overlook Rd",
    "sg:city":"Cleveland",
    "sg:classifiers":[
        {
            "category":"Shopping",
            "subcategory":"Used Merchandise",
            "type":"Retail Goods"
        }
    ],
    "sg:phone":"+1 216 791 0774",
    "sg:postcode":"44106",
    "sg:province":"OH",
    "wof:name":"Chinese Antique Art",
    "wof:placetype":"venue"
},
  "geometry": {"coordinates":[-81.59724799999999,41.499688],"type":"Point"}
}