{
  "type": "Feature",
  "properties": {
    "addr:full": "651 E 128th St Cleveland OH 44108",
    "addr:housenumber": "651",
    "addr:postcode": "44108",
    "addr:street": "E 128Th St",
    "iso:country": "US",
    "sg:address": "651 E 128th St",
    "sg:city": "Cleveland",
    "sg:classifiers": [
      {
        "category": "Professional",
        "type": "Services"
      }
    ],
    "sg:phone": "+1 216 268 3445",
    "sg:postcode": "44108",
    "sg:province": "OH",
    "wof:name": "Dorothy A Bolden-Bullard",
    "wof:placetype": "venue"
  },
  "geometry": {"coordinates":[-81.594454,41.540278],"type":"Point"}
}
