{
  "type": "Feature",
  "properties": {
    "addr:full":"453 N 20th St Columbus OH 43203",
    "addr:housenumber":"453",
    "addr:postcode":"43203",
    "addr:street":"N 20Th St",
    "iso:country":"US",
    "sg:address":"453 N 20th St",
    "sg:city":"Columbus",
    "sg:classifiers":[
        {
            "category":"Social Services",
            "subcategory":"Child Care",
            "type":"Services"
        }
    ],
    "sg:phone":"+1 614 253 6567",
    "sg:postcode":"43203",
    "sg:province":"OH",
    "sg:tags":[
        "kindergarten",
        "academic",
        "school"
    ],
    "wof:name":"John Xxiii Head Start Program",
    "wof:placetype":"venue"
},
  "geometry": {"coordinates":[-82.973178,39.975013],"type":"Point"}
}