{
  "type": "Feature",
  "properties": {
    "addr:full":"800 Indiana Ave St Marys OH 45885",
    "addr:housenumber":"800",
    "addr:postcode":"45885",
    "addr:street":"Indiana Ave",
    "iso:country":"US",
    "sg:address":"800 Indiana Ave",
    "sg:city":"St Marys",
    "sg:classifiers":[
        {
            "category":"Real Estate",
            "subcategory":"Real Estate Operator",
            "type":"Services"
        }
    ],
    "sg:phone":"+1 419 394 4230",
    "sg:postcode":"45885",
    "sg:province":"OH",
    "sg:tags":[
        "apartment"
    ],
    "wof:name":"St Marys Senior Village Apts",
    "wof:placetype":"venue"
},
  "geometry": {"coordinates":[-84.400155,40.548103],"type":"Point"}
}