{
  "type": "Feature",
  "properties": {
    "addr:full":"16 S Oakmont Rd Northfield OH 44067",
    "addr:housenumber":"16",
    "addr:postcode":"44067",
    "addr:street":"S Oakmont Rd",
    "iso:country":"US",
    "sg:address":"16 S Oakmont Rd",
    "sg:city":"Northfield",
    "sg:classifiers":[
        {
            "category":"Retail",
            "subcategory":"Repair Shop",
            "type":"Services"
        },
        {
            "category":"Building & Trades",
            "subcategory":"Plumbing",
            "type":"Services"
        }
    ],
    "sg:phone":"+1 330 468 2750",
    "sg:postcode":"44067",
    "sg:province":"OH",
    "sg:tags":[
        "equipment",
        "air",
        "conditioning",
        "contractor"
    ],
    "wof:name":"Joe's A/C & Refrigeration",
    "wof:placetype":"venue"
},
  "geometry": {"coordinates":[-81.516436,41.291347],"type":"Point"}
}