{
  "type": "Feature",
  "properties": {
    "addr:full": "115 E 3rd St Dayton OH 45402",
    "addr:housenumber": "115",
    "addr:postcode": "45402",
    "addr:street": "E 3Rd St",
    "iso:country": "US",
    "sg:address": "115 E 3rd St",
    "sg:city": "Dayton",
    "sg:classifiers": [
      {
        "category": "Professional",
        "type": "Services"
      }
    ],
    "sg:phone": "+1 937 222 7412",
    "sg:postcode": "45402",
    "sg:province": "OH",
    "sg:tags": [
      "establishment"
    ],
    "wof:name": "Pager One",
    "wof:placetype": "venue"
  },
  "geometry": {"coordinates":[-84.188495,39.760124],"type":"Point"}
}
