{
  "type": "Feature",
  "properties": {
    "addr:full":"3728 Isabella Ave Cincinnati OH 45209",
    "addr:housenumber":"3728",
    "addr:postcode":"45209",
    "addr:street":"Isabella Ave",
    "iso:country":"US",
    "sg:address":"3728 Isabella Ave",
    "sg:city":"Cincinnati",
    "sg:classifiers":[
        {
            "category":"Building & Trades",
            "subcategory":"Construction",
            "type":"Services"
        },
        {
            "category":"Wholesale",
            "subcategory":"Furniture",
            "type":"Manufacturing & Wholesale Goods"
        }
    ],
    "sg:phone":"+1 513 351 6736",
    "sg:postcode":"45209",
    "sg:province":"OH",
    "sg:tags":[
        "wooden",
        "maker",
        "cabinet"
    ],
    "wof:name":"Cabinet Masters Inc",
    "wof:placetype":"venue"
},
  "geometry": {"coordinates":[-84.43261699999999,39.146495],"type":"Point"}
}