{
  "type": "Feature",
  "properties": {
    "addr:full": "623 Ardiss Pl Sidney OH 45365",
    "addr:housenumber": "623",
    "addr:postcode": "45365",
    "addr:street": "Ardiss Pl",
    "iso:country": "US",
    "sg:address": "623 Ardiss Pl",
    "sg:city": "Sidney",
    "sg:classifiers": [
      {
        "category": "Insurance",
        "subcategory": "Insurance Agent",
        "type": "Services"
      }
    ],
    "sg:phone": "+1 937 492 3414",
    "sg:postcode": "45365",
    "sg:province": "OH",
    "wof:name": "Dean Julian Insurance Co",
    "wof:placetype": "venue"
  },
  "geometry": {"coordinates":[-84.148343,40.279789],"type":"Point"}
}
