{
  "type": "Feature",
  "properties": {
    "iso:country":"US",
    "sg:address":"4852 Hunt Rd",
    "sg:city":"Cincinnati",
    "sg:classifiers":[
        {
            "category":"Personal",
            "subcategory":"Beauty Salon",
            "type":"Services"
        }
    ],
    "sg:phone":"+1 513 791 6330",
    "sg:postcode":"45242",
    "sg:province":"OH",
    "sg:website":"www.kennethshaircutting.com",
    "wof:name":"Kenneth's Haircutting Inc",
    "wof:placetype":"venue"
},
  "geometry": {"coordinates":[-84.375022,39.230563],"type":"Point"}
}