{
  "type": "Feature",
  "properties": {
    "addr:full":"9501 Sunrise Blvd Cleveland OH 44133",
    "addr:housenumber":"9501",
    "addr:postcode":"44133",
    "addr:street":"Sunrise Blvd",
    "iso:country":"US",
    "sg:address":"9501 Sunrise Blvd",
    "sg:city":"Cleveland",
    "sg:classifiers":[
        {
            "category":"Building & Trades",
            "subcategory":"Landscaping Services",
            "type":"Services"
        }
    ],
    "sg:phone":"+1 440 877 1060",
    "sg:postcode":"44133",
    "sg:province":"OH",
    "sg:tags":[
        "landscape",
        "contractor"
    ],
    "wof:name":"Lawrin Landscaping",
    "wof:placetype":"venue"
},
  "geometry": {"coordinates":[-81.759367,41.327625],"type":"Point"}
}