{
  "type": "Feature",
  "properties": {
    "iso:country":"US",
    "sg:address":"750 Garfield Ave NW",
    "sg:city":"Carrollton",
    "sg:classifiers":[
        {
            "category":"Wholesale",
            "subcategory":"Stationery",
            "type":"Manufacturing & Wholesale Goods"
        }
    ],
    "sg:phone":"+1 330 627 2210",
    "sg:postcode":"44615",
    "sg:province":"OH",
    "sg:tags":[
        "paper"
    ],
    "wof:name":"Noramco",
    "wof:placetype":"venue"
},
  "geometry": {"coordinates":[-81.08700899999999,40.580352],"type":"Point"}
}