{
  "type": "Feature",
  "properties": {
    "addr:full":"200 N Main St Rittman OH 44270",
    "addr:housenumber":"200",
    "addr:postcode":"44270",
    "addr:street":"N Main St",
    "iso:country":"US",
    "sg:address":"200 N Main St",
    "sg:city":"Rittman",
    "sg:classifiers":[
        {
            "category":"Restaurant",
            "type":"Food & Drink"
        }
    ],
    "sg:menulink":"http://www.allmenus.com/oh/milton/170377-burger-king/menu/",
    "sg:phone":"+1 330 927 5464",
    "sg:postcode":"44270",
    "sg:province":"OH",
    "sg:tags":[
        "burger",
        "american"
    ],
    "wof:name":"Burger King",
    "wof:placetype":"venue"
},
  "geometry": {"coordinates":[-81.78149500000001,40.976244],"type":"Point"}
}