{
  "type": "Feature",
  "properties": {
    "iso:country":"US",
    "sg:address":"7720 Montgomery Rd",
    "sg:city":"Cincinnati",
    "sg:classifiers":[
        {
            "category":"Professional",
            "subcategory":"Research",
            "type":"Services"
        }
    ],
    "sg:phone":"+1 513 984 6868",
    "sg:postcode":"45236",
    "sg:province":"OH",
    "sg:tags":[
        "commercial",
        "physical"
    ],
    "wof:name":"Hill Top Research Inc",
    "wof:placetype":"venue"
},
  "geometry": {"coordinates":[-84.382549,39.198052],"type":"Point"}
}