{
  "type": "Feature",
  "properties": {
    "addr:full": "820 3rd St Findlay OH 45840",
    "addr:housenumber": "820",
    "addr:postcode": "45840",
    "addr:street": "3Rd St",
    "iso:country": "US",
    "sg:address": "820 3rd St",
    "sg:city": "Findlay",
    "sg:classifiers": [
      {
        "category": "Real Estate",
        "subcategory": "Real Estate Agent",
        "type": "Services"
      }
    ],
    "sg:phone": "+1 419 424 1359",
    "sg:postcode": "45840",
    "sg:province": "OH",
    "sg:tags": [
      "manager"
    ],
    "wof:name": "Joe Edinger Realty",
    "wof:placetype": "venue"
  },
  "geometry": {"coordinates":[-83.635494,41.026343],"type":"Point"}
}
