{
  "type": "Feature",
  "properties": {
    "addr:full":"5380 Monroe St Toledo OH 43623",
    "addr:housenumber":"5380",
    "addr:postcode":"43623",
    "addr:street":"Monroe St",
    "iso:country":"US",
    "sg:address":"5380 Monroe St",
    "sg:city":"Toledo",
    "sg:classifiers":[
        {
            "category":"Shopping",
            "type":"Retail Goods"
        }
    ],
    "sg:phone":"+1 419 843 4384",
    "sg:postcode":"43623",
    "sg:province":"OH",
    "sg:tags":[
        "electronic",
        "merchandise"
    ],
    "wof:name":"Verizon",
    "wof:placetype":"venue"
},
  "geometry": {"coordinates":[-83.660134,41.704545],"type":"Point"}
}