{
  "type": "Feature",
  "properties": {
    "iso:country":"US",
    "sg:address":"3454 Oak Alley Ct",
    "sg:city":"Toledo",
    "sg:classifiers":[
        {
            "category":"Professional",
            "subcategory":"Management & Consulting",
            "type":"Services"
        }
    ],
    "sg:phone":"+1 419 720 0006",
    "sg:postcode":"43606",
    "sg:province":"OH",
    "sg:tags":[
        "personnel",
        "consultant"
    ],
    "wof:name":"Alphacare Services Inc",
    "wof:placetype":"venue"
},
  "geometry": {"coordinates":[-83.62883100000001,41.682845],"type":"Point"}
}