{
  "type": "Feature",
  "properties": {
    "iso:country":"US",
    "sg:address":"875 Warner Rd SE",
    "sg:city":"Brookfield",
    "sg:classifiers":[
        {
            "category":"Manufacturing",
            "subcategory":"Printing",
            "type":"Manufacturing & Wholesale Goods"
        }
    ],
    "sg:phone":"+1 330 568 1311",
    "sg:postcode":"44403",
    "sg:province":"OH",
    "sg:tags":[
        "newspaper"
    ],
    "wof:name":"Page 1NA",
    "wof:placetype":"venue"
},
  "geometry": {"coordinates":[-80.616851,41.219371],"type":"Point"}
}