{
  "type": "Feature",
  "properties": {
    "addr:full":"704 W Washington St Sandusky OH 44870",
    "addr:housenumber":"704",
    "addr:postcode":"44870",
    "addr:street":"W Washington St",
    "iso:country":"US",
    "sg:address":"704 W Washington St",
    "sg:city":"Sandusky",
    "sg:classifiers":[
        {
            "category":"Retail",
            "subcategory":"Auto Repair",
            "type":"Services"
        }
    ],
    "sg:phone":"+1 419 627 8713",
    "sg:postcode":"44870",
    "sg:province":"OH",
    "wof:name":"J & J Automtv",
    "wof:placetype":"venue"
},
  "geometry": {"coordinates":[-82.71579699999999,41.4534],"type":"Point"}
}