{
  "type": "Feature",
  "properties": {
    "addr:full": "10280 Chester Rd Cincinnati OH 45215",
    "addr:housenumber": "10280",
    "addr:postcode": "45215",
    "addr:street": "Chester Rd",
    "iso:country": "US",
    "sg:address": "10280 Chester Rd",
    "sg:city": "Cincinnati",
    "sg:classifiers": [
      {
        "category": "Government",
        "subcategory": "Fire Station",
        "type": "Public Place"
      },
      {
        "category": "Building \u0026 Trades",
        "subcategory": "Cleaning \u0026 Sanitation",
        "type": "Services"
      },
      {
        "category": "Building \u0026 Trades",
        "subcategory": "Construction",
        "type": "Services"
      }
    ],
    "sg:phone": "+1 877 378 6724",
    "sg:postcode": "45215",
    "sg:province": "OH",
    "sg:tags": [
      "recovery",
      "altering",
      "damage",
      "contractor",
      "water",
      "restoration",
      "relief",
      "remodeling",
      "disaster"
    ],
    "sg:website": "http://www.restoraid.com",
    "wof:name": "Restoraid Restoration",
    "wof:placetype": "venue"
  },
  "geometry": {"coordinates":[-84.457161,39.253799],"type":"Point"}
}
