{
  "type": "Feature",
  "properties": {
    "iso:country":"US",
    "sg:address":"839 Sheridan Dr",
    "sg:city":"Lancaster",
    "sg:classifiers":[
        {
            "category":"Wholesale",
            "subcategory":"Machinery & Supplies",
            "type":"Manufacturing & Wholesale Goods"
        }
    ],
    "sg:phone":"+1 740 687 6556",
    "sg:postcode":"43130",
    "sg:province":"OH",
    "sg:tags":[
        "machine",
        "tool"
    ],
    "wof:name":"Dakota Machine Inc",
    "wof:placetype":"venue"
},
  "geometry": {"coordinates":[-82.577522,39.722746],"type":"Point"}
}