{
  "type": "Feature",
  "properties": {
    "addr:full": "7830 Cleveland Rd Wooster OH 44691",
    "addr:housenumber": "7830",
    "addr:postcode": "44691",
    "addr:street": "Cleveland Rd",
    "iso:country": "US",
    "sg:address": "7830 Cleveland Rd",
    "sg:city": "Wooster",
    "sg:classifiers": [
      {
        "category": "Professional",
        "subcategory": "Business Services",
        "type": "Services"
      }
    ],
    "sg:phone": "+1 330 345 9000",
    "sg:postcode": "44691",
    "sg:province": "OH",
    "sg:website": "www.oc2d.com",
    "wof:name": "One Call Digital Designs",
    "wof:placetype": "venue"
  },
  "geometry": {"coordinates":[-81.915054,40.89868],"type":"Point"}
}
