{
  "type": "Feature",
  "properties": {
    "iso:country":"US",
    "sg:address":"80 E Nottingham Rd",
    "sg:city":"Dayton",
    "sg:classifiers":[
        {
            "category":"Organizations",
            "subcategory":"Religious Organization",
            "type":"Services"
        }
    ],
    "sg:phone":"+1 937 278 9648",
    "sg:postcode":"45405",
    "sg:province":"OH",
    "sg:tags":[
        "church"
    ],
    "wof:name":"Deliverance Temple",
    "wof:placetype":"venue"
},
  "geometry": {"coordinates":[-84.22195600000001,39.805736],"type":"Point"}
}