{
  "type": "Feature",
  "properties": {
    "iso:country":"US",
    "sg:address":"4300 Gateway Blvd",
    "sg:city":"Springfield",
    "sg:classifiers":[
        {
            "category":"Manufacturing",
            "subcategory":"Textiles",
            "type":"Manufacturing & Wholesale Goods"
        }
    ],
    "sg:phone":"+1 937 323 7024",
    "sg:postcode":"45502",
    "sg:province":"OH",
    "sg:website":"www.fhbonn.com",
    "wof:name":"F H Bonn Co",
    "wof:placetype":"venue"
},
  "geometry": {"coordinates":[-83.721781,39.90693],"type":"Point"}
}