{
  "type": "Feature",
  "properties": {
    "addr:full": "4300 Gateway Blvd Springfield OH 45502",
    "addr:housenumber": "4300",
    "addr:postcode": "45502",
    "addr:street": "Gateway Blvd",
    "iso:country": "US",
    "sg:address": "4300 Gateway Blvd",
    "sg:city": "Springfield",
    "sg:classifiers": [
      {
        "category": "Manufacturing",
        "subcategory": "Textiles",
        "type": "Manufacturing \u0026 Wholesale Goods"
      }
    ],
    "sg:phone": "+1 937 323 7024",
    "sg:postcode": "45502",
    "sg:province": "OH",
    "sg:website": "www.fhbonn.com",
    "wof:name": "F H Bonn Co",
    "wof:placetype": "venue"
  },
  "geometry": {"coordinates":[-83.721781,39.90693],"type":"Point"}
}
