{
  "type": "Feature",
  "properties": {
    "addr:full":"260 Northland Blvd Cincinnati OH 45246",
    "addr:housenumber":"260",
    "addr:postcode":"45246",
    "addr:street":"Northland Blvd",
    "iso:country":"US",
    "sg:address":"260 Northland Blvd",
    "sg:city":"Cincinnati",
    "sg:classifiers":[
        {
            "category":"Banks & Credit Unions",
            "subcategory":"Bank",
            "type":"Services"
        }
    ],
    "sg:phone":"+1 513 771 9376",
    "sg:postcode":"45246",
    "sg:province":"OH",
    "sg:tags":[
        "loan",
        "real estate"
    ],
    "wof:name":"Premier Mortgage Funding-Oh",
    "wof:placetype":"venue"
},
  "geometry": {"coordinates":[-84.48319499999999,39.282517],"type":"Point"}
}