{
  "type": "Feature",
  "properties": {
    "iso:country":"US",
    "sg:address":"7100 State Rd",
    "sg:city":"Cleveland",
    "sg:classifiers":[
        {
            "category":"Building & Trades",
            "subcategory":"Construction",
            "type":"Services"
        }
    ],
    "sg:phone":"+1 440 845 0699",
    "sg:postcode":"44134",
    "sg:province":"OH",
    "sg:tags":[
        "restoration",
        "cleaning",
        "patio",
        "deck"
    ],
    "wof:name":"Crystal Kleen Pressure Washing",
    "wof:placetype":"venue"
},
  "geometry": {"coordinates":[-81.715193,41.370906],"type":"Point"}
}