{
  "type": "Feature",
  "properties": {
    "iso:country":"US",
    "sg:address":"123 S Keowee St",
    "sg:city":"Dayton",
    "sg:classifiers":[
        {
            "category":"Wholesale",
            "subcategory":"Electrical",
            "type":"Manufacturing & Wholesale Goods"
        }
    ],
    "sg:phone":"+1 937 228 4188",
    "sg:postcode":"45402",
    "sg:province":"OH",
    "sg:tags":[
        "parts",
        "electronic",
        "contractor"
    ],
    "sg:website":"www.copp.com",
    "wof:name":"Copp Systems Integrator",
    "wof:placetype":"venue"
},
  "geometry": {"coordinates":[-84.17768100000001,39.759765],"type":"Point"}
}