{
  "type": "Feature",
  "properties": {
    "addr:full": "123 S Keowee St Dayton OH 45402",
    "addr:housenumber": "123",
    "addr:postcode": "45402",
    "addr:street": "S Keowee St",
    "iso:country": "US",
    "sg:address": "123 S Keowee St",
    "sg:city": "Dayton",
    "sg:classifiers": [
      {
        "category": "Wholesale",
        "subcategory": "Electrical",
        "type": "Manufacturing \u0026 Wholesale Goods"
      }
    ],
    "sg:phone": "+1 937 228 4188",
    "sg:postcode": "45402",
    "sg:province": "OH",
    "sg:tags": [
      "parts",
      "electronic",
      "contractor"
    ],
    "sg:website": "www.copp.com",
    "wof:name": "Copp Systems Integrator",
    "wof:placetype": "venue"
  },
  "geometry": {"coordinates":[-84.177681,39.759765],"type":"Point"}
}
