{
  "type": "Feature",
  "properties": {
    "addr:full": "940 N Old State Rd Delaware OH 43015",
    "addr:housenumber": "940",
    "addr:postcode": "43015",
    "addr:street": "N Old State Rd",
    "iso:country": "US",
    "sg:address": "940 N Old State Rd",
    "sg:city": "Delaware",
    "sg:classifiers": [
      {
        "category": "Retail",
        "subcategory": "Repair Shop",
        "type": "Services"
      }
    ],
    "sg:phone": "+1 614 882 6664",
    "sg:postcode": "43015",
    "sg:province": "OH",
    "sg:tags": [
      "appliance"
    ],
    "wof:name": "Davco Service",
    "wof:placetype": "venue"
  },
  "geometry": {"coordinates":[-82.965423,40.287396],"type":"Point"}
}
