{
  "type": "Feature",
  "properties": {
    "iso:country":"US",
    "sg:address":"36 E 4th St",
    "sg:city":"Mansfield",
    "sg:classifiers":[
        {
            "category":"Real Estate",
            "subcategory":"Real Estate Operator",
            "type":"Services"
        },
        {
            "category":"Insurance",
            "subcategory":"Insurance Agent",
            "type":"Services"
        }
    ],
    "sg:phone":"+1 419 756 1013",
    "sg:postcode":"44902",
    "sg:province":"OH",
    "sg:tags":[
        "building",
        "apartment"
    ],
    "wof:name":"D & D Rentals",
    "wof:placetype":"venue"
},
  "geometry": {"coordinates":[-82.51494599999999,40.760924],"type":"Point"}
}