{
  "type": "Feature",
  "properties": {
    "iso:country":"US",
    "sg:address":"905 W Schrock Rd",
    "sg:city":"Columbus",
    "sg:classifiers":[
        {
            "category":"Government",
            "subcategory":"Post Office",
            "type":"Public Place"
        }
    ],
    "sg:phone":"+1 614 000 1111",
    "sg:postcode":"43229",
    "sg:province":"OH",
    "wof:name":"US Post Office",
    "wof:placetype":"venue"
},
  "geometry": {"coordinates":[-82.98641600000001,40.103729],"type":"Point"}
}