{
  "type": "Feature",
  "properties": {
    "addr:full": "905 W Schrock Rd Columbus OH 43229",
    "addr:housenumber": "905",
    "addr:postcode": "43229",
    "addr:street": "W Schrock Rd",
    "iso:country": "US",
    "sg:address": "905 W Schrock Rd",
    "sg:city": "Columbus",
    "sg:classifiers": [
      {
        "category": "Government",
        "subcategory": "Post Office",
        "type": "Public Place"
      }
    ],
    "sg:phone": "+1 614 000 1111",
    "sg:postcode": "43229",
    "sg:province": "OH",
    "wof:name": "US Post Office",
    "wof:placetype": "venue"
  },
  "geometry": {"coordinates":[-82.986416,40.103729],"type":"Point"}
}
