{
  "type": "Feature",
  "properties": {
    "addr:full":"192 S 2nd St Byesville OH 43723",
    "addr:housenumber":"192",
    "addr:postcode":"43723",
    "addr:street":"S 2Nd St",
    "iso:country":"US",
    "sg:address":"192 S 2nd St",
    "sg:city":"Byesville",
    "sg:classifiers":[
        {
            "category":"Shopping",
            "subcategory":"Gifts & Souvenirs",
            "type":"Retail Goods"
        }
    ],
    "sg:phone":"+1 740 685 8653",
    "sg:postcode":"43723",
    "sg:province":"OH",
    "wof:name":"Occasions Grtg Cds & Pty Sups",
    "wof:placetype":"venue"
},
  "geometry": {"coordinates":[-81.53701,39.96852],"type":"Point"}
}