{
  "type": "Feature",
  "properties": {
    "addr:full":"5760 Interstate Blvd Youngstown OH 44515",
    "addr:housenumber":"5760",
    "addr:postcode":"44515",
    "addr:street":"Interstate Blvd",
    "iso:country":"US",
    "sg:address":"5760 Interstate Blvd",
    "sg:city":"Youngstown",
    "sg:classifiers":[
        {
            "category":"Shopping",
            "subcategory":"Clothing, Apparel, & Fashions",
            "type":"Retail Goods"
        }
    ],
    "sg:phone":"+1 330 505 7017",
    "sg:postcode":"44515",
    "sg:province":"OH",
    "sg:tags":[
        "family"
    ],
    "wof:name":"Sears Service Center",
    "wof:placetype":"venue"
},
  "geometry": {"coordinates":[-80.76916799999999,41.12019],"type":"Point"}
}