{
  "type": "Feature",
  "properties": {
    "iso:country":"US",
    "sg:address":"8584 State Rte 725 W",
    "sg:city":"Camden",
    "sg:phone":"+1 513 798 4871",
    "sg:postcode":"45311",
    "sg:province":"OH",
    "sg:tags":[
        "farm"
    ],
    "wof:name":"Self John",
    "wof:placetype":"venue"
},
  "geometry": {"coordinates":[-84.809387,39.626501],"type":"Point"}
}