{
  "type": "Feature",
  "properties": {
    "iso:country":"US",
    "sg:address":"3234 W 90th St",
    "sg:city":"Cleveland",
    "sg:classifiers":[
        {
            "category":"Retail",
            "subcategory":"Laundry & Dry Cleaning",
            "type":"Services"
        }
    ],
    "sg:phone":"+1 216 961 3230",
    "sg:postcode":"44102",
    "sg:province":"OH",
    "sg:tags":[
        "cleaners",
        "rug",
        "carpet"
    ],
    "wof:name":"Cheryl's Carpet Cleaner's",
    "wof:placetype":"venue"
},
  "geometry": {"coordinates":[-81.74584400000001,41.468331],"type":"Point"}
}