{
  "type": "Feature",
  "properties": {
    "iso:country":"US",
    "sg:address":"5311 Northfield Rd",
    "sg:city":"Bedford",
    "sg:classifiers":[
        {
            "category":"Real Estate",
            "subcategory":"Real Estate Agent",
            "type":"Services"
        }
    ],
    "sg:phone":"+1 216 587 3123",
    "sg:postcode":"44146",
    "sg:province":"OH",
    "sg:tags":[
        "appraiser"
    ],
    "wof:name":"Rahmon & Associates Inc",
    "wof:placetype":"venue"
},
  "geometry": {"coordinates":[-81.52729100000001,41.415161],"type":"Point"}
}