{
  "type": "Feature",
  "properties": {
    "addr:full": "1423 Harrisburg Pike Columbus OH 43223",
    "addr:housenumber": "1423",
    "addr:postcode": "43223",
    "addr:street": "Harrisburg Pike",
    "iso:country": "US",
    "sg:address": "1423 Harrisburg Pike",
    "sg:city": "Columbus",
    "sg:classifiers": [
      {
        "category": "Autos \u0026 Motor Vehicles",
        "subcategory": "Automobile Sales",
        "type": "Retail Goods"
      }
    ],
    "sg:phone": "+1 614 272 7200",
    "sg:postcode": "43223",
    "sg:province": "OH",
    "sg:tags": [
      "car",
      "dealer"
    ],
    "wof:name": "Hartley's Used Cars",
    "wof:placetype": "venue"
  },
  "geometry": {"coordinates":[-83.05351,39.92884],"type":"Point"}
}
