{
  "type": "Feature",
  "properties": {
    "addr:full": "2594 Sugar Ridge Ln Dayton OH 45458",
    "addr:housenumber": "2594",
    "addr:postcode": "45458",
    "addr:street": "Sugar Ridge Ln",
    "iso:country": "US",
    "sg:address": "2594 Sugar Ridge Ln",
    "sg:city": "Dayton",
    "sg:classifiers": [
      {
        "category": "Banks \u0026 Credit Unions",
        "subcategory": "Financial Services",
        "type": "Services"
      }
    ],
    "sg:phone": "+1 937 433 5236",
    "sg:postcode": "45458",
    "sg:province": "OH",
    "sg:tags": [
      "trust",
      "management"
    ],
    "wof:name": "Fred E Morehead",
    "wof:placetype": "venue"
  },
  "geometry": {"coordinates":[-84.118922,39.613922],"type":"Point"}
}
