{
  "type": "Feature",
  "properties": {
    "addr:full":"6720 N Ridge Rd Madison OH 44057",
    "addr:housenumber":"6720",
    "addr:postcode":"44057",
    "addr:street":"N Ridge Rd",
    "iso:country":"US",
    "sg:address":"6720 N Ridge Rd",
    "sg:city":"Madison",
    "sg:classifiers":[
        {
            "category":"Autos & Motor Vehicles",
            "subcategory":"Auto Supplies",
            "type":"Retail Goods"
        }
    ],
    "sg:phone":"+1 440 428 5113",
    "sg:postcode":"44057",
    "sg:province":"OH",
    "sg:tags":[
        "home",
        "store"
    ],
    "wof:name":"Carquest Auto Parts",
    "wof:placetype":"venue"
},
  "geometry": {"coordinates":[-81.04719900000001,41.801905],"type":"Point"}
}