{
  "type": "Feature",
  "properties": {
    "iso:country":"US",
    "sg:address":"26300 Cedar Rd",
    "sg:city":"Cleveland",
    "sg:classifiers":[
        {
            "category":"Restaurant",
            "type":"Food & Drink"
        }
    ],
    "sg:phone":"+1 216 378 1551",
    "sg:postcode":"44122",
    "sg:province":"OH",
    "sg:tags":[
        "eating"
    ],
    "wof:name":"Johnny Rockets",
    "wof:placetype":"venue"
},
  "geometry": {"coordinates":[-81.493205,41.501129],"type":"Point"}
}