{
  "type": "Feature",
  "properties": {
    "addr:full": "1117 N Hamilton Rd Gahanna OH 43230",
    "addr:housenumber": "1117",
    "addr:postcode": "43230",
    "addr:street": "N Hamilton Rd",
    "iso:country": "US",
    "sg:address": "1117 N Hamilton Rd",
    "sg:city": "Gahanna",
    "sg:classifiers": [
      {
        "category": "Shopping",
        "subcategory": "Hobbies, Toys, \u0026 Games",
        "type": "Retail Goods"
      }
    ],
    "sg:phone": "+1 614 418 0420",
    "sg:postcode": "43230",
    "sg:province": "OH",
    "sg:tags": [
      "supply"
    ],
    "wof:name": "Level One Gaming Inc",
    "wof:placetype": "venue"
  },
  "geometry": {"coordinates":[-82.868202,39.999749],"type":"Point"}
}
