{
  "type": "Feature",
  "properties": {
    "addr:full": "11169 Louisville St NE Louisville OH 44641",
    "addr:housenumber": "11169",
    "addr:postcode": "44641",
    "addr:street": "Louisville St Ne",
    "iso:country": "US",
    "sg:address": "11169 Louisville St NE",
    "sg:city": "Louisville",
    "sg:classifiers": [
      {
        "category": "Farming",
        "subcategory": "Nursery",
        "type": "Manufacturing \u0026 Wholesale Goods"
      }
    ],
    "sg:phone": "+1 330 875 0603",
    "sg:postcode": "44641",
    "sg:province": "OH",
    "sg:tags": [
      "ornamental"
    ],
    "wof:name": "Brians Greenhouse",
    "wof:placetype": "venue"
  },
  "geometry": {"coordinates":[-81.185188,40.832581],"type":"Point"}
}
