{
  "type": "Feature",
  "properties": {
    "addr:full":"263 N Main St Niles OH 44446",
    "addr:housenumber":"263",
    "addr:postcode":"44446",
    "addr:street":"N Main St",
    "iso:country":"US",
    "sg:address":"263 N Main St",
    "sg:city":"Niles",
    "sg:classifiers":[
        {
            "category":"Restaurant",
            "type":"Food & Drink"
        }
    ],
    "sg:phone":"+1 330 544 1241",
    "sg:postcode":"44446",
    "sg:province":"OH",
    "sg:tags":[
        "beverage"
    ],
    "wof:name":"Ms Kitty's",
    "wof:placetype":"venue"
},
  "geometry": {"coordinates":[-80.765005,41.183623],"type":"Point"}
}