{
  "type": "Feature",
  "properties": {
    "iso:country":"US",
    "sg:address":"2662 Cleveland Rd",
    "sg:city":"Wooster",
    "sg:classifiers":[
        {
            "category":"Real Estate",
            "subcategory":"Real Estate Agent",
            "type":"Services"
        }
    ],
    "sg:phone":"+1 330 262 6070",
    "sg:postcode":"44691",
    "sg:province":"OH",
    "wof:name":"Smucker Team Realty",
    "wof:placetype":"venue"
},
  "geometry": {"coordinates":[-81.930402,40.831701],"type":"Point"}
}