{
  "type": "Feature",
  "properties": {
    "addr:full":"145 E Main St Lancaster OH 43130",
    "addr:housenumber":"145",
    "addr:postcode":"43130",
    "addr:street":"E Main St",
    "iso:country":"US",
    "sg:address":"145 E Main St",
    "sg:city":"Lancaster",
    "sg:classifiers":[
        {
            "category":"Shopping",
            "type":"Retail Goods"
        }
    ],
    "sg:phone":"+1 740 681 1423",
    "sg:postcode":"43130",
    "sg:province":"OH",
    "sg:tags":[
        "art",
        "gallery",
        "dealer"
    ],
    "sg:website":"www.decartsohio.org",
    "wof:name":"Decorative Arts Ctr Of Oh",
    "wof:placetype":"venue"
},
  "geometry": {"coordinates":[-82.6009,39.713773],"type":"Point"}
}