{
  "type": "Feature",
  "properties": {
    "addr:full":"6223 Granite St NW Canton OH 44718",
    "addr:housenumber":"6223",
    "addr:postcode":"44718",
    "addr:street":"Granite St Nw",
    "iso:country":"US",
    "sg:address":"6223 Granite St NW",
    "sg:city":"Canton",
    "sg:classifiers":[
        {
            "category":"Professional",
            "type":"Services"
        }
    ],
    "sg:phone":"+1 330 309 6547",
    "sg:postcode":"44718",
    "sg:province":"OH",
    "wof:name":"Kathleen Sarver",
    "wof:placetype":"venue"
},
  "geometry": {"coordinates":[-81.466016,40.872542],"type":"Point"}
}