{
  "type": "Feature",
  "properties": {
    "iso:country":"US",
    "sg:address":"380 S 5th St",
    "sg:city":"Columbus",
    "sg:classifiers":[
        {
            "category":"Organizations",
            "subcategory":"Non-profit Organization",
            "type":"Services"
        }
    ],
    "sg:phone":"+1 614 228 0157",
    "sg:postcode":"43215",
    "sg:province":"OH",
    "wof:name":"Ohio Sickle Cell & Health",
    "wof:placetype":"venue"
},
  "geometry": {"coordinates":[-82.99267399999999,39.954222],"type":"Point"}
}