{
  "type": "Feature",
  "properties": {
    "addr:full":"108 6th St Philo OH 43771",
    "addr:housenumber":"108",
    "addr:postcode":"43771",
    "addr:street":"6Th St",
    "iso:country":"US",
    "sg:address":"108 6th St",
    "sg:city":"Philo",
    "sg:classifiers":[
        {
            "category":"Government",
            "subcategory":"Office",
            "type":"Public Place"
        }
    ],
    "sg:phone":"+1 740 674 6481",
    "sg:postcode":"43771",
    "sg:province":"OH",
    "sg:tags":[
        "executive"
    ],
    "wof:name":"Harrison Township",
    "wof:placetype":"venue"
},
  "geometry": {"coordinates":[-81.904887,39.857286],"type":"Point"}
}