{
  "type": "Feature",
  "properties": {
    "addr:full":"315 S Chase Ave Columbus OH 43204",
    "addr:housenumber":"315",
    "addr:postcode":"43204",
    "addr:street":"S Chase Ave",
    "iso:country":"US",
    "sg:address":"315 S Chase Ave",
    "sg:city":"Columbus",
    "sg:classifiers":[
        {
            "category":"Freight",
            "type":"Transportation"
        }
    ],
    "sg:phone":"+1 614 279 7026",
    "sg:postcode":"43204",
    "sg:province":"OH",
    "sg:tags":[
        "operator",
        "local",
        "trucking"
    ],
    "wof:name":"Big Wells Trucking Company",
    "wof:placetype":"venue"
},
  "geometry": {"coordinates":[-83.075884,39.946538],"type":"Point"}
}