{
  "type": "Feature",
  "properties": {
    "addr:full":"1714 Boardman Poland Rd Youngstown OH 44514",
    "addr:housenumber":"1714",
    "addr:postcode":"44514",
    "addr:street":"Boardman Poland Rd",
    "iso:country":"US",
    "sg:address":"1714 Boardman Poland Rd",
    "sg:city":"Youngstown",
    "sg:classifiers":[
        {
            "category":"Health Services",
            "subcategory":"Chiropractor",
            "type":"Services"
        }
    ],
    "sg:phone":"+1 330 757 1151",
    "sg:postcode":"44514",
    "sg:province":"OH",
    "wof:name":"Western Reserve Chiropractic",
    "wof:placetype":"venue"
},
  "geometry": {"coordinates":[-80.62651099999999,41.024179],"type":"Point"}
}