{
  "type": "Feature",
  "properties": {
    "addr:full": "6074 Benken Ln Cincinnati OH 45248",
    "addr:postcode": "6074;45248",
    "addr:street": "Benken Ln",
    "iso:country": "US",
    "sg:address": "6074 Benken Ln",
    "sg:city": "Cincinnati",
    "sg:classifiers": [
      {
        "category": "Retail",
        "subcategory": "Laundry \u0026 Dry Cleaning",
        "type": "Services"
      }
    ],
    "sg:phone": "+1 513 574 1643",
    "sg:postcode": "45248",
    "sg:province": "OH",
    "sg:tags": [
      "cleaners",
      "rug",
      "carpet"
    ],
    "wof:name": "Hatfield Carpet Care",
    "wof:placetype": "venue"
  },
  "geometry": {"coordinates":[-84.647939,39.164491],"type":"Point"}
}
