{
  "type": "Feature",
  "properties": {
    "iso:country":"US",
    "sg:address":"6074 Benken Ln",
    "sg:city":"Cincinnati",
    "sg:classifiers":[
        {
            "category":"Retail",
            "subcategory":"Laundry & Dry Cleaning",
            "type":"Services"
        }
    ],
    "sg:phone":"+1 513 574 1643",
    "sg:postcode":"45248",
    "sg:province":"OH",
    "sg:tags":[
        "cleaners",
        "rug",
        "carpet"
    ],
    "wof:name":"Hatfield Carpet Care",
    "wof:placetype":"venue"
},
  "geometry": {"coordinates":[-84.64793899999999,39.164491],"type":"Point"}
}