{
  "type": "Feature",
  "properties": {
    "addr:full":"1225 Oakwood St Fremont OH 43420",
    "addr:housenumber":"1225",
    "addr:postcode":"43420",
    "addr:street":"Oakwood St",
    "iso:country":"US",
    "sg:address":"1225 Oakwood St",
    "sg:city":"Fremont",
    "sg:classifiers":[
        {
            "category":"Wholesale",
            "subcategory":"Machinery & Supplies",
            "type":"Manufacturing & Wholesale Goods"
        },
        {
            "category":"Real Estate",
            "subcategory":"Developer",
            "type":"Services"
        }
    ],
    "sg:phone":"+1 419 332 3671",
    "sg:postcode":"43420",
    "sg:province":"OH",
    "sg:tags":[
        "burial",
        "cemetery",
        "vault"
    ],
    "wof:name":"Oakwood Burial Vault Co",
    "wof:placetype":"venue"
},
  "geometry": {"coordinates":[-83.136994,41.329992],"type":"Point"}
}