{
  "type": "Feature",
  "properties": {
    "addr:full": "41 Wall St Jefferson OH 44047",
    "addr:housenumber": "41",
    "addr:postcode": "44047",
    "addr:street": "Wall St",
    "iso:country": "US",
    "sg:address": "41 Wall St",
    "sg:city": "Jefferson",
    "sg:classifiers": [
      {
        "category": "Insurance",
        "subcategory": "Insurance Agent",
        "type": "Services"
      }
    ],
    "sg:phone": "+1 440 576 2921",
    "sg:postcode": "44047",
    "sg:province": "OH",
    "wof:name": "Glazer Insurance Agency Inc",
    "wof:placetype": "venue"
  },
  "geometry": {"coordinates":[-80.768566,41.739267],"type":"Point"}
}
