{
  "type": "Feature",
  "properties": {
    "iso:country":"US",
    "sg:address":"835 Goodale Blvd",
    "sg:city":"Columbus",
    "sg:classifiers":[
        {
            "category":"Wholesale",
            "subcategory":"Machinery & Supplies",
            "type":"Manufacturing & Wholesale Goods"
        },
        {
            "category":"Manufacturing",
            "subcategory":"Tools & Machinery",
            "type":"Manufacturing & Wholesale Goods"
        }
    ],
    "sg:phone":"+1 614 228 5000",
    "sg:postcode":"43212",
    "sg:province":"OH",
    "sg:tags":[
        "engine",
        "generator",
        "power",
        "transmission",
        "shift",
        "diesel",
        "motor"
    ],
    "sg:website":"www.wwwilliams.com",
    "wof:name":"W W Williams Company",
    "wof:placetype":"venue"
},
  "geometry": {"coordinates":[-83.025003,39.974121],"type":"Point"}
}