{
  "type": "Feature",
  "properties": {
    "addr:full": "835 Goodale Blvd Columbus OH 43212",
    "addr:housenumber": "835",
    "addr:postcode": "43212",
    "addr:street": "Goodale Blvd",
    "iso:country": "US",
    "sg:address": "835 Goodale Blvd",
    "sg:city": "Columbus",
    "sg:classifiers": [
      {
        "category": "Wholesale",
        "subcategory": "Machinery \u0026 Supplies",
        "type": "Manufacturing \u0026 Wholesale Goods"
      },
      {
        "category": "Manufacturing",
        "subcategory": "Tools \u0026 Machinery",
        "type": "Manufacturing \u0026 Wholesale Goods"
      }
    ],
    "sg:phone": "+1 614 228 5000",
    "sg:postcode": "43212",
    "sg:province": "OH",
    "sg:tags": [
      "engine",
      "generator",
      "power",
      "transmission",
      "shift",
      "diesel",
      "motor"
    ],
    "sg:website": "www.wwwilliams.com",
    "wof:name": "W W Williams Company",
    "wof:placetype": "venue"
  },
  "geometry": {"coordinates":[-83.025003,39.974121],"type":"Point"}
}
