{
  "type": "Feature",
  "properties": {
    "addr:full":"18489 Pearl Rd Strongsville OH 44136",
    "addr:housenumber":"18489",
    "addr:postcode":"44136",
    "addr:street":"Pearl Rd",
    "iso:country":"US",
    "sg:address":"18489 Pearl Rd",
    "sg:city":"Strongsville",
    "sg:classifiers":[
        {
            "category":"Shopping",
            "subcategory":"Music",
            "type":"Retail Goods"
        }
    ],
    "sg:phone":"+1 440 846 9293",
    "sg:postcode":"44136",
    "sg:province":"OH",
    "sg:tags":[
        "compact",
        "record",
        "disc",
        "tape"
    ],
    "wof:name":"C Cd Mfg",
    "wof:placetype":"venue"
},
  "geometry": {"coordinates":[-81.83517399999999,41.284572],"type":"Point"}
}