{
  "type": "Feature",
  "properties": {
    "addr:full": "1395 Collier Rd Akron OH 44320",
    "addr:housenumber": "1395",
    "addr:postcode": "44320",
    "addr:street": "Collier Rd",
    "iso:country": "US",
    "sg:address": "1395 Collier Rd",
    "sg:city": "Akron",
    "sg:classifiers": [
      {
        "category": "Farming",
        "subcategory": "Nursery",
        "type": "Manufacturing \u0026 Wholesale Goods"
      }
    ],
    "sg:phone": "+1 330 836 4963",
    "sg:postcode": "44320",
    "sg:province": "OH",
    "sg:tags": [
      "greenhouse"
    ],
    "wof:name": "Kraus Greenhouses Inc",
    "wof:placetype": "venue"
  },
  "geometry": {"coordinates":[-81.58837,41.079405],"type":"Point"}
}
