{
  "type": "Feature",
  "properties": {
    "iso:country":"US",
    "sg:address":"19215 Hilliard Blvd",
    "sg:city":"Rocky River",
    "sg:classifiers":[
        {
            "category":"Restaurant",
            "type":"Food & Drink"
        }
    ],
    "sg:phone":"+1 440 333 7890",
    "sg:postcode":"44116",
    "sg:province":"OH",
    "sg:tags":[
        "eating"
    ],
    "wof:name":"Joes Deli",
    "wof:placetype":"venue"
},
  "geometry": {"coordinates":[-81.829796,41.471403],"type":"Point"}
}