{
  "type": "Feature",
  "properties": {
    "iso:country":"US",
    "sg:address":"5830 Lee Rd S",
    "sg:city":"Maple Heights",
    "sg:classifiers":[
        {
            "category":"Shopping",
            "subcategory":"Discount & Variety Stores",
            "type":"Retail Goods"
        }
    ],
    "sg:phone":"+1 216 662 4689",
    "sg:postcode":"44137",
    "sg:province":"OH",
    "wof:name":"Univrsl Whole Sale Variety",
    "wof:placetype":"venue"
},
  "geometry": {"coordinates":[-81.56574,41.400344],"type":"Point"}
}