{
  "type": "Feature",
  "properties": {
    "addr:full": "5830 Lee Rd S Maple Heights OH 44137",
    "addr:housenumber": "5830",
    "addr:postcode": "44137",
    "addr:street": "Lee Rd S",
    "iso:country": "US",
    "sg:address": "5830 Lee Rd S",
    "sg:city": "Maple Heights",
    "sg:classifiers": [
      {
        "category": "Shopping",
        "subcategory": "Discount \u0026 Variety Stores",
        "type": "Retail Goods"
      }
    ],
    "sg:phone": "+1 216 662 4689",
    "sg:postcode": "44137",
    "sg:province": "OH",
    "wof:name": "Univrsl Whole Sale Variety",
    "wof:placetype": "venue"
  },
  "geometry": {"coordinates":[-81.56574,41.400344],"type":"Point"}
}
