{
  "type": "Feature",
  "properties": {
    "addr:full": "9400 State Rte 161 E Plain City OH 43064",
    "addr:housenumber": "9400",
    "addr:postcode": "43064",
    "addr:street": "State Rte 161 E",
    "iso:country": "US",
    "sg:address": "9400 State Rte 161 E",
    "sg:city": "Plain City",
    "sg:phone": "+1 614 873 5037",
    "sg:postcode": "43064",
    "sg:province": "OH",
    "sg:tags": [
      "farm",
      "wheat",
      "soybean"
    ],
    "wof:name": "Yoder Trust",
    "wof:placetype": "venue"
  },
  "geometry": {"coordinates":[-83.219188,40.101613],"type":"Point"}
}
