{
  "type": "Feature",
  "properties": {
    "addr:full": "7334 W Chester Rd West Chester OH 45069",
    "addr:housenumber": "7334",
    "addr:postcode": "45069",
    "addr:street": "W Chester Rd",
    "iso:country": "US",
    "sg:address": "7334 W Chester Rd",
    "sg:city": "West Chester",
    "sg:classifiers": [
      {
        "category": "Real Estate",
        "subcategory": "Real Estate Agent",
        "type": "Services"
      }
    ],
    "sg:phone": "+1 513 759 1600",
    "sg:postcode": "45069",
    "sg:province": "OH",
    "sg:tags": [
      "relocation"
    ],
    "wof:name": "Equity Corporate Housing",
    "wof:placetype": "venue"
  },
  "geometry": {"coordinates":[-84.385857,39.321463],"type":"Point"}
}
