{
  "type": "Feature",
  "properties": {
    "addr:full":"4242 Airport Rd Ste 302 Cincinnati OH 45226",
    "addr:housenumber":"4242",
    "addr:postcode":"45226",
    "addr:street":"Airport Rd Ste 302",
    "iso:country":"US",
    "sg:address":"4242 Airport Rd Ste 302",
    "sg:city":"Cincinnati",
    "sg:classifiers":[
        {
            "category":"Professional",
            "subcategory":"Business Services",
            "type":"Services"
        },
        {
            "category":"Government",
            "subcategory":"Post Office",
            "type":"Public Place"
        }
    ],
    "sg:phone":"+1 513 533 0120",
    "sg:postcode":"45226",
    "sg:province":"OH",
    "sg:tags":[
        "delivery",
        "messenger",
        "courier"
    ],
    "wof:name":"The M Courier Company",
    "wof:placetype":"venue"
},
  "geometry": {"coordinates":[-84.43027499999999,39.10559],"type":"Point"}
}