{
  "type": "Feature",
  "properties": {
    "addr:full":"1111 S Smithville Rd Dayton OH 45403",
    "addr:housenumber":"1111",
    "addr:postcode":"45403",
    "addr:street":"S Smithville Rd",
    "iso:country":"US",
    "sg:address":"1111 S Smithville Rd",
    "sg:city":"Dayton",
    "sg:classifiers":[
        {
            "category":"Restaurant",
            "type":"Food & Drink"
        }
    ],
    "sg:menulink":"http://www.allmenus.com/oh/dayton/162882-rallys/menu/",
    "sg:phone":"+1 937 256 4293",
    "sg:postcode":"45403",
    "sg:province":"OH",
    "sg:tags":[
        "sandwich",
        "dog",
        "burger",
        "hot",
        "wrap",
        "american"
    ],
    "wof:name":"Rally's",
    "wof:placetype":"venue"
},
  "geometry": {"coordinates":[-84.139285,39.752276],"type":"Point"}
}