{
  "type": "Feature",
  "properties": {
    "addr:full": "147 S Springfield St St Paris OH 43072",
    "addr:housenumber": "147",
    "addr:postcode": "43072",
    "addr:street": "S Springfield St St",
    "iso:country": "US",
    "sg:address": "147 S Springfield St",
    "sg:city": "St Paris",
    "sg:classifiers": [
      {
        "category": "Home \u0026 Garden",
        "subcategory": "Carpets \u0026 Floor Coverings",
        "type": "Retail Goods"
      }
    ],
    "sg:phone": "+1 937 663 5288",
    "sg:postcode": "43072",
    "sg:province": "OH",
    "sg:tags": [
      "dealer",
      "rug"
    ],
    "wof:name": "Thornton's Carpet\u0026 Interiors",
    "wof:placetype": "venue"
  },
  "geometry": {"coordinates":[-83.959178,40.127919],"type":"Point"}
}
