{
  "type": "Feature",
  "properties": {
    "iso:country":"US",
    "sg:address":"147 S Springfield St",
    "sg:city":"St Paris",
    "sg:classifiers":[
        {
            "category":"Home & Garden",
            "subcategory":"Carpets & Floor Coverings",
            "type":"Retail Goods"
        }
    ],
    "sg:phone":"+1 937 663 5288",
    "sg:postcode":"43072",
    "sg:province":"OH",
    "sg:tags":[
        "dealer",
        "rug"
    ],
    "wof:name":"Thornton's Carpet& Interiors",
    "wof:placetype":"venue"
},
  "geometry": {"coordinates":[-83.95917799999999,40.127919],"type":"Point"}
}