{
  "type": "Feature",
  "properties": {
    "iso:country":"US",
    "sg:address":"16882 Town Hwy 126",
    "sg:city":"Caldwell",
    "sg:classifiers":[
        {
            "category":"Wholesale",
            "subcategory":"Farm Supplies",
            "type":"Manufacturing & Wholesale Goods"
        },
        {
            "category":"Government",
            "subcategory":"Office",
            "type":"Public Place"
        }
    ],
    "sg:phone":"+1 740 732 4275",
    "sg:postcode":"43724",
    "sg:province":"OH",
    "sg:tags":[
        "livestock"
    ],
    "wof:name":"Eastern Ohio Resource Dev Ctr",
    "wof:placetype":"venue"
},
  "geometry": {"coordinates":[-81.525084,39.792747],"type":"Point"}
}