{
  "type": "Feature",
  "properties": {
    "addr:full":"2337 S Union Ave Alliance OH 44601",
    "addr:housenumber":"2337",
    "addr:postcode":"44601",
    "addr:street":"S Union Ave",
    "iso:country":"US",
    "sg:address":"2337 S Union Ave",
    "sg:city":"Alliance",
    "sg:classifiers":[
        {
            "category":"Shopping",
            "subcategory":"Computers & Home Electronics",
            "type":"Retail Goods"
        }
    ],
    "sg:phone":"+1 330 823 2738",
    "sg:postcode":"44601",
    "sg:province":"OH",
    "sg:tags":[
        "audio"
    ],
    "wof:name":"Horizon Audio",
    "wof:placetype":"venue"
},
  "geometry": {"coordinates":[-81.105912,40.898713],"type":"Point"}
}