{
  "type": "Feature",
  "properties": {
    "addr:full":"500 Providence St Delta OH 43515",
    "addr:housenumber":"500",
    "addr:postcode":"43515",
    "addr:street":"Providence St",
    "iso:country":"US",
    "sg:address":"500 Providence St",
    "sg:city":"Delta",
    "sg:classifiers":[
        {
            "category":"Organizations",
            "subcategory":"Religious Organization",
            "type":"Services"
        }
    ],
    "sg:phone":"+1 419 822 3248",
    "sg:postcode":"43515",
    "sg:province":"OH",
    "sg:tags":[
        "church"
    ],
    "sg:website":"www.deltachurchofchrist.com",
    "wof:name":"Delta Church Of Christ",
    "wof:placetype":"venue"
},
  "geometry": {"coordinates":[-84.003591,41.572136],"type":"Point"}
}