{
  "type": "Feature",
  "properties": {
    "iso:country":"US",
    "sg:address":"2043 Brown Hill Rd",
    "sg:city":"Manchester",
    "sg:classifiers":[
        {
            "category":"Farming",
            "subcategory":"Farm",
            "type":"Manufacturing & Wholesale Goods"
        }
    ],
    "sg:phone":"+1 937 549 2250",
    "sg:postcode":"45144",
    "sg:province":"OH",
    "sg:tags":[
        "crop",
        "general"
    ],
    "wof:name":"Donald Stricklett",
    "wof:placetype":"venue"
},
  "geometry": {"coordinates":[-83.627102,38.715691],"type":"Point"}
}