{
  "type": "Feature",
  "properties": {
    "iso:country":"US",
    "sg:address":"2939 McClintocksburg Rd",
    "sg:city":"Diamond",
    "sg:classifiers":[
        {
            "category":"Freight",
            "type":"Transportation"
        }
    ],
    "sg:phone":"+1 330 654 9770",
    "sg:postcode":"44412",
    "sg:province":"OH",
    "sg:tags":[
        "operator",
        "local",
        "trucking"
    ],
    "wof:name":"Big Buck Trucking LLC",
    "wof:placetype":"venue"
},
  "geometry": {"coordinates":[-81.03193899999999,41.06987],"type":"Point"}
}