{
  "type": "Feature",
  "properties": {
    "addr:full":"410 S Wheeling St Oregon OH 43616",
    "addr:housenumber":"410",
    "addr:postcode":"43616",
    "addr:street":"S Wheeling St",
    "iso:country":"US",
    "sg:address":"410 S Wheeling St",
    "sg:city":"Oregon",
    "sg:classifiers":[
        {
            "category":"Shopping",
            "subcategory":"Pharmacy",
            "type":"Retail Goods"
        }
    ],
    "sg:phone":"+1 419 691 4412",
    "sg:postcode":"43616",
    "sg:province":"OH",
    "wof:name":"Pharm Deep Discount Drug Strs",
    "wof:placetype":"venue"
},
  "geometry": {"coordinates":[-83.486932,41.642915],"type":"Point"}
}