{
  "type": "Feature",
  "properties": {
    "addr:full": "2655 Patterson Rd Dayton OH 45420",
    "addr:housenumber": "2655",
    "addr:postcode": "45420",
    "addr:street": "Patterson Rd",
    "iso:country": "US",
    "sg:address": "2655 Patterson Rd",
    "sg:city": "Dayton",
    "sg:classifiers": [
      {
        "category": "Retail",
        "subcategory": "Auto Repair",
        "type": "Services"
      }
    ],
    "sg:phone": "+1 937 254 3184",
    "sg:postcode": "45420",
    "sg:province": "OH",
    "sg:tags": [
      "body",
      "general"
    ],
    "wof:name": "Tabers Collision Center Inc",
    "wof:placetype": "venue"
  },
  "geometry": {"coordinates":[-84.124237,39.72273],"type":"Point"}
}
