{
  "type": "Feature",
  "properties": {
    "iso:country":"US",
    "sg:address":"2655 Patterson Rd",
    "sg:city":"Dayton",
    "sg:classifiers":[
        {
            "category":"Retail",
            "subcategory":"Auto Repair",
            "type":"Services"
        }
    ],
    "sg:phone":"+1 937 254 3184",
    "sg:postcode":"45420",
    "sg:province":"OH",
    "sg:tags":[
        "body",
        "general"
    ],
    "wof:name":"Tabers Collision Center Inc",
    "wof:placetype":"venue"
},
  "geometry": {"coordinates":[-84.12423699999999,39.72273],"type":"Point"}
}