{
  "type": "Feature",
  "properties": {
    "addr:full": "727 Gregg St Washington Ct Hs OH 43160",
    "addr:housenumber": "727",
    "addr:postcode": "43160",
    "addr:street": "Gregg St",
    "iso:country": "US",
    "sg:address": "727 Gregg St",
    "sg:city": "Washington Ct Hs",
    "sg:classifiers": [
      {
        "category": "Utilities",
        "subcategory": "Refuse",
        "type": "Services"
      }
    ],
    "sg:phone": "+1 740 335 5213",
    "sg:postcode": "43160",
    "sg:province": "OH",
    "sg:tags": [
      "garbage",
      "collection"
    ],
    "wof:name": "Jones Hauling \u0026 Cleanup",
    "wof:placetype": "venue"
  },
  "geometry": {"coordinates":[-83.436127,39.54592],"type":"Point"}
}
