{
  "type": "Feature",
  "properties": {
    "iso:country":"US",
    "sg:address":"900 N Blackhoof St",
    "sg:city":"Wapakoneta",
    "sg:classifiers":[
        {
            "category":"Education",
            "subcategory":"School",
            "type":"Public Place"
        }
    ],
    "sg:phone":"+1 419 739 5055",
    "sg:postcode":"45895",
    "sg:province":"OH",
    "sg:website":"www.noacsc.org",
    "wof:name":"Northridge Elementary Schl Inc",
    "wof:placetype":"venue"
},
  "geometry": {"coordinates":[-84.19624899999999,40.580788],"type":"Point"}
}