{
  "type": "Feature",
  "properties": {
    "addr:full": "745 N Pierce Ave Lancaster OH 43130",
    "addr:housenumber": "745",
    "addr:postcode": "43130",
    "addr:street": "N Pierce Ave",
    "iso:country": "US",
    "sg:address": "745 N Pierce Ave",
    "sg:city": "Lancaster",
    "sg:classifiers": [
      {
        "category": "Restaurant",
        "type": "Food \u0026 Drink"
      }
    ],
    "sg:phone": "+1 740 653 1765",
    "sg:postcode": "43130",
    "sg:province": "OH",
    "sg:tags": [
      "eating"
    ],
    "wof:name": "Ten Buck Pizza",
    "wof:placetype": "venue"
  },
  "geometry": {"coordinates":[-82.618473,39.722533],"type":"Point"}
}
