{
  "type": "Feature",
  "properties": {
    "iso:country":"US",
    "sg:address":"745 N Pierce Ave",
    "sg:city":"Lancaster",
    "sg:classifiers":[
        {
            "category":"Restaurant",
            "type":"Food & Drink"
        }
    ],
    "sg:phone":"+1 740 653 1765",
    "sg:postcode":"43130",
    "sg:province":"OH",
    "sg:tags":[
        "eating"
    ],
    "wof:name":"Ten Buck Pizza",
    "wof:placetype":"venue"
},
  "geometry": {"coordinates":[-82.61847299999999,39.722533],"type":"Point"}
}