{
  "type": "Feature",
  "properties": {
    "addr:full":"29050 Detroit Rd Cleveland OH 44145",
    "addr:housenumber":"29050",
    "addr:postcode":"44145",
    "addr:street":"Detroit Rd",
    "iso:country":"US",
    "sg:address":"29050 Detroit Rd",
    "sg:city":"Cleveland",
    "sg:classifiers":[
        {
            "category":"Real Estate",
            "subcategory":"Real Estate Operator",
            "type":"Services"
        }
    ],
    "sg:phone":"+1 440 899 1175",
    "sg:postcode":"44145",
    "sg:province":"OH",
    "sg:tags":[
        "apartment"
    ],
    "wof:name":"Westfield Apartments",
    "wof:placetype":"venue"
},
  "geometry": {"coordinates":[-81.942277,41.464938],"type":"Point"}
}