{
  "type": "Feature",
  "properties": {
    "addr:full": "8969 Fields Ertel Rd Cincinnati OH 45249",
    "addr:housenumber": "8969",
    "addr:postcode": "45249",
    "addr:street": "Fields Ertel Rd",
    "iso:country": "US",
    "sg:address": "8969 Fields Ertel Rd",
    "sg:city": "Cincinnati",
    "sg:classifiers": [
      {
        "category": "Restaurant",
        "type": "Food \u0026 Drink"
      }
    ],
    "sg:menulink": "http://www.allmenus.com/oh/symmes/195497-mcdonalds/menu/",
    "sg:postcode": "45249",
    "sg:province": "OH",
    "sg:tags": [
      "burger",
      "american"
    ],
    "wof:name": "McDonald's",
    "wof:placetype": "venue"
  },
  "geometry": {"coordinates":[-84.31342,39.29211],"type":"Point"}
}
