{
  "type": "Feature",
  "properties": {
    "addr:full":"6 E 4th St Cincinnati OH 45202",
    "addr:housenumber":"6",
    "addr:postcode":"45202",
    "addr:street":"E 4Th St",
    "iso:country":"US",
    "sg:address":"6 E 4th St",
    "sg:city":"Cincinnati",
    "sg:classifiers":[
        {
            "category":"Manufacturing",
            "subcategory":"Printing",
            "type":"Manufacturing & Wholesale Goods"
        }
    ],
    "sg:phone":"+1 513 241 1513",
    "sg:postcode":"45202",
    "sg:province":"OH",
    "sg:tags":[
        "periodical"
    ],
    "wof:name":"Ohio Business Magazine",
    "wof:placetype":"venue"
},
  "geometry": {"coordinates":[-84.512052,39.100115],"type":"Point"}
}