{
  "type": "Feature",
  "properties": {
    "iso:country":"US",
    "sg:address":"505 N High St",
    "sg:city":"Pandora",
    "sg:classifiers":[
        {
            "category":"Organizations",
            "subcategory":"Religious Organization",
            "type":"Services"
        }
    ],
    "sg:phone":"+1 419 384 3289",
    "sg:postcode":"45877",
    "sg:province":"OH",
    "wof:name":"Saint John Menonite Church",
    "wof:placetype":"venue"
},
  "geometry": {"coordinates":[-83.960212,40.954358],"type":"Point"}
}