{
  "type": "Feature",
  "properties": {
    "iso:country":"US",
    "sg:address":"1407 Cranover Rd",
    "sg:city":"Cleveland",
    "sg:classifiers":[
        {
            "category":"Shopping",
            "subcategory":"Bicycles & Sporting Goods",
            "type":"Retail Goods"
        }
    ],
    "sg:phone":"+1 216 382 4510",
    "sg:postcode":"44124",
    "sg:province":"OH",
    "wof:name":"J & N Sporting Goods",
    "wof:placetype":"venue"
},
  "geometry": {"coordinates":[-81.50167500000001,41.521746],"type":"Point"}
}