{
  "type": "Feature",
  "properties": {
    "addr:full":"69 Granville St Newark OH 43055",
    "addr:housenumber":"69",
    "addr:postcode":"43055",
    "addr:street":"Granville St",
    "iso:country":"US",
    "sg:address":"69 Granville St",
    "sg:city":"Newark",
    "sg:classifiers":[
        {
            "category":"Professional",
            "type":"Services"
        }
    ],
    "sg:phone":"+1 740 349 7685",
    "sg:postcode":"43055",
    "sg:province":"OH",
    "sg:tags":[
        "establishment"
    ],
    "wof:name":"AAAA",
    "wof:placetype":"venue"
},
  "geometry": {"coordinates":[-82.409688,40.060174],"type":"Point"}
}