{
  "type": "Feature",
  "properties": {
    "iso:country":"US",
    "sg:address":"3550 Secor Rd",
    "sg:city":"Toledo",
    "sg:classifiers":[
        {
            "category":"Insurance",
            "subcategory":"Insurance Agent",
            "type":"Services"
        }
    ],
    "sg:phone":"+1 419 536 1139",
    "sg:postcode":"43606",
    "sg:province":"OH",
    "wof:name":"AFLAC",
    "wof:placetype":"venue"
},
  "geometry": {"coordinates":[-83.622963,41.685092],"type":"Point"}
}