{
  "type": "Feature",
  "properties": {
    "addr:full":"5436 Summit Rd Cleveland OH 44124",
    "addr:housenumber":"5436",
    "addr:postcode":"44124",
    "addr:street":"Summit Rd",
    "iso:country":"US",
    "sg:address":"5436 Summit Rd",
    "sg:city":"Cleveland",
    "sg:classifiers":[
        {
            "category":"Building & Trades",
            "subcategory":"Construction",
            "type":"Services"
        }
    ],
    "sg:phone":"+1 440 461 9607",
    "sg:postcode":"44124",
    "sg:province":"OH",
    "sg:tags":[
        "excavation",
        "concrete",
        "line",
        "sewer",
        "contracting"
    ],
    "wof:name":"G M P Concrete and Excvtg",
    "wof:placetype":"venue"
},
  "geometry": {"coordinates":[-81.484962,41.51385],"type":"Point"}
}