{
  "type": "Feature",
  "properties": {
    "addr:full":"1300 E Ash St Piqua OH 45356",
    "addr:housenumber":"1300",
    "addr:postcode":"45356",
    "addr:street":"E Ash St",
    "iso:country":"US",
    "sg:address":"1300 E Ash St",
    "sg:city":"Piqua",
    "sg:classifiers":[
        {
            "category":"Banks & Credit Unions",
            "subcategory":"Bank",
            "type":"Services"
        }
    ],
    "sg:phone":"+1 937 773 9000",
    "sg:postcode":"45356",
    "sg:province":"OH",
    "wof:name":"Unity National Bank",
    "wof:placetype":"venue"
},
  "geometry": {"coordinates":[-84.20732700000001,40.150509],"type":"Point"}
}