{
  "type": "Feature",
  "properties": {
    "iso:country":"US",
    "sg:address":"1350 Euclid Ave",
    "sg:city":"Cleveland",
    "sg:classifiers":[
        {
            "category":"Government",
            "subcategory":"Office",
            "type":"Public Place"
        }
    ],
    "sg:phone":"+1 216 522 4058",
    "sg:postcode":"44115",
    "sg:province":"OH",
    "sg:tags":[
        "federal",
        "program"
    ],
    "sg:website":"www.hud.gov",
    "wof:name":"US Housing & Urban Dev Dept",
    "wof:placetype":"venue"
},
  "geometry": {"coordinates":[-81.682228,41.500756],"type":"Point"}
}