{
  "type": "Feature",
  "properties": {
    "addr:full": "24775 Meadow Ln Cleveland OH 44145",
    "addr:housenumber": "24775",
    "addr:postcode": "44145",
    "addr:street": "Meadow Ln",
    "iso:country": "US",
    "sg:address": "24775 Meadow Ln",
    "sg:city": "Cleveland",
    "sg:classifiers": [
      {
        "category": "Professional",
        "subcategory": "Accounting \u0026 Tax Preparation",
        "type": "Services"
      }
    ],
    "sg:phone": "+1 440 779 6801",
    "sg:postcode": "44145",
    "sg:province": "OH",
    "sg:tags": [
      "consultant"
    ],
    "wof:name": "Diversified Strategies",
    "wof:placetype": "venue"
  },
  "geometry": {"coordinates":[-81.898123,41.443588],"type":"Point"}
}
