{
  "type": "Feature",
  "properties": {
    "iso:country":"US",
    "sg:address":"2001 11th St",
    "sg:city":"Portsmouth",
    "sg:classifiers":[
        {
            "category":"Autos & Motor Vehicles",
            "subcategory":"Automobile Sales",
            "type":"Retail Goods"
        }
    ],
    "sg:phone":"+1 740 354 4884",
    "sg:postcode":"45662",
    "sg:province":"OH",
    "sg:tags":[
        "used"
    ],
    "wof:name":"Carroll Auto Inc",
    "wof:placetype":"venue"
},
  "geometry": {"coordinates":[-82.975619,38.738693],"type":"Point"}
}