{
  "type": "Feature",
  "properties": {
    "addr:full": "800 Linden Ave Zanesville OH 43701",
    "addr:housenumber": "800",
    "addr:postcode": "43701",
    "addr:street": "Linden Ave",
    "iso:country": "US",
    "sg:address": "800 Linden Ave",
    "sg:city": "Zanesville",
    "sg:classifiers": [
      {
        "category": "Home \u0026 Garden",
        "subcategory": "Building Materials",
        "type": "Retail Goods"
      }
    ],
    "sg:phone": "+1 740 455 6434",
    "sg:postcode": "43701",
    "sg:province": "OH",
    "wof:name": "Buckeye Insulation \u0026 Gypsum",
    "wof:placetype": "venue"
  },
  "geometry": {"coordinates":[-82.009568,39.948318],"type":"Point"}
}
