{
  "type": "Feature",
  "properties": {
    "addr:full": "8434 Washington St Chagrin Falls OH 44023",
    "addr:housenumber": "8434",
    "addr:postcode": "44023",
    "addr:street": "Washington St",
    "iso:country": "US",
    "sg:address": "8434 Washington St",
    "sg:city": "Chagrin Falls",
    "sg:classifiers": [
      {
        "category": "Wholesale",
        "subcategory": "Stationery",
        "type": "Manufacturing \u0026 Wholesale Goods"
      }
    ],
    "sg:phone": "+1 440 543 1040",
    "sg:postcode": "44023",
    "sg:province": "OH",
    "sg:tags": [
      "card"
    ],
    "wof:name": "Cinnamon Bear",
    "wof:placetype": "venue"
  },
  "geometry": {"coordinates":[-81.339516,41.412397],"type":"Point"}
}
