{
  "type": "Feature",
  "properties": {
    "addr:full": "804 Central Ave Findlay OH 45840",
    "addr:housenumber": "804",
    "addr:postcode": "45840",
    "addr:street": "Central Ave",
    "iso:country": "US",
    "sg:address": "804 Central Ave",
    "sg:city": "Findlay",
    "sg:classifiers": [
      {
        "category": "Professional",
        "subcategory": "Management \u0026 Consulting",
        "type": "Services"
      }
    ],
    "sg:phone": "+1 419 422 6218",
    "sg:postcode": "45840",
    "sg:province": "OH",
    "sg:tags": [
      "business"
    ],
    "wof:name": "S Ingram \u0026 Associates Inc",
    "wof:placetype": "venue"
  },
  "geometry": {"coordinates":[-83.636166,41.050467],"type":"Point"}
}
