{
  "type": "Feature",
  "properties": {
    "addr:full":"6760 State Rte 134 Lynchburg OH 45142",
    "addr:housenumber":"6760",
    "addr:postcode":"45142",
    "addr:street":"State Rte 134",
    "iso:country":"US",
    "sg:address":"6760 State Rte 134",
    "sg:city":"Lynchburg",
    "sg:classifiers":[
        {
            "category":"Education",
            "subcategory":"School",
            "type":"Public Place"
        }
    ],
    "sg:phone":"+1 937 364 9119",
    "sg:postcode":"45142",
    "sg:province":"OH",
    "sg:website":"www.lynchclay.k12.oh.us",
    "wof:name":"Lynchburg-Clay Elementary Schl",
    "wof:placetype":"venue"
},
  "geometry": {"coordinates":[-83.817109,39.190225],"type":"Point"}
}