{
  "type": "Feature",
  "properties": {
    "iso:country":"US",
    "sg:address":"8035 Hosbrook Rd",
    "sg:city":"Cincinnati",
    "sg:classifiers":[
        {
            "category":"Insurance",
            "subcategory":"Insurance Agent",
            "type":"Services"
        }
    ],
    "sg:phone":"+1 513 891 4400",
    "sg:postcode":"45236",
    "sg:province":"OH",
    "sg:website":"www.dempsey-siders.com",
    "wof:name":"Dempsey & Siders Inc",
    "wof:placetype":"venue"
},
  "geometry": {"coordinates":[-84.371037,39.203739],"type":"Point"}
}