{
  "type": "Feature",
  "properties": {
    "addr:full":"1063 Bradley Rd Cleveland OH 44145",
    "addr:housenumber":"1063",
    "addr:postcode":"44145",
    "addr:street":"Bradley Rd",
    "iso:country":"US",
    "sg:address":"1063 Bradley Rd",
    "sg:city":"Cleveland",
    "sg:classifiers":[
        {
            "category":"Wholesale",
            "subcategory":"Vending Machines",
            "type":"Manufacturing & Wholesale Goods"
        }
    ],
    "sg:phone":"+1 440 808 8553",
    "sg:postcode":"44145",
    "sg:province":"OH",
    "wof:name":"Charisma Vending LTD LLC",
    "wof:placetype":"venue"
},
  "geometry": {"coordinates":[-81.960302,41.470855],"type":"Point"}
}