{
  "type": "Feature",
  "properties": {
    "iso:country":"US",
    "sg:address":"1553 State Rte 303",
    "sg:city":"Streetsboro",
    "sg:classifiers":[
        {
            "category":"Personal",
            "subcategory":"Beauty Salon",
            "type":"Services"
        }
    ],
    "sg:phone":"+1 330 626 3112",
    "sg:postcode":"44241",
    "sg:province":"OH",
    "sg:tags":[
        "shop"
    ],
    "wof:name":"Fashion Trend Hairdressers",
    "wof:placetype":"venue"
},
  "geometry": {"coordinates":[-81.338573,41.23928],"type":"Point"}
}