{
  "type": "Feature",
  "properties": {
    "iso:country":"US",
    "sg:address":"7611 US Hwy 23",
    "sg:city":"Lucasville",
    "sg:classifiers":[
        {
            "category":"Government",
            "subcategory":"Police Station",
            "type":"Public Place"
        }
    ],
    "sg:phone":"+1 740 354 2888",
    "sg:postcode":"45648",
    "sg:province":"OH",
    "sg:tags":[
        "state",
        "patrol",
        "highway"
    ],
    "wof:name":"Portsmouth Patrol Post",
    "wof:placetype":"venue"
},
  "geometry": {"coordinates":[-82.984443,38.838789],"type":"Point"}
}