{
  "type": "Feature",
  "properties": {
    "addr:full": "154 Lincoln Pike Gallipolis OH 45631",
    "addr:housenumber": "154",
    "addr:postcode": "45631",
    "addr:street": "Lincoln Pike",
    "iso:country": "US",
    "sg:address": "154 Lincoln Pike",
    "sg:city": "Gallipolis",
    "sg:classifiers": [
      {
        "category": "Wholesale",
        "subcategory": "Auto Parts",
        "type": "Manufacturing \u0026 Wholesale Goods"
      }
    ],
    "sg:phone": "+1 740 446 0800",
    "sg:postcode": "45631",
    "sg:province": "OH",
    "sg:tags": [
      "truck",
      "accessory"
    ],
    "wof:name": "Scufy's Rv \u0026 Supply Inc",
    "wof:placetype": "venue"
  },
  "geometry": {"coordinates":[-82.275885,38.793358],"type":"Point"}
}
