{
  "type": "Feature",
  "properties": {
    "iso:country":"US",
    "sg:address":"370 Hyatts Rd",
    "sg:city":"Delaware",
    "sg:classifiers":[
        {
            "category":"Recreation",
            "type":"Entertainment"
        }
    ],
    "sg:phone":"+1 740 548 6188",
    "sg:postcode":"43015",
    "sg:province":"OH",
    "sg:tags":[
        "boarding",
        "horse",
        "lesson"
    ],
    "wof:name":"Horse Center LTD",
    "wof:placetype":"venue"
},
  "geometry": {"coordinates":[-83.03913799999999,40.214217],"type":"Point"}
}