{
  "type": "Feature",
  "properties": {
    "iso:country":"US",
    "sg:address":"4020 Mahoning Rd NE",
    "sg:city":"Canton",
    "sg:classifiers":[
        {
            "category":"Farming",
            "subcategory":"Dairy Farm",
            "type":"Manufacturing & Wholesale Goods"
        }
    ],
    "sg:phone":"+1 330 478 2697",
    "sg:postcode":"44705",
    "sg:province":"OH",
    "wof:name":"Robert Bebout",
    "wof:placetype":"venue"
},
  "geometry": {"coordinates":[-81.31781100000001,40.822661],"type":"Point"}
}