{
  "type": "Feature",
  "properties": {
    "addr:full": "4020 Mahoning Rd NE Canton OH 44705",
    "addr:housenumber": "4020",
    "addr:postcode": "44705",
    "addr:street": "Mahoning Rd Ne",
    "iso:country": "US",
    "sg:address": "4020 Mahoning Rd NE",
    "sg:city": "Canton",
    "sg:classifiers": [
      {
        "category": "Farming",
        "subcategory": "Dairy Farm",
        "type": "Manufacturing \u0026 Wholesale Goods"
      }
    ],
    "sg:phone": "+1 330 478 2697",
    "sg:postcode": "44705",
    "sg:province": "OH",
    "wof:name": "Robert Bebout",
    "wof:placetype": "venue"
  },
  "geometry": {"coordinates":[-81.317811,40.822661],"type":"Point"}
}
