{
  "type": "Feature",
  "properties": {
    "addr:full":"4636 Gateway Cir Dayton OH 45440",
    "addr:housenumber":"4636",
    "addr:postcode":"45440",
    "addr:street":"Gateway Cir",
    "iso:country":"US",
    "sg:address":"4636 Gateway Cir",
    "sg:city":"Dayton",
    "sg:classifiers":[
        {
            "category":"Retail",
            "subcategory":"Repair Shop",
            "type":"Services"
        }
    ],
    "sg:phone":"+1 937 293 3487",
    "sg:postcode":"45440",
    "sg:province":"OH",
    "sg:tags":[
        "upholsterer"
    ],
    "wof:name":"Battigaglia's Upholstering",
    "wof:placetype":"venue"
},
  "geometry": {"coordinates":[-84.134353,39.679877],"type":"Point"}
}