{
  "type": "Feature",
  "properties": {
    "addr:full": "1075 Polaris Pkwy Columbus OH 43240",
    "addr:housenumber": "1075",
    "addr:postcode": "43240",
    "addr:street": "Polaris Pkwy",
    "iso:country": "US",
    "sg:address": "1075 Polaris Pkwy",
    "sg:city": "Columbus",
    "sg:classifiers": [
      {
        "category": "Sports \u0026 Exercise",
        "subcategory": "Gym",
        "type": "Entertainment"
      }
    ],
    "sg:phone": "+1 614 781 0261",
    "sg:postcode": "43240",
    "sg:province": "OH",
    "sg:tags": [
      "club",
      "health",
      "studio",
      "gymnasium"
    ],
    "wof:name": "California Fitness Inc",
    "wof:placetype": "venue"
  },
  "geometry": {"coordinates":[-82.992465,40.147405],"type":"Point"}
}
