{
  "type": "Feature",
  "properties": {
    "iso:country":"US",
    "sg:address":"5500 Floral Cir S",
    "sg:city":"Columbus",
    "sg:classifiers":[
        {
            "category":"Real Estate",
            "subcategory":"Real Estate Operator",
            "type":"Services"
        }
    ],
    "sg:phone":"+1 614 878 7296",
    "sg:postcode":"43228",
    "sg:province":"OH",
    "sg:tags":[
        "building",
        "apartment"
    ],
    "sg:website":"www.jvmreality.com",
    "wof:name":"Weston Gardens Apartments",
    "wof:placetype":"venue"
},
  "geometry": {"coordinates":[-83.145094,39.939514],"type":"Point"}
}