{
  "type": "Feature",
  "properties": {
    "addr:full": "5029 Maple View Dr Vermilion OH 44089",
    "addr:housenumber": "5029",
    "addr:postcode": "44089",
    "addr:street": "Maple View Dr",
    "iso:country": "US",
    "sg:address": "5029 Maple View Dr",
    "sg:city": "Vermilion",
    "sg:classifiers": [
      {
        "category": "Real Estate",
        "subcategory": "Real Estate Agent",
        "type": "Services"
      }
    ],
    "sg:phone": "+1 440 967 9070",
    "sg:postcode": "44089",
    "sg:province": "OH",
    "wof:name": "Re/Max",
    "wof:placetype": "venue"
  },
  "geometry": {"coordinates":[-82.35506,41.406907],"type":"Point"}
}
