{
  "type": "Feature",
  "properties": {
    "addr:full": "743 E Waterloo Rd Akron OH 44306",
    "addr:housenumber": "743",
    "addr:postcode": "44306",
    "addr:street": "E Waterloo Rd",
    "iso:country": "US",
    "sg:address": "743 E Waterloo Rd",
    "sg:city": "Akron",
    "sg:classifiers": [
      {
        "category": "Organizations",
        "subcategory": "Non-profit Organization",
        "type": "Services"
      }
    ],
    "sg:phone": "+1 330 724 4494",
    "sg:postcode": "44306",
    "sg:province": "OH",
    "wof:name": "Waterloo Safe Haven",
    "wof:placetype": "venue"
  },
  "geometry": {"coordinates":[-81.499812,41.029544],"type":"Point"}
}
