{
  "type": "Feature",
  "properties": {
    "iso:country":"US",
    "sg:address":"7107 Charles Ave",
    "sg:city":"Cleveland",
    "sg:classifiers":[
        {
            "category":"Freight",
            "type":"Transportation"
        }
    ],
    "sg:phone":"+1 440 886 5090",
    "sg:postcode":"44129",
    "sg:province":"OH",
    "sg:tags":[
        "operator",
        "local",
        "trucking"
    ],
    "wof:name":"Mlm Material Hauling Inc",
    "wof:placetype":"venue"
},
  "geometry": {"coordinates":[-81.732077,41.402099],"type":"Point"}
}