{
  "type": "Feature",
  "properties": {
    "addr:full":"305 W 12th Ave Columbus OH 43210",
    "addr:housenumber":"305",
    "addr:postcode":"43210",
    "addr:street":"W 12Th Ave",
    "iso:country":"US",
    "sg:address":"305 W 12th Ave",
    "sg:city":"Columbus",
    "sg:classifiers":[
        {
            "category":"Health Services",
            "subcategory":"Doctor",
            "type":"Services"
        }
    ],
    "sg:phone":"+1 614 292 1472",
    "sg:postcode":"43210",
    "sg:province":"OH",
    "sg:tags":[
        "dentist"
    ],
    "sg:website":"www.osu.edu",
    "wof:name":"OSU Dental Faculty Practice",
    "wof:placetype":"venue"
},
  "geometry": {"coordinates":[-83.020325,39.995956],"type":"Point"}
}