{
  "type": "Feature",
  "properties": {
    "addr:full": "433 S Grant St Wooster OH 44691",
    "addr:housenumber": "433",
    "addr:postcode": "44691",
    "addr:street": "S Grant St",
    "iso:country": "US",
    "sg:address": "433 S Grant St",
    "sg:city": "Wooster",
    "sg:classifiers": [
      {
        "category": "Building \u0026 Trades",
        "subcategory": "Construction",
        "type": "Services"
      }
    ],
    "sg:phone": "+1 330 263 2992",
    "sg:postcode": "44691",
    "sg:province": "OH",
    "sg:tags": [
      "specializing",
      "commercial",
      "painting",
      "painter",
      "contractor"
    ],
    "wof:name": "Al Barto Decorating",
    "wof:placetype": "venue"
  },
  "geometry": {"coordinates":[-81.942207,40.793651],"type":"Point"}
}
