{
  "type": "Feature",
  "properties": {
    "addr:full": "5972 Oak Grove Ct Hamilton OH 45011",
    "addr:housenumber": "5972",
    "addr:postcode": "45011",
    "addr:street": "Oak Grove Ct",
    "iso:country": "US",
    "sg:address": "5972 Oak Grove Ct",
    "sg:city": "Hamilton",
    "sg:classifiers": [
      {
        "category": "Building \u0026 Trades",
        "subcategory": "Plumbing",
        "type": "Services"
      }
    ],
    "sg:phone": "+1 513 779 6782",
    "sg:postcode": "45011",
    "sg:province": "OH",
    "sg:tags": [
      "heating",
      "contractor"
    ],
    "wof:name": "Liberty Electrical Heating",
    "wof:placetype": "venue"
  },
  "geometry": {"coordinates":[-84.422993,39.37645],"type":"Point"}
}
