{
  "type": "Feature",
  "properties": {
    "addr:full":"810 Matson Pl Cincinnati OH 45204",
    "addr:housenumber":"810",
    "addr:postcode":"45204",
    "addr:street":"Matson Pl",
    "iso:country":"US",
    "sg:address":"810 Matson Pl",
    "sg:city":"Cincinnati",
    "sg:classifiers":[
        {
            "category":"Real Estate",
            "subcategory":"Real Estate Operator",
            "type":"Services"
        }
    ],
    "sg:phone":"+1 513 251 2223",
    "sg:postcode":"45204",
    "sg:province":"OH",
    "sg:tags":[
        "building",
        "apartment"
    ],
    "wof:name":"Queen's Tower",
    "wof:placetype":"venue"
},
  "geometry": {"coordinates":[-84.556856,39.106461],"type":"Point"}
}