{
  "type": "Feature",
  "properties": {
    "addr:full": "5206 Homewood Ave Cleveland OH 44137",
    "addr:housenumber": "5206",
    "addr:postcode": "44137",
    "addr:street": "Homewood Ave",
    "iso:country": "US",
    "sg:address": "5206 Homewood Ave",
    "sg:city": "Cleveland",
    "sg:classifiers": [
      {
        "category": "Manufacturing",
        "subcategory": "Printing",
        "type": "Manufacturing \u0026 Wholesale Goods"
      }
    ],
    "sg:phone": "+1 216 475 0300",
    "sg:postcode": "44137",
    "sg:province": "OH",
    "sg:tags": [
      "periodical"
    ],
    "wof:name": "Gem Magazine",
    "wof:placetype": "venue"
  },
  "geometry": {"coordinates":[-81.54633,41.420406],"type":"Point"}
}
