{
  "type": "Feature",
  "properties": {
    "iso:country":"US",
    "sg:address":"4188 Harrison Rd",
    "sg:city":"Celina",
    "sg:classifiers":[
        {
            "category":"Farming",
            "subcategory":"Dairy Farm",
            "type":"Manufacturing & Wholesale Goods"
        }
    ],
    "sg:phone":"+1 419 268 2572",
    "sg:postcode":"45822",
    "sg:province":"OH",
    "wof:name":"Sweet Land Farms",
    "wof:placetype":"venue"
},
  "geometry": {"coordinates":[-84.512209,40.47137],"type":"Point"}
}