{
  "type": "Feature",
  "properties": {
    "iso:country":"US",
    "sg:address":"1070 Old Logan Rd",
    "sg:city":"Lancaster",
    "sg:classifiers":[
        {
            "category":"Retail",
            "subcategory":"Auto Repair",
            "type":"Services"
        }
    ],
    "sg:phone":"+1 740 654 7443",
    "sg:postcode":"43130",
    "sg:province":"OH",
    "sg:tags":[
        "muffler",
        "exhaust",
        "system"
    ],
    "wof:name":"Muffler Man",
    "wof:placetype":"venue"
},
  "geometry": {"coordinates":[-82.592724,39.700238],"type":"Point"}
}