{
  "type": "Feature",
  "properties": {
    "addr:full": "7989 State Rte 108 Ottawa OH 45875",
    "addr:housenumber": "7989",
    "addr:postcode": "45875",
    "addr:street": "State Rte 108",
    "iso:country": "US",
    "sg:address": "7989 State Rte 108",
    "sg:city": "Ottawa",
    "sg:classifiers": [
      {
        "category": "Social Services",
        "subcategory": "Child Care",
        "type": "Services"
      }
    ],
    "sg:phone": "+1 419 876 3880",
    "sg:postcode": "45875",
    "sg:province": "OH",
    "sg:tags": [
      "day"
    ],
    "wof:name": "Around The Clock Child Care",
    "wof:placetype": "venue"
  },
  "geometry": {"coordinates":[-84.130787,41.063628],"type":"Point"}
}
