{
  "type": "Feature",
  "properties": {
    "iso:country":"US",
    "sg:address":"841 Lafayette Rd",
    "sg:city":"Medina",
    "sg:classifiers":[
        {
            "category":"Travel",
            "subcategory":"Hotels & Motels",
            "type":"Entertainment"
        }
    ],
    "sg:phone":"+1 330 725 6200",
    "sg:postcode":"44256",
    "sg:province":"OH",
    "wof:name":"Medina Motel",
    "wof:placetype":"venue"
},
  "geometry": {"coordinates":[-81.885369,41.126924],"type":"Point"}
}