{
  "type": "Feature",
  "properties": {
    "addr:full":"2054 Atkins Ave Lakewood OH 44107",
    "addr:housenumber":"2054",
    "addr:postcode":"44107",
    "addr:street":"Atkins Ave",
    "iso:country":"US",
    "sg:address":"2054 Atkins Ave",
    "sg:city":"Lakewood",
    "sg:classifiers":[
        {
            "category":"Manufacturing",
            "subcategory":"Signs",
            "type":"Manufacturing & Wholesale Goods"
        }
    ],
    "sg:phone":"+1 216 227 7446",
    "sg:postcode":"44107",
    "sg:province":"OH",
    "sg:tags":[
        "advertising",
        "specialty"
    ],
    "wof:name":"Ohio City Sign Masters",
    "wof:placetype":"venue"
},
  "geometry": {"coordinates":[-81.814673,41.4764],"type":"Point"}
}