{
  "type": "Feature",
  "properties": {
    "iso:country":"US",
    "sg:address":"33 W 11th Ave",
    "sg:city":"Columbus",
    "sg:classifiers":[
        {
            "category":"Education",
            "subcategory":"College",
            "type":"Public Place"
        }
    ],
    "sg:phone":"+1 614 292 9334",
    "sg:postcode":"43201",
    "sg:province":"OH",
    "wof:name":"O S U Student Affairs",
    "wof:placetype":"venue"
},
  "geometry": {"coordinates":[-83.0088,39.995263],"type":"Point"}
}