{
  "type": "Feature",
  "properties": {
    "addr:full": "11551 Blossom Ave Cleveland OH 44130",
    "addr:housenumber": "11551",
    "addr:postcode": "44130",
    "addr:street": "Blossom Ave",
    "iso:country": "US",
    "sg:address": "11551 Blossom Ave",
    "sg:city": "Cleveland",
    "sg:classifiers": [
      {
        "category": "Building \u0026 Trades",
        "subcategory": "Construction",
        "type": "Services"
      }
    ],
    "sg:phone": "+1 440 888 6988",
    "sg:postcode": "44130",
    "sg:province": "OH",
    "sg:tags": [
      "cement",
      "contractor"
    ],
    "wof:name": "Andrew Babkin",
    "wof:placetype": "venue"
  },
  "geometry": {"coordinates":[-81.769552,41.379341],"type":"Point"}
}
