{
  "type": "Feature",
  "properties": {
    "iso:country":"US",
    "sg:address":"11551 Blossom Ave",
    "sg:city":"Cleveland",
    "sg:classifiers":[
        {
            "category":"Building & Trades",
            "subcategory":"Construction",
            "type":"Services"
        }
    ],
    "sg:phone":"+1 440 888 6988",
    "sg:postcode":"44130",
    "sg:province":"OH",
    "sg:tags":[
        "cement",
        "contractor"
    ],
    "wof:name":"Andrew Babkin",
    "wof:placetype":"venue"
},
  "geometry": {"coordinates":[-81.769552,41.379341],"type":"Point"}
}