{
  "type": "Feature",
  "properties": {
    "addr:full": "1072 State Rte 81 Ada OH 45810",
    "addr:housenumber": "1072",
    "addr:postcode": "45810",
    "addr:street": "State Rte 81",
    "iso:country": "US",
    "sg:address": "1072 State Rte 81",
    "sg:city": "Ada",
    "sg:classifiers": [
      {
        "category": "Building \u0026 Trades",
        "subcategory": "Plumbing",
        "type": "Services"
      }
    ],
    "sg:phone": "+1 419 634 9182",
    "sg:postcode": "45810",
    "sg:province": "OH",
    "sg:tags": [
      "contractor"
    ],
    "wof:name": "Harris Heating \u0026 AC",
    "wof:placetype": "venue"
  },
  "geometry": {"coordinates":[-83.860148,40.776419],"type":"Point"}
}
