{
  "type": "Feature",
  "properties": {
    "addr:full":"131 Salem Ave Dayton OH 45406",
    "addr:housenumber":"131",
    "addr:postcode":"45406",
    "addr:street":"Salem Ave",
    "iso:country":"US",
    "sg:address":"131 Salem Ave",
    "sg:city":"Dayton",
    "sg:classifiers":[
        {
            "category":"Professional",
            "subcategory":"Employment Agencies",
            "type":"Services"
        }
    ],
    "sg:phone":"+1 937 222 3350",
    "sg:postcode":"45406",
    "sg:province":"OH",
    "sg:tags":[
        "opportunity"
    ],
    "sg:website":"www.laborready.com",
    "wof:name":"Labor Ready Inc",
    "wof:placetype":"venue"
},
  "geometry": {"coordinates":[-84.206388,39.763769],"type":"Point"}
}