{
  "type": "Feature",
  "properties": {
    "addr:full":"3684 E 110th St Cleveland OH 44105",
    "addr:housenumber":"3684",
    "addr:postcode":"44105",
    "addr:street":"E 110Th St",
    "iso:country":"US",
    "sg:address":"3684 E 110th St",
    "sg:city":"Cleveland",
    "sg:classifiers":[
        {
            "category":"Organizations",
            "subcategory":"Religious Organization",
            "type":"Services"
        }
    ],
    "sg:phone":"+1 216 441 6352",
    "sg:postcode":"44105",
    "sg:province":"OH",
    "sg:tags":[
        "clergy"
    ],
    "wof:name":"Karious Mc Daniel",
    "wof:placetype":"venue"
},
  "geometry": {"coordinates":[-81.608239,41.458158],"type":"Point"}
}