{
  "type": "Feature",
  "properties": {
    "addr:full": "9224 Village Green Dr Cincinnati OH 45242",
    "addr:housenumber": "9224",
    "addr:postcode": "45242",
    "addr:street": "Village Green Dr",
    "iso:country": "US",
    "sg:address": "9224 Village Green Dr",
    "sg:city": "Cincinnati",
    "sg:classifiers": [
      {
        "category": "Building \u0026 Trades",
        "subcategory": "Landscaping Services",
        "type": "Services"
      }
    ],
    "sg:phone": "+1 513 984 3242",
    "sg:postcode": "45242",
    "sg:province": "OH",
    "wof:name": "Thomas Barnes Lawn Service I",
    "wof:placetype": "venue"
  },
  "geometry": {"coordinates":[-84.363395,39.227368],"type":"Point"}
}
