{
  "type": "Feature",
  "properties": {
    "iso:country":"US",
    "sg:address":"4831 Pleasant Ave",
    "sg:city":"Fairfield",
    "sg:classifiers":[
        {
            "category":"Organizations",
            "subcategory":"Religious Organization",
            "type":"Services"
        }
    ],
    "sg:phone":"+1 513 844 8598",
    "sg:postcode":"45014",
    "sg:province":"OH",
    "sg:tags":[
        "church"
    ],
    "wof:name":"Church Of Jesus Christ Of Lds",
    "wof:placetype":"venue"
},
  "geometry": {"coordinates":[-84.559421,39.34639],"type":"Point"}
}