{
  "type": "Feature",
  "properties": {
    "addr:full": "4831 Pleasant Ave Fairfield OH 45014",
    "addr:housenumber": "4831",
    "addr:postcode": "45014",
    "addr:street": "Pleasant Ave",
    "iso:country": "US",
    "sg:address": "4831 Pleasant Ave",
    "sg:city": "Fairfield",
    "sg:classifiers": [
      {
        "category": "Organizations",
        "subcategory": "Religious Organization",
        "type": "Services"
      }
    ],
    "sg:phone": "+1 513 844 8598",
    "sg:postcode": "45014",
    "sg:province": "OH",
    "sg:tags": [
      "church"
    ],
    "wof:name": "Church Of Jesus Christ Of Lds",
    "wof:placetype": "venue"
  },
  "geometry": {"coordinates":[-84.559421,39.34639],"type":"Point"}
}
