{
  "type": "Feature",
  "properties": {
    "addr:full": "1436 Eastview Ave NE Canton OH 44705",
    "addr:housenumber": "1436",
    "addr:postcode": "44705",
    "addr:street": "Eastview Ave Ne",
    "iso:country": "US",
    "sg:address": "1436 Eastview Ave NE",
    "sg:city": "Canton",
    "sg:classifiers": [
      {
        "category": "Retail",
        "subcategory": "Auto Repair",
        "type": "Services"
      }
    ],
    "sg:phone": "+1 330 452 2867",
    "sg:postcode": "44705",
    "sg:province": "OH",
    "sg:tags": [
      "body",
      "automobile",
      "painting"
    ],
    "wof:name": "Mc Millen \u0026 Son",
    "wof:placetype": "venue"
  },
  "geometry": {"coordinates":[-81.335991,40.812492],"type":"Point"}
}
