{
  "type": "Feature",
  "properties": {
    "iso:country":"US",
    "sg:address":"24062 Hull Prairie Rd",
    "sg:city":"Perrysburg",
    "sg:classifiers":[
        {
            "category":"Professional",
            "type":"Services"
        }
    ],
    "sg:phone":"+1 419 823 1474",
    "sg:postcode":"43551",
    "sg:province":"OH",
    "wof:name":"Maribeth Moser",
    "wof:placetype":"venue"
},
  "geometry": {"coordinates":[-83.674803,41.510726],"type":"Point"}
}