{
  "type": "Feature",
  "properties": {
    "iso:country":"US",
    "sg:address":"1445 S Meridian Rd",
    "sg:city":"Youngstown",
    "sg:classifiers":[
        {
            "category":"Organizations",
            "subcategory":"Religious Organization",
            "type":"Services"
        }
    ],
    "sg:phone":"+1 330 799 5389",
    "sg:postcode":"44511",
    "sg:province":"OH",
    "sg:tags":[
        "clergy"
    ],
    "wof:name":"Richard B Driscoll",
    "wof:placetype":"venue"
},
  "geometry": {"coordinates":[-80.71094100000001,41.082134],"type":"Point"}
}