{
  "type": "Feature",
  "properties": {
    "addr:full": "1445 S Meridian Rd Youngstown OH 44511",
    "addr:housenumber": "1445",
    "addr:postcode": "44511",
    "addr:street": "S Meridian Rd",
    "iso:country": "US",
    "sg:address": "1445 S Meridian Rd",
    "sg:city": "Youngstown",
    "sg:classifiers": [
      {
        "category": "Organizations",
        "subcategory": "Religious Organization",
        "type": "Services"
      }
    ],
    "sg:phone": "+1 330 799 5389",
    "sg:postcode": "44511",
    "sg:province": "OH",
    "sg:tags": [
      "clergy"
    ],
    "wof:name": "Richard B Driscoll",
    "wof:placetype": "venue"
  },
  "geometry": {"coordinates":[-80.710941,41.082134],"type":"Point"}
}
