{
  "type": "Feature",
  "properties": {
    "iso:country":"US",
    "sg:address":"990 W Emmitt Ave",
    "sg:city":"Waverly",
    "sg:classifiers":[
        {
            "category":"Retail",
            "subcategory":"Portrait Studio",
            "type":"Services"
        }
    ],
    "sg:phone":"+1 740 941 4804",
    "sg:postcode":"45690",
    "sg:province":"OH",
    "sg:tags":[
        "photographer"
    ],
    "wof:name":"Wal-Mart Portrait Studio",
    "wof:placetype":"venue"
},
  "geometry": {"coordinates":[-82.990945,39.123283],"type":"Point"}
}