{
  "type": "Feature",
  "properties": {
    "addr:full": "5423 Kister Rd Wooster OH 44691",
    "addr:housenumber": "5423",
    "addr:postcode": "44691",
    "addr:street": "Kister Rd",
    "iso:country": "US",
    "sg:address": "5423 Kister Rd",
    "sg:city": "Wooster",
    "sg:classifiers": [
      {
        "category": "Farming",
        "subcategory": "Dairy Farm",
        "type": "Manufacturing \u0026 Wholesale Goods"
      }
    ],
    "sg:phone": "+1 330 264 1244",
    "sg:postcode": "44691",
    "sg:province": "OH",
    "wof:name": "William Troutman",
    "wof:placetype": "venue"
  },
  "geometry": {"coordinates":[-82.033748,40.736935],"type":"Point"}
}
