{
  "type": "Feature",
  "properties": {
    "addr:full": "441 Jentes Rd Wooster OH 44691",
    "addr:housenumber": "441",
    "addr:postcode": "44691",
    "addr:street": "Jentes Rd",
    "iso:country": "US",
    "sg:address": "441 Jentes Rd",
    "sg:city": "Wooster",
    "sg:classifiers": [
      {
        "category": "Farming",
        "subcategory": "Farm",
        "type": "Manufacturing \u0026 Wholesale Goods"
      }
    ],
    "sg:phone": "+1 330 345 8085",
    "sg:postcode": "44691",
    "sg:province": "OH",
    "sg:tags": [
      "crop",
      "general"
    ],
    "wof:name": "Marla Millhoan",
    "wof:placetype": "venue"
  },
  "geometry": {"coordinates":[-81.956877,40.887369],"type":"Point"}
}
