{
  "type": "Feature",
  "properties": {
    "iso:country":"US",
    "sg:address":"441 Jentes Rd",
    "sg:city":"Wooster",
    "sg:classifiers":[
        {
            "category":"Farming",
            "subcategory":"Farm",
            "type":"Manufacturing & Wholesale Goods"
        }
    ],
    "sg:phone":"+1 330 345 8085",
    "sg:postcode":"44691",
    "sg:province":"OH",
    "sg:tags":[
        "crop",
        "general"
    ],
    "wof:name":"Marla Millhoan",
    "wof:placetype":"venue"
},
  "geometry": {"coordinates":[-81.956877,40.887369],"type":"Point"}
}