{
  "type": "Feature",
  "properties": {
    "addr:full":"135 W 6th Ave Lancaster OH 43130",
    "addr:housenumber":"135",
    "addr:postcode":"43130",
    "addr:street":"W 6Th Ave",
    "iso:country":"US",
    "sg:address":"135 W 6th Ave",
    "sg:city":"Lancaster",
    "sg:classifiers":[
        {
            "category":"Health Services",
            "subcategory":"Optometrist",
            "type":"Services"
        }
    ],
    "sg:phone":"+1 740 654 4762",
    "sg:postcode":"43130",
    "sg:province":"OH",
    "wof:name":"Family Eye Care Professionals",
    "wof:placetype":"venue"
},
  "geometry": {"coordinates":[-82.602335,39.719916],"type":"Point"}
}