{
  "type": "Feature",
  "properties": {
    "iso:country":"US",
    "sg:address":"2727 N Fairfield Rd",
    "sg:city":"Dayton",
    "sg:classifiers":[
        {
            "category":"Shopping",
            "subcategory":"Shoes",
            "type":"Retail Goods"
        },
        {
            "category":"Shopping",
            "subcategory":"Clothing, Apparel, & Fashions",
            "type":"Retail Goods"
        }
    ],
    "sg:phone":"+1 937 320 0124",
    "sg:postcode":"45431",
    "sg:province":"OH",
    "sg:tags":[
        "sportswear"
    ],
    "wof:name":"Finish Line",
    "wof:placetype":"venue"
},
  "geometry": {"coordinates":[-84.05221899999999,39.768912],"type":"Point"}
}