{
  "type": "Feature",
  "properties": {
    "iso:country":"US",
    "sg:address":"225 S 1st St",
    "sg:city":"Union City",
    "sg:classifiers":[
        {
            "category":"Organizations",
            "subcategory":"Religious Organization",
            "type":"Services"
        }
    ],
    "sg:phone":"+1 937 968 6163",
    "sg:postcode":"45390",
    "sg:province":"OH",
    "sg:tags":[
        "church"
    ],
    "wof:name":"First Baptist Church Office",
    "wof:placetype":"venue"
},
  "geometry": {"coordinates":[-84.80306400000001,40.196087],"type":"Point"}
}