{
  "type": "Feature",
  "properties": {
    "addr:full": "225 S 1st St Union City OH 45390",
    "addr:housenumber": "225",
    "addr:postcode": "45390",
    "addr:street": "S 1St St",
    "iso:country": "US",
    "sg:address": "225 S 1st St",
    "sg:city": "Union City",
    "sg:classifiers": [
      {
        "category": "Organizations",
        "subcategory": "Religious Organization",
        "type": "Services"
      }
    ],
    "sg:phone": "+1 937 968 6163",
    "sg:postcode": "45390",
    "sg:province": "OH",
    "sg:tags": [
      "church"
    ],
    "wof:name": "First Baptist Church Office",
    "wof:placetype": "venue"
  },
  "geometry": {"coordinates":[-84.803064,40.196087],"type":"Point"}
}
