{
  "type": "Feature",
  "properties": {
    "iso:country":"US",
    "sg:address":"17 S High St",
    "sg:city":"Columbus",
    "sg:classifiers":[
        {
            "category":"Professional",
            "subcategory":"Lawyer & Legal Services",
            "type":"Services"
        }
    ],
    "sg:phone":"+1 614 621 1417",
    "sg:postcode":"43215",
    "sg:province":"OH",
    "sg:tags":[
        "plan"
    ],
    "wof:name":"Mc Cord Co",
    "wof:placetype":"venue"
},
  "geometry": {"coordinates":[-83.000658,39.961976],"type":"Point"}
}