{
  "type": "Feature",
  "properties": {
    "addr:full": "14225 Wade Ave NE Hartville OH 44632",
    "addr:housenumber": "14225",
    "addr:postcode": "44632",
    "addr:street": "Wade Ave Ne",
    "iso:country": "US",
    "sg:address": "14225 Wade Ave NE",
    "sg:city": "Hartville",
    "sg:classifiers": [
      {
        "category": "Mining \u0026 Drilling",
        "type": "Manufacturing \u0026 Wholesale Goods"
      }
    ],
    "sg:phone": "+1 330 935 0125",
    "sg:postcode": "44632",
    "sg:province": "OH",
    "sg:tags": [
      "oil",
      "gas",
      "wells"
    ],
    "wof:name": "X Ces Oil Field Services",
    "wof:placetype": "venue"
  },
  "geometry": {"coordinates":[-81.251759,40.976753],"type":"Point"}
}
