{
  "type": "Feature",
  "properties": {
    "iso:country":"US",
    "sg:address":"14225 Wade Ave NE",
    "sg:city":"Hartville",
    "sg:classifiers":[
        {
            "category":"Mining & Drilling",
            "type":"Manufacturing & Wholesale Goods"
        }
    ],
    "sg:phone":"+1 330 935 0125",
    "sg:postcode":"44632",
    "sg:province":"OH",
    "sg:tags":[
        "oil",
        "gas",
        "wells"
    ],
    "wof:name":"X Ces Oil Field Services",
    "wof:placetype":"venue"
},
  "geometry": {"coordinates":[-81.25175900000001,40.976753],"type":"Point"}
}