{
  "type": "Feature",
  "properties": {
    "addr:full":"283 Union St Bedford OH 44146",
    "addr:housenumber":"283",
    "addr:postcode":"44146",
    "addr:street":"Union St",
    "iso:country":"US",
    "sg:address":"283 Union St",
    "sg:city":"Bedford",
    "sg:classifiers":[
        {
            "category":"Health Services",
            "subcategory":"Nursing And Care Facility",
            "type":"Services"
        },
        {
            "category":"Social Services",
            "subcategory":"Retirement Home",
            "type":"Services"
        }
    ],
    "sg:phone":"+1 440 232 1991",
    "sg:postcode":"44146",
    "sg:province":"OH",
    "sg:tags":[
        "living",
        "people",
        "residential",
        "assisted",
        "convalescent",
        "homes-elderly",
        "homes-intermediate"
    ],
    "sg:website":"http://www.lightofheartsvilla.org",
    "wof:name":"Light Of Hearts Villa",
    "wof:placetype":"venue"
},
  "geometry": {"coordinates":[-81.52576500000001,41.381354],"type":"Point"}
}