{
  "type": "Feature",
  "properties": {
    "addr:full": "31000 Solon Rd Cleveland OH 44139",
    "addr:postcode": "31000;44139",
    "addr:street": "Solon Rd",
    "iso:country": "US",
    "sg:address": "31000 Solon Rd",
    "sg:city": "Cleveland",
    "sg:classifiers": [
      {
        "category": "Professional",
        "subcategory": "Business Services",
        "type": "Services"
      },
      {
        "category": "Utilities",
        "subcategory": "Refuse",
        "type": "Services"
      }
    ],
    "sg:phone": "+1 440 519 9528",
    "sg:postcode": "44139",
    "sg:province": "OH",
    "sg:tags": [
      "water",
      "system",
      "treatment"
    ],
    "wof:name": "American Multitech Svc Inc",
    "wof:placetype": "venue"
  },
  "geometry": {"coordinates":[-81.457102,41.38713],"type":"Point"}
}
