{
  "type": "Feature",
  "properties": {
    "addr:full": "10221 Union Ave Cleveland OH 44105",
    "addr:housenumber": "10221",
    "addr:postcode": "44105",
    "addr:street": "Union Ave",
    "iso:country": "US",
    "sg:address": "10221 Union Ave",
    "sg:city": "Cleveland",
    "sg:classifiers": [
      {
        "category": "Food \u0026 Beverages",
        "subcategory": "Groceries \u0026 Convenience Stores",
        "type": "Retail Goods"
      }
    ],
    "sg:phone": "+1 216 429 2191",
    "sg:postcode": "44105",
    "sg:province": "OH",
    "wof:name": "Union Uptown Deli",
    "wof:placetype": "venue"
  },
  "geometry": {"coordinates":[-81.613811,41.463652],"type":"Point"}
}
