{
  "type": "Feature",
  "properties": {
    "iso:country":"US",
    "sg:address":"5059 Otterbein-Ithaca Rd",
    "sg:city":"Arcanum",
    "sg:classifiers":[
        {
            "category":"Farming",
            "subcategory":"Farm",
            "type":"Manufacturing & Wholesale Goods"
        }
    ],
    "sg:phone":"+1 937 678 9961",
    "sg:postcode":"45304",
    "sg:province":"OH",
    "sg:tags":[
        "crop",
        "general"
    ],
    "wof:name":"Kemp Richard Farm of",
    "wof:placetype":"venue"
},
  "geometry": {"coordinates":[-84.599251,39.9459],"type":"Point"}
}