{
  "type": "Feature",
  "properties": {
    "addr:full": "5059 Otterbein-Ithaca Rd Arcanum OH 45304",
    "addr:housenumber": "5059",
    "addr:postcode": "45304",
    "addr:street": "Otterbein-Ithaca Rd",
    "iso:country": "US",
    "sg:address": "5059 Otterbein-Ithaca Rd",
    "sg:city": "Arcanum",
    "sg:classifiers": [
      {
        "category": "Farming",
        "subcategory": "Farm",
        "type": "Manufacturing \u0026 Wholesale Goods"
      }
    ],
    "sg:phone": "+1 937 678 9961",
    "sg:postcode": "45304",
    "sg:province": "OH",
    "sg:tags": [
      "crop",
      "general"
    ],
    "wof:name": "Kemp Richard Farm of",
    "wof:placetype": "venue"
  },
  "geometry": {"coordinates":[-84.599251,39.9459],"type":"Point"}
}
