{
  "type": "Feature",
  "properties": {
    "addr:full": "643 Wheeling Ave Cambridge OH 43725",
    "addr:housenumber": "643",
    "addr:postcode": "43725",
    "addr:street": "Wheeling Ave",
    "iso:country": "US",
    "sg:address": "643 Wheeling Ave",
    "sg:city": "Cambridge",
    "sg:classifiers": [
      {
        "category": "Shopping",
        "subcategory": "Hobbies, Toys, \u0026 Games",
        "type": "Retail Goods"
      }
    ],
    "sg:phone": "+1 740 435 8701",
    "sg:postcode": "43725",
    "sg:province": "OH",
    "sg:tags": [
      "equipment",
      "ceramic",
      "supply"
    ],
    "wof:name": "Lin's Clay House",
    "wof:placetype": "venue"
  },
  "geometry": {"coordinates":[-81.592796,40.024907],"type":"Point"}
}
