{
  "type": "Feature",
  "properties": {
    "addr:full":"10090 Old Tile Factory Rd Van Wert OH 45891",
    "addr:housenumber":"10090",
    "addr:postcode":"45891",
    "addr:street":"Old Tile Factory Rd",
    "iso:country":"US",
    "sg:address":"10090 Old Tile Factory Rd",
    "sg:city":"Van Wert",
    "sg:classifiers":[
        {
            "category":"Professional",
            "subcategory":"Business Services",
            "type":"Services"
        }
    ],
    "sg:phone":"+1 419 232 3035",
    "sg:postcode":"45891",
    "sg:province":"OH",
    "sg:tags":[
        "embroidery"
    ],
    "wof:name":"Taylor Embroidery & More",
    "wof:placetype":"venue"
},
  "geometry": {"coordinates":[-84.626831,40.865934],"type":"Point"}
}