{
  "type": "Feature",
  "properties": {
    "iso:country":"US",
    "sg:address":"9575 Jackson St",
    "sg:city":"Mentor",
    "sg:classifiers":[
        {
            "category":"Real Estate",
            "subcategory":"Real Estate Agent",
            "type":"Services"
        }
    ],
    "sg:phone":"+1 440 357 8119",
    "sg:postcode":"44060",
    "sg:province":"OH",
    "wof:name":"Regency Realty & Investments",
    "wof:placetype":"venue"
},
  "geometry": {"coordinates":[-81.29476,41.697286],"type":"Point"}
}