{
  "type": "Feature",
  "properties": {
    "iso:country":"US",
    "sg:address":"34490 Melinz Pkwy",
    "sg:city":"Willoughby",
    "sg:classifiers":[
        {
            "category":"Manufacturing",
            "subcategory":"Retail Goods",
            "type":"Manufacturing & Wholesale Goods"
        },
        {
            "category":"Retail",
            "subcategory":"Repair Shop",
            "type":"Services"
        },
        {
            "category":"Professional",
            "subcategory":"Computer Services",
            "type":"Services"
        }
    ],
    "sg:phone":"+1 440 946 8406",
    "sg:postcode":"44095",
    "sg:province":"OH",
    "sg:tags":[
        "product",
        "sales",
        "mfg"
    ],
    "wof:name":"Soho Tech Village Ltd",
    "wof:placetype":"venue"
},
  "geometry": {"coordinates":[-81.44362,41.636414],"type":"Point"}
}