{
  "type": "Feature",
  "properties": {
    "iso:country":"US",
    "sg:address":"3020 Stoney Creek Rd",
    "sg:city":"Chillicothe",
    "sg:classifiers":[
        {
            "category":"Real Estate",
            "subcategory":"Real Estate Agent",
            "type":"Services"
        }
    ],
    "sg:phone":"+1 740 663 5491",
    "sg:postcode":"45601",
    "sg:province":"OH",
    "wof:name":"Weeses Country Est",
    "wof:placetype":"venue"
},
  "geometry": {"coordinates":[-82.92651499999999,39.224272],"type":"Point"}
}