{
  "type": "Feature",
  "properties": {
    "addr:full": "2214 Lake St Fremont OH 43420",
    "addr:housenumber": "2214",
    "addr:postcode": "43420",
    "addr:street": "Lake St",
    "iso:country": "US",
    "sg:address": "2214 Lake St",
    "sg:city": "Fremont",
    "sg:classifiers": [
      {
        "category": "Professional",
        "type": "Services"
      }
    ],
    "sg:phone": "+1 419 334 7444",
    "sg:postcode": "43420",
    "sg:province": "OH",
    "wof:name": "American Federation of St",
    "wof:placetype": "venue"
  },
  "geometry": {"coordinates":[-83.143459,41.352962],"type":"Point"}
}
