{
  "type": "Feature",
  "properties": {
    "iso:country":"US",
    "sg:address":"1839 Middle Bellville Rd",
    "sg:city":"Mansfield",
    "sg:classifiers":[
        {
            "category":"Real Estate",
            "subcategory":"Real Estate Agent",
            "type":"Services"
        }
    ],
    "sg:phone":"+1 419 756 9856",
    "sg:postcode":"44904",
    "sg:province":"OH",
    "wof:name":"240-B Tappan Dr N",
    "wof:placetype":"venue"
},
  "geometry": {"coordinates":[-82.536677,40.709483],"type":"Point"}
}