{
  "type": "Feature",
  "properties": {
    "addr:full": "1065 E Tallmadge Ave Akron OH 44310",
    "addr:housenumber": "1065",
    "addr:postcode": "44310",
    "addr:street": "E Tallmadge Ave",
    "iso:country": "US",
    "sg:address": "1065 E Tallmadge Ave",
    "sg:city": "Akron",
    "sg:classifiers": [
      {
        "category": "Restaurant",
        "type": "Food \u0026 Drink"
      }
    ],
    "sg:phone": "+1 330 633 4922",
    "sg:postcode": "44310",
    "sg:province": "OH",
    "wof:name": "Great Garden",
    "wof:placetype": "venue"
  },
  "geometry": {"coordinates":[-81.475802,41.10211],"type":"Point"}
}
