{
  "type": "Feature",
  "properties": {
    "addr:full": "1120 Chester Ave Cleveland OH 44114",
    "addr:housenumber": "1120",
    "addr:postcode": "44114",
    "addr:street": "Chester Ave",
    "iso:country": "US",
    "sg:address": "1120 Chester Ave",
    "sg:city": "Cleveland",
    "sg:classifiers": [
      {
        "category": "Banks \u0026 Credit Unions",
        "subcategory": "Bank",
        "type": "Services"
      }
    ],
    "sg:phone": "+1 216 902 8500",
    "sg:postcode": "44114",
    "sg:province": "OH",
    "sg:tags": [
      "firm",
      "finance",
      "loan",
      "real estate",
      "investment"
    ],
    "sg:website": "www.capstone-realty.com",
    "wof:name": "Capstone Realty Advisors LLC",
    "wof:placetype": "venue"
  },
  "geometry": {"coordinates":[-81.685203,41.502036],"type":"Point"}
}
