{
  "type": "Feature",
  "properties": {
    "addr:full":"901 Copley Rd Akron OH 44320",
    "addr:housenumber":"901",
    "addr:postcode":"44320",
    "addr:street":"Copley Rd",
    "iso:country":"US",
    "sg:address":"901 Copley Rd",
    "sg:city":"Akron",
    "sg:classifiers":[
        {
            "category":"Organizations",
            "subcategory":"Religious Organization",
            "type":"Services"
        }
    ],
    "sg:phone":"+1 330 836 0035",
    "sg:postcode":"44320",
    "sg:province":"OH",
    "sg:tags":[
        "church"
    ],
    "wof:name":"Bethel Seventh Day Adventist",
    "wof:placetype":"venue"
},
  "geometry": {"coordinates":[-81.554771,41.084207],"type":"Point"}
}