{
  "type": "Feature",
  "properties": {
    "addr:full": "3093 Patterson Ridge Rd Stockport OH 43787",
    "addr:housenumber": "3093",
    "addr:postcode": "43787",
    "addr:street": "Patterson Ridge Rd",
    "iso:country": "US",
    "sg:address": "3093 Patterson Ridge Rd",
    "sg:city": "Stockport",
    "sg:classifiers": [
      {
        "category": "Building \u0026 Trades",
        "subcategory": "Electrical",
        "type": "Services"
      }
    ],
    "sg:phone": "+1 740 559 2309",
    "sg:postcode": "43787",
    "sg:province": "OH",
    "sg:tags": [
      "electric",
      "contractor"
    ],
    "wof:name": "Bebout Electric",
    "wof:placetype": "venue"
  },
  "geometry": {"coordinates":[-81.768883,39.552943],"type":"Point"}
}
