{
  "type": "Feature",
  "properties": {
    "iso:country":"US",
    "sg:address":"1622 Pasadena Ave",
    "sg:city":"Cincinnati",
    "sg:classifiers":[
        {
            "category":"Organizations",
            "subcategory":"Religious Organization",
            "type":"Services"
        }
    ],
    "sg:phone":"+1 513 681 5041",
    "sg:postcode":"45224",
    "sg:province":"OH",
    "sg:tags":[
        "clergy"
    ],
    "wof:name":"David Allen",
    "wof:placetype":"venue"
},
  "geometry": {"coordinates":[-84.546938,39.192151],"type":"Point"}
}