{
  "type": "Feature",
  "properties": {
    "iso:country":"US",
    "sg:address":"2400 Romig Rd",
    "sg:city":"Akron",
    "sg:classifiers":[
        {
            "category":"Restaurant",
            "type":"Food & Drink"
        }
    ],
    "sg:phone":"+1 330 745 9615",
    "sg:postcode":"44320",
    "sg:province":"OH",
    "sg:tags":[
        "caterer"
    ],
    "wof:name":"Judd's Bar BQ",
    "wof:placetype":"venue"
},
  "geometry": {"coordinates":[-81.58081300000001,41.048739],"type":"Point"}
}