{
  "type": "Feature",
  "properties": {
    "addr:full": "1070 E State St Salem OH 44460",
    "addr:housenumber": "1070",
    "addr:postcode": "44460",
    "addr:street": "E State St",
    "iso:country": "US",
    "sg:address": "1070 E State St",
    "sg:city": "Salem",
    "sg:classifiers": [
      {
        "category": "Health Services",
        "subcategory": "Doctor",
        "type": "Services"
      }
    ],
    "sg:phone": "+1 330 332 4274",
    "sg:postcode": "44460",
    "sg:province": "OH",
    "sg:tags": [
      "medical"
    ],
    "wof:name": "Handel Daniel W MD",
    "wof:placetype": "venue"
  },
  "geometry": {"coordinates":[-80.846749,40.901012],"type":"Point"}
}
