{
  "type": "Feature",
  "properties": {
    "iso:country":"US",
    "sg:address":"1070 E State St",
    "sg:city":"Salem",
    "sg:classifiers":[
        {
            "category":"Health Services",
            "subcategory":"Doctor",
            "type":"Services"
        }
    ],
    "sg:phone":"+1 330 332 4274",
    "sg:postcode":"44460",
    "sg:province":"OH",
    "sg:tags":[
        "medical"
    ],
    "wof:name":"Handel Daniel W MD",
    "wof:placetype":"venue"
},
  "geometry": {"coordinates":[-80.846749,40.901012],"type":"Point"}
}