{
  "type": "Feature",
  "properties": {
    "iso:country":"US",
    "sg:address":"4394 Eastgate Square Dr",
    "sg:city":"Cincinnati",
    "sg:classifiers":[
        {
            "category":"Restaurant",
            "type":"Food & Drink"
        }
    ],
    "sg:phone":"+1 513 943 7555",
    "sg:postcode":"45245",
    "sg:province":"OH",
    "wof:name":"China Buffet",
    "wof:placetype":"venue"
},
  "geometry": {"coordinates":[-84.268761,39.095251],"type":"Point"}
}