{
  "type": "Feature",
  "properties": {
    "addr:full":"644 Linn St Cincinnati OH 45203",
    "addr:housenumber":"644",
    "addr:postcode":"45203",
    "addr:street":"Linn St",
    "iso:country":"US",
    "sg:address":"644 Linn St",
    "sg:city":"Cincinnati",
    "sg:classifiers":[
        {
            "category":"Health Services",
            "subcategory":"Clinic",
            "type":"Services"
        },
        {
            "category":"Social Services",
            "type":"Services"
        }
    ],
    "sg:phone":"+1 513 721 7440",
    "sg:postcode":"45203",
    "sg:province":"OH",
    "sg:tags":[
        "home",
        "child",
        "day",
        "care"
    ],
    "wof:name":"Family Care Inc",
    "wof:placetype":"venue"
},
  "geometry": {"coordinates":[-84.528935,39.104113],"type":"Point"}
}