{
  "type": "Feature",
  "properties": {
    "addr:full":"2160 E 5th St Dayton OH 45403",
    "addr:housenumber":"2160",
    "addr:postcode":"45403",
    "addr:street":"E 5Th St",
    "iso:country":"US",
    "sg:address":"2160 E 5th St",
    "sg:city":"Dayton",
    "sg:classifiers":[
        {
            "category":"Government",
            "subcategory":"Office",
            "type":"Public Place"
        }
    ],
    "sg:phone":"+1 937 333 7373",
    "sg:postcode":"45403",
    "sg:province":"OH",
    "sg:tags":[
        "village"
    ],
    "wof:name":"Dayton Priority Boards",
    "wof:placetype":"venue"
},
  "geometry": {"coordinates":[-84.165586,39.759749],"type":"Point"}
}