{
  "type": "Feature",
  "properties": {
    "addr:full":"6861 Co Rd H Edon OH 43518",
    "addr:housenumber":"6861",
    "addr:postcode":"43518",
    "addr:street":"Co Rd H",
    "iso:country":"US",
    "sg:address":"6861 Co Rd H",
    "sg:city":"Edon",
    "sg:classifiers":[
        {
            "category":"Farming",
            "subcategory":"Livestock Farm",
            "type":"Manufacturing & Wholesale Goods"
        }
    ],
    "sg:phone":"+1 419 272 2783",
    "sg:postcode":"43518",
    "sg:province":"OH",
    "sg:tags":[
        "hog",
        "or",
        "feedlot"
    ],
    "wof:name":"James Brigle",
    "wof:placetype":"venue"
},
  "geometry": {"coordinates":[-84.69582699999999,41.528002],"type":"Point"}
}