{
  "type": "Feature",
  "properties": {
    "addr:full":"1441 Kirkley Rd Columbus OH 43221",
    "addr:housenumber":"1441",
    "addr:postcode":"43221",
    "addr:street":"Kirkley Rd",
    "iso:country":"US",
    "sg:address":"1441 Kirkley Rd",
    "sg:city":"Columbus",
    "sg:classifiers":[
        {
            "category":"Professional",
            "subcategory":"Accounting & Tax Preparation",
            "type":"Services"
        }
    ],
    "sg:phone":"+1 614 459 0754",
    "sg:postcode":"43221",
    "sg:province":"OH",
    "sg:tags":[
        "bookkeeping",
        "general"
    ],
    "wof:name":"To The Penny Bookkeeping",
    "wof:placetype":"venue"
},
  "geometry": {"coordinates":[-83.05074399999999,40.020001],"type":"Point"}
}