{
  "type": "Feature",
  "properties": {
    "iso:country":"US",
    "sg:address":"1324 3rd St NW",
    "sg:city":"New Philadelphia",
    "sg:classifiers":[
        {
            "category":"Social Services",
            "subcategory":"Adult Care",
            "type":"Services"
        }
    ],
    "sg:phone":"+1 330 364 9251",
    "sg:postcode":"44663",
    "sg:province":"OH",
    "sg:tags":[
        "organization",
        "senior",
        "citizen"
    ],
    "wof:name":"Retired & Senior Volunteer",
    "wof:placetype":"venue"
},
  "geometry": {"coordinates":[-81.450731,40.507264],"type":"Point"}
}