{
  "type": "Feature",
  "properties": {
    "addr:full":"14 Victor Ave Cuyahoga Falls OH 44221",
    "addr:housenumber":"14",
    "addr:postcode":"44221",
    "addr:street":"Victor Ave",
    "iso:country":"US",
    "sg:address":"14 Victor Ave",
    "sg:city":"Cuyahoga Falls",
    "sg:classifiers":[
        {
            "category":"Freight",
            "type":"Transportation"
        }
    ],
    "sg:phone":"+1 330 945 7761",
    "sg:postcode":"44221",
    "sg:province":"OH",
    "sg:tags":[
        "operator",
        "local",
        "trucking"
    ],
    "wof:name":"Bear Trucking Inc",
    "wof:placetype":"venue"
},
  "geometry": {"coordinates":[-81.48571800000001,41.151642],"type":"Point"}
}