{
  "type": "Feature",
  "properties": {
    "addr:full":"6080 Manchester Rd Akron OH 44319",
    "addr:housenumber":"6080",
    "addr:postcode":"44319",
    "addr:street":"Manchester Rd",
    "iso:country":"US",
    "sg:address":"6080 Manchester Rd",
    "sg:city":"Akron",
    "sg:classifiers":[
        {
            "category":"Building & Trades",
            "subcategory":"Construction",
            "type":"Services"
        }
    ],
    "sg:phone":"+1 330 882 0840",
    "sg:postcode":"44319",
    "sg:province":"OH",
    "sg:tags":[
        "general",
        "contractor"
    ],
    "wof:name":"SEA Co",
    "wof:placetype":"venue"
},
  "geometry": {"coordinates":[-81.569446,40.939663],"type":"Point"}
}