{
  "type": "Feature",
  "properties": {
    "addr:full": "5671 Webster St Dayton OH 45414",
    "addr:housenumber": "5671",
    "addr:postcode": "45414",
    "addr:street": "Webster St",
    "iso:country": "US",
    "sg:address": "5671 Webster St",
    "sg:city": "Dayton",
    "sg:classifiers": [
      {
        "category": "Professional",
        "subcategory": "Art Services",
        "type": "Services"
      }
    ],
    "sg:phone": "+1 937 898 1117",
    "sg:postcode": "45414",
    "sg:province": "OH",
    "sg:tags": [
      "design",
      "typesetting"
    ],
    "wof:name": "Spectrum Printing \u0026 Design",
    "wof:placetype": "venue"
  },
  "geometry": {"coordinates":[-84.179663,39.82577],"type":"Point"}
}
