{
  "type": "Feature",
  "properties": {
    "addr:full":"25935 Detroit Rd Cleveland OH 44145",
    "addr:housenumber":"25935",
    "addr:postcode":"44145",
    "addr:street":"Detroit Rd",
    "iso:country":"US",
    "sg:address":"25935 Detroit Rd",
    "sg:city":"Cleveland",
    "sg:classifiers":[
        {
            "category":"Wholesale",
            "subcategory":"Stationery",
            "type":"Manufacturing & Wholesale Goods"
        }
    ],
    "sg:phone":"+1 440 899 0707",
    "sg:postcode":"44145",
    "sg:province":"OH",
    "sg:tags":[
        "mill",
        "paper",
        "broker",
        "representative"
    ],
    "wof:name":"Stora Enso",
    "wof:placetype":"venue"
},
  "geometry": {"coordinates":[-81.907083,41.469463],"type":"Point"}
}