{
  "type": "Feature",
  "properties": {
    "iso:country":"US",
    "sg:address":"3575 Maple Ave",
    "sg:city":"Zanesville",
    "sg:classifiers":[
        {
            "category":"Shopping",
            "subcategory":"Jewelry",
            "type":"Retail Goods"
        }
    ],
    "sg:phone":"+1 740 455 2978",
    "sg:postcode":"43701",
    "sg:province":"OH",
    "wof:name":"Lazarus-Macys Jewelry Dept",
    "wof:placetype":"venue"
},
  "geometry": {"coordinates":[-82.022252,39.986451],"type":"Point"}
}