{
  "type": "Feature",
  "properties": {
    "iso:country":"US",
    "sg:address":"161 Winder St",
    "sg:city":"North Lewisburg",
    "sg:classifiers":[
        {
            "category":"Education",
            "subcategory":"Library",
            "type":"Public Place"
        }
    ],
    "sg:phone":"+1 937 747 3043",
    "sg:postcode":"43060",
    "sg:province":"OH",
    "wof:name":"Champaign County Library",
    "wof:placetype":"venue"
},
  "geometry": {"coordinates":[-83.55871,40.227661],"type":"Point"}
}