{
  "type": "Feature",
  "properties": {
    "addr:full":"6081 Gender Rd Canal Winchester OH 43110",
    "addr:housenumber":"6081",
    "addr:postcode":"43110",
    "addr:street":"Gender Rd",
    "iso:country":"US",
    "sg:address":"6081 Gender Rd",
    "sg:city":"Canal Winchester",
    "sg:classifiers":[
        {
            "category":"Restaurant",
            "type":"Food & Drink"
        }
    ],
    "sg:menulink":"http://www.allmenus.com/oh/madison/200116-long-john-silvers/menu/",
    "sg:phone":"+1 614 920 9477",
    "sg:postcode":"43110",
    "sg:province":"OH",
    "sg:tags":[
        "seafood",
        "american"
    ],
    "wof:name":"Long John Silver's",
    "wof:placetype":"venue"
},
  "geometry": {"coordinates":[-82.828118,39.856335],"type":"Point"}
}