{
  "type": "Feature",
  "properties": {
    "addr:full":"38 N State St Westerville OH 43081",
    "addr:housenumber":"38",
    "addr:postcode":"43081",
    "addr:street":"N State St",
    "iso:country":"US",
    "sg:address":"38 N State St",
    "sg:city":"Westerville",
    "sg:classifiers":[
        {
            "category":"Home & Garden",
            "subcategory":"Furniture",
            "type":"Retail Goods"
        }
    ],
    "sg:phone":"+1 614 823 5549",
    "sg:postcode":"43081",
    "sg:province":"OH",
    "sg:website":"www.amishoriginals.com",
    "wof:name":"Amish Originals Furniture Co",
    "wof:placetype":"venue"
},
  "geometry": {"coordinates":[-82.932039,40.127231],"type":"Point"}
}