{
  "type": "Feature",
  "properties": {
    "iso:country":"US",
    "sg:address":"3649 Prospect Ave E",
    "sg:city":"Cleveland",
    "sg:classifiers":[
        {
            "category":"Real Estate",
            "subcategory":"Real Estate Agent",
            "type":"Services"
        }
    ],
    "sg:phone":"+1 216 426 1753",
    "sg:postcode":"44115",
    "sg:province":"OH",
    "wof:name":"Esmond Group Inc",
    "wof:placetype":"venue"
},
  "geometry": {"coordinates":[-81.658118,41.502233],"type":"Point"}
}