{
  "type": "Feature",
  "properties": {
    "addr:full": "290 Paul Copas Rd Winchester OH 45697",
    "addr:housenumber": "290",
    "addr:postcode": "45697",
    "addr:street": "Paul Copas Rd",
    "iso:country": "US",
    "sg:address": "290 Paul Copas Rd",
    "sg:city": "Winchester",
    "sg:classifiers": [
      {
        "category": "Farming",
        "subcategory": "Livestock Farm",
        "type": "Manufacturing \u0026 Wholesale Goods"
      }
    ],
    "sg:phone": "+1 937 386 2564",
    "sg:postcode": "45697",
    "sg:province": "OH",
    "sg:tags": [
      "beef",
      "feedlot",
      "cattle"
    ],
    "wof:name": "Norma Young",
    "wof:placetype": "venue"
  },
  "geometry": {"coordinates":[-83.54881,38.892717],"type":"Point"}
}
