{
  "type": "Feature",
  "properties": {
    "addr:full":"1200 E 2nd St Franklin OH 45005",
    "addr:housenumber":"1200",
    "addr:postcode":"45005",
    "addr:street":"E 2Nd St",
    "iso:country":"US",
    "sg:address":"1200 E 2nd St",
    "sg:city":"Franklin",
    "sg:classifiers":[
        {
            "category":"Banks & Credit Unions",
            "subcategory":"Investment Brokerage",
            "type":"Services"
        }
    ],
    "sg:phone":"+1 937 746 2545",
    "sg:postcode":"45005",
    "sg:province":"OH",
    "sg:tags":[
        "security"
    ],
    "sg:website":"www.edwardjones.com",
    "wof:name":"Edward Jones",
    "wof:placetype":"venue"
},
  "geometry": {"coordinates":[-84.27978400000001,39.563711],"type":"Point"}
}