{
  "type": "Feature",
  "properties": {
    "iso:country":"US",
    "sg:address":"4800 Wolf Rd",
    "sg:city":"Dayton",
    "sg:classifiers":[
        {
            "category":"Professional",
            "type":"Services"
        }
    ],
    "sg:phone":"+1 937 274 9002",
    "sg:postcode":"45416",
    "sg:province":"OH",
    "sg:tags":[
        "establishment"
    ],
    "wof:name":"Envirotest Systems Corp",
    "wof:placetype":"venue"
},
  "geometry": {"coordinates":[-84.254064,39.816129],"type":"Point"}
}