{
  "type": "Feature",
  "properties": {
    "addr:full":"11640 S State Line Rd Petersburg OH 44454",
    "addr:housenumber":"11640",
    "addr:postcode":"44454",
    "addr:street":"S State Line Rd",
    "iso:country":"US",
    "sg:address":"11640 S State Line Rd",
    "sg:city":"Petersburg",
    "sg:classifiers":[
        {
            "category":"Building & Trades",
            "subcategory":"Construction",
            "type":"Services"
        }
    ],
    "sg:phone":"+1 330 542 1100",
    "sg:postcode":"44454",
    "sg:province":"OH",
    "sg:tags":[
        "general",
        "contractor"
    ],
    "wof:name":"Excavation Technologies",
    "wof:placetype":"venue"
},
  "geometry": {"coordinates":[-80.519085,40.949083],"type":"Point"}
}