{
  "type": "Feature",
  "properties": {
    "addr:full": "4555 Lake Forest Dr Cincinnati OH 45242",
    "addr:housenumber": "4555",
    "addr:postcode": "45242",
    "addr:street": "Lake Forest Dr",
    "iso:country": "US",
    "sg:address": "4555 Lake Forest Dr",
    "sg:city": "Cincinnati",
    "sg:classifiers": [
      {
        "category": "Real Estate",
        "subcategory": "Real Estate Services",
        "type": "Services"
      }
    ],
    "sg:phone": "+1 513 563 3559",
    "sg:postcode": "45242",
    "sg:province": "OH",
    "sg:tags": [
      "company",
      "title"
    ],
    "wof:name": "Lakeside Title \u0026 Escrow Agcy",
    "wof:placetype": "venue"
  },
  "geometry": {"coordinates":[-84.37745,39.253512],"type":"Point"}
}
