{
  "type": "Feature",
  "properties": {
    "iso:country":"US",
    "sg:address":"4220 Windham Pl S",
    "sg:city":"Sandusky",
    "sg:classifiers":[
        {
            "category":"Professional",
            "type":"Services"
        }
    ],
    "sg:phone":"+1 419 621 9354",
    "sg:postcode":"44870",
    "sg:province":"OH",
    "sg:tags":[
        "establishment"
    ],
    "wof:name":"Fischer & Fischer",
    "wof:placetype":"venue"
},
  "geometry": {"coordinates":[-82.702376,41.405156],"type":"Point"}
}