{
  "type": "Feature",
  "properties": {
    "iso:country":"US",
    "sg:address":"9847 Pondside Ct",
    "sg:city":"Cincinnati",
    "sg:classifiers":[
        {
            "category":"Real Estate",
            "subcategory":"Real Estate Operator",
            "type":"Services"
        }
    ],
    "sg:phone":"+1 513 733 1388",
    "sg:postcode":"45241",
    "sg:province":"OH",
    "sg:tags":[
        "apartment"
    ],
    "wof:name":"Ryalke Apartments",
    "wof:placetype":"venue"
},
  "geometry": {"coordinates":[-84.413325,39.24524],"type":"Point"}
}