{
  "type": "Feature",
  "properties": {
    "addr:full": "9015 Fields Ertel Rd Cincinnati OH 45249",
    "addr:housenumber": "9015",
    "addr:postcode": "45249",
    "addr:street": "Fields Ertel Rd",
    "iso:country": "US",
    "sg:address": "9015 Fields Ertel Rd",
    "sg:city": "Cincinnati",
    "sg:classifiers": [
      {
        "category": "Banks \u0026 Credit Unions",
        "subcategory": "Bank",
        "type": "Services"
      }
    ],
    "sg:phone": "+1 513 677 2411",
    "sg:postcode": "45249",
    "sg:province": "OH",
    "sg:tags": [
      "national",
      "commercial"
    ],
    "wof:name": "First National Bank",
    "wof:placetype": "venue"
  },
  "geometry": {"coordinates":[-84.313213,39.292528],"type":"Point"}
}
