{
  "type": "Feature",
  "properties": {
    "iso:country":"US",
    "sg:address":"9015 Fields Ertel Rd",
    "sg:city":"Cincinnati",
    "sg:classifiers":[
        {
            "category":"Banks & Credit Unions",
            "subcategory":"Bank",
            "type":"Services"
        }
    ],
    "sg:phone":"+1 513 677 2411",
    "sg:postcode":"45249",
    "sg:province":"OH",
    "sg:tags":[
        "national",
        "commercial"
    ],
    "wof:name":"First National Bank",
    "wof:placetype":"venue"
},
  "geometry": {"coordinates":[-84.313213,39.292528],"type":"Point"}
}