{
  "type": "Feature",
  "properties": {
    "iso:country":"US",
    "sg:address":"121 E Erie Ave",
    "sg:city":"Lorain",
    "sg:classifiers":[
        {
            "category":"Real Estate",
            "subcategory":"Real Estate Operator",
            "type":"Services"
        }
    ],
    "sg:phone":"+1 440 288 3752",
    "sg:postcode":"44052",
    "sg:province":"OH",
    "sg:tags":[
        "apartment"
    ],
    "wof:name":"Gross Enterprises",
    "wof:placetype":"venue"
},
  "geometry": {"coordinates":[-82.174983,41.470314],"type":"Point"}
}