{
  "type": "Feature",
  "properties": {
    "iso:country":"US",
    "sg:address":"13315 Arlington Rd",
    "sg:city":"Norwalk",
    "sg:classifiers":[
        {
            "category":"Building & Trades",
            "subcategory":"Construction",
            "type":"Services"
        }
    ],
    "sg:phone":"+1 419 499 2954",
    "sg:postcode":"44857",
    "sg:province":"OH",
    "sg:tags":[
        "steel",
        "erection",
        "structural"
    ],
    "wof:name":"Assocted Stl Erectors Sheeters",
    "wof:placetype":"venue"
},
  "geometry": {"coordinates":[-82.535185,41.298227],"type":"Point"}
}