{
  "type": "Feature",
  "properties": {
    "addr:full": "34999 Mills Rd North Ridgeville OH 44039",
    "addr:housenumber": "34999",
    "addr:postcode": "44039",
    "addr:street": "Mills Rd",
    "iso:country": "US",
    "sg:address": "34999 Mills Rd",
    "sg:city": "North Ridgeville",
    "sg:classifiers": [
      {
        "category": "Professional",
        "type": "Services"
      }
    ],
    "sg:phone": "+1 440 353 1002",
    "sg:postcode": "44039",
    "sg:province": "OH",
    "wof:name": "Ken Tool",
    "wof:placetype": "venue"
  },
  "geometry": {"coordinates":[-82.006288,41.418743],"type":"Point"}
}
