{
  "type": "Feature",
  "properties": {
    "addr:full": "7576 Hamilton Ave Maineville OH 45039",
    "addr:housenumber": "7576",
    "addr:postcode": "45039",
    "addr:street": "Hamilton Ave",
    "iso:country": "US",
    "sg:address": "7576 Hamilton Ave",
    "sg:city": "Maineville",
    "sg:classifiers": [
      {
        "category": "Building \u0026 Trades",
        "subcategory": "Construction",
        "type": "Services"
      }
    ],
    "sg:phone": "+1 513 683 8709",
    "sg:postcode": "45039",
    "sg:province": "OH",
    "sg:tags": [
      "concrete",
      "contractor"
    ],
    "wof:name": "C \u0026 J Concrete",
    "wof:placetype": "venue"
  },
  "geometry": {"coordinates":[-84.235585,39.325757],"type":"Point"}
}
