{
  "type": "Feature",
  "properties": {
    "addr:full": "241 Barb Ct Heath OH 43056",
    "addr:housenumber": "241",
    "addr:postcode": "43056",
    "addr:street": "Barb Ct",
    "iso:country": "US",
    "sg:address": "241 Barb Ct",
    "sg:city": "Heath",
    "sg:classifiers": [
      {
        "category": "Building \u0026 Trades",
        "subcategory": "Construction",
        "type": "Services"
      }
    ],
    "sg:phone": "+1 740 404 5925",
    "sg:postcode": "43056",
    "sg:province": "OH",
    "sg:tags": [
      "painter"
    ],
    "wof:name": "Accu Pro Painters",
    "wof:placetype": "venue"
  },
  "geometry": {"coordinates":[-82.442571,40.017439],"type":"Point"}
}
