{
  "type": "Feature",
  "properties": {
    "addr:full": "8373 N State Rte 66 Defiance OH 43512",
    "addr:housenumber": "8373",
    "addr:postcode": "43512",
    "addr:street": "N State Rte 66",
    "iso:country": "US",
    "sg:address": "8373 N State Rte 66",
    "sg:city": "Defiance",
    "sg:classifiers": [
      {
        "category": "Autos \u0026 Motor Vehicles",
        "subcategory": "Motorcycle Sales",
        "type": "Retail Goods"
      }
    ],
    "sg:phone": "+1 419 782 4883",
    "sg:postcode": "43512",
    "sg:province": "OH",
    "sg:tags": [
      "snowmobile"
    ],
    "wof:name": "McCarthys",
    "wof:placetype": "venue"
  },
  "geometry": {"coordinates":[-84.360798,41.320208],"type":"Point"}
}
