{
  "type": "Feature",
  "properties": {
    "addr:full":"9846 W Salem Rd West Salem OH 44287",
    "addr:housenumber":"9846",
    "addr:postcode":"44287",
    "addr:street":"W Salem Rd",
    "iso:country":"US",
    "sg:address":"9846 W Salem Rd",
    "sg:city":"West Salem",
    "sg:phone":"+1 419 846 3892",
    "sg:postcode":"44287",
    "sg:province":"OH",
    "sg:tags":[
        "farm",
        "corn",
        "soybean"
    ],
    "wof:name":"Donald Bowman",
    "wof:placetype":"venue"
},
  "geometry": {"coordinates":[-82.070475,40.990942],"type":"Point"}
}