{
  "type": "Feature",
  "properties": {
    "addr:full": "747 Willow St Youngstown OH 44506",
    "addr:housenumber": "747",
    "addr:postcode": "44506",
    "addr:street": "Willow St",
    "iso:country": "US",
    "sg:address": "747 Willow St",
    "sg:city": "Youngstown",
    "sg:classifiers": [
      {
        "category": "Organizations",
        "subcategory": "Religious Organization",
        "type": "Services"
      }
    ],
    "sg:phone": "+1 330 743 5756",
    "sg:postcode": "44506",
    "sg:province": "OH",
    "sg:tags": [
      "church"
    ],
    "wof:name": "Morning Star Baptist Church",
    "wof:placetype": "venue"
  },
  "geometry": {"coordinates":[-80.634627,41.107201],"type":"Point"}
}
