{
  "type": "Feature",
  "properties": {
    "addr:full":"3939 Market Ave N Canton OH 44714",
    "addr:housenumber":"3939",
    "addr:postcode":"44714",
    "addr:street":"Market Ave N",
    "iso:country":"US",
    "sg:address":"3939 Market Ave N",
    "sg:city":"Canton",
    "sg:classifiers":[
        {
            "category":"Real Estate",
            "subcategory":"Real Estate Operator",
            "type":"Services"
        }
    ],
    "sg:phone":"+1 330 492 5335",
    "sg:postcode":"44714",
    "sg:province":"OH",
    "sg:tags":[
        "apartment"
    ],
    "wof:name":"Edgewater Development Corp",
    "wof:placetype":"venue"
},
  "geometry": {"coordinates":[-81.36556899999999,40.842217],"type":"Point"}
}