{
  "type": "Feature",
  "properties": {
    "addr:full": "345 S Chestnut St Jefferson OH 44047",
    "addr:housenumber": "345",
    "addr:postcode": "44047",
    "addr:street": "S Chestnut St",
    "iso:country": "US",
    "sg:address": "345 S Chestnut St",
    "sg:city": "Jefferson",
    "sg:classifiers": [
      {
        "category": "Banks \u0026 Credit Unions",
        "subcategory": "Bank",
        "type": "Services"
      }
    ],
    "sg:phone": "+1 440 576 4382",
    "sg:postcode": "44047",
    "sg:province": "OH",
    "sg:website": "www.lakeviewfcu.com",
    "wof:name": "Lakeview Federal Credit Union",
    "wof:placetype": "venue"
  },
  "geometry": {"coordinates":[-80.769523,41.730849],"type":"Point"}
}
