{
  "type": "Feature",
  "properties": {
    "iso:country":"US",
    "sg:address":"345 S Chestnut St",
    "sg:city":"Jefferson",
    "sg:classifiers":[
        {
            "category":"Banks & Credit Unions",
            "subcategory":"Bank",
            "type":"Services"
        }
    ],
    "sg:phone":"+1 440 576 4382",
    "sg:postcode":"44047",
    "sg:province":"OH",
    "sg:website":"www.lakeviewfcu.com",
    "wof:name":"Lakeview Federal Credit Union",
    "wof:placetype":"venue"
},
  "geometry": {"coordinates":[-80.76952300000001,41.730849],"type":"Point"}
}