{
  "type": "Feature",
  "properties": {
    "addr:full":"2015 Wal Mart Dr NE Warren OH 44483",
    "addr:housenumber":"2015",
    "addr:postcode":"44483",
    "addr:street":"Wal Mart Dr Ne",
    "iso:country":"US",
    "sg:address":"2015 Wal Mart Dr NE",
    "sg:city":"Warren",
    "sg:classifiers":[
        {
            "category":"Shopping",
            "subcategory":"Department Store",
            "type":"Retail Goods"
        }
    ],
    "sg:phone":"+1 330 372 1772",
    "sg:postcode":"44483",
    "sg:province":"OH",
    "sg:tags":[
        "discount"
    ],
    "wof:name":"Wal-Mart",
    "wof:placetype":"venue"
},
  "geometry": {"coordinates":[-80.780508,41.272928],"type":"Point"}
}