{
  "type": "Feature",
  "properties": {
    "iso:country":"US",
    "sg:address":"7913 State Rte 61",
    "sg:city":"Huron",
    "sg:classifiers":[
        {
            "category":"Building & Trades",
            "subcategory":"Construction",
            "type":"Services"
        }
    ],
    "sg:phone":"+1 419 433 5739",
    "sg:postcode":"44839",
    "sg:province":"OH",
    "sg:tags":[
        "heavy"
    ],
    "wof:name":"Irrigation Consultants",
    "wof:placetype":"venue"
},
  "geometry": {"coordinates":[-82.494183,41.368939],"type":"Point"}
}