{
  "type": "Feature",
  "properties": {
    "addr:full": "350 S B St Hamilton IN 45013",
    "addr:housenumber": "350",
    "addr:postcode": "45013",
    "addr:street": "S B St",
    "iso:country": "US",
    "sg:address": "350 S B St",
    "sg:city": "Hamilton",
    "sg:classifiers": [
      {
        "category": "Building \u0026 Trades",
        "subcategory": "Equipment Rental",
        "type": "Services"
      }
    ],
    "sg:phone": "+1 513 868 8665",
    "sg:postcode": "45013",
    "sg:province": "IN",
    "sg:tags": [
      "tool"
    ],
    "wof:name": "Hamilton Rental Ctr Inc",
    "wof:placetype": "venue"
  },
  "geometry": {"coordinates":[-84.570906,39.398975],"type":"Point"}
}
