{
  "type": "Feature",
  "properties": {
    "iso:country":"US",
    "sg:address":"350 S B St",
    "sg:city":"Hamilton",
    "sg:classifiers":[
        {
            "category":"Building & Trades",
            "subcategory":"Equipment Rental",
            "type":"Services"
        }
    ],
    "sg:phone":"+1 513 868 8665",
    "sg:postcode":"45013",
    "sg:province":"IN",
    "sg:tags":[
        "tool"
    ],
    "wof:name":"Hamilton Rental Ctr Inc",
    "wof:placetype":"venue"
},
  "geometry": {"coordinates":[-84.57090599999999,39.398975],"type":"Point"}
}