{
  "type": "Feature",
  "properties": {
    "addr:full":"38 S Fairgreen Dr Dayton OH 45416",
    "addr:housenumber":"38",
    "addr:postcode":"45416",
    "addr:street":"S Fairgreen Dr",
    "iso:country":"US",
    "sg:address":"38 S Fairgreen Dr",
    "sg:city":"Dayton",
    "sg:classifiers":[
        {
            "category":"Organizations",
            "subcategory":"Religious Organization",
            "type":"Services"
        }
    ],
    "sg:phone":"+1 937 278 3347",
    "sg:postcode":"45416",
    "sg:province":"OH",
    "sg:tags":[
        "church"
    ],
    "wof:name":"Living Hope Church",
    "wof:placetype":"venue"
},
  "geometry": {"coordinates":[-84.262006,39.807415],"type":"Point"}
}