{
  "type": "Feature",
  "properties": {
    "addr:full":"410 E 152nd St Cleveland OH 44110",
    "addr:housenumber":"410",
    "addr:postcode":"44110",
    "addr:street":"E 152Nd St",
    "iso:country":"US",
    "sg:address":"410 E 152nd St",
    "sg:city":"Cleveland",
    "sg:classifiers":[
        {
            "category":"Professional",
            "type":"Services"
        }
    ],
    "sg:phone":"+1 216 481 0312",
    "sg:postcode":"44110",
    "sg:province":"OH",
    "wof:name":"O H G R Team",
    "wof:placetype":"venue"
},
  "geometry": {"coordinates":[-81.57514999999999,41.57157],"type":"Point"}
}