{
  "type": "Feature",
  "properties": {
    "addr:full": "1023 Monroe Ave Cuyahoga Falls OH 44221",
    "addr:housenumber": "1023",
    "addr:postcode": "44221",
    "addr:street": "Monroe Ave",
    "iso:country": "US",
    "sg:address": "1023 Monroe Ave",
    "sg:city": "Cuyahoga Falls",
    "sg:classifiers": [
      {
        "category": "Home \u0026 Garden",
        "subcategory": "Household Appliances",
        "type": "Retail Goods"
      }
    ],
    "sg:phone": "+1 330 929 7311",
    "sg:postcode": "44221",
    "sg:province": "OH",
    "sg:tags": [
      "repair",
      "electrical"
    ],
    "wof:name": "Jpl \u0026 Asso",
    "wof:placetype": "venue"
  },
  "geometry": {"coordinates":[-81.495616,41.153242],"type":"Point"}
}
