{
  "type": "Feature",
  "properties": {
    "addr:full": "310 Main St Dover OH 44622",
    "addr:housenumber": "310",
    "addr:postcode": "44622",
    "addr:street": "Main St",
    "iso:country": "US",
    "sg:address": "310 Main St",
    "sg:city": "Dover",
    "sg:classifiers": [
      {
        "category": "Organizations",
        "subcategory": "Religious Organization",
        "type": "Services"
      }
    ],
    "sg:phone": "+1 330 602 7742",
    "sg:postcode": "44622",
    "sg:province": "OH",
    "sg:tags": [
      "church"
    ],
    "wof:name": "Community Christian Fellowship",
    "wof:placetype": "venue"
  },
  "geometry": {"coordinates":[-81.468139,40.51169],"type":"Point"}
}
