{
  "type": "Feature",
  "properties": {
    "addr:full":"716 S Prospect St Marion OH 43302",
    "addr:housenumber":"716",
    "addr:postcode":"43302",
    "addr:street":"S Prospect St",
    "iso:country":"US",
    "sg:address":"716 S Prospect St",
    "sg:city":"Marion",
    "sg:classifiers":[
        {
            "category":"Health Services",
            "subcategory":"Doctor",
            "type":"Services"
        }
    ],
    "sg:phone":"+1 740 387 5188",
    "sg:postcode":"43302",
    "sg:province":"OH",
    "wof:name":"Carroll C Conklin Jr DDS",
    "wof:placetype":"venue"
},
  "geometry": {"coordinates":[-83.13162800000001,40.576282],"type":"Point"}
}