{
  "type": "Feature",
  "properties": {
    "iso:country":"US",
    "sg:address":"4003 Broadway",
    "sg:city":"Grove City",
    "sg:classifiers":[
        {
            "category":"Shopping",
            "subcategory":"Hobbies, Toys, & Games",
            "type":"Retail Goods"
        }
    ],
    "sg:phone":"+1 614 875 6024",
    "sg:postcode":"43123",
    "sg:province":"OH",
    "sg:tags":[
        "craft"
    ],
    "wof:name":"Natural Pleasures",
    "wof:placetype":"venue"
},
  "geometry": {"coordinates":[-83.093548,39.882426],"type":"Point"}
}