{
  "type": "Feature",
  "properties": {
    "addr:full":"2317 Wick Campbell Rd Hubbard OH 44425",
    "addr:housenumber":"2317",
    "addr:postcode":"44425",
    "addr:street":"Wick Campbell Rd",
    "iso:country":"US",
    "sg:address":"2317 Wick Campbell Rd",
    "sg:city":"Hubbard",
    "sg:classifiers":[
        {
            "category":"Building & Trades",
            "subcategory":"Electrical",
            "type":"Services"
        }
    ],
    "sg:phone":"+1 330 568 0926",
    "sg:postcode":"44425",
    "sg:province":"OH",
    "sg:tags":[
        "electrical",
        "contractor"
    ],
    "wof:name":"AC Electric",
    "wof:placetype":"venue"
},
  "geometry": {"coordinates":[-80.59401200000001,41.180524],"type":"Point"}
}