{
  "type": "Feature",
  "properties": {
    "addr:full": "700 S Arlington St Akron OH 44306",
    "addr:housenumber": "700",
    "addr:postcode": "44306",
    "addr:street": "S Arlington St",
    "iso:country": "US",
    "sg:address": "700 S Arlington St",
    "sg:city": "Akron",
    "sg:classifiers": [
      {
        "category": "Restaurant",
        "type": "Food \u0026 Drink"
      }
    ],
    "sg:phone": "+1 330 724 7797",
    "sg:postcode": "44306",
    "sg:province": "OH",
    "sg:tags": [
      "eating"
    ],
    "sg:website": "www.churchs.com",
    "wof:name": "Church's Chicken",
    "wof:placetype": "venue"
  },
  "geometry": {"coordinates":[-81.491078,41.053388],"type":"Point"}
}
