{
  "type": "Feature",
  "properties": {
    "iso:country":"US",
    "sg:address":"700 S Arlington St",
    "sg:city":"Akron",
    "sg:classifiers":[
        {
            "category":"Restaurant",
            "type":"Food & Drink"
        }
    ],
    "sg:phone":"+1 330 724 7797",
    "sg:postcode":"44306",
    "sg:province":"OH",
    "sg:tags":[
        "eating"
    ],
    "sg:website":"www.churchs.com",
    "wof:name":"Church's Chicken",
    "wof:placetype":"venue"
},
  "geometry": {"coordinates":[-81.491078,41.053388],"type":"Point"}
}