{
  "type": "Feature",
  "properties": {
    "addr:full":"308 W Main St Barnesville OH 43713",
    "addr:housenumber":"308",
    "addr:postcode":"43713",
    "addr:street":"W Main St",
    "iso:country":"US",
    "sg:address":"308 W Main St",
    "sg:city":"Barnesville",
    "sg:classifiers":[
        {
            "category":"Education",
            "subcategory":"Library",
            "type":"Public Place"
        }
    ],
    "sg:phone":"+1 740 425 1651",
    "sg:postcode":"43713",
    "sg:province":"OH",
    "wof:name":"Hutton Memorial Public Library",
    "wof:placetype":"venue"
},
  "geometry": {"coordinates":[-81.180348,39.988531],"type":"Point"}
}