{
  "type": "Feature",
  "properties": {
    "iso:country":"US",
    "sg:address":"1700 Riverside Dr",
    "sg:city":"Sidney",
    "sg:classifiers":[
        {
            "category":"Freight",
            "type":"Transportation"
        }
    ],
    "sg:phone":"+1 937 492 2280",
    "sg:postcode":"45365",
    "sg:province":"OH",
    "sg:tags":[
        "operator",
        "local",
        "trucking"
    ],
    "wof:name":"D T Trucking LLC",
    "wof:placetype":"venue"
},
  "geometry": {"coordinates":[-84.136726,40.309314],"type":"Point"}
}