{
  "type": "Feature",
  "properties": {
    "addr:full":"4389 Stone Trace Ln Hamilton OH 45011",
    "addr:housenumber":"4389",
    "addr:postcode":"45011",
    "addr:street":"Stone Trace Ln",
    "iso:country":"US",
    "sg:address":"4389 Stone Trace Ln",
    "sg:city":"Hamilton",
    "sg:classifiers":[
        {
            "category":"Shopping",
            "subcategory":"Gifts & Souvenirs",
            "type":"Retail Goods"
        }
    ],
    "sg:phone":"+1 513 312 3440",
    "sg:postcode":"45011",
    "sg:province":"OH",
    "sg:tags":[
        "shop"
    ],
    "wof:name":"Obsidian Butterfly",
    "wof:placetype":"venue"
},
  "geometry": {"coordinates":[-84.472404,39.38506],"type":"Point"}
}