{
  "type": "Feature",
  "properties": {
    "iso:country":"US",
    "sg:address":"2828 Springboro Rd",
    "sg:city":"Dayton",
    "sg:classifiers":[
        {
            "category":"Retail",
            "subcategory":"Auto Repair",
            "type":"Services"
        }
    ],
    "sg:phone":"+1 937 297 1340",
    "sg:postcode":"45439",
    "sg:province":"OH",
    "sg:tags":[
        "wrecker"
    ],
    "wof:name":"Sandy's Garage",
    "wof:placetype":"venue"
},
  "geometry": {"coordinates":[-84.215598,39.715557],"type":"Point"}
}