{
  "type": "Feature",
  "properties": {
    "addr:full": "5370 Sullivant Ave Galloway OH 43119",
    "addr:housenumber": "5370",
    "addr:postcode": "43119",
    "addr:street": "Sullivant Ave",
    "iso:country": "US",
    "sg:address": "5370 Sullivant Ave",
    "sg:city": "Galloway",
    "sg:classifiers": [
      {
        "category": "Cinema",
        "subcategory": "Movie Rental",
        "type": "Entertainment"
      }
    ],
    "sg:phone": "+1 614 853 4970",
    "sg:postcode": "43119",
    "sg:province": "OH",
    "sg:tags": [
      "leasing",
      "video",
      "disc",
      "tape"
    ],
    "wof:name": "Family Video Movie Club Inc",
    "wof:placetype": "venue"
  },
  "geometry": {"coordinates":[-83.139153,39.94309],"type":"Point"}
}
