{
  "type": "Feature",
  "properties": {
    "iso:country":"US",
    "sg:address":"15751 Lisbon St NE",
    "sg:city":"Minerva",
    "sg:classifiers":[
        {
            "category":"Retail",
            "subcategory":"Auto Repair",
            "type":"Services"
        }
    ],
    "sg:phone":"+1 330 862 3838",
    "sg:postcode":"44657",
    "sg:province":"OH",
    "sg:tags":[
        "machine",
        "automobile",
        "shop"
    ],
    "wof:name":"Interstate Auto Glass",
    "wof:placetype":"venue"
},
  "geometry": {"coordinates":[-81.12161999999999,40.793478],"type":"Point"}
}