{
  "type": "Feature",
  "properties": {
    "addr:full":"17615 Horseshoe Bend Rd E Newcomerstown OH 43832",
    "addr:housenumber":"17615",
    "addr:postcode":"43832",
    "addr:street":"Horseshoe Bend Rd E",
    "iso:country":"US",
    "sg:address":"17615 Horseshoe Bend Rd E",
    "sg:city":"Newcomerstown",
    "sg:classifiers":[
        {
            "category":"Building & Trades",
            "subcategory":"Plumbing",
            "type":"Services"
        }
    ],
    "sg:phone":"+1 740 492 0811",
    "sg:postcode":"43832",
    "sg:province":"OH",
    "sg:tags":[
        "product",
        "management",
        "energy",
        "system"
    ],
    "wof:name":"North Coast Energy",
    "wof:placetype":"venue"
},
  "geometry": {"coordinates":[-81.462316,40.217362],"type":"Point"}
}