{
  "type": "Feature",
  "properties": {
    "addr:full": "1601 E David Rd Dayton OH 45429",
    "addr:housenumber": "1601",
    "addr:postcode": "45429",
    "addr:street": "E David Rd",
    "iso:country": "US",
    "sg:address": "1601 E David Rd",
    "sg:city": "Dayton",
    "sg:classifiers": [
      {
        "category": "Recreation",
        "type": "Entertainment"
      }
    ],
    "sg:phone": "+1 937 294 4032",
    "sg:postcode": "45429",
    "sg:province": "OH",
    "sg:tags": [
      "skating",
      "eating",
      "rink"
    ],
    "wof:name": "Skateworld Of Kettering",
    "wof:placetype": "venue"
  },
  "geometry": {"coordinates":[-84.139677,39.68121],"type":"Point"}
}
