{
  "type": "Feature",
  "properties": {
    "iso:country":"US",
    "sg:address":"1601 E David Rd",
    "sg:city":"Dayton",
    "sg:classifiers":[
        {
            "category":"Recreation",
            "type":"Entertainment"
        }
    ],
    "sg:phone":"+1 937 294 4032",
    "sg:postcode":"45429",
    "sg:province":"OH",
    "sg:tags":[
        "skating",
        "eating",
        "rink"
    ],
    "wof:name":"Skateworld Of Kettering",
    "wof:placetype":"venue"
},
  "geometry": {"coordinates":[-84.13967700000001,39.68121],"type":"Point"}
}