{
  "type": "Feature",
  "properties": {
    "iso:country":"US",
    "sg:address":"139 S 3rd St",
    "sg:city":"Coshocton",
    "sg:classifiers":[
        {
            "category":"Autos & Motor Vehicles",
            "subcategory":"Automobile Sales",
            "type":"Retail Goods"
        }
    ],
    "sg:phone":"+1 740 622 6079",
    "sg:postcode":"43812",
    "sg:province":"OH",
    "sg:tags":[
        "car",
        "used",
        "dealer"
    ],
    "wof:name":"Hilltop Auto Sales",
    "wof:placetype":"venue"
},
  "geometry": {"coordinates":[-81.86714000000001,40.273226],"type":"Point"}
}