{
  "type": "Feature",
  "properties": {
    "iso:country":"US",
    "sg:address":"1317 E 260th St",
    "sg:city":"Cleveland",
    "sg:classifiers":[
        {
            "category":"Wholesale",
            "subcategory":"Machinery & Supplies",
            "type":"Manufacturing & Wholesale Goods"
        }
    ],
    "sg:phone":"+1 216 732 9435",
    "sg:postcode":"44132",
    "sg:province":"OH",
    "sg:tags":[
        "gage"
    ],
    "wof:name":"Alves Precision Tool Co",
    "wof:placetype":"venue"
},
  "geometry": {"coordinates":[-81.502761,41.592896],"type":"Point"}
}