{
  "type": "Feature",
  "properties": {
    "addr:full":"6176 State Rte 162 E New London OH 44851",
    "addr:housenumber":"6176",
    "addr:postcode":"44851",
    "addr:street":"State Rte 162 E",
    "iso:country":"US",
    "sg:address":"6176 State Rte 162 E",
    "sg:city":"New London",
    "sg:classifiers":[
        {
            "category":"Recreation",
            "type":"Entertainment"
        }
    ],
    "sg:phone":"+1 419 929 1331",
    "sg:postcode":"44851",
    "sg:province":"OH",
    "sg:tags":[
        "martial",
        "arts",
        "instruction"
    ],
    "wof:name":"Hess's Martial Arts",
    "wof:placetype":"venue"
},
  "geometry": {"coordinates":[-82.363995,41.082671],"type":"Point"}
}