{
  "type": "Feature",
  "properties": {
    "addr:full": "2239 Dunzweiler Dr Zanesville OH 43701",
    "addr:housenumber": "2239",
    "addr:postcode": "43701",
    "addr:street": "Dunzweiler Dr",
    "iso:country": "US",
    "sg:address": "2239 Dunzweiler Dr",
    "sg:city": "Zanesville",
    "sg:classifiers": [
      {
        "category": "Building \u0026 Trades",
        "subcategory": "Construction",
        "type": "Services"
      }
    ],
    "sg:phone": "+1 740 452 8112",
    "sg:postcode": "43701",
    "sg:province": "OH",
    "sg:tags": [
      "excavation",
      "contractor"
    ],
    "wof:name": "Steve Zemba Excavating",
    "wof:placetype": "venue"
  },
  "geometry": {"coordinates":[-82.046142,39.974483],"type":"Point"}
}
