{
  "type": "Feature",
  "properties": {
    "addr:full": "424 Wards Corner Rd Loveland OH 45140",
    "addr:housenumber": "424",
    "addr:postcode": "45140",
    "addr:street": "Wards Corner Rd",
    "iso:country": "US",
    "sg:address": "424 Wards Corner Rd",
    "sg:city": "Loveland",
    "sg:classifiers": [
      {
        "category": "Shopping",
        "subcategory": "Computers \u0026 Home Electronics",
        "type": "Retail Goods"
      }
    ],
    "sg:phone": "+1 513 965 8030",
    "sg:postcode": "45140",
    "sg:province": "OH",
    "sg:tags": [
      "software"
    ],
    "sg:website": "www.attachmate.com",
    "wof:name": "Attachmate Corp",
    "wof:placetype": "venue"
  },
  "geometry": {"coordinates":[-84.289357,39.22058],"type":"Point"}
}
