{
  "type": "Feature",
  "properties": {
    "addr:full": "3648 Lincoln Way E Massillon OH 44646",
    "addr:housenumber": "3648",
    "addr:postcode": "44646",
    "addr:street": "Lincoln Way E",
    "iso:country": "US",
    "sg:address": "3648 Lincoln Way E",
    "sg:city": "Massillon",
    "sg:classifiers": [
      {
        "category": "Restaurant",
        "type": "Food \u0026 Drink"
      }
    ],
    "sg:phone": "+1 330 479 9879",
    "sg:postcode": "44646",
    "sg:province": "OH",
    "wof:name": "Lincoln Way Pizza",
    "wof:placetype": "venue"
  },
  "geometry": {"coordinates":[-81.463857,40.79447],"type":"Point"}
}
