{
  "type": "Feature",
  "properties": {
    "iso:country":"US",
    "sg:address":"3725 Mercer Auglaize County Line Rd",
    "sg:city":"New Bremen",
    "sg:classifiers":[
        {
            "category":"Shopping",
            "subcategory":"Bicycles & Sporting Goods",
            "type":"Retail Goods"
        }
    ],
    "sg:phone":"+1 419 629 2003",
    "sg:postcode":"45869",
    "sg:province":"OH",
    "sg:tags":[
        "gun",
        "gunsmith"
    ],
    "wof:name":"Hibbys Huntin Supplies",
    "wof:placetype":"venue"
},
  "geometry": {"coordinates":[-84.45505799999999,40.460791],"type":"Point"}
}