{
  "type": "Feature",
  "properties": {
    "addr:full": "3725 Mercer Auglaize County Line Rd New Bremen OH 45869",
    "addr:housenumber": "3725",
    "addr:postcode": "45869",
    "addr:street": "Mercer Auglaize County Line Rd",
    "iso:country": "US",
    "sg:address": "3725 Mercer Auglaize County Line Rd",
    "sg:city": "New Bremen",
    "sg:classifiers": [
      {
        "category": "Shopping",
        "subcategory": "Bicycles \u0026 Sporting Goods",
        "type": "Retail Goods"
      }
    ],
    "sg:phone": "+1 419 629 2003",
    "sg:postcode": "45869",
    "sg:province": "OH",
    "sg:tags": [
      "gun",
      "gunsmith"
    ],
    "wof:name": "Hibbys Huntin Supplies",
    "wof:placetype": "venue"
  },
  "geometry": {"coordinates":[-84.455058,40.460791],"type":"Point"}
}
