{
  "type": "Feature",
  "properties": {
    "addr:full":"13111 Fulton Rd Sidney OH 45365",
    "addr:housenumber":"13111",
    "addr:postcode":"45365",
    "addr:street":"Fulton Rd",
    "iso:country":"US",
    "sg:address":"13111 Fulton Rd",
    "sg:city":"Sidney",
    "sg:classifiers":[
        {
            "category":"Arts & Performance",
            "subcategory":"Theater",
            "type":"Entertainment"
        }
    ],
    "sg:phone":"+1 937 492 3963",
    "sg:postcode":"45365",
    "sg:province":"OH",
    "sg:tags":[
        "musician"
    ],
    "wof:name":"Big Muss Music Promotion",
    "wof:placetype":"venue"
},
  "geometry": {"coordinates":[-84.17576800000001,40.232977],"type":"Point"}
}