{
  "type": "Feature",
  "properties": {
    "addr:full": "657 N Woodhill Dr Amherst OH 44001",
    "addr:housenumber": "657",
    "addr:postcode": "44001",
    "addr:street": "N Woodhill Dr",
    "iso:country": "US",
    "sg:address": "657 N Woodhill Dr",
    "sg:city": "Amherst",
    "sg:classifiers": [
      {
        "category": "Professional",
        "type": "Services"
      }
    ],
    "sg:phone": "+1 440 988 9590",
    "sg:postcode": "44001",
    "sg:province": "OH",
    "wof:name": "Hugent Businesses",
    "wof:placetype": "venue"
  },
  "geometry": {"coordinates":[-82.215399,41.41124],"type":"Point"}
}
