{
  "type": "Feature",
  "properties": {
    "addr:full": "551 Barber Rd Barberton OH 44203",
    "addr:housenumber": "551",
    "addr:postcode": "44203",
    "addr:street": "Barber Rd",
    "iso:country": "US",
    "sg:address": "551 Barber Rd",
    "sg:city": "Barberton",
    "sg:classifiers": [
      {
        "category": "Government",
        "subcategory": "Office",
        "type": "Public Place"
      }
    ],
    "sg:phone": "+1 330 745 6914",
    "sg:postcode": "44203",
    "sg:province": "OH",
    "sg:tags": [
      "village"
    ],
    "wof:name": "City Of Barberton",
    "wof:placetype": "venue"
  },
  "geometry": {"coordinates":[-81.609286,41.024474],"type":"Point"}
}
