{
  "type": "Feature",
  "properties": {
    "iso:country":"US",
    "sg:address":"4168 Parkviewlake Dr",
    "sg:city":"Columbus",
    "sg:classifiers":[
        {
            "category":"Insurance",
            "subcategory":"Insurance Agent",
            "type":"Services"
        }
    ],
    "sg:phone":"+1 614 491 7700",
    "sg:postcode":"43207",
    "sg:province":"OH",
    "wof:name":"Jack P Holland & Associates",
    "wof:placetype":"venue"
},
  "geometry": {"coordinates":[-82.921668,39.882536],"type":"Point"}
}