{
  "type": "Feature",
  "properties": {
    "addr:full":"1825 Co Rd 32 Gibsonburg OH 43431",
    "addr:housenumber":"1825;32",
    "addr:postcode":"43431",
    "addr:street":"Co Rd",
    "iso:country":"US",
    "sg:address":"1825 Co Rd 32",
    "sg:city":"Gibsonburg",
    "sg:phone":"+1 419 637 2709",
    "sg:postcode":"43431",
    "sg:province":"OH",
    "sg:tags":[
        "farm",
        "wheat",
        "corn",
        "grain",
        "cash"
    ],
    "wof:name":"Schlea Randal",
    "wof:placetype":"venue"
},
  "geometry": {"coordinates":[-83.35823000000001,41.389665],"type":"Point"}
}