{
  "type": "Feature",
  "properties": {
    "addr:full":"2622 Sullivant Ave Columbus OH 43204",
    "addr:housenumber":"2622",
    "addr:postcode":"43204",
    "addr:street":"Sullivant Ave",
    "iso:country":"US",
    "sg:address":"2622 Sullivant Ave",
    "sg:city":"Columbus",
    "sg:classifiers":[
        {
            "category":"Organizations",
            "subcategory":"Religious Organization",
            "type":"Services"
        }
    ],
    "sg:phone":"+1 614 279 3686",
    "sg:postcode":"43204",
    "sg:province":"OH",
    "sg:tags":[
        "church"
    ],
    "wof:name":"Hilltop Seventh Day Adventist",
    "wof:placetype":"venue"
},
  "geometry": {"coordinates":[-83.069658,39.944318],"type":"Point"}
}