{
  "type": "Feature",
  "properties": {
    "addr:full": "1114 N Court St Medina OH 44256",
    "addr:housenumber": "1114",
    "addr:postcode": "44256",
    "addr:street": "N Court St",
    "iso:country": "US",
    "sg:address": "1114 N Court St",
    "sg:city": "Medina",
    "sg:classifiers": [
      {
        "category": "Professional",
        "subcategory": "Business Services",
        "type": "Services"
      }
    ],
    "sg:phone": "+1 330 667 2912",
    "sg:postcode": "44256",
    "sg:province": "OH",
    "sg:tags": [
      "drafting"
    ],
    "wof:name": "Crown Detailing \u0026 Design Inc",
    "wof:placetype": "venue"
  },
  "geometry": {"coordinates":[-81.862766,41.153574],"type":"Point"}
}
