{
  "type": "Feature",
  "properties": {
    "iso:country":"US",
    "sg:address":"1330 Mercy Dr NW",
    "sg:city":"Canton",
    "sg:classifiers":[
        {
            "category":"Health Services",
            "subcategory":"Doctor",
            "type":"Services"
        }
    ],
    "sg:phone":"+1 330 588 4840",
    "sg:postcode":"44708",
    "sg:province":"OH",
    "sg:tags":[
        "physician",
        "surgeon"
    ],
    "wof:name":"Linda Camp MD",
    "wof:placetype":"venue"
},
  "geometry": {"coordinates":[-81.396969,40.812453],"type":"Point"}
}