{
  "type": "Feature",
  "properties": {
    "iso:country":"US",
    "sg:address":"3910 Cleveland Ave",
    "sg:city":"Columbus",
    "sg:classifiers":[
        {
            "category":"Wholesale",
            "subcategory":"Auto Parts",
            "type":"Manufacturing & Wholesale Goods"
        }
    ],
    "sg:phone":"+1 614 470 9999",
    "sg:postcode":"43224",
    "sg:province":"OH",
    "sg:tags":[
        "tire",
        "supply"
    ],
    "wof:name":"Taz Used & New Tires",
    "wof:placetype":"venue"
},
  "geometry": {"coordinates":[-82.955083,40.047904],"type":"Point"}
}