{
  "type": "Feature",
  "properties": {
    "addr:full": "3910 Cleveland Ave Columbus OH 43224",
    "addr:housenumber": "3910",
    "addr:postcode": "43224",
    "addr:street": "Cleveland Ave",
    "iso:country": "US",
    "sg:address": "3910 Cleveland Ave",
    "sg:city": "Columbus",
    "sg:classifiers": [
      {
        "category": "Wholesale",
        "subcategory": "Auto Parts",
        "type": "Manufacturing \u0026 Wholesale Goods"
      }
    ],
    "sg:phone": "+1 614 470 9999",
    "sg:postcode": "43224",
    "sg:province": "OH",
    "sg:tags": [
      "tire",
      "supply"
    ],
    "wof:name": "Taz Used \u0026 New Tires",
    "wof:placetype": "venue"
  },
  "geometry": {"coordinates":[-82.955083,40.047904],"type":"Point"}
}
