{
  "type": "Feature",
  "properties": {
    "addr:full":"5991 Meijer Dr Milford OH 45150",
    "addr:housenumber":"5991",
    "addr:postcode":"45150",
    "addr:street":"Meijer Dr",
    "iso:country":"US",
    "sg:address":"5991 Meijer Dr",
    "sg:city":"Milford",
    "sg:classifiers":[
        {
            "category":"Health Services",
            "subcategory":"Medical Lab",
            "type":"Services"
        }
    ],
    "sg:phone":"+1 419 798 9999",
    "sg:postcode":"45150",
    "sg:province":"OH",
    "sg:tags":[
        "laboratory"
    ],
    "wof:name":"Gen Alysis Laboratory Inc",
    "wof:placetype":"venue"
},
  "geometry": {"coordinates":[-84.237111,39.195413],"type":"Point"}
}