{
  "type": "Feature",
  "properties": {
    "addr:full": "2810 Burnet Ave Cincinnati OH 45219",
    "addr:housenumber": "2810",
    "addr:postcode": "45219",
    "addr:street": "Burnet Ave",
    "iso:country": "US",
    "sg:address": "2810 Burnet Ave",
    "sg:city": "Cincinnati",
    "sg:classifiers": [
      {
        "category": "Social Services",
        "type": "Services"
      }
    ],
    "sg:phone": "+1 513 751 9200",
    "sg:postcode": "45219",
    "sg:province": "OH",
    "sg:tags": [
      "worker"
    ],
    "wof:name": "Joanne Lindy",
    "wof:placetype": "venue"
  },
  "geometry": {"coordinates":[-84.501254,39.132437],"type":"Point"}
}
