{
  "type": "Feature",
  "properties": {
    "addr:full": "1850 Belmore Rd Cleveland OH 44112",
    "addr:housenumber": "1850",
    "addr:postcode": "44112",
    "addr:street": "Belmore Rd",
    "iso:country": "US",
    "sg:address": "1850 Belmore Rd",
    "sg:city": "Cleveland",
    "sg:classifiers": [
      {
        "category": "Organizations",
        "subcategory": "Religious Organization",
        "type": "Services"
      }
    ],
    "sg:phone": "+1 216 249 0330",
    "sg:postcode": "44112",
    "sg:province": "OH",
    "sg:tags": [
      "church"
    ],
    "sg:website": "www.thelivingtruth.org",
    "wof:name": "Living Truth Ctr For Betr Livn",
    "wof:placetype": "venue"
  },
  "geometry": {"coordinates":[-81.583149,41.526128],"type":"Point"}
}
