{
  "type": "Feature",
  "properties": {
    "iso:country":"US",
    "sg:address":"1850 Belmore Rd",
    "sg:city":"Cleveland",
    "sg:classifiers":[
        {
            "category":"Organizations",
            "subcategory":"Religious Organization",
            "type":"Services"
        }
    ],
    "sg:phone":"+1 216 249 0330",
    "sg:postcode":"44112",
    "sg:province":"OH",
    "sg:tags":[
        "church"
    ],
    "sg:website":"www.thelivingtruth.org",
    "wof:name":"Living Truth Ctr For Betr Livn",
    "wof:placetype":"venue"
},
  "geometry": {"coordinates":[-81.58314900000001,41.526128],"type":"Point"}
}