{
  "type": "Feature",
  "properties": {
    "iso:country":"US",
    "sg:address":"4081 Essex Ct",
    "sg:city":"Powell",
    "sg:classifiers":[
        {
            "category":"Shopping",
            "subcategory":"Stationery & Office Supplies",
            "type":"Retail Goods"
        }
    ],
    "sg:phone":"+1 614 761 8004",
    "sg:postcode":"43065",
    "sg:province":"OH",
    "sg:tags":[
        "stationer"
    ],
    "wof:name":"Yours Truly Designs",
    "wof:placetype":"venue"
},
  "geometry": {"coordinates":[-83.098518,40.164951],"type":"Point"}
}