{
  "type": "Feature",
  "properties": {
    "addr:full":"1592 George Rd NE Lancaster OH 43130",
    "addr:housenumber":"1592",
    "addr:postcode":"43130",
    "addr:street":"George Rd Ne",
    "iso:country":"US",
    "sg:address":"1592 George Rd NE",
    "sg:city":"Lancaster",
    "sg:classifiers":[
        {
            "category":"Professional",
            "subcategory":"Business Services",
            "type":"Services"
        }
    ],
    "sg:phone":"+1 740 654 2104",
    "sg:postcode":"43130",
    "sg:province":"OH",
    "sg:tags":[
        "auctioneer"
    ],
    "wof:name":"B & B Auctions",
    "wof:placetype":"venue"
},
  "geometry": {"coordinates":[-82.53073999999999,39.744051],"type":"Point"}
}