{
  "type": "Feature",
  "properties": {
    "iso:country":"US",
    "sg:address":"8718 Mosswood Cir",
    "sg:city":"North Ridgeville",
    "sg:classifiers":[
        {
            "category":"Shopping",
            "subcategory":"Computers & Home Electronics",
            "type":"Retail Goods"
        }
    ],
    "sg:phone":"+1 440 748 1440",
    "sg:postcode":"44039",
    "sg:province":"OH",
    "sg:tags":[
        "software"
    ],
    "wof:name":"Sirius Computer Solutions Inc",
    "wof:placetype":"venue"
},
  "geometry": {"coordinates":[-81.97955,41.36738],"type":"Point"}
}