{
  "type": "Feature",
  "properties": {
    "iso:country":"US",
    "sg:address":"172 Belleview Ave",
    "sg:city":"Chillicothe",
    "sg:classifiers":[
        {
            "category":"Banks & Credit Unions",
            "subcategory":"Financial Services",
            "type":"Services"
        }
    ],
    "sg:phone":"+1 740 773 7776",
    "sg:postcode":"45601",
    "sg:province":"OH",
    "sg:tags":[
        "investor"
    ],
    "wof:name":"TS Troesters Ltd",
    "wof:placetype":"venue"
},
  "geometry": {"coordinates":[-82.986756,39.328941],"type":"Point"}
}