{
  "type": "Feature",
  "properties": {
    "addr:full": "172 Belleview Ave Chillicothe OH 45601",
    "addr:housenumber": "172",
    "addr:postcode": "45601",
    "addr:street": "Belleview Ave",
    "iso:country": "US",
    "sg:address": "172 Belleview Ave",
    "sg:city": "Chillicothe",
    "sg:classifiers": [
      {
        "category": "Banks \u0026 Credit Unions",
        "subcategory": "Financial Services",
        "type": "Services"
      }
    ],
    "sg:phone": "+1 740 773 7776",
    "sg:postcode": "45601",
    "sg:province": "OH",
    "sg:tags": [
      "investor"
    ],
    "wof:name": "TS Troesters Ltd",
    "wof:placetype": "venue"
  },
  "geometry": {"coordinates":[-82.986756,39.328941],"type":"Point"}
}
