{
  "type": "Feature",
  "properties": {
    "addr:full": "974 Crouse Chapel Rd Chillicothe OH 45601",
    "addr:housenumber": "974",
    "addr:postcode": "45601",
    "addr:street": "Crouse Chapel Rd",
    "iso:country": "US",
    "sg:address": "974 Crouse Chapel Rd",
    "sg:city": "Chillicothe",
    "sg:classifiers": [
      {
        "category": "Organizations",
        "subcategory": "Religious Organization",
        "type": "Services"
      }
    ],
    "sg:phone": "+1 740 642 4030",
    "sg:postcode": "45601",
    "sg:province": "OH",
    "sg:tags": [
      "church"
    ],
    "wof:name": "Voice Of Truth Connection",
    "wof:placetype": "venue"
  },
  "geometry": {"coordinates":[-82.960834,39.437007],"type":"Point"}
}
