{
  "type": "Feature",
  "properties": {
    "iso:country":"US",
    "sg:address":"4492 Mayfield Rd",
    "sg:city":"Cleveland",
    "sg:classifiers":[
        {
            "category":"Personal",
            "subcategory":"Beauty Salon",
            "type":"Services"
        }
    ],
    "sg:phone":"+1 216 382 6220",
    "sg:postcode":"44121",
    "sg:province":"OH",
    "wof:name":"Mirrorcles",
    "wof:placetype":"venue"
},
  "geometry": {"coordinates":[-81.518467,41.519891],"type":"Point"}
}