{
  "type": "Feature",
  "properties": {
    "iso:country":"US",
    "sg:address":"5279 Dellbrook Dr",
    "sg:city":"Fairfield",
    "sg:classifiers":[
        {
            "category":"Banks & Credit Unions",
            "subcategory":"Investment Brokerage",
            "type":"Services"
        }
    ],
    "sg:phone":"+1 513 858 2112",
    "sg:postcode":"45014",
    "sg:province":"OH",
    "sg:tags":[
        "advisory",
        "financial"
    ],
    "wof:name":"Lincoln Financial",
    "wof:placetype":"venue"
},
  "geometry": {"coordinates":[-84.577525,39.333998],"type":"Point"}
}