{
  "type": "Feature",
  "properties": {
    "addr:full": "2117 Darby Dr NE Massillon OH 44646",
    "addr:housenumber": "2117",
    "addr:postcode": "44646",
    "addr:street": "Darby Dr Ne",
    "iso:country": "US",
    "sg:address": "2117 Darby Dr NE",
    "sg:city": "Massillon",
    "sg:classifiers": [
      {
        "category": "Banks \u0026 Credit Unions",
        "subcategory": "Bank",
        "type": "Services"
      }
    ],
    "sg:phone": "+1 330 834 3470",
    "sg:postcode": "44646",
    "sg:province": "OH",
    "sg:tags": [
      "broker",
      "mortgage"
    ],
    "wof:name": "3t Mortage Corp",
    "wof:placetype": "venue"
  },
  "geometry": {"coordinates":[-81.508543,40.824247],"type":"Point"}
}
