{
  "type": "Feature",
  "properties": {
    "addr:full": "239 Marie Pl Perrysburg OH 43551",
    "addr:housenumber": "239",
    "addr:postcode": "43551",
    "addr:street": "Marie Pl",
    "iso:country": "US",
    "sg:address": "239 Marie Pl",
    "sg:city": "Perrysburg",
    "sg:classifiers": [
      {
        "category": "Home \u0026 Garden",
        "subcategory": "Building Materials",
        "type": "Retail Goods"
      }
    ],
    "sg:phone": "+1 419 874 2806",
    "sg:postcode": "43551",
    "sg:province": "OH",
    "sg:tags": [
      "door"
    ],
    "wof:name": "New Image Door Systems Inc",
    "wof:placetype": "venue"
  },
  "geometry": {"coordinates":[-83.62403,41.542085],"type":"Point"}
}
