{
  "type": "Feature",
  "properties": {
    "addr:full":"2432 Ridgeland Dr Avon OH 44011",
    "addr:housenumber":"2432",
    "addr:postcode":"44011",
    "addr:street":"Ridgeland Dr",
    "iso:country":"US",
    "sg:address":"2432 Ridgeland Dr",
    "sg:city":"Avon",
    "sg:classifiers":[
        {
            "category":"Wholesale",
            "subcategory":"Electrical",
            "type":"Manufacturing & Wholesale Goods"
        }
    ],
    "sg:phone":"+1 440 934 5268",
    "sg:postcode":"44011",
    "sg:province":"OH",
    "sg:tags":[
        "communication",
        "radio",
        "system"
    ],
    "sg:website":"www.vasucom.com",
    "wof:name":"Vasu Communications Inc",
    "wof:placetype":"venue"
},
  "geometry": {"coordinates":[-82.030873,41.462576],"type":"Point"}
}