{
  "type": "Feature",
  "properties": {
    "addr:full":"2393 Edgewater Blvd Youngstown OH 44514",
    "addr:housenumber":"2393",
    "addr:postcode":"44514",
    "addr:street":"Edgewater Blvd",
    "iso:country":"US",
    "sg:address":"2393 Edgewater Blvd",
    "sg:city":"Youngstown",
    "sg:classifiers":[
        {
            "category":"Professional",
            "type":"Services"
        }
    ],
    "sg:phone":"+1 330 757 7162",
    "sg:postcode":"44514",
    "sg:province":"OH",
    "wof:name":"Southwest Greens Of Ne Ohio",
    "wof:placetype":"venue"
},
  "geometry": {"coordinates":[-80.608656,41.035276],"type":"Point"}
}