{
  "type": "Feature",
  "properties": {
    "addr:full":"284 Berwin Pl Munroe Falls OH 44262",
    "addr:housenumber":"284",
    "addr:postcode":"44262",
    "addr:street":"Berwin Pl",
    "iso:country":"US",
    "sg:address":"284 Berwin Pl",
    "sg:city":"Munroe Falls",
    "sg:classifiers":[
        {
            "category":"Retail",
            "subcategory":"Portrait Studio",
            "type":"Services"
        }
    ],
    "sg:phone":"+1 330 688 8513",
    "sg:postcode":"44262",
    "sg:province":"OH",
    "sg:tags":[
        "photographer"
    ],
    "wof:name":"Tom Trainer Photography",
    "wof:placetype":"venue"
},
  "geometry": {"coordinates":[-81.427464,41.147525],"type":"Point"}
}