{
  "type": "Feature",
  "properties": {
    "addr:full": "119 Walnut Ct SW Warren OH 44483",
    "addr:housenumber": "119",
    "addr:postcode": "44483",
    "addr:street": "Walnut Ct Sw",
    "iso:country": "US",
    "sg:address": "119 Walnut Ct SW",
    "sg:city": "Warren",
    "sg:classifiers": [
      {
        "category": "Taxi",
        "type": "Transportation"
      }
    ],
    "sg:phone": "+1 330 743 7433",
    "sg:postcode": "44483",
    "sg:province": "OH",
    "sg:tags": [
      "taxicab"
    ],
    "wof:name": "Deluxe Cab",
    "wof:placetype": "venue"
  },
  "geometry": {"coordinates":[-80.81788,41.229646],"type":"Point"}
}
