{
  "type": "Feature",
  "properties": {
    "addr:full": "238 N Burgess Ave Columbus OH 43204",
    "addr:housenumber": "238",
    "addr:postcode": "43204",
    "addr:street": "N Burgess Ave",
    "iso:country": "US",
    "sg:address": "238 N Burgess Ave",
    "sg:city": "Columbus",
    "sg:classifiers": [
      {
        "category": "Real Estate",
        "subcategory": "Real Estate Agent",
        "type": "Services"
      }
    ],
    "sg:phone": "+1 614 272 2080",
    "sg:postcode": "43204",
    "sg:province": "OH",
    "wof:name": "Msl Property Management",
    "wof:placetype": "venue"
  },
  "geometry": {"coordinates":[-83.069931,39.959469],"type":"Point"}
}
