{
  "type": "Feature",
  "properties": {
    "addr:full":"3280 Ravine Pl Mason OH 45039",
    "addr:housenumber":"3280",
    "addr:postcode":"45039",
    "addr:street":"Ravine Pl",
    "iso:country":"US",
    "sg:address":"3280 Ravine Pl",
    "sg:city":"Mason",
    "sg:classifiers":[
        {
            "category":"Real Estate",
            "subcategory":"Real Estate Operator",
            "type":"Services"
        }
    ],
    "sg:phone":"+1 513 336 6768",
    "sg:postcode":"45039",
    "sg:province":"OH",
    "sg:tags":[
        "condominium"
    ],
    "wof:name":"Ravine At Timbers Edge",
    "wof:placetype":"venue"
},
  "geometry": {"coordinates":[-84.279112,39.33127],"type":"Point"}
}