{
  "type": "Feature",
  "properties": {
    "addr:full":"12511 Detroit Ave Cleveland OH 44107",
    "addr:housenumber":"12511",
    "addr:postcode":"44107",
    "addr:street":"Detroit Ave",
    "iso:country":"US",
    "sg:address":"12511 Detroit Ave",
    "sg:city":"Cleveland",
    "sg:classifiers":[
        {
            "category":"Retail",
            "subcategory":"Auto Repair",
            "type":"Services"
        }
    ],
    "sg:phone":"+1 216 521 0343",
    "sg:postcode":"44107",
    "sg:province":"OH",
    "sg:tags":[
        "repairing",
        "automobile"
    ],
    "wof:name":"Detroit Lakewood Automotive",
    "wof:placetype":"venue"
},
  "geometry": {"coordinates":[-81.775941,41.484173],"type":"Point"}
}