{
  "type": "Feature",
  "properties": {
    "addr:full":"25 S Ludlow St Dayton OH 45402",
    "addr:housenumber":"25",
    "addr:postcode":"45402",
    "addr:street":"S Ludlow St",
    "iso:country":"US",
    "sg:address":"25 S Ludlow St",
    "sg:city":"Dayton",
    "sg:classifiers":[
        {
            "category":"Restaurant",
            "type":"Food & Drink"
        }
    ],
    "sg:phone":"+1 937 222 7358",
    "sg:postcode":"45402",
    "sg:province":"OH",
    "sg:tags":[
        "drinking",
        "eating"
    ],
    "wof:name":"Moraine Embassy Inc",
    "wof:placetype":"venue"
},
  "geometry": {"coordinates":[-84.193378,39.758163],"type":"Point"}
}