{
  "type": "Feature",
  "properties": {
    "addr:full": "401 Wall St Tiffin OH 44883",
    "addr:housenumber": "401",
    "addr:postcode": "44883",
    "addr:street": "Wall St",
    "iso:country": "US",
    "sg:address": "401 Wall St",
    "sg:city": "Tiffin",
    "sg:classifiers": [
      {
        "category": "Manufacturing",
        "subcategory": "Motor Vehicles \u0026 Parts",
        "type": "Manufacturing \u0026 Wholesale Goods"
      }
    ],
    "sg:phone": "+1 419 447 4730",
    "sg:postcode": "44883",
    "sg:province": "OH",
    "sg:tags": [
      "mfg"
    ],
    "sg:website": "www.atlas-industries.com",
    "wof:name": "Atlas Industries Inc",
    "wof:placetype": "venue"
  },
  "geometry": {"coordinates":[-83.186849,41.126723],"type":"Point"}
}
