{
  "type": "Feature",
  "properties": {
    "iso:country":"US",
    "sg:address":"6851 Flags Center Dr",
    "sg:city":"Columbus",
    "sg:classifiers":[
        {
            "category":"Education",
            "subcategory":"Vocational School",
            "type":"Public Place"
        }
    ],
    "sg:phone":"+1 614 890 9971",
    "sg:postcode":"43229",
    "sg:province":"OH",
    "sg:tags":[
        "training",
        "computer"
    ],
    "sg:website":"www.webwiseseniors.com",
    "wof:name":"Web Wise Seniors",
    "wof:placetype":"venue"
},
  "geometry": {"coordinates":[-82.951275,40.109517],"type":"Point"}
}