{
  "type": "Feature",
  "properties": {
    "iso:country":"US",
    "sg:address":"5224 Settlement East Rd",
    "sg:city":"Shelby",
    "sg:classifiers":[
        {
            "category":"Building & Trades",
            "subcategory":"Construction",
            "type":"Services"
        }
    ],
    "sg:phone":"+1 419 347 6509",
    "sg:postcode":"44875",
    "sg:province":"OH",
    "sg:tags":[
        "general",
        "commercial",
        "contractor"
    ],
    "wof:name":"James P Finnegan Construction",
    "wof:placetype":"venue"
},
  "geometry": {"coordinates":[-82.702254,40.83602],"type":"Point"}
}