{
  "type": "Feature",
  "properties": {
    "addr:full": "1145 W Pleasant Valley Rd Cleveland OH 44134",
    "addr:housenumber": "1145",
    "addr:postcode": "44134",
    "addr:street": "W Pleasant Valley Rd",
    "iso:country": "US",
    "sg:address": "1145 W Pleasant Valley Rd",
    "sg:city": "Cleveland",
    "sg:classifiers": [
      {
        "category": "Manufacturing",
        "subcategory": "Chemicals \u0026 Compounds",
        "type": "Manufacturing \u0026 Wholesale Goods"
      },
      {
        "category": "Shopping",
        "subcategory": "Beauty \u0026 Cosmetics",
        "type": "Retail Goods"
      }
    ],
    "sg:phone": "+1 440 845 0233",
    "sg:postcode": "44134",
    "sg:province": "OH",
    "sg:tags": [
      "toilet",
      "mfg",
      "prep",
      "merchandise",
      "perfume"
    ],
    "wof:name": "Kristine Marie's Olfactorium",
    "wof:placetype": "venue"
  },
  "geometry": {"coordinates":[-81.688041,41.36142],"type":"Point"}
}
