{
  "type": "Feature",
  "properties": {
    "iso:country":"US",
    "sg:address":"3560 S Main St",
    "sg:city":"Middletown",
    "sg:classifiers":[
        {
            "category":"Wholesale",
            "subcategory":"Machinery & Supplies",
            "type":"Manufacturing & Wholesale Goods"
        }
    ],
    "sg:phone":"+1 513 420 9400",
    "sg:postcode":"45044",
    "sg:province":"OH",
    "sg:tags":[
        "salon",
        "beauty"
    ],
    "wof:name":"Decca Plus",
    "wof:placetype":"venue"
},
  "geometry": {"coordinates":[-84.42016,39.477678],"type":"Point"}
}