{
  "type": "Feature",
  "properties": {
    "iso:country":"US",
    "sg:address":"37567 Stoney Lake Dr",
    "sg:city":"North Ridgeville",
    "sg:classifiers":[
        {
            "category":"Building & Trades",
            "subcategory":"Construction",
            "type":"Services"
        }
    ],
    "sg:phone":"+1 440 327 7464",
    "sg:postcode":"44039",
    "sg:province":"OH",
    "sg:tags":[
        "home",
        "builder"
    ],
    "wof:name":"Ryan Homes",
    "wof:placetype":"venue"
},
  "geometry": {"coordinates":[-82.042614,41.408562],"type":"Point"}
}