{
  "type": "Feature",
  "properties": {
    "addr:full": "3108 Deforest Rd SE Warren OH 44484",
    "addr:housenumber": "3108",
    "addr:postcode": "44484",
    "addr:street": "Deforest Rd Se",
    "iso:country": "US",
    "sg:address": "3108 Deforest Rd SE",
    "sg:city": "Warren",
    "sg:classifiers": [
      {
        "category": "Building \u0026 Trades",
        "subcategory": "Construction",
        "type": "Services"
      }
    ],
    "sg:phone": "+1 330 369 1689",
    "sg:postcode": "44484",
    "sg:province": "OH",
    "sg:tags": [
      "maintenance",
      "contractor"
    ],
    "wof:name": "Atlas Maintenance",
    "wof:placetype": "venue"
  },
  "geometry": {"coordinates":[-80.781889,41.203155],"type":"Point"}
}
