{
  "type": "Feature",
  "properties": {
    "iso:country":"US",
    "sg:address":"3108 Deforest Rd SE",
    "sg:city":"Warren",
    "sg:classifiers":[
        {
            "category":"Building & Trades",
            "subcategory":"Construction",
            "type":"Services"
        }
    ],
    "sg:phone":"+1 330 369 1689",
    "sg:postcode":"44484",
    "sg:province":"OH",
    "sg:tags":[
        "maintenance",
        "contractor"
    ],
    "wof:name":"Atlas Maintenance",
    "wof:placetype":"venue"
},
  "geometry": {"coordinates":[-80.78188900000001,41.203155],"type":"Point"}
}