{
  "type": "Feature",
  "properties": {
    "addr:full": "2626 Lewis Center Rd Lewis Center OH 43035",
    "addr:housenumber": "2626",
    "addr:postcode": "43035",
    "addr:street": "Lewis Center Rd",
    "iso:country": "US",
    "sg:address": "2626 Lewis Center Rd",
    "sg:city": "Lewis Center",
    "sg:classifiers": [
      {
        "category": "Utilities",
        "subcategory": "Natural Gas",
        "type": "Services"
      }
    ],
    "sg:phone": "+1 740 548 2450",
    "sg:postcode": "43035",
    "sg:province": "OH",
    "sg:tags": [
      "distribution",
      "company"
    ],
    "sg:website": "www.sngco.com",
    "wof:name": "Suburban Natural Gas Company",
    "wof:placetype": "venue"
  },
  "geometry": {"coordinates":[-83.005758,40.199229],"type":"Point"}
}
