{
  "type": "Feature",
  "properties": {
    "addr:full":"3120 Homeward Way Fairfield OH 45014",
    "addr:housenumber":"3120",
    "addr:postcode":"45014",
    "addr:street":"Homeward Way",
    "iso:country":"US",
    "sg:address":"3120 Homeward Way",
    "sg:city":"Fairfield",
    "sg:classifiers":[
        {
            "category":"Professional",
            "subcategory":"Management & Consulting",
            "type":"Services"
        }
    ],
    "sg:phone":"+1 513 942 6625",
    "sg:postcode":"45014",
    "sg:province":"OH",
    "sg:tags":[
        "fuel"
    ],
    "wof:name":"Facility Management Svc",
    "wof:placetype":"venue"
},
  "geometry": {"coordinates":[-84.505638,39.327979],"type":"Point"}
}