{
  "type": "Feature",
  "properties": {
    "addr:full": "27970 Chagrin Blvd Cleveland OH 44122",
    "addr:housenumber": "27970",
    "addr:postcode": "44122",
    "addr:street": "Chagrin Blvd",
    "iso:country": "US",
    "sg:address": "27970 Chagrin Blvd",
    "sg:city": "Cleveland",
    "sg:classifiers": [
      {
        "category": "Personal",
        "subcategory": "Beauty Salon",
        "type": "Services"
      }
    ],
    "sg:phone": "+1 216 292 4247",
    "sg:postcode": "44122",
    "sg:province": "OH",
    "wof:name": "D'Maz Lifestyle Salon Inc",
    "wof:placetype": "venue"
  },
  "geometry": {"coordinates":[-81.481374,41.462267],"type":"Point"}
}
