{
  "type": "Feature",
  "properties": {
    "iso:country":"US",
    "sg:address":"28833 Euclid Ave",
    "sg:city":"Wickliffe",
    "sg:classifiers":[
        {
            "category":"Banks & Credit Unions",
            "subcategory":"Bank",
            "type":"Services"
        }
    ],
    "sg:phone":"+1 440 516 0452",
    "sg:postcode":"44092",
    "sg:province":"OH",
    "sg:tags":[
        "loan",
        "real estate"
    ],
    "wof:name":"Money Management Financial",
    "wof:placetype":"venue"
},
  "geometry": {"coordinates":[-81.4835,41.599499],"type":"Point"}
}