{
  "type": "Feature",
  "properties": {
    "addr:full":"707 N 5th St Fremont OH 43420",
    "addr:housenumber":"707",
    "addr:postcode":"43420",
    "addr:street":"N 5Th St",
    "iso:country":"US",
    "sg:address":"707 N 5th St",
    "sg:city":"Fremont",
    "sg:classifiers":[
        {
            "category":"Manufacturing",
            "subcategory":"Tools & Machinery",
            "type":"Manufacturing & Wholesale Goods"
        }
    ],
    "sg:phone":"+1 419 332 3996",
    "sg:postcode":"43420",
    "sg:province":"OH",
    "sg:tags":[
        "industrial",
        "mfg"
    ],
    "wof:name":"Hoffman Machining & Repair LLC",
    "wof:placetype":"venue"
},
  "geometry": {"coordinates":[-83.097168,41.353709],"type":"Point"}
}