{
  "type": "Feature",
  "properties": {
    "iso:country":"US",
    "sg:address":"4020 Shields Rd",
    "sg:city":"Arcanum",
    "sg:phone":"+1 937 548 7237",
    "sg:postcode":"45304",
    "sg:province":"OH",
    "sg:tags":[
        "farm",
        "wheat",
        "soybean"
    ],
    "wof:name":"Wanda Reck",
    "wof:placetype":"venue"
},
  "geometry": {"coordinates":[-84.569283,40.033166],"type":"Point"}
}