{
  "type": "Feature",
  "properties": {
    "addr:full":"210 S Walnut St Ravenna OH 44266",
    "addr:housenumber":"210",
    "addr:postcode":"44266",
    "addr:street":"S Walnut St",
    "iso:country":"US",
    "sg:address":"210 S Walnut St",
    "sg:city":"Ravenna",
    "sg:classifiers":[
        {
            "category":"Shopping",
            "subcategory":"Used Merchandise",
            "type":"Retail Goods"
        }
    ],
    "sg:phone":"+1 330 296 5657",
    "sg:postcode":"44266",
    "sg:province":"OH",
    "sg:tags":[
        "antique"
    ],
    "wof:name":"Harold's Old Fashion Carpet",
    "wof:placetype":"venue"
},
  "geometry": {"coordinates":[-81.239941,41.157399],"type":"Point"}
}