{
  "type": "Feature",
  "properties": {
    "iso:country":"US",
    "sg:address":"400 Crystal Ave",
    "sg:city":"Findlay",
    "sg:classifiers":[
        {
            "category":"Manufacturing",
            "subcategory":"Wood Products",
            "type":"Manufacturing & Wholesale Goods"
        }
    ],
    "sg:phone":"+1 419 425 9889",
    "sg:postcode":"45840",
    "sg:province":"OH",
    "sg:tags":[
        "preserving",
        "container",
        "mfg"
    ],
    "wof:name":"Clark Rm Inc",
    "wof:placetype":"venue"
},
  "geometry": {"coordinates":[-83.642485,41.052298],"type":"Point"}
}