{
  "type": "Feature",
  "properties": {
    "iso:country":"US",
    "sg:address":"151 W 2nd St",
    "sg:city":"Chillicothe",
    "sg:classifiers":[
        {
            "category":"Organizations",
            "subcategory":"Religious Organization",
            "type":"Services"
        }
    ],
    "sg:phone":"+1 740 774 1265",
    "sg:postcode":"45601",
    "sg:province":"OH",
    "sg:tags":[
        "church"
    ],
    "sg:website":"www.spirituality.com",
    "wof:name":"Christian Science Society",
    "wof:placetype":"venue"
},
  "geometry": {"coordinates":[-82.986901,39.333883],"type":"Point"}
}