{
  "type": "Feature",
  "properties": {
    "addr:full": "9905 Slough Rd Canal Winchester OH 43110",
    "addr:housenumber": "9905",
    "addr:postcode": "43110",
    "addr:street": "Slough Rd",
    "iso:country": "US",
    "sg:address": "9905 Slough Rd",
    "sg:city": "Canal Winchester",
    "sg:classifiers": [
      {
        "category": "Organizations",
        "subcategory": "Religious Organization",
        "type": "Services"
      }
    ],
    "sg:phone": "+1 614 837 1832",
    "sg:postcode": "43110",
    "sg:province": "OH",
    "wof:name": "Vocal Point",
    "wof:placetype": "venue"
  },
  "geometry": {"coordinates":[-82.783307,39.804301],"type":"Point"}
}
