{
  "type": "Feature",
  "properties": {
    "addr:full":"1025 S Main St Bowling Green OH 43402",
    "addr:housenumber":"1025",
    "addr:postcode":"43402",
    "addr:street":"S Main St",
    "iso:country":"US",
    "sg:address":"1025 S Main St",
    "sg:city":"Bowling Green",
    "sg:classifiers":[
        {
            "category":"Autos & Motor Vehicles",
            "subcategory":"Auto Supplies",
            "type":"Retail Goods"
        }
    ],
    "sg:phone":"+1 419 352 2008",
    "sg:postcode":"43402",
    "sg:province":"OH",
    "sg:tags":[
        "automobile",
        "parts"
    ],
    "wof:name":"Advance Auto Parts Inc",
    "wof:placetype":"venue"
},
  "geometry": {"coordinates":[-83.650357,41.358944],"type":"Point"}
}