{
  "type": "Feature",
  "properties": {
    "addr:full": "762 Bev Rd Youngstown OH 44512",
    "addr:housenumber": "762",
    "addr:postcode": "44512",
    "addr:street": "Bev Rd",
    "iso:country": "US",
    "sg:address": "762 Bev Rd",
    "sg:city": "Youngstown",
    "sg:classifiers": [
      {
        "category": "Building \u0026 Trades",
        "subcategory": "Construction",
        "type": "Services"
      }
    ],
    "sg:phone": "+1 330 629 9788",
    "sg:postcode": "44512",
    "sg:province": "OH",
    "sg:tags": [
      "maker",
      "cabinet"
    ],
    "wof:name": "Joseph Sylvester Constr Co",
    "wof:placetype": "venue"
  },
  "geometry": {"coordinates":[-80.64149,40.993485],"type":"Point"}
}
