{
  "type": "Feature",
  "properties": {
    "iso:country":"US",
    "sg:address":"715 Hodapp Ave",
    "sg:city":"Dayton",
    "sg:classifiers":[
        {
            "category":"Building & Trades",
            "subcategory":"Construction",
            "type":"Services"
        }
    ],
    "sg:phone":"+1 937 258 8268",
    "sg:postcode":"45410",
    "sg:province":"OH",
    "sg:tags":[
        "contractor"
    ],
    "wof:name":"Honious Exteriors",
    "wof:placetype":"venue"
},
  "geometry": {"coordinates":[-84.151399,39.748961],"type":"Point"}
}