{
  "type": "Feature",
  "properties": {
    "iso:country":"US",
    "sg:address":"6324 E Law Rd",
    "sg:city":"Valley City",
    "sg:classifiers":[
        {
            "category":"Building & Trades",
            "subcategory":"Landscaping Services",
            "type":"Services"
        }
    ],
    "sg:phone":"+1 330 483 4621",
    "sg:postcode":"44280",
    "sg:province":"OH",
    "sg:tags":[
        "landscape"
    ],
    "wof:name":"Brandon Stricklett",
    "wof:placetype":"venue"
},
  "geometry": {"coordinates":[-81.912337,41.222791],"type":"Point"}
}