{
  "type": "Feature",
  "properties": {
    "addr:full": "6324 E Law Rd Valley City OH 44280",
    "addr:housenumber": "6324",
    "addr:postcode": "44280",
    "addr:street": "E Law Rd",
    "iso:country": "US",
    "sg:address": "6324 E Law Rd",
    "sg:city": "Valley City",
    "sg:classifiers": [
      {
        "category": "Building \u0026 Trades",
        "subcategory": "Landscaping Services",
        "type": "Services"
      }
    ],
    "sg:phone": "+1 330 483 4621",
    "sg:postcode": "44280",
    "sg:province": "OH",
    "sg:tags": [
      "landscape"
    ],
    "wof:name": "Brandon Stricklett",
    "wof:placetype": "venue"
  },
  "geometry": {"coordinates":[-81.912337,41.222791],"type":"Point"}
}
