{
  "type": "Feature",
  "properties": {
    "addr:full": "19153 Cadiz Rd Lore City OH 43755",
    "addr:postcode": "19153;43755",
    "addr:street": "Cadiz Rd",
    "iso:country": "US",
    "sg:address": "19153 Cadiz Rd",
    "sg:city": "Lore City",
    "sg:classifiers": [
      {
        "category": "Education",
        "subcategory": "School",
        "type": "Public Place"
      }
    ],
    "sg:phone": "+1 740 489 5041",
    "sg:postcode": "43755",
    "sg:province": "OH",
    "wof:name": "Madison Elementary School",
    "wof:placetype": "venue"
  },
  "geometry": {"coordinates":[-81.377336,40.10559],"type":"Point"}
}
