{
  "type": "Feature",
  "properties": {
    "iso:country":"US",
    "sg:address":"8886 E Market St",
    "sg:city":"Warren",
    "sg:classifiers":[
        {
            "category":"Banks & Credit Unions",
            "subcategory":"Bank",
            "type":"Services"
        }
    ],
    "sg:phone":"+1 330 856 9085",
    "sg:postcode":"44484",
    "sg:province":"OH",
    "sg:tags":[
        "personal",
        "institution"
    ],
    "wof:name":"Redmond & Associates",
    "wof:placetype":"venue"
},
  "geometry": {"coordinates":[-80.729286,41.237796],"type":"Point"}
}