{
  "type": "Feature",
  "properties": {
    "addr:full": "881 Mount Vernon Ave Columbus OH 43203",
    "addr:housenumber": "881",
    "addr:postcode": "43203",
    "addr:street": "Mount Vernon Ave",
    "iso:country": "US",
    "sg:address": "881 Mount Vernon Ave",
    "sg:city": "Columbus",
    "sg:classifiers": [
      {
        "category": "Bars \u0026 Pubs",
        "type": "Food \u0026 Drink"
      }
    ],
    "sg:phone": "+1 614 258 2995",
    "sg:postcode": "43203",
    "sg:province": "OH",
    "sg:tags": [
      "drinking"
    ],
    "wof:name": "Diva Den",
    "wof:placetype": "venue"
  },
  "geometry": {"coordinates":[-82.978642,39.971107],"type":"Point"}
}
