{
  "type": "Feature",
  "properties": {
    "addr:full": "642 E Main St St Henry OH 45883",
    "addr:housenumber": "642",
    "addr:postcode": "45883",
    "addr:street": "E Main St St",
    "iso:country": "US",
    "sg:address": "642 E Main St",
    "sg:city": "St Henry",
    "sg:classifiers": [
      {
        "category": "Personal",
        "subcategory": "Barber",
        "type": "Services"
      }
    ],
    "sg:phone": "+1 419 678 4414",
    "sg:postcode": "45883",
    "sg:province": "OH",
    "wof:name": "J \u0026 J Cutting Edge",
    "wof:placetype": "venue"
  },
  "geometry": {"coordinates":[-84.631405,40.417646],"type":"Point"}
}
