{
  "type": "Feature",
  "properties": {
    "addr:full": "86427 Black Rd Hopedale OH 43986",
    "addr:housenumber": "86427",
    "addr:postcode": "43986",
    "addr:street": "Black Rd",
    "iso:country": "US",
    "sg:address": "86427 Black Rd",
    "sg:city": "Hopedale",
    "sg:classifiers": [
      {
        "category": "Wholesale",
        "subcategory": "Petroleum",
        "type": "Manufacturing \u0026 Wholesale Goods"
      }
    ],
    "sg:phone": "+1 740 937 2300",
    "sg:postcode": "43986",
    "sg:province": "OH",
    "sg:tags": [
      "pipe",
      "line",
      "company"
    ],
    "wof:name": "Allegheny Pipeline Co",
    "wof:placetype": "venue"
  },
  "geometry": {"coordinates":[-80.924999,40.34413],"type":"Point"}
}
