{
  "type": "Feature",
  "properties": {
    "iso:country":"US",
    "sg:address":"3116 W 38th St",
    "sg:city":"Cleveland",
    "sg:classifiers":[
        {
            "category":"Shopping",
            "subcategory":"Florist",
            "type":"Retail Goods"
        }
    ],
    "sg:phone":"+1 216 281 6109",
    "sg:postcode":"44109",
    "sg:province":"OH",
    "wof:name":"Crystals Boutique",
    "wof:placetype":"venue"
},
  "geometry": {"coordinates":[-81.710339,41.469295],"type":"Point"}
}