{
  "type": "Feature",
  "properties": {
    "addr:full": "13118 State Rte 31 Kenton OH 43326",
    "addr:housenumber": "13118",
    "addr:postcode": "43326",
    "addr:street": "State Rte 31",
    "iso:country": "US",
    "sg:address": "13118 State Rte 31",
    "sg:city": "Kenton",
    "sg:classifiers": [
      {
        "category": "Wholesale",
        "subcategory": "Farm Supplies",
        "type": "Manufacturing \u0026 Wholesale Goods"
      }
    ],
    "sg:phone": "+1 419 674 4045",
    "sg:postcode": "43326",
    "sg:province": "OH",
    "wof:name": "Grain Center",
    "wof:placetype": "venue"
  },
  "geometry": {"coordinates":[-83.598998,40.630311],"type":"Point"}
}
