{
  "type": "Feature",
  "properties": {
    "iso:country":"US",
    "sg:address":"8054 Darrow Rd",
    "sg:city":"Twinsburg",
    "sg:classifiers":[
        {
            "category":"Recreation",
            "type":"Entertainment"
        }
    ],
    "sg:phone":"+1 330 425 8800",
    "sg:postcode":"44087",
    "sg:province":"OH",
    "sg:tags":[
        "course",
        "eating",
        "public",
        "golf"
    ],
    "wof:name":"Fore Seasons Indoor Golf",
    "wof:placetype":"venue"
},
  "geometry": {"coordinates":[-81.440522,41.285736],"type":"Point"}
}