{
  "type": "Feature",
  "properties": {
    "addr:full": "7960 Ohio River Rd Wheelersburg OH 45694",
    "addr:housenumber": "7960",
    "addr:postcode": "45694",
    "addr:street": "Ohio River Rd",
    "iso:country": "US",
    "sg:address": "7960 Ohio River Rd",
    "sg:city": "Wheelersburg",
    "sg:classifiers": [
      {
        "category": "Personal",
        "subcategory": "Tanning Parlor",
        "type": "Services"
      }
    ],
    "sg:phone": "+1 740 574 0544",
    "sg:postcode": "45694",
    "sg:province": "OH",
    "sg:tags": [
      "salon"
    ],
    "wof:name": "Sun Spot Tanning Salon",
    "wof:placetype": "venue"
  },
  "geometry": {"coordinates":[-82.859686,38.733099],"type":"Point"}
}
