{
  "type": "Feature",
  "properties": {
    "addr:full": "5515 Hahn Rd NE Canton OH 44721",
    "addr:housenumber": "5515",
    "addr:postcode": "44721",
    "addr:street": "Hahn Rd Ne",
    "iso:country": "US",
    "sg:address": "5515 Hahn Rd NE",
    "sg:city": "Canton",
    "sg:classifiers": [
      {
        "category": "Building \u0026 Trades",
        "subcategory": "Construction",
        "type": "Services"
      }
    ],
    "sg:phone": "+1 330 875 3734",
    "sg:postcode": "44721",
    "sg:province": "OH",
    "sg:tags": [
      "house"
    ],
    "wof:name": "Now Homes Inc",
    "wof:placetype": "venue"
  },
  "geometry": {"coordinates":[-81.297732,40.888219],"type":"Point"}
}
