{
  "type": "Feature",
  "properties": {
    "iso:country":"US",
    "sg:address":"5515 Hahn Rd NE",
    "sg:city":"Canton",
    "sg:classifiers":[
        {
            "category":"Building & Trades",
            "subcategory":"Construction",
            "type":"Services"
        }
    ],
    "sg:phone":"+1 330 875 3734",
    "sg:postcode":"44721",
    "sg:province":"OH",
    "sg:tags":[
        "house"
    ],
    "wof:name":"Now Homes Inc",
    "wof:placetype":"venue"
},
  "geometry": {"coordinates":[-81.297732,40.888219],"type":"Point"}
}