{
  "type": "Feature",
  "properties": {
    "iso:country":"US",
    "sg:address":"1134 W Fair Ave",
    "sg:city":"Lancaster",
    "sg:classifiers":[
        {
            "category":"Recreation",
            "type":"Entertainment"
        }
    ],
    "sg:phone":"+1 740 653 3712",
    "sg:postcode":"43130",
    "sg:province":"OH",
    "sg:tags":[
        "facility",
        "shooting",
        "supply"
    ],
    "wof:name":"Ohio Target Co",
    "wof:placetype":"venue"
},
  "geometry": {"coordinates":[-82.61957,39.724513],"type":"Point"}
}