{
  "type": "Feature",
  "properties": {
    "iso:country":"US",
    "sg:address":"3985 Warrensville Center Rd",
    "sg:city":"Cleveland",
    "sg:classifiers":[
        {
            "category":"Health Services",
            "subcategory":"Doctor",
            "type":"Services"
        }
    ],
    "sg:phone":"+1 216 283 4494",
    "sg:postcode":"44122",
    "sg:province":"OH",
    "sg:tags":[
        "physician",
        "surgeon"
    ],
    "wof:name":"Richard M King MD",
    "wof:placetype":"venue"
},
  "geometry": {"coordinates":[-81.536032,41.451533],"type":"Point"}
}