{
  "type": "Feature",
  "properties": {
    "addr:full":"338 S High St Columbus OH 43215",
    "addr:housenumber":"338",
    "addr:postcode":"43215",
    "addr:street":"S High St",
    "iso:country":"US",
    "sg:address":"338 S High St",
    "sg:city":"Columbus",
    "sg:classifiers":[
        {
            "category":"Professional",
            "subcategory":"Lawyer & Legal Services",
            "type":"Services"
        }
    ],
    "sg:phone":"+1 614 224 0531",
    "sg:postcode":"43215",
    "sg:province":"OH",
    "sg:tags":[
        "attorney"
    ],
    "wof:name":"Williams & Petro Co LLC",
    "wof:placetype":"venue"
},
  "geometry": {"coordinates":[-82.999185,39.955146],"type":"Point"}
}