{
  "type": "Feature",
  "properties": {
    "iso:country":"US",
    "sg:address":"3205 S Waynesville Rd",
    "sg:city":"Morrow",
    "sg:classifiers":[
        {
            "category":"Landmark",
            "subcategory":"Tourist Information",
            "type":"Public Place"
        }
    ],
    "sg:phone":"+1 513 563 8339",
    "sg:postcode":"45152",
    "sg:province":"OH",
    "sg:tags":[
        "attraction"
    ],
    "wof:name":"Cincinnati Soft Adventures",
    "wof:placetype":"venue"
},
  "geometry": {"coordinates":[-84.13699,39.379276],"type":"Point"}
}