{
  "type": "Feature",
  "properties": {
    "iso:country":"US",
    "sg:address":"963 Cedar Trace Blvd",
    "sg:city":"Westerville",
    "sg:classifiers":[
        {
            "category":"Real Estate",
            "subcategory":"Real Estate Operator",
            "type":"Services"
        }
    ],
    "sg:phone":"+1 614 846 8488",
    "sg:postcode":"43081",
    "sg:province":"OH",
    "sg:tags":[
        "building",
        "apartment"
    ],
    "wof:name":"Cedar Trace Apartments",
    "wof:placetype":"venue"
},
  "geometry": {"coordinates":[-82.99323800000001,40.127717],"type":"Point"}
}