{
  "type": "Feature",
  "properties": {
    "addr:full": "963 Cedar Trace Blvd Westerville OH 43081",
    "addr:housenumber": "963",
    "addr:postcode": "43081",
    "addr:street": "Cedar Trace Blvd",
    "iso:country": "US",
    "sg:address": "963 Cedar Trace Blvd",
    "sg:city": "Westerville",
    "sg:classifiers": [
      {
        "category": "Real Estate",
        "subcategory": "Real Estate Operator",
        "type": "Services"
      }
    ],
    "sg:phone": "+1 614 846 8488",
    "sg:postcode": "43081",
    "sg:province": "OH",
    "sg:tags": [
      "building",
      "apartment"
    ],
    "wof:name": "Cedar Trace Apartments",
    "wof:placetype": "venue"
  },
  "geometry": {"coordinates":[-82.993238,40.127717],"type":"Point"}
}
