{
  "type": "Feature",
  "properties": {
    "addr:full": "1002 Columbus Ave Marysville OH 43040",
    "addr:housenumber": "1002",
    "addr:postcode": "43040",
    "addr:street": "Columbus Ave",
    "iso:country": "US",
    "sg:address": "1002 Columbus Ave",
    "sg:city": "Marysville",
    "sg:classifiers": [
      {
        "category": "Local Transit",
        "type": "Transportation"
      }
    ],
    "sg:phone": "+1 937 578 0263",
    "sg:postcode": "43040",
    "sg:province": "OH",
    "sg:tags": [
      "ambulance"
    ],
    "wof:name": "Kare Medical Transport Svc LTD",
    "wof:placetype": "venue"
  },
  "geometry": {"coordinates":[-83.352468,40.232408],"type":"Point"}
}
