{
  "type": "Feature",
  "properties": {
    "addr:full": "1009 Spring St Zanesville OH 43701",
    "addr:housenumber": "1009",
    "addr:postcode": "43701",
    "addr:street": "Spring St",
    "iso:country": "US",
    "sg:address": "1009 Spring St",
    "sg:city": "Zanesville",
    "sg:classifiers": [
      {
        "category": "Travel",
        "subcategory": "Hotels \u0026 Motels",
        "type": "Entertainment"
      }
    ],
    "sg:phone": "+1 740 453 6511",
    "sg:postcode": "43701",
    "sg:province": "OH",
    "sg:tags": [
      "operation"
    ],
    "wof:name": "Hampton Inn",
    "wof:placetype": "venue"
  },
  "geometry": {"coordinates":[-81.998776,39.946493],"type":"Point"}
}
