{
  "type": "Feature",
  "properties": {
    "iso:country":"US",
    "sg:address":"1009 Spring St",
    "sg:city":"Zanesville",
    "sg:classifiers":[
        {
            "category":"Travel",
            "subcategory":"Hotels & Motels",
            "type":"Entertainment"
        }
    ],
    "sg:phone":"+1 740 453 6511",
    "sg:postcode":"43701",
    "sg:province":"OH",
    "sg:tags":[
        "operation"
    ],
    "wof:name":"Hampton Inn",
    "wof:placetype":"venue"
},
  "geometry": {"coordinates":[-81.99877600000001,39.946493],"type":"Point"}
}