{
  "type": "Feature",
  "properties": {
    "addr:full": "445 Chestnut Blvd Cuyahoga Falls OH 44221",
    "addr:housenumber": "445",
    "addr:postcode": "44221",
    "addr:street": "Chestnut Blvd",
    "iso:country": "US",
    "sg:address": "445 Chestnut Blvd",
    "sg:city": "Cuyahoga Falls",
    "sg:classifiers": [
      {
        "category": "Health Services",
        "subcategory": "Medical Lab",
        "type": "Services"
      }
    ],
    "sg:phone": "+1 330 920 1940",
    "sg:postcode": "44221",
    "sg:province": "OH",
    "sg:tags": [
      "laboratory",
      "dental"
    ],
    "wof:name": "Crystal Dental Lab Inc",
    "wof:placetype": "venue"
  },
  "geometry": {"coordinates":[-81.489306,41.129187],"type":"Point"}
}
