{
  "type": "Feature",
  "properties": {
    "addr:full": "21706 State Rte 698 Jenera OH 45841",
    "addr:housenumber": "21706",
    "addr:postcode": "45841",
    "addr:street": "State Rte 698",
    "iso:country": "US",
    "sg:address": "21706 State Rte 698",
    "sg:city": "Jenera",
    "sg:phone": "+1 419 326 5491",
    "sg:postcode": "45841",
    "sg:province": "OH",
    "sg:tags": [
      "wheat",
      "farm",
      "corn",
      "crop",
      "field",
      "soybean"
    ],
    "wof:name": "Double M",
    "wof:placetype": "venue"
  },
  "geometry": {"coordinates":[-83.727682,40.852724],"type":"Point"}
}
