{
  "type": "Feature",
  "properties": {
    "iso:country":"US",
    "sg:address":"21706 State Rte 698",
    "sg:city":"Jenera",
    "sg:phone":"+1 419 326 5491",
    "sg:postcode":"45841",
    "sg:province":"OH",
    "sg:tags":[
        "wheat",
        "farm",
        "corn",
        "crop",
        "field",
        "soybean"
    ],
    "wof:name":"Double M",
    "wof:placetype":"venue"
},
  "geometry": {"coordinates":[-83.727682,40.852724],"type":"Point"}
}