{
  "type": "Feature",
  "properties": {
    "addr:full": "501 Loveland Madeira Rd Loveland OH 45140",
    "addr:housenumber": "501",
    "addr:postcode": "45140",
    "addr:street": "Loveland Madeira Rd",
    "iso:country": "US",
    "sg:address": "501 Loveland Madeira Rd",
    "sg:city": "Loveland",
    "sg:classifiers": [
      {
        "category": "Wholesale",
        "subcategory": "Auto Parts",
        "type": "Manufacturing \u0026 Wholesale Goods"
      }
    ],
    "sg:phone": "+1 513 583 9808",
    "sg:postcode": "45140",
    "sg:province": "OH",
    "sg:tags": [
      "automobile",
      "supply"
    ],
    "wof:name": "Automotive Service Supply Inc",
    "wof:placetype": "venue"
  },
  "geometry": {"coordinates":[-84.271084,39.262216],"type":"Point"}
}
