{
  "type": "Feature",
  "properties": {
    "iso:country":"US",
    "sg:address":"115 E Main St",
    "sg:city":"Bellevue",
    "sg:classifiers":[
        {
            "category":"Travel",
            "subcategory":"Travel Agent",
            "type":"Entertainment"
        }
    ],
    "sg:phone":"+1 419 483 3314",
    "sg:postcode":"44811",
    "sg:province":"OH",
    "sg:tags":[
        "agency"
    ],
    "wof:name":"Four Seasons Travel",
    "wof:placetype":"venue"
},
  "geometry": {"coordinates":[-82.840576,41.273706],"type":"Point"}
}