{
  "type": "Feature",
  "properties": {
    "addr:full": "10679 Lancaster Rd Hebron OH 43025",
    "addr:housenumber": "10679",
    "addr:postcode": "43025",
    "addr:street": "Lancaster Rd",
    "iso:country": "US",
    "sg:address": "10679 Lancaster Rd",
    "sg:city": "Hebron",
    "sg:classifiers": [
      {
        "category": "Shopping",
        "subcategory": "Computers \u0026 Home Electronics",
        "type": "Retail Goods"
      }
    ],
    "sg:phone": "+1 740 467 2145",
    "sg:postcode": "43025",
    "sg:province": "OH",
    "sg:tags": [
      "equipment",
      "electronic",
      "supply"
    ],
    "wof:name": "Magna Electronics",
    "wof:placetype": "venue"
  },
  "geometry": {"coordinates":[-82.535501,39.94029],"type":"Point"}
}
