{
  "type": "Feature",
  "properties": {
    "addr:full":"2600 N High St Columbus OH 43202",
    "addr:housenumber":"2600",
    "addr:postcode":"43202",
    "addr:street":"N High St",
    "iso:country":"US",
    "sg:address":"2600 N High St",
    "sg:city":"Columbus",
    "sg:classifiers":[
        {
            "category":"Restaurant",
            "type":"Food & Drink"
        }
    ],
    "sg:menulink":"http://www.allmenus.com/oh/columbus/258484-minuteman-pizza/menu/",
    "sg:phone":"+1 614 262 6200",
    "sg:postcode":"43202",
    "sg:province":"OH",
    "sg:tags":[
        "pasta",
        "american",
        "sandwich",
        "wing",
        "pizza"
    ],
    "wof:name":"Minuteman Pizza",
    "wof:placetype":"venue"
},
  "geometry": {"coordinates":[-83.01138899999999,40.015278],"type":"Point"}
}