{
  "type": "Feature",
  "properties": {
    "iso:country":"US",
    "sg:address":"580 Lincoln Park Blvd",
    "sg:city":"Dayton",
    "sg:classifiers":[
        {
            "category":"Real Estate",
            "subcategory":"Real Estate Agent",
            "type":"Services"
        }
    ],
    "sg:phone":"+1 937 298 1446",
    "sg:postcode":"45429",
    "sg:province":"OH",
    "wof:name":"Amerohome Onlinecom",
    "wof:placetype":"venue"
},
  "geometry": {"coordinates":[-84.160168,39.696629],"type":"Point"}
}