{
  "type": "Feature",
  "properties": {
    "addr:full":"50985 National Rd E St Clairsville OH 43950",
    "addr:housenumber":"50985",
    "addr:postcode":"43950",
    "addr:street":"National Rd E",
    "iso:country":"US",
    "sg:address":"50985 National Rd E",
    "sg:city":"St Clairsville",
    "sg:classifiers":[
        {
            "category":"Government",
            "subcategory":"Office",
            "type":"Public Place"
        }
    ],
    "sg:phone":"+1 740 695 2297",
    "sg:postcode":"43950",
    "sg:province":"OH",
    "sg:tags":[
        "federal"
    ],
    "wof:name":"US Mine Safety & Health Adm",
    "wof:placetype":"venue"
},
  "geometry": {"coordinates":[-80.868966,40.077133],"type":"Point"}
}