{
  "type": "Feature",
  "properties": {
    "addr:full":"4740 Reed Rd Columbus OH 43220",
    "addr:housenumber":"4740",
    "addr:postcode":"43220",
    "addr:street":"Reed Rd",
    "iso:country":"US",
    "sg:address":"4740 Reed Rd",
    "sg:city":"Columbus",
    "sg:classifiers":[
        {
            "category":"Bars & Pubs",
            "type":"Food & Drink"
        }
    ],
    "sg:phone":"+1 614 451 4288",
    "sg:postcode":"43220",
    "sg:province":"OH",
    "sg:tags":[
        "lounge",
        "cocktail"
    ],
    "wof:name":"Cocktail Lounge",
    "wof:placetype":"venue"
},
  "geometry": {"coordinates":[-83.066861,40.052399],"type":"Point"}
}