{
  "type": "Feature",
  "properties": {
    "iso:country":"US",
    "sg:address":"1110 S Water St",
    "sg:city":"Kent",
    "sg:classifiers":[
        {
            "category":"Personal",
            "subcategory":"Tanning Parlor",
            "type":"Services"
        }
    ],
    "sg:phone":"+1 330 677 8888",
    "sg:postcode":"44240",
    "sg:province":"OH",
    "sg:tags":[
        "salon"
    ],
    "wof:name":"Sunsation",
    "wof:placetype":"venue"
},
  "geometry": {"coordinates":[-81.358208,41.143103],"type":"Point"}
}