{
  "type": "Feature",
  "properties": {
    "iso:country":"US",
    "sg:address":"6687 Wilson Mills Rd",
    "sg:city":"Gates Mills",
    "sg:classifiers":[
        {
            "category":"Restaurant",
            "type":"Food & Drink"
        }
    ],
    "sg:phone":"+1 440 449 0776",
    "sg:postcode":"44040",
    "sg:province":"OH",
    "sg:tags":[
        "pizza"
    ],
    "wof:name":"Migelito's Pizza",
    "wof:placetype":"venue"
},
  "geometry": {"coordinates":[-81.435723,41.539001],"type":"Point"}
}