{
  "type": "Feature",
  "properties": {
    "addr:full": "5213 Deeds Rd SW Pataskala OH 43062",
    "addr:housenumber": "5213",
    "addr:postcode": "43062",
    "addr:street": "Deeds Rd Sw",
    "iso:country": "US",
    "sg:address": "5213 Deeds Rd SW",
    "sg:city": "Pataskala",
    "sg:classifiers": [
      {
        "category": "Manufacturing",
        "subcategory": "Toys \u0026 Sporting Goods",
        "type": "Manufacturing \u0026 Wholesale Goods"
      }
    ],
    "sg:phone": "+1 740 927 2095",
    "sg:postcode": "43062",
    "sg:province": "OH",
    "sg:tags": [
      "mfg"
    ],
    "wof:name": "Country Blssngs By Candy Walsh",
    "wof:placetype": "venue"
  },
  "geometry": {"coordinates":[-82.595228,40.012672],"type":"Point"}
}
