{
  "type": "Feature",
  "properties": {
    "iso:country":"US",
    "sg:address":"5213 Deeds Rd SW",
    "sg:city":"Pataskala",
    "sg:classifiers":[
        {
            "category":"Manufacturing",
            "subcategory":"Toys & Sporting Goods",
            "type":"Manufacturing & Wholesale Goods"
        }
    ],
    "sg:phone":"+1 740 927 2095",
    "sg:postcode":"43062",
    "sg:province":"OH",
    "sg:tags":[
        "mfg"
    ],
    "wof:name":"Country Blssngs By Candy Walsh",
    "wof:placetype":"venue"
},
  "geometry": {"coordinates":[-82.59522800000001,40.012672],"type":"Point"}
}