{
  "type": "Feature",
  "properties": {
    "iso:country":"US",
    "sg:address":"49 W 5th Ave",
    "sg:city":"Columbus",
    "sg:classifiers":[
        {
            "category":"Organizations",
            "subcategory":"Religious Organization",
            "type":"Services"
        }
    ],
    "sg:phone":"+1 614 299 0919",
    "sg:postcode":"43201",
    "sg:province":"OH",
    "sg:tags":[
        "church"
    ],
    "wof:name":"Grace Central Presbyterian Chr",
    "wof:placetype":"venue"
},
  "geometry": {"coordinates":[-83.007199,39.987075],"type":"Point"}
}