{
  "type": "Feature",
  "properties": {
    "iso:country":"US",
    "sg:address":"540 Water St",
    "sg:city":"Chardon",
    "sg:classifiers":[
        {
            "category":"Restaurant",
            "type":"Food & Drink"
        }
    ],
    "sg:phone":"+1 440 286 5151",
    "sg:postcode":"44024",
    "sg:province":"OH",
    "wof:name":"Maple Leaf Restaurant",
    "wof:placetype":"venue"
},
  "geometry": {"coordinates":[-81.212627,41.580877],"type":"Point"}
}