{
  "type": "Feature",
  "properties": {
    "iso:country":"US",
    "sg:address":"5663 Sprucewood Dr",
    "sg:city":"Cincinnati",
    "sg:classifiers":[
        {
            "category":"Professional",
            "type":"Services"
        }
    ],
    "sg:phone":"+1 513 741 8868",
    "sg:postcode":"45239",
    "sg:province":"OH",
    "sg:tags":[
        "arts",
        "artist"
    ],
    "wof:name":"Cincy Egg Art",
    "wof:placetype":"venue"
},
  "geometry": {"coordinates":[-84.588722,39.194476],"type":"Point"}
}