{
  "type": "Feature",
  "properties": {
    "addr:full":"1809 S Main St Findlay OH 45840",
    "addr:housenumber":"1809",
    "addr:postcode":"45840",
    "addr:street":"S Main St",
    "iso:country":"US",
    "sg:address":"1809 S Main St",
    "sg:city":"Findlay",
    "sg:classifiers":[
        {
            "category":"Health Services",
            "subcategory":"Doctor",
            "type":"Services"
        }
    ],
    "sg:phone":"+1 419 420 0100",
    "sg:postcode":"45840",
    "sg:province":"OH",
    "sg:tags":[
        "physician",
        "surgeon"
    ],
    "wof:name":"Infection Prevention & Trtmnt",
    "wof:placetype":"venue"
},
  "geometry": {"coordinates":[-83.650262,41.018438],"type":"Point"}
}