{
  "type": "Feature",
  "properties": {
    "addr:full": "3581 Love Rd Felicity OH 45120",
    "addr:housenumber": "3581",
    "addr:postcode": "45120",
    "addr:street": "Love Rd",
    "iso:country": "US",
    "sg:address": "3581 Love Rd",
    "sg:city": "Felicity",
    "sg:phone": "+1 513 876 3543",
    "sg:postcode": "45120",
    "sg:province": "OH",
    "sg:tags": [
      "farm",
      "corn",
      "wheat",
      "soybean",
      "tobacco"
    ],
    "wof:name": "David Morgan Farms",
    "wof:placetype": "venue"
  },
  "geometry": {"coordinates":[-84.081253,38.823744],"type":"Point"}
}
