{
  "type": "Feature",
  "properties": {
    "addr:full":"20611 Euclid Ave Euclid OH 44117",
    "addr:housenumber":"20611",
    "addr:postcode":"44117",
    "addr:street":"Euclid Ave",
    "iso:country":"US",
    "sg:address":"20611 Euclid Ave",
    "sg:city":"Euclid",
    "sg:classifiers":[
        {
            "category":"Health Services",
            "subcategory":"Nursing And Care Facility",
            "type":"Services"
        }
    ],
    "sg:phone":"+1 216 486 9300",
    "sg:postcode":"44117",
    "sg:province":"OH",
    "sg:tags":[
        "skilled",
        "home",
        "intermediate",
        "center"
    ],
    "wof:name":"Braeview Care Rhbilitation Ctr",
    "wof:placetype":"venue"
},
  "geometry": {"coordinates":[-81.53671799999999,41.567481],"type":"Point"}
}