{
  "type": "Feature",
  "properties": {
    "iso:country":"US",
    "sg:address":"9797 Colerain Ave",
    "sg:city":"Cincinnati",
    "sg:classifiers":[
        {
            "category":"Autos & Motor Vehicles",
            "subcategory":"Automobile Sales",
            "type":"Retail Goods"
        }
    ],
    "sg:phone":"+1 513 923 3999",
    "sg:postcode":"45251",
    "sg:province":"OH",
    "sg:tags":[
        "car",
        "dealer"
    ],
    "sg:website":"www.jdbyrider.com",
    "wof:name":"J D Byrider Auto Sales",
    "wof:placetype":"venue"
},
  "geometry": {"coordinates":[-84.59729,39.249713],"type":"Point"}
}