{
  "type": "Feature",
  "properties": {
    "iso:country":"US",
    "sg:address":"1074 Summit Dr",
    "sg:city":"Middletown",
    "sg:classifiers":[
        {
            "category":"Shopping",
            "type":"Retail Goods"
        }
    ],
    "sg:phone":"+1 513 422 2143",
    "sg:postcode":"45042",
    "sg:province":"OH",
    "sg:tags":[
        "church",
        "supply"
    ],
    "sg:website":"www.inword.org",
    "wof:name":"Inword Resources",
    "wof:placetype":"venue"
},
  "geometry": {"coordinates":[-84.35273,39.525249],"type":"Point"}
}