{
  "type": "Feature",
  "properties": {
    "iso:country":"US",
    "sg:address":"3857 Easton Way",
    "sg:city":"Columbus",
    "sg:classifiers":[
        {
            "category":"Banks & Credit Unions",
            "subcategory":"Bank",
            "type":"Services"
        }
    ],
    "sg:phone":"+1 614 475 6572",
    "sg:postcode":"43219",
    "sg:province":"OH",
    "sg:tags":[
        "loan",
        "real estate"
    ],
    "wof:name":"Equity Corp Housing",
    "wof:placetype":"venue"
},
  "geometry": {"coordinates":[-82.918637,40.048374],"type":"Point"}
}