{
  "type": "Feature",
  "properties": {
    "addr:full": "14820 Saint Clair Ave Cleveland OH 44110",
    "addr:housenumber": "14820",
    "addr:postcode": "44110",
    "addr:street": "Saint Clair Ave",
    "iso:country": "US",
    "sg:address": "14820 Saint Clair Ave",
    "sg:city": "Cleveland",
    "sg:classifiers": [
      {
        "category": "Shopping",
        "subcategory": "Used Merchandise",
        "type": "Retail Goods"
      }
    ],
    "sg:phone": "+1 216 761 2160",
    "sg:postcode": "44110",
    "sg:province": "OH",
    "wof:name": "Kristyle Fashion",
    "wof:placetype": "venue"
  },
  "geometry": {"coordinates":[-81.578072,41.552547],"type":"Point"}
}
