{
  "type": "Feature",
  "properties": {
    "iso:country":"US",
    "sg:address":"6366 Kings Arms Way",
    "sg:city":"Fairfield",
    "sg:classifiers":[
        {
            "category":"Building & Trades",
            "subcategory":"Construction",
            "type":"Services"
        }
    ],
    "sg:phone":"+1 513 829 8978",
    "sg:postcode":"45014",
    "sg:province":"OH",
    "sg:tags":[
        "contractor"
    ],
    "wof:name":"Innovative Installations Inc",
    "wof:placetype":"venue"
},
  "geometry": {"coordinates":[-84.575504,39.308591],"type":"Point"}
}