{
  "type": "Feature",
  "properties": {
    "iso:country":"US",
    "sg:address":"9892 Old State Rd",
    "sg:city":"Chardon",
    "sg:classifiers":[
        {
            "category":"Organizations",
            "subcategory":"Religious Organization",
            "type":"Services"
        }
    ],
    "sg:phone":"+1 440 286 3540",
    "sg:postcode":"44024",
    "sg:province":"OH",
    "sg:tags":[
        "church"
    ],
    "sg:website":"www.hambdenalliance.org",
    "wof:name":"Hambden Alliance Church",
    "wof:placetype":"venue"
},
  "geometry": {"coordinates":[-81.143709,41.601727],"type":"Point"}
}