{
  "type": "Feature",
  "properties": {
    "addr:full": "501 W Perkins Ave Sandusky OH 44870",
    "addr:housenumber": "501",
    "addr:postcode": "44870",
    "addr:street": "W Perkins Ave",
    "iso:country": "US",
    "sg:address": "501 W Perkins Ave",
    "sg:city": "Sandusky",
    "sg:classifiers": [
      {
        "category": "Real Estate",
        "subcategory": "Real Estate Services",
        "type": "Services"
      }
    ],
    "sg:phone": "+1 419 625 6950",
    "sg:postcode": "44870",
    "sg:province": "OH",
    "wof:name": "Stadtmiller Reg Realtor",
    "wof:placetype": "venue"
  },
  "geometry": {"coordinates":[-82.7071,41.432999],"type":"Point"}
}
