{
  "type": "Feature",
  "properties": {
    "addr:full":"10917 Prospect Rd Strongsville OH 44149",
    "addr:housenumber":"10917",
    "addr:postcode":"44149",
    "addr:street":"Prospect Rd",
    "iso:country":"US",
    "sg:address":"10917 Prospect Rd",
    "sg:city":"Strongsville",
    "sg:classifiers":[
        {
            "category":"Restaurant",
            "type":"Food & Drink"
        }
    ],
    "sg:phone":"+1 440 238 1106",
    "sg:postcode":"44149",
    "sg:province":"OH",
    "sg:tags":[
        "chinese"
    ],
    "wof:name":"Empire Wok Chinese Carry Out",
    "wof:placetype":"venue"
},
  "geometry": {"coordinates":[-81.857567,41.335284],"type":"Point"}
}