{
  "type": "Feature",
  "properties": {
    "addr:full": "1210 Kenton St Springfield OH 45505",
    "addr:housenumber": "1210",
    "addr:postcode": "45505",
    "addr:street": "Kenton St",
    "iso:country": "US",
    "sg:address": "1210 Kenton St",
    "sg:city": "Springfield",
    "sg:classifiers": [
      {
        "category": "Professional",
        "subcategory": "Management \u0026 Consulting",
        "type": "Services"
      }
    ],
    "sg:phone": "+1 937 325 9850",
    "sg:postcode": "45505",
    "sg:province": "OH",
    "wof:name": "Logistics Management",
    "wof:placetype": "venue"
  },
  "geometry": {"coordinates":[-83.792397,39.914026],"type":"Point"}
}
