{
  "type": "Feature",
  "properties": {
    "addr:full": "4984 Turney Rd Cleveland OH 44125",
    "addr:housenumber": "4984",
    "addr:postcode": "44125",
    "addr:street": "Turney Rd",
    "iso:country": "US",
    "sg:address": "4984 Turney Rd",
    "sg:city": "Cleveland",
    "sg:classifiers": [
      {
        "category": "Restaurant",
        "type": "Food \u0026 Drink"
      }
    ],
    "sg:phone": "+1 216 341 3110",
    "sg:postcode": "44125",
    "sg:province": "OH",
    "sg:tags": [
      "eating"
    ],
    "wof:name": "Subway",
    "wof:placetype": "venue"
  },
  "geometry": {"coordinates":[-81.611344,41.424428],"type":"Point"}
}
