{
  "type": "Feature",
  "properties": {
    "addr:full":"35 E Chestnut St Columbus OH 43215",
    "addr:housenumber":"35",
    "addr:postcode":"43215",
    "addr:street":"E Chestnut St",
    "iso:country":"US",
    "sg:address":"35 E Chestnut St",
    "sg:city":"Columbus",
    "sg:classifiers":[
        {
            "category":"Organizations",
            "subcategory":"Community Association",
            "type":"Services"
        }
    ],
    "sg:phone":"+1 614 227 0358",
    "sg:postcode":"43215",
    "sg:province":"OH",
    "sg:tags":[
        "military"
    ],
    "wof:name":"Ladies Auxiliary To VFW Dept",
    "wof:placetype":"venue"
},
  "geometry": {"coordinates":[-82.99918,39.967817],"type":"Point"}
}