{
  "type": "Feature",
  "properties": {
    "addr:full":"38700 Mentor Ave Willoughby OH 44094",
    "addr:postcode":"38700;44094",
    "addr:street":"Mentor Ave",
    "iso:country":"US",
    "sg:address":"38700 Mentor Ave",
    "sg:city":"Willoughby",
    "sg:classifiers":[
        {
            "category":"Autos & Motor Vehicles",
            "subcategory":"Fuel & Gas Station",
            "type":"Retail Goods"
        }
    ],
    "sg:phone":"+1 440 946 6935",
    "sg:postcode":"44094",
    "sg:province":"OH",
    "sg:tags":[
        "oil"
    ],
    "sg:website":"www.speedway.com",
    "wof:name":"Speedway",
    "wof:placetype":"venue"
},
  "geometry": {"coordinates":[-81.39202400000001,41.645277],"type":"Point"}
}