{
  "type": "Feature",
  "properties": {
    "addr:full":"601 Woodstone Cir Akron OH 44319",
    "addr:housenumber":"601",
    "addr:postcode":"44319",
    "addr:street":"Woodstone Cir",
    "iso:country":"US",
    "sg:address":"601 Woodstone Cir",
    "sg:city":"Akron",
    "sg:classifiers":[
        {
            "category":"Manufacturing",
            "subcategory":"Signs",
            "type":"Manufacturing & Wholesale Goods"
        }
    ],
    "sg:phone":"+1 330 644 4075",
    "sg:postcode":"44319",
    "sg:province":"OH",
    "sg:tags":[
        "specialty",
        "mfg"
    ],
    "wof:name":"Kaddi Corp",
    "wof:placetype":"venue"
},
  "geometry": {"coordinates":[-81.541111,40.987898],"type":"Point"}
}