{
  "type": "Feature",
  "properties": {
    "addr:full":"3000 Auburn Dr Beachwood OH 44122",
    "addr:housenumber":"3000",
    "addr:postcode":"44122",
    "addr:street":"Auburn Dr",
    "iso:country":"US",
    "sg:address":"3000 Auburn Dr",
    "sg:city":"Beachwood",
    "sg:classifiers":[
        {
            "category":"Professional",
            "subcategory":"Computer Services",
            "type":"Services"
        }
    ],
    "sg:phone":"+1 216 450 5200",
    "sg:postcode":"44122",
    "sg:province":"OH",
    "sg:tags":[
        "information",
        "recovery",
        "processing",
        "system",
        "equipment",
        "data",
        "retrieval"
    ],
    "sg:website":"http://www.intellicorp.net",
    "wof:name":"Intellicorp Records Inc",
    "wof:placetype":"venue"
},
  "geometry": {"coordinates":[-81.494148,41.45554],"type":"Point"}
}