{
  "type": "Feature",
  "properties": {
    "addr:full": "1667 Footville-Richmond Rd W Jefferson OH 44047",
    "addr:housenumber": "1667",
    "addr:postcode": "44047",
    "addr:street": "Footville-Richmond Rd W",
    "iso:country": "US",
    "sg:address": "1667 Footville-Richmond Rd W",
    "sg:city": "Jefferson",
    "sg:classifiers": [
      {
        "category": "Food \u0026 Beverages",
        "subcategory": "Dairy",
        "type": "Retail Goods"
      }
    ],
    "sg:phone": "+1 440 563 5716",
    "sg:postcode": "44047",
    "sg:province": "OH",
    "sg:tags": [
      "product"
    ],
    "wof:name": "Syak Dairy Farms",
    "wof:placetype": "venue"
  },
  "geometry": {"coordinates":[-80.811031,41.686681],"type":"Point"}
}
