{
  "type": "Feature",
  "properties": {
    "iso:country":"US",
    "sg:address":"2424 Deewood Dr",
    "sg:city":"Columbus",
    "sg:classifiers":[
        {
            "category":"Building & Trades",
            "subcategory":"Landscaping Services",
            "type":"Services"
        }
    ],
    "sg:phone":"+1 614 804 6859",
    "sg:postcode":"43229",
    "sg:province":"OH",
    "sg:tags":[
        "lawn",
        "maintenance",
        "grounds"
    ],
    "wof:name":"Sensational Lawn Creations LLC",
    "wof:placetype":"venue"
},
  "geometry": {"coordinates":[-82.952061,40.096258],"type":"Point"}
}