{
  "type": "Feature",
  "properties": {
    "addr:full": "3340 Urbancrest Industrial Dr Grove City OH 43123",
    "addr:housenumber": "3340",
    "addr:postcode": "43123",
    "addr:street": "Urbancrest Industrial Dr",
    "iso:country": "US",
    "sg:address": "3340 Urbancrest Industrial Dr",
    "sg:city": "Grove City",
    "sg:classifiers": [
      {
        "category": "Freight",
        "type": "Transportation"
      }
    ],
    "sg:phone": "+1 614 539 3230",
    "sg:postcode": "43123",
    "sg:province": "OH",
    "sg:tags": [
      "warehouse"
    ],
    "wof:name": "Kittles Home Furn Dist Ctr",
    "wof:placetype": "venue"
  },
  "geometry": {"coordinates":[-83.080653,39.902438],"type":"Point"}
}
