{
  "type": "Feature",
  "properties": {
    "iso:country":"US",
    "sg:address":"3400 Mahoning Ave",
    "sg:city":"Youngstown",
    "sg:classifiers":[
        {
            "category":"Autos & Motor Vehicles",
            "subcategory":"Auto Supplies",
            "type":"Retail Goods"
        }
    ],
    "sg:phone":"+1 330 792 2331",
    "sg:postcode":"44509",
    "sg:province":"OH",
    "sg:tags":[
        "repair",
        "general"
    ],
    "wof:name":"Goodyear",
    "wof:placetype":"venue"
},
  "geometry": {"coordinates":[-80.709707,41.103097],"type":"Point"}
}