{
  "type": "Feature",
  "properties": {
    "addr:full":"521 Union St Martins Ferry OH 43935",
    "addr:housenumber":"521",
    "addr:postcode":"43935",
    "addr:street":"Union St",
    "iso:country":"US",
    "sg:address":"521 Union St",
    "sg:city":"Martins Ferry",
    "sg:classifiers":[
        {
            "category":"Personal",
            "subcategory":"Beauty Salon",
            "type":"Services"
        }
    ],
    "sg:phone":"+1 740 633 2603",
    "sg:postcode":"43935",
    "sg:province":"OH",
    "wof:name":"Lyfe Style Beauty Boutique",
    "wof:placetype":"venue"
},
  "geometry": {"coordinates":[-80.735771,40.086316],"type":"Point"}
}