{
  "type": "Feature",
  "properties": {
    "addr:full":"2050 Mc Gaw Rd Obetz OH 43207",
    "addr:housenumber":"2050",
    "addr:postcode":"43207",
    "addr:street":"Mc Gaw Rd",
    "iso:country":"US",
    "sg:address":"2050 Mc Gaw Rd",
    "sg:city":"Obetz",
    "sg:classifiers":[
        {
            "category":"Insurance",
            "subcategory":"Insurance Agent",
            "type":"Services"
        }
    ],
    "sg:phone":"+1 614 497 8300",
    "sg:postcode":"43207",
    "sg:province":"OH",
    "wof:name":"Lifeline Shelter",
    "wof:placetype":"venue"
},
  "geometry": {"coordinates":[-82.946828,39.867628],"type":"Point"}
}