{
  "type": "Feature",
  "properties": {
    "addr:full":"110 W Streetsboro St Hudson OH 44236",
    "addr:housenumber":"110",
    "addr:postcode":"44236",
    "addr:street":"W Streetsboro St",
    "iso:country":"US",
    "sg:address":"110 W Streetsboro St",
    "sg:city":"Hudson",
    "sg:classifiers":[
        {
            "category":"Professional",
            "type":"Services"
        }
    ],
    "sg:phone":"+1 330 656 1162",
    "sg:postcode":"44236",
    "sg:province":"OH",
    "sg:tags":[
        "establishment"
    ],
    "wof:name":"Voice Track Systems",
    "wof:placetype":"venue"
},
  "geometry": {"coordinates":[-81.449673,41.239898],"type":"Point"}
}