{
  "type": "Feature",
  "properties": {
    "iso:country":"US",
    "sg:address":"4152 Twp Rd 25",
    "sg:city":"Ada",
    "sg:classifiers":[
        {
            "category":"Professional",
            "type":"Services"
        }
    ],
    "sg:phone":"+1 419 634 9440",
    "sg:postcode":"45810",
    "sg:province":"OH",
    "wof:name":"Still Water Acres",
    "wof:placetype":"venue"
},
  "geometry": {"coordinates":[-83.86141600000001,40.759243],"type":"Point"}
}