{
  "type": "Feature",
  "properties": {
    "addr:full": "4152 Twp Rd 25 Ada OH 45810",
    "addr:housenumber": "25",
    "addr:postcode": "4152;45810",
    "addr:street": "Twp Rd",
    "iso:country": "US",
    "sg:address": "4152 Twp Rd 25",
    "sg:city": "Ada",
    "sg:classifiers": [
      {
        "category": "Professional",
        "type": "Services"
      }
    ],
    "sg:phone": "+1 419 634 9440",
    "sg:postcode": "45810",
    "sg:province": "OH",
    "wof:name": "Still Water Acres",
    "wof:placetype": "venue"
  },
  "geometry": {"coordinates":[-83.861416,40.759243],"type":"Point"}
}
