{
  "type": "Feature",
  "properties": {
    "addr:full":"10326 Pine Needle Trl Strongsville OH 44149",
    "addr:housenumber":"10326",
    "addr:postcode":"44149",
    "addr:street":"Pine Needle Trl",
    "iso:country":"US",
    "sg:address":"10326 Pine Needle Trl",
    "sg:city":"Strongsville",
    "sg:classifiers":[
        {
            "category":"Wholesale",
            "subcategory":"Office Equipment",
            "type":"Manufacturing & Wholesale Goods"
        }
    ],
    "sg:phone":"+1 440 846 0963",
    "sg:postcode":"44149",
    "sg:province":"OH",
    "sg:tags":[
        "scanning",
        "code",
        "bar"
    ],
    "wof:name":"Miles Technologies Inc",
    "wof:placetype":"venue"
},
  "geometry": {"coordinates":[-81.862257,41.335025],"type":"Point"}
}