{
  "type": "Feature",
  "properties": {
    "addr:full": "903 Sherwood Dr Elyria OH 44035",
    "addr:housenumber": "903",
    "addr:postcode": "44035",
    "addr:street": "Sherwood Dr",
    "iso:country": "US",
    "sg:address": "903 Sherwood Dr",
    "sg:city": "Elyria",
    "sg:classifiers": [
      {
        "category": "Shopping",
        "subcategory": "Gifts \u0026 Souvenirs",
        "type": "Retail Goods"
      }
    ],
    "sg:phone": "+1 440 365 3244",
    "sg:postcode": "44035",
    "sg:province": "OH",
    "wof:name": "That Special Touch",
    "wof:placetype": "venue"
  },
  "geometry": {"coordinates":[-82.068765,41.394652],"type":"Point"}
}
