{
  "type": "Feature",
  "properties": {
    "addr:full": "115 N Lynn St Bryan OH 43506",
    "addr:housenumber": "115",
    "addr:postcode": "43506",
    "addr:street": "N Lynn St",
    "iso:country": "US",
    "sg:address": "115 N Lynn St",
    "sg:city": "Bryan",
    "sg:classifiers": [
      {
        "category": "Real Estate",
        "subcategory": "Real Estate Agent",
        "type": "Services"
      }
    ],
    "sg:phone": "+1 419 630 0111",
    "sg:postcode": "43506",
    "sg:province": "OH",
    "wof:name": "Westfall Realty Inc",
    "wof:placetype": "venue"
  },
  "geometry": {"coordinates":[-84.552466,41.475718],"type":"Point"}
}
