{
  "type": "Feature",
  "properties": {
    "addr:full":"505 West Ave Tallmadge OH 44278",
    "addr:housenumber":"505",
    "addr:postcode":"44278",
    "addr:street":"West Ave",
    "iso:country":"US",
    "sg:address":"505 West Ave",
    "sg:city":"Tallmadge",
    "sg:classifiers":[
        {
            "category":"Retail",
            "subcategory":"Car Wash",
            "type":"Services"
        }
    ],
    "sg:phone":"+1 330 633 2220",
    "sg:postcode":"44278",
    "sg:province":"OH",
    "sg:tags":[
        "carwash"
    ],
    "wof:name":"Wash Works Car Wash",
    "wof:placetype":"venue"
},
  "geometry": {"coordinates":[-81.460159,41.101689],"type":"Point"}
}