{
  "type": "Feature",
  "properties": {
    "iso:country":"US",
    "sg:address":"561 N Main St",
    "sg:city":"Marion",
    "sg:classifiers":[
        {
            "category":"Ice Cream",
            "type":"Food & Drink"
        }
    ],
    "sg:menulink":"http://www.allmenus.com/oh/marion/165233-dairy-queen/menu/",
    "sg:phone":"+1 740 382 3838",
    "sg:postcode":"43302",
    "sg:province":"OH",
    "sg:tags":[
        "burger",
        "american"
    ],
    "wof:name":"Dairy Queen",
    "wof:placetype":"venue"
},
  "geometry": {"coordinates":[-83.12949,40.598199],"type":"Point"}
}