{
  "type": "Feature",
  "properties": {
    "iso:country":"US",
    "sg:address":"13910 Purdy Rd",
    "sg:city":"Spencerville",
    "sg:classifiers":[
        {
            "category":"Professional",
            "subcategory":"Management & Consulting",
            "type":"Services"
        }
    ],
    "sg:phone":"+1 419 647 6381",
    "sg:postcode":"45887",
    "sg:province":"OH",
    "sg:tags":[
        "product",
        "agriculture"
    ],
    "wof:name":"R & G Sales Co",
    "wof:placetype":"venue"
},
  "geometry": {"coordinates":[-84.370071,40.728728],"type":"Point"}
}