{
  "type": "Feature",
  "properties": {
    "addr:full": "13910 Purdy Rd Spencerville OH 45887",
    "addr:housenumber": "13910",
    "addr:postcode": "45887",
    "addr:street": "Purdy Rd",
    "iso:country": "US",
    "sg:address": "13910 Purdy Rd",
    "sg:city": "Spencerville",
    "sg:classifiers": [
      {
        "category": "Professional",
        "subcategory": "Management \u0026 Consulting",
        "type": "Services"
      }
    ],
    "sg:phone": "+1 419 647 6381",
    "sg:postcode": "45887",
    "sg:province": "OH",
    "sg:tags": [
      "product",
      "agriculture"
    ],
    "wof:name": "R \u0026 G Sales Co",
    "wof:placetype": "venue"
  },
  "geometry": {"coordinates":[-84.370071,40.728728],"type":"Point"}
}
