{
  "type": "Feature",
  "properties": {
    "iso:country":"US",
    "sg:address":"100 S Bridge St",
    "sg:city":"Struthers",
    "sg:classifiers":[
        {
            "category":"Wholesale",
            "subcategory":"Construction Materials",
            "type":"Manufacturing & Wholesale Goods"
        }
    ],
    "sg:phone":"+1 330 755 5900",
    "sg:postcode":"44471",
    "sg:province":"OH",
    "sg:tags":[
        "building"
    ],
    "wof:name":"Macmillian Bloedel Bldg Mtls",
    "wof:placetype":"venue"
},
  "geometry": {"coordinates":[-80.58574,41.058861],"type":"Point"}
}