{
  "type": "Feature",
  "properties": {
    "addr:full": "1456 Delashmut Ave Columbus OH 43212",
    "addr:housenumber": "1456",
    "addr:postcode": "43212",
    "addr:street": "Delashmut Ave",
    "iso:country": "US",
    "sg:address": "1456 Delashmut Ave",
    "sg:city": "Columbus",
    "sg:classifiers": [
      {
        "category": "Wholesale",
        "subcategory": "Machinery \u0026 Supplies",
        "type": "Manufacturing \u0026 Wholesale Goods"
      }
    ],
    "sg:phone": "+1 614 294 2659",
    "sg:postcode": "43212",
    "sg:province": "OH",
    "sg:tags": [
      "clamp"
    ],
    "wof:name": "Astral Corp",
    "wof:placetype": "venue"
  },
  "geometry": {"coordinates":[-83.030144,39.991043],"type":"Point"}
}
