{
  "type": "Feature",
  "properties": {
    "addr:full": "33 W Market St Germantown OH 45327",
    "addr:housenumber": "33",
    "addr:postcode": "45327",
    "addr:street": "W Market St",
    "iso:country": "US",
    "sg:address": "33 W Market St",
    "sg:city": "Germantown",
    "sg:classifiers": [
      {
        "category": "Travel",
        "subcategory": "Hotels \u0026 Motels",
        "type": "Entertainment"
      }
    ],
    "sg:phone": "+1 937 855 3508",
    "sg:postcode": "45327",
    "sg:province": "OH",
    "sg:tags": [
      "breakfast",
      "accommodation",
      "bed"
    ],
    "wof:name": "Gunckel Heritage Bed-Breakfast",
    "wof:placetype": "venue"
  },
  "geometry": {"coordinates":[-84.371504,39.62484],"type":"Point"}
}
