{
  "type": "Feature",
  "properties": {
    "iso:country":"US",
    "sg:address":"33 W Market St",
    "sg:city":"Germantown",
    "sg:classifiers":[
        {
            "category":"Travel",
            "subcategory":"Hotels & Motels",
            "type":"Entertainment"
        }
    ],
    "sg:phone":"+1 937 855 3508",
    "sg:postcode":"45327",
    "sg:province":"OH",
    "sg:tags":[
        "breakfast",
        "accommodation",
        "bed"
    ],
    "wof:name":"Gunckel Heritage Bed-Breakfast",
    "wof:placetype":"venue"
},
  "geometry": {"coordinates":[-84.371504,39.62484],"type":"Point"}
}