{
  "type": "Feature",
  "properties": {
    "iso:country":"US",
    "sg:address":"518 Dan Jones Rd",
    "sg:city":"Gallipolis",
    "sg:classifiers":[
        {
            "category":"Recreation",
            "type":"Entertainment"
        }
    ],
    "sg:phone":"+1 740 379 2711",
    "sg:postcode":"45631",
    "sg:province":"OH",
    "sg:tags":[
        "parks"
    ],
    "wof:name":"Raccoon Creek County Park",
    "wof:placetype":"venue"
},
  "geometry": {"coordinates":[-82.348122,38.79358],"type":"Point"}
}