{
  "type": "Feature",
  "properties": {
    "addr:full": "518 Dan Jones Rd Gallipolis OH 45631",
    "addr:housenumber": "518",
    "addr:postcode": "45631",
    "addr:street": "Dan Jones Rd",
    "iso:country": "US",
    "sg:address": "518 Dan Jones Rd",
    "sg:city": "Gallipolis",
    "sg:classifiers": [
      {
        "category": "Recreation",
        "type": "Entertainment"
      }
    ],
    "sg:phone": "+1 740 379 2711",
    "sg:postcode": "45631",
    "sg:province": "OH",
    "sg:tags": [
      "parks"
    ],
    "wof:name": "Raccoon Creek County Park",
    "wof:placetype": "venue"
  },
  "geometry": {"coordinates":[-82.348122,38.79358],"type":"Point"}
}
