{
  "type": "Feature",
  "properties": {
    "iso:country":"US",
    "sg:address":"13005 Old Mill Rd",
    "sg:city":"Spencer",
    "sg:classifiers":[
        {
            "category":"Building & Trades",
            "subcategory":"Landscaping Services",
            "type":"Services"
        }
    ],
    "sg:phone":"+1 330 648 3001",
    "sg:postcode":"44275",
    "sg:province":"OH",
    "sg:tags":[
        "landscape",
        "contractor"
    ],
    "wof:name":"Meer's Landscaping",
    "wof:placetype":"venue"
},
  "geometry": {"coordinates":[-82.161798,41.08598],"type":"Point"}
}