{
  "type": "Feature",
  "properties": {
    "addr:full":"9355 Allen Rd West Chester OH 45069",
    "addr:housenumber":"9355",
    "addr:postcode":"45069",
    "addr:street":"Allen Rd",
    "iso:country":"US",
    "sg:address":"9355 Allen Rd",
    "sg:city":"West Chester",
    "sg:classifiers":[
        {
            "category":"Wholesale",
            "subcategory":"Electrical",
            "type":"Manufacturing & Wholesale Goods"
        }
    ],
    "sg:phone":"+1 513 942 9070",
    "sg:postcode":"45069",
    "sg:province":"OH",
    "sg:tags":[
        "equipment",
        "electric",
        "supply"
    ],
    "wof:name":"Allen-Bradley",
    "wof:placetype":"venue"
},
  "geometry": {"coordinates":[-84.435062,39.320994],"type":"Point"}
}