{
  "type": "Feature",
  "properties": {
    "addr:full":"102 N Main St Columbiana OH 44408",
    "addr:housenumber":"102",
    "addr:postcode":"44408",
    "addr:street":"N Main St",
    "iso:country":"US",
    "sg:address":"102 N Main St",
    "sg:city":"Columbiana",
    "sg:classifiers":[
        {
            "category":"Manufacturing",
            "subcategory":"Glass & Minerals",
            "type":"Manufacturing & Wholesale Goods"
        }
    ],
    "sg:phone":"+1 330 482 3020",
    "sg:postcode":"44408",
    "sg:province":"OH",
    "sg:tags":[
        "refractory"
    ],
    "wof:name":"Holland Manufacturing Corp",
    "wof:placetype":"venue"
},
  "geometry": {"coordinates":[-80.69347399999999,40.890094],"type":"Point"}
}