{
  "type": "Feature",
  "properties": {
    "iso:country":"US",
    "sg:address":"5670 Mayfield Rd",
    "sg:city":"Cleveland",
    "sg:classifiers":[
        {
            "category":"Restaurant",
            "type":"Food & Drink"
        }
    ],
    "sg:phone":"+1 440 646 9100",
    "sg:postcode":"44124",
    "sg:province":"OH",
    "sg:tags":[
        "eating"
    ],
    "wof:name":"Hunan Of Lyndhurst",
    "wof:placetype":"venue"
},
  "geometry": {"coordinates":[-81.47398800000001,41.51995],"type":"Point"}
}