{
  "type": "Feature",
  "properties": {
    "addr:full": "208 Crestview Dr Creston OH 44217",
    "addr:housenumber": "208",
    "addr:postcode": "44217",
    "addr:street": "Crestview Dr",
    "iso:country": "US",
    "sg:address": "208 Crestview Dr",
    "sg:city": "Creston",
    "sg:classifiers": [
      {
        "category": "Shopping",
        "type": "Retail Goods"
      }
    ],
    "sg:phone": "+1 330 435 4139",
    "sg:postcode": "44217",
    "sg:province": "OH",
    "sg:tags": [
      "merchandise"
    ],
    "wof:name": "Wolf Trophies \u0026 Awards",
    "wof:placetype": "venue"
  },
  "geometry": {"coordinates":[-81.899946,40.977881],"type":"Point"}
}
