{
  "type": "Feature",
  "properties": {
    "iso:country":"US",
    "sg:address":"4491 Mayfield Rd",
    "sg:city":"Cleveland",
    "sg:classifiers":[
        {
            "category":"Freight",
            "type":"Transportation"
        }
    ],
    "sg:phone":"+1 216 382 4349",
    "sg:postcode":"44121",
    "sg:province":"OH",
    "sg:tags":[
        "delivery"
    ],
    "wof:name":"Don't Shoot The Messenger",
    "wof:placetype":"venue"
},
  "geometry": {"coordinates":[-81.518111,41.519997],"type":"Point"}
}