{
  "type": "Feature",
  "properties": {
    "addr:full":"5285 Hudson Dr Hudson OH 44236",
    "addr:housenumber":"5285",
    "addr:postcode":"44236",
    "addr:street":"Hudson Dr",
    "iso:country":"US",
    "sg:address":"5285 Hudson Dr",
    "sg:city":"Hudson",
    "sg:classifiers":[
        {
            "category":"Wholesale",
            "subcategory":"Machinery & Supplies",
            "type":"Manufacturing & Wholesale Goods"
        }
    ],
    "sg:phone":"+1 330 650 2223",
    "sg:postcode":"44236",
    "sg:province":"OH",
    "sg:tags":[
        "rubber",
        "product"
    ],
    "wof:name":"Alttran",
    "wof:placetype":"venue"
},
  "geometry": {"coordinates":[-81.445178,41.215234],"type":"Point"}
}