{
  "type": "Feature",
  "properties": {
    "addr:full": "603 W Park Ave Columbiana OH 44408",
    "addr:housenumber": "603",
    "addr:postcode": "44408",
    "addr:street": "W Park Ave",
    "iso:country": "US",
    "sg:address": "603 W Park Ave",
    "sg:city": "Columbiana",
    "sg:classifiers": [
      {
        "category": "Organizations",
        "subcategory": "Religious Organization",
        "type": "Services"
      }
    ],
    "sg:phone": "+1 330 482 9775",
    "sg:postcode": "44408",
    "sg:province": "OH",
    "sg:tags": [
      "church"
    ],
    "wof:name": "Jehovah's Witnesses",
    "wof:placetype": "venue"
  },
  "geometry": {"coordinates":[-80.702889,40.88725],"type":"Point"}
}
