{
  "type": "Feature",
  "properties": {
    "addr:full": "221 Clinton St Defiance OH 43512",
    "addr:housenumber": "221",
    "addr:postcode": "43512",
    "addr:street": "Clinton St",
    "iso:country": "US",
    "sg:address": "221 Clinton St",
    "sg:city": "Defiance",
    "sg:classifiers": [
      {
        "category": "Government",
        "subcategory": "Office",
        "type": "Public Place"
      }
    ],
    "sg:phone": "+1 419 782 1926",
    "sg:postcode": "43512",
    "sg:province": "OH",
    "sg:tags": [
      "dog",
      "license"
    ],
    "wof:name": "Auditor Office",
    "wof:placetype": "venue"
  },
  "geometry": {"coordinates":[-84.361804,41.287123],"type":"Point"}
}
