{
  "type": "Feature",
  "properties": {
    "addr:full": "5133 Chipman Dr Columbus OH 43232",
    "addr:housenumber": "5133",
    "addr:postcode": "43232",
    "addr:street": "Chipman Dr",
    "iso:country": "US",
    "sg:address": "5133 Chipman Dr",
    "sg:city": "Columbus",
    "sg:classifiers": [
      {
        "category": "Building \u0026 Trades",
        "subcategory": "Construction",
        "type": "Services"
      }
    ],
    "sg:phone": "+1 614 833 1306",
    "sg:postcode": "43232",
    "sg:province": "OH",
    "sg:tags": [
      "residential"
    ],
    "wof:name": "Richard Luthur",
    "wof:placetype": "venue"
  },
  "geometry": {"coordinates":[-82.8705,39.898729],"type":"Point"}
}
