{
  "type": "Feature",
  "properties": {
    "iso:country":"US",
    "sg:address":"500 E Park St",
    "sg:city":"Fort Loramie",
    "sg:classifiers":[
        {
            "category":"Banks & Credit Unions",
            "subcategory":"Bank",
            "type":"Services"
        }
    ],
    "sg:phone":"+1 937 295 2900",
    "sg:postcode":"45845",
    "sg:province":"OH",
    "wof:name":"Osgood State Bank",
    "wof:placetype":"venue"
},
  "geometry": {"coordinates":[-84.36682399999999,40.347952],"type":"Point"}
}