{
  "type": "Feature",
  "properties": {
    "addr:full": "500 E Park St Fort Loramie OH 45845",
    "addr:housenumber": "500",
    "addr:postcode": "45845",
    "addr:street": "E Park St",
    "iso:country": "US",
    "sg:address": "500 E Park St",
    "sg:city": "Fort Loramie",
    "sg:classifiers": [
      {
        "category": "Banks \u0026 Credit Unions",
        "subcategory": "Bank",
        "type": "Services"
      }
    ],
    "sg:phone": "+1 937 295 2900",
    "sg:postcode": "45845",
    "sg:province": "OH",
    "wof:name": "Osgood State Bank",
    "wof:placetype": "venue"
  },
  "geometry": {"coordinates":[-84.366824,40.347952],"type":"Point"}
}
