{
  "type": "Feature",
  "properties": {
    "addr:full":"1460 Manchester Rd Akron OH 44314",
    "addr:housenumber":"1460",
    "addr:postcode":"44314",
    "addr:street":"Manchester Rd",
    "iso:country":"US",
    "sg:address":"1460 Manchester Rd",
    "sg:city":"Akron",
    "sg:classifiers":[
        {
            "category":"Professional",
            "type":"Services"
        }
    ],
    "sg:phone":"+1 330 745 2410",
    "sg:postcode":"44314",
    "sg:province":"OH",
    "sg:tags":[
        "establishment"
    ],
    "wof:name":"Jaffery Union Of NE Ohio",
    "wof:placetype":"venue"
},
  "geometry": {"coordinates":[-81.550314,41.059129],"type":"Point"}
}