{
  "type": "Feature",
  "properties": {
    "iso:country":"US",
    "sg:address":"3700 Kolbe Rd",
    "sg:city":"Lorain",
    "sg:classifiers":[
        {
            "category":"Health Services",
            "subcategory":"Doctor",
            "type":"Services"
        },
        {
            "category":"Health Services",
            "subcategory":"Hospital",
            "type":"Services"
        },
        {
            "category":"Community Center",
            "type":"Public Place"
        }
    ],
    "sg:phone":"+1 440 960 4000",
    "sg:postcode":"44053",
    "sg:province":"OH",
    "sg:tags":[
        "physician",
        "medical",
        "surgeon"
    ],
    "sg:website":"http://www.community-health-partners.com",
    "wof:name":"Community Regional Medical Center",
    "wof:placetype":"venue"
},
  "geometry": {"coordinates":[-82.235252,41.43679],"type":"Point"}
}