{
  "type": "Feature",
  "properties": {
    "addr:full": "1855 Mechanicsburg Rd Wooster OH 44691",
    "addr:housenumber": "1855",
    "addr:postcode": "44691",
    "addr:street": "Mechanicsburg Rd",
    "iso:country": "US",
    "sg:address": "1855 Mechanicsburg Rd",
    "sg:city": "Wooster",
    "sg:classifiers": [
      {
        "category": "Real Estate",
        "subcategory": "Real Estate Operator",
        "type": "Services"
      }
    ],
    "sg:phone": "+1 330 262 1717",
    "sg:postcode": "44691",
    "sg:province": "OH",
    "sg:tags": [
      "building",
      "apartment"
    ],
    "wof:name": "Summit Place Apartments",
    "wof:placetype": "venue"
  },
  "geometry": {"coordinates":[-81.96275,40.821107],"type":"Point"}
}
