{
  "type": "Feature",
  "properties": {
    "iso:country":"US",
    "sg:address":"27 Oak St",
    "sg:city":"Shelby",
    "sg:classifiers":[
        {
            "category":"Building & Trades",
            "subcategory":"Construction",
            "type":"Services"
        }
    ],
    "sg:phone":"+1 419 544 4544",
    "sg:postcode":"44875",
    "sg:province":"OH",
    "sg:tags":[
        "hanging",
        "contractor"
    ],
    "wof:name":"Kinkel Wallcovering Paintings",
    "wof:placetype":"venue"
},
  "geometry": {"coordinates":[-82.65375400000001,40.884283],"type":"Point"}
}