{
  "type": "Feature",
  "properties": {
    "addr:full": "27 Oak St Shelby OH 44875",
    "addr:housenumber": "27",
    "addr:postcode": "44875",
    "addr:street": "Oak St",
    "iso:country": "US",
    "sg:address": "27 Oak St",
    "sg:city": "Shelby",
    "sg:classifiers": [
      {
        "category": "Building \u0026 Trades",
        "subcategory": "Construction",
        "type": "Services"
      }
    ],
    "sg:phone": "+1 419 544 4544",
    "sg:postcode": "44875",
    "sg:province": "OH",
    "sg:tags": [
      "hanging",
      "contractor"
    ],
    "wof:name": "Kinkel Wallcovering Paintings",
    "wof:placetype": "venue"
  },
  "geometry": {"coordinates":[-82.653754,40.884283],"type":"Point"}
}
