{
  "type": "Feature",
  "properties": {
    "iso:country":"US",
    "sg:address":"812 Stryker St",
    "sg:city":"Archbold",
    "sg:classifiers":[
        {
            "category":"Retail",
            "subcategory":"Car Wash",
            "type":"Services"
        }
    ],
    "sg:phone":"+1 419 445 5491",
    "sg:postcode":"43502",
    "sg:province":"OH",
    "sg:tags":[
        "polishing",
        "washing"
    ],
    "wof:name":"Super Wash Inc",
    "wof:placetype":"venue"
},
  "geometry": {"coordinates":[-84.318089,41.521606],"type":"Point"}
}