{
  "type": "Feature",
  "properties": {
    "addr:full": "226 S 5th St Byesville OH 43723",
    "addr:housenumber": "226",
    "addr:postcode": "43723",
    "addr:street": "S 5Th St",
    "iso:country": "US",
    "sg:address": "226 S 5th St",
    "sg:city": "Byesville",
    "sg:classifiers": [
      {
        "category": "Social Services",
        "type": "Services"
      }
    ],
    "sg:phone": "+1 740 685 7636",
    "sg:postcode": "43723",
    "sg:province": "OH",
    "sg:tags": [
      "organization",
      "welfare"
    ],
    "wof:name": "Southeast Ohio Disaster Relief",
    "wof:placetype": "venue"
  },
  "geometry": {"coordinates":[-81.54185,39.96837],"type":"Point"}
}
