{
  "type": "Feature",
  "properties": {
    "addr:full": "3543 Williams Lake Rd SW New Philadelphia OH 44663",
    "addr:housenumber": "3543",
    "addr:postcode": "44663",
    "addr:street": "Williams Lake Rd Sw",
    "iso:country": "US",
    "sg:address": "3543 Williams Lake Rd SW",
    "sg:city": "New Philadelphia",
    "sg:classifiers": [
      {
        "category": "Farming",
        "subcategory": "Livestock Farm",
        "type": "Manufacturing \u0026 Wholesale Goods"
      }
    ],
    "sg:phone": "+1 330 339 3982",
    "sg:postcode": "44663",
    "sg:province": "OH",
    "sg:tags": [
      "beef",
      "corn",
      "crop",
      "field",
      "cattle",
      "feedlot"
    ],
    "wof:name": "Degen Farm",
    "wof:placetype": "venue"
  },
  "geometry": {"coordinates":[-81.528143,40.398634],"type":"Point"}
}
