{
  "type": "Feature",
  "properties": {
    "addr:full":"328 S Todd St Mc Comb OH 45858",
    "addr:housenumber":"328",
    "addr:postcode":"45858",
    "addr:street":"S Todd St Mc Comb",
    "iso:country":"US",
    "sg:address":"328 S Todd St",
    "sg:city":"Mc Comb",
    "sg:classifiers":[
        {
            "category":"Education",
            "subcategory":"School",
            "type":"Public Place"
        }
    ],
    "sg:phone":"+1 419 293 3161",
    "sg:postcode":"45858",
    "sg:province":"OH",
    "wof:name":"Mc Comb Schools",
    "wof:placetype":"venue"
},
  "geometry": {"coordinates":[-83.791405,41.10381],"type":"Point"}
}