{
  "type": "Feature",
  "properties": {
    "addr:full": "1210 N Byrne Rd Toledo OH 43607",
    "addr:housenumber": "1210",
    "addr:postcode": "43607",
    "addr:street": "N Byrne Rd",
    "iso:country": "US",
    "sg:address": "1210 N Byrne Rd",
    "sg:city": "Toledo",
    "sg:classifiers": [
      {
        "category": "Food \u0026 Beverages",
        "subcategory": "Groceries \u0026 Convenience Stores",
        "type": "Retail Goods"
      }
    ],
    "sg:phone": "+1 419 531 8478",
    "sg:postcode": "43607",
    "sg:province": "OH",
    "wof:name": "Excell Food Inc",
    "wof:placetype": "venue"
  },
  "geometry": {"coordinates":[-83.625902,41.651221],"type":"Point"}
}
