{
  "type": "Feature",
  "properties": {
    "iso:country":"US",
    "sg:address":"1210 N Byrne Rd",
    "sg:city":"Toledo",
    "sg:classifiers":[
        {
            "category":"Food & Beverages",
            "subcategory":"Groceries & Convenience Stores",
            "type":"Retail Goods"
        }
    ],
    "sg:phone":"+1 419 531 8478",
    "sg:postcode":"43607",
    "sg:province":"OH",
    "wof:name":"Excell Food Inc",
    "wof:placetype":"venue"
},
  "geometry": {"coordinates":[-83.625902,41.651221],"type":"Point"}
}