{
  "type": "Feature",
  "properties": {
    "iso:country":"US",
    "sg:address":"311 N Seltzer St",
    "sg:city":"Crestline",
    "sg:classifiers":[
        {
            "category":"Shopping",
            "subcategory":"Pharmacy",
            "type":"Retail Goods"
        }
    ],
    "sg:phone":"+1 419 683 2512",
    "sg:postcode":"44827",
    "sg:province":"OH",
    "wof:name":"Rite Aid Pharmacy",
    "wof:placetype":"venue"
},
  "geometry": {"coordinates":[-82.73654000000001,40.786369],"type":"Point"}
}