{
  "type": "Feature",
  "properties": {
    "addr:full": "9516 E Harbor Rd Lakeside Marblhd OH 43440",
    "addr:housenumber": "9516 e",
    "addr:postcode": "43440",
    "addr:street": "Harbor Rd",
    "iso:country": "US",
    "sg:address": "9516 E Harbor Rd",
    "sg:city": "Lakeside Marblhd",
    "sg:classifiers": [
      {
        "category": "Shopping",
        "type": "Retail Goods"
      }
    ],
    "sg:phone": "+1 419 798 5060",
    "sg:postcode": "43440",
    "sg:province": "OH",
    "sg:tags": [
      "wood",
      "carving"
    ],
    "wof:name": "Country Woodcrafter",
    "wof:placetype": "venue"
  },
  "geometry": {"coordinates":[-82.7529,41.536461],"type":"Point"}
}
