{
  "type": "Feature",
  "properties": {
    "addr:full":"650 Valley Ridge Ct Troy OH 45373",
    "addr:housenumber":"650",
    "addr:postcode":"45373",
    "addr:street":"Valley Ridge Ct",
    "iso:country":"US",
    "sg:address":"650 Valley Ridge Ct",
    "sg:city":"Troy",
    "sg:classifiers":[
        {
            "category":"Wholesale",
            "subcategory":"Durable Goods & Equipment",
            "type":"Manufacturing & Wholesale Goods"
        }
    ],
    "sg:phone":"+1 937 339 3748",
    "sg:postcode":"45373",
    "sg:province":"OH",
    "sg:tags":[
        "representative",
        "manufacturer"
    ],
    "wof:name":"Hawks Sales Corp",
    "wof:placetype":"venue"
},
  "geometry": {"coordinates":[-84.21374900000001,40.014269],"type":"Point"}
}