{
  "type": "Feature",
  "properties": {
    "addr:full":"7300 Longano Dr Cleveland OH 44131",
    "addr:housenumber":"7300",
    "addr:postcode":"44131",
    "addr:street":"Longano Dr",
    "iso:country":"US",
    "sg:address":"7300 Longano Dr",
    "sg:city":"Cleveland",
    "sg:classifiers":[
        {
            "category":"Manufacturing",
            "subcategory":"Tools & Machinery",
            "type":"Manufacturing & Wholesale Goods"
        }
    ],
    "sg:phone":"+1 216 524 2148",
    "sg:postcode":"44131",
    "sg:province":"OH",
    "sg:tags":[
        "machine",
        "mfg"
    ],
    "wof:name":"L&L Machine Co",
    "wof:placetype":"venue"
},
  "geometry": {"coordinates":[-81.635346,41.40238],"type":"Point"}
}