{
  "type": "Feature",
  "properties": {
    "addr:full":"112 Logan St Bedford OH 44146",
    "addr:housenumber":"112",
    "addr:postcode":"44146",
    "addr:street":"Logan St",
    "iso:country":"US",
    "sg:address":"112 Logan St",
    "sg:city":"Bedford",
    "sg:classifiers":[
        {
            "category":"Shopping",
            "subcategory":"Clothing, Apparel, & Fashions",
            "type":"Retail Goods"
        }
    ],
    "sg:phone":"+1 440 232 7080",
    "sg:postcode":"44146",
    "sg:province":"OH",
    "wof:name":"Cuyahoga Police & Fire Spc",
    "wof:placetype":"venue"
},
  "geometry": {"coordinates":[-81.532873,41.39716],"type":"Point"}
}