{
  "type": "Feature",
  "properties": {
    "iso:country":"US",
    "sg:address":"27251 Markbarry Ave",
    "sg:city":"Cleveland",
    "sg:classifiers":[
        {
            "category":"Shopping",
            "subcategory":"Catalog Store",
            "type":"Retail Goods"
        }
    ],
    "sg:phone":"+1 216 731 1991",
    "sg:postcode":"44132",
    "sg:province":"OH",
    "sg:tags":[
        "internet"
    ],
    "wof:name":"Paul's Gift World",
    "wof:placetype":"venue"
},
  "geometry": {"coordinates":[-81.490241,41.616045],"type":"Point"}
}