{
  "type": "Feature",
  "properties": {
    "addr:full": "1450 Coventry Rd Dayton OH 45410",
    "addr:housenumber": "1450",
    "addr:postcode": "45410",
    "addr:street": "Coventry Rd",
    "iso:country": "US",
    "sg:address": "1450 Coventry Rd",
    "sg:city": "Dayton",
    "sg:classifiers": [
      {
        "category": "Organizations",
        "subcategory": "Religious Organization",
        "type": "Services"
      }
    ],
    "sg:phone": "+1 937 252 9152",
    "sg:postcode": "45410",
    "sg:province": "OH",
    "sg:tags": [
      "monastery",
      "convent"
    ],
    "wof:name": "Sisters Of Notre Dame",
    "wof:placetype": "venue"
  },
  "geometry": {"coordinates":[-84.1429,39.747408],"type":"Point"}
}
