{
  "type": "Feature",
  "properties": {
    "iso:country":"US",
    "sg:address":"500 W State St",
    "sg:city":"Fremont",
    "sg:classifiers":[
        {
            "category":"Professional",
            "subcategory":"Business Services",
            "type":"Services"
        }
    ],
    "sg:phone":"+1 419 332 9511",
    "sg:postcode":"43420",
    "sg:province":"OH",
    "sg:tags":[
        "license"
    ],
    "wof:name":"Motor Vehicle Dept",
    "wof:placetype":"venue"
},
  "geometry": {"coordinates":[-83.116614,41.348566],"type":"Point"}
}