{
  "type": "Feature",
  "properties": {
    "addr:full":"601 Hill St Middletown OH 45042",
    "addr:housenumber":"601",
    "addr:postcode":"45042",
    "addr:street":"Hill St",
    "iso:country":"US",
    "sg:address":"601 Hill St",
    "sg:city":"Middletown",
    "sg:classifiers":[
        {
            "category":"Building & Trades",
            "subcategory":"Construction",
            "type":"Services"
        }
    ],
    "sg:phone":"+1 513 422 3445",
    "sg:postcode":"45042",
    "sg:province":"OH",
    "sg:tags":[
        "general",
        "contractor"
    ],
    "wof:name":"Old School Construction Co",
    "wof:placetype":"venue"
},
  "geometry": {"coordinates":[-84.422203,39.523573],"type":"Point"}
}