{
  "type": "Feature",
  "properties": {
    "addr:full": "136 W 5th Ave Columbus OH 43201",
    "addr:housenumber": "136",
    "addr:postcode": "43201",
    "addr:street": "W 5Th Ave",
    "iso:country": "US",
    "sg:address": "136 W 5th Ave",
    "sg:city": "Columbus",
    "sg:classifiers": [
      {
        "category": "Building \u0026 Trades",
        "subcategory": "Plumbing",
        "type": "Services"
      }
    ],
    "sg:phone": "+1 614 291 3131",
    "sg:postcode": "43201",
    "sg:province": "OH",
    "sg:tags": [
      "plumbing",
      "contractor"
    ],
    "wof:name": "Benjamin Franklin The Punctual",
    "wof:placetype": "venue"
  },
  "geometry": {"coordinates":[-83.008511,39.987286],"type":"Point"}
}
