{
  "type": "Feature",
  "properties": {
    "iso:country":"US",
    "sg:address":"136 W 5th Ave",
    "sg:city":"Columbus",
    "sg:classifiers":[
        {
            "category":"Building & Trades",
            "subcategory":"Plumbing",
            "type":"Services"
        }
    ],
    "sg:phone":"+1 614 291 3131",
    "sg:postcode":"43201",
    "sg:province":"OH",
    "sg:tags":[
        "plumbing",
        "contractor"
    ],
    "wof:name":"Benjamin Franklin The Punctual",
    "wof:placetype":"venue"
},
  "geometry": {"coordinates":[-83.008511,39.987286],"type":"Point"}
}