{
  "type": "Feature",
  "properties": {
    "iso:country":"US",
    "sg:address":"5660 Julmar Dr",
    "sg:city":"Cincinnati",
    "sg:classifiers":[
        {
            "category":"Real Estate",
            "subcategory":"Real Estate Agent",
            "type":"Services"
        }
    ],
    "sg:phone":"+1 513 922 5666",
    "sg:postcode":"45238",
    "sg:province":"OH",
    "sg:tags":[
        "agency"
    ],
    "wof:name":"Steve Junker Realtors",
    "wof:placetype":"venue"
},
  "geometry": {"coordinates":[-84.63076100000001,39.1236],"type":"Point"}
}