{
  "type": "Feature",
  "properties": {
    "addr:full": "7629 Mountain Park Dr Mentor OH 44060",
    "addr:housenumber": "7629",
    "addr:postcode": "44060",
    "addr:street": "Mountain Park Dr",
    "iso:country": "US",
    "sg:address": "7629 Mountain Park Dr",
    "sg:city": "Mentor",
    "sg:classifiers": [
      {
        "category": "Restaurant",
        "type": "Food \u0026 Drink"
      }
    ],
    "sg:phone": "+1 440 350 1879",
    "sg:postcode": "44060",
    "sg:province": "OH",
    "sg:tags": [
      "eating"
    ],
    "wof:name": "Mama Primozz Pizza and Catrg",
    "wof:placetype": "venue"
  },
  "geometry": {"coordinates":[-81.287875,41.664311],"type":"Point"}
}
