{
  "type": "Feature",
  "properties": {
    "addr:full":"140 W 6th St East Liverpool OH 43920",
    "addr:housenumber":"140",
    "addr:postcode":"43920",
    "addr:street":"W 6Th St",
    "iso:country":"US",
    "sg:address":"140 W 6th St",
    "sg:city":"East Liverpool",
    "sg:classifiers":[
        {
            "category":"Freight",
            "type":"Transportation"
        }
    ],
    "sg:phone":"+1 330 424 6544",
    "sg:postcode":"43920",
    "sg:province":"OH",
    "sg:tags":[
        "special"
    ],
    "wof:name":"Ferguson Fun Food",
    "wof:placetype":"venue"
},
  "geometry": {"coordinates":[-80.58048599999999,40.620445],"type":"Point"}
}