{
  "type": "Feature",
  "properties": {
    "addr:full": "2763 Westbelt Dr Columbus OH 43228",
    "addr:housenumber": "2763",
    "addr:postcode": "43228",
    "addr:street": "Westbelt Dr",
    "iso:country": "US",
    "sg:address": "2763 Westbelt Dr",
    "sg:city": "Columbus",
    "sg:classifiers": [
      {
        "category": "Shopping",
        "subcategory": "Discount \u0026 Variety Stores",
        "type": "Retail Goods"
      }
    ],
    "sg:phone": "+1 614 527 4645",
    "sg:postcode": "43228",
    "sg:province": "OH",
    "sg:tags": [
      "merchandise",
      "general"
    ],
    "wof:name": "Moc Products Co Inc",
    "wof:placetype": "venue"
  },
  "geometry": {"coordinates":[-83.12314,40.003478],"type":"Point"}
}
