{
  "type": "Feature",
  "properties": {
    "addr:full":"947 Antwerp Rd Columbus OH 43213",
    "addr:housenumber":"947",
    "addr:postcode":"43213",
    "addr:street":"Antwerp Rd",
    "iso:country":"US",
    "sg:address":"947 Antwerp Rd",
    "sg:city":"Columbus",
    "sg:classifiers":[
        {
            "category":"Real Estate",
            "subcategory":"Surveying",
            "type":"Services"
        }
    ],
    "sg:phone":"+1 614 866 1625",
    "sg:postcode":"43213",
    "sg:province":"OH",
    "sg:tags":[
        "surveyor"
    ],
    "sg:website":"www.pssllc.com",
    "wof:name":"Precision Surveying Svc",
    "wof:placetype":"venue"
},
  "geometry": {"coordinates":[-82.862314,39.958406],"type":"Point"}
}