{
  "type": "Feature",
  "properties": {
    "addr:full": "1464 W 5th Ave Columbus OH 43212",
    "addr:housenumber": "1464",
    "addr:postcode": "43212",
    "addr:street": "W 5Th Ave",
    "iso:country": "US",
    "sg:address": "1464 W 5th Ave",
    "sg:city": "Columbus",
    "sg:classifiers": [
      {
        "category": "Shopping",
        "subcategory": "Books",
        "type": "Retail Goods"
      }
    ],
    "sg:phone": "+1 614 486 1860",
    "sg:postcode": "43212",
    "sg:province": "OH",
    "sg:tags": [
      "dealer"
    ],
    "wof:name": "Acorn Bookshop Inc",
    "wof:placetype": "venue"
  },
  "geometry": {"coordinates":[-83.044925,39.988882],"type":"Point"}
}
