{
  "type": "Feature",
  "properties": {
    "iso:country":"US",
    "sg:address":"934 Toronto Ave",
    "sg:city":"Toledo",
    "sg:classifiers":[
        {
            "category":"Building & Trades",
            "subcategory":"Construction",
            "type":"Services"
        }
    ],
    "sg:phone":"+1 419 380 0538",
    "sg:postcode":"43609",
    "sg:province":"OH",
    "sg:tags":[
        "hanging",
        "contractor"
    ],
    "wof:name":"D & R Professional Painting &",
    "wof:placetype":"venue"
},
  "geometry": {"coordinates":[-83.585716,41.622187],"type":"Point"}
}