{
  "type": "Feature",
  "properties": {
    "iso:country":"US",
    "sg:address":"1627 Wigwam Trl",
    "sg:city":"Xenia",
    "sg:classifiers":[
        {
            "category":"Professional",
            "subcategory":"Computer Services",
            "type":"Services"
        }
    ],
    "sg:phone":"+1 937 376 0104",
    "sg:postcode":"45385",
    "sg:province":"OH",
    "sg:tags":[
        "consultant",
        "designer"
    ],
    "wof:name":"5-Star Solutions",
    "wof:placetype":"venue"
},
  "geometry": {"coordinates":[-83.956369,39.67591],"type":"Point"}
}