{
  "type": "Feature",
  "properties": {
    "addr:full":"900 Michigan Ave Columbus OH 43215",
    "addr:housenumber":"900",
    "addr:postcode":"43215",
    "addr:street":"Michigan Ave",
    "iso:country":"US",
    "sg:address":"900 Michigan Ave",
    "sg:city":"Columbus",
    "sg:classifiers":[
        {
            "category":"Banks & Credit Unions",
            "subcategory":"Financial Services",
            "type":"Services"
        }
    ],
    "sg:phone":"+1 614 645 6171",
    "sg:postcode":"43215",
    "sg:province":"OH",
    "sg:tags":[
        "loan"
    ],
    "sg:website":"http://www.ccdcorp.org",
    "wof:name":"C C D C",
    "wof:placetype":"venue"
},
  "geometry": {"coordinates":[-83.01712000000001,39.97913],"type":"Point"}
}