{
  "type": "Feature",
  "properties": {
    "iso:country":"US",
    "sg:address":"25 Deep Creek Ln",
    "sg:city":"Chagrin Falls",
    "sg:classifiers":[
        {
            "category":"Wholesale",
            "subcategory":"Electrical",
            "type":"Manufacturing & Wholesale Goods"
        }
    ],
    "sg:phone":"+1 440 247 7006",
    "sg:postcode":"44022",
    "sg:province":"OH",
    "sg:tags":[
        "parts",
        "electronic"
    ],
    "wof:name":"E Squared",
    "wof:placetype":"venue"
},
  "geometry": {"coordinates":[-81.441,41.447288],"type":"Point"}
}