{
  "type": "Feature",
  "properties": {
    "iso:country":"US",
    "sg:address":"1275 Polaris Pkwy",
    "sg:city":"Columbus",
    "sg:classifiers":[
        {
            "category":"Home & Garden",
            "subcategory":"Furniture",
            "type":"Retail Goods"
        }
    ],
    "sg:phone":"+1 614 847 4279",
    "sg:postcode":"43240",
    "sg:province":"OH",
    "wof:name":"Arhaus Furniture",
    "wof:placetype":"venue"
},
  "geometry": {"coordinates":[-82.988657,40.142866],"type":"Point"}
}