{
  "type": "Feature",
  "properties": {
    "addr:full":"131 Youngstown Warren Rd Niles OH 44446",
    "addr:housenumber":"131",
    "addr:postcode":"44446",
    "addr:street":"Youngstown Warren Rd",
    "iso:country":"US",
    "sg:address":"131 Youngstown Warren Rd",
    "sg:city":"Niles",
    "sg:classifiers":[
        {
            "category":"Wholesale",
            "subcategory":"Groceries",
            "type":"Manufacturing & Wholesale Goods"
        }
    ],
    "sg:phone":"+1 330 518 8000",
    "sg:postcode":"44446",
    "sg:province":"OH",
    "sg:tags":[
        "product",
        "related"
    ],
    "wof:name":"Carnation Wholesale Inc LLC",
    "wof:placetype":"venue"
},
  "geometry": {"coordinates":[-80.71895499999999,41.183615],"type":"Point"}
}