{
  "type": "Feature",
  "properties": {
    "iso:country":"US",
    "sg:address":"12341 Emerson Rd",
    "sg:city":"Apple Creek",
    "sg:classifiers":[
        {
            "category":"Wholesale",
            "subcategory":"Machinery & Supplies",
            "type":"Manufacturing & Wholesale Goods"
        }
    ],
    "sg:phone":"+1 330 857 6955",
    "sg:postcode":"44606",
    "sg:province":"OH",
    "sg:tags":[
        "farm",
        "repair",
        "equipment"
    ],
    "sg:website":"www.kidronsupply.com",
    "wof:name":"Kidron Supply Inc",
    "wof:placetype":"venue"
},
  "geometry": {"coordinates":[-81.759747,40.74109],"type":"Point"}
}