{
  "type": "Feature",
  "properties": {
    "addr:full": "957 Grosjean Rd Wooster OH 44691",
    "addr:housenumber": "957",
    "addr:postcode": "44691",
    "addr:street": "Grosjean Rd",
    "iso:country": "US",
    "sg:address": "957 Grosjean Rd",
    "sg:city": "Wooster",
    "sg:classifiers": [
      {
        "category": "Food \u0026 Beverages",
        "subcategory": "Groceries \u0026 Convenience Stores",
        "type": "Retail Goods"
      }
    ],
    "sg:phone": "+1 330 263 9967",
    "sg:postcode": "44691",
    "sg:province": "OH",
    "sg:tags": [
      "meat"
    ],
    "wof:name": "Walnut Creek Kitchen",
    "wof:placetype": "venue"
  },
  "geometry": {"coordinates":[-81.936372,40.788809],"type":"Point"}
}
