{
  "type": "Feature",
  "properties": {
    "addr:full":"3255 W Siebenthaler Ave Dayton OH 45406",
    "addr:housenumber":"3255",
    "addr:postcode":"45406",
    "addr:street":"W Siebenthaler Ave",
    "iso:country":"US",
    "sg:address":"3255 W Siebenthaler Ave",
    "sg:city":"Dayton",
    "sg:classifiers":[
        {
            "category":"Shopping",
            "type":"Retail Goods"
        }
    ],
    "sg:phone":"+1 937 277 9700",
    "sg:postcode":"45406",
    "sg:province":"OH",
    "sg:tags":[
        "merchandise"
    ],
    "wof:name":"Pager Place One",
    "wof:placetype":"venue"
},
  "geometry": {"coordinates":[-84.244686,39.798206],"type":"Point"}
}