{
  "type": "Feature",
  "properties": {
    "iso:country":"US",
    "sg:address":"2405 N Columbus St",
    "sg:city":"Lancaster",
    "sg:classifiers":[
        {
            "category":"Health Services",
            "subcategory":"Doctor",
            "type":"Services"
        }
    ],
    "sg:phone":"+1 740 681 9905",
    "sg:postcode":"43130",
    "sg:province":"OH",
    "sg:tags":[
        "medical"
    ],
    "wof:name":"Ohio Physcl Mdcine Rhabilation",
    "wof:placetype":"venue"
},
  "geometry": {"coordinates":[-82.63182399999999,39.740598],"type":"Point"}
}