{
  "type": "Feature",
  "properties": {
    "iso:country":"US",
    "sg:address":"3619 Olde Falls Rd",
    "sg:city":"Zanesville",
    "sg:classifiers":[
        {
            "category":"Autos & Motor Vehicles",
            "subcategory":"Auto Supplies",
            "type":"Retail Goods"
        }
    ],
    "sg:phone":"+1 740 453 4660",
    "sg:postcode":"43701",
    "sg:province":"OH",
    "sg:tags":[
        "customizes",
        "van",
        "accessory"
    ],
    "wof:name":"Custom Vans of Zanesville Inc",
    "wof:placetype":"venue"
},
  "geometry": {"coordinates":[-82.04874,39.983681],"type":"Point"}
}