{
  "type": "Feature",
  "properties": {
    "addr:full": "165 W Center St London OH 43140",
    "addr:housenumber": "165",
    "addr:postcode": "43140",
    "addr:street": "W Center St",
    "iso:country": "US",
    "sg:address": "165 W Center St",
    "sg:city": "London",
    "sg:classifiers": [
      {
        "category": "Restaurant",
        "type": "Food \u0026 Drink"
      }
    ],
    "sg:phone": "+1 740 852 3055",
    "sg:postcode": "43140",
    "sg:province": "OH",
    "sg:tags": [
      "eating"
    ],
    "wof:name": "Gees China Lantern",
    "wof:placetype": "venue"
  },
  "geometry": {"coordinates":[-83.44861,39.880594],"type":"Point"}
}
