{
  "type": "Feature",
  "properties": {
    "addr:full":"206 Wooster Rd Mount Vernon OH 43050",
    "addr:housenumber":"206",
    "addr:postcode":"43050",
    "addr:street":"Wooster Rd",
    "iso:country":"US",
    "sg:address":"206 Wooster Rd",
    "sg:city":"Mount Vernon",
    "sg:classifiers":[
        {
            "category":"Restaurant",
            "type":"Food & Drink"
        }
    ],
    "sg:phone":"+1 740 392 3238",
    "sg:postcode":"43050",
    "sg:province":"OH",
    "sg:tags":[
        "ice",
        "cream"
    ],
    "wof:name":"Youngs Drive In",
    "wof:placetype":"venue"
},
  "geometry": {"coordinates":[-82.48144499999999,40.402622],"type":"Point"}
}