{
  "type": "Feature",
  "properties": {
    "addr:full": "10870 Hamilton Ave Cincinnati OH 45231",
    "addr:housenumber": "10870",
    "addr:postcode": "45231",
    "addr:street": "Hamilton Ave",
    "iso:country": "US",
    "sg:address": "10870 Hamilton Ave",
    "sg:city": "Cincinnati",
    "sg:classifiers": [
      {
        "category": "Social Services",
        "subcategory": "Child Care",
        "type": "Services"
      },
      {
        "category": "Home \u0026 Garden",
        "subcategory": "Garden Supply",
        "type": "Retail Goods"
      }
    ],
    "sg:phone": "+1 513 742 0636",
    "sg:postcode": "45231",
    "sg:province": "OH",
    "sg:tags": [
      "item",
      "nurseryman",
      "craft",
      "day"
    ],
    "sg:website": "www.franksnursery.com",
    "wof:name": "Franks Nursery \u0026 Crafts Inc",
    "wof:placetype": "venue"
  },
  "geometry": {"coordinates":[-84.56268,39.275017],"type":"Point"}
}
