{
  "type": "Feature",
  "properties": {
    "iso:country":"US",
    "sg:address":"10870 Hamilton Ave",
    "sg:city":"Cincinnati",
    "sg:classifiers":[
        {
            "category":"Social Services",
            "subcategory":"Child Care",
            "type":"Services"
        },
        {
            "category":"Home & Garden",
            "subcategory":"Garden Supply",
            "type":"Retail Goods"
        }
    ],
    "sg:phone":"+1 513 742 0636",
    "sg:postcode":"45231",
    "sg:province":"OH",
    "sg:tags":[
        "item",
        "nurseryman",
        "craft",
        "day"
    ],
    "sg:website":"www.franksnursery.com",
    "wof:name":"Franks Nursery & Crafts Inc",
    "wof:placetype":"venue"
},
  "geometry": {"coordinates":[-84.56268,39.275017],"type":"Point"}
}