{
  "type": "Feature",
  "properties": {
    "iso:country":"US",
    "sg:address":"6415 Tantamount Ln",
    "sg:city":"Dayton",
    "sg:classifiers":[
        {
            "category":"Health Services",
            "subcategory":"Doctor",
            "type":"Services"
        }
    ],
    "sg:phone":"+1 937 435 8887",
    "sg:postcode":"45449",
    "sg:province":"OH",
    "sg:tags":[
        "physician",
        "surgeon"
    ],
    "wof:name":"John Matthews MD",
    "wof:placetype":"venue"
},
  "geometry": {"coordinates":[-84.231343,39.647556],"type":"Point"}
}