{
  "type": "Feature",
  "properties": {
    "addr:full":"4538 Sabina Rd Sabina OH 45169",
    "addr:housenumber":"4538",
    "addr:postcode":"45169",
    "addr:street":"Sabina Rd",
    "iso:country":"US",
    "sg:address":"4538 Sabina Rd",
    "sg:city":"Sabina",
    "sg:classifiers":[
        {
            "category":"Building & Trades",
            "subcategory":"Landscaping Services",
            "type":"Services"
        }
    ],
    "sg:phone":"+1 937 382 7505",
    "sg:postcode":"45169",
    "sg:province":"OH",
    "sg:tags":[
        "lawn",
        "maintenance",
        "grounds"
    ],
    "wof:name":"Haggerty Lawn Maintenance",
    "wof:placetype":"venue"
},
  "geometry": {"coordinates":[-83.739046,39.511079],"type":"Point"}
}