{
  "type": "Feature",
  "properties": {
    "addr:full":"5181 Hardin-Wapakoneta Rd Sidney OH 45365",
    "addr:housenumber":"5181",
    "addr:postcode":"45365",
    "addr:street":"Hardin-Wapakoneta Rd",
    "iso:country":"US",
    "sg:address":"5181 Hardin-Wapakoneta Rd",
    "sg:city":"Sidney",
    "sg:classifiers":[
        {
            "category":"Wholesale",
            "subcategory":"Machinery & Supplies",
            "type":"Manufacturing & Wholesale Goods"
        }
    ],
    "sg:phone":"+1 937 492 6096",
    "sg:postcode":"45365",
    "sg:province":"OH",
    "sg:tags":[
        "equipment",
        "printing"
    ],
    "wof:name":"K A Bindery Equipment Co",
    "wof:placetype":"venue"
},
  "geometry": {"coordinates":[-84.24484,40.272464],"type":"Point"}
}