{
  "type": "Feature",
  "properties": {
    "addr:full": "27889 White Rd Perrysburg OH 43551",
    "addr:housenumber": "27889",
    "addr:postcode": "43551",
    "addr:street": "White Rd",
    "iso:country": "US",
    "sg:address": "27889 White Rd",
    "sg:city": "Perrysburg",
    "sg:classifiers": [
      {
        "category": "Wholesale",
        "subcategory": "Medical Equipment \u0026 Supplies",
        "type": "Manufacturing \u0026 Wholesale Goods"
      }
    ],
    "sg:phone": "+1 419 872 0911",
    "sg:postcode": "43551",
    "sg:province": "OH",
    "wof:name": "Universal Medical Products",
    "wof:placetype": "venue"
  },
  "geometry": {"coordinates":[-83.608758,41.558598],"type":"Point"}
}
