{
  "type": "Feature",
  "properties": {
    "addr:full": "3300 Harrison Ave Cincinnati OH 45211",
    "addr:housenumber": "3300",
    "addr:postcode": "45211",
    "addr:street": "Harrison Ave",
    "iso:country": "US",
    "sg:address": "3300 Harrison Ave",
    "sg:city": "Cincinnati",
    "sg:classifiers": [
      {
        "category": "Banks \u0026 Credit Unions",
        "subcategory": "Bank",
        "type": "Services"
      }
    ],
    "sg:phone": "+1 513 661 6903",
    "sg:postcode": "45211",
    "sg:province": "OH",
    "sg:tags": [
      "loan",
      "state",
      "insured",
      "savings",
      "chartered",
      "association"
    ],
    "sg:website": "www.cincinnatussl.com",
    "wof:name": "Cincinnatus Savings \u0026 Loan Co",
    "wof:placetype": "venue"
  },
  "geometry": {"coordinates":[-84.605826,39.155359],"type":"Point"}
}
