{
  "type": "Feature",
  "properties": {
    "addr:full":"125 Springhouse Dr Union OH 45322",
    "addr:housenumber":"125",
    "addr:postcode":"45322",
    "addr:street":"Springhouse Dr",
    "iso:country":"US",
    "sg:address":"125 Springhouse Dr",
    "sg:city":"Union",
    "sg:classifiers":[
        {
            "category":"Organizations",
            "subcategory":"Professional Association",
            "type":"Services"
        }
    ],
    "sg:phone":"+1 937 836 7894",
    "sg:postcode":"45322",
    "sg:province":"OH",
    "wof:name":"Irongate Estates Comm Assn",
    "wof:placetype":"venue"
},
  "geometry": {"coordinates":[-84.33294600000001,39.901038],"type":"Point"}
}