{
  "type": "Feature",
  "properties": {
    "iso:country":"US",
    "sg:address":"302 E Markison Ave",
    "sg:city":"Columbus",
    "sg:classifiers":[
        {
            "category":"Building & Trades",
            "subcategory":"Plumbing",
            "type":"Services"
        }
    ],
    "sg:phone":"+1 614 443 5078",
    "sg:postcode":"43207",
    "sg:province":"OH",
    "sg:tags":[
        "plumber",
        "industrial",
        "contractors-commercial"
    ],
    "wof:name":"Steve Brown Plumbing",
    "wof:placetype":"venue"
},
  "geometry": {"coordinates":[-82.987561,39.931062],"type":"Point"}
}