{
  "type": "Feature",
  "properties": {
    "iso:country":"US",
    "sg:address":"22255 Center Ridge Rd",
    "sg:city":"Cleveland",
    "sg:classifiers":[
        {
            "category":"Organizations",
            "subcategory":"Professional Association",
            "type":"Services"
        }
    ],
    "sg:phone":"+1 216 523 1341",
    "sg:postcode":"44116",
    "sg:province":"OH",
    "wof:name":"Florist Association Of Ne Oh",
    "wof:placetype":"venue"
},
  "geometry": {"coordinates":[-81.863266,41.458845],"type":"Point"}
}