{
  "type": "Feature",
  "properties": {
    "addr:full": "50 W Sugartree St Wilmington OH 45177",
    "addr:housenumber": "50",
    "addr:postcode": "45177",
    "addr:street": "W Sugartree St",
    "iso:country": "US",
    "sg:address": "50 W Sugartree St",
    "sg:city": "Wilmington",
    "sg:classifiers": [
      {
        "category": "Wholesale",
        "subcategory": "Vending Machines",
        "type": "Manufacturing \u0026 Wholesale Goods"
      }
    ],
    "sg:phone": "+1 937 382 6404",
    "sg:postcode": "45177",
    "sg:province": "OH",
    "wof:name": "Derringer Co",
    "wof:placetype": "venue"
  },
  "geometry": {"coordinates":[-83.829807,39.444177],"type":"Point"}
}
