{
  "type": "Feature",
  "properties": {
    "iso:country":"US",
    "sg:address":"6715 Tippecanoe Rd",
    "sg:city":"Canfield",
    "sg:classifiers":[
        {
            "category":"Health Services",
            "subcategory":"Chiropractor",
            "type":"Services"
        }
    ],
    "sg:phone":"+1 330 286 3669",
    "sg:postcode":"44406",
    "sg:province":"OH",
    "sg:tags":[
        "chiropractic"
    ],
    "sg:website":"http://www.drmarucci.com",
    "wof:name":"Marucci Chiropractic & Wellness Center",
    "wof:placetype":"venue"
},
  "geometry": {"coordinates":[-80.711281,41.022449],"type":"Point"}
}