{
  "type": "Feature",
  "properties": {
    "addr:full": "420 N Broad St Lancaster OH 43130",
    "addr:housenumber": "420",
    "addr:postcode": "43130",
    "addr:street": "N Broad St",
    "iso:country": "US",
    "sg:address": "420 N Broad St",
    "sg:city": "Lancaster",
    "sg:classifiers": [
      {
        "category": "Retail",
        "subcategory": "Car Wash",
        "type": "Services"
      }
    ],
    "sg:phone": "+1 740 653 3904",
    "sg:postcode": "43130",
    "sg:province": "OH",
    "sg:tags": [
      "polishing",
      "washing"
    ],
    "wof:name": "Mobile Fleet \u0026 Auto Cleaning",
    "wof:placetype": "venue"
  },
  "geometry": {"coordinates":[-82.601651,39.717743],"type":"Point"}
}
