{
  "type": "Feature",
  "properties": {
    "addr:full":"8653 Taylorsville Rd Dayton OH 45424",
    "addr:housenumber":"8653",
    "addr:postcode":"45424",
    "addr:street":"Taylorsville Rd",
    "iso:country":"US",
    "sg:address":"8653 Taylorsville Rd",
    "sg:city":"Dayton",
    "sg:classifiers":[
        {
            "category":"Wholesale",
            "subcategory":"Computers",
            "type":"Manufacturing & Wholesale Goods"
        }
    ],
    "sg:phone":"+1 937 236 2144",
    "sg:postcode":"45424",
    "sg:province":"OH",
    "sg:tags":[
        "equipment"
    ],
    "wof:name":"Creative Cmpters Comunications",
    "wof:placetype":"venue"
},
  "geometry": {"coordinates":[-84.080658,39.859741],"type":"Point"}
}