{
  "type": "Feature",
  "properties": {
    "iso:country":"US",
    "sg:address":"8507 Main St",
    "sg:city":"Kinsman",
    "sg:classifiers":[
        {
            "category":"Food & Beverages",
            "subcategory":"Groceries & Convenience Stores",
            "type":"Retail Goods"
        }
    ],
    "sg:phone":"+1 330 876 1001",
    "sg:postcode":"44428",
    "sg:province":"OH",
    "wof:name":"True North 208",
    "wof:placetype":"venue"
},
  "geometry": {"coordinates":[-80.584198,41.44894],"type":"Point"}
}