{
  "type": "Feature",
  "properties": {
    "addr:full":"115 E Water St Oak Harbor OH 43449",
    "addr:housenumber":"115",
    "addr:postcode":"43449",
    "addr:street":"E Water St",
    "iso:country":"US",
    "sg:address":"115 E Water St",
    "sg:city":"Oak Harbor",
    "sg:classifiers":[
        {
            "category":"Health Services",
            "subcategory":"Doctor",
            "type":"Services"
        }
    ],
    "sg:phone":"+1 419 898 8811",
    "sg:postcode":"43449",
    "sg:province":"OH",
    "sg:tags":[
        "dentist"
    ],
    "wof:name":"George A Hablitzel DDS",
    "wof:placetype":"venue"
},
  "geometry": {"coordinates":[-83.14464599999999,41.507567],"type":"Point"}
}