{
  "type": "Feature",
  "properties": {
    "iso:country":"US",
    "sg:address":"519 W Wooster St",
    "sg:city":"Bowling Green",
    "sg:classifiers":[
        {
            "category":"Professional",
            "subcategory":"Computer Services",
            "type":"Services"
        }
    ],
    "sg:phone":"+1 419 352 3568",
    "sg:postcode":"43402",
    "sg:province":"OH",
    "sg:tags":[
        "internet"
    ],
    "sg:website":"www.dacor.net",
    "wof:name":"Dacor Inc",
    "wof:placetype":"venue"
},
  "geometry": {"coordinates":[-83.656329,41.374973],"type":"Point"}
}