{
  "type": "Feature",
  "properties": {
    "iso:country":"US",
    "sg:address":"657 Edgewood Ave",
    "sg:city":"Akron",
    "sg:classifiers":[
        {
            "category":"Retail",
            "subcategory":"Auto Repair",
            "type":"Services"
        }
    ],
    "sg:phone":"+1 330 376 4855",
    "sg:postcode":"44307",
    "sg:province":"OH",
    "sg:tags":[
        "repairing",
        "automobile"
    ],
    "wof:name":"Hennis Auto Svc",
    "wof:placetype":"venue"
},
  "geometry": {"coordinates":[-81.539722,41.07683],"type":"Point"}
}