{
  "type": "Feature",
  "properties": {
    "addr:full": "2124 Wales Ave NW Massillon OH 44646",
    "addr:housenumber": "2124",
    "addr:postcode": "44646",
    "addr:street": "Wales Ave Nw",
    "iso:country": "US",
    "sg:address": "2124 Wales Ave NW",
    "sg:city": "Massillon",
    "sg:classifiers": [
      {
        "category": "Home \u0026 Garden",
        "subcategory": "Carpets \u0026 Floor Coverings",
        "type": "Retail Goods"
      }
    ],
    "sg:phone": "+1 330 830 6491",
    "sg:postcode": "44646",
    "sg:province": "OH",
    "wof:name": "Rices Carpet Place LTD",
    "wof:placetype": "venue"
  },
  "geometry": {"coordinates":[-81.502843,40.823529],"type":"Point"}
}
