{
  "type": "Feature",
  "properties": {
    "addr:full": "24 W 3rd St Mansfield OH 44902",
    "addr:housenumber": "24",
    "addr:postcode": "44902",
    "addr:street": "W 3Rd St",
    "iso:country": "US",
    "sg:address": "24 W 3rd St",
    "sg:city": "Mansfield",
    "sg:classifiers": [
      {
        "category": "Professional",
        "subcategory": "Lawyer \u0026 Legal Services",
        "type": "Services"
      }
    ],
    "sg:phone": "+1 419 524 1403",
    "sg:postcode": "44902",
    "sg:province": "OH",
    "sg:tags": [
      "attorney"
    ],
    "wof:name": "Mabee \u0026 Mills",
    "wof:placetype": "venue"
  },
  "geometry": {"coordinates":[-82.51789,40.759905],"type":"Point"}
}
