{
  "type": "Feature",
  "properties": {
    "iso:country":"US",
    "sg:address":"24 W 3rd St",
    "sg:city":"Mansfield",
    "sg:classifiers":[
        {
            "category":"Professional",
            "subcategory":"Lawyer & Legal Services",
            "type":"Services"
        }
    ],
    "sg:phone":"+1 419 524 1403",
    "sg:postcode":"44902",
    "sg:province":"OH",
    "sg:tags":[
        "attorney"
    ],
    "wof:name":"Mabee & Mills",
    "wof:placetype":"venue"
},
  "geometry": {"coordinates":[-82.51788999999999,40.759905],"type":"Point"}
}