{
  "type": "Feature",
  "properties": {
    "iso:country":"US",
    "sg:address":"300 Madison St",
    "sg:city":"Genoa",
    "sg:classifiers":[
        {
            "category":"Building & Trades",
            "subcategory":"Plumbing",
            "type":"Services"
        }
    ],
    "sg:phone":"+1 419 249 5380",
    "sg:postcode":"43452",
    "sg:province":"OH",
    "sg:tags":[
        "product",
        "management",
        "energy",
        "system"
    ],
    "wof:name":"Centerior Energy Svc Customer",
    "wof:placetype":"venue"
},
  "geometry": {"coordinates":[-82.941087,41.509097],"type":"Point"}
}