{
  "type": "Feature",
  "properties": {
    "addr:full": "1217 Polaris Pkwy Columbus OH 43240",
    "addr:housenumber": "1217",
    "addr:postcode": "43240",
    "addr:street": "Polaris Pkwy",
    "iso:country": "US",
    "sg:address": "1217 Polaris Pkwy",
    "sg:city": "Columbus",
    "sg:classifiers": [
      {
        "category": "Personal",
        "subcategory": "Beauty Salon",
        "type": "Services"
      }
    ],
    "sg:phone": "+1 614 436 3518",
    "sg:postcode": "43240",
    "sg:province": "OH",
    "sg:tags": [
      "spa",
      "day"
    ],
    "wof:name": "Allure Spa \u0026 Salon II",
    "wof:placetype": "venue"
  },
  "geometry": {"coordinates":[-82.99023,40.143994],"type":"Point"}
}
