{
  "type": "Feature",
  "properties": {
    "iso:country":"US",
    "sg:address":"24 Randolph St",
    "sg:city":"Wilmington",
    "sg:classifiers":[
        {
            "category":"Government",
            "subcategory":"Office",
            "type":"Public Place"
        }
    ],
    "sg:phone":"+1 937 382 2315",
    "sg:postcode":"45177",
    "sg:province":"OH",
    "wof:name":"Clinton Agricultural",
    "wof:placetype":"venue"
},
  "geometry": {"coordinates":[-83.832959,39.434699],"type":"Point"}
}