{
  "type": "Feature",
  "properties": {
    "addr:full": "4828 Calloway Ct Dublin OH 43017",
    "addr:housenumber": "4828",
    "addr:postcode": "43017",
    "addr:street": "Calloway Ct",
    "iso:country": "US",
    "sg:address": "4828 Calloway Ct",
    "sg:city": "Dublin",
    "sg:classifiers": [
      {
        "category": "Shopping",
        "subcategory": "Gifts \u0026 Souvenirs",
        "type": "Retail Goods"
      }
    ],
    "sg:phone": "+1 614 766 1389",
    "sg:postcode": "43017",
    "sg:province": "OH",
    "sg:tags": [
      "cards",
      "item",
      "greeting"
    ],
    "wof:name": "Lairs Hallmark Center",
    "wof:placetype": "venue"
  },
  "geometry": {"coordinates":[-83.118899,40.12723],"type":"Point"}
}
