{
  "type": "Feature",
  "properties": {
    "iso:country":"US",
    "sg:address":"2475 Madison Rd",
    "sg:city":"Cincinnati",
    "sg:classifiers":[
        {
            "category":"Organizations",
            "subcategory":"Religious Organization",
            "type":"Services"
        }
    ],
    "sg:phone":"+1 513 321 1169",
    "sg:postcode":"45208",
    "sg:province":"OH",
    "sg:tags":[
        "clergy"
    ],
    "wof:name":"M Saville",
    "wof:placetype":"venue"
},
  "geometry": {"coordinates":[-84.453337,39.13894],"type":"Point"}
}