{
  "type": "Feature",
  "properties": {
    "addr:full":"67800 Mall Rd St Clairsville OH 43950",
    "addr:housenumber":"67800",
    "addr:postcode":"43950",
    "addr:street":"Mall Rd",
    "iso:country":"US",
    "sg:address":"67800 Mall Rd",
    "sg:city":"St Clairsville",
    "sg:classifiers":[
        {
            "category":"Shopping",
            "subcategory":"Jewelry",
            "type":"Retail Goods"
        }
    ],
    "sg:phone":"+1 740 695 1342",
    "sg:postcode":"43950",
    "sg:province":"OH",
    "sg:tags":[
        "jeweler"
    ],
    "wof:name":"Zales The Diamond Store",
    "wof:placetype":"venue"
},
  "geometry": {"coordinates":[-80.864137,40.069942],"type":"Point"}
}