{
  "type": "Feature",
  "properties": {
    "addr:full":"3432 Eastwoodlands Trl Hilliard OH 43026",
    "addr:housenumber":"3432",
    "addr:postcode":"43026",
    "addr:street":"Eastwoodlands Trl",
    "iso:country":"US",
    "sg:address":"3432 Eastwoodlands Trl",
    "sg:city":"Hilliard",
    "sg:classifiers":[
        {
            "category":"Travel",
            "subcategory":"Hotels & Motels",
            "type":"Entertainment"
        }
    ],
    "sg:phone":"+1 614 850 8932",
    "sg:postcode":"43026",
    "sg:province":"OH",
    "wof:name":"Red Roof Inn",
    "wof:placetype":"venue"
},
  "geometry": {"coordinates":[-83.11174699999999,40.023664],"type":"Point"}
}