{
  "type": "Feature",
  "properties": {
    "addr:full": "14515 Madison Ave Lakewood OH 44107",
    "addr:housenumber": "14515",
    "addr:postcode": "44107",
    "addr:street": "Madison Ave",
    "iso:country": "US",
    "sg:address": "14515 Madison Ave",
    "sg:city": "Lakewood",
    "sg:classifiers": [
      {
        "category": "Shopping",
        "subcategory": "Bicycles \u0026 Sporting Goods",
        "type": "Retail Goods"
      }
    ],
    "sg:phone": "+1 216 228 9228",
    "sg:postcode": "44107",
    "sg:province": "OH",
    "sg:tags": [
      "repair"
    ],
    "wof:name": "Lakewood Cycle",
    "wof:placetype": "venue"
  },
  "geometry": {"coordinates":[-81.796798,41.477113],"type":"Point"}
}
