{
  "type": "Feature",
  "properties": {
    "iso:country":"US",
    "sg:address":"9 West St",
    "sg:city":"Lucasville",
    "sg:classifiers":[
        {
            "category":"Shopping",
            "subcategory":"Gifts & Souvenirs",
            "type":"Retail Goods"
        }
    ],
    "sg:phone":"+1 740 259 3002",
    "sg:postcode":"45648",
    "sg:province":"OH",
    "sg:tags":[
        "shop"
    ],
    "wof:name":"Olde Lamplighter",
    "wof:placetype":"venue"
},
  "geometry": {"coordinates":[-82.998169,38.880001],"type":"Point"}
}