{
  "type": "Feature",
  "properties": {
    "addr:full": "9 West St Lucasville OH 45648",
    "addr:housenumber": "9",
    "addr:postcode": "45648",
    "addr:street": "West St",
    "iso:country": "US",
    "sg:address": "9 West St",
    "sg:city": "Lucasville",
    "sg:classifiers": [
      {
        "category": "Shopping",
        "subcategory": "Gifts \u0026 Souvenirs",
        "type": "Retail Goods"
      }
    ],
    "sg:phone": "+1 740 259 3002",
    "sg:postcode": "45648",
    "sg:province": "OH",
    "sg:tags": [
      "shop"
    ],
    "wof:name": "Olde Lamplighter",
    "wof:placetype": "venue"
  },
  "geometry": {"coordinates":[-82.998169,38.880001],"type":"Point"}
}
