{
  "type": "Feature",
  "properties": {
    "addr:full":"624 Main St Genoa OH 43430",
    "addr:housenumber":"624",
    "addr:postcode":"43430",
    "addr:street":"Main St",
    "iso:country":"US",
    "sg:address":"624 Main St",
    "sg:city":"Genoa",
    "sg:classifiers":[
        {
            "category":"Shopping",
            "subcategory":"Gifts & Souvenirs",
            "type":"Retail Goods"
        }
    ],
    "sg:phone":"+1 419 855 7205",
    "sg:postcode":"43430",
    "sg:province":"OH",
    "sg:tags":[
        "shop"
    ],
    "wof:name":"A Most Unusual Gdn & Gift Shop",
    "wof:placetype":"venue"
},
  "geometry": {"coordinates":[-83.358727,41.519711],"type":"Point"}
}