{
  "type": "Feature",
  "properties": {
    "addr:full":"2365 Lakeview Dr Dayton OH 45431",
    "addr:housenumber":"2365",
    "addr:postcode":"45431",
    "addr:street":"Lakeview Dr",
    "iso:country":"US",
    "sg:address":"2365 Lakeview Dr",
    "sg:city":"Dayton",
    "sg:classifiers":[
        {
            "category":"Travel",
            "subcategory":"Travel Agent",
            "type":"Entertainment"
        }
    ],
    "sg:phone":"+1 937 431 1539",
    "sg:postcode":"45431",
    "sg:province":"OH",
    "sg:tags":[
        "agency",
        "bureau"
    ],
    "wof:name":"License 2 Travel",
    "wof:placetype":"venue"
},
  "geometry": {"coordinates":[-84.056089,39.758503],"type":"Point"}
}