{
  "type": "Feature",
  "properties": {
    "addr:full":"5478 Grafton Rd Valley City OH 44280",
    "addr:housenumber":"5478",
    "addr:postcode":"44280",
    "addr:street":"Grafton Rd",
    "iso:country":"US",
    "sg:address":"5478 Grafton Rd",
    "sg:city":"Valley City",
    "sg:classifiers":[
        {
            "category":"Manufacturing",
            "subcategory":"Metals",
            "type":"Manufacturing & Wholesale Goods"
        }
    ],
    "sg:phone":"+1 330 220 0627",
    "sg:postcode":"44280",
    "sg:province":"OH",
    "sg:tags":[
        "manufacture",
        "jig",
        "component",
        "specialty",
        "machine",
        "parts"
    ],
    "wof:name":"Benton Enterprises Inc",
    "wof:placetype":"venue"
},
  "geometry": {"coordinates":[-81.882983,41.260027],"type":"Point"}
}