{
  "type": "Feature",
  "properties": {
    "addr:full": "212 Warden Ave Elyria OH 44035",
    "addr:housenumber": "212",
    "addr:postcode": "44035",
    "addr:street": "Warden Ave",
    "iso:country": "US",
    "sg:address": "212 Warden Ave",
    "sg:city": "Elyria",
    "sg:classifiers": [
      {
        "category": "Professional",
        "subcategory": "Printing \u0026 Photocopies",
        "type": "Services"
      }
    ],
    "sg:phone": "+1 440 323 9665",
    "sg:postcode": "44035",
    "sg:province": "OH",
    "sg:tags": [
      "blueprinting"
    ],
    "wof:name": "CIR",
    "wof:placetype": "venue"
  },
  "geometry": {"coordinates":[-82.12158,41.389211],"type":"Point"}
}
