{
  "type": "Feature",
  "properties": {
    "iso:country":"US",
    "sg:address":"212 Warden Ave",
    "sg:city":"Elyria",
    "sg:classifiers":[
        {
            "category":"Professional",
            "subcategory":"Printing & Photocopies",
            "type":"Services"
        }
    ],
    "sg:phone":"+1 440 323 9665",
    "sg:postcode":"44035",
    "sg:province":"OH",
    "sg:tags":[
        "blueprinting"
    ],
    "wof:name":"CIR",
    "wof:placetype":"venue"
},
  "geometry": {"coordinates":[-82.12158,41.389211],"type":"Point"}
}