{
  "type": "Feature",
  "properties": {
    "addr:full":"287 E Market St Warren OH 44481",
    "addr:housenumber":"287",
    "addr:postcode":"44481",
    "addr:street":"E Market St",
    "iso:country":"US",
    "sg:address":"287 E Market St",
    "sg:city":"Warren",
    "sg:classifiers":[
        {
            "category":"Home & Garden",
            "subcategory":"Household Appliances",
            "type":"Retail Goods"
        }
    ],
    "sg:phone":"+1 330 399 1883",
    "sg:postcode":"44481",
    "sg:province":"OH",
    "sg:tags":[
        "cleaners",
        "vacuum"
    ],
    "wof:name":"Kirby Sweeper Co Of Warren",
    "wof:placetype":"venue"
},
  "geometry": {"coordinates":[-80.813715,41.236247],"type":"Point"}
}