{
  "type": "Feature",
  "properties": {
    "addr:full": "8625 Indian Hill Rd Cincinnati OH 45243",
    "addr:housenumber": "8625",
    "addr:postcode": "45243",
    "addr:street": "Indian Hill Rd",
    "iso:country": "US",
    "sg:address": "8625 Indian Hill Rd",
    "sg:city": "Cincinnati",
    "sg:classifiers": [
      {
        "category": "Shopping",
        "type": "Retail Goods"
      }
    ],
    "sg:phone": "+1 513 561 6888",
    "sg:postcode": "45243",
    "sg:province": "OH",
    "sg:tags": [
      "art",
      "gallery",
      "dealer"
    ],
    "wof:name": "Joanne M Stoneker Art",
    "wof:placetype": "venue"
  },
  "geometry": {"coordinates":[-84.337942,39.159976],"type":"Point"}
}
