{
  "type": "Feature",
  "properties": {
    "addr:full": "1610 N West St Lima OH 45801",
    "addr:housenumber": "1610",
    "addr:postcode": "45801",
    "addr:street": "N West St",
    "iso:country": "US",
    "sg:address": "1610 N West St",
    "sg:city": "Lima",
    "sg:classifiers": [
      {
        "category": "Banks \u0026 Credit Unions",
        "subcategory": "Bank",
        "type": "Services"
      }
    ],
    "sg:phone": "+1 419 226 8227",
    "sg:postcode": "45801",
    "sg:province": "OH",
    "sg:tags": [
      "national",
      "commercial"
    ],
    "wof:name": "Huntington National Bank",
    "wof:placetype": "venue"
  },
  "geometry": {"coordinates":[-84.10852,40.765621],"type":"Point"}
}
