{
  "type": "Feature",
  "properties": {
    "addr:full": "14830 Co Rd G Bryan OH 43506",
    "addr:housenumber": "14830",
    "addr:postcode": "43506",
    "addr:street": "Co Rd",
    "iso:country": "US",
    "sg:address": "14830 Co Rd G",
    "sg:city": "Bryan",
    "sg:classifiers": [
      {
        "category": "Farming",
        "subcategory": "Farm",
        "type": "Manufacturing \u0026 Wholesale Goods"
      }
    ],
    "sg:phone": "+1 419 636 3059",
    "sg:postcode": "43506",
    "sg:province": "OH",
    "sg:tags": [
      "feedlot",
      "cattle",
      "crop",
      "beef",
      "general"
    ],
    "wof:name": "Bever Farms",
    "wof:placetype": "venue"
  },
  "geometry": {"coordinates":[-84.539731,41.514027],"type":"Point"}
}
