{
  "type": "Feature",
  "properties": {
    "iso:country":"US",
    "sg:address":"1101 Market Ave N",
    "sg:city":"Canton",
    "sg:classifiers":[
        {
            "category":"Organizations",
            "subcategory":"Religious Organization",
            "type":"Services"
        }
    ],
    "sg:phone":"+1 330 455 5964",
    "sg:postcode":"44702",
    "sg:province":"OH",
    "sg:tags":[
        "church"
    ],
    "wof:name":"Greek Orthodox Church",
    "wof:placetype":"venue"
},
  "geometry": {"coordinates":[-81.372068,40.808907],"type":"Point"}
}