{
  "type": "Feature",
  "properties": {
    "addr:full": "2101 Tucker Trl Lewis Center OH 43035",
    "addr:housenumber": "2101",
    "addr:postcode": "43035",
    "addr:street": "Tucker Trl",
    "iso:country": "US",
    "sg:address": "2101 Tucker Trl",
    "sg:city": "Lewis Center",
    "sg:classifiers": [
      {
        "category": "Wholesale",
        "subcategory": "Machinery \u0026 Supplies",
        "type": "Manufacturing \u0026 Wholesale Goods"
      }
    ],
    "sg:phone": "+1 740 549 0025",
    "sg:postcode": "43035",
    "sg:province": "OH",
    "sg:tags": [
      "equipment",
      "handling",
      "representative",
      "air"
    ],
    "wof:name": "Chrissinger Co",
    "wof:placetype": "venue"
  },
  "geometry": {"coordinates":[-82.980607,40.161808],"type":"Point"}
}
