{
  "type": "Feature",
  "properties": {
    "iso:country":"US",
    "sg:address":"2101 Tucker Trl",
    "sg:city":"Lewis Center",
    "sg:classifiers":[
        {
            "category":"Wholesale",
            "subcategory":"Machinery & Supplies",
            "type":"Manufacturing & Wholesale Goods"
        }
    ],
    "sg:phone":"+1 740 549 0025",
    "sg:postcode":"43035",
    "sg:province":"OH",
    "sg:tags":[
        "equipment",
        "handling",
        "representative",
        "air"
    ],
    "wof:name":"Chrissinger Co",
    "wof:placetype":"venue"
},
  "geometry": {"coordinates":[-82.98060700000001,40.161808],"type":"Point"}
}