{
  "type": "Feature",
  "properties": {
    "addr:full": "537 Woodland Dr Rossford OH 43460",
    "addr:housenumber": "537",
    "addr:postcode": "43460",
    "addr:street": "Woodland Dr",
    "iso:country": "US",
    "sg:address": "537 Woodland Dr",
    "sg:city": "Rossford",
    "sg:classifiers": [
      {
        "category": "Building \u0026 Trades",
        "subcategory": "Construction",
        "type": "Services"
      }
    ],
    "sg:phone": "+1 419 666 4198",
    "sg:postcode": "43460",
    "sg:province": "OH",
    "sg:tags": [
      "excavation",
      "contractor"
    ],
    "wof:name": "Hutch Unlimited LLC",
    "wof:placetype": "venue"
  },
  "geometry": {"coordinates":[-83.551354,41.600018],"type":"Point"}
}
