{
  "type": "Feature",
  "properties": {
    "iso:country":"US",
    "sg:address":"6000 W Broad St",
    "sg:city":"Galloway",
    "sg:classifiers":[
        {
            "category":"Sports & Exercise",
            "subcategory":"Golf",
            "type":"Entertainment"
        }
    ],
    "sg:phone":"+1 614 851 1122",
    "sg:postcode":"43119",
    "sg:province":"OH",
    "sg:tags":[
        "range",
        "practice"
    ],
    "wof:name":"West Broad Golf Center",
    "wof:placetype":"venue"
},
  "geometry": {"coordinates":[-83.162003,39.950779],"type":"Point"}
}