{
  "type": "Feature",
  "properties": {
    "iso:country":"US",
    "sg:address":"165 W Main St",
    "sg:city":"Newark",
    "sg:classifiers":[
        {
            "category":"Wholesale",
            "subcategory":"Machinery & Supplies",
            "type":"Manufacturing & Wholesale Goods"
        }
    ],
    "sg:phone":"+1 740 345 2092",
    "sg:postcode":"43055",
    "sg:province":"OH",
    "sg:tags":[
        "equipment",
        "industrial"
    ],
    "wof:name":"Tech Heat Exchange",
    "wof:placetype":"venue"
},
  "geometry": {"coordinates":[-82.40866200000001,40.056139],"type":"Point"}
}