{
  "type": "Feature",
  "properties": {
    "iso:country":"US",
    "sg:address":"650 N State St",
    "sg:city":"Westerville",
    "sg:classifiers":[
        {
            "category":"Banks & Credit Unions",
            "subcategory":"Bank",
            "type":"Services"
        }
    ],
    "sg:phone":"+1 614 823 3894",
    "sg:postcode":"43082",
    "sg:province":"OH",
    "wof:name":"Us Bank",
    "wof:placetype":"venue"
},
  "geometry": {"coordinates":[-82.92727600000001,40.141224],"type":"Point"}
}