{
  "type": "Feature",
  "properties": {
    "addr:full": "3610 Washington Ave Cincinnati OH 45229",
    "addr:housenumber": "3610",
    "addr:postcode": "45229",
    "addr:street": "Washington Ave",
    "iso:country": "US",
    "sg:address": "3610 Washington Ave",
    "sg:city": "Cincinnati",
    "sg:classifiers": [
      {
        "category": "Health Services",
        "subcategory": "Nursing And Care Facility",
        "type": "Services"
      }
    ],
    "sg:phone": "+1 513 221 2775",
    "sg:postcode": "45229",
    "sg:province": "OH",
    "sg:tags": [
      "home",
      "convalescent"
    ],
    "wof:name": "Zion Care Ctr",
    "wof:placetype": "venue"
  },
  "geometry": {"coordinates":[-84.494593,39.15],"type":"Point"}
}
