{
  "type": "Feature",
  "properties": {
    "iso:country":"US",
    "sg:address":"1135 Dearth Rd",
    "sg:city":"Kingston",
    "sg:classifiers":[
        {
            "category":"Farming",
            "subcategory":"Farm",
            "type":"Manufacturing & Wholesale Goods"
        }
    ],
    "sg:phone":"+1 740 655 2959",
    "sg:postcode":"45644",
    "sg:province":"OH",
    "sg:tags":[
        "crop",
        "general"
    ],
    "wof:name":"Slater Farms",
    "wof:placetype":"venue"
},
  "geometry": {"coordinates":[-82.862093,39.39356],"type":"Point"}
}