{
  "type": "Feature",
  "properties": {
    "addr:full": "1048 Dayton St Akron OH 44310",
    "addr:housenumber": "1048",
    "addr:postcode": "44310",
    "addr:street": "Dayton St",
    "iso:country": "US",
    "sg:address": "1048 Dayton St",
    "sg:city": "Akron",
    "sg:classifiers": [
      {
        "category": "Banks \u0026 Credit Unions",
        "subcategory": "Bank",
        "type": "Services"
      }
    ],
    "sg:phone": "+1 330 922 3016",
    "sg:postcode": "44310",
    "sg:province": "OH",
    "sg:tags": [
      "federal",
      "agency"
    ],
    "wof:name": "Reids Import Ltd Inc",
    "wof:placetype": "venue"
  },
  "geometry": {"coordinates":[-81.507212,41.113603],"type":"Point"}
}
