{
  "type": "Feature",
  "properties": {
    "addr:full":"2880 Kenyon Ave NW Massillon OH 44647",
    "addr:housenumber":"2880",
    "addr:postcode":"44647",
    "addr:street":"Kenyon Ave Nw",
    "iso:country":"US",
    "sg:address":"2880 Kenyon Ave NW",
    "sg:city":"Massillon",
    "sg:classifiers":[
        {
            "category":"Farming",
            "subcategory":"Dairy Farm",
            "type":"Manufacturing & Wholesale Goods"
        }
    ],
    "sg:phone":"+1 330 833 0895",
    "sg:postcode":"44647",
    "sg:province":"OH",
    "wof:name":"Jerry Rohr",
    "wof:placetype":"venue"
},
  "geometry": {"coordinates":[-81.58077299999999,40.830497],"type":"Point"}
}