{
  "type": "Feature",
  "properties": {
    "addr:full": "6351 Sterling Woods Dr Clayton OH 45315",
    "addr:housenumber": "6351",
    "addr:postcode": "45315",
    "addr:street": "Sterling Woods Dr",
    "iso:country": "US",
    "sg:address": "6351 Sterling Woods Dr",
    "sg:city": "Clayton",
    "sg:classifiers": [
      {
        "category": "Restaurant",
        "type": "Food \u0026 Drink"
      }
    ],
    "sg:phone": "+1 937 837 5525",
    "sg:postcode": "45315",
    "sg:province": "OH",
    "sg:tags": [
      "eating"
    ],
    "wof:name": "Pickles and Rye Delicatessen",
    "wof:placetype": "venue"
  },
  "geometry": {"coordinates":[-84.320148,39.838506],"type":"Point"}
}
