{
  "type": "Feature",
  "properties": {
    "addr:full": "1540 S Water St Kent OH 44240",
    "addr:housenumber": "1540",
    "addr:postcode": "44240",
    "addr:street": "S Water St",
    "iso:country": "US",
    "sg:address": "1540 S Water St",
    "sg:city": "Kent",
    "sg:classifiers": [
      {
        "category": "Personal",
        "subcategory": "Beauty Salon",
        "type": "Services"
      }
    ],
    "sg:phone": "+1 330 673 3957",
    "sg:postcode": "44240",
    "sg:province": "OH",
    "wof:name": "Sara's Hair Styling",
    "wof:placetype": "venue"
  },
  "geometry": {"coordinates":[-81.356554,41.139924],"type":"Point"}
}
