{
  "type": "Feature",
  "properties": {
    "iso:country":"US",
    "sg:address":"6775 W Twp Rd 154",
    "sg:city":"Fostoria",
    "sg:classifiers":[
        {
            "category":"Personal",
            "subcategory":"Beauty Salon",
            "type":"Services"
        }
    ],
    "sg:phone":"+1 419 435 8898",
    "sg:postcode":"44830",
    "sg:province":"OH",
    "sg:tags":[
        "manicuring"
    ],
    "wof:name":"10 Nails Etc",
    "wof:placetype":"venue"
},
  "geometry": {"coordinates":[-83.301006,41.20353],"type":"Point"}
}