{
  "type": "Feature",
  "properties": {
    "addr:full": "6651 Frank Ave NW North Canton OH 44720",
    "addr:housenumber": "6651",
    "addr:postcode": "44720",
    "addr:street": "Frank Ave Nw",
    "iso:country": "US",
    "sg:address": "6651 Frank Ave NW",
    "sg:city": "North Canton",
    "sg:classifiers": [
      {
        "category": "Health Services",
        "subcategory": "Health Practitioner",
        "type": "Services"
      }
    ],
    "sg:phone": "+1 330 244 8761",
    "sg:postcode": "44720",
    "sg:province": "OH",
    "sg:tags": [
      "therapist",
      "physical"
    ],
    "wof:name": "Northside Rehabilitation Inc",
    "wof:placetype": "venue"
  },
  "geometry": {"coordinates":[-81.441606,40.873433],"type":"Point"}
}
