{
  "type": "Feature",
  "properties": {
    "addr:full": "634 Main St Zanesville OH 43701",
    "addr:housenumber": "634",
    "addr:postcode": "43701",
    "addr:street": "Main St",
    "iso:country": "US",
    "sg:address": "634 Main St",
    "sg:city": "Zanesville",
    "sg:classifiers": [
      {
        "category": "Shopping",
        "subcategory": "Bicycles \u0026 Sporting Goods",
        "type": "Retail Goods"
      }
    ],
    "sg:phone": "+1 740 453 3438",
    "sg:postcode": "43701",
    "sg:province": "OH",
    "sg:tags": [
      "repair"
    ],
    "wof:name": "Wheel \u0026 Spoke Bike Shop",
    "wof:placetype": "venue"
  },
  "geometry": {"coordinates":[-82.004821,39.93995],"type":"Point"}
}
