{
  "type": "Feature",
  "properties": {
    "iso:country":"US",
    "sg:address":"634 Main St",
    "sg:city":"Zanesville",
    "sg:classifiers":[
        {
            "category":"Shopping",
            "subcategory":"Bicycles & Sporting Goods",
            "type":"Retail Goods"
        }
    ],
    "sg:phone":"+1 740 453 3438",
    "sg:postcode":"43701",
    "sg:province":"OH",
    "sg:tags":[
        "repair"
    ],
    "wof:name":"Wheel & Spoke Bike Shop",
    "wof:placetype":"venue"
},
  "geometry": {"coordinates":[-82.00482100000001,39.93995],"type":"Point"}
}