{
  "type": "Feature",
  "properties": {
    "iso:country":"US",
    "sg:address":"88 Remick Blvd",
    "sg:city":"Springboro",
    "sg:classifiers":[
        {
            "category":"Social Services",
            "type":"Services"
        }
    ],
    "sg:phone":"+1 937 886 9622",
    "sg:postcode":"45066",
    "sg:province":"OH",
    "sg:tags":[
        "child",
        "day",
        "care"
    ],
    "wof:name":"Young Mens Chrstn Assoc Grt D",
    "wof:placetype":"venue"
},
  "geometry": {"coordinates":[-84.224653,39.579283],"type":"Point"}
}