{
  "type": "Feature",
  "properties": {
    "iso:country":"US",
    "sg:address":"27221 Chardon Rd",
    "sg:city":"Cleveland",
    "sg:classifiers":[
        {
            "category":"Restaurant",
            "type":"Food & Drink"
        }
    ],
    "sg:phone":"+1 440 943 6444",
    "sg:postcode":"44143",
    "sg:province":"OH",
    "sg:tags":[
        "eating"
    ],
    "wof:name":"Casa Di Borally",
    "wof:placetype":"venue"
},
  "geometry": {"coordinates":[-81.488542,41.582059],"type":"Point"}
}