{
  "type": "Feature",
  "properties": {
    "addr:full": "1475 Mentor Ave Painesville OH 44077",
    "addr:housenumber": "1475",
    "addr:postcode": "44077",
    "addr:street": "Mentor Ave",
    "iso:country": "US",
    "sg:address": "1475 Mentor Ave",
    "sg:city": "Painesville",
    "sg:classifiers": [
      {
        "category": "Food \u0026 Beverages",
        "subcategory": "Groceries \u0026 Convenience Stores",
        "type": "Retail Goods"
      }
    ],
    "sg:phone": "+1 440 354 2348",
    "sg:postcode": "44077",
    "sg:province": "OH",
    "sg:tags": [
      "grocer"
    ],
    "wof:name": "Save-A-Lot",
    "wof:placetype": "venue"
  },
  "geometry": {"coordinates":[-81.276659,41.699876],"type":"Point"}
}
