{
  "type": "Feature",
  "properties": {
    "addr:full":"2245 Briarwood Rd Cleveland OH 44118",
    "addr:housenumber":"2245",
    "addr:postcode":"44118",
    "addr:street":"Briarwood Rd",
    "iso:country":"US",
    "sg:address":"2245 Briarwood Rd",
    "sg:city":"Cleveland",
    "sg:classifiers":[
        {
            "category":"Professional",
            "type":"Services"
        }
    ],
    "sg:phone":"+1 216 371 2812",
    "sg:postcode":"44118",
    "sg:province":"OH",
    "wof:name":"Bhadra Niloy Dr",
    "wof:placetype":"venue"
},
  "geometry": {"coordinates":[-81.571466,41.498413],"type":"Point"}
}