{
  "type": "Feature",
  "properties": {
    "addr:full":"28 E Rahn Rd Dayton OH 45429",
    "addr:housenumber":"28",
    "addr:postcode":"45429",
    "addr:street":"E Rahn Rd",
    "iso:country":"US",
    "sg:address":"28 E Rahn Rd",
    "sg:city":"Dayton",
    "sg:classifiers":[
        {
            "category":"Health Services",
            "subcategory":"Health Practitioner",
            "type":"Services"
        }
    ],
    "sg:phone":"+1 937 439 0505",
    "sg:postcode":"45429",
    "sg:province":"OH",
    "sg:tags":[
        "psychologist"
    ],
    "wof:name":"Holly R Counts",
    "wof:placetype":"venue"
},
  "geometry": {"coordinates":[-84.16177999999999,39.668888],"type":"Point"}
}