{
  "type": "Feature",
  "properties": {
    "iso:country":"US",
    "sg:address":"1053 N Court St",
    "sg:city":"Medina",
    "sg:classifiers":[
        {
            "category":"Professional",
            "type":"Services"
        }
    ],
    "sg:phone":"+1 330 722 4760",
    "sg:postcode":"44256",
    "sg:province":"OH",
    "sg:tags":[
        "establishment"
    ],
    "wof:name":"Zaremba Group Inc",
    "wof:placetype":"venue"
},
  "geometry": {"coordinates":[-81.863069,41.152477],"type":"Point"}
}