{
  "type": "Feature",
  "properties": {
    "addr:full": "9511 Bowling Green Rd E Bowling Green OH 43402",
    "addr:housenumber": "9511",
    "addr:postcode": "43402",
    "addr:street": "Bowling Green Rd E",
    "iso:country": "US",
    "sg:address": "9511 Bowling Green Rd E",
    "sg:city": "Bowling Green",
    "sg:classifiers": [
      {
        "category": "Building \u0026 Trades",
        "subcategory": "Construction",
        "type": "Services"
      }
    ],
    "sg:phone": "+1 419 352 6979",
    "sg:postcode": "43402",
    "sg:province": "OH",
    "sg:tags": [
      "house"
    ],
    "wof:name": "Jason Martin Construction",
    "wof:placetype": "venue"
  },
  "geometry": {"coordinates":[-83.59096,41.374303],"type":"Point"}
}
