{
  "type": "Feature",
  "properties": {
    "addr:full": "30006 Lakeland Blvd Wickliffe OH 44092",
    "addr:housenumber": "30006",
    "addr:postcode": "44092",
    "addr:street": "Lakeland Blvd",
    "iso:country": "US",
    "sg:address": "30006 Lakeland Blvd",
    "sg:city": "Wickliffe",
    "sg:classifiers": [
      {
        "category": "Manufacturing",
        "subcategory": "Metals",
        "type": "Manufacturing \u0026 Wholesale Goods"
      }
    ],
    "sg:phone": "+1 440 943 3213",
    "sg:postcode": "44092",
    "sg:province": "OH",
    "sg:tags": [
      "spring",
      "mfg",
      "coil"
    ],
    "sg:website": "www.euclidspring.com",
    "wof:name": "Euclid Spring Co",
    "wof:placetype": "venue"
  },
  "geometry": {"coordinates":[-81.462971,41.62173],"type":"Point"}
}
