{
  "type": "Feature",
  "properties": {
    "iso:country":"US",
    "sg:address":"32 S Main St",
    "sg:city":"Dayton",
    "sg:classifiers":[
        {
            "category":"Organizations",
            "subcategory":"Professional Association",
            "type":"Services"
        }
    ],
    "sg:phone":"+1 937 222 6225",
    "sg:postcode":"45402",
    "sg:province":"OH",
    "wof:name":"Nat'l Conf-Community&Justice",
    "wof:placetype":"venue"
},
  "geometry": {"coordinates":[-84.191581,39.759186],"type":"Point"}
}