{
  "type": "Feature",
  "properties": {
    "addr:full":"9158 Ravenna Rd Twinsburg OH 44087",
    "addr:housenumber":"9158",
    "addr:postcode":"44087",
    "addr:street":"Ravenna Rd",
    "iso:country":"US",
    "sg:address":"9158 Ravenna Rd",
    "sg:city":"Twinsburg",
    "sg:classifiers":[
        {
            "category":"Retail",
            "subcategory":"Auto Repair",
            "type":"Services"
        }
    ],
    "sg:phone":"+1 330 425 7339",
    "sg:postcode":"44087",
    "sg:province":"OH",
    "sg:tags":[
        "repairing",
        "automobile"
    ],
    "wof:name":"Ralph's Auto Svc",
    "wof:placetype":"venue"
},
  "geometry": {"coordinates":[-81.42623,41.306636],"type":"Point"}
}