{
  "type": "Feature",
  "properties": {
    "iso:country":"US",
    "sg:address":"3653 Rd 13",
    "sg:city":"Leipsic",
    "sg:phone":"+1 419 876 3057",
    "sg:postcode":"45856",
    "sg:province":"OH",
    "sg:tags":[
        "farm",
        "field",
        "crop"
    ],
    "wof:name":"Gdbr Farms LLC",
    "wof:placetype":"venue"
},
  "geometry": {"coordinates":[-84.112189,41.127868],"type":"Point"}
}