{
  "type": "Feature",
  "properties": {
    "iso:country":"US",
    "sg:address":"80 High St",
    "sg:city":"Glouster",
    "sg:classifiers":[
        {
            "category":"Professional",
            "subcategory":"Accounting & Tax Preparation",
            "type":"Services"
        }
    ],
    "sg:phone":"+1 740 767 3212",
    "sg:postcode":"45764",
    "sg:province":"OH",
    "sg:tags":[
        "return",
        "filing"
    ],
    "wof:name":"H & R Block Tax Svc",
    "wof:placetype":"venue"
},
  "geometry": {"coordinates":[-82.084234,39.502649],"type":"Point"}
}