{
  "type": "Feature",
  "properties": {
    "addr:full": "113 N Hambden St Chardon OH 44024",
    "addr:housenumber": "113",
    "addr:postcode": "44024",
    "addr:street": "N Hambden St",
    "iso:country": "US",
    "sg:address": "113 N Hambden St",
    "sg:city": "Chardon",
    "sg:classifiers": [
      {
        "category": "Wholesale",
        "subcategory": "Hardware",
        "type": "Manufacturing \u0026 Wholesale Goods"
      }
    ],
    "sg:phone": "+1 440 286 6269",
    "sg:postcode": "44024",
    "sg:province": "OH",
    "sg:tags": [
      "dust",
      "collecting",
      "system"
    ],
    "wof:name": "Aquilla Engineering Inc",
    "wof:placetype": "venue"
  },
  "geometry": {"coordinates":[-81.202867,41.583529],"type":"Point"}
}
