{
  "type": "Feature",
  "properties": {
    "iso:country":"US",
    "sg:address":"113 N Hambden St",
    "sg:city":"Chardon",
    "sg:classifiers":[
        {
            "category":"Wholesale",
            "subcategory":"Hardware",
            "type":"Manufacturing & Wholesale Goods"
        }
    ],
    "sg:phone":"+1 440 286 6269",
    "sg:postcode":"44024",
    "sg:province":"OH",
    "sg:tags":[
        "dust",
        "collecting",
        "system"
    ],
    "wof:name":"Aquilla Engineering Inc",
    "wof:placetype":"venue"
},
  "geometry": {"coordinates":[-81.202867,41.583529],"type":"Point"}
}