{
  "type": "Feature",
  "properties": {
    "addr:full": "880 E 11th Ave Columbus OH 43211",
    "addr:housenumber": "880",
    "addr:postcode": "43211",
    "addr:street": "E 11Th Ave",
    "iso:country": "US",
    "sg:address": "880 E 11th Ave",
    "sg:city": "Columbus",
    "sg:classifiers": [
      {
        "category": "Real Estate",
        "subcategory": "Real Estate Operator",
        "type": "Services"
      }
    ],
    "sg:phone": "+1 614 237 2072",
    "sg:postcode": "43211",
    "sg:province": "OH",
    "sg:tags": [
      "apartment"
    ],
    "wof:name": "Eastmoor Square",
    "wof:placetype": "venue"
  },
  "geometry": {"coordinates":[-82.982927,39.993824],"type":"Point"}
}
