{
  "type": "Feature",
  "properties": {
    "addr:full":"1006 S High St Columbus OH 43206",
    "addr:housenumber":"1006",
    "addr:postcode":"43206",
    "addr:street":"S High St",
    "iso:country":"US",
    "sg:address":"1006 S High St",
    "sg:city":"Columbus",
    "sg:classifiers":[
        {
            "category":"Restaurant",
            "type":"Food & Drink"
        }
    ],
    "sg:menulink":"http://www.allmenus.com/oh/columbus/194827-mcdonalds/menu/",
    "sg:postcode":"43206",
    "sg:province":"OH",
    "sg:tags":[
        "burger",
        "american"
    ],
    "wof:name":"McDonald's",
    "wof:placetype":"venue"
},
  "geometry": {"coordinates":[-82.996669,39.941537],"type":"Point"}
}