{
  "type": "Feature",
  "properties": {
    "addr:full": "217 N Grant Ave Columbus OH 43215",
    "addr:housenumber": "217",
    "addr:postcode": "43215",
    "addr:street": "N Grant Ave",
    "iso:country": "US",
    "sg:address": "217 N Grant Ave",
    "sg:city": "Columbus",
    "sg:classifiers": [
      {
        "category": "Manufacturing",
        "subcategory": "Printing",
        "type": "Manufacturing \u0026 Wholesale Goods"
      }
    ],
    "sg:phone": "+1 614 221 6811",
    "sg:postcode": "43215",
    "sg:province": "OH",
    "sg:tags": [
      "printer",
      "ad",
      "lithographic",
      "direct",
      "typesetting",
      "print",
      "mail"
    ],
    "sg:website": "www.buckeyepm.com",
    "wof:name": "Buckeye Printing \u0026 Mailing Svc",
    "wof:placetype": "venue"
  },
  "geometry": {"coordinates":[-82.992127,39.968444],"type":"Point"}
}
