{
  "type": "Feature",
  "properties": {
    "iso:country":"US",
    "sg:address":"213 Liberty St",
    "sg:city":"Conneaut",
    "sg:classifiers":[
        {
            "category":"Autos & Motor Vehicles",
            "subcategory":"Automobile Sales",
            "type":"Retail Goods"
        }
    ],
    "sg:phone":"+1 440 599 5544",
    "sg:postcode":"44030",
    "sg:province":"OH",
    "sg:tags":[
        "car",
        "dealer"
    ],
    "wof:name":"Community Auto Ctr",
    "wof:placetype":"venue"
},
  "geometry": {"coordinates":[-80.554007,41.942403],"type":"Point"}
}