{
  "type": "Feature",
  "properties": {
    "addr:full": "1890 S Taylor Rd Cleveland OH 44118",
    "addr:housenumber": "1890",
    "addr:postcode": "44118",
    "addr:street": "S Taylor Rd",
    "iso:country": "US",
    "sg:address": "1890 S Taylor Rd",
    "sg:city": "Cleveland",
    "sg:classifiers": [
      {
        "category": "Retail",
        "subcategory": "Auto Repair",
        "type": "Services"
      }
    ],
    "sg:phone": "+1 216 321 0553",
    "sg:postcode": "44118",
    "sg:province": "OH",
    "sg:tags": [
      "repairing",
      "automobile"
    ],
    "wof:name": "Mike's Service",
    "wof:placetype": "venue"
  },
  "geometry": {"coordinates":[-81.555897,41.507344],"type":"Point"}
}
