{
  "type": "Feature",
  "properties": {
    "addr:full": "1042 Mentor Ave Painesville OH 44077",
    "addr:housenumber": "1042",
    "addr:postcode": "44077",
    "addr:street": "Mentor Ave",
    "iso:country": "US",
    "sg:address": "1042 Mentor Ave",
    "sg:city": "Painesville",
    "sg:classifiers": [
      {
        "category": "Shopping",
        "subcategory": "Musical Instruments",
        "type": "Retail Goods"
      }
    ],
    "sg:phone": "+1 440 352 2391",
    "sg:postcode": "44077",
    "sg:province": "OH",
    "wof:name": "Four Oaks Music",
    "wof:placetype": "venue"
  },
  "geometry": {"coordinates":[-81.265224,41.709315],"type":"Point"}
}
