{
  "type": "Feature",
  "properties": {
    "addr:full": "2419 Far Hills Ave Dayton OH 45419",
    "addr:housenumber": "2419",
    "addr:postcode": "45419",
    "addr:street": "Far Hills Ave",
    "iso:country": "US",
    "sg:address": "2419 Far Hills Ave",
    "sg:city": "Dayton",
    "sg:classifiers": [
      {
        "category": "Shopping",
        "subcategory": "Pharmacy",
        "type": "Retail Goods"
      }
    ],
    "sg:phone": "+1 937 293 3172",
    "sg:postcode": "45419",
    "sg:province": "OH",
    "wof:name": "Medicine Shoppe",
    "wof:placetype": "venue"
  },
  "geometry": {"coordinates":[-84.171085,39.709095],"type":"Point"}
}
