{
  "type": "Feature",
  "properties": {
    "iso:country":"US",
    "sg:address":"3150 Compton Rd",
    "sg:city":"Cincinnati",
    "sg:classifiers":[
        {
            "category":"Shopping",
            "subcategory":"Florist",
            "type":"Retail Goods"
        }
    ],
    "sg:phone":"+1 513 729 1134",
    "sg:postcode":"45251",
    "sg:province":"OH",
    "sg:tags":[
        "plant"
    ],
    "wof:name":"Jim Krismer Northgate Grnhouse",
    "wof:placetype":"venue"
},
  "geometry": {"coordinates":[-84.584838,39.238333],"type":"Point"}
}