{
  "type": "Feature",
  "properties": {
    "addr:full": "3118 Cleveland Ave NW Canton OH 44709",
    "addr:housenumber": "3118",
    "addr:postcode": "44709",
    "addr:street": "Cleveland Ave Nw",
    "iso:country": "US",
    "sg:address": "3118 Cleveland Ave NW",
    "sg:city": "Canton",
    "sg:classifiers": [
      {
        "category": "Health Services",
        "subcategory": "Health Practitioner",
        "type": "Services"
      }
    ],
    "sg:phone": "+1 330 492 9913",
    "sg:postcode": "44709",
    "sg:province": "OH",
    "sg:tags": [
      "psychologist"
    ],
    "wof:name": "Richard A George PHD Inc",
    "wof:placetype": "venue"
  },
  "geometry": {"coordinates":[-81.388576,40.833512],"type":"Point"}
}
