{
  "type": "Feature",
  "properties": {
    "addr:full": "7140 Garden Rd Cincinnati OH 45236",
    "addr:housenumber": "7140",
    "addr:postcode": "45236",
    "addr:street": "Garden Rd",
    "iso:country": "US",
    "sg:address": "7140 Garden Rd",
    "sg:city": "Cincinnati",
    "sg:classifiers": [
      {
        "category": "Building \u0026 Trades",
        "subcategory": "Construction",
        "type": "Services"
      }
    ],
    "sg:phone": "+1 513 821 2985",
    "sg:postcode": "45236",
    "sg:province": "OH",
    "sg:tags": [
      "contractor",
      "hanging"
    ],
    "wof:name": "Devore Roofing LLC",
    "wof:placetype": "venue"
  },
  "geometry": {"coordinates":[-84.387749,39.199134],"type":"Point"}
}
