{
  "type": "Feature",
  "properties": {
    "addr:full": "1871 Cardinal Ct Niles OH 44446",
    "addr:housenumber": "1871",
    "addr:postcode": "44446",
    "addr:street": "Cardinal Ct",
    "iso:country": "US",
    "sg:address": "1871 Cardinal Ct",
    "sg:city": "Niles",
    "sg:classifiers": [
      {
        "category": "Real Estate",
        "subcategory": "Real Estate Agent",
        "type": "Services"
      }
    ],
    "sg:phone": "+1 330 652 2615",
    "sg:postcode": "44446",
    "sg:province": "OH",
    "wof:name": "Barbara Setting Real Estate",
    "wof:placetype": "venue"
  },
  "geometry": {"coordinates":[-80.728146,41.190797],"type":"Point"}
}
