{
  "type": "Feature",
  "properties": {
    "addr:full":"7051 E Miami River Rd Cleves OH 45002",
    "addr:housenumber":"7051",
    "addr:postcode":"45002",
    "addr:street":"E Miami River Rd",
    "iso:country":"US",
    "sg:address":"7051 E Miami River Rd",
    "sg:city":"Cleves",
    "sg:classifiers":[
        {
            "category":"Building & Trades",
            "subcategory":"Construction",
            "type":"Services"
        }
    ],
    "sg:phone":"+1 513 353 3332",
    "sg:postcode":"45002",
    "sg:province":"OH",
    "sg:tags":[
        "contractor"
    ],
    "wof:name":"T H E Roofing and Shtmtl Co",
    "wof:placetype":"venue"
},
  "geometry": {"coordinates":[-84.694362,39.211785],"type":"Point"}
}