{
  "type": "Feature",
  "properties": {
    "addr:full": "2865 S High St Columbus OH 43207",
    "addr:housenumber": "2865",
    "addr:postcode": "43207",
    "addr:street": "S High St",
    "iso:country": "US",
    "sg:address": "2865 S High St",
    "sg:city": "Columbus",
    "sg:classifiers": [
      {
        "category": "Retail",
        "subcategory": "Driving School",
        "type": "Services"
      },
      {
        "category": "Autos \u0026 Motor Vehicles",
        "subcategory": "Motorcycle Sales",
        "type": "Retail Goods"
      },
      {
        "category": "Retail",
        "subcategory": "Auto Repair",
        "type": "Services"
      }
    ],
    "sg:phone": "+1 614 491 5618",
    "sg:postcode": "43207",
    "sg:province": "OH",
    "sg:tags": [
      "scooters-repairing",
      "scooters-parts",
      "instruction",
      "supply"
    ],
    "sg:website": "http://www.reiserscycle.com",
    "wof:name": "Reiser's Cycle Service",
    "wof:placetype": "venue"
  },
  "geometry": {"coordinates":[-82.995338,39.903118],"type":"Point"}
}
