{
  "type": "Feature",
  "properties": {
    "addr:full": "3200 Vestal Rd Youngstown OH 44509",
    "addr:housenumber": "3200",
    "addr:postcode": "44509",
    "addr:street": "Vestal Rd",
    "iso:country": "US",
    "sg:address": "3200 Vestal Rd",
    "sg:city": "Youngstown",
    "sg:classifiers": [
      {
        "category": "Recreation",
        "type": "Entertainment"
      },
      {
        "category": "Restaurant",
        "type": "Food \u0026 Drink"
      }
    ],
    "sg:phone": "+1 330 799 0914",
    "sg:postcode": "44509",
    "sg:province": "OH",
    "sg:tags": [
      "eating",
      "hall",
      "auditorium"
    ],
    "wof:name": "Croation Home",
    "wof:placetype": "venue"
  },
  "geometry": {"coordinates":[-80.708032,41.117867],"type":"Point"}
}
