{
  "type": "Feature",
  "properties": {
    "iso:country":"US",
    "sg:address":"35 E Hudson St",
    "sg:city":"Columbus",
    "sg:classifiers":[
        {
            "category":"Professional",
            "subcategory":"Accounting & Tax Preparation",
            "type":"Services"
        }
    ],
    "sg:phone":"+1 614 847 2141",
    "sg:postcode":"43202",
    "sg:province":"OH",
    "sg:tags":[
        "return",
        "filing"
    ],
    "wof:name":"Jackson Hewitt Tax Svc",
    "wof:placetype":"venue"
},
  "geometry": {"coordinates":[-83.010189,40.014561],"type":"Point"}
}