{
  "type": "Feature",
  "properties": {
    "addr:full": "17524 Miles Ave Cleveland OH 44128",
    "addr:housenumber": "17524",
    "addr:postcode": "44128",
    "addr:street": "Miles Ave",
    "iso:country": "US",
    "sg:address": "17524 Miles Ave",
    "sg:city": "Cleveland",
    "sg:classifiers": [
      {
        "category": "Sports \u0026 Exercise",
        "subcategory": "Race Track",
        "type": "Entertainment"
      }
    ],
    "sg:phone": "+1 216 752 1140",
    "sg:postcode": "44128",
    "sg:province": "OH",
    "wof:name": "Ace Racing Team",
    "wof:placetype": "venue"
  },
  "geometry": {"coordinates":[-81.556189,41.437768],"type":"Point"}
}
