{
  "type": "Feature",
  "properties": {
    "iso:country":"US",
    "sg:address":"840 Heath Rd",
    "sg:city":"Newark",
    "sg:phone":"+1 740 522 8448",
    "sg:postcode":"43056",
    "sg:province":"OH",
    "sg:tags":[
        "oil"
    ],
    "wof:name":"Ashland Oil Inc",
    "wof:placetype":"venue"
},
  "geometry": {"coordinates":[-82.470461,40.023893],"type":"Point"}
}