{
  "type": "Feature",
  "properties": {
    "iso:country":"US",
    "sg:address":"7890 Navarre Rd SW",
    "sg:city":"Massillon",
    "sg:classifiers":[
        {
            "category":"Autos & Motor Vehicles",
            "subcategory":"Automobile Sales",
            "type":"Retail Goods"
        }
    ],
    "sg:phone":"+1 330 484 1554",
    "sg:postcode":"44646",
    "sg:province":"OH",
    "sg:tags":[
        "car",
        "dealer"
    ],
    "wof:name":"Exit 99 Sales",
    "wof:placetype":"venue"
},
  "geometry": {"coordinates":[-81.50694799999999,40.746874],"type":"Point"}
}