{
  "type": "Feature",
  "properties": {
    "addr:full": "188 E William St Delaware OH 43015",
    "addr:housenumber": "188",
    "addr:postcode": "43015",
    "addr:street": "E William St",
    "iso:country": "US",
    "sg:address": "188 E William St",
    "sg:city": "Delaware",
    "sg:classifiers": [
      {
        "category": "Home \u0026 Garden",
        "subcategory": "Building Materials",
        "type": "Retail Goods"
      }
    ],
    "sg:phone": "+1 740 363 1196",
    "sg:postcode": "43015",
    "sg:province": "OH",
    "sg:website": "www.hamiltonparker.com",
    "wof:name": "Hamilton Parker Co",
    "wof:placetype": "venue"
  },
  "geometry": {"coordinates":[-83.058287,40.298339],"type":"Point"}
}
