{
  "type": "Feature",
  "properties": {
    "iso:country":"US",
    "sg:address":"2600 Parsons Ave",
    "sg:city":"Columbus",
    "sg:classifiers":[
        {
            "category":"Railroad",
            "type":"Transportation"
        }
    ],
    "sg:phone":"+1 614 444 1753",
    "sg:postcode":"43207",
    "sg:province":"OH",
    "sg:tags":[
        "line"
    ],
    "wof:name":"Chessie Systems C&O 142",
    "wof:placetype":"venue"
},
  "geometry": {"coordinates":[-82.985529,39.908945],"type":"Point"}
}