{
  "type": "Feature",
  "properties": {
    "addr:full":"479 W Dussel Dr Maumee OH 43537",
    "addr:housenumber":"479",
    "addr:postcode":"43537",
    "addr:street":"W Dussel Dr",
    "iso:country":"US",
    "sg:address":"479 W Dussel Dr",
    "sg:city":"Maumee",
    "sg:classifiers":[
        {
            "category":"Ice Cream",
            "type":"Food & Drink"
        }
    ],
    "sg:menulink":"http://www.allmenus.com/oh/maumee/184259-cold-stone-creamery/menu/",
    "sg:phone":"+1 419 482 6610",
    "sg:postcode":"43537",
    "sg:province":"OH",
    "sg:tags":[
        "smoothy",
        "juice",
        "american"
    ],
    "wof:name":"Cold Stone Creamery",
    "wof:placetype":"venue"
},
  "geometry": {"coordinates":[-83.679351,41.58026],"type":"Point"}
}