{
  "type": "Feature",
  "properties": {
    "iso:country":"US",
    "sg:address":"3803 Fox Run Dr",
    "sg:city":"Cincinnati",
    "sg:classifiers":[
        {
            "category":"Real Estate",
            "subcategory":"Real Estate Operator",
            "type":"Services"
        }
    ],
    "sg:phone":"+1 513 791 3638",
    "sg:postcode":"45236",
    "sg:province":"OH",
    "sg:tags":[
        "apartment"
    ],
    "wof:name":"Fox Run Apartments",
    "wof:placetype":"venue"
},
  "geometry": {"coordinates":[-84.407623,39.225006],"type":"Point"}
}