{
  "type": "Feature",
  "properties": {
    "iso:country":"US",
    "sg:address":"30432 Euclid Ave",
    "sg:city":"Wickliffe",
    "sg:classifiers":[
        {
            "category":"Professional",
            "subcategory":"Management & Consulting",
            "type":"Services"
        }
    ],
    "sg:phone":"+1 440 943 3717",
    "sg:postcode":"44092",
    "sg:province":"OH",
    "sg:tags":[
        "construction"
    ],
    "wof:name":"KNM Consultants Inc",
    "wof:placetype":"venue"
},
  "geometry": {"coordinates":[-81.458485,41.617817],"type":"Point"}
}