{
  "type": "Feature",
  "properties": {
    "addr:full": "7162 Reading Rd Cincinnati OH 45237",
    "addr:housenumber": "7162",
    "addr:postcode": "45237",
    "addr:street": "Reading Rd",
    "iso:country": "US",
    "sg:address": "7162 Reading Rd",
    "sg:city": "Cincinnati",
    "sg:classifiers": [
      {
        "category": "Insurance",
        "subcategory": "Insurance Agent",
        "type": "Services"
      }
    ],
    "sg:phone": "+1 513 351 1222",
    "sg:postcode": "45237",
    "sg:province": "OH",
    "sg:tags": [
      "administrator"
    ],
    "sg:website": "www.mtrxinc.com",
    "wof:name": "Matrix Investigations \u0026 Cnsltg",
    "wof:placetype": "venue"
  },
  "geometry": {"coordinates":[-84.462217,39.19058],"type":"Point"}
}
