{
  "type": "Feature",
  "properties": {
    "iso:country":"US",
    "sg:address":"1524 13th St SE",
    "sg:city":"Canton",
    "sg:classifiers":[
        {
            "category":"Professional",
            "type":"Services"
        }
    ],
    "sg:phone":"+1 330 456 6414",
    "sg:postcode":"44707",
    "sg:province":"OH",
    "wof:name":"Virginia Hawk",
    "wof:placetype":"venue"
},
  "geometry": {"coordinates":[-81.36097100000001,40.786529],"type":"Point"}
}