{
  "type": "Feature",
  "properties": {
    "addr:full":"3746 Riverside Dr Columbus OH 43221",
    "addr:housenumber":"3746",
    "addr:postcode":"43221",
    "addr:street":"Riverside Dr",
    "iso:country":"US",
    "sg:address":"3746 Riverside Dr",
    "sg:city":"Columbus",
    "sg:classifiers":[
        {
            "category":"Restaurant",
            "type":"Food & Drink"
        }
    ],
    "sg:phone":"+1 614 326 3663",
    "sg:postcode":"43221",
    "sg:province":"OH",
    "wof:name":"Mc Donald's",
    "wof:placetype":"venue"
},
  "geometry": {"coordinates":[-83.091132,40.026885],"type":"Point"}
}