{
  "type": "Feature",
  "properties": {
    "addr:full":"3683 Corporate Dr Columbus OH 43231",
    "addr:housenumber":"3683",
    "addr:postcode":"43231",
    "addr:street":"Corporate Dr",
    "iso:country":"US",
    "sg:address":"3683 Corporate Dr",
    "sg:city":"Columbus",
    "sg:classifiers":[
        {
            "category":"Professional",
            "subcategory":"Detective & Security Services",
            "type":"Services"
        }
    ],
    "sg:phone":"+1 614 794 3400",
    "sg:postcode":"43231",
    "sg:province":"OH",
    "sg:tags":[
        "equipment",
        "electrical",
        "system"
    ],
    "wof:name":"Protection One Alarm Mnitoring",
    "wof:placetype":"venue"
},
  "geometry": {"coordinates":[-82.921183,40.07911],"type":"Point"}
}