{
  "type": "Feature",
  "properties": {
    "addr:full": "14200 Superior Rd Cleveland OH 44118",
    "addr:housenumber": "14200",
    "addr:postcode": "44118",
    "addr:street": "Superior Rd",
    "iso:country": "US",
    "sg:address": "14200 Superior Rd",
    "sg:city": "Cleveland",
    "sg:classifiers": [
      {
        "category": "Building \u0026 Trades",
        "subcategory": "Construction",
        "type": "Services"
      }
    ],
    "sg:phone": "+1 216 691 7300",
    "sg:postcode": "44118",
    "sg:province": "OH",
    "sg:tags": [
      "marking",
      "maintenance",
      "parking"
    ],
    "wof:name": "Cleveland Heights Public Works",
    "wof:placetype": "venue"
  },
  "geometry": {"coordinates":[-81.572977,41.514374],"type":"Point"}
}
