{
  "type": "Feature",
  "properties": {
    "iso:country":"US",
    "sg:address":"6770 Mayfield Rd",
    "sg:city":"Cleveland",
    "sg:classifiers":[
        {
            "category":"Health Services",
            "subcategory":"Doctor",
            "type":"Services"
        }
    ],
    "sg:phone":"+1 216 241 6638",
    "sg:postcode":"44124",
    "sg:province":"OH",
    "sg:tags":[
        "specialist",
        "retinal"
    ],
    "wof:name":"Northern Ohio Retinal Cons",
    "wof:placetype":"venue"
},
  "geometry": {"coordinates":[-81.434549,41.52003],"type":"Point"}
}