{
  "type": "Feature",
  "properties": {
    "addr:full": "2287 Johnston Rd Columbus OH 43220",
    "addr:housenumber": "2287",
    "addr:postcode": "43220",
    "addr:street": "Johnston Rd",
    "iso:country": "US",
    "sg:address": "2287 Johnston Rd",
    "sg:city": "Columbus",
    "sg:classifiers": [
      {
        "category": "Professional",
        "subcategory": "Management \u0026 Consulting",
        "type": "Services"
      }
    ],
    "sg:phone": "+1 614 442 5505",
    "sg:postcode": "43220",
    "sg:province": "OH",
    "sg:tags": [
      "construction"
    ],
    "wof:name": "Project Control Systs",
    "wof:placetype": "venue"
  },
  "geometry": {"coordinates":[-83.078571,40.034907],"type":"Point"}
}
