{
  "type": "Feature",
  "properties": {
    "iso:country":"US",
    "sg:address":"1043 W North Bend Rd",
    "sg:city":"Cincinnati",
    "sg:classifiers":[
        {
            "category":"Personal",
            "subcategory":"Beauty Salon",
            "type":"Services"
        }
    ],
    "sg:phone":"+1 513 541 5662",
    "sg:postcode":"45224",
    "sg:province":"OH",
    "wof:name":"Beauty & Glamour Salon",
    "wof:placetype":"venue"
},
  "geometry": {"coordinates":[-84.531018,39.201939],"type":"Point"}
}