{
  "type": "Feature",
  "properties": {
    "iso:country":"US",
    "sg:address":"3481 Lindsey Rd",
    "sg:city":"Mansfield",
    "sg:classifiers":[
        {
            "category":"Government",
            "subcategory":"Office",
            "type":"Public Place"
        }
    ],
    "sg:phone":"+1 419 884 3698",
    "sg:postcode":"44904",
    "sg:province":"OH",
    "sg:tags":[
        "executive"
    ],
    "wof:name":"Clerks Office",
    "wof:placetype":"venue"
},
  "geometry": {"coordinates":[-82.602092,40.661655],"type":"Point"}
}