{
  "type": "Feature",
  "properties": {
    "addr:full": "358 Erie St S Massillon OH 44646",
    "addr:housenumber": "358",
    "addr:postcode": "44646",
    "addr:street": "Erie St S",
    "iso:country": "US",
    "sg:address": "358 Erie St S",
    "sg:city": "Massillon",
    "sg:classifiers": [
      {
        "category": "Retail",
        "subcategory": "Auto Rental",
        "type": "Services"
      }
    ],
    "sg:phone": "+1 330 833 6791",
    "sg:postcode": "44646",
    "sg:province": "OH",
    "sg:tags": [
      "renting",
      "automobile"
    ],
    "wof:name": "Ed Hendon's Daily Car Rental",
    "wof:placetype": "venue"
  },
  "geometry": {"coordinates":[-81.52157,40.793471],"type":"Point"}
}
