{
  "type": "Feature",
  "properties": {
    "iso:country":"US",
    "sg:address":"711 Hadley Dr",
    "sg:city":"Columbus",
    "sg:classifiers":[
        {
            "category":"Wholesale",
            "subcategory":"Construction Materials",
            "type":"Manufacturing & Wholesale Goods"
        }
    ],
    "sg:phone":"+1 614 272 5577",
    "sg:postcode":"43228",
    "sg:province":"OH",
    "sg:tags":[
        "windows",
        "roofing",
        "siding",
        "door"
    ],
    "wof:name":"Marsh Building Products",
    "wof:placetype":"venue"
},
  "geometry": {"coordinates":[-83.098264,39.968318],"type":"Point"}
}