{
  "type": "Feature",
  "properties": {
    "addr:full": "46 Mattatuck Way Waterville OH 43566",
    "addr:housenumber": "46",
    "addr:postcode": "43566",
    "addr:street": "Mattatuck Way",
    "iso:country": "US",
    "sg:address": "46 Mattatuck Way",
    "sg:city": "Waterville",
    "sg:classifiers": [
      {
        "category": "Manufacturing",
        "subcategory": "Tools \u0026 Machinery",
        "type": "Manufacturing \u0026 Wholesale Goods"
      }
    ],
    "sg:phone": "+1 419 878 0042",
    "sg:postcode": "43566",
    "sg:province": "OH",
    "sg:tags": [
      "industrial",
      "mfg"
    ],
    "wof:name": "T\u0026R Design Ltd",
    "wof:placetype": "venue"
  },
  "geometry": {"coordinates":[-83.735891,41.506301],"type":"Point"}
}
