{
  "type": "Feature",
  "properties": {
    "addr:full": "87 Progress Dr Xenia OH 45385",
    "addr:housenumber": "87",
    "addr:postcode": "45385",
    "addr:street": "Progress Dr",
    "iso:country": "US",
    "sg:address": "87 Progress Dr",
    "sg:city": "Xenia",
    "sg:classifiers": [
      {
        "category": "Professional",
        "subcategory": "Lawyer \u0026 Legal Services",
        "type": "Services"
      }
    ],
    "sg:phone": "+1 937 372 3584",
    "sg:postcode": "45385",
    "sg:province": "OH",
    "sg:tags": [
      "attorney"
    ],
    "wof:name": "Peterson \u0026 Peterson",
    "wof:placetype": "venue"
  },
  "geometry": {"coordinates":[-83.962988,39.689259],"type":"Point"}
}
