{
  "type": "Feature",
  "properties": {
    "iso:country":"US",
    "sg:address":"371 Marion Ave",
    "sg:city":"Mansfield",
    "sg:classifiers":[
        {
            "category":"Restaurant",
            "type":"Food & Drink"
        }
    ],
    "sg:phone":"+1 419 526 6009",
    "sg:postcode":"44903",
    "sg:province":"OH",
    "sg:tags":[
        "lunch",
        "brunch",
        "cafeteria",
        "breakfast"
    ],
    "wof:name":"Sip N Surf Cyber Caf",
    "wof:placetype":"venue"
},
  "geometry": {"coordinates":[-82.53434300000001,40.753914],"type":"Point"}
}