{
  "type": "Feature",
  "properties": {
    "addr:full": "1859 Burbank Rd Wooster OH 44691",
    "addr:housenumber": "1859",
    "addr:postcode": "44691",
    "addr:street": "Burbank Rd",
    "iso:country": "US",
    "sg:address": "1859 Burbank Rd",
    "sg:city": "Wooster",
    "sg:classifiers": [
      {
        "category": "Social Services",
        "subcategory": "Child Care",
        "type": "Services"
      }
    ],
    "sg:phone": "+1 330 264 5222",
    "sg:postcode": "44691",
    "sg:province": "OH",
    "sg:tags": [
      "kindergarten",
      "academic",
      "school"
    ],
    "wof:name": "Children's House Montessori",
    "wof:placetype": "venue"
  },
  "geometry": {"coordinates":[-81.938508,40.822787],"type":"Point"}
}
