{
  "type": "Feature",
  "properties": {
    "iso:country":"US",
    "sg:address":"8008 Lakeloop Dr",
    "sg:city":"Westerville",
    "sg:classifiers":[
        {
            "category":"Freight",
            "type":"Transportation"
        }
    ],
    "sg:phone":"+1 614 846 3565",
    "sg:postcode":"43081",
    "sg:province":"OH",
    "wof:name":"L&P Transport & Logistics Inc",
    "wof:placetype":"venue"
},
  "geometry": {"coordinates":[-82.99185900000001,40.128493],"type":"Point"}
}