{
  "type": "Feature",
  "properties": {
    "addr:full": "8008 Lakeloop Dr Westerville OH 43081",
    "addr:housenumber": "8008",
    "addr:postcode": "43081",
    "addr:street": "Lakeloop Dr",
    "iso:country": "US",
    "sg:address": "8008 Lakeloop Dr",
    "sg:city": "Westerville",
    "sg:classifiers": [
      {
        "category": "Freight",
        "type": "Transportation"
      }
    ],
    "sg:phone": "+1 614 846 3565",
    "sg:postcode": "43081",
    "sg:province": "OH",
    "wof:name": "L\u0026P Transport \u0026 Logistics Inc",
    "wof:placetype": "venue"
  },
  "geometry": {"coordinates":[-82.991859,40.128493],"type":"Point"}
}
