{
  "type": "Feature",
  "properties": {
    "addr:full": "2890 Brecksville Rd Richfield OH 44286",
    "addr:housenumber": "2890",
    "addr:postcode": "44286",
    "addr:street": "Brecksville Rd",
    "iso:country": "US",
    "sg:address": "2890 Brecksville Rd",
    "sg:city": "Richfield",
    "sg:classifiers": [
      {
        "category": "Banks \u0026 Credit Unions",
        "subcategory": "Investment Brokerage",
        "type": "Services"
      }
    ],
    "sg:phone": "+1 330 659 6191",
    "sg:postcode": "44286",
    "sg:province": "OH",
    "wof:name": "Broker's Investment Corp",
    "wof:placetype": "venue"
  },
  "geometry": {"coordinates":[-81.638147,41.211145],"type":"Point"}
}
