{
  "type": "Feature",
  "properties": {
    "addr:full": "5840 Co Rd 201 Millersburg OH 44654",
    "addr:housenumber": "5840",
    "addr:postcode": "201;44654",
    "addr:street": "Co Rd",
    "iso:country": "US",
    "sg:address": "5840 Co Rd 201",
    "sg:city": "Millersburg",
    "sg:classifiers": [
      {
        "category": "Building \u0026 Trades",
        "subcategory": "Construction",
        "type": "Services"
      }
    ],
    "sg:phone": "+1 330 893 3674",
    "sg:postcode": "44654",
    "sg:province": "OH",
    "sg:tags": [
      "a",
      "summer",
      "mfg",
      "frame",
      "storage",
      "erects",
      "small",
      "home",
      "barn"
    ],
    "wof:name": "J D M Structures LLC",
    "wof:placetype": "venue"
  },
  "geometry": {"coordinates":[-81.820627,40.568803],"type":"Point"}
}
