{
  "type": "Feature",
  "properties": {
    "iso:country":"US",
    "sg:address":"5840 Co Rd 201",
    "sg:city":"Millersburg",
    "sg:classifiers":[
        {
            "category":"Building & Trades",
            "subcategory":"Construction",
            "type":"Services"
        }
    ],
    "sg:phone":"+1 330 893 3674",
    "sg:postcode":"44654",
    "sg:province":"OH",
    "sg:tags":[
        "a",
        "summer",
        "mfg",
        "frame",
        "storage",
        "erects",
        "small",
        "home",
        "barn"
    ],
    "wof:name":"J D M Structures LLC",
    "wof:placetype":"venue"
},
  "geometry": {"coordinates":[-81.820627,40.568803],"type":"Point"}
}