{
  "type": "Feature",
  "properties": {
    "addr:full":"2120 Centennial Rd Toledo OH 43617",
    "addr:housenumber":"2120",
    "addr:postcode":"43617",
    "addr:street":"Centennial Rd",
    "iso:country":"US",
    "sg:address":"2120 Centennial Rd",
    "sg:city":"Toledo",
    "sg:classifiers":[
        {
            "category":"Shopping",
            "type":"Retail Goods"
        }
    ],
    "sg:phone":"+1 419 841 9896",
    "sg:postcode":"43617",
    "sg:province":"OH",
    "sg:tags":[
        "wedding",
        "supply"
    ],
    "wof:name":"Floral Designer Annette",
    "wof:placetype":"venue"
},
  "geometry": {"coordinates":[-83.741315,41.658302],"type":"Point"}
}