{
  "type": "Feature",
  "properties": {
    "addr:full": "3104 State Rd Ashtabula OH 44004",
    "addr:housenumber": "3104",
    "addr:postcode": "44004",
    "addr:street": "State Rd",
    "iso:country": "US",
    "sg:address": "3104 State Rd",
    "sg:city": "Ashtabula",
    "sg:classifiers": [
      {
        "category": "Wholesale",
        "subcategory": "Fruits \u0026 Vegetables",
        "type": "Manufacturing \u0026 Wholesale Goods"
      }
    ],
    "sg:phone": "+1 440 992 5252",
    "sg:postcode": "44004",
    "sg:province": "OH",
    "wof:name": "Chapman's Produce",
    "wof:placetype": "venue"
  },
  "geometry": {"coordinates":[-80.772467,41.8777],"type":"Point"}
}
