{
  "type": "Feature",
  "properties": {
    "iso:country":"US",
    "sg:address":"3104 State Rd",
    "sg:city":"Ashtabula",
    "sg:classifiers":[
        {
            "category":"Wholesale",
            "subcategory":"Fruits & Vegetables",
            "type":"Manufacturing & Wholesale Goods"
        }
    ],
    "sg:phone":"+1 440 992 5252",
    "sg:postcode":"44004",
    "sg:province":"OH",
    "wof:name":"Chapman's Produce",
    "wof:placetype":"venue"
},
  "geometry": {"coordinates":[-80.772467,41.8777],"type":"Point"}
}