{
  "type": "Feature",
  "properties": {
    "addr:full":"114 S Defiance St Stryker OH 43557",
    "addr:housenumber":"114",
    "addr:postcode":"43557",
    "addr:street":"S Defiance St",
    "iso:country":"US",
    "sg:address":"114 S Defiance St",
    "sg:city":"Stryker",
    "sg:classifiers":[
        {
            "category":"Government",
            "subcategory":"Post Office",
            "type":"Public Place"
        }
    ],
    "sg:phone":"+1 419 682 3221",
    "sg:postcode":"43557",
    "sg:province":"OH",
    "wof:name":"US Post Office",
    "wof:placetype":"venue"
},
  "geometry": {"coordinates":[-84.414404,41.49968],"type":"Point"}
}