{
  "type": "Feature",
  "properties": {
    "addr:full": "5733 Springboro Pike Dayton OH 45449",
    "addr:housenumber": "5733",
    "addr:postcode": "45449",
    "addr:street": "Springboro Pike",
    "iso:country": "US",
    "sg:address": "5733 Springboro Pike",
    "sg:city": "Dayton",
    "sg:classifiers": [
      {
        "category": "Building \u0026 Trades",
        "subcategory": "Construction",
        "type": "Services"
      }
    ],
    "sg:phone": "+1 937 299 2054",
    "sg:postcode": "45449",
    "sg:province": "OH",
    "sg:tags": [
      "coping",
      "plastering",
      "tiling",
      "pool",
      "swimming"
    ],
    "wof:name": "Bethesda Pool Svc",
    "wof:placetype": "venue"
  },
  "geometry": {"coordinates":[-84.221955,39.67337],"type":"Point"}
}
