{
  "type": "Feature",
  "properties": {
    "addr:full":"6864 State Rte 66 Archbold OH 43502",
    "addr:housenumber":"6864",
    "addr:postcode":"43502",
    "addr:street":"State Rte 66",
    "iso:country":"US",
    "sg:address":"6864 State Rte 66",
    "sg:city":"Archbold",
    "sg:classifiers":[
        {
            "category":"Building & Trades",
            "subcategory":"Electrical",
            "type":"Services"
        }
    ],
    "sg:phone":"+1 419 445 6406",
    "sg:postcode":"43502",
    "sg:province":"OH",
    "sg:tags":[
        "electric",
        "contractor"
    ],
    "wof:name":"Elden Roth Electric Co",
    "wof:placetype":"venue"
},
  "geometry": {"coordinates":[-84.306709,41.570888],"type":"Point"}
}