{
  "type": "Feature",
  "properties": {
    "addr:full": "510 Nilles Rd Fairfield OH 45014",
    "addr:housenumber": "510",
    "addr:postcode": "45014",
    "addr:street": "Nilles Rd",
    "iso:country": "US",
    "sg:address": "510 Nilles Rd",
    "sg:city": "Fairfield",
    "sg:classifiers": [
      {
        "category": "Restaurant",
        "type": "Food \u0026 Drink"
      }
    ],
    "sg:menulink": "http://www.allmenus.com/oh/fairfield/79342-pizza-hut/menu/",
    "sg:phone": "+1 513 829 0500",
    "sg:postcode": "45014",
    "sg:province": "OH",
    "sg:tags": [
      "american",
      "pizza"
    ],
    "wof:name": "Pizza Hut",
    "wof:placetype": "venue"
  },
  "geometry": {"coordinates":[-84.562778,39.338542],"type":"Point"}
}
