{
  "type": "Feature",
  "properties": {
    "iso:country":"US",
    "sg:address":"510 Nilles Rd",
    "sg:city":"Fairfield",
    "sg:classifiers":[
        {
            "category":"Restaurant",
            "type":"Food & Drink"
        }
    ],
    "sg:menulink":"http://www.allmenus.com/oh/fairfield/79342-pizza-hut/menu/",
    "sg:phone":"+1 513 829 0500",
    "sg:postcode":"45014",
    "sg:province":"OH",
    "sg:tags":[
        "american",
        "pizza"
    ],
    "wof:name":"Pizza Hut",
    "wof:placetype":"venue"
},
  "geometry": {"coordinates":[-84.56277799999999,39.338542],"type":"Point"}
}