{
  "type": "Feature",
  "properties": {
    "addr:full": "15179 Pleasant Valley Rd Chillicothe OH 45601",
    "addr:housenumber": "15179",
    "addr:postcode": "45601",
    "addr:street": "Pleasant Valley Rd",
    "iso:country": "US",
    "sg:address": "15179 Pleasant Valley Rd",
    "sg:city": "Chillicothe",
    "sg:classifiers": [
      {
        "category": "Home \u0026 Garden",
        "subcategory": "Building Materials",
        "type": "Retail Goods"
      }
    ],
    "sg:phone": "+1 740 773 2261",
    "sg:postcode": "45601",
    "sg:province": "OH",
    "sg:tags": [
      "glass",
      "window",
      "plate"
    ],
    "wof:name": "Grady Glass",
    "wof:placetype": "venue"
  },
  "geometry": {"coordinates":[-83.002197,39.355657],"type":"Point"}
}
