{
  "type": "Feature",
  "properties": {
    "iso:country":"US",
    "sg:address":"3111 State Rte 132",
    "sg:city":"Amelia",
    "sg:classifiers":[
        {
            "category":"Building & Trades",
            "subcategory":"Plumbing",
            "type":"Services"
        }
    ],
    "sg:phone":"+1 513 797 7008",
    "sg:postcode":"45102",
    "sg:province":"OH",
    "sg:tags":[
        "tank",
        "septic"
    ],
    "wof:name":"All Repair Septic Svc",
    "wof:placetype":"venue"
},
  "geometry": {"coordinates":[-84.210106,38.994844],"type":"Point"}
}