{
  "type": "Feature",
  "properties": {
    "addr:full": "3111 State Rte 132 Amelia OH 45102",
    "addr:housenumber": "3111",
    "addr:postcode": "45102",
    "addr:street": "State Rte 132",
    "iso:country": "US",
    "sg:address": "3111 State Rte 132",
    "sg:city": "Amelia",
    "sg:classifiers": [
      {
        "category": "Building \u0026 Trades",
        "subcategory": "Plumbing",
        "type": "Services"
      }
    ],
    "sg:phone": "+1 513 797 7008",
    "sg:postcode": "45102",
    "sg:province": "OH",
    "sg:tags": [
      "tank",
      "septic"
    ],
    "wof:name": "All Repair Septic Svc",
    "wof:placetype": "venue"
  },
  "geometry": {"coordinates":[-84.210106,38.994844],"type":"Point"}
}
