{
  "type": "Feature",
  "properties": {
    "addr:full": "333 Broadway Ave Bedford OH 44146",
    "addr:housenumber": "333",
    "addr:postcode": "44146",
    "addr:street": "Broadway Ave",
    "iso:country": "US",
    "sg:address": "333 Broadway Ave",
    "sg:city": "Bedford",
    "sg:classifiers": [
      {
        "category": "Autos \u0026 Motor Vehicles",
        "subcategory": "Automobile Sales",
        "type": "Retail Goods"
      }
    ],
    "sg:phone": "+1 440 439 7600",
    "sg:postcode": "44146",
    "sg:province": "OH",
    "sg:tags": [
      "car",
      "used",
      "dealer"
    ],
    "wof:name": "Bedford Auto Wholesale",
    "wof:placetype": "venue"
  },
  "geometry": {"coordinates":[-81.544633,41.399284],"type":"Point"}
}
