{
  "type": "Feature",
  "properties": {
    "iso:country":"US",
    "sg:address":"333 Broadway Ave",
    "sg:city":"Bedford",
    "sg:classifiers":[
        {
            "category":"Autos & Motor Vehicles",
            "subcategory":"Automobile Sales",
            "type":"Retail Goods"
        }
    ],
    "sg:phone":"+1 440 439 7600",
    "sg:postcode":"44146",
    "sg:province":"OH",
    "sg:tags":[
        "car",
        "used",
        "dealer"
    ],
    "wof:name":"Bedford Auto Wholesale",
    "wof:placetype":"venue"
},
  "geometry": {"coordinates":[-81.544633,41.399284],"type":"Point"}
}