{
  "type": "Feature",
  "properties": {
    "addr:full":"308 Van Buren St Delta OH 43515",
    "addr:housenumber":"308",
    "addr:postcode":"43515",
    "addr:street":"Van Buren St",
    "iso:country":"US",
    "sg:address":"308 Van Buren St",
    "sg:city":"Delta",
    "sg:classifiers":[
        {
            "category":"Retail",
            "subcategory":"Laundry & Dry Cleaning",
            "type":"Services"
        }
    ],
    "sg:phone":"+1 419 822 5811",
    "sg:postcode":"43515",
    "sg:province":"OH",
    "sg:tags":[
        "cleaners",
        "rug",
        "carpet"
    ],
    "wof:name":"Delta Carpet Care",
    "wof:placetype":"venue"
},
  "geometry": {"coordinates":[-83.99738600000001,41.576764],"type":"Point"}
}