{
  "type": "Feature",
  "properties": {
    "addr:full": "1822 W 25th St Cleveland OH 44113",
    "addr:housenumber": "1822",
    "addr:postcode": "44113",
    "addr:street": "W 25Th St",
    "iso:country": "US",
    "sg:address": "1822 W 25th St",
    "sg:city": "Cleveland",
    "sg:classifiers": [
      {
        "category": "Food \u0026 Beverages",
        "subcategory": "Groceries \u0026 Convenience Stores",
        "type": "Retail Goods"
      }
    ],
    "sg:phone": "+1 216 241 1449",
    "sg:postcode": "44113",
    "sg:province": "OH",
    "wof:name": "Gateway Food Market",
    "wof:placetype": "venue"
  },
  "geometry": {"coordinates":[-81.705084,41.48625],"type":"Point"}
}
