{
  "type": "Feature",
  "properties": {
    "iso:country":"US",
    "sg:address":"11223 Granger Rd",
    "sg:city":"Cleveland",
    "sg:classifiers":[
        {
            "category":"Shopping",
            "subcategory":"Pharmacy",
            "type":"Retail Goods"
        }
    ],
    "sg:phone":"+1 216 332 7801",
    "sg:postcode":"44125",
    "sg:province":"OH",
    "wof:name":"CVS Pharmacy",
    "wof:placetype":"venue"
},
  "geometry": {"coordinates":[-81.60349600000001,41.417141],"type":"Point"}
}