{
  "type": "Feature",
  "properties": {
    "iso:country":"US",
    "sg:address":"6788 Whipple Ave NW",
    "sg:city":"North Canton",
    "sg:classifiers":[
        {
            "category":"Autos & Motor Vehicles",
            "subcategory":"Automobile Sales",
            "type":"Retail Goods"
        }
    ],
    "sg:phone":"+1 330 499 8555",
    "sg:postcode":"44720",
    "sg:province":"OH",
    "sg:tags":[
        "car",
        "dealer"
    ],
    "sg:website":"www.northwestautosales.com",
    "wof:name":"Northwest Auto Sales Inc",
    "wof:placetype":"venue"
},
  "geometry": {"coordinates":[-81.423776,40.881421],"type":"Point"}
}