{
  "type": "Feature",
  "properties": {
    "iso:country":"US",
    "sg:address":"817 E Bowman St",
    "sg:city":"Wooster",
    "sg:classifiers":[
        {
            "category":"Food & Beverages",
            "subcategory":"Meat & Fish",
            "type":"Retail Goods"
        }
    ],
    "sg:phone":"+1 330 262 9871",
    "sg:postcode":"44691",
    "sg:province":"OH",
    "sg:tags":[
        "grocery"
    ],
    "wof:name":"Bobs Quality Meats",
    "wof:placetype":"venue"
},
  "geometry": {"coordinates":[-81.928763,40.804776],"type":"Point"}
}