{
  "type": "Feature",
  "properties": {
    "addr:full": "817 E Bowman St Wooster OH 44691",
    "addr:housenumber": "817",
    "addr:postcode": "44691",
    "addr:street": "E Bowman St",
    "iso:country": "US",
    "sg:address": "817 E Bowman St",
    "sg:city": "Wooster",
    "sg:classifiers": [
      {
        "category": "Food \u0026 Beverages",
        "subcategory": "Meat \u0026 Fish",
        "type": "Retail Goods"
      }
    ],
    "sg:phone": "+1 330 262 9871",
    "sg:postcode": "44691",
    "sg:province": "OH",
    "sg:tags": [
      "grocery"
    ],
    "wof:name": "Bobs Quality Meats",
    "wof:placetype": "venue"
  },
  "geometry": {"coordinates":[-81.928763,40.804776],"type":"Point"}
}
