{
  "type": "Feature",
  "properties": {
    "addr:full": "2030 Fairgrove Ave Hamilton OH 45011",
    "addr:housenumber": "2030",
    "addr:postcode": "45011",
    "addr:street": "Fairgrove Ave",
    "iso:country": "US",
    "sg:address": "2030 Fairgrove Ave",
    "sg:city": "Hamilton",
    "sg:classifiers": [
      {
        "category": "Restaurant",
        "type": "Food \u0026 Drink"
      }
    ],
    "sg:phone": "+1 513 893 0991",
    "sg:postcode": "45011",
    "sg:province": "OH",
    "wof:name": "Hyde's Drive-In",
    "wof:placetype": "venue"
  },
  "geometry": {"coordinates":[-84.533476,39.403348],"type":"Point"}
}
