{
  "type": "Feature",
  "properties": {
    "iso:country":"US",
    "sg:address":"2815 State Rte 100",
    "sg:city":"Tiffin",
    "sg:classifiers":[
        {
            "category":"Health Services",
            "subcategory":"Doctor",
            "type":"Services"
        }
    ],
    "sg:phone":"+1 419 448 9728",
    "sg:postcode":"44883",
    "sg:province":"OH",
    "sg:tags":[
        "physician",
        "surgeon"
    ],
    "wof:name":"Michael Scherer DO",
    "wof:placetype":"venue"
},
  "geometry": {"coordinates":[-83.155455,41.083536],"type":"Point"}
}