{
  "type": "Feature",
  "properties": {
    "iso:country":"US",
    "sg:address":"200 E Wapakoneta St",
    "sg:city":"Waynesfield",
    "sg:classifiers":[
        {
            "category":"Social Services",
            "type":"Services"
        }
    ],
    "sg:phone":"+1 419 568 2030",
    "sg:postcode":"45896",
    "sg:province":"OH",
    "sg:tags":[
        "agency",
        "adoption"
    ],
    "wof:name":"New Visions Creative Care",
    "wof:placetype":"venue"
},
  "geometry": {"coordinates":[-83.973485,40.600601],"type":"Point"}
}