{
  "type": "Feature",
  "properties": {
    "addr:full": "3900 Wildlife Way Cleveland OH 44109",
    "addr:housenumber": "3900",
    "addr:postcode": "44109",
    "addr:street": "Wildlife Way",
    "iso:country": "US",
    "sg:address": "3900 Wildlife Way",
    "sg:city": "Cleveland",
    "sg:classifiers": [
      {
        "category": "Restaurant",
        "type": "Food \u0026 Drink"
      }
    ],
    "sg:phone": "+1 216 398 5318",
    "sg:postcode": "44109",
    "sg:province": "OH",
    "sg:tags": [
      "caterer"
    ],
    "wof:name": "Ogden Services",
    "wof:placetype": "venue"
  },
  "geometry": {"coordinates":[-81.708064,41.445587],"type":"Point"}
}
