{
  "type": "Feature",
  "properties": {
    "iso:country":"US",
    "sg:address":"99 Maple Ave",
    "sg:city":"Dayton",
    "sg:classifiers":[
        {
            "category":"Government",
            "subcategory":"Post Office",
            "type":"Public Place"
        }
    ],
    "sg:phone":"+1 937 000 1111",
    "sg:postcode":"45459",
    "sg:province":"OH",
    "wof:name":"US Post Office",
    "wof:placetype":"venue"
},
  "geometry": {"coordinates":[-84.15611699999999,39.632352],"type":"Point"}
}