{
  "type": "Feature",
  "properties": {
    "addr:full": "99 Maple Ave Dayton OH 45459",
    "addr:housenumber": "99",
    "addr:postcode": "45459",
    "addr:street": "Maple Ave",
    "iso:country": "US",
    "sg:address": "99 Maple Ave",
    "sg:city": "Dayton",
    "sg:classifiers": [
      {
        "category": "Government",
        "subcategory": "Post Office",
        "type": "Public Place"
      }
    ],
    "sg:phone": "+1 937 000 1111",
    "sg:postcode": "45459",
    "sg:province": "OH",
    "wof:name": "US Post Office",
    "wof:placetype": "venue"
  },
  "geometry": {"coordinates":[-84.156117,39.632352],"type":"Point"}
}
