{
  "type": "Feature",
  "properties": {
    "addr:full": "4282 Boudinot Ave Cincinnati OH 45211",
    "addr:housenumber": "4282",
    "addr:postcode": "45211",
    "addr:street": "Boudinot Ave",
    "iso:country": "US",
    "sg:address": "4282 Boudinot Ave",
    "sg:city": "Cincinnati",
    "sg:classifiers": [
      {
        "category": "Building \u0026 Trades",
        "subcategory": "Construction",
        "type": "Services"
      }
    ],
    "sg:phone": "+1 513 661 4031",
    "sg:postcode": "45211",
    "sg:province": "OH",
    "sg:tags": [
      "tank",
      "removal"
    ],
    "wof:name": "Alpha-Ram Inc",
    "wof:placetype": "venue"
  },
  "geometry": {"coordinates":[-84.601637,39.165886],"type":"Point"}
}
