{
  "type": "Feature",
  "properties": {
    "addr:full":"119 W Maple Ave Van Wert OH 45891",
    "addr:housenumber":"119",
    "addr:postcode":"45891",
    "addr:street":"W Maple Ave",
    "iso:country":"US",
    "sg:address":"119 W Maple Ave",
    "sg:city":"Van Wert",
    "sg:classifiers":[
        {
            "category":"Organizations",
            "subcategory":"Religious Organization",
            "type":"Services"
        }
    ],
    "sg:phone":"+1 419 238 1690",
    "sg:postcode":"45891",
    "sg:province":"OH",
    "sg:tags":[
        "church"
    ],
    "wof:name":"Calvary United Methodist",
    "wof:placetype":"venue"
},
  "geometry": {"coordinates":[-84.58395899999999,40.866672],"type":"Point"}
}