{
  "type": "Feature",
  "properties": {
    "addr:full": "1192 County Line Rd Westerville OH 43081",
    "addr:housenumber": "1192",
    "addr:postcode": "43081",
    "addr:street": "County Line Rd",
    "iso:country": "US",
    "sg:address": "1192 County Line Rd",
    "sg:city": "Westerville",
    "sg:classifiers": [
      {
        "category": "Personal",
        "subcategory": "Beauty Salon",
        "type": "Services"
      }
    ],
    "sg:phone": "+1 614 891 7714",
    "sg:postcode": "43081",
    "sg:province": "OH",
    "sg:tags": [
      "manicuring"
    ],
    "wof:name": "Angel Nails",
    "wof:placetype": "venue"
  },
  "geometry": {"coordinates":[-82.990154,40.135655],"type":"Point"}
}
