{
  "type": "Feature",
  "properties": {
    "iso:country":"US",
    "sg:address":"4212 Airport Rd",
    "sg:city":"Cincinnati",
    "sg:classifiers":[
        {
            "category":"Real Estate",
            "subcategory":"Real Estate Operator",
            "type":"Services"
        }
    ],
    "sg:phone":"+1 513 871 5881",
    "sg:postcode":"45226",
    "sg:province":"OH",
    "sg:tags":[
        "building",
        "parks"
    ],
    "wof:name":"Lunken Executive Bldg",
    "wof:placetype":"venue"
},
  "geometry": {"coordinates":[-84.430833,39.106671],"type":"Point"}
}