{
  "type": "Feature",
  "properties": {
    "addr:full":"773 S Andover Rd Mansfield OH 44907",
    "addr:housenumber":"773",
    "addr:postcode":"44907",
    "addr:street":"S Andover Rd",
    "iso:country":"US",
    "sg:address":"773 S Andover Rd",
    "sg:city":"Mansfield",
    "sg:classifiers":[
        {
            "category":"Organizations",
            "subcategory":"Religious Organization",
            "type":"Services"
        }
    ],
    "sg:phone":"+1 419 774 0551",
    "sg:postcode":"44907",
    "sg:province":"OH",
    "sg:tags":[
        "clergy"
    ],
    "wof:name":"Faith Proietti",
    "wof:placetype":"venue"
},
  "geometry": {"coordinates":[-82.534229,40.736553],"type":"Point"}
}