{
  "type": "Feature",
  "properties": {
    "addr:full":"250 E 5th St Cincinnati OH 45202",
    "addr:housenumber":"250",
    "addr:postcode":"45202",
    "addr:street":"E 5Th St",
    "iso:country":"US",
    "sg:address":"250 E 5th St",
    "sg:city":"Cincinnati",
    "sg:classifiers":[
        {
            "category":"Manufacturing",
            "subcategory":"Retail Goods",
            "type":"Manufacturing & Wholesale Goods"
        }
    ],
    "sg:phone":"+1 513 762 7680",
    "sg:postcode":"45202",
    "sg:province":"OH",
    "sg:tags":[
        "assembly",
        "fabricating"
    ],
    "wof:name":"Cutter Fabricators Inc",
    "wof:placetype":"venue"
},
  "geometry": {"coordinates":[-84.508324,39.101923],"type":"Point"}
}