{
  "type": "Feature",
  "properties": {
    "addr:full":"1728 Cleveland Ave NW Canton OH 44703",
    "addr:housenumber":"1728",
    "addr:postcode":"44703",
    "addr:street":"Cleveland Ave Nw",
    "iso:country":"US",
    "sg:address":"1728 Cleveland Ave NW",
    "sg:city":"Canton",
    "sg:classifiers":[
        {
            "category":"Food & Beverages",
            "subcategory":"Liquor & Beverages",
            "type":"Retail Goods"
        }
    ],
    "sg:phone":"+1 330 454 8108",
    "sg:postcode":"44703",
    "sg:province":"OH",
    "sg:tags":[
        "wine"
    ],
    "wof:name":"Avenue Wine Shop",
    "wof:placetype":"venue"
},
  "geometry": {"coordinates":[-81.380458,40.817697],"type":"Point"}
}