{
  "type": "Feature",
  "properties": {
    "iso:country":"US",
    "sg:address":"5040 Pine Creek Dr",
    "sg:city":"Westerville",
    "sg:classifiers":[
        {
            "category":"Professional",
            "subcategory":"Accounting & Tax Preparation",
            "type":"Services"
        }
    ],
    "sg:phone":"+1 614 882 9111",
    "sg:postcode":"43081",
    "sg:province":"OH",
    "sg:tags":[
        "accountant"
    ],
    "wof:name":"Zimmerman Boltz & Company",
    "wof:placetype":"venue"
},
  "geometry": {"coordinates":[-82.879676,40.07892],"type":"Point"}
}