{
  "type": "Feature",
  "properties": {
    "addr:full": "5040 Pine Creek Dr Westerville OH 43081",
    "addr:housenumber": "5040",
    "addr:postcode": "43081",
    "addr:street": "Pine Creek Dr",
    "iso:country": "US",
    "sg:address": "5040 Pine Creek Dr",
    "sg:city": "Westerville",
    "sg:classifiers": [
      {
        "category": "Professional",
        "subcategory": "Accounting \u0026 Tax Preparation",
        "type": "Services"
      }
    ],
    "sg:phone": "+1 614 882 9111",
    "sg:postcode": "43081",
    "sg:province": "OH",
    "sg:tags": [
      "accountant"
    ],
    "wof:name": "Zimmerman Boltz \u0026 Company",
    "wof:placetype": "venue"
  },
  "geometry": {"coordinates":[-82.879676,40.07892],"type":"Point"}
}
