{
  "type": "Feature",
  "properties": {
    "addr:full": "9298 State Rte 314 Mansfield OH 44904",
    "addr:housenumber": "9298",
    "addr:postcode": "44904",
    "addr:street": "State Rte 314",
    "iso:country": "US",
    "sg:address": "9298 State Rte 314",
    "sg:city": "Mansfield",
    "sg:classifiers": [
      {
        "category": "Farming",
        "subcategory": "Livestock Farm",
        "type": "Manufacturing \u0026 Wholesale Goods"
      }
    ],
    "sg:phone": "+1 419 884 3107",
    "sg:postcode": "44904",
    "sg:province": "OH",
    "sg:tags": [
      "feedlot",
      "corn",
      "soybean",
      "beef",
      "cattle"
    ],
    "wof:name": "Harold Caudill",
    "wof:placetype": "venue"
  },
  "geometry": {"coordinates":[-82.664739,40.687211],"type":"Point"}
}
