{
  "type": "Feature",
  "properties": {
    "iso:country":"US",
    "sg:address":"600 E 11th Ave",
    "sg:city":"Columbus",
    "sg:classifiers":[
        {
            "category":"Community Center",
            "type":"Public Place"
        },
        {
            "category":"Government",
            "subcategory":"Office",
            "type":"Public Place"
        }
    ],
    "sg:phone":"+1 614 645 5954",
    "sg:postcode":"43211",
    "sg:province":"OH",
    "sg:tags":[
        "recreation",
        "government-city",
        "township",
        "village"
    ],
    "sg:website":"http://www.columbuscitycouncil.com",
    "wof:name":"City Of Columbus",
    "wof:placetype":"venue"
},
  "geometry": {"coordinates":[-82.99144699999999,39.99411],"type":"Point"}
}