{
  "type": "Feature",
  "properties": {
    "addr:full": "1652 Columbiana Lisbon Rd Columbiana OH 44408",
    "addr:housenumber": "1652",
    "addr:postcode": "44408",
    "addr:street": "Lisbon Rd",
    "iso:country": "US",
    "sg:address": "1652 Columbiana Lisbon Rd",
    "sg:city": "Columbiana",
    "sg:classifiers": [
      {
        "category": "Manufacturing",
        "subcategory": "Metals",
        "type": "Manufacturing \u0026 Wholesale Goods"
      }
    ],
    "sg:phone": "+1 330 482 2636",
    "sg:postcode": "44408",
    "sg:province": "OH",
    "sg:tags": [
      "forging"
    ],
    "wof:name": "J \u0026 H Mfg Co",
    "wof:placetype": "venue"
  },
  "geometry": {"coordinates":[-80.715368,40.875771],"type":"Point"}
}
