{
  "type": "Feature",
  "properties": {
    "iso:country":"US",
    "sg:address":"601 W Wenger Rd",
    "sg:city":"Englewood",
    "sg:classifiers":[
        {
            "category":"Organizations",
            "subcategory":"Religious Organization",
            "type":"Services"
        }
    ],
    "sg:phone":"+1 937 836 4458",
    "sg:postcode":"45322",
    "sg:province":"OH",
    "sg:tags":[
        "clergy"
    ],
    "wof:name":"Daniel Crabtree",
    "wof:placetype":"venue"
},
  "geometry": {"coordinates":[-84.306249,39.862066],"type":"Point"}
}