{
  "type": "Feature",
  "properties": {
    "addr:full": "3407 Beekman St Cincinnati OH 45223",
    "addr:housenumber": "3407",
    "addr:postcode": "45223",
    "addr:street": "Beekman St",
    "iso:country": "US",
    "sg:address": "3407 Beekman St",
    "sg:city": "Cincinnati",
    "sg:classifiers": [
      {
        "category": "Retail",
        "subcategory": "Repair Shop",
        "type": "Services"
      }
    ],
    "sg:phone": "+1 513 541 6333",
    "sg:postcode": "45223",
    "sg:province": "OH",
    "sg:tags": [
      "television",
      "radio"
    ],
    "wof:name": "ABC TV \u0026 Stereo",
    "wof:placetype": "venue"
  },
  "geometry": {"coordinates":[-84.551234,39.14908],"type":"Point"}
}
