{
  "type": "Feature",
  "properties": {
    "iso:country":"US",
    "sg:address":"3407 Beekman St",
    "sg:city":"Cincinnati",
    "sg:classifiers":[
        {
            "category":"Retail",
            "subcategory":"Repair Shop",
            "type":"Services"
        }
    ],
    "sg:phone":"+1 513 541 6333",
    "sg:postcode":"45223",
    "sg:province":"OH",
    "sg:tags":[
        "television",
        "radio"
    ],
    "wof:name":"ABC TV & Stereo",
    "wof:placetype":"venue"
},
  "geometry": {"coordinates":[-84.55123399999999,39.14908],"type":"Point"}
}