{
  "type": "Feature",
  "properties": {
    "iso:country":"US",
    "sg:address":"1058 Clark St",
    "sg:city":"Holland",
    "sg:classifiers":[
        {
            "category":"Health Services",
            "subcategory":"Health Practitioner",
            "type":"Services"
        }
    ],
    "sg:phone":"+1 419 868 7378",
    "sg:postcode":"43528",
    "sg:province":"OH",
    "sg:tags":[
        "therapist",
        "physical"
    ],
    "wof:name":"Restorative Concepts",
    "wof:placetype":"venue"
},
  "geometry": {"coordinates":[-83.713252,41.622518],"type":"Point"}
}