{
  "type": "Feature",
  "properties": {
    "iso:country":"US",
    "sg:address":"4569 State Rte 41 SE",
    "sg:city":"Washington Ct Hs",
    "sg:classifiers":[
        {
            "category":"Home & Garden",
            "subcategory":"Building Materials",
            "type":"Retail Goods"
        }
    ],
    "sg:phone":"+1 740 636 8276",
    "sg:postcode":"43160",
    "sg:province":"OH",
    "sg:tags":[
        "windows",
        "install",
        "patio"
    ],
    "wof:name":"Window and Patio Impressions",
    "wof:placetype":"venue"
},
  "geometry": {"coordinates":[-83.434663,39.466939],"type":"Point"}
}