{
  "type": "Feature",
  "properties": {
    "iso:country":"US",
    "sg:address":"11000 Cedar Ave",
    "sg:city":"Cleveland",
    "sg:classifiers":[
        {
            "category":"Organizations",
            "subcategory":"Non-profit Organization",
            "type":"Services"
        }
    ],
    "sg:phone":"+1 216 229 9445",
    "sg:postcode":"44106",
    "sg:province":"OH",
    "sg:website":"www.edinc.org",
    "wof:name":"Enterprise Development Inc",
    "wof:placetype":"venue"
},
  "geometry": {"coordinates":[-81.60672,41.499904],"type":"Point"}
}