{
  "type": "Feature",
  "properties": {
    "addr:full": "11000 Cedar Ave Cleveland OH 44106",
    "addr:housenumber": "11000",
    "addr:postcode": "44106",
    "addr:street": "Cedar Ave",
    "iso:country": "US",
    "sg:address": "11000 Cedar Ave",
    "sg:city": "Cleveland",
    "sg:classifiers": [
      {
        "category": "Organizations",
        "subcategory": "Non-profit Organization",
        "type": "Services"
      }
    ],
    "sg:phone": "+1 216 229 9445",
    "sg:postcode": "44106",
    "sg:province": "OH",
    "sg:website": "www.edinc.org",
    "wof:name": "Enterprise Development Inc",
    "wof:placetype": "venue"
  },
  "geometry": {"coordinates":[-81.60672,41.499904],"type":"Point"}
}
