{
  "type": "Feature",
  "properties": {
    "iso:country":"US",
    "sg:address":"1311 W Main St",
    "sg:city":"Springfield",
    "sg:classifiers":[
        {
            "category":"Museum",
            "type":"Entertainment"
        }
    ],
    "sg:phone":"+1 937 322 7668",
    "sg:postcode":"45504",
    "sg:province":"OH",
    "wof:name":"Pennsylvania House",
    "wof:placetype":"venue"
},
  "geometry": {"coordinates":[-83.833692,39.925809],"type":"Point"}
}