{
  "type": "Feature",
  "properties": {
    "iso:country":"US",
    "sg:address":"3996 Fulton Dr NW",
    "sg:city":"Canton",
    "sg:classifiers":[
        {
            "category":"Personal",
            "subcategory":"Beauty Salon",
            "type":"Services"
        }
    ],
    "sg:phone":"+1 330 492 2600",
    "sg:postcode":"44718",
    "sg:province":"OH",
    "wof:name":"Allevare Hair Clinic",
    "wof:placetype":"venue"
},
  "geometry": {"coordinates":[-81.42138,40.835445],"type":"Point"}
}