{
  "type": "Feature",
  "properties": {
    "addr:full":"4157 Crossgate Ln Cincinnati OH 45236",
    "addr:housenumber":"4157",
    "addr:postcode":"45236",
    "addr:street":"Crossgate Ln",
    "iso:country":"US",
    "sg:address":"4157 Crossgate Ln",
    "sg:city":"Cincinnati",
    "sg:classifiers":[
        {
            "category":"Manufacturing",
            "subcategory":"Printing",
            "type":"Manufacturing & Wholesale Goods"
        }
    ],
    "sg:phone":"+1 513 891 0415",
    "sg:postcode":"45236",
    "sg:province":"OH",
    "sg:tags":[
        "publisher"
    ],
    "wof:name":"Four Winds ATOC",
    "wof:placetype":"venue"
},
  "geometry": {"coordinates":[-84.394047,39.224121],"type":"Point"}
}