{
  "type": "Feature",
  "properties": {
    "iso:country":"US",
    "sg:address":"56 Diamond Ave",
    "sg:city":"Barberton",
    "sg:classifiers":[
        {
            "category":"Building & Trades",
            "subcategory":"Construction",
            "type":"Services"
        }
    ],
    "sg:phone":"+1 330 848 2058",
    "sg:postcode":"44203",
    "sg:province":"OH",
    "sg:tags":[
        "contractor"
    ],
    "wof:name":"Terry Starcher",
    "wof:placetype":"venue"
},
  "geometry": {"coordinates":[-81.60944600000001,41.00673],"type":"Point"}
}