{
  "type": "Feature",
  "properties": {
    "addr:full": "6385 Oak Creek Dr Cincinnati OH 45247",
    "addr:housenumber": "6385",
    "addr:postcode": "45247",
    "addr:street": "Oak Creek Dr",
    "iso:country": "US",
    "sg:address": "6385 Oak Creek Dr",
    "sg:city": "Cincinnati",
    "sg:classifiers": [
      {
        "category": "Professional",
        "type": "Services"
      }
    ],
    "sg:phone": "+1 513 741 1603",
    "sg:postcode": "45247",
    "sg:province": "OH",
    "wof:name": "Ljubomir Vujic",
    "wof:placetype": "venue"
  },
  "geometry": {"coordinates":[-84.60866,39.209755],"type":"Point"}
}
