{
  "type": "Feature",
  "properties": {
    "iso:country":"US",
    "sg:address":"5532 Williams Center Cecil Rd",
    "sg:city":"Sherwood",
    "sg:phone":"+1 419 658 2141",
    "sg:postcode":"43556",
    "sg:province":"OH",
    "sg:tags":[
        "farm",
        "corn",
        "wheat",
        "soybean"
    ],
    "wof:name":"Allan Lucas",
    "wof:placetype":"venue"
},
  "geometry": {"coordinates":[-84.61161300000001,41.363439],"type":"Point"}
}