{
  "type": "Feature",
  "properties": {
    "addr:full": "1919 Ottawa Ln Perrysburg OH 43551",
    "addr:housenumber": "1919",
    "addr:postcode": "43551",
    "addr:street": "Ottawa Ln",
    "iso:country": "US",
    "sg:address": "1919 Ottawa Ln",
    "sg:city": "Perrysburg",
    "sg:classifiers": [
      {
        "category": "Professional",
        "type": "Services"
      }
    ],
    "sg:phone": "+1 419 874 9505",
    "sg:postcode": "43551",
    "sg:province": "OH",
    "sg:tags": [
      "establishment"
    ],
    "wof:name": "Eagle Canyon Productions Inc",
    "wof:placetype": "venue"
  },
  "geometry": {"coordinates":[-83.668922,41.540963],"type":"Point"}
}
