{
  "type": "Feature",
  "properties": {
    "iso:country":"US",
    "sg:address":"3229 Hilliard Rome Rd",
    "sg:city":"Hilliard",
    "sg:classifiers":[
        {
            "category":"Real Estate",
            "subcategory":"Real Estate Agent",
            "type":"Services"
        }
    ],
    "sg:phone":"+1 614 850 4700",
    "sg:postcode":"43026",
    "sg:province":"OH",
    "wof:name":"Help U Sell",
    "wof:placetype":"venue"
},
  "geometry": {"coordinates":[-83.1562,40.016727],"type":"Point"}
}