{
  "type": "Feature",
  "properties": {
    "iso:country":"US",
    "sg:address":"869 Eastern Ave",
    "sg:city":"Woodsfield",
    "sg:classifiers":[
        {
            "category":"Retail",
            "subcategory":"Auto Rental",
            "type":"Services"
        }
    ],
    "sg:phone":"+1 740 472 1185",
    "sg:postcode":"43793",
    "sg:province":"OH",
    "sg:tags":[
        "automobile",
        "leasing"
    ],
    "wof:name":"Monroe Auto Rental & Sales",
    "wof:placetype":"venue"
},
  "geometry": {"coordinates":[-81.096448,39.759378],"type":"Point"}
}