{
  "type": "Feature",
  "properties": {
    "addr:full": "122 S Erie Hwy Hamilton OH 45011",
    "addr:housenumber": "122",
    "addr:postcode": "45011",
    "addr:street": "S Erie Hwy",
    "iso:country": "US",
    "sg:address": "122 S Erie Hwy",
    "sg:city": "Hamilton",
    "sg:classifiers": [
      {
        "category": "Autos \u0026 Motor Vehicles",
        "subcategory": "Automobile Sales",
        "type": "Retail Goods"
      }
    ],
    "sg:phone": "+1 513 868 1121",
    "sg:postcode": "45011",
    "sg:province": "OH",
    "sg:tags": [
      "car",
      "dealer"
    ],
    "wof:name": "Stevens Auto Tops",
    "wof:placetype": "venue"
  },
  "geometry": {"coordinates":[-84.547521,39.390741],"type":"Point"}
}
