{
  "type": "Feature",
  "properties": {
    "addr:full": "7637 Kittery Ln Mentor OH 44060",
    "addr:housenumber": "7637",
    "addr:postcode": "44060",
    "addr:street": "Kittery Ln",
    "iso:country": "US",
    "sg:address": "7637 Kittery Ln",
    "sg:city": "Mentor",
    "sg:classifiers": [
      {
        "category": "Professional",
        "subcategory": "Business Services",
        "type": "Services"
      }
    ],
    "sg:phone": "+1 440 333 8258",
    "sg:postcode": "44060",
    "sg:province": "OH",
    "sg:tags": [
      "appraiser"
    ],
    "sg:website": "www.whitenaglemazza.com",
    "wof:name": "White Nagle \u0026 Mazza",
    "wof:placetype": "venue"
  },
  "geometry": {"coordinates":[-81.383049,41.664359],"type":"Point"}
}
