{
  "type": "Feature",
  "properties": {
    "addr:full": "915 Cornell Ave Youngstown OH 44502",
    "addr:housenumber": "915",
    "addr:postcode": "44502",
    "addr:street": "Cornell Ave",
    "iso:country": "US",
    "sg:address": "915 Cornell Ave",
    "sg:city": "Youngstown",
    "sg:classifiers": [
      {
        "category": "Organizations",
        "subcategory": "Religious Organization",
        "type": "Services"
      }
    ],
    "sg:phone": "+1 330 788 5082",
    "sg:postcode": "44502",
    "sg:province": "OH",
    "sg:tags": [
      "church"
    ],
    "wof:name": "St Matthias Church",
    "wof:placetype": "venue"
  },
  "geometry": {"coordinates":[-80.634474,41.072081],"type":"Point"}
}
