{
  "type": "Feature",
  "properties": {
    "addr:full":"1834 W Sylvania Ave Toledo OH 43613",
    "addr:housenumber":"1834",
    "addr:postcode":"43613",
    "addr:street":"W Sylvania Ave",
    "iso:country":"US",
    "sg:address":"1834 W Sylvania Ave",
    "sg:city":"Toledo",
    "sg:classifiers":[
        {
            "category":"Shopping",
            "subcategory":"Used Merchandise",
            "type":"Retail Goods"
        }
    ],
    "sg:phone":"+1 419 691 4240",
    "sg:postcode":"43613",
    "sg:province":"OH",
    "sg:tags":[
        "shop",
        "consignment"
    ],
    "wof:name":"Kids Korner",
    "wof:placetype":"venue"
},
  "geometry": {"coordinates":[-83.589439,41.692358],"type":"Point"}
}