{
  "type": "Feature",
  "properties": {
    "iso:country":"US",
    "sg:address":"143 E Wooster St",
    "sg:city":"Bowling Green",
    "sg:classifiers":[
        {
            "category":"Food & Beverages",
            "subcategory":"Groceries & Convenience Stores",
            "type":"Retail Goods"
        }
    ],
    "sg:phone":"+1 419 352 7603",
    "sg:postcode":"43402",
    "sg:province":"OH",
    "wof:name":"B Js Food Emporium",
    "wof:placetype":"venue"
},
  "geometry": {"coordinates":[-83.64987499999999,41.374958],"type":"Point"}
}