{
  "type": "Feature",
  "properties": {
    "addr:full": "143 E Wooster St Bowling Green OH 43402",
    "addr:housenumber": "143",
    "addr:postcode": "43402",
    "addr:street": "E Wooster St",
    "iso:country": "US",
    "sg:address": "143 E Wooster St",
    "sg:city": "Bowling Green",
    "sg:classifiers": [
      {
        "category": "Food \u0026 Beverages",
        "subcategory": "Groceries \u0026 Convenience Stores",
        "type": "Retail Goods"
      }
    ],
    "sg:phone": "+1 419 352 7603",
    "sg:postcode": "43402",
    "sg:province": "OH",
    "wof:name": "B Js Food Emporium",
    "wof:placetype": "venue"
  },
  "geometry": {"coordinates":[-83.649875,41.374958],"type":"Point"}
}
