{
  "type": "Feature",
  "properties": {
    "addr:full":"4736 Socialville Foster Rd Mason OH 45040",
    "addr:postcode":"4736;45040",
    "addr:street":"Socialville Foster Rd",
    "iso:country":"US",
    "sg:address":"4736 Socialville Foster Rd",
    "sg:city":"Mason",
    "sg:classifiers":[
        {
            "category":"Manufacturing",
            "subcategory":"Tools & Machinery",
            "type":"Manufacturing & Wholesale Goods"
        }
    ],
    "sg:phone":"+1 513 229 7000",
    "sg:postcode":"45040",
    "sg:province":"OH",
    "sg:tags":[
        "physician",
        "surgeon"
    ],
    "wof:name":"Teledyne TEKMAR",
    "wof:placetype":"venue"
},
  "geometry": {"coordinates":[-84.31181100000001,39.322709],"type":"Point"}
}