{
  "type": "Feature",
  "properties": {
    "iso:country":"US",
    "sg:address":"6961 Shimp Rd",
    "sg:city":"Germantown",
    "sg:phone":"+1 937 855 3161",
    "sg:postcode":"45327",
    "sg:province":"OH",
    "sg:tags":[
        "farm",
        "wheat",
        "corn",
        "grain",
        "cash"
    ],
    "wof:name":"Kenneth Lake Farm",
    "wof:placetype":"venue"
},
  "geometry": {"coordinates":[-84.435982,39.643712],"type":"Point"}
}