{
  "type": "Feature",
  "properties": {
    "iso:country":"US",
    "sg:address":"520 S Main St",
    "sg:city":"Akron",
    "sg:classifiers":[
        {
            "category":"Professional",
            "subcategory":"Engineering",
            "type":"Services"
        }
    ],
    "sg:phone":"+1 330 374 9058",
    "sg:postcode":"44311",
    "sg:province":"OH",
    "wof:name":"Hatch Mott Macdonald I & E LLC",
    "wof:placetype":"venue"
},
  "geometry": {"coordinates":[-81.52443100000001,41.073244],"type":"Point"}
}