{
  "type": "Feature",
  "properties": {
    "iso:country":"US",
    "sg:address":"25875 Science Park Dr",
    "sg:city":"Cleveland",
    "sg:classifiers":[
        {
            "category":"Restaurant",
            "type":"Food & Drink"
        }
    ],
    "sg:phone":"+1 216 545 0968",
    "sg:postcode":"44122",
    "sg:province":"OH",
    "wof:name":"Wood Company",
    "wof:placetype":"venue"
},
  "geometry": {"coordinates":[-81.491519,41.473378],"type":"Point"}
}