{
  "type": "Feature",
  "properties": {
    "addr:full": "25875 Science Park Dr Cleveland OH 44122",
    "addr:housenumber": "25875",
    "addr:postcode": "44122",
    "addr:street": "Science Park Dr",
    "iso:country": "US",
    "sg:address": "25875 Science Park Dr",
    "sg:city": "Cleveland",
    "sg:classifiers": [
      {
        "category": "Restaurant",
        "type": "Food \u0026 Drink"
      }
    ],
    "sg:phone": "+1 216 545 0968",
    "sg:postcode": "44122",
    "sg:province": "OH",
    "wof:name": "Wood Company",
    "wof:placetype": "venue"
  },
  "geometry": {"coordinates":[-81.491519,41.473378],"type":"Point"}
}
