{
  "type": "Feature",
  "properties": {
    "iso:country":"US",
    "sg:address":"5080 W Alexis Rd",
    "sg:city":"Sylvania",
    "sg:classifiers":[
        {
            "category":"Autos & Motor Vehicles",
            "subcategory":"Recreational Vehicle Sales",
            "type":"Retail Goods"
        }
    ],
    "sg:phone":"+1 419 885 4601",
    "sg:postcode":"43560",
    "sg:province":"OH",
    "sg:tags":[
        "home"
    ],
    "sg:website":"www.aacoach.com",
    "wof:name":"All American Coach Company",
    "wof:placetype":"venue"
},
  "geometry": {"coordinates":[-83.664456,41.718158],"type":"Point"}
}