{
  "type": "Feature",
  "properties": {
    "addr:full":"1119 W Washington St Sandusky OH 44870",
    "addr:housenumber":"1119",
    "addr:postcode":"44870",
    "addr:street":"W Washington St",
    "iso:country":"US",
    "sg:address":"1119 W Washington St",
    "sg:city":"Sandusky",
    "sg:classifiers":[
        {
            "category":"Bars & Pubs",
            "type":"Food & Drink"
        }
    ],
    "sg:phone":"+1 419 621 1184",
    "sg:postcode":"44870",
    "sg:province":"OH",
    "wof:name":"Cronin's Tavern",
    "wof:placetype":"venue"
},
  "geometry": {"coordinates":[-82.719705,41.452093],"type":"Point"}
}