{
  "type": "Feature",
  "properties": {
    "addr:full": "1546 Georgetown Rd Hudson OH 44236",
    "addr:housenumber": "1546",
    "addr:postcode": "44236",
    "addr:street": "Georgetown Rd",
    "iso:country": "US",
    "sg:address": "1546 Georgetown Rd",
    "sg:city": "Hudson",
    "sg:classifiers": [
      {
        "category": "Retail",
        "subcategory": "Laundry \u0026 Dry Cleaning",
        "type": "Services"
      }
    ],
    "sg:phone": "+1 330 650 4486",
    "sg:postcode": "44236",
    "sg:province": "OH",
    "wof:name": "Servpro",
    "wof:placetype": "venue"
  },
  "geometry": {"coordinates":[-81.425144,41.207876],"type":"Point"}
}
