{
  "type": "Feature",
  "properties": {
    "addr:full": "7731 Jordan Xing Reynoldsburg OH 43068",
    "addr:housenumber": "7731",
    "addr:postcode": "43068",
    "addr:street": "Jordan Xing",
    "iso:country": "US",
    "sg:address": "7731 Jordan Xing",
    "sg:city": "Reynoldsburg",
    "sg:classifiers": [
      {
        "category": "Professional",
        "type": "Services"
      }
    ],
    "sg:phone": "+1 614 501 3204",
    "sg:postcode": "43068",
    "sg:province": "OH",
    "wof:name": "Educare Solutions \u0026 Svc",
    "wof:placetype": "venue"
  },
  "geometry": {"coordinates":[-82.791031,39.964693],"type":"Point"}
}
