{
  "type": "Feature",
  "properties": {
    "iso:country":"US",
    "sg:address":"7731 Jordan Xing",
    "sg:city":"Reynoldsburg",
    "sg:classifiers":[
        {
            "category":"Professional",
            "type":"Services"
        }
    ],
    "sg:phone":"+1 614 501 3204",
    "sg:postcode":"43068",
    "sg:province":"OH",
    "wof:name":"Educare Solutions & Svc",
    "wof:placetype":"venue"
},
  "geometry": {"coordinates":[-82.791031,39.964693],"type":"Point"}
}