{
  "type": "Feature",
  "properties": {
    "iso:country":"US",
    "sg:address":"3024 E 116th St",
    "sg:city":"Cleveland",
    "sg:classifiers":[
        {
            "category":"Personal",
            "subcategory":"Beauty Salon",
            "type":"Services"
        }
    ],
    "sg:phone":"+1 216 707 1334",
    "sg:postcode":"44120",
    "sg:province":"OH",
    "wof:name":"Hook Up",
    "wof:placetype":"venue"
},
  "geometry": {"coordinates":[-81.602881,41.476181],"type":"Point"}
}