{
  "type": "Feature",
  "properties": {
    "addr:full":"97 W Main St Chillicothe OH 45601",
    "addr:housenumber":"97",
    "addr:postcode":"45601",
    "addr:street":"W Main St",
    "iso:country":"US",
    "sg:address":"97 W Main St",
    "sg:city":"Chillicothe",
    "sg:classifiers":[
        {
            "category":"Professional",
            "subcategory":"Lawyer & Legal Services",
            "type":"Services"
        }
    ],
    "sg:phone":"+1 740 773 3952",
    "sg:postcode":"45601",
    "sg:province":"OH",
    "sg:tags":[
        "attorney"
    ],
    "wof:name":"Edward J Brown",
    "wof:placetype":"venue"
},
  "geometry": {"coordinates":[-82.985027,39.332796],"type":"Point"}
}