{
  "type": "Feature",
  "properties": {
    "iso:country":"US",
    "sg:address":"2557 Cleveland Rd",
    "sg:city":"Wooster",
    "sg:classifiers":[
        {
            "category":"Food & Beverages",
            "subcategory":"Liquor & Beverages",
            "type":"Retail Goods"
        }
    ],
    "sg:phone":"+1 330 345 2337",
    "sg:postcode":"44691",
    "sg:province":"OH",
    "sg:tags":[
        "alcoholic"
    ],
    "wof:name":"Chasers Drive Thru LTD",
    "wof:placetype":"venue"
},
  "geometry": {"coordinates":[-81.930671,40.830864],"type":"Point"}
}