{
  "type": "Feature",
  "properties": {
    "addr:full": "2557 Cleveland Rd Wooster OH 44691",
    "addr:housenumber": "2557",
    "addr:postcode": "44691",
    "addr:street": "Cleveland Rd",
    "iso:country": "US",
    "sg:address": "2557 Cleveland Rd",
    "sg:city": "Wooster",
    "sg:classifiers": [
      {
        "category": "Food \u0026 Beverages",
        "subcategory": "Liquor \u0026 Beverages",
        "type": "Retail Goods"
      }
    ],
    "sg:phone": "+1 330 345 2337",
    "sg:postcode": "44691",
    "sg:province": "OH",
    "sg:tags": [
      "alcoholic"
    ],
    "wof:name": "Chasers Drive Thru LTD",
    "wof:placetype": "venue"
  },
  "geometry": {"coordinates":[-81.930671,40.830864],"type":"Point"}
}
