{
  "type": "Feature",
  "properties": {
    "iso:country":"US",
    "sg:address":"1790 Marion-Agosta Rd",
    "sg:city":"Marion",
    "sg:classifiers":[
        {
            "category":"Freight",
            "type":"Transportation"
        }
    ],
    "sg:phone":"+1 740 223 2800",
    "sg:postcode":"43302",
    "sg:province":"OH",
    "sg:tags":[
        "warehouse",
        "self",
        "storage"
    ],
    "wof:name":"Galion Partners",
    "wof:placetype":"venue"
},
  "geometry": {"coordinates":[-83.175662,40.586049],"type":"Point"}
}