{
  "type": "Feature",
  "properties": {
    "addr:full":"860 E Broad St Elyria OH 44035",
    "addr:housenumber":"860",
    "addr:postcode":"44035",
    "addr:street":"E Broad St",
    "iso:country":"US",
    "sg:address":"860 E Broad St",
    "sg:city":"Elyria",
    "sg:classifiers":[
        {
            "category":"Health Services",
            "subcategory":"Doctor",
            "type":"Services"
        }
    ],
    "sg:phone":"+1 440 323 2032",
    "sg:postcode":"44035",
    "sg:province":"OH",
    "sg:tags":[
        "dentist"
    ],
    "wof:name":"Private Practice Dentistry",
    "wof:placetype":"venue"
},
  "geometry": {"coordinates":[-82.080468,41.365013],"type":"Point"}
}