{
  "type": "Feature",
  "properties": {
    "addr:full": "1784 E Dublin Granville Rd Columbus OH 43229",
    "addr:housenumber": "1784",
    "addr:postcode": "43229",
    "addr:street": "E Dublin Granville Rd",
    "iso:country": "US",
    "sg:address": "1784 E Dublin Granville Rd",
    "sg:city": "Columbus",
    "sg:classifiers": [
      {
        "category": "Restaurant",
        "type": "Food \u0026 Drink"
      }
    ],
    "sg:phone": "+1 614 523 2256",
    "sg:postcode": "43229",
    "sg:province": "OH",
    "sg:tags": [
      "eating"
    ],
    "wof:name": "Lapoao",
    "wof:placetype": "venue"
  },
  "geometry": {"coordinates":[-82.97415,40.087186],"type":"Point"}
}
