{
  "type": "Feature",
  "properties": {
    "addr:full": "210 N Walnut St Englewood OH 45322",
    "addr:housenumber": "210",
    "addr:postcode": "45322",
    "addr:street": "N Walnut St",
    "iso:country": "US",
    "sg:address": "210 N Walnut St",
    "sg:city": "Englewood",
    "sg:classifiers": [
      {
        "category": "Building \u0026 Trades",
        "subcategory": "Construction",
        "type": "Services"
      }
    ],
    "sg:phone": "+1 937 832 8697",
    "sg:postcode": "45322",
    "sg:province": "OH",
    "sg:tags": [
      "contractor"
    ],
    "wof:name": "G A Despain CUSTOM Homes LLC",
    "wof:placetype": "venue"
  },
  "geometry": {"coordinates":[-84.304169,39.881184],"type":"Point"}
}
