{
  "type": "Feature",
  "properties": {
    "addr:full": "141 South St SE Warren OH 44483",
    "addr:housenumber": "141",
    "addr:postcode": "44483",
    "addr:street": "South St Se",
    "iso:country": "US",
    "sg:address": "141 South St SE",
    "sg:city": "Warren",
    "sg:classifiers": [
      {
        "category": "Government",
        "subcategory": "Police Station",
        "type": "Public Place"
      }
    ],
    "sg:phone": "+1 330 841 2656",
    "sg:postcode": "44483",
    "sg:province": "OH",
    "sg:tags": [
      "department"
    ],
    "wof:name": "Warren Police Investigative",
    "wof:placetype": "venue"
  },
  "geometry": {"coordinates":[-80.816634,41.23415],"type":"Point"}
}
