{
  "type": "Feature",
  "properties": {
    "iso:country":"US",
    "sg:address":"141 South St SE",
    "sg:city":"Warren",
    "sg:classifiers":[
        {
            "category":"Government",
            "subcategory":"Police Station",
            "type":"Public Place"
        }
    ],
    "sg:phone":"+1 330 841 2656",
    "sg:postcode":"44483",
    "sg:province":"OH",
    "sg:tags":[
        "department"
    ],
    "wof:name":"Warren Police Investigative",
    "wof:placetype":"venue"
},
  "geometry": {"coordinates":[-80.81663399999999,41.23415],"type":"Point"}
}