{
  "type": "Feature",
  "properties": {
    "addr:full":"7867 Plains Rd Mentor On Lake OH 44060",
    "addr:housenumber":"7867",
    "addr:postcode":"lake;44060",
    "addr:street":"Plains Rd",
    "iso:country":"US",
    "sg:address":"7867 Plains Rd",
    "sg:city":"Mentor On Lake",
    "sg:classifiers":[
        {
            "category":"Personal",
            "subcategory":"Beauty Salon",
            "type":"Services"
        }
    ],
    "sg:phone":"+1 440 257 4747",
    "sg:postcode":"44060",
    "sg:province":"OH",
    "sg:website":"www.greatclips.com",
    "wof:name":"Great Clips",
    "wof:placetype":"venue"
},
  "geometry": {"coordinates":[-81.35731800000001,41.706656],"type":"Point"}
}