{
  "type": "Feature",
  "properties": {
    "addr:full": "7103 W Chester Rd West Chester OH 45069",
    "addr:housenumber": "7103",
    "addr:postcode": "45069",
    "addr:street": "W Chester Rd",
    "iso:country": "US",
    "sg:address": "7103 W Chester Rd",
    "sg:city": "West Chester",
    "sg:classifiers": [
      {
        "category": "Health Services",
        "subcategory": "Clinic",
        "type": "Services"
      }
    ],
    "sg:phone": "+1 513 759 9790",
    "sg:postcode": "45069",
    "sg:province": "OH",
    "wof:name": "Johnson \u0026 Johnson Health",
    "wof:placetype": "venue"
  },
  "geometry": {"coordinates":[-84.390734,39.322168],"type":"Point"}
}
