{
  "type": "Feature",
  "properties": {
    "iso:country":"US",
    "sg:address":"7103 W Chester Rd",
    "sg:city":"West Chester",
    "sg:classifiers":[
        {
            "category":"Health Services",
            "subcategory":"Clinic",
            "type":"Services"
        }
    ],
    "sg:phone":"+1 513 759 9790",
    "sg:postcode":"45069",
    "sg:province":"OH",
    "wof:name":"Johnson & Johnson Health",
    "wof:placetype":"venue"
},
  "geometry": {"coordinates":[-84.39073399999999,39.322168],"type":"Point"}
}