{
  "type": "Feature",
  "properties": {
    "addr:full":"7604 State Rte 7 Proctorville OH 45669",
    "addr:housenumber":"7604",
    "addr:postcode":"45669",
    "addr:street":"State Rte 7",
    "iso:country":"US",
    "sg:address":"7604 State Rte 7",
    "sg:city":"Proctorville",
    "sg:classifiers":[
        {
            "category":"Food & Beverages",
            "subcategory":"Groceries & Convenience Stores",
            "type":"Retail Goods"
        }
    ],
    "sg:phone":"+1 740 886 9990",
    "sg:postcode":"45669",
    "sg:province":"OH",
    "sg:tags":[
        "retailing",
        "dairy",
        "meat"
    ],
    "wof:name":"Coal Grove Food Center Inc",
    "wof:placetype":"venue"
},
  "geometry": {"coordinates":[-82.356765,38.442618],"type":"Point"}
}