{
  "type": "Feature",
  "properties": {
    "iso:country":"US",
    "sg:address":"2544 Chamberlain Rd",
    "sg:city":"Fairlawn",
    "sg:classifiers":[
        {
            "category":"Personal",
            "subcategory":"Beauty Salon",
            "type":"Services"
        }
    ],
    "sg:phone":"+1 330 836 2339",
    "sg:postcode":"44333",
    "sg:province":"OH",
    "wof:name":"Skin Zone",
    "wof:placetype":"venue"
},
  "geometry": {"coordinates":[-81.608592,41.125133],"type":"Point"}
}