{
  "type": "Feature",
  "properties": {
    "iso:country":"US",
    "sg:address":"123 S Walnut St",
    "sg:city":"Bucyrus",
    "sg:classifiers":[
        {
            "category":"Building & Trades",
            "subcategory":"Construction",
            "type":"Services"
        }
    ],
    "sg:phone":"+1 419 563 0077",
    "sg:postcode":"44820",
    "sg:province":"OH",
    "sg:tags":[
        "general",
        "contractor"
    ],
    "wof:name":"Matt Quinn & Co",
    "wof:placetype":"venue"
},
  "geometry": {"coordinates":[-82.974201,40.808429],"type":"Point"}
}