{
  "type": "Feature",
  "properties": {
    "addr:full": "610 Morrison Rd Gahanna OH 43230",
    "addr:housenumber": "610",
    "addr:postcode": "43230",
    "addr:street": "Morrison Rd",
    "iso:country": "US",
    "sg:address": "610 Morrison Rd",
    "sg:city": "Gahanna",
    "sg:classifiers": [
      {
        "category": "Insurance",
        "subcategory": "Insurance Agent",
        "type": "Services"
      }
    ],
    "sg:phone": "+1 614 861 3300",
    "sg:postcode": "43230",
    "sg:province": "OH",
    "sg:tags": [
      "consultant"
    ],
    "sg:website": "www.pro-tected.net",
    "wof:name": "David Downey \u0026 Assoc",
    "wof:placetype": "venue"
  },
  "geometry": {"coordinates":[-82.857522,40.000366],"type":"Point"}
}
