{
  "type": "Feature",
  "properties": {
    "iso:country":"US",
    "sg:address":"1745 Richmond Rd",
    "sg:city":"Cleveland",
    "sg:classifiers":[
        {
            "category":"Professional",
            "subcategory":"Engineering",
            "type":"Services"
        }
    ],
    "sg:phone":"+1 216 297 9950",
    "sg:postcode":"44124",
    "sg:province":"OH",
    "sg:tags":[
        "engineer"
    ],
    "wof:name":"Givens Geotech",
    "wof:placetype":"venue"
},
  "geometry": {"coordinates":[-81.497406,41.510547],"type":"Point"}
}