{
  "type": "Feature",
  "properties": {
    "addr:full": "4901 Millers Run-Fallen Timber Rd Lucasville OH 45648",
    "addr:housenumber": "4901;run-fallen",
    "addr:postcode": "45648",
    "addr:street": "Millers;Timber Rd",
    "iso:country": "US",
    "sg:address": "4901 Millers Run-Fallen Timber Rd",
    "sg:city": "Lucasville",
    "sg:classifiers": [
      {
        "category": "Building \u0026 Trades",
        "subcategory": "Construction",
        "type": "Services"
      }
    ],
    "sg:phone": "+1 740 820 8276",
    "sg:postcode": "45648",
    "sg:province": "OH",
    "sg:tags": [
      "contractor"
    ],
    "wof:name": "Twin Rivers Continuous Gutters",
    "wof:placetype": "venue"
  },
  "geometry": {"coordinates":[-82.934862,38.92957],"type":"Point"}
}
