{
  "type": "Feature",
  "properties": {
    "addr:full":"1540 Cornell Dr Dayton OH 45406",
    "addr:housenumber":"1540",
    "addr:postcode":"45406",
    "addr:street":"Cornell Dr",
    "iso:country":"US",
    "sg:address":"1540 Cornell Dr",
    "sg:city":"Dayton",
    "sg:classifiers":[
        {
            "category":"Professional",
            "subcategory":"Computer Services",
            "type":"Services"
        }
    ],
    "sg:phone":"+1 937 274 6671",
    "sg:postcode":"45406",
    "sg:province":"OH",
    "sg:tags":[
        "repair"
    ],
    "wof:name":"Select PC Repair",
    "wof:placetype":"venue"
},
  "geometry": {"coordinates":[-84.230931,39.776326],"type":"Point"}
}