{
  "type": "Feature",
  "properties": {
    "addr:full":"269 Bridge St Jackson OH 45640",
    "addr:housenumber":"269",
    "addr:postcode":"45640",
    "addr:street":"Bridge St",
    "iso:country":"US",
    "sg:address":"269 Bridge St",
    "sg:city":"Jackson",
    "sg:classifiers":[
        {
            "category":"Autos & Motor Vehicles",
            "subcategory":"Fuel & Gas Station",
            "type":"Retail Goods"
        }
    ],
    "sg:phone":"+1 740 286 9753",
    "sg:postcode":"45640",
    "sg:province":"OH",
    "sg:tags":[
        "station"
    ],
    "wof:name":"Gulf",
    "wof:placetype":"venue"
},
  "geometry": {"coordinates":[-82.63904700000001,39.055528],"type":"Point"}
}