{
  "type": "Feature",
  "properties": {
    "addr:full": "9122 W Salem Rd West Salem OH 44287",
    "addr:housenumber": "9122",
    "addr:postcode": "44287",
    "addr:street": "W Salem Rd",
    "iso:country": "US",
    "sg:address": "9122 W Salem Rd",
    "sg:city": "West Salem",
    "sg:classifiers": [
      {
        "category": "Farming",
        "subcategory": "Farm",
        "type": "Manufacturing \u0026 Wholesale Goods"
      }
    ],
    "sg:phone": "+1 419 846 3818",
    "sg:postcode": "44287",
    "sg:province": "OH",
    "sg:tags": [
      "crop",
      "general"
    ],
    "wof:name": "Badger Farms Ltd",
    "wof:placetype": "venue"
  },
  "geometry": {"coordinates":[-82.091111,40.981415],"type":"Point"}
}
