{
  "type": "Feature",
  "properties": {
    "addr:full":"1075 State Rte 343 Yellow Springs OH 45387",
    "addr:housenumber":"1075",
    "addr:postcode":"45387",
    "addr:street":"State Rte 343",
    "iso:country":"US",
    "sg:address":"1075 State Rte 343",
    "sg:city":"Yellow Springs",
    "sg:classifiers":[
        {
            "category":"Education",
            "subcategory":"School",
            "type":"Public Place"
        }
    ],
    "sg:phone":"+1 937 767 7648",
    "sg:postcode":"45387",
    "sg:province":"OH",
    "wof:name":"Antioch College",
    "wof:placetype":"venue"
},
  "geometry": {"coordinates":[-83.881816,39.807764],"type":"Point"}
}