{
  "type": "Feature",
  "properties": {
    "iso:country":"US",
    "sg:address":"210 High St",
    "sg:city":"Flushing",
    "sg:classifiers":[
        {
            "category":"Health Services",
            "subcategory":"Doctor",
            "type":"Services"
        }
    ],
    "sg:phone":"+1 740 968 4482",
    "sg:postcode":"43977",
    "sg:province":"OH",
    "sg:tags":[
        "dentist"
    ],
    "wof:name":"Robert J Kolanski DDS",
    "wof:placetype":"venue"
},
  "geometry": {"coordinates":[-81.067681,40.149291],"type":"Point"}
}