{
  "type": "Feature",
  "properties": {
    "addr:full":"627 Prospect Ave E Cleveland OH 44115",
    "addr:housenumber":"627",
    "addr:postcode":"44115",
    "addr:street":"Prospect Ave E",
    "iso:country":"US",
    "sg:address":"627 Prospect Ave E",
    "sg:city":"Cleveland",
    "sg:classifiers":[
        {
            "category":"Retail",
            "subcategory":"Repair Shop",
            "type":"Services"
        }
    ],
    "sg:phone":"+1 216 621 5878",
    "sg:postcode":"44115",
    "sg:province":"OH",
    "sg:tags":[
        "jewelry",
        "store",
        "variety"
    ],
    "wof:name":"Quality Jewelers Inc",
    "wof:placetype":"venue"
},
  "geometry": {"coordinates":[-81.68727199999999,41.498793],"type":"Point"}
}