{
  "type": "Feature",
  "properties": {
    "addr:full": "1730 State Rte 131 Milford OH 45150",
    "addr:housenumber": "1730",
    "addr:postcode": "45150",
    "addr:street": "State Rte 131",
    "iso:country": "US",
    "sg:address": "1730 State Rte 131",
    "sg:city": "Milford",
    "sg:classifiers": [
      {
        "category": "Building \u0026 Trades",
        "subcategory": "Plumbing",
        "type": "Services"
      }
    ],
    "sg:phone": "+1 513 575 4588",
    "sg:postcode": "45150",
    "sg:province": "OH",
    "sg:tags": [
      "air",
      "heating",
      "conditioning",
      "contractor"
    ],
    "wof:name": "Advanco Engineering Inc",
    "wof:placetype": "venue"
  },
  "geometry": {"coordinates":[-84.18508,39.175896],"type":"Point"}
}
