{
  "type": "Feature",
  "properties": {
    "addr:full": "659 S Breiel Blvd Middletown OH 45044",
    "addr:housenumber": "659",
    "addr:postcode": "45044",
    "addr:street": "S Breiel Blvd",
    "iso:country": "US",
    "sg:address": "659 S Breiel Blvd",
    "sg:city": "Middletown",
    "sg:classifiers": [
      {
        "category": "Professional",
        "subcategory": "Employment Agencies",
        "type": "Services"
      }
    ],
    "sg:phone": "+1 513 424 9925",
    "sg:postcode": "45044",
    "sg:province": "OH",
    "sg:tags": [
      "help",
      "contractor"
    ],
    "wof:name": "Westaff",
    "wof:placetype": "venue"
  },
  "geometry": {"coordinates":[-84.354938,39.50592],"type":"Point"}
}
