{
  "type": "Feature",
  "properties": {
    "addr:full": "19851 Ingersoll Dr Cleveland OH 44116",
    "addr:housenumber": "19851",
    "addr:postcode": "44116",
    "addr:street": "Ingersoll Dr",
    "iso:country": "US",
    "sg:address": "19851 Ingersoll Dr",
    "sg:city": "Cleveland",
    "sg:classifiers": [
      {
        "category": "Manufacturing",
        "subcategory": "Rubber \u0026 Plastics",
        "type": "Manufacturing \u0026 Wholesale Goods"
      }
    ],
    "sg:phone": "+1 440 331 5575",
    "sg:postcode": "44116",
    "sg:province": "OH",
    "sg:tags": [
      "packaging",
      "forming",
      "product",
      "foam",
      "mfg"
    ],
    "wof:name": "Plastic Works Inc",
    "wof:placetype": "venue"
  },
  "geometry": {"coordinates":[-81.842987,41.480765],"type":"Point"}
}
