{
  "type": "Feature",
  "properties": {
    "iso:country":"US",
    "sg:address":"19851 Ingersoll Dr",
    "sg:city":"Cleveland",
    "sg:classifiers":[
        {
            "category":"Manufacturing",
            "subcategory":"Rubber & Plastics",
            "type":"Manufacturing & Wholesale Goods"
        }
    ],
    "sg:phone":"+1 440 331 5575",
    "sg:postcode":"44116",
    "sg:province":"OH",
    "sg:tags":[
        "packaging",
        "forming",
        "product",
        "foam",
        "mfg"
    ],
    "wof:name":"Plastic Works Inc",
    "wof:placetype":"venue"
},
  "geometry": {"coordinates":[-81.842987,41.480765],"type":"Point"}
}