{
  "type": "Feature",
  "properties": {
    "iso:country":"US",
    "sg:address":"170 Monroe St NW",
    "sg:city":"Warren",
    "sg:classifiers":[
        {
            "category":"Professional",
            "subcategory":"Lawyer & Legal Services",
            "type":"Services"
        }
    ],
    "sg:phone":"+1 330 393 4611",
    "sg:postcode":"44483",
    "sg:province":"OH",
    "wof:name":"Keating Keating & Kuzman",
    "wof:placetype":"venue"
},
  "geometry": {"coordinates":[-80.81890799999999,41.24083],"type":"Point"}
}