{
  "type": "Feature",
  "properties": {
    "addr:full": "170 Monroe St NW Warren OH 44483",
    "addr:housenumber": "170",
    "addr:postcode": "44483",
    "addr:street": "Monroe St Nw",
    "iso:country": "US",
    "sg:address": "170 Monroe St NW",
    "sg:city": "Warren",
    "sg:classifiers": [
      {
        "category": "Professional",
        "subcategory": "Lawyer \u0026 Legal Services",
        "type": "Services"
      }
    ],
    "sg:phone": "+1 330 393 4611",
    "sg:postcode": "44483",
    "sg:province": "OH",
    "wof:name": "Keating Keating \u0026 Kuzman",
    "wof:placetype": "venue"
  },
  "geometry": {"coordinates":[-80.818908,41.24083],"type":"Point"}
}
