{
  "type": "Feature",
  "properties": {
    "iso:country":"US",
    "sg:address":"4303 Mahoning Ave",
    "sg:city":"Youngstown",
    "sg:classifiers":[
        {
            "category":"Retail",
            "subcategory":"Funeral Services",
            "type":"Services"
        }
    ],
    "sg:phone":"+1 330 792 2353",
    "sg:postcode":"44515",
    "sg:province":"OH",
    "sg:tags":[
        "director",
        "embalmer"
    ],
    "sg:website":"http://www.higgins-reardon.com",
    "wof:name":"Boardman Canfield Chapel",
    "wof:placetype":"venue"
},
  "geometry": {"coordinates":[-80.729946,41.102439],"type":"Point"}
}