{
  "type": "Feature",
  "properties": {
    "iso:country":"US",
    "sg:address":"250 E Wilson Bridge Rd",
    "sg:city":"Columbus",
    "sg:classifiers":[
        {
            "category":"Professional",
            "subcategory":"Business Services",
            "type":"Services"
        }
    ],
    "sg:phone":"+1 614 846 8630",
    "sg:postcode":"43085",
    "sg:province":"OH",
    "sg:tags":[
        "show",
        "printing",
        "promotional",
        "advertising",
        "trade"
    ],
    "wof:name":"Three Leaf Productions Inc",
    "wof:placetype":"venue"
},
  "geometry": {"coordinates":[-83.01177,40.109672],"type":"Point"}
}