{
  "type": "Feature",
  "properties": {
    "addr:full":"135 N Bever St Wooster OH 44691",
    "addr:housenumber":"135",
    "addr:postcode":"44691",
    "addr:street":"N Bever St",
    "iso:country":"US",
    "sg:address":"135 N Bever St",
    "sg:city":"Wooster",
    "sg:classifiers":[
        {
            "category":"Building & Trades",
            "subcategory":"Construction",
            "type":"Services"
        }
    ],
    "sg:phone":"+1 330 264 3671",
    "sg:postcode":"44691",
    "sg:province":"OH",
    "sg:tags":[
        "roofing",
        "contractor"
    ],
    "wof:name":"Steele's Roofing & Remodeling",
    "wof:placetype":"venue"
},
  "geometry": {"coordinates":[-81.937016,40.799881],"type":"Point"}
}