{
  "type": "Feature",
  "properties": {
    "addr:full": "3913 Roosevelt Blvd Middletown OH 45044",
    "addr:housenumber": "3913",
    "addr:postcode": "45044",
    "addr:street": "Roosevelt Blvd",
    "iso:country": "US",
    "sg:address": "3913 Roosevelt Blvd",
    "sg:city": "Middletown",
    "sg:classifiers": [
      {
        "category": "Health Services",
        "subcategory": "Podiatrist",
        "type": "Services"
      },
      {
        "category": "Wholesale",
        "subcategory": "Durable Goods \u0026 Equipment",
        "type": "Manufacturing \u0026 Wholesale Goods"
      }
    ],
    "sg:phone": "+1 513 727 8444",
    "sg:postcode": "45044",
    "sg:province": "OH",
    "sg:tags": [
      "professional"
    ],
    "wof:name": "Wilmington Foot \u0026 Ankle Inc",
    "wof:placetype": "venue"
  },
  "geometry": {"coordinates":[-84.36274,39.49988],"type":"Point"}
}
