{
  "type": "Feature",
  "properties": {
    "addr:full":"17781 State Route 31 Marysville OH 43040",
    "addr:housenumber":"17781",
    "addr:postcode":"43040",
    "addr:street":"State Route 31",
    "iso:country":"US",
    "sg:address":"17781 State Route 31",
    "sg:city":"Marysville",
    "sg:classifiers":[
        {
            "category":"Restaurant",
            "type":"Food & Drink"
        }
    ],
    "sg:menulink":"http://www.allmenus.com/oh/paris/195007-mcdonalds/menu/",
    "sg:postcode":"43040",
    "sg:province":"OH",
    "sg:tags":[
        "burger",
        "american"
    ],
    "wof:name":"McDonald's",
    "wof:placetype":"venue"
},
  "geometry": {"coordinates":[-83.373811,40.259095],"type":"Point"}
}