{
  "type": "Feature",
  "properties": {
    "addr:full": "1818 State Rte 169 Niles OH 44446",
    "addr:housenumber": "1818",
    "addr:postcode": "44446",
    "addr:street": "State Rte 169",
    "iso:country": "US",
    "sg:address": "1818 State Rte 169",
    "sg:city": "Niles",
    "sg:classifiers": [
      {
        "category": "Freight",
        "type": "Transportation"
      }
    ],
    "sg:phone": "+1 330 544 9555",
    "sg:postcode": "44446",
    "sg:province": "OH",
    "sg:tags": [
      "hauling",
      "trucking"
    ],
    "wof:name": "Exactatruck Inc",
    "wof:placetype": "venue"
  },
  "geometry": {"coordinates":[-80.771005,41.194147],"type":"Point"}
}
