{
  "type": "Feature",
  "properties": {
    "addr:full":"12450 Plaza Dr Cleveland OH 44130",
    "addr:housenumber":"12450",
    "addr:postcode":"44130",
    "addr:street":"Plaza Dr",
    "iso:country":"US",
    "sg:address":"12450 Plaza Dr",
    "sg:city":"Cleveland",
    "sg:classifiers":[
        {
            "category":"Building & Trades",
            "subcategory":"Construction",
            "type":"Services"
        }
    ],
    "sg:phone":"+1 216 267 2144",
    "sg:postcode":"44130",
    "sg:province":"OH",
    "sg:tags":[
        "repairing",
        "remodeling",
        "contractor"
    ],
    "wof:name":"H E Klefman Co",
    "wof:placetype":"venue"
},
  "geometry": {"coordinates":[-81.77708699999999,41.399973],"type":"Point"}
}