{
  "type": "Feature",
  "properties": {
    "addr:full": "7948 Mayfield Rd Chesterland OH 44026",
    "addr:housenumber": "7948",
    "addr:postcode": "44026",
    "addr:street": "Mayfield Rd",
    "iso:country": "US",
    "sg:address": "7948 Mayfield Rd",
    "sg:city": "Chesterland",
    "sg:classifiers": [
      {
        "category": "Building \u0026 Trades",
        "subcategory": "Construction",
        "type": "Services"
      }
    ],
    "sg:phone": "+1 440 729 2255",
    "sg:postcode": "44026",
    "sg:province": "OH",
    "sg:tags": [
      "containment",
      "electronic",
      "dog",
      "fence",
      "contractor"
    ],
    "wof:name": "Invisible Fence Northeast Ohio",
    "wof:placetype": "venue"
  },
  "geometry": {"coordinates":[-81.35732,41.522452],"type":"Point"}
}
