{
  "type": "Feature",
  "properties": {
    "addr:full":"4000 Embassy Pkwy Akron OH 44333",
    "addr:housenumber":"4000",
    "addr:postcode":"44333",
    "addr:street":"Embassy Pkwy",
    "iso:country":"US",
    "sg:address":"4000 Embassy Pkwy",
    "sg:city":"Akron",
    "sg:classifiers":[
        {
            "category":"Banks & Credit Unions",
            "subcategory":"Investment Brokerage",
            "type":"Services"
        }
    ],
    "sg:phone":"+1 330 666 8878",
    "sg:postcode":"44333",
    "sg:province":"OH",
    "sg:tags":[
        "advisory",
        "financial"
    ],
    "wof:name":"H & R Block Financial Advisors",
    "wof:placetype":"venue"
},
  "geometry": {"coordinates":[-81.656097,41.137371],"type":"Point"}
}