{
  "type": "Feature",
  "properties": {
    "addr:full":"4810 Lamme Rd Dayton OH 45439",
    "addr:postcode":"4810;45439",
    "addr:street":"Lamme Rd",
    "iso:country":"US",
    "sg:address":"4810 Lamme Rd",
    "sg:city":"Dayton",
    "sg:classifiers":[
        {
            "category":"Home & Garden",
            "subcategory":"Building Materials",
            "type":"Retail Goods"
        }
    ],
    "sg:phone":"+1 937 299 4146",
    "sg:postcode":"45439",
    "sg:province":"OH",
    "wof:name":"Contractors Fencing",
    "wof:placetype":"venue"
},
  "geometry": {"coordinates":[-84.212234,39.681992],"type":"Point"}
}