{
  "type": "Feature",
  "properties": {
    "addr:full": "4908 Turney Rd Cleveland OH 44125",
    "addr:housenumber": "4908",
    "addr:postcode": "44125",
    "addr:street": "Turney Rd",
    "iso:country": "US",
    "sg:address": "4908 Turney Rd",
    "sg:city": "Cleveland",
    "sg:classifiers": [
      {
        "category": "Shopping",
        "subcategory": "Clothing, Apparel, \u0026 Fashions",
        "type": "Retail Goods"
      }
    ],
    "sg:phone": "+1 216 271 9597",
    "sg:postcode": "44125",
    "sg:province": "OH",
    "sg:tags": [
      "medical",
      "work",
      "uniform"
    ],
    "wof:name": "Affordable Uniforms",
    "wof:placetype": "venue"
  },
  "geometry": {"coordinates":[-81.613202,41.426927],"type":"Point"}
}
