{
  "type": "Feature",
  "properties": {
    "addr:full":"4480 Summit Ridge Rd Columbus OH 43220",
    "addr:housenumber":"4480",
    "addr:postcode":"43220",
    "addr:street":"Summit Ridge Rd",
    "iso:country":"US",
    "sg:address":"4480 Summit Ridge Rd",
    "sg:city":"Columbus",
    "sg:classifiers":[
        {
            "category":"Wholesale",
            "subcategory":"Non-durable Goods",
            "type":"Manufacturing & Wholesale Goods"
        }
    ],
    "sg:phone":"+1 614 538 8207",
    "sg:postcode":"43220",
    "sg:province":"OH",
    "sg:tags":[
        "advertising"
    ],
    "sg:website":"www.betalaser.com",
    "wof:name":"Beta Electronics",
    "wof:placetype":"venue"
},
  "geometry": {"coordinates":[-83.089288,40.057833],"type":"Point"}
}