{
  "type": "Feature",
  "properties": {
    "addr:full": "800 Ward-Koebel Rd Oregonia OH 45054",
    "addr:housenumber": "800",
    "addr:postcode": "45054",
    "addr:street": "Ward-Koebel Rd",
    "iso:country": "US",
    "sg:address": "800 Ward-Koebel Rd",
    "sg:city": "Oregonia",
    "sg:classifiers": [
      {
        "category": "Restaurant",
        "type": "Food \u0026 Drink"
      }
    ],
    "sg:phone": "+1 937 289 2850",
    "sg:postcode": "45054",
    "sg:province": "OH",
    "wof:name": "Perkins Family Restaurant",
    "wof:placetype": "venue"
  },
  "geometry": {"coordinates":[-84.046736,39.41448],"type":"Point"}
}
