{
  "type": "Feature",
  "properties": {
    "addr:full": "1910 W Robb Ave Lima OH 45805",
    "addr:housenumber": "1910",
    "addr:postcode": "45805",
    "addr:street": "W Robb Ave",
    "iso:country": "US",
    "sg:address": "1910 W Robb Ave",
    "sg:city": "Lima",
    "sg:classifiers": [
      {
        "category": "Shopping",
        "subcategory": "Computers \u0026 Home Electronics",
        "type": "Retail Goods"
      },
      {
        "category": "Professional",
        "subcategory": "Computer Services",
        "type": "Services"
      }
    ],
    "sg:phone": "+1 419 224 8344",
    "sg:postcode": "45805",
    "sg:province": "OH",
    "sg:tags": [
      "repair"
    ],
    "sg:website": "www.vipersystems.biz",
    "wof:name": "Viper Systems",
    "wof:placetype": "venue"
  },
  "geometry": {"coordinates":[-84.137563,40.758826],"type":"Point"}
}
