{
  "type": "Feature",
  "properties": {
    "addr:full":"2352 E 40th St Cleveland OH 44104",
    "addr:housenumber":"2352",
    "addr:postcode":"44104",
    "addr:street":"E 40Th St",
    "iso:country":"US",
    "sg:address":"2352 E 40th St",
    "sg:city":"Cleveland",
    "sg:classifiers":[
        {
            "category":"Organizations",
            "subcategory":"Religious Organization",
            "type":"Services"
        }
    ],
    "sg:phone":"+1 216 881 7513",
    "sg:postcode":"44104",
    "sg:province":"OH",
    "sg:tags":[
        "church"
    ],
    "wof:name":"Pilgrim Baptist Church",
    "wof:placetype":"venue"
},
  "geometry": {"coordinates":[-81.65742,41.493814],"type":"Point"}
}