{
  "type": "Feature",
  "properties": {
    "addr:full": "3005 Dixie Hwy Middletown OH 45044",
    "addr:housenumber": "3005",
    "addr:postcode": "45044",
    "addr:street": "Dixie Hwy",
    "iso:country": "US",
    "sg:address": "3005 Dixie Hwy",
    "sg:city": "Middletown",
    "sg:classifiers": [
      {
        "category": "Health Services",
        "subcategory": "Doctor",
        "type": "Services"
      }
    ],
    "sg:phone": "+1 513 281 0101",
    "sg:postcode": "45044",
    "sg:province": "OH",
    "sg:tags": [
      "physician",
      "surgeon"
    ],
    "wof:name": "Christine Horner-Taylor MD",
    "wof:placetype": "venue"
  },
  "geometry": {"coordinates":[-84.345061,39.469863],"type":"Point"}
}
