{
  "type": "Feature",
  "properties": {
    "iso:country":"US",
    "sg:address":"7154 Industrial Park Blvd",
    "sg:city":"Mentor",
    "sg:classifiers":[
        {
            "category":"Manufacturing",
            "subcategory":"Rubber & Plastics",
            "type":"Manufacturing & Wholesale Goods"
        },
        {
            "category":"Manufacturing",
            "subcategory":"Tools & Machinery",
            "type":"Manufacturing & Wholesale Goods"
        }
    ],
    "sg:phone":"+1 440 942 7585",
    "sg:postcode":"44060",
    "sg:province":"OH",
    "sg:tags":[
        "mold",
        "mfg"
    ],
    "wof:name":"Vast Mold & Tool Co",
    "wof:placetype":"venue"
},
  "geometry": {"coordinates":[-81.384985,41.654157],"type":"Point"}
}