{
  "type": "Feature",
  "properties": {
    "iso:country":"US",
    "sg:address":"804 N Columbus St",
    "sg:city":"Lancaster",
    "sg:classifiers":[
        {
            "category":"Personal",
            "subcategory":"Beauty Salon",
            "type":"Services"
        }
    ],
    "sg:phone":"+1 740 687 5566",
    "sg:postcode":"43130",
    "sg:province":"OH",
    "wof:name":"Adare Studio Of Hair Design",
    "wof:placetype":"venue"
},
  "geometry": {"coordinates":[-82.604096,39.722614],"type":"Point"}
}