{
  "type": "Feature",
  "properties": {
    "addr:full":"1133 Evans Way Ct Columbus OH 43228",
    "addr:housenumber":"1133",
    "addr:postcode":"43228",
    "addr:street":"Evans Way Ct",
    "iso:country":"US",
    "sg:address":"1133 Evans Way Ct",
    "sg:city":"Columbus",
    "sg:classifiers":[
        {
            "category":"Travel",
            "subcategory":"Hotels & Motels",
            "type":"Entertainment"
        }
    ],
    "sg:phone":"+1 877 574 2464",
    "sg:postcode":"43228",
    "sg:province":"OH",
    "sg:website":"http://book.bestwestern.com/bestwestern/priceAvail.do?propertyCode=36106&cm_mmc=IYP-_-YP-_-property-_-36106",
    "wof:name":"Best Western Suites",
    "wof:placetype":"venue"
},
  "geometry": {"coordinates":[-83.151768,39.974906],"type":"Point"}
}