{
  "type": "Feature",
  "properties": {
    "addr:full":"130 Eswin St Cincinnati OH 45218",
    "addr:housenumber":"130",
    "addr:postcode":"45218",
    "addr:street":"Eswin St",
    "iso:country":"US",
    "sg:address":"130 Eswin St",
    "sg:city":"Cincinnati",
    "sg:classifiers":[
        {
            "category":"Shopping",
            "subcategory":"Discount & Variety Stores",
            "type":"Retail Goods"
        }
    ],
    "sg:phone":"+1 513 742 2632",
    "sg:postcode":"45218",
    "sg:province":"OH",
    "wof:name":"Dollar General",
    "wof:placetype":"venue"
},
  "geometry": {"coordinates":[-84.522713,39.27054],"type":"Point"}
}