{
  "type": "Feature",
  "properties": {
    "addr:full":"670 Ridgewood Dr Circleville OH 43113",
    "addr:housenumber":"670",
    "addr:postcode":"43113",
    "addr:street":"Ridgewood Dr",
    "iso:country":"US",
    "sg:address":"670 Ridgewood Dr",
    "sg:city":"Circleville",
    "sg:classifiers":[
        {
            "category":"Banks & Credit Unions",
            "subcategory":"Investment Brokerage",
            "type":"Services"
        }
    ],
    "sg:phone":"+1 740 474 3424",
    "sg:postcode":"43113",
    "sg:province":"OH",
    "sg:tags":[
        "security"
    ],
    "wof:name":"Jlsd Inc",
    "wof:placetype":"venue"
},
  "geometry": {"coordinates":[-82.926311,39.620925],"type":"Point"}
}