{
  "type": "Feature",
  "properties": {
    "addr:full": "11217 State Rte 41 West Union OH 45693",
    "addr:housenumber": "11217",
    "addr:postcode": "45693",
    "addr:street": "State Rte 41 West",
    "iso:country": "US",
    "sg:address": "11217 State Rte 41",
    "sg:city": "West Union",
    "sg:classifiers": [
      {
        "category": "Banks \u0026 Credit Unions",
        "subcategory": "Bank",
        "type": "Services"
      }
    ],
    "sg:phone": "+1 937 544 4197",
    "sg:postcode": "45693",
    "sg:province": "OH",
    "sg:website": "www.nbtdirect.com",
    "wof:name": "National Bank \u0026 Trust",
    "wof:placetype": "venue"
  },
  "geometry": {"coordinates":[-83.56106,38.783651],"type":"Point"}
}
