{
  "type": "Feature",
  "properties": {
    "iso:country":"US",
    "sg:address":"11217 State Rte 41",
    "sg:city":"West Union",
    "sg:classifiers":[
        {
            "category":"Banks & Credit Unions",
            "subcategory":"Bank",
            "type":"Services"
        }
    ],
    "sg:phone":"+1 937 544 4197",
    "sg:postcode":"45693",
    "sg:province":"OH",
    "sg:website":"www.nbtdirect.com",
    "wof:name":"National Bank & Trust",
    "wof:placetype":"venue"
},
  "geometry": {"coordinates":[-83.56106,38.783651],"type":"Point"}
}