{
  "type": "Feature",
  "properties": {
    "iso:country":"US",
    "sg:address":"5100 Glenway Ave",
    "sg:city":"Cincinnati",
    "sg:classifiers":[
        {
            "category":"Insurance",
            "subcategory":"Insurance Agent",
            "type":"Services"
        }
    ],
    "sg:phone":"+1 513 251 1633",
    "sg:postcode":"45238",
    "sg:province":"OH",
    "sg:website":"www.westernsouthernlife.com",
    "wof:name":"Western-Southern Life Ins Co",
    "wof:placetype":"venue"
},
  "geometry": {"coordinates":[-84.602339,39.122977],"type":"Point"}
}