{
  "type": "Feature",
  "properties": {
    "iso:country":"US",
    "sg:address":"1738 S Main St",
    "sg:city":"Bellefontaine",
    "sg:classifiers":[
        {
            "category":"Shopping",
            "subcategory":"Gifts & Souvenirs",
            "type":"Retail Goods"
        }
    ],
    "sg:phone":"+1 937 592 6700",
    "sg:postcode":"43311",
    "sg:province":"OH",
    "sg:tags":[
        "shop"
    ],
    "wof:name":"M & R Hallmark",
    "wof:placetype":"venue"
},
  "geometry": {"coordinates":[-83.761932,40.337176],"type":"Point"}
}