{
  "type": "Feature",
  "properties": {
    "addr:full": "1738 S Main St Bellefontaine OH 43311",
    "addr:housenumber": "1738",
    "addr:postcode": "43311",
    "addr:street": "S Main St",
    "iso:country": "US",
    "sg:address": "1738 S Main St",
    "sg:city": "Bellefontaine",
    "sg:classifiers": [
      {
        "category": "Shopping",
        "subcategory": "Gifts \u0026 Souvenirs",
        "type": "Retail Goods"
      }
    ],
    "sg:phone": "+1 937 592 6700",
    "sg:postcode": "43311",
    "sg:province": "OH",
    "sg:tags": [
      "shop"
    ],
    "wof:name": "M \u0026 R Hallmark",
    "wof:placetype": "venue"
  },
  "geometry": {"coordinates":[-83.761932,40.337176],"type":"Point"}
}
