{
  "type": "Feature",
  "properties": {
    "addr:full": "336 N Main St Minster OH 45865",
    "addr:housenumber": "336",
    "addr:postcode": "45865",
    "addr:street": "N Main St",
    "iso:country": "US",
    "sg:address": "336 N Main St",
    "sg:city": "Minster",
    "sg:classifiers": [
      {
        "category": "Shopping",
        "subcategory": "Clothing, Apparel, \u0026 Fashions",
        "type": "Retail Goods"
      }
    ],
    "sg:phone": "+1 419 628 7555",
    "sg:postcode": "45865",
    "sg:province": "OH",
    "sg:tags": [
      "personal",
      "shop",
      "bridal"
    ],
    "sg:website": "www.emmysbridal.com",
    "wof:name": "Emmy's Bridal Shop",
    "wof:placetype": "venue"
  },
  "geometry": {"coordinates":[-84.37658,40.39946],"type":"Point"}
}
