{
  "type": "Feature",
  "properties": {
    "iso:country":"US",
    "sg:address":"1272 W Main St",
    "sg:city":"Newark",
    "sg:classifiers":[
        {
            "category":"Shopping",
            "subcategory":"Pharmacy",
            "type":"Retail Goods"
        }
    ],
    "sg:phone":"+1 740 344 2195",
    "sg:postcode":"43055",
    "sg:province":"OH",
    "sg:tags":[
        "health"
    ],
    "wof:name":"Arensberg Home Health",
    "wof:placetype":"venue"
},
  "geometry": {"coordinates":[-82.45076400000001,40.046955],"type":"Point"}
}