{
  "type": "Feature",
  "properties": {
    "iso:country":"US",
    "sg:address":"7355 Mudbrook St NW",
    "sg:city":"Massillon",
    "sg:classifiers":[
        {
            "category":"Education",
            "subcategory":"School",
            "type":"Public Place"
        }
    ],
    "sg:phone":"+1 330 830 8042",
    "sg:postcode":"44646",
    "sg:province":"OH",
    "wof:name":"Jackson Local Sch Dist Trans",
    "wof:placetype":"venue"
},
  "geometry": {"coordinates":[-81.487878,40.866481],"type":"Point"}
}