{
  "type": "Feature",
  "properties": {
    "addr:full": "7415 Diley Rd Canal Winchester OH 43110",
    "addr:housenumber": "7415",
    "addr:postcode": "43110",
    "addr:street": "Diley Rd",
    "iso:country": "US",
    "sg:address": "7415 Diley Rd",
    "sg:city": "Canal Winchester",
    "sg:classifiers": [
      {
        "category": "Manufacturing",
        "subcategory": "Glass \u0026 Minerals",
        "type": "Manufacturing \u0026 Wholesale Goods"
      }
    ],
    "sg:phone": "+1 614 837 8444",
    "sg:postcode": "43110",
    "sg:province": "OH",
    "sg:tags": [
      "concrete",
      "brick",
      "prod",
      "block"
    ],
    "wof:name": "E C Babbert Inc",
    "wof:placetype": "venue"
  },
  "geometry": {"coordinates":[-82.781971,39.842293],"type":"Point"}
}
