{
  "type": "Feature",
  "properties": {
    "iso:country":"US",
    "sg:address":"7415 Diley Rd",
    "sg:city":"Canal Winchester",
    "sg:classifiers":[
        {
            "category":"Manufacturing",
            "subcategory":"Glass & Minerals",
            "type":"Manufacturing & Wholesale Goods"
        }
    ],
    "sg:phone":"+1 614 837 8444",
    "sg:postcode":"43110",
    "sg:province":"OH",
    "sg:tags":[
        "concrete",
        "brick",
        "prod",
        "block"
    ],
    "wof:name":"E C Babbert Inc",
    "wof:placetype":"venue"
},
  "geometry": {"coordinates":[-82.781971,39.842293],"type":"Point"}
}