{
  "type": "Feature",
  "properties": {
    "addr:full":"372 Northridge Rd Columbus OH 43214",
    "addr:housenumber":"372",
    "addr:postcode":"43214",
    "addr:street":"Northridge Rd",
    "iso:country":"US",
    "sg:address":"372 Northridge Rd",
    "sg:city":"Columbus",
    "sg:classifiers":[
        {
            "category":"Building & Trades",
            "subcategory":"Construction",
            "type":"Services"
        }
    ],
    "sg:phone":"+1 614 273 4000",
    "sg:postcode":"43214",
    "sg:province":"OH",
    "sg:tags":[
        "equipment",
        "retail"
    ],
    "wof:name":"Northridge Enviornmental Eqp",
    "wof:placetype":"venue"
},
  "geometry": {"coordinates":[-83.007873,40.042515],"type":"Point"}
}