{
  "type": "Feature",
  "properties": {
    "addr:full": "1075 Amboise Dr Marion OH 43302",
    "addr:housenumber": "1075",
    "addr:postcode": "43302",
    "addr:street": "Amboise Dr",
    "iso:country": "US",
    "sg:address": "1075 Amboise Dr",
    "sg:city": "Marion",
    "sg:classifiers": [
      {
        "category": "Restaurant",
        "type": "Food \u0026 Drink"
      }
    ],
    "sg:phone": "+1 740 389 4038",
    "sg:postcode": "43302",
    "sg:province": "OH",
    "sg:tags": [
      "eating"
    ],
    "wof:name": "Mc House Inc",
    "wof:placetype": "venue"
  },
  "geometry": {"coordinates":[-83.099925,40.569753],"type":"Point"}
}
