{
  "type": "Feature",
  "properties": {
    "iso:country":"US",
    "sg:address":"1075 Amboise Dr",
    "sg:city":"Marion",
    "sg:classifiers":[
        {
            "category":"Restaurant",
            "type":"Food & Drink"
        }
    ],
    "sg:phone":"+1 740 389 4038",
    "sg:postcode":"43302",
    "sg:province":"OH",
    "sg:tags":[
        "eating"
    ],
    "wof:name":"Mc House Inc",
    "wof:placetype":"venue"
},
  "geometry": {"coordinates":[-83.099925,40.569753],"type":"Point"}
}