{
  "type": "Feature",
  "properties": {
    "addr:full":"76 E Lincoln St Westerville OH 43081",
    "addr:housenumber":"76",
    "addr:postcode":"43081",
    "addr:street":"E Lincoln St",
    "iso:country":"US",
    "sg:address":"76 E Lincoln St",
    "sg:city":"Westerville",
    "sg:classifiers":[
        {
            "category":"Education",
            "subcategory":"Special Training",
            "type":"Public Place"
        }
    ],
    "sg:phone":"+1 614 895 3249",
    "sg:postcode":"43081",
    "sg:province":"OH",
    "sg:tags":[
        "instruction",
        "music"
    ],
    "wof:name":"Piano Lessons For Less",
    "wof:placetype":"venue"
},
  "geometry": {"coordinates":[-82.93088400000001,40.128836],"type":"Point"}
}