{
  "type": "Feature",
  "properties": {
    "addr:full":"45721 US Hwy 20 Oberlin OH 44074",
    "addr:postcode":"45721;44074",
    "addr:street":"Us Hwy 20",
    "iso:country":"US",
    "sg:address":"45721 US Hwy 20",
    "sg:city":"Oberlin",
    "sg:classifiers":[
        {
            "category":"Restaurant",
            "type":"Food & Drink"
        }
    ],
    "sg:phone":"+1 440 774 8111",
    "sg:postcode":"44074",
    "sg:province":"OH",
    "sg:tags":[
        "parlor",
        "ice",
        "cream"
    ],
    "wof:name":"Dairy Twist",
    "wof:placetype":"venue"
},
  "geometry": {"coordinates":[-82.20475500000001,41.267971],"type":"Point"}
}