{
  "type": "Feature",
  "properties": {
    "addr:full":"1935 Edgewood Dr Twinsburg OH 44087",
    "addr:housenumber":"1935",
    "addr:postcode":"44087",
    "addr:street":"Edgewood Dr",
    "iso:country":"US",
    "sg:address":"1935 Edgewood Dr",
    "sg:city":"Twinsburg",
    "sg:classifiers":[
        {
            "category":"Shopping",
            "subcategory":"Florist",
            "type":"Retail Goods"
        }
    ],
    "sg:phone":"+1 330 405 7142",
    "sg:postcode":"44087",
    "sg:province":"OH",
    "wof:name":"Gifts In Bloom",
    "wof:placetype":"venue"
},
  "geometry": {"coordinates":[-81.458297,41.333499],"type":"Point"}
}