{
  "type": "Feature",
  "properties": {
    "addr:full":"50 Carpenters Ridge Cincinnati OH 45241",
    "addr:housenumber":"50",
    "addr:postcode":"45241",
    "addr:street":"Carpenters Ridge",
    "iso:country":"US",
    "sg:address":"50 Carpenters Ridge",
    "sg:city":"Cincinnati",
    "sg:classifiers":[
        {
            "category":"Insurance",
            "subcategory":"Insurance Agent",
            "type":"Services"
        }
    ],
    "sg:phone":"+1 513 891 7900",
    "sg:postcode":"45241",
    "sg:province":"OH",
    "wof:name":"Mc Donald & Assoc",
    "wof:placetype":"venue"
},
  "geometry": {"coordinates":[-84.408891,39.241703],"type":"Point"}
}