{
  "type": "Feature",
  "properties": {
    "addr:full": "1356 Lexington Ave Mansfield OH 44907",
    "addr:housenumber": "1356",
    "addr:postcode": "44907",
    "addr:street": "Lexington Ave",
    "iso:country": "US",
    "sg:address": "1356 Lexington Ave",
    "sg:city": "Mansfield",
    "sg:classifiers": [
      {
        "category": "Insurance",
        "subcategory": "Insurance Agent",
        "type": "Services"
      },
      {
        "category": "Insurance",
        "subcategory": "Hazard Insurance",
        "type": "Services"
      }
    ],
    "sg:phone": "+1 419 526 4700",
    "sg:postcode": "44907",
    "sg:province": "OH",
    "sg:tags": [
      "auto",
      "recreational",
      "motorcycle",
      "vehicle",
      "marine",
      "boat"
    ],
    "sg:website": "http://www.hamiltonins.net",
    "wof:name": "Hamilton Insurance Services, Inc.",
    "wof:placetype": "venue"
  },
  "geometry": {"coordinates":[-82.543764,40.721159],"type":"Point"}
}
