{
  "type": "Feature",
  "properties": {
    "addr:full": "4067 Round Bottom Rd Cincinnati OH 45244",
    "addr:housenumber": "4067",
    "addr:postcode": "45244",
    "addr:street": "Round Bottom Rd",
    "iso:country": "US",
    "sg:address": "4067 Round Bottom Rd",
    "sg:city": "Cincinnati",
    "sg:classifiers": [
      {
        "category": "Building \u0026 Trades",
        "subcategory": "Electrical",
        "type": "Services"
      },
      {
        "category": "Wholesale",
        "subcategory": "Electrical",
        "type": "Manufacturing \u0026 Wholesale Goods"
      }
    ],
    "sg:phone": "+1 513 474 0380",
    "sg:postcode": "45244",
    "sg:province": "OH",
    "sg:tags": [
      "alarm",
      "custom",
      "burglar",
      "security",
      "system"
    ],
    "sg:website": "www.soundsecurityinc.com",
    "wof:name": "Sound Security Inc",
    "wof:placetype": "venue"
  },
  "geometry": {"coordinates":[-84.337487,39.133978],"type":"Point"}
}
