{
  "type": "Feature",
  "properties": {
    "iso:country":"US",
    "sg:address":"4067 Round Bottom Rd",
    "sg:city":"Cincinnati",
    "sg:classifiers":[
        {
            "category":"Building & Trades",
            "subcategory":"Electrical",
            "type":"Services"
        },
        {
            "category":"Wholesale",
            "subcategory":"Electrical",
            "type":"Manufacturing & Wholesale Goods"
        }
    ],
    "sg:phone":"+1 513 474 0380",
    "sg:postcode":"45244",
    "sg:province":"OH",
    "sg:tags":[
        "alarm",
        "custom",
        "burglar",
        "security",
        "system"
    ],
    "sg:website":"www.soundsecurityinc.com",
    "wof:name":"Sound Security Inc",
    "wof:placetype":"venue"
},
  "geometry": {"coordinates":[-84.337487,39.133978],"type":"Point"}
}