{
  "type": "Feature",
  "properties": {
    "iso:country":"US",
    "sg:address":"2891 State Rte 5",
    "sg:city":"Leavittsburg",
    "sg:classifiers":[
        {
            "category":"Banks & Credit Unions",
            "subcategory":"Bank",
            "type":"Services"
        }
    ],
    "sg:phone":"+1 330 898 3089",
    "sg:postcode":"44430",
    "sg:province":"OH",
    "sg:tags":[
        "machine",
        "teller",
        "automated"
    ],
    "wof:name":"ATMUSALLC",
    "wof:placetype":"venue"
},
  "geometry": {"coordinates":[-80.90611199999999,41.229769],"type":"Point"}
}