{
  "type": "Feature",
  "properties": {
    "addr:full": "5137 Wayne Trace Rd Hamilton OH 45011",
    "addr:housenumber": "5137",
    "addr:postcode": "45011",
    "addr:street": "Wayne Trace Rd",
    "iso:country": "US",
    "sg:address": "5137 Wayne Trace Rd",
    "sg:city": "Hamilton",
    "sg:classifiers": [
      {
        "category": "Shopping",
        "subcategory": "Used Merchandise",
        "type": "Retail Goods"
      }
    ],
    "sg:phone": "+1 513 726 5496",
    "sg:postcode": "45011",
    "sg:province": "OH",
    "sg:tags": [
      "antique"
    ],
    "wof:name": "1848 House Antique",
    "wof:placetype": "venue"
  },
  "geometry": {"coordinates":[-84.571494,39.516664],"type":"Point"}
}
