{
  "type": "Feature",
  "properties": {
    "iso:country":"US",
    "sg:address":"1423 W 64th St",
    "sg:city":"Ashtabula",
    "sg:classifiers":[
        {
            "category":"Banks & Credit Unions",
            "subcategory":"Financial Services",
            "type":"Services"
        }
    ],
    "sg:phone":"+1 440 997 2485",
    "sg:postcode":"44004",
    "sg:province":"OH",
    "sg:tags":[
        "trust",
        "management"
    ],
    "wof:name":"Quinn Family Revocable Trust",
    "wof:placetype":"venue"
},
  "geometry": {"coordinates":[-80.798448,41.846753],"type":"Point"}
}