{
  "type": "Feature",
  "properties": {
    "iso:country":"US",
    "sg:address":"1724 Northwest Blvd",
    "sg:city":"Columbus",
    "sg:classifiers":[
        {
            "category":"Personal",
            "subcategory":"Beauty Salon",
            "type":"Services"
        }
    ],
    "sg:phone":"+1 614 488 6010",
    "sg:postcode":"43212",
    "sg:province":"OH",
    "sg:tags":[
        "manicuring"
    ],
    "wof:name":"Nailtique",
    "wof:placetype":"venue"
},
  "geometry": {"coordinates":[-83.04084400000001,39.992546],"type":"Point"}
}