{
  "type": "Feature",
  "properties": {
    "addr:full": "2515 Twp Hwy 36 Mount Cory OH 45868",
    "addr:housenumber": "2515",
    "addr:postcode": "45868",
    "addr:street": "Twp Hwy 36 Mount",
    "iso:country": "US",
    "sg:address": "2515 Twp Hwy 36",
    "sg:city": "Mount Cory",
    "sg:classifiers": [
      {
        "category": "Retail",
        "subcategory": "Repair Shop",
        "type": "Services"
      }
    ],
    "sg:phone": "+1 419 477 5332",
    "sg:postcode": "45868",
    "sg:province": "OH",
    "sg:tags": [
      "fluid",
      "power",
      "mfg"
    ],
    "wof:name": "D N C Hydraulic Service",
    "wof:placetype": "venue"
  },
  "geometry": {"coordinates":[-83.832301,40.929253],"type":"Point"}
}
