{
  "type": "Feature",
  "properties": {
    "iso:country":"US",
    "sg:address":"4275 Lincoln Way W",
    "sg:city":"Massillon",
    "sg:classifiers":[
        {
            "category":"Organizations",
            "subcategory":"Religious Organization",
            "type":"Services"
        }
    ],
    "sg:phone":"+1 330 832 5263",
    "sg:postcode":"44647",
    "sg:province":"OH",
    "sg:website":"www.htlcmassillon.org",
    "wof:name":"Holy Trinity Lutheran Church",
    "wof:placetype":"venue"
},
  "geometry": {"coordinates":[-81.57334,40.795932],"type":"Point"}
}