{
  "type": "Feature",
  "properties": {
    "iso:country":"US",
    "sg:address":"19607 US Hwy 20A",
    "sg:city":"Wauseon",
    "sg:phone":"+1 419 445 5007",
    "sg:postcode":"43567",
    "sg:province":"OH",
    "sg:tags":[
        "farm",
        "corn",
        "soybean"
    ],
    "wof:name":"Wyse Family Farm",
    "wof:placetype":"venue"
},
  "geometry": {"coordinates":[-84.24118300000001,41.572487],"type":"Point"}
}