{
  "type": "Feature",
  "properties": {
    "addr:full":"9410 Farmcourt Ln Loveland OH 45140",
    "addr:housenumber":"9410",
    "addr:postcode":"45140",
    "addr:street":"Farmcourt Ln",
    "iso:country":"US",
    "sg:address":"9410 Farmcourt Ln",
    "sg:city":"Loveland",
    "sg:classifiers":[
        {
            "category":"Manufacturing",
            "subcategory":"Printing",
            "type":"Manufacturing & Wholesale Goods"
        }
    ],
    "sg:phone":"+1 513 295 0464",
    "sg:postcode":"45140",
    "sg:province":"OH",
    "sg:tags":[
        "publisher"
    ],
    "sg:website":"www.longestraid.com",
    "wof:name":"Farmcourt Publishing Inc",
    "wof:placetype":"venue"
},
  "geometry": {"coordinates":[-84.303766,39.240695],"type":"Point"}
}