{
  "type": "Feature",
  "properties": {
    "addr:full": "5959 Lambert Rd Orient OH 43123",
    "addr:housenumber": "5959",
    "addr:postcode": "43123",
    "addr:street": "Lambert Rd",
    "iso:country": "US",
    "sg:address": "5959 Lambert Rd",
    "sg:city": "Orient",
    "sg:classifiers": [
      {
        "category": "Home \u0026 Garden",
        "subcategory": "Garden Supply",
        "type": "Retail Goods"
      }
    ],
    "sg:phone": "+1 614 877 4551",
    "sg:postcode": "43123",
    "sg:province": "OH",
    "sg:tags": [
      "plant",
      "bedding",
      "greenhouse"
    ],
    "wof:name": "Ehmanns Greenhouse",
    "wof:placetype": "venue"
  },
  "geometry": {"coordinates":[-83.162623,39.834904],"type":"Point"}
}
