{
  "type": "Feature",
  "properties": {
    "addr:full":"28013 Osborn Rd Bay Village OH 44140",
    "addr:housenumber":"28013",
    "addr:postcode":"44140",
    "addr:street":"Osborn Rd",
    "iso:country":"US",
    "sg:address":"28013 Osborn Rd",
    "sg:city":"Bay Village",
    "sg:classifiers":[
        {
            "category":"Building & Trades",
            "subcategory":"Construction",
            "type":"Services"
        }
    ],
    "sg:phone":"+1 440 835 2269",
    "sg:postcode":"44140",
    "sg:province":"OH",
    "sg:tags":[
        "house",
        "carpentry",
        "contractor"
    ],
    "wof:name":"Kerver Company",
    "wof:placetype":"venue"
},
  "geometry": {"coordinates":[-81.929424,41.482103],"type":"Point"}
}