{
  "type": "Feature",
  "properties": {
    "iso:country":"US",
    "sg:address":"6572 State Rte 47",
    "sg:city":"Versailles",
    "sg:classifiers":[
        {
            "category":"Manufacturing",
            "subcategory":"Food",
            "type":"Manufacturing & Wholesale Goods"
        }
    ],
    "sg:phone":"+1 937 526 3232",
    "sg:postcode":"45380",
    "sg:province":"OH",
    "sg:tags":[
        "winery",
        "mfg"
    ],
    "wof:name":"Winery At Versailles",
    "wof:placetype":"venue"
},
  "geometry": {"coordinates":[-84.56877299999999,40.223918],"type":"Point"}
}