{
  "type": "Feature",
  "properties": {
    "addr:full": "6572 State Rte 47 Versailles OH 45380",
    "addr:housenumber": "6572",
    "addr:postcode": "45380",
    "addr:street": "State Rte 47",
    "iso:country": "US",
    "sg:address": "6572 State Rte 47",
    "sg:city": "Versailles",
    "sg:classifiers": [
      {
        "category": "Manufacturing",
        "subcategory": "Food",
        "type": "Manufacturing \u0026 Wholesale Goods"
      }
    ],
    "sg:phone": "+1 937 526 3232",
    "sg:postcode": "45380",
    "sg:province": "OH",
    "sg:tags": [
      "winery",
      "mfg"
    ],
    "wof:name": "Winery At Versailles",
    "wof:placetype": "venue"
  },
  "geometry": {"coordinates":[-84.568773,40.223918],"type":"Point"}
}
