{
  "type": "Feature",
  "properties": {
    "iso:country":"US",
    "sg:address":"2215 E Waterloo Rd",
    "sg:city":"Akron",
    "sg:classifiers":[
        {
            "category":"Professional",
            "subcategory":"Lawyer & Legal Services",
            "type":"Services"
        }
    ],
    "sg:phone":"+1 330 252 9950",
    "sg:postcode":"44312",
    "sg:province":"OH",
    "sg:tags":[
        "attorney"
    ],
    "wof:name":"Larry Shenise",
    "wof:placetype":"venue"
},
  "geometry": {"coordinates":[-81.44736399999999,41.034621],"type":"Point"}
}