{
  "type": "Feature",
  "properties": {
    "addr:full": "2215 E Waterloo Rd Akron OH 44312",
    "addr:housenumber": "2215",
    "addr:postcode": "44312",
    "addr:street": "E Waterloo Rd",
    "iso:country": "US",
    "sg:address": "2215 E Waterloo Rd",
    "sg:city": "Akron",
    "sg:classifiers": [
      {
        "category": "Professional",
        "subcategory": "Lawyer \u0026 Legal Services",
        "type": "Services"
      }
    ],
    "sg:phone": "+1 330 252 9950",
    "sg:postcode": "44312",
    "sg:province": "OH",
    "sg:tags": [
      "attorney"
    ],
    "wof:name": "Larry Shenise",
    "wof:placetype": "venue"
  },
  "geometry": {"coordinates":[-81.447364,41.034621],"type":"Point"}
}
