{
  "type": "Feature",
  "properties": {
    "addr:full": "8855 Co Rd K Delta OH 43515",
    "addr:housenumber": "8855",
    "addr:postcode": "43515",
    "addr:street": "Co Rd",
    "iso:country": "US",
    "sg:address": "8855 Co Rd K",
    "sg:city": "Delta",
    "sg:classifiers": [
      {
        "category": "Organizations",
        "subcategory": "Religious Organization",
        "type": "Services"
      }
    ],
    "sg:phone": "+1 419 822 3086",
    "sg:postcode": "43515",
    "sg:province": "OH",
    "sg:tags": [
      "church"
    ],
    "wof:name": "Liberty Center Baptist Church",
    "wof:placetype": "venue"
  },
  "geometry": {"coordinates":[-84.033885,41.617843],"type":"Point"}
}
