{
  "type": "Feature",
  "properties": {
    "addr:full": "5405 Avion Park Dr Cleveland OH 44143",
    "addr:housenumber": "5405",
    "addr:postcode": "44143",
    "addr:street": "Avion Park Dr",
    "iso:country": "US",
    "sg:address": "5405 Avion Park Dr",
    "sg:city": "Cleveland",
    "sg:classifiers": [
      {
        "category": "Manufacturing",
        "subcategory": "Tools \u0026 Machinery",
        "type": "Manufacturing \u0026 Wholesale Goods"
      }
    ],
    "sg:phone": "+1 440 461 1443",
    "sg:postcode": "44143",
    "sg:province": "OH",
    "sg:tags": [
      "machine",
      "shop"
    ],
    "wof:name": "Masco Machine Inc",
    "wof:placetype": "venue"
  },
  "geometry": {"coordinates":[-81.482576,41.559542],"type":"Point"}
}
