{
  "type": "Feature",
  "properties": {
    "iso:country":"US",
    "sg:address":"756 River Rd",
    "sg:city":"Huron",
    "sg:phone":"+1 419 433 4856",
    "sg:postcode":"44839",
    "sg:province":"OH",
    "sg:tags":[
        "farm",
        "corn",
        "soybean"
    ],
    "wof:name":"Enderle Berry Farm",
    "wof:placetype":"venue"
},
  "geometry": {"coordinates":[-82.547228,41.378701],"type":"Point"}
}