{
  "type": "Feature",
  "properties": {
    "addr:full":"2272 Eaton Gettysburg Rd Eaton OH 45320",
    "addr:housenumber":"2272",
    "addr:postcode":"45320",
    "addr:street":"Eaton Gettysburg Rd",
    "iso:country":"US",
    "sg:address":"2272 Eaton Gettysburg Rd",
    "sg:city":"Eaton",
    "sg:classifiers":[
        {
            "category":"Personal",
            "subcategory":"Beauty Salon",
            "type":"Services"
        }
    ],
    "sg:phone":"+1 937 456 3131",
    "sg:postcode":"45320",
    "sg:province":"OH",
    "wof:name":"Carol's Hairstyling Studio",
    "wof:placetype":"venue"
},
  "geometry": {"coordinates":[-84.654612,39.771861],"type":"Point"}
}