{
  "type": "Feature",
  "properties": {
    "addr:full":"2269 Bennington Dr Mansfield OH 44904",
    "addr:housenumber":"2269",
    "addr:postcode":"44904",
    "addr:street":"Bennington Dr",
    "iso:country":"US",
    "sg:address":"2269 Bennington Dr",
    "sg:city":"Mansfield",
    "sg:phone":"+1 419 756 3621",
    "sg:postcode":"44904",
    "sg:province":"OH",
    "sg:tags":[
        "farm",
        "corn"
    ],
    "wof:name":"Tom Wapner",
    "wof:placetype":"venue"
},
  "geometry": {"coordinates":[-82.537792,40.697377],"type":"Point"}
}