{
  "type": "Feature",
  "properties": {
    "addr:full":"761 E Main St Columbus OH 43205",
    "addr:housenumber":"761",
    "addr:postcode":"43205",
    "addr:street":"E Main St",
    "iso:country":"US",
    "sg:address":"761 E Main St",
    "sg:city":"Columbus",
    "sg:classifiers":[
        {
            "category":"Professional",
            "subcategory":"Employment Agencies",
            "type":"Services"
        }
    ],
    "sg:phone":"+1 614 258 6712",
    "sg:postcode":"43205",
    "sg:province":"OH",
    "sg:tags":[
        "opportunity"
    ],
    "wof:name":"T Grooms & Assoc Inc",
    "wof:placetype":"venue"
},
  "geometry": {"coordinates":[-82.98163099999999,39.958008],"type":"Point"}
}