{
  "type": "Feature",
  "properties": {
    "iso:country":"US",
    "sg:address":"3000 Park Ave W",
    "sg:city":"Mansfield",
    "sg:classifiers":[
        {
            "category":"Building & Trades",
            "subcategory":"Construction",
            "type":"Services"
        }
    ],
    "sg:phone":"+1 419 529 5958",
    "sg:postcode":"44906",
    "sg:province":"OH",
    "sg:tags":[
        "contractor"
    ],
    "wof:name":"Mc Fadden Building Svc",
    "wof:placetype":"venue"
},
  "geometry": {"coordinates":[-82.624311,40.760215],"type":"Point"}
}