{
  "type": "Feature",
  "properties": {
    "addr:full":"2394 Briers Dr Columbus OH 43209",
    "addr:housenumber":"2394",
    "addr:postcode":"43209",
    "addr:street":"Briers Dr",
    "iso:country":"US",
    "sg:address":"2394 Briers Dr",
    "sg:city":"Columbus",
    "sg:classifiers":[
        {
            "category":"Building & Trades",
            "subcategory":"Electrical",
            "type":"Services"
        }
    ],
    "sg:phone":"+1 614 235 5267",
    "sg:postcode":"43209",
    "sg:province":"OH",
    "sg:tags":[
        "electrical",
        "contractor"
    ],
    "wof:name":"Jgl Communications",
    "wof:placetype":"venue"
},
  "geometry": {"coordinates":[-82.929236,39.927713],"type":"Point"}
}