{
  "type": "Feature",
  "properties": {
    "iso:country":"US",
    "sg:address":"11355 Swing Rd",
    "sg:city":"Cincinnati",
    "sg:classifiers":[
        {
            "category":"Sports & Exercise",
            "subcategory":"Golf",
            "type":"Entertainment"
        }
    ],
    "sg:phone":"+1 513 769 4325",
    "sg:postcode":"45241",
    "sg:province":"OH",
    "sg:tags":[
        "course"
    ],
    "sg:website":"www.greatparks.org",
    "wof:name":"Sharon Woods",
    "wof:placetype":"venue"
},
  "geometry": {"coordinates":[-84.38796499999999,39.273674],"type":"Point"}
}