{
  "type": "Feature",
  "properties": {
    "addr:full": "124 S 5th St Steubenville OH 43952",
    "addr:housenumber": "124",
    "addr:postcode": "43952",
    "addr:street": "S 5Th St",
    "iso:country": "US",
    "sg:address": "124 S 5th St",
    "sg:city": "Steubenville",
    "sg:classifiers": [
      {
        "category": "Professional",
        "type": "Services"
      }
    ],
    "sg:phone": "+1 740 283 5900",
    "sg:postcode": "43952",
    "sg:province": "OH",
    "sg:tags": [
      "establishment"
    ],
    "wof:name": "Brigadoon Com",
    "wof:placetype": "venue"
  },
  "geometry": {"coordinates":[-80.617246,40.358732],"type":"Point"}
}
