{
  "type": "Feature",
  "properties": {
    "iso:country":"US",
    "sg:address":"30500 Fairmount Blvd",
    "sg:city":"Cleveland",
    "sg:classifiers":[
        {
            "category":"Organizations",
            "subcategory":"Religious Organization",
            "type":"Services"
        }
    ],
    "sg:phone":"+1 440 605 9459",
    "sg:postcode":"44124",
    "sg:province":"OH",
    "sg:tags":[
        "church"
    ],
    "wof:name":"Korean American Presbyterian",
    "wof:placetype":"venue"
},
  "geometry": {"coordinates":[-81.45478199999999,41.491921],"type":"Point"}
}