{
  "type": "Feature",
  "properties": {
    "addr:full": "166 8th Ave Tiffin OH 44883",
    "addr:housenumber": "166",
    "addr:postcode": "44883",
    "addr:street": "8Th Ave",
    "iso:country": "US",
    "sg:address": "166 8th Ave",
    "sg:city": "Tiffin",
    "sg:classifiers": [
      {
        "category": "Building \u0026 Trades",
        "subcategory": "Construction",
        "type": "Services"
      }
    ],
    "sg:phone": "+1 419 447 3148",
    "sg:postcode": "44883",
    "sg:province": "OH",
    "sg:tags": [
      "hanging",
      "contractor"
    ],
    "wof:name": "Marks Painting",
    "wof:placetype": "venue"
  },
  "geometry": {"coordinates":[-83.181979,41.133898],"type":"Point"}
}
