{
  "type": "Feature",
  "properties": {
    "addr:full":"1289 E Dublin Granville Rd Columbus OH 43229",
    "addr:housenumber":"1289",
    "addr:postcode":"43229",
    "addr:street":"E Dublin Granville Rd",
    "iso:country":"US",
    "sg:address":"1289 E Dublin Granville Rd",
    "sg:city":"Columbus",
    "sg:classifiers":[
        {
            "category":"Travel",
            "subcategory":"Hotels & Motels",
            "type":"Entertainment"
        }
    ],
    "sg:phone":"+1 614 846 9860",
    "sg:postcode":"43229",
    "sg:province":"OH",
    "sg:tags":[
        "operation"
    ],
    "wof:name":"Motel 6",
    "wof:placetype":"venue"
},
  "geometry": {"coordinates":[-82.981179,40.087339],"type":"Point"}
}