{
  "type": "Feature",
  "properties": {
    "iso:country":"US",
    "sg:address":"5929 Stillwell Rd",
    "sg:city":"Oxford",
    "sg:classifiers":[
        {
            "category":"Insurance",
            "subcategory":"Insurance Agent",
            "type":"Services"
        }
    ],
    "sg:phone":"+1 513 756 0700",
    "sg:postcode":"45056",
    "sg:province":"OH",
    "wof:name":"Trinity Insurance Ctr",
    "wof:placetype":"venue"
},
  "geometry": {"coordinates":[-84.752311,39.434778],"type":"Point"}
}