{
  "type": "Feature",
  "properties": {
    "addr:full": "3673 Jessup Rd Cincinnati OH 45247",
    "addr:housenumber": "3673",
    "addr:postcode": "45247",
    "addr:street": "Jessup Rd",
    "iso:country": "US",
    "sg:address": "3673 Jessup Rd",
    "sg:city": "Cincinnati",
    "sg:classifiers": [
      {
        "category": "Building \u0026 Trades",
        "subcategory": "Construction",
        "type": "Services"
      }
    ],
    "sg:phone": "+1 513 385 2178",
    "sg:postcode": "45247",
    "sg:province": "OH",
    "sg:tags": [
      "siding",
      "contractor"
    ],
    "wof:name": "Bleh Siding Company",
    "wof:placetype": "venue"
  },
  "geometry": {"coordinates":[-84.604202,39.1988],"type":"Point"}
}
