{
  "type": "Feature",
  "properties": {
    "iso:country":"US",
    "sg:address":"3673 Jessup Rd",
    "sg:city":"Cincinnati",
    "sg:classifiers":[
        {
            "category":"Building & Trades",
            "subcategory":"Construction",
            "type":"Services"
        }
    ],
    "sg:phone":"+1 513 385 2178",
    "sg:postcode":"45247",
    "sg:province":"OH",
    "sg:tags":[
        "siding",
        "contractor"
    ],
    "wof:name":"Bleh Siding Company",
    "wof:placetype":"venue"
},
  "geometry": {"coordinates":[-84.604202,39.1988],"type":"Point"}
}