{
  "type": "Feature",
  "properties": {
    "addr:full": "3333 Manchester Rd Akron OH 44319",
    "addr:housenumber": "3333",
    "addr:postcode": "44319",
    "addr:street": "Manchester Rd",
    "iso:country": "US",
    "sg:address": "3333 Manchester Rd",
    "sg:city": "Akron",
    "sg:classifiers": [
      {
        "category": "Professional",
        "subcategory": "Management \u0026 Consulting",
        "type": "Services"
      }
    ],
    "sg:phone": "+1 330 644 4688",
    "sg:postcode": "44319",
    "sg:province": "OH",
    "sg:tags": [
      "consultant",
      "educational"
    ],
    "wof:name": "Tutor Hut",
    "wof:placetype": "venue"
  },
  "geometry": {"coordinates":[-81.554826,41.009923],"type":"Point"}
}
