{
  "type": "Feature",
  "properties": {
    "addr:full": "1151 Chase Ave Hamilton OH 45015",
    "addr:housenumber": "1151",
    "addr:postcode": "45015",
    "addr:street": "Chase Ave",
    "iso:country": "US",
    "sg:address": "1151 Chase Ave",
    "sg:city": "Hamilton",
    "sg:classifiers": [
      {
        "category": "Shopping",
        "type": "Retail Goods"
      }
    ],
    "sg:phone": "+1 513 868 9699",
    "sg:postcode": "45015",
    "sg:province": "OH",
    "sg:tags": [
      "repair",
      "electrical",
      "merchandise",
      "se"
    ],
    "wof:name": "Hearing Aid Care",
    "wof:placetype": "venue"
  },
  "geometry": {"coordinates":[-84.548639,39.364215],"type":"Point"}
}
