{
  "type": "Feature",
  "properties": {
    "addr:full": "236 New Towne Square Dr Toledo OH 43612",
    "addr:housenumber": "236",
    "addr:postcode": "43612",
    "addr:street": "New Towne Square Dr",
    "iso:country": "US",
    "sg:address": "236 New Towne Square Dr",
    "sg:city": "Toledo",
    "sg:classifiers": [
      {
        "category": "Manufacturing",
        "subcategory": "Wood Products",
        "type": "Manufacturing \u0026 Wholesale Goods"
      }
    ],
    "sg:phone": "+1 419 269 3963",
    "sg:postcode": "43612",
    "sg:province": "OH",
    "sg:tags": [
      "line",
      "clothes",
      "supply"
    ],
    "wof:name": "Dyme AUC",
    "wof:placetype": "venue"
  },
  "geometry": {"coordinates":[-83.544064,41.723297],"type":"Point"}
}
