{
  "type": "Feature",
  "properties": {
    "addr:full":"8441 Main St Kinsman OH 44428",
    "addr:housenumber":"8441",
    "addr:postcode":"44428",
    "addr:street":"Main St",
    "iso:country":"US",
    "sg:address":"8441 Main St",
    "sg:city":"Kinsman",
    "sg:classifiers":[
        {
            "category":"Health Services",
            "subcategory":"Doctor",
            "type":"Services"
        }
    ],
    "sg:phone":"+1 330 876 3981",
    "sg:postcode":"44428",
    "sg:province":"OH",
    "sg:tags":[
        "dentist"
    ],
    "wof:name":"Donald J Chionchio Inc",
    "wof:placetype":"venue"
},
  "geometry": {"coordinates":[-80.58363199999999,41.449885],"type":"Point"}
}