{
  "type": "Feature",
  "properties": {
    "addr:full": "1981 Riverside Dr Columbus OH 43221",
    "addr:housenumber": "1981",
    "addr:postcode": "43221",
    "addr:street": "Riverside Dr",
    "iso:country": "US",
    "sg:address": "1981 Riverside Dr",
    "sg:city": "Columbus",
    "sg:classifiers": [
      {
        "category": "Restaurant",
        "type": "Food \u0026 Drink"
      }
    ],
    "sg:menulink": "http://www.allmenus.com/oh/upper-arlington/134267-subway/menu/",
    "sg:phone": "+1 614 488 7827",
    "sg:postcode": "43221",
    "sg:province": "OH",
    "sg:tags": [
      "american",
      "sandwich"
    ],
    "wof:name": "Subway",
    "wof:placetype": "venue"
  },
  "geometry": {"coordinates":[-83.071988,39.995112],"type":"Point"}
}
