{
  "type": "Feature",
  "properties": {
    "addr:full":"4411 Louisville St NE Canton OH 44705",
    "addr:housenumber":"4411",
    "addr:postcode":"44705",
    "addr:street":"Louisville St Ne",
    "iso:country":"US",
    "sg:address":"4411 Louisville St NE",
    "sg:city":"Canton",
    "sg:classifiers":[
        {
            "category":"Manufacturing",
            "subcategory":"Tools & Machinery",
            "type":"Manufacturing & Wholesale Goods"
        }
    ],
    "sg:phone":"+1 330 453 3441",
    "sg:postcode":"44705",
    "sg:province":"OH",
    "sg:tags":[
        "foundry",
        "aluminum",
        "mfg"
    ],
    "wof:name":"Anchor Foundry & Machine Inc",
    "wof:placetype":"venue"
},
  "geometry": {"coordinates":[-81.31121899999999,40.825525],"type":"Point"}
}