{
  "type": "Feature",
  "properties": {
    "iso:country":"US",
    "sg:address":"2241 Lake Ave",
    "sg:city":"Ashtabula",
    "sg:classifiers":[
        {
            "category":"Health Services",
            "subcategory":"Health Practitioner",
            "type":"Services"
        }
    ],
    "sg:phone":"+1 440 998 0033",
    "sg:postcode":"44004",
    "sg:province":"OH",
    "sg:tags":[
        "therapist",
        "physical"
    ],
    "wof:name":"Center For Health Enhancement",
    "wof:placetype":"venue"
},
  "geometry": {"coordinates":[-80.798389,41.881882],"type":"Point"}
}