{
  "type": "Feature",
  "properties": {
    "addr:full":"2273 Picket Post Ln Columbus OH 43220",
    "addr:housenumber":"2273",
    "addr:postcode":"43220",
    "addr:street":"Picket Post Ln",
    "iso:country":"US",
    "sg:address":"2273 Picket Post Ln",
    "sg:city":"Columbus",
    "sg:classifiers":[
        {
            "category":"Shopping",
            "subcategory":"Clothing, Apparel, & Fashions",
            "type":"Retail Goods"
        }
    ],
    "sg:phone":"+1 614 457 9598",
    "sg:postcode":"43220",
    "sg:province":"OH",
    "wof:name":"AK Cachet",
    "wof:placetype":"venue"
},
  "geometry": {"coordinates":[-83.081187,40.050673],"type":"Point"}
}