{
  "type": "Feature",
  "properties": {
    "addr:full": "6209 Gender Rd Canal Winchester OH 43110",
    "addr:housenumber": "6209",
    "addr:postcode": "43110",
    "addr:street": "Gender Rd",
    "iso:country": "US",
    "sg:address": "6209 Gender Rd",
    "sg:city": "Canal Winchester",
    "sg:classifiers": [
      {
        "category": "Personal",
        "subcategory": "Beauty Salon",
        "type": "Services"
      }
    ],
    "sg:phone": "+1 614 834 1464",
    "sg:postcode": "43110",
    "sg:province": "OH",
    "wof:name": "Saturday's Family Hair Care",
    "wof:placetype": "venue"
  },
  "geometry": {"coordinates":[-82.828274,39.855145],"type":"Point"}
}
