{
  "type": "Feature",
  "properties": {
    "addr:full": "3565 Urbana Rd Springfield OH 45502",
    "addr:housenumber": "3565",
    "addr:postcode": "45502",
    "addr:street": "Urbana Rd",
    "iso:country": "US",
    "sg:address": "3565 Urbana Rd",
    "sg:city": "Springfield",
    "sg:classifiers": [
      {
        "category": "Freight",
        "type": "Transportation"
      }
    ],
    "sg:phone": "+1 937 399 7403",
    "sg:postcode": "45502",
    "sg:province": "OH",
    "sg:tags": [
      "management",
      "special",
      "warehousing"
    ],
    "wof:name": "Key \u0026 Lock Mini Warehouse",
    "wof:placetype": "venue"
  },
  "geometry": {"coordinates":[-83.806708,39.980854],"type":"Point"}
}
