{
  "type": "Feature",
  "properties": {
    "iso:country":"US",
    "sg:address":"1761 E Ohio Pike",
    "sg:city":"Amelia",
    "sg:classifiers":[
        {
            "category":"Banks & Credit Unions",
            "subcategory":"Bank",
            "type":"Services"
        }
    ],
    "sg:phone":"+1 513 797 1600",
    "sg:postcode":"45102",
    "sg:province":"OH",
    "sg:tags":[
        "cashing",
        "check"
    ],
    "wof:name":"Checksmart",
    "wof:placetype":"venue"
},
  "geometry": {"coordinates":[-84.20311,39.019265],"type":"Point"}
}