{
  "type": "Feature",
  "properties": {
    "addr:full": "6440 Norwalk Rd Medina OH 44256",
    "addr:housenumber": "6440",
    "addr:postcode": "44256",
    "addr:street": "Norwalk Rd",
    "iso:country": "US",
    "sg:address": "6440 Norwalk Rd",
    "sg:city": "Medina",
    "sg:classifiers": [
      {
        "category": "Home \u0026 Garden",
        "subcategory": "Carpets \u0026 Floor Coverings",
        "type": "Retail Goods"
      }
    ],
    "sg:phone": "+1 330 722 0903",
    "sg:postcode": "44256",
    "sg:province": "OH",
    "sg:tags": [
      "installation",
      "rug",
      "dealer"
    ],
    "wof:name": "Miller's Carpet \u0026 Vinyl Svc",
    "wof:placetype": "venue"
  },
  "geometry": {"coordinates":[-81.911681,41.159784],"type":"Point"}
}
