{
  "type": "Feature",
  "properties": {
    "addr:full": "201 S Main St West Milton OH 45383",
    "addr:housenumber": "201",
    "addr:postcode": "45383",
    "addr:street": "S Main St West",
    "iso:country": "US",
    "sg:address": "201 S Main St",
    "sg:city": "West Milton",
    "sg:classifiers": [
      {
        "category": "Organizations",
        "subcategory": "Religious Organization",
        "type": "Services"
      }
    ],
    "sg:phone": "+1 937 698 4401",
    "sg:postcode": "45383",
    "sg:province": "OH",
    "sg:tags": [
      "church"
    ],
    "wof:name": "Hoffman United Methodist Chr",
    "wof:placetype": "venue"
  },
  "geometry": {"coordinates":[-84.328288,39.959731],"type":"Point"}
}
