{
  "type": "Feature",
  "properties": {
    "iso:country":"US",
    "sg:address":"3100 State Rd",
    "sg:city":"Cuyahoga Falls",
    "sg:classifiers":[
        {
            "category":"Social Services",
            "subcategory":"Child Care",
            "type":"Services"
        }
    ],
    "sg:phone":"+1 330 923 1700",
    "sg:postcode":"44223",
    "sg:province":"OH",
    "sg:tags":[
        "day"
    ],
    "wof:name":"Kindercare Child Care Network",
    "wof:placetype":"venue"
},
  "geometry": {"coordinates":[-81.51035899999999,41.154937],"type":"Point"}
}