{
  "type": "Feature",
  "properties": {
    "addr:full": "3100 State Rd Cuyahoga Falls OH 44223",
    "addr:housenumber": "3100",
    "addr:postcode": "44223",
    "addr:street": "State Rd",
    "iso:country": "US",
    "sg:address": "3100 State Rd",
    "sg:city": "Cuyahoga Falls",
    "sg:classifiers": [
      {
        "category": "Social Services",
        "subcategory": "Child Care",
        "type": "Services"
      }
    ],
    "sg:phone": "+1 330 923 1700",
    "sg:postcode": "44223",
    "sg:province": "OH",
    "sg:tags": [
      "day"
    ],
    "wof:name": "Kindercare Child Care Network",
    "wof:placetype": "venue"
  },
  "geometry": {"coordinates":[-81.510359,41.154937],"type":"Point"}
}
