{
  "type": "Feature",
  "properties": {
    "addr:full": "180 Pleasant Valley Rd NW Sugarcreek OH 44681",
    "addr:housenumber": "180",
    "addr:postcode": "44681",
    "addr:street": "Pleasant Valley Rd Nw",
    "iso:country": "US",
    "sg:address": "180 Pleasant Valley Rd NW",
    "sg:city": "Sugarcreek",
    "sg:classifiers": [
      {
        "category": "Building \u0026 Trades",
        "subcategory": "Construction",
        "type": "Services"
      }
    ],
    "sg:phone": "+1 330 878 5579",
    "sg:postcode": "44681",
    "sg:province": "OH",
    "sg:tags": [
      "concrete",
      "contractor"
    ],
    "wof:name": "Miller Bros Concrete",
    "wof:placetype": "venue"
  },
  "geometry": {"coordinates":[-81.637999,40.48307],"type":"Point"}
}
