{
  "type": "Feature",
  "properties": {
    "addr:full":"35 S Broad St Fairborn OH 45324",
    "addr:housenumber":"35",
    "addr:postcode":"45324",
    "addr:street":"S Broad St",
    "iso:country":"US",
    "sg:address":"35 S Broad St",
    "sg:city":"Fairborn",
    "sg:classifiers":[
        {
            "category":"Insurance",
            "subcategory":"Insurance Agent",
            "type":"Services"
        }
    ],
    "sg:phone":"+1 937 879 7077",
    "sg:postcode":"45324",
    "sg:province":"OH",
    "wof:name":"Wertz Insurance Group",
    "wof:placetype":"venue"
},
  "geometry": {"coordinates":[-84.027923,39.820106],"type":"Point"}
}