{
  "type": "Feature",
  "properties": {
    "addr:full":"5473 Oberlin Ave Lorain OH 44053",
    "addr:housenumber":"5473",
    "addr:postcode":"44053",
    "addr:street":"Oberlin Ave",
    "iso:country":"US",
    "sg:address":"5473 Oberlin Ave",
    "sg:city":"Lorain",
    "sg:classifiers":[
        {
            "category":"Building & Trades",
            "subcategory":"Construction",
            "type":"Services"
        }
    ],
    "sg:phone":"+1 440 282 7400",
    "sg:postcode":"44053",
    "sg:province":"OH",
    "sg:tags":[
        "shed",
        "utility"
    ],
    "wof:name":"Outdoor Store",
    "wof:placetype":"venue"
},
  "geometry": {"coordinates":[-82.18566300000001,41.418663],"type":"Point"}
}