{
  "type": "Feature",
  "properties": {
    "addr:full": "15737 US Hwy 36 Marysville OH 43040",
    "addr:housenumber": "15737",
    "addr:postcode": "43040",
    "addr:street": "Us Hwy 36",
    "iso:country": "US",
    "sg:address": "15737 US Hwy 36",
    "sg:city": "Marysville",
    "sg:classifiers": [
      {
        "category": "Restaurant",
        "type": "Food \u0026 Drink"
      }
    ],
    "sg:phone": "+1 937 642 3006",
    "sg:postcode": "43040",
    "sg:province": "OH",
    "sg:tags": [
      "eating"
    ],
    "wof:name": "First Choice Inc",
    "wof:placetype": "venue"
  },
  "geometry": {"coordinates":[-83.340849,40.24013],"type":"Point"}
}
