{
  "type": "Feature",
  "properties": {
    "iso:country":"US",
    "sg:address":"15737 US Hwy 36",
    "sg:city":"Marysville",
    "sg:classifiers":[
        {
            "category":"Restaurant",
            "type":"Food & Drink"
        }
    ],
    "sg:phone":"+1 937 642 3006",
    "sg:postcode":"43040",
    "sg:province":"OH",
    "sg:tags":[
        "eating"
    ],
    "wof:name":"First Choice Inc",
    "wof:placetype":"venue"
},
  "geometry": {"coordinates":[-83.34084900000001,40.24013],"type":"Point"}
}