{
  "type": "Feature",
  "properties": {
    "iso:country":"US",
    "sg:address":"1887 W Market St",
    "sg:city":"Akron",
    "sg:classifiers":[
        {
            "category":"Personal",
            "subcategory":"Beauty Salon",
            "type":"Services"
        }
    ],
    "sg:phone":"+1 330 869 9541",
    "sg:postcode":"44313",
    "sg:province":"OH",
    "sg:tags":[
        "manicuring"
    ],
    "wof:name":"Vo Nails",
    "wof:placetype":"venue"
},
  "geometry": {"coordinates":[-81.57642199999999,41.11274],"type":"Point"}
}