{
  "type": "Feature",
  "properties": {
    "addr:full": "1887 W Market St Akron OH 44313",
    "addr:housenumber": "1887",
    "addr:postcode": "44313",
    "addr:street": "W Market St",
    "iso:country": "US",
    "sg:address": "1887 W Market St",
    "sg:city": "Akron",
    "sg:classifiers": [
      {
        "category": "Personal",
        "subcategory": "Beauty Salon",
        "type": "Services"
      }
    ],
    "sg:phone": "+1 330 869 9541",
    "sg:postcode": "44313",
    "sg:province": "OH",
    "sg:tags": [
      "manicuring"
    ],
    "wof:name": "Vo Nails",
    "wof:placetype": "venue"
  },
  "geometry": {"coordinates":[-81.576422,41.11274],"type":"Point"}
}
