{
  "type": "Feature",
  "properties": {
    "addr:full": "1800 Plymouth Knoll Ave NW Massillon OH 44646",
    "addr:housenumber": "1800",
    "addr:postcode": "44646",
    "addr:street": "Plymouth Knoll Ave Nw",
    "iso:country": "US",
    "sg:address": "1800 Plymouth Knoll Ave NW",
    "sg:city": "Massillon",
    "sg:classifiers": [
      {
        "category": "Building \u0026 Trades",
        "subcategory": "Construction",
        "type": "Services"
      }
    ],
    "sg:phone": "+1 330 830 8655",
    "sg:postcode": "44646",
    "sg:province": "OH",
    "sg:tags": [
      "house"
    ],
    "wof:name": "Fink Construction Company",
    "wof:placetype": "venue"
  },
  "geometry": {"coordinates":[-81.480611,40.818674],"type":"Point"}
}
