{
  "type": "Feature",
  "properties": {
    "iso:country":"US",
    "sg:address":"33 S Saint Clair St",
    "sg:city":"Dayton",
    "sg:classifiers":[
        {
            "category":"Professional",
            "type":"Services"
        }
    ],
    "sg:phone":"+1 937 424 5452",
    "sg:postcode":"45402",
    "sg:province":"OH",
    "wof:name":"H David Clay Studio",
    "wof:placetype":"venue"
},
  "geometry": {"coordinates":[-84.188271,39.759843],"type":"Point"}
}