{
  "type": "Feature",
  "properties": {
    "addr:full": "2327 Quail Hollow Ln Sandusky OH 44870",
    "addr:housenumber": "2327",
    "addr:postcode": "44870",
    "addr:street": "Quail Hollow Ln",
    "iso:country": "US",
    "sg:address": "2327 Quail Hollow Ln",
    "sg:city": "Sandusky",
    "sg:classifiers": [
      {
        "category": "Professional",
        "type": "Services"
      }
    ],
    "sg:phone": "+1 419 626 6557",
    "sg:postcode": "44870",
    "sg:province": "OH",
    "wof:name": "Nathan \u0026 Madeline D Lich",
    "wof:placetype": "venue"
  },
  "geometry": {"coordinates":[-82.649162,41.409451],"type":"Point"}
}
