{
  "type": "Feature",
  "properties": {
    "addr:full": "211 S Wilson Dr West Union OH 45693",
    "addr:housenumber": "211",
    "addr:postcode": "45693",
    "addr:street": "S Wilson Dr West",
    "iso:country": "US",
    "sg:address": "211 S Wilson Dr",
    "sg:city": "West Union",
    "sg:classifiers": [
      {
        "category": "Social Services",
        "subcategory": "Job Training",
        "type": "Services"
      }
    ],
    "sg:phone": "+1 937 544 7500",
    "sg:postcode": "45693",
    "sg:province": "OH",
    "sg:tags": [
      "rehabilitation"
    ],
    "wof:name": "ADAMS County Hosp Rehab Ctr",
    "wof:placetype": "venue"
  },
  "geometry": {"coordinates":[-83.536952,38.792105],"type":"Point"}
}
