{
  "type": "Feature",
  "properties": {
    "addr:full":"378 Sylvia Dr Chardon OH 44024",
    "addr:housenumber":"378",
    "addr:postcode":"44024",
    "addr:street":"Sylvia Dr",
    "iso:country":"US",
    "sg:address":"378 Sylvia Dr",
    "sg:city":"Chardon",
    "sg:classifiers":[
        {
            "category":"Travel",
            "subcategory":"Travel Agent",
            "type":"Entertainment"
        }
    ],
    "sg:phone":"+1 440 285 4967",
    "sg:postcode":"44024",
    "sg:province":"OH",
    "sg:tags":[
        "agency",
        "bureau"
    ],
    "sg:website":"www.cruisevacationshop.com",
    "wof:name":"Cruise Planners",
    "wof:placetype":"venue"
},
  "geometry": {"coordinates":[-81.194705,41.578179],"type":"Point"}
}