{
  "type": "Feature",
  "properties": {
    "iso:country":"US",
    "sg:address":"960 S Washington St",
    "sg:city":"Millersburg",
    "sg:classifiers":[
        {
            "category":"Social Services",
            "subcategory":"Child Care",
            "type":"Services"
        }
    ],
    "sg:phone":"+1 330 674 9574",
    "sg:postcode":"44654",
    "sg:province":"OH",
    "sg:tags":[
        "day"
    ],
    "wof:name":"Little Tots Childcare Center",
    "wof:placetype":"venue"
},
  "geometry": {"coordinates":[-81.917466,40.546114],"type":"Point"}
}