{
  "type": "Feature",
  "properties": {
    "addr:full": "3910 Wabash Rd Fort Recovery OH 45846",
    "addr:housenumber": "3910",
    "addr:postcode": "45846",
    "addr:street": "Wabash Rd",
    "iso:country": "US",
    "sg:address": "3910 Wabash Rd",
    "sg:city": "Fort Recovery",
    "sg:classifiers": [
      {
        "category": "Freight",
        "type": "Transportation"
      }
    ],
    "sg:phone": "+1 419 375 4719",
    "sg:postcode": "45846",
    "sg:province": "OH",
    "sg:tags": [
      "distance",
      "long",
      "trucking"
    ],
    "wof:name": "Mike Ressner",
    "wof:placetype": "venue"
  },
  "geometry": {"coordinates":[-84.765126,40.464509],"type":"Point"}
}
