{
  "type": "Feature",
  "properties": {
    "addr:full":"206 Walden Ave Tiltonsville OH 43963",
    "addr:housenumber":"206",
    "addr:postcode":"43963",
    "addr:street":"Walden Ave",
    "iso:country":"US",
    "sg:address":"206 Walden Ave",
    "sg:city":"Tiltonsville",
    "sg:classifiers":[
        {
            "category":"Food & Beverages",
            "subcategory":"Groceries & Convenience Stores",
            "type":"Retail Goods"
        }
    ],
    "sg:phone":"+1 740 859 0318",
    "sg:postcode":"43963",
    "sg:province":"OH",
    "sg:tags":[
        "grocer"
    ],
    "wof:name":"Foodland",
    "wof:placetype":"venue"
},
  "geometry": {"coordinates":[-80.697678,40.170954],"type":"Point"}
}