{
  "type": "Feature",
  "properties": {
    "addr:full": "4282 Shenandoah Pkwy Brunswick OH 44212",
    "addr:housenumber": "4282",
    "addr:postcode": "44212",
    "addr:street": "Shenandoah Pkwy",
    "iso:country": "US",
    "sg:address": "4282 Shenandoah Pkwy",
    "sg:city": "Brunswick",
    "sg:classifiers": [
      {
        "category": "Bars \u0026 Pubs",
        "type": "Food \u0026 Drink"
      }
    ],
    "sg:phone": "+1 330 273 9999",
    "sg:postcode": "44212",
    "sg:province": "OH",
    "sg:tags": [
      "drinking"
    ],
    "wof:name": "Nikos Bar \u0026 Grill",
    "wof:placetype": "venue"
  },
  "geometry": {"coordinates":[-81.840161,41.24442],"type":"Point"}
}
