{
  "type": "Feature",
  "properties": {
    "iso:country":"US",
    "sg:address":"4282 Shenandoah Pkwy",
    "sg:city":"Brunswick",
    "sg:classifiers":[
        {
            "category":"Bars & Pubs",
            "type":"Food & Drink"
        }
    ],
    "sg:phone":"+1 330 273 9999",
    "sg:postcode":"44212",
    "sg:province":"OH",
    "sg:tags":[
        "drinking"
    ],
    "wof:name":"Nikos Bar & Grill",
    "wof:placetype":"venue"
},
  "geometry": {"coordinates":[-81.840161,41.24442],"type":"Point"}
}