{
  "type": "Feature",
  "properties": {
    "addr:full":"4168 Locust Ridge Dr Cleves OH 45002",
    "addr:housenumber":"4168",
    "addr:postcode":"45002",
    "addr:street":"Locust Ridge Dr",
    "iso:country":"US",
    "sg:address":"4168 Locust Ridge Dr",
    "sg:city":"Cleves",
    "sg:classifiers":[
        {
            "category":"Building & Trades",
            "subcategory":"Construction",
            "type":"Services"
        }
    ],
    "sg:phone":"+1 513 941 1917",
    "sg:postcode":"45002",
    "sg:province":"OH",
    "sg:tags":[
        "house"
    ],
    "wof:name":"Anthony J Obert",
    "wof:placetype":"venue"
},
  "geometry": {"coordinates":[-84.707989,39.17181],"type":"Point"}
}