{
  "type": "Feature",
  "properties": {
    "addr:full":"61 S Plains Rd The Plains OH 45780",
    "addr:housenumber":"61",
    "addr:postcode":"45780",
    "addr:street":"S Plains Rd",
    "iso:country":"US",
    "sg:address":"61 S Plains Rd",
    "sg:city":"The Plains",
    "sg:classifiers":[
        {
            "category":"Retail",
            "subcategory":"Self-service Laundry",
            "type":"Services"
        }
    ],
    "sg:phone":"+1 740 797 3139",
    "sg:postcode":"45780",
    "sg:province":"OH",
    "sg:tags":[
        "stone",
        "coin"
    ],
    "wof:name":"Laughlin's Laundromat",
    "wof:placetype":"venue"
},
  "geometry": {"coordinates":[-82.131199,39.365589],"type":"Point"}
}