{
  "type": "Feature",
  "properties": {
    "iso:country":"US",
    "sg:address":"1257 Linden Ave",
    "sg:city":"Zanesville",
    "sg:classifiers":[
        {
            "category":"Insurance",
            "subcategory":"Insurance Agent",
            "type":"Services"
        }
    ],
    "sg:phone":"+1 740 454 0171",
    "sg:postcode":"43701",
    "sg:province":"OH",
    "wof:name":"John Dudas Agency Inc",
    "wof:placetype":"venue"
},
  "geometry": {"coordinates":[-82.004829,39.95493],"type":"Point"}
}