{
  "type": "Feature",
  "properties": {
    "addr:full":"6265 Riverside Dr Dublin OH 43017",
    "addr:housenumber":"6265",
    "addr:postcode":"43017",
    "addr:street":"Riverside Dr",
    "iso:country":"US",
    "sg:address":"6265 Riverside Dr",
    "sg:city":"Dublin",
    "sg:classifiers":[
        {
            "category":"Professional",
            "subcategory":"Management & Consulting",
            "type":"Services"
        }
    ],
    "sg:phone":"+1 614 761 8484",
    "sg:postcode":"43017",
    "sg:province":"OH",
    "sg:tags":[
        "consultant",
        "hospital"
    ],
    "sg:website":"www.shbajo.com",
    "wof:name":"Smith Hager Bajo",
    "wof:placetype":"venue"
},
  "geometry": {"coordinates":[-83.10818,40.094695],"type":"Point"}
}