{
  "type": "Feature",
  "properties": {
    "iso:country":"US",
    "sg:address":"1814 Pearl Rd",
    "sg:city":"Brunswick",
    "sg:classifiers":[
        {
            "category":"Sports & Exercise",
            "subcategory":"Gym",
            "type":"Entertainment"
        }
    ],
    "sg:phone":"+1 330 558 0088",
    "sg:postcode":"44212",
    "sg:province":"OH",
    "sg:tags":[
        "club",
        "health",
        "studio",
        "gymnasium"
    ],
    "wof:name":"Curves",
    "wof:placetype":"venue"
},
  "geometry": {"coordinates":[-81.841517,41.22612],"type":"Point"}
}