{
  "type": "Feature",
  "properties": {
    "iso:country":"US",
    "sg:address":"950 Michigan Ave",
    "sg:city":"Columbus",
    "sg:classifiers":[
        {
            "category":"Building & Trades",
            "subcategory":"Construction",
            "type":"Services"
        }
    ],
    "sg:phone":"+1 614 340 2780",
    "sg:postcode":"43215",
    "sg:province":"OH",
    "sg:tags":[
        "equipment",
        "computer",
        "rooms"
    ],
    "wof:name":"IBS Group",
    "wof:placetype":"venue"
},
  "geometry": {"coordinates":[-83.017009,39.979658],"type":"Point"}
}