{
  "type": "Feature",
  "properties": {
    "iso:country":"US",
    "sg:address":"102 Bacher Sq",
    "sg:city":"Fairfield",
    "sg:classifiers":[
        {
            "category":"Social Services",
            "type":"Services"
        }
    ],
    "sg:phone":"+1 513 858 1701",
    "sg:postcode":"45014",
    "sg:province":"OH",
    "sg:tags":[
        "organization",
        "welfare"
    ],
    "wof:name":"Lacosta Facility Support Svc",
    "wof:placetype":"venue"
},
  "geometry": {"coordinates":[-84.53968,39.348855],"type":"Point"}
}