{
  "type": "Feature",
  "properties": {
    "addr:full": "1706 E High Ave New Philadelphia OH 44663",
    "addr:housenumber": "1706",
    "addr:postcode": "44663",
    "addr:street": "E High Ave",
    "iso:country": "US",
    "sg:address": "1706 E High Ave",
    "sg:city": "New Philadelphia",
    "sg:classifiers": [
      {
        "category": "Restaurant",
        "type": "Food \u0026 Drink"
      }
    ],
    "sg:phone": "+1 330 339 7555",
    "sg:postcode": "44663",
    "sg:province": "OH",
    "sg:tags": [
      "parlor",
      "ice",
      "cream"
    ],
    "wof:name": "New Philly Creamery",
    "wof:placetype": "venue"
  },
  "geometry": {"coordinates":[-81.420372,40.473501],"type":"Point"}
}
