{
  "type": "Feature",
  "properties": {
    "addr:full":"1198 W Galbraith Rd Cincinnati OH 45231",
    "addr:housenumber":"1198",
    "addr:postcode":"45231",
    "addr:street":"W Galbraith Rd",
    "iso:country":"US",
    "sg:address":"1198 W Galbraith Rd",
    "sg:city":"Cincinnati",
    "sg:classifiers":[
        {
            "category":"Shopping",
            "subcategory":"Pharmacy",
            "type":"Retail Goods"
        }
    ],
    "sg:phone":"+1 513 522 4091",
    "sg:postcode":"45231",
    "sg:province":"OH",
    "sg:tags":[
        "drug",
        "store"
    ],
    "wof:name":"Rite Aid",
    "wof:placetype":"venue"
},
  "geometry": {"coordinates":[-84.529991,39.216006],"type":"Point"}
}