{
  "type": "Feature",
  "properties": {
    "iso:country":"US",
    "sg:address":"101 Lawton Ave",
    "sg:city":"Monroe",
    "sg:classifiers":[
        {
            "category":"Wholesale",
            "subcategory":"Machinery & Supplies",
            "type":"Manufacturing & Wholesale Goods"
        }
    ],
    "sg:phone":"+1 513 539 8464",
    "sg:postcode":"45050",
    "sg:province":"OH",
    "sg:tags":[
        "equipment",
        "industrial"
    ],
    "wof:name":"Portman Equipment Company",
    "wof:placetype":"venue"
},
  "geometry": {"coordinates":[-84.345736,39.450585],"type":"Point"}
}