{
  "type": "Feature",
  "properties": {
    "addr:full": "5858 N High St Worthington OH 43085",
    "addr:housenumber": "5858",
    "addr:postcode": "43085",
    "addr:street": "N High St",
    "iso:country": "US",
    "sg:address": "5858 N High St",
    "sg:city": "Worthington",
    "sg:classifiers": [
      {
        "category": "Wholesale",
        "subcategory": "Durable Goods \u0026 Equipment",
        "type": "Manufacturing \u0026 Wholesale Goods"
      }
    ],
    "sg:phone": "+1 614 847 0309",
    "sg:postcode": "43085",
    "sg:province": "OH",
    "sg:tags": [
      "representative",
      "manufacturer"
    ],
    "wof:name": "Landers \u0026 Assoc",
    "wof:placetype": "venue"
  },
  "geometry": {"coordinates":[-83.01837,40.08257],"type":"Point"}
}
