{
  "type": "Feature",
  "properties": {
    "iso:country":"US",
    "sg:address":"5858 N High St",
    "sg:city":"Worthington",
    "sg:classifiers":[
        {
            "category":"Wholesale",
            "subcategory":"Durable Goods & Equipment",
            "type":"Manufacturing & Wholesale Goods"
        }
    ],
    "sg:phone":"+1 614 847 0309",
    "sg:postcode":"43085",
    "sg:province":"OH",
    "sg:tags":[
        "representative",
        "manufacturer"
    ],
    "wof:name":"Landers & Assoc",
    "wof:placetype":"venue"
},
  "geometry": {"coordinates":[-83.01837,40.08257],"type":"Point"}
}