{
  "type": "Feature",
  "properties": {
    "addr:full":"415 W Schrock Rd Westerville OH 43081",
    "addr:housenumber":"415",
    "addr:postcode":"43081",
    "addr:street":"W Schrock Rd",
    "iso:country":"US",
    "sg:address":"415 W Schrock Rd",
    "sg:city":"Westerville",
    "sg:classifiers":[
        {
            "category":"Wholesale",
            "subcategory":"Machinery & Supplies",
            "type":"Manufacturing & Wholesale Goods"
        },
        {
            "category":"Retail",
            "subcategory":"Repair Shop",
            "type":"Services"
        }
    ],
    "sg:phone":"+1 614 882 9022",
    "sg:postcode":"43081",
    "sg:province":"OH",
    "sg:tags":[
        "cleaners",
        "electrical",
        "vacuum"
    ],
    "wof:name":"Handy Andy Sweeper Company",
    "wof:placetype":"venue"
},
  "geometry": {"coordinates":[-82.94283299999999,40.110614],"type":"Point"}
}