{
  "type": "Feature",
  "properties": {
    "addr:full": "4600 W Broad St Columbus OH 43228",
    "addr:housenumber": "4600",
    "addr:postcode": "43228",
    "addr:street": "W Broad St",
    "iso:country": "US",
    "sg:address": "4600 W Broad St",
    "sg:city": "Columbus",
    "sg:classifiers": [
      {
        "category": "Home \u0026 Garden",
        "subcategory": "Household Appliances",
        "type": "Retail Goods"
      }
    ],
    "sg:phone": "+1 614 870 7909",
    "sg:postcode": "43228",
    "sg:province": "OH",
    "sg:tags": [
      "machine",
      "sewing"
    ],
    "wof:name": "Stitching Post",
    "wof:placetype": "venue"
  },
  "geometry": {"coordinates":[-83.129263,39.952228],"type":"Point"}
}
