{
  "type": "Feature",
  "properties": {
    "addr:full": "731 Keen St Zanesville OH 43701",
    "addr:housenumber": "731",
    "addr:postcode": "43701",
    "addr:street": "Keen St",
    "iso:country": "US",
    "sg:address": "731 Keen St",
    "sg:city": "Zanesville",
    "sg:classifiers": [
      {
        "category": "Shopping",
        "subcategory": "Clothing, Apparel, \u0026 Fashions",
        "type": "Retail Goods"
      }
    ],
    "sg:phone": "+1 740 453 3702",
    "sg:postcode": "43701",
    "sg:province": "OH",
    "sg:tags": [
      "navy",
      "army"
    ],
    "sg:website": "www.ghillie.com",
    "wof:name": "Custom Concealment Inc",
    "wof:placetype": "venue"
  },
  "geometry": {"coordinates":[-82.014417,39.945488],"type":"Point"}
}
