{
  "type": "Feature",
  "properties": {
    "addr:full":"1693 Co Rd 153 Lindsey OH 43442",
    "addr:housenumber":"1693;153",
    "addr:postcode":"43442",
    "addr:street":"Co Rd",
    "iso:country":"US",
    "sg:address":"1693 Co Rd 153",
    "sg:city":"Lindsey",
    "sg:phone":"+1 419 665 2693",
    "sg:postcode":"43442",
    "sg:province":"OH",
    "sg:tags":[
        "farm",
        "corn"
    ],
    "wof:name":"Boyer Farm",
    "wof:placetype":"venue"
},
  "geometry": {"coordinates":[-83.185591,41.451054],"type":"Point"}
}