{
  "type": "Feature",
  "properties": {
    "iso:country":"US",
    "sg:address":"126 E 2nd St",
    "sg:city":"Chillicothe",
    "sg:classifiers":[
        {
            "category":"Professional",
            "subcategory":"Business Services",
            "type":"Services"
        }
    ],
    "sg:phone":"+1 740 773 8394",
    "sg:postcode":"45601",
    "sg:province":"OH",
    "wof:name":"3SG Corp",
    "wof:placetype":"venue"
},
  "geometry": {"coordinates":[-82.97704,39.335265],"type":"Point"}
}