{
  "type": "Feature",
  "properties": {
    "addr:full":"12990 Millersburg Rd Danville OH 43014",
    "addr:postcode":"12990;43014",
    "addr:street":"Millersburg Rd",
    "iso:country":"US",
    "sg:address":"12990 Millersburg Rd",
    "sg:city":"Danville",
    "sg:classifiers":[
        {
            "category":"Professional",
            "subcategory":"Advertising",
            "type":"Services"
        }
    ],
    "sg:phone":"+1 740 599 5716",
    "sg:postcode":"43014",
    "sg:province":"OH",
    "sg:website":"www.dirtgraphx.com",
    "wof:name":"DIRTGRAPHX.COM",
    "wof:placetype":"venue"
},
  "geometry": {"coordinates":[-82.272764,40.408107],"type":"Point"}
}