{
  "type": "Feature",
  "properties": {
    "addr:full":"3131 Spring Grove Ave Cincinnati OH 45225",
    "addr:housenumber":"3131",
    "addr:postcode":"45225",
    "addr:street":"Spring Grove Ave",
    "iso:country":"US",
    "sg:address":"3131 Spring Grove Ave",
    "sg:city":"Cincinnati",
    "sg:classifiers":[
        {
            "category":"Manufacturing",
            "subcategory":"Paper Products",
            "type":"Manufacturing & Wholesale Goods"
        }
    ],
    "sg:phone":"+1 513 853 2148",
    "sg:postcode":"45225",
    "sg:province":"OH",
    "sg:tags":[
        "mill"
    ],
    "wof:name":"Ryder",
    "wof:placetype":"venue"
},
  "geometry": {"coordinates":[-84.541865,39.137538],"type":"Point"}
}