{
  "type": "Feature",
  "properties": {
    "iso:country":"US",
    "sg:address":"6338 Helen Dr",
    "sg:city":"Toledo",
    "sg:classifiers":[
        {
            "category":"Building & Trades",
            "subcategory":"Construction",
            "type":"Services"
        }
    ],
    "sg:phone":"+1 419 539 7330",
    "sg:postcode":"43615",
    "sg:province":"OH",
    "sg:tags":[
        "house"
    ],
    "wof:name":"Ed Taylor Construction",
    "wof:placetype":"venue"
},
  "geometry": {"coordinates":[-83.69288400000001,41.636678],"type":"Point"}
}