{
  "type": "Feature",
  "properties": {
    "addr:full": "6338 Helen Dr Toledo OH 43615",
    "addr:housenumber": "6338",
    "addr:postcode": "43615",
    "addr:street": "Helen Dr",
    "iso:country": "US",
    "sg:address": "6338 Helen Dr",
    "sg:city": "Toledo",
    "sg:classifiers": [
      {
        "category": "Building \u0026 Trades",
        "subcategory": "Construction",
        "type": "Services"
      }
    ],
    "sg:phone": "+1 419 539 7330",
    "sg:postcode": "43615",
    "sg:province": "OH",
    "sg:tags": [
      "house"
    ],
    "wof:name": "Ed Taylor Construction",
    "wof:placetype": "venue"
  },
  "geometry": {"coordinates":[-83.692884,41.636678],"type":"Point"}
}
