{
  "type": "Feature",
  "properties": {
    "addr:full":"7261 Engle Rd Cleveland OH 44130",
    "addr:housenumber":"7261",
    "addr:postcode":"44130",
    "addr:street":"Engle Rd",
    "iso:country":"US",
    "sg:address":"7261 Engle Rd",
    "sg:city":"Cleveland",
    "sg:classifiers":[
        {
            "category":"Real Estate",
            "subcategory":"Real Estate Agent",
            "type":"Services"
        }
    ],
    "sg:phone":"+1 440 239 1900",
    "sg:postcode":"44130",
    "sg:province":"OH",
    "wof:name":"Coriell Realty",
    "wof:placetype":"venue"
},
  "geometry": {"coordinates":[-81.825052,41.365563],"type":"Point"}
}