{
  "type": "Feature",
  "properties": {
    "iso:country":"US",
    "sg:address":"2447 Scioto Harper Dr",
    "sg:city":"Columbus",
    "sg:classifiers":[
        {
            "category":"Retail",
            "subcategory":"Car Wash",
            "type":"Services"
        }
    ],
    "sg:phone":"+1 614 272 5568",
    "sg:postcode":"43204",
    "sg:province":"OH",
    "sg:tags":[
        "automobile",
        "detail",
        "clean"
    ],
    "wof:name":"Auto Brite Detail",
    "wof:placetype":"venue"
},
  "geometry": {"coordinates":[-83.062755,39.966381],"type":"Point"}
}