{
  "type": "Feature",
  "properties": {
    "iso:country":"US",
    "sg:address":"14400 Pearl Rd",
    "sg:city":"Strongsville",
    "sg:classifiers":[
        {
            "category":"Professional",
            "subcategory":"Accounting & Tax Preparation",
            "type":"Services"
        }
    ],
    "sg:phone":"+1 440 572 8773",
    "sg:postcode":"44136",
    "sg:province":"OH",
    "sg:tags":[
        "return"
    ],
    "wof:name":"Strongsvlle Accouting Tax Svcs",
    "wof:placetype":"venue"
},
  "geometry": {"coordinates":[-81.835234,41.308607],"type":"Point"}
}