{
  "type": "Feature",
  "properties": {
    "addr:full":"4510 Granada Blvd Cleveland OH 44128",
    "addr:housenumber":"4510",
    "addr:postcode":"44128",
    "addr:street":"Granada Blvd",
    "iso:country":"US",
    "sg:address":"4510 Granada Blvd",
    "sg:city":"Cleveland",
    "sg:classifiers":[
        {
            "category":"Building & Trades",
            "subcategory":"Construction",
            "type":"Services"
        }
    ],
    "sg:phone":"+1 216 663 3443",
    "sg:postcode":"44128",
    "sg:province":"OH",
    "sg:tags":[
        "floor"
    ],
    "wof:name":"Richison Supplies & Svc",
    "wof:placetype":"venue"
},
  "geometry": {"coordinates":[-81.52122900000001,41.435271],"type":"Point"}
}