{
  "type": "Feature",
  "properties": {
    "addr:full": "4510 Granada Blvd Cleveland OH 44128",
    "addr:housenumber": "4510",
    "addr:postcode": "44128",
    "addr:street": "Granada Blvd",
    "iso:country": "US",
    "sg:address": "4510 Granada Blvd",
    "sg:city": "Cleveland",
    "sg:classifiers": [
      {
        "category": "Building \u0026 Trades",
        "subcategory": "Construction",
        "type": "Services"
      }
    ],
    "sg:phone": "+1 216 663 3443",
    "sg:postcode": "44128",
    "sg:province": "OH",
    "sg:tags": [
      "floor"
    ],
    "wof:name": "Richison Supplies \u0026 Svc",
    "wof:placetype": "venue"
  },
  "geometry": {"coordinates":[-81.521229,41.435271],"type":"Point"}
}
