{
  "type": "Feature",
  "properties": {
    "addr:full": "3255 Seajay Dr Dayton OH 45430",
    "addr:housenumber": "3255",
    "addr:postcode": "45430",
    "addr:street": "Seajay Dr",
    "iso:country": "US",
    "sg:address": "3255 Seajay Dr",
    "sg:city": "Dayton",
    "sg:classifiers": [
      {
        "category": "Food \u0026 Beverages",
        "subcategory": "Groceries \u0026 Convenience Stores",
        "type": "Retail Goods"
      }
    ],
    "sg:phone": "+1 937 431 1662",
    "sg:postcode": "45430",
    "sg:province": "OH",
    "sg:tags": [
      "grocer"
    ],
    "wof:name": "Cub Foods",
    "wof:placetype": "venue"
  },
  "geometry": {"coordinates":[-84.062202,39.720974],"type":"Point"}
}
