{
  "type": "Feature",
  "properties": {
    "addr:full":"8210 Co Rd 140 Findlay OH 45840",
    "addr:housenumber":"8210",
    "addr:postcode":"45840",
    "addr:street":"Co Rd 140",
    "iso:country":"US",
    "sg:address":"8210 Co Rd 140",
    "sg:city":"Findlay",
    "sg:classifiers":[
        {
            "category":"Government",
            "subcategory":"Police Station",
            "type":"Public Place"
        }
    ],
    "sg:phone":"+1 419 423 2841",
    "sg:postcode":"45840",
    "sg:province":"OH",
    "sg:tags":[
        "protection"
    ],
    "wof:name":"State Patrol Office",
    "wof:placetype":"venue"
},
  "geometry": {"coordinates":[-83.688368,41.055454],"type":"Point"}
}