{
  "type": "Feature",
  "properties": {
    "addr:full":"1 N High St Covington OH 45318",
    "addr:housenumber":"1",
    "addr:postcode":"45318",
    "addr:street":"N High St",
    "iso:country":"US",
    "sg:address":"1 N High St",
    "sg:city":"Covington",
    "sg:classifiers":[
        {
            "category":"Building & Trades",
            "subcategory":"Landscaping Services",
            "type":"Services"
        }
    ],
    "sg:phone":"+1 937 473 5852",
    "sg:postcode":"45318",
    "sg:province":"OH",
    "sg:tags":[
        "lawn",
        "maintenance",
        "grounds"
    ],
    "wof:name":"Total Lawn & Landscape",
    "wof:placetype":"venue"
},
  "geometry": {"coordinates":[-84.35464899999999,40.117492],"type":"Point"}
}