{
  "type": "Feature",
  "properties": {
    "addr:full": "7819 Euclid Ave Cincinnati OH 45243",
    "addr:housenumber": "7819",
    "addr:postcode": "45243",
    "addr:street": "Euclid Ave",
    "iso:country": "US",
    "sg:address": "7819 Euclid Ave",
    "sg:city": "Cincinnati",
    "sg:classifiers": [
      {
        "category": "Real Estate",
        "subcategory": "Real Estate Operator",
        "type": "Services"
      }
    ],
    "sg:phone": "+1 513 561 8657",
    "sg:postcode": "45243",
    "sg:province": "OH",
    "sg:tags": [
      "billboard",
      "commercial"
    ],
    "wof:name": "Golden Oldies Promotions",
    "wof:placetype": "venue"
  },
  "geometry": {"coordinates":[-84.36182,39.19104],"type":"Point"}
}
