{
  "type": "Feature",
  "properties": {
    "iso:country":"US",
    "sg:address":"1861 Ginder Rd NW",
    "sg:city":"Lancaster",
    "sg:classifiers":[
        {
            "category":"Bars & Pubs",
            "type":"Food & Drink"
        }
    ],
    "sg:phone":"+1 740 756 7313",
    "sg:postcode":"43130",
    "sg:province":"OH",
    "sg:tags":[
        "drinking"
    ],
    "wof:name":"Locker 8 Sports Bar LLC",
    "wof:placetype":"venue"
},
  "geometry": {"coordinates":[-82.634526,39.78148],"type":"Point"}
}