{
  "type": "Feature",
  "properties": {
    "iso:country":"US",
    "sg:address":"301 Broadway",
    "sg:city":"Lorain",
    "sg:classifiers":[
        {
            "category":"Shopping",
            "subcategory":"Computers & Home Electronics",
            "type":"Retail Goods"
        }
    ],
    "sg:phone":"+1 440 245 1609",
    "sg:postcode":"44052",
    "sg:province":"OH",
    "sg:tags":[
        "equipment",
        "satellite",
        "system"
    ],
    "wof:name":"Satellite Movies Inc",
    "wof:placetype":"venue"
},
  "geometry": {"coordinates":[-82.17696599999999,41.46731],"type":"Point"}
}