{
  "type": "Feature",
  "properties": {
    "addr:full": "301 Broadway Lorain OH 44052",
    "addr:housenumber": "301",
    "addr:postcode": "44052",
    "addr:street": "Broadway",
    "iso:country": "US",
    "sg:address": "301 Broadway",
    "sg:city": "Lorain",
    "sg:classifiers": [
      {
        "category": "Shopping",
        "subcategory": "Computers \u0026 Home Electronics",
        "type": "Retail Goods"
      }
    ],
    "sg:phone": "+1 440 245 1609",
    "sg:postcode": "44052",
    "sg:province": "OH",
    "sg:tags": [
      "equipment",
      "satellite",
      "system"
    ],
    "wof:name": "Satellite Movies Inc",
    "wof:placetype": "venue"
  },
  "geometry": {"coordinates":[-82.176966,41.46731],"type":"Point"}
}
