{
  "type": "Feature",
  "properties": {
    "addr:full": "303 Center St Ashtabula OH 44004",
    "addr:housenumber": "303",
    "addr:postcode": "44004",
    "addr:street": "Center St",
    "iso:country": "US",
    "sg:address": "303 Center St",
    "sg:city": "Ashtabula",
    "sg:classifiers": [
      {
        "category": "Retail",
        "subcategory": "Auto Repair",
        "type": "Services"
      }
    ],
    "sg:phone": "+1 440 992 0315",
    "sg:postcode": "44004",
    "sg:province": "OH",
    "sg:tags": [
      "repairing",
      "automobile"
    ],
    "wof:name": "Steve's Car Care",
    "wof:placetype": "venue"
  },
  "geometry": {"coordinates":[-80.78592,41.865007],"type":"Point"}
}
