{
  "type": "Feature",
  "properties": {
    "addr:full": "6650 S Palmer Rd New Carlisle OH 45344",
    "addr:housenumber": "6650",
    "addr:postcode": "45344",
    "addr:street": "S Palmer Rd",
    "iso:country": "US",
    "sg:address": "6650 S Palmer Rd",
    "sg:city": "New Carlisle",
    "sg:classifiers": [
      {
        "category": "Farming",
        "subcategory": "Farm",
        "type": "Manufacturing \u0026 Wholesale Goods"
      }
    ],
    "sg:phone": "+1 937 846 1800",
    "sg:postcode": "45344",
    "sg:province": "OH",
    "sg:tags": [
      "crop",
      "general"
    ],
    "wof:name": "Darrowby Farm",
    "wof:placetype": "venue"
  },
  "geometry": {"coordinates":[-84.065528,39.929042],"type":"Point"}
}
