{
  "type": "Feature",
  "properties": {
    "addr:full": "4173 Minard Rd Dover OH 44622",
    "addr:postcode": "4173;44622",
    "addr:street": "Minard Rd",
    "iso:country": "US",
    "sg:address": "4173 Minard Rd",
    "sg:city": "Dover",
    "sg:classifiers": [
      {
        "category": "Organizations",
        "subcategory": "Religious Organization",
        "type": "Services"
      }
    ],
    "sg:phone": "+1 330 343 3413",
    "sg:postcode": "44622",
    "sg:province": "OH",
    "sg:tags": [
      "church"
    ],
    "wof:name": "Dover Bible Church",
    "wof:placetype": "venue"
  },
  "geometry": {"coordinates":[-81.532107,40.544828],"type":"Point"}
}
