{
  "type": "Feature",
  "properties": {
    "addr:full":"11665 Lebanon Rd Cincinnati OH 45241",
    "addr:housenumber":"11665",
    "addr:postcode":"45241",
    "addr:street":"Lebanon Rd",
    "iso:country":"US",
    "sg:address":"11665 Lebanon Rd",
    "sg:city":"Cincinnati",
    "sg:classifiers":[
        {
            "category":"Organizations",
            "subcategory":"Community Association",
            "type":"Services"
        }
    ],
    "sg:phone":"+1 513 697 8752",
    "sg:postcode":"45241",
    "sg:province":"OH",
    "sg:tags":[
        "fraternal"
    ],
    "wof:name":"Madsionville-Madeira Lodge",
    "wof:placetype":"venue"
},
  "geometry": {"coordinates":[-84.39961,39.284252],"type":"Point"}
}