{
  "type": "Feature",
  "properties": {
    "addr:full":"7208 Harrison Ave Cincinnati OH 45247",
    "addr:housenumber":"7208",
    "addr:postcode":"45247",
    "addr:street":"Harrison Ave",
    "iso:country":"US",
    "sg:address":"7208 Harrison Ave",
    "sg:city":"Cincinnati",
    "sg:classifiers":[
        {
            "category":"Shopping",
            "subcategory":"Bicycles & Sporting Goods",
            "type":"Retail Goods"
        }
    ],
    "sg:phone":"+1 513 353 3536",
    "sg:postcode":"45247",
    "sg:province":"OH",
    "wof:name":"Afield",
    "wof:placetype":"venue"
},
  "geometry": {"coordinates":[-84.678211,39.217258],"type":"Point"}
}