{
  "type": "Feature",
  "properties": {
    "addr:full": "614 W Superior Ave Cleveland OH 44113",
    "addr:housenumber": "614",
    "addr:postcode": "44113",
    "addr:street": "W Superior Ave",
    "iso:country": "US",
    "sg:address": "614 W Superior Ave",
    "sg:city": "Cleveland",
    "sg:phone": "+1 216 781 7990",
    "sg:postcode": "44113",
    "sg:province": "OH",
    "sg:website": "http://www.sammonbolmeyer.com",
    "wof:name": "Sammon \u0026 Bolmeyer",
    "wof:placetype": "venue"
  },
  "geometry": {"coordinates":[-81.697419,41.497716],"type":"Point"}
}
