{
  "type": "Feature",
  "properties": {
    "addr:full": "4192 Pennyroyal Rd Franklin OH 45005",
    "addr:housenumber": "4192",
    "addr:postcode": "45005",
    "addr:street": "Pennyroyal Rd",
    "iso:country": "US",
    "sg:address": "4192 Pennyroyal Rd",
    "sg:city": "Franklin",
    "sg:classifiers": [
      {
        "category": "Organizations",
        "subcategory": "Religious Organization",
        "type": "Services"
      }
    ],
    "sg:phone": "+1 513 422 6136",
    "sg:postcode": "45005",
    "sg:province": "OH",
    "sg:tags": [
      "church"
    ],
    "wof:name": "Full Gospel Outreach",
    "wof:placetype": "venue"
  },
  "geometry": {"coordinates":[-84.260068,39.580323],"type":"Point"}
}
