{
  "type": "Feature",
  "properties": {
    "addr:full": "927 Wertz Ave NW Canton OH 44708",
    "addr:housenumber": "927",
    "addr:postcode": "44708",
    "addr:street": "Wertz Ave Nw",
    "iso:country": "US",
    "sg:address": "927 Wertz Ave NW",
    "sg:city": "Canton",
    "sg:classifiers": [
      {
        "category": "Autos \u0026 Motor Vehicles",
        "subcategory": "Automobile Sales",
        "type": "Retail Goods"
      }
    ],
    "sg:phone": "+1 330 453 3700",
    "sg:postcode": "44708",
    "sg:province": "OH",
    "sg:tags": [
      "used"
    ],
    "wof:name": "Car Credit Inc",
    "wof:placetype": "venue"
  },
  "geometry": {"coordinates":[-81.40706,40.80808],"type":"Point"}
}
