{
  "type": "Feature",
  "properties": {
    "iso:country":"US",
    "sg:address":"1700 Crest Rd",
    "sg:city":"Cleveland",
    "sg:classifiers":[
        {
            "category":"Social Services",
            "subcategory":"Child Care",
            "type":"Services"
        }
    ],
    "sg:phone":"+1 216 371 7356",
    "sg:postcode":"44121",
    "sg:province":"OH",
    "sg:website":"www.chuh.org",
    "wof:name":"Millikin Early Childhood Ctr",
    "wof:placetype":"venue"
},
  "geometry": {"coordinates":[-81.545749,41.517465],"type":"Point"}
}