{
  "type": "Feature",
  "properties": {
    "addr:full": "4546 State Rte 309 Ada OH 45810",
    "addr:housenumber": "4546",
    "addr:postcode": "45810",
    "addr:street": "State Rte 309",
    "iso:country": "US",
    "sg:address": "4546 State Rte 309",
    "sg:city": "Ada",
    "sg:classifiers": [
      {
        "category": "Building \u0026 Trades",
        "subcategory": "Construction",
        "type": "Services"
      }
    ],
    "sg:phone": "+1 419 634 4986",
    "sg:postcode": "45810",
    "sg:province": "OH",
    "sg:tags": [
      "concrete",
      "contractor"
    ],
    "wof:name": "Castle Construction",
    "wof:placetype": "venue"
  },
  "geometry": {"coordinates":[-83.794273,40.730774],"type":"Point"}
}
