{
  "type": "Feature",
  "properties": {
    "iso:country":"US",
    "sg:address":"4546 State Rte 309",
    "sg:city":"Ada",
    "sg:classifiers":[
        {
            "category":"Building & Trades",
            "subcategory":"Construction",
            "type":"Services"
        }
    ],
    "sg:phone":"+1 419 634 4986",
    "sg:postcode":"45810",
    "sg:province":"OH",
    "sg:tags":[
        "concrete",
        "contractor"
    ],
    "wof:name":"Castle Construction",
    "wof:placetype":"venue"
},
  "geometry": {"coordinates":[-83.794273,40.730774],"type":"Point"}
}