{
  "type": "Feature",
  "properties": {
    "iso:country":"US",
    "sg:address":"466 Northfield Rd",
    "sg:city":"Bedford",
    "sg:classifiers":[
        {
            "category":"Education",
            "subcategory":"Vocational School",
            "type":"Public Place"
        }
    ],
    "sg:phone":"+1 440 232 3846",
    "sg:postcode":"44146",
    "sg:province":"OH",
    "sg:tags":[
        "a",
        "training",
        "consultant",
        "operates",
        "as",
        "computer",
        "software"
    ],
    "wof:name":"Devore Technologies Inc",
    "wof:placetype":"venue"
},
  "geometry": {"coordinates":[-81.52739200000001,41.406991],"type":"Point"}
}