{
  "type": "Feature",
  "properties": {
    "addr:full": "657 N James Rd Columbus OH 43219",
    "addr:housenumber": "657",
    "addr:postcode": "43219",
    "addr:street": "N James Rd",
    "iso:country": "US",
    "sg:address": "657 N James Rd",
    "sg:city": "Columbus",
    "sg:classifiers": [
      {
        "category": "Restaurant",
        "type": "Food \u0026 Drink"
      }
    ],
    "sg:phone": "+1 614 231 4439",
    "sg:postcode": "43219",
    "sg:province": "OH",
    "wof:name": "Hot Dog Wally's",
    "wof:placetype": "venue"
  },
  "geometry": {"coordinates":[-82.905992,39.986828],"type":"Point"}
}
