{
  "type": "Feature",
  "properties": {
    "addr:full": "24 Clark Ave Cincinnati OH 45215",
    "addr:housenumber": "24",
    "addr:postcode": "45215",
    "addr:street": "Clark Ave",
    "iso:country": "US",
    "sg:address": "24 Clark Ave",
    "sg:city": "Cincinnati",
    "sg:classifiers": [
      {
        "category": "Farming",
        "subcategory": "Farm",
        "type": "Manufacturing \u0026 Wholesale Goods"
      }
    ],
    "sg:phone": "+1 513 761 5841",
    "sg:postcode": "45215",
    "sg:province": "OH",
    "sg:tags": [
      "crop",
      "general"
    ],
    "wof:name": "Saul Farms Inc",
    "wof:placetype": "venue"
  },
  "geometry": {"coordinates":[-84.471356,39.221655],"type":"Point"}
}
