{
  "type": "Feature",
  "properties": {
    "iso:country":"US",
    "sg:address":"418 W Wenger Rd",
    "sg:city":"Englewood",
    "sg:classifiers":[
        {
            "category":"Social Services",
            "subcategory":"Child Care",
            "type":"Services"
        }
    ],
    "sg:phone":"+1 937 836 8002",
    "sg:postcode":"45322",
    "sg:province":"OH",
    "sg:website":"www.kindercare.com",
    "wof:name":"Kinder Care Learning Ctr",
    "wof:placetype":"venue"
},
  "geometry": {"coordinates":[-84.30198300000001,39.862033],"type":"Point"}
}