{
  "type": "Feature",
  "properties": {
    "iso:country":"US",
    "sg:address":"830 Elysian Ave",
    "sg:city":"Toledo",
    "sg:classifiers":[
        {
            "category":"Building & Trades",
            "subcategory":"Construction",
            "type":"Services"
        }
    ],
    "sg:phone":"+1 419 385 0291",
    "sg:postcode":"43607",
    "sg:province":"OH",
    "sg:tags":[
        "roofing",
        "siding",
        "contractor"
    ],
    "wof:name":"Interstate Roofing Co Inc",
    "wof:placetype":"venue"
},
  "geometry": {"coordinates":[-83.610892,41.648041],"type":"Point"}
}