{
  "type": "Feature",
  "properties": {
    "addr:full": "10055 Winton Rd Cincinnati OH 45231",
    "addr:housenumber": "10055",
    "addr:postcode": "45231",
    "addr:street": "Winton Rd",
    "iso:country": "US",
    "sg:address": "10055 Winton Rd",
    "sg:city": "Cincinnati",
    "sg:classifiers": [
      {
        "category": "Utilities",
        "subcategory": "Mobile Phone",
        "type": "Services"
      }
    ],
    "sg:phone": "+1 513 521 9884",
    "sg:postcode": "45231",
    "sg:province": "OH",
    "sg:tags": [
      "communication",
      "radiotelephone"
    ],
    "wof:name": "Tri Comm Communications",
    "wof:placetype": "venue"
  },
  "geometry": {"coordinates":[-84.513359,39.250834],"type":"Point"}
}
