{
  "type": "Feature",
  "properties": {
    "addr:full": "1230 N Columbus St Lancaster OH 43130",
    "addr:housenumber": "1230",
    "addr:postcode": "43130",
    "addr:street": "N Columbus St",
    "iso:country": "US",
    "sg:address": "1230 N Columbus St",
    "sg:city": "Lancaster",
    "sg:classifiers": [
      {
        "category": "Manufacturing",
        "subcategory": "Metals",
        "type": "Manufacturing \u0026 Wholesale Goods"
      }
    ],
    "sg:phone": "+1 740 653 1900",
    "sg:postcode": "43130",
    "sg:province": "OH",
    "sg:tags": [
      "repair",
      "blast",
      "furnace",
      "works",
      "welding"
    ],
    "wof:name": "Wendells Machine",
    "wof:placetype": "venue"
  },
  "geometry": {"coordinates":[-82.606055,39.731067],"type":"Point"}
}
