{
  "type": "Feature",
  "properties": {
    "iso:country":"US",
    "sg:address":"4757 State Rte 39",
    "sg:city":"Berlin",
    "sg:classifiers":[
        {
            "category":"Shopping",
            "subcategory":"Gifts & Souvenirs",
            "type":"Retail Goods"
        }
    ],
    "sg:phone":"+1 330 893 3444",
    "sg:postcode":"44615",
    "sg:province":"OH",
    "sg:tags":[
        "shop"
    ],
    "wof:name":"Country Treasures",
    "wof:placetype":"venue"
},
  "geometry": {"coordinates":[-81.003998,40.603495],"type":"Point"}
}