{
  "type": "Feature",
  "properties": {
    "addr:full": "6395 Westbrook Pl Columbus OH 43085",
    "addr:housenumber": "6395",
    "addr:postcode": "43085",
    "addr:street": "Westbrook Pl",
    "iso:country": "US",
    "sg:address": "6395 Westbrook Pl",
    "sg:city": "Columbus",
    "sg:classifiers": [
      {
        "category": "Building \u0026 Trades",
        "subcategory": "Construction",
        "type": "Services"
      }
    ],
    "sg:phone": "+1 614 848 5253",
    "sg:postcode": "43085",
    "sg:province": "OH",
    "sg:tags": [
      "hanging",
      "contractor"
    ],
    "wof:name": "Guglielmi Company",
    "wof:placetype": "venue"
  },
  "geometry": {"coordinates":[-83.048249,40.088375],"type":"Point"}
}
