{
  "type": "Feature",
  "properties": {
    "addr:full": "38536 State Rte 93 Hamden OH 45634",
    "addr:housenumber": "38536",
    "addr:postcode": "45634",
    "addr:street": "State Rte 93",
    "iso:country": "US",
    "sg:address": "38536 State Rte 93",
    "sg:city": "Hamden",
    "sg:classifiers": [
      {
        "category": "Restaurant",
        "type": "Food \u0026 Drink"
      }
    ],
    "sg:phone": "+1 740 384 1454",
    "sg:postcode": "45634",
    "sg:province": "OH",
    "wof:name": "Hamden Junction Bar \u0026 Grill",
    "wof:placetype": "venue"
  },
  "geometry": {"coordinates":[-82.522153,39.1703],"type":"Point"}
}
