{
  "type": "Feature",
  "properties": {
    "iso:country":"US",
    "sg:address":"38536 State Rte 93",
    "sg:city":"Hamden",
    "sg:classifiers":[
        {
            "category":"Restaurant",
            "type":"Food & Drink"
        }
    ],
    "sg:phone":"+1 740 384 1454",
    "sg:postcode":"45634",
    "sg:province":"OH",
    "wof:name":"Hamden Junction Bar & Grill",
    "wof:placetype":"venue"
},
  "geometry": {"coordinates":[-82.522153,39.1703],"type":"Point"}
}