{
  "type": "Feature",
  "properties": {
    "iso:country":"US",
    "sg:address":"9784 Salem Church Rd NW",
    "sg:city":"Canal Winchester",
    "sg:classifiers":[
        {
            "category":"Building & Trades",
            "subcategory":"Landscaping Services",
            "type":"Services"
        }
    ],
    "sg:phone":"+1 614 834 8349",
    "sg:postcode":"43110",
    "sg:province":"OH",
    "sg:tags":[
        "landscape"
    ],
    "wof:name":"Wilkinson Landscaping LLC",
    "wof:placetype":"venue"
},
  "geometry": {"coordinates":[-82.785633,39.793709],"type":"Point"}
}