{
  "type": "Feature",
  "properties": {
    "iso:country":"US",
    "sg:address":"7450 W 130th St",
    "sg:city":"Cleveland",
    "sg:classifiers":[
        {
            "category":"Farming",
            "subcategory":"Farm",
            "type":"Manufacturing & Wholesale Goods"
        }
    ],
    "sg:phone":"+1 440 843 7181",
    "sg:postcode":"44130",
    "sg:province":"OH",
    "sg:tags":[
        "crop",
        "general"
    ],
    "wof:name":"Settle Down Farms",
    "wof:placetype":"venue"
},
  "geometry": {"coordinates":[-81.785003,41.363501],"type":"Point"}
}