{
  "type": "Feature",
  "properties": {
    "addr:full":"757 Garden Rd Columbus OH 43214",
    "addr:housenumber":"757",
    "addr:postcode":"43214",
    "addr:street":"Garden Rd",
    "iso:country":"US",
    "sg:address":"757 Garden Rd",
    "sg:city":"Columbus",
    "sg:classifiers":[
        {
            "category":"Home & Garden",
            "subcategory":"Building Materials",
            "type":"Retail Goods"
        },
        {
            "category":"Building & Trades",
            "subcategory":"Construction",
            "type":"Services"
        }
    ],
    "sg:phone":"+1 614 268 8611",
    "sg:postcode":"43214",
    "sg:province":"OH",
    "sg:tags":[
        "glass",
        "window",
        "contractor",
        "plate"
    ],
    "wof:name":"Thomas Glass Company Inc",
    "wof:placetype":"venue"
},
  "geometry": {"coordinates":[-83.00024500000001,40.055452],"type":"Point"}
}