{
  "type": "Feature",
  "properties": {
    "iso:country":"US",
    "sg:address":"15146 Co Rd M1",
    "sg:city":"Napoleon",
    "sg:classifiers":[
        {
            "category":"Banks & Credit Unions",
            "subcategory":"Investment Brokerage",
            "type":"Services"
        }
    ],
    "sg:phone":"+1 419 599 9955",
    "sg:postcode":"43545",
    "sg:province":"OH",
    "sg:tags":[
        "advisory",
        "financial"
    ],
    "wof:name":"Thrivent Financial-Lutherans",
    "wof:placetype":"venue"
},
  "geometry": {"coordinates":[-84.148957,41.341203],"type":"Point"}
}