{
  "type": "Feature",
  "properties": {
    "iso:country":"US",
    "sg:address":"11512 Fay Rd",
    "sg:city":"Painesville",
    "sg:classifiers":[
        {
            "category":"Organizations",
            "subcategory":"Religious Organization",
            "type":"Services"
        }
    ],
    "sg:phone":"+1 440 352 4884",
    "sg:postcode":"44077",
    "sg:province":"OH",
    "sg:tags":[
        "clergy"
    ],
    "wof:name":"Wilbur L Stemen",
    "wof:placetype":"venue"
},
  "geometry": {"coordinates":[-81.22314299999999,41.687145],"type":"Point"}
}