{
  "type": "Feature",
  "properties": {
    "addr:full": "19284 Bradner Rd Pemberville OH 43450",
    "addr:housenumber": "19284",
    "addr:postcode": "43450",
    "addr:street": "Bradner Rd",
    "iso:country": "US",
    "sg:address": "19284 Bradner Rd",
    "sg:city": "Pemberville",
    "sg:classifiers": [
      {
        "category": "Real Estate",
        "subcategory": "Developer",
        "type": "Services"
      }
    ],
    "sg:phone": "+1 419 287 1713",
    "sg:postcode": "43450",
    "sg:province": "OH",
    "wof:name": "LAMD Development",
    "wof:placetype": "venue"
  },
  "geometry": {"coordinates":[-83.434619,41.429295],"type":"Point"}
}
