{
  "type": "Feature",
  "properties": {
    "iso:country":"US",
    "sg:address":"3766 State Rte 193",
    "sg:city":"Cortland",
    "sg:classifiers":[
        {
            "category":"Education",
            "subcategory":"Dance Studio",
            "type":"Public Place"
        }
    ],
    "sg:phone":"+1 330 638 7598",
    "sg:postcode":"44410",
    "sg:province":"OH",
    "sg:tags":[
        "instruction",
        "dancing"
    ],
    "wof:name":"Jill's Dance Shop",
    "wof:placetype":"venue"
},
  "geometry": {"coordinates":[-80.65554299999999,41.328897],"type":"Point"}
}