{
  "type": "Feature",
  "properties": {
    "addr:full":"294 Union St Newark OH 43055",
    "addr:housenumber":"294",
    "addr:postcode":"43055",
    "addr:street":"Union St",
    "iso:country":"US",
    "sg:address":"294 Union St",
    "sg:city":"Newark",
    "sg:classifiers":[
        {
            "category":"Social Services",
            "subcategory":"Job Training",
            "type":"Services"
        }
    ],
    "sg:phone":"+1 740 344 2786",
    "sg:postcode":"43055",
    "sg:province":"OH",
    "sg:tags":[
        "rehabilitation"
    ],
    "wof:name":"VIP Rehab Svc",
    "wof:placetype":"venue"
},
  "geometry": {"coordinates":[-82.421712,40.04715],"type":"Point"}
}