{
  "type": "Feature",
  "properties": {
    "addr:full": "5323 Warrensville Center Rd Cleveland OH 44137",
    "addr:housenumber": "5323",
    "addr:postcode": "44137",
    "addr:street": "Warrensville Center Rd",
    "iso:country": "US",
    "sg:address": "5323 Warrensville Center Rd",
    "sg:city": "Cleveland",
    "sg:classifiers": [
      {
        "category": "Shopping",
        "subcategory": "Discount \u0026 Variety Stores",
        "type": "Retail Goods"
      }
    ],
    "sg:phone": "+1 216 663 9707",
    "sg:postcode": "44137",
    "sg:province": "OH",
    "wof:name": "Family Dollar Store",
    "wof:placetype": "venue"
  },
  "geometry": {"coordinates":[-81.537234,41.416511],"type":"Point"}
}
