{
  "type": "Feature",
  "properties": {
    "addr:full":"24 Beech St Berea OH 44017",
    "addr:housenumber":"24",
    "addr:postcode":"44017",
    "addr:street":"Beech St",
    "iso:country":"US",
    "sg:address":"24 Beech St",
    "sg:city":"Berea",
    "sg:classifiers":[
        {
            "category":"Real Estate",
            "subcategory":"Surveying",
            "type":"Services"
        }
    ],
    "sg:phone":"+1 440 234 5544",
    "sg:postcode":"44017",
    "sg:province":"OH",
    "sg:tags":[
        "surveyor"
    ],
    "wof:name":"Hofmann-Metzker Inc",
    "wof:placetype":"venue"
},
  "geometry": {"coordinates":[-81.850005,41.366386],"type":"Point"}
}