{
  "type": "Feature",
  "properties": {
    "addr:full":"1370 W 6th St Cleveland OH 44113",
    "addr:housenumber":"1370",
    "addr:postcode":"44113",
    "addr:street":"W 6Th St",
    "iso:country":"US",
    "sg:address":"1370 W 6th St",
    "sg:city":"Cleveland",
    "sg:classifiers":[
        {
            "category":"Professional",
            "subcategory":"Employment Agencies",
            "type":"Services"
        }
    ],
    "sg:phone":"+1 216 241 7744",
    "sg:postcode":"44113",
    "sg:province":"OH",
    "sg:tags":[
        "opportunity"
    ],
    "wof:name":"Affordable Staffing Employment Services Inc.",
    "wof:placetype":"venue"
},
  "geometry": {"coordinates":[-81.698319,41.499394],"type":"Point"}
}