{
  "type": "Feature",
  "properties": {
    "iso:country":"US",
    "sg:address":"7813 W Ridgewood Dr",
    "sg:city":"Cleveland",
    "sg:classifiers":[
        {
            "category":"Personal",
            "type":"Services"
        }
    ],
    "sg:phone":"+1 440 845 2889",
    "sg:postcode":"44129",
    "sg:province":"OH",
    "wof:name":"American Commodore",
    "wof:placetype":"venue"
},
  "geometry": {"coordinates":[-81.739873,41.384452],"type":"Point"}
}