{
  "type": "Feature",
  "properties": {
    "iso:country":"US",
    "sg:address":"665 Delaware Ave",
    "sg:city":"Marion",
    "sg:classifiers":[
        {
            "category":"Restaurant",
            "type":"Food & Drink"
        }
    ],
    "sg:menulink":"http://www.allmenus.com/oh/marion/79107-pizza-hut/menu/",
    "sg:phone":"+1 740 387 2500",
    "sg:postcode":"43302",
    "sg:province":"OH",
    "sg:tags":[
        "american",
        "pizza"
    ],
    "wof:name":"Pizza Hut",
    "wof:placetype":"venue"
},
  "geometry": {"coordinates":[-83.12563900000001,40.577307],"type":"Point"}
}