{
  "type": "Feature",
  "properties": {
    "addr:full": "665 Delaware Ave Marion OH 43302",
    "addr:housenumber": "665",
    "addr:postcode": "43302",
    "addr:street": "Delaware Ave",
    "iso:country": "US",
    "sg:address": "665 Delaware Ave",
    "sg:city": "Marion",
    "sg:classifiers": [
      {
        "category": "Restaurant",
        "type": "Food \u0026 Drink"
      }
    ],
    "sg:menulink": "http://www.allmenus.com/oh/marion/79107-pizza-hut/menu/",
    "sg:phone": "+1 740 387 2500",
    "sg:postcode": "43302",
    "sg:province": "OH",
    "sg:tags": [
      "american",
      "pizza"
    ],
    "wof:name": "Pizza Hut",
    "wof:placetype": "venue"
  },
  "geometry": {"coordinates":[-83.125639,40.577307],"type":"Point"}
}
