{
  "type": "Feature",
  "properties": {
    "iso:country":"US",
    "sg:address":"1700 Morse Rd",
    "sg:city":"Columbus",
    "sg:classifiers":[
        {
            "category":"Shopping",
            "subcategory":"Clothing, Apparel, & Fashions",
            "type":"Retail Goods"
        }
    ],
    "sg:phone":"+1 614 841 1600",
    "sg:postcode":"43229",
    "sg:province":"OH",
    "wof:name":"Toys r US",
    "wof:placetype":"venue"
},
  "geometry": {"coordinates":[-82.97351399999999,40.060486],"type":"Point"}
}