{
  "type": "Feature",
  "properties": {
    "addr:full": "5075 Fisher Rd Columbus OH 43228",
    "addr:housenumber": "5075",
    "addr:postcode": "43228",
    "addr:street": "Fisher Rd",
    "iso:country": "US",
    "sg:address": "5075 Fisher Rd",
    "sg:city": "Columbus",
    "sg:classifiers": [
      {
        "category": "Freight",
        "type": "Transportation"
      }
    ],
    "sg:phone": "+1 614 853 6110",
    "sg:postcode": "43228",
    "sg:province": "OH",
    "sg:tags": [
      "dry",
      "bulk",
      "trucking"
    ],
    "sg:website": "www.qualitydistribution.com",
    "wof:name": "Ineos",
    "wof:placetype": "venue"
  },
  "geometry": {"coordinates":[-83.13669,39.973576],"type":"Point"}
}
