{
  "type": "Feature",
  "properties": {
    "addr:full": "22442 State Rte 73 Portsmouth OH 45663",
    "addr:housenumber": "22442",
    "addr:postcode": "45663",
    "addr:street": "State Rte 73",
    "iso:country": "US",
    "sg:address": "22442 State Rte 73",
    "sg:city": "Portsmouth",
    "sg:classifiers": [
      {
        "category": "Health Services",
        "subcategory": "Doctor",
        "type": "Services"
      }
    ],
    "sg:phone": "+1 740 858 6656",
    "sg:postcode": "45663",
    "sg:province": "OH",
    "sg:tags": [
      "physician",
      "surgeon",
      "medical"
    ],
    "wof:name": "James H Duncan Do Inc",
    "wof:placetype": "venue"
  },
  "geometry": {"coordinates":[-83.014321,38.774343],"type":"Point"}
}
