{
  "type": "Feature",
  "properties": {
    "iso:country":"US",
    "sg:address":"22442 State Rte 73",
    "sg:city":"Portsmouth",
    "sg:classifiers":[
        {
            "category":"Health Services",
            "subcategory":"Doctor",
            "type":"Services"
        }
    ],
    "sg:phone":"+1 740 858 6656",
    "sg:postcode":"45663",
    "sg:province":"OH",
    "sg:tags":[
        "physician",
        "surgeon",
        "medical"
    ],
    "wof:name":"James H Duncan Do Inc",
    "wof:placetype":"venue"
},
  "geometry": {"coordinates":[-83.014321,38.774343],"type":"Point"}
}