{
  "type": "Feature",
  "properties": {
    "addr:full": "9042 Heritage Dr Plain City OH 43064",
    "addr:housenumber": "9042",
    "addr:postcode": "43064",
    "addr:street": "Heritage Dr",
    "iso:country": "US",
    "sg:address": "9042 Heritage Dr",
    "sg:city": "Plain City",
    "sg:classifiers": [
      {
        "category": "Professional",
        "subcategory": "Business Services",
        "type": "Services"
      }
    ],
    "sg:phone": "+1 614 873 2460",
    "sg:postcode": "43064",
    "sg:province": "OH",
    "wof:name": "Fibercor Composites",
    "wof:placetype": "venue"
  },
  "geometry": {"coordinates":[-83.206379,40.136977],"type":"Point"}
}
