{
  "type": "Feature",
  "properties": {
    "iso:country":"US",
    "sg:address":"310 E Innis Ave",
    "sg:city":"Columbus",
    "sg:classifiers":[
        {
            "category":"Professional",
            "type":"Services"
        }
    ],
    "sg:phone":"+1 614 441 1198",
    "sg:postcode":"43207",
    "sg:province":"OH",
    "sg:tags":[
        "establishment"
    ],
    "wof:name":"South Side Settlemtn House",
    "wof:placetype":"venue"
},
  "geometry": {"coordinates":[-82.987542,39.926056],"type":"Point"}
}