{
  "type": "Feature",
  "properties": {
    "iso:country":"US",
    "sg:address":"632 Riegart Sq",
    "sg:city":"Fairfield",
    "sg:classifiers":[
        {
            "category":"Personal",
            "subcategory":"Beauty Salon",
            "type":"Services"
        }
    ],
    "sg:phone":"+1 513 863 5739",
    "sg:postcode":"45014",
    "sg:province":"OH",
    "wof:name":"A J's Curl Connection",
    "wof:placetype":"venue"
},
  "geometry": {"coordinates":[-84.55923199999999,39.340963],"type":"Point"}
}