{
  "type": "Feature",
  "properties": {
    "addr:full": "718 Dover Ave SW Warren OH 44485",
    "addr:housenumber": "718",
    "addr:postcode": "44485",
    "addr:street": "Dover Ave Sw",
    "iso:country": "US",
    "sg:address": "718 Dover Ave SW",
    "sg:city": "Warren",
    "sg:classifiers": [
      {
        "category": "Organizations",
        "subcategory": "Religious Organization",
        "type": "Services"
      }
    ],
    "sg:phone": "+1 330 394 3986",
    "sg:postcode": "44485",
    "sg:province": "OH",
    "sg:tags": [
      "clergy"
    ],
    "wof:name": "James Johnson",
    "wof:placetype": "venue"
  },
  "geometry": {"coordinates":[-80.826257,41.215517],"type":"Point"}
}
