{
  "type": "Feature",
  "properties": {
    "iso:country":"US",
    "sg:address":"5805 Laurel Creek Rd",
    "sg:city":"Tippecanoe",
    "sg:classifiers":[
        {
            "category":"Manufacturing",
            "subcategory":"Lumber",
            "type":"Manufacturing & Wholesale Goods"
        }
    ],
    "sg:phone":"+1 740 254 4664",
    "sg:postcode":"44699",
    "sg:province":"OH",
    "sg:tags":[
        "planing",
        "mills",
        "sawmill"
    ],
    "wof:name":"Gardner Lumber Co",
    "wof:placetype":"venue"
},
  "geometry": {"coordinates":[-81.346507,40.252527],"type":"Point"}
}