{
  "type": "Feature",
  "properties": {
    "addr:full": "3525 S Arlington Rd Akron OH 44312",
    "addr:housenumber": "3525",
    "addr:postcode": "44312",
    "addr:street": "S Arlington Rd",
    "iso:country": "US",
    "sg:address": "3525 S Arlington Rd",
    "sg:city": "Akron",
    "sg:classifiers": [
      {
        "category": "Professional",
        "type": "Services"
      }
    ],
    "sg:phone": "+1 330 896 0800",
    "sg:postcode": "44312",
    "sg:province": "OH",
    "sg:tags": [
      "establishment"
    ],
    "wof:name": "Sweeney \u0026 Collins Enterprises",
    "wof:placetype": "venue"
  },
  "geometry": {"coordinates":[-81.493279,40.974816],"type":"Point"}
}
