{
  "type": "Feature",
  "properties": {
    "iso:country":"US",
    "sg:address":"3525 S Arlington Rd",
    "sg:city":"Akron",
    "sg:classifiers":[
        {
            "category":"Professional",
            "type":"Services"
        }
    ],
    "sg:phone":"+1 330 896 0800",
    "sg:postcode":"44312",
    "sg:province":"OH",
    "sg:tags":[
        "establishment"
    ],
    "wof:name":"Sweeney & Collins Enterprises",
    "wof:placetype":"venue"
},
  "geometry": {"coordinates":[-81.493279,40.974816],"type":"Point"}
}