{
  "type": "Feature",
  "properties": {
    "addr:full":"738 W Market St Akron OH 44303",
    "addr:housenumber":"738",
    "addr:postcode":"44303",
    "addr:street":"W Market St",
    "iso:country":"US",
    "sg:address":"738 W Market St",
    "sg:city":"Akron",
    "sg:classifiers":[
        {
            "category":"Wholesale",
            "subcategory":"Machinery & Supplies",
            "type":"Manufacturing & Wholesale Goods"
        }
    ],
    "sg:phone":"+1 330 253 9460",
    "sg:postcode":"44303",
    "sg:province":"OH",
    "sg:tags":[
        "equipment",
        "tool"
    ],
    "wof:name":"National Tool & Equipment",
    "wof:placetype":"venue"
},
  "geometry": {"coordinates":[-81.54098999999999,41.095489],"type":"Point"}
}