{
  "type": "Feature",
  "properties": {
    "iso:country":"US",
    "sg:address":"7618 Rosewood Dr",
    "sg:city":"Blanchester",
    "sg:classifiers":[
        {
            "category":"Retail",
            "subcategory":"Repair Shop",
            "type":"Services"
        }
    ],
    "sg:phone":"+1 937 783 3344",
    "sg:postcode":"45107",
    "sg:province":"OH",
    "sg:tags":[
        "lock",
        "locksmith"
    ],
    "wof:name":"Dick's Lock & Key Svc",
    "wof:placetype":"venue"
},
  "geometry": {"coordinates":[-83.97770800000001,39.279139],"type":"Point"}
}