{
  "type": "Feature",
  "properties": {
    "addr:full": "7618 Rosewood Dr Blanchester OH 45107",
    "addr:housenumber": "7618",
    "addr:postcode": "45107",
    "addr:street": "Rosewood Dr",
    "iso:country": "US",
    "sg:address": "7618 Rosewood Dr",
    "sg:city": "Blanchester",
    "sg:classifiers": [
      {
        "category": "Retail",
        "subcategory": "Repair Shop",
        "type": "Services"
      }
    ],
    "sg:phone": "+1 937 783 3344",
    "sg:postcode": "45107",
    "sg:province": "OH",
    "sg:tags": [
      "lock",
      "locksmith"
    ],
    "wof:name": "Dick's Lock \u0026 Key Svc",
    "wof:placetype": "venue"
  },
  "geometry": {"coordinates":[-83.977708,39.279139],"type":"Point"}
}
