{
  "type": "Feature",
  "properties": {
    "addr:full":"3883 E Broad St Columbus OH 43213",
    "addr:housenumber":"3883",
    "addr:postcode":"43213",
    "addr:street":"E Broad St",
    "iso:country":"US",
    "sg:address":"3883 E Broad St",
    "sg:city":"Columbus",
    "sg:classifiers":[
        {
            "category":"Insurance",
            "subcategory":"Insurance Agent",
            "type":"Services"
        }
    ],
    "sg:phone":"+1 614 231 0200",
    "sg:postcode":"43213",
    "sg:province":"OH",
    "wof:name":"Safe Auto Insurance",
    "wof:placetype":"venue"
},
  "geometry": {"coordinates":[-82.900696,39.973388],"type":"Point"}
}