{
  "type": "Feature",
  "properties": {
    "addr:full": "9725 Fox Lake Rd Orrville OH 44667",
    "addr:housenumber": "9725",
    "addr:postcode": "44667",
    "addr:street": "Fox Lake Rd",
    "iso:country": "US",
    "sg:address": "9725 Fox Lake Rd",
    "sg:city": "Orrville",
    "sg:classifiers": [
      {
        "category": "Building \u0026 Trades",
        "subcategory": "Construction",
        "type": "Services"
      }
    ],
    "sg:phone": "+1 330 682 0730",
    "sg:postcode": "44667",
    "sg:province": "OH",
    "sg:tags": [
      "excavating",
      "contractor"
    ],
    "wof:name": "Buckeye Excavating Development",
    "wof:placetype": "venue"
  },
  "geometry": {"coordinates":[-81.801108,40.888585],"type":"Point"}
}
