{
  "type": "Feature",
  "properties": {
    "iso:country":"US",
    "sg:address":"11353 Lebanon Rd",
    "sg:city":"Cincinnati",
    "sg:classifiers":[
        {
            "category":"Professional",
            "subcategory":"Management & Consulting",
            "type":"Services"
        }
    ],
    "sg:phone":"+1 513 554 4570",
    "sg:postcode":"45241",
    "sg:province":"OH",
    "sg:tags":[
        "marketing",
        "program"
    ],
    "sg:website":"www.ameridiansvcs.com",
    "wof:name":"Ameridian",
    "wof:placetype":"venue"
},
  "geometry": {"coordinates":[-84.410588,39.275264],"type":"Point"}
}