{
  "type": "Feature",
  "properties": {
    "iso:country":"US",
    "sg:address":"7113 State Rte 115",
    "sg:city":"Continental",
    "sg:phone":"+1 419 596 3448",
    "sg:postcode":"45831",
    "sg:province":"OH",
    "sg:tags":[
        "farm",
        "corn",
        "wheat",
        "soybean"
    ],
    "wof:name":"Joseph Morman",
    "wof:placetype":"venue"
},
  "geometry": {"coordinates":[-84.19834899999999,41.078809],"type":"Point"}
}