{
  "type": "Feature",
  "properties": {
    "iso:country":"US",
    "sg:address":"5463 Bentonhurst Ct",
    "sg:city":"Galloway",
    "sg:classifiers":[
        {
            "category":"Retail",
            "subcategory":"Animal Services",
            "type":"Services"
        }
    ],
    "sg:phone":"+1 614 878 8000",
    "sg:postcode":"43119",
    "sg:province":"OH",
    "wof:name":"Doody Free In Home Pet Care",
    "wof:placetype":"venue"
},
  "geometry": {"coordinates":[-83.142905,39.945772],"type":"Point"}
}