{
  "type": "Feature",
  "properties": {
    "addr:full":"6701 Hamilton Ave Cincinnati OH 45224",
    "addr:housenumber":"6701",
    "addr:postcode":"45224",
    "addr:street":"Hamilton Ave",
    "iso:country":"US",
    "sg:address":"6701 Hamilton Ave",
    "sg:city":"Cincinnati",
    "sg:classifiers":[
        {
            "category":"Banks & Credit Unions",
            "subcategory":"Bank",
            "type":"Services"
        }
    ],
    "sg:phone":"+1 513 931 8400",
    "sg:postcode":"45224",
    "sg:province":"OH",
    "sg:tags":[
        "state",
        "savings"
    ],
    "sg:website":"www.usavingsbank.com",
    "wof:name":"Union Savings Bank",
    "wof:placetype":"venue"
},
  "geometry": {"coordinates":[-84.549076,39.214737],"type":"Point"}
}