{
  "type": "Feature",
  "properties": {
    "addr:full": "105 Corwin St Norwalk OH 44857",
    "addr:housenumber": "105",
    "addr:postcode": "44857",
    "addr:street": "Corwin St",
    "iso:country": "US",
    "sg:address": "105 Corwin St",
    "sg:city": "Norwalk",
    "sg:classifiers": [
      {
        "category": "Manufacturing",
        "subcategory": "Printing",
        "type": "Manufacturing \u0026 Wholesale Goods"
      }
    ],
    "sg:phone": "+1 419 663 8711",
    "sg:postcode": "44857",
    "sg:province": "OH",
    "sg:tags": [
      "typesetting"
    ],
    "wof:name": "Insight Type \u0026 Graphics",
    "wof:placetype": "venue"
  },
  "geometry": {"coordinates":[-82.601623,41.241321],"type":"Point"}
}
