{
  "type": "Feature",
  "properties": {
    "iso:country":"US",
    "sg:address":"1625 N Detroit St",
    "sg:city":"Xenia",
    "sg:classifiers":[
        {
            "category":"Shopping",
            "subcategory":"Florist",
            "type":"Retail Goods"
        }
    ],
    "sg:phone":"+1 937 372 2461",
    "sg:postcode":"45385",
    "sg:province":"OH",
    "wof:name":"Wickline's Florist & Garden",
    "wof:placetype":"venue"
},
  "geometry": {"coordinates":[-83.93368700000001,39.70686],"type":"Point"}
}