{
  "type": "Feature",
  "properties": {
    "addr:full": "1625 N Detroit St Xenia OH 45385",
    "addr:housenumber": "1625",
    "addr:postcode": "45385",
    "addr:street": "N Detroit St",
    "iso:country": "US",
    "sg:address": "1625 N Detroit St",
    "sg:city": "Xenia",
    "sg:classifiers": [
      {
        "category": "Shopping",
        "subcategory": "Florist",
        "type": "Retail Goods"
      }
    ],
    "sg:phone": "+1 937 372 2461",
    "sg:postcode": "45385",
    "sg:province": "OH",
    "wof:name": "Wickline's Florist \u0026 Garden",
    "wof:placetype": "venue"
  },
  "geometry": {"coordinates":[-83.933687,39.70686],"type":"Point"}
}
