{
  "type": "Feature",
  "properties": {
    "addr:full":"10945 Reed Hartman Hwy Cincinnati OH 45242",
    "addr:housenumber":"10945",
    "addr:postcode":"45242",
    "addr:street":"Reed Hartman Hwy",
    "iso:country":"US",
    "sg:address":"10945 Reed Hartman Hwy",
    "sg:city":"Cincinnati",
    "sg:classifiers":[
        {
            "category":"Shopping",
            "type":"Retail Goods"
        }
    ],
    "sg:phone":"+1 513 791 4404",
    "sg:postcode":"45242",
    "sg:province":"OH",
    "sg:tags":[
        "merchandise"
    ],
    "wof:name":"Bonus Building Care",
    "wof:placetype":"venue"
},
  "geometry": {"coordinates":[-84.376316,39.269065],"type":"Point"}
}