{
  "type": "Feature",
  "properties": {
    "iso:country":"US",
    "sg:address":"27 Robin Hood Dr",
    "sg:city":"Greenville",
    "sg:classifiers":[
        {
            "category":"Real Estate",
            "subcategory":"Real Estate Operator",
            "type":"Services"
        }
    ],
    "sg:phone":"+1 937 548 9898",
    "sg:postcode":"45331",
    "sg:province":"OH",
    "sg:tags":[
        "mobile",
        "home",
        "site"
    ],
    "wof:name":"Sherwood Forest MBL Hm Cmnty",
    "wof:placetype":"venue"
},
  "geometry": {"coordinates":[-84.60521900000001,40.054519],"type":"Point"}
}