{
  "type": "Feature",
  "properties": {
    "iso:country":"US",
    "sg:address":"837 Chestnut Blvd",
    "sg:city":"Cuyahoga Falls",
    "sg:classifiers":[
        {
            "category":"Organizations",
            "subcategory":"Religious Organization",
            "type":"Services"
        }
    ],
    "sg:phone":"+1 330 929 4717",
    "sg:postcode":"44221",
    "sg:province":"OH",
    "sg:website":"www.churchinthefalls.com",
    "wof:name":"Church In The Falls",
    "wof:placetype":"venue"
},
  "geometry": {"coordinates":[-81.492476,41.128676],"type":"Point"}
}