{
  "type": "Feature",
  "properties": {
    "iso:country":"US",
    "sg:address":"654 High Bridge Rd",
    "sg:city":"Vermilion",
    "sg:classifiers":[
        {
            "category":"Building & Trades",
            "subcategory":"Construction",
            "type":"Services"
        }
    ],
    "sg:phone":"+1 440 963 0654",
    "sg:postcode":"44089",
    "sg:province":"OH",
    "sg:tags":[
        "contractor"
    ],
    "wof:name":"Yoders 654 Roofing",
    "wof:placetype":"venue"
},
  "geometry": {"coordinates":[-82.325622,41.419696],"type":"Point"}
}