{
  "type": "Feature",
  "properties": {
    "iso:country":"US",
    "sg:address":"871 E Wilbeth Rd",
    "sg:city":"Akron",
    "sg:classifiers":[
        {
            "category":"Professional",
            "type":"Services"
        }
    ],
    "sg:phone":"+1 330 773 7607",
    "sg:postcode":"44306",
    "sg:province":"OH",
    "sg:tags":[
        "establishment"
    ],
    "wof:name":"Lula Mae Foundation",
    "wof:placetype":"venue"
},
  "geometry": {"coordinates":[-81.495502,41.03988],"type":"Point"}
}