{
  "type": "Feature",
  "properties": {
    "addr:full":"3153 E Main St Columbus OH 43213",
    "addr:housenumber":"3153",
    "addr:postcode":"43213",
    "addr:street":"E Main St",
    "iso:country":"US",
    "sg:address":"3153 E Main St",
    "sg:city":"Columbus",
    "sg:classifiers":[
        {
            "category":"Retail",
            "subcategory":"Auto Repair",
            "type":"Services"
        }
    ],
    "sg:phone":"+1 614 239 8040",
    "sg:postcode":"43213",
    "sg:province":"OH",
    "sg:tags":[
        "brake"
    ],
    "wof:name":"Tyre Zone",
    "wof:placetype":"venue"
},
  "geometry": {"coordinates":[-82.91445299999999,39.9565],"type":"Point"}
}