{
  "type": "Feature",
  "properties": {
    "addr:full": "3015 Marks Rd Medina OH 44256",
    "addr:housenumber": "3015",
    "addr:postcode": "44256",
    "addr:street": "Marks Rd",
    "iso:country": "US",
    "sg:address": "3015 Marks Rd",
    "sg:city": "Medina",
    "sg:classifiers": [
      {
        "category": "Professional",
        "subcategory": "Management \u0026 Consulting",
        "type": "Services"
      }
    ],
    "sg:phone": "+1 330 723 3170",
    "sg:postcode": "44256",
    "sg:province": "OH",
    "sg:tags": [
      "retail",
      "miscellaneous"
    ],
    "wof:name": "Wildar Inc",
    "wof:placetype": "venue"
  },
  "geometry": {"coordinates":[-81.878193,41.195848],"type":"Point"}
}
