{
  "type": "Feature",
  "properties": {
    "iso:country":"US",
    "sg:address":"10659 Highland Ave",
    "sg:city":"Garrettsville",
    "sg:classifiers":[
        {
            "category":"Home & Garden",
            "subcategory":"Furniture",
            "type":"Retail Goods"
        }
    ],
    "sg:phone":"+1 330 527 5954",
    "sg:postcode":"44231",
    "sg:province":"OH",
    "sg:tags":[
        "equipment",
        "kitchen",
        "cabinet"
    ],
    "wof:name":"Goodnight's Kitchen & Bath Inc",
    "wof:placetype":"venue"
},
  "geometry": {"coordinates":[-81.09691599999999,41.281688],"type":"Point"}
}