{
  "type": "Feature",
  "properties": {
    "addr:full": "1516 S Water St Kent OH 44240",
    "addr:housenumber": "1516",
    "addr:postcode": "44240",
    "addr:street": "S Water St",
    "iso:country": "US",
    "sg:address": "1516 S Water St",
    "sg:city": "Kent",
    "sg:classifiers": [
      {
        "category": "Health Services",
        "subcategory": "Podiatrist",
        "type": "Services"
      }
    ],
    "sg:phone": "+1 330 678 4800",
    "sg:postcode": "44240",
    "sg:province": "OH",
    "wof:name": "John F Kunkel DPM",
    "wof:placetype": "venue"
  },
  "geometry": {"coordinates":[-81.356111,41.138872],"type":"Point"}
}
