{
  "type": "Feature",
  "properties": {
    "addr:full":"1255 S Limestone St Springfield OH 45505",
    "addr:housenumber":"1255",
    "addr:postcode":"45505",
    "addr:street":"S Limestone St",
    "iso:country":"US",
    "sg:address":"1255 S Limestone St",
    "sg:city":"Springfield",
    "sg:classifiers":[
        {
            "category":"Wholesale",
            "subcategory":"Toys & Hobbies",
            "type":"Manufacturing & Wholesale Goods"
        }
    ],
    "sg:phone":"+1 937 325 6556",
    "sg:postcode":"45505",
    "sg:province":"OH",
    "sg:tags":[
        "arts",
        "craft"
    ],
    "wof:name":"J Jacks Arts and Crafts",
    "wof:placetype":"venue"
},
  "geometry": {"coordinates":[-83.810058,39.909886],"type":"Point"}
}