{
  "type": "Feature",
  "properties": {
    "addr:full":"122 W High St Bryan OH 43506",
    "addr:housenumber":"122",
    "addr:postcode":"43506",
    "addr:street":"W High St",
    "iso:country":"US",
    "sg:address":"122 W High St",
    "sg:city":"Bryan",
    "sg:classifiers":[
        {
            "category":"Shopping",
            "subcategory":"Computers & Home Electronics",
            "type":"Retail Goods"
        }
    ],
    "sg:phone":"+1 419 633 9141",
    "sg:postcode":"43506",
    "sg:province":"OH",
    "sg:tags":[
        "audio"
    ],
    "wof:name":"Jupiter Theater Design",
    "wof:placetype":"venue"
},
  "geometry": {"coordinates":[-84.551557,41.474667],"type":"Point"}
}