{
  "type": "Feature",
  "properties": {
    "iso:country":"US",
    "sg:address":"1118 Woodbine Ave",
    "sg:city":"Marion",
    "sg:classifiers":[
        {
            "category":"Retail",
            "subcategory":"Laundry & Dry Cleaning",
            "type":"Services"
        }
    ],
    "sg:phone":"+1 740 387 0200",
    "sg:postcode":"43302",
    "sg:province":"OH",
    "sg:tags":[
        "cleaners",
        "rug",
        "carpet"
    ],
    "wof:name":"Freshly Clean",
    "wof:placetype":"venue"
},
  "geometry": {"coordinates":[-83.156856,40.572144],"type":"Point"}
}