{
  "type": "Feature",
  "properties": {
    "addr:full":"348 W Main Rd Conneaut OH 44030",
    "addr:housenumber":"348",
    "addr:postcode":"44030",
    "addr:street":"W Main Rd",
    "iso:country":"US",
    "sg:address":"348 W Main Rd",
    "sg:city":"Conneaut",
    "sg:classifiers":[
        {
            "category":"Bakery",
            "type":"Food & Drink"
        }
    ],
    "sg:menulink":"http://www.allmenus.com/oh/conneaut/102173-perkins-restaurant--bakery/menu/",
    "sg:phone":"+1 440 593 2500",
    "sg:postcode":"44030",
    "sg:province":"OH",
    "sg:tags":[
        "sandwich",
        "salad",
        "soup",
        "american",
        "pastry",
        "wrap"
    ],
    "wof:name":"Perkins Restaurant & Bakery",
    "wof:placetype":"venue"
},
  "geometry": {"coordinates":[-80.584682,41.937108],"type":"Point"}
}