{
  "type": "Feature",
  "properties": {
    "addr:full": "8857 Co Rd 14 Wauseon OH 43567",
    "addr:housenumber": "8857;14",
    "addr:postcode": "43567",
    "addr:street": "Co Rd",
    "iso:country": "US",
    "sg:address": "8857 Co Rd 14",
    "sg:city": "Wauseon",
    "sg:classifiers": [
      {
        "category": "Building \u0026 Trades",
        "subcategory": "Construction",
        "type": "Services"
      },
      {
        "category": "Building \u0026 Trades",
        "subcategory": "Landscaping Services",
        "type": "Services"
      }
    ],
    "sg:phone": "+1 419 335 3148",
    "sg:postcode": "43567",
    "sg:province": "OH",
    "sg:tags": [
      "excavating",
      "landscape",
      "contractor"
    ],
    "wof:name": "Dave's Services",
    "wof:placetype": "venue"
  },
  "geometry": {"coordinates":[-84.134399,41.596186],"type":"Point"}
}
