{
  "type": "Feature",
  "properties": {
    "addr:full": "161 E Possum Rd Springfield OH 45502",
    "addr:housenumber": "161",
    "addr:postcode": "45502",
    "addr:street": "E Possum Rd",
    "iso:country": "US",
    "sg:address": "161 E Possum Rd",
    "sg:city": "Springfield",
    "sg:classifiers": [
      {
        "category": "Building \u0026 Trades",
        "subcategory": "Construction",
        "type": "Services"
      }
    ],
    "sg:phone": "+1 937 322 2147",
    "sg:postcode": "45502",
    "sg:province": "OH",
    "sg:tags": [
      "house"
    ],
    "wof:name": "Deselem Construction",
    "wof:placetype": "venue"
  },
  "geometry": {"coordinates":[-83.805649,39.872395],"type":"Point"}
}
