{
  "type": "Feature",
  "properties": {
    "addr:full":"204 N Main St Lima OH 45801",
    "addr:housenumber":"204",
    "addr:postcode":"45801",
    "addr:street":"N Main St",
    "iso:country":"US",
    "sg:address":"204 N Main St",
    "sg:city":"Lima",
    "sg:classifiers":[
        {
            "category":"Government",
            "subcategory":"Court House",
            "type":"Public Place"
        }
    ],
    "sg:phone":"+1 419 228 3700",
    "sg:postcode":"45801",
    "sg:province":"OH",
    "sg:tags":[
        "county",
        "counsel"
    ],
    "wof:name":"Allen County Prosecuting Atty",
    "wof:placetype":"venue"
},
  "geometry": {"coordinates":[-84.104904,40.742083],"type":"Point"}
}