{
  "type": "Feature",
  "properties": {
    "addr:full": "4215 Ridge Rd Cleveland OH 44144",
    "addr:housenumber": "4215",
    "addr:postcode": "44144",
    "addr:street": "Ridge Rd",
    "iso:country": "US",
    "sg:address": "4215 Ridge Rd",
    "sg:city": "Cleveland",
    "sg:classifiers": [
      {
        "category": "Autos \u0026 Motor Vehicles",
        "subcategory": "Fuel \u0026 Gas Station",
        "type": "Retail Goods"
      },
      {
        "category": "Retail",
        "subcategory": "Auto Repair",
        "type": "Services"
      }
    ],
    "sg:phone": "+1 216 351 1190",
    "sg:postcode": "44144",
    "sg:province": "OH",
    "sg:tags": [
      "repairing",
      "automobile",
      "station",
      "gasoline"
    ],
    "wof:name": "Haller's Delco Tech",
    "wof:placetype": "venue"
  },
  "geometry": {"coordinates":[-81.735202,41.442166],"type":"Point"}
}
