{
  "type": "Feature",
  "properties": {
    "addr:full":"2475 Fairfield Pike Springfield OH 45502",
    "addr:housenumber":"2475",
    "addr:postcode":"45502",
    "addr:street":"Fairfield Pike",
    "iso:country":"US",
    "sg:address":"2475 Fairfield Pike",
    "sg:city":"Springfield",
    "sg:phone":"+1 937 322 2623",
    "sg:postcode":"45502",
    "sg:province":"OH",
    "sg:tags":[
        "farm"
    ],
    "wof:name":"Mellinger Farm",
    "wof:placetype":"venue"
},
  "geometry": {"coordinates":[-83.865281,39.87006],"type":"Point"}
}