{
  "type": "Feature",
  "properties": {
    "addr:full": "536 York St Cincinnati OH 45214",
    "addr:housenumber": "536",
    "addr:postcode": "45214",
    "addr:street": "York St",
    "iso:country": "US",
    "sg:address": "536 York St",
    "sg:city": "Cincinnati",
    "sg:classifiers": [
      {
        "category": "Food \u0026 Beverages",
        "subcategory": "Liquor \u0026 Beverages",
        "type": "Retail Goods"
      }
    ],
    "sg:phone": "+1 513 890 6656",
    "sg:postcode": "45214",
    "sg:province": "OH",
    "sg:tags": [
      "beer",
      "ale"
    ],
    "wof:name": "Mac's Carry Out",
    "wof:placetype": "venue"
  },
  "geometry": {"coordinates":[-84.525826,39.117093],"type":"Point"}
}
