{
  "type": "Feature",
  "properties": {
    "iso:country":"US",
    "sg:address":"4030 N River Rd NE",
    "sg:city":"Warren",
    "sg:classifiers":[
        {
            "category":"Education",
            "subcategory":"Dance Studio",
            "type":"Public Place"
        }
    ],
    "sg:phone":"+1 330 856 1711",
    "sg:postcode":"44484",
    "sg:province":"OH",
    "sg:tags":[
        "instruction",
        "dancing"
    ],
    "wof:name":"James Dance & Performing Arts",
    "wof:placetype":"venue"
},
  "geometry": {"coordinates":[-80.76336499999999,41.26546],"type":"Point"}
}