{
  "type": "Feature",
  "properties": {
    "addr:full": "4030 N River Rd NE Warren OH 44484",
    "addr:housenumber": "4030",
    "addr:postcode": "44484",
    "addr:street": "N River Rd Ne",
    "iso:country": "US",
    "sg:address": "4030 N River Rd NE",
    "sg:city": "Warren",
    "sg:classifiers": [
      {
        "category": "Education",
        "subcategory": "Dance Studio",
        "type": "Public Place"
      }
    ],
    "sg:phone": "+1 330 856 1711",
    "sg:postcode": "44484",
    "sg:province": "OH",
    "sg:tags": [
      "instruction",
      "dancing"
    ],
    "wof:name": "James Dance \u0026 Performing Arts",
    "wof:placetype": "venue"
  },
  "geometry": {"coordinates":[-80.763365,41.26546],"type":"Point"}
}
