{
  "type": "Feature",
  "properties": {
    "addr:full": "11501 Mayfield Rd Cleveland OH 44106",
    "addr:housenumber": "11501",
    "addr:postcode": "44106",
    "addr:street": "Mayfield Rd",
    "iso:country": "US",
    "sg:address": "11501 Mayfield Rd",
    "sg:city": "Cleveland",
    "sg:classifiers": [
      {
        "category": "Real Estate",
        "subcategory": "Real Estate Agent",
        "type": "Services"
      }
    ],
    "sg:phone": "+1 216 791 5025",
    "sg:postcode": "44106",
    "sg:province": "OH",
    "wof:name": "Abington Arms Apartments",
    "wof:placetype": "venue"
  },
  "geometry": {"coordinates":[-81.602591,41.508702],"type":"Point"}
}
