{
  "type": "Feature",
  "properties": {
    "iso:country":"US",
    "sg:address":"11138 Montgomery Rd",
    "sg:city":"Cincinnati",
    "sg:classifiers":[
        {
            "category":"Restaurant",
            "type":"Food & Drink"
        }
    ],
    "sg:menulink":"http://www.allmenus.com/oh/symmes/16842-deweys-pizza/menu/",
    "sg:phone":"+1 513 247 9955",
    "sg:postcode":"45249",
    "sg:province":"OH",
    "sg:tags":[
        "italian"
    ],
    "wof:name":"Dewey's Pizza",
    "wof:placetype":"venue"
},
  "geometry": {"coordinates":[-84.331675,39.267084],"type":"Point"}
}