{
  "type": "Feature",
  "properties": {
    "iso:country":"US",
    "sg:address":"300 E Stroop Rd",
    "sg:city":"Dayton",
    "sg:classifiers":[
        {
            "category":"Shopping",
            "subcategory":"Clothing, Apparel, & Fashions",
            "type":"Retail Goods"
        }
    ],
    "sg:phone":"+1 937 299 4242",
    "sg:postcode":"45429",
    "sg:province":"OH",
    "sg:tags":[
        "infant",
        "wear"
    ],
    "wof:name":"Gaga's",
    "wof:placetype":"venue"
},
  "geometry": {"coordinates":[-84.168133,39.689498],"type":"Point"}
}