{
  "type": "Feature",
  "properties": {
    "addr:full":"3979 Schnorf-Jones Rd Arcanum OH 45304",
    "addr:housenumber":"3979",
    "addr:postcode":"45304",
    "addr:street":"Schnorf-Jones Rd",
    "iso:country":"US",
    "sg:address":"3979 Schnorf-Jones Rd",
    "sg:city":"Arcanum",
    "sg:classifiers":[
        {
            "category":"Manufacturing",
            "subcategory":"Glass & Minerals",
            "type":"Manufacturing & Wholesale Goods"
        }
    ],
    "sg:phone":"+1 937 548 9199",
    "sg:postcode":"45304",
    "sg:province":"OH",
    "sg:tags":[
        "abrasive",
        "product",
        "mfg"
    ],
    "wof:name":"KS Graphics",
    "wof:placetype":"venue"
},
  "geometry": {"coordinates":[-84.469921,40.034372],"type":"Point"}
}