{
  "type": "Feature",
  "properties": {
    "addr:full": "2631 Northland Plaza Dr Columbus OH 43231",
    "addr:housenumber": "2631",
    "addr:postcode": "43231",
    "addr:street": "Northland Plaza Dr",
    "iso:country": "US",
    "sg:address": "2631 Northland Plaza Dr",
    "sg:city": "Columbus",
    "sg:classifiers": [
      {
        "category": "Shopping",
        "type": "Retail Goods"
      }
    ],
    "sg:phone": "+1 614 794 0184",
    "sg:postcode": "43231",
    "sg:province": "OH",
    "sg:tags": [
      "pet",
      "shop"
    ],
    "sg:website": "www.jackspets.com",
    "wof:name": "Jack's Aquarium \u0026 Pets",
    "wof:placetype": "venue"
  },
  "geometry": {"coordinates":[-82.945811,40.082954],"type":"Point"}
}
