{
  "type": "Feature",
  "properties": {
    "iso:country":"US",
    "sg:address":"2631 Northland Plaza Dr",
    "sg:city":"Columbus",
    "sg:classifiers":[
        {
            "category":"Shopping",
            "type":"Retail Goods"
        }
    ],
    "sg:phone":"+1 614 794 0184",
    "sg:postcode":"43231",
    "sg:province":"OH",
    "sg:tags":[
        "pet",
        "shop"
    ],
    "sg:website":"www.jackspets.com",
    "wof:name":"Jack's Aquarium & Pets",
    "wof:placetype":"venue"
},
  "geometry": {"coordinates":[-82.94581100000001,40.082954],"type":"Point"}
}