{
  "type": "Feature",
  "properties": {
    "iso:country":"US",
    "sg:address":"560 Sunbury Rd",
    "sg:city":"Delaware",
    "sg:classifiers":[
        {
            "category":"Manufacturing",
            "subcategory":"Printing",
            "type":"Manufacturing & Wholesale Goods"
        }
    ],
    "sg:phone":"+1 740 363 2395",
    "sg:postcode":"43015",
    "sg:province":"OH",
    "sg:tags":[
        "publisher"
    ],
    "wof:name":"Farm & Ranch Publishing",
    "wof:placetype":"venue"
},
  "geometry": {"coordinates":[-83.04248699999999,40.296329],"type":"Point"}
}