{
  "type": "Feature",
  "properties": {
    "addr:full": "560 Sunbury Rd Delaware OH 43015",
    "addr:housenumber": "560",
    "addr:postcode": "43015",
    "addr:street": "Sunbury Rd",
    "iso:country": "US",
    "sg:address": "560 Sunbury Rd",
    "sg:city": "Delaware",
    "sg:classifiers": [
      {
        "category": "Manufacturing",
        "subcategory": "Printing",
        "type": "Manufacturing \u0026 Wholesale Goods"
      }
    ],
    "sg:phone": "+1 740 363 2395",
    "sg:postcode": "43015",
    "sg:province": "OH",
    "sg:tags": [
      "publisher"
    ],
    "wof:name": "Farm \u0026 Ranch Publishing",
    "wof:placetype": "venue"
  },
  "geometry": {"coordinates":[-83.042487,40.296329],"type":"Point"}
}
