{
  "type": "Feature",
  "properties": {
    "addr:full": "58 Larrimer Ave Columbus OH 43085",
    "addr:housenumber": "58",
    "addr:postcode": "43085",
    "addr:street": "Larrimer Ave",
    "iso:country": "US",
    "sg:address": "58 Larrimer Ave",
    "sg:city": "Columbus",
    "sg:classifiers": [
      {
        "category": "Real Estate",
        "subcategory": "Real Estate Agent",
        "type": "Services"
      }
    ],
    "sg:phone": "+1 614 846 3831",
    "sg:postcode": "43085",
    "sg:province": "OH",
    "wof:name": "Rush Appraisal Services LLC",
    "wof:placetype": "venue"
  },
  "geometry": {"coordinates":[-83.018124,40.09932],"type":"Point"}
}
