{
  "type": "Feature",
  "properties": {
    "addr:full": "10 E Vine St Mt Vernon OH 43050",
    "addr:housenumber": "10",
    "addr:postcode": "43050",
    "addr:street": "E Vine St",
    "iso:country": "US",
    "sg:address": "10 E Vine St",
    "sg:city": "Mt Vernon",
    "sg:classifiers": [
      {
        "category": "Professional",
        "subcategory": "Lawyer \u0026 Legal Services",
        "type": "Services"
      }
    ],
    "sg:phone": "+1 740 397 0711",
    "sg:postcode": "43050",
    "sg:province": "OH",
    "sg:tags": [
      "attorney"
    ],
    "wof:name": "T Garrett Ressing",
    "wof:placetype": "venue"
  },
  "geometry": {"coordinates":[-82.485445,40.392577],"type":"Point"}
}
