{
  "type": "Feature",
  "properties": {
    "iso:country":"US",
    "sg:address":"1067 US Hwy 68",
    "sg:city":"Xenia",
    "sg:classifiers":[
        {
            "category":"Organizations",
            "subcategory":"Religious Organization",
            "type":"Services"
        }
    ],
    "sg:phone":"+1 937 372 1069",
    "sg:postcode":"45385",
    "sg:province":"OH",
    "sg:tags":[
        "church"
    ],
    "sg:website":"www.independentbaptist.net",
    "wof:name":"Freedom Baptist Temple",
    "wof:placetype":"venue"
},
  "geometry": {"coordinates":[-83.932778,39.700428],"type":"Point"}
}