{
  "type": "Feature",
  "properties": {
    "addr:full": "6950 Pondlick Rd Seaman OH 45697",
    "addr:housenumber": "6950",
    "addr:postcode": "45697",
    "addr:street": "Pondlick Rd",
    "iso:country": "US",
    "sg:address": "6950 Pondlick Rd",
    "sg:city": "Seaman",
    "sg:classifiers": [
      {
        "category": "Building \u0026 Trades",
        "subcategory": "Construction",
        "type": "Services"
      }
    ],
    "sg:phone": "+1 937 927 5543",
    "sg:postcode": "45697",
    "sg:province": "OH",
    "sg:tags": [
      "house"
    ],
    "wof:name": "Villarreal Construction",
    "wof:placetype": "venue"
  },
  "geometry": {"coordinates":[-83.623604,39.037603],"type":"Point"}
}
