{
  "type": "Feature",
  "properties": {
    "iso:country":"US",
    "sg:address":"1224 Amelia Ave",
    "sg:city":"Findlay",
    "sg:classifiers":[
        {
            "category":"Building & Trades",
            "subcategory":"Plumbing",
            "type":"Services"
        }
    ],
    "sg:phone":"+1 419 422 1973",
    "sg:postcode":"45840",
    "sg:province":"OH",
    "sg:tags":[
        "plumbing",
        "contractor"
    ],
    "wof:name":"Keith Willford Plumbing & Htg",
    "wof:placetype":"venue"
},
  "geometry": {"coordinates":[-83.62998,41.025903],"type":"Point"}
}