{
  "type": "Feature",
  "properties": {
    "addr:full": "1224 Amelia Ave Findlay OH 45840",
    "addr:housenumber": "1224",
    "addr:postcode": "45840",
    "addr:street": "Amelia Ave",
    "iso:country": "US",
    "sg:address": "1224 Amelia Ave",
    "sg:city": "Findlay",
    "sg:classifiers": [
      {
        "category": "Building \u0026 Trades",
        "subcategory": "Plumbing",
        "type": "Services"
      }
    ],
    "sg:phone": "+1 419 422 1973",
    "sg:postcode": "45840",
    "sg:province": "OH",
    "sg:tags": [
      "plumbing",
      "contractor"
    ],
    "wof:name": "Keith Willford Plumbing \u0026 Htg",
    "wof:placetype": "venue"
  },
  "geometry": {"coordinates":[-83.62998,41.025903],"type":"Point"}
}
