{
  "type": "Feature",
  "properties": {
    "addr:full":"4507 N Holland Sylvania Ave Toledo OH 43623",
    "addr:housenumber":"4507",
    "addr:postcode":"43623",
    "addr:street":"N Holland Sylvania Ave",
    "iso:country":"US",
    "sg:address":"4507 N Holland Sylvania Ave",
    "sg:city":"Toledo",
    "sg:classifiers":[
        {
            "category":"Shopping",
            "subcategory":"Florist",
            "type":"Retail Goods"
        },
        {
            "category":"Shopping",
            "subcategory":"Gifts & Souvenirs",
            "type":"Retail Goods"
        }
    ],
    "sg:phone":"+1 419 882 3032",
    "sg:postcode":"43623",
    "sg:province":"OH",
    "wof:name":"Grams Florists & Gifts",
    "wof:placetype":"venue"
},
  "geometry": {"coordinates":[-83.691092,41.698221],"type":"Point"}
}