{
  "type": "Feature",
  "properties": {
    "addr:full":"1045 Meta Dr Cincinnati OH 45237",
    "addr:housenumber":"1045",
    "addr:postcode":"45237",
    "addr:street":"Meta Dr",
    "iso:country":"US",
    "sg:address":"1045 Meta Dr",
    "sg:city":"Cincinnati",
    "sg:classifiers":[
        {
            "category":"Manufacturing",
            "subcategory":"Tools & Machinery",
            "type":"Manufacturing & Wholesale Goods"
        },
        {
            "category":"Wholesale",
            "subcategory":"Machinery & Supplies",
            "type":"Manufacturing & Wholesale Goods"
        }
    ],
    "sg:phone":"+1 513 871 7867",
    "sg:postcode":"45237",
    "sg:province":"OH",
    "sg:tags":[
        "control",
        "flood",
        "pump",
        "equipment"
    ],
    "wof:name":"Blue Chip Pump",
    "wof:placetype":"venue"
},
  "geometry": {"coordinates":[-84.482631,39.175094],"type":"Point"}
}