{
  "type": "Feature",
  "properties": {
    "addr:full":"1436 Needmore Rd Dayton OH 45414",
    "addr:housenumber":"1436",
    "addr:postcode":"45414",
    "addr:street":"Needmore Rd",
    "iso:country":"US",
    "sg:address":"1436 Needmore Rd",
    "sg:city":"Dayton",
    "sg:classifiers":[
        {
            "category":"Retail",
            "subcategory":"Auto Rental",
            "type":"Services"
        }
    ],
    "sg:phone":"+1 937 278 0556",
    "sg:postcode":"45414",
    "sg:province":"OH",
    "sg:tags":[
        "renting",
        "automobile"
    ],
    "wof:name":"Enterprise Rent A Car",
    "wof:placetype":"venue"
},
  "geometry": {"coordinates":[-84.208077,39.817282],"type":"Point"}
}