{
  "type": "Feature",
  "properties": {
    "addr:full":"30 W 3rd St Cincinnati OH 45202",
    "addr:housenumber":"30",
    "addr:postcode":"45202",
    "addr:street":"W 3Rd St",
    "iso:country":"US",
    "sg:address":"30 W 3rd St",
    "sg:city":"Cincinnati",
    "sg:classifiers":[
        {
            "category":"Insurance",
            "subcategory":"Insurance Agent",
            "type":"Services"
        }
    ],
    "sg:phone":"+1 513 621 9650",
    "sg:postcode":"45202",
    "sg:province":"OH",
    "sg:website":"www.dbsfmb.com",
    "wof:name":"Diversified Brokerage Spec Inc",
    "wof:placetype":"venue"
},
  "geometry": {"coordinates":[-84.513615,39.098574],"type":"Point"}
}