{
  "type": "Feature",
  "properties": {
    "addr:full":"4033 Klein Ave Stow OH 44224",
    "addr:housenumber":"4033",
    "addr:postcode":"44224",
    "addr:street":"Klein Ave",
    "iso:country":"US",
    "sg:address":"4033 Klein Ave",
    "sg:city":"Stow",
    "sg:phone":"+1 330 688 6301",
    "sg:postcode":"44224",
    "sg:province":"OH",
    "sg:tags":[
        "product",
        "petroleum"
    ],
    "wof:name":"Swadley Oil & Gas Inc",
    "wof:placetype":"venue"
},
  "geometry": {"coordinates":[-81.429846,41.172664],"type":"Point"}
}