{
  "type": "Feature",
  "properties": {
    "iso:country":"US",
    "sg:address":"4898 Guerley Rd",
    "sg:city":"Cincinnati",
    "sg:classifiers":[
        {
            "category":"Health Services",
            "subcategory":"Doctor",
            "type":"Services"
        }
    ],
    "sg:phone":"+1 513 251 2700",
    "sg:postcode":"45238",
    "sg:province":"OH",
    "sg:tags":[
        "physician",
        "surgeon"
    ],
    "wof:name":"Healthy Beginning Inc",
    "wof:placetype":"venue"
},
  "geometry": {"coordinates":[-84.597211,39.118445],"type":"Point"}
}