{
  "type": "Feature",
  "properties": {
    "addr:full": "32 Howard Ave Columbus OH 43085",
    "addr:housenumber": "32",
    "addr:postcode": "43085",
    "addr:street": "Howard Ave",
    "iso:country": "US",
    "sg:address": "32 Howard Ave",
    "sg:city": "Columbus",
    "sg:classifiers": [
      {
        "category": "Wholesale",
        "subcategory": "Farm Supplies",
        "type": "Manufacturing \u0026 Wholesale Goods"
      }
    ],
    "sg:phone": "+1 614 846 3196",
    "sg:postcode": "43085",
    "sg:province": "OH",
    "sg:tags": [
      "queen",
      "bee",
      "provider"
    ],
    "wof:name": "Ohio Queen Breeders",
    "wof:placetype": "venue"
  },
  "geometry": {"coordinates":[-83.017155,40.083618],"type":"Point"}
}
