{
  "type": "Feature",
  "properties": {
    "addr:full":"1047 N Lisbon St Carrollton OH 44615",
    "addr:housenumber":"1047",
    "addr:postcode":"44615",
    "addr:street":"N Lisbon St",
    "iso:country":"US",
    "sg:address":"1047 N Lisbon St",
    "sg:city":"Carrollton",
    "sg:classifiers":[
        {
            "category":"Organizations",
            "subcategory":"Religious Organization",
            "type":"Services"
        }
    ],
    "sg:phone":"+1 330 627 1111",
    "sg:postcode":"44615",
    "sg:province":"OH",
    "sg:tags":[
        "clergy",
        "church"
    ],
    "wof:name":"Church Of Christ",
    "wof:placetype":"venue"
},
  "geometry": {"coordinates":[-81.08313800000001,40.579584],"type":"Point"}
}