{
  "type": "Feature",
  "properties": {
    "iso:country":"US",
    "sg:address":"135 W Elm St",
    "sg:city":"Wauseon",
    "sg:classifiers":[
        {
            "category":"Organizations",
            "subcategory":"Religious Organization",
            "type":"Services"
        }
    ],
    "sg:phone":"+1 419 335 5571",
    "sg:postcode":"43567",
    "sg:province":"OH",
    "sg:tags":[
        "church"
    ],
    "wof:name":"Congregational United Church",
    "wof:placetype":"venue"
},
  "geometry": {"coordinates":[-84.141864,41.549033],"type":"Point"}
}