{
  "type": "Feature",
  "properties": {
    "iso:country":"US",
    "sg:address":"1679 Lance Pointe Rd",
    "sg:city":"Maumee",
    "sg:classifiers":[
        {
            "category":"Professional",
            "subcategory":"Business Services",
            "type":"Services"
        }
    ],
    "sg:phone":"+1 419 897 7873",
    "sg:postcode":"43537",
    "sg:province":"OH",
    "sg:tags":[
        "water",
        "treatment"
    ],
    "wof:name":"Aquawave-Nature's Way",
    "wof:placetype":"venue"
},
  "geometry": {"coordinates":[-83.67103400000001,41.585396],"type":"Point"}
}