{
  "type": "Feature",
  "properties": {
    "addr:full": "63 E Western Reserve Rd Youngstown OH 44514",
    "addr:housenumber": "63",
    "addr:postcode": "44514",
    "addr:street": "E Western Reserve Rd",
    "iso:country": "US",
    "sg:address": "63 E Western Reserve Rd",
    "sg:city": "Youngstown",
    "sg:classifiers": [
      {
        "category": "Autos \u0026 Motor Vehicles",
        "subcategory": "Auto Supplies",
        "type": "Retail Goods"
      }
    ],
    "sg:phone": "+1 330 629 2776",
    "sg:postcode": "44514",
    "sg:province": "OH",
    "sg:tags": [
      "automobile",
      "alarm"
    ],
    "wof:name": "Total Image N Sound",
    "wof:placetype": "venue"
  },
  "geometry": {"coordinates":[-80.658593,40.987852],"type":"Point"}
}
