{
  "type": "Feature",
  "properties": {
    "addr:full": "130 Commerce Dr Loveland OH 45140",
    "addr:housenumber": "130",
    "addr:postcode": "45140",
    "addr:street": "Commerce Dr",
    "iso:country": "US",
    "sg:address": "130 Commerce Dr",
    "sg:city": "Loveland",
    "sg:classifiers": [
      {
        "category": "Manufacturing",
        "subcategory": "Tools \u0026 Machinery",
        "type": "Manufacturing \u0026 Wholesale Goods"
      }
    ],
    "sg:phone": "+1 513 697 9000",
    "sg:postcode": "45140",
    "sg:province": "OH",
    "sg:tags": [
      "industry",
      "mfg",
      "mach"
    ],
    "wof:name": "Amano Cincinatti Incorporated",
    "wof:placetype": "venue"
  },
  "geometry": {"coordinates":[-84.304216,39.281678],"type":"Point"}
}
