{
  "type": "Feature",
  "properties": {
    "iso:country":"US",
    "sg:address":"1734 Wall Rd",
    "sg:city":"Wadsworth",
    "sg:classifiers":[
        {
            "category":"Manufacturing",
            "subcategory":"Rubber & Plastics",
            "type":"Manufacturing & Wholesale Goods"
        }
    ],
    "sg:phone":"+1 330 334 6111",
    "sg:postcode":"44281",
    "sg:province":"OH",
    "sg:tags":[
        "product",
        "molded",
        "mfg"
    ],
    "wof:name":"Raydar Inc of Ohio",
    "wof:placetype":"venue"
},
  "geometry": {"coordinates":[-81.75548499999999,40.995709],"type":"Point"}
}