{
  "type": "Feature",
  "properties": {
    "addr:full":"7121 Medallion Ct Reynoldsburg OH 43068",
    "addr:housenumber":"7121",
    "addr:postcode":"43068",
    "addr:street":"Medallion Ct",
    "iso:country":"US",
    "sg:address":"7121 Medallion Ct",
    "sg:city":"Reynoldsburg",
    "sg:classifiers":[
        {
            "category":"Professional",
            "type":"Services"
        }
    ],
    "sg:phone":"+1 614 863 1847",
    "sg:postcode":"43068",
    "sg:province":"OH",
    "wof:name":"Tim Johnson",
    "wof:placetype":"venue"
},
  "geometry": {"coordinates":[-82.808868,39.963859],"type":"Point"}
}