{
  "type": "Feature",
  "properties": {
    "iso:country":"US",
    "sg:address":"1680 Norton Ct",
    "sg:city":"Columbus",
    "sg:classifiers":[
        {
            "category":"Professional",
            "subcategory":"Business Services",
            "type":"Services"
        }
    ],
    "sg:phone":"+1 614 853 4198",
    "sg:postcode":"43228",
    "sg:province":"OH",
    "sg:tags":[
        "translator",
        "interpreter"
    ],
    "wof:name":"Reliable Interpreting Agency",
    "wof:placetype":"venue"
},
  "geometry": {"coordinates":[-83.14399400000001,39.917493],"type":"Point"}
}