{
  "type": "Feature",
  "properties": {
    "addr:full": "133 S River St Franklin OH 45005",
    "addr:housenumber": "133",
    "addr:postcode": "45005",
    "addr:street": "S River St",
    "iso:country": "US",
    "sg:address": "133 S River St",
    "sg:city": "Franklin",
    "sg:classifiers": [
      {
        "category": "Manufacturing",
        "subcategory": "Tools \u0026 Machinery",
        "type": "Manufacturing \u0026 Wholesale Goods"
      }
    ],
    "sg:phone": "+1 937 743 5751",
    "sg:postcode": "45005",
    "sg:province": "OH",
    "sg:tags": [
      "machine",
      "shop",
      "industrial",
      "mfg"
    ],
    "wof:name": "Thompson \u0026 Ward Machines LLC",
    "wof:placetype": "venue"
  },
  "geometry": {"coordinates":[-84.31315,39.551805],"type":"Point"}
}
