{
  "type": "Feature",
  "properties": {
    "addr:full": "2213 Ridgeview Rd Columbus OH 43221",
    "addr:housenumber": "2213",
    "addr:postcode": "43221",
    "addr:street": "Ridgeview Rd",
    "iso:country": "US",
    "sg:address": "2213 Ridgeview Rd",
    "sg:city": "Columbus",
    "sg:classifiers": [
      {
        "category": "Building \u0026 Trades",
        "subcategory": "Construction",
        "type": "Services"
      }
    ],
    "sg:phone": "+1 614 989 1493",
    "sg:postcode": "43221",
    "sg:province": "OH",
    "sg:tags": [
      "residential"
    ],
    "wof:name": "Donovan Mathews Co",
    "wof:placetype": "venue"
  },
  "geometry": {"coordinates":[-83.071822,40.016],"type":"Point"}
}
