{
  "type": "Feature",
  "properties": {
    "iso:country":"US",
    "sg:address":"5712 Bridgetown Rd",
    "sg:city":"Cincinnati",
    "sg:classifiers":[
        {
            "category":"Banks & Credit Unions",
            "subcategory":"Bank",
            "type":"Services"
        }
    ],
    "sg:phone":"+1 513 661 6612",
    "sg:postcode":"45248",
    "sg:province":"OH",
    "sg:website":"www.pcbionline.com",
    "wof:name":"Peoples Community Bank",
    "wof:placetype":"venue"
},
  "geometry": {"coordinates":[-84.63592800000001,39.15906],"type":"Point"}
}