{
  "type": "Feature",
  "properties": {
    "addr:full":"1310 W 70th St Cleveland OH 44102",
    "addr:housenumber":"1310",
    "addr:postcode":"44102",
    "addr:street":"W 70Th St",
    "iso:country":"US",
    "sg:address":"1310 W 70th St",
    "sg:city":"Cleveland",
    "sg:classifiers":[
        {
            "category":"Building & Trades",
            "subcategory":"Construction",
            "type":"Services"
        }
    ],
    "sg:phone":"+1 216 631 7514",
    "sg:postcode":"44102",
    "sg:province":"OH",
    "sg:tags":[
        "general",
        "contractor"
    ],
    "wof:name":"Mike O'Malley Construction Co",
    "wof:placetype":"venue"
},
  "geometry": {"coordinates":[-81.73349,41.487264],"type":"Point"}
}