{
  "type": "Feature",
  "properties": {
    "iso:country":"US",
    "sg:address":"3280 Pearl Rd",
    "sg:city":"Medina",
    "sg:classifiers":[
        {
            "category":"Sports & Exercise",
            "subcategory":"Golf",
            "type":"Entertainment"
        }
    ],
    "sg:phone":"+1 330 725 2829",
    "sg:postcode":"44256",
    "sg:province":"OH",
    "sg:tags":[
        "course"
    ],
    "wof:name":"Bunker Hill Maintenance",
    "wof:placetype":"venue"
},
  "geometry": {"coordinates":[-81.850397,41.188303],"type":"Point"}
}