{
  "type": "Feature",
  "properties": {
    "iso:country":"US",
    "sg:address":"740 E Washington St",
    "sg:city":"Medina",
    "sg:classifiers":[
        {
            "category":"Health Services",
            "subcategory":"Medical Lab",
            "type":"Services"
        }
    ],
    "sg:phone":"+1 330 722 8844",
    "sg:postcode":"44256",
    "sg:province":"OH",
    "sg:tags":[
        "laboratory"
    ],
    "wof:name":"Hackenberg Dental Lab",
    "wof:placetype":"venue"
},
  "geometry": {"coordinates":[-81.850374,41.138072],"type":"Point"}
}