{
  "type": "Feature",
  "properties": {
    "addr:full":"2000 Summit Rd Kent OH 44240",
    "addr:housenumber":"2000",
    "addr:postcode":"44240",
    "addr:street":"Summit Rd",
    "iso:country":"US",
    "sg:address":"2000 Summit Rd",
    "sg:city":"Kent",
    "sg:classifiers":[
        {
            "category":"Professional",
            "type":"Services"
        }
    ],
    "sg:phone":"+1 330 676 9273",
    "sg:postcode":"44240",
    "sg:province":"OH",
    "sg:tags":[
        "establishment"
    ],
    "wof:name":"Parta",
    "wof:placetype":"venue"
},
  "geometry": {"coordinates":[-81.31991600000001,41.138148],"type":"Point"}
}