{
  "type": "Feature",
  "properties": {
    "addr:full": "500 W 6th Ave Lancaster OH 43130",
    "addr:housenumber": "500",
    "addr:postcode": "43130",
    "addr:street": "W 6Th Ave",
    "iso:country": "US",
    "sg:address": "500 W 6th Ave",
    "sg:city": "Lancaster",
    "sg:classifiers": [
      {
        "category": "Autos \u0026 Motor Vehicles",
        "subcategory": "Auto Supplies",
        "type": "Retail Goods"
      }
    ],
    "sg:phone": "+1 740 654 3093",
    "sg:postcode": "43130",
    "sg:province": "OH",
    "sg:tags": [
      "parts",
      "tire"
    ],
    "wof:name": "Tire Shop",
    "wof:placetype": "venue"
  },
  "geometry": {"coordinates":[-82.610854,39.720147],"type":"Point"}
}
