{
  "type": "Feature",
  "properties": {
    "iso:country":"US",
    "sg:address":"1355 E Main St",
    "sg:city":"Bellevue",
    "sg:classifiers":[
        {
            "category":"Restaurant",
            "type":"Food & Drink"
        }
    ],
    "sg:phone":"+1 419 483 5004",
    "sg:postcode":"44811",
    "sg:province":"OH",
    "sg:tags":[
        "eating"
    ],
    "wof:name":"Taco Bell",
    "wof:placetype":"venue"
},
  "geometry": {"coordinates":[-82.8245,41.272054],"type":"Point"}
}