{
  "type": "Feature",
  "properties": {
    "addr:full": "8414 Market St Youngstown OH 44512",
    "addr:housenumber": "8414",
    "addr:postcode": "44512",
    "addr:street": "Market St",
    "iso:country": "US",
    "sg:address": "8414 Market St",
    "sg:city": "Youngstown",
    "sg:classifiers": [
      {
        "category": "Personal",
        "type": "Services"
      }
    ],
    "sg:phone": "+1 330 965 1313",
    "sg:postcode": "44512",
    "sg:province": "OH",
    "sg:tags": [
      "program",
      "physical",
      "exercise",
      "fitness"
    ],
    "wof:name": "Fitness Results For Women",
    "wof:placetype": "venue"
  },
  "geometry": {"coordinates":[-80.662812,40.994239],"type":"Point"}
}
