{
  "type": "Feature",
  "properties": {
    "addr:full":"536 Mill St Chillicothe OH 45601",
    "addr:housenumber":"536",
    "addr:postcode":"45601",
    "addr:street":"Mill St",
    "iso:country":"US",
    "sg:address":"536 Mill St",
    "sg:city":"Chillicothe",
    "sg:classifiers":[
        {
            "category":"Organizations",
            "subcategory":"Religious Organization",
            "type":"Services"
        }
    ],
    "sg:phone":"+1 740 775 0343",
    "sg:postcode":"45601",
    "sg:province":"OH",
    "sg:tags":[
        "church"
    ],
    "wof:name":"Zion Baptist Church Outreach",
    "wof:placetype":"venue"
},
  "geometry": {"coordinates":[-82.999302,39.337302],"type":"Point"}
}