{
  "type": "Feature",
  "properties": {
    "iso:country":"US",
    "sg:address":"970 Lakeview Rd",
    "sg:city":"Cleveland",
    "sg:classifiers":[
        {
            "category":"Food & Beverages",
            "subcategory":"Groceries & Convenience Stores",
            "type":"Retail Goods"
        }
    ],
    "sg:phone":"+1 216 851 1771",
    "sg:postcode":"44108",
    "sg:province":"OH",
    "wof:name":"Alex Food Market",
    "wof:placetype":"venue"
},
  "geometry": {"coordinates":[-81.606758,41.531479],"type":"Point"}
}