{
  "type": "Feature",
  "properties": {
    "addr:full": "970 Lakeview Rd Cleveland OH 44108",
    "addr:housenumber": "970",
    "addr:postcode": "44108",
    "addr:street": "Lakeview Rd",
    "iso:country": "US",
    "sg:address": "970 Lakeview Rd",
    "sg:city": "Cleveland",
    "sg:classifiers": [
      {
        "category": "Food \u0026 Beverages",
        "subcategory": "Groceries \u0026 Convenience Stores",
        "type": "Retail Goods"
      }
    ],
    "sg:phone": "+1 216 851 1771",
    "sg:postcode": "44108",
    "sg:province": "OH",
    "wof:name": "Alex Food Market",
    "wof:placetype": "venue"
  },
  "geometry": {"coordinates":[-81.606758,41.531479],"type":"Point"}
}
