{
  "type": "Feature",
  "properties": {
    "addr:full": "8427 W South Range Rd Salem OH 44460",
    "addr:housenumber": "8427",
    "addr:postcode": "44460",
    "addr:street": "W South Range Rd",
    "iso:country": "US",
    "sg:address": "8427 W South Range Rd",
    "sg:city": "Salem",
    "sg:classifiers": [
      {
        "category": "Building \u0026 Trades",
        "subcategory": "Landscaping Services",
        "type": "Services"
      }
    ],
    "sg:phone": "+1 330 533 7530",
    "sg:postcode": "44460",
    "sg:province": "OH",
    "sg:tags": [
      "tree"
    ],
    "wof:name": "Mc Knight Tree Svc",
    "wof:placetype": "venue"
  },
  "geometry": {"coordinates":[-80.808958,40.944038],"type":"Point"}
}
