{
  "type": "Feature",
  "properties": {
    "addr:full": "7759 Blackberry Ln Gates Mills OH 44040",
    "addr:housenumber": "7759",
    "addr:postcode": "44040",
    "addr:street": "Blackberry Ln",
    "iso:country": "US",
    "sg:address": "7759 Blackberry Ln",
    "sg:city": "Gates Mills",
    "sg:classifiers": [
      {
        "category": "Airline",
        "type": "Transportation"
      }
    ],
    "sg:phone": "+1 440 423 0707",
    "sg:postcode": "44040",
    "sg:province": "OH",
    "sg:tags": [
      "nonscheduled",
      "air"
    ],
    "wof:name": "Mustang Air Services",
    "wof:placetype": "venue"
  },
  "geometry": {"coordinates":[-81.399546,41.562247],"type":"Point"}
}
