{
  "type": "Feature",
  "properties": {
    "iso:country":"US",
    "sg:address":"1353 Lear Industrial Pkwy",
    "sg:city":"Avon",
    "sg:classifiers":[
        {
            "category":"Building & Trades",
            "subcategory":"Landscaping Services",
            "type":"Services"
        }
    ],
    "sg:phone":"+1 440 937 7760",
    "sg:postcode":"44011",
    "sg:province":"OH",
    "wof:name":"Pattie Group Inc",
    "wof:placetype":"venue"
},
  "geometry": {"coordinates":[-81.992518,41.471923],"type":"Point"}
}