{
  "type": "Feature",
  "properties": {
    "iso:country":"US",
    "sg:address":"5660 Monroe St",
    "sg:city":"Sylvania",
    "sg:classifiers":[
        {
            "category":"Health Services",
            "subcategory":"Doctor",
            "type":"Services"
        },
        {
            "category":"Health Services",
            "subcategory":"Medical Lab",
            "type":"Services"
        }
    ],
    "sg:phone":"+1 419 882 8327",
    "sg:postcode":"43560",
    "sg:province":"OH",
    "sg:tags":[
        "laboratory",
        "imaging",
        "diagnostic"
    ],
    "wof:name":"Toledo Medical Imaging",
    "wof:placetype":"venue"
},
  "geometry": {"coordinates":[-83.674041,41.708989],"type":"Point"}
}