{
  "type": "Feature",
  "properties": {
    "addr:full":"125 Patterson St Piketon OH 45661",
    "addr:housenumber":"125",
    "addr:postcode":"45661",
    "addr:street":"Patterson St",
    "iso:country":"US",
    "sg:address":"125 Patterson St",
    "sg:city":"Piketon",
    "sg:classifiers":[
        {
            "category":"Local Transit",
            "type":"Transportation"
        }
    ],
    "sg:phone":"+1 740 226 5433",
    "sg:postcode":"45661",
    "sg:province":"OH",
    "sg:tags":[
        "ambulance"
    ],
    "wof:name":"Life Ambulance Svc",
    "wof:placetype":"venue"
},
  "geometry": {"coordinates":[-83.015821,39.063947],"type":"Point"}
}