{
  "type": "Feature",
  "properties": {
    "iso:country":"US",
    "sg:address":"3035 State Rte 95",
    "sg:city":"Edison",
    "sg:classifiers":[
        {
            "category":"Banks & Credit Unions",
            "subcategory":"Bank",
            "type":"Services"
        }
    ],
    "sg:phone":"+1 419 946 6530",
    "sg:postcode":"43320",
    "sg:province":"OH",
    "sg:tags":[
        "cashing",
        "check"
    ],
    "wof:name":"Sunset Cash Advance",
    "wof:placetype":"venue"
},
  "geometry": {"coordinates":[-82.86965,40.559075],"type":"Point"}
}