{
  "type": "Feature",
  "properties": {
    "addr:full":"443 E Market St Warren OH 44481",
    "addr:housenumber":"443",
    "addr:postcode":"44481",
    "addr:street":"E Market St",
    "iso:country":"US",
    "sg:address":"443 E Market St",
    "sg:city":"Warren",
    "sg:classifiers":[
        {
            "category":"Personal",
            "subcategory":"Massage",
            "type":"Services"
        }
    ],
    "sg:phone":"+1 330 399 5556",
    "sg:postcode":"44481",
    "sg:province":"OH",
    "wof:name":"Oriental Sauna",
    "wof:placetype":"venue"
},
  "geometry": {"coordinates":[-80.81249099999999,41.23627],"type":"Point"}
}