{
  "type": "Feature",
  "properties": {
    "addr:full":"3528 Millvale Ave NE Canton OH 44705",
    "addr:housenumber":"3528",
    "addr:postcode":"44705",
    "addr:street":"Millvale Ave Ne",
    "iso:country":"US",
    "sg:address":"3528 Millvale Ave NE",
    "sg:city":"Canton",
    "sg:classifiers":[
        {
            "category":"Health Services",
            "subcategory":"Nursing And Care Facility",
            "type":"Services"
        }
    ],
    "sg:phone":"+1 330 455 1905",
    "sg:postcode":"44705",
    "sg:province":"OH",
    "sg:tags":[
        "disabled",
        "independent",
        "for",
        "living"
    ],
    "wof:name":"Cedar Oaks",
    "wof:placetype":"venue"
},
  "geometry": {"coordinates":[-81.313112,40.833394],"type":"Point"}
}