{
  "type": "Feature",
  "properties": {
    "addr:full": "500 Richards Rd Columbus OH 43214",
    "addr:housenumber": "500",
    "addr:postcode": "43214",
    "addr:street": "Richards Rd",
    "iso:country": "US",
    "sg:address": "500 Richards Rd",
    "sg:city": "Columbus",
    "sg:classifiers": [
      {
        "category": "Shopping",
        "type": "Retail Goods"
      }
    ],
    "sg:phone": "+1 614 262 7083",
    "sg:postcode": "43214",
    "sg:province": "OH",
    "sg:tags": [
      "used",
      "merchandise"
    ],
    "wof:name": "Jeffrey Derr",
    "wof:placetype": "venue"
  },
  "geometry": {"coordinates":[-83.000947,40.039438],"type":"Point"}
}
