{
  "type": "Feature",
  "properties": {
    "addr:full": "10970 Co Rd H Delta OH 43515",
    "addr:housenumber": "10970",
    "addr:postcode": "43515",
    "addr:street": "Co Rd H",
    "iso:country": "US",
    "sg:address": "10970 Co Rd H",
    "sg:city": "Delta",
    "sg:classifiers": [
      {
        "category": "Personal",
        "subcategory": "Beauty Salon",
        "type": "Services"
      }
    ],
    "sg:phone": "+1 419 822 5005",
    "sg:postcode": "43515",
    "sg:province": "OH",
    "wof:name": "Mulls Beauty Salon",
    "wof:placetype": "venue"
  },
  "geometry": {"coordinates":[-84.075556,41.587883],"type":"Point"}
}
