{
  "type": "Feature",
  "properties": {
    "addr:full":"5409 Roberts Rd Hilliard OH 43026",
    "addr:housenumber":"5409",
    "addr:postcode":"43026",
    "addr:street":"Roberts Rd",
    "iso:country":"US",
    "sg:address":"5409 Roberts Rd",
    "sg:city":"Hilliard",
    "sg:classifiers":[
        {
            "category":"Health Services",
            "subcategory":"Chiropractor",
            "type":"Services"
        }
    ],
    "sg:phone":"+1 614 771 4200",
    "sg:postcode":"43026",
    "sg:province":"OH",
    "wof:name":"A Better Backs Chiropractic",
    "wof:placetype":"venue"
},
  "geometry": {"coordinates":[-83.150746,40.003653],"type":"Point"}
}