{
  "type": "Feature",
  "properties": {
    "addr:full": "1156 McArthur Rd Jeffersonville OH 43128",
    "addr:housenumber": "1156",
    "addr:postcode": "43128",
    "addr:street": "Mcarthur Rd",
    "iso:country": "US",
    "sg:address": "1156 McArthur Rd",
    "sg:city": "Jeffersonville",
    "sg:classifiers": [
      {
        "category": "Home \u0026 Garden",
        "subcategory": "Household Appliances",
        "type": "Retail Goods"
      }
    ],
    "sg:phone": "+1 740 426 8711",
    "sg:postcode": "43128",
    "sg:province": "OH",
    "wof:name": "Hoover Company",
    "wof:placetype": "venue"
  },
  "geometry": {"coordinates":[-83.540503,39.650848],"type":"Point"}
}
