{
  "type": "Feature",
  "properties": {
    "iso:country":"US",
    "sg:address":"21245 Lorain Rd",
    "sg:city":"Cleveland",
    "sg:classifiers":[
        {
            "category":"Wholesale",
            "subcategory":"Non-durable Goods",
            "type":"Manufacturing & Wholesale Goods"
        }
    ],
    "sg:phone":"+1 440 331 1230",
    "sg:postcode":"44126",
    "sg:province":"OH",
    "wof:name":"McGovern & Assoc Inc",
    "wof:placetype":"venue"
},
  "geometry": {"coordinates":[-81.85689600000001,41.444437],"type":"Point"}
}