{
  "type": "Feature",
  "properties": {
    "addr:full":"8011 W Chester Rd West Chester OH 45069",
    "addr:housenumber":"8011",
    "addr:postcode":"45069",
    "addr:street":"W Chester Rd",
    "iso:country":"US",
    "sg:address":"8011 W Chester Rd",
    "sg:city":"West Chester",
    "sg:classifiers":[
        {
            "category":"Manufacturing",
            "subcategory":"Printing",
            "type":"Manufacturing & Wholesale Goods"
        }
    ],
    "sg:phone":"+1 513 779 7595",
    "sg:postcode":"45069",
    "sg:province":"OH",
    "sg:tags":[
        "commercial"
    ],
    "wof:name":"Proforma Comm Graphics",
    "wof:placetype":"venue"
},
  "geometry": {"coordinates":[-84.36429800000001,39.317825],"type":"Point"}
}