{
  "type": "Feature",
  "properties": {
    "iso:country":"US",
    "sg:address":"8011 W Chester Rd",
    "sg:city":"West Chester",
    "sg:classifiers":[
        {
            "category":"Manufacturing",
            "subcategory":"Printing",
            "type":"Manufacturing & Wholesale Goods"
        }
    ],
    "sg:phone":"+1 513 779 7595",
    "sg:postcode":"45069",
    "sg:province":"OH",
    "sg:tags":[
        "commercial"
    ],
    "wof:name":"Proforma Comm Graphics",
    "wof:placetype":"venue"
},
  "geometry": {"coordinates":[-84.364298,39.317825],"type":"Point"}
}