{
  "type": "Feature",
  "properties": {
    "iso:country":"US",
    "sg:address":"1616 Industry Rd",
    "sg:city":"Atwater",
    "sg:classifiers":[
        {
            "category":"Professional",
            "subcategory":"Advertising",
            "type":"Services"
        }
    ],
    "sg:phone":"+1 330 947 2050",
    "sg:postcode":"44201",
    "sg:province":"OH",
    "sg:tags":[
        "counselor"
    ],
    "sg:website":"www.studioontopofthebarn.com",
    "wof:name":"Studio On Top Of The Barn",
    "wof:placetype":"venue"
},
  "geometry": {"coordinates":[-81.194903,41.030967],"type":"Point"}
}