{
  "type": "Feature",
  "properties": {
    "iso:country":"US",
    "sg:address":"200 E High St",
    "sg:city":"Oxford",
    "sg:classifiers":[
        {
            "category":"Organizations",
            "subcategory":"Community Association",
            "type":"Services"
        }
    ],
    "sg:phone":"+1 513 523 6209",
    "sg:postcode":"45056",
    "sg:province":"IN",
    "sg:tags":[
        "sorority",
        "fraternity"
    ],
    "sg:website":"www.alphaofbetathetapi.com",
    "wof:name":"Beta Theta Pi",
    "wof:placetype":"venue"
},
  "geometry": {"coordinates":[-84.737653,39.510422],"type":"Point"}
}