{
  "type": "Feature",
  "properties": {
    "addr:full":"20 Trumbull Ct Youngstown OH 44505",
    "addr:housenumber":"20",
    "addr:postcode":"44505",
    "addr:street":"Trumbull Ct",
    "iso:country":"US",
    "sg:address":"20 Trumbull Ct",
    "sg:city":"Youngstown",
    "sg:classifiers":[
        {
            "category":"Real Estate",
            "subcategory":"Real Estate Operator",
            "type":"Services"
        }
    ],
    "sg:phone":"+1 330 759 1772",
    "sg:postcode":"44505",
    "sg:province":"OH",
    "sg:tags":[
        "apartment"
    ],
    "wof:name":"Oaktree Place Apartments",
    "wof:placetype":"venue"
},
  "geometry": {"coordinates":[-80.664174,41.141629],"type":"Point"}
}