{
  "type": "Feature",
  "properties": {
    "addr:full":"5625 Memphis Ave Cleveland OH 44144",
    "addr:housenumber":"5625",
    "addr:postcode":"44144",
    "addr:street":"Memphis Ave",
    "iso:country":"US",
    "sg:address":"5625 Memphis Ave",
    "sg:city":"Cleveland",
    "sg:classifiers":[
        {
            "category":"Wholesale",
            "subcategory":"Machinery & Supplies",
            "type":"Manufacturing & Wholesale Goods"
        }
    ],
    "sg:phone":"+1 216 749 0463",
    "sg:postcode":"44144",
    "sg:province":"OH",
    "sg:tags":[
        "equipment",
        "establishment"
    ],
    "wof:name":"Ohio Casket Company",
    "wof:placetype":"venue"
},
  "geometry": {"coordinates":[-81.725836,41.439824],"type":"Point"}
}