{
  "type": "Feature",
  "properties": {
    "addr:full":"130 E Simpson St Alliance OH 44601",
    "addr:housenumber":"130",
    "addr:postcode":"44601",
    "addr:street":"E Simpson St",
    "iso:country":"US",
    "sg:address":"130 E Simpson St",
    "sg:city":"Alliance",
    "sg:classifiers":[
        {
            "category":"Real Estate",
            "subcategory":"Real Estate Operator",
            "type":"Services"
        }
    ],
    "sg:phone":"+1 330 821 7965",
    "sg:postcode":"44601",
    "sg:province":"OH",
    "sg:tags":[
        "apartment"
    ],
    "wof:name":"Stark Metropolitan Housing",
    "wof:placetype":"venue"
},
  "geometry": {"coordinates":[-81.10288199999999,40.905915],"type":"Point"}
}