{
  "type": "Feature",
  "properties": {
    "iso:country":"US",
    "sg:address":"228 Lexington Ave",
    "sg:city":"Mansfield",
    "sg:classifiers":[
        {
            "category":"Restaurant",
            "type":"Food & Drink"
        }
    ],
    "sg:phone":"+1 419 522 0019",
    "sg:postcode":"44907",
    "sg:province":"OH",
    "wof:name":"Hardee's",
    "wof:placetype":"venue"
},
  "geometry": {"coordinates":[-82.52086,40.748342],"type":"Point"}
}