{
  "type": "Feature",
  "properties": {
    "addr:full":"10071 Darrow Rd Twinsburg OH 44087",
    "addr:housenumber":"10071",
    "addr:postcode":"44087",
    "addr:street":"Darrow Rd",
    "iso:country":"US",
    "sg:address":"10071 Darrow Rd",
    "sg:city":"Twinsburg",
    "sg:classifiers":[
        {
            "category":"Education",
            "subcategory":"Special Training",
            "type":"Public Place"
        }
    ],
    "sg:phone":"+1 330 425 0797",
    "sg:postcode":"44087",
    "sg:province":"OH",
    "sg:tags":[
        "tutoring"
    ],
    "wof:name":"Learning RX",
    "wof:placetype":"venue"
},
  "geometry": {"coordinates":[-81.43990700000001,41.339577],"type":"Point"}
}