{
  "type": "Feature",
  "properties": {
    "addr:full": "1085 Polaris Pkwy Columbus OH 43240",
    "addr:housenumber": "1085",
    "addr:postcode": "43240",
    "addr:street": "Polaris Pkwy",
    "iso:country": "US",
    "sg:address": "1085 Polaris Pkwy",
    "sg:city": "Columbus",
    "sg:classifiers": [
      {
        "category": "Restaurant",
        "type": "Food \u0026 Drink"
      }
    ],
    "sg:menulink": "http://www.allmenus.com/oh/columbus-city/161218-cheeburger-cheeburger/menu/",
    "sg:phone": "+1 614 430 8451",
    "sg:postcode": "43240",
    "sg:province": "OH",
    "sg:tags": [
      "burger",
      "american",
      "diner"
    ],
    "wof:name": "Cheeburger Cheeburger",
    "wof:placetype": "venue"
  },
  "geometry": {"coordinates":[-82.992402,40.145013],"type":"Point"}
}
