{
  "type": "Feature",
  "properties": {
    "addr:full": "4530 Kenny Rd Columbus OH 43220",
    "addr:housenumber": "4530",
    "addr:postcode": "43220",
    "addr:street": "Kenny Rd",
    "iso:country": "US",
    "sg:address": "4530 Kenny Rd",
    "sg:city": "Columbus",
    "sg:classifiers": [
      {
        "category": "Shopping",
        "subcategory": "Pharmacy",
        "type": "Retail Goods"
      }
    ],
    "sg:phone": "+1 614 326 0654",
    "sg:postcode": "43220",
    "sg:province": "OH",
    "wof:name": "Walgreens",
    "wof:placetype": "venue"
  },
  "geometry": {"coordinates":[-83.049541,40.05345],"type":"Point"}
}
