{
  "type": "Feature",
  "properties": {
    "addr:full": "459 Moose Ridge Rd Woodsfield OH 43793",
    "addr:housenumber": "459",
    "addr:postcode": "43793",
    "addr:street": "Moose Ridge Rd",
    "iso:country": "US",
    "sg:address": "459 Moose Ridge Rd",
    "sg:city": "Woodsfield",
    "sg:classifiers": [
      {
        "category": "Government",
        "subcategory": "Office",
        "type": "Public Place"
      }
    ],
    "sg:phone": "+1 740 472 1765",
    "sg:postcode": "43793",
    "sg:province": "OH",
    "sg:tags": [
      "executive"
    ],
    "wof:name": "Center Township",
    "wof:placetype": "venue"
  },
  "geometry": {"coordinates":[-81.125569,39.76016],"type":"Point"}
}
