{
  "type": "Feature",
  "properties": {
    "iso:country":"US",
    "sg:address":"70 Cove Ct",
    "sg:city":"Chagrin Falls",
    "sg:classifiers":[
        {
            "category":"Real Estate",
            "subcategory":"Architect",
            "type":"Services"
        }
    ],
    "sg:phone":"+1 440 543 8018",
    "sg:postcode":"44023",
    "sg:province":"OH",
    "sg:tags":[
        "home",
        "planning",
        "design"
    ],
    "wof:name":"Home Planning",
    "wof:placetype":"venue"
},
  "geometry": {"coordinates":[-81.29328599999999,41.39738],"type":"Point"}
}