{
  "type": "Feature",
  "properties": {
    "addr:full": "4935 Crooked Run Rd NW New Philadelphia OH 44663",
    "addr:housenumber": "4935",
    "addr:postcode": "44663",
    "addr:street": "Crooked Run Rd Nw New Philadelphia",
    "iso:country": "US",
    "sg:address": "4935 Crooked Run Rd NW",
    "sg:city": "New Philadelphia",
    "sg:classifiers": [
      {
        "category": "Farming",
        "subcategory": "Farm",
        "type": "Manufacturing \u0026 Wholesale Goods"
      }
    ],
    "sg:phone": "+1 330 339 5786",
    "sg:postcode": "44663",
    "sg:province": "OH",
    "sg:tags": [
      "crop",
      "general"
    ],
    "wof:name": "Mm Wenger Farm Family Part",
    "wof:placetype": "venue"
  },
  "geometry": {"coordinates":[-81.550969,40.482839],"type":"Point"}
}
