{
  "type": "Feature",
  "properties": {
    "addr:full": "8092 W Chester Rd West Chester OH 45069",
    "addr:housenumber": "8092",
    "addr:postcode": "45069",
    "addr:street": "W Chester Rd",
    "iso:country": "US",
    "sg:address": "8092 W Chester Rd",
    "sg:city": "West Chester",
    "sg:classifiers": [
      {
        "category": "Organizations",
        "subcategory": "Professional Association",
        "type": "Services"
      }
    ],
    "sg:phone": "+1 513 755 3280",
    "sg:postcode": "45069",
    "sg:province": "OH",
    "wof:name": "Islamic Education Council",
    "wof:placetype": "venue"
  },
  "geometry": {"coordinates":[-84.359723,39.317733],"type":"Point"}
}
