{
  "type": "Feature",
  "properties": {
    "iso:country":"US",
    "sg:address":"286 Peterson Rd",
    "sg:city":"Xenia",
    "sg:phone":"+1 937 376 2686",
    "sg:postcode":"45385",
    "sg:province":"OH",
    "sg:tags":[
        "hog",
        "farm",
        "corn",
        "cash",
        "field",
        "grain",
        "cr",
        "or",
        "feedlot"
    ],
    "wof:name":"Ronald Johannes Farm",
    "wof:placetype":"venue"
},
  "geometry": {"coordinates":[-83.928281,39.622205],"type":"Point"}
}