{
  "type": "Feature",
  "properties": {
    "addr:full": "6689 Co Rd 17 Wauseon OH 43567",
    "addr:housenumber": "6689;17",
    "addr:postcode": "43567",
    "addr:street": "Co Rd",
    "iso:country": "US",
    "sg:address": "6689 Co Rd 17",
    "sg:city": "Wauseon",
    "sg:classifiers": [
      {
        "category": "Shopping",
        "subcategory": "Florist",
        "type": "Retail Goods"
      }
    ],
    "sg:phone": "+1 419 337 4642",
    "sg:postcode": "43567",
    "sg:province": "OH",
    "wof:name": "Plant Shop The",
    "wof:placetype": "venue"
  },
  "geometry": {"coordinates":[-84.19223,41.567295],"type":"Point"}
}
