{
  "type": "Feature",
  "properties": {
    "addr:full":"980 Palmyra Rd SW Warren OH 44485",
    "addr:housenumber":"980",
    "addr:postcode":"44485",
    "addr:street":"Palmyra Rd Sw",
    "iso:country":"US",
    "sg:address":"980 Palmyra Rd SW",
    "sg:city":"Warren",
    "sg:classifiers":[
        {
            "category":"Personal",
            "subcategory":"Beauty Salon",
            "type":"Services"
        }
    ],
    "sg:phone":"+1 330 394 8211",
    "sg:postcode":"44485",
    "sg:province":"OH",
    "wof:name":"Hair-Is-Es Hair Clinic",
    "wof:placetype":"venue"
},
  "geometry": {"coordinates":[-80.83111100000001,41.228295],"type":"Point"}
}