{
  "type": "Feature",
  "properties": {
    "iso:country":"US",
    "sg:address":"203 S Market St",
    "sg:city":"Wooster",
    "sg:phone":"+1 330 263 6246",
    "sg:postcode":"44691",
    "sg:province":"OH",
    "sg:tags":[
        "transmission",
        "facsimile"
    ],
    "wof:name":"Mark II Businesss Systems",
    "wof:placetype":"venue"
},
  "geometry": {"coordinates":[-81.939621,40.796951],"type":"Point"}
}