{
  "type": "Feature",
  "properties": {
    "addr:full": "203 S Market St Wooster OH 44691",
    "addr:housenumber": "203",
    "addr:postcode": "44691",
    "addr:street": "S Market St",
    "iso:country": "US",
    "sg:address": "203 S Market St",
    "sg:city": "Wooster",
    "sg:phone": "+1 330 263 6246",
    "sg:postcode": "44691",
    "sg:province": "OH",
    "sg:tags": [
      "transmission",
      "facsimile"
    ],
    "wof:name": "Mark II Businesss Systems",
    "wof:placetype": "venue"
  },
  "geometry": {"coordinates":[-81.939621,40.796951],"type":"Point"}
}
