{
  "type": "Feature",
  "properties": {
    "addr:full":"828 Som Center Rd Cleveland OH 44143",
    "addr:housenumber":"828",
    "addr:postcode":"44143",
    "addr:street":"Som Center Rd",
    "iso:country":"US",
    "sg:address":"828 Som Center Rd",
    "sg:city":"Cleveland",
    "sg:classifiers":[
        {
            "category":"Manufacturing",
            "subcategory":"Pottery",
            "type":"Manufacturing & Wholesale Goods"
        }
    ],
    "sg:phone":"+1 440 684 0001",
    "sg:postcode":"44143",
    "sg:province":"OH",
    "sg:tags":[
        "product",
        "mfg"
    ],
    "wof:name":"Spirit Of Clay",
    "wof:placetype":"venue"
},
  "geometry": {"coordinates":[-81.438869,41.537997],"type":"Point"}
}