{
  "type": "Feature",
  "properties": {
    "addr:full": "5430 Glenway Ave Cincinnati OH 45238",
    "addr:housenumber": "5430",
    "addr:postcode": "45238",
    "addr:street": "Glenway Ave",
    "iso:country": "US",
    "sg:address": "5430 Glenway Ave",
    "sg:city": "Cincinnati",
    "sg:classifiers": [
      {
        "category": "Food \u0026 Beverages",
        "subcategory": "Liquor \u0026 Beverages",
        "type": "Retail Goods"
      }
    ],
    "sg:phone": "+1 513 922 0496",
    "sg:postcode": "45238",
    "sg:province": "OH",
    "sg:tags": [
      "alcoholic"
    ],
    "wof:name": "Smile Drive Thru",
    "wof:placetype": "venue"
  },
  "geometry": {"coordinates":[-84.606697,39.129623],"type":"Point"}
}
