{
  "type": "Feature",
  "properties": {
    "addr:full":"2977 Lamb Ave Columbus OH 43219",
    "addr:housenumber":"2977",
    "addr:postcode":"43219",
    "addr:street":"Lamb Ave",
    "iso:country":"US",
    "sg:address":"2977 Lamb Ave",
    "sg:city":"Columbus",
    "sg:classifiers":[
        {
            "category":"Wholesale",
            "subcategory":"Machinery & Supplies",
            "type":"Manufacturing & Wholesale Goods"
        }
    ],
    "sg:phone":"+1 614 471 5200",
    "sg:postcode":"43219",
    "sg:province":"OH",
    "sg:tags":[
        "tape"
    ],
    "sg:website":"www.marcyadhesives.com",
    "wof:name":"Marcy Enterprise Inc",
    "wof:placetype":"venue"
},
  "geometry": {"coordinates":[-82.92798999999999,39.996858],"type":"Point"}
}