{
  "type": "Feature",
  "properties": {
    "addr:full":"860 Ansonia St Oregon OH 43616",
    "addr:housenumber":"860",
    "addr:postcode":"43616",
    "addr:street":"Ansonia St",
    "iso:country":"US",
    "sg:address":"860 Ansonia St",
    "sg:city":"Oregon",
    "sg:classifiers":[
        {
            "category":"Personal",
            "subcategory":"Hair Removal",
            "type":"Services"
        }
    ],
    "sg:phone":"+1 419 697 3814",
    "sg:postcode":"43616",
    "sg:province":"OH",
    "sg:tags":[
        "removing"
    ],
    "wof:name":"Willow Bend",
    "wof:placetype":"venue"
},
  "geometry": {"coordinates":[-83.48783299999999,41.634372],"type":"Point"}
}