{
  "type": "Feature",
  "properties": {
    "addr:full": "1927 S State Route 53 Tiffin OH 44883",
    "addr:housenumber": "1927",
    "addr:postcode": "44883",
    "addr:street": "S State Route 53",
    "iso:country": "US",
    "sg:address": "1927 S State Route 53",
    "sg:city": "Tiffin",
    "sg:classifiers": [
      {
        "category": "Restaurant",
        "type": "Food \u0026 Drink"
      }
    ],
    "sg:menulink": "http://www.allmenus.com/oh/hopewell/141402-shell-shuckers/menu/",
    "sg:phone": "+1 419 447 6313",
    "sg:postcode": "44883",
    "sg:province": "OH",
    "sg:tags": [
      "american"
    ],
    "wof:name": "Shell Shuckers",
    "wof:placetype": "venue"
  },
  "geometry": {"coordinates":[-83.201184,41.096293],"type":"Point"}
}
