{
  "type": "Feature",
  "properties": {
    "addr:full": "306 E McMillan St Cincinnati OH 45219",
    "addr:housenumber": "306",
    "addr:postcode": "45219",
    "addr:street": "E Mcmillan St",
    "iso:country": "US",
    "sg:address": "306 E McMillan St",
    "sg:city": "Cincinnati",
    "sg:classifiers": [
      {
        "category": "Personal",
        "subcategory": "Beauty Salon",
        "type": "Services"
      }
    ],
    "sg:phone": "+1 513 751 7700",
    "sg:postcode": "45219",
    "sg:province": "OH",
    "wof:name": "Artistic Faith Hair \u0026 Art",
    "wof:placetype": "venue"
  },
  "geometry": {"coordinates":[-84.502808,39.12682],"type":"Point"}
}
