{
  "type": "Feature",
  "properties": {
    "addr:full": "2525 Fenner Rd Troy OH 45373",
    "addr:housenumber": "2525",
    "addr:postcode": "45373",
    "addr:street": "Fenner Rd",
    "iso:country": "US",
    "sg:address": "2525 Fenner Rd",
    "sg:city": "Troy",
    "sg:classifiers": [
      {
        "category": "Building \u0026 Trades",
        "subcategory": "Construction",
        "type": "Services"
      }
    ],
    "sg:phone": "+1 937 335 1202",
    "sg:postcode": "45373",
    "sg:province": "OH",
    "sg:tags": [
      "excavating",
      "contractor"
    ],
    "wof:name": "Estey Excavating Inc",
    "wof:placetype": "venue"
  },
  "geometry": {"coordinates":[-84.248921,40.024341],"type":"Point"}
}
