{
  "type": "Feature",
  "properties": {
    "iso:country":"US",
    "sg:address":"697 Mc Clurg Rd",
    "sg:city":"Youngstown",
    "sg:classifiers":[
        {
            "category":"Manufacturing",
            "subcategory":"Tools & Machinery",
            "type":"Manufacturing & Wholesale Goods"
        }
    ],
    "sg:phone":"+1 330 726 7175",
    "sg:postcode":"44512",
    "sg:province":"OH",
    "sg:tags":[
        "industrial",
        "mfg"
    ],
    "wof:name":"Duca Mfg & Consulting",
    "wof:placetype":"venue"
},
  "geometry": {"coordinates":[-80.634923,40.99512],"type":"Point"}
}