{
  "type": "Feature",
  "properties": {
    "addr:full": "697 Mc Clurg Rd Youngstown OH 44512",
    "addr:housenumber": "697",
    "addr:postcode": "44512",
    "addr:street": "Mc Clurg Rd",
    "iso:country": "US",
    "sg:address": "697 Mc Clurg Rd",
    "sg:city": "Youngstown",
    "sg:classifiers": [
      {
        "category": "Manufacturing",
        "subcategory": "Tools \u0026 Machinery",
        "type": "Manufacturing \u0026 Wholesale Goods"
      }
    ],
    "sg:phone": "+1 330 726 7175",
    "sg:postcode": "44512",
    "sg:province": "OH",
    "sg:tags": [
      "industrial",
      "mfg"
    ],
    "wof:name": "Duca Mfg \u0026 Consulting",
    "wof:placetype": "venue"
  },
  "geometry": {"coordinates":[-80.634923,40.99512],"type":"Point"}
}
