{
  "type": "Feature",
  "properties": {
    "addr:full": "21 N Beckel St Dayton OH 45403",
    "addr:housenumber": "21",
    "addr:postcode": "45403",
    "addr:street": "N Beckel St",
    "iso:country": "US",
    "sg:address": "21 N Beckel St",
    "sg:city": "Dayton",
    "sg:classifiers": [
      {
        "category": "Organizations",
        "subcategory": "Labor Organization",
        "type": "Services"
      }
    ],
    "sg:phone": "+1 937 224 7912",
    "sg:postcode": "45403",
    "sg:province": "OH",
    "wof:name": "American Postal Workers Union",
    "wof:placetype": "venue"
  },
  "geometry": {"coordinates":[-84.17307,39.763016],"type":"Point"}
}
