{
  "type": "Feature",
  "properties": {
    "iso:country":"US",
    "sg:address":"501 W River St",
    "sg:city":"Antwerp",
    "sg:classifiers":[
        {
            "category":"Retail",
            "subcategory":"Repair Shop",
            "type":"Services"
        }
    ],
    "sg:phone":"+1 419 258 7564",
    "sg:postcode":"45813",
    "sg:province":"OH",
    "sg:tags":[
        "upholsterer"
    ],
    "wof:name":"Mickelson's Upholstery",
    "wof:placetype":"venue"
},
  "geometry": {"coordinates":[-84.752317,41.177611],"type":"Point"}
}