{
  "type": "Feature",
  "properties": {
    "addr:full": "4906 Thomas Dr Geneva OH 44041",
    "addr:housenumber": "4906",
    "addr:postcode": "44041",
    "addr:street": "Thomas Dr",
    "iso:country": "US",
    "sg:address": "4906 Thomas Dr",
    "sg:city": "Geneva",
    "sg:classifiers": [
      {
        "category": "Real Estate",
        "subcategory": "Real Estate Agent",
        "type": "Services"
      }
    ],
    "sg:phone": "+1 440 466 8841",
    "sg:postcode": "44041",
    "sg:province": "OH",
    "wof:name": "Firestone Realty",
    "wof:placetype": "venue"
  },
  "geometry": {"coordinates":[-80.944224,41.857811],"type":"Point"}
}
