{
  "type": "Feature",
  "properties": {
    "iso:country":"US",
    "sg:address":"4906 Thomas Dr",
    "sg:city":"Geneva",
    "sg:classifiers":[
        {
            "category":"Real Estate",
            "subcategory":"Real Estate Agent",
            "type":"Services"
        }
    ],
    "sg:phone":"+1 440 466 8841",
    "sg:postcode":"44041",
    "sg:province":"OH",
    "wof:name":"Firestone Realty",
    "wof:placetype":"venue"
},
  "geometry": {"coordinates":[-80.94422400000001,41.857811],"type":"Point"}
}