{
  "type": "Feature",
  "properties": {
    "addr:full": "614 Shock Ave Lima OH 45805",
    "addr:housenumber": "614",
    "addr:postcode": "45805",
    "addr:street": "Shock Ave",
    "iso:country": "US",
    "sg:address": "614 Shock Ave",
    "sg:city": "Lima",
    "sg:classifiers": [
      {
        "category": "Wholesale",
        "subcategory": "Construction Materials",
        "type": "Manufacturing \u0026 Wholesale Goods"
      }
    ],
    "sg:phone": "+1 419 629 3000",
    "sg:postcode": "45805",
    "sg:province": "OH",
    "wof:name": "Sharon Terrace Apartments",
    "wof:placetype": "venue"
  },
  "geometry": {"coordinates":[-84.157304,40.733695],"type":"Point"}
}
