{
  "type": "Feature",
  "properties": {
    "addr:full":"15210 Bagley Rd Cleveland OH 44130",
    "addr:housenumber":"15210",
    "addr:postcode":"44130",
    "addr:street":"Bagley Rd",
    "iso:country":"US",
    "sg:address":"15210 Bagley Rd",
    "sg:city":"Cleveland",
    "sg:classifiers":[
        {
            "category":"Restaurant",
            "type":"Food & Drink"
        }
    ],
    "sg:phone":"+1 440 886 3456",
    "sg:postcode":"44130",
    "sg:province":"OH",
    "sg:tags":[
        "chinese"
    ],
    "wof:name":"Wah Fu Chinese Restaurant Inc",
    "wof:placetype":"venue"
},
  "geometry": {"coordinates":[-81.80649099999999,41.369768],"type":"Point"}
}