{
  "type": "Feature",
  "properties": {
    "addr:full":"680 Lee Ct Vermilion OH 44089",
    "addr:housenumber":"680",
    "addr:postcode":"44089",
    "addr:street":"Lee Ct",
    "iso:country":"US",
    "sg:address":"680 Lee Ct",
    "sg:city":"Vermilion",
    "sg:classifiers":[
        {
            "category":"Professional",
            "type":"Services"
        }
    ],
    "sg:phone":"+1 440 967 3363",
    "sg:postcode":"44089",
    "sg:province":"OH",
    "wof:name":"Mind Advantage Resources Inc",
    "wof:placetype":"venue"
},
  "geometry": {"coordinates":[-82.301867,41.420975],"type":"Point"}
}