{
  "type": "Feature",
  "properties": {
    "addr:full": "5466 State Rte 13 N Shiloh OH 44878",
    "addr:housenumber": "5466",
    "addr:postcode": "44878",
    "addr:street": "State Rte 13 N",
    "iso:country": "US",
    "sg:address": "5466 State Rte 13 N",
    "sg:city": "Shiloh",
    "sg:classifiers": [
      {
        "category": "Farming",
        "subcategory": "Livestock Farm",
        "type": "Manufacturing \u0026 Wholesale Goods"
      }
    ],
    "sg:phone": "+1 419 895 1865",
    "sg:postcode": "44878",
    "sg:province": "OH",
    "sg:tags": [
      "beef",
      "feedlot",
      "cattle"
    ],
    "wof:name": "Sunny Crest",
    "wof:placetype": "venue"
  },
  "geometry": {"coordinates":[-82.500742,40.902127],"type":"Point"}
}
