{
  "type": "Feature",
  "properties": {
    "addr:full":"2354 Kemper Ln Cincinnati OH 45206",
    "addr:housenumber":"2354",
    "addr:postcode":"45206",
    "addr:street":"Kemper Ln",
    "iso:country":"US",
    "sg:address":"2354 Kemper Ln",
    "sg:city":"Cincinnati",
    "sg:classifiers":[
        {
            "category":"Professional",
            "subcategory":"Advertising",
            "type":"Services"
        }
    ],
    "sg:phone":"+1 513 281 2301",
    "sg:postcode":"45206",
    "sg:province":"OH",
    "sg:tags":[
        "counselor"
    ],
    "sg:website":"www.liaisonmarketing.com",
    "wof:name":"Liaison Marketing Comms",
    "wof:placetype":"venue"
},
  "geometry": {"coordinates":[-84.48808699999999,39.122963],"type":"Point"}
}