{
  "type": "Feature",
  "properties": {
    "addr:full": "8607 Beech Ave Cleveland OH 44144",
    "addr:housenumber": "8607",
    "addr:postcode": "44144",
    "addr:street": "Beech Ave",
    "iso:country": "US",
    "sg:address": "8607 Beech Ave",
    "sg:city": "Cleveland",
    "sg:classifiers": [
      {
        "category": "Building \u0026 Trades",
        "subcategory": "Landscaping Services",
        "type": "Services"
      }
    ],
    "sg:phone": "+1 216 513 1299",
    "sg:postcode": "44144",
    "sg:province": "OH",
    "wof:name": "Perkins Lawnscape Inc",
    "wof:placetype": "venue"
  },
  "geometry": {"coordinates":[-81.747097,41.433476],"type":"Point"}
}
