{
  "type": "Feature",
  "properties": {
    "addr:full":"3142 N County Line Rd Geneva OH 44041",
    "addr:housenumber":"3142",
    "addr:postcode":"44041",
    "addr:street":"N County Line Rd",
    "iso:country":"US",
    "sg:address":"3142 N County Line Rd",
    "sg:city":"Geneva",
    "sg:classifiers":[
        {
            "category":"Health Services",
            "subcategory":"Nursing And Care Facility",
            "type":"Services"
        }
    ],
    "sg:phone":"+1 440 466 1678",
    "sg:postcode":"44041",
    "sg:province":"OH",
    "sg:tags":[
        "home",
        "convalescent"
    ],
    "wof:name":"Lakeland Nursing Home",
    "wof:placetype":"venue"
},
  "geometry": {"coordinates":[-81.002304,41.809987],"type":"Point"}
}