{
  "type": "Feature",
  "properties": {
    "iso:country":"US",
    "sg:address":"1500 Polaris Pkwy",
    "sg:city":"Columbus",
    "sg:classifiers":[
        {
            "category":"Shopping",
            "subcategory":"Luggage & Leather Goods",
            "type":"Retail Goods"
        }
    ],
    "sg:phone":"+1 614 885 6184",
    "sg:postcode":"43240",
    "sg:province":"OH",
    "wof:name":"Coach Leatherware",
    "wof:placetype":"venue"
},
  "geometry": {"coordinates":[-82.985922,40.141536],"type":"Point"}
}