{
  "type": "Feature",
  "properties": {
    "addr:full":"1005 Bridge St Ashtabula OH 44004",
    "addr:housenumber":"1005",
    "addr:postcode":"44004",
    "addr:street":"Bridge St",
    "iso:country":"US",
    "sg:address":"1005 Bridge St",
    "sg:city":"Ashtabula",
    "sg:classifiers":[
        {
            "category":"Professional",
            "subcategory":"Management & Consulting",
            "type":"Services"
        },
        {
            "category":"Shopping",
            "subcategory":"Gifts & Souvenirs",
            "type":"Retail Goods"
        }
    ],
    "sg:phone":"+1 440 964 8000",
    "sg:postcode":"44004",
    "sg:province":"OH",
    "sg:tags":[
        "interior",
        "home",
        "shop"
    ],
    "wof:name":"Carlisle's Home In The Harbor",
    "wof:placetype":"venue"
},
  "geometry": {"coordinates":[-80.798557,41.900021],"type":"Point"}
}