{
  "type": "Feature",
  "properties": {
    "iso:country":"US",
    "sg:address":"223 Hess Rd",
    "sg:city":"Washington Ct Hs",
    "sg:classifiers":[
        {
            "category":"Building & Trades",
            "subcategory":"Construction",
            "type":"Services"
        }
    ],
    "sg:phone":"+1 740 335 4836",
    "sg:postcode":"43160",
    "sg:province":"OH",
    "sg:tags":[
        "concrete",
        "contractor"
    ],
    "wof:name":"Buckeye Concrete",
    "wof:placetype":"venue"
},
  "geometry": {"coordinates":[-83.334858,39.552046],"type":"Point"}
}