{
  "type": "Feature",
  "properties": {
    "iso:country":"US",
    "sg:address":"7607 Wooster Pike",
    "sg:city":"Cincinnati",
    "sg:classifiers":[
        {
            "category":"Building & Trades",
            "subcategory":"Construction",
            "type":"Services"
        }
    ],
    "sg:phone":"+1 937 441 3647",
    "sg:postcode":"45227",
    "sg:province":"OH",
    "sg:tags":[
        "contractor",
        "fence-sales"
    ],
    "wof:name":"Invisible Fencing of Northern Kentucky",
    "wof:placetype":"venue"
},
  "geometry": {"coordinates":[-84.354418,39.139412],"type":"Point"}
}