{
  "type": "Feature",
  "properties": {
    "iso:country":"US",
    "sg:address":"22611 State Rte 2",
    "sg:city":"Archbold",
    "sg:classifiers":[
        {
            "category":"Restaurant",
            "type":"Food & Drink"
        }
    ],
    "sg:phone":"+1 419 445 2231",
    "sg:postcode":"43502",
    "sg:province":"OH",
    "sg:website":"www.saudervillage.org",
    "wof:name":"Barn Restaurant",
    "wof:placetype":"venue"
},
  "geometry": {"coordinates":[-84.29874,41.543225],"type":"Point"}
}