{
  "type": "Feature",
  "properties": {
    "addr:full": "1065 Bradley Rd Cleveland OH 44145",
    "addr:housenumber": "1065",
    "addr:postcode": "44145",
    "addr:street": "Bradley Rd",
    "iso:country": "US",
    "sg:address": "1065 Bradley Rd",
    "sg:city": "Cleveland",
    "sg:classifiers": [
      {
        "category": "Wholesale",
        "subcategory": "Construction Materials",
        "type": "Manufacturing \u0026 Wholesale Goods"
      },
      {
        "category": "Building \u0026 Trades",
        "subcategory": "Construction",
        "type": "Services"
      }
    ],
    "sg:phone": "+1 440 808 6000",
    "sg:postcode": "44145",
    "sg:province": "OH",
    "sg:tags": [
      "specializing",
      "industrial",
      "door",
      "frame",
      "contractor",
      "installation"
    ],
    "wof:name": "Action Automatics Inc",
    "wof:placetype": "venue"
  },
  "geometry": {"coordinates":[-81.960302,41.470886],"type":"Point"}
}
