{
  "type": "Feature",
  "properties": {
    "iso:country":"US",
    "sg:address":"1100 Chester Ave",
    "sg:city":"Cleveland",
    "sg:classifiers":[
        {
            "category":"Insurance",
            "subcategory":"Insurance Agent",
            "type":"Services"
        }
    ],
    "sg:phone":"+1 216 621 3453",
    "sg:postcode":"44103",
    "sg:province":"OH",
    "wof:name":"John D Byrne & Assoc",
    "wof:placetype":"venue"
},
  "geometry": {"coordinates":[-81.68511100000001,41.502192],"type":"Point"}
}