{
  "type": "Feature",
  "properties": {
    "addr:full": "105 Gilman Ave Marietta OH 45750",
    "addr:housenumber": "105",
    "addr:postcode": "45750",
    "addr:street": "Gilman Ave",
    "iso:country": "US",
    "sg:address": "105 Gilman Ave",
    "sg:city": "Marietta",
    "sg:classifiers": [
      {
        "category": "Arts \u0026 Performance",
        "subcategory": "Theater",
        "type": "Entertainment"
      }
    ],
    "sg:phone": "+1 740 374 8023",
    "sg:postcode": "45750",
    "sg:province": "OH",
    "sg:tags": [
      "live",
      "music"
    ],
    "wof:name": "M C Produtions",
    "wof:placetype": "venue"
  },
  "geometry": {"coordinates":[-81.459801,39.409416],"type":"Point"}
}
