{
  "type": "Feature",
  "properties": {
    "iso:country":"US",
    "sg:address":"610 W Exchange St",
    "sg:city":"Akron",
    "sg:classifiers":[
        {
            "category":"Restaurant",
            "type":"Food & Drink"
        }
    ],
    "sg:phone":"+1 330 535 3950",
    "sg:postcode":"44302",
    "sg:province":"OH",
    "sg:tags":[
        "banquet",
        "rooms"
    ],
    "wof:name":"St Joseph's Family Ctr",
    "wof:placetype":"venue"
},
  "geometry": {"coordinates":[-81.540844,41.08832],"type":"Point"}
}