{
  "type": "Feature",
  "properties": {
    "addr:full":"4866 Medusa Rd Norwalk OH 44857",
    "addr:housenumber":"4866",
    "addr:postcode":"44857",
    "addr:street":"Medusa Rd",
    "iso:country":"US",
    "sg:address":"4866 Medusa Rd",
    "sg:city":"Norwalk",
    "sg:phone":"+1 419 668 9848",
    "sg:postcode":"44857",
    "sg:province":"OH",
    "sg:tags":[
        "farm",
        "corn",
        "soybean"
    ],
    "wof:name":"Glen Goodell",
    "wof:placetype":"venue"
},
  "geometry": {"coordinates":[-82.532466,41.279705],"type":"Point"}
}