{
  "type": "Feature",
  "properties": {
    "iso:country":"US",
    "sg:address":"6605 Clark Ave",
    "sg:city":"Cleveland",
    "sg:classifiers":[
        {
            "category":"Manufacturing",
            "subcategory":"Metals",
            "type":"Manufacturing & Wholesale Goods"
        },
        {
            "category":"Manufacturing",
            "subcategory":"Tools & Machinery",
            "type":"Manufacturing & Wholesale Goods"
        }
    ],
    "sg:phone":"+1 216 631 6260",
    "sg:postcode":"44102",
    "sg:province":"OH",
    "sg:tags":[
        "product",
        "mfg",
        "elevator",
        "architectural",
        "custom"
    ],
    "sg:website":"www.apd-inc.com",
    "wof:name":"Architectural Products Dev",
    "wof:placetype":"venue"
},
  "geometry": {"coordinates":[-81.731089,41.469545],"type":"Point"}
}