{
  "type": "Feature",
  "properties": {
    "addr:full": "39 E College Ave Westerville OH 43081",
    "addr:housenumber": "39",
    "addr:postcode": "43081",
    "addr:street": "E College Ave",
    "iso:country": "US",
    "sg:address": "39 E College Ave",
    "sg:city": "Westerville",
    "sg:classifiers": [
      {
        "category": "Home \u0026 Garden",
        "subcategory": "Furniture",
        "type": "Retail Goods"
      },
      {
        "category": "Shopping",
        "subcategory": "Gifts \u0026 Souvenirs",
        "type": "Retail Goods"
      }
    ],
    "sg:phone": "+1 614 890 1119",
    "sg:postcode": "43081",
    "sg:province": "OH",
    "sg:tags": [
      "shop"
    ],
    "wof:name": "Sunny Knoll Farm Shop",
    "wof:placetype": "venue"
  },
  "geometry": {"coordinates":[-82.93036,40.125971],"type":"Point"}
}
