{
  "type": "Feature",
  "properties": {
    "addr:full":"7348 Broadway Ave Cleveland OH 44105",
    "addr:housenumber":"7348",
    "addr:postcode":"44105",
    "addr:street":"Broadway Ave",
    "iso:country":"US",
    "sg:address":"7348 Broadway Ave",
    "sg:city":"Cleveland",
    "sg:classifiers":[
        {
            "category":"Restaurant",
            "type":"Food & Drink"
        }
    ],
    "sg:phone":"+1 216 883 9301",
    "sg:postcode":"44105",
    "sg:province":"OH",
    "wof:name":"Monterey Grille",
    "wof:placetype":"venue"
},
  "geometry": {"coordinates":[-81.637111,41.456765],"type":"Point"}
}