{
  "type": "Feature",
  "properties": {
    "iso:country":"US",
    "sg:address":"238 5th St SE",
    "sg:city":"Barberton",
    "sg:classifiers":[
        {
            "category":"Food & Beverages",
            "subcategory":"Groceries & Convenience Stores",
            "type":"Retail Goods"
        }
    ],
    "sg:phone":"+1 330 745 0310",
    "sg:postcode":"44203",
    "sg:province":"OH",
    "wof:name":"Lawson Milk Co",
    "wof:placetype":"venue"
},
  "geometry": {"coordinates":[-81.58904200000001,41.003205],"type":"Point"}
}