{
  "type": "Feature",
  "properties": {
    "addr:full": "238 5th St SE Barberton OH 44203",
    "addr:housenumber": "238",
    "addr:postcode": "44203",
    "addr:street": "5Th St Se",
    "iso:country": "US",
    "sg:address": "238 5th St SE",
    "sg:city": "Barberton",
    "sg:classifiers": [
      {
        "category": "Food \u0026 Beverages",
        "subcategory": "Groceries \u0026 Convenience Stores",
        "type": "Retail Goods"
      }
    ],
    "sg:phone": "+1 330 745 0310",
    "sg:postcode": "44203",
    "sg:province": "OH",
    "wof:name": "Lawson Milk Co",
    "wof:placetype": "venue"
  },
  "geometry": {"coordinates":[-81.589042,41.003205],"type":"Point"}
}
