{
  "type": "Feature",
  "properties": {
    "addr:full": "921 Jasonway Ave Columbus OH 43214",
    "addr:housenumber": "921",
    "addr:postcode": "43214",
    "addr:street": "Jasonway Ave",
    "iso:country": "US",
    "sg:address": "921 Jasonway Ave",
    "sg:city": "Columbus",
    "sg:classifiers": [
      {
        "category": "Manufacturing",
        "subcategory": "Tools \u0026 Machinery",
        "type": "Manufacturing \u0026 Wholesale Goods"
      }
    ],
    "sg:phone": "+1 614 457 7660",
    "sg:postcode": "43214",
    "sg:province": "OH",
    "wof:name": "Womens Imaging Center  LLC",
    "wof:placetype": "venue"
  },
  "geometry": {"coordinates":[-83.043753,40.062859],"type":"Point"}
}
