{
  "type": "Feature",
  "properties": {
    "iso:country":"US",
    "sg:address":"15621 Waterloo Rd",
    "sg:city":"Cleveland",
    "sg:classifiers":[
        {
            "category":"Health Services",
            "subcategory":"Doctor",
            "type":"Services"
        }
    ],
    "sg:phone":"+1 216 481 7788",
    "sg:postcode":"44110",
    "sg:province":"OH",
    "sg:tags":[
        "physician",
        "surgeon"
    ],
    "wof:name":"Adolph F Znidarsic Inc",
    "wof:placetype":"venue"
},
  "geometry": {"coordinates":[-81.57109199999999,41.5712],"type":"Point"}
}