{
  "type": "Feature",
  "properties": {
    "addr:full":"3569 Shade Tree Dr Beavercreek OH 45431",
    "addr:housenumber":"3569",
    "addr:postcode":"45431",
    "addr:street":"Shade Tree Dr",
    "iso:country":"US",
    "sg:address":"3569 Shade Tree Dr",
    "sg:city":"Beavercreek",
    "sg:classifiers":[
        {
            "category":"Arena",
            "subcategory":"Sports Club",
            "type":"Entertainment"
        }
    ],
    "sg:phone":"+1 937 431 8850",
    "sg:postcode":"45431",
    "sg:province":"OH",
    "sg:tags":[
        "manager",
        "recruiter",
        "promoter"
    ],
    "wof:name":"Excel Sports Consultants",
    "wof:placetype":"venue"
},
  "geometry": {"coordinates":[-84.065192,39.769187],"type":"Point"}
}