{
  "type": "Feature",
  "properties": {
    "iso:country":"US",
    "sg:address":"3494 Reading Rd",
    "sg:city":"Cincinnati",
    "sg:classifiers":[
        {
            "category":"Health Services",
            "subcategory":"Doctor",
            "type":"Services"
        }
    ],
    "sg:phone":"+1 513 559 9200",
    "sg:postcode":"45229",
    "sg:province":"OH",
    "sg:tags":[
        "dentist"
    ],
    "wof:name":"Dental-One",
    "wof:placetype":"venue"
},
  "geometry": {"coordinates":[-84.491288,39.14346],"type":"Point"}
}