{
  "type": "Feature",
  "properties": {
    "addr:full": "3036 Urwiler Ave Cincinnati OH 45211",
    "addr:housenumber": "3036",
    "addr:postcode": "45211",
    "addr:street": "Urwiler Ave",
    "iso:country": "US",
    "sg:address": "3036 Urwiler Ave",
    "sg:city": "Cincinnati",
    "sg:classifiers": [
      {
        "category": "Shopping",
        "subcategory": "Stationery \u0026 Office Supplies",
        "type": "Retail Goods"
      }
    ],
    "sg:phone": "+1 513 521 1921",
    "sg:postcode": "45211",
    "sg:province": "OH",
    "wof:name": "Office Source One Inc",
    "wof:placetype": "venue"
  },
  "geometry": {"coordinates":[-84.600598,39.150669],"type":"Point"}
}
