{
  "type": "Feature",
  "properties": {
    "iso:country":"US",
    "sg:address":"3036 Urwiler Ave",
    "sg:city":"Cincinnati",
    "sg:classifiers":[
        {
            "category":"Shopping",
            "subcategory":"Stationery & Office Supplies",
            "type":"Retail Goods"
        }
    ],
    "sg:phone":"+1 513 521 1921",
    "sg:postcode":"45211",
    "sg:province":"OH",
    "wof:name":"Office Source One Inc",
    "wof:placetype":"venue"
},
  "geometry": {"coordinates":[-84.600598,39.150669],"type":"Point"}
}