{
  "type": "Feature",
  "properties": {
    "addr:full":"7670 1st Pl Bedford OH 44146",
    "addr:housenumber":"7670",
    "addr:postcode":"44146",
    "addr:street":"1St Pl",
    "iso:country":"US",
    "sg:address":"7670 1st Pl",
    "sg:city":"Bedford",
    "sg:classifiers":[
        {
            "category":"Mining & Drilling",
            "type":"Manufacturing & Wholesale Goods"
        }
    ],
    "sg:phone":"+1 440 359 0000",
    "sg:postcode":"44146",
    "sg:province":"OH",
    "sg:tags":[
        "exploration"
    ],
    "wof:name":"Fgb International LLC",
    "wof:placetype":"venue"
},
  "geometry": {"coordinates":[-81.511267,41.375525],"type":"Point"}
}