{
  "type": "Feature",
  "properties": {
    "addr:full": "300 Main St Cincinnati OH 45202",
    "addr:housenumber": "300",
    "addr:postcode": "45202",
    "addr:street": "Main St",
    "iso:country": "US",
    "sg:address": "300 Main St",
    "sg:city": "Cincinnati",
    "sg:classifiers": [
      {
        "category": "Banks \u0026 Credit Unions",
        "subcategory": "Investment Brokerage",
        "type": "Services"
      }
    ],
    "sg:phone": "+1 513 621 2875",
    "sg:postcode": "45202",
    "sg:province": "OH",
    "sg:tags": [
      "security",
      "counselor"
    ],
    "wof:name": "Reynolds De Witt Securities",
    "wof:placetype": "venue"
  },
  "geometry": {"coordinates":[-84.509262,39.09968],"type":"Point"}
}
