{
  "type": "Feature",
  "properties": {
    "addr:full": "405 S Burnett Rd Springfield OH 45505",
    "addr:housenumber": "405",
    "addr:postcode": "45505",
    "addr:street": "S Burnett Rd",
    "iso:country": "US",
    "sg:address": "405 S Burnett Rd",
    "sg:city": "Springfield",
    "sg:classifiers": [
      {
        "category": "Autos \u0026 Motor Vehicles",
        "subcategory": "Fuel \u0026 Gas Station",
        "type": "Retail Goods"
      }
    ],
    "sg:phone": "+1 937 324 2707",
    "sg:postcode": "45505",
    "sg:province": "OH",
    "sg:tags": [
      "oil"
    ],
    "wof:name": "Bonded Oil Co",
    "wof:placetype": "venue"
  },
  "geometry": {"coordinates":[-83.770587,39.914334],"type":"Point"}
}
