{
  "type": "Feature",
  "properties": {
    "iso:country":"US",
    "sg:address":"405 S Burnett Rd",
    "sg:city":"Springfield",
    "sg:classifiers":[
        {
            "category":"Autos & Motor Vehicles",
            "subcategory":"Fuel & Gas Station",
            "type":"Retail Goods"
        }
    ],
    "sg:phone":"+1 937 324 2707",
    "sg:postcode":"45505",
    "sg:province":"OH",
    "sg:tags":[
        "oil"
    ],
    "wof:name":"Bonded Oil Co",
    "wof:placetype":"venue"
},
  "geometry": {"coordinates":[-83.77058700000001,39.914334],"type":"Point"}
}