{
  "type": "Feature",
  "properties": {
    "addr:full": "100 W Main St Madison OH 44057",
    "addr:housenumber": "100",
    "addr:postcode": "44057",
    "addr:street": "W Main St",
    "iso:country": "US",
    "sg:address": "100 W Main St",
    "sg:city": "Madison",
    "sg:classifiers": [
      {
        "category": "Banks \u0026 Credit Unions",
        "subcategory": "Bank",
        "type": "Services"
      }
    ],
    "sg:phone": "+1 440 417 1608",
    "sg:postcode": "44057",
    "sg:province": "OH",
    "sg:tags": [
      "loan",
      "real estate"
    ],
    "wof:name": "Statewide Home Mortgage",
    "wof:placetype": "venue"
  },
  "geometry": {"coordinates":[-81.050957,41.771171],"type":"Point"}
}
