{
  "type": "Feature",
  "properties": {
    "addr:full":"4924 Burrville Rd Coldwater OH 45828",
    "addr:housenumber":"4924",
    "addr:postcode":"45828",
    "addr:street":"Burrville Rd",
    "iso:country":"US",
    "sg:address":"4924 Burrville Rd",
    "sg:city":"Coldwater",
    "sg:classifiers":[
        {
            "category":"Wholesale",
            "subcategory":"Machinery & Supplies",
            "type":"Manufacturing & Wholesale Goods"
        }
    ],
    "sg:phone":"+1 419 942 1258",
    "sg:postcode":"45828",
    "sg:province":"OH",
    "sg:tags":[
        "farm",
        "equipment"
    ],
    "wof:name":"Boeckmen & Son Grain Systems",
    "wof:placetype":"venue"
},
  "geometry": {"coordinates":[-84.72699900000001,40.488354],"type":"Point"}
}