{
  "type": "Feature",
  "properties": {
    "iso:country":"US",
    "sg:address":"2720 Salt Springs Rd",
    "sg:city":"Girard",
    "sg:classifiers":[
        {
            "category":"Autos & Motor Vehicles",
            "subcategory":"Fuel & Gas Station",
            "type":"Retail Goods"
        }
    ],
    "sg:phone":"+1 330 530 0834",
    "sg:postcode":"44420",
    "sg:province":"OH",
    "sg:tags":[
        "oil"
    ],
    "wof:name":"BP",
    "wof:placetype":"venue"
},
  "geometry": {"coordinates":[-80.722987,41.143854],"type":"Point"}
}