{
  "type": "Feature",
  "properties": {
    "addr:full":"3530 Warrensville Center Rd Cleveland OH 44122",
    "addr:housenumber":"3530",
    "addr:postcode":"44122",
    "addr:street":"Warrensville Center Rd",
    "iso:country":"US",
    "sg:address":"3530 Warrensville Center Rd",
    "sg:city":"Cleveland",
    "sg:classifiers":[
        {
            "category":"Insurance",
            "subcategory":"Insurance Agent",
            "type":"Services"
        }
    ],
    "sg:phone":"+1 216 491 0698",
    "sg:postcode":"44122",
    "sg:province":"OH",
    "wof:name":"Thomas Harrington & Associates",
    "wof:placetype":"venue"
},
  "geometry": {"coordinates":[-81.53621699999999,41.46042],"type":"Point"}
}