{
  "type": "Feature",
  "properties": {
    "iso:country":"US",
    "sg:address":"5214 E Farnhurst Rd",
    "sg:city":"Cleveland",
    "sg:classifiers":[
        {
            "category":"Manufacturing",
            "subcategory":"Tools & Machinery",
            "type":"Manufacturing & Wholesale Goods"
        }
    ],
    "sg:phone":"+1 440 461 9940",
    "sg:postcode":"44124",
    "sg:province":"OH",
    "sg:tags":[
        "equipment",
        "computer"
    ],
    "wof:name":"Port Inc",
    "wof:placetype":"venue"
},
  "geometry": {"coordinates":[-81.493336,41.523692],"type":"Point"}
}