{
  "type": "Feature",
  "properties": {
    "addr:full": "5214 E Farnhurst Rd Cleveland OH 44124",
    "addr:housenumber": "5214",
    "addr:postcode": "44124",
    "addr:street": "E Farnhurst Rd",
    "iso:country": "US",
    "sg:address": "5214 E Farnhurst Rd",
    "sg:city": "Cleveland",
    "sg:classifiers": [
      {
        "category": "Manufacturing",
        "subcategory": "Tools \u0026 Machinery",
        "type": "Manufacturing \u0026 Wholesale Goods"
      }
    ],
    "sg:phone": "+1 440 461 9940",
    "sg:postcode": "44124",
    "sg:province": "OH",
    "sg:tags": [
      "equipment",
      "computer"
    ],
    "wof:name": "Port Inc",
    "wof:placetype": "venue"
  },
  "geometry": {"coordinates":[-81.493336,41.523692],"type":"Point"}
}
