{
  "type": "Feature",
  "properties": {
    "addr:full": "11234 Sebring Dr Cincinnati OH 45240",
    "addr:postcode": "11234;45240",
    "addr:street": "Sebring Dr",
    "iso:country": "US",
    "sg:address": "11234 Sebring Dr",
    "sg:city": "Cincinnati",
    "sg:classifiers": [
      {
        "category": "Shopping",
        "subcategory": "Used Merchandise",
        "type": "Retail Goods"
      }
    ],
    "sg:phone": "+1 513 674 0202",
    "sg:postcode": "45240",
    "sg:province": "OH",
    "sg:tags": [
      "new"
    ],
    "wof:name": "Once Upon A Child",
    "wof:placetype": "venue"
  },
  "geometry": {"coordinates":[-84.556427,39.282326],"type":"Point"}
}
