{
  "type": "Feature",
  "properties": {
    "addr:full":"217 W Wyandot Ave Upper Sandusky OH 43351",
    "addr:housenumber":"217",
    "addr:postcode":"43351",
    "addr:street":"W Wyandot Ave",
    "iso:country":"US",
    "sg:address":"217 W Wyandot Ave",
    "sg:city":"Upper Sandusky",
    "sg:classifiers":[
        {
            "category":"Banks & Credit Unions",
            "subcategory":"Investment Brokerage",
            "type":"Services"
        }
    ],
    "sg:phone":"+1 419 294 1953",
    "sg:postcode":"43351",
    "sg:province":"OH",
    "sg:tags":[
        "stock",
        "bond"
    ],
    "wof:name":"Edward Jones Co",
    "wof:placetype":"venue"
},
  "geometry": {"coordinates":[-83.284318,40.827436],"type":"Point"}
}