{
  "type": "Feature",
  "properties": {
    "iso:country":"US",
    "sg:address":"754 Longfellow Dr",
    "sg:city":"Berea",
    "sg:classifiers":[
        {
            "category":"Freight",
            "type":"Transportation"
        }
    ],
    "sg:phone":"+1 216 387 0177",
    "sg:postcode":"44017",
    "sg:province":"OH",
    "sg:tags":[
        "courier"
    ],
    "wof:name":"Amazon Transport LLC",
    "wof:placetype":"venue"
},
  "geometry": {"coordinates":[-81.860837,41.385733],"type":"Point"}
}