{
  "type": "Feature",
  "properties": {
    "iso:country":"US",
    "sg:address":"4152 Tallmadge Rd",
    "sg:city":"Rootstown",
    "sg:classifiers":[
        {
            "category":"Government",
            "subcategory":"Fire Station",
            "type":"Public Place"
        }
    ],
    "sg:phone":"+1 330 325 7233",
    "sg:postcode":"44272",
    "sg:province":"OH",
    "sg:tags":[
        "department"
    ],
    "wof:name":"Rootstown Township Fire Dept",
    "wof:placetype":"venue"
},
  "geometry": {"coordinates":[-81.24279,41.099145],"type":"Point"}
}