{
  "type": "Feature",
  "properties": {
    "addr:full":"213 S Main St Bryan OH 43506",
    "addr:housenumber":"213",
    "addr:postcode":"43506",
    "addr:street":"S Main St",
    "iso:country":"US",
    "sg:address":"213 S Main St",
    "sg:city":"Bryan",
    "sg:classifiers":[
        {
            "category":"Shopping",
            "subcategory":"Computers & Home Electronics",
            "type":"Retail Goods"
        }
    ],
    "sg:phone":"+1 419 636 9009",
    "sg:postcode":"43506",
    "sg:province":"OH",
    "sg:tags":[
        "game",
        "video"
    ],
    "wof:name":"Video Game Trade 2",
    "wof:placetype":"venue"
},
  "geometry": {"coordinates":[-84.550968,41.473143],"type":"Point"}
}