{
  "type": "Feature",
  "properties": {
    "addr:full":"1205 Park Rd Mount Vernon OH 43050",
    "addr:housenumber":"1205",
    "addr:postcode":"43050",
    "addr:street":"Park Rd",
    "iso:country":"US",
    "sg:address":"1205 Park Rd",
    "sg:city":"Mount Vernon",
    "sg:classifiers":[
        {
            "category":"Organizations",
            "subcategory":"Community Association",
            "type":"Services"
        }
    ],
    "sg:phone":"+1 740 392 0211",
    "sg:postcode":"43050",
    "sg:province":"OH",
    "wof:name":"Kiwanis International Inc",
    "wof:placetype":"venue"
},
  "geometry": {"coordinates":[-82.457904,40.386161],"type":"Point"}
}