{
  "type": "Feature",
  "properties": {
    "addr:full": "20683 Hull Prairie Rd Bowling Green OH 43402",
    "addr:housenumber": "20683",
    "addr:postcode": "43402",
    "addr:street": "Hull Prairie Rd",
    "iso:country": "US",
    "sg:address": "20683 Hull Prairie Rd",
    "sg:city": "Bowling Green",
    "sg:classifiers": [
      {
        "category": "Manufacturing",
        "subcategory": "Aerospace",
        "type": "Manufacturing \u0026 Wholesale Goods"
      }
    ],
    "sg:phone": "+1 419 823 1651",
    "sg:postcode": "43402",
    "sg:province": "OH",
    "sg:tags": [
      "aircraft",
      "mfg"
    ],
    "wof:name": "Ohio Powered Paragliding",
    "wof:placetype": "venue"
  },
  "geometry": {"coordinates":[-83.674601,41.454441],"type":"Point"}
}
