{
  "type": "Feature",
  "properties": {
    "addr:full":"555 W Nottingham Rd Dayton OH 45405",
    "addr:housenumber":"555",
    "addr:postcode":"45405",
    "addr:street":"W Nottingham Rd",
    "iso:country":"US",
    "sg:address":"555 W Nottingham Rd",
    "sg:city":"Dayton",
    "sg:classifiers":[
        {
            "category":"Professional",
            "subcategory":"Business Services",
            "type":"Services"
        }
    ],
    "sg:phone":"+1 937 886 0782",
    "sg:postcode":"45405",
    "sg:province":"OH",
    "sg:tags":[
        "information",
        "referral"
    ],
    "wof:name":"Burrelle's Information Svc",
    "wof:placetype":"venue"
},
  "geometry": {"coordinates":[-84.232567,39.807192],"type":"Point"}
}