{
  "type": "Feature",
  "properties": {
    "addr:full":"600 S Pennsylvania Ave Wellston OH 45692",
    "addr:housenumber":"600",
    "addr:postcode":"45692",
    "addr:street":"S Pennsylvania Ave",
    "iso:country":"US",
    "sg:address":"600 S Pennsylvania Ave",
    "sg:city":"Wellston",
    "sg:classifiers":[
        {
            "category":"Education",
            "subcategory":"School",
            "type":"Public Place"
        }
    ],
    "sg:phone":"+1 740 384 2162",
    "sg:postcode":"45692",
    "sg:province":"OH",
    "sg:tags":[
        "high"
    ],
    "wof:name":"Wellston High School",
    "wof:placetype":"venue"
},
  "geometry": {"coordinates":[-82.533519,39.118843],"type":"Point"}
}