{
  "type": "Feature",
  "properties": {
    "addr:full": "11254 Marietta Rd Kingston OH 45644",
    "addr:housenumber": "11254",
    "addr:postcode": "45644",
    "addr:street": "Marietta Rd",
    "iso:country": "US",
    "sg:address": "11254 Marietta Rd",
    "sg:city": "Kingston",
    "sg:phone": "+1 740 655 2832",
    "sg:postcode": "45644",
    "sg:province": "OH",
    "sg:tags": [
      "farm",
      "soybean"
    ],
    "wof:name": "Franklin Dresbach",
    "wof:placetype": "venue"
  },
  "geometry": {"coordinates":[-82.86331,39.42542],"type":"Point"}
}
