{
  "type": "Feature",
  "properties": {
    "iso:country":"US",
    "sg:address":"5799 Sunbury Rd",
    "sg:city":"Columbus",
    "sg:classifiers":[
        {
            "category":"Building & Trades",
            "subcategory":"Construction",
            "type":"Services"
        }
    ],
    "sg:phone":"+1 614 476 6016",
    "sg:postcode":"43230",
    "sg:province":"OH",
    "sg:tags":[
        "contractor"
    ],
    "wof:name":"Tap Masonry",
    "wof:placetype":"venue"
},
  "geometry": {"coordinates":[-82.89715700000001,40.077049],"type":"Point"}
}