{
  "type": "Feature",
  "properties": {
    "addr:full": "4197 N Dayton Xenia Rd Dayton OH 45432",
    "addr:housenumber": "4197",
    "addr:postcode": "45432",
    "addr:street": "N Dayton Xenia Rd",
    "iso:country": "US",
    "sg:address": "4197 N Dayton Xenia Rd",
    "sg:city": "Dayton",
    "sg:classifiers": [
      {
        "category": "Organizations",
        "subcategory": "Religious Organization",
        "type": "Services"
      }
    ],
    "sg:phone": "+1 937 252 6927",
    "sg:postcode": "45432",
    "sg:province": "OH",
    "sg:tags": [
      "church"
    ],
    "wof:name": "Calvary Chapel Of Dayton",
    "wof:placetype": "venue"
  },
  "geometry": {"coordinates":[-84.091971,39.738722],"type":"Point"}
}
