{
  "type": "Feature",
  "properties": {
    "addr:full": "4669 W 130th St Cleveland OH 44135",
    "addr:housenumber": "4669",
    "addr:postcode": "44135",
    "addr:street": "W 130Th St",
    "iso:country": "US",
    "sg:address": "4669 W 130th St",
    "sg:city": "Cleveland",
    "sg:classifiers": [
      {
        "category": "Restaurant",
        "type": "Food \u0026 Drink"
      }
    ],
    "sg:phone": "+1 216 688 1208",
    "sg:postcode": "44135",
    "sg:province": "OH",
    "sg:tags": [
      "eating"
    ],
    "wof:name": "Good Fellas Pizzeria",
    "wof:placetype": "venue"
  },
  "geometry": {"coordinates":[-81.780058,41.42732],"type":"Point"}
}
