{
  "type": "Feature",
  "properties": {
    "addr:full": "2150 Arlington Ave Toledo OH 43609",
    "addr:housenumber": "2150",
    "addr:postcode": "43609",
    "addr:street": "Arlington Ave",
    "iso:country": "US",
    "sg:address": "2150 Arlington Ave",
    "sg:city": "Toledo",
    "sg:classifiers": [
      {
        "category": "Restaurant",
        "type": "Food \u0026 Drink"
      }
    ],
    "sg:phone": "+1 419 385 3776",
    "sg:postcode": "43609",
    "sg:province": "OH",
    "sg:tags": [
      "pizza"
    ],
    "wof:name": "Gino's Arlington",
    "wof:placetype": "venue"
  },
  "geometry": {"coordinates":[-83.596468,41.623322],"type":"Point"}
}
