{
  "type": "Feature",
  "properties": {
    "iso:country":"US",
    "sg:address":"4180 Stelzer Rd",
    "sg:city":"Columbus",
    "sg:classifiers":[
        {
            "category":"Retail",
            "subcategory":"Auto Repair",
            "type":"Services"
        }
    ],
    "sg:phone":"+1 614 472 0896",
    "sg:postcode":"43230",
    "sg:province":"OH",
    "sg:tags":[
        "tire",
        "supply"
    ],
    "wof:name":"Tire Kingdom",
    "wof:placetype":"venue"
},
  "geometry": {"coordinates":[-82.913352,40.062852],"type":"Point"}
}