{
  "type": "Feature",
  "properties": {
    "iso:country":"US",
    "sg:address":"3681 Green Rd",
    "sg:city":"Cleveland",
    "sg:classifiers":[
        {
            "category":"Professional",
            "subcategory":"Lawyer & Legal Services",
            "type":"Services"
        }
    ],
    "sg:phone":"+1 216 763 6100",
    "sg:postcode":"44122",
    "sg:province":"OH",
    "sg:tags":[
        "attorney"
    ],
    "wof:name":"Divorce Mediation Ctr Of Ohio",
    "wof:placetype":"venue"
},
  "geometry": {"coordinates":[-81.516898,41.463987],"type":"Point"}
}