{
  "type": "Feature",
  "properties": {
    "iso:country":"US",
    "sg:address":"2310 International St",
    "sg:city":"Columbus",
    "sg:classifiers":[
        {
            "category":"Building & Trades",
            "subcategory":"Plumbing",
            "type":"Services"
        }
    ],
    "sg:phone":"+1 614 527 9287",
    "sg:postcode":"43228",
    "sg:province":"OH",
    "sg:tags":[
        "air",
        "conditioning",
        "heating"
    ],
    "wof:name":"De Bra-Kuempel",
    "wof:placetype":"venue"
},
  "geometry": {"coordinates":[-83.134135,39.997787],"type":"Point"}
}