{
  "type": "Feature",
  "properties": {
    "addr:full": "4567 Olentangy River Rd Columbus OH 43214",
    "addr:housenumber": "4567",
    "addr:postcode": "43214",
    "addr:street": "Olentangy River Rd",
    "iso:country": "US",
    "sg:address": "4567 Olentangy River Rd",
    "sg:city": "Columbus",
    "sg:classifiers": [
      {
        "category": "Organizations",
        "subcategory": "Religious Organization",
        "type": "Services"
      }
    ],
    "sg:phone": "+1 614 451 3900",
    "sg:postcode": "43214",
    "sg:province": "OH",
    "sg:tags": [
      "monastery",
      "convent"
    ],
    "wof:name": "Sisters-The Poor Child Jesus",
    "wof:placetype": "venue"
  },
  "geometry": {"coordinates":[-83.03386,40.053517],"type":"Point"}
}
