{
  "type": "Feature",
  "properties": {
    "iso:country":"US",
    "sg:address":"2260 W Market St",
    "sg:city":"Akron",
    "sg:classifiers":[
        {
            "category":"Retail",
            "subcategory":"Auto Repair",
            "type":"Services"
        }
    ],
    "sg:phone":"+1 330 869 9878",
    "sg:postcode":"44313",
    "sg:province":"OH",
    "sg:tags":[
        "automobile",
        "lubrication"
    ],
    "wof:name":"Jiffy Lube",
    "wof:placetype":"venue"
},
  "geometry": {"coordinates":[-81.58709899999999,41.117179],"type":"Point"}
}