{
  "type": "Feature",
  "properties": {
    "addr:full": "55 Merz Blvd Akron OH 44333",
    "addr:housenumber": "55",
    "addr:postcode": "44333",
    "addr:street": "Merz Blvd",
    "iso:country": "US",
    "sg:address": "55 Merz Blvd",
    "sg:city": "Akron",
    "sg:classifiers": [
      {
        "category": "Real Estate",
        "subcategory": "Real Estate Services",
        "type": "Services"
      }
    ],
    "sg:phone": "+1 330 836 3500",
    "sg:postcode": "44333",
    "sg:province": "OH",
    "sg:tags": [
      "abstract",
      "title"
    ],
    "wof:name": "American Certified Title",
    "wof:placetype": "venue"
  },
  "geometry": {"coordinates":[-81.612747,41.130402],"type":"Point"}
}
