{
  "type": "Feature",
  "properties": {
    "iso:country":"US",
    "sg:address":"3203 Harvard Ave",
    "sg:city":"Cleveland",
    "sg:classifiers":[
        {
            "category":"Retail",
            "subcategory":"Auto Repair",
            "type":"Services"
        }
    ],
    "sg:phone":"+1 216 883 6644",
    "sg:postcode":"44105",
    "sg:province":"OH",
    "sg:tags":[
        "repairing",
        "cylinder"
    ],
    "wof:name":"Ohio Hydraulic & Machine",
    "wof:placetype":"venue"
},
  "geometry": {"coordinates":[-81.666265,41.447214],"type":"Point"}
}