{
  "type": "Feature",
  "properties": {
    "addr:full": "3203 Harvard Ave Cleveland OH 44105",
    "addr:housenumber": "3203",
    "addr:postcode": "44105",
    "addr:street": "Harvard Ave",
    "iso:country": "US",
    "sg:address": "3203 Harvard Ave",
    "sg:city": "Cleveland",
    "sg:classifiers": [
      {
        "category": "Retail",
        "subcategory": "Auto Repair",
        "type": "Services"
      }
    ],
    "sg:phone": "+1 216 883 6644",
    "sg:postcode": "44105",
    "sg:province": "OH",
    "sg:tags": [
      "repairing",
      "cylinder"
    ],
    "wof:name": "Ohio Hydraulic \u0026 Machine",
    "wof:placetype": "venue"
  },
  "geometry": {"coordinates":[-81.666265,41.447214],"type":"Point"}
}
