{
  "type": "Feature",
  "properties": {
    "addr:full": "1564 Covered Bridge Rd Cincinnati OH 45231",
    "addr:housenumber": "1564",
    "addr:postcode": "45231",
    "addr:street": "Covered Bridge Rd",
    "iso:country": "US",
    "sg:address": "1564 Covered Bridge Rd",
    "sg:city": "Cincinnati",
    "sg:classifiers": [
      {
        "category": "Professional",
        "subcategory": "Engineering",
        "type": "Services"
      }
    ],
    "sg:phone": "+1 513 742 2990",
    "sg:postcode": "45231",
    "sg:province": "OH",
    "sg:tags": [
      "engineer"
    ],
    "wof:name": "Pyro-Technical Investigations",
    "wof:placetype": "venue"
  },
  "geometry": {"coordinates":[-84.540208,39.249602],"type":"Point"}
}
