{
  "type": "Feature",
  "properties": {
    "iso:country":"US",
    "sg:address":"10080 Commerce Park Dr",
    "sg:city":"Cincinnati",
    "sg:classifiers":[
        {
            "category":"Home & Garden",
            "subcategory":"Carpets & Floor Coverings",
            "type":"Retail Goods"
        }
    ],
    "sg:phone":"+1 937 439 0499",
    "sg:postcode":"45246",
    "sg:province":"OH",
    "sg:tags":[
        "etc-repair",
        "cleaning",
        "vertical",
        "blinds-venetian"
    ],
    "wof:name":"Blinds Brite",
    "wof:placetype":"venue"
},
  "geometry": {"coordinates":[-84.45411900000001,39.304537],"type":"Point"}
}