{
  "type": "Feature",
  "properties": {
    "addr:full": "10080 Commerce Park Dr Cincinnati OH 45246",
    "addr:housenumber": "10080",
    "addr:postcode": "45246",
    "addr:street": "Commerce Park Dr",
    "iso:country": "US",
    "sg:address": "10080 Commerce Park Dr",
    "sg:city": "Cincinnati",
    "sg:classifiers": [
      {
        "category": "Home \u0026 Garden",
        "subcategory": "Carpets \u0026 Floor Coverings",
        "type": "Retail Goods"
      }
    ],
    "sg:phone": "+1 937 439 0499",
    "sg:postcode": "45246",
    "sg:province": "OH",
    "sg:tags": [
      "etc-repair",
      "cleaning",
      "vertical",
      "blinds-venetian"
    ],
    "wof:name": "Blinds Brite",
    "wof:placetype": "venue"
  },
  "geometry": {"coordinates":[-84.454119,39.304537],"type":"Point"}
}
