{
  "type": "Feature",
  "properties": {
    "addr:full": "6625 Twp Rd 34 Rawson OH 45881",
    "addr:housenumber": "34",
    "addr:postcode": "6625;45881",
    "addr:street": "Twp Rd",
    "iso:country": "US",
    "sg:address": "6625 Twp Rd 34",
    "sg:city": "Rawson",
    "sg:classifiers": [
      {
        "category": "Farming",
        "subcategory": "Nursery",
        "type": "Manufacturing \u0026 Wholesale Goods"
      }
    ],
    "sg:phone": "+1 419 326 6525",
    "sg:postcode": "45881",
    "sg:province": "OH",
    "sg:tags": [
      "ornamental"
    ],
    "wof:name": "Pure Country Greenhouses",
    "wof:placetype": "venue"
  },
  "geometry": {"coordinates":[-83.750884,40.912786],"type":"Point"}
}
