{
  "type": "Feature",
  "properties": {
    "iso:country":"US",
    "sg:address":"601 Indiana Ave",
    "sg:city":"Mc Donald",
    "sg:classifiers":[
        {
            "category":"Social Services",
            "type":"Services"
        }
    ],
    "sg:phone":"+1 330 530 1111",
    "sg:postcode":"44437",
    "sg:province":"OH",
    "sg:tags":[
        "organization",
        "religious"
    ],
    "wof:name":"Our Lady Prptual Help Ctchtcal",
    "wof:placetype":"venue"
},
  "geometry": {"coordinates":[-80.725428,41.161792],"type":"Point"}
}