{
  "type": "Feature",
  "properties": {
    "addr:full": "100 Elmwood Pl Athens OH 45701",
    "addr:housenumber": "100",
    "addr:postcode": "45701",
    "addr:street": "Elmwood Pl",
    "iso:country": "US",
    "sg:address": "100 Elmwood Pl",
    "sg:city": "Athens",
    "sg:classifiers": [
      {
        "category": "Wholesale",
        "subcategory": "Machinery \u0026 Supplies",
        "type": "Manufacturing \u0026 Wholesale Goods"
      }
    ],
    "sg:phone": "+1 740 592 2155",
    "sg:postcode": "45701",
    "sg:province": "OH",
    "sg:tags": [
      "equipment",
      "welding"
    ],
    "wof:name": "Cline Welding Supply",
    "wof:placetype": "venue"
  },
  "geometry": {"coordinates":[-82.088141,39.336343],"type":"Point"}
}
