{
  "type": "Feature",
  "properties": {
    "iso:country":"US",
    "sg:address":"5093 Creekside Blvd",
    "sg:city":"Brunswick",
    "sg:classifiers":[
        {
            "category":"Real Estate",
            "subcategory":"Real Estate Agent",
            "type":"Services"
        }
    ],
    "sg:phone":"+1 330 220 9926",
    "sg:postcode":"44212",
    "sg:province":"OH",
    "sg:tags":[
        "inspection"
    ],
    "wof:name":"A Cornerstone Home Inspection",
    "wof:placetype":"venue"
},
  "geometry": {"coordinates":[-81.873915,41.254712],"type":"Point"}
}