{
  "type": "Feature",
  "properties": {
    "addr:full": "9095 Twp Rd 108 New Riegel OH 44853",
    "addr:housenumber": "9095;108",
    "addr:postcode": "44853",
    "addr:street": "Twp Rd",
    "iso:country": "US",
    "sg:address": "9095 Twp Rd 108",
    "sg:city": "New Riegel",
    "sg:classifiers": [
      {
        "category": "Farming",
        "subcategory": "Farm",
        "type": "Manufacturing \u0026 Wholesale Goods"
      }
    ],
    "sg:phone": "+1 419 595 2635",
    "sg:postcode": "44853",
    "sg:province": "OH",
    "sg:tags": [
      "crop",
      "general"
    ],
    "wof:name": "Charles Brendle",
    "wof:placetype": "venue"
  },
  "geometry": {"coordinates":[-83.337432,41.094371],"type":"Point"}
}
