{
  "type": "Feature",
  "properties": {
    "iso:country":"US",
    "sg:address":"1202 18th St",
    "sg:city":"Portsmouth",
    "sg:classifiers":[
        {
            "category":"Health Services",
            "subcategory":"Health Practitioner",
            "type":"Services"
        }
    ],
    "sg:phone":"+1 740 356 7632",
    "sg:postcode":"45662",
    "sg:province":"OH",
    "sg:tags":[
        "therapist",
        "physical"
    ],
    "sg:website":"www.somc.org",
    "wof:name":"Somc Rehab Svc",
    "wof:placetype":"venue"
},
  "geometry": {"coordinates":[-82.988648,38.745892],"type":"Point"}
}