{
  "type": "Feature",
  "properties": {
    "addr:full":"172 Terrace Dr Youngstown OH 44512",
    "addr:housenumber":"172",
    "addr:postcode":"44512",
    "addr:street":"Terrace Dr",
    "iso:country":"US",
    "sg:address":"172 Terrace Dr",
    "sg:city":"Youngstown",
    "sg:classifiers":[
        {
            "category":"Freight",
            "type":"Transportation"
        }
    ],
    "sg:phone":"+1 330 783 0250",
    "sg:postcode":"44512",
    "sg:province":"OH",
    "sg:tags":[
        "operator",
        "local",
        "trucking"
    ],
    "wof:name":"Moss Trucking Co",
    "wof:placetype":"venue"
},
  "geometry": {"coordinates":[-80.65561,41.049642],"type":"Point"}
}