{
  "type": "Feature",
  "properties": {
    "addr:full":"5056 Spaulding Ct Lorain OH 44053",
    "addr:housenumber":"5056",
    "addr:postcode":"44053",
    "addr:street":"Spaulding Ct",
    "iso:country":"US",
    "sg:address":"5056 Spaulding Ct",
    "sg:city":"Lorain",
    "sg:classifiers":[
        {
            "category":"Professional",
            "type":"Services"
        }
    ],
    "sg:phone":"+1 440 960 5390",
    "sg:postcode":"44053",
    "sg:province":"OH",
    "wof:name":"M Maltezos",
    "wof:placetype":"venue"
},
  "geometry": {"coordinates":[-82.23248599999999,41.429237],"type":"Point"}
}