{
  "type": "Feature",
  "properties": {
    "addr:full":"312 Columbia St Higginsport OH 45131",
    "addr:housenumber":"312",
    "addr:postcode":"45131",
    "addr:street":"Columbia St",
    "iso:country":"US",
    "sg:address":"312 Columbia St",
    "sg:city":"Higginsport",
    "sg:classifiers":[
        {
            "category":"Shopping",
            "subcategory":"Used Merchandise",
            "type":"Retail Goods"
        }
    ],
    "sg:phone":"+1 937 375 6008",
    "sg:postcode":"45131",
    "sg:province":"OH",
    "sg:tags":[
        "antique"
    ],
    "wof:name":"Higginsport Mini Mall",
    "wof:placetype":"venue"
},
  "geometry": {"coordinates":[-83.96886600000001,38.790201],"type":"Point"}
}