{
  "type": "Feature",
  "properties": {
    "addr:full": "3517 Colchester Rd Columbus OH 43221",
    "addr:housenumber": "3517",
    "addr:postcode": "43221",
    "addr:street": "Colchester Rd",
    "iso:country": "US",
    "sg:address": "3517 Colchester Rd",
    "sg:city": "Columbus",
    "sg:classifiers": [
      {
        "category": "Manufacturing",
        "subcategory": "Glass \u0026 Minerals",
        "type": "Manufacturing \u0026 Wholesale Goods"
      }
    ],
    "sg:phone": "+1 614 459 1748",
    "sg:postcode": "43221",
    "sg:province": "OH",
    "sg:tags": [
      "glassware-wholesale",
      "manufacturer",
      "mfg"
    ],
    "wof:name": "Hervey, Lee Glass",
    "wof:placetype": "venue"
  },
  "geometry": {"coordinates":[-83.066258,40.02781],"type":"Point"}
}
