{
  "type": "Feature",
  "properties": {
    "iso:country":"US",
    "sg:address":"3517 Colchester Rd",
    "sg:city":"Columbus",
    "sg:classifiers":[
        {
            "category":"Manufacturing",
            "subcategory":"Glass & Minerals",
            "type":"Manufacturing & Wholesale Goods"
        }
    ],
    "sg:phone":"+1 614 459 1748",
    "sg:postcode":"43221",
    "sg:province":"OH",
    "sg:tags":[
        "glassware-wholesale",
        "manufacturer",
        "mfg"
    ],
    "wof:name":"Hervey, Lee Glass",
    "wof:placetype":"venue"
},
  "geometry": {"coordinates":[-83.066258,40.02781],"type":"Point"}
}