{
  "type": "Feature",
  "properties": {
    "addr:full": "820 Ohio Pike Cincinnati OH 45245",
    "addr:housenumber": "820",
    "addr:postcode": "45245",
    "addr:street": "Ohio Pike",
    "iso:country": "US",
    "sg:address": "820 Ohio Pike",
    "sg:city": "Cincinnati",
    "sg:classifiers": [
      {
        "category": "Building \u0026 Trades",
        "subcategory": "Construction",
        "type": "Services"
      }
    ],
    "sg:phone": "+1 513 752 8509",
    "sg:postcode": "45245",
    "sg:province": "OH",
    "sg:tags": [
      "glass",
      "installation",
      "contractor"
    ],
    "wof:name": "Beechmont Glass",
    "wof:placetype": "venue"
  },
  "geometry": {"coordinates":[-84.281408,39.064838],"type":"Point"}
}
