{
  "type": "Feature",
  "properties": {
    "iso:country":"US",
    "sg:address":"101 Mountain St",
    "sg:city":"Bainbridge",
    "sg:classifiers":[
        {
            "category":"Autos & Motor Vehicles",
            "subcategory":"Auto Supplies",
            "type":"Retail Goods"
        }
    ],
    "sg:phone":"+1 740 634 2108",
    "sg:postcode":"45612",
    "sg:province":"OH",
    "sg:tags":[
        "automobile",
        "parts"
    ],
    "wof:name":"Central Auto & Farm Ctr",
    "wof:placetype":"venue"
},
  "geometry": {"coordinates":[-83.271756,39.22723],"type":"Point"}
}