{
  "type": "Feature",
  "properties": {
    "addr:full":"1340 Compton Rd Cincinnati OH 45231",
    "addr:housenumber":"1340",
    "addr:postcode":"45231",
    "addr:street":"Compton Rd",
    "iso:country":"US",
    "sg:address":"1340 Compton Rd",
    "sg:city":"Cincinnati",
    "sg:classifiers":[
        {
            "category":"Real Estate",
            "subcategory":"Real Estate Agent",
            "type":"Services"
        }
    ],
    "sg:phone":"+1 513 891 8801",
    "sg:postcode":"45231",
    "sg:province":"OH",
    "wof:name":"Metro-Prop Realty Inc",
    "wof:placetype":"venue"
},
  "geometry": {"coordinates":[-84.535392,39.231203],"type":"Point"}
}