{
  "type": "Feature",
  "properties": {
    "addr:full": "7733 Reading Rd Cincinnati OH 45237",
    "addr:housenumber": "7733",
    "addr:postcode": "45237",
    "addr:street": "Reading Rd",
    "iso:country": "US",
    "sg:address": "7733 Reading Rd",
    "sg:city": "Cincinnati",
    "sg:classifiers": [
      {
        "category": "Professional",
        "subcategory": "Business Services",
        "type": "Services"
      }
    ],
    "sg:phone": "+1 513 761 8554",
    "sg:postcode": "45237",
    "sg:province": "OH",
    "sg:tags": [
      "telemarketing"
    ],
    "wof:name": "Jfd Of America",
    "wof:placetype": "venue"
  },
  "geometry": {"coordinates":[-84.454288,39.204085],"type":"Point"}
}
