{
  "type": "Feature",
  "properties": {
    "iso:country":"US",
    "sg:address":"8779 Pheasant Ln",
    "sg:city":"Willoughby",
    "sg:classifiers":[
        {
            "category":"Professional",
            "subcategory":"Lawyer & Legal Services",
            "type":"Services"
        }
    ],
    "sg:phone":"+1 440 357 4700",
    "sg:postcode":"44094",
    "sg:province":"OH",
    "sg:tags":[
        "attorney"
    ],
    "wof:name":"Nager & Bencivenni",
    "wof:placetype":"venue"
},
  "geometry": {"coordinates":[-81.330359,41.599578],"type":"Point"}
}