{
  "type": "Feature",
  "properties": {
    "iso:country":"US",
    "sg:address":"114 N West St",
    "sg:city":"Lima",
    "sg:classifiers":[
        {
            "category":"Health Services",
            "subcategory":"Clinic",
            "type":"Services"
        }
    ],
    "sg:phone":"+1 419 222 8109",
    "sg:postcode":"45801",
    "sg:province":"OH",
    "sg:tags":[
        "home",
        "care"
    ],
    "wof:name":"Home Instead Senior Care",
    "wof:placetype":"venue"
},
  "geometry": {"coordinates":[-84.107708,40.741161],"type":"Point"}
}