{
  "type": "Feature",
  "properties": {
    "addr:full":"1234 Old Oxford Rd Hamilton OH 45013",
    "addr:housenumber":"1234",
    "addr:postcode":"45013",
    "addr:street":"Old Oxford Rd",
    "iso:country":"US",
    "sg:address":"1234 Old Oxford Rd",
    "sg:city":"Hamilton",
    "sg:classifiers":[
        {
            "category":"Building & Trades",
            "subcategory":"Plumbing",
            "type":"Services"
        }
    ],
    "sg:phone":"+1 513 863 8782",
    "sg:postcode":"45013",
    "sg:province":"OH",
    "sg:tags":[
        "contractor"
    ],
    "wof:name":"Capital Heating & Cooling",
    "wof:placetype":"venue"
},
  "geometry": {"coordinates":[-84.61790000000001,39.429728],"type":"Point"}
}