{
  "type": "Feature",
  "properties": {
    "addr:full":"5046 E Messner Rd Apple Creek OH 44606",
    "addr:housenumber":"5046",
    "addr:postcode":"44606",
    "addr:street":"E Messner Rd",
    "iso:country":"US",
    "sg:address":"5046 E Messner Rd",
    "sg:city":"Apple Creek",
    "sg:classifiers":[
        {
            "category":"Real Estate",
            "subcategory":"Real Estate Agent",
            "type":"Services"
        }
    ],
    "sg:phone":"+1 330 698 9408",
    "sg:postcode":"44606",
    "sg:province":"OH",
    "wof:name":"S&C Real Estate LLC",
    "wof:placetype":"venue"
},
  "geometry": {"coordinates":[-81.87474,40.742426],"type":"Point"}
}