{
  "type": "Feature",
  "properties": {
    "iso:country":"US",
    "sg:address":"660 Elmwood Pt",
    "sg:city":"Aurora",
    "sg:classifiers":[
        {
            "category":"Building & Trades",
            "subcategory":"Construction",
            "type":"Services"
        }
    ],
    "sg:phone":"+1 330 995 4066",
    "sg:postcode":"44202",
    "sg:province":"OH",
    "sg:tags":[
        "hanging",
        "contractor"
    ],
    "wof:name":"Nuhue Refinishing LLC",
    "wof:placetype":"venue"
},
  "geometry": {"coordinates":[-81.367418,41.312744],"type":"Point"}
}