{
  "type": "Feature",
  "properties": {
    "addr:full": "16923 Fulton Rd Marshallville OH 44645",
    "addr:housenumber": "16923",
    "addr:postcode": "44645",
    "addr:street": "Fulton Rd",
    "iso:country": "US",
    "sg:address": "16923 Fulton Rd",
    "sg:city": "Marshallville",
    "sg:classifiers": [
      {
        "category": "Shopping",
        "subcategory": "Bicycles \u0026 Sporting Goods",
        "type": "Retail Goods"
      }
    ],
    "sg:phone": "+1 330 855 6305",
    "sg:postcode": "44645",
    "sg:province": "OH",
    "wof:name": "MDS Baseball Bats",
    "wof:placetype": "venue"
  },
  "geometry": {"coordinates":[-81.684434,40.897923],"type":"Point"}
}
