{
  "type": "Feature",
  "properties": {
    "addr:full": "14850 Greystone Dr Cleveland OH 44142",
    "addr:housenumber": "14850",
    "addr:postcode": "44142",
    "addr:street": "Greystone Dr",
    "iso:country": "US",
    "sg:address": "14850 Greystone Dr",
    "sg:city": "Cleveland",
    "sg:classifiers": [
      {
        "category": "Banks \u0026 Credit Unions",
        "subcategory": "Financial Services",
        "type": "Services"
      }
    ],
    "sg:phone": "+1 216 676 5422",
    "sg:postcode": "44142",
    "sg:province": "OH",
    "sg:tags": [
      "trust",
      "management"
    ],
    "wof:name": "Klun Family Trust",
    "wof:placetype": "venue"
  },
  "geometry": {"coordinates":[-81.799426,41.397528],"type":"Point"}
}
