{
  "type": "Feature",
  "properties": {
    "iso:country":"US",
    "sg:address":"5010 Mayfield Rd",
    "sg:city":"Cleveland",
    "sg:classifiers":[
        {
            "category":"Health Services",
            "subcategory":"Hospital",
            "type":"Services"
        }
    ],
    "sg:phone":"+1 216 381 9455",
    "sg:postcode":"44124",
    "sg:province":"OH",
    "sg:tags":[
        "mental"
    ],
    "wof:name":"Rakesh Ranjan MD & Assoc & Co",
    "wof:placetype":"venue"
},
  "geometry": {"coordinates":[-81.497998,41.519763],"type":"Point"}
}