{
  "type": "Feature",
  "properties": {
    "addr:full": "4600 Superior Ave Cleveland OH 44103",
    "addr:housenumber": "4600",
    "addr:postcode": "44103",
    "addr:street": "Superior Ave",
    "iso:country": "US",
    "sg:address": "4600 Superior Ave",
    "sg:city": "Cleveland",
    "sg:classifiers": [
      {
        "category": "Retail",
        "subcategory": "Auto Repair",
        "type": "Services"
      }
    ],
    "sg:phone": "+1 216 432 4975",
    "sg:postcode": "44103",
    "sg:province": "OH",
    "sg:tags": [
      "sale",
      "tire"
    ],
    "wof:name": "Superior Safety Center",
    "wof:placetype": "venue"
  },
  "geometry": {"coordinates":[-81.657908,41.51541],"type":"Point"}
}
