{
  "type": "Feature",
  "properties": {
    "addr:full":"3928 Jackpot Rd Grove City OH 43123",
    "addr:housenumber":"3928",
    "addr:postcode":"43123",
    "addr:street":"Jackpot Rd",
    "iso:country":"US",
    "sg:address":"3928 Jackpot Rd",
    "sg:city":"Grove City",
    "sg:classifiers":[
        {
            "category":"Travel",
            "subcategory":"Hotels & Motels",
            "type":"Entertainment"
        }
    ],
    "sg:phone":"+1 614 539 8944",
    "sg:postcode":"43123",
    "sg:province":"OH",
    "wof:name":"Hilton",
    "wof:placetype":"venue"
},
  "geometry": {"coordinates":[-83.045592,39.879519],"type":"Point"}
}