{
  "type": "Feature",
  "properties": {
    "iso:country":"US",
    "sg:address":"5660 Overbrooke Rd",
    "sg:city":"Dayton",
    "sg:classifiers":[
        {
            "category":"Travel",
            "subcategory":"Campground",
            "type":"Entertainment"
        }
    ],
    "sg:phone":"+1 937 435 0667",
    "sg:postcode":"45440",
    "sg:province":"OH",
    "wof:name":"Old 35 Campground",
    "wof:placetype":"venue"
},
  "geometry": {"coordinates":[-84.118612,39.659962],"type":"Point"}
}