{
  "type": "Feature",
  "properties": {
    "addr:full":"1955 E Dublin Granville Rd Columbus OH 43229",
    "addr:housenumber":"1955",
    "addr:postcode":"43229",
    "addr:street":"E Dublin Granville Rd",
    "iso:country":"US",
    "sg:address":"1955 E Dublin Granville Rd",
    "sg:city":"Columbus",
    "sg:classifiers":[
        {
            "category":"Home & Garden",
            "subcategory":"Household Appliances",
            "type":"Retail Goods"
        },
        {
            "category":"Retail",
            "subcategory":"Repair Shop",
            "type":"Services"
        }
    ],
    "sg:phone":"+1 614 888 1900",
    "sg:postcode":"43229",
    "sg:province":"OH",
    "sg:tags":[
        "machine",
        "sewing"
    ],
    "wof:name":"Northland Sewing Ctr",
    "wof:placetype":"venue"
},
  "geometry": {"coordinates":[-82.968171,40.086798],"type":"Point"}
}