{
  "type": "Feature",
  "properties": {
    "addr:full": "330 Main St Bridgeport OH 43912",
    "addr:housenumber": "330",
    "addr:postcode": "43912",
    "addr:street": "Main St",
    "iso:country": "US",
    "sg:address": "330 Main St",
    "sg:city": "Bridgeport",
    "sg:classifiers": [
      {
        "category": "Education",
        "subcategory": "Dance Studio",
        "type": "Public Place"
      }
    ],
    "sg:phone": "+1 740 635 3602",
    "sg:postcode": "43912",
    "sg:province": "OH",
    "sg:tags": [
      "instruction",
      "dancing"
    ],
    "wof:name": "Ohio Valley Dance \u0026 Baton",
    "wof:placetype": "venue"
  },
  "geometry": {"coordinates":[-80.743816,40.07248],"type":"Point"}
}
