{
  "type": "Feature",
  "properties": {
    "addr:full": "1869 E Aurora Rd Twinsburg OH 44087",
    "addr:housenumber": "1869",
    "addr:postcode": "44087",
    "addr:street": "E Aurora Rd",
    "iso:country": "US",
    "sg:address": "1869 E Aurora Rd",
    "sg:city": "Twinsburg",
    "sg:classifiers": [
      {
        "category": "Health Services",
        "subcategory": "Clinic",
        "type": "Services"
      }
    ],
    "sg:phone": "+1 330 405 1040",
    "sg:postcode": "44087",
    "sg:province": "OH",
    "sg:tags": [
      "home",
      "care"
    ],
    "wof:name": "Cambridge Home Health Care",
    "wof:placetype": "venue"
  },
  "geometry": {"coordinates":[-81.463169,41.311415],"type":"Point"}
}
