{
  "type": "Feature",
  "properties": {
    "iso:country":"US",
    "sg:address":"1869 E Aurora Rd",
    "sg:city":"Twinsburg",
    "sg:classifiers":[
        {
            "category":"Health Services",
            "subcategory":"Clinic",
            "type":"Services"
        }
    ],
    "sg:phone":"+1 330 405 1040",
    "sg:postcode":"44087",
    "sg:province":"OH",
    "sg:tags":[
        "home",
        "care"
    ],
    "wof:name":"Cambridge Home Health Care",
    "wof:placetype":"venue"
},
  "geometry": {"coordinates":[-81.46316899999999,41.311415],"type":"Point"}
}