{
  "type": "Feature",
  "properties": {
    "addr:full":"6067 Branch Hill-Guinea Pike Milford OH 45150",
    "addr:housenumber":"6067",
    "addr:postcode":"45150",
    "addr:street":"Branch Hill-Guinea Pike",
    "iso:country":"US",
    "sg:address":"6067 Branch Hill-Guinea Pike",
    "sg:city":"Milford",
    "sg:classifiers":[
        {
            "category":"Shopping",
            "type":"Retail Goods"
        },
        {
            "category":"Autos & Motor Vehicles",
            "subcategory":"Motorcycle Sales",
            "type":"Retail Goods"
        }
    ],
    "sg:phone":"+1 513 575 5400",
    "sg:postcode":"45150",
    "sg:province":"OH",
    "sg:tags":[
        "scooter",
        "merchandise"
    ],
    "wof:name":"Dirt Sports Warehouse LLC",
    "wof:placetype":"venue"
},
  "geometry": {"coordinates":[-84.223761,39.204892],"type":"Point"}
}