{
  "type": "Feature",
  "properties": {
    "addr:full": "1030 S South St Wilmington OH 45177",
    "addr:housenumber": "1030",
    "addr:postcode": "45177",
    "addr:street": "S South St",
    "iso:country": "US",
    "sg:address": "1030 S South St",
    "sg:city": "Wilmington",
    "sg:classifiers": [
      {
        "category": "Restaurant",
        "type": "Food \u0026 Drink"
      }
    ],
    "sg:phone": "+1 937 382 2269",
    "sg:postcode": "45177",
    "sg:province": "OH",
    "wof:name": "Stacey's Buffet",
    "wof:placetype": "venue"
  },
  "geometry": {"coordinates":[-83.830294,39.433471],"type":"Point"}
}
