{
  "type": "Feature",
  "properties": {
    "addr:full":"1420 Boardman Canfield Rd Youngstown OH 44512",
    "addr:housenumber":"1420",
    "addr:postcode":"44512",
    "addr:street":"Boardman Canfield Rd",
    "iso:country":"US",
    "sg:address":"1420 Boardman Canfield Rd",
    "sg:city":"Youngstown",
    "sg:classifiers":[
        {
            "category":"Shopping",
            "subcategory":"Clothing, Apparel, & Fashions",
            "type":"Retail Goods"
        }
    ],
    "sg:phone":"+1 330 726 4449",
    "sg:postcode":"44512",
    "sg:province":"OH",
    "wof:name":"Powells Shoppe",
    "wof:placetype":"venue"
},
  "geometry": {"coordinates":[-80.70277900000001,41.024702],"type":"Point"}
}