{
  "type": "Feature",
  "properties": {
    "iso:country":"US",
    "sg:address":"830 Amherst Rd NE",
    "sg:city":"Massillon",
    "sg:classifiers":[
        {
            "category":"Health Services",
            "subcategory":"Doctor",
            "type":"Services"
        }
    ],
    "sg:phone":"+1 330 837 5191",
    "sg:postcode":"44646",
    "sg:province":"OH",
    "sg:tags":[
        "physician",
        "surgeon"
    ],
    "wof:name":"Eye Clinic Inc",
    "wof:placetype":"venue"
},
  "geometry": {"coordinates":[-81.518534,40.805538],"type":"Point"}
}