{
  "type": "Feature",
  "properties": {
    "addr:full": "41 S Stanfield Rd Troy OH 45373",
    "addr:housenumber": "41",
    "addr:postcode": "45373",
    "addr:street": "S Stanfield Rd",
    "iso:country": "US",
    "sg:address": "41 S Stanfield Rd",
    "sg:city": "Troy",
    "sg:classifiers": [
      {
        "category": "Insurance",
        "subcategory": "Insurance Agent",
        "type": "Services"
      }
    ],
    "sg:phone": "+1 937 339 0447",
    "sg:postcode": "45373",
    "sg:province": "OH",
    "wof:name": "Bruce Knisley",
    "wof:placetype": "venue"
  },
  "geometry": {"coordinates":[-84.240573,40.054809],"type":"Point"}
}
