{
  "type": "Feature",
  "properties": {
    "addr:full": "7712 Hamilton Ave Cincinnati OH 45231",
    "addr:housenumber": "7712",
    "addr:postcode": "45231",
    "addr:street": "Hamilton Ave",
    "iso:country": "US",
    "sg:address": "7712 Hamilton Ave",
    "sg:city": "Cincinnati",
    "sg:classifiers": [
      {
        "category": "Health Services",
        "subcategory": "Chiropractor",
        "type": "Services"
      }
    ],
    "sg:phone": "+1 513 522 2220",
    "sg:postcode": "45231",
    "sg:province": "OH",
    "wof:name": "Woeste Chiropractic",
    "wof:placetype": "venue"
  },
  "geometry": {"coordinates":[-84.547959,39.234376],"type":"Point"}
}
