{
  "type": "Feature",
  "properties": {
    "iso:country":"US",
    "sg:address":"1034 Gardner Blvd",
    "sg:city":"Barberton",
    "sg:classifiers":[
        {
            "category":"Building & Trades",
            "subcategory":"Construction",
            "type":"Services"
        }
    ],
    "sg:phone":"+1 330 848 1670",
    "sg:postcode":"44203",
    "sg:province":"OH",
    "sg:tags":[
        "hanging",
        "contractor"
    ],
    "wof:name":"Kostko Painting Dick",
    "wof:placetype":"venue"
},
  "geometry": {"coordinates":[-81.627576,41.021451],"type":"Point"}
}