{
  "type": "Feature",
  "properties": {
    "iso:country":"US",
    "sg:address":"4071 Myron Ave",
    "sg:city":"Dayton",
    "sg:classifiers":[
        {
            "category":"Building & Trades",
            "subcategory":"Construction",
            "type":"Services"
        }
    ],
    "sg:phone":"+1 937 277 5636",
    "sg:postcode":"45416",
    "sg:province":"OH",
    "sg:tags":[
        "hanging",
        "contractor"
    ],
    "wof:name":"Edwards David Painting & Rmdlg",
    "wof:placetype":"venue"
},
  "geometry": {"coordinates":[-84.265387,39.807664],"type":"Point"}
}