{
  "type": "Feature",
  "properties": {
    "addr:full": "4071 Myron Ave Dayton OH 45416",
    "addr:housenumber": "4071",
    "addr:postcode": "45416",
    "addr:street": "Myron Ave",
    "iso:country": "US",
    "sg:address": "4071 Myron Ave",
    "sg:city": "Dayton",
    "sg:classifiers": [
      {
        "category": "Building \u0026 Trades",
        "subcategory": "Construction",
        "type": "Services"
      }
    ],
    "sg:phone": "+1 937 277 5636",
    "sg:postcode": "45416",
    "sg:province": "OH",
    "sg:tags": [
      "hanging",
      "contractor"
    ],
    "wof:name": "Edwards David Painting \u0026 Rmdlg",
    "wof:placetype": "venue"
  },
  "geometry": {"coordinates":[-84.265387,39.807664],"type":"Point"}
}
