{
  "type": "Feature",
  "properties": {
    "addr:full": "45994 State Rte 145 Lewisville OH 43754",
    "addr:housenumber": "45994",
    "addr:postcode": "43754",
    "addr:street": "State Rte 145",
    "iso:country": "US",
    "sg:address": "45994 State Rte 145",
    "sg:city": "Lewisville",
    "sg:classifiers": [
      {
        "category": "Social Services",
        "subcategory": "Adult Care",
        "type": "Services"
      }
    ],
    "sg:phone": "+1 740 567 3516",
    "sg:postcode": "43754",
    "sg:province": "OH",
    "sg:tags": [
      "home",
      "residential"
    ],
    "wof:name": "Hillcrest Manor",
    "wof:placetype": "venue"
  },
  "geometry": {"coordinates":[-81.219257,39.763248],"type":"Point"}
}
