{
  "type": "Feature",
  "properties": {
    "addr:full":"340 W Steels Corners Rd Cuyahoga Falls OH 44223",
    "addr:housenumber":"340",
    "addr:postcode":"44223",
    "addr:street":"W Steels Corners Rd",
    "iso:country":"US",
    "sg:address":"340 W Steels Corners Rd",
    "sg:city":"Cuyahoga Falls",
    "sg:classifiers":[
        {
            "category":"Manufacturing",
            "subcategory":"Glass & Minerals",
            "type":"Manufacturing & Wholesale Goods"
        }
    ],
    "sg:phone":"+1 330 928 9777",
    "sg:postcode":"44223",
    "sg:province":"OH",
    "sg:tags":[
        "ready"
    ],
    "wof:name":"Medina Supply Co",
    "wof:placetype":"venue"
},
  "geometry": {"coordinates":[-81.519201,41.180851],"type":"Point"}
}