{
  "type": "Feature",
  "properties": {
    "iso:country":"US",
    "sg:address":"6326 Pawnee Pl",
    "sg:city":"Youngstown",
    "sg:classifiers":[
        {
            "category":"Building & Trades",
            "subcategory":"Construction",
            "type":"Services"
        }
    ],
    "sg:phone":"+1 330 757 7445",
    "sg:postcode":"44514",
    "sg:province":"OH",
    "sg:tags":[
        "hanging",
        "contractor"
    ],
    "wof:name":"Delisio Painting",
    "wof:placetype":"venue"
},
  "geometry": {"coordinates":[-80.59965699999999,41.026179],"type":"Point"}
}