{
  "type": "Feature",
  "properties": {
    "iso:country":"US",
    "sg:address":"2508 Civic Center Dr",
    "sg:city":"Cincinnati",
    "sg:classifiers":[
        {
            "category":"Building & Trades",
            "subcategory":"Construction",
            "type":"Services"
        }
    ],
    "sg:phone":"+1 513 931 5256",
    "sg:postcode":"45231",
    "sg:province":"OH",
    "sg:tags":[
        "repairing",
        "family",
        "contractor",
        "new",
        "home",
        "remodeling"
    ],
    "wof:name":"Gerbus Remodeling",
    "wof:placetype":"venue"
},
  "geometry": {"coordinates":[-84.571476,39.278466],"type":"Point"}
}