{
  "type": "Feature",
  "properties": {
    "addr:full": "2508 Civic Center Dr Cincinnati OH 45231",
    "addr:housenumber": "2508",
    "addr:postcode": "45231",
    "addr:street": "Civic Center Dr",
    "iso:country": "US",
    "sg:address": "2508 Civic Center Dr",
    "sg:city": "Cincinnati",
    "sg:classifiers": [
      {
        "category": "Building \u0026 Trades",
        "subcategory": "Construction",
        "type": "Services"
      }
    ],
    "sg:phone": "+1 513 931 5256",
    "sg:postcode": "45231",
    "sg:province": "OH",
    "sg:tags": [
      "repairing",
      "family",
      "contractor",
      "new",
      "home",
      "remodeling"
    ],
    "wof:name": "Gerbus Remodeling",
    "wof:placetype": "venue"
  },
  "geometry": {"coordinates":[-84.571476,39.278466],"type":"Point"}
}
