{
  "type": "Feature",
  "properties": {
    "iso:country":"US",
    "sg:address":"450 Elm St",
    "sg:city":"Lorain",
    "sg:classifiers":[
        {
            "category":"Building & Trades",
            "subcategory":"Construction",
            "type":"Services"
        }
    ],
    "sg:phone":"+1 440 342 3123",
    "sg:postcode":"44035",
    "sg:province":"OH",
    "sg:tags":[
        "builder",
        "patio",
        "deck"
    ],
    "wof:name":"Decknology Experts",
    "wof:placetype":"venue"
},
  "geometry": {"coordinates":[-82.111401,41.369791],"type":"Point"}
}