{
  "type": "Feature",
  "properties": {
    "iso:country":"US",
    "sg:address":"8751 Mentor Ave",
    "sg:city":"Mentor",
    "sg:classifiers":[
        {
            "category":"Social Services",
            "subcategory":"Child Care",
            "type":"Services"
        }
    ],
    "sg:phone":"+1 440 255 6231",
    "sg:postcode":"44060",
    "sg:province":"OH",
    "sg:tags":[
        "kindergarten",
        "academic",
        "school"
    ],
    "wof:name":"Widening World Pre-School",
    "wof:placetype":"venue"
},
  "geometry": {"coordinates":[-81.326156,41.672983],"type":"Point"}
}