{
  "type": "Feature",
  "properties": {
    "addr:full": "806 Central Ave Middletown OH 45044",
    "addr:housenumber": "806",
    "addr:postcode": "45044",
    "addr:street": "Central Ave",
    "iso:country": "US",
    "sg:address": "806 Central Ave",
    "sg:city": "Middletown",
    "sg:classifiers": [
      {
        "category": "Manufacturing",
        "subcategory": "Tools \u0026 Machinery",
        "type": "Manufacturing \u0026 Wholesale Goods"
      }
    ],
    "sg:phone": "+1 513 423 7624",
    "sg:postcode": "45044",
    "sg:province": "OH",
    "sg:tags": [
      "machine",
      "shop",
      "general"
    ],
    "wof:name": "Whitt Machine Inc",
    "wof:placetype": "venue"
  },
  "geometry": {"coordinates":[-84.406352,39.517664],"type":"Point"}
}
