{
  "type": "Feature",
  "properties": {
    "addr:full":"135 Williams St Cincinnati OH 45215",
    "addr:housenumber":"135",
    "addr:postcode":"45215",
    "addr:street":"Williams St",
    "iso:country":"US",
    "sg:address":"135 Williams St",
    "sg:city":"Cincinnati",
    "sg:classifiers":[
        {
            "category":"Organizations",
            "subcategory":"Religious Organization",
            "type":"Services"
        }
    ],
    "sg:phone":"+1 513 761 1151",
    "sg:postcode":"45215",
    "sg:province":"OH",
    "sg:tags":[
        "church"
    ],
    "sg:website":"www.cincinnatibaptist.com",
    "wof:name":"Cincinnati Baptist Assn",
    "wof:placetype":"venue"
},
  "geometry": {"coordinates":[-84.452454,39.224985],"type":"Point"}
}