{
  "type": "Feature",
  "properties": {
    "addr:full":"4434 Co Rd 24-D Stryker OH 43557",
    "addr:housenumber":"4434;24-d",
    "addr:postcode":"43557",
    "addr:street":"Co Rd",
    "iso:country":"US",
    "sg:address":"4434 Co Rd 24-D",
    "sg:city":"Stryker",
    "sg:phone":"+1 419 445 3242",
    "sg:postcode":"43557",
    "sg:province":"OH",
    "sg:tags":[
        "farm",
        "corn",
        "wheat",
        "soybean"
    ],
    "wof:name":"G R B Farms",
    "wof:placetype":"venue"
},
  "geometry": {"coordinates":[-84.353937,41.4768],"type":"Point"}
}