{
  "type": "Feature",
  "properties": {
    "iso:country":"US",
    "sg:address":"525 Parkview Dr",
    "sg:city":"Eldorado",
    "sg:classifiers":[
        {
            "category":"Government",
            "subcategory":"Office",
            "type":"Public Place"
        }
    ],
    "sg:phone":"+1 937 273 0035",
    "sg:postcode":"45321",
    "sg:province":"OH",
    "sg:tags":[
        "govt",
        "city"
    ],
    "wof:name":"Eldorado Water Treatment Plant",
    "wof:placetype":"venue"
},
  "geometry": {"coordinates":[-84.673198,39.908733],"type":"Point"}
}