{
  "type": "Feature",
  "properties": {
    "iso:country":"US",
    "sg:address":"2058 Randolph Rd",
    "sg:city":"Mogadore",
    "sg:classifiers":[
        {
            "category":"Building & Trades",
            "subcategory":"Construction",
            "type":"Services"
        }
    ],
    "sg:phone":"+1 330 628 8216",
    "sg:postcode":"44260",
    "sg:province":"OH",
    "sg:tags":[
        "foundation",
        "cement",
        "contractor",
        "concrete",
        "driveway",
        "sidewalk"
    ],
    "wof:name":"Mudd Construction Co Inc",
    "wof:placetype":"venue"
},
  "geometry": {"coordinates":[-81.31902100000001,41.050354],"type":"Point"}
}