{
  "type": "Feature",
  "properties": {
    "addr:full":"205 Utah St Toledo OH 43605",
    "addr:housenumber":"205",
    "addr:postcode":"43605",
    "addr:street":"Utah St",
    "iso:country":"US",
    "sg:address":"205 Utah St",
    "sg:city":"Toledo",
    "sg:classifiers":[
        {
            "category":"Manufacturing",
            "subcategory":"Tools & Machinery",
            "type":"Manufacturing & Wholesale Goods"
        }
    ],
    "sg:phone":"+1 419 697 1201",
    "sg:postcode":"43605",
    "sg:province":"OH",
    "sg:tags":[
        "industrial",
        "mfg"
    ],
    "wof:name":"Vorlage Special Tool",
    "wof:placetype":"venue"
},
  "geometry": {"coordinates":[-83.527445,41.643816],"type":"Point"}
}