{
  "type": "Feature",
  "properties": {
    "iso:country":"US",
    "sg:address":"5055 Sinclair Rd",
    "sg:city":"Columbus",
    "sg:classifiers":[
        {
            "category":"Bars & Pubs",
            "type":"Food & Drink"
        }
    ],
    "sg:phone":"+1 614 885 2588",
    "sg:postcode":"43229",
    "sg:province":"OH",
    "sg:tags":[
        "drinking"
    ],
    "wof:name":"Alrosa Villa",
    "wof:placetype":"venue"
},
  "geometry": {"coordinates":[-82.998511,40.066606],"type":"Point"}
}