{
  "type": "Feature",
  "properties": {
    "addr:full": "3294 Denison Ave Cleveland OH 44109",
    "addr:housenumber": "3294",
    "addr:postcode": "44109",
    "addr:street": "Denison Ave",
    "iso:country": "US",
    "sg:address": "3294 Denison Ave",
    "sg:city": "Cleveland",
    "sg:classifiers": [
      {
        "category": "Organizations",
        "subcategory": "Religious Organization",
        "type": "Services"
      }
    ],
    "sg:phone": "+1 216 739 1877",
    "sg:postcode": "44109",
    "sg:province": "OH",
    "sg:tags": [
      "church"
    ],
    "wof:name": "Episcopal West Side Shared Min",
    "wof:placetype": "venue"
  },
  "geometry": {"coordinates":[-81.703707,41.450726],"type":"Point"}
}
