{
  "type": "Feature",
  "properties": {
    "addr:full": "1260 Matzinger Rd Toledo OH 43612",
    "addr:housenumber": "1260",
    "addr:postcode": "43612",
    "addr:street": "Matzinger Rd",
    "iso:country": "US",
    "sg:address": "1260 Matzinger Rd",
    "sg:city": "Toledo",
    "sg:classifiers": [
      {
        "category": "Freight",
        "type": "Transportation"
      }
    ],
    "sg:phone": "+1 419 727 1424",
    "sg:postcode": "43612",
    "sg:province": "OH",
    "sg:tags": [
      "operator",
      "trucking"
    ],
    "sg:website": "www.vitran-express.com",
    "wof:name": "Vitran Express Inc",
    "wof:placetype": "venue"
  },
  "geometry": {"coordinates":[-83.516315,41.708719],"type":"Point"}
}
