{
  "type": "Feature",
  "properties": {
    "addr:full": "616 N Columbus St Lancaster OH 43130",
    "addr:housenumber": "616",
    "addr:postcode": "43130",
    "addr:street": "N Columbus St",
    "iso:country": "US",
    "sg:address": "616 N Columbus St",
    "sg:city": "Lancaster",
    "sg:classifiers": [
      {
        "category": "Health Services",
        "subcategory": "Chiropractor",
        "type": "Services"
      }
    ],
    "sg:phone": "+1 740 653 2973",
    "sg:postcode": "43130",
    "sg:province": "OH",
    "wof:name": "Lancaster Chiropractic Clinic",
    "wof:placetype": "venue"
  },
  "geometry": {"coordinates":[-82.604212,39.720361],"type":"Point"}
}
