{
  "type": "Feature",
  "properties": {
    "addr:full": "2149 Bethel Hygiene Rd Bethel OH 45106",
    "addr:housenumber": "2149",
    "addr:postcode": "45106",
    "addr:street": "Bethel Hygiene Rd",
    "iso:country": "US",
    "sg:address": "2149 Bethel Hygiene Rd",
    "sg:city": "Bethel",
    "sg:classifiers": [
      {
        "category": "Retail",
        "subcategory": "Animal Services",
        "type": "Services"
      }
    ],
    "sg:phone": "+1 513 734 2655",
    "sg:postcode": "45106",
    "sg:province": "OH",
    "wof:name": "Dog Groomg By Carla",
    "wof:placetype": "venue"
  },
  "geometry": {"coordinates":[-84.118999,38.926166],"type":"Point"}
}
