{
  "type": "Feature",
  "properties": {
    "addr:full":"12575 Columbiana Canfield Rd Columbiana OH 44408",
    "addr:housenumber":"12575",
    "addr:postcode":"44408",
    "addr:street":"Canfield Rd",
    "iso:country":"US",
    "sg:address":"12575 Columbiana Canfield Rd",
    "sg:city":"Columbiana",
    "sg:classifiers":[
        {
            "category":"Banks & Credit Unions",
            "subcategory":"Financial Services",
            "type":"Services"
        }
    ],
    "sg:phone":"+1 330 549 2212",
    "sg:postcode":"44408",
    "sg:province":"OH",
    "sg:tags":[
        "investor"
    ],
    "wof:name":"Adda Investments LLC",
    "wof:placetype":"venue"
},
  "geometry": {"coordinates":[-80.726529,40.935627],"type":"Point"}
}