{
  "type": "Feature",
  "properties": {
    "addr:full":"7812 Colerain Ave Cincinnati OH 45239",
    "addr:housenumber":"7812",
    "addr:postcode":"45239",
    "addr:street":"Colerain Ave",
    "iso:country":"US",
    "sg:address":"7812 Colerain Ave",
    "sg:city":"Cincinnati",
    "sg:classifiers":[
        {
            "category":"Shopping",
            "type":"Retail Goods"
        }
    ],
    "sg:phone":"+1 513 728 3200",
    "sg:postcode":"45239",
    "sg:province":"OH",
    "sg:tags":[
        "wedding",
        "supply"
    ],
    "wof:name":"Jack Herb Florists",
    "wof:placetype":"venue"
},
  "geometry": {"coordinates":[-84.585273,39.21614],"type":"Point"}
}