{
  "type": "Feature",
  "properties": {
    "addr:full":"3406 Carper Ave Akron OH 44312",
    "addr:housenumber":"3406",
    "addr:postcode":"44312",
    "addr:street":"Carper Ave",
    "iso:country":"US",
    "sg:address":"3406 Carper Ave",
    "sg:city":"Akron",
    "sg:classifiers":[
        {
            "category":"Building & Trades",
            "subcategory":"Plumbing",
            "type":"Services"
        }
    ],
    "sg:phone":"+1 330 628 5108",
    "sg:postcode":"44312",
    "sg:province":"OH",
    "sg:tags":[
        "plumbing",
        "contractor"
    ],
    "wof:name":"American Patriot Plbg & Drain",
    "wof:placetype":"venue"
},
  "geometry": {"coordinates":[-81.402807,41.038321],"type":"Point"}
}