{
  "type": "Feature",
  "properties": {
    "addr:full":"6410 Honeytown Rd Smithville OH 44677",
    "addr:housenumber":"6410",
    "addr:postcode":"44677",
    "addr:street":"Honeytown Rd",
    "iso:country":"US",
    "sg:address":"6410 Honeytown Rd",
    "sg:city":"Smithville",
    "sg:classifiers":[
        {
            "category":"Shopping",
            "subcategory":"Jewelry",
            "type":"Retail Goods"
        }
    ],
    "sg:phone":"+1 330 669 2114",
    "sg:postcode":"44677",
    "sg:province":"OH",
    "sg:tags":[
        "clocks"
    ],
    "wof:name":"Wooster Clock",
    "wof:placetype":"venue"
},
  "geometry": {"coordinates":[-81.878297,40.875568],"type":"Point"}
}