{
  "type": "Feature",
  "properties": {
    "addr:full":"1915 Scioto Trl Portsmouth OH 45662",
    "addr:housenumber":"1915",
    "addr:postcode":"45662",
    "addr:street":"Scioto Trl",
    "iso:country":"US",
    "sg:address":"1915 Scioto Trl",
    "sg:city":"Portsmouth",
    "sg:classifiers":[
        {
            "category":"Professional",
            "subcategory":"Research",
            "type":"Services"
        }
    ],
    "sg:phone":"+1 740 353 5464",
    "sg:postcode":"45662",
    "sg:province":"OH",
    "sg:tags":[
        "laboratory"
    ],
    "wof:name":"Laboratory For Automated",
    "wof:placetype":"venue"
},
  "geometry": {"coordinates":[-82.99228599999999,38.747195],"type":"Point"}
}