{
  "type": "Feature",
  "properties": {
    "iso:country":"US",
    "sg:address":"6058 Winnebago St",
    "sg:city":"Grove City",
    "sg:classifiers":[
        {
            "category":"Restaurant",
            "type":"Food & Drink"
        }
    ],
    "sg:phone":"+1 614 491 9317",
    "sg:postcode":"43123",
    "sg:province":"OH",
    "wof:name":"Down South Diner",
    "wof:placetype":"venue"
},
  "geometry": {"coordinates":[-83.052362,39.837449],"type":"Point"}
}