{
  "type": "Feature",
  "properties": {
    "iso:country":"US",
    "sg:address":"30338 Nagel Rd",
    "sg:city":"Defiance",
    "sg:classifiers":[
        {
            "category":"Building & Trades",
            "subcategory":"Construction",
            "type":"Services"
        }
    ],
    "sg:phone":"+1 419 267 3639",
    "sg:postcode":"43512",
    "sg:province":"OH",
    "sg:tags":[
        "contractor"
    ],
    "wof:name":"David Meyer",
    "wof:placetype":"venue"
},
  "geometry": {"coordinates":[-84.242377,41.41314],"type":"Point"}
}