{
  "type": "Feature",
  "properties": {
    "addr:full": "787 Lexington Ave Mansfield OH 44907",
    "addr:housenumber": "787",
    "addr:postcode": "44907",
    "addr:street": "Lexington Ave",
    "iso:country": "US",
    "sg:address": "787 Lexington Ave",
    "sg:city": "Mansfield",
    "sg:classifiers": [
      {
        "category": "Personal",
        "type": "Services"
      }
    ],
    "sg:phone": "+1 419 774 9566",
    "sg:postcode": "44907",
    "sg:province": "OH",
    "sg:tags": [
      "therapist",
      "massage"
    ],
    "wof:name": "Amy Arnold",
    "wof:placetype": "venue"
  },
  "geometry": {"coordinates":[-82.532243,40.735639],"type":"Point"}
}
