{
  "type": "Feature",
  "properties": {
    "addr:full": "936 Prestige Blvd Lancaster OH 43130",
    "addr:housenumber": "936",
    "addr:postcode": "43130",
    "addr:street": "Prestige Blvd",
    "iso:country": "US",
    "sg:address": "936 Prestige Blvd",
    "sg:city": "Lancaster",
    "sg:classifiers": [
      {
        "category": "Shopping",
        "subcategory": "Florist",
        "type": "Retail Goods"
      }
    ],
    "sg:phone": "+1 740 653 8551",
    "sg:postcode": "43130",
    "sg:province": "OH",
    "sg:tags": [
      "flower"
    ],
    "wof:name": "Helens Flowers \u0026GReenhouse",
    "wof:placetype": "venue"
  },
  "geometry": {"coordinates":[-82.632313,39.726819],"type":"Point"}
}
