{
  "type": "Feature",
  "properties": {
    "iso:country":"US",
    "sg:address":"936 Prestige Blvd",
    "sg:city":"Lancaster",
    "sg:classifiers":[
        {
            "category":"Shopping",
            "subcategory":"Florist",
            "type":"Retail Goods"
        }
    ],
    "sg:phone":"+1 740 653 8551",
    "sg:postcode":"43130",
    "sg:province":"OH",
    "sg:tags":[
        "flower"
    ],
    "wof:name":"Helens Flowers &GReenhouse",
    "wof:placetype":"venue"
},
  "geometry": {"coordinates":[-82.632313,39.726819],"type":"Point"}
}