{
  "type": "Feature",
  "properties": {
    "iso:country":"US",
    "sg:address":"3292 Stones Throw Ave",
    "sg:city":"Youngstown",
    "sg:classifiers":[
        {
            "category":"Banks & Credit Unions",
            "subcategory":"Financial Services",
            "type":"Services"
        }
    ],
    "sg:phone":"+1 330 707 5864",
    "sg:postcode":"44514",
    "sg:province":"OH",
    "sg:tags":[
        "company",
        "holding"
    ],
    "wof:name":"APM Holdings LLC",
    "wof:placetype":"venue"
},
  "geometry": {"coordinates":[-80.58926200000001,41.024657],"type":"Point"}
}