{
  "type": "Feature",
  "properties": {
    "addr:full":"1144 E Rookwood Dr Cincinnati OH 45208",
    "addr:housenumber":"1144",
    "addr:postcode":"45208",
    "addr:street":"E Rookwood Dr",
    "iso:country":"US",
    "sg:address":"1144 E Rookwood Dr",
    "sg:city":"Cincinnati",
    "sg:classifiers":[
        {
            "category":"Professional",
            "subcategory":"Lawyer & Legal Services",
            "type":"Services"
        }
    ],
    "sg:phone":"+1 513 651 0100",
    "sg:postcode":"45208",
    "sg:province":"OH",
    "sg:tags":[
        "attorney"
    ],
    "wof:name":"Robert S Bromberg",
    "wof:placetype":"venue"
},
  "geometry": {"coordinates":[-84.44519699999999,39.131569],"type":"Point"}
}