{
  "type": "Feature",
  "properties": {
    "addr:full":"1111 Chevy Ln Piqua OH 45356",
    "addr:housenumber":"1111",
    "addr:postcode":"45356",
    "addr:street":"Chevy Ln",
    "iso:country":"US",
    "sg:address":"1111 Chevy Ln",
    "sg:city":"Piqua",
    "sg:classifiers":[
        {
            "category":"Professional",
            "subcategory":"Computer Services",
            "type":"Services"
        }
    ],
    "sg:phone":"+1 937 773 1121",
    "sg:postcode":"45356",
    "sg:province":"OH",
    "sg:tags":[
        "information",
        "retrieval",
        "real estate"
    ],
    "wof:name":"First Class Results Inc",
    "wof:placetype":"venue"
},
  "geometry": {"coordinates":[-84.238428,40.164332],"type":"Point"}
}