{
  "type": "Feature",
  "properties": {
    "addr:full": "21254 State Rte 12 Fostoria OH 44830",
    "addr:housenumber": "21254",
    "addr:postcode": "44830",
    "addr:street": "State Rte 12",
    "iso:country": "US",
    "sg:address": "21254 State Rte 12",
    "sg:city": "Fostoria",
    "sg:classifiers": [
      {
        "category": "Recreation",
        "type": "Entertainment"
      }
    ],
    "sg:phone": "+1 419 435 9568",
    "sg:postcode": "44830",
    "sg:province": "OH",
    "sg:tags": [
      "center"
    ],
    "wof:name": "Putt'n Pond Park",
    "wof:placetype": "venue"
  },
  "geometry": {"coordinates":[-83.46453,41.133416],"type":"Point"}
}
