{
  "type": "Feature",
  "properties": {
    "addr:full":"350 S Main St Swanton OH 43558",
    "addr:housenumber":"350",
    "addr:postcode":"43558",
    "addr:street":"S Main St",
    "iso:country":"US",
    "sg:address":"350 S Main St",
    "sg:city":"Swanton",
    "sg:classifiers":[
        {
            "category":"Recreation",
            "type":"Entertainment"
        }
    ],
    "sg:phone":"+1 419 826 5487",
    "sg:postcode":"43558",
    "sg:province":"OH",
    "sg:tags":[
        "parks"
    ],
    "wof:name":"Swanton Park & Recreation Dept",
    "wof:placetype":"venue"
},
  "geometry": {"coordinates":[-83.88874199999999,41.584316],"type":"Point"}
}