{
  "type": "Feature",
  "properties": {
    "iso:country":"US",
    "sg:address":"7134 Atlantic Ave",
    "sg:city":"Sterling",
    "sg:classifiers":[
        {
            "category":"Farming",
            "subcategory":"Farm",
            "type":"Manufacturing & Wholesale Goods"
        }
    ],
    "sg:phone":"+1 330 939 3172",
    "sg:postcode":"44276",
    "sg:province":"OH",
    "sg:tags":[
        "crop",
        "general"
    ],
    "wof:name":"Mervin Miller",
    "wof:placetype":"venue"
},
  "geometry": {"coordinates":[-81.83927,40.967551],"type":"Point"}
}