{
  "type": "Feature",
  "properties": {
    "addr:full": "121 N Paul St Woodsfield OH 43793",
    "addr:housenumber": "121",
    "addr:postcode": "43793",
    "addr:street": "N Paul St",
    "iso:country": "US",
    "sg:address": "121 N Paul St",
    "sg:city": "Woodsfield",
    "sg:classifiers": [
      {
        "category": "Retail",
        "subcategory": "Repair Shop",
        "type": "Services"
      }
    ],
    "sg:phone": "+1 740 472 2467",
    "sg:postcode": "43793",
    "sg:province": "OH",
    "sg:tags": [
      "taxidermist"
    ],
    "wof:name": "Griffin's Taxidermy",
    "wof:placetype": "venue"
  },
  "geometry": {"coordinates":[-81.114647,39.762485],"type":"Point"}
}
