{
  "type": "Feature",
  "properties": {
    "addr:full": "811 W 8th St Cincinnati OH 45203",
    "addr:housenumber": "811",
    "addr:postcode": "45203",
    "addr:street": "W 8Th St",
    "iso:country": "US",
    "sg:address": "811 W 8th St",
    "sg:city": "Cincinnati",
    "sg:classifiers": [
      {
        "category": "Autos \u0026 Motor Vehicles",
        "subcategory": "Fuel \u0026 Gas Station",
        "type": "Retail Goods"
      }
    ],
    "sg:phone": "+1 513 241 7885",
    "sg:postcode": "45203",
    "sg:province": "OH",
    "sg:tags": [
      "station",
      "gasoline"
    ],
    "wof:name": "Stephenson Oil Co",
    "wof:placetype": "venue"
  },
  "geometry": {"coordinates":[-84.532959,39.10363],"type":"Point"}
}
