{
  "type": "Feature",
  "properties": {
    "iso:country":"US",
    "sg:address":"523 W Main St",
    "sg:city":"Springfield",
    "sg:classifiers":[
        {
            "category":"Autos & Motor Vehicles",
            "subcategory":"Automobile Sales",
            "type":"Retail Goods"
        },
        {
            "category":"Manufacturing",
            "subcategory":"Motor Vehicles & Parts",
            "type":"Manufacturing & Wholesale Goods"
        }
    ],
    "sg:phone":"+1 937 322 5134",
    "sg:postcode":"45504",
    "sg:province":"OH",
    "sg:tags":[
        "mfg",
        "suppl",
        "classic"
    ],
    "wof:name":"Bill's Rod & Custom Shop",
    "wof:placetype":"venue"
},
  "geometry": {"coordinates":[-83.82104099999999,39.925166],"type":"Point"}
}