{
  "type": "Feature",
  "properties": {
    "addr:full": "523 W Main St Springfield OH 45504",
    "addr:housenumber": "523",
    "addr:postcode": "45504",
    "addr:street": "W Main St",
    "iso:country": "US",
    "sg:address": "523 W Main St",
    "sg:city": "Springfield",
    "sg:classifiers": [
      {
        "category": "Autos \u0026 Motor Vehicles",
        "subcategory": "Automobile Sales",
        "type": "Retail Goods"
      },
      {
        "category": "Manufacturing",
        "subcategory": "Motor Vehicles \u0026 Parts",
        "type": "Manufacturing \u0026 Wholesale Goods"
      }
    ],
    "sg:phone": "+1 937 322 5134",
    "sg:postcode": "45504",
    "sg:province": "OH",
    "sg:tags": [
      "mfg",
      "suppl",
      "classic"
    ],
    "wof:name": "Bill's Rod \u0026 Custom Shop",
    "wof:placetype": "venue"
  },
  "geometry": {"coordinates":[-83.821041,39.925166],"type":"Point"}
}
