{
  "type": "Feature",
  "properties": {
    "addr:full": "100 E 2nd St Waverly OH 45690",
    "addr:housenumber": "100",
    "addr:postcode": "45690",
    "addr:street": "E 2Nd St",
    "iso:country": "US",
    "sg:address": "100 E 2nd St",
    "sg:city": "Waverly",
    "sg:classifiers": [
      {
        "category": "Government",
        "subcategory": "Office",
        "type": "Public Place"
      }
    ],
    "sg:phone": "+1 740 947 2622",
    "sg:postcode": "45690",
    "sg:province": "OH",
    "wof:name": "Pike County Recorder's Office",
    "wof:placetype": "venue"
  },
  "geometry": {"coordinates":[-82.98328,39.126979],"type":"Point"}
}
