{
  "type": "Feature",
  "properties": {
    "iso:country":"US",
    "sg:address":"299 Cramer Creek Ct",
    "sg:city":"Dublin",
    "sg:classifiers":[
        {
            "category":"Social Services",
            "type":"Services"
        }
    ],
    "sg:phone":"+1 614 889 9477",
    "sg:postcode":"43017",
    "sg:province":"OH",
    "sg:tags":[
        "employee",
        "assistance",
        "program"
    ],
    "wof:name":"Well Choice Enterprises",
    "wof:placetype":"venue"
},
  "geometry": {"coordinates":[-83.121372,40.083725],"type":"Point"}
}