{
  "type": "Feature",
  "properties": {
    "iso:country":"US",
    "sg:address":"2341 S Clinton St",
    "sg:city":"Defiance",
    "sg:classifiers":[
        {
            "category":"Insurance",
            "subcategory":"Insurance Agent",
            "type":"Services"
        }
    ],
    "sg:phone":"+1 419 782 0228",
    "sg:postcode":"43512",
    "sg:province":"OH",
    "wof:name":"Thrivent Financial-Lutherans",
    "wof:placetype":"venue"
},
  "geometry": {"coordinates":[-84.39704399999999,41.254791],"type":"Point"}
}