{
  "type": "Feature",
  "properties": {
    "iso:country":"US",
    "sg:address":"203 E Broadway St",
    "sg:city":"Wellston",
    "sg:classifiers":[
        {
            "category":"Organizations",
            "subcategory":"Professional Association",
            "type":"Services"
        }
    ],
    "sg:phone":"+1 740 384 3051",
    "sg:postcode":"45692",
    "sg:province":"OH",
    "sg:tags":[
        "chambers",
        "commerce"
    ],
    "wof:name":"Chamber Of Commerce",
    "wof:placetype":"venue"
},
  "geometry": {"coordinates":[-82.532985,39.123542],"type":"Point"}
}