{
  "type": "Feature",
  "properties": {
    "addr:full": "3774 Rocky River Dr Cleveland OH 44111",
    "addr:housenumber": "3774",
    "addr:postcode": "44111",
    "addr:street": "Rocky River Dr",
    "iso:country": "US",
    "sg:address": "3774 Rocky River Dr",
    "sg:city": "Cleveland",
    "sg:classifiers": [
      {
        "category": "Retail",
        "subcategory": "Laundry \u0026 Dry Cleaning",
        "type": "Services"
      }
    ],
    "sg:phone": "+1 216 251 0515",
    "sg:postcode": "44111",
    "sg:province": "OH",
    "sg:tags": [
      "drycleaning",
      "plant"
    ],
    "wof:name": "Handee Cleaners",
    "wof:placetype": "venue"
  },
  "geometry": {"coordinates":[-81.816783,41.450573],"type":"Point"}
}
