{
  "type": "Feature",
  "properties": {
    "addr:full":"773 Mc Clurg Rd Youngstown OH 44512",
    "addr:housenumber":"773",
    "addr:postcode":"44512",
    "addr:street":"Mc Clurg Rd",
    "iso:country":"US",
    "sg:address":"773 Mc Clurg Rd",
    "sg:city":"Youngstown",
    "sg:classifiers":[
        {
            "category":"Wholesale",
            "subcategory":"Metals & Minerals",
            "type":"Manufacturing & Wholesale Goods"
        }
    ],
    "sg:phone":"+1 330 965 2340",
    "sg:postcode":"44512",
    "sg:province":"OH",
    "sg:tags":[
        "machine",
        "work",
        "representative",
        "for",
        "broker"
    ],
    "wof:name":"R C Olson Enterprises Inc",
    "wof:placetype":"venue"
},
  "geometry": {"coordinates":[-80.63605,40.995127],"type":"Point"}
}