{
  "type": "Feature",
  "properties": {
    "addr:full":"204 Linden Ave Dayton OH 45403",
    "addr:housenumber":"204",
    "addr:postcode":"45403",
    "addr:street":"Linden Ave",
    "iso:country":"US",
    "sg:address":"204 Linden Ave",
    "sg:city":"Dayton",
    "sg:classifiers":[
        {
            "category":"Retail",
            "subcategory":"Repair Shop",
            "type":"Services"
        }
    ],
    "sg:phone":"+1 937 259 0091",
    "sg:postcode":"45403",
    "sg:province":"OH",
    "sg:tags":[
        "electrical"
    ],
    "wof:name":"Comm Parts & Service of Dayton",
    "wof:placetype":"venue"
},
  "geometry": {"coordinates":[-84.159205,39.758953],"type":"Point"}
}