{
  "type": "Feature",
  "properties": {
    "addr:full":"19800 Center Ridge Rd Cleveland OH 44116",
    "addr:housenumber":"19800",
    "addr:postcode":"44116",
    "addr:street":"Center Ridge Rd",
    "iso:country":"US",
    "sg:address":"19800 Center Ridge Rd",
    "sg:city":"Cleveland",
    "sg:classifiers":[
        {
            "category":"Personal",
            "subcategory":"Beauty Salon",
            "type":"Services"
        }
    ],
    "sg:phone":"+1 440 333 6050",
    "sg:postcode":"44116",
    "sg:province":"OH",
    "wof:name":"Sharon's Hair Design & Tanning",
    "wof:placetype":"venue"
},
  "geometry": {"coordinates":[-81.841953,41.464981],"type":"Point"}
}