{
  "type": "Feature",
  "properties": {
    "iso:country":"US",
    "sg:address":"4201 W 8th St",
    "sg:city":"Cincinnati",
    "sg:classifiers":[
        {
            "category":"Food & Beverages",
            "subcategory":"Liquor & Beverages",
            "type":"Retail Goods"
        },
        {
            "category":"Autos & Motor Vehicles",
            "subcategory":"Fuel & Gas Station",
            "type":"Retail Goods"
        }
    ],
    "sg:phone":"+1 513 244 5001",
    "sg:postcode":"45205",
    "sg:province":"OH",
    "sg:tags":[
        "repair",
        "ale",
        "gasoline",
        "general",
        "beer",
        "station"
    ],
    "wof:name":"Eighth Street Drive Thru",
    "wof:placetype":"venue"
},
  "geometry": {"coordinates":[-84.589371,39.107486],"type":"Point"}
}