{
  "type": "Feature",
  "properties": {
    "addr:full": "4201 W 8th St Cincinnati OH 45205",
    "addr:housenumber": "4201",
    "addr:postcode": "45205",
    "addr:street": "W 8Th St",
    "iso:country": "US",
    "sg:address": "4201 W 8th St",
    "sg:city": "Cincinnati",
    "sg:classifiers": [
      {
        "category": "Food \u0026 Beverages",
        "subcategory": "Liquor \u0026 Beverages",
        "type": "Retail Goods"
      },
      {
        "category": "Autos \u0026 Motor Vehicles",
        "subcategory": "Fuel \u0026 Gas Station",
        "type": "Retail Goods"
      }
    ],
    "sg:phone": "+1 513 244 5001",
    "sg:postcode": "45205",
    "sg:province": "OH",
    "sg:tags": [
      "repair",
      "ale",
      "gasoline",
      "general",
      "beer",
      "station"
    ],
    "wof:name": "Eighth Street Drive Thru",
    "wof:placetype": "venue"
  },
  "geometry": {"coordinates":[-84.589371,39.107486],"type":"Point"}
}
