{
  "type": "Feature",
  "properties": {
    "addr:full":"1619 Salt Springs Rd Youngstown OH 44509",
    "addr:housenumber":"1619",
    "addr:postcode":"44509",
    "addr:street":"Salt Springs Rd",
    "iso:country":"US",
    "sg:address":"1619 Salt Springs Rd",
    "sg:city":"Youngstown",
    "sg:classifiers":[
        {
            "category":"Building & Trades",
            "subcategory":"Plumbing",
            "type":"Services"
        }
    ],
    "sg:phone":"+1 330 792 1234",
    "sg:postcode":"44509",
    "sg:province":"OH",
    "sg:tags":[
        "contractor"
    ],
    "wof:name":"City Heating Service",
    "wof:placetype":"venue"
},
  "geometry": {"coordinates":[-80.693815,41.119914],"type":"Point"}
}