{
  "type": "Feature",
  "properties": {
    "addr:full": "17421 Honeysuckle Ln Columbia Station OH 44028",
    "addr:housenumber": "17421",
    "addr:postcode": "44028",
    "addr:street": "Honeysuckle Ln",
    "iso:country": "US",
    "sg:address": "17421 Honeysuckle Ln",
    "sg:city": "Columbia Station",
    "sg:classifiers": [
      {
        "category": "Building \u0026 Trades",
        "subcategory": "Construction",
        "type": "Services"
      }
    ],
    "sg:phone": "+1 440 236 3535",
    "sg:postcode": "44028",
    "sg:province": "OH",
    "sg:tags": [
      "house"
    ],
    "wof:name": "S\u0026R Builders Inc",
    "wof:placetype": "venue"
  },
  "geometry": {"coordinates":[-81.962132,41.291251],"type":"Point"}
}
