{
  "type": "Feature",
  "properties": {
    "iso:country":"US",
    "sg:address":"17421 Honeysuckle Ln",
    "sg:city":"Columbia Station",
    "sg:classifiers":[
        {
            "category":"Building & Trades",
            "subcategory":"Construction",
            "type":"Services"
        }
    ],
    "sg:phone":"+1 440 236 3535",
    "sg:postcode":"44028",
    "sg:province":"OH",
    "sg:tags":[
        "house"
    ],
    "wof:name":"S&R Builders Inc",
    "wof:placetype":"venue"
},
  "geometry": {"coordinates":[-81.962132,41.291251],"type":"Point"}
}