{
  "type": "Feature",
  "properties": {
    "addr:full":"1570 Covington Ave Piqua OH 45356",
    "addr:housenumber":"1570",
    "addr:postcode":"45356",
    "addr:street":"Covington Ave",
    "iso:country":"US",
    "sg:address":"1570 Covington Ave",
    "sg:city":"Piqua",
    "sg:classifiers":[
        {
            "category":"Banks & Credit Unions",
            "subcategory":"Bank",
            "type":"Services"
        }
    ],
    "sg:phone":"+1 937 778 8841",
    "sg:postcode":"45356",
    "sg:province":"OH",
    "sg:tags":[
        "cashing",
        "check"
    ],
    "wof:name":"Advance America",
    "wof:placetype":"venue"
},
  "geometry": {"coordinates":[-84.266972,40.141444],"type":"Point"}
}