{
  "type": "Feature",
  "properties": {
    "iso:country":"US",
    "sg:address":"7495 State Rte 15",
    "sg:city":"Defiance",
    "sg:classifiers":[
        {
            "category":"Government",
            "subcategory":"Office",
            "type":"Public Place"
        }
    ],
    "sg:phone":"+1 419 658 2309",
    "sg:postcode":"43512",
    "sg:province":"OH",
    "sg:tags":[
        "county",
        "garage",
        "highway"
    ],
    "wof:name":"Highway Garage",
    "wof:placetype":"venue"
},
  "geometry": {"coordinates":[-84.43011199999999,41.333928],"type":"Point"}
}