{
  "type": "Feature",
  "properties": {
    "addr:full":"145 N Main St Roseville OH 43777",
    "addr:housenumber":"145",
    "addr:postcode":"43777",
    "addr:street":"N Main St",
    "iso:country":"US",
    "sg:address":"145 N Main St",
    "sg:city":"Roseville",
    "sg:classifiers":[
        {
            "category":"Shopping",
            "subcategory":"Florist",
            "type":"Retail Goods"
        }
    ],
    "sg:phone":"+1 740 697 0080",
    "sg:postcode":"43777",
    "sg:province":"OH",
    "sg:tags":[
        "flower"
    ],
    "wof:name":"Tracy's Flowers",
    "wof:placetype":"venue"
},
  "geometry": {"coordinates":[-82.072778,39.805655],"type":"Point"}
}