{
  "type": "Feature",
  "properties": {
    "addr:full":"233 Tuxedo Ave Cleveland OH 44131",
    "addr:housenumber":"233",
    "addr:postcode":"44131",
    "addr:street":"Tuxedo Ave",
    "iso:country":"US",
    "sg:address":"233 Tuxedo Ave",
    "sg:city":"Cleveland",
    "sg:classifiers":[
        {
            "category":"Autos & Motor Vehicles",
            "subcategory":"Fuel & Gas Station",
            "type":"Retail Goods"
        }
    ],
    "sg:phone":"+1 216 351 0131",
    "sg:postcode":"44131",
    "sg:province":"OH",
    "sg:tags":[
        "station",
        "gasoline"
    ],
    "wof:name":"Village Of Brooklyn Heights",
    "wof:placetype":"venue"
},
  "geometry": {"coordinates":[-81.67899300000001,41.420177],"type":"Point"}
}