{
  "type": "Feature",
  "properties": {
    "addr:full": "3770 W National Rd Springfield OH 45504",
    "addr:housenumber": "3770",
    "addr:postcode": "45504",
    "addr:street": "W National Rd",
    "iso:country": "US",
    "sg:address": "3770 W National Rd",
    "sg:city": "Springfield",
    "sg:classifiers": [
      {
        "category": "Retail",
        "subcategory": "Auto Repair",
        "type": "Services"
      }
    ],
    "sg:phone": "+1 937 325 8389",
    "sg:postcode": "45504",
    "sg:province": "OH",
    "sg:tags": [
      "automobile",
      "restoration",
      "classic"
    ],
    "wof:name": "Lobeck's V-8 Shop Hot Rod Pts",
    "wof:placetype": "venue"
  },
  "geometry": {"coordinates":[-83.880222,39.925531],"type":"Point"}
}
