{
  "type": "Feature",
  "properties": {
    "iso:country":"US",
    "sg:address":"5209 Ashwood Dr",
    "sg:city":"Cleveland",
    "sg:classifiers":[
        {
            "category":"Professional",
            "subcategory":"Management & Consulting",
            "type":"Services"
        }
    ],
    "sg:phone":"+1 440 461 0054",
    "sg:postcode":"44124",
    "sg:province":"OH",
    "sg:tags":[
        "consultant",
        "business"
    ],
    "wof:name":"Krj & Assoc Management Svc",
    "wof:placetype":"venue"
},
  "geometry": {"coordinates":[-81.49051,41.533032],"type":"Point"}
}