{
  "type": "Feature",
  "properties": {
    "addr:full": "5309 Rockwood Dr Castalia OH 44824",
    "addr:housenumber": "5309",
    "addr:postcode": "44824",
    "addr:street": "Rockwood Dr",
    "iso:country": "US",
    "sg:address": "5309 Rockwood Dr",
    "sg:city": "Castalia",
    "sg:classifiers": [
      {
        "category": "Retail",
        "subcategory": "Repair Shop",
        "type": "Services"
      }
    ],
    "sg:phone": "+1 419 684 7747",
    "sg:postcode": "44824",
    "sg:province": "OH",
    "sg:tags": [
      "cleaners",
      "parts",
      "vacuum"
    ],
    "wof:name": "Bud's Sweeper Sales \u0026 Svc",
    "wof:placetype": "venue"
  },
  "geometry": {"coordinates":[-82.774521,41.399215],"type":"Point"}
}
