{
  "type": "Feature",
  "properties": {
    "iso:country":"US",
    "sg:address":"3632 Upton Ave",
    "sg:city":"Toledo",
    "sg:classifiers":[
        {
            "category":"Personal",
            "subcategory":"Beauty Salon",
            "type":"Services"
        }
    ],
    "sg:phone":"+1 419 486 9070",
    "sg:postcode":"43613",
    "sg:province":"OH",
    "wof:name":"First Class Beauty Salon",
    "wof:placetype":"venue"
},
  "geometry": {"coordinates":[-83.58928400000001,41.686317],"type":"Point"}
}