{
  "type": "Feature",
  "properties": {
    "addr:full": "1581 N Curry Rd Wilmington OH 45177",
    "addr:housenumber": "1581",
    "addr:postcode": "45177",
    "addr:street": "N Curry Rd",
    "iso:country": "US",
    "sg:address": "1581 N Curry Rd",
    "sg:city": "Wilmington",
    "sg:classifiers": [
      {
        "category": "Education",
        "subcategory": "Special Training",
        "type": "Public Place"
      }
    ],
    "sg:phone": "+1 937 382 4638",
    "sg:postcode": "45177",
    "sg:province": "OH",
    "sg:tags": [
      "aircraft",
      "school"
    ],
    "wof:name": "Daniel's Aviation",
    "wof:placetype": "venue"
  },
  "geometry": {"coordinates":[-83.862669,39.50097],"type":"Point"}
}
