{
  "type": "Feature",
  "properties": {
    "iso:country":"US",
    "sg:address":"29 E Main St",
    "sg:city":"Xenia",
    "sg:classifiers":[
        {
            "category":"Shopping",
            "subcategory":"Gifts & Souvenirs",
            "type":"Retail Goods"
        }
    ],
    "sg:phone":"+1 937 372 2721",
    "sg:postcode":"45385",
    "sg:province":"OH",
    "sg:tags":[
        "shop"
    ],
    "wof:name":"Gifts & More",
    "wof:placetype":"venue"
},
  "geometry": {"coordinates":[-83.928888,39.684962],"type":"Point"}
}