{
  "type": "Feature",
  "properties": {
    "addr:full": "29 E Main St Xenia OH 45385",
    "addr:housenumber": "29",
    "addr:postcode": "45385",
    "addr:street": "E Main St",
    "iso:country": "US",
    "sg:address": "29 E Main St",
    "sg:city": "Xenia",
    "sg:classifiers": [
      {
        "category": "Shopping",
        "subcategory": "Gifts \u0026 Souvenirs",
        "type": "Retail Goods"
      }
    ],
    "sg:phone": "+1 937 372 2721",
    "sg:postcode": "45385",
    "sg:province": "OH",
    "sg:tags": [
      "shop"
    ],
    "wof:name": "Gifts \u0026 More",
    "wof:placetype": "venue"
  },
  "geometry": {"coordinates":[-83.928888,39.684962],"type":"Point"}
}
