{
  "type": "Feature",
  "properties": {
    "addr:full": "208 N Main St Minerva OH 44657",
    "addr:housenumber": "208",
    "addr:postcode": "44657",
    "addr:street": "N Main St",
    "iso:country": "US",
    "sg:address": "208 N Main St",
    "sg:city": "Minerva",
    "sg:classifiers": [
      {
        "category": "Professional",
        "type": "Services"
      }
    ],
    "sg:phone": "+1 330 868 5007",
    "sg:postcode": "44657",
    "sg:province": "OH",
    "sg:tags": [
      "establishment"
    ],
    "wof:name": "C C \u0026 S Inc",
    "wof:placetype": "venue"
  },
  "geometry": {"coordinates":[-81.104628,40.729351],"type":"Point"}
}
