{
  "type": "Feature",
  "properties": {
    "iso:country":"US",
    "sg:address":"208 N Main St",
    "sg:city":"Minerva",
    "sg:classifiers":[
        {
            "category":"Professional",
            "type":"Services"
        }
    ],
    "sg:phone":"+1 330 868 5007",
    "sg:postcode":"44657",
    "sg:province":"OH",
    "sg:tags":[
        "establishment"
    ],
    "wof:name":"C C & S Inc",
    "wof:placetype":"venue"
},
  "geometry": {"coordinates":[-81.10462800000001,40.729351],"type":"Point"}
}