{
  "type": "Feature",
  "properties": {
    "iso:country":"US",
    "sg:address":"467 N Dugan Rd",
    "sg:city":"Urbana",
    "sg:classifiers":[
        {
            "category":"Retail",
            "subcategory":"Animal Services",
            "type":"Services"
        }
    ],
    "sg:phone":"+1 937 653 6210",
    "sg:postcode":"43078",
    "sg:province":"OH",
    "wof:name":"Betty J Taylor",
    "wof:placetype":"venue"
},
  "geometry": {"coordinates":[-83.712238,40.107012],"type":"Point"}
}