{
  "type": "Feature",
  "properties": {
    "iso:country":"US",
    "sg:address":"93 Renee Dr",
    "sg:city":"Struthers",
    "sg:classifiers":[
        {
            "category":"Restaurant",
            "type":"Food & Drink"
        }
    ],
    "sg:phone":"+1 330 755 1853",
    "sg:postcode":"44471",
    "sg:province":"OH",
    "sg:tags":[
        "caterer"
    ],
    "wof:name":"Loretta's Catering",
    "wof:placetype":"venue"
},
  "geometry": {"coordinates":[-80.593348,41.046354],"type":"Point"}
}