{
  "type": "Feature",
  "properties": {
    "addr:full":"1708 S Main St Bellefontaine OH 43311",
    "addr:housenumber":"1708",
    "addr:postcode":"43311",
    "addr:street":"S Main St",
    "iso:country":"US",
    "sg:address":"1708 S Main St",
    "sg:city":"Bellefontaine",
    "sg:classifiers":[
        {
            "category":"Food & Beverages",
            "subcategory":"Groceries & Convenience Stores",
            "type":"Retail Goods"
        }
    ],
    "sg:phone":"+1 937 000 1111",
    "sg:postcode":"43311",
    "sg:province":"OH",
    "sg:tags":[
        "grocer"
    ],
    "wof:name":"Aldi",
    "wof:placetype":"venue"
},
  "geometry": {"coordinates":[-83.761932,40.337176],"type":"Point"}
}