{
  "type": "Feature",
  "properties": {
    "addr:full":"405 Gregorian Dr Fairfield OH 45014",
    "addr:housenumber":"405",
    "addr:postcode":"45014",
    "addr:street":"Gregorian Dr",
    "iso:country":"US",
    "sg:address":"405 Gregorian Dr",
    "sg:city":"Fairfield",
    "sg:classifiers":[
        {
            "category":"Building & Trades",
            "subcategory":"Construction",
            "type":"Services"
        }
    ],
    "sg:phone":"+1 513 829 7790",
    "sg:postcode":"45014",
    "sg:province":"OH",
    "sg:tags":[
        "residential"
    ],
    "wof:name":"Hershner Homes LLC",
    "wof:placetype":"venue"
},
  "geometry": {"coordinates":[-84.59788399999999,39.317845],"type":"Point"}
}