{
  "type": "Feature",
  "properties": {
    "addr:full": "950 Main St Toronto OH 43964",
    "addr:housenumber": "950",
    "addr:postcode": "43964",
    "addr:street": "Main St",
    "iso:country": "US",
    "sg:address": "950 Main St",
    "sg:city": "Toronto",
    "sg:classifiers": [
      {
        "category": "Building \u0026 Trades",
        "subcategory": "Construction",
        "type": "Services"
      }
    ],
    "sg:phone": "+1 740 537 9122",
    "sg:postcode": "43964",
    "sg:province": "OH",
    "sg:tags": [
      "house"
    ],
    "wof:name": "Jack Gibson Construction Co",
    "wof:placetype": "venue"
  },
  "geometry": {"coordinates":[-80.60953,40.463919],"type":"Point"}
}
