{
  "type": "Feature",
  "properties": {
    "addr:full": "2650 Case Rd Bethel OH 45157",
    "addr:housenumber": "2650",
    "addr:postcode": "45157",
    "addr:street": "Case Rd",
    "iso:country": "US",
    "sg:address": "2650 Case Rd",
    "sg:city": "Bethel",
    "sg:classifiers": [
      {
        "category": "Travel",
        "subcategory": "Hotels \u0026 Motels",
        "type": "Entertainment"
      }
    ],
    "sg:phone": "+1 513 734 4949",
    "sg:postcode": "45157",
    "sg:province": "OH",
    "sg:tags": [
      "resort",
      "operation"
    ],
    "wof:name": "Ohio State Park \u0026 Resort",
    "wof:placetype": "venue"
  },
  "geometry": {"coordinates":[-84.136544,38.944726],"type":"Point"}
}
