{
  "type": "Feature",
  "properties": {
    "addr:full":"1000 30th St NW Canton OH 44709",
    "addr:housenumber":"1000",
    "addr:postcode":"44709",
    "addr:street":"30Th St Nw",
    "iso:country":"US",
    "sg:address":"1000 30th St NW",
    "sg:city":"Canton",
    "sg:classifiers":[
        {
            "category":"Shopping",
            "subcategory":"Used Merchandise",
            "type":"Retail Goods"
        }
    ],
    "sg:phone":"+1 330 649 9179",
    "sg:postcode":"44709",
    "sg:province":"OH",
    "wof:name":"Goodwill Thrift Shop",
    "wof:placetype":"venue"
},
  "geometry": {"coordinates":[-81.381788,40.831344],"type":"Point"}
}