{
  "type": "Feature",
  "properties": {
    "iso:country":"US",
    "sg:address":"4821 Corporate St SW",
    "sg:city":"Canton",
    "sg:classifiers":[
        {
            "category":"Freight",
            "type":"Transportation"
        }
    ],
    "sg:phone":"+1 330 478 2114",
    "sg:postcode":"44706",
    "sg:province":"OH",
    "sg:tags":[
        "trucking"
    ],
    "wof:name":"Blue Velvet Transport Inc",
    "wof:placetype":"venue"
},
  "geometry": {"coordinates":[-81.439769,40.778543],"type":"Point"}
}