{
  "type": "Feature",
  "properties": {
    "addr:full":"11769 Milnor Rd Pickerington OH 43147",
    "addr:housenumber":"11769",
    "addr:postcode":"43147",
    "addr:street":"Milnor Rd",
    "iso:country":"US",
    "sg:address":"11769 Milnor Rd",
    "sg:city":"Pickerington",
    "sg:classifiers":[
        {
            "category":"Building & Trades",
            "subcategory":"Cleaning & Sanitation",
            "type":"Services"
        },
        {
            "category":"Retail",
            "subcategory":"Laundry & Dry Cleaning",
            "type":"Services"
        }
    ],
    "sg:phone":"+1 614 231 0812",
    "sg:postcode":"43147",
    "sg:province":"OH",
    "sg:tags":[
        "cleaners",
        "rug",
        "maintenance",
        "carpet"
    ],
    "wof:name":"Stephson Carpet Cleaning",
    "wof:placetype":"venue"
},
  "geometry": {"coordinates":[-82.74768,39.905184],"type":"Point"}
}