{
  "type": "Feature",
  "properties": {
    "iso:country":"US",
    "sg:address":"351 1st St",
    "sg:city":"Perrysburg",
    "sg:classifiers":[
        {
            "category":"Education",
            "subcategory":"Junior College",
            "type":"Public Place"
        }
    ],
    "sg:phone":"+1 419 661 7000",
    "sg:postcode":"43551",
    "sg:province":"OH",
    "wof:name":"Receiving Dept",
    "wof:placetype":"venue"
},
  "geometry": {"coordinates":[-83.538348,41.590366],"type":"Point"}
}