{
  "type": "Feature",
  "properties": {
    "iso:country":"US",
    "sg:address":"251 W Main St",
    "sg:city":"Pomeroy",
    "sg:classifiers":[
        {
            "category":"Restaurant",
            "type":"Food & Drink"
        }
    ],
    "sg:phone":"+1 740 992 0099",
    "sg:postcode":"45769",
    "sg:province":"OH",
    "sg:tags":[
        "eating"
    ],
    "wof:name":"Wild Horse Cafe",
    "wof:placetype":"venue"
},
  "geometry": {"coordinates":[-82.039146,39.024059],"type":"Point"}
}