{
  "type": "Feature",
  "properties": {
    "iso:country":"US",
    "sg:address":"625 S Main St",
    "sg:city":"Piqua",
    "sg:classifiers":[
        {
            "category":"Education",
            "subcategory":"School",
            "type":"Public Place"
        }
    ],
    "sg:phone":"+1 937 773 0386",
    "sg:postcode":"45356",
    "sg:province":"OH",
    "wof:name":"Bennett Intermediate School",
    "wof:placetype":"venue"
},
  "geometry": {"coordinates":[-84.238913,40.139386],"type":"Point"}
}