{
  "type": "Feature",
  "properties": {
    "addr:full":"523 Kittery Ln Cincinnati OH 45255",
    "addr:housenumber":"523",
    "addr:postcode":"45255",
    "addr:street":"Kittery Ln",
    "iso:country":"US",
    "sg:address":"523 Kittery Ln",
    "sg:city":"Cincinnati",
    "sg:classifiers":[
        {
            "category":"Wholesale",
            "subcategory":"Non-durable Goods",
            "type":"Manufacturing & Wholesale Goods"
        }
    ],
    "sg:phone":"+1 513 753 8392",
    "sg:postcode":"45255",
    "sg:province":"OH",
    "sg:tags":[
        "dry",
        "goods-wholesale"
    ],
    "wof:name":"Supply Ease",
    "wof:placetype":"venue"
},
  "geometry": {"coordinates":[-84.302888,39.042911],"type":"Point"}
}