{
  "type": "Feature",
  "properties": {
    "addr:full":"483 Colonial Ave Columbus OH 43085",
    "addr:housenumber":"483",
    "addr:postcode":"43085",
    "addr:street":"Colonial Ave",
    "iso:country":"US",
    "sg:address":"483 Colonial Ave",
    "sg:city":"Columbus",
    "sg:classifiers":[
        {
            "category":"Health Services",
            "subcategory":"Doctor",
            "type":"Services"
        }
    ],
    "sg:phone":"+1 614 459 2441",
    "sg:postcode":"43085",
    "sg:province":"OH",
    "wof:name":"Dr Steven C Walton DDS",
    "wof:placetype":"venue"
},
  "geometry": {"coordinates":[-83.00433099999999,40.082],"type":"Point"}
}