{
  "type": "Feature",
  "properties": {
    "addr:full": "160 S Mulberry St Logan OH 43138",
    "addr:housenumber": "160",
    "addr:postcode": "43138",
    "addr:street": "S Mulberry St",
    "iso:country": "US",
    "sg:address": "160 S Mulberry St",
    "sg:city": "Logan",
    "sg:classifiers": [
      {
        "category": "Health Services",
        "subcategory": "Doctor",
        "type": "Services"
      }
    ],
    "sg:phone": "+1 740 385 8620",
    "sg:postcode": "43138",
    "sg:province": "OH",
    "sg:tags": [
      "dentist"
    ],
    "wof:name": "W Daniel Alder Inc",
    "wof:placetype": "venue"
  },
  "geometry": {"coordinates":[-82.406988,39.538294],"type":"Point"}
}
