{
  "type": "Feature",
  "properties": {
    "addr:full": "37340 Royalton Rd Grafton OH 44044",
    "addr:housenumber": "37340",
    "addr:postcode": "44044",
    "addr:street": "Royalton Rd",
    "iso:country": "US",
    "sg:address": "37340 Royalton Rd",
    "sg:city": "Grafton",
    "sg:classifiers": [
      {
        "category": "Arts \u0026 Performance",
        "subcategory": "Theater",
        "type": "Entertainment"
      }
    ],
    "sg:phone": "+1 440 748 3571",
    "sg:postcode": "44044",
    "sg:province": "OH",
    "sg:tags": [
      "karaoke"
    ],
    "wof:name": "Dejavu Entertainment",
    "wof:placetype": "venue"
  },
  "geometry": {"coordinates":[-82.044866,41.314845],"type":"Point"}
}
