{
  "type": "Feature",
  "properties": {
    "addr:full":"8533 Washington St Chagrin Falls OH 44023",
    "addr:housenumber":"8533",
    "addr:postcode":"44023",
    "addr:street":"Washington St",
    "iso:country":"US",
    "sg:address":"8533 Washington St",
    "sg:city":"Chagrin Falls",
    "sg:classifiers":[
        {
            "category":"Restaurant",
            "type":"Food & Drink"
        }
    ],
    "sg:phone":"+1 440 708 0777",
    "sg:postcode":"44023",
    "sg:province":"OH",
    "sg:tags":[
        "japanese"
    ],
    "wof:name":"Mr Terriyaki",
    "wof:placetype":"venue"
},
  "geometry": {"coordinates":[-81.335994,41.41087],"type":"Point"}
}