{
  "type": "Feature",
  "properties": {
    "addr:full":"241 14th St NW Barberton OH 44203",
    "addr:housenumber":"241",
    "addr:postcode":"44203",
    "addr:street":"14Th St Nw",
    "iso:country":"US",
    "sg:address":"241 14th St NW",
    "sg:city":"Barberton",
    "sg:classifiers":[
        {
            "category":"Professional",
            "type":"Services"
        }
    ],
    "sg:phone":"+1 330 825 9294",
    "sg:postcode":"44203",
    "sg:province":"OH",
    "wof:name":"House of Paper",
    "wof:placetype":"venue"
},
  "geometry": {"coordinates":[-81.620893,41.015842],"type":"Point"}
}