{
  "type": "Feature",
  "properties": {
    "iso:country":"US",
    "sg:address":"1100 E Main Cross St",
    "sg:city":"Findlay",
    "sg:classifiers":[
        {
            "category":"Social Services",
            "type":"Services"
        }
    ],
    "sg:phone":"+1 419 424 1335",
    "sg:postcode":"45840",
    "sg:province":"OH",
    "wof:name":"Community Partnership",
    "wof:placetype":"venue"
},
  "geometry": {"coordinates":[-83.628374,41.041494],"type":"Point"}
}