{
  "type": "Feature",
  "properties": {
    "addr:full": "11780 Rd 22K Cloverdale OH 45827",
    "addr:housenumber": "11780;22k",
    "addr:postcode": "45827",
    "addr:street": "Rd",
    "iso:country": "US",
    "sg:address": "11780 Rd 22K",
    "sg:city": "Cloverdale",
    "sg:phone": "+1 419 488 4511",
    "sg:postcode": "45827",
    "sg:province": "OH",
    "sg:tags": [
      "farm",
      "soybean"
    ],
    "wof:name": "Wannamacher Farms",
    "wof:placetype": "venue"
  },
  "geometry": {"coordinates":[-84.280172,41.008622],"type":"Point"}
}
