{
  "type": "Feature",
  "properties": {
    "addr:full":"2500 Carroll Eastern Rd NW Lancaster OH 43130",
    "addr:housenumber":"2500",
    "addr:postcode":"43130",
    "addr:street":"Carroll Eastern Rd Nw",
    "iso:country":"US",
    "sg:address":"2500 Carroll Eastern Rd NW",
    "sg:city":"Lancaster",
    "sg:classifiers":[
        {
            "category":"Shopping",
            "subcategory":"Beauty & Cosmetics",
            "type":"Retail Goods"
        }
    ],
    "sg:phone":"+1 740 756 7021",
    "sg:postcode":"43130",
    "sg:province":"OH",
    "wof:name":"Home & Yard Cosmt By Henrietta",
    "wof:placetype":"venue"
},
  "geometry": {"coordinates":[-82.64510799999999,39.799673],"type":"Point"}
}