{
  "type": "Feature",
  "properties": {
    "addr:full": "10266 Edgewood Dr Findlay OH 45840",
    "addr:housenumber": "10266",
    "addr:postcode": "45840",
    "addr:street": "Edgewood Dr",
    "iso:country": "US",
    "sg:address": "10266 Edgewood Dr",
    "sg:city": "Findlay",
    "sg:classifiers": [
      {
        "category": "Building \u0026 Trades",
        "subcategory": "Construction",
        "type": "Services"
      }
    ],
    "sg:phone": "+1 419 425 4345",
    "sg:postcode": "45840",
    "sg:province": "OH",
    "sg:tags": [
      "mobile",
      "home"
    ],
    "wof:name": "Phil's Mobile Home Repair",
    "wof:placetype": "venue"
  },
  "geometry": {"coordinates":[-83.686128,41.049953],"type":"Point"}
}
