{
  "type": "Feature",
  "properties": {
    "addr:full":"1800 W Turkeyfoot Lake Rd Barberton OH 44203",
    "addr:housenumber":"1800",
    "addr:postcode":"44203",
    "addr:street":"W Turkeyfoot Lake Rd",
    "iso:country":"US",
    "sg:address":"1800 W Turkeyfoot Lake Rd",
    "sg:city":"Barberton",
    "sg:classifiers":[
        {
            "category":"Utilities",
            "subcategory":"Fuel Oil & Lpg",
            "type":"Services"
        }
    ],
    "sg:phone":"+1 330 825 0400",
    "sg:postcode":"44203",
    "sg:province":"OH",
    "sg:tags":[
        "firewood"
    ],
    "wof:name":"Norton Hardwood",
    "wof:placetype":"venue"
},
  "geometry": {"coordinates":[-81.580564,40.992725],"type":"Point"}
}