{
  "type": "Feature",
  "properties": {
    "iso:country":"US",
    "sg:address":"550 Park Ave E",
    "sg:city":"Mansfield",
    "sg:classifiers":[
        {
            "category":"Building & Trades",
            "subcategory":"Landscaping Services",
            "type":"Services"
        }
    ],
    "sg:phone":"+1 419 589 0305",
    "sg:postcode":"44905",
    "sg:province":"OH",
    "sg:tags":[
        "landscape",
        "contractor"
    ],
    "wof:name":"Mid-Ohio Lawn & Landscape",
    "wof:placetype":"venue"
},
  "geometry": {"coordinates":[-82.492186,40.758096],"type":"Point"}
}