{
  "type": "Feature",
  "properties": {
    "addr:full": "550 Park Ave E Mansfield OH 44905",
    "addr:housenumber": "550",
    "addr:postcode": "44905",
    "addr:street": "Park Ave E",
    "iso:country": "US",
    "sg:address": "550 Park Ave E",
    "sg:city": "Mansfield",
    "sg:classifiers": [
      {
        "category": "Building \u0026 Trades",
        "subcategory": "Landscaping Services",
        "type": "Services"
      }
    ],
    "sg:phone": "+1 419 589 0305",
    "sg:postcode": "44905",
    "sg:province": "OH",
    "sg:tags": [
      "landscape",
      "contractor"
    ],
    "wof:name": "Mid-Ohio Lawn \u0026 Landscape",
    "wof:placetype": "venue"
  },
  "geometry": {"coordinates":[-82.492186,40.758096],"type":"Point"}
}
