{
  "type": "Feature",
  "properties": {
    "iso:country":"US",
    "sg:address":"2959 Wren-Landeck Rd",
    "sg:city":"Ohio City",
    "sg:classifiers":[
        {
            "category":"Professional",
            "type":"Services"
        }
    ],
    "sg:phone":"+1 419 495 2767",
    "sg:postcode":"45874",
    "sg:province":"OH",
    "wof:name":"Jim Henrey",
    "wof:placetype":"venue"
},
  "geometry": {"coordinates":[-84.766479,40.800992],"type":"Point"}
}