{
  "type": "Feature",
  "properties": {
    "addr:full": "25861 Annesley Rd Beachwood OH 44122",
    "addr:housenumber": "25861",
    "addr:postcode": "44122",
    "addr:street": "Annesley Rd",
    "iso:country": "US",
    "sg:address": "25861 Annesley Rd",
    "sg:city": "Beachwood",
    "sg:classifiers": [
      {
        "category": "Wholesale",
        "subcategory": "Non-durable Goods",
        "type": "Manufacturing \u0026 Wholesale Goods"
      }
    ],
    "sg:phone": "+1 216 896 9618",
    "sg:postcode": "44122",
    "sg:province": "OH",
    "sg:tags": [
      "shop",
      "advertising",
      "gift"
    ],
    "wof:name": "Weis Incentives",
    "wof:placetype": "venue"
  },
  "geometry": {"coordinates":[-81.496045,41.481339],"type":"Point"}
}
