{
  "type": "Feature",
  "properties": {
    "addr:full":"1 Park Centre Dr Wadsworth OH 44281",
    "addr:housenumber":"1",
    "addr:postcode":"44281",
    "addr:street":"Park Centre Dr",
    "iso:country":"US",
    "sg:address":"1 Park Centre Dr",
    "sg:city":"Wadsworth",
    "sg:classifiers":[
        {
            "category":"Shopping",
            "subcategory":"Computers & Home Electronics",
            "type":"Retail Goods"
        }
    ],
    "sg:phone":"+1 330 336 6860",
    "sg:postcode":"44281",
    "sg:province":"OH",
    "sg:tags":[
        "software"
    ],
    "wof:name":"ATI Application Svc Co Inc",
    "wof:placetype":"venue"
},
  "geometry": {"coordinates":[-81.72826999999999,41.048304],"type":"Point"}
}