{
  "type": "Feature",
  "properties": {
    "addr:full":"3157 Ebenezer Rd Cincinnati OH 45248",
    "addr:housenumber":"3157",
    "addr:postcode":"45248",
    "addr:street":"Ebenezer Rd",
    "iso:country":"US",
    "sg:address":"3157 Ebenezer Rd",
    "sg:city":"Cincinnati",
    "sg:classifiers":[
        {
            "category":"Organizations",
            "subcategory":"Religious Organization",
            "type":"Services"
        }
    ],
    "sg:phone":"+1 513 921 8902",
    "sg:postcode":"45248",
    "sg:province":"OH",
    "sg:tags":[
        "church"
    ],
    "wof:name":"Quebec Road Church Of God",
    "wof:placetype":"venue"
},
  "geometry": {"coordinates":[-84.650554,39.144302],"type":"Point"}
}