{
  "type": "Feature",
  "properties": {
    "iso:country":"US",
    "sg:address":"209 Main St",
    "sg:city":"Belpre",
    "sg:classifiers":[
        {
            "category":"Shopping",
            "subcategory":"Hobbies, Toys, & Games",
            "type":"Retail Goods"
        }
    ],
    "sg:phone":"+1 740 423 9096",
    "sg:postcode":"45714",
    "sg:province":"OH",
    "sg:tags":[
        "craft",
        "supply"
    ],
    "wof:name":"P G's Craftmania",
    "wof:placetype":"venue"
},
  "geometry": {"coordinates":[-81.569462,39.274153],"type":"Point"}
}