{
  "type": "Feature",
  "properties": {
    "iso:country":"US",
    "sg:address":"6067 Bayshore Rd",
    "sg:city":"Oregon",
    "sg:classifiers":[
        {
            "category":"Professional",
            "type":"Services"
        }
    ],
    "sg:phone":"+1 419 698 3037",
    "sg:postcode":"43618",
    "sg:province":"OH",
    "sg:tags":[
        "establishment"
    ],
    "wof:name":"Captains Last Port",
    "wof:placetype":"venue"
},
  "geometry": {"coordinates":[-83.403547,41.68919],"type":"Point"}
}