{
  "type": "Feature",
  "properties": {
    "addr:full":"1973 Millvale Ct Cincinnati OH 45225",
    "addr:housenumber":"1973",
    "addr:postcode":"45225",
    "addr:street":"Millvale Ct",
    "iso:country":"US",
    "sg:address":"1973 Millvale Ct",
    "sg:city":"Cincinnati",
    "sg:classifiers":[
        {
            "category":"Social Services",
            "type":"Services"
        }
    ],
    "sg:phone":"+1 513 541 7910",
    "sg:postcode":"45225",
    "sg:province":"OH",
    "sg:tags":[
        "youth",
        "organization",
        "center"
    ],
    "wof:name":"Citizens Committee On Youth",
    "wof:placetype":"venue"
},
  "geometry": {"coordinates":[-84.554412,39.148561],"type":"Point"}
}