{
  "type": "Feature",
  "properties": {
    "addr:full": "5974 Ropes Dr Cincinnati OH 45244",
    "addr:housenumber": "5974",
    "addr:postcode": "45244",
    "addr:street": "Ropes Dr",
    "iso:country": "US",
    "sg:address": "5974 Ropes Dr",
    "sg:city": "Cincinnati",
    "sg:classifiers": [
      {
        "category": "Professional",
        "subcategory": "Management \u0026 Consulting",
        "type": "Services"
      }
    ],
    "sg:phone": "+1 513 232 1333",
    "sg:postcode": "45244",
    "sg:province": "OH",
    "sg:tags": [
      "marketing",
      "consultant"
    ],
    "wof:name": "Emergence Creative Lab",
    "wof:placetype": "venue"
  },
  "geometry": {"coordinates":[-84.37873,39.113531],"type":"Point"}
}
