{
  "type": "Feature",
  "properties": {
    "iso:country":"US",
    "sg:address":"1835 E 30th St",
    "sg:city":"Cleveland",
    "sg:classifiers":[
        {
            "category":"Autos & Motor Vehicles",
            "subcategory":"Automobile Sales",
            "type":"Retail Goods"
        }
    ],
    "sg:phone":"+1 216 685 9000",
    "sg:postcode":"44114",
    "sg:province":"OH",
    "sg:tags":[
        "car",
        "dealer"
    ],
    "wof:name":"Exotic Auto Import Store",
    "wof:placetype":"venue"
},
  "geometry": {"coordinates":[-81.667756,41.50484],"type":"Point"}
}