{
  "type": "Feature",
  "properties": {
    "iso:country":"US",
    "sg:address":"1666 E 29th St",
    "sg:city":"Lorain",
    "sg:classifiers":[
        {
            "category":"Professional",
            "type":"Services"
        }
    ],
    "sg:phone":"+1 440 240 1854",
    "sg:postcode":"44055",
    "sg:province":"OH",
    "wof:name":"Miguel Luna",
    "wof:placetype":"venue"
},
  "geometry": {"coordinates":[-82.142427,41.44429],"type":"Point"}
}