{
  "type": "Feature",
  "properties": {
    "iso:country":"US",
    "sg:address":"4760 Sandra Lee Ln",
    "sg:city":"Cincinnati",
    "sg:classifiers":[
        {
            "category":"Professional",
            "subcategory":"Lawyer & Legal Services",
            "type":"Services"
        }
    ],
    "sg:phone":"+1 513 528 1414",
    "sg:postcode":"45244",
    "sg:province":"OH",
    "sg:tags":[
        "attorney"
    ],
    "wof:name":"Masters & Co",
    "wof:placetype":"venue"
},
  "geometry": {"coordinates":[-84.292991,39.120304],"type":"Point"}
}