{
  "type": "Feature",
  "properties": {
    "addr:full":"315 S 11th St Coshocton OH 43812",
    "addr:housenumber":"315",
    "addr:postcode":"43812",
    "addr:street":"S 11Th St",
    "iso:country":"US",
    "sg:address":"315 S 11th St",
    "sg:city":"Coshocton",
    "sg:classifiers":[
        {
            "category":"Personal",
            "subcategory":"Beauty Salon",
            "type":"Services"
        }
    ],
    "sg:phone":"+1 740 622 2406",
    "sg:postcode":"43812",
    "sg:province":"OH",
    "wof:name":"Hair Gallery",
    "wof:placetype":"venue"
},
  "geometry": {"coordinates":[-81.85359699999999,40.272546],"type":"Point"}
}