{
  "type": "Feature",
  "properties": {
    "addr:full": "14055 State Rte 115 Columbus Grove OH 45830",
    "addr:housenumber": "14055",
    "addr:postcode": "45830",
    "addr:street": "State Rte 115 Columbus Grove",
    "iso:country": "US",
    "sg:address": "14055 State Rte 115",
    "sg:city": "Columbus Grove",
    "sg:classifiers": [
      {
        "category": "Wholesale",
        "subcategory": "Non-durable Goods",
        "type": "Manufacturing \u0026 Wholesale Goods"
      }
    ],
    "sg:phone": "+1 419 532 3599",
    "sg:postcode": "45830",
    "sg:province": "OH",
    "sg:tags": [
      "tarpaulin"
    ],
    "wof:name": "Schulte Tarp Service",
    "wof:placetype": "venue"
  },
  "geometry": {"coordinates":[-84.189039,40.972294],"type":"Point"}
}
