{
  "type": "Feature",
  "properties": {
    "iso:country":"US",
    "sg:address":"3359 W 2nd St",
    "sg:city":"Dayton",
    "sg:classifiers":[
        {
            "category":"Recreation",
            "type":"Entertainment"
        },
        {
            "category":"Organizations",
            "subcategory":"Community Association",
            "type":"Services"
        }
    ],
    "sg:phone":"+1 937 262 9949",
    "sg:postcode":"45417",
    "sg:province":"OH",
    "sg:tags":[
        "club",
        "membership"
    ],
    "wof:name":"Dayton West Club Inc",
    "wof:placetype":"venue"
},
  "geometry": {"coordinates":[-84.24458799999999,39.754133],"type":"Point"}
}