{
  "type": "Feature",
  "properties": {
    "iso:country":"US",
    "sg:address":"6880 Taylor Rd",
    "sg:city":"Clinton",
    "sg:classifiers":[
        {
            "category":"Building & Trades",
            "subcategory":"Construction",
            "type":"Services"
        }
    ],
    "sg:phone":"+1 330 825 9800",
    "sg:postcode":"44216",
    "sg:province":"OH",
    "sg:tags":[
        "concrete",
        "contractor"
    ],
    "wof:name":"Goliath Concrete Construction",
    "wof:placetype":"venue"
},
  "geometry": {"coordinates":[-81.64779799999999,40.941792],"type":"Point"}
}