{
  "type": "Feature",
  "properties": {
    "addr:full": "6880 Taylor Rd Clinton OH 44216",
    "addr:housenumber": "6880",
    "addr:postcode": "44216",
    "addr:street": "Taylor Rd",
    "iso:country": "US",
    "sg:address": "6880 Taylor Rd",
    "sg:city": "Clinton",
    "sg:classifiers": [
      {
        "category": "Building \u0026 Trades",
        "subcategory": "Construction",
        "type": "Services"
      }
    ],
    "sg:phone": "+1 330 825 9800",
    "sg:postcode": "44216",
    "sg:province": "OH",
    "sg:tags": [
      "concrete",
      "contractor"
    ],
    "wof:name": "Goliath Concrete Construction",
    "wof:placetype": "venue"
  },
  "geometry": {"coordinates":[-81.647798,40.941792],"type":"Point"}
}
