{
  "type": "Feature",
  "properties": {
    "iso:country":"US",
    "sg:address":"101 W Sandusky St",
    "sg:city":"Findlay",
    "sg:classifiers":[
        {
            "category":"Organizations",
            "subcategory":"Labor Organization",
            "type":"Services"
        }
    ],
    "sg:phone":"+1 419 424 1708",
    "sg:postcode":"45840",
    "sg:province":"OH",
    "wof:name":"Northwestern Ohio Education",
    "wof:placetype":"venue"
},
  "geometry": {"coordinates":[-83.650272,41.037039],"type":"Point"}
}