{
  "type": "Feature",
  "properties": {
    "addr:full": "601 W High St Piqua OH 45356",
    "addr:housenumber": "601",
    "addr:postcode": "45356",
    "addr:street": "W High St",
    "iso:country": "US",
    "sg:address": "601 W High St",
    "sg:city": "Piqua",
    "sg:classifiers": [
      {
        "category": "Health Services",
        "subcategory": "Health Practitioner",
        "type": "Services"
      }
    ],
    "sg:phone": "+1 937 773 3485",
    "sg:postcode": "45356",
    "sg:province": "OH",
    "sg:tags": [
      "therapist",
      "physical"
    ],
    "wof:name": "Miami Physical Rehabilitation",
    "wof:placetype": "venue"
  },
  "geometry": {"coordinates":[-84.24689,40.148554],"type":"Point"}
}
