{
  "type": "Feature",
  "properties": {
    "addr:full": "3808 Surrey Hill Pl Columbus OH 43220",
    "addr:housenumber": "3808",
    "addr:postcode": "43220",
    "addr:street": "Surrey Hill Pl",
    "iso:country": "US",
    "sg:address": "3808 Surrey Hill Pl",
    "sg:city": "Columbus",
    "sg:classifiers": [
      {
        "category": "Professional",
        "subcategory": "Management \u0026 Consulting",
        "type": "Services"
      }
    ],
    "sg:phone": "+1 614 451 8914",
    "sg:postcode": "43220",
    "sg:province": "OH",
    "sg:tags": [
      "consultant",
      "training"
    ],
    "wof:name": "Van Meter Law Enforcement",
    "wof:placetype": "venue"
  },
  "geometry": {"coordinates":[-83.076747,40.033988],"type":"Point"}
}
