{
  "type": "Feature",
  "properties": {
    "addr:full": "2915 Mogadore Rd Akron OH 44312",
    "addr:housenumber": "2915",
    "addr:postcode": "44312",
    "addr:street": "Mogadore Rd",
    "iso:country": "US",
    "sg:address": "2915 Mogadore Rd",
    "sg:city": "Akron",
    "sg:classifiers": [
      {
        "category": "Autos \u0026 Motor Vehicles",
        "subcategory": "Automobile Sales",
        "type": "Retail Goods"
      },
      {
        "category": "Autos \u0026 Motor Vehicles",
        "subcategory": "Auto Supplies",
        "type": "Retail Goods"
      }
    ],
    "sg:phone": "+1 330 784 6029",
    "sg:postcode": "44312",
    "sg:province": "OH",
    "sg:tags": [
      "cars-wholesale",
      "dealers-used",
      "part",
      "supplies-used",
      "rebuilt",
      "salvage"
    ],
    "sg:website": "http://www.brownseastsideauto.com",
    "wof:name": "Brown's Eastside Auto Recycling",
    "wof:placetype": "venue"
  },
  "geometry": {"coordinates":[-81.4265,41.056533],"type":"Point"}
}
