{
  "type": "Feature",
  "properties": {
    "addr:full": "200 Public Sq Cleveland OH 44114",
    "addr:housenumber": "200",
    "addr:postcode": "44114",
    "addr:street": "Public Sq",
    "iso:country": "US",
    "sg:address": "200 Public Sq",
    "sg:city": "Cleveland",
    "sg:classifiers": [
      {
        "category": "Restaurant",
        "type": "Food \u0026 Drink"
      }
    ],
    "sg:phone": "+1 216 579 9999",
    "sg:postcode": "44114",
    "sg:province": "OH",
    "sg:tags": [
      "serving"
    ],
    "wof:name": "FRAnk\u0026paulys Banquets LLC",
    "wof:placetype": "venue"
  },
  "geometry": {"coordinates":[-81.693357,41.50076],"type":"Point"}
}
