{
  "type": "Feature",
  "properties": {
    "addr:full": "3480 Refugee Rd Columbus OH 43232",
    "addr:housenumber": "3480",
    "addr:postcode": "43232",
    "addr:street": "Refugee Rd",
    "iso:country": "US",
    "sg:address": "3480 Refugee Rd",
    "sg:city": "Columbus",
    "sg:classifiers": [
      {
        "category": "Restaurant",
        "type": "Food \u0026 Drink"
      }
    ],
    "sg:phone": "+1 614 236 2662",
    "sg:postcode": "43232",
    "sg:province": "OH",
    "wof:name": "Manna Cafe",
    "wof:placetype": "venue"
  },
  "geometry": {"coordinates":[-82.908125,39.917142],"type":"Point"}
}
