{
  "type": "Feature",
  "properties": {
    "iso:country":"US",
    "sg:address":"20 E 1st St",
    "sg:city":"Fredericktown",
    "sg:classifiers":[
        {
            "category":"Wholesale",
            "subcategory":"Auto Parts",
            "type":"Manufacturing & Wholesale Goods"
        }
    ],
    "sg:phone":"+1 740 694 4015",
    "sg:postcode":"43019",
    "sg:province":"OH",
    "wof:name":"NAPA Auto Parts",
    "wof:placetype":"venue"
},
  "geometry": {"coordinates":[-82.543075,40.483224],"type":"Point"}
}