{
  "type": "Feature",
  "properties": {
    "iso:country":"US",
    "sg:address":"412 Washington St",
    "sg:city":"Coal Grove",
    "sg:classifiers":[
        {
            "category":"Organizations",
            "subcategory":"Religious Organization",
            "type":"Services"
        }
    ],
    "sg:phone":"+1 740 532 0434",
    "sg:postcode":"45638",
    "sg:province":"OH",
    "sg:tags":[
        "church"
    ],
    "wof:name":"Jeffersonville Baptist Church",
    "wof:placetype":"venue"
},
  "geometry": {"coordinates":[-82.64466400000001,38.505584],"type":"Point"}
}