{
  "type": "Feature",
  "properties": {
    "addr:full": "9200 Worthington Woods Blvd Columbus OH 43085",
    "addr:housenumber": "9200",
    "addr:postcode": "43085",
    "addr:street": "Worthington Woods Blvd",
    "iso:country": "US",
    "sg:address": "9200 Worthington Woods Blvd",
    "sg:city": "Columbus",
    "sg:classifiers": [
      {
        "category": "Insurance",
        "subcategory": "Hazard Insurance",
        "type": "Services"
      }
    ],
    "sg:phone": "+1 614 410 7000",
    "sg:postcode": "43085",
    "sg:province": "OH",
    "sg:tags": [
      "group"
    ],
    "sg:website": "http://www.uhc.com",
    "wof:name": "United Healthcare",
    "wof:placetype": "venue"
  },
  "geometry": {"coordinates":[-82.978462,40.12203],"type":"Point"}
}
