{
  "type": "Feature",
  "properties": {
    "iso:country":"US",
    "sg:address":"9200 Worthington Woods Blvd",
    "sg:city":"Columbus",
    "sg:classifiers":[
        {
            "category":"Insurance",
            "subcategory":"Hazard Insurance",
            "type":"Services"
        }
    ],
    "sg:phone":"+1 614 410 7000",
    "sg:postcode":"43085",
    "sg:province":"OH",
    "sg:tags":[
        "group"
    ],
    "sg:website":"http://www.uhc.com",
    "wof:name":"United Healthcare",
    "wof:placetype":"venue"
},
  "geometry": {"coordinates":[-82.97846199999999,40.12203],"type":"Point"}
}