{
  "type": "Feature",
  "properties": {
    "addr:full": "10155 Royalton Rd Cleveland OH 44133",
    "addr:housenumber": "10155",
    "addr:postcode": "44133",
    "addr:street": "Royalton Rd",
    "iso:country": "US",
    "sg:address": "10155 Royalton Rd",
    "sg:city": "Cleveland",
    "sg:classifiers": [
      {
        "category": "Building \u0026 Trades",
        "subcategory": "Construction",
        "type": "Services"
      }
    ],
    "sg:phone": "+1 440 877 1740",
    "sg:postcode": "44133",
    "sg:province": "OH",
    "sg:tags": [
      "carpenter"
    ],
    "wof:name": "Poelking Carpentry Corp",
    "wof:placetype": "venue"
  },
  "geometry": {"coordinates":[-81.761193,41.313354],"type":"Point"}
}
