{
  "type": "Feature",
  "properties": {
    "addr:full":"1218 W Main St Kent OH 44240",
    "addr:housenumber":"1218",
    "addr:postcode":"44240",
    "addr:street":"W Main St",
    "iso:country":"US",
    "sg:address":"1218 W Main St",
    "sg:city":"Kent",
    "sg:classifiers":[
        {
            "category":"Autos & Motor Vehicles",
            "subcategory":"Automobile Sales",
            "type":"Retail Goods"
        }
    ],
    "sg:phone":"+1 330 678 5031",
    "sg:postcode":"44240",
    "sg:province":"OH",
    "sg:tags":[
        "car",
        "dealer"
    ],
    "wof:name":"Dean's Auto Store Inc",
    "wof:placetype":"venue"
},
  "geometry": {"coordinates":[-81.389447,41.152232],"type":"Point"}
}