{
  "type": "Feature",
  "properties": {
    "iso:country":"US",
    "sg:address":"5410 Brownfield Dr",
    "sg:city":"Cleveland",
    "sg:phone":"+1 440 888 8925",
    "sg:postcode":"44129",
    "sg:province":"OH",
    "sg:website":"http://chem-dry.net/dd.oh",
    "wof:name":"Chem Dry D & D",
    "wof:placetype":"venue"
},
  "geometry": {"coordinates":[-81.722813,41.397209],"type":"Point"}
}