{
  "type": "Feature",
  "properties": {
    "iso:country":"US",
    "sg:address":"5501 Weller Rd NW",
    "sg:city":"New Philadelphia",
    "sg:classifiers":[
        {
            "category":"Farming",
            "subcategory":"Dairy Farm",
            "type":"Manufacturing & Wholesale Goods"
        }
    ],
    "sg:phone":"+1 330 343 4952",
    "sg:postcode":"44663",
    "sg:province":"OH",
    "wof:name":"George Weller",
    "wof:placetype":"venue"
},
  "geometry": {"coordinates":[-81.564813,40.49631],"type":"Point"}
}