{
  "type": "Feature",
  "properties": {
    "addr:full": "5501 Weller Rd NW New Philadelphia OH 44663",
    "addr:housenumber": "5501",
    "addr:postcode": "44663",
    "addr:street": "Weller Rd Nw New Philadelphia",
    "iso:country": "US",
    "sg:address": "5501 Weller Rd NW",
    "sg:city": "New Philadelphia",
    "sg:classifiers": [
      {
        "category": "Farming",
        "subcategory": "Dairy Farm",
        "type": "Manufacturing \u0026 Wholesale Goods"
      }
    ],
    "sg:phone": "+1 330 343 4952",
    "sg:postcode": "44663",
    "sg:province": "OH",
    "wof:name": "George Weller",
    "wof:placetype": "venue"
  },
  "geometry": {"coordinates":[-81.564813,40.49631],"type":"Point"}
}
