{
  "type": "Feature",
  "properties": {
    "iso:country":"US",
    "sg:address":"4800 Greely Chapel Rd",
    "sg:city":"Lima",
    "sg:phone":"+1 419 221 2246",
    "sg:postcode":"45806",
    "sg:province":"OH",
    "sg:tags":[
        "farm",
        "corn",
        "wheat",
        "soybean"
    ],
    "wof:name":"Louis Johnson",
    "wof:placetype":"venue"
},
  "geometry": {"coordinates":[-84.070694,40.673084],"type":"Point"}
}