{
  "type": "Feature",
  "properties": {
    "addr:full": "205 S Greenwood St Marion OH 43302",
    "addr:housenumber": "205",
    "addr:postcode": "43302",
    "addr:street": "S Greenwood St",
    "iso:country": "US",
    "sg:address": "205 S Greenwood St",
    "sg:city": "Marion",
    "sg:classifiers": [
      {
        "category": "Health Services",
        "subcategory": "Doctor",
        "type": "Services"
      }
    ],
    "sg:phone": "+1 740 382 5222",
    "sg:postcode": "43302",
    "sg:province": "OH",
    "sg:tags": [
      "dentist"
    ],
    "wof:name": "Robert W Imbody DDS",
    "wof:placetype": "venue"
  },
  "geometry": {"coordinates":[-83.120016,40.586847],"type":"Point"}
}
