{
  "type": "Feature",
  "properties": {
    "addr:full":"79475 Freeport Tippecanoe Rd Tippecanoe OH 44699",
    "addr:housenumber":"79475",
    "addr:postcode":"44699",
    "addr:street":"Freeport Tippecanoe Rd",
    "iso:country":"US",
    "sg:address":"79475 Freeport Tippecanoe Rd",
    "sg:city":"Tippecanoe",
    "sg:classifiers":[
        {
            "category":"Wholesale",
            "subcategory":"Plants",
            "type":"Manufacturing & Wholesale Goods"
        }
    ],
    "sg:phone":"+1 740 658 3544",
    "sg:postcode":"44699",
    "sg:province":"OH",
    "sg:tags":[
        "supply"
    ],
    "wof:name":"Weminuche Evergreens",
    "wof:placetype":"venue"
},
  "geometry": {"coordinates":[-81.25636,40.253376],"type":"Point"}
}