{
  "type": "Feature",
  "properties": {
    "addr:full": "5886 E Pine Lake Rd Petersburg OH 44454",
    "addr:housenumber": "5886",
    "addr:postcode": "44454",
    "addr:street": "E Pine Lake Rd",
    "iso:country": "US",
    "sg:address": "5886 E Pine Lake Rd",
    "sg:city": "Petersburg",
    "sg:classifiers": [
      {
        "category": "Building \u0026 Trades",
        "subcategory": "Construction",
        "type": "Services"
      }
    ],
    "sg:phone": "+1 330 542 0970",
    "sg:postcode": "44454",
    "sg:province": "OH",
    "sg:tags": [
      "general",
      "contractor"
    ],
    "wof:name": "LA Farge Construction",
    "wof:placetype": "venue"
  },
  "geometry": {"coordinates":[-80.540499,40.925068],"type":"Point"}
}
