{
  "type": "Feature",
  "properties": {
    "iso:country":"US",
    "sg:address":"5886 E Pine Lake Rd",
    "sg:city":"Petersburg",
    "sg:classifiers":[
        {
            "category":"Building & Trades",
            "subcategory":"Construction",
            "type":"Services"
        }
    ],
    "sg:phone":"+1 330 542 0970",
    "sg:postcode":"44454",
    "sg:province":"OH",
    "sg:tags":[
        "general",
        "contractor"
    ],
    "wof:name":"LA Farge Construction",
    "wof:placetype":"venue"
},
  "geometry": {"coordinates":[-80.540499,40.925068],"type":"Point"}
}