{
  "type": "Feature",
  "properties": {
    "addr:full": "5553 Salem Ave Dayton OH 45426",
    "addr:housenumber": "5553",
    "addr:postcode": "45426",
    "addr:street": "Salem Ave",
    "iso:country": "US",
    "sg:address": "5553 Salem Ave",
    "sg:city": "Dayton",
    "sg:classifiers": [
      {
        "category": "Wholesale",
        "subcategory": "Machinery \u0026 Supplies",
        "type": "Manufacturing \u0026 Wholesale Goods"
      }
    ],
    "sg:phone": "+1 937 837 5245",
    "sg:postcode": "45426",
    "sg:province": "OH",
    "sg:tags": [
      "equipment",
      "salon",
      "establishment",
      "beauty"
    ],
    "wof:name": "Sally Beauty Supply 336",
    "wof:placetype": "venue"
  },
  "geometry": {"coordinates":[-84.29161,39.825135],"type":"Point"}
}
