{
  "type": "Feature",
  "properties": {
    "addr:full": "5001 Fleet Ave Cleveland OH 44105",
    "addr:housenumber": "5001",
    "addr:postcode": "44105",
    "addr:street": "Fleet Ave",
    "iso:country": "US",
    "sg:address": "5001 Fleet Ave",
    "sg:city": "Cleveland",
    "sg:classifiers": [
      {
        "category": "Building \u0026 Trades",
        "subcategory": "Construction",
        "type": "Services"
      }
    ],
    "sg:phone": "+1 216 883 7630",
    "sg:postcode": "44105",
    "sg:province": "OH",
    "sg:tags": [
      "house",
      "carpentry",
      "contractor"
    ],
    "wof:name": "Kirsch Construction Inc",
    "wof:placetype": "venue"
  },
  "geometry": {"coordinates":[-81.654389,41.455852],"type":"Point"}
}
