{
  "type": "Feature",
  "properties": {
    "iso:country":"US",
    "sg:address":"5245 W 130th St",
    "sg:city":"Cleveland",
    "sg:classifiers":[
        {
            "category":"Home & Garden",
            "subcategory":"Building Materials",
            "type":"Retail Goods"
        }
    ],
    "sg:phone":"+1 216 265 8260",
    "sg:postcode":"44130",
    "sg:province":"OH",
    "sg:website":"www.wbsinc.org",
    "wof:name":"Wholesale Builders Supply",
    "wof:placetype":"venue"
},
  "geometry": {"coordinates":[-81.782313,41.417015],"type":"Point"}
}