{
  "type": "Feature",
  "properties": {
    "addr:full": "5245 W 130th St Cleveland OH 44130",
    "addr:housenumber": "5245",
    "addr:postcode": "44130",
    "addr:street": "W 130Th St",
    "iso:country": "US",
    "sg:address": "5245 W 130th St",
    "sg:city": "Cleveland",
    "sg:classifiers": [
      {
        "category": "Home \u0026 Garden",
        "subcategory": "Building Materials",
        "type": "Retail Goods"
      }
    ],
    "sg:phone": "+1 216 265 8260",
    "sg:postcode": "44130",
    "sg:province": "OH",
    "sg:website": "www.wbsinc.org",
    "wof:name": "Wholesale Builders Supply",
    "wof:placetype": "venue"
  },
  "geometry": {"coordinates":[-81.782313,41.417015],"type":"Point"}
}
