{
  "type": "Feature",
  "properties": {
    "addr:full": "429 Old Shay Ln Boardman OH 44512",
    "addr:housenumber": "429",
    "addr:postcode": "44512",
    "addr:street": "Old Shay Ln",
    "iso:country": "US",
    "sg:address": "429 Old Shay Ln",
    "sg:city": "Boardman",
    "sg:classifiers": [
      {
        "category": "Health Services",
        "subcategory": "Doctor",
        "type": "Services"
      }
    ],
    "sg:phone": "+1 330 726 1067",
    "sg:postcode": "44512",
    "sg:province": "OH",
    "sg:tags": [
      "dentist"
    ],
    "wof:name": "Kevert O Bean DDS",
    "wof:placetype": "venue"
  },
  "geometry": {"coordinates":[-80.675515,41.045243],"type":"Point"}
}
