{
  "type": "Feature",
  "properties": {
    "addr:full": "3553 State Rte 160 Gallipolis OH 45631",
    "addr:housenumber": "3553",
    "addr:postcode": "45631",
    "addr:street": "State Rte 160",
    "iso:country": "US",
    "sg:address": "3553 State Rte 160",
    "sg:city": "Gallipolis",
    "sg:classifiers": [
      {
        "category": "Professional",
        "type": "Services"
      }
    ],
    "sg:phone": "+1 740 441 0358",
    "sg:postcode": "45631",
    "sg:province": "OH",
    "wof:name": "Clad Inc",
    "wof:placetype": "venue"
  },
  "geometry": {"coordinates":[-82.237257,38.851615],"type":"Point"}
}
