{
  "type": "Feature",
  "properties": {
    "iso:country":"US",
    "sg:address":"3001 Napoleon Rd",
    "sg:city":"Fremont",
    "sg:classifiers":[
        {
            "category":"Building & Trades",
            "subcategory":"Construction",
            "type":"Services"
        }
    ],
    "sg:phone":"+1 419 332 8764",
    "sg:postcode":"43420",
    "sg:province":"OH",
    "sg:tags":[
        "remodeling",
        "commercial"
    ],
    "wof:name":"Paul Reiter Construction",
    "wof:placetype":"venue"
},
  "geometry": {"coordinates":[-83.15887,41.349289],"type":"Point"}
}