{
  "type": "Feature",
  "properties": {
    "addr:full":"8310 Kesegs Way Blacklick OH 43004",
    "addr:housenumber":"8310",
    "addr:postcode":"43004",
    "addr:street":"Kesegs Way",
    "iso:country":"US",
    "sg:address":"8310 Kesegs Way",
    "sg:city":"Blacklick",
    "sg:classifiers":[
        {
            "category":"Professional",
            "type":"Services"
        }
    ],
    "sg:phone":"+1 614 939 5371",
    "sg:postcode":"43004",
    "sg:province":"OH",
    "sg:tags":[
        "establishment"
    ],
    "wof:name":"Mc Kesson Corp",
    "wof:placetype":"venue"
},
  "geometry": {"coordinates":[-82.794416,40.034837],"type":"Point"}
}