{
  "type": "Feature",
  "properties": {
    "addr:full":"10 Rustic Dr Millersburg OH 44654",
    "addr:housenumber":"10",
    "addr:postcode":"44654",
    "addr:street":"Rustic Dr",
    "iso:country":"US",
    "sg:address":"10 Rustic Dr",
    "sg:city":"Millersburg",
    "sg:classifiers":[
        {
            "category":"Travel",
            "subcategory":"Travel Agent",
            "type":"Entertainment"
        }
    ],
    "sg:phone":"+1 330 674 6553",
    "sg:postcode":"44654",
    "sg:province":"OH",
    "sg:tags":[
        "agency",
        "bureau"
    ],
    "wof:name":"Cruise One",
    "wof:placetype":"venue"
},
  "geometry": {"coordinates":[-81.914823,40.547462],"type":"Point"}
}