{
  "type": "Feature",
  "properties": {
    "addr:full": "16643 State Rte 136 Winchester OH 45697",
    "addr:housenumber": "16643",
    "addr:postcode": "45697",
    "addr:street": "State Rte 136",
    "iso:country": "US",
    "sg:address": "16643 State Rte 136",
    "sg:city": "Winchester",
    "sg:classifiers": [
      {
        "category": "Recreation",
        "type": "Entertainment"
      }
    ],
    "sg:phone": "+1 937 695 9035",
    "sg:postcode": "45697",
    "sg:province": "OH",
    "sg:tags": [
      "instruction",
      "gymnastic"
    ],
    "wof:name": "American Flyers T \u0026 T",
    "wof:placetype": "venue"
  },
  "geometry": {"coordinates":[-83.632358,38.910267],"type":"Point"}
}
