{
  "type": "Feature",
  "properties": {
    "iso:country":"US",
    "sg:address":"16643 State Rte 136",
    "sg:city":"Winchester",
    "sg:classifiers":[
        {
            "category":"Recreation",
            "type":"Entertainment"
        }
    ],
    "sg:phone":"+1 937 695 9035",
    "sg:postcode":"45697",
    "sg:province":"OH",
    "sg:tags":[
        "instruction",
        "gymnastic"
    ],
    "wof:name":"American Flyers T & T",
    "wof:placetype":"venue"
},
  "geometry": {"coordinates":[-83.632358,38.910267],"type":"Point"}
}