{
  "type": "Feature",
  "properties": {
    "iso:country":"US",
    "sg:address":"117 E Center St",
    "sg:city":"Marion",
    "sg:classifiers":[
        {
            "category":"Professional",
            "subcategory":"Lawyer & Legal Services",
            "type":"Services"
        }
    ],
    "sg:phone":"+1 740 382 2611",
    "sg:postcode":"43302",
    "sg:province":"OH",
    "sg:tags":[
        "attorney"
    ],
    "wof:name":"Cordrick & Roston",
    "wof:placetype":"venue"
},
  "geometry": {"coordinates":[-83.127697,40.588614],"type":"Point"}
}