{
  "type": "Feature",
  "properties": {
    "iso:country":"US",
    "sg:address":"12087 Sheraton Ln",
    "sg:city":"Cincinnati",
    "sg:classifiers":[
        {
            "category":"Insurance",
            "subcategory":"Insurance Agent",
            "type":"Services"
        }
    ],
    "sg:phone":"+1 513 346 3200",
    "sg:postcode":"45246",
    "sg:province":"OH",
    "wof:name":"Friedman Agency",
    "wof:placetype":"venue"
},
  "geometry": {"coordinates":[-84.485176,39.299965],"type":"Point"}
}