{
  "type": "Feature",
  "properties": {
    "iso:country":"US",
    "sg:address":"1117 E 105th St",
    "sg:city":"Cleveland",
    "sg:classifiers":[
        {
            "category":"Organizations",
            "subcategory":"Religious Organization",
            "type":"Services"
        }
    ],
    "sg:phone":"+1 216 249 5829",
    "sg:postcode":"44108",
    "sg:province":"OH",
    "sg:tags":[
        "church"
    ],
    "wof:name":"Parents & Children Together",
    "wof:placetype":"venue"
},
  "geometry": {"coordinates":[-81.615538,41.527812],"type":"Point"}
}