{
  "type": "Feature",
  "properties": {
    "addr:full":"3568 Columbia Pkwy Cincinnati OH 45226",
    "addr:housenumber":"3568",
    "addr:postcode":"45226",
    "addr:street":"Columbia Pkwy",
    "iso:country":"US",
    "sg:address":"3568 Columbia Pkwy",
    "sg:city":"Cincinnati",
    "sg:classifiers":[
        {
            "category":"Coffee & Tea",
            "type":"Food & Drink"
        }
    ],
    "sg:menulink":"http://www.allmenus.com/oh/cincinnati/124756-starbucks-coffee/menu/",
    "sg:phone":"+1 513 533 4127",
    "sg:postcode":"45226",
    "sg:province":"OH",
    "sg:tags":[
        "american"
    ],
    "wof:name":"Starbucks Coffee",
    "wof:placetype":"venue"
},
  "geometry": {"coordinates":[-84.43647300000001,39.11571],"type":"Point"}
}