{
  "type": "Feature",
  "properties": {
    "iso:country":"US",
    "sg:address":"1171 E State St",
    "sg:city":"Salem",
    "sg:classifiers":[
        {
            "category":"Real Estate",
            "subcategory":"Real Estate Operator",
            "type":"Services"
        }
    ],
    "sg:phone":"+1 330 337 3697",
    "sg:postcode":"44460",
    "sg:province":"OH",
    "sg:tags":[
        "building",
        "apartment"
    ],
    "wof:name":"Century House Of Salem",
    "wof:placetype":"venue"
},
  "geometry": {"coordinates":[-80.844623,40.900862],"type":"Point"}
}