{
  "type": "Feature",
  "properties": {
    "addr:full":"404 W High St Mt Vernon OH 43050",
    "addr:housenumber":"404",
    "addr:postcode":"43050",
    "addr:street":"W High St",
    "iso:country":"US",
    "sg:address":"404 W High St",
    "sg:city":"Mt Vernon",
    "sg:classifiers":[
        {
            "category":"Personal",
            "subcategory":"Barber",
            "type":"Services"
        }
    ],
    "sg:phone":"+1 740 392 5871",
    "sg:postcode":"43050",
    "sg:province":"OH",
    "wof:name":"Jerry's Barber Shop",
    "wof:placetype":"venue"
},
  "geometry": {"coordinates":[-82.490937,40.393811],"type":"Point"}
}