{
  "type": "Feature",
  "properties": {
    "iso:country":"US",
    "sg:address":"1669 W 130th St",
    "sg:city":"Hinckley",
    "sg:classifiers":[
        {
            "category":"Professional",
            "type":"Services"
        },
        {
            "category":"Building & Trades",
            "subcategory":"Construction",
            "type":"Services"
        }
    ],
    "sg:phone":"+1 330 220 6511",
    "sg:postcode":"44233",
    "sg:province":"OH",
    "sg:tags":[
        "control",
        "establishment",
        "erosion"
    ],
    "wof:name":"Specialized Grouting Systems",
    "wof:placetype":"venue"
},
  "geometry": {"coordinates":[-81.784878,41.227261],"type":"Point"}
}