{
  "type": "Feature",
  "properties": {
    "iso:country":"US",
    "sg:address":"651 W Indianola Ave",
    "sg:city":"Youngstown",
    "sg:classifiers":[
        {
            "category":"Retail",
            "subcategory":"Auto Repair",
            "type":"Services"
        }
    ],
    "sg:phone":"+1 330 788 2447",
    "sg:postcode":"44511",
    "sg:province":"OH",
    "sg:tags":[
        "repairing",
        "automobile"
    ],
    "wof:name":"Poor Man's Auto Repair",
    "wof:placetype":"venue"
},
  "geometry": {"coordinates":[-80.674903,41.071913],"type":"Point"}
}