{
  "type": "Feature",
  "properties": {
    "iso:country":"US",
    "sg:address":"4382 Indian Ripple Rd",
    "sg:city":"Dayton",
    "sg:classifiers":[
        {
            "category":"Restaurant",
            "type":"Food & Drink"
        }
    ],
    "sg:menulink":"http://www.allmenus.com/oh/beavercreek/141807-waffle-house/menu/",
    "sg:phone":"+1 937 320 1231",
    "sg:postcode":"45440",
    "sg:province":"OH",
    "sg:tags":[
        "american"
    ],
    "wof:name":"Waffle House",
    "wof:placetype":"venue"
},
  "geometry": {"coordinates":[-84.101907,39.696294],"type":"Point"}
}