{
  "type": "Feature",
  "properties": {
    "addr:full": "4515 Brookpark Rd Cleveland OH 44134",
    "addr:housenumber": "4515",
    "addr:postcode": "44134",
    "addr:street": "Brookpark Rd",
    "iso:country": "US",
    "sg:address": "4515 Brookpark Rd",
    "sg:city": "Cleveland",
    "sg:classifiers": [
      {
        "category": "Professional",
        "type": "Services"
      }
    ],
    "sg:phone": "+1 216 741 0470",
    "sg:postcode": "44134",
    "sg:province": "OH",
    "wof:name": "U S Protective Svc",
    "wof:placetype": "venue"
  },
  "geometry": {"coordinates":[-81.71724,41.418713],"type":"Point"}
}
