{
  "type": "Feature",
  "properties": {
    "addr:full": "17060 Purdum Rd Logan OH 43138",
    "addr:postcode": "17060;43138",
    "addr:street": "Purdum Rd",
    "iso:country": "US",
    "sg:address": "17060 Purdum Rd",
    "sg:city": "Logan",
    "sg:classifiers": [
      {
        "category": "Building \u0026 Trades",
        "subcategory": "Construction",
        "type": "Services"
      }
    ],
    "sg:phone": "+1 740 380 6565",
    "sg:postcode": "43138",
    "sg:province": "OH",
    "sg:tags": [
      "concrete",
      "contractor"
    ],
    "wof:name": "Affordable Concrete Pumping",
    "wof:placetype": "venue"
  },
  "geometry": {"coordinates":[-82.32215,39.485852],"type":"Point"}
}
