{
  "type": "Feature",
  "properties": {
    "iso:country":"US",
    "sg:address":"17060 Purdum Rd",
    "sg:city":"Logan",
    "sg:classifiers":[
        {
            "category":"Building & Trades",
            "subcategory":"Construction",
            "type":"Services"
        }
    ],
    "sg:phone":"+1 740 380 6565",
    "sg:postcode":"43138",
    "sg:province":"OH",
    "sg:tags":[
        "concrete",
        "contractor"
    ],
    "wof:name":"Affordable Concrete Pumping",
    "wof:placetype":"venue"
},
  "geometry": {"coordinates":[-82.32214999999999,39.485852],"type":"Point"}
}