{
  "type": "Feature",
  "properties": {
    "iso:country":"US",
    "sg:address":"509 Woodview Dr",
    "sg:city":"Chillicothe",
    "sg:classifiers":[
        {
            "category":"Shopping",
            "subcategory":"Clothing, Apparel, & Fashions",
            "type":"Retail Goods"
        }
    ],
    "sg:phone":"+1 740 649 1818",
    "sg:postcode":"45601",
    "sg:province":"OH",
    "sg:tags":[
        "alteration"
    ],
    "wof:name":"Sewing By Beth",
    "wof:placetype":"venue"
},
  "geometry": {"coordinates":[-83.012398,39.436559],"type":"Point"}
}