{
  "type": "Feature",
  "properties": {
    "addr:full": "509 Woodview Dr Chillicothe OH 45601",
    "addr:housenumber": "509",
    "addr:postcode": "45601",
    "addr:street": "Woodview Dr",
    "iso:country": "US",
    "sg:address": "509 Woodview Dr",
    "sg:city": "Chillicothe",
    "sg:classifiers": [
      {
        "category": "Shopping",
        "subcategory": "Clothing, Apparel, \u0026 Fashions",
        "type": "Retail Goods"
      }
    ],
    "sg:phone": "+1 740 649 1818",
    "sg:postcode": "45601",
    "sg:province": "OH",
    "sg:tags": [
      "alteration"
    ],
    "wof:name": "Sewing By Beth",
    "wof:placetype": "venue"
  },
  "geometry": {"coordinates":[-83.012398,39.436559],"type":"Point"}
}
