{
  "type": "Feature",
  "properties": {
    "addr:full": "6263 Sweet Briar Ct Loveland OH 45140",
    "addr:housenumber": "6263",
    "addr:postcode": "45140",
    "addr:street": "Sweet Briar Ct",
    "iso:country": "US",
    "sg:address": "6263 Sweet Briar Ct",
    "sg:city": "Loveland",
    "sg:classifiers": [
      {
        "category": "Manufacturing",
        "subcategory": "Printing",
        "type": "Manufacturing \u0026 Wholesale Goods"
      }
    ],
    "sg:phone": "+1 513 683 5162",
    "sg:postcode": "45140",
    "sg:province": "OH",
    "sg:tags": [
      "newspaper"
    ],
    "wof:name": "Soundings Trade Only",
    "wof:placetype": "venue"
  },
  "geometry": {"coordinates":[-84.260488,39.220645],"type":"Point"}
}
