{
  "type": "Feature",
  "properties": {
    "addr:full":"3260 Westbourne Dr Cincinnati OH 45248",
    "addr:housenumber":"3260",
    "addr:postcode":"45248",
    "addr:street":"Westbourne Dr",
    "iso:country":"US",
    "sg:address":"3260 Westbourne Dr",
    "sg:city":"Cincinnati",
    "sg:classifiers":[
        {
            "category":"Real Estate",
            "subcategory":"Real Estate Agent",
            "type":"Services"
        }
    ],
    "sg:phone":"+1 513 922 9400",
    "sg:postcode":"45248",
    "sg:province":"OH",
    "wof:name":"Coldwell Banker",
    "wof:placetype":"venue"
},
  "geometry": {"coordinates":[-84.62880699999999,39.14709],"type":"Point"}
}