{
  "type": "Feature",
  "properties": {
    "addr:full":"3623 Sanctuary Dr Akron OH 44333",
    "addr:housenumber":"3623",
    "addr:postcode":"44333",
    "addr:street":"Sanctuary Dr",
    "iso:country":"US",
    "sg:address":"3623 Sanctuary Dr",
    "sg:city":"Akron",
    "sg:classifiers":[
        {
            "category":"Professional",
            "subcategory":"Management & Consulting",
            "type":"Services"
        }
    ],
    "sg:phone":"+1 330 668 3835",
    "sg:postcode":"44333",
    "sg:province":"OH",
    "sg:tags":[
        "consultant",
        "business"
    ],
    "wof:name":"K B Kleckner Consulting",
    "wof:placetype":"venue"
},
  "geometry": {"coordinates":[-81.639822,41.154107],"type":"Point"}
}