{
  "type": "Feature",
  "properties": {
    "addr:full": "944 Main St Huron OH 44839",
    "addr:housenumber": "944",
    "addr:postcode": "44839",
    "addr:street": "Main St",
    "iso:country": "US",
    "sg:address": "944 Main St",
    "sg:city": "Huron",
    "sg:classifiers": [
      {
        "category": "Professional",
        "subcategory": "Business Services",
        "type": "Services"
      }
    ],
    "sg:phone": "+1 419 433 2140",
    "sg:postcode": "44839",
    "sg:province": "OH",
    "sg:tags": [
      "painter",
      "sign"
    ],
    "sg:website": "www.holidayharbor.com",
    "wof:name": "Holiday Harbor Marina Inc",
    "wof:placetype": "venue"
  },
  "geometry": {"coordinates":[-82.562571,41.386919],"type":"Point"}
}
