{
  "type": "Feature",
  "properties": {
    "iso:country":"US",
    "sg:address":"944 Main St",
    "sg:city":"Huron",
    "sg:classifiers":[
        {
            "category":"Professional",
            "subcategory":"Business Services",
            "type":"Services"
        }
    ],
    "sg:phone":"+1 419 433 2140",
    "sg:postcode":"44839",
    "sg:province":"OH",
    "sg:tags":[
        "painter",
        "sign"
    ],
    "sg:website":"www.holidayharbor.com",
    "wof:name":"Holiday Harbor Marina Inc",
    "wof:placetype":"venue"
},
  "geometry": {"coordinates":[-82.56257100000001,41.386919],"type":"Point"}
}