{
  "type": "Feature",
  "properties": {
    "addr:full": "28707 Center Ridge Rd Cleveland OH 44145",
    "addr:housenumber": "28707",
    "addr:postcode": "44145",
    "addr:street": "Center Ridge Rd",
    "iso:country": "US",
    "sg:address": "28707 Center Ridge Rd",
    "sg:city": "Cleveland",
    "sg:classifiers": [
      {
        "category": "Personal",
        "subcategory": "Beauty Salon",
        "type": "Services"
      }
    ],
    "sg:phone": "+1 440 892 0019",
    "sg:postcode": "44145",
    "sg:province": "OH",
    "sg:tags": [
      "manicuring"
    ],
    "wof:name": "Hair By Devereaux",
    "wof:placetype": "venue"
  },
  "geometry": {"coordinates":[-81.94023,41.436421],"type":"Point"}
}
