{
  "type": "Feature",
  "properties": {
    "addr:full": "3115 Parsons Ave Columbus OH 43207",
    "addr:housenumber": "3115",
    "addr:postcode": "43207",
    "addr:street": "Parsons Ave",
    "iso:country": "US",
    "sg:address": "3115 Parsons Ave",
    "sg:city": "Columbus",
    "sg:classifiers": [
      {
        "category": "Shopping",
        "subcategory": "Discount \u0026 Variety Stores",
        "type": "Retail Goods"
      }
    ],
    "sg:phone": "+1 614 497 2550",
    "sg:postcode": "43207",
    "sg:province": "OH",
    "sg:tags": [
      "merchandise",
      "general"
    ],
    "wof:name": "Chapter 752",
    "wof:placetype": "venue"
  },
  "geometry": {"coordinates":[-82.986457,39.899124],"type":"Point"}
}
