{
  "type": "Feature",
  "properties": {
    "addr:full": "2177 Hunters Ridge Blvd Dayton OH 45434",
    "addr:housenumber": "2177",
    "addr:postcode": "45434",
    "addr:street": "Hunters Ridge Blvd",
    "iso:country": "US",
    "sg:address": "2177 Hunters Ridge Blvd",
    "sg:city": "Dayton",
    "sg:classifiers": [
      {
        "category": "Professional",
        "subcategory": "Management \u0026 Consulting",
        "type": "Services"
      }
    ],
    "sg:phone": "+1 937 427 1717",
    "sg:postcode": "45434",
    "sg:province": "OH",
    "sg:tags": [
      "training",
      "sales"
    ],
    "wof:name": "Sales Professional Training",
    "wof:placetype": "venue"
  },
  "geometry": {"coordinates":[-84.015547,39.721283],"type":"Point"}
}
