{
  "type": "Feature",
  "properties": {
    "addr:full": "839 W Central Ave Springboro OH 45066",
    "addr:housenumber": "839",
    "addr:postcode": "45066",
    "addr:street": "W Central Ave",
    "iso:country": "US",
    "sg:address": "839 W Central Ave",
    "sg:city": "Springboro",
    "sg:classifiers": [
      {
        "category": "Personal",
        "subcategory": "Beauty Salon",
        "type": "Services"
      }
    ],
    "sg:phone": "+1 937 743 9334",
    "sg:postcode": "45066",
    "sg:province": "OH",
    "wof:name": "Fiesta Hair \u0026 Tanning",
    "wof:placetype": "venue"
  },
  "geometry": {"coordinates":[-84.251199,39.561412],"type":"Point"}
}
