{
  "type": "Feature",
  "properties": {
    "iso:country":"US",
    "sg:address":"839 W Central Ave",
    "sg:city":"Springboro",
    "sg:classifiers":[
        {
            "category":"Personal",
            "subcategory":"Beauty Salon",
            "type":"Services"
        }
    ],
    "sg:phone":"+1 937 743 9334",
    "sg:postcode":"45066",
    "sg:province":"OH",
    "wof:name":"Fiesta Hair & Tanning",
    "wof:placetype":"venue"
},
  "geometry": {"coordinates":[-84.251199,39.561412],"type":"Point"}
}