{
  "type": "Feature",
  "properties": {
    "addr:full":"4170 Bowmansroot Ct Hilliard OH 43026",
    "addr:housenumber":"4170",
    "addr:postcode":"43026",
    "addr:street":"Bowmansroot Ct",
    "iso:country":"US",
    "sg:address":"4170 Bowmansroot Ct",
    "sg:city":"Hilliard",
    "sg:classifiers":[
        {
            "category":"Professional",
            "type":"Services"
        }
    ],
    "sg:phone":"+1 614 876 6374",
    "sg:postcode":"43026",
    "sg:province":"OH",
    "sg:tags":[
        "establishment"
    ],
    "wof:name":"T Leland Seeger & Assoc Inc",
    "wof:placetype":"venue"
},
  "geometry": {"coordinates":[-83.108152,40.039793],"type":"Point"}
}