{
  "type": "Feature",
  "properties": {
    "addr:full": "6620 Wooster Pike Cincinnati OH 45227",
    "addr:postcode": "6620;45227",
    "addr:street": "Wooster Pike",
    "iso:country": "US",
    "sg:address": "6620 Wooster Pike",
    "sg:city": "Cincinnati",
    "sg:classifiers": [
      {
        "category": "Manufacturing",
        "subcategory": "Rubber \u0026 Plastics",
        "type": "Manufacturing \u0026 Wholesale Goods"
      },
      {
        "category": "Autos \u0026 Motor Vehicles",
        "subcategory": "Auto Supplies",
        "type": "Retail Goods"
      },
      {
        "category": "Retail",
        "subcategory": "Auto Repair",
        "type": "Services"
      }
    ],
    "sg:phone": "+1 513 624 2641",
    "sg:postcode": "45227",
    "sg:province": "OH",
    "sg:tags": [
      "recap",
      "retread",
      "tires-wholesale",
      "tire",
      "manufacturer"
    ],
    "sg:website": "http://www.coopertire.com/html/",
    "wof:name": "Ulmer's Auto Care",
    "wof:placetype": "venue"
  },
  "geometry": {"coordinates":[-84.382616,39.145032],"type":"Point"}
}
