{
  "type": "Feature",
  "properties": {
    "addr:full": "562 S Reynolds Rd Toledo OH 43615",
    "addr:housenumber": "562",
    "addr:postcode": "43615",
    "addr:street": "S Reynolds Rd",
    "iso:country": "US",
    "sg:address": "562 S Reynolds Rd",
    "sg:city": "Toledo",
    "sg:classifiers": [
      {
        "category": "Wholesale",
        "subcategory": "Construction Materials",
        "type": "Manufacturing \u0026 Wholesale Goods"
      }
    ],
    "sg:phone": "+1 419 535 1100",
    "sg:postcode": "43615",
    "sg:province": "OH",
    "sg:website": "www.sidingworld.com",
    "wof:name": "Siding World",
    "wof:placetype": "venue"
  },
  "geometry": {"coordinates":[-83.664582,41.629452],"type":"Point"}
}
