{
  "type": "Feature",
  "properties": {
    "addr:full":"2731 Surf Ave Lorain OH 44053",
    "addr:housenumber":"2731",
    "addr:postcode":"44053",
    "addr:street":"Surf Ave",
    "iso:country":"US",
    "sg:address":"2731 Surf Ave",
    "sg:city":"Lorain",
    "sg:classifiers":[
        {
            "category":"Professional",
            "type":"Services"
        }
    ],
    "sg:phone":"+1 440 989 5864",
    "sg:postcode":"44053",
    "sg:province":"OH",
    "wof:name":"World Overcomers Outreach Inc",
    "wof:placetype":"venue"
},
  "geometry": {"coordinates":[-82.22409399999999,41.445884],"type":"Point"}
}