{
  "type": "Feature",
  "properties": {
    "iso:country":"US",
    "sg:address":"8246 Shiloh-Norwalk Rd",
    "sg:city":"Shiloh",
    "sg:phone":"+1 419 896 2630",
    "sg:postcode":"44878",
    "sg:province":"OH",
    "sg:tags":[
        "farm",
        "grain",
        "cash"
    ],
    "wof:name":"Kranz Farms",
    "wof:placetype":"venue"
},
  "geometry": {"coordinates":[-82.605414,40.985121],"type":"Point"}
}