{
  "type": "Feature",
  "properties": {
    "addr:full":"41 S 1st St Miamisburg OH 45342",
    "addr:housenumber":"41",
    "addr:postcode":"45342",
    "addr:street":"S 1St St",
    "iso:country":"US",
    "sg:address":"41 S 1st St",
    "sg:city":"Miamisburg",
    "sg:classifiers":[
        {
            "category":"Banks & Credit Unions",
            "subcategory":"Financial Services",
            "type":"Services"
        }
    ],
    "sg:phone":"+1 937 866 2455",
    "sg:postcode":"45342",
    "sg:province":"OH",
    "sg:tags":[
        "company",
        "holding"
    ],
    "wof:name":"F & M Bancorp",
    "wof:placetype":"venue"
},
  "geometry": {"coordinates":[-84.28824400000001,39.640654],"type":"Point"}
}