{
  "type": "Feature",
  "properties": {
    "addr:full": "41 S 1st St Miamisburg OH 45342",
    "addr:housenumber": "41",
    "addr:postcode": "45342",
    "addr:street": "S 1St St",
    "iso:country": "US",
    "sg:address": "41 S 1st St",
    "sg:city": "Miamisburg",
    "sg:classifiers": [
      {
        "category": "Banks \u0026 Credit Unions",
        "subcategory": "Financial Services",
        "type": "Services"
      }
    ],
    "sg:phone": "+1 937 866 2455",
    "sg:postcode": "45342",
    "sg:province": "OH",
    "sg:tags": [
      "company",
      "holding"
    ],
    "wof:name": "F \u0026 M Bancorp",
    "wof:placetype": "venue"
  },
  "geometry": {"coordinates":[-84.288244,39.640654],"type":"Point"}
}
