{
  "type": "Feature",
  "properties": {
    "addr:full":"720 N Main St Akron OH 44310",
    "addr:housenumber":"720",
    "addr:postcode":"44310",
    "addr:street":"N Main St",
    "iso:country":"US",
    "sg:address":"720 N Main St",
    "sg:city":"Akron",
    "sg:classifiers":[
        {
            "category":"Banks & Credit Unions",
            "subcategory":"Investment Brokerage",
            "type":"Services"
        }
    ],
    "sg:phone":"+1 330 762 8540",
    "sg:postcode":"44310",
    "sg:province":"OH",
    "sg:tags":[
        "advisory"
    ],
    "wof:name":"SSS Investment",
    "wof:placetype":"venue"
},
  "geometry": {"coordinates":[-81.51090499999999,41.102154],"type":"Point"}
}