{
  "type": "Feature",
  "properties": {
    "addr:full": "4615 Carlynn Dr Cincinnati OH 45241",
    "addr:housenumber": "4615",
    "addr:postcode": "45241",
    "addr:street": "Carlynn Dr",
    "iso:country": "US",
    "sg:address": "4615 Carlynn Dr",
    "sg:city": "Cincinnati",
    "sg:classifiers": [
      {
        "category": "Wholesale",
        "subcategory": "Home Furnishings",
        "type": "Manufacturing \u0026 Wholesale Goods"
      }
    ],
    "sg:phone": "+1 513 489 6822",
    "sg:postcode": "45241",
    "sg:province": "OH",
    "wof:name": "Skandia Industries",
    "wof:placetype": "venue"
  },
  "geometry": {"coordinates":[-84.377297,39.274556],"type":"Point"}
}
