{
  "type": "Feature",
  "properties": {
    "addr:full":"2500 Commerce Blvd Cincinnati OH 45241",
    "addr:housenumber":"2500",
    "addr:postcode":"45241",
    "addr:street":"Commerce Blvd",
    "iso:country":"US",
    "sg:address":"2500 Commerce Blvd",
    "sg:city":"Cincinnati",
    "sg:classifiers":[
        {
            "category":"Freight",
            "type":"Transportation"
        }
    ],
    "sg:phone":"+1 513 772 4781",
    "sg:postcode":"45241",
    "sg:province":"OH",
    "sg:tags":[
        "trucking"
    ],
    "sg:website":"www.alvanmotor.com",
    "wof:name":"Alvan Motor Freight Inc",
    "wof:placetype":"venue"
},
  "geometry": {"coordinates":[-84.425021,39.28989],"type":"Point"}
}