{
  "type": "Feature",
  "properties": {
    "iso:country":"US",
    "sg:address":"315 S Detroit St",
    "sg:city":"Bellefontaine",
    "sg:classifiers":[
        {
            "category":"Utilities",
            "type":"Services"
        }
    ],
    "sg:phone":"+1 937 592 2217",
    "sg:postcode":"43311",
    "sg:province":"OH",
    "sg:tags":[
        "sanitary"
    ],
    "wof:name":"Nicholl Snowplowing",
    "wof:placetype":"venue"
},
  "geometry": {"coordinates":[-83.761974,40.357866],"type":"Point"}
}