{
  "type": "Feature",
  "properties": {
    "addr:full": "1304 Sunrise Dr Loveland OH 45140",
    "addr:housenumber": "1304",
    "addr:postcode": "45140",
    "addr:street": "Sunrise Dr",
    "iso:country": "US",
    "sg:address": "1304 Sunrise Dr",
    "sg:city": "Loveland",
    "sg:classifiers": [
      {
        "category": "Building \u0026 Trades",
        "subcategory": "Construction",
        "type": "Services"
      }
    ],
    "sg:phone": "+1 513 677 3032",
    "sg:postcode": "45140",
    "sg:province": "OH",
    "sg:tags": [
      "hanging",
      "contractor"
    ],
    "wof:name": "Jenkins Painting",
    "wof:placetype": "venue"
  },
  "geometry": {"coordinates":[-84.273705,39.266988],"type":"Point"}
}
