{
  "type": "Feature",
  "properties": {
    "iso:country":"US",
    "sg:address":"1304 Sunrise Dr",
    "sg:city":"Loveland",
    "sg:classifiers":[
        {
            "category":"Building & Trades",
            "subcategory":"Construction",
            "type":"Services"
        }
    ],
    "sg:phone":"+1 513 677 3032",
    "sg:postcode":"45140",
    "sg:province":"OH",
    "sg:tags":[
        "hanging",
        "contractor"
    ],
    "wof:name":"Jenkins Painting",
    "wof:placetype":"venue"
},
  "geometry": {"coordinates":[-84.27370500000001,39.266988],"type":"Point"}
}