{
  "type": "Feature",
  "properties": {
    "addr:full": "1223 E Central Ave Miamisburg OH 45342",
    "addr:housenumber": "1223",
    "addr:postcode": "45342",
    "addr:street": "E Central Ave",
    "iso:country": "US",
    "sg:address": "1223 E Central Ave",
    "sg:city": "Miamisburg",
    "sg:classifiers": [
      {
        "category": "Health Services",
        "subcategory": "Doctor",
        "type": "Services"
      }
    ],
    "sg:phone": "+1 937 866 2501",
    "sg:postcode": "45342",
    "sg:province": "OH",
    "wof:name": "Brad A Vosler",
    "wof:placetype": "venue"
  },
  "geometry": {"coordinates":[-84.269939,39.640829],"type":"Point"}
}
