{
  "type": "Feature",
  "properties": {
    "iso:country":"US",
    "sg:address":"1223 E Central Ave",
    "sg:city":"Miamisburg",
    "sg:classifiers":[
        {
            "category":"Health Services",
            "subcategory":"Doctor",
            "type":"Services"
        }
    ],
    "sg:phone":"+1 937 866 2501",
    "sg:postcode":"45342",
    "sg:province":"OH",
    "wof:name":"Brad A Vosler",
    "wof:placetype":"venue"
},
  "geometry": {"coordinates":[-84.26993899999999,39.640829],"type":"Point"}
}