{
  "type": "Feature",
  "properties": {
    "iso:country":"US",
    "sg:address":"14008 Rochelle Dr",
    "sg:city":"Cleveland",
    "sg:classifiers":[
        {
            "category":"Social Services",
            "subcategory":"Adult Care",
            "type":"Services"
        }
    ],
    "sg:phone":"+1 216 581 6362",
    "sg:postcode":"44137",
    "sg:province":"OH",
    "sg:tags":[
        "home",
        "group"
    ],
    "wof:name":"L'Arche Cleveland",
    "wof:placetype":"venue"
},
  "geometry": {"coordinates":[-81.57977700000001,41.397476],"type":"Point"}
}