{
  "type": "Feature",
  "properties": {
    "addr:full": "14008 Rochelle Dr Cleveland OH 44137",
    "addr:housenumber": "14008",
    "addr:postcode": "44137",
    "addr:street": "Rochelle Dr",
    "iso:country": "US",
    "sg:address": "14008 Rochelle Dr",
    "sg:city": "Cleveland",
    "sg:classifiers": [
      {
        "category": "Social Services",
        "subcategory": "Adult Care",
        "type": "Services"
      }
    ],
    "sg:phone": "+1 216 581 6362",
    "sg:postcode": "44137",
    "sg:province": "OH",
    "sg:tags": [
      "home",
      "group"
    ],
    "wof:name": "L'Arche Cleveland",
    "wof:placetype": "venue"
  },
  "geometry": {"coordinates":[-81.579777,41.397476],"type":"Point"}
}
