{
  "type": "Feature",
  "properties": {
    "addr:full": "12715 Roachton Rd Perrysburg OH 43551",
    "addr:housenumber": "12715",
    "addr:postcode": "43551",
    "addr:street": "Roachton Rd",
    "iso:country": "US",
    "sg:address": "12715 Roachton Rd",
    "sg:city": "Perrysburg",
    "sg:classifiers": [
      {
        "category": "Retail",
        "subcategory": "Auto Repair",
        "type": "Services"
      }
    ],
    "sg:phone": "+1 419 874 5889",
    "sg:postcode": "43551",
    "sg:province": "OH",
    "sg:tags": [
      "wrecker"
    ],
    "wof:name": "Shane's Towing \u0026 Recovery",
    "wof:placetype": "venue"
  },
  "geometry": {"coordinates":[-83.638899,41.521979],"type":"Point"}
}
