{
  "type": "Feature",
  "properties": {
    "iso:country":"US",
    "sg:address":"100 E Main St",
    "sg:city":"Mc Arthur",
    "sg:classifiers":[
        {
            "category":"Professional",
            "subcategory":"Engineering",
            "type":"Services"
        },
        {
            "category":"Government",
            "subcategory":"Office",
            "type":"Public Place"
        }
    ],
    "sg:phone":"+1 740 596 5144",
    "sg:postcode":"45651",
    "sg:province":"OH",
    "sg:tags":[
        "construction"
    ],
    "wof:name":"Vinton County Engineer's Ofc",
    "wof:placetype":"venue"
},
  "geometry": {"coordinates":[-82.478972,39.246641],"type":"Point"}
}