{
  "type": "Feature",
  "properties": {
    "addr:full":"914 Lincoln Ave Toledo OH 43607",
    "addr:housenumber":"914",
    "addr:postcode":"43607",
    "addr:street":"Lincoln Ave",
    "iso:country":"US",
    "sg:address":"914 Lincoln Ave",
    "sg:city":"Toledo",
    "sg:classifiers":[
        {
            "category":"Building & Trades",
            "subcategory":"Construction",
            "type":"Services"
        }
    ],
    "sg:phone":"+1 419 243 2890",
    "sg:postcode":"43607",
    "sg:province":"OH",
    "wof:name":"Synergy & Associates Dev LLC",
    "wof:placetype":"venue"
},
  "geometry": {"coordinates":[-83.56612199999999,41.657523],"type":"Point"}
}