{
  "type": "Feature",
  "properties": {
    "addr:full":"8126 W Chester Rd West Chester OH 45069",
    "addr:housenumber":"8126",
    "addr:postcode":"45069",
    "addr:street":"W Chester Rd",
    "iso:country":"US",
    "sg:address":"8126 W Chester Rd",
    "sg:city":"West Chester",
    "sg:classifiers":[
        {
            "category":"Restaurant",
            "type":"Food & Drink"
        }
    ],
    "sg:phone":"+1 513 860 0862",
    "sg:postcode":"45069",
    "sg:province":"OH",
    "sg:tags":[
        "eating"
    ],
    "wof:name":"Taco Bell",
    "wof:placetype":"venue"
},
  "geometry": {"coordinates":[-84.358602,39.317698],"type":"Point"}
}