{
  "type": "Feature",
  "properties": {
    "iso:country":"US",
    "sg:address":"2232 Circle Dr",
    "sg:city":"Cleveland",
    "sg:classifiers":[
        {
            "category":"Professional",
            "subcategory":"Advertising",
            "type":"Services"
        }
    ],
    "sg:phone":"+1 216 368 2564",
    "sg:postcode":"44106",
    "sg:province":"OH",
    "sg:tags":[
        "mail",
        "direct"
    ],
    "wof:name":"Shipping & Receiving Dept",
    "wof:placetype":"venue"
},
  "geometry": {"coordinates":[-81.60278099999999,41.505949],"type":"Point"}
}