{
  "type": "Feature",
  "properties": {
    "addr:full": "2232 Circle Dr Cleveland OH 44106",
    "addr:housenumber": "2232",
    "addr:postcode": "44106",
    "addr:street": "Circle Dr",
    "iso:country": "US",
    "sg:address": "2232 Circle Dr",
    "sg:city": "Cleveland",
    "sg:classifiers": [
      {
        "category": "Professional",
        "subcategory": "Advertising",
        "type": "Services"
      }
    ],
    "sg:phone": "+1 216 368 2564",
    "sg:postcode": "44106",
    "sg:province": "OH",
    "sg:tags": [
      "mail",
      "direct"
    ],
    "wof:name": "Shipping \u0026 Receiving Dept",
    "wof:placetype": "venue"
  },
  "geometry": {"coordinates":[-81.602781,41.505949],"type":"Point"}
}
