{
  "type": "Feature",
  "properties": {
    "addr:full":"835 High St Wadsworth OH 44281",
    "addr:housenumber":"835",
    "addr:postcode":"44281",
    "addr:street":"High St",
    "iso:country":"US",
    "sg:address":"835 High St",
    "sg:city":"Wadsworth",
    "sg:classifiers":[
        {
            "category":"Autos & Motor Vehicles",
            "subcategory":"Fuel & Gas Station",
            "type":"Retail Goods"
        }
    ],
    "sg:phone":"+1 330 336 3809",
    "sg:postcode":"44281",
    "sg:province":"OH",
    "sg:tags":[
        "oil"
    ],
    "wof:name":"Citgo",
    "wof:placetype":"venue"
},
  "geometry": {"coordinates":[-81.728739,41.045135],"type":"Point"}
}