{
  "type": "Feature",
  "properties": {
    "addr:full": "4771 Glendale Milford Rd Cincinnati OH 45242",
    "addr:housenumber": "4771",
    "addr:postcode": "45242",
    "addr:street": "Glendale Milford Rd",
    "iso:country": "US",
    "sg:address": "4771 Glendale Milford Rd",
    "sg:city": "Cincinnati",
    "sg:classifiers": [
      {
        "category": "Professional",
        "subcategory": "Detective \u0026 Security Services",
        "type": "Services"
      }
    ],
    "sg:phone": "+1 513 984 6447",
    "sg:postcode": "45242",
    "sg:province": "OH",
    "sg:tags": [
      "guard",
      "agency",
      "patrol"
    ],
    "wof:name": "Quest Associates Of Ohio LLC",
    "wof:placetype": "venue"
  },
  "geometry": {"coordinates":[-84.375575,39.250517],"type":"Point"}
}
