{
  "type": "Feature",
  "properties": {
    "iso:country":"US",
    "sg:address":"8250 Winton Rd",
    "sg:city":"Cincinnati",
    "sg:classifiers":[
        {
            "category":"Professional",
            "type":"Services"
        }
    ],
    "sg:phone":"+1 513 941 3721",
    "sg:postcode":"45231",
    "sg:province":"OH",
    "wof:name":"Restoration Services Co",
    "wof:placetype":"venue"
},
  "geometry": {"coordinates":[-84.518202,39.217041],"type":"Point"}
}