{
  "type": "Feature",
  "properties": {
    "addr:full": "9380 Amish Pike Plain City OH 43064",
    "addr:postcode": "9380;43064",
    "addr:street": "Amish Pike",
    "iso:country": "US",
    "sg:address": "9380 Amish Pike",
    "sg:city": "Plain City",
    "sg:classifiers": [
      {
        "category": "Organizations",
        "subcategory": "Religious Organization",
        "type": "Services"
      }
    ],
    "sg:phone": "+1 614 873 8301",
    "sg:postcode": "43064",
    "sg:province": "OH",
    "sg:tags": [
      "church"
    ],
    "wof:name": "Canaan Fellowship",
    "wof:placetype": "venue"
  },
  "geometry": {"coordinates":[-83.339505,40.076066],"type":"Point"}
}
