{
  "type": "Feature",
  "properties": {
    "iso:country":"US",
    "sg:address":"941 E Franklin St",
    "sg:city":"Dayton",
    "sg:classifiers":[
        {
            "category":"Shopping",
            "type":"Retail Goods"
        }
    ],
    "sg:phone":"+1 937 434 4499",
    "sg:postcode":"45459",
    "sg:province":"OH",
    "sg:tags":[
        "shop",
        "frame",
        "art",
        "gallery"
    ],
    "wof:name":"Houndstooth Gallery",
    "wof:placetype":"venue"
},
  "geometry": {"coordinates":[-84.140344,39.628546],"type":"Point"}
}