{
  "type": "Feature",
  "properties": {
    "addr:full": "1602 Wogaman Ave New Carlisle OH 45344",
    "addr:housenumber": "1602",
    "addr:postcode": "45344",
    "addr:street": "Wogaman Ave",
    "iso:country": "US",
    "sg:address": "1602 Wogaman Ave",
    "sg:city": "New Carlisle",
    "sg:classifiers": [
      {
        "category": "Shopping",
        "subcategory": "Jewelry",
        "type": "Retail Goods"
      }
    ],
    "sg:phone": "+1 937 849 0328",
    "sg:postcode": "45344",
    "sg:province": "OH",
    "wof:name": "L \u0026 L Jewelers",
    "wof:placetype": "venue"
  },
  "geometry": {"coordinates":[-84.042343,39.889129],"type":"Point"}
}
