{
  "type": "Feature",
  "properties": {
    "addr:full": "3991 Mogadore Rd Mogadore OH 44260",
    "addr:housenumber": "3991",
    "addr:postcode": "44260",
    "addr:street": "Mogadore Rd",
    "iso:country": "US",
    "sg:address": "3991 Mogadore Rd",
    "sg:city": "Mogadore",
    "sg:classifiers": [
      {
        "category": "Retail",
        "subcategory": "Auto Repair",
        "type": "Services"
      }
    ],
    "sg:phone": "+1 330 628 7233",
    "sg:postcode": "44260",
    "sg:province": "OH",
    "sg:tags": [
      "muffler",
      "exhaust",
      "system"
    ],
    "wof:name": "Safety Brake \u0026 Muffler",
    "wof:placetype": "venue"
  },
  "geometry": {"coordinates":[-81.398013,41.051156],"type":"Point"}
}
