{
  "type": "Feature",
  "properties": {
    "iso:country":"US",
    "sg:address":"1506 Foster Ave",
    "sg:city":"Toledo",
    "sg:classifiers":[
        {
            "category":"Retail",
            "subcategory":"Auto Repair",
            "type":"Services"
        }
    ],
    "sg:phone":"+1 419 243 6912",
    "sg:postcode":"43606",
    "sg:province":"OH",
    "sg:tags":[
        "body",
        "automobile",
        "painting"
    ],
    "wof:name":"Slim's Automotive Svc",
    "wof:placetype":"venue"
},
  "geometry": {"coordinates":[-83.576886,41.658287],"type":"Point"}
}