{
  "type": "Feature",
  "properties": {
    "addr:full": "126 Morton St Jackson OH 45640",
    "addr:housenumber": "126",
    "addr:postcode": "45640",
    "addr:street": "Morton St",
    "iso:country": "US",
    "sg:address": "126 Morton St",
    "sg:city": "Jackson",
    "sg:classifiers": [
      {
        "category": "Retail",
        "subcategory": "Car Wash",
        "type": "Services"
      }
    ],
    "sg:phone": "+1 740 286 4468",
    "sg:postcode": "45640",
    "sg:province": "OH",
    "sg:tags": [
      "automobile",
      "detail",
      "clean"
    ],
    "wof:name": "Jackson Custom Detailing",
    "wof:placetype": "venue"
  },
  "geometry": {"coordinates":[-82.636958,39.061972],"type":"Point"}
}
