{
  "type": "Feature",
  "properties": {
    "iso:country":"US",
    "sg:address":"5577 Nightingale Ct",
    "sg:city":"Cincinnati",
    "sg:classifiers":[
        {
            "category":"Building & Trades",
            "subcategory":"Construction",
            "type":"Services"
        }
    ],
    "sg:phone":"+1 513 272 3728",
    "sg:postcode":"45227",
    "sg:province":"OH",
    "sg:tags":[
        "hanging",
        "contractor"
    ],
    "wof:name":"A W L Custom Painting",
    "wof:placetype":"venue"
},
  "geometry": {"coordinates":[-84.397835,39.141964],"type":"Point"}
}