{
  "type": "Feature",
  "properties": {
    "iso:country":"US",
    "sg:address":"499 Portage Lakes Dr",
    "sg:city":"Akron",
    "sg:classifiers":[
        {
            "category":"Food & Beverages",
            "subcategory":"Specialty",
            "type":"Retail Goods"
        }
    ],
    "sg:phone":"+1 330 645 4372",
    "sg:postcode":"44319",
    "sg:province":"OH",
    "sg:tags":[
        "herb"
    ],
    "wof:name":"Healing Bridges",
    "wof:placetype":"venue"
},
  "geometry": {"coordinates":[-81.535615,40.995776],"type":"Point"}
}