{
  "type": "Feature",
  "properties": {
    "addr:full":"1305 Friendship Dr New Concord OH 43762",
    "addr:housenumber":"1305",
    "addr:postcode":"43762",
    "addr:street":"Friendship Dr",
    "iso:country":"US",
    "sg:address":"1305 Friendship Dr",
    "sg:city":"New Concord",
    "sg:classifiers":[
        {
            "category":"Social Services",
            "subcategory":"Adult Care",
            "type":"Services"
        }
    ],
    "sg:phone":"+1 740 826 2004",
    "sg:postcode":"43762",
    "sg:province":"OH",
    "sg:tags":[
        "home",
        "group"
    ],
    "wof:name":"RIA Inc",
    "wof:placetype":"venue"
},
  "geometry": {"coordinates":[-81.744421,40.006108],"type":"Point"}
}