{
  "type": "Feature",
  "properties": {
    "addr:full": "216 W Main St Loudonville OH 44842",
    "addr:housenumber": "216",
    "addr:postcode": "44842",
    "addr:street": "W Main St",
    "iso:country": "US",
    "sg:address": "216 W Main St",
    "sg:city": "Loudonville",
    "sg:classifiers": [
      {
        "category": "Shopping",
        "subcategory": "Clothing, Apparel, \u0026 Fashions",
        "type": "Retail Goods"
      }
    ],
    "sg:phone": "+1 419 994 5932",
    "sg:postcode": "44842",
    "sg:province": "OH",
    "wof:name": "Activewares",
    "wof:placetype": "venue"
  },
  "geometry": {"coordinates":[-82.235607,40.635797],"type":"Point"}
}
