{
  "type": "Feature",
  "properties": {
    "iso:country":"US",
    "sg:address":"7740 Olde Eight Rd",
    "sg:city":"Hudson",
    "sg:classifiers":[
        {
            "category":"Building & Trades",
            "subcategory":"Construction",
            "type":"Services"
        }
    ],
    "sg:phone":"+1 330 656 4346",
    "sg:postcode":"44236",
    "sg:province":"OH",
    "sg:tags":[
        "concrete",
        "contractor"
    ],
    "wof:name":"Concrete Dimensions Inc",
    "wof:placetype":"venue"
},
  "geometry": {"coordinates":[-81.513645,41.272236],"type":"Point"}
}