{
  "type": "Feature",
  "properties": {
    "iso:country":"US",
    "sg:address":"1716 Spielbusch Ave",
    "sg:city":"Toledo",
    "sg:classifiers":[
        {
            "category":"Professional",
            "subcategory":"Secretarial Services",
            "type":"Services"
        }
    ],
    "sg:phone":"+1 419 243 3607",
    "sg:postcode":"43604",
    "sg:province":"OH",
    "sg:tags":[
        "convention",
        "court",
        "reporter"
    ],
    "wof:name":"Tracy Spore",
    "wof:placetype":"venue"
},
  "geometry": {"coordinates":[-83.536199,41.658169],"type":"Point"}
}