{
  "type": "Feature",
  "properties": {
    "addr:full":"935 Main St Hamilton OH 45013",
    "addr:housenumber":"935",
    "addr:postcode":"45013",
    "addr:street":"Main St",
    "iso:country":"US",
    "sg:address":"935 Main St",
    "sg:city":"Hamilton",
    "sg:classifiers":[
        {
            "category":"Real Estate",
            "subcategory":"Real Estate Agent",
            "type":"Services"
        }
    ],
    "sg:phone":"+1 513 844 8405",
    "sg:postcode":"45013",
    "sg:province":"OH",
    "sg:tags":[
        "broker",
        "auctioneer"
    ],
    "sg:website":"www.bowling-kugler-repo.com",
    "wof:name":"Bowling & Kugler Realty",
    "wof:placetype":"venue"
},
  "geometry": {"coordinates":[-84.579075,39.411244],"type":"Point"}
}