{
  "type": "Feature",
  "properties": {
    "addr:full": "2781 Westbelt Dr Columbus OH 43228",
    "addr:housenumber": "2781",
    "addr:postcode": "43228",
    "addr:street": "Westbelt Dr",
    "iso:country": "US",
    "sg:address": "2781 Westbelt Dr",
    "sg:city": "Columbus",
    "sg:classifiers": [
      {
        "category": "Freight",
        "type": "Transportation"
      }
    ],
    "sg:phone": "+1 614 876 1011",
    "sg:postcode": "43228",
    "sg:province": "OH",
    "sg:tags": [
      "distribution",
      "center"
    ],
    "wof:name": "Exel Inc",
    "wof:placetype": "venue"
  },
  "geometry": {"coordinates":[-83.123091,40.003012],"type":"Point"}
}
