{
  "type": "Feature",
  "properties": {
    "addr:full": "347 Stanley Ave Cincinnati OH 45226",
    "addr:housenumber": "347",
    "addr:postcode": "45226",
    "addr:street": "Stanley Ave",
    "iso:country": "US",
    "sg:address": "347 Stanley Ave",
    "sg:city": "Cincinnati",
    "sg:classifiers": [
      {
        "category": "Restaurant",
        "type": "Food \u0026 Drink"
      }
    ],
    "sg:phone": "+1 513 321 3711",
    "sg:postcode": "45226",
    "sg:province": "OH",
    "wof:name": "Great Steak \u0026 Fry",
    "wof:placetype": "venue"
  },
  "geometry": {"coordinates":[-84.437,39.114969],"type":"Point"}
}
