{
  "type": "Feature",
  "properties": {
    "iso:country":"US",
    "sg:address":"347 Stanley Ave",
    "sg:city":"Cincinnati",
    "sg:classifiers":[
        {
            "category":"Restaurant",
            "type":"Food & Drink"
        }
    ],
    "sg:phone":"+1 513 321 3711",
    "sg:postcode":"45226",
    "sg:province":"OH",
    "wof:name":"Great Steak & Fry",
    "wof:placetype":"venue"
},
  "geometry": {"coordinates":[-84.437,39.114969],"type":"Point"}
}