{
  "type": "Feature",
  "properties": {
    "addr:full":"1340 Secrest Rd Wooster OH 44691",
    "addr:housenumber":"1340",
    "addr:postcode":"44691",
    "addr:street":"Secrest Rd",
    "iso:country":"US",
    "sg:address":"1340 Secrest Rd",
    "sg:city":"Wooster",
    "sg:classifiers":[
        {
            "category":"Building & Trades",
            "subcategory":"Construction",
            "type":"Services"
        }
    ],
    "sg:phone":"+1 330 264 6800",
    "sg:postcode":"44691",
    "sg:province":"OH",
    "sg:tags":[
        "house"
    ],
    "wof:name":"Nadeline Construction",
    "wof:placetype":"venue"
},
  "geometry": {"coordinates":[-81.93195900000001,40.78464],"type":"Point"}
}