{
  "type": "Feature",
  "properties": {
    "iso:country":"US",
    "sg:address":"2577 Centerville Rd",
    "sg:city":"Spring Valley",
    "sg:classifiers":[
        {
            "category":"Real Estate",
            "subcategory":"Real Estate Operator",
            "type":"Services"
        }
    ],
    "sg:phone":"+1 937 862 4256",
    "sg:postcode":"45370",
    "sg:province":"OH",
    "sg:tags":[
        "property",
        "lessor"
    ],
    "wof:name":"James Kyne Farm",
    "wof:placetype":"venue"
},
  "geometry": {"coordinates":[-84.036817,39.602405],"type":"Point"}
}