{
  "type": "Feature",
  "properties": {
    "addr:full": "13020 Oxford Rd Germantown OH 45327",
    "addr:housenumber": "13020",
    "addr:postcode": "45327",
    "addr:street": "Oxford Rd",
    "iso:country": "US",
    "sg:address": "13020 Oxford Rd",
    "sg:city": "Germantown",
    "sg:classifiers": [
      {
        "category": "Shopping",
        "subcategory": "Used Merchandise",
        "type": "Retail Goods"
      }
    ],
    "sg:phone": "+1 937 855 2070",
    "sg:postcode": "45327",
    "sg:province": "OH",
    "wof:name": "Hanes Antiques \u0026 Collectibles",
    "wof:placetype": "venue"
  },
  "geometry": {"coordinates":[-84.409275,39.615944],"type":"Point"}
}
