{
  "type": "Feature",
  "properties": {
    "addr:full": "5582 Penway Ct Cincinnati OH 45239",
    "addr:housenumber": "5582",
    "addr:postcode": "45239",
    "addr:street": "Penway Ct",
    "iso:country": "US",
    "sg:address": "5582 Penway Ct",
    "sg:city": "Cincinnati",
    "sg:classifiers": [
      {
        "category": "Professional",
        "subcategory": "Management \u0026 Consulting",
        "type": "Services"
      }
    ],
    "sg:phone": "+1 513 703 9349",
    "sg:postcode": "45239",
    "sg:province": "OH",
    "sg:tags": [
      "marketing",
      "program"
    ],
    "wof:name": "M G Carr \u0026 Assoc",
    "wof:placetype": "venue"
  },
  "geometry": {"coordinates":[-84.582008,39.193321],"type":"Point"}
}
