{
  "type": "Feature",
  "properties": {
    "iso:country":"US",
    "sg:address":"85 E Main St",
    "sg:city":"Berlin Heights",
    "sg:classifiers":[
        {
            "category":"Organizations",
            "subcategory":"Religious Organization",
            "type":"Services"
        }
    ],
    "sg:phone":"+1 419 588 2332",
    "sg:postcode":"44814",
    "sg:province":"OH",
    "sg:tags":[
        "church"
    ],
    "wof:name":"Berlin Heights Baptist Church",
    "wof:placetype":"venue"
},
  "geometry": {"coordinates":[-82.485491,41.325238],"type":"Point"}
}