{
  "type": "Feature",
  "properties": {
    "iso:country":"US",
    "sg:address":"197 8th St NW",
    "sg:city":"Barberton",
    "sg:classifiers":[
        {
            "category":"Building & Trades",
            "subcategory":"Construction",
            "type":"Services"
        }
    ],
    "sg:phone":"+1 330 861 0026",
    "sg:postcode":"44203",
    "sg:province":"OH",
    "sg:tags":[
        "nonresidential"
    ],
    "wof:name":"Benjamin Thompson",
    "wof:placetype":"venue"
},
  "geometry": {"coordinates":[-81.614661,41.015486],"type":"Point"}
}