{
  "type": "Feature",
  "properties": {
    "iso:country":"US",
    "sg:address":"11135 Montgomery Rd",
    "sg:city":"Cincinnati",
    "sg:classifiers":[
        {
            "category":"Building & Trades",
            "subcategory":"Construction",
            "type":"Services"
        }
    ],
    "sg:phone":"+1 513 489 4443",
    "sg:postcode":"45249",
    "sg:province":"OH",
    "sg:tags":[
        "home",
        "builder",
        "general",
        "contractor"
    ],
    "wof:name":"Garry Brasch Custom Homes",
    "wof:placetype":"venue"
},
  "geometry": {"coordinates":[-84.332723,39.266015],"type":"Point"}
}