{
  "type": "Feature",
  "properties": {
    "addr:full": "11135 Montgomery Rd Cincinnati OH 45249",
    "addr:housenumber": "11135",
    "addr:postcode": "45249",
    "addr:street": "Montgomery Rd",
    "iso:country": "US",
    "sg:address": "11135 Montgomery Rd",
    "sg:city": "Cincinnati",
    "sg:classifiers": [
      {
        "category": "Building \u0026 Trades",
        "subcategory": "Construction",
        "type": "Services"
      }
    ],
    "sg:phone": "+1 513 489 4443",
    "sg:postcode": "45249",
    "sg:province": "OH",
    "sg:tags": [
      "home",
      "builder",
      "general",
      "contractor"
    ],
    "wof:name": "Garry Brasch Custom Homes",
    "wof:placetype": "venue"
  },
  "geometry": {"coordinates":[-84.332723,39.266015],"type":"Point"}
}
