{
  "type": "Feature",
  "properties": {
    "addr:full": "7700 Reynolds Rd Mentor OH 44060",
    "addr:housenumber": "7700",
    "addr:postcode": "44060",
    "addr:street": "Reynolds Rd",
    "iso:country": "US",
    "sg:address": "7700 Reynolds Rd",
    "sg:city": "Mentor",
    "sg:classifiers": [
      {
        "category": "Restaurant",
        "type": "Food \u0026 Drink"
      }
    ],
    "sg:menulink": "http://www.allmenus.com/oh/mentor/195456-mcdonalds/menu/",
    "sg:postcode": "44060",
    "sg:province": "OH",
    "sg:tags": [
      "burger",
      "american"
    ],
    "wof:name": "McDonald's",
    "wof:placetype": "venue"
  },
  "geometry": {"coordinates":[-81.378445,41.661194],"type":"Point"}
}
