{
  "type": "Feature",
  "properties": {
    "addr:full":"5251 Glenway Ave Cincinnati OH 45238",
    "addr:housenumber":"5251",
    "addr:postcode":"45238",
    "addr:street":"Glenway Ave",
    "iso:country":"US",
    "sg:address":"5251 Glenway Ave",
    "sg:city":"Cincinnati",
    "sg:classifiers":[
        {
            "category":"Restaurant",
            "type":"Food & Drink"
        }
    ],
    "sg:menulink":"http://www.allmenus.com/oh/cincinnati/233013-lees-famous-recipe-chicken/menu/",
    "sg:phone":"+1 513 921 1386",
    "sg:postcode":"45238",
    "sg:province":"OH",
    "sg:tags":[
        "american"
    ],
    "wof:name":"Lee's Famous Recipe Chicken",
    "wof:placetype":"venue"
},
  "geometry": {"coordinates":[-84.603981,39.125021],"type":"Point"}
}