{
  "type": "Feature",
  "properties": {
    "iso:country":"US",
    "sg:address":"400 S Broad St",
    "sg:city":"Lancaster",
    "sg:classifiers":[
        {
            "category":"Professional",
            "subcategory":"Art Services",
            "type":"Services"
        }
    ],
    "sg:phone":"+1 740 653 4529",
    "sg:postcode":"43130",
    "sg:province":"OH",
    "sg:tags":[
        "graphic",
        "designer"
    ],
    "wof:name":"MAH Graphics",
    "wof:placetype":"venue"
},
  "geometry": {"coordinates":[-82.602096,39.710218],"type":"Point"}
}