{
  "type": "Feature",
  "properties": {
    "addr:full": "135 S Eureka Ave Columbus OH 43204",
    "addr:housenumber": "135",
    "addr:postcode": "43204",
    "addr:street": "S Eureka Ave",
    "iso:country": "US",
    "sg:address": "135 S Eureka Ave",
    "sg:city": "Columbus",
    "sg:classifiers": [
      {
        "category": "Health Services",
        "subcategory": "Medical Lab",
        "type": "Services"
      }
    ],
    "sg:phone": "+1 614 276 1164",
    "sg:postcode": "43204",
    "sg:province": "OH",
    "sg:tags": [
      "laboratory"
    ],
    "wof:name": "Nick Gerris Dental Lab Inc",
    "wof:placetype": "venue"
  },
  "geometry": {"coordinates":[-83.06527,39.951496],"type":"Point"}
}
