{
  "type": "Feature",
  "properties": {
    "addr:full": "201 S 1st St Oakwood OH 45873",
    "addr:housenumber": "201",
    "addr:postcode": "45873",
    "addr:street": "S 1St St",
    "iso:country": "US",
    "sg:address": "201 S 1st St",
    "sg:city": "Oakwood",
    "sg:classifiers": [
      {
        "category": "Shopping",
        "subcategory": "Clothing, Apparel, \u0026 Fashions",
        "type": "Retail Goods"
      }
    ],
    "sg:phone": "+1 419 594 3694",
    "sg:postcode": "45873",
    "sg:province": "OH",
    "sg:tags": [
      "item",
      "boutique"
    ],
    "wof:name": "Backyard Boutique",
    "wof:placetype": "venue"
  },
  "geometry": {"coordinates":[-84.378813,41.089141],"type":"Point"}
}
