{
  "type": "Feature",
  "properties": {
    "iso:country":"US",
    "sg:address":"201 S 1st St",
    "sg:city":"Oakwood",
    "sg:classifiers":[
        {
            "category":"Shopping",
            "subcategory":"Clothing, Apparel, & Fashions",
            "type":"Retail Goods"
        }
    ],
    "sg:phone":"+1 419 594 3694",
    "sg:postcode":"45873",
    "sg:province":"OH",
    "sg:tags":[
        "item",
        "boutique"
    ],
    "wof:name":"Backyard Boutique",
    "wof:placetype":"venue"
},
  "geometry": {"coordinates":[-84.37881299999999,41.089141],"type":"Point"}
}