{
  "type": "Feature",
  "properties": {
    "iso:country":"US",
    "sg:address":"8875 Chandlersville Rd",
    "sg:city":"Chandlersville",
    "sg:classifiers":[
        {
            "category":"Government",
            "subcategory":"Post Office",
            "type":"Public Place"
        }
    ],
    "sg:phone":"+1 740 674 6117",
    "sg:postcode":"43727",
    "sg:province":"OH",
    "wof:name":"US Post Office",
    "wof:placetype":"venue"
},
  "geometry": {"coordinates":[-81.82943899999999,39.898946],"type":"Point"}
}