{
  "type": "Feature",
  "properties": {
    "addr:full": "1532 Home Ave Akron OH 44310",
    "addr:housenumber": "1532",
    "addr:postcode": "44310",
    "addr:street": "Home Ave",
    "iso:country": "US",
    "sg:address": "1532 Home Ave",
    "sg:city": "Akron",
    "sg:classifiers": [
      {
        "category": "Food \u0026 Beverages",
        "subcategory": "Liquor \u0026 Beverages",
        "type": "Retail Goods"
      }
    ],
    "sg:phone": "+1 330 633 1330",
    "sg:postcode": "44310",
    "sg:province": "OH",
    "sg:tags": [
      "alcoholic"
    ],
    "wof:name": "Wine Barrel",
    "wof:placetype": "venue"
  },
  "geometry": {"coordinates":[-81.486212,41.112128],"type":"Point"}
}
