{
  "type": "Feature",
  "properties": {
    "iso:country":"US",
    "sg:address":"1532 Home Ave",
    "sg:city":"Akron",
    "sg:classifiers":[
        {
            "category":"Food & Beverages",
            "subcategory":"Liquor & Beverages",
            "type":"Retail Goods"
        }
    ],
    "sg:phone":"+1 330 633 1330",
    "sg:postcode":"44310",
    "sg:province":"OH",
    "sg:tags":[
        "alcoholic"
    ],
    "wof:name":"Wine Barrel",
    "wof:placetype":"venue"
},
  "geometry": {"coordinates":[-81.48621199999999,41.112128],"type":"Point"}
}