{
  "type": "Feature",
  "properties": {
    "addr:full": "4144 Erie St Willoughby OH 44094",
    "addr:housenumber": "4144",
    "addr:postcode": "44094",
    "addr:street": "Erie St",
    "iso:country": "US",
    "sg:address": "4144 Erie St",
    "sg:city": "Willoughby",
    "sg:classifiers": [
      {
        "category": "Shopping",
        "subcategory": "Gifts \u0026 Souvenirs",
        "type": "Retail Goods"
      }
    ],
    "sg:phone": "+1 440 942 9840",
    "sg:postcode": "44094",
    "sg:province": "OH",
    "sg:tags": [
      "shop"
    ],
    "wof:name": "China Treasure House",
    "wof:placetype": "venue"
  },
  "geometry": {"coordinates":[-81.406762,41.640111],"type":"Point"}
}
