{
  "type": "Feature",
  "properties": {
    "iso:country":"US",
    "sg:address":"1046 Gaynelle Ave",
    "sg:city":"Streetsboro",
    "sg:classifiers":[
        {
            "category":"Freight",
            "type":"Transportation"
        }
    ],
    "sg:phone":"+1 330 626 5977",
    "sg:postcode":"44241",
    "sg:province":"OH",
    "sg:tags":[
        "operator",
        "local",
        "trucking"
    ],
    "wof:name":"M J Haney Trucking Inc",
    "wof:placetype":"venue"
},
  "geometry": {"coordinates":[-81.349673,41.25905],"type":"Point"}
}