{
  "type": "Feature",
  "properties": {
    "addr:full":"33700 Vine St Willowick OH 44095",
    "addr:housenumber":"33700",
    "addr:postcode":"44095",
    "addr:street":"Vine St",
    "iso:country":"US",
    "sg:address":"33700 Vine St",
    "sg:city":"Willowick",
    "sg:classifiers":[
        {
            "category":"Banks & Credit Unions",
            "subcategory":"Bank",
            "type":"Services"
        }
    ],
    "sg:phone":"+1 440 953 0387",
    "sg:postcode":"44095",
    "sg:province":"OH",
    "wof:name":"Charter One Bank",
    "wof:placetype":"venue"
},
  "geometry": {"coordinates":[-81.446299,41.642523],"type":"Point"}
}