{
  "type": "Feature",
  "properties": {
    "addr:full":"1115 W Main St Louisville OH 44641",
    "addr:housenumber":"1115",
    "addr:postcode":"44641",
    "addr:street":"W Main St",
    "iso:country":"US",
    "sg:address":"1115 W Main St",
    "sg:city":"Louisville",
    "sg:classifiers":[
        {
            "category":"Building & Trades",
            "subcategory":"Electrical",
            "type":"Services"
        }
    ],
    "sg:phone":"+1 330 875 1651",
    "sg:postcode":"44641",
    "sg:province":"OH",
    "sg:tags":[
        "electrical",
        "electric",
        "contractor"
    ],
    "wof:name":"O D Miller Electric Co Inc",
    "wof:placetype":"venue"
},
  "geometry": {"coordinates":[-81.27199299999999,40.836351],"type":"Point"}
}