{
  "type": "Feature",
  "properties": {
    "addr:full":"5001 Monroe St Toledo OH 43606",
    "addr:housenumber":"5001",
    "addr:postcode":"43606",
    "addr:street":"Monroe St",
    "iso:country":"US",
    "sg:address":"5001 Monroe St",
    "sg:city":"Toledo",
    "sg:classifiers":[
        {
            "category":"Shopping",
            "subcategory":"Optical Goods",
            "type":"Retail Goods"
        }
    ],
    "sg:phone":"+1 419 472 8925",
    "sg:postcode":"43606",
    "sg:province":"OH",
    "sg:tags":[
        "sun",
        "goggles",
        "sunglasses"
    ],
    "wof:name":"Sun Vision",
    "wof:placetype":"venue"
},
  "geometry": {"coordinates":[-83.642016,41.697742],"type":"Point"}
}