{
  "type": "Feature",
  "properties": {
    "addr:full":"6615 Promway Ave NW Canton OH 44720",
    "addr:housenumber":"6615",
    "addr:postcode":"44720",
    "addr:street":"Promway Ave Nw",
    "iso:country":"US",
    "sg:address":"6615 Promway Ave NW",
    "sg:city":"Canton",
    "sg:classifiers":[
        {
            "category":"Wholesale",
            "subcategory":"Non-durable Goods",
            "type":"Manufacturing & Wholesale Goods"
        }
    ],
    "sg:phone":"+1 330 966 2070",
    "sg:postcode":"44720",
    "sg:province":"OH",
    "sg:tags":[
        "packaging",
        "material",
        "supplying"
    ],
    "wof:name":"Questar Inc",
    "wof:placetype":"venue"
},
  "geometry": {"coordinates":[-81.42832300000001,40.878778],"type":"Point"}
}