{
  "type": "Feature",
  "properties": {
    "addr:full": "6950 Bellefontaine Rd Dayton OH 45424",
    "addr:housenumber": "6950",
    "addr:postcode": "45424",
    "addr:street": "Bellefontaine Rd",
    "iso:country": "US",
    "sg:address": "6950 Bellefontaine Rd",
    "sg:city": "Dayton",
    "sg:classifiers": [
      {
        "category": "Restaurant",
        "type": "Food \u0026 Drink"
      }
    ],
    "sg:phone": "+1 419 648 9137",
    "sg:postcode": "45424",
    "sg:province": "OH",
    "wof:name": "Red Canary",
    "wof:placetype": "venue"
  },
  "geometry": {"coordinates":[-84.093947,39.852391],"type":"Point"}
}
