{
  "type": "Feature",
  "properties": {
    "addr:full":"23685 Colopy Rd Howard OH 43028",
    "addr:postcode":"23685;43028",
    "addr:street":"Colopy Rd",
    "iso:country":"US",
    "sg:address":"23685 Colopy Rd",
    "sg:city":"Howard",
    "sg:classifiers":[
        {
            "category":"Building & Trades",
            "subcategory":"Construction",
            "type":"Services"
        }
    ],
    "sg:phone":"+1 740 599 6765",
    "sg:postcode":"43028",
    "sg:province":"OH",
    "sg:tags":[
        "nonresidential"
    ],
    "wof:name":"Wert Construction",
    "wof:placetype":"venue"
},
  "geometry": {"coordinates":[-82.320375,40.439112],"type":"Point"}
}