{
  "type": "Feature",
  "properties": {
    "iso:country":"US",
    "sg:address":"670 Hardy Rd",
    "sg:city":"Painesville",
    "sg:classifiers":[
        {
            "category":"Manufacturing",
            "subcategory":"Paper Products",
            "type":"Manufacturing & Wholesale Goods"
        }
    ],
    "sg:phone":"+1 440 358 3408",
    "sg:postcode":"44077",
    "sg:province":"OH",
    "sg:tags":[
        "mfg",
        "unsupported",
        "film",
        "plastic"
    ],
    "wof:name":"Avery Dennison Corporation",
    "wof:placetype":"venue"
},
  "geometry": {"coordinates":[-81.23066300000001,41.755994],"type":"Point"}
}