{
  "type": "Feature",
  "properties": {
    "addr:full": "670 Hardy Rd Painesville OH 44077",
    "addr:housenumber": "670",
    "addr:postcode": "44077",
    "addr:street": "Hardy Rd",
    "iso:country": "US",
    "sg:address": "670 Hardy Rd",
    "sg:city": "Painesville",
    "sg:classifiers": [
      {
        "category": "Manufacturing",
        "subcategory": "Paper Products",
        "type": "Manufacturing \u0026 Wholesale Goods"
      }
    ],
    "sg:phone": "+1 440 358 3408",
    "sg:postcode": "44077",
    "sg:province": "OH",
    "sg:tags": [
      "mfg",
      "unsupported",
      "film",
      "plastic"
    ],
    "wof:name": "Avery Dennison Corporation",
    "wof:placetype": "venue"
  },
  "geometry": {"coordinates":[-81.230663,41.755994],"type":"Point"}
}
