{
  "type": "Feature",
  "properties": {
    "addr:full":"206 Maple St Marietta OH 45750",
    "addr:housenumber":"206",
    "addr:postcode":"45750",
    "addr:street":"Maple St",
    "iso:country":"US",
    "sg:address":"206 Maple St",
    "sg:city":"Marietta",
    "sg:classifiers":[
        {
            "category":"Shopping",
            "subcategory":"Computers & Home Electronics",
            "type":"Retail Goods"
        }
    ],
    "sg:phone":"+1 740 374 4020",
    "sg:postcode":"45750",
    "sg:province":"OH",
    "sg:tags":[
        "repair"
    ],
    "wof:name":"Days T V",
    "wof:placetype":"venue"
},
  "geometry": {"coordinates":[-81.461056,39.411389],"type":"Point"}
}