{
  "type": "Feature",
  "properties": {
    "addr:full":"10902 Almira Ave Cleveland OH 44111",
    "addr:housenumber":"10902",
    "addr:postcode":"44111",
    "addr:street":"Almira Ave",
    "iso:country":"US",
    "sg:address":"10902 Almira Ave",
    "sg:city":"Cleveland",
    "sg:classifiers":[
        {
            "category":"Freight",
            "type":"Transportation"
        }
    ],
    "sg:phone":"+1 216 251 0539",
    "sg:postcode":"44111",
    "sg:province":"OH",
    "sg:tags":[
        "operator",
        "local",
        "trucking"
    ],
    "wof:name":"Kilpatrick Hauling",
    "wof:placetype":"venue"
},
  "geometry": {"coordinates":[-81.760278,41.462277],"type":"Point"}
}