{
  "type": "Feature",
  "properties": {
    "addr:full": "806 Aeronca St Middletown OH 45042",
    "addr:housenumber": "806",
    "addr:postcode": "45042",
    "addr:street": "Aeronca St",
    "iso:country": "US",
    "sg:address": "806 Aeronca St",
    "sg:city": "Middletown",
    "sg:classifiers": [
      {
        "category": "Wholesale",
        "subcategory": "Hardware",
        "type": "Manufacturing \u0026 Wholesale Goods"
      }
    ],
    "sg:phone": "+1 513 424 1369",
    "sg:postcode": "45042",
    "sg:province": "OH",
    "sg:tags": [
      "purifying",
      "cleaning",
      "air"
    ],
    "wof:name": "Pure Air \u0026 Water",
    "wof:placetype": "venue"
  },
  "geometry": {"coordinates":[-84.375332,39.524227],"type":"Point"}
}
