{
  "type": "Feature",
  "properties": {
    "iso:country":"US",
    "sg:address":"806 Aeronca St",
    "sg:city":"Middletown",
    "sg:classifiers":[
        {
            "category":"Wholesale",
            "subcategory":"Hardware",
            "type":"Manufacturing & Wholesale Goods"
        }
    ],
    "sg:phone":"+1 513 424 1369",
    "sg:postcode":"45042",
    "sg:province":"OH",
    "sg:tags":[
        "purifying",
        "cleaning",
        "air"
    ],
    "wof:name":"Pure Air & Water",
    "wof:placetype":"venue"
},
  "geometry": {"coordinates":[-84.375332,39.524227],"type":"Point"}
}