{
  "type": "Feature",
  "properties": {
    "addr:full": "36460 Valley Vista Dr Willoughby OH 44095",
    "addr:housenumber": "36460",
    "addr:postcode": "44095",
    "addr:street": "Valley Vista Dr",
    "iso:country": "US",
    "sg:address": "36460 Valley Vista Dr",
    "sg:city": "Willoughby",
    "sg:classifiers": [
      {
        "category": "Building \u0026 Trades",
        "subcategory": "Construction",
        "type": "Services"
      }
    ],
    "sg:phone": "+1 440 951 2033",
    "sg:postcode": "44095",
    "sg:province": "OH",
    "sg:tags": [
      "contractor"
    ],
    "wof:name": "Klemenc Construction Co Inc",
    "wof:placetype": "venue"
  },
  "geometry": {"coordinates":[-81.42806,41.650525],"type":"Point"}
}
