{
  "type": "Feature",
  "properties": {
    "iso:country":"US",
    "sg:address":"8063 Arcanum Painters Creek Rd",
    "sg:city":"Arcanum",
    "sg:phone":"+1 937 548 3279",
    "sg:postcode":"45304",
    "sg:province":"OH",
    "sg:tags":[
        "farm",
        "corn",
        "grain",
        "cash"
    ],
    "wof:name":"Gary Kingrey",
    "wof:placetype":"venue"
},
  "geometry": {"coordinates":[-84.507366,40.035021],"type":"Point"}
}