{
  "type": "Feature",
  "properties": {
    "addr:full": "543 Pepper Ridge Rd Cincinnati OH 45244",
    "addr:housenumber": "543",
    "addr:postcode": "45244",
    "addr:street": "Pepper Ridge Rd",
    "iso:country": "US",
    "sg:address": "543 Pepper Ridge Rd",
    "sg:city": "Cincinnati",
    "sg:classifiers": [
      {
        "category": "Building \u0026 Trades",
        "subcategory": "Construction",
        "type": "Services"
      }
    ],
    "sg:phone": "+1 513 831 8673",
    "sg:postcode": "45244",
    "sg:province": "OH",
    "sg:tags": [
      "house"
    ],
    "wof:name": "Heffernans Construction",
    "wof:placetype": "venue"
  },
  "geometry": {"coordinates":[-84.294971,39.134232],"type":"Point"}
}
