{
  "type": "Feature",
  "properties": {
    "addr:full": "10335 Jackson St Byesville OH 43723",
    "addr:housenumber": "10335",
    "addr:postcode": "43723",
    "addr:street": "Jackson St",
    "iso:country": "US",
    "sg:address": "10335 Jackson St",
    "sg:city": "Byesville",
    "sg:classifiers": [
      {
        "category": "Organizations",
        "subcategory": "Community Association",
        "type": "Services"
      }
    ],
    "sg:phone": "+1 740 685 6033",
    "sg:postcode": "43723",
    "sg:province": "OH",
    "wof:name": "Byes Mill Post 3760",
    "wof:placetype": "venue"
  },
  "geometry": {"coordinates":[-81.550338,39.977489],"type":"Point"}
}
