{
  "type": "Feature",
  "properties": {
    "iso:country":"US",
    "sg:address":"8699 Broadway Ave",
    "sg:city":"Cleveland",
    "sg:classifiers":[
        {
            "category":"Autos & Motor Vehicles",
            "subcategory":"Automobile Sales",
            "type":"Retail Goods"
        }
    ],
    "sg:phone":"+1 216 429 1177",
    "sg:postcode":"44105",
    "sg:province":"OH",
    "wof:name":"Ferrari Ron Auto Sales Inc",
    "wof:placetype":"venue"
},
  "geometry": {"coordinates":[-81.625886,41.447327],"type":"Point"}
}