{
  "type": "Feature",
  "properties": {
    "addr:full":"2819 Hayes Ave Ste 6 Sandusky OH 44870",
    "addr:housenumber":"2819",
    "addr:postcode":"44870",
    "addr:street":"Hayes Ave Ste 6",
    "iso:country":"US",
    "sg:address":"2819 Hayes Ave Ste 6",
    "sg:city":"Sandusky",
    "sg:classifiers":[
        {
            "category":"Health Services",
            "subcategory":"Doctor",
            "type":"Services"
        }
    ],
    "sg:phone":"+1 419 626 0225",
    "sg:postcode":"44870",
    "sg:province":"OH",
    "wof:name":"Cooper Marsha D MD",
    "wof:placetype":"venue"
},
  "geometry": {"coordinates":[-82.71820099999999,41.425701],"type":"Point"}
}