{
  "type": "Feature",
  "properties": {
    "iso:country":"US",
    "sg:address":"23502 Beachwood Blvd",
    "sg:city":"Cleveland",
    "sg:classifiers":[
        {
            "category":"Wholesale",
            "subcategory":"Stationery",
            "type":"Manufacturing & Wholesale Goods"
        }
    ],
    "sg:phone":"+1 216 382 8436",
    "sg:postcode":"44122",
    "sg:province":"OH",
    "sg:tags":[
        "business",
        "form",
        "system"
    ],
    "wof:name":"H M Printing",
    "wof:placetype":"venue"
},
  "geometry": {"coordinates":[-81.513149,41.496202],"type":"Point"}
}