{
  "type": "Feature",
  "properties": {
    "addr:full": "839 Rhoads Ave Columbus OH 43205",
    "addr:housenumber": "839",
    "addr:postcode": "43205",
    "addr:street": "Rhoads Ave",
    "iso:country": "US",
    "sg:address": "839 Rhoads Ave",
    "sg:city": "Columbus",
    "sg:classifiers": [
      {
        "category": "Professional",
        "type": "Services"
      }
    ],
    "sg:phone": "+1 614 372 1530",
    "sg:postcode": "43205",
    "sg:province": "OH",
    "sg:tags": [
      "establishment"
    ],
    "wof:name": "Rebecca's Place",
    "wof:placetype": "venue"
  },
  "geometry": {"coordinates":[-82.948824,39.95153],"type":"Point"}
}
