{
  "type": "Feature",
  "properties": {
    "iso:country":"US",
    "sg:address":"1201 State Rte 97",
    "sg:city":"Mansfield",
    "sg:classifiers":[
        {
            "category":"Retail",
            "subcategory":"Repair Shop",
            "type":"Services"
        }
    ],
    "sg:phone":"+1 419 884 3105",
    "sg:postcode":"44904",
    "sg:province":"OH",
    "sg:tags":[
        "taxidermist"
    ],
    "wof:name":"Woodville Taxidermy",
    "wof:placetype":"venue"
},
  "geometry": {"coordinates":[-82.559445,40.666634],"type":"Point"}
}