{
  "type": "Feature",
  "properties": {
    "addr:full": "1814 Walden Dr Columbus OH 43229",
    "addr:housenumber": "1814",
    "addr:postcode": "43229",
    "addr:street": "Walden Dr",
    "iso:country": "US",
    "sg:address": "1814 Walden Dr",
    "sg:city": "Columbus",
    "sg:classifiers": [
      {
        "category": "Manufacturing",
        "subcategory": "Printing",
        "type": "Manufacturing \u0026 Wholesale Goods"
      }
    ],
    "sg:phone": "+1 614 846 3875",
    "sg:postcode": "43229",
    "sg:province": "OH",
    "sg:tags": [
      "book",
      "electronic"
    ],
    "wof:name": "Sweethaven Publishing Services",
    "wof:placetype": "venue"
  },
  "geometry": {"coordinates":[-82.965822,40.080395],"type":"Point"}
}
