{
  "type": "Feature",
  "properties": {
    "iso:country":"US",
    "sg:address":"424 Wards Corner Road, 2nd Floor",
    "sg:city":"Loveland",
    "sg:classifiers":[
        {
            "category":"Professional",
            "subcategory":"Computer Services",
            "type":"Services"
        }
    ],
    "sg:phone":"+1 877 536 0222",
    "sg:postcode":"45140",
    "sg:province":"OH",
    "sg:tags":[
        "higher-education"
    ],
    "sg:website":"http://www.jenzabar.net",
    "wof:name":"Jenzabar",
    "wof:placetype":"venue"
},
  "geometry": {"coordinates":[-84.30019299999999,39.213286],"type":"Point"}
}