{
  "type": "Feature",
  "properties": {
    "addr:full": "3725 Susanna Dr Cincinnati OH 45251",
    "addr:housenumber": "3725",
    "addr:postcode": "45251",
    "addr:street": "Susanna Dr",
    "iso:country": "US",
    "sg:address": "3725 Susanna Dr",
    "sg:city": "Cincinnati",
    "sg:classifiers": [
      {
        "category": "Manufacturing",
        "subcategory": "Paper Products",
        "type": "Manufacturing \u0026 Wholesale Goods"
      }
    ],
    "sg:phone": "+1 513 742 2760",
    "sg:postcode": "45251",
    "sg:province": "OH",
    "sg:tags": [
      "converted",
      "mfg"
    ],
    "wof:name": "L C Label Co",
    "wof:placetype": "venue"
  },
  "geometry": {"coordinates":[-84.600672,39.247636],"type":"Point"}
}
