{
  "type": "Feature",
  "properties": {
    "iso:country":"US",
    "sg:address":"192 Twin Oaks Dr",
    "sg:city":"Jackson",
    "sg:classifiers":[
        {
            "category":"Building & Trades",
            "subcategory":"Equipment Rental",
            "type":"Services"
        }
    ],
    "sg:phone":"+1 740 286 8665",
    "sg:postcode":"45640",
    "sg:province":"OH",
    "sg:tags":[
        "yard"
    ],
    "wof:name":"Wagner Tool Rental Inc",
    "wof:placetype":"venue"
},
  "geometry": {"coordinates":[-82.636816,39.031735],"type":"Point"}
}