{
  "type": "Feature",
  "properties": {
    "iso:country":"US",
    "sg:address":"12732 Emerson Rd",
    "sg:city":"Apple Creek",
    "sg:classifiers":[
        {
            "category":"Personal",
            "type":"Services"
        }
    ],
    "sg:phone":"+1 330 857 0383",
    "sg:postcode":"44606",
    "sg:province":"OH",
    "sg:tags":[
        "therapist",
        "massage"
    ],
    "wof:name":"Full Spectrum Massotherapy",
    "wof:placetype":"venue"
},
  "geometry": {"coordinates":[-81.745898,40.741143],"type":"Point"}
}