{
  "type": "Feature",
  "properties": {
    "iso:country":"US",
    "sg:address":"245 N Broad St",
    "sg:city":"Bremen",
    "sg:classifiers":[
        {
            "category":"Manufacturing",
            "subcategory":"Metals",
            "type":"Manufacturing & Wholesale Goods"
        }
    ],
    "sg:phone":"+1 740 569 4143",
    "sg:postcode":"43107",
    "sg:province":"OH",
    "sg:tags":[
        "tank"
    ],
    "sg:website":"www.westermancompanies.com",
    "wof:name":"Westerman Companies",
    "wof:placetype":"venue"
},
  "geometry": {"coordinates":[-82.426596,39.705246],"type":"Point"}
}