{
  "type": "Feature",
  "properties": {
    "addr:full": "3129 Fair Ave Columbus OH 43209",
    "addr:housenumber": "3129",
    "addr:postcode": "43209",
    "addr:street": "Fair Ave",
    "iso:country": "US",
    "sg:address": "3129 Fair Ave",
    "sg:city": "Columbus",
    "sg:classifiers": [
      {
        "category": "Shopping",
        "subcategory": "Clothing, Apparel, \u0026 Fashions",
        "type": "Retail Goods"
      }
    ],
    "sg:phone": "+1 614 235 7220",
    "sg:postcode": "43209",
    "sg:province": "OH",
    "sg:tags": [
      "fur",
      "business"
    ],
    "wof:name": "Alley's Fur Remodeling \u0026 Rpr",
    "wof:placetype": "venue"
  },
  "geometry": {"coordinates":[-82.91583,39.961205],"type":"Point"}
}
