{
  "type": "Feature",
  "properties": {
    "addr:full": "4660 Duke Dr Lebanon OH 45040",
    "addr:housenumber": "4660",
    "addr:postcode": "45040",
    "addr:street": "Duke Dr",
    "iso:country": "US",
    "sg:address": "4660 Duke Dr",
    "sg:city": "Lebanon",
    "sg:classifiers": [
      {
        "category": "Professional",
        "subcategory": "Lawyer \u0026 Legal Services",
        "type": "Services"
      }
    ],
    "sg:phone": "+1 513 459 1745",
    "sg:postcode": "45040",
    "sg:province": "OH",
    "sg:tags": [
      "attorney"
    ],
    "wof:name": "Carol Garner Stark",
    "wof:placetype": "venue"
  },
  "geometry": {"coordinates":[-84.309916,39.301167],"type":"Point"}
}
