{
  "type": "Feature",
  "properties": {
    "addr:full":"7715 Laurel Ave Cincinnati OH 45243",
    "addr:housenumber":"7715",
    "addr:postcode":"45243",
    "addr:street":"Laurel Ave",
    "iso:country":"US",
    "sg:address":"7715 Laurel Ave",
    "sg:city":"Cincinnati",
    "sg:classifiers":[
        {
            "category":"Shopping",
            "subcategory":"Florist",
            "type":"Retail Goods"
        }
    ],
    "sg:phone":"+1 513 561 7766",
    "sg:postcode":"45243",
    "sg:province":"OH",
    "wof:name":"Curious Garden",
    "wof:placetype":"venue"
},
  "geometry": {"coordinates":[-84.361211,39.189495],"type":"Point"}
}