{
  "type": "Feature",
  "properties": {
    "addr:full": "21171 State Rte 751 West Lafayette OH 43845",
    "addr:housenumber": "21171",
    "addr:postcode": "43845",
    "addr:street": "State Rte 751",
    "iso:country": "US",
    "sg:address": "21171 State Rte 751",
    "sg:city": "West Lafayette",
    "sg:classifiers": [
      {
        "category": "Manufacturing",
        "subcategory": "Motor Vehicles \u0026 Parts",
        "type": "Manufacturing \u0026 Wholesale Goods"
      }
    ],
    "sg:phone": "+1 740 545 0101",
    "sg:postcode": "43845",
    "sg:province": "OH",
    "sg:tags": [
      "truck",
      "trailer",
      "mfg"
    ],
    "wof:name": "Mitch Hayes",
    "wof:placetype": "venue"
  },
  "geometry": {"coordinates":[-81.742078,40.273745],"type":"Point"}
}
