{
  "type": "Feature",
  "properties": {
    "addr:full":"4111 Co Rd Hj Delta OH 43515",
    "addr:housenumber":"4111",
    "addr:postcode":"43515",
    "addr:street":"Co Rd",
    "iso:country":"US",
    "sg:address":"4111 Co Rd Hj",
    "sg:city":"Delta",
    "sg:classifiers":[
        {
            "category":"Freight",
            "type":"Transportation"
        }
    ],
    "sg:phone":"+1 419 822 3770",
    "sg:postcode":"43515",
    "sg:province":"OH",
    "sg:tags":[
        "operator",
        "local",
        "trucking"
    ],
    "wof:name":"Paul F Szkudlarek",
    "wof:placetype":"venue"
},
  "geometry": {"coordinates":[-83.955578,41.595711],"type":"Point"}
}