{
  "type": "Feature",
  "properties": {
    "addr:full": "1085 Albany Ter Cincinnati OH 45224",
    "addr:housenumber": "1085",
    "addr:postcode": "45224",
    "addr:street": "Albany Ter",
    "iso:country": "US",
    "sg:address": "1085 Albany Ter",
    "sg:city": "Cincinnati",
    "sg:classifiers": [
      {
        "category": "Real Estate",
        "subcategory": "Real Estate Operator",
        "type": "Services"
      }
    ],
    "sg:phone": "+1 513 541 8850",
    "sg:postcode": "45224",
    "sg:province": "OH",
    "sg:tags": [
      "building",
      "apartment"
    ],
    "wof:name": "Cornelius Taylor Jr",
    "wof:placetype": "venue"
  },
  "geometry": {"coordinates":[-84.535069,39.196844],"type":"Point"}
}
