{
  "type": "Feature",
  "properties": {
    "addr:full":"1395 N 21st St Newark OH 43055",
    "addr:housenumber":"1395",
    "addr:postcode":"43055",
    "addr:street":"N 21St St",
    "iso:country":"US",
    "sg:address":"1395 N 21st St",
    "sg:city":"Newark",
    "sg:classifiers":[
        {
            "category":"Autos & Motor Vehicles",
            "subcategory":"Fuel & Gas Station",
            "type":"Retail Goods"
        }
    ],
    "sg:phone":"+1 740 364 0813",
    "sg:postcode":"43055",
    "sg:province":"OH",
    "sg:tags":[
        "station",
        "gasoline"
    ],
    "wof:name":"Murphy Oil USA Inc",
    "wof:placetype":"venue"
},
  "geometry": {"coordinates":[-82.427392,40.086507],"type":"Point"}
}