{
  "type": "Feature",
  "properties": {
    "addr:full":"2149 N Reynolds Rd Toledo OH 43615",
    "addr:housenumber":"2149",
    "addr:postcode":"43615",
    "addr:street":"N Reynolds Rd",
    "iso:country":"US",
    "sg:address":"2149 N Reynolds Rd",
    "sg:city":"Toledo",
    "sg:classifiers":[
        {
            "category":"Autos & Motor Vehicles",
            "subcategory":"Fuel & Gas Station",
            "type":"Retail Goods"
        }
    ],
    "sg:phone":"+1 419 531 6131",
    "sg:postcode":"43615",
    "sg:province":"OH",
    "sg:tags":[
        "station",
        "gasoline"
    ],
    "wof:name":"Reynolds Road Marathon",
    "wof:placetype":"venue"
},
  "geometry": {"coordinates":[-83.667751,41.661211],"type":"Point"}
}