{
  "type": "Feature",
  "properties": {
    "addr:full":"252 High St Hamilton OH 45011",
    "addr:housenumber":"252",
    "addr:postcode":"45011",
    "addr:street":"High St",
    "iso:country":"US",
    "sg:address":"252 High St",
    "sg:city":"Hamilton",
    "sg:classifiers":[
        {
            "category":"Restaurant",
            "type":"Food & Drink"
        }
    ],
    "sg:phone":"+1 513 863 0088",
    "sg:postcode":"45011",
    "sg:province":"OH",
    "sg:tags":[
        "eating"
    ],
    "wof:name":"City Diners",
    "wof:placetype":"venue"
},
  "geometry": {"coordinates":[-84.560959,39.399668],"type":"Point"}
}