{
  "type": "Feature",
  "properties": {
    "iso:country":"US",
    "sg:address":"2462 Princeton Rd",
    "sg:city":"Cleveland",
    "sg:classifiers":[
        {
            "category":"Manufacturing",
            "subcategory":"Tools & Machinery",
            "type":"Manufacturing & Wholesale Goods"
        }
    ],
    "sg:phone":"+1 216 932 0928",
    "sg:postcode":"44118",
    "sg:province":"OH",
    "sg:tags":[
        "machine",
        "repair",
        "electrical",
        "mfg"
    ],
    "wof:name":"Tausz Machine Repair",
    "wof:placetype":"venue"
},
  "geometry": {"coordinates":[-81.551139,41.491956],"type":"Point"}
}