{
  "type": "Feature",
  "properties": {
    "iso:country":"US",
    "sg:address":"9884 S Chapel St",
    "sg:city":"Garrettsville",
    "sg:classifiers":[
        {
            "category":"Wholesale",
            "subcategory":"Non-durable Goods",
            "type":"Manufacturing & Wholesale Goods"
        }
    ],
    "sg:phone":"+1 330 326 3248",
    "sg:postcode":"44231",
    "sg:province":"OH",
    "wof:name":"Southern Drum Trading Post",
    "wof:placetype":"venue"
},
  "geometry": {"coordinates":[-81.059757,41.262517],"type":"Point"}
}