{
  "type": "Feature",
  "properties": {
    "addr:full":"5475 Liberty Ave Vermilion OH 44089",
    "addr:housenumber":"5475",
    "addr:postcode":"44089",
    "addr:street":"Liberty Ave",
    "iso:country":"US",
    "sg:address":"5475 Liberty Ave",
    "sg:city":"Vermilion",
    "sg:classifiers":[
        {
            "category":"Banks & Credit Unions",
            "subcategory":"Bank",
            "type":"Services"
        }
    ],
    "sg:phone":"+1 440 967 2265",
    "sg:postcode":"44089",
    "sg:province":"OH",
    "sg:tags":[
        "national",
        "commercial"
    ],
    "wof:name":"First National Bank",
    "wof:placetype":"venue"
},
  "geometry": {"coordinates":[-82.36426,41.42195],"type":"Point"}
}