{
  "type": "Feature",
  "properties": {
    "iso:country":"US",
    "sg:address":"3000 Euclid Ave",
    "sg:city":"Cleveland",
    "sg:classifiers":[
        {
            "category":"Social Services",
            "subcategory":"Adult Care",
            "type":"Services"
        }
    ],
    "sg:phone":"+1 216 231 4015",
    "sg:postcode":"44115",
    "sg:province":"OH",
    "sg:tags":[
        "organization",
        "senior",
        "citizen"
    ],
    "wof:name":"Golden Age Ctr",
    "wof:placetype":"venue"
},
  "geometry": {"coordinates":[-81.665334,41.502767],"type":"Point"}
}