{
  "type": "Feature",
  "properties": {
    "iso:country":"US",
    "sg:address":"7297 John Glenn Hwy",
    "sg:city":"Cambridge",
    "sg:classifiers":[
        {
            "category":"Health Services",
            "subcategory":"Doctor",
            "type":"Services"
        }
    ],
    "sg:phone":"+1 740 432 8768",
    "sg:postcode":"43725",
    "sg:province":"OH",
    "wof:name":"East Ohio Memorial Servic",
    "wof:placetype":"venue"
},
  "geometry": {"coordinates":[-81.609864,40.021788],"type":"Point"}
}