{
  "type": "Feature",
  "properties": {
    "iso:country":"US",
    "sg:address":"25821 Akins Rd",
    "sg:city":"Columbia Station",
    "sg:classifiers":[
        {
            "category":"Shopping",
            "subcategory":"Hobbies, Toys, & Games",
            "type":"Retail Goods"
        }
    ],
    "sg:phone":"+1 440 236 8547",
    "sg:postcode":"44028",
    "sg:province":"OH",
    "sg:tags":[
        "craft",
        "supply"
    ],
    "wof:name":"Cutie Pies Inc",
    "wof:placetype":"venue"
},
  "geometry": {"coordinates":[-81.934011,41.2895],"type":"Point"}
}