{
  "type": "Feature",
  "properties": {
    "iso:country":"US",
    "sg:address":"21825 Chagrin Blvd",
    "sg:city":"Cleveland",
    "sg:classifiers":[
        {
            "category":"Professional",
            "subcategory":"Employment Agencies",
            "type":"Services"
        }
    ],
    "sg:phone":"+1 216 295 1500",
    "sg:postcode":"44122",
    "sg:province":"OH",
    "sg:tags":[
        "help",
        "supply"
    ],
    "wof:name":"Firstat Nursing Services",
    "wof:placetype":"venue"
},
  "geometry": {"coordinates":[-81.522458,41.464584],"type":"Point"}
}