{
  "type": "Feature",
  "properties": {
    "iso:country":"US",
    "sg:address":"1978 W 3rd St",
    "sg:city":"Cleveland",
    "sg:classifiers":[
        {
            "category":"Freight",
            "type":"Transportation"
        }
    ],
    "sg:phone":"+1 216 771 1870",
    "sg:postcode":"44113",
    "sg:province":"OH",
    "sg:tags":[
        "delivery"
    ],
    "wof:name":"Hencin Warehousing & Delivery",
    "wof:placetype":"venue"
},
  "geometry": {"coordinates":[-81.68842100000001,41.49097],"type":"Point"}
}