{
  "type": "Feature",
  "properties": {
    "addr:full": "1978 W 3rd St Cleveland OH 44113",
    "addr:housenumber": "1978",
    "addr:postcode": "44113",
    "addr:street": "W 3Rd St",
    "iso:country": "US",
    "sg:address": "1978 W 3rd St",
    "sg:city": "Cleveland",
    "sg:classifiers": [
      {
        "category": "Freight",
        "type": "Transportation"
      }
    ],
    "sg:phone": "+1 216 771 1870",
    "sg:postcode": "44113",
    "sg:province": "OH",
    "sg:tags": [
      "delivery"
    ],
    "wof:name": "Hencin Warehousing \u0026 Delivery",
    "wof:placetype": "venue"
  },
  "geometry": {"coordinates":[-81.688421,41.49097],"type":"Point"}
}
