{
  "type": "Feature",
  "properties": {
    "addr:full":"2099 W 5th Ave Columbus OH 43212",
    "addr:housenumber":"2099",
    "addr:postcode":"43212",
    "addr:street":"W 5Th Ave",
    "iso:country":"US",
    "sg:address":"2099 W 5th Ave",
    "sg:city":"Columbus",
    "sg:classifiers":[
        {
            "category":"Real Estate",
            "subcategory":"Surveying",
            "type":"Services"
        }
    ],
    "sg:phone":"+1 614 485 9000",
    "sg:postcode":"43212",
    "sg:province":"OH",
    "sg:tags":[
        "surveyor",
        "land"
    ],
    "wof:name":"Landmark Survey Group Inc",
    "wof:placetype":"venue"
},
  "geometry": {"coordinates":[-83.06312,39.989474],"type":"Point"}
}