{
  "type": "Feature",
  "properties": {
    "addr:full":"5825 Heather Hedge Dr Chippewa Lake OH 44215",
    "addr:housenumber":"5825",
    "addr:postcode":"44215",
    "addr:street":"Heather Hedge Dr Chippewa",
    "iso:country":"US",
    "sg:address":"5825 Heather Hedge Dr",
    "sg:city":"Chippewa Lake",
    "sg:classifiers":[
        {
            "category":"Government",
            "subcategory":"Post Office",
            "type":"Public Place"
        }
    ],
    "sg:phone":"+1 330 769 3514",
    "sg:postcode":"44215",
    "sg:province":"OH",
    "sg:tags":[
        "postal",
        "us"
    ],
    "wof:name":"Chippewa Lake Main Office",
    "wof:placetype":"venue"
},
  "geometry": {"coordinates":[-81.898717,41.070966],"type":"Point"}
}