{
  "type": "Feature",
  "properties": {
    "addr:full":"7965 N High St Columbus OH 43235",
    "addr:housenumber":"7965",
    "addr:postcode":"43235",
    "addr:street":"N High St",
    "iso:country":"US",
    "sg:address":"7965 N High St",
    "sg:city":"Columbus",
    "sg:classifiers":[
        {
            "category":"Insurance",
            "subcategory":"Insurance Agent",
            "type":"Services"
        }
    ],
    "sg:phone":"+1 614 848 8550",
    "sg:postcode":"43235",
    "sg:province":"OH",
    "sg:tags":[
        "life",
        "carrier"
    ],
    "wof:name":"Principal Life Insurance Co",
    "wof:placetype":"venue"
},
  "geometry": {"coordinates":[-83.01652199999999,40.129858],"type":"Point"}
}