{
  "type": "Feature",
  "properties": {
    "addr:full": "33 W Elm St Butler OH 44822",
    "addr:housenumber": "33",
    "addr:postcode": "44822",
    "addr:street": "W Elm St",
    "iso:country": "US",
    "sg:address": "33 W Elm St",
    "sg:city": "Butler",
    "sg:classifiers": [
      {
        "category": "Government",
        "subcategory": "Office",
        "type": "Public Place"
      }
    ],
    "sg:phone": "+1 419 883 2481",
    "sg:postcode": "44822",
    "sg:province": "OH",
    "sg:tags": [
      "village"
    ],
    "wof:name": "Butler Village Hall",
    "wof:placetype": "venue"
  },
  "geometry": {"coordinates":[-82.426191,40.588373],"type":"Point"}
}
