{
  "type": "Feature",
  "properties": {
    "addr:full":"6555 Frederick Pike Dayton OH 45414",
    "addr:housenumber":"6555",
    "addr:postcode":"45414",
    "addr:street":"Frederick Pike",
    "iso:country":"US",
    "sg:address":"6555 Frederick Pike",
    "sg:city":"Dayton",
    "sg:classifiers":[
        {
            "category":"Building & Trades",
            "subcategory":"Landscaping Services",
            "type":"Services"
        }
    ],
    "sg:phone":"+1 937 361 6600",
    "sg:postcode":"45414",
    "sg:province":"OH",
    "sg:tags":[
        "lawn",
        "maintenance",
        "grounds"
    ],
    "wof:name":"R & D Lawn & Lawnscaping",
    "wof:placetype":"venue"
},
  "geometry": {"coordinates":[-84.235246,39.840267],"type":"Point"}
}