{
  "type": "Feature",
  "properties": {
    "addr:full": "305 W Plane St Bethel OH 45106",
    "addr:housenumber": "305",
    "addr:postcode": "45106",
    "addr:street": "W Plane St",
    "iso:country": "US",
    "sg:address": "305 W Plane St",
    "sg:city": "Bethel",
    "sg:classifiers": [
      {
        "category": "Shopping",
        "subcategory": "Discount \u0026 Variety Stores",
        "type": "Retail Goods"
      }
    ],
    "sg:phone": "+1 513 734 7464",
    "sg:postcode": "45106",
    "sg:province": "OH",
    "wof:name": "Ben Franklin Store 0191",
    "wof:placetype": "venue"
  },
  "geometry": {"coordinates":[-84.081173,38.96351],"type":"Point"}
}
