{
  "type": "Feature",
  "properties": {
    "iso:country":"US",
    "sg:address":"305 W Plane St",
    "sg:city":"Bethel",
    "sg:classifiers":[
        {
            "category":"Shopping",
            "subcategory":"Discount & Variety Stores",
            "type":"Retail Goods"
        }
    ],
    "sg:phone":"+1 513 734 7464",
    "sg:postcode":"45106",
    "sg:province":"OH",
    "wof:name":"Ben Franklin Store 0191",
    "wof:placetype":"venue"
},
  "geometry": {"coordinates":[-84.08117300000001,38.96351],"type":"Point"}
}