{
  "type": "Feature",
  "properties": {
    "addr:full":"7886 S Ridge Rd Madison OH 44057",
    "addr:housenumber":"7886",
    "addr:postcode":"44057",
    "addr:street":"S Ridge Rd",
    "iso:country":"US",
    "sg:address":"7886 S Ridge Rd",
    "sg:city":"Madison",
    "sg:classifiers":[
        {
            "category":"Home & Garden",
            "subcategory":"Hardware",
            "type":"Retail Goods"
        }
    ],
    "sg:phone":"+1 440 428 3177",
    "sg:postcode":"44057",
    "sg:province":"OH",
    "wof:name":"Infia Red Ohio Sales",
    "wof:placetype":"venue"
},
  "geometry": {"coordinates":[-81.003681,41.779992],"type":"Point"}
}