{
  "type": "Feature",
  "properties": {
    "addr:full":"33550 Vine St Eastlake OH 44095",
    "addr:housenumber":"33550",
    "addr:postcode":"44095",
    "addr:street":"Vine St",
    "iso:country":"US",
    "sg:address":"33550 Vine St",
    "sg:city":"Eastlake",
    "sg:classifiers":[
        {
            "category":"Restaurant",
            "type":"Food & Drink"
        }
    ],
    "sg:menulink":"http://www.allmenus.com/oh/eastlake/31862-mandarin-seafood-buffet/menu/",
    "sg:phone":"+1 440 602 9888",
    "sg:postcode":"44095",
    "sg:province":"OH",
    "sg:tags":[
        "asian",
        "chinese"
    ],
    "wof:name":"Mandarin Seafood Buffet",
    "wof:placetype":"venue"
},
  "geometry": {"coordinates":[-81.44941300000001,41.642523],"type":"Point"}
}