{
  "type": "Feature",
  "properties": {
    "iso:country":"US",
    "sg:address":"2098 Portage Rd",
    "sg:city":"Wooster",
    "sg:classifiers":[
        {
            "category":"Mining & Drilling",
            "type":"Manufacturing & Wholesale Goods"
        }
    ],
    "sg:phone":"+1 330 264 5069",
    "sg:postcode":"44691",
    "sg:province":"OH",
    "sg:tags":[
        "oil",
        "well"
    ],
    "wof:name":"Petroset Cementing Svc",
    "wof:placetype":"venue"
},
  "geometry": {"coordinates":[-81.910447,40.828453],"type":"Point"}
}