{
  "type": "Feature",
  "properties": {
    "addr:full":"210 S Heincke Rd Miamisburg OH 45342",
    "addr:housenumber":"210",
    "addr:postcode":"45342",
    "addr:street":"S Heincke Rd",
    "iso:country":"US",
    "sg:address":"210 S Heincke Rd",
    "sg:city":"Miamisburg",
    "sg:classifiers":[
        {
            "category":"Banks & Credit Unions",
            "subcategory":"Bank",
            "type":"Services"
        }
    ],
    "sg:phone":"+1 937 443 6180",
    "sg:postcode":"45342",
    "sg:province":"OH",
    "sg:tags":[
        "national",
        "commercial"
    ],
    "wof:name":"Bank One",
    "wof:placetype":"venue"
},
  "geometry": {"coordinates":[-84.26497000000001,39.637413],"type":"Point"}
}