{
  "type": "Feature",
  "properties": {
    "iso:country":"US",
    "sg:address":"24300 Solon Rd",
    "sg:city":"Bedford",
    "sg:classifiers":[
        {
            "category":"Manufacturing",
            "subcategory":"Signs",
            "type":"Manufacturing & Wholesale Goods"
        }
    ],
    "sg:phone":"+1 440 439 1858",
    "sg:postcode":"44146",
    "sg:province":"OH",
    "sg:tags":[
        "specialty",
        "mfg"
    ],
    "wof:name":"Neon Workshop LLC",
    "wof:placetype":"venue"
},
  "geometry": {"coordinates":[-81.503878,41.3853],"type":"Point"}
}