{
  "type": "Feature",
  "properties": {
    "addr:full": "1351 Fotler St Springfield OH 45504",
    "addr:housenumber": "1351",
    "addr:postcode": "45504",
    "addr:street": "Fotler St",
    "iso:country": "US",
    "sg:address": "1351 Fotler St",
    "sg:city": "Springfield",
    "sg:classifiers": [
      {
        "category": "Health Services",
        "subcategory": "Hospital",
        "type": "Services"
      }
    ],
    "sg:phone": "+1 937 324 8249",
    "sg:postcode": "45504",
    "sg:province": "OH",
    "sg:website": "www.medcorpinc.com",
    "wof:name": "Medcorp",
    "wof:placetype": "venue"
  },
  "geometry": {"coordinates":[-83.834145,39.936355],"type":"Point"}
}
