{
  "type": "Feature",
  "properties": {
    "iso:country":"US",
    "sg:address":"1351 Fotler St",
    "sg:city":"Springfield",
    "sg:classifiers":[
        {
            "category":"Health Services",
            "subcategory":"Hospital",
            "type":"Services"
        }
    ],
    "sg:phone":"+1 937 324 8249",
    "sg:postcode":"45504",
    "sg:province":"OH",
    "sg:website":"www.medcorpinc.com",
    "wof:name":"Medcorp",
    "wof:placetype":"venue"
},
  "geometry": {"coordinates":[-83.83414500000001,39.936355],"type":"Point"}
}