{
  "type": "Feature",
  "properties": {
    "addr:full":"7659 Bridgetown Rd Cincinnati OH 45248",
    "addr:housenumber":"7659",
    "addr:postcode":"45248",
    "addr:street":"Bridgetown Rd",
    "iso:country":"US",
    "sg:address":"7659 Bridgetown Rd",
    "sg:city":"Cincinnati",
    "sg:classifiers":[
        {
            "category":"Personal",
            "type":"Services"
        }
    ],
    "sg:phone":"+1 513 708 2849",
    "sg:postcode":"45248",
    "sg:province":"OH",
    "sg:tags":[
        "therapist",
        "massage"
    ],
    "wof:name":"Massage Therapy Ctr",
    "wof:placetype":"venue"
},
  "geometry": {"coordinates":[-84.69942899999999,39.166173],"type":"Point"}
}