{
  "type": "Feature",
  "properties": {
    "iso:country":"US",
    "sg:address":"88 E Broad St",
    "sg:city":"Columbus",
    "sg:classifiers":[
        {
            "category":"Professional",
            "subcategory":"Lawyer & Legal Services",
            "type":"Services"
        }
    ],
    "sg:phone":"+1 614 229 0024",
    "sg:postcode":"43215",
    "sg:province":"OH",
    "sg:tags":[
        "attorney"
    ],
    "wof:name":"Lesley R Avery Attorney",
    "wof:placetype":"venue"
},
  "geometry": {"coordinates":[-82.999481,39.962421],"type":"Point"}
}