{
  "type": "Feature",
  "properties": {
    "addr:full":"610 E Perkins Ave Sandusky OH 44870",
    "addr:housenumber":"610",
    "addr:postcode":"44870",
    "addr:street":"E Perkins Ave",
    "iso:country":"US",
    "sg:address":"610 E Perkins Ave",
    "sg:city":"Sandusky",
    "sg:classifiers":[
        {
            "category":"Autos & Motor Vehicles",
            "subcategory":"Automobile Sales",
            "type":"Retail Goods"
        }
    ],
    "sg:phone":"+1 419 626 4721",
    "sg:postcode":"44870",
    "sg:province":"OH",
    "sg:tags":[
        "new",
        "used"
    ],
    "sg:website":"www.mathewsford.com",
    "wof:name":"Mathews Ford Lincoln Mercury",
    "wof:placetype":"venue"
},
  "geometry": {"coordinates":[-82.68991200000001,41.432571],"type":"Point"}
}