{
  "type": "Feature",
  "properties": {
    "addr:full": "2263 Salem Ave Dayton OH 45406",
    "addr:housenumber": "2263",
    "addr:postcode": "45406",
    "addr:street": "Salem Ave",
    "iso:country": "US",
    "sg:address": "2263 Salem Ave",
    "sg:city": "Dayton",
    "sg:classifiers": [
      {
        "category": "Health Services",
        "subcategory": "Doctor",
        "type": "Services"
      }
    ],
    "sg:phone": "+1 937 278 7914",
    "sg:postcode": "45406",
    "sg:province": "OH",
    "sg:tags": [
      "physician",
      "surgeon"
    ],
    "wof:name": "Lolita L Rana MD Inc",
    "wof:placetype": "venue"
  },
  "geometry": {"coordinates":[-84.229116,39.784691],"type":"Point"}
}
