{
  "type": "Feature",
  "properties": {
    "addr:full": "139 S 3rd St Coshocton OH 43812",
    "addr:housenumber": "139",
    "addr:postcode": "43812",
    "addr:street": "S 3Rd St",
    "iso:country": "US",
    "sg:address": "139 S 3rd St",
    "sg:city": "Coshocton",
    "sg:classifiers": [
      {
        "category": "Shopping",
        "type": "Retail Goods"
      }
    ],
    "sg:phone": "+1 740 623 8840",
    "sg:postcode": "43812",
    "sg:province": "OH",
    "sg:tags": [
      "merchandise"
    ],
    "wof:name": "Cell Phone Zone",
    "wof:placetype": "venue"
  },
  "geometry": {"coordinates":[-81.86714,40.273226],"type":"Point"}
}
