{
  "type": "Feature",
  "properties": {
    "iso:country":"US",
    "sg:address":"7235 Whipple Ave NW",
    "sg:city":"North Canton",
    "sg:classifiers":[
        {
            "category":"Manufacturing",
            "subcategory":"Tools & Machinery",
            "type":"Manufacturing & Wholesale Goods"
        }
    ],
    "sg:phone":"+1 330 498 8047",
    "sg:postcode":"44720",
    "sg:province":"OH",
    "sg:tags":[
        "physician",
        "surgeon"
    ],
    "sg:website":"www.altercareonline.net",
    "wof:name":"Schroer Ancillary Svc",
    "wof:placetype":"venue"
},
  "geometry": {"coordinates":[-81.423512,40.882443],"type":"Point"}
}