{
  "type": "Feature",
  "properties": {
    "addr:full": "7235 Whipple Ave NW North Canton OH 44720",
    "addr:housenumber": "7235",
    "addr:postcode": "44720",
    "addr:street": "Whipple Ave Nw",
    "iso:country": "US",
    "sg:address": "7235 Whipple Ave NW",
    "sg:city": "North Canton",
    "sg:classifiers": [
      {
        "category": "Manufacturing",
        "subcategory": "Tools \u0026 Machinery",
        "type": "Manufacturing \u0026 Wholesale Goods"
      }
    ],
    "sg:phone": "+1 330 498 8047",
    "sg:postcode": "44720",
    "sg:province": "OH",
    "sg:tags": [
      "physician",
      "surgeon"
    ],
    "sg:website": "www.altercareonline.net",
    "wof:name": "Schroer Ancillary Svc",
    "wof:placetype": "venue"
  },
  "geometry": {"coordinates":[-81.423512,40.882443],"type":"Point"}
}
