{
  "type": "Feature",
  "properties": {
    "iso:country":"US",
    "sg:address":"6660 Clough Pike",
    "sg:city":"Cincinnati",
    "sg:classifiers":[
        {
            "category":"Food & Beverages",
            "subcategory":"Groceries & Convenience Stores",
            "type":"Retail Goods"
        }
    ],
    "sg:phone":"+1 513 231 6483",
    "sg:postcode":"45244",
    "sg:province":"OH",
    "wof:name":"Silverglade & Sons of Findlay",
    "wof:placetype":"venue"
},
  "geometry": {"coordinates":[-84.368539,39.097116],"type":"Point"}
}