{
  "type": "Feature",
  "properties": {
    "addr:full": "2265 E 71st St Cleveland OH 44103",
    "addr:housenumber": "2265",
    "addr:postcode": "44103",
    "addr:street": "E 71St St",
    "iso:country": "US",
    "sg:address": "2265 E 71st St",
    "sg:city": "Cleveland",
    "sg:classifiers": [
      {
        "category": "Social Services",
        "subcategory": "Child Care",
        "type": "Services"
      }
    ],
    "sg:phone": "+1 216 426 8036",
    "sg:postcode": "44103",
    "sg:province": "OH",
    "wof:name": "C C 's Childcare",
    "wof:placetype": "venue"
  },
  "geometry": {"coordinates":[-81.639386,41.497595],"type":"Point"}
}
