{
  "type": "Feature",
  "properties": {
    "addr:full": "1650 Allentown Rd Lima OH 45805",
    "addr:housenumber": "1650",
    "addr:postcode": "45805",
    "addr:street": "Allentown Rd",
    "iso:country": "US",
    "sg:address": "1650 Allentown Rd",
    "sg:city": "Lima",
    "sg:classifiers": [
      {
        "category": "Health Services",
        "subcategory": "Nursing And Care Facility",
        "type": "Services"
      }
    ],
    "sg:phone": "+1 419 224 9741",
    "sg:postcode": "45805",
    "sg:province": "OH",
    "sg:tags": [
      "skilled"
    ],
    "wof:name": "Lima Convalescent Home",
    "wof:placetype": "venue"
  },
  "geometry": {"coordinates":[-84.137766,40.746176],"type":"Point"}
}
