{
  "type": "Feature",
  "properties": {
    "addr:full":"1240 E 9th St Cleveland OH 44114",
    "addr:housenumber":"1240",
    "addr:postcode":"44114",
    "addr:street":"E 9Th St",
    "iso:country":"US",
    "sg:address":"1240 E 9th St",
    "sg:city":"Cleveland",
    "sg:classifiers":[
        {
            "category":"Government",
            "subcategory":"Police Station",
            "type":"Public Place"
        }
    ],
    "sg:phone":"+1 216 522 1400",
    "sg:postcode":"44114",
    "sg:province":"OH",
    "sg:tags":[
        "federal"
    ],
    "wof:name":"Federal Bureau-Investigation",
    "wof:placetype":"venue"
},
  "geometry": {"coordinates":[-81.69050900000001,41.504531],"type":"Point"}
}