{
  "type": "Feature",
  "properties": {
    "addr:full": "422 Morse Rd Columbus OH 43214",
    "addr:housenumber": "422",
    "addr:postcode": "43214",
    "addr:street": "Morse Rd",
    "iso:country": "US",
    "sg:address": "422 Morse Rd",
    "sg:city": "Columbus",
    "sg:classifiers": [
      {
        "category": "Health Services",
        "subcategory": "Chiropractor",
        "type": "Services"
      }
    ],
    "sg:phone": "+1 614 885 4480",
    "sg:postcode": "43214",
    "sg:province": "OH",
    "wof:name": "Keller Chiropractic",
    "wof:placetype": "venue"
  },
  "geometry": {"coordinates":[-83.00821,40.062061],"type":"Point"}
}
