{
  "type": "Feature",
  "properties": {
    "iso:country":"US",
    "sg:address":"422 Morse Rd",
    "sg:city":"Columbus",
    "sg:classifiers":[
        {
            "category":"Health Services",
            "subcategory":"Chiropractor",
            "type":"Services"
        }
    ],
    "sg:phone":"+1 614 885 4480",
    "sg:postcode":"43214",
    "sg:province":"OH",
    "wof:name":"Keller Chiropractic",
    "wof:placetype":"venue"
},
  "geometry": {"coordinates":[-83.00821000000001,40.062061],"type":"Point"}
}