{
  "type": "Feature",
  "properties": {
    "addr:full":"24400 Highpoint Rd Cleveland OH 44122",
    "addr:housenumber":"24400",
    "addr:postcode":"44122",
    "addr:street":"Highpoint Rd",
    "iso:country":"US",
    "sg:address":"24400 Highpoint Rd",
    "sg:city":"Cleveland",
    "sg:classifiers":[
        {
            "category":"Professional",
            "subcategory":"Management & Consulting",
            "type":"Services"
        }
    ],
    "sg:phone":"+1 216 831 3011",
    "sg:postcode":"44122",
    "sg:province":"OH",
    "sg:tags":[
        "consultant",
        "business"
    ],
    "wof:name":"Le Grand Mc Hale Advertising",
    "wof:placetype":"venue"
},
  "geometry": {"coordinates":[-81.50335099999999,41.458269],"type":"Point"}
}