{
  "type": "Feature",
  "properties": {
    "iso:country":"US",
    "sg:address":"250 N Fair Ave",
    "sg:city":"Hamilton",
    "sg:classifiers":[
        {
            "category":"Organizations",
            "subcategory":"Membership Organization",
            "type":"Services"
        }
    ],
    "sg:phone":"+1 513 894 0811",
    "sg:postcode":"45011",
    "sg:province":"OH",
    "sg:tags":[
        "athletic"
    ],
    "wof:name":"North End Baseball Assn",
    "wof:placetype":"venue"
},
  "geometry": {"coordinates":[-84.54132799999999,39.397428],"type":"Point"}
}