{
  "type": "Feature",
  "properties": {
    "addr:full": "5011 Reform Rd NE Newark OH 43055",
    "addr:postcode": "5011;43055",
    "addr:street": "Reform Rd Ne",
    "iso:country": "US",
    "sg:address": "5011 Reform Rd NE",
    "sg:city": "Newark",
    "sg:classifiers": [
      {
        "category": "Farming",
        "subcategory": "Farm",
        "type": "Manufacturing \u0026 Wholesale Goods"
      }
    ],
    "sg:phone": "+1 740 763 3492",
    "sg:postcode": "43055",
    "sg:province": "OH",
    "sg:tags": [
      "crop",
      "general"
    ],
    "wof:name": "Eibest Farms LLC",
    "wof:placetype": "venue"
  },
  "geometry": {"coordinates":[-82.250688,40.131358],"type":"Point"}
}
