{
  "type": "Feature",
  "properties": {
    "addr:full": "17617 Detroit Ave Cleveland OH 44107",
    "addr:housenumber": "17617",
    "addr:postcode": "44107",
    "addr:street": "Detroit Ave",
    "iso:country": "US",
    "sg:address": "17617 Detroit Ave",
    "sg:city": "Cleveland",
    "sg:classifiers": [
      {
        "category": "Personal",
        "subcategory": "Beauty Salon",
        "type": "Services"
      }
    ],
    "sg:phone": "+1 216 228 9677",
    "sg:postcode": "44107",
    "sg:province": "OH",
    "sg:tags": [
      "spa",
      "day"
    ],
    "sg:website": "www.reaglebeagle.net",
    "wof:name": "Reagle Beagle Inc",
    "wof:placetype": "venue"
  },
  "geometry": {"coordinates":[-81.819368,41.484805],"type":"Point"}
}
