{
  "type": "Feature",
  "properties": {
    "iso:country":"US",
    "sg:address":"204 Taylor Blvd",
    "sg:city":"Lagrange",
    "sg:classifiers":[
        {
            "category":"Utilities",
            "subcategory":"Telephone",
            "type":"Services"
        }
    ],
    "sg:phone":"+1 440 355 5552",
    "sg:postcode":"44050",
    "sg:province":"OH",
    "sg:tags":[
        "internet",
        "provider"
    ],
    "wof:name":"Teleconnections",
    "wof:placetype":"venue"
},
  "geometry": {"coordinates":[-82.11868200000001,41.242249],"type":"Point"}
}