{
  "type": "Feature",
  "properties": {
    "iso:country":"US",
    "sg:address":"7879 Auburn Rd",
    "sg:city":"Painesville",
    "sg:classifiers":[
        {
            "category":"Health Services",
            "subcategory":"Doctor",
            "type":"Services"
        }
    ],
    "sg:phone":"+1 440 639 6550",
    "sg:postcode":"44077",
    "sg:province":"OH",
    "sg:tags":[
        "physician",
        "surgeon"
    ],
    "wof:name":"Neurological Associates-Lk Co",
    "wof:placetype":"venue"
},
  "geometry": {"coordinates":[-81.243478,41.653557],"type":"Point"}
}