{
  "type": "Feature",
  "properties": {
    "iso:country":"US",
    "sg:address":"5623 Eastman Dr",
    "sg:city":"Lorain",
    "sg:classifiers":[
        {
            "category":"Arts & Performance",
            "subcategory":"Theater",
            "type":"Entertainment"
        }
    ],
    "sg:phone":"+1 440 282 1978",
    "sg:postcode":"44053",
    "sg:province":"OH",
    "sg:tags":[
        "live",
        "music"
    ],
    "wof:name":"Colorful Sounds DJ Svc",
    "wof:placetype":"venue"
},
  "geometry": {"coordinates":[-82.207816,41.422724],"type":"Point"}
}