{
  "type": "Feature",
  "properties": {
    "addr:full": "5623 Eastman Dr Lorain OH 44053",
    "addr:housenumber": "5623",
    "addr:postcode": "44053",
    "addr:street": "Eastman Dr",
    "iso:country": "US",
    "sg:address": "5623 Eastman Dr",
    "sg:city": "Lorain",
    "sg:classifiers": [
      {
        "category": "Arts \u0026 Performance",
        "subcategory": "Theater",
        "type": "Entertainment"
      }
    ],
    "sg:phone": "+1 440 282 1978",
    "sg:postcode": "44053",
    "sg:province": "OH",
    "sg:tags": [
      "live",
      "music"
    ],
    "wof:name": "Colorful Sounds DJ Svc",
    "wof:placetype": "venue"
  },
  "geometry": {"coordinates":[-82.207816,41.422724],"type":"Point"}
}
