{
  "type": "Feature",
  "properties": {
    "iso:country":"US",
    "sg:address":"550 Hyatt Ln",
    "sg:city":"Toledo",
    "sg:classifiers":[
        {
            "category":"Shopping",
            "subcategory":"Clothing, Apparel, & Fashions",
            "type":"Retail Goods"
        }
    ],
    "sg:phone":"+1 419 244 2303",
    "sg:postcode":"43604",
    "sg:province":"OH",
    "sg:tags":[
        "item",
        "boutique"
    ],
    "wof:name":"Dana's Boutique",
    "wof:placetype":"venue"
},
  "geometry": {"coordinates":[-83.552308,41.644891],"type":"Point"}
}