{
  "type": "Feature",
  "properties": {
    "iso:country":"US",
    "sg:address":"1225 Woodlawn Ave",
    "sg:city":"Cambridge",
    "sg:classifiers":[
        {
            "category":"Government",
            "subcategory":"Office",
            "type":"Public Place"
        }
    ],
    "sg:phone":"+1 740 435 9922",
    "sg:postcode":"43725",
    "sg:province":"OH",
    "sg:tags":[
        "armed",
        "force",
        "recruiting"
    ],
    "wof:name":"Marine Corp Recruiting Station",
    "wof:placetype":"venue"
},
  "geometry": {"coordinates":[-81.582265,40.011911],"type":"Point"}
}