{
  "type": "Feature",
  "properties": {
    "addr:full": "917 Locust Corner Rd Cincinnati OH 45245",
    "addr:housenumber": "917",
    "addr:postcode": "45245",
    "addr:street": "Locust Corner Rd",
    "iso:country": "US",
    "sg:address": "917 Locust Corner Rd",
    "sg:city": "Cincinnati",
    "sg:classifiers": [
      {
        "category": "Place Of Worship",
        "subcategory": "Church",
        "type": "Public Place"
      },
      {
        "category": "Place Of Worship",
        "type": "Public Place"
      }
    ],
    "sg:phone": "+1 513 752 8459",
    "sg:postcode": "45245",
    "sg:province": "OH",
    "sg:tags": [
      "churches-methodist"
    ],
    "wof:name": "Locust Corner United Meth Chur",
    "wof:placetype": "venue"
  },
  "geometry": {"coordinates":[-84.275666,39.024343],"type":"Point"}
}
