{
  "type": "Feature",
  "properties": {
    "addr:full":"4048 Erie St Willoughby OH 44094",
    "addr:housenumber":"4048",
    "addr:postcode":"44094",
    "addr:street":"Erie St",
    "iso:country":"US",
    "sg:address":"4048 Erie St",
    "sg:city":"Willoughby",
    "sg:classifiers":[
        {
            "category":"Restaurant",
            "type":"Food & Drink"
        }
    ],
    "sg:phone":"+1 440 942 7646",
    "sg:postcode":"44094",
    "sg:province":"OH",
    "wof:name":"Kleifeldf Restaurant",
    "wof:placetype":"venue"
},
  "geometry": {"coordinates":[-81.406657,41.640554],"type":"Point"}
}