{
  "type": "Feature",
  "properties": {
    "iso:country":"US",
    "sg:address":"11 Buttles Ave",
    "sg:city":"Columbus",
    "sg:classifiers":[
        {
            "category":"Social Services",
            "type":"Services"
        }
    ],
    "sg:phone":"+1 614 228 7275",
    "sg:postcode":"43215",
    "sg:province":"OH",
    "sg:tags":[
        "counselor",
        "marriage",
        "family"
    ],
    "wof:name":"Counseling At Goodale Park",
    "wof:placetype":"venue"
},
  "geometry": {"coordinates":[-83.004105,39.977114],"type":"Point"}
}