{
  "type": "Feature",
  "properties": {
    "addr:full":"6850 Ridge Rd Cleveland OH 44129",
    "addr:housenumber":"6850",
    "addr:postcode":"44129",
    "addr:street":"Ridge Rd",
    "iso:country":"US",
    "sg:address":"6850 Ridge Rd",
    "sg:city":"Cleveland",
    "sg:classifiers":[
        {
            "category":"Coffee & Tea",
            "type":"Food & Drink"
        }
    ],
    "sg:menulink":"http://www.allmenus.com/oh/parma/124858-starbucks-coffee/menu/",
    "sg:phone":"+1 440 842 9001",
    "sg:postcode":"44129",
    "sg:province":"OH",
    "sg:tags":[
        "american"
    ],
    "wof:name":"Starbucks Coffee",
    "wof:placetype":"venue"
},
  "geometry": {"coordinates":[-81.734707,41.378453],"type":"Point"}
}