{
  "type": "Feature",
  "properties": {
    "addr:full": "6900 Tylersville Rd Ste B Mason OH 45040",
    "addr:housenumber": "6900",
    "addr:postcode": "45040",
    "addr:street": "Tylersville Rd Ste B",
    "iso:country": "US",
    "sg:address": "6900 Tylersville Rd Ste B",
    "sg:city": "Mason",
    "sg:classifiers": [
      {
        "category": "Professional",
        "subcategory": "Lawyer \u0026 Legal Services",
        "type": "Services"
      }
    ],
    "sg:phone": "+1 513 336 6363",
    "sg:postcode": "45040",
    "sg:province": "OH",
    "sg:tags": [
      "attorney",
      "partnership",
      "business",
      "corporation",
      "practice",
      "law"
    ],
    "sg:website": "http://www.mfitton.com",
    "wof:name": "Millikin \u0026 Fitton Law Firm",
    "wof:placetype": "venue"
  },
  "geometry": {"coordinates":[-84.347764,39.351822],"type":"Point"}
}
