{
  "type": "Feature",
  "properties": {
    "iso:country":"US",
    "sg:address":"145 E Southern Ave",
    "sg:city":"Bucyrus",
    "sg:classifiers":[
        {
            "category":"Professional",
            "type":"Services"
        }
    ],
    "sg:phone":"+1 419 562 7322",
    "sg:postcode":"44820",
    "sg:province":"OH",
    "sg:tags":[
        "establishment"
    ],
    "wof:name":"Broken Arrow Inc",
    "wof:placetype":"venue"
},
  "geometry": {"coordinates":[-82.975437,40.797359],"type":"Point"}
}