{
  "type": "Feature",
  "properties": {
    "addr:full":"6101 Busch Blvd Columbus OH 43229",
    "addr:housenumber":"6101",
    "addr:postcode":"43229",
    "addr:street":"Busch Blvd",
    "iso:country":"US",
    "sg:address":"6101 Busch Blvd",
    "sg:city":"Columbus",
    "sg:classifiers":[
        {
            "category":"Retail",
            "subcategory":"Repair Shop",
            "type":"Services"
        }
    ],
    "sg:phone":"+1 614 433 9304",
    "sg:postcode":"43229",
    "sg:province":"OH",
    "sg:tags":[
        "lock",
        "locksmith"
    ],
    "wof:name":"AAA 24 Hour Emergency",
    "wof:placetype":"venue"
},
  "geometry": {"coordinates":[-82.99374299999999,40.093883],"type":"Point"}
}