{
  "type": "Feature",
  "properties": {
    "addr:full":"4665 Cornell Rd Cincinnati OH 45241",
    "addr:housenumber":"4665",
    "addr:postcode":"45241",
    "addr:street":"Cornell Rd",
    "iso:country":"US",
    "sg:address":"4665 Cornell Rd",
    "sg:city":"Cincinnati",
    "sg:classifiers":[
        {
            "category":"Health Services",
            "subcategory":"Clinic",
            "type":"Services"
        }
    ],
    "sg:phone":"+1 513 469 0068",
    "sg:postcode":"45241",
    "sg:province":"OH",
    "sg:tags":[
        "specialty",
        "outpatient"
    ],
    "wof:name":"Medical Alliance",
    "wof:placetype":"venue"
},
  "geometry": {"coordinates":[-84.377527,39.270406],"type":"Point"}
}