{
  "type": "Feature",
  "properties": {
    "iso:country":"US",
    "sg:address":"14547 State Rte 66",
    "sg:city":"Defiance",
    "sg:classifiers":[
        {
            "category":"Education",
            "subcategory":"Dance Studio",
            "type":"Public Place"
        }
    ],
    "sg:phone":"+1 419 393 2622",
    "sg:postcode":"43512",
    "sg:province":"OH",
    "wof:name":"Defiance Dance Studio",
    "wof:placetype":"venue"
},
  "geometry": {"coordinates":[-84.361049,41.230155],"type":"Point"}
}