{
  "type": "Feature",
  "properties": {
    "addr:full":"115 S Main St North Baltimore OH 45872",
    "addr:housenumber":"115",
    "addr:postcode":"45872",
    "addr:street":"S Main St",
    "iso:country":"US",
    "sg:address":"115 S Main St",
    "sg:city":"North Baltimore",
    "sg:classifiers":[
        {
            "category":"Personal",
            "subcategory":"Barber",
            "type":"Services"
        }
    ],
    "sg:phone":"+1 419 257 2257",
    "sg:postcode":"45872",
    "sg:province":"OH",
    "wof:name":"Don's Barber Shop",
    "wof:placetype":"venue"
},
  "geometry": {"coordinates":[-83.67826700000001,41.180801],"type":"Point"}
}