{
  "type": "Feature",
  "properties": {
    "iso:country":"US",
    "sg:address":"115 S Main St",
    "sg:city":"North Baltimore",
    "sg:classifiers":[
        {
            "category":"Personal",
            "subcategory":"Barber",
            "type":"Services"
        }
    ],
    "sg:phone":"+1 419 257 2257",
    "sg:postcode":"45872",
    "sg:province":"OH",
    "wof:name":"Don's Barber Shop",
    "wof:placetype":"venue"
},
  "geometry": {"coordinates":[-83.678267,41.180801],"type":"Point"}
}