{
  "type": "Feature",
  "properties": {
    "addr:full": "250 2nd Ave Gallipolis OH 45631",
    "addr:housenumber": "250",
    "addr:postcode": "45631",
    "addr:street": "2Nd Ave",
    "iso:country": "US",
    "sg:address": "250 2nd Ave",
    "sg:city": "Gallipolis",
    "sg:classifiers": [
      {
        "category": "Personal",
        "subcategory": "Tattoo Parlor",
        "type": "Services"
      }
    ],
    "sg:phone": "+1 740 441 8287",
    "sg:postcode": "45631",
    "sg:province": "OH",
    "sg:tags": [
      "tattooing"
    ],
    "wof:name": "Temple Tattoo \u0026 Body Piercing",
    "wof:placetype": "venue"
  },
  "geometry": {"coordinates":[-82.208219,38.805954],"type":"Point"}
}
