{
  "type": "Feature",
  "properties": {
    "addr:full":"1199 East St Fairport Harbor OH 44077",
    "addr:housenumber":"1199",
    "addr:postcode":"44077",
    "addr:street":"East St",
    "iso:country":"US",
    "sg:address":"1199 East St",
    "sg:city":"Fairport Harbor",
    "sg:classifiers":[
        {
            "category":"Retail",
            "subcategory":"Auto Repair",
            "type":"Services"
        }
    ],
    "sg:phone":"+1 440 357 5814",
    "sg:postcode":"44077",
    "sg:province":"OH",
    "sg:tags":[
        "body",
        "automobile",
        "painting"
    ],
    "wof:name":"Jeff's Garage",
    "wof:placetype":"venue"
},
  "geometry": {"coordinates":[-81.268441,41.73949],"type":"Point"}
}