{
  "type": "Feature",
  "properties": {
    "addr:full":"3980 Hamilton Cleves Rd Hamilton OH 45013",
    "addr:housenumber":"3980",
    "addr:postcode":"45013",
    "addr:street":"Cleves Rd",
    "iso:country":"US",
    "sg:address":"3980 Hamilton Cleves Rd",
    "sg:city":"Hamilton",
    "sg:classifiers":[
        {
            "category":"Education",
            "subcategory":"School",
            "type":"Public Place"
        }
    ],
    "sg:phone":"+1 513 738 1972",
    "sg:postcode":"45013",
    "sg:province":"OH",
    "sg:website":"www.rosd.k12.oh.us",
    "wof:name":"Elda Elementary School",
    "wof:placetype":"venue"
},
  "geometry": {"coordinates":[-84.64188,39.319512],"type":"Point"}
}