{
  "type": "Feature",
  "properties": {
    "iso:country":"US",
    "sg:address":"5685 Springdale Rd",
    "sg:city":"Cincinnati",
    "sg:classifiers":[
        {
            "category":"Cinema",
            "subcategory":"Movie Rental",
            "type":"Entertainment"
        }
    ],
    "sg:phone":"+1 513 923 9559",
    "sg:postcode":"45251",
    "sg:province":"OH",
    "sg:tags":[
        "leasing",
        "video",
        "disc",
        "tape"
    ],
    "wof:name":"Video Village",
    "wof:placetype":"venue"
},
  "geometry": {"coordinates":[-84.627613,39.233338],"type":"Point"}
}