{
  "type": "Feature",
  "properties": {
    "addr:full":"5876 Youngstown Warren Rd Niles OH 44446",
    "addr:housenumber":"5876",
    "addr:postcode":"44446",
    "addr:street":"Youngstown Warren Rd",
    "iso:country":"US",
    "sg:address":"5876 Youngstown Warren Rd",
    "sg:city":"Niles",
    "sg:classifiers":[
        {
            "category":"Utilities",
            "subcategory":"Mobile Phone",
            "type":"Services"
        }
    ],
    "sg:phone":"+1 330 544 8239",
    "sg:postcode":"44446",
    "sg:province":"OH",
    "sg:tags":[
        "telephone",
        "cellular"
    ],
    "wof:name":"Revol Dealer",
    "wof:placetype":"venue"
},
  "geometry": {"coordinates":[-80.74358599999999,41.207662],"type":"Point"}
}