{
  "type": "Feature",
  "properties": {
    "addr:full": "4940 N Ridge Rd Perry OH 44081",
    "addr:housenumber": "4940",
    "addr:postcode": "44081",
    "addr:street": "N Ridge Rd",
    "iso:country": "US",
    "sg:address": "4940 N Ridge Rd",
    "sg:city": "Perry",
    "sg:classifiers": [
      {
        "category": "Food \u0026 Beverages",
        "subcategory": "Fruits \u0026 Vegetables",
        "type": "Retail Goods"
      }
    ],
    "sg:phone": "+1 440 259 3487",
    "sg:postcode": "44081",
    "sg:province": "OH",
    "sg:tags": [
      "produce"
    ],
    "wof:name": "Secor's Nurseries \u0026 Fruit Mkt",
    "wof:placetype": "venue"
  },
  "geometry": {"coordinates":[-81.112558,41.789902],"type":"Point"}
}
