{
  "type": "Feature",
  "properties": {
    "iso:country":"US",
    "sg:address":"4940 N Ridge Rd",
    "sg:city":"Perry",
    "sg:classifiers":[
        {
            "category":"Food & Beverages",
            "subcategory":"Fruits & Vegetables",
            "type":"Retail Goods"
        }
    ],
    "sg:phone":"+1 440 259 3487",
    "sg:postcode":"44081",
    "sg:province":"OH",
    "sg:tags":[
        "produce"
    ],
    "wof:name":"Secor's Nurseries & Fruit Mkt",
    "wof:placetype":"venue"
},
  "geometry": {"coordinates":[-81.11255800000001,41.789902],"type":"Point"}
}