{
  "type": "Feature",
  "properties": {
    "addr:full":"4251 Kimberly Pkwy N Columbus OH 43232",
    "addr:housenumber":"4251",
    "addr:postcode":"43232",
    "addr:street":"Kimberly Pkwy N",
    "iso:country":"US",
    "sg:address":"4251 Kimberly Pkwy N",
    "sg:city":"Columbus",
    "sg:classifiers":[
        {
            "category":"Food & Beverages",
            "subcategory":"Groceries & Convenience Stores",
            "type":"Retail Goods"
        }
    ],
    "sg:phone":"+1 614 868 8736",
    "sg:postcode":"43232",
    "sg:province":"OH",
    "sg:tags":[
        "station",
        "gasoline"
    ],
    "wof:name":"Dairy Mart Convenience Store",
    "wof:placetype":"venue"
},
  "geometry": {"coordinates":[-82.888085,39.925528],"type":"Point"}
}