{
  "type": "Feature",
  "properties": {
    "iso:country":"US",
    "sg:address":"3841 Panhandle Rd",
    "sg:city":"Lynchburg",
    "sg:classifiers":[
        {
            "category":"Wholesale",
            "subcategory":"Farm Supplies",
            "type":"Manufacturing & Wholesale Goods"
        }
    ],
    "sg:phone":"+1 937 364 1022",
    "sg:postcode":"45142",
    "sg:province":"OH",
    "sg:tags":[
        "equipment",
        "kennel"
    ],
    "wof:name":"Happy Tails Pet Boarding",
    "wof:placetype":"venue"
},
  "geometry": {"coordinates":[-83.74664900000001,39.267863],"type":"Point"}
}