{
  "type": "Feature",
  "properties": {
    "addr:full":"2400 Olentangy River Rd Columbus OH 43202",
    "addr:housenumber":"2400",
    "addr:postcode":"43202",
    "addr:street":"Olentangy River Rd",
    "iso:country":"US",
    "sg:address":"2400 Olentangy River Rd",
    "sg:city":"Columbus",
    "sg:classifiers":[
        {
            "category":"Education",
            "subcategory":"College",
            "type":"Public Place"
        }
    ],
    "sg:phone":"+1 614 292 2141",
    "sg:postcode":"43202",
    "sg:province":"OH",
    "sg:tags":[
        "academic",
        "school"
    ],
    "sg:website":"www.alumni-osu.org",
    "wof:name":"Ohio State University",
    "wof:placetype":"venue"
},
  "geometry": {"coordinates":[-83.022192,40.010814],"type":"Point"}
}