{
  "type": "Feature",
  "properties": {
    "addr:full":"1065 Ohio Pike Cincinnati OH 45245",
    "addr:housenumber":"1065",
    "addr:postcode":"45245",
    "addr:street":"Ohio Pike",
    "iso:country":"US",
    "sg:address":"1065 Ohio Pike",
    "sg:city":"Cincinnati",
    "sg:classifiers":[
        {
            "category":"Autos & Motor Vehicles",
            "subcategory":"Automobile Sales",
            "type":"Retail Goods"
        },
        {
            "category":"Retail",
            "subcategory":"Auto Repair",
            "type":"Services"
        }
    ],
    "sg:phone":"+1 513 752 1804",
    "sg:postcode":"45245",
    "sg:province":"OH",
    "sg:tags":[
        "body",
        "shop",
        "car"
    ],
    "sg:website":"www.dodge.com",
    "wof:name":"Kidd Joe Dodge Inc",
    "wof:placetype":"venue"
},
  "geometry": {"coordinates":[-84.2621,39.0578],"type":"Point"}
}