{
  "type": "Feature",
  "properties": {
    "iso:country":"US",
    "sg:address":"2576 Ashton Rd",
    "sg:city":"Cleveland",
    "sg:classifiers":[
        {
            "category":"Education",
            "subcategory":"Special Training",
            "type":"Public Place"
        }
    ],
    "sg:phone":"+1 216 932 5016",
    "sg:postcode":"44118",
    "sg:province":"OH",
    "sg:tags":[
        "self",
        "motivational",
        "improvement"
    ],
    "sg:website":"www.marriagemovement.com",
    "wof:name":"Marriage Movement",
    "wof:placetype":"venue"
},
  "geometry": {"coordinates":[-81.559803,41.486871],"type":"Point"}
}