{
  "type": "Feature",
  "properties": {
    "iso:country":"US",
    "sg:address":"3580 Poe Rd",
    "sg:city":"Medina",
    "sg:classifiers":[
        {
            "category":"Shopping",
            "subcategory":"Computers & Home Electronics",
            "type":"Retail Goods"
        }
    ],
    "sg:phone":"+1 330 723 3295",
    "sg:postcode":"44256",
    "sg:province":"OH",
    "wof:name":"North Coast Dynamics",
    "wof:placetype":"venue"
},
  "geometry": {"coordinates":[-81.814533,41.091496],"type":"Point"}
}