{
  "type": "Feature",
  "properties": {
    "iso:country":"US",
    "sg:address":"1100 Walnut St",
    "sg:city":"Coshocton",
    "sg:classifiers":[
        {
            "category":"Banks & Credit Unions",
            "subcategory":"Bank",
            "type":"Services"
        }
    ],
    "sg:phone":"+1 740 622 9089",
    "sg:postcode":"43812",
    "sg:province":"OH",
    "wof:name":"Ohio Heritage Bank",
    "wof:placetype":"venue"
},
  "geometry": {"coordinates":[-81.853568,40.271817],"type":"Point"}
}