{
  "type": "Feature",
  "properties": {
    "addr:full": "7777 Newcomb Dr Cleveland OH 44129",
    "addr:housenumber": "7777",
    "addr:postcode": "44129",
    "addr:street": "Newcomb Dr",
    "iso:country": "US",
    "sg:address": "7777 Newcomb Dr",
    "sg:city": "Cleveland",
    "sg:classifiers": [
      {
        "category": "Building \u0026 Trades",
        "subcategory": "Construction",
        "type": "Services"
      }
    ],
    "sg:phone": "+1 440 845 8276",
    "sg:postcode": "44129",
    "sg:province": "OH",
    "sg:tags": [
      "painter"
    ],
    "wof:name": "Apollon Painting Co",
    "wof:placetype": "venue"
  },
  "geometry": {"coordinates":[-81.739444,41.375629],"type":"Point"}
}
