{
  "type": "Feature",
  "properties": {
    "addr:full":"6079 Hillgrove-Southern Rd Greenville OH 45331",
    "addr:housenumber":"6079",
    "addr:postcode":"45331",
    "addr:street":"Hillgrove-Southern Rd",
    "iso:country":"US",
    "sg:address":"6079 Hillgrove-Southern Rd",
    "sg:city":"Greenville",
    "sg:classifiers":[
        {
            "category":"Retail",
            "subcategory":"Repair Shop",
            "type":"Services"
        }
    ],
    "sg:phone":"+1 937 547 1239",
    "sg:postcode":"45331",
    "sg:province":"OH",
    "sg:tags":[
        "sporting"
    ],
    "wof:name":"Nashville Gun",
    "wof:placetype":"venue"
},
  "geometry": {"coordinates":[-84.77089599999999,40.093702],"type":"Point"}
}