{
  "type": "Feature",
  "properties": {
    "addr:full": "2844 US Hwy 23 Portsmouth OH 45662",
    "addr:housenumber": "2844",
    "addr:postcode": "45662",
    "addr:street": "Us Hwy 23",
    "iso:country": "US",
    "sg:address": "2844 US Hwy 23",
    "sg:city": "Portsmouth",
    "sg:classifiers": [
      {
        "category": "Restaurant",
        "type": "Food \u0026 Drink"
      }
    ],
    "sg:phone": "+1 740 355 1226",
    "sg:postcode": "45662",
    "sg:province": "OH",
    "sg:tags": [
      "eating"
    ],
    "wof:name": "Renos Roadhouse",
    "wof:placetype": "venue"
  },
  "geometry": {"coordinates":[-82.990857,38.757512],"type":"Point"}
}
