{
  "type": "Feature",
  "properties": {
    "iso:country":"US",
    "sg:address":"98 N Paint St",
    "sg:city":"Chillicothe",
    "sg:classifiers":[
        {
            "category":"Shopping",
            "subcategory":"Clothing, Apparel, & Fashions",
            "type":"Retail Goods"
        }
    ],
    "sg:phone":"+1 740 773 8423",
    "sg:postcode":"45601",
    "sg:province":"OH",
    "wof:name":"Vibe",
    "wof:placetype":"venue"
},
  "geometry": {"coordinates":[-82.982545,39.334608],"type":"Point"}
}