{
  "type": "Feature",
  "properties": {
    "addr:full":"309 East St Gordon OH 45304",
    "addr:housenumber":"309",
    "addr:postcode":"45304",
    "addr:street":"East St",
    "iso:country":"US",
    "sg:address":"309 East St",
    "sg:city":"Gordon",
    "sg:classifiers":[
        {
            "category":"Organizations",
            "subcategory":"Religious Organization",
            "type":"Services"
        }
    ],
    "sg:phone":"+1 937 884 5127",
    "sg:postcode":"45304",
    "sg:province":"OH",
    "sg:tags":[
        "clergy"
    ],
    "wof:name":"David Hood",
    "wof:placetype":"venue"
},
  "geometry": {"coordinates":[-84.507431,39.93055],"type":"Point"}
}