{
  "type": "Feature",
  "properties": {
    "addr:full": "5268 Fisher Corinth Rd Farmdale OH 44417",
    "addr:housenumber": "5268",
    "addr:postcode": "44417",
    "addr:street": "Fisher Corinth Rd",
    "iso:country": "US",
    "sg:address": "5268 Fisher Corinth Rd",
    "sg:city": "Farmdale",
    "sg:classifiers": [
      {
        "category": "Building \u0026 Trades",
        "subcategory": "Construction",
        "type": "Services"
      }
    ],
    "sg:phone": "+1 330 924 2484",
    "sg:postcode": "44417",
    "sg:province": "OH",
    "sg:tags": [
      "contractor"
    ],
    "wof:name": "Ed Sandblasting \u0026 Paint",
    "wof:placetype": "venue"
  },
  "geometry": {"coordinates":[-80.648811,41.412656],"type":"Point"}
}
