{
  "type": "Feature",
  "properties": {
    "iso:country":"US",
    "sg:address":"1240 E 55th St",
    "sg:city":"Cleveland",
    "sg:classifiers":[
        {
            "category":"Shopping",
            "subcategory":"Department Store",
            "type":"Retail Goods"
        }
    ],
    "sg:phone":"+1 216 432 0421",
    "sg:postcode":"44103",
    "sg:province":"OH",
    "sg:tags":[
        "shop"
    ],
    "wof:name":"United Discount",
    "wof:placetype":"venue"
},
  "geometry": {"coordinates":[-81.65202600000001,41.526182],"type":"Point"}
}