{
  "type": "Feature",
  "properties": {
    "addr:full": "20 Danielle Dr Newark OH 43055",
    "addr:housenumber": "20",
    "addr:postcode": "43055",
    "addr:street": "Danielle Dr",
    "iso:country": "US",
    "sg:address": "20 Danielle Dr",
    "sg:city": "Newark",
    "sg:classifiers": [
      {
        "category": "Building \u0026 Trades",
        "subcategory": "Landscaping Services",
        "type": "Services"
      }
    ],
    "sg:phone": "+1 740 364 9187",
    "sg:postcode": "43055",
    "sg:province": "OH",
    "sg:tags": [
      "tree"
    ],
    "wof:name": "Boyd's Tree Svc",
    "wof:placetype": "venue"
  },
  "geometry": {"coordinates":[-82.426774,40.102607],"type":"Point"}
}
