{
  "type": "Feature",
  "properties": {
    "iso:country":"US",
    "sg:address":"20 Danielle Dr",
    "sg:city":"Newark",
    "sg:classifiers":[
        {
            "category":"Building & Trades",
            "subcategory":"Landscaping Services",
            "type":"Services"
        }
    ],
    "sg:phone":"+1 740 364 9187",
    "sg:postcode":"43055",
    "sg:province":"OH",
    "sg:tags":[
        "tree"
    ],
    "wof:name":"Boyd's Tree Svc",
    "wof:placetype":"venue"
},
  "geometry": {"coordinates":[-82.42677399999999,40.102607],"type":"Point"}
}