{
  "type": "Feature",
  "properties": {
    "addr:full": "9107 Pleasantwood Ave NW Canton OH 44720",
    "addr:housenumber": "9107",
    "addr:postcode": "44720",
    "addr:street": "Pleasantwood Ave Nw",
    "iso:country": "US",
    "sg:address": "9107 Pleasantwood Ave NW",
    "sg:city": "Canton",
    "sg:classifiers": [
      {
        "category": "Manufacturing",
        "subcategory": "Tools \u0026 Machinery",
        "type": "Manufacturing \u0026 Wholesale Goods"
      }
    ],
    "sg:phone": "+1 330 499 4913",
    "sg:postcode": "44720",
    "sg:province": "OH",
    "sg:tags": [
      "metal",
      "mfg",
      "foundry",
      "m",
      "nonferrous"
    ],
    "wof:name": "Parr-Green Mold \u0026 Machine Co",
    "wof:placetype": "venue"
  },
  "geometry": {"coordinates":[-81.415051,40.917354],"type":"Point"}
}
