{
  "type": "Feature",
  "properties": {
    "iso:country":"US",
    "sg:address":"23308 Mccann St",
    "sg:city":"Cleveland",
    "sg:classifiers":[
        {
            "category":"Professional",
            "subcategory":"Employment Agencies",
            "type":"Services"
        }
    ],
    "sg:phone":"+1 216 355 0383",
    "sg:postcode":"44128",
    "sg:province":"OH",
    "sg:tags":[
        "opportunity"
    ],
    "wof:name":"2ndure Professional Administrative Support Service",
    "wof:placetype":"venue"
},
  "geometry": {"coordinates":[-81.514501,41.431333],"type":"Point"}
}