{
  "type": "Feature",
  "properties": {
    "iso:country":"US",
    "sg:address":"3000 W Alex Bell Rd",
    "sg:city":"Dayton",
    "sg:classifiers":[
        {
            "category":"Food & Beverages",
            "subcategory":"Groceries & Convenience Stores",
            "type":"Retail Goods"
        }
    ],
    "sg:phone":"+1 937 439 4158",
    "sg:postcode":"45449",
    "sg:province":"OH",
    "wof:name":"Speedway 9630",
    "wof:placetype":"venue"
},
  "geometry": {"coordinates":[-84.235576,39.67441],"type":"Point"}
}