{
  "type": "Feature",
  "properties": {
    "addr:full": "3000 W Alex Bell Rd Dayton OH 45449",
    "addr:housenumber": "3000",
    "addr:postcode": "45449",
    "addr:street": "W Alex Bell Rd",
    "iso:country": "US",
    "sg:address": "3000 W Alex Bell Rd",
    "sg:city": "Dayton",
    "sg:classifiers": [
      {
        "category": "Food \u0026 Beverages",
        "subcategory": "Groceries \u0026 Convenience Stores",
        "type": "Retail Goods"
      }
    ],
    "sg:phone": "+1 937 439 4158",
    "sg:postcode": "45449",
    "sg:province": "OH",
    "wof:name": "Speedway 9630",
    "wof:placetype": "venue"
  },
  "geometry": {"coordinates":[-84.235576,39.67441],"type":"Point"}
}
