{
  "type": "Feature",
  "properties": {
    "iso:country":"US",
    "sg:address":"100 State Rte 770",
    "sg:city":"Seaman",
    "sg:classifiers":[
        {
            "category":"Restaurant",
            "type":"Food & Drink"
        }
    ],
    "sg:phone":"+1 937 386 3181",
    "sg:postcode":"45679",
    "sg:province":"OH",
    "sg:tags":[
        "parlor",
        "ice",
        "cream"
    ],
    "wof:name":"Seaman Frostee Freeze",
    "wof:placetype":"venue"
},
  "geometry": {"coordinates":[-83.568338,38.948894],"type":"Point"}
}