{
  "type": "Feature",
  "properties": {
    "addr:full":"6360 Defiance Trl Delphos OH 45833",
    "addr:housenumber":"6360",
    "addr:postcode":"45833",
    "addr:street":"Defiance Trl",
    "iso:country":"US",
    "sg:address":"6360 Defiance Trl",
    "sg:city":"Delphos",
    "sg:classifiers":[
        {
            "category":"Food & Beverages",
            "subcategory":"Specialty",
            "type":"Retail Goods"
        },
        {
            "category":"Food & Beverages",
            "subcategory":"Fruits & Vegetables",
            "type":"Retail Goods"
        }
    ],
    "sg:phone":"+1 419 692 1445",
    "sg:postcode":"45833",
    "sg:province":"OH",
    "sg:tags":[
        "farm",
        "market"
    ],
    "wof:name":"Lynn's Farm",
    "wof:placetype":"venue"
},
  "geometry": {"coordinates":[-84.286489,40.828688],"type":"Point"}
}