{
  "type": "Feature",
  "properties": {
    "addr:full": "13700 State Rd Cleveland OH 44133",
    "addr:housenumber": "13700",
    "addr:postcode": "44133",
    "addr:street": "State Rd",
    "iso:country": "US",
    "sg:address": "13700 State Rd",
    "sg:city": "Cleveland",
    "sg:classifiers": [
      {
        "category": "Professional",
        "subcategory": "Engineering",
        "type": "Services"
      }
    ],
    "sg:phone": "+1 440 582 8200",
    "sg:postcode": "44133",
    "sg:province": "OH",
    "sg:tags": [
      "engineer"
    ],
    "wof:name": "Charles A Lewis \u0026 Assoc Inc",
    "wof:placetype": "venue"
  },
  "geometry": {"coordinates":[-81.724628,41.31814],"type":"Point"}
}
