{
  "type": "Feature",
  "properties": {
    "iso:country":"US",
    "sg:address":"13700 State Rd",
    "sg:city":"Cleveland",
    "sg:classifiers":[
        {
            "category":"Professional",
            "subcategory":"Engineering",
            "type":"Services"
        }
    ],
    "sg:phone":"+1 440 582 8200",
    "sg:postcode":"44133",
    "sg:province":"OH",
    "sg:tags":[
        "engineer"
    ],
    "wof:name":"Charles A Lewis & Assoc Inc",
    "wof:placetype":"venue"
},
  "geometry": {"coordinates":[-81.724628,41.31814],"type":"Point"}
}