{
  "type": "Feature",
  "properties": {
    "iso:country":"US",
    "sg:address":"118 Lucy Dr",
    "sg:city":"Toronto",
    "sg:classifiers":[
        {
            "category":"Shopping",
            "type":"Retail Goods"
        }
    ],
    "sg:phone":"+1 740 282 0795",
    "sg:postcode":"43964",
    "sg:province":"OH",
    "sg:tags":[
        "merchandise"
    ],
    "wof:name":"Embroidery & Emporium",
    "wof:placetype":"venue"
},
  "geometry": {"coordinates":[-80.631597,40.435247],"type":"Point"}
}