{
  "type": "Feature",
  "properties": {
    "iso:country":"US",
    "sg:address":"1075 Main St",
    "sg:city":"Wellsville",
    "sg:classifiers":[
        {
            "category":"Government",
            "subcategory":"Post Office",
            "type":"Public Place"
        }
    ],
    "sg:phone":"+1 330 532 3088",
    "sg:postcode":"43968",
    "sg:province":"OH",
    "sg:tags":[
        "postal",
        "us"
    ],
    "wof:name":"US Post Office",
    "wof:placetype":"venue"
},
  "geometry": {"coordinates":[-80.64921,40.602758],"type":"Point"}
}