{
  "type": "Feature",
  "properties": {
    "iso:country":"US",
    "sg:address":"3703 Station Ave",
    "sg:city":"Ashtabula",
    "sg:classifiers":[
        {
            "category":"Education",
            "subcategory":"School",
            "type":"Public Place"
        }
    ],
    "sg:phone":"+1 440 993 2588",
    "sg:postcode":"44004",
    "sg:province":"OH",
    "wof:name":"Thurgood Marshall School",
    "wof:placetype":"venue"
},
  "geometry": {"coordinates":[-80.78947700000001,41.871553],"type":"Point"}
}