{
  "type": "Feature",
  "properties": {
    "iso:country":"US",
    "sg:address":"7471 Tyler Blvd",
    "sg:city":"Mentor",
    "sg:classifiers":[
        {
            "category":"Building & Trades",
            "subcategory":"Landscaping Services",
            "type":"Services"
        }
    ],
    "sg:phone":"+1 440 942 2400",
    "sg:postcode":"44060",
    "sg:province":"OH",
    "sg:tags":[
        "lawn",
        "maintenance",
        "grounds"
    ],
    "wof:name":"Outsiders Inc",
    "wof:placetype":"venue"
},
  "geometry": {"coordinates":[-81.374855,41.659427],"type":"Point"}
}