{
  "type": "Feature",
  "properties": {
    "iso:country":"US",
    "sg:address":"9599 Miles Rd",
    "sg:city":"La Rue",
    "sg:classifiers":[
        {
            "category":"Insurance",
            "subcategory":"Insurance Agent",
            "type":"Services"
        }
    ],
    "sg:phone":"+1 740 499 2649",
    "sg:postcode":"43332",
    "sg:province":"OH",
    "wof:name":"Rural Ohio Insurance Agency Lt",
    "wof:placetype":"venue"
},
  "geometry": {"coordinates":[-83.381438,40.65073],"type":"Point"}
}