{
  "type": "Feature",
  "properties": {
    "addr:full":"3037 Long Rd Centerburg OH 43011",
    "addr:housenumber":"3037",
    "addr:postcode":"43011",
    "addr:street":"Long Rd",
    "iso:country":"US",
    "sg:address":"3037 Long Rd",
    "sg:city":"Centerburg",
    "sg:classifiers":[
        {
            "category":"Farming",
            "subcategory":"Livestock Farm",
            "type":"Manufacturing & Wholesale Goods"
        }
    ],
    "sg:phone":"+1 740 625 6372",
    "sg:postcode":"43011",
    "sg:province":"OH",
    "sg:tags":[
        "feedlot",
        "hog",
        "or",
        "beef",
        "cattle"
    ],
    "wof:name":"Douglas Mulpas",
    "wof:placetype":"venue"
},
  "geometry": {"coordinates":[-82.713615,40.339231],"type":"Point"}
}