{
  "type": "Feature",
  "properties": {
    "addr:full": "2700 W 3rd St Cleveland OH 44113",
    "addr:housenumber": "2700",
    "addr:postcode": "44113",
    "addr:street": "W 3Rd St",
    "iso:country": "US",
    "sg:address": "2700 W 3rd St",
    "sg:city": "Cleveland",
    "sg:classifiers": [
      {
        "category": "Freight",
        "type": "Transportation"
      }
    ],
    "sg:phone": "+1 216 231 1807",
    "sg:postcode": "44113",
    "sg:province": "OH",
    "sg:tags": [
      "transfer",
      "rail",
      "truck",
      "to"
    ],
    "wof:name": "CSX Transportation",
    "wof:placetype": "venue"
  },
  "geometry": {"coordinates":[-81.675017,41.475682],"type":"Point"}
}
