{
  "type": "Feature",
  "properties": {
    "addr:full":"52 S Meridian Rd Youngstown OH 44509",
    "addr:housenumber":"52",
    "addr:postcode":"44509",
    "addr:street":"S Meridian Rd",
    "iso:country":"US",
    "sg:address":"52 S Meridian Rd",
    "sg:city":"Youngstown",
    "sg:classifiers":[
        {
            "category":"Wholesale",
            "subcategory":"Hardware",
            "type":"Manufacturing & Wholesale Goods"
        }
    ],
    "sg:phone":"+1 330 799 6677",
    "sg:postcode":"44509",
    "sg:province":"OH",
    "sg:tags":[
        "supply",
        "heating",
        "conditioning",
        "air"
    ],
    "wof:name":"Torok Supply Company",
    "wof:placetype":"venue"
},
  "geometry": {"coordinates":[-80.71114799999999,41.099796],"type":"Point"}
}