{
  "type": "Feature",
  "properties": {
    "addr:full":"1821 Spencer St Toledo OH 43609",
    "addr:housenumber":"1821",
    "addr:postcode":"43609",
    "addr:street":"Spencer St",
    "iso:country":"US",
    "sg:address":"1821 Spencer St",
    "sg:city":"Toledo",
    "sg:classifiers":[
        {
            "category":"Manufacturing",
            "subcategory":"Printing",
            "type":"Manufacturing & Wholesale Goods"
        }
    ],
    "sg:phone":"+1 419 380 5000",
    "sg:postcode":"43609",
    "sg:province":"OH",
    "sg:tags":[
        "printer"
    ],
    "wof:name":"Proforma Specialty Printing",
    "wof:placetype":"venue"
},
  "geometry": {"coordinates":[-83.58754,41.620149],"type":"Point"}
}