{
  "type": "Feature",
  "properties": {
    "addr:full": "4305 W 229th St Cleveland OH 44126",
    "addr:housenumber": "4305",
    "addr:postcode": "44126",
    "addr:street": "W 229Th St",
    "iso:country": "US",
    "sg:address": "4305 W 229th St",
    "sg:city": "Cleveland",
    "sg:classifiers": [
      {
        "category": "Manufacturing",
        "subcategory": "Metals",
        "type": "Manufacturing \u0026 Wholesale Goods"
      }
    ],
    "sg:phone": "+1 440 779 5188",
    "sg:postcode": "44126",
    "sg:province": "OH",
    "sg:tags": [
      "machine",
      "screw",
      "product",
      "mfg"
    ],
    "wof:name": "Testo Manufacturing Inc",
    "wof:placetype": "venue"
  },
  "geometry": {"coordinates":[-81.87368,41.438329],"type":"Point"}
}
