{
  "type": "Feature",
  "properties": {
    "iso:country":"US",
    "sg:address":"13210 State Rte 29",
    "sg:city":"Conover",
    "sg:classifiers":[
        {
            "category":"Real Estate",
            "subcategory":"Real Estate Operator",
            "type":"Services"
        }
    ],
    "sg:phone":"+1 937 362 4514",
    "sg:postcode":"45317",
    "sg:province":"OH",
    "sg:tags":[
        "property",
        "lessor"
    ],
    "wof:name":"Mc Alexander Autom Farm",
    "wof:placetype":"venue"
},
  "geometry": {"coordinates":[-84.007646,40.224089],"type":"Point"}
}