{
  "type": "Feature",
  "properties": {
    "iso:country":"US",
    "sg:address":"109 E 6th St",
    "sg:city":"East Liverpool",
    "sg:classifiers":[
        {
            "category":"Manufacturing",
            "subcategory":"Printing",
            "type":"Manufacturing & Wholesale Goods"
        }
    ],
    "sg:phone":"+1 330 385 2070",
    "sg:postcode":"43920",
    "sg:province":"OH",
    "sg:tags":[
        "screen"
    ],
    "wof:name":"All-Sport Trophies & Supplies",
    "wof:placetype":"venue"
},
  "geometry": {"coordinates":[-80.578248,40.619877],"type":"Point"}
}