{
  "type": "Feature",
  "properties": {
    "addr:full": "109 E 6th St East Liverpool OH 43920",
    "addr:housenumber": "109",
    "addr:postcode": "43920",
    "addr:street": "E 6Th St",
    "iso:country": "US",
    "sg:address": "109 E 6th St",
    "sg:city": "East Liverpool",
    "sg:classifiers": [
      {
        "category": "Manufacturing",
        "subcategory": "Printing",
        "type": "Manufacturing \u0026 Wholesale Goods"
      }
    ],
    "sg:phone": "+1 330 385 2070",
    "sg:postcode": "43920",
    "sg:province": "OH",
    "sg:tags": [
      "screen"
    ],
    "wof:name": "All-Sport Trophies \u0026 Supplies",
    "wof:placetype": "venue"
  },
  "geometry": {"coordinates":[-80.578248,40.619877],"type":"Point"}
}
