{
  "type": "Feature",
  "properties": {
    "addr:full": "4159 N Holland Sylvania Ave Toledo OH 43623",
    "addr:housenumber": "4159",
    "addr:postcode": "43623",
    "addr:street": "N Holland Sylvania Ave",
    "iso:country": "US",
    "sg:address": "4159 N Holland Sylvania Ave",
    "sg:city": "Toledo",
    "sg:classifiers": [
      {
        "category": "Insurance",
        "subcategory": "Insurance Agent",
        "type": "Services"
      }
    ],
    "sg:phone": "+1 419 882 9655",
    "sg:postcode": "43623",
    "sg:province": "OH",
    "wof:name": "Dj Financial Services of",
    "wof:placetype": "venue"
  },
  "geometry": {"coordinates":[-83.687565,41.693521],"type":"Point"}
}
