{
  "type": "Feature",
  "properties": {
    "iso:country":"US",
    "sg:address":"4159 N Holland Sylvania Ave",
    "sg:city":"Toledo",
    "sg:classifiers":[
        {
            "category":"Insurance",
            "subcategory":"Insurance Agent",
            "type":"Services"
        }
    ],
    "sg:phone":"+1 419 882 9655",
    "sg:postcode":"43623",
    "sg:province":"OH",
    "wof:name":"Dj Financial Services of",
    "wof:placetype":"venue"
},
  "geometry": {"coordinates":[-83.68756500000001,41.693521],"type":"Point"}
}