{
  "type": "Feature",
  "properties": {
    "iso:country":"US",
    "sg:address":"3272 Highland Ave",
    "sg:city":"Cincinnati",
    "sg:classifiers":[
        {
            "category":"Manufacturing",
            "subcategory":"Signs",
            "type":"Manufacturing & Wholesale Goods"
        }
    ],
    "sg:phone":"+1 513 396 7446",
    "sg:postcode":"45213",
    "sg:province":"OH",
    "sg:website":"www.fastsigns.com",
    "wof:name":"Fastsigns International",
    "wof:placetype":"venue"
},
  "geometry": {"coordinates":[-84.42755099999999,39.168467],"type":"Point"}
}