{
  "type": "Feature",
  "properties": {
    "addr:full": "3272 Highland Ave Cincinnati OH 45213",
    "addr:housenumber": "3272",
    "addr:postcode": "45213",
    "addr:street": "Highland Ave",
    "iso:country": "US",
    "sg:address": "3272 Highland Ave",
    "sg:city": "Cincinnati",
    "sg:classifiers": [
      {
        "category": "Manufacturing",
        "subcategory": "Signs",
        "type": "Manufacturing \u0026 Wholesale Goods"
      }
    ],
    "sg:phone": "+1 513 396 7446",
    "sg:postcode": "45213",
    "sg:province": "OH",
    "sg:website": "www.fastsigns.com",
    "wof:name": "Fastsigns International",
    "wof:placetype": "venue"
  },
  "geometry": {"coordinates":[-84.427551,39.168467],"type":"Point"}
}
