{
  "type": "Feature",
  "properties": {
    "addr:full":"181 N 4th St Steubenville OH 43952",
    "addr:housenumber":"181",
    "addr:postcode":"43952",
    "addr:street":"N 4Th St",
    "iso:country":"US",
    "sg:address":"181 N 4th St",
    "sg:city":"Steubenville",
    "sg:classifiers":[
        {
            "category":"Professional",
            "subcategory":"Accounting & Tax Preparation",
            "type":"Services"
        }
    ],
    "sg:phone":"+1 740 283 2492",
    "sg:postcode":"43952",
    "sg:province":"OH",
    "sg:tags":[
        "return",
        "filing"
    ],
    "wof:name":"H & R Block Tax Svc",
    "wof:placetype":"venue"
},
  "geometry": {"coordinates":[-80.614778,40.360781],"type":"Point"}
}