{
  "type": "Feature",
  "properties": {
    "addr:full": "116 S Main St New Lexington OH 43764",
    "addr:housenumber": "116",
    "addr:postcode": "43764",
    "addr:street": "S Main St",
    "iso:country": "US",
    "sg:address": "116 S Main St",
    "sg:city": "New Lexington",
    "sg:classifiers": [
      {
        "category": "Professional",
        "subcategory": "Advertising",
        "type": "Services"
      }
    ],
    "sg:phone": "+1 740 342 5483",
    "sg:postcode": "43764",
    "sg:province": "OH",
    "sg:tags": [
      "counselor"
    ],
    "wof:name": "Perry Advertiser",
    "wof:placetype": "venue"
  },
  "geometry": {"coordinates":[-82.207702,39.713821],"type":"Point"}
}
