{
  "type": "Feature",
  "properties": {
    "iso:country":"US",
    "sg:address":"5252 Mayfield Rd",
    "sg:city":"Cleveland",
    "sg:classifiers":[
        {
            "category":"Retail",
            "subcategory":"Funeral Services",
            "type":"Services"
        }
    ],
    "sg:phone":"+1 440 473 6299",
    "sg:postcode":"44124",
    "sg:province":"OH",
    "sg:tags":[
        "director"
    ],
    "wof:name":"Lopresti Funeral Home",
    "wof:placetype":"venue"
},
  "geometry": {"coordinates":[-81.490004,41.519855],"type":"Point"}
}