{
  "type": "Feature",
  "properties": {
    "addr:full": "3489 S Wapak Rd Lima OH 45806",
    "addr:housenumber": "3489",
    "addr:postcode": "45806",
    "addr:street": "S Wapak Rd",
    "iso:country": "US",
    "sg:address": "3489 S Wapak Rd",
    "sg:city": "Lima",
    "sg:classifiers": [
      {
        "category": "Autos \u0026 Motor Vehicles",
        "subcategory": "Motorcycle Sales",
        "type": "Retail Goods"
      }
    ],
    "sg:phone": "+1 419 230 1731",
    "sg:postcode": "45806",
    "sg:province": "OH",
    "sg:tags": [
      "car",
      "golf",
      "cart"
    ],
    "wof:name": "Brian's Golf Carts",
    "wof:placetype": "venue"
  },
  "geometry": {"coordinates":[-84.203701,40.689467],"type":"Point"}
}
