{
  "type": "Feature",
  "properties": {
    "addr:full":"29341 Lorain Ave North Olmsted OH 44070",
    "addr:housenumber":"29341",
    "addr:postcode":"44070",
    "addr:street":"Lorain Ave",
    "iso:country":"US",
    "sg:address":"29341 Lorain Ave",
    "sg:city":"North Olmsted",
    "sg:classifiers":[
        {
            "category":"Building & Trades",
            "subcategory":"Construction",
            "type":"Services"
        }
    ],
    "sg:phone":"+1 440 777 7555",
    "sg:postcode":"44070",
    "sg:province":"OH",
    "sg:tags":[
        "general",
        "family",
        "contractor",
        "new",
        "home",
        "improvement",
        "remodeling"
    ],
    "wof:name":"Bennett Dover Home Remodelers",
    "wof:placetype":"venue"
},
  "geometry": {"coordinates":[-81.87830700000001,41.441766],"type":"Point"}
}