{
  "type": "Feature",
  "properties": {
    "addr:full": "4514 State Rte 775 Proctorville OH 45669",
    "addr:housenumber": "4514",
    "addr:postcode": "45669",
    "addr:street": "State Rte 775",
    "iso:country": "US",
    "sg:address": "4514 State Rte 775",
    "sg:city": "Proctorville",
    "sg:classifiers": [
      {
        "category": "Food \u0026 Beverages",
        "subcategory": "Groceries \u0026 Convenience Stores",
        "type": "Retail Goods"
      }
    ],
    "sg:phone": "+1 740 886 6564",
    "sg:postcode": "45669",
    "sg:province": "OH",
    "wof:name": "Blakes Country \u0026 Convenient",
    "wof:placetype": "venue"
  },
  "geometry": {"coordinates":[-82.385155,38.493744],"type":"Point"}
}
