{
  "type": "Feature",
  "properties": {
    "iso:country":"US",
    "sg:address":"4514 State Rte 775",
    "sg:city":"Proctorville",
    "sg:classifiers":[
        {
            "category":"Food & Beverages",
            "subcategory":"Groceries & Convenience Stores",
            "type":"Retail Goods"
        }
    ],
    "sg:phone":"+1 740 886 6564",
    "sg:postcode":"45669",
    "sg:province":"OH",
    "wof:name":"Blakes Country & Convenient",
    "wof:placetype":"venue"
},
  "geometry": {"coordinates":[-82.385155,38.493744],"type":"Point"}
}