{
  "type": "Feature",
  "properties": {
    "addr:full": "1200 E Dorothy Ln Dayton OH 45419",
    "addr:housenumber": "1200",
    "addr:postcode": "45419",
    "addr:street": "E Dorothy Ln",
    "iso:country": "US",
    "sg:address": "1200 E Dorothy Ln",
    "sg:city": "Dayton",
    "sg:classifiers": [
      {
        "category": "Professional",
        "subcategory": "Lawyer \u0026 Legal Services",
        "type": "Services"
      }
    ],
    "sg:phone": "+1 937 299 1895",
    "sg:postcode": "45419",
    "sg:province": "OH",
    "sg:tags": [
      "attorney"
    ],
    "wof:name": "David R Schmidt",
    "wof:placetype": "venue"
  },
  "geometry": {"coordinates":[-84.144219,39.703821],"type":"Point"}
}
