{
  "type": "Feature",
  "properties": {
    "addr:full":"3116 Montgomery Rd Maineville OH 45039",
    "addr:housenumber":"3116",
    "addr:postcode":"45039",
    "addr:street":"Montgomery Rd",
    "iso:country":"US",
    "sg:address":"3116 Montgomery Rd",
    "sg:city":"Maineville",
    "sg:classifiers":[
        {
            "category":"Retail",
            "subcategory":"Auto Repair",
            "type":"Services"
        }
    ],
    "sg:phone":"+1 513 677 5544",
    "sg:postcode":"45039",
    "sg:province":"OH",
    "sg:tags":[
        "body",
        "automobile",
        "painting"
    ],
    "sg:website":"www.carstar.com",
    "wof:name":"King's Carstar Collision",
    "wof:placetype":"venue"
},
  "geometry": {"coordinates":[-84.27883799999999,39.307225],"type":"Point"}
}