{
  "type": "Feature",
  "properties": {
    "addr:full": "106 Scheid Rd Sandusky OH 44870",
    "addr:housenumber": "106",
    "addr:postcode": "44870",
    "addr:street": "Scheid Rd",
    "iso:country": "US",
    "sg:address": "106 Scheid Rd",
    "sg:city": "Sandusky",
    "sg:classifiers": [
      {
        "category": "Organizations",
        "subcategory": "Religious Organization",
        "type": "Services"
      }
    ],
    "sg:phone": "+1 419 625 2192",
    "sg:postcode": "44870",
    "sg:province": "OH",
    "sg:tags": [
      "church"
    ],
    "wof:name": "St John Lutheran Church",
    "wof:placetype": "venue"
  },
  "geometry": {"coordinates":[-82.646502,41.359128],"type":"Point"}
}
