{
  "type": "Feature",
  "properties": {
    "iso:country":"US",
    "sg:address":"1065 Wayne Rd",
    "sg:city":"Wilmington",
    "sg:classifiers":[
        {
            "category":"Manufacturing",
            "subcategory":"Tools & Machinery",
            "type":"Manufacturing & Wholesale Goods"
        }
    ],
    "sg:phone":"+1 937 382 2127",
    "sg:postcode":"45177",
    "sg:province":"OH",
    "sg:tags":[
        "manufacture",
        "shop",
        "product",
        "working",
        "metal",
        "precision",
        "machine"
    ],
    "wof:name":"Hale Manufacturing LLC",
    "wof:placetype":"venue"
},
  "geometry": {"coordinates":[-83.847756,39.447334],"type":"Point"}
}