{
  "type": "Feature",
  "properties": {
    "addr:full": "1065 Wayne Rd Wilmington OH 45177",
    "addr:housenumber": "1065",
    "addr:postcode": "45177",
    "addr:street": "Wayne Rd",
    "iso:country": "US",
    "sg:address": "1065 Wayne Rd",
    "sg:city": "Wilmington",
    "sg:classifiers": [
      {
        "category": "Manufacturing",
        "subcategory": "Tools \u0026 Machinery",
        "type": "Manufacturing \u0026 Wholesale Goods"
      }
    ],
    "sg:phone": "+1 937 382 2127",
    "sg:postcode": "45177",
    "sg:province": "OH",
    "sg:tags": [
      "manufacture",
      "shop",
      "product",
      "working",
      "metal",
      "precision",
      "machine"
    ],
    "wof:name": "Hale Manufacturing LLC",
    "wof:placetype": "venue"
  },
  "geometry": {"coordinates":[-83.847756,39.447334],"type":"Point"}
}
