{
  "type": "Feature",
  "properties": {
    "addr:full":"11216 Gladstone Rd Warren OH 44481",
    "addr:housenumber":"11216",
    "addr:postcode":"44481",
    "addr:street":"Gladstone Rd",
    "iso:country":"US",
    "sg:address":"11216 Gladstone Rd",
    "sg:city":"Warren",
    "sg:classifiers":[
        {
            "category":"Home & Garden",
            "subcategory":"Home Furnishings",
            "type":"Retail Goods"
        }
    ],
    "sg:phone":"+1 330 538 2367",
    "sg:postcode":"44481",
    "sg:province":"OH",
    "sg:tags":[
        "equipment",
        "fireplace"
    ],
    "wof:name":"Bush's Inc",
    "wof:placetype":"venue"
},
  "geometry": {"coordinates":[-80.858042,41.128571],"type":"Point"}
}