{
  "type": "Feature",
  "properties": {
    "addr:full": "1685 Salt Springs Rd Warren OH 44481",
    "addr:housenumber": "1685",
    "addr:postcode": "44481",
    "addr:street": "Salt Springs Rd",
    "iso:country": "US",
    "sg:address": "1685 Salt Springs Rd",
    "sg:city": "Warren",
    "sg:classifiers": [
      {
        "category": "Retail",
        "subcategory": "Auto Repair",
        "type": "Services"
      }
    ],
    "sg:phone": "+1 330 824 3747",
    "sg:postcode": "44481",
    "sg:province": "OH",
    "sg:tags": [
      "machine",
      "automobile",
      "shop"
    ],
    "wof:name": "Minor's Performance Machine",
    "wof:placetype": "venue"
  },
  "geometry": {"coordinates":[-80.864528,41.165817],"type":"Point"}
}
