{
  "type": "Feature",
  "properties": {
    "addr:full": "4600 Navarre Rd SW Canton OH 44706",
    "addr:housenumber": "4600",
    "addr:postcode": "44706",
    "addr:street": "Navarre Rd Sw",
    "iso:country": "US",
    "sg:address": "4600 Navarre Rd SW",
    "sg:city": "Canton",
    "sg:classifiers": [
      {
        "category": "Shopping",
        "type": "Retail Goods"
      }
    ],
    "sg:phone": "+1 330 478 5923",
    "sg:postcode": "44706",
    "sg:province": "OH",
    "sg:tags": [
      "pet",
      "food",
      "supply"
    ],
    "wof:name": "Dilley's Dog Paw-Lor",
    "wof:placetype": "venue"
  },
  "geometry": {"coordinates":[-81.43243,40.774386],"type":"Point"}
}
