{
  "type": "Feature",
  "properties": {
    "iso:country":"US",
    "sg:address":"6505 Alabama Ave NW",
    "sg:city":"Canal Fulton",
    "sg:classifiers":[
        {
            "category":"Health Services",
            "subcategory":"Podiatrist",
            "type":"Services"
        }
    ],
    "sg:phone":"+1 330 833 2828",
    "sg:postcode":"44614",
    "sg:province":"OH",
    "wof:name":"Bruce D Fertal DPM",
    "wof:placetype":"venue"
},
  "geometry": {"coordinates":[-81.627106,40.878696],"type":"Point"}
}