{
  "type": "Feature",
  "properties": {
    "addr:full":"112 Woodman Dr Dayton OH 45431",
    "addr:housenumber":"112",
    "addr:postcode":"45431",
    "addr:street":"Woodman Dr",
    "iso:country":"US",
    "sg:address":"112 Woodman Dr",
    "sg:city":"Dayton",
    "sg:classifiers":[
        {
            "category":"Restaurant",
            "type":"Food & Drink"
        }
    ],
    "sg:phone":"+1 937 781 9999",
    "sg:postcode":"45431",
    "sg:province":"OH",
    "sg:tags":[
        "eating",
        "chinese"
    ],
    "wof:name":"China Garden Buffet",
    "wof:placetype":"venue"
},
  "geometry": {"coordinates":[-84.123411,39.766465],"type":"Point"}
}