{
  "type": "Feature",
  "properties": {
    "iso:country":"US",
    "sg:address":"1307 S Main St",
    "sg:city":"Canton",
    "sg:classifiers":[
        {
            "category":"Home & Garden",
            "subcategory":"Building Materials",
            "type":"Retail Goods"
        }
    ],
    "sg:phone":"+1 330 966 2447",
    "sg:postcode":"44720",
    "sg:province":"OH",
    "wof:name":"1st Choice Windshield Repair",
    "wof:placetype":"venue"
},
  "geometry": {"coordinates":[-81.396548,40.863427],"type":"Point"}
}