{
  "type": "Feature",
  "properties": {
    "addr:full": "5950 N Dixie Dr Dayton OH 45414",
    "addr:housenumber": "5950",
    "addr:postcode": "45414",
    "addr:street": "N Dixie Dr",
    "iso:country": "US",
    "sg:address": "5950 N Dixie Dr",
    "sg:city": "Dayton",
    "sg:classifiers": [
      {
        "category": "Home \u0026 Garden",
        "subcategory": "Building Materials",
        "type": "Retail Goods"
      },
      {
        "category": "Retail",
        "subcategory": "Auto Repair",
        "type": "Services"
      }
    ],
    "sg:phone": "+1 937 890 5992",
    "sg:postcode": "45414",
    "sg:province": "OH",
    "sg:tags": [
      "glass",
      "window",
      "plate",
      "replacement"
    ],
    "wof:name": "Safelite Auto Glass",
    "wof:placetype": "venue"
  },
  "geometry": {"coordinates":[-84.19822,39.822443],"type":"Point"}
}
