{
  "type": "Feature",
  "properties": {
    "addr:full": "1149 Parsons Ave Columbus OH 43206",
    "addr:housenumber": "1149",
    "addr:postcode": "43206",
    "addr:street": "Parsons Ave",
    "iso:country": "US",
    "sg:address": "1149 Parsons Ave",
    "sg:city": "Columbus",
    "sg:classifiers": [
      {
        "category": "Professional",
        "subcategory": "Employment Agencies",
        "type": "Services"
      }
    ],
    "sg:phone": "+1 614 445 8661",
    "sg:postcode": "43206",
    "sg:province": "OH",
    "sg:tags": [
      "opportunity"
    ],
    "sg:website": "www.laborready.com",
    "wof:name": "Labor Ready Inc",
    "wof:placetype": "venue"
  },
  "geometry": {"coordinates":[-82.983362,39.940031],"type":"Point"}
}
