{
  "type": "Feature",
  "properties": {
    "addr:full": "2297 Baltimore Ave Cincinnati OH 45225",
    "addr:housenumber": "2297",
    "addr:postcode": "45225",
    "addr:street": "Baltimore Ave",
    "iso:country": "US",
    "sg:address": "2297 Baltimore Ave",
    "sg:city": "Cincinnati",
    "sg:classifiers": [
      {
        "category": "Organizations",
        "subcategory": "Professional Association",
        "type": "Services"
      }
    ],
    "sg:phone": "+1 513 542 8610",
    "sg:postcode": "45225",
    "sg:province": "OH",
    "wof:name": "East Westwood Improvement Assn",
    "wof:placetype": "venue"
  },
  "geometry": {"coordinates":[-84.562364,39.148465],"type":"Point"}
}
