{
  "type": "Feature",
  "properties": {
    "iso:country":"US",
    "sg:address":"1036 W Liberty St",
    "sg:city":"Cincinnati",
    "sg:classifiers":[
        {
            "category":"Professional",
            "subcategory":"Computer Services",
            "type":"Services"
        }
    ],
    "sg:phone":"+1 513 241 7451",
    "sg:postcode":"45214",
    "sg:province":"OH",
    "sg:tags":[
        "processing",
        "datum"
    ],
    "wof:name":"Aads-Cincinnati",
    "wof:placetype":"venue"
},
  "geometry": {"coordinates":[-84.53453399999999,39.114137],"type":"Point"}
}