{
  "type": "Feature",
  "properties": {
    "addr:full": "6178 Youngstown Hubbard Rd Hubbard OH 44425",
    "addr:housenumber": "6178",
    "addr:postcode": "44425",
    "addr:street": "Hubbard Rd",
    "iso:country": "US",
    "sg:address": "6178 Youngstown Hubbard Rd",
    "sg:city": "Hubbard",
    "sg:classifiers": [
      {
        "category": "Building \u0026 Trades",
        "subcategory": "Construction",
        "type": "Services"
      }
    ],
    "sg:phone": "+1 330 534 4123",
    "sg:postcode": "44425",
    "sg:province": "OH",
    "sg:tags": [
      "general",
      "retail",
      "commercial",
      "contractor"
    ],
    "wof:name": "L F Wolf Contracting Inc",
    "wof:placetype": "venue"
  },
  "geometry": {"coordinates":[-80.599616,41.148328],"type":"Point"}
}
