{
  "type": "Feature",
  "properties": {
    "addr:full": "582 Chancellor Ct Avon Lake OH 44012",
    "addr:housenumber": "582",
    "addr:postcode": "44012",
    "addr:street": "Chancellor Ct",
    "iso:country": "US",
    "sg:address": "582 Chancellor Ct",
    "sg:city": "Avon Lake",
    "sg:classifiers": [
      {
        "category": "Professional",
        "subcategory": "Business Services",
        "type": "Services"
      }
    ],
    "sg:phone": "+1 440 236 8936",
    "sg:postcode": "44012",
    "sg:province": "OH",
    "sg:tags": [
      "interior",
      "consultant",
      "design",
      "decorator"
    ],
    "wof:name": "IDX Inc",
    "wof:placetype": "venue"
  },
  "geometry": {"coordinates":[-81.993826,41.491109],"type":"Point"}
}
