{
  "type": "Feature",
  "properties": {
    "addr:full":"160 E Main St Donnelsville OH 45320",
    "addr:housenumber":"160",
    "addr:postcode":"45320",
    "addr:street":"E Main St",
    "iso:country":"US",
    "sg:address":"160 E Main St",
    "sg:city":"Donnelsville",
    "sg:classifiers":[
        {
            "category":"Professional",
            "type":"Services"
        }
    ],
    "sg:phone":"+1 937 882 9221",
    "sg:postcode":"45320",
    "sg:province":"OH",
    "sg:tags":[
        "establishment"
    ],
    "wof:name":"Storm Enterprises",
    "wof:placetype":"venue"
},
  "geometry": {"coordinates":[-84.63557299999999,39.74402],"type":"Point"}
}