{
  "type": "Feature",
  "properties": {
    "iso:country":"US",
    "sg:address":"45505 N Ridge Rd",
    "sg:city":"Amherst",
    "sg:classifiers":[
        {
            "category":"Building & Trades",
            "subcategory":"Landscaping Services",
            "type":"Services"
        }
    ],
    "sg:phone":"+1 440 985 2475",
    "sg:postcode":"44001",
    "sg:province":"OH",
    "wof:name":"Clean Cut Lawn Care",
    "wof:placetype":"venue"
},
  "geometry": {"coordinates":[-82.253666,41.397959],"type":"Point"}
}