{
  "type": "Feature",
  "properties": {
    "addr:full": "45505 N Ridge Rd Amherst OH 44001",
    "addr:housenumber": "45505",
    "addr:postcode": "44001",
    "addr:street": "N Ridge Rd",
    "iso:country": "US",
    "sg:address": "45505 N Ridge Rd",
    "sg:city": "Amherst",
    "sg:classifiers": [
      {
        "category": "Building \u0026 Trades",
        "subcategory": "Landscaping Services",
        "type": "Services"
      }
    ],
    "sg:phone": "+1 440 985 2475",
    "sg:postcode": "44001",
    "sg:province": "OH",
    "wof:name": "Clean Cut Lawn Care",
    "wof:placetype": "venue"
  },
  "geometry": {"coordinates":[-82.253666,41.397959],"type":"Point"}
}
