{
  "type": "Feature",
  "properties": {
    "iso:country":"US",
    "sg:address":"1375 Euclid Ave",
    "sg:city":"Cleveland",
    "sg:classifiers":[
        {
            "category":"Internet Cafe",
            "subcategory":"None",
            "type":"Food & Drink"
        }
    ],
    "sg:phone":"+1 216 583 5000",
    "sg:postcode":"44115",
    "sg:province":"OH",
    "sg:tags":[
        "product"
    ],
    "wof:name":"Schoolone",
    "wof:placetype":"venue"
},
  "geometry": {"coordinates":[-81.682175,41.50086],"type":"Point"}
}