{
  "type": "Feature",
  "properties": {
    "addr:full": "7789 Cooper Rd Cincinnati OH 45242",
    "addr:housenumber": "7789",
    "addr:postcode": "45242",
    "addr:street": "Cooper Rd",
    "iso:country": "US",
    "sg:address": "7789 Cooper Rd",
    "sg:city": "Cincinnati",
    "sg:classifiers": [
      {
        "category": "Professional",
        "subcategory": "Art Services",
        "type": "Services"
      }
    ],
    "sg:phone": "+1 513 985 0433",
    "sg:postcode": "45242",
    "sg:province": "OH",
    "sg:tags": [
      "photographer"
    ],
    "wof:name": "Kelly Ross",
    "wof:placetype": "venue"
  },
  "geometry": {"coordinates":[-84.355081,39.226495],"type":"Point"}
}
