{
  "type": "Feature",
  "properties": {
    "addr:full":"114 E William St Maumee OH 43537",
    "addr:housenumber":"114",
    "addr:postcode":"43537",
    "addr:street":"E William St",
    "iso:country":"US",
    "sg:address":"114 E William St",
    "sg:city":"Maumee",
    "sg:classifiers":[
        {
            "category":"Professional",
            "subcategory":"Research",
            "type":"Services"
        }
    ],
    "sg:phone":"+1 419 897 9892",
    "sg:postcode":"43537",
    "sg:province":"OH",
    "sg:tags":[
        "environmental",
        "ecological"
    ],
    "wof:name":"ART",
    "wof:placetype":"venue"
},
  "geometry": {"coordinates":[-83.653291,41.565139],"type":"Point"}
}