{
  "type": "Feature",
  "properties": {
    "addr:full": "303 N Warpole St Upper Sandusky OH 43351",
    "addr:housenumber": "303",
    "addr:postcode": "43351",
    "addr:street": "N Warpole St",
    "iso:country": "US",
    "sg:address": "303 N Warpole St",
    "sg:city": "Upper Sandusky",
    "sg:classifiers": [
      {
        "category": "Restaurant",
        "type": "Food \u0026 Drink"
      }
    ],
    "sg:menulink": "http://www.allmenus.com/oh/crane/185025-dairy-snack/menu/",
    "sg:phone": "+1 419 294 2385",
    "sg:postcode": "43351",
    "sg:province": "OH",
    "sg:tags": [
      "american"
    ],
    "wof:name": "Dairy Snack",
    "wof:placetype": "venue"
  },
  "geometry": {"coordinates":[-83.290054,40.828386],"type":"Point"}
}
