{
  "type": "Feature",
  "properties": {
    "addr:full":"9883 Waterstone Blvd Cincinnati OH 45249",
    "addr:housenumber":"9883",
    "addr:postcode":"45249",
    "addr:street":"Waterstone Blvd",
    "iso:country":"US",
    "sg:address":"9883 Waterstone Blvd",
    "sg:city":"Cincinnati",
    "sg:classifiers":[
        {
            "category":"Shopping",
            "subcategory":"Shoes",
            "type":"Retail Goods"
        }
    ],
    "sg:phone":"+1 513 697 1333",
    "sg:postcode":"45249",
    "sg:province":"OH",
    "wof:name":"Rack Room Shoes",
    "wof:placetype":"venue"
},
  "geometry": {"coordinates":[-84.306259,39.292638],"type":"Point"}
}