{
  "type": "Feature",
  "properties": {
    "iso:country":"US",
    "sg:address":"14021 Lakota Ave",
    "sg:city":"Cleveland",
    "sg:classifiers":[
        {
            "category":"Arts & Performance",
            "subcategory":"Theater",
            "type":"Entertainment"
        }
    ],
    "sg:phone":"+1 216 251 7489",
    "sg:postcode":"44111",
    "sg:province":"OH",
    "sg:tags":[
        "bureau"
    ],
    "wof:name":"Elite Entertainment",
    "wof:placetype":"venue"
},
  "geometry": {"coordinates":[-81.79359700000001,41.448676],"type":"Point"}
}