{
  "type": "Feature",
  "properties": {
    "addr:full": "14021 Lakota Ave Cleveland OH 44111",
    "addr:housenumber": "14021",
    "addr:postcode": "44111",
    "addr:street": "Lakota Ave",
    "iso:country": "US",
    "sg:address": "14021 Lakota Ave",
    "sg:city": "Cleveland",
    "sg:classifiers": [
      {
        "category": "Arts \u0026 Performance",
        "subcategory": "Theater",
        "type": "Entertainment"
      }
    ],
    "sg:phone": "+1 216 251 7489",
    "sg:postcode": "44111",
    "sg:province": "OH",
    "sg:tags": [
      "bureau"
    ],
    "wof:name": "Elite Entertainment",
    "wof:placetype": "venue"
  },
  "geometry": {"coordinates":[-81.793597,41.448676],"type":"Point"}
}
