{
  "type": "Feature",
  "properties": {
    "addr:full":"5105 Delhi Ave Cincinnati OH 45238",
    "addr:housenumber":"5105",
    "addr:postcode":"45238",
    "addr:street":"Delhi Ave",
    "iso:country":"US",
    "sg:address":"5105 Delhi Ave",
    "sg:city":"Cincinnati",
    "sg:classifiers":[
        {
            "category":"Autos & Motor Vehicles",
            "subcategory":"Auto Supplies",
            "type":"Retail Goods"
        },
        {
            "category":"Retail",
            "subcategory":"Auto Repair",
            "type":"Services"
        }
    ],
    "sg:phone":"+1 513 922 5010",
    "sg:postcode":"45238",
    "sg:province":"OH",
    "sg:tags":[
        "wheel",
        "exhaust",
        "absorber",
        "shock",
        "tire",
        "automobile",
        "wheels-aligning",
        "system",
        "strut",
        "alignment-frame",
        "servicing-automotive",
        "part",
        "brake",
        "axle",
        "equipment-service",
        "muffler",
        "balancing",
        "accessory",
        "air conditioning"
    ],
    "sg:website":"http://www.midaslocator.com",
    "wof:name":"Midas Auto Service Experts",
    "wof:placetype":"venue"
},
  "geometry": {"coordinates":[-84.613083,39.09486],"type":"Point"}
}