{
  "type": "Feature",
  "properties": {
    "addr:full": "5089 Wainfleet Ct Columbus OH 43221",
    "addr:housenumber": "5089",
    "addr:postcode": "43221",
    "addr:street": "Wainfleet Ct",
    "iso:country": "US",
    "sg:address": "5089 Wainfleet Ct",
    "sg:city": "Columbus",
    "sg:classifiers": [
      {
        "category": "Autos \u0026 Motor Vehicles",
        "subcategory": "Automobile Sales",
        "type": "Retail Goods"
      }
    ],
    "sg:phone": "+1 614 488 0020",
    "sg:postcode": "43221",
    "sg:province": "OH",
    "sg:tags": [
      "car",
      "dealer"
    ],
    "wof:name": "Northwest Motor Sales",
    "wof:placetype": "venue"
  },
  "geometry": {"coordinates":[-83.110433,40.058261],"type":"Point"}
}
