{
  "type": "Feature",
  "properties": {
    "addr:full":"23643 Patrick-Brush Run Rd Marysville OH 43040",
    "addr:housenumber":"23643",
    "addr:postcode":"43040",
    "addr:street":"Patrick-Brush Run Rd",
    "iso:country":"US",
    "sg:address":"23643 Patrick-Brush Run Rd",
    "sg:city":"Marysville",
    "sg:classifiers":[
        {
            "category":"Shopping",
            "subcategory":"Used Merchandise",
            "type":"Retail Goods"
        }
    ],
    "sg:phone":"+1 937 246 0259",
    "sg:postcode":"43040",
    "sg:province":"OH",
    "wof:name":"Kirks Used Appliances",
    "wof:placetype":"venue"
},
  "geometry": {"coordinates":[-83.43826199999999,40.342102],"type":"Point"}
}