{
  "type": "Feature",
  "properties": {
    "addr:full": "1935 W 25th St Cleveland OH 44113",
    "addr:housenumber": "1935",
    "addr:postcode": "44113",
    "addr:street": "W 25Th St",
    "iso:country": "US",
    "sg:address": "1935 W 25th St",
    "sg:city": "Cleveland",
    "sg:classifiers": [
      {
        "category": "Manufacturing",
        "subcategory": "Printing",
        "type": "Manufacturing \u0026 Wholesale Goods"
      }
    ],
    "sg:phone": "+1 216 781 8655",
    "sg:postcode": "44113",
    "sg:province": "OH",
    "sg:tags": [
      "commercial",
      "b",
      "printer",
      "lithographic",
      "typesetting"
    ],
    "wof:name": "Orange Blossom Press Inc",
    "wof:placetype": "venue"
  },
  "geometry": {"coordinates":[-81.703845,41.484922],"type":"Point"}
}
