{
  "type": "Feature",
  "properties": {
    "addr:full": "695 Summit St NW Warren OH 44485",
    "addr:housenumber": "695",
    "addr:postcode": "44485",
    "addr:street": "Summit St Nw",
    "iso:country": "US",
    "sg:address": "695 Summit St NW",
    "sg:city": "Warren",
    "sg:classifiers": [
      {
        "category": "Freight",
        "type": "Transportation"
      }
    ],
    "sg:phone": "+1 330 372 1883",
    "sg:postcode": "44485",
    "sg:province": "OH",
    "sg:tags": [
      "trucking"
    ],
    "wof:name": "Sanfrey Freight Serv Inc",
    "wof:placetype": "venue"
  },
  "geometry": {"coordinates":[-80.826143,41.24348],"type":"Point"}
}
