{
  "type": "Feature",
  "properties": {
    "addr:full": "663 Dan St Akron OH 44310",
    "addr:housenumber": "663",
    "addr:postcode": "44310",
    "addr:street": "Dan St",
    "iso:country": "US",
    "sg:address": "663 Dan St",
    "sg:city": "Akron",
    "sg:classifiers": [
      {
        "category": "Building \u0026 Trades",
        "subcategory": "Construction",
        "type": "Services"
      }
    ],
    "sg:phone": "+1 330 253 6569",
    "sg:postcode": "44310",
    "sg:province": "OH",
    "sg:tags": [
      "carpentry",
      "contractor"
    ],
    "wof:name": "Ken Krites",
    "wof:placetype": "venue"
  },
  "geometry": {"coordinates":[-81.496215,41.091944],"type":"Point"}
}
