{
  "type": "Feature",
  "properties": {
    "iso:country":"US",
    "sg:address":"663 Dan St",
    "sg:city":"Akron",
    "sg:classifiers":[
        {
            "category":"Building & Trades",
            "subcategory":"Construction",
            "type":"Services"
        }
    ],
    "sg:phone":"+1 330 253 6569",
    "sg:postcode":"44310",
    "sg:province":"OH",
    "sg:tags":[
        "carpentry",
        "contractor"
    ],
    "wof:name":"Ken Krites",
    "wof:placetype":"venue"
},
  "geometry": {"coordinates":[-81.49621500000001,41.091944],"type":"Point"}
}