{
  "type": "Feature",
  "properties": {
    "addr:full": "48245 State Rte 248 Long Bottom OH 45743",
    "addr:housenumber": "48245",
    "addr:postcode": "45743",
    "addr:street": "State Rte 248;Bottom",
    "iso:country": "US",
    "sg:address": "48245 State Rte 248",
    "sg:city": "Long Bottom",
    "sg:classifiers": [
      {
        "category": "Restaurant",
        "type": "Food \u0026 Drink"
      }
    ],
    "sg:phone": "+1 740 985 3902",
    "sg:postcode": "45743",
    "sg:province": "OH",
    "wof:name": "M J \u0026 Family Restaurant",
    "wof:placetype": "venue"
  },
  "geometry": {"coordinates":[-81.890341,39.098808],"type":"Point"}
}
