{
  "type": "Feature",
  "properties": {
    "addr:full":"4619 Pleasant Ave Fairfield OH 45014",
    "addr:housenumber":"4619",
    "addr:postcode":"45014",
    "addr:street":"Pleasant Ave",
    "iso:country":"US",
    "sg:address":"4619 Pleasant Ave",
    "sg:city":"Fairfield",
    "sg:classifiers":[
        {
            "category":"Building & Trades",
            "subcategory":"Plumbing",
            "type":"Services"
        }
    ],
    "sg:phone":"+1 513 863 2554",
    "sg:postcode":"45014",
    "sg:province":"OH",
    "sg:tags":[
        "contractor"
    ],
    "wof:name":"Howell Heating & Air Condtng",
    "wof:placetype":"venue"
},
  "geometry": {"coordinates":[-84.55894600000001,39.351932],"type":"Point"}
}