{
  "type": "Feature",
  "properties": {
    "addr:full": "300 N Water St Kent OH 44240",
    "addr:housenumber": "300",
    "addr:postcode": "44240",
    "addr:street": "N Water St",
    "iso:country": "US",
    "sg:address": "300 N Water St",
    "sg:city": "Kent",
    "sg:classifiers": [
      {
        "category": "Freight",
        "type": "Transportation"
      }
    ],
    "sg:phone": "+1 330 673 9660",
    "sg:postcode": "44240",
    "sg:province": "OH",
    "sg:tags": [
      "special"
    ],
    "wof:name": "Kent Self Storage",
    "wof:placetype": "venue"
  },
  "geometry": {"coordinates":[-81.358228,41.154905],"type":"Point"}
}
