{
  "type": "Feature",
  "properties": {
    "iso:country":"US",
    "sg:address":"2454 Wood Ave",
    "sg:city":"Columbus",
    "sg:classifiers":[
        {
            "category":"Manufacturing",
            "subcategory":"Rubber & Plastics",
            "type":"Manufacturing & Wholesale Goods"
        }
    ],
    "sg:phone":"+1 614 488 6857",
    "sg:postcode":"43221",
    "sg:province":"OH",
    "sg:tags":[
        "bottle",
        "mfg"
    ],
    "wof:name":"Golden Plastics",
    "wof:placetype":"venue"
},
  "geometry": {"coordinates":[-83.03395999999999,40.009282],"type":"Point"}
}