{
  "type": "Feature",
  "properties": {
    "iso:country":"US",
    "sg:address":"4013 Columbus Ave",
    "sg:city":"Sandusky",
    "sg:classifiers":[
        {
            "category":"Organizations",
            "subcategory":"Religious Organization",
            "type":"Services"
        }
    ],
    "sg:phone":"+1 419 625 0804",
    "sg:postcode":"44870",
    "sg:province":"OH",
    "sg:tags":[
        "church"
    ],
    "wof:name":"Church Of The Nazarene",
    "wof:placetype":"venue"
},
  "geometry": {"coordinates":[-82.684988,41.411334],"type":"Point"}
}