{
  "type": "Feature",
  "properties": {
    "iso:country":"US",
    "sg:address":"3203 W Laskey Rd",
    "sg:city":"Toledo",
    "sg:classifiers":[
        {
            "category":"Building & Trades",
            "subcategory":"Construction",
            "type":"Services"
        }
    ],
    "sg:phone":"+1 419 474 5610",
    "sg:postcode":"43613",
    "sg:province":"OH",
    "sg:tags":[
        "resurfacing",
        "laying",
        "refinishing",
        "floor"
    ],
    "wof:name":"Randy Wilson Hardwood Floors",
    "wof:placetype":"venue"
},
  "geometry": {"coordinates":[-83.62366400000001,41.706243],"type":"Point"}
}