{
  "type": "Feature",
  "properties": {
    "addr:full": "3203 W Laskey Rd Toledo OH 43613",
    "addr:housenumber": "3203",
    "addr:postcode": "43613",
    "addr:street": "W Laskey Rd",
    "iso:country": "US",
    "sg:address": "3203 W Laskey Rd",
    "sg:city": "Toledo",
    "sg:classifiers": [
      {
        "category": "Building \u0026 Trades",
        "subcategory": "Construction",
        "type": "Services"
      }
    ],
    "sg:phone": "+1 419 474 5610",
    "sg:postcode": "43613",
    "sg:province": "OH",
    "sg:tags": [
      "resurfacing",
      "laying",
      "refinishing",
      "floor"
    ],
    "wof:name": "Randy Wilson Hardwood Floors",
    "wof:placetype": "venue"
  },
  "geometry": {"coordinates":[-83.623664,41.706243],"type":"Point"}
}
