{
  "type": "Feature",
  "properties": {
    "addr:full":"40 Austin Rd Geneva OH 44041",
    "addr:housenumber":"40",
    "addr:postcode":"44041",
    "addr:street":"Austin Rd",
    "iso:country":"US",
    "sg:address":"40 Austin Rd",
    "sg:city":"Geneva",
    "sg:classifiers":[
        {
            "category":"Personal",
            "subcategory":"Barber",
            "type":"Services"
        }
    ],
    "sg:phone":"+1 440 466 8342",
    "sg:postcode":"44041",
    "sg:province":"OH",
    "wof:name":"Hair House",
    "wof:placetype":"venue"
},
  "geometry": {"coordinates":[-80.937083,41.810642],"type":"Point"}
}