{
  "type": "Feature",
  "properties": {
    "addr:full": "242 N West St Versailles OH 45380",
    "addr:housenumber": "242",
    "addr:postcode": "45380",
    "addr:street": "N West St",
    "iso:country": "US",
    "sg:address": "242 N West St",
    "sg:city": "Versailles",
    "sg:classifiers": [
      {
        "category": "Wholesale",
        "subcategory": "Farm Supplies",
        "type": "Manufacturing \u0026 Wholesale Goods"
      }
    ],
    "sg:phone": "+1 937 526 4311",
    "sg:postcode": "45380",
    "sg:province": "OH",
    "sg:tags": [
      "feed",
      "fertilizer",
      "grain"
    ],
    "wof:name": "Versailles Feed Mill Inc",
    "wof:placetype": "venue"
  },
  "geometry": {"coordinates":[-84.487761,40.225835],"type":"Point"}
}
