{
  "type": "Feature",
  "properties": {
    "iso:country":"US",
    "sg:address":"242 N West St",
    "sg:city":"Versailles",
    "sg:classifiers":[
        {
            "category":"Wholesale",
            "subcategory":"Farm Supplies",
            "type":"Manufacturing & Wholesale Goods"
        }
    ],
    "sg:phone":"+1 937 526 4311",
    "sg:postcode":"45380",
    "sg:province":"OH",
    "sg:tags":[
        "feed",
        "fertilizer",
        "grain"
    ],
    "wof:name":"Versailles Feed Mill Inc",
    "wof:placetype":"venue"
},
  "geometry": {"coordinates":[-84.48776100000001,40.225835],"type":"Point"}
}