{
  "type": "Feature",
  "properties": {
    "addr:full": "11475 Musselman Rd New Carlisle OH 45344",
    "addr:housenumber": "11475",
    "addr:postcode": "45344",
    "addr:street": "Musselman Rd",
    "iso:country": "US",
    "sg:address": "11475 Musselman Rd",
    "sg:city": "New Carlisle",
    "sg:classifiers": [
      {
        "category": "Wholesale",
        "subcategory": "Auto Parts",
        "type": "Manufacturing \u0026 Wholesale Goods"
      }
    ],
    "sg:phone": "+1 937 845 3236",
    "sg:postcode": "45344",
    "sg:province": "OH",
    "sg:tags": [
      "used"
    ],
    "wof:name": "New Carlisle Auto Parts",
    "wof:placetype": "venue"
  },
  "geometry": {"coordinates":[-84.026341,39.925292],"type":"Point"}
}
