{
  "type": "Feature",
  "properties": {
    "iso:country":"US",
    "sg:address":"401 Broadway St",
    "sg:city":"Cincinnati",
    "sg:classifiers":[
        {
            "category":"Restaurant",
            "type":"Food & Drink"
        }
    ],
    "sg:phone":"+1 513 381 6000",
    "sg:postcode":"45202",
    "sg:province":"OH",
    "wof:name":"Cahills Corner Cafe",
    "wof:placetype":"venue"
},
  "geometry": {"coordinates":[-84.506269,39.101293],"type":"Point"}
}