{
  "type": "Feature",
  "properties": {
    "addr:full":"9 W Mitchell Ave Cincinnati OH 45217",
    "addr:housenumber":"9",
    "addr:postcode":"45217",
    "addr:street":"W Mitchell Ave",
    "iso:country":"US",
    "sg:address":"9 W Mitchell Ave",
    "sg:city":"Cincinnati",
    "sg:classifiers":[
        {
            "category":"Wholesale",
            "subcategory":"Groceries",
            "type":"Manufacturing & Wholesale Goods"
        }
    ],
    "sg:phone":"+1 513 641 2345",
    "sg:postcode":"45217",
    "sg:province":"OH",
    "sg:tags":[
        "confectionery",
        "candy"
    ],
    "wof:name":"Marshmallow Products Inc",
    "wof:placetype":"venue"
},
  "geometry": {"coordinates":[-84.505493,39.160614],"type":"Point"}
}