{
  "type": "Feature",
  "properties": {
    "iso:country":"US",
    "sg:address":"3023 Dorr St",
    "sg:city":"Toledo",
    "sg:classifiers":[
        {
            "category":"Autos & Motor Vehicles",
            "subcategory":"Fuel & Gas Station",
            "type":"Retail Goods"
        }
    ],
    "sg:phone":"+1 419 531 4400",
    "sg:postcode":"43607",
    "sg:province":"OH",
    "sg:tags":[
        "station",
        "gasoline"
    ],
    "wof:name":"Marathon",
    "wof:placetype":"venue"
},
  "geometry": {"coordinates":[-83.61493900000001,41.652868],"type":"Point"}
}