{
  "type": "Feature",
  "properties": {
    "iso:country":"US",
    "sg:address":"1543 Brown St",
    "sg:city":"Akron",
    "sg:classifiers":[
        {
            "category":"Bars & Pubs",
            "type":"Food & Drink"
        }
    ],
    "sg:phone":"+1 330 724 6082",
    "sg:postcode":"44301",
    "sg:province":"OH",
    "sg:tags":[
        "lounge",
        "cocktail"
    ],
    "wof:name":"Karam's Lounge",
    "wof:placetype":"venue"
},
  "geometry": {"coordinates":[-81.510276,41.039774],"type":"Point"}
}