{
  "type": "Feature",
  "properties": {
    "addr:full": "2501 Ley Dr Akron OH 44319",
    "addr:housenumber": "2501",
    "addr:postcode": "44319",
    "addr:street": "Ley Dr",
    "iso:country": "US",
    "sg:address": "2501 Ley Dr",
    "sg:city": "Akron",
    "sg:classifiers": [
      {
        "category": "Shopping",
        "subcategory": "Used Merchandise",
        "type": "Retail Goods"
      }
    ],
    "sg:phone": "+1 330 724 8090",
    "sg:postcode": "44319",
    "sg:province": "OH",
    "sg:tags": [
      "junk"
    ],
    "wof:name": "BMR Salvage",
    "wof:placetype": "venue"
  },
  "geometry": {"coordinates":[-81.538177,41.024501],"type":"Point"}
}
