{
  "type": "Feature",
  "properties": {
    "addr:full":"701 Reese Ave Lancaster OH 43130",
    "addr:housenumber":"701",
    "addr:postcode":"43130",
    "addr:street":"Reese Ave",
    "iso:country":"US",
    "sg:address":"701 Reese Ave",
    "sg:city":"Lancaster",
    "sg:classifiers":[
        {
            "category":"Bars & Pubs",
            "type":"Food & Drink"
        }
    ],
    "sg:phone":"+1 740 653 6026",
    "sg:postcode":"43130",
    "sg:province":"OH",
    "sg:tags":[
        "drinking"
    ],
    "wof:name":"Dog House Tavern",
    "wof:placetype":"venue"
},
  "geometry": {"coordinates":[-82.614773,39.704668],"type":"Point"}
}