{
  "type": "Feature",
  "properties": {
    "iso:country":"US",
    "sg:address":"700 Morse Rd",
    "sg:city":"Columbus",
    "sg:classifiers":[
        {
            "category":"Building & Trades",
            "subcategory":"Pest Control",
            "type":"Services"
        }
    ],
    "sg:phone":"+1 614 436 2200",
    "sg:postcode":"43214",
    "sg:province":"OH",
    "wof:name":"Hisco Co Inc",
    "wof:placetype":"venue"
},
  "geometry": {"coordinates":[-83.000019,40.06176],"type":"Point"}
}