{
  "type": "Feature",
  "properties": {
    "iso:country":"US",
    "sg:address":"4225 Greensview Dr",
    "sg:city":"Columbus",
    "sg:classifiers":[
        {
            "category":"Restaurant",
            "type":"Food & Drink"
        }
    ],
    "sg:phone":"+1 614 888 8618",
    "sg:postcode":"43220",
    "sg:province":"OH",
    "sg:tags":[
        "caterer"
    ],
    "wof:name":"Da Vinci Pronto",
    "wof:placetype":"venue"
},
  "geometry": {"coordinates":[-83.058074,40.043504],"type":"Point"}
}