{
  "type": "Feature",
  "properties": {
    "addr:full":"35822 Detroit Rd Avon OH 44011",
    "addr:housenumber":"35822",
    "addr:postcode":"44011",
    "addr:street":"Detroit Rd",
    "iso:country":"US",
    "sg:address":"35822 Detroit Rd",
    "sg:city":"Avon",
    "sg:classifiers":[
        {
            "category":"Home & Garden",
            "subcategory":"Furniture",
            "type":"Retail Goods"
        }
    ],
    "sg:phone":"+1 440 937 2100",
    "sg:postcode":"44011",
    "sg:province":"OH",
    "wof:name":"World Market",
    "wof:placetype":"venue"
},
  "geometry": {"coordinates":[-82.013902,41.457862],"type":"Point"}
}