{
  "type": "Feature",
  "properties": {
    "addr:full": "322 Grandview Ave Wadsworth OH 44281",
    "addr:housenumber": "322",
    "addr:postcode": "44281",
    "addr:street": "Grandview Ave",
    "iso:country": "US",
    "sg:address": "322 Grandview Ave",
    "sg:city": "Wadsworth",
    "sg:classifiers": [
      {
        "category": "Retail",
        "subcategory": "Auto Repair",
        "type": "Services"
      }
    ],
    "sg:phone": "+1 330 336 3100",
    "sg:postcode": "44281",
    "sg:province": "OH",
    "sg:tags": [
      "body",
      "automobile",
      "painting"
    ],
    "wof:name": "Kelleman Collision",
    "wof:placetype": "venue"
  },
  "geometry": {"coordinates":[-81.736091,41.019355],"type":"Point"}
}
