{
  "type": "Feature",
  "properties": {
    "addr:full": "234 Shadow Lake Dr Mason OH 45040",
    "addr:housenumber": "234",
    "addr:postcode": "45040",
    "addr:street": "Shadow Lake Dr",
    "iso:country": "US",
    "sg:address": "234 Shadow Lake Dr",
    "sg:city": "Mason",
    "sg:classifiers": [
      {
        "category": "Real Estate",
        "subcategory": "Real Estate Operator",
        "type": "Services"
      }
    ],
    "sg:phone": "+1 513 398 5966",
    "sg:postcode": "45040",
    "sg:province": "OH",
    "sg:tags": [
      "mobile",
      "home",
      "site"
    ],
    "wof:name": "Shadow Lake Mobile Home Vlg",
    "wof:placetype": "venue"
  },
  "geometry": {"coordinates":[-84.311548,39.401858],"type":"Point"}
}
