{
  "type": "Feature",
  "properties": {
    "iso:country":"US",
    "sg:address":"16009 Lucille Ave",
    "sg:city":"Cleveland",
    "sg:classifiers":[
        {
            "category":"Manufacturing",
            "subcategory":"Retail Goods",
            "type":"Manufacturing & Wholesale Goods"
        }
    ],
    "sg:phone":"+1 216 251 9002",
    "sg:postcode":"44111",
    "sg:province":"OH",
    "sg:tags":[
        "resale",
        "craft",
        "for"
    ],
    "wof:name":"Minihaha",
    "wof:placetype":"venue"
},
  "geometry": {"coordinates":[-81.812833,41.453931],"type":"Point"}
}