{
  "type": "Feature",
  "properties": {
    "addr:full": "16009 Lucille Ave Cleveland OH 44111",
    "addr:housenumber": "16009",
    "addr:postcode": "44111",
    "addr:street": "Lucille Ave",
    "iso:country": "US",
    "sg:address": "16009 Lucille Ave",
    "sg:city": "Cleveland",
    "sg:classifiers": [
      {
        "category": "Manufacturing",
        "subcategory": "Retail Goods",
        "type": "Manufacturing \u0026 Wholesale Goods"
      }
    ],
    "sg:phone": "+1 216 251 9002",
    "sg:postcode": "44111",
    "sg:province": "OH",
    "sg:tags": [
      "resale",
      "craft",
      "for"
    ],
    "wof:name": "Minihaha",
    "wof:placetype": "venue"
  },
  "geometry": {"coordinates":[-81.812833,41.453931],"type":"Point"}
}
