{
  "type": "Feature",
  "properties": {
    "iso:country":"US",
    "sg:address":"4092 Kister Rd",
    "sg:city":"Shreve",
    "sg:classifiers":[
        {
            "category":"Farming",
            "subcategory":"Livestock Farm",
            "type":"Manufacturing & Wholesale Goods"
        }
    ],
    "sg:phone":"+1 330 567 3369",
    "sg:postcode":"44676",
    "sg:province":"OH",
    "sg:tags":[
        "field",
        "cattle",
        "beef",
        "feedlot",
        "cr"
    ],
    "wof:name":"Carl Sidle",
    "wof:placetype":"venue"
},
  "geometry": {"coordinates":[-82.010211,40.728099],"type":"Point"}
}