{
  "type": "Feature",
  "properties": {
    "addr:full":"5195 Manchester Rd Franklin OH 45005",
    "addr:housenumber":"5195",
    "addr:postcode":"45005",
    "addr:street":"Manchester Rd",
    "iso:country":"US",
    "sg:address":"5195 Manchester Rd",
    "sg:city":"Franklin",
    "sg:classifiers":[
        {
            "category":"Shopping",
            "subcategory":"Discount & Variety Stores",
            "type":"Retail Goods"
        }
    ],
    "sg:phone":"+1 937 644 2276",
    "sg:postcode":"45005",
    "sg:province":"OH",
    "sg:tags":[
        "merchandise",
        "general"
    ],
    "wof:name":"Lake Sales",
    "wof:placetype":"venue"
},
  "geometry": {"coordinates":[-84.297783,39.526006],"type":"Point"}
}