{
  "type": "Feature",
  "properties": {
    "addr:full":"2035 N Ridge Rd Painesville OH 44077",
    "addr:housenumber":"2035",
    "addr:postcode":"44077",
    "addr:street":"N Ridge Rd",
    "iso:country":"US",
    "sg:address":"2035 N Ridge Rd",
    "sg:city":"Painesville",
    "sg:classifiers":[
        {
            "category":"Building & Trades",
            "subcategory":"Construction",
            "type":"Services"
        }
    ],
    "sg:phone":"+1 440 357 0203",
    "sg:postcode":"44077",
    "sg:province":"OH",
    "sg:tags":[
        "concrete",
        "contractor"
    ],
    "wof:name":"Ohio Contractors",
    "wof:placetype":"venue"
},
  "geometry": {"coordinates":[-81.20195099999999,41.752957],"type":"Point"}
}