{
  "type": "Feature",
  "properties": {
    "iso:country":"US",
    "sg:address":"3525 E 93rd St",
    "sg:city":"Cleveland",
    "sg:classifiers":[
        {
            "category":"Organizations",
            "subcategory":"Religious Organization",
            "type":"Services"
        }
    ],
    "sg:phone":"+1 216 271 0301",
    "sg:postcode":"44105",
    "sg:province":"OH",
    "sg:tags":[
        "church"
    ],
    "wof:name":"Glorious Church Of God-Christ",
    "wof:placetype":"venue"
},
  "geometry": {"coordinates":[-81.621376,41.462361],"type":"Point"}
}