{
  "type": "Feature",
  "properties": {
    "addr:full": "11667 Durkee Rd Grafton OH 44044",
    "addr:housenumber": "11667",
    "addr:postcode": "44044",
    "addr:street": "Durkee Rd",
    "iso:country": "US",
    "sg:address": "11667 Durkee Rd",
    "sg:city": "Grafton",
    "sg:classifiers": [
      {
        "category": "Building \u0026 Trades",
        "subcategory": "Construction",
        "type": "Services"
      }
    ],
    "sg:phone": "+1 440 748 3909",
    "sg:postcode": "44044",
    "sg:province": "OH",
    "sg:tags": [
      "house"
    ],
    "wof:name": "Brandyberry Construction",
    "wof:placetype": "venue"
  },
  "geometry": {"coordinates":[-82.050778,41.320876],"type":"Point"}
}
