{
  "type": "Feature",
  "properties": {
    "iso:country":"US",
    "sg:address":"11667 Durkee Rd",
    "sg:city":"Grafton",
    "sg:classifiers":[
        {
            "category":"Building & Trades",
            "subcategory":"Construction",
            "type":"Services"
        }
    ],
    "sg:phone":"+1 440 748 3909",
    "sg:postcode":"44044",
    "sg:province":"OH",
    "sg:tags":[
        "house"
    ],
    "wof:name":"Brandyberry Construction",
    "wof:placetype":"venue"
},
  "geometry": {"coordinates":[-82.05077799999999,41.320876],"type":"Point"}
}