{
  "type": "Feature",
  "properties": {
    "addr:full":"3601 State Rte 703 Celina OH 45822",
    "addr:housenumber":"3601",
    "addr:postcode":"45822",
    "addr:street":"State Rte 703",
    "iso:country":"US",
    "sg:address":"3601 State Rte 703",
    "sg:city":"Celina",
    "sg:classifiers":[
        {
            "category":"Real Estate",
            "subcategory":"Real Estate Operator",
            "type":"Services"
        }
    ],
    "sg:phone":"+1 419 586 8931",
    "sg:postcode":"45822",
    "sg:province":"OH",
    "sg:tags":[
        "mobile",
        "home",
        "site",
        "modular"
    ],
    "wof:name":"Grand Manor Mobile Home Cmnty",
    "wof:placetype":"venue"
},
  "geometry": {"coordinates":[-84.525728,40.547004],"type":"Point"}
}