{
  "type": "Feature",
  "properties": {
    "addr:full": "539 Wilson Dr Xenia OH 45385",
    "addr:housenumber": "539",
    "addr:postcode": "45385",
    "addr:street": "Wilson Dr",
    "iso:country": "US",
    "sg:address": "539 Wilson Dr",
    "sg:city": "Xenia",
    "sg:classifiers": [
      {
        "category": "Personal",
        "type": "Services"
      }
    ],
    "sg:phone": "+1 937 376 3821",
    "sg:postcode": "45385",
    "sg:province": "OH",
    "sg:tags": [
      "therapist",
      "massage"
    ],
    "wof:name": "Pamela King Massage Therapist",
    "wof:placetype": "venue"
  },
  "geometry": {"coordinates":[-83.926032,39.699313],"type":"Point"}
}
