{
  "type": "Feature",
  "properties": {
    "addr:full": "4640 Richmond Rd Cleveland OH 44128",
    "addr:housenumber": "4640",
    "addr:postcode": "44128",
    "addr:street": "Richmond Rd",
    "iso:country": "US",
    "sg:address": "4640 Richmond Rd",
    "sg:city": "Cleveland",
    "sg:classifiers": [
      {
        "category": "Restaurant",
        "type": "Food \u0026 Drink"
      }
    ],
    "sg:phone": "+1 216 364 2400",
    "sg:postcode": "44128",
    "sg:province": "OH",
    "sg:tags": [
      "delicatessen"
    ],
    "wof:name": "Sidelines Deli",
    "wof:placetype": "venue"
  },
  "geometry": {"coordinates":[-81.49798,41.431408],"type":"Point"}
}
