{
  "type": "Feature",
  "properties": {
    "addr:full": "9285 Blacklick-Eastern Rd NW Pickerington OH 43147",
    "addr:housenumber": "9285",
    "addr:postcode": "43147",
    "addr:street": "Blacklick-Eastern Rd Nw",
    "iso:country": "US",
    "sg:address": "9285 Blacklick-Eastern Rd NW",
    "sg:city": "Pickerington",
    "sg:classifiers": [
      {
        "category": "Retail",
        "subcategory": "Animal Services",
        "type": "Services"
      }
    ],
    "sg:phone": "+1 614 755 2436",
    "sg:postcode": "43147",
    "sg:province": "OH",
    "wof:name": "Florence Wilson Beall",
    "wof:placetype": "venue"
  },
  "geometry": {"coordinates":[-82.761054,39.931121],"type":"Point"}
}
