{
  "type": "Feature",
  "properties": {
    "addr:full": "848 Schocalog Rd Akron OH 44320",
    "addr:housenumber": "848",
    "addr:postcode": "44320",
    "addr:street": "Schocalog Rd",
    "iso:country": "US",
    "sg:address": "848 Schocalog Rd",
    "sg:city": "Akron",
    "sg:classifiers": [
      {
        "category": "Professional",
        "type": "Services"
      }
    ],
    "sg:phone": "+1 330 867 1672",
    "sg:postcode": "44320",
    "sg:province": "OH",
    "wof:name": "Revere Decorative Finishing",
    "wof:placetype": "venue"
  },
  "geometry": {"coordinates":[-81.603085,41.102229],"type":"Point"}
}
