{
  "type": "Feature",
  "properties": {
    "addr:full": "30080 Phelps Rd Logan OH 43138",
    "addr:housenumber": "30080",
    "addr:postcode": "43138",
    "addr:street": "Phelps Rd",
    "iso:country": "US",
    "sg:address": "30080 Phelps Rd",
    "sg:city": "Logan",
    "sg:classifiers": [
      {
        "category": "Travel",
        "subcategory": "Hotels \u0026 Motels",
        "type": "Entertainment"
      }
    ],
    "sg:phone": "+1 740 385 8722",
    "sg:postcode": "43138",
    "sg:province": "OH",
    "sg:tags": [
      "operation"
    ],
    "wof:name": "Sunrise Log Cabins",
    "wof:placetype": "venue"
  },
  "geometry": {"coordinates":[-82.464064,39.493106],"type":"Point"}
}
