{
  "type": "Feature",
  "properties": {
    "iso:country":"US",
    "sg:address":"621 Callowhill St",
    "sg:city":"Wooster",
    "sg:classifiers":[
        {
            "category":"Building & Trades",
            "subcategory":"Cleaning & Sanitation",
            "type":"Services"
        }
    ],
    "sg:phone":"+1 330 262 9456",
    "sg:postcode":"44691",
    "sg:province":"OH",
    "sg:tags":[
        "window"
    ],
    "wof:name":"AAAA Wayne County Window",
    "wof:placetype":"venue"
},
  "geometry": {"coordinates":[-81.93182,40.794953],"type":"Point"}
}