{
  "type": "Feature",
  "properties": {
    "addr:full": "5495 Salem Ave Dayton OH 45426",
    "addr:housenumber": "5495",
    "addr:postcode": "45426",
    "addr:street": "Salem Ave",
    "iso:country": "US",
    "sg:address": "5495 Salem Ave",
    "sg:city": "Dayton",
    "sg:classifiers": [
      {
        "category": "Food \u0026 Beverages",
        "subcategory": "Groceries \u0026 Convenience Stores",
        "type": "Retail Goods"
      }
    ],
    "sg:phone": "+1 937 837 8008",
    "sg:postcode": "45426",
    "sg:province": "OH",
    "wof:name": "Cub Foods 93 or 38134",
    "wof:placetype": "venue"
  },
  "geometry": {"coordinates":[-84.291104,39.824364],"type":"Point"}
}
