{
  "type": "Feature",
  "properties": {
    "addr:full":"4439 State Rte 159 Chillicothe OH 45601",
    "addr:housenumber":"4439",
    "addr:postcode":"45601",
    "addr:street":"State Rte 159",
    "iso:country":"US",
    "sg:address":"4439 State Rte 159",
    "sg:city":"Chillicothe",
    "sg:classifiers":[
        {
            "category":"Health Services",
            "subcategory":"Doctor",
            "type":"Services"
        }
    ],
    "sg:phone":"+1 740 775 2652",
    "sg:postcode":"45601",
    "sg:province":"OH",
    "sg:tags":[
        "physician",
        "surgeon"
    ],
    "wof:name":"First Capital Internal Med",
    "wof:placetype":"venue"
},
  "geometry": {"coordinates":[-82.967812,39.393657],"type":"Point"}
}