{
  "type": "Feature",
  "properties": {
    "iso:country":"US",
    "sg:address":"415 Market St",
    "sg:city":"New Richmond",
    "sg:classifiers":[
        {
            "category":"Banks & Credit Unions",
            "subcategory":"Bank",
            "type":"Services"
        }
    ],
    "sg:phone":"+1 513 876 2581",
    "sg:postcode":"45157",
    "sg:province":"OH",
    "wof:name":"New Richmond National Bank",
    "wof:placetype":"venue"
},
  "geometry": {"coordinates":[-84.28289700000001,38.953713],"type":"Point"}
}