{
  "type": "Feature",
  "properties": {
    "addr:full": "415 Market St New Richmond OH 45157",
    "addr:housenumber": "415",
    "addr:postcode": "45157",
    "addr:street": "Market St",
    "iso:country": "US",
    "sg:address": "415 Market St",
    "sg:city": "New Richmond",
    "sg:classifiers": [
      {
        "category": "Banks \u0026 Credit Unions",
        "subcategory": "Bank",
        "type": "Services"
      }
    ],
    "sg:phone": "+1 513 876 2581",
    "sg:postcode": "45157",
    "sg:province": "OH",
    "wof:name": "New Richmond National Bank",
    "wof:placetype": "venue"
  },
  "geometry": {"coordinates":[-84.282897,38.953713],"type":"Point"}
}
