{
  "type": "Feature",
  "properties": {
    "iso:country":"US",
    "sg:address":"1620 Edna Dr",
    "sg:city":"Lima",
    "sg:classifiers":[
        {
            "category":"Building & Trades",
            "subcategory":"Construction",
            "type":"Services"
        }
    ],
    "sg:phone":"+1 419 225 7248",
    "sg:postcode":"45807",
    "sg:province":"OH",
    "sg:tags":[
        "general"
    ],
    "wof:name":"J & J Builders",
    "wof:placetype":"venue"
},
  "geometry": {"coordinates":[-84.131799,40.775481],"type":"Point"}
}