{
  "type": "Feature",
  "properties": {
    "addr:full": "1620 Edna Dr Lima OH 45807",
    "addr:housenumber": "1620",
    "addr:postcode": "45807",
    "addr:street": "Edna Dr",
    "iso:country": "US",
    "sg:address": "1620 Edna Dr",
    "sg:city": "Lima",
    "sg:classifiers": [
      {
        "category": "Building \u0026 Trades",
        "subcategory": "Construction",
        "type": "Services"
      }
    ],
    "sg:phone": "+1 419 225 7248",
    "sg:postcode": "45807",
    "sg:province": "OH",
    "sg:tags": [
      "general"
    ],
    "wof:name": "J \u0026 J Builders",
    "wof:placetype": "venue"
  },
  "geometry": {"coordinates":[-84.131799,40.775481],"type":"Point"}
}
