{
  "type": "Feature",
  "properties": {
    "addr:full":"3367 Glenn Hwy Cambridge OH 43725",
    "addr:housenumber":"3367",
    "addr:postcode":"43725",
    "addr:street":"Glenn Hwy",
    "iso:country":"US",
    "sg:address":"3367 Glenn Hwy",
    "sg:city":"Cambridge",
    "sg:classifiers":[
        {
            "category":"Shopping",
            "type":"Retail Goods"
        }
    ],
    "sg:phone":"+1 740 435 0400",
    "sg:postcode":"43725",
    "sg:province":"OH",
    "sg:tags":[
        "merchandise"
    ],
    "wof:name":"My Pet Store",
    "wof:placetype":"venue"
},
  "geometry": {"coordinates":[-81.680432,40.001506],"type":"Point"}
}