{
  "type": "Feature",
  "properties": {
    "addr:full": "3375 W 117th St Cleveland OH 44111",
    "addr:housenumber": "3375",
    "addr:postcode": "44111",
    "addr:street": "W 117Th St",
    "iso:country": "US",
    "sg:address": "3375 W 117th St",
    "sg:city": "Cleveland",
    "sg:classifiers": [
      {
        "category": "Retail",
        "subcategory": "Repair Shop",
        "type": "Services"
      }
    ],
    "sg:phone": "+1 216 941 8497",
    "sg:postcode": "44111",
    "sg:province": "OH",
    "sg:tags": [
      "television",
      "radio"
    ],
    "wof:name": "Bodkin TV Svc",
    "wof:placetype": "venue"
  },
  "geometry": {"coordinates":[-81.768923,41.461469],"type":"Point"}
}
