{
  "type": "Feature",
  "properties": {
    "addr:full": "3419 State Rte 39 Millersburg OH 44654",
    "addr:housenumber": "3419",
    "addr:postcode": "44654",
    "addr:street": "State Rte 39",
    "iso:country": "US",
    "sg:address": "3419 State Rte 39",
    "sg:city": "Millersburg",
    "sg:classifiers": [
      {
        "category": "Food \u0026 Beverages",
        "subcategory": "Specialty",
        "type": "Retail Goods"
      }
    ],
    "sg:phone": "+1 330 893 3209",
    "sg:postcode": "44654",
    "sg:province": "OH",
    "sg:tags": [
      "gourmet",
      "shop"
    ],
    "wof:name": "Amish Country Gourmet",
    "wof:placetype": "venue"
  },
  "geometry": {"coordinates":[-81.746698,40.546441],"type":"Point"}
}
