{
  "type": "Feature",
  "properties": {
    "iso:country":"US",
    "sg:address":"3419 State Rte 39",
    "sg:city":"Millersburg",
    "sg:classifiers":[
        {
            "category":"Food & Beverages",
            "subcategory":"Specialty",
            "type":"Retail Goods"
        }
    ],
    "sg:phone":"+1 330 893 3209",
    "sg:postcode":"44654",
    "sg:province":"OH",
    "sg:tags":[
        "gourmet",
        "shop"
    ],
    "wof:name":"Amish Country Gourmet",
    "wof:placetype":"venue"
},
  "geometry": {"coordinates":[-81.74669799999999,40.546441],"type":"Point"}
}