{
  "type": "Feature",
  "properties": {
    "addr:full": "59 Grant St Newark OH 43055",
    "addr:housenumber": "59",
    "addr:postcode": "43055",
    "addr:street": "Grant St",
    "iso:country": "US",
    "sg:address": "59 Grant St",
    "sg:city": "Newark",
    "sg:classifiers": [
      {
        "category": "Building \u0026 Trades",
        "subcategory": "Construction",
        "type": "Services"
      }
    ],
    "sg:phone": "+1 740 344 4362",
    "sg:postcode": "43055",
    "sg:province": "OH",
    "sg:tags": [
      "general",
      "industrial",
      "commercial",
      "contractor"
    ],
    "sg:website": "www.rcsnewark.com",
    "wof:name": "Robertson Construction Svcs",
    "wof:placetype": "venue"
  },
  "geometry": {"coordinates":[-82.42331,40.047256],"type":"Point"}
}
