{
  "type": "Feature",
  "properties": {
    "addr:full": "7858 State Rte 188 Circleville OH 43113",
    "addr:housenumber": "7858",
    "addr:postcode": "43113",
    "addr:street": "State Rte 188",
    "iso:country": "US",
    "sg:address": "7858 State Rte 188",
    "sg:city": "Circleville",
    "sg:classifiers": [
      {
        "category": "Farming",
        "subcategory": "Farm",
        "type": "Manufacturing \u0026 Wholesale Goods"
      }
    ],
    "sg:phone": "+1 740 477 9897",
    "sg:postcode": "43113",
    "sg:province": "OH",
    "sg:tags": [
      "crop",
      "general"
    ],
    "wof:name": "Jeff Barr",
    "wof:placetype": "venue"
  },
  "geometry": {"coordinates":[-82.86852,39.660211],"type":"Point"}
}
