{
  "type": "Feature",
  "properties": {
    "iso:country":"US",
    "sg:address":"7858 State Rte 188",
    "sg:city":"Circleville",
    "sg:classifiers":[
        {
            "category":"Farming",
            "subcategory":"Farm",
            "type":"Manufacturing & Wholesale Goods"
        }
    ],
    "sg:phone":"+1 740 477 9897",
    "sg:postcode":"43113",
    "sg:province":"OH",
    "sg:tags":[
        "crop",
        "general"
    ],
    "wof:name":"Jeff Barr",
    "wof:placetype":"venue"
},
  "geometry": {"coordinates":[-82.86852,39.660211],"type":"Point"}
}