{
  "type": "Feature",
  "properties": {
    "iso:country":"US",
    "sg:address":"480 Dussel Dr",
    "sg:city":"Maumee",
    "sg:classifiers":[
        {
            "category":"Social Services",
            "subcategory":"Adult Care",
            "type":"Services"
        }
    ],
    "sg:phone":"+1 419 482 6032",
    "sg:postcode":"43537",
    "sg:province":"OH",
    "sg:tags":[
        "foster"
    ],
    "wof:name":"Ohio Youth Advocate Program",
    "wof:placetype":"venue"
},
  "geometry": {"coordinates":[-83.657579,41.585607],"type":"Point"}
}