{
  "type": "Feature",
  "properties": {
    "addr:full": "5990 State Rte 128 Cleves OH 45002",
    "addr:housenumber": "5990",
    "addr:postcode": "45002",
    "addr:street": "State Rte 128",
    "iso:country": "US",
    "sg:address": "5990 State Rte 128",
    "sg:city": "Cleves",
    "sg:classifiers": [
      {
        "category": "Retail",
        "subcategory": "Veterinary Services",
        "type": "Services"
      }
    ],
    "sg:phone": "+1 513 353 1229",
    "sg:postcode": "45002",
    "sg:province": "OH",
    "sg:tags": [
      "veterinarian"
    ],
    "wof:name": "Miamitown Pet Hospital",
    "wof:placetype": "venue"
  },
  "geometry": {"coordinates":[-84.722388,39.202084],"type":"Point"}
}
