{
  "type": "Feature",
  "properties": {
    "addr:full": "601 Miami St Tiffin OH 44883",
    "addr:housenumber": "601",
    "addr:postcode": "44883",
    "addr:street": "Miami St",
    "iso:country": "US",
    "sg:address": "601 Miami St",
    "sg:city": "Tiffin",
    "sg:classifiers": [
      {
        "category": "Building \u0026 Trades",
        "subcategory": "Construction",
        "type": "Services"
      }
    ],
    "sg:phone": "+1 419 448 5430",
    "sg:postcode": "44883",
    "sg:province": "OH",
    "sg:tags": [
      "marking",
      "maintenance",
      "parking"
    ],
    "wof:name": "Tiffin Public Works Dept",
    "wof:placetype": "venue"
  },
  "geometry": {"coordinates":[-83.201567,41.116871],"type":"Point"}
}
