{
  "type": "Feature",
  "properties": {
    "iso:country":"US",
    "sg:address":"3501 Pleasant Ave",
    "sg:city":"Hamilton",
    "sg:classifiers":[
        {
            "category":"Organizations",
            "subcategory":"Religious Organization",
            "type":"Services"
        }
    ],
    "sg:phone":"+1 513 863 8822",
    "sg:postcode":"45015",
    "sg:province":"OH",
    "sg:tags":[
        "church"
    ],
    "sg:website":"www.lindenwaldumc.org",
    "wof:name":"Lindenwald United Methodist",
    "wof:placetype":"venue"
},
  "geometry": {"coordinates":[-84.558268,39.359292],"type":"Point"}
}