{
  "type": "Feature",
  "properties": {
    "addr:full": "770 E Buchtel Ave Akron OH 44305",
    "addr:housenumber": "770",
    "addr:postcode": "44305",
    "addr:street": "E Buchtel Ave",
    "iso:country": "US",
    "sg:address": "770 E Buchtel Ave",
    "sg:city": "Akron",
    "sg:classifiers": [
      {
        "category": "Real Estate",
        "subcategory": "Real Estate Operator",
        "type": "Services"
      }
    ],
    "sg:phone": "+1 330 253 5058",
    "sg:postcode": "44305",
    "sg:province": "OH",
    "sg:tags": [
      "apartment"
    ],
    "wof:name": "Buchtel Apartments",
    "wof:placetype": "venue"
  },
  "geometry": {"coordinates":[-81.494038,41.076559],"type":"Point"}
}
