{
  "type": "Feature",
  "properties": {
    "iso:country":"US",
    "sg:address":"770 E Buchtel Ave",
    "sg:city":"Akron",
    "sg:classifiers":[
        {
            "category":"Real Estate",
            "subcategory":"Real Estate Operator",
            "type":"Services"
        }
    ],
    "sg:phone":"+1 330 253 5058",
    "sg:postcode":"44305",
    "sg:province":"OH",
    "sg:tags":[
        "apartment"
    ],
    "wof:name":"Buchtel Apartments",
    "wof:placetype":"venue"
},
  "geometry": {"coordinates":[-81.494038,41.076559],"type":"Point"}
}