{
  "type": "Feature",
  "properties": {
    "iso:country":"US",
    "sg:address":"905 River Rd",
    "sg:city":"Granville",
    "sg:classifiers":[
        {
            "category":"Professional",
            "subcategory":"Management & Consulting",
            "type":"Services"
        }
    ],
    "sg:phone":"+1 740 587 1444",
    "sg:postcode":"43023",
    "sg:province":"OH",
    "sg:tags":[
        "marketing",
        "consultant"
    ],
    "wof:name":"Dsb Marketing Group",
    "wof:placetype":"venue"
},
  "geometry": {"coordinates":[-82.518396,40.058805],"type":"Point"}
}