{
  "type": "Feature",
  "properties": {
    "addr:full": "1001 Cherry Valley Rd SE Newark OH 43055",
    "addr:housenumber": "1001",
    "addr:postcode": "43055",
    "addr:street": "Cherry Valley Rd Se",
    "iso:country": "US",
    "sg:address": "1001 Cherry Valley Rd SE",
    "sg:city": "Newark",
    "sg:classifiers": [
      {
        "category": "Restaurant",
        "type": "Food \u0026 Drink"
      }
    ],
    "sg:menulink": "http://www.allmenus.com/oh/newark/44159-bob-evans/menu/",
    "sg:phone": "+1 740 522 3834",
    "sg:postcode": "43055",
    "sg:province": "OH",
    "sg:tags": [
      "american"
    ],
    "wof:name": "Bob Evans",
    "wof:placetype": "venue"
  },
  "geometry": {"coordinates":[-82.465949,40.042809],"type":"Point"}
}
