{
  "type": "Feature",
  "properties": {
    "addr:full":"14032 State Rte 15 Defiance OH 43512",
    "addr:housenumber":"14032",
    "addr:postcode":"43512",
    "addr:street":"State Rte 15",
    "iso:country":"US",
    "sg:address":"14032 State Rte 15",
    "sg:city":"Defiance",
    "sg:classifiers":[
        {
            "category":"Building & Trades",
            "subcategory":"Landscaping Services",
            "type":"Services"
        }
    ],
    "sg:phone":"+1 419 395 2515",
    "sg:postcode":"43512",
    "sg:province":"OH",
    "wof:name":"Chiccotelli Designs",
    "wof:placetype":"venue"
},
  "geometry": {"coordinates":[-84.34170399999999,41.237847],"type":"Point"}
}