{
  "type": "Feature",
  "properties": {
    "addr:full": "2950 US Hwy 68 N Bellefontaine OH 43311",
    "addr:housenumber": "2950",
    "addr:postcode": "43311",
    "addr:street": "Us Hwy 68 N",
    "iso:country": "US",
    "sg:address": "2950 US Hwy 68 N",
    "sg:city": "Bellefontaine",
    "sg:classifiers": [
      {
        "category": "Freight",
        "type": "Transportation"
      }
    ],
    "sg:phone": "+1 937 599 1744",
    "sg:postcode": "43311",
    "sg:province": "OH",
    "sg:tags": [
      "commercial",
      "storage"
    ],
    "wof:name": "Hi-Point Storage",
    "wof:placetype": "venue"
  },
  "geometry": {"coordinates":[-83.760964,40.324501],"type":"Point"}
}
