{
  "type": "Feature",
  "properties": {
    "iso:country":"US",
    "sg:address":"3032 Perry Park Rd",
    "sg:city":"Perry",
    "sg:classifiers":[
        {
            "category":"Organizations",
            "subcategory":"Non-profit Organization",
            "type":"Services"
        }
    ],
    "sg:phone":"+1 440 259 3333",
    "sg:postcode":"44081",
    "sg:province":"OH",
    "sg:tags":[
        "information",
        "alcoholism",
        "treatment"
    ],
    "wof:name":"Teen Challenge",
    "wof:placetype":"venue"
},
  "geometry": {"coordinates":[-81.16392999999999,41.788808],"type":"Point"}
}