{
  "type": "Feature",
  "properties": {
    "addr:full": "82 Seaman Dr Jamestown OH 45335",
    "addr:housenumber": "82",
    "addr:postcode": "45335",
    "addr:street": "Seaman Dr",
    "iso:country": "US",
    "sg:address": "82 Seaman Dr",
    "sg:city": "Jamestown",
    "sg:classifiers": [
      {
        "category": "Home \u0026 Garden",
        "subcategory": "Hardware",
        "type": "Retail Goods"
      }
    ],
    "sg:phone": "+1 937 675 6744",
    "sg:postcode": "45335",
    "sg:province": "OH",
    "wof:name": "D \u0026 B Village Hardware",
    "wof:placetype": "venue"
  },
  "geometry": {"coordinates":[-83.741335,39.658343],"type":"Point"}
}
