{
  "type": "Feature",
  "properties": {
    "addr:full":"3232 Logan-Lancaster Rd Lancaster OH 43130",
    "addr:housenumber":"3232",
    "addr:postcode":"43130",
    "addr:street":"Logan-Lancaster Rd",
    "iso:country":"US",
    "sg:address":"3232 Logan-Lancaster Rd",
    "sg:city":"Lancaster",
    "sg:classifiers":[
        {
            "category":"Wholesale",
            "subcategory":"Construction Materials",
            "type":"Manufacturing & Wholesale Goods"
        }
    ],
    "sg:phone":"+1 740 687 0164",
    "sg:postcode":"43130",
    "sg:province":"OH",
    "sg:tags":[
        "sand",
        "gravel"
    ],
    "wof:name":"Lancaster Sand & Gravel",
    "wof:placetype":"venue"
},
  "geometry": {"coordinates":[-82.56662300000001,39.679384],"type":"Point"}
}