{
  "type": "Feature",
  "properties": {
    "iso:country":"US",
    "sg:address":"1600 Hinckley Hills Rd",
    "sg:city":"Hinckley",
    "sg:classifiers":[
        {
            "category":"Building & Trades",
            "subcategory":"Construction",
            "type":"Services"
        }
    ],
    "sg:phone":"+1 330 278 2300",
    "sg:postcode":"44233",
    "sg:province":"OH",
    "sg:tags":[
        "excavating",
        "contractor"
    ],
    "wof:name":"De Hoff & Co",
    "wof:placetype":"venue"
},
  "geometry": {"coordinates":[-81.723935,41.230027],"type":"Point"}
}