{
  "type": "Feature",
  "properties": {
    "addr:full": "1600 Hinckley Hills Rd Hinckley OH 44233",
    "addr:housenumber": "1600",
    "addr:postcode": "44233",
    "addr:street": "Hinckley Hills Rd",
    "iso:country": "US",
    "sg:address": "1600 Hinckley Hills Rd",
    "sg:city": "Hinckley",
    "sg:classifiers": [
      {
        "category": "Building \u0026 Trades",
        "subcategory": "Construction",
        "type": "Services"
      }
    ],
    "sg:phone": "+1 330 278 2300",
    "sg:postcode": "44233",
    "sg:province": "OH",
    "sg:tags": [
      "excavating",
      "contractor"
    ],
    "wof:name": "De Hoff \u0026 Co",
    "wof:placetype": "venue"
  },
  "geometry": {"coordinates":[-81.723935,41.230027],"type":"Point"}
}
