{
  "type": "Feature",
  "properties": {
    "iso:country":"US",
    "sg:address":"2084 N Dixie Hwy",
    "sg:city":"Lima",
    "sg:classifiers":[
        {
            "category":"Autos & Motor Vehicles",
            "subcategory":"Automobile Sales",
            "type":"Retail Goods"
        }
    ],
    "sg:phone":"+1 419 222 8785",
    "sg:postcode":"45801",
    "sg:province":"OH",
    "sg:tags":[
        "car",
        "dealer"
    ],
    "wof:name":"North Dixie Truck & Trailer",
    "wof:placetype":"venue"
},
  "geometry": {"coordinates":[-84.05595599999999,40.765444],"type":"Point"}
}