{
  "type": "Feature",
  "properties": {
    "addr:full": "2084 N Dixie Hwy Lima OH 45801",
    "addr:housenumber": "2084",
    "addr:postcode": "45801",
    "addr:street": "N Dixie Hwy",
    "iso:country": "US",
    "sg:address": "2084 N Dixie Hwy",
    "sg:city": "Lima",
    "sg:classifiers": [
      {
        "category": "Autos \u0026 Motor Vehicles",
        "subcategory": "Automobile Sales",
        "type": "Retail Goods"
      }
    ],
    "sg:phone": "+1 419 222 8785",
    "sg:postcode": "45801",
    "sg:province": "OH",
    "sg:tags": [
      "car",
      "dealer"
    ],
    "wof:name": "North Dixie Truck \u0026 Trailer",
    "wof:placetype": "venue"
  },
  "geometry": {"coordinates":[-84.055956,40.765444],"type":"Point"}
}
