{
  "type": "Feature",
  "properties": {
    "addr:full": "31390 Viking Pkwy Cleveland OH 44145",
    "addr:housenumber": "31390",
    "addr:postcode": "44145",
    "addr:street": "Viking Pkwy",
    "iso:country": "US",
    "sg:address": "31390 Viking Pkwy",
    "sg:city": "Cleveland",
    "sg:classifiers": [
      {
        "category": "Manufacturing",
        "subcategory": "Metals",
        "type": "Manufacturing \u0026 Wholesale Goods"
      }
    ],
    "sg:phone": "+1 440 835 5601",
    "sg:postcode": "44145",
    "sg:province": "OH",
    "sg:tags": [
      "product",
      "wire"
    ],
    "wof:name": "Industrial Electric Wire",
    "wof:placetype": "venue"
  },
  "geometry": {"coordinates":[-81.960676,41.472429],"type":"Point"}
}
