{
  "type": "Feature",
  "properties": {
    "addr:full": "56 Urbana Ave Dayton OH 45404",
    "addr:housenumber": "56",
    "addr:postcode": "45404",
    "addr:street": "Urbana Ave",
    "iso:country": "US",
    "sg:address": "56 Urbana Ave",
    "sg:city": "Dayton",
    "sg:classifiers": [
      {
        "category": "Freight",
        "type": "Transportation"
      }
    ],
    "sg:phone": "+1 937 226 7451",
    "sg:postcode": "45404",
    "sg:province": "OH",
    "sg:tags": [
      "mover"
    ],
    "wof:name": "Daniel Movers",
    "wof:placetype": "venue"
  },
  "geometry": {"coordinates":[-84.159696,39.783773],"type":"Point"}
}
