{
  "type": "Feature",
  "properties": {
    "iso:country":"US",
    "sg:address":"3390 E 145th St",
    "sg:city":"Cleveland",
    "sg:classifiers":[
        {
            "category":"Real Estate",
            "subcategory":"Real Estate Agent",
            "type":"Services"
        }
    ],
    "sg:phone":"+1 216 991 6663",
    "sg:postcode":"44120",
    "sg:province":"OH",
    "wof:name":"Cor Rae Realty",
    "wof:placetype":"venue"
},
  "geometry": {"coordinates":[-81.581062,41.470866],"type":"Point"}
}