{
  "type": "Feature",
  "properties": {
    "addr:full":"919 Hostetler Rd Orrville OH 44667",
    "addr:housenumber":"919",
    "addr:postcode":"44667",
    "addr:street":"Hostetler Rd",
    "iso:country":"US",
    "sg:address":"919 Hostetler Rd",
    "sg:city":"Orrville",
    "sg:classifiers":[
        {
            "category":"Building & Trades",
            "subcategory":"Cleaning & Sanitation",
            "type":"Services"
        }
    ],
    "sg:phone":"+1 330 682 1459",
    "sg:postcode":"44667",
    "sg:province":"OH",
    "sg:tags":[
        "polishing",
        "waxing",
        "floor"
    ],
    "wof:name":"Independent Professional Floor",
    "wof:placetype":"venue"
},
  "geometry": {"coordinates":[-81.774564,40.854555],"type":"Point"}
}