{
  "type": "Feature",
  "properties": {
    "addr:full": "20875 Lake Rd Rocky River OH 44116",
    "addr:housenumber": "20875",
    "addr:postcode": "44116",
    "addr:street": "Lake Rd",
    "iso:country": "US",
    "sg:address": "20875 Lake Rd",
    "sg:city": "Rocky River",
    "sg:classifiers": [
      {
        "category": "Utilities",
        "subcategory": "Telephone",
        "type": "Services"
      }
    ],
    "sg:phone": "+1 440 720 2389",
    "sg:postcode": "44116",
    "sg:province": "OH",
    "sg:tags": [
      "communications"
    ],
    "wof:name": "Donald Culp",
    "wof:placetype": "venue"
  },
  "geometry": {"coordinates":[-81.848797,41.483062],"type":"Point"}
}
