{
  "type": "Feature",
  "properties": {
    "addr:full": "3168 Harrison Ave Cincinnati OH 45211",
    "addr:housenumber": "3168",
    "addr:postcode": "45211",
    "addr:street": "Harrison Ave",
    "iso:country": "US",
    "sg:address": "3168 Harrison Ave",
    "sg:city": "Cincinnati",
    "sg:classifiers": [
      {
        "category": "Banks \u0026 Credit Unions",
        "subcategory": "Bank",
        "type": "Services"
      }
    ],
    "sg:phone": "+1 513 389 4212",
    "sg:postcode": "45211",
    "sg:province": "OH",
    "wof:name": "US Bank",
    "wof:placetype": "venue"
  },
  "geometry": {"coordinates":[-84.602558,39.153293],"type":"Point"}
}
