{
  "type": "Feature",
  "properties": {
    "addr:full":"6830 Franklin Lebanon Rd Franklin OH 45005",
    "addr:housenumber":"6830",
    "addr:postcode":"45005",
    "addr:street":"Franklin Lebanon Rd",
    "iso:country":"US",
    "sg:address":"6830 Franklin Lebanon Rd",
    "sg:city":"Franklin",
    "sg:classifiers":[
        {
            "category":"Autos & Motor Vehicles",
            "subcategory":"Fuel & Gas Station",
            "type":"Retail Goods"
        }
    ],
    "sg:phone":"+1 513 746 4409",
    "sg:postcode":"45005",
    "sg:province":"OH",
    "sg:tags":[
        "gasoline",
        "station",
        "eating"
    ],
    "wof:name":"Subway",
    "wof:placetype":"venue"
},
  "geometry": {"coordinates":[-84.2915,39.541706],"type":"Point"}
}