{
  "type": "Feature",
  "properties": {
    "addr:full": "9437 Shepler Church Ave SW Navarre OH 44662",
    "addr:housenumber": "9437",
    "addr:postcode": "44662",
    "addr:street": "Shepler Church Ave Sw",
    "iso:country": "US",
    "sg:address": "9437 Shepler Church Ave SW",
    "sg:city": "Navarre",
    "sg:classifiers": [
      {
        "category": "Banks \u0026 Credit Unions",
        "subcategory": "Financial Services",
        "type": "Services"
      }
    ],
    "sg:phone": "+1 330 874 2700",
    "sg:postcode": "44662",
    "sg:province": "OH",
    "sg:tags": [
      "company",
      "bank",
      "holding"
    ],
    "wof:name": "Wildcat Leasing Inc",
    "wof:placetype": "venue"
  },
  "geometry": {"coordinates":[-81.473505,40.656531],"type":"Point"}
}
