{
  "type": "Feature",
  "properties": {
    "addr:full": "110 W Herrick Ave Wellington OH 44090",
    "addr:housenumber": "110",
    "addr:postcode": "44090",
    "addr:street": "W Herrick Ave",
    "iso:country": "US",
    "sg:address": "110 W Herrick Ave",
    "sg:city": "Wellington",
    "sg:classifiers": [
      {
        "category": "Professional",
        "subcategory": "Lawyer \u0026 Legal Services",
        "type": "Services"
      }
    ],
    "sg:phone": "+1 440 647 4219",
    "sg:postcode": "44090",
    "sg:province": "OH",
    "sg:tags": [
      "attorney"
    ],
    "wof:name": "Baumgartner \u0026 O'Toole",
    "wof:placetype": "venue"
  },
  "geometry": {"coordinates":[-82.217848,41.168642],"type":"Point"}
}
