{
  "type": "Feature",
  "properties": {
    "iso:country":"US",
    "sg:address":"110 W Herrick Ave",
    "sg:city":"Wellington",
    "sg:classifiers":[
        {
            "category":"Professional",
            "subcategory":"Lawyer & Legal Services",
            "type":"Services"
        }
    ],
    "sg:phone":"+1 440 647 4219",
    "sg:postcode":"44090",
    "sg:province":"OH",
    "sg:tags":[
        "attorney"
    ],
    "wof:name":"Baumgartner & O'Toole",
    "wof:placetype":"venue"
},
  "geometry": {"coordinates":[-82.217848,41.168642],"type":"Point"}
}