{
  "type": "Feature",
  "properties": {
    "addr:full": "9685 Washington St Chagrin Falls OH 44023",
    "addr:housenumber": "9685",
    "addr:postcode": "44023",
    "addr:street": "Washington St",
    "iso:country": "US",
    "sg:address": "9685 Washington St",
    "sg:city": "Chagrin Falls",
    "sg:classifiers": [
      {
        "category": "Autos \u0026 Motor Vehicles",
        "subcategory": "Auto Supplies",
        "type": "Retail Goods"
      },
      {
        "category": "Retail",
        "subcategory": "Auto Repair",
        "type": "Services"
      }
    ],
    "sg:phone": "+1 440 543 2929",
    "sg:postcode": "44023",
    "sg:province": "OH",
    "sg:tags": [
      "tire"
    ],
    "wof:name": "A B Tire \u0026 Repair",
    "wof:placetype": "venue"
  },
  "geometry": {"coordinates":[-81.296794,41.395349],"type":"Point"}
}
