{
  "type": "Feature",
  "properties": {
    "iso:country":"US",
    "sg:address":"253 Airport Rd SE",
    "sg:city":"Carrollton",
    "sg:classifiers":[
        {
            "category":"Restaurant",
            "type":"Food & Drink"
        }
    ],
    "sg:phone":"+1 330 627 5250",
    "sg:postcode":"44615",
    "sg:province":"OH",
    "wof:name":"Carroll County Airport",
    "wof:placetype":"venue"
},
  "geometry": {"coordinates":[-81.078213,40.562259],"type":"Point"}
}