{
  "type": "Feature",
  "properties": {
    "addr:full": "253 Airport Rd SE Carrollton OH 44615",
    "addr:housenumber": "253",
    "addr:postcode": "44615",
    "addr:street": "Airport Rd Se",
    "iso:country": "US",
    "sg:address": "253 Airport Rd SE",
    "sg:city": "Carrollton",
    "sg:classifiers": [
      {
        "category": "Restaurant",
        "type": "Food \u0026 Drink"
      }
    ],
    "sg:phone": "+1 330 627 5250",
    "sg:postcode": "44615",
    "sg:province": "OH",
    "wof:name": "Carroll County Airport",
    "wof:placetype": "venue"
  },
  "geometry": {"coordinates":[-81.078213,40.562259],"type":"Point"}
}
