{
  "type": "Feature",
  "properties": {
    "addr:full":"15986 State Rte 56 E Laurelville OH 43135",
    "addr:housenumber":"15986",
    "addr:postcode":"43135",
    "addr:street":"State Rte 56 E Laurelville",
    "iso:country":"US",
    "sg:address":"15986 State Rte 56 E",
    "sg:city":"Laurelville",
    "sg:classifiers":[
        {
            "category":"Food & Beverages",
            "subcategory":"Groceries & Convenience Stores",
            "type":"Retail Goods"
        }
    ],
    "sg:phone":"+1 740 332 8822",
    "sg:postcode":"43135",
    "sg:province":"OH",
    "sg:tags":[
        "grocer"
    ],
    "wof:name":"Young's Family Market",
    "wof:placetype":"venue"
},
  "geometry": {"coordinates":[-82.741393,39.47383],"type":"Point"}
}