{
  "type": "Feature",
  "properties": {
    "addr:full":"2326 Garden Creek Dr Maumee OH 43537",
    "addr:housenumber":"2326",
    "addr:postcode":"43537",
    "addr:street":"Garden Creek Dr",
    "iso:country":"US",
    "sg:address":"2326 Garden Creek Dr",
    "sg:city":"Maumee",
    "sg:classifiers":[
        {
            "category":"Real Estate",
            "subcategory":"Real Estate Agent",
            "type":"Services"
        }
    ],
    "sg:phone":"+1 419 865 9078",
    "sg:postcode":"43537",
    "sg:province":"OH",
    "wof:name":"Richard N Billmaier LLC",
    "wof:placetype":"venue"
},
  "geometry": {"coordinates":[-83.709433,41.599226],"type":"Point"}
}