{
  "type": "Feature",
  "properties": {
    "addr:full":"5118 Clancy Ct Gahanna OH 43230",
    "addr:housenumber":"5118",
    "addr:postcode":"43230",
    "addr:street":"Clancy Ct",
    "iso:country":"US",
    "sg:address":"5118 Clancy Ct",
    "sg:city":"Gahanna",
    "sg:classifiers":[
        {
            "category":"Building & Trades",
            "subcategory":"Landscaping Services",
            "type":"Services"
        }
    ],
    "sg:phone":"+1 614 478 2973",
    "sg:postcode":"43230",
    "sg:province":"OH",
    "sg:tags":[
        "lawn",
        "maintenance",
        "grounds"
    ],
    "wof:name":"Staygreen Lawn Svc",
    "wof:placetype":"venue"
},
  "geometry": {"coordinates":[-82.89147800000001,40.078526],"type":"Point"}
}