{
  "type": "Feature",
  "properties": {
    "addr:full":"909 Hickok Rd Jefferson OH 44047",
    "addr:housenumber":"909",
    "addr:postcode":"44047",
    "addr:street":"Hickok Rd",
    "iso:country":"US",
    "sg:address":"909 Hickok Rd",
    "sg:city":"Jefferson",
    "sg:classifiers":[
        {
            "category":"Organizations",
            "subcategory":"Community Association",
            "type":"Services"
        }
    ],
    "sg:phone":"+1 440 576 1581",
    "sg:postcode":"44047",
    "sg:province":"OH",
    "wof:name":"Delta Kppa Gmma Soc Intrntonal",
    "wof:placetype":"venue"
},
  "geometry": {"coordinates":[-80.799098,41.740543],"type":"Point"}
}