{
  "type": "Feature",
  "properties": {
    "addr:full": "1302 Gary Blvd Brunswick OH 44212",
    "addr:housenumber": "1302",
    "addr:postcode": "44212",
    "addr:street": "Gary Blvd",
    "iso:country": "US",
    "sg:address": "1302 Gary Blvd",
    "sg:city": "Brunswick",
    "sg:classifiers": [
      {
        "category": "Manufacturing",
        "subcategory": "Toys \u0026 Sporting Goods",
        "type": "Manufacturing \u0026 Wholesale Goods"
      }
    ],
    "sg:phone": "+1 330 225 3342",
    "sg:postcode": "44212",
    "sg:province": "OH",
    "sg:tags": [
      "mfg"
    ],
    "wof:name": "Accurate RC Services",
    "wof:placetype": "venue"
  },
  "geometry": {"coordinates":[-81.830304,41.239416],"type":"Point"}
}
