{
  "type": "Feature",
  "properties": {
    "iso:country":"US",
    "sg:address":"7038 Linwood Ave",
    "sg:city":"Cleveland",
    "sg:classifiers":[
        {
            "category":"Food & Beverages",
            "subcategory":"Groceries & Convenience Stores",
            "type":"Retail Goods"
        }
    ],
    "sg:phone":"+1 216 391 0102",
    "sg:postcode":"44103",
    "sg:province":"OH",
    "wof:name":"Greens Linwood Deli",
    "wof:placetype":"venue"
},
  "geometry": {"coordinates":[-81.640069,41.512271],"type":"Point"}
}