{
  "type": "Feature",
  "properties": {
    "addr:full": "7038 Linwood Ave Cleveland OH 44103",
    "addr:housenumber": "7038",
    "addr:postcode": "44103",
    "addr:street": "Linwood Ave",
    "iso:country": "US",
    "sg:address": "7038 Linwood Ave",
    "sg:city": "Cleveland",
    "sg:classifiers": [
      {
        "category": "Food \u0026 Beverages",
        "subcategory": "Groceries \u0026 Convenience Stores",
        "type": "Retail Goods"
      }
    ],
    "sg:phone": "+1 216 391 0102",
    "sg:postcode": "44103",
    "sg:province": "OH",
    "wof:name": "Greens Linwood Deli",
    "wof:placetype": "venue"
  },
  "geometry": {"coordinates":[-81.640069,41.512271],"type":"Point"}
}
