{
  "type": "Feature",
  "properties": {
    "addr:full": "49862 State Rte 513 Summerfield OH 43788",
    "addr:housenumber": "49862",
    "addr:postcode": "43788",
    "addr:street": "State Rte 513",
    "iso:country": "US",
    "sg:address": "49862 State Rte 513",
    "sg:city": "Summerfield",
    "sg:classifiers": [
      {
        "category": "Travel",
        "subcategory": "Hotels \u0026 Motels",
        "type": "Entertainment"
      }
    ],
    "sg:phone": "+1 740 838 6000",
    "sg:postcode": "43788",
    "sg:province": "OH",
    "wof:name": "Traders",
    "wof:placetype": "venue"
  },
  "geometry": {"coordinates":[-81.331106,39.816779],"type":"Point"}
}
