{
  "type": "Feature",
  "properties": {
    "addr:full":"7536 Brandt Pike Dayton OH 45424",
    "addr:housenumber":"7536",
    "addr:postcode":"45424",
    "addr:street":"Brandt Pike",
    "iso:country":"US",
    "sg:address":"7536 Brandt Pike",
    "sg:city":"Dayton",
    "sg:classifiers":[
        {
            "category":"Autos & Motor Vehicles",
            "subcategory":"Fuel & Gas Station",
            "type":"Retail Goods"
        }
    ],
    "sg:phone":"+1 937 235 0450",
    "sg:postcode":"45424",
    "sg:province":"OH",
    "sg:tags":[
        "station",
        "gasoline"
    ],
    "wof:name":"Smokes For Less",
    "wof:placetype":"venue"
},
  "geometry": {"coordinates":[-84.103711,39.862014],"type":"Point"}
}