{
  "type": "Feature",
  "properties": {
    "iso:country":"US",
    "sg:address":"477 Dussel Dr",
    "sg:city":"Maumee",
    "sg:classifiers":[
        {
            "category":"Professional",
            "subcategory":"Business Services",
            "type":"Services"
        }
    ],
    "sg:phone":"+1 419 891 1200",
    "sg:postcode":"43537",
    "sg:province":"OH",
    "sg:tags":[
        "embroidery"
    ],
    "wof:name":"Embroidme",
    "wof:placetype":"venue"
},
  "geometry": {"coordinates":[-83.657341,41.58576],"type":"Point"}
}