{
  "type": "Feature",
  "properties": {
    "addr:full": "1100 Breezewood Ct Findlay OH 45840",
    "addr:housenumber": "1100",
    "addr:postcode": "45840",
    "addr:street": "Breezewood Ct",
    "iso:country": "US",
    "sg:address": "1100 Breezewood Ct",
    "sg:city": "Findlay",
    "sg:classifiers": [
      {
        "category": "Personal",
        "subcategory": "Beauty Salon",
        "type": "Services"
      }
    ],
    "sg:phone": "+1 419 424 0284",
    "sg:postcode": "45840",
    "sg:province": "OH",
    "wof:name": "New Attitude Styling Salon",
    "wof:placetype": "venue"
  },
  "geometry": {"coordinates":[-83.631222,41.025375],"type":"Point"}
}
