{
  "type": "Feature",
  "properties": {
    "addr:full": "546 Graham Rd Cuyahoga Falls OH 44221",
    "addr:housenumber": "546",
    "addr:postcode": "44221",
    "addr:street": "Graham Rd",
    "iso:country": "US",
    "sg:address": "546 Graham Rd",
    "sg:city": "Cuyahoga Falls",
    "sg:classifiers": [
      {
        "category": "Wholesale",
        "subcategory": "Durable Goods \u0026 Equipment",
        "type": "Manufacturing \u0026 Wholesale Goods"
      }
    ],
    "sg:phone": "+1 330 926 1663",
    "sg:postcode": "44221",
    "sg:province": "OH",
    "wof:name": "Vegas Game Supply",
    "wof:placetype": "venue"
  },
  "geometry": {"coordinates":[-81.492067,41.158705],"type":"Point"}
}
