{
  "type": "Feature",
  "properties": {
    "iso:country":"US",
    "sg:address":"546 Graham Rd",
    "sg:city":"Cuyahoga Falls",
    "sg:classifiers":[
        {
            "category":"Wholesale",
            "subcategory":"Durable Goods & Equipment",
            "type":"Manufacturing & Wholesale Goods"
        }
    ],
    "sg:phone":"+1 330 926 1663",
    "sg:postcode":"44221",
    "sg:province":"OH",
    "wof:name":"Vegas Game Supply",
    "wof:placetype":"venue"
},
  "geometry": {"coordinates":[-81.49206700000001,41.158705],"type":"Point"}
}