{
  "type": "Feature",
  "properties": {
    "iso:country":"US",
    "sg:address":"2241 W Spring St",
    "sg:city":"Lima",
    "sg:classifiers":[
        {
            "category":"Home & Garden",
            "subcategory":"Household Appliances",
            "type":"Retail Goods"
        }
    ],
    "sg:phone":"+1 419 227 2431",
    "sg:postcode":"45805",
    "sg:province":"OH",
    "sg:tags":[
        "cleaners",
        "vacuum"
    ],
    "wof:name":"Rainbow Air Sales & Svc",
    "wof:placetype":"venue"
},
  "geometry": {"coordinates":[-84.15078699999999,40.737862],"type":"Point"}
}