{
  "type": "Feature",
  "properties": {
    "addr:full": "2241 W Spring St Lima OH 45805",
    "addr:housenumber": "2241",
    "addr:postcode": "45805",
    "addr:street": "W Spring St",
    "iso:country": "US",
    "sg:address": "2241 W Spring St",
    "sg:city": "Lima",
    "sg:classifiers": [
      {
        "category": "Home \u0026 Garden",
        "subcategory": "Household Appliances",
        "type": "Retail Goods"
      }
    ],
    "sg:phone": "+1 419 227 2431",
    "sg:postcode": "45805",
    "sg:province": "OH",
    "sg:tags": [
      "cleaners",
      "vacuum"
    ],
    "wof:name": "Rainbow Air Sales \u0026 Svc",
    "wof:placetype": "venue"
  },
  "geometry": {"coordinates":[-84.150787,40.737862],"type":"Point"}
}
