{
  "type": "Feature",
  "properties": {
    "iso:country":"US",
    "sg:address":"7781 Broadview Rd",
    "sg:city":"Cleveland",
    "sg:classifiers":[
        {
            "category":"Banks & Credit Unions",
            "subcategory":"Bank",
            "type":"Services"
        }
    ],
    "sg:phone":"+1 216 524 2995",
    "sg:postcode":"44131",
    "sg:province":"OH",
    "sg:tags":[
        "national",
        "commercial"
    ],
    "sg:website":"www.nationalcity.com",
    "wof:name":"National City Bank",
    "wof:placetype":"venue"
},
  "geometry": {"coordinates":[-81.684575,41.355292],"type":"Point"}
}