{
  "type": "Feature",
  "properties": {
    "addr:full": "2025 Guadalupe Ave Youngstown OH 44504",
    "addr:housenumber": "2025",
    "addr:postcode": "44504",
    "addr:street": "Guadalupe Ave",
    "iso:country": "US",
    "sg:address": "2025 Guadalupe Ave",
    "sg:city": "Youngstown",
    "sg:classifiers": [
      {
        "category": "Recreation",
        "type": "Entertainment"
      }
    ],
    "sg:phone": "+1 216 426 8888",
    "sg:postcode": "44504",
    "sg:province": "OH",
    "sg:tags": [
      "ticket"
    ],
    "wof:name": "TICKETYCITY.COM",
    "wof:placetype": "venue"
  },
  "geometry": {"coordinates":[-80.659576,41.127639],"type":"Point"}
}
