{
  "type": "Feature",
  "properties": {
    "iso:country":"US",
    "sg:address":"2025 Guadalupe Ave",
    "sg:city":"Youngstown",
    "sg:classifiers":[
        {
            "category":"Recreation",
            "type":"Entertainment"
        }
    ],
    "sg:phone":"+1 216 426 8888",
    "sg:postcode":"44504",
    "sg:province":"OH",
    "sg:tags":[
        "ticket"
    ],
    "wof:name":"TICKETYCITY.COM",
    "wof:placetype":"venue"
},
  "geometry": {"coordinates":[-80.659576,41.127639],"type":"Point"}
}