{
  "type": "Feature",
  "properties": {
    "addr:full": "8226 Grey Abby Ct Dublin OH 43017",
    "addr:housenumber": "8226",
    "addr:postcode": "43017",
    "addr:street": "Grey Abby Ct",
    "iso:country": "US",
    "sg:address": "8226 Grey Abby Ct",
    "sg:city": "Dublin",
    "sg:classifiers": [
      {
        "category": "Professional",
        "subcategory": "Employment Agencies",
        "type": "Services"
      }
    ],
    "sg:phone": "+1 614 761 2095",
    "sg:postcode": "43017",
    "sg:province": "OH",
    "sg:tags": [
      "opportunity"
    ],
    "wof:name": "Employment Services",
    "wof:placetype": "venue"
  },
  "geometry": {"coordinates":[-83.118367,40.134423],"type":"Point"}
}
