{
  "type": "Feature",
  "properties": {
    "iso:country":"US",
    "sg:address":"8226 Grey Abby Ct",
    "sg:city":"Dublin",
    "sg:classifiers":[
        {
            "category":"Professional",
            "subcategory":"Employment Agencies",
            "type":"Services"
        }
    ],
    "sg:phone":"+1 614 761 2095",
    "sg:postcode":"43017",
    "sg:province":"OH",
    "sg:tags":[
        "opportunity"
    ],
    "wof:name":"Employment Services",
    "wof:placetype":"venue"
},
  "geometry": {"coordinates":[-83.11836700000001,40.134423],"type":"Point"}
}