{
  "type": "Feature",
  "properties": {
    "addr:full": "4230 Rose Hill Ave Cincinnati OH 45229",
    "addr:housenumber": "4230",
    "addr:postcode": "45229",
    "addr:street": "Rose Hill Ave",
    "iso:country": "US",
    "sg:address": "4230 Rose Hill Ave",
    "sg:city": "Cincinnati",
    "sg:classifiers": [
      {
        "category": "Real Estate",
        "subcategory": "Real Estate Operator",
        "type": "Services"
      }
    ],
    "sg:phone": "+1 513 281 7808",
    "sg:postcode": "45229",
    "sg:province": "OH",
    "sg:tags": [
      "building",
      "nonresidential"
    ],
    "wof:name": "J JW Enterprises",
    "wof:placetype": "venue"
  },
  "geometry": {"coordinates":[-84.488416,39.160788],"type":"Point"}
}
