{
  "type": "Feature",
  "properties": {
    "iso:country":"US",
    "sg:address":"31 Main St",
    "sg:city":"Greenwich",
    "sg:classifiers":[
        {
            "category":"Professional",
            "subcategory":"Computer Services",
            "type":"Services"
        }
    ],
    "sg:phone":"+1 419 752 8109",
    "sg:postcode":"44837",
    "sg:province":"OH",
    "sg:tags":[
        "repair"
    ],
    "wof:name":"Village PC Solutions",
    "wof:placetype":"venue"
},
  "geometry": {"coordinates":[-82.517191,41.029957],"type":"Point"}
}