{
  "type": "Feature",
  "properties": {
    "addr:full":"299 State St Kipton OH 44030",
    "addr:housenumber":"299",
    "addr:postcode":"44030",
    "addr:street":"State St",
    "iso:country":"US",
    "sg:address":"299 State St",
    "sg:city":"Kipton",
    "sg:classifiers":[
        {
            "category":"Government",
            "subcategory":"Office",
            "type":"Public Place"
        },
        {
            "category":"Government",
            "subcategory":"Police Station",
            "type":"Public Place"
        }
    ],
    "sg:phone":"+1 440 775 2525",
    "sg:postcode":"44030",
    "sg:province":"OH",
    "sg:tags":[
        "department",
        "village"
    ],
    "wof:name":"Kipton Village Police",
    "wof:placetype":"venue"
},
  "geometry": {"coordinates":[-80.557378,41.943998],"type":"Point"}
}