{
  "type": "Feature",
  "properties": {
    "addr:full":"206 E Ohio Ave Sebring OH 44672",
    "addr:housenumber":"206",
    "addr:postcode":"44672",
    "addr:street":"E Ohio Ave",
    "iso:country":"US",
    "sg:address":"206 E Ohio Ave",
    "sg:city":"Sebring",
    "sg:classifiers":[
        {
            "category":"Organizations",
            "subcategory":"Community Association",
            "type":"Services"
        }
    ],
    "sg:phone":"+1 330 938 9066",
    "sg:postcode":"44672",
    "sg:province":"OH",
    "sg:tags":[
        "military"
    ],
    "sg:website":"www.vfw.org",
    "wof:name":"Veterans Of Foreign Wars",
    "wof:placetype":"venue"
},
  "geometry": {"coordinates":[-81.016797,40.923171],"type":"Point"}
}