{
  "type": "Feature",
  "properties": {
    "addr:full": "6876 Casey Rd Mechanicsburg OH 43044",
    "addr:housenumber": "6876",
    "addr:postcode": "43044",
    "addr:street": "Casey Rd",
    "iso:country": "US",
    "sg:address": "6876 Casey Rd",
    "sg:city": "Mechanicsburg",
    "sg:classifiers": [
      {
        "category": "Professional",
        "type": "Services"
      }
    ],
    "sg:phone": "+1 937 828 1380",
    "sg:postcode": "43044",
    "sg:province": "OH",
    "wof:name": "Society of St Vincent Dep",
    "wof:placetype": "venue"
  },
  "geometry": {"coordinates":[-83.626926,40.04516],"type":"Point"}
}
