{
  "type": "Feature",
  "properties": {
    "addr:full": "10765 Reading Rd Cincinnati OH 45241",
    "addr:housenumber": "10765",
    "addr:postcode": "45241",
    "addr:street": "Reading Rd",
    "iso:country": "US",
    "sg:address": "10765 Reading Rd",
    "sg:city": "Cincinnati",
    "sg:classifiers": [
      {
        "category": "Health Services",
        "subcategory": "Doctor",
        "type": "Services"
      }
    ],
    "sg:phone": "+1 513 956 5060",
    "sg:postcode": "45241",
    "sg:province": "OH",
    "wof:name": "Beacon Orthpedics Spt Medicine",
    "wof:placetype": "venue"
  },
  "geometry": {"coordinates":[-84.415799,39.263579],"type":"Point"}
}
