{
  "type": "Feature",
  "properties": {
    "addr:full":"1647 Mahala St Oregon OH 43616",
    "addr:housenumber":"1647",
    "addr:postcode":"43616",
    "addr:street":"Mahala St",
    "iso:country":"US",
    "sg:address":"1647 Mahala St",
    "sg:city":"Oregon",
    "sg:classifiers":[
        {
            "category":"Mining & Drilling",
            "type":"Manufacturing & Wholesale Goods"
        },
        {
            "category":"Social Services",
            "type":"Services"
        }
    ],
    "sg:phone":"+1 419 693 4307",
    "sg:postcode":"43616",
    "sg:province":"OH",
    "sg:tags":[
        "notification",
        "well",
        "emergency"
    ],
    "wof:name":"AAA Emergency Gas Service",
    "wof:placetype":"venue"
},
  "geometry": {"coordinates":[-83.49868600000001,41.621351],"type":"Point"}
}