{
  "type": "Feature",
  "properties": {
    "iso:country":"US",
    "sg:address":"6802 Carnegie Ave",
    "sg:city":"Cleveland",
    "sg:classifiers":[
        {
            "category":"Autos & Motor Vehicles",
            "subcategory":"Motorcycle Sales",
            "type":"Retail Goods"
        }
    ],
    "sg:phone":"+1 216 570 4000",
    "sg:postcode":"44103",
    "sg:province":"OH",
    "wof:name":"Big V Cycles Inc",
    "wof:placetype":"venue"
},
  "geometry": {"coordinates":[-81.645809,41.501555],"type":"Point"}
}