{
  "type": "Feature",
  "properties": {
    "addr:full":"7061 Hoover Rd Orient OH 43146",
    "addr:housenumber":"7061",
    "addr:postcode":"43146",
    "addr:street":"Hoover Rd",
    "iso:country":"US",
    "sg:address":"7061 Hoover Rd",
    "sg:city":"Orient",
    "sg:classifiers":[
        {
            "category":"Building & Trades",
            "subcategory":"Construction",
            "type":"Services"
        }
    ],
    "sg:phone":"+1 614 875 2441",
    "sg:postcode":"43146",
    "sg:province":"OH",
    "sg:tags":[
        "masonry",
        "contractor"
    ],
    "sg:website":"www.modernconstruction.com",
    "wof:name":"Modern Construction Svc",
    "wof:placetype":"venue"
},
  "geometry": {"coordinates":[-83.073702,39.820797],"type":"Point"}
}