{
  "type": "Feature",
  "properties": {
    "addr:full": "5291 State Rte 350 Oregonia OH 45054",
    "addr:housenumber": "5291",
    "addr:postcode": "45054",
    "addr:street": "State Rte 350",
    "iso:country": "US",
    "sg:address": "5291 State Rte 350",
    "sg:city": "Oregonia",
    "sg:classifiers": [
      {
        "category": "Travel",
        "subcategory": "Campground",
        "type": "Entertainment"
      }
    ],
    "sg:phone": "+1 513 932 3756",
    "sg:postcode": "45054",
    "sg:province": "OH",
    "sg:tags": [
      "trailer"
    ],
    "wof:name": "Dayotn YMCA Camp Kern",
    "wof:placetype": "venue"
  },
  "geometry": {"coordinates":[-84.10894,39.405917],"type":"Point"}
}
