{
  "type": "Feature",
  "properties": {
    "addr:full":"4121 Main St Hilliard OH 43026",
    "addr:housenumber":"4121",
    "addr:postcode":"43026",
    "addr:street":"Main St",
    "iso:country":"US",
    "sg:address":"4121 Main St",
    "sg:city":"Hilliard",
    "sg:classifiers":[
        {
            "category":"Education",
            "subcategory":"Dance Studio",
            "type":"Public Place"
        }
    ],
    "sg:phone":"+1 614 529 6683",
    "sg:postcode":"43026",
    "sg:province":"OH",
    "sg:tags":[
        "instruction",
        "dancing"
    ],
    "wof:name":"Dance Connection Inc",
    "wof:placetype":"venue"
},
  "geometry": {"coordinates":[-83.156845,40.036298],"type":"Point"}
}