{
  "type": "Feature",
  "properties": {
    "addr:full":"6761 Washington Cir Franklin OH 45005",
    "addr:housenumber":"6761",
    "addr:postcode":"45005",
    "addr:street":"Washington Cir",
    "iso:country":"US",
    "sg:address":"6761 Washington Cir",
    "sg:city":"Franklin",
    "sg:classifiers":[
        {
            "category":"Real Estate",
            "subcategory":"Real Estate Agent",
            "type":"Services"
        }
    ],
    "sg:phone":"+1 513 420 1721",
    "sg:postcode":"45005",
    "sg:province":"OH",
    "wof:name":"Town Properties",
    "wof:placetype":"venue"
},
  "geometry": {"coordinates":[-84.332072,39.502135],"type":"Point"}
}