{
  "type": "Feature",
  "properties": {
    "iso:country":"US",
    "sg:address":"576 State Rte 560",
    "sg:city":"Urbana",
    "sg:classifiers":[
        {
            "category":"Farming",
            "subcategory":"Farm & Veterinary Services",
            "type":"Manufacturing & Wholesale Goods"
        }
    ],
    "sg:phone":"+1 937 653 4558",
    "sg:postcode":"43078",
    "sg:province":"OH",
    "sg:tags":[
        "management"
    ],
    "wof:name":"Louden Family Orchard",
    "wof:placetype":"venue"
},
  "geometry": {"coordinates":[-83.837344,40.110766],"type":"Point"}
}