{
  "type": "Feature",
  "properties": {
    "addr:full": "576 State Rte 560 Urbana OH 43078",
    "addr:housenumber": "576",
    "addr:postcode": "43078",
    "addr:street": "State Rte 560",
    "iso:country": "US",
    "sg:address": "576 State Rte 560",
    "sg:city": "Urbana",
    "sg:classifiers": [
      {
        "category": "Farming",
        "subcategory": "Farm \u0026 Veterinary Services",
        "type": "Manufacturing \u0026 Wholesale Goods"
      }
    ],
    "sg:phone": "+1 937 653 4558",
    "sg:postcode": "43078",
    "sg:province": "OH",
    "sg:tags": [
      "management"
    ],
    "wof:name": "Louden Family Orchard",
    "wof:placetype": "venue"
  },
  "geometry": {"coordinates":[-83.837344,40.110766],"type":"Point"}
}
