{
  "type": "Feature",
  "properties": {
    "iso:country":"US",
    "sg:address":"819 Vine St",
    "sg:city":"Cincinnati",
    "sg:classifiers":[
        {
            "category":"Restaurant",
            "type":"Food & Drink"
        }
    ],
    "sg:phone":"+1 513 721 5638",
    "sg:postcode":"45202",
    "sg:province":"OH",
    "sg:tags":[
        "shop",
        "coffee",
        "catering"
    ],
    "sg:website":"www.leboxxcafe.com",
    "wof:name":"Le Boxx Cafe",
    "wof:placetype":"venue"
},
  "geometry": {"coordinates":[-84.51404599999999,39.105378],"type":"Point"}
}