{
  "type": "Feature",
  "properties": {
    "addr:full": "819 Vine St Cincinnati OH 45202",
    "addr:housenumber": "819",
    "addr:postcode": "45202",
    "addr:street": "Vine St",
    "iso:country": "US",
    "sg:address": "819 Vine St",
    "sg:city": "Cincinnati",
    "sg:classifiers": [
      {
        "category": "Restaurant",
        "type": "Food \u0026 Drink"
      }
    ],
    "sg:phone": "+1 513 721 5638",
    "sg:postcode": "45202",
    "sg:province": "OH",
    "sg:tags": [
      "shop",
      "coffee",
      "catering"
    ],
    "sg:website": "www.leboxxcafe.com",
    "wof:name": "Le Boxx Cafe",
    "wof:placetype": "venue"
  },
  "geometry": {"coordinates":[-84.514046,39.105378],"type":"Point"}
}
