{
  "type": "Feature",
  "properties": {
    "iso:country":"US",
    "sg:address":"6681 Ridge Rd",
    "sg:city":"Cleveland",
    "sg:classifiers":[
        {
            "category":"Health Services",
            "subcategory":"Doctor",
            "type":"Services"
        }
    ],
    "sg:phone":"+1 440 884 2909",
    "sg:postcode":"44129",
    "sg:province":"OH",
    "sg:tags":[
        "physician",
        "surgeon"
    ],
    "wof:name":"I D Associates Inc",
    "wof:placetype":"venue"
},
  "geometry": {"coordinates":[-81.73462499999999,41.380706],"type":"Point"}
}