{
  "type": "Feature",
  "properties": {
    "addr:full": "216 E Cuyahoga Falls Ave Akron OH 44310",
    "addr:housenumber": "216",
    "addr:postcode": "44310",
    "addr:street": "E Cuyahoga Falls Ave",
    "iso:country": "US",
    "sg:address": "216 E Cuyahoga Falls Ave",
    "sg:city": "Akron",
    "sg:classifiers": [
      {
        "category": "Home \u0026 Garden",
        "subcategory": "Furniture",
        "type": "Retail Goods"
      }
    ],
    "sg:phone": "+1 330 252 0599",
    "sg:postcode": "44310",
    "sg:province": "OH",
    "sg:tags": [
      "mattress"
    ],
    "wof:name": "M K Inc",
    "wof:placetype": "venue"
  },
  "geometry": {"coordinates":[-81.509084,41.108245],"type":"Point"}
}
