{
  "type": "Feature",
  "properties": {
    "addr:full": "926 Crestview Dr Crestline OH 44827",
    "addr:housenumber": "926",
    "addr:postcode": "44827",
    "addr:street": "Crestview Dr",
    "iso:country": "US",
    "sg:address": "926 Crestview Dr",
    "sg:city": "Crestline",
    "sg:classifiers": [
      {
        "category": "Building \u0026 Trades",
        "subcategory": "Plumbing",
        "type": "Services"
      }
    ],
    "sg:phone": "+1 419 683 1145",
    "sg:postcode": "44827",
    "sg:province": "OH",
    "sg:tags": [
      "plumbing",
      "contractor"
    ],
    "wof:name": "Carter Dan Plumbing \u0026 Heating",
    "wof:placetype": "venue"
  },
  "geometry": {"coordinates":[-82.689073,40.780969],"type":"Point"}
}
