{
  "type": "Feature",
  "properties": {
    "iso:country":"US",
    "sg:address":"926 Crestview Dr",
    "sg:city":"Crestline",
    "sg:classifiers":[
        {
            "category":"Building & Trades",
            "subcategory":"Plumbing",
            "type":"Services"
        }
    ],
    "sg:phone":"+1 419 683 1145",
    "sg:postcode":"44827",
    "sg:province":"OH",
    "sg:tags":[
        "plumbing",
        "contractor"
    ],
    "wof:name":"Carter Dan Plumbing & Heating",
    "wof:placetype":"venue"
},
  "geometry": {"coordinates":[-82.68907299999999,40.780969],"type":"Point"}
}