{
  "type": "Feature",
  "properties": {
    "addr:full": "2448 Auburn Ave Cincinnati OH 45219",
    "addr:housenumber": "2448",
    "addr:postcode": "45219",
    "addr:street": "Auburn Ave",
    "iso:country": "US",
    "sg:address": "2448 Auburn Ave",
    "sg:city": "Cincinnati",
    "sg:classifiers": [
      {
        "category": "Professional",
        "type": "Services"
      }
    ],
    "sg:phone": "+1 513 721 0433",
    "sg:postcode": "45219",
    "sg:province": "OH",
    "sg:tags": [
      "establishment"
    ],
    "wof:name": "Kahle Sister Joyce",
    "wof:placetype": "venue"
  },
  "geometry": {"coordinates":[-84.508319,39.126586],"type":"Point"}
}
