{
  "type": "Feature",
  "properties": {
    "addr:full": "381 Boardman Poland Rd Youngstown OH 44512",
    "addr:housenumber": "381",
    "addr:postcode": "44512",
    "addr:street": "Boardman Poland Rd",
    "iso:country": "US",
    "sg:address": "381 Boardman Poland Rd",
    "sg:city": "Youngstown",
    "sg:classifiers": [
      {
        "category": "Shopping",
        "subcategory": "Books",
        "type": "Retail Goods"
      }
    ],
    "sg:phone": "+1 330 629 9436",
    "sg:postcode": "44512",
    "sg:province": "OH",
    "sg:tags": [
      "dealer"
    ],
    "wof:name": "Barnes \u0026 Noble Booksellers",
    "wof:placetype": "venue"
  },
  "geometry": {"coordinates":[-80.64495,41.024227],"type":"Point"}
}
