{
  "type": "Feature",
  "properties": {
    "iso:country":"US",
    "sg:address":"381 Boardman Poland Rd",
    "sg:city":"Youngstown",
    "sg:classifiers":[
        {
            "category":"Shopping",
            "subcategory":"Books",
            "type":"Retail Goods"
        }
    ],
    "sg:phone":"+1 330 629 9436",
    "sg:postcode":"44512",
    "sg:province":"OH",
    "sg:tags":[
        "dealer"
    ],
    "wof:name":"Barnes & Noble Booksellers",
    "wof:placetype":"venue"
},
  "geometry": {"coordinates":[-80.64494999999999,41.024227],"type":"Point"}
}