{
  "type": "Feature",
  "properties": {
    "addr:full": "1072 Grant St Akron OH 44311",
    "addr:housenumber": "1072",
    "addr:postcode": "44311",
    "addr:street": "Grant St",
    "iso:country": "US",
    "sg:address": "1072 Grant St",
    "sg:city": "Akron",
    "sg:classifiers": [
      {
        "category": "Food \u0026 Beverages",
        "subcategory": "Meat \u0026 Fish",
        "type": "Retail Goods"
      }
    ],
    "sg:phone": "+1 330 773 1551",
    "sg:postcode": "44311",
    "sg:province": "OH",
    "sg:tags": [
      "restaurant"
    ],
    "wof:name": "Klein Seafood",
    "wof:placetype": "venue"
  },
  "geometry": {"coordinates":[-81.518356,41.053726],"type":"Point"}
}
