{
  "type": "Feature",
  "properties": {
    "addr:full": "522 S Mulberry St Troy OH 45373",
    "addr:housenumber": "522",
    "addr:postcode": "45373",
    "addr:street": "S Mulberry St",
    "iso:country": "US",
    "sg:address": "522 S Mulberry St",
    "sg:city": "Troy",
    "sg:classifiers": [
      {
        "category": "Manufacturing",
        "subcategory": "Tools \u0026 Machinery",
        "type": "Manufacturing \u0026 Wholesale Goods"
      }
    ],
    "sg:phone": "+1 937 335 3562",
    "sg:postcode": "45373",
    "sg:province": "OH",
    "sg:tags": [
      "die",
      "maker"
    ],
    "wof:name": "Ultimate Tool \u0026 Gage",
    "wof:placetype": "venue"
  },
  "geometry": {"coordinates":[-84.205641,40.033216],"type":"Point"}
}
