{
  "type": "Feature",
  "properties": {
    "iso:country":"US",
    "sg:address":"522 S Mulberry St",
    "sg:city":"Troy",
    "sg:classifiers":[
        {
            "category":"Manufacturing",
            "subcategory":"Tools & Machinery",
            "type":"Manufacturing & Wholesale Goods"
        }
    ],
    "sg:phone":"+1 937 335 3562",
    "sg:postcode":"45373",
    "sg:province":"OH",
    "sg:tags":[
        "die",
        "maker"
    ],
    "wof:name":"Ultimate Tool & Gage",
    "wof:placetype":"venue"
},
  "geometry": {"coordinates":[-84.205641,40.033216],"type":"Point"}
}