{
  "type": "Feature",
  "properties": {
    "iso:country":"US",
    "sg:address":"1727 Doan Ave",
    "sg:city":"Cleveland",
    "sg:classifiers":[
        {
            "category":"Retail",
            "subcategory":"Auto Repair",
            "type":"Services"
        }
    ],
    "sg:phone":"+1 216 268 5500",
    "sg:postcode":"44112",
    "sg:province":"OH",
    "sg:tags":[
        "repairing",
        "automobile"
    ],
    "wof:name":"Alvins & Sons",
    "wof:placetype":"venue"
},
  "geometry": {"coordinates":[-81.581863,41.531098],"type":"Point"}
}