{
  "type": "Feature",
  "properties": {
    "addr:full": "5555 Scarborough Blvd Columbus OH 43232",
    "addr:housenumber": "5555",
    "addr:postcode": "43232",
    "addr:street": "Scarborough Blvd",
    "iso:country": "US",
    "sg:address": "5555 Scarborough Blvd",
    "sg:city": "Columbus",
    "sg:classifiers": [
      {
        "category": "Shopping",
        "subcategory": "Department Store",
        "type": "Retail Goods"
      }
    ],
    "sg:phone": "+1 614 863 8800",
    "sg:postcode": "43232",
    "sg:province": "OH",
    "sg:website": "www.jcpenney.com",
    "wof:name": "J C Penney Co",
    "wof:placetype": "venue"
  },
  "geometry": {"coordinates":[-82.850431,39.931671],"type":"Point"}
}
