{
  "type": "Feature",
  "properties": {
    "addr:full": "225 Waggaman Cir Youngstown OH 44512",
    "addr:housenumber": "225",
    "addr:postcode": "44512",
    "addr:street": "Waggaman Cir",
    "iso:country": "US",
    "sg:address": "225 Waggaman Cir",
    "sg:city": "Youngstown",
    "sg:classifiers": [
      {
        "category": "Building \u0026 Trades",
        "subcategory": "Construction",
        "type": "Services"
      }
    ],
    "sg:phone": "+1 330 758 4974",
    "sg:postcode": "44512",
    "sg:province": "OH",
    "sg:tags": [
      "hanging",
      "contractor"
    ],
    "wof:name": "Faux Masters",
    "wof:placetype": "venue"
  },
  "geometry": {"coordinates":[-80.671184,40.990101],"type":"Point"}
}
