{
  "type": "Feature",
  "properties": {
    "iso:country":"US",
    "sg:address":"225 Waggaman Cir",
    "sg:city":"Youngstown",
    "sg:classifiers":[
        {
            "category":"Building & Trades",
            "subcategory":"Construction",
            "type":"Services"
        }
    ],
    "sg:phone":"+1 330 758 4974",
    "sg:postcode":"44512",
    "sg:province":"OH",
    "sg:tags":[
        "hanging",
        "contractor"
    ],
    "wof:name":"Faux Masters",
    "wof:placetype":"venue"
},
  "geometry": {"coordinates":[-80.671184,40.990101],"type":"Point"}
}