{
  "type": "Feature",
  "properties": {
    "iso:country":"US",
    "sg:address":"3540 Norton Rd",
    "sg:city":"Cleveland",
    "sg:classifiers":[
        {
            "category":"Wholesale",
            "subcategory":"Electrical",
            "type":"Manufacturing & Wholesale Goods"
        }
    ],
    "sg:phone":"+1 216 671 7000",
    "sg:postcode":"44111",
    "sg:province":"OH",
    "sg:tags":[
        "battery",
        "repairing",
        "rebuilding"
    ],
    "wof:name":"R H Welf & Assoc",
    "wof:placetype":"venue"
},
  "geometry": {"coordinates":[-81.791089,41.456411],"type":"Point"}
}