{
  "type": "Feature",
  "properties": {
    "addr:full": "5350 Transportation Blvd Cleveland OH 44125",
    "addr:housenumber": "5350",
    "addr:postcode": "44125",
    "addr:street": "Transportation Blvd",
    "iso:country": "US",
    "sg:address": "5350 Transportation Blvd",
    "sg:city": "Cleveland",
    "sg:classifiers": [
      {
        "category": "Professional",
        "subcategory": "Management \u0026 Consulting",
        "type": "Services"
      }
    ],
    "sg:phone": "+1 216 518 2805",
    "sg:postcode": "44125",
    "sg:province": "OH",
    "sg:tags": [
      "marketing",
      "consultant"
    ],
    "wof:name": "NSRC-National Survey Rsrch",
    "wof:placetype": "venue"
  },
  "geometry": {"coordinates":[-81.615951,41.413641],"type":"Point"}
}
