{
  "type": "Feature",
  "properties": {
    "addr:full":"3329 Dorr St Toledo OH 43607",
    "addr:housenumber":"3329",
    "addr:postcode":"43607",
    "addr:street":"Dorr St",
    "iso:country":"US",
    "sg:address":"3329 Dorr St",
    "sg:city":"Toledo",
    "sg:classifiers":[
        {
            "category":"Restaurant",
            "type":"Food & Drink"
        }
    ],
    "sg:menulink":"http://www.allmenus.com/oh/toledo/59508-papa-johns-pizza/menu/",
    "sg:phone":"+1 419 539 7777",
    "sg:postcode":"43607",
    "sg:province":"OH",
    "sg:tags":[
        "american",
        "pizza"
    ],
    "wof:name":"Papa John's Pizza",
    "wof:placetype":"venue"
},
  "geometry": {"coordinates":[-83.622269,41.652655],"type":"Point"}
}