{
  "type": "Feature",
  "properties": {
    "addr:full":"3103 Little Dry Run Rd Cincinnati OH 45244",
    "addr:housenumber":"3103",
    "addr:postcode":"45244",
    "addr:street":"Little Dry Run Rd",
    "iso:country":"US",
    "sg:address":"3103 Little Dry Run Rd",
    "sg:city":"Cincinnati",
    "sg:classifiers":[
        {
            "category":"Professional",
            "subcategory":"Research",
            "type":"Services"
        }
    ],
    "sg:phone":"+1 513 474 7799",
    "sg:postcode":"45244",
    "sg:province":"OH",
    "sg:tags":[
        "educational"
    ],
    "wof:name":"New Ideas For North America",
    "wof:placetype":"venue"
},
  "geometry": {"coordinates":[-84.334474,39.113195],"type":"Point"}
}