{
  "type": "Feature",
  "properties": {
    "iso:country":"US",
    "sg:address":"116 Wooster Rd",
    "sg:city":"Mount Vernon",
    "sg:classifiers":[
        {
            "category":"Shopping",
            "subcategory":"Used Merchandise",
            "type":"Retail Goods"
        }
    ],
    "sg:phone":"+1 740 393 1910",
    "sg:postcode":"43050",
    "sg:province":"OH",
    "sg:tags":[
        "antique"
    ],
    "wof:name":"Heritage Hall Antiques",
    "wof:placetype":"venue"
},
  "geometry": {"coordinates":[-82.483001,40.401314],"type":"Point"}
}