{
  "type": "Feature",
  "properties": {
    "iso:country":"US",
    "sg:address":"120 Bent Tree Rd",
    "sg:city":"Sunbury",
    "sg:classifiers":[
        {
            "category":"Professional",
            "type":"Services"
        }
    ],
    "sg:phone":"+1 740 965 3401",
    "sg:postcode":"43074",
    "sg:province":"OH",
    "wof:name":"Elizabeth G & Leslie K BR",
    "wof:placetype":"venue"
},
  "geometry": {"coordinates":[-82.90562,40.265496],"type":"Point"}
}