{
  "type": "Feature",
  "properties": {
    "addr:full": "1086 Cheshire Rd Delaware OH 43015",
    "addr:housenumber": "1086",
    "addr:postcode": "43015",
    "addr:street": "Cheshire Rd",
    "iso:country": "US",
    "sg:address": "1086 Cheshire Rd",
    "sg:city": "Delaware",
    "sg:classifiers": [
      {
        "category": "Organizations",
        "subcategory": "Community Association",
        "type": "Services"
      }
    ],
    "sg:phone": "+1 740 549 9983",
    "sg:postcode": "43015",
    "sg:province": "OH",
    "sg:tags": [
      "club"
    ],
    "wof:name": "Reserve At Glenross Clubhouse",
    "wof:placetype": "venue"
  },
  "geometry": {"coordinates":[-83.033433,40.241293],"type":"Point"}
}
