{
  "type": "Feature",
  "properties": {
    "addr:full":"5271 Gender Rd Canal Winchester OH 43110",
    "addr:housenumber":"5271",
    "addr:postcode":"43110",
    "addr:street":"Gender Rd",
    "iso:country":"US",
    "sg:address":"5271 Gender Rd",
    "sg:city":"Canal Winchester",
    "sg:classifiers":[
        {
            "category":"Education",
            "subcategory":"Special Training",
            "type":"Public Place"
        }
    ],
    "sg:phone":"+1 614 834 8810",
    "sg:postcode":"43110",
    "sg:province":"OH",
    "sg:tags":[
        "instruction",
        "driving"
    ],
    "wof:name":"Carroll Lyn Driving School Inc",
    "wof:placetype":"venue"
},
  "geometry": {"coordinates":[-82.826515,39.874158],"type":"Point"}
}