{
  "type": "Feature",
  "properties": {
    "iso:country":"US",
    "sg:address":"23 Deerfield Ln",
    "sg:city":"Cleveland",
    "sg:classifiers":[
        {
            "category":"Professional",
            "subcategory":"Management & Consulting",
            "type":"Services"
        }
    ],
    "sg:phone":"+1 216 464 6630",
    "sg:postcode":"44122",
    "sg:province":"OH",
    "sg:tags":[
        "construction"
    ],
    "wof:name":"Conger Corp",
    "wof:placetype":"venue"
},
  "geometry": {"coordinates":[-81.49621,41.489897],"type":"Point"}
}