{
  "type": "Feature",
  "properties": {
    "addr:full": "891 Bluffway Dr Columbus OH 43235",
    "addr:housenumber": "891",
    "addr:postcode": "43235",
    "addr:street": "Bluffway Dr",
    "iso:country": "US",
    "sg:address": "891 Bluffway Dr",
    "sg:city": "Columbus",
    "sg:classifiers": [
      {
        "category": "Building \u0026 Trades",
        "subcategory": "Plumbing",
        "type": "Services"
      }
    ],
    "sg:phone": "+1 614 785 1603",
    "sg:postcode": "43235",
    "sg:province": "OH",
    "sg:tags": [
      "contractor"
    ],
    "wof:name": "A\u0026G Maintenance",
    "wof:placetype": "venue"
  },
  "geometry": {"coordinates":[-83.040553,40.113211],"type":"Point"}
}
