{
  "type": "Feature",
  "properties": {
    "iso:country":"US",
    "sg:address":"1850 State Rte 88",
    "sg:city":"Bristolville",
    "sg:classifiers":[
        {
            "category":"Government",
            "subcategory":"Post Office",
            "type":"Public Place"
        }
    ],
    "sg:phone":"+1 330 889 2463",
    "sg:postcode":"44402",
    "sg:province":"OH",
    "wof:name":"Usps",
    "wof:placetype":"venue"
},
  "geometry": {"coordinates":[-80.87082599999999,41.38751],"type":"Point"}
}