{
  "type": "Feature",
  "properties": {
    "addr:full": "957 Raymond Ave Barberton OH 44203",
    "addr:housenumber": "957",
    "addr:postcode": "44203",
    "addr:street": "Raymond Ave",
    "iso:country": "US",
    "sg:address": "957 Raymond Ave",
    "sg:city": "Barberton",
    "sg:classifiers": [
      {
        "category": "Wholesale",
        "subcategory": "Non-durable Goods",
        "type": "Manufacturing \u0026 Wholesale Goods"
      }
    ],
    "sg:phone": "+1 330 861 1115",
    "sg:postcode": "44203",
    "sg:province": "OH",
    "sg:tags": [
      "item",
      "novelty"
    ],
    "wof:name": "J W Throttle Company",
    "wof:placetype": "venue"
  },
  "geometry": {"coordinates":[-81.622197,41.021028],"type":"Point"}
}
