{
  "type": "Feature",
  "properties": {
    "iso:country":"US",
    "sg:address":"1335 Main St",
    "sg:city":"Cincinnati",
    "sg:classifiers":[
        {
            "category":"Shopping",
            "subcategory":"Clothing, Apparel, & Fashions",
            "type":"Retail Goods"
        }
    ],
    "sg:phone":"+1 513 421 5979",
    "sg:postcode":"45202",
    "sg:province":"OH",
    "wof:name":"Addicted Two Luxury",
    "wof:placetype":"venue"
},
  "geometry": {"coordinates":[-84.51216700000001,39.110889],"type":"Point"}
}