{
  "type": "Feature",
  "properties": {
    "addr:full": "1335 Main St Cincinnati OH 45202",
    "addr:housenumber": "1335",
    "addr:postcode": "45202",
    "addr:street": "Main St",
    "iso:country": "US",
    "sg:address": "1335 Main St",
    "sg:city": "Cincinnati",
    "sg:classifiers": [
      {
        "category": "Shopping",
        "subcategory": "Clothing, Apparel, \u0026 Fashions",
        "type": "Retail Goods"
      }
    ],
    "sg:phone": "+1 513 421 5979",
    "sg:postcode": "45202",
    "sg:province": "OH",
    "wof:name": "Addicted Two Luxury",
    "wof:placetype": "venue"
  },
  "geometry": {"coordinates":[-84.512167,39.110889],"type":"Point"}
}
