{
  "type": "Feature",
  "properties": {
    "iso:country":"US",
    "sg:address":"1387 Clarendon Ave SW",
    "sg:city":"Canton",
    "sg:classifiers":[
        {
            "category":"Building & Trades",
            "subcategory":"Construction",
            "type":"Services"
        }
    ],
    "sg:phone":"+1 330 455 0684",
    "sg:postcode":"44710",
    "sg:province":"OH",
    "sg:tags":[
        "paving",
        "contractor"
    ],
    "wof:name":"Jet-Black Sealcoating & Repair",
    "wof:placetype":"venue"
},
  "geometry": {"coordinates":[-81.404141,40.787664],"type":"Point"}
}