{
  "type": "Feature",
  "properties": {
    "addr:full":"820 E State St Fremont OH 43420",
    "addr:housenumber":"820",
    "addr:postcode":"43420",
    "addr:street":"E State St",
    "iso:country":"US",
    "sg:address":"820 E State St",
    "sg:city":"Fremont",
    "sg:classifiers":[
        {
            "category":"Insurance",
            "subcategory":"Insurance Agent",
            "type":"Services"
        }
    ],
    "sg:phone":"+1 419 334 2500",
    "sg:postcode":"43420",
    "sg:province":"OH",
    "wof:name":"Nationwide Mutual Insurance",
    "wof:placetype":"venue"
},
  "geometry": {"coordinates":[-83.101383,41.344244],"type":"Point"}
}