{
  "type": "Feature",
  "properties": {
    "addr:full":"276 Cranz Pl Akron OH 44310",
    "addr:housenumber":"276",
    "addr:postcode":"44310",
    "addr:street":"Cranz Pl",
    "iso:country":"US",
    "sg:address":"276 Cranz Pl",
    "sg:city":"Akron",
    "sg:classifiers":[
        {
            "category":"Building & Trades",
            "subcategory":"Construction",
            "type":"Services"
        }
    ],
    "sg:phone":"+1 330 376 6425",
    "sg:postcode":"44310",
    "sg:province":"OH",
    "sg:tags":[
        "hanging",
        "contractor"
    ],
    "wof:name":"GE Squiere Painting",
    "wof:placetype":"venue"
},
  "geometry": {"coordinates":[-81.507335,41.099212],"type":"Point"}
}