{
  "type": "Feature",
  "properties": {
    "addr:full": "2113 State Rd Cuyahoga Falls OH 44223",
    "addr:housenumber": "2113",
    "addr:postcode": "44223",
    "addr:street": "State Rd",
    "iso:country": "US",
    "sg:address": "2113 State Rd",
    "sg:city": "Cuyahoga Falls",
    "sg:classifiers": [
      {
        "category": "Food \u0026 Beverages",
        "subcategory": "Groceries \u0026 Convenience Stores",
        "type": "Retail Goods"
      }
    ],
    "sg:phone": "+1 330 928 8048",
    "sg:postcode": "44223",
    "sg:province": "OH",
    "wof:name": "Sunoco",
    "wof:placetype": "venue"
  },
  "geometry": {"coordinates":[-81.508478,41.136299],"type":"Point"}
}
