{
  "type": "Feature",
  "properties": {
    "iso:country":"US",
    "sg:address":"2113 State Rd",
    "sg:city":"Cuyahoga Falls",
    "sg:classifiers":[
        {
            "category":"Food & Beverages",
            "subcategory":"Groceries & Convenience Stores",
            "type":"Retail Goods"
        }
    ],
    "sg:phone":"+1 330 928 8048",
    "sg:postcode":"44223",
    "sg:province":"OH",
    "wof:name":"Sunoco",
    "wof:placetype":"venue"
},
  "geometry": {"coordinates":[-81.508478,41.136299],"type":"Point"}
}