{
  "type": "Feature",
  "properties": {
    "addr:full":"1751 Brice Rd Reynoldsburg OH 43068",
    "addr:housenumber":"1751",
    "addr:postcode":"43068",
    "addr:street":"Brice Rd",
    "iso:country":"US",
    "sg:address":"1751 Brice Rd",
    "sg:city":"Reynoldsburg",
    "sg:classifiers":[
        {
            "category":"Food & Beverages",
            "subcategory":"Bakery",
            "type":"Retail Goods"
        }
    ],
    "sg:phone":"+1 614 861 1136",
    "sg:postcode":"43068",
    "sg:province":"OH",
    "sg:tags":[
        "baker"
    ],
    "wof:name":"Wonder Hostess Thrift Shop",
    "wof:placetype":"venue"
},
  "geometry": {"coordinates":[-82.82981100000001,39.943772],"type":"Point"}
}