{
  "type": "Feature",
  "properties": {
    "addr:full": "520 S High St Columbus OH 43215",
    "addr:housenumber": "520",
    "addr:postcode": "43215",
    "addr:street": "S High St",
    "iso:country": "US",
    "sg:address": "520 S High St",
    "sg:city": "Columbus",
    "sg:classifiers": [
      {
        "category": "Manufacturing",
        "subcategory": "Printing",
        "type": "Manufacturing \u0026 Wholesale Goods"
      }
    ],
    "sg:phone": "+1 614 228 6440",
    "sg:postcode": "43215",
    "sg:province": "OH",
    "sg:tags": [
      "printer"
    ],
    "wof:name": "Blue Print Lounge",
    "wof:placetype": "venue"
  },
  "geometry": {"coordinates":[-82.998438,39.951268],"type":"Point"}
}
