{
  "type": "Feature",
  "properties": {
    "iso:country":"US",
    "sg:address":"520 S High St",
    "sg:city":"Columbus",
    "sg:classifiers":[
        {
            "category":"Manufacturing",
            "subcategory":"Printing",
            "type":"Manufacturing & Wholesale Goods"
        }
    ],
    "sg:phone":"+1 614 228 6440",
    "sg:postcode":"43215",
    "sg:province":"OH",
    "sg:tags":[
        "printer"
    ],
    "wof:name":"Blue Print Lounge",
    "wof:placetype":"venue"
},
  "geometry": {"coordinates":[-82.99843799999999,39.951268],"type":"Point"}
}