{
  "type": "Feature",
  "properties": {
    "addr:full":"2411 Seaman St Toledo OH 43605",
    "addr:housenumber":"2411",
    "addr:postcode":"43605",
    "addr:street":"Seaman St",
    "iso:country":"US",
    "sg:address":"2411 Seaman St",
    "sg:city":"Toledo",
    "sg:classifiers":[
        {
            "category":"Restaurant",
            "type":"Food & Drink"
        }
    ],
    "sg:phone":"+1 419 693 0751",
    "sg:postcode":"43605",
    "sg:province":"OH",
    "sg:tags":[
        "skilled",
        "eating",
        "nursing",
        "care",
        "facility"
    ],
    "wof:name":"Aramark",
    "wof:placetype":"venue"
},
  "geometry": {"coordinates":[-83.487334,41.651265],"type":"Point"}
}