{
  "type": "Feature",
  "properties": {
    "addr:full":"7300 Bittern Ave Cleveland OH 44103",
    "addr:housenumber":"7300",
    "addr:postcode":"44103",
    "addr:street":"Bittern Ave",
    "iso:country":"US",
    "sg:address":"7300 Bittern Ave",
    "sg:city":"Cleveland",
    "sg:classifiers":[
        {
            "category":"Manufacturing",
            "subcategory":"Metals",
            "type":"Manufacturing & Wholesale Goods"
        },
        {
            "category":"Wholesale",
            "subcategory":"Metals & Minerals",
            "type":"Manufacturing & Wholesale Goods"
        }
    ],
    "sg:phone":"+1 216 432 3250",
    "sg:postcode":"44103",
    "sg:province":"OH",
    "sg:tags":[
        "product",
        "wire",
        "working",
        "forming",
        "fabricated",
        "equipment",
        "manufacturer"
    ],
    "wof:name":"Advance Wire Forming Inc",
    "wof:placetype":"venue"
},
  "geometry": {"coordinates":[-81.637705,41.533492],"type":"Point"}
}