{
  "type": "Feature",
  "properties": {
    "addr:full": "1372 Riviera Pl Cincinnati OH 45231",
    "addr:housenumber": "1372",
    "addr:postcode": "45231",
    "addr:street": "Riviera Pl",
    "iso:country": "US",
    "sg:address": "1372 Riviera Pl",
    "sg:city": "Cincinnati",
    "sg:classifiers": [
      {
        "category": "Organizations",
        "subcategory": "Religious Organization",
        "type": "Services"
      }
    ],
    "sg:phone": "+1 513 522 5029",
    "sg:postcode": "45231",
    "sg:province": "OH",
    "sg:tags": [
      "clergy"
    ],
    "wof:name": "William C Cox",
    "wof:placetype": "venue"
  },
  "geometry": {"coordinates":[-84.53644,39.244649],"type":"Point"}
}
