{
  "type": "Feature",
  "properties": {
    "addr:full":"7496 Mentor Ave Mentor OH 44060",
    "addr:housenumber":"7496",
    "addr:postcode":"44060",
    "addr:street":"Mentor Ave",
    "iso:country":"US",
    "sg:address":"7496 Mentor Ave",
    "sg:city":"Mentor",
    "sg:classifiers":[
        {
            "category":"Recreation",
            "type":"Entertainment"
        }
    ],
    "sg:phone":"+1 440 942 2717",
    "sg:postcode":"44060",
    "sg:province":"OH",
    "sg:tags":[
        "astrologer"
    ],
    "wof:name":"Gina's Psychic Studio",
    "wof:placetype":"venue"
},
  "geometry": {"coordinates":[-81.373265,41.655216],"type":"Point"}
}