{
  "type": "Feature",
  "properties": {
    "addr:full": "4 Main St Centerburg OH 43011",
    "addr:housenumber": "4",
    "addr:postcode": "43011",
    "addr:street": "Main St",
    "iso:country": "US",
    "sg:address": "4 Main St",
    "sg:city": "Centerburg",
    "sg:classifiers": [
      {
        "category": "Real Estate",
        "subcategory": "Real Estate Agent",
        "type": "Services"
      }
    ],
    "sg:phone": "+1 740 625 6000",
    "sg:postcode": "43011",
    "sg:province": "OH",
    "sg:website": "www.peakrealtyinc.com",
    "wof:name": "Peak Realty Inc",
    "wof:placetype": "venue"
  },
  "geometry": {"coordinates":[-82.695475,40.30507],"type":"Point"}
}
