{
  "type": "Feature",
  "properties": {
    "iso:country":"US",
    "sg:address":"8127 E Main St",
    "sg:city":"Ottawa",
    "sg:classifiers":[
        {
            "category":"Organizations",
            "subcategory":"Religious Organization",
            "type":"Services"
        }
    ],
    "sg:phone":"+1 419 523 6250",
    "sg:postcode":"45875",
    "sg:province":"OH",
    "sg:tags":[
        "church"
    ],
    "sg:website":"www.newcreation-ottawa.com",
    "wof:name":"New Creation Lutheran Church",
    "wof:placetype":"venue"
},
  "geometry": {"coordinates":[-84.011646,41.02171],"type":"Point"}
}