{
  "type": "Feature",
  "properties": {
    "addr:full":"11515 Stablewatch Ct Cincinnati OH 45249",
    "addr:housenumber":"11515",
    "addr:postcode":"45249",
    "addr:street":"Stablewatch Ct",
    "iso:country":"US",
    "sg:address":"11515 Stablewatch Ct",
    "sg:city":"Cincinnati",
    "sg:classifiers":[
        {
            "category":"Insurance",
            "subcategory":"Insurance Agent",
            "type":"Services"
        }
    ],
    "sg:phone":"+1 513 489 1414",
    "sg:postcode":"45249",
    "sg:province":"OH",
    "wof:name":"Carson & Assoc Inc",
    "wof:placetype":"venue"
},
  "geometry": {"coordinates":[-84.32156999999999,39.279559],"type":"Point"}
}