{
  "type": "Feature",
  "properties": {
    "addr:full":"4717 State Rte 53 N Upper Sandusky OH 43351",
    "addr:housenumber":"4717",
    "addr:postcode":"43351",
    "addr:street":"State Rte 53 N",
    "iso:country":"US",
    "sg:address":"4717 State Rte 53 N",
    "sg:city":"Upper Sandusky",
    "sg:classifiers":[
        {
            "category":"Farming",
            "subcategory":"Livestock Farm",
            "type":"Manufacturing & Wholesale Goods"
        }
    ],
    "sg:phone":"+1 419 294 2610",
    "sg:postcode":"43351",
    "sg:province":"OH",
    "sg:tags":[
        "hog",
        "or",
        "feedlot"
    ],
    "wof:name":"Kalbach Wagner",
    "wof:placetype":"venue"
},
  "geometry": {"coordinates":[-83.273098,40.924884],"type":"Point"}
}