{
  "type": "Feature",
  "properties": {
    "addr:full": "1898 Wikel Rd Eldorado OH 45321",
    "addr:housenumber": "1898",
    "addr:postcode": "45321",
    "addr:street": "Wikel Rd",
    "iso:country": "US",
    "sg:address": "1898 Wikel Rd",
    "sg:city": "Eldorado",
    "sg:phone": "+1 937 273 5630",
    "sg:postcode": "45321",
    "sg:province": "OH",
    "sg:tags": [
      "real",
      "lessor",
      "farm",
      "cash",
      "grain",
      "property"
    ],
    "wof:name": "Melvin James",
    "wof:placetype": "venue"
  },
  "geometry": {"coordinates":[-84.659149,39.90187],"type":"Point"}
}
