{
  "type": "Feature",
  "properties": {
    "addr:full":"456 S Washington St New Bremen OH 45869",
    "addr:housenumber":"456",
    "addr:postcode":"45869",
    "addr:street":"S Washington St",
    "iso:country":"US",
    "sg:address":"456 S Washington St",
    "sg:city":"New Bremen",
    "sg:classifiers":[
        {
            "category":"Arts & Performance",
            "subcategory":"Theater",
            "type":"Entertainment"
        }
    ],
    "sg:phone":"+1 419 977 2141",
    "sg:postcode":"45869",
    "sg:province":"OH",
    "sg:tags":[
        "bureau"
    ],
    "wof:name":"Entertainment Exchange",
    "wof:placetype":"venue"
},
  "geometry": {"coordinates":[-84.378844,40.427634],"type":"Point"}
}