{
  "type": "Feature",
  "properties": {
    "addr:full": "10949 Chamberlain Rd Mantua OH 44255",
    "addr:housenumber": "10949",
    "addr:postcode": "44255",
    "addr:street": "Chamberlain Rd",
    "iso:country": "US",
    "sg:address": "10949 Chamberlain Rd",
    "sg:city": "Mantua",
    "sg:classifiers": [
      {
        "category": "Farming",
        "subcategory": "Farm",
        "type": "Manufacturing \u0026 Wholesale Goods"
      }
    ],
    "sg:phone": "+1 330 562 7259",
    "sg:postcode": "44255",
    "sg:province": "OH",
    "sg:tags": [
      "crop",
      "general"
    ],
    "wof:name": "Ronald Echelberry",
    "wof:placetype": "venue"
  },
  "geometry": {"coordinates":[-81.287497,41.287427],"type":"Point"}
}
