{
  "type": "Feature",
  "properties": {
    "addr:full": "3878 Huntmere Ave Austintown OH 44515",
    "addr:housenumber": "3878",
    "addr:postcode": "44515",
    "addr:street": "Huntmere Ave",
    "iso:country": "US",
    "sg:address": "3878 Huntmere Ave",
    "sg:city": "Austintown",
    "sg:classifiers": [
      {
        "category": "Retail",
        "subcategory": "Repair Shop",
        "type": "Services"
      }
    ],
    "sg:phone": "+1 330 793 3699",
    "sg:postcode": "44515",
    "sg:province": "OH",
    "sg:tags": [
      "taxidermist"
    ],
    "wof:name": "G \u0026 J Taxidermy",
    "wof:placetype": "venue"
  },
  "geometry": {"coordinates":[-80.716639,41.09888],"type":"Point"}
}
