{
  "type": "Feature",
  "properties": {
    "addr:full": "1340 Fairchild Ave Kent OH 44240",
    "addr:housenumber": "1340",
    "addr:postcode": "44240",
    "addr:street": "Fairchild Ave",
    "iso:country": "US",
    "sg:address": "1340 Fairchild Ave",
    "sg:city": "Kent",
    "sg:classifiers": [
      {
        "category": "Food \u0026 Beverages",
        "subcategory": "Groceries \u0026 Convenience Stores",
        "type": "Retail Goods"
      }
    ],
    "sg:phone": "+1 330 677 5955",
    "sg:postcode": "44240",
    "sg:province": "OH",
    "wof:name": "Safe Way Market",
    "wof:placetype": "venue"
  },
  "geometry": {"coordinates":[-81.388642,41.165441],"type":"Point"}
}
