{
  "type": "Feature",
  "properties": {
    "iso:country":"US",
    "sg:address":"5654 Vine St",
    "sg:city":"Cincinnati",
    "sg:classifiers":[
        {
            "category":"Food & Beverages",
            "subcategory":"Groceries & Convenience Stores",
            "type":"Retail Goods"
        },
        {
            "category":"Manufacturing",
            "subcategory":"Food",
            "type":"Manufacturing & Wholesale Goods"
        }
    ],
    "sg:phone":"+1 513 242 3895",
    "sg:postcode":"45216",
    "sg:province":"OH",
    "sg:tags":[
        "frozen",
        "dessert",
        "ice",
        "cream"
    ],
    "sg:website":"www.udfinc.com",
    "wof:name":"United Dairy Farmers 154",
    "wof:placetype":"venue"
},
  "geometry": {"coordinates":[-84.490883,39.184303],"type":"Point"}
}