{
  "type": "Feature",
  "properties": {
    "addr:full":"605 W State St Fremont OH 43420",
    "addr:housenumber":"605",
    "addr:postcode":"43420",
    "addr:street":"W State St",
    "iso:country":"US",
    "sg:address":"605 W State St",
    "sg:city":"Fremont",
    "sg:classifiers":[
        {
            "category":"Insurance",
            "subcategory":"Insurance Agent",
            "type":"Services"
        }
    ],
    "sg:phone":"+1 419 332 9060",
    "sg:postcode":"43420",
    "sg:province":"OH",
    "wof:name":"South Bay Insurance Agency",
    "wof:placetype":"venue"
},
  "geometry": {"coordinates":[-83.11787200000001,41.349009],"type":"Point"}
}