{
  "type": "Feature",
  "properties": {
    "iso:country":"US",
    "sg:address":"3970 Salem Ave",
    "sg:city":"Dayton",
    "sg:classifiers":[
        {
            "category":"Professional",
            "subcategory":"Detective & Security Services",
            "type":"Services"
        }
    ],
    "sg:phone":"+1 937 277 9458",
    "sg:postcode":"45406",
    "sg:province":"OH",
    "sg:tags":[
        "guard",
        "patrol"
    ],
    "wof:name":"B Si Security",
    "wof:placetype":"venue"
},
  "geometry": {"coordinates":[-84.253486,39.800278],"type":"Point"}
}