{
  "type": "Feature",
  "properties": {
    "iso:country":"US",
    "sg:address":"1916 Whipp Rd",
    "sg:city":"Dayton",
    "sg:classifiers":[
        {
            "category":"Restaurant",
            "type":"Food & Drink"
        }
    ],
    "sg:phone":"+1 937 429 4222",
    "sg:postcode":"45440",
    "sg:province":"OH",
    "sg:tags":[
        "pizzeria",
        "pizza"
    ],
    "wof:name":"Donatos Pizza",
    "wof:placetype":"venue"
},
  "geometry": {"coordinates":[-84.131376,39.661195],"type":"Point"}
}