{
  "type": "Feature",
  "properties": {
    "addr:full":"4981 Eck Rd Middletown OH 45042",
    "addr:housenumber":"4981",
    "addr:postcode":"45042",
    "addr:street":"Eck Rd",
    "iso:country":"US",
    "sg:address":"4981 Eck Rd",
    "sg:city":"Middletown",
    "sg:classifiers":[
        {
            "category":"Building & Trades",
            "subcategory":"Construction",
            "type":"Services"
        }
    ],
    "sg:phone":"+1 513 423 9382",
    "sg:postcode":"45042",
    "sg:province":"OH",
    "sg:tags":[
        "paving",
        "contractor"
    ],
    "wof:name":"A-1 Paving",
    "wof:placetype":"venue"
},
  "geometry": {"coordinates":[-84.43768,39.510646],"type":"Point"}
}