{
  "type": "Feature",
  "properties": {
    "addr:full": "5646 Springfield-Urbana Pike Urbana OH 43078",
    "addr:housenumber": "5646",
    "addr:postcode": "43078",
    "addr:street": "Springfield-Urbana Pike",
    "iso:country": "US",
    "sg:address": "5646 Springfield-Urbana Pike",
    "sg:city": "Urbana",
    "sg:classifiers": [
      {
        "category": "Real Estate",
        "subcategory": "Real Estate Operator",
        "type": "Services"
      }
    ],
    "sg:phone": "+1 937 484 3403",
    "sg:postcode": "43078",
    "sg:province": "OH",
    "sg:tags": [
      "mobile",
      "home",
      "community"
    ],
    "wof:name": "Harvest Square Mobile Home",
    "wof:placetype": "venue"
  },
  "geometry": {"coordinates":[-83.782047,40.028421],"type":"Point"}
}
