{
  "type": "Feature",
  "properties": {
    "iso:country":"US",
    "sg:address":"5646 Springfield-Urbana Pike",
    "sg:city":"Urbana",
    "sg:classifiers":[
        {
            "category":"Real Estate",
            "subcategory":"Real Estate Operator",
            "type":"Services"
        }
    ],
    "sg:phone":"+1 937 484 3403",
    "sg:postcode":"43078",
    "sg:province":"OH",
    "sg:tags":[
        "mobile",
        "home",
        "community"
    ],
    "wof:name":"Harvest Square Mobile Home",
    "wof:placetype":"venue"
},
  "geometry": {"coordinates":[-83.78204700000001,40.028421],"type":"Point"}
}