{
  "type": "Feature",
  "properties": {
    "iso:country":"US",
    "sg:address":"8401 Chagrin Rd Ste 13A",
    "sg:city":"Chagrin Falls",
    "sg:classifiers":[
        {
            "category":"Professional",
            "subcategory":"Employment Agencies",
            "type":"Services"
        }
    ],
    "sg:phone":"+1 440 543 2992",
    "sg:postcode":"44023",
    "sg:province":"OH",
    "sg:website":"www.onpartners.com",
    "wof:name":"On Search Partners",
    "wof:placetype":"venue"
},
  "geometry": {"coordinates":[-81.34197,41.389629],"type":"Point"}
}