{
  "type": "Feature",
  "properties": {
    "iso:country":"US",
    "sg:address":"3065 State Rte 65",
    "sg:city":"Leipsic",
    "sg:phone":"+1 419 275 2535",
    "sg:postcode":"45856",
    "sg:province":"OH",
    "sg:tags":[
        "farm",
        "corn",
        "wheat",
        "soybean"
    ],
    "wof:name":"Kenneth Stearns",
    "wof:placetype":"venue"
},
  "geometry": {"coordinates":[-83.938368,41.13569],"type":"Point"}
}