{
  "type": "Feature",
  "properties": {
    "addr:full": "1225 Barnard Rd Wooster OH 44691",
    "addr:housenumber": "1225",
    "addr:postcode": "44691",
    "addr:street": "Barnard Rd",
    "iso:country": "US",
    "sg:address": "1225 Barnard Rd",
    "sg:city": "Wooster",
    "sg:classifiers": [
      {
        "category": "Wholesale",
        "subcategory": "Electrical",
        "type": "Manufacturing \u0026 Wholesale Goods"
      }
    ],
    "sg:phone": "+1 330 698 7252",
    "sg:postcode": "44691",
    "sg:province": "OH",
    "sg:tags": [
      "fire",
      "equipment",
      "protection"
    ],
    "wof:name": "Southeast Enterprises",
    "wof:placetype": "venue"
  },
  "geometry": {"coordinates":[-81.853777,40.784223],"type":"Point"}
}
