{
  "type": "Feature",
  "properties": {
    "iso:country":"US",
    "sg:address":"1225 Barnard Rd",
    "sg:city":"Wooster",
    "sg:classifiers":[
        {
            "category":"Wholesale",
            "subcategory":"Electrical",
            "type":"Manufacturing & Wholesale Goods"
        }
    ],
    "sg:phone":"+1 330 698 7252",
    "sg:postcode":"44691",
    "sg:province":"OH",
    "sg:tags":[
        "fire",
        "equipment",
        "protection"
    ],
    "wof:name":"Southeast Enterprises",
    "wof:placetype":"venue"
},
  "geometry": {"coordinates":[-81.85377699999999,40.784223],"type":"Point"}
}