{
  "type": "Feature",
  "properties": {
    "addr:full": "10250 Alliance Rd Cincinnati OH 45242",
    "addr:housenumber": "10250",
    "addr:postcode": "45242",
    "addr:street": "Alliance Rd",
    "iso:country": "US",
    "sg:address": "10250 Alliance Rd",
    "sg:city": "Cincinnati",
    "sg:classifiers": [
      {
        "category": "Wholesale",
        "subcategory": "Electrical",
        "type": "Manufacturing \u0026 Wholesale Goods"
      }
    ],
    "sg:phone": "+1 513 563 0067",
    "sg:postcode": "45242",
    "sg:province": "OH",
    "sg:tags": [
      "equipment",
      "electric",
      "supply"
    ],
    "wof:name": "Summit Automation \u0026 Control",
    "wof:placetype": "venue"
  },
  "geometry": {"coordinates":[-84.380271,39.246043],"type":"Point"}
}
