{
  "type": "Feature",
  "properties": {
    "addr:full":"6917 W 130th St Cleveland OH 44130",
    "addr:housenumber":"6917",
    "addr:postcode":"44130",
    "addr:street":"W 130Th St",
    "iso:country":"US",
    "sg:address":"6917 W 130th St",
    "sg:city":"Cleveland",
    "sg:classifiers":[
        {
            "category":"Railroad",
            "type":"Transportation"
        },
        {
            "category":"Airline",
            "type":"Transportation"
        },
        {
            "category":"Travel",
            "subcategory":"Travel Agent",
            "type":"Entertainment"
        },
        {
            "category":"Train Station",
            "subcategory":"Rail",
            "type":"Transportation"
        },
        {
            "category":"Marine",
            "type":"Transportation"
        }
    ],
    "sg:phone":"+1 440 888 6666",
    "sg:postcode":"44130",
    "sg:province":"OH",
    "sg:tags":[
        "ticket",
        "agency",
        "railroads-ticket",
        "cruise"
    ],
    "sg:website":"http://www.atoztravelctr.com",
    "wof:name":"A to Z Travel Center",
    "wof:placetype":"venue"
},
  "geometry": {"coordinates":[-81.78475899999999,41.376027],"type":"Point"}
}