{
  "type": "Feature",
  "properties": {
    "iso:country":"US",
    "sg:address":"120 N Center St",
    "sg:city":"Bowling Green",
    "sg:classifiers":[
        {
            "category":"Education",
            "subcategory":"College",
            "type":"Public Place"
        }
    ],
    "sg:phone":"+1 419 372 2791",
    "sg:postcode":"43466",
    "sg:province":"OH",
    "wof:name":"Graduate College Bgsu",
    "wof:placetype":"venue"
},
  "geometry": {"coordinates":[-83.47356499999999,41.301603],"type":"Point"}
}