{
  "type": "Feature",
  "properties": {
    "iso:country":"US",
    "sg:address":"6045 Hardin-Wapakoneta Rd",
    "sg:city":"Sidney",
    "sg:classifiers":[
        {
            "category":"Social Services",
            "subcategory":"Child Care",
            "type":"Services"
        }
    ],
    "sg:phone":"+1 937 497 7600",
    "sg:postcode":"45365",
    "sg:province":"OH",
    "wof:name":"Happyland Daycare",
    "wof:placetype":"venue"
},
  "geometry": {"coordinates":[-84.24517,40.28778],"type":"Point"}
}