{
  "type": "Feature",
  "properties": {
    "addr:full": "104 Cleveland Ave Doylestown OH 44230",
    "addr:housenumber": "104",
    "addr:postcode": "44230",
    "addr:street": "Cleveland Ave",
    "iso:country": "US",
    "sg:address": "104 Cleveland Ave",
    "sg:city": "Doylestown",
    "sg:classifiers": [
      {
        "category": "Social Services",
        "subcategory": "Child Care",
        "type": "Services"
      }
    ],
    "sg:phone": "+1 330 658 8430",
    "sg:postcode": "44230",
    "sg:province": "OH",
    "wof:name": "Von Harten \u0026 Von Harten",
    "wof:placetype": "venue"
  },
  "geometry": {"coordinates":[-81.699692,40.96888],"type":"Point"}
}
