{
  "type": "Feature",
  "properties": {
    "iso:country":"US",
    "sg:address":"100 S 4th St",
    "sg:city":"Columbus",
    "sg:classifiers":[
        {
            "category":"Professional",
            "subcategory":"Lawyer & Legal Services",
            "type":"Services"
        }
    ],
    "sg:phone":"+1 614 464 1610",
    "sg:postcode":"43215",
    "sg:province":"OH",
    "sg:tags":[
        "firm",
        "law"
    ],
    "wof:name":"Kervin F Kurgis Attorney",
    "wof:placetype":"venue"
},
  "geometry": {"coordinates":[-82.99566299999999,39.960093],"type":"Point"}
}