{
  "type": "Feature",
  "properties": {
    "addr:full": "6448 Brookedge Ct Dublin OH 43017",
    "addr:housenumber": "6448",
    "addr:postcode": "43017",
    "addr:street": "Brookedge Ct",
    "iso:country": "US",
    "sg:address": "6448 Brookedge Ct",
    "sg:city": "Dublin",
    "sg:classifiers": [
      {
        "category": "Building \u0026 Trades",
        "subcategory": "Construction",
        "type": "Services"
      }
    ],
    "sg:phone": "+1 614 793 9934",
    "sg:postcode": "43017",
    "sg:province": "OH",
    "sg:tags": [
      "floor",
      "laying",
      "contractor"
    ],
    "wof:name": "Peter F Apostel",
    "wof:placetype": "venue"
  },
  "geometry": {"coordinates":[-83.106818,40.086133],"type":"Point"}
}
