{
  "type": "Feature",
  "properties": {
    "addr:full": "3691 Lee Rd Cleveland OH 44120",
    "addr:housenumber": "3691",
    "addr:postcode": "44120",
    "addr:street": "Lee Rd",
    "iso:country": "US",
    "sg:address": "3691 Lee Rd",
    "sg:city": "Cleveland",
    "sg:classifiers": [
      {
        "category": "Banks \u0026 Credit Unions",
        "subcategory": "Bank",
        "type": "Services"
      }
    ],
    "sg:phone": "+1 216 767 1750",
    "sg:postcode": "44120",
    "sg:province": "OH",
    "sg:tags": [
      "loan",
      "real estate"
    ],
    "wof:name": "Financial Solutions Lending",
    "wof:placetype": "venue"
  },
  "geometry": {"coordinates":[-81.564824,41.457733],"type":"Point"}
}
