{
  "type": "Feature",
  "properties": {
    "addr:full": "1612 State Rd Vermilion OH 44089",
    "addr:housenumber": "1612",
    "addr:postcode": "44089",
    "addr:street": "State Rd",
    "iso:country": "US",
    "sg:address": "1612 State Rd",
    "sg:city": "Vermilion",
    "sg:classifiers": [
      {
        "category": "Freight",
        "type": "Transportation"
      }
    ],
    "sg:phone": "+1 440 967 7867",
    "sg:postcode": "44089",
    "sg:province": "OH",
    "sg:tags": [
      "storage",
      "eating",
      "commercial",
      "general"
    ],
    "wof:name": "Route 60 U-Stor-All",
    "wof:placetype": "venue"
  },
  "geometry": {"coordinates":[-82.364847,41.402045],"type":"Point"}
}
