{
  "type": "Feature",
  "properties": {
    "addr:full": "3729 Lee Rd Cleveland OH 44120",
    "addr:housenumber": "3729",
    "addr:postcode": "44120",
    "addr:street": "Lee Rd",
    "iso:country": "US",
    "sg:address": "3729 Lee Rd",
    "sg:city": "Cleveland",
    "sg:classifiers": [
      {
        "category": "Health Services",
        "subcategory": "Dentist",
        "type": "Services"
      }
    ],
    "sg:phone": "+1 216 751 9922",
    "sg:postcode": "44120",
    "sg:province": "OH",
    "sg:tags": [
      "product",
      "dentists-cosmetic",
      "dentistry",
      "dentists-pediatric",
      "whitening",
      "teeth",
      "implant",
      "dentists-implantology"
    ],
    "sg:website": "http://www.godentalexpress.com",
    "wof:name": "Dental Express Shaker Heights",
    "wof:placetype": "venue"
  },
  "geometry": {"coordinates":[-81.564919,41.458144],"type":"Point"}
}
