{
  "type": "Feature",
  "properties": {
    "addr:full":"6094 River Styx Rd Medina OH 44256",
    "addr:housenumber":"6094",
    "addr:postcode":"44256",
    "addr:street":"River Styx Rd",
    "iso:country":"US",
    "sg:address":"6094 River Styx Rd",
    "sg:city":"Medina",
    "sg:classifiers":[
        {
            "category":"Shopping",
            "subcategory":"Computers & Home Electronics",
            "type":"Retail Goods"
        }
    ],
    "sg:phone":"+1 330 722 1291",
    "sg:postcode":"44256",
    "sg:province":"OH",
    "sg:tags":[
        "equipment",
        "audio"
    ],
    "wof:name":"U S Satellite Dish Services",
    "wof:placetype":"venue"
},
  "geometry": {"coordinates":[-81.809995,41.108966],"type":"Point"}
}