{
  "type": "Feature",
  "properties": {
    "addr:full": "44195 State Rte 14 Columbiana OH 44408",
    "addr:housenumber": "44195",
    "addr:postcode": "44408",
    "addr:street": "State Rte 14",
    "iso:country": "US",
    "sg:address": "44195 State Rte 14",
    "sg:city": "Columbiana",
    "sg:classifiers": [
      {
        "category": "Autos \u0026 Motor Vehicles",
        "subcategory": "Automobile Sales",
        "type": "Retail Goods"
      }
    ],
    "sg:phone": "+1 330 482 1066",
    "sg:postcode": "44408",
    "sg:province": "OH",
    "sg:tags": [
      "car",
      "used",
      "dealer"
    ],
    "wof:name": "L and L Auto Outlet",
    "wof:placetype": "venue"
  },
  "geometry": {"coordinates":[-80.665224,40.899814],"type":"Point"}
}
