{
  "type": "Feature",
  "properties": {
    "iso:country":"US",
    "sg:address":"1708 Pelton Rd",
    "sg:city":"Fostoria",
    "sg:classifiers":[
        {
            "category":"Retail",
            "subcategory":"Repair Shop",
            "type":"Services"
        }
    ],
    "sg:phone":"+1 419 435 8041",
    "sg:postcode":"44830",
    "sg:province":"OH",
    "sg:tags":[
        "television",
        "radio"
    ],
    "wof:name":"B & J TV & Electronics",
    "wof:placetype":"venue"
},
  "geometry": {"coordinates":[-83.43278599999999,41.190774],"type":"Point"}
}