{
  "type": "Feature",
  "properties": {
    "addr:full": "1708 Pelton Rd Fostoria OH 44830",
    "addr:housenumber": "1708",
    "addr:postcode": "44830",
    "addr:street": "Pelton Rd",
    "iso:country": "US",
    "sg:address": "1708 Pelton Rd",
    "sg:city": "Fostoria",
    "sg:classifiers": [
      {
        "category": "Retail",
        "subcategory": "Repair Shop",
        "type": "Services"
      }
    ],
    "sg:phone": "+1 419 435 8041",
    "sg:postcode": "44830",
    "sg:province": "OH",
    "sg:tags": [
      "television",
      "radio"
    ],
    "wof:name": "B \u0026 J TV \u0026 Electronics",
    "wof:placetype": "venue"
  },
  "geometry": {"coordinates":[-83.432786,41.190774],"type":"Point"}
}
