{
  "type": "Feature",
  "properties": {
    "addr:full": "10 N 1st St Miamisburg OH 45342",
    "addr:housenumber": "10",
    "addr:postcode": "45342",
    "addr:street": "N 1St St",
    "iso:country": "US",
    "sg:address": "10 N 1st St",
    "sg:city": "Miamisburg",
    "sg:classifiers": [
      {
        "category": "Government",
        "subcategory": "Office",
        "type": "Public Place"
      }
    ],
    "sg:phone": "+1 937 847 6456",
    "sg:postcode": "45342",
    "sg:province": "OH",
    "sg:tags": [
      "city"
    ],
    "wof:name": "Miamisburg City Manager",
    "wof:placetype": "venue"
  },
  "geometry": {"coordinates":[-84.287293,39.643385],"type":"Point"}
}
