{
  "type": "Feature",
  "properties": {
    "addr:full":"3434 S Dixie Hwy Lima OH 45804",
    "addr:housenumber":"3434",
    "addr:postcode":"45804",
    "addr:street":"S Dixie Hwy",
    "iso:country":"US",
    "sg:address":"3434 S Dixie Hwy",
    "sg:city":"Lima",
    "sg:classifiers":[
        {
            "category":"Wholesale",
            "subcategory":"Machinery & Supplies",
            "type":"Manufacturing & Wholesale Goods"
        }
    ],
    "sg:phone":"+1 419 991 2065",
    "sg:postcode":"45804",
    "sg:province":"OH",
    "sg:tags":[
        "equipment",
        "sewer",
        "cleaning"
    ],
    "sg:website":"www.sreco.com",
    "wof:name":"Sreco Flexible",
    "wof:placetype":"venue"
},
  "geometry": {"coordinates":[-84.125478,40.693509],"type":"Point"}
}