{
  "type": "Feature",
  "properties": {
    "iso:country":"US",
    "sg:address":"2974 E Broad St",
    "sg:city":"Columbus",
    "sg:classifiers":[
        {
            "category":"Restaurant",
            "type":"Food & Drink"
        }
    ],
    "sg:phone":"+1 614 237 6767",
    "sg:postcode":"43209",
    "sg:province":"OH",
    "sg:tags":[
        "drinking",
        "eating"
    ],
    "wof:name":"Billy Lee's Chinese Cuisine",
    "wof:placetype":"venue"
},
  "geometry": {"coordinates":[-82.921198,39.971227],"type":"Point"}
}