{
  "type": "Feature",
  "properties": {
    "addr:full":"6752 Welland St Dublin OH 43017",
    "addr:housenumber":"6752",
    "addr:postcode":"43017",
    "addr:street":"Welland St",
    "iso:country":"US",
    "sg:address":"6752 Welland St",
    "sg:city":"Dublin",
    "sg:classifiers":[
        {
            "category":"Building & Trades",
            "subcategory":"Landscaping Services",
            "type":"Services"
        }
    ],
    "sg:phone":"+1 614 932 7333",
    "sg:postcode":"43017",
    "sg:province":"OH",
    "sg:tags":[
        "landscape",
        "contractor"
    ],
    "wof:name":"Central OH Hydro Seeding",
    "wof:placetype":"venue"
},
  "geometry": {"coordinates":[-83.10524599999999,40.093014],"type":"Point"}
}