{
  "type": "Feature",
  "properties": {
    "iso:country":"US",
    "sg:address":"221 Brooks Rd",
    "sg:city":"Hamilton",
    "sg:classifiers":[
        {
            "category":"Farming",
            "subcategory":"Farm",
            "type":"Manufacturing & Wholesale Goods"
        }
    ],
    "sg:phone":"+1 513 726 5531",
    "sg:postcode":"45013",
    "sg:province":"IN",
    "wof:name":"Harris Farm & Fish",
    "wof:placetype":"venue"
},
  "geometry": {"coordinates":[-84.571415,39.472721],"type":"Point"}
}