{
  "type": "Feature",
  "properties": {
    "addr:full": "221 Brooks Rd Hamilton IN 45013",
    "addr:housenumber": "221",
    "addr:postcode": "45013",
    "addr:street": "Brooks Rd",
    "iso:country": "US",
    "sg:address": "221 Brooks Rd",
    "sg:city": "Hamilton",
    "sg:classifiers": [
      {
        "category": "Farming",
        "subcategory": "Farm",
        "type": "Manufacturing \u0026 Wholesale Goods"
      }
    ],
    "sg:phone": "+1 513 726 5531",
    "sg:postcode": "45013",
    "sg:province": "IN",
    "wof:name": "Harris Farm \u0026 Fish",
    "wof:placetype": "venue"
  },
  "geometry": {"coordinates":[-84.571415,39.472721],"type":"Point"}
}
