{
  "type": "Feature",
  "properties": {
    "iso:country":"US",
    "sg:address":"252 Barnsbury Dr",
    "sg:city":"Lima",
    "sg:classifiers":[
        {
            "category":"Organizations",
            "subcategory":"Religious Organization",
            "type":"Services"
        }
    ],
    "sg:phone":"+1 419 221 0963",
    "sg:postcode":"45804",
    "sg:province":"OH",
    "sg:tags":[
        "clergy"
    ],
    "wof:name":"Ronald Jones",
    "wof:placetype":"venue"
},
  "geometry": {"coordinates":[-84.055032,40.737694],"type":"Point"}
}