{
  "type": "Feature",
  "properties": {
    "iso:country":"US",
    "sg:address":"222 High St NW",
    "sg:city":"Carrollton",
    "sg:classifiers":[
        {
            "category":"Shopping",
            "type":"Retail Goods"
        }
    ],
    "sg:phone":"+1 330 627 0535",
    "sg:postcode":"44615",
    "sg:province":"OH",
    "sg:tags":[
        "pet",
        "shop",
        "merchandise"
    ],
    "wof:name":"Tweety's Pet Haven",
    "wof:placetype":"venue"
},
  "geometry": {"coordinates":[-81.08635599999999,40.574966],"type":"Point"}
}