{
  "type": "Feature",
  "properties": {
    "addr:full": "622 W Waterloo Rd Akron OH 44314",
    "addr:housenumber": "622",
    "addr:postcode": "44314",
    "addr:street": "W Waterloo Rd",
    "iso:country": "US",
    "sg:address": "622 W Waterloo Rd",
    "sg:city": "Akron",
    "sg:classifiers": [
      {
        "category": "Wholesale",
        "subcategory": "Construction Materials",
        "type": "Manufacturing \u0026 Wholesale Goods"
      }
    ],
    "sg:phone": "+1 330 848 3006",
    "sg:postcode": "44314",
    "sg:province": "OH",
    "sg:tags": [
      "pallet",
      "skid"
    ],
    "wof:name": "R \u0026 P Pallets",
    "wof:placetype": "venue"
  },
  "geometry": {"coordinates":[-81.547013,41.030581],"type":"Point"}
}
