{
  "type": "Feature",
  "properties": {
    "iso:country":"US",
    "sg:address":"622 W Waterloo Rd",
    "sg:city":"Akron",
    "sg:classifiers":[
        {
            "category":"Wholesale",
            "subcategory":"Construction Materials",
            "type":"Manufacturing & Wholesale Goods"
        }
    ],
    "sg:phone":"+1 330 848 3006",
    "sg:postcode":"44314",
    "sg:province":"OH",
    "sg:tags":[
        "pallet",
        "skid"
    ],
    "wof:name":"R & P Pallets",
    "wof:placetype":"venue"
},
  "geometry": {"coordinates":[-81.54701300000001,41.030581],"type":"Point"}
}