{
  "type": "Feature",
  "properties": {
    "addr:full": "4366 The Trail Port Clinton OH 43452",
    "addr:housenumber": "4366",
    "addr:postcode": "43452",
    "addr:street": "The Trail",
    "iso:country": "US",
    "sg:address": "4366 The Trail",
    "sg:city": "Port Clinton",
    "sg:classifiers": [
      {
        "category": "Building \u0026 Trades",
        "subcategory": "Construction",
        "type": "Services"
      }
    ],
    "sg:phone": "+1 419 797 4965",
    "sg:postcode": "43452",
    "sg:province": "OH",
    "sg:tags": [
      "general",
      "contractor"
    ],
    "wof:name": "Catawba Island Builders LLC",
    "wof:placetype": "venue"
  },
  "geometry": {"coordinates":[-82.82241,41.569495],"type":"Point"}
}
