{
  "type": "Feature",
  "properties": {
    "addr:full":"9337 Ravenna Rd Twinsburg OH 44087",
    "addr:housenumber":"9337",
    "addr:postcode":"44087",
    "addr:street":"Ravenna Rd",
    "iso:country":"US",
    "sg:address":"9337 Ravenna Rd",
    "sg:city":"Twinsburg",
    "sg:classifiers":[
        {
            "category":"Building & Trades",
            "subcategory":"Plumbing",
            "type":"Services"
        }
    ],
    "sg:phone":"+1 330 963 3504",
    "sg:postcode":"44087",
    "sg:province":"OH",
    "sg:tags":[
        "plumbing",
        "contractor"
    ],
    "wof:name":"M G Plumbing Inc",
    "wof:placetype":"venue"
},
  "geometry": {"coordinates":[-81.429654,41.308319],"type":"Point"}
}