{
  "type": "Feature",
  "properties": {
    "addr:full": "3852 State Rte 669 Somerset OH 43783",
    "addr:housenumber": "3852",
    "addr:postcode": "43783",
    "addr:street": "State Rte 669",
    "iso:country": "US",
    "sg:address": "3852 State Rte 669",
    "sg:city": "Somerset",
    "sg:classifiers": [
      {
        "category": "Retail",
        "subcategory": "Repair Shop",
        "type": "Services"
      }
    ],
    "sg:phone": "+1 740 743 1461",
    "sg:postcode": "43783",
    "sg:province": "OH",
    "sg:tags": [
      "appliance"
    ],
    "wof:name": "Somerset Appliance Repair",
    "wof:placetype": "venue"
  },
  "geometry": {"coordinates":[-82.251207,39.790844],"type":"Point"}
}
