{
  "type": "Feature",
  "properties": {
    "iso:country":"US",
    "sg:address":"3852 State Rte 669",
    "sg:city":"Somerset",
    "sg:classifiers":[
        {
            "category":"Retail",
            "subcategory":"Repair Shop",
            "type":"Services"
        }
    ],
    "sg:phone":"+1 740 743 1461",
    "sg:postcode":"43783",
    "sg:province":"OH",
    "sg:tags":[
        "appliance"
    ],
    "wof:name":"Somerset Appliance Repair",
    "wof:placetype":"venue"
},
  "geometry": {"coordinates":[-82.25120699999999,39.790844],"type":"Point"}
}