{
  "type": "Feature",
  "properties": {
    "iso:country":"US",
    "sg:address":"3450 W Central Ave",
    "sg:city":"Toledo",
    "sg:classifiers":[
        {
            "category":"Professional",
            "subcategory":"Employment Agencies",
            "type":"Services"
        }
    ],
    "sg:phone":"+1 419 535 6233",
    "sg:postcode":"43606",
    "sg:province":"OH",
    "sg:tags":[
        "home",
        "supply",
        "health",
        "help",
        "care"
    ],
    "wof:name":"Kelly Services",
    "wof:placetype":"venue"
},
  "geometry": {"coordinates":[-83.62496899999999,41.677433],"type":"Point"}
}