{
  "type": "Feature",
  "properties": {
    "addr:full": "2568 S Hamilton Rd Columbus OH 43232",
    "addr:housenumber": "2568",
    "addr:postcode": "43232",
    "addr:street": "S Hamilton Rd",
    "iso:country": "US",
    "sg:address": "2568 S Hamilton Rd",
    "sg:city": "Columbus",
    "sg:classifiers": [
      {
        "category": "Shopping",
        "type": "Retail Goods"
      }
    ],
    "sg:phone": "+1 614 866 6661",
    "sg:postcode": "43232",
    "sg:province": "OH",
    "sg:tags": [
      "pet",
      "shop"
    ],
    "sg:website": "www.petland.com",
    "wof:name": "Petland",
    "wof:placetype": "venue"
  },
  "geometry": {"coordinates":[-82.88019,39.919723],"type":"Point"}
}
