{
  "type": "Feature",
  "properties": {
    "addr:full": "8419 State Rte 19 Green Springs OH 44836",
    "addr:housenumber": "8419",
    "addr:postcode": "44836",
    "addr:street": "State Rte 19 Green Springs",
    "iso:country": "US",
    "sg:address": "8419 State Rte 19",
    "sg:city": "Green Springs",
    "sg:classifiers": [
      {
        "category": "Wholesale",
        "subcategory": "Farm Supplies",
        "type": "Manufacturing \u0026 Wholesale Goods"
      },
      {
        "category": "Freight",
        "type": "Transportation"
      }
    ],
    "sg:phone": "+1 419 639 2242",
    "sg:postcode": "44836",
    "sg:province": "OH",
    "sg:tags": [
      "grain",
      "elevator"
    ],
    "wof:name": "Country Springs Farmers Co-Op",
    "wof:placetype": "venue"
  },
  "geometry": {"coordinates":[-83.054253,41.244517],"type":"Point"}
}
