{
  "type": "Feature",
  "properties": {
    "addr:full": "135 Muskingum Ave Zanesville OH 43701",
    "addr:housenumber": "135",
    "addr:postcode": "43701",
    "addr:street": "Muskingum Ave",
    "iso:country": "US",
    "sg:address": "135 Muskingum Ave",
    "sg:city": "Zanesville",
    "sg:classifiers": [
      {
        "category": "Professional",
        "type": "Services"
      }
    ],
    "sg:phone": "+1 740 588 9755",
    "sg:postcode": "43701",
    "sg:province": "OH",
    "sg:tags": [
      "establishment"
    ],
    "wof:name": "Elk Eye River Trading Co",
    "wof:placetype": "venue"
  },
  "geometry": {"coordinates":[-82.010206,39.936349],"type":"Point"}
}
