{
  "type": "Feature",
  "properties": {
    "addr:full":"299 W Main St Ashville OH 43103",
    "addr:housenumber":"299",
    "addr:postcode":"43103",
    "addr:street":"W Main St",
    "iso:country":"US",
    "sg:address":"299 W Main St",
    "sg:city":"Ashville",
    "sg:classifiers":[
        {
            "category":"Health Services",
            "subcategory":"Doctor",
            "type":"Services"
        }
    ],
    "sg:phone":"+1 740 983 2594",
    "sg:postcode":"43103",
    "sg:province":"OH",
    "sg:tags":[
        "physician",
        "surgeon"
    ],
    "wof:name":"Pickaway Medical Group",
    "wof:placetype":"venue"
},
  "geometry": {"coordinates":[-82.960239,39.713209],"type":"Point"}
}