{
  "type": "Feature",
  "properties": {
    "addr:full": "6010 Sebright Ln Cincinnati OH 45230",
    "addr:postcode": "6010;45230",
    "addr:street": "Sebright Ln",
    "iso:country": "US",
    "sg:address": "6010 Sebright Ln",
    "sg:city": "Cincinnati",
    "sg:classifiers": [
      {
        "category": "Shopping",
        "subcategory": "Hobbies, Toys, \u0026 Games",
        "type": "Retail Goods"
      },
      {
        "category": "Shopping",
        "subcategory": "Crafts \u0026 Fabrics",
        "type": "Retail Goods"
      }
    ],
    "sg:phone": "+1 513 624 6764",
    "sg:postcode": "45230",
    "sg:province": "OH",
    "sg:tags": [
      "shop",
      "hobby",
      "model",
      "supply"
    ],
    "wof:name": "Stone Crafts",
    "wof:placetype": "venue"
  },
  "geometry": {"coordinates":[-84.395416,39.073639],"type":"Point"}
}
