{
  "type": "Feature",
  "properties": {
    "iso:country":"US",
    "sg:address":"4519 N High St",
    "sg:city":"Columbus",
    "sg:classifiers":[
        {
            "category":"Restaurant",
            "type":"Food & Drink"
        },
        {
            "category":"Bakery",
            "type":"Food & Drink"
        }
    ],
    "sg:menulink":"http://www.allmenus.com/oh/columbus/106037-panera-bread/menu/",
    "sg:phone":"+1 614 262 5200",
    "sg:postcode":"43214",
    "sg:province":"OH",
    "sg:tags":[
        "american",
        "sandwich",
        "bakery",
        "pastry"
    ],
    "wof:name":"Panera Bread",
    "wof:placetype":"venue"
},
  "geometry": {"coordinates":[-83.019976,40.05426],"type":"Point"}
}