{
  "type": "Feature",
  "properties": {
    "iso:country":"US",
    "sg:address":"5492 Mayfield Rd",
    "sg:city":"Cleveland",
    "sg:classifiers":[
        {
            "category":"Wholesale",
            "subcategory":"Apparel",
            "type":"Manufacturing & Wholesale Goods"
        }
    ],
    "sg:phone":"+1 440 605 9002",
    "sg:postcode":"44124",
    "sg:province":"OH",
    "sg:tags":[
        "sewing",
        "supply"
    ],
    "wof:name":"G & T Inc",
    "wof:placetype":"venue"
},
  "geometry": {"coordinates":[-81.479958,41.519896],"type":"Point"}
}