{
  "type": "Feature",
  "properties": {
    "iso:country":"US",
    "sg:address":"2391 Meadow Spring Cir",
    "sg:city":"Columbus",
    "sg:classifiers":[
        {
            "category":"Real Estate",
            "subcategory":"Real Estate Operator",
            "type":"Services"
        }
    ],
    "sg:phone":"+1 614 766 0312",
    "sg:postcode":"43235",
    "sg:province":"OH",
    "sg:tags":[
        "apartment"
    ],
    "wof:name":"Meadow View Apartments",
    "wof:placetype":"venue"
},
  "geometry": {"coordinates":[-83.07837499999999,40.094407],"type":"Point"}
}