{
  "type": "Feature",
  "properties": {
    "iso:country":"US",
    "sg:address":"7632 State Rte 138",
    "sg:city":"Hillsboro",
    "sg:classifiers":[
        {
            "category":"Shopping",
            "subcategory":"Florist",
            "type":"Retail Goods"
        }
    ],
    "sg:phone":"+1 937 840 0669",
    "sg:postcode":"45133",
    "sg:province":"OH",
    "sg:tags":[
        "merchandise"
    ],
    "wof:name":"Katina's Flowers",
    "wof:placetype":"venue"
},
  "geometry": {"coordinates":[-83.594178,39.217962],"type":"Point"}
}