{
  "type": "Feature",
  "properties": {
    "addr:full": "7310 Alexander Rd Painesville OH 44077",
    "addr:housenumber": "7310",
    "addr:postcode": "44077",
    "addr:street": "Alexander Rd",
    "iso:country": "US",
    "sg:address": "7310 Alexander Rd",
    "sg:city": "Painesville",
    "sg:classifiers": [
      {
        "category": "Professional",
        "type": "Services"
      }
    ],
    "sg:phone": "+1 440 352 6310",
    "sg:postcode": "44077",
    "sg:province": "OH",
    "sg:tags": [
      "establishment"
    ],
    "wof:name": "Napqo Limited",
    "wof:placetype": "venue"
  },
  "geometry": {"coordinates":[-81.212019,41.675403],"type":"Point"}
}
