{
  "type": "Feature",
  "properties": {
    "addr:full":"910 E Market St Cadiz OH 43907",
    "addr:housenumber":"910",
    "addr:postcode":"43907",
    "addr:street":"E Market St",
    "iso:country":"US",
    "sg:address":"910 E Market St",
    "sg:city":"Cadiz",
    "sg:classifiers":[
        {
            "category":"Real Estate",
            "subcategory":"Real Estate Agent",
            "type":"Services"
        }
    ],
    "sg:phone":"+1 740 942 2023",
    "sg:postcode":"43907",
    "sg:province":"OH",
    "wof:name":"Coultrap Management",
    "wof:placetype":"venue"
},
  "geometry": {"coordinates":[-80.98033100000001,40.259442],"type":"Point"}
}