{
  "type": "Feature",
  "properties": {
    "addr:full": "50 E Main St Mc Connelsville OH 43756",
    "addr:housenumber": "50",
    "addr:postcode": "43756",
    "addr:street": "E Main St",
    "iso:country": "US",
    "sg:address": "50 E Main St",
    "sg:city": "Mc Connelsville",
    "sg:classifiers": [
      {
        "category": "Home \u0026 Garden",
        "subcategory": "Hardware",
        "type": "Retail Goods"
      }
    ],
    "sg:phone": "+1 740 962 4261",
    "sg:postcode": "43756",
    "sg:province": "OH",
    "wof:name": "True Value Hardware",
    "wof:placetype": "venue"
  },
  "geometry": {"coordinates":[-81.852588,39.648711],"type":"Point"}
}
