{
  "type": "Feature",
  "properties": {
    "addr:full": "7030 Seville Rd Seville OH 44273",
    "addr:housenumber": "7030",
    "addr:postcode": "44273",
    "addr:street": "Seville Rd",
    "iso:country": "US",
    "sg:address": "7030 Seville Rd",
    "sg:city": "Seville",
    "sg:classifiers": [
      {
        "category": "Building \u0026 Trades",
        "subcategory": "Cleaning \u0026 Sanitation",
        "type": "Services"
      }
    ],
    "sg:phone": "+1 330 990 4404",
    "sg:postcode": "44273",
    "sg:province": "OH",
    "sg:tags": [
      "house"
    ],
    "wof:name": "Superior House Cleaning",
    "wof:placetype": "venue"
  },
  "geometry": {"coordinates":[-81.941748,41.0123],"type":"Point"}
}
