{
  "type": "Feature",
  "properties": {
    "addr:full":"21400 Chagrin Blvd Cleveland OH 44122",
    "addr:housenumber":"21400",
    "addr:postcode":"44122",
    "addr:street":"Chagrin Blvd",
    "iso:country":"US",
    "sg:address":"21400 Chagrin Blvd",
    "sg:city":"Cleveland",
    "sg:classifiers":[
        {
            "category":"Government",
            "subcategory":"Office",
            "type":"Public Place"
        }
    ],
    "sg:phone":"+1 216 348 7210",
    "sg:postcode":"44122",
    "sg:province":"OH",
    "sg:tags":[
        "village"
    ],
    "wof:name":"Cleveland Cemeteries General",
    "wof:placetype":"venue"
},
  "geometry": {"coordinates":[-81.520166,41.46442],"type":"Point"}
}