{
  "type": "Feature",
  "properties": {
    "addr:full":"1446 S Union Ave Alliance OH 44601",
    "addr:housenumber":"1446",
    "addr:postcode":"44601",
    "addr:street":"S Union Ave",
    "iso:country":"US",
    "sg:address":"1446 S Union Ave",
    "sg:city":"Alliance",
    "sg:classifiers":[
        {
            "category":"Organizations",
            "subcategory":"Community Association",
            "type":"Services"
        }
    ],
    "sg:phone":"+1 330 823 0956",
    "sg:postcode":"44601",
    "sg:province":"OH",
    "sg:tags":[
        "sorority",
        "fraternity"
    ],
    "wof:name":"Sturgeon House",
    "wof:placetype":"venue"
},
  "geometry": {"coordinates":[-81.105782,40.907527],"type":"Point"}
}