{
  "type": "Feature",
  "properties": {
    "iso:country":"US",
    "sg:address":"5109 Pearl Ave",
    "sg:city":"Lorain",
    "sg:classifiers":[
        {
            "category":"Retail",
            "subcategory":"Repair Shop",
            "type":"Services"
        }
    ],
    "sg:phone":"+1 440 277 9626",
    "sg:postcode":"44055",
    "sg:province":"OH",
    "sg:tags":[
        "equipment",
        "material",
        "handling",
        "related"
    ],
    "wof:name":"Universal Container Repair Inc",
    "wof:placetype":"venue"
},
  "geometry": {"coordinates":[-82.13459,41.420992],"type":"Point"}
}