{
  "type": "Feature",
  "properties": {
    "addr:full": "10600 US Hwy 42 Marysville OH 43040",
    "addr:housenumber": "10600",
    "addr:postcode": "43040",
    "addr:street": "Us Hwy 42",
    "iso:country": "US",
    "sg:address": "10600 US Hwy 42",
    "sg:city": "Marysville",
    "sg:classifiers": [
      {
        "category": "Organizations",
        "subcategory": "Non-profit Organization",
        "type": "Services"
      },
      {
        "category": "Organizations",
        "subcategory": "Professional Association",
        "type": "Services"
      }
    ],
    "sg:phone": "+1 614 873 6736",
    "sg:postcode": "43040",
    "sg:province": "OH",
    "sg:tags": [
      "trade"
    ],
    "wof:name": "Ohio Cattlemens Association",
    "wof:placetype": "venue"
  },
  "geometry": {"coordinates":[-83.228013,40.164608],"type":"Point"}
}
