{
  "type": "Feature",
  "properties": {
    "addr:full": "275 S 21st St Newark OH 43055",
    "addr:housenumber": "275",
    "addr:postcode": "43055",
    "addr:street": "S 21St St",
    "iso:country": "US",
    "sg:address": "275 S 21st St",
    "sg:city": "Newark",
    "sg:classifiers": [
      {
        "category": "Real Estate",
        "subcategory": "Real Estate Agent",
        "type": "Services"
      }
    ],
    "sg:phone": "+1 740 344 2311",
    "sg:postcode": "43055",
    "sg:province": "OH",
    "sg:tags": [
      "appraiser"
    ],
    "wof:name": "First Choice Appraisal Service",
    "wof:placetype": "venue"
  },
  "geometry": {"coordinates":[-82.431502,40.044186],"type":"Point"}
}
