{
  "type": "Feature",
  "properties": {
    "iso:country":"US",
    "sg:address":"1 E 4th St",
    "sg:city":"Cincinnati",
    "sg:classifiers":[
        {
            "category":"Banks & Credit Unions",
            "subcategory":"Financial Services",
            "type":"Services"
        }
    ],
    "sg:phone":"+1 513 579 2866",
    "sg:postcode":"45202",
    "sg:province":"OH",
    "sg:tags":[
        "trust",
        "management"
    ],
    "wof:name":"Aht Service Corp",
    "wof:placetype":"venue"
},
  "geometry": {"coordinates":[-84.511887,39.100069],"type":"Point"}
}