{
  "type": "Feature",
  "properties": {
    "addr:full":"2528 Edgehill Rd Cleveland OH 44106",
    "addr:housenumber":"2528",
    "addr:postcode":"44106",
    "addr:street":"Edgehill Rd",
    "iso:country":"US",
    "sg:address":"2528 Edgehill Rd",
    "sg:city":"Cleveland",
    "sg:classifiers":[
        {
            "category":"Communications",
            "subcategory":"Film & Video Production",
            "type":"Services"
        }
    ],
    "sg:phone":"+1 216 321 1440",
    "sg:postcode":"44106",
    "sg:province":"OH",
    "sg:tags":[
        "duplication",
        "tape"
    ],
    "wof:name":"Videodub International",
    "wof:placetype":"venue"
},
  "geometry": {"coordinates":[-81.58876100000001,41.50623],"type":"Point"}
}