{
  "type": "Feature",
  "properties": {
    "addr:full": "3324 Secor Rd Toledo OH 43606",
    "addr:housenumber": "3324",
    "addr:postcode": "43606",
    "addr:street": "Secor Rd",
    "iso:country": "US",
    "sg:address": "3324 Secor Rd",
    "sg:city": "Toledo",
    "sg:classifiers": [
      {
        "category": "Food \u0026 Beverages",
        "subcategory": "Groceries \u0026 Convenience Stores",
        "type": "Retail Goods"
      }
    ],
    "sg:phone": "+1 419 531 6570",
    "sg:postcode": "43606",
    "sg:province": "OH",
    "wof:name": "Seaway Food Town",
    "wof:placetype": "venue"
  },
  "geometry": {"coordinates":[-83.622662,41.678635],"type":"Point"}
}
