{
  "type": "Feature",
  "properties": {
    "iso:country":"US",
    "sg:address":"1137 S Main St",
    "sg:city":"Findlay",
    "sg:classifiers":[
        {
            "category":"Organizations",
            "subcategory":"Religious Organization",
            "type":"Services"
        }
    ],
    "sg:phone":"+1 419 422 3551",
    "sg:postcode":"45840",
    "sg:province":"OH",
    "sg:tags":[
        "church"
    ],
    "wof:name":"Christian Science Reading Room",
    "wof:placetype":"venue"
},
  "geometry": {"coordinates":[-83.65021900000001,41.027023],"type":"Point"}
}