{
  "type": "Feature",
  "properties": {
    "addr:full": "1137 S Main St Findlay OH 45840",
    "addr:housenumber": "1137",
    "addr:postcode": "45840",
    "addr:street": "S Main St",
    "iso:country": "US",
    "sg:address": "1137 S Main St",
    "sg:city": "Findlay",
    "sg:classifiers": [
      {
        "category": "Organizations",
        "subcategory": "Religious Organization",
        "type": "Services"
      }
    ],
    "sg:phone": "+1 419 422 3551",
    "sg:postcode": "45840",
    "sg:province": "OH",
    "sg:tags": [
      "church"
    ],
    "wof:name": "Christian Science Reading Room",
    "wof:placetype": "venue"
  },
  "geometry": {"coordinates":[-83.650219,41.027023],"type":"Point"}
}
