{
  "type": "Feature",
  "properties": {
    "addr:full":"69 Pearl St Painesville OH 44077",
    "addr:housenumber":"69",
    "addr:postcode":"44077",
    "addr:street":"Pearl St",
    "iso:country":"US",
    "sg:address":"69 Pearl St",
    "sg:city":"Painesville",
    "sg:classifiers":[
        {
            "category":"Social Services",
            "subcategory":"Adult Care",
            "type":"Services"
        }
    ],
    "sg:phone":"+1 440 354 3774",
    "sg:postcode":"44077",
    "sg:province":"OH",
    "sg:tags":[
        "residential"
    ],
    "wof:name":"Salvation Army",
    "wof:placetype":"venue"
},
  "geometry": {"coordinates":[-81.240484,41.720199],"type":"Point"}
}