{
  "type": "Feature",
  "properties": {
    "addr:full":"6266 W Chester Rd West Chester OH 45069",
    "addr:housenumber":"6266",
    "addr:postcode":"45069",
    "addr:street":"W Chester Rd",
    "iso:country":"US",
    "sg:address":"6266 W Chester Rd",
    "sg:city":"West Chester",
    "sg:classifiers":[
        {
            "category":"Banks & Credit Unions",
            "subcategory":"Bank",
            "type":"Services"
        }
    ],
    "sg:phone":"+1 513 779 6845",
    "sg:postcode":"45069",
    "sg:province":"OH",
    "sg:tags":[
        "loan",
        "real estate"
    ],
    "wof:name":"James C Sanders",
    "wof:placetype":"venue"
},
  "geometry": {"coordinates":[-84.41633899999999,39.326087],"type":"Point"}
}