{
  "type": "Feature",
  "properties": {
    "addr:full": "7879 Cresthill Dr Cleveland OH 44131",
    "addr:housenumber": "7879",
    "addr:postcode": "44131",
    "addr:street": "Cresthill Dr",
    "iso:country": "US",
    "sg:address": "7879 Cresthill Dr",
    "sg:city": "Cleveland",
    "sg:classifiers": [
      {
        "category": "Education",
        "subcategory": "Dance Studio",
        "type": "Public Place"
      }
    ],
    "sg:phone": "+1 216 475 8277",
    "sg:postcode": "44131",
    "sg:province": "OH",
    "sg:tags": [
      "instruction",
      "dancing"
    ],
    "wof:name": "Revolutions Dance Academy",
    "wof:placetype": "venue"
  },
  "geometry": {"coordinates":[-81.671133,41.364098],"type":"Point"}
}
