{
  "type": "Feature",
  "properties": {
    "iso:country":"US",
    "sg:address":"900 Scioto St",
    "sg:city":"Urbana",
    "sg:classifiers":[
        {
            "category":"Health Services",
            "subcategory":"Doctor",
            "type":"Services"
        }
    ],
    "sg:phone":"+1 937 652 3828",
    "sg:postcode":"43078",
    "sg:province":"OH",
    "sg:tags":[
        "physician",
        "surgeon"
    ],
    "wof:name":"Greater Oh Eye Surgeons",
    "wof:placetype":"venue"
},
  "geometry": {"coordinates":[-83.730136,40.106707],"type":"Point"}
}