{
  "type": "Feature",
  "properties": {
    "addr:full": "28596 Woodland Pl Perrysburg OH 43551",
    "addr:housenumber": "28596",
    "addr:postcode": "43551",
    "addr:street": "Woodland Pl",
    "iso:country": "US",
    "sg:address": "28596 Woodland Pl",
    "sg:city": "Perrysburg",
    "sg:classifiers": [
      {
        "category": "Banks \u0026 Credit Unions",
        "subcategory": "Financial Services",
        "type": "Services"
      }
    ],
    "sg:phone": "+1 419 874 6144",
    "sg:postcode": "43551",
    "sg:province": "OH",
    "sg:tags": [
      "trust",
      "management"
    ],
    "wof:name": "Harvey Loving Trust",
    "wof:placetype": "venue"
  },
  "geometry": {"coordinates":[-83.597847,41.566442],"type":"Point"}
}
