{
  "type": "Feature",
  "properties": {
    "iso:country":"US",
    "sg:address":"2235 Needmore Rd",
    "sg:city":"Dayton",
    "sg:classifiers":[
        {
            "category":"Restaurant",
            "type":"Food & Drink"
        }
    ],
    "sg:menulink":"http://www.allmenus.com/oh/harrison/151734-aw-restaurant/menu/",
    "sg:phone":"+1 937 275 5940",
    "sg:postcode":"45414",
    "sg:province":"OH",
    "sg:tags":[
        "burger",
        "american",
        "dog",
        "pub",
        "hot"
    ],
    "wof:name":"A&W Restaurant",
    "wof:placetype":"venue"
},
  "geometry": {"coordinates":[-84.19215800000001,39.819891],"type":"Point"}
}