{
  "type": "Feature",
  "properties": {
    "addr:full": "2235 Needmore Rd Dayton OH 45414",
    "addr:housenumber": "2235",
    "addr:postcode": "45414",
    "addr:street": "Needmore Rd",
    "iso:country": "US",
    "sg:address": "2235 Needmore Rd",
    "sg:city": "Dayton",
    "sg:classifiers": [
      {
        "category": "Restaurant",
        "type": "Food \u0026 Drink"
      }
    ],
    "sg:menulink": "http://www.allmenus.com/oh/harrison/151734-aw-restaurant/menu/",
    "sg:phone": "+1 937 275 5940",
    "sg:postcode": "45414",
    "sg:province": "OH",
    "sg:tags": [
      "burger",
      "american",
      "dog",
      "pub",
      "hot"
    ],
    "wof:name": "A\u0026W Restaurant",
    "wof:placetype": "venue"
  },
  "geometry": {"coordinates":[-84.192158,39.819891],"type":"Point"}
}
