{
  "type": "Feature",
  "properties": {
    "addr:full": "7586 Germantown Rd Middletown OH 45042",
    "addr:housenumber": "7586",
    "addr:postcode": "45042",
    "addr:street": "Germantown Rd",
    "iso:country": "US",
    "sg:address": "7586 Germantown Rd",
    "sg:city": "Middletown",
    "sg:classifiers": [
      {
        "category": "Retail",
        "subcategory": "Repair Shop",
        "type": "Services"
      }
    ],
    "sg:phone": "+1 937 855 4327",
    "sg:postcode": "45042",
    "sg:province": "OH",
    "sg:tags": [
      "equipment",
      "hydraulic"
    ],
    "wof:name": "Gray Hydraulic Repair",
    "wof:placetype": "venue"
  },
  "geometry": {"coordinates":[-84.374224,39.575291],"type":"Point"}
}
