{
  "type": "Feature",
  "properties": {
    "iso:country":"US",
    "sg:address":"16140 Allen Center Rd",
    "sg:city":"Marysville",
    "sg:classifiers":[
        {
            "category":"Building & Trades",
            "subcategory":"Plumbing",
            "type":"Services"
        }
    ],
    "sg:phone":"+1 937 578 0100",
    "sg:postcode":"43040",
    "sg:province":"OH",
    "sg:tags":[
        "air",
        "heating",
        "contractor"
    ],
    "wof:name":"Marysville Air LLC",
    "wof:placetype":"venue"
},
  "geometry": {"coordinates":[-83.464703,40.233189],"type":"Point"}
}