{
  "type": "Feature",
  "properties": {
    "iso:country":"US",
    "sg:address":"4327 Wales Dr",
    "sg:city":"Dayton",
    "sg:classifiers":[
        {
            "category":"Building & Trades",
            "subcategory":"Construction",
            "type":"Services"
        }
    ],
    "sg:phone":"+1 937 277 2042",
    "sg:postcode":"45405",
    "sg:province":"OH",
    "sg:tags":[
        "house",
        "contractor",
        "construct",
        "roofing"
    ],
    "wof:name":"Peterson's Roofing",
    "wof:placetype":"venue"
},
  "geometry": {"coordinates":[-84.23147,39.805026],"type":"Point"}
}