{
  "type": "Feature",
  "properties": {
    "iso:country":"US",
    "sg:address":"2642 Swansea Rd",
    "sg:city":"Columbus",
    "sg:classifiers":[
        {
            "category":"Professional",
            "subcategory":"Management & Consulting",
            "type":"Services"
        }
    ],
    "sg:phone":"+1 614 442 7614",
    "sg:postcode":"43221",
    "sg:province":"OH",
    "sg:tags":[
        "consultant",
        "business"
    ],
    "wof:name":"Pacificomm Associates",
    "wof:placetype":"venue"
},
  "geometry": {"coordinates":[-83.089873,40.02426],"type":"Point"}
}