{
  "type": "Feature",
  "properties": {
    "addr:full": "1134 Spencerville Ave Delphos OH 45833",
    "addr:housenumber": "1134",
    "addr:postcode": "45833",
    "addr:street": "Spencerville Ave",
    "iso:country": "US",
    "sg:address": "1134 Spencerville Ave",
    "sg:city": "Delphos",
    "sg:classifiers": [
      {
        "category": "Shopping",
        "subcategory": "Computers \u0026 Home Electronics",
        "type": "Retail Goods"
      }
    ],
    "sg:phone": "+1 419 692 9751",
    "sg:postcode": "45833",
    "sg:province": "OH",
    "wof:name": "Radio Store",
    "wof:placetype": "venue"
  },
  "geometry": {"coordinates":[-84.334975,40.831346],"type":"Point"}
}
