{
  "type": "Feature",
  "properties": {
    "iso:country":"US",
    "sg:address":"1134 Spencerville Ave",
    "sg:city":"Delphos",
    "sg:classifiers":[
        {
            "category":"Shopping",
            "subcategory":"Computers & Home Electronics",
            "type":"Retail Goods"
        }
    ],
    "sg:phone":"+1 419 692 9751",
    "sg:postcode":"45833",
    "sg:province":"OH",
    "wof:name":"Radio Store",
    "wof:placetype":"venue"
},
  "geometry": {"coordinates":[-84.334975,40.831346],"type":"Point"}
}