{
  "type": "Feature",
  "properties": {
    "addr:full":"5900 Co Rd F Delta OH 43515",
    "addr:housenumber":"5900",
    "addr:postcode":"43515",
    "addr:street":"Co Rd",
    "iso:country":"US",
    "sg:address":"5900 Co Rd F",
    "sg:city":"Delta",
    "sg:phone":"+1 419 822 5643",
    "sg:postcode":"43515",
    "sg:province":"OH",
    "sg:tags":[
        "farm",
        "corn",
        "soybean"
    ],
    "wof:name":"Gary Fager",
    "wof:placetype":"venue"
},
  "geometry": {"coordinates":[-83.971971,41.559021],"type":"Point"}
}