{
  "type": "Feature",
  "properties": {
    "addr:full":"1187 Hayden Ave Cleveland OH 44110",
    "addr:housenumber":"1187",
    "addr:postcode":"44110",
    "addr:street":"Hayden Ave",
    "iso:country":"US",
    "sg:address":"1187 Hayden Ave",
    "sg:city":"Cleveland",
    "sg:classifiers":[
        {
            "category":"Professional",
            "type":"Services"
        }
    ],
    "sg:phone":"+1 216 761 0772",
    "sg:postcode":"44110",
    "sg:province":"OH",
    "sg:tags":[
        "establishment"
    ],
    "wof:name":"Masjid Al Qiyamah",
    "wof:placetype":"venue"
},
  "geometry": {"coordinates":[-81.58656499999999,41.546333],"type":"Point"}
}