{
  "type": "Feature",
  "properties": {
    "iso:country":"US",
    "sg:address":"209 S King Rd",
    "sg:city":"Holland",
    "sg:classifiers":[
        {
            "category":"Organizations",
            "subcategory":"Religious Organization",
            "type":"Services"
        }
    ],
    "sg:phone":"+1 419 867 3759",
    "sg:postcode":"43528",
    "sg:province":"OH",
    "sg:tags":[
        "church"
    ],
    "wof:name":"Payne Memorial AMEC Church",
    "wof:placetype":"venue"
},
  "geometry": {"coordinates":[-83.722781,41.634314],"type":"Point"}
}