{
  "type": "Feature",
  "properties": {
    "iso:country":"US",
    "sg:address":"1020 W 1st St",
    "sg:city":"Uhrichsville",
    "sg:classifiers":[
        {
            "category":"Wholesale",
            "subcategory":"Machinery & Supplies",
            "type":"Manufacturing & Wholesale Goods"
        }
    ],
    "sg:phone":"+1 740 922 3671",
    "sg:postcode":"44683",
    "sg:province":"OH",
    "sg:tags":[
        "equipment",
        "safety",
        "clothing"
    ],
    "wof:name":"Hall Safety Apparel",
    "wof:placetype":"venue"
},
  "geometry": {"coordinates":[-81.358636,40.39236],"type":"Point"}
}