{
  "type": "Feature",
  "properties": {
    "addr:full": "1020 W 1st St Uhrichsville OH 44683",
    "addr:housenumber": "1020",
    "addr:postcode": "44683",
    "addr:street": "W 1St St",
    "iso:country": "US",
    "sg:address": "1020 W 1st St",
    "sg:city": "Uhrichsville",
    "sg:classifiers": [
      {
        "category": "Wholesale",
        "subcategory": "Machinery \u0026 Supplies",
        "type": "Manufacturing \u0026 Wholesale Goods"
      }
    ],
    "sg:phone": "+1 740 922 3671",
    "sg:postcode": "44683",
    "sg:province": "OH",
    "sg:tags": [
      "equipment",
      "safety",
      "clothing"
    ],
    "wof:name": "Hall Safety Apparel",
    "wof:placetype": "venue"
  },
  "geometry": {"coordinates":[-81.358636,40.39236],"type":"Point"}
}
