{
  "type": "Feature",
  "properties": {
    "iso:country":"US",
    "sg:address":"1909 Robinson Ave",
    "sg:city":"Portsmouth",
    "sg:classifiers":[
        {
            "category":"Personal",
            "subcategory":"Barber",
            "type":"Services"
        }
    ],
    "sg:phone":"+1 740 354 6724",
    "sg:postcode":"45662",
    "sg:province":"OH",
    "wof:name":"Bender's Barber Shop",
    "wof:placetype":"venue"
},
  "geometry": {"coordinates":[-82.976395,38.739674],"type":"Point"}
}