{
  "type": "Feature",
  "properties": {
    "addr:full": "734 S Progress Dr Medina OH 44256",
    "addr:housenumber": "734",
    "addr:postcode": "44256",
    "addr:street": "S Progress Dr",
    "iso:country": "US",
    "sg:address": "734 S Progress Dr",
    "sg:city": "Medina",
    "sg:classifiers": [
      {
        "category": "Utilities",
        "subcategory": "Refuse",
        "type": "Services"
      }
    ],
    "sg:phone": "+1 330 723 6659",
    "sg:postcode": "44256",
    "sg:province": "OH",
    "sg:tags": [
      "system"
    ],
    "wof:name": "Schaefer Energy",
    "wof:placetype": "venue"
  },
  "geometry": {"coordinates":[-81.879271,41.144143],"type":"Point"}
}
