{
  "type": "Feature",
  "properties": {
    "iso:country":"US",
    "sg:address":"5558 Pearl Rd",
    "sg:city":"Cleveland",
    "sg:classifiers":[
        {
            "category":"Insurance",
            "subcategory":"Insurance Agent",
            "type":"Services"
        }
    ],
    "sg:phone":"+1 440 888 0655",
    "sg:postcode":"44129",
    "sg:province":"OH",
    "wof:name":"Benefit Buliders Insurance Grp",
    "wof:placetype":"venue"
},
  "geometry": {"coordinates":[-81.737961,41.41022],"type":"Point"}
}