{
  "type": "Feature",
  "properties": {
    "addr:full": "4838 Dalton-Fox Lake Rd North Lawrence OH 44666",
    "addr:housenumber": "4838",
    "addr:postcode": "44666",
    "addr:street": "Dalton-Fox Lake Rd",
    "iso:country": "US",
    "sg:address": "4838 Dalton-Fox Lake Rd",
    "sg:city": "North Lawrence",
    "sg:classifiers": [
      {
        "category": "Shopping",
        "subcategory": "Computers \u0026 Home Electronics",
        "type": "Retail Goods"
      }
    ],
    "sg:phone": "+1 330 682 3633",
    "sg:postcode": "44666",
    "sg:province": "OH",
    "sg:tags": [
      "parts",
      "supply"
    ],
    "wof:name": "PC Clones",
    "wof:placetype": "venue"
  },
  "geometry": {"coordinates":[-81.67687,40.859579],"type":"Point"}
}
