{
  "type": "Feature",
  "properties": {
    "addr:full": "130 Maple St Lisbon OH 44432",
    "addr:housenumber": "130",
    "addr:postcode": "44432",
    "addr:street": "Maple St",
    "iso:country": "US",
    "sg:address": "130 Maple St",
    "sg:city": "Lisbon",
    "sg:classifiers": [
      {
        "category": "Government",
        "subcategory": "Office",
        "type": "Public Place"
      }
    ],
    "sg:phone": "+1 330 424 9078",
    "sg:postcode": "44432",
    "sg:province": "OH",
    "sg:tags": [
      "county",
      "program",
      "adm"
    ],
    "wof:name": "Columbiana County Economic Dev",
    "wof:placetype": "venue"
  },
  "geometry": {"coordinates":[-80.769507,40.769806],"type":"Point"}
}
