{
  "type": "Feature",
  "properties": {
    "addr:full": "415 Prospect Ave E Cleveland OH 44115",
    "addr:housenumber": "415",
    "addr:postcode": "44115",
    "addr:street": "Prospect Ave E",
    "iso:country": "US",
    "sg:address": "415 Prospect Ave E",
    "sg:city": "Cleveland",
    "sg:classifiers": [
      {
        "category": "Shopping",
        "subcategory": "Music",
        "type": "Retail Goods"
      }
    ],
    "sg:phone": "+1 216 861 4567",
    "sg:postcode": "44115",
    "sg:province": "OH",
    "sg:tags": [
      "compact",
      "record",
      "disc",
      "tape"
    ],
    "wof:name": "Downtown Records \u0026 Tapes",
    "wof:placetype": "venue"
  },
  "geometry": {"coordinates":[-81.688905,41.498541],"type":"Point"}
}
