{
  "type": "Feature",
  "properties": {
    "iso:country":"US",
    "sg:address":"415 Prospect Ave E",
    "sg:city":"Cleveland",
    "sg:classifiers":[
        {
            "category":"Shopping",
            "subcategory":"Music",
            "type":"Retail Goods"
        }
    ],
    "sg:phone":"+1 216 861 4567",
    "sg:postcode":"44115",
    "sg:province":"OH",
    "sg:tags":[
        "compact",
        "record",
        "disc",
        "tape"
    ],
    "wof:name":"Downtown Records & Tapes",
    "wof:placetype":"venue"
},
  "geometry": {"coordinates":[-81.68890500000001,41.498541],"type":"Point"}
}