{
  "type": "Feature",
  "properties": {
    "addr:full":"528 S Main St Ada OH 45810",
    "addr:housenumber":"528",
    "addr:postcode":"45810",
    "addr:street":"S Main St",
    "iso:country":"US",
    "sg:address":"528 S Main St",
    "sg:city":"Ada",
    "sg:classifiers":[
        {
            "category":"Banks & Credit Unions",
            "subcategory":"Bank",
            "type":"Services"
        }
    ],
    "sg:phone":"+1 419 634 7045",
    "sg:postcode":"45810",
    "sg:province":"OH",
    "sg:website":"www.usbank.com",
    "wof:name":"US Bank",
    "wof:placetype":"venue"
},
  "geometry": {"coordinates":[-83.823131,40.766336],"type":"Point"}
}