{
  "type": "Feature",
  "properties": {
    "addr:full":"100 W Main St Ashland OH 44805",
    "addr:housenumber":"100",
    "addr:postcode":"44805",
    "addr:street":"W Main St",
    "iso:country":"US",
    "sg:address":"100 W Main St",
    "sg:city":"Ashland",
    "sg:classifiers":[
        {
            "category":"Personal",
            "type":"Services"
        }
    ],
    "sg:phone":"+1 419 289 6633",
    "sg:postcode":"44805",
    "sg:province":"OH",
    "sg:tags":[
        "therapist",
        "massage"
    ],
    "wof:name":"Ashland Masso Therapy Clinic",
    "wof:placetype":"venue"
},
  "geometry": {"coordinates":[-82.31727600000001,40.868718],"type":"Point"}
}