{
  "type": "Feature",
  "properties": {
    "addr:full": "5580 Bennington Rd Hillsboro OH 45133",
    "addr:housenumber": "5580",
    "addr:postcode": "45133",
    "addr:street": "Bennington Rd",
    "iso:country": "US",
    "sg:address": "5580 Bennington Rd",
    "sg:city": "Hillsboro",
    "sg:classifiers": [
      {
        "category": "Home \u0026 Garden",
        "subcategory": "Garden Supply",
        "type": "Retail Goods"
      }
    ],
    "sg:phone": "+1 937 393 0903",
    "sg:postcode": "45133",
    "sg:province": "OH",
    "wof:name": "Chappas Outdoor Pwr Eqp Repai",
    "wof:placetype": "venue"
  },
  "geometry": {"coordinates":[-83.554392,39.166325],"type":"Point"}
}
