{
  "type": "Feature",
  "properties": {
    "addr:full": "16275 Rd 27 Fort Jennings OH 45844",
    "addr:housenumber": "16275",
    "addr:postcode": "45844",
    "addr:street": "Rd 27 Fort",
    "iso:country": "US",
    "sg:address": "16275 Rd 27",
    "sg:city": "Fort Jennings",
    "sg:classifiers": [
      {
        "category": "Real Estate",
        "subcategory": "Real Estate Agent",
        "type": "Services"
      }
    ],
    "sg:phone": "+1 419 453 2281",
    "sg:postcode": "45844",
    "sg:province": "OH",
    "wof:name": "Langhals Realty",
    "wof:placetype": "venue"
  },
  "geometry": {"coordinates":[-84.379695,40.942884],"type":"Point"}
}
