{
  "type": "Feature",
  "properties": {
    "iso:country":"US",
    "sg:address":"22973 Co Rd 265",
    "sg:city":"Ridgeway",
    "sg:classifiers":[
        {
            "category":"Farming",
            "subcategory":"Farm",
            "type":"Manufacturing & Wholesale Goods"
        }
    ],
    "sg:phone":"+1 937 363 3906",
    "sg:postcode":"43345",
    "sg:province":"OH",
    "sg:tags":[
        "crop",
        "general"
    ],
    "wof:name":"Mike L Jacobs",
    "wof:placetype":"venue"
},
  "geometry": {"coordinates":[-83.62207100000001,40.533971],"type":"Point"}
}