{
  "type": "Feature",
  "properties": {
    "addr:full": "22973 Co Rd 265 Ridgeway OH 43345",
    "addr:housenumber": "22973;265",
    "addr:postcode": "43345",
    "addr:street": "Co Rd",
    "iso:country": "US",
    "sg:address": "22973 Co Rd 265",
    "sg:city": "Ridgeway",
    "sg:classifiers": [
      {
        "category": "Farming",
        "subcategory": "Farm",
        "type": "Manufacturing \u0026 Wholesale Goods"
      }
    ],
    "sg:phone": "+1 937 363 3906",
    "sg:postcode": "43345",
    "sg:province": "OH",
    "sg:tags": [
      "crop",
      "general"
    ],
    "wof:name": "Mike L Jacobs",
    "wof:placetype": "venue"
  },
  "geometry": {"coordinates":[-83.622071,40.533971],"type":"Point"}
}
