{
  "type": "Feature",
  "properties": {
    "addr:full": "2645 Charter St Columbus OH 43228",
    "addr:housenumber": "2645",
    "addr:postcode": "43228",
    "addr:street": "Charter St",
    "iso:country": "US",
    "sg:address": "2645 Charter St",
    "sg:city": "Columbus",
    "sg:classifiers": [
      {
        "category": "Shopping",
        "type": "Retail Goods"
      },
      {
        "category": "Wholesale",
        "subcategory": "Chemicals \u0026 Plastics",
        "type": "Manufacturing \u0026 Wholesale Goods"
      }
    ],
    "sg:phone": "+1 614 777 9240",
    "sg:postcode": "43228",
    "sg:province": "OH",
    "sg:tags": [
      "water",
      "industrial",
      "treatment",
      "sewage"
    ],
    "sg:website": "www.chemgroup.com",
    "wof:name": "Bonded Chemicals Inc",
    "wof:placetype": "venue"
  },
  "geometry": {"coordinates":[-83.13548,40.013677],"type":"Point"}
}
