{
  "type": "Feature",
  "properties": {
    "addr:full":"7030 Reading Rd Cincinnati OH 45237",
    "addr:housenumber":"7030",
    "addr:postcode":"45237",
    "addr:street":"Reading Rd",
    "iso:country":"US",
    "sg:address":"7030 Reading Rd",
    "sg:city":"Cincinnati",
    "sg:classifiers":[
        {
            "category":"Wholesale",
            "subcategory":"Home Furnishings",
            "type":"Manufacturing & Wholesale Goods"
        }
    ],
    "sg:phone":"+1 513 351 0994",
    "sg:postcode":"45237",
    "sg:province":"OH",
    "sg:tags":[
        "material",
        "floor"
    ],
    "wof:name":"Montgomery Hardwood Flooring",
    "wof:placetype":"venue"
},
  "geometry": {"coordinates":[-84.46402,39.188198],"type":"Point"}
}