{
  "type": "Feature",
  "properties": {
    "addr:full":"5300 Harvard Ave Cleveland OH 44105",
    "addr:housenumber":"5300",
    "addr:postcode":"44105",
    "addr:street":"Harvard Ave",
    "iso:country":"US",
    "sg:address":"5300 Harvard Ave",
    "sg:city":"Cleveland",
    "sg:classifiers":[
        {
            "category":"Manufacturing",
            "subcategory":"Rubber & Plastics",
            "type":"Manufacturing & Wholesale Goods"
        }
    ],
    "sg:phone":"+1 216 429 8950",
    "sg:postcode":"44105",
    "sg:province":"OH",
    "sg:tags":[
        "compounding",
        "resin",
        "custom"
    ],
    "wof:name":"Tymex Plastics Inc",
    "wof:placetype":"venue"
},
  "geometry": {"coordinates":[-81.65208800000001,41.448242],"type":"Point"}
}