{
  "type": "Feature",
  "properties": {
    "addr:full": "5300 Harvard Ave Cleveland OH 44105",
    "addr:housenumber": "5300",
    "addr:postcode": "44105",
    "addr:street": "Harvard Ave",
    "iso:country": "US",
    "sg:address": "5300 Harvard Ave",
    "sg:city": "Cleveland",
    "sg:classifiers": [
      {
        "category": "Manufacturing",
        "subcategory": "Rubber \u0026 Plastics",
        "type": "Manufacturing \u0026 Wholesale Goods"
      }
    ],
    "sg:phone": "+1 216 429 8950",
    "sg:postcode": "44105",
    "sg:province": "OH",
    "sg:tags": [
      "compounding",
      "resin",
      "custom"
    ],
    "wof:name": "Tymex Plastics Inc",
    "wof:placetype": "venue"
  },
  "geometry": {"coordinates":[-81.652088,41.448242],"type":"Point"}
}
