{
  "type": "Feature",
  "properties": {
    "addr:full": "401 W 44th St Ashtabula OH 44004",
    "addr:housenumber": "401",
    "addr:postcode": "44004",
    "addr:street": "W 44Th St",
    "iso:country": "US",
    "sg:address": "401 W 44th St",
    "sg:city": "Ashtabula",
    "sg:classifiers": [
      {
        "category": "Education",
        "subcategory": "School",
        "type": "Public Place"
      }
    ],
    "sg:phone": "+1 440 993 2522",
    "sg:postcode": "44004",
    "sg:province": "OH",
    "wof:name": "Lakeside High School",
    "wof:placetype": "venue"
  },
  "geometry": {"coordinates":[-80.784462,41.867345],"type":"Point"}
}
