{
  "type": "Feature",
  "properties": {
    "iso:country":"US",
    "sg:address":"3550 Woodford Rd",
    "sg:city":"Cincinnati",
    "sg:classifiers":[
        {
            "category":"Building & Trades",
            "subcategory":"Landscaping Services",
            "type":"Services"
        }
    ],
    "sg:phone":"+1 513 841 1237",
    "sg:postcode":"45213",
    "sg:province":"OH",
    "sg:tags":[
        "house",
        "construction",
        "landscape",
        "contractor"
    ],
    "wof:name":"Cianciolo Landscape Inc",
    "wof:placetype":"venue"
},
  "geometry": {"coordinates":[-84.415219,39.179825],"type":"Point"}
}