{
  "type": "Feature",
  "properties": {
    "addr:full": "3550 Woodford Rd Cincinnati OH 45213",
    "addr:housenumber": "3550",
    "addr:postcode": "45213",
    "addr:street": "Woodford Rd",
    "iso:country": "US",
    "sg:address": "3550 Woodford Rd",
    "sg:city": "Cincinnati",
    "sg:classifiers": [
      {
        "category": "Building \u0026 Trades",
        "subcategory": "Landscaping Services",
        "type": "Services"
      }
    ],
    "sg:phone": "+1 513 841 1237",
    "sg:postcode": "45213",
    "sg:province": "OH",
    "sg:tags": [
      "house",
      "construction",
      "landscape",
      "contractor"
    ],
    "wof:name": "Cianciolo Landscape Inc",
    "wof:placetype": "venue"
  },
  "geometry": {"coordinates":[-84.415219,39.179825],"type":"Point"}
}
