{
  "type": "Feature",
  "properties": {
    "addr:full": "18948 Coshocton Rd Mount Vernon OH 43050",
    "addr:housenumber": "18948",
    "addr:postcode": "43050",
    "addr:street": "Coshocton Rd",
    "iso:country": "US",
    "sg:address": "18948 Coshocton Rd",
    "sg:city": "Mount Vernon",
    "sg:classifiers": [
      {
        "category": "Building \u0026 Trades",
        "subcategory": "Construction",
        "type": "Services"
      }
    ],
    "sg:phone": "+1 740 397 7416",
    "sg:postcode": "43050",
    "sg:province": "OH",
    "sg:tags": [
      "house"
    ],
    "wof:name": "Erskine Enterprises",
    "wof:placetype": "venue"
  },
  "geometry": {"coordinates":[-82.4092,40.411785],"type":"Point"}
}
