{
  "type": "Feature",
  "properties": {
    "addr:full":"13922 Bartlett Ave Cleveland OH 44120",
    "addr:housenumber":"13922",
    "addr:postcode":"44120",
    "addr:street":"Bartlett Ave",
    "iso:country":"US",
    "sg:address":"13922 Bartlett Ave",
    "sg:city":"Cleveland",
    "sg:classifiers":[
        {
            "category":"Building & Trades",
            "subcategory":"Construction",
            "type":"Services"
        }
    ],
    "sg:phone":"+1 216 991 7138",
    "sg:postcode":"44120",
    "sg:province":"OH",
    "sg:tags":[
        "house"
    ],
    "wof:name":"Alls Homes Builders & Remodeli",
    "wof:placetype":"venue"
},
  "geometry": {"coordinates":[-81.585841,41.457409],"type":"Point"}
}