{
  "type": "Feature",
  "properties": {
    "addr:full":"5100 Whipple Ave NW Canton OH 44718",
    "addr:housenumber":"5100",
    "addr:postcode":"44718",
    "addr:street":"Whipple Ave Nw",
    "iso:country":"US",
    "sg:address":"5100 Whipple Ave NW",
    "sg:city":"Canton",
    "sg:classifiers":[
        {
            "category":"Home & Garden",
            "subcategory":"Furniture",
            "type":"Retail Goods"
        }
    ],
    "sg:phone":"+1 330 493 9625",
    "sg:postcode":"44718",
    "sg:province":"OH",
    "wof:name":"Belden Oak Furniture Outlet",
    "wof:placetype":"venue"
},
  "geometry": {"coordinates":[-81.422888,40.85585],"type":"Point"}
}