{
  "type": "Feature",
  "properties": {
    "addr:full": "2840 Boudinot Ave Cincinnati OH 45238",
    "addr:postcode": "2840;45238",
    "addr:street": "Boudinot Ave",
    "iso:country": "US",
    "sg:address": "2840 Boudinot Ave",
    "sg:city": "Cincinnati",
    "sg:classifiers": [
      {
        "category": "Education",
        "subcategory": "School",
        "type": "Public Place"
      }
    ],
    "sg:phone": "+1 513 363 0900",
    "sg:postcode": "45238",
    "sg:province": "OH",
    "sg:website": "www.cps-k12.org",
    "wof:name": "Dater Montessori School",
    "wof:placetype": "venue"
  },
  "geometry": {"coordinates":[-84.604873,39.133332],"type":"Point"}
}
