{
  "type": "Feature",
  "properties": {
    "addr:full":"4636 Indianola Ave Columbus OH 43214",
    "addr:housenumber":"4636",
    "addr:postcode":"43214",
    "addr:street":"Indianola Ave",
    "iso:country":"US",
    "sg:address":"4636 Indianola Ave",
    "sg:city":"Columbus",
    "sg:classifiers":[
        {
            "category":"Building & Trades",
            "subcategory":"Construction",
            "type":"Services"
        }
    ],
    "sg:phone":"+1 614 262 9700",
    "sg:postcode":"43214",
    "sg:province":"OH",
    "sg:tags":[
        "roofing",
        "siding",
        "contractor"
    ],
    "wof:name":"Nelson Roofing Co",
    "wof:placetype":"venue"
},
  "geometry": {"coordinates":[-83.000775,40.059194],"type":"Point"}
}