{
  "type": "Feature",
  "properties": {
    "addr:full": "4801 Memphis Ave Cleveland OH 44144",
    "addr:housenumber": "4801",
    "addr:postcode": "44144",
    "addr:street": "Memphis Ave",
    "iso:country": "US",
    "sg:address": "4801 Memphis Ave",
    "sg:city": "Cleveland",
    "sg:classifiers": [
      {
        "category": "Retail",
        "subcategory": "Funeral Services",
        "type": "Services"
      }
    ],
    "sg:phone": "+1 216 351 4625",
    "sg:postcode": "44144",
    "sg:province": "OH",
    "sg:tags": [
      "director"
    ],
    "wof:name": "Sauer Funeral Home",
    "wof:placetype": "venue"
  },
  "geometry": {"coordinates":[-81.71987,41.439886],"type":"Point"}
}
