{
  "type": "Feature",
  "properties": {
    "iso:country":"US",
    "sg:address":"24350 Center Ridge Rd",
    "sg:city":"Cleveland",
    "sg:classifiers":[
        {
            "category":"Personal",
            "subcategory":"Beauty Salon",
            "type":"Services"
        }
    ],
    "sg:phone":"+1 440 899 1225",
    "sg:postcode":"44145",
    "sg:province":"OH",
    "sg:website":"www.bellacapelli.com",
    "wof:name":"Bella Capelli Salon",
    "wof:placetype":"venue"
},
  "geometry": {"coordinates":[-81.897077,41.457367],"type":"Point"}
}