{
  "type": "Feature",
  "properties": {
    "addr:full": "746 Morrison Rd Columbus OH 43230",
    "addr:housenumber": "746",
    "addr:postcode": "43230",
    "addr:street": "Morrison Rd",
    "iso:country": "US",
    "sg:address": "746 Morrison Rd",
    "sg:city": "Columbus",
    "sg:classifiers": [
      {
        "category": "Professional",
        "subcategory": "Management \u0026 Consulting",
        "type": "Services"
      }
    ],
    "sg:phone": "+1 614 501 1100",
    "sg:postcode": "43230",
    "sg:province": "OH",
    "wof:name": "Offinger Management Co",
    "wof:placetype": "venue"
  },
  "geometry": {"coordinates":[-82.861289,40.003118],"type":"Point"}
}
