{
  "type": "Feature",
  "properties": {
    "addr:full":"1550 Ottawa Ave Defiance OH 43512",
    "addr:housenumber":"1550",
    "addr:postcode":"43512",
    "addr:street":"Ottawa Ave",
    "iso:country":"US",
    "sg:address":"1550 Ottawa Ave",
    "sg:city":"Defiance",
    "sg:classifiers":[
        {
            "category":"Building & Trades",
            "subcategory":"Construction",
            "type":"Services"
        }
    ],
    "sg:phone":"+1 419 782 1141",
    "sg:postcode":"43512",
    "sg:province":"OH",
    "sg:tags":[
        "remodeling",
        "contractor"
    ],
    "wof:name":"Barth Builders and Supply Inc",
    "wof:placetype":"venue"
},
  "geometry": {"coordinates":[-84.34837,41.266305],"type":"Point"}
}