{
  "type": "Feature",
  "properties": {
    "addr:full": "1224 Elbur Ave Cleveland OH 44107",
    "addr:housenumber": "1224",
    "addr:postcode": "44107",
    "addr:street": "Elbur Ave",
    "iso:country": "US",
    "sg:address": "1224 Elbur Ave",
    "sg:city": "Cleveland",
    "sg:classifiers": [
      {
        "category": "Manufacturing",
        "subcategory": "Printing",
        "type": "Manufacturing \u0026 Wholesale Goods"
      }
    ],
    "sg:phone": "+1 440 777 0222",
    "sg:postcode": "44107",
    "sg:province": "OH",
    "sg:tags": [
      "printer"
    ],
    "wof:name": "Mattern's Quickprint",
    "wof:placetype": "venue"
  },
  "geometry": {"coordinates":[-81.786463,41.490207],"type":"Point"}
}
