{
  "type": "Feature",
  "properties": {
    "addr:full": "289 Mount Vernon Rd Newark OH 43055",
    "addr:housenumber": "289",
    "addr:postcode": "43055",
    "addr:street": "Mount Vernon Rd",
    "iso:country": "US",
    "sg:address": "289 Mount Vernon Rd",
    "sg:city": "Newark",
    "sg:classifiers": [
      {
        "category": "Personal",
        "subcategory": "Barber",
        "type": "Services"
      }
    ],
    "sg:phone": "+1 740 349 8764",
    "sg:postcode": "43055",
    "sg:province": "OH",
    "wof:name": "Denny's Hair Station",
    "wof:placetype": "venue"
  },
  "geometry": {"coordinates":[-82.40887,40.066953],"type":"Point"}
}
