{
  "type": "Feature",
  "properties": {
    "iso:country":"US",
    "sg:address":"1400 Washington Ave",
    "sg:city":"Washington Ct Hs",
    "sg:classifiers":[
        {
            "category":"Wholesale",
            "subcategory":"Construction Materials",
            "type":"Manufacturing & Wholesale Goods"
        }
    ],
    "sg:phone":"+1 740 335 1294",
    "sg:postcode":"43160",
    "sg:province":"OH",
    "sg:tags":[
        "pallet",
        "skid"
    ],
    "wof:name":"Rehrig Penn Pallet",
    "wof:placetype":"venue"
},
  "geometry": {"coordinates":[-83.421711,39.53995],"type":"Point"}
}