{
  "type": "Feature",
  "properties": {
    "addr:full": "3440 E Main St Columbus OH 43213",
    "addr:housenumber": "3440",
    "addr:postcode": "43213",
    "addr:street": "E Main St",
    "iso:country": "US",
    "sg:address": "3440 E Main St",
    "sg:city": "Columbus",
    "sg:classifiers": [
      {
        "category": "Shopping",
        "subcategory": "Bicycles \u0026 Sporting Goods",
        "type": "Retail Goods"
      }
    ],
    "sg:phone": "+1 614 235 8585",
    "sg:postcode": "43213",
    "sg:province": "OH",
    "sg:tags": [
      "equipment",
      "gymnasium",
      "supply"
    ],
    "wof:name": "A K Athletic Equipment Inc",
    "wof:placetype": "venue"
  },
  "geometry": {"coordinates":[-82.905622,39.956381],"type":"Point"}
}
