{
  "type": "Feature",
  "properties": {
    "addr:full": "47 W South St Worthington OH 43085",
    "addr:housenumber": "47",
    "addr:postcode": "43085",
    "addr:street": "W South St",
    "iso:country": "US",
    "sg:address": "47 W South St",
    "sg:city": "Worthington",
    "sg:classifiers": [
      {
        "category": "Organizations",
        "subcategory": "Professional Association",
        "type": "Services"
      }
    ],
    "sg:phone": "+1 614 847 0160",
    "sg:postcode": "43085",
    "sg:province": "OH",
    "sg:website": "www.ohima.org",
    "wof:name": "Ohio Health Info Mgmt Assn",
    "wof:placetype": "venue"
  },
  "geometry": {"coordinates":[-83.019369,40.08436],"type":"Point"}
}
