{
  "type": "Feature",
  "properties": {
    "addr:full":"8317 Lake Ave Cincinnati OH 45236",
    "addr:housenumber":"8317",
    "addr:postcode":"45236",
    "addr:street":"Lake Ave",
    "iso:country":"US",
    "sg:address":"8317 Lake Ave",
    "sg:city":"Cincinnati",
    "sg:classifiers":[
        {
            "category":"Professional",
            "subcategory":"Secretarial Services",
            "type":"Services"
        }
    ],
    "sg:phone":"+1 513 745 0953",
    "sg:postcode":"45236",
    "sg:province":"OH",
    "sg:tags":[
        "reporting",
        "court"
    ],
    "wof:name":"Procomp Professional Computer",
    "wof:placetype":"venue"
},
  "geometry": {"coordinates":[-84.395493,39.209458],"type":"Point"}
}