{
  "type": "Feature",
  "properties": {
    "addr:full": "887 E Main St Smithville OH 44677",
    "addr:housenumber": "887",
    "addr:postcode": "44677",
    "addr:street": "E Main St",
    "iso:country": "US",
    "sg:address": "887 E Main St",
    "sg:city": "Smithville",
    "sg:classifiers": [
      {
        "category": "Home \u0026 Garden",
        "subcategory": "Furniture",
        "type": "Retail Goods"
      }
    ],
    "sg:phone": "+1 330 669 9292",
    "sg:postcode": "44677",
    "sg:province": "OH",
    "sg:tags": [
      "builder",
      "custom"
    ],
    "wof:name": "Amish Furniture Workshop",
    "wof:placetype": "venue"
  },
  "geometry": {"coordinates":[-81.849669,40.869305],"type":"Point"}
}
