{
  "type": "Feature",
  "properties": {
    "iso:country":"US",
    "sg:address":"887 E Main St",
    "sg:city":"Smithville",
    "sg:classifiers":[
        {
            "category":"Home & Garden",
            "subcategory":"Furniture",
            "type":"Retail Goods"
        }
    ],
    "sg:phone":"+1 330 669 9292",
    "sg:postcode":"44677",
    "sg:province":"OH",
    "sg:tags":[
        "builder",
        "custom"
    ],
    "wof:name":"Amish Furniture Workshop",
    "wof:placetype":"venue"
},
  "geometry": {"coordinates":[-81.84966900000001,40.869305],"type":"Point"}
}