{
  "type": "Feature",
  "properties": {
    "iso:country":"US",
    "sg:address":"4555 Lake Forest Dr Ste 510",
    "sg:city":"Cincinnati",
    "sg:classifiers":[
        {
            "category":"Insurance",
            "subcategory":"Hazard Insurance",
            "type":"Services"
        }
    ],
    "sg:phone":"+1 513 247 2700",
    "sg:postcode":"45242",
    "sg:province":"OH",
    "sg:tags":[
        "commercial",
        "business"
    ],
    "wof:name":"Benefits Network",
    "wof:placetype":"venue"
},
  "geometry": {"coordinates":[-84.381272,39.254519],"type":"Point"}
}