{
  "type": "Feature",
  "properties": {
    "iso:country":"US",
    "sg:address":"300 E Silver St",
    "sg:city":"Lebanon",
    "sg:classifiers":[
        {
            "category":"Building & Trades",
            "subcategory":"Landscaping Services",
            "type":"Services"
        }
    ],
    "sg:phone":"+1 513 932 4040",
    "sg:postcode":"45036",
    "sg:province":"OH",
    "sg:tags":[
        "lawn",
        "park"
    ],
    "wof:name":"Warren County Park District",
    "wof:placetype":"venue"
},
  "geometry": {"coordinates":[-84.202306,39.435117],"type":"Point"}
}