{
  "type": "Feature",
  "properties": {
    "addr:full": "435 Minnich Ave NW New Philadelphia OH 44663",
    "addr:housenumber": "435",
    "addr:postcode": "44663",
    "addr:street": "Minnich Ave Nw New Philadelphia",
    "iso:country": "US",
    "sg:address": "435 Minnich Ave NW",
    "sg:city": "New Philadelphia",
    "sg:classifiers": [
      {
        "category": "Restaurant",
        "type": "Food \u0026 Drink"
      }
    ],
    "sg:phone": "+1 330 364 2349",
    "sg:postcode": "44663",
    "sg:province": "OH",
    "wof:name": "Uncle Primo's",
    "wof:placetype": "venue"
  },
  "geometry": {"coordinates":[-81.452528,40.497304],"type":"Point"}
}
