{
  "type": "Feature",
  "properties": {
    "iso:country":"US",
    "sg:address":"435 Minnich Ave NW",
    "sg:city":"New Philadelphia",
    "sg:classifiers":[
        {
            "category":"Restaurant",
            "type":"Food & Drink"
        }
    ],
    "sg:phone":"+1 330 364 2349",
    "sg:postcode":"44663",
    "sg:province":"OH",
    "wof:name":"Uncle Primo's",
    "wof:placetype":"venue"
},
  "geometry": {"coordinates":[-81.452528,40.497304],"type":"Point"}
}