{
  "type": "Feature",
  "properties": {
    "addr:full":"6633 State Rd Wadsworth OH 44281",
    "addr:housenumber":"6633",
    "addr:postcode":"44281",
    "addr:street":"State Rd",
    "iso:country":"US",
    "sg:address":"6633 State Rd",
    "sg:city":"Wadsworth",
    "sg:classifiers":[
        {
            "category":"Farming",
            "subcategory":"Livestock Farm",
            "type":"Manufacturing & Wholesale Goods"
        }
    ],
    "sg:phone":"+1 330 239 1671",
    "sg:postcode":"44281",
    "sg:province":"OH",
    "sg:tags":[
        "equine"
    ],
    "wof:name":"Rick Cecil Quarter Horses",
    "wof:placetype":"venue"
},
  "geometry": {"coordinates":[-81.717984,41.097367],"type":"Point"}
}