{
  "type": "Feature",
  "properties": {
    "addr:full": "705 E 5th St Waverly OH 45690",
    "addr:housenumber": "705",
    "addr:postcode": "45690",
    "addr:street": "E 5Th St",
    "iso:country": "US",
    "sg:address": "705 E 5th St",
    "sg:city": "Waverly",
    "sg:classifiers": [
      {
        "category": "Real Estate",
        "subcategory": "Real Estate Operator",
        "type": "Services"
      }
    ],
    "sg:phone": "+1 740 941 0306",
    "sg:postcode": "45690",
    "sg:province": "OH",
    "sg:tags": [
      "building",
      "nonresidential"
    ],
    "wof:name": "Denniss Properties LLC",
    "wof:placetype": "venue"
  },
  "geometry": {"coordinates":[-82.967752,39.133609],"type":"Point"}
}
