{
  "type": "Feature",
  "properties": {
    "iso:country":"US",
    "sg:address":"2505 Devils Backbone Rd",
    "sg:city":"Cincinnati",
    "sg:classifiers":[
        {
            "category":"Professional",
            "type":"Services"
        }
    ],
    "sg:phone":"+1 513 922 9481",
    "sg:postcode":"45233",
    "sg:province":"OH",
    "wof:name":"Bill Geisel",
    "wof:placetype":"venue"
},
  "geometry": {"coordinates":[-84.66551200000001,39.140241],"type":"Point"}
}