{
  "type": "Feature",
  "properties": {
    "addr:full":"20 E Scioto St Orient OH 43146",
    "addr:housenumber":"20",
    "addr:postcode":"43146",
    "addr:street":"E Scioto St",
    "iso:country":"US",
    "sg:address":"20 E Scioto St",
    "sg:city":"Orient",
    "sg:classifiers":[
        {
            "category":"Professional",
            "type":"Services"
        }
    ],
    "sg:phone":"+1 614 877 9291",
    "sg:postcode":"43146",
    "sg:province":"OH",
    "sg:tags":[
        "establishment"
    ],
    "wof:name":"Lighthouse Community Christia",
    "wof:placetype":"venue"
},
  "geometry": {"coordinates":[-83.05783599999999,39.768294],"type":"Point"}
}