{
  "type": "Feature",
  "properties": {
    "addr:full": "7244 Co Hwy 623 Millersburg OH 44654",
    "addr:housenumber": "7244",
    "addr:postcode": "44654",
    "addr:street": "Co Hwy 623",
    "iso:country": "US",
    "sg:address": "7244 Co Hwy 623",
    "sg:city": "Millersburg",
    "sg:classifiers": [
      {
        "category": "Autos \u0026 Motor Vehicles",
        "subcategory": "Auto Supplies",
        "type": "Retail Goods"
      }
    ],
    "sg:phone": "+1 330 674 7066",
    "sg:postcode": "44654",
    "sg:province": "OH",
    "sg:tags": [
      "repair",
      "tire",
      "general"
    ],
    "wof:name": "Snyder Darb Tire Sales",
    "wof:placetype": "venue"
  },
  "geometry": {"coordinates":[-81.883304,40.554314],"type":"Point"}
}
