{
  "type": "Feature",
  "properties": {
    "addr:full": "9951 Aurora Hudson Rd Hudson OH 44236",
    "addr:housenumber": "9951",
    "addr:postcode": "44236",
    "addr:street": "Aurora Hudson Rd",
    "iso:country": "US",
    "sg:address": "9951 Aurora Hudson Rd",
    "sg:city": "Hudson",
    "sg:classifiers": [
      {
        "category": "Autos \u0026 Motor Vehicles",
        "subcategory": "Fuel \u0026 Gas Station",
        "type": "Retail Goods"
      }
    ],
    "sg:phone": "+1 330 653 2976",
    "sg:postcode": "44236",
    "sg:province": "OH",
    "sg:tags": [
      "oil"
    ],
    "wof:name": "Streetsboro Interstate Sunoco",
    "wof:placetype": "venue"
  },
  "geometry": {"coordinates":[-81.391715,41.263088],"type":"Point"}
}
