{
  "type": "Feature",
  "properties": {
    "iso:country":"US",
    "sg:address":"1338 Copley Rd",
    "sg:city":"Akron",
    "sg:classifiers":[
        {
            "category":"Personal",
            "subcategory":"Beauty Salon",
            "type":"Services"
        }
    ],
    "sg:phone":"+1 330 836 2111",
    "sg:postcode":"44320",
    "sg:province":"OH",
    "sg:tags":[
        "shop"
    ],
    "wof:name":"Cosmetique West",
    "wof:placetype":"venue"
},
  "geometry": {"coordinates":[-81.569975,41.083984],"type":"Point"}
}