{
  "type": "Feature",
  "properties": {
    "addr:full":"12550 Youngstown Salem Rd Salem OH 44460",
    "addr:housenumber":"12550",
    "addr:postcode":"44460",
    "addr:street":"Youngstown Salem Rd",
    "iso:country":"US",
    "sg:address":"12550 Youngstown Salem Rd",
    "sg:city":"Salem",
    "sg:classifiers":[
        {
            "category":"Wholesale",
            "subcategory":"Auto Parts",
            "type":"Manufacturing & Wholesale Goods"
        }
    ],
    "sg:phone":"+1 330 332 0512",
    "sg:postcode":"44460",
    "sg:province":"OH",
    "sg:tags":[
        "automobile",
        "rebuilt",
        "wrecking"
    ],
    "sg:website":"www.beautoparts.com",
    "wof:name":"Quaker City Auto Parts Inc",
    "wof:placetype":"venue"
},
  "geometry": {"coordinates":[-80.840435,40.934814],"type":"Point"}
}