{
  "type": "Feature",
  "properties": {
    "addr:full": "76576 Johnson Run Rd Kimbolton OH 43749",
    "addr:housenumber": "76576",
    "addr:postcode": "43749",
    "addr:street": "Johnson Run Rd",
    "iso:country": "US",
    "sg:address": "76576 Johnson Run Rd",
    "sg:city": "Kimbolton",
    "sg:classifiers": [
      {
        "category": "Building \u0026 Trades",
        "subcategory": "Construction",
        "type": "Services"
      }
    ],
    "sg:phone": "+1 740 498 5218",
    "sg:postcode": "43749",
    "sg:province": "OH",
    "sg:tags": [
      "excavation",
      "contractor"
    ],
    "wof:name": "Little Excavating",
    "wof:placetype": "venue"
  },
  "geometry": {"coordinates":[-81.535139,40.21403],"type":"Point"}
}
