{
  "type": "Feature",
  "properties": {
    "addr:full":"4149 N Holland Sylvania Ave Toledo OH 43623",
    "addr:housenumber":"4149",
    "addr:postcode":"43623",
    "addr:street":"N Holland Sylvania Ave",
    "iso:country":"US",
    "sg:address":"4149 N Holland Sylvania Ave",
    "sg:city":"Toledo",
    "sg:classifiers":[
        {
            "category":"Building & Trades",
            "subcategory":"Construction",
            "type":"Services"
        }
    ],
    "sg:phone":"+1 419 885 3949",
    "sg:postcode":"43623",
    "sg:province":"OH",
    "sg:tags":[
        "contractor"
    ],
    "wof:name":"Harry Young Building Co",
    "wof:placetype":"venue"
},
  "geometry": {"coordinates":[-83.687665,41.69366],"type":"Point"}
}