{
  "type": "Feature",
  "properties": {
    "addr:full": "13 W 4th St Cincinnati OH 45202",
    "addr:housenumber": "13",
    "addr:postcode": "45202",
    "addr:street": "W 4Th St",
    "iso:country": "US",
    "sg:address": "13 W 4th St",
    "sg:city": "Cincinnati",
    "sg:classifiers": [
      {
        "category": "Shopping",
        "subcategory": "Shoes",
        "type": "Retail Goods"
      }
    ],
    "sg:phone": "+1 513 352 4400",
    "sg:postcode": "45202",
    "sg:province": "OH",
    "wof:name": "Jarman 415",
    "wof:placetype": "venue"
  },
  "geometry": {"coordinates":[-84.514118,39.09967],"type":"Point"}
}
