{
  "type": "Feature",
  "properties": {
    "addr:full": "295 Upper Lewisburg Salem Rd Brookville OH 45309",
    "addr:housenumber": "295",
    "addr:postcode": "45309",
    "addr:street": "Upper Lewisburg Salem Rd",
    "iso:country": "US",
    "sg:address": "295 Upper Lewisburg Salem Rd",
    "sg:city": "Brookville",
    "sg:classifiers": [
      {
        "category": "Building \u0026 Trades",
        "subcategory": "Equipment Rental",
        "type": "Services"
      }
    ],
    "sg:phone": "+1 937 833 4000",
    "sg:postcode": "45309",
    "sg:province": "OH",
    "sg:tags": [
      "yard"
    ],
    "wof:name": "Brookville Rental \u0026 Sales",
    "wof:placetype": "venue"
  },
  "geometry": {"coordinates":[-84.376601,39.846495],"type":"Point"}
}
