{
  "type": "Feature",
  "properties": {
    "iso:country":"US",
    "sg:address":"295 Upper Lewisburg Salem Rd",
    "sg:city":"Brookville",
    "sg:classifiers":[
        {
            "category":"Building & Trades",
            "subcategory":"Equipment Rental",
            "type":"Services"
        }
    ],
    "sg:phone":"+1 937 833 4000",
    "sg:postcode":"45309",
    "sg:province":"OH",
    "sg:tags":[
        "yard"
    ],
    "wof:name":"Brookville Rental & Sales",
    "wof:placetype":"venue"
},
  "geometry": {"coordinates":[-84.37660099999999,39.846495],"type":"Point"}
}