{
  "type": "Feature",
  "properties": {
    "addr:full":"409 Lexington Ave Mansfield OH 44907",
    "addr:housenumber":"409",
    "addr:postcode":"44907",
    "addr:street":"Lexington Ave",
    "iso:country":"US",
    "sg:address":"409 Lexington Ave",
    "sg:city":"Mansfield",
    "sg:classifiers":[
        {
            "category":"Insurance",
            "subcategory":"Insurance Agent",
            "type":"Services"
        }
    ],
    "sg:phone":"+1 419 756 6155",
    "sg:postcode":"44907",
    "sg:province":"OH",
    "wof:name":"Nationwide Mutual Insurance",
    "wof:placetype":"venue"
},
  "geometry": {"coordinates":[-82.524534,40.74392],"type":"Point"}
}