{
  "type": "Feature",
  "properties": {
    "addr:full": "10 W Broad St Columbus OH 43215",
    "addr:housenumber": "10",
    "addr:postcode": "43215",
    "addr:street": "W Broad St",
    "iso:country": "US",
    "sg:address": "10 W Broad St",
    "sg:city": "Columbus",
    "sg:classifiers": [
      {
        "category": "Utilities",
        "subcategory": "Telephone",
        "type": "Services"
      }
    ],
    "sg:phone": "+1 614 233 4062",
    "sg:postcode": "43215",
    "sg:province": "OH",
    "sg:tags": [
      "telecommunication"
    ],
    "wof:name": "MCI",
    "wof:placetype": "venue"
  },
  "geometry": {"coordinates":[-83.001337,39.962228],"type":"Point"}
}
