{
  "type": "Feature",
  "properties": {
    "iso:country":"US",
    "sg:address":"310 Everett Ave",
    "sg:city":"Newark",
    "sg:classifiers":[
        {
            "category":"Education",
            "subcategory":"School",
            "type":"Public Place"
        }
    ],
    "sg:phone":"+1 740 349 2355",
    "sg:postcode":"43055",
    "sg:province":"OH",
    "sg:website":"www.laca.org",
    "wof:name":"Conrad Elementary School",
    "wof:placetype":"venue"
},
  "geometry": {"coordinates":[-82.387422,40.06329],"type":"Point"}
}