{
  "type": "Feature",
  "properties": {
    "addr:full": "4920 Scioto Darby Rd Hilliard OH 43026",
    "addr:housenumber": "4920",
    "addr:postcode": "43026",
    "addr:street": "Scioto Darby Rd",
    "iso:country": "US",
    "sg:address": "4920 Scioto Darby Rd",
    "sg:city": "Hilliard",
    "sg:classifiers": [
      {
        "category": "Freight",
        "type": "Transportation"
      }
    ],
    "sg:phone": "+1 614 777 0292",
    "sg:postcode": "43026",
    "sg:province": "OH",
    "sg:tags": [
      "truck"
    ],
    "wof:name": "Faxit",
    "wof:placetype": "venue"
  },
  "geometry": {"coordinates":[-83.144153,40.021006],"type":"Point"}
}
