{
  "type": "Feature",
  "properties": {
    "addr:full": "4940 N Thayer Rd Lima OH 45807",
    "addr:housenumber": "4940",
    "addr:postcode": "45807",
    "addr:street": "N Thayer Rd",
    "iso:country": "US",
    "sg:address": "4940 N Thayer Rd",
    "sg:city": "Lima",
    "sg:classifiers": [
      {
        "category": "Organizations",
        "subcategory": "Religious Organization",
        "type": "Services"
      }
    ],
    "sg:phone": "+1 419 643 3143",
    "sg:postcode": "45807",
    "sg:province": "OH",
    "sg:tags": [
      "clergy"
    ],
    "wof:name": "K D Barkley",
    "wof:placetype": "venue"
  },
  "geometry": {"coordinates":[-84.013177,40.812986],"type":"Point"}
}
