{
  "type": "Feature",
  "properties": {
    "addr:full":"601 Lakeside Ave E Cleveland OH 44114",
    "addr:housenumber":"601",
    "addr:postcode":"44114",
    "addr:street":"Lakeside Ave E",
    "iso:country":"US",
    "sg:address":"601 Lakeside Ave E",
    "sg:city":"Cleveland",
    "sg:classifiers":[
        {
            "category":"Government",
            "subcategory":"Office",
            "type":"Public Place"
        }
    ],
    "sg:phone":"+1 216 664 2840",
    "sg:postcode":"44114",
    "sg:province":"OH",
    "sg:tags":[
        "legislative",
        "body"
    ],
    "wof:name":"City Council Offices",
    "wof:placetype":"venue"
},
  "geometry": {"coordinates":[-81.691907,41.505407],"type":"Point"}
}