{
  "type": "Feature",
  "properties": {
    "addr:full": "3551 State Rte 83 Millersburg OH 44654",
    "addr:housenumber": "3551",
    "addr:postcode": "44654",
    "addr:street": "State Rte 83",
    "iso:country": "US",
    "sg:address": "3551 State Rte 83",
    "sg:city": "Millersburg",
    "sg:classifiers": [
      {
        "category": "Real Estate",
        "subcategory": "Real Estate Operator",
        "type": "Services"
      }
    ],
    "sg:phone": "+1 330 674 4697",
    "sg:postcode": "44654",
    "sg:province": "OH",
    "sg:tags": [
      "mobile",
      "home",
      "community"
    ],
    "wof:name": "Twin Springs Mobile Homes",
    "wof:placetype": "venue"
  },
  "geometry": {"coordinates":[-81.90979,40.508663],"type":"Point"}
}
