{
  "type": "Feature",
  "properties": {
    "iso:country":"US",
    "sg:address":"21 N Main St",
    "sg:city":"North Hampton",
    "sg:classifiers":[
        {
            "category":"Personal",
            "subcategory":"Barber",
            "type":"Services"
        }
    ],
    "sg:phone":"+1 937 964 1374",
    "sg:postcode":"45349",
    "sg:province":"OH",
    "wof:name":"Ayres Barber Shop",
    "wof:placetype":"venue"
},
  "geometry": {"coordinates":[-83.940049,39.990919],"type":"Point"}
}