{
  "type": "Feature",
  "properties": {
    "addr:full": "1200 County House Ln Marietta OH 45750",
    "addr:housenumber": "1200",
    "addr:postcode": "45750",
    "addr:street": "County House Ln",
    "iso:country": "US",
    "sg:address": "1200 County House Ln",
    "sg:city": "Marietta",
    "sg:classifiers": [
      {
        "category": "Insurance",
        "subcategory": "Insurance Agent",
        "type": "Services"
      }
    ],
    "sg:phone": "+1 740 373 6058",
    "sg:postcode": "45750",
    "sg:province": "OH",
    "wof:name": "Robert Carr Insurance",
    "wof:placetype": "venue"
  },
  "geometry": {"coordinates":[-81.410921,39.404546],"type":"Point"}
}
