{
  "type": "Feature",
  "properties": {
    "addr:full": "15644 State Rte 136 Winchester OH 45697",
    "addr:housenumber": "15644",
    "addr:postcode": "45697",
    "addr:street": "State Rte 136",
    "iso:country": "US",
    "sg:address": "15644 State Rte 136",
    "sg:city": "Winchester",
    "sg:classifiers": [
      {
        "category": "Retail",
        "subcategory": "Auto Repair",
        "type": "Services"
      }
    ],
    "sg:phone": "+1 937 695 0876",
    "sg:postcode": "45697",
    "sg:province": "OH",
    "sg:tags": [
      "repairing",
      "automobile"
    ],
    "wof:name": "B \u0026 W Auto Ctr LLC",
    "wof:placetype": "venue"
  },
  "geometry": {"coordinates":[-83.622262,38.902759],"type":"Point"}
}
