{
  "type": "Feature",
  "properties": {
    "addr:full": "4953 Teagues Rd Bradford OH 45308",
    "addr:housenumber": "4953",
    "addr:postcode": "45308",
    "addr:street": "Teagues Rd",
    "iso:country": "US",
    "sg:address": "4953 Teagues Rd",
    "sg:city": "Bradford",
    "sg:phone": "+1 937 448 2610",
    "sg:postcode": "45308",
    "sg:province": "OH",
    "sg:tags": [
      "farm",
      "corn",
      "soybean"
    ],
    "wof:name": "Stanley Shellabarger",
    "wof:placetype": "venue"
  },
  "geometry": {"coordinates":[-84.434113,40.062662],"type":"Point"}
}
