{
  "type": "Feature",
  "properties": {
    "iso:country":"US",
    "sg:address":"4953 Teagues Rd",
    "sg:city":"Bradford",
    "sg:phone":"+1 937 448 2610",
    "sg:postcode":"45308",
    "sg:province":"OH",
    "sg:tags":[
        "farm",
        "corn",
        "soybean"
    ],
    "wof:name":"Stanley Shellabarger",
    "wof:placetype":"venue"
},
  "geometry": {"coordinates":[-84.434113,40.062662],"type":"Point"}
}