{
  "type": "Feature",
  "properties": {
    "addr:full":"40 N Sandusky St Delaware OH 43015",
    "addr:housenumber":"40",
    "addr:postcode":"43015",
    "addr:street":"N Sandusky St",
    "iso:country":"US",
    "sg:address":"40 N Sandusky St",
    "sg:city":"Delaware",
    "sg:classifiers":[
        {
            "category":"Professional",
            "subcategory":"Lawyer & Legal Services",
            "type":"Services"
        }
    ],
    "sg:phone":"+1 740 363 8988",
    "sg:postcode":"43015",
    "sg:province":"OH",
    "sg:tags":[
        "attorney"
    ],
    "wof:name":"Gordon & Gordon",
    "wof:placetype":"venue"
},
  "geometry": {"coordinates":[-83.067542,40.301491],"type":"Point"}
}