{
  "type": "Feature",
  "properties": {
    "addr:full": "2409 N High St Columbus OH 43202",
    "addr:housenumber": "2409",
    "addr:postcode": "43202",
    "addr:street": "N High St",
    "iso:country": "US",
    "sg:address": "2409 N High St",
    "sg:city": "Columbus",
    "sg:classifiers": [
      {
        "category": "Restaurant",
        "type": "Food \u0026 Drink"
      }
    ],
    "sg:phone": "+1 614 784 2222",
    "sg:postcode": "43202",
    "sg:province": "OH",
    "wof:name": "City Pizza",
    "wof:placetype": "venue"
  },
  "geometry": {"coordinates":[-83.010716,40.011756],"type":"Point"}
}
