{
  "type": "Feature",
  "properties": {
    "addr:full":"51470 National Rd E St Clairsville OH 43950",
    "addr:housenumber":"51470",
    "addr:postcode":"43950",
    "addr:street":"National Rd E",
    "iso:country":"US",
    "sg:address":"51470 National Rd E",
    "sg:city":"St Clairsville",
    "sg:classifiers":[
        {
            "category":"Autos & Motor Vehicles",
            "subcategory":"Automobile Sales",
            "type":"Retail Goods"
        }
    ],
    "sg:phone":"+1 740 695 1354",
    "sg:postcode":"43950",
    "sg:province":"OH",
    "sg:tags":[
        "car",
        "dealer"
    ],
    "wof:name":"Marhefka's St Clairsville",
    "wof:placetype":"venue"
},
  "geometry": {"coordinates":[-80.863636,40.074735],"type":"Point"}
}