{
  "type": "Feature",
  "properties": {
    "addr:full":"6873 Bryne Ct Dublin OH 43017",
    "addr:postcode":"6873;43017",
    "addr:street":"Bryne Ct",
    "iso:country":"US",
    "sg:address":"6873 Bryne Ct",
    "sg:city":"Dublin",
    "sg:classifiers":[
        {
            "category":"Wholesale",
            "subcategory":"Durable Goods & Equipment",
            "type":"Manufacturing & Wholesale Goods"
        }
    ],
    "sg:phone":"+1 614 761 8944",
    "sg:postcode":"43017",
    "sg:province":"OH",
    "sg:tags":[
        "representative",
        "manufacturer"
    ],
    "wof:name":"Airy Sales",
    "wof:placetype":"venue"
},
  "geometry": {"coordinates":[-83.117693,40.112338],"type":"Point"}
}