{
  "type": "Feature",
  "properties": {
    "addr:full":"3804 Grey Birch Dr Amelia OH 45102",
    "addr:housenumber":"3804",
    "addr:postcode":"45102",
    "addr:street":"Grey Birch Dr",
    "iso:country":"US",
    "sg:address":"3804 Grey Birch Dr",
    "sg:city":"Amelia",
    "sg:classifiers":[
        {
            "category":"Manufacturing",
            "subcategory":"Glass & Minerals",
            "type":"Manufacturing & Wholesale Goods"
        }
    ],
    "sg:phone":"+1 513 753 8353",
    "sg:postcode":"45102",
    "sg:province":"OH",
    "sg:tags":[
        "tile",
        "ceramic",
        "mfg"
    ],
    "wof:name":"Daniel R Delany",
    "wof:placetype":"venue"
},
  "geometry": {"coordinates":[-84.23332000000001,39.051867],"type":"Point"}
}