{
  "type": "Feature",
  "properties": {
    "iso:country":"US",
    "sg:address":"11460 Co Rd 12",
    "sg:city":"Wauseon",
    "sg:classifiers":[
        {
            "category":"Building & Trades",
            "subcategory":"Construction",
            "type":"Services"
        }
    ],
    "sg:phone":"+1 419 923 4402",
    "sg:postcode":"43567",
    "sg:province":"OH",
    "sg:tags":[
        "concrete",
        "contractor"
    ],
    "wof:name":"Great Lakes Concrete  Inc",
    "wof:placetype":"venue"
},
  "geometry": {"coordinates":[-84.092714,41.63112],"type":"Point"}
}