{
  "type": "Feature",
  "properties": {
    "addr:full":"2890 Medina Ave Columbus OH 43224",
    "addr:housenumber":"2890",
    "addr:postcode":"43224",
    "addr:street":"Medina Ave",
    "iso:country":"US",
    "sg:address":"2890 Medina Ave",
    "sg:city":"Columbus",
    "sg:classifiers":[
        {
            "category":"Shopping",
            "subcategory":"Jewelry",
            "type":"Retail Goods"
        }
    ],
    "sg:phone":"+1 614 262 3785",
    "sg:postcode":"43224",
    "sg:province":"OH",
    "wof:name":"G C B Enterprises",
    "wof:placetype":"venue"
},
  "geometry": {"coordinates":[-82.973722,40.025892],"type":"Point"}
}