{
  "type": "Feature",
  "properties": {
    "addr:full": "676 E 152nd St Cleveland OH 44110",
    "addr:housenumber": "676",
    "addr:postcode": "44110",
    "addr:street": "E 152Nd St",
    "iso:country": "US",
    "sg:address": "676 E 152nd St",
    "sg:city": "Cleveland",
    "sg:classifiers": [
      {
        "category": "Building \u0026 Trades",
        "subcategory": "Construction",
        "type": "Services"
      }
    ],
    "sg:phone": "+1 216 451 1355",
    "sg:postcode": "44110",
    "sg:province": "OH",
    "sg:tags": [
      "roofing",
      "contractor"
    ],
    "wof:name": "Reader Roofing Heating \u0026 Cool",
    "wof:placetype": "venue"
  },
  "geometry": {"coordinates":[-81.575563,41.559895],"type":"Point"}
}
