{
  "type": "Feature",
  "properties": {
    "addr:full":"2227 Buckley Rd Columbus OH 43220",
    "addr:housenumber":"2227",
    "addr:postcode":"43220",
    "addr:street":"Buckley Rd",
    "iso:country":"US",
    "sg:address":"2227 Buckley Rd",
    "sg:city":"Columbus",
    "sg:classifiers":[
        {
            "category":"Social Services",
            "type":"Services"
        }
    ],
    "sg:phone":"+1 614 457 3177",
    "sg:postcode":"43220",
    "sg:province":"OH",
    "sg:tags":[
        "professional",
        "counselor"
    ],
    "wof:name":"Family Matters Counseling Svc",
    "wof:placetype":"venue"
},
  "geometry": {"coordinates":[-83.080635,40.040007],"type":"Point"}
}