{
  "type": "Feature",
  "properties": {
    "addr:full":"14 New Hudson Rd Aurora OH 44202",
    "addr:housenumber":"14",
    "addr:postcode":"44202",
    "addr:street":"New Hudson Rd",
    "iso:country":"US",
    "sg:address":"14 New Hudson Rd",
    "sg:city":"Aurora",
    "sg:classifiers":[
        {
            "category":"Sports & Exercise",
            "subcategory":"Gym",
            "type":"Entertainment"
        }
    ],
    "sg:phone":"+1 330 562 6500",
    "sg:postcode":"44202",
    "sg:province":"OH",
    "sg:tags":[
        "club",
        "health",
        "studio",
        "gymnasium"
    ],
    "wof:name":"Curves For Women",
    "wof:placetype":"venue"
},
  "geometry": {"coordinates":[-81.33408,41.316054],"type":"Point"}
}