{
  "type": "Feature",
  "properties": {
    "addr:full":"2323 Countryside Dr Fremont OH 43420",
    "addr:housenumber":"2323",
    "addr:postcode":"43420",
    "addr:street":"Countryside Dr",
    "iso:country":"US",
    "sg:address":"2323 Countryside Dr",
    "sg:city":"Fremont",
    "sg:classifiers":[
        {
            "category":"Government",
            "subcategory":"Police Station",
            "type":"Public Place"
        }
    ],
    "sg:phone":"+1 419 334 6251",
    "sg:postcode":"43420",
    "sg:province":"OH",
    "sg:tags":[
        "sheriff"
    ],
    "wof:name":"Sandusky County Sheriff Dept",
    "wof:placetype":"venue"
},
  "geometry": {"coordinates":[-83.084487,41.357996],"type":"Point"}
}