{
  "type": "Feature",
  "properties": {
    "addr:full": "1300 E State St Fremont OH 43420",
    "addr:housenumber": "1300",
    "addr:postcode": "43420",
    "addr:street": "E State St",
    "iso:country": "US",
    "sg:address": "1300 E State St",
    "sg:city": "Fremont",
    "sg:classifiers": [
      {
        "category": "Banks \u0026 Credit Unions",
        "subcategory": "Investment Brokerage",
        "type": "Services"
      }
    ],
    "sg:phone": "+1 419 334 3830",
    "sg:postcode": "43420",
    "sg:province": "OH",
    "sg:tags": [
      "advisory",
      "financial"
    ],
    "wof:name": "Thrivent Financial-Lutherans",
    "wof:placetype": "venue"
  },
  "geometry": {"coordinates":[-83.095683,41.342642],"type":"Point"}
}
