{
  "type": "Feature",
  "properties": {
    "addr:full": "689 Miamisburg Centerville Rd Dayton OH 45459",
    "addr:housenumber": "689",
    "addr:postcode": "45459",
    "addr:street": "Miamisburg Centerville Rd",
    "iso:country": "US",
    "sg:address": "689 Miamisburg Centerville Rd",
    "sg:city": "Dayton",
    "sg:classifiers": [
      {
        "category": "Shopping",
        "subcategory": "Crafts \u0026 Fabrics",
        "type": "Retail Goods"
      }
    ],
    "sg:phone": "+1 937 433 5565",
    "sg:postcode": "45459",
    "sg:province": "OH",
    "sg:tags": [
      "material",
      "needlework"
    ],
    "wof:name": "Stitching Cottage",
    "wof:placetype": "venue"
  },
  "geometry": {"coordinates":[-84.170651,39.628055],"type":"Point"}
}
