{
  "type": "Feature",
  "properties": {
    "addr:full":"5033 Delhi Ave Cincinnati OH 45238",
    "addr:housenumber":"5033",
    "addr:postcode":"45238",
    "addr:street":"Delhi Ave",
    "iso:country":"US",
    "sg:address":"5033 Delhi Ave",
    "sg:city":"Cincinnati",
    "sg:classifiers":[
        {
            "category":"Home & Garden",
            "subcategory":"Furniture",
            "type":"Retail Goods"
        }
    ],
    "sg:phone":"+1 513 451 6420",
    "sg:postcode":"45238",
    "sg:province":"OH",
    "wof:name":"Value City Furniture",
    "wof:placetype":"venue"
},
  "geometry": {"coordinates":[-84.61027300000001,39.095161],"type":"Point"}
}