{
  "type": "Feature",
  "properties": {
    "iso:country":"US",
    "sg:address":"5002 New Cumberland Rd NE",
    "sg:city":"Mineral City",
    "sg:classifiers":[
        {
            "category":"Shopping",
            "subcategory":"Bicycles & Sporting Goods",
            "type":"Retail Goods"
        }
    ],
    "sg:phone":"+1 330 364 2108",
    "sg:postcode":"44656",
    "sg:province":"OH",
    "sg:tags":[
        "repair",
        "sport",
        "gun",
        "gunsmith"
    ],
    "wof:name":"Gun Atwood & Sports",
    "wof:placetype":"venue"
},
  "geometry": {"coordinates":[-81.30975100000001,40.561343],"type":"Point"}
}