{
  "type": "Feature",
  "properties": {
    "addr:full": "5002 New Cumberland Rd NE Mineral City OH 44656",
    "addr:housenumber": "5002",
    "addr:postcode": "44656",
    "addr:street": "New Cumberland Rd Ne",
    "iso:country": "US",
    "sg:address": "5002 New Cumberland Rd NE",
    "sg:city": "Mineral City",
    "sg:classifiers": [
      {
        "category": "Shopping",
        "subcategory": "Bicycles \u0026 Sporting Goods",
        "type": "Retail Goods"
      }
    ],
    "sg:phone": "+1 330 364 2108",
    "sg:postcode": "44656",
    "sg:province": "OH",
    "sg:tags": [
      "repair",
      "sport",
      "gun",
      "gunsmith"
    ],
    "wof:name": "Gun Atwood \u0026 Sports",
    "wof:placetype": "venue"
  },
  "geometry": {"coordinates":[-81.309751,40.561343],"type":"Point"}
}
