{
  "type": "Feature",
  "properties": {
    "iso:country":"US",
    "sg:address":"119 Main St",
    "sg:city":"Huron",
    "sg:classifiers":[
        {
            "category":"Health Services",
            "subcategory":"Doctor",
            "type":"Services"
        }
    ],
    "sg:phone":"+1 419 433 5093",
    "sg:postcode":"44839",
    "sg:province":"OH",
    "sg:tags":[
        "dentist"
    ],
    "wof:name":"TLC Family Dentistry",
    "wof:placetype":"venue"
},
  "geometry": {"coordinates":[-82.55622099999999,41.393059],"type":"Point"}
}