{
  "type": "Feature",
  "properties": {
    "iso:country":"US",
    "sg:address":"5639 Montgomery Rd",
    "sg:city":"Cincinnati",
    "sg:classifiers":[
        {
            "category":"Professional",
            "type":"Services"
        }
    ],
    "sg:phone":"+1 513 731 8500",
    "sg:postcode":"45212",
    "sg:province":"OH",
    "wof:name":"Taquira Banderas",
    "wof:placetype":"venue"
},
  "geometry": {"coordinates":[-84.439644,39.176719],"type":"Point"}
}