{
  "type": "Feature",
  "properties": {
    "addr:full": "965 William Penn Dr Galloway OH 43119",
    "addr:housenumber": "965",
    "addr:postcode": "43119",
    "addr:street": "William Penn Dr",
    "iso:country": "US",
    "sg:address": "965 William Penn Dr",
    "sg:city": "Galloway",
    "sg:classifiers": [
      {
        "category": "Professional",
        "type": "Services"
      }
    ],
    "sg:phone": "+1 614 870 9798",
    "sg:postcode": "43119",
    "sg:province": "OH",
    "wof:name": "Melvin M Engel Inc",
    "wof:placetype": "venue"
  },
  "geometry": {"coordinates":[-83.167198,39.969664],"type":"Point"}
}
