{
  "type": "Feature",
  "properties": {
    "addr:full": "12221 Madison Ave Cleveland OH 44107",
    "addr:housenumber": "12221",
    "addr:postcode": "44107",
    "addr:street": "Madison Ave",
    "iso:country": "US",
    "sg:address": "12221 Madison Ave",
    "sg:city": "Cleveland",
    "sg:classifiers": [
      {
        "category": "Health Services",
        "subcategory": "Health Practitioner",
        "type": "Services"
      }
    ],
    "sg:phone": "+1 216 221 2525",
    "sg:postcode": "44107",
    "sg:province": "OH",
    "sg:tags": [
      "therapist",
      "physical"
    ],
    "wof:name": "Rehab Professionals-Cleveland",
    "wof:placetype": "venue"
  },
  "geometry": {"coordinates":[-81.774825,41.476851],"type":"Point"}
}
