{
  "type": "Feature",
  "properties": {
    "addr:full":"2324 N Cleveland Massillon Rd Akron OH 44333",
    "addr:housenumber":"2324",
    "addr:postcode":"44333",
    "addr:street":"N Cleveland Massillon Rd",
    "iso:country":"US",
    "sg:address":"2324 N Cleveland Massillon Rd",
    "sg:city":"Akron",
    "sg:classifiers":[
        {
            "category":"Manufacturing",
            "subcategory":"Metals",
            "type":"Manufacturing & Wholesale Goods"
        }
    ],
    "sg:phone":"+1 330 659 4440",
    "sg:postcode":"44333",
    "sg:province":"OH",
    "sg:tags":[
        "tower"
    ],
    "wof:name":"Warmus & Assoc Inc",
    "wof:placetype":"venue"
},
  "geometry": {"coordinates":[-81.636905,41.197682],"type":"Point"}
}