{
  "type": "Feature",
  "properties": {
    "iso:country":"US",
    "sg:address":"1505 N Star Ave",
    "sg:city":"Columbus",
    "sg:classifiers":[
        {
            "category":"Shopping",
            "subcategory":"Pharmacy",
            "type":"Retail Goods"
        }
    ],
    "sg:phone":"+1 614 885 0928",
    "sg:postcode":"43212",
    "sg:province":"OH",
    "sg:tags":[
        "grocery"
    ],
    "wof:name":"Coughlins Market Inc",
    "wof:placetype":"venue"
},
  "geometry": {"coordinates":[-83.049069,39.986308],"type":"Point"}
}