{
  "type": "Feature",
  "properties": {
    "addr:full": "4450 Eastgate Blvd Cincinnati OH 45245",
    "addr:housenumber": "4450",
    "addr:postcode": "45245",
    "addr:street": "Eastgate Blvd",
    "iso:country": "US",
    "sg:address": "4450 Eastgate Blvd",
    "sg:city": "Cincinnati",
    "sg:classifiers": [
      {
        "category": "Utilities",
        "subcategory": "Fuel Oil \u0026 Lpg",
        "type": "Services"
      }
    ],
    "sg:phone": "+1 513 752 4004",
    "sg:postcode": "45245",
    "sg:province": "OH",
    "sg:tags": [
      "gas",
      "supply"
    ],
    "wof:name": "Marathon At Biggs Place",
    "wof:placetype": "venue"
  },
  "geometry": {"coordinates":[-84.274509,39.098168],"type":"Point"}
}
