{
  "type": "Feature",
  "properties": {
    "iso:country":"US",
    "sg:address":"329 Deer Creek Dr",
    "sg:city":"Struthers",
    "sg:classifiers":[
        {
            "category":"Professional",
            "type":"Services"
        }
    ],
    "sg:phone":"+1 330 755 9591",
    "sg:postcode":"44471",
    "sg:province":"OH",
    "sg:tags":[
        "establishment"
    ],
    "wof:name":"Ecot",
    "wof:placetype":"venue"
},
  "geometry": {"coordinates":[-80.58796599999999,41.037814],"type":"Point"}
}