{
  "type": "Feature",
  "properties": {
    "addr:full":"6826 Hillman Ridge Rd Georgetown OH 45121",
    "addr:housenumber":"6826",
    "addr:postcode":"45121",
    "addr:street":"Hillman Ridge Rd",
    "iso:country":"US",
    "sg:address":"6826 Hillman Ridge Rd",
    "sg:city":"Georgetown",
    "sg:phone":"+1 937 378 6018",
    "sg:postcode":"45121",
    "sg:province":"OH",
    "sg:tags":[
        "farm",
        "tobacco"
    ],
    "wof:name":"Helbling Brothers Farms",
    "wof:placetype":"venue"
},
  "geometry": {"coordinates":[-83.8653,38.822978],"type":"Point"}
}