{
  "type": "Feature",
  "properties": {
    "addr:full":"15104 State Rte 328 Logan OH 43138",
    "addr:housenumber":"15104",
    "addr:postcode":"43138",
    "addr:street":"State Rte 328",
    "iso:country":"US",
    "sg:address":"15104 State Rte 328",
    "sg:city":"Logan",
    "sg:classifiers":[
        {
            "category":"Mining & Drilling",
            "type":"Manufacturing & Wholesale Goods"
        }
    ],
    "sg:phone":"+1 740 385 9637",
    "sg:postcode":"43138",
    "sg:province":"OH",
    "sg:tags":[
        "oil",
        "well"
    ],
    "wof:name":"Paul A Grim Inc",
    "wof:placetype":"venue"
},
  "geometry": {"coordinates":[-82.371993,39.508226],"type":"Point"}
}