{
  "type": "Feature",
  "properties": {
    "addr:full":"2500 E 79th St Cleveland OH 44104",
    "addr:housenumber":"2500",
    "addr:postcode":"44104",
    "addr:street":"E 79Th St",
    "iso:country":"US",
    "sg:address":"2500 E 79th St",
    "sg:city":"Cleveland",
    "sg:classifiers":[
        {
            "category":"Health Services",
            "subcategory":"Clinic",
            "type":"Services"
        }
    ],
    "sg:phone":"+1 216 391 3200",
    "sg:postcode":"44104",
    "sg:province":"OH",
    "sg:tags":[
        "specialty",
        "outpatient"
    ],
    "wof:name":"Metrohlth Clement Ctr-Families",
    "wof:placetype":"venue"
},
  "geometry": {"coordinates":[-81.633421,41.491419],"type":"Point"}
}