{
  "type": "Feature",
  "properties": {
    "addr:full":"4340 S Detroit Ave Toledo OH 43614",
    "addr:housenumber":"4340",
    "addr:postcode":"43614",
    "addr:street":"S Detroit Ave",
    "iso:country":"US",
    "sg:address":"4340 S Detroit Ave",
    "sg:city":"Toledo",
    "sg:classifiers":[
        {
            "category":"Personal",
            "subcategory":"Beauty Salon",
            "type":"Services"
        }
    ],
    "sg:phone":"+1 419 382 3541",
    "sg:postcode":"43614",
    "sg:province":"OH",
    "wof:name":"Shear Design Image Studios",
    "wof:placetype":"venue"
},
  "geometry": {"coordinates":[-83.614811,41.59091],"type":"Point"}
}