{
  "type": "Feature",
  "properties": {
    "addr:full":"2535 State Rte 218 Gallipolis OH 45631",
    "addr:housenumber":"2535",
    "addr:postcode":"45631",
    "addr:street":"State Rte 218",
    "iso:country":"US",
    "sg:address":"2535 State Rte 218",
    "sg:city":"Gallipolis",
    "sg:classifiers":[
        {
            "category":"Building & Trades",
            "subcategory":"Electrical",
            "type":"Services"
        }
    ],
    "sg:phone":"+1 740 446 9950",
    "sg:postcode":"45631",
    "sg:province":"OH",
    "sg:tags":[
        "electrical",
        "electric",
        "contractor"
    ],
    "wof:name":"Welsh Electric Inc",
    "wof:placetype":"venue"
},
  "geometry": {"coordinates":[-82.24176799999999,38.740967],"type":"Point"}
}