{
  "type": "Feature",
  "properties": {
    "iso:country":"US",
    "sg:address":"26235 Broadway Ave",
    "sg:city":"Bedford",
    "sg:classifiers":[
        {
            "category":"Wholesale",
            "subcategory":"Construction Materials",
            "type":"Manufacturing & Wholesale Goods"
        },
        {
            "category":"Home & Garden",
            "subcategory":"Building Materials",
            "type":"Retail Goods"
        }
    ],
    "sg:phone":"+1 440 439 9510",
    "sg:postcode":"44146",
    "sg:province":"OH",
    "sg:tags":[
        "windows",
        "distributor",
        "siding"
    ],
    "wof:name":"Ohio Builder Supply",
    "wof:placetype":"venue"
},
  "geometry": {"coordinates":[-81.49156600000001,41.351782],"type":"Point"}
}