{
  "type": "Feature",
  "properties": {
    "addr:full": "26235 Broadway Ave Bedford OH 44146",
    "addr:housenumber": "26235",
    "addr:postcode": "44146",
    "addr:street": "Broadway Ave",
    "iso:country": "US",
    "sg:address": "26235 Broadway Ave",
    "sg:city": "Bedford",
    "sg:classifiers": [
      {
        "category": "Wholesale",
        "subcategory": "Construction Materials",
        "type": "Manufacturing \u0026 Wholesale Goods"
      },
      {
        "category": "Home \u0026 Garden",
        "subcategory": "Building Materials",
        "type": "Retail Goods"
      }
    ],
    "sg:phone": "+1 440 439 9510",
    "sg:postcode": "44146",
    "sg:province": "OH",
    "sg:tags": [
      "windows",
      "distributor",
      "siding"
    ],
    "wof:name": "Ohio Builder Supply",
    "wof:placetype": "venue"
  },
  "geometry": {"coordinates":[-81.491566,41.351782],"type":"Point"}
}
