{
  "type": "Feature",
  "properties": {
    "addr:full": "1476 N Portage Path Akron OH 44313",
    "addr:housenumber": "1476",
    "addr:postcode": "44313",
    "addr:street": "N Portage Path",
    "iso:country": "US",
    "sg:address": "1476 N Portage Path",
    "sg:city": "Akron",
    "sg:classifiers": [
      {
        "category": "Real Estate",
        "subcategory": "Real Estate Operator",
        "type": "Services"
      },
      {
        "category": "Building \u0026 Trades",
        "subcategory": "Construction",
        "type": "Services"
      }
    ],
    "sg:phone": "+1 330 867 2236",
    "sg:postcode": "44313",
    "sg:province": "OH",
    "sg:tags": [
      "parks",
      "contractor"
    ],
    "wof:name": "Fairlawn Building Co",
    "wof:placetype": "venue"
  },
  "geometry": {"coordinates":[-81.547872,41.135319],"type":"Point"}
}
