{
  "type": "Feature",
  "properties": {
    "iso:country":"US",
    "sg:address":"3386 Soldiers Home Miamisburg Rd",
    "sg:city":"Dayton",
    "sg:classifiers":[
        {
            "category":"Retail",
            "subcategory":"Auto Repair",
            "type":"Services"
        }
    ],
    "sg:phone":"+1 937 268 9167",
    "sg:postcode":"45418",
    "sg:province":"OH",
    "sg:tags":[
        "body",
        "automobile",
        "top",
        "upholstery"
    ],
    "wof:name":"Dewey's Auto Trim",
    "wof:placetype":"venue"
},
  "geometry": {"coordinates":[-84.290663,39.697449],"type":"Point"}
}