{
  "type": "Feature",
  "properties": {
    "iso:country":"US",
    "sg:address":"5001 Monroe St",
    "sg:city":"Toledo",
    "sg:classifiers":[
        {
            "category":"Cinema",
            "subcategory":"Movie Theater",
            "type":"Entertainment"
        }
    ],
    "sg:phone":"+1 419 472 1457",
    "sg:postcode":"43606",
    "sg:province":"OH",
    "wof:name":"610 Franklin Park Cinema",
    "wof:placetype":"venue"
},
  "geometry": {"coordinates":[-83.642016,41.697742],"type":"Point"}
}