{
  "type": "Feature",
  "properties": {
    "addr:full":"577 Newark Ave Thornville OH 43076",
    "addr:housenumber":"577",
    "addr:postcode":"43076",
    "addr:street":"Newark Ave",
    "iso:country":"US",
    "sg:address":"577 Newark Ave",
    "sg:city":"Thornville",
    "sg:classifiers":[
        {
            "category":"Building & Trades",
            "subcategory":"Construction",
            "type":"Services"
        }
    ],
    "sg:phone":"+1 740 928 1886",
    "sg:postcode":"43076",
    "sg:province":"OH",
    "sg:tags":[
        "contractor"
    ],
    "wof:name":"Vandagriff Siding Hm Improving",
    "wof:placetype":"venue"
},
  "geometry": {"coordinates":[-82.434821,39.933293],"type":"Point"}
}