{
  "type": "Feature",
  "properties": {
    "addr:full":"744 Franklin Rd NE Massillon OH 44646",
    "addr:housenumber":"744",
    "addr:postcode":"44646",
    "addr:street":"Franklin Rd Ne",
    "iso:country":"US",
    "sg:address":"744 Franklin Rd NE",
    "sg:city":"Massillon",
    "sg:classifiers":[
        {
            "category":"Shopping",
            "subcategory":"Hobbies, Toys, & Games",
            "type":"Retail Goods"
        }
    ],
    "sg:phone":"+1 330 833 7045",
    "sg:postcode":"44646",
    "sg:province":"OH",
    "sg:tags":[
        "craft"
    ],
    "wof:name":"Crookston's Crafts",
    "wof:placetype":"venue"
},
  "geometry": {"coordinates":[-81.501925,40.803801],"type":"Point"}
}