{
  "type": "Feature",
  "properties": {
    "addr:full":"5400 Transportation Blvd Cleveland OH 44125",
    "addr:postcode":"5400;44125",
    "addr:street":"Transportation Blvd",
    "iso:country":"US",
    "sg:address":"5400 Transportation Blvd",
    "sg:city":"Cleveland",
    "sg:classifiers":[
        {
            "category":"Health Services",
            "subcategory":"Doctor",
            "type":"Services"
        }
    ],
    "sg:phone":"+1 216 662 3373",
    "sg:postcode":"44125",
    "sg:province":"OH",
    "sg:tags":[
        "physician",
        "surgeon",
        "medical"
    ],
    "wof:name":"Cleveland Ear Nose Throat Ctr",
    "wof:placetype":"venue"
},
  "geometry": {"coordinates":[-81.61599,41.41432],"type":"Point"}
}