{
  "type": "Feature",
  "properties": {
    "addr:full":"3900 Fisher Rd Columbus OH 43228",
    "addr:housenumber":"3900",
    "addr:postcode":"43228",
    "addr:street":"Fisher Rd",
    "iso:country":"US",
    "sg:address":"3900 Fisher Rd",
    "sg:city":"Columbus",
    "sg:classifiers":[
        {
            "category":"Real Estate",
            "subcategory":"Real Estate Operator",
            "type":"Services"
        }
    ],
    "sg:phone":"+1 614 351 9681",
    "sg:postcode":"43228",
    "sg:province":"OH",
    "sg:tags":[
        "building",
        "apartment"
    ],
    "wof:name":"Mid State Door Sales",
    "wof:placetype":"venue"
},
  "geometry": {"coordinates":[-83.104742,39.968244],"type":"Point"}
}