{
  "type": "Feature",
  "properties": {
    "addr:full": "517 S Main St Findlay OH 45840",
    "addr:housenumber": "517",
    "addr:postcode": "45840",
    "addr:street": "S Main St",
    "iso:country": "US",
    "sg:address": "517 S Main St",
    "sg:city": "Findlay",
    "sg:classifiers": [
      {
        "category": "Shopping",
        "subcategory": "Discount \u0026 Variety Stores",
        "type": "Retail Goods"
      }
    ],
    "sg:phone": "+1 419 423 8358",
    "sg:postcode": "45840",
    "sg:province": "OH",
    "sg:tags": [
      "merchandise",
      "general"
    ],
    "wof:name": "Vicki D Wisely",
    "wof:placetype": "venue"
  },
  "geometry": {"coordinates":[-83.650197,41.036823],"type":"Point"}
}
