{
  "type": "Feature",
  "properties": {
    "iso:country":"US",
    "sg:address":"517 S Main St",
    "sg:city":"Findlay",
    "sg:classifiers":[
        {
            "category":"Shopping",
            "subcategory":"Discount & Variety Stores",
            "type":"Retail Goods"
        }
    ],
    "sg:phone":"+1 419 423 8358",
    "sg:postcode":"45840",
    "sg:province":"OH",
    "sg:tags":[
        "merchandise",
        "general"
    ],
    "wof:name":"Vicki D Wisely",
    "wof:placetype":"venue"
},
  "geometry": {"coordinates":[-83.65019700000001,41.036823],"type":"Point"}
}