{
  "type": "Feature",
  "properties": {
    "addr:full": "4870 Strand Rd Westerville OH 43081",
    "addr:housenumber": "4870",
    "addr:postcode": "43081",
    "addr:street": "Strand Rd",
    "iso:country": "US",
    "sg:address": "4870 Strand Rd",
    "sg:city": "Westerville",
    "sg:classifiers": [
      {
        "category": "Professional",
        "subcategory": "Computer Services",
        "type": "Services"
      }
    ],
    "sg:phone": "+1 614 478 2868",
    "sg:postcode": "43081",
    "sg:province": "OH",
    "sg:tags": [
      "consultant",
      "designer"
    ],
    "wof:name": "SSIT Consulting",
    "wof:placetype": "venue"
  },
  "geometry": {"coordinates":[-82.865004,40.077963],"type":"Point"}
}
