{
  "type": "Feature",
  "properties": {
    "iso:country":"US",
    "sg:address":"4870 Strand Rd",
    "sg:city":"Westerville",
    "sg:classifiers":[
        {
            "category":"Professional",
            "subcategory":"Computer Services",
            "type":"Services"
        }
    ],
    "sg:phone":"+1 614 478 2868",
    "sg:postcode":"43081",
    "sg:province":"OH",
    "sg:tags":[
        "consultant",
        "designer"
    ],
    "wof:name":"SSIT Consulting",
    "wof:placetype":"venue"
},
  "geometry": {"coordinates":[-82.865004,40.077963],"type":"Point"}
}