{
  "type": "Feature",
  "properties": {
    "addr:full":"210 N Wooster Ave Dover OH 44622",
    "addr:housenumber":"210",
    "addr:postcode":"44622",
    "addr:street":"N Wooster Ave",
    "iso:country":"US",
    "sg:address":"210 N Wooster Ave",
    "sg:city":"Dover",
    "sg:classifiers":[
        {
            "category":"Personal",
            "type":"Services"
        }
    ],
    "sg:phone":"+1 330 343 3900",
    "sg:postcode":"44622",
    "sg:province":"OH",
    "sg:tags":[
        "fitness",
        "physical",
        "facility"
    ],
    "wof:name":"Pumphouse & Electric Beach",
    "wof:placetype":"venue"
},
  "geometry": {"coordinates":[-81.475827,40.521744],"type":"Point"}
}