{
  "type": "Feature",
  "properties": {
    "addr:full": "6821 Salisbury Rd Maumee OH 43537",
    "addr:housenumber": "6821",
    "addr:postcode": "43537",
    "addr:street": "Salisbury Rd",
    "iso:country": "US",
    "sg:address": "6821 Salisbury Rd",
    "sg:city": "Maumee",
    "sg:classifiers": [
      {
        "category": "Real Estate",
        "subcategory": "Architect",
        "type": "Services"
      }
    ],
    "sg:phone": "+1 419 865 8830",
    "sg:postcode": "43537",
    "sg:province": "OH",
    "sg:tags": [
      "interior",
      "engineering",
      "design",
      "architectural"
    ],
    "sg:website": "www.springvalleyarch.com",
    "wof:name": "Spring Valley Architects Inc",
    "wof:placetype": "venue"
  },
  "geometry": {"coordinates":[-83.707155,41.584213],"type":"Point"}
}
