{
  "type": "Feature",
  "properties": {
    "addr:full": "103 Railroad St Oak Hill OH 45656",
    "addr:housenumber": "103",
    "addr:postcode": "45656",
    "addr:street": "Railroad St",
    "iso:country": "US",
    "sg:address": "103 Railroad St",
    "sg:city": "Oak Hill",
    "sg:classifiers": [
      {
        "category": "Restaurant",
        "type": "Food \u0026 Drink"
      }
    ],
    "sg:phone": "+1 740 682 3314",
    "sg:postcode": "45656",
    "sg:province": "OH",
    "wof:name": "Giovanni's Pizza",
    "wof:placetype": "venue"
  },
  "geometry": {"coordinates":[-82.572258,38.896053],"type":"Point"}
}
