{
  "type": "Feature",
  "properties": {
    "iso:country":"US",
    "sg:address":"103 Railroad St",
    "sg:city":"Oak Hill",
    "sg:classifiers":[
        {
            "category":"Restaurant",
            "type":"Food & Drink"
        }
    ],
    "sg:phone":"+1 740 682 3314",
    "sg:postcode":"45656",
    "sg:province":"OH",
    "wof:name":"Giovanni's Pizza",
    "wof:placetype":"venue"
},
  "geometry": {"coordinates":[-82.57225800000001,38.896053],"type":"Point"}
}