{
  "type": "Feature",
  "properties": {
    "iso:country":"US",
    "sg:address":"12577 Co Rd 2",
    "sg:city":"Scottown",
    "sg:classifiers":[
        {
            "category":"Food & Beverages",
            "subcategory":"Groceries & Convenience Stores",
            "type":"Retail Goods"
        }
    ],
    "sg:phone":"+1 740 643 2542",
    "sg:postcode":"45678",
    "sg:province":"OH",
    "wof:name":"R & R Grocery",
    "wof:placetype":"venue"
},
  "geometry": {"coordinates":[-82.411569,38.604727],"type":"Point"}
}