{
  "type": "Feature",
  "properties": {
    "iso:country":"US",
    "sg:address":"13830 McBeth Rd",
    "sg:city":"New Hampshire",
    "sg:classifiers":[
        {
            "category":"Manufacturing",
            "subcategory":"Toys & Sporting Goods",
            "type":"Manufacturing & Wholesale Goods"
        },
        {
            "category":"Manufacturing",
            "subcategory":"Tools & Machinery",
            "type":"Manufacturing & Wholesale Goods"
        }
    ],
    "sg:phone":"+1 419 568 1100",
    "sg:postcode":"45895",
    "sg:province":"OH",
    "sg:tags":[
        "tackle",
        "paint",
        "mfg",
        "system",
        "fishing"
    ],
    "sg:website":"www.bethelengr.com",
    "wof:name":"Bethel Engineering",
    "wof:placetype":"venue"
},
  "geometry": {"coordinates":[-83.95563,40.553446],"type":"Point"}
}