{
  "type": "Feature",
  "properties": {
    "addr:full": "13830 McBeth Rd New Hampshire OH 45895",
    "addr:housenumber": "13830",
    "addr:postcode": "45895",
    "addr:street": "Mcbeth Rd",
    "iso:country": "US",
    "sg:address": "13830 McBeth Rd",
    "sg:city": "New Hampshire",
    "sg:classifiers": [
      {
        "category": "Manufacturing",
        "subcategory": "Toys \u0026 Sporting Goods",
        "type": "Manufacturing \u0026 Wholesale Goods"
      },
      {
        "category": "Manufacturing",
        "subcategory": "Tools \u0026 Machinery",
        "type": "Manufacturing \u0026 Wholesale Goods"
      }
    ],
    "sg:phone": "+1 419 568 1100",
    "sg:postcode": "45895",
    "sg:province": "OH",
    "sg:tags": [
      "tackle",
      "paint",
      "mfg",
      "system",
      "fishing"
    ],
    "sg:website": "www.bethelengr.com",
    "wof:name": "Bethel Engineering",
    "wof:placetype": "venue"
  },
  "geometry": {"coordinates":[-83.95563,40.553446],"type":"Point"}
}
