{
  "type": "Feature",
  "properties": {
    "iso:country":"US",
    "sg:address":"21 E State St",
    "sg:city":"Columbus",
    "sg:classifiers":[
        {
            "category":"Banks & Credit Unions",
            "subcategory":"Investment Brokerage",
            "type":"Services"
        }
    ],
    "sg:phone":"+1 614 621 6212",
    "sg:postcode":"43215",
    "sg:province":"OH",
    "sg:tags":[
        "advisory",
        "financial"
    ],
    "wof:name":"Investment Advisors Inc",
    "wof:placetype":"venue"
},
  "geometry": {"coordinates":[-82.999859,39.9601],"type":"Point"}
}