{
  "type": "Feature",
  "properties": {
    "addr:full":"1204 Salem Ave Dayton OH 45406",
    "addr:housenumber":"1204",
    "addr:postcode":"45406",
    "addr:street":"Salem Ave",
    "iso:country":"US",
    "sg:address":"1204 Salem Ave",
    "sg:city":"Dayton",
    "sg:classifiers":[
        {
            "category":"Social Services",
            "subcategory":"Adult Care",
            "type":"Services"
        }
    ],
    "sg:phone":"+1 937 277 3855",
    "sg:postcode":"45406",
    "sg:province":"OH",
    "sg:tags":[
        "home",
        "group"
    ],
    "wof:name":"Valetta Gaston Heights & Assoc",
    "wof:placetype":"venue"
},
  "geometry": {"coordinates":[-84.217493,39.77557],"type":"Point"}
}