{
  "type": "Feature",
  "properties": {
    "addr:full": "7355 Piqua-Clayton Rd Covington OH 45318",
    "addr:housenumber": "7355",
    "addr:postcode": "45318",
    "addr:street": "Piqua-Clayton Rd",
    "iso:country": "US",
    "sg:address": "7355 Piqua-Clayton Rd",
    "sg:city": "Covington",
    "sg:classifiers": [
      {
        "category": "Building \u0026 Trades",
        "subcategory": "Landscaping Services",
        "type": "Services"
      }
    ],
    "sg:phone": "+1 937 473 3968",
    "sg:postcode": "45318",
    "sg:province": "OH",
    "wof:name": "R \u0026 M Lawns",
    "wof:placetype": "venue"
  },
  "geometry": {"coordinates":[-84.345232,40.147146],"type":"Point"}
}
