{
  "type": "Feature",
  "properties": {
    "iso:country":"US",
    "sg:address":"7355 Piqua-Clayton Rd",
    "sg:city":"Covington",
    "sg:classifiers":[
        {
            "category":"Building & Trades",
            "subcategory":"Landscaping Services",
            "type":"Services"
        }
    ],
    "sg:phone":"+1 937 473 3968",
    "sg:postcode":"45318",
    "sg:province":"OH",
    "wof:name":"R & M Lawns",
    "wof:placetype":"venue"
},
  "geometry": {"coordinates":[-84.345232,40.147146],"type":"Point"}
}