{
  "type": "Feature",
  "properties": {
    "iso:country":"US",
    "sg:address":"116 Sibley St",
    "sg:city":"Van Wert",
    "sg:classifiers":[
        {
            "category":"Home & Garden",
            "subcategory":"Building Materials",
            "type":"Retail Goods"
        }
    ],
    "sg:phone":"+1 419 238 1139",
    "sg:postcode":"45891",
    "sg:province":"OH",
    "sg:tags":[
        "glass",
        "window",
        "plate"
    ],
    "wof:name":"Van WERT Glass Co",
    "wof:placetype":"venue"
},
  "geometry": {"coordinates":[-84.595446,40.872399],"type":"Point"}
}