{
  "type": "Feature",
  "properties": {
    "addr:full": "2727 Winchester Pike Columbus OH 43232",
    "addr:housenumber": "2727",
    "addr:postcode": "43232",
    "addr:street": "Winchester Pike",
    "iso:country": "US",
    "sg:address": "2727 Winchester Pike",
    "sg:city": "Columbus",
    "sg:classifiers": [
      {
        "category": "Professional",
        "subcategory": "Computer Services",
        "type": "Services"
      }
    ],
    "sg:phone": "+1 614 338 1111",
    "sg:postcode": "43232",
    "sg:province": "OH",
    "sg:tags": [
      "repair"
    ],
    "wof:name": "U Do Personal Computer Repair",
    "wof:placetype": "venue"
  },
  "geometry": {"coordinates":[-82.912732,39.914933],"type":"Point"}
}
