{
  "type": "Feature",
  "properties": {
    "addr:full":"1440 Snow Rd Cleveland OH 44134",
    "addr:housenumber":"1440",
    "addr:postcode":"44134",
    "addr:street":"Snow Rd",
    "iso:country":"US",
    "sg:address":"1440 Snow Rd",
    "sg:city":"Cleveland",
    "sg:classifiers":[
        {
            "category":"Health Services",
            "subcategory":"Hospital",
            "type":"Services"
        }
    ],
    "sg:phone":"+1 216 741 3455",
    "sg:postcode":"44134",
    "sg:province":"OH",
    "sg:tags":[
        "mental"
    ],
    "wof:name":"Sora Vigorito Inc",
    "wof:placetype":"venue"
},
  "geometry": {"coordinates":[-81.69060399999999,41.405327],"type":"Point"}
}