{
  "type": "Feature",
  "properties": {
    "addr:full":"1501 S Hawkins Ave Akron OH 44320",
    "addr:housenumber":"1501",
    "addr:postcode":"44320",
    "addr:street":"S Hawkins Ave",
    "iso:country":"US",
    "sg:address":"1501 S Hawkins Ave",
    "sg:city":"Akron",
    "sg:classifiers":[
        {
            "category":"Health Services",
            "subcategory":"Hospital",
            "type":"Services"
        }
    ],
    "sg:phone":"+1 330 867 5711",
    "sg:postcode":"44320",
    "sg:province":"OH",
    "sg:tags":[
        "specialty"
    ],
    "wof:name":"Exodus Program",
    "wof:placetype":"venue"
},
  "geometry": {"coordinates":[-81.569715,41.064862],"type":"Point"}
}