{
  "type": "Feature",
  "properties": {
    "addr:full":"19501 Emery Rd Cleveland OH 44128",
    "addr:housenumber":"19501",
    "addr:postcode":"44128",
    "addr:street":"Emery Rd",
    "iso:country":"US",
    "sg:address":"19501 Emery Rd",
    "sg:city":"Cleveland",
    "sg:classifiers":[
        {
            "category":"Manufacturing",
            "subcategory":"Motor Vehicles & Parts",
            "type":"Manufacturing & Wholesale Goods"
        }
    ],
    "sg:phone":"+1 216 332 7100",
    "sg:postcode":"44128",
    "sg:province":"OH",
    "sg:tags":[
        "body",
        "automobile"
    ],
    "wof:name":"Trw Automotive Us LLC",
    "wof:placetype":"venue"
},
  "geometry": {"coordinates":[-81.542202,41.433667],"type":"Point"}
}