{
  "type": "Feature",
  "properties": {
    "iso:country":"US",
    "sg:address":"12470 US Hwy 50",
    "sg:city":"Hillsboro",
    "sg:classifiers":[
        {
            "category":"Government",
            "subcategory":"Office",
            "type":"Public Place"
        }
    ],
    "sg:phone":"+1 937 365 1494",
    "sg:postcode":"45133",
    "sg:province":"OH",
    "sg:tags":[
        "executive"
    ],
    "wof:name":"Paint Township Board Trustees",
    "wof:placetype":"venue"
},
  "geometry": {"coordinates":[-83.43871799999999,39.217698],"type":"Point"}
}