{
  "type": "Feature",
  "properties": {
    "addr:full":"9853 Young Rd Defiance OH 43512",
    "addr:housenumber":"9853",
    "addr:postcode":"43512",
    "addr:street":"Young Rd",
    "iso:country":"US",
    "sg:address":"9853 Young Rd",
    "sg:city":"Defiance",
    "sg:classifiers":[
        {
            "category":"Farming",
            "subcategory":"Livestock Farm",
            "type":"Manufacturing & Wholesale Goods"
        }
    ],
    "sg:phone":"+1 419 784 3277",
    "sg:postcode":"43512",
    "sg:province":"OH",
    "wof:name":"Ray Clevenger",
    "wof:placetype":"venue"
},
  "geometry": {"coordinates":[-84.275013,41.299215],"type":"Point"}
}