{
  "type": "Feature",
  "properties": {
    "addr:full":"7600 Auburn Rd Painesville OH 44077",
    "addr:housenumber":"7600",
    "addr:postcode":"44077",
    "addr:street":"Auburn Rd",
    "iso:country":"US",
    "sg:address":"7600 Auburn Rd",
    "sg:city":"Painesville",
    "sg:classifiers":[
        {
            "category":"Shopping",
            "subcategory":"Computers & Home Electronics",
            "type":"Retail Goods"
        }
    ],
    "sg:phone":"+1 440 358 4675",
    "sg:postcode":"44077",
    "sg:province":"OH",
    "sg:tags":[
        "printer"
    ],
    "wof:name":"Novexx Company",
    "wof:placetype":"venue"
},
  "geometry": {"coordinates":[-81.24574200000001,41.665713],"type":"Point"}
}