{
  "type": "Feature",
  "properties": {
    "iso:country":"US",
    "sg:address":"1303 W 117th St",
    "sg:city":"Cleveland",
    "sg:classifiers":[
        {
            "category":"Retail",
            "subcategory":"Auto Repair",
            "type":"Services"
        }
    ],
    "sg:phone":"+1 216 228 5150",
    "sg:postcode":"44107",
    "sg:province":"OH",
    "sg:tags":[
        "body",
        "automobile",
        "painting"
    ],
    "wof:name":"Ferrari Auto Body",
    "wof:placetype":"venue"
},
  "geometry": {"coordinates":[-81.768665,41.485611],"type":"Point"}
}