{
  "type": "Feature",
  "properties": {
    "addr:full": "3132 Olentangy River Rd Columbus OH 43202",
    "addr:housenumber": "3132",
    "addr:postcode": "43202",
    "addr:street": "Olentangy River Rd",
    "iso:country": "US",
    "sg:address": "3132 Olentangy River Rd",
    "sg:city": "Columbus",
    "sg:classifiers": [
      {
        "category": "Health Services",
        "subcategory": "Doctor",
        "type": "Services"
      }
    ],
    "sg:phone": "+1 614 784 8522",
    "sg:postcode": "43202",
    "sg:province": "OH",
    "sg:tags": [
      "medical",
      "imaging"
    ],
    "wof:name": "Capital Imaging",
    "wof:placetype": "venue"
  },
  "geometry": {"coordinates":[-83.02891,40.028406],"type":"Point"}
}
