{
  "type": "Feature",
  "properties": {
    "addr:full": "309 W Main St Lucas OH 44843",
    "addr:housenumber": "309",
    "addr:postcode": "44843",
    "addr:street": "W Main St",
    "iso:country": "US",
    "sg:address": "309 W Main St",
    "sg:city": "Lucas",
    "sg:classifiers": [
      {
        "category": "Restaurant",
        "type": "Food \u0026 Drink"
      }
    ],
    "sg:phone": "+1 419 892 3583",
    "sg:postcode": "44843",
    "sg:province": "OH",
    "sg:tags": [
      "caterer"
    ],
    "wof:name": "Port-A-Cook-Inc",
    "wof:placetype": "venue"
  },
  "geometry": {"coordinates":[-82.428056,40.704852],"type":"Point"}
}
