{
  "type": "Feature",
  "properties": {
    "addr:full": "20508 Watson Rd Cleveland OH 44137",
    "addr:housenumber": "20508",
    "addr:postcode": "44137",
    "addr:street": "Watson Rd",
    "iso:country": "US",
    "sg:address": "20508 Watson Rd",
    "sg:city": "Cleveland",
    "sg:classifiers": [
      {
        "category": "Professional",
        "subcategory": "Computer Services",
        "type": "Services"
      }
    ],
    "sg:phone": "+1 216 663 2352",
    "sg:postcode": "44137",
    "sg:province": "OH",
    "sg:tags": [
      "develops",
      "design",
      "developer"
    ],
    "wof:name": "Computer Associates Intl Inc",
    "wof:placetype": "venue"
  },
  "geometry": {"coordinates":[-81.535177,41.422594],"type":"Point"}
}
