{
  "type": "Feature",
  "properties": {
    "addr:full":"62913 Wintergreen Rd Lore City OH 43755",
    "addr:housenumber":"62913",
    "addr:postcode":"43755",
    "addr:street":"Wintergreen Rd",
    "iso:country":"US",
    "sg:address":"62913 Wintergreen Rd",
    "sg:city":"Lore City",
    "sg:classifiers":[
        {
            "category":"Retail",
            "subcategory":"Repair Shop",
            "type":"Services"
        }
    ],
    "sg:phone":"+1 740 489 5157",
    "sg:postcode":"43755",
    "sg:province":"OH",
    "sg:tags":[
        "industrial",
        "machinery",
        "welding",
        "mfg"
    ],
    "wof:name":"M & R Machine Shop",
    "wof:placetype":"venue"
},
  "geometry": {"coordinates":[-81.4581,40.016549],"type":"Point"}
}