{
  "type": "Feature",
  "properties": {
    "iso:country":"US",
    "sg:address":"3716 Refugee Rd",
    "sg:city":"Columbus",
    "sg:classifiers":[
        {
            "category":"Cinema",
            "subcategory":"Movie Rental",
            "type":"Entertainment"
        }
    ],
    "sg:phone":"+1 614 231 2939",
    "sg:postcode":"43232",
    "sg:province":"OH",
    "sg:tags":[
        "video",
        "tape"
    ],
    "wof:name":"Rent A Flick",
    "wof:placetype":"venue"
},
  "geometry": {"coordinates":[-82.894193,39.916374],"type":"Point"}
}