{
  "type": "Feature",
  "properties": {
    "iso:country":"US",
    "sg:address":"3826 Round Bottom Rd",
    "sg:city":"Cincinnati",
    "sg:classifiers":[
        {
            "category":"Building & Trades",
            "subcategory":"Construction",
            "type":"Services"
        }
    ],
    "sg:phone":"+1 513 561 3324",
    "sg:postcode":"45244",
    "sg:province":"OH",
    "sg:tags":[
        "general",
        "contractor"
    ],
    "wof:name":"Patriot Industrial Cntrctng",
    "wof:placetype":"venue"
},
  "geometry": {"coordinates":[-84.341201,39.131654],"type":"Point"}
}