{
  "type": "Feature",
  "properties": {
    "addr:full": "6944 Co Rd M Grelton OH 43535",
    "addr:housenumber": "6944",
    "addr:postcode": "43535",
    "addr:street": "Co Rd M Grelton",
    "iso:country": "US",
    "sg:address": "6944 Co Rd M",
    "sg:city": "Grelton",
    "sg:classifiers": [
      {
        "category": "Wholesale",
        "subcategory": "Farm Supplies",
        "type": "Manufacturing \u0026 Wholesale Goods"
      }
    ],
    "sg:phone": "+1 419 256 6381",
    "sg:postcode": "43535",
    "sg:province": "OH",
    "sg:tags": [
      "fertilizer"
    ],
    "wof:name": "Grelton Elevator Inc",
    "wof:placetype": "venue"
  },
  "geometry": {"coordinates":[-83.9981,41.341913],"type":"Point"}
}
