{
  "type": "Feature",
  "properties": {
    "addr:full":"4445 N Monastery Rd NW Mc Connelsville OH 43756",
    "addr:housenumber":"4445",
    "addr:postcode":"43756",
    "addr:street":"N Monastery Rd Nw",
    "iso:country":"US",
    "sg:address":"4445 N Monastery Rd NW",
    "sg:city":"Mc Connelsville",
    "sg:classifiers":[
        {
            "category":"Utilities",
            "subcategory":"Water",
            "type":"Services"
        }
    ],
    "sg:phone":"+1 740 962 6395",
    "sg:postcode":"43756",
    "sg:province":"OH",
    "sg:tags":[
        "company",
        "sewage"
    ],
    "wof:name":"Morgan Meigsville Water Dist",
    "wof:placetype":"venue"
},
  "geometry": {"coordinates":[-81.834496,39.672033],"type":"Point"}
}