{
  "type": "Feature",
  "properties": {
    "iso:country":"US",
    "sg:address":"3657 Trabue Rd",
    "sg:city":"Columbus",
    "sg:classifiers":[
        {
            "category":"Wholesale",
            "subcategory":"Home Furnishings",
            "type":"Manufacturing & Wholesale Goods"
        }
    ],
    "sg:phone":"+1 614 481 6960",
    "sg:postcode":"43228",
    "sg:province":"OH",
    "sg:tags":[
        "curtain",
        "drapery"
    ],
    "wof:name":"Tim Perini's",
    "wof:placetype":"venue"
},
  "geometry": {"coordinates":[-83.097225,39.991143],"type":"Point"}
}