{
  "type": "Feature",
  "properties": {
    "addr:full": "2951 E Lytle-Five Points Rd Waynesville OH 45068",
    "addr:housenumber": "2951",
    "addr:postcode": "45068",
    "addr:street": "E Lytle-Five Points Rd",
    "iso:country": "US",
    "sg:address": "2951 E Lytle-Five Points Rd",
    "sg:city": "Waynesville",
    "sg:classifiers": [
      {
        "category": "Home \u0026 Garden",
        "subcategory": "Garden Supply",
        "type": "Retail Goods"
      }
    ],
    "sg:phone": "+1 513 897 3552",
    "sg:postcode": "45068",
    "sg:province": "OH",
    "sg:tags": [
      "mulch"
    ],
    "wof:name": "Debi's Mulch",
    "wof:placetype": "venue"
  },
  "geometry": {"coordinates":[-84.135257,39.564015],"type":"Point"}
}
