{
  "type": "Feature",
  "properties": {
    "iso:country":"US",
    "sg:address":"2951 E Lytle-Five Points Rd",
    "sg:city":"Waynesville",
    "sg:classifiers":[
        {
            "category":"Home & Garden",
            "subcategory":"Garden Supply",
            "type":"Retail Goods"
        }
    ],
    "sg:phone":"+1 513 897 3552",
    "sg:postcode":"45068",
    "sg:province":"OH",
    "sg:tags":[
        "mulch"
    ],
    "wof:name":"Debi's Mulch",
    "wof:placetype":"venue"
},
  "geometry": {"coordinates":[-84.135257,39.564015],"type":"Point"}
}