{
  "type": "Feature",
  "properties": {
    "addr:full":"109 Pearl St New Paris OH 45347",
    "addr:housenumber":"109",
    "addr:postcode":"45347",
    "addr:street":"Pearl St",
    "iso:country":"US",
    "sg:address":"109 Pearl St",
    "sg:city":"New Paris",
    "sg:classifiers":[
        {
            "category":"Freight",
            "type":"Transportation"
        }
    ],
    "sg:phone":"+1 937 437 0823",
    "sg:postcode":"45347",
    "sg:province":"OH",
    "sg:tags":[
        "trucking"
    ],
    "wof:name":"Josh Truck Lines",
    "wof:placetype":"venue"
},
  "geometry": {"coordinates":[-84.792609,39.855541],"type":"Point"}
}