{
  "type": "Feature",
  "properties": {
    "addr:full":"615 W Washington St Nelsonville OH 45764",
    "addr:housenumber":"615",
    "addr:postcode":"45764",
    "addr:street":"W Washington St",
    "iso:country":"US",
    "sg:address":"615 W Washington St",
    "sg:city":"Nelsonville",
    "sg:classifiers":[
        {
            "category":"Restaurant",
            "type":"Food & Drink"
        }
    ],
    "sg:phone":"+1 740 753 3336",
    "sg:postcode":"45764",
    "sg:province":"OH",
    "sg:tags":[
        "banquet",
        "rooms"
    ],
    "wof:name":"Coffee Cup Restaurant",
    "wof:placetype":"venue"
},
  "geometry": {"coordinates":[-82.24637199999999,39.462911],"type":"Point"}
}