{
  "type": "Feature",
  "properties": {
    "iso:country":"US",
    "sg:address":"13645 Spargur Ln",
    "sg:city":"Hillsboro",
    "sg:classifiers":[
        {
            "category":"Food & Beverages",
            "subcategory":"Groceries & Convenience Stores",
            "type":"Retail Goods"
        }
    ],
    "sg:phone":"+1 937 466 2898",
    "sg:postcode":"45133",
    "sg:province":"OH",
    "sg:tags":[
        "grocer"
    ],
    "wof:name":"Family Market",
    "wof:placetype":"venue"
},
  "geometry": {"coordinates":[-83.40428,39.18537],"type":"Point"}
}