{
  "type": "Feature",
  "properties": {
    "iso:country":"US",
    "sg:address":"17944 Framingham Oval",
    "sg:city":"Cleveland",
    "sg:classifiers":[
        {
            "category":"Recreation",
            "type":"Entertainment"
        }
    ],
    "sg:phone":"+1 440 238 8340",
    "sg:postcode":"44136",
    "sg:province":"OH",
    "sg:tags":[
        "instruction",
        "golf"
    ],
    "wof:name":"Golf Inside & Out",
    "wof:placetype":"venue"
},
  "geometry": {"coordinates":[-81.827304,41.288249],"type":"Point"}
}