{
  "type": "Feature",
  "properties": {
    "addr:full": "5010 Mayfield Rd Cleveland OH 44124",
    "addr:housenumber": "5010",
    "addr:postcode": "44124",
    "addr:street": "Mayfield Rd",
    "iso:country": "US",
    "sg:address": "5010 Mayfield Rd",
    "sg:city": "Cleveland",
    "sg:classifiers": [
      {
        "category": "Real Estate",
        "subcategory": "Real Estate Agent",
        "type": "Services"
      }
    ],
    "sg:phone": "+1 216 381 2728",
    "sg:postcode": "44124",
    "sg:province": "OH",
    "sg:tags": [
      "management"
    ],
    "wof:name": "United Management Co",
    "wof:placetype": "venue"
  },
  "geometry": {"coordinates":[-81.497998,41.519763],"type":"Point"}
}
