{
  "type": "Feature",
  "properties": {
    "addr:full": "2500 Grand Ave Middletown OH 45044",
    "addr:housenumber": "2500",
    "addr:postcode": "45044",
    "addr:street": "Grand Ave",
    "iso:country": "US",
    "sg:address": "2500 Grand Ave",
    "sg:city": "Middletown",
    "sg:classifiers": [
      {
        "category": "Organizations",
        "subcategory": "Religious Organization",
        "type": "Services"
      }
    ],
    "sg:phone": "+1 513 422 2312",
    "sg:postcode": "45044",
    "sg:province": "OH",
    "sg:tags": [
      "church"
    ],
    "wof:name": "Sts Constantine \u0026 Helen Greek",
    "wof:placetype": "venue"
  },
  "geometry": {"coordinates":[-84.381441,39.504799],"type":"Point"}
}
