{
  "type": "Feature",
  "properties": {
    "addr:full": "208 Defiance St Wapakoneta OH 45895",
    "addr:housenumber": "208",
    "addr:postcode": "45895",
    "addr:street": "Defiance St",
    "iso:country": "US",
    "sg:address": "208 Defiance St",
    "sg:city": "Wapakoneta",
    "sg:classifiers": [
      {
        "category": "Food \u0026 Beverages",
        "subcategory": "Liquor \u0026 Beverages",
        "type": "Retail Goods"
      }
    ],
    "sg:phone": "+1 419 738 4618",
    "sg:postcode": "45895",
    "sg:province": "OH",
    "sg:tags": [
      "beer",
      "ale"
    ],
    "wof:name": "LA Grande Zip Stop",
    "wof:placetype": "venue"
  },
  "geometry": {"coordinates":[-84.196727,40.572632],"type":"Point"}
}
