{
  "type": "Feature",
  "properties": {
    "iso:country":"US",
    "sg:address":"208 Defiance St",
    "sg:city":"Wapakoneta",
    "sg:classifiers":[
        {
            "category":"Food & Beverages",
            "subcategory":"Liquor & Beverages",
            "type":"Retail Goods"
        }
    ],
    "sg:phone":"+1 419 738 4618",
    "sg:postcode":"45895",
    "sg:province":"OH",
    "sg:tags":[
        "beer",
        "ale"
    ],
    "wof:name":"LA Grande Zip Stop",
    "wof:placetype":"venue"
},
  "geometry": {"coordinates":[-84.196727,40.572632],"type":"Point"}
}