{
  "type": "Feature",
  "properties": {
    "addr:full":"30100 Chagrin Blvd Cleveland OH 44124",
    "addr:postcode":"30100;44124",
    "addr:street":"Chagrin Blvd",
    "iso:country":"US",
    "sg:address":"30100 Chagrin Blvd",
    "sg:city":"Cleveland",
    "sg:classifiers":[
        {
            "category":"Professional",
            "subcategory":"Lawyer & Legal Services",
            "type":"Services"
        }
    ],
    "sg:phone":"+1 216 514 3283",
    "sg:postcode":"44124",
    "sg:province":"OH",
    "wof:name":"Phillips David G",
    "wof:placetype":"venue"
},
  "geometry": {"coordinates":[-81.46520200000001,41.5116],"type":"Point"}
}