{
  "type": "Feature",
  "properties": {
    "addr:full": "3600 Park 42 Dr Cincinnati OH 45241",
    "addr:housenumber": "3600;42",
    "addr:postcode": "45241",
    "addr:street": "Park;Dr",
    "iso:country": "US",
    "sg:address": "3600 Park 42 Dr",
    "sg:city": "Cincinnati",
    "sg:classifiers": [
      {
        "category": "Wholesale",
        "subcategory": "Computers",
        "type": "Manufacturing \u0026 Wholesale Goods"
      },
      {
        "category": "Shopping",
        "subcategory": "Computers \u0026 Home Electronics",
        "type": "Retail Goods"
      }
    ],
    "sg:phone": "+1 513 745 2700",
    "sg:postcode": "45241",
    "sg:province": "OH",
    "sg:tags": [
      "reseller",
      "software"
    ],
    "sg:website": "www.microsolid.com",
    "wof:name": "3dvision Technologies",
    "wof:placetype": "venue"
  },
  "geometry": {"coordinates":[-84.406061,39.281495],"type":"Point"}
}
