{
  "type": "Feature",
  "properties": {
    "iso:country":"US",
    "sg:address":"3600 Park 42 Dr",
    "sg:city":"Cincinnati",
    "sg:classifiers":[
        {
            "category":"Wholesale",
            "subcategory":"Computers",
            "type":"Manufacturing & Wholesale Goods"
        },
        {
            "category":"Shopping",
            "subcategory":"Computers & Home Electronics",
            "type":"Retail Goods"
        }
    ],
    "sg:phone":"+1 513 745 2700",
    "sg:postcode":"45241",
    "sg:province":"OH",
    "sg:tags":[
        "reseller",
        "software"
    ],
    "sg:website":"www.microsolid.com",
    "wof:name":"3dvision Technologies",
    "wof:placetype":"venue"
},
  "geometry": {"coordinates":[-84.40606099999999,39.281495],"type":"Point"}
}