{
  "type": "Feature",
  "properties": {
    "addr:full": "6519 Freeport Dr Dayton OH 45415",
    "addr:housenumber": "6519",
    "addr:postcode": "45415",
    "addr:street": "Freeport Dr",
    "iso:country": "US",
    "sg:address": "6519 Freeport Dr",
    "sg:city": "Dayton",
    "sg:classifiers": [
      {
        "category": "Building \u0026 Trades",
        "subcategory": "Construction",
        "type": "Services"
      }
    ],
    "sg:phone": "+1 937 454 1803",
    "sg:postcode": "45415",
    "sg:province": "OH",
    "sg:tags": [
      "house"
    ],
    "wof:name": "B\u0026F Homes LLC",
    "wof:placetype": "venue"
  },
  "geometry": {"coordinates":[-84.282132,39.839122],"type":"Point"}
}
