{
  "type": "Feature",
  "properties": {
    "iso:country":"US",
    "sg:address":"6519 Freeport Dr",
    "sg:city":"Dayton",
    "sg:classifiers":[
        {
            "category":"Building & Trades",
            "subcategory":"Construction",
            "type":"Services"
        }
    ],
    "sg:phone":"+1 937 454 1803",
    "sg:postcode":"45415",
    "sg:province":"OH",
    "sg:tags":[
        "house"
    ],
    "wof:name":"B&F Homes LLC",
    "wof:placetype":"venue"
},
  "geometry": {"coordinates":[-84.282132,39.839122],"type":"Point"}
}