{
  "type": "Feature",
  "properties": {
    "addr:full":"8801 Colerain Ave Cincinnati OH 45251",
    "addr:housenumber":"8801",
    "addr:postcode":"45251",
    "addr:street":"Colerain Ave",
    "iso:country":"US",
    "sg:address":"8801 Colerain Ave",
    "sg:city":"Cincinnati",
    "sg:classifiers":[
        {
            "category":"Restaurant",
            "type":"Food & Drink"
        }
    ],
    "sg:menulink":"http://www.allmenus.com/oh/colerain/64419-chuck-e-cheeses/menu/",
    "sg:phone":"+1 513 385 1438",
    "sg:postcode":"45251",
    "sg:province":"OH",
    "sg:tags":[
        "american",
        "pizza"
    ],
    "wof:name":"Chuck E. Cheese's",
    "wof:placetype":"venue"
},
  "geometry": {"coordinates":[-84.59125899999999,39.231271],"type":"Point"}
}