{
  "type": "Feature",
  "properties": {
    "addr:full":"1300 W 9th St Cleveland OH 44113",
    "addr:housenumber":"1300",
    "addr:postcode":"44113",
    "addr:street":"W 9Th St",
    "iso:country":"US",
    "sg:address":"1300 W 9th St",
    "sg:city":"Cleveland",
    "sg:classifiers":[
        {
            "category":"Personal",
            "subcategory":"Beauty Salon",
            "type":"Services"
        }
    ],
    "sg:phone":"+1 216 685 1400",
    "sg:postcode":"44113",
    "sg:province":"OH",
    "wof:name":"Salon Mandalfino",
    "wof:placetype":"venue"
},
  "geometry": {"coordinates":[-81.70031,41.498741],"type":"Point"}
}