{
  "type": "Feature",
  "properties": {
    "addr:full": "106 S Hill St Brookville OH 45309",
    "addr:housenumber": "106",
    "addr:postcode": "45309",
    "addr:street": "S Hill St",
    "iso:country": "US",
    "sg:address": "106 S Hill St",
    "sg:city": "Brookville",
    "sg:classifiers": [
      {
        "category": "Restaurant",
        "type": "Food \u0026 Drink"
      }
    ],
    "sg:phone": "+1 937 833 6761",
    "sg:postcode": "45309",
    "sg:province": "OH",
    "sg:tags": [
      "high",
      "school",
      "public"
    ],
    "wof:name": "Brookville High School",
    "wof:placetype": "venue"
  },
  "geometry": {"coordinates":[-84.413384,39.831535],"type":"Point"}
}
