{
  "type": "Feature",
  "properties": {
    "addr:full":"351 N Broad St Fairborn OH 45324",
    "addr:housenumber":"351",
    "addr:postcode":"45324",
    "addr:street":"N Broad St",
    "iso:country":"US",
    "sg:address":"351 N Broad St",
    "sg:city":"Fairborn",
    "sg:classifiers":[
        {
            "category":"Building & Trades",
            "subcategory":"Plumbing",
            "type":"Services"
        }
    ],
    "sg:phone":"+1 937 879 2775",
    "sg:postcode":"45324",
    "sg:province":"OH",
    "sg:tags":[
        "contractor"
    ],
    "wof:name":"Deer Heating",
    "wof:placetype":"venue"
},
  "geometry": {"coordinates":[-84.02537599999999,39.828517],"type":"Point"}
}