{
  "type": "Feature",
  "properties": {
    "iso:country":"US",
    "sg:address":"325 Front St",
    "sg:city":"Green Springs",
    "sg:classifiers":[
        {
            "category":"Government",
            "subcategory":"Fire Station",
            "type":"Public Place"
        }
    ],
    "sg:phone":"+1 419 000 1111",
    "sg:postcode":"44890",
    "sg:province":"OH",
    "sg:tags":[
        "department"
    ],
    "wof:name":"Cygnet Village Fire Dept",
    "wof:placetype":"venue"
},
  "geometry": {"coordinates":[-82.728514,41.062401],"type":"Point"}
}