{
  "type": "Feature",
  "properties": {
    "addr:full": "15404 Co Rd Y New Bavaria OH 43548",
    "addr:housenumber": "15404",
    "addr:postcode": "43548",
    "addr:street": "Co Rd Y New",
    "iso:country": "US",
    "sg:address": "15404 Co Rd Y",
    "sg:city": "New Bavaria",
    "sg:phone": "+1 419 653 4209",
    "sg:postcode": "43548",
    "sg:province": "OH",
    "sg:tags": [
      "farm",
      "wheat",
      "soybean"
    ],
    "wof:name": "James Thomas",
    "wof:placetype": "venue"
  },
  "geometry": {"coordinates":[-84.156632,41.198087],"type":"Point"}
}
