{
  "type": "Feature",
  "properties": {
    "iso:country":"US",
    "sg:address":"20133 Van Aken Blvd",
    "sg:city":"Cleveland",
    "sg:classifiers":[
        {
            "category":"Health Services",
            "subcategory":"Optometrist",
            "type":"Services"
        }
    ],
    "sg:phone":"+1 216 921 4231",
    "sg:postcode":"44122",
    "sg:province":"OH",
    "wof:name":"Ohio Optometric Consultants",
    "wof:placetype":"venue"
},
  "geometry": {"coordinates":[-81.537801,41.46637],"type":"Point"}
}