{
  "type": "Feature",
  "properties": {
    "addr:full": "19142 Detroit Rd Cleveland OH 44116",
    "addr:housenumber": "19142",
    "addr:postcode": "44116",
    "addr:street": "Detroit Rd",
    "iso:country": "US",
    "sg:address": "19142 Detroit Rd",
    "sg:city": "Cleveland",
    "sg:classifiers": [
      {
        "category": "Retail",
        "subcategory": "Repair Shop",
        "type": "Services"
      }
    ],
    "sg:phone": "+1 440 356 2880",
    "sg:postcode": "44116",
    "sg:province": "OH",
    "sg:tags": [
      "clocks",
      "merchandise",
      "parts",
      "used"
    ],
    "wof:name": "Clock Shop",
    "wof:placetype": "venue"
  },
  "geometry": {"coordinates":[-81.833857,41.483186],"type":"Point"}
}
