{
  "type": "Feature",
  "properties": {
    "iso:country":"US",
    "sg:address":"19142 Detroit Rd",
    "sg:city":"Cleveland",
    "sg:classifiers":[
        {
            "category":"Retail",
            "subcategory":"Repair Shop",
            "type":"Services"
        }
    ],
    "sg:phone":"+1 440 356 2880",
    "sg:postcode":"44116",
    "sg:province":"OH",
    "sg:tags":[
        "clocks",
        "merchandise",
        "parts",
        "used"
    ],
    "wof:name":"Clock Shop",
    "wof:placetype":"venue"
},
  "geometry": {"coordinates":[-81.83385699999999,41.483186],"type":"Point"}
}