{
  "type": "Feature",
  "properties": {
    "addr:full": "450 Fairground Blvd Canfield OH 44406",
    "addr:housenumber": "450",
    "addr:postcode": "44406",
    "addr:street": "Fairground Blvd",
    "iso:country": "US",
    "sg:address": "450 Fairground Blvd",
    "sg:city": "Canfield",
    "sg:classifiers": [
      {
        "category": "Retail",
        "subcategory": "Car Wash",
        "type": "Services"
      }
    ],
    "sg:phone": "+1 330 533 4053",
    "sg:postcode": "44406",
    "sg:province": "OH",
    "sg:tags": [
      "automobile",
      "detail",
      "clean"
    ],
    "wof:name": "Top Notch Car Care",
    "wof:placetype": "venue"
  },
  "geometry": {"coordinates":[-80.753992,41.015096],"type":"Point"}
}
