{
  "type": "Feature",
  "properties": {
    "iso:country":"US",
    "sg:address":"5314 Riverside Dr",
    "sg:city":"Columbus",
    "sg:classifiers":[
        {
            "category":"Retail",
            "subcategory":"Portrait Studio",
            "type":"Services"
        }
    ],
    "sg:phone":"+1 614 457 6609",
    "sg:postcode":"43220",
    "sg:province":"OH",
    "sg:tags":[
        "photo"
    ],
    "wof:name":"Hurt Photography",
    "wof:placetype":"venue"
},
  "geometry": {"coordinates":[-83.10355800000001,40.062842],"type":"Point"}
}