{
  "type": "Feature",
  "properties": {
    "addr:full": "5314 Riverside Dr Columbus OH 43220",
    "addr:housenumber": "5314",
    "addr:postcode": "43220",
    "addr:street": "Riverside Dr",
    "iso:country": "US",
    "sg:address": "5314 Riverside Dr",
    "sg:city": "Columbus",
    "sg:classifiers": [
      {
        "category": "Retail",
        "subcategory": "Portrait Studio",
        "type": "Services"
      }
    ],
    "sg:phone": "+1 614 457 6609",
    "sg:postcode": "43220",
    "sg:province": "OH",
    "sg:tags": [
      "photo"
    ],
    "wof:name": "Hurt Photography",
    "wof:placetype": "venue"
  },
  "geometry": {"coordinates":[-83.103558,40.062842],"type":"Point"}
}
