{
  "type": "Feature",
  "properties": {
    "iso:country":"US",
    "sg:address":"758 Cincinnati-Batavia Pike",
    "sg:city":"Cincinnati",
    "sg:classifiers":[
        {
            "category":"Freight",
            "type":"Transportation"
        }
    ],
    "sg:phone":"+1 513 752 7772",
    "sg:postcode":"45245",
    "sg:province":"OH",
    "sg:tags":[
        "storage"
    ],
    "wof:name":"Stronghold Self-Storage Mini",
    "wof:placetype":"venue"
},
  "geometry": {"coordinates":[-84.277989,39.106144],"type":"Point"}
}