{
  "type": "Feature",
  "properties": {
    "addr:full": "55 Cliffview Dr Mount Sterling OH 43143",
    "addr:housenumber": "55",
    "addr:postcode": "43143",
    "addr:street": "Cliffview Dr",
    "iso:country": "US",
    "sg:address": "55 Cliffview Dr",
    "sg:city": "Mount Sterling",
    "sg:phone": "+1 740 869 2565",
    "sg:postcode": "43143",
    "sg:province": "OH",
    "sg:tags": [
      "farm",
      "soybean"
    ],
    "wof:name": "Helen Jacobs",
    "wof:placetype": "venue"
  },
  "geometry": {"coordinates":[-83.266461,39.71571],"type":"Point"}
}
