{
  "type": "Feature",
  "properties": {
    "addr:full":"1366 N Honeytown Rd Wooster OH 44691",
    "addr:housenumber":"1366",
    "addr:postcode":"44691",
    "addr:street":"N Honeytown Rd",
    "iso:country":"US",
    "sg:address":"1366 N Honeytown Rd",
    "sg:city":"Wooster",
    "sg:classifiers":[
        {
            "category":"Farming",
            "subcategory":"Livestock Farm",
            "type":"Manufacturing & Wholesale Goods"
        }
    ],
    "sg:phone":"+1 330 262 1332",
    "sg:postcode":"44691",
    "sg:province":"OH",
    "sg:tags":[
        "beef",
        "feedlot",
        "animal",
        "cattle"
    ],
    "wof:name":"Trivanovich Farm",
    "wof:placetype":"venue"
},
  "geometry": {"coordinates":[-81.87736700000001,40.815239],"type":"Point"}
}