{
  "type": "Feature",
  "properties": {
    "addr:full": "210 Scotland Ave Youngstown OH 44512",
    "addr:housenumber": "210",
    "addr:postcode": "44512",
    "addr:street": "Scotland Ave",
    "iso:country": "US",
    "sg:address": "210 Scotland Ave",
    "sg:city": "Youngstown",
    "sg:classifiers": [
      {
        "category": "Building \u0026 Trades",
        "subcategory": "Construction",
        "type": "Services"
      }
    ],
    "sg:phone": "+1 330 726 5782",
    "sg:postcode": "44512",
    "sg:province": "OH",
    "sg:tags": [
      "nonresidential"
    ],
    "wof:name": "Beda Construction",
    "wof:placetype": "venue"
  },
  "geometry": {"coordinates":[-80.656168,41.009687],"type":"Point"}
}
