{
  "type": "Feature",
  "properties": {
    "addr:full":"34480 Vine St Willowick OH 44095",
    "addr:housenumber":"34480",
    "addr:postcode":"44095",
    "addr:street":"Vine St",
    "iso:country":"US",
    "sg:address":"34480 Vine St",
    "sg:city":"Willowick",
    "sg:classifiers":[
        {
            "category":"Cinema",
            "subcategory":"Movie Rental",
            "type":"Entertainment"
        }
    ],
    "sg:phone":"+1 440 975 9515",
    "sg:postcode":"44095",
    "sg:province":"OH",
    "sg:tags":[
        "leasing",
        "video",
        "disc",
        "tape"
    ],
    "wof:name":"Blockbuster Video",
    "wof:placetype":"venue"
},
  "geometry": {"coordinates":[-81.443798,41.64246],"type":"Point"}
}