{
  "type": "Feature",
  "properties": {
    "addr:full": "4125 Saint Williams Ave Cincinnati OH 45205",
    "addr:housenumber": "4125",
    "addr:postcode": "45205",
    "addr:street": "Saint Williams Ave",
    "iso:country": "US",
    "sg:address": "4125 Saint Williams Ave",
    "sg:city": "Cincinnati",
    "sg:classifiers": [
      {
        "category": "Education",
        "subcategory": "School",
        "type": "Public Place"
      }
    ],
    "sg:phone": "+1 513 471 2989",
    "sg:postcode": "45205",
    "sg:province": "OH",
    "sg:tags": [
      "religious"
    ],
    "wof:name": "St Williams School",
    "wof:placetype": "venue"
  },
  "geometry": {"coordinates":[-84.587661,39.108494],"type":"Point"}
}
