{
  "type": "Feature",
  "properties": {
    "iso:country":"US",
    "sg:address":"3205 State Rte 47",
    "sg:city":"Houston",
    "sg:classifiers":[
        {
            "category":"Retail",
            "subcategory":"Auto Repair",
            "type":"Services"
        }
    ],
    "sg:phone":"+1 937 295 3800",
    "sg:postcode":"45333",
    "sg:province":"OH",
    "sg:tags":[
        "repairing",
        "automobile"
    ],
    "wof:name":"Grilliot Newport Svc LLC",
    "wof:placetype":"venue"
},
  "geometry": {"coordinates":[-84.37460299999999,40.290334],"type":"Point"}
}