{
  "type": "Feature",
  "properties": {
    "iso:country":"US",
    "sg:address":"6236 Wadsworth Rd",
    "sg:city":"Medina",
    "sg:classifiers":[
        {
            "category":"Building & Trades",
            "subcategory":"Electrical",
            "type":"Services"
        }
    ],
    "sg:phone":"+1 330 725 8720",
    "sg:postcode":"44256",
    "sg:province":"OH",
    "sg:tags":[
        "electrical",
        "contractor"
    ],
    "wof:name":"Fetzer Construction Inc",
    "wof:placetype":"venue"
},
  "geometry": {"coordinates":[-81.835098,41.104154],"type":"Point"}
}