{
  "type": "Feature",
  "properties": {
    "addr:full":"3434 W Sylvania Ave Toledo OH 43623",
    "addr:housenumber":"3434",
    "addr:postcode":"43623",
    "addr:street":"W Sylvania Ave",
    "iso:country":"US",
    "sg:address":"3434 W Sylvania Ave",
    "sg:city":"Toledo",
    "sg:classifiers":[
        {
            "category":"Wholesale",
            "subcategory":"Electrical",
            "type":"Manufacturing & Wholesale Goods"
        },
        {
            "category":"Shopping",
            "subcategory":"Musical Instruments",
            "type":"Retail Goods"
        }
    ],
    "sg:phone":"+1 419 473 9993",
    "sg:postcode":"43623",
    "sg:province":"OH",
    "sg:tags":[
        "sound",
        "equipment",
        "system"
    ],
    "wof:name":"Prodigy Music Inc",
    "wof:placetype":"venue"
},
  "geometry": {"coordinates":[-83.62568899999999,41.691809],"type":"Point"}
}