{
  "type": "Feature",
  "properties": {
    "iso:country":"US",
    "sg:address":"1544 Felton Rd",
    "sg:city":"Cleveland",
    "sg:classifiers":[
        {
            "category":"Professional",
            "type":"Services"
        }
    ],
    "sg:phone":"+1 216 382 4934",
    "sg:postcode":"44121",
    "sg:province":"OH",
    "wof:name":"Andrew K Oster",
    "wof:placetype":"venue"
},
  "geometry": {"coordinates":[-81.53163000000001,41.515605],"type":"Point"}
}