{
  "type": "Feature",
  "properties": {
    "addr:full": "109 S Main St Dayton OH 45402",
    "addr:housenumber": "109",
    "addr:postcode": "45402",
    "addr:street": "S Main St",
    "iso:country": "US",
    "sg:address": "109 S Main St",
    "sg:city": "Dayton",
    "sg:classifiers": [
      {
        "category": "Organizations",
        "subcategory": "Professional Association",
        "type": "Services"
      }
    ],
    "sg:phone": "+1 937 222 7902",
    "sg:postcode": "45402",
    "sg:province": "OH",
    "sg:website": "www.daybar.org",
    "wof:name": "Dayton Bar Assn",
    "wof:placetype": "venue"
  },
  "geometry": {"coordinates":[-84.191138,39.757006],"type":"Point"}
}
