{
  "type": "Feature",
  "properties": {
    "addr:full": "138 Cherry St Marysville OH 43040",
    "addr:housenumber": "138",
    "addr:postcode": "43040",
    "addr:street": "Cherry St",
    "iso:country": "US",
    "sg:address": "138 Cherry St",
    "sg:city": "Marysville",
    "sg:classifiers": [
      {
        "category": "Home \u0026 Garden",
        "subcategory": "Building Materials",
        "type": "Retail Goods"
      }
    ],
    "sg:phone": "+1 937 642 3987",
    "sg:postcode": "43040",
    "sg:province": "OH",
    "sg:tags": [
      "door"
    ],
    "wof:name": "Bob Van Hoose Door Sales \u0026 Svc",
    "wof:placetype": "venue"
  },
  "geometry": {"coordinates":[-83.356467,40.236462],"type":"Point"}
}
