{
  "type": "Feature",
  "properties": {
    "iso:country":"US",
    "sg:address":"138 Cherry St",
    "sg:city":"Marysville",
    "sg:classifiers":[
        {
            "category":"Home & Garden",
            "subcategory":"Building Materials",
            "type":"Retail Goods"
        }
    ],
    "sg:phone":"+1 937 642 3987",
    "sg:postcode":"43040",
    "sg:province":"OH",
    "sg:tags":[
        "door"
    ],
    "wof:name":"Bob Van Hoose Door Sales & Svc",
    "wof:placetype":"venue"
},
  "geometry": {"coordinates":[-83.35646699999999,40.236462],"type":"Point"}
}