{
  "type": "Feature",
  "properties": {
    "addr:full": "180 N 4th St Steubenville OH 43952",
    "addr:housenumber": "180",
    "addr:postcode": "43952",
    "addr:street": "N 4Th St",
    "iso:country": "US",
    "sg:address": "180 N 4th St",
    "sg:city": "Steubenville",
    "sg:classifiers": [
      {
        "category": "Social Services",
        "subcategory": "Adult Care",
        "type": "Services"
      }
    ],
    "sg:phone": "+1 740 282 1661",
    "sg:postcode": "43952",
    "sg:province": "OH",
    "sg:tags": [
      "organization",
      "senior",
      "citizen"
    ],
    "wof:name": "RSVP Program",
    "wof:placetype": "venue"
  },
  "geometry": {"coordinates":[-80.615099,40.359992],"type":"Point"}
}
