{
  "type": "Feature",
  "properties": {
    "addr:full":"7128 Connaught Dr New Albany OH 43054",
    "addr:housenumber":"7128",
    "addr:postcode":"43054",
    "addr:street":"Connaught Dr",
    "iso:country":"US",
    "sg:address":"7128 Connaught Dr",
    "sg:city":"New Albany",
    "sg:classifiers":[
        {
            "category":"Health Services",
            "subcategory":"Clinic",
            "type":"Services"
        }
    ],
    "sg:phone":"+1 614 775 9659",
    "sg:postcode":"43054",
    "sg:province":"OH",
    "wof:name":"Health Care Marketing Strtgs",
    "wof:placetype":"venue"
},
  "geometry": {"coordinates":[-82.83185400000001,40.090408],"type":"Point"}
}