{
  "type": "Feature",
  "properties": {
    "addr:full":"1612 Windsor Dr Cleveland OH 44124",
    "addr:housenumber":"1612",
    "addr:postcode":"44124",
    "addr:street":"Windsor Dr",
    "iso:country":"US",
    "sg:address":"1612 Windsor Dr",
    "sg:city":"Cleveland",
    "sg:classifiers":[
        {
            "category":"Food & Beverages",
            "subcategory":"Groceries & Convenience Stores",
            "type":"Retail Goods"
        }
    ],
    "sg:phone":"+1 440 449 0087",
    "sg:postcode":"44124",
    "sg:province":"OH",
    "wof:name":"Just Rite Inc",
    "wof:placetype":"venue"
},
  "geometry": {"coordinates":[-81.43298900000001,41.516863],"type":"Point"}
}