{
  "type": "Feature",
  "properties": {
    "addr:full":"237 E Main St Hillsboro OH 45133",
    "addr:housenumber":"237",
    "addr:postcode":"45133",
    "addr:street":"E Main St",
    "iso:country":"US",
    "sg:address":"237 E Main St",
    "sg:city":"Hillsboro",
    "sg:classifiers":[
        {
            "category":"Health Services",
            "subcategory":"Podiatrist",
            "type":"Services"
        }
    ],
    "sg:phone":"+1 937 393 2036",
    "sg:postcode":"45133",
    "sg:province":"OH",
    "wof:name":"J Michael Moran DPM",
    "wof:placetype":"venue"
},
  "geometry": {"coordinates":[-83.608422,39.201639],"type":"Point"}
}