{
  "type": "Feature",
  "properties": {
    "iso:country":"US",
    "sg:address":"7425 Jeremy Ave",
    "sg:city":"Mentor",
    "sg:classifiers":[
        {
            "category":"Building & Trades",
            "subcategory":"Construction",
            "type":"Services"
        }
    ],
    "sg:phone":"+1 440 974 5455",
    "sg:postcode":"44060",
    "sg:province":"OH",
    "sg:tags":[
        "home",
        "improvement"
    ],
    "wof:name":"Jenco Inc",
    "wof:placetype":"venue"
},
  "geometry": {"coordinates":[-81.370436,41.69187],"type":"Point"}
}