{
  "type": "Feature",
  "properties": {
    "addr:full":"4450 Eastgate Blvd Cincinnati OH 45245",
    "addr:housenumber":"4450",
    "addr:postcode":"45245",
    "addr:street":"Eastgate Blvd",
    "iso:country":"US",
    "sg:address":"4450 Eastgate Blvd",
    "sg:city":"Cincinnati",
    "sg:classifiers":[
        {
            "category":"Food & Beverages",
            "subcategory":"Groceries & Convenience Stores",
            "type":"Retail Goods"
        }
    ],
    "sg:phone":"+1 513 753 7500",
    "sg:postcode":"45245",
    "sg:province":"OH",
    "wof:name":"Biggs Hypermarket",
    "wof:placetype":"venue"
},
  "geometry": {"coordinates":[-84.27450899999999,39.098168],"type":"Point"}
}