{
  "type": "Feature",
  "properties": {
    "iso:country":"US",
    "sg:address":"1966 Cherry Wood Ln",
    "sg:city":"Akron",
    "sg:classifiers":[
        {
            "category":"Building & Trades",
            "subcategory":"Cleaning & Sanitation",
            "type":"Services"
        }
    ],
    "sg:phone":"+1 330 733 5600",
    "sg:postcode":"44312",
    "sg:province":"OH",
    "sg:tags":[
        "window"
    ],
    "wof:name":"Shoaff's Window Cleaning",
    "wof:placetype":"venue"
},
  "geometry": {"coordinates":[-81.45666900000001,41.032929],"type":"Point"}
}