{
  "type": "Feature",
  "properties": {
    "addr:full": "1966 Cherry Wood Ln Akron OH 44312",
    "addr:housenumber": "1966",
    "addr:postcode": "44312",
    "addr:street": "Cherry Wood Ln",
    "iso:country": "US",
    "sg:address": "1966 Cherry Wood Ln",
    "sg:city": "Akron",
    "sg:classifiers": [
      {
        "category": "Building \u0026 Trades",
        "subcategory": "Cleaning \u0026 Sanitation",
        "type": "Services"
      }
    ],
    "sg:phone": "+1 330 733 5600",
    "sg:postcode": "44312",
    "sg:province": "OH",
    "sg:tags": [
      "window"
    ],
    "wof:name": "Shoaff's Window Cleaning",
    "wof:placetype": "venue"
  },
  "geometry": {"coordinates":[-81.456669,41.032929],"type":"Point"}
}
