{
  "type": "Feature",
  "properties": {
    "addr:full": "6411 Chestnut Rd Cleveland OH 44131",
    "addr:housenumber": "6411",
    "addr:postcode": "44131",
    "addr:street": "Chestnut Rd",
    "iso:country": "US",
    "sg:address": "6411 Chestnut Rd",
    "sg:city": "Cleveland",
    "sg:classifiers": [
      {
        "category": "Building \u0026 Trades",
        "subcategory": "Construction",
        "type": "Services"
      }
    ],
    "sg:phone": "+1 216 387 9908",
    "sg:postcode": "44131",
    "sg:province": "OH",
    "sg:tags": [
      "gas",
      "line",
      "installation",
      "repair"
    ],
    "wof:name": "Precision Piping Plus",
    "wof:placetype": "venue"
  },
  "geometry": {"coordinates":[-81.644944,41.384961],"type":"Point"}
}
