{
  "type": "Feature",
  "properties": {
    "addr:full":"1999 Lockbourne Rd Columbus OH 43207",
    "addr:housenumber":"1999",
    "addr:postcode":"43207",
    "addr:street":"Lockbourne Rd",
    "iso:country":"US",
    "sg:address":"1999 Lockbourne Rd",
    "sg:city":"Columbus",
    "sg:classifiers":[
        {
            "category":"Organizations",
            "subcategory":"Religious Organization",
            "type":"Services"
        }
    ],
    "sg:phone":"+1 614 443 3273",
    "sg:postcode":"43207",
    "sg:province":"OH",
    "sg:tags":[
        "church"
    ],
    "wof:name":"Church Of Christ",
    "wof:placetype":"venue"
},
  "geometry": {"coordinates":[-82.96521199999999,39.924915],"type":"Point"}
}