{
  "type": "Feature",
  "properties": {
    "iso:country":"US",
    "sg:address":"1093 State Rte 28",
    "sg:city":"Milford",
    "sg:classifiers":[
        {
            "category":"Banks & Credit Unions",
            "subcategory":"Bank",
            "type":"Services"
        }
    ],
    "sg:phone":"+1 513 248 0434",
    "sg:postcode":"45150",
    "sg:province":"OH",
    "sg:tags":[
        "state"
    ],
    "sg:website":"www.53.com",
    "wof:name":"Fifth Third Bank",
    "wof:placetype":"venue"
},
  "geometry": {"coordinates":[-84.23684900000001,39.194587],"type":"Point"}
}