{
  "type": "Feature",
  "properties": {
    "iso:country":"US",
    "sg:address":"1111 Freedom St",
    "sg:city":"Toledo",
    "sg:classifiers":[
        {
            "category":"Local Transit",
            "type":"Transportation"
        }
    ],
    "sg:phone":"+1 419 466 9356",
    "sg:postcode":"43605",
    "sg:province":"OH",
    "sg:tags":[
        "limousine"
    ],
    "wof:name":"Expressions Limousine",
    "wof:placetype":"venue"
},
  "geometry": {"coordinates":[-83.513993,41.627446],"type":"Point"}
}