{
  "type": "Feature",
  "properties": {
    "addr:full":"4540 Fulton Rd Smithville OH 44677",
    "addr:housenumber":"4540",
    "addr:postcode":"44677",
    "addr:street":"Fulton Rd",
    "iso:country":"US",
    "sg:address":"4540 Fulton Rd",
    "sg:city":"Smithville",
    "sg:classifiers":[
        {
            "category":"Building & Trades",
            "subcategory":"Construction",
            "type":"Services"
        }
    ],
    "sg:phone":"+1 330 669 9910",
    "sg:postcode":"44677",
    "sg:province":"OH",
    "sg:tags":[
        "house"
    ],
    "wof:name":"Zollinger Builders",
    "wof:placetype":"venue"
},
  "geometry": {"coordinates":[-81.894837,40.901411],"type":"Point"}
}