{
  "type": "Feature",
  "properties": {
    "iso:country":"US",
    "sg:address":"1130 E Dorothy Ln",
    "sg:city":"Dayton",
    "sg:classifiers":[
        {
            "category":"Building & Trades",
            "subcategory":"Construction",
            "type":"Services"
        }
    ],
    "sg:phone":"+1 937 294 2503",
    "sg:postcode":"45419",
    "sg:province":"OH",
    "sg:tags":[
        "fence",
        "contractor"
    ],
    "sg:website":"www.bellbrookfence.com",
    "wof:name":"Bellbrook Fence Co Inc",
    "wof:placetype":"venue"
},
  "geometry": {"coordinates":[-84.146781,39.703762],"type":"Point"}
}