{
  "type": "Feature",
  "properties": {
    "addr:full": "2816 Niles Rd SE Warren OH 44484",
    "addr:housenumber": "2816",
    "addr:postcode": "44484",
    "addr:street": "Niles Rd Se",
    "iso:country": "US",
    "sg:address": "2816 Niles Rd SE",
    "sg:city": "Warren",
    "sg:classifiers": [
      {
        "category": "Organizations",
        "subcategory": "Religious Organization",
        "type": "Services"
      }
    ],
    "sg:phone": "+1 330 369 4766",
    "sg:postcode": "44484",
    "sg:province": "OH",
    "sg:tags": [
      "church"
    ],
    "wof:name": "Barnes Temple Church Of God",
    "wof:placetype": "venue"
  },
  "geometry": {"coordinates":[-80.789856,41.213974],"type":"Point"}
}
