{
  "type": "Feature",
  "properties": {
    "addr:full": "5717 Kendon St Dayton OH 45414",
    "addr:housenumber": "5717",
    "addr:postcode": "45414",
    "addr:street": "Kendon St",
    "iso:country": "US",
    "sg:address": "5717 Kendon St",
    "sg:city": "Dayton",
    "sg:classifiers": [
      {
        "category": "Real Estate",
        "subcategory": "Real Estate Agent",
        "type": "Services"
      }
    ],
    "sg:phone": "+1 937 890 6937",
    "sg:postcode": "45414",
    "sg:province": "OH",
    "wof:name": "Joe E Hughes Real Estate Inc",
    "wof:placetype": "venue"
  },
  "geometry": {"coordinates":[-84.204443,39.832051],"type":"Point"}
}
