{
  "type": "Feature",
  "properties": {
    "addr:full":"308 E Warren St Lebanon OH 45036",
    "addr:housenumber":"308",
    "addr:postcode":"45036",
    "addr:street":"E Warren St",
    "iso:country":"US",
    "sg:address":"308 E Warren St",
    "sg:city":"Lebanon",
    "sg:classifiers":[
        {
            "category":"Real Estate",
            "subcategory":"Surveying",
            "type":"Services"
        }
    ],
    "sg:phone":"+1 513 932 1720",
    "sg:postcode":"45036",
    "sg:province":"OH",
    "wof:name":"Ballinger & Assocs Engrg Svc",
    "wof:placetype":"venue"
},
  "geometry": {"coordinates":[-84.203506,39.436375],"type":"Point"}
}