{
  "type": "Feature",
  "properties": {
    "iso:country":"US",
    "sg:address":"605 Taylor St",
    "sg:city":"Elyria",
    "sg:classifiers":[
        {
            "category":"Building & Trades",
            "subcategory":"Construction",
            "type":"Services"
        }
    ],
    "sg:phone":"+1 440 323 9970",
    "sg:postcode":"44035",
    "sg:province":"OH",
    "sg:tags":[
        "general",
        "contractor"
    ],
    "wof:name":"Greg Decker Construction LLC",
    "wof:placetype":"venue"
},
  "geometry": {"coordinates":[-82.085885,41.371684],"type":"Point"}
}