{
  "type": "Feature",
  "properties": {
    "addr:full": "3225 Gardenia Dr Dayton OH 45449",
    "addr:housenumber": "3225",
    "addr:postcode": "45449",
    "addr:street": "Gardenia Dr",
    "iso:country": "US",
    "sg:address": "3225 Gardenia Dr",
    "sg:city": "Dayton",
    "sg:classifiers": [
      {
        "category": "Personal",
        "type": "Services"
      }
    ],
    "sg:phone": "+1 937 438 3591",
    "sg:postcode": "45449",
    "sg:province": "OH",
    "sg:tags": [
      "dating"
    ],
    "wof:name": "Sessions Dating",
    "wof:placetype": "venue"
  },
  "geometry": {"coordinates":[-84.225283,39.667592],"type":"Point"}
}
