{
  "type": "Feature",
  "properties": {
    "iso:country":"US",
    "sg:address":"825 Bricker Ave",
    "sg:city":"Toledo",
    "sg:classifiers":[
        {
            "category":"Organizations",
            "subcategory":"Religious Organization",
            "type":"Services"
        }
    ],
    "sg:phone":"+1 419 727 0449",
    "sg:postcode":"43608",
    "sg:province":"OH",
    "sg:tags":[
        "church"
    ],
    "wof:name":"Christ The King Redemptive",
    "wof:placetype":"venue"
},
  "geometry": {"coordinates":[-83.525808,41.685786],"type":"Point"}
}