{
  "type": "Feature",
  "properties": {
    "addr:full":"34746 Vine St Willowick OH 44095",
    "addr:housenumber":"34746",
    "addr:postcode":"44095",
    "addr:street":"Vine St",
    "iso:country":"US",
    "sg:address":"34746 Vine St",
    "sg:city":"Willowick",
    "sg:classifiers":[
        {
            "category":"Restaurant",
            "type":"Food & Drink"
        }
    ],
    "sg:phone":"+1 440 953 0821",
    "sg:postcode":"44095",
    "sg:province":"OH",
    "wof:name":"Quiznos Sub",
    "wof:placetype":"venue"
},
  "geometry": {"coordinates":[-81.441309,41.642465],"type":"Point"}
}