{
  "type": "Feature",
  "properties": {
    "addr:full":"34931 Vine St Willoughby OH 44095",
    "addr:housenumber":"34931",
    "addr:postcode":"44095",
    "addr:street":"Vine St",
    "iso:country":"US",
    "sg:address":"34931 Vine St",
    "sg:city":"Willoughby",
    "sg:classifiers":[
        {
            "category":"Restaurant",
            "type":"Food & Drink"
        }
    ],
    "sg:phone":"+1 440 942 6622",
    "sg:postcode":"44095",
    "sg:province":"OH",
    "sg:tags":[
        "eating"
    ],
    "wof:name":"Catherine & Anthony Inc",
    "wof:placetype":"venue"
},
  "geometry": {"coordinates":[-81.43862900000001,41.642643],"type":"Point"}
}