{
  "type": "Feature",
  "properties": {
    "addr:full": "3794 Fishinger Blvd Hilliard OH 43026",
    "addr:housenumber": "3794",
    "addr:postcode": "43026",
    "addr:street": "Fishinger Blvd",
    "iso:country": "US",
    "sg:address": "3794 Fishinger Blvd",
    "sg:city": "Hilliard",
    "sg:classifiers": [
      {
        "category": "Restaurant",
        "type": "Food \u0026 Drink"
      }
    ],
    "sg:phone": "+1 614 771 3870",
    "sg:postcode": "43026",
    "sg:province": "OH",
    "sg:tags": [
      "eating"
    ],
    "wof:name": "Taj Palace",
    "wof:placetype": "venue"
  },
  "geometry": {"coordinates":[-83.115996,40.031812],"type":"Point"}
}
