{
  "type": "Feature",
  "properties": {
    "addr:full":"11309 Montgomery Rd Cincinnati OH 45249",
    "addr:housenumber":"11309",
    "addr:postcode":"45249",
    "addr:street":"Montgomery Rd",
    "iso:country":"US",
    "sg:address":"11309 Montgomery Rd",
    "sg:city":"Cincinnati",
    "sg:classifiers":[
        {
            "category":"Professional",
            "type":"Services"
        }
    ],
    "sg:phone":"+1 513 489 5777",
    "sg:postcode":"45249",
    "sg:province":"OH",
    "sg:tags":[
        "establishment"
    ],
    "wof:name":"Huntington Harpers",
    "wof:placetype":"venue"
},
  "geometry": {"coordinates":[-84.32733,39.272687],"type":"Point"}
}