{
  "type": "Feature",
  "properties": {
    "addr:full": "3301 Montgomery Rd Cincinnati OH 45207",
    "addr:housenumber": "3301",
    "addr:postcode": "45207",
    "addr:street": "Montgomery Rd",
    "iso:country": "US",
    "sg:address": "3301 Montgomery Rd",
    "sg:city": "Cincinnati",
    "sg:classifiers": [
      {
        "category": "Personal",
        "subcategory": "Barber",
        "type": "Services"
      }
    ],
    "sg:phone": "+1 513 281 9648",
    "sg:postcode": "45207",
    "sg:province": "OH",
    "wof:name": "Johnny's Barber Shop",
    "wof:placetype": "venue"
  },
  "geometry": {"coordinates":[-84.474572,39.138914],"type":"Point"}
}
