{
  "type": "Feature",
  "properties": {
    "addr:full": "24400 Highland Rd Cleveland OH 44143",
    "addr:housenumber": "24400",
    "addr:postcode": "44143",
    "addr:street": "Highland Rd",
    "iso:country": "US",
    "sg:address": "24400 Highland Rd",
    "sg:city": "Cleveland",
    "sg:classifiers": [
      {
        "category": "Professional",
        "subcategory": "Computer Services",
        "type": "Services"
      }
    ],
    "sg:phone": "+1 216 481 4044",
    "sg:postcode": "44143",
    "sg:province": "OH",
    "sg:tags": [
      "consultant",
      "designer"
    ],
    "sg:website": "www.ksac.com",
    "wof:name": "Stauffer \u0026 Co",
    "wof:placetype": "venue"
  },
  "geometry": {"coordinates":[-81.523447,41.553875],"type":"Point"}
}
