{
  "type": "Feature",
  "properties": {
    "addr:full":"3729 Glenmore Ave Cincinnati OH 45211",
    "addr:housenumber":"3729",
    "addr:postcode":"45211",
    "addr:street":"Glenmore Ave",
    "iso:country":"US",
    "sg:address":"3729 Glenmore Ave",
    "sg:city":"Cincinnati",
    "sg:classifiers":[
        {
            "category":"Personal",
            "subcategory":"Beauty Salon",
            "type":"Services"
        }
    ],
    "sg:phone":"+1 513 662 8600",
    "sg:postcode":"45211",
    "sg:province":"OH",
    "wof:name":"Mindy's Salon",
    "wof:placetype":"venue"
},
  "geometry": {"coordinates":[-84.611175,39.156256],"type":"Point"}
}