{
  "type": "Feature",
  "properties": {
    "addr:full":"13035 State Rte 122 Somerville OH 45064",
    "addr:housenumber":"13035",
    "addr:postcode":"45064",
    "addr:street":"State Rte 122",
    "iso:country":"US",
    "sg:address":"13035 State Rte 122",
    "sg:city":"Somerville",
    "sg:classifiers":[
        {
            "category":"Shopping",
            "subcategory":"Bicycles & Sporting Goods",
            "type":"Retail Goods"
        }
    ],
    "sg:phone":"+1 937 787 4236",
    "sg:postcode":"45064",
    "sg:province":"OH",
    "wof:name":"Bob Wells Saddlery",
    "wof:placetype":"venue"
},
  "geometry": {"coordinates":[-84.510014,39.596911],"type":"Point"}
}