{
  "type": "Feature",
  "properties": {
    "iso:country":"US",
    "sg:address":"115 Mount Vernon Ave",
    "sg:city":"Mount Vernon",
    "sg:classifiers":[
        {
            "category":"Retail",
            "subcategory":"Auto Repair",
            "type":"Services"
        }
    ],
    "sg:phone":"+1 740 392 9200",
    "sg:postcode":"43050",
    "sg:province":"OH",
    "sg:tags":[
        "automotive",
        "vehicle",
        "motor",
        "mfg"
    ],
    "wof:name":"Hisan Inc",
    "wof:placetype":"venue"
},
  "geometry": {"coordinates":[-82.481697,40.384714],"type":"Point"}
}