{
  "type": "Feature",
  "properties": {
    "addr:full": "216 S 3rd St Hamilton OH 45011",
    "addr:housenumber": "216",
    "addr:postcode": "45011",
    "addr:street": "S 3Rd St",
    "iso:country": "US",
    "sg:address": "216 S 3rd St",
    "sg:city": "Hamilton",
    "sg:classifiers": [
      {
        "category": "Home \u0026 Garden",
        "subcategory": "Furniture",
        "type": "Retail Goods"
      }
    ],
    "sg:phone": "+1 513 868 7694",
    "sg:postcode": "45011",
    "sg:province": "OH",
    "wof:name": "Max Joffe Furniture Co",
    "wof:placetype": "venue"
  },
  "geometry": {"coordinates":[-84.56122,39.397409],"type":"Point"}
}
