{
  "type": "Feature",
  "properties": {
    "iso:country":"US",
    "sg:address":"216 S 3rd St",
    "sg:city":"Hamilton",
    "sg:classifiers":[
        {
            "category":"Home & Garden",
            "subcategory":"Furniture",
            "type":"Retail Goods"
        }
    ],
    "sg:phone":"+1 513 868 7694",
    "sg:postcode":"45011",
    "sg:province":"OH",
    "wof:name":"Max Joffe Furniture Co",
    "wof:placetype":"venue"
},
  "geometry": {"coordinates":[-84.56122000000001,39.397409],"type":"Point"}
}