{
  "type": "Feature",
  "properties": {
    "addr:full": "8650 Brookpark Rd Cleveland OH 44134",
    "addr:housenumber": "8650",
    "addr:postcode": "44134",
    "addr:street": "Brookpark Rd",
    "iso:country": "US",
    "sg:address": "8650 Brookpark Rd",
    "sg:city": "Cleveland",
    "sg:classifiers": [
      {
        "category": "Retail",
        "subcategory": "Auto Repair",
        "type": "Services"
      }
    ],
    "sg:phone": "+1 216 749 3302",
    "sg:postcode": "44134",
    "sg:province": "OH",
    "sg:tags": [
      "truck"
    ],
    "wof:name": "Cleveland Peterbilt LLC",
    "wof:placetype": "venue"
  },
  "geometry": {"coordinates":[-81.750996,41.41858],"type":"Point"}
}
