{
  "type": "Feature",
  "properties": {
    "iso:country":"US",
    "sg:address":"7111 Orchard Centre Dr",
    "sg:city":"Holland",
    "sg:classifiers":[
        {
            "category":"Shopping",
            "subcategory":"Books",
            "type":"Retail Goods"
        }
    ],
    "sg:phone":"+1 419 865 0139",
    "sg:postcode":"43528",
    "sg:province":"OH",
    "sg:tags":[
        "dealer"
    ],
    "wof:name":"Little Professor Book Ctr",
    "wof:placetype":"venue"
},
  "geometry": {"coordinates":[-83.711412,41.609315],"type":"Point"}
}