{
  "type": "Feature",
  "properties": {
    "addr:full":"2945 Shaw Rd Zanesville OH 43701",
    "addr:housenumber":"2945",
    "addr:postcode":"43701",
    "addr:street":"Shaw Rd",
    "iso:country":"US",
    "sg:address":"2945 Shaw Rd",
    "sg:city":"Zanesville",
    "sg:classifiers":[
        {
            "category":"Autos & Motor Vehicles",
            "subcategory":"Auto Supplies",
            "type":"Retail Goods"
        }
    ],
    "sg:phone":"+1 740 453 2708",
    "sg:postcode":"43701",
    "sg:province":"OH",
    "wof:name":"Robison Auto Parts",
    "wof:placetype":"venue"
},
  "geometry": {"coordinates":[-82.03748400000001,39.889394],"type":"Point"}
}