{
  "type": "Feature",
  "properties": {
    "addr:full":"1335 Massillon Rd Akron OH 44306",
    "addr:housenumber":"1335",
    "addr:postcode":"44306",
    "addr:street":"Massillon Rd",
    "iso:country":"US",
    "sg:address":"1335 Massillon Rd",
    "sg:city":"Akron",
    "sg:classifiers":[
        {
            "category":"Social Services",
            "subcategory":"Child Care",
            "type":"Services"
        }
    ],
    "sg:phone":"+1 330 733 2290",
    "sg:postcode":"44306",
    "sg:province":"OH",
    "sg:tags":[
        "day"
    ],
    "wof:name":"Akron-Summit Cmnty Action Agcy",
    "wof:placetype":"venue"
},
  "geometry": {"coordinates":[-81.463313,41.022657],"type":"Point"}
}