{
  "type": "Feature",
  "properties": {
    "iso:country":"US",
    "sg:address":"1421 Herschel Ave",
    "sg:city":"Cincinnati",
    "sg:classifiers":[
        {
            "category":"Banks & Credit Unions",
            "subcategory":"Financial Services",
            "type":"Services"
        }
    ],
    "sg:phone":"+1 513 871 1493",
    "sg:postcode":"45208",
    "sg:province":"OH",
    "sg:tags":[
        "investment",
        "private"
    ],
    "wof:name":"Unlimited Ventures Stock Club",
    "wof:placetype":"venue"
},
  "geometry": {"coordinates":[-84.42095999999999,39.137485],"type":"Point"}
}