{
  "type": "Feature",
  "properties": {
    "iso:country":"US",
    "sg:address":"8276 W Chester Rd",
    "sg:city":"West Chester",
    "sg:classifiers":[
        {
            "category":"Utilities",
            "subcategory":"Cable",
            "type":"Services"
        }
    ],
    "sg:phone":"+1 513 779 5135",
    "sg:postcode":"45069",
    "sg:province":"OH",
    "sg:tags":[
        "television"
    ],
    "wof:name":"First Team Cable Marketing",
    "wof:placetype":"venue"
},
  "geometry": {"coordinates":[-84.354288,39.317754],"type":"Point"}
}