{
  "type": "Feature",
  "properties": {
    "addr:full": "1024 Grant St Akron OH 44311",
    "addr:housenumber": "1024",
    "addr:postcode": "44311",
    "addr:street": "Grant St",
    "iso:country": "US",
    "sg:address": "1024 Grant St",
    "sg:city": "Akron",
    "sg:classifiers": [
      {
        "category": "Banks \u0026 Credit Unions",
        "subcategory": "Financial Services",
        "type": "Services"
      }
    ],
    "sg:phone": "+1 330 724 4791",
    "sg:postcode": "44311",
    "sg:province": "OH",
    "sg:tags": [
      "company",
      "holding"
    ],
    "wof:name": "Moose Holding Inc",
    "wof:placetype": "venue"
  },
  "geometry": {"coordinates":[-81.518249,41.054976],"type":"Point"}
}
