{
  "type": "Feature",
  "properties": {
    "iso:country":"US",
    "sg:address":"1024 Grant St",
    "sg:city":"Akron",
    "sg:classifiers":[
        {
            "category":"Banks & Credit Unions",
            "subcategory":"Financial Services",
            "type":"Services"
        }
    ],
    "sg:phone":"+1 330 724 4791",
    "sg:postcode":"44311",
    "sg:province":"OH",
    "sg:tags":[
        "company",
        "holding"
    ],
    "wof:name":"Moose Holding Inc",
    "wof:placetype":"venue"
},
  "geometry": {"coordinates":[-81.518249,41.054976],"type":"Point"}
}