{
  "type": "Feature",
  "properties": {
    "addr:full": "14205 Fruend Rd Delphos OH 45833",
    "addr:housenumber": "14205",
    "addr:postcode": "45833",
    "addr:street": "Fruend Rd",
    "iso:country": "US",
    "sg:address": "14205 Fruend Rd",
    "sg:city": "Delphos",
    "sg:phone": "+1 419 692 5037",
    "sg:postcode": "45833",
    "sg:province": "OH",
    "sg:tags": [
      "farm",
      "corn",
      "soybean"
    ],
    "wof:name": "Schulte Farms",
    "wof:placetype": "venue"
  },
  "geometry": {"coordinates":[-84.376786,40.771976],"type":"Point"}
}
