{
  "type": "Feature",
  "properties": {
    "iso:country":"US",
    "sg:address":"1818 Eastern Ave",
    "sg:city":"Gallipolis",
    "sg:classifiers":[
        {
            "category":"Autos & Motor Vehicles",
            "subcategory":"Auto Supplies",
            "type":"Retail Goods"
        }
    ],
    "sg:phone":"+1 740 446 1113",
    "sg:postcode":"45631",
    "sg:province":"OH",
    "sg:tags":[
        "repair",
        "tire"
    ],
    "wof:name":"Tom's Tire & Auto Clinic",
    "wof:placetype":"venue"
},
  "geometry": {"coordinates":[-82.17685,38.821529],"type":"Point"}
}