{
  "type": "Feature",
  "properties": {
    "addr:full": "1818 Eastern Ave Gallipolis OH 45631",
    "addr:housenumber": "1818",
    "addr:postcode": "45631",
    "addr:street": "Eastern Ave",
    "iso:country": "US",
    "sg:address": "1818 Eastern Ave",
    "sg:city": "Gallipolis",
    "sg:classifiers": [
      {
        "category": "Autos \u0026 Motor Vehicles",
        "subcategory": "Auto Supplies",
        "type": "Retail Goods"
      }
    ],
    "sg:phone": "+1 740 446 1113",
    "sg:postcode": "45631",
    "sg:province": "OH",
    "sg:tags": [
      "repair",
      "tire"
    ],
    "wof:name": "Tom's Tire \u0026 Auto Clinic",
    "wof:placetype": "venue"
  },
  "geometry": {"coordinates":[-82.17685,38.821529],"type":"Point"}
}
