{
  "type": "Feature",
  "properties": {
    "iso:country":"US",
    "sg:address":"672 N Main St",
    "sg:city":"Springboro",
    "sg:classifiers":[
        {
            "category":"Personal",
            "subcategory":"Beauty Salon",
            "type":"Services"
        }
    ],
    "sg:phone":"+1 937 748 4447",
    "sg:postcode":"45066",
    "sg:province":"OH",
    "wof:name":"Big League Haircuts",
    "wof:placetype":"venue"
},
  "geometry": {"coordinates":[-84.231486,39.570141],"type":"Point"}
}