{
  "type": "Feature",
  "properties": {
    "addr:full": "4430 Sir Richard Ave Cleveland OH 44133",
    "addr:housenumber": "4430",
    "addr:postcode": "44133",
    "addr:street": "Sir Richard Ave",
    "iso:country": "US",
    "sg:address": "4430 Sir Richard Ave",
    "sg:city": "Cleveland",
    "sg:classifiers": [
      {
        "category": "Shopping",
        "subcategory": "Gifts \u0026 Souvenirs",
        "type": "Retail Goods"
      }
    ],
    "sg:phone": "+1 440 237 4327",
    "sg:postcode": "44133",
    "sg:province": "OH",
    "sg:tags": [
      "basket",
      "parcel"
    ],
    "wof:name": "Original Basket Co",
    "wof:placetype": "venue"
  },
  "geometry": {"coordinates":[-81.715339,41.315684],"type":"Point"}
}
