{
  "type": "Feature",
  "properties": {
    "addr:full": "729 Sycamore St Belpre OH 45714",
    "addr:housenumber": "729",
    "addr:postcode": "45714",
    "addr:street": "Sycamore St",
    "iso:country": "US",
    "sg:address": "729 Sycamore St",
    "sg:city": "Belpre",
    "sg:classifiers": [
      {
        "category": "Retail",
        "subcategory": "Repair Shop",
        "type": "Services"
      }
    ],
    "sg:phone": "+1 740 423 5789",
    "sg:postcode": "45714",
    "sg:province": "OH",
    "sg:tags": [
      "television",
      "radio-service"
    ],
    "wof:name": "Cliff's T V",
    "wof:placetype": "venue"
  },
  "geometry": {"coordinates":[-81.599761,39.277858],"type":"Point"}
}
