{
  "type": "Feature",
  "properties": {
    "addr:full": "759 E 200th St Cleveland OH 44119",
    "addr:housenumber": "759",
    "addr:postcode": "44119",
    "addr:street": "E 200Th St",
    "iso:country": "US",
    "sg:address": "759 E 200th St",
    "sg:city": "Cleveland",
    "sg:classifiers": [
      {
        "category": "Health Services",
        "subcategory": "Doctor",
        "type": "Services"
      }
    ],
    "sg:phone": "+1 216 486 2156",
    "sg:postcode": "44119",
    "sg:province": "OH",
    "wof:name": "Paul A Clark DDS",
    "wof:placetype": "venue"
  },
  "geometry": {"coordinates":[-81.540058,41.585606],"type":"Point"}
}
