{
  "type": "Feature",
  "properties": {
    "iso:country":"US",
    "sg:address":"2580 Woodman Dr",
    "sg:city":"Dayton",
    "sg:classifiers":[
        {
            "category":"Organizations",
            "subcategory":"Religious Organization",
            "type":"Services"
        }
    ],
    "sg:phone":"+1 937 296 1914",
    "sg:postcode":"45420",
    "sg:province":"OH",
    "sg:tags":[
        "church"
    ],
    "wof:name":"Southeast Congregation",
    "wof:placetype":"venue"
},
  "geometry": {"coordinates":[-84.12380400000001,39.708283],"type":"Point"}
}