{
  "type": "Feature",
  "properties": {
    "addr:full": "2580 Woodman Dr Dayton OH 45420",
    "addr:housenumber": "2580",
    "addr:postcode": "45420",
    "addr:street": "Woodman Dr",
    "iso:country": "US",
    "sg:address": "2580 Woodman Dr",
    "sg:city": "Dayton",
    "sg:classifiers": [
      {
        "category": "Organizations",
        "subcategory": "Religious Organization",
        "type": "Services"
      }
    ],
    "sg:phone": "+1 937 296 1914",
    "sg:postcode": "45420",
    "sg:province": "OH",
    "sg:tags": [
      "church"
    ],
    "wof:name": "Southeast Congregation",
    "wof:placetype": "venue"
  },
  "geometry": {"coordinates":[-84.123804,39.708283],"type":"Point"}
}
