{
  "type": "Feature",
  "properties": {
    "addr:full": "9500 State Rte 66 Piqua OH 45356",
    "addr:housenumber": "9500",
    "addr:postcode": "45356",
    "addr:street": "State Rte 66",
    "iso:country": "US",
    "sg:address": "9500 State Rte 66",
    "sg:city": "Piqua",
    "sg:classifiers": [
      {
        "category": "Home \u0026 Garden",
        "subcategory": "Furniture",
        "type": "Retail Goods"
      }
    ],
    "sg:phone": "+1 937 773 6794",
    "sg:postcode": "45356",
    "sg:province": "OH",
    "wof:name": "B \u0026 D Furniture",
    "wof:placetype": "venue"
  },
  "geometry": {"coordinates":[-84.262832,40.178274],"type":"Point"}
}
