{
  "type": "Feature",
  "properties": {
    "iso:country":"US",
    "sg:address":"9500 State Rte 66",
    "sg:city":"Piqua",
    "sg:classifiers":[
        {
            "category":"Home & Garden",
            "subcategory":"Furniture",
            "type":"Retail Goods"
        }
    ],
    "sg:phone":"+1 937 773 6794",
    "sg:postcode":"45356",
    "sg:province":"OH",
    "wof:name":"B & D Furniture",
    "wof:placetype":"venue"
},
  "geometry": {"coordinates":[-84.262832,40.178274],"type":"Point"}
}