{
  "type": "Feature",
  "properties": {
    "iso:country":"US",
    "sg:address":"5738 Reynoldsburg Baltimore Rd NW",
    "sg:city":"Pickerington",
    "sg:classifiers":[
        {
            "category":"Building & Trades",
            "subcategory":"Construction",
            "type":"Services"
        }
    ],
    "sg:phone":"+1 740 862 8569",
    "sg:postcode":"43147",
    "sg:province":"OH",
    "sg:tags":[
        "general",
        "contractor"
    ],
    "wof:name":"Bottoms Construction Inc",
    "wof:placetype":"venue"
},
  "geometry": {"coordinates":[-82.69580999999999,39.869716],"type":"Point"}
}