{
  "type": "Feature",
  "properties": {
    "iso:country":"US",
    "sg:address":"7454 Jager Ct",
    "sg:city":"Cincinnati",
    "sg:classifiers":[
        {
            "category":"Professional",
            "subcategory":"Management & Consulting",
            "type":"Services"
        },
        {
            "category":"Banks & Credit Unions",
            "subcategory":"Financial Services",
            "type":"Services"
        }
    ],
    "sg:phone":"+1 513 474 9191",
    "sg:postcode":"45230",
    "sg:province":"OH",
    "sg:tags":[
        "consultant",
        "financing",
        "planning"
    ],
    "sg:website":"http://www.bernofinmgt.com",
    "wof:name":"Berno Financial Management Inc",
    "wof:placetype":"venue"
},
  "geometry": {"coordinates":[-84.351068,39.066903],"type":"Point"}
}