{
  "type": "Feature",
  "properties": {
    "iso:country":"US",
    "sg:address":"3379 Dowling Dr",
    "sg:city":"Akron",
    "sg:classifiers":[
        {
            "category":"Building & Trades",
            "subcategory":"Construction",
            "type":"Services"
        }
    ],
    "sg:phone":"+1 330 666 8183",
    "sg:postcode":"44333",
    "sg:province":"OH",
    "sg:tags":[
        "home",
        "general",
        "family",
        "contractor"
    ],
    "wof:name":"Maselli Construction Company",
    "wof:placetype":"venue"
},
  "geometry": {"coordinates":[-81.633989,41.121765],"type":"Point"}
}