{
  "type": "Feature",
  "properties": {
    "iso:country":"US",
    "sg:address":"206 E Elm St",
    "sg:city":"Wauseon",
    "sg:classifiers":[
        {
            "category":"Real Estate",
            "subcategory":"Real Estate Agent",
            "type":"Services"
        }
    ],
    "sg:phone":"+1 419 335 4339",
    "sg:postcode":"43567",
    "sg:province":"OH",
    "sg:tags":[
        "appraiser"
    ],
    "wof:name":"Upon The Rock Real Estate Svc",
    "wof:placetype":"venue"
},
  "geometry": {"coordinates":[-84.13946799999999,41.549362],"type":"Point"}
}