{
  "type": "Feature",
  "properties": {
    "iso:country":"US",
    "sg:address":"8005 East St",
    "sg:city":"Adamsville",
    "sg:classifiers":[
        {
            "category":"Retail",
            "subcategory":"Funeral Services",
            "type":"Services"
        }
    ],
    "sg:phone":"+1 740 796 5261",
    "sg:postcode":"43802",
    "sg:province":"OH",
    "sg:tags":[
        "director"
    ],
    "wof:name":"Vensil-Orr Funeral Home",
    "wof:placetype":"venue"
},
  "geometry": {"coordinates":[-81.88253,40.068992],"type":"Point"}
}