{
  "type": "Feature",
  "properties": {
    "iso:country":"US",
    "sg:address":"3913 Alicante Ln",
    "sg:city":"Cincinnati",
    "sg:classifiers":[
        {
            "category":"Professional",
            "subcategory":"Accounting & Tax Preparation",
            "type":"Services"
        }
    ],
    "sg:phone":"+1 513 947 9114",
    "sg:postcode":"45255",
    "sg:province":"OH",
    "sg:tags":[
        "accountant"
    ],
    "wof:name":"Albonetti & Co",
    "wof:placetype":"venue"
},
  "geometry": {"coordinates":[-84.308026,39.061052],"type":"Point"}
}