{
  "type": "Feature",
  "properties": {
    "addr:full": "3913 Alicante Ln Cincinnati OH 45255",
    "addr:housenumber": "3913",
    "addr:postcode": "45255",
    "addr:street": "Alicante Ln",
    "iso:country": "US",
    "sg:address": "3913 Alicante Ln",
    "sg:city": "Cincinnati",
    "sg:classifiers": [
      {
        "category": "Professional",
        "subcategory": "Accounting \u0026 Tax Preparation",
        "type": "Services"
      }
    ],
    "sg:phone": "+1 513 947 9114",
    "sg:postcode": "45255",
    "sg:province": "OH",
    "sg:tags": [
      "accountant"
    ],
    "wof:name": "Albonetti \u0026 Co",
    "wof:placetype": "venue"
  },
  "geometry": {"coordinates":[-84.308026,39.061052],"type":"Point"}
}
