{
  "type": "Feature",
  "properties": {
    "addr:full": "7888 Troy Pike Dayton OH 45424",
    "addr:housenumber": "7888",
    "addr:postcode": "45424",
    "addr:street": "Troy Pike",
    "iso:country": "US",
    "sg:address": "7888 Troy Pike",
    "sg:city": "Dayton",
    "sg:classifiers": [
      {
        "category": "Retail",
        "subcategory": "Auto Repair",
        "type": "Services"
      }
    ],
    "sg:phone": "+1 937 233 8624",
    "sg:postcode": "45424",
    "sg:province": "OH",
    "sg:tags": [
      "automobile",
      "diagnostic"
    ],
    "wof:name": "Pro Care Automotive",
    "wof:placetype": "venue"
  },
  "geometry": {"coordinates":[-84.13771,39.868061],"type":"Point"}
}
