{
  "type": "Feature",
  "properties": {
    "addr:full":"826 Woodbridge Ct Amherst OH 44001",
    "addr:housenumber":"826",
    "addr:postcode":"44001",
    "addr:street":"Woodbridge Ct",
    "iso:country":"US",
    "sg:address":"826 Woodbridge Ct",
    "sg:city":"Amherst",
    "sg:classifiers":[
        {
            "category":"Sports & Exercise",
            "subcategory":"Race Track",
            "type":"Entertainment"
        }
    ],
    "sg:phone":"+1 440 984 2817",
    "sg:postcode":"44001",
    "sg:province":"OH",
    "sg:tags":[
        "operation",
        "racing",
        "or",
        "supply"
    ],
    "wof:name":"Lorain County Speedway",
    "wof:placetype":"venue"
},
  "geometry": {"coordinates":[-82.23329099999999,41.403707],"type":"Point"}
}