{
  "type": "Feature",
  "properties": {
    "iso:country":"US",
    "sg:address":"1016 Tiffin Ave",
    "sg:city":"Findlay",
    "sg:classifiers":[
        {
            "category":"Real Estate",
            "subcategory":"Real Estate Operator",
            "type":"Services"
        }
    ],
    "sg:phone":"+1 419 424 1114",
    "sg:postcode":"45840",
    "sg:province":"OH",
    "sg:tags":[
        "building",
        "nonresidential"
    ],
    "wof:name":"Marbo Investments Inc",
    "wof:placetype":"venue"
},
  "geometry": {"coordinates":[-83.631933,41.048506],"type":"Point"}
}