{
  "type": "Feature",
  "properties": {
    "iso:country":"US",
    "sg:address":"27887 Clemens Rd",
    "sg:city":"Cleveland",
    "sg:classifiers":[
        {
            "category":"Utilities",
            "subcategory":"Cable",
            "type":"Services"
        },
        {
            "category":"Professional",
            "subcategory":"Advertising",
            "type":"Services"
        }
    ],
    "sg:phone":"+1 440 617 2280",
    "sg:postcode":"44145",
    "sg:province":"OH",
    "sg:tags":[
        "television"
    ],
    "sg:website":"www.adelphia.com",
    "wof:name":"Adelphia",
    "wof:placetype":"venue"
},
  "geometry": {"coordinates":[-81.94301900000001,41.470347],"type":"Point"}
}