{
  "type": "Feature",
  "properties": {
    "iso:country":"US",
    "sg:address":"1500 Polaris Pkwy",
    "sg:city":"Columbus",
    "sg:classifiers":[
        {
            "category":"Manufacturing",
            "subcategory":"Jewelry",
            "type":"Manufacturing & Wholesale Goods"
        }
    ],
    "sg:phone":"+1 614 985 3587",
    "sg:postcode":"43240",
    "sg:province":"OH",
    "sg:tags":[
        "platinum",
        "buyer",
        "silver",
        "gold"
    ],
    "wof:name":"Gold Buyers On The Mall",
    "wof:placetype":"venue"
},
  "geometry": {"coordinates":[-82.97799500000001,40.141542],"type":"Point"}
}