{
  "type": "Feature",
  "properties": {
    "iso:country":"US",
    "sg:address":"410 E Broad St",
    "sg:city":"Pataskala",
    "sg:classifiers":[
        {
            "category":"Restaurant",
            "type":"Food & Drink"
        }
    ],
    "sg:phone":"+1 740 964 6925",
    "sg:postcode":"43062",
    "sg:province":"OH",
    "sg:tags":[
        "eating"
    ],
    "wof:name":"Super Wok",
    "wof:placetype":"venue"
},
  "geometry": {"coordinates":[-82.668293,40.004302],"type":"Point"}
}