{
  "type": "Feature",
  "properties": {
    "iso:country":"US",
    "sg:address":"1560 Longwood Dr NE",
    "sg:city":"Lancaster",
    "sg:classifiers":[
        {
            "category":"Organizations",
            "subcategory":"Community Association",
            "type":"Services"
        }
    ],
    "sg:phone":"+1 740 654 1075",
    "sg:postcode":"43130",
    "sg:province":"OH",
    "wof:name":"Local Chapter of Lancaster",
    "wof:placetype":"venue"
},
  "geometry": {"coordinates":[-82.57761000000001,39.746266],"type":"Point"}
}