{
  "type": "Feature",
  "properties": {
    "addr:full":"2775 Maysville Pike Zanesville OH 43701",
    "addr:housenumber":"2775",
    "addr:postcode":"43701",
    "addr:street":"Maysville Pike",
    "iso:country":"US",
    "sg:address":"2775 Maysville Pike",
    "sg:city":"Zanesville",
    "sg:classifiers":[
        {
            "category":"Banks & Credit Unions",
            "subcategory":"Bank",
            "type":"Services"
        }
    ],
    "sg:phone":"+1 740 450 2265",
    "sg:postcode":"43701",
    "sg:province":"OH",
    "sg:website":"www.nvboh.com",
    "wof:name":"North Valley Bank",
    "wof:placetype":"venue"
},
  "geometry": {"coordinates":[-82.042192,39.894581],"type":"Point"}
}