{
  "type": "Feature",
  "properties": {
    "addr:full":"2110 State Rte 229 Ashley OH 43003",
    "addr:housenumber":"2110",
    "addr:postcode":"43003",
    "addr:street":"State Rte 229",
    "iso:country":"US",
    "sg:address":"2110 State Rte 229",
    "sg:city":"Ashley",
    "sg:classifiers":[
        {
            "category":"Freight",
            "type":"Transportation"
        }
    ],
    "sg:phone":"+1 740 524 2111",
    "sg:postcode":"43003",
    "sg:province":"OH",
    "sg:tags":[
        "commercial",
        "storage",
        "special"
    ],
    "wof:name":"229 Storage LLC",
    "wof:placetype":"venue"
},
  "geometry": {"coordinates":[-83.020174,40.4153],"type":"Point"}
}