{
  "type": "Feature",
  "properties": {
    "iso:country":"US",
    "sg:address":"301 E Sandusky St",
    "sg:city":"Findlay",
    "sg:classifiers":[
        {
            "category":"Social Services",
            "type":"Services"
        }
    ],
    "sg:phone":"+1 419 423 9133",
    "sg:postcode":"45840",
    "sg:province":"OH",
    "sg:tags":[
        "counselor",
        "marriage",
        "family"
    ],
    "wof:name":"Lighthouse Counseling Svc",
    "wof:placetype":"venue"
},
  "geometry": {"coordinates":[-83.64684099999999,41.037009],"type":"Point"}
}