{
  "type": "Feature",
  "properties": {
    "iso:country":"US",
    "sg:address":"9433 Olde Eight Rd",
    "sg:city":"Northfield",
    "sg:classifiers":[
        {
            "category":"Retail",
            "subcategory":"Animal Services",
            "type":"Services"
        }
    ],
    "sg:phone":"+1 330 468 0961",
    "sg:postcode":"44067",
    "sg:province":"OH",
    "sg:tags":[
        "pet",
        "training"
    ],
    "wof:name":"Reward Dog Training & Act Ctr",
    "wof:placetype":"venue"
},
  "geometry": {"coordinates":[-81.53892399999999,41.318192],"type":"Point"}
}