{
  "type": "Feature",
  "properties": {
    "addr:full":"704 Lynnwood Dr Minerva OH 44657",
    "addr:housenumber":"704",
    "addr:postcode":"44657",
    "addr:street":"Lynnwood Dr",
    "iso:country":"US",
    "sg:address":"704 Lynnwood Dr",
    "sg:city":"Minerva",
    "sg:classifiers":[
        {
            "category":"Organizations",
            "subcategory":"Religious Organization",
            "type":"Services"
        }
    ],
    "sg:phone":"+1 330 868 7520",
    "sg:postcode":"44657",
    "sg:province":"OH",
    "sg:tags":[
        "church"
    ],
    "wof:name":"Open Door Tabernacle",
    "wof:placetype":"venue"
},
  "geometry": {"coordinates":[-81.096885,40.731295],"type":"Point"}
}