{
  "type": "Feature",
  "properties": {
    "iso:country":"US",
    "sg:address":"1074 Cayuga Trl SW",
    "sg:city":"Hartville",
    "sg:classifiers":[
        {
            "category":"Professional",
            "type":"Services"
        }
    ],
    "sg:phone":"+1 330 877 0911",
    "sg:postcode":"44632",
    "sg:province":"OH",
    "wof:name":"Wendy J Mann",
    "wof:placetype":"venue"
},
  "geometry": {"coordinates":[-81.33663199999999,40.951651],"type":"Point"}
}