{
  "type": "Feature",
  "properties": {
    "addr:full":"1030 Xenia Ave Yellow Springs OH 45387",
    "addr:postcode":"1030;45387",
    "addr:street":"Xenia Ave",
    "iso:country":"US",
    "sg:address":"1030 Xenia Ave",
    "sg:city":"Yellow Springs",
    "sg:classifiers":[
        {
            "category":"Health Services",
            "subcategory":"Doctor",
            "type":"Services"
        }
    ],
    "sg:phone":"+1 937 767 7731",
    "sg:postcode":"45387",
    "sg:province":"OH",
    "sg:tags":[
        "dentist"
    ],
    "wof:name":"Perfecting Smiles",
    "wof:placetype":"venue"
},
  "geometry": {"coordinates":[-83.894863,39.797304],"type":"Point"}
}