{
  "type": "Feature",
  "properties": {
    "addr:full": "162 Morris Ave Hamilton OH 45011",
    "addr:housenumber": "162",
    "addr:postcode": "45011",
    "addr:street": "Morris Ave",
    "iso:country": "US",
    "sg:address": "162 Morris Ave",
    "sg:city": "Hamilton",
    "sg:classifiers": [
      {
        "category": "Building \u0026 Trades",
        "subcategory": "Plumbing",
        "type": "Services"
      }
    ],
    "sg:phone": "+1 513 894 0370",
    "sg:postcode": "45011",
    "sg:province": "OH",
    "sg:tags": [
      "contractor"
    ],
    "wof:name": "Jones Heating \u0026 Cooling",
    "wof:placetype": "venue"
  },
  "geometry": {"coordinates":[-84.538618,39.434638],"type":"Point"}
}
