{
  "type": "Feature",
  "properties": {
    "iso:country":"US",
    "sg:address":"9484 Princeton Glendale Rd",
    "sg:city":"Hamilton",
    "sg:classifiers":[
        {
            "category":"Wholesale",
            "subcategory":"Hardware",
            "type":"Manufacturing & Wholesale Goods"
        }
    ],
    "sg:phone":"+1 513 874 1500",
    "sg:postcode":"45011",
    "sg:province":"OH",
    "sg:tags":[
        "steam",
        "specialty"
    ],
    "sg:website":"www.steamspecrepair.com",
    "wof:name":"Steam Specialties Repair Inc",
    "wof:placetype":"venue"
},
  "geometry": {"coordinates":[-84.46401,39.320438],"type":"Point"}
}