{
  "type": "Feature",
  "properties": {
    "addr:full": "9484 Princeton Glendale Rd Hamilton OH 45011",
    "addr:housenumber": "9484",
    "addr:postcode": "45011",
    "addr:street": "Princeton Glendale Rd",
    "iso:country": "US",
    "sg:address": "9484 Princeton Glendale Rd",
    "sg:city": "Hamilton",
    "sg:classifiers": [
      {
        "category": "Wholesale",
        "subcategory": "Hardware",
        "type": "Manufacturing \u0026 Wholesale Goods"
      }
    ],
    "sg:phone": "+1 513 874 1500",
    "sg:postcode": "45011",
    "sg:province": "OH",
    "sg:tags": [
      "steam",
      "specialty"
    ],
    "sg:website": "www.steamspecrepair.com",
    "wof:name": "Steam Specialties Repair Inc",
    "wof:placetype": "venue"
  },
  "geometry": {"coordinates":[-84.46401,39.320438],"type":"Point"}
}
