{
  "type": "Feature",
  "properties": {
    "addr:full":"302 W High St St Marys OH 45885",
    "addr:housenumber":"302",
    "addr:postcode":"45885",
    "addr:street":"W High St",
    "iso:country":"US",
    "sg:address":"302 W High St",
    "sg:city":"St Marys",
    "sg:classifiers":[
        {
            "category":"Organizations",
            "subcategory":"Religious Organization",
            "type":"Services"
        }
    ],
    "sg:phone":"+1 419 394 7276",
    "sg:postcode":"45885",
    "sg:province":"OH",
    "sg:tags":[
        "church"
    ],
    "wof:name":"Calvary Christian Fellowship",
    "wof:placetype":"venue"
},
  "geometry": {"coordinates":[-84.390986,40.543304],"type":"Point"}
}