{
  "type": "Feature",
  "properties": {
    "addr:full":"5100 Springfield St Dayton OH 45431",
    "addr:housenumber":"5100",
    "addr:postcode":"45431",
    "addr:street":"Springfield St",
    "iso:country":"US",
    "sg:address":"5100 Springfield St",
    "sg:city":"Dayton",
    "sg:classifiers":[
        {
            "category":"Professional",
            "subcategory":"Computer Services",
            "type":"Services"
        }
    ],
    "sg:phone":"+1 937 259 0074",
    "sg:postcode":"45431",
    "sg:province":"OH",
    "sg:tags":[
        "consultant",
        "designer"
    ],
    "sg:website":"www.stginc.com",
    "wof:name":"Stg Inc",
    "wof:placetype":"venue"
},
  "geometry": {"coordinates":[-84.118025,39.783149],"type":"Point"}
}