{
  "type": "Feature",
  "properties": {
    "addr:full": "1500 Rathmell Rd Lockbourne OH 43137",
    "addr:housenumber": "1500",
    "addr:postcode": "43137",
    "addr:street": "Rathmell Rd",
    "iso:country": "US",
    "sg:address": "1500 Rathmell Rd",
    "sg:city": "Lockbourne",
    "sg:classifiers": [
      {
        "category": "Food \u0026 Beverages",
        "subcategory": "Candy",
        "type": "Retail Goods"
      }
    ],
    "sg:phone": "+1 614 491 7114",
    "sg:postcode": "43137",
    "sg:province": "OH",
    "wof:name": "Heavenly Candies",
    "wof:placetype": "venue"
  },
  "geometry": {"coordinates":[-82.961435,39.860847],"type":"Point"}
}
