{
  "type": "Feature",
  "properties": {
    "iso:country":"US",
    "sg:address":"899 Moe Dr",
    "sg:city":"Akron",
    "sg:classifiers":[
        {
            "category":"Building & Trades",
            "subcategory":"Cleaning & Sanitation",
            "type":"Services"
        }
    ],
    "sg:phone":"+1 330 630 2844",
    "sg:postcode":"44310",
    "sg:province":"OH",
    "sg:tags":[
        "janitor"
    ],
    "wof:name":"Rhiel Supply Co",
    "wof:placetype":"venue"
},
  "geometry": {"coordinates":[-81.48428800000001,41.107669],"type":"Point"}
}