{
  "type": "Feature",
  "properties": {
    "addr:full":"5440 W Central Ave Toledo OH 43615",
    "addr:housenumber":"5440",
    "addr:postcode":"43615",
    "addr:street":"W Central Ave",
    "iso:country":"US",
    "sg:address":"5440 W Central Ave",
    "sg:city":"Toledo",
    "sg:classifiers":[
        {
            "category":"Retail",
            "subcategory":"Car Wash",
            "type":"Services"
        }
    ],
    "sg:phone":"+1 419 536 7540",
    "sg:postcode":"43615",
    "sg:province":"OH",
    "sg:tags":[
        "polishing",
        "washing"
    ],
    "wof:name":"Expresso Car Wash",
    "wof:placetype":"venue"
},
  "geometry": {"coordinates":[-83.673844,41.676652],"type":"Point"}
}