{
  "type": "Feature",
  "properties": {
    "iso:country":"US",
    "sg:address":"207 E 4th St",
    "sg:city":"Greenville",
    "sg:classifiers":[
        {
            "category":"Social Services",
            "type":"Services"
        }
    ],
    "sg:phone":"+1 937 547 1272",
    "sg:postcode":"45331",
    "sg:province":"OH",
    "sg:tags":[
        "organization",
        "welfare"
    ],
    "wof:name":"United Way",
    "wof:placetype":"venue"
},
  "geometry": {"coordinates":[-84.62994500000001,40.101658],"type":"Point"}
}