{
  "type": "Feature",
  "properties": {
    "addr:full": "3865 Breck Ave Grove City OH 43123",
    "addr:housenumber": "3865",
    "addr:postcode": "43123",
    "addr:street": "Breck Ave",
    "iso:country": "US",
    "sg:address": "3865 Breck Ave",
    "sg:city": "Grove City",
    "sg:classifiers": [
      {
        "category": "Sports \u0026 Exercise",
        "subcategory": "Bowling",
        "type": "Entertainment"
      }
    ],
    "sg:phone": "+1 614 871 3499",
    "sg:postcode": "43123",
    "sg:province": "OH",
    "sg:tags": [
      "center"
    ],
    "wof:name": "Marvin D Bowling",
    "wof:placetype": "venue"
  },
  "geometry": {"coordinates":[-83.088308,39.886699],"type":"Point"}
}
