{
  "type": "Feature",
  "properties": {
    "iso:country":"US",
    "sg:address":"1951 Havemann Rd",
    "sg:city":"Celina",
    "sg:classifiers":[
        {
            "category":"Utilities",
            "subcategory":"Mobile Phone",
            "type":"Services"
        }
    ],
    "sg:phone":"+1 419 305 2100",
    "sg:postcode":"45822",
    "sg:province":"OH",
    "sg:tags":[
        "communication",
        "radiotelephone"
    ],
    "wof:name":"Verizon",
    "wof:placetype":"venue"
},
  "geometry": {"coordinates":[-84.540313,40.556845],"type":"Point"}
}