{
  "type": "Feature",
  "properties": {
    "iso:country":"US",
    "sg:address":"2391 Manchester Rd",
    "sg:city":"Akron",
    "sg:classifiers":[
        {
            "category":"Personal",
            "subcategory":"Beauty Salon",
            "type":"Services"
        }
    ],
    "sg:phone":"+1 330 745 2428",
    "sg:postcode":"44314",
    "sg:province":"OH",
    "wof:name":"Allusions",
    "wof:placetype":"venue"
},
  "geometry": {"coordinates":[-81.545255,41.034104],"type":"Point"}
}