{
  "type": "Feature",
  "properties": {
    "addr:full": "1607 Archwood Ln Toledo OH 43614",
    "addr:housenumber": "1607",
    "addr:postcode": "43614",
    "addr:street": "Archwood Ln",
    "iso:country": "US",
    "sg:address": "1607 Archwood Ln",
    "sg:city": "Toledo",
    "sg:classifiers": [
      {
        "category": "Restaurant",
        "type": "Food \u0026 Drink"
      }
    ],
    "sg:phone": "+1 419 389 9070",
    "sg:postcode": "43614",
    "sg:province": "OH",
    "wof:name": "Ragtime Ricks First Draught",
    "wof:placetype": "venue"
  },
  "geometry": {"coordinates":[-83.638819,41.609316],"type":"Point"}
}
