{
  "type": "Feature",
  "properties": {
    "addr:full":"96 Stadium Dr Tallmadge OH 44278",
    "addr:housenumber":"96",
    "addr:postcode":"44278",
    "addr:street":"Stadium Dr",
    "iso:country":"US",
    "sg:address":"96 Stadium Dr",
    "sg:city":"Tallmadge",
    "sg:classifiers":[
        {
            "category":"Building & Trades",
            "subcategory":"Cleaning & Sanitation",
            "type":"Services"
        }
    ],
    "sg:phone":"+1 330 633 9905",
    "sg:postcode":"44278",
    "sg:province":"OH",
    "sg:tags":[
        "janitor"
    ],
    "wof:name":"Lease Cleaning Svc Inc",
    "wof:placetype":"venue"
},
  "geometry": {"coordinates":[-81.443117,41.105237],"type":"Point"}
}