{
  "type": "Feature",
  "properties": {
    "addr:full": "309 Court Ave NW Canton OH 44702",
    "addr:housenumber": "309",
    "addr:postcode": "44702",
    "addr:street": "Court Ave Nw",
    "iso:country": "US",
    "sg:address": "309 Court Ave NW",
    "sg:city": "Canton",
    "sg:classifiers": [
      {
        "category": "Wholesale",
        "subcategory": "Fruits \u0026 Vegetables",
        "type": "Manufacturing \u0026 Wholesale Goods"
      }
    ],
    "sg:phone": "+1 330 455 9475",
    "sg:postcode": "44702",
    "sg:province": "OH",
    "wof:name": "Frank's Produce Inc",
    "wof:placetype": "venue"
  },
  "geometry": {"coordinates":[-81.374997,40.800691],"type":"Point"}
}
