{
  "type": "Feature",
  "properties": {
    "addr:full": "4336 Belden Village St NW Canton OH 44718",
    "addr:housenumber": "4336",
    "addr:postcode": "44718",
    "addr:street": "Belden Village St Nw",
    "iso:country": "US",
    "sg:address": "4336 Belden Village St NW",
    "sg:city": "Canton",
    "sg:classifiers": [
      {
        "category": "Shopping",
        "subcategory": "Clothing, Apparel, \u0026 Fashions",
        "type": "Retail Goods"
      }
    ],
    "sg:phone": "+1 330 966 0088",
    "sg:postcode": "44718",
    "sg:province": "OH",
    "sg:tags": [
      "shop",
      "specialty"
    ],
    "wof:name": "Joan Bari",
    "wof:placetype": "venue"
  },
  "geometry": {"coordinates":[-81.430529,40.855898],"type":"Point"}
}
