{
  "type": "Feature",
  "properties": {
    "addr:full": "710 Anthony St Cleveland OH 44143",
    "addr:housenumber": "710",
    "addr:postcode": "44143",
    "addr:street": "Anthony St",
    "iso:country": "US",
    "sg:address": "710 Anthony St",
    "sg:city": "Cleveland",
    "sg:classifiers": [
      {
        "category": "Shopping",
        "subcategory": "Computers \u0026 Home Electronics",
        "type": "Retail Goods"
      }
    ],
    "sg:phone": "+1 216 691 9737",
    "sg:postcode": "44143",
    "sg:province": "OH",
    "sg:tags": [
      "software"
    ],
    "wof:name": "Importech",
    "wof:placetype": "venue"
  },
  "geometry": {"coordinates":[-81.506599,41.540504],"type":"Point"}
}
