{
  "type": "Feature",
  "properties": {
    "addr:full":"26899 Chagrin Blvd Cleveland OH 44122",
    "addr:housenumber":"26899",
    "addr:postcode":"44122",
    "addr:street":"Chagrin Blvd",
    "iso:country":"US",
    "sg:address":"26899 Chagrin Blvd",
    "sg:city":"Cleveland",
    "sg:classifiers":[
        {
            "category":"Restaurant",
            "type":"Food & Drink"
        }
    ],
    "sg:phone":"+1 216 595 0808",
    "sg:postcode":"44122",
    "sg:province":"OH",
    "sg:tags":[
        "steak"
    ],
    "wof:name":"Capital City Restaurants Inc",
    "wof:placetype":"venue"
},
  "geometry": {"coordinates":[-81.489126,41.46281],"type":"Point"}
}