{
  "type": "Feature",
  "properties": {
    "iso:country":"US",
    "sg:address":"215 Burkhardt Ave",
    "sg:city":"Dayton",
    "sg:classifiers":[
        {
            "category":"Recreation",
            "type":"Entertainment"
        }
    ],
    "sg:phone":"+1 937 333 7985",
    "sg:postcode":"45403",
    "sg:province":"OH",
    "sg:tags":[
        "center"
    ],
    "wof:name":"Dayton Burkhardt Ctr",
    "wof:placetype":"venue"
},
  "geometry": {"coordinates":[-84.15154099999999,39.761195],"type":"Point"}
}