{
  "type": "Feature",
  "properties": {
    "iso:country":"US",
    "sg:address":"413 N High St",
    "sg:city":"Cortland",
    "sg:classifiers":[
        {
            "category":"Sports & Exercise",
            "subcategory":"Golf",
            "type":"Entertainment"
        }
    ],
    "sg:phone":"+1 330 637 8208",
    "sg:postcode":"44410",
    "sg:province":"OH",
    "sg:tags":[
        "course",
        "public"
    ],
    "wof:name":"Nelson Ledges Road Course LLC",
    "wof:placetype":"venue"
},
  "geometry": {"coordinates":[-80.723608,41.338558],"type":"Point"}
}