{
  "type": "Feature",
  "properties": {
    "addr:full": "175 Montrose West Ave Copley OH 44321",
    "addr:housenumber": "175",
    "addr:postcode": "44321",
    "addr:street": "Montrose West Ave",
    "iso:country": "US",
    "sg:address": "175 Montrose West Ave",
    "sg:city": "Copley",
    "sg:classifiers": [
      {
        "category": "Professional",
        "subcategory": "Management \u0026 Consulting",
        "type": "Services"
      }
    ],
    "sg:phone": "+1 330 668 3500",
    "sg:postcode": "44321",
    "sg:province": "OH",
    "sg:tags": [
      "marketing",
      "consultant"
    ],
    "wof:name": "Omada Group",
    "wof:placetype": "venue"
  },
  "geometry": {"coordinates":[-81.653403,41.131387],"type":"Point"}
}
