{
  "type": "Feature",
  "properties": {
    "addr:full": "20282 Hannan Pkwy Cleveland OH 44146",
    "addr:housenumber": "20282",
    "addr:postcode": "44146",
    "addr:street": "Hannan Pkwy",
    "iso:country": "US",
    "sg:address": "20282 Hannan Pkwy",
    "sg:city": "Cleveland",
    "sg:classifiers": [
      {
        "category": "Shopping",
        "type": "Retail Goods"
      }
    ],
    "sg:phone": "+1 440 232 6570",
    "sg:postcode": "44146",
    "sg:province": "OH",
    "sg:tags": [
      "dry",
      "ice"
    ],
    "wof:name": "Homecity Ice Co",
    "wof:placetype": "venue"
  },
  "geometry": {"coordinates":[-81.531812,41.364495],"type":"Point"}
}
