{
  "type": "Feature",
  "properties": {
    "addr:full": "301 E Stroop Rd Dayton OH 45429",
    "addr:housenumber": "301",
    "addr:postcode": "45429",
    "addr:street": "E Stroop Rd",
    "iso:country": "US",
    "sg:address": "301 E Stroop Rd",
    "sg:city": "Dayton",
    "sg:classifiers": [
      {
        "category": "Wholesale",
        "subcategory": "Machinery \u0026 Supplies",
        "type": "Manufacturing \u0026 Wholesale Goods"
      }
    ],
    "sg:phone": "+1 937 293 5330",
    "sg:postcode": "45429",
    "sg:province": "OH",
    "sg:tags": [
      "tool"
    ],
    "wof:name": "E M Wick \u0026 Sons Inc",
    "wof:placetype": "venue"
  },
  "geometry": {"coordinates":[-84.163378,39.68944],"type":"Point"}
}
