{
  "type": "Feature",
  "properties": {
    "addr:full": "101 E Main St Scio OH 43988",
    "addr:housenumber": "101",
    "addr:postcode": "43988",
    "addr:street": "E Main St",
    "iso:country": "US",
    "sg:address": "101 E Main St",
    "sg:city": "Scio",
    "sg:classifiers": [
      {
        "category": "Food \u0026 Beverages",
        "subcategory": "Groceries \u0026 Convenience Stores",
        "type": "Retail Goods"
      }
    ],
    "sg:phone": "+1 740 945 0214",
    "sg:postcode": "43988",
    "sg:province": "OH",
    "wof:name": "Dairy Mart",
    "wof:placetype": "venue"
  },
  "geometry": {"coordinates":[-81.085354,40.396933],"type":"Point"}
}
