{
  "type": "Feature",
  "properties": {
    "addr:full": "444 N Hawkins Ave Akron OH 44313",
    "addr:housenumber": "444",
    "addr:postcode": "44313",
    "addr:street": "N Hawkins Ave",
    "iso:country": "US",
    "sg:address": "444 N Hawkins Ave",
    "sg:city": "Akron",
    "sg:classifiers": [
      {
        "category": "Social Services",
        "subcategory": "Child Care",
        "type": "Services"
      }
    ],
    "sg:phone": "+1 330 867 4311",
    "sg:postcode": "44313",
    "sg:province": "OH",
    "sg:tags": [
      "kindergarten",
      "academic",
      "school"
    ],
    "wof:name": "Woodland Preschool",
    "wof:placetype": "venue"
  },
  "geometry": {"coordinates":[-81.569994,41.120398],"type":"Point"}
}
