{
  "type": "Feature",
  "properties": {
    "iso:country":"US",
    "sg:address":"444 N Hawkins Ave",
    "sg:city":"Akron",
    "sg:classifiers":[
        {
            "category":"Social Services",
            "subcategory":"Child Care",
            "type":"Services"
        }
    ],
    "sg:phone":"+1 330 867 4311",
    "sg:postcode":"44313",
    "sg:province":"OH",
    "sg:tags":[
        "kindergarten",
        "academic",
        "school"
    ],
    "wof:name":"Woodland Preschool",
    "wof:placetype":"venue"
},
  "geometry": {"coordinates":[-81.56999399999999,41.120398],"type":"Point"}
}