{
  "type": "Feature",
  "properties": {
    "iso:country":"US",
    "sg:address":"3240 Homeward Way",
    "sg:city":"Fairfield",
    "sg:classifiers":[
        {
            "category":"Recreation",
            "subcategory":"Marina",
            "type":"Entertainment"
        }
    ],
    "sg:phone":"+1 513 874 7676",
    "sg:postcode":"45014",
    "sg:province":"OH",
    "sg:tags":[
        "operation"
    ],
    "wof:name":"Bains Anchor Marine Inc",
    "wof:placetype":"venue"
},
  "geometry": {"coordinates":[-84.50885599999999,39.331745],"type":"Point"}
}