{
  "type": "Feature",
  "properties": {
    "iso:country":"US",
    "sg:address":"957 Ironwood Rd",
    "sg:city":"Akron",
    "sg:classifiers":[
        {
            "category":"Food & Beverages",
            "subcategory":"Bakery",
            "type":"Retail Goods"
        }
    ],
    "sg:phone":"+1 330 773 7110",
    "sg:postcode":"44306",
    "sg:province":"OH",
    "sg:tags":[
        "baker"
    ],
    "wof:name":"Nita's Cake Shop",
    "wof:placetype":"venue"
},
  "geometry": {"coordinates":[-81.491445,41.012026],"type":"Point"}
}