{
  "type": "Feature",
  "properties": {
    "iso:country":"US",
    "sg:address":"60 E Broad St",
    "sg:city":"Columbus",
    "sg:classifiers":[
        {
            "category":"Professional",
            "subcategory":"Accounting & Tax Preparation",
            "type":"Services"
        }
    ],
    "sg:phone":"+1 614 461 4177",
    "sg:postcode":"43215",
    "sg:province":"OH",
    "sg:tags":[
        "consultant"
    ],
    "wof:name":"Levin Driscoll & Fleeter",
    "wof:placetype":"venue"
},
  "geometry": {"coordinates":[-82.998586,39.962503],"type":"Point"}
}