{
  "type": "Feature",
  "properties": {
    "addr:full": "9831 State Rte 164 Amsterdam OH 43903",
    "addr:housenumber": "9831",
    "addr:postcode": "43903",
    "addr:street": "State Rte 164",
    "iso:country": "US",
    "sg:address": "9831 State Rte 164",
    "sg:city": "Amsterdam",
    "sg:classifiers": [
      {
        "category": "Sports \u0026 Exercise",
        "subcategory": "Bowling",
        "type": "Entertainment"
      }
    ],
    "sg:phone": "+1 740 543 3500",
    "sg:postcode": "43903",
    "sg:province": "OH",
    "sg:tags": [
      "center"
    ],
    "wof:name": "Garson Bowling Lanes",
    "wof:placetype": "venue"
  },
  "geometry": {"coordinates":[-80.918492,40.478904],"type":"Point"}
}
