{
  "type": "Feature",
  "properties": {
    "iso:country":"US",
    "sg:address":"270 W Main St",
    "sg:city":"Batavia",
    "sg:classifiers":[
        {
            "category":"Government",
            "subcategory":"Office",
            "type":"Public Place"
        }
    ],
    "sg:phone":"+1 513 732 7108",
    "sg:postcode":"45103",
    "sg:province":"OH",
    "wof:name":"Clermont County Common Pleas",
    "wof:placetype":"venue"
},
  "geometry": {"coordinates":[-84.18408599999999,39.081259],"type":"Point"}
}