{
  "type": "Feature",
  "properties": {
    "addr:full": "270 W Main St Batavia OH 45103",
    "addr:housenumber": "270",
    "addr:postcode": "45103",
    "addr:street": "W Main St",
    "iso:country": "US",
    "sg:address": "270 W Main St",
    "sg:city": "Batavia",
    "sg:classifiers": [
      {
        "category": "Government",
        "subcategory": "Office",
        "type": "Public Place"
      }
    ],
    "sg:phone": "+1 513 732 7108",
    "sg:postcode": "45103",
    "sg:province": "OH",
    "wof:name": "Clermont County Common Pleas",
    "wof:placetype": "venue"
  },
  "geometry": {"coordinates":[-84.184086,39.081259],"type":"Point"}
}
