{
  "type": "Feature",
  "properties": {
    "iso:country":"US",
    "sg:address":"3816 Lincoln Way E",
    "sg:city":"Massillon",
    "sg:classifiers":[
        {
            "category":"Bars & Pubs",
            "type":"Food & Drink"
        }
    ],
    "sg:phone":"+1 330 477 0985",
    "sg:postcode":"44646",
    "sg:province":"OH",
    "sg:tags":[
        "drinking"
    ],
    "wof:name":"Fireside Lounge",
    "wof:placetype":"venue"
},
  "geometry": {"coordinates":[-81.46024800000001,40.793922],"type":"Point"}
}