{
  "type": "Feature",
  "properties": {
    "addr:full": "3800 Osage St Stow OH 44224",
    "addr:housenumber": "3800",
    "addr:postcode": "44224",
    "addr:street": "Osage St",
    "iso:country": "US",
    "sg:address": "3800 Osage St",
    "sg:city": "Stow",
    "sg:classifiers": [
      {
        "category": "Shopping",
        "subcategory": "Gifts \u0026 Souvenirs",
        "type": "Retail Goods"
      }
    ],
    "sg:phone": "+1 330 990 8008",
    "sg:postcode": "44224",
    "sg:province": "OH",
    "sg:tags": [
      "basket",
      "parcel"
    ],
    "wof:name": "Baskets By Donna",
    "wof:placetype": "venue"
  },
  "geometry": {"coordinates":[-81.423345,41.162783],"type":"Point"}
}
