{
  "type": "Feature",
  "properties": {
    "addr:full": "437 W Main St Cumberland OH 43732",
    "addr:housenumber": "437",
    "addr:postcode": "43732",
    "addr:street": "W Main St",
    "iso:country": "US",
    "sg:address": "437 W Main St",
    "sg:city": "Cumberland",
    "sg:classifiers": [
      {
        "category": "Organizations",
        "subcategory": "Religious Organization",
        "type": "Services"
      }
    ],
    "sg:phone": "+1 740 638 2061",
    "sg:postcode": "43732",
    "sg:province": "OH",
    "sg:tags": [
      "church"
    ],
    "wof:name": "Cumberland United Mthdst Chr",
    "wof:placetype": "venue"
  },
  "geometry": {"coordinates":[-81.657607,39.852033],"type":"Point"}
}
