{
  "type": "Feature",
  "properties": {
    "iso:country":"US",
    "sg:address":"3601 Carnegie Ave",
    "sg:city":"Cleveland",
    "sg:classifiers":[
        {
            "category":"Retail",
            "subcategory":"Auto Repair",
            "type":"Services"
        }
    ],
    "sg:phone":"+1 216 391 9995",
    "sg:postcode":"44115",
    "sg:province":"OH",
    "sg:tags":[
        "body",
        "repairing",
        "painting",
        "automobile"
    ],
    "wof:name":"Crown Auto Body",
    "wof:placetype":"venue"
},
  "geometry": {"coordinates":[-81.662239,41.500431],"type":"Point"}
}