{
  "type": "Feature",
  "properties": {
    "addr:full":"7790 Cooper Rd Cincinnati OH 45242",
    "addr:housenumber":"7790",
    "addr:postcode":"45242",
    "addr:street":"Cooper Rd",
    "iso:country":"US",
    "sg:address":"7790 Cooper Rd",
    "sg:city":"Cincinnati",
    "sg:classifiers":[
        {
            "category":"Organizations",
            "subcategory":"Community Association",
            "type":"Services"
        }
    ],
    "sg:phone":"+1 513 793 6602",
    "sg:postcode":"45242",
    "sg:province":"OH",
    "sg:tags":[
        "fraternal"
    ],
    "wof:name":"Masonic Lodge",
    "wof:placetype":"venue"
},
  "geometry": {"coordinates":[-84.35503199999999,39.226642],"type":"Point"}
}