{
  "type": "Feature",
  "properties": {
    "addr:full": "10411 Silver Maple Ct Dayton OH 45458",
    "addr:housenumber": "10411",
    "addr:postcode": "45458",
    "addr:street": "Silver Maple Ct",
    "iso:country": "US",
    "sg:address": "10411 Silver Maple Ct",
    "sg:city": "Dayton",
    "sg:classifiers": [
      {
        "category": "Banks \u0026 Credit Unions",
        "subcategory": "Bank",
        "type": "Services"
      }
    ],
    "sg:phone": "+1 937 885 1100",
    "sg:postcode": "45458",
    "sg:province": "OH",
    "sg:tags": [
      "equipment"
    ],
    "wof:name": "Paragon Financial Services",
    "wof:placetype": "venue"
  },
  "geometry": {"coordinates":[-84.124323,39.590488],"type":"Point"}
}
