{
  "type": "Feature",
  "properties": {
    "addr:full":"139 S Main St Prospect OH 43342",
    "addr:housenumber":"139",
    "addr:postcode":"43342",
    "addr:street":"S Main St",
    "iso:country":"US",
    "sg:address":"139 S Main St",
    "sg:city":"Prospect",
    "sg:classifiers":[
        {
            "category":"Utilities",
            "subcategory":"Electric",
            "type":"Services"
        }
    ],
    "sg:phone":"+1 740 494 2115",
    "sg:postcode":"43342",
    "sg:province":"OH",
    "sg:tags":[
        "company"
    ],
    "wof:name":"Prospect Municipal Electric",
    "wof:placetype":"venue"
},
  "geometry": {"coordinates":[-83.189386,40.449832],"type":"Point"}
}