{
  "type": "Feature",
  "properties": {
    "iso:country":"US",
    "sg:address":"350 Loveland Madeira Rd",
    "sg:city":"Loveland",
    "sg:classifiers":[
        {
            "category":"Personal",
            "subcategory":"Barber",
            "type":"Services"
        }
    ],
    "sg:phone":"+1 513 683 1434",
    "sg:postcode":"45140",
    "sg:province":"OH",
    "sg:tags":[
        "shop"
    ],
    "wof:name":"Curt's Barber Shop",
    "wof:placetype":"venue"
},
  "geometry": {"coordinates":[-84.267015,39.265493],"type":"Point"}
}