{
  "type": "Feature",
  "properties": {
    "addr:full":"911 S 2nd St Ripley OH 45167",
    "addr:housenumber":"911",
    "addr:postcode":"45167",
    "addr:street":"S 2Nd St",
    "iso:country":"US",
    "sg:address":"911 S 2nd St",
    "sg:city":"Ripley",
    "sg:classifiers":[
        {
            "category":"Food & Beverages",
            "subcategory":"Groceries & Convenience Stores",
            "type":"Retail Goods"
        }
    ],
    "sg:phone":"+1 937 392 1107",
    "sg:postcode":"45167",
    "sg:province":"OH",
    "wof:name":"Ripley First Stop",
    "wof:placetype":"venue"
},
  "geometry": {"coordinates":[-83.837194,38.732036],"type":"Point"}
}