{
  "type": "Feature",
  "properties": {
    "addr:full": "10601 Glendale Rd Cincinnati OH 45215",
    "addr:housenumber": "10601",
    "addr:postcode": "45215",
    "addr:street": "Glendale Rd",
    "iso:country": "US",
    "sg:address": "10601 Glendale Rd",
    "sg:city": "Cincinnati",
    "sg:classifiers": [
      {
        "category": "Wholesale",
        "subcategory": "Machinery \u0026 Supplies",
        "type": "Manufacturing \u0026 Wholesale Goods"
      }
    ],
    "sg:phone": "+1 513 771 1952",
    "sg:postcode": "45215",
    "sg:province": "OH",
    "sg:website": "www.mohawkmachinery.com",
    "wof:name": "Mohawk Machinery Inc",
    "wof:placetype": "venue"
  },
  "geometry": {"coordinates":[-84.463827,39.260871],"type":"Point"}
}
