{
  "type": "Feature",
  "properties": {
    "addr:full": "1429 Lenox-New Lyme Rd Jefferson OH 44047",
    "addr:housenumber": "1429",
    "addr:postcode": "44047",
    "addr:street": "Lenox-New Lyme Rd",
    "iso:country": "US",
    "sg:address": "1429 Lenox-New Lyme Rd",
    "sg:city": "Jefferson",
    "sg:classifiers": [
      {
        "category": "Shopping",
        "subcategory": "Clothing, Apparel, \u0026 Fashions",
        "type": "Retail Goods"
      }
    ],
    "sg:phone": "+1 440 576 3981",
    "sg:postcode": "44047",
    "sg:province": "OH",
    "wof:name": "Just For You Plus \u0026 Minus",
    "wof:placetype": "venue"
  },
  "geometry": {"coordinates":[-80.764336,41.712812],"type":"Point"}
}
