{
  "type": "Feature",
  "properties": {
    "iso:country":"US",
    "sg:address":"1429 Lenox-New Lyme Rd",
    "sg:city":"Jefferson",
    "sg:classifiers":[
        {
            "category":"Shopping",
            "subcategory":"Clothing, Apparel, & Fashions",
            "type":"Retail Goods"
        }
    ],
    "sg:phone":"+1 440 576 3981",
    "sg:postcode":"44047",
    "sg:province":"OH",
    "wof:name":"Just For You Plus & Minus",
    "wof:placetype":"venue"
},
  "geometry": {"coordinates":[-80.764336,41.712812],"type":"Point"}
}