{
  "type": "Feature",
  "properties": {
    "addr:full":"986 Belvedere Dr Lebanon OH 45036",
    "addr:housenumber":"986",
    "addr:postcode":"45036",
    "addr:street":"Belvedere Dr",
    "iso:country":"US",
    "sg:address":"986 Belvedere Dr",
    "sg:city":"Lebanon",
    "sg:classifiers":[
        {
            "category":"Health Services",
            "subcategory":"Health Practitioner",
            "type":"Services"
        }
    ],
    "sg:phone":"+1 513 934 1226",
    "sg:postcode":"45036",
    "sg:province":"OH",
    "sg:tags":[
        "occupational",
        "therapist"
    ],
    "wof:name":"Therapy Learning Ctr",
    "wof:placetype":"venue"
},
  "geometry": {"coordinates":[-84.18677,39.449945],"type":"Point"}
}