{
  "type": "Feature",
  "properties": {
    "iso:country":"US",
    "sg:address":"20 Executive Center Dr",
    "sg:city":"Chillicothe",
    "sg:classifiers":[
        {
            "category":"Personal",
            "subcategory":"Tanning Parlor",
            "type":"Services"
        }
    ],
    "sg:phone":"+1 740 779 1135",
    "sg:postcode":"45601",
    "sg:province":"OH",
    "sg:tags":[
        "salon"
    ],
    "wof:name":"Tropical Tan & Treats",
    "wof:placetype":"venue"
},
  "geometry": {"coordinates":[-83.036946,39.343781],"type":"Point"}
}