{
  "type": "Feature",
  "properties": {
    "addr:full": "1855 Crestview Dr Orrville OH 44667",
    "addr:housenumber": "1855",
    "addr:postcode": "44667",
    "addr:street": "Crestview Dr",
    "iso:country": "US",
    "sg:address": "1855 Crestview Dr",
    "sg:city": "Orrville",
    "sg:classifiers": [
      {
        "category": "Social Services",
        "subcategory": "Child Care",
        "type": "Services"
      }
    ],
    "sg:phone": "+1 330 682 8765",
    "sg:postcode": "44667",
    "sg:province": "OH",
    "wof:name": "Head Start",
    "wof:placetype": "venue"
  },
  "geometry": {"coordinates":[-81.789733,40.83929],"type":"Point"}
}
