{
  "type": "Feature",
  "properties": {
    "addr:full":"947 W Galbraith Rd Cincinnati OH 45231",
    "addr:housenumber":"947",
    "addr:postcode":"45231",
    "addr:street":"W Galbraith Rd",
    "iso:country":"US",
    "sg:address":"947 W Galbraith Rd",
    "sg:city":"Cincinnati",
    "sg:classifiers":[
        {
            "category":"Insurance",
            "subcategory":"Insurance Agent",
            "type":"Services"
        }
    ],
    "sg:phone":"+1 513 522 1544",
    "sg:postcode":"45231",
    "sg:province":"OH",
    "wof:name":"Atkins Insurance Inc",
    "wof:placetype":"venue"
},
  "geometry": {"coordinates":[-84.524393,39.215881],"type":"Point"}
}