{
  "type": "Feature",
  "properties": {
    "addr:full": "1199 Delaware Ave Marion OH 43302",
    "addr:housenumber": "1199",
    "addr:postcode": "43302",
    "addr:street": "Delaware Ave",
    "iso:country": "US",
    "sg:address": "1199 Delaware Ave",
    "sg:city": "Marion",
    "sg:classifiers": [
      {
        "category": "Banks \u0026 Credit Unions",
        "subcategory": "Bank",
        "type": "Services"
      }
    ],
    "sg:phone": "+1 740 223 3704",
    "sg:postcode": "43302",
    "sg:province": "OH",
    "sg:tags": [
      "loan",
      "real estate"
    ],
    "wof:name": "Three C Credit Group",
    "wof:placetype": "venue"
  },
  "geometry": {"coordinates":[-83.121522,40.567657],"type":"Point"}
}
