{
  "type": "Feature",
  "properties": {
    "addr:full": "7863 Beechmont Ave Cincinnati OH 45255",
    "addr:postcode": "7863;45255",
    "addr:street": "Beechmont Ave",
    "iso:country": "US",
    "sg:address": "7863 Beechmont Ave",
    "sg:city": "Cincinnati",
    "sg:classifiers": [
      {
        "category": "Restaurant",
        "type": "Food \u0026 Drink"
      }
    ],
    "sg:phone": "+1 513 474 0386",
    "sg:postcode": "45255",
    "sg:province": "OH",
    "sg:tags": [
      "eating"
    ],
    "sg:website": "www.maliaskitchen.com",
    "wof:name": "Malias Kitchen",
    "wof:placetype": "venue"
  },
  "geometry": {"coordinates":[-84.338961,39.07261],"type":"Point"}
}
