{
  "type": "Feature",
  "properties": {
    "addr:full":"855 Cascade Dr Dayton OH 45431",
    "addr:housenumber":"855",
    "addr:postcode":"45431",
    "addr:street":"Cascade Dr",
    "iso:country":"US",
    "sg:address":"855 Cascade Dr",
    "sg:city":"Dayton",
    "sg:classifiers":[
        {
            "category":"Professional",
            "subcategory":"Management & Consulting",
            "type":"Services"
        }
    ],
    "sg:phone":"+1 937 258 2806",
    "sg:postcode":"45431",
    "sg:province":"OH",
    "sg:tags":[
        "retail",
        "direct",
        "sales"
    ],
    "wof:name":"Benjamin R Carpenter",
    "wof:placetype":"venue"
},
  "geometry": {"coordinates":[-84.10288799999999,39.753633],"type":"Point"}
}