{
  "type": "Feature",
  "properties": {
    "iso:country":"US",
    "sg:address":"3307 Herbert St",
    "sg:city":"Mogadore",
    "sg:classifiers":[
        {
            "category":"Manufacturing",
            "subcategory":"Wood Products",
            "type":"Manufacturing & Wholesale Goods"
        }
    ],
    "sg:phone":"+1 330 628 2447",
    "sg:postcode":"44260",
    "sg:province":"OH",
    "sg:tags":[
        "mfg"
    ],
    "wof:name":"Stakepuller Corp",
    "wof:placetype":"venue"
},
  "geometry": {"coordinates":[-81.411934,41.047131],"type":"Point"}
}