{
  "type": "Feature",
  "properties": {
    "iso:country":"US",
    "sg:address":"720 Griswold Rd",
    "sg:city":"Elyria",
    "sg:classifiers":[
        {
            "category":"Retail",
            "subcategory":"Car Wash",
            "type":"Services"
        }
    ],
    "sg:phone":"+1 440 324 7666",
    "sg:postcode":"44035",
    "sg:province":"OH",
    "sg:tags":[
        "polishing",
        "washing"
    ],
    "wof:name":"Ryko Car Wash",
    "wof:placetype":"venue"
},
  "geometry": {"coordinates":[-82.120807,41.400331],"type":"Point"}
}