{
  "type": "Feature",
  "properties": {
    "iso:country":"US",
    "sg:address":"328 S Main St",
    "sg:city":"Bowling Green",
    "sg:classifiers":[
        {
            "category":"Banks & Credit Unions",
            "subcategory":"Bank",
            "type":"Services"
        }
    ],
    "sg:phone":"+1 419 353 3223",
    "sg:postcode":"43402",
    "sg:province":"OH",
    "sg:tags":[
        "loan",
        "broker",
        "real estate"
    ],
    "wof:name":"Evans Home Loans Ltd",
    "wof:placetype":"venue"
},
  "geometry": {"coordinates":[-83.650481,41.371144],"type":"Point"}
}