{
  "type": "Feature",
  "properties": {
    "addr:full":"835 E 156th St Cleveland OH 44110",
    "addr:housenumber":"835",
    "addr:postcode":"44110",
    "addr:street":"E 156Th St",
    "iso:country":"US",
    "sg:address":"835 E 156th St",
    "sg:city":"Cleveland",
    "sg:classifiers":[
        {
            "category":"Building & Trades",
            "subcategory":"Construction",
            "type":"Services"
        }
    ],
    "sg:phone":"+1 216 253 0925",
    "sg:postcode":"44110",
    "sg:province":"OH",
    "wof:name":"Equi Construction Company",
    "wof:placetype":"venue"
},
  "geometry": {"coordinates":[-81.57192999999999,41.558196],"type":"Point"}
}