{
  "type": "Feature",
  "properties": {
    "iso:country":"US",
    "sg:address":"300 E River St",
    "sg:city":"Elyria",
    "sg:classifiers":[
        {
            "category":"Retail",
            "subcategory":"Repair Shop",
            "type":"Services"
        }
    ],
    "sg:phone":"+1 440 323 8459",
    "sg:postcode":"44035",
    "sg:province":"OH",
    "sg:tags":[
        "refinishing",
        "furniture"
    ],
    "wof:name":"Russell's Refinishing",
    "wof:placetype":"venue"
},
  "geometry": {"coordinates":[-82.09841,41.371173],"type":"Point"}
}