{
  "type": "Feature",
  "properties": {
    "addr:full": "210 W South Range Rd North Lima OH 44452",
    "addr:housenumber": "210",
    "addr:postcode": "44452",
    "addr:street": "W South Range Rd",
    "iso:country": "US",
    "sg:address": "210 W South Range Rd",
    "sg:city": "North Lima",
    "sg:classifiers": [
      {
        "category": "Wholesale",
        "subcategory": "Electrical",
        "type": "Manufacturing \u0026 Wholesale Goods"
      }
    ],
    "sg:phone": "+1 330 549 9855",
    "sg:postcode": "44452",
    "sg:province": "OH",
    "sg:tags": [
      "light",
      "tube",
      "bulb"
    ],
    "wof:name": "All Bulbs",
    "wof:placetype": "venue"
  },
  "geometry": {"coordinates":[-80.660102,40.944104],"type":"Point"}
}
