{
  "type": "Feature",
  "properties": {
    "iso:country":"US",
    "sg:address":"210 W South Range Rd",
    "sg:city":"North Lima",
    "sg:classifiers":[
        {
            "category":"Wholesale",
            "subcategory":"Electrical",
            "type":"Manufacturing & Wholesale Goods"
        }
    ],
    "sg:phone":"+1 330 549 9855",
    "sg:postcode":"44452",
    "sg:province":"OH",
    "sg:tags":[
        "light",
        "tube",
        "bulb"
    ],
    "wof:name":"All Bulbs",
    "wof:placetype":"venue"
},
  "geometry": {"coordinates":[-80.66010199999999,40.944104],"type":"Point"}
}