{
  "type": "Feature",
  "properties": {
    "iso:country":"US",
    "sg:address":"200 W North Ave",
    "sg:city":"East Palestine",
    "sg:classifiers":[
        {
            "category":"Education",
            "subcategory":"School",
            "type":"Public Place"
        }
    ],
    "sg:phone":"+1 330 426 3355",
    "sg:postcode":"44413",
    "sg:province":"OH",
    "sg:tags":[
        "city",
        "district"
    ],
    "wof:name":"East Palestine City School Dst",
    "wof:placetype":"venue"
},
  "geometry": {"coordinates":[-80.54266200000001,40.838065],"type":"Point"}
}