{
  "type": "Feature",
  "properties": {
    "iso:country":"US",
    "sg:address":"17955 W 3rd St",
    "sg:city":"Elliston",
    "sg:classifiers":[
        {
            "category":"Organizations",
            "subcategory":"Religious Organization",
            "type":"Services"
        }
    ],
    "sg:phone":"+1 419 862 3417",
    "sg:postcode":"43432",
    "sg:province":"OH",
    "sg:tags":[
        "church"
    ],
    "wof:name":"Trinity United Church-Christ",
    "wof:placetype":"venue"
},
  "geometry": {"coordinates":[-83.279022,41.548202],"type":"Point"}
}