{
  "type": "Feature",
  "properties": {
    "iso:country":"US",
    "sg:address":"6000 Glenway Ave",
    "sg:city":"Cincinnati",
    "sg:classifiers":[
        {
            "category":"Shopping",
            "subcategory":"Department Store",
            "type":"Retail Goods"
        }
    ],
    "sg:phone":"+1 513 389 4396",
    "sg:postcode":"45211",
    "sg:province":"OH",
    "wof:name":"Sears Roebuck & Co",
    "wof:placetype":"venue"
},
  "geometry": {"coordinates":[-84.619193,39.142196],"type":"Point"}
}