{
  "type": "Feature",
  "properties": {
    "iso:country":"US",
    "sg:address":"335 W Benson Ave",
    "sg:city":"Cincinnati",
    "sg:classifiers":[
        {
            "category":"Shopping",
            "subcategory":"Clothing, Apparel, & Fashions",
            "type":"Retail Goods"
        }
    ],
    "sg:phone":"+1 513 761 1333",
    "sg:postcode":"45215",
    "sg:province":"OH",
    "sg:tags":[
        "lingerie"
    ],
    "wof:name":"Tickle Your Fancy",
    "wof:placetype":"venue"
},
  "geometry": {"coordinates":[-84.44562500000001,39.223612],"type":"Point"}
}