{
  "type": "Feature",
  "properties": {
    "addr:full": "16947 Twp Hwy 166 Arlington OH 45814",
    "addr:postcode": "16947;45814",
    "addr:street": "Twp Hwy 166",
    "iso:country": "US",
    "sg:address": "16947 Twp Hwy 166",
    "sg:city": "Arlington",
    "sg:phone": "+1 419 694 5341",
    "sg:postcode": "45814",
    "sg:province": "OH",
    "sg:tags": [
      "farm",
      "corn",
      "wheat",
      "soybean"
    ],
    "wof:name": "Richard Inbody",
    "wof:placetype": "venue"
  },
  "geometry": {"coordinates":[-83.557691,40.956632],"type":"Point"}
}
