{
  "type": "Feature",
  "properties": {
    "iso:country":"US",
    "sg:address":"31 Township Ave",
    "sg:city":"Cincinnati",
    "sg:classifiers":[
        {
            "category":"Shopping",
            "type":"Retail Goods"
        }
    ],
    "sg:phone":"+1 513 631 8080",
    "sg:postcode":"45216",
    "sg:province":"OH",
    "sg:tags":[
        "merchandise"
    ],
    "wof:name":"CB Radio of Cincinnati",
    "wof:placetype":"venue"
},
  "geometry": {"coordinates":[-84.485229,39.18378],"type":"Point"}
}