{
  "type": "Feature",
  "properties": {
    "addr:full":"5615 State Rte 45 Lisbon OH 44432",
    "addr:housenumber":"5615",
    "addr:postcode":"44432",
    "addr:street":"State Rte 45",
    "iso:country":"US",
    "sg:address":"5615 State Rte 45",
    "sg:city":"Lisbon",
    "sg:classifiers":[
        {
            "category":"Autos & Motor Vehicles",
            "subcategory":"Auto Supplies",
            "type":"Retail Goods"
        }
    ],
    "sg:phone":"+1 330 424 9413",
    "sg:postcode":"44432",
    "sg:province":"OH",
    "sg:tags":[
        "automotive",
        "parts"
    ],
    "wof:name":"Williams Ted H Enterprises",
    "wof:placetype":"venue"
},
  "geometry": {"coordinates":[-80.79827899999999,40.818851],"type":"Point"}
}