{
  "type": "Feature",
  "properties": {
    "iso:country":"US",
    "sg:address":"2600 Church Ave",
    "sg:city":"Cleveland",
    "sg:classifiers":[
        {
            "category":"Organizations",
            "subcategory":"Religious Organization",
            "type":"Services"
        }
    ],
    "sg:phone":"+1 216 781 5546",
    "sg:postcode":"44113",
    "sg:province":"OH",
    "sg:tags":[
        "church"
    ],
    "wof:name":"St John's Episcopal Church",
    "wof:placetype":"venue"
},
  "geometry": {"coordinates":[-81.70894699999999,41.489748],"type":"Point"}
}