{
  "type": "Feature",
  "properties": {
    "addr:full":"97 Karl St Berea OH 44017",
    "addr:housenumber":"97",
    "addr:postcode":"44017",
    "addr:street":"Karl St",
    "iso:country":"US",
    "sg:address":"97 Karl St",
    "sg:city":"Berea",
    "sg:classifiers":[
        {
            "category":"Building & Trades",
            "subcategory":"Landscaping Services",
            "type":"Services"
        }
    ],
    "sg:phone":"+1 440 234 4995",
    "sg:postcode":"44017",
    "sg:province":"OH",
    "sg:tags":[
        "landscape",
        "contractor"
    ],
    "wof:name":"Shuleva Landscape Co",
    "wof:placetype":"venue"
},
  "geometry": {"coordinates":[-81.871576,41.374046],"type":"Point"}
}