{
  "type": "Feature",
  "properties": {
    "iso:country":"US",
    "sg:address":"1374 Edendale St",
    "sg:city":"Cleveland",
    "sg:classifiers":[
        {
            "category":"Health Services",
            "subcategory":"Nursing And Care Facility",
            "type":"Services"
        }
    ],
    "sg:phone":"+1 216 381 9993",
    "sg:postcode":"44121",
    "sg:province":"OH",
    "sg:tags":[
        "intermediate"
    ],
    "wof:name":"Edendale House",
    "wof:placetype":"venue"
},
  "geometry": {"coordinates":[-81.542984,41.520758],"type":"Point"}
}