{
  "type": "Feature",
  "properties": {
    "addr:full": "501 S Green Rd Cleveland OH 44121",
    "addr:housenumber": "501",
    "addr:postcode": "44121",
    "addr:street": "S Green Rd",
    "iso:country": "US",
    "sg:address": "501 S Green Rd",
    "sg:city": "Cleveland",
    "sg:classifiers": [
      {
        "category": "Wholesale",
        "subcategory": "Hardware",
        "type": "Manufacturing \u0026 Wholesale Goods"
      }
    ],
    "sg:phone": "+1 216 291 8877",
    "sg:postcode": "44121",
    "sg:province": "OH",
    "sg:tags": [
      "plumbing",
      "fixture",
      "supply"
    ],
    "wof:name": "Becker Plumbing Supply Co Inc",
    "wof:placetype": "venue"
  },
  "geometry": {"coordinates":[-81.529793,41.541306],"type":"Point"}
}
