{
  "type": "Feature",
  "properties": {
    "addr:full":"10718 Lake Shore Blvd Cleveland OH 44108",
    "addr:housenumber":"10718",
    "addr:postcode":"44108",
    "addr:street":"Lake Shore Blvd",
    "iso:country":"US",
    "sg:address":"10718 Lake Shore Blvd",
    "sg:city":"Cleveland",
    "sg:classifiers":[
        {
            "category":"Wholesale",
            "subcategory":"Machinery & Supplies",
            "type":"Manufacturing & Wholesale Goods"
        },
        {
            "category":"Professional",
            "subcategory":"Management & Consulting",
            "type":"Services"
        }
    ],
    "sg:phone":"+1 216 268 5075",
    "sg:postcode":"44108",
    "sg:province":"OH",
    "sg:tags":[
        "fuel",
        "barbecue",
        "equipment"
    ],
    "wof:name":"NOI Management",
    "wof:placetype":"venue"
},
  "geometry": {"coordinates":[-81.61238400000001,41.548367],"type":"Point"}
}