{
  "type": "Feature",
  "properties": {
    "addr:full": "1800 S Burnett Rd Springfield OH 45505",
    "addr:housenumber": "1800",
    "addr:postcode": "45505",
    "addr:street": "S Burnett Rd",
    "iso:country": "US",
    "sg:address": "1800 S Burnett Rd",
    "sg:city": "Springfield",
    "sg:classifiers": [
      {
        "category": "Organizations",
        "subcategory": "Religious Organization",
        "type": "Services"
      }
    ],
    "sg:phone": "+1 937 322 3266",
    "sg:postcode": "45505",
    "sg:province": "OH",
    "wof:name": "Islamic Assn Of Miami Valley",
    "wof:placetype": "venue"
  },
  "geometry": {"coordinates":[-83.772262,39.898887],"type":"Point"}
}
