{
  "type": "Feature",
  "properties": {
    "addr:full":"5474 Starcrest Dr Cincinnati OH 45238",
    "addr:housenumber":"5474",
    "addr:postcode":"45238",
    "addr:street":"Starcrest Dr",
    "iso:country":"US",
    "sg:address":"5474 Starcrest Dr",
    "sg:city":"Cincinnati",
    "sg:classifiers":[
        {
            "category":"Insurance",
            "subcategory":"Insurance Agent",
            "type":"Services"
        }
    ],
    "sg:phone":"+1 513 922 7100",
    "sg:postcode":"45238",
    "sg:province":"OH",
    "wof:name":"Wurtz Insurance",
    "wof:placetype":"venue"
},
  "geometry": {"coordinates":[-84.62846999999999,39.096007],"type":"Point"}
}