{
  "type": "Feature",
  "properties": {
    "addr:full":"14660 Euclid Ave Cleveland OH 44112",
    "addr:housenumber":"14660",
    "addr:postcode":"44112",
    "addr:street":"Euclid Ave",
    "iso:country":"US",
    "sg:address":"14660 Euclid Ave",
    "sg:city":"Cleveland",
    "sg:classifiers":[
        {
            "category":"Travel",
            "subcategory":"Hotels & Motels",
            "type":"Entertainment"
        }
    ],
    "sg:phone":"+1 216 681 8500",
    "sg:postcode":"44112",
    "sg:province":"OH",
    "wof:name":"Mc Call's Motor Inn",
    "wof:placetype":"venue"
},
  "geometry": {"coordinates":[-81.57924800000001,41.532961],"type":"Point"}
}