{
  "type": "Feature",
  "properties": {
    "addr:full": "10009 Springfield Pike Cincinnati OH 45215",
    "addr:housenumber": "10009",
    "addr:postcode": "45215",
    "addr:street": "Springfield Pike",
    "iso:country": "US",
    "sg:address": "10009 Springfield Pike",
    "sg:city": "Cincinnati",
    "sg:classifiers": [
      {
        "category": "Professional",
        "type": "Services"
      }
    ],
    "sg:phone": "+1 513 771 3900",
    "sg:postcode": "45215",
    "sg:province": "OH",
    "sg:tags": [
      "establishment"
    ],
    "wof:name": "Hit Studio",
    "wof:placetype": "venue"
  },
  "geometry": {"coordinates":[-84.470778,39.247773],"type":"Point"}
}
