{
  "type": "Feature",
  "properties": {
    "addr:full": "47 W Bel Meadow Ln Chagrin Falls OH 44022",
    "addr:housenumber": "47",
    "addr:postcode": "44022",
    "addr:street": "W Bel Meadow Ln",
    "iso:country": "US",
    "sg:address": "47 W Bel Meadow Ln",
    "sg:city": "Chagrin Falls",
    "sg:classifiers": [
      {
        "category": "Building \u0026 Trades",
        "subcategory": "Construction",
        "type": "Services"
      }
    ],
    "sg:phone": "+1 440 477 9660",
    "sg:postcode": "44022",
    "sg:province": "OH",
    "sg:tags": [
      "enclosure",
      "pool",
      "swimming"
    ],
    "wof:name": "Home Safety Solutions",
    "wof:placetype": "venue"
  },
  "geometry": {"coordinates":[-81.334212,41.435104],"type":"Point"}
}
