{
  "type": "Feature",
  "properties": {
    "iso:country":"US",
    "sg:address":"47 W Bel Meadow Ln",
    "sg:city":"Chagrin Falls",
    "sg:classifiers":[
        {
            "category":"Building & Trades",
            "subcategory":"Construction",
            "type":"Services"
        }
    ],
    "sg:phone":"+1 440 477 9660",
    "sg:postcode":"44022",
    "sg:province":"OH",
    "sg:tags":[
        "enclosure",
        "pool",
        "swimming"
    ],
    "wof:name":"Home Safety Solutions",
    "wof:placetype":"venue"
},
  "geometry": {"coordinates":[-81.33421199999999,41.435104],"type":"Point"}
}