{
  "type": "Feature",
  "properties": {
    "iso:country":"US",
    "sg:address":"470 E Welch Ave",
    "sg:city":"Columbus",
    "sg:classifiers":[
        {
            "category":"Organizations",
            "subcategory":"Religious Organization",
            "type":"Services"
        }
    ],
    "sg:phone":"+1 614 444 7372",
    "sg:postcode":"43207",
    "sg:province":"OH",
    "sg:tags":[
        "church"
    ],
    "wof:name":"First Mt Carmel Baptist Church",
    "wof:placetype":"venue"
},
  "geometry": {"coordinates":[-82.98211000000001,39.930305],"type":"Point"}
}