{
  "type": "Feature",
  "properties": {
    "iso:country":"US",
    "sg:address":"78 Jefferson Dr",
    "sg:city":"Hudson",
    "sg:classifiers":[
        {
            "category":"Manufacturing",
            "subcategory":"Printing",
            "type":"Manufacturing & Wholesale Goods"
        }
    ],
    "sg:phone":"+1 330 650 2712",
    "sg:postcode":"44236",
    "sg:province":"OH",
    "sg:tags":[
        "book"
    ],
    "wof:name":"Shaffer Brown Co",
    "wof:placetype":"venue"
},
  "geometry": {"coordinates":[-81.45450700000001,41.24108],"type":"Point"}
}