{
  "type": "Feature",
  "properties": {
    "addr:full":"308 S East St Gratis OH 45330",
    "addr:housenumber":"308",
    "addr:postcode":"45330",
    "addr:street":"S East St",
    "iso:country":"US",
    "sg:address":"308 S East St",
    "sg:city":"Gratis",
    "sg:classifiers":[
        {
            "category":"Professional",
            "type":"Services"
        }
    ],
    "sg:phone":"+1 937 787 9999",
    "sg:postcode":"45330",
    "sg:province":"OH",
    "sg:tags":[
        "establishment"
    ],
    "wof:name":"Premier Recovery Concepts",
    "wof:placetype":"venue"
},
  "geometry": {"coordinates":[-84.5265,39.645179],"type":"Point"}
}