{
  "type": "Feature",
  "properties": {
    "addr:full": "4429 W Edgerton Rd Cleveland OH 44133",
    "addr:housenumber": "4429",
    "addr:postcode": "44133",
    "addr:street": "W Edgerton Rd",
    "iso:country": "US",
    "sg:address": "4429 W Edgerton Rd",
    "sg:city": "Cleveland",
    "sg:classifiers": [
      {
        "category": "Building \u0026 Trades",
        "subcategory": "Landscaping Services",
        "type": "Services"
      }
    ],
    "sg:phone": "+1 440 582 9733",
    "sg:postcode": "44133",
    "sg:province": "OH",
    "sg:tags": [
      "designer",
      "landscape"
    ],
    "wof:name": "Beauty Scapes",
    "wof:placetype": "venue"
  },
  "geometry": {"coordinates":[-81.715605,41.295867],"type":"Point"}
}
