{
  "type": "Feature",
  "properties": {
    "addr:full": "238 N 5th St Steubenville OH 43952",
    "addr:housenumber": "238",
    "addr:postcode": "43952",
    "addr:street": "N 5Th St",
    "iso:country": "US",
    "sg:address": "238 N 5th St",
    "sg:city": "Steubenville",
    "sg:classifiers": [
      {
        "category": "Autos \u0026 Motor Vehicles",
        "subcategory": "Automobile Sales",
        "type": "Retail Goods"
      }
    ],
    "sg:phone": "+1 740 282 2571",
    "sg:postcode": "43952",
    "sg:province": "OH",
    "wof:name": "McKitrick-Harms Inc",
    "wof:placetype": "venue"
  },
  "geometry": {"coordinates":[-80.614963,40.363122],"type":"Point"}
}
