{
  "type": "Feature",
  "properties": {
    "addr:full": "910 Bexton Dr Perrysburg OH 43551",
    "addr:housenumber": "910",
    "addr:postcode": "43551",
    "addr:street": "Bexton Dr",
    "iso:country": "US",
    "sg:address": "910 Bexton Dr",
    "sg:city": "Perrysburg",
    "sg:classifiers": [
      {
        "category": "Organizations",
        "subcategory": "Religious Organization",
        "type": "Services"
      }
    ],
    "sg:phone": "+1 419 874 0142",
    "sg:postcode": "43551",
    "sg:province": "OH",
    "sg:tags": [
      "clergy"
    ],
    "wof:name": "Tim Philabaum",
    "wof:placetype": "venue"
  },
  "geometry": {"coordinates":[-83.609332,41.554372],"type":"Point"}
}
