{
  "type": "Feature",
  "properties": {
    "iso:country":"US",
    "sg:address":"978 Hilliard Dr",
    "sg:city":"Cincinnati",
    "sg:classifiers":[
        {
            "category":"Retail",
            "subcategory":"Repair Shop",
            "type":"Services"
        }
    ],
    "sg:phone":"+1 513 922 7088",
    "sg:postcode":"45238",
    "sg:province":"OH",
    "sg:tags":[
        "repairing",
        "organs"
    ],
    "wof:name":"Schaedle Pipe Organ Svc",
    "wof:placetype":"venue"
},
  "geometry": {"coordinates":[-84.628879,39.11334],"type":"Point"}
}