{
  "type": "Feature",
  "properties": {
    "addr:full": "5148 Curtice Rd Northwood OH 43619",
    "addr:housenumber": "5148",
    "addr:postcode": "43619",
    "addr:street": "Curtice Rd",
    "iso:country": "US",
    "sg:address": "5148 Curtice Rd",
    "sg:city": "Northwood",
    "sg:phone": "+1 419 693 7185",
    "sg:postcode": "43619",
    "sg:province": "OH",
    "sg:tags": [
      "farm",
      "corn",
      "soybean"
    ],
    "wof:name": "William Kowalka",
    "wof:placetype": "venue"
  },
  "geometry": {"coordinates":[-83.418107,41.61635],"type":"Point"}
}
