{
  "type": "Feature",
  "properties": {
    "iso:country":"US",
    "sg:address":"5148 Curtice Rd",
    "sg:city":"Northwood",
    "sg:phone":"+1 419 693 7185",
    "sg:postcode":"43619",
    "sg:province":"OH",
    "sg:tags":[
        "farm",
        "corn",
        "soybean"
    ],
    "wof:name":"William Kowalka",
    "wof:placetype":"venue"
},
  "geometry": {"coordinates":[-83.41810700000001,41.61635],"type":"Point"}
}