{
  "type": "Feature",
  "properties": {
    "addr:full": "6200 Som Center Rd Cleveland OH 44139",
    "addr:postcode": "6200;44139",
    "addr:street": "Som Center Rd",
    "iso:country": "US",
    "sg:address": "6200 Som Center Rd",
    "sg:city": "Cleveland",
    "sg:classifiers": [
      {
        "category": "Travel",
        "subcategory": "Travel Agent",
        "type": "Entertainment"
      }
    ],
    "sg:phone": "+1 440 248 7740",
    "sg:postcode": "44139",
    "sg:province": "OH",
    "sg:tags": [
      "agency",
      "bureau"
    ],
    "wof:name": "Astro Travel Svc Inc",
    "wof:placetype": "venue"
  },
  "geometry": {"coordinates":[-81.437752,41.388315],"type":"Point"}
}
