{
  "type": "Feature",
  "properties": {
    "addr:full":"12953 Co Rd G Bryan OH 43506",
    "addr:housenumber":"12953",
    "addr:postcode":"43506",
    "addr:street":"Co Rd",
    "iso:country":"US",
    "sg:address":"12953 Co Rd G",
    "sg:city":"Bryan",
    "sg:classifiers":[
        {
            "category":"Government",
            "subcategory":"Office",
            "type":"Public Place"
        }
    ],
    "sg:phone":"+1 419 636 2854",
    "sg:postcode":"43506",
    "sg:province":"OH",
    "sg:tags":[
        "executive"
    ],
    "wof:name":"Williams County Highway Garage",
    "wof:placetype":"venue"
},
  "geometry": {"coordinates":[-84.58601,41.51404],"type":"Point"}
}