{
  "type": "Feature",
  "properties": {
    "addr:full":"80 Rossway Ave Rossford OH 43460",
    "addr:housenumber":"80",
    "addr:postcode":"43460",
    "addr:street":"Rossway Ave",
    "iso:country":"US",
    "sg:address":"80 Rossway Ave",
    "sg:city":"Rossford",
    "sg:classifiers":[
        {
            "category":"Real Estate",
            "subcategory":"Real Estate Operator",
            "type":"Services"
        }
    ],
    "sg:phone":"+1 419 666 4000",
    "sg:postcode":"43460",
    "sg:province":"OH",
    "sg:tags":[
        "apartment"
    ],
    "wof:name":"Rivers Ridge Apartments",
    "wof:placetype":"venue"
},
  "geometry": {"coordinates":[-83.56053300000001,41.604011],"type":"Point"}
}