{
  "type": "Feature",
  "properties": {
    "addr:full":"8385 Nearwood St NW Massillon OH 44646",
    "addr:housenumber":"8385",
    "addr:postcode":"44646",
    "addr:street":"Nearwood St Nw",
    "iso:country":"US",
    "sg:address":"8385 Nearwood St NW",
    "sg:city":"Massillon",
    "sg:classifiers":[
        {
            "category":"Real Estate",
            "subcategory":"Real Estate Agent",
            "type":"Services"
        }
    ],
    "sg:phone":"+1 330 832 6825",
    "sg:postcode":"44646",
    "sg:province":"OH",
    "sg:tags":[
        "inspection"
    ],
    "wof:name":"Salem Engineers Home Inspect",
    "wof:placetype":"venue"
},
  "geometry": {"coordinates":[-81.509747,40.83657],"type":"Point"}
}