{
  "type": "Feature",
  "properties": {
    "addr:full": "411 Independence Dr Medina OH 44256",
    "addr:housenumber": "411",
    "addr:postcode": "44256",
    "addr:street": "Independence Dr",
    "iso:country": "US",
    "sg:address": "411 Independence Dr",
    "sg:city": "Medina",
    "sg:classifiers": [
      {
        "category": "Wholesale",
        "subcategory": "Machinery \u0026 Supplies",
        "type": "Manufacturing \u0026 Wholesale Goods"
      }
    ],
    "sg:phone": "+1 330 725 0061",
    "sg:postcode": "44256",
    "sg:province": "OH",
    "sg:tags": [
      "commercial",
      "fan"
    ],
    "sg:website": "www.tltbabcock.com",
    "wof:name": "TLT Babcock Inc",
    "wof:placetype": "venue"
  },
  "geometry": {"coordinates":[-81.888777,41.129291],"type":"Point"}
}
