{
  "type": "Feature",
  "properties": {
    "iso:country":"US",
    "sg:address":"611 Sheldon Ave",
    "sg:city":"Columbus",
    "sg:classifiers":[
        {
            "category":"Building & Trades",
            "subcategory":"Plumbing",
            "type":"Services"
        }
    ],
    "sg:phone":"+1 614 449 9766",
    "sg:postcode":"43207",
    "sg:province":"OH",
    "sg:tags":[
        "contractor",
        "mechanical"
    ],
    "wof:name":"Environmental Systems Pro",
    "wof:placetype":"venue"
},
  "geometry": {"coordinates":[-82.979416,39.933535],"type":"Point"}
}