{
  "type": "Feature",
  "properties": {
    "addr:full":"707 Hadley Dr Columbus OH 43228",
    "addr:housenumber":"707",
    "addr:postcode":"43228",
    "addr:street":"Hadley Dr",
    "iso:country":"US",
    "sg:address":"707 Hadley Dr",
    "sg:city":"Columbus",
    "sg:phone":"+1 614 274 9851",
    "sg:postcode":"43228",
    "sg:province":"OH",
    "sg:tags":[
        "oil"
    ],
    "wof:name":"Amsoil Inc Distribution Ctr",
    "wof:placetype":"venue"
},
  "geometry": {"coordinates":[-83.098248,39.968385],"type":"Point"}
}