{
  "type": "Feature",
  "properties": {
    "iso:country":"US",
    "sg:address":"2718 State Rte 559",
    "sg:city":"Woodstock",
    "sg:phone":"+1 937 826 4941",
    "sg:postcode":"43084",
    "sg:province":"OH",
    "sg:tags":[
        "hog",
        "wheat",
        "farm",
        "corn",
        "or",
        "feedlot"
    ],
    "wof:name":"Blazer & Blazer",
    "wof:placetype":"venue"
},
  "geometry": {"coordinates":[-83.52220199999999,40.182948],"type":"Point"}
}