{
  "type": "Feature",
  "properties": {
    "addr:full": "2718 State Rte 559 Woodstock OH 43084",
    "addr:housenumber": "2718",
    "addr:postcode": "43084",
    "addr:street": "State Rte 559",
    "iso:country": "US",
    "sg:address": "2718 State Rte 559",
    "sg:city": "Woodstock",
    "sg:phone": "+1 937 826 4941",
    "sg:postcode": "43084",
    "sg:province": "OH",
    "sg:tags": [
      "hog",
      "wheat",
      "farm",
      "corn",
      "or",
      "feedlot"
    ],
    "wof:name": "Blazer \u0026 Blazer",
    "wof:placetype": "venue"
  },
  "geometry": {"coordinates":[-83.522202,40.182948],"type":"Point"}
}
