{
  "type": "Feature",
  "properties": {
    "addr:full": "5855 Monroe St Sylvania OH 43560",
    "addr:housenumber": "5855",
    "addr:postcode": "43560",
    "addr:street": "Monroe St",
    "iso:country": "US",
    "sg:address": "5855 Monroe St",
    "sg:city": "Sylvania",
    "sg:classifiers": [
      {
        "category": "Wholesale",
        "subcategory": "Medical Equipment \u0026 Supplies",
        "type": "Manufacturing \u0026 Wholesale Goods"
      }
    ],
    "sg:phone": "+1 419 882 1629",
    "sg:postcode": "43560",
    "sg:province": "OH",
    "sg:tags": [
      "hosp"
    ],
    "wof:name": "Health Solution",
    "wof:placetype": "venue"
  },
  "geometry": {"coordinates":[-83.68777,41.715102],"type":"Point"}
}
