{
  "type": "Feature",
  "properties": {
    "addr:full": "1949 E Concord Rd Amelia OH 45102",
    "addr:housenumber": "1949",
    "addr:postcode": "45102",
    "addr:street": "E Concord Rd",
    "iso:country": "US",
    "sg:address": "1949 E Concord Rd",
    "sg:city": "Amelia",
    "sg:classifiers": [
      {
        "category": "Building \u0026 Trades",
        "subcategory": "Equipment Rental",
        "type": "Services"
      }
    ],
    "sg:phone": "+1 513 797 7060",
    "sg:postcode": "45102",
    "sg:province": "OH",
    "sg:website": "www.platinumvideo.com",
    "wof:name": "Platinum Video Systems",
    "wof:placetype": "venue"
  },
  "geometry": {"coordinates":[-84.190351,39.002824],"type":"Point"}
}
