{
  "type": "Feature",
  "properties": {
    "addr:full":"1510 S Main St Akron OH 44301",
    "addr:housenumber":"1510",
    "addr:postcode":"44301",
    "addr:street":"S Main St",
    "iso:country":"US",
    "sg:address":"1510 S Main St",
    "sg:city":"Akron",
    "sg:classifiers":[
        {
            "category":"Restaurant",
            "type":"Food & Drink"
        }
    ],
    "sg:phone":"+1 330 724 8633",
    "sg:postcode":"44301",
    "sg:province":"OH",
    "sg:tags":[
        "eating"
    ],
    "wof:name":"K & ES Family Restaurant",
    "wof:placetype":"venue"
},
  "geometry": {"coordinates":[-81.52736299999999,41.044971],"type":"Point"}
}