{
  "type": "Feature",
  "properties": {
    "addr:full":"610 N Race St Springfield OH 45504",
    "addr:housenumber":"610",
    "addr:postcode":"45504",
    "addr:street":"N Race St",
    "iso:country":"US",
    "sg:address":"610 N Race St",
    "sg:city":"Springfield",
    "sg:classifiers":[
        {
            "category":"Organizations",
            "subcategory":"Religious Organization",
            "type":"Services"
        }
    ],
    "sg:phone":"+1 937 322 2375",
    "sg:postcode":"45504",
    "sg:province":"OH",
    "sg:tags":[
        "church"
    ],
    "wof:name":"Race Street Church Of God",
    "wof:placetype":"venue"
},
  "geometry": {"coordinates":[-83.82028200000001,39.932431],"type":"Point"}
}