{
  "type": "Feature",
  "properties": {
    "iso:country":"US",
    "sg:address":"9485 Glen Dr",
    "sg:city":"Cleveland",
    "sg:classifiers":[
        {
            "category":"Real Estate",
            "subcategory":"Real Estate Agent",
            "type":"Services"
        }
    ],
    "sg:phone":"+1 440 526 1289",
    "sg:postcode":"44141",
    "sg:province":"OH",
    "sg:tags":[
        "investment"
    ],
    "wof:name":"Advantage Investors Mortgage",
    "wof:placetype":"venue"
},
  "geometry": {"coordinates":[-81.632214,41.304422],"type":"Point"}
}