{
  "type": "Feature",
  "properties": {
    "addr:full":"4416 Lee Rd Cleveland OH 44128",
    "addr:housenumber":"4416",
    "addr:postcode":"44128",
    "addr:street":"Lee Rd",
    "iso:country":"US",
    "sg:address":"4416 Lee Rd",
    "sg:city":"Cleveland",
    "sg:classifiers":[
        {
            "category":"Manufacturing",
            "subcategory":"Tools & Machinery",
            "type":"Manufacturing & Wholesale Goods"
        }
    ],
    "sg:phone":"+1 216 581 1166",
    "sg:postcode":"44128",
    "sg:province":"OH",
    "sg:tags":[
        "industry",
        "special"
    ],
    "sg:website":"www.besteninc.com",
    "wof:name":"Besten Inc",
    "wof:placetype":"venue"
},
  "geometry": {"coordinates":[-81.56486599999999,41.438912],"type":"Point"}
}