{
  "type": "Feature",
  "properties": {
    "addr:full":"1687 Fulton St Port Clinton OH 43452",
    "addr:housenumber":"1687",
    "addr:postcode":"43452",
    "addr:street":"Fulton St",
    "iso:country":"US",
    "sg:address":"1687 Fulton St",
    "sg:city":"Port Clinton",
    "sg:phone":"+1 419 732 2687",
    "sg:postcode":"43452",
    "sg:province":"OH",
    "sg:tags":[
        "farm",
        "soybean"
    ],
    "wof:name":"Harold Sass",
    "wof:placetype":"venue"
},
  "geometry": {"coordinates":[-82.93369300000001,41.491538],"type":"Point"}
}