{
  "type": "Feature",
  "properties": {
    "addr:full": "11240 Sebring Dr Cincinnati OH 45240",
    "addr:postcode": "11240;45240",
    "addr:street": "Sebring Dr",
    "iso:country": "US",
    "sg:address": "11240 Sebring Dr",
    "sg:city": "Cincinnati",
    "sg:classifiers": [
      {
        "category": "Manufacturing",
        "subcategory": "Tools \u0026 Machinery",
        "type": "Manufacturing \u0026 Wholesale Goods"
      }
    ],
    "sg:phone": "+1 513 771 3684",
    "sg:postcode": "45240",
    "sg:province": "OH",
    "sg:tags": [
      "equipment",
      "industrial",
      "safety"
    ],
    "wof:name": "Industrial Sltons Unlmited LLC",
    "wof:placetype": "venue"
  },
  "geometry": {"coordinates":[-84.556348,39.28216],"type":"Point"}
}
