{
  "type": "Feature",
  "properties": {
    "iso:country":"US",
    "sg:address":"2118 Bennington Dr",
    "sg:city":"Mansfield",
    "sg:classifiers":[
        {
            "category":"Insurance",
            "subcategory":"Insurance Agent",
            "type":"Services"
        }
    ],
    "sg:phone":"+1 419 756 1333",
    "sg:postcode":"44904",
    "sg:province":"OH",
    "sg:tags":[
        "adjuster"
    ],
    "wof:name":"Crawford & Co",
    "wof:placetype":"venue"
},
  "geometry": {"coordinates":[-82.539501,40.697972],"type":"Point"}
}