{
  "type": "Feature",
  "properties": {
    "addr:full": "159 E 2nd St Chillicothe OH 45601",
    "addr:housenumber": "159",
    "addr:postcode": "45601",
    "addr:street": "E 2Nd St",
    "iso:country": "US",
    "sg:address": "159 E 2nd St",
    "sg:city": "Chillicothe",
    "sg:classifiers": [
      {
        "category": "Health Services",
        "subcategory": "Doctor",
        "type": "Services"
      }
    ],
    "sg:phone": "+1 740 773 6348",
    "sg:postcode": "45601",
    "sg:province": "OH",
    "sg:tags": [
      "physician",
      "medical",
      "surgeon"
    ],
    "wof:name": "Southern Ohio Eye Srgcl Assocs",
    "wof:placetype": "venue"
  },
  "geometry": {"coordinates":[-82.977996,39.335273],"type":"Point"}
}
