{
  "type": "Feature",
  "properties": {
    "iso:country":"US",
    "sg:address":"2290 Concord Village Dr",
    "sg:city":"Columbus",
    "sg:classifiers":[
        {
            "category":"Banks & Credit Unions",
            "subcategory":"Investment Brokerage",
            "type":"Services"
        }
    ],
    "sg:phone":"+1 614 459 5144",
    "sg:postcode":"43220",
    "sg:province":"OH",
    "sg:tags":[
        "consultant",
        "planning",
        "financial"
    ],
    "wof:name":"Don Shkolnik",
    "wof:placetype":"venue"
},
  "geometry": {"coordinates":[-83.077732,40.052623],"type":"Point"}
}