{
  "type": "Feature",
  "properties": {
    "addr:full": "460 West Ave Tallmadge OH 44278",
    "addr:housenumber": "460",
    "addr:postcode": "44278",
    "addr:street": "West Ave",
    "iso:country": "US",
    "sg:address": "460 West Ave",
    "sg:city": "Tallmadge",
    "sg:classifiers": [
      {
        "category": "Education",
        "subcategory": "Dance Studio",
        "type": "Public Place"
      }
    ],
    "sg:phone": "+1 330 633 1071",
    "sg:postcode": "44278",
    "sg:province": "OH",
    "sg:tags": [
      "instruction",
      "dancing"
    ],
    "wof:name": "Denise Bryant Studio Of Dance",
    "wof:placetype": "venue"
  },
  "geometry": {"coordinates":[-81.461063,41.101861],"type":"Point"}
}
