{
  "type": "Feature",
  "properties": {
    "addr:full":"212 S State St Westerville OH 43081",
    "addr:housenumber":"212",
    "addr:postcode":"43081",
    "addr:street":"S State St",
    "iso:country":"US",
    "sg:address":"212 S State St",
    "sg:city":"Westerville",
    "sg:classifiers":[
        {
            "category":"Real Estate",
            "subcategory":"Real Estate Agent",
            "type":"Services"
        }
    ],
    "sg:phone":"+1 614 839 5025",
    "sg:postcode":"43081",
    "sg:province":"OH",
    "wof:name":"Realty Executives",
    "wof:placetype":"venue"
},
  "geometry": {"coordinates":[-82.929035,40.119174],"type":"Point"}
}