{
  "type": "Feature",
  "properties": {
    "addr:full": "1345 Atcheson St Columbus OH 43203",
    "addr:housenumber": "1345",
    "addr:postcode": "43203",
    "addr:street": "Atcheson St",
    "iso:country": "US",
    "sg:address": "1345 Atcheson St",
    "sg:city": "Columbus",
    "sg:classifiers": [
      {
        "category": "Organizations",
        "subcategory": "Religious Organization",
        "type": "Services"
      }
    ],
    "sg:phone": "+1 614 258 1677",
    "sg:postcode": "43203",
    "sg:province": "OH",
    "sg:tags": [
      "church"
    ],
    "wof:name": "Union Tabernacle Of God",
    "wof:placetype": "venue"
  },
  "geometry": {"coordinates":[-82.965214,39.975255],"type":"Point"}
}
