{
  "type": "Feature",
  "properties": {
    "iso:country":"US",
    "sg:address":"4966 New Hope-Mckinley Rd",
    "sg:city":"Georgetown",
    "sg:phone":"+1 937 446 3091",
    "sg:postcode":"45121",
    "sg:province":"OH",
    "sg:tags":[
        "farm",
        "soybean"
    ],
    "wof:name":"Willard McKinley",
    "wof:placetype":"venue"
},
  "geometry": {"coordinates":[-83.886189,38.958358],"type":"Point"}
}