{
  "type": "Feature",
  "properties": {
    "addr:full": "6961 Shawnee Run Rd Cincinnati OH 45243",
    "addr:housenumber": "6961",
    "addr:postcode": "45243",
    "addr:street": "Shawnee Run Rd",
    "iso:country": "US",
    "sg:address": "6961 Shawnee Run Rd",
    "sg:city": "Cincinnati",
    "sg:classifiers": [
      {
        "category": "Manufacturing",
        "subcategory": "Glass \u0026 Minerals",
        "type": "Manufacturing \u0026 Wholesale Goods"
      }
    ],
    "sg:phone": "+1 513 561 8134",
    "sg:postcode": "45243",
    "sg:province": "OH",
    "sg:tags": [
      "ceramics"
    ],
    "wof:name": "B \u0026 E Ceramic Inc",
    "wof:placetype": "venue"
  },
  "geometry": {"coordinates":[-84.378932,39.181231],"type":"Point"}
}
