{
  "type": "Feature",
  "properties": {
    "iso:country":"US",
    "sg:address":"6961 Shawnee Run Rd",
    "sg:city":"Cincinnati",
    "sg:classifiers":[
        {
            "category":"Manufacturing",
            "subcategory":"Glass & Minerals",
            "type":"Manufacturing & Wholesale Goods"
        }
    ],
    "sg:phone":"+1 513 561 8134",
    "sg:postcode":"45243",
    "sg:province":"OH",
    "sg:tags":[
        "ceramics"
    ],
    "wof:name":"B & E Ceramic Inc",
    "wof:placetype":"venue"
},
  "geometry": {"coordinates":[-84.37893200000001,39.181231],"type":"Point"}
}