{
  "type": "Feature",
  "properties": {
    "iso:country":"US",
    "sg:address":"4101 Woodville Rd",
    "sg:city":"Northwood",
    "sg:classifiers":[
        {
            "category":"Autos & Motor Vehicles",
            "subcategory":"Fuel & Gas Station",
            "type":"Retail Goods"
        }
    ],
    "sg:phone":"+1 419 697 5681",
    "sg:postcode":"43619",
    "sg:province":"OH",
    "wof:name":"Fuel Mart 632",
    "wof:placetype":"venue"
},
  "geometry": {"coordinates":[-83.472326,41.607427],"type":"Point"}
}