{
  "type": "Feature",
  "properties": {
    "iso:country":"US",
    "sg:address":"2737 Blossom Ave",
    "sg:city":"Columbus",
    "sg:classifiers":[
        {
            "category":"Building & Trades",
            "subcategory":"Construction",
            "type":"Services"
        }
    ],
    "sg:phone":"+1 614 989 7304",
    "sg:postcode":"43231",
    "sg:province":"OH",
    "sg:tags":[
        "contractor"
    ],
    "wof:name":"Merjaerz Construction",
    "wof:placetype":"venue"
},
  "geometry": {"coordinates":[-82.944214,40.092458],"type":"Point"}
}