{
  "type": "Feature",
  "properties": {
    "addr:full":"4297 E Johnstown Rd Gahanna OH 43230",
    "addr:housenumber":"4297",
    "addr:postcode":"43230",
    "addr:street":"E Johnstown Rd",
    "iso:country":"US",
    "sg:address":"4297 E Johnstown Rd",
    "sg:city":"Gahanna",
    "sg:classifiers":[
        {
            "category":"Health Services",
            "subcategory":"Chiropractor",
            "type":"Services"
        }
    ],
    "sg:phone":"+1 614 855 3300",
    "sg:postcode":"43230",
    "sg:province":"OH",
    "wof:name":"Common Sense Chiropractic",
    "wof:placetype":"venue"
},
  "geometry": {"coordinates":[-82.859919,40.044919],"type":"Point"}
}