{
  "type": "Feature",
  "properties": {
    "addr:full":"10283 Forestwood Ln Cleveland OH 44133",
    "addr:housenumber":"10283",
    "addr:postcode":"44133",
    "addr:street":"Forestwood Ln",
    "iso:country":"US",
    "sg:address":"10283 Forestwood Ln",
    "sg:city":"Cleveland",
    "sg:classifiers":[
        {
            "category":"Real Estate",
            "subcategory":"Real Estate Agent",
            "type":"Services"
        }
    ],
    "sg:phone":"+1 440 237 2435",
    "sg:postcode":"44133",
    "sg:province":"OH",
    "wof:name":"Beaver Valley Estate Inc",
    "wof:placetype":"venue"
},
  "geometry": {"coordinates":[-81.71077699999999,41.329512],"type":"Point"}
}