{
  "type": "Feature",
  "properties": {
    "addr:full":"7381 Co Rd 23 Archbold OH 43502",
    "addr:housenumber":"7381;23",
    "addr:postcode":"43502",
    "addr:street":"Co Rd",
    "iso:country":"US",
    "sg:address":"7381 Co Rd 23",
    "sg:city":"Archbold",
    "sg:classifiers":[
        {
            "category":"Building & Trades",
            "subcategory":"Construction",
            "type":"Services"
        }
    ],
    "sg:phone":"+1 419 445 1916",
    "sg:postcode":"43502",
    "sg:province":"OH",
    "sg:tags":[
        "excavating",
        "contractor"
    ],
    "wof:name":"Heer Excavating",
    "wof:placetype":"venue"
},
  "geometry": {"coordinates":[-84.306839,41.577096],"type":"Point"}
}