{
  "type": "Feature",
  "properties": {
    "addr:full":"9651 Wengerlawn Rd Brookville OH 45309",
    "addr:housenumber":"9651",
    "addr:postcode":"45309",
    "addr:street":"Wengerlawn Rd",
    "iso:country":"US",
    "sg:address":"9651 Wengerlawn Rd",
    "sg:city":"Brookville",
    "sg:classifiers":[
        {
            "category":"Building & Trades",
            "subcategory":"Plumbing",
            "type":"Services"
        }
    ],
    "sg:phone":"+1 937 884 7733",
    "sg:postcode":"45309",
    "sg:province":"OH",
    "sg:tags":[
        "contractor"
    ],
    "wof:name":"Keiths Plumbing Services",
    "wof:placetype":"venue"
},
  "geometry": {"coordinates":[-84.43392799999999,39.874884],"type":"Point"}
}