{
  "type": "Feature",
  "properties": {
    "addr:full":"2265 N High St Columbus OH 43201",
    "addr:housenumber":"2265",
    "addr:postcode":"43201",
    "addr:street":"N High St",
    "iso:country":"US",
    "sg:address":"2265 N High St",
    "sg:city":"Columbus",
    "sg:classifiers":[
        {
            "category":"Real Estate",
            "subcategory":"Real Estate Agent",
            "type":"Services"
        }
    ],
    "sg:phone":"+1 614 297 0496",
    "sg:postcode":"43201",
    "sg:province":"OH",
    "wof:name":"Coldwell Banker",
    "wof:placetype":"venue"
},
  "geometry": {"coordinates":[-83.009947,40.00889],"type":"Point"}
}