{
  "type": "Feature",
  "properties": {
    "addr:full": "6960 Market St Youngstown OH 44512",
    "addr:housenumber": "6960",
    "addr:postcode": "44512",
    "addr:street": "Market St",
    "iso:country": "US",
    "sg:address": "6960 Market St",
    "sg:city": "Youngstown",
    "sg:classifiers": [
      {
        "category": "Personal",
        "subcategory": "Beauty Salon",
        "type": "Services"
      }
    ],
    "sg:phone": "+1 330 629 8820",
    "sg:postcode": "44512",
    "sg:province": "OH",
    "sg:tags": [
      "manicuring"
    ],
    "wof:name": "Elegant Experience",
    "wof:placetype": "venue"
  },
  "geometry": {"coordinates":[-80.662821,41.028402],"type":"Point"}
}
