{
  "type": "Feature",
  "properties": {
    "iso:country":"US",
    "sg:address":"4175 N High St",
    "sg:city":"Columbus",
    "sg:classifiers":[
        {
            "category":"Real Estate",
            "subcategory":"Real Estate Agent",
            "type":"Services"
        }
    ],
    "sg:phone":"+1 614 447 8133",
    "sg:postcode":"43214",
    "sg:province":"OH",
    "wof:name":"Garrison Bob Realtor",
    "wof:placetype":"venue"
},
  "geometry": {"coordinates":[-83.019918,40.046288],"type":"Point"}
}