{
  "type": "Feature",
  "properties": {
    "iso:country":"US",
    "sg:address":"22366 Lake Shore Blvd",
    "sg:city":"Cleveland",
    "sg:classifiers":[
        {
            "category":"Insurance",
            "subcategory":"Insurance Agent",
            "type":"Services"
        }
    ],
    "sg:phone":"+1 216 731 4200",
    "sg:postcode":"44123",
    "sg:province":"OH",
    "wof:name":"A-1 General Insurance",
    "wof:placetype":"venue"
},
  "geometry": {"coordinates":[-81.52627099999999,41.609594],"type":"Point"}
}