{
  "type": "Feature",
  "properties": {
    "addr:full": "8189 W Ridgewood Dr Cleveland OH 44129",
    "addr:housenumber": "8189",
    "addr:postcode": "44129",
    "addr:street": "W Ridgewood Dr",
    "iso:country": "US",
    "sg:address": "8189 W Ridgewood Dr",
    "sg:city": "Cleveland",
    "sg:classifiers": [
      {
        "category": "Shopping",
        "subcategory": "Jewelry",
        "type": "Retail Goods"
      }
    ],
    "sg:phone": "+1 440 888 2450",
    "sg:postcode": "44129",
    "sg:province": "OH",
    "wof:name": "Alvins Jewelers 20",
    "wof:placetype": "venue"
  },
  "geometry": {"coordinates":[-81.743006,41.384455],"type":"Point"}
}
