{
  "type": "Feature",
  "properties": {
    "addr:full":"50008 State Rte 681 Reedsville OH 45772",
    "addr:housenumber":"50008",
    "addr:postcode":"45772",
    "addr:street":"State Rte 681",
    "iso:country":"US",
    "sg:address":"50008 State Rte 681",
    "sg:city":"Reedsville",
    "sg:classifiers":[
        {
            "category":"Education",
            "subcategory":"School",
            "type":"Public Place"
        }
    ],
    "sg:phone":"+1 740 667 6079",
    "sg:postcode":"45772",
    "sg:province":"OH",
    "sg:tags":[
        "independent",
        "district"
    ],
    "wof:name":"Eastern Local School District",
    "wof:placetype":"venue"
},
  "geometry": {"coordinates":[-81.844615,39.168779],"type":"Point"}
}