{
  "type": "Feature",
  "properties": {
    "addr:full": "11132 Industrial Pkwy NW Bolivar OH 44612",
    "addr:housenumber": "11132",
    "addr:postcode": "44612",
    "addr:street": "Industrial Pkwy Nw Bolivar",
    "iso:country": "US",
    "sg:address": "11132 Industrial Pkwy NW",
    "sg:city": "Bolivar",
    "sg:classifiers": [
      {
        "category": "Retail",
        "subcategory": "Repair Shop",
        "type": "Services"
      }
    ],
    "sg:phone": "+1 330 874 4009",
    "sg:postcode": "44612",
    "sg:province": "OH",
    "sg:tags": [
      "tank",
      "cryogenic"
    ],
    "wof:name": "Eleet Cryogenics Inc",
    "wof:placetype": "venue"
  },
  "geometry": {"coordinates":[-81.461329,40.642186],"type":"Point"}
}
