{
  "type": "Feature",
  "properties": {
    "addr:full":"8330 Clough Pike Cincinnati OH 45244",
    "addr:housenumber":"8330",
    "addr:postcode":"45244",
    "addr:street":"Clough Pike",
    "iso:country":"US",
    "sg:address":"8330 Clough Pike",
    "sg:city":"Cincinnati",
    "sg:classifiers":[
        {
            "category":"Professional",
            "subcategory":"Testing Lab",
            "type":"Services"
        },
        {
            "category":"Health Services",
            "subcategory":"Medical Lab",
            "type":"Services"
        },
        {
            "category":"Health Services",
            "subcategory":"Dentist",
            "type":"Services"
        }
    ],
    "sg:phone":"+1 513 474 5499",
    "sg:postcode":"45244",
    "sg:province":"OH",
    "sg:tags":[
        "laboratory",
        "dental",
        "clinic"
    ],
    "wof:name":"Perfecto Dental Laboratory",
    "wof:placetype":"venue"
},
  "geometry": {"coordinates":[-84.321426,39.087952],"type":"Point"}
}