{
  "type": "Feature",
  "properties": {
    "addr:full": "15 Ridge Ave North Bend OH 45052",
    "addr:housenumber": "15",
    "addr:postcode": "45052",
    "addr:street": "Ridge Ave",
    "iso:country": "US",
    "sg:address": "15 Ridge Ave",
    "sg:city": "North Bend",
    "sg:classifiers": [
      {
        "category": "Professional",
        "subcategory": "Art Services",
        "type": "Services"
      }
    ],
    "sg:phone": "+1 513 941 7351",
    "sg:postcode": "45052",
    "sg:province": "OH",
    "sg:tags": [
      "photographer"
    ],
    "wof:name": "Picture Perfect Photos",
    "wof:placetype": "venue"
  },
  "geometry": {"coordinates":[-84.745586,39.154886],"type":"Point"}
}
