{
  "type": "Feature",
  "properties": {
    "addr:full": "361 Elm Rd NE Warren OH 44483",
    "addr:housenumber": "361",
    "addr:postcode": "44483",
    "addr:street": "Elm Rd Ne",
    "iso:country": "US",
    "sg:address": "361 Elm Rd NE",
    "sg:city": "Warren",
    "sg:classifiers": [
      {
        "category": "Social Services",
        "type": "Services"
      }
    ],
    "sg:phone": "+1 330 394 5437",
    "sg:postcode": "44483",
    "sg:province": "OH",
    "sg:tags": [
      "organization",
      "welfare"
    ],
    "wof:name": "Warren Family Mission",
    "wof:placetype": "venue"
  },
  "geometry": {"coordinates":[-80.811026,41.23919],"type":"Point"}
}
