{
  "type": "Feature",
  "properties": {
    "iso:country":"US",
    "sg:address":"4726 Jeannette Rd",
    "sg:city":"Hilliard",
    "sg:classifiers":[
        {
            "category":"Professional",
            "subcategory":"Advertising",
            "type":"Services"
        }
    ],
    "sg:phone":"+1 614 777 1289",
    "sg:postcode":"43026",
    "sg:province":"OH",
    "sg:tags":[
        "mailing",
        "list"
    ],
    "wof:name":"Homefacts",
    "wof:placetype":"venue"
},
  "geometry": {"coordinates":[-83.140462,40.02575],"type":"Point"}
}