{
  "type": "Feature",
  "properties": {
    "addr:full":"507 Miamisburg Centerville Rd Dayton OH 45459",
    "addr:housenumber":"507",
    "addr:postcode":"45459",
    "addr:street":"Miamisburg Centerville Rd",
    "iso:country":"US",
    "sg:address":"507 Miamisburg Centerville Rd",
    "sg:city":"Dayton",
    "sg:classifiers":[
        {
            "category":"Bars & Pubs",
            "type":"Food & Drink"
        }
    ],
    "sg:phone":"+1 937 291 9212",
    "sg:postcode":"45459",
    "sg:province":"OH",
    "sg:tags":[
        "club",
        "night"
    ],
    "wof:name":"Pulsations Night Club",
    "wof:placetype":"venue"
},
  "geometry": {"coordinates":[-84.174668,39.627931],"type":"Point"}
}