{
  "type": "Feature",
  "properties": {
    "addr:full": "140 Mansfield Ave Shelby OH 44875",
    "addr:housenumber": "140",
    "addr:postcode": "44875",
    "addr:street": "Mansfield Ave",
    "iso:country": "US",
    "sg:address": "140 Mansfield Ave",
    "sg:city": "Shelby",
    "sg:classifiers": [
      {
        "category": "Food \u0026 Beverages",
        "subcategory": "Groceries \u0026 Convenience Stores",
        "type": "Retail Goods"
      }
    ],
    "sg:phone": "+1 419 347 2223",
    "sg:postcode": "44875",
    "sg:province": "OH",
    "sg:tags": [
      "grocer"
    ],
    "wof:name": "Cornell's Iga Foodliner Inc",
    "wof:placetype": "venue"
  },
  "geometry": {"coordinates":[-82.648344,40.872447],"type":"Point"}
}
