{
  "type": "Feature",
  "properties": {
    "iso:country":"US",
    "sg:address":"140 Mansfield Ave",
    "sg:city":"Shelby",
    "sg:classifiers":[
        {
            "category":"Food & Beverages",
            "subcategory":"Groceries & Convenience Stores",
            "type":"Retail Goods"
        }
    ],
    "sg:phone":"+1 419 347 2223",
    "sg:postcode":"44875",
    "sg:province":"OH",
    "sg:tags":[
        "grocer"
    ],
    "wof:name":"Cornell's Iga Foodliner Inc",
    "wof:placetype":"venue"
},
  "geometry": {"coordinates":[-82.64834399999999,40.872447],"type":"Point"}
}