{
  "type": "Feature",
  "properties": {
    "iso:country":"US",
    "sg:address":"131 Dillmont Dr",
    "sg:city":"Columbus",
    "sg:classifiers":[
        {
            "category":"Wholesale",
            "subcategory":"Stationery",
            "type":"Manufacturing & Wholesale Goods"
        }
    ],
    "sg:phone":"+1 614 885 0980",
    "sg:postcode":"43235",
    "sg:province":"OH",
    "sg:tags":[
        "mapping"
    ],
    "wof:name":"Navteq Corp",
    "wof:placetype":"venue"
},
  "geometry": {"coordinates":[-83.012452,40.134135],"type":"Point"}
}