{
  "type": "Feature",
  "properties": {
    "iso:country":"US",
    "sg:address":"840 W State St",
    "sg:city":"Columbus",
    "sg:classifiers":[
        {
            "category":"Social Services",
            "type":"Services"
        }
    ],
    "sg:phone":"+1 614 221 7855",
    "sg:postcode":"43222",
    "sg:province":"OH",
    "wof:name":"St Vincent Family Center Inc",
    "wof:placetype":"venue"
},
  "geometry": {"coordinates":[-83.023212,39.957547],"type":"Point"}
}