{
  "type": "Feature",
  "properties": {
    "addr:full": "907 Tremont St Dover OH 44622",
    "addr:housenumber": "907",
    "addr:postcode": "44622",
    "addr:street": "Tremont St",
    "iso:country": "US",
    "sg:address": "907 Tremont St",
    "sg:city": "Dover",
    "sg:classifiers": [
      {
        "category": "Shopping",
        "type": "Retail Goods"
      }
    ],
    "sg:phone": "+1 330 343 1375",
    "sg:postcode": "44622",
    "sg:province": "OH",
    "sg:tags": [
      "wedding",
      "supply"
    ],
    "wof:name": "Harper Design Decorating",
    "wof:placetype": "venue"
  },
  "geometry": {"coordinates":[-81.47688,40.530371],"type":"Point"}
}
