{
  "type": "Feature",
  "properties": {
    "iso:country":"US",
    "sg:address":"5 Samson Pl",
    "sg:city":"Granville",
    "sg:classifiers":[
        {
            "category":"Shopping",
            "subcategory":"Used Merchandise",
            "type":"Retail Goods"
        }
    ],
    "sg:phone":"+1 740 587 1408",
    "sg:postcode":"43023",
    "sg:province":"OH",
    "sg:tags":[
        "book"
    ],
    "wof:name":"Dream Weaver Books",
    "wof:placetype":"venue"
},
  "geometry": {"coordinates":[-82.530439,40.072257],"type":"Point"}
}