{
  "type": "Feature",
  "properties": {
    "addr:full":"4197 Shoppers Ln Columbus OH 43228",
    "addr:housenumber":"4197",
    "addr:postcode":"43228",
    "addr:street":"Shoppers Ln",
    "iso:country":"US",
    "sg:address":"4197 Shoppers Ln",
    "sg:city":"Columbus",
    "sg:classifiers":[
        {
            "category":"Recreation",
            "type":"Entertainment"
        }
    ],
    "sg:phone":"+1 614 272 8880",
    "sg:postcode":"43228",
    "sg:province":"OH",
    "sg:tags":[
        "bingo",
        "game"
    ],
    "wof:name":"A Plus Bingo",
    "wof:placetype":"venue"
},
  "geometry": {"coordinates":[-83.111942,39.949902],"type":"Point"}
}