{
  "type": "Feature",
  "properties": {
    "iso:country":"US",
    "sg:address":"641 Hill Rd N",
    "sg:city":"Pickerington",
    "sg:classifiers":[
        {
            "category":"Health Services",
            "subcategory":"Doctor",
            "type":"Services"
        }
    ],
    "sg:phone":"+1 614 833 0880",
    "sg:postcode":"43147",
    "sg:province":"OH",
    "sg:tags":[
        "physician",
        "surgeon",
        "medical"
    ],
    "wof:name":"Pickerington Family Practice",
    "wof:placetype":"venue"
},
  "geometry": {"coordinates":[-82.768886,39.901613],"type":"Point"}
}