{
  "type": "Feature",
  "properties": {
    "addr:full": "3455 Poole Rd Cincinnati OH 45251",
    "addr:housenumber": "3455",
    "addr:postcode": "45251",
    "addr:street": "Poole Rd",
    "iso:country": "US",
    "sg:address": "3455 Poole Rd",
    "sg:city": "Cincinnati",
    "sg:classifiers": [
      {
        "category": "Shopping",
        "subcategory": "Gifts \u0026 Souvenirs",
        "type": "Retail Goods"
      }
    ],
    "sg:phone": "+1 513 923 3665",
    "sg:postcode": "45251",
    "sg:province": "OH",
    "sg:tags": [
      "shop"
    ],
    "wof:name": "Nature's Niche Gift \u0026 Book",
    "wof:placetype": "venue"
  },
  "geometry": {"coordinates":[-84.593711,39.234956],"type":"Point"}
}
