{
  "type": "Feature",
  "properties": {
    "addr:full":"4795 Trudy Ln Hamilton OH 45013",
    "addr:housenumber":"4795",
    "addr:postcode":"45013",
    "addr:street":"Trudy Ln",
    "iso:country":"US",
    "sg:address":"4795 Trudy Ln",
    "sg:city":"Hamilton",
    "sg:classifiers":[
        {
            "category":"Banks & Credit Unions",
            "subcategory":"Financial Services",
            "type":"Services"
        }
    ],
    "sg:phone":"+1 513 738 3775",
    "sg:postcode":"45013",
    "sg:province":"OH",
    "sg:tags":[
        "investor"
    ],
    "wof:name":"Sierra Properties LLC",
    "wof:placetype":"venue"
},
  "geometry": {"coordinates":[-84.71581399999999,39.364054],"type":"Point"}
}