{
  "type": "Feature",
  "properties": {
    "iso:country":"US",
    "sg:address":"6 N Jackson St",
    "sg:city":"Youngstown",
    "sg:classifiers":[
        {
            "category":"Education",
            "subcategory":"Library",
            "type":"Public Place"
        }
    ],
    "sg:phone":"+1 330 744 2790",
    "sg:postcode":"44506",
    "sg:province":"OH",
    "wof:name":"Youngstown Public Library",
    "wof:placetype":"venue"
},
  "geometry": {"coordinates":[-80.62211499999999,41.098029],"type":"Point"}
}