{
  "type": "Feature",
  "properties": {
    "addr:full": "6 N Jackson St Youngstown OH 44506",
    "addr:housenumber": "6",
    "addr:postcode": "44506",
    "addr:street": "N Jackson St",
    "iso:country": "US",
    "sg:address": "6 N Jackson St",
    "sg:city": "Youngstown",
    "sg:classifiers": [
      {
        "category": "Education",
        "subcategory": "Library",
        "type": "Public Place"
      }
    ],
    "sg:phone": "+1 330 744 2790",
    "sg:postcode": "44506",
    "sg:province": "OH",
    "wof:name": "Youngstown Public Library",
    "wof:placetype": "venue"
  },
  "geometry": {"coordinates":[-80.622115,41.098029],"type":"Point"}
}
