{
  "type": "Feature",
  "properties": {
    "addr:full": "8101 State Rte 44 Ravenna OH 44266",
    "addr:housenumber": "8101",
    "addr:postcode": "44266",
    "addr:street": "State Rte 44",
    "iso:country": "US",
    "sg:address": "8101 State Rte 44",
    "sg:city": "Ravenna",
    "sg:classifiers": [
      {
        "category": "Airport",
        "type": "Transportation"
      }
    ],
    "sg:phone": "+1 330 297 0087",
    "sg:postcode": "44266",
    "sg:province": "OH",
    "sg:tags": [
      "aircraft",
      "cleaning",
      "maintenance"
    ],
    "wof:name": "Novaks Aircraft Maintenance",
    "wof:placetype": "venue"
  },
  "geometry": {"coordinates":[-81.243745,41.209453],"type":"Point"}
}
