{
  "type": "Feature",
  "properties": {
    "iso:country":"US",
    "sg:address":"102 Rhoades Ave",
    "sg:city":"Greenville",
    "sg:classifiers":[
        {
            "category":"Banks & Credit Unions",
            "subcategory":"Bank",
            "type":"Services"
        }
    ],
    "sg:phone":"+1 937 548 0104",
    "sg:postcode":"45331",
    "sg:province":"OH",
    "sg:tags":[
        "loan"
    ],
    "wof:name":"Fast Payday Loans Of Ohio",
    "wof:placetype":"venue"
},
  "geometry": {"coordinates":[-84.62294,40.116984],"type":"Point"}
}