{
  "type": "Feature",
  "properties": {
    "addr:full": "102 Rhoades Ave Greenville OH 45331",
    "addr:housenumber": "102",
    "addr:postcode": "45331",
    "addr:street": "Rhoades Ave",
    "iso:country": "US",
    "sg:address": "102 Rhoades Ave",
    "sg:city": "Greenville",
    "sg:classifiers": [
      {
        "category": "Banks \u0026 Credit Unions",
        "subcategory": "Bank",
        "type": "Services"
      }
    ],
    "sg:phone": "+1 937 548 0104",
    "sg:postcode": "45331",
    "sg:province": "OH",
    "sg:tags": [
      "loan"
    ],
    "wof:name": "Fast Payday Loans Of Ohio",
    "wof:placetype": "venue"
  },
  "geometry": {"coordinates":[-84.62294,40.116984],"type":"Point"}
}
