{
  "type": "Feature",
  "properties": {
    "addr:full": "350 E Orange Rd Lewis Center OH 43035",
    "addr:housenumber": "350",
    "addr:postcode": "43035",
    "addr:street": "E Orange Rd",
    "iso:country": "US",
    "sg:address": "350 E Orange Rd",
    "sg:city": "Lewis Center",
    "sg:classifiers": [
      {
        "category": "Sports \u0026 Exercise",
        "subcategory": "Gym",
        "type": "Entertainment"
      }
    ],
    "sg:phone": "+1 740 548 3637",
    "sg:postcode": "43035",
    "sg:province": "OH",
    "sg:tags": [
      "club",
      "health",
      "studio",
      "gymnasium"
    ],
    "wof:name": "Elite Physiques Personal Trnr",
    "wof:placetype": "venue"
  },
  "geometry": {"coordinates":[-83.019567,40.175134],"type":"Point"}
}
