{
  "type": "Feature",
  "properties": {
    "iso:country":"US",
    "sg:address":"889 Ashland Rd",
    "sg:city":"Mansfield",
    "sg:classifiers":[
        {
            "category":"Restaurant",
            "type":"Food & Drink"
        }
    ],
    "sg:phone":"+1 419 589 6888",
    "sg:postcode":"44905",
    "sg:province":"OH",
    "sg:tags":[
        "delivery",
        "pick"
    ],
    "wof:name":"Mamas Pizza Inc",
    "wof:placetype":"venue"
},
  "geometry": {"coordinates":[-82.4835,40.771821],"type":"Point"}
}