{
  "type": "Feature",
  "properties": {
    "addr:full": "889 Ashland Rd Mansfield OH 44905",
    "addr:housenumber": "889",
    "addr:postcode": "44905",
    "addr:street": "Ashland Rd",
    "iso:country": "US",
    "sg:address": "889 Ashland Rd",
    "sg:city": "Mansfield",
    "sg:classifiers": [
      {
        "category": "Restaurant",
        "type": "Food \u0026 Drink"
      }
    ],
    "sg:phone": "+1 419 589 6888",
    "sg:postcode": "44905",
    "sg:province": "OH",
    "sg:tags": [
      "delivery",
      "pick"
    ],
    "wof:name": "Mamas Pizza Inc",
    "wof:placetype": "venue"
  },
  "geometry": {"coordinates":[-82.4835,40.771821],"type":"Point"}
}
