{
  "type": "Feature",
  "properties": {
    "addr:full":"6330 Paxton Woods Dr Loveland OH 45140",
    "addr:housenumber":"6330",
    "addr:postcode":"45140",
    "addr:street":"Paxton Woods Dr",
    "iso:country":"US",
    "sg:address":"6330 Paxton Woods Dr",
    "sg:city":"Loveland",
    "sg:classifiers":[
        {
            "category":"Building & Trades",
            "subcategory":"Landscaping Services",
            "type":"Services"
        }
    ],
    "sg:phone":"+1 513 697 9090",
    "sg:postcode":"45140",
    "sg:province":"OH",
    "sg:tags":[
        "landscape"
    ],
    "wof:name":"Oasis Lawn & Landscape",
    "wof:placetype":"venue"
},
  "geometry": {"coordinates":[-84.241034,39.224969],"type":"Point"}
}