{
  "type": "Feature",
  "properties": {
    "iso:country":"US",
    "sg:address":"600 Plainfield Rd",
    "sg:city":"West Lafayette",
    "sg:classifiers":[
        {
            "category":"Real Estate",
            "subcategory":"Real Estate Operator",
            "type":"Services"
        }
    ],
    "sg:phone":"+1 740 545 9705",
    "sg:postcode":"43845",
    "sg:province":"OH",
    "sg:tags":[
        "building",
        "apartment"
    ],
    "wof:name":"Lafayette Mills",
    "wof:placetype":"venue"
},
  "geometry": {"coordinates":[-81.74435,40.269833],"type":"Point"}
}