{
  "type": "Feature",
  "properties": {
    "addr:full": "33003 Aurora Rd Cleveland OH 44139",
    "addr:housenumber": "33003",
    "addr:postcode": "44139",
    "addr:street": "Aurora Rd",
    "iso:country": "US",
    "sg:address": "33003 Aurora Rd",
    "sg:city": "Cleveland",
    "sg:classifiers": [
      {
        "category": "Restaurant",
        "type": "Food \u0026 Drink"
      }
    ],
    "sg:phone": "+1 440 248 8860",
    "sg:postcode": "44139",
    "sg:province": "OH",
    "wof:name": "Spaghetti Co",
    "wof:placetype": "venue"
  },
  "geometry": {"coordinates":[-81.445648,41.386884],"type":"Point"}
}
