{
  "type": "Feature",
  "properties": {
    "iso:country":"US",
    "sg:address":"33003 Aurora Rd",
    "sg:city":"Cleveland",
    "sg:classifiers":[
        {
            "category":"Restaurant",
            "type":"Food & Drink"
        }
    ],
    "sg:phone":"+1 440 248 8860",
    "sg:postcode":"44139",
    "sg:province":"OH",
    "wof:name":"Spaghetti Co",
    "wof:placetype":"venue"
},
  "geometry": {"coordinates":[-81.44564800000001,41.386884],"type":"Point"}
}