{
  "type": "Feature",
  "properties": {
    "addr:full":"1430 Virginia St Zanesville OH 43701",
    "addr:housenumber":"1430",
    "addr:postcode":"43701",
    "addr:street":"Virginia St",
    "iso:country":"US",
    "sg:address":"1430 Virginia St",
    "sg:city":"Zanesville",
    "sg:classifiers":[
        {
            "category":"Restaurant",
            "type":"Food & Drink"
        }
    ],
    "sg:phone":"+1 740 454 0605",
    "sg:postcode":"43701",
    "sg:province":"OH",
    "sg:tags":[
        "eating"
    ],
    "wof:name":"Ater & Son China Sales LLP",
    "wof:placetype":"venue"
},
  "geometry": {"coordinates":[-82.025993,39.92684],"type":"Point"}
}