{
  "type": "Feature",
  "properties": {
    "addr:full": "6050 W Central Ave Toledo OH 43615",
    "addr:housenumber": "6050",
    "addr:postcode": "43615",
    "addr:street": "W Central Ave",
    "iso:country": "US",
    "sg:address": "6050 W Central Ave",
    "sg:city": "Toledo",
    "sg:classifiers": [
      {
        "category": "Insurance",
        "subcategory": "Insurance Agent",
        "type": "Services"
      }
    ],
    "sg:phone": "+1 419 843 4001",
    "sg:postcode": "43615",
    "sg:province": "OH",
    "wof:name": "Bender Brad State Farm Insuran",
    "wof:placetype": "venue"
  },
  "geometry": {"coordinates":[-83.687357,41.676134],"type":"Point"}
}
