{
  "type": "Feature",
  "properties": {
    "iso:country":"US",
    "sg:address":"4073 Monterey Dr",
    "sg:city":"Medina",
    "sg:classifiers":[
        {
            "category":"Manufacturing",
            "subcategory":"Signs",
            "type":"Manufacturing & Wholesale Goods"
        }
    ],
    "sg:phone":"+1 330 722 6201",
    "sg:postcode":"44256",
    "sg:province":"OH",
    "sg:tags":[
        "specialty",
        "mfg"
    ],
    "wof:name":"Adams Signs",
    "wof:placetype":"venue"
},
  "geometry": {"coordinates":[-81.853953,41.163949],"type":"Point"}
}