{
  "type": "Feature",
  "properties": {
    "addr:full": "4073 Monterey Dr Medina OH 44256",
    "addr:housenumber": "4073",
    "addr:postcode": "44256",
    "addr:street": "Monterey Dr",
    "iso:country": "US",
    "sg:address": "4073 Monterey Dr",
    "sg:city": "Medina",
    "sg:classifiers": [
      {
        "category": "Manufacturing",
        "subcategory": "Signs",
        "type": "Manufacturing \u0026 Wholesale Goods"
      }
    ],
    "sg:phone": "+1 330 722 6201",
    "sg:postcode": "44256",
    "sg:province": "OH",
    "sg:tags": [
      "specialty",
      "mfg"
    ],
    "wof:name": "Adams Signs",
    "wof:placetype": "venue"
  },
  "geometry": {"coordinates":[-81.853953,41.163949],"type":"Point"}
}
