{
  "type": "Feature",
  "properties": {
    "addr:full": "312 Railroad St Gordon OH 45304",
    "addr:housenumber": "312",
    "addr:postcode": "45304",
    "addr:street": "Railroad St",
    "iso:country": "US",
    "sg:address": "312 Railroad St",
    "sg:city": "Gordon",
    "sg:phone": "+1 937 884 7690",
    "sg:postcode": "45304",
    "sg:province": "OH",
    "sg:tags": [
      "oil"
    ],
    "wof:name": "Carlin Fuels Inc",
    "wof:placetype": "venue"
  },
  "geometry": {"coordinates":[-84.510224,39.931744],"type":"Point"}
}
