{
  "type": "Feature",
  "properties": {
    "iso:country":"US",
    "sg:address":"15602 Chillicothe Rd",
    "sg:city":"Chagrin Falls",
    "sg:classifiers":[
        {
            "category":"Retail",
            "subcategory":"Animal Services",
            "type":"Services"
        }
    ],
    "sg:phone":"+1 440 338 1330",
    "sg:postcode":"44022",
    "sg:province":"OH",
    "sg:tags":[
        "pet",
        "grooming",
        "washing"
    ],
    "wof:name":"Alicia's Pet Parlor",
    "wof:placetype":"venue"
},
  "geometry": {"coordinates":[-81.338351,41.441864],"type":"Point"}
}