{
  "type": "Feature",
  "properties": {
    "iso:country":"US",
    "sg:address":"4223 Saint Andrews Pl",
    "sg:city":"Cincinnati",
    "sg:classifiers":[
        {
            "category":"Wholesale",
            "subcategory":"Jewelry",
            "type":"Manufacturing & Wholesale Goods"
        }
    ],
    "sg:phone":"+1 513 984 3819",
    "sg:postcode":"45236",
    "sg:province":"OH",
    "sg:tags":[
        "diamonds-wholesale"
    ],
    "wof:name":"Fk Diamonds",
    "wof:placetype":"venue"
},
  "geometry": {"coordinates":[-84.394102,39.228939],"type":"Point"}
}