{
  "type": "Feature",
  "properties": {
    "iso:country":"US",
    "sg:address":"3195 Linwood Ave",
    "sg:city":"Cincinnati",
    "sg:classifiers":[
        {
            "category":"Personal",
            "subcategory":"Tanning Parlor",
            "type":"Services"
        }
    ],
    "sg:phone":"+1 513 871 0999",
    "sg:postcode":"45208",
    "sg:province":"OH",
    "sg:tags":[
        "salon"
    ],
    "wof:name":"Sunpoint Tanning Salon",
    "wof:placetype":"venue"
},
  "geometry": {"coordinates":[-84.430329,39.129915],"type":"Point"}
}