{
  "type": "Feature",
  "properties": {
    "addr:full":"1289 Edison St NE Hartville OH 44632",
    "addr:housenumber":"1289",
    "addr:postcode":"44632",
    "addr:street":"Edison St Ne",
    "iso:country":"US",
    "sg:address":"1289 Edison St NE",
    "sg:city":"Hartville",
    "sg:classifiers":[
        {
            "category":"Home & Garden",
            "subcategory":"Home Furnishings",
            "type":"Retail Goods"
        }
    ],
    "sg:phone":"+1 330 877 6662",
    "sg:postcode":"44632",
    "sg:province":"OH",
    "sg:tags":[
        "kitchen",
        "accessory"
    ],
    "wof:name":"Judy's Kitchen Gadgets",
    "wof:placetype":"venue"
},
  "geometry": {"coordinates":[-81.35121100000001,40.969005],"type":"Point"}
}