{
  "type": "Feature",
  "properties": {
    "iso:country":"US",
    "sg:address":"7843 Laurel Ave",
    "sg:city":"Cincinnati",
    "sg:classifiers":[
        {
            "category":"Health Services",
            "subcategory":"Chiropractor",
            "type":"Services"
        }
    ],
    "sg:phone":"+1 513 272 3553",
    "sg:postcode":"45243",
    "sg:province":"OH",
    "wof:name":"Madeira Chiropractic Ctr",
    "wof:placetype":"venue"
},
  "geometry": {"coordinates":[-84.358643,39.190134],"type":"Point"}
}