{
  "type": "Feature",
  "properties": {
    "iso:country":"US",
    "sg:address":"3666 Paxton Ave",
    "sg:city":"Cincinnati",
    "sg:classifiers":[
        {
            "category":"Health Services",
            "subcategory":"Doctor",
            "type":"Services"
        }
    ],
    "sg:phone":"+1 513 321 3003",
    "sg:postcode":"45208",
    "sg:province":"OH",
    "sg:tags":[
        "dentist"
    ],
    "wof:name":"Dale R Siemer DDS",
    "wof:placetype":"venue"
},
  "geometry": {"coordinates":[-84.433381,39.144056],"type":"Point"}
}