{
  "type": "Feature",
  "properties": {
    "iso:country":"US",
    "sg:address":"3250 Yorktown Dr",
    "sg:city":"Oregon",
    "sg:classifiers":[
        {
            "category":"Real Estate",
            "subcategory":"Real Estate Operator",
            "type":"Services"
        }
    ],
    "sg:phone":"+1 419 693 6811",
    "sg:postcode":"43616",
    "sg:province":"OH",
    "sg:tags":[
        "building",
        "apartment"
    ],
    "wof:name":"Oregon Village Co",
    "wof:placetype":"venue"
},
  "geometry": {"coordinates":[-83.469818,41.6396],"type":"Point"}
}