{
  "type": "Feature",
  "properties": {
    "addr:full": "3425 Nebraska Ave Toledo OH 43607",
    "addr:housenumber": "3425",
    "addr:postcode": "43607",
    "addr:street": "Nebraska Ave",
    "iso:country": "US",
    "sg:address": "3425 Nebraska Ave",
    "sg:city": "Toledo",
    "sg:classifiers": [
      {
        "category": "Social Services",
        "type": "Services"
      }
    ],
    "sg:phone": "+1 419 537 8963",
    "sg:postcode": "43607",
    "sg:province": "OH",
    "sg:tags": [
      "senior",
      "citizen"
    ],
    "wof:name": "Flory Gardens Senior Citizen",
    "wof:placetype": "venue"
  },
  "geometry": {"coordinates":[-83.625815,41.645483],"type":"Point"}
}
