{
  "type": "Feature",
  "properties": {
    "iso:country":"US",
    "sg:address":"182 W Oxford St",
    "sg:city":"Alliance",
    "sg:classifiers":[
        {
            "category":"Social Services",
            "subcategory":"Child Care",
            "type":"Services"
        }
    ],
    "sg:phone":"+1 330 823 3609",
    "sg:postcode":"44601",
    "sg:province":"OH",
    "wof:name":"Ogie's Day Care",
    "wof:placetype":"venue"
},
  "geometry": {"coordinates":[-81.109248,40.917427],"type":"Point"}
}