{
  "type": "Feature",
  "properties": {
    "addr:full":"9525 Kile Rd Chardon OH 44024",
    "addr:housenumber":"9525",
    "addr:postcode":"44024",
    "addr:street":"Kile Rd",
    "iso:country":"US",
    "sg:address":"9525 Kile Rd",
    "sg:city":"Chardon",
    "sg:classifiers":[
        {
            "category":"Building & Trades",
            "subcategory":"Construction",
            "type":"Services"
        }
    ],
    "sg:phone":"+1 440 286 4062",
    "sg:postcode":"44024",
    "sg:province":"OH",
    "sg:tags":[
        "contractor"
    ],
    "wof:name":"Hart Roofing",
    "wof:placetype":"venue"
},
  "geometry": {"coordinates":[-81.100944,41.612299],"type":"Point"}
}