{
  "type": "Feature",
  "properties": {
    "iso:country":"US",
    "sg:address":"30737 Logan Horns Mill Rd",
    "sg:city":"Logan",
    "sg:classifiers":[
        {
            "category":"Recreation",
            "type":"Entertainment"
        }
    ],
    "sg:phone":"+1 740 385 3100",
    "sg:postcode":"43138",
    "sg:province":"OH",
    "sg:tags":[
        "hall",
        "auditorium"
    ],
    "wof:name":"Marion Twp Community Ctr",
    "wof:placetype":"venue"
},
  "geometry": {"coordinates":[-82.434988,39.610538],"type":"Point"}
}