{
  "type": "Feature",
  "properties": {
    "addr:full":"1219 Carmella Dr NW New Philadelphia OH 44663",
    "addr:housenumber":"1219",
    "addr:postcode":"44663",
    "addr:street":"Carmella Dr Nw New Philadelphia",
    "iso:country":"US",
    "sg:address":"1219 Carmella Dr NW",
    "sg:city":"New Philadelphia",
    "sg:classifiers":[
        {
            "category":"Professional",
            "subcategory":"Business Services",
            "type":"Services"
        }
    ],
    "sg:phone":"+1 330 343 0220",
    "sg:postcode":"44663",
    "sg:province":"OH",
    "sg:tags":[
        "water",
        "treatment"
    ],
    "wof:name":"Aquablue Inc",
    "wof:placetype":"venue"
},
  "geometry": {"coordinates":[-81.44265799999999,40.508052],"type":"Point"}
}