{
  "type": "Feature",
  "properties": {
    "addr:full": "7437 Egypt Rd Sterling OH 44276",
    "addr:housenumber": "7437",
    "addr:postcode": "44276",
    "addr:street": "Egypt Rd",
    "iso:country": "US",
    "sg:address": "7437 Egypt Rd",
    "sg:city": "Sterling",
    "sg:classifiers": [
      {
        "category": "Shopping",
        "subcategory": "Discount \u0026 Variety Stores",
        "type": "Retail Goods"
      }
    ],
    "sg:phone": "+1 330 669 3239",
    "sg:postcode": "44276",
    "sg:province": "OH",
    "sg:tags": [
      "merchandise",
      "general"
    ],
    "wof:name": "Spurlock Enterprises",
    "wof:placetype": "venue"
  },
  "geometry": {"coordinates":[-81.822449,40.894075],"type":"Point"}
}
