{
  "type": "Feature",
  "properties": {
    "iso:country":"US",
    "sg:address":"7437 Egypt Rd",
    "sg:city":"Sterling",
    "sg:classifiers":[
        {
            "category":"Shopping",
            "subcategory":"Discount & Variety Stores",
            "type":"Retail Goods"
        }
    ],
    "sg:phone":"+1 330 669 3239",
    "sg:postcode":"44276",
    "sg:province":"OH",
    "sg:tags":[
        "merchandise",
        "general"
    ],
    "wof:name":"Spurlock Enterprises",
    "wof:placetype":"venue"
},
  "geometry": {"coordinates":[-81.82244900000001,40.894075],"type":"Point"}
}