{
  "type": "Feature",
  "properties": {
    "addr:full":"3426 Fernside Pl Cincinnati OH 45207",
    "addr:housenumber":"3426",
    "addr:postcode":"45207",
    "addr:street":"Fernside Pl",
    "iso:country":"US",
    "sg:address":"3426 Fernside Pl",
    "sg:city":"Cincinnati",
    "sg:classifiers":[
        {
            "category":"Organizations",
            "subcategory":"Religious Organization",
            "type":"Services"
        }
    ],
    "sg:phone":"+1 513 221 1822",
    "sg:postcode":"45207",
    "sg:province":"OH",
    "sg:tags":[
        "church"
    ],
    "wof:name":"New Testament Baptist Church",
    "wof:placetype":"venue"
},
  "geometry": {"coordinates":[-84.47667800000001,39.142136],"type":"Point"}
}