{
  "type": "Feature",
  "properties": {
    "iso:country":"US",
    "sg:address":"705 Main Ave SW",
    "sg:city":"Warren",
    "sg:classifiers":[
        {
            "category":"Retail",
            "subcategory":"Laundry & Dry Cleaning",
            "type":"Services"
        }
    ],
    "sg:phone":"+1 330 399 2235",
    "sg:postcode":"44483",
    "sg:province":"OH",
    "sg:tags":[
        "drycleaning",
        "plant",
        "cleaners"
    ],
    "wof:name":"Rite Cleaners & Drapery Svc",
    "wof:placetype":"venue"
},
  "geometry": {"coordinates":[-80.819648,41.229731],"type":"Point"}
}