{
  "type": "Feature",
  "properties": {
    "iso:country":"US",
    "sg:address":"90 E William St",
    "sg:city":"Delaware",
    "sg:classifiers":[
        {
            "category":"Health Services",
            "subcategory":"Optometrist",
            "type":"Services"
        }
    ],
    "sg:phone":"+1 740 369 3909",
    "sg:postcode":"43015",
    "sg:province":"OH",
    "wof:name":"Andrea Dinovo Family Eyecare",
    "wof:placetype":"venue"
},
  "geometry": {"coordinates":[-83.064255,40.298622],"type":"Point"}
}