{
  "type": "Feature",
  "properties": {
    "iso:country":"US",
    "sg:address":"5155 Stickney Ave",
    "sg:city":"Toledo",
    "sg:classifiers":[
        {
            "category":"Freight",
            "type":"Transportation"
        }
    ],
    "sg:phone":"+1 419 726 0079",
    "sg:postcode":"43612",
    "sg:province":"OH",
    "sg:tags":[
        "operator",
        "local",
        "trucking"
    ],
    "wof:name":"Futrell Enterprises LLC",
    "wof:placetype":"venue"
},
  "geometry": {"coordinates":[-83.527912,41.713441],"type":"Point"}
}