{
  "type": "Feature",
  "properties": {
    "addr:full": "7777 Exchange Rd Cleveland OH 44125",
    "addr:housenumber": "7777",
    "addr:postcode": "44125",
    "addr:street": "Exchange Rd",
    "iso:country": "US",
    "sg:address": "7777 Exchange Rd",
    "sg:city": "Cleveland",
    "sg:classifiers": [
      {
        "category": "Real Estate",
        "subcategory": "Real Estate Agent",
        "type": "Services"
      }
    ],
    "sg:phone": "+1 216 524 5223",
    "sg:postcode": "44125",
    "sg:province": "OH",
    "wof:name": "Industrial Space LTD",
    "wof:placetype": "venue"
  },
  "geometry": {"coordinates":[-81.630175,41.407928],"type":"Point"}
}
