{
  "type": "Feature",
  "properties": {
    "addr:full": "11 N Grand Ave Fairborn OH 45324",
    "addr:housenumber": "11",
    "addr:postcode": "45324",
    "addr:street": "N Grand Ave",
    "iso:country": "US",
    "sg:address": "11 N Grand Ave",
    "sg:city": "Fairborn",
    "sg:classifiers": [
      {
        "category": "Home \u0026 Garden",
        "subcategory": "Hardware",
        "type": "Retail Goods"
      }
    ],
    "sg:phone": "+1 937 879 0141",
    "sg:postcode": "45324",
    "sg:province": "OH",
    "wof:name": "Ace Hardware",
    "wof:placetype": "venue"
  },
  "geometry": {"coordinates":[-84.022496,39.821963],"type":"Point"}
}
