{
  "type": "Feature",
  "properties": {
    "addr:full": "7870 Surrywood Dr North Bend OH 45052",
    "addr:postcode": "7870;45052",
    "addr:street": "Surrywood Dr",
    "iso:country": "US",
    "sg:address": "7870 Surrywood Dr",
    "sg:city": "North Bend",
    "sg:classifiers": [
      {
        "category": "Farming",
        "subcategory": "Farm",
        "type": "Manufacturing \u0026 Wholesale Goods"
      }
    ],
    "sg:phone": "+1 513 941 3348",
    "sg:postcode": "45052",
    "sg:province": "OH",
    "sg:tags": [
      "crop",
      "general"
    ],
    "wof:name": "TS Ripley Farm Inc",
    "wof:placetype": "venue"
  },
  "geometry": {"coordinates":[-84.706461,39.14823],"type":"Point"}
}
