{
  "type": "Feature",
  "properties": {
    "iso:country":"US",
    "sg:address":"7870 Surrywood Dr",
    "sg:city":"North Bend",
    "sg:classifiers":[
        {
            "category":"Farming",
            "subcategory":"Farm",
            "type":"Manufacturing & Wholesale Goods"
        }
    ],
    "sg:phone":"+1 513 941 3348",
    "sg:postcode":"45052",
    "sg:province":"OH",
    "sg:tags":[
        "crop",
        "general"
    ],
    "wof:name":"TS Ripley Farm Inc",
    "wof:placetype":"venue"
},
  "geometry": {"coordinates":[-84.706461,39.14823],"type":"Point"}
}