{
  "type": "Feature",
  "properties": {
    "iso:country":"US",
    "sg:address":"2278 Patterson Rd",
    "sg:city":"Dayton",
    "sg:classifiers":[
        {
            "category":"Real Estate",
            "subcategory":"Real Estate Agent",
            "type":"Services"
        }
    ],
    "sg:phone":"+1 937 252 7728",
    "sg:postcode":"45420",
    "sg:province":"OH",
    "wof:name":"Cunningham Realty",
    "wof:placetype":"venue"
},
  "geometry": {"coordinates":[-84.130578,39.722932],"type":"Point"}
}