{
  "type": "Feature",
  "properties": {
    "addr:full":"29525 Chagrin Blvd Beachwood OH 44122",
    "addr:housenumber":"29525",
    "addr:postcode":"44122",
    "addr:street":"Chagrin Blvd",
    "iso:country":"US",
    "sg:address":"29525 Chagrin Blvd",
    "sg:city":"Beachwood",
    "sg:classifiers":[
        {
            "category":"Professional",
            "subcategory":"Accounting & Tax Preparation",
            "type":"Services"
        }
    ],
    "sg:phone":"+1 216 765 1664",
    "sg:postcode":"44122",
    "sg:province":"OH",
    "sg:tags":[
        "accountant"
    ],
    "wof:name":"Berkman Stafman Masters & Co",
    "wof:placetype":"venue"
},
  "geometry": {"coordinates":[-81.47530399999999,41.462399],"type":"Point"}
}