{
  "type": "Feature",
  "properties": {
    "addr:full": "1108 S Shannon St Van Wert OH 45891",
    "addr:housenumber": "1108",
    "addr:postcode": "45891",
    "addr:street": "S Shannon St",
    "iso:country": "US",
    "sg:address": "1108 S Shannon St",
    "sg:city": "Van Wert",
    "sg:classifiers": [
      {
        "category": "Real Estate",
        "subcategory": "Real Estate Agent",
        "type": "Services"
      }
    ],
    "sg:phone": "+1 419 232 3230",
    "sg:postcode": "45891",
    "sg:province": "OH",
    "wof:name": "Schear Financial Service Inc",
    "wof:placetype": "venue"
  },
  "geometry": {"coordinates":[-84.5972,40.858546],"type":"Point"}
}
