{
  "type": "Feature",
  "properties": {
    "addr:full": "6248 Struthers Rd Lowellville OH 44436",
    "addr:housenumber": "6248",
    "addr:postcode": "44436",
    "addr:street": "Struthers Rd",
    "iso:country": "US",
    "sg:address": "6248 Struthers Rd",
    "sg:city": "Lowellville",
    "sg:classifiers": [
      {
        "category": "Organizations",
        "subcategory": "Religious Organization",
        "type": "Services"
      }
    ],
    "sg:phone": "+1 330 536 8004",
    "sg:postcode": "44436",
    "sg:province": "OH",
    "sg:tags": [
      "place",
      "worship",
      "church"
    ],
    "wof:name": "Poland Christian Church",
    "wof:placetype": "venue"
  },
  "geometry": {"coordinates":[-80.567574,41.031151],"type":"Point"}
}
