{
  "type": "Feature",
  "properties": {
    "iso:country":"US",
    "sg:address":"1140 Deerfield Rd",
    "sg:city":"Lebanon",
    "sg:classifiers":[
        {
            "category":"Professional",
            "type":"Services"
        }
    ],
    "sg:phone":"+1 513 228 0850",
    "sg:postcode":"45036",
    "sg:province":"OH",
    "wof:name":"Robyn Prater",
    "wof:placetype":"venue"
},
  "geometry": {"coordinates":[-84.207105,39.419022],"type":"Point"}
}