{
  "type": "Feature",
  "properties": {
    "iso:country":"US",
    "sg:address":"860 Boardman Canfield Rd",
    "sg:city":"Boardman",
    "sg:classifiers":[
        {
            "category":"Banks & Credit Unions",
            "subcategory":"Bank",
            "type":"Services"
        }
    ],
    "sg:phone":"+1 330 629 2531",
    "sg:postcode":"44512",
    "sg:province":"OH",
    "sg:tags":[
        "loan",
        "real estate"
    ],
    "wof:name":"First American Lenders-Equity",
    "wof:placetype":"venue"
},
  "geometry": {"coordinates":[-80.688287,41.024618],"type":"Point"}
}