{
  "type": "Feature",
  "properties": {
    "iso:country":"US",
    "sg:address":"2900 Banwick Rd",
    "sg:city":"Columbus",
    "sg:classifiers":[
        {
            "category":"Manufacturing",
            "subcategory":"Printing",
            "type":"Manufacturing & Wholesale Goods"
        }
    ],
    "sg:phone":"+1 614 239 9090",
    "sg:postcode":"43232",
    "sg:province":"OH",
    "sg:tags":[
        "lithographic",
        "commercial"
    ],
    "wof:name":"Typographic Printing Company",
    "wof:placetype":"venue"
},
  "geometry": {"coordinates":[-82.92137,39.925946],"type":"Point"}
}