{
  "type": "Feature",
  "properties": {
    "addr:full": "2900 Banwick Rd Columbus OH 43232",
    "addr:housenumber": "2900",
    "addr:postcode": "43232",
    "addr:street": "Banwick Rd",
    "iso:country": "US",
    "sg:address": "2900 Banwick Rd",
    "sg:city": "Columbus",
    "sg:classifiers": [
      {
        "category": "Manufacturing",
        "subcategory": "Printing",
        "type": "Manufacturing \u0026 Wholesale Goods"
      }
    ],
    "sg:phone": "+1 614 239 9090",
    "sg:postcode": "43232",
    "sg:province": "OH",
    "sg:tags": [
      "lithographic",
      "commercial"
    ],
    "wof:name": "Typographic Printing Company",
    "wof:placetype": "venue"
  },
  "geometry": {"coordinates":[-82.92137,39.925946],"type":"Point"}
}
