{
  "type": "Feature",
  "properties": {
    "iso:country":"US",
    "sg:address":"8270 Sharp Ln",
    "sg:city":"Chesterland",
    "sg:classifiers":[
        {
            "category":"Building & Trades",
            "subcategory":"Landscaping Services",
            "type":"Services"
        }
    ],
    "sg:phone":"+1 440 729 2066",
    "sg:postcode":"44026",
    "sg:province":"OH",
    "sg:tags":[
        "landscape"
    ],
    "wof:name":"Flc Land Design Inc",
    "wof:placetype":"venue"
},
  "geometry": {"coordinates":[-81.33680200000001,41.569309],"type":"Point"}
}