{
  "type": "Feature",
  "properties": {
    "addr:full": "8270 Sharp Ln Chesterland OH 44026",
    "addr:housenumber": "8270",
    "addr:postcode": "44026",
    "addr:street": "Sharp Ln",
    "iso:country": "US",
    "sg:address": "8270 Sharp Ln",
    "sg:city": "Chesterland",
    "sg:classifiers": [
      {
        "category": "Building \u0026 Trades",
        "subcategory": "Landscaping Services",
        "type": "Services"
      }
    ],
    "sg:phone": "+1 440 729 2066",
    "sg:postcode": "44026",
    "sg:province": "OH",
    "sg:tags": [
      "landscape"
    ],
    "wof:name": "Flc Land Design Inc",
    "wof:placetype": "venue"
  },
  "geometry": {"coordinates":[-81.336802,41.569309],"type":"Point"}
}
