{
  "type": "Feature",
  "properties": {
    "addr:full": "1619 Burney Ln Cincinnati OH 45230",
    "addr:housenumber": "1619",
    "addr:postcode": "45230",
    "addr:street": "Burney Ln",
    "iso:country": "US",
    "sg:address": "1619 Burney Ln",
    "sg:city": "Cincinnati",
    "sg:classifiers": [
      {
        "category": "Professional",
        "subcategory": "Computer Services",
        "type": "Services"
      }
    ],
    "sg:phone": "+1 513 231 7700",
    "sg:postcode": "45230",
    "sg:province": "OH",
    "sg:tags": [
      "repair",
      "design",
      "system"
    ],
    "wof:name": "J D Computer Systems",
    "wof:placetype": "venue"
  },
  "geometry": {"coordinates":[-84.374639,39.083038],"type":"Point"}
}
