{
  "type": "Feature",
  "properties": {
    "addr:full":"8639 Lake In the Woods Trl Chagrin Falls OH 44023",
    "addr:housenumber":"8639",
    "addr:postcode":"44023",
    "addr:street":"Lake In The Woods Trl",
    "iso:country":"US",
    "sg:address":"8639 Lake In the Woods Trl",
    "sg:city":"Chagrin Falls",
    "sg:classifiers":[
        {
            "category":"Professional",
            "subcategory":"Employment Agencies",
            "type":"Services"
        }
    ],
    "sg:phone":"+1 440 708 0364",
    "sg:postcode":"44023",
    "sg:province":"OH",
    "wof:name":"Cornerstone",
    "wof:placetype":"venue"
},
  "geometry": {"coordinates":[-81.332489,41.421445],"type":"Point"}
}