{
  "type": "Feature",
  "properties": {
    "addr:full": "1125 Gahanna Pkwy Gahanna OH 43230",
    "addr:housenumber": "1125",
    "addr:postcode": "43230",
    "addr:street": "Gahanna Pkwy",
    "iso:country": "US",
    "sg:address": "1125 Gahanna Pkwy",
    "sg:city": "Gahanna",
    "sg:classifiers": [
      {
        "category": "Manufacturing",
        "subcategory": "Rubber \u0026 Plastics",
        "type": "Manufacturing \u0026 Wholesale Goods"
      }
    ],
    "sg:phone": "+1 614 864 3989",
    "sg:postcode": "43230",
    "sg:province": "OH",
    "sg:tags": [
      "product"
    ],
    "sg:website": "www.alloypolymers.com",
    "wof:name": "Alloy Polymers Inc",
    "wof:placetype": "venue"
  },
  "geometry": {"coordinates":[-82.844308,39.99039],"type":"Point"}
}
