{
  "type": "Feature",
  "properties": {
    "iso:country":"US",
    "sg:address":"1125 Gahanna Pkwy",
    "sg:city":"Gahanna",
    "sg:classifiers":[
        {
            "category":"Manufacturing",
            "subcategory":"Rubber & Plastics",
            "type":"Manufacturing & Wholesale Goods"
        }
    ],
    "sg:phone":"+1 614 864 3989",
    "sg:postcode":"43230",
    "sg:province":"OH",
    "sg:tags":[
        "product"
    ],
    "sg:website":"www.alloypolymers.com",
    "wof:name":"Alloy Polymers Inc",
    "wof:placetype":"venue"
},
  "geometry": {"coordinates":[-82.844308,39.99039],"type":"Point"}
}