{
  "type": "Feature",
  "properties": {
    "addr:full":"28999 Starr Route Rd Logan OH 43138",
    "addr:housenumber":"28999",
    "addr:postcode":"43138",
    "addr:street":"Starr Route Rd",
    "iso:country":"US",
    "sg:address":"28999 Starr Route Rd",
    "sg:city":"Logan",
    "sg:classifiers":[
        {
            "category":"Home & Garden",
            "subcategory":"Building Materials",
            "type":"Retail Goods"
        }
    ],
    "sg:phone":"+1 740 385 2492",
    "sg:postcode":"43138",
    "sg:province":"OH",
    "wof:name":"Larry Kornmiller",
    "wof:placetype":"venue"
},
  "geometry": {"coordinates":[-82.493267,39.516081],"type":"Point"}
}