{
  "type": "Feature",
  "properties": {
    "iso:country":"US",
    "sg:address":"1835 Britton Dr",
    "sg:city":"Piqua",
    "sg:classifiers":[
        {
            "category":"Freight",
            "type":"Transportation"
        }
    ],
    "sg:phone":"+1 937 773 4478",
    "sg:postcode":"45356",
    "sg:province":"OH",
    "sg:tags":[
        "hauling",
        "trucking"
    ],
    "wof:name":"Miami Transport Inc",
    "wof:placetype":"venue"
},
  "geometry": {"coordinates":[-84.275971,40.15092],"type":"Point"}
}