{
  "type": "Feature",
  "properties": {
    "addr:full": "7988 Rockville Rd SW Navarre OH 44662",
    "addr:housenumber": "7988",
    "addr:postcode": "44662",
    "addr:street": "Rockville Rd Sw",
    "iso:country": "US",
    "sg:address": "7988 Rockville Rd SW",
    "sg:city": "Navarre",
    "sg:classifiers": [
      {
        "category": "Building \u0026 Trades",
        "subcategory": "Construction",
        "type": "Services"
      },
      {
        "category": "Manufacturing",
        "subcategory": "Tools \u0026 Machinery",
        "type": "Manufacturing \u0026 Wholesale Goods"
      }
    ],
    "sg:phone": "+1 330 756 2289",
    "sg:postcode": "44662",
    "sg:province": "OH",
    "sg:tags": [
      "farm",
      "agricultural",
      "silo",
      "equipment"
    ],
    "wof:name": "Farmer's Service \u0026 Repair Co",
    "wof:placetype": "venue"
  },
  "geometry": {"coordinates":[-81.50581,40.6895],"type":"Point"}
}
