{
  "type": "Feature",
  "properties": {
    "iso:country":"US",
    "sg:address":"7988 Rockville Rd SW",
    "sg:city":"Navarre",
    "sg:classifiers":[
        {
            "category":"Building & Trades",
            "subcategory":"Construction",
            "type":"Services"
        },
        {
            "category":"Manufacturing",
            "subcategory":"Tools & Machinery",
            "type":"Manufacturing & Wholesale Goods"
        }
    ],
    "sg:phone":"+1 330 756 2289",
    "sg:postcode":"44662",
    "sg:province":"OH",
    "sg:tags":[
        "farm",
        "agricultural",
        "silo",
        "equipment"
    ],
    "wof:name":"Farmer's Service & Repair Co",
    "wof:placetype":"venue"
},
  "geometry": {"coordinates":[-81.50581,40.6895],"type":"Point"}
}