{
  "type": "Feature",
  "properties": {
    "iso:country":"US",
    "sg:address":"3601 Green Rd",
    "sg:city":"Cleveland",
    "sg:classifiers":[
        {
            "category":"Health Services",
            "subcategory":"Health Practitioner",
            "type":"Services"
        }
    ],
    "sg:phone":"+1 216 586 9167",
    "sg:postcode":"44122",
    "sg:province":"OH",
    "sg:tags":[
        "psychologist"
    ],
    "wof:name":"Barbara Hill-Newby PHD",
    "wof:placetype":"venue"
},
  "geometry": {"coordinates":[-81.516937,41.461837],"type":"Point"}
}