{
  "type": "Feature",
  "properties": {
    "iso:country":"US",
    "sg:address":"209 S Chestnut St",
    "sg:city":"Ravenna",
    "sg:classifiers":[
        {
            "category":"Health Services",
            "subcategory":"Doctor",
            "type":"Services"
        }
    ],
    "sg:phone":"+1 330 296 7526",
    "sg:postcode":"44266",
    "sg:province":"OH",
    "sg:tags":[
        "clinic"
    ],
    "sg:website":"www.plannedparenthood.org",
    "wof:name":"Planned Parenthood",
    "wof:placetype":"venue"
},
  "geometry": {"coordinates":[-81.243123,41.157271],"type":"Point"}
}