{
  "type": "Feature",
  "properties": {
    "addr:full":"4760 Brainard Rd Chagrin Falls OH 44022",
    "addr:housenumber":"4760",
    "addr:postcode":"44022",
    "addr:street":"Brainard Rd",
    "iso:country":"US",
    "sg:address":"4760 Brainard Rd",
    "sg:city":"Chagrin Falls",
    "sg:classifiers":[
        {
            "category":"Home & Garden",
            "subcategory":"Home Furnishings",
            "type":"Retail Goods"
        }
    ],
    "sg:phone":"+1 440 349 2378",
    "sg:postcode":"44022",
    "sg:province":"OH",
    "sg:tags":[
        "venetian",
        "blind"
    ],
    "wof:name":"Best Blinds & Window Treatment",
    "wof:placetype":"venue"
},
  "geometry": {"coordinates":[-81.480463,41.431452],"type":"Point"}
}