{
  "type": "Feature",
  "properties": {
    "addr:full": "36945 Independence Ct Cleveland OH 44139",
    "addr:housenumber": "36945",
    "addr:postcode": "44139",
    "addr:street": "Independence Ct",
    "iso:country": "US",
    "sg:address": "36945 Independence Ct",
    "sg:city": "Cleveland",
    "sg:classifiers": [
      {
        "category": "Building \u0026 Trades",
        "subcategory": "Construction",
        "type": "Services"
      }
    ],
    "sg:phone": "+1 440 248 0808",
    "sg:postcode": "44139",
    "sg:province": "OH",
    "sg:tags": [
      "acoustical",
      "contractor"
    ],
    "wof:name": "MJS Interiors",
    "wof:placetype": "venue"
  },
  "geometry": {"coordinates":[-81.416292,41.394648],"type":"Point"}
}
