{
  "type": "Feature",
  "properties": {
    "addr:full":"8977 Columbia Rd Loveland OH 45140",
    "addr:housenumber":"8977",
    "addr:postcode":"45140",
    "addr:street":"Columbia Rd",
    "iso:country":"US",
    "sg:address":"8977 Columbia Rd",
    "sg:city":"Loveland",
    "sg:classifiers":[
        {
            "category":"Professional",
            "subcategory":"Lawyer & Legal Services",
            "type":"Services"
        }
    ],
    "sg:phone":"+1 513 583 8888",
    "sg:postcode":"45140",
    "sg:province":"OH",
    "sg:tags":[
        "attorney"
    ],
    "wof:name":"Heath & Assoc",
    "wof:placetype":"venue"
},
  "geometry": {"coordinates":[-84.279568,39.305632],"type":"Point"}
}