{
  "type": "Feature",
  "properties": {
    "addr:full":"500 Ohio Ave Mc Donald OH 44437",
    "addr:housenumber":"500",
    "addr:postcode":"44437",
    "addr:street":"Ohio Ave Mc",
    "iso:country":"US",
    "sg:address":"500 Ohio Ave",
    "sg:city":"Mc Donald",
    "sg:classifiers":[
        {
            "category":"Government",
            "subcategory":"Post Office",
            "type":"Public Place"
        }
    ],
    "sg:phone":"+1 330 530 2887",
    "sg:postcode":"44437",
    "sg:province":"OH",
    "sg:tags":[
        "postal",
        "us"
    ],
    "wof:name":"US Post Office",
    "wof:placetype":"venue"
},
  "geometry": {"coordinates":[-80.724356,41.163463],"type":"Point"}
}