{
  "type": "Feature",
  "properties": {
    "iso:country":"US",
    "sg:address":"916 Columbus Ave",
    "sg:city":"Lebanon",
    "sg:classifiers":[
        {
            "category":"Government",
            "subcategory":"Office",
            "type":"Public Place"
        }
    ],
    "sg:phone":"+1 513 932 5825",
    "sg:postcode":"45036",
    "sg:province":"OH",
    "sg:tags":[
        "transportation"
    ],
    "wof:name":"Drivers Exam Station",
    "wof:placetype":"venue"
},
  "geometry": {"coordinates":[-84.192537,39.443221],"type":"Point"}
}