{
  "type": "Feature",
  "properties": {
    "iso:country":"US",
    "sg:address":"8080 State Rte 124",
    "sg:city":"Hillsboro",
    "sg:classifiers":[
        {
            "category":"Organizations",
            "subcategory":"Religious Organization",
            "type":"Services"
        }
    ],
    "sg:phone":"+1 937 393 2911",
    "sg:postcode":"45133",
    "sg:province":"OH",
    "sg:tags":[
        "church"
    ],
    "wof:name":"Hillsboro Bible Baptist Church",
    "wof:placetype":"venue"
},
  "geometry": {"coordinates":[-83.589983,39.195742],"type":"Point"}
}