{
  "type": "Feature",
  "properties": {
    "addr:full": "23737 Fairmount Blvd Cleveland OH 44122",
    "addr:housenumber": "23737",
    "addr:postcode": "44122",
    "addr:street": "Fairmount Blvd",
    "iso:country": "US",
    "sg:address": "23737 Fairmount Blvd",
    "sg:city": "Cleveland",
    "sg:classifiers": [
      {
        "category": "Shopping",
        "subcategory": "Gifts \u0026 Souvenirs",
        "type": "Retail Goods"
      }
    ],
    "sg:phone": "+1 216 464 1330",
    "sg:postcode": "44122",
    "sg:province": "OH",
    "wof:name": "Fairmount Temple Gift Shop",
    "wof:placetype": "venue"
  },
  "geometry": {"coordinates":[-81.509019,41.486362],"type":"Point"}
}
