{
  "type": "Feature",
  "properties": {
    "iso:country":"US",
    "sg:address":"41933 Co Rd 75",
    "sg:city":"Conesville",
    "sg:classifiers":[
        {
            "category":"Shopping",
            "subcategory":"Bicycles & Sporting Goods",
            "type":"Retail Goods"
        }
    ],
    "sg:phone":"+1 740 754 2969",
    "sg:postcode":"43811",
    "sg:province":"OH",
    "sg:tags":[
        "gun",
        "gunsmith"
    ],
    "wof:name":"J J's Guns & Hunting Supplies",
    "wof:placetype":"venue"
},
  "geometry": {"coordinates":[-81.98616699999999,40.182116],"type":"Point"}
}