{
  "type": "Feature",
  "properties": {
    "addr:full": "41933 Co Rd 75 Conesville OH 43811",
    "addr:housenumber": "41933;75",
    "addr:postcode": "43811",
    "addr:street": "Co Rd",
    "iso:country": "US",
    "sg:address": "41933 Co Rd 75",
    "sg:city": "Conesville",
    "sg:classifiers": [
      {
        "category": "Shopping",
        "subcategory": "Bicycles \u0026 Sporting Goods",
        "type": "Retail Goods"
      }
    ],
    "sg:phone": "+1 740 754 2969",
    "sg:postcode": "43811",
    "sg:province": "OH",
    "sg:tags": [
      "gun",
      "gunsmith"
    ],
    "wof:name": "J J's Guns \u0026 Hunting Supplies",
    "wof:placetype": "venue"
  },
  "geometry": {"coordinates":[-81.986167,40.182116],"type":"Point"}
}
