{
  "type": "Feature",
  "properties": {
    "iso:country":"US",
    "sg:address":"6817 Sutherland Ct",
    "sg:city":"Mentor",
    "sg:classifiers":[
        {
            "category":"Professional",
            "type":"Services"
        }
    ],
    "sg:phone":"+1 440 255 6537",
    "sg:postcode":"44060",
    "sg:province":"OH",
    "wof:name":"David E Richter",
    "wof:placetype":"venue"
},
  "geometry": {"coordinates":[-81.368239,41.684698],"type":"Point"}
}