{
  "type": "Feature",
  "properties": {
    "iso:country":"US",
    "sg:address":"20884 Royalton Rd",
    "sg:city":"Strongsville",
    "sg:classifiers":[
        {
            "category":"Recreation",
            "type":"Entertainment"
        }
    ],
    "sg:phone":"+1 440 572 3113",
    "sg:postcode":"44149",
    "sg:province":"OH",
    "sg:tags":[
        "martial",
        "arts",
        "instruction"
    ],
    "wof:name":"A A Kenpo Karate",
    "wof:placetype":"venue"
},
  "geometry": {"coordinates":[-81.855473,41.312552],"type":"Point"}
}