{
  "type": "Feature",
  "properties": {
    "addr:full": "635 Norton Ave Barberton OH 44203",
    "addr:housenumber": "635",
    "addr:postcode": "44203",
    "addr:street": "Norton Ave",
    "iso:country": "US",
    "sg:address": "635 Norton Ave",
    "sg:city": "Barberton",
    "sg:classifiers": [
      {
        "category": "Bars \u0026 Pubs",
        "type": "Food \u0026 Drink"
      }
    ],
    "sg:phone": "+1 330 745 0181",
    "sg:postcode": "44203",
    "sg:province": "OH",
    "sg:tags": [
      "drinking"
    ],
    "wof:name": "Shamrock Country Nite Club",
    "wof:placetype": "venue"
  },
  "geometry": {"coordinates":[-81.6111,41.024373],"type":"Point"}
}
