{
  "type": "Feature",
  "properties": {
    "iso:country":"US",
    "sg:address":"2800 Keenan Ave",
    "sg:city":"Dayton",
    "sg:classifiers":[
        {
            "category":"Manufacturing",
            "subcategory":"Metals",
            "type":"Manufacturing & Wholesale Goods"
        }
    ],
    "sg:phone":"+1 937 222 6732",
    "sg:postcode":"45414",
    "sg:province":"OH",
    "sg:tags":[
        "spinning"
    ],
    "sg:website":"www.spinmetal.com",
    "wof:name":"Dayton United Metal Spinners",
    "wof:placetype":"venue"
},
  "geometry": {"coordinates":[-84.17919999999999,39.806413],"type":"Point"}
}