{
  "type": "Feature",
  "properties": {
    "addr:full": "2800 Keenan Ave Dayton OH 45414",
    "addr:housenumber": "2800",
    "addr:postcode": "45414",
    "addr:street": "Keenan Ave",
    "iso:country": "US",
    "sg:address": "2800 Keenan Ave",
    "sg:city": "Dayton",
    "sg:classifiers": [
      {
        "category": "Manufacturing",
        "subcategory": "Metals",
        "type": "Manufacturing \u0026 Wholesale Goods"
      }
    ],
    "sg:phone": "+1 937 222 6732",
    "sg:postcode": "45414",
    "sg:province": "OH",
    "sg:tags": [
      "spinning"
    ],
    "sg:website": "www.spinmetal.com",
    "wof:name": "Dayton United Metal Spinners",
    "wof:placetype": "venue"
  },
  "geometry": {"coordinates":[-84.1792,39.806413],"type":"Point"}
}
