{
  "type": "Feature",
  "properties": {
    "addr:full": "355 E Selby Blvd Worthington OH 43085",
    "addr:housenumber": "355",
    "addr:postcode": "43085",
    "addr:street": "E Selby Blvd",
    "iso:country": "US",
    "sg:address": "355 E Selby Blvd",
    "sg:city": "Worthington",
    "sg:classifiers": [
      {
        "category": "Social Services",
        "subcategory": "Job Training",
        "type": "Services"
      }
    ],
    "sg:phone": "+1 614 888 6976",
    "sg:postcode": "43085",
    "sg:province": "OH",
    "sg:tags": [
      "rehabilitation"
    ],
    "wof:name": "Vocational Alternatives",
    "wof:placetype": "venue"
  },
  "geometry": {"coordinates":[-83.009635,40.077249],"type":"Point"}
}
