{
  "type": "Feature",
  "properties": {
    "addr:full":"4236 Hazelton-Etna Rd SW Pataskala OH 43062",
    "addr:housenumber":"4236",
    "addr:postcode":"43062",
    "addr:street":"Hazelton-Etna Rd Sw",
    "iso:country":"US",
    "sg:address":"4236 Hazelton-Etna Rd SW",
    "sg:city":"Pataskala",
    "sg:classifiers":[
        {
            "category":"Building & Trades",
            "subcategory":"Landscaping Services",
            "type":"Services"
        }
    ],
    "sg:phone":"+1 740 927 8803",
    "sg:postcode":"43062",
    "sg:province":"OH",
    "sg:tags":[
        "farm",
        "landscape",
        "contractor"
    ],
    "wof:name":"Willits Nursery Co",
    "wof:placetype":"venue"
},
  "geometry": {"coordinates":[-82.671026,40.02451],"type":"Point"}
}