{
  "type": "Feature",
  "properties": {
    "addr:full": "8501 Springboro Pike Miamisburg OH 45342",
    "addr:housenumber": "8501",
    "addr:postcode": "45342",
    "addr:street": "Springboro Pike",
    "iso:country": "US",
    "sg:address": "8501 Springboro Pike",
    "sg:city": "Miamisburg",
    "sg:classifiers": [
      {
        "category": "Freight",
        "type": "Transportation"
      }
    ],
    "sg:phone": "+1 937 435 3244",
    "sg:postcode": "45342",
    "sg:province": "OH",
    "sg:tags": [
      "commercial",
      "storage"
    ],
    "sg:website": "www.ustoreit.com",
    "wof:name": "U-Store-It",
    "wof:placetype": "venue"
  },
  "geometry": {"coordinates":[-84.226066,39.628266],"type":"Point"}
}
