{
  "type": "Feature",
  "properties": {
    "addr:full": "633 N Vandemark Rd Sidney OH 45365",
    "addr:housenumber": "633",
    "addr:postcode": "45365",
    "addr:street": "N Vandemark Rd",
    "iso:country": "US",
    "sg:address": "633 N Vandemark Rd",
    "sg:city": "Sidney",
    "sg:classifiers": [
      {
        "category": "Home \u0026 Garden",
        "subcategory": "Building Materials",
        "type": "Retail Goods"
      }
    ],
    "sg:phone": "+1 937 492 6275",
    "sg:postcode": "45365",
    "sg:province": "OH",
    "wof:name": "Hemms Glass",
    "wof:placetype": "venue"
  },
  "geometry": {"coordinates":[-84.188006,40.294479],"type":"Point"}
}
