{
  "type": "Feature",
  "properties": {
    "iso:country":"US",
    "sg:address":"732 E National Rd",
    "sg:city":"Vandalia",
    "sg:classifiers":[
        {
            "category":"Food & Beverages",
            "subcategory":"Groceries & Convenience Stores",
            "type":"Retail Goods"
        }
    ],
    "sg:phone":"+1 937 898 6463",
    "sg:postcode":"45377",
    "sg:province":"OH",
    "wof:name":"Fulmer Foods",
    "wof:placetype":"venue"
},
  "geometry": {"coordinates":[-84.18347799999999,39.892073],"type":"Point"}
}