{
  "type": "Feature",
  "properties": {
    "addr:full":"1740 Cumberland Rd Cleveland OH 44118",
    "addr:housenumber":"1740",
    "addr:postcode":"44118",
    "addr:street":"Cumberland Rd",
    "iso:country":"US",
    "sg:address":"1740 Cumberland Rd",
    "sg:city":"Cleveland",
    "sg:classifiers":[
        {
            "category":"Recreation",
            "type":"Entertainment"
        }
    ],
    "sg:phone":"+1 216 691 7390",
    "sg:postcode":"44118",
    "sg:province":"OH",
    "sg:tags":[
        "pool",
        "swimming"
    ],
    "wof:name":"Cumberland Pool",
    "wof:placetype":"venue"
},
  "geometry": {"coordinates":[-81.56790700000001,41.510632],"type":"Point"}
}