{
  "type": "Feature",
  "properties": {
    "addr:full": "2124 Pershing Blvd Dayton OH 45420",
    "addr:housenumber": "2124",
    "addr:postcode": "45420",
    "addr:street": "Pershing Blvd",
    "iso:country": "US",
    "sg:address": "2124 Pershing Blvd",
    "sg:city": "Dayton",
    "sg:classifiers": [
      {
        "category": "Building \u0026 Trades",
        "subcategory": "Landscaping Services",
        "type": "Services"
      }
    ],
    "sg:phone": "+1 937 253 9546",
    "sg:postcode": "45420",
    "sg:province": "OH",
    "wof:name": "Montgomery Tree Works",
    "wof:placetype": "venue"
  },
  "geometry": {"coordinates":[-84.146357,39.735895],"type":"Point"}
}
