{
  "type": "Feature",
  "properties": {
    "iso:country":"US",
    "sg:address":"8303 Sancus Blvd",
    "sg:city":"Westerville",
    "sg:classifiers":[
        {
            "category":"Food & Beverages",
            "subcategory":"Groceries & Convenience Stores",
            "type":"Retail Goods"
        }
    ],
    "sg:phone":"+1 614 885 9970",
    "sg:postcode":"43081",
    "sg:province":"OH",
    "wof:name":"Dairy Mart Convenience Store",
    "wof:placetype":"venue"
},
  "geometry": {"coordinates":[-82.991824,40.134716],"type":"Point"}
}