{
  "type": "Feature",
  "properties": {
    "addr:full": "112 W Liberty St Wooster OH 44691",
    "addr:housenumber": "112",
    "addr:postcode": "44691",
    "addr:street": "W Liberty St",
    "iso:country": "US",
    "sg:address": "112 W Liberty St",
    "sg:city": "Wooster",
    "sg:classifiers": [
      {
        "category": "Banks \u0026 Credit Unions",
        "subcategory": "Bank",
        "type": "Services"
      }
    ],
    "sg:phone": "+1 330 264 1222",
    "sg:postcode": "44691",
    "sg:province": "OH",
    "sg:website": "www.wcnbwooster.com",
    "wof:name": "National City Bank",
    "wof:placetype": "venue"
  },
  "geometry": {"coordinates":[-81.940035,40.798129],"type":"Point"}
}
