{
  "type": "Feature",
  "properties": {
    "addr:full":"335 Clinton Heights Ave Columbus OH 43202",
    "addr:housenumber":"335",
    "addr:postcode":"43202",
    "addr:street":"Clinton Heights Ave",
    "iso:country":"US",
    "sg:address":"335 Clinton Heights Ave",
    "sg:city":"Columbus",
    "sg:classifiers":[
        {
            "category":"Personal",
            "type":"Services"
        }
    ],
    "sg:phone":"+1 614 447 7529",
    "sg:postcode":"43202",
    "sg:province":"OH",
    "sg:tags":[
        "therapist",
        "massage"
    ],
    "wof:name":"Jan M Lindner",
    "wof:placetype":"venue"
},
  "geometry": {"coordinates":[-83.00219199999999,40.029917],"type":"Point"}
}