{
  "type": "Feature",
  "properties": {
    "addr:full": "2909 N Detroit Ave Toledo OH 43610",
    "addr:housenumber": "2909",
    "addr:postcode": "43610",
    "addr:street": "N Detroit Ave",
    "iso:country": "US",
    "sg:address": "2909 N Detroit Ave",
    "sg:city": "Toledo",
    "sg:classifiers": [
      {
        "category": "Organizations",
        "subcategory": "Religious Organization",
        "type": "Services"
      }
    ],
    "sg:phone": "+1 419 244 3537",
    "sg:postcode": "43610",
    "sg:province": "OH",
    "sg:tags": [
      "church"
    ],
    "wof:name": "True Light Pentecostal Church",
    "wof:placetype": "venue"
  },
  "geometry": {"coordinates":[-83.562689,41.676612],"type":"Point"}
}
