{
  "type": "Feature",
  "properties": {
    "addr:full": "8121 Main St Garrettsville OH 44231",
    "addr:housenumber": "8121",
    "addr:postcode": "44231",
    "addr:street": "Main St",
    "iso:country": "US",
    "sg:address": "8121 Main St",
    "sg:city": "Garrettsville",
    "sg:classifiers": [
      {
        "category": "Professional",
        "subcategory": "Lawyer \u0026 Legal Services",
        "type": "Services"
      }
    ],
    "sg:phone": "+1 330 527 2335",
    "sg:postcode": "44231",
    "sg:province": "OH",
    "sg:tags": [
      "attorney"
    ],
    "wof:name": "Robert E Mishler Realty Inc",
    "wof:placetype": "venue"
  },
  "geometry": {"coordinates":[-81.096968,41.284237],"type":"Point"}
}
