{
  "type": "Feature",
  "properties": {
    "addr:full": "35 N Walnut St London OH 43140",
    "addr:housenumber": "35",
    "addr:postcode": "43140",
    "addr:street": "N Walnut St",
    "iso:country": "US",
    "sg:address": "35 N Walnut St",
    "sg:city": "London",
    "sg:classifiers": [
      {
        "category": "Building \u0026 Trades",
        "subcategory": "Construction",
        "type": "Services"
      }
    ],
    "sg:phone": "+1 740 852 7539",
    "sg:postcode": "43140",
    "sg:province": "OH",
    "sg:tags": [
      "house"
    ],
    "wof:name": "Youngs Home Improvement",
    "wof:placetype": "venue"
  },
  "geometry": {"coordinates":[-83.446625,39.887678],"type":"Point"}
}
