{
  "type": "Feature",
  "properties": {
    "addr:full": "120 Colton Ave Bellefontaine OH 43311",
    "addr:housenumber": "120",
    "addr:postcode": "43311",
    "addr:street": "Colton Ave",
    "iso:country": "US",
    "sg:address": "120 Colton Ave",
    "sg:city": "Bellefontaine",
    "sg:classifiers": [
      {
        "category": "Organizations",
        "subcategory": "Community Association",
        "type": "Services"
      }
    ],
    "sg:phone": "+1 937 592 4891",
    "sg:postcode": "43311",
    "sg:province": "OH",
    "wof:name": "Harold Kerr Post 173",
    "wof:placetype": "venue"
  },
  "geometry": {"coordinates":[-83.760201,40.353917],"type":"Point"}
}
