{
  "type": "Feature",
  "properties": {
    "addr:full":"1743 Fife Ave Wilmington OH 45177",
    "addr:housenumber":"1743",
    "addr:postcode":"45177",
    "addr:street":"Fife Ave",
    "iso:country":"US",
    "sg:address":"1743 Fife Ave",
    "sg:city":"Wilmington",
    "sg:classifiers":[
        {
            "category":"Retail",
            "subcategory":"Auto Repair",
            "type":"Services"
        }
    ],
    "sg:phone":"+1 937 382 5265",
    "sg:postcode":"45177",
    "sg:province":"OH",
    "sg:tags":[
        "brake"
    ],
    "wof:name":"B & B Brakes & Towing",
    "wof:placetype":"venue"
},
  "geometry": {"coordinates":[-83.800366,39.438958],"type":"Point"}
}