{
  "type": "Feature",
  "properties": {
    "iso:country":"US",
    "sg:address":"9909 Avon Lake Rd",
    "sg:city":"Burbank",
    "sg:classifiers":[
        {
            "category":"Restaurant",
            "type":"Food & Drink"
        }
    ],
    "sg:phone":"+1 330 948 8316",
    "sg:postcode":"44214",
    "sg:province":"OH",
    "sg:website":"www.arbys.com",
    "wof:name":"Arby's",
    "wof:placetype":"venue"
},
  "geometry": {"coordinates":[-81.996174,41.003022],"type":"Point"}
}