{
  "type": "Feature",
  "properties": {
    "addr:full": "13917 Tyler Ave Cleveland OH 44111",
    "addr:housenumber": "13917",
    "addr:postcode": "44111",
    "addr:street": "Tyler Ave",
    "iso:country": "US",
    "sg:address": "13917 Tyler Ave",
    "sg:city": "Cleveland",
    "sg:classifiers": [
      {
        "category": "Shopping",
        "subcategory": "Gifts \u0026 Souvenirs",
        "type": "Retail Goods"
      }
    ],
    "sg:phone": "+1 216 671 0463",
    "sg:postcode": "44111",
    "sg:province": "OH",
    "wof:name": "Goober Ann \u0026 Friends",
    "wof:placetype": "venue"
  },
  "geometry": {"coordinates":[-81.788485,41.446511],"type":"Point"}
}
