{
  "type": "Feature",
  "properties": {
    "iso:country":"US",
    "sg:address":"13917 Tyler Ave",
    "sg:city":"Cleveland",
    "sg:classifiers":[
        {
            "category":"Shopping",
            "subcategory":"Gifts & Souvenirs",
            "type":"Retail Goods"
        }
    ],
    "sg:phone":"+1 216 671 0463",
    "sg:postcode":"44111",
    "sg:province":"OH",
    "wof:name":"Goober Ann & Friends",
    "wof:placetype":"venue"
},
  "geometry": {"coordinates":[-81.78848499999999,41.446511],"type":"Point"}
}