{
  "type": "Feature",
  "properties": {
    "addr:full": "2846 Mahoning Ave Youngstown OH 44509",
    "addr:housenumber": "2846",
    "addr:postcode": "44509",
    "addr:street": "Mahoning Ave",
    "iso:country": "US",
    "sg:address": "2846 Mahoning Ave",
    "sg:city": "Youngstown",
    "sg:classifiers": [
      {
        "category": "Shopping",
        "subcategory": "Pharmacy",
        "type": "Retail Goods"
      }
    ],
    "sg:phone": "+1 330 792 8668",
    "sg:postcode": "44509",
    "sg:province": "OH",
    "sg:tags": [
      "drug",
      "store"
    ],
    "wof:name": "CVS",
    "wof:placetype": "venue"
  },
  "geometry": {"coordinates":[-80.702337,41.103141],"type":"Point"}
}
