{
  "type": "Feature",
  "properties": {
    "addr:full": "122 S Main St Cadiz OH 43907",
    "addr:housenumber": "122",
    "addr:postcode": "43907",
    "addr:street": "S Main St",
    "iso:country": "US",
    "sg:address": "122 S Main St",
    "sg:city": "Cadiz",
    "sg:classifiers": [
      {
        "category": "Shopping",
        "subcategory": "Pharmacy",
        "type": "Retail Goods"
      }
    ],
    "sg:phone": "+1 740 942 2726",
    "sg:postcode": "43907",
    "sg:province": "OH",
    "sg:tags": [
      "drug",
      "store"
    ],
    "wof:name": "Custer Pharmacy",
    "wof:placetype": "venue"
  },
  "geometry": {"coordinates":[-80.997279,40.272718],"type":"Point"}
}
