{
  "type": "Feature",
  "properties": {
    "addr:full": "1088 E Tallmadge Ave Akron OH 44310",
    "addr:housenumber": "1088",
    "addr:postcode": "44310",
    "addr:street": "E Tallmadge Ave",
    "iso:country": "US",
    "sg:address": "1088 E Tallmadge Ave",
    "sg:city": "Akron",
    "sg:classifiers": [
      {
        "category": "Personal",
        "subcategory": "Beauty Salon",
        "type": "Services"
      }
    ],
    "sg:phone": "+1 330 633 7181",
    "sg:postcode": "44310",
    "sg:province": "OH",
    "wof:name": "J \u0026 J Styling Ctr Tanning",
    "wof:placetype": "venue"
  },
  "geometry": {"coordinates":[-81.476596,41.10197],"type":"Point"}
}
