{
  "type": "Feature",
  "properties": {
    "addr:full": "853 E Liberty St Hubbard OH 44425",
    "addr:housenumber": "853",
    "addr:postcode": "44425",
    "addr:street": "E Liberty St",
    "iso:country": "US",
    "sg:address": "853 E Liberty St",
    "sg:city": "Hubbard",
    "sg:classifiers": [
      {
        "category": "Food \u0026 Beverages",
        "subcategory": "Groceries \u0026 Convenience Stores",
        "type": "Retail Goods"
      }
    ],
    "sg:phone": "+1 330 534 1376",
    "sg:postcode": "44425",
    "sg:province": "OH",
    "wof:name": "Nadias Mini Market",
    "wof:placetype": "venue"
  },
  "geometry": {"coordinates":[-80.553936,41.157839],"type":"Point"}
}
