{
  "type": "Feature",
  "properties": {
    "iso:country":"US",
    "sg:address":"853 E Liberty St",
    "sg:city":"Hubbard",
    "sg:classifiers":[
        {
            "category":"Food & Beverages",
            "subcategory":"Groceries & Convenience Stores",
            "type":"Retail Goods"
        }
    ],
    "sg:phone":"+1 330 534 1376",
    "sg:postcode":"44425",
    "sg:province":"OH",
    "wof:name":"Nadias Mini Market",
    "wof:placetype":"venue"
},
  "geometry": {"coordinates":[-80.55393599999999,41.157839],"type":"Point"}
}