{
  "type": "Feature",
  "properties": {
    "iso:country":"US",
    "sg:address":"20 S Shawnee Ave",
    "sg:city":"Zanesville",
    "sg:classifiers":[
        {
            "category":"Insurance",
            "subcategory":"Insurance Agent",
            "type":"Services"
        }
    ],
    "sg:phone":"+1 740 453 3609",
    "sg:postcode":"43701",
    "sg:province":"OH",
    "wof:name":"Houston Insurance",
    "wof:placetype":"venue"
},
  "geometry": {"coordinates":[-82.01961,39.901641],"type":"Point"}
}