{
  "type": "Feature",
  "properties": {
    "iso:country":"US",
    "sg:address":"2802 State Rte 4",
    "sg:city":"Bellevue",
    "sg:classifiers":[
        {
            "category":"Local Transit",
            "type":"Transportation"
        }
    ],
    "sg:phone":"+1 419 483 8121",
    "sg:postcode":"44811",
    "sg:province":"OH",
    "wof:name":"Jeanette Lyons",
    "wof:placetype":"venue"
},
  "geometry": {"coordinates":[-82.841536,41.163671],"type":"Point"}
}