{
  "type": "Feature",
  "properties": {
    "addr:full": "5119 Glenway Ave Cincinnati OH 45238",
    "addr:housenumber": "5119",
    "addr:postcode": "45238",
    "addr:street": "Glenway Ave",
    "iso:country": "US",
    "sg:address": "5119 Glenway Ave",
    "sg:city": "Cincinnati",
    "sg:classifiers": [
      {
        "category": "Banks \u0026 Credit Unions",
        "subcategory": "Bank",
        "type": "Services"
      }
    ],
    "sg:phone": "+1 513 471 7300",
    "sg:postcode": "45238",
    "sg:province": "OH",
    "sg:tags": [
      "federal",
      "savings",
      "institution"
    ],
    "wof:name": "Franklin Savings \u0026 Loan Co",
    "wof:placetype": "venue"
  },
  "geometry": {"coordinates":[-84.602765,39.123441],"type":"Point"}
}
