{
  "type": "Feature",
  "properties": {
    "addr:full":"6863 Mahoning Ave NW Warren OH 44481",
    "addr:housenumber":"6863",
    "addr:postcode":"44481",
    "addr:street":"Mahoning Ave Nw",
    "iso:country":"US",
    "sg:address":"6863 Mahoning Ave NW",
    "sg:city":"Warren",
    "sg:classifiers":[
        {
            "category":"Recreation",
            "type":"Entertainment"
        }
    ],
    "sg:phone":"+1 330 847 8614",
    "sg:postcode":"44481",
    "sg:province":"OH",
    "sg:tags":[
        "pool",
        "swimming"
    ],
    "wof:name":"Willow Lake Park Inc",
    "wof:placetype":"venue"
},
  "geometry": {"coordinates":[-80.858097,41.343758],"type":"Point"}
}