{
  "type": "Feature",
  "properties": {
    "addr:full": "1661 State Rte 98 Bucyrus OH 44820",
    "addr:housenumber": "1661",
    "addr:postcode": "44820",
    "addr:street": "State Rte 98",
    "iso:country": "US",
    "sg:address": "1661 State Rte 98",
    "sg:city": "Bucyrus",
    "sg:classifiers": [
      {
        "category": "Shopping",
        "subcategory": "Gifts \u0026 Souvenirs",
        "type": "Retail Goods"
      }
    ],
    "sg:phone": "+1 419 562 8083",
    "sg:postcode": "44820",
    "sg:province": "OH",
    "wof:name": "Ppk Oriangles",
    "wof:placetype": "venue"
  },
  "geometry": {"coordinates":[-82.978861,40.788675],"type":"Point"}
}
