{
  "type": "Feature",
  "properties": {
    "addr:full":"199 Gateway Ave Conneaut OH 44030",
    "addr:housenumber":"199",
    "addr:postcode":"44030",
    "addr:street":"Gateway Ave",
    "iso:country":"US",
    "sg:address":"199 Gateway Ave",
    "sg:city":"Conneaut",
    "sg:classifiers":[
        {
            "category":"Autos & Motor Vehicles",
            "subcategory":"Auto Supplies",
            "type":"Retail Goods"
        }
    ],
    "sg:phone":"+1 440 593 6934",
    "sg:postcode":"44030",
    "sg:province":"OH",
    "sg:tags":[
        "automobile",
        "parts",
        "accessory"
    ],
    "sg:website":"www.autozone.com",
    "wof:name":"Autozone",
    "wof:placetype":"venue"
},
  "geometry": {"coordinates":[-80.56806899999999,41.923483],"type":"Point"}
}