{
  "type": "Feature",
  "properties": {
    "addr:full":"32000 Powder Plant Rd Mc Arthur OH 45651",
    "addr:housenumber":"32000",
    "addr:postcode":"45651",
    "addr:street":"Powder Plant Rd",
    "iso:country":"US",
    "sg:address":"32000 Powder Plant Rd",
    "sg:city":"Mc Arthur",
    "sg:classifiers":[
        {
            "category":"Shopping",
            "subcategory":"Discount & Variety Stores",
            "type":"Retail Goods"
        }
    ],
    "sg:phone":"+1 740 596 2513",
    "sg:postcode":"45651",
    "sg:province":"OH",
    "sg:tags":[
        "merchandise",
        "general"
    ],
    "wof:name":"Mc Arthur Sales Office",
    "wof:placetype":"venue"
},
  "geometry": {"coordinates":[-82.43407500000001,39.253443],"type":"Point"}
}