{
  "type": "Feature",
  "properties": {
    "iso:country":"US",
    "sg:address":"2634 Jackson Pike",
    "sg:city":"Batavia",
    "sg:classifiers":[
        {
            "category":"Building & Trades",
            "subcategory":"Plumbing",
            "type":"Services"
        }
    ],
    "sg:phone":"+1 513 735 2137",
    "sg:postcode":"45103",
    "sg:province":"OH",
    "sg:tags":[
        "plumbing",
        "contractor"
    ],
    "wof:name":"D & P Plumbing",
    "wof:placetype":"venue"
},
  "geometry": {"coordinates":[-84.133302,39.117234],"type":"Point"}
}