{
  "type": "Feature",
  "properties": {
    "iso:country":"US",
    "sg:address":"2602 Elm St",
    "sg:city":"Toledo",
    "sg:classifiers":[
        {
            "category":"Building & Trades",
            "subcategory":"Cleaning & Sanitation",
            "type":"Services"
        }
    ],
    "sg:phone":"+1 419 259 0623",
    "sg:postcode":"43608",
    "sg:province":"OH",
    "sg:tags":[
        "janitor"
    ],
    "wof:name":"Donna's Quality Cleaning",
    "wof:placetype":"venue"
},
  "geometry": {"coordinates":[-83.536002,41.673607],"type":"Point"}
}