{
  "type": "Feature",
  "properties": {
    "iso:country":"US",
    "sg:address":"29 W Main St",
    "sg:city":"Norwalk",
    "sg:classifiers":[
        {
            "category":"Professional",
            "subcategory":"Advertising",
            "type":"Services"
        }
    ],
    "sg:phone":"+1 419 668 3776",
    "sg:postcode":"44857",
    "sg:province":"OH",
    "wof:name":"Media One Advertising",
    "wof:placetype":"venue"
},
  "geometry": {"coordinates":[-82.616567,41.241773],"type":"Point"}
}