{
  "type": "Feature",
  "properties": {
    "addr:full": "29 W Main St Norwalk OH 44857",
    "addr:housenumber": "29",
    "addr:postcode": "44857",
    "addr:street": "W Main St",
    "iso:country": "US",
    "sg:address": "29 W Main St",
    "sg:city": "Norwalk",
    "sg:classifiers": [
      {
        "category": "Professional",
        "subcategory": "Advertising",
        "type": "Services"
      }
    ],
    "sg:phone": "+1 419 668 3776",
    "sg:postcode": "44857",
    "sg:province": "OH",
    "wof:name": "Media One Advertising",
    "wof:placetype": "venue"
  },
  "geometry": {"coordinates":[-82.616567,41.241773],"type":"Point"}
}
