{
  "type": "Feature",
  "properties": {
    "addr:full":"1635 River Valley Cir S Lancaster OH 43130",
    "addr:housenumber":"1635",
    "addr:postcode":"43130",
    "addr:street":"River Valley Cir S",
    "iso:country":"US",
    "sg:address":"1635 River Valley Cir S",
    "sg:city":"Lancaster",
    "sg:classifiers":[
        {
            "category":"Restaurant",
            "type":"Food & Drink"
        }
    ],
    "sg:menulink":"http://www.allmenus.com/oh/lancaster/72584-sbarro/menu/",
    "sg:phone":"+1 740 689 0197",
    "sg:postcode":"43130",
    "sg:province":"OH",
    "sg:tags":[
        "american",
        "pizza"
    ],
    "wof:name":"Sbarro",
    "wof:placetype":"venue"
},
  "geometry": {"coordinates":[-82.629294,39.730386],"type":"Point"}
}