{
  "type": "Feature",
  "properties": {
    "addr:full":"111 S Nelson Ave Wilmington OH 45177",
    "addr:housenumber":"111",
    "addr:postcode":"45177",
    "addr:street":"S Nelson Ave",
    "iso:country":"US",
    "sg:address":"111 S Nelson Ave",
    "sg:city":"Wilmington",
    "sg:classifiers":[
        {
            "category":"Government",
            "subcategory":"Office",
            "type":"Public Place"
        }
    ],
    "sg:phone":"+1 937 382 2461",
    "sg:postcode":"45177",
    "sg:province":"OH",
    "sg:tags":[
        "federal"
    ],
    "wof:name":"Natural Resources Conservation",
    "wof:placetype":"venue"
},
  "geometry": {"coordinates":[-83.851884,39.443803],"type":"Point"}
}