{
  "type": "Feature",
  "properties": {
    "addr:full": "1922 Dunkeith Dr NW Canton OH 44708",
    "addr:housenumber": "1922",
    "addr:postcode": "44708",
    "addr:street": "Dunkeith Dr Nw",
    "iso:country": "US",
    "sg:address": "1922 Dunkeith Dr NW",
    "sg:city": "Canton",
    "sg:classifiers": [
      {
        "category": "Organizations",
        "subcategory": "Religious Organization",
        "type": "Services"
      }
    ],
    "sg:phone": "+1 330 477 2414",
    "sg:postcode": "44708",
    "sg:province": "OH",
    "sg:tags": [
      "clergy"
    ],
    "wof:name": "Jack H Dawson",
    "wof:placetype": "venue"
  },
  "geometry": {"coordinates":[-81.439904,40.821199],"type":"Point"}
}
