{
  "type": "Feature",
  "properties": {
    "iso:country":"US",
    "sg:address":"3906 Rocky River Dr",
    "sg:city":"Cleveland",
    "sg:classifiers":[
        {
            "category":"Health Services",
            "subcategory":"Doctor",
            "type":"Services"
        }
    ],
    "sg:phone":"+1 216 251 1232",
    "sg:postcode":"44111",
    "sg:province":"OH",
    "sg:tags":[
        "dentist"
    ],
    "wof:name":"Casey L O'Connor Orthodontics",
    "wof:placetype":"venue"
},
  "geometry": {"coordinates":[-81.817375,41.448402],"type":"Point"}
}