{
  "type": "Feature",
  "properties": {
    "iso:country":"US",
    "sg:address":"3031 S Limestone St",
    "sg:city":"Springfield",
    "sg:classifiers":[
        {
            "category":"Professional",
            "subcategory":"Accounting & Tax Preparation",
            "type":"Services"
        }
    ],
    "sg:phone":"+1 937 322 2168",
    "sg:postcode":"45505",
    "sg:province":"OH",
    "sg:tags":[
        "accountant"
    ],
    "wof:name":"Judith A Paden CPA",
    "wof:placetype":"venue"
},
  "geometry": {"coordinates":[-83.81313400000001,39.879951],"type":"Point"}
}