{
  "type": "Feature",
  "properties": {
    "iso:country":"US",
    "sg:address":"214 Lima Ave",
    "sg:city":"Huron",
    "sg:classifiers":[
        {
            "category":"Food & Beverages",
            "subcategory":"Bakery",
            "type":"Retail Goods"
        }
    ],
    "sg:phone":"+1 419 621 7444",
    "sg:postcode":"44839",
    "sg:province":"OH",
    "sg:tags":[
        "baker"
    ],
    "wof:name":"Neat Sweets Bakery",
    "wof:placetype":"venue"
},
  "geometry": {"coordinates":[-82.578035,41.409],"type":"Point"}
}