{
  "type": "Feature",
  "properties": {
    "addr:full": "214 Lima Ave Huron OH 44839",
    "addr:housenumber": "214",
    "addr:postcode": "44839",
    "addr:street": "Lima Ave",
    "iso:country": "US",
    "sg:address": "214 Lima Ave",
    "sg:city": "Huron",
    "sg:classifiers": [
      {
        "category": "Food \u0026 Beverages",
        "subcategory": "Bakery",
        "type": "Retail Goods"
      }
    ],
    "sg:phone": "+1 419 621 7444",
    "sg:postcode": "44839",
    "sg:province": "OH",
    "sg:tags": [
      "baker"
    ],
    "wof:name": "Neat Sweets Bakery",
    "wof:placetype": "venue"
  },
  "geometry": {"coordinates":[-82.578035,41.409],"type":"Point"}
}
