{
  "type": "Feature",
  "properties": {
    "addr:full": "332 Buckeye Blvd Port Clinton OH 43452",
    "addr:housenumber": "332",
    "addr:postcode": "43452",
    "addr:street": "Buckeye Blvd",
    "iso:country": "US",
    "sg:address": "332 Buckeye Blvd",
    "sg:city": "Port Clinton",
    "sg:classifiers": [
      {
        "category": "Personal",
        "subcategory": "Beauty Salon",
        "type": "Services"
      }
    ],
    "sg:phone": "+1 419 732 3302",
    "sg:postcode": "43452",
    "sg:province": "OH",
    "sg:tags": [
      "shop"
    ],
    "sg:website": "www.hair-quarters.com",
    "wof:name": "Hair Quarters Inc",
    "wof:placetype": "venue"
  },
  "geometry": {"coordinates":[-82.913239,41.510583],"type":"Point"}
}
