{
  "type": "Feature",
  "properties": {
    "iso:country":"US",
    "sg:address":"7197 Co Rd 46",
    "sg:city":"Mt Gilead",
    "sg:classifiers":[
        {
            "category":"Organizations",
            "subcategory":"Religious Organization",
            "type":"Services"
        }
    ],
    "sg:phone":"+1 419 946 4244",
    "sg:postcode":"43338",
    "sg:province":"OH",
    "sg:tags":[
        "church"
    ],
    "wof:name":"Pleasant Grove Church-Christ",
    "wof:placetype":"venue"
},
  "geometry": {"coordinates":[-82.74705,40.622374],"type":"Point"}
}