{
  "type": "Feature",
  "properties": {
    "addr:full": "3500 Sherman Church Ave SW Canton OH 44706",
    "addr:housenumber": "3500",
    "addr:postcode": "44706",
    "addr:street": "Sherman Church Ave Sw",
    "iso:country": "US",
    "sg:address": "3500 Sherman Church Ave SW",
    "sg:city": "Canton",
    "sg:classifiers": [
      {
        "category": "Organizations",
        "subcategory": "Religious Organization",
        "type": "Services"
      }
    ],
    "sg:phone": "+1 330 484 3133",
    "sg:postcode": "44706",
    "sg:province": "OH",
    "sg:tags": [
      "church"
    ],
    "sg:website": "www.cantoncommunitychurch.net",
    "wof:name": "Canton Community Church",
    "wof:placetype": "venue"
  },
  "geometry": {"coordinates":[-81.418998,40.759324],"type":"Point"}
}
