{
  "type": "Feature",
  "properties": {
    "addr:full": "228 S Main St Bryan OH 43506",
    "addr:housenumber": "228",
    "addr:postcode": "43506",
    "addr:street": "S Main St",
    "iso:country": "US",
    "sg:address": "228 S Main St",
    "sg:city": "Bryan",
    "sg:classifiers": [
      {
        "category": "Social Services",
        "type": "Services"
      }
    ],
    "sg:phone": "+1 419 636 1092",
    "sg:postcode": "43506",
    "sg:province": "OH",
    "sg:tags": [
      "organization",
      "mentoring",
      "welfare"
    ],
    "wof:name": "Big Brothers \u0026 Big Sisters",
    "wof:placetype": "venue"
  },
  "geometry": {"coordinates":[-84.551116,41.472931],"type":"Point"}
}
