{
  "type": "Feature",
  "properties": {
    "addr:full": "5305 Springfield Xenia Rd Springfield OH 45506",
    "addr:housenumber": "5305",
    "addr:postcode": "45506",
    "addr:street": "Springfield Xenia Rd",
    "iso:country": "US",
    "sg:address": "5305 Springfield Xenia Rd",
    "sg:city": "Springfield",
    "sg:classifiers": [
      {
        "category": "Wholesale",
        "subcategory": "Machinery \u0026 Supplies",
        "type": "Manufacturing \u0026 Wholesale Goods"
      },
      {
        "category": "Professional",
        "type": "Services"
      }
    ],
    "sg:phone": "+1 937 525 9913",
    "sg:postcode": "45506",
    "sg:province": "OH",
    "sg:tags": [
      "repairing"
    ],
    "wof:name": "Mc Kibben Inc",
    "wof:placetype": "venue"
  },
  "geometry": {"coordinates":[-83.858508,39.848328],"type":"Point"}
}
