{
  "type": "Feature",
  "properties": {
    "iso:country":"US",
    "sg:address":"328 Village St",
    "sg:city":"Hamilton",
    "sg:classifiers":[
        {
            "category":"Shopping",
            "subcategory":"Crafts & Fabrics",
            "type":"Retail Goods"
        }
    ],
    "sg:phone":"+1 513 868 7556",
    "sg:postcode":"45011",
    "sg:province":"OH",
    "sg:tags":[
        "material",
        "needlework"
    ],
    "wof:name":"Stitch & Such Needlework",
    "wof:placetype":"venue"
},
  "geometry": {"coordinates":[-84.557234,39.403654],"type":"Point"}
}