{
  "type": "Feature",
  "properties": {
    "addr:full": "328 Village St Hamilton OH 45011",
    "addr:housenumber": "328",
    "addr:postcode": "45011",
    "addr:street": "Village St",
    "iso:country": "US",
    "sg:address": "328 Village St",
    "sg:city": "Hamilton",
    "sg:classifiers": [
      {
        "category": "Shopping",
        "subcategory": "Crafts \u0026 Fabrics",
        "type": "Retail Goods"
      }
    ],
    "sg:phone": "+1 513 868 7556",
    "sg:postcode": "45011",
    "sg:province": "OH",
    "sg:tags": [
      "material",
      "needlework"
    ],
    "wof:name": "Stitch \u0026 Such Needlework",
    "wof:placetype": "venue"
  },
  "geometry": {"coordinates":[-84.557234,39.403654],"type":"Point"}
}
