{
  "type": "Feature",
  "properties": {
    "addr:full":"5484 Schiering Dr Fairfield OH 45014",
    "addr:housenumber":"5484",
    "addr:postcode":"45014",
    "addr:street":"Schiering Dr",
    "iso:country":"US",
    "sg:address":"5484 Schiering Dr",
    "sg:city":"Fairfield",
    "sg:classifiers":[
        {
            "category":"Organizations",
            "subcategory":"Religious Organization",
            "type":"Services"
        }
    ],
    "sg:phone":"+1 513 867 0575",
    "sg:postcode":"45014",
    "sg:province":"OH",
    "sg:tags":[
        "clergy"
    ],
    "wof:name":"Stanley L Booher",
    "wof:placetype":"venue"
},
  "geometry": {"coordinates":[-84.57742500000001,39.341058],"type":"Point"}
}