{
  "type": "Feature",
  "properties": {
    "addr:full":"4239 W 150th St Cleveland OH 44135",
    "addr:housenumber":"4239",
    "addr:postcode":"44135",
    "addr:street":"W 150Th St",
    "iso:country":"US",
    "sg:address":"4239 W 150th St",
    "sg:city":"Cleveland",
    "sg:classifiers":[
        {
            "category":"Banks & Credit Unions",
            "subcategory":"Bank",
            "type":"Services"
        }
    ],
    "sg:phone":"+1 216 875 7008",
    "sg:postcode":"44135",
    "sg:province":"OH",
    "sg:tags":[
        "loan",
        "real estate"
    ],
    "sg:website":"www.greatdaylending.com",
    "wof:name":"GREATDAYLENDING.COM",
    "wof:placetype":"venue"
},
  "geometry": {"coordinates":[-81.801188,41.439358],"type":"Point"}
}