{
  "type": "Feature",
  "properties": {
    "addr:full":"133 E Morenci St Lyons OH 43533",
    "addr:housenumber":"133",
    "addr:postcode":"43533",
    "addr:street":"E Morenci St",
    "iso:country":"US",
    "sg:address":"133 E Morenci St",
    "sg:city":"Lyons",
    "sg:classifiers":[
        {
            "category":"Banks & Credit Unions",
            "subcategory":"Bank",
            "type":"Services"
        }
    ],
    "sg:phone":"+1 419 923 3471",
    "sg:postcode":"43533",
    "sg:province":"OH",
    "wof:name":"State Bank & Trust Co",
    "wof:placetype":"venue"
},
  "geometry": {"coordinates":[-84.06943200000001,41.699421],"type":"Point"}
}