{
  "type": "Feature",
  "properties": {
    "addr:full":"724 Sumner St Akron OH 44311",
    "addr:housenumber":"724",
    "addr:postcode":"44311",
    "addr:street":"Sumner St",
    "iso:country":"US",
    "sg:address":"724 Sumner St",
    "sg:city":"Akron",
    "sg:classifiers":[
        {
            "category":"Social Services",
            "subcategory":"Child Care",
            "type":"Services"
        }
    ],
    "sg:phone":"+1 330 535 1433",
    "sg:postcode":"44311",
    "sg:province":"OH",
    "sg:tags":[
        "organization",
        "religious",
        "day"
    ],
    "wof:name":"Open Arms Chrstn Child Dev Ctr",
    "wof:placetype":"venue"
},
  "geometry": {"coordinates":[-81.514978,41.062955],"type":"Point"}
}