{
  "type": "Feature",
  "properties": {
    "addr:full": "2321 Saint Clair Ave NE Cleveland OH 44114",
    "addr:housenumber": "2321",
    "addr:postcode": "44114",
    "addr:street": "Saint Clair Ave Ne",
    "iso:country": "US",
    "sg:address": "2321 Saint Clair Ave NE",
    "sg:city": "Cleveland",
    "sg:classifiers": [
      {
        "category": "Home \u0026 Garden",
        "subcategory": "Household Appliances",
        "type": "Retail Goods"
      }
    ],
    "sg:phone": "+1 216 781 0896",
    "sg:postcode": "44114",
    "sg:province": "OH",
    "sg:tags": [
      "air",
      "room",
      "unit",
      "conditioning"
    ],
    "wof:name": "Select Aire Svc Corp",
    "wof:placetype": "venue"
  },
  "geometry": {"coordinates":[-81.676768,41.510548],"type":"Point"}
}
