{
  "type": "Feature",
  "properties": {
    "addr:full": "45575 Winkler Rd Clarington OH 43915",
    "addr:housenumber": "45575",
    "addr:postcode": "43915",
    "addr:street": "Winkler Rd",
    "iso:country": "US",
    "sg:address": "45575 Winkler Rd",
    "sg:city": "Clarington",
    "sg:classifiers": [
      {
        "category": "Building \u0026 Trades",
        "subcategory": "Construction",
        "type": "Services"
      }
    ],
    "sg:phone": "+1 740 458 1638",
    "sg:postcode": "43915",
    "sg:province": "OH",
    "sg:tags": [
      "carpentry",
      "contractor"
    ],
    "wof:name": "Bernard E Ollom Jr",
    "wof:placetype": "venue"
  },
  "geometry": {"coordinates":[-80.96353,39.749381],"type":"Point"}
}
