{
  "type": "Feature",
  "properties": {
    "iso:country":"US",
    "sg:address":"1517 State Rte 28",
    "sg:city":"Loveland",
    "sg:classifiers":[
        {
            "category":"Retail",
            "subcategory":"Auto Repair",
            "type":"Services"
        }
    ],
    "sg:phone":"+1 513 575 1732",
    "sg:postcode":"45140",
    "sg:province":"OH",
    "sg:tags":[
        "repairing",
        "automobile"
    ],
    "wof:name":"Quick Snatch",
    "wof:placetype":"venue"
},
  "geometry": {"coordinates":[-84.201391,39.214458],"type":"Point"}
}