{
  "type": "Feature",
  "properties": {
    "iso:country":"US",
    "sg:address":"407 Vine St",
    "sg:city":"Cincinnati",
    "sg:classifiers":[
        {
            "category":"Professional",
            "subcategory":"Advertising",
            "type":"Services"
        }
    ],
    "sg:phone":"+1 513 929 0090",
    "sg:postcode":"45202",
    "sg:province":"OH",
    "sg:tags":[
        "mailing",
        "shipping"
    ],
    "wof:name":"Mail Boxes Etc",
    "wof:placetype":"venue"
},
  "geometry": {"coordinates":[-84.512826,39.100241],"type":"Point"}
}