{
  "type": "Feature",
  "properties": {
    "addr:full":"354 Charlotte Ave Lebanon OH 45036",
    "addr:housenumber":"354",
    "addr:postcode":"45036",
    "addr:street":"Charlotte Ave",
    "iso:country":"US",
    "sg:address":"354 Charlotte Ave",
    "sg:city":"Lebanon",
    "sg:classifiers":[
        {
            "category":"Wholesale",
            "subcategory":"Construction Materials",
            "type":"Manufacturing & Wholesale Goods"
        }
    ],
    "sg:phone":"+1 513 932 8911",
    "sg:postcode":"45036",
    "sg:province":"OH",
    "sg:tags":[
        "fence"
    ],
    "wof:name":"Inman Fence",
    "wof:placetype":"venue"
},
  "geometry": {"coordinates":[-84.19537800000001,39.474001],"type":"Point"}
}