{
  "type": "Feature",
  "properties": {
    "addr:full": "45 N Main St West Alexandria OH 45381",
    "addr:housenumber": "45",
    "addr:postcode": "45381",
    "addr:street": "N Main St",
    "iso:country": "US",
    "sg:address": "45 N Main St",
    "sg:city": "West Alexandria",
    "sg:classifiers": [
      {
        "category": "Education",
        "subcategory": "School",
        "type": "Public Place"
      }
    ],
    "sg:phone": "+1 937 839 3409",
    "sg:postcode": "45381",
    "sg:province": "OH",
    "wof:name": "Samaritan At Third Street Sch",
    "wof:placetype": "venue"
  },
  "geometry": {"coordinates":[-84.532143,39.746296],"type":"Point"}
}
