{
  "type": "Feature",
  "properties": {
    "addr:full": "1074 Fairfield Ave Columbiana OH 44408",
    "addr:housenumber": "1074",
    "addr:postcode": "44408",
    "addr:street": "Fairfield Ave",
    "iso:country": "US",
    "sg:address": "1074 Fairfield Ave",
    "sg:city": "Columbiana",
    "sg:classifiers": [
      {
        "category": "Building \u0026 Trades",
        "subcategory": "Construction",
        "type": "Services"
      }
    ],
    "sg:phone": "+1 330 482 1314",
    "sg:postcode": "44408",
    "sg:province": "OH",
    "sg:tags": [
      "home",
      "builder"
    ],
    "wof:name": "Titan Construction",
    "wof:placetype": "venue"
  },
  "geometry": {"coordinates":[-80.684573,40.867504],"type":"Point"}
}
