{
  "type": "Feature",
  "properties": {
    "addr:full":"1350 E Market St Warren OH 44483",
    "addr:housenumber":"1350",
    "addr:postcode":"44483",
    "addr:street":"E Market St",
    "iso:country":"US",
    "sg:address":"1350 E Market St",
    "sg:city":"Warren",
    "sg:classifiers":[
        {
            "category":"Professional",
            "subcategory":"Business Services",
            "type":"Services"
        }
    ],
    "sg:phone":"+1 330 399 5080",
    "sg:postcode":"44483",
    "sg:province":"OH",
    "sg:tags":[
        "paging",
        "signaling"
    ],
    "wof:name":"Paging Network",
    "wof:placetype":"venue"
},
  "geometry": {"coordinates":[-80.79987199999999,41.236357],"type":"Point"}
}