{
  "type": "Feature",
  "properties": {
    "addr:full": "3771 E Kemper Rd Cincinnati OH 45241",
    "addr:housenumber": "3771",
    "addr:postcode": "45241",
    "addr:street": "E Kemper Rd",
    "iso:country": "US",
    "sg:address": "3771 E Kemper Rd",
    "sg:city": "Cincinnati",
    "sg:classifiers": [
      {
        "category": "Real Estate",
        "subcategory": "Real Estate Operator",
        "type": "Services"
      }
    ],
    "sg:phone": "+1 513 769 1312",
    "sg:postcode": "45241",
    "sg:province": "OH",
    "sg:tags": [
      "apartment"
    ],
    "wof:name": "Sharon Woods Apartments",
    "wof:placetype": "venue"
  },
  "geometry": {"coordinates":[-84.405252,39.282959],"type":"Point"}
}
