{
  "type": "Feature",
  "properties": {
    "addr:full": "401 Agnes St Defiance OH 43512",
    "addr:housenumber": "401",
    "addr:postcode": "43512",
    "addr:street": "Agnes St",
    "iso:country": "US",
    "sg:address": "401 Agnes St",
    "sg:city": "Defiance",
    "sg:classifiers": [
      {
        "category": "Manufacturing",
        "subcategory": "Metals",
        "type": "Manufacturing \u0026 Wholesale Goods"
      }
    ],
    "sg:phone": "+1 419 782 6896",
    "sg:postcode": "43512",
    "sg:province": "OH",
    "sg:tags": [
      "stampings",
      "mfg"
    ],
    "wof:name": "Figley Stamping Company",
    "wof:placetype": "venue"
  },
  "geometry": {"coordinates":[-84.354726,41.26974],"type":"Point"}
}
