{
  "type": "Feature",
  "properties": {
    "iso:country":"US",
    "sg:address":"401 Agnes St",
    "sg:city":"Defiance",
    "sg:classifiers":[
        {
            "category":"Manufacturing",
            "subcategory":"Metals",
            "type":"Manufacturing & Wholesale Goods"
        }
    ],
    "sg:phone":"+1 419 782 6896",
    "sg:postcode":"43512",
    "sg:province":"OH",
    "sg:tags":[
        "stampings",
        "mfg"
    ],
    "wof:name":"Figley Stamping Company",
    "wof:placetype":"venue"
},
  "geometry": {"coordinates":[-84.354726,41.26974],"type":"Point"}
}