{
  "type": "Feature",
  "properties": {
    "iso:country":"US",
    "sg:address":"6915 Perrill Rd",
    "sg:city":"Ashville",
    "sg:classifiers":[
        {
            "category":"Farming",
            "subcategory":"Livestock Farm",
            "type":"Manufacturing & Wholesale Goods"
        }
    ],
    "sg:phone":"+1 740 983 3197",
    "sg:postcode":"43103",
    "sg:province":"OH",
    "sg:tags":[
        "corn",
        "beef",
        "feedlot",
        "cattle"
    ],
    "wof:name":"KB Cattle Co LLC",
    "wof:placetype":"venue"
},
  "geometry": {"coordinates":[-82.89437599999999,39.783959],"type":"Point"}
}