{
  "type": "Feature",
  "properties": {
    "addr:full":"1006 Meadowview Dr Celina OH 45822",
    "addr:housenumber":"1006",
    "addr:postcode":"45822",
    "addr:street":"Meadowview Dr",
    "iso:country":"US",
    "sg:address":"1006 Meadowview Dr",
    "sg:city":"Celina",
    "sg:classifiers":[
        {
            "category":"Shopping",
            "subcategory":"Hobbies, Toys, & Games",
            "type":"Retail Goods"
        }
    ],
    "sg:phone":"+1 419 586 4609",
    "sg:postcode":"45822",
    "sg:province":"OH",
    "wof:name":"Pick-A-Wick",
    "wof:placetype":"venue"
},
  "geometry": {"coordinates":[-84.55556799999999,40.559462],"type":"Point"}
}