{
  "type": "Feature",
  "properties": {
    "addr:full": "11 Terrace Dr Cincinnati OH 45215",
    "addr:housenumber": "11",
    "addr:postcode": "45215",
    "addr:street": "Terrace Dr",
    "iso:country": "US",
    "sg:address": "11 Terrace Dr",
    "sg:city": "Cincinnati",
    "sg:classifiers": [
      {
        "category": "Shopping",
        "type": "Retail Goods"
      }
    ],
    "sg:phone": "+1 513 769 8383",
    "sg:postcode": "45215",
    "sg:province": "OH",
    "sg:tags": [
      "equipment",
      "telephone",
      "supply"
    ],
    "wof:name": "Teleco Cincinnati",
    "wof:placetype": "venue"
  },
  "geometry": {"coordinates":[-84.469026,39.242622],"type":"Point"}
}
