{
  "type": "Feature",
  "properties": {
    "addr:full": "409 W Euclid Ave Springfield OH 45506",
    "addr:housenumber": "409",
    "addr:postcode": "45506",
    "addr:street": "W Euclid Ave",
    "iso:country": "US",
    "sg:address": "409 W Euclid Ave",
    "sg:city": "Springfield",
    "sg:classifiers": [
      {
        "category": "Organizations",
        "subcategory": "Religious Organization",
        "type": "Services"
      }
    ],
    "sg:phone": "+1 937 325 9357",
    "sg:postcode": "45506",
    "sg:province": "OH",
    "sg:tags": [
      "clergy"
    ],
    "wof:name": "Willie C Hookfin",
    "wof:placetype": "venue"
  },
  "geometry": {"coordinates":[-83.821567,39.913658],"type":"Point"}
}
