{
  "type": "Feature",
  "properties": {
    "addr:full": "4846 Bowser Dr Toledo OH 43613",
    "addr:postcode": "4846;43613",
    "addr:street": "Bowser Dr",
    "iso:country": "US",
    "sg:address": "4846 Bowser Dr",
    "sg:city": "Toledo",
    "sg:classifiers": [
      {
        "category": "Building \u0026 Trades",
        "subcategory": "Landscaping Services",
        "type": "Services"
      }
    ],
    "sg:phone": "+1 419 475 8911",
    "sg:postcode": "43613",
    "sg:province": "OH",
    "sg:tags": [
      "designer",
      "landscape"
    ],
    "wof:name": "Toledo Lawn Care Inc",
    "wof:placetype": "venue"
  },
  "geometry": {"coordinates":[-83.615222,41.7053],"type":"Point"}
}
