{
  "type": "Feature",
  "properties": {
    "iso:country":"US",
    "sg:address":"4846 Bowser Dr",
    "sg:city":"Toledo",
    "sg:classifiers":[
        {
            "category":"Building & Trades",
            "subcategory":"Landscaping Services",
            "type":"Services"
        }
    ],
    "sg:phone":"+1 419 475 8911",
    "sg:postcode":"43613",
    "sg:province":"OH",
    "sg:tags":[
        "designer",
        "landscape"
    ],
    "wof:name":"Toledo Lawn Care Inc",
    "wof:placetype":"venue"
},
  "geometry": {"coordinates":[-83.615222,41.7053],"type":"Point"}
}