{
  "type": "Feature",
  "properties": {
    "iso:country":"US",
    "sg:address":"826 E Aurora Rd",
    "sg:city":"Macedonia",
    "sg:classifiers":[
        {
            "category":"Banks & Credit Unions",
            "subcategory":"Investment Brokerage",
            "type":"Services"
        }
    ],
    "sg:phone":"+1 330 467 0101",
    "sg:postcode":"44056",
    "sg:province":"OH",
    "wof:name":"Edward Jones Co",
    "wof:placetype":"venue"
},
  "geometry": {"coordinates":[-81.510626,41.313852],"type":"Point"}
}