{
  "type": "Feature",
  "properties": {
    "iso:country":"US",
    "sg:address":"471 Morrison Rd",
    "sg:city":"Gahanna",
    "sg:classifiers":[
        {
            "category":"Banks & Credit Unions",
            "subcategory":"Investment Brokerage",
            "type":"Services"
        }
    ],
    "sg:phone":"+1 614 471 2475",
    "sg:postcode":"43230",
    "sg:province":"OH",
    "sg:tags":[
        "security"
    ],
    "sg:website":"www.edwardjones.com",
    "wof:name":"Edward Jones Co",
    "wof:placetype":"venue"
},
  "geometry": {"coordinates":[-82.865054,40.008886],"type":"Point"}
}