{
  "type": "Feature",
  "properties": {
    "iso:country":"US",
    "sg:address":"2177 Mc Kinley Ave",
    "sg:city":"Columbus",
    "sg:classifiers":[
        {
            "category":"Wholesale",
            "subcategory":"Construction Materials",
            "type":"Manufacturing & Wholesale Goods"
        },
        {
            "category":"Building & Trades",
            "subcategory":"Equipment Rental",
            "type":"Services"
        }
    ],
    "sg:phone":"+1 614 308 1100",
    "sg:postcode":"43204",
    "sg:province":"OH",
    "sg:tags":[
        "fence",
        "contractor"
    ],
    "sg:website":"www.rentnational.com",
    "wof:name":"National Rent A Fence Inc",
    "wof:placetype":"venue"
},
  "geometry": {"coordinates":[-83.062521,39.969952],"type":"Point"}
}