{
  "type": "Feature",
  "properties": {
    "addr:full": "2177 Mc Kinley Ave Columbus OH 43204",
    "addr:housenumber": "2177",
    "addr:postcode": "43204",
    "addr:street": "Mc Kinley Ave",
    "iso:country": "US",
    "sg:address": "2177 Mc Kinley Ave",
    "sg:city": "Columbus",
    "sg:classifiers": [
      {
        "category": "Wholesale",
        "subcategory": "Construction Materials",
        "type": "Manufacturing \u0026 Wholesale Goods"
      },
      {
        "category": "Building \u0026 Trades",
        "subcategory": "Equipment Rental",
        "type": "Services"
      }
    ],
    "sg:phone": "+1 614 308 1100",
    "sg:postcode": "43204",
    "sg:province": "OH",
    "sg:tags": [
      "fence",
      "contractor"
    ],
    "sg:website": "www.rentnational.com",
    "wof:name": "National Rent A Fence Inc",
    "wof:placetype": "venue"
  },
  "geometry": {"coordinates":[-83.062521,39.969952],"type":"Point"}
}
