{
  "type": "Feature",
  "properties": {
    "iso:country":"US",
    "sg:address":"19 S Main St",
    "sg:city":"Miamisburg",
    "sg:classifiers":[
        {
            "category":"Shopping",
            "subcategory":"Clothing, Apparel, & Fashions",
            "type":"Retail Goods"
        }
    ],
    "sg:phone":"+1 937 866 6966",
    "sg:postcode":"45342",
    "sg:province":"OH",
    "sg:tags":[
        "theatrical",
        "costume"
    ],
    "wof:name":"Odd Bodkin Renaissance Shop",
    "wof:placetype":"venue"
},
  "geometry": {"coordinates":[-84.28961200000001,39.640343],"type":"Point"}
}