{
  "type": "Feature",
  "properties": {
    "addr:full": "19 S Main St Miamisburg OH 45342",
    "addr:housenumber": "19",
    "addr:postcode": "45342",
    "addr:street": "S Main St",
    "iso:country": "US",
    "sg:address": "19 S Main St",
    "sg:city": "Miamisburg",
    "sg:classifiers": [
      {
        "category": "Shopping",
        "subcategory": "Clothing, Apparel, \u0026 Fashions",
        "type": "Retail Goods"
      }
    ],
    "sg:phone": "+1 937 866 6966",
    "sg:postcode": "45342",
    "sg:province": "OH",
    "sg:tags": [
      "theatrical",
      "costume"
    ],
    "wof:name": "Odd Bodkin Renaissance Shop",
    "wof:placetype": "venue"
  },
  "geometry": {"coordinates":[-84.289612,39.640343],"type":"Point"}
}
