{
  "type": "Feature",
  "properties": {
    "addr:full": "32 Bachtel Ave Akron OH 44311",
    "addr:housenumber": "32",
    "addr:postcode": "44311",
    "addr:street": "Bachtel Ave",
    "iso:country": "US",
    "sg:address": "32 Bachtel Ave",
    "sg:city": "Akron",
    "sg:classifiers": [
      {
        "category": "Professional",
        "type": "Services"
      }
    ],
    "sg:phone": "+1 330 896 8664",
    "sg:postcode": "44311",
    "sg:province": "OH",
    "wof:name": "Care N For 2 Inc",
    "wof:placetype": "venue"
  },
  "geometry": {"coordinates":[-81.528754,41.060195],"type":"Point"}
}
