{
  "type": "Feature",
  "properties": {
    "addr:full":"2224 Ketwood Pl Dayton OH 45420",
    "addr:housenumber":"2224",
    "addr:postcode":"45420",
    "addr:street":"Ketwood Pl",
    "iso:country":"US",
    "sg:address":"2224 Ketwood Pl",
    "sg:city":"Dayton",
    "sg:classifiers":[
        {
            "category":"Real Estate",
            "subcategory":"Real Estate Operator",
            "type":"Services"
        }
    ],
    "sg:phone":"+1 937 294 5779",
    "sg:postcode":"45420",
    "sg:province":"OH",
    "sg:tags":[
        "building",
        "apartment"
    ],
    "wof:name":"Ketwood Place Apartments",
    "wof:placetype":"venue"
},
  "geometry": {"coordinates":[-84.12219399999999,39.709224],"type":"Point"}
}