{
  "type": "Feature",
  "properties": {
    "addr:full": "4785 Streeter Rd Mantua OH 44255",
    "addr:housenumber": "4785",
    "addr:postcode": "44255",
    "addr:street": "Streeter Rd",
    "iso:country": "US",
    "sg:address": "4785 Streeter Rd",
    "sg:city": "Mantua",
    "sg:classifiers": [
      {
        "category": "Food \u0026 Beverages",
        "subcategory": "Groceries \u0026 Convenience Stores",
        "type": "Retail Goods"
      }
    ],
    "sg:phone": "+1 330 274 0299",
    "sg:postcode": "44255",
    "sg:province": "OH",
    "wof:name": "Mkt Supply Co",
    "wof:placetype": "venue"
  },
  "geometry": {"coordinates":[-81.219328,41.252974],"type":"Point"}
}
