{
  "type": "Feature",
  "properties": {
    "addr:full":"225 Woodford Ave Elyria OH 44035",
    "addr:housenumber":"225",
    "addr:postcode":"44035",
    "addr:street":"Woodford Ave",
    "iso:country":"US",
    "sg:address":"225 Woodford Ave",
    "sg:city":"Elyria",
    "sg:classifiers":[
        {
            "category":"Organizations",
            "subcategory":"Religious Organization",
            "type":"Services"
        }
    ],
    "sg:phone":"+1 440 323 7725",
    "sg:postcode":"44035",
    "sg:province":"OH",
    "sg:tags":[
        "church"
    ],
    "wof:name":"Church Of God In Christ",
    "wof:placetype":"venue"
},
  "geometry": {"coordinates":[-82.123015,41.363328],"type":"Point"}
}