{
  "type": "Feature",
  "properties": {
    "addr:full": "7818 Lake Ave Cleveland OH 44102",
    "addr:housenumber": "7818",
    "addr:postcode": "44102",
    "addr:street": "Lake Ave",
    "iso:country": "US",
    "sg:address": "7818 Lake Ave",
    "sg:city": "Cleveland",
    "sg:classifiers": [
      {
        "category": "Manufacturing",
        "subcategory": "Glass \u0026 Minerals",
        "type": "Manufacturing \u0026 Wholesale Goods"
      }
    ],
    "sg:phone": "+1 216 281 5557",
    "sg:postcode": "44102",
    "sg:province": "OH",
    "sg:tags": [
      "product",
      "cut",
      "marble",
      "mfg"
    ],
    "wof:name": "Suburban Marble and Granite Co",
    "wof:placetype": "venue"
  },
  "geometry": {"coordinates":[-81.739163,41.483067],"type":"Point"}
}
