{
  "type": "Feature",
  "properties": {
    "iso:country":"US",
    "sg:address":"7818 Lake Ave",
    "sg:city":"Cleveland",
    "sg:classifiers":[
        {
            "category":"Manufacturing",
            "subcategory":"Glass & Minerals",
            "type":"Manufacturing & Wholesale Goods"
        }
    ],
    "sg:phone":"+1 216 281 5557",
    "sg:postcode":"44102",
    "sg:province":"OH",
    "sg:tags":[
        "product",
        "cut",
        "marble",
        "mfg"
    ],
    "wof:name":"Suburban Marble and Granite Co",
    "wof:placetype":"venue"
},
  "geometry": {"coordinates":[-81.739163,41.483067],"type":"Point"}
}