{
  "type": "Feature",
  "properties": {
    "iso:country":"US",
    "sg:address":"15094 Co Rd 6",
    "sg:city":"Dresden",
    "sg:classifiers":[
        {
            "category":"Wholesale",
            "subcategory":"Meat",
            "type":"Manufacturing & Wholesale Goods"
        }
    ],
    "sg:phone":"+1 740 754 3422",
    "sg:postcode":"43821",
    "sg:province":"OH",
    "sg:tags":[
        "butchering"
    ],
    "wof:name":"Lacy's Meats",
    "wof:placetype":"venue"
},
  "geometry": {"coordinates":[-81.989537,40.174383],"type":"Point"}
}