{
  "type": "Feature",
  "properties": {
    "addr:full":"26908 Detroit Rd Cleveland OH 44145",
    "addr:housenumber":"26908",
    "addr:postcode":"44145",
    "addr:street":"Detroit Rd",
    "iso:country":"US",
    "sg:address":"26908 Detroit Rd",
    "sg:city":"Cleveland",
    "sg:classifiers":[
        {
            "category":"Personal",
            "subcategory":"Beauty Salon",
            "type":"Services"
        }
    ],
    "sg:phone":"+1 440 808 1606",
    "sg:postcode":"44145",
    "sg:province":"OH",
    "sg:tags":[
        "treatment",
        "skin"
    ],
    "wof:name":"Associates In Dermatology",
    "wof:placetype":"venue"
},
  "geometry": {"coordinates":[-81.916707,41.468237],"type":"Point"}
}