{
  "type": "Feature",
  "properties": {
    "addr:full": "121 Central Ave Westerville OH 43081",
    "addr:housenumber": "121",
    "addr:postcode": "43081",
    "addr:street": "Central Ave",
    "iso:country": "US",
    "sg:address": "121 Central Ave",
    "sg:city": "Westerville",
    "sg:classifiers": [
      {
        "category": "Wholesale",
        "subcategory": "Apparel",
        "type": "Manufacturing \u0026 Wholesale Goods"
      }
    ],
    "sg:phone": "+1 614 891 9024",
    "sg:postcode": "43081",
    "sg:province": "OH",
    "sg:tags": [
      "sportswear"
    ],
    "sg:website": "www.icebeams.com",
    "wof:name": "I B Sports",
    "wof:placetype": "venue"
  },
  "geometry": {"coordinates":[-82.932798,40.116811],"type":"Point"}
}
