{
  "type": "Feature",
  "properties": {
    "addr:full": "2152 Green Rd Cleveland OH 44121",
    "addr:housenumber": "2152",
    "addr:postcode": "44121",
    "addr:street": "Green Rd",
    "iso:country": "US",
    "sg:address": "2152 Green Rd",
    "sg:city": "Cleveland",
    "sg:classifiers": [
      {
        "category": "Retail",
        "subcategory": "Auto Repair",
        "type": "Services"
      }
    ],
    "sg:phone": "+1 216 531 7805",
    "sg:postcode": "44121",
    "sg:province": "OH",
    "sg:tags": [
      "truck"
    ],
    "wof:name": "Heavy Duty Truck \u0026 Trailer",
    "wof:placetype": "venue"
  },
  "geometry": {"coordinates":[-81.541796,41.550151],"type":"Point"}
}
