{
  "type": "Feature",
  "properties": {
    "addr:full":"14 Highland Ct Medina OH 44256",
    "addr:housenumber":"14",
    "addr:postcode":"44256",
    "addr:street":"Highland Ct",
    "iso:country":"US",
    "sg:address":"14 Highland Ct",
    "sg:city":"Medina",
    "sg:classifiers":[
        {
            "category":"Personal",
            "subcategory":"Barber",
            "type":"Services"
        }
    ],
    "sg:phone":"+1 330 725 4725",
    "sg:postcode":"44256",
    "sg:province":"OH",
    "wof:name":"Carl's Barber Shop",
    "wof:placetype":"venue"
},
  "geometry": {"coordinates":[-81.863693,41.148775],"type":"Point"}
}