{
  "type": "Feature",
  "properties": {
    "addr:full": "110 W Main St Cridersville OH 45806",
    "addr:housenumber": "110",
    "addr:postcode": "45806",
    "addr:street": "W Main St",
    "iso:country": "US",
    "sg:address": "110 W Main St",
    "sg:city": "Cridersville",
    "sg:classifiers": [
      {
        "category": "Personal",
        "subcategory": "Beauty Salon",
        "type": "Services"
      }
    ],
    "sg:phone": "+1 419 643 3585",
    "sg:postcode": "45806",
    "sg:province": "OH",
    "wof:name": "Janey's Golden Shears",
    "wof:placetype": "venue"
  },
  "geometry": {"coordinates":[-84.14404,40.654313],"type":"Point"}
}
