{
  "type": "Feature",
  "properties": {
    "addr:full":"1668 Wilton Dr Columbus OH 43227",
    "addr:housenumber":"1668",
    "addr:postcode":"43227",
    "addr:street":"Wilton Dr",
    "iso:country":"US",
    "sg:address":"1668 Wilton Dr",
    "sg:city":"Columbus",
    "sg:classifiers":[
        {
            "category":"Shopping",
            "subcategory":"Gifts & Souvenirs",
            "type":"Retail Goods"
        }
    ],
    "sg:phone":"+1 614 231 8734",
    "sg:postcode":"43227",
    "sg:province":"OH",
    "wof:name":"Gentle Dragon",
    "wof:placetype":"venue"
},
  "geometry": {"coordinates":[-82.88017499999999,39.940694],"type":"Point"}
}