{
  "type": "Feature",
  "properties": {
    "iso:country":"US",
    "sg:address":"7140 N Dixie Dr",
    "sg:city":"Dayton",
    "sg:classifiers":[
        {
            "category":"Social Services",
            "type":"Services"
        }
    ],
    "sg:phone":"+1 937 898 1649",
    "sg:postcode":"45414",
    "sg:province":"OH",
    "sg:tags":[
        "organization",
        "welfare"
    ],
    "wof:name":"Goodwill Auto Auctions",
    "wof:placetype":"venue"
},
  "geometry": {"coordinates":[-84.198476,39.832843],"type":"Point"}
}