{
  "type": "Feature",
  "properties": {
    "addr:full": "3950 Morse Rd Columbus OH 43231",
    "addr:housenumber": "3950",
    "addr:postcode": "43231",
    "addr:street": "Morse Rd",
    "iso:country": "US",
    "sg:address": "3950 Morse Rd",
    "sg:city": "Columbus",
    "sg:classifiers": [
      {
        "category": "Shopping",
        "subcategory": "Department Store",
        "type": "Retail Goods"
      }
    ],
    "sg:phone": "+1 614 476 4224",
    "sg:postcode": "43231",
    "sg:province": "OH",
    "sg:tags": [
      "club",
      "wholesale"
    ],
    "sg:website": "www.samsclub.com",
    "wof:name": "Sam's Club",
    "wof:placetype": "venue"
  },
  "geometry": {"coordinates":[-82.913651,40.05776],"type":"Point"}
}
