{
  "type": "Feature",
  "properties": {
    "addr:full": "522 S Spring St Bucyrus OH 44820",
    "addr:housenumber": "522",
    "addr:postcode": "44820",
    "addr:street": "S Spring St",
    "iso:country": "US",
    "sg:address": "522 S Spring St",
    "sg:city": "Bucyrus",
    "sg:classifiers": [
      {
        "category": "Social Services",
        "subcategory": "Child Care",
        "type": "Services"
      }
    ],
    "sg:phone": "+1 419 562 0399",
    "sg:postcode": "44820",
    "sg:province": "OH",
    "sg:tags": [
      "day"
    ],
    "wof:name": "DC Daycare Inc",
    "wof:placetype": "venue"
  },
  "geometry": {"coordinates":[-82.978487,40.803534],"type":"Point"}
}
