{
  "type": "Feature",
  "properties": {
    "iso:country":"US",
    "sg:address":"880 Royma Rd NE",
    "sg:city":"Corning",
    "sg:classifiers":[
        {
            "category":"Real Estate",
            "subcategory":"Real Estate Operator",
            "type":"Services"
        }
    ],
    "sg:phone":"+1 740 342 2202",
    "sg:postcode":"43730",
    "sg:province":"OH",
    "sg:tags":[
        "property",
        "lessor"
    ],
    "wof:name":"Reed Raymond",
    "wof:placetype":"venue"
},
  "geometry": {"coordinates":[-82.044105,39.688838],"type":"Point"}
}