{
  "type": "Feature",
  "properties": {
    "addr:full": "4944 Belmont Ave Youngstown OH 44505",
    "addr:housenumber": "4944",
    "addr:postcode": "44505",
    "addr:street": "Belmont Ave",
    "iso:country": "US",
    "sg:address": "4944 Belmont Ave",
    "sg:city": "Youngstown",
    "sg:classifiers": [
      {
        "category": "Real Estate",
        "subcategory": "Real Estate Agent",
        "type": "Services"
      }
    ],
    "sg:phone": "+1 330 759 8638",
    "sg:postcode": "44505",
    "sg:province": "OH",
    "wof:name": "V \u0026 V Real Estate",
    "wof:placetype": "venue"
  },
  "geometry": {"coordinates":[-80.664831,41.169041],"type":"Point"}
}
