{
  "type": "Feature",
  "properties": {
    "addr:full":"112 W Main St Circleville OH 43113",
    "addr:housenumber":"112",
    "addr:postcode":"43113",
    "addr:street":"W Main St",
    "iso:country":"US",
    "sg:address":"112 W Main St",
    "sg:city":"Circleville",
    "sg:classifiers":[
        {
            "category":"Professional",
            "subcategory":"Lawyer & Legal Services",
            "type":"Services"
        }
    ],
    "sg:phone":"+1 740 477 6044",
    "sg:postcode":"43113",
    "sg:province":"OH",
    "sg:tags":[
        "attorney"
    ],
    "wof:name":"Agee Clymer Mitchell & Laret",
    "wof:placetype":"venue"
},
  "geometry": {"coordinates":[-82.947442,39.602672],"type":"Point"}
}