{
  "type": "Feature",
  "properties": {
    "addr:full":"1317 E Archwood Ave Akron OH 44306",
    "addr:housenumber":"1317",
    "addr:postcode":"44306",
    "addr:street":"E Archwood Ave",
    "iso:country":"US",
    "sg:address":"1317 E Archwood Ave",
    "sg:city":"Akron",
    "sg:classifiers":[
        {
            "category":"Bars & Pubs",
            "type":"Food & Drink"
        }
    ],
    "sg:phone":"+1 330 724 4187",
    "sg:postcode":"44306",
    "sg:province":"OH",
    "wof:name":"K C's Dugout",
    "wof:placetype":"venue"
},
  "geometry": {"coordinates":[-81.48026299999999,41.047458],"type":"Point"}
}