{
  "type": "Feature",
  "properties": {
    "addr:full":"3913 N Fordham Pl Cincinnati OH 45213",
    "addr:housenumber":"3913",
    "addr:postcode":"45213",
    "addr:street":"N Fordham Pl",
    "iso:country":"US",
    "sg:address":"3913 N Fordham Pl",
    "sg:city":"Cincinnati",
    "sg:classifiers":[
        {
            "category":"Organizations",
            "subcategory":"Religious Organization",
            "type":"Services"
        }
    ],
    "sg:phone":"+1 513 677 1034",
    "sg:postcode":"45213",
    "sg:province":"OH",
    "sg:tags":[
        "clergy"
    ],
    "wof:name":"Robert W Holmes",
    "wof:placetype":"venue"
},
  "geometry": {"coordinates":[-84.40189599999999,39.182834],"type":"Point"}
}