{
  "type": "Feature",
  "properties": {
    "addr:full":"165 N Wilhelm St Holgate OH 43527",
    "addr:housenumber":"165",
    "addr:postcode":"43527",
    "addr:street":"N Wilhelm St",
    "iso:country":"US",
    "sg:address":"165 N Wilhelm St",
    "sg:city":"Holgate",
    "sg:classifiers":[
        {
            "category":"Government",
            "subcategory":"Post Office",
            "type":"Public Place"
        }
    ],
    "sg:phone":"+1 419 264 2111",
    "sg:postcode":"43527",
    "sg:province":"OH",
    "sg:tags":[
        "postal",
        "us"
    ],
    "wof:name":"US Post Office",
    "wof:placetype":"venue"
},
  "geometry": {"coordinates":[-84.13261,41.250631],"type":"Point"}
}