{
  "type": "Feature",
  "properties": {
    "iso:country":"US",
    "sg:address":"660 N High St",
    "sg:city":"Columbus",
    "sg:classifiers":[
        {
            "category":"Restaurant",
            "type":"Food & Drink"
        }
    ],
    "sg:menulink":"http://www.allmenus.com/oh/columbus/19353-the-happy-greek/menu/",
    "sg:phone":"+1 614 463 1111",
    "sg:postcode":"43215",
    "sg:province":"OH",
    "sg:tags":[
        "greek"
    ],
    "wof:name":"The Happy Greek",
    "wof:placetype":"venue"
},
  "geometry": {"coordinates":[-83.003236,39.975811],"type":"Point"}
}