{
  "type": "Feature",
  "properties": {
    "iso:country":"US",
    "sg:address":"7383 E Huntington Dr",
    "sg:city":"Youngstown",
    "sg:classifiers":[
        {
            "category":"Real Estate",
            "subcategory":"Developer",
            "type":"Services"
        }
    ],
    "sg:phone":"+1 330 758 1384",
    "sg:postcode":"44512",
    "sg:province":"OH",
    "wof:name":"Villa Rosa Gardens LTD",
    "wof:placetype":"venue"
},
  "geometry": {"coordinates":[-80.706546,41.017841],"type":"Point"}
}