{
  "type": "Feature",
  "properties": {
    "addr:full":"455 E Market St Tiffin OH 44883",
    "addr:housenumber":"455",
    "addr:postcode":"44883",
    "addr:street":"E Market St",
    "iso:country":"US",
    "sg:address":"455 E Market St",
    "sg:city":"Tiffin",
    "sg:classifiers":[
        {
            "category":"Social Services",
            "type":"Services"
        }
    ],
    "sg:phone":"+1 419 447 0084",
    "sg:postcode":"44883",
    "sg:province":"OH",
    "sg:tags":[
        "organization",
        "welfare"
    ],
    "wof:name":"WSOS Community Action Cmssn",
    "wof:placetype":"venue"
},
  "geometry": {"coordinates":[-83.164963,41.119204],"type":"Point"}
}