{
  "type": "Feature",
  "properties": {
    "addr:full": "3032 Linmuth Dr W Springfield OH 45503",
    "addr:housenumber": "3032",
    "addr:postcode": "45503",
    "addr:street": "Linmuth Dr W",
    "iso:country": "US",
    "sg:address": "3032 Linmuth Dr W",
    "sg:city": "Springfield",
    "sg:classifiers": [
      {
        "category": "Health Services",
        "subcategory": "Doctor",
        "type": "Services"
      }
    ],
    "sg:phone": "+1 937 322 3066",
    "sg:postcode": "45503",
    "sg:province": "OH",
    "sg:tags": [
      "physician",
      "surgeon"
    ],
    "wof:name": "Malati G Potdar MD",
    "wof:placetype": "venue"
  },
  "geometry": {"coordinates":[-83.793243,39.961995],"type":"Point"}
}
