{
  "type": "Feature",
  "properties": {
    "addr:full": "2810 Cedar Ave Cleveland OH 44115",
    "addr:housenumber": "2810",
    "addr:postcode": "44115",
    "addr:street": "Cedar Ave",
    "iso:country": "US",
    "sg:address": "2810 Cedar Ave",
    "sg:city": "Cleveland",
    "sg:classifiers": [
      {
        "category": "Food \u0026 Beverages",
        "subcategory": "Groceries \u0026 Convenience Stores",
        "type": "Retail Goods"
      }
    ],
    "sg:phone": "+1 216 621 7711",
    "sg:postcode": "44115",
    "sg:province": "OH",
    "wof:name": "Negro Market Research Dev",
    "wof:placetype": "venue"
  },
  "geometry": {"coordinates":[-81.669895,41.498482],"type":"Point"}
}
