{
  "type": "Feature",
  "properties": {
    "iso:country":"US",
    "sg:address":"2810 Cedar Ave",
    "sg:city":"Cleveland",
    "sg:classifiers":[
        {
            "category":"Food & Beverages",
            "subcategory":"Groceries & Convenience Stores",
            "type":"Retail Goods"
        }
    ],
    "sg:phone":"+1 216 621 7711",
    "sg:postcode":"44115",
    "sg:province":"OH",
    "wof:name":"Negro Market Research Dev",
    "wof:placetype":"venue"
},
  "geometry": {"coordinates":[-81.669895,41.498482],"type":"Point"}
}