{
  "type": "Feature",
  "properties": {
    "addr:full":"30059 State Rte 18 Holgate OH 43527",
    "addr:housenumber":"30059",
    "addr:postcode":"43527",
    "addr:street":"State Rte 18",
    "iso:country":"US",
    "sg:address":"30059 State Rte 18",
    "sg:city":"Holgate",
    "sg:classifiers":[
        {
            "category":"Real Estate",
            "subcategory":"Real Estate Operator",
            "type":"Services"
        }
    ],
    "sg:phone":"+1 419 395 2292",
    "sg:postcode":"43527",
    "sg:province":"OH",
    "sg:tags":[
        "property",
        "lessor"
    ],
    "wof:name":"Ken Kipp",
    "wof:placetype":"venue"
},
  "geometry": {"coordinates":[-84.245726,41.253288],"type":"Point"}
}