{
  "type": "Feature",
  "properties": {
    "addr:full": "189 Seneak Ave Franklin Furnace OH 45629",
    "addr:housenumber": "189",
    "addr:postcode": "45629",
    "addr:street": "Seneak Ave",
    "iso:country": "US",
    "sg:address": "189 Seneak Ave",
    "sg:city": "Franklin Furnace",
    "sg:classifiers": [
      {
        "category": "Retail",
        "subcategory": "Auto Repair",
        "type": "Services"
      }
    ],
    "sg:phone": "+1 740 354 9709",
    "sg:postcode": "45629",
    "sg:province": "OH",
    "sg:tags": [
      "repairing",
      "automobile"
    ],
    "wof:name": "Cogan's Automotive",
    "wof:placetype": "venue"
  },
  "geometry": {"coordinates":[-82.848902,38.633662],"type":"Point"}
}
