{
  "type": "Feature",
  "properties": {
    "addr:full": "983 State Rte 109 Hamler OH 43524",
    "addr:housenumber": "983",
    "addr:postcode": "43524",
    "addr:street": "State Rte 109",
    "iso:country": "US",
    "sg:address": "983 State Rte 109",
    "sg:city": "Hamler",
    "sg:classifiers": [
      {
        "category": "Organizations",
        "subcategory": "Religious Organization",
        "type": "Services"
      }
    ],
    "sg:phone": "+1 419 274 4811",
    "sg:postcode": "43524",
    "sg:province": "OH",
    "sg:tags": [
      "church"
    ],
    "wof:name": "Immanuel Lutheran Church Inc",
    "wof:placetype": "venue"
  },
  "geometry": {"coordinates":[-84.03688,41.274243],"type":"Point"}
}
