{
  "type": "Feature",
  "properties": {
    "addr:full": "895 Central Ave Cincinnati OH 45202",
    "addr:housenumber": "895",
    "addr:postcode": "45202",
    "addr:street": "Central Ave",
    "iso:country": "US",
    "sg:address": "895 Central Ave",
    "sg:city": "Cincinnati",
    "sg:classifiers": [
      {
        "category": "Professional",
        "type": "Services"
      }
    ],
    "sg:phone": "+1 513 469 7211",
    "sg:postcode": "45202",
    "sg:province": "OH",
    "sg:tags": [
      "establishment"
    ],
    "wof:name": "Worldwide Express",
    "wof:placetype": "venue"
  },
  "geometry": {"coordinates":[-84.520384,39.103773],"type":"Point"}
}
