{
  "type": "Feature",
  "properties": {
    "addr:full": "48 Church St Hubbard OH 44425",
    "addr:housenumber": "48",
    "addr:postcode": "44425",
    "addr:street": "Church St",
    "iso:country": "US",
    "sg:address": "48 Church St",
    "sg:city": "Hubbard",
    "sg:classifiers": [
      {
        "category": "Organizations",
        "subcategory": "Religious Organization",
        "type": "Services"
      }
    ],
    "sg:phone": "+1 330 534 3383",
    "sg:postcode": "44425",
    "sg:province": "OH",
    "sg:tags": [
      "church"
    ],
    "wof:name": "First United Methodist Church",
    "wof:placetype": "venue"
  },
  "geometry": {"coordinates":[-80.570746,41.155051],"type":"Point"}
}
