{
  "type": "Feature",
  "properties": {
    "addr:full": "20 W Main St Norwalk OH 44857",
    "addr:housenumber": "20",
    "addr:postcode": "44857",
    "addr:street": "W Main St",
    "iso:country": "US",
    "sg:address": "20 W Main St",
    "sg:city": "Norwalk",
    "sg:classifiers": [
      {
        "category": "Organizations",
        "subcategory": "Community Association",
        "type": "Services"
      }
    ],
    "sg:phone": "+1 419 663 4062",
    "sg:postcode": "44857",
    "sg:province": "OH",
    "sg:tags": [
      "civic"
    ],
    "wof:name": "Jaycees",
    "wof:placetype": "venue"
  },
  "geometry": {"coordinates":[-82.616387,41.242035],"type":"Point"}
}
