{
  "type": "Feature",
  "properties": {
    "addr:full": "8109 Reading Rd Cincinnati OH 45237",
    "addr:housenumber": "8109",
    "addr:postcode": "45237",
    "addr:street": "Reading Rd",
    "iso:country": "US",
    "sg:address": "8109 Reading Rd",
    "sg:city": "Cincinnati",
    "sg:classifiers": [
      {
        "category": "Travel",
        "subcategory": "Hotels \u0026 Motels",
        "type": "Entertainment"
      }
    ],
    "sg:phone": "+1 513 761 5100",
    "sg:postcode": "45237",
    "sg:province": "OH",
    "wof:name": "Drake Motel",
    "wof:placetype": "venue"
  },
  "geometry": {"coordinates":[-84.449434,39.20886],"type":"Point"}
}
