{
  "type": "Feature",
  "properties": {
    "addr:full": "1000 5th Ave Youngstown OH 44504",
    "addr:housenumber": "1000",
    "addr:postcode": "44504",
    "addr:street": "5Th Ave",
    "iso:country": "US",
    "sg:address": "1000 5th Ave",
    "sg:city": "Youngstown",
    "sg:classifiers": [
      {
        "category": "Organizations",
        "subcategory": "Community Association",
        "type": "Services"
      }
    ],
    "sg:phone": "+1 330 743 3200",
    "sg:postcode": "44504",
    "sg:province": "OH",
    "sg:tags": [
      "club"
    ],
    "wof:name": "Junior League Of Youngstown",
    "wof:placetype": "venue"
  },
  "geometry": {"coordinates":[-80.651449,41.113305],"type":"Point"}
}
