{
  "type": "Feature",
  "properties": {
    "iso:country":"US",
    "sg:address":"224 N 5th St",
    "sg:city":"Steubenville",
    "sg:classifiers":[
        {
            "category":"Building & Trades",
            "subcategory":"Construction",
            "type":"Services"
        }
    ],
    "sg:phone":"+1 740 282 5481",
    "sg:postcode":"43952",
    "sg:province":"OH",
    "sg:tags":[
        "hanging",
        "contractor"
    ],
    "wof:name":"Pyrovolikos Vasilios",
    "wof:placetype":"venue"
},
  "geometry": {"coordinates":[-80.614857,40.363361],"type":"Point"}
}