{
  "type": "Feature",
  "properties": {
    "addr:full":"6004 Turney Rd Cleveland OH 44125",
    "addr:housenumber":"6004",
    "addr:postcode":"44125",
    "addr:street":"Turney Rd",
    "iso:country":"US",
    "sg:address":"6004 Turney Rd",
    "sg:city":"Cleveland",
    "sg:classifiers":[
        {
            "category":"Building & Trades",
            "subcategory":"Electrical",
            "type":"Services"
        }
    ],
    "sg:phone":"+1 216 663 3378",
    "sg:postcode":"44125",
    "sg:province":"OH",
    "sg:tags":[
        "electric",
        "contractor"
    ],
    "wof:name":"Perram Electric",
    "wof:placetype":"venue"
},
  "geometry": {"coordinates":[-81.594019,41.400023],"type":"Point"}
}