{
  "type": "Feature",
  "properties": {
    "addr:full":"70 Ross Rd Ashtabula OH 44004",
    "addr:housenumber":"70",
    "addr:postcode":"44004",
    "addr:street":"Ross Rd",
    "iso:country":"US",
    "sg:address":"70 Ross Rd",
    "sg:city":"Ashtabula",
    "sg:classifiers":[
        {
            "category":"Education",
            "subcategory":"Special Training",
            "type":"Public Place"
        }
    ],
    "sg:phone":"+1 440 993 1060",
    "sg:postcode":"44004",
    "sg:province":"OH",
    "sg:tags":[
        "educational"
    ],
    "wof:name":"After School Discovery",
    "wof:placetype":"venue"
},
  "geometry": {"coordinates":[-80.78390400000001,41.856441],"type":"Point"}
}