{
  "type": "Feature",
  "properties": {
    "addr:full":"3980 Turtlecreek Rd Lebanon OH 45036",
    "addr:housenumber":"3980",
    "addr:postcode":"45036",
    "addr:street":"Turtlecreek Rd",
    "iso:country":"US",
    "sg:address":"3980 Turtlecreek Rd",
    "sg:city":"Lebanon",
    "sg:classifiers":[
        {
            "category":"Mining & Drilling",
            "type":"Manufacturing & Wholesale Goods"
        }
    ],
    "sg:phone":"+1 513 494 1555",
    "sg:postcode":"45036",
    "sg:province":"OH",
    "sg:tags":[
        "dump",
        "hauling",
        "sand",
        "truck",
        "gravel",
        "pit"
    ],
    "wof:name":"Sand & Gravel Inc",
    "wof:placetype":"venue"
},
  "geometry": {"coordinates":[-84.231487,39.37592],"type":"Point"}
}