{
  "type": "Feature",
  "properties": {
    "iso:country":"US",
    "sg:address":"2416 Argonne Rd",
    "sg:city":"Portsmouth",
    "sg:classifiers":[
        {
            "category":"Manufacturing",
            "subcategory":"Glass & Minerals",
            "type":"Manufacturing & Wholesale Goods"
        }
    ],
    "sg:phone":"+1 740 353 5290",
    "sg:postcode":"45662",
    "sg:province":"OH",
    "sg:tags":[
        "refractory",
        "shape"
    ],
    "wof:name":"A & M Refractories",
    "wof:placetype":"venue"
},
  "geometry": {"coordinates":[-82.99270300000001,38.752094],"type":"Point"}
}