{
  "type": "Feature",
  "properties": {
    "addr:full": "2416 Argonne Rd Portsmouth OH 45662",
    "addr:housenumber": "2416",
    "addr:postcode": "45662",
    "addr:street": "Argonne Rd",
    "iso:country": "US",
    "sg:address": "2416 Argonne Rd",
    "sg:city": "Portsmouth",
    "sg:classifiers": [
      {
        "category": "Manufacturing",
        "subcategory": "Glass \u0026 Minerals",
        "type": "Manufacturing \u0026 Wholesale Goods"
      }
    ],
    "sg:phone": "+1 740 353 5290",
    "sg:postcode": "45662",
    "sg:province": "OH",
    "sg:tags": [
      "refractory",
      "shape"
    ],
    "wof:name": "A \u0026 M Refractories",
    "wof:placetype": "venue"
  },
  "geometry": {"coordinates":[-82.992703,38.752094],"type":"Point"}
}
