{
  "type": "Feature",
  "properties": {
    "addr:full": "9054 McKinley Dr Northfield OH 44067",
    "addr:housenumber": "9054",
    "addr:postcode": "44067",
    "addr:street": "Mckinley Dr",
    "iso:country": "US",
    "sg:address": "9054 McKinley Dr",
    "sg:city": "Northfield",
    "sg:classifiers": [
      {
        "category": "Marine",
        "type": "Transportation"
      }
    ],
    "sg:phone": "+1 330 467 1132",
    "sg:postcode": "44067",
    "sg:province": "OH",
    "sg:tags": [
      "water",
      "transport"
    ],
    "wof:name": "Fish On Charters",
    "wof:placetype": "venue"
  },
  "geometry": {"coordinates":[-81.538697,41.345587],"type":"Point"}
}
