{
  "type": "Feature",
  "properties": {
    "addr:full":"40 Severance Cir Cleveland OH 44118",
    "addr:housenumber":"40",
    "addr:postcode":"44118",
    "addr:street":"Severance Cir",
    "iso:country":"US",
    "sg:address":"40 Severance Cir",
    "sg:city":"Cleveland",
    "sg:classifiers":[
        {
            "category":"Social Services",
            "type":"Services"
        }
    ],
    "sg:phone":"+1 216 691 7377",
    "sg:postcode":"44118",
    "sg:province":"OH",
    "sg:tags":[
        "senior",
        "citizen"
    ],
    "sg:website":"www.cainpark.com",
    "wof:name":"Cleveland Hts Sr Activity Ctr",
    "wof:placetype":"venue"
},
  "geometry": {"coordinates":[-81.547898,41.517994],"type":"Point"}
}