{
  "type": "Feature",
  "properties": {
    "iso:country":"US",
    "sg:address":"518 Garfield Ave",
    "sg:city":"Troy",
    "sg:classifiers":[
        {
            "category":"Organizations",
            "subcategory":"Non-profit Organization",
            "type":"Services"
        }
    ],
    "sg:phone":"+1 937 332 3763",
    "sg:postcode":"45373",
    "sg:province":"OH",
    "sg:tags":[
        "contractor",
        "ho",
        "family",
        "provides"
    ],
    "wof:name":"Habitat For Hmnty of Miami",
    "wof:placetype":"venue"
},
  "geometry": {"coordinates":[-84.212411,40.035863],"type":"Point"}
}