{
  "type": "Feature",
  "properties": {
    "addr:full": "8135 Wisteria Dr Chagrin Falls OH 44023",
    "addr:housenumber": "8135",
    "addr:postcode": "44023",
    "addr:street": "Wisteria Dr",
    "iso:country": "US",
    "sg:address": "8135 Wisteria Dr",
    "sg:city": "Chagrin Falls",
    "sg:classifiers": [
      {
        "category": "Shopping",
        "subcategory": "Clothing, Apparel, \u0026 Fashions",
        "type": "Retail Goods"
      }
    ],
    "sg:phone": "+1 440 543 2514",
    "sg:postcode": "44023",
    "sg:province": "OH",
    "wof:name": "Allure Inside Out",
    "wof:placetype": "venue"
  },
  "geometry": {"coordinates":[-81.352428,41.370965],"type":"Point"}
}
