{
  "type": "Feature",
  "properties": {
    "iso:country":"US",
    "sg:address":"16215 Madison Ave",
    "sg:city":"Lakewood",
    "sg:classifiers":[
        {
            "category":"Health Services",
            "subcategory":"Doctor",
            "type":"Services"
        }
    ],
    "sg:phone":"+1 216 521 4400",
    "sg:postcode":"44107",
    "sg:province":"OH",
    "sg:tags":[
        "practice",
        "group",
        "primary",
        "care"
    ],
    "wof:name":"Lakewood Clveland Fmly Med Ctr",
    "wof:placetype":"venue"
},
  "geometry": {"coordinates":[-81.811665,41.477342],"type":"Point"}
}