{
  "type": "Feature",
  "properties": {
    "addr:full":"11106 Avon Ave Cleveland OH 44105",
    "addr:housenumber":"11106",
    "addr:postcode":"44105",
    "addr:street":"Avon Ave",
    "iso:country":"US",
    "sg:address":"11106 Avon Ave",
    "sg:city":"Cleveland",
    "sg:classifiers":[
        {
            "category":"Freight",
            "type":"Transportation"
        }
    ],
    "sg:phone":"+1 216 341 5479",
    "sg:postcode":"44105",
    "sg:province":"OH",
    "wof:name":"RWR Transportation LTD",
    "wof:placetype":"venue"
},
  "geometry": {"coordinates":[-81.608487,41.451271],"type":"Point"}
}