{
  "type": "Feature",
  "properties": {
    "addr:full":"212 Wabash Ave N Brewster OH 44613",
    "addr:housenumber":"212",
    "addr:postcode":"44613",
    "addr:street":"Wabash Ave N",
    "iso:country":"US",
    "sg:address":"212 Wabash Ave N",
    "sg:city":"Brewster",
    "sg:classifiers":[
        {
            "category":"Autos & Motor Vehicles",
            "subcategory":"Automobile Sales",
            "type":"Retail Goods"
        }
    ],
    "sg:phone":"+1 330 767 2277",
    "sg:postcode":"44613",
    "sg:province":"OH",
    "sg:tags":[
        "car",
        "dealer"
    ],
    "wof:name":"Ries Motors",
    "wof:placetype":"venue"
},
  "geometry": {"coordinates":[-81.597343,40.717258],"type":"Point"}
}