{
  "type": "Feature",
  "properties": {
    "addr:full": "9196 Sharp Rd Olmsted Falls OH 44138",
    "addr:housenumber": "9196",
    "addr:postcode": "44138",
    "addr:street": "Sharp Rd",
    "iso:country": "US",
    "sg:address": "9196 Sharp Rd",
    "sg:city": "Olmsted Falls",
    "sg:classifiers": [
      {
        "category": "Building \u0026 Trades",
        "subcategory": "Construction",
        "type": "Services"
      }
    ],
    "sg:phone": "+1 440 235 5239",
    "sg:postcode": "44138",
    "sg:province": "OH",
    "sg:tags": [
      "carpentry",
      "contractor"
    ],
    "wof:name": "Complete/Restoration",
    "wof:placetype": "venue"
  },
  "geometry": {"coordinates":[-81.954277,41.363057],"type":"Point"}
}
