{
  "type": "Feature",
  "properties": {
    "iso:country":"US",
    "sg:address":"3704 Chelsea Dr",
    "sg:city":"Brunswick",
    "sg:classifiers":[
        {
            "category":"Building & Trades",
            "subcategory":"Construction",
            "type":"Services"
        }
    ],
    "sg:phone":"+1 330 225 2134",
    "sg:postcode":"44212",
    "sg:province":"OH",
    "sg:tags":[
        "contractor"
    ],
    "wof:name":"West Interiors Inc",
    "wof:placetype":"venue"
},
  "geometry": {"coordinates":[-81.818552,41.228999],"type":"Point"}
}