{
  "type": "Feature",
  "properties": {
    "iso:country":"US",
    "sg:address":"35886 Lakeland Blvd",
    "sg:city":"Willoughby",
    "sg:classifiers":[
        {
            "category":"Retail",
            "subcategory":"Auto Repair",
            "type":"Services"
        }
    ],
    "sg:phone":"+1 440 946 7100",
    "sg:postcode":"44095",
    "sg:province":"OH",
    "sg:tags":[
        "body",
        "automobile",
        "painting"
    ],
    "wof:name":"Jeff's Paint & Body Work Inc",
    "wof:placetype":"venue"
},
  "geometry": {"coordinates":[-81.436159,41.635945],"type":"Point"}
}