{
  "type": "Feature",
  "properties": {
    "iso:country":"US",
    "sg:address":"14822 Lake Shore Blvd",
    "sg:city":"Cleveland",
    "sg:classifiers":[
        {
            "category":"Professional",
            "subcategory":"Detective & Security Services",
            "type":"Services"
        }
    ],
    "sg:phone":"+1 216 348 7111",
    "sg:postcode":"44110",
    "sg:province":"OH",
    "sg:tags":[
        "guard",
        "patrol"
    ],
    "wof:name":"Lake Shore Patrol",
    "wof:placetype":"venue"
},
  "geometry": {"coordinates":[-81.578041,41.572972],"type":"Point"}
}