{
  "type": "Feature",
  "properties": {
    "addr:full": "14822 Lake Shore Blvd Cleveland OH 44110",
    "addr:housenumber": "14822",
    "addr:postcode": "44110",
    "addr:street": "Lake Shore Blvd",
    "iso:country": "US",
    "sg:address": "14822 Lake Shore Blvd",
    "sg:city": "Cleveland",
    "sg:classifiers": [
      {
        "category": "Professional",
        "subcategory": "Detective \u0026 Security Services",
        "type": "Services"
      }
    ],
    "sg:phone": "+1 216 348 7111",
    "sg:postcode": "44110",
    "sg:province": "OH",
    "sg:tags": [
      "guard",
      "patrol"
    ],
    "wof:name": "Lake Shore Patrol",
    "wof:placetype": "venue"
  },
  "geometry": {"coordinates":[-81.578041,41.572972],"type":"Point"}
}
