{
  "type": "Feature",
  "properties": {
    "iso:country":"US",
    "sg:address":"864 State Rte 138 NE",
    "sg:city":"Greenfield",
    "sg:classifiers":[
        {
            "category":"Building & Trades",
            "subcategory":"Construction",
            "type":"Services"
        }
    ],
    "sg:phone":"+1 937 981 3610",
    "sg:postcode":"45123",
    "sg:province":"OH",
    "sg:tags":[
        "excavating",
        "contractor"
    ],
    "wof:name":"Mc Neal's Excavating",
    "wof:placetype":"venue"
},
  "geometry": {"coordinates":[-83.370588,39.362437],"type":"Point"}
}