{
  "type": "Feature",
  "properties": {
    "addr:full": "248 Niles Cortland Rd NE Warren OH 44484",
    "addr:housenumber": "248",
    "addr:postcode": "44484",
    "addr:street": "Niles Cortland Rd Ne",
    "iso:country": "US",
    "sg:address": "248 Niles Cortland Rd NE",
    "sg:city": "Warren",
    "sg:classifiers": [
      {
        "category": "Health Services",
        "subcategory": "Podiatrist",
        "type": "Services"
      }
    ],
    "sg:phone": "+1 330 856 1700",
    "sg:postcode": "44484",
    "sg:province": "OH",
    "wof:name": "Thomas M Pokabla DPM",
    "wof:placetype": "venue"
  },
  "geometry": {"coordinates":[-80.740491,41.242232],"type":"Point"}
}
