{
  "type": "Feature",
  "properties": {
    "iso:country":"US",
    "sg:address":"4132 US Hwy 23",
    "sg:city":"Portsmouth",
    "sg:classifiers":[
        {
            "category":"Building & Trades",
            "subcategory":"Pest Control",
            "type":"Services"
        }
    ],
    "sg:phone":"+1 740 354 3281",
    "sg:postcode":"45662",
    "sg:province":"OH",
    "wof:name":"Orkin Exterminating Co Inc",
    "wof:placetype":"venue"
},
  "geometry": {"coordinates":[-82.985116,38.789731],"type":"Point"}
}