{
  "type": "Feature",
  "properties": {
    "addr:full": "4132 US Hwy 23 Portsmouth OH 45662",
    "addr:housenumber": "4132",
    "addr:postcode": "45662",
    "addr:street": "Us Hwy 23",
    "iso:country": "US",
    "sg:address": "4132 US Hwy 23",
    "sg:city": "Portsmouth",
    "sg:classifiers": [
      {
        "category": "Building \u0026 Trades",
        "subcategory": "Pest Control",
        "type": "Services"
      }
    ],
    "sg:phone": "+1 740 354 3281",
    "sg:postcode": "45662",
    "sg:province": "OH",
    "wof:name": "Orkin Exterminating Co Inc",
    "wof:placetype": "venue"
  },
  "geometry": {"coordinates":[-82.985116,38.789731],"type":"Point"}
}
