{
  "type": "Feature",
  "properties": {
    "addr:full": "6449 Marcy Rd Pierpont OH 44082",
    "addr:housenumber": "6449",
    "addr:postcode": "44082",
    "addr:street": "Marcy Rd",
    "iso:country": "US",
    "sg:address": "6449 Marcy Rd",
    "sg:city": "Pierpont",
    "sg:phone": "+1 440 577 1210",
    "sg:postcode": "44082",
    "sg:province": "OH",
    "sg:tags": [
      "farm",
      "wheat",
      "corn",
      "dairy",
      "soybean"
    ],
    "wof:name": "Randy Woodard",
    "wof:placetype": "venue"
  },
  "geometry": {"coordinates":[-80.558889,41.752618],"type":"Point"}
}
