{
  "type": "Feature",
  "properties": {
    "addr:full":"201 W Charles St Bucyrus OH 44820",
    "addr:housenumber":"201",
    "addr:postcode":"44820",
    "addr:street":"W Charles St",
    "iso:country":"US",
    "sg:address":"201 W Charles St",
    "sg:city":"Bucyrus",
    "sg:classifiers":[
        {
            "category":"Professional",
            "subcategory":"Accounting & Tax Preparation",
            "type":"Services"
        }
    ],
    "sg:phone":"+1 419 562 6286",
    "sg:postcode":"44820",
    "sg:province":"OH",
    "sg:tags":[
        "accountant"
    ],
    "wof:name":"Pigman & Walter & Assoc",
    "wof:placetype":"venue"
},
  "geometry": {"coordinates":[-82.97781500000001,40.8054],"type":"Point"}
}