{
  "type": "Feature",
  "properties": {
    "iso:country":"US",
    "sg:address":"4165 N West St",
    "sg:city":"Lima",
    "sg:classifiers":[
        {
            "category":"Retail",
            "subcategory":"Auto Repair",
            "type":"Services"
        }
    ],
    "sg:phone":"+1 419 225 8185",
    "sg:postcode":"45801",
    "sg:province":"OH",
    "sg:tags":[
        "body",
        "automobile",
        "painting"
    ],
    "wof:name":"Cellar's Auto Body",
    "wof:placetype":"venue"
},
  "geometry": {"coordinates":[-84.10893,40.79689],"type":"Point"}
}