{
  "type": "Feature",
  "properties": {
    "addr:full":"12184 Lisbon Rd Greenford OH 44460",
    "addr:housenumber":"12184",
    "addr:postcode":"44460",
    "addr:street":"Lisbon Rd",
    "iso:country":"US",
    "sg:address":"12184 Lisbon Rd",
    "sg:city":"Greenford",
    "sg:classifiers":[
        {
            "category":"Government",
            "subcategory":"Post Office",
            "type":"Public Place"
        }
    ],
    "sg:phone":"+1 330 533 7134",
    "sg:postcode":"44460",
    "sg:province":"OH",
    "sg:tags":[
        "postal",
        "us"
    ],
    "wof:name":"US Post Office",
    "wof:placetype":"venue"
},
  "geometry": {"coordinates":[-80.790395,40.939767],"type":"Point"}
}