{
  "type": "Feature",
  "properties": {
    "addr:full": "2014 S Smithville Rd Dayton OH 45420",
    "addr:housenumber": "2014",
    "addr:postcode": "45420",
    "addr:street": "S Smithville Rd",
    "iso:country": "US",
    "sg:address": "2014 S Smithville Rd",
    "sg:city": "Dayton",
    "sg:classifiers": [
      {
        "category": "Retail",
        "subcategory": "Repair Shop",
        "type": "Services"
      }
    ],
    "sg:phone": "+1 937 252 9644",
    "sg:postcode": "45420",
    "sg:province": "OH",
    "sg:tags": [
      "nonferrous"
    ],
    "wof:name": "Tin Shop Inc",
    "wof:placetype": "venue"
  },
  "geometry": {"coordinates":[-84.140432,39.737363],"type":"Point"}
}
