{
  "type": "Feature",
  "properties": {
    "addr:full": "54382 National Rd Bridgeport OH 43912",
    "addr:housenumber": "54382",
    "addr:postcode": "43912",
    "addr:street": "National Rd",
    "iso:country": "US",
    "sg:address": "54382 National Rd",
    "sg:city": "Bridgeport",
    "sg:classifiers": [
      {
        "category": "Home \u0026 Garden",
        "subcategory": "Building Materials",
        "type": "Retail Goods"
      }
    ],
    "sg:phone": "+1 740 635 9000",
    "sg:postcode": "43912",
    "sg:province": "OH",
    "wof:name": "Lorenzi Building Products Ctr",
    "wof:placetype": "venue"
  },
  "geometry": {"coordinates":[-80.804091,40.068237],"type":"Point"}
}
