{
  "type": "Feature",
  "properties": {
    "addr:full":"1660 Bechtle Ave Springfield OH 45504",
    "addr:housenumber":"1660",
    "addr:postcode":"45504",
    "addr:street":"Bechtle Ave",
    "iso:country":"US",
    "sg:address":"1660 Bechtle Ave",
    "sg:city":"Springfield",
    "sg:classifiers":[
        {
            "category":"Restaurant",
            "type":"Food & Drink"
        }
    ],
    "sg:phone":"+1 937 325 6888",
    "sg:postcode":"45504",
    "sg:province":"OH",
    "wof:name":"King Buffet Chinese Rstrnt",
    "wof:placetype":"venue"
},
  "geometry": {"coordinates":[-83.83558600000001,39.942353],"type":"Point"}
}