{
  "type": "Feature",
  "properties": {
    "iso:country":"US",
    "sg:address":"926 E McMillan St",
    "sg:city":"Cincinnati",
    "sg:classifiers":[
        {
            "category":"Shopping",
            "type":"Retail Goods"
        }
    ],
    "sg:phone":"+1 513 861 2485",
    "sg:postcode":"45206",
    "sg:province":"OH",
    "sg:tags":[
        "cosmetic",
        "perfume"
    ],
    "wof:name":"Wig Land",
    "wof:placetype":"venue"
},
  "geometry": {"coordinates":[-84.488446,39.125907],"type":"Point"}
}