{
  "type": "Feature",
  "properties": {
    "addr:full": "1367 Hildreth Ave Columbus OH 43203",
    "addr:housenumber": "1367",
    "addr:postcode": "43203",
    "addr:street": "Hildreth Ave",
    "iso:country": "US",
    "sg:address": "1367 Hildreth Ave",
    "sg:city": "Columbus",
    "sg:classifiers": [
      {
        "category": "Wholesale",
        "subcategory": "Vending Machines",
        "type": "Manufacturing \u0026 Wholesale Goods"
      }
    ],
    "sg:phone": "+1 614 253 0505",
    "sg:postcode": "43203",
    "sg:province": "OH",
    "sg:tags": [
      "operator"
    ],
    "wof:name": "Mikey S Vending",
    "wof:placetype": "venue"
  },
  "geometry": {"coordinates":[-82.966714,39.974077],"type":"Point"}
}
