{
  "type": "Feature",
  "properties": {
    "addr:full": "1622 Clarendon Ave SW Canton OH 44706",
    "addr:housenumber": "1622",
    "addr:postcode": "44706",
    "addr:street": "Clarendon Ave Sw",
    "iso:country": "US",
    "sg:address": "1622 Clarendon Ave SW",
    "sg:city": "Canton",
    "sg:classifiers": [
      {
        "category": "Shopping",
        "subcategory": "Hobbies, Toys, \u0026 Games",
        "type": "Retail Goods"
      }
    ],
    "sg:phone": "+1 330 454 9706",
    "sg:postcode": "44706",
    "sg:province": "OH",
    "wof:name": "G\u0026L Crafts",
    "wof:placetype": "venue"
  },
  "geometry": {"coordinates":[-81.40421,40.780933],"type":"Point"}
}
