{
  "type": "Feature",
  "properties": {
    "iso:country":"US",
    "sg:address":"1622 Clarendon Ave SW",
    "sg:city":"Canton",
    "sg:classifiers":[
        {
            "category":"Shopping",
            "subcategory":"Hobbies, Toys, & Games",
            "type":"Retail Goods"
        }
    ],
    "sg:phone":"+1 330 454 9706",
    "sg:postcode":"44706",
    "sg:province":"OH",
    "wof:name":"G&L Crafts",
    "wof:placetype":"venue"
},
  "geometry": {"coordinates":[-81.40421000000001,40.780933],"type":"Point"}
}