{
  "type": "Feature",
  "properties": {
    "addr:full": "6002 W Smith Rd Medina OH 44256",
    "addr:housenumber": "6002",
    "addr:postcode": "44256",
    "addr:street": "W Smith Rd",
    "iso:country": "US",
    "sg:address": "6002 W Smith Rd",
    "sg:city": "Medina",
    "sg:classifiers": [
      {
        "category": "Wholesale",
        "subcategory": "Hardware",
        "type": "Manufacturing \u0026 Wholesale Goods"
      },
      {
        "category": "Shopping",
        "type": "Retail Goods"
      },
      {
        "category": "Building \u0026 Trades",
        "subcategory": "Plumbing",
        "type": "Services"
      }
    ],
    "sg:phone": "+1 330 786 1380",
    "sg:postcode": "44256",
    "sg:province": "OH",
    "sg:tags": [
      "water",
      "heater",
      "contractor"
    ],
    "wof:name": "A 1 Hot Water Tanks",
    "wof:placetype": "venue"
  },
  "geometry": {"coordinates":[-81.907973,41.135996],"type":"Point"}
}
