{
  "type": "Feature",
  "properties": {
    "iso:country":"US",
    "sg:address":"6002 W Smith Rd",
    "sg:city":"Medina",
    "sg:classifiers":[
        {
            "category":"Wholesale",
            "subcategory":"Hardware",
            "type":"Manufacturing & Wholesale Goods"
        },
        {
            "category":"Shopping",
            "type":"Retail Goods"
        },
        {
            "category":"Building & Trades",
            "subcategory":"Plumbing",
            "type":"Services"
        }
    ],
    "sg:phone":"+1 330 786 1380",
    "sg:postcode":"44256",
    "sg:province":"OH",
    "sg:tags":[
        "water",
        "heater",
        "contractor"
    ],
    "wof:name":"A 1 Hot Water Tanks",
    "wof:placetype":"venue"
},
  "geometry": {"coordinates":[-81.907973,41.135996],"type":"Point"}
}