{
  "type": "Feature",
  "properties": {
    "iso:country":"US",
    "sg:address":"10530 Wellington Blvd",
    "sg:city":"Powell",
    "sg:classifiers":[
        {
            "category":"Health Services",
            "subcategory":"Doctor",
            "type":"Services"
        }
    ],
    "sg:phone":"+1 614 791 1298",
    "sg:postcode":"43065",
    "sg:province":"OH",
    "sg:tags":[
        "clinic"
    ],
    "wof:name":"Hygene Biomedical",
    "wof:placetype":"venue"
},
  "geometry": {"coordinates":[-83.09781,40.144734],"type":"Point"}
}