{
  "type": "Feature",
  "properties": {
    "addr:full": "585 N Trimble Rd Mansfield OH 44906",
    "addr:housenumber": "585",
    "addr:postcode": "44906",
    "addr:street": "N Trimble Rd",
    "iso:country": "US",
    "sg:address": "585 N Trimble Rd",
    "sg:city": "Mansfield",
    "sg:classifiers": [
      {
        "category": "Autos \u0026 Motor Vehicles",
        "subcategory": "Fuel \u0026 Gas Station",
        "type": "Retail Goods"
      }
    ],
    "sg:phone": "+1 419 747 1170",
    "sg:postcode": "44906",
    "sg:province": "OH",
    "sg:tags": [
      "oil"
    ],
    "wof:name": "Don's Sunoco",
    "wof:placetype": "venue"
  },
  "geometry": {"coordinates":[-82.5517,40.776395],"type":"Point"}
}
