{
  "type": "Feature",
  "properties": {
    "iso:country":"US",
    "sg:address":"4126 Pearl Rd",
    "sg:city":"Cleveland",
    "sg:classifiers":[
        {
            "category":"Food & Beverages",
            "subcategory":"Groceries & Convenience Stores",
            "type":"Retail Goods"
        }
    ],
    "sg:phone":"+1 216 661 0721",
    "sg:postcode":"44109",
    "sg:province":"OH",
    "wof:name":"Petro Mart Inc",
    "wof:placetype":"venue"
},
  "geometry": {"coordinates":[-81.703579,41.443995],"type":"Point"}
}