{
  "type": "Feature",
  "properties": {
    "addr:full": "8171 Warren-Sharon Rd Masury OH 44438",
    "addr:housenumber": "8171",
    "addr:postcode": "44438",
    "addr:street": "Warren-Sharon Rd",
    "iso:country": "US",
    "sg:address": "8171 Warren-Sharon Rd",
    "sg:city": "Masury",
    "sg:classifiers": [
      {
        "category": "Food \u0026 Beverages",
        "subcategory": "Groceries \u0026 Convenience Stores",
        "type": "Retail Goods"
      }
    ],
    "sg:phone": "+1 330 448 0760",
    "sg:postcode": "44438",
    "sg:province": "OH",
    "sg:tags": [
      "grocer"
    ],
    "wof:name": "Standard Market Inc",
    "wof:placetype": "venue"
  },
  "geometry": {"coordinates":[-80.52311,41.23384],"type":"Point"}
}
