{
  "type": "Feature",
  "properties": {
    "addr:full": "663 Arch St Salem OH 44460",
    "addr:housenumber": "663",
    "addr:postcode": "44460",
    "addr:street": "Arch St",
    "iso:country": "US",
    "sg:address": "663 Arch St",
    "sg:city": "Salem",
    "sg:classifiers": [
      {
        "category": "Building \u0026 Trades",
        "subcategory": "Plumbing",
        "type": "Services"
      }
    ],
    "sg:phone": "+1 330 332 8805",
    "sg:postcode": "44460",
    "sg:province": "OH",
    "sg:tags": [
      "contractor"
    ],
    "wof:name": "Sunrise Plbg Repr \u0026 Draining",
    "wof:placetype": "venue"
  },
  "geometry": {"coordinates":[-80.866104,40.895077],"type":"Point"}
}
