{
  "type": "Feature",
  "properties": {
    "addr:full":"5414 Forest Highland Ct Westerville OH 43082",
    "addr:housenumber":"5414",
    "addr:postcode":"43082",
    "addr:street":"Forest Highland Ct",
    "iso:country":"US",
    "sg:address":"5414 Forest Highland Ct",
    "sg:city":"Westerville",
    "sg:classifiers":[
        {
            "category":"Building & Trades",
            "subcategory":"Electrical",
            "type":"Services"
        }
    ],
    "sg:phone":"+1 614 895 0943",
    "sg:postcode":"43082",
    "sg:province":"OH",
    "sg:tags":[
        "electrical",
        "contractor"
    ],
    "wof:name":"Posi-Tread LLC",
    "wof:placetype":"venue"
},
  "geometry": {"coordinates":[-82.931251,40.157983],"type":"Point"}
}