{
  "type": "Feature",
  "properties": {
    "addr:full": "1905 Torchwood Dr Columbus OH 43229",
    "addr:housenumber": "1905",
    "addr:postcode": "43229",
    "addr:street": "Torchwood Dr",
    "iso:country": "US",
    "sg:address": "1905 Torchwood Dr",
    "sg:city": "Columbus",
    "sg:classifiers": [
      {
        "category": "Professional",
        "subcategory": "Management \u0026 Consulting",
        "type": "Services"
      }
    ],
    "sg:phone": "+1 614 847 3627",
    "sg:postcode": "43229",
    "sg:province": "OH",
    "sg:tags": [
      "distributor",
      "snack"
    ],
    "wof:name": "United Snack Group Inc",
    "wof:placetype": "venue"
  },
  "geometry": {"coordinates":[-82.966288,40.07879],"type":"Point"}
}
