{
  "type": "Feature",
  "properties": {
    "addr:full":"406 Jamison Rd Frankfort OH 45628",
    "addr:housenumber":"406",
    "addr:postcode":"45628",
    "addr:street":"Jamison Rd",
    "iso:country":"US",
    "sg:address":"406 Jamison Rd",
    "sg:city":"Frankfort",
    "sg:classifiers":[
        {
            "category":"Manufacturing",
            "subcategory":"Metals",
            "type":"Manufacturing & Wholesale Goods"
        }
    ],
    "sg:phone":"+1 740 998 4304",
    "sg:postcode":"45628",
    "sg:province":"OH",
    "wof:name":"Buckeye Metal Sales",
    "wof:placetype":"venue"
},
  "geometry": {"coordinates":[-83.199973,39.386229],"type":"Point"}
}