{
  "type": "Feature",
  "properties": {
    "iso:country":"US",
    "sg:address":"1640 Fishinger Rd",
    "sg:city":"Columbus",
    "sg:classifiers":[
        {
            "category":"Food & Beverages",
            "subcategory":"Groceries & Convenience Stores",
            "type":"Retail Goods"
        }
    ],
    "sg:phone":"+1 614 457 3996",
    "sg:postcode":"43221",
    "sg:province":"OH",
    "wof:name":"Sunoco",
    "wof:placetype":"venue"
},
  "geometry": {"coordinates":[-83.05953700000001,40.026565],"type":"Point"}
}