{
  "type": "Feature",
  "properties": {
    "addr:full":"877 Wright St Newtonsville OH 45158",
    "addr:housenumber":"877",
    "addr:postcode":"45158",
    "addr:street":"Wright St",
    "iso:country":"US",
    "sg:address":"877 Wright St",
    "sg:city":"Newtonsville",
    "sg:classifiers":[
        {
            "category":"Retail",
            "subcategory":"Animal Services",
            "type":"Services"
        }
    ],
    "sg:phone":"+1 513 625 5106",
    "sg:postcode":"45158",
    "sg:province":"OH",
    "sg:tags":[
        "pet",
        "grooming",
        "washing"
    ],
    "wof:name":"Bridon Grooming",
    "wof:placetype":"venue"
},
  "geometry": {"coordinates":[-84.077822,39.181515],"type":"Point"}
}