{
  "type": "Feature",
  "properties": {
    "addr:full": "12101 Berlin Rd Berlin Heights OH 44814",
    "addr:postcode": "12101;44814",
    "addr:street": "Berlin Rd",
    "iso:country": "US",
    "sg:address": "12101 Berlin Rd",
    "sg:city": "Berlin Heights",
    "sg:classifiers": [
      {
        "category": "Government",
        "subcategory": "Fire Station",
        "type": "Public Place"
      }
    ],
    "sg:phone": "+1 419 588 2667",
    "sg:postcode": "44814",
    "sg:province": "OH",
    "sg:tags": [
      "department"
    ],
    "wof:name": "Berlin Fire",
    "wof:placetype": "venue"
  },
  "geometry": {"coordinates":[-82.499267,41.318761],"type":"Point"}
}
