{
  "type": "Feature",
  "properties": {
    "addr:full": "1862 Noble Rd Cleveland OH 44112",
    "addr:housenumber": "1862",
    "addr:postcode": "44112",
    "addr:street": "Noble Rd",
    "iso:country": "US",
    "sg:address": "1862 Noble Rd",
    "sg:city": "Cleveland",
    "sg:classifiers": [
      {
        "category": "Organizations",
        "subcategory": "Religious Organization",
        "type": "Services"
      }
    ],
    "sg:phone": "+1 216 851 4388",
    "sg:postcode": "44112",
    "sg:province": "OH",
    "wof:name": "Christ The King",
    "wof:placetype": "venue"
  },
  "geometry": {"coordinates":[-81.566909,41.542968],"type":"Point"}
}
