{
  "type": "Feature",
  "properties": {
    "iso:country":"US",
    "sg:address":"5277 E Broad St",
    "sg:city":"Columbus",
    "sg:classifiers":[
        {
            "category":"Organizations",
            "subcategory":"Religious Organization",
            "type":"Services"
        }
    ],
    "sg:phone":"+1 614 866 1611",
    "sg:postcode":"43213",
    "sg:province":"OH",
    "sg:tags":[
        "church"
    ],
    "wof:name":"St Theresa's Retreat Ctr",
    "wof:placetype":"venue"
},
  "geometry": {"coordinates":[-82.864984,39.977092],"type":"Point"}
}