{
  "type": "Feature",
  "properties": {
    "iso:country":"US",
    "sg:address":"620 E Smith Rd",
    "sg:city":"Medina",
    "sg:classifiers":[
        {
            "category":"Freight",
            "type":"Transportation"
        },
        {
            "category":"Local Transit",
            "type":"Transportation"
        }
    ],
    "sg:phone":"+1 330 273 6041",
    "sg:postcode":"44256",
    "sg:province":"OH",
    "sg:tags":[
        "airport"
    ],
    "wof:name":"Foxx Transportation",
    "wof:placetype":"venue"
},
  "geometry": {"coordinates":[-81.84746,41.134588],"type":"Point"}
}