{
  "type": "Feature",
  "properties": {
    "addr:full": "1500 Maple Ave NE Canton OH 44705",
    "addr:housenumber": "1500",
    "addr:postcode": "44705",
    "addr:street": "Maple Ave Ne",
    "iso:country": "US",
    "sg:address": "1500 Maple Ave NE",
    "sg:city": "Canton",
    "sg:classifiers": [
      {
        "category": "Utilities",
        "subcategory": "Refuse",
        "type": "Services"
      }
    ],
    "sg:phone": "+1 330 434 0190",
    "sg:postcode": "44705",
    "sg:province": "OH",
    "sg:tags": [
      "garbage",
      "collection"
    ],
    "wof:name": "Disposal Services Inc",
    "wof:placetype": "venue"
  },
  "geometry": {"coordinates":[-81.354293,40.81371],"type":"Point"}
}
