{
  "type": "Feature",
  "properties": {
    "iso:country":"US",
    "sg:address":"3765 Sandlewood Dr",
    "sg:city":"Brunswick",
    "sg:classifiers":[
        {
            "category":"Building & Trades",
            "subcategory":"Construction",
            "type":"Services"
        }
    ],
    "sg:phone":"+1 330 220 5292",
    "sg:postcode":"44212",
    "sg:province":"OH",
    "sg:tags":[
        "house"
    ],
    "wof:name":"Advanced Construction Services",
    "wof:placetype":"venue"
},
  "geometry": {"coordinates":[-81.820391,41.23295],"type":"Point"}
}