{
  "type": "Feature",
  "properties": {
    "addr:full":"125 N Main St Bowling Green OH 43402",
    "addr:housenumber":"125",
    "addr:postcode":"43402",
    "addr:street":"N Main St",
    "iso:country":"US",
    "sg:address":"125 N Main St",
    "sg:city":"Bowling Green",
    "sg:classifiers":[
        {
            "category":"Professional",
            "subcategory":"Computer Services",
            "type":"Services"
        },
        {
            "category":"Shopping",
            "subcategory":"Computers & Home Electronics",
            "type":"Retail Goods"
        }
    ],
    "sg:phone":"+1 419 352 4371",
    "sg:postcode":"43402",
    "sg:province":"OH",
    "sg:tags":[
        "consultant",
        "designer",
        "programing",
        "custom"
    ],
    "wof:name":"Senecio Software Inc",
    "wof:placetype":"venue"
},
  "geometry": {"coordinates":[-83.650488,41.375723],"type":"Point"}
}