{
  "type": "Feature",
  "properties": {
    "addr:full": "833 Rutter Ave Lancaster OH 43130",
    "addr:housenumber": "833",
    "addr:postcode": "43130",
    "addr:street": "Rutter Ave",
    "iso:country": "US",
    "sg:address": "833 Rutter Ave",
    "sg:city": "Lancaster",
    "sg:classifiers": [
      {
        "category": "Wholesale",
        "subcategory": "Auto Parts",
        "type": "Manufacturing \u0026 Wholesale Goods"
      }
    ],
    "sg:phone": "+1 740 687 4607",
    "sg:postcode": "43130",
    "sg:province": "OH",
    "sg:tags": [
      "outboard",
      "motor"
    ],
    "wof:name": "American Suzuki Motor Corp",
    "wof:placetype": "venue"
  },
  "geometry": {"coordinates":[-82.586374,39.722977],"type":"Point"}
}
