{
  "type": "Feature",
  "properties": {
    "addr:full":"972 E Main St Jackson OH 45640",
    "addr:housenumber":"972",
    "addr:postcode":"45640",
    "addr:street":"E Main St",
    "iso:country":"US",
    "sg:address":"972 E Main St",
    "sg:city":"Jackson",
    "sg:classifiers":[
        {
            "category":"Cinema",
            "subcategory":"Movie Theater",
            "type":"Entertainment"
        }
    ],
    "sg:phone":"+1 740 286 4027",
    "sg:postcode":"45640",
    "sg:province":"OH",
    "sg:tags":[
        "motion",
        "picture"
    ],
    "wof:name":"Tri City Theaters",
    "wof:placetype":"venue"
},
  "geometry": {"coordinates":[-82.627088,39.036891],"type":"Point"}
}