{
  "type": "Feature",
  "properties": {
    "addr:full": "205 S High St Columbus OH 43215",
    "addr:housenumber": "205",
    "addr:postcode": "43215",
    "addr:street": "S High St",
    "iso:country": "US",
    "sg:address": "205 S High St",
    "sg:city": "Columbus",
    "sg:classifiers": [
      {
        "category": "Restaurant",
        "type": "Food \u0026 Drink"
      }
    ],
    "sg:phone": "+1 614 280 1811",
    "sg:postcode": "43215",
    "sg:province": "OH",
    "sg:tags": [
      "eating"
    ],
    "wof:name": "Canton Buffet Inc",
    "wof:placetype": "venue"
  },
  "geometry": {"coordinates":[-82.999828,39.957677],"type":"Point"}
}
