{
  "type": "Feature",
  "properties": {
    "addr:full":"743 S High St Columbus OH 43206",
    "addr:housenumber":"743",
    "addr:postcode":"43206",
    "addr:street":"S High St",
    "iso:country":"US",
    "sg:address":"743 S High St",
    "sg:city":"Columbus",
    "sg:classifiers":[
        {
            "category":"Bagels",
            "type":"Food & Drink"
        }
    ],
    "sg:menulink":"http://www.allmenus.com/oh/columbus/149715-einstein-bros/menu/",
    "sg:phone":"+1 614 449 2164",
    "sg:postcode":"43206",
    "sg:province":"OH",
    "sg:tags":[
        "wrap",
        "soup",
        "american",
        "sandwich",
        "salad"
    ],
    "wof:name":"Einstein Bros",
    "wof:placetype":"venue"
},
  "geometry": {"coordinates":[-82.997891,39.946778],"type":"Point"}
}