{
  "type": "Feature",
  "properties": {
    "addr:full": "324 Chestnut St Coshocton OH 43812",
    "addr:housenumber": "324",
    "addr:postcode": "43812",
    "addr:street": "Chestnut St",
    "iso:country": "US",
    "sg:address": "324 Chestnut St",
    "sg:city": "Coshocton",
    "sg:classifiers": [
      {
        "category": "Building \u0026 Trades",
        "subcategory": "Cleaning \u0026 Sanitation",
        "type": "Services"
      }
    ],
    "sg:phone": "+1 740 623 6500",
    "sg:postcode": "43812",
    "sg:province": "OH",
    "sg:tags": [
      "executive",
      "maintenance"
    ],
    "wof:name": "Coshocton County Maint Dept",
    "wof:placetype": "venue"
  },
  "geometry": {"coordinates":[-81.866649,40.27512],"type":"Point"}
}
