{
  "type": "Feature",
  "properties": {
    "iso:country":"US",
    "sg:address":"324 Chestnut St",
    "sg:city":"Coshocton",
    "sg:classifiers":[
        {
            "category":"Building & Trades",
            "subcategory":"Cleaning & Sanitation",
            "type":"Services"
        }
    ],
    "sg:phone":"+1 740 623 6500",
    "sg:postcode":"43812",
    "sg:province":"OH",
    "sg:tags":[
        "executive",
        "maintenance"
    ],
    "wof:name":"Coshocton County Maint Dept",
    "wof:placetype":"venue"
},
  "geometry": {"coordinates":[-81.866649,40.27512],"type":"Point"}
}