{
  "type": "Feature",
  "properties": {
    "addr:full":"27 S High St Glouster OH 45732",
    "addr:housenumber":"27",
    "addr:postcode":"45732",
    "addr:street":"S High St",
    "iso:country":"US",
    "sg:address":"27 S High St",
    "sg:city":"Glouster",
    "sg:classifiers":[
        {
            "category":"Shopping",
            "subcategory":"Discount & Variety Stores",
            "type":"Retail Goods"
        }
    ],
    "sg:phone":"+1 740 767 3704",
    "sg:postcode":"45732",
    "sg:province":"OH",
    "wof:name":"Dollar General",
    "wof:placetype":"venue"
},
  "geometry": {"coordinates":[-82.085255,39.499564],"type":"Point"}
}