{
  "type": "Feature",
  "properties": {
    "addr:full": "1001 W Main St Louisville OH 44641",
    "addr:housenumber": "1001",
    "addr:postcode": "44641",
    "addr:street": "W Main St",
    "iso:country": "US",
    "sg:address": "1001 W Main St",
    "sg:city": "Louisville",
    "sg:classifiers": [
      {
        "category": "Insurance",
        "subcategory": "Insurance Agent",
        "type": "Services"
      }
    ],
    "sg:phone": "+1 330 875 8592",
    "sg:postcode": "44641",
    "sg:province": "OH",
    "wof:name": "R L Byers Insurance",
    "wof:placetype": "venue"
  },
  "geometry": {"coordinates":[-81.269927,40.836466],"type":"Point"}
}
