{
  "type": "Feature",
  "properties": {
    "iso:country":"US",
    "sg:address":"2408 Ley Dr",
    "sg:city":"Akron",
    "sg:classifiers":[
        {
            "category":"Freight",
            "type":"Transportation"
        }
    ],
    "sg:phone":"+1 330 699 1198",
    "sg:postcode":"44319",
    "sg:province":"OH",
    "sg:tags":[
        "local",
        "without",
        "storage",
        "provides",
        "trucking"
    ],
    "wof:name":"Norms Trucking Co Inc",
    "wof:placetype":"venue"
},
  "geometry": {"coordinates":[-81.537564,41.027391],"type":"Point"}
}