{
  "type": "Feature",
  "properties": {
    "addr:full": "71 Chelsea Dr Granville OH 43023",
    "addr:housenumber": "71",
    "addr:postcode": "43023",
    "addr:street": "Chelsea Dr",
    "iso:country": "US",
    "sg:address": "71 Chelsea Dr",
    "sg:city": "Granville",
    "sg:classifiers": [
      {
        "category": "Professional",
        "type": "Services"
      }
    ],
    "sg:phone": "+1 740 587 3052",
    "sg:postcode": "43023",
    "sg:province": "OH",
    "wof:name": "Mark Hauenstein",
    "wof:placetype": "venue"
  },
  "geometry": {"coordinates":[-82.541761,40.078252],"type":"Point"}
}
