{
  "type": "Feature",
  "properties": {
    "addr:full": "10165 Phillipp Pkwy Streetsboro OH 44241",
    "addr:housenumber": "10165",
    "addr:postcode": "44241",
    "addr:street": "Phillipp Pkwy",
    "iso:country": "US",
    "sg:address": "10165 Phillipp Pkwy",
    "sg:city": "Streetsboro",
    "sg:classifiers": [
      {
        "category": "Professional",
        "subcategory": "Business Services",
        "type": "Services"
      }
    ],
    "sg:phone": "+1 330 463 3500",
    "sg:postcode": "44241",
    "sg:province": "OH",
    "sg:tags": [
      "precision",
      "grinding"
    ],
    "wof:name": "Lange Grinding Inc",
    "wof:placetype": "venue"
  },
  "geometry": {"coordinates":[-81.365851,41.270586],"type":"Point"}
}
