{
  "type": "Feature",
  "properties": {
    "iso:country":"US",
    "sg:address":"344 E Rosewood Ave",
    "sg:city":"Defiance",
    "sg:classifiers":[
        {
            "category":"Personal",
            "subcategory":"Tanning Parlor",
            "type":"Services"
        }
    ],
    "sg:phone":"+1 419 784 5200",
    "sg:postcode":"43512",
    "sg:province":"OH",
    "sg:tags":[
        "salon"
    ],
    "wof:name":"Bronzi",
    "wof:placetype":"venue"
},
  "geometry": {"coordinates":[-84.358481,41.258484],"type":"Point"}
}