{
  "type": "Feature",
  "properties": {
    "addr:full": "1370 Troon Ave Brunswick OH 44212",
    "addr:housenumber": "1370",
    "addr:postcode": "44212",
    "addr:street": "Troon Ave",
    "iso:country": "US",
    "sg:address": "1370 Troon Ave",
    "sg:city": "Brunswick",
    "sg:classifiers": [
      {
        "category": "Building \u0026 Trades",
        "subcategory": "Construction",
        "type": "Services"
      }
    ],
    "sg:phone": "+1 330 273 9980",
    "sg:postcode": "44212",
    "sg:province": "OH",
    "sg:tags": [
      "home",
      "builder"
    ],
    "wof:name": "Sweet Briar Homes",
    "wof:placetype": "venue"
  },
  "geometry": {"coordinates":[-81.851825,41.235573],"type":"Point"}
}
