{
  "type": "Feature",
  "properties": {
    "addr:full": "945 S Main St Akron OH 44311",
    "addr:housenumber": "945",
    "addr:postcode": "44311",
    "addr:street": "S Main St",
    "iso:country": "US",
    "sg:address": "945 S Main St",
    "sg:city": "Akron",
    "sg:classifiers": [
      {
        "category": "Home \u0026 Garden",
        "subcategory": "Building Materials",
        "type": "Retail Goods"
      }
    ],
    "sg:phone": "+1 330 253 1013",
    "sg:postcode": "44311",
    "sg:province": "OH",
    "sg:website": "www.building9.com",
    "wof:name": "Building 9",
    "wof:placetype": "venue"
  },
  "geometry": {"coordinates":[-81.527495,41.061669],"type":"Point"}
}
