{
  "type": "Feature",
  "properties": {
    "addr:full": "221 Summit St Celina OH 45822",
    "addr:housenumber": "221",
    "addr:postcode": "45822",
    "addr:street": "Summit St",
    "iso:country": "US",
    "sg:address": "221 Summit St",
    "sg:city": "Celina",
    "sg:classifiers": [
      {
        "category": "Food \u0026 Beverages",
        "subcategory": "Groceries \u0026 Convenience Stores",
        "type": "Retail Goods"
      }
    ],
    "sg:phone": "+1 419 586 4268",
    "sg:postcode": "45822",
    "sg:province": "OH",
    "sg:tags": [
      "grocer"
    ],
    "wof:name": "Chiefs Supermarkets",
    "wof:placetype": "venue"
  },
  "geometry": {"coordinates":[-84.572711,40.560401],"type":"Point"}
}
