{
  "type": "Feature",
  "properties": {
    "addr:full": "4172 W 130th St Cleveland OH 44135",
    "addr:housenumber": "4172",
    "addr:postcode": "44135",
    "addr:street": "W 130Th St",
    "iso:country": "US",
    "sg:address": "4172 W 130th St",
    "sg:city": "Cleveland",
    "sg:classifiers": [
      {
        "category": "Restaurant",
        "type": "Food \u0026 Drink"
      }
    ],
    "sg:phone": "+1 216 941 2552",
    "sg:postcode": "44135",
    "sg:province": "OH",
    "wof:name": "Golden Crown",
    "wof:placetype": "venue"
  },
  "geometry": {"coordinates":[-81.779907,41.441397],"type":"Point"}
}
