{
  "type": "Feature",
  "properties": {
    "addr:full": "415 Illinois Ave Maumee OH 43537",
    "addr:housenumber": "415",
    "addr:postcode": "43537",
    "addr:street": "Illinois Ave",
    "iso:country": "US",
    "sg:address": "415 Illinois Ave",
    "sg:city": "Maumee",
    "sg:classifiers": [
      {
        "category": "Manufacturing",
        "subcategory": "Metals",
        "type": "Manufacturing \u0026 Wholesale Goods"
      }
    ],
    "sg:phone": "+1 419 891 2930",
    "sg:postcode": "43537",
    "sg:province": "OH",
    "sg:tags": [
      "steel"
    ],
    "wof:name": "Andersons Fabrication Div",
    "wof:placetype": "venue"
  },
  "geometry": {"coordinates":[-83.670998,41.56895],"type":"Point"}
}
