{
  "type": "Feature",
  "properties": {
    "addr:full": "5132 Delhi Ave Cincinnati OH 45238",
    "addr:housenumber": "5132",
    "addr:postcode": "45238",
    "addr:street": "Delhi Ave",
    "iso:country": "US",
    "sg:address": "5132 Delhi Ave",
    "sg:city": "Cincinnati",
    "sg:classifiers": [
      {
        "category": "Banks \u0026 Credit Unions",
        "subcategory": "Bank",
        "type": "Services"
      }
    ],
    "sg:phone": "+1 513 347 9870",
    "sg:postcode": "45238",
    "sg:province": "OH",
    "sg:tags": [
      "cashing",
      "check"
    ],
    "wof:name": "Ky Check Exchange",
    "wof:placetype": "venue"
  },
  "geometry": {"coordinates":[-84.614781,39.094678],"type":"Point"}
}
