{
  "type": "Feature",
  "properties": {
    "iso:country":"US",
    "sg:address":"5132 Delhi Ave",
    "sg:city":"Cincinnati",
    "sg:classifiers":[
        {
            "category":"Banks & Credit Unions",
            "subcategory":"Bank",
            "type":"Services"
        }
    ],
    "sg:phone":"+1 513 347 9870",
    "sg:postcode":"45238",
    "sg:province":"OH",
    "sg:tags":[
        "cashing",
        "check"
    ],
    "wof:name":"Ky Check Exchange",
    "wof:placetype":"venue"
},
  "geometry": {"coordinates":[-84.61478099999999,39.094678],"type":"Point"}
}