{
  "type": "Feature",
  "properties": {
    "addr:full": "135 S Main St Springboro OH 45066",
    "addr:housenumber": "135",
    "addr:postcode": "45066",
    "addr:street": "S Main St",
    "iso:country": "US",
    "sg:address": "135 S Main St",
    "sg:city": "Springboro",
    "sg:classifiers": [
      {
        "category": "Shopping",
        "subcategory": "Clothing, Apparel, \u0026 Fashions",
        "type": "Retail Goods"
      }
    ],
    "sg:phone": "+1 937 748 8494",
    "sg:postcode": "45066",
    "sg:province": "OH",
    "sg:tags": [
      "shop",
      "bridal"
    ],
    "wof:name": "Bridal On Main",
    "wof:placetype": "venue"
  },
  "geometry": {"coordinates":[-84.233236,39.554969],"type":"Point"}
}
