{
  "type": "Feature",
  "properties": {
    "iso:country":"US",
    "sg:address":"135 S Main St",
    "sg:city":"Springboro",
    "sg:classifiers":[
        {
            "category":"Shopping",
            "subcategory":"Clothing, Apparel, & Fashions",
            "type":"Retail Goods"
        }
    ],
    "sg:phone":"+1 937 748 8494",
    "sg:postcode":"45066",
    "sg:province":"OH",
    "sg:tags":[
        "shop",
        "bridal"
    ],
    "wof:name":"Bridal On Main",
    "wof:placetype":"venue"
},
  "geometry": {"coordinates":[-84.23323600000001,39.554969],"type":"Point"}
}