{
  "type": "Feature",
  "properties": {
    "iso:country":"US",
    "sg:address":"3187 Western Row Rd",
    "sg:city":"Maineville",
    "sg:classifiers":[
        {
            "category":"Education",
            "subcategory":"Special Training",
            "type":"Public Place"
        }
    ],
    "sg:phone":"+1 513 737 7323",
    "sg:postcode":"45039",
    "sg:province":"OH",
    "sg:tags":[
        "tutoring"
    ],
    "wof:name":"Kumon Center For Kings",
    "wof:placetype":"venue"
},
  "geometry": {"coordinates":[-84.282011,39.336316],"type":"Point"}
}