{
  "type": "Feature",
  "properties": {
    "addr:full":"12925 Woodworth Rd New Springfield OH 44443",
    "addr:housenumber":"12925",
    "addr:postcode":"44443",
    "addr:street":"Woodworth Rd",
    "iso:country":"US",
    "sg:address":"12925 Woodworth Rd",
    "sg:city":"New Springfield",
    "sg:classifiers":[
        {
            "category":"Autos & Motor Vehicles",
            "subcategory":"Automobile Sales",
            "type":"Retail Goods"
        },
        {
            "category":"Autos & Motor Vehicles",
            "subcategory":"Auto Supplies",
            "type":"Retail Goods"
        }
    ],
    "sg:phone":"+1 330 549 5313",
    "sg:postcode":"44443",
    "sg:province":"OH",
    "sg:tags":[
        "antique",
        "parts",
        "classic"
    ],
    "sg:website":"www.snydersantiqueauto.com",
    "wof:name":"Snyder's Antique Auto Parts",
    "wof:placetype":"venue"
},
  "geometry": {"coordinates":[-80.623941,40.929068],"type":"Point"}
}