{
  "type": "Feature",
  "properties": {
    "iso:country":"US",
    "sg:address":"6937 Promway Ave NW",
    "sg:city":"Canton",
    "sg:classifiers":[
        {
            "category":"Building & Trades",
            "subcategory":"Construction",
            "type":"Services"
        }
    ],
    "sg:phone":"+1 330 497 3990",
    "sg:postcode":"44720",
    "sg:province":"OH",
    "sg:tags":[
        "contractor"
    ],
    "wof:name":"AAA Roofing",
    "wof:placetype":"venue"
},
  "geometry": {"coordinates":[-81.429991,40.881826],"type":"Point"}
}