{
  "type": "Feature",
  "properties": {
    "addr:full":"150 Coen Rd Vermilion OH 44089",
    "addr:housenumber":"150",
    "addr:postcode":"44089",
    "addr:street":"Coen Rd",
    "iso:country":"US",
    "sg:address":"150 Coen Rd",
    "sg:city":"Vermilion",
    "sg:classifiers":[
        {
            "category":"Shopping",
            "subcategory":"Florist",
            "type":"Retail Goods"
        }
    ],
    "sg:phone":"+1 440 949 5330",
    "sg:postcode":"44089",
    "sg:province":"OH",
    "wof:name":"Country Tyme Florists",
    "wof:placetype":"venue"
},
  "geometry": {"coordinates":[-82.391076,41.415914],"type":"Point"}
}