{
  "type": "Feature",
  "properties": {
    "addr:full": "1437 Crown St Zanesville OH 43701",
    "addr:housenumber": "1437",
    "addr:postcode": "43701",
    "addr:street": "Crown St",
    "iso:country": "US",
    "sg:address": "1437 Crown St",
    "sg:city": "Zanesville",
    "sg:classifiers": [
      {
        "category": "Autos \u0026 Motor Vehicles",
        "subcategory": "Automobile Sales",
        "type": "Retail Goods"
      }
    ],
    "sg:phone": "+1 740 454 2277",
    "sg:postcode": "43701",
    "sg:province": "OH",
    "sg:tags": [
      "used"
    ],
    "wof:name": "Crown Motors",
    "wof:placetype": "venue"
  },
  "geometry": {"coordinates":[-82.024847,39.939139],"type":"Point"}
}
