{
  "type": "Feature",
  "properties": {
    "iso:country":"US",
    "sg:address":"1437 Crown St",
    "sg:city":"Zanesville",
    "sg:classifiers":[
        {
            "category":"Autos & Motor Vehicles",
            "subcategory":"Automobile Sales",
            "type":"Retail Goods"
        }
    ],
    "sg:phone":"+1 740 454 2277",
    "sg:postcode":"43701",
    "sg:province":"OH",
    "sg:tags":[
        "used"
    ],
    "wof:name":"Crown Motors",
    "wof:placetype":"venue"
},
  "geometry": {"coordinates":[-82.02484699999999,39.939139],"type":"Point"}
}