{
  "type": "Feature",
  "properties": {
    "addr:full": "1 N Hawkins Ave Akron OH 44313",
    "addr:housenumber": "1",
    "addr:postcode": "44313",
    "addr:street": "N Hawkins Ave",
    "iso:country": "US",
    "sg:address": "1 N Hawkins Ave",
    "sg:city": "Akron",
    "sg:classifiers": [
      {
        "category": "Restaurant",
        "type": "Food \u0026 Drink"
      }
    ],
    "sg:phone": "+1 330 869 5571",
    "sg:postcode": "44313",
    "sg:province": "OH",
    "sg:tags": [
      "shop",
      "coffee"
    ],
    "wof:name": "Caribou Coffee Store",
    "wof:placetype": "venue"
  },
  "geometry": {"coordinates":[-81.569225,41.110459],"type":"Point"}
}
