{
  "type": "Feature",
  "properties": {
    "iso:country":"US",
    "sg:address":"2634 W State St",
    "sg:city":"Alliance",
    "sg:classifiers":[
        {
            "category":"Utilities",
            "subcategory":"Mobile Phone",
            "type":"Services"
        },
        {
            "category":"Shopping",
            "type":"Retail Goods"
        }
    ],
    "sg:phone":"+1 330 823 0920",
    "sg:postcode":"44601",
    "sg:province":"OH",
    "sg:tags":[
        "cellular",
        "telephone",
        "merchandise"
    ],
    "wof:name":"Alltel",
    "wof:placetype":"venue"
},
  "geometry": {"coordinates":[-81.158576,40.901956],"type":"Point"}
}