{
  "type": "Feature",
  "properties": {
    "addr:full": "507 N Garland Ave Youngstown OH 44506",
    "addr:housenumber": "507",
    "addr:postcode": "44506",
    "addr:street": "N Garland Ave",
    "iso:country": "US",
    "sg:address": "507 N Garland Ave",
    "sg:city": "Youngstown",
    "sg:classifiers": [
      {
        "category": "Manufacturing",
        "subcategory": "Tools \u0026 Machinery",
        "type": "Manufacturing \u0026 Wholesale Goods"
      }
    ],
    "sg:phone": "+1 330 743 4905",
    "sg:postcode": "44506",
    "sg:province": "OH",
    "wof:name": "Blattman Bros Tool \u0026 Cutter",
    "wof:placetype": "venue"
  },
  "geometry": {"coordinates":[-80.628292,41.104709],"type":"Point"}
}
