{
  "type": "Feature",
  "properties": {
    "iso:country":"US",
    "sg:address":"507 N Garland Ave",
    "sg:city":"Youngstown",
    "sg:classifiers":[
        {
            "category":"Manufacturing",
            "subcategory":"Tools & Machinery",
            "type":"Manufacturing & Wholesale Goods"
        }
    ],
    "sg:phone":"+1 330 743 4905",
    "sg:postcode":"44506",
    "sg:province":"OH",
    "wof:name":"Blattman Bros Tool & Cutter",
    "wof:placetype":"venue"
},
  "geometry": {"coordinates":[-80.628292,41.104709],"type":"Point"}
}