{
  "type": "Feature",
  "properties": {
    "iso:country":"US",
    "sg:address":"109 S Union St",
    "sg:city":"Bethel",
    "sg:classifiers":[
        {
            "category":"Retail",
            "subcategory":"Repair Shop",
            "type":"Services"
        }
    ],
    "sg:phone":"+1 513 734 6444",
    "sg:postcode":"45106",
    "sg:province":"OH",
    "sg:tags":[
        "lighting",
        "fixture"
    ],
    "wof:name":"National Maintenance",
    "wof:placetype":"venue"
},
  "geometry": {"coordinates":[-84.079897,38.963019],"type":"Point"}
}