{
  "type": "Feature",
  "properties": {
    "iso:country":"US",
    "sg:address":"9748 Montgomery Rd",
    "sg:city":"Cincinnati",
    "sg:classifiers":[
        {
            "category":"Wholesale",
            "subcategory":"Durable Goods & Equipment",
            "type":"Manufacturing & Wholesale Goods"
        }
    ],
    "sg:phone":"+1 513 985 9003",
    "sg:postcode":"45242",
    "sg:province":"OH",
    "sg:tags":[
        "antique",
        "door",
        "fixture",
        "lighting",
        "retail",
        "whole"
    ],
    "wof:name":"Wooden Nickel Antiques Inc",
    "wof:placetype":"venue"
},
  "geometry": {"coordinates":[-84.351287,39.234048],"type":"Point"}
}