{
  "type": "Feature",
  "properties": {
    "addr:full": "9748 Montgomery Rd Cincinnati OH 45242",
    "addr:housenumber": "9748",
    "addr:postcode": "45242",
    "addr:street": "Montgomery Rd",
    "iso:country": "US",
    "sg:address": "9748 Montgomery Rd",
    "sg:city": "Cincinnati",
    "sg:classifiers": [
      {
        "category": "Wholesale",
        "subcategory": "Durable Goods \u0026 Equipment",
        "type": "Manufacturing \u0026 Wholesale Goods"
      }
    ],
    "sg:phone": "+1 513 985 9003",
    "sg:postcode": "45242",
    "sg:province": "OH",
    "sg:tags": [
      "antique",
      "door",
      "fixture",
      "lighting",
      "retail",
      "whole"
    ],
    "wof:name": "Wooden Nickel Antiques Inc",
    "wof:placetype": "venue"
  },
  "geometry": {"coordinates":[-84.351287,39.234048],"type":"Point"}
}
