{
  "type": "Feature",
  "properties": {
    "addr:full":"7535 Yankee St Dayton OH 45459",
    "addr:housenumber":"7535",
    "addr:postcode":"45459",
    "addr:street":"Yankee St",
    "iso:country":"US",
    "sg:address":"7535 Yankee St",
    "sg:city":"Dayton",
    "sg:classifiers":[
        {
            "category":"Building & Trades",
            "subcategory":"Construction",
            "type":"Services"
        }
    ],
    "sg:phone":"+1 937 433 7019",
    "sg:postcode":"45459",
    "sg:province":"OH",
    "sg:tags":[
        "painter"
    ],
    "wof:name":"George's Painting Contractor",
    "wof:placetype":"venue"
},
  "geometry": {"coordinates":[-84.19971200000001,39.638164],"type":"Point"}
}