{
  "type": "Feature",
  "properties": {
    "iso:country":"US",
    "sg:address":"36 N Brookwood Way",
    "sg:city":"Mansfield",
    "sg:classifiers":[
        {
            "category":"Retail",
            "subcategory":"Laundry & Dry Cleaning",
            "type":"Services"
        }
    ],
    "sg:phone":"+1 419 529 8000",
    "sg:postcode":"44906",
    "sg:province":"OH",
    "sg:tags":[
        "cleaners"
    ],
    "wof:name":"Kimmel Corp",
    "wof:placetype":"venue"
},
  "geometry": {"coordinates":[-82.56364000000001,40.760847],"type":"Point"}
}