{
  "type": "Feature",
  "properties": {
    "addr:full": "36 N Brookwood Way Mansfield OH 44906",
    "addr:housenumber": "36",
    "addr:postcode": "44906",
    "addr:street": "N Brookwood Way",
    "iso:country": "US",
    "sg:address": "36 N Brookwood Way",
    "sg:city": "Mansfield",
    "sg:classifiers": [
      {
        "category": "Retail",
        "subcategory": "Laundry \u0026 Dry Cleaning",
        "type": "Services"
      }
    ],
    "sg:phone": "+1 419 529 8000",
    "sg:postcode": "44906",
    "sg:province": "OH",
    "sg:tags": [
      "cleaners"
    ],
    "wof:name": "Kimmel Corp",
    "wof:placetype": "venue"
  },
  "geometry": {"coordinates":[-82.56364,40.760847],"type":"Point"}
}
