{
  "type": "Feature",
  "properties": {
    "iso:country":"US",
    "sg:address":"30 Long St",
    "sg:city":"Ashville",
    "sg:classifiers":[
        {
            "category":"Personal",
            "subcategory":"Beauty Salon",
            "type":"Services"
        }
    ],
    "sg:phone":"+1 740 983 6741",
    "sg:postcode":"43103",
    "sg:province":"OH",
    "sg:tags":[
        "manicuring"
    ],
    "wof:name":"Modern Design Nail Gallery",
    "wof:placetype":"venue"
},
  "geometry": {"coordinates":[-82.953523,39.713378],"type":"Point"}
}