{
  "type": "Feature",
  "properties": {
    "iso:country":"US",
    "sg:address":"1327 Pearl Rd",
    "sg:city":"Brunswick",
    "sg:classifiers":[
        {
            "category":"Professional",
            "subcategory":"Lawyer & Legal Services",
            "type":"Services"
        }
    ],
    "sg:phone":"+1 330 225 1234",
    "sg:postcode":"44212",
    "sg:province":"OH",
    "sg:tags":[
        "attorney"
    ],
    "wof:name":"Ray Jones",
    "wof:placetype":"venue"
},
  "geometry": {"coordinates":[-81.841255,41.23919],"type":"Point"}
}