{
  "type": "Feature",
  "properties": {
    "addr:full": "478 S Church St Bowling Green OH 43402",
    "addr:housenumber": "478",
    "addr:postcode": "43402",
    "addr:street": "S Church St",
    "iso:country": "US",
    "sg:address": "478 S Church St",
    "sg:city": "Bowling Green",
    "sg:classifiers": [
      {
        "category": "Restaurant",
        "type": "Food \u0026 Drink"
      }
    ],
    "sg:phone": "+1 419 352 9900",
    "sg:postcode": "43402",
    "sg:province": "OH",
    "sg:tags": [
      "parlor",
      "ice",
      "cream"
    ],
    "wof:name": "Marble Slab Creamery",
    "wof:placetype": "venue"
  },
  "geometry": {"coordinates":[-83.652146,41.367212],"type":"Point"}
}
