{
  "type": "Feature",
  "properties": {
    "addr:full":"5108 Wadsworth Rd Dayton OH 45414",
    "addr:housenumber":"5108",
    "addr:postcode":"45414",
    "addr:street":"Wadsworth Rd",
    "iso:country":"US",
    "sg:address":"5108 Wadsworth Rd",
    "sg:city":"Dayton",
    "sg:classifiers":[
        {
            "category":"Retail",
            "subcategory":"Auto Repair",
            "type":"Services"
        }
    ],
    "sg:phone":"+1 937 278 4403",
    "sg:postcode":"45414",
    "sg:province":"OH",
    "sg:tags":[
        "body",
        "automobile",
        "painting"
    ],
    "wof:name":"C & D Collision Ctr Inc",
    "wof:placetype":"venue"
},
  "geometry": {"coordinates":[-84.18709200000001,39.821286],"type":"Point"}
}