{
  "type": "Feature",
  "properties": {
    "addr:full": "4303 Olentangy River Rd Columbus OH 43214",
    "addr:housenumber": "4303",
    "addr:postcode": "43214",
    "addr:street": "Olentangy River Rd",
    "iso:country": "US",
    "sg:address": "4303 Olentangy River Rd",
    "sg:city": "Columbus",
    "sg:classifiers": [
      {
        "category": "Building \u0026 Trades",
        "subcategory": "Construction",
        "type": "Services"
      }
    ],
    "sg:phone": "+1 614 459 6360",
    "sg:postcode": "43214",
    "sg:province": "OH",
    "sg:tags": [
      "house"
    ],
    "wof:name": "Jim Klinksick Properties",
    "wof:placetype": "venue"
  },
  "geometry": {"coordinates":[-83.033978,40.049239],"type":"Point"}
}
