{
  "type": "Feature",
  "properties": {
    "addr:full": "7654 Co Rd 223 Findlay OH 45840",
    "addr:housenumber": "7654",
    "addr:postcode": "45840",
    "addr:street": "Co Rd 223",
    "iso:country": "US",
    "sg:address": "7654 Co Rd 223",
    "sg:city": "Findlay",
    "sg:classifiers": [
      {
        "category": "Wholesale",
        "subcategory": "Scrap",
        "type": "Manufacturing \u0026 Wholesale Goods"
      }
    ],
    "sg:phone": "+1 419 427 1110",
    "sg:postcode": "45840",
    "sg:province": "OH",
    "sg:tags": [
      "material"
    ],
    "wof:name": "Flag City Brokers",
    "wof:placetype": "venue"
  },
  "geometry": {"coordinates":[-83.677312,41.056512],"type":"Point"}
}
