{
  "type": "Feature",
  "properties": {
    "addr:full":"2610 Lance Dr Dayton OH 45409",
    "addr:housenumber":"2610",
    "addr:postcode":"45409",
    "addr:street":"Lance Dr",
    "iso:country":"US",
    "sg:address":"2610 Lance Dr",
    "sg:city":"Dayton",
    "sg:classifiers":[
        {
            "category":"Wholesale",
            "subcategory":"Construction Materials",
            "type":"Manufacturing & Wholesale Goods"
        },
        {
            "category":"Professional",
            "subcategory":"Management & Consulting",
            "type":"Services"
        }
    ],
    "sg:phone":"+1 937 299 2053",
    "sg:postcode":"45409",
    "sg:province":"OH",
    "sg:tags":[
        "building",
        "administrative"
    ],
    "wof:name":"Select Building Supplies",
    "wof:placetype":"venue"
},
  "geometry": {"coordinates":[-84.200517,39.715711],"type":"Point"}
}