{
  "type": "Feature",
  "properties": {
    "addr:full":"20 Lakota Ave Akron OH 44319",
    "addr:housenumber":"20",
    "addr:postcode":"44319",
    "addr:street":"Lakota Ave",
    "iso:country":"US",
    "sg:address":"20 Lakota Ave",
    "sg:city":"Akron",
    "sg:classifiers":[
        {
            "category":"Wholesale",
            "subcategory":"Vending Machines",
            "type":"Manufacturing & Wholesale Goods"
        }
    ],
    "sg:phone":"+1 330 645 6080",
    "sg:postcode":"44319",
    "sg:province":"OH",
    "sg:tags":[
        "operates"
    ],
    "wof:name":"Adcor Vending Services Inc",
    "wof:placetype":"venue"
},
  "geometry": {"coordinates":[-81.526248,41.002531],"type":"Point"}
}