{
  "type": "Feature",
  "properties": {
    "iso:country":"US",
    "sg:address":"15413 Steinway Blvd",
    "sg:city":"Cleveland",
    "sg:classifiers":[
        {
            "category":"Professional",
            "subcategory":"Art Services",
            "type":"Services"
        }
    ],
    "sg:phone":"+1 216 518 0384",
    "sg:postcode":"44137",
    "sg:province":"OH",
    "sg:tags":[
        "graphic",
        "designer"
    ],
    "wof:name":"Toasterart",
    "wof:placetype":"venue"
},
  "geometry": {"coordinates":[-81.571816,41.395516],"type":"Point"}
}