{
  "type": "Feature",
  "properties": {
    "addr:full":"7430 W Central Ave Toledo OH 43617",
    "addr:housenumber":"7430",
    "addr:postcode":"43617",
    "addr:street":"W Central Ave",
    "iso:country":"US",
    "sg:address":"7430 W Central Ave",
    "sg:city":"Toledo",
    "sg:classifiers":[
        {
            "category":"Restaurant",
            "type":"Food & Drink"
        }
    ],
    "sg:phone":"+1 419 842 1013",
    "sg:postcode":"43617",
    "sg:province":"OH",
    "wof:name":"Taruman Sushi Takeout",
    "wof:placetype":"venue"
},
  "geometry": {"coordinates":[-83.72174699999999,41.67394],"type":"Point"}
}