{
  "type": "Feature",
  "properties": {
    "iso:country":"US",
    "sg:address":"6845 Commerce Court Dr",
    "sg:city":"Blacklick",
    "sg:classifiers":[
        {
            "category":"Home & Garden",
            "subcategory":"Household Appliances",
            "type":"Retail Goods"
        }
    ],
    "sg:phone":"+1 614 751 4525",
    "sg:postcode":"43004",
    "sg:province":"OH",
    "wof:name":"Builder Appliance Supply",
    "wof:placetype":"venue"
},
  "geometry": {"coordinates":[-82.817902,39.989074],"type":"Point"}
}