{
  "type": "Feature",
  "properties": {
    "addr:full": "6845 Commerce Court Dr Blacklick OH 43004",
    "addr:housenumber": "6845",
    "addr:postcode": "43004",
    "addr:street": "Commerce Court Dr",
    "iso:country": "US",
    "sg:address": "6845 Commerce Court Dr",
    "sg:city": "Blacklick",
    "sg:classifiers": [
      {
        "category": "Home \u0026 Garden",
        "subcategory": "Household Appliances",
        "type": "Retail Goods"
      }
    ],
    "sg:phone": "+1 614 751 4525",
    "sg:postcode": "43004",
    "sg:province": "OH",
    "wof:name": "Builder Appliance Supply",
    "wof:placetype": "venue"
  },
  "geometry": {"coordinates":[-82.817902,39.989074],"type":"Point"}
}
