{
  "type": "Feature",
  "properties": {
    "iso:country":"US",
    "sg:address":"406 E Vine St",
    "sg:city":"Mount Vernon",
    "sg:classifiers":[
        {
            "category":"Building & Trades",
            "subcategory":"Construction",
            "type":"Services"
        }
    ],
    "sg:phone":"+1 740 392 9996",
    "sg:postcode":"43050",
    "sg:province":"OH",
    "sg:tags":[
        "hanging",
        "contractor"
    ],
    "wof:name":"Mlw Decorative Painting",
    "wof:placetype":"venue"
},
  "geometry": {"coordinates":[-82.47900300000001,40.392247],"type":"Point"}
}