{
  "type": "Feature",
  "properties": {
    "addr:full": "406 E Vine St Mount Vernon OH 43050",
    "addr:housenumber": "406",
    "addr:postcode": "43050",
    "addr:street": "E Vine St",
    "iso:country": "US",
    "sg:address": "406 E Vine St",
    "sg:city": "Mount Vernon",
    "sg:classifiers": [
      {
        "category": "Building \u0026 Trades",
        "subcategory": "Construction",
        "type": "Services"
      }
    ],
    "sg:phone": "+1 740 392 9996",
    "sg:postcode": "43050",
    "sg:province": "OH",
    "sg:tags": [
      "hanging",
      "contractor"
    ],
    "wof:name": "Mlw Decorative Painting",
    "wof:placetype": "venue"
  },
  "geometry": {"coordinates":[-82.479003,40.392247],"type":"Point"}
}
