{
  "type": "Feature",
  "properties": {
    "iso:country":"US",
    "sg:address":"8539 Co Rd 14",
    "sg:city":"Dunkirk",
    "sg:phone":"+1 419 759 3556",
    "sg:postcode":"45836",
    "sg:province":"OH",
    "sg:tags":[
        "farm",
        "corn",
        "wheat",
        "soybean"
    ],
    "wof:name":"Allen Boehm",
    "wof:placetype":"venue"
},
  "geometry": {"coordinates":[-83.719711,40.811028],"type":"Point"}
}