{
  "type": "Feature",
  "properties": {
    "addr:full":"6888 N Beach Rd Hillsboro OH 45133",
    "addr:housenumber":"6888",
    "addr:postcode":"45133",
    "addr:street":"N Beach Rd",
    "iso:country":"US",
    "sg:address":"6888 N Beach Rd",
    "sg:city":"Hillsboro",
    "sg:classifiers":[
        {
            "category":"Shopping",
            "type":"Retail Goods"
        }
    ],
    "sg:phone":"+1 937 393 4082",
    "sg:postcode":"45133",
    "sg:province":"OH",
    "sg:tags":[
        "equipment",
        "hospital",
        "medical",
        "supply"
    ],
    "wof:name":"Balloon & Stuff",
    "wof:placetype":"venue"
},
  "geometry": {"coordinates":[-83.480716,39.202058],"type":"Point"}
}