{
  "type": "Feature",
  "properties": {
    "addr:full": "110 W Oak St Wauseon OH 43567",
    "addr:housenumber": "110",
    "addr:postcode": "43567",
    "addr:street": "W Oak St",
    "iso:country": "US",
    "sg:address": "110 W Oak St",
    "sg:city": "Wauseon",
    "sg:classifiers": [
      {
        "category": "Restaurant",
        "type": "Food \u0026 Drink"
      }
    ],
    "sg:phone": "+1 419 335 0865",
    "sg:postcode": "43567",
    "sg:province": "OH",
    "wof:name": "Wing Shack",
    "wof:placetype": "venue"
  },
  "geometry": {"coordinates":[-84.142059,41.550725],"type":"Point"}
}
