{
  "type": "Feature",
  "properties": {
    "iso:country":"US",
    "sg:address":"110 W Oak St",
    "sg:city":"Wauseon",
    "sg:classifiers":[
        {
            "category":"Restaurant",
            "type":"Food & Drink"
        }
    ],
    "sg:phone":"+1 419 335 0865",
    "sg:postcode":"43567",
    "sg:province":"OH",
    "wof:name":"Wing Shack",
    "wof:placetype":"venue"
},
  "geometry": {"coordinates":[-84.142059,41.550725],"type":"Point"}
}