{
  "type": "Feature",
  "properties": {
    "addr:full": "PO Box 30085 Cincinnati OH 45230",
    "addr:housenumber": "po box 30085",
    "addr:postcode": "45230",
    "iso:country": "US",
    "sg:address": "PO Box 30085",
    "sg:city": "Cincinnati",
    "sg:classifiers": [
      {
        "category": "Professional",
        "subcategory": "Research",
        "type": "Services"
      }
    ],
    "sg:phone": "+1 513 225 8765",
    "sg:postcode": "45230",
    "sg:province": "OH",
    "sg:tags": [
      "biotech",
      "cleantech",
      "alternative-energy",
      "bacteria",
      "electricity",
      "hydrogen-gas",
      "water"
    ],
    "sg:website": "http://PilusEnergy.com",
    "wof:name": "Pilus Energy",
    "wof:placetype": "venue"
  },
  "geometry": {"coordinates":[-84.37584,39.071262],"type":"Point"}
}
