{
  "type": "Feature",
  "properties": {
    "addr:full": "1500 W 3rd St Cleveland OH 44113",
    "addr:housenumber": "1500",
    "addr:postcode": "44113",
    "addr:street": "W 3Rd St",
    "iso:country": "US",
    "sg:address": "1500 W 3rd St",
    "sg:city": "Cleveland",
    "sg:classifiers": [
      {
        "category": "Insurance",
        "subcategory": "Insurance Agent",
        "type": "Services"
      }
    ],
    "sg:phone": "+1 216 566 9976",
    "sg:postcode": "44113",
    "sg:province": "OH",
    "sg:website": "www.ajg.com",
    "wof:name": "Gallagher Pipino Inc",
    "wof:placetype": "venue"
  },
  "geometry": {"coordinates":[-81.694913,41.496828],"type":"Point"}
}
