{
  "type": "Feature",
  "properties": {
    "addr:full": "565 E Main St Canfield OH 44406",
    "addr:housenumber": "565",
    "addr:postcode": "44406",
    "addr:street": "E Main St",
    "iso:country": "US",
    "sg:address": "565 E Main St",
    "sg:city": "Canfield",
    "sg:classifiers": [
      {
        "category": "Real Estate",
        "subcategory": "Architect",
        "type": "Services"
      }
    ],
    "sg:phone": "+1 330 533 7227",
    "sg:postcode": "44406",
    "sg:province": "OH",
    "wof:name": "Thomas J Keller Architect",
    "wof:placetype": "venue"
  },
  "geometry": {"coordinates":[-80.749242,41.02466],"type":"Point"}
}
