{
  "type": "Feature",
  "properties": {
    "addr:full": "2710 Dayton Ave Columbus OH 43202",
    "addr:housenumber": "2710",
    "addr:postcode": "43202",
    "addr:street": "Dayton Ave",
    "iso:country": "US",
    "sg:address": "2710 Dayton Ave",
    "sg:city": "Columbus",
    "sg:classifiers": [
      {
        "category": "Professional",
        "subcategory": "Management \u0026 Consulting",
        "type": "Services"
      }
    ],
    "sg:phone": "+1 614 261 0433",
    "sg:postcode": "43202",
    "sg:province": "OH",
    "sg:tags": [
      "promotion",
      "sales"
    ],
    "wof:name": "Signature Marketing",
    "wof:placetype": "venue"
  },
  "geometry": {"coordinates":[-83.004253,40.017779],"type":"Point"}
}
