{
  "type": "Feature",
  "properties": {
    "iso:country":"US",
    "sg:address":"2460 Greentree Rd",
    "sg:city":"Lebanon",
    "sg:classifiers":[
        {
            "category":"Local Transit",
            "type":"Transportation"
        },
        {
            "category":"Airport",
            "type":"Transportation"
        }
    ],
    "sg:phone":"+1 513 932 7966",
    "sg:postcode":"45036",
    "sg:province":"OH",
    "sg:tags":[
        "operator"
    ],
    "sg:website":"www.warrencountyairport.com",
    "wof:name":"Warren County Airport Auth",
    "wof:placetype":"venue"
},
  "geometry": {"coordinates":[-84.252221,39.454662],"type":"Point"}
}