{
  "type": "Feature",
  "properties": {
    "iso:country":"US",
    "sg:address":"230 Northland Blvd",
    "sg:city":"Cincinnati",
    "sg:classifiers":[
        {
            "category":"Professional",
            "type":"Services"
        }
    ],
    "sg:phone":"+1 513 253 5623",
    "sg:postcode":"45246",
    "sg:province":"OH",
    "wof:name":"C Phelps Logistics  Inc",
    "wof:placetype":"venue"
},
  "geometry": {"coordinates":[-84.481279,39.282735],"type":"Point"}
}