{
  "type": "Feature",
  "properties": {
    "iso:country":"US",
    "sg:address":"6581 Harrison Ave",
    "sg:city":"Cincinnati",
    "sg:classifiers":[
        {
            "category":"Banks & Credit Unions",
            "subcategory":"Bank",
            "type":"Services"
        }
    ],
    "sg:phone":"+1 513 598 1900",
    "sg:postcode":"45247",
    "sg:province":"OH",
    "sg:tags":[
        "loan",
        "real estate"
    ],
    "wof:name":"Barnaclo Home Loans",
    "wof:placetype":"venue"
},
  "geometry": {"coordinates":[-84.661693,39.19464],"type":"Point"}
}