{
  "type": "Feature",
  "properties": {
    "iso:country":"US",
    "sg:address":"1436 Cincinnati St",
    "sg:city":"Dayton",
    "sg:classifiers":[
        {
            "category":"Wholesale",
            "subcategory":"Electrical",
            "type":"Manufacturing & Wholesale Goods"
        }
    ],
    "sg:phone":"+1 937 224 1537",
    "sg:postcode":"45408",
    "sg:province":"OH",
    "sg:tags":[
        "transmission",
        "equipment",
        "power"
    ],
    "wof:name":"Bearing Distributors Inc",
    "wof:placetype":"venue"
},
  "geometry": {"coordinates":[-84.207387,39.733912],"type":"Point"}
}