{
  "type": "Feature",
  "properties": {
    "addr:full":"5937 Deanmont Pl Dayton OH 45459",
    "addr:postcode":"5937;45459",
    "addr:street":"Deanmont Pl",
    "iso:country":"US",
    "sg:address":"5937 Deanmont Pl",
    "sg:city":"Dayton",
    "sg:classifiers":[
        {
            "category":"Communications",
            "type":"Services"
        }
    ],
    "sg:phone":"+1 937 438 2500",
    "sg:postcode":"45459",
    "sg:province":"OH",
    "wof:name":"Bis Writes Communications",
    "wof:placetype":"venue"
},
  "geometry": {"coordinates":[-84.18022000000001,39.660101],"type":"Point"}
}