{
  "type": "Feature",
  "properties": {
    "iso:country":"US",
    "sg:address":"4713 Mahoning Ave NW",
    "sg:city":"Warren",
    "sg:classifiers":[
        {
            "category":"Restaurant",
            "type":"Food & Drink"
        }
    ],
    "sg:phone":"+1 330 609 5663",
    "sg:postcode":"44483",
    "sg:province":"OH",
    "sg:tags":[
        "parlor",
        "ice",
        "cream"
    ],
    "wof:name":"Katies Korner Champion",
    "wof:placetype":"venue"
},
  "geometry": {"coordinates":[-80.846277,41.285203],"type":"Point"}
}