{
  "type": "Feature",
  "properties": {
    "addr:full": "15115 E US Hwy 224 Findlay OH 45840",
    "addr:housenumber": "15115",
    "addr:postcode": "45840",
    "addr:street": "E Us Hwy 224",
    "iso:country": "US",
    "sg:address": "15115 E US Hwy 224",
    "sg:city": "Findlay",
    "sg:classifiers": [
      {
        "category": "Building \u0026 Trades",
        "subcategory": "Construction",
        "type": "Services"
      }
    ],
    "sg:phone": "+1 419 423 5668",
    "sg:postcode": "45840",
    "sg:province": "OH",
    "sg:tags": [
      "house"
    ],
    "wof:name": "Belisle Construction Inc",
    "wof:placetype": "venue"
  },
  "geometry": {"coordinates":[-83.590518,41.055954],"type":"Point"}
}
