{
  "type": "Feature",
  "properties": {
    "iso:country":"US",
    "sg:address":"155 Northland Dr",
    "sg:city":"Medina",
    "sg:classifiers":[
        {
            "category":"Retail",
            "subcategory":"Auto Repair",
            "type":"Services"
        }
    ],
    "sg:phone":"+1 330 721 9898",
    "sg:postcode":"44256",
    "sg:province":"OH",
    "sg:tags":[
        "repairing",
        "automobile",
        "automotive"
    ],
    "wof:name":"A Plus Automotive Inc",
    "wof:placetype":"venue"
},
  "geometry": {"coordinates":[-81.865109,41.152552],"type":"Point"}
}