{
  "type": "Feature",
  "properties": {
    "addr:full": "1253 Deerfield Ave N Dalton OH 44618",
    "addr:housenumber": "1253",
    "addr:postcode": "44618",
    "addr:street": "Deerfield Ave N",
    "iso:country": "US",
    "sg:address": "1253 Deerfield Ave N",
    "sg:city": "Dalton",
    "sg:classifiers": [
      {
        "category": "Professional",
        "type": "Services"
      }
    ],
    "sg:phone": "+1 330 828 0619",
    "sg:postcode": "44618",
    "sg:province": "OH",
    "wof:name": "Watkins Inc",
    "wof:placetype": "venue"
  },
  "geometry": {"coordinates":[-81.648051,40.804383],"type":"Point"}
}
