{
  "type": "Feature",
  "properties": {
    "addr:full": "53 Price Rd Newark OH 43055",
    "addr:housenumber": "53",
    "addr:postcode": "43055",
    "addr:street": "Price Rd",
    "iso:country": "US",
    "sg:address": "53 Price Rd",
    "sg:city": "Newark",
    "sg:classifiers": [
      {
        "category": "Professional",
        "subcategory": "Advertising",
        "type": "Services"
      }
    ],
    "sg:phone": "+1 740 366 3816",
    "sg:postcode": "43055",
    "sg:province": "OH",
    "sg:tags": [
      "counselor"
    ],
    "wof:name": "A \u0026 D Advertising/Design",
    "wof:placetype": "venue"
  },
  "geometry": {"coordinates":[-82.425617,40.098647],"type":"Point"}
}
