{
  "type": "Feature",
  "properties": {
    "addr:full":"1923 W Dorothy Ln Dayton OH 45409",
    "addr:housenumber":"1923",
    "addr:postcode":"45409",
    "addr:street":"W Dorothy Ln",
    "iso:country":"US",
    "sg:address":"1923 W Dorothy Ln",
    "sg:city":"Dayton",
    "sg:classifiers":[
        {
            "category":"Banks & Credit Unions",
            "subcategory":"Bank",
            "type":"Services"
        }
    ],
    "sg:phone":"+1 937 297 5300",
    "sg:postcode":"45409",
    "sg:province":"OH",
    "wof:name":"Fifth Third Bank",
    "wof:placetype":"venue"
},
  "geometry": {"coordinates":[-84.20838999999999,39.709752],"type":"Point"}
}