{
  "type": "Feature",
  "properties": {
    "addr:full": "390 Seven Pines Dr Pickerington OH 43147",
    "addr:housenumber": "390",
    "addr:postcode": "43147",
    "addr:street": "Seven Pines Dr",
    "iso:country": "US",
    "sg:address": "390 Seven Pines Dr",
    "sg:city": "Pickerington",
    "sg:classifiers": [
      {
        "category": "Professional",
        "subcategory": "Computer Services",
        "type": "Services"
      }
    ],
    "sg:phone": "+1 614 837 7026",
    "sg:postcode": "43147",
    "sg:province": "OH",
    "sg:tags": [
      "home",
      "consulting",
      "page",
      "dev",
      "internet"
    ],
    "wof:name": "Consumer Sense",
    "wof:placetype": "venue"
  },
  "geometry": {"coordinates":[-82.761795,39.886046],"type":"Point"}
}
