{
  "type": "Feature",
  "properties": {
    "addr:full":"133 1st St Powhatan Point OH 43942",
    "addr:housenumber":"133",
    "addr:postcode":"43942",
    "addr:street":"1St St",
    "iso:country":"US",
    "sg:address":"133 1st St",
    "sg:city":"Powhatan Point",
    "sg:classifiers":[
        {
            "category":"Education",
            "subcategory":"Dance Studio",
            "type":"Public Place"
        }
    ],
    "sg:phone":"+1 740 795 5654",
    "sg:postcode":"43942",
    "sg:province":"OH",
    "sg:tags":[
        "instruction",
        "dancing"
    ],
    "wof:name":"All Valley School Of Dance",
    "wof:placetype":"venue"
},
  "geometry": {"coordinates":[-80.80475199999999,39.858442],"type":"Point"}
}