{
  "type": "Feature",
  "properties": {
    "addr:full": "203 W Main St Mc Arthur OH 45651",
    "addr:housenumber": "203",
    "addr:postcode": "45651",
    "addr:street": "W Main St",
    "iso:country": "US",
    "sg:address": "203 W Main St",
    "sg:city": "Mc Arthur",
    "sg:classifiers": [
      {
        "category": "Restaurant",
        "type": "Food \u0026 Drink"
      }
    ],
    "sg:phone": "+1 740 596 9349",
    "sg:postcode": "45651",
    "sg:province": "OH",
    "wof:name": "Mc Clure's Restaurant",
    "wof:placetype": "venue"
  },
  "geometry": {"coordinates":[-82.480898,39.246841],"type":"Point"}
}
