{
  "type": "Feature",
  "properties": {
    "iso:country":"US",
    "sg:address":"203 W Main St",
    "sg:city":"Mc Arthur",
    "sg:classifiers":[
        {
            "category":"Restaurant",
            "type":"Food & Drink"
        }
    ],
    "sg:phone":"+1 740 596 9349",
    "sg:postcode":"45651",
    "sg:province":"OH",
    "wof:name":"Mc Clure's Restaurant",
    "wof:placetype":"venue"
},
  "geometry": {"coordinates":[-82.480898,39.246841],"type":"Point"}
}