{
  "type": "Feature",
  "properties": {
    "addr:full":"3267 E Overlook Rd Cleveland OH 44118",
    "addr:housenumber":"3267",
    "addr:postcode":"44118",
    "addr:street":"E Overlook Rd",
    "iso:country":"US",
    "sg:address":"3267 E Overlook Rd",
    "sg:city":"Cleveland",
    "sg:classifiers":[
        {
            "category":"Building & Trades",
            "subcategory":"Construction",
            "type":"Services"
        }
    ],
    "sg:phone":"+1 216 321 8780",
    "sg:postcode":"44118",
    "sg:province":"OH",
    "sg:tags":[
        "painter"
    ],
    "wof:name":"DKH Painting Inc",
    "wof:placetype":"venue"
},
  "geometry": {"coordinates":[-81.56244700000001,41.506177],"type":"Point"}
}