{
  "type": "Feature",
  "properties": {
    "addr:full": "1394 Johnsville Brookville Rd Brookville OH 45309",
    "addr:housenumber": "1394",
    "addr:postcode": "45309",
    "addr:street": "Johnsville Brookville Rd",
    "iso:country": "US",
    "sg:address": "1394 Johnsville Brookville Rd",
    "sg:city": "Brookville",
    "sg:classifiers": [
      {
        "category": "Retail",
        "subcategory": "Repair Shop",
        "type": "Services"
      }
    ],
    "sg:phone": "+1 937 687 2379",
    "sg:postcode": "45309",
    "sg:province": "OH",
    "sg:tags": [
      "television",
      "radio"
    ],
    "wof:name": "Dick Berry TV Svc",
    "wof:placetype": "venue"
  },
  "geometry": {"coordinates":[-84.423046,39.76376],"type":"Point"}
}
