{
  "type": "Feature",
  "properties": {
    "iso:country":"US",
    "sg:address":"660 S 7th St",
    "sg:city":"Greenfield",
    "sg:classifiers":[
        {
            "category":"Home & Garden",
            "subcategory":"Furniture",
            "type":"Retail Goods"
        }
    ],
    "sg:phone":"+1 937 981 1326",
    "sg:postcode":"45123",
    "sg:province":"OH",
    "wof:name":"Bright Furniture",
    "wof:placetype":"venue"
},
  "geometry": {"coordinates":[-83.39018299999999,39.345193],"type":"Point"}
}