{
  "type": "Feature",
  "properties": {
    "addr:full": "4240 Lisa Dr Tipp City OH 45371",
    "addr:housenumber": "4240",
    "addr:postcode": "45371",
    "addr:street": "Lisa Dr",
    "iso:country": "US",
    "sg:address": "4240 Lisa Dr",
    "sg:city": "Tipp City",
    "sg:classifiers": [
      {
        "category": "Retail",
        "subcategory": "Auto Repair",
        "type": "Services"
      }
    ],
    "sg:phone": "+1 937 669 3434",
    "sg:postcode": "45371",
    "sg:province": "OH",
    "sg:tags": [
      "body",
      "mfg",
      "automobile",
      "sign",
      "design",
      "customizing"
    ],
    "wof:name": "Custom Gallery",
    "wof:placetype": "venue"
  },
  "geometry": {"coordinates":[-84.138787,39.888648],"type":"Point"}
}
