{
  "type": "Feature",
  "properties": {
    "iso:country":"US",
    "sg:address":"4240 Lisa Dr",
    "sg:city":"Tipp City",
    "sg:classifiers":[
        {
            "category":"Retail",
            "subcategory":"Auto Repair",
            "type":"Services"
        }
    ],
    "sg:phone":"+1 937 669 3434",
    "sg:postcode":"45371",
    "sg:province":"OH",
    "sg:tags":[
        "body",
        "mfg",
        "automobile",
        "sign",
        "design",
        "customizing"
    ],
    "wof:name":"Custom Gallery",
    "wof:placetype":"venue"
},
  "geometry": {"coordinates":[-84.13878699999999,39.888648],"type":"Point"}
}