{
  "type": "Feature",
  "properties": {
    "addr:full": "6263 Jessica Ct Middletown OH 45044",
    "addr:housenumber": "6263",
    "addr:postcode": "45044",
    "addr:street": "Jessica Ct",
    "iso:country": "US",
    "sg:address": "6263 Jessica Ct",
    "sg:city": "Middletown",
    "sg:classifiers": [
      {
        "category": "Professional",
        "subcategory": "Management \u0026 Consulting",
        "type": "Services"
      }
    ],
    "sg:phone": "+1 513 755 6157",
    "sg:postcode": "45044",
    "sg:province": "OH",
    "sg:tags": [
      "marketing",
      "program"
    ],
    "wof:name": "Liberty Marketing Of Ohio LLC",
    "wof:placetype": "venue"
  },
  "geometry": {"coordinates":[-84.390479,39.394245],"type":"Point"}
}
