{
  "type": "Feature",
  "properties": {
    "addr:full":"400 Ascot Rd SE Carrollton OH 44615",
    "addr:housenumber":"400",
    "addr:postcode":"44615",
    "addr:street":"Ascot Rd Se",
    "iso:country":"US",
    "sg:address":"400 Ascot Rd SE",
    "sg:city":"Carrollton",
    "sg:classifiers":[
        {
            "category":"Farming",
            "subcategory":"Farm",
            "type":"Manufacturing & Wholesale Goods"
        }
    ],
    "sg:phone":"+1 330 627 4948",
    "sg:postcode":"44615",
    "sg:province":"OH",
    "sg:tags":[
        "wheat",
        "corn",
        "cash",
        "crop",
        "general",
        "grain"
    ],
    "wof:name":"Ray C Kugler & Co",
    "wof:placetype":"venue"
},
  "geometry": {"coordinates":[-81.078191,40.560196],"type":"Point"}
}