{
  "type": "Feature",
  "properties": {
    "iso:country":"US",
    "sg:address":"13990 Pleasant Ridge Dr",
    "sg:city":"Marysville",
    "sg:classifiers":[
        {
            "category":"Freight",
            "type":"Transportation"
        }
    ],
    "sg:phone":"+1 937 642 1133",
    "sg:postcode":"43040",
    "sg:province":"OH",
    "sg:tags":[
        "trucking"
    ],
    "wof:name":"RNA Trucking",
    "wof:placetype":"venue"
},
  "geometry": {"coordinates":[-83.30888,40.230874],"type":"Point"}
}