{
  "type": "Feature",
  "properties": {
    "addr:full": "13990 Pleasant Ridge Dr Marysville OH 43040",
    "addr:housenumber": "13990",
    "addr:postcode": "43040",
    "addr:street": "Pleasant Ridge Dr",
    "iso:country": "US",
    "sg:address": "13990 Pleasant Ridge Dr",
    "sg:city": "Marysville",
    "sg:classifiers": [
      {
        "category": "Freight",
        "type": "Transportation"
      }
    ],
    "sg:phone": "+1 937 642 1133",
    "sg:postcode": "43040",
    "sg:province": "OH",
    "sg:tags": [
      "trucking"
    ],
    "wof:name": "RNA Trucking",
    "wof:placetype": "venue"
  },
  "geometry": {"coordinates":[-83.30888,40.230874],"type":"Point"}
}
