{
  "type": "Feature",
  "properties": {
    "addr:full":"10013 Loches Rd St Louisville OH 43071",
    "addr:postcode":"10013;43071",
    "addr:street":"Loches Rd St",
    "iso:country":"US",
    "sg:address":"10013 Loches Rd",
    "sg:city":"St Louisville",
    "sg:classifiers":[
        {
            "category":"Building & Trades",
            "subcategory":"Landscaping Services",
            "type":"Services"
        }
    ],
    "sg:phone":"+1 740 745 3453",
    "sg:postcode":"43071",
    "sg:province":"OH",
    "sg:tags":[
        "landscape",
        "contractor"
    ],
    "wof:name":"Mid Ohio Pines",
    "wof:placetype":"venue"
},
  "geometry": {"coordinates":[-82.35701400000001,40.16264],"type":"Point"}
}