{
  "type": "Feature",
  "properties": {
    "iso:country":"US",
    "sg:address":"2194 E Waterloo Rd",
    "sg:city":"Akron",
    "sg:classifiers":[
        {
            "category":"Autos & Motor Vehicles",
            "subcategory":"Automobile Sales",
            "type":"Retail Goods"
        }
    ],
    "sg:phone":"+1 330 794 4555",
    "sg:postcode":"44312",
    "sg:province":"OH",
    "sg:tags":[
        "car",
        "dealer"
    ],
    "wof:name":"224 Auto Sales",
    "wof:placetype":"venue"
},
  "geometry": {"coordinates":[-81.453093,41.030197],"type":"Point"}
}