{
  "type": "Feature",
  "properties": {
    "addr:full":"1307 Wertz Ave SW Canton OH 44710",
    "addr:housenumber":"1307",
    "addr:postcode":"44710",
    "addr:street":"Wertz Ave Sw",
    "iso:country":"US",
    "sg:address":"1307 Wertz Ave SW",
    "sg:city":"Canton",
    "sg:classifiers":[
        {
            "category":"Professional",
            "type":"Services"
        }
    ],
    "sg:phone":"+1 330 456 8470",
    "sg:postcode":"44710",
    "sg:province":"OH",
    "wof:name":"Weil Transcription",
    "wof:placetype":"venue"
},
  "geometry": {"coordinates":[-81.408207,40.787743],"type":"Point"}
}