{
  "type": "Feature",
  "properties": {
    "addr:full": "21 E State St Columbus OH 43215",
    "addr:housenumber": "21",
    "addr:postcode": "43215",
    "addr:street": "E State St",
    "iso:country": "US",
    "sg:address": "21 E State St",
    "sg:city": "Columbus",
    "sg:classifiers": [
      {
        "category": "Professional",
        "subcategory": "Lawyer \u0026 Legal Services",
        "type": "Services"
      }
    ],
    "sg:phone": "+1 614 228 1144",
    "sg:postcode": "43215",
    "sg:province": "OH",
    "sg:tags": [
      "attorney"
    ],
    "wof:name": "Philip M Collins \u0026 Associates",
    "wof:placetype": "venue"
  },
  "geometry": {"coordinates":[-82.999859,39.9601],"type":"Point"}
}
