{
  "type": "Feature",
  "properties": {
    "addr:full": "3514 Patterson Rd Bethel OH 45106",
    "addr:housenumber": "3514",
    "addr:postcode": "45106",
    "addr:street": "Patterson Rd",
    "iso:country": "US",
    "sg:address": "3514 Patterson Rd",
    "sg:city": "Bethel",
    "sg:classifiers": [
      {
        "category": "Home \u0026 Garden",
        "subcategory": "Garden Supply",
        "type": "Retail Goods"
      }
    ],
    "sg:phone": "+1 330 686 7466",
    "sg:postcode": "45106",
    "sg:province": "OH",
    "sg:tags": [
      "nurseryman"
    ],
    "wof:name": "Green Valley Nursery",
    "wof:placetype": "venue"
  },
  "geometry": {"coordinates":[-84.055093,38.942416],"type":"Point"}
}
