{
  "type": "Feature",
  "properties": {
    "addr:full": "6235 Monroe St Sylvania OH 43560",
    "addr:housenumber": "6235",
    "addr:postcode": "43560",
    "addr:street": "Monroe St",
    "iso:country": "US",
    "sg:address": "6235 Monroe St",
    "sg:city": "Sylvania",
    "sg:classifiers": [
      {
        "category": "Banks \u0026 Credit Unions",
        "subcategory": "Bank",
        "type": "Services"
      }
    ],
    "sg:phone": "+1 419 885 1217",
    "sg:postcode": "43560",
    "sg:province": "OH",
    "wof:name": "Charter One Bank",
    "wof:placetype": "venue"
  },
  "geometry": {"coordinates":[-83.694411,41.715259],"type":"Point"}
}
