{
  "type": "Feature",
  "properties": {
    "addr:full": "6537 E Livingston Ave Reynoldsburg OH 43068",
    "addr:housenumber": "6537",
    "addr:postcode": "43068",
    "addr:street": "E Livingston Ave",
    "iso:country": "US",
    "sg:address": "6537 E Livingston Ave",
    "sg:city": "Reynoldsburg",
    "sg:classifiers": [
      {
        "category": "Personal",
        "subcategory": "Beauty Salon",
        "type": "Services"
      }
    ],
    "sg:phone": "+1 614 868 0091",
    "sg:postcode": "43068",
    "sg:province": "OH",
    "wof:name": "Artistic Ebony Hair \u0026 Nail Std",
    "wof:placetype": "venue"
  },
  "geometry": {"coordinates":[-82.819588,39.943218],"type":"Point"}
}
