{
  "type": "Feature",
  "properties": {
    "addr:full": "4971 Arlington Centre Blvd Columbus OH 43220",
    "addr:housenumber": "4971",
    "addr:postcode": "43220",
    "addr:street": "Arlington Centre Blvd",
    "iso:country": "US",
    "sg:address": "4971 Arlington Centre Blvd",
    "sg:city": "Columbus",
    "sg:classifiers": [
      {
        "category": "Shopping",
        "type": "Retail Goods"
      }
    ],
    "sg:phone": "+1 614 457 4222",
    "sg:postcode": "43220",
    "sg:province": "OH",
    "sg:tags": [
      "cosmetic",
      "perfume"
    ],
    "wof:name": "Skin Aesthetics",
    "wof:placetype": "venue"
  },
  "geometry": {"coordinates":[-83.079107,40.058409],"type":"Point"}
}
