{
  "type": "Feature",
  "properties": {
    "addr:full": "2255 E Sharon Rd Cincinnati OH 45241",
    "addr:housenumber": "2255",
    "addr:postcode": "45241",
    "addr:street": "E Sharon Rd",
    "iso:country": "US",
    "sg:address": "2255 E Sharon Rd",
    "sg:city": "Cincinnati",
    "sg:classifiers": [
      {
        "category": "Bars \u0026 Pubs",
        "type": "Food \u0026 Drink"
      }
    ],
    "sg:menulink": "http://www.allmenus.com/oh/sharonville/222941-cracker-barrel-old-country-store/menu/",
    "sg:phone": "+1 513 771 3207",
    "sg:postcode": "45241",
    "sg:province": "OH",
    "sg:tags": [
      "american",
      "southern"
    ],
    "wof:name": "Cracker Barrel Old Country Store",
    "wof:placetype": "venue"
  },
  "geometry": {"coordinates":[-84.436807,39.269893],"type":"Point"}
}
