{
  "type": "Feature",
  "properties": {
    "iso:country":"US",
    "sg:address":"2255 E Sharon Rd",
    "sg:city":"Cincinnati",
    "sg:classifiers":[
        {
            "category":"Bars & Pubs",
            "type":"Food & Drink"
        }
    ],
    "sg:menulink":"http://www.allmenus.com/oh/sharonville/222941-cracker-barrel-old-country-store/menu/",
    "sg:phone":"+1 513 771 3207",
    "sg:postcode":"45241",
    "sg:province":"OH",
    "sg:tags":[
        "american",
        "southern"
    ],
    "wof:name":"Cracker Barrel Old Country Store",
    "wof:placetype":"venue"
},
  "geometry": {"coordinates":[-84.436807,39.269893],"type":"Point"}
}