{
  "type": "Feature",
  "properties": {
    "iso:country":"US",
    "sg:address":"6929 Vinewood Ave",
    "sg:city":"Cincinnati",
    "sg:classifiers":[
        {
            "category":"Wholesale",
            "subcategory":"Vending Machines",
            "type":"Manufacturing & Wholesale Goods"
        }
    ],
    "sg:phone":"+1 513 271 3448",
    "sg:postcode":"45227",
    "sg:province":"OH",
    "sg:tags":[
        "operator"
    ],
    "wof:name":"Ultimate Vending Bus Systems",
    "wof:placetype":"venue"
},
  "geometry": {"coordinates":[-84.37599400000001,39.156896],"type":"Point"}
}