{
  "type": "Feature",
  "properties": {
    "addr:full": "6929 Vinewood Ave Cincinnati OH 45227",
    "addr:housenumber": "6929",
    "addr:postcode": "45227",
    "addr:street": "Vinewood Ave",
    "iso:country": "US",
    "sg:address": "6929 Vinewood Ave",
    "sg:city": "Cincinnati",
    "sg:classifiers": [
      {
        "category": "Wholesale",
        "subcategory": "Vending Machines",
        "type": "Manufacturing \u0026 Wholesale Goods"
      }
    ],
    "sg:phone": "+1 513 271 3448",
    "sg:postcode": "45227",
    "sg:province": "OH",
    "sg:tags": [
      "operator"
    ],
    "wof:name": "Ultimate Vending Bus Systems",
    "wof:placetype": "venue"
  },
  "geometry": {"coordinates":[-84.375994,39.156896],"type":"Point"}
}
