{
  "type": "Feature",
  "properties": {
    "addr:full":"11792 Lebanon Rd Cincinnati OH 45241",
    "addr:housenumber":"11792",
    "addr:postcode":"45241",
    "addr:street":"Lebanon Rd",
    "iso:country":"US",
    "sg:address":"11792 Lebanon Rd",
    "sg:city":"Cincinnati",
    "sg:classifiers":[
        {
            "category":"Banks & Credit Unions",
            "subcategory":"Bank",
            "type":"Services"
        }
    ],
    "sg:phone":"+1 513 733 9292",
    "sg:postcode":"45241",
    "sg:province":"OH",
    "sg:tags":[
        "state",
        "commercial",
        "national"
    ],
    "wof:name":"Fifth Third Bank",
    "wof:placetype":"venue"
},
  "geometry": {"coordinates":[-84.396764,39.286919],"type":"Point"}
}