{
  "type": "Feature",
  "properties": {
    "addr:full": "215 N Main St New Lexington OH 43764",
    "addr:housenumber": "215",
    "addr:postcode": "43764",
    "addr:street": "N Main St",
    "iso:country": "US",
    "sg:address": "215 N Main St",
    "sg:city": "New Lexington",
    "sg:classifiers": [
      {
        "category": "Banks \u0026 Credit Unions",
        "subcategory": "Bank",
        "type": "Services"
      }
    ],
    "sg:phone": "+1 740 342 7822",
    "sg:postcode": "43764",
    "sg:province": "OH",
    "sg:tags": [
      "loan",
      "real estate"
    ],
    "wof:name": "Accubanc Mortgage",
    "wof:placetype": "venue"
  },
  "geometry": {"coordinates":[-82.207989,39.713981],"type":"Point"}
}
