{
  "type": "Feature",
  "properties": {
    "iso:country":"US",
    "sg:address":"215 N Main St",
    "sg:city":"New Lexington",
    "sg:classifiers":[
        {
            "category":"Banks & Credit Unions",
            "subcategory":"Bank",
            "type":"Services"
        }
    ],
    "sg:phone":"+1 740 342 7822",
    "sg:postcode":"43764",
    "sg:province":"OH",
    "sg:tags":[
        "loan",
        "real estate"
    ],
    "wof:name":"Accubanc Mortgage",
    "wof:placetype":"venue"
},
  "geometry": {"coordinates":[-82.207989,39.713981],"type":"Point"}
}