{
  "type": "Feature",
  "properties": {
    "addr:full":"8350 Fremont Pike Perrysburg OH 43551",
    "addr:housenumber":"8350",
    "addr:postcode":"43551",
    "addr:street":"Fremont Pike",
    "iso:country":"US",
    "sg:address":"8350 Fremont Pike",
    "sg:city":"Perrysburg",
    "sg:classifiers":[
        {
            "category":"Building & Trades",
            "subcategory":"Construction",
            "type":"Services"
        }
    ],
    "sg:phone":"+1 419 872 7000",
    "sg:postcode":"43551",
    "sg:province":"OH",
    "sg:tags":[
        "general",
        "contractor"
    ],
    "wof:name":"Spieker Co",
    "wof:placetype":"venue"
},
  "geometry": {"coordinates":[-83.558485,41.531711],"type":"Point"}
}