{
  "type": "Feature",
  "properties": {
    "addr:full": "155 N Oval Mall Columbus OH 43210",
    "addr:housenumber": "155",
    "addr:postcode": "43210",
    "addr:street": "N Oval Mall",
    "iso:country": "US",
    "sg:address": "155 N Oval Mall",
    "sg:city": "Columbus",
    "sg:classifiers": [
      {
        "category": "Museum",
        "type": "Entertainment"
      }
    ],
    "sg:phone": "+1 614 292 6896",
    "sg:postcode": "43210",
    "sg:province": "OH",
    "wof:name": "Orton Geological Museum",
    "wof:placetype": "venue"
  },
  "geometry": {"coordinates":[-83.012646,40.000752],"type":"Point"}
}
