{
  "type": "Feature",
  "properties": {
    "addr:full": "4420 Walford St Columbus OH 43224",
    "addr:housenumber": "4420",
    "addr:postcode": "43224",
    "addr:street": "Walford St",
    "iso:country": "US",
    "sg:address": "4420 Walford St",
    "sg:city": "Columbus",
    "sg:classifiers": [
      {
        "category": "Shopping",
        "subcategory": "Beauty \u0026 Cosmetics",
        "type": "Retail Goods"
      }
    ],
    "sg:phone": "+1 614 476 1311",
    "sg:postcode": "43224",
    "sg:province": "OH",
    "sg:tags": [
      "merchandise"
    ],
    "wof:name": "Modern Beauty Supply",
    "wof:placetype": "venue"
  },
  "geometry": {"coordinates":[-82.961751,40.059556],"type":"Point"}
}
