{
  "type": "Feature",
  "properties": {
    "iso:country":"US",
    "sg:address":"4420 Walford St",
    "sg:city":"Columbus",
    "sg:classifiers":[
        {
            "category":"Shopping",
            "subcategory":"Beauty & Cosmetics",
            "type":"Retail Goods"
        }
    ],
    "sg:phone":"+1 614 476 1311",
    "sg:postcode":"43224",
    "sg:province":"OH",
    "sg:tags":[
        "merchandise"
    ],
    "wof:name":"Modern Beauty Supply",
    "wof:placetype":"venue"
},
  "geometry": {"coordinates":[-82.96175100000001,40.059556],"type":"Point"}
}