{
  "type": "Feature",
  "properties": {
    "addr:full": "29605 Aurora Rd Solon OH 44139",
    "addr:housenumber": "29605",
    "addr:postcode": "44139",
    "addr:street": "Aurora Rd",
    "iso:country": "US",
    "sg:address": "29605 Aurora Rd",
    "sg:city": "Solon",
    "sg:classifiers": [
      {
        "category": "Autos \u0026 Motor Vehicles",
        "subcategory": "Fuel \u0026 Gas Station",
        "type": "Retail Goods"
      },
      {
        "category": "Retail",
        "subcategory": "Auto Repair",
        "type": "Services"
      }
    ],
    "sg:phone": "+1 440 248 1177",
    "sg:postcode": "44139",
    "sg:province": "OH",
    "wof:name": "Aurora-Harper Sunoco Inc",
    "wof:placetype": "venue"
  },
  "geometry": {"coordinates":[-81.467903,41.397999],"type":"Point"}
}
