{
  "type": "Feature",
  "properties": {
    "iso:country":"US",
    "sg:address":"29605 Aurora Rd",
    "sg:city":"Solon",
    "sg:classifiers":[
        {
            "category":"Autos & Motor Vehicles",
            "subcategory":"Fuel & Gas Station",
            "type":"Retail Goods"
        },
        {
            "category":"Retail",
            "subcategory":"Auto Repair",
            "type":"Services"
        }
    ],
    "sg:phone":"+1 440 248 1177",
    "sg:postcode":"44139",
    "sg:province":"OH",
    "wof:name":"Aurora-Harper Sunoco Inc",
    "wof:placetype":"venue"
},
  "geometry": {"coordinates":[-81.46790300000001,41.397999],"type":"Point"}
}