{
  "type": "Feature",
  "properties": {
    "addr:full": "3669 E Livingston Ave Columbus OH 43227",
    "addr:housenumber": "3669",
    "addr:postcode": "43227",
    "addr:street": "E Livingston Ave",
    "iso:country": "US",
    "sg:address": "3669 E Livingston Ave",
    "sg:city": "Columbus",
    "sg:classifiers": [
      {
        "category": "Bars \u0026 Pubs",
        "type": "Food \u0026 Drink"
      }
    ],
    "sg:phone": "+1 614 239 7390",
    "sg:postcode": "43227",
    "sg:province": "OH",
    "sg:tags": [
      "club",
      "night"
    ],
    "wof:name": "Society Page Supper Club",
    "wof:placetype": "venue"
  },
  "geometry": {"coordinates":[-82.898126,39.945851],"type":"Point"}
}
