{
  "type": "Feature",
  "properties": {
    "iso:country":"US",
    "sg:address":"30825 Euclid Ave",
    "sg:city":"Wickliffe",
    "sg:classifiers":[
        {
            "category":"Bars & Pubs",
            "type":"Food & Drink"
        }
    ],
    "sg:phone":"+1 440 585 3039",
    "sg:postcode":"44092",
    "sg:province":"OH",
    "sg:tags":[
        "drinking"
    ],
    "wof:name":"Horvat's Pub",
    "wof:placetype":"venue"
},
  "geometry": {"coordinates":[-81.453654,41.620275],"type":"Point"}
}