{
  "type": "Feature",
  "properties": {
    "iso:country":"US",
    "sg:address":"7420 James Dr",
    "sg:city":"North Royalton",
    "sg:classifiers":[
        {
            "category":"Manufacturing",
            "subcategory":"Building Materials",
            "type":"Manufacturing & Wholesale Goods"
        }
    ],
    "sg:phone":"+1 440 237 3626",
    "sg:postcode":"44133",
    "sg:province":"OH",
    "sg:tags":[
        "mfg"
    ],
    "wof:name":"Sylvan Forge Inc",
    "wof:placetype":"venue"
},
  "geometry": {"coordinates":[-81.74310800000001,41.323388],"type":"Point"}
}