{
  "type": "Feature",
  "properties": {
    "addr:full": "7420 James Dr North Royalton OH 44133",
    "addr:housenumber": "7420",
    "addr:postcode": "44133",
    "addr:street": "James Dr",
    "iso:country": "US",
    "sg:address": "7420 James Dr",
    "sg:city": "North Royalton",
    "sg:classifiers": [
      {
        "category": "Manufacturing",
        "subcategory": "Building Materials",
        "type": "Manufacturing \u0026 Wholesale Goods"
      }
    ],
    "sg:phone": "+1 440 237 3626",
    "sg:postcode": "44133",
    "sg:province": "OH",
    "sg:tags": [
      "mfg"
    ],
    "wof:name": "Sylvan Forge Inc",
    "wof:placetype": "venue"
  },
  "geometry": {"coordinates":[-81.743108,41.323388],"type":"Point"}
}
