{
  "type": "Feature",
  "properties": {
    "addr:full": "608 S Broadway St Greenville OH 45331",
    "addr:housenumber": "608",
    "addr:postcode": "45331",
    "addr:street": "S Broadway St",
    "iso:country": "US",
    "sg:address": "608 S Broadway St",
    "sg:city": "Greenville",
    "sg:classifiers": [
      {
        "category": "Shopping",
        "subcategory": "Gifts \u0026 Souvenirs",
        "type": "Retail Goods"
      }
    ],
    "sg:phone": "+1 937 547 2250",
    "sg:postcode": "45331",
    "sg:province": "OH",
    "sg:tags": [
      "shop"
    ],
    "wof:name": "Unwrapped Gifts LLC",
    "wof:placetype": "venue"
  },
  "geometry": {"coordinates":[-84.630643,40.099826],"type":"Point"}
}
