{
  "type": "Feature",
  "properties": {
    "iso:country":"US",
    "sg:address":"608 S Broadway St",
    "sg:city":"Greenville",
    "sg:classifiers":[
        {
            "category":"Shopping",
            "subcategory":"Gifts & Souvenirs",
            "type":"Retail Goods"
        }
    ],
    "sg:phone":"+1 937 547 2250",
    "sg:postcode":"45331",
    "sg:province":"OH",
    "sg:tags":[
        "shop"
    ],
    "wof:name":"Unwrapped Gifts LLC",
    "wof:placetype":"venue"
},
  "geometry": {"coordinates":[-84.63064300000001,40.099826],"type":"Point"}
}