{
  "type": "Feature",
  "properties": {
    "iso:country":"US",
    "sg:address":"1209 Hill Rd N",
    "sg:city":"Pickerington",
    "sg:classifiers":[
        {
            "category":"Health Services",
            "subcategory":"Clinic",
            "type":"Services"
        }
    ],
    "sg:phone":"+1 614 755 4945",
    "sg:postcode":"43147",
    "sg:province":"OH",
    "sg:website":"www.priority-systems.com",
    "wof:name":"PRIORITY-Systems.Com",
    "wof:placetype":"venue"
},
  "geometry": {"coordinates":[-82.779904,39.914166],"type":"Point"}
}