{
  "type": "Feature",
  "properties": {
    "iso:country":"US",
    "sg:address":"132 S Broad St",
    "sg:city":"Canfield",
    "sg:classifiers":[
        {
            "category":"Insurance",
            "subcategory":"Insurance Agent",
            "type":"Services"
        }
    ],
    "sg:phone":"+1 330 533 1523",
    "sg:postcode":"44406",
    "sg:province":"OH",
    "wof:name":"Canale Insurance",
    "wof:placetype":"venue"
},
  "geometry": {"coordinates":[-80.761034,41.022385],"type":"Point"}
}