{
  "type": "Feature",
  "properties": {
    "addr:full":"1100 Resource Dr Cleveland OH 44131",
    "addr:housenumber":"1100",
    "addr:postcode":"44131",
    "addr:street":"Resource Dr",
    "iso:country":"US",
    "sg:address":"1100 Resource Dr",
    "sg:city":"Cleveland",
    "sg:classifiers":[
        {
            "category":"Building & Trades",
            "subcategory":"Construction",
            "type":"Services"
        },
        {
            "category":"Wholesale",
            "subcategory":"Home Furnishings",
            "type":"Manufacturing & Wholesale Goods"
        }
    ],
    "sg:phone":"+1 216 741 9000",
    "sg:postcode":"44131",
    "sg:province":"OH",
    "sg:tags":[
        "organizer",
        "accessory",
        "closet",
        "custom"
    ],
    "sg:website":"www.calclosets.com",
    "wof:name":"California Closet Co",
    "wof:placetype":"venue"
},
  "geometry": {"coordinates":[-81.661978,41.412931],"type":"Point"}
}