{
  "type": "Feature",
  "properties": {
    "iso:country":"US",
    "sg:address":"1348 Beacon St",
    "sg:city":"Cincinnati",
    "sg:classifiers":[
        {
            "category":"Food & Beverages",
            "subcategory":"Groceries & Convenience Stores",
            "type":"Retail Goods"
        }
    ],
    "sg:phone":"+1 513 231 8220",
    "sg:postcode":"45230",
    "sg:province":"OH",
    "sg:tags":[
        "shop",
        "meat"
    ],
    "wof:name":"Beacon Food Mart",
    "wof:placetype":"venue"
},
  "geometry": {"coordinates":[-84.382401,39.078201],"type":"Point"}
}