{
  "type": "Feature",
  "properties": {
    "addr:full":"11407 Corduroy Rd Curtice OH 43412",
    "addr:housenumber":"11407",
    "addr:postcode":"43412",
    "addr:street":"Corduroy Rd",
    "iso:country":"US",
    "sg:address":"11407 Corduroy Rd",
    "sg:city":"Curtice",
    "sg:classifiers":[
        {
            "category":"Bars & Pubs",
            "type":"Food & Drink"
        }
    ],
    "sg:phone":"+1 419 836 5757",
    "sg:postcode":"43412",
    "sg:province":"OH",
    "wof:name":"Judy's Again",
    "wof:placetype":"venue"
},
  "geometry": {"coordinates":[-83.27697499999999,41.661137],"type":"Point"}
}