{
  "type": "Feature",
  "properties": {
    "addr:full": "320 Main St Zanesville OH 43701",
    "addr:housenumber": "320",
    "addr:postcode": "43701",
    "addr:street": "Main St",
    "iso:country": "US",
    "sg:address": "320 Main St",
    "sg:city": "Zanesville",
    "sg:classifiers": [
      {
        "category": "Professional",
        "subcategory": "Lawyer \u0026 Legal Services",
        "type": "Services"
      }
    ],
    "sg:phone": "+1 740 452 7555",
    "sg:postcode": "43701",
    "sg:province": "OH",
    "sg:tags": [
      "attorney"
    ],
    "sg:website": "www.zanesvillelaw.com",
    "wof:name": "Gottlieb Johnston Beam \u0026 Dal",
    "wof:placetype": "venue"
  },
  "geometry": {"coordinates":[-82.008777,39.940111],"type":"Point"}
}
