{
  "type": "Feature",
  "properties": {
    "iso:country":"US",
    "sg:address":"320 Main St",
    "sg:city":"Zanesville",
    "sg:classifiers":[
        {
            "category":"Professional",
            "subcategory":"Lawyer & Legal Services",
            "type":"Services"
        }
    ],
    "sg:phone":"+1 740 452 7555",
    "sg:postcode":"43701",
    "sg:province":"OH",
    "sg:tags":[
        "attorney"
    ],
    "sg:website":"www.zanesvillelaw.com",
    "wof:name":"Gottlieb Johnston Beam & Dal",
    "wof:placetype":"venue"
},
  "geometry": {"coordinates":[-82.00877699999999,39.940111],"type":"Point"}
}