{
  "type": "Feature",
  "properties": {
    "iso:country":"US",
    "sg:address":"1321 Hull Rd",
    "sg:city":"Sandusky",
    "sg:classifiers":[
        {
            "category":"Health Services",
            "subcategory":"Health Practitioner",
            "type":"Services"
        }
    ],
    "sg:phone":"+1 419 626 9602",
    "sg:postcode":"44870",
    "sg:province":"OH",
    "wof:name":"Firelands Foot & Ankle",
    "wof:placetype":"venue"
},
  "geometry": {"coordinates":[-82.666877,41.414633],"type":"Point"}
}