{
  "type": "Feature",
  "properties": {
    "addr:full": "1190 Inman St Akron OH 44306",
    "addr:housenumber": "1190",
    "addr:postcode": "44306",
    "addr:street": "Inman St",
    "iso:country": "US",
    "sg:address": "1190 Inman St",
    "sg:city": "Akron",
    "sg:classifiers": [
      {
        "category": "Organizations",
        "subcategory": "Religious Organization",
        "type": "Services"
      }
    ],
    "sg:phone": "+1 330 773 5298",
    "sg:postcode": "44306",
    "sg:province": "OH",
    "sg:tags": [
      "church"
    ],
    "wof:name": "Cascade Community Church",
    "wof:placetype": "venue"
  },
  "geometry": {"coordinates":[-81.500135,41.046744],"type":"Point"}
}
