{
  "type": "Feature",
  "properties": {
    "addr:full": "4874 Harding Hwy W Marion OH 43302",
    "addr:housenumber": "4874",
    "addr:postcode": "43302",
    "addr:street": "Harding Hwy W",
    "iso:country": "US",
    "sg:address": "4874 Harding Hwy W",
    "sg:city": "Marion",
    "sg:phone": "+1 740 382 9878",
    "sg:postcode": "43302",
    "sg:province": "OH",
    "sg:tags": [
      "farm",
      "corn",
      "soybean"
    ],
    "wof:name": "Tim Fogle",
    "wof:placetype": "venue"
  },
  "geometry": {"coordinates":[-83.269073,40.634586],"type":"Point"}
}
