{
  "type": "Feature",
  "properties": {
    "addr:full": "814 Wheeling Ave Cambridge OH 43725",
    "addr:housenumber": "814",
    "addr:postcode": "43725",
    "addr:street": "Wheeling Ave",
    "iso:country": "US",
    "sg:address": "814 Wheeling Ave",
    "sg:city": "Cambridge",
    "sg:classifiers": [
      {
        "category": "Insurance",
        "subcategory": "Insurance Agent",
        "type": "Services"
      }
    ],
    "sg:phone": "+1 740 432 6363",
    "sg:postcode": "43725",
    "sg:province": "OH",
    "sg:tags": [
      "agency",
      "title"
    ],
    "wof:name": "Moorehead Robert S Jr",
    "wof:placetype": "venue"
  },
  "geometry": {"coordinates":[-81.589902,40.02469],"type":"Point"}
}
