{
  "type": "Feature",
  "properties": {
    "iso:country":"US",
    "sg:address":"2 E Main St",
    "sg:city":"Norwalk",
    "sg:classifiers":[
        {
            "category":"Education",
            "subcategory":"Library",
            "type":"Public Place"
        }
    ],
    "sg:phone":"+1 419 668 5127",
    "sg:postcode":"44857",
    "sg:province":"OH",
    "sg:tags":[
        "executive"
    ],
    "wof:name":"Law Library",
    "wof:placetype":"venue"
},
  "geometry": {"coordinates":[-82.614586,41.242813],"type":"Point"}
}