{
  "type": "Feature",
  "properties": {
    "iso:country":"US",
    "sg:address":"5899 Broadview Rd",
    "sg:city":"Cleveland",
    "sg:classifiers":[
        {
            "category":"Retail",
            "subcategory":"Repair Shop",
            "type":"Services"
        }
    ],
    "sg:phone":"+1 216 749 0625",
    "sg:postcode":"44134",
    "sg:province":"OH",
    "sg:tags":[
        "jewelry"
    ],
    "wof:name":"Jewel House Inc",
    "wof:placetype":"venue"
},
  "geometry": {"coordinates":[-81.68971999999999,41.402568],"type":"Point"}
}