{
  "type": "Feature",
  "properties": {
    "addr:full": "5478 Eaglesnest Dr Westerville OH 43081",
    "addr:housenumber": "5478",
    "addr:postcode": "43081",
    "addr:street": "Eaglesnest Dr",
    "iso:country": "US",
    "sg:address": "5478 Eaglesnest Dr",
    "sg:city": "Westerville",
    "sg:classifiers": [
      {
        "category": "Building \u0026 Trades",
        "subcategory": "Construction",
        "type": "Services"
      }
    ],
    "sg:phone": "+1 614 882 7817",
    "sg:postcode": "43081",
    "sg:province": "OH",
    "sg:tags": [
      "home",
      "speculative",
      "general",
      "builder",
      "contractor"
    ],
    "wof:name": "Elite Builders Inc",
    "wof:placetype": "venue"
  },
  "geometry": {"coordinates":[-82.875886,40.082471],"type":"Point"}
}
