{
  "type": "Feature",
  "properties": {
    "iso:country":"US",
    "sg:address":"5478 Eaglesnest Dr",
    "sg:city":"Westerville",
    "sg:classifiers":[
        {
            "category":"Building & Trades",
            "subcategory":"Construction",
            "type":"Services"
        }
    ],
    "sg:phone":"+1 614 882 7817",
    "sg:postcode":"43081",
    "sg:province":"OH",
    "sg:tags":[
        "home",
        "speculative",
        "general",
        "builder",
        "contractor"
    ],
    "wof:name":"Elite Builders Inc",
    "wof:placetype":"venue"
},
  "geometry": {"coordinates":[-82.87588599999999,40.082471],"type":"Point"}
}