{
  "type": "Feature",
  "properties": {
    "addr:full": "11679 Meadowbrook Dr Cleveland OH 44130",
    "addr:housenumber": "11679",
    "addr:postcode": "44130",
    "addr:street": "Meadowbrook Dr",
    "iso:country": "US",
    "sg:address": "11679 Meadowbrook Dr",
    "sg:city": "Cleveland",
    "sg:classifiers": [
      {
        "category": "Building \u0026 Trades",
        "subcategory": "Plumbing",
        "type": "Services"
      }
    ],
    "sg:phone": "+1 440 886 2130",
    "sg:postcode": "44130",
    "sg:province": "OH",
    "sg:tags": [
      "contractor"
    ],
    "wof:name": "D Alessio Ralph J",
    "wof:placetype": "venue"
  },
  "geometry": {"coordinates":[-81.768186,41.373656],"type":"Point"}
}
