{
  "type": "Feature",
  "properties": {
    "iso:country":"US",
    "sg:address":"1260 Monroe St NW",
    "sg:city":"New Philadelphia",
    "sg:classifiers":[
        {
            "category":"Professional",
            "subcategory":"Accounting & Tax Preparation",
            "type":"Services"
        }
    ],
    "sg:phone":"+1 330 343 0607",
    "sg:postcode":"44663",
    "sg:province":"OH",
    "sg:tags":[
        "accountant",
        "payroll"
    ],
    "sg:website":"www.bmacpa.net",
    "wof:name":"Smart Office Support Inc",
    "wof:placetype":"venue"
},
  "geometry": {"coordinates":[-81.456804,40.505182],"type":"Point"}
}