{
  "type": "Feature",
  "properties": {
    "iso:country":"US",
    "sg:address":"929 Twp Rd 115",
    "sg:city":"Deshler",
    "sg:classifiers":[
        {
            "category":"Farming",
            "subcategory":"Farm",
            "type":"Manufacturing & Wholesale Goods"
        }
    ],
    "sg:phone":"+1 419 275 2324",
    "sg:postcode":"43516",
    "sg:province":"OH",
    "sg:tags":[
        "crop",
        "general"
    ],
    "wof:name":"Roger Adams",
    "wof:placetype":"venue"
},
  "geometry": {"coordinates":[-83.87106,41.1611],"type":"Point"}
}