{
  "type": "Feature",
  "properties": {
    "addr:full": "4700 Duke Dr Mason OH 45040",
    "addr:housenumber": "4700",
    "addr:postcode": "45040",
    "addr:street": "Duke Dr",
    "iso:country": "US",
    "sg:address": "4700 Duke Dr",
    "sg:city": "Mason",
    "sg:classifiers": [
      {
        "category": "Professional",
        "subcategory": "Business Services",
        "type": "Services"
      }
    ],
    "sg:phone": "+1 513 459 5000",
    "sg:postcode": "45040",
    "sg:province": "OH",
    "sg:tags": [
      "record",
      "medical"
    ],
    "wof:name": "Smart Corp",
    "wof:placetype": "venue"
  },
  "geometry": {"coordinates":[-84.309486,39.301577],"type":"Point"}
}
