{
  "type": "Feature",
  "properties": {
    "addr:full":"21 W Main St Lexington OH 44904",
    "addr:housenumber":"21",
    "addr:postcode":"44904",
    "addr:street":"W Main St",
    "iso:country":"US",
    "sg:address":"21 W Main St",
    "sg:city":"Lexington",
    "sg:classifiers":[
        {
            "category":"Personal",
            "subcategory":"Beauty Salon",
            "type":"Services"
        }
    ],
    "sg:phone":"+1 419 884 0002",
    "sg:postcode":"44904",
    "sg:province":"OH",
    "wof:name":"Twisted Scissors Hair & Nail",
    "wof:placetype":"venue"
},
  "geometry": {"coordinates":[-82.58400899999999,40.678748],"type":"Point"}
}