{
  "type": "Feature",
  "properties": {
    "addr:full": "2121 Herrick Ave Cincinnati OH 45208",
    "addr:housenumber": "2121",
    "addr:postcode": "45208",
    "addr:street": "Herrick Ave",
    "iso:country": "US",
    "sg:address": "2121 Herrick Ave",
    "sg:city": "Cincinnati",
    "sg:classifiers": [
      {
        "category": "Professional",
        "type": "Services"
      }
    ],
    "sg:phone": "+1 513 321 1097",
    "sg:postcode": "45208",
    "sg:province": "OH",
    "sg:tags": [
      "inventor"
    ],
    "sg:website": "www.parkermedical.com",
    "wof:name": "Parker Medical Inc",
    "wof:placetype": "venue"
  },
  "geometry": {"coordinates":[-84.460837,39.130387],"type":"Point"}
}
