{
  "type": "Feature",
  "properties": {
    "iso:country":"US",
    "sg:address":"34454 Laurel Way",
    "sg:city":"Avon",
    "sg:classifiers":[
        {
            "category":"Real Estate",
            "subcategory":"Real Estate Operator",
            "type":"Services"
        }
    ],
    "sg:phone":"+1 440 937 4455",
    "sg:postcode":"44011",
    "sg:province":"OH",
    "sg:tags":[
        "building",
        "apartment"
    ],
    "wof:name":"Robert E King Properties LLC",
    "wof:placetype":"venue"
},
  "geometry": {"coordinates":[-82.001903,41.423326],"type":"Point"}
}