{
  "type": "Feature",
  "properties": {
    "addr:full": "18050 Royalton Rd Cleveland OH 44136",
    "addr:housenumber": "18050",
    "addr:postcode": "44136",
    "addr:street": "Royalton Rd",
    "iso:country": "US",
    "sg:address": "18050 Royalton Rd",
    "sg:city": "Cleveland",
    "sg:classifiers": [
      {
        "category": "Home \u0026 Garden",
        "subcategory": "Household Appliances",
        "type": "Retail Goods"
      }
    ],
    "sg:phone": "+1 440 268 9320",
    "sg:postcode": "44136",
    "sg:province": "OH",
    "sg:tags": [
      "cleaners",
      "vacuum"
    ],
    "wof:name": "Oreck Floorcare",
    "wof:placetype": "venue"
  },
  "geometry": {"coordinates":[-81.821998,41.313002],"type":"Point"}
}
