{
  "type": "Feature",
  "properties": {
    "iso:country":"US",
    "sg:address":"18050 Royalton Rd",
    "sg:city":"Cleveland",
    "sg:classifiers":[
        {
            "category":"Home & Garden",
            "subcategory":"Household Appliances",
            "type":"Retail Goods"
        }
    ],
    "sg:phone":"+1 440 268 9320",
    "sg:postcode":"44136",
    "sg:province":"OH",
    "sg:tags":[
        "cleaners",
        "vacuum"
    ],
    "wof:name":"Oreck Floorcare",
    "wof:placetype":"venue"
},
  "geometry": {"coordinates":[-81.82199799999999,41.313002],"type":"Point"}
}