{
  "type": "Feature",
  "properties": {
    "iso:country":"US",
    "sg:address":"3630 Co Rd 6-1",
    "sg:city":"Delta",
    "sg:classifiers":[
        {
            "category":"Wholesale",
            "subcategory":"Petroleum",
            "type":"Manufacturing & Wholesale Goods"
        }
    ],
    "sg:phone":"+1 419 822 3907",
    "sg:postcode":"43515",
    "sg:province":"OH",
    "sg:tags":[
        "pipe",
        "crude",
        "pipeline",
        "line",
        "company"
    ],
    "wof:name":"Norco Pipeline Inc",
    "wof:placetype":"venue"
},
  "geometry": {"coordinates":[-83.984432,41.526562],"type":"Point"}
}