{
  "type": "Feature",
  "properties": {
    "iso:country":"US",
    "sg:address":"4403 Saint Clair Ave",
    "sg:city":"Cleveland",
    "sg:classifiers":[
        {
            "category":"Professional",
            "subcategory":"Detective & Security Services",
            "type":"Services"
        }
    ],
    "sg:phone":"+1 216 241 4661",
    "sg:postcode":"44103",
    "sg:province":"OH",
    "sg:tags":[
        "polygraph"
    ],
    "wof:name":"Poly-Tech Assocs Inc",
    "wof:placetype":"venue"
},
  "geometry": {"coordinates":[-81.66142000000001,41.517812],"type":"Point"}
}