{
  "type": "Feature",
  "properties": {
    "addr:full": "4403 Saint Clair Ave Cleveland OH 44103",
    "addr:housenumber": "4403",
    "addr:postcode": "44103",
    "addr:street": "Saint Clair Ave",
    "iso:country": "US",
    "sg:address": "4403 Saint Clair Ave",
    "sg:city": "Cleveland",
    "sg:classifiers": [
      {
        "category": "Professional",
        "subcategory": "Detective \u0026 Security Services",
        "type": "Services"
      }
    ],
    "sg:phone": "+1 216 241 4661",
    "sg:postcode": "44103",
    "sg:province": "OH",
    "sg:tags": [
      "polygraph"
    ],
    "wof:name": "Poly-Tech Assocs Inc",
    "wof:placetype": "venue"
  },
  "geometry": {"coordinates":[-81.66142,41.517812],"type":"Point"}
}
