{
  "type": "Feature",
  "properties": {
    "iso:country":"US",
    "sg:address":"5242 Graham Dr",
    "sg:city":"Cleveland",
    "sg:classifiers":[
        {
            "category":"Real Estate",
            "subcategory":"Real Estate Agent",
            "type":"Services"
        }
    ],
    "sg:phone":"+1 440 646 9120",
    "sg:postcode":"44124",
    "sg:province":"OH",
    "sg:tags":[
        "agency",
        "rental"
    ],
    "wof:name":"Rent Way",
    "wof:placetype":"venue"
},
  "geometry": {"coordinates":[-81.49105900000001,41.533886],"type":"Point"}
}