{
  "type": "Feature",
  "properties": {
    "iso:country":"US",
    "sg:address":"732 Russell Ave",
    "sg:city":"Akron",
    "sg:classifiers":[
        {
            "category":"Organizations",
            "subcategory":"Religious Organization",
            "type":"Services"
        }
    ],
    "sg:phone":"+1 330 253 5098",
    "sg:postcode":"44307",
    "sg:province":"OH",
    "sg:tags":[
        "church"
    ],
    "wof:name":"Baptist Corinthiians Mssnry Ch",
    "wof:placetype":"venue"
},
  "geometry": {"coordinates":[-81.555323,41.061546],"type":"Point"}
}