{
  "type": "Feature",
  "properties": {
    "addr:full": "1075 Edison St NW Hartville OH 44632",
    "addr:housenumber": "1075",
    "addr:postcode": "hartville;44632",
    "addr:street": "Edison St Nw",
    "iso:country": "US",
    "sg:address": "1075 Edison St NW",
    "sg:city": "Hartville",
    "sg:classifiers": [
      {
        "category": "Restaurant",
        "type": "Food \u0026 Drink"
      }
    ],
    "sg:phone": "+1 330 877 9353",
    "sg:postcode": "44632",
    "sg:province": "OH",
    "wof:name": "Hartville Collectibles",
    "wof:placetype": "venue"
  },
  "geometry": {"coordinates":[-81.360483,40.970901],"type":"Point"}
}
