{
  "type": "Feature",
  "properties": {
    "iso:country":"US",
    "sg:address":"100 W Cherry St",
    "sg:city":"Sunbury",
    "sg:classifiers":[
        {
            "category":"Organizations",
            "subcategory":"Religious Organization",
            "type":"Services"
        }
    ],
    "sg:phone":"+1 740 965 3813",
    "sg:postcode":"43074",
    "sg:province":"OH",
    "sg:tags":[
        "church"
    ],
    "sg:website":"www.sunburyumc.org",
    "wof:name":"Sunbury United Methodist Chr",
    "wof:placetype":"venue"
},
  "geometry": {"coordinates":[-82.86145399999999,40.243236],"type":"Point"}
}