{
  "type": "Feature",
  "properties": {
    "iso:country":"US",
    "sg:address":"3250 Tremont Rd",
    "sg:city":"Columbus",
    "sg:classifiers":[
        {
            "category":"Travel",
            "subcategory":"Travel Agent",
            "type":"Entertainment"
        }
    ],
    "sg:phone":"+1 614 248 3145",
    "sg:postcode":"43221",
    "sg:province":"OH",
    "sg:tags":[
        "agency"
    ],
    "wof:name":"Worldtravel Bti",
    "wof:placetype":"venue"
},
  "geometry": {"coordinates":[-83.059055,40.023255],"type":"Point"}
}