{
  "type": "Feature",
  "properties": {
    "iso:country":"US",
    "sg:address":"325 5th St SE",
    "sg:city":"Canton",
    "sg:classifiers":[
        {
            "category":"Building & Trades",
            "subcategory":"Plumbing",
            "type":"Services"
        }
    ],
    "sg:phone":"+1 330 452 6700",
    "sg:postcode":"44702",
    "sg:province":"OH",
    "sg:tags":[
        "sheet",
        "work",
        "metal",
        "contractor"
    ],
    "wof:name":"Sheetmetal Crafters Inc",
    "wof:placetype":"venue"
},
  "geometry": {"coordinates":[-81.373131,40.795213],"type":"Point"}
}