{
  "type": "Feature",
  "properties": {
    "addr:full": "8216 Panhandle Rd Newark OH 43056",
    "addr:housenumber": "8216",
    "addr:postcode": "43056",
    "addr:street": "Panhandle Rd",
    "iso:country": "US",
    "sg:address": "8216 Panhandle Rd",
    "sg:city": "Newark",
    "sg:classifiers": [
      {
        "category": "Building \u0026 Trades",
        "subcategory": "Construction",
        "type": "Services"
      }
    ],
    "sg:phone": "+1 740 323 2330",
    "sg:postcode": "43056",
    "sg:province": "OH",
    "sg:tags": [
      "house",
      "contractor",
      "roofing"
    ],
    "wof:name": "Hottinger General Construction",
    "wof:placetype": "venue"
  },
  "geometry": {"coordinates":[-82.371957,39.959251],"type":"Point"}
}
