{
  "type": "Feature",
  "properties": {
    "iso:country":"US",
    "sg:address":"8216 Panhandle Rd",
    "sg:city":"Newark",
    "sg:classifiers":[
        {
            "category":"Building & Trades",
            "subcategory":"Construction",
            "type":"Services"
        }
    ],
    "sg:phone":"+1 740 323 2330",
    "sg:postcode":"43056",
    "sg:province":"OH",
    "sg:tags":[
        "house",
        "contractor",
        "roofing"
    ],
    "wof:name":"Hottinger General Construction",
    "wof:placetype":"venue"
},
  "geometry": {"coordinates":[-82.37195699999999,39.959251],"type":"Point"}
}