{
  "type": "Feature",
  "properties": {
    "addr:full": "1 E National Rd Vandalia OH 45377",
    "addr:housenumber": "1",
    "addr:postcode": "45377",
    "addr:street": "E National Rd",
    "iso:country": "US",
    "sg:address": "1 E National Rd",
    "sg:city": "Vandalia",
    "sg:classifiers": [
      {
        "category": "Health Services",
        "subcategory": "Doctor",
        "type": "Services"
      }
    ],
    "sg:phone": "+1 937 226 7888",
    "sg:postcode": "45377",
    "sg:province": "OH",
    "sg:tags": [
      "physician",
      "surgeon"
    ],
    "wof:name": "Cosmetic \u0026 Aesthetic Surgery",
    "wof:placetype": "venue"
  },
  "geometry": {"coordinates":[-84.197307,39.890927],"type":"Point"}
}
