{
  "type": "Feature",
  "properties": {
    "addr:full": "1715 Mohican Rd Stow OH 44224",
    "addr:housenumber": "1715",
    "addr:postcode": "44224",
    "addr:street": "Mohican Rd",
    "iso:country": "US",
    "sg:address": "1715 Mohican Rd",
    "sg:city": "Stow",
    "sg:classifiers": [
      {
        "category": "Arts \u0026 Performance",
        "subcategory": "Theater",
        "type": "Entertainment"
      }
    ],
    "sg:phone": "+1 330 678 3170",
    "sg:postcode": "44224",
    "sg:province": "OH",
    "sg:tags": [
      "entertainer",
      "business"
    ],
    "wof:name": "Mister O Juggling \u0026 Balloon",
    "wof:placetype": "venue"
  },
  "geometry": {"coordinates":[-81.446557,41.17345],"type":"Point"}
}
