{
  "type": "Feature",
  "properties": {
    "iso:country":"US",
    "sg:address":"1715 Mohican Rd",
    "sg:city":"Stow",
    "sg:classifiers":[
        {
            "category":"Arts & Performance",
            "subcategory":"Theater",
            "type":"Entertainment"
        }
    ],
    "sg:phone":"+1 330 678 3170",
    "sg:postcode":"44224",
    "sg:province":"OH",
    "sg:tags":[
        "entertainer",
        "business"
    ],
    "wof:name":"Mister O Juggling & Balloon",
    "wof:placetype":"venue"
},
  "geometry": {"coordinates":[-81.446557,41.17345],"type":"Point"}
}