{
  "type": "Feature",
  "properties": {
    "addr:full": "4112 Milan Rd Sandusky OH 44870",
    "addr:housenumber": "4112",
    "addr:postcode": "44870",
    "addr:street": "Milan Rd",
    "iso:country": "US",
    "sg:address": "4112 Milan Rd",
    "sg:city": "Sandusky",
    "sg:classifiers": [
      {
        "category": "Banks \u0026 Credit Unions",
        "subcategory": "Bank",
        "type": "Services"
      }
    ],
    "sg:phone": "+1 419 627 2747",
    "sg:postcode": "44870",
    "sg:province": "OH",
    "sg:tags": [
      "savings",
      "state",
      "loan",
      "institution"
    ],
    "wof:name": "Home Savings \u0026 Loan Company",
    "wof:placetype": "venue"
  },
  "geometry": {"coordinates":[-82.67474,41.418856],"type":"Point"}
}
