{
  "type": "Feature",
  "properties": {
    "addr:full":"224 N 5th St Steubenville OH 43952",
    "addr:housenumber":"224",
    "addr:postcode":"43952",
    "addr:street":"N 5Th St",
    "iso:country":"US",
    "sg:address":"224 N 5th St",
    "sg:city":"Steubenville",
    "sg:classifiers":[
        {
            "category":"Building & Trades",
            "subcategory":"Construction",
            "type":"Services"
        }
    ],
    "sg:phone":"+1 740 282 6650",
    "sg:postcode":"43952",
    "sg:province":"OH",
    "sg:tags":[
        "general",
        "contractor"
    ],
    "wof:name":"Gpc Contracting Co",
    "wof:placetype":"venue"
},
  "geometry": {"coordinates":[-80.614857,40.363361],"type":"Point"}
}