{
  "type": "Feature",
  "properties": {
    "addr:full":"1610 Frederick Ave Cincinnati OH 45223",
    "addr:housenumber":"1610",
    "addr:postcode":"45223",
    "addr:street":"Frederick Ave",
    "iso:country":"US",
    "sg:address":"1610 Frederick Ave",
    "sg:city":"Cincinnati",
    "sg:classifiers":[
        {
            "category":"Building & Trades",
            "subcategory":"Construction",
            "type":"Services"
        }
    ],
    "sg:phone":"+1 513 681 6555",
    "sg:postcode":"45223",
    "sg:province":"OH",
    "sg:tags":[
        "general",
        "contractor"
    ],
    "wof:name":"Larry Smith Contractors Inc",
    "wof:placetype":"venue"
},
  "geometry": {"coordinates":[-84.54475600000001,39.171607],"type":"Point"}
}