{
  "type": "Feature",
  "properties": {
    "addr:full":"9870 Alderman Rd Millfield OH 45761",
    "addr:housenumber":"9870",
    "addr:postcode":"45761",
    "addr:street":"Alderman Rd",
    "iso:country":"US",
    "sg:address":"9870 Alderman Rd",
    "sg:city":"Millfield",
    "sg:classifiers":[
        {
            "category":"Wholesale",
            "subcategory":"Hardware",
            "type":"Manufacturing & Wholesale Goods"
        },
        {
            "category":"Building & Trades",
            "subcategory":"Plumbing",
            "type":"Services"
        }
    ],
    "sg:phone":"+1 740 592 2377",
    "sg:postcode":"45761",
    "sg:province":"OH",
    "sg:tags":[
        "furnace",
        "contractor"
    ],
    "wof:name":"Browns Plumbing & Heating",
    "wof:placetype":"venue"
},
  "geometry": {"coordinates":[-82.099493,39.376638],"type":"Point"}
}