{
  "type": "Feature",
  "properties": {
    "iso:country":"US",
    "sg:address":"19333 Van Aken Blvd",
    "sg:city":"Cleveland",
    "sg:classifiers":[
        {
            "category":"Real Estate",
            "subcategory":"Real Estate Operator",
            "type":"Services"
        }
    ],
    "sg:phone":"+1 216 751 7677",
    "sg:postcode":"44122",
    "sg:province":"OH",
    "sg:tags":[
        "apartment"
    ],
    "wof:name":"Essex House Apartments",
    "wof:placetype":"venue"
},
  "geometry": {"coordinates":[-81.54156999999999,41.466828],"type":"Point"}
}