{
  "type": "Feature",
  "properties": {
    "iso:country":"US",
    "sg:address":"1113 S 4th St",
    "sg:city":"Ironton",
    "sg:classifiers":[
        {
            "category":"Building & Trades",
            "subcategory":"Construction",
            "type":"Services"
        }
    ],
    "sg:phone":"+1 740 532 8246",
    "sg:postcode":"45638",
    "sg:province":"OH",
    "sg:tags":[
        "residential"
    ],
    "wof:name":"Frank Norris Construction",
    "wof:placetype":"venue"
},
  "geometry": {"coordinates":[-82.67725799999999,38.527302],"type":"Point"}
}