{
  "type": "Feature",
  "properties": {
    "addr:full": "1113 S 4th St Ironton OH 45638",
    "addr:housenumber": "1113",
    "addr:postcode": "45638",
    "addr:street": "S 4Th St",
    "iso:country": "US",
    "sg:address": "1113 S 4th St",
    "sg:city": "Ironton",
    "sg:classifiers": [
      {
        "category": "Building \u0026 Trades",
        "subcategory": "Construction",
        "type": "Services"
      }
    ],
    "sg:phone": "+1 740 532 8246",
    "sg:postcode": "45638",
    "sg:province": "OH",
    "sg:tags": [
      "residential"
    ],
    "wof:name": "Frank Norris Construction",
    "wof:placetype": "venue"
  },
  "geometry": {"coordinates":[-82.677258,38.527302],"type":"Point"}
}
