{
  "type": "Feature",
  "properties": {
    "addr:full":"11946 Tramway Dr Cincinnati OH 45241",
    "addr:housenumber":"11946",
    "addr:postcode":"45241",
    "addr:street":"Tramway Dr",
    "iso:country":"US",
    "sg:address":"11946 Tramway Dr",
    "sg:city":"Cincinnati",
    "sg:classifiers":[
        {
            "category":"Building & Trades",
            "subcategory":"Construction",
            "type":"Services"
        }
    ],
    "sg:phone":"+1 513 322 3956",
    "sg:postcode":"45241",
    "sg:province":"OH",
    "sg:tags":[
        "downspouts",
        "gutter"
    ],
    "wof:name":"Gutter Guardian-Cincinnati",
    "wof:placetype":"venue"
},
  "geometry": {"coordinates":[-84.40542000000001,39.291428],"type":"Point"}
}