{
  "type": "Feature",
  "properties": {
    "addr:full": "3796 London Hollow Rd NE Newark OH 43055",
    "addr:housenumber": "3796",
    "addr:postcode": "43055",
    "addr:street": "London Hollow Rd Ne",
    "iso:country": "US",
    "sg:address": "3796 London Hollow Rd NE",
    "sg:city": "Newark",
    "sg:classifiers": [
      {
        "category": "Professional",
        "subcategory": "Computer Services",
        "type": "Services"
      }
    ],
    "sg:phone": "+1 740 349 8283",
    "sg:postcode": "43055",
    "sg:province": "OH",
    "sg:tags": [
      "website",
      "design"
    ],
    "wof:name": "Eagles Nest Internet Svc",
    "wof:placetype": "venue"
  },
  "geometry": {"coordinates":[-82.32756,40.107329],"type":"Point"}
}
