{
  "type": "Feature",
  "properties": {
    "iso:country":"US",
    "sg:address":"38 Franklin Hollow Rd",
    "sg:city":"Cheshire",
    "sg:classifiers":[
        {
            "category":"Professional",
            "type":"Services"
        }
    ],
    "sg:phone":"+1 740 548 7417",
    "sg:postcode":"45629",
    "sg:province":"OH",
    "sg:tags":[
        "establishment"
    ],
    "wof:name":"Senior Serice-Independent",
    "wof:placetype":"venue"
},
  "geometry": {"coordinates":[-82.818461,38.636296],"type":"Point"}
}