{
  "type": "Feature",
  "properties": {
    "iso:country":"US",
    "sg:address":"37640 Aurora Rd",
    "sg:city":"Solon",
    "sg:classifiers":[
        {
            "category":"Building & Trades",
            "subcategory":"Construction",
            "type":"Services"
        }
    ],
    "sg:phone":"+1 440 248 8569",
    "sg:postcode":"44139",
    "sg:province":"OH",
    "sg:tags":[
        "garage",
        "door",
        "installation",
        "repair"
    ],
    "wof:name":"Sal Bertolone & Son Gar Doors",
    "wof:placetype":"venue"
},
  "geometry": {"coordinates":[-81.408236,41.367525],"type":"Point"}
}