{
  "type": "Feature",
  "properties": {
    "addr:full":"14990 Co Rd 21 Fayette OH 43521",
    "addr:housenumber":"14990;21",
    "addr:postcode":"43521",
    "addr:street":"Co Rd",
    "iso:country":"US",
    "sg:address":"14990 Co Rd 21",
    "sg:city":"Fayette",
    "sg:phone":"+1 419 237 2182",
    "sg:postcode":"43521",
    "sg:province":"OH",
    "sg:tags":[
        "farm",
        "corn"
    ],
    "wof:name":"Seiler Farms Inc",
    "wof:placetype":"venue"
},
  "geometry": {"coordinates":[-84.268461,41.652589],"type":"Point"}
}