{
  "type": "Feature",
  "properties": {
    "addr:full": "4335 Pinecrest Dr Zanesville OH 43701",
    "addr:housenumber": "4335",
    "addr:postcode": "43701",
    "addr:street": "Pinecrest Dr",
    "iso:country": "US",
    "sg:address": "4335 Pinecrest Dr",
    "sg:city": "Zanesville",
    "sg:classifiers": [
      {
        "category": "Real Estate",
        "subcategory": "Real Estate Agent",
        "type": "Services"
      }
    ],
    "sg:phone": "+1 740 452 6593",
    "sg:postcode": "43701",
    "sg:province": "OH",
    "wof:name": "James R Kessler",
    "wof:placetype": "venue"
  },
  "geometry": {"coordinates":[-82.071255,39.973192],"type":"Point"}
}
