{
  "type": "Feature",
  "properties": {
    "addr:full":"3727 Upton Ave Toledo OH 43613",
    "addr:housenumber":"3727",
    "addr:postcode":"43613",
    "addr:street":"Upton Ave",
    "iso:country":"US",
    "sg:address":"3727 Upton Ave",
    "sg:city":"Toledo",
    "sg:classifiers":[
        {
            "category":"Home & Garden",
            "subcategory":"Home Furnishings",
            "type":"Retail Goods"
        }
    ],
    "sg:phone":"+1 419 475 3801",
    "sg:postcode":"43613",
    "sg:province":"OH",
    "sg:tags":[
        "glass",
        "mirror"
    ],
    "wof:name":"Horwitz Design Mirror & Glass",
    "wof:placetype":"venue"
},
  "geometry": {"coordinates":[-83.58937899999999,41.687203],"type":"Point"}
}