{
  "type": "Feature",
  "properties": {
    "addr:full": "327 N 20th St Columbus OH 43203",
    "addr:housenumber": "327",
    "addr:postcode": "43203",
    "addr:street": "N 20Th St",
    "iso:country": "US",
    "sg:address": "327 N 20th St",
    "sg:city": "Columbus",
    "sg:classifiers": [
      {
        "category": "Professional",
        "subcategory": "Business Services",
        "type": "Services"
      },
      {
        "category": "Government",
        "subcategory": "Post Office",
        "type": "Public Place"
      }
    ],
    "sg:phone": "+1 800 275 8777",
    "sg:postcode": "43203",
    "sg:province": "OH",
    "sg:tags": [
      "mail",
      "shipping"
    ],
    "sg:website": "http://www.usps.com",
    "wof:name": "USPS - United States Post Office - Mount Vernon Finance Station",
    "wof:placetype": "venue"
  },
  "geometry": {"coordinates":[-82.973251,39.97303],"type":"Point"}
}
