{
  "type": "Feature",
  "properties": {
    "iso:country":"US",
    "sg:address":"8000 5 Mile Rd Ste 250",
    "sg:city":"Cincinnati",
    "sg:phone":"+1 513 233 2444",
    "sg:postcode":"45230",
    "sg:province":"OH",
    "wof:name":"Anderson Primary Care",
    "wof:placetype":"venue"
},
  "geometry": {"coordinates":[-84.35131800000001,39.084538],"type":"Point"}
}