{
  "type": "Feature",
  "properties": {
    "addr:full": "8000 5 Mile Rd Ste 250 Cincinnati OH 45230",
    "addr:housenumber": "8000",
    "addr:postcode": "45230",
    "addr:street": "5 Mile Rd Ste 250",
    "iso:country": "US",
    "sg:address": "8000 5 Mile Rd Ste 250",
    "sg:city": "Cincinnati",
    "sg:phone": "+1 513 233 2444",
    "sg:postcode": "45230",
    "sg:province": "OH",
    "wof:name": "Anderson Primary Care",
    "wof:placetype": "venue"
  },
  "geometry": {"coordinates":[-84.351318,39.084538],"type":"Point"}
}
