{
  "type": "Feature",
  "properties": {
    "addr:full": "31000 Solon Rd Cleveland OH 44139",
    "addr:postcode": "31000;44139",
    "addr:street": "Solon Rd",
    "iso:country": "US",
    "sg:address": "31000 Solon Rd",
    "sg:city": "Cleveland",
    "sg:classifiers": [
      {
        "category": "Manufacturing",
        "subcategory": "Metals",
        "type": "Manufacturing \u0026 Wholesale Goods"
      }
    ],
    "sg:phone": "+1 440 248 0290",
    "sg:postcode": "44139",
    "sg:province": "OH",
    "sg:tags": [
      "steel",
      "mills"
    ],
    "wof:name": "Bcs Cuyahoga LLC",
    "wof:placetype": "venue"
  },
  "geometry": {"coordinates":[-81.457102,41.38713],"type":"Point"}
}
