{
  "type": "Feature",
  "properties": {
    "iso:country":"US",
    "sg:address":"31000 Solon Rd",
    "sg:city":"Cleveland",
    "sg:classifiers":[
        {
            "category":"Manufacturing",
            "subcategory":"Metals",
            "type":"Manufacturing & Wholesale Goods"
        }
    ],
    "sg:phone":"+1 440 248 0290",
    "sg:postcode":"44139",
    "sg:province":"OH",
    "sg:tags":[
        "steel",
        "mills"
    ],
    "wof:name":"Bcs Cuyahoga LLC",
    "wof:placetype":"venue"
},
  "geometry": {"coordinates":[-81.45710200000001,41.38713],"type":"Point"}
}