{
  "type": "Feature",
  "properties": {
    "iso:country":"US",
    "sg:address":"12215 Aldersyde Dr",
    "sg:city":"Cleveland",
    "sg:classifiers":[
        {
            "category":"Building & Trades",
            "subcategory":"Plumbing",
            "type":"Services"
        }
    ],
    "sg:phone":"+1 216 901 9202",
    "sg:postcode":"44125",
    "sg:province":"OH",
    "sg:tags":[
        "control",
        "air",
        "pollution"
    ],
    "wof:name":"Regency Sales Inc",
    "wof:placetype":"venue"
},
  "geometry": {"coordinates":[-81.598156,41.374135],"type":"Point"}
}