{
  "type": "Feature",
  "properties": {
    "iso:country":"US",
    "sg:address":"2735 Edmondson Rd",
    "sg:city":"Cincinnati",
    "sg:classifiers":[
        {
            "category":"Shopping",
            "subcategory":"Clothing, Apparel, & Fashions",
            "type":"Retail Goods"
        }
    ],
    "sg:phone":"+1 513 533 3424",
    "sg:postcode":"45209",
    "sg:province":"OH",
    "wof:name":"Lane Bryant",
    "wof:placetype":"venue"
},
  "geometry": {"coordinates":[-84.445483,39.149607],"type":"Point"}
}