{
  "type": "Feature",
  "properties": {
    "addr:full": "2735 Edmondson Rd Cincinnati OH 45209",
    "addr:housenumber": "2735",
    "addr:postcode": "45209",
    "addr:street": "Edmondson Rd",
    "iso:country": "US",
    "sg:address": "2735 Edmondson Rd",
    "sg:city": "Cincinnati",
    "sg:classifiers": [
      {
        "category": "Shopping",
        "subcategory": "Clothing, Apparel, \u0026 Fashions",
        "type": "Retail Goods"
      }
    ],
    "sg:phone": "+1 513 533 3424",
    "sg:postcode": "45209",
    "sg:province": "OH",
    "wof:name": "Lane Bryant",
    "wof:placetype": "venue"
  },
  "geometry": {"coordinates":[-84.445483,39.149607],"type":"Point"}
}
