{
  "type": "Feature",
  "properties": {
    "addr:full":"5933 Marietta Rd Chillicothe OH 45601",
    "addr:housenumber":"5933",
    "addr:postcode":"45601",
    "addr:street":"Marietta Rd",
    "iso:country":"US",
    "sg:address":"5933 Marietta Rd",
    "sg:city":"Chillicothe",
    "sg:classifiers":[
        {
            "category":"Real Estate",
            "subcategory":"Real Estate Operator",
            "type":"Services"
        }
    ],
    "sg:phone":"+1 740 775 8215",
    "sg:postcode":"45601",
    "sg:province":"OH",
    "sg:tags":[
        "property",
        "lessor"
    ],
    "wof:name":"Conaway Farm",
    "wof:placetype":"venue"
},
  "geometry": {"coordinates":[-82.934648,39.405986],"type":"Point"}
}