{
  "type": "Feature",
  "properties": {
    "addr:full": "5732 Woodville Rd Northwood OH 43619",
    "addr:housenumber": "5732",
    "addr:postcode": "43619",
    "addr:street": "Woodville Rd",
    "iso:country": "US",
    "sg:address": "5732 Woodville Rd",
    "sg:city": "Northwood",
    "sg:classifiers": [
      {
        "category": "Wholesale",
        "subcategory": "Durable Goods \u0026 Equipment",
        "type": "Manufacturing \u0026 Wholesale Goods"
      }
    ],
    "sg:phone": "+1 419 836 2300",
    "sg:postcode": "43619",
    "sg:province": "OH",
    "sg:tags": [
      "representative",
      "manufacturer"
    ],
    "wof:name": "Whitney Co",
    "wof:placetype": "venue"
  },
  "geometry": {"coordinates":[-83.440317,41.585723],"type":"Point"}
}
