{
  "type": "Feature",
  "properties": {
    "iso:country":"US",
    "sg:address":"5732 Woodville Rd",
    "sg:city":"Northwood",
    "sg:classifiers":[
        {
            "category":"Wholesale",
            "subcategory":"Durable Goods & Equipment",
            "type":"Manufacturing & Wholesale Goods"
        }
    ],
    "sg:phone":"+1 419 836 2300",
    "sg:postcode":"43619",
    "sg:province":"OH",
    "sg:tags":[
        "representative",
        "manufacturer"
    ],
    "wof:name":"Whitney Co",
    "wof:placetype":"venue"
},
  "geometry": {"coordinates":[-83.44031699999999,41.585723],"type":"Point"}
}