{
  "type": "Feature",
  "properties": {
    "addr:full":"419 N Broad St Fairborn OH 45324",
    "addr:housenumber":"419",
    "addr:postcode":"45324",
    "addr:street":"N Broad St",
    "iso:country":"US",
    "sg:address":"419 N Broad St",
    "sg:city":"Fairborn",
    "sg:classifiers":[
        {
            "category":"Professional",
            "type":"Services"
        }
    ],
    "sg:phone":"+1 937 873 8040",
    "sg:postcode":"45324",
    "sg:province":"OH",
    "wof:name":"El Monarca",
    "wof:placetype":"venue"
},
  "geometry": {"coordinates":[-84.026156,39.827876],"type":"Point"}
}