{
  "type": "Feature",
  "properties": {
    "iso:country":"US",
    "sg:address":"6900 State Rte 754",
    "sg:city":"Shreve",
    "sg:classifiers":[
        {
            "category":"Organizations",
            "subcategory":"Religious Organization",
            "type":"Services"
        }
    ],
    "sg:phone":"+1 330 567 3786",
    "sg:postcode":"44676",
    "sg:province":"OH",
    "sg:tags":[
        "church"
    ],
    "wof:name":"Hopewell Presbyterian Church",
    "wof:placetype":"venue"
},
  "geometry": {"coordinates":[-82.024397,40.606511],"type":"Point"}
}