{
  "type": "Feature",
  "properties": {
    "addr:full":"2317 Manchester Rd Akron OH 44314",
    "addr:housenumber":"2317",
    "addr:postcode":"44314",
    "addr:street":"Manchester Rd",
    "iso:country":"US",
    "sg:address":"2317 Manchester Rd",
    "sg:city":"Akron",
    "sg:classifiers":[
        {
            "category":"Building & Trades",
            "subcategory":"Equipment Rental",
            "type":"Services"
        }
    ],
    "sg:phone":"+1 330 745 9069",
    "sg:postcode":"44314",
    "sg:province":"OH",
    "sg:tags":[
        "rep",
        "ac",
        "for",
        "heating"
    ],
    "sg:website":"www.pierhvac.com",
    "wof:name":"Pier Associates Inc",
    "wof:placetype":"venue"
},
  "geometry": {"coordinates":[-81.54527400000001,41.035353],"type":"Point"}
}