{
  "type": "Feature",
  "properties": {
    "addr:full": "66550 N Moss Run Rd Bellaire OH 43906",
    "addr:housenumber": "66550",
    "addr:postcode": "43906",
    "addr:street": "N Moss Run Rd",
    "iso:country": "US",
    "sg:address": "66550 N Moss Run Rd",
    "sg:city": "Bellaire",
    "sg:classifiers": [
      {
        "category": "Real Estate",
        "subcategory": "Real Estate Agent",
        "type": "Services"
      }
    ],
    "sg:phone": "+1 740 676 0600",
    "sg:postcode": "43906",
    "sg:province": "OH",
    "wof:name": "Rl Construction",
    "wof:placetype": "venue"
  },
  "geometry": {"coordinates":[-80.785551,40.045694],"type":"Point"}
}
