{
  "type": "Feature",
  "properties": {
    "addr:full":"7356 Wooster Pike Cincinnati OH 45227",
    "addr:housenumber":"7356",
    "addr:postcode":"45227",
    "addr:street":"Wooster Pike",
    "iso:country":"US",
    "sg:address":"7356 Wooster Pike",
    "sg:city":"Cincinnati",
    "sg:classifiers":[
        {
            "category":"Travel",
            "subcategory":"Travel Agent",
            "type":"Entertainment"
        }
    ],
    "sg:phone":"+1 513 561 1500",
    "sg:postcode":"45227",
    "sg:province":"OH",
    "sg:tags":[
        "cruise"
    ],
    "sg:website":"www.haversham.com",
    "wof:name":"Haversham & Baker LTD",
    "wof:placetype":"venue"
},
  "geometry": {"coordinates":[-84.36213499999999,39.142649],"type":"Point"}
}