{
  "type": "Feature",
  "properties": {
    "addr:full":"73 Melmore St Tiffin OH 44883",
    "addr:housenumber":"73",
    "addr:postcode":"44883",
    "addr:street":"Melmore St",
    "iso:country":"US",
    "sg:address":"73 Melmore St",
    "sg:city":"Tiffin",
    "sg:classifiers":[
        {
            "category":"Food & Beverages",
            "subcategory":"Groceries & Convenience Stores",
            "type":"Retail Goods"
        }
    ],
    "sg:phone":"+1 419 447 1705",
    "sg:postcode":"44883",
    "sg:province":"OH",
    "wof:name":"Dairy Mart Convenience Store",
    "wof:placetype":"venue"
},
  "geometry": {"coordinates":[-83.173839,41.107724],"type":"Point"}
}