{
  "type": "Feature",
  "properties": {
    "addr:full":"64759 Slaughter Hill Rd Cambridge OH 43725",
    "addr:housenumber":"64759",
    "addr:postcode":"43725",
    "addr:street":"Slaughter Hill Rd",
    "iso:country":"US",
    "sg:address":"64759 Slaughter Hill Rd",
    "sg:city":"Cambridge",
    "sg:classifiers":[
        {
            "category":"Autos & Motor Vehicles",
            "subcategory":"Automobile Sales",
            "type":"Retail Goods"
        }
    ],
    "sg:phone":"+1 740 432 3392",
    "sg:postcode":"43725",
    "sg:province":"OH",
    "sg:tags":[
        "car",
        "dealer"
    ],
    "wof:name":"Helmick Motor Sales",
    "wof:placetype":"venue"
},
  "geometry": {"coordinates":[-81.558758,40.037201],"type":"Point"}
}