{
  "type": "Feature",
  "properties": {
    "iso:country":"US",
    "sg:address":"5354 N High St",
    "sg:city":"Columbus",
    "sg:classifiers":[
        {
            "category":"Professional",
            "subcategory":"Lawyer & Legal Services",
            "type":"Services"
        }
    ],
    "sg:phone":"+1 614 802 2327",
    "sg:postcode":"43214",
    "sg:province":"OH",
    "sg:tags":[
        "attorney"
    ],
    "wof:name":"David C Baldwin Atty At Law",
    "wof:placetype":"venue"
},
  "geometry": {"coordinates":[-83.018941,40.071411],"type":"Point"}
}