{
  "type": "Feature",
  "properties": {
    "iso:country":"US",
    "sg:address":"13470 Acorn Cir NW",
    "sg:city":"Mogadore",
    "sg:classifiers":[
        {
            "category":"Building & Trades",
            "subcategory":"Landscaping Services",
            "type":"Services"
        }
    ],
    "sg:phone":"+1 330 699 5755",
    "sg:postcode":"44260",
    "sg:province":"OH",
    "wof:name":"By The Yard",
    "wof:placetype":"venue"
},
  "geometry": {"coordinates":[-81.376403,40.986756],"type":"Point"}
}