{
  "type": "Feature",
  "properties": {
    "addr:full": "18756 Rd 24 Fort Jennings OH 45844",
    "addr:housenumber": "18756",
    "addr:postcode": "45844",
    "addr:street": "Rd 24 Fort",
    "iso:country": "US",
    "sg:address": "18756 Rd 24",
    "sg:city": "Fort Jennings",
    "sg:classifiers": [
      {
        "category": "Freight",
        "type": "Transportation"
      }
    ],
    "sg:phone": "+1 419 453 3597",
    "sg:postcode": "45844",
    "sg:province": "OH",
    "sg:tags": [
      "special"
    ],
    "wof:name": "Countryside Storage",
    "wof:placetype": "venue"
  },
  "geometry": {"coordinates":[-84.320798,40.909369],"type":"Point"}
}
