{
  "type": "Feature",
  "properties": {
    "iso:country":"US",
    "sg:address":"1007 E Bogart Rd",
    "sg:city":"Sandusky",
    "sg:classifiers":[
        {
            "category":"Organizations",
            "subcategory":"Religious Organization",
            "type":"Services"
        }
    ],
    "sg:phone":"+1 419 625 4207",
    "sg:postcode":"44870",
    "sg:province":"OH",
    "sg:tags":[
        "clergy"
    ],
    "wof:name":"P Kentus",
    "wof:placetype":"venue"
},
  "geometry": {"coordinates":[-82.657672,41.395883],"type":"Point"}
}