{
  "type": "Feature",
  "properties": {
    "addr:full":"1560 Callander Dr Hudson OH 44236",
    "addr:postcode":"1560;44236",
    "addr:street":"Callander Dr",
    "iso:country":"US",
    "sg:address":"1560 Callander Dr",
    "sg:city":"Hudson",
    "sg:classifiers":[
        {
            "category":"Building & Trades",
            "subcategory":"Construction",
            "type":"Services"
        }
    ],
    "sg:phone":"+1 330 650 9929",
    "sg:postcode":"44236",
    "sg:province":"OH",
    "sg:tags":[
        "contractor"
    ],
    "wof:name":"Budget Waterproofing of Ohio",
    "wof:placetype":"venue"
},
  "geometry": {"coordinates":[-81.43718,41.224933],"type":"Point"}
}