{
  "type": "Feature",
  "properties": {
    "addr:full":"7382 State Rte 7 Proctorville OH 45669",
    "addr:housenumber":"7382",
    "addr:postcode":"45669",
    "addr:street":"State Rte 7",
    "iso:country":"US",
    "sg:address":"7382 State Rte 7",
    "sg:city":"Proctorville",
    "sg:classifiers":[
        {
            "category":"Retail",
            "subcategory":"Auto Repair",
            "type":"Services"
        }
    ],
    "sg:phone":"+1 740 886 5193",
    "sg:postcode":"45669",
    "sg:province":"OH",
    "sg:tags":[
        "wrecker"
    ],
    "wof:name":"R & G Towing & Recovery",
    "wof:placetype":"venue"
},
  "geometry": {"coordinates":[-82.361452,38.441697],"type":"Point"}
}