{
  "type": "Feature",
  "properties": {
    "addr:full": "9347 Ravenna Rd Twinsburg OH 44087",
    "addr:housenumber": "9347",
    "addr:postcode": "44087",
    "addr:street": "Ravenna Rd",
    "iso:country": "US",
    "sg:address": "9347 Ravenna Rd",
    "sg:city": "Twinsburg",
    "sg:phone": "+1 216 478 0507",
    "sg:postcode": "44087",
    "sg:province": "OH",
    "sg:tags": [
      "product",
      "petroleum"
    ],
    "wof:name": "Northeast Lubricants",
    "wof:placetype": "venue"
  },
  "geometry": {"coordinates":[-81.429432,41.308191],"type":"Point"}
}
