{
  "type": "Feature",
  "properties": {
    "addr:full":"211 S Kansas St Green Springs OH 44836",
    "addr:housenumber":"211",
    "addr:postcode":"44836",
    "addr:street":"S Kansas St",
    "iso:country":"US",
    "sg:address":"211 S Kansas St",
    "sg:city":"Green Springs",
    "sg:classifiers":[
        {
            "category":"Banks & Credit Unions",
            "subcategory":"Bank",
            "type":"Services"
        }
    ],
    "sg:phone":"+1 419 639 2364",
    "sg:postcode":"44836",
    "sg:province":"OH",
    "sg:tags":[
        "loan",
        "broker"
    ],
    "wof:name":"M&C Midwest Enterprises",
    "wof:placetype":"venue"
},
  "geometry": {"coordinates":[-83.05442499999999,41.255061],"type":"Point"}
}