{
  "type": "Feature",
  "properties": {
    "addr:full": "9495 Palmer Rd SW Pataskala OH 43062",
    "addr:housenumber": "9495",
    "addr:postcode": "43062",
    "addr:street": "Palmer Rd Sw",
    "iso:country": "US",
    "sg:address": "9495 Palmer Rd SW",
    "sg:city": "Pataskala",
    "sg:classifiers": [
      {
        "category": "Building \u0026 Trades",
        "subcategory": "Construction",
        "type": "Services"
      }
    ],
    "sg:phone": "+1 740 927 6021",
    "sg:postcode": "43062",
    "sg:province": "OH",
    "sg:tags": [
      "floor",
      "laying",
      "contractor"
    ],
    "wof:name": "Bowman Boyd",
    "wof:placetype": "venue"
  },
  "geometry": {"coordinates":[-82.682403,39.937622],"type":"Point"}
}
