{
  "type": "Feature",
  "properties": {
    "addr:full": "22043 Lorain Rd Cleveland OH 44126",
    "addr:housenumber": "22043",
    "addr:postcode": "44126",
    "addr:street": "Lorain Rd",
    "iso:country": "US",
    "sg:address": "22043 Lorain Rd",
    "sg:city": "Cleveland",
    "sg:classifiers": [
      {
        "category": "Shopping",
        "subcategory": "Bicycles \u0026 Sporting Goods",
        "type": "Retail Goods"
      }
    ],
    "sg:phone": "+1 440 777 6800",
    "sg:postcode": "44126",
    "sg:province": "OH",
    "sg:tags": [
      "equipment",
      "golf",
      "supply"
    ],
    "wof:name": "Pro Golf Discount",
    "wof:placetype": "venue"
  },
  "geometry": {"coordinates":[-81.865341,41.441199],"type":"Point"}
}
