{
  "type": "Feature",
  "properties": {
    "addr:full": "180 W Streetsboro St Hudson OH 44236",
    "addr:housenumber": "180",
    "addr:postcode": "44236",
    "addr:street": "W Streetsboro St",
    "iso:country": "US",
    "sg:address": "180 W Streetsboro St",
    "sg:city": "Hudson",
    "sg:classifiers": [
      {
        "category": "Shopping",
        "subcategory": "Jewelry",
        "type": "Retail Goods"
      }
    ],
    "sg:phone": "+1 330 650 1003",
    "sg:postcode": "44236",
    "sg:province": "OH",
    "sg:tags": [
      "jeweler"
    ],
    "wof:name": "Hickman Jewelry",
    "wof:placetype": "venue"
  },
  "geometry": {"coordinates":[-81.450904,41.239931],"type":"Point"}
}
