{
  "type": "Feature",
  "properties": {
    "iso:country":"US",
    "sg:address":"2901 Hardale Blvd",
    "sg:city":"Toledo",
    "sg:classifiers":[
        {
            "category":"Insurance",
            "subcategory":"Insurance Agent",
            "type":"Services"
        }
    ],
    "sg:phone":"+1 419 725 7244",
    "sg:postcode":"43606",
    "sg:province":"OH",
    "sg:tags":[
        "consulting",
        "management"
    ],
    "wof:name":"Daniel N Steinberg",
    "wof:placetype":"venue"
},
  "geometry": {"coordinates":[-83.638752,41.674983],"type":"Point"}
}