{
  "type": "Feature",
  "properties": {
    "iso:country":"US",
    "sg:address":"2151 Stumbo Rd S",
    "sg:city":"Mansfield",
    "sg:classifiers":[
        {
            "category":"Building & Trades",
            "subcategory":"Construction",
            "type":"Services"
        }
    ],
    "sg:phone":"+1 419 756 3680",
    "sg:postcode":"44906",
    "sg:province":"OH",
    "sg:tags":[
        "home",
        "builder"
    ],
    "wof:name":"Getz Builders Inc",
    "wof:placetype":"venue"
},
  "geometry": {"coordinates":[-82.59656699999999,40.766192],"type":"Point"}
}