{
  "type": "Feature",
  "properties": {
    "addr:full": "2151 Stumbo Rd S Mansfield OH 44906",
    "addr:housenumber": "2151",
    "addr:postcode": "44906",
    "addr:street": "Stumbo Rd",
    "iso:country": "US",
    "sg:address": "2151 Stumbo Rd S",
    "sg:city": "Mansfield",
    "sg:classifiers": [
      {
        "category": "Building \u0026 Trades",
        "subcategory": "Construction",
        "type": "Services"
      }
    ],
    "sg:phone": "+1 419 756 3680",
    "sg:postcode": "44906",
    "sg:province": "OH",
    "sg:tags": [
      "home",
      "builder"
    ],
    "wof:name": "Getz Builders Inc",
    "wof:placetype": "venue"
  },
  "geometry": {"coordinates":[-82.596567,40.766192],"type":"Point"}
}
