{
  "type": "Feature",
  "properties": {
    "addr:full":"6505 Hasler Ln Cincinnati OH 45216",
    "addr:housenumber":"6505",
    "addr:postcode":"45216",
    "addr:street":"Hasler Ln",
    "iso:country":"US",
    "sg:address":"6505 Hasler Ln",
    "sg:city":"Cincinnati",
    "sg:classifiers":[
        {
            "category":"Organizations",
            "subcategory":"Religious Organization",
            "type":"Services"
        }
    ],
    "sg:phone":"+1 513 242 4803",
    "sg:postcode":"45216",
    "sg:province":"OH",
    "sg:tags":[
        "clergy"
    ],
    "wof:name":"Benjamin Omosebi",
    "wof:placetype":"venue"
},
  "geometry": {"coordinates":[-84.48262,39.188612],"type":"Point"}
}