{
  "type": "Feature",
  "properties": {
    "addr:full":"138 Sandusky Blvd Chillicothe OH 45601",
    "addr:housenumber":"138",
    "addr:postcode":"45601",
    "addr:street":"Sandusky Blvd",
    "iso:country":"US",
    "sg:address":"138 Sandusky Blvd",
    "sg:city":"Chillicothe",
    "sg:classifiers":[
        {
            "category":"Education",
            "subcategory":"School",
            "type":"Public Place"
        }
    ],
    "sg:phone":"+1 740 773 4103",
    "sg:postcode":"45601",
    "sg:province":"OH",
    "wof:name":"Union Scioto Primary School",
    "wof:placetype":"venue"
},
  "geometry": {"coordinates":[-83.018218,39.37245],"type":"Point"}
}