{
  "type": "Feature",
  "properties": {
    "iso:country":"US",
    "sg:address":"7358 Clingan Rd",
    "sg:city":"Youngstown",
    "sg:classifiers":[
        {
            "category":"Building & Trades",
            "subcategory":"Construction",
            "type":"Services"
        }
    ],
    "sg:phone":"+1 330 757 3274",
    "sg:postcode":"44514",
    "sg:province":"OH",
    "sg:tags":[
        "contractor"
    ],
    "wof:name":"Mike Cikovich Masonry Inc",
    "wof:placetype":"venue"
},
  "geometry": {"coordinates":[-80.591235,41.007625],"type":"Point"}
}