{
  "type": "Feature",
  "properties": {
    "iso:country":"US",
    "sg:address":"8200 Avery Rd",
    "sg:city":"Cleveland",
    "sg:classifiers":[
        {
            "category":"Health Services",
            "subcategory":"Podiatrist",
            "type":"Services"
        }
    ],
    "sg:phone":"+1 440 526 0860",
    "sg:postcode":"44147",
    "sg:province":"OH",
    "wof:name":"David A Harding DPM",
    "wof:placetype":"venue"
},
  "geometry": {"coordinates":[-81.68361299999999,41.342874],"type":"Point"}
}