{
  "type": "Feature",
  "properties": {
    "addr:full": "8200 Avery Rd Cleveland OH 44147",
    "addr:housenumber": "8200",
    "addr:postcode": "44147",
    "addr:street": "Avery Rd",
    "iso:country": "US",
    "sg:address": "8200 Avery Rd",
    "sg:city": "Cleveland",
    "sg:classifiers": [
      {
        "category": "Health Services",
        "subcategory": "Podiatrist",
        "type": "Services"
      }
    ],
    "sg:phone": "+1 440 526 0860",
    "sg:postcode": "44147",
    "sg:province": "OH",
    "wof:name": "David A Harding DPM",
    "wof:placetype": "venue"
  },
  "geometry": {"coordinates":[-81.683613,41.342874],"type":"Point"}
}
