{
  "type": "Feature",
  "properties": {
    "addr:full":"1430 Breckenridge Dr Amelia OH 45102",
    "addr:housenumber":"1430",
    "addr:postcode":"45102",
    "addr:street":"Breckenridge Dr",
    "iso:country":"US",
    "sg:address":"1430 Breckenridge Dr",
    "sg:city":"Amelia",
    "sg:classifiers":[
        {
            "category":"Building & Trades",
            "subcategory":"Construction",
            "type":"Services"
        }
    ],
    "sg:phone":"+1 513 583 0289",
    "sg:postcode":"45102",
    "sg:province":"OH",
    "sg:tags":[
        "roofing",
        "contractor"
    ],
    "wof:name":"E R Roofing",
    "wof:placetype":"venue"
},
  "geometry": {"coordinates":[-84.22848999999999,39.054339],"type":"Point"}
}