{
  "type": "Feature",
  "properties": {
    "addr:full": "4747 N Holland Sylvania Ave Sylvania OH 43560",
    "addr:housenumber": "4747",
    "addr:postcode": "43560",
    "addr:street": "N Holland Sylvania Ave",
    "iso:country": "US",
    "sg:address": "4747 N Holland Sylvania Ave",
    "sg:city": "Sylvania",
    "sg:classifiers": [
      {
        "category": "Real Estate",
        "subcategory": "Real Estate Agent",
        "type": "Services"
      }
    ],
    "sg:phone": "+1 419 885 1974",
    "sg:postcode": "43560",
    "sg:province": "OH",
    "wof:name": "Five Star Premier Properties",
    "wof:placetype": "venue"
  },
  "geometry": {"coordinates":[-83.693528,41.701035],"type":"Point"}
}
