{
  "type": "Feature",
  "properties": {
    "addr:full": "1907 South Ave Youngstown OH 44502",
    "addr:housenumber": "1907",
    "addr:postcode": "44502",
    "addr:street": "South Ave",
    "iso:country": "US",
    "sg:address": "1907 South Ave",
    "sg:city": "Youngstown",
    "sg:classifiers": [
      {
        "category": "Restaurant",
        "type": "Food \u0026 Drink"
      }
    ],
    "sg:phone": "+1 330 747 2231",
    "sg:postcode": "44502",
    "sg:province": "OH",
    "sg:tags": [
      "eating"
    ],
    "wof:name": "Tokyo House Restaurant",
    "wof:placetype": "venue"
  },
  "geometry": {"coordinates":[-80.64619,41.0801],"type":"Point"}
}
