{
  "type": "Feature",
  "properties": {
    "iso:country":"US",
    "sg:address":"1907 South Ave",
    "sg:city":"Youngstown",
    "sg:classifiers":[
        {
            "category":"Restaurant",
            "type":"Food & Drink"
        }
    ],
    "sg:phone":"+1 330 747 2231",
    "sg:postcode":"44502",
    "sg:province":"OH",
    "sg:tags":[
        "eating"
    ],
    "wof:name":"Tokyo House Restaurant",
    "wof:placetype":"venue"
},
  "geometry": {"coordinates":[-80.64619,41.0801],"type":"Point"}
}