{
  "type": "Feature",
  "properties": {
    "addr:full": "8500 Columbia Rd SW Pataskala OH 43062",
    "addr:housenumber": "8500",
    "addr:postcode": "43062",
    "addr:street": "Columbia Rd Sw",
    "iso:country": "US",
    "sg:address": "8500 Columbia Rd SW",
    "sg:city": "Pataskala",
    "sg:classifiers": [
      {
        "category": "Education",
        "subcategory": "School",
        "type": "Public Place"
      }
    ],
    "sg:phone": "+1 740 927 5906",
    "sg:postcode": "43062",
    "sg:province": "OH",
    "wof:name": "Etna Elementary School",
    "wof:placetype": "venue"
  },
  "geometry": {"coordinates":[-82.694153,39.970884],"type":"Point"}
}
