{
  "type": "Feature",
  "properties": {
    "addr:full": "1171 White Rd Grove City OH 43123",
    "addr:housenumber": "1171",
    "addr:postcode": "43123",
    "addr:street": "White Rd",
    "iso:country": "US",
    "sg:address": "1171 White Rd",
    "sg:city": "Grove City",
    "sg:classifiers": [
      {
        "category": "Building \u0026 Trades",
        "subcategory": "Landscaping Services",
        "type": "Services"
      }
    ],
    "sg:phone": "+1 614 801 0689",
    "sg:postcode": "43123",
    "sg:province": "OH",
    "wof:name": "Torgys Lawn Care",
    "wof:placetype": "venue"
  },
  "geometry": {"coordinates":[-83.034629,39.869496],"type":"Point"}
}
