{
  "type": "Feature",
  "properties": {
    "addr:full":"2934 Twp Rd 82 Findlay OH 45840",
    "addr:housenumber":"2934;82",
    "addr:postcode":"45840",
    "addr:street":"Twp Rd",
    "iso:country":"US",
    "sg:address":"2934 Twp Rd 82",
    "sg:city":"Findlay",
    "sg:classifiers":[
        {
            "category":"Building & Trades",
            "subcategory":"Construction",
            "type":"Services"
        }
    ],
    "sg:phone":"+1 419 859 3314",
    "sg:postcode":"45840",
    "sg:province":"OH",
    "sg:tags":[
        "contractor"
    ],
    "wof:name":"Roofing & Home Repair",
    "wof:placetype":"venue"
},
  "geometry": {"coordinates":[-83.82392900000001,41.007984],"type":"Point"}
}