{
  "type": "Feature",
  "properties": {
    "addr:full": "908 E Perkins Ave Sandusky OH 44870",
    "addr:housenumber": "908",
    "addr:postcode": "44870",
    "addr:street": "E Perkins Ave",
    "iso:country": "US",
    "sg:address": "908 E Perkins Ave",
    "sg:city": "Sandusky",
    "sg:classifiers": [
      {
        "category": "Personal",
        "subcategory": "Barber",
        "type": "Services"
      }
    ],
    "sg:phone": "+1 419 627 9855",
    "sg:postcode": "44870",
    "sg:province": "OH",
    "wof:name": "Real Life Hair Designs",
    "wof:placetype": "venue"
  },
  "geometry": {"coordinates":[-82.683449,41.432554],"type":"Point"}
}
