{
  "type": "Feature",
  "properties": {
    "addr:full": "11366 Ann Dr NW Baltimore OH 43105",
    "addr:housenumber": "11366",
    "addr:postcode": "43105",
    "addr:street": "Ann Dr Nw",
    "iso:country": "US",
    "sg:address": "11366 Ann Dr NW",
    "sg:city": "Baltimore",
    "sg:classifiers": [
      {
        "category": "Shopping",
        "subcategory": "Computers \u0026 Home Electronics",
        "type": "Retail Goods"
      }
    ],
    "sg:phone": "+1 740 862 5327",
    "sg:postcode": "43105",
    "sg:province": "OH",
    "wof:name": "Allentek Computer Services",
    "wof:placetype": "venue"
  },
  "geometry": {"coordinates":[-82.68532,39.892173],"type":"Point"}
}
