{
  "type": "Feature",
  "properties": {
    "iso:country":"US",
    "sg:address":"11366 Ann Dr NW",
    "sg:city":"Baltimore",
    "sg:classifiers":[
        {
            "category":"Shopping",
            "subcategory":"Computers & Home Electronics",
            "type":"Retail Goods"
        }
    ],
    "sg:phone":"+1 740 862 5327",
    "sg:postcode":"43105",
    "sg:province":"OH",
    "wof:name":"Allentek Computer Services",
    "wof:placetype":"venue"
},
  "geometry": {"coordinates":[-82.68532,39.892173],"type":"Point"}
}