{
  "type": "Feature",
  "properties": {
    "addr:full": "1167 Walnut St Coshocton OH 43812",
    "addr:housenumber": "1167",
    "addr:postcode": "43812",
    "addr:street": "Walnut St",
    "iso:country": "US",
    "sg:address": "1167 Walnut St",
    "sg:city": "Coshocton",
    "sg:classifiers": [
      {
        "category": "Restaurant",
        "type": "Food \u0026 Drink"
      }
    ],
    "sg:phone": "+1 740 623 2600",
    "sg:postcode": "43812",
    "sg:province": "OH",
    "sg:tags": [
      "eating"
    ],
    "wof:name": "Yucatan Mexican Restaurant",
    "wof:placetype": "venue"
  },
  "geometry": {"coordinates":[-81.851099,40.271626],"type":"Point"}
}
