{
  "type": "Feature",
  "properties": {
    "addr:full": "617 Vine St Cincinnati OH 45202",
    "addr:housenumber": "617",
    "addr:postcode": "45202",
    "addr:street": "Vine St",
    "iso:country": "US",
    "sg:address": "617 Vine St",
    "sg:city": "Cincinnati",
    "sg:classifiers": [
      {
        "category": "Restaurant",
        "type": "Food \u0026 Drink"
      }
    ],
    "sg:phone": "+1 513 421 3200",
    "sg:postcode": "45202",
    "sg:province": "OH",
    "sg:tags": [
      "eating"
    ],
    "wof:name": "Ice Consultants",
    "wof:placetype": "venue"
  },
  "geometry": {"coordinates":[-84.513489,39.102846],"type":"Point"}
}
