{
  "type": "Feature",
  "properties": {
    "iso:country":"US",
    "sg:address":"777 Portage Lakes Dr",
    "sg:city":"Akron",
    "sg:classifiers":[
        {
            "category":"Wholesale",
            "subcategory":"Machinery & Supplies",
            "type":"Manufacturing & Wholesale Goods"
        }
    ],
    "sg:phone":"+1 330 644 0232",
    "sg:postcode":"44319",
    "sg:province":"OH",
    "sg:tags":[
        "equipment",
        "material",
        "handling"
    ],
    "wof:name":"E J Werner Co",
    "wof:placetype":"venue"
},
  "geometry": {"coordinates":[-81.54286500000001,41.002469],"type":"Point"}
}