{
  "type": "Feature",
  "properties": {
    "addr:full": "777 Portage Lakes Dr Akron OH 44319",
    "addr:housenumber": "777",
    "addr:postcode": "44319",
    "addr:street": "Portage Lakes Dr",
    "iso:country": "US",
    "sg:address": "777 Portage Lakes Dr",
    "sg:city": "Akron",
    "sg:classifiers": [
      {
        "category": "Wholesale",
        "subcategory": "Machinery \u0026 Supplies",
        "type": "Manufacturing \u0026 Wholesale Goods"
      }
    ],
    "sg:phone": "+1 330 644 0232",
    "sg:postcode": "44319",
    "sg:province": "OH",
    "sg:tags": [
      "equipment",
      "material",
      "handling"
    ],
    "wof:name": "E J Werner Co",
    "wof:placetype": "venue"
  },
  "geometry": {"coordinates":[-81.542865,41.002469],"type":"Point"}
}
