{
  "type": "Feature",
  "properties": {
    "addr:full": "3662 Broadway Grove City OH 43123",
    "addr:housenumber": "3662",
    "addr:postcode": "43123",
    "addr:street": "Broadway",
    "iso:country": "US",
    "sg:address": "3662 Broadway",
    "sg:city": "Grove City",
    "sg:classifiers": [
      {
        "category": "Real Estate",
        "subcategory": "Real Estate Services",
        "type": "Services"
      }
    ],
    "sg:phone": "+1 614 875 8900",
    "sg:postcode": "43123",
    "sg:province": "OH",
    "sg:tags": [
      "company",
      "title"
    ],
    "wof:name": "Covenant Title Agency",
    "wof:placetype": "venue"
  },
  "geometry": {"coordinates":[-83.087204,39.889587],"type":"Point"}
}
