{
  "type": "Feature",
  "properties": {
    "iso:country":"US",
    "sg:address":"100 School Ave",
    "sg:city":"New Lexington",
    "sg:classifiers":[
        {
            "category":"Social Services",
            "subcategory":"Child Care",
            "type":"Services"
        }
    ],
    "sg:phone":"+1 740 342 9000",
    "sg:postcode":"43764",
    "sg:province":"OH",
    "wof:name":"Building Blocks Learning Ctr",
    "wof:placetype":"venue"
},
  "geometry": {"coordinates":[-82.207469,39.715306],"type":"Point"}
}