{
  "type": "Feature",
  "properties": {
    "iso:country":"US",
    "sg:address":"1100 S Miami St",
    "sg:city":"West Milton",
    "sg:classifiers":[
        {
            "category":"Organizations",
            "subcategory":"Religious Organization",
            "type":"Services"
        }
    ],
    "sg:phone":"+1 937 698 9376",
    "sg:postcode":"45383",
    "sg:province":"OH",
    "sg:tags":[
        "church"
    ],
    "sg:website":"www.daytonopc.org",
    "wof:name":"Covenant Orthodox Presbyterian",
    "wof:placetype":"venue"
},
  "geometry": {"coordinates":[-84.321074,39.945786],"type":"Point"}
}