{
  "type": "Feature",
  "properties": {
    "iso:country":"US",
    "sg:address":"122 Mount Vernon Ave",
    "sg:city":"Mt Vernon",
    "sg:classifiers":[
        {
            "category":"Health Services",
            "subcategory":"Health Practitioner",
            "type":"Services"
        }
    ],
    "sg:phone":"+1 740 392 0221",
    "sg:postcode":"43050",
    "sg:province":"OH",
    "sg:tags":[
        "audiologists"
    ],
    "wof:name":"Christy Naples Hearing Ctr",
    "wof:placetype":"venue"
},
  "geometry": {"coordinates":[-82.481475,40.384545],"type":"Point"}
}