{
  "type": "Feature",
  "properties": {
    "iso:country":"US",
    "sg:address":"110 Jefferson St",
    "sg:city":"Dexter City",
    "sg:classifiers":[
        {
            "category":"Food & Beverages",
            "subcategory":"Groceries & Convenience Stores",
            "type":"Retail Goods"
        }
    ],
    "sg:phone":"+1 740 783 2125",
    "sg:postcode":"45727",
    "sg:province":"OH",
    "wof:name":"Barlow's Grocery",
    "wof:placetype":"venue"
},
  "geometry": {"coordinates":[-81.473074,39.659754],"type":"Point"}
}