{
  "type": "Feature",
  "properties": {
    "addr:full": "21 E Main St Columbus OH 43215",
    "addr:housenumber": "21",
    "addr:postcode": "43215",
    "addr:street": "E Main St",
    "iso:country": "US",
    "sg:address": "21 E Main St",
    "sg:city": "Columbus",
    "sg:classifiers": [
      {
        "category": "Arts \u0026 Performance",
        "subcategory": "Theater",
        "type": "Entertainment"
      }
    ],
    "sg:phone": "+1 614 340 1896",
    "sg:postcode": "43215",
    "sg:province": "OH",
    "wof:name": "Southern Theatre Capa",
    "wof:placetype": "venue"
  },
  "geometry": {"coordinates":[-82.998992,39.956104],"type":"Point"}
}
