{
  "type": "Feature",
  "properties": {
    "addr:full":"3838 Massillon Rd Uniontown OH 44685",
    "addr:housenumber":"3838",
    "addr:postcode":"44685",
    "addr:street":"Massillon Rd",
    "iso:country":"US",
    "sg:address":"3838 Massillon Rd",
    "sg:city":"Uniontown",
    "sg:classifiers":[
        {
            "category":"Health Services",
            "subcategory":"Chiropractor",
            "type":"Services"
        }
    ],
    "sg:phone":"+1 330 896 2030",
    "sg:postcode":"44685",
    "sg:province":"OH",
    "wof:name":"Fedorko Chiropractic Health",
    "wof:placetype":"venue"
},
  "geometry": {"coordinates":[-81.465636,40.957206],"type":"Point"}
}