{
  "type": "Feature",
  "properties": {
    "addr:full": "183 N High St Chillicothe OH 45601",
    "addr:housenumber": "183",
    "addr:postcode": "45601",
    "addr:street": "N High St",
    "iso:country": "US",
    "sg:address": "183 N High St",
    "sg:city": "Chillicothe",
    "sg:classifiers": [
      {
        "category": "Social Services",
        "subcategory": "Adult Care",
        "type": "Services"
      }
    ],
    "sg:phone": "+1 740 775 4238",
    "sg:postcode": "45601",
    "sg:province": "OH",
    "sg:tags": [
      "residential"
    ],
    "wof:name": "Joyce Baer",
    "wof:placetype": "venue"
  },
  "geometry": {"coordinates":[-82.989011,39.335431],"type":"Point"}
}
