{
  "type": "Feature",
  "properties": {
    "addr:full": "49305 Cadiz-Harrisville Rd Harrisville OH 43974",
    "addr:postcode": "49305;43974",
    "addr:street": "Cadiz-Harrisville Rd",
    "iso:country": "US",
    "sg:address": "49305 Cadiz-Harrisville Rd",
    "sg:city": "Harrisville",
    "sg:classifiers": [
      {
        "category": "Health Services",
        "subcategory": "Doctor",
        "type": "Services"
      }
    ],
    "sg:phone": "+1 740 546 4464",
    "sg:postcode": "43974",
    "sg:province": "OH",
    "sg:tags": [
      "physician",
      "surgeon"
    ],
    "wof:name": "Harrison Community Hospital",
    "wof:placetype": "venue"
  },
  "geometry": {"coordinates":[-80.898421,40.182129],"type":"Point"}
}
