{
  "type": "Feature",
  "properties": {
    "addr:full":"120 Shady Lane Dr Norwalk OH 44857",
    "addr:housenumber":"120",
    "addr:postcode":"44857",
    "addr:street":"Shady Lane Dr",
    "iso:country":"US",
    "sg:address":"120 Shady Lane Dr",
    "sg:city":"Norwalk",
    "sg:classifiers":[
        {
            "category":"Organizations",
            "subcategory":"Non-profit Organization",
            "type":"Services"
        }
    ],
    "sg:phone":"+1 419 668 8387",
    "sg:postcode":"44857",
    "sg:province":"OH",
    "wof:name":"Norwalk Child Care Ctr Inc",
    "wof:placetype":"venue"
},
  "geometry": {"coordinates":[-82.607033,41.225342],"type":"Point"}
}