{
  "type": "Feature",
  "properties": {
    "iso:country":"US",
    "sg:address":"7520 Dudley Ave",
    "sg:city":"Cleveland",
    "sg:classifiers":[
        {
            "category":"Restaurant",
            "type":"Food & Drink"
        }
    ],
    "sg:phone":"+1 216 281 5301",
    "sg:postcode":"44102",
    "sg:province":"OH",
    "sg:tags":[
        "delicatessen"
    ],
    "wof:name":"Nacho's Delicatessen",
    "wof:placetype":"venue"
},
  "geometry": {"coordinates":[-81.736026,41.475164],"type":"Point"}
}