{
  "type": "Feature",
  "properties": {
    "addr:full": "5569 Harwalk Rd NW Strasburg OH 44680",
    "addr:housenumber": "5569",
    "addr:postcode": "44680",
    "addr:street": "Harwalk Rd Nw",
    "iso:country": "US",
    "sg:address": "5569 Harwalk Rd NW",
    "sg:city": "Strasburg",
    "sg:classifiers": [
      {
        "category": "Shopping",
        "subcategory": "Jewelry",
        "type": "Retail Goods"
      }
    ],
    "sg:phone": "+1 330 878 7295",
    "sg:postcode": "44680",
    "sg:province": "OH",
    "wof:name": "Price Enterprise",
    "wof:placetype": "venue"
  },
  "geometry": {"coordinates":[-81.541823,40.617031],"type":"Point"}
}
