{
  "type": "Feature",
  "properties": {
    "iso:country":"US",
    "sg:address":"5569 Harwalk Rd NW",
    "sg:city":"Strasburg",
    "sg:classifiers":[
        {
            "category":"Shopping",
            "subcategory":"Jewelry",
            "type":"Retail Goods"
        }
    ],
    "sg:phone":"+1 330 878 7295",
    "sg:postcode":"44680",
    "sg:province":"OH",
    "wof:name":"Price Enterprise",
    "wof:placetype":"venue"
},
  "geometry": {"coordinates":[-81.54182299999999,40.617031],"type":"Point"}
}