{
  "type": "Feature",
  "properties": {
    "addr:full":"21450 Co Rd 60 Grover Hill OH 45849",
    "addr:housenumber":"21450;60",
    "addr:postcode":"45849",
    "addr:street":"Co Rd",
    "iso:country":"US",
    "sg:address":"21450 Co Rd 60",
    "sg:city":"Grover Hill",
    "sg:classifiers":[
        {
            "category":"Shopping",
            "subcategory":"Bicycles & Sporting Goods",
            "type":"Retail Goods"
        }
    ],
    "sg:phone":"+1 419 587 4000",
    "sg:postcode":"45849",
    "sg:province":"OH",
    "sg:tags":[
        "gun",
        "gunsmith"
    ],
    "wof:name":"Black Swamp Guns & Supplies",
    "wof:placetype":"venue"
},
  "geometry": {"coordinates":[-84.416439,41.04844],"type":"Point"}
}