{
  "type": "Feature",
  "properties": {
    "iso:country":"US",
    "sg:address":"6650 Broadway Ave",
    "sg:city":"Cleveland",
    "sg:classifiers":[
        {
            "category":"Cinema",
            "subcategory":"Movie Rental",
            "type":"Entertainment"
        }
    ],
    "sg:phone":"+1 216 441 1199",
    "sg:postcode":"44105",
    "sg:province":"OH",
    "sg:tags":[
        "leasing",
        "video",
        "disc",
        "tape"
    ],
    "wof:name":"York Video",
    "wof:placetype":"venue"
},
  "geometry": {"coordinates":[-81.643259,41.461698],"type":"Point"}
}