{
  "type": "Feature",
  "properties": {
    "addr:full":"14321 Keirns Rd Millfield OH 45701",
    "addr:housenumber":"14321",
    "addr:postcode":"45701",
    "addr:street":"Keirns Rd",
    "iso:country":"US",
    "sg:address":"14321 Keirns Rd",
    "sg:city":"Millfield",
    "sg:classifiers":[
        {
            "category":"Freight",
            "type":"Transportation"
        }
    ],
    "sg:phone":"+1 740 797 9005",
    "sg:postcode":"45701",
    "sg:province":"OH",
    "wof:name":"CC Transport Inc",
    "wof:placetype":"venue"
},
  "geometry": {"coordinates":[-82.075812,39.413357],"type":"Point"}
}