{
  "type": "Feature",
  "properties": {
    "addr:full":"1118 Race St Cincinnati OH 45202",
    "addr:housenumber":"1118",
    "addr:postcode":"45202",
    "addr:street":"Race St",
    "iso:country":"US",
    "sg:address":"1118 Race St",
    "sg:city":"Cincinnati",
    "sg:classifiers":[
        {
            "category":"Shopping",
            "subcategory":"Gifts & Souvenirs",
            "type":"Retail Goods"
        }
    ],
    "sg:phone":"+1 513 381 5425",
    "sg:postcode":"45202",
    "sg:province":"OH",
    "wof:name":"Just For Kicks Sllng Eclctc St",
    "wof:placetype":"venue"
},
  "geometry": {"coordinates":[-84.516273,39.10786],"type":"Point"}
}