{
  "type": "Feature",
  "properties": {
    "addr:full":"1011 E 2nd St Franklin OH 45005",
    "addr:housenumber":"1011",
    "addr:postcode":"45005",
    "addr:street":"E 2Nd St",
    "iso:country":"US",
    "sg:address":"1011 E 2nd St",
    "sg:city":"Franklin",
    "sg:classifiers":[
        {
            "category":"Autos & Motor Vehicles",
            "subcategory":"Automobile Sales",
            "type":"Retail Goods"
        }
    ],
    "sg:phone":"+1 937 746 0999",
    "sg:postcode":"45005",
    "sg:province":"OH",
    "sg:tags":[
        "car",
        "dealer"
    ],
    "wof:name":"Bill Williams Auto Sales Inc",
    "wof:placetype":"venue"
},
  "geometry": {"coordinates":[-84.28494600000001,39.564033],"type":"Point"}
}