{
  "type": "Feature",
  "properties": {
    "iso:country":"US",
    "sg:address":"1284 Auburn Ave",
    "sg:city":"Barberton",
    "sg:classifiers":[
        {
            "category":"Social Services",
            "subcategory":"Child Care",
            "type":"Services"
        }
    ],
    "sg:phone":"+1 330 706 1361",
    "sg:postcode":"44203",
    "sg:province":"OH",
    "wof:name":"Stephanies Lil Munchkins Daycr",
    "wof:placetype":"venue"
},
  "geometry": {"coordinates":[-81.63497599999999,41.004696],"type":"Point"}
}