{
  "type": "Feature",
  "properties": {
    "addr:full": "1284 Auburn Ave Barberton OH 44203",
    "addr:housenumber": "1284",
    "addr:postcode": "44203",
    "addr:street": "Auburn Ave",
    "iso:country": "US",
    "sg:address": "1284 Auburn Ave",
    "sg:city": "Barberton",
    "sg:classifiers": [
      {
        "category": "Social Services",
        "subcategory": "Child Care",
        "type": "Services"
      }
    ],
    "sg:phone": "+1 330 706 1361",
    "sg:postcode": "44203",
    "sg:province": "OH",
    "wof:name": "Stephanies Lil Munchkins Daycr",
    "wof:placetype": "venue"
  },
  "geometry": {"coordinates":[-81.634976,41.004696],"type":"Point"}
}
