{
  "type": "Feature",
  "properties": {
    "addr:full": "5915 Landerbrook Dr Ste 120 Cleveland OH 44124",
    "addr:housenumber": "5915",
    "addr:postcode": "44124",
    "addr:street": "Landerbrook Dr Ste 120",
    "iso:country": "US",
    "sg:address": "5915 Landerbrook Dr Ste 120",
    "sg:city": "Cleveland",
    "sg:classifiers": [
      {
        "category": "Real Estate",
        "subcategory": "Real Estate Services",
        "type": "Services"
      },
      {
        "category": "Building \u0026 Trades",
        "subcategory": "Construction",
        "type": "Services"
      }
    ],
    "sg:phone": "+1 440 646 1222",
    "sg:postcode": "44124",
    "sg:province": "OH",
    "sg:tags": [
      "management",
      "property",
      "contractor"
    ],
    "sg:website": "www.npointe.com",
    "wof:name": "North Pointe Realty Inc",
    "wof:placetype": "venue"
  },
  "geometry": {"coordinates":[-81.467598,41.504398],"type":"Point"}
}
