{
  "type": "Feature",
  "properties": {
    "addr:full":"2535 Marion Avenue Rd Mansfield OH 44903",
    "addr:housenumber":"2535",
    "addr:postcode":"44903",
    "addr:street":"Marion Avenue Rd",
    "iso:country":"US",
    "sg:address":"2535 Marion Avenue Rd",
    "sg:city":"Mansfield",
    "sg:classifiers":[
        {
            "category":"Farming",
            "subcategory":"Livestock Farm",
            "type":"Manufacturing & Wholesale Goods"
        }
    ],
    "sg:phone":"+1 419 529 9037",
    "sg:postcode":"44903",
    "sg:province":"OH",
    "sg:tags":[
        "equine"
    ],
    "wof:name":"Walnut Valley Farm",
    "wof:placetype":"venue"
},
  "geometry": {"coordinates":[-82.605844,40.720448],"type":"Point"}
}