{
  "type": "Feature",
  "properties": {
    "addr:full":"211 E Clark St Fostoria OH 44830",
    "addr:housenumber":"211",
    "addr:postcode":"44830",
    "addr:street":"E Clark St",
    "iso:country":"US",
    "sg:address":"211 E Clark St",
    "sg:city":"Fostoria",
    "sg:classifiers":[
        {
            "category":"Professional",
            "subcategory":"Secretarial Services",
            "type":"Services"
        }
    ],
    "sg:phone":"+1 419 435 4886",
    "sg:postcode":"44830",
    "sg:province":"OH",
    "sg:tags":[
        "reporting",
        "court"
    ],
    "wof:name":"Dennis A Franklin",
    "wof:placetype":"venue"
},
  "geometry": {"coordinates":[-83.411125,41.145845],"type":"Point"}
}