{
  "type": "Feature",
  "properties": {
    "addr:full": "665 Harcourt Rd Mount Vernon OH 43050",
    "addr:housenumber": "665",
    "addr:postcode": "43050",
    "addr:street": "Harcourt Rd",
    "iso:country": "US",
    "sg:address": "665 Harcourt Rd",
    "sg:city": "Mount Vernon",
    "sg:classifiers": [
      {
        "category": "Home \u0026 Garden",
        "subcategory": "Building Materials",
        "type": "Retail Goods"
      }
    ],
    "sg:phone": "+1 740 397 8400",
    "sg:postcode": "43050",
    "sg:province": "OH",
    "sg:tags": [
      "lumber"
    ],
    "wof:name": "84 Lumber",
    "wof:placetype": "venue"
  },
  "geometry": {"coordinates":[-82.507869,40.37995],"type":"Point"}
}
