{
  "type": "Feature",
  "properties": {
    "addr:full": "170 Twp Hwy 303 A Toronto OH 43964",
    "addr:housenumber": "170",
    "addr:postcode": "43964",
    "addr:street": "Twp Hwy 303 A",
    "iso:country": "US",
    "sg:address": "170 Twp Hwy 303 A",
    "sg:city": "Toronto",
    "sg:classifiers": [
      {
        "category": "Shopping",
        "subcategory": "Computers \u0026 Home Electronics",
        "type": "Retail Goods"
      }
    ],
    "sg:phone": "+1 740 537 2369",
    "sg:postcode": "43964",
    "sg:province": "OH",
    "sg:tags": [
      "software"
    ],
    "wof:name": "Paperless Office Solutions",
    "wof:placetype": "venue"
  },
  "geometry": {"coordinates":[-80.701721,40.525109],"type":"Point"}
}
