{
  "type": "Feature",
  "properties": {
    "addr:full":"30315 Detroit Rd Westlake OH 44145",
    "addr:housenumber":"30315",
    "addr:postcode":"44145",
    "addr:street":"Detroit Rd",
    "iso:country":"US",
    "sg:address":"30315 Detroit Rd",
    "sg:city":"Westlake",
    "sg:classifiers":[
        {
            "category":"Personal",
            "subcategory":"Beauty Salon",
            "type":"Services"
        }
    ],
    "sg:phone":"+1 440 871 6770",
    "sg:postcode":"44145",
    "sg:province":"OH",
    "wof:name":"Best Cuts Inc",
    "wof:placetype":"venue"
},
  "geometry": {"coordinates":[-81.95764,41.462212],"type":"Point"}
}