{
  "type": "Feature",
  "properties": {
    "addr:full": "32125 Solon Rd Cleveland OH 44139",
    "addr:housenumber": "32125",
    "addr:postcode": "44139",
    "addr:street": "Solon Rd",
    "iso:country": "US",
    "sg:address": "32125 Solon Rd",
    "sg:city": "Cleveland",
    "sg:classifiers": [
      {
        "category": "Organizations",
        "subcategory": "Non-profit Organization",
        "type": "Services"
      }
    ],
    "sg:phone": "+1 440 498 1300",
    "sg:postcode": "44139",
    "sg:province": "OH",
    "sg:tags": [
      "charitable",
      "institution"
    ],
    "wof:name": "Patrons-The Arts",
    "wof:placetype": "venue"
  },
  "geometry": {"coordinates":[-81.451529,41.387215],"type":"Point"}
}
