{
  "type": "Feature",
  "properties": {
    "addr:full": "205 Vine Ave NE Warren OH 44483",
    "addr:housenumber": "205",
    "addr:postcode": "44483",
    "addr:street": "Vine Ave Ne",
    "iso:country": "US",
    "sg:address": "205 Vine Ave NE",
    "sg:city": "Warren",
    "sg:classifiers": [
      {
        "category": "Building \u0026 Trades",
        "subcategory": "Construction",
        "type": "Services"
      }
    ],
    "sg:phone": "+1 330 647 3287",
    "sg:postcode": "44483",
    "sg:province": "OH",
    "sg:tags": [
      "hanging",
      "contractor"
    ],
    "wof:name": "Jeff Zampella",
    "wof:placetype": "venue"
  },
  "geometry": {"coordinates":[-80.813869,41.239063],"type":"Point"}
}
