{
  "type": "Feature",
  "properties": {
    "addr:full": "1893 E 55th St Cleveland OH 44103",
    "addr:housenumber": "1893",
    "addr:postcode": "44103",
    "addr:street": "E 55Th St",
    "iso:country": "US",
    "sg:address": "1893 E 55th St",
    "sg:city": "Cleveland",
    "sg:classifiers": [
      {
        "category": "Professional",
        "type": "Services"
      }
    ],
    "sg:phone": "+1 216 391 6324",
    "sg:postcode": "44103",
    "sg:province": "OH",
    "sg:tags": [
      "establishment"
    ],
    "wof:name": "Jordan-Roberts Development",
    "wof:placetype": "venue"
  },
  "geometry": {"coordinates":[-81.651772,41.508238],"type":"Point"}
}
