{
  "type": "Feature",
  "properties": {
    "iso:country":"US",
    "sg:address":"9920 Rosedale-Milford Center Rd",
    "sg:city":"Irwin",
    "sg:classifiers":[
        {
            "category":"Organizations",
            "subcategory":"Religious Organization",
            "type":"Services"
        }
    ],
    "sg:phone":"+1 740 857 1366",
    "sg:postcode":"43029",
    "sg:province":"OH",
    "wof:name":"Conservative Mennonite Bd",
    "wof:placetype":"venue"
},
  "geometry": {"coordinates":[-83.46588,40.092572],"type":"Point"}
}