{
  "type": "Feature",
  "properties": {
    "addr:full": "5248 Camp Run Rd Georgetown OH 45121",
    "addr:housenumber": "5248",
    "addr:postcode": "45121",
    "addr:street": "Camp Run Rd",
    "iso:country": "US",
    "sg:address": "5248 Camp Run Rd",
    "sg:city": "Georgetown",
    "sg:phone": "+1 937 378 3012",
    "sg:postcode": "45121",
    "sg:province": "OH",
    "sg:tags": [
      "farm",
      "corn",
      "tobacco"
    ],
    "wof:name": "Carl Berz",
    "wof:placetype": "venue"
  },
  "geometry": {"coordinates":[-83.876529,38.876341],"type":"Point"}
}
