{
  "type": "Feature",
  "properties": {
    "iso:country":"US",
    "sg:address":"14105 Caves Rd",
    "sg:city":"Novelty",
    "sg:classifiers":[
        {
            "category":"Building & Trades",
            "subcategory":"Construction",
            "type":"Services"
        }
    ],
    "sg:phone":"+1 440 338 5185",
    "sg:postcode":"44072",
    "sg:province":"OH",
    "sg:tags":[
        "house"
    ],
    "wof:name":"Lauge Construction",
    "wof:placetype":"venue"
},
  "geometry": {"coordinates":[-81.36228199999999,41.482077],"type":"Point"}
}