{
  "type": "Feature",
  "properties": {
    "addr:full": "14105 Caves Rd Novelty OH 44072",
    "addr:housenumber": "14105",
    "addr:postcode": "44072",
    "addr:street": "Caves Rd",
    "iso:country": "US",
    "sg:address": "14105 Caves Rd",
    "sg:city": "Novelty",
    "sg:classifiers": [
      {
        "category": "Building \u0026 Trades",
        "subcategory": "Construction",
        "type": "Services"
      }
    ],
    "sg:phone": "+1 440 338 5185",
    "sg:postcode": "44072",
    "sg:province": "OH",
    "sg:tags": [
      "house"
    ],
    "wof:name": "Lauge Construction",
    "wof:placetype": "venue"
  },
  "geometry": {"coordinates":[-81.362282,41.482077],"type":"Point"}
}
