{
  "type": "Feature",
  "properties": {
    "addr:full": "4780 Hinckley Industrial Pkwy Cleveland OH 44109",
    "addr:postcode": "4780;44109",
    "addr:street": "Hinckley Industrial Pkwy",
    "iso:country": "US",
    "sg:address": "4780 Hinckley Industrial Pkwy",
    "sg:city": "Cleveland",
    "sg:classifiers": [
      {
        "category": "Shopping",
        "subcategory": "Gifts \u0026 Souvenirs",
        "type": "Retail Goods"
      }
    ],
    "sg:phone": "+1 216 398 7033",
    "sg:postcode": "44109",
    "sg:province": "OH",
    "sg:tags": [
      "shop"
    ],
    "wof:name": "Norm's At Hinckley",
    "wof:placetype": "venue"
  },
  "geometry": {"coordinates":[-81.681009,41.423287],"type":"Point"}
}
