{
  "type": "Feature",
  "properties": {
    "iso:country":"US",
    "sg:address":"4780 Hinckley Industrial Pkwy",
    "sg:city":"Cleveland",
    "sg:classifiers":[
        {
            "category":"Shopping",
            "subcategory":"Gifts & Souvenirs",
            "type":"Retail Goods"
        }
    ],
    "sg:phone":"+1 216 398 7033",
    "sg:postcode":"44109",
    "sg:province":"OH",
    "sg:tags":[
        "shop"
    ],
    "wof:name":"Norm's At Hinckley",
    "wof:placetype":"venue"
},
  "geometry": {"coordinates":[-81.681009,41.423287],"type":"Point"}
}