{
  "type": "Feature",
  "properties": {
    "addr:full":"1820 Newark Granville Rd Granville OH 43023",
    "addr:housenumber":"1820",
    "addr:postcode":"43023",
    "addr:street":"Newark Granville Rd",
    "iso:country":"US",
    "sg:address":"1820 Newark Granville Rd",
    "sg:city":"Granville",
    "sg:classifiers":[
        {
            "category":"Social Services",
            "subcategory":"Child Care",
            "type":"Services"
        },
        {
            "category":"Education",
            "subcategory":"School",
            "type":"Public Place"
        }
    ],
    "sg:phone":"+1 740 587 2111",
    "sg:postcode":"43023",
    "sg:province":"OH",
    "sg:tags":[
        "kindergarten",
        "academic"
    ],
    "wof:name":"Sonshine School",
    "wof:placetype":"venue"
},
  "geometry": {"coordinates":[-82.49095800000001,40.06275],"type":"Point"}
}