{
  "type": "Feature",
  "properties": {
    "addr:full": "26090 Euclid Ave Cleveland OH 44132",
    "addr:housenumber": "26090",
    "addr:postcode": "44132",
    "addr:street": "Euclid Ave",
    "iso:country": "US",
    "sg:address": "26090 Euclid Ave",
    "sg:city": "Cleveland",
    "sg:classifiers": [
      {
        "category": "Retail",
        "subcategory": "Auto Repair",
        "type": "Services"
      }
    ],
    "sg:phone": "+1 216 261 0100",
    "sg:postcode": "44132",
    "sg:province": "OH",
    "sg:tags": [
      "transmission"
    ],
    "wof:name": "All Engines \u0026 Transmission",
    "wof:placetype": "venue"
  },
  "geometry": {"coordinates":[-81.501541,41.588015],"type":"Point"}
}
