{
  "type": "Feature",
  "properties": {
    "iso:country":"US",
    "sg:address":"26090 Euclid Ave",
    "sg:city":"Cleveland",
    "sg:classifiers":[
        {
            "category":"Retail",
            "subcategory":"Auto Repair",
            "type":"Services"
        }
    ],
    "sg:phone":"+1 216 261 0100",
    "sg:postcode":"44132",
    "sg:province":"OH",
    "sg:tags":[
        "transmission"
    ],
    "wof:name":"All Engines & Transmission",
    "wof:placetype":"venue"
},
  "geometry": {"coordinates":[-81.501541,41.588015],"type":"Point"}
}