{
  "type": "Feature",
  "properties": {
    "addr:full": "105 E Main St Mason OH 45040",
    "addr:housenumber": "105",
    "addr:postcode": "45040",
    "addr:street": "E Main St",
    "iso:country": "US",
    "sg:address": "105 E Main St",
    "sg:city": "Mason",
    "sg:classifiers": [
      {
        "category": "Professional",
        "subcategory": "Art Services",
        "type": "Services"
      }
    ],
    "sg:phone": "+1 513 398 2788",
    "sg:postcode": "45040",
    "sg:province": "OH",
    "sg:tags": [
      "graphic",
      "designer"
    ],
    "wof:name": "Bear Graphics",
    "wof:placetype": "venue"
  },
  "geometry": {"coordinates":[-84.307552,39.360786],"type":"Point"}
}
