{
  "type": "Feature",
  "properties": {
    "addr:full": "3741 E Broad St Columbus OH 43213",
    "addr:housenumber": "3741",
    "addr:postcode": "43213",
    "addr:street": "E Broad St",
    "iso:country": "US",
    "sg:address": "3741 E Broad St",
    "sg:city": "Columbus",
    "sg:classifiers": [
      {
        "category": "Shopping",
        "subcategory": "Shoes",
        "type": "Retail Goods"
      }
    ],
    "sg:phone": "+1 614 338 0824",
    "sg:postcode": "43213",
    "sg:province": "OH",
    "wof:name": "Foot Locker",
    "wof:placetype": "venue"
  },
  "geometry": {"coordinates":[-82.899541,39.973546],"type":"Point"}
}
