{
  "type": "Feature",
  "properties": {
    "addr:full":"8970 Winton Rd Cincinnati OH 45231",
    "addr:housenumber":"8970",
    "addr:postcode":"45231",
    "addr:street":"Winton Rd",
    "iso:country":"US",
    "sg:address":"8970 Winton Rd",
    "sg:city":"Cincinnati",
    "sg:classifiers":[
        {
            "category":"Professional",
            "subcategory":"Lawyer & Legal Services",
            "type":"Services"
        }
    ],
    "sg:phone":"+1 513 721 1200",
    "sg:postcode":"45231",
    "sg:province":"OH",
    "sg:tags":[
        "attorney"
    ],
    "wof:name":"Young Reverman & Mazzei",
    "wof:placetype":"venue"
},
  "geometry": {"coordinates":[-84.511636,39.228133],"type":"Point"}
}