{
  "type": "Feature",
  "properties": {
    "addr:full":"7522 Hamilton Ave Cincinnati OH 45231",
    "addr:housenumber":"7522",
    "addr:postcode":"45231",
    "addr:street":"Hamilton Ave",
    "iso:country":"US",
    "sg:address":"7522 Hamilton Ave",
    "sg:city":"Cincinnati",
    "sg:classifiers":[
        {
            "category":"Banks & Credit Unions",
            "subcategory":"Bank",
            "type":"Services"
        }
    ],
    "sg:phone":"+1 513 521 4881",
    "sg:postcode":"45231",
    "sg:province":"OH",
    "sg:tags":[
        "savings",
        "institution"
    ],
    "wof:name":"Peoples Community Bank",
    "wof:placetype":"venue"
},
  "geometry": {"coordinates":[-84.54813,39.232279],"type":"Point"}
}