{
  "type": "Feature",
  "properties": {
    "iso:country":"US",
    "sg:address":"5590 Cheviot Rd",
    "sg:city":"Cincinnati",
    "sg:classifiers":[
        {
            "category":"Manufacturing",
            "subcategory":"Tools & Machinery",
            "type":"Manufacturing & Wholesale Goods"
        }
    ],
    "sg:phone":"+1 513 741 4410",
    "sg:postcode":"45247",
    "sg:province":"OH",
    "sg:tags":[
        "designed",
        "built"
    ],
    "wof:name":"Henwood Technical Inc",
    "wof:placetype":"venue"
},
  "geometry": {"coordinates":[-84.599199,39.19084],"type":"Point"}
}