{
  "type": "Feature",
  "properties": {
    "addr:full":"410 Hillsdale Dr Sebring OH 44672",
    "addr:housenumber":"410",
    "addr:postcode":"44672",
    "addr:street":"Hillsdale Dr",
    "iso:country":"US",
    "sg:address":"410 Hillsdale Dr",
    "sg:city":"Sebring",
    "sg:classifiers":[
        {
            "category":"Recreation",
            "type":"Entertainment"
        }
    ],
    "sg:phone":"+1 330 938 2037",
    "sg:postcode":"44672",
    "sg:province":"OH",
    "sg:tags":[
        "balloon"
    ],
    "wof:name":"Peter Hawkins/Pleasure Balloon",
    "wof:placetype":"venue"
},
  "geometry": {"coordinates":[-81.015839,40.91575],"type":"Point"}
}