{
  "type": "Feature",
  "properties": {
    "addr:full":"639 W Main St Mc Arthur OH 45651",
    "addr:housenumber":"639",
    "addr:postcode":"45651",
    "addr:street":"W Main St",
    "iso:country":"US",
    "sg:address":"639 W Main St",
    "sg:city":"Mc Arthur",
    "sg:classifiers":[
        {
            "category":"Autos & Motor Vehicles",
            "subcategory":"Automobile Sales",
            "type":"Retail Goods"
        }
    ],
    "sg:phone":"+1 740 596 9696",
    "sg:postcode":"45651",
    "sg:province":"OH",
    "sg:tags":[
        "car",
        "dealer"
    ],
    "wof:name":"Terry Walker Auto Sales",
    "wof:placetype":"venue"
},
  "geometry": {"coordinates":[-82.489603,39.250349],"type":"Point"}
}