{
  "type": "Feature",
  "properties": {
    "iso:country":"US",
    "sg:address":"1120 Bucyrus Rd",
    "sg:city":"Galion",
    "sg:classifiers":[
        {
            "category":"Banks & Credit Unions",
            "subcategory":"Investment Brokerage",
            "type":"Services"
        }
    ],
    "sg:phone":"+1 419 468 9190",
    "sg:postcode":"44833",
    "sg:province":"OH",
    "wof:name":"House Of Investment",
    "wof:placetype":"venue"
},
  "geometry": {"coordinates":[-82.814232,40.736085],"type":"Point"}
}