{
  "type": "Feature",
  "properties": {
    "iso:country":"US",
    "sg:address":"41452 School Lot Acl Rd",
    "sg:city":"Albany",
    "sg:classifiers":[
        {
            "category":"Restaurant",
            "type":"Food & Drink"
        }
    ],
    "sg:phone":"+1 740 594 7111",
    "sg:postcode":"45710",
    "sg:province":"OH",
    "sg:tags":[
        "eating"
    ],
    "wof:name":"Firehouse Pizza",
    "wof:placetype":"venue"
},
  "geometry": {"coordinates":[-82.236061,39.177075],"type":"Point"}
}