{
  "type": "Feature",
  "properties": {
    "iso:country":"US",
    "sg:address":"511 E Spring St",
    "sg:city":"St Marys",
    "sg:classifiers":[
        {
            "category":"Organizations",
            "subcategory":"Religious Organization",
            "type":"Services"
        }
    ],
    "sg:phone":"+1 419 394 5050",
    "sg:postcode":"45885",
    "sg:province":"OH",
    "sg:tags":[
        "elementary",
        "school",
        "church"
    ],
    "wof:name":"Holy Rosary Church",
    "wof:placetype":"venue"
},
  "geometry": {"coordinates":[-84.38256,40.545281],"type":"Point"}
}