{
  "type": "Feature",
  "properties": {
    "addr:full":"1607 E Kemper Rd Cincinnati OH 45246",
    "addr:housenumber":"1607",
    "addr:postcode":"45246",
    "addr:street":"E Kemper Rd",
    "iso:country":"US",
    "sg:address":"1607 E Kemper Rd",
    "sg:city":"Cincinnati",
    "sg:classifiers":[
        {
            "category":"Restaurant",
            "type":"Food & Drink"
        }
    ],
    "sg:menulink":"http://www.allmenus.com/oh/sharonville/213106-taco-bell/menu/",
    "sg:phone":"+1 513 772 3290",
    "sg:postcode":"45246",
    "sg:province":"OH",
    "sg:tags":[
        "mexican"
    ],
    "wof:name":"Taco Bell",
    "wof:placetype":"venue"
},
  "geometry": {"coordinates":[-84.445705,39.285188],"type":"Point"}
}