{
  "type": "Feature",
  "properties": {
    "iso:country":"US",
    "sg:address":"7640 Hub Pkwy",
    "sg:city":"Cleveland",
    "sg:classifiers":[
        {
            "category":"Wholesale",
            "subcategory":"Machinery & Supplies",
            "type":"Manufacturing & Wholesale Goods"
        }
    ],
    "sg:phone":"+1 216 642 5455",
    "sg:postcode":"44125",
    "sg:province":"OH",
    "sg:tags":[
        "exhaust",
        "fan"
    ],
    "wof:name":"Copperfield Chimney Supply",
    "wof:placetype":"venue"
},
  "geometry": {"coordinates":[-81.588858,41.36409],"type":"Point"}
}