{
  "type": "Feature",
  "properties": {
    "addr:full": "17740 Buckland Holden Rd Wapakoneta OH 45895",
    "addr:housenumber": "17740",
    "addr:postcode": "45895",
    "addr:street": "Buckland Holden Rd",
    "iso:country": "US",
    "sg:address": "17740 Buckland Holden Rd",
    "sg:city": "Wapakoneta",
    "sg:phone": "+1 419 738 8337",
    "sg:postcode": "45895",
    "sg:province": "OH",
    "sg:tags": [
      "farm",
      "grain",
      "cash"
    ],
    "wof:name": "M \u0026 J Farms",
    "wof:placetype": "venue"
  },
  "geometry": {"coordinates":[-84.10854,40.628995],"type":"Point"}
}
