{
  "type": "Feature",
  "properties": {
    "addr:full": "500 W Main St Fairborn OH 45324",
    "addr:housenumber": "500",
    "addr:postcode": "45324",
    "addr:street": "W Main St",
    "iso:country": "US",
    "sg:address": "500 W Main St",
    "sg:city": "Fairborn",
    "sg:classifiers": [
      {
        "category": "Food \u0026 Beverages",
        "subcategory": "Groceries \u0026 Convenience Stores",
        "type": "Retail Goods"
      },
      {
        "category": "Food \u0026 Beverages",
        "subcategory": "Specialty",
        "type": "Retail Goods"
      }
    ],
    "sg:phone": "+1 937 878 6102",
    "sg:postcode": "45324",
    "sg:province": "OH",
    "sg:tags": [
      "product",
      "oriental"
    ],
    "wof:name": "Dong Yang Oriental Food \u0026 Gift",
    "wof:placetype": "venue"
  },
  "geometry": {"coordinates":[-84.027689,39.821956],"type":"Point"}
}
