{
  "type": "Feature",
  "properties": {
    "iso:country":"US",
    "sg:address":"500 W Main St",
    "sg:city":"Fairborn",
    "sg:classifiers":[
        {
            "category":"Food & Beverages",
            "subcategory":"Groceries & Convenience Stores",
            "type":"Retail Goods"
        },
        {
            "category":"Food & Beverages",
            "subcategory":"Specialty",
            "type":"Retail Goods"
        }
    ],
    "sg:phone":"+1 937 878 6102",
    "sg:postcode":"45324",
    "sg:province":"OH",
    "sg:tags":[
        "product",
        "oriental"
    ],
    "wof:name":"Dong Yang Oriental Food & Gift",
    "wof:placetype":"venue"
},
  "geometry": {"coordinates":[-84.027689,39.821956],"type":"Point"}
}