{
  "type": "Feature",
  "properties": {
    "addr:full":"1455 W Sylvania Ave Toledo OH 43612",
    "addr:housenumber":"1455",
    "addr:postcode":"43612",
    "addr:street":"W Sylvania Ave",
    "iso:country":"US",
    "sg:address":"1455 W Sylvania Ave",
    "sg:city":"Toledo",
    "sg:classifiers":[
        {
            "category":"Building & Trades",
            "subcategory":"Plumbing",
            "type":"Services"
        }
    ],
    "sg:phone":"+1 419 478 2804",
    "sg:postcode":"43612",
    "sg:province":"OH",
    "sg:tags":[
        "conditioning",
        "air",
        "system",
        "contractor"
    ],
    "wof:name":"Independent Heating & Air Cond",
    "wof:placetype":"venue"
},
  "geometry": {"coordinates":[-83.577507,41.692288],"type":"Point"}
}