{
  "type": "Feature",
  "properties": {
    "iso:country":"US",
    "sg:address":"1201 S Main St",
    "sg:city":"Canton",
    "sg:classifiers":[
        {
            "category":"Building & Trades",
            "subcategory":"Construction",
            "type":"Services"
        }
    ],
    "sg:phone":"+1 330 497 8686",
    "sg:postcode":"44720",
    "sg:province":"OH",
    "sg:tags":[
        "res",
        "dev",
        "contractor",
        "comm",
        "real estate"
    ],
    "wof:name":"Lemmon & Lemmon Inc",
    "wof:placetype":"venue"
},
  "geometry": {"coordinates":[-81.397415,40.865221],"type":"Point"}
}