{
  "type": "Feature",
  "properties": {
    "addr:full": "1201 S Main St Canton OH 44720",
    "addr:housenumber": "1201",
    "addr:postcode": "44720",
    "addr:street": "S Main St",
    "iso:country": "US",
    "sg:address": "1201 S Main St",
    "sg:city": "Canton",
    "sg:classifiers": [
      {
        "category": "Building \u0026 Trades",
        "subcategory": "Construction",
        "type": "Services"
      }
    ],
    "sg:phone": "+1 330 497 8686",
    "sg:postcode": "44720",
    "sg:province": "OH",
    "sg:tags": [
      "res",
      "dev",
      "contractor",
      "comm",
      "real estate"
    ],
    "wof:name": "Lemmon \u0026 Lemmon Inc",
    "wof:placetype": "venue"
  },
  "geometry": {"coordinates":[-81.397415,40.865221],"type":"Point"}
}
