{
  "type": "Feature",
  "properties": {
    "addr:full": "55 Wood St Mansfield OH 44903",
    "addr:housenumber": "55",
    "addr:postcode": "44903",
    "addr:street": "Wood St",
    "iso:country": "US",
    "sg:address": "55 Wood St",
    "sg:city": "Mansfield",
    "sg:classifiers": [
      {
        "category": "Health Services",
        "subcategory": "Nursing And Care Facility",
        "type": "Services"
      }
    ],
    "sg:phone": "+1 419 774 5156",
    "sg:postcode": "44903",
    "sg:province": "OH",
    "sg:tags": [
      "home",
      "retirement",
      "community"
    ],
    "wof:name": "Robert Sturges Memorial Homes",
    "wof:placetype": "venue"
  },
  "geometry": {"coordinates":[-82.526079,40.757266],"type":"Point"}
}
