{
  "type": "Feature",
  "properties": {
    "addr:full": "42880 State Rte 7 Newport OH 45783",
    "addr:housenumber": "42880",
    "addr:postcode": "45783",
    "addr:street": "State Rte 7",
    "iso:country": "US",
    "sg:address": "42880 State Rte 7",
    "sg:city": "Newport",
    "sg:classifiers": [
      {
        "category": "Mining \u0026 Drilling",
        "type": "Manufacturing \u0026 Wholesale Goods"
      }
    ],
    "sg:phone": "+1 740 473 1503",
    "sg:postcode": "45783",
    "sg:province": "OH",
    "sg:tags": [
      "development",
      "gas",
      "oil",
      "exploration"
    ],
    "wof:name": "Benjamin Smeltzer Co",
    "wof:placetype": "venue"
  },
  "geometry": {"coordinates":[-81.845372,39.173572],"type":"Point"}
}
