{
  "type": "Feature",
  "properties": {
    "addr:full":"1849 N Belleview Dr Bellbrook OH 45305",
    "addr:housenumber":"1849",
    "addr:postcode":"45305",
    "addr:street":"N Belleview Dr",
    "iso:country":"US",
    "sg:address":"1849 N Belleview Dr",
    "sg:city":"Bellbrook",
    "sg:classifiers":[
        {
            "category":"Professional",
            "subcategory":"Business Services",
            "type":"Services"
        }
    ],
    "sg:phone":"+1 937 848 4817",
    "sg:postcode":"45305",
    "sg:province":"OH",
    "wof:name":"Baby Shoe Bronzing Co",
    "wof:placetype":"venue"
},
  "geometry": {"coordinates":[-84.09432,39.64791],"type":"Point"}
}