{
  "type": "Feature",
  "properties": {
    "addr:full":"5900 Landerbrook Dr Cleveland OH 44124",
    "addr:postcode":"5900;44124",
    "addr:street":"Landerbrook Dr",
    "iso:country":"US",
    "sg:address":"5900 Landerbrook Dr",
    "sg:city":"Cleveland",
    "sg:classifiers":[
        {
            "category":"Professional",
            "subcategory":"Employment Agencies",
            "type":"Services"
        }
    ],
    "sg:phone":"+1 440 684 7218",
    "sg:postcode":"44124",
    "sg:province":"OH",
    "sg:tags":[
        "placement",
        "executive",
        "temporary"
    ],
    "wof:name":"Staffing Solutions Enterprises",
    "wof:placetype":"venue"
},
  "geometry": {"coordinates":[-81.463246,41.505148],"type":"Point"}
}