{
  "type": "Feature",
  "properties": {
    "addr:full": "9191 Youngstown Pittsburgh Rd Youngstown OH 44514",
    "addr:housenumber": "9191",
    "addr:postcode": "44514",
    "addr:street": "Youngstown Pittsburgh Rd",
    "iso:country": "US",
    "sg:address": "9191 Youngstown Pittsburgh Rd",
    "sg:city": "Youngstown",
    "sg:classifiers": [
      {
        "category": "Farming",
        "subcategory": "Livestock Farm",
        "type": "Manufacturing \u0026 Wholesale Goods"
      }
    ],
    "sg:phone": "+1 330 542 0909",
    "sg:postcode": "44514",
    "sg:province": "OH",
    "sg:tags": [
      "equine"
    ],
    "wof:name": "Harold L Hake",
    "wof:placetype": "venue"
  },
  "geometry": {"coordinates":[-80.577149,40.984239],"type":"Point"}
}
