{
  "type": "Feature",
  "properties": {
    "addr:full": "20360 Co Rd X Napoleon OH 43545",
    "addr:housenumber": "20360",
    "addr:postcode": "43545",
    "addr:street": "Co Rd",
    "iso:country": "US",
    "sg:address": "20360 Co Rd X",
    "sg:city": "Napoleon",
    "sg:classifiers": [
      {
        "category": "Personal",
        "type": "Services"
      }
    ],
    "sg:phone": "+1 419 267 5220",
    "sg:postcode": "43545",
    "sg:province": "OH",
    "sg:tags": [
      "therapist",
      "massage"
    ],
    "wof:name": "Relaxations Massage Studio",
    "wof:placetype": "venue"
  },
  "geometry": {"coordinates":[-84.25718,41.437694],"type":"Point"}
}
