{
  "type": "Feature",
  "properties": {
    "iso:country":"US",
    "sg:address":"20360 Co Rd X",
    "sg:city":"Napoleon",
    "sg:classifiers":[
        {
            "category":"Personal",
            "type":"Services"
        }
    ],
    "sg:phone":"+1 419 267 5220",
    "sg:postcode":"43545",
    "sg:province":"OH",
    "sg:tags":[
        "therapist",
        "massage"
    ],
    "wof:name":"Relaxations Massage Studio",
    "wof:placetype":"venue"
},
  "geometry": {"coordinates":[-84.25718000000001,41.437694],"type":"Point"}
}