{
  "type": "Feature",
  "properties": {
    "addr:full": "6100 Dublin Park Dr Dublin OH 43016",
    "addr:housenumber": "6100",
    "addr:postcode": "43016",
    "addr:street": "Dublin Park Dr",
    "iso:country": "US",
    "sg:address": "6100 Dublin Park Dr",
    "sg:city": "Dublin",
    "sg:classifiers": [
      {
        "category": "Recreation",
        "type": "Entertainment"
      }
    ],
    "sg:phone": "+1 614 791 3002",
    "sg:postcode": "43016",
    "sg:province": "OH",
    "sg:tags": [
      "range",
      "practice",
      "golf"
    ],
    "wof:name": "Golf Center At Sports Ohio",
    "wof:placetype": "venue"
  },
  "geometry": {"coordinates":[-83.188531,40.097895],"type":"Point"}
}
