{
  "type": "Feature",
  "properties": {
    "iso:country":"US",
    "sg:address":"6100 Dublin Park Dr",
    "sg:city":"Dublin",
    "sg:classifiers":[
        {
            "category":"Recreation",
            "type":"Entertainment"
        }
    ],
    "sg:phone":"+1 614 791 3002",
    "sg:postcode":"43016",
    "sg:province":"OH",
    "sg:tags":[
        "range",
        "practice",
        "golf"
    ],
    "wof:name":"Golf Center At Sports Ohio",
    "wof:placetype":"venue"
},
  "geometry": {"coordinates":[-83.188531,40.097895],"type":"Point"}
}