{
  "type": "Feature",
  "properties": {
    "addr:full": "2297 Benning Dr Powell OH 43065",
    "addr:housenumber": "2297",
    "addr:postcode": "43065",
    "addr:street": "Benning Dr",
    "iso:country": "US",
    "sg:address": "2297 Benning Dr",
    "sg:city": "Powell",
    "sg:classifiers": [
      {
        "category": "Manufacturing",
        "subcategory": "Retail Goods",
        "type": "Manufacturing \u0026 Wholesale Goods"
      }
    ],
    "sg:phone": "+1 614 889 5222",
    "sg:postcode": "43065",
    "sg:province": "OH",
    "sg:tags": [
      "web",
      "customized",
      "manufacturer"
    ],
    "wof:name": "Customized Creations",
    "wof:placetype": "venue"
  },
  "geometry": {"coordinates":[-83.078927,40.136435],"type":"Point"}
}
