{
  "type": "Feature",
  "properties": {
    "addr:full":"1681 S Washington St Millersburg OH 44654",
    "addr:housenumber":"1681",
    "addr:postcode":"44654",
    "addr:street":"S Washington St",
    "iso:country":"US",
    "sg:address":"1681 S Washington St",
    "sg:city":"Millersburg",
    "sg:classifiers":[
        {
            "category":"Restaurant",
            "type":"Food & Drink"
        }
    ],
    "sg:phone":"+1 330 674 6688",
    "sg:postcode":"44654",
    "sg:province":"OH",
    "sg:tags":[
        "eating"
    ],
    "wof:name":"Pizza Hut",
    "wof:placetype":"venue"
},
  "geometry": {"coordinates":[-81.91701999999999,40.544807],"type":"Point"}
}