{
  "type": "Feature",
  "properties": {
    "iso:country":"US",
    "sg:address":"3091 Carroll-Southern Rd NW",
    "sg:city":"Carroll",
    "sg:classifiers":[
        {
            "category":"Building & Trades",
            "subcategory":"Construction",
            "type":"Services"
        }
    ],
    "sg:phone":"+1 740 756 7081",
    "sg:postcode":"43112",
    "sg:province":"OH",
    "sg:tags":[
        "concrete",
        "contractor"
    ],
    "wof:name":"P J Martins and Sons",
    "wof:placetype":"venue"
},
  "geometry": {"coordinates":[-82.704213,39.773416],"type":"Point"}
}