{
  "type": "Feature",
  "properties": {
    "addr:full": "3091 Carroll-Southern Rd NW Carroll OH 43112",
    "addr:housenumber": "3091",
    "addr:postcode": "43112",
    "addr:street": "Carroll-Southern Rd Nw",
    "iso:country": "US",
    "sg:address": "3091 Carroll-Southern Rd NW",
    "sg:city": "Carroll",
    "sg:classifiers": [
      {
        "category": "Building \u0026 Trades",
        "subcategory": "Construction",
        "type": "Services"
      }
    ],
    "sg:phone": "+1 740 756 7081",
    "sg:postcode": "43112",
    "sg:province": "OH",
    "sg:tags": [
      "concrete",
      "contractor"
    ],
    "wof:name": "P J Martins and Sons",
    "wof:placetype": "venue"
  },
  "geometry": {"coordinates":[-82.704213,39.773416],"type":"Point"}
}
