{
  "type": "Feature",
  "properties": {
    "addr:full": "3573 State Rte 83 Millersburg OH 44654",
    "addr:housenumber": "3573",
    "addr:postcode": "44654",
    "addr:street": "State Rte 83",
    "iso:country": "US",
    "sg:address": "3573 State Rte 83",
    "sg:city": "Millersburg",
    "sg:classifiers": [
      {
        "category": "Manufacturing",
        "subcategory": "Wood Products",
        "type": "Manufacturing \u0026 Wholesale Goods"
      }
    ],
    "sg:phone": "+1 330 674 3052",
    "sg:postcode": "44654",
    "sg:province": "OH",
    "sg:tags": [
      "mfg"
    ],
    "wof:name": "In House Pallet Management LLC",
    "wof:placetype": "venue"
  },
  "geometry": {"coordinates":[-81.910631,40.508963],"type":"Point"}
}
