{
  "type": "Feature",
  "properties": {
    "iso:country":"US",
    "sg:address":"3573 State Rte 83",
    "sg:city":"Millersburg",
    "sg:classifiers":[
        {
            "category":"Manufacturing",
            "subcategory":"Wood Products",
            "type":"Manufacturing & Wholesale Goods"
        }
    ],
    "sg:phone":"+1 330 674 3052",
    "sg:postcode":"44654",
    "sg:province":"OH",
    "sg:tags":[
        "mfg"
    ],
    "wof:name":"In House Pallet Management LLC",
    "wof:placetype":"venue"
},
  "geometry": {"coordinates":[-81.910631,40.508963],"type":"Point"}
}