{
  "type": "Feature",
  "properties": {
    "addr:full": "46 E Crescentville Rd Cincinnati OH 45246",
    "addr:housenumber": "46",
    "addr:postcode": "45246",
    "addr:street": "E Crescentville Rd",
    "iso:country": "US",
    "sg:address": "46 E Crescentville Rd",
    "sg:city": "Cincinnati",
    "sg:classifiers": [
      {
        "category": "Restaurant",
        "type": "Food \u0026 Drink"
      }
    ],
    "sg:phone": "+1 513 671 3080",
    "sg:postcode": "45246",
    "sg:province": "OH",
    "sg:tags": [
      "eating"
    ],
    "wof:name": "Quiznos Tri County",
    "wof:placetype": "venue"
  },
  "geometry": {"coordinates":[-84.463084,39.302603],"type":"Point"}
}
