{
  "type": "Feature",
  "properties": {
    "addr:full": "5350 Mast Rd Duncan Falls OH 43734",
    "addr:housenumber": "5350",
    "addr:postcode": "43734",
    "addr:street": "Mast Rd",
    "iso:country": "US",
    "sg:address": "5350 Mast Rd",
    "sg:city": "Duncan Falls",
    "sg:classifiers": [
      {
        "category": "Building \u0026 Trades",
        "subcategory": "Construction",
        "type": "Services"
      }
    ],
    "sg:phone": "+1 740 674 6607",
    "sg:postcode": "43734",
    "sg:province": "OH",
    "sg:tags": [
      "excavation",
      "excavating",
      "contractor"
    ],
    "wof:name": "Nite Owl Excavating Ltd",
    "wof:placetype": "venue"
  },
  "geometry": {"coordinates":[-81.894725,39.890799],"type":"Point"}
}
