{
  "type": "Feature",
  "properties": {
    "addr:full": "310 Osborne Dr Fairfield OH 45014",
    "addr:housenumber": "310",
    "addr:postcode": "45014",
    "addr:street": "Osborne Dr",
    "iso:country": "US",
    "sg:address": "310 Osborne Dr",
    "sg:city": "Fairfield",
    "sg:classifiers": [
      {
        "category": "Manufacturing",
        "subcategory": "Metals",
        "type": "Manufacturing \u0026 Wholesale Goods"
      }
    ],
    "sg:phone": "+1 513 896 1112",
    "sg:postcode": "45014",
    "sg:province": "OH",
    "sg:tags": [
      "coating"
    ],
    "wof:name": "Carboline",
    "wof:placetype": "venue"
  },
  "geometry": {"coordinates":[-84.498176,39.333127],"type":"Point"}
}
