{
  "type": "Feature",
  "properties": {
    "addr:full": "1479 Taylor Corners Cir Blacklick OH 43004",
    "addr:housenumber": "1479",
    "addr:postcode": "43004",
    "addr:street": "Taylor Corners Cir",
    "iso:country": "US",
    "sg:address": "1479 Taylor Corners Cir",
    "sg:city": "Blacklick",
    "sg:classifiers": [
      {
        "category": "Professional",
        "subcategory": "Lawyer \u0026 Legal Services",
        "type": "Services"
      }
    ],
    "sg:phone": "+1 614 759 9599",
    "sg:postcode": "43004",
    "sg:province": "OH",
    "sg:tags": [
      "attorney"
    ],
    "wof:name": "Amy Sue Taylor",
    "wof:placetype": "venue"
  },
  "geometry": {"coordinates":[-82.827632,40.012605],"type":"Point"}
}
