{
  "type": "Feature",
  "properties": {
    "iso:country":"US",
    "sg:address":"19636 Center Ridge Rd",
    "sg:city":"Cleveland",
    "sg:classifiers":[
        {
            "category":"Food & Beverages",
            "subcategory":"Bakery",
            "type":"Retail Goods"
        }
    ],
    "sg:phone":"+1 440 333 2010",
    "sg:postcode":"44116",
    "sg:province":"OH",
    "sg:tags":[
        "baker"
    ],
    "wof:name":"Cakes Plus",
    "wof:placetype":"venue"
},
  "geometry": {"coordinates":[-81.840743,41.465253],"type":"Point"}
}