{
  "type": "Feature",
  "properties": {
    "addr:full":"2326 Brixton Rd Columbus OH 43221",
    "addr:housenumber":"2326",
    "addr:postcode":"43221",
    "addr:street":"Brixton Rd",
    "iso:country":"US",
    "sg:address":"2326 Brixton Rd",
    "sg:city":"Columbus",
    "sg:classifiers":[
        {
            "category":"Shopping",
            "subcategory":"Clothing, Apparel, & Fashions",
            "type":"Retail Goods"
        }
    ],
    "sg:phone":"+1 614 488 8111",
    "sg:postcode":"43221",
    "sg:province":"OH",
    "wof:name":"Covington Collections",
    "wof:placetype":"venue"
},
  "geometry": {"coordinates":[-83.073358,40.011724],"type":"Point"}
}