{
  "type": "Feature",
  "properties": {
    "iso:country":"US",
    "sg:address":"55 Lazelle Rd",
    "sg:city":"Columbus",
    "sg:classifiers":[
        {
            "category":"Health Services",
            "subcategory":"Nursing And Care Facility",
            "type":"Services"
        }
    ],
    "sg:phone":"+1 614 885 3300",
    "sg:postcode":"43240",
    "sg:province":"OH",
    "sg:tags":[
        "skilled"
    ],
    "sg:website":"www.willow-brook.org",
    "wof:name":"Willow Brook Christian Home",
    "wof:placetype":"venue"
},
  "geometry": {"coordinates":[-83.013475,40.136624],"type":"Point"}
}