{
  "type": "Feature",
  "properties": {
    "addr:full": "4580 E Berwald Rd Cleveland OH 44121",
    "addr:housenumber": "4580",
    "addr:postcode": "44121",
    "addr:street": "E Berwald Rd",
    "iso:country": "US",
    "sg:address": "4580 E Berwald Rd",
    "sg:city": "Cleveland",
    "sg:classifiers": [
      {
        "category": "Building \u0026 Trades",
        "subcategory": "Construction",
        "type": "Services"
      }
    ],
    "sg:phone": "+1 216 691 3390",
    "sg:postcode": "44121",
    "sg:province": "OH",
    "sg:tags": [
      "house"
    ],
    "wof:name": "Specialty Rehab",
    "wof:placetype": "venue"
  },
  "geometry": {"coordinates":[-81.518315,41.527318],"type":"Point"}
}
