{
  "type": "Feature",
  "properties": {
    "addr:full":"12 Public Sq Cleveland OH 44113",
    "addr:housenumber":"12",
    "addr:postcode":"44113",
    "addr:street":"Public Sq",
    "iso:country":"US",
    "sg:address":"12 Public Sq",
    "sg:city":"Cleveland",
    "sg:classifiers":[
        {
            "category":"Shopping",
            "subcategory":"Florist",
            "type":"Retail Goods"
        }
    ],
    "sg:phone":"+1 216 344 1004",
    "sg:postcode":"44113",
    "sg:province":"OH",
    "wof:name":"Pat's Flowers On The Square",
    "wof:placetype":"venue"
},
  "geometry": {"coordinates":[-81.69482000000001,41.499692],"type":"Point"}
}