{
  "type": "Feature",
  "properties": {
    "addr:full":"7717 Pinemeadow Ln Cincinnati OH 45224",
    "addr:housenumber":"7717",
    "addr:postcode":"45224",
    "addr:street":"Pinemeadow Ln",
    "iso:country":"US",
    "sg:address":"7717 Pinemeadow Ln",
    "sg:city":"Cincinnati",
    "sg:classifiers":[
        {
            "category":"Wholesale",
            "subcategory":"Electrical",
            "type":"Manufacturing & Wholesale Goods"
        }
    ],
    "sg:phone":"+1 513 521 3925",
    "sg:postcode":"45224",
    "sg:province":"OH",
    "sg:tags":[
        "electronic"
    ],
    "wof:name":"Blaine Stegman Marketing Inc",
    "wof:placetype":"venue"
},
  "geometry": {"coordinates":[-84.52697499999999,39.210685],"type":"Point"}
}