{
  "type": "Feature",
  "properties": {
    "addr:full": "218 Cedar Run Rd Seaman OH 45616",
    "addr:housenumber": "218",
    "addr:postcode": "45616",
    "addr:street": "Cedar Run Rd",
    "iso:country": "US",
    "sg:address": "218 Cedar Run Rd",
    "sg:city": "Seaman",
    "sg:classifiers": [
      {
        "category": "Shopping",
        "subcategory": "Pharmacy",
        "type": "Retail Goods"
      }
    ],
    "sg:phone": "+1 937 386 0049",
    "sg:postcode": "45616",
    "sg:province": "OH",
    "wof:name": "Seaman Pharmacy",
    "wof:placetype": "venue"
  },
  "geometry": {"coordinates":[-83.356791,38.822638],"type":"Point"}
}
