{
  "type": "Feature",
  "properties": {
    "iso:country":"US",
    "sg:address":"29197 Hartley Rd",
    "sg:city":"Salem",
    "sg:classifiers":[
        {
            "category":"Building & Trades",
            "subcategory":"Construction",
            "type":"Services"
        }
    ],
    "sg:phone":"+1 330 537 2627",
    "sg:postcode":"44460",
    "sg:province":"OH",
    "sg:tags":[
        "general",
        "contractor"
    ],
    "wof:name":"Csd Contracting",
    "wof:placetype":"venue"
},
  "geometry": {"coordinates":[-80.954824,40.886134],"type":"Point"}
}