{
  "type": "Feature",
  "properties": {
    "iso:country":"US",
    "sg:address":"331 W 9th St",
    "sg:city":"Dover",
    "sg:classifiers":[
        {
            "category":"Retail",
            "subcategory":"Auto Repair",
            "type":"Services"
        }
    ],
    "sg:phone":"+1 330 364 1066",
    "sg:postcode":"44622",
    "sg:province":"OH",
    "sg:tags":[
        "repairing",
        "automobile"
    ],
    "wof:name":"Buehler Automotive Inc",
    "wof:placetype":"venue"
},
  "geometry": {"coordinates":[-81.486951,40.524814],"type":"Point"}
}