{
  "type": "Feature",
  "properties": {
    "iso:country":"US",
    "sg:address":"2531 N Verity Pkwy",
    "sg:city":"Middletown",
    "sg:classifiers":[
        {
            "category":"Building & Trades",
            "subcategory":"Construction",
            "type":"Services"
        }
    ],
    "sg:phone":"+1 513 422 4316",
    "sg:postcode":"45042",
    "sg:province":"OH",
    "sg:tags":[
        "painter"
    ],
    "wof:name":"William Gilbert Painting",
    "wof:placetype":"venue"
},
  "geometry": {"coordinates":[-84.38002299999999,39.528021],"type":"Point"}
}