{
  "type": "Feature",
  "properties": {
    "iso:country":"US",
    "sg:address":"801 3rd St",
    "sg:city":"Cincinnati",
    "sg:classifiers":[
        {
            "category":"Building & Trades",
            "subcategory":"Construction",
            "type":"Services"
        }
    ],
    "sg:phone":"+1 513 271 1000",
    "sg:postcode":"45215",
    "sg:province":"OH",
    "sg:tags":[
        "fire",
        "restoration",
        "damage"
    ],
    "wof:name":"Home Again Restoration LTD",
    "wof:placetype":"venue"
},
  "geometry": {"coordinates":[-84.440019,39.221079],"type":"Point"}
}