{
  "type": "Feature",
  "properties": {
    "addr:full": "801 3rd St Cincinnati OH 45215",
    "addr:housenumber": "801",
    "addr:postcode": "45215",
    "addr:street": "3Rd St",
    "iso:country": "US",
    "sg:address": "801 3rd St",
    "sg:city": "Cincinnati",
    "sg:classifiers": [
      {
        "category": "Building \u0026 Trades",
        "subcategory": "Construction",
        "type": "Services"
      }
    ],
    "sg:phone": "+1 513 271 1000",
    "sg:postcode": "45215",
    "sg:province": "OH",
    "sg:tags": [
      "fire",
      "restoration",
      "damage"
    ],
    "wof:name": "Home Again Restoration LTD",
    "wof:placetype": "venue"
  },
  "geometry": {"coordinates":[-84.440019,39.221079],"type":"Point"}
}
