{
  "type": "Feature",
  "properties": {
    "iso:country":"US",
    "sg:address":"355 E Pike St",
    "sg:city":"Morrow",
    "sg:classifiers":[
        {
            "category":"Shopping",
            "subcategory":"Hobbies, Toys, & Games",
            "type":"Retail Goods"
        }
    ],
    "sg:phone":"+1 513 899 4531",
    "sg:postcode":"45152",
    "sg:province":"OH",
    "wof:name":"Annas Craft Shop",
    "wof:placetype":"venue"
},
  "geometry": {"coordinates":[-84.122894,39.35507],"type":"Point"}
}