{
  "type": "Feature",
  "properties": {
    "addr:full": "234 N Main St Hudson OH 44236",
    "addr:housenumber": "234",
    "addr:postcode": "44236",
    "addr:street": "N Main St",
    "iso:country": "US",
    "sg:address": "234 N Main St",
    "sg:city": "Hudson",
    "sg:classifiers": [
      {
        "category": "Shopping",
        "subcategory": "Florist",
        "type": "Retail Goods"
      }
    ],
    "sg:phone": "+1 330 650 1837",
    "sg:postcode": "44236",
    "sg:province": "OH",
    "wof:name": "Stems",
    "wof:placetype": "venue"
  },
  "geometry": {"coordinates":[-81.440486,41.244138],"type":"Point"}
}
