{
  "type": "Feature",
  "properties": {
    "addr:full": "29 Lynette Pl S Westerville OH 43081",
    "addr:housenumber": "29",
    "addr:postcode": "43081",
    "addr:street": "Lynette Pl S",
    "iso:country": "US",
    "sg:address": "29 Lynette Pl S",
    "sg:city": "Westerville",
    "sg:classifiers": [
      {
        "category": "Building \u0026 Trades",
        "subcategory": "Construction",
        "type": "Services"
      }
    ],
    "sg:phone": "+1 614 523 0535",
    "sg:postcode": "43081",
    "sg:province": "OH",
    "sg:tags": [
      "heavy"
    ],
    "wof:name": "Clear Cut Tree Co",
    "wof:placetype": "venue"
  },
  "geometry": {"coordinates":[-82.902089,40.124431],"type":"Point"}
}
