{
  "type": "Feature",
  "properties": {
    "addr:full":"1341 Clough Pike Batavia OH 45103",
    "addr:housenumber":"1341",
    "addr:postcode":"45103",
    "addr:street":"Clough Pike",
    "iso:country":"US",
    "sg:address":"1341 Clough Pike",
    "sg:city":"Batavia",
    "sg:classifiers":[
        {
            "category":"Education",
            "subcategory":"School",
            "type":"Public Place"
        }
    ],
    "sg:phone":"+1 513 753 5010",
    "sg:postcode":"45103",
    "sg:province":"OH",
    "wof:name":"Amelia Middle School",
    "wof:placetype":"venue"
},
  "geometry": {"coordinates":[-84.234776,39.064756],"type":"Point"}
}