{
  "type": "Feature",
  "properties": {
    "addr:full": "7428 Chillicothe Rd Mentor OH 44060",
    "addr:housenumber": "7428",
    "addr:postcode": "44060",
    "addr:street": "Chillicothe Rd",
    "iso:country": "US",
    "sg:address": "7428 Chillicothe Rd",
    "sg:city": "Mentor",
    "sg:classifiers": [
      {
        "category": "Food \u0026 Beverages",
        "subcategory": "Candy",
        "type": "Retail Goods"
      }
    ],
    "sg:phone": "+1 440 974 6045",
    "sg:postcode": "44060",
    "sg:province": "OH",
    "sg:tags": [
      "confectionery"
    ],
    "wof:name": "Cady's Candy Corner",
    "wof:placetype": "venue"
  },
  "geometry": {"coordinates":[-81.301757,41.671891],"type":"Point"}
}
