{
  "type": "Feature",
  "properties": {
    "addr:full":"7 Middleton Dr Painesville OH 44077",
    "addr:housenumber":"7",
    "addr:postcode":"44077",
    "addr:street":"Middleton Dr",
    "iso:country":"US",
    "sg:address":"7 Middleton Dr",
    "sg:city":"Painesville",
    "sg:classifiers":[
        {
            "category":"Recreation",
            "type":"Entertainment"
        }
    ],
    "sg:phone":"+1 440 352 7575",
    "sg:postcode":"44077",
    "sg:province":"OH",
    "sg:tags":[
        "course",
        "golf"
    ],
    "sg:website":"www.buy.com",
    "wof:name":"Buy.Com Greater Cleveland Open",
    "wof:placetype":"venue"
},
  "geometry": {"coordinates":[-81.273107,41.692785],"type":"Point"}
}