{
  "type": "Feature",
  "properties": {
    "iso:country":"US",
    "sg:address":"760 N Trimble Rd",
    "sg:city":"Mansfield",
    "sg:classifiers":[
        {
            "category":"Organizations",
            "subcategory":"Religious Organization",
            "type":"Services"
        }
    ],
    "sg:phone":"+1 419 747 3875",
    "sg:postcode":"44906",
    "sg:province":"OH",
    "sg:tags":[
        "clergy"
    ],
    "wof:name":"Jon Mc Millan",
    "wof:placetype":"venue"
},
  "geometry": {"coordinates":[-82.551834,40.78125],"type":"Point"}
}