{
  "type": "Feature",
  "properties": {
    "iso:country":"US",
    "sg:address":"3955 Brown Park Dr",
    "sg:city":"Hilliard",
    "sg:classifiers":[
        {
            "category":"Health Services",
            "subcategory":"Health Practitioner",
            "type":"Services"
        }
    ],
    "sg:phone":"+1 614 355 8200",
    "sg:postcode":"43026",
    "sg:province":"OH",
    "sg:tags":[
        "therapist",
        "physical"
    ],
    "wof:name":"Children's Hospital",
    "wof:placetype":"venue"
},
  "geometry": {"coordinates":[-83.136527,40.033059],"type":"Point"}
}