{
  "type": "Feature",
  "properties": {
    "addr:full": "4005 Fail Rd La Rue OH 43332",
    "addr:housenumber": "4005",
    "addr:postcode": "43332",
    "addr:street": "Fail Rd",
    "iso:country": "US",
    "sg:address": "4005 Fail Rd",
    "sg:city": "La Rue",
    "sg:phone": "+1 740 499 3371",
    "sg:postcode": "43332",
    "sg:province": "OH",
    "sg:tags": [
      "farm",
      "corn",
      "wheat",
      "soybean"
    ],
    "wof:name": "Norman Walton",
    "wof:placetype": "venue"
  },
  "geometry": {"coordinates":[-83.390636,40.65789],"type":"Point"}
}
