{
  "type": "Feature",
  "properties": {
    "iso:country":"US",
    "sg:address":"11386 Hire Rd",
    "sg:city":"Defiance",
    "sg:phone":"+1 419 395 1988",
    "sg:postcode":"43512",
    "sg:province":"OH",
    "sg:tags":[
        "farm",
        "field",
        "corn",
        "soybean",
        "crop"
    ],
    "wof:name":"Tony Willitzer",
    "wof:placetype":"venue"
},
  "geometry": {"coordinates":[-84.31417999999999,41.272126],"type":"Point"}
}