{
  "type": "Feature",
  "properties": {
    "addr:full": "11386 Hire Rd Defiance OH 43512",
    "addr:postcode": "11386;43512",
    "addr:street": "Hire Rd",
    "iso:country": "US",
    "sg:address": "11386 Hire Rd",
    "sg:city": "Defiance",
    "sg:phone": "+1 419 395 1988",
    "sg:postcode": "43512",
    "sg:province": "OH",
    "sg:tags": [
      "farm",
      "field",
      "corn",
      "soybean",
      "crop"
    ],
    "wof:name": "Tony Willitzer",
    "wof:placetype": "venue"
  },
  "geometry": {"coordinates":[-84.31418,41.272126],"type":"Point"}
}
