{
  "type": "Feature",
  "properties": {
    "addr:full":"6225 Coopermill Rd Zanesville OH 43701",
    "addr:housenumber":"6225",
    "addr:postcode":"43701",
    "addr:street":"Coopermill Rd",
    "iso:country":"US",
    "sg:address":"6225 Coopermill Rd",
    "sg:city":"Zanesville",
    "sg:classifiers":[
        {
            "category":"Farming",
            "subcategory":"Farm",
            "type":"Manufacturing & Wholesale Goods"
        }
    ],
    "sg:phone":"+1 740 452 6812",
    "sg:postcode":"43701",
    "sg:province":"OH",
    "sg:tags":[
        "crop",
        "general"
    ],
    "wof:name":"Carl F Creeks",
    "wof:placetype":"venue"
},
  "geometry": {"coordinates":[-82.111958,39.915869],"type":"Point"}
}