{
  "type": "Feature",
  "properties": {
    "addr:full": "20100 Johnson Rd Marysville OH 43040",
    "addr:housenumber": "20100",
    "addr:postcode": "43040",
    "addr:street": "Johnson Rd",
    "iso:country": "US",
    "sg:address": "20100 Johnson Rd",
    "sg:city": "Marysville",
    "sg:classifiers": [
      {
        "category": "Professional",
        "subcategory": "Business Services",
        "type": "Services"
      }
    ],
    "sg:phone": "+1 937 644 8215",
    "sg:postcode": "43040",
    "sg:province": "OH",
    "wof:name": "Harmony AG Pdts In Ohio",
    "wof:placetype": "venue"
  },
  "geometry": {"coordinates":[-83.499669,40.285258],"type":"Point"}
}
