{
  "type": "Feature",
  "properties": {
    "addr:full": "1235 N Main St Miamisburg OH 45342",
    "addr:housenumber": "1235",
    "addr:postcode": "45342",
    "addr:street": "N Main St",
    "iso:country": "US",
    "sg:address": "1235 N Main St",
    "sg:city": "Miamisburg",
    "sg:classifiers": [
      {
        "category": "Retail",
        "subcategory": "Funeral Services",
        "type": "Services"
      }
    ],
    "sg:phone": "+1 937 866 1001",
    "sg:postcode": "45342",
    "sg:province": "OH",
    "sg:tags": [
      "crematory"
    ],
    "wof:name": "J L Getts \u0026 Co Inc",
    "wof:placetype": "venue"
  },
  "geometry": {"coordinates":[-84.278592,39.655627],"type":"Point"}
}
