{
  "type": "Feature",
  "properties": {
    "iso:country":"US",
    "sg:address":"1235 N Main St",
    "sg:city":"Miamisburg",
    "sg:classifiers":[
        {
            "category":"Retail",
            "subcategory":"Funeral Services",
            "type":"Services"
        }
    ],
    "sg:phone":"+1 937 866 1001",
    "sg:postcode":"45342",
    "sg:province":"OH",
    "sg:tags":[
        "crematory"
    ],
    "wof:name":"J L Getts & Co Inc",
    "wof:placetype":"venue"
},
  "geometry": {"coordinates":[-84.278592,39.655627],"type":"Point"}
}