{
  "type": "Feature",
  "properties": {
    "addr:full":"6070 Highton St SW Navarre OH 44662",
    "addr:postcode":"6070;44662",
    "addr:street":"Highton St Sw",
    "iso:country":"US",
    "sg:address":"6070 Highton St SW",
    "sg:city":"Navarre",
    "sg:classifiers":[
        {
            "category":"Building & Trades",
            "subcategory":"Construction",
            "type":"Services"
        }
    ],
    "sg:phone":"+1 330 837 3351",
    "sg:postcode":"44662",
    "sg:province":"OH",
    "sg:tags":[
        "carpentry",
        "contractor"
    ],
    "wof:name":"Builders Intr Carpentry Svc",
    "wof:placetype":"venue"
},
  "geometry": {"coordinates":[-81.469793,40.746958],"type":"Point"}
}