{
  "type": "Feature",
  "properties": {
    "addr:full": "502 S 4th St Ironton OH 45638",
    "addr:housenumber": "502",
    "addr:postcode": "45638",
    "addr:street": "S 4Th St",
    "iso:country": "US",
    "sg:address": "502 S 4th St",
    "sg:city": "Ironton",
    "sg:classifiers": [
      {
        "category": "Restaurant",
        "type": "Food \u0026 Drink"
      }
    ],
    "sg:menulink": "http://www.allmenus.com/oh/upper/86330-little-caesars-pizza/menu/",
    "sg:phone": "+1 304 736 6658",
    "sg:postcode": "45638",
    "sg:province": "OH",
    "sg:tags": [
      "american",
      "pizza"
    ],
    "wof:name": "Little Caesar's Pizza",
    "wof:placetype": "venue"
  },
  "geometry": {"coordinates":[-82.682118,38.53286],"type":"Point"}
}
