{
  "type": "Feature",
  "properties": {
    "addr:full":"12655 Cedar Rd Cleveland OH 44106",
    "addr:housenumber":"12655",
    "addr:postcode":"44106",
    "addr:street":"Cedar Rd",
    "iso:country":"US",
    "sg:address":"12655 Cedar Rd",
    "sg:city":"Cleveland",
    "sg:classifiers":[
        {
            "category":"Real Estate",
            "subcategory":"Real Estate Agent",
            "type":"Services"
        }
    ],
    "sg:phone":"+1 216 321 6667",
    "sg:postcode":"44106",
    "sg:province":"OH",
    "wof:name":"G & Z Real Estate LLC",
    "wof:placetype":"venue"
},
  "geometry": {"coordinates":[-81.58376,41.501198],"type":"Point"}
}