{
  "type": "Feature",
  "properties": {
    "addr:full": "7810 E Main St Reynoldsburg OH 43068",
    "addr:housenumber": "7810",
    "addr:postcode": "43068",
    "addr:street": "E Main St",
    "iso:country": "US",
    "sg:address": "7810 E Main St",
    "sg:city": "Reynoldsburg",
    "sg:phone": "+1 614 866 4176",
    "sg:postcode": "43068",
    "sg:province": "OH",
    "sg:tags": [
      "oil"
    ],
    "wof:name": "Earhart Petroleum",
    "wof:placetype": "venue"
  },
  "geometry": {"coordinates":[-82.790853,39.955593],"type":"Point"}
}
