{
  "type": "Feature",
  "properties": {
    "addr:full": "951 Northwest Blvd Columbus OH 43212",
    "addr:housenumber": "951",
    "addr:postcode": "43212",
    "addr:street": "Northwest Blvd",
    "iso:country": "US",
    "sg:address": "951 Northwest Blvd",
    "sg:city": "Columbus",
    "sg:classifiers": [
      {
        "category": "Building \u0026 Trades",
        "subcategory": "Plumbing",
        "type": "Services"
      }
    ],
    "sg:phone": "+1 614 214 4706",
    "sg:postcode": "43212",
    "sg:province": "OH",
    "sg:tags": [
      "heating",
      "contractor"
    ],
    "wof:name": "Salmon's Heating \u0026 Cooling",
    "wof:placetype": "venue"
  },
  "geometry": {"coordinates":[-83.030751,39.978638],"type":"Point"}
}
