{
  "type": "Feature",
  "properties": {
    "iso:country":"US",
    "sg:address":"3500 Coolville Station Rd",
    "sg:city":"Coolville",
    "sg:classifiers":[
        {
            "category":"Professional",
            "type":"Services"
        }
    ],
    "sg:phone":"+1 740 667 6431",
    "sg:postcode":"45723",
    "sg:province":"OH",
    "wof:name":"David Johnson",
    "wof:placetype":"venue"
},
  "geometry": {"coordinates":[-81.785164,39.236526],"type":"Point"}
}