{
  "type": "Feature",
  "properties": {
    "addr:full": "3960 Fulton Grove Rd Cincinnati OH 45245",
    "addr:housenumber": "3960",
    "addr:postcode": "45245",
    "addr:street": "Fulton Grove Rd",
    "iso:country": "US",
    "sg:address": "3960 Fulton Grove Rd",
    "sg:city": "Cincinnati",
    "sg:classifiers": [
      {
        "category": "Building \u0026 Trades",
        "subcategory": "Construction",
        "type": "Services"
      }
    ],
    "sg:phone": "+1 513 241 3075",
    "sg:postcode": "45245",
    "sg:province": "OH",
    "sg:tags": [
      "repair",
      "metal"
    ],
    "wof:name": "Industrial Bldg \u0026 Maint Compan",
    "wof:placetype": "venue"
  },
  "geometry": {"coordinates":[-84.282557,39.064122],"type":"Point"}
}
