{
  "type": "Feature",
  "properties": {
    "iso:country":"US",
    "sg:address":"3960 Fulton Grove Rd",
    "sg:city":"Cincinnati",
    "sg:classifiers":[
        {
            "category":"Building & Trades",
            "subcategory":"Construction",
            "type":"Services"
        }
    ],
    "sg:phone":"+1 513 241 3075",
    "sg:postcode":"45245",
    "sg:province":"OH",
    "sg:tags":[
        "repair",
        "metal"
    ],
    "wof:name":"Industrial Bldg & Maint Compan",
    "wof:placetype":"venue"
},
  "geometry": {"coordinates":[-84.282557,39.064122],"type":"Point"}
}