{
  "type": "Feature",
  "properties": {
    "addr:full":"33608 Saint Sharbel Dr Avon OH 44011",
    "addr:housenumber":"33608",
    "addr:postcode":"44011",
    "addr:street":"Saint Sharbel Dr",
    "iso:country":"US",
    "sg:address":"33608 Saint Sharbel Dr",
    "sg:city":"Avon",
    "sg:classifiers":[
        {
            "category":"Professional",
            "subcategory":"Lawyer & Legal Services",
            "type":"Services"
        }
    ],
    "sg:phone":"+1 440 937 0300",
    "sg:postcode":"44011",
    "sg:province":"OH",
    "sg:tags":[
        "attorney"
    ],
    "wof:name":"Larry E Mc Dougal Co Lpa",
    "wof:placetype":"venue"
},
  "geometry": {"coordinates":[-81.992374,41.425882],"type":"Point"}
}