{
  "type": "Feature",
  "properties": {
    "addr:full":"1800 Linn St Cincinnati OH 45214",
    "addr:housenumber":"1800",
    "addr:postcode":"45214",
    "addr:street":"Linn St",
    "iso:country":"US",
    "sg:address":"1800 Linn St",
    "sg:city":"Cincinnati",
    "sg:classifiers":[
        {
            "category":"Bars & Pubs",
            "type":"Food & Drink"
        }
    ],
    "sg:phone":"+1 513 929 4159",
    "sg:postcode":"45214",
    "sg:province":"OH",
    "wof:name":"Junebug Riverside Bar BQ",
    "wof:placetype":"venue"
},
  "geometry": {"coordinates":[-84.52715000000001,39.116627],"type":"Point"}
}