{
  "type": "Feature",
  "properties": {
    "addr:full": "1730 W 25th St Cleveland OH 44113",
    "addr:housenumber": "1730",
    "addr:postcode": "44113",
    "addr:street": "W 25Th St",
    "iso:country": "US",
    "sg:address": "1730 W 25th St",
    "sg:city": "Cleveland",
    "sg:classifiers": [
      {
        "category": "Health Services",
        "subcategory": "Doctor",
        "type": "Services"
      }
    ],
    "sg:phone": "+1 216 363 2402",
    "sg:postcode": "44113",
    "sg:province": "OH",
    "sg:tags": [
      "physician",
      "surgeon",
      "medical"
    ],
    "wof:name": "Bruce D Long MD",
    "wof:placetype": "venue"
  },
  "geometry": {"coordinates":[-81.706209,41.487854],"type":"Point"}
}
