{
  "type": "Feature",
  "properties": {
    "iso:country":"US",
    "sg:address":"6520 Carnegie Ave",
    "sg:city":"Cleveland",
    "sg:classifiers":[
        {
            "category":"Manufacturing",
            "subcategory":"Apparel",
            "type":"Manufacturing & Wholesale Goods"
        }
    ],
    "sg:phone":"+1 216 881 6534",
    "sg:postcode":"44103",
    "sg:province":"OH",
    "sg:tags":[
        "table",
        "mat",
        "mfg"
    ],
    "wof:name":"Pioneer Table Pad",
    "wof:placetype":"venue"
},
  "geometry": {"coordinates":[-81.645284,41.501567],"type":"Point"}
}