{
  "type": "Feature",
  "properties": {
    "addr:full":"18306 Flamingo Ave Cleveland OH 44135",
    "addr:housenumber":"18306",
    "addr:postcode":"44135",
    "addr:street":"Flamingo Ave",
    "iso:country":"US",
    "sg:address":"18306 Flamingo Ave",
    "sg:city":"Cleveland",
    "sg:classifiers":[
        {
            "category":"Real Estate",
            "subcategory":"Real Estate Agent",
            "type":"Services"
        }
    ],
    "sg:phone":"+1 216 898 9588",
    "sg:postcode":"44135",
    "sg:province":"OH",
    "sg:tags":[
        "appraiser"
    ],
    "wof:name":"Laserdata Appraisal Services",
    "wof:placetype":"venue"
},
  "geometry": {"coordinates":[-81.828597,41.433235],"type":"Point"}
}