{
  "type": "Feature",
  "properties": {
    "addr:full": "3880 Groveport Rd Columbus OH 43207",
    "addr:postcode": "3880;43207",
    "addr:street": "Groveport Rd",
    "iso:country": "US",
    "sg:address": "3880 Groveport Rd",
    "sg:city": "Columbus",
    "sg:classifiers": [
      {
        "category": "Freight",
        "type": "Transportation"
      }
    ],
    "sg:phone": "+1 614 492 8494",
    "sg:postcode": "43207",
    "sg:province": "OH",
    "sg:tags": [
      "warehouse"
    ],
    "wof:name": "Aspen Warehouse",
    "wof:placetype": "venue"
  },
  "geometry": {"coordinates":[-82.955048,39.887863],"type":"Point"}
}
