{
  "type": "Feature",
  "properties": {
    "iso:country":"US",
    "sg:address":"3880 Groveport Rd",
    "sg:city":"Columbus",
    "sg:classifiers":[
        {
            "category":"Freight",
            "type":"Transportation"
        }
    ],
    "sg:phone":"+1 614 492 8494",
    "sg:postcode":"43207",
    "sg:province":"OH",
    "sg:tags":[
        "warehouse"
    ],
    "wof:name":"Aspen Warehouse",
    "wof:placetype":"venue"
},
  "geometry": {"coordinates":[-82.95504800000001,39.887863],"type":"Point"}
}