{
  "type": "Feature",
  "properties": {
    "addr:full": "1616 Coutant Ave Cleveland OH 44107",
    "addr:housenumber": "1616",
    "addr:postcode": "44107",
    "addr:street": "Coutant Ave",
    "iso:country": "US",
    "sg:address": "1616 Coutant Ave",
    "sg:city": "Cleveland",
    "sg:classifiers": [
      {
        "category": "Wholesale",
        "subcategory": "Machinery \u0026 Supplies",
        "type": "Manufacturing \u0026 Wholesale Goods"
      }
    ],
    "sg:phone": "+1 216 521 1190",
    "sg:postcode": "44107",
    "sg:province": "OH",
    "sg:tags": [
      "packing",
      "gasket",
      "mechanical"
    ],
    "sg:website": "www.jnojdisch.com",
    "wof:name": "Jno J Disch Co",
    "wof:placetype": "venue"
  },
  "geometry": {"coordinates":[-81.770404,41.478253],"type":"Point"}
}
