{
  "type": "Feature",
  "properties": {
    "iso:country":"US",
    "sg:address":"1616 Coutant Ave",
    "sg:city":"Cleveland",
    "sg:classifiers":[
        {
            "category":"Wholesale",
            "subcategory":"Machinery & Supplies",
            "type":"Manufacturing & Wholesale Goods"
        }
    ],
    "sg:phone":"+1 216 521 1190",
    "sg:postcode":"44107",
    "sg:province":"OH",
    "sg:tags":[
        "packing",
        "gasket",
        "mechanical"
    ],
    "sg:website":"www.jnojdisch.com",
    "wof:name":"Jno J Disch Co",
    "wof:placetype":"venue"
},
  "geometry": {"coordinates":[-81.770404,41.478253],"type":"Point"}
}