{
  "type": "Feature",
  "properties": {
    "iso:country":"US",
    "sg:address":"675 Oxford St",
    "sg:city":"Columbus",
    "sg:classifiers":[
        {
            "category":"Banks & Credit Unions",
            "subcategory":"Financial Services",
            "type":"Services"
        }
    ],
    "sg:phone":"+1 614 885 2466",
    "sg:postcode":"43085",
    "sg:province":"OH",
    "sg:tags":[
        "investor"
    ],
    "wof:name":"Delaworth Investment Group LLC",
    "wof:placetype":"venue"
},
  "geometry": {"coordinates":[-83.020321,40.087745],"type":"Point"}
}