{
  "type": "Feature",
  "properties": {
    "iso:country":"US",
    "sg:address":"2041 Riverside Dr",
    "sg:city":"Columbus",
    "sg:classifiers":[
        {
            "category":"Professional",
            "subcategory":"Management & Consulting",
            "type":"Services"
        }
    ],
    "sg:phone":"+1 614 488 3165",
    "sg:postcode":"43221",
    "sg:province":"OH",
    "sg:tags":[
        "consultant",
        "business"
    ],
    "wof:name":"K B Ackerman Co",
    "wof:placetype":"venue"
},
  "geometry": {"coordinates":[-83.07508799999999,39.998183],"type":"Point"}
}