{
  "type": "Feature",
  "properties": {
    "addr:full": "4722 Shaker Rd Franklin OH 45005",
    "addr:housenumber": "4722",
    "addr:postcode": "45005",
    "addr:street": "Shaker Rd",
    "iso:country": "US",
    "sg:address": "4722 Shaker Rd",
    "sg:city": "Franklin",
    "sg:classifiers": [
      {
        "category": "Building \u0026 Trades",
        "subcategory": "Construction",
        "type": "Services"
      }
    ],
    "sg:phone": "+1 937 746 3815",
    "sg:postcode": "45005",
    "sg:province": "OH",
    "sg:tags": [
      "house"
    ],
    "wof:name": "Brooks Construction",
    "wof:placetype": "venue"
  },
  "geometry": {"coordinates":[-84.296044,39.514097],"type":"Point"}
}
