{
  "type": "Feature",
  "properties": {
    "iso:country":"US",
    "sg:address":"4722 Shaker Rd",
    "sg:city":"Franklin",
    "sg:classifiers":[
        {
            "category":"Building & Trades",
            "subcategory":"Construction",
            "type":"Services"
        }
    ],
    "sg:phone":"+1 937 746 3815",
    "sg:postcode":"45005",
    "sg:province":"OH",
    "sg:tags":[
        "house"
    ],
    "wof:name":"Brooks Construction",
    "wof:placetype":"venue"
},
  "geometry": {"coordinates":[-84.29604399999999,39.514097],"type":"Point"}
}