{
  "type": "Feature",
  "properties": {
    "iso:country":"US",
    "sg:address":"2050 Midway Dr",
    "sg:city":"Twinsburg",
    "sg:classifiers":[
        {
            "category":"Utilities",
            "subcategory":"Refuse",
            "type":"Services"
        }
    ],
    "sg:phone":"+1 330 405 5454",
    "sg:postcode":"44087",
    "sg:province":"OH",
    "sg:tags":[
        "recycling",
        "metal",
        "processing"
    ],
    "sg:website":"www.deccoalloys.com",
    "wof:name":"Decco Alloys Inc",
    "wof:placetype":"venue"
},
  "geometry": {"coordinates":[-81.464038,41.315454],"type":"Point"}
}