{
  "type": "Feature",
  "properties": {
    "iso:country":"US",
    "sg:address":"3705 Medina Rd",
    "sg:city":"Medina",
    "sg:classifiers":[
        {
            "category":"Retail",
            "subcategory":"Auto Rental",
            "type":"Services"
        }
    ],
    "sg:phone":"+1 330 723 5040",
    "sg:postcode":"44256",
    "sg:province":"OH",
    "sg:tags":[
        "renting",
        "automobile"
    ],
    "wof:name":"Hertz Rent A Car",
    "wof:placetype":"venue"
},
  "geometry": {"coordinates":[-81.81774900000001,41.136679],"type":"Point"}
}