{
  "type": "Feature",
  "properties": {
    "addr:full": "5097 Tippwood Ct Youngstown OH 44512",
    "addr:housenumber": "5097",
    "addr:postcode": "44512",
    "addr:street": "Tippwood Ct",
    "iso:country": "US",
    "sg:address": "5097 Tippwood Ct",
    "sg:city": "Youngstown",
    "sg:classifiers": [
      {
        "category": "Manufacturing",
        "subcategory": "Metals",
        "type": "Manufacturing \u0026 Wholesale Goods"
      }
    ],
    "sg:phone": "+1 330 758 1915",
    "sg:postcode": "44512",
    "sg:province": "OH",
    "sg:tags": [
      "product",
      "plastic",
      "structural",
      "fabrication",
      "mfg"
    ],
    "wof:name": "Contract Mfg \u0026 Engrg Co",
    "wof:placetype": "venue"
  },
  "geometry": {"coordinates":[-80.708447,41.045822],"type":"Point"}
}
