{
  "type": "Feature",
  "properties": {
    "addr:full":"2601 Far Hills Ave Dayton OH 45419",
    "addr:housenumber":"2601",
    "addr:postcode":"45419",
    "addr:street":"Far Hills Ave",
    "iso:country":"US",
    "sg:address":"2601 Far Hills Ave",
    "sg:city":"Dayton",
    "sg:classifiers":[
        {
            "category":"Banks & Credit Unions",
            "subcategory":"Bank",
            "type":"Services"
        }
    ],
    "sg:phone":"+1 937 298 1078",
    "sg:postcode":"45419",
    "sg:province":"OH",
    "wof:name":"PNC",
    "wof:placetype":"venue"
},
  "geometry": {"coordinates":[-84.17068999999999,39.706886],"type":"Point"}
}