{
  "type": "Feature",
  "properties": {
    "iso:country":"US",
    "sg:address":"559 E State St",
    "sg:city":"Athens",
    "sg:classifiers":[
        {
            "category":"Shopping",
            "type":"Retail Goods"
        }
    ],
    "sg:phone":"+1 740 594 7441",
    "sg:postcode":"45701",
    "sg:province":"OH",
    "sg:tags":[
        "merchandise"
    ],
    "wof:name":"Athens Bow Shop",
    "wof:placetype":"venue"
},
  "geometry": {"coordinates":[-82.078659,39.337508],"type":"Point"}
}