{
  "type": "Feature",
  "properties": {
    "iso:country":"US",
    "sg:address":"5919 Sherman Rd",
    "sg:city":"Galena",
    "sg:classifiers":[
        {
            "category":"Building & Trades",
            "subcategory":"Plumbing",
            "type":"Services"
        }
    ],
    "sg:phone":"+1 740 548 4613",
    "sg:postcode":"43021",
    "sg:province":"OH",
    "sg:tags":[
        "contractor"
    ],
    "wof:name":"Newkirk II Inc",
    "wof:placetype":"venue"
},
  "geometry": {"coordinates":[-82.94191499999999,40.253978],"type":"Point"}
}