{
  "type": "Feature",
  "properties": {
    "addr:full":"171 Lakota Ave Akron OH 44319",
    "addr:housenumber":"171",
    "addr:postcode":"44319",
    "addr:street":"Lakota Ave",
    "iso:country":"US",
    "sg:address":"171 Lakota Ave",
    "sg:city":"Akron",
    "sg:classifiers":[
        {
            "category":"Building & Trades",
            "subcategory":"Construction",
            "type":"Services"
        }
    ],
    "sg:phone":"+1 330 645 0972",
    "sg:postcode":"44319",
    "sg:province":"OH",
    "sg:tags":[
        "water",
        "well",
        "drilling"
    ],
    "wof:name":"R H Fowler Well Drilling",
    "wof:placetype":"venue"
},
  "geometry": {"coordinates":[-81.531797,41.00266],"type":"Point"}
}