{
  "type": "Feature",
  "properties": {
    "addr:full":"9296 Van Wert Willshire Rd Van Wert OH 45891",
    "addr:housenumber":"9296",
    "addr:postcode":"45891",
    "addr:street":"Willshire Rd",
    "iso:country":"US",
    "sg:address":"9296 Van Wert Willshire Rd",
    "sg:city":"Van Wert",
    "sg:classifiers":[
        {
            "category":"Home & Garden",
            "subcategory":"Home Furnishings",
            "type":"Retail Goods"
        }
    ],
    "sg:phone":"+1 419 238 4580",
    "sg:postcode":"45891",
    "sg:province":"OH",
    "sg:tags":[
        "stove",
        "cash",
        "heating",
        "equipment",
        "grain",
        "fireplace"
    ],
    "wof:name":"Rural Energy Products LLC",
    "wof:placetype":"venue"
},
  "geometry": {"coordinates":[-84.63737500000001,40.829435],"type":"Point"}
}