{
  "type": "Feature",
  "properties": {
    "addr:full":"3551 Glendale Ave Toledo OH 43614",
    "addr:housenumber":"3551",
    "addr:postcode":"43614",
    "addr:street":"Glendale Ave",
    "iso:country":"US",
    "sg:address":"3551 Glendale Ave",
    "sg:city":"Toledo",
    "sg:classifiers":[
        {
            "category":"Wholesale",
            "subcategory":"Machinery & Supplies",
            "type":"Manufacturing & Wholesale Goods"
        }
    ],
    "sg:phone":"+1 419 389 1262",
    "sg:postcode":"43614",
    "sg:province":"OH",
    "sg:tags":[
        "janitor"
    ],
    "wof:name":"Auburn Supply Co Inc",
    "wof:placetype":"venue"
},
  "geometry": {"coordinates":[-83.627004,41.612408],"type":"Point"}
}