{
  "type": "Feature",
  "properties": {
    "addr:full": "1164 Lloyd Rd Wickliffe OH 44092",
    "addr:housenumber": "1164",
    "addr:postcode": "44092",
    "addr:street": "Lloyd Rd",
    "iso:country": "US",
    "sg:address": "1164 Lloyd Rd",
    "sg:city": "Wickliffe",
    "sg:classifiers": [
      {
        "category": "Home \u0026 Garden",
        "subcategory": "Building Materials",
        "type": "Retail Goods"
      }
    ],
    "sg:phone": "+1 440 585 3580",
    "sg:postcode": "44092",
    "sg:province": "OH",
    "wof:name": "General Drywall",
    "wof:placetype": "venue"
  },
  "geometry": {"coordinates":[-81.483803,41.612146],"type":"Point"}
}
