{
  "type": "Feature",
  "properties": {
    "iso:country":"US",
    "sg:address":"1164 Lloyd Rd",
    "sg:city":"Wickliffe",
    "sg:classifiers":[
        {
            "category":"Home & Garden",
            "subcategory":"Building Materials",
            "type":"Retail Goods"
        }
    ],
    "sg:phone":"+1 440 585 3580",
    "sg:postcode":"44092",
    "sg:province":"OH",
    "wof:name":"General Drywall",
    "wof:placetype":"venue"
},
  "geometry": {"coordinates":[-81.48380299999999,41.612146],"type":"Point"}
}