{
  "type": "Feature",
  "properties": {
    "addr:full": "1148 Lake Point Dr Westerville OH 43082",
    "addr:housenumber": "1148",
    "addr:postcode": "43082",
    "addr:street": "Lake Point Dr",
    "iso:country": "US",
    "sg:address": "1148 Lake Point Dr",
    "sg:city": "Westerville",
    "sg:classifiers": [
      {
        "category": "Building \u0026 Trades",
        "subcategory": "Landscaping Services",
        "type": "Services"
      }
    ],
    "sg:phone": "+1 614 523 2323",
    "sg:postcode": "43082",
    "sg:province": "OH",
    "sg:tags": [
      "landscape"
    ],
    "wof:name": "Earth Tones Landscaping",
    "wof:placetype": "venue"
  },
  "geometry": {"coordinates":[-82.886871,40.14117],"type":"Point"}
}
