{
  "type": "Feature",
  "properties": {
    "addr:full":"4925 Jackman Rd Toledo OH 43613",
    "addr:housenumber":"4925",
    "addr:postcode":"43613",
    "addr:street":"Jackman Rd",
    "iso:country":"US",
    "sg:address":"4925 Jackman Rd",
    "sg:city":"Toledo",
    "sg:classifiers":[
        {
            "category":"Shopping",
            "subcategory":"Department Store",
            "type":"Retail Goods"
        }
    ],
    "sg:phone":"+1 419 473 0742",
    "sg:postcode":"43613",
    "sg:province":"OH",
    "wof:name":"TJ Maxx",
    "wof:placetype":"venue"
},
  "geometry": {"coordinates":[-83.585474,41.704461],"type":"Point"}
}