{
  "type": "Feature",
  "properties": {
    "iso:country":"US",
    "sg:address":"6000 Mahoning Ave",
    "sg:city":"Youngstown",
    "sg:classifiers":[
        {
            "category":"Government",
            "subcategory":"Post Office",
            "type":"Public Place"
        }
    ],
    "sg:phone":"+1 330 799 5061",
    "sg:postcode":"44515",
    "sg:province":"OH",
    "sg:tags":[
        "postal",
        "us"
    ],
    "wof:name":"US Post Office",
    "wof:placetype":"venue"
},
  "geometry": {"coordinates":[-80.775138,41.099669],"type":"Point"}
}