{
  "type": "Feature",
  "properties": {
    "iso:country":"US",
    "sg:address":"4800 W Bath Rd",
    "sg:city":"Akron",
    "sg:classifiers":[
        {
            "category":"Retail",
            "subcategory":"Animal Services",
            "type":"Services"
        }
    ],
    "sg:phone":"+1 330 666 8688",
    "sg:postcode":"44333",
    "sg:province":"OH",
    "wof:name":"Jeanne P Bills",
    "wof:placetype":"venue"
},
  "geometry": {"coordinates":[-81.669403,41.168888],"type":"Point"}
}