{
  "type": "Feature",
  "properties": {
    "iso:country":"US",
    "sg:address":"4420 Cherry Grove Rd",
    "sg:city":"Jamestown",
    "sg:classifiers":[
        {
            "category":"Travel",
            "subcategory":"Travel Agent",
            "type":"Entertainment"
        }
    ],
    "sg:phone":"+1 937 675 3128",
    "sg:postcode":"45335",
    "sg:province":"OH",
    "sg:tags":[
        "operator",
        "tour"
    ],
    "wof:name":"All About Cruises & Tours",
    "wof:placetype":"venue"
},
  "geometry": {"coordinates":[-83.769988,39.678364],"type":"Point"}
}