{
  "type": "Feature",
  "properties": {
    "iso:country":"US",
    "sg:address":"294 Wood Ave SE",
    "sg:city":"Niles",
    "sg:classifiers":[
        {
            "category":"Shopping",
            "subcategory":"Jewelry",
            "type":"Retail Goods"
        }
    ],
    "sg:phone":"+1 330 393 5916",
    "sg:postcode":"44446",
    "sg:province":"OH",
    "sg:tags":[
        "jeweler"
    ],
    "wof:name":"Le Roy's Jewelers",
    "wof:placetype":"venue"
},
  "geometry": {"coordinates":[-80.751886,41.17972],"type":"Point"}
}