{
  "type": "Feature",
  "properties": {
    "addr:full": "1416 Franklin St Toronto OH 43964",
    "addr:housenumber": "1416",
    "addr:postcode": "43964",
    "addr:street": "Franklin St",
    "iso:country": "US",
    "sg:address": "1416 Franklin St",
    "sg:city": "Toronto",
    "sg:classifiers": [
      {
        "category": "Home \u0026 Garden",
        "subcategory": "Household Appliances",
        "type": "Retail Goods"
      },
      {
        "category": "Building \u0026 Trades",
        "subcategory": "Plumbing",
        "type": "Services"
      },
      {
        "category": "Building \u0026 Trades",
        "subcategory": "Construction",
        "type": "Services"
      },
      {
        "category": "Professional",
        "subcategory": "Engineering",
        "type": "Services"
      }
    ],
    "sg:phone": "+1 740 537 3430",
    "sg:postcode": "43964",
    "sg:province": "OH",
    "sg:tags": [
      "plumber",
      "industrial",
      "cleaning",
      "system",
      "purifying",
      "specialty",
      "equipment",
      "heating",
      "contractor",
      "air conditioning",
      "contractors-commercial"
    ],
    "sg:website": "http://find.americanstandardair.com/customer-care-dealer-414020?utm_source=YP\u0026utm_medium=banner\u0026utm_campaign=TL",
    "wof:name": "ROD HENRY \u0026 SONS INC",
    "wof:placetype": "venue"
  },
  "geometry": {"coordinates":[-80.607702,40.452956],"type":"Point"}
}
