{
  "type": "Feature",
  "properties": {
    "iso:country":"US",
    "sg:address":"6632 Providence St",
    "sg:city":"Whitehouse",
    "sg:classifiers":[
        {
            "category":"Organizations",
            "subcategory":"Community Association",
            "type":"Services"
        }
    ],
    "sg:phone":"+1 419 877 0081",
    "sg:postcode":"43571",
    "sg:province":"OH",
    "wof:name":"J D & G Enterprises",
    "wof:placetype":"venue"
},
  "geometry": {"coordinates":[-83.804101,41.519621],"type":"Point"}
}