{
  "type": "Feature",
  "properties": {
    "addr:full": "6632 Providence St Whitehouse OH 43571",
    "addr:housenumber": "6632",
    "addr:postcode": "43571",
    "addr:street": "Providence St",
    "iso:country": "US",
    "sg:address": "6632 Providence St",
    "sg:city": "Whitehouse",
    "sg:classifiers": [
      {
        "category": "Organizations",
        "subcategory": "Community Association",
        "type": "Services"
      }
    ],
    "sg:phone": "+1 419 877 0081",
    "sg:postcode": "43571",
    "sg:province": "OH",
    "wof:name": "J D \u0026 G Enterprises",
    "wof:placetype": "venue"
  },
  "geometry": {"coordinates":[-83.804101,41.519621],"type":"Point"}
}
