{
  "type": "Feature",
  "properties": {
    "addr:full": "1373 Byrd Ave Cincinnati OH 45215",
    "addr:housenumber": "1373",
    "addr:postcode": "45215",
    "addr:street": "Byrd Ave",
    "iso:country": "US",
    "sg:address": "1373 Byrd Ave",
    "sg:city": "Cincinnati",
    "sg:classifiers": [
      {
        "category": "Organizations",
        "subcategory": "Religious Organization",
        "type": "Services"
      }
    ],
    "sg:phone": "+1 513 733 3262",
    "sg:postcode": "45215",
    "sg:province": "OH",
    "sg:tags": [
      "clergy"
    ],
    "wof:name": "Cecil Norman",
    "wof:placetype": "venue"
  },
  "geometry": {"coordinates":[-84.45436,39.240066],"type":"Point"}
}
