{
  "type": "Feature",
  "properties": {
    "addr:full":"4568 Cemetery Rd Hilliard OH 43026",
    "addr:housenumber":"4568",
    "addr:postcode":"43026",
    "addr:street":"Cemetery Rd",
    "iso:country":"US",
    "sg:address":"4568 Cemetery Rd",
    "sg:city":"Hilliard",
    "sg:classifiers":[
        {
            "category":"Restaurant",
            "type":"Food & Drink"
        }
    ],
    "sg:menulink":"http://www.allmenus.com/oh/norwich/70010-cottage-inn-pizza/menu/",
    "sg:phone":"+1 614 777 5450",
    "sg:postcode":"43026",
    "sg:province":"OH",
    "sg:tags":[
        "wrap",
        "american",
        "sandwich",
        "pizza"
    ],
    "wof:name":"Cottage Inn Pizza",
    "wof:placetype":"venue"
},
  "geometry": {"coordinates":[-83.13852199999999,40.032891],"type":"Point"}
}