{
  "type": "Feature",
  "properties": {
    "addr:full": "25973 State Rte 328 New Plymouth OH 45654",
    "addr:housenumber": "25973",
    "addr:postcode": "45654",
    "addr:street": "State Rte 328",
    "iso:country": "US",
    "sg:address": "25973 State Rte 328",
    "sg:city": "New Plymouth",
    "sg:phone": "+1 740 596 5355",
    "sg:postcode": "45654",
    "sg:province": "OH",
    "sg:tags": [
      "farm",
      "field",
      "crop"
    ],
    "wof:name": "Steve Bigham",
    "wof:placetype": "venue"
  },
  "geometry": {"coordinates":[-82.396103,39.346303],"type":"Point"}
}
