{
  "type": "Feature",
  "properties": {
    "addr:full": "19785 State Rd North Royalton OH 44133",
    "addr:housenumber": "19785",
    "addr:postcode": "44133",
    "addr:street": "State Rd",
    "iso:country": "US",
    "sg:address": "19785 State Rd",
    "sg:city": "North Royalton",
    "sg:classifiers": [
      {
        "category": "Building \u0026 Trades",
        "subcategory": "Construction",
        "type": "Services"
      }
    ],
    "sg:phone": "+1 440 230 1545",
    "sg:postcode": "44133",
    "sg:province": "OH",
    "sg:tags": [
      "house"
    ],
    "wof:name": "Aqua Santi Builders Liabil",
    "wof:placetype": "venue"
  },
  "geometry": {"coordinates":[-81.719217,41.278848],"type":"Point"}
}
