{
  "type": "Feature",
  "properties": {
    "addr:full":"850 Brainard Rd Cleveland OH 44143",
    "addr:housenumber":"850",
    "addr:postcode":"44143",
    "addr:street":"Brainard Rd",
    "iso:country":"US",
    "sg:address":"850 Brainard Rd",
    "sg:city":"Cleveland",
    "sg:classifiers":[
        {
            "category":"Professional",
            "subcategory":"Accounting & Tax Preparation",
            "type":"Services"
        },
        {
            "category":"Insurance",
            "subcategory":"Insurance Agent",
            "type":"Services"
        }
    ],
    "sg:phone":"+1 216 291 0050",
    "sg:postcode":"44143",
    "sg:province":"OH",
    "sg:tags":[
        "medical",
        "billing"
    ],
    "wof:name":"Great Lakes Billing Associates",
    "wof:placetype":"venue"
},
  "geometry": {"coordinates":[-81.478009,41.530999],"type":"Point"}
}