{
  "type": "Feature",
  "properties": {
    "addr:full": "3763 N High St Columbus OH 43214",
    "addr:housenumber": "3763",
    "addr:postcode": "43214",
    "addr:street": "N High St",
    "iso:country": "US",
    "sg:address": "3763 N High St",
    "sg:city": "Columbus",
    "sg:classifiers": [
      {
        "category": "Professional",
        "subcategory": "Lawyer \u0026 Legal Services",
        "type": "Services"
      }
    ],
    "sg:phone": "+1 614 784 8882",
    "sg:postcode": "43214",
    "sg:province": "OH",
    "sg:tags": [
      "attorney"
    ],
    "wof:name": "Gerald L King",
    "wof:placetype": "venue"
  },
  "geometry": {"coordinates":[-83.017855,40.038736],"type":"Point"}
}
