{
  "type": "Feature",
  "properties": {
    "addr:full": "2560 Ingleside Ave Cincinnati OH 45206",
    "addr:housenumber": "2560",
    "addr:postcode": "45206",
    "addr:street": "Ingleside Ave",
    "iso:country": "US",
    "sg:address": "2560 Ingleside Ave",
    "sg:city": "Cincinnati",
    "sg:classifiers": [
      {
        "category": "Education",
        "subcategory": "Vocational School",
        "type": "Public Place"
      }
    ],
    "sg:phone": "+1 513 761 3737",
    "sg:postcode": "45206",
    "sg:province": "OH",
    "sg:tags": [
      "processing",
      "datum"
    ],
    "wof:name": "Rdp Services Inc",
    "wof:placetype": "venue"
  },
  "geometry": {"coordinates":[-84.477513,39.12694],"type":"Point"}
}
