{
  "type": "Feature",
  "properties": {
    "addr:full": "13336 Root Rd Columbia Station OH 44028",
    "addr:housenumber": "13336",
    "addr:postcode": "44028",
    "addr:street": "Root Rd",
    "iso:country": "US",
    "sg:address": "13336 Root Rd",
    "sg:city": "Columbia Station",
    "sg:classifiers": [
      {
        "category": "Freight",
        "type": "Transportation"
      }
    ],
    "sg:phone": "+1 440 236 8679",
    "sg:postcode": "44028",
    "sg:province": "OH",
    "sg:tags": [
      "leasing"
    ],
    "wof:name": "Welling Trucking Inc",
    "wof:placetype": "venue"
  },
  "geometry": {"coordinates":[-81.947342,41.320015],"type":"Point"}
}
