{
  "type": "Feature",
  "properties": {
    "iso:country":"US",
    "sg:address":"1216 W Bancroft St",
    "sg:city":"Toledo",
    "sg:classifiers":[
        {
            "category":"Manufacturing",
            "subcategory":"Furniture",
            "type":"Manufacturing & Wholesale Goods"
        }
    ],
    "sg:phone":"+1 419 244 3645",
    "sg:postcode":"43606",
    "sg:province":"OH",
    "sg:tags":[
        "mattress"
    ],
    "wof:name":"Select Mattress",
    "wof:placetype":"venue"
},
  "geometry": {"coordinates":[-83.573171,41.663632],"type":"Point"}
}