{
  "type": "Feature",
  "properties": {
    "addr:full": "45 W Main St Westerville OH 43081",
    "addr:housenumber": "45",
    "addr:postcode": "43081",
    "addr:street": "W Main St",
    "iso:country": "US",
    "sg:address": "45 W Main St",
    "sg:city": "Westerville",
    "sg:classifiers": [
      {
        "category": "Professional",
        "subcategory": "Accounting \u0026 Tax Preparation",
        "type": "Services"
      }
    ],
    "sg:phone": "+1 614 891 1041",
    "sg:postcode": "43081",
    "sg:province": "OH",
    "sg:tags": [
      "accountant"
    ],
    "sg:website": "www.lykins.com",
    "wof:name": "Ron Lykins Inc",
    "wof:placetype": "venue"
  },
  "geometry": {"coordinates":[-82.934316,40.126295],"type":"Point"}
}
