{
  "type": "Feature",
  "properties": {
    "iso:country":"US",
    "sg:address":"14801 Holland Rd",
    "sg:city":"Cleveland",
    "sg:classifiers":[
        {
            "category":"Social Services",
            "subcategory":"Adult Care",
            "type":"Services"
        }
    ],
    "sg:phone":"+1 216 267 0555",
    "sg:postcode":"44142",
    "sg:province":"OH",
    "sg:tags":[
        "residential"
    ],
    "sg:website":"www.sovereignhealthcare.com",
    "wof:name":"North Park Retirement Cmnty",
    "wof:placetype":"venue"
},
  "geometry": {"coordinates":[-81.801424,41.395668],"type":"Point"}
}