{
  "type": "Feature",
  "properties": {
    "addr:full": "177 S Frey Ave West Jefferson OH 43162",
    "addr:housenumber": "177",
    "addr:postcode": "43162",
    "addr:street": "S Frey Ave",
    "iso:country": "US",
    "sg:address": "177 S Frey Ave",
    "sg:city": "West Jefferson",
    "sg:classifiers": [
      {
        "category": "Education",
        "subcategory": "School",
        "type": "Public Place"
      }
    ],
    "sg:phone": "+1 614 879 8345",
    "sg:postcode": "43162",
    "sg:province": "OH",
    "wof:name": "Memorial Middle School",
    "wof:placetype": "venue"
  },
  "geometry": {"coordinates":[-83.271798,39.942085],"type":"Point"}
}
