{
  "type": "Feature",
  "properties": {
    "iso:country":"US",
    "sg:address":"3984 W Harbor Rd",
    "sg:city":"Port Clinton",
    "sg:classifiers":[
        {
            "category":"Recreation",
            "type":"Entertainment"
        }
    ],
    "sg:phone":"+1 419 734 4575",
    "sg:postcode":"43452",
    "sg:province":"OH",
    "sg:tags":[
        "course",
        "golf"
    ],
    "wof:name":"Glow Worm Mini Golf LLC",
    "wof:placetype":"venue"
},
  "geometry": {"coordinates":[-83.010058,41.517674],"type":"Point"}
}