{
  "type": "Feature",
  "properties": {
    "addr:full": "5480 Whipple Ave NW Canton OH 44720",
    "addr:housenumber": "5480",
    "addr:postcode": "44720",
    "addr:street": "Whipple Ave Nw",
    "iso:country": "US",
    "sg:address": "5480 Whipple Ave NW",
    "sg:city": "Canton",
    "sg:classifiers": [
      {
        "category": "Shopping",
        "type": "Retail Goods"
      }
    ],
    "sg:phone": "+1 330 497 5556",
    "sg:postcode": "44720",
    "sg:province": "OH",
    "sg:tags": [
      "phone",
      "cellular"
    ],
    "wof:name": "Cellular International Inc",
    "wof:placetype": "venue"
  },
  "geometry": {"coordinates":[-81.422566,40.860999],"type":"Point"}
}
