{
  "type": "Feature",
  "properties": {
    "addr:full": "10175 Old Orchard Dr Cleveland OH 44141",
    "addr:housenumber": "10175",
    "addr:postcode": "44141",
    "addr:street": "Old Orchard Dr",
    "iso:country": "US",
    "sg:address": "10175 Old Orchard Dr",
    "sg:city": "Cleveland",
    "sg:classifiers": [
      {
        "category": "Wholesale",
        "subcategory": "Durable Goods \u0026 Equipment",
        "type": "Manufacturing \u0026 Wholesale Goods"
      }
    ],
    "sg:phone": "+1 440 526 2023",
    "sg:postcode": "44141",
    "sg:province": "OH",
    "sg:tags": [
      "representative",
      "manufacturer"
    ],
    "wof:name": "WRR Assoc",
    "wof:placetype": "venue"
  },
  "geometry": {"coordinates":[-81.597019,41.286568],"type":"Point"}
}
