{
  "type": "Feature",
  "properties": {
    "iso:country":"US",
    "sg:address":"10175 Old Orchard Dr",
    "sg:city":"Cleveland",
    "sg:classifiers":[
        {
            "category":"Wholesale",
            "subcategory":"Durable Goods & Equipment",
            "type":"Manufacturing & Wholesale Goods"
        }
    ],
    "sg:phone":"+1 440 526 2023",
    "sg:postcode":"44141",
    "sg:province":"OH",
    "sg:tags":[
        "representative",
        "manufacturer"
    ],
    "wof:name":"WRR Assoc",
    "wof:placetype":"venue"
},
  "geometry": {"coordinates":[-81.597019,41.286568],"type":"Point"}
}