{
  "type": "Feature",
  "properties": {
    "addr:full": "3532 Irwin Simpson Rd Mason OH 45040",
    "addr:housenumber": "3532",
    "addr:postcode": "45040",
    "addr:street": "Irwin Simpson Rd",
    "iso:country": "US",
    "sg:address": "3532 Irwin Simpson Rd",
    "sg:city": "Mason",
    "sg:classifiers": [
      {
        "category": "Professional",
        "type": "Services"
      }
    ],
    "sg:phone": "+1 513 229 0484",
    "sg:postcode": "45040",
    "sg:province": "OH",
    "sg:tags": [
      "establishment"
    ],
    "wof:name": "CMF Intl Tchnlgs",
    "wof:placetype": "venue"
  },
  "geometry": {"coordinates":[-84.285262,39.314563],"type":"Point"}
}
