{
  "type": "Feature",
  "properties": {
    "addr:full": "7 Hawthorne St Elyria OH 44035",
    "addr:housenumber": "7",
    "addr:postcode": "44035",
    "addr:street": "Hawthorne St",
    "iso:country": "US",
    "sg:address": "7 Hawthorne St",
    "sg:city": "Elyria",
    "sg:classifiers": [
      {
        "category": "Wholesale",
        "subcategory": "Vending Machines",
        "type": "Manufacturing \u0026 Wholesale Goods"
      }
    ],
    "sg:phone": "+1 440 365 9455",
    "sg:postcode": "44035",
    "sg:province": "OH",
    "sg:tags": [
      "operator"
    ],
    "wof:name": "A 1 American Music Co",
    "wof:placetype": "venue"
  },
  "geometry": {"coordinates":[-82.080334,41.376313],"type":"Point"}
}
