{
  "type": "Feature",
  "properties": {
    "iso:country":"US",
    "sg:address":"7 Hawthorne St",
    "sg:city":"Elyria",
    "sg:classifiers":[
        {
            "category":"Wholesale",
            "subcategory":"Vending Machines",
            "type":"Manufacturing & Wholesale Goods"
        }
    ],
    "sg:phone":"+1 440 365 9455",
    "sg:postcode":"44035",
    "sg:province":"OH",
    "sg:tags":[
        "operator"
    ],
    "wof:name":"A 1 American Music Co",
    "wof:placetype":"venue"
},
  "geometry": {"coordinates":[-82.08033399999999,41.376313],"type":"Point"}
}