{
  "type": "Feature",
  "properties": {
    "addr:full":"3653 Marine Rd Toledo OH 43609",
    "addr:housenumber":"3653",
    "addr:postcode":"43609",
    "addr:street":"Marine Rd",
    "iso:country":"US",
    "sg:address":"3653 Marine Rd",
    "sg:city":"Toledo",
    "sg:classifiers":[
        {
            "category":"Building & Trades",
            "subcategory":"Construction",
            "type":"Services"
        }
    ],
    "sg:phone":"+1 419 389 9551",
    "sg:postcode":"43609",
    "sg:province":"OH",
    "sg:tags":[
        "contractor"
    ],
    "wof:name":"Midwest Waterproofing",
    "wof:placetype":"venue"
},
  "geometry": {"coordinates":[-83.629963,41.629504],"type":"Point"}
}