{
  "type": "Feature",
  "properties": {
    "addr:full":"7949 Stillwell Rd Cincinnati OH 45237",
    "addr:housenumber":"7949",
    "addr:postcode":"45237",
    "addr:street":"Stillwell Rd",
    "iso:country":"US",
    "sg:address":"7949 Stillwell Rd",
    "sg:city":"Cincinnati",
    "sg:classifiers":[
        {
            "category":"Organizations",
            "subcategory":"Religious Organization",
            "type":"Services"
        }
    ],
    "sg:phone":"+1 513 351 7074",
    "sg:postcode":"45237",
    "sg:province":"OH",
    "sg:tags":[
        "clergy"
    ],
    "wof:name":"Daniel T Smith",
    "wof:placetype":"venue"
},
  "geometry": {"coordinates":[-84.45667299999999,39.205545],"type":"Point"}
}