{
  "type": "Feature",
  "properties": {
    "addr:full":"2089 Schenley Dr Columbus OH 43219",
    "addr:housenumber":"2089",
    "addr:postcode":"43219",
    "addr:street":"Schenley Dr",
    "iso:country":"US",
    "sg:address":"2089 Schenley Dr",
    "sg:city":"Columbus",
    "sg:classifiers":[
        {
            "category":"Organizations",
            "subcategory":"Religious Organization",
            "type":"Services"
        }
    ],
    "sg:phone":"+1 614 257 0047",
    "sg:postcode":"43219",
    "sg:province":"OH",
    "sg:tags":[
        "church"
    ],
    "wof:name":"Every Lasting Life Ministries",
    "wof:placetype":"venue"
},
  "geometry": {"coordinates":[-82.950569,40.004853],"type":"Point"}
}