{
  "type": "Feature",
  "properties": {
    "iso:country":"US",
    "sg:address":"7142 Salem Rd",
    "sg:city":"Lewisburg",
    "sg:classifiers":[
        {
            "category":"Home & Garden",
            "subcategory":"Building Materials",
            "type":"Retail Goods"
        }
    ],
    "sg:phone":"+1 937 962 8000",
    "sg:postcode":"45338",
    "sg:province":"OH",
    "sg:tags":[
        "window",
        "door",
        "replacement"
    ],
    "wof:name":"Double Tilt Sash & Door",
    "wof:placetype":"venue"
},
  "geometry": {"coordinates":[-84.520273,39.844358],"type":"Point"}
}