{
  "type": "Feature",
  "properties": {
    "addr:full": "105 Malone Rd Mansfield OH 44907",
    "addr:housenumber": "105",
    "addr:postcode": "44907",
    "addr:street": "Malone Rd",
    "iso:country": "US",
    "sg:address": "105 Malone Rd",
    "sg:city": "Mansfield",
    "sg:classifiers": [
      {
        "category": "Health Services",
        "subcategory": "Doctor",
        "type": "Services"
      }
    ],
    "sg:phone": "+1 419 756 1051",
    "sg:postcode": "44907",
    "sg:province": "OH",
    "sg:tags": [
      "physician",
      "surgeon"
    ],
    "wof:name": "Cornerstone General Surgery",
    "wof:placetype": "venue"
  },
  "geometry": {"coordinates":[-82.512805,40.735445],"type":"Point"}
}
