{
  "type": "Feature",
  "properties": {
    "addr:full":"4410 Rocky River Dr Cleveland OH 44135",
    "addr:housenumber":"4410",
    "addr:postcode":"44135",
    "addr:street":"Rocky River Dr",
    "iso:country":"US",
    "sg:address":"4410 Rocky River Dr",
    "sg:city":"Cleveland",
    "sg:classifiers":[
        {
            "category":"Banks & Credit Unions",
            "subcategory":"Bank",
            "type":"Services"
        }
    ],
    "sg:phone":"+1 216 941 3600",
    "sg:postcode":"44135",
    "sg:province":"OH",
    "sg:tags":[
        "federal"
    ],
    "wof:name":"St Patricks Credit Union",
    "wof:placetype":"venue"
},
  "geometry": {"coordinates":[-81.822323,41.434667],"type":"Point"}
}