{
  "type": "Feature",
  "properties": {
    "addr:full": "531 Orchard Ave Barberton OH 44203",
    "addr:housenumber": "531",
    "addr:postcode": "44203",
    "addr:street": "Orchard Ave",
    "iso:country": "US",
    "sg:address": "531 Orchard Ave",
    "sg:city": "Barberton",
    "sg:classifiers": [
      {
        "category": "Shopping",
        "subcategory": "Catalog Store",
        "type": "Retail Goods"
      }
    ],
    "sg:phone": "+1 330 745 7234",
    "sg:postcode": "44203",
    "sg:province": "OH",
    "sg:tags": [
      "house",
      "mail"
    ],
    "wof:name": "Nautical Products Co",
    "wof:placetype": "venue"
  },
  "geometry": {"coordinates":[-81.594933,41.024815],"type":"Point"}
}
