{
  "type": "Feature",
  "properties": {
    "addr:full": "5777 Chantry Dr Columbus OH 43232",
    "addr:housenumber": "5777",
    "addr:postcode": "43232",
    "addr:street": "Chantry Dr",
    "iso:country": "US",
    "sg:address": "5777 Chantry Dr",
    "sg:city": "Columbus",
    "sg:classifiers": [
      {
        "category": "Shopping",
        "subcategory": "Discount \u0026 Variety Stores",
        "type": "Retail Goods"
      }
    ],
    "sg:phone": "+1 614 863 9201",
    "sg:postcode": "43232",
    "sg:province": "OH",
    "wof:name": "Dollar Tree",
    "wof:placetype": "venue"
  },
  "geometry": {"coordinates":[-82.843732,39.925712],"type":"Point"}
}
