{
  "type": "Feature",
  "properties": {
    "iso:country":"US",
    "sg:address":"830 E Erie St",
    "sg:city":"Painesville",
    "sg:classifiers":[
        {
            "category":"Manufacturing",
            "subcategory":"Metals",
            "type":"Manufacturing & Wholesale Goods"
        }
    ],
    "sg:phone":"+1 440 354 0400",
    "sg:postcode":"44077",
    "sg:province":"OH",
    "sg:tags":[
        "product",
        "primary"
    ],
    "sg:website":"www.eckartamerica.com",
    "wof:name":"Eckart America LP",
    "wof:placetype":"venue"
},
  "geometry": {"coordinates":[-81.233156,41.736758],"type":"Point"}
}