{
  "type": "Feature",
  "properties": {
    "addr:full":"10362 Co Rd 6 Edon OH 43518",
    "addr:housenumber":"10362",
    "addr:postcode":"43518",
    "addr:street":"Co Rd 6",
    "iso:country":"US",
    "sg:address":"10362 Co Rd 6",
    "sg:city":"Edon",
    "sg:phone":"+1 419 272 2769",
    "sg:postcode":"43518",
    "sg:province":"OH",
    "sg:tags":[
        "farm",
        "soybean"
    ],
    "wof:name":"Dave Curry",
    "wof:placetype":"venue"
},
  "geometry": {"coordinates":[-84.71096199999999,41.562434],"type":"Point"}
}