{
  "type": "Feature",
  "properties": {
    "addr:full":"11702 Buckeye Rd Cleveland OH 44120",
    "addr:housenumber":"11702",
    "addr:postcode":"44120",
    "addr:street":"Buckeye Rd",
    "iso:country":"US",
    "sg:address":"11702 Buckeye Rd",
    "sg:city":"Cleveland",
    "sg:classifiers":[
        {
            "category":"Shopping",
            "type":"Retail Goods"
        }
    ],
    "sg:phone":"+1 216 921 1857",
    "sg:postcode":"44120",
    "sg:province":"OH",
    "sg:tags":[
        "african"
    ],
    "wof:name":"Diop Place II",
    "wof:placetype":"venue"
},
  "geometry": {"coordinates":[-81.60192499999999,41.480812],"type":"Point"}
}