{
  "type": "Feature",
  "properties": {
    "iso:country":"US",
    "sg:address":"485 E Exchange St",
    "sg:city":"Akron",
    "sg:classifiers":[
        {
            "category":"Restaurant",
            "type":"Food & Drink"
        }
    ],
    "sg:phone":"+1 330 376 9744",
    "sg:postcode":"44304",
    "sg:province":"OH",
    "sg:tags":[
        "shop",
        "sub"
    ],
    "wof:name":"Subway",
    "wof:placetype":"venue"
},
  "geometry": {"coordinates":[-81.505591,41.071214],"type":"Point"}
}