{
  "type": "Feature",
  "properties": {
    "addr:full": "485 E Exchange St Akron OH 44304",
    "addr:housenumber": "485",
    "addr:postcode": "44304",
    "addr:street": "E Exchange St",
    "iso:country": "US",
    "sg:address": "485 E Exchange St",
    "sg:city": "Akron",
    "sg:classifiers": [
      {
        "category": "Restaurant",
        "type": "Food \u0026 Drink"
      }
    ],
    "sg:phone": "+1 330 376 9744",
    "sg:postcode": "44304",
    "sg:province": "OH",
    "sg:tags": [
      "shop",
      "sub"
    ],
    "wof:name": "Subway",
    "wof:placetype": "venue"
  },
  "geometry": {"coordinates":[-81.505591,41.071214],"type":"Point"}
}
