{
  "type": "Feature",
  "properties": {
    "addr:full":"4645 Dressler Rd NW Canton OH 44720",
    "addr:housenumber":"4645",
    "addr:postcode":"44720",
    "addr:street":"Dressler Rd Nw",
    "iso:country":"US",
    "sg:address":"4645 Dressler Rd NW",
    "sg:city":"Canton",
    "sg:classifiers":[
        {
            "category":"Shopping",
            "type":"Retail Goods"
        }
    ],
    "sg:phone":"+1 330 492 2002",
    "sg:postcode":"44720",
    "sg:province":"OH",
    "sg:tags":[
        "merchandise"
    ],
    "wof:name":"Verizon",
    "wof:placetype":"venue"
},
  "geometry": {"coordinates":[-81.434495,40.848842],"type":"Point"}
}