{
  "type": "Feature",
  "properties": {
    "addr:full":"8801 Ohio River Rd Wheelersburg OH 45694",
    "addr:housenumber":"8801",
    "addr:postcode":"45694",
    "addr:street":"Ohio River Rd",
    "iso:country":"US",
    "sg:address":"8801 Ohio River Rd",
    "sg:city":"Wheelersburg",
    "sg:classifiers":[
        {
            "category":"Restaurant",
            "type":"Food & Drink"
        }
    ],
    "sg:menulink":"http://www.allmenus.com/oh/porter/214824-ponderosa-steak-house/menu/",
    "sg:phone":"+1 740 574 8355",
    "sg:postcode":"45694",
    "sg:province":"OH",
    "sg:tags":[
        "american",
        "steakhouse"
    ],
    "wof:name":"Ponderosa Steak House",
    "wof:placetype":"venue"
},
  "geometry": {"coordinates":[-82.85720600000001,38.716521],"type":"Point"}
}