{
  "type": "Feature",
  "properties": {
    "iso:country":"US",
    "sg:address":"6717 Cleveland Rd",
    "sg:city":"Wooster",
    "sg:classifiers":[
        {
            "category":"Building & Trades",
            "subcategory":"Construction",
            "type":"Services"
        }
    ],
    "sg:phone":"+1 330 345 8321",
    "sg:postcode":"44691",
    "sg:province":"OH",
    "sg:tags":[
        "excavation",
        "excavating",
        "contractor"
    ],
    "wof:name":"Snyder Excavating Inc",
    "wof:placetype":"venue"
},
  "geometry": {"coordinates":[-81.918384,40.885443],"type":"Point"}
}