{
  "type": "Feature",
  "properties": {
    "addr:full": "7589 Sebastian Rd Celina OH 45822",
    "addr:housenumber": "7589",
    "addr:postcode": "45822",
    "addr:street": "Sebastian Rd",
    "iso:country": "US",
    "sg:address": "7589 Sebastian Rd",
    "sg:city": "Celina",
    "sg:classifiers": [
      {
        "category": "Wholesale",
        "subcategory": "Hardware",
        "type": "Manufacturing \u0026 Wholesale Goods"
      }
    ],
    "sg:phone": "+1 419 925 5039",
    "sg:postcode": "45822",
    "sg:province": "OH",
    "wof:name": "Post Clean A \u0026 Wtr Systems LLC",
    "wof:placetype": "venue"
  },
  "geometry": {"coordinates":[-84.509491,40.443453],"type":"Point"}
}
