{
  "type": "Feature",
  "properties": {
    "iso:country":"US",
    "sg:address":"7589 Sebastian Rd",
    "sg:city":"Celina",
    "sg:classifiers":[
        {
            "category":"Wholesale",
            "subcategory":"Hardware",
            "type":"Manufacturing & Wholesale Goods"
        }
    ],
    "sg:phone":"+1 419 925 5039",
    "sg:postcode":"45822",
    "sg:province":"OH",
    "wof:name":"Post Clean A & Wtr Systems LLC",
    "wof:placetype":"venue"
},
  "geometry": {"coordinates":[-84.509491,40.443453],"type":"Point"}
}