{
  "type": "Feature",
  "properties": {
    "iso:country":"US",
    "sg:address":"2105 S Hamilton Rd",
    "sg:city":"Columbus",
    "sg:classifiers":[
        {
            "category":"Building & Trades",
            "subcategory":"Construction",
            "type":"Services"
        }
    ],
    "sg:phone":"+1 614 552 0202",
    "sg:postcode":"43232",
    "sg:province":"OH",
    "sg:tags":[
        "house"
    ],
    "wof:name":"Mae Builders",
    "wof:placetype":"venue"
},
  "geometry": {"coordinates":[-82.87914,39.9325],"type":"Point"}
}