{
  "type": "Feature",
  "properties": {
    "iso:country":"US",
    "sg:address":"1200 Buffalo Rd",
    "sg:city":"Bryan",
    "sg:classifiers":[
        {
            "category":"Wholesale",
            "subcategory":"Scrap",
            "type":"Manufacturing & Wholesale Goods"
        }
    ],
    "sg:phone":"+1 419 636 3382",
    "sg:postcode":"43506",
    "sg:province":"OH",
    "sg:tags":[
        "recycling",
        "center"
    ],
    "wof:name":"Bryan Recycling Ctr",
    "wof:placetype":"venue"
},
  "geometry": {"coordinates":[-84.569993,41.476024],"type":"Point"}
}