{
  "type": "Feature",
  "properties": {
    "addr:full": "8015 Deershadow Ln Cincinnati OH 45242",
    "addr:housenumber": "8015",
    "addr:postcode": "45242",
    "addr:street": "Deershadow Ln",
    "iso:country": "US",
    "sg:address": "8015 Deershadow Ln",
    "sg:city": "Cincinnati",
    "sg:classifiers": [
      {
        "category": "Communications",
        "type": "Services"
      }
    ],
    "sg:phone": "+1 513 984 4865",
    "sg:postcode": "45242",
    "sg:province": "OH",
    "sg:tags": [
      "communication"
    ],
    "wof:name": "Zanger Communications LLC",
    "wof:placetype": "venue"
  },
  "geometry": {"coordinates":[-84.348493,39.258646],"type":"Point"}
}
