{
  "type": "Feature",
  "properties": {
    "addr:full": "3090 State Rte 59 Ravenna OH 44266",
    "addr:housenumber": "3090",
    "addr:postcode": "44266",
    "addr:street": "State Rte 59",
    "iso:country": "US",
    "sg:address": "3090 State Rte 59",
    "sg:city": "Ravenna",
    "sg:classifiers": [
      {
        "category": "Organizations",
        "subcategory": "Community Association",
        "type": "Services"
      }
    ],
    "sg:phone": "+1 330 296 9504",
    "sg:postcode": "44266",
    "sg:province": "OH",
    "sg:tags": [
      "fraternal"
    ],
    "wof:name": "Loyal Order Of Moose",
    "wof:placetype": "venue"
  },
  "geometry": {"coordinates":[-81.282377,41.159113],"type":"Point"}
}
