{
  "type": "Feature",
  "properties": {
    "iso:country":"US",
    "sg:address":"3090 State Rte 59",
    "sg:city":"Ravenna",
    "sg:classifiers":[
        {
            "category":"Organizations",
            "subcategory":"Community Association",
            "type":"Services"
        }
    ],
    "sg:phone":"+1 330 296 9504",
    "sg:postcode":"44266",
    "sg:province":"OH",
    "sg:tags":[
        "fraternal"
    ],
    "wof:name":"Loyal Order Of Moose",
    "wof:placetype":"venue"
},
  "geometry": {"coordinates":[-81.282377,41.159113],"type":"Point"}
}