{
  "type": "Feature",
  "properties": {
    "iso:country":"US",
    "sg:address":"160 S Ardmore Rd",
    "sg:city":"Columbus",
    "sg:classifiers":[
        {
            "category":"Wholesale",
            "subcategory":"Non-durable Goods",
            "type":"Manufacturing & Wholesale Goods"
        }
    ],
    "sg:phone":"+1 614 236 0600",
    "sg:postcode":"43209",
    "sg:province":"OH",
    "sg:tags":[
        "advertising",
        "specialty"
    ],
    "wof:name":"Linda Joffe and Associates",
    "wof:placetype":"venue"
},
  "geometry": {"coordinates":[-82.93162700000001,39.970043],"type":"Point"}
}