{
  "type": "Feature",
  "properties": {
    "iso:country":"US",
    "sg:address":"3637 Green Rd",
    "sg:city":"Cleveland",
    "sg:classifiers":[
        {
            "category":"Banks & Credit Unions",
            "subcategory":"Bank",
            "type":"Services"
        }
    ],
    "sg:phone":"+1 216 464 4611",
    "sg:postcode":"44122",
    "sg:province":"OH",
    "sg:tags":[
        "banker",
        "mortgage"
    ],
    "wof:name":"La Salle Mortgage Company Inc",
    "wof:placetype":"venue"
},
  "geometry": {"coordinates":[-81.51692799999999,41.462806],"type":"Point"}
}