{
  "type": "Feature",
  "properties": {
    "addr:full": "3637 Green Rd Cleveland OH 44122",
    "addr:housenumber": "3637",
    "addr:postcode": "44122",
    "addr:street": "Green Rd",
    "iso:country": "US",
    "sg:address": "3637 Green Rd",
    "sg:city": "Cleveland",
    "sg:classifiers": [
      {
        "category": "Banks \u0026 Credit Unions",
        "subcategory": "Bank",
        "type": "Services"
      }
    ],
    "sg:phone": "+1 216 464 4611",
    "sg:postcode": "44122",
    "sg:province": "OH",
    "sg:tags": [
      "banker",
      "mortgage"
    ],
    "wof:name": "La Salle Mortgage Company Inc",
    "wof:placetype": "venue"
  },
  "geometry": {"coordinates":[-81.516928,41.462806],"type":"Point"}
}
