{
  "type": "Feature",
  "properties": {
    "addr:full": "158 Brookside Blvd Hinckley OH 44233",
    "addr:housenumber": "158",
    "addr:postcode": "44233",
    "addr:street": "Brookside Blvd",
    "iso:country": "US",
    "sg:address": "158 Brookside Blvd",
    "sg:city": "Hinckley",
    "sg:classifiers": [
      {
        "category": "Professional",
        "type": "Services"
      }
    ],
    "sg:phone": "+1 330 273 6463",
    "sg:postcode": "44233",
    "sg:province": "OH",
    "sg:tags": [
      "establishment"
    ],
    "wof:name": "Sherwood Technologies Inc",
    "wof:placetype": "venue"
  },
  "geometry": {"coordinates":[-81.769793,41.271432],"type":"Point"}
}
