{
  "type": "Feature",
  "properties": {
    "iso:country":"US",
    "sg:address":"378 Clinton St",
    "sg:city":"Clayton",
    "sg:classifiers":[
        {
            "category":"Manufacturing",
            "subcategory":"Tools & Machinery",
            "type":"Manufacturing & Wholesale Goods"
        }
    ],
    "sg:phone":"+1 937 836 4533",
    "sg:postcode":"45315",
    "sg:province":"OH",
    "sg:tags":[
        "machine",
        "shop"
    ],
    "wof:name":"Hofacker Precision Machining",
    "wof:placetype":"venue"
},
  "geometry": {"coordinates":[-84.354178,39.859014],"type":"Point"}
}