{
  "type": "Feature",
  "properties": {
    "addr:full": "378 Clinton St Clayton OH 45315",
    "addr:housenumber": "378",
    "addr:postcode": "45315",
    "addr:street": "Clinton St",
    "iso:country": "US",
    "sg:address": "378 Clinton St",
    "sg:city": "Clayton",
    "sg:classifiers": [
      {
        "category": "Manufacturing",
        "subcategory": "Tools \u0026 Machinery",
        "type": "Manufacturing \u0026 Wholesale Goods"
      }
    ],
    "sg:phone": "+1 937 836 4533",
    "sg:postcode": "45315",
    "sg:province": "OH",
    "sg:tags": [
      "machine",
      "shop"
    ],
    "wof:name": "Hofacker Precision Machining",
    "wof:placetype": "venue"
  },
  "geometry": {"coordinates":[-84.354178,39.859014],"type":"Point"}
}
