{
  "type": "Feature",
  "properties": {
    "addr:full":"3706 W 169th St Cleveland OH 44111",
    "addr:housenumber":"3706",
    "addr:postcode":"44111",
    "addr:street":"W 169Th St",
    "iso:country":"US",
    "sg:address":"3706 W 169th St",
    "sg:city":"Cleveland",
    "sg:classifiers":[
        {
            "category":"Home & Garden",
            "subcategory":"Hardware",
            "type":"Retail Goods"
        }
    ],
    "sg:phone":"+1 216 941 8618",
    "sg:postcode":"44111",
    "sg:province":"OH",
    "sg:tags":[
        "antique",
        "supply"
    ],
    "wof:name":"Antique Trunk Co",
    "wof:placetype":"venue"
},
  "geometry": {"coordinates":[-81.81536,41.451366],"type":"Point"}
}