{
  "type": "Feature",
  "properties": {
    "addr:full": "5850 S Co Rd 25A Tipp City OH 45371",
    "addr:housenumber": "5850;25a",
    "addr:postcode": "45371",
    "addr:street": "S Co Rd",
    "iso:country": "US",
    "sg:address": "5850 S Co Rd 25A",
    "sg:city": "Tipp City",
    "sg:classifiers": [
      {
        "category": "Insurance",
        "subcategory": "Insurance Agent",
        "type": "Services"
      }
    ],
    "sg:phone": "+1 937 667 3965",
    "sg:postcode": "45371",
    "sg:province": "OH",
    "wof:name": "Nickol Insurance",
    "wof:placetype": "venue"
  },
  "geometry": {"coordinates":[-84.19912,39.952746],"type":"Point"}
}
