{
  "type": "Feature",
  "properties": {
    "addr:full": "206 Wagner Ave Greenville OH 45331",
    "addr:housenumber": "206",
    "addr:postcode": "45331",
    "addr:street": "Wagner Ave",
    "iso:country": "US",
    "sg:address": "206 Wagner Ave",
    "sg:city": "Greenville",
    "sg:classifiers": [
      {
        "category": "Organizations",
        "subcategory": "Non-profit Organization",
        "type": "Services"
      }
    ],
    "sg:phone": "+1 937 547 3113",
    "sg:postcode": "45331",
    "sg:province": "OH",
    "sg:tags": [
      "alternative",
      "abortion"
    ],
    "wof:name": "Darke County Right To Life",
    "wof:placetype": "venue"
  },
  "geometry": {"coordinates":[-84.62247,40.111446],"type":"Point"}
}
