{
  "type": "Feature",
  "properties": {
    "iso:country":"US",
    "sg:address":"129 W Main St",
    "sg:city":"Medway",
    "sg:classifiers":[
        {
            "category":"Retail",
            "subcategory":"Laundry & Dry Cleaning",
            "type":"Services"
        }
    ],
    "sg:phone":"+1 937 849 0870",
    "sg:postcode":"45341",
    "sg:province":"OH",
    "sg:tags":[
        "cleaners"
    ],
    "wof:name":"Medway Cleaners",
    "wof:placetype":"venue"
},
  "geometry": {"coordinates":[-84.011127,39.881202],"type":"Point"}
}