{
  "type": "Feature",
  "properties": {
    "addr:full": "129 W Main St Medway OH 45341",
    "addr:housenumber": "129",
    "addr:postcode": "45341",
    "addr:street": "W Main St",
    "iso:country": "US",
    "sg:address": "129 W Main St",
    "sg:city": "Medway",
    "sg:classifiers": [
      {
        "category": "Retail",
        "subcategory": "Laundry \u0026 Dry Cleaning",
        "type": "Services"
      }
    ],
    "sg:phone": "+1 937 849 0870",
    "sg:postcode": "45341",
    "sg:province": "OH",
    "sg:tags": [
      "cleaners"
    ],
    "wof:name": "Medway Cleaners",
    "wof:placetype": "venue"
  },
  "geometry": {"coordinates":[-84.011127,39.881202],"type":"Point"}
}
