{
  "type": "Feature",
  "properties": {
    "addr:full": "15 Atterbury Blvd Hudson OH 44236",
    "addr:housenumber": "15",
    "addr:postcode": "44236",
    "addr:street": "Atterbury Blvd",
    "iso:country": "US",
    "sg:address": "15 Atterbury Blvd",
    "sg:city": "Hudson",
    "sg:classifiers": [
      {
        "category": "Building \u0026 Trades",
        "subcategory": "Pest Control",
        "type": "Services"
      }
    ],
    "sg:phone": "+1 330 650 0717",
    "sg:postcode": "44236",
    "sg:province": "OH",
    "wof:name": "All Bugs Exterminators",
    "wof:placetype": "venue"
  },
  "geometry": {"coordinates":[-81.446127,41.240461],"type":"Point"}
}
