{
  "type": "Feature",
  "properties": {
    "addr:full":"3923 E Main St Columbus OH 43213",
    "addr:housenumber":"3923",
    "addr:postcode":"43213",
    "addr:street":"E Main St",
    "iso:country":"US",
    "sg:address":"3923 E Main St",
    "sg:city":"Columbus",
    "sg:classifiers":[
        {
            "category":"Building & Trades",
            "subcategory":"Construction",
            "type":"Services"
        }
    ],
    "sg:phone":"+1 614 338 1999",
    "sg:postcode":"43213",
    "sg:province":"OH",
    "sg:tags":[
        "roofing",
        "contractor"
    ],
    "wof:name":"Us Roofing",
    "wof:placetype":"venue"
},
  "geometry": {"coordinates":[-82.89707199999999,39.956063],"type":"Point"}
}