{
  "type": "Feature",
  "properties": {
    "iso:country":"US",
    "sg:address":"316 North St",
    "sg:city":"Fremont",
    "sg:classifiers":[
        {
            "category":"Wholesale",
            "subcategory":"Construction Materials",
            "type":"Manufacturing & Wholesale Goods"
        }
    ],
    "sg:phone":"+1 419 332 8913",
    "sg:postcode":"43420",
    "sg:province":"OH",
    "sg:tags":[
        "fence"
    ],
    "sg:website":"www.fremontfenceandguardrailco.com",
    "wof:name":"Fremont Fence & Guard Rail Co",
    "wof:placetype":"venue"
},
  "geometry": {"coordinates":[-83.112651,41.361415],"type":"Point"}
}