{
  "type": "Feature",
  "properties": {
    "addr:full": "316 North St Fremont OH 43420",
    "addr:housenumber": "316",
    "addr:postcode": "43420",
    "addr:street": "North St",
    "iso:country": "US",
    "sg:address": "316 North St",
    "sg:city": "Fremont",
    "sg:classifiers": [
      {
        "category": "Wholesale",
        "subcategory": "Construction Materials",
        "type": "Manufacturing \u0026 Wholesale Goods"
      }
    ],
    "sg:phone": "+1 419 332 8913",
    "sg:postcode": "43420",
    "sg:province": "OH",
    "sg:tags": [
      "fence"
    ],
    "sg:website": "www.fremontfenceandguardrailco.com",
    "wof:name": "Fremont Fence \u0026 Guard Rail Co",
    "wof:placetype": "venue"
  },
  "geometry": {"coordinates":[-83.112651,41.361415],"type":"Point"}
}
