{
  "type": "Feature",
  "properties": {
    "iso:country":"US",
    "sg:address":"531 Dover Rd NE",
    "sg:city":"Sugarcreek",
    "sg:classifiers":[
        {
            "category":"Organizations",
            "subcategory":"Religious Organization",
            "type":"Services"
        }
    ],
    "sg:phone":"+1 330 852 2825",
    "sg:postcode":"44681",
    "sg:province":"OH",
    "wof:name":"Sugarcreek Free Methdst Church",
    "wof:placetype":"venue"
},
  "geometry": {"coordinates":[-81.63343399999999,40.508529],"type":"Point"}
}