{
  "type": "Feature",
  "properties": {
    "addr:full": "11020 Yingling Ln Frazeysburg OH 43822",
    "addr:housenumber": "11020",
    "addr:postcode": "43822",
    "addr:street": "Yingling Ln",
    "iso:country": "US",
    "sg:address": "11020 Yingling Ln",
    "sg:city": "Frazeysburg",
    "sg:classifiers": [
      {
        "category": "Manufacturing",
        "subcategory": "Tools \u0026 Machinery",
        "type": "Manufacturing \u0026 Wholesale Goods"
      }
    ],
    "sg:phone": "+1 740 828 3630",
    "sg:postcode": "43822",
    "sg:province": "OH",
    "sg:tags": [
      "electrical",
      "mfg"
    ],
    "wof:name": "Slide-Master",
    "wof:placetype": "venue"
  },
  "geometry": {"coordinates":[-82.165942,40.129179],"type":"Point"}
}
