{
  "type": "Feature",
  "properties": {
    "iso:country":"US",
    "sg:address":"11020 Yingling Ln",
    "sg:city":"Frazeysburg",
    "sg:classifiers":[
        {
            "category":"Manufacturing",
            "subcategory":"Tools & Machinery",
            "type":"Manufacturing & Wholesale Goods"
        }
    ],
    "sg:phone":"+1 740 828 3630",
    "sg:postcode":"43822",
    "sg:province":"OH",
    "sg:tags":[
        "electrical",
        "mfg"
    ],
    "wof:name":"Slide-Master",
    "wof:placetype":"venue"
},
  "geometry": {"coordinates":[-82.165942,40.129179],"type":"Point"}
}