{
  "type": "Feature",
  "properties": {
    "addr:full":"4180 Warrensville Center Rd Cleveland OH 44122",
    "addr:housenumber":"4180",
    "addr:postcode":"44122",
    "addr:street":"Warrensville Center Rd",
    "iso:country":"US",
    "sg:address":"4180 Warrensville Center Rd",
    "sg:city":"Cleveland",
    "sg:classifiers":[
        {
            "category":"Shopping",
            "subcategory":"Gifts & Souvenirs",
            "type":"Retail Goods"
        }
    ],
    "sg:phone":"+1 216 491 6159",
    "sg:postcode":"44122",
    "sg:province":"OH",
    "wof:name":"Suburban Hospital Gift Shop",
    "wof:placetype":"venue"
},
  "geometry": {"coordinates":[-81.53616100000001,41.446496],"type":"Point"}
}