{
  "type": "Feature",
  "properties": {
    "addr:full":"2250 N Cleveland Massillon Rd Akron OH 44333",
    "addr:housenumber":"2250",
    "addr:postcode":"44333",
    "addr:street":"N Cleveland Massillon Rd",
    "iso:country":"US",
    "sg:address":"2250 N Cleveland Massillon Rd",
    "sg:city":"Akron",
    "sg:classifiers":[
        {
            "category":"Travel",
            "subcategory":"Hotels & Motels",
            "type":"Entertainment"
        }
    ],
    "sg:phone":"+1 330 659 9999",
    "sg:postcode":"44333",
    "sg:province":"OH",
    "wof:name":"Ohio Motel",
    "wof:placetype":"venue"
},
  "geometry": {"coordinates":[-81.636962,41.197934],"type":"Point"}
}