{
  "type": "Feature",
  "properties": {
    "addr:full":"1237 E 16th Ave Columbus OH 43211",
    "addr:housenumber":"1237",
    "addr:postcode":"43211",
    "addr:street":"E 16Th Ave",
    "iso:country":"US",
    "sg:address":"1237 E 16th Ave",
    "sg:city":"Columbus",
    "sg:classifiers":[
        {
            "category":"Manufacturing",
            "subcategory":"Printing",
            "type":"Manufacturing & Wholesale Goods"
        }
    ],
    "sg:phone":"+1 614 251 0972",
    "sg:postcode":"43211",
    "sg:province":"OH",
    "sg:tags":[
        "publisher",
        "music"
    ],
    "wof:name":"Green",
    "wof:placetype":"venue"
},
  "geometry": {"coordinates":[-82.97319299999999,39.999212],"type":"Point"}
}