{
  "type": "Feature",
  "properties": {
    "iso:country":"US",
    "sg:address":"103 E Greenwood Dr",
    "sg:city":"Haskins",
    "sg:classifiers":[
        {
            "category":"Building & Trades",
            "subcategory":"Construction",
            "type":"Services"
        }
    ],
    "sg:phone":"+1 419 450 8100",
    "sg:postcode":"43525",
    "sg:province":"OH",
    "sg:tags":[
        "house"
    ],
    "wof:name":"Black Ridge Builders",
    "wof:placetype":"venue"
},
  "geometry": {"coordinates":[-83.70484500000001,41.469767],"type":"Point"}
}