{
  "type": "Feature",
  "properties": {
    "addr:full": "103 E Greenwood Dr Haskins OH 43525",
    "addr:housenumber": "103",
    "addr:postcode": "43525",
    "addr:street": "E Greenwood Dr",
    "iso:country": "US",
    "sg:address": "103 E Greenwood Dr",
    "sg:city": "Haskins",
    "sg:classifiers": [
      {
        "category": "Building \u0026 Trades",
        "subcategory": "Construction",
        "type": "Services"
      }
    ],
    "sg:phone": "+1 419 450 8100",
    "sg:postcode": "43525",
    "sg:province": "OH",
    "sg:tags": [
      "house"
    ],
    "wof:name": "Black Ridge Builders",
    "wof:placetype": "venue"
  },
  "geometry": {"coordinates":[-83.704845,41.469767],"type":"Point"}
}
