{
  "type": "Feature",
  "properties": {
    "addr:full": "2040 Atlas St Columbus OH 43228",
    "addr:housenumber": "2040",
    "addr:postcode": "43228",
    "addr:street": "Atlas St",
    "iso:country": "US",
    "sg:address": "2040 Atlas St",
    "sg:city": "Columbus",
    "sg:classifiers": [
      {
        "category": "Freight",
        "type": "Transportation"
      }
    ],
    "sg:phone": "+1 614 529 7900",
    "sg:postcode": "43228",
    "sg:province": "OH",
    "sg:tags": [
      "a",
      "as",
      "acts",
      "company",
      "holding"
    ],
    "wof:name": "FST Logistics Inc",
    "wof:placetype": "venue"
  },
  "geometry": {"coordinates":[-83.142832,39.989831],"type":"Point"}
}
