{
  "type": "Feature",
  "properties": {
    "addr:full":"1685 Lockbourne Rd Columbus OH 43207",
    "addr:housenumber":"1685",
    "addr:postcode":"43207",
    "addr:street":"Lockbourne Rd",
    "iso:country":"US",
    "sg:address":"1685 Lockbourne Rd",
    "sg:city":"Columbus",
    "sg:classifiers":[
        {
            "category":"Health Services",
            "subcategory":"Doctor",
            "type":"Services"
        }
    ],
    "sg:phone":"+1 614 444 9849",
    "sg:postcode":"43207",
    "sg:province":"OH",
    "sg:tags":[
        "dentist"
    ],
    "wof:name":"Southmoor Dental Group",
    "wof:placetype":"venue"
},
  "geometry": {"coordinates":[-82.964769,39.9316],"type":"Point"}
}