{
  "type": "Feature",
  "properties": {
    "addr:full":"3967 State Rte 245 Cable OH 43009",
    "addr:housenumber":"3967",
    "addr:postcode":"43009",
    "addr:street":"State Rte 245",
    "iso:country":"US",
    "sg:address":"3967 State Rte 245",
    "sg:city":"Cable",
    "sg:phone":"+1 937 653 7894",
    "sg:postcode":"43009",
    "sg:province":"OH",
    "sg:tags":[
        "farm",
        "corn"
    ],
    "wof:name":"Doug Doty",
    "wof:placetype":"venue"
},
  "geometry": {"coordinates":[-83.662918,40.21112],"type":"Point"}
}