{
  "type": "Feature",
  "properties": {
    "addr:full":"1504 S Main St Bellefontaine OH 43311",
    "addr:housenumber":"1504",
    "addr:postcode":"43311",
    "addr:street":"S Main St",
    "iso:country":"US",
    "sg:address":"1504 S Main St",
    "sg:city":"Bellefontaine",
    "sg:classifiers":[
        {
            "category":"Autos & Motor Vehicles",
            "subcategory":"Fuel & Gas Station",
            "type":"Retail Goods"
        }
    ],
    "sg:phone":"+1 937 592 2857",
    "sg:postcode":"43311",
    "sg:province":"OH",
    "sg:tags":[
        "station",
        "gasoline"
    ],
    "wof:name":"Amoco",
    "wof:placetype":"venue"
},
  "geometry": {"coordinates":[-83.762001,40.339504],"type":"Point"}
}