{
  "type": "Feature",
  "properties": {
    "iso:country":"US",
    "sg:address":"70 Northfield Rd",
    "sg:city":"Bedford",
    "sg:classifiers":[
        {
            "category":"Building & Trades",
            "subcategory":"Construction",
            "type":"Services"
        }
    ],
    "sg:phone":"+1 440 439 4610",
    "sg:postcode":"44146",
    "sg:province":"OH",
    "sg:tags":[
        "door",
        "aluminum",
        "siding",
        "contractor",
        "window",
        "replacement"
    ],
    "wof:name":"Palumbo Siding",
    "wof:placetype":"venue"
},
  "geometry": {"coordinates":[-81.52695300000001,41.379443],"type":"Point"}
}