{
  "type": "Feature",
  "properties": {
    "addr:full":"73260 Grays Ridge Rd Saint Clairsville OH 43950",
    "addr:postcode":"73260;43950",
    "addr:street":"Grays Ridge Rd",
    "iso:country":"US",
    "sg:address":"73260 Grays Ridge Rd",
    "sg:city":"Saint Clairsville",
    "sg:classifiers":[
        {
            "category":"Manufacturing",
            "subcategory":"Retail Goods",
            "type":"Manufacturing & Wholesale Goods"
        }
    ],
    "sg:phone":"+1 740 695 0262",
    "sg:postcode":"43950",
    "sg:province":"OH",
    "sg:tags":[
        "product",
        "mfg"
    ],
    "wof:name":"GSM Industries",
    "wof:placetype":"venue"
},
  "geometry": {"coordinates":[-80.874623,40.150026],"type":"Point"}
}