{
  "type": "Feature",
  "properties": {
    "addr:full": "252 Avon Belden Rd Avon Lake OH 44012",
    "addr:housenumber": "252",
    "addr:postcode": "44012",
    "addr:street": "Avon Belden Rd",
    "iso:country": "US",
    "sg:address": "252 Avon Belden Rd",
    "sg:city": "Avon Lake",
    "sg:classifiers": [
      {
        "category": "Building \u0026 Trades",
        "subcategory": "Construction",
        "type": "Services"
      }
    ],
    "sg:phone": "+1 440 930 5569",
    "sg:postcode": "44012",
    "sg:province": "OH",
    "wof:name": "Knapp Construction",
    "wof:placetype": "venue"
  },
  "geometry": {"coordinates":[-82.018811,41.503109],"type":"Point"}
}
