{
  "type": "Feature",
  "properties": {
    "iso:country":"US",
    "sg:address":"780 Nilles Rd",
    "sg:city":"Fairfield",
    "sg:classifiers":[
        {
            "category":"Professional",
            "subcategory":"Lawyer & Legal Services",
            "type":"Services"
        }
    ],
    "sg:phone":"+1 513 829 0300",
    "sg:postcode":"45014",
    "sg:province":"OH",
    "sg:tags":[
        "attorney"
    ],
    "wof:name":"Maxwell N Wear",
    "wof:placetype":"venue"
},
  "geometry": {"coordinates":[-84.555356,39.337507],"type":"Point"}
}