{
  "type": "Feature",
  "properties": {
    "addr:full":"3757 W Edgerton Rd Cleveland OH 44133",
    "addr:housenumber":"3757",
    "addr:postcode":"44133",
    "addr:street":"W Edgerton Rd",
    "iso:country":"US",
    "sg:address":"3757 W Edgerton Rd",
    "sg:city":"Cleveland",
    "sg:classifiers":[
        {
            "category":"Banks & Credit Unions",
            "subcategory":"Investment Brokerage",
            "type":"Services"
        }
    ],
    "sg:phone":"+1 440 877 9503",
    "sg:postcode":"44133",
    "sg:province":"OH",
    "sg:tags":[
        "consultant",
        "financing"
    ],
    "wof:name":"AFA Financial",
    "wof:placetype":"venue"
},
  "geometry": {"coordinates":[-81.709937,41.295817],"type":"Point"}
}