{
  "type": "Feature",
  "properties": {
    "addr:full": "11641 Alspach Rd NW Canal Winchester OH 43110",
    "addr:housenumber": "11641",
    "addr:postcode": "43110",
    "addr:street": "Alspach Rd Nw",
    "iso:country": "US",
    "sg:address": "11641 Alspach Rd NW",
    "sg:city": "Canal Winchester",
    "sg:classifiers": [
      {
        "category": "Recreation",
        "type": "Entertainment"
      }
    ],
    "sg:phone": "+1 614 833 6701",
    "sg:postcode": "43110",
    "sg:province": "OH",
    "sg:tags": [
      "stable"
    ],
    "sg:website": "www.eaglesnestranch.com",
    "wof:name": "Eagles Nest Ranch",
    "wof:placetype": "venue"
  },
  "geometry": {"coordinates":[-82.818255,39.765891],"type":"Point"}
}
