{
  "type": "Feature",
  "properties": {
    "addr:full": "826 Chalker St Akron OH 44310",
    "addr:housenumber": "826",
    "addr:postcode": "44310",
    "addr:street": "Chalker St",
    "iso:country": "US",
    "sg:address": "826 Chalker St",
    "sg:city": "Akron",
    "sg:classifiers": [
      {
        "category": "Building \u0026 Trades",
        "subcategory": "Plumbing",
        "type": "Services"
      }
    ],
    "sg:phone": "+1 330 253 9500",
    "sg:postcode": "44310",
    "sg:province": "OH",
    "sg:tags": [
      "heating",
      "contractor"
    ],
    "wof:name": "Allied Heating \u0026 Air Cond",
    "wof:placetype": "venue"
  },
  "geometry": {"coordinates":[-81.513771,41.107371],"type":"Point"}
}
