{
  "type": "Feature",
  "properties": {
    "iso:country":"US",
    "sg:address":"826 Chalker St",
    "sg:city":"Akron",
    "sg:classifiers":[
        {
            "category":"Building & Trades",
            "subcategory":"Plumbing",
            "type":"Services"
        }
    ],
    "sg:phone":"+1 330 253 9500",
    "sg:postcode":"44310",
    "sg:province":"OH",
    "sg:tags":[
        "heating",
        "contractor"
    ],
    "wof:name":"Allied Heating & Air Cond",
    "wof:placetype":"venue"
},
  "geometry": {"coordinates":[-81.51377100000001,41.107371],"type":"Point"}
}