{
  "type": "Feature",
  "properties": {
    "iso:country":"US",
    "sg:address":"2253 Waterworks Dr",
    "sg:city":"Toledo",
    "sg:classifiers":[
        {
            "category":"Home & Garden",
            "subcategory":"Carpets & Floor Coverings",
            "type":"Retail Goods"
        }
    ],
    "sg:phone":"+1 419 389 9441",
    "sg:postcode":"43609",
    "sg:province":"OH",
    "wof:name":"Deborh Bxtr Cmrcl & Rsdntl FL",
    "wof:placetype":"venue"
},
  "geometry": {"coordinates":[-83.569486,41.623515],"type":"Point"}
}