{
  "type": "Feature",
  "properties": {
    "iso:country":"US",
    "sg:address":"14785 Ford Rd",
    "sg:city":"Madison",
    "sg:phone":"+1 440 298 3836",
    "sg:postcode":"44057",
    "sg:province":"OH",
    "sg:tags":[
        "farm",
        "field",
        "corn",
        "crop"
    ],
    "wof:name":"Harold Bennington Trust",
    "wof:placetype":"venue"
},
  "geometry": {"coordinates":[-81.10709,41.722609],"type":"Point"}
}