{
  "type": "Feature",
  "properties": {
    "addr:full": "555 W Goodale St Columbus OH 43215",
    "addr:housenumber": "555",
    "addr:postcode": "43215",
    "addr:street": "W Goodale St",
    "iso:country": "US",
    "sg:address": "555 W Goodale St",
    "sg:city": "Columbus",
    "sg:classifiers": [
      {
        "category": "Restaurant",
        "type": "Food \u0026 Drink"
      }
    ],
    "sg:phone": "+1 614 228 5781",
    "sg:postcode": "43215",
    "sg:province": "OH",
    "sg:website": "www.whitecastle.com",
    "wof:name": "White Castle Management Co",
    "wof:placetype": "venue"
  },
  "geometry": {"coordinates":[-83.018057,39.974059],"type":"Point"}
}
