{
  "type": "Feature",
  "properties": {
    "addr:full": "627 Kaderly St NW New Philadelphia OH 44663",
    "addr:housenumber": "627",
    "addr:postcode": "44663",
    "addr:street": "Kaderly St Nw New Philadelphia",
    "iso:country": "US",
    "sg:address": "627 Kaderly St NW",
    "sg:city": "New Philadelphia",
    "sg:classifiers": [
      {
        "category": "Retail",
        "subcategory": "Car Wash",
        "type": "Services"
      }
    ],
    "sg:phone": "+1 330 343 4989",
    "sg:postcode": "44663",
    "sg:province": "OH",
    "sg:tags": [
      "automobile",
      "detail",
      "clean"
    ],
    "wof:name": "Park Detailing",
    "wof:placetype": "venue"
  },
  "geometry": {"coordinates":[-81.451592,40.498044],"type":"Point"}
}
