{
  "type": "Feature",
  "properties": {
    "iso:country":"US",
    "sg:address":"1649 Buck Run Rd",
    "sg:city":"Wilmington",
    "sg:classifiers":[
        {
            "category":"Shopping",
            "type":"Retail Goods"
        }
    ],
    "sg:phone":"+1 937 488 3303",
    "sg:postcode":"45177",
    "sg:province":"OH",
    "sg:tags":[
        "merchandise"
    ],
    "wof:name":"Long Brothers Diversfd Packg",
    "wof:placetype":"venue"
},
  "geometry": {"coordinates":[-83.92906499999999,39.546672],"type":"Point"}
}