{
  "type": "Feature",
  "properties": {
    "addr:full":"6945 N Renwood Rd Cleveland OH 44131",
    "addr:housenumber":"6945",
    "addr:postcode":"44131",
    "addr:street":"N Renwood Rd",
    "iso:country":"US",
    "sg:address":"6945 N Renwood Rd",
    "sg:city":"Cleveland",
    "sg:classifiers":[
        {
            "category":"Banks & Credit Unions",
            "subcategory":"Financial Services",
            "type":"Services"
        }
    ],
    "sg:phone":"+1 216 328 9587",
    "sg:postcode":"44131",
    "sg:province":"OH",
    "sg:tags":[
        "trust",
        "investment",
        "real estate"
    ],
    "wof:name":"Renwood Inc",
    "wof:placetype":"venue"
},
  "geometry": {"coordinates":[-81.64156800000001,41.364912],"type":"Point"}
}