{
  "type": "Feature",
  "properties": {
    "addr:full":"5476 Lake Ct Cleveland OH 44114",
    "addr:housenumber":"5476",
    "addr:postcode":"44114",
    "addr:street":"Lake Ct",
    "iso:country":"US",
    "sg:address":"5476 Lake Ct",
    "sg:city":"Cleveland",
    "sg:classifiers":[
        {
            "category":"Professional",
            "type":"Services"
        }
    ],
    "sg:phone":"+1 216 426 6650",
    "sg:postcode":"44114",
    "sg:province":"OH",
    "sg:tags":[
        "establishment"
    ],
    "wof:name":"Hi Tecmetal Group Brite Brzng",
    "wof:placetype":"venue"
},
  "geometry": {"coordinates":[-81.65271300000001,41.527213],"type":"Point"}
}