{
  "type": "Feature",
  "properties": {
    "addr:full":"762 Chestnut St Nelsonville OH 45764",
    "addr:housenumber":"762",
    "addr:postcode":"45764",
    "addr:street":"Chestnut St",
    "iso:country":"US",
    "sg:address":"762 Chestnut St",
    "sg:city":"Nelsonville",
    "sg:classifiers":[
        {
            "category":"Social Services",
            "subcategory":"Adult Care",
            "type":"Services"
        }
    ],
    "sg:phone":"+1 740 753 2384",
    "sg:postcode":"45764",
    "sg:province":"OH",
    "sg:tags":[
        "organization",
        "senior",
        "citizen"
    ],
    "wof:name":"Nelsonville Senior Citizens",
    "wof:placetype":"venue"
},
  "geometry": {"coordinates":[-82.22302500000001,39.453111],"type":"Point"}
}