{
  "type": "Feature",
  "properties": {
    "addr:full":"4765 Higbee Ave NW Canton OH 44718",
    "addr:housenumber":"4765",
    "addr:postcode":"44718",
    "addr:street":"Higbee Ave Nw",
    "iso:country":"US",
    "sg:address":"4765 Higbee Ave NW",
    "sg:city":"Canton",
    "sg:classifiers":[
        {
            "category":"Professional",
            "type":"Services"
        },
        {
            "category":"Health Services",
            "subcategory":"Doctor",
            "type":"Services"
        }
    ],
    "sg:phone":"+1 330 492 0444",
    "sg:postcode":"44718",
    "sg:province":"OH",
    "sg:tags":[
        "physician",
        "surgeon"
    ],
    "wof:name":"Arrhythmia Specialists Inc",
    "wof:placetype":"venue"
},
  "geometry": {"coordinates":[-81.427925,40.850578],"type":"Point"}
}