{
  "type": "Feature",
  "properties": {
    "addr:full": "801 Plum St Cincinnati OH 45202",
    "addr:housenumber": "801",
    "addr:postcode": "45202",
    "addr:street": "Plum St",
    "iso:country": "US",
    "sg:address": "801 Plum St",
    "sg:city": "Cincinnati",
    "sg:classifiers": [
      {
        "category": "Government",
        "subcategory": "Office",
        "type": "Public Place"
      }
    ],
    "sg:phone": "+1 513 352 3401",
    "sg:postcode": "45202",
    "sg:province": "OH",
    "sg:tags": [
      "water",
      "executive",
      "association",
      "supply"
    ],
    "wof:name": "City of Cincinnati",
    "wof:placetype": "venue"
  },
  "geometry": {"coordinates":[-84.51878,39.104288],"type":"Point"}
}
