{
  "type": "Feature",
  "properties": {
    "addr:full": "5934 Beechtop Dr Cincinnati OH 45233",
    "addr:housenumber": "5934",
    "addr:postcode": "45233",
    "addr:street": "Beechtop Dr",
    "iso:country": "US",
    "sg:address": "5934 Beechtop Dr",
    "sg:city": "Cincinnati",
    "sg:classifiers": [
      {
        "category": "Building \u0026 Trades",
        "subcategory": "Construction",
        "type": "Services"
      }
    ],
    "sg:phone": "+1 513 922 5709",
    "sg:postcode": "45233",
    "sg:province": "OH",
    "sg:tags": [
      "floor",
      "laying",
      "contractor"
    ],
    "wof:name": "Schmutte Custom Floor Co",
    "wof:placetype": "venue"
  },
  "geometry": {"coordinates":[-84.64693,39.124407],"type":"Point"}
}
