{
  "type": "Feature",
  "properties": {
    "iso:country":"US",
    "sg:address":"681 Broadway Ave",
    "sg:city":"Cleveland",
    "sg:classifiers":[
        {
            "category":"Personal",
            "subcategory":"Tattoo Parlor",
            "type":"Services"
        }
    ],
    "sg:phone":"+1 440 439 6999",
    "sg:postcode":"44146",
    "sg:province":"OH",
    "sg:tags":[
        "tattooing"
    ],
    "wof:name":"A Nu Tatt 2",
    "wof:placetype":"venue"
},
  "geometry": {"coordinates":[-81.535179,41.391401],"type":"Point"}
}