{
  "type": "Feature",
  "properties": {
    "iso:country":"US",
    "sg:address":"211 Buffalo St",
    "sg:city":"Conneaut",
    "sg:classifiers":[
        {
            "category":"Place Of Worship",
            "subcategory":"Church",
            "type":"Public Place"
        },
        {
            "category":"Place Of Worship",
            "type":"Public Place"
        }
    ],
    "sg:phone":"+1 440 599 8744",
    "sg:postcode":"44030",
    "sg:province":"OH",
    "sg:tags":[
        "churches-interdenominational",
        "churches-various",
        "denomination"
    ],
    "wof:name":"Fist Congregational Ucc",
    "wof:placetype":"venue"
},
  "geometry": {"coordinates":[-80.557309,41.942712],"type":"Point"}
}