{
  "type": "Feature",
  "properties": {
    "addr:full":"7150 State Rte 108 Wauseon OH 43567",
    "addr:housenumber":"7150",
    "addr:postcode":"43567",
    "addr:street":"State Rte 108",
    "iso:country":"US",
    "sg:address":"7150 State Rte 108",
    "sg:city":"Wauseon",
    "sg:classifiers":[
        {
            "category":"Retail",
            "subcategory":"Auto Repair",
            "type":"Services"
        }
    ],
    "sg:phone":"+1 419 337 7290",
    "sg:postcode":"43567",
    "sg:province":"OH",
    "sg:tags":[
        "truck"
    ],
    "wof:name":"Wood Truck Svc",
    "wof:placetype":"venue"
},
  "geometry": {"coordinates":[-84.148535,41.574245],"type":"Point"}
}