{
  "type": "Feature",
  "properties": {
    "iso:country":"US",
    "sg:address":"1205 E John St",
    "sg:city":"Springfield",
    "sg:classifiers":[
        {
            "category":"Real Estate",
            "subcategory":"Real Estate Operator",
            "type":"Services"
        }
    ],
    "sg:phone":"+1 937 322 2700",
    "sg:postcode":"45505",
    "sg:province":"OH",
    "sg:tags":[
        "apartment"
    ],
    "wof:name":"Cornerstone Apartments",
    "wof:placetype":"venue"
},
  "geometry": {"coordinates":[-83.794437,39.902173],"type":"Point"}
}