{
  "type": "Feature",
  "properties": {
    "addr:full":"855 Spartan Dr Vandalia OH 45377",
    "addr:housenumber":"855",
    "addr:postcode":"45377",
    "addr:street":"Spartan Dr",
    "iso:country":"US",
    "sg:address":"855 Spartan Dr",
    "sg:city":"Vandalia",
    "sg:classifiers":[
        {
            "category":"Wholesale",
            "subcategory":"Medical Equipment & Supplies",
            "type":"Manufacturing & Wholesale Goods"
        }
    ],
    "sg:phone":"+1 937 890 7605",
    "sg:postcode":"45377",
    "sg:province":"OH",
    "wof:name":"Jlm Medical Equip Mail Order",
    "wof:placetype":"venue"
},
  "geometry": {"coordinates":[-84.18165999999999,39.89717],"type":"Point"}
}