{
  "type": "Feature",
  "properties": {
    "addr:full": "3301 Westbourne Dr Cincinnati OH 45248",
    "addr:housenumber": "3301",
    "addr:postcode": "45248",
    "addr:street": "Westbourne Dr",
    "iso:country": "US",
    "sg:address": "3301 Westbourne Dr",
    "sg:city": "Cincinnati",
    "sg:classifiers": [
      {
        "category": "Building \u0026 Trades",
        "subcategory": "Construction",
        "type": "Services"
      }
    ],
    "sg:phone": "+1 513 598 1653",
    "sg:postcode": "45248",
    "sg:province": "OH",
    "sg:tags": [
      "home",
      "builder"
    ],
    "wof:name": "Sowder \u0026 Sullivan Custom Hm",
    "wof:placetype": "venue"
  },
  "geometry": {"coordinates":[-84.629009,39.146307],"type":"Point"}
}
