{
  "type": "Feature",
  "properties": {
    "iso:country":"US",
    "sg:address":"1345 Bellbrook Ave",
    "sg:city":"Xenia",
    "sg:classifiers":[
        {
            "category":"Health Services",
            "subcategory":"Chiropractor",
            "type":"Services"
        }
    ],
    "sg:phone":"+1 937 372 7683",
    "sg:postcode":"45385",
    "sg:province":"OH",
    "wof:name":"Robert D Boike DC",
    "wof:placetype":"venue"
},
  "geometry": {"coordinates":[-83.954988,39.672639],"type":"Point"}
}