{
  "type": "Feature",
  "properties": {
    "iso:country":"US",
    "sg:address":"12026 Zelis Rd",
    "sg:city":"Cleveland",
    "sg:classifiers":[
        {
            "category":"Manufacturing",
            "subcategory":"Tools & Machinery",
            "type":"Manufacturing & Wholesale Goods"
        }
    ],
    "sg:phone":"+1 216 252 0550",
    "sg:postcode":"44135",
    "sg:province":"OH",
    "sg:tags":[
        "g",
        "mfg",
        "printing",
        "equipment",
        "paper",
        "converting"
    ],
    "wof:name":"Pearce Inc",
    "wof:placetype":"venue"
},
  "geometry": {"coordinates":[-81.768448,41.442838],"type":"Point"}
}