{
  "type": "Feature",
  "properties": {
    "iso:country":"US",
    "sg:address":"5577 Monroe St",
    "sg:city":"Sylvania",
    "sg:classifiers":[
        {
            "category":"Building & Trades",
            "subcategory":"Construction",
            "type":"Services"
        }
    ],
    "sg:phone":"+1 419 885 8618",
    "sg:postcode":"43560",
    "sg:province":"OH",
    "sg:tags":[
        "carpentry",
        "contractor"
    ],
    "wof:name":"Pella Products",
    "wof:placetype":"venue"
},
  "geometry": {"coordinates":[-83.670016,41.707718],"type":"Point"}
}