{
  "type": "Feature",
  "properties": {
    "iso:country":"US",
    "sg:address":"6969 Worthington Galena Rd",
    "sg:city":"Columbus",
    "sg:classifiers":[
        {
            "category":"Wholesale",
            "subcategory":"Vending Machines",
            "type":"Manufacturing & Wholesale Goods"
        }
    ],
    "sg:phone":"+1 614 785 6250",
    "sg:postcode":"43085",
    "sg:province":"OH",
    "sg:tags":[
        "operator"
    ],
    "wof:name":"Progrsv Vending Services Inc",
    "wof:placetype":"venue"
},
  "geometry": {"coordinates":[-83.002392,40.10573],"type":"Point"}
}