{
  "type": "Feature",
  "properties": {
    "addr:full": "6969 Worthington Galena Rd Columbus OH 43085",
    "addr:housenumber": "6969",
    "addr:postcode": "43085",
    "addr:street": "Worthington Galena Rd",
    "iso:country": "US",
    "sg:address": "6969 Worthington Galena Rd",
    "sg:city": "Columbus",
    "sg:classifiers": [
      {
        "category": "Wholesale",
        "subcategory": "Vending Machines",
        "type": "Manufacturing \u0026 Wholesale Goods"
      }
    ],
    "sg:phone": "+1 614 785 6250",
    "sg:postcode": "43085",
    "sg:province": "OH",
    "sg:tags": [
      "operator"
    ],
    "wof:name": "Progrsv Vending Services Inc",
    "wof:placetype": "venue"
  },
  "geometry": {"coordinates":[-83.002392,40.10573],"type":"Point"}
}
