{
  "type": "Feature",
  "properties": {
    "iso:country":"US",
    "sg:address":"10258 Maumee Western Rd",
    "sg:city":"Monclova",
    "sg:classifiers":[
        {
            "category":"Building & Trades",
            "subcategory":"Cleaning & Sanitation",
            "type":"Services"
        }
    ],
    "sg:phone":"+1 419 865 9660",
    "sg:postcode":"43542",
    "sg:province":"OH",
    "sg:tags":[
        "janitor"
    ],
    "wof:name":"C 3 Svc LLC",
    "wof:placetype":"venue"
},
  "geometry": {"coordinates":[-83.78776499999999,41.574899],"type":"Point"}
}