{
  "type": "Feature",
  "properties": {
    "iso:country":"US",
    "sg:address":"6520 Broadview Rd",
    "sg:city":"Cleveland",
    "sg:classifiers":[
        {
            "category":"Organizations",
            "subcategory":"Religious Organization",
            "type":"Services"
        }
    ],
    "sg:phone":"+1 216 447 1015",
    "sg:postcode":"44134",
    "sg:province":"OH",
    "sg:tags":[
        "church"
    ],
    "wof:name":"St Sergius Russian Orthodox",
    "wof:placetype":"venue"
},
  "geometry": {"coordinates":[-81.68492999999999,41.389016],"type":"Point"}
}