{
  "type": "Feature",
  "properties": {
    "iso:country":"US",
    "sg:address":"2111 S Wynn Rd",
    "sg:city":"Okeana",
    "sg:classifiers":[
        {
            "category":"Retail",
            "subcategory":"Repair Shop",
            "type":"Services"
        },
        {
            "category":"Building & Trades",
            "subcategory":"Construction",
            "type":"Services"
        }
    ],
    "sg:phone":"+1 513 738 3553",
    "sg:postcode":"45053",
    "sg:province":"IN",
    "sg:tags":[
        "metal",
        "contractor",
        "piping",
        "welding",
        "fabrication",
        "structural"
    ],
    "wof:name":"T G Young Contracting Inc",
    "wof:placetype":"venue"
},
  "geometry": {"coordinates":[-84.758413,39.362788],"type":"Point"}
}