{
  "type": "Feature",
  "properties": {
    "iso:country":"US",
    "sg:address":"11132 E Pike Rd",
    "sg:city":"Cambridge",
    "sg:classifiers":[
        {
            "category":"Home & Garden",
            "subcategory":"Building Materials",
            "type":"Retail Goods"
        }
    ],
    "sg:phone":"+1 740 439 0098",
    "sg:postcode":"43725",
    "sg:province":"OH",
    "sg:tags":[
        "windows",
        "glass",
        "door"
    ],
    "wof:name":"Cambridge Door Company Inc",
    "wof:placetype":"venue"
},
  "geometry": {"coordinates":[-81.545676,40.024375],"type":"Point"}
}