{
  "type": "Feature",
  "properties": {
    "addr:full": "11132 E Pike Rd Cambridge OH 43725",
    "addr:housenumber": "11132",
    "addr:postcode": "43725",
    "addr:street": "E Pike Rd",
    "iso:country": "US",
    "sg:address": "11132 E Pike Rd",
    "sg:city": "Cambridge",
    "sg:classifiers": [
      {
        "category": "Home \u0026 Garden",
        "subcategory": "Building Materials",
        "type": "Retail Goods"
      }
    ],
    "sg:phone": "+1 740 439 0098",
    "sg:postcode": "43725",
    "sg:province": "OH",
    "sg:tags": [
      "windows",
      "glass",
      "door"
    ],
    "wof:name": "Cambridge Door Company Inc",
    "wof:placetype": "venue"
  },
  "geometry": {"coordinates":[-81.545676,40.024375],"type":"Point"}
}
