{
  "type": "Feature",
  "properties": {
    "iso:country":"US",
    "sg:address":"36420 Biltmore Pl",
    "sg:city":"Willoughby",
    "sg:classifiers":[
        {
            "category":"Building & Trades",
            "subcategory":"Construction",
            "type":"Services"
        }
    ],
    "sg:phone":"+1 440 951 9354",
    "sg:postcode":"44094",
    "sg:province":"OH",
    "sg:tags":[
        "marking",
        "maintenance",
        "cleaning",
        "lot",
        "parking"
    ],
    "wof:name":"All Sweep Inc",
    "wof:placetype":"venue"
},
  "geometry": {"coordinates":[-81.42496,41.632501],"type":"Point"}
}