{
  "type": "Feature",
  "properties": {
    "iso:country":"US",
    "sg:address":"1200 E 6th St",
    "sg:city":"Salem",
    "sg:classifiers":[
        {
            "category":"Education",
            "subcategory":"Vocational School",
            "type":"Public Place"
        }
    ],
    "sg:phone":"+1 330 332 8940",
    "sg:postcode":"44460",
    "sg:province":"OH",
    "sg:tags":[
        "nurse"
    ],
    "wof:name":"Hannah E Mullins Schl-Nursing",
    "wof:placetype":"venue"
},
  "geometry": {"coordinates":[-80.845755,40.906296],"type":"Point"}
}