{
  "type": "Feature",
  "properties": {
    "addr:full":"315 12th St NE Canton OH 44703",
    "addr:housenumber":"315",
    "addr:postcode":"44703",
    "addr:street":"12Th St Ne",
    "iso:country":"US",
    "sg:address":"315 12th St NE",
    "sg:city":"Canton",
    "sg:classifiers":[
        {
            "category":"Manufacturing",
            "subcategory":"Printing",
            "type":"Manufacturing & Wholesale Goods"
        }
    ],
    "sg:phone":"+1 330 454 9444",
    "sg:postcode":"44703",
    "sg:province":"OH",
    "sg:tags":[
        "printer"
    ],
    "wof:name":"PPI Graphics",
    "wof:placetype":"venue"
},
  "geometry": {"coordinates":[-81.37606100000001,40.809354],"type":"Point"}
}