{
  "type": "Feature",
  "properties": {
    "addr:full":"1275 Morman Rd Hamilton OH 45013",
    "addr:housenumber":"1275",
    "addr:postcode":"45013",
    "addr:street":"Morman Rd",
    "iso:country":"US",
    "sg:address":"1275 Morman Rd",
    "sg:city":"Hamilton",
    "sg:classifiers":[
        {
            "category":"Autos & Motor Vehicles",
            "subcategory":"Auto Supplies",
            "type":"Retail Goods"
        }
    ],
    "sg:phone":"+1 513 892 2038",
    "sg:postcode":"45013",
    "sg:province":"OH",
    "sg:tags":[
        "equipment",
        "racing",
        "car",
        "automobile"
    ],
    "wof:name":"Hyper Performance Motor Sports",
    "wof:placetype":"venue"
},
  "geometry": {"coordinates":[-84.646371,39.42226],"type":"Point"}
}