{
  "type": "Feature",
  "properties": {
    "iso:country":"US",
    "sg:address":"12778 Royalton Rd",
    "sg:city":"Cleveland",
    "sg:classifiers":[
        {
            "category":"Restaurant",
            "type":"Food & Drink"
        }
    ],
    "sg:phone":"+1 440 230 2625",
    "sg:postcode":"44133",
    "sg:province":"OH",
    "sg:tags":[
        "shop",
        "coffee"
    ],
    "wof:name":"Flowers Coffee Garden",
    "wof:placetype":"venue"
},
  "geometry": {"coordinates":[-81.78209099999999,41.315645],"type":"Point"}
}