{
  "type": "Feature",
  "properties": {
    "addr:full": "12778 Royalton Rd Cleveland OH 44133",
    "addr:housenumber": "12778",
    "addr:postcode": "44133",
    "addr:street": "Royalton Rd",
    "iso:country": "US",
    "sg:address": "12778 Royalton Rd",
    "sg:city": "Cleveland",
    "sg:classifiers": [
      {
        "category": "Restaurant",
        "type": "Food \u0026 Drink"
      }
    ],
    "sg:phone": "+1 440 230 2625",
    "sg:postcode": "44133",
    "sg:province": "OH",
    "sg:tags": [
      "shop",
      "coffee"
    ],
    "wof:name": "Flowers Coffee Garden",
    "wof:placetype": "venue"
  },
  "geometry": {"coordinates":[-81.782091,41.315645],"type":"Point"}
}
