{
  "type": "Feature",
  "properties": {
    "addr:full":"7635 Commerce Pl Plain City OH 43064",
    "addr:housenumber":"7635",
    "addr:postcode":"43064",
    "addr:street":"Commerce Pl",
    "iso:country":"US",
    "sg:address":"7635 Commerce Pl",
    "sg:city":"Plain City",
    "sg:classifiers":[
        {
            "category":"Wholesale",
            "subcategory":"Construction Materials",
            "type":"Manufacturing & Wholesale Goods"
        }
    ],
    "sg:phone":"+1 614 873 2211",
    "sg:postcode":"43064",
    "sg:province":"OH",
    "sg:tags":[
        "granite"
    ],
    "wof:name":"Marble & Granite Works",
    "wof:placetype":"venue"
},
  "geometry": {"coordinates":[-83.190145,40.123834],"type":"Point"}
}