{
  "type": "Feature",
  "properties": {
    "addr:full":"2609 E Main St Lancaster OH 43130",
    "addr:housenumber":"2609",
    "addr:postcode":"43130",
    "addr:street":"E Main St",
    "iso:country":"US",
    "sg:address":"2609 E Main St",
    "sg:city":"Lancaster",
    "sg:classifiers":[
        {
            "category":"Autos & Motor Vehicles",
            "subcategory":"Automobile Sales",
            "type":"Retail Goods"
        }
    ],
    "sg:phone":"+1 740 652 9920",
    "sg:postcode":"43130",
    "sg:province":"OH",
    "sg:tags":[
        "car",
        "dealer"
    ],
    "wof:name":"3 Digit Auto Sales",
    "wof:placetype":"venue"
},
  "geometry": {"coordinates":[-82.53889700000001,39.719046],"type":"Point"}
}