{
  "type": "Feature",
  "properties": {
    "addr:full":"3847 Lake Vista Rd Akron OH 44319",
    "addr:housenumber":"3847",
    "addr:postcode":"44319",
    "addr:street":"Lake Vista Rd",
    "iso:country":"US",
    "sg:address":"3847 Lake Vista Rd",
    "sg:city":"Akron",
    "sg:classifiers":[
        {
            "category":"Retail",
            "subcategory":"Laundry & Dry Cleaning",
            "type":"Services"
        }
    ],
    "sg:phone":"+1 330 753 4844",
    "sg:postcode":"44319",
    "sg:province":"OH",
    "sg:tags":[
        "cleaners",
        "rug",
        "carpet"
    ],
    "wof:name":"Chem-Dry",
    "wof:placetype":"venue"
},
  "geometry": {"coordinates":[-81.56312800000001,40.996914],"type":"Point"}
}