{
  "type": "Feature",
  "properties": {
    "iso:country":"US",
    "sg:address":"24672 Euclid Ave",
    "sg:city":"Cleveland",
    "sg:classifiers":[
        {
            "category":"Government",
            "subcategory":"Office",
            "type":"Public Place"
        }
    ],
    "sg:phone":"+1 216 531 9926",
    "sg:postcode":"44117",
    "sg:province":"OH",
    "sg:tags":[
        "armed",
        "national",
        "force",
        "security",
        "recruiting"
    ],
    "wof:name":"US Army Recruiting Office",
    "wof:placetype":"venue"
},
  "geometry": {"coordinates":[-81.51093400000001,41.580322],"type":"Point"}
}