{
  "type": "Feature",
  "properties": {
    "addr:full": "5383 Hamilton Mason Rd Hamilton OH 45011",
    "addr:housenumber": "5383",
    "addr:postcode": "45011",
    "addr:street": "Hamilton Mason Rd",
    "iso:country": "US",
    "sg:address": "5383 Hamilton Mason Rd",
    "sg:city": "Hamilton",
    "sg:classifiers": [
      {
        "category": "Building \u0026 Trades",
        "subcategory": "Construction",
        "type": "Services"
      }
    ],
    "sg:phone": "+1 513 868 0332",
    "sg:postcode": "45011",
    "sg:province": "OH",
    "sg:tags": [
      "maintenance",
      "contractor"
    ],
    "wof:name": "D \u0026 S Professional Grnd Mntnc",
    "wof:placetype": "venue"
  },
  "geometry": {"coordinates":[-84.443432,39.373065],"type":"Point"}
}
