{
  "type": "Feature",
  "properties": {
    "iso:country":"US",
    "sg:address":"5383 Hamilton Mason Rd",
    "sg:city":"Hamilton",
    "sg:classifiers":[
        {
            "category":"Building & Trades",
            "subcategory":"Construction",
            "type":"Services"
        }
    ],
    "sg:phone":"+1 513 868 0332",
    "sg:postcode":"45011",
    "sg:province":"OH",
    "sg:tags":[
        "maintenance",
        "contractor"
    ],
    "wof:name":"D & S Professional Grnd Mntnc",
    "wof:placetype":"venue"
},
  "geometry": {"coordinates":[-84.443432,39.373065],"type":"Point"}
}