{
  "type": "Feature",
  "properties": {
    "addr:full": "1632 Owen Rd Northwood OH 43619",
    "addr:housenumber": "1632",
    "addr:postcode": "43619",
    "addr:street": "Owen Rd",
    "iso:country": "US",
    "sg:address": "1632 Owen Rd",
    "sg:city": "Northwood",
    "sg:classifiers": [
      {
        "category": "Wholesale",
        "subcategory": "Sporting Goods",
        "type": "Manufacturing \u0026 Wholesale Goods"
      }
    ],
    "sg:phone": "+1 419 691 5002",
    "sg:postcode": "43619",
    "sg:province": "OH",
    "wof:name": "Rd Collectibles Ltd",
    "wof:placetype": "venue"
  },
  "geometry": {"coordinates":[-83.459377,41.591025],"type":"Point"}
}
