{
  "type": "Feature",
  "properties": {
    "addr:full": "50 W Broad St Columbus OH 43215",
    "addr:housenumber": "50",
    "addr:postcode": "43215",
    "addr:street": "W Broad St",
    "iso:country": "US",
    "sg:address": "50 W Broad St",
    "sg:city": "Columbus",
    "sg:classifiers": [
      {
        "category": "Professional",
        "subcategory": "Management \u0026 Consulting",
        "type": "Services"
      }
    ],
    "sg:phone": "+1 614 255 4111",
    "sg:postcode": "43215",
    "sg:province": "OH",
    "wof:name": "Atlantic Management Center",
    "wof:placetype": "venue"
  },
  "geometry": {"coordinates":[-83.001973,39.962163],"type":"Point"}
}
