{
  "type": "Feature",
  "properties": {
    "iso:country":"US",
    "sg:address":"3212 Lakeside Ave E",
    "sg:city":"Cleveland",
    "sg:classifiers":[
        {
            "category":"Retail",
            "subcategory":"Auto Repair",
            "type":"Services"
        }
    ],
    "sg:phone":"+1 216 861 1473",
    "sg:postcode":"44114",
    "sg:province":"OH",
    "sg:tags":[
        "exchanging",
        "engine"
    ],
    "wof:name":"Howell's Racing Engines",
    "wof:placetype":"venue"
},
  "geometry": {"coordinates":[-81.672659,41.515014],"type":"Point"}
}