{
  "type": "Feature",
  "properties": {
    "iso:country":"US",
    "sg:address":"7796 Ponderosa Rd",
    "sg:city":"Perrysburg",
    "sg:classifiers":[
        {
            "category":"Autos & Motor Vehicles",
            "subcategory":"Auto Supplies",
            "type":"Retail Goods"
        }
    ],
    "sg:phone":"+1 419 661 2357",
    "sg:postcode":"43551",
    "sg:province":"OH",
    "sg:tags":[
        "automobile",
        "accessory"
    ],
    "wof:name":"Northcoast Automotive Spec",
    "wof:placetype":"venue"
},
  "geometry": {"coordinates":[-83.543121,41.562482],"type":"Point"}
}