{
  "type": "Feature",
  "properties": {
    "addr:full":"8456 Weaver Rd Saint Louisville OH 43071",
    "addr:housenumber":"8456",
    "addr:postcode":"43071",
    "addr:street":"Weaver Rd",
    "iso:country":"US",
    "sg:address":"8456 Weaver Rd",
    "sg:city":"Saint Louisville",
    "sg:classifiers":[
        {
            "category":"Professional",
            "type":"Services"
        }
    ],
    "sg:phone":"+1 740 745 5417",
    "sg:postcode":"43071",
    "sg:province":"OH",
    "wof:name":"John A Holton",
    "wof:placetype":"venue"
},
  "geometry": {"coordinates":[-82.432981,40.176263],"type":"Point"}
}