{
  "type": "Feature",
  "properties": {
    "addr:full":"4180 W Hillcrest Ave Dayton OH 45406",
    "addr:housenumber":"4180",
    "addr:postcode":"45406",
    "addr:street":"W Hillcrest Ave",
    "iso:country":"US",
    "sg:address":"4180 W Hillcrest Ave",
    "sg:city":"Dayton",
    "sg:classifiers":[
        {
            "category":"Shopping",
            "subcategory":"Music",
            "type":"Retail Goods"
        }
    ],
    "sg:phone":"+1 937 276 4652",
    "sg:postcode":"45406",
    "sg:province":"OH",
    "sg:tags":[
        "compact",
        "record",
        "disc",
        "tape"
    ],
    "wof:name":"14 Carat Gold Cd's & Tapes",
    "wof:placetype":"venue"
},
  "geometry": {"coordinates":[-84.251597,39.790519],"type":"Point"}
}