{
  "type": "Feature",
  "properties": {
    "iso:country":"US",
    "sg:address":"718 Hammer Ct",
    "sg:city":"Elyria",
    "sg:classifiers":[
        {
            "category":"Retail",
            "subcategory":"Portrait Studio",
            "type":"Services"
        }
    ],
    "sg:phone":"+1 440 365 8986",
    "sg:postcode":"44035",
    "sg:province":"OH",
    "sg:tags":[
        "photographer"
    ],
    "wof:name":"Rodriguez Photography",
    "wof:placetype":"venue"
},
  "geometry": {"coordinates":[-82.076463,41.397572],"type":"Point"}
}