{
  "type": "Feature",
  "properties": {
    "addr:full":"11316 Euclid Ave Cleveland OH 44106",
    "addr:housenumber":"11316",
    "addr:postcode":"44106",
    "addr:street":"Euclid Ave",
    "iso:country":"US",
    "sg:address":"11316 Euclid Ave",
    "sg:city":"Cleveland",
    "sg:classifiers":[
        {
            "category":"Restaurant",
            "type":"Food & Drink"
        }
    ],
    "sg:phone":"+1 216 791 4444",
    "sg:postcode":"44106",
    "sg:province":"OH",
    "wof:name":"Rascal House Pizza",
    "wof:placetype":"venue"
},
  "geometry": {"coordinates":[-81.60538099999999,41.508846],"type":"Point"}
}