{
  "type": "Feature",
  "properties": {
    "iso:country":"US",
    "sg:address":"12261 Convoy Rd",
    "sg:city":"Van Wert",
    "sg:classifiers":[
        {
            "category":"Real Estate",
            "subcategory":"Real Estate Operator",
            "type":"Services"
        }
    ],
    "sg:phone":"+1 419 238 2898",
    "sg:postcode":"45891",
    "sg:province":"OH",
    "sg:tags":[
        "property",
        "lessor"
    ],
    "wof:name":"Jerry Nihiser",
    "wof:placetype":"venue"
},
  "geometry": {"coordinates":[-84.586596,40.917275],"type":"Point"}
}