{
  "type": "Feature",
  "properties": {
    "addr:full": "35761 Curtis Blvd Willoughby OH 44095",
    "addr:housenumber": "35761",
    "addr:postcode": "44095",
    "addr:street": "Curtis Blvd",
    "iso:country": "US",
    "sg:address": "35761 Curtis Blvd",
    "sg:city": "Willoughby",
    "sg:classifiers": [
      {
        "category": "Shopping",
        "subcategory": "Gifts \u0026 Souvenirs",
        "type": "Retail Goods"
      }
    ],
    "sg:phone": "+1 440 942 4100",
    "sg:postcode": "44095",
    "sg:province": "OH",
    "sg:tags": [
      "party",
      "supply"
    ],
    "wof:name": "Aladdin Rents",
    "wof:placetype": "venue"
  },
  "geometry": {"coordinates":[-81.435372,41.638404],"type":"Point"}
}
