{
  "type": "Feature",
  "properties": {
    "addr:full":"3022 Graham Rd Stow OH 44224",
    "addr:housenumber":"3022",
    "addr:postcode":"44224",
    "addr:street":"Graham Rd",
    "iso:country":"US",
    "sg:address":"3022 Graham Rd",
    "sg:city":"Stow",
    "sg:classifiers":[
        {
            "category":"Restaurant",
            "type":"Food & Drink"
        }
    ],
    "sg:menulink":"http://www.allmenus.com/oh/stow/134425-subway/menu/",
    "sg:phone":"+1 330 688 6142",
    "sg:postcode":"44224",
    "sg:province":"OH",
    "sg:tags":[
        "american",
        "sandwich"
    ],
    "wof:name":"Subway",
    "wof:placetype":"venue"
},
  "geometry": {"coordinates":[-81.405461,41.166512],"type":"Point"}
}