{
  "type": "Feature",
  "properties": {
    "addr:full": "4320 Liberty Ave Vermilion OH 44089",
    "addr:housenumber": "4320",
    "addr:postcode": "44089",
    "addr:street": "Liberty Ave",
    "iso:country": "US",
    "sg:address": "4320 Liberty Ave",
    "sg:city": "Vermilion",
    "sg:classifiers": [
      {
        "category": "Restaurant",
        "type": "Food \u0026 Drink"
      }
    ],
    "sg:phone": "+1 440 967 2200",
    "sg:postcode": "44089",
    "sg:province": "OH",
    "wof:name": "Alize At Elberta",
    "wof:placetype": "venue"
  },
  "geometry": {"coordinates":[-82.338265,41.424948],"type":"Point"}
}
