{
  "type": "Feature",
  "properties": {
    "iso:country":"US",
    "sg:address":"4320 Liberty Ave",
    "sg:city":"Vermilion",
    "sg:classifiers":[
        {
            "category":"Restaurant",
            "type":"Food & Drink"
        }
    ],
    "sg:phone":"+1 440 967 2200",
    "sg:postcode":"44089",
    "sg:province":"OH",
    "wof:name":"Alize At Elberta",
    "wof:placetype":"venue"
},
  "geometry": {"coordinates":[-82.33826500000001,41.424948],"type":"Point"}
}