{
  "type": "Feature",
  "properties": {
    "addr:full": "1840 Belmont Ave Youngstown OH 44504",
    "addr:housenumber": "1840",
    "addr:postcode": "44504",
    "addr:street": "Belmont Ave",
    "iso:country": "US",
    "sg:address": "1840 Belmont Ave",
    "sg:city": "Youngstown",
    "sg:classifiers": [
      {
        "category": "Food \u0026 Beverages",
        "subcategory": "Liquor \u0026 Beverages",
        "type": "Retail Goods"
      }
    ],
    "sg:phone": "+1 330 747 4013",
    "sg:postcode": "44504",
    "sg:province": "OH",
    "sg:tags": [
      "wine"
    ],
    "wof:name": "Brothers Food Inc",
    "wof:placetype": "venue"
  },
  "geometry": {"coordinates":[-80.664014,41.125158],"type":"Point"}
}
