{
  "type": "Feature",
  "properties": {
    "iso:country":"US",
    "sg:address":"7550 Lucerne Dr",
    "sg:city":"Cleveland",
    "sg:classifiers":[
        {
            "category":"Banks & Credit Unions",
            "subcategory":"Bank",
            "type":"Services"
        }
    ],
    "sg:phone":"+1 440 239 9385",
    "sg:postcode":"44130",
    "sg:province":"OH",
    "sg:tags":[
        "mortgage",
        "loan",
        "banker",
        "real estate"
    ],
    "wof:name":"Premier Mortgage Group Ltd",
    "wof:placetype":"venue"
},
  "geometry": {"coordinates":[-81.817138,41.357746],"type":"Point"}
}