{
  "type": "Feature",
  "properties": {
    "addr:full":"4015 Executive Park Dr Cincinnati OH 45241",
    "addr:housenumber":"4015",
    "addr:postcode":"45241",
    "addr:street":"Executive Park Dr",
    "iso:country":"US",
    "sg:address":"4015 Executive Park Dr",
    "sg:city":"Cincinnati",
    "sg:classifiers":[
        {
            "category":"Wholesale",
            "subcategory":"Electrical",
            "type":"Manufacturing & Wholesale Goods"
        }
    ],
    "sg:phone":"+1 513 563 9380",
    "sg:postcode":"45241",
    "sg:province":"OH",
    "sg:tags":[
        "supply"
    ],
    "wof:name":"Eaton Electrical Inc",
    "wof:placetype":"venue"
},
  "geometry": {"coordinates":[-84.392822,39.288498],"type":"Point"}
}