{
  "type": "Feature",
  "properties": {
    "addr:full":"5520 Cheviot Rd Cincinnati OH 45247",
    "addr:housenumber":"5520",
    "addr:postcode":"45247",
    "addr:street":"Cheviot Rd",
    "iso:country":"US",
    "sg:address":"5520 Cheviot Rd",
    "sg:city":"Cincinnati",
    "sg:classifiers":[
        {
            "category":"Health Services",
            "subcategory":"Doctor",
            "type":"Services"
        }
    ],
    "sg:phone":"+1 513 451 4033",
    "sg:postcode":"45247",
    "sg:province":"OH",
    "sg:tags":[
        "physician",
        "surgeon"
    ],
    "sg:website":"www.oncology-partners.com",
    "wof:name":"Oncology Partners Network LTD",
    "wof:placetype":"venue"
},
  "geometry": {"coordinates":[-84.599177,39.191215],"type":"Point"}
}