{
  "type": "Feature",
  "properties": {
    "iso:country":"US",
    "sg:address":"18665 Sheldon Rd",
    "sg:city":"Cleveland",
    "sg:classifiers":[
        {
            "category":"Shopping",
            "type":"Retail Goods"
        }
    ],
    "sg:phone":"+1 216 898 1490",
    "sg:postcode":"44130",
    "sg:province":"OH",
    "sg:tags":[
        "trophy",
        "medal",
        "award"
    ],
    "wof:name":"Alenite",
    "wof:placetype":"venue"
},
  "geometry": {"coordinates":[-81.832394,41.388979],"type":"Point"}
}