{
  "type": "Feature",
  "properties": {
    "addr:full": "17485 State Rte 579 Martin OH 43445",
    "addr:housenumber": "17485",
    "addr:postcode": "43445",
    "addr:street": "State Rte 579",
    "iso:country": "US",
    "sg:address": "17485 State Rte 579",
    "sg:city": "Martin",
    "sg:classifiers": [
      {
        "category": "Building \u0026 Trades",
        "subcategory": "Construction",
        "type": "Services"
      }
    ],
    "sg:phone": "+1 419 340 5629",
    "sg:postcode": "43445",
    "sg:province": "OH",
    "sg:tags": [
      "sandblasting",
      "contractor"
    ],
    "wof:name": "Seagate Sandblasting",
    "wof:placetype": "venue"
  },
  "geometry": {"coordinates":[-83.268993,41.603923],"type":"Point"}
}
