{
  "type": "Feature",
  "properties": {
    "iso:country":"US",
    "sg:address":"17485 State Rte 579",
    "sg:city":"Martin",
    "sg:classifiers":[
        {
            "category":"Building & Trades",
            "subcategory":"Construction",
            "type":"Services"
        }
    ],
    "sg:phone":"+1 419 340 5629",
    "sg:postcode":"43445",
    "sg:province":"OH",
    "sg:tags":[
        "sandblasting",
        "contractor"
    ],
    "wof:name":"Seagate Sandblasting",
    "wof:placetype":"venue"
},
  "geometry": {"coordinates":[-83.26899299999999,41.603923],"type":"Point"}
}