{
  "type": "Feature",
  "properties": {
    "addr:full": "266 N Water St Kent OH 44240",
    "addr:housenumber": "266",
    "addr:postcode": "44240",
    "addr:street": "N Water St",
    "iso:country": "US",
    "sg:address": "266 N Water St",
    "sg:city": "Kent",
    "sg:classifiers": [
      {
        "category": "Personal",
        "subcategory": "Tattoo Parlor",
        "type": "Services"
      }
    ],
    "sg:phone": "+1 330 678 0109",
    "sg:postcode": "44240",
    "sg:province": "OH",
    "sg:tags": [
      "tattooing"
    ],
    "wof:name": "Smokin' Tattooz",
    "wof:placetype": "venue"
  },
  "geometry": {"coordinates":[-81.358226,41.155236],"type":"Point"}
}
