{
  "type": "Feature",
  "properties": {
    "iso:country":"US",
    "sg:address":"2645 Oakview Ct",
    "sg:city":"Lebanon",
    "sg:classifiers":[
        {
            "category":"Shopping",
            "type":"Retail Goods"
        }
    ],
    "sg:phone":"+1 513 934 0645",
    "sg:postcode":"45036",
    "sg:province":"OH",
    "sg:tags":[
        "merchandise"
    ],
    "wof:name":"Garden of Gems",
    "wof:placetype":"venue"
},
  "geometry": {"coordinates":[-84.210229,39.476346],"type":"Point"}
}