{
  "type": "Feature",
  "properties": {
    "addr:full": "33 S Michigan St Toledo OH 43604",
    "addr:housenumber": "33",
    "addr:postcode": "43604",
    "addr:street": "S Michigan St",
    "iso:country": "US",
    "sg:address": "33 S Michigan St",
    "sg:city": "Toledo",
    "sg:classifiers": [
      {
        "category": "Professional",
        "subcategory": "Lawyer \u0026 Legal Services",
        "type": "Services"
      }
    ],
    "sg:phone": "+1 419 255 5990",
    "sg:postcode": "43604",
    "sg:province": "OH",
    "sg:tags": [
      "attorney"
    ],
    "sg:website": "www.kergerkerger.com",
    "wof:name": "Kerger \u0026 Kerger",
    "wof:placetype": "venue"
  },
  "geometry": {"coordinates":[-83.543857,41.64879],"type":"Point"}
}
