{
  "type": "Feature",
  "properties": {
    "addr:full": "4500 N Ridge Rd Perry OH 44081",
    "addr:housenumber": "4500",
    "addr:postcode": "44081",
    "addr:street": "N Ridge Rd",
    "iso:country": "US",
    "sg:address": "4500 N Ridge Rd",
    "sg:city": "Perry",
    "sg:classifiers": [
      {
        "category": "Autos \u0026 Motor Vehicles",
        "subcategory": "Automobile Sales",
        "type": "Retail Goods"
      }
    ],
    "sg:phone": "+1 440 259 1080",
    "sg:postcode": "44081",
    "sg:province": "OH",
    "sg:tags": [
      "used"
    ],
    "wof:name": "Bobbys Auto Sales",
    "wof:placetype": "venue"
  },
  "geometry": {"coordinates":[-81.121003,41.78805],"type":"Point"}
}
