{
  "type": "Feature",
  "properties": {
    "iso:country":"US",
    "sg:address":"414 S Wood St",
    "sg:city":"Canton",
    "sg:classifiers":[
        {
            "category":"Farming",
            "subcategory":"Nursery",
            "type":"Manufacturing & Wholesale Goods"
        }
    ],
    "sg:phone":"+1 330 488 1162",
    "sg:postcode":"44730",
    "sg:province":"OH",
    "sg:tags":[
        "ornamental"
    ],
    "wof:name":"Douglas Flowers",
    "wof:placetype":"venue"
},
  "geometry": {"coordinates":[-81.282189,40.782517],"type":"Point"}
}