{
  "type": "Feature",
  "properties": {
    "addr:full": "414 S Wood St Canton OH 44730",
    "addr:housenumber": "414",
    "addr:postcode": "44730",
    "addr:street": "S Wood St",
    "iso:country": "US",
    "sg:address": "414 S Wood St",
    "sg:city": "Canton",
    "sg:classifiers": [
      {
        "category": "Farming",
        "subcategory": "Nursery",
        "type": "Manufacturing \u0026 Wholesale Goods"
      }
    ],
    "sg:phone": "+1 330 488 1162",
    "sg:postcode": "44730",
    "sg:province": "OH",
    "sg:tags": [
      "ornamental"
    ],
    "wof:name": "Douglas Flowers",
    "wof:placetype": "venue"
  },
  "geometry": {"coordinates":[-81.282189,40.782517],"type":"Point"}
}
