{
  "type": "Feature",
  "properties": {
    "addr:full":"1810 Styer Dr New Carlisle OH 45344",
    "addr:housenumber":"1810",
    "addr:postcode":"45344",
    "addr:street":"Styer Dr",
    "iso:country":"US",
    "sg:address":"1810 Styer Dr",
    "sg:city":"New Carlisle",
    "sg:classifiers":[
        {
            "category":"Building & Trades",
            "subcategory":"Construction",
            "type":"Services"
        }
    ],
    "sg:phone":"+1 937 849 9433",
    "sg:postcode":"45344",
    "sg:province":"OH",
    "sg:tags":[
        "merchandise",
        "business",
        "contractor"
    ],
    "wof:name":"A D George Excavating",
    "wof:placetype":"venue"
},
  "geometry": {"coordinates":[-84.046494,39.890328],"type":"Point"}
}