{
  "type": "Feature",
  "properties": {
    "iso:country":"US",
    "sg:address":"100 Kensington Rd NE",
    "sg:city":"Carrollton",
    "sg:classifiers":[
        {
            "category":"Government",
            "subcategory":"Office",
            "type":"Public Place"
        }
    ],
    "sg:phone":"+1 330 627 7017",
    "sg:postcode":"44615",
    "sg:province":"OH",
    "wof:name":"Carroll County Information Ctr",
    "wof:placetype":"venue"
},
  "geometry": {"coordinates":[-81.08274,40.584372],"type":"Point"}
}