{
  "type": "Feature",
  "properties": {
    "addr:full":"6817 Morley Rd Painesville OH 44077",
    "addr:housenumber":"6817",
    "addr:postcode":"44077",
    "addr:street":"Morley Rd",
    "iso:country":"US",
    "sg:address":"6817 Morley Rd",
    "sg:city":"Painesville",
    "sg:classifiers":[
        {
            "category":"Manufacturing",
            "subcategory":"Lumber",
            "type":"Manufacturing & Wholesale Goods"
        }
    ],
    "sg:phone":"+1 440 354 0974",
    "sg:postcode":"44077",
    "sg:province":"OH",
    "sg:tags":[
        "hardwood",
        "installation",
        "floor"
    ],
    "wof:name":"Kelco Hardwood Floors",
    "wof:placetype":"venue"
},
  "geometry": {"coordinates":[-81.259513,41.685069],"type":"Point"}
}