{
  "type": "Feature",
  "properties": {
    "iso:country":"US",
    "sg:address":"10 E Washington St",
    "sg:city":"Chagrin Falls",
    "sg:classifiers":[
        {
            "category":"Travel",
            "subcategory":"Travel Agent",
            "type":"Entertainment"
        }
    ],
    "sg:phone":"+1 440 247 7940",
    "sg:postcode":"44022",
    "sg:province":"OH",
    "sg:tags":[
        "agency",
        "bureau"
    ],
    "wof:name":"Jensen Travel Svc",
    "wof:placetype":"venue"
},
  "geometry": {"coordinates":[-81.391374,41.429707],"type":"Point"}
}