{
  "type": "Feature",
  "properties": {
    "iso:country":"US",
    "sg:address":"1301 Wagner Ave",
    "sg:city":"Greenville",
    "sg:classifiers":[
        {
            "category":"Restaurant",
            "type":"Food & Drink"
        }
    ],
    "sg:menulink":"http://www.allmenus.com/oh/greenville/194922-mcdonalds/menu/",
    "sg:postcode":"45331",
    "sg:province":"OH",
    "sg:tags":[
        "burger",
        "american"
    ],
    "wof:name":"McDonald's",
    "wof:placetype":"venue"
},
  "geometry": {"coordinates":[-84.621853,40.121377],"type":"Point"}
}