{
  "type": "Feature",
  "properties": {
    "addr:full":"115 N Vine St Medina OH 44256",
    "addr:housenumber":"115",
    "addr:postcode":"44256",
    "addr:street":"N Vine St",
    "iso:country":"US",
    "sg:address":"115 N Vine St",
    "sg:city":"Medina",
    "sg:classifiers":[
        {
            "category":"Personal",
            "subcategory":"Beauty Salon",
            "type":"Services"
        }
    ],
    "sg:phone":"+1 330 725 7333",
    "sg:postcode":"44256",
    "sg:province":"OH",
    "wof:name":"T & M Salon",
    "wof:placetype":"venue"
},
  "geometry": {"coordinates":[-81.869631,41.139552],"type":"Point"}
}