{
  "type": "Feature",
  "properties": {
    "addr:full": "4403 State Rte 725 Bellbrook OH 45305",
    "addr:housenumber": "4403",
    "addr:postcode": "45305",
    "addr:street": "State Rte 725",
    "iso:country": "US",
    "sg:address": "4403 State Rte 725",
    "sg:city": "Bellbrook",
    "sg:classifiers": [
      {
        "category": "Health Services",
        "subcategory": "Doctor",
        "type": "Services"
      }
    ],
    "sg:phone": "+1 937 427 9154",
    "sg:postcode": "45305",
    "sg:province": "OH",
    "sg:tags": [
      "physician",
      "surgeon"
    ],
    "wof:name": "Miami Valley Heart Ctr",
    "wof:placetype": "venue"
  },
  "geometry": {"coordinates":[-84.107848,39.63794],"type":"Point"}
}
