{
  "type": "Feature",
  "properties": {
    "addr:full": "230 Seminary Dr Monroe OH 45050",
    "addr:housenumber": "230",
    "addr:postcode": "45050",
    "addr:street": "Seminary Dr",
    "iso:country": "US",
    "sg:address": "230 Seminary Dr",
    "sg:city": "Monroe",
    "sg:classifiers": [
      {
        "category": "Social Services",
        "subcategory": "Child Care",
        "type": "Services"
      }
    ],
    "sg:phone": "+1 513 539 7709",
    "sg:postcode": "45050",
    "sg:province": "OH",
    "wof:name": "Mount Pleasant Retirement Vlg",
    "wof:placetype": "venue"
  },
  "geometry": {"coordinates":[-84.367249,39.446778],"type":"Point"}
}
