{
  "type": "Feature",
  "properties": {
    "addr:full": "12429 Cedar Rd Cleveland OH 44106",
    "addr:housenumber": "12429",
    "addr:postcode": "44106",
    "addr:street": "Cedar Rd",
    "iso:country": "US",
    "sg:address": "12429 Cedar Rd",
    "sg:city": "Cleveland",
    "sg:classifiers": [
      {
        "category": "Wholesale",
        "subcategory": "Construction Materials",
        "type": "Manufacturing \u0026 Wholesale Goods"
      },
      {
        "category": "Manufacturing",
        "subcategory": "Wood Products",
        "type": "Manufacturing \u0026 Wholesale Goods"
      }
    ],
    "sg:phone": "+1 216 421 2775",
    "sg:postcode": "44106",
    "sg:province": "OH",
    "sg:tags": [
      "pallet",
      "skid",
      "mfg"
    ],
    "sg:website": "www.olyforest.com",
    "wof:name": "Olympic Forest Products Co",
    "wof:placetype": "venue"
  },
  "geometry": {"coordinates":[-81.592518,41.501131],"type":"Point"}
}
