{
  "type": "Feature",
  "properties": {
    "addr:full":"1201 Scott St Napoleon OH 43545",
    "addr:housenumber":"1201",
    "addr:postcode":"43545",
    "addr:street":"Scott St",
    "iso:country":"US",
    "sg:address":"1201 Scott St",
    "sg:city":"Napoleon",
    "sg:classifiers":[
        {
            "category":"Autos & Motor Vehicles",
            "subcategory":"Fuel & Gas Station",
            "type":"Retail Goods"
        }
    ],
    "sg:phone":"+1 419 599 5186",
    "sg:postcode":"43545",
    "sg:province":"OH",
    "sg:tags":[
        "oil"
    ],
    "wof:name":"Lassus Brothers Oil Inc",
    "wof:placetype":"venue"
},
  "geometry": {"coordinates":[-84.132031,41.397152],"type":"Point"}
}