{
  "type": "Feature",
  "properties": {
    "addr:full":"15064 Twp Rd 390 Frazeysburg OH 43822",
    "addr:postcode":"15064;43822",
    "addr:street":"Twp Rd 390",
    "iso:country":"US",
    "sg:address":"15064 Twp Rd 390",
    "sg:city":"Frazeysburg",
    "sg:classifiers":[
        {
            "category":"Organizations",
            "subcategory":"Religious Organization",
            "type":"Services"
        }
    ],
    "sg:phone":"+1 740 828 3415",
    "sg:postcode":"43822",
    "sg:province":"OH",
    "sg:tags":[
        "clergy"
    ],
    "wof:name":"Robert Mc Graw",
    "wof:placetype":"venue"
},
  "geometry": {"coordinates":[-82.136028,40.169863],"type":"Point"}
}