{
  "type": "Feature",
  "properties": {
    "iso:country":"US",
    "sg:address":"9975 Foot Hills Ln",
    "sg:city":"Cambridge",
    "sg:classifiers":[
        {
            "category":"Building & Trades",
            "subcategory":"Construction",
            "type":"Services"
        }
    ],
    "sg:phone":"+1 740 432 7784",
    "sg:postcode":"43725",
    "sg:province":"OH",
    "sg:tags":[
        "excavation",
        "contractor"
    ],
    "wof:name":"Conkle Excavating",
    "wof:placetype":"venue"
},
  "geometry": {"coordinates":[-81.55381,40.027257],"type":"Point"}
}