{
  "type": "Feature",
  "properties": {
    "addr:full": "9975 Foot Hills Ln Cambridge OH 43725",
    "addr:housenumber": "9975",
    "addr:postcode": "43725",
    "addr:street": "Foot Hills Ln",
    "iso:country": "US",
    "sg:address": "9975 Foot Hills Ln",
    "sg:city": "Cambridge",
    "sg:classifiers": [
      {
        "category": "Building \u0026 Trades",
        "subcategory": "Construction",
        "type": "Services"
      }
    ],
    "sg:phone": "+1 740 432 7784",
    "sg:postcode": "43725",
    "sg:province": "OH",
    "sg:tags": [
      "excavation",
      "contractor"
    ],
    "wof:name": "Conkle Excavating",
    "wof:placetype": "venue"
  },
  "geometry": {"coordinates":[-81.55381,40.027257],"type":"Point"}
}
