{
  "type": "Feature",
  "properties": {
    "addr:full": "1560 Co Hwy 218 Marengo OH 43334",
    "addr:housenumber": "1560",
    "addr:postcode": "43334",
    "addr:street": "Co Hwy 218",
    "iso:country": "US",
    "sg:address": "1560 Co Hwy 218",
    "sg:city": "Marengo",
    "sg:classifiers": [
      {
        "category": "Building \u0026 Trades",
        "subcategory": "Plumbing",
        "type": "Services"
      }
    ],
    "sg:phone": "+1 419 253 9445",
    "sg:postcode": "43334",
    "sg:province": "OH",
    "sg:tags": [
      "contractor"
    ],
    "wof:name": "Alum Creek Heating \u0026 Cooling",
    "wof:placetype": "venue"
  },
  "geometry": {"coordinates":[-82.852386,40.40509],"type":"Point"}
}
