{
  "type": "Feature",
  "properties": {
    "addr:full": "5840 London Lancaster Rd Groveport OH 43125",
    "addr:housenumber": "5840",
    "addr:postcode": "43125",
    "addr:street": "London Lancaster Rd",
    "iso:country": "US",
    "sg:address": "5840 London Lancaster Rd",
    "sg:city": "Groveport",
    "sg:classifiers": [
      {
        "category": "Travel",
        "subcategory": "Travel Agent",
        "type": "Entertainment"
      }
    ],
    "sg:phone": "+1 614 836 9514",
    "sg:postcode": "43125",
    "sg:province": "OH",
    "sg:tags": [
      "agency"
    ],
    "wof:name": "Sterling Services",
    "wof:placetype": "venue"
  },
  "geometry": {"coordinates":[-82.861494,39.79704],"type":"Point"}
}
