{
  "type": "Feature",
  "properties": {
    "iso:country":"US",
    "sg:address":"500 Oakwood Ln",
    "sg:city":"Delta",
    "sg:classifiers":[
        {
            "category":"Retail",
            "subcategory":"Portrait Studio",
            "type":"Services"
        }
    ],
    "sg:phone":"+1 419 826 0777",
    "sg:postcode":"43515",
    "sg:province":"OH",
    "sg:tags":[
        "photographer"
    ],
    "wof:name":"Nawrocki Photography",
    "wof:placetype":"venue"
},
  "geometry": {"coordinates":[-84.004092,41.581696],"type":"Point"}
}