{
  "type": "Feature",
  "properties": {
    "addr:full": "3146 Oakwood Trl Broadview Heights OH 44147",
    "addr:housenumber": "3146",
    "addr:postcode": "44147",
    "addr:street": "Oakwood Trl",
    "iso:country": "US",
    "sg:address": "3146 Oakwood Trl",
    "sg:city": "Broadview Heights",
    "sg:classifiers": [
      {
        "category": "Professional",
        "type": "Services"
      }
    ],
    "sg:phone": "+1 440 230 5369",
    "sg:postcode": "44147",
    "sg:province": "OH",
    "wof:name": "Support Soft",
    "wof:placetype": "venue"
  },
  "geometry": {"coordinates":[-81.703915,41.318022],"type":"Point"}
}
