{
  "type": "Feature",
  "properties": {
    "addr:full": "400 Pike St Cincinnati OH 45202",
    "addr:housenumber": "400",
    "addr:postcode": "45202",
    "addr:street": "Pike St",
    "iso:country": "US",
    "sg:address": "400 Pike St",
    "sg:city": "Cincinnati",
    "sg:classifiers": [
      {
        "category": "Manufacturing",
        "subcategory": "Signs",
        "type": "Manufacturing \u0026 Wholesale Goods"
      }
    ],
    "sg:phone": "+1 513 651 1888",
    "sg:postcode": "45202",
    "sg:province": "OH",
    "sg:tags": [
      "advertising"
    ],
    "sg:website": "www.ehowe.com",
    "wof:name": "John K Howe Co",
    "wof:placetype": "venue"
  },
  "geometry": {"coordinates":[-84.503236,39.101888],"type":"Point"}
}
