{
  "type": "Feature",
  "properties": {
    "iso:country":"US",
    "sg:address":"4540 Heatherdowns Blvd",
    "sg:city":"Toledo",
    "sg:classifiers":[
        {
            "category":"Banks & Credit Unions",
            "subcategory":"Bank",
            "type":"Services"
        }
    ],
    "sg:phone":"+1 419 385 8000",
    "sg:postcode":"43614",
    "sg:province":"OH",
    "sg:tags":[
        "loan",
        "real estate"
    ],
    "wof:name":"First Place Bank",
    "wof:placetype":"venue"
},
  "geometry": {"coordinates":[-83.64676900000001,41.594352],"type":"Point"}
}