{
  "type": "Feature",
  "properties": {
    "addr:full": "5195 Engle Rd Cleveland OH 44142",
    "addr:housenumber": "5195",
    "addr:postcode": "44142",
    "addr:street": "Engle Rd",
    "iso:country": "US",
    "sg:address": "5195 Engle Rd",
    "sg:city": "Cleveland",
    "sg:classifiers": [
      {
        "category": "Freight",
        "type": "Transportation"
      }
    ],
    "sg:phone": "+1 216 898 9020",
    "sg:postcode": "44142",
    "sg:province": "OH",
    "sg:tags": [
      "delivery"
    ],
    "wof:name": "Pro Ex Professional Express",
    "wof:placetype": "venue"
  },
  "geometry": {"coordinates":[-81.819683,41.411106],"type":"Point"}
}
