{
  "type": "Feature",
  "properties": {
    "addr:full":"3345 Crown Point St NW Massillon OH 44646",
    "addr:housenumber":"3345",
    "addr:postcode":"44646",
    "addr:street":"Crown Point St Nw",
    "iso:country":"US",
    "sg:address":"3345 Crown Point St NW",
    "sg:city":"Massillon",
    "sg:classifiers":[
        {
            "category":"Building & Trades",
            "subcategory":"Construction",
            "type":"Services"
        }
    ],
    "sg:phone":"+1 330 837 8909",
    "sg:postcode":"44646",
    "sg:province":"OH",
    "sg:tags":[
        "product",
        "asphalt"
    ],
    "wof:name":"Seals & Stripes Asphalt",
    "wof:placetype":"venue"
},
  "geometry": {"coordinates":[-81.47121,40.804006],"type":"Point"}
}