{
  "type": "Feature",
  "properties": {
    "addr:full": "36 N Center St Springfield OH 45502",
    "addr:housenumber": "36",
    "addr:postcode": "45502",
    "addr:street": "N Center St",
    "iso:country": "US",
    "sg:address": "36 N Center St",
    "sg:city": "Springfield",
    "sg:classifiers": [
      {
        "category": "Bars \u0026 Pubs",
        "type": "Food \u0026 Drink"
      }
    ],
    "sg:phone": "+1 937 323 3643",
    "sg:postcode": "45502",
    "sg:province": "OH",
    "sg:tags": [
      "drinking"
    ],
    "wof:name": "Savoy Lounge",
    "wof:placetype": "venue"
  },
  "geometry": {"coordinates":[-83.812136,39.924859],"type":"Point"}
}
