{
  "type": "Feature",
  "properties": {
    "addr:full": "1399 Stoutsville Pike Circleville OH 43113",
    "addr:housenumber": "1399",
    "addr:postcode": "43113",
    "addr:street": "Stoutsville Pike",
    "iso:country": "US",
    "sg:address": "1399 Stoutsville Pike",
    "sg:city": "Circleville",
    "sg:classifiers": [
      {
        "category": "Recreation",
        "type": "Entertainment"
      }
    ],
    "sg:phone": "+1 740 474 4786",
    "sg:postcode": "43113",
    "sg:province": "OH",
    "sg:tags": [
      "course",
      "golf"
    ],
    "wof:name": "Pickaway Country Club",
    "wof:placetype": "venue"
  },
  "geometry": {"coordinates":[-82.9064,39.601238],"type":"Point"}
}
