{
  "type": "Feature",
  "properties": {
    "addr:full":"10378 Dowling Rd Perrysburg OH 43551",
    "addr:housenumber":"10378",
    "addr:postcode":"43551",
    "addr:street":"Dowling Rd",
    "iso:country":"US",
    "sg:address":"10378 Dowling Rd",
    "sg:city":"Perrysburg",
    "sg:classifiers":[
        {
            "category":"Government",
            "subcategory":"Office",
            "type":"Public Place"
        }
    ],
    "sg:phone":"+1 419 833 1863",
    "sg:postcode":"43551",
    "sg:province":"OH",
    "sg:tags":[
        "housing",
        "program"
    ],
    "wof:name":"GSG Rentals LTD",
    "wof:placetype":"venue"
},
  "geometry": {"coordinates":[-83.600362,41.478049],"type":"Point"}
}