{
  "type": "Feature",
  "properties": {
    "addr:full":"1702 S Limestone St Springfield OH 45505",
    "addr:housenumber":"1702",
    "addr:postcode":"45505",
    "addr:street":"S Limestone St",
    "iso:country":"US",
    "sg:address":"1702 S Limestone St",
    "sg:city":"Springfield",
    "sg:classifiers":[
        {
            "category":"Utilities",
            "subcategory":"Fuel Oil & Lpg",
            "type":"Services"
        }
    ],
    "sg:phone":"+1 937 322 7010",
    "sg:postcode":"45505",
    "sg:province":"OH",
    "sg:tags":[
        "dealer"
    ],
    "wof:name":"Fashion Park",
    "wof:placetype":"venue"
},
  "geometry": {"coordinates":[-83.81042100000001,39.905116],"type":"Point"}
}