{
  "type": "Feature",
  "properties": {
    "addr:full":"462 Bonnie Brae Ave Niles OH 44446",
    "addr:housenumber":"462",
    "addr:postcode":"44446",
    "addr:street":"Bonnie Brae Ave",
    "iso:country":"US",
    "sg:address":"462 Bonnie Brae Ave",
    "sg:city":"Niles",
    "sg:classifiers":[
        {
            "category":"Building & Trades",
            "subcategory":"Construction",
            "type":"Services"
        }
    ],
    "sg:phone":"+1 330 652 1164",
    "sg:postcode":"44446",
    "sg:province":"OH",
    "sg:tags":[
        "contractor"
    ],
    "wof:name":"T & D Thermal Acoustics",
    "wof:placetype":"venue"
},
  "geometry": {"coordinates":[-80.73389,41.191187],"type":"Point"}
}