{
  "type": "Feature",
  "properties": {
    "addr:full": "522 Lenora St Dover OH 44622",
    "addr:housenumber": "522",
    "addr:postcode": "44622",
    "addr:street": "Lenora St",
    "iso:country": "US",
    "sg:address": "522 Lenora St",
    "sg:city": "Dover",
    "sg:classifiers": [
      {
        "category": "Building \u0026 Trades",
        "subcategory": "Construction",
        "type": "Services"
      }
    ],
    "sg:phone": "+1 330 364 1582",
    "sg:postcode": "44622",
    "sg:province": "OH",
    "sg:tags": [
      "dry wall",
      "contractor"
    ],
    "wof:name": "Custom Drywall \u0026 More",
    "wof:placetype": "venue"
  },
  "geometry": {"coordinates":[-81.472141,40.509145],"type":"Point"}
}
