{
  "type": "Feature",
  "properties": {
    "iso:country":"US",
    "sg:address":"522 Lenora St",
    "sg:city":"Dover",
    "sg:classifiers":[
        {
            "category":"Building & Trades",
            "subcategory":"Construction",
            "type":"Services"
        }
    ],
    "sg:phone":"+1 330 364 1582",
    "sg:postcode":"44622",
    "sg:province":"OH",
    "sg:tags":[
        "dry wall",
        "contractor"
    ],
    "wof:name":"Custom Drywall & More",
    "wof:placetype":"venue"
},
  "geometry": {"coordinates":[-81.47214099999999,40.509145],"type":"Point"}
}