{
  "type": "Feature",
  "properties": {
    "addr:full": "14300 Euclid Ave Cleveland OH 44112",
    "addr:housenumber": "14300",
    "addr:postcode": "44112",
    "addr:street": "Euclid Ave",
    "iso:country": "US",
    "sg:address": "14300 Euclid Ave",
    "sg:city": "Cleveland",
    "sg:classifiers": [
      {
        "category": "Banks \u0026 Credit Unions",
        "subcategory": "Bank",
        "type": "Services"
      }
    ],
    "sg:phone": "+1 216 761 1871",
    "sg:postcode": "44112",
    "sg:province": "OH",
    "sg:tags": [
      "cashing",
      "check"
    ],
    "wof:name": "American Cash Exchange",
    "wof:placetype": "venue"
  },
  "geometry": {"coordinates":[-81.582031,41.530373],"type":"Point"}
}
