{
  "type": "Feature",
  "properties": {
    "iso:country":"US",
    "sg:address":"205 W 4th St",
    "sg:city":"Cincinnati",
    "sg:classifiers":[
        {
            "category":"Real Estate",
            "subcategory":"Real Estate Agent",
            "type":"Services"
        }
    ],
    "sg:phone":"+1 513 763 7600",
    "sg:postcode":"45202",
    "sg:province":"OH",
    "wof:name":"KOLL Management",
    "wof:placetype":"venue"
},
  "geometry": {"coordinates":[-84.516501,39.099303],"type":"Point"}
}