{
  "type": "Feature",
  "properties": {
    "addr:full":"265 W Coshocton St Johnstown OH 43031",
    "addr:housenumber":"265",
    "addr:postcode":"43031",
    "addr:street":"W Coshocton St",
    "iso:country":"US",
    "sg:address":"265 W Coshocton St",
    "sg:city":"Johnstown",
    "sg:classifiers":[
        {
            "category":"Autos & Motor Vehicles",
            "subcategory":"Fuel & Gas Station",
            "type":"Retail Goods"
        }
    ],
    "sg:phone":"+1 740 967 2916",
    "sg:postcode":"43031",
    "sg:province":"OH",
    "sg:tags":[
        "oil"
    ],
    "wof:name":"Johnstown BP Svc Ctr",
    "wof:placetype":"venue"
},
  "geometry": {"coordinates":[-82.69079000000001,40.150898],"type":"Point"}
}