{
  "type": "Feature",
  "properties": {
    "addr:full":"1509 Golden Gate Plz Cleveland OH 44124",
    "addr:housenumber":"1509",
    "addr:postcode":"44124",
    "addr:street":"Golden Gate Plz",
    "iso:country":"US",
    "sg:address":"1509 Golden Gate Plz",
    "sg:city":"Cleveland",
    "sg:classifiers":[
        {
            "category":"Shopping",
            "subcategory":"Shoes",
            "type":"Retail Goods"
        }
    ],
    "sg:phone":"+1 440 442 8464",
    "sg:postcode":"44124",
    "sg:province":"OH",
    "wof:name":"Dallas Shoes Mayfield Hts",
    "wof:placetype":"venue"
},
  "geometry": {"coordinates":[-81.449094,41.518908],"type":"Point"}
}