{
  "type": "Feature",
  "properties": {
    "iso:country":"US",
    "sg:address":"251 State Rte 511",
    "sg:city":"Nova",
    "sg:classifiers":[
        {
            "category":"Building & Trades",
            "subcategory":"Electrical",
            "type":"Services"
        }
    ],
    "sg:phone":"+1 419 652 2626",
    "sg:postcode":"44859",
    "sg:province":"OH",
    "sg:tags":[
        "electrical",
        "contractor"
    ],
    "wof:name":"Russ Electric Inc",
    "wof:placetype":"venue"
},
  "geometry": {"coordinates":[-82.30481,41.029012],"type":"Point"}
}