{
  "type": "Feature",
  "properties": {
    "addr:full": "2095 Co Rd 57 W Huntsville OH 43324",
    "addr:housenumber": "2095;57",
    "addr:postcode": "43324",
    "addr:street": "Co Rd;W",
    "iso:country": "US",
    "sg:address": "2095 Co Rd 57 W",
    "sg:city": "Huntsville",
    "sg:classifiers": [
      {
        "category": "Building \u0026 Trades",
        "subcategory": "Construction",
        "type": "Services"
      }
    ],
    "sg:phone": "+1 937 593 5173",
    "sg:postcode": "43324",
    "sg:province": "OH",
    "sg:tags": [
      "paving",
      "contractor"
    ],
    "wof:name": "H \u0026 S Asphalt",
    "wof:placetype": "venue"
  },
  "geometry": {"coordinates":[-83.776348,40.413016],"type":"Point"}
}
