{
  "type": "Feature",
  "properties": {
    "iso:country":"US",
    "sg:address":"2095 Co Rd 57 W",
    "sg:city":"Huntsville",
    "sg:classifiers":[
        {
            "category":"Building & Trades",
            "subcategory":"Construction",
            "type":"Services"
        }
    ],
    "sg:phone":"+1 937 593 5173",
    "sg:postcode":"43324",
    "sg:province":"OH",
    "sg:tags":[
        "paving",
        "contractor"
    ],
    "wof:name":"H & S Asphalt",
    "wof:placetype":"venue"
},
  "geometry": {"coordinates":[-83.776348,40.413016],"type":"Point"}
}