{
  "type": "Feature",
  "properties": {
    "addr:full":"9688 Eby Rd Germantown OH 45327",
    "addr:housenumber":"9688",
    "addr:postcode":"45327",
    "addr:street":"Eby Rd",
    "iso:country":"US",
    "sg:address":"9688 Eby Rd",
    "sg:city":"Germantown",
    "sg:classifiers":[
        {
            "category":"Recreation",
            "type":"Entertainment"
        }
    ],
    "sg:phone":"+1 937 275 7275",
    "sg:postcode":"45327",
    "sg:province":"OH",
    "sg:tags":[
        "parks"
    ],
    "wof:name":"Twin Creek Metropark",
    "wof:placetype":"venue"
},
  "geometry": {"coordinates":[-84.36533,39.599074],"type":"Point"}
}