{
  "type": "Feature",
  "properties": {
    "iso:country":"US",
    "sg:address":"264 Upper River Rd",
    "sg:city":"Gallipolis",
    "sg:classifiers":[
        {
            "category":"Autos & Motor Vehicles",
            "subcategory":"Automobile Sales",
            "type":"Retail Goods"
        }
    ],
    "sg:phone":"+1 740 446 9971",
    "sg:postcode":"45631",
    "sg:province":"OH",
    "sg:tags":[
        "used"
    ],
    "wof:name":"Kennys Auto Rental",
    "wof:placetype":"venue"
},
  "geometry": {"coordinates":[-82.153647,38.834934],"type":"Point"}
}