{
  "type": "Feature",
  "properties": {
    "addr:full": "10061 Harrison Ave Harrison OH 45030",
    "addr:housenumber": "10061",
    "addr:postcode": "45030",
    "addr:street": "Harrison Ave",
    "iso:country": "US",
    "sg:address": "10061 Harrison Ave",
    "sg:city": "Harrison",
    "sg:classifiers": [
      {
        "category": "Farming",
        "subcategory": "Nursery",
        "type": "Manufacturing \u0026 Wholesale Goods"
      }
    ],
    "sg:phone": "+1 513 367 4838",
    "sg:postcode": "45030",
    "sg:province": "OH",
    "sg:tags": [
      "ornamental"
    ],
    "wof:name": "Growing Interest Inc",
    "wof:placetype": "venue"
  },
  "geometry": {"coordinates":[-84.778273,39.243093],"type":"Point"}
}
