{
  "type": "Feature",
  "properties": {
    "addr:full":"1819 N Westwood Ave Toledo OH 43607",
    "addr:housenumber":"1819",
    "addr:postcode":"43607",
    "addr:street":"N Westwood Ave",
    "iso:country":"US",
    "sg:address":"1819 N Westwood Ave",
    "sg:city":"Toledo",
    "sg:classifiers":[
        {
            "category":"Autos & Motor Vehicles",
            "subcategory":"Fuel & Gas Station",
            "type":"Retail Goods"
        }
    ],
    "sg:phone":"+1 419 698 6926",
    "sg:postcode":"43607",
    "sg:province":"OH",
    "sg:tags":[
        "station",
        "gasoline"
    ],
    "wof:name":"Sunoco",
    "wof:placetype":"venue"
},
  "geometry": {"coordinates":[-83.607741,41.658156],"type":"Point"}
}