{
  "type": "Feature",
  "properties": {
    "addr:full":"106 Linden St Cincinnati OH 45216",
    "addr:housenumber":"106",
    "addr:postcode":"45216",
    "addr:street":"Linden St",
    "iso:country":"US",
    "sg:address":"106 Linden St",
    "sg:city":"Cincinnati",
    "sg:classifiers":[
        {
            "category":"Government",
            "subcategory":"Office",
            "type":"Public Place"
        }
    ],
    "sg:phone":"+1 859 292 5769",
    "sg:postcode":"45216",
    "sg:province":"OH",
    "sg:tags":[
        "policy"
    ],
    "wof:name":"Internal Revenue Service",
    "wof:placetype":"venue"
},
  "geometry": {"coordinates":[-84.486362,39.1848],"type":"Point"}
}