{
  "type": "Feature",
  "properties": {
    "addr:full":"9368 Mentor Ave Mentor OH 44060",
    "addr:housenumber":"9368",
    "addr:postcode":"44060",
    "addr:street":"Mentor Ave",
    "iso:country":"US",
    "sg:address":"9368 Mentor Ave",
    "sg:city":"Mentor",
    "sg:classifiers":[
        {
            "category":"Shopping",
            "type":"Retail Goods"
        }
    ],
    "sg:phone":"+1 440 266 1999",
    "sg:postcode":"44060",
    "sg:province":"OH",
    "sg:tags":[
        "telephone",
        "cellular"
    ],
    "wof:name":"I Wireless",
    "wof:placetype":"venue"
},
  "geometry": {"coordinates":[-81.30749,41.677876],"type":"Point"}
}