{
  "type": "Feature",
  "properties": {
    "iso:country":"US",
    "sg:address":"9723 Kenwood Rd",
    "sg:city":"Cincinnati",
    "sg:classifiers":[
        {
            "category":"Shopping",
            "subcategory":"Bicycles & Sporting Goods",
            "type":"Retail Goods"
        }
    ],
    "sg:phone":"+1 513 791 8888",
    "sg:postcode":"45242",
    "sg:province":"OH",
    "sg:tags":[
        "equipment",
        "arts",
        "supply",
        "martial"
    ],
    "sg:website":"www.ahntkd.com",
    "wof:name":"Ahn's Taekwondo Institute",
    "wof:placetype":"venue"
},
  "geometry": {"coordinates":[-84.376721,39.234766],"type":"Point"}
}