{
  "type": "Feature",
  "properties": {
    "addr:full": "2717 N Reynolds Rd Toledo OH 43615",
    "addr:housenumber": "2717",
    "addr:postcode": "43615",
    "addr:street": "N Reynolds Rd",
    "iso:country": "US",
    "sg:address": "2717 N Reynolds Rd",
    "sg:city": "Toledo",
    "sg:classifiers": [
      {
        "category": "Shopping",
        "subcategory": "Used Merchandise",
        "type": "Retail Goods"
      }
    ],
    "sg:phone": "+1 419 536 1900",
    "sg:postcode": "43615",
    "sg:province": "OH",
    "sg:tags": [
      "antique"
    ],
    "wof:name": "Wildwood Antiques Center",
    "wof:placetype": "venue"
  },
  "geometry": {"coordinates":[-83.672669,41.675178],"type":"Point"}
}
