{
  "type": "Feature",
  "properties": {
    "addr:full":"4859 W Sylvania Ave Toledo OH 43623",
    "addr:housenumber":"4859",
    "addr:postcode":"43623",
    "addr:street":"W Sylvania Ave",
    "iso:country":"US",
    "sg:address":"4859 W Sylvania Ave",
    "sg:city":"Toledo",
    "sg:classifiers":[
        {
            "category":"Professional",
            "subcategory":"Lawyer & Legal Services",
            "type":"Services"
        }
    ],
    "sg:phone":"+1 419 841 0792",
    "sg:postcode":"43623",
    "sg:province":"OH",
    "sg:tags":[
        "attorney"
    ],
    "wof:name":"V Robert Candiello",
    "wof:placetype":"venue"
},
  "geometry": {"coordinates":[-83.658788,41.691019],"type":"Point"}
}