{
  "type": "Feature",
  "properties": {
    "iso:country":"US",
    "sg:address":"870 E 77th St",
    "sg:city":"Cleveland",
    "sg:classifiers":[
        {
            "category":"Wholesale",
            "subcategory":"Machinery & Supplies",
            "type":"Manufacturing & Wholesale Goods"
        }
    ],
    "sg:phone":"+1 216 251 5656",
    "sg:postcode":"44103",
    "sg:province":"OH",
    "sg:tags":[
        "equipment",
        "material",
        "handling"
    ],
    "wof:name":"Erie Industrial Equipment",
    "wof:placetype":"venue"
},
  "geometry": {"coordinates":[-81.63554000000001,41.527286],"type":"Point"}
}