{
  "type": "Feature",
  "properties": {
    "addr:full": "870 E 77th St Cleveland OH 44103",
    "addr:housenumber": "870",
    "addr:postcode": "44103",
    "addr:street": "E 77Th St",
    "iso:country": "US",
    "sg:address": "870 E 77th St",
    "sg:city": "Cleveland",
    "sg:classifiers": [
      {
        "category": "Wholesale",
        "subcategory": "Machinery \u0026 Supplies",
        "type": "Manufacturing \u0026 Wholesale Goods"
      }
    ],
    "sg:phone": "+1 216 251 5656",
    "sg:postcode": "44103",
    "sg:province": "OH",
    "sg:tags": [
      "equipment",
      "material",
      "handling"
    ],
    "wof:name": "Erie Industrial Equipment",
    "wof:placetype": "venue"
  },
  "geometry": {"coordinates":[-81.63554,41.527286],"type":"Point"}
}
