{
  "type": "Feature",
  "properties": {
    "addr:full": "639 Scioto St Urbana OH 43078",
    "addr:housenumber": "639",
    "addr:postcode": "43078",
    "addr:street": "Scioto St",
    "iso:country": "US",
    "sg:address": "639 Scioto St",
    "sg:city": "Urbana",
    "sg:classifiers": [
      {
        "category": "Ice Cream",
        "type": "Food \u0026 Drink"
      }
    ],
    "sg:menulink": "http://www.allmenus.com/oh/urbana/165263-dairy-queen/menu/",
    "sg:phone": "+1 937 653 3331",
    "sg:postcode": "43078",
    "sg:province": "OH",
    "sg:tags": [
      "burger",
      "american"
    ],
    "wof:name": "Dairy Queen",
    "wof:placetype": "venue"
  },
  "geometry": {"coordinates":[-83.739932,40.107321],"type":"Point"}
}
