{
  "type": "Feature",
  "properties": {
    "addr:full": "2730 Som Center Rd Willoughby OH 44094",
    "addr:postcode": "2730;44094",
    "addr:street": "Som Center Rd",
    "iso:country": "US",
    "sg:address": "2730 Som Center Rd",
    "sg:city": "Willoughby",
    "sg:classifiers": [
      {
        "category": "Home \u0026 Garden",
        "subcategory": "Garden Supply",
        "type": "Retail Goods"
      }
    ],
    "sg:phone": "+1 440 944 6066",
    "sg:postcode": "44094",
    "sg:province": "OH",
    "wof:name": "Cleveland Wholesale Garden Sup",
    "wof:placetype": "venue"
  },
  "geometry": {"coordinates":[-81.439529,41.587613],"type":"Point"}
}
