{
  "type": "Feature",
  "properties": {
    "addr:full": "25781 Lake Shore Blvd Cleveland OH 44132",
    "addr:housenumber": "25781",
    "addr:postcode": "44132",
    "addr:street": "Lake Shore Blvd",
    "iso:country": "US",
    "sg:address": "25781 Lake Shore Blvd",
    "sg:city": "Cleveland",
    "sg:classifiers": [
      {
        "category": "Real Estate",
        "subcategory": "Real Estate Operator",
        "type": "Services"
      }
    ],
    "sg:phone": "+1 216 210 3900",
    "sg:postcode": "44132",
    "sg:province": "OH",
    "sg:tags": [
      "apartment",
      "complex"
    ],
    "wof:name": "Bonneville East Apartments",
    "wof:placetype": "venue"
  },
  "geometry": {"coordinates":[-81.50513,41.61973],"type":"Point"}
}
