{
  "type": "Feature",
  "properties": {
    "addr:full":"2636 S Smithville Rd Dayton OH 45420",
    "addr:housenumber":"2636",
    "addr:postcode":"45420",
    "addr:street":"S Smithville Rd",
    "iso:country":"US",
    "sg:address":"2636 S Smithville Rd",
    "sg:city":"Dayton",
    "sg:classifiers":[
        {
            "category":"Autos & Motor Vehicles",
            "subcategory":"Auto Supplies",
            "type":"Retail Goods"
        }
    ],
    "sg:phone":"+1 937 253 5266",
    "sg:postcode":"45420",
    "sg:province":"OH",
    "sg:tags":[
        "automobile",
        "parts"
    ],
    "wof:name":"Advance Auto Parts Inc",
    "wof:placetype":"venue"
},
  "geometry": {"coordinates":[-84.141193,39.729165],"type":"Point"}
}