{
  "type": "Feature",
  "properties": {
    "iso:country":"US",
    "sg:address":"1465 Thiel Rd",
    "sg:city":"Jefferson",
    "sg:classifiers":[
        {
            "category":"Building & Trades",
            "subcategory":"Construction",
            "type":"Services"
        }
    ],
    "sg:phone":"+1 440 576 3267",
    "sg:postcode":"44047",
    "sg:province":"OH",
    "sg:tags":[
        "contractor"
    ],
    "wof:name":"Joe Busch Builders LTD",
    "wof:placetype":"venue"
},
  "geometry": {"coordinates":[-80.809453,41.714111],"type":"Point"}
}