{
  "type": "Feature",
  "properties": {
    "iso:country":"US",
    "sg:address":"6273 Branch Hill-Miamiville Rd",
    "sg:city":"Loveland",
    "sg:classifiers":[
        {
            "category":"Building & Trades",
            "subcategory":"Landscaping Services",
            "type":"Services"
        }
    ],
    "sg:phone":"+1 513 553 2299",
    "sg:postcode":"45140",
    "sg:province":"OH",
    "sg:tags":[
        "tree"
    ],
    "wof:name":"Tree People",
    "wof:placetype":"venue"
},
  "geometry": {"coordinates":[-84.301388,39.227308],"type":"Point"}
}