{
  "type": "Feature",
  "properties": {
    "addr:full": "1681 Honodle Ave Akron OH 44305",
    "addr:housenumber": "1681",
    "addr:postcode": "44305",
    "addr:street": "Honodle Ave",
    "iso:country": "US",
    "sg:address": "1681 Honodle Ave",
    "sg:city": "Akron",
    "sg:classifiers": [
      {
        "category": "Shopping",
        "subcategory": "Computers \u0026 Home Electronics",
        "type": "Retail Goods"
      }
    ],
    "sg:phone": "+1 330 733 9540",
    "sg:postcode": "44305",
    "sg:province": "OH",
    "sg:tags": [
      "software"
    ],
    "wof:name": "Selzer Software Consulting",
    "wof:placetype": "venue"
  },
  "geometry": {"coordinates":[-81.46129,41.074525],"type":"Point"}
}
