{
  "type": "Feature",
  "properties": {
    "iso:country":"US",
    "sg:address":"3411 York Commons Blvd",
    "sg:city":"Dayton",
    "sg:classifiers":[
        {
            "category":"Restaurant",
            "type":"Food & Drink"
        }
    ],
    "sg:menulink":"http://www.allmenus.com/oh/butler/195196-mcdonalds/menu/",
    "sg:postcode":"45414",
    "sg:province":"OH",
    "sg:tags":[
        "burger",
        "american"
    ],
    "wof:name":"McDonald's",
    "wof:placetype":"venue"
},
  "geometry": {"coordinates":[-84.19781500000001,39.844698],"type":"Point"}
}