{
  "type": "Feature",
  "properties": {
    "addr:full": "1159 Dublin Rd Columbus OH 43215",
    "addr:housenumber": "1159",
    "addr:postcode": "43215",
    "addr:street": "Dublin Rd",
    "iso:country": "US",
    "sg:address": "1159 Dublin Rd",
    "sg:city": "Columbus",
    "sg:classifiers": [
      {
        "category": "Professional",
        "subcategory": "Advertising",
        "type": "Services"
      }
    ],
    "sg:phone": "+1 614 457 8118",
    "sg:postcode": "43215",
    "sg:province": "OH",
    "sg:tags": [
      "mail"
    ],
    "wof:name": "David B Bowen \u0026 Assoc Inc",
    "wof:placetype": "venue"
  },
  "geometry": {"coordinates":[-83.050916,39.974277],"type":"Point"}
}
