{
  "type": "Feature",
  "properties": {
    "addr:full": "403 S Front St Fremont OH 43420",
    "addr:housenumber": "403",
    "addr:postcode": "43420",
    "addr:street": "S Front St",
    "iso:country": "US",
    "sg:address": "403 S Front St",
    "sg:city": "Fremont",
    "sg:classifiers": [
      {
        "category": "Manufacturing",
        "subcategory": "Tools \u0026 Machinery",
        "type": "Manufacturing \u0026 Wholesale Goods"
      }
    ],
    "sg:phone": "+1 419 334 9277",
    "sg:postcode": "43420",
    "sg:province": "OH",
    "sg:tags": [
      "industrial",
      "mfg"
    ],
    "wof:name": "Industrial Concepts \u0026 Solution",
    "wof:placetype": "venue"
  },
  "geometry": {"coordinates":[-83.113546,41.343222],"type":"Point"}
}
