{
  "type": "Feature",
  "properties": {
    "iso:country":"US",
    "sg:address":"403 S Front St",
    "sg:city":"Fremont",
    "sg:classifiers":[
        {
            "category":"Manufacturing",
            "subcategory":"Tools & Machinery",
            "type":"Manufacturing & Wholesale Goods"
        }
    ],
    "sg:phone":"+1 419 334 9277",
    "sg:postcode":"43420",
    "sg:province":"OH",
    "sg:tags":[
        "industrial",
        "mfg"
    ],
    "wof:name":"Industrial Concepts & Solution",
    "wof:placetype":"venue"
},
  "geometry": {"coordinates":[-83.113546,41.343222],"type":"Point"}
}