{
  "type": "Feature",
  "properties": {
    "addr:full":"1945 Claremont Ave Ashland OH 44805",
    "addr:housenumber":"1945",
    "addr:postcode":"44805",
    "addr:street":"Claremont Ave",
    "iso:country":"US",
    "sg:address":"1945 Claremont Ave",
    "sg:city":"Ashland",
    "sg:classifiers":[
        {
            "category":"Freight",
            "type":"Transportation"
        }
    ],
    "sg:phone":"+1 419 289 2324",
    "sg:postcode":"44805",
    "sg:province":"OH",
    "sg:tags":[
        "commercial",
        "storage"
    ],
    "wof:name":"Anytime Stor-N-Loc",
    "wof:placetype":"venue"
},
  "geometry": {"coordinates":[-82.341261,40.851291],"type":"Point"}
}