{
  "type": "Feature",
  "properties": {
    "iso:country":"US",
    "sg:address":"1281 E 167th St",
    "sg:city":"Cleveland",
    "sg:classifiers":[
        {
            "category":"Professional",
            "type":"Services"
        }
    ],
    "sg:phone":"+1 216 486 4354",
    "sg:postcode":"44110",
    "sg:province":"OH",
    "wof:name":"Millionaire Dreams In Full Sig",
    "wof:placetype":"venue"
},
  "geometry": {"coordinates":[-81.564122,41.572792],"type":"Point"}
}