{
  "type": "Feature",
  "properties": {
    "addr:full": "450 Elm St Struthers OH 44471",
    "addr:housenumber": "450",
    "addr:postcode": "44471",
    "addr:street": "Elm St",
    "iso:country": "US",
    "sg:address": "450 Elm St",
    "sg:city": "Struthers",
    "sg:classifiers": [
      {
        "category": "Building \u0026 Trades",
        "subcategory": "Landscaping Services",
        "type": "Services"
      }
    ],
    "sg:phone": "+1 330 755 4154",
    "sg:postcode": "44471",
    "sg:province": "OH",
    "sg:tags": [
      "snow",
      "removal"
    ],
    "wof:name": "Constantino Arthur",
    "wof:placetype": "venue"
  },
  "geometry": {"coordinates":[-80.60627,41.055854],"type":"Point"}
}
