{
  "type": "Feature",
  "properties": {
    "addr:full": "4800 Grayton Rd Cleveland OH 44135",
    "addr:housenumber": "4800",
    "addr:postcode": "44135",
    "addr:street": "Grayton Rd",
    "iso:country": "US",
    "sg:address": "4800 Grayton Rd",
    "sg:city": "Cleveland",
    "sg:classifiers": [
      {
        "category": "Government",
        "subcategory": "Office",
        "type": "Public Place"
      }
    ],
    "sg:phone": "+1 216 676 5295",
    "sg:postcode": "44135",
    "sg:province": "OH",
    "sg:tags": [
      "state",
      "program"
    ],
    "wof:name": "Transportation Dept",
    "wof:placetype": "venue"
  },
  "geometry": {"coordinates":[-81.842783,41.421437],"type":"Point"}
}
