{
  "type": "Feature",
  "properties": {
    "addr:full": "10832 Kenwood Rd Cincinnati OH 45242",
    "addr:housenumber": "10832",
    "addr:postcode": "45242",
    "addr:street": "Kenwood Rd",
    "iso:country": "US",
    "sg:address": "10832 Kenwood Rd",
    "sg:city": "Cincinnati",
    "sg:classifiers": [
      {
        "category": "Home \u0026 Garden",
        "subcategory": "Carpets \u0026 Floor Coverings",
        "type": "Retail Goods"
      }
    ],
    "sg:phone": "+1 513 792 9981",
    "sg:postcode": "45242",
    "sg:province": "OH",
    "sg:tags": [
      "dealer",
      "rug"
    ],
    "wof:name": "Invironmentalists",
    "wof:placetype": "venue"
  },
  "geometry": {"coordinates":[-84.374002,39.261275],"type":"Point"}
}
