{
  "type": "Feature",
  "properties": {
    "addr:full": "1300 Wayne Ave Dayton OH 45410",
    "addr:housenumber": "1300",
    "addr:postcode": "45410",
    "addr:street": "Wayne Ave",
    "iso:country": "US",
    "sg:address": "1300 Wayne Ave",
    "sg:city": "Dayton",
    "sg:classifiers": [
      {
        "category": "Manufacturing",
        "subcategory": "Paper Products",
        "type": "Manufacturing \u0026 Wholesale Goods"
      }
    ],
    "sg:phone": "+1 937 254 8422",
    "sg:postcode": "45410",
    "sg:province": "OH",
    "sg:tags": [
      "corrugated",
      "solid",
      "fiber",
      "box"
    ],
    "wof:name": "Dayton Corrugated Packaging",
    "wof:placetype": "venue"
  },
  "geometry": {"coordinates":[-84.173619,39.748919],"type":"Point"}
}
