{
  "type": "Feature",
  "properties": {
    "addr:full":"5838 Highland Ridge Dr Cincinnati OH 45232",
    "addr:housenumber":"5838",
    "addr:postcode":"45232",
    "addr:street":"Highland Ridge Dr",
    "iso:country":"US",
    "sg:address":"5838 Highland Ridge Dr",
    "sg:city":"Cincinnati",
    "sg:classifiers":[
        {
            "category":"Manufacturing",
            "subcategory":"Printing",
            "type":"Manufacturing & Wholesale Goods"
        }
    ],
    "sg:phone":"+1 513 641 0820",
    "sg:postcode":"45232",
    "sg:province":"OH",
    "sg:tags":[
        "printer"
    ],
    "sg:website":"www.htpsi.com",
    "wof:name":"Hi-Tech Printing Svc Inc",
    "wof:placetype":"venue"
},
  "geometry": {"coordinates":[-84.499026,39.192705],"type":"Point"}
}