{
  "type": "Feature",
  "properties": {
    "addr:full": "14540 Co Rd U Napoleon OH 43545",
    "addr:housenumber": "14540",
    "addr:postcode": "43545",
    "addr:street": "Co Rd",
    "iso:country": "US",
    "sg:address": "14540 Co Rd U",
    "sg:city": "Napoleon",
    "sg:classifiers": [
      {
        "category": "Freight",
        "type": "Transportation"
      }
    ],
    "sg:phone": "+1 419 598 8015",
    "sg:postcode": "43545",
    "sg:province": "OH",
    "sg:tags": [
      "grain",
      "elevator"
    ],
    "wof:name": "Gerald Grain Ctr",
    "wof:placetype": "venue"
  },
  "geometry": {"coordinates":[-84.144551,41.45713],"type":"Point"}
}
