{
  "type": "Feature",
  "properties": {
    "iso:country":"US",
    "sg:address":"3601 Columbia Pkwy",
    "sg:city":"Cincinnati",
    "sg:classifiers":[
        {
            "category":"Autos & Motor Vehicles",
            "subcategory":"Fuel & Gas Station",
            "type":"Retail Goods"
        }
    ],
    "sg:phone":"+1 513 871 5206",
    "sg:postcode":"45226",
    "sg:province":"OH",
    "sg:tags":[
        "oil"
    ],
    "wof:name":"Speedway",
    "wof:placetype":"venue"
},
  "geometry": {"coordinates":[-84.43532399999999,39.113758],"type":"Point"}
}