{
  "type": "Feature",
  "properties": {
    "addr:full": "3601 Columbia Pkwy Cincinnati OH 45226",
    "addr:housenumber": "3601",
    "addr:postcode": "45226",
    "addr:street": "Columbia Pkwy",
    "iso:country": "US",
    "sg:address": "3601 Columbia Pkwy",
    "sg:city": "Cincinnati",
    "sg:classifiers": [
      {
        "category": "Autos \u0026 Motor Vehicles",
        "subcategory": "Fuel \u0026 Gas Station",
        "type": "Retail Goods"
      }
    ],
    "sg:phone": "+1 513 871 5206",
    "sg:postcode": "45226",
    "sg:province": "OH",
    "sg:tags": [
      "oil"
    ],
    "wof:name": "Speedway",
    "wof:placetype": "venue"
  },
  "geometry": {"coordinates":[-84.435324,39.113758],"type":"Point"}
}
