{
  "type": "Feature",
  "properties": {
    "iso:country":"US",
    "sg:address":"3766 Ridge Rd",
    "sg:city":"Cleveland",
    "sg:classifiers":[
        {
            "category":"Retail",
            "subcategory":"Auto Repair",
            "type":"Services"
        }
    ],
    "sg:phone":"+1 216 281 4040",
    "sg:postcode":"44144",
    "sg:province":"OH",
    "sg:tags":[
        "exchanging",
        "engine"
    ],
    "wof:name":"Budget Engine Rebuilders",
    "wof:placetype":"venue"
},
  "geometry": {"coordinates":[-81.737911,41.457073],"type":"Point"}
}