{
  "type": "Feature",
  "properties": {
    "addr:full": "45 Rawson Woods Cir Cincinnati OH 45220",
    "addr:housenumber": "45",
    "addr:postcode": "45220",
    "addr:street": "Rawson Woods Cir",
    "iso:country": "US",
    "sg:address": "45 Rawson Woods Cir",
    "sg:city": "Cincinnati",
    "sg:classifiers": [
      {
        "category": "Professional",
        "type": "Services"
      }
    ],
    "sg:phone": "+1 513 861 5745",
    "sg:postcode": "45220",
    "sg:province": "OH",
    "wof:name": "Philip Khoury",
    "wof:placetype": "venue"
  },
  "geometry": {"coordinates":[-84.523602,39.152343],"type":"Point"}
}
