{
  "type": "Feature",
  "properties": {
    "addr:full": "110 E Howard St Willard OH 44890",
    "addr:housenumber": "110",
    "addr:postcode": "44890",
    "addr:street": "E Howard St",
    "iso:country": "US",
    "sg:address": "110 E Howard St",
    "sg:city": "Willard",
    "sg:classifiers": [
      {
        "category": "Health Services",
        "subcategory": "Doctor",
        "type": "Services"
      }
    ],
    "sg:phone": "+1 419 663 5000",
    "sg:postcode": "44890",
    "sg:province": "OH",
    "sg:tags": [
      "physician",
      "surgeon"
    ],
    "wof:name": "Access Orthopedics",
    "wof:placetype": "venue"
  },
  "geometry": {"coordinates":[-82.724611,41.048515],"type":"Point"}
}
