{
  "type": "Feature",
  "properties": {
    "iso:country":"US",
    "sg:address":"80 Park Dr",
    "sg:city":"Thornville",
    "sg:classifiers":[
        {
            "category":"Manufacturing",
            "subcategory":"Petroleum Products",
            "type":"Manufacturing & Wholesale Goods"
        }
    ],
    "sg:phone":"+1 740 246 5168",
    "sg:postcode":"43076",
    "sg:province":"OH",
    "sg:tags":[
        "asphalt",
        "mfg"
    ],
    "wof:name":"Thornville Youth Baseball",
    "wof:placetype":"venue"
},
  "geometry": {"coordinates":[-82.41174700000001,39.924443],"type":"Point"}
}