{
  "type": "Feature",
  "properties": {
    "iso:country":"US",
    "sg:address":"3747 Watkins Rd",
    "sg:city":"Medina",
    "sg:classifiers":[
        {
            "category":"Professional",
            "subcategory":"Management & Consulting",
            "type":"Services"
        }
    ],
    "sg:phone":"+1 330 722 6859",
    "sg:postcode":"44256",
    "sg:province":"OH",
    "sg:tags":[
        "consultant",
        "business"
    ],
    "wof:name":"Boars Co LTD Liability Co",
    "wof:placetype":"venue"
},
  "geometry": {"coordinates":[-81.868109,41.179501],"type":"Point"}
}