{
  "type": "Feature",
  "properties": {
    "addr:full": "13016 Meadow Dr Roseville OH 43777",
    "addr:housenumber": "13016",
    "addr:postcode": "43777",
    "addr:street": "Meadow Dr",
    "iso:country": "US",
    "sg:address": "13016 Meadow Dr",
    "sg:city": "Roseville",
    "sg:classifiers": [
      {
        "category": "Professional",
        "type": "Services"
      }
    ],
    "sg:phone": "+1 740 215 3005",
    "sg:postcode": "43777",
    "sg:province": "OH",
    "wof:name": "Dolores C Carruthers",
    "wof:placetype": "venue"
  },
  "geometry": {"coordinates":[-82.07767,39.812197],"type":"Point"}
}
