{
  "type": "Feature",
  "properties": {
    "addr:full":"3200 Epworth Ave Cincinnati OH 45211",
    "addr:housenumber":"3200",
    "addr:postcode":"45211",
    "addr:street":"Epworth Ave",
    "iso:country":"US",
    "sg:address":"3200 Epworth Ave",
    "sg:city":"Cincinnati",
    "sg:classifiers":[
        {
            "category":"Freight",
            "type":"Transportation"
        }
    ],
    "sg:phone":"+1 513 661 8600",
    "sg:postcode":"45211",
    "sg:province":"OH",
    "sg:tags":[
        "arrangement"
    ],
    "wof:name":"Transnet",
    "wof:placetype":"venue"
},
  "geometry": {"coordinates":[-84.60040499999999,39.143303],"type":"Point"}
}