{
  "type": "Feature",
  "properties": {
    "addr:full": "2644 Wildcat Rd Greenville OH 45331",
    "addr:housenumber": "2644",
    "addr:postcode": "45331",
    "addr:street": "Wildcat Rd",
    "iso:country": "US",
    "sg:address": "2644 Wildcat Rd",
    "sg:city": "Greenville",
    "sg:phone": "+1 937 548 0531",
    "sg:postcode": "45331",
    "sg:province": "OH",
    "sg:tags": [
      "farm",
      "corn",
      "wheat",
      "soybean"
    ],
    "wof:name": "Dan Grimes",
    "wof:placetype": "venue"
  },
  "geometry": {"coordinates":[-84.707574,40.121262],"type":"Point"}
}
