{
  "type": "Feature",
  "properties": {
    "addr:full": "1932 S Taylor Rd Cleveland OH 44118",
    "addr:housenumber": "1932",
    "addr:postcode": "44118",
    "addr:street": "S Taylor Rd",
    "iso:country": "US",
    "sg:address": "1932 S Taylor Rd",
    "sg:city": "Cleveland",
    "sg:classifiers": [
      {
        "category": "Restaurant",
        "type": "Food \u0026 Drink"
      }
    ],
    "sg:phone": "+1 216 932 3823",
    "sg:postcode": "44118",
    "sg:province": "OH",
    "wof:name": "Gibb's Restaurant",
    "wof:placetype": "venue"
  },
  "geometry": {"coordinates":[-81.555833,41.506307],"type":"Point"}
}
