{
  "type": "Feature",
  "properties": {
    "iso:country":"US",
    "sg:address":"30 Neise Ave",
    "sg:city":"Toledo",
    "sg:classifiers":[
        {
            "category":"Building & Trades",
            "subcategory":"Construction",
            "type":"Services"
        }
    ],
    "sg:phone":"+1 419 698 9901",
    "sg:postcode":"43605",
    "sg:province":"OH",
    "sg:tags":[
        "contractor"
    ],
    "wof:name":"American Fence Co",
    "wof:placetype":"venue"
},
  "geometry": {"coordinates":[-83.529089,41.638687],"type":"Point"}
}