{
  "type": "Feature",
  "properties": {
    "addr:full": "20 Governors Pl Columbus OH 43203",
    "addr:housenumber": "20",
    "addr:postcode": "43203",
    "addr:street": "Governors Pl",
    "iso:country": "US",
    "sg:address": "20 Governors Pl",
    "sg:city": "Columbus",
    "sg:classifiers": [
      {
        "category": "Organizations",
        "subcategory": "Membership Organization",
        "type": "Services"
      },
      {
        "category": "Education",
        "subcategory": "Special Training",
        "type": "Public Place"
      }
    ],
    "sg:phone": "+1 614 253 7699",
    "sg:postcode": "43203",
    "sg:province": "OH",
    "sg:tags": [
      "reading",
      "instruction",
      "improvement"
    ],
    "sg:website": "www.iknowican.org",
    "wof:name": "I Know I Can Co",
    "wof:placetype": "venue"
  },
  "geometry": {"coordinates":[-82.968451,39.966177],"type":"Point"}
}
