{
  "type": "Feature",
  "properties": {
    "addr:full":"2526 Barrington Rd Akron OH 44333",
    "addr:housenumber":"2526",
    "addr:postcode":"44333",
    "addr:street":"Barrington Rd",
    "iso:country":"US",
    "sg:address":"2526 Barrington Rd",
    "sg:city":"Akron",
    "sg:classifiers":[
        {
            "category":"Education",
            "subcategory":"Vocational School",
            "type":"Public Place"
        }
    ],
    "sg:phone":"+1 330 865 0761",
    "sg:postcode":"44333",
    "sg:province":"OH",
    "sg:tags":[
        "teaching",
        "search",
        "court"
    ],
    "wof:name":"Capitol Court Reporting & Capt",
    "wof:placetype":"venue"
},
  "geometry": {"coordinates":[-81.60170599999999,41.135366],"type":"Point"}
}