{
  "type": "Feature",
  "properties": {
    "iso:country":"US",
    "sg:address":"3811 Bridgeview Dr",
    "sg:city":"Cleveland",
    "sg:classifiers":[
        {
            "category":"Professional",
            "type":"Services"
        }
    ],
    "sg:phone":"+1 216 691 1885",
    "sg:postcode":"44121",
    "sg:province":"OH",
    "wof:name":"Craig T Strasshofer",
    "wof:placetype":"venue"
},
  "geometry": {"coordinates":[-81.546379,41.545592],"type":"Point"}
}