{
  "type": "Feature",
  "properties": {
    "addr:full": "438 E Main St Ashland OH 44805",
    "addr:housenumber": "438",
    "addr:postcode": "44805",
    "addr:street": "E Main St",
    "iso:country": "US",
    "sg:address": "438 E Main St",
    "sg:city": "Ashland",
    "sg:classifiers": [
      {
        "category": "Building \u0026 Trades",
        "subcategory": "Electrical",
        "type": "Services"
      }
    ],
    "sg:phone": "+1 419 289 1518",
    "sg:postcode": "44805",
    "sg:province": "OH",
    "sg:tags": [
      "electrical",
      "electric",
      "contractor"
    ],
    "wof:name": "Strong Electric Inc",
    "wof:placetype": "venue"
  },
  "geometry": {"coordinates":[-82.306991,40.867901],"type":"Point"}
}
