{
  "type": "Feature",
  "properties": {
    "iso:country":"US",
    "sg:address":"438 E Main St",
    "sg:city":"Ashland",
    "sg:classifiers":[
        {
            "category":"Building & Trades",
            "subcategory":"Electrical",
            "type":"Services"
        }
    ],
    "sg:phone":"+1 419 289 1518",
    "sg:postcode":"44805",
    "sg:province":"OH",
    "sg:tags":[
        "electrical",
        "electric",
        "contractor"
    ],
    "wof:name":"Strong Electric Inc",
    "wof:placetype":"venue"
},
  "geometry": {"coordinates":[-82.306991,40.867901],"type":"Point"}
}