{
  "type": "Feature",
  "properties": {
    "addr:full": "255 W High St London OH 43140",
    "addr:housenumber": "255",
    "addr:postcode": "43140",
    "addr:street": "W High St",
    "iso:country": "US",
    "sg:address": "255 W High St",
    "sg:city": "London",
    "sg:classifiers": [
      {
        "category": "Insurance",
        "subcategory": "Insurance Agent",
        "type": "Services"
      }
    ],
    "sg:phone": "+1 740 852 2266",
    "sg:postcode": "43140",
    "sg:province": "OH",
    "wof:name": "Kronk \u0026 Scaggs Insurance Inc",
    "wof:placetype": "venue"
  },
  "geometry": {"coordinates":[-83.458348,39.880395],"type":"Point"}
}
