{
  "type": "Feature",
  "properties": {
    "iso:country":"US",
    "sg:address":"4802 Hillgrove-Woodington Rd",
    "sg:city":"Ansonia",
    "sg:phone":"+1 937 548 6107",
    "sg:postcode":"45303",
    "sg:province":"OH",
    "sg:tags":[
        "farm",
        "corn",
        "soybean"
    ],
    "wof:name":"Dan Hartzell",
    "wof:placetype":"venue"
},
  "geometry": {"coordinates":[-84.622834,40.178783],"type":"Point"}
}