{
  "type": "Feature",
  "properties": {
    "iso:country":"US",
    "sg:address":"10518 Pemberville Rd",
    "sg:city":"Wayne",
    "sg:classifiers":[
        {
            "category":"Building & Trades",
            "subcategory":"Construction",
            "type":"Services"
        }
    ],
    "sg:phone":"+1 419 288 3621",
    "sg:postcode":"43466",
    "sg:province":"OH",
    "sg:tags":[
        "special",
        "contractor"
    ],
    "wof:name":"J & M Alexander Construction",
    "wof:placetype":"venue"
},
  "geometry": {"coordinates":[-83.456502,41.310363],"type":"Point"}
}