{
  "type": "Feature",
  "properties": {
    "addr:full":"2552 Lockbourne Rd Columbus OH 43207",
    "addr:housenumber":"2552",
    "addr:postcode":"43207",
    "addr:street":"Lockbourne Rd",
    "iso:country":"US",
    "sg:address":"2552 Lockbourne Rd",
    "sg:city":"Columbus",
    "sg:classifiers":[
        {
            "category":"Food & Beverages",
            "subcategory":"Groceries & Convenience Stores",
            "type":"Retail Goods"
        }
    ],
    "sg:phone":"+1 614 491 7600",
    "sg:postcode":"43207",
    "sg:province":"OH",
    "wof:name":"B & M Market",
    "wof:placetype":"venue"
},
  "geometry": {"coordinates":[-82.965953,39.915047],"type":"Point"}
}