{
  "type": "Feature",
  "properties": {
    "addr:full": "114 W 2nd St Cardington OH 43315",
    "addr:housenumber": "114",
    "addr:postcode": "43315",
    "addr:street": "W 2Nd St",
    "iso:country": "US",
    "sg:address": "114 W 2nd St",
    "sg:city": "Cardington",
    "sg:classifiers": [
      {
        "category": "Retail",
        "subcategory": "Laundry \u0026 Dry Cleaning",
        "type": "Services"
      }
    ],
    "sg:phone": "+1 740 965 8163",
    "sg:postcode": "43315",
    "sg:province": "OH",
    "wof:name": "Cardington Coin Laundry",
    "wof:placetype": "venue"
  },
  "geometry": {"coordinates":[-82.894954,40.499677],"type":"Point"}
}
