{
  "type": "Feature",
  "properties": {
    "iso:country":"US",
    "sg:address":"114 W 2nd St",
    "sg:city":"Cardington",
    "sg:classifiers":[
        {
            "category":"Retail",
            "subcategory":"Laundry & Dry Cleaning",
            "type":"Services"
        }
    ],
    "sg:phone":"+1 740 965 8163",
    "sg:postcode":"43315",
    "sg:province":"OH",
    "wof:name":"Cardington Coin Laundry",
    "wof:placetype":"venue"
},
  "geometry": {"coordinates":[-82.894954,40.499677],"type":"Point"}
}