{
  "type": "Feature",
  "properties": {
    "iso:country":"US",
    "sg:address":"2100 State Rte 59",
    "sg:city":"Kent",
    "sg:classifiers":[
        {
            "category":"Retail",
            "subcategory":"Car Wash",
            "type":"Services"
        }
    ],
    "sg:phone":"+1 330 474 0555",
    "sg:postcode":"44240",
    "sg:province":"OH",
    "sg:tags":[
        "automobile",
        "detail",
        "clean"
    ],
    "wof:name":"Custom Car Concepts",
    "wof:placetype":"venue"
},
  "geometry": {"coordinates":[-81.31403,41.156318],"type":"Point"}
}