{
  "type": "Feature",
  "properties": {
    "addr:full":"8500 Station St Mentor OH 44060",
    "addr:housenumber":"8500",
    "addr:postcode":"44060",
    "addr:street":"Station St",
    "iso:country":"US",
    "sg:address":"8500 Station St",
    "sg:city":"Mentor",
    "sg:classifiers":[
        {
            "category":"Insurance",
            "subcategory":"Insurance Agent",
            "type":"Services"
        }
    ],
    "sg:phone":"+1 440 255 2485",
    "sg:postcode":"44060",
    "sg:province":"OH",
    "sg:website":"www.goodhueinsurance.com",
    "wof:name":"Goodhue Insurance",
    "wof:placetype":"venue"
},
  "geometry": {"coordinates":[-81.337295,41.678921],"type":"Point"}
}