{
  "type": "Feature",
  "properties": {
    "addr:full": "315 S West St Lebanon OH 45036",
    "addr:housenumber": "315",
    "addr:postcode": "west;45036",
    "addr:street": "S;St",
    "iso:country": "US",
    "sg:address": "315 S West St",
    "sg:city": "Lebanon",
    "sg:classifiers": [
      {
        "category": "Manufacturing",
        "subcategory": "Rubber \u0026 Plastics",
        "type": "Manufacturing \u0026 Wholesale Goods"
      }
    ],
    "sg:phone": "+1 513 932 5130",
    "sg:postcode": "45036",
    "sg:province": "OH",
    "sg:tags": [
      "product",
      "mfg"
    ],
    "wof:name": "Innatech LLC",
    "wof:placetype": "venue"
  },
  "geometry": {"coordinates":[-84.215647,39.432766],"type":"Point"}
}
