{
  "type": "Feature",
  "properties": {
    "iso:country":"US",
    "sg:address":"315 S West St",
    "sg:city":"Lebanon",
    "sg:classifiers":[
        {
            "category":"Manufacturing",
            "subcategory":"Rubber & Plastics",
            "type":"Manufacturing & Wholesale Goods"
        }
    ],
    "sg:phone":"+1 513 932 5130",
    "sg:postcode":"45036",
    "sg:province":"OH",
    "sg:tags":[
        "product",
        "mfg"
    ],
    "wof:name":"Innatech LLC",
    "wof:placetype":"venue"
},
  "geometry": {"coordinates":[-84.215647,39.432766],"type":"Point"}
}