{
  "type": "Feature",
  "properties": {
    "iso:country":"US",
    "sg:address":"631 Central Center",
    "sg:city":"Chillicothe",
    "sg:classifiers":[
        {
            "category":"Professional",
            "subcategory":"Accounting & Tax Preparation",
            "type":"Services"
        }
    ],
    "sg:phone":"+1 740 779 9181",
    "sg:postcode":"45601",
    "sg:province":"OH",
    "sg:tags":[
        "accountant"
    ],
    "wof:name":"David R Dilley Inc",
    "wof:placetype":"venue"
},
  "geometry": {"coordinates":[-83.002054,39.337169],"type":"Point"}
}