{
  "type": "Feature",
  "properties": {
    "iso:country":"US",
    "sg:address":"6975 Patterson-Halpin Rd",
    "sg:city":"Sidney",
    "sg:classifiers":[
        {
            "category":"Farming",
            "subcategory":"Farm",
            "type":"Manufacturing & Wholesale Goods"
        }
    ],
    "sg:phone":"+1 937 492 7339",
    "sg:postcode":"45365",
    "sg:province":"OH",
    "sg:tags":[
        "crop",
        "general"
    ],
    "wof:name":"Jeffrey Eilerman",
    "wof:placetype":"venue"
},
  "geometry": {"coordinates":[-84.264399,40.291672],"type":"Point"}
}