{
  "type": "Feature",
  "properties": {
    "iso:country":"US",
    "sg:address":"9525 Kenwood Rd",
    "sg:city":"Cincinnati",
    "sg:classifiers":[
        {
            "category":"Shopping",
            "subcategory":"Luggage & Leather Goods",
            "type":"Retail Goods"
        }
    ],
    "sg:phone":"+1 513 793 2996",
    "sg:postcode":"45242",
    "sg:province":"OH",
    "wof:name":"American Luggage & Leather",
    "wof:placetype":"venue"
},
  "geometry": {"coordinates":[-84.377153,39.230829],"type":"Point"}
}