{
  "type": "Feature",
  "properties": {
    "addr:full": "3115 W Market St Fairlawn OH 44333",
    "addr:housenumber": "3115",
    "addr:postcode": "44333",
    "addr:street": "W Market St",
    "iso:country": "US",
    "sg:address": "3115 W Market St",
    "sg:city": "Fairlawn",
    "sg:classifiers": [
      {
        "category": "Wholesale",
        "subcategory": "Durable Goods \u0026 Equipment",
        "type": "Manufacturing \u0026 Wholesale Goods"
      }
    ],
    "sg:phone": "+1 330 864 2135",
    "sg:postcode": "44333",
    "sg:province": "OH",
    "sg:tags": [
      "representative",
      "manufacturer"
    ],
    "wof:name": "Leverett A Anderson Co",
    "wof:placetype": "venue"
  },
  "geometry": {"coordinates":[-81.613337,41.129825],"type":"Point"}
}
