{
  "type": "Feature",
  "properties": {
    "addr:full":"1181 Tioga Ave Akron OH 44305",
    "addr:housenumber":"1181",
    "addr:postcode":"44305",
    "addr:street":"Tioga Ave",
    "iso:country":"US",
    "sg:address":"1181 Tioga Ave",
    "sg:city":"Akron",
    "sg:classifiers":[
        {
            "category":"Professional",
            "subcategory":"Management & Consulting",
            "type":"Services"
        }
    ],
    "sg:phone":"+1 330 733 0840",
    "sg:postcode":"44305",
    "sg:province":"OH",
    "sg:tags":[
        "marketing",
        "consultant"
    ],
    "wof:name":"TLC Assoc",
    "wof:placetype":"venue"
},
  "geometry": {"coordinates":[-81.47548500000001,41.088291],"type":"Point"}
}