{
  "type": "Feature",
  "properties": {
    "addr:full":"11788 Market St North Lima OH 44452",
    "addr:housenumber":"11788",
    "addr:postcode":"44452",
    "addr:street":"Market St",
    "iso:country":"US",
    "sg:address":"11788 Market St",
    "sg:city":"North Lima",
    "sg:classifiers":[
        {
            "category":"Home & Garden",
            "subcategory":"Hardware",
            "type":"Retail Goods"
        }
    ],
    "sg:phone":"+1 330 549 2143",
    "sg:postcode":"44452",
    "sg:province":"OH",
    "wof:name":"Crouse Mill True Value Ctr",
    "wof:placetype":"venue"
},
  "geometry": {"coordinates":[-80.658359,40.947077],"type":"Point"}
}