{
  "type": "Feature",
  "properties": {
    "addr:full": "345 Martin Dr Gallipolis OH 45631",
    "addr:housenumber": "345",
    "addr:postcode": "45631",
    "addr:street": "Martin Dr",
    "iso:country": "US",
    "sg:address": "345 Martin Dr",
    "sg:city": "Gallipolis",
    "sg:classifiers": [
      {
        "category": "Health Services",
        "subcategory": "Doctor",
        "type": "Services"
      }
    ],
    "sg:phone": "+1 740 286 6665",
    "sg:postcode": "45631",
    "sg:province": "OH",
    "sg:tags": [
      "physician",
      "surgeon"
    ],
    "wof:name": "H J Eyecare Inc",
    "wof:placetype": "venue"
  },
  "geometry": {"coordinates":[-82.224638,38.841074],"type":"Point"}
}
