{
  "type": "Feature",
  "properties": {
    "iso:country":"US",
    "sg:address":"3606 Warsaw Ave",
    "sg:city":"Cincinnati",
    "sg:classifiers":[
        {
            "category":"Shopping",
            "subcategory":"Clothing, Apparel, & Fashions",
            "type":"Retail Goods"
        }
    ],
    "sg:phone":"+1 513 921 7837",
    "sg:postcode":"45205",
    "sg:province":"OH",
    "sg:tags":[
        "item",
        "boutique"
    ],
    "wof:name":"Snazzy's Ladies Boutique",
    "wof:placetype":"venue"
},
  "geometry": {"coordinates":[-84.571682,39.110606],"type":"Point"}
}