{
  "type": "Feature",
  "properties": {
    "addr:full": "6655 Dull Rd Arcanum OH 45304",
    "addr:postcode": "6655;45304",
    "addr:street": "Dull Rd",
    "iso:country": "US",
    "sg:address": "6655 Dull Rd",
    "sg:city": "Arcanum",
    "sg:classifiers": [
      {
        "category": "Building \u0026 Trades",
        "subcategory": "Construction",
        "type": "Services"
      }
    ],
    "sg:phone": "+1 937 692 9910",
    "sg:postcode": "45304",
    "sg:province": "OH",
    "sg:tags": [
      "masonry",
      "contractor"
    ],
    "wof:name": "Carroll Masonry",
    "wof:placetype": "venue"
  },
  "geometry": {"coordinates":[-84.556728,39.975496],"type":"Point"}
}
