{
  "type": "Feature",
  "properties": {
    "iso:country":"US",
    "sg:address":"3410 State Rte 3",
    "sg:city":"Wilmington",
    "sg:classifiers":[
        {
            "category":"Recreation",
            "type":"Entertainment"
        }
    ],
    "sg:phone":"+1 937 383 2161",
    "sg:postcode":"45177",
    "sg:province":"OH",
    "sg:tags":[
        "course",
        "golf"
    ],
    "wof:name":"Adventure Cove",
    "wof:placetype":"venue"
},
  "geometry": {"coordinates":[-83.776391,39.45535],"type":"Point"}
}