{
  "type": "Feature",
  "properties": {
    "addr:full":"16165 E Liverpool Rd East Liverpool OH 43920",
    "addr:housenumber":"16165",
    "addr:postcode":"43920",
    "addr:street":"E Liverpool Rd",
    "iso:country":"US",
    "sg:address":"16165 E Liverpool Rd",
    "sg:city":"East Liverpool",
    "sg:classifiers":[
        {
            "category":"Building & Trades",
            "subcategory":"Construction",
            "type":"Services"
        }
    ],
    "sg:phone":"+1 330 385 8073",
    "sg:postcode":"43920",
    "sg:province":"OH",
    "sg:tags":[
        "home",
        "builder"
    ],
    "wof:name":"Eastern Homes",
    "wof:placetype":"venue"
},
  "geometry": {"coordinates":[-80.59866100000001,40.667262],"type":"Point"}
}