{
  "type": "Feature",
  "properties": {
    "addr:full": "6769 Middle Ridge Rd Madison OH 44057",
    "addr:housenumber": "6769",
    "addr:postcode": "44057",
    "addr:street": "Middle Ridge Rd",
    "iso:country": "US",
    "sg:address": "6769 Middle Ridge Rd",
    "sg:city": "Madison",
    "sg:classifiers": [
      {
        "category": "Organizations",
        "subcategory": "Religious Organization",
        "type": "Services"
      }
    ],
    "sg:phone": "+1 440 428 1835",
    "sg:postcode": "44057",
    "sg:province": "OH",
    "sg:tags": [
      "clergy"
    ],
    "wof:name": "Jeff Ziegler",
    "wof:placetype": "venue"
  },
  "geometry": {"coordinates":[-81.031088,41.78952],"type":"Point"}
}
