{
  "type": "Feature",
  "properties": {
    "iso:country":"US",
    "sg:address":"1325 Wagner Ave",
    "sg:city":"Greenville",
    "sg:classifiers":[
        {
            "category":"Food & Beverages",
            "subcategory":"Groceries & Convenience Stores",
            "type":"Retail Goods"
        }
    ],
    "sg:phone":"+1 937 548 5815",
    "sg:postcode":"45331",
    "sg:province":"OH",
    "sg:tags":[
        "independent"
    ],
    "wof:name":"Eikenberrys Super Valu",
    "wof:placetype":"venue"
},
  "geometry": {"coordinates":[-84.621661,40.122018],"type":"Point"}
}