{
  "type": "Feature",
  "properties": {
    "addr:full": "1325 Wagner Ave Greenville OH 45331",
    "addr:housenumber": "1325",
    "addr:postcode": "45331",
    "addr:street": "Wagner Ave",
    "iso:country": "US",
    "sg:address": "1325 Wagner Ave",
    "sg:city": "Greenville",
    "sg:classifiers": [
      {
        "category": "Food \u0026 Beverages",
        "subcategory": "Groceries \u0026 Convenience Stores",
        "type": "Retail Goods"
      }
    ],
    "sg:phone": "+1 937 548 5815",
    "sg:postcode": "45331",
    "sg:province": "OH",
    "sg:tags": [
      "independent"
    ],
    "wof:name": "Eikenberrys Super Valu",
    "wof:placetype": "venue"
  },
  "geometry": {"coordinates":[-84.621661,40.122018],"type":"Point"}
}
