{
  "type": "Feature",
  "properties": {
    "iso:country":"US",
    "sg:address":"11010 Diagonal Rd",
    "sg:city":"Mantua",
    "sg:classifiers":[
        {
            "category":"Freight",
            "type":"Transportation"
        }
    ],
    "sg:phone":"+1 216 857 2695",
    "sg:postcode":"44255",
    "sg:province":"OH",
    "sg:tags":[
        "local",
        "trucking"
    ],
    "wof:name":"Ablaze Transportation Inc",
    "wof:placetype":"venue"
},
  "geometry": {"coordinates":[-81.262517,41.291327],"type":"Point"}
}