{
  "type": "Feature",
  "properties": {
    "addr:full": "38 Alpha Park Cleveland OH 44143",
    "addr:housenumber": "38",
    "addr:postcode": "44143",
    "addr:street": "Alpha",
    "iso:country": "US",
    "sg:address": "38 Alpha Park",
    "sg:city": "Cleveland",
    "sg:classifiers": [
      {
        "category": "Professional",
        "subcategory": "Credit Reporting \u0026 Collection",
        "type": "Services"
      }
    ],
    "sg:phone": "+1 440 449 6270",
    "sg:postcode": "44143",
    "sg:province": "OH",
    "sg:tags": [
      "agency"
    ],
    "wof:name": "Dart Collections",
    "wof:placetype": "venue"
  },
  "geometry": {"coordinates":[-81.451377,41.553406],"type":"Point"}
}
