{
  "type": "Feature",
  "properties": {
    "addr:full": "748 Andora Dr Toledo OH 43609",
    "addr:housenumber": "748",
    "addr:postcode": "43609",
    "addr:street": "Andora Dr",
    "iso:country": "US",
    "sg:address": "748 Andora Dr",
    "sg:city": "Toledo",
    "sg:classifiers": [
      {
        "category": "Social Services",
        "subcategory": "Adult Care",
        "type": "Services"
      }
    ],
    "sg:phone": "+1 419 381 1808",
    "sg:postcode": "43609",
    "sg:province": "OH",
    "sg:tags": [
      "home",
      "group"
    ],
    "wof:name": "Quality Community Living LTD",
    "wof:placetype": "venue"
  },
  "geometry": {"coordinates":[-83.602249,41.626535],"type":"Point"}
}
