{
  "type": "Feature",
  "properties": {
    "addr:full":"233 Graff Rd SE New Philadelphia OH 44663",
    "addr:housenumber":"233",
    "addr:postcode":"44663",
    "addr:street":"Graff Rd Se New",
    "iso:country":"US",
    "sg:address":"233 Graff Rd SE",
    "sg:city":"New Philadelphia",
    "sg:classifiers":[
        {
            "category":"Restaurant",
            "type":"Food & Drink"
        }
    ],
    "sg:menulink":"http://www.allmenus.com/oh/new-philadelphia/88786-applebees/menu/",
    "sg:phone":"+1 330 308 5530",
    "sg:postcode":"44663",
    "sg:province":"OH",
    "sg:tags":[
        "burger",
        "american",
        "sandwich",
        "soup"
    ],
    "wof:name":"Applebee's",
    "wof:placetype":"venue"
},
  "geometry": {"coordinates":[-81.446591,40.479992],"type":"Point"}
}