{
  "type": "Feature",
  "properties": {
    "iso:country":"US",
    "sg:address":"1300 Hidden Lakes Dr NE",
    "sg:city":"Warren",
    "sg:classifiers":[
        {
            "category":"Professional",
            "type":"Services"
        }
    ],
    "sg:phone":"+1 330 395 6852",
    "sg:postcode":"44484",
    "sg:province":"OH",
    "wof:name":"Edward J Urban",
    "wof:placetype":"venue"
},
  "geometry": {"coordinates":[-80.726486,41.266605],"type":"Point"}
}