{
  "type": "Feature",
  "properties": {
    "addr:full": "8210 Macedonia Commons Blvd Macedonia OH 44056",
    "addr:postcode": "8210;44056",
    "addr:street": "Commons Blvd",
    "iso:country": "US",
    "sg:address": "8210 Macedonia Commons Blvd",
    "sg:city": "Macedonia",
    "sg:classifiers": [
      {
        "category": "Wholesale",
        "subcategory": "Machinery \u0026 Supplies",
        "type": "Manufacturing \u0026 Wholesale Goods"
      }
    ],
    "sg:phone": "+1 330 467 4429",
    "sg:postcode": "44056",
    "sg:province": "OH",
    "sg:tags": [
      "salon",
      "beauty"
    ],
    "wof:name": "Sally Beauty Supply",
    "wof:placetype": "venue"
  },
  "geometry": {"coordinates":[-81.517623,41.305451],"type":"Point"}
}
