{
  "type": "Feature",
  "properties": {
    "iso:country":"US",
    "sg:address":"8210 Macedonia Commons Blvd",
    "sg:city":"Macedonia",
    "sg:classifiers":[
        {
            "category":"Wholesale",
            "subcategory":"Machinery & Supplies",
            "type":"Manufacturing & Wholesale Goods"
        }
    ],
    "sg:phone":"+1 330 467 4429",
    "sg:postcode":"44056",
    "sg:province":"OH",
    "sg:tags":[
        "salon",
        "beauty"
    ],
    "wof:name":"Sally Beauty Supply",
    "wof:placetype":"venue"
},
  "geometry": {"coordinates":[-81.517623,41.305451],"type":"Point"}
}