{
  "type": "Feature",
  "properties": {
    "addr:full":"25 Orchard Park Tiffin OH 44883",
    "addr:housenumber":"25",
    "addr:postcode":"44883",
    "addr:street":"Orchard Park",
    "iso:country":"US",
    "sg:address":"25 Orchard Park",
    "sg:city":"Tiffin",
    "sg:classifiers":[
        {
            "category":"Organizations",
            "subcategory":"Religious Organization",
            "type":"Services"
        }
    ],
    "sg:phone":"+1 419 448 9477",
    "sg:postcode":"44883",
    "sg:province":"OH",
    "sg:tags":[
        "clergy"
    ],
    "wof:name":"Jan Kucera",
    "wof:placetype":"venue"
},
  "geometry": {"coordinates":[-83.174087,41.100016],"type":"Point"}
}