{
  "type": "Feature",
  "properties": {
    "addr:full": "140 N Main St Niles OH 44446",
    "addr:housenumber": "140",
    "addr:postcode": "44446",
    "addr:street": "N Main St",
    "iso:country": "US",
    "sg:address": "140 N Main St",
    "sg:city": "Niles",
    "sg:classifiers": [
      {
        "category": "Food \u0026 Beverages",
        "subcategory": "Groceries \u0026 Convenience Stores",
        "type": "Retail Goods"
      }
    ],
    "sg:phone": "+1 330 544 3478",
    "sg:postcode": "44446",
    "sg:province": "OH",
    "sg:tags": [
      "grocer"
    ],
    "sg:website": "www.sparklemarkets.com",
    "wof:name": "Niles Sparkle Market",
    "wof:placetype": "venue"
  },
  "geometry": {"coordinates":[-80.765211,41.181985],"type":"Point"}
}
