{
  "type": "Feature",
  "properties": {
    "iso:country":"US",
    "sg:address":"1900 Howland Wilson Rd NE",
    "sg:city":"Warren",
    "sg:classifiers":[
        {
            "category":"Building & Trades",
            "subcategory":"Construction",
            "type":"Services"
        }
    ],
    "sg:phone":"+1 330 856 3147",
    "sg:postcode":"44484",
    "sg:province":"OH",
    "sg:tags":[
        "general",
        "contractor"
    ],
    "wof:name":"E D Baker & Sons Construction",
    "wof:placetype":"venue"
},
  "geometry": {"coordinates":[-80.725053,41.256506],"type":"Point"}
}