{
  "type": "Feature",
  "properties": {
    "addr:full": "719 Main St Dresden OH 43821",
    "addr:housenumber": "719",
    "addr:postcode": "43821",
    "addr:street": "Main St",
    "iso:country": "US",
    "sg:address": "719 Main St",
    "sg:city": "Dresden",
    "sg:classifiers": [
      {
        "category": "Shopping",
        "subcategory": "Gifts \u0026 Souvenirs",
        "type": "Retail Goods"
      }
    ],
    "sg:phone": "+1 740 754 4200",
    "sg:postcode": "43821",
    "sg:province": "OH",
    "sg:tags": [
      "shop"
    ],
    "sg:website": "www.dresdenpottery.com",
    "wof:name": "Our Favorite Things",
    "wof:placetype": "venue"
  },
  "geometry": {"coordinates":[-82.011483,40.122113],"type":"Point"}
}
