{
  "type": "Feature",
  "properties": {
    "iso:country":"US",
    "sg:address":"202 Main St",
    "sg:city":"Lore City",
    "sg:classifiers":[
        {
            "category":"Retail",
            "subcategory":"Auto Repair",
            "type":"Services"
        }
    ],
    "sg:phone":"+1 740 685 6133",
    "sg:postcode":"43755",
    "sg:province":"OH",
    "sg:tags":[
        "repairing",
        "automobile"
    ],
    "wof:name":"Nolls Automotive",
    "wof:placetype":"venue"
},
  "geometry": {"coordinates":[-81.45913899999999,39.985189],"type":"Point"}
}