{
  "type": "Feature",
  "properties": {
    "addr:full": "16837 Wolf Run Cir Cleveland OH 44136",
    "addr:housenumber": "16837",
    "addr:postcode": "44136",
    "addr:street": "Wolf Run Cir",
    "iso:country": "US",
    "sg:address": "16837 Wolf Run Cir",
    "sg:city": "Cleveland",
    "sg:classifiers": [
      {
        "category": "Mining \u0026 Drilling",
        "type": "Manufacturing \u0026 Wholesale Goods"
      }
    ],
    "sg:phone": "+1 440 572 5141",
    "sg:postcode": "44136",
    "sg:province": "OH",
    "sg:tags": [
      "jacking",
      "mud",
      "contractor"
    ],
    "wof:name": "Accurate Concrete Leveling",
    "wof:placetype": "venue"
  },
  "geometry": {"coordinates":[-81.827843,41.292884],"type":"Point"}
}
