{
  "type": "Feature",
  "properties": {
    "iso:country":"US",
    "sg:address":"16837 Wolf Run Cir",
    "sg:city":"Cleveland",
    "sg:classifiers":[
        {
            "category":"Mining & Drilling",
            "type":"Manufacturing & Wholesale Goods"
        }
    ],
    "sg:phone":"+1 440 572 5141",
    "sg:postcode":"44136",
    "sg:province":"OH",
    "sg:tags":[
        "jacking",
        "mud",
        "contractor"
    ],
    "wof:name":"Accurate Concrete Leveling",
    "wof:placetype":"venue"
},
  "geometry": {"coordinates":[-81.827843,41.292884],"type":"Point"}
}