{
  "type": "Feature",
  "properties": {
    "iso:country":"US",
    "sg:address":"567 Leacrest Pl W",
    "sg:city":"Westerville",
    "sg:classifiers":[
        {
            "category":"Manufacturing",
            "subcategory":"Jewelry",
            "type":"Manufacturing & Wholesale Goods"
        },
        {
            "category":"Wholesale",
            "subcategory":"Jewelry",
            "type":"Manufacturing & Wholesale Goods"
        }
    ],
    "sg:phone":"+1 614 882 8248",
    "sg:postcode":"43081",
    "sg:province":"OH",
    "sg:tags":[
        "stone"
    ],
    "wof:name":"J P D Enterprises",
    "wof:placetype":"venue"
},
  "geometry": {"coordinates":[-82.917427,40.111439],"type":"Point"}
}