{
  "type": "Feature",
  "properties": {
    "addr:full": "567 Leacrest Pl W Westerville OH 43081",
    "addr:housenumber": "567",
    "addr:postcode": "westerville oh 43081",
    "addr:street": "Leacrest Pl W",
    "iso:country": "US",
    "sg:address": "567 Leacrest Pl W",
    "sg:city": "Westerville",
    "sg:classifiers": [
      {
        "category": "Manufacturing",
        "subcategory": "Jewelry",
        "type": "Manufacturing \u0026 Wholesale Goods"
      },
      {
        "category": "Wholesale",
        "subcategory": "Jewelry",
        "type": "Manufacturing \u0026 Wholesale Goods"
      }
    ],
    "sg:phone": "+1 614 882 8248",
    "sg:postcode": "43081",
    "sg:province": "OH",
    "sg:tags": [
      "stone"
    ],
    "wof:name": "J P D Enterprises",
    "wof:placetype": "venue"
  },
  "geometry": {"coordinates":[-82.917427,40.111439],"type":"Point"}
}
