{
  "type": "Feature",
  "properties": {
    "iso:country":"US",
    "sg:address":"2405 International St",
    "sg:city":"Columbus",
    "sg:classifiers":[
        {
            "category":"Professional",
            "type":"Services"
        },
        {
            "category":"Wholesale",
            "subcategory":"Non-durable Goods",
            "type":"Manufacturing & Wholesale Goods"
        }
    ],
    "sg:phone":"+1 614 921 0535",
    "sg:postcode":"43228",
    "sg:province":"OH",
    "sg:tags":[
        "establishment"
    ],
    "wof:name":"Sports Images Inc",
    "wof:placetype":"venue"
},
  "geometry": {"coordinates":[-83.131288,40.004397],"type":"Point"}
}