{
  "type": "Feature",
  "properties": {
    "addr:full": "2405 International St Columbus OH 43228",
    "addr:housenumber": "2405",
    "addr:postcode": "43228",
    "addr:street": "International St",
    "iso:country": "US",
    "sg:address": "2405 International St",
    "sg:city": "Columbus",
    "sg:classifiers": [
      {
        "category": "Professional",
        "type": "Services"
      },
      {
        "category": "Wholesale",
        "subcategory": "Non-durable Goods",
        "type": "Manufacturing \u0026 Wholesale Goods"
      }
    ],
    "sg:phone": "+1 614 921 0535",
    "sg:postcode": "43228",
    "sg:province": "OH",
    "sg:tags": [
      "establishment"
    ],
    "wof:name": "Sports Images Inc",
    "wof:placetype": "venue"
  },
  "geometry": {"coordinates":[-83.131288,40.004397],"type":"Point"}
}
