{
  "type": "Feature",
  "properties": {
    "iso:country":"US",
    "sg:address":"2929 Belmont Ave",
    "sg:city":"Youngstown",
    "sg:classifiers":[
        {
            "category":"Personal",
            "subcategory":"Barber",
            "type":"Services"
        }
    ],
    "sg:phone":"+1 330 759 2311",
    "sg:postcode":"44505",
    "sg:province":"OH",
    "wof:name":"Esquire Barber Shop",
    "wof:placetype":"venue"
},
  "geometry": {"coordinates":[-80.66544,41.136022],"type":"Point"}
}