{
  "type": "Feature",
  "properties": {
    "addr:full":"1965 Glamorgan St Alliance OH 44601",
    "addr:housenumber":"1965",
    "addr:postcode":"44601",
    "addr:street":"Glamorgan St",
    "iso:country":"US",
    "sg:address":"1965 Glamorgan St",
    "sg:city":"Alliance",
    "sg:classifiers":[
        {
            "category":"Real Estate",
            "subcategory":"Real Estate Agent",
            "type":"Services"
        }
    ],
    "sg:phone":"+1 330 823 8880",
    "sg:postcode":"44601",
    "sg:province":"OH",
    "sg:tags":[
        "home",
        "builder",
        "agency"
    ],
    "wof:name":"Tanner Real Estate Co",
    "wof:placetype":"venue"
},
  "geometry": {"coordinates":[-81.136191,40.912785],"type":"Point"}
}