{
  "type": "Feature",
  "properties": {
    "addr:full": "1878 Ashland Rd Mansfield OH 44905",
    "addr:housenumber": "1878",
    "addr:postcode": "44905",
    "addr:street": "Ashland Rd",
    "iso:country": "US",
    "sg:address": "1878 Ashland Rd",
    "sg:city": "Mansfield",
    "sg:classifiers": [
      {
        "category": "Shopping",
        "type": "Retail Goods"
      }
    ],
    "sg:phone": "+1 419 589 4345",
    "sg:postcode": "44905",
    "sg:province": "OH",
    "sg:tags": [
      "ice"
    ],
    "wof:name": "Hitching Post Feed \u0026 Dry Ice",
    "wof:placetype": "venue"
  },
  "geometry": {"coordinates":[-82.44606,40.79307],"type":"Point"}
}
