{
  "type": "Feature",
  "properties": {
    "iso:country":"US",
    "sg:address":"5810 Martinsburg Rd NE",
    "sg:city":"Newark",
    "sg:classifiers":[
        {
            "category":"Building & Trades",
            "subcategory":"Construction",
            "type":"Services"
        }
    ],
    "sg:phone":"+1 740 745 2813",
    "sg:postcode":"43055",
    "sg:province":"OH",
    "sg:tags":[
        "house"
    ],
    "wof:name":"Sturm Constuction",
    "wof:placetype":"venue"
},
  "geometry": {"coordinates":[-82.37752399999999,40.140439],"type":"Point"}
}