{
  "type": "Feature",
  "properties": {
    "iso:country":"US",
    "sg:address":"28828 Glenwood Rd",
    "sg:city":"Perrysburg",
    "sg:classifiers":[
        {
            "category":"Government",
            "subcategory":"Office",
            "type":"Public Place"
        }
    ],
    "sg:phone":"+1 419 661 1321",
    "sg:postcode":"43551",
    "sg:province":"OH",
    "sg:tags":[
        "armed",
        "national",
        "force",
        "security",
        "recruiting"
    ],
    "wof:name":"US Naval Reserve Recruiting",
    "wof:placetype":"venue"
},
  "geometry": {"coordinates":[-83.557534,41.566584],"type":"Point"}
}