{
  "type": "Feature",
  "properties": {
    "addr:full":"11445 Fitchburg Ln Cincinnati OH 45240",
    "addr:housenumber":"11445",
    "addr:postcode":"45240",
    "addr:street":"Fitchburg Ln",
    "iso:country":"US",
    "sg:address":"11445 Fitchburg Ln",
    "sg:city":"Cincinnati",
    "sg:classifiers":[
        {
            "category":"Freight",
            "type":"Transportation"
        }
    ],
    "sg:phone":"+1 513 742 1953",
    "sg:postcode":"45240",
    "sg:province":"OH",
    "sg:tags":[
        "local",
        "except",
        "trucking"
    ],
    "wof:name":"McDonald-Jenkins Enterprises",
    "wof:placetype":"venue"
},
  "geometry": {"coordinates":[-84.499736,39.288029],"type":"Point"}
}