{
  "type": "Feature",
  "properties": {
    "addr:full": "2101 N Cleveland Massillon Rd Akron OH 44333",
    "addr:housenumber": "2101",
    "addr:postcode": "44333",
    "addr:street": "N Cleveland Massillon Rd",
    "iso:country": "US",
    "sg:address": "2101 N Cleveland Massillon Rd",
    "sg:city": "Akron",
    "sg:classifiers": [
      {
        "category": "Retail",
        "subcategory": "Veterinary Services",
        "type": "Services"
      }
    ],
    "sg:phone": "+1 330 665 5915",
    "sg:postcode": "44333",
    "sg:province": "OH",
    "sg:tags": [
      "veterinarian"
    ],
    "wof:name": "Visiting Vet",
    "wof:placetype": "venue"
  },
  "geometry": {"coordinates":[-81.636198,41.193291],"type":"Point"}
}
