{
  "type": "Feature",
  "properties": {
    "addr:full": "138 N Main St Fredericktown OH 43019",
    "addr:housenumber": "138",
    "addr:postcode": "43019",
    "addr:street": "N Main St",
    "iso:country": "US",
    "sg:address": "138 N Main St",
    "sg:city": "Fredericktown",
    "sg:classifiers": [
      {
        "category": "Food \u0026 Beverages",
        "subcategory": "Specialty",
        "type": "Retail Goods"
      },
      {
        "category": "Wholesale",
        "subcategory": "Groceries",
        "type": "Manufacturing \u0026 Wholesale Goods"
      }
    ],
    "sg:phone": "+1 740 694 3111",
    "sg:postcode": "43019",
    "sg:province": "OH",
    "sg:tags": [
      "product"
    ],
    "wof:name": "Taste Of Country Bulk Food Str",
    "wof:placetype": "venue"
  },
  "geometry": {"coordinates":[-82.543293,40.482707],"type":"Point"}
}
