{
  "type": "Feature",
  "properties": {
    "addr:full": "255 Twp Rd 85 W Chesapeake OH 45619",
    "addr:housenumber": "255;85",
    "addr:postcode": "45619",
    "addr:street": "Twp Rd;W",
    "iso:country": "US",
    "sg:address": "255 Twp Rd 85 W",
    "sg:city": "Chesapeake",
    "sg:classifiers": [
      {
        "category": "Farming",
        "subcategory": "Dairy Farm",
        "type": "Manufacturing \u0026 Wholesale Goods"
      }
    ],
    "sg:phone": "+1 740 867 3690",
    "sg:postcode": "45619",
    "sg:province": "OH",
    "wof:name": "John Smith Wilhliam",
    "wof:placetype": "venue"
  },
  "geometry": {"coordinates":[-82.45788,38.473428],"type":"Point"}
}
