{
  "type": "Feature",
  "properties": {
    "addr:full": "1459 Wendy St NW Canton OH 44709",
    "addr:housenumber": "1459",
    "addr:postcode": "44709",
    "addr:street": "Wendy St Nw",
    "iso:country": "US",
    "sg:address": "1459 Wendy St NW",
    "sg:city": "Canton",
    "sg:classifiers": [
      {
        "category": "Real Estate",
        "subcategory": "Real Estate Operator",
        "type": "Services"
      }
    ],
    "sg:phone": "+1 330 493 9122",
    "sg:postcode": "44709",
    "sg:province": "OH",
    "sg:tags": [
      "apartment"
    ],
    "wof:name": "Mt Vernon Apartments",
    "wof:placetype": "venue"
  },
  "geometry": {"coordinates":[-81.388227,40.834873],"type":"Point"}
}
