{
  "type": "Feature",
  "properties": {
    "addr:full": "657 E State St Salem OH 44460",
    "addr:housenumber": "657",
    "addr:postcode": "44460",
    "addr:street": "E State St",
    "iso:country": "US",
    "sg:address": "657 E State St",
    "sg:city": "Salem",
    "sg:classifiers": [
      {
        "category": "Arts \u0026 Performance",
        "subcategory": "Theater",
        "type": "Entertainment"
      }
    ],
    "sg:phone": "+1 330 332 9726",
    "sg:postcode": "44460",
    "sg:province": "OH",
    "sg:tags": [
      "entertainer",
      "business"
    ],
    "wof:name": "Merry Messenger",
    "wof:placetype": "venue"
  },
  "geometry": {"coordinates":[-80.852099,40.900861],"type":"Point"}
}
