{
  "type": "Feature",
  "properties": {
    "iso:country":"US",
    "sg:address":"7171 Royalton Rd",
    "sg:city":"Cleveland",
    "sg:classifiers":[
        {
            "category":"Travel",
            "subcategory":"Travel Agent",
            "type":"Entertainment"
        }
    ],
    "sg:phone":"+1 440 237 3344",
    "sg:postcode":"44133",
    "sg:province":"OH",
    "sg:tags":[
        "agency",
        "bureau"
    ],
    "sg:website":"www.nowaktours.com",
    "wof:name":"Jerry Nowak Group Tours",
    "wof:placetype":"venue"
},
  "geometry": {"coordinates":[-81.738435,41.313641],"type":"Point"}
}