{
  "type": "Feature",
  "properties": {
    "iso:country":"US",
    "sg:address":"5061 Abbe Rd N",
    "sg:city":"Elyria",
    "sg:classifiers":[
        {
            "category":"Insurance",
            "subcategory":"Insurance Agent",
            "type":"Services"
        }
    ],
    "sg:phone":"+1 440 934 7799",
    "sg:postcode":"44035",
    "sg:province":"OH",
    "wof:name":"Remax Homeward Bound",
    "wof:placetype":"venue"
},
  "geometry": {"coordinates":[-82.07692400000001,41.424494],"type":"Point"}
}