{
  "type": "Feature",
  "properties": {
    "iso:country":"US",
    "sg:address":"401 W North St",
    "sg:city":"Lima",
    "sg:classifiers":[
        {
            "category":"Government",
            "subcategory":"Office",
            "type":"Public Place"
        }
    ],
    "sg:phone":"+1 419 223 5866",
    "sg:postcode":"45801",
    "sg:province":"OH",
    "sg:tags":[
        "federal",
        "wage",
        "control",
        "agency"
    ],
    "wof:name":"Wage and Hour Div Field Off",
    "wof:placetype":"venue"
},
  "geometry": {"coordinates":[-84.10938299999999,40.742681],"type":"Point"}
}