{
  "type": "Feature",
  "properties": {
    "addr:full": "401 W North St Lima OH 45801",
    "addr:housenumber": "401",
    "addr:postcode": "45801",
    "addr:street": "W North St",
    "iso:country": "US",
    "sg:address": "401 W North St",
    "sg:city": "Lima",
    "sg:classifiers": [
      {
        "category": "Government",
        "subcategory": "Office",
        "type": "Public Place"
      }
    ],
    "sg:phone": "+1 419 223 5866",
    "sg:postcode": "45801",
    "sg:province": "OH",
    "sg:tags": [
      "federal",
      "wage",
      "control",
      "agency"
    ],
    "wof:name": "Wage and Hour Div Field Off",
    "wof:placetype": "venue"
  },
  "geometry": {"coordinates":[-84.109383,40.742681],"type":"Point"}
}
