{
  "type": "Feature",
  "properties": {
    "addr:full":"4041 W Sylvania Ave Toledo OH 43623",
    "addr:housenumber":"4041",
    "addr:postcode":"43623",
    "addr:street":"W Sylvania Ave",
    "iso:country":"US",
    "sg:address":"4041 W Sylvania Ave",
    "sg:city":"Toledo",
    "sg:classifiers":[
        {
            "category":"Shopping",
            "subcategory":"Optical Goods",
            "type":"Retail Goods"
        }
    ],
    "sg:phone":"+1 419 472 2020",
    "sg:postcode":"43623",
    "sg:province":"OH",
    "wof:name":"Franklin Park Vision",
    "wof:placetype":"venue"
},
  "geometry": {"coordinates":[-83.641835,41.691132],"type":"Point"}
}