{
  "type": "Feature",
  "properties": {
    "addr:full":"130 S Main St Bellefontaine OH 43311",
    "addr:housenumber":"130",
    "addr:postcode":"43311",
    "addr:street":"S Main St",
    "iso:country":"US",
    "sg:address":"130 S Main St",
    "sg:city":"Bellefontaine",
    "sg:classifiers":[
        {
            "category":"Restaurant",
            "type":"Food & Drink"
        }
    ],
    "sg:phone":"+1 937 599 2866",
    "sg:postcode":"43311",
    "sg:province":"OH",
    "sg:tags":[
        "caterer"
    ],
    "wof:name":"KLW Holdings LTD",
    "wof:placetype":"venue"
},
  "geometry": {"coordinates":[-83.759843,40.360651],"type":"Point"}
}