{
  "type": "Feature",
  "properties": {
    "addr:full": "116 W Front St Findlay OH 45840",
    "addr:housenumber": "116",
    "addr:postcode": "45840",
    "addr:street": "W Front St",
    "iso:country": "US",
    "sg:address": "116 W Front St",
    "sg:city": "Findlay",
    "sg:classifiers": [
      {
        "category": "Banks \u0026 Credit Unions",
        "subcategory": "Investment Brokerage",
        "type": "Services"
      }
    ],
    "sg:phone": "+1 419 420 9035",
    "sg:postcode": "45840",
    "sg:province": "OH",
    "sg:tags": [
      "consultant",
      "planning",
      "financial"
    ],
    "wof:name": "Feldmeyer Ginsburg \u0026 Assoc",
    "wof:placetype": "venue"
  },
  "geometry": {"coordinates":[-83.650485,41.040554],"type":"Point"}
}
