{
  "type": "Feature",
  "properties": {
    "iso:country":"US",
    "sg:address":"116 W Front St",
    "sg:city":"Findlay",
    "sg:classifiers":[
        {
            "category":"Banks & Credit Unions",
            "subcategory":"Investment Brokerage",
            "type":"Services"
        }
    ],
    "sg:phone":"+1 419 420 9035",
    "sg:postcode":"45840",
    "sg:province":"OH",
    "sg:tags":[
        "consultant",
        "planning",
        "financial"
    ],
    "wof:name":"Feldmeyer Ginsburg & Assoc",
    "wof:placetype":"venue"
},
  "geometry": {"coordinates":[-83.650485,41.040554],"type":"Point"}
}