{
  "type": "Feature",
  "properties": {
    "addr:full":"420 N Conover St Dayton OH 45402",
    "addr:housenumber":"420",
    "addr:postcode":"45402",
    "addr:street":"N Conover St",
    "iso:country":"US",
    "sg:address":"420 N Conover St",
    "sg:city":"Dayton",
    "sg:classifiers":[
        {
            "category":"Organizations",
            "subcategory":"Religious Organization",
            "type":"Services"
        }
    ],
    "sg:phone":"+1 937 226 1495",
    "sg:postcode":"45402",
    "sg:province":"OH",
    "sg:tags":[
        "church"
    ],
    "wof:name":"Pilgrim Church",
    "wof:placetype":"venue"
},
  "geometry": {"coordinates":[-84.21745900000001,39.75987],"type":"Point"}
}