{
  "type": "Feature",
  "properties": {
    "addr:full": "850 Westhafer Rd Vandalia OH 45377",
    "addr:housenumber": "850",
    "addr:postcode": "45377",
    "addr:street": "Westhafer Rd",
    "iso:country": "US",
    "sg:address": "850 Westhafer Rd",
    "sg:city": "Vandalia",
    "sg:classifiers": [
      {
        "category": "Building \u0026 Trades",
        "subcategory": "Plumbing",
        "type": "Services"
      }
    ],
    "sg:phone": "+1 937 890 2321",
    "sg:postcode": "45377",
    "sg:province": "OH",
    "sg:tags": [
      "contractor"
    ],
    "wof:name": "Stephens Heating",
    "wof:placetype": "venue"
  },
  "geometry": {"coordinates":[-84.184234,39.893985],"type":"Point"}
}
