{
  "type": "Feature",
  "properties": {
    "iso:country":"US",
    "sg:address":"850 Westhafer Rd",
    "sg:city":"Vandalia",
    "sg:classifiers":[
        {
            "category":"Building & Trades",
            "subcategory":"Plumbing",
            "type":"Services"
        }
    ],
    "sg:phone":"+1 937 890 2321",
    "sg:postcode":"45377",
    "sg:province":"OH",
    "sg:tags":[
        "contractor"
    ],
    "wof:name":"Stephens Heating",
    "wof:placetype":"venue"
},
  "geometry": {"coordinates":[-84.184234,39.893985],"type":"Point"}
}