{
  "type": "Feature",
  "properties": {
    "addr:full":"802 Lynbrook St SE Canton OH 44720",
    "addr:housenumber":"802",
    "addr:postcode":"44720",
    "addr:street":"Lynbrook St Se",
    "iso:country":"US",
    "sg:address":"802 Lynbrook St SE",
    "sg:city":"Canton",
    "sg:classifiers":[
        {
            "category":"Wholesale",
            "subcategory":"Auto Parts",
            "type":"Manufacturing & Wholesale Goods"
        }
    ],
    "sg:phone":"+1 330 966 6760",
    "sg:postcode":"44720",
    "sg:province":"OH",
    "wof:name":"Ikoyis Hydraulics & Cstm Auto",
    "wof:placetype":"venue"
},
  "geometry": {"coordinates":[-81.390505,40.865472],"type":"Point"}
}