{
  "type": "Feature",
  "properties": {
    "iso:country":"US",
    "sg:address":"515 Abbe Rd N",
    "sg:city":"Elyria",
    "sg:classifiers":[
        {
            "category":"Recreation",
            "type":"Entertainment"
        }
    ],
    "sg:phone":"+1 440 366 9493",
    "sg:postcode":"44035",
    "sg:province":"OH",
    "sg:tags":[
        "martial",
        "arts",
        "instruction"
    ],
    "wof:name":"Mr Dee's Karate Academy",
    "wof:placetype":"venue"
},
  "geometry": {"coordinates":[-82.077377,41.388673],"type":"Point"}
}