{
  "type": "Feature",
  "properties": {
    "addr:full": "1040 E Tallmadge Ave Akron OH 44310",
    "addr:housenumber": "1040",
    "addr:postcode": "44310",
    "addr:street": "E Tallmadge Ave",
    "iso:country": "US",
    "sg:address": "1040 E Tallmadge Ave",
    "sg:city": "Akron",
    "sg:classifiers": [
      {
        "category": "Professional",
        "subcategory": "Employment Agencies",
        "type": "Services"
      }
    ],
    "sg:phone": "+1 330 633 1050",
    "sg:postcode": "44310",
    "sg:province": "OH",
    "sg:tags": [
      "opportunity"
    ],
    "wof:name": "Job Center",
    "wof:placetype": "venue"
  },
  "geometry": {"coordinates":[-81.47722,41.10198],"type":"Point"}
}
