{
  "type": "Feature",
  "properties": {
    "addr:full":"3037 Cleveland Ave SW Canton OH 44707",
    "addr:housenumber":"3037",
    "addr:postcode":"44707",
    "addr:street":"Cleveland Ave Sw",
    "iso:country":"US",
    "sg:address":"3037 Cleveland Ave SW",
    "sg:city":"Canton",
    "sg:classifiers":[
        {
            "category":"Shopping",
            "subcategory":"Computers & Home Electronics",
            "type":"Retail Goods"
        }
    ],
    "sg:phone":"+1 330 484 2086",
    "sg:postcode":"44707",
    "sg:province":"OH",
    "wof:name":"Radio Shack",
    "wof:placetype":"venue"
},
  "geometry": {"coordinates":[-81.380979,40.76367],"type":"Point"}
}