{
  "type": "Feature",
  "properties": {
    "iso:country":"US",
    "sg:address":"701 Chestnut St",
    "sg:city":"Nelsonville",
    "sg:classifiers":[
        {
            "category":"Organizations",
            "subcategory":"Community Association",
            "type":"Services"
        }
    ],
    "sg:phone":"+1 740 753 2922",
    "sg:postcode":"45764",
    "sg:province":"OH",
    "sg:tags":[
        "club"
    ],
    "wof:name":"Canal Street Barbell Club",
    "wof:placetype":"venue"
},
  "geometry": {"coordinates":[-82.223888,39.453503],"type":"Point"}
}