{
  "type": "Feature",
  "properties": {
    "addr:full":"7787 Joan Dr West Chester OH 45069",
    "addr:housenumber":"7787",
    "addr:postcode":"45069",
    "addr:street":"Joan Dr",
    "iso:country":"US",
    "sg:address":"7787 Joan Dr",
    "sg:city":"West Chester",
    "sg:classifiers":[
        {
            "category":"Insurance",
            "subcategory":"Insurance Agent",
            "type":"Services"
        }
    ],
    "sg:phone":"+1 513 779 9333",
    "sg:postcode":"45069",
    "sg:province":"OH",
    "wof:name":"Liberty Mutual Insurance",
    "wof:placetype":"venue"
},
  "geometry": {"coordinates":[-84.36971800000001,39.32127],"type":"Point"}
}