{
  "type": "Feature",
  "properties": {
    "addr:full": "4287 Manchester Ave NW North Lawrence OH 44666",
    "addr:housenumber": "4287",
    "addr:postcode": "44666",
    "addr:street": "Manchester Ave Nw North",
    "iso:country": "US",
    "sg:address": "4287 Manchester Ave NW",
    "sg:city": "North Lawrence",
    "sg:classifiers": [
      {
        "category": "Manufacturing",
        "subcategory": "Textiles",
        "type": "Manufacturing \u0026 Wholesale Goods"
      }
    ],
    "sg:phone": "+1 330 834 1104",
    "sg:postcode": "44666",
    "sg:province": "OH",
    "sg:tags": [
      "underwear",
      "knit",
      "mill"
    ],
    "wof:name": "Peteys TS",
    "wof:placetype": "venue"
  },
  "geometry": {"coordinates":[-81.599983,40.838847],"type":"Point"}
}
