{
  "type": "Feature",
  "properties": {
    "addr:full":"1399 State Rte 28 Loveland OH 45140",
    "addr:housenumber":"1399",
    "addr:postcode":"45140",
    "addr:street":"State Rte 28",
    "iso:country":"US",
    "sg:address":"1399 State Rte 28",
    "sg:city":"Loveland",
    "sg:classifiers":[
        {
            "category":"Food & Beverages",
            "subcategory":"Bakery",
            "type":"Retail Goods"
        }
    ],
    "sg:phone":"+1 513 575 1077",
    "sg:postcode":"45140",
    "sg:province":"OH",
    "wof:name":"Holtmans Donuts",
    "wof:placetype":"venue"
},
  "geometry": {"coordinates":[-84.20313899999999,39.213594],"type":"Point"}
}