{
  "type": "Feature",
  "properties": {
    "iso:country":"US",
    "sg:address":"30 E High St",
    "sg:city":"Oxford",
    "sg:classifiers":[
        {
            "category":"Professional",
            "subcategory":"Art Services",
            "type":"Services"
        }
    ],
    "sg:phone":"+1 513 523 3884",
    "sg:postcode":"45056",
    "sg:province":"IN",
    "sg:tags":[
        "photographer"
    ],
    "wof:name":"Schult & Assoc",
    "wof:placetype":"venue"
},
  "geometry": {"coordinates":[-84.740891,39.510543],"type":"Point"}
}