{
  "type": "Feature",
  "properties": {
    "addr:full": "5812 Darrow Rd Hudson OH 44236",
    "addr:housenumber": "5812",
    "addr:postcode": "44236",
    "addr:street": "Darrow Rd",
    "iso:country": "US",
    "sg:address": "5812 Darrow Rd",
    "sg:city": "Hudson",
    "sg:classifiers": [
      {
        "category": "Social Services",
        "subcategory": "Child Care",
        "type": "Services"
      }
    ],
    "sg:phone": "+1 330 656 2737",
    "sg:postcode": "44236",
    "sg:province": "OH",
    "sg:tags": [
      "kindergarten",
      "academic",
      "school",
      "day"
    ],
    "sg:website": "www.cwlc.com",
    "wof:name": "Children's World Learning Ctr",
    "wof:placetype": "venue"
  },
  "geometry": {"coordinates":[-81.440412,41.222169],"type":"Point"}
}
