{
  "type": "Feature",
  "properties": {
    "iso:country":"US",
    "sg:address":"6041 W Liberty St",
    "sg:city":"Hubbard",
    "sg:classifiers":[
        {
            "category":"Home & Garden",
            "subcategory":"Building Materials",
            "type":"Retail Goods"
        }
    ],
    "sg:phone":"+1 330 534 2211",
    "sg:postcode":"44425",
    "sg:province":"OH",
    "wof:name":"Buckeye Tack Lumber & Sup Co",
    "wof:placetype":"venue"
},
  "geometry": {"coordinates":[-80.602119,41.157527],"type":"Point"}
}