{
  "type": "Feature",
  "properties": {
    "addr:full": "6041 W Liberty St Hubbard OH 44425",
    "addr:housenumber": "6041",
    "addr:postcode": "44425",
    "addr:street": "W Liberty St",
    "iso:country": "US",
    "sg:address": "6041 W Liberty St",
    "sg:city": "Hubbard",
    "sg:classifiers": [
      {
        "category": "Home \u0026 Garden",
        "subcategory": "Building Materials",
        "type": "Retail Goods"
      }
    ],
    "sg:phone": "+1 330 534 2211",
    "sg:postcode": "44425",
    "sg:province": "OH",
    "wof:name": "Buckeye Tack Lumber \u0026 Sup Co",
    "wof:placetype": "venue"
  },
  "geometry": {"coordinates":[-80.602119,41.157527],"type":"Point"}
}
