{
  "type": "Feature",
  "properties": {
    "iso:country":"US",
    "sg:address":"127 Prospect Ave S",
    "sg:city":"Hartville",
    "sg:classifiers":[
        {
            "category":"Restaurant",
            "type":"Food & Drink"
        }
    ],
    "sg:phone":"+1 330 877 2364",
    "sg:postcode":"44632",
    "sg:province":"OH",
    "wof:name":"Zeppe S Pizza",
    "wof:placetype":"venue"
},
  "geometry": {"coordinates":[-81.332323,40.963122],"type":"Point"}
}