{
  "type": "Feature",
  "properties": {
    "iso:country":"US",
    "sg:address":"100 S 3rd St",
    "sg:city":"Columbus",
    "sg:classifiers":[
        {
            "category":"Professional",
            "subcategory":"Lawyer & Legal Services",
            "type":"Services"
        }
    ],
    "sg:phone":"+1 614 227 4893",
    "sg:postcode":"43215",
    "sg:province":"OH",
    "sg:tags":[
        "litigation",
        "attorney",
        "business",
        "practice",
        "tort",
        "governmental",
        "plan",
        "law",
        "administrative"
    ],
    "wof:name":"Gregory J Le Stini Attorney",
    "wof:placetype":"venue"
},
  "geometry": {"coordinates":[-82.997559,39.96048],"type":"Point"}
}