{
  "type": "Feature",
  "properties": {
    "addr:full": "7991 Beechmont Ave Cincinnati OH 45255",
    "addr:housenumber": "7991",
    "addr:postcode": "45255",
    "addr:street": "Beechmont Ave",
    "iso:country": "US",
    "sg:address": "7991 Beechmont Ave",
    "sg:city": "Cincinnati",
    "sg:classifiers": [
      {
        "category": "Real Estate",
        "subcategory": "Real Estate Agent",
        "type": "Services"
      }
    ],
    "sg:phone": "+1 513 474 3500",
    "sg:postcode": "45255",
    "sg:province": "OH",
    "wof:name": "Huff Realty",
    "wof:placetype": "venue"
  },
  "geometry": {"coordinates":[-84.335357,39.072635],"type":"Point"}
}
