{
  "type": "Feature",
  "properties": {
    "addr:full": "113 Kossuth St Sidney OH 45365",
    "addr:housenumber": "113",
    "addr:postcode": "45365",
    "addr:street": "Kossuth St",
    "iso:country": "US",
    "sg:address": "113 Kossuth St",
    "sg:city": "Sidney",
    "sg:classifiers": [
      {
        "category": "Organizations",
        "subcategory": "Religious Organization",
        "type": "Services"
      }
    ],
    "sg:phone": "+1 937 498 1958",
    "sg:postcode": "45365",
    "sg:province": "OH",
    "sg:tags": [
      "church"
    ],
    "wof:name": "Central Bible Ministries",
    "wof:placetype": "venue"
  },
  "geometry": {"coordinates":[-84.155484,40.296248],"type":"Point"}
}
