{
  "type": "Feature",
  "properties": {
    "addr:full": "563 Barrenwood Dr Wadsworth OH 44281",
    "addr:housenumber": "563",
    "addr:postcode": "44281",
    "addr:street": "Barrenwood Dr",
    "iso:country": "US",
    "sg:address": "563 Barrenwood Dr",
    "sg:city": "Wadsworth",
    "sg:classifiers": [
      {
        "category": "Mining \u0026 Drilling",
        "type": "Manufacturing \u0026 Wholesale Goods"
      }
    ],
    "sg:phone": "+1 330 335 4211",
    "sg:postcode": "44281",
    "sg:province": "OH",
    "sg:website": "www.solvaychemicals.com",
    "wof:name": "Solvay Chemicals Inc",
    "wof:placetype": "venue"
  },
  "geometry": {"coordinates":[-81.745867,41.015456],"type":"Point"}
}
