{
  "type": "Feature",
  "properties": {
    "addr:full": "50 Erie St S Massillon OH 44646",
    "addr:housenumber": "50",
    "addr:postcode": "44646",
    "addr:street": "Erie St S",
    "iso:country": "US",
    "sg:address": "50 Erie St S",
    "sg:city": "Massillon",
    "sg:classifiers": [
      {
        "category": "Food \u0026 Beverages",
        "subcategory": "Liquor \u0026 Beverages",
        "type": "Retail Goods"
      }
    ],
    "sg:phone": "+1 330 832 1382",
    "sg:postcode": "44646",
    "sg:province": "OH",
    "wof:name": "Massillon Wine \u0026 Spirits",
    "wof:placetype": "venue"
  },
  "geometry": {"coordinates":[-81.522696,40.795611],"type":"Point"}
}
