{
  "type": "Feature",
  "properties": {
    "addr:full": "3976 Bach Buxton Rd Amelia OH 45102",
    "addr:housenumber": "3976",
    "addr:postcode": "45102",
    "addr:street": "Buxton Rd",
    "iso:country": "US",
    "sg:address": "3976 Bach Buxton Rd",
    "sg:city": "Amelia",
    "sg:classifiers": [
      {
        "category": "Manufacturing",
        "subcategory": "Chemicals \u0026 Compounds",
        "type": "Manufacturing \u0026 Wholesale Goods"
      }
    ],
    "sg:phone": "+1 513 943 0599",
    "sg:postcode": "45102",
    "sg:province": "OH",
    "sg:tags": [
      "water",
      "mfg",
      "lithographing",
      "ink"
    ],
    "wof:name": "Printink Inc",
    "wof:placetype": "venue"
  },
  "geometry": {"coordinates":[-84.245605,39.057232],"type":"Point"}
}
