{
  "type": "Feature",
  "properties": {
    "addr:full":"5 High St Fairport Harbor OH 44077",
    "addr:housenumber":"5",
    "addr:postcode":"44077",
    "addr:street":"High St",
    "iso:country":"US",
    "sg:address":"5 High St",
    "sg:city":"Fairport Harbor",
    "sg:classifiers":[
        {
            "category":"Utilities",
            "subcategory":"Water",
            "type":"Services"
        }
    ],
    "sg:phone":"+1 440 352 0154",
    "sg:postcode":"44077",
    "sg:province":"OH",
    "sg:tags":[
        "company",
        "sewage"
    ],
    "wof:name":"Fairport Water Works",
    "wof:placetype":"venue"
},
  "geometry": {"coordinates":[-81.277199,41.756801],"type":"Point"}
}