{
  "type": "Feature",
  "properties": {
    "addr:full": "2566 Outville Rd Alexandria OH 43001",
    "addr:housenumber": "2566",
    "addr:postcode": "43001",
    "addr:street": "Outville Rd",
    "iso:country": "US",
    "sg:address": "2566 Outville Rd",
    "sg:city": "Alexandria",
    "sg:classifiers": [
      {
        "category": "Freight",
        "type": "Transportation"
      }
    ],
    "sg:phone": "+1 740 967 9944",
    "sg:postcode": "43001",
    "sg:province": "OH",
    "sg:tags": [
      "trucking"
    ],
    "wof:name": "Martin Trucking",
    "wof:placetype": "venue"
  },
  "geometry": {"coordinates":[-82.594446,40.052968],"type":"Point"}
}
