{
  "type": "Feature",
  "properties": {
    "addr:full":"1006 N University Blvd Middletown OH 45042",
    "addr:housenumber":"1006",
    "addr:postcode":"45042",
    "addr:street":"N University Blvd",
    "iso:country":"US",
    "sg:address":"1006 N University Blvd",
    "sg:city":"Middletown",
    "sg:classifiers":[
        {
            "category":"Health Services",
            "subcategory":"Doctor",
            "type":"Services"
        }
    ],
    "sg:phone":"+1 513 423 0077",
    "sg:postcode":"45042",
    "sg:province":"OH",
    "sg:tags":[
        "physician",
        "surgeon"
    ],
    "wof:name":"Walter H Roehll Jr MD",
    "wof:placetype":"venue"
},
  "geometry": {"coordinates":[-84.370225,39.523742],"type":"Point"}
}