{
  "type": "Feature",
  "properties": {
    "iso:country":"US",
    "sg:address":"1 S Limestone St",
    "sg:city":"Springfield",
    "sg:classifiers":[
        {
            "category":"Professional",
            "type":"Services"
        }
    ],
    "sg:phone":"+1 937 323 3574",
    "sg:postcode":"45505",
    "sg:province":"OH",
    "sg:tags":[
        "establishment"
    ],
    "wof:name":"Donet",
    "wof:placetype":"venue"
},
  "geometry": {"coordinates":[-83.808584,39.923215],"type":"Point"}
}