{
  "type": "Feature",
  "properties": {
    "iso:country":"US",
    "sg:address":"6809 Quimby Ave",
    "sg:city":"Cleveland",
    "sg:classifiers":[
        {
            "category":"Social Services",
            "type":"Services"
        }
    ],
    "sg:phone":"+1 216 391 4170",
    "sg:postcode":"44103",
    "sg:province":"OH",
    "sg:tags":[
        "counselor",
        "marriage",
        "family"
    ],
    "wof:name":"Fatima Family Ctr",
    "wof:placetype":"venue"
},
  "geometry": {"coordinates":[-81.64224,41.509868],"type":"Point"}
}