{
  "type": "Feature",
  "properties": {
    "addr:full":"208 Co Rd 16 Napoleon OH 43545",
    "addr:housenumber":"208;16",
    "addr:postcode":"43545",
    "addr:street":"Co Rd",
    "iso:country":"US",
    "sg:address":"208 Co Rd 16",
    "sg:city":"Napoleon",
    "sg:classifiers":[
        {
            "category":"Wholesale",
            "subcategory":"Non-durable Goods",
            "type":"Manufacturing & Wholesale Goods"
        },
        {
            "category":"Shopping",
            "subcategory":"Bicycles & Sporting Goods",
            "type":"Retail Goods"
        }
    ],
    "sg:phone":"+1 419 598 8026",
    "sg:postcode":"43545",
    "sg:province":"OH",
    "wof:name":"Mahnke Stable & Tack Store",
    "wof:placetype":"venue"
},
  "geometry": {"coordinates":[-84.172883,41.472172],"type":"Point"}
}