{
  "type": "Feature",
  "properties": {
    "iso:country":"US",
    "sg:address":"1144 E Market St",
    "sg:city":"Akron",
    "sg:classifiers":[
        {
            "category":"Freight",
            "type":"Transportation"
        }
    ],
    "sg:phone":"+1 330 796 0123",
    "sg:postcode":"44305",
    "sg:province":"OH",
    "sg:tags":[
        "forwarding",
        "air"
    ],
    "wof:name":"Eagle Global Logistics",
    "wof:placetype":"venue"
},
  "geometry": {"coordinates":[-81.48503599999999,41.067888],"type":"Point"}
}