{
  "type": "Feature",
  "properties": {
    "addr:full": "1144 E Market St Akron OH 44305",
    "addr:housenumber": "1144",
    "addr:postcode": "44305",
    "addr:street": "E Market St",
    "iso:country": "US",
    "sg:address": "1144 E Market St",
    "sg:city": "Akron",
    "sg:classifiers": [
      {
        "category": "Freight",
        "type": "Transportation"
      }
    ],
    "sg:phone": "+1 330 796 0123",
    "sg:postcode": "44305",
    "sg:province": "OH",
    "sg:tags": [
      "forwarding",
      "air"
    ],
    "wof:name": "Eagle Global Logistics",
    "wof:placetype": "venue"
  },
  "geometry": {"coordinates":[-81.485036,41.067888],"type":"Point"}
}
