{
  "type": "Feature",
  "properties": {
    "addr:full": "5410 Hetzell St Cincinnati OH 45227",
    "addr:housenumber": "5410",
    "addr:postcode": "45227",
    "addr:street": "Hetzell St",
    "iso:country": "US",
    "sg:address": "5410 Hetzell St",
    "sg:city": "Cincinnati",
    "sg:classifiers": [
      {
        "category": "Manufacturing",
        "subcategory": "Tools \u0026 Machinery",
        "type": "Manufacturing \u0026 Wholesale Goods"
      }
    ],
    "sg:phone": "+1 513 527 5370",
    "sg:postcode": "45227",
    "sg:province": "OH",
    "sg:tags": [
      "instrument",
      "mfg",
      "musical",
      "ho"
    ],
    "wof:name": "Nutone Inc",
    "wof:placetype": "venue"
  },
  "geometry": {"coordinates":[-84.402334,39.157954],"type":"Point"}
}
