{
  "type": "Feature",
  "properties": {
    "addr:full":"67 W 2nd St Xenia OH 45385",
    "addr:housenumber":"67",
    "addr:postcode":"45385",
    "addr:street":"W 2Nd St",
    "iso:country":"US",
    "sg:address":"67 W 2nd St",
    "sg:city":"Xenia",
    "sg:classifiers":[
        {
            "category":"Personal",
            "subcategory":"Tattoo Parlor",
            "type":"Services"
        }
    ],
    "sg:phone":"+1 937 376 3930",
    "sg:postcode":"45385",
    "sg:province":"OH",
    "sg:tags":[
        "tattooing"
    ],
    "wof:name":"Art Othe Skin",
    "wof:placetype":"venue"
},
  "geometry": {"coordinates":[-83.92995000000001,39.683731],"type":"Point"}
}