{
  "type": "Feature",
  "properties": {
    "addr:full": "9337 Ravenna Rd Twinsburg OH 44087",
    "addr:housenumber": "9337",
    "addr:postcode": "44087",
    "addr:street": "Ravenna Rd",
    "iso:country": "US",
    "sg:address": "9337 Ravenna Rd",
    "sg:city": "Twinsburg",
    "sg:classifiers": [
      {
        "category": "Manufacturing",
        "subcategory": "Tools \u0026 Machinery",
        "type": "Manufacturing \u0026 Wholesale Goods"
      }
    ],
    "sg:phone": "+1 330 425 9077",
    "sg:postcode": "44087",
    "sg:province": "OH",
    "sg:tags": [
      "dist",
      "surgical",
      "appliance",
      "for",
      "supply"
    ],
    "wof:name": "Biomet Inc",
    "wof:placetype": "venue"
  },
  "geometry": {"coordinates":[-81.429654,41.308319],"type":"Point"}
}
