{
  "type": "Feature",
  "properties": {
    "addr:full": "697 Baltzley Valley Rd SE New Philadelphia OH 44663",
    "addr:housenumber": "697",
    "addr:postcode": "44663",
    "addr:street": "Baltzley Valley Rd Se New",
    "iso:country": "US",
    "sg:address": "697 Baltzley Valley Rd SE",
    "sg:city": "New Philadelphia",
    "sg:classifiers": [
      {
        "category": "Manufacturing",
        "subcategory": "Retail Goods",
        "type": "Manufacturing \u0026 Wholesale Goods"
      }
    ],
    "sg:phone": "+1 330 602 1294",
    "sg:postcode": "44663",
    "sg:province": "OH",
    "sg:tags": [
      "product",
      "merchandise",
      "mfg"
    ],
    "wof:name": "Sugarcreek Candles",
    "wof:placetype": "venue"
  },
  "geometry": {"coordinates":[-81.372475,40.466424],"type":"Point"}
}
