{
  "type": "Feature",
  "properties": {
    "iso:country":"US",
    "sg:address":"697 Baltzley Valley Rd SE",
    "sg:city":"New Philadelphia",
    "sg:classifiers":[
        {
            "category":"Manufacturing",
            "subcategory":"Retail Goods",
            "type":"Manufacturing & Wholesale Goods"
        }
    ],
    "sg:phone":"+1 330 602 1294",
    "sg:postcode":"44663",
    "sg:province":"OH",
    "sg:tags":[
        "product",
        "merchandise",
        "mfg"
    ],
    "wof:name":"Sugarcreek Candles",
    "wof:placetype":"venue"
},
  "geometry": {"coordinates":[-81.37247499999999,40.466424],"type":"Point"}
}