{
  "type": "Feature",
  "properties": {
    "addr:full": "110 Island Rd Circleville OH 43113",
    "addr:housenumber": "110",
    "addr:postcode": "43113",
    "addr:street": "Island Rd",
    "iso:country": "US",
    "sg:address": "110 Island Rd",
    "sg:city": "Circleville",
    "sg:classifiers": [
      {
        "category": "Government",
        "subcategory": "Office",
        "type": "Public Place"
      }
    ],
    "sg:phone": "+1 740 477 1911",
    "sg:postcode": "43113",
    "sg:province": "OH",
    "sg:tags": [
      "county",
      "program",
      "health"
    ],
    "wof:name": "Board Of HEALTH-Wic Program",
    "wof:placetype": "venue"
  },
  "geometry": {"coordinates":[-82.94952,39.604211],"type":"Point"}
}
