{
  "type": "Feature",
  "properties": {
    "addr:full":"120 Main St Ripley OH 45167",
    "addr:housenumber":"120",
    "addr:postcode":"45167",
    "addr:street":"Main St",
    "iso:country":"US",
    "sg:address":"120 Main St",
    "sg:city":"Ripley",
    "sg:classifiers":[
        {
            "category":"Education",
            "subcategory":"School",
            "type":"Public Place"
        }
    ],
    "sg:phone":"+1 937 392 1527",
    "sg:postcode":"45167",
    "sg:province":"OH",
    "sg:tags":[
        "management"
    ],
    "wof:name":"Ruhl Schools",
    "wof:placetype":"venue"
},
  "geometry": {"coordinates":[-83.84419800000001,38.746045],"type":"Point"}
}