{
  "type": "Feature",
  "properties": {
    "addr:full": "810 2nd St Brilliant OH 43913",
    "addr:housenumber": "810",
    "addr:postcode": "43913",
    "addr:street": "2Nd St",
    "iso:country": "US",
    "sg:address": "810 2nd St",
    "sg:city": "Brilliant",
    "sg:classifiers": [
      {
        "category": "Retail",
        "subcategory": "Animal Services",
        "type": "Services"
      }
    ],
    "sg:phone": "+1 740 598 4303",
    "sg:postcode": "43913",
    "sg:province": "OH",
    "wof:name": "Dianas Pet Grooming",
    "wof:placetype": "venue"
  },
  "geometry": {"coordinates":[-80.629636,40.263391],"type":"Point"}
}
