{
  "type": "Feature",
  "properties": {
    "addr:full":"2880 W Elm St Lima OH 45805",
    "addr:housenumber":"2880",
    "addr:postcode":"45805",
    "addr:street":"W Elm St",
    "iso:country":"US",
    "sg:address":"2880 W Elm St",
    "sg:city":"Lima",
    "sg:classifiers":[
        {
            "category":"Restaurant",
            "type":"Food & Drink"
        }
    ],
    "sg:phone":"+1 419 227 4200",
    "sg:postcode":"45805",
    "sg:province":"OH",
    "sg:tags":[
        "eating"
    ],
    "wof:name":"Quincys",
    "wof:placetype":"venue"
},
  "geometry": {"coordinates":[-84.157479,40.737101],"type":"Point"}
}