{
  "type": "Feature",
  "properties": {
    "addr:full":"1151 Stone Dr Harrison IN 45030",
    "addr:housenumber":"1151",
    "addr:postcode":"45030",
    "addr:street":"Stone Dr",
    "iso:country":"US",
    "sg:address":"1151 Stone Dr",
    "sg:city":"Harrison",
    "sg:classifiers":[
        {
            "category":"Wholesale",
            "subcategory":"Groceries",
            "type":"Manufacturing & Wholesale Goods"
        }
    ],
    "sg:phone":"+1 513 367 5878",
    "sg:postcode":"45030",
    "sg:province":"IN",
    "sg:tags":[
        "bakery",
        "product",
        "baker"
    ],
    "wof:name":"Butternut Bread",
    "wof:placetype":"venue"
},
  "geometry": {"coordinates":[-84.795816,39.253728],"type":"Point"}
}