{
  "type": "Feature",
  "properties": {
    "addr:full":"1536 River Valley Cir S Lancaster OH 43130",
    "addr:housenumber":"1536",
    "addr:postcode":"43130",
    "addr:street":"River Valley Cir S",
    "iso:country":"US",
    "sg:address":"1536 River Valley Cir S",
    "sg:city":"Lancaster",
    "sg:classifiers":[
        {
            "category":"Personal",
            "subcategory":"Beauty Salon",
            "type":"Services"
        }
    ],
    "sg:phone":"+1 740 653 5003",
    "sg:postcode":"43130",
    "sg:province":"OH",
    "wof:name":"Saturday's Family Hair Care",
    "wof:placetype":"venue"
},
  "geometry": {"coordinates":[-82.624973,39.731905],"type":"Point"}
}