{
  "type": "Feature",
  "properties": {
    "addr:full": "1520 S Arlington St Akron OH 44306",
    "addr:housenumber": "1520",
    "addr:postcode": "44306",
    "addr:street": "S Arlington St",
    "iso:country": "US",
    "sg:address": "1520 S Arlington St",
    "sg:city": "Akron",
    "sg:classifiers": [
      {
        "category": "Professional",
        "subcategory": "Detective \u0026 Security Services",
        "type": "Services"
      }
    ],
    "sg:phone": "+1 330 773 1635",
    "sg:postcode": "44306",
    "sg:province": "OH",
    "sg:tags": [
      "guard",
      "patrol"
    ],
    "wof:name": "Burns International Security",
    "wof:placetype": "venue"
  },
  "geometry": {"coordinates":[-81.491562,41.028841],"type":"Point"}
}
