{
  "type": "Feature",
  "properties": {
    "iso:country":"US",
    "sg:address":"4127 Rosehill Dr",
    "sg:city":"Dayton",
    "sg:classifiers":[
        {
            "category":"Real Estate",
            "subcategory":"Real Estate Operator",
            "type":"Services"
        }
    ],
    "sg:phone":"+1 937 426 5714",
    "sg:postcode":"45431",
    "sg:province":"OH",
    "sg:tags":[
        "property",
        "lessor"
    ],
    "wof:name":"Robert Buchner",
    "wof:placetype":"venue"
},
  "geometry": {"coordinates":[-84.083741,39.765984],"type":"Point"}
}