{
  "type": "Feature",
  "properties": {
    "iso:country":"US",
    "sg:address":"259 Township Ave",
    "sg:city":"Cincinnati",
    "sg:classifiers":[
        {
            "category":"Building & Trades",
            "subcategory":"Construction",
            "type":"Services"
        }
    ],
    "sg:phone":"+1 513 641 2222",
    "sg:postcode":"45216",
    "sg:province":"OH",
    "sg:tags":[
        "tank"
    ],
    "wof:name":"B & R Fabricators & Mntnc",
    "wof:placetype":"venue"
},
  "geometry": {"coordinates":[-84.488822,39.184169],"type":"Point"}
}