{
  "type": "Feature",
  "properties": {
    "addr:full":"515 Town Line Rd Bryan OH 43506",
    "addr:housenumber":"515",
    "addr:postcode":"43506",
    "addr:street":"Town Line Rd",
    "iso:country":"US",
    "sg:address":"515 Town Line Rd",
    "sg:city":"Bryan",
    "sg:classifiers":[
        {
            "category":"Organizations",
            "subcategory":"Religious Organization",
            "type":"Services"
        }
    ],
    "sg:phone":"+1 419 636 0003",
    "sg:postcode":"43506",
    "sg:province":"OH",
    "sg:tags":[
        "church"
    ],
    "wof:name":"Church Of Jesus Christ Of Lds",
    "wof:placetype":"venue"
},
  "geometry": {"coordinates":[-84.57381700000001,41.469789],"type":"Point"}
}