{
  "type": "Feature",
  "properties": {
    "iso:country":"US",
    "sg:address":"1055 Saint Paul Pl",
    "sg:city":"Cincinnati",
    "sg:classifiers":[
        {
            "category":"Organizations",
            "subcategory":"Community Association",
            "type":"Services"
        }
    ],
    "sg:phone":"+1 513 381 0729",
    "sg:postcode":"45202",
    "sg:province":"OH",
    "wof:name":"Rossford Run Hoa",
    "wof:placetype":"venue"
},
  "geometry": {"coordinates":[-84.498493,39.107438],"type":"Point"}
}