{
  "type": "Feature",
  "properties": {
    "addr:full": "12116 Sobieski Ave Cleveland OH 44135",
    "addr:postcode": "12116;44135",
    "addr:street": "Sobieski Ave",
    "iso:country": "US",
    "sg:address": "12116 Sobieski Ave",
    "sg:city": "Cleveland",
    "sg:classifiers": [
      {
        "category": "Building \u0026 Trades",
        "subcategory": "Construction",
        "type": "Services"
      }
    ],
    "sg:phone": "+1 216 898 1900",
    "sg:postcode": "44135",
    "sg:province": "OH",
    "sg:tags": [
      "roofing",
      "contractor"
    ],
    "wof:name": "West Side Roofing Co Inc",
    "wof:placetype": "venue"
  },
  "geometry": {"coordinates":[-81.774128,41.439274],"type":"Point"}
}
