{
  "type": "Feature",
  "properties": {
    "addr:full":"828 Warehouse Rd Toledo OH 43615",
    "addr:housenumber":"828",
    "addr:postcode":"43615",
    "addr:street":"Warehouse Rd",
    "iso:country":"US",
    "sg:address":"828 Warehouse Rd",
    "sg:city":"Toledo",
    "sg:classifiers":[
        {
            "category":"Home & Garden",
            "subcategory":"Household Appliances",
            "type":"Retail Goods"
        },
        {
            "category":"Building & Trades",
            "subcategory":"Construction",
            "type":"Services"
        }
    ],
    "sg:phone":"+1 419 385 9299",
    "sg:postcode":"43615",
    "sg:province":"OH",
    "sg:tags":[
        "installs",
        "planning",
        "remodeling",
        "kitchen",
        "cabinet"
    ],
    "sg:website":"www.toledokitchensunlimited.com",
    "wof:name":"Bob Hahn's Kitchens Unlimited",
    "wof:placetype":"venue"
},
  "geometry": {"coordinates":[-83.653746,41.624435],"type":"Point"}
}