{
  "type": "Feature",
  "properties": {
    "addr:full":"22300 Euclid Ave Cleveland OH 44117",
    "addr:housenumber":"22300",
    "addr:postcode":"44117",
    "addr:street":"Euclid Ave",
    "iso:country":"US",
    "sg:address":"22300 Euclid Ave",
    "sg:city":"Cleveland",
    "sg:classifiers":[
        {
            "category":"Shopping",
            "subcategory":"Clothing, Apparel, & Fashions",
            "type":"Retail Goods"
        }
    ],
    "sg:phone":"+1 216 692 2824",
    "sg:postcode":"44117",
    "sg:province":"OH",
    "wof:name":"Allure Fashions",
    "wof:placetype":"venue"
},
  "geometry": {"coordinates":[-81.523894,41.572929],"type":"Point"}
}