{
  "type": "Feature",
  "properties": {
    "addr:full": "8315 Beechmont Ave Cincinnati OH 45255",
    "addr:housenumber": "8315",
    "addr:postcode": "45255",
    "addr:street": "Beechmont Ave",
    "iso:country": "US",
    "sg:address": "8315 Beechmont Ave",
    "sg:city": "Cincinnati",
    "sg:classifiers": [
      {
        "category": "Shopping",
        "type": "Retail Goods"
      }
    ],
    "sg:phone": "+1 513 923 4999",
    "sg:postcode": "45255",
    "sg:province": "OH",
    "sg:tags": [
      "hearing",
      "equipment",
      "supply",
      "impaired"
    ],
    "wof:name": "Beltone Hearing Aid Ctr",
    "wof:placetype": "venue"
  },
  "geometry": {"coordinates":[-84.325826,39.07265],"type":"Point"}
}
