{
  "type": "Feature",
  "properties": {
    "iso:country":"US",
    "sg:address":"5377 Beach Blvd",
    "sg:city":"Mason",
    "sg:classifiers":[
        {
            "category":"Restaurant",
            "type":"Food & Drink"
        }
    ],
    "sg:menulink":"http://www.allmenus.com/oh/mason/141828-waffle-house/menu/",
    "sg:phone":"+1 513 398 2974",
    "sg:postcode":"45040",
    "sg:province":"OH",
    "sg:tags":[
        "american"
    ],
    "wof:name":"Waffle House",
    "wof:placetype":"venue"
},
  "geometry": {"coordinates":[-84.26746799999999,39.359042],"type":"Point"}
}