{
  "type": "Feature",
  "properties": {
    "addr:full":"485 S Front St Columbus OH 43215",
    "addr:housenumber":"485",
    "addr:postcode":"43215",
    "addr:street":"S Front St",
    "iso:country":"US",
    "sg:address":"485 S Front St",
    "sg:city":"Columbus",
    "sg:classifiers":[
        {
            "category":"Bars & Pubs",
            "type":"Food & Drink"
        }
    ],
    "sg:phone":"+1 614 221 9663",
    "sg:postcode":"43215",
    "sg:province":"OH",
    "sg:tags":[
        "club",
        "night"
    ],
    "wof:name":"Major Woody's LLC",
    "wof:placetype":"venue"
},
  "geometry": {"coordinates":[-83.00046,39.95159],"type":"Point"}
}