{
  "type": "Feature",
  "properties": {
    "iso:country":"US",
    "sg:address":"301 E Lake Ave",
    "sg:city":"Bellefontaine",
    "sg:classifiers":[
        {
            "category":"Government",
            "subcategory":"Office",
            "type":"Public Place"
        }
    ],
    "sg:phone":"+1 937 599 4178",
    "sg:postcode":"43311",
    "sg:province":"OH",
    "wof:name":"Logan County Fairgrounds",
    "wof:placetype":"venue"
},
  "geometry": {"coordinates":[-83.758466,40.346675],"type":"Point"}
}