{
  "type": "Feature",
  "properties": {
    "addr:full": "103 Woodland Dr Millersburg OH 44654",
    "addr:housenumber": "103",
    "addr:postcode": "44654",
    "addr:street": "Woodland Dr",
    "iso:country": "US",
    "sg:address": "103 Woodland Dr",
    "sg:city": "Millersburg",
    "sg:classifiers": [
      {
        "category": "Banks \u0026 Credit Unions",
        "subcategory": "Financial Services",
        "type": "Services"
      }
    ],
    "sg:phone": "+1 330 674 5766",
    "sg:postcode": "44654",
    "sg:province": "OH",
    "sg:tags": [
      "trust",
      "management"
    ],
    "wof:name": "Burkey Family Trust",
    "wof:placetype": "venue"
  },
  "geometry": {"coordinates":[-81.919734,40.564354],"type":"Point"}
}
