{
  "type": "Feature",
  "properties": {
    "addr:full":"17262 Rd K Ottawa OH 45875",
    "addr:postcode":"17262;45875",
    "addr:street":"Rd",
    "iso:country":"US",
    "sg:address":"17262 Rd K",
    "sg:city":"Ottawa",
    "sg:classifiers":[
        {
            "category":"Professional",
            "type":"Services"
        }
    ],
    "sg:phone":"+1 419 532 2270",
    "sg:postcode":"45875",
    "sg:province":"OH",
    "wof:name":"Mark Siebeneck",
    "wof:placetype":"venue"
},
  "geometry": {"coordinates":[-84.193288,41.020796],"type":"Point"}
}