{
  "type": "Feature",
  "properties": {
    "iso:country":"US",
    "sg:address":"612 Central Center",
    "sg:city":"Chillicothe",
    "sg:classifiers":[
        {
            "category":"Banks & Credit Unions",
            "subcategory":"Investment Brokerage",
            "type":"Services"
        }
    ],
    "sg:phone":"+1 740 773 9444",
    "sg:postcode":"45601",
    "sg:province":"OH",
    "sg:tags":[
        "security"
    ],
    "wof:name":"A G Edwards 645",
    "wof:placetype":"venue"
},
  "geometry": {"coordinates":[-83.00186100000001,39.337316],"type":"Point"}
}