{
  "type": "Feature",
  "properties": {
    "addr:full": "612 Central Center Chillicothe OH 45601",
    "addr:housenumber": "612",
    "addr:postcode": "45601",
    "addr:street": "Central Center",
    "iso:country": "US",
    "sg:address": "612 Central Center",
    "sg:city": "Chillicothe",
    "sg:classifiers": [
      {
        "category": "Banks \u0026 Credit Unions",
        "subcategory": "Investment Brokerage",
        "type": "Services"
      }
    ],
    "sg:phone": "+1 740 773 9444",
    "sg:postcode": "45601",
    "sg:province": "OH",
    "sg:tags": [
      "security"
    ],
    "wof:name": "A G Edwards 645",
    "wof:placetype": "venue"
  },
  "geometry": {"coordinates":[-83.001861,39.337316],"type":"Point"}
}
