{
  "type": "Feature",
  "properties": {
    "iso:country":"US",
    "sg:address":"222 Front St",
    "sg:city":"Berea",
    "sg:classifiers":[
        {
            "category":"Personal",
            "subcategory":"Barber",
            "type":"Services"
        }
    ],
    "sg:phone":"+1 440 826 3544",
    "sg:postcode":"44017",
    "sg:province":"OH",
    "wof:name":"Campus Barber Styling Shop",
    "wof:placetype":"venue"
},
  "geometry": {"coordinates":[-81.853022,41.371],"type":"Point"}
}