{
  "type": "Feature",
  "properties": {
    "iso:country":"US",
    "sg:address":"26 E Water St",
    "sg:city":"Chillicothe",
    "sg:classifiers":[
        {
            "category":"Personal",
            "subcategory":"Barber",
            "type":"Services"
        }
    ],
    "sg:phone":"+1 740 772 2656",
    "sg:postcode":"45601",
    "sg:province":"OH",
    "wof:name":"Water Street Barber Shop",
    "wof:placetype":"venue"
},
  "geometry": {"coordinates":[-82.980401,39.336119],"type":"Point"}
}