{
  "type": "Feature",
  "properties": {
    "addr:full": "18 E Columbus St Pickerington OH 43147",
    "addr:housenumber": "18",
    "addr:postcode": "43147",
    "addr:street": "E Columbus St",
    "iso:country": "US",
    "sg:address": "18 E Columbus St",
    "sg:city": "Pickerington",
    "sg:classifiers": [
      {
        "category": "Freight",
        "type": "Transportation"
      }
    ],
    "sg:phone": "+1 614 833 9841",
    "sg:postcode": "43147",
    "sg:province": "OH",
    "sg:tags": [
      "excavation",
      "utility",
      "contractor"
    ],
    "wof:name": "McCook Excavating",
    "wof:placetype": "venue"
  },
  "geometry": {"coordinates":[-82.753344,39.88411],"type":"Point"}
}
