{
  "type": "Feature",
  "properties": {
    "iso:country":"US",
    "sg:address":"18 E Columbus St",
    "sg:city":"Pickerington",
    "sg:classifiers":[
        {
            "category":"Freight",
            "type":"Transportation"
        }
    ],
    "sg:phone":"+1 614 833 9841",
    "sg:postcode":"43147",
    "sg:province":"OH",
    "sg:tags":[
        "excavation",
        "utility",
        "contractor"
    ],
    "wof:name":"McCook Excavating",
    "wof:placetype":"venue"
},
  "geometry": {"coordinates":[-82.753344,39.88411],"type":"Point"}
}