{
  "type": "Feature",
  "properties": {
    "iso:country":"US",
    "sg:address":"3221 Cleveland Ave SW",
    "sg:city":"Canton",
    "sg:classifiers":[
        {
            "category":"Banks & Credit Unions",
            "subcategory":"Bank",
            "type":"Services"
        }
    ],
    "sg:phone":"+1 330 866 9392",
    "sg:postcode":"44707",
    "sg:province":"OH",
    "sg:tags":[
        "federal",
        "savings",
        "institution"
    ],
    "wof:name":"Bank of Magnolia Company",
    "wof:placetype":"venue"
},
  "geometry": {"coordinates":[-81.380056,40.761738],"type":"Point"}
}