{
  "type": "Feature",
  "properties": {
    "addr:full": "548 N McElroy Rd Mansfield OH 44905",
    "addr:housenumber": "548",
    "addr:postcode": "44905",
    "addr:street": "N Mcelroy Rd",
    "iso:country": "US",
    "sg:address": "548 N McElroy Rd",
    "sg:city": "Mansfield",
    "sg:classifiers": [
      {
        "category": "Organizations",
        "subcategory": "Religious Organization",
        "type": "Services"
      }
    ],
    "sg:phone": "+1 419 589 6612",
    "sg:postcode": "44905",
    "sg:province": "OH",
    "sg:tags": [
      "church"
    ],
    "wof:name": "Mayflower Congregational Chr",
    "wof:placetype": "venue"
  },
  "geometry": {"coordinates":[-82.464934,40.771121],"type":"Point"}
}
