{
  "type": "Feature",
  "properties": {
    "addr:full": "205 S Main St Akron OH 44308",
    "addr:housenumber": "205",
    "addr:postcode": "44308",
    "addr:street": "S Main St",
    "iso:country": "US",
    "sg:address": "205 S Main St",
    "sg:city": "Akron",
    "sg:classifiers": [
      {
        "category": "Real Estate",
        "subcategory": "Real Estate Agent",
        "type": "Services"
      }
    ],
    "sg:phone": "+1 330 761 1079",
    "sg:postcode": "44308",
    "sg:province": "OH",
    "sg:tags": [
      "management"
    ],
    "wof:name": "North Coast Oil",
    "wof:placetype": "venue"
  },
  "geometry": {"coordinates":[-81.519467,41.08038],"type":"Point"}
}
