{
  "type": "Feature",
  "properties": {
    "addr:full":"7724 Washington Park Dr Dayton OH 45459",
    "addr:housenumber":"7724",
    "addr:postcode":"45459",
    "addr:street":"Washington Park Dr",
    "iso:country":"US",
    "sg:address":"7724 Washington Park Dr",
    "sg:city":"Dayton",
    "sg:classifiers":[
        {
            "category":"Health Services",
            "subcategory":"Doctor",
            "type":"Services"
        }
    ],
    "sg:phone":"+1 937 439 7420",
    "sg:postcode":"45459",
    "sg:province":"OH",
    "wof:name":"Providence Medical Imaging",
    "wof:placetype":"venue"
},
  "geometry": {"coordinates":[-84.20791,39.636724],"type":"Point"}
}