{
  "type": "Feature",
  "properties": {
    "addr:full": "6940 State Rte 100 Tiffin OH 44883",
    "addr:housenumber": "6940",
    "addr:postcode": "44883",
    "addr:street": "State Rte 100",
    "iso:country": "US",
    "sg:address": "6940 State Rte 100",
    "sg:city": "Tiffin",
    "sg:classifiers": [
      {
        "category": "Retail",
        "subcategory": "Repair Shop",
        "type": "Services"
      }
    ],
    "sg:phone": "+1 419 397 2517",
    "sg:postcode": "44883",
    "sg:province": "OH",
    "sg:tags": [
      "repairing",
      "saw"
    ],
    "wof:name": "Gittinger Saw Shop",
    "wof:placetype": "venue"
  },
  "geometry": {"coordinates":[-83.109542,41.023256],"type":"Point"}
}
