{
  "type": "Feature",
  "properties": {
    "addr:full":"21445 State Rte 243 Proctorville OH 45669",
    "addr:housenumber":"21445",
    "addr:postcode":"45669",
    "addr:street":"State Rte 243",
    "iso:country":"US",
    "sg:address":"21445 State Rte 243",
    "sg:city":"Proctorville",
    "sg:classifiers":[
        {
            "category":"Organizations",
            "subcategory":"Religious Organization",
            "type":"Services"
        }
    ],
    "sg:phone":"+1 740 886 6905",
    "sg:postcode":"45669",
    "sg:province":"OH",
    "sg:tags":[
        "child",
        "day",
        "care",
        "church"
    ],
    "sg:website":"www.fbcproctorville.com",
    "wof:name":"First Baptist Church Inc",
    "wof:placetype":"venue"
},
  "geometry": {"coordinates":[-82.36131899999999,38.449975],"type":"Point"}
}