{
  "type": "Feature",
  "properties": {
    "iso:country":"US",
    "sg:address":"1334 N Lutheran Church Rd",
    "sg:city":"Dayton",
    "sg:classifiers":[
        {
            "category":"Education",
            "subcategory":"Vocational School",
            "type":"Public Place"
        }
    ],
    "sg:phone":"+1 937 854 1406",
    "sg:postcode":"45309",
    "sg:province":"OH",
    "wof:name":"Dahio Trottwood",
    "wof:placetype":"venue"
},
  "geometry": {"coordinates":[-84.348294,39.760707],"type":"Point"}
}