{
  "type": "Feature",
  "properties": {
    "iso:country":"US",
    "sg:address":"2741 Sullivant Ave",
    "sg:city":"Columbus",
    "sg:classifiers":[
        {
            "category":"Autos & Motor Vehicles",
            "subcategory":"Auto Supplies",
            "type":"Retail Goods"
        }
    ],
    "sg:phone":"+1 614 274 3465",
    "sg:postcode":"43204",
    "sg:province":"OH",
    "sg:tags":[
        "automobile",
        "stereo",
        "radio"
    ],
    "wof:name":"Extreme Audio Outlet",
    "wof:placetype":"venue"
},
  "geometry": {"coordinates":[-83.070944,39.943918],"type":"Point"}
}