{
  "type": "Feature",
  "properties": {
    "addr:full":"33587 Walker Rd Avon Lake OH 44012",
    "addr:housenumber":"33587",
    "addr:postcode":"44012",
    "addr:street":"Walker Rd",
    "iso:country":"US",
    "sg:address":"33587 Walker Rd",
    "sg:city":"Avon Lake",
    "sg:classifiers":[
        {
            "category":"Wholesale",
            "subcategory":"Chemicals & Plastics",
            "type":"Manufacturing & Wholesale Goods"
        }
    ],
    "sg:phone":"+1 440 930 1000",
    "sg:postcode":"44012",
    "sg:province":"OH",
    "sg:website":"www.polyone.com",
    "wof:name":"Poly One Corp",
    "wof:placetype":"venue"
},
  "geometry": {"coordinates":[-82.05333400000001,41.493413],"type":"Point"}
}