{
  "type": "Feature",
  "properties": {
    "addr:full":"5668 Piquad Rd Lima OH 45807",
    "addr:housenumber":"5668",
    "addr:postcode":"45807",
    "addr:street":"Piquad Rd",
    "iso:country":"US",
    "sg:address":"5668 Piquad Rd",
    "sg:city":"Lima",
    "sg:classifiers":[
        {
            "category":"Building & Trades",
            "subcategory":"Construction",
            "type":"Services"
        }
    ],
    "sg:phone":"+1 419 339 1717",
    "sg:postcode":"45807",
    "sg:province":"OH",
    "sg:tags":[
        "concrete",
        "contractor"
    ],
    "wof:name":"Craftsman Construction",
    "wof:placetype":"venue"
},
  "geometry": {"coordinates":[-84.211671,40.787961],"type":"Point"}
}