{
  "type": "Feature",
  "properties": {
    "addr:full": "3605 Mahoning Ave Youngstown OH 44515",
    "addr:housenumber": "3605",
    "addr:postcode": "44515",
    "addr:street": "Mahoning Ave",
    "iso:country": "US",
    "sg:address": "3605 Mahoning Ave",
    "sg:city": "Youngstown",
    "sg:classifiers": [
      {
        "category": "Autos \u0026 Motor Vehicles",
        "subcategory": "Fuel \u0026 Gas Station",
        "type": "Retail Goods"
      }
    ],
    "sg:phone": "+1 330 270 3566",
    "sg:postcode": "44515",
    "sg:province": "OH",
    "sg:tags": [
      "oil"
    ],
    "wof:name": "Dal-D Service Inc",
    "wof:placetype": "venue"
  },
  "geometry": {"coordinates":[-80.712136,41.102659],"type":"Point"}
}
