{
  "type": "Feature",
  "properties": {
    "addr:full":"13705 Euclid Ave Cleveland OH 44112",
    "addr:housenumber":"13705",
    "addr:postcode":"44112",
    "addr:street":"Euclid Ave",
    "iso:country":"US",
    "sg:address":"13705 Euclid Ave",
    "sg:city":"Cleveland",
    "sg:classifiers":[
        {
            "category":"Restaurant",
            "type":"Food & Drink"
        }
    ],
    "sg:menulink":"http://www.allmenus.com/oh/east-cleveland/194929-mcdonalds/menu/",
    "sg:postcode":"44112",
    "sg:province":"OH",
    "sg:tags":[
        "burger",
        "american"
    ],
    "wof:name":"McDonald's",
    "wof:placetype":"venue"
},
  "geometry": {"coordinates":[-81.58739799999999,41.525184],"type":"Point"}
}