{
  "type": "Feature",
  "properties": {
    "addr:full": "188 N Brookwood Ave Hamilton IN 45013",
    "addr:housenumber": "188",
    "addr:postcode": "45013",
    "addr:street": "N Brookwood Ave",
    "iso:country": "US",
    "sg:address": "188 N Brookwood Ave",
    "sg:city": "Hamilton",
    "sg:classifiers": [
      {
        "category": "Banks \u0026 Credit Unions",
        "subcategory": "Financial Services",
        "type": "Services"
      }
    ],
    "sg:phone": "+1 513 896 9695",
    "sg:postcode": "45013",
    "sg:province": "IN",
    "sg:tags": [
      "sell",
      "franchise",
      "sandwich",
      "shop",
      "operates"
    ],
    "wof:name": "Great Steak \u0026 Potato",
    "wof:placetype": "venue"
  },
  "geometry": {"coordinates":[-84.58919,39.42034],"type":"Point"}
}
