{
  "type": "Feature",
  "properties": {
    "iso:country":"US",
    "sg:address":"262 Hillsdale Dr",
    "sg:city":"Coshocton",
    "sg:classifiers":[
        {
            "category":"Building & Trades",
            "subcategory":"Construction",
            "type":"Services"
        }
    ],
    "sg:phone":"+1 740 622 1013",
    "sg:postcode":"43812",
    "sg:province":"OH",
    "sg:tags":[
        "house"
    ],
    "wof:name":"Custom Remodeling",
    "wof:placetype":"venue"
},
  "geometry": {"coordinates":[-81.887576,40.275828],"type":"Point"}
}