{
  "type": "Feature",
  "properties": {
    "addr:full": "4248 N River Rd NE Warren OH 44484",
    "addr:housenumber": "4248",
    "addr:postcode": "44484",
    "addr:street": "N River Rd Ne",
    "iso:country": "US",
    "sg:address": "4248 N River Rd NE",
    "sg:city": "Warren",
    "sg:classifiers": [
      {
        "category": "Bars \u0026 Pubs",
        "type": "Food \u0026 Drink"
      }
    ],
    "sg:phone": "+1 330 856 5650",
    "sg:postcode": "44484",
    "sg:province": "OH",
    "wof:name": "Without A Paddle Bar \u0026 Grill",
    "wof:placetype": "venue"
  },
  "geometry": {"coordinates":[-80.740977,41.265441],"type":"Point"}
}
