{
  "type": "Feature",
  "properties": {
    "iso:country":"US",
    "sg:address":"404 N Lake St",
    "sg:city":"Madison",
    "sg:classifiers":[
        {
            "category":"Building & Trades",
            "subcategory":"Construction",
            "type":"Services"
        }
    ],
    "sg:phone":"+1 440 428 5222",
    "sg:postcode":"44057",
    "sg:province":"OH",
    "sg:tags":[
        "siding",
        "contractor"
    ],
    "wof:name":"Morin Sidings Inc",
    "wof:placetype":"venue"
},
  "geometry": {"coordinates":[-81.047245,41.778908],"type":"Point"}
}