{
  "type": "Feature",
  "properties": {
    "iso:country":"US",
    "sg:address":"1503 26th St NW",
    "sg:city":"Canton",
    "sg:classifiers":[
        {
            "category":"Restaurant",
            "type":"Food & Drink"
        }
    ],
    "sg:phone":"+1 330 456 9779",
    "sg:postcode":"44709",
    "sg:province":"OH",
    "wof:name":"Gioninos Pizzaria",
    "wof:placetype":"venue"
},
  "geometry": {"coordinates":[-81.387529,40.82516],"type":"Point"}
}