{
  "type": "Feature",
  "properties": {
    "addr:full": "1503 26th St NW Canton OH 44709",
    "addr:housenumber": "1503",
    "addr:postcode": "44709",
    "addr:street": "26Th St Nw",
    "iso:country": "US",
    "sg:address": "1503 26th St NW",
    "sg:city": "Canton",
    "sg:classifiers": [
      {
        "category": "Restaurant",
        "type": "Food \u0026 Drink"
      }
    ],
    "sg:phone": "+1 330 456 9779",
    "sg:postcode": "44709",
    "sg:province": "OH",
    "wof:name": "Gioninos Pizzaria",
    "wof:placetype": "venue"
  },
  "geometry": {"coordinates":[-81.387529,40.82516],"type":"Point"}
}
