{
  "type": "Feature",
  "properties": {
    "addr:full":"7253 Hills and Dales Rd NW Massillon OH 44646",
    "addr:housenumber":"7253",
    "addr:postcode":"44646",
    "addr:street":"Hills And Dales Rd Nw",
    "iso:country":"US",
    "sg:address":"7253 Hills and Dales Rd NW",
    "sg:city":"Massillon",
    "sg:classifiers":[
        {
            "category":"Professional",
            "type":"Services"
        }
    ],
    "sg:phone":"+1 330 837 4434",
    "sg:postcode":"44646",
    "sg:province":"OH",
    "wof:name":"Clayton Livengood",
    "wof:placetype":"venue"
},
  "geometry": {"coordinates":[-81.489243,40.827067],"type":"Point"}
}