{
  "type": "Feature",
  "properties": {
    "addr:full": "720 Armstrong St Saint Marys OH 45885",
    "addr:housenumber": "720",
    "addr:postcode": "45885",
    "addr:street": "Armstrong St",
    "iso:country": "US",
    "sg:address": "720 Armstrong St",
    "sg:city": "Saint Marys",
    "sg:classifiers": [
      {
        "category": "Social Services",
        "type": "Services"
      }
    ],
    "sg:phone": "+1 419 394 4194",
    "sg:postcode": "45885",
    "sg:province": "OH",
    "wof:name": "Family Resourse Ctr",
    "wof:placetype": "venue"
  },
  "geometry": {"coordinates":[-84.379004,40.550889],"type":"Point"}
}
