{
  "type": "Feature",
  "properties": {
    "iso:country":"US",
    "sg:address":"720 Armstrong St",
    "sg:city":"Saint Marys",
    "sg:classifiers":[
        {
            "category":"Social Services",
            "type":"Services"
        }
    ],
    "sg:phone":"+1 419 394 4194",
    "sg:postcode":"45885",
    "sg:province":"OH",
    "wof:name":"Family Resourse Ctr",
    "wof:placetype":"venue"
},
  "geometry": {"coordinates":[-84.37900399999999,40.550889],"type":"Point"}
}