{
  "type": "Feature",
  "properties": {
    "addr:full": "1945 S Gettysburg Ave Dayton OH 45418",
    "addr:housenumber": "1945",
    "addr:postcode": "45418",
    "addr:street": "S Gettysburg Ave",
    "iso:country": "US",
    "sg:address": "1945 S Gettysburg Ave",
    "sg:city": "Dayton",
    "sg:classifiers": [
      {
        "category": "Social Services",
        "type": "Services"
      }
    ],
    "sg:phone": "+1 937 224 3728",
    "sg:postcode": "45418",
    "sg:province": "OH",
    "sg:tags": [
      "probation"
    ],
    "wof:name": "Montgomery County Probation",
    "wof:placetype": "venue"
  },
  "geometry": {"coordinates":[-84.252622,39.728958],"type":"Point"}
}
