{
  "type": "Feature",
  "properties": {
    "iso:country":"US",
    "sg:address":"1971 Mackletree Rd",
    "sg:city":"Blue Creek",
    "sg:classifiers":[
        {
            "category":"Freight",
            "type":"Transportation"
        }
    ],
    "sg:phone":"+1 740 858 6747",
    "sg:postcode":"45616",
    "sg:province":"OH",
    "sg:tags":[
        "operator",
        "local",
        "trucking"
    ],
    "wof:name":"Weghorst Trucking",
    "wof:placetype":"venue"
},
  "geometry": {"coordinates":[-83.191107,38.719294],"type":"Point"}
}