{
  "type": "Feature",
  "properties": {
    "addr:full": "3508 Brecksville Rd Richfield OH 44286",
    "addr:housenumber": "3508",
    "addr:postcode": "44286",
    "addr:street": "Brecksville Rd",
    "iso:country": "US",
    "sg:address": "3508 Brecksville Rd",
    "sg:city": "Richfield",
    "sg:classifiers": [
      {
        "category": "Building \u0026 Trades",
        "subcategory": "Construction",
        "type": "Services"
      }
    ],
    "sg:phone": "+1 330 659 4030",
    "sg:postcode": "44286",
    "sg:province": "OH",
    "sg:tags": [
      "industrial",
      "installation",
      "machinery"
    ],
    "wof:name": "Align-All Inc",
    "wof:placetype": "venue"
  },
  "geometry": {"coordinates":[-81.637964,41.236223],"type":"Point"}
}
