{
  "type": "Feature",
  "properties": {
    "addr:full":"35909 Lake Shore Blvd Willoughby OH 44095",
    "addr:housenumber":"35909",
    "addr:postcode":"44095",
    "addr:street":"Lake Shore Blvd",
    "iso:country":"US",
    "sg:address":"35909 Lake Shore Blvd",
    "sg:city":"Willoughby",
    "sg:classifiers":[
        {
            "category":"Recreation",
            "subcategory":"Marina",
            "type":"Entertainment"
        }
    ],
    "sg:phone":"+1 440 942 7267",
    "sg:postcode":"44095",
    "sg:province":"OH",
    "wof:name":"East Bank Marina",
    "wof:placetype":"venue"
},
  "geometry": {"coordinates":[-81.42419700000001,41.670228],"type":"Point"}
}