{
  "type": "Feature",
  "properties": {
    "iso:country":"US",
    "sg:address":"4463 Limrick Rd",
    "sg:city":"Springfield",
    "sg:classifiers":[
        {
            "category":"Building & Trades",
            "subcategory":"Plumbing",
            "type":"Services"
        }
    ],
    "sg:phone":"+1 937 265 5205",
    "sg:postcode":"45502",
    "sg:province":"OH",
    "sg:tags":[
        "contractor"
    ],
    "wof:name":"Jl Plumbing",
    "wof:placetype":"venue"
},
  "geometry": {"coordinates":[-83.74783499999999,39.856918],"type":"Point"}
}