{
  "type": "Feature",
  "properties": {
    "addr:full": "4463 Limrick Rd Springfield OH 45502",
    "addr:housenumber": "4463",
    "addr:postcode": "45502",
    "addr:street": "Limrick Rd",
    "iso:country": "US",
    "sg:address": "4463 Limrick Rd",
    "sg:city": "Springfield",
    "sg:classifiers": [
      {
        "category": "Building \u0026 Trades",
        "subcategory": "Plumbing",
        "type": "Services"
      }
    ],
    "sg:phone": "+1 937 265 5205",
    "sg:postcode": "45502",
    "sg:province": "OH",
    "sg:tags": [
      "contractor"
    ],
    "wof:name": "Jl Plumbing",
    "wof:placetype": "venue"
  },
  "geometry": {"coordinates":[-83.747835,39.856918],"type":"Point"}
}
