{
  "type": "Feature",
  "properties": {
    "addr:full":"30 S Mulberry St Mansfield OH 44902",
    "addr:housenumber":"30",
    "addr:postcode":"44902",
    "addr:street":"S Mulberry St",
    "iso:country":"US",
    "sg:address":"30 S Mulberry St",
    "sg:city":"Mansfield",
    "sg:classifiers":[
        {
            "category":"Professional",
            "subcategory":"Lawyer & Legal Services",
            "type":"Services"
        }
    ],
    "sg:phone":"+1 419 524 3608",
    "sg:postcode":"44902",
    "sg:province":"OH",
    "sg:tags":[
        "attorney"
    ],
    "wof:name":"Wilbur H Flippin Jr Co",
    "wof:placetype":"venue"
},
  "geometry": {"coordinates":[-82.518123,40.757724],"type":"Point"}
}