{
  "type": "Feature",
  "properties": {
    "addr:full":"330 Lebanon St Monroe OH 45050",
    "addr:housenumber":"330",
    "addr:postcode":"45050",
    "addr:street":"Lebanon St",
    "iso:country":"US",
    "sg:address":"330 Lebanon St",
    "sg:city":"Monroe",
    "sg:classifiers":[
        {
            "category":"Organizations",
            "subcategory":"Professional Association",
            "type":"Services"
        }
    ],
    "sg:phone":"+1 513 539 2273",
    "sg:postcode":"45050",
    "sg:province":"OH",
    "sg:tags":[
        "elementary",
        "catholic",
        "school"
    ],
    "wof:name":"Mother Thresa Cthlic Elmentary",
    "wof:placetype":"venue"
},
  "geometry": {"coordinates":[-84.357072,39.439987],"type":"Point"}
}