{
  "type": "Feature",
  "properties": {
    "iso:country":"US",
    "sg:address":"3710 Kersdale Pl",
    "sg:city":"Grove City",
    "sg:classifiers":[
        {
            "category":"Utilities",
            "type":"Services"
        }
    ],
    "sg:phone":"+1 614 539 5774",
    "sg:postcode":"43123",
    "sg:province":"OH",
    "sg:tags":[
        "sanitary"
    ],
    "wof:name":"Sweep A Lot Inc",
    "wof:placetype":"venue"
},
  "geometry": {"coordinates":[-83.114048,39.888721],"type":"Point"}
}