{
  "type": "Feature",
  "properties": {
    "addr:full": "26757 Lakevue Dr Perrysburg OH 43551",
    "addr:postcode": "26757;43551",
    "addr:street": "Lakevue Dr",
    "iso:country": "US",
    "sg:address": "26757 Lakevue Dr",
    "sg:city": "Perrysburg",
    "sg:classifiers": [
      {
        "category": "Banks \u0026 Credit Unions",
        "subcategory": "Investment Brokerage",
        "type": "Services"
      }
    ],
    "sg:phone": "+1 419 666 1910",
    "sg:postcode": "43551",
    "sg:province": "OH",
    "sg:tags": [
      "security"
    ],
    "sg:website": "www.edwardjones.com",
    "wof:name": "Edward Jones",
    "wof:placetype": "venue"
  },
  "geometry": {"coordinates":[-83.602491,41.545307],"type":"Point"}
}
