{
  "type": "Feature",
  "properties": {
    "iso:country":"US",
    "sg:address":"179 S River Rd",
    "sg:city":"Waterville",
    "sg:classifiers":[
        {
            "category":"Travel",
            "subcategory":"Travel Agent",
            "type":"Entertainment"
        }
    ],
    "sg:phone":"+1 419 878 7447",
    "sg:postcode":"43566",
    "sg:province":"OH",
    "sg:tags":[
        "cruise"
    ],
    "wof:name":"Cruise Planners Inc",
    "wof:placetype":"venue"
},
  "geometry": {"coordinates":[-83.717966,41.495781],"type":"Point"}
}