{
  "type": "Feature",
  "properties": {
    "iso:country":"US",
    "sg:address":"2901 Tremainsville Rd",
    "sg:city":"Toledo",
    "sg:classifiers":[
        {
            "category":"Real Estate",
            "subcategory":"Real Estate Agent",
            "type":"Services"
        }
    ],
    "sg:phone":"+1 419 578 9900",
    "sg:postcode":"43613",
    "sg:province":"OH",
    "wof:name":"Land Contract Homes",
    "wof:placetype":"venue"
},
  "geometry": {"coordinates":[-83.61510199999999,41.715697],"type":"Point"}
}