{
  "type": "Feature",
  "properties": {
    "addr:full":"1857 Co Rd 24 S De Graff OH 43318",
    "addr:housenumber":"1857;24",
    "addr:postcode":"43318",
    "addr:street":"Co Rd;S",
    "iso:country":"US",
    "sg:address":"1857 Co Rd 24 S",
    "sg:city":"De Graff",
    "sg:classifiers":[
        {
            "category":"Manufacturing",
            "subcategory":"Glass & Minerals",
            "type":"Manufacturing & Wholesale Goods"
        }
    ],
    "sg:phone":"+1 937 585 4971",
    "sg:postcode":"43318",
    "sg:province":"OH",
    "sg:tags":[
        "mfg",
        "burial",
        "product",
        "cut",
        "concrete"
    ],
    "wof:name":"Reames Vaults",
    "wof:placetype":"venue"
},
  "geometry": {"coordinates":[-83.921492,40.320054],"type":"Point"}
}