{
  "type": "Feature",
  "properties": {
    "iso:country":"US",
    "sg:address":"116 S Frank St",
    "sg:city":"Troy",
    "sg:classifiers":[
        {
            "category":"Personal",
            "subcategory":"Beauty Salon",
            "type":"Services"
        }
    ],
    "sg:phone":"+1 937 339 0371",
    "sg:postcode":"45373",
    "sg:province":"OH",
    "wof:name":"Styles By Angela",
    "wof:placetype":"venue"
},
  "geometry": {"coordinates":[-84.196522,40.034254],"type":"Point"}
}