{
  "type": "Feature",
  "properties": {
    "addr:full":"9687 Portage St NW Massillon OH 44646",
    "addr:housenumber":"9687",
    "addr:postcode":"44646",
    "addr:street":"Portage St Nw",
    "iso:country":"US",
    "sg:address":"9687 Portage St NW",
    "sg:city":"Massillon",
    "sg:classifiers":[
        {
            "category":"Social Services",
            "subcategory":"Child Care",
            "type":"Services"
        },
        {
            "category":"Organizations",
            "subcategory":"Religious Organization",
            "type":"Services"
        }
    ],
    "sg:phone":"+1 330 832 2826",
    "sg:postcode":"44646",
    "sg:province":"OH",
    "sg:tags":[
        "day"
    ],
    "sg:website":"www.familyofchristlc.org",
    "wof:name":"Family of Christ Child Care Center",
    "wof:placetype":"venue"
},
  "geometry": {"coordinates":[-81.528801,40.880501],"type":"Point"}
}