{
  "type": "Feature",
  "properties": {
    "addr:full":"10901 Reed Hartman Hwy Cincinnati OH 45242",
    "addr:housenumber":"10901",
    "addr:postcode":"45242",
    "addr:street":"Reed Hartman Hwy",
    "iso:country":"US",
    "sg:address":"10901 Reed Hartman Hwy",
    "sg:city":"Cincinnati",
    "sg:classifiers":[
        {
            "category":"Autos & Motor Vehicles",
            "subcategory":"Auto Supplies",
            "type":"Retail Goods"
        }
    ],
    "sg:phone":"+1 513 794 0038",
    "sg:postcode":"45242",
    "sg:province":"OH",
    "sg:tags":[
        "clutch"
    ],
    "wof:name":"I & C Sales Corp",
    "wof:placetype":"venue"
},
  "geometry": {"coordinates":[-84.380432,39.258751],"type":"Point"}
}