{
  "type": "Feature",
  "properties": {
    "addr:full": "1090 Lizabeth Cir Heath OH 43056",
    "addr:housenumber": "1090",
    "addr:postcode": "43056",
    "addr:street": "Lizabeth Cir",
    "iso:country": "US",
    "sg:address": "1090 Lizabeth Cir",
    "sg:city": "Heath",
    "sg:classifiers": [
      {
        "category": "Wholesale",
        "subcategory": "Electrical",
        "type": "Manufacturing \u0026 Wholesale Goods"
      }
    ],
    "sg:phone": "+1 740 522 0622",
    "sg:postcode": "43056",
    "sg:province": "OH",
    "sg:tags": [
      "alarm",
      "burglar",
      "system"
    ],
    "wof:name": "ADA Security \u0026 Sureillance",
    "wof:placetype": "venue"
  },
  "geometry": {"coordinates":[-82.407004,40.035785],"type":"Point"}
}
