{
  "type": "Feature",
  "properties": {
    "iso:country":"US",
    "sg:address":"1090 Lizabeth Cir",
    "sg:city":"Heath",
    "sg:classifiers":[
        {
            "category":"Wholesale",
            "subcategory":"Electrical",
            "type":"Manufacturing & Wholesale Goods"
        }
    ],
    "sg:phone":"+1 740 522 0622",
    "sg:postcode":"43056",
    "sg:province":"OH",
    "sg:tags":[
        "alarm",
        "burglar",
        "system"
    ],
    "wof:name":"ADA Security & Sureillance",
    "wof:placetype":"venue"
},
  "geometry": {"coordinates":[-82.407004,40.035785],"type":"Point"}
}