{
  "type": "Feature",
  "properties": {
    "iso:country":"US",
    "sg:address":"7438 Montgomery Rd",
    "sg:city":"Cincinnati",
    "sg:classifiers":[
        {
            "category":"Health Services",
            "subcategory":"Doctor",
            "type":"Services"
        }
    ],
    "sg:phone":"+1 513 891 4324",
    "sg:postcode":"45236",
    "sg:province":"OH",
    "sg:tags":[
        "orthodontist"
    ],
    "wof:name":"Fry Chalk DDS Inc",
    "wof:placetype":"venue"
},
  "geometry": {"coordinates":[-84.39532199999999,39.193923],"type":"Point"}
}