{
  "type": "Feature",
  "properties": {
    "addr:full": "1808 Portage Trl Cuyahoga Falls OH 44223",
    "addr:housenumber": "1808",
    "addr:postcode": "44223",
    "addr:street": "Portage Trl",
    "iso:country": "US",
    "sg:address": "1808 Portage Trl",
    "sg:city": "Cuyahoga Falls",
    "sg:classifiers": [
      {
        "category": "Food \u0026 Beverages",
        "subcategory": "Dairy",
        "type": "Retail Goods"
      }
    ],
    "sg:phone": "+1 330 928 1056",
    "sg:postcode": "44223",
    "sg:province": "OH",
    "sg:tags": [
      "product"
    ],
    "wof:name": "P JS Dairy",
    "wof:placetype": "venue"
  },
  "geometry": {"coordinates":[-81.505823,41.147977],"type":"Point"}
}
