{
  "type": "Feature",
  "properties": {
    "iso:country":"US",
    "sg:address":"1808 Portage Trl",
    "sg:city":"Cuyahoga Falls",
    "sg:classifiers":[
        {
            "category":"Food & Beverages",
            "subcategory":"Dairy",
            "type":"Retail Goods"
        }
    ],
    "sg:phone":"+1 330 928 1056",
    "sg:postcode":"44223",
    "sg:province":"OH",
    "sg:tags":[
        "product"
    ],
    "wof:name":"P JS Dairy",
    "wof:placetype":"venue"
},
  "geometry": {"coordinates":[-81.50582300000001,41.147977],"type":"Point"}
}