{
  "type": "Feature",
  "properties": {
    "addr:full": "2207 S Union Ave Alliance OH 44601",
    "addr:housenumber": "2207",
    "addr:postcode": "44601",
    "addr:street": "S Union Ave",
    "iso:country": "US",
    "sg:address": "2207 S Union Ave",
    "sg:city": "Alliance",
    "sg:classifiers": [
      {
        "category": "Professional",
        "subcategory": "Management \u0026 Consulting",
        "type": "Services"
      }
    ],
    "sg:phone": "+1 330 823 2643",
    "sg:postcode": "44601",
    "sg:province": "OH",
    "sg:tags": [
      "retail",
      "direct",
      "sales"
    ],
    "wof:name": "This \u0026 That Merchandise Outlet",
    "wof:placetype": "venue"
  },
  "geometry": {"coordinates":[-81.105968,40.89916],"type":"Point"}
}
