{
  "type": "Feature",
  "properties": {
    "addr:full": "3684 Edgewater Dr St Marys OH 45885",
    "addr:housenumber": "3684",
    "addr:postcode": "45885",
    "addr:street": "Edgewater Dr",
    "iso:country": "US",
    "sg:address": "3684 Edgewater Dr",
    "sg:city": "St Marys",
    "sg:classifiers": [
      {
        "category": "Freight",
        "type": "Transportation"
      }
    ],
    "sg:phone": "+1 419 394 7356",
    "sg:postcode": "45885",
    "sg:province": "OH",
    "sg:tags": [
      "commercial",
      "storage"
    ],
    "wof:name": "Doseck Rentals/St Mary's Self",
    "wof:placetype": "venue"
  },
  "geometry": {"coordinates":[-84.438053,40.549137],"type":"Point"}
}
