{
  "type": "Feature",
  "properties": {
    "iso:country":"US",
    "sg:address":"4949 State Rte 515",
    "sg:city":"Walnut Creek",
    "sg:classifiers":[
        {
            "category":"Travel",
            "subcategory":"Hotels & Motels",
            "type":"Entertainment"
        }
    ],
    "sg:phone":"+1 330 893 3636",
    "sg:postcode":"44654",
    "sg:province":"OH",
    "sg:website":"www.carlislevillageinn.com",
    "wof:name":"Carlisle Village Inn",
    "wof:placetype":"venue"
},
  "geometry": {"coordinates":[-81.72270399999999,40.541603],"type":"Point"}
}