{
  "type": "Feature",
  "properties": {
    "addr:full": "7933 Burgundy Ln Cincinnati OH 45224",
    "addr:housenumber": "7933",
    "addr:postcode": "45224",
    "addr:street": "Burgundy Ln",
    "iso:country": "US",
    "sg:address": "7933 Burgundy Ln",
    "sg:city": "Cincinnati",
    "sg:classifiers": [
      {
        "category": "Shopping",
        "subcategory": "Stationery \u0026 Office Supplies",
        "type": "Retail Goods"
      }
    ],
    "sg:phone": "+1 513 521 8365",
    "sg:postcode": "45224",
    "sg:province": "OH",
    "wof:name": "Accuforms Plus Inc",
    "wof:placetype": "venue"
  },
  "geometry": {"coordinates":[-84.527851,39.214134],"type":"Point"}
}
