{
  "type": "Feature",
  "properties": {
    "iso:country":"US",
    "sg:address":"1 W Corry St",
    "sg:city":"Cincinnati",
    "sg:classifiers":[
        {
            "category":"Wholesale",
            "subcategory":"Machinery & Supplies",
            "type":"Manufacturing & Wholesale Goods"
        }
    ],
    "sg:phone":"+1 513 751 0658",
    "sg:postcode":"45219",
    "sg:province":"OH",
    "sg:tags":[
        "equipment",
        "establishment"
    ],
    "wof:name":"Mainland Beauty Supply",
    "wof:placetype":"venue"
},
  "geometry": {"coordinates":[-84.510514,39.12916],"type":"Point"}
}