{
  "type": "Feature",
  "properties": {
    "addr:full": "1 W Corry St Cincinnati OH 45219",
    "addr:housenumber": "1",
    "addr:postcode": "45219",
    "addr:street": "W Corry St",
    "iso:country": "US",
    "sg:address": "1 W Corry St",
    "sg:city": "Cincinnati",
    "sg:classifiers": [
      {
        "category": "Wholesale",
        "subcategory": "Machinery \u0026 Supplies",
        "type": "Manufacturing \u0026 Wholesale Goods"
      }
    ],
    "sg:phone": "+1 513 751 0658",
    "sg:postcode": "45219",
    "sg:province": "OH",
    "sg:tags": [
      "equipment",
      "establishment"
    ],
    "wof:name": "Mainland Beauty Supply",
    "wof:placetype": "venue"
  },
  "geometry": {"coordinates":[-84.510514,39.12916],"type":"Point"}
}
