{
  "type": "Feature",
  "properties": {
    "addr:full":"1499 State Rte 522 Wheelersburg OH 45694",
    "addr:housenumber":"1499",
    "addr:postcode":"45694",
    "addr:street":"State Rte 522",
    "iso:country":"US",
    "sg:address":"1499 State Rte 522",
    "sg:city":"Wheelersburg",
    "sg:classifiers":[
        {
            "category":"Health Services",
            "subcategory":"Clinic",
            "type":"Services"
        }
    ],
    "sg:phone":"+1 740 574 4242",
    "sg:postcode":"45694",
    "sg:province":"OH",
    "sg:tags":[
        "home"
    ],
    "wof:name":"Country Angels Home Health",
    "wof:placetype":"venue"
},
  "geometry": {"coordinates":[-82.834907,38.70251],"type":"Point"}
}