{
  "type": "Feature",
  "properties": {
    "addr:full":"3403 Chickasaw Ct Sidney OH 45365",
    "addr:housenumber":"3403",
    "addr:postcode":"45365",
    "addr:street":"Chickasaw Ct",
    "iso:country":"US",
    "sg:address":"3403 Chickasaw Ct",
    "sg:city":"Sidney",
    "sg:classifiers":[
        {
            "category":"Organizations",
            "subcategory":"Community Association",
            "type":"Services"
        }
    ],
    "sg:phone":"+1 937 492 9705",
    "sg:postcode":"45365",
    "sg:province":"OH",
    "sg:tags":[
        "civic",
        "social"
    ],
    "wof:name":"Action Motor Sports",
    "wof:placetype":"venue"
},
  "geometry": {"coordinates":[-84.227208,40.249006],"type":"Point"}
}