{
  "type": "Feature",
  "properties": {
    "iso:country":"US",
    "sg:address":"7011 Miami Ave",
    "sg:city":"Cincinnati",
    "sg:classifiers":[
        {
            "category":"Restaurant",
            "type":"Food & Drink"
        }
    ],
    "sg:phone":"+1 513 561 3322",
    "sg:postcode":"45243",
    "sg:province":"OH",
    "sg:tags":[
        "eating"
    ],
    "wof:name":"TCBY",
    "wof:placetype":"venue"
},
  "geometry": {"coordinates":[-84.36332400000001,39.188658],"type":"Point"}
}