{
  "type": "Feature",
  "properties": {
    "addr:full": "7011 Miami Ave Cincinnati OH 45243",
    "addr:housenumber": "7011",
    "addr:postcode": "45243",
    "addr:street": "Miami Ave",
    "iso:country": "US",
    "sg:address": "7011 Miami Ave",
    "sg:city": "Cincinnati",
    "sg:classifiers": [
      {
        "category": "Restaurant",
        "type": "Food \u0026 Drink"
      }
    ],
    "sg:phone": "+1 513 561 3322",
    "sg:postcode": "45243",
    "sg:province": "OH",
    "sg:tags": [
      "eating"
    ],
    "wof:name": "TCBY",
    "wof:placetype": "venue"
  },
  "geometry": {"coordinates":[-84.363324,39.188658],"type":"Point"}
}
