{
  "type": "Feature",
  "properties": {
    "addr:full":"2584 Trailwind St Grove City OH 43123",
    "addr:housenumber":"2584",
    "addr:postcode":"43123",
    "addr:street":"Trailwind St",
    "iso:country":"US",
    "sg:address":"2584 Trailwind St",
    "sg:city":"Grove City",
    "sg:classifiers":[
        {
            "category":"Retail",
            "subcategory":"Repair Shop",
            "type":"Services"
        }
    ],
    "sg:phone":"+1 614 875 8521",
    "sg:postcode":"43123",
    "sg:province":"OH",
    "sg:tags":[
        "repairing",
        "lawn",
        "mower"
    ],
    "wof:name":"Ken's Mower Repair",
    "wof:placetype":"venue"
},
  "geometry": {"coordinates":[-83.044432,39.903415],"type":"Point"}
}