{
  "type": "Feature",
  "properties": {
    "addr:full": "2468 State Rte 54 Urbana OH 43078",
    "addr:housenumber": "2468",
    "addr:postcode": "43078",
    "addr:street": "State Rte 54",
    "iso:country": "US",
    "sg:address": "2468 State Rte 54",
    "sg:city": "Urbana",
    "sg:classifiers": [
      {
        "category": "Education",
        "subcategory": "School",
        "type": "Public Place"
      }
    ],
    "sg:phone": "+1 937 653 1457",
    "sg:postcode": "43078",
    "sg:province": "OH",
    "wof:name": "Schools Public Urbana Cy Schl",
    "wof:placetype": "venue"
  },
  "geometry": {"coordinates":[-83.735414,40.06965],"type":"Point"}
}
