{
  "type": "Feature",
  "properties": {
    "addr:full":"88 Center Rd Cleveland OH 44146",
    "addr:housenumber":"88",
    "addr:postcode":"44146",
    "addr:street":"Center Rd",
    "iso:country":"US",
    "sg:address":"88 Center Rd",
    "sg:city":"Cleveland",
    "sg:classifiers":[
        {
            "category":"Health Services",
            "subcategory":"Doctor",
            "type":"Services"
        }
    ],
    "sg:phone":"+1 440 285 7874",
    "sg:postcode":"44146",
    "sg:province":"OH",
    "sg:tags":[
        "physician",
        "surgeon"
    ],
    "wof:name":"Seung Kwon Lee MD",
    "wof:placetype":"venue"
},
  "geometry": {"coordinates":[-81.536939,41.394711],"type":"Point"}
}