{
  "type": "Feature",
  "properties": {
    "addr:full": "7141 London Groveport Rd Grove City OH 43123",
    "addr:housenumber": "7141",
    "addr:postcode": "43123",
    "addr:street": "London Groveport Rd",
    "iso:country": "US",
    "sg:address": "7141 London Groveport Rd",
    "sg:city": "Grove City",
    "sg:classifiers": [
      {
        "category": "Recreation",
        "type": "Entertainment"
      }
    ],
    "sg:phone": "+1 614 877 4321",
    "sg:postcode": "43123",
    "sg:province": "OH",
    "sg:tags": [
      "charter",
      "canoe"
    ],
    "wof:name": "Trapper John's Canoe Livery",
    "wof:placetype": "venue"
  },
  "geometry": {"coordinates":[-83.189423,39.85131],"type":"Point"}
}
