{
  "type": "Feature",
  "properties": {
    "addr:full": "5547 Lansbury Ln Cleveland OH 44124",
    "addr:housenumber": "5547",
    "addr:postcode": "44124",
    "addr:street": "Lansbury Ln",
    "iso:country": "US",
    "sg:address": "5547 Lansbury Ln",
    "sg:city": "Cleveland",
    "sg:classifiers": [
      {
        "category": "Insurance",
        "subcategory": "Insurance Agent",
        "type": "Services"
      }
    ],
    "sg:phone": "+1 440 461 9434",
    "sg:postcode": "44124",
    "sg:province": "OH",
    "wof:name": "Graubard Group Inc",
    "wof:placetype": "venue"
  },
  "geometry": {"coordinates":[-81.480202,41.506016],"type":"Point"}
}
