{
  "type": "Feature",
  "properties": {
    "addr:full":"3204 Eastport Rd SE Dennison OH 44621",
    "addr:housenumber":"3204",
    "addr:postcode":"44621",
    "addr:street":"Eastport Rd Se",
    "iso:country":"US",
    "sg:address":"3204 Eastport Rd SE",
    "sg:city":"Dennison",
    "sg:classifiers":[
        {
            "category":"Manufacturing",
            "subcategory":"Tools & Machinery",
            "type":"Manufacturing & Wholesale Goods"
        }
    ],
    "sg:phone":"+1 740 922 7036",
    "sg:postcode":"44621",
    "sg:province":"OH",
    "sg:tags":[
        "industrial",
        "electrical",
        "apparatus",
        "mfg"
    ],
    "wof:name":"Charlton Electronics",
    "wof:placetype":"venue"
},
  "geometry": {"coordinates":[-81.349343,40.420243],"type":"Point"}
}