{
  "type": "Feature",
  "properties": {
    "iso:country":"US",
    "sg:address":"9483 Falcon Tract",
    "sg:city":"Warren",
    "sg:classifiers":[
        {
            "category":"Professional",
            "subcategory":"Business Services",
            "type":"Services"
        }
    ],
    "sg:phone":"+1 330 609 5082",
    "sg:postcode":"44484",
    "sg:province":"OH",
    "sg:tags":[
        "appraiser"
    ],
    "wof:name":"Northeastern Ohio Appraisal",
    "wof:placetype":"venue"
},
  "geometry": {"coordinates":[-80.71975399999999,41.253816],"type":"Point"}
}