{
  "type": "Feature",
  "properties": {
    "iso:country":"US",
    "sg:address":"2323 Citygate Dr",
    "sg:city":"Columbus",
    "sg:classifiers":[
        {
            "category":"Banks & Credit Unions",
            "subcategory":"Bank",
            "type":"Services"
        }
    ],
    "sg:phone":"+1 614 337 1475",
    "sg:postcode":"43219",
    "sg:province":"OH",
    "wof:name":"Columbus Postal Employee's CU",
    "wof:placetype":"venue"
},
  "geometry": {"coordinates":[-82.921531,40.02014],"type":"Point"}
}