{
  "type": "Feature",
  "properties": {
    "addr:full": "2323 Citygate Dr Columbus OH 43219",
    "addr:postcode": "2323;43219",
    "addr:street": "Citygate Dr",
    "iso:country": "US",
    "sg:address": "2323 Citygate Dr",
    "sg:city": "Columbus",
    "sg:classifiers": [
      {
        "category": "Banks \u0026 Credit Unions",
        "subcategory": "Bank",
        "type": "Services"
      }
    ],
    "sg:phone": "+1 614 337 1475",
    "sg:postcode": "43219",
    "sg:province": "OH",
    "wof:name": "Columbus Postal Employee's CU",
    "wof:placetype": "venue"
  },
  "geometry": {"coordinates":[-82.921531,40.02014],"type":"Point"}
}
