{
  "type": "Feature",
  "properties": {
    "addr:full": "3818 Thunderbird Cir NW North Canton OH 44720",
    "addr:housenumber": "3818",
    "addr:postcode": "44720",
    "addr:street": "Thunderbird Cir Nw",
    "iso:country": "US",
    "sg:address": "3818 Thunderbird Cir NW",
    "sg:city": "North Canton",
    "sg:classifiers": [
      {
        "category": "Building \u0026 Trades",
        "subcategory": "Construction",
        "type": "Services"
      }
    ],
    "sg:phone": "+1 330 497 9290",
    "sg:postcode": "44720",
    "sg:province": "OH",
    "sg:tags": [
      "home",
      "builder"
    ],
    "wof:name": "Benko Signature Builders Inc",
    "wof:placetype": "venue"
  },
  "geometry": {"coordinates":[-81.417974,40.862295],"type":"Point"}
}
