{
  "type": "Feature",
  "properties": {
    "addr:full": "75 State Rte 66 Archbold OH 43502",
    "addr:housenumber": "75",
    "addr:postcode": "43502",
    "addr:street": "State Rte 66",
    "iso:country": "US",
    "sg:address": "75 State Rte 66",
    "sg:city": "Archbold",
    "sg:classifiers": [
      {
        "category": "Manufacturing",
        "subcategory": "Tools \u0026 Machinery",
        "type": "Manufacturing \u0026 Wholesale Goods"
      }
    ],
    "sg:phone": "+1 419 267 5687",
    "sg:postcode": "43502",
    "sg:province": "OH",
    "sg:tags": [
      "equipment",
      "system",
      "automation"
    ],
    "sg:website": "www.tjautomation.com",
    "wof:name": "T J Automation",
    "wof:placetype": "venue"
  },
  "geometry": {"coordinates":[-84.305911,41.474633],"type":"Point"}
}
