{
  "type": "Feature",
  "properties": {
    "addr:full": "245 Elmwood Dr Dayton OH 45459",
    "addr:housenumber": "245",
    "addr:postcode": "45459",
    "addr:street": "Elmwood Dr",
    "iso:country": "US",
    "sg:address": "245 Elmwood Dr",
    "sg:city": "Dayton",
    "sg:classifiers": [
      {
        "category": "Health Services",
        "subcategory": "Doctor",
        "type": "Services"
      }
    ],
    "sg:phone": "+1 937 312 9693",
    "sg:postcode": "45459",
    "sg:province": "OH",
    "sg:tags": [
      "physician",
      "surgeon"
    ],
    "wof:name": "DCR Surgery Ctr",
    "wof:placetype": "venue"
  },
  "geometry": {"coordinates":[-84.152798,39.637184],"type":"Point"}
}
