{
  "type": "Feature",
  "properties": {
    "addr:full":"5410 Dixie Hwy Fairfield OH 45014",
    "addr:housenumber":"5410",
    "addr:postcode":"45014",
    "addr:street":"Dixie Hwy",
    "iso:country":"US",
    "sg:address":"5410 Dixie Hwy",
    "sg:city":"Fairfield",
    "sg:classifiers":[
        {
            "category":"Professional",
            "type":"Services"
        }
    ],
    "sg:phone":"+1 513 939 2222",
    "sg:postcode":"45014",
    "sg:province":"OH",
    "sg:tags":[
        "establishment"
    ],
    "wof:name":"Caseys Residential Coml Clning",
    "wof:placetype":"venue"
},
  "geometry": {"coordinates":[-84.524001,39.333931],"type":"Point"}
}