{
  "type": "Feature",
  "properties": {
    "iso:country":"US",
    "sg:address":"151 S 4th St",
    "sg:city":"Steubenville",
    "sg:classifiers":[
        {
            "category":"Food & Beverages",
            "subcategory":"Bakery",
            "type":"Retail Goods"
        }
    ],
    "sg:phone":"+1 740 283 1138",
    "sg:postcode":"43952",
    "sg:province":"OH",
    "wof:name":"Downtown Bakery",
    "wof:placetype":"venue"
},
  "geometry": {"coordinates":[-80.61573300000001,40.359205],"type":"Point"}
}