{
  "type": "Feature",
  "properties": {
    "addr:full": "151 S 4th St Steubenville OH 43952",
    "addr:housenumber": "151",
    "addr:postcode": "43952",
    "addr:street": "S 4Th St",
    "iso:country": "US",
    "sg:address": "151 S 4th St",
    "sg:city": "Steubenville",
    "sg:classifiers": [
      {
        "category": "Food \u0026 Beverages",
        "subcategory": "Bakery",
        "type": "Retail Goods"
      }
    ],
    "sg:phone": "+1 740 283 1138",
    "sg:postcode": "43952",
    "sg:province": "OH",
    "wof:name": "Downtown Bakery",
    "wof:placetype": "venue"
  },
  "geometry": {"coordinates":[-80.615733,40.359205],"type":"Point"}
}
