{
  "type": "Feature",
  "properties": {
    "addr:full": "6197 Waynesburg Dr SE Waynesburg OH 44688",
    "addr:housenumber": "6197",
    "addr:postcode": "44688",
    "addr:street": "Waynesburg Dr Se",
    "iso:country": "US",
    "sg:address": "6197 Waynesburg Dr SE",
    "sg:city": "Waynesburg",
    "sg:classifiers": [
      {
        "category": "Retail",
        "subcategory": "Animal Services",
        "type": "Services"
      }
    ],
    "sg:phone": "+1 330 866 1178",
    "sg:postcode": "44688",
    "sg:province": "OH",
    "sg:tags": [
      "pet",
      "boarding",
      "sitting"
    ],
    "wof:name": "Carla's Critter Care",
    "wof:placetype": "venue"
  },
  "geometry": {"coordinates":[-81.277652,40.711817],"type":"Point"}
}
