{
  "type": "Feature",
  "properties": {
    "addr:full": "1174 Deblin Dr Milford OH 45150",
    "addr:housenumber": "1174",
    "addr:postcode": "45150",
    "addr:street": "Deblin Dr",
    "iso:country": "US",
    "sg:address": "1174 Deblin Dr",
    "sg:city": "Milford",
    "sg:classifiers": [
      {
        "category": "Professional",
        "type": "Services"
      }
    ],
    "sg:phone": "+1 513 831 3748",
    "sg:postcode": "45150",
    "sg:province": "OH",
    "wof:name": "Phyllis G Jarrell",
    "wof:placetype": "venue"
  },
  "geometry": {"coordinates":[-84.230736,39.184418],"type":"Point"}
}
