{
  "type": "Feature",
  "properties": {
    "addr:full": "1701 W Dorothy Ln Dayton OH 45409",
    "addr:housenumber": "1701",
    "addr:postcode": "45409",
    "addr:street": "W Dorothy Ln",
    "iso:country": "US",
    "sg:address": "1701 W Dorothy Ln",
    "sg:city": "Dayton",
    "sg:classifiers": [
      {
        "category": "Manufacturing",
        "subcategory": "Food",
        "type": "Manufacturing \u0026 Wholesale Goods"
      },
      {
        "category": "Wholesale",
        "subcategory": "Groceries",
        "type": "Manufacturing \u0026 Wholesale Goods"
      }
    ],
    "sg:phone": "+1 937 298 7655",
    "sg:postcode": "45409",
    "sg:province": "OH",
    "sg:tags": [
      "pretzel",
      "mfg"
    ],
    "wof:name": "We'Re Rolling Pretzel",
    "wof:placetype": "venue"
  },
  "geometry": {"coordinates":[-84.202283,39.708821],"type":"Point"}
}
