{
  "type": "Feature",
  "properties": {
    "iso:country":"US",
    "sg:address":"1701 W Dorothy Ln",
    "sg:city":"Dayton",
    "sg:classifiers":[
        {
            "category":"Manufacturing",
            "subcategory":"Food",
            "type":"Manufacturing & Wholesale Goods"
        },
        {
            "category":"Wholesale",
            "subcategory":"Groceries",
            "type":"Manufacturing & Wholesale Goods"
        }
    ],
    "sg:phone":"+1 937 298 7655",
    "sg:postcode":"45409",
    "sg:province":"OH",
    "sg:tags":[
        "pretzel",
        "mfg"
    ],
    "wof:name":"We'Re Rolling Pretzel",
    "wof:placetype":"venue"
},
  "geometry": {"coordinates":[-84.20228299999999,39.708821],"type":"Point"}
}