{
  "type": "Feature",
  "properties": {
    "iso:country":"US",
    "sg:address":"214 Sentry Hill Dr",
    "sg:city":"Loveland",
    "sg:classifiers":[
        {
            "category":"Professional",
            "subcategory":"Advertising",
            "type":"Services"
        }
    ],
    "sg:phone":"+1 513 792 0077",
    "sg:postcode":"45140",
    "sg:province":"OH",
    "sg:tags":[
        "agency"
    ],
    "wof:name":"Driven Images LLC",
    "wof:placetype":"venue"
},
  "geometry": {"coordinates":[-84.250665,39.272323],"type":"Point"}
}