{
  "type": "Feature",
  "properties": {
    "iso:country":"US",
    "sg:address":"335 S Main St",
    "sg:city":"Delphos",
    "sg:classifiers":[
        {
            "category":"Organizations",
            "subcategory":"Religious Organization",
            "type":"Services"
        }
    ],
    "sg:phone":"+1 419 692 9526",
    "sg:postcode":"45833",
    "sg:province":"OH",
    "sg:tags":[
        "church"
    ],
    "wof:name":"St Paul United Methodist Chr",
    "wof:placetype":"venue"
},
  "geometry": {"coordinates":[-84.33976,40.839934],"type":"Point"}
}