{
  "type": "Feature",
  "properties": {
    "iso:country":"US",
    "sg:address":"5945 Trojan St NE",
    "sg:city":"Louisville",
    "sg:classifiers":[
        {
            "category":"Travel",
            "subcategory":"Travel Agent",
            "type":"Entertainment"
        }
    ],
    "sg:phone":"+1 330 875 3000",
    "sg:postcode":"44641",
    "sg:province":"OH",
    "sg:tags":[
        "bureau",
        "passenger",
        "agency",
        "transportation",
        "arrangement"
    ],
    "sg:website":"www.letstalktravel.net",
    "wof:name":"Let's Talk Travel Inc",
    "wof:placetype":"venue"
},
  "geometry": {"coordinates":[-81.25718000000001,40.860806],"type":"Point"}
}