{
  "type": "Feature",
  "properties": {
    "iso:country":"US",
    "sg:address":"19540 Progress Dr",
    "sg:city":"Strongsville",
    "sg:classifiers":[
        {
            "category":"Manufacturing",
            "subcategory":"Printing",
            "type":"Manufacturing & Wholesale Goods"
        }
    ],
    "sg:phone":"+1 440 238 3318",
    "sg:postcode":"44149",
    "sg:province":"OH",
    "sg:tags":[
        "printer"
    ],
    "wof:name":"Acorn Graphics",
    "wof:placetype":"venue"
},
  "geometry": {"coordinates":[-81.837153,41.326862],"type":"Point"}
}