{
  "type": "Feature",
  "properties": {
    "iso:country":"US",
    "sg:address":"135 N Chestnut St",
    "sg:city":"Jefferson",
    "sg:classifiers":[
        {
            "category":"Restaurant",
            "type":"Food & Drink"
        }
    ],
    "sg:phone":"+1 440 576 3004",
    "sg:postcode":"44047",
    "sg:province":"OH",
    "sg:tags":[
        "eating"
    ],
    "wof:name":"Subway",
    "wof:placetype":"venue"
},
  "geometry": {"coordinates":[-80.769538,41.741686],"type":"Point"}
}