{
  "type": "Feature",
  "properties": {
    "addr:full":"24400 Twp Hwy 1169 Coshocton OH 43812",
    "addr:postcode":"24400;1169;43812",
    "addr:street":"Twp Hwy",
    "iso:country":"US",
    "sg:address":"24400 Twp Hwy 1169",
    "sg:city":"Coshocton",
    "sg:classifiers":[
        {
            "category":"Shopping",
            "subcategory":"Bicycles & Sporting Goods",
            "type":"Retail Goods"
        }
    ],
    "sg:phone":"+1 740 622 4446",
    "sg:postcode":"43812",
    "sg:province":"OH",
    "wof:name":"Savy S Tackle",
    "wof:placetype":"venue"
},
  "geometry": {"coordinates":[-81.892263,40.308217],"type":"Point"}
}