{
  "type": "Feature",
  "properties": {
    "iso:country":"US",
    "sg:address":"5901 Harrison Ave",
    "sg:city":"Cincinnati",
    "sg:classifiers":[
        {
            "category":"Wholesale",
            "subcategory":"Auto Parts",
            "type":"Manufacturing & Wholesale Goods"
        }
    ],
    "sg:phone":"+1 513 574 6603",
    "sg:postcode":"45248",
    "sg:province":"OH",
    "sg:tags":[
        "used"
    ],
    "wof:name":"Nickoson Auto Parts",
    "wof:placetype":"venue"
},
  "geometry": {"coordinates":[-84.643656,39.175995],"type":"Point"}
}