{
  "type": "Feature",
  "properties": {
    "addr:full": "890 N Canfield Niles Rd Youngstown OH 44515",
    "addr:housenumber": "890",
    "addr:postcode": "44515",
    "addr:street": "N Canfield Niles Rd",
    "iso:country": "US",
    "sg:address": "890 N Canfield Niles Rd",
    "sg:city": "Youngstown",
    "sg:classifiers": [
      {
        "category": "Autos \u0026 Motor Vehicles",
        "subcategory": "Fuel \u0026 Gas Station",
        "type": "Retail Goods"
      }
    ],
    "sg:phone": "+1 330 652 6850",
    "sg:postcode": "44515",
    "sg:province": "OH",
    "sg:tags": [
      "oil"
    ],
    "wof:name": "Bp Oil",
    "wof:placetype": "venue"
  },
  "geometry": {"coordinates":[-80.768225,41.122968],"type":"Point"}
}
