{
  "type": "Feature",
  "properties": {
    "addr:full": "120 E Mill St Akron OH 44308",
    "addr:housenumber": "120",
    "addr:postcode": "44308",
    "addr:street": "E Mill St",
    "iso:country": "US",
    "sg:address": "120 E Mill St",
    "sg:city": "Akron",
    "sg:classifiers": [
      {
        "category": "Organizations",
        "subcategory": "Non-profit Organization",
        "type": "Services"
      }
    ],
    "sg:phone": "+1 330 374 9445",
    "sg:postcode": "44308",
    "sg:province": "OH",
    "wof:name": "Tri County Jog",
    "wof:placetype": "venue"
  },
  "geometry": {"coordinates":[-81.515318,41.08185],"type":"Point"}
}
