{
  "type": "Feature",
  "properties": {
    "iso:country":"US",
    "sg:address":"25800 Hilliard Blvd",
    "sg:city":"Cleveland",
    "sg:classifiers":[
        {
            "category":"Organizations",
            "subcategory":"Religious Organization",
            "type":"Services"
        }
    ],
    "sg:phone":"+1 440 871 2400",
    "sg:postcode":"44145",
    "sg:province":"OH",
    "sg:tags":[
        "church"
    ],
    "sg:website":"www.westlakechristianchurch.com",
    "wof:name":"Westlake Christian Church",
    "wof:placetype":"venue"
},
  "geometry": {"coordinates":[-81.90818299999999,41.462491],"type":"Point"}
}