{
  "type": "Feature",
  "properties": {
    "addr:full": "150 E Wilson Bridge Rd Columbus OH 43085",
    "addr:housenumber": "150",
    "addr:postcode": "43085",
    "addr:street": "E Wilson Bridge Rd",
    "iso:country": "US",
    "sg:address": "150 E Wilson Bridge Rd",
    "sg:city": "Columbus",
    "sg:classifiers": [
      {
        "category": "Banks \u0026 Credit Unions",
        "subcategory": "Bank",
        "type": "Services"
      }
    ],
    "sg:phone": "+1 614 431 1141",
    "sg:postcode": "43085",
    "sg:province": "OH",
    "sg:tags": [
      "originator",
      "mortgage",
      "residential",
      "loan",
      "real estate"
    ],
    "wof:name": "Priority Mortgage Corp",
    "wof:placetype": "venue"
  },
  "geometry": {"coordinates":[-83.007259,40.109505],"type":"Point"}
}
