{
  "type": "Feature",
  "properties": {
    "iso:country":"US",
    "sg:address":"165 E 15th Ave",
    "sg:city":"Columbus",
    "sg:classifiers":[
        {
            "category":"Organizations",
            "subcategory":"Community Association",
            "type":"Services"
        }
    ],
    "sg:phone":"+1 614 294 9380",
    "sg:postcode":"43201",
    "sg:province":"OH",
    "sg:tags":[
        "sorority",
        "fraternity"
    ],
    "wof:name":"Beta Theta Pi Fraternity",
    "wof:placetype":"venue"
},
  "geometry": {"coordinates":[-83.001447,39.999652],"type":"Point"}
}