{
  "type": "Feature",
  "properties": {
    "addr:full":"12 E Columbia Ave Cincinnati OH 45215",
    "addr:housenumber":"12",
    "addr:postcode":"45215",
    "addr:street":"E Columbia Ave",
    "iso:country":"US",
    "sg:address":"12 E Columbia Ave",
    "sg:city":"Cincinnati",
    "sg:classifiers":[
        {
            "category":"Restaurant",
            "type":"Food & Drink"
        }
    ],
    "sg:phone":"+1 513 769 1777",
    "sg:postcode":"45215",
    "sg:province":"OH",
    "sg:tags":[
        "eating"
    ],
    "wof:name":"Blue Devils Diner",
    "wof:placetype":"venue"
},
  "geometry": {"coordinates":[-84.437696,39.227404],"type":"Point"}
}