{
  "type": "Feature",
  "properties": {
    "addr:full":"11260 Rapp Rd New Middletown OH 44442",
    "addr:postcode":"11260;44442",
    "addr:street":"Rapp Rd",
    "iso:country":"US",
    "sg:address":"11260 Rapp Rd",
    "sg:city":"New Middletown",
    "sg:phone":"+1 330 542 9950",
    "sg:postcode":"44442",
    "sg:province":"OH",
    "sg:tags":[
        "farm",
        "field",
        "corn",
        "wheat",
        "crop"
    ],
    "wof:name":"Green Acres",
    "wof:placetype":"venue"
},
  "geometry": {"coordinates":[-80.53830600000001,40.957797],"type":"Point"}
}