{
  "type": "Feature",
  "properties": {
    "iso:country":"US",
    "sg:address":"230 Northland Blvd",
    "sg:city":"Cincinnati",
    "sg:classifiers":[
        {
            "category":"Freight",
            "type":"Transportation"
        }
    ],
    "sg:phone":"+1 513 305 9004",
    "sg:postcode":"45246",
    "sg:province":"OH",
    "sg:tags":[
        "trucking"
    ],
    "wof:name":"Broyles Transport Express LLC",
    "wof:placetype":"venue"
},
  "geometry": {"coordinates":[-84.481279,39.282735],"type":"Point"}
}