{
  "type": "Feature",
  "properties": {
    "iso:country":"US",
    "sg:address":"10026 Elton St SW",
    "sg:city":"Navarre",
    "sg:classifiers":[
        {
            "category":"Manufacturing",
            "subcategory":"Tools & Machinery",
            "type":"Manufacturing & Wholesale Goods"
        }
    ],
    "sg:phone":"+1 330 879 2065",
    "sg:postcode":"44662",
    "sg:province":"OH",
    "sg:tags":[
        "conductive",
        "wiring",
        "devices",
        "mfg"
    ],
    "wof:name":"Hofacrelightning System",
    "wof:placetype":"venue"
},
  "geometry": {"coordinates":[-81.53908300000001,40.725005],"type":"Point"}
}