{
  "type": "Feature",
  "properties": {
    "addr:full": "10026 Elton St SW Navarre OH 44662",
    "addr:housenumber": "10026",
    "addr:postcode": "44662",
    "addr:street": "Elton St Sw",
    "iso:country": "US",
    "sg:address": "10026 Elton St SW",
    "sg:city": "Navarre",
    "sg:classifiers": [
      {
        "category": "Manufacturing",
        "subcategory": "Tools \u0026 Machinery",
        "type": "Manufacturing \u0026 Wholesale Goods"
      }
    ],
    "sg:phone": "+1 330 879 2065",
    "sg:postcode": "44662",
    "sg:province": "OH",
    "sg:tags": [
      "conductive",
      "wiring",
      "devices",
      "mfg"
    ],
    "wof:name": "Hofacrelightning System",
    "wof:placetype": "venue"
  },
  "geometry": {"coordinates":[-81.539083,40.725005],"type":"Point"}
}
