{
  "type": "Feature",
  "properties": {
    "addr:full": "5304 Blossom St Hamilton OH 45011",
    "addr:housenumber": "5304",
    "addr:postcode": "45011",
    "addr:street": "Blossom St",
    "iso:country": "US",
    "sg:address": "5304 Blossom St",
    "sg:city": "Hamilton",
    "sg:classifiers": [
      {
        "category": "Autos \u0026 Motor Vehicles",
        "subcategory": "Auto Supplies",
        "type": "Retail Goods"
      }
    ],
    "sg:phone": "+1 513 478 4706",
    "sg:postcode": "45011",
    "sg:province": "OH",
    "sg:tags": [
      "automobile",
      "parts"
    ],
    "wof:name": "Eric Heid Automotive",
    "wof:placetype": "venue"
  },
  "geometry": {"coordinates":[-84.448163,39.316905],"type":"Point"}
}
