{
  "type": "Feature",
  "properties": {
    "iso:country":"US",
    "sg:address":"5304 Blossom St",
    "sg:city":"Hamilton",
    "sg:classifiers":[
        {
            "category":"Autos & Motor Vehicles",
            "subcategory":"Auto Supplies",
            "type":"Retail Goods"
        }
    ],
    "sg:phone":"+1 513 478 4706",
    "sg:postcode":"45011",
    "sg:province":"OH",
    "sg:tags":[
        "automobile",
        "parts"
    ],
    "wof:name":"Eric Heid Automotive",
    "wof:placetype":"venue"
},
  "geometry": {"coordinates":[-84.448163,39.316905],"type":"Point"}
}