{
  "type": "Feature",
  "properties": {
    "iso:country":"US",
    "sg:address":"4141 Colonel Glenn Hwy",
    "sg:city":"Dayton",
    "sg:classifiers":[
        {
            "category":"Education",
            "subcategory":"Special Training",
            "type":"Public Place"
        }
    ],
    "sg:phone":"+1 937 427 4360",
    "sg:postcode":"45431",
    "sg:province":"OH",
    "sg:tags":[
        "program"
    ],
    "wof:name":"Upper Mohawk Inc",
    "wof:placetype":"venue"
},
  "geometry": {"coordinates":[-84.08757799999999,39.773348],"type":"Point"}
}