{
  "type": "Feature",
  "properties": {
    "iso:country":"US",
    "sg:address":"1789 N Bailey Rd",
    "sg:city":"Warren",
    "sg:classifiers":[
        {
            "category":"Manufacturing",
            "subcategory":"Rubber & Plastics",
            "type":"Manufacturing & Wholesale Goods"
        }
    ],
    "sg:phone":"+1 330 675 4400",
    "sg:postcode":"44451",
    "sg:province":"OH",
    "sg:tags":[
        "building",
        "product",
        "furniture",
        "public",
        "mfg"
    ],
    "wof:name":"Lear Corporation",
    "wof:placetype":"venue"
},
  "geometry": {"coordinates":[-80.88724000000001,41.116956],"type":"Point"}
}