{
  "type": "Feature",
  "properties": {
    "addr:full": "1789 N Bailey Rd Warren OH 44451",
    "addr:housenumber": "1789",
    "addr:postcode": "44451",
    "addr:street": "N Bailey Rd",
    "iso:country": "US",
    "sg:address": "1789 N Bailey Rd",
    "sg:city": "Warren",
    "sg:classifiers": [
      {
        "category": "Manufacturing",
        "subcategory": "Rubber \u0026 Plastics",
        "type": "Manufacturing \u0026 Wholesale Goods"
      }
    ],
    "sg:phone": "+1 330 675 4400",
    "sg:postcode": "44451",
    "sg:province": "OH",
    "sg:tags": [
      "building",
      "product",
      "furniture",
      "public",
      "mfg"
    ],
    "wof:name": "Lear Corporation",
    "wof:placetype": "venue"
  },
  "geometry": {"coordinates":[-80.88724,41.116956],"type":"Point"}
}
