{
  "type": "Feature",
  "properties": {
    "addr:full": "1324 Betana Ave Akron OH 44310",
    "addr:housenumber": "1324",
    "addr:postcode": "44310",
    "addr:street": "Betana Ave",
    "iso:country": "US",
    "sg:address": "1324 Betana Ave",
    "sg:city": "Akron",
    "sg:classifiers": [
      {
        "category": "Autos \u0026 Motor Vehicles",
        "subcategory": "Auto Supplies",
        "type": "Retail Goods"
      }
    ],
    "sg:phone": "+1 330 630 2356",
    "sg:postcode": "44310",
    "sg:province": "OH",
    "wof:name": "Copley Circle Auto Parts Co",
    "wof:placetype": "venue"
  },
  "geometry": {"coordinates":[-81.472974,41.10612],"type":"Point"}
}
