{
  "type": "Feature",
  "properties": {
    "iso:country":"US",
    "sg:address":"1324 Betana Ave",
    "sg:city":"Akron",
    "sg:classifiers":[
        {
            "category":"Autos & Motor Vehicles",
            "subcategory":"Auto Supplies",
            "type":"Retail Goods"
        }
    ],
    "sg:phone":"+1 330 630 2356",
    "sg:postcode":"44310",
    "sg:province":"OH",
    "wof:name":"Copley Circle Auto Parts Co",
    "wof:placetype":"venue"
},
  "geometry": {"coordinates":[-81.47297399999999,41.10612],"type":"Point"}
}