{
  "type": "Feature",
  "properties": {
    "addr:full": "2300 Ferguson Rd Cincinnati OH 45238",
    "addr:housenumber": "2300",
    "addr:postcode": "45238",
    "addr:street": "Ferguson Rd",
    "iso:country": "US",
    "sg:address": "2300 Ferguson Rd",
    "sg:city": "Cincinnati",
    "sg:classifiers": [
      {
        "category": "Autos \u0026 Motor Vehicles",
        "subcategory": "Automobile Sales",
        "type": "Retail Goods"
      }
    ],
    "sg:phone": "+1 513 922 1400",
    "sg:postcode": "45238",
    "sg:province": "OH",
    "sg:tags": [
      "used"
    ],
    "wof:name": "SD Pontiac GMC",
    "wof:placetype": "venue"
  },
  "geometry": {"coordinates":[-84.600905,39.128091],"type":"Point"}
}
