{
  "type": "Feature",
  "properties": {
    "iso:country":"US",
    "sg:address":"521 Bell Rd",
    "sg:city":"Wooster",
    "sg:classifiers":[
        {
            "category":"Social Services",
            "type":"Services"
        }
    ],
    "sg:phone":"+1 330 262 7836",
    "sg:postcode":"44691",
    "sg:province":"OH",
    "sg:tags":[
        "counseling",
        "family"
    ],
    "wof:name":"Catholic Charities Svcs Corp",
    "wof:placetype":"venue"
},
  "geometry": {"coordinates":[-82.127208,40.801835],"type":"Point"}
}