{
  "type": "Feature",
  "properties": {
    "iso:country":"US",
    "sg:address":"5002 Pershing Ave",
    "sg:city":"Cleveland",
    "sg:classifiers":[
        {
            "category":"Professional",
            "subcategory":"Business Services",
            "type":"Services"
        }
    ],
    "sg:phone":"+1 440 886 5772",
    "sg:postcode":"44134",
    "sg:province":"OH",
    "sg:tags":[
        "appraiser"
    ],
    "wof:name":"Central Appraisal Svc",
    "wof:placetype":"venue"
},
  "geometry": {"coordinates":[-81.721762,41.409542],"type":"Point"}
}