{
  "type": "Feature",
  "properties": {
    "addr:full":"5800 Monroe St Sylvania OH 43560",
    "addr:housenumber":"5800",
    "addr:postcode":"43560",
    "addr:street":"Monroe St",
    "iso:country":"US",
    "sg:address":"5800 Monroe St",
    "sg:city":"Sylvania",
    "sg:classifiers":[
        {
            "category":"Professional",
            "subcategory":"Lawyer & Legal Services",
            "type":"Services"
        }
    ],
    "sg:phone":"+1 419 882 1144",
    "sg:postcode":"43560",
    "sg:province":"OH",
    "sg:tags":[
        "attorney"
    ],
    "wof:name":"Theodore Gersz",
    "wof:placetype":"venue"
},
  "geometry": {"coordinates":[-83.68465399999999,41.714327],"type":"Point"}
}