{
  "type": "Feature",
  "properties": {
    "addr:full":"13706 Madison Ave Cleveland OH 44107",
    "addr:housenumber":"13706",
    "addr:postcode":"44107",
    "addr:street":"Madison Ave",
    "iso:country":"US",
    "sg:address":"13706 Madison Ave",
    "sg:city":"Cleveland",
    "sg:classifiers":[
        {
            "category":"Personal",
            "subcategory":"Barber",
            "type":"Services"
        }
    ],
    "sg:phone":"+1 216 221 8026",
    "sg:postcode":"44107",
    "sg:province":"OH",
    "wof:name":"Wink's Barber Shop",
    "wof:placetype":"venue"
},
  "geometry": {"coordinates":[-81.788177,41.477142],"type":"Point"}
}