{
  "type": "Feature",
  "properties": {
    "iso:country":"US",
    "sg:address":"12160 Montgomery Rd",
    "sg:city":"Cincinnati",
    "sg:classifiers":[
        {
            "category":"Health Services",
            "subcategory":"Doctor",
            "type":"Services"
        }
    ],
    "sg:phone":"+1 513 697 4300",
    "sg:postcode":"45249",
    "sg:province":"OH",
    "sg:tags":[
        "dentist"
    ],
    "wof:name":"Family Dental Care Assoc Mason",
    "wof:placetype":"venue"
},
  "geometry": {"coordinates":[-84.301616,39.288943],"type":"Point"}
}