{
  "type": "Feature",
  "properties": {
    "iso:country":"US",
    "sg:address":"1945 Cumberland St",
    "sg:city":"London",
    "sg:classifiers":[
        {
            "category":"Government",
            "subcategory":"Office",
            "type":"Public Place"
        }
    ],
    "sg:phone":"+1 740 852 5872",
    "sg:postcode":"43140",
    "sg:province":"OH",
    "sg:tags":[
        "legislative",
        "body"
    ],
    "wof:name":"Deercreek Township",
    "wof:placetype":"venue"
},
  "geometry": {"coordinates":[-83.404421,39.937726],"type":"Point"}
}