{
  "type": "Feature",
  "properties": {
    "addr:full": "8225 Worthington Galena Rd Westerville OH 43081",
    "addr:housenumber": "8225",
    "addr:postcode": "43081",
    "addr:street": "Worthington Galena Rd",
    "iso:country": "US",
    "sg:address": "8225 Worthington Galena Rd",
    "sg:city": "Westerville",
    "sg:classifiers": [
      {
        "category": "Social Services",
        "subcategory": "Child Care",
        "type": "Services"
      }
    ],
    "sg:phone": "+1 614 431 8230",
    "sg:postcode": "43081",
    "sg:province": "OH",
    "sg:tags": [
      "day"
    ],
    "wof:name": "Grace Brethren Preschool",
    "wof:placetype": "venue"
  },
  "geometry": {"coordinates":[-82.974693,40.130889],"type":"Point"}
}
