{
  "type": "Feature",
  "properties": {
    "addr:full":"2626 Vine St Cincinnati OH 45219",
    "addr:housenumber":"2626",
    "addr:postcode":"45219",
    "addr:street":"Vine St",
    "iso:country":"US",
    "sg:address":"2626 Vine St",
    "sg:city":"Cincinnati",
    "sg:classifiers":[
        {
            "category":"Bars & Pubs",
            "type":"Food & Drink"
        }
    ],
    "sg:phone":"+1 513 751 2300",
    "sg:postcode":"45219",
    "sg:province":"OH",
    "sg:tags":[
        "club",
        "night"
    ],
    "sg:website":"www.sudsys.com",
    "wof:name":"Sudsy Malone's Rock & Roll Bar",
    "wof:placetype":"venue"
},
  "geometry": {"coordinates":[-84.509444,39.130026],"type":"Point"}
}