{
  "type": "Feature",
  "properties": {
    "addr:full": "2026 Delaware Ave Cincinnati OH 45212",
    "addr:housenumber": "2026",
    "addr:postcode": "45212",
    "addr:street": "Delaware Ave",
    "iso:country": "US",
    "sg:address": "2026 Delaware Ave",
    "sg:city": "Cincinnati",
    "sg:classifiers": [
      {
        "category": "Home \u0026 Garden",
        "subcategory": "Building Materials",
        "type": "Retail Goods"
      }
    ],
    "sg:phone": "+1 513 351 1600",
    "sg:postcode": "45212",
    "sg:province": "OH",
    "sg:tags": [
      "plumbing",
      "fixture",
      "supply"
    ],
    "wof:name": "Keidel Supply Co Inc",
    "wof:placetype": "venue"
  },
  "geometry": {"coordinates":[-84.46076,39.154339],"type":"Point"}
}
