{
  "type": "Feature",
  "properties": {
    "iso:country":"US",
    "sg:address":"7647 E Twp Rd 44",
    "sg:city":"Bloomville",
    "sg:classifiers":[
        {
            "category":"Farming",
            "subcategory":"Dairy Farm",
            "type":"Manufacturing & Wholesale Goods"
        }
    ],
    "sg:phone":"+1 419 983 4861",
    "sg:postcode":"44818",
    "sg:province":"OH",
    "wof:name":"Lyle Linn",
    "wof:placetype":"venue"
},
  "geometry": {"coordinates":[-83.035873,41.008344],"type":"Point"}
}