{
  "type": "Feature",
  "properties": {
    "addr:full": "505 Elberon Ave Cincinnati OH 45205",
    "addr:housenumber": "505",
    "addr:postcode": "45205",
    "addr:street": "Elberon Ave",
    "iso:country": "US",
    "sg:address": "505 Elberon Ave",
    "sg:city": "Cincinnati",
    "sg:classifiers": [
      {
        "category": "Retail",
        "subcategory": "Auto Repair",
        "type": "Services"
      }
    ],
    "sg:phone": "+1 513 251 3693",
    "sg:postcode": "45205",
    "sg:province": "OH",
    "sg:tags": [
      "repairing",
      "automobile"
    ],
    "wof:name": "Oliver \u0026 Johnsons Auto Care",
    "wof:placetype": "venue"
  },
  "geometry": {"coordinates":[-84.566378,39.10389],"type":"Point"}
}
