{
  "type": "Feature",
  "properties": {
    "iso:country":"US",
    "sg:address":"505 Elberon Ave",
    "sg:city":"Cincinnati",
    "sg:classifiers":[
        {
            "category":"Retail",
            "subcategory":"Auto Repair",
            "type":"Services"
        }
    ],
    "sg:phone":"+1 513 251 3693",
    "sg:postcode":"45205",
    "sg:province":"OH",
    "sg:tags":[
        "repairing",
        "automobile"
    ],
    "wof:name":"Oliver & Johnsons Auto Care",
    "wof:placetype":"venue"
},
  "geometry": {"coordinates":[-84.566378,39.10389],"type":"Point"}
}