{
  "type": "Feature",
  "properties": {
    "iso:country":"US",
    "sg:address":"6832 Convent Blvd",
    "sg:city":"Sylvania",
    "sg:classifiers":[
        {
            "category":"Social Services",
            "type":"Services"
        }
    ],
    "sg:phone":"+1 419 882 4529",
    "sg:postcode":"43560",
    "sg:province":"OH",
    "wof:name":"Nijakowski S Rachel",
    "wof:placetype":"venue"
},
  "geometry": {"coordinates":[-83.70949400000001,41.70811],"type":"Point"}
}