{
  "type": "Feature",
  "properties": {
    "addr:full": "6832 Convent Blvd Sylvania OH 43560",
    "addr:housenumber": "6832",
    "addr:postcode": "43560",
    "addr:street": "Convent Blvd",
    "iso:country": "US",
    "sg:address": "6832 Convent Blvd",
    "sg:city": "Sylvania",
    "sg:classifiers": [
      {
        "category": "Social Services",
        "type": "Services"
      }
    ],
    "sg:phone": "+1 419 882 4529",
    "sg:postcode": "43560",
    "sg:province": "OH",
    "wof:name": "Nijakowski S Rachel",
    "wof:placetype": "venue"
  },
  "geometry": {"coordinates":[-83.709494,41.70811],"type":"Point"}
}
