{
  "type": "Feature",
  "properties": {
    "addr:full": "30151 Happy Ln Richwood OH 43344",
    "addr:housenumber": "30151",
    "addr:postcode": "43344",
    "addr:street": "Happy Ln",
    "iso:country": "US",
    "sg:address": "30151 Happy Ln",
    "sg:city": "Richwood",
    "sg:phone": "+1 740 943 2845",
    "sg:postcode": "43344",
    "sg:province": "OH",
    "sg:tags": [
      "farm",
      "field",
      "crop"
    ],
    "wof:name": "Harold \u0026 Ruth Simmons",
    "wof:placetype": "venue"
  },
  "geometry": {"coordinates":[-83.364731,40.442712],"type":"Point"}
}
