{
  "type": "Feature",
  "properties": {
    "addr:full": "888 Antioch School Rd Vandalia OH 45377",
    "addr:housenumber": "888",
    "addr:postcode": "45377",
    "addr:street": "Antioch School Rd",
    "iso:country": "US",
    "sg:address": "888 Antioch School Rd",
    "sg:city": "Vandalia",
    "sg:classifiers": [
      {
        "category": "Banks \u0026 Credit Unions",
        "subcategory": "Investment Brokerage",
        "type": "Services"
      }
    ],
    "sg:phone": "+1 937 264 8396",
    "sg:postcode": "45377",
    "sg:province": "OH",
    "sg:tags": [
      "management"
    ],
    "wof:name": "Lawson \u0026 Combs Investments LTD",
    "wof:placetype": "venue"
  },
  "geometry": {"coordinates":[-84.280538,39.909128],"type":"Point"}
}
