{
  "type": "Feature",
  "properties": {
    "addr:full":"1030 Jackson Ln Middletown OH 45044",
    "addr:housenumber":"1030",
    "addr:postcode":"45044",
    "addr:street":"Jackson Ln",
    "iso:country":"US",
    "sg:address":"1030 Jackson Ln",
    "sg:city":"Middletown",
    "sg:classifiers":[
        {
            "category":"Organizations",
            "subcategory":"Religious Organization",
            "type":"Services"
        }
    ],
    "sg:phone":"+1 513 422 8549",
    "sg:postcode":"45044",
    "sg:province":"OH",
    "sg:tags":[
        "clergy"
    ],
    "wof:name":"Lloyd Friend",
    "wof:placetype":"venue"
},
  "geometry": {"coordinates":[-84.368551,39.500011],"type":"Point"}
}