{
  "type": "Feature",
  "properties": {
    "addr:full": "12613 Berlin Rd Berlin Heights OH 44814",
    "addr:postcode": "12613;44814",
    "addr:street": "Berlin Rd",
    "iso:country": "US",
    "sg:address": "12613 Berlin Rd",
    "sg:city": "Berlin Heights",
    "sg:classifiers": [
      {
        "category": "Home \u0026 Garden",
        "subcategory": "Home Furnishings",
        "type": "Retail Goods"
      }
    ],
    "sg:phone": "+1 419 588 2402",
    "sg:postcode": "44814",
    "sg:province": "OH",
    "wof:name": "Garlocks Custom Closets",
    "wof:placetype": "venue"
  },
  "geometry": {"coordinates":[-82.502904,41.312752],"type":"Point"}
}
