{
  "type": "Feature",
  "properties": {
    "iso:country":"US",
    "sg:address":"12613 Berlin Rd",
    "sg:city":"Berlin Heights",
    "sg:classifiers":[
        {
            "category":"Home & Garden",
            "subcategory":"Home Furnishings",
            "type":"Retail Goods"
        }
    ],
    "sg:phone":"+1 419 588 2402",
    "sg:postcode":"44814",
    "sg:province":"OH",
    "wof:name":"Garlocks Custom Closets",
    "wof:placetype":"venue"
},
  "geometry": {"coordinates":[-82.502904,41.312752],"type":"Point"}
}