{
  "type": "Feature",
  "properties": {
    "addr:full": "409 Chillicothe St Portsmouth OH 45662",
    "addr:housenumber": "409",
    "addr:postcode": "45662",
    "addr:street": "Chillicothe St",
    "iso:country": "US",
    "sg:address": "409 Chillicothe St",
    "sg:city": "Portsmouth",
    "sg:classifiers": [
      {
        "category": "Personal",
        "subcategory": "Beauty Salon",
        "type": "Services"
      }
    ],
    "sg:phone": "+1 740 354 6171",
    "sg:postcode": "45662",
    "sg:province": "OH",
    "wof:name": "From Head To Toe Solutions",
    "wof:placetype": "venue"
  },
  "geometry": {"coordinates":[-82.996641,38.73391],"type":"Point"}
}
