{
  "type": "Feature",
  "properties": {
    "iso:country":"US",
    "sg:address":"501 Sunset Blvd",
    "sg:city":"Mansfield",
    "sg:classifiers":[
        {
            "category":"Professional",
            "subcategory":"Business Services",
            "type":"Services"
        }
    ],
    "sg:phone":"+1 419 565 5805",
    "sg:postcode":"44907",
    "sg:province":"OH",
    "sg:tags":[
        "auctioneer"
    ],
    "wof:name":"James Angeloff",
    "wof:placetype":"venue"
},
  "geometry": {"coordinates":[-82.535944,40.726045],"type":"Point"}
}