{
  "type": "Feature",
  "properties": {
    "iso:country":"US",
    "sg:address":"10735 Lagrange Rd",
    "sg:city":"Elyria",
    "sg:classifiers":[
        {
            "category":"Retail",
            "subcategory":"Veterinary Services",
            "type":"Services"
        }
    ],
    "sg:phone":"+1 440 458 4291",
    "sg:postcode":"44035",
    "sg:province":"OH",
    "wof:name":"Fox Veterinary Hospital Inc",
    "wof:placetype":"venue"
},
  "geometry": {"coordinates":[-82.117379,41.33555],"type":"Point"}
}