{
  "type": "Feature",
  "properties": {
    "iso:country":"US",
    "sg:address":"11101 Loudermilk Rd",
    "sg:city":"Glouster",
    "sg:classifiers":[
        {
            "category":"Building & Trades",
            "subcategory":"Landscaping Services",
            "type":"Services"
        }
    ],
    "sg:phone":"+1 740 767 2605",
    "sg:postcode":"45732",
    "sg:province":"OH",
    "wof:name":"Bycofski Hauling & Landscaping",
    "wof:placetype":"venue"
},
  "geometry": {"coordinates":[-82.069186,39.487114],"type":"Point"}
}