{
  "type": "Feature",
  "properties": {
    "addr:full": "6170 Parkcenter Cir Dublin OH 43017",
    "addr:housenumber": "6170",
    "addr:postcode": "43017",
    "addr:street": "Parkcenter Cir",
    "iso:country": "US",
    "sg:address": "6170 Parkcenter Cir",
    "sg:city": "Dublin",
    "sg:classifiers": [
      {
        "category": "Travel",
        "subcategory": "Hotels \u0026 Motels",
        "type": "Entertainment"
      }
    ],
    "sg:phone": "+1 614 798 8802",
    "sg:postcode": "43017",
    "sg:province": "OH",
    "wof:name": "Drury Inns",
    "wof:placetype": "venue"
  },
  "geometry": {"coordinates":[-83.132281,40.077174],"type":"Point"}
}
