{
  "type": "Feature",
  "properties": {
    "iso:country":"US",
    "sg:address":"6170 Parkcenter Cir",
    "sg:city":"Dublin",
    "sg:classifiers":[
        {
            "category":"Travel",
            "subcategory":"Hotels & Motels",
            "type":"Entertainment"
        }
    ],
    "sg:phone":"+1 614 798 8802",
    "sg:postcode":"43017",
    "sg:province":"OH",
    "wof:name":"Drury Inns",
    "wof:placetype":"venue"
},
  "geometry": {"coordinates":[-83.13228100000001,40.077174],"type":"Point"}
}