{
  "type": "Feature",
  "properties": {
    "addr:full":"12443 Church Rd Orrville OH 44667",
    "addr:housenumber":"12443",
    "addr:postcode":"44667",
    "addr:street":"Church Rd",
    "iso:country":"US",
    "sg:address":"12443 Church Rd",
    "sg:city":"Orrville",
    "sg:classifiers":[
        {
            "category":"Building & Trades",
            "subcategory":"Landscaping Services",
            "type":"Services"
        }
    ],
    "sg:phone":"+1 330 683 4331",
    "sg:postcode":"44667",
    "sg:province":"OH",
    "wof:name":"Branch Tree Service",
    "wof:placetype":"venue"
},
  "geometry": {"coordinates":[-81.757561,40.821887],"type":"Point"}
}