{
  "type": "Feature",
  "properties": {
    "addr:full": "253 Richards Rd Columbus OH 43214",
    "addr:housenumber": "253",
    "addr:postcode": "43214",
    "addr:street": "Richards Rd",
    "iso:country": "US",
    "sg:address": "253 Richards Rd",
    "sg:city": "Columbus",
    "sg:classifiers": [
      {
        "category": "Manufacturing",
        "subcategory": "Tools \u0026 Machinery",
        "type": "Manufacturing \u0026 Wholesale Goods"
      }
    ],
    "sg:phone": "+1 614 261 8010",
    "sg:postcode": "43214",
    "sg:province": "OH",
    "sg:tags": [
      "mold"
    ],
    "wof:name": "Sinitron",
    "wof:placetype": "venue"
  },
  "geometry": {"coordinates":[-83.013793,40.039977],"type":"Point"}
}
