{
  "type": "Feature",
  "properties": {
    "iso:country":"US",
    "sg:address":"253 Richards Rd",
    "sg:city":"Columbus",
    "sg:classifiers":[
        {
            "category":"Manufacturing",
            "subcategory":"Tools & Machinery",
            "type":"Manufacturing & Wholesale Goods"
        }
    ],
    "sg:phone":"+1 614 261 8010",
    "sg:postcode":"43214",
    "sg:province":"OH",
    "sg:tags":[
        "mold"
    ],
    "wof:name":"Sinitron",
    "wof:placetype":"venue"
},
  "geometry": {"coordinates":[-83.013793,40.039977],"type":"Point"}
}