{
  "type": "Feature",
  "properties": {
    "iso:country":"US",
    "sg:address":"6432 Kinsman Nickerson Rd",
    "sg:city":"Kinsman",
    "sg:classifiers":[
        {
            "category":"Insurance",
            "subcategory":"Hazard Insurance",
            "type":"Services"
        }
    ],
    "sg:phone":"+1 330 876 2781",
    "sg:postcode":"44428",
    "sg:province":"OH",
    "sg:tags":[
        "commercial",
        "business"
    ],
    "wof:name":"Noxon Insurance Agency Inc",
    "wof:placetype":"venue"
},
  "geometry": {"coordinates":[-80.588112,41.444031],"type":"Point"}
}