{
  "type": "Feature",
  "properties": {
    "iso:country":"US",
    "sg:address":"31 N Main St",
    "sg:city":"Frankfort",
    "sg:classifiers":[
        {
            "category":"Government",
            "subcategory":"Office",
            "type":"Public Place"
        }
    ],
    "sg:phone":"+1 740 998 6871",
    "sg:postcode":"45628",
    "sg:province":"OH",
    "sg:tags":[
        "county"
    ],
    "wof:name":"Frankfort Senior Citizens Ctr",
    "wof:placetype":"venue"
},
  "geometry": {"coordinates":[-83.17750599999999,39.404471],"type":"Point"}
}