{
  "type": "Feature",
  "properties": {
    "iso:country":"US",
    "sg:address":"4740 Interstate Dr",
    "sg:city":"Cincinnati",
    "sg:phone":"+1 513 892 4000",
    "sg:postcode":"45246",
    "sg:province":"OH",
    "sg:tags":[
        "oil"
    ],
    "sg:website":"www.coolantsplus.com",
    "wof:name":"Coolants Plus Inc",
    "wof:placetype":"venue"
},
  "geometry": {"coordinates":[-84.46798099999999,39.308774],"type":"Point"}
}