{
  "type": "Feature",
  "properties": {
    "addr:full": "4740 Interstate Dr Cincinnati OH 45246",
    "addr:housenumber": "4740",
    "addr:postcode": "45246",
    "addr:street": "Interstate Dr",
    "iso:country": "US",
    "sg:address": "4740 Interstate Dr",
    "sg:city": "Cincinnati",
    "sg:phone": "+1 513 892 4000",
    "sg:postcode": "45246",
    "sg:province": "OH",
    "sg:tags": [
      "oil"
    ],
    "sg:website": "www.coolantsplus.com",
    "wof:name": "Coolants Plus Inc",
    "wof:placetype": "venue"
  },
  "geometry": {"coordinates":[-84.467981,39.308774],"type":"Point"}
}
