{
  "type": "Feature",
  "properties": {
    "addr:full": "2245 Wienburg Dr Dayton OH 45418",
    "addr:housenumber": "2245",
    "addr:postcode": "45418",
    "addr:street": "Wienburg Dr",
    "iso:country": "US",
    "sg:address": "2245 Wienburg Dr",
    "sg:city": "Dayton",
    "sg:classifiers": [
      {
        "category": "Building \u0026 Trades",
        "subcategory": "Landscaping Services",
        "type": "Services"
      }
    ],
    "sg:phone": "+1 937 293 5953",
    "sg:postcode": "45418",
    "sg:province": "OH",
    "sg:tags": [
      "landscape",
      "contractor"
    ],
    "wof:name": "Sizemore Tree \u0026 Landscaping",
    "wof:placetype": "venue"
  },
  "geometry": {"coordinates":[-84.241454,39.700173],"type":"Point"}
}
