{
  "type": "Feature",
  "properties": {
    "addr:full": "12974 National Rd SW Pataskala OH 43062",
    "addr:housenumber": "12974",
    "addr:postcode": "43062",
    "addr:street": "National Rd Sw",
    "iso:country": "US",
    "sg:address": "12974 National Rd SW",
    "sg:city": "Pataskala",
    "sg:classifiers": [
      {
        "category": "Autos \u0026 Motor Vehicles",
        "subcategory": "Automobile Sales",
        "type": "Retail Goods"
      }
    ],
    "sg:phone": "+1 740 927 0079",
    "sg:postcode": "43062",
    "sg:province": "OH",
    "sg:tags": [
      "car",
      "dealer"
    ],
    "wof:name": "Ray's Auto Sales",
    "wof:placetype": "venue"
  },
  "geometry": {"coordinates":[-82.729438,39.956848],"type":"Point"}
}
