{
  "type": "Feature",
  "properties": {
    "addr:full": "7838 W Chester Rd West Chester OH 45069",
    "addr:housenumber": "7838",
    "addr:postcode": "45069",
    "addr:street": "W Chester Rd",
    "iso:country": "US",
    "sg:address": "7838 W Chester Rd",
    "sg:city": "West Chester",
    "sg:classifiers": [
      {
        "category": "Bars \u0026 Pubs",
        "type": "Food \u0026 Drink"
      }
    ],
    "sg:phone": "+1 513 777 0761",
    "sg:postcode": "45069",
    "sg:province": "OH",
    "sg:tags": [
      "drinking"
    ],
    "wof:name": "Hill Station",
    "wof:placetype": "venue"
  },
  "geometry": {"coordinates":[-84.367098,39.318317],"type":"Point"}
}
