{
  "type": "Feature",
  "properties": {
    "addr:full": "8648 Troy Pike Dayton OH 45424",
    "addr:housenumber": "8648",
    "addr:postcode": "45424",
    "addr:street": "Troy Pike",
    "iso:country": "US",
    "sg:address": "8648 Troy Pike",
    "sg:city": "Dayton",
    "sg:classifiers": [
      {
        "category": "Personal",
        "type": "Services"
      }
    ],
    "sg:phone": "+1 937 212 9465",
    "sg:postcode": "45424",
    "sg:province": "OH",
    "sg:tags": [
      "therapist",
      "massage"
    ],
    "wof:name": "Therapeutic Touch Massage Clnc",
    "wof:placetype": "venue"
  },
  "geometry": {"coordinates":[-84.136694,39.877893],"type":"Point"}
}
