{
  "type": "Feature",
  "properties": {
    "addr:full":"2322 W 4th St Mansfield OH 44906",
    "addr:housenumber":"2322",
    "addr:postcode":"44906",
    "addr:street":"W 4Th St",
    "iso:country":"US",
    "sg:address":"2322 W 4th St",
    "sg:city":"Mansfield",
    "sg:classifiers":[
        {
            "category":"Restaurant",
            "type":"Food & Drink"
        }
    ],
    "sg:menulink":"http://www.allmenus.com/oh/five-corners/128153-red-lobster/menu/",
    "sg:phone":"+1 419 747 4700",
    "sg:postcode":"44906",
    "sg:province":"OH",
    "sg:tags":[
        "seafood",
        "american"
    ],
    "wof:name":"Red Lobster",
    "wof:placetype":"venue"
},
  "geometry": {"coordinates":[-82.598229,40.77366],"type":"Point"}
}