{
  "type": "Feature",
  "properties": {
    "addr:full":"16 Canary Dr Lake Milton OH 44429",
    "addr:housenumber":"16",
    "addr:postcode":"44429",
    "addr:street":"Canary Dr",
    "iso:country":"US",
    "sg:address":"16 Canary Dr",
    "sg:city":"Lake Milton",
    "sg:classifiers":[
        {
            "category":"Real Estate",
            "subcategory":"Real Estate Operator",
            "type":"Services"
        }
    ],
    "sg:phone":"+1 330 654 5151",
    "sg:postcode":"44429",
    "sg:province":"OH",
    "sg:tags":[
        "mobile",
        "home",
        "community"
    ],
    "wof:name":"Lake Milton Mobile Home Park",
    "wof:placetype":"venue"
},
  "geometry": {"coordinates":[-80.97660999999999,41.069001],"type":"Point"}
}