{
  "type": "Feature",
  "properties": {
    "addr:full": "80 Park Ave Shelby OH 44875",
    "addr:housenumber": "80",
    "addr:postcode": "44875",
    "addr:street": "Park Ave",
    "iso:country": "US",
    "sg:address": "80 Park Ave",
    "sg:city": "Shelby",
    "sg:classifiers": [
      {
        "category": "Manufacturing",
        "subcategory": "Printing",
        "type": "Manufacturing \u0026 Wholesale Goods"
      }
    ],
    "sg:phone": "+1 419 347 8156",
    "sg:postcode": "44875",
    "sg:province": "OH",
    "sg:tags": [
      "cards",
      "greeting"
    ],
    "wof:name": "Corner Cupboard Creations",
    "wof:placetype": "venue"
  },
  "geometry": {"coordinates":[-82.659323,40.87392],"type":"Point"}
}
