{
  "type": "Feature",
  "properties": {
    "iso:country":"US",
    "sg:address":"80 Park Ave",
    "sg:city":"Shelby",
    "sg:classifiers":[
        {
            "category":"Manufacturing",
            "subcategory":"Printing",
            "type":"Manufacturing & Wholesale Goods"
        }
    ],
    "sg:phone":"+1 419 347 8156",
    "sg:postcode":"44875",
    "sg:province":"OH",
    "sg:tags":[
        "cards",
        "greeting"
    ],
    "wof:name":"Corner Cupboard Creations",
    "wof:placetype":"venue"
},
  "geometry": {"coordinates":[-82.659323,40.87392],"type":"Point"}
}