{
  "type": "Feature",
  "properties": {
    "iso:country":"US",
    "sg:address":"26001 Miles Rd",
    "sg:city":"Cleveland",
    "sg:classifiers":[
        {
            "category":"Professional",
            "type":"Services"
        }
    ],
    "sg:phone":"+1 216 292 7234",
    "sg:postcode":"44128",
    "sg:province":"OH",
    "sg:tags":[
        "establishment"
    ],
    "wof:name":"Liquid Living",
    "wof:placetype":"venue"
},
  "geometry": {"coordinates":[-81.494479,41.424333],"type":"Point"}
}