{
  "type": "Feature",
  "properties": {
    "addr:full":"3832 N Dayton Xenia Rd Dayton OH 45432",
    "addr:housenumber":"3832",
    "addr:postcode":"45432",
    "addr:street":"N Dayton Xenia Rd",
    "iso:country":"US",
    "sg:address":"3832 N Dayton Xenia Rd",
    "sg:city":"Dayton",
    "sg:classifiers":[
        {
            "category":"Retail",
            "subcategory":"Auto Repair",
            "type":"Services"
        }
    ],
    "sg:phone":"+1 937 426 5275",
    "sg:postcode":"45432",
    "sg:province":"OH",
    "sg:tags":[
        "engine",
        "automotive",
        "exchanging",
        "machine",
        "parts"
    ],
    "wof:name":"Automotive Parts & Machine Inc",
    "wof:placetype":"venue"
},
  "geometry": {"coordinates":[-84.07612899999999,39.735718],"type":"Point"}
}