{
  "type": "Feature",
  "properties": {
    "iso:country":"US",
    "sg:address":"3146 W 44th St",
    "sg:city":"Cleveland",
    "sg:classifiers":[
        {
            "category":"Retail",
            "subcategory":"Auto Repair",
            "type":"Services"
        }
    ],
    "sg:phone":"+1 216 334 1750",
    "sg:postcode":"44109",
    "sg:province":"OH",
    "sg:tags":[
        "wrecker"
    ],
    "wof:name":"Independent Towing & Recovery",
    "wof:placetype":"venue"
},
  "geometry": {"coordinates":[-81.71654599999999,41.468319],"type":"Point"}
}