{
  "type": "Feature",
  "properties": {
    "addr:full": "3146 W 44th St Cleveland OH 44109",
    "addr:housenumber": "3146",
    "addr:postcode": "44109",
    "addr:street": "W 44Th St",
    "iso:country": "US",
    "sg:address": "3146 W 44th St",
    "sg:city": "Cleveland",
    "sg:classifiers": [
      {
        "category": "Retail",
        "subcategory": "Auto Repair",
        "type": "Services"
      }
    ],
    "sg:phone": "+1 216 334 1750",
    "sg:postcode": "44109",
    "sg:province": "OH",
    "sg:tags": [
      "wrecker"
    ],
    "wof:name": "Independent Towing \u0026 Recovery",
    "wof:placetype": "venue"
  },
  "geometry": {"coordinates":[-81.716546,41.468319],"type":"Point"}
}
