{
  "type": "Feature",
  "properties": {
    "addr:full": "174 N Mecca St Cortland OH 44410",
    "addr:housenumber": "174",
    "addr:postcode": "44410",
    "addr:street": "N Mecca St",
    "iso:country": "US",
    "sg:address": "174 N Mecca St",
    "sg:city": "Cortland",
    "sg:classifiers": [
      {
        "category": "Insurance",
        "subcategory": "Insurance Agent",
        "type": "Services"
      }
    ],
    "sg:phone": "+1 330 637 0067",
    "sg:postcode": "44410",
    "sg:province": "OH",
    "wof:name": "Allstate Insurance",
    "wof:placetype": "venue"
  },
  "geometry": {"coordinates":[-80.731185,41.332276],"type":"Point"}
}
