{
  "type": "Feature",
  "properties": {
    "addr:full": "1956 N Fairfield Rd Beavercreek OH 45432",
    "addr:housenumber": "1956",
    "addr:postcode": "45432",
    "addr:street": "N Fairfield Rd",
    "iso:country": "US",
    "sg:address": "1956 N Fairfield Rd",
    "sg:city": "Beavercreek",
    "sg:classifiers": [
      {
        "category": "Organizations",
        "subcategory": "Non-profit Organization",
        "type": "Services"
      },
      {
        "category": "Social Services",
        "type": "Services"
      }
    ],
    "sg:phone": "+1 937 426 7333",
    "sg:postcode": "45432",
    "sg:province": "OH",
    "sg:tags": [
      "home",
      "senior",
      "citizen"
    ],
    "wof:name": "Fairwood Village Inc",
    "wof:placetype": "venue"
  },
  "geometry": {"coordinates":[-84.056639,39.743569],"type":"Point"}
}
