{
  "type": "Feature",
  "properties": {
    "addr:full": "5311 Clark Ave Cleveland OH 44102",
    "addr:housenumber": "5311",
    "addr:postcode": "44102",
    "addr:street": "Clark Ave",
    "iso:country": "US",
    "sg:address": "5311 Clark Ave",
    "sg:city": "Cleveland",
    "sg:classifiers": [
      {
        "category": "Restaurant",
        "type": "Food \u0026 Drink"
      }
    ],
    "sg:phone": "+1 216 961 8947",
    "sg:postcode": "44102",
    "sg:province": "OH",
    "sg:tags": [
      "eating"
    ],
    "wof:name": "Top Dog Connections",
    "wof:placetype": "venue"
  },
  "geometry": {"coordinates":[-81.723385,41.469579],"type":"Point"}
}
