{
  "type": "Feature",
  "properties": {
    "iso:country":"US",
    "sg:address":"5311 Clark Ave",
    "sg:city":"Cleveland",
    "sg:classifiers":[
        {
            "category":"Restaurant",
            "type":"Food & Drink"
        }
    ],
    "sg:phone":"+1 216 961 8947",
    "sg:postcode":"44102",
    "sg:province":"OH",
    "sg:tags":[
        "eating"
    ],
    "wof:name":"Top Dog Connections",
    "wof:placetype":"venue"
},
  "geometry": {"coordinates":[-81.72338499999999,41.469579],"type":"Point"}
}