{
  "type": "Feature",
  "properties": {
    "addr:full":"4311 Eastern Ave Cincinnati OH 45226",
    "addr:housenumber":"4311",
    "addr:postcode":"45226",
    "addr:street":"Eastern Ave",
    "iso:country":"US",
    "sg:address":"4311 Eastern Ave",
    "sg:city":"Cincinnati",
    "sg:classifiers":[
        {
            "category":"Organizations",
            "subcategory":"Religious Organization",
            "type":"Services"
        }
    ],
    "sg:phone":"+1 513 533 1364",
    "sg:postcode":"45226",
    "sg:province":"OH",
    "sg:tags":[
        "church"
    ],
    "wof:name":"True Light Bapt Church",
    "wof:placetype":"venue"
},
  "geometry": {"coordinates":[-84.424091,39.111256],"type":"Point"}
}