{
  "type": "Feature",
  "properties": {
    "addr:full": "7625 N Sarasota Dr Cleveland OH 44134",
    "addr:housenumber": "7625",
    "addr:postcode": "44134",
    "addr:street": "N Sarasota Dr",
    "iso:country": "US",
    "sg:address": "7625 N Sarasota Dr",
    "sg:city": "Cleveland",
    "sg:classifiers": [
      {
        "category": "Professional",
        "type": "Services"
      }
    ],
    "sg:phone": "+1 440 842 3356",
    "sg:postcode": "44134",
    "sg:province": "OH",
    "wof:name": "JR\u0026h of Ohio LLC",
    "wof:placetype": "venue"
  },
  "geometry": {"coordinates":[-81.71127,41.358286],"type":"Point"}
}
