{
  "type": "Feature",
  "properties": {
    "addr:full":"2231 State Rte 45 S Rock Creek OH 44084",
    "addr:housenumber":"2231",
    "addr:postcode":"44084",
    "addr:street":"State Rte 45 S Rock Creek",
    "iso:country":"US",
    "sg:address":"2231 State Rte 45 S",
    "sg:city":"Rock Creek",
    "sg:classifiers":[
        {
            "category":"Freight",
            "type":"Transportation"
        }
    ],
    "sg:phone":"+1 440 466 7988",
    "sg:postcode":"44084",
    "sg:province":"OH",
    "sg:tags":[
        "commercial",
        "storage"
    ],
    "wof:name":"Smurf Storage Lockers",
    "wof:placetype":"venue"
},
  "geometry": {"coordinates":[-80.854871,41.69063],"type":"Point"}
}