{
  "type": "Feature",
  "properties": {
    "addr:full": "2083 Elm Rd NE Warren OH 44483",
    "addr:housenumber": "2083",
    "addr:postcode": "44483",
    "addr:street": "Elm Rd Ne",
    "iso:country": "US",
    "sg:address": "2083 Elm Rd NE",
    "sg:city": "Warren",
    "sg:classifiers": [
      {
        "category": "Social Services",
        "type": "Services"
      }
    ],
    "sg:phone": "+1 330 372 1214",
    "sg:postcode": "44483",
    "sg:province": "OH",
    "sg:tags": [
      "organization",
      "welfare"
    ],
    "wof:name": "Goodwill Industries",
    "wof:placetype": "venue"
  },
  "geometry": {"coordinates":[-80.79217,41.253764],"type":"Point"}
}
