{
  "type": "Feature",
  "properties": {
    "addr:full": "876 Glenwood Ave Cincinnati OH 45229",
    "addr:housenumber": "876",
    "addr:postcode": "45229",
    "addr:street": "Glenwood Ave",
    "iso:country": "US",
    "sg:address": "876 Glenwood Ave",
    "sg:city": "Cincinnati",
    "sg:classifiers": [
      {
        "category": "Education",
        "subcategory": "School",
        "type": "Public Place"
      }
    ],
    "sg:phone": "+1 513 872 7200",
    "sg:postcode": "45229",
    "sg:province": "OH",
    "wof:name": "Cincinnati Public Sch Burton",
    "wof:placetype": "venue"
  },
  "geometry": {"coordinates":[-84.485334,39.14752],"type":"Point"}
}
