{
  "type": "Feature",
  "properties": {
    "iso:country":"US",
    "sg:address":"28 Hammann Dr",
    "sg:city":"Amelia",
    "sg:classifiers":[
        {
            "category":"Real Estate",
            "subcategory":"Real Estate Operator",
            "type":"Services"
        }
    ],
    "sg:phone":"+1 513 753 3699",
    "sg:postcode":"45102",
    "sg:province":"OH",
    "sg:tags":[
        "property",
        "lessor"
    ],
    "wof:name":"Camm Properties",
    "wof:placetype":"venue"
},
  "geometry": {"coordinates":[-84.23871,39.049275],"type":"Point"}
}