{
  "type": "Feature",
  "properties": {
    "iso:country":"US",
    "sg:address":"111 Lawrence Ave",
    "sg:city":"Brilliant",
    "sg:classifiers":[
        {
            "category":"Professional",
            "subcategory":"Business Services",
            "type":"Services"
        }
    ],
    "sg:phone":"+1 740 222 2610",
    "sg:postcode":"43913",
    "sg:province":"OH",
    "wof:name":"Carols Message Center",
    "wof:placetype":"venue"
},
  "geometry": {"coordinates":[-80.624933,40.266974],"type":"Point"}
}