{
  "type": "Feature",
  "properties": {
    "addr:full":"6875 Wilson Mills Rd Gates Mills OH 44040",
    "addr:housenumber":"6875",
    "addr:postcode":"44040",
    "addr:street":"Wilson Mills Rd",
    "iso:country":"US",
    "sg:address":"6875 Wilson Mills Rd",
    "sg:city":"Gates Mills",
    "sg:classifiers":[
        {
            "category":"Building & Trades",
            "subcategory":"Plumbing",
            "type":"Services"
        }
    ],
    "sg:phone":"+1 440 449 3867",
    "sg:postcode":"44040",
    "sg:province":"OH",
    "sg:tags":[
        "contractor"
    ],
    "wof:name":"Bill Ward Heating & Cooli",
    "wof:placetype":"venue"
},
  "geometry": {"coordinates":[-81.429113,41.540822],"type":"Point"}
}