{
  "type": "Feature",
  "properties": {
    "addr:full": "2255 Shawnee Ave Springfield OH 45506",
    "addr:housenumber": "2255",
    "addr:postcode": "45506",
    "addr:street": "Shawnee Ave",
    "iso:country": "US",
    "sg:address": "2255 Shawnee Ave",
    "sg:city": "Springfield",
    "sg:classifiers": [
      {
        "category": "Professional",
        "subcategory": "Business Services",
        "type": "Services"
      }
    ],
    "sg:phone": "+1 937 408 6013",
    "sg:postcode": "45506",
    "sg:province": "OH",
    "sg:tags": [
      "recording",
      "studio"
    ],
    "wof:name": "Envisage Recording Svc",
    "wof:placetype": "venue"
  },
  "geometry": {"coordinates":[-83.834205,39.899081],"type":"Point"}
}
