{
  "type": "Feature",
  "properties": {
    "iso:country":"US",
    "sg:address":"751 Main St",
    "sg:city":"Groveport",
    "sg:classifiers":[
        {
            "category":"Education",
            "subcategory":"School",
            "type":"Public Place"
        }
    ],
    "sg:phone":"+1 614 836 4957",
    "sg:postcode":"43125",
    "sg:province":"OH",
    "sg:website":"www.gocruisers.org",
    "wof:name":"Groveport Madison Jr High",
    "wof:placetype":"venue"
},
  "geometry": {"coordinates":[-82.876355,39.850506],"type":"Point"}
}