{
  "type": "Feature",
  "properties": {
    "iso:country":"US",
    "sg:address":"769 E Main St",
    "sg:city":"Ravenna",
    "sg:classifiers":[
        {
            "category":"Restaurant",
            "type":"Food & Drink"
        }
    ],
    "sg:menulink":"http://www.allmenus.com/oh/ravenna/151736-aw-restaurant/menu/",
    "sg:phone":"+1 330 296 5028",
    "sg:postcode":"44266",
    "sg:province":"OH",
    "sg:tags":[
        "burger",
        "american",
        "dog",
        "pub",
        "hot"
    ],
    "wof:name":"A&W Restaurant",
    "wof:placetype":"venue"
},
  "geometry": {"coordinates":[-81.229635,41.157246],"type":"Point"}
}