{
  "type": "Feature",
  "properties": {
    "addr:full":"2362 Professor Ave Cleveland OH 44113",
    "addr:housenumber":"2362",
    "addr:postcode":"44113",
    "addr:street":"Professor Ave",
    "iso:country":"US",
    "sg:address":"2362 Professor Ave",
    "sg:city":"Cleveland",
    "sg:classifiers":[
        {
            "category":"Restaurant",
            "type":"Food & Drink"
        }
    ],
    "sg:phone":"+1 216 781 0352",
    "sg:postcode":"44113",
    "sg:province":"OH",
    "sg:tags":[
        "eating"
    ],
    "wof:name":"Tremont Scoops",
    "wof:placetype":"venue"
},
  "geometry": {"coordinates":[-81.68499300000001,41.479933],"type":"Point"}
}