{
  "type": "Feature",
  "properties": {
    "addr:full": "3790 E 5th Ave Columbus OH 43219",
    "addr:housenumber": "3790",
    "addr:postcode": "43219",
    "addr:street": "E 5Th Ave",
    "iso:country": "US",
    "sg:address": "3790 E 5th Ave",
    "sg:city": "Columbus",
    "sg:classifiers": [
      {
        "category": "Retail",
        "subcategory": "Auto Repair",
        "type": "Services"
      }
    ],
    "sg:phone": "+1 614 464 1884",
    "sg:postcode": "43219",
    "sg:province": "OH",
    "sg:tags": [
      "transmission"
    ],
    "wof:name": "Capital Core Inc",
    "wof:placetype": "venue"
  },
  "geometry": {"coordinates":[-82.903108,39.985484],"type":"Point"}
}
