{
  "type": "Feature",
  "properties": {
    "iso:country":"US",
    "sg:address":"3790 E 5th Ave",
    "sg:city":"Columbus",
    "sg:classifiers":[
        {
            "category":"Retail",
            "subcategory":"Auto Repair",
            "type":"Services"
        }
    ],
    "sg:phone":"+1 614 464 1884",
    "sg:postcode":"43219",
    "sg:province":"OH",
    "sg:tags":[
        "transmission"
    ],
    "wof:name":"Capital Core Inc",
    "wof:placetype":"venue"
},
  "geometry": {"coordinates":[-82.903108,39.985484],"type":"Point"}
}