{
  "type": "Feature",
  "properties": {
    "addr:full": "130 Madison St Port Clinton OH 43452",
    "addr:housenumber": "130",
    "addr:postcode": "43452",
    "addr:street": "Madison St",
    "iso:country": "US",
    "sg:address": "130 Madison St",
    "sg:city": "Port Clinton",
    "sg:classifiers": [
      {
        "category": "Shopping",
        "subcategory": "Gifts \u0026 Souvenirs",
        "type": "Retail Goods"
      }
    ],
    "sg:phone": "+1 419 732 2360",
    "sg:postcode": "43452",
    "sg:province": "OH",
    "sg:tags": [
      "shop"
    ],
    "wof:name": "Wide World Shop Inc",
    "wof:placetype": "venue"
  },
  "geometry": {"coordinates":[-82.941223,41.512344],"type":"Point"}
}
