{
  "type": "Feature",
  "properties": {
    "iso:country":"US",
    "sg:address":"119 W Buckeye St",
    "sg:city":"Ada",
    "sg:classifiers":[
        {
            "category":"Building & Trades",
            "subcategory":"Construction",
            "type":"Services"
        }
    ],
    "sg:phone":"+1 419 634 2511",
    "sg:postcode":"45810",
    "sg:province":"OH",
    "sg:tags":[
        "general",
        "contractor"
    ],
    "wof:name":"Amburgey Construction Company",
    "wof:placetype":"venue"
},
  "geometry": {"coordinates":[-83.824472,40.771258],"type":"Point"}
}