{
  "type": "Feature",
  "properties": {
    "iso:country":"US",
    "sg:address":"2743 Afton Valley Ct",
    "sg:city":"Maineville",
    "sg:classifiers":[
        {
            "category":"Freight",
            "type":"Transportation"
        }
    ],
    "sg:phone":"+1 513 398 6322",
    "sg:postcode":"45039",
    "sg:province":"OH",
    "sg:tags":[
        "operator",
        "local",
        "trucking"
    ],
    "wof:name":"Anthony P Conte Inc",
    "wof:placetype":"venue"
},
  "geometry": {"coordinates":[-84.270358,39.3337],"type":"Point"}
}