{
  "type": "Feature",
  "properties": {
    "iso:country":"US",
    "sg:address":"2814 Lagrange St",
    "sg:city":"Toledo",
    "sg:classifiers":[
        {
            "category":"Bars & Pubs",
            "type":"Food & Drink"
        }
    ],
    "sg:phone":"+1 419 727 9270",
    "sg:postcode":"43608",
    "sg:province":"OH",
    "wof:name":"Lion's Den Bar & Grill",
    "wof:placetype":"venue"
},
  "geometry": {"coordinates":[-83.539094,41.675567],"type":"Point"}
}