{
  "type": "Feature",
  "properties": {
    "iso:country":"US",
    "sg:address":"487 College St",
    "sg:city":"Wadsworth",
    "sg:classifiers":[
        {
            "category":"Manufacturing",
            "subcategory":"Printing",
            "type":"Manufacturing & Wholesale Goods"
        }
    ],
    "sg:phone":"+1 330 336 6700",
    "sg:postcode":"44281",
    "sg:province":"OH",
    "sg:tags":[
        "lithographic",
        "commercial"
    ],
    "wof:name":"RBA Inc",
    "wof:placetype":"venue"
},
  "geometry": {"coordinates":[-81.743331,41.025338],"type":"Point"}
}