{
  "type": "Feature",
  "properties": {
    "addr:full": "1222 Easton St NE Canton OH 44721",
    "addr:housenumber": "1222",
    "addr:postcode": "44721",
    "addr:street": "Easton St Ne",
    "iso:country": "US",
    "sg:address": "1222 Easton St NE",
    "sg:city": "Canton",
    "sg:classifiers": [
      {
        "category": "Utilities",
        "subcategory": "Telephone",
        "type": "Services"
      }
    ],
    "sg:phone": "+1 330 494 7266",
    "sg:postcode": "44721",
    "sg:province": "OH",
    "sg:tags": [
      "internet",
      "provider"
    ],
    "wof:name": "Best Position Corporation",
    "wof:placetype": "venue"
  },
  "geometry": {"coordinates":[-81.357947,40.874705],"type":"Point"}
}
