{
  "type": "Feature",
  "properties": {
    "addr:full": "3338 Harrison Ave Cincinnati OH 45211",
    "addr:housenumber": "3338",
    "addr:postcode": "45211",
    "addr:street": "Harrison Ave",
    "iso:country": "US",
    "sg:address": "3338 Harrison Ave",
    "sg:city": "Cincinnati",
    "sg:classifiers": [
      {
        "category": "Professional",
        "subcategory": "Business Services",
        "type": "Services"
      },
      {
        "category": "Organizations",
        "subcategory": "Non-profit Organization",
        "type": "Services"
      }
    ],
    "sg:phone": "+1 513 661 6500",
    "sg:postcode": "45211",
    "sg:province": "OH",
    "sg:tags": [
      "fund",
      "counselor",
      "telemarketing",
      "raising"
    ],
    "wof:name": "A J Cappel Enterprises Inc",
    "wof:placetype": "venue"
  },
  "geometry": {"coordinates":[-84.605812,39.155361],"type":"Point"}
}
