{
  "type": "Feature",
  "properties": {
    "addr:full": "5074 Warrensville Center Rd Cleveland OH 44137",
    "addr:housenumber": "5074",
    "addr:postcode": "44137",
    "addr:street": "Warrensville Center Rd",
    "iso:country": "US",
    "sg:address": "5074 Warrensville Center Rd",
    "sg:city": "Cleveland",
    "sg:classifiers": [
      {
        "category": "Recreation",
        "type": "Entertainment"
      }
    ],
    "sg:phone": "+1 216 518 9670",
    "sg:postcode": "44137",
    "sg:province": "OH",
    "sg:tags": [
      "martial",
      "arts",
      "instruction"
    ],
    "wof:name": "United Martial Arts",
    "wof:placetype": "venue"
  },
  "geometry": {"coordinates":[-81.537449,41.422105],"type":"Point"}
}
