{
  "type": "Feature",
  "properties": {
    "addr:full":"7778 Refugee Rd SW Pataskala OH 43062",
    "addr:housenumber":"7778",
    "addr:postcode":"43062",
    "addr:street":"Refugee Rd Sw",
    "iso:country":"US",
    "sg:address":"7778 Refugee Rd SW",
    "sg:city":"Pataskala",
    "sg:classifiers":[
        {
            "category":"Communications",
            "type":"Services"
        }
    ],
    "sg:phone":"+1 740 964 1883",
    "sg:postcode":"43062",
    "sg:province":"OH",
    "sg:tags":[
        "communication"
    ],
    "wof:name":"Crown Communications",
    "wof:placetype":"venue"
},
  "geometry": {"coordinates":[-82.637316,39.969958],"type":"Point"}
}