{
  "type": "Feature",
  "properties": {
    "addr:full": "47048 US Hwy 20 Oberlin OH 44074",
    "addr:housenumber": "47048",
    "addr:postcode": "44074",
    "addr:street": "Us Hwy 20",
    "iso:country": "US",
    "sg:address": "47048 US Hwy 20",
    "sg:city": "Oberlin",
    "sg:classifiers": [
      {
        "category": "Building \u0026 Trades",
        "subcategory": "Construction",
        "type": "Services"
      }
    ],
    "sg:phone": "+1 440 774 4330",
    "sg:postcode": "44074",
    "sg:province": "OH",
    "sg:tags": [
      "residential"
    ],
    "wof:name": "Bennie J Williamson",
    "wof:placetype": "venue"
  },
  "geometry": {"coordinates":[-82.236358,41.265305],"type":"Point"}
}
