{
  "type": "Feature",
  "properties": {
    "iso:country":"US",
    "sg:address":"250 Walker St",
    "sg:city":"Galion",
    "sg:classifiers":[
        {
            "category":"Building & Trades",
            "subcategory":"Construction",
            "type":"Services"
        }
    ],
    "sg:phone":"+1 419 468 9820",
    "sg:postcode":"44833",
    "sg:province":"OH",
    "sg:tags":[
        "house"
    ],
    "wof:name":"Lantz Remodeling & RPR",
    "wof:placetype":"venue"
},
  "geometry": {"coordinates":[-82.793221,40.738426],"type":"Point"}
}