{
  "type": "Feature",
  "properties": {
    "addr:full":"1555 Corporate Woods Pkwy Uniontown OH 44685",
    "addr:housenumber":"1555",
    "addr:postcode":"44685",
    "addr:street":"Corporate Woods Pkwy",
    "iso:country":"US",
    "sg:address":"1555 Corporate Woods Pkwy",
    "sg:city":"Uniontown",
    "sg:classifiers":[
        {
            "category":"Manufacturing",
            "subcategory":"Tools & Machinery",
            "type":"Manufacturing & Wholesale Goods"
        }
    ],
    "sg:phone":"+1 330 374 3040",
    "sg:postcode":"44685",
    "sg:province":"OH",
    "sg:tags":[
        "equipment",
        "industrial",
        "mfg"
    ],
    "sg:website":"www.onesite.com",
    "wof:name":"Goodrich Aerospace",
    "wof:placetype":"venue"
},
  "geometry": {"coordinates":[-81.470107,40.964261],"type":"Point"}
}