{
  "type": "Feature",
  "properties": {
    "addr:full": "555 S 18th St Columbus OH 43205",
    "addr:housenumber": "555",
    "addr:postcode": "43205",
    "addr:street": "S 18Th St",
    "iso:country": "US",
    "sg:address": "555 S 18th St",
    "sg:city": "Columbus",
    "sg:classifiers": [
      {
        "category": "Health Services",
        "subcategory": "Doctor",
        "type": "Services"
      }
    ],
    "sg:phone": "+1 614 221 6789",
    "sg:postcode": "43205",
    "sg:province": "OH",
    "sg:tags": [
      "physician",
      "surgeon"
    ],
    "wof:name": "EXCEL Ent",
    "wof:placetype": "venue"
  },
  "geometry": {"coordinates":[-82.976524,39.953357],"type":"Point"}
}
