{
  "type": "Feature",
  "properties": {
    "addr:full":"85 Waldorf Dr Akron OH 44313",
    "addr:housenumber":"85",
    "addr:postcode":"44313",
    "addr:street":"Waldorf Dr",
    "iso:country":"US",
    "sg:address":"85 Waldorf Dr",
    "sg:city":"Akron",
    "sg:classifiers":[
        {
            "category":"Building & Trades",
            "subcategory":"Construction",
            "type":"Services"
        }
    ],
    "sg:phone":"+1 330 836 6005",
    "sg:postcode":"44313",
    "sg:province":"OH",
    "sg:tags":[
        "remodeling",
        "contractor"
    ],
    "wof:name":"How To Construction Co Inc",
    "wof:placetype":"venue"
},
  "geometry": {"coordinates":[-81.579832,41.118866],"type":"Point"}
}