{
  "type": "Feature",
  "properties": {
    "addr:full": "17476 Snyder Rd Chagrin Falls OH 44023",
    "addr:housenumber": "17476",
    "addr:postcode": "44023",
    "addr:street": "Snyder Rd",
    "iso:country": "US",
    "sg:address": "17476 Snyder Rd",
    "sg:city": "Chagrin Falls",
    "sg:classifiers": [
      {
        "category": "Building \u0026 Trades",
        "subcategory": "Construction",
        "type": "Services"
      }
    ],
    "sg:phone": "+1 440 543 4335",
    "sg:postcode": "44023",
    "sg:province": "OH",
    "sg:tags": [
      "concrete",
      "contractor"
    ],
    "wof:name": "Tony Nero Cement \u0026 Cnstrctn",
    "wof:placetype": "venue"
  },
  "geometry": {"coordinates":[-81.308092,41.393852],"type":"Point"}
}
