{
  "type": "Feature",
  "properties": {
    "iso:country":"US",
    "sg:address":"17476 Snyder Rd",
    "sg:city":"Chagrin Falls",
    "sg:classifiers":[
        {
            "category":"Building & Trades",
            "subcategory":"Construction",
            "type":"Services"
        }
    ],
    "sg:phone":"+1 440 543 4335",
    "sg:postcode":"44023",
    "sg:province":"OH",
    "sg:tags":[
        "concrete",
        "contractor"
    ],
    "wof:name":"Tony Nero Cement & Cnstrctn",
    "wof:placetype":"venue"
},
  "geometry": {"coordinates":[-81.308092,41.393852],"type":"Point"}
}