{
  "type": "Feature",
  "properties": {
    "iso:country":"US",
    "sg:address":"354 Balmoral Dr",
    "sg:city":"Cleveland",
    "sg:classifiers":[
        {
            "category":"Wholesale",
            "subcategory":"Non-durable Goods",
            "type":"Manufacturing & Wholesale Goods"
        }
    ],
    "sg:phone":"+1 216 486 1213",
    "sg:postcode":"44143",
    "sg:province":"OH",
    "wof:name":"Direct Import Assistance Corp",
    "wof:placetype":"venue"
},
  "geometry": {"coordinates":[-81.514297,41.564522],"type":"Point"}
}