{
  "type": "Feature",
  "properties": {
    "iso:country":"US",
    "sg:address":"3788 Fishinger Blvd",
    "sg:city":"Hilliard",
    "sg:classifiers":[
        {
            "category":"Personal",
            "subcategory":"Beauty Salon",
            "type":"Services"
        }
    ],
    "sg:phone":"+1 614 527 9390",
    "sg:postcode":"43026",
    "sg:province":"OH",
    "sg:website":"www.greatclips.com",
    "wof:name":"Great Clips",
    "wof:placetype":"venue"
},
  "geometry": {"coordinates":[-83.115962,40.031642],"type":"Point"}
}