{
  "type": "Feature",
  "properties": {
    "addr:full": "7362 Tri County Hwy Sardinia OH 45171",
    "addr:postcode": "7362;45171",
    "addr:street": "Tri County Hwy",
    "iso:country": "US",
    "sg:address": "7362 Tri County Hwy",
    "sg:city": "Sardinia",
    "sg:classifiers": [
      {
        "category": "Personal",
        "type": "Services"
      }
    ],
    "sg:phone": "+1 937 446 3448",
    "sg:postcode": "45171",
    "sg:province": "OH",
    "sg:tags": [
      "therapist",
      "massage"
    ],
    "wof:name": "Te-Alah Wellness Ctr",
    "wof:placetype": "venue"
  },
  "geometry": {"coordinates":[-83.797459,39.002383],"type":"Point"}
}
