{
  "type": "Feature",
  "properties": {
    "addr:full":"98 Village Pointe Dr Powell OH 43065",
    "addr:housenumber":"98",
    "addr:postcode":"43065",
    "addr:street":"Village Pointe Dr",
    "iso:country":"US",
    "sg:address":"98 Village Pointe Dr",
    "sg:city":"Powell",
    "sg:classifiers":[
        {
            "category":"Bus Charters",
            "type":"Transportation"
        },
        {
            "category":"Local Transit",
            "type":"Transportation"
        }
    ],
    "sg:phone":"+1 614 760 9519",
    "sg:postcode":"43065",
    "sg:province":"OH",
    "sg:tags":[
        "limousine",
        "rental"
    ],
    "wof:name":"Limousines & Charter",
    "wof:placetype":"venue"
},
  "geometry": {"coordinates":[-83.08382400000001,40.158283],"type":"Point"}
}