{
  "type": "Feature",
  "properties": {
    "iso:country":"US",
    "sg:address":"8651 Mentor Rd",
    "sg:city":"Mentor",
    "sg:classifiers":[
        {
            "category":"Restaurant",
            "type":"Food & Drink"
        }
    ],
    "sg:phone":"+1 440 974 5090",
    "sg:postcode":"44060",
    "sg:province":"OH",
    "sg:tags":[
        "pizzeria"
    ],
    "wof:name":"Longos Pizza",
    "wof:placetype":"venue"
},
  "geometry": {"coordinates":[-81.29859399999999,41.640285],"type":"Point"}
}