{
  "type": "Feature",
  "properties": {
    "addr:full": "8442 Mayfield Rd Chesterland OH 44026",
    "addr:housenumber": "8442",
    "addr:postcode": "44026",
    "addr:street": "Mayfield Rd",
    "iso:country": "US",
    "sg:address": "8442 Mayfield Rd",
    "sg:city": "Chesterland",
    "sg:classifiers": [
      {
        "category": "Insurance",
        "subcategory": "Insurance Agent",
        "type": "Services"
      }
    ],
    "sg:phone": "+1 419 729 1996",
    "sg:postcode": "44026",
    "sg:province": "OH",
    "wof:name": "AA American Insurance",
    "wof:placetype": "venue"
  },
  "geometry": {"coordinates":[-81.339129,41.522233],"type":"Point"}
}
