{
  "type": "Feature",
  "properties": {
    "addr:full":"233 N Fair St Ottawa OH 45875",
    "addr:housenumber":"233",
    "addr:postcode":"45875",
    "addr:street":"N Fair St",
    "iso:country":"US",
    "sg:address":"233 N Fair St",
    "sg:city":"Ottawa",
    "sg:classifiers":[
        {
            "category":"Manufacturing",
            "subcategory":"Signs",
            "type":"Manufacturing & Wholesale Goods"
        }
    ],
    "sg:phone":"+1 419 523 6309",
    "sg:postcode":"45875",
    "sg:province":"OH",
    "sg:tags":[
        "specialty",
        "mfg"
    ],
    "wof:name":"M&R Signs",
    "wof:placetype":"venue"
},
  "geometry": {"coordinates":[-84.029729,41.02121],"type":"Point"}
}