{
  "type": "Feature",
  "properties": {
    "addr:full": "1169 Waverly Ave Youngstown OH 44509",
    "addr:housenumber": "1169",
    "addr:postcode": "44509",
    "addr:street": "Waverly Ave",
    "iso:country": "US",
    "sg:address": "1169 Waverly Ave",
    "sg:city": "Youngstown",
    "sg:classifiers": [
      {
        "category": "Building \u0026 Trades",
        "subcategory": "Construction",
        "type": "Services"
      }
    ],
    "sg:phone": "+1 330 799 7994",
    "sg:postcode": "44509",
    "sg:province": "OH",
    "sg:tags": [
      "hanging",
      "contractor"
    ],
    "wof:name": "Waverly Painting \u0026 Wallwashing",
    "wof:placetype": "venue"
  },
  "geometry": {"coordinates":[-80.684741,41.117486],"type":"Point"}
}
