{
  "type": "Feature",
  "properties": {
    "iso:country":"US",
    "sg:address":"2912 Cleveland Rd",
    "sg:city":"Wooster",
    "sg:classifiers":[
        {
            "category":"Personal",
            "subcategory":"Beauty Salon",
            "type":"Services"
        }
    ],
    "sg:phone":"+1 330 345 8666",
    "sg:postcode":"44691",
    "sg:province":"OH",
    "sg:tags":[
        "shop"
    ],
    "sg:website":"www.sheerprofessionals.com",
    "wof:name":"Sheer Professionals Hair",
    "wof:placetype":"venue"
},
  "geometry": {"coordinates":[-81.92933499999999,40.83605],"type":"Point"}
}