{
  "type": "Feature",
  "properties": {
    "addr:full":"10320 Saint Rita Ln Cincinnati OH 45215",
    "addr:housenumber":"10320",
    "addr:postcode":"45215",
    "addr:street":"Saint Rita Ln",
    "iso:country":"US",
    "sg:address":"10320 Saint Rita Ln",
    "sg:city":"Cincinnati",
    "sg:classifiers":[
        {
            "category":"Banks & Credit Unions",
            "subcategory":"Bank",
            "type":"Services"
        }
    ],
    "sg:phone":"+1 513 771 8866",
    "sg:postcode":"45215",
    "sg:province":"OH",
    "sg:tags":[
        "state",
        "commercial"
    ],
    "sg:website":"www.53.com",
    "wof:name":"Fifth Third Bank",
    "wof:placetype":"venue"
},
  "geometry": {"coordinates":[-84.446997,39.254787],"type":"Point"}
}