{
  "type": "Feature",
  "properties": {
    "addr:full": "1935 Central Ave Middletown OH 45044",
    "addr:housenumber": "1935",
    "addr:postcode": "45044",
    "addr:street": "Central Ave",
    "iso:country": "US",
    "sg:address": "1935 Central Ave",
    "sg:city": "Middletown",
    "sg:classifiers": [
      {
        "category": "Retail",
        "subcategory": "Car Wash",
        "type": "Services"
      }
    ],
    "sg:phone": "+1 513 423 4963",
    "sg:postcode": "45044",
    "sg:province": "OH",
    "sg:tags": [
      "polishing",
      "washing"
    ],
    "wof:name": "Middletown Super Wash",
    "wof:placetype": "venue"
  },
  "geometry": {"coordinates":[-84.390814,39.512978],"type":"Point"}
}
