{
  "type": "Feature",
  "properties": {
    "addr:full":"6525 Airport Hwy Holland OH 43528",
    "addr:housenumber":"6525",
    "addr:postcode":"43528",
    "addr:street":"Airport Hwy",
    "iso:country":"US",
    "sg:address":"6525 Airport Hwy",
    "sg:city":"Holland",
    "sg:classifiers":[
        {
            "category":"Restaurant",
            "type":"Food & Drink"
        }
    ],
    "sg:menulink":"http://www.allmenus.com/oh/holland/164653-wendys/menu/",
    "sg:phone":"+1 419 866 6099",
    "sg:postcode":"43528",
    "sg:province":"OH",
    "sg:tags":[
        "burger",
        "american",
        "soup"
    ],
    "wof:name":"Wendy's",
    "wof:placetype":"venue"
},
  "geometry": {"coordinates":[-83.698733,41.612295],"type":"Point"}
}