{
  "type": "Feature",
  "properties": {
    "addr:full": "375 Muskingum Ave Zanesville OH 43701",
    "addr:housenumber": "375",
    "addr:postcode": "43701",
    "addr:street": "Muskingum Ave",
    "iso:country": "US",
    "sg:address": "375 Muskingum Ave",
    "sg:city": "Zanesville",
    "sg:classifiers": [
      {
        "category": "Restaurant",
        "type": "Food \u0026 Drink"
      }
    ],
    "sg:phone": "+1 740 452 6303",
    "sg:postcode": "43701",
    "sg:province": "OH",
    "sg:website": "www.papachucks.com",
    "wof:name": "Papa Chuck's",
    "wof:placetype": "venue"
  },
  "geometry": {"coordinates":[-82.005995,39.933292],"type":"Point"}
}
