{
  "type": "Feature",
  "properties": {
    "addr:full":"4889 Sinclair Rd Columbus OH 43229",
    "addr:housenumber":"4889",
    "addr:postcode":"43229",
    "addr:street":"Sinclair Rd",
    "iso:country":"US",
    "sg:address":"4889 Sinclair Rd",
    "sg:city":"Columbus",
    "sg:classifiers":[
        {
            "category":"Professional",
            "subcategory":"Computer Services",
            "type":"Services"
        }
    ],
    "sg:phone":"+1 614 410 1760",
    "sg:postcode":"43229",
    "sg:province":"OH",
    "sg:tags":[
        "system",
        "cad"
    ],
    "wof:name":"Imaginit Technologies",
    "wof:placetype":"venue"
},
  "geometry": {"coordinates":[-82.998823,40.062287],"type":"Point"}
}