{
  "type": "Feature",
  "properties": {
    "iso:country":"US",
    "sg:address":"5028 Kill Rd",
    "sg:city":"Delphos",
    "sg:classifiers":[
        {
            "category":"Retail",
            "subcategory":"Auto Repair",
            "type":"Services"
        }
    ],
    "sg:phone":"+1 419 692 5881",
    "sg:postcode":"45833",
    "sg:province":"OH",
    "sg:tags":[
        "truck",
        "leasing",
        "trailer"
    ],
    "wof:name":"Rodoc Lsg Sls & Svc Ltd Partnr",
    "wof:placetype":"venue"
},
  "geometry": {"coordinates":[-84.387876,40.809179],"type":"Point"}
}