{
  "type": "Feature",
  "properties": {
    "iso:country":"US",
    "sg:address":"9563 Corduroy Rd",
    "sg:city":"Curtice",
    "sg:classifiers":[
        {
            "category":"Building & Trades",
            "subcategory":"Construction",
            "type":"Services"
        }
    ],
    "sg:phone":"+1 419 836 3000",
    "sg:postcode":"43412",
    "sg:province":"OH",
    "sg:tags":[
        "heavy"
    ],
    "wof:name":"Maumee Bay Aquatics",
    "wof:placetype":"venue"
},
  "geometry": {"coordinates":[-83.324802,41.660233],"type":"Point"}
}