{
  "type": "Feature",
  "properties": {
    "addr:full": "9563 Corduroy Rd Curtice OH 43412",
    "addr:housenumber": "9563",
    "addr:postcode": "43412",
    "addr:street": "Corduroy Rd",
    "iso:country": "US",
    "sg:address": "9563 Corduroy Rd",
    "sg:city": "Curtice",
    "sg:classifiers": [
      {
        "category": "Building \u0026 Trades",
        "subcategory": "Construction",
        "type": "Services"
      }
    ],
    "sg:phone": "+1 419 836 3000",
    "sg:postcode": "43412",
    "sg:province": "OH",
    "sg:tags": [
      "heavy"
    ],
    "wof:name": "Maumee Bay Aquatics",
    "wof:placetype": "venue"
  },
  "geometry": {"coordinates":[-83.324802,41.660233],"type":"Point"}
}
