{
  "type": "Feature",
  "properties": {
    "addr:full":"552 Danberry St Toledo OH 43609",
    "addr:housenumber":"552",
    "addr:postcode":"43609",
    "addr:street":"Danberry St",
    "iso:country":"US",
    "sg:address":"552 Danberry St",
    "sg:city":"Toledo",
    "sg:classifiers":[
        {
            "category":"Utilities",
            "subcategory":"Refuse",
            "type":"Services"
        }
    ],
    "sg:phone":"+1 419 381 8255",
    "sg:postcode":"43609",
    "sg:province":"OH",
    "sg:tags":[
        "crime",
        "trauma",
        "up",
        "clean",
        "scene"
    ],
    "sg:website":"www.bio-recovery.net",
    "wof:name":"Bio-Recovery Svc Of America",
    "wof:placetype":"venue"
},
  "geometry": {"coordinates":[-83.596937,41.629707],"type":"Point"}
}