{
  "type": "Feature",
  "properties": {
    "addr:full": "58 Fairview Ave Athens OH 45701",
    "addr:housenumber": "58",
    "addr:postcode": "45701",
    "addr:street": "Fairview Ave",
    "iso:country": "US",
    "sg:address": "58 Fairview Ave",
    "sg:city": "Athens",
    "sg:classifiers": [
      {
        "category": "Building \u0026 Trades",
        "subcategory": "Construction",
        "type": "Services"
      }
    ],
    "sg:phone": "+1 740 592 4091",
    "sg:postcode": "45701",
    "sg:province": "OH",
    "sg:tags": [
      "restoration",
      "cleaning",
      "patio",
      "deck"
    ],
    "wof:name": "Clean \u0026 Clear Window \u0026 Power",
    "wof:placetype": "venue"
  },
  "geometry": {"coordinates":[-82.10064,39.33415],"type":"Point"}
}
