{
  "type": "Feature",
  "properties": {
    "addr:full":"3991 Lee Rd Cleveland OH 44128",
    "addr:housenumber":"3991",
    "addr:postcode":"44128",
    "addr:street":"Lee Rd",
    "iso:country":"US",
    "sg:address":"3991 Lee Rd",
    "sg:city":"Cleveland",
    "sg:classifiers":[
        {
            "category":"Building & Trades",
            "subcategory":"Equipment Rental",
            "type":"Services"
        }
    ],
    "sg:phone":"+1 216 752 6000",
    "sg:postcode":"44128",
    "sg:province":"OH",
    "sg:tags":[
        "yard"
    ],
    "wof:name":"Rent-A-Center",
    "wof:placetype":"venue"
},
  "geometry": {"coordinates":[-81.564841,41.44979],"type":"Point"}
}