{
  "type": "Feature",
  "properties": {
    "addr:full":"1315 W 47th St Ashtabula OH 44004",
    "addr:housenumber":"1315",
    "addr:postcode":"44004",
    "addr:street":"W 47Th St",
    "iso:country":"US",
    "sg:address":"1315 W 47th St",
    "sg:city":"Ashtabula",
    "sg:classifiers":[
        {
            "category":"Professional",
            "type":"Services"
        }
    ],
    "sg:phone":"+1 440 993 6886",
    "sg:postcode":"44004",
    "sg:province":"OH",
    "sg:tags":[
        "establishment"
    ],
    "wof:name":"Robert S Morrison & Co",
    "wof:placetype":"venue"
},
  "geometry": {"coordinates":[-80.802373,41.864396],"type":"Point"}
}