{
  "type": "Feature",
  "properties": {
    "addr:full": "6903 Bunker Hill Rd Amanda OH 43102",
    "addr:housenumber": "6903",
    "addr:postcode": "43102",
    "addr:street": "Bunker Hill Rd",
    "iso:country": "US",
    "sg:address": "6903 Bunker Hill Rd",
    "sg:city": "Amanda",
    "sg:classifiers": [
      {
        "category": "Organizations",
        "subcategory": "Religious Organization",
        "type": "Services"
      }
    ],
    "sg:phone": "+1 740 498 4552",
    "sg:postcode": "43102",
    "sg:province": "OH",
    "sg:tags": [
      "church"
    ],
    "sg:website": "www.watchtower.org",
    "wof:name": "Jehovah's Witnesses",
    "wof:placetype": "venue"
  },
  "geometry": {"coordinates":[-82.77111,39.635767],"type":"Point"}
}
