{
  "type": "Feature",
  "properties": {
    "iso:country":"US",
    "sg:address":"25 Market St",
    "sg:city":"Youngstown",
    "sg:classifiers":[
        {
            "category":"Real Estate",
            "subcategory":"Real Estate Operator",
            "type":"Services"
        }
    ],
    "sg:phone":"+1 330 747 9300",
    "sg:postcode":"44503",
    "sg:province":"OH",
    "sg:tags":[
        "building",
        "apartment"
    ],
    "wof:name":"International Towers",
    "wof:placetype":"venue"
},
  "geometry": {"coordinates":[-80.64967300000001,41.099591],"type":"Point"}
}