{
  "type": "Feature",
  "properties": {
    "addr:full": "25 Market St Youngstown OH 44503",
    "addr:housenumber": "25",
    "addr:postcode": "44503",
    "addr:street": "Market St",
    "iso:country": "US",
    "sg:address": "25 Market St",
    "sg:city": "Youngstown",
    "sg:classifiers": [
      {
        "category": "Real Estate",
        "subcategory": "Real Estate Operator",
        "type": "Services"
      }
    ],
    "sg:phone": "+1 330 747 9300",
    "sg:postcode": "44503",
    "sg:province": "OH",
    "sg:tags": [
      "building",
      "apartment"
    ],
    "wof:name": "International Towers",
    "wof:placetype": "venue"
  },
  "geometry": {"coordinates":[-80.649673,41.099591],"type":"Point"}
}
