{
  "type": "Feature",
  "properties": {
    "addr:full":"411 Ryburn Ave Dayton OH 45405",
    "addr:housenumber":"411",
    "addr:postcode":"45405",
    "addr:street":"Ryburn Ave",
    "iso:country":"US",
    "sg:address":"411 Ryburn Ave",
    "sg:city":"Dayton",
    "sg:classifiers":[
        {
            "category":"Building & Trades",
            "subcategory":"Landscaping Services",
            "type":"Services"
        }
    ],
    "sg:phone":"+1 937 275 9473",
    "sg:postcode":"45405",
    "sg:province":"OH",
    "sg:tags":[
        "lawn",
        "maintenance",
        "grounds"
    ],
    "wof:name":"Grayland Robinson Lawn Care",
    "wof:placetype":"venue"
},
  "geometry": {"coordinates":[-84.20690500000001,39.796804],"type":"Point"}
}