{
  "type": "Feature",
  "properties": {
    "addr:full": "7340 Pawnee Rd Spencer OH 44275",
    "addr:housenumber": "7340",
    "addr:postcode": "44275",
    "addr:street": "Pawnee Rd",
    "iso:country": "US",
    "sg:address": "7340 Pawnee Rd",
    "sg:city": "Spencer",
    "sg:classifiers": [
      {
        "category": "Professional",
        "subcategory": "Business Services",
        "type": "Services"
      }
    ],
    "sg:phone": "+1 330 667 1084",
    "sg:postcode": "44275",
    "sg:province": "OH",
    "wof:name": "Powder Systems Consulting",
    "wof:placetype": "venue"
  },
  "geometry": {"coordinates":[-82.076358,41.073045],"type":"Point"}
}
