{
  "type": "Feature",
  "properties": {
    "addr:full":"1308 W Trenton Ave Findlay OH 45840",
    "addr:housenumber":"1308",
    "addr:postcode":"45840",
    "addr:street":"W Trenton Ave",
    "iso:country":"US",
    "sg:address":"1308 W Trenton Ave",
    "sg:city":"Findlay",
    "sg:classifiers":[
        {
            "category":"Professional",
            "type":"Services"
        }
    ],
    "sg:phone":"+1 419 425 5829",
    "sg:postcode":"45840",
    "sg:province":"OH",
    "sg:tags":[
        "establishment"
    ],
    "wof:name":"Border To Border Logistics",
    "wof:placetype":"venue"
},
  "geometry": {"coordinates":[-83.67534999999999,41.058655],"type":"Point"}
}