{
  "type": "Feature",
  "properties": {
    "iso:country":"US",
    "sg:address":"501 Clark St",
    "sg:city":"Cambridge",
    "sg:classifiers":[
        {
            "category":"Personal",
            "subcategory":"Beauty Salon",
            "type":"Services"
        }
    ],
    "sg:phone":"+1 740 439 1627",
    "sg:postcode":"43725",
    "sg:province":"OH",
    "wof:name":"Marlene's Touch Of Class Salon",
    "wof:placetype":"venue"
},
  "geometry": {"coordinates":[-81.58131899999999,40.030539],"type":"Point"}
}