{
  "type": "Feature",
  "properties": {
    "addr:full":"234 Honey Creek Rd E Bellville OH 44813",
    "addr:housenumber":"234",
    "addr:postcode":"44813",
    "addr:street":"Honey Creek Rd E",
    "iso:country":"US",
    "sg:address":"234 Honey Creek Rd E",
    "sg:city":"Bellville",
    "sg:phone":"+1 419 886 2015",
    "sg:postcode":"44813",
    "sg:province":"OH",
    "sg:tags":[
        "farm",
        "corn",
        "beef",
        "feedlot",
        "cattle"
    ],
    "wof:name":"Bacon Acres",
    "wof:placetype":"venue"
},
  "geometry": {"coordinates":[-82.506167,40.598136],"type":"Point"}
}