{
  "type": "Feature",
  "properties": {
    "iso:country":"US",
    "sg:address":"6199 Frank Ave NW",
    "sg:city":"North Canton",
    "sg:classifiers":[
        {
            "category":"Social Services",
            "subcategory":"Child Care",
            "type":"Services"
        }
    ],
    "sg:phone":"+1 330 305 0700",
    "sg:postcode":"44720",
    "sg:province":"OH",
    "wof:name":"All About Children's Learning",
    "wof:placetype":"venue"
},
  "geometry": {"coordinates":[-81.44176299999999,40.869156],"type":"Point"}
}