{
  "type": "Feature",
  "properties": {
    "addr:full":"2620 Vayview Dr Dayton OH 45431",
    "addr:housenumber":"2620",
    "addr:postcode":"45431",
    "addr:street":"Vayview Dr",
    "iso:country":"US",
    "sg:address":"2620 Vayview Dr",
    "sg:city":"Dayton",
    "sg:classifiers":[
        {
            "category":"Building & Trades",
            "subcategory":"Construction",
            "type":"Services"
        }
    ],
    "sg:phone":"+1 937 296 0259",
    "sg:postcode":"45431",
    "sg:province":"OH",
    "sg:tags":[
        "roofing",
        "contractor"
    ],
    "wof:name":"JBL Roofing",
    "wof:placetype":"venue"
},
  "geometry": {"coordinates":[-84.081137,39.767364],"type":"Point"}
}