{
  "type": "Feature",
  "properties": {
    "addr:full":"13018 Buckeye Rd Cleveland OH 44120",
    "addr:housenumber":"13018",
    "addr:postcode":"44120",
    "addr:street":"Buckeye Rd",
    "iso:country":"US",
    "sg:address":"13018 Buckeye Rd",
    "sg:city":"Cleveland",
    "sg:classifiers":[
        {
            "category":"Shopping",
            "subcategory":"Clothing, Apparel, & Fashions",
            "type":"Retail Goods"
        }
    ],
    "sg:phone":"+1 216 921 3477",
    "sg:postcode":"44120",
    "sg:province":"OH",
    "wof:name":"I S Fashions",
    "wof:placetype":"venue"
},
  "geometry": {"coordinates":[-81.591112,41.479653],"type":"Point"}
}