{
  "type": "Feature",
  "properties": {
    "addr:full":"1140 Cleveland Rd W Sandusky OH 44870",
    "addr:housenumber":"1140",
    "addr:postcode":"44870",
    "addr:street":"Cleveland Rd W",
    "iso:country":"US",
    "sg:address":"1140 Cleveland Rd W",
    "sg:city":"Sandusky",
    "sg:classifiers":[
        {
            "category":"Banks & Credit Unions",
            "subcategory":"Bank",
            "type":"Services"
        }
    ],
    "sg:phone":"+1 419 609 2274",
    "sg:postcode":"44870",
    "sg:province":"OH",
    "sg:tags":[
        "cashing",
        "check"
    ],
    "wof:name":"ACE Cash Express",
    "wof:placetype":"venue"
},
  "geometry": {"coordinates":[-82.694523,41.445328],"type":"Point"}
}