{
  "type": "Feature",
  "properties": {
    "addr:full":"7530 Lucerne Dr Cleveland OH 44130",
    "addr:housenumber":"7530",
    "addr:postcode":"44130",
    "addr:street":"Lucerne Dr",
    "iso:country":"US",
    "sg:address":"7530 Lucerne Dr",
    "sg:city":"Cleveland",
    "sg:classifiers":[
        {
            "category":"Real Estate",
            "subcategory":"Real Estate Agent",
            "type":"Services"
        }
    ],
    "sg:phone":"+1 440 234 7000",
    "sg:postcode":"44130",
    "sg:province":"OH",
    "wof:name":"Deerfield Estates Inc",
    "wof:placetype":"venue"
},
  "geometry": {"coordinates":[-81.816554,41.357313],"type":"Point"}
}