{
  "type": "Feature",
  "properties": {
    "iso:country":"US",
    "sg:address":"3350 Prange Dr",
    "sg:city":"Cuyahoga Falls",
    "sg:classifiers":[
        {
            "category":"Real Estate",
            "subcategory":"Real Estate Operator",
            "type":"Services"
        }
    ],
    "sg:phone":"+1 330 929 3738",
    "sg:postcode":"44223",
    "sg:province":"OH",
    "sg:tags":[
        "building",
        "apartment"
    ],
    "wof:name":"Friendship Terrace Inc",
    "wof:placetype":"venue"
},
  "geometry": {"coordinates":[-81.50141000000001,41.154841],"type":"Point"}
}