{
  "type": "Feature",
  "properties": {
    "addr:full": "6754 North St NW Newark OH 43055",
    "addr:housenumber": "6754",
    "addr:postcode": "43055",
    "addr:street": "North St Nw",
    "iso:country": "US",
    "sg:address": "6754 North St NW",
    "sg:city": "Newark",
    "sg:classifiers": [
      {
        "category": "Real Estate",
        "subcategory": "Real Estate Operator",
        "type": "Services"
      }
    ],
    "sg:phone": "+1 740 587 4064",
    "sg:postcode": "43055",
    "sg:province": "OH",
    "sg:tags": [
      "mall",
      "shopping",
      "center"
    ],
    "wof:name": "Fredonia Mall",
    "wof:placetype": "venue"
  },
  "geometry": {"coordinates":[-82.519908,40.154596],"type":"Point"}
}
