{
  "type": "Feature",
  "properties": {
    "iso:country":"US",
    "sg:address":"4283 Paradise Rd",
    "sg:city":"Seville",
    "sg:classifiers":[
        {
            "category":"Travel",
            "subcategory":"Campground",
            "type":"Entertainment"
        }
    ],
    "sg:phone":"+1 330 725 7041",
    "sg:postcode":"44273",
    "sg:province":"OH",
    "sg:tags":[
        "residential",
        "camp",
        "care"
    ],
    "wof:name":"Camp Paradise",
    "wof:placetype":"venue"
},
  "geometry": {"coordinates":[-81.841729,41.078181],"type":"Point"}
}