{
  "type": "Feature",
  "properties": {
    "addr:full": "14 de Camp Ave Cincinnati OH 45216",
    "addr:postcode": "45216",
    "addr:street": "14 De Camp Ave",
    "iso:country": "US",
    "sg:address": "14 de Camp Ave",
    "sg:city": "Cincinnati",
    "sg:classifiers": [
      {
        "category": "Retail",
        "subcategory": "Auto Repair",
        "type": "Services"
      }
    ],
    "sg:phone": "+1 513 631 2462",
    "sg:postcode": "45216",
    "sg:province": "OH",
    "sg:tags": [
      "automobile",
      "co",
      "drive",
      "transporter"
    ],
    "wof:name": "Action Towing \u0026 Auto Transport",
    "wof:placetype": "venue"
  },
  "geometry": {"coordinates":[-84.474298,39.20642],"type":"Point"}
}
