{
  "type": "Feature",
  "properties": {
    "iso:country":"US",
    "sg:address":"2915 12th St NW",
    "sg:city":"Canton",
    "sg:classifiers":[
        {
            "category":"Organizations",
            "subcategory":"Religious Organization",
            "type":"Services"
        }
    ],
    "sg:phone":"+1 330 456 0942",
    "sg:postcode":"44708",
    "sg:province":"OH",
    "sg:tags":[
        "church"
    ],
    "wof:name":"Friendship Community Church",
    "wof:placetype":"venue"
},
  "geometry": {"coordinates":[-81.406899,40.810298],"type":"Point"}
}