{
  "type": "Feature",
  "properties": {
    "iso:country":"US",
    "sg:address":"4707 Great Northern Blvd",
    "sg:city":"North Olmsted",
    "sg:classifiers":[
        {
            "category":"Restaurant",
            "type":"Food & Drink"
        }
    ],
    "sg:menulink":"http://www.allmenus.com/oh/north-olmsted/90176-penn-station/menu/",
    "sg:phone":"+1 440 716 8600",
    "sg:postcode":"44070",
    "sg:province":"OH",
    "sg:tags":[
        "wrap",
        "american",
        "sandwich"
    ],
    "wof:name":"Penn Station",
    "wof:placetype":"venue"
},
  "geometry": {"coordinates":[-81.901687,41.420576],"type":"Point"}
}