{
  "type": "Feature",
  "properties": {
    "addr:full": "9900 Princeton Glendale Rd Cincinnati OH 45246",
    "addr:housenumber": "9900",
    "addr:postcode": "45246",
    "addr:street": "Princeton Glendale Rd",
    "iso:country": "US",
    "sg:address": "9900 Princeton Glendale Rd",
    "sg:city": "Cincinnati",
    "sg:classifiers": [
      {
        "category": "Professional",
        "subcategory": "Computer Services",
        "type": "Services"
      }
    ],
    "sg:phone": "+1 513 874 3306",
    "sg:postcode": "45246",
    "sg:province": "OH",
    "sg:tags": [
      "repair"
    ],
    "wof:name": "Laptop Oncall",
    "wof:placetype": "venue"
  },
  "geometry": {"coordinates":[-84.464667,39.312174],"type":"Point"}
}
