{
  "type": "Feature",
  "properties": {
    "addr:full": "80 Mead St Dayton OH 45402",
    "addr:housenumber": "80",
    "addr:postcode": "45402",
    "addr:street": "Mead St",
    "iso:country": "US",
    "sg:address": "80 Mead St",
    "sg:city": "Dayton",
    "sg:classifiers": [
      {
        "category": "Shopping",
        "subcategory": "Clothing, Apparel, \u0026 Fashions",
        "type": "Retail Goods"
      }
    ],
    "sg:phone": "+1 937 222 8597",
    "sg:postcode": "45402",
    "sg:province": "OH",
    "sg:tags": [
      "uniform"
    ],
    "wof:name": "Premier Paper Company",
    "wof:placetype": "venue"
  },
  "geometry": {"coordinates":[-84.197963,39.754686],"type":"Point"}
}
