{
  "type": "Feature",
  "properties": {
    "addr:full":"2440 Wyandot Rd Bucyrus OH 44820",
    "addr:housenumber":"2440",
    "addr:postcode":"44820",
    "addr:street":"Wyandot Rd",
    "iso:country":"US",
    "sg:address":"2440 Wyandot Rd",
    "sg:city":"Bucyrus",
    "sg:classifiers":[
        {
            "category":"Real Estate",
            "subcategory":"Real Estate Operator",
            "type":"Services"
        }
    ],
    "sg:phone":"+1 419 562 6273",
    "sg:postcode":"44820",
    "sg:province":"OH",
    "sg:tags":[
        "property",
        "lessor"
    ],
    "wof:name":"Wwbeachecapenet",
    "wof:placetype":"venue"
},
  "geometry": {"coordinates":[-82.996365,40.795713],"type":"Point"}
}