{
  "type": "Feature",
  "properties": {
    "addr:full": "22790 Lake Shore Blvd Cleveland OH 44123",
    "addr:housenumber": "22790",
    "addr:postcode": "44123",
    "addr:street": "Lake Shore Blvd",
    "iso:country": "US",
    "sg:address": "22790 Lake Shore Blvd",
    "sg:city": "Cleveland",
    "sg:classifiers": [
      {
        "category": "Personal",
        "subcategory": "Tanning Parlor",
        "type": "Services"
      },
      {
        "category": "Personal",
        "type": "Services"
      }
    ],
    "sg:phone": "+1 216 289 6633",
    "sg:postcode": "44123",
    "sg:province": "OH",
    "sg:tags": [
      "salon"
    ],
    "wof:name": "South Shore Tanning Salon",
    "wof:placetype": "venue"
  },
  "geometry": {"coordinates":[-81.523778,41.611334],"type":"Point"}
}
