{
  "type": "Feature",
  "properties": {
    "iso:country":"US",
    "sg:address":"28 E Main St",
    "sg:city":"Norwalk",
    "sg:classifiers":[
        {
            "category":"Shopping",
            "type":"Retail Goods"
        }
    ],
    "sg:phone":"+1 419 660 1122",
    "sg:postcode":"44857",
    "sg:province":"OH",
    "sg:tags":[
        "telephone",
        "cellular"
    ],
    "wof:name":"Worry Less Wireless",
    "wof:placetype":"venue"
},
  "geometry": {"coordinates":[-82.613664,41.243247],"type":"Point"}
}