{
  "type": "Feature",
  "properties": {
    "addr:full":"441 Hopewell Dr Heath OH 43056",
    "addr:housenumber":"441",
    "addr:postcode":"43056",
    "addr:street":"Hopewell Dr",
    "iso:country":"US",
    "sg:address":"441 Hopewell Dr",
    "sg:city":"Heath",
    "sg:classifiers":[
        {
            "category":"Autos & Motor Vehicles",
            "subcategory":"Auto Supplies",
            "type":"Retail Goods"
        },
        {
            "category":"Wholesale",
            "subcategory":"Auto Parts",
            "type":"Manufacturing & Wholesale Goods"
        }
    ],
    "sg:phone":"+1 740 522 9445",
    "sg:postcode":"43056",
    "sg:province":"OH",
    "sg:tags":[
        "automobile"
    ],
    "sg:website":"www.napaonline.com",
    "wof:name":"NAPA Auto Parts",
    "wof:placetype":"venue"
},
  "geometry": {"coordinates":[-82.426241,40.036858],"type":"Point"}
}