{
  "type": "Feature",
  "properties": {
    "iso:country":"US",
    "sg:address":"621 Miami St",
    "sg:city":"Akron",
    "sg:classifiers":[
        {
            "category":"Wholesale",
            "subcategory":"Electrical",
            "type":"Manufacturing & Wholesale Goods"
        }
    ],
    "sg:phone":"+1 330 535 4153",
    "sg:postcode":"44311",
    "sg:province":"OH",
    "sg:tags":[
        "transmission",
        "equipment",
        "power"
    ],
    "wof:name":"Applied Industrial Tech Inc",
    "wof:placetype":"venue"
},
  "geometry": {"coordinates":[-81.52269800000001,41.065961],"type":"Point"}
}