{
  "type": "Feature",
  "properties": {
    "addr:full": "621 Miami St Akron OH 44311",
    "addr:housenumber": "621",
    "addr:postcode": "44311",
    "addr:street": "Miami St",
    "iso:country": "US",
    "sg:address": "621 Miami St",
    "sg:city": "Akron",
    "sg:classifiers": [
      {
        "category": "Wholesale",
        "subcategory": "Electrical",
        "type": "Manufacturing \u0026 Wholesale Goods"
      }
    ],
    "sg:phone": "+1 330 535 4153",
    "sg:postcode": "44311",
    "sg:province": "OH",
    "sg:tags": [
      "transmission",
      "equipment",
      "power"
    ],
    "wof:name": "Applied Industrial Tech Inc",
    "wof:placetype": "venue"
  },
  "geometry": {"coordinates":[-81.522698,41.065961],"type":"Point"}
}
