{
  "type": "Feature",
  "properties": {
    "addr:full": "409 S Grant Ave Columbus OH 43215",
    "addr:housenumber": "409",
    "addr:postcode": "43215",
    "addr:street": "S Grant Ave",
    "iso:country": "US",
    "sg:address": "409 S Grant Ave",
    "sg:city": "Columbus",
    "sg:classifiers": [
      {
        "category": "Social Services",
        "type": "Services"
      }
    ],
    "sg:phone": "+1 614 221 8890",
    "sg:postcode": "43215",
    "sg:province": "OH",
    "sg:tags": [
      "organization",
      "welfare"
    ],
    "wof:name": "Salvation Army",
    "wof:placetype": "venue"
  },
  "geometry": {"coordinates":[-82.989508,39.954919],"type":"Point"}
}
