{
  "type": "Feature",
  "properties": {
    "addr:full": "10727 Falls Creek Ln Dayton OH 45458",
    "addr:housenumber": "10727",
    "addr:postcode": "45458",
    "addr:street": "Falls Creek Ln",
    "iso:country": "US",
    "sg:address": "10727 Falls Creek Ln",
    "sg:city": "Dayton",
    "sg:classifiers": [
      {
        "category": "Shopping",
        "subcategory": "Computers \u0026 Home Electronics",
        "type": "Retail Goods"
      }
    ],
    "sg:phone": "+1 937 885 5508",
    "sg:postcode": "45458",
    "sg:province": "OH",
    "wof:name": "Cranel Inc",
    "wof:placetype": "venue"
  },
  "geometry": {"coordinates":[-84.192343,39.588373],"type":"Point"}
}
