{
  "type": "Feature",
  "properties": {
    "addr:full":"20 Mansfield Ave Mount Vernon OH 43050",
    "addr:housenumber":"20",
    "addr:postcode":"43050",
    "addr:street":"Mansfield Ave",
    "iso:country":"US",
    "sg:address":"20 Mansfield Ave",
    "sg:city":"Mount Vernon",
    "sg:classifiers":[
        {
            "category":"Building & Trades",
            "subcategory":"Plumbing",
            "type":"Services"
        }
    ],
    "sg:phone":"+1 740 392 0645",
    "sg:postcode":"43050",
    "sg:province":"OH",
    "sg:tags":[
        "contractor"
    ],
    "wof:name":"J & B Heating & Cooling",
    "wof:placetype":"venue"
},
  "geometry": {"coordinates":[-82.48580699999999,40.402424],"type":"Point"}
}