{
  "type": "Feature",
  "properties": {
    "iso:country":"US",
    "sg:address":"4141 Hamilton Ave",
    "sg:city":"Cincinnati",
    "sg:classifiers":[
        {
            "category":"Professional",
            "subcategory":"Accounting & Tax Preparation",
            "type":"Services"
        }
    ],
    "sg:phone":"+1 513 542 0700",
    "sg:postcode":"45223",
    "sg:province":"OH",
    "sg:tags":[
        "return",
        "filing"
    ],
    "wof:name":"Tax Professionals",
    "wof:placetype":"venue"
},
  "geometry": {"coordinates":[-84.539368,39.161052],"type":"Point"}
}