{
  "type": "Feature",
  "properties": {
    "addr:full": "106 E High St Bryan OH 43506",
    "addr:housenumber": "106",
    "addr:postcode": "43506",
    "addr:street": "E High St",
    "iso:country": "US",
    "sg:address": "106 E High St",
    "sg:city": "Bryan",
    "sg:classifiers": [
      {
        "category": "Professional",
        "type": "Services"
      }
    ],
    "sg:phone": "+1 419 636 3966",
    "sg:postcode": "43506",
    "sg:province": "OH",
    "sg:tags": [
      "establishment"
    ],
    "wof:name": "Stadium",
    "wof:placetype": "venue"
  },
  "geometry": {"coordinates":[-84.55041,41.474533],"type":"Point"}
}
