{
  "type": "Feature",
  "properties": {
    "iso:country":"US",
    "sg:address":"1450 Som Center Rd",
    "sg:city":"Cleveland",
    "sg:classifiers":[
        {
            "category":"Shopping",
            "subcategory":"Clothing, Apparel, & Fashions",
            "type":"Retail Goods"
        }
    ],
    "sg:phone":"+1 440 461 4247",
    "sg:postcode":"44124",
    "sg:province":"OH",
    "sg:tags":[
        "wig",
        "toupee",
        "hairpiece"
    ],
    "wof:name":"MJG & Co",
    "wof:placetype":"venue"
},
  "geometry": {"coordinates":[-81.438777,41.522904],"type":"Point"}
}