{
  "type": "Feature",
  "properties": {
    "addr:full": "360 E Summit St Kent OH 44240",
    "addr:housenumber": "360",
    "addr:postcode": "44240",
    "addr:street": "E Summit St",
    "iso:country": "US",
    "sg:address": "360 E Summit St",
    "sg:city": "Kent",
    "sg:classifiers": [
      {
        "category": "Personal",
        "subcategory": "Beauty Salon",
        "type": "Services"
      }
    ],
    "sg:phone": "+1 330 673 6400",
    "sg:postcode": "44240",
    "sg:province": "OH",
    "wof:name": "Susan's Hair Designs",
    "wof:placetype": "venue"
  },
  "geometry": {"coordinates":[-81.354041,41.150016],"type":"Point"}
}
