{
  "type": "Feature",
  "properties": {
    "iso:country":"US",
    "sg:address":"360 E Summit St",
    "sg:city":"Kent",
    "sg:classifiers":[
        {
            "category":"Personal",
            "subcategory":"Beauty Salon",
            "type":"Services"
        }
    ],
    "sg:phone":"+1 330 673 6400",
    "sg:postcode":"44240",
    "sg:province":"OH",
    "wof:name":"Susan's Hair Designs",
    "wof:placetype":"venue"
},
  "geometry": {"coordinates":[-81.354041,41.150016],"type":"Point"}
}