{
  "type": "Feature",
  "properties": {
    "iso:country":"US",
    "sg:address":"8120 Tyler Blvd",
    "sg:city":"Mentor",
    "sg:classifiers":[
        {
            "category":"Freight",
            "type":"Transportation"
        },
        {
            "category":"Wholesale",
            "subcategory":"Electrical",
            "type":"Manufacturing & Wholesale Goods"
        }
    ],
    "sg:phone":"+1 440 255 5678",
    "sg:postcode":"44060",
    "sg:province":"OH",
    "sg:tags":[
        "warehouse",
        "distribution",
        "appliance",
        "center"
    ],
    "wof:name":"Royal Appliance Mfg Co",
    "wof:placetype":"venue"
},
  "geometry": {"coordinates":[-81.357597,41.680094],"type":"Point"}
}