{
  "type": "Feature",
  "properties": {
    "addr:full": "420 State Rte 7 Brookfield OH 44403",
    "addr:housenumber": "420",
    "addr:postcode": "44403",
    "addr:street": "State Rte 7",
    "iso:country": "US",
    "sg:address": "420 State Rte 7",
    "sg:city": "Brookfield",
    "sg:classifiers": [
      {
        "category": "Shopping",
        "subcategory": "Clothing, Apparel, \u0026 Fashions",
        "type": "Retail Goods"
      }
    ],
    "sg:phone": "+1 330 448 4476",
    "sg:postcode": "44403",
    "sg:province": "OH",
    "sg:tags": [
      "shop",
      "bridal"
    ],
    "wof:name": "K's Bridal Emporium",
    "wof:placetype": "venue"
  },
  "geometry": {"coordinates":[-80.568123,41.231849],"type":"Point"}
}
