{
  "type": "Feature",
  "properties": {
    "addr:full": "3680 Easton Market Columbus OH 43219",
    "addr:housenumber": "3680",
    "addr:postcode": "43219",
    "addr:street": "Easton",
    "iso:country": "US",
    "sg:address": "3680 Easton Market",
    "sg:city": "Columbus",
    "sg:classifiers": [
      {
        "category": "Shopping",
        "subcategory": "Hobbies, Toys, \u0026 Games",
        "type": "Retail Goods"
      }
    ],
    "sg:phone": "+1 614 475 4123",
    "sg:postcode": "43219",
    "sg:province": "OH",
    "sg:tags": [
      "craft",
      "supply"
    ],
    "sg:website": "www.michaels.com",
    "wof:name": "Michaels Stores",
    "wof:placetype": "venue"
  },
  "geometry": {"coordinates":[-82.922837,40.051444],"type":"Point"}
}
