{
  "type": "Feature",
  "properties": {
    "addr:full":"14 N Beech St Oxford IN 45056",
    "addr:housenumber":"14",
    "addr:postcode":"45056",
    "addr:street":"N Beech St",
    "iso:country":"US",
    "sg:address":"14 N Beech St",
    "sg:city":"Oxford",
    "sg:classifiers":[
        {
            "category":"Shopping",
            "subcategory":"Used Merchandise",
            "type":"Retail Goods"
        }
    ],
    "sg:phone":"+1 513 523 0121",
    "sg:postcode":"45056",
    "sg:province":"IN",
    "sg:tags":[
        "antique"
    ],
    "wof:name":"Bird House Antiques",
    "wof:placetype":"venue"
},
  "geometry": {"coordinates":[-84.744073,39.510904],"type":"Point"}
}