{
  "type": "Feature",
  "properties": {
    "addr:full": "1916 36th St NW Canton OH 44709",
    "addr:housenumber": "1916",
    "addr:postcode": "44709",
    "addr:street": "36Th St Nw",
    "iso:country": "US",
    "sg:address": "1916 36th St NW",
    "sg:city": "Canton",
    "sg:classifiers": [
      {
        "category": "Professional",
        "type": "Services"
      }
    ],
    "sg:phone": "+1 330 492 6518",
    "sg:postcode": "44709",
    "sg:province": "OH",
    "wof:name": "Margaret N McCaulley",
    "wof:placetype": "venue"
  },
  "geometry": {"coordinates":[-81.39123,40.83797],"type":"Point"}
}
