{
  "type": "Feature",
  "properties": {
    "iso:country":"US",
    "sg:address":"1609 Mahoning Ave",
    "sg:city":"Youngstown",
    "sg:classifiers":[
        {
            "category":"Home & Garden",
            "subcategory":"Building Materials",
            "type":"Retail Goods"
        }
    ],
    "sg:phone":"+1 330 792 9335",
    "sg:postcode":"44509",
    "sg:province":"OH",
    "sg:tags":[
        "windows"
    ],
    "wof:name":"Hassay Construction",
    "wof:placetype":"venue"
},
  "geometry": {"coordinates":[-80.681455,41.101842],"type":"Point"}
}