{
  "type": "Feature",
  "properties": {
    "iso:country":"US",
    "sg:address":"6727 Hill Ave",
    "sg:city":"Toledo",
    "sg:classifiers":[
        {
            "category":"Professional",
            "type":"Services"
        }
    ],
    "sg:phone":"+1 419 861 3444",
    "sg:postcode":"43615",
    "sg:province":"OH",
    "wof:name":"Coker Virginia M",
    "wof:placetype":"venue"
},
  "geometry": {"coordinates":[-83.70316099999999,41.638759],"type":"Point"}
}