{
  "type": "Feature",
  "properties": {
    "iso:country":"US",
    "sg:address":"6438 Ridge Rd",
    "sg:city":"Wadsworth",
    "sg:classifiers":[
        {
            "category":"Professional",
            "subcategory":"Engineering",
            "type":"Services"
        }
    ],
    "sg:phone":"+1 330 239 3131",
    "sg:postcode":"44274",
    "sg:province":"OH",
    "sg:tags":[
        "engineer"
    ],
    "wof:name":"HRSG Inc",
    "wof:placetype":"venue"
},
  "geometry": {"coordinates":[-81.73539700000001,41.114491],"type":"Point"}
}