{
  "type": "Feature",
  "properties": {
    "addr:full":"15286 Pearl Rd Cleveland OH 44136",
    "addr:housenumber":"15286",
    "addr:postcode":"44136",
    "addr:street":"Pearl Rd",
    "iso:country":"US",
    "sg:address":"15286 Pearl Rd",
    "sg:city":"Cleveland",
    "sg:classifiers":[
        {
            "category":"Retail",
            "subcategory":"Photofinishing",
            "type":"Services"
        }
    ],
    "sg:phone":"+1 440 238 5559",
    "sg:postcode":"44136",
    "sg:province":"OH",
    "sg:tags":[
        "photo",
        "finishing"
    ],
    "wof:name":"Snapshot Photo Ctr",
    "wof:placetype":"venue"
},
  "geometry": {"coordinates":[-81.83528699999999,41.304938],"type":"Point"}
}