{
  "type": "Feature",
  "properties": {
    "addr:full":"6363 Fiesta Dr Columbus OH 43235",
    "addr:housenumber":"6363",
    "addr:postcode":"43235",
    "addr:street":"Fiesta Dr",
    "iso:country":"US",
    "sg:address":"6363 Fiesta Dr",
    "sg:city":"Columbus",
    "sg:classifiers":[
        {
            "category":"Real Estate",
            "subcategory":"Developer",
            "type":"Services"
        }
    ],
    "sg:phone":"+1 614 766 6363",
    "sg:postcode":"43235",
    "sg:province":"OH",
    "wof:name":"Fiesta",
    "wof:placetype":"venue"
},
  "geometry": {"coordinates":[-83.06381399999999,40.086286],"type":"Point"}
}