{
  "type": "Feature",
  "properties": {
    "addr:full":"2701 Sunset Blvd Steubenville OH 43952",
    "addr:housenumber":"2701",
    "addr:postcode":"43952",
    "addr:street":"Sunset Blvd",
    "iso:country":"US",
    "sg:address":"2701 Sunset Blvd",
    "sg:city":"Steubenville",
    "sg:classifiers":[
        {
            "category":"Autos & Motor Vehicles",
            "subcategory":"Fuel & Gas Station",
            "type":"Retail Goods"
        }
    ],
    "sg:phone":"+1 740 266 2605",
    "sg:postcode":"43952",
    "sg:province":"OH",
    "sg:tags":[
        "station",
        "gasoline"
    ],
    "wof:name":"BP",
    "wof:placetype":"venue"
},
  "geometry": {"coordinates":[-80.65230699999999,40.374441],"type":"Point"}
}