{
  "type": "Feature",
  "properties": {
    "addr:full": "225 Cedar Hill Rd Lancaster OH 43130",
    "addr:housenumber": "225",
    "addr:postcode": "43130",
    "addr:street": "Cedar Hill Rd",
    "iso:country": "US",
    "sg:address": "225 Cedar Hill Rd",
    "sg:city": "Lancaster",
    "sg:classifiers": [
      {
        "category": "Manufacturing",
        "subcategory": "Tools \u0026 Machinery",
        "type": "Manufacturing \u0026 Wholesale Goods"
      }
    ],
    "sg:phone": "+1 740 681 1326",
    "sg:postcode": "43130",
    "sg:province": "OH",
    "sg:tags": [
      "machine",
      "shop"
    ],
    "wof:name": "J D Enterprises Inc",
    "wof:placetype": "venue"
  },
  "geometry": {"coordinates":[-82.615314,39.713428],"type":"Point"}
}
