{
  "type": "Feature",
  "properties": {
    "addr:full":"835 Marilyn Dr Wooster OH 44691",
    "addr:housenumber":"835",
    "addr:postcode":"44691",
    "addr:street":"Marilyn Dr",
    "iso:country":"US",
    "sg:address":"835 Marilyn Dr",
    "sg:city":"Wooster",
    "sg:classifiers":[
        {
            "category":"Professional",
            "subcategory":"Business Services",
            "type":"Services"
        }
    ],
    "sg:phone":"+1 330 262 6480",
    "sg:postcode":"44691",
    "sg:province":"OH",
    "sg:tags":[
        "translator",
        "interpreter"
    ],
    "wof:name":"Tongue-Tied Inc",
    "wof:placetype":"venue"
},
  "geometry": {"coordinates":[-81.95342599999999,40.823455],"type":"Point"}
}