{
  "type": "Feature",
  "properties": {
    "addr:full": "10621 Rochester Rd East Rochester OH 44625",
    "addr:housenumber": "10621",
    "addr:postcode": "44625",
    "addr:street": "Rochester Rd",
    "iso:country": "US",
    "sg:address": "10621 Rochester Rd",
    "sg:city": "East Rochester",
    "sg:classifiers": [
      {
        "category": "Government",
        "subcategory": "Office",
        "type": "Public Place"
      }
    ],
    "sg:phone": "+1 330 894 2110",
    "sg:postcode": "44625",
    "sg:province": "OH",
    "sg:tags": [
      "village"
    ],
    "wof:name": "West Twp Garages",
    "wof:placetype": "venue"
  },
  "geometry": {"coordinates":[-81.034809,40.747203],"type":"Point"}
}
