{
  "type": "Feature",
  "properties": {
    "addr:full": "33 Fairington Oval Aurora OH 44202",
    "addr:housenumber": "33",
    "addr:postcode": "44202",
    "addr:street": "Fairington Oval",
    "iso:country": "US",
    "sg:address": "33 Fairington Oval",
    "sg:city": "Aurora",
    "sg:classifiers": [
      {
        "category": "Professional",
        "subcategory": "Management \u0026 Consulting",
        "type": "Services"
      }
    ],
    "sg:phone": "+1 330 995 2611",
    "sg:postcode": "44202",
    "sg:province": "OH",
    "sg:tags": [
      "consultant",
      "hospital",
      "radiology"
    ],
    "wof:name": "A F Naylor Co Inc",
    "wof:placetype": "venue"
  },
  "geometry": {"coordinates":[-81.368507,41.299789],"type":"Point"}
}
