{
  "type": "Feature",
  "properties": {
    "iso:country":"US",
    "sg:address":"2181 Mock Rd",
    "sg:city":"Columbus",
    "sg:classifiers":[
        {
            "category":"Organizations",
            "subcategory":"Religious Organization",
            "type":"Services"
        }
    ],
    "sg:phone":"+1 614 471 0549",
    "sg:postcode":"43219",
    "sg:province":"OH",
    "sg:tags":[
        "church"
    ],
    "sg:website":"www.lfac.org",
    "wof:name":"Living Faith Apostolic Church",
    "wof:placetype":"venue"
},
  "geometry": {"coordinates":[-82.952253,40.011635],"type":"Point"}
}