{
  "type": "Feature",
  "properties": {
    "iso:country":"US",
    "sg:address":"120 S Wayne St",
    "sg:city":"Fort Recovery",
    "sg:classifiers":[
        {
            "category":"Banks & Credit Unions",
            "subcategory":"Bank",
            "type":"Services"
        }
    ],
    "sg:phone":"+1 419 375 4149",
    "sg:postcode":"45846",
    "sg:province":"OH",
    "wof:name":"Mercer Savings Bank",
    "wof:placetype":"venue"
},
  "geometry": {"coordinates":[-84.779745,40.412314],"type":"Point"}
}