{
  "type": "Feature",
  "properties": {
    "addr:full":"120 S Wayne St Fort Recovery OH 45846",
    "addr:housenumber":"120",
    "addr:postcode":"45846",
    "addr:street":"S Wayne St",
    "iso:country":"US",
    "sg:address":"120 S Wayne St",
    "sg:city":"Fort Recovery",
    "sg:classifiers":[
        {
            "category":"Banks & Credit Unions",
            "subcategory":"Bank",
            "type":"Services"
        }
    ],
    "sg:phone":"+1 419 375 4149",
    "sg:postcode":"45846",
    "sg:province":"OH",
    "wof:name":"Mercer Savings Bank",
    "wof:placetype":"venue"
},
  "geometry": {"coordinates":[-84.77974500000001,40.412314],"type":"Point"}
}