{
  "type": "Feature",
  "properties": {
    "iso:country":"US",
    "sg:address":"380 Summit Ave",
    "sg:city":"Steubenville",
    "sg:classifiers":[
        {
            "category":"Health Services",
            "subcategory":"Hospital",
            "type":"Services"
        }
    ],
    "sg:phone":"+1 740 283 7000",
    "sg:postcode":"43952",
    "sg:province":"OH",
    "sg:website":"www.fm94.com",
    "wof:name":"Trinity Health Systems",
    "wof:placetype":"venue"
},
  "geometry": {"coordinates":[-80.62562,40.358231],"type":"Point"}
}