{
  "type": "Feature",
  "properties": {
    "iso:country":"US",
    "sg:address":"7881 Root Rd",
    "sg:city":"North Ridgeville",
    "sg:classifiers":[
        {
            "category":"Freight",
            "type":"Transportation"
        }
    ],
    "sg:phone":"+1 440 353 1076",
    "sg:postcode":"44039",
    "sg:province":"OH",
    "wof:name":"Reliable Transportation",
    "wof:placetype":"venue"
},
  "geometry": {"coordinates":[-82.005685,41.378869],"type":"Point"}
}