{
  "type": "Feature",
  "properties": {
    "addr:full": "8168 Otterbein Trl NW Lancaster OH 43130",
    "addr:postcode": "8168;43130",
    "addr:street": "Otterbein Trl Nw",
    "iso:country": "US",
    "sg:address": "8168 Otterbein Trl NW",
    "sg:city": "Lancaster",
    "sg:classifiers": [
      {
        "category": "Building \u0026 Trades",
        "subcategory": "Construction",
        "type": "Services"
      }
    ],
    "sg:phone": "+1 614 837 1562",
    "sg:postcode": "43130",
    "sg:province": "OH",
    "sg:tags": [
      "housing"
    ],
    "wof:name": "Sebastian Homes Inc",
    "wof:placetype": "venue"
  },
  "geometry": {"coordinates":[-82.755812,39.737444],"type":"Point"}
}
