{
  "type": "Feature",
  "properties": {
    "iso:country":"US",
    "sg:address":"8168 Otterbein Trl NW",
    "sg:city":"Lancaster",
    "sg:classifiers":[
        {
            "category":"Building & Trades",
            "subcategory":"Construction",
            "type":"Services"
        }
    ],
    "sg:phone":"+1 614 837 1562",
    "sg:postcode":"43130",
    "sg:province":"OH",
    "sg:tags":[
        "housing"
    ],
    "wof:name":"Sebastian Homes Inc",
    "wof:placetype":"venue"
},
  "geometry": {"coordinates":[-82.755812,39.737444],"type":"Point"}
}