{
  "type": "Feature",
  "properties": {
    "addr:full": "18435 State Rd Van Wert OH 45891",
    "addr:housenumber": "18435",
    "addr:postcode": "45891",
    "addr:street": "State Rd",
    "iso:country": "US",
    "sg:address": "18435 State Rd",
    "sg:city": "Van Wert",
    "sg:classifiers": [
      {
        "category": "Arts \u0026 Performance",
        "subcategory": "Theater",
        "type": "Entertainment"
      }
    ],
    "sg:phone": "+1 419 968 2521",
    "sg:postcode": "45891",
    "sg:province": "OH",
    "sg:tags": [
      "group"
    ],
    "wof:name": "Dinnertainment",
    "wof:placetype": "venue"
  },
  "geometry": {"coordinates":[-84.468526,40.815664],"type":"Point"}
}
