{
  "type": "Feature",
  "properties": {
    "iso:country":"US",
    "sg:address":"4711 Venice Rd",
    "sg:city":"Sandusky",
    "sg:classifiers":[
        {
            "category":"Travel",
            "subcategory":"Campground",
            "type":"Entertainment"
        }
    ],
    "sg:phone":"+1 419 621 7900",
    "sg:postcode":"44870",
    "sg:province":"OH",
    "wof:name":"Cold Creek Trout Camp",
    "wof:placetype":"venue"
},
  "geometry": {"coordinates":[-82.770064,41.445526],"type":"Point"}
}