{
  "type": "Feature",
  "properties": {
    "addr:full":"3534 Behymer Rd Cincinnati OH 45245",
    "addr:housenumber":"3534",
    "addr:postcode":"45245",
    "addr:street":"Behymer Rd",
    "iso:country":"US",
    "sg:address":"3534 Behymer Rd",
    "sg:city":"Cincinnati",
    "sg:classifiers":[
        {
            "category":"Building & Trades",
            "subcategory":"Construction",
            "type":"Services"
        }
    ],
    "sg:phone":"+1 513 752 8028",
    "sg:postcode":"45245",
    "sg:province":"OH",
    "sg:tags":[
        "residential"
    ],
    "wof:name":"Crockett Brothers Creative",
    "wof:placetype":"venue"
},
  "geometry": {"coordinates":[-84.274959,39.03134],"type":"Point"}
}