{
  "type": "Feature",
  "properties": {
    "addr:full": "4690 Interstate Dr Cincinnati OH 45246",
    "addr:housenumber": "4690",
    "addr:postcode": "45246",
    "addr:street": "Interstate Dr",
    "iso:country": "US",
    "sg:address": "4690 Interstate Dr",
    "sg:city": "Cincinnati",
    "sg:classifiers": [
      {
        "category": "Manufacturing",
        "subcategory": "Food",
        "type": "Manufacturing \u0026 Wholesale Goods"
      }
    ],
    "sg:phone": "+1 513 874 3305",
    "sg:postcode": "45246",
    "sg:province": "OH",
    "sg:tags": [
      "product",
      "health"
    ],
    "wof:name": "Parrillo Performance",
    "wof:placetype": "venue"
  },
  "geometry": {"coordinates":[-84.467466,39.308822],"type":"Point"}
}
