{
  "type": "Feature",
  "properties": {
    "iso:country":"US",
    "sg:address":"4690 Interstate Dr",
    "sg:city":"Cincinnati",
    "sg:classifiers":[
        {
            "category":"Manufacturing",
            "subcategory":"Food",
            "type":"Manufacturing & Wholesale Goods"
        }
    ],
    "sg:phone":"+1 513 874 3305",
    "sg:postcode":"45246",
    "sg:province":"OH",
    "sg:tags":[
        "product",
        "health"
    ],
    "wof:name":"Parrillo Performance",
    "wof:placetype":"venue"
},
  "geometry": {"coordinates":[-84.467466,39.308822],"type":"Point"}
}