{
  "type": "Feature",
  "properties": {
    "addr:full":"11999 Stratton Rd Salem OH 44460",
    "addr:housenumber":"11999",
    "addr:postcode":"44460",
    "addr:street":"Stratton Rd",
    "iso:country":"US",
    "sg:address":"11999 Stratton Rd",
    "sg:city":"Salem",
    "sg:classifiers":[
        {
            "category":"Food & Beverages",
            "subcategory":"Groceries & Convenience Stores",
            "type":"Retail Goods"
        }
    ],
    "sg:phone":"+1 330 337 0468",
    "sg:postcode":"44460",
    "sg:province":"OH",
    "wof:name":"Roberts Country Store Inc",
    "wof:placetype":"venue"
},
  "geometry": {"coordinates":[-80.88585399999999,40.956672],"type":"Point"}
}