{
  "type": "Feature",
  "properties": {
    "addr:full": "865 Howland Wilson Rd NE Warren OH 44484",
    "addr:housenumber": "865",
    "addr:postcode": "44484",
    "addr:street": "Howland Wilson Rd Ne",
    "iso:country": "US",
    "sg:address": "865 Howland Wilson Rd NE",
    "sg:city": "Warren",
    "sg:classifiers": [
      {
        "category": "Building \u0026 Trades",
        "subcategory": "Landscaping Services",
        "type": "Services"
      }
    ],
    "sg:phone": "+1 330 856 7427",
    "sg:postcode": "44484",
    "sg:province": "OH",
    "sg:tags": [
      "landscape",
      "contractor"
    ],
    "wof:name": "Preferred Services",
    "wof:placetype": "venue"
  },
  "geometry": {"coordinates":[-80.730943,41.247094],"type":"Point"}
}
