{
  "type": "Feature",
  "properties": {
    "addr:full":"18 Bechtle Ave Springfield OH 45504",
    "addr:housenumber":"18",
    "addr:postcode":"45504",
    "addr:street":"Bechtle Ave",
    "iso:country":"US",
    "sg:address":"18 Bechtle Ave",
    "sg:city":"Springfield",
    "sg:classifiers":[
        {
            "category":"Manufacturing",
            "subcategory":"Metals",
            "type":"Manufacturing & Wholesale Goods"
        }
    ],
    "sg:phone":"+1 937 323 6339",
    "sg:postcode":"45504",
    "sg:province":"OH",
    "sg:tags":[
        "brass",
        "foundry",
        "bronze"
    ],
    "sg:website":"www.palmermfg.com",
    "wof:name":"Palmer Manufacturing & Supply",
    "wof:placetype":"venue"
},
  "geometry": {"coordinates":[-83.83346299999999,39.92636],"type":"Point"}
}