{
  "type": "Feature",
  "properties": {
    "addr:full": "18 Bechtle Ave Springfield OH 45504",
    "addr:housenumber": "18",
    "addr:postcode": "45504",
    "addr:street": "Bechtle Ave",
    "iso:country": "US",
    "sg:address": "18 Bechtle Ave",
    "sg:city": "Springfield",
    "sg:classifiers": [
      {
        "category": "Manufacturing",
        "subcategory": "Metals",
        "type": "Manufacturing \u0026 Wholesale Goods"
      }
    ],
    "sg:phone": "+1 937 323 6339",
    "sg:postcode": "45504",
    "sg:province": "OH",
    "sg:tags": [
      "brass",
      "foundry",
      "bronze"
    ],
    "sg:website": "www.palmermfg.com",
    "wof:name": "Palmer Manufacturing \u0026 Supply",
    "wof:placetype": "venue"
  },
  "geometry": {"coordinates":[-83.833463,39.92636],"type":"Point"}
}
