{
  "type": "Feature",
  "properties": {
    "addr:full": "536 Main St Hamilton OH 45013",
    "addr:housenumber": "536",
    "addr:postcode": "45013",
    "addr:street": "Main St",
    "iso:country": "US",
    "sg:address": "536 Main St",
    "sg:city": "Hamilton",
    "sg:classifiers": [
      {
        "category": "Shopping",
        "subcategory": "Shoes",
        "type": "Retail Goods"
      }
    ],
    "sg:phone": "+1 513 893 0021",
    "sg:postcode": "45013",
    "sg:province": "OH",
    "wof:name": "Willis For Women",
    "wof:placetype": "venue"
  },
  "geometry": {"coordinates":[-84.572903,39.406501],"type":"Point"}
}
