{
  "type": "Feature",
  "properties": {
    "addr:full":"11897 London Rd Orient OH 43146",
    "addr:housenumber":"11897",
    "addr:postcode":"43146",
    "addr:street":"London Rd",
    "iso:country":"US",
    "sg:address":"11897 London Rd",
    "sg:city":"Orient",
    "sg:classifiers":[
        {
            "category":"Wholesale",
            "subcategory":"Farm Supplies",
            "type":"Manufacturing & Wholesale Goods"
        }
    ],
    "sg:phone":"+1 614 877 3495",
    "sg:postcode":"43146",
    "sg:province":"OH",
    "sg:tags":[
        "grain"
    ],
    "wof:name":"Champagn Landmark Inc",
    "wof:placetype":"venue"
},
  "geometry": {"coordinates":[-83.205499,39.768833],"type":"Point"}
}