{
  "type": "Feature",
  "properties": {
    "addr:full": "3163 E Main St Columbus OH 43213",
    "addr:housenumber": "3163",
    "addr:postcode": "43213",
    "addr:street": "E Main St",
    "iso:country": "US",
    "sg:address": "3163 E Main St",
    "sg:city": "Columbus",
    "sg:classifiers": [
      {
        "category": "Retail",
        "subcategory": "Auto Repair",
        "type": "Services"
      }
    ],
    "sg:phone": "+1 614 231 0082",
    "sg:postcode": "43213",
    "sg:province": "OH",
    "sg:tags": [
      "transmission"
    ],
    "wof:name": "Cottman Transmission Ctr",
    "wof:placetype": "venue"
  },
  "geometry": {"coordinates":[-82.913476,39.956466],"type":"Point"}
}
