{
  "type": "Feature",
  "properties": {
    "iso:country":"US",
    "sg:address":"5600 Poe Ave",
    "sg:city":"Dayton",
    "sg:classifiers":[
        {
            "category":"Recreation",
            "type":"Entertainment"
        }
    ],
    "sg:phone":"+1 937 277 1681",
    "sg:postcode":"45414",
    "sg:province":"OH",
    "sg:tags":[
        "merchandise"
    ],
    "wof:name":"Schertle Galleries",
    "wof:placetype":"venue"
},
  "geometry": {"coordinates":[-84.18915200000001,39.832846],"type":"Point"}
}