{
  "type": "Feature",
  "properties": {
    "addr:full": "1245 Park Plaza Dr Columbus OH 43213",
    "addr:housenumber": "1245",
    "addr:postcode": "43213",
    "addr:street": "Park Plaza Dr",
    "iso:country": "US",
    "sg:address": "1245 Park Plaza Dr",
    "sg:city": "Columbus",
    "sg:classifiers": [
      {
        "category": "Real Estate",
        "subcategory": "Real Estate Operator",
        "type": "Services"
      }
    ],
    "sg:phone": "+1 614 864 0649",
    "sg:postcode": "43213",
    "sg:province": "OH",
    "sg:tags": [
      "building",
      "apartment"
    ],
    "wof:name": "Plaza Properties",
    "wof:placetype": "venue"
  },
  "geometry": {"coordinates":[-82.849203,39.956003],"type":"Point"}
}
