{
  "type": "Feature",
  "properties": {
    "addr:full":"2546 Old 122 Rd Lebanon OH 45036",
    "addr:housenumber":"2546;122",
    "addr:postcode":"45036",
    "addr:street":"Old;Rd",
    "iso:country":"US",
    "sg:address":"2546 Old 122 Rd",
    "sg:city":"Lebanon",
    "sg:classifiers":[
        {
            "category":"Farming",
            "subcategory":"Farm",
            "type":"Manufacturing & Wholesale Goods"
        }
    ],
    "sg:phone":"+1 513 932 4629",
    "sg:postcode":"45036",
    "sg:province":"OH",
    "sg:tags":[
        "feedlot",
        "cattle",
        "crop",
        "beef",
        "general"
    ],
    "wof:name":"Miller F&R Farm",
    "wof:placetype":"venue"
},
  "geometry": {"coordinates":[-84.15206499999999,39.493847],"type":"Point"}
}