{
  "type": "Feature",
  "properties": {
    "addr:full": "3784 State Rte 303 Ravenna OH 44266",
    "addr:housenumber": "3784",
    "addr:postcode": "44266",
    "addr:street": "State Rte 303",
    "iso:country": "US",
    "sg:address": "3784 State Rte 303",
    "sg:city": "Ravenna",
    "sg:classifiers": [
      {
        "category": "Utilities",
        "subcategory": "Fuel Oil \u0026 Lpg",
        "type": "Services"
      }
    ],
    "sg:phone": "+1 330 626 5212",
    "sg:postcode": "44266",
    "sg:province": "OH",
    "sg:tags": [
      "liquefied",
      "gas",
      "petroleum"
    ],
    "wof:name": "Portage Propane",
    "wof:placetype": "venue"
  },
  "geometry": {"coordinates":[-81.262479,41.244966],"type":"Point"}
}
