{
  "type": "Feature",
  "properties": {
    "addr:full": "9621 Lansford Dr Cincinnati OH 45242",
    "addr:housenumber": "9621",
    "addr:postcode": "45242",
    "addr:street": "Lansford Dr",
    "iso:country": "US",
    "sg:address": "9621 Lansford Dr",
    "sg:city": "Cincinnati",
    "sg:classifiers": [
      {
        "category": "Wholesale",
        "subcategory": "Electrical",
        "type": "Manufacturing \u0026 Wholesale Goods"
      }
    ],
    "sg:phone": "+1 513 793 8093",
    "sg:postcode": "45242",
    "sg:province": "OH",
    "sg:tags": [
      "equipment",
      "janitorial",
      "supply"
    ],
    "wof:name": "Rle",
    "wof:placetype": "venue"
  },
  "geometry": {"coordinates":[-84.384712,39.2309],"type":"Point"}
}
