{
  "type": "Feature",
  "properties": {
    "iso:country":"US",
    "sg:address":"9621 Lansford Dr",
    "sg:city":"Cincinnati",
    "sg:classifiers":[
        {
            "category":"Wholesale",
            "subcategory":"Electrical",
            "type":"Manufacturing & Wholesale Goods"
        }
    ],
    "sg:phone":"+1 513 793 8093",
    "sg:postcode":"45242",
    "sg:province":"OH",
    "sg:tags":[
        "equipment",
        "janitorial",
        "supply"
    ],
    "wof:name":"Rle",
    "wof:placetype":"venue"
},
  "geometry": {"coordinates":[-84.38471199999999,39.2309],"type":"Point"}
}