{
  "type": "Feature",
  "properties": {
    "iso:country":"US",
    "sg:address":"27879 Chagrin Blvd",
    "sg:city":"Beachwood",
    "sg:classifiers":[
        {
            "category":"Retail",
            "subcategory":"Repair Shop",
            "type":"Services"
        },
        {
            "category":"Shopping",
            "subcategory":"Crafts & Fabrics",
            "type":"Retail Goods"
        },
        {
            "category":"Building & Trades",
            "subcategory":"Construction",
            "type":"Services"
        },
        {
            "category":"Home & Garden",
            "subcategory":"Furniture",
            "type":"Retail Goods"
        }
    ],
    "sg:phone":"+1 216 360 9176",
    "sg:postcode":"44122",
    "sg:province":"OH",
    "sg:tags":[
        "interior",
        "reupholstery",
        "design",
        "store"
    ],
    "sg:website":"www.calicocorners.com",
    "wof:name":"Calico Corners",
    "wof:placetype":"venue"
},
  "geometry": {"coordinates":[-81.48191199999999,41.462487],"type":"Point"}
}