{
  "type": "Feature",
  "properties": {
    "iso:country":"US",
    "sg:address":"395 Twp Hwy 219 W",
    "sg:city":"Bellefontaine",
    "sg:classifiers":[
        {
            "category":"Food & Beverages",
            "subcategory":"Groceries & Convenience Stores",
            "type":"Retail Goods"
        }
    ],
    "sg:phone":"+1 937 592 0100",
    "sg:postcode":"43311",
    "sg:province":"OH",
    "sg:tags":[
        "grocer"
    ],
    "wof:name":"Groceries To Go",
    "wof:placetype":"venue"
},
  "geometry": {"coordinates":[-83.752894,40.405475],"type":"Point"}
}