{
  "type": "Feature",
  "properties": {
    "addr:full": "6427 Firethorne Ave Reynoldsburg OH 43068",
    "addr:housenumber": "6427",
    "addr:postcode": "43068",
    "addr:street": "Firethorne Ave",
    "iso:country": "US",
    "sg:address": "6427 Firethorne Ave",
    "sg:city": "Reynoldsburg",
    "sg:classifiers": [
      {
        "category": "Building \u0026 Trades",
        "subcategory": "Plumbing",
        "type": "Services"
      }
    ],
    "sg:phone": "+1 614 868 0800",
    "sg:postcode": "43068",
    "sg:province": "OH",
    "sg:tags": [
      "air",
      "heating",
      "conditioning",
      "contractor"
    ],
    "wof:name": "Reynoldsburg Heating \u0026 AC",
    "wof:placetype": "venue"
  },
  "geometry": {"coordinates":[-82.828898,39.975096],"type":"Point"}
}
