{
  "type": "Feature",
  "properties": {
    "addr:full":"13510 Tyler Ave Cleveland OH 44111",
    "addr:housenumber":"13510",
    "addr:postcode":"44111",
    "addr:street":"Tyler Ave",
    "iso:country":"US",
    "sg:address":"13510 Tyler Ave",
    "sg:city":"Cleveland",
    "sg:classifiers":[
        {
            "category":"Restaurant",
            "type":"Food & Drink"
        }
    ],
    "sg:phone":"+1 216 252 2228",
    "sg:postcode":"44111",
    "sg:province":"OH",
    "sg:tags":[
        "eating"
    ],
    "wof:name":"L Cart Coffee Inc",
    "wof:placetype":"venue"
},
  "geometry": {"coordinates":[-81.786153,41.446631],"type":"Point"}
}