{
  "type": "Feature",
  "properties": {
    "iso:country":"US",
    "sg:address":"44884 US Hwy 20",
    "sg:city":"Oberlin",
    "sg:classifiers":[
        {
            "category":"Retail",
            "subcategory":"Auto Rental",
            "type":"Services"
        }
    ],
    "sg:phone":"+1 440 774 2077",
    "sg:postcode":"44074",
    "sg:province":"OH",
    "sg:tags":[
        "renting",
        "truck",
        "leasing"
    ],
    "wof:name":"U-Haul Co",
    "wof:placetype":"venue"
},
  "geometry": {"coordinates":[-82.183583,41.282738],"type":"Point"}
}