{
  "type": "Feature",
  "properties": {
    "addr:full": "17000 Saint Clair Ave Cleveland OH 44110",
    "addr:postcode": "17000;44110",
    "addr:street": "Saint Clair Ave",
    "iso:country": "US",
    "sg:address": "17000 Saint Clair Ave",
    "sg:city": "Cleveland",
    "sg:classifiers": [
      {
        "category": "Shopping",
        "subcategory": "Bicycles \u0026 Sporting Goods",
        "type": "Retail Goods"
      }
    ],
    "sg:phone": "+1 216 738 2510",
    "sg:postcode": "44110",
    "sg:province": "OH",
    "sg:tags": [
      "hair",
      "equipment",
      "supply",
      "skiing",
      "accessory"
    ],
    "sg:website": "www.teamwendy.com",
    "wof:name": "Team Wendy",
    "wof:placetype": "venue"
  },
  "geometry": {"coordinates":[-81.560612,41.564649],"type":"Point"}
}
