{
  "type": "Feature",
  "properties": {
    "addr:full": "825 W Market St Lima OH 45805",
    "addr:housenumber": "825",
    "addr:postcode": "45805",
    "addr:street": "W Market St",
    "iso:country": "US",
    "sg:address": "825 W Market St",
    "sg:city": "Lima",
    "sg:classifiers": [
      {
        "category": "Health Services",
        "subcategory": "Doctor",
        "type": "Services"
      }
    ],
    "sg:phone": "+1 419 229 3973",
    "sg:postcode": "45805",
    "sg:province": "OH",
    "sg:tags": [
      "physician",
      "surgeon"
    ],
    "wof:name": "R E Teruel Inc",
    "wof:placetype": "venue"
  },
  "geometry": {"coordinates":[-84.121821,40.739988],"type":"Point"}
}
