{
  "type": "Feature",
  "properties": {
    "addr:full":"2834 Meldon Blvd Cleveland OH 44122",
    "addr:housenumber":"2834",
    "addr:postcode":"44122",
    "addr:street":"Meldon Blvd",
    "iso:country":"US",
    "sg:address":"2834 Meldon Blvd",
    "sg:city":"Cleveland",
    "sg:classifiers":[
        {
            "category":"Manufacturing",
            "subcategory":"Printing",
            "type":"Manufacturing & Wholesale Goods"
        }
    ],
    "sg:phone":"+1 216 591 1231",
    "sg:postcode":"44122",
    "sg:province":"OH",
    "sg:tags":[
        "commercial"
    ],
    "wof:name":"Enk Enterprise",
    "wof:placetype":"venue"
},
  "geometry": {"coordinates":[-81.503332,41.48046],"type":"Point"}
}