{
  "type": "Feature",
  "properties": {
    "iso:country":"US",
    "sg:address":"100 E Park Ave",
    "sg:city":"Fairfield",
    "sg:classifiers":[
        {
            "category":"Shopping",
            "subcategory":"Computers & Home Electronics",
            "type":"Retail Goods"
        }
    ],
    "sg:phone":"+1 513 892 2000",
    "sg:postcode":"45036",
    "sg:province":"OH",
    "sg:tags":[
        "software"
    ],
    "wof:name":"Factory Floor Solutions",
    "wof:placetype":"venue"
},
  "geometry": {"coordinates":[-84.206493,39.427062],"type":"Point"}
}