{
  "type": "Feature",
  "properties": {
    "addr:full": "100 E Park Ave Fairfield OH 45036",
    "addr:housenumber": "100",
    "addr:postcode": "45036",
    "addr:street": "E Park Ave",
    "iso:country": "US",
    "sg:address": "100 E Park Ave",
    "sg:city": "Fairfield",
    "sg:classifiers": [
      {
        "category": "Shopping",
        "subcategory": "Computers \u0026 Home Electronics",
        "type": "Retail Goods"
      }
    ],
    "sg:phone": "+1 513 892 2000",
    "sg:postcode": "45036",
    "sg:province": "OH",
    "sg:tags": [
      "software"
    ],
    "wof:name": "Factory Floor Solutions",
    "wof:placetype": "venue"
  },
  "geometry": {"coordinates":[-84.206493,39.427062],"type":"Point"}
}
