{
  "type": "Feature",
  "properties": {
    "addr:full": "5522 Boehm Dr Fairfield OH 45014",
    "addr:postcode": "5522;45014",
    "addr:street": "Boehm Dr",
    "iso:country": "US",
    "sg:address": "5522 Boehm Dr",
    "sg:city": "Fairfield",
    "sg:classifiers": [
      {
        "category": "Professional",
        "type": "Services"
      }
    ],
    "sg:phone": "+1 513 858 6001",
    "sg:postcode": "45014",
    "sg:province": "OH",
    "wof:name": "Gardner Day-Tek",
    "wof:placetype": "venue"
  },
  "geometry": {"coordinates":[-84.528056,39.327042],"type":"Point"}
}
