{
  "type": "Feature",
  "properties": {
    "iso:country":"US",
    "sg:address":"4098 E Danville Rd",
    "sg:city":"Hillsboro",
    "sg:classifiers":[
        {
            "category":"Shopping",
            "subcategory":"Bicycles & Sporting Goods",
            "type":"Retail Goods"
        }
    ],
    "sg:phone":"+1 937 288 0058",
    "sg:postcode":"45133",
    "sg:province":"OH",
    "wof:name":"1stopfishingshopcom",
    "wof:placetype":"venue"
},
  "geometry": {"coordinates":[-83.72805099999999,39.127786],"type":"Point"}
}