{
  "type": "Feature",
  "properties": {
    "addr:full": "4098 E Danville Rd Hillsboro OH 45133",
    "addr:housenumber": "4098",
    "addr:postcode": "45133",
    "addr:street": "E Danville Rd",
    "iso:country": "US",
    "sg:address": "4098 E Danville Rd",
    "sg:city": "Hillsboro",
    "sg:classifiers": [
      {
        "category": "Shopping",
        "subcategory": "Bicycles \u0026 Sporting Goods",
        "type": "Retail Goods"
      }
    ],
    "sg:phone": "+1 937 288 0058",
    "sg:postcode": "45133",
    "sg:province": "OH",
    "wof:name": "1stopfishingshopcom",
    "wof:placetype": "venue"
  },
  "geometry": {"coordinates":[-83.728051,39.127786],"type":"Point"}
}
