{
  "type": "Feature",
  "properties": {
    "addr:full":"200 Industrial Pkwy Chagrin Falls OH 44022",
    "addr:housenumber":"200",
    "addr:postcode":"44022",
    "addr:street":"Industrial Pkwy",
    "iso:country":"US",
    "sg:address":"200 Industrial Pkwy",
    "sg:city":"Chagrin Falls",
    "sg:classifiers":[
        {
            "category":"Professional",
            "subcategory":"Lawyer & Legal Services",
            "type":"Services"
        }
    ],
    "sg:phone":"+1 440 247 2102",
    "sg:postcode":"44022",
    "sg:province":"OH",
    "wof:name":"Bruner Henry B",
    "wof:placetype":"venue"
},
  "geometry": {"coordinates":[-81.36990400000001,41.423599],"type":"Point"}
}