{
  "type": "Feature",
  "properties": {
    "addr:full": "12 Walnut St Cincinnati OH 45215",
    "addr:housenumber": "12",
    "addr:postcode": "45215",
    "addr:street": "Walnut St",
    "iso:country": "US",
    "sg:address": "12 Walnut St",
    "sg:city": "Cincinnati",
    "sg:classifiers": [
      {
        "category": "Retail",
        "subcategory": "Repair Shop",
        "type": "Services"
      }
    ],
    "sg:phone": "+1 513 769 5226",
    "sg:postcode": "45215",
    "sg:province": "OH",
    "sg:tags": [
      "elevator"
    ],
    "wof:name": "American Elevators Inc",
    "wof:placetype": "venue"
  },
  "geometry": {"coordinates":[-84.440734,39.225571],"type":"Point"}
}
