{
  "type": "Feature",
  "properties": {
    "iso:country":"US",
    "sg:address":"101 E Stewart St",
    "sg:city":"Dayton",
    "sg:classifiers":[
        {
            "category":"Bars & Pubs",
            "type":"Food & Drink"
        }
    ],
    "sg:phone":"+1 937 228 5776",
    "sg:postcode":"45409",
    "sg:province":"OH",
    "wof:name":"Flanagan's Pub",
    "wof:placetype":"venue"
},
  "geometry": {"coordinates":[-84.182118,39.740912],"type":"Point"}
}