{
  "type": "Feature",
  "properties": {
    "addr:full": "101 E Stewart St Dayton OH 45409",
    "addr:housenumber": "101",
    "addr:postcode": "45409",
    "addr:street": "E Stewart St",
    "iso:country": "US",
    "sg:address": "101 E Stewart St",
    "sg:city": "Dayton",
    "sg:classifiers": [
      {
        "category": "Bars \u0026 Pubs",
        "type": "Food \u0026 Drink"
      }
    ],
    "sg:phone": "+1 937 228 5776",
    "sg:postcode": "45409",
    "sg:province": "OH",
    "wof:name": "Flanagan's Pub",
    "wof:placetype": "venue"
  },
  "geometry": {"coordinates":[-84.182118,39.740912],"type":"Point"}
}
