{
  "type": "Feature",
  "properties": {
    "addr:full": "11461 Northlake Dr Cincinnati OH 45249",
    "addr:housenumber": "11461",
    "addr:postcode": "45249",
    "addr:street": "Northlake Dr",
    "iso:country": "US",
    "sg:address": "11461 Northlake Dr",
    "sg:city": "Cincinnati",
    "sg:classifiers": [
      {
        "category": "Wholesale",
        "subcategory": "Office Equipment",
        "type": "Manufacturing \u0026 Wholesale Goods"
      }
    ],
    "sg:phone": "+1 513 469 2679",
    "sg:postcode": "45249",
    "sg:province": "OH",
    "sg:website": "www.donnellonmccarthy.com",
    "wof:name": "Donnellon Mc Carthy Inc",
    "wof:placetype": "venue"
  },
  "geometry": {"coordinates":[-84.346924,39.277223],"type":"Point"}
}
