{
  "type": "Feature",
  "properties": {
    "iso:country":"US",
    "sg:address":"11461 Northlake Dr",
    "sg:city":"Cincinnati",
    "sg:classifiers":[
        {
            "category":"Wholesale",
            "subcategory":"Office Equipment",
            "type":"Manufacturing & Wholesale Goods"
        }
    ],
    "sg:phone":"+1 513 469 2679",
    "sg:postcode":"45249",
    "sg:province":"OH",
    "sg:website":"www.donnellonmccarthy.com",
    "wof:name":"Donnellon Mc Carthy Inc",
    "wof:placetype":"venue"
},
  "geometry": {"coordinates":[-84.346924,39.277223],"type":"Point"}
}