{
  "type": "Feature",
  "properties": {
    "addr:full":"3229 State Rte 7 Fowler OH 44418",
    "addr:housenumber":"3229",
    "addr:postcode":"44418",
    "addr:street":"State Rte 7",
    "iso:country":"US",
    "sg:address":"3229 State Rte 7",
    "sg:city":"Fowler",
    "sg:classifiers":[
        {
            "category":"Shopping",
            "subcategory":"Gifts & Souvenirs",
            "type":"Retail Goods"
        }
    ],
    "sg:phone":"+1 330 772 2611",
    "sg:postcode":"44418",
    "sg:province":"OH",
    "sg:tags":[
        "shop"
    ],
    "wof:name":"Whatever Shop",
    "wof:placetype":"venue"
},
  "geometry": {"coordinates":[-80.56851,41.308717],"type":"Point"}
}