{
  "type": "Feature",
  "properties": {
    "addr:full":"777 S Wapakoneta Rd Lima OH 45805",
    "addr:housenumber":"777",
    "addr:postcode":"45805",
    "addr:street":"S Wapakoneta Rd",
    "iso:country":"US",
    "sg:address":"777 S Wapakoneta Rd",
    "sg:city":"Lima",
    "sg:classifiers":[
        {
            "category":"Personal",
            "type":"Services"
        }
    ],
    "sg:phone":"+1 419 999 4244",
    "sg:postcode":"45805",
    "sg:province":"OH",
    "sg:tags":[
        "electrolysis"
    ],
    "wof:name":"Karen Mc Neeley Electrologist",
    "wof:placetype":"venue"
},
  "geometry": {"coordinates":[-84.204244,40.728824],"type":"Point"}
}