{
  "type": "Feature",
  "properties": {
    "addr:full": "4033 Gilmore Ave Cincinnati OH 45209",
    "addr:housenumber": "4033",
    "addr:postcode": "45209",
    "addr:street": "Gilmore Ave",
    "iso:country": "US",
    "sg:address": "4033 Gilmore Ave",
    "sg:city": "Cincinnati",
    "sg:classifiers": [
      {
        "category": "Education",
        "subcategory": "Library",
        "type": "Public Place"
      }
    ],
    "sg:phone": "+1 513 369 6038",
    "sg:postcode": "45209",
    "sg:province": "OH",
    "sg:website": "http://www.mhrecovery.com",
    "wof:name": "Public Library",
    "wof:placetype": "venue"
  },
  "geometry": {"coordinates":[-84.429424,39.151283],"type":"Point"}
}
