{
  "type": "Feature",
  "properties": {
    "iso:country":"US",
    "sg:address":"470 Railroad St",
    "sg:city":"Painesville",
    "sg:classifiers":[
        {
            "category":"Restaurant",
            "type":"Food & Drink"
        }
    ],
    "sg:phone":"+1 440 354 4475",
    "sg:postcode":"44077",
    "sg:province":"OH",
    "wof:name":"Silvestro's Depot Cafe Inc",
    "wof:placetype":"venue"
},
  "geometry": {"coordinates":[-81.243185,41.733209],"type":"Point"}
}