{
  "type": "Feature",
  "properties": {
    "addr:full": "470 Railroad St Painesville OH 44077",
    "addr:housenumber": "470",
    "addr:postcode": "44077",
    "addr:street": "Railroad St",
    "iso:country": "US",
    "sg:address": "470 Railroad St",
    "sg:city": "Painesville",
    "sg:classifiers": [
      {
        "category": "Restaurant",
        "type": "Food \u0026 Drink"
      }
    ],
    "sg:phone": "+1 440 354 4475",
    "sg:postcode": "44077",
    "sg:province": "OH",
    "wof:name": "Silvestro's Depot Cafe Inc",
    "wof:placetype": "venue"
  },
  "geometry": {"coordinates":[-81.243185,41.733209],"type":"Point"}
}
