{
  "type": "Feature",
  "properties": {
    "addr:full":"1289 East Ave Elyria OH 44035",
    "addr:housenumber":"1289",
    "addr:postcode":"44035",
    "addr:street":"East Ave",
    "iso:country":"US",
    "sg:address":"1289 East Ave",
    "sg:city":"Elyria",
    "sg:classifiers":[
        {
            "category":"Organizations",
            "subcategory":"Non-profit Organization",
            "type":"Services"
        }
    ],
    "sg:phone":"+1 440 322 4435",
    "sg:postcode":"44035",
    "sg:province":"OH",
    "sg:website":"www.clevelandnurse.org",
    "wof:name":"Greater Cleveland Nurses Assoc",
    "wof:placetype":"venue"
},
  "geometry": {"coordinates":[-82.102937,41.353307],"type":"Point"}
}