{
  "type": "Feature",
  "properties": {
    "addr:full": "407 E Yeasting St Gibsonburg OH 43431",
    "addr:housenumber": "407",
    "addr:postcode": "43431",
    "addr:street": "E Yeasting St",
    "iso:country": "US",
    "sg:address": "407 E Yeasting St",
    "sg:city": "Gibsonburg",
    "sg:classifiers": [
      {
        "category": "Restaurant",
        "type": "Food \u0026 Drink"
      }
    ],
    "sg:phone": "+1 419 637 2107",
    "sg:postcode": "43431",
    "sg:province": "OH",
    "wof:name": "Pisanello's Pizza",
    "wof:placetype": "venue"
  },
  "geometry": {"coordinates":[-83.31625,41.383497],"type":"Point"}
}
