{
  "type": "Feature",
  "properties": {
    "addr:full":"1276 Bennett Rd Madison OH 44057",
    "addr:housenumber":"1276",
    "addr:postcode":"44057",
    "addr:street":"Bennett Rd",
    "iso:country":"US",
    "sg:address":"1276 Bennett Rd",
    "sg:city":"Madison",
    "sg:classifiers":[
        {
            "category":"Building & Trades",
            "subcategory":"Landscaping Services",
            "type":"Services"
        }
    ],
    "sg:phone":"+1 440 428 7268",
    "sg:postcode":"44057",
    "sg:province":"OH",
    "sg:tags":[
        "landscape"
    ],
    "wof:name":"Davis Landscape Maintenance",
    "wof:placetype":"venue"
},
  "geometry": {"coordinates":[-81.032239,41.841412],"type":"Point"}
}