{
  "type": "Feature",
  "properties": {
    "addr:full":"26460 Curtiss Wright Pkwy Cleveland OH 44143",
    "addr:postcode":"26460;44143",
    "addr:street":"Wright Pkwy",
    "iso:country":"US",
    "sg:address":"26460 Curtiss Wright Pkwy",
    "sg:city":"Cleveland",
    "sg:classifiers":[
        {
            "category":"Banks & Credit Unions",
            "subcategory":"Bank",
            "type":"Services"
        }
    ],
    "sg:phone":"+1 216 261 9674",
    "sg:postcode":"44143",
    "sg:province":"OH",
    "sg:tags":[
        "national",
        "commercial"
    ],
    "wof:name":"Ncc Services Inc",
    "wof:placetype":"venue"
},
  "geometry": {"coordinates":[-81.490431,41.567315],"type":"Point"}
}