{
  "type": "Feature",
  "properties": {
    "addr:full":"8252 Darrow Rd Twinsburg OH 44087",
    "addr:housenumber":"8252",
    "addr:postcode":"44087",
    "addr:street":"Darrow Rd",
    "iso:country":"US",
    "sg:address":"8252 Darrow Rd",
    "sg:city":"Twinsburg",
    "sg:classifiers":[
        {
            "category":"Wholesale",
            "subcategory":"Medical Equipment & Supplies",
            "type":"Manufacturing & Wholesale Goods"
        }
    ],
    "sg:phone":"+1 330 487 0222",
    "sg:postcode":"44087",
    "sg:province":"OH",
    "sg:tags":[
        "product"
    ],
    "wof:name":"Corrective Vision Systems",
    "wof:placetype":"venue"
},
  "geometry": {"coordinates":[-81.44044599999999,41.285817],"type":"Point"}
}