{
  "type": "Feature",
  "properties": {
    "addr:full": "2825 Neil Ave Columbus OH 43202",
    "addr:housenumber": "2825",
    "addr:postcode": "43202",
    "addr:street": "Neil Ave",
    "iso:country": "US",
    "sg:address": "2825 Neil Ave",
    "sg:city": "Columbus",
    "sg:classifiers": [
      {
        "category": "Wholesale",
        "subcategory": "Machinery \u0026 Supplies",
        "type": "Manufacturing \u0026 Wholesale Goods"
      }
    ],
    "sg:phone": "+1 614 262 7867",
    "sg:postcode": "43202",
    "sg:province": "OH",
    "sg:tags": [
      "equipment",
      "industrial"
    ],
    "sg:website": "www.gitomac.com",
    "wof:name": "Gitomac Industrial Tool \u0026 Mach",
    "wof:placetype": "venue"
  },
  "geometry": {"coordinates":[-83.014823,40.021341],"type":"Point"}
}
