{
  "type": "Feature",
  "properties": {
    "iso:country":"US",
    "sg:address":"2825 Neil Ave",
    "sg:city":"Columbus",
    "sg:classifiers":[
        {
            "category":"Wholesale",
            "subcategory":"Machinery & Supplies",
            "type":"Manufacturing & Wholesale Goods"
        }
    ],
    "sg:phone":"+1 614 262 7867",
    "sg:postcode":"43202",
    "sg:province":"OH",
    "sg:tags":[
        "equipment",
        "industrial"
    ],
    "sg:website":"www.gitomac.com",
    "wof:name":"Gitomac Industrial Tool & Mach",
    "wof:placetype":"venue"
},
  "geometry": {"coordinates":[-83.01482300000001,40.021341],"type":"Point"}
}