{
  "type": "Feature",
  "properties": {
    "iso:country":"US",
    "sg:address":"5700 Market St",
    "sg:city":"Youngstown",
    "sg:classifiers":[
        {
            "category":"Banks & Credit Unions",
            "subcategory":"Bank",
            "type":"Services"
        }
    ],
    "sg:phone":"+1 330 783 3416",
    "sg:postcode":"44512",
    "sg:province":"OH",
    "sg:tags":[
        "loan",
        "broker"
    ],
    "wof:name":"American Home Loans",
    "wof:placetype":"venue"
},
  "geometry": {"coordinates":[-80.662767,41.039956],"type":"Point"}
}