{
  "type": "Feature",
  "properties": {
    "iso:country":"US",
    "sg:address":"5049 Crookshank Rd",
    "sg:city":"Cincinnati",
    "sg:classifiers":[
        {
            "category":"Health Services",
            "subcategory":"Medical Lab",
            "type":"Services"
        }
    ],
    "sg:phone":"+1 513 922 5565",
    "sg:postcode":"45238",
    "sg:province":"OH",
    "sg:tags":[
        "laboratory"
    ],
    "wof:name":"Western Hills Med Imaging Ctr",
    "wof:placetype":"venue"
},
  "geometry": {"coordinates":[-84.608874,39.127831],"type":"Point"}
}