{
  "type": "Feature",
  "properties": {
    "addr:full":"5996 E Livingston Ave Columbus OH 43232",
    "addr:housenumber":"5996",
    "addr:postcode":"43232",
    "addr:street":"E Livingston Ave",
    "iso:country":"US",
    "sg:address":"5996 E Livingston Ave",
    "sg:city":"Columbus",
    "sg:classifiers":[
        {
            "category":"Personal",
            "subcategory":"Barber",
            "type":"Services"
        }
    ],
    "sg:phone":"+1 614 864 9064",
    "sg:postcode":"43232",
    "sg:province":"OH",
    "wof:name":"KRS Barber & Salon",
    "wof:placetype":"venue"
},
  "geometry": {"coordinates":[-82.83277099999999,39.942143],"type":"Point"}
}