{
  "type": "Feature",
  "properties": {
    "addr:full":"136 W 6th St Mansfield OH 44902",
    "addr:housenumber":"136",
    "addr:postcode":"44902",
    "addr:street":"W 6Th St",
    "iso:country":"US",
    "sg:address":"136 W 6th St",
    "sg:city":"Mansfield",
    "sg:classifiers":[
        {
            "category":"Manufacturing",
            "subcategory":"Metals",
            "type":"Manufacturing & Wholesale Goods"
        }
    ],
    "sg:phone":"+1 419 525 1230",
    "sg:postcode":"44902",
    "sg:province":"OH",
    "sg:tags":[
        "stamping"
    ],
    "wof:name":"Milark Industries Inc",
    "wof:placetype":"venue"
},
  "geometry": {"coordinates":[-82.52144,40.765392],"type":"Point"}
}