{
  "type": "Feature",
  "properties": {
    "addr:full": "2140 Broadview Rd Cleveland OH 44109",
    "addr:housenumber": "2140",
    "addr:postcode": "44109",
    "addr:street": "Broadview Rd",
    "iso:country": "US",
    "sg:address": "2140 Broadview Rd",
    "sg:city": "Cleveland",
    "sg:classifiers": [
      {
        "category": "Personal",
        "subcategory": "Beauty Salon",
        "type": "Services"
      }
    ],
    "sg:phone": "+1 216 749 1191",
    "sg:postcode": "44109",
    "sg:province": "OH",
    "wof:name": "Valley West Hair Design",
    "wof:placetype": "venue"
  },
  "geometry": {"coordinates":[-81.699034,41.437619],"type":"Point"}
}
