{
  "type": "Feature",
  "properties": {
    "addr:full": "2775 S Co Rd 25A Troy OH 45373",
    "addr:housenumber": "2775;25a",
    "addr:postcode": "45373",
    "addr:street": "S Co Rd",
    "iso:country": "US",
    "sg:address": "2775 S Co Rd 25A",
    "sg:city": "Troy",
    "sg:classifiers": [
      {
        "category": "Autos \u0026 Motor Vehicles",
        "subcategory": "Automobile Sales",
        "type": "Retail Goods"
      }
    ],
    "sg:phone": "+1 937 335 5696",
    "sg:postcode": "45373",
    "sg:province": "OH",
    "sg:tags": [
      "car",
      "dealer"
    ],
    "wof:name": "Erwin Chrysler Dodge Jeep",
    "wof:placetype": "venue"
  },
  "geometry": {"coordinates":[-84.200502,39.999833],"type":"Point"}
}
