{
  "type": "Feature",
  "properties": {
    "addr:full": "974 Palmer Rd Columbus OH 43212",
    "addr:housenumber": "974",
    "addr:postcode": "43212",
    "addr:street": "Palmer Rd",
    "iso:country": "US",
    "sg:address": "974 Palmer Rd",
    "sg:city": "Columbus",
    "sg:classifiers": [
      {
        "category": "Food \u0026 Beverages",
        "subcategory": "Groceries \u0026 Convenience Stores",
        "type": "Retail Goods"
      }
    ],
    "sg:phone": "+1 614 485 9454",
    "sg:postcode": "43212",
    "sg:province": "OH",
    "wof:name": "One Eleven Place",
    "wof:placetype": "venue"
  },
  "geometry": {"coordinates":[-83.036993,39.977203],"type":"Point"}
}
