{
  "type": "Feature",
  "properties": {
    "addr:full": "800 Cross Pointe Rd Columbus OH 43230",
    "addr:housenumber": "800",
    "addr:postcode": "43230",
    "addr:street": "Cross Pointe Rd",
    "iso:country": "US",
    "sg:address": "800 Cross Pointe Rd",
    "sg:city": "Columbus",
    "sg:classifiers": [
      {
        "category": "Insurance",
        "subcategory": "Insurance Agent",
        "type": "Services"
      }
    ],
    "sg:phone": "+1 614 501 1938",
    "sg:postcode": "43230",
    "sg:province": "OH",
    "wof:name": "Cross Pointe Insurance",
    "wof:placetype": "venue"
  },
  "geometry": {"coordinates":[-82.836762,39.997216],"type":"Point"}
}
