{
  "type": "Feature",
  "properties": {
    "iso:country":"US",
    "sg:address":"2736 Powhattan Pkwy",
    "sg:city":"Toledo",
    "sg:classifiers":[
        {
            "category":"Wholesale",
            "subcategory":"Non-durable Goods",
            "type":"Manufacturing & Wholesale Goods"
        }
    ],
    "sg:phone":"+1 419 474 6010",
    "sg:postcode":"43606",
    "sg:province":"OH",
    "sg:tags":[
        "advertising",
        "specialty"
    ],
    "wof:name":"Creative Promotions Inc",
    "wof:placetype":"venue"
},
  "geometry": {"coordinates":[-83.601555,41.674868],"type":"Point"}
}