{
  "type": "Feature",
  "properties": {
    "addr:full":"754 Mistletoe St Columbus OH 43230",
    "addr:housenumber":"754",
    "addr:postcode":"43230",
    "addr:street":"Mistletoe St",
    "iso:country":"US",
    "sg:address":"754 Mistletoe St",
    "sg:city":"Columbus",
    "sg:classifiers":[
        {
            "category":"Building & Trades",
            "subcategory":"Landscaping Services",
            "type":"Services"
        }
    ],
    "sg:phone":"+1 614 478 2973",
    "sg:postcode":"43230",
    "sg:province":"OH",
    "sg:tags":[
        "lawn",
        "maintenance",
        "grounds"
    ],
    "wof:name":"Staygreen Lawn Svc",
    "wof:placetype":"venue"
},
  "geometry": {"coordinates":[-82.899198,40.038645],"type":"Point"}
}