{
  "type": "Feature",
  "properties": {
    "iso:country":"US",
    "sg:address":"444 Franklin Ave",
    "sg:city":"Steubenville",
    "sg:classifiers":[
        {
            "category":"Health Services",
            "subcategory":"Doctor",
            "type":"Services"
        }
    ],
    "sg:phone":"+1 740 264 4493",
    "sg:postcode":"43952",
    "sg:province":"OH",
    "wof:name":"Thomas R Brown DDS Inc",
    "wof:placetype":"venue"
},
  "geometry": {"coordinates":[-80.609876,40.370452],"type":"Point"}
}