{
  "type": "Feature",
  "properties": {
    "iso:country":"US",
    "sg:address":"2584 Trebein Rd",
    "sg:city":"Fairborn",
    "sg:classifiers":[
        {
            "category":"Building & Trades",
            "subcategory":"Plumbing",
            "type":"Services"
        }
    ],
    "sg:phone":"+1 937 427 9190",
    "sg:postcode":"45324",
    "sg:province":"OH",
    "sg:tags":[
        "plumbing",
        "contractor"
    ],
    "wof:name":"Nick Daniels Lawn & Landscape",
    "wof:placetype":"venue"
},
  "geometry": {"coordinates":[-83.993296,39.769539],"type":"Point"}
}