{
  "type": "Feature",
  "properties": {
    "addr:full": "2584 Trebein Rd Fairborn OH 45324",
    "addr:postcode": "2584;45324",
    "addr:street": "Trebein Rd",
    "iso:country": "US",
    "sg:address": "2584 Trebein Rd",
    "sg:city": "Fairborn",
    "sg:classifiers": [
      {
        "category": "Building \u0026 Trades",
        "subcategory": "Plumbing",
        "type": "Services"
      }
    ],
    "sg:phone": "+1 937 427 9190",
    "sg:postcode": "45324",
    "sg:province": "OH",
    "sg:tags": [
      "plumbing",
      "contractor"
    ],
    "wof:name": "Nick Daniels Lawn \u0026 Landscape",
    "wof:placetype": "venue"
  },
  "geometry": {"coordinates":[-83.993296,39.769539],"type":"Point"}
}
