{
  "type": "Feature",
  "properties": {
    "iso:country":"US",
    "sg:address":"3046 State Rte 125",
    "sg:city":"Bethel",
    "sg:classifiers":[
        {
            "category":"Education",
            "subcategory":"School",
            "type":"Public Place"
        }
    ],
    "sg:phone":"+1 513 734 6222",
    "sg:postcode":"45106",
    "sg:province":"OH",
    "wof:name":"US Grant Voc School District",
    "wof:placetype":"venue"
},
  "geometry": {"coordinates":[-84.09320200000001,38.965569],"type":"Point"}
}