{
  "type": "Feature",
  "properties": {
    "addr:full": "3046 State Rte 125 Bethel OH 45106",
    "addr:housenumber": "3046",
    "addr:postcode": "45106",
    "addr:street": "State Rte 125",
    "iso:country": "US",
    "sg:address": "3046 State Rte 125",
    "sg:city": "Bethel",
    "sg:classifiers": [
      {
        "category": "Education",
        "subcategory": "School",
        "type": "Public Place"
      }
    ],
    "sg:phone": "+1 513 734 6222",
    "sg:postcode": "45106",
    "sg:province": "OH",
    "wof:name": "US Grant Voc School District",
    "wof:placetype": "venue"
  },
  "geometry": {"coordinates":[-84.093202,38.965569],"type":"Point"}
}
