{
  "type": "Feature",
  "properties": {
    "addr:full":"6199 Som Center Rd Solon OH 44139",
    "addr:housenumber":"6199",
    "addr:postcode":"44139",
    "addr:street":"Som Center Rd",
    "iso:country":"US",
    "sg:address":"6199 Som Center Rd",
    "sg:city":"Solon",
    "sg:classifiers":[
        {
            "category":"Home & Garden",
            "subcategory":"Building Materials",
            "type":"Retail Goods"
        }
    ],
    "sg:phone":"+1 440 248 5355",
    "sg:postcode":"44139",
    "sg:province":"OH",
    "sg:tags":[
        "supply"
    ],
    "sg:website":"www.carterlumber.com",
    "wof:name":"Carter Lumber",
    "wof:placetype":"venue"
},
  "geometry": {"coordinates":[-81.43759900000001,41.389099],"type":"Point"}
}