{
  "type": "Feature",
  "properties": {
    "iso:country":"US",
    "sg:address":"1591 E 22nd St",
    "sg:city":"Cleveland",
    "sg:classifiers":[
        {
            "category":"Retail",
            "subcategory":"Photofinishing",
            "type":"Services"
        }
    ],
    "sg:phone":"+1 216 621 7567",
    "sg:postcode":"44114",
    "sg:province":"OH",
    "sg:tags":[
        "photo",
        "finishing"
    ],
    "wof:name":"Labwork",
    "wof:placetype":"venue"
},
  "geometry": {"coordinates":[-81.67627400000001,41.50682],"type":"Point"}
}