{
  "type": "Feature",
  "properties": {
    "iso:country":"US",
    "sg:address":"3396 Briarcliff Rd",
    "sg:city":"Nashport",
    "sg:classifiers":[
        {
            "category":"Restaurant",
            "type":"Food & Drink"
        }
    ],
    "sg:phone":"+1 740 763 4615",
    "sg:postcode":"43830",
    "sg:province":"OH",
    "wof:name":"T G Subs Inc",
    "wof:placetype":"venue"
},
  "geometry": {"coordinates":[-82.234711,40.106153],"type":"Point"}
}