{
  "type": "Feature",
  "properties": {
    "iso:country":"US",
    "sg:address":"309 S Snyder Rd",
    "sg:city":"New Lebanon",
    "sg:classifiers":[
        {
            "category":"Building & Trades",
            "subcategory":"Construction",
            "type":"Services"
        }
    ],
    "sg:phone":"+1 937 835 7231",
    "sg:postcode":"45345",
    "sg:province":"OH",
    "sg:tags":[
        "house"
    ],
    "wof:name":"R & S Home Improvement",
    "wof:placetype":"venue"
},
  "geometry": {"coordinates":[-84.328693,39.744909],"type":"Point"}
}