{
  "type": "Feature",
  "properties": {
    "iso:country":"US",
    "sg:address":"11750 Rd 82",
    "sg:city":"Haviland",
    "sg:classifiers":[
        {
            "category":"Building & Trades",
            "subcategory":"Construction",
            "type":"Services"
        }
    ],
    "sg:phone":"+1 937 842 9663",
    "sg:postcode":"45879",
    "sg:province":"OH",
    "sg:tags":[
        "home",
        "builder"
    ],
    "wof:name":"S & S Fine Homes LTD",
    "wof:placetype":"venue"
},
  "geometry": {"coordinates":[-84.59621799999999,41.076849],"type":"Point"}
}