{
  "type": "Feature",
  "properties": {
    "addr:full": "475 S Main St Pataskala OH 43062",
    "addr:housenumber": "475",
    "addr:postcode": "43062",
    "addr:street": "S Main St",
    "iso:country": "US",
    "sg:address": "475 S Main St",
    "sg:city": "Pataskala",
    "sg:classifiers": [
      {
        "category": "Building \u0026 Trades",
        "subcategory": "Construction",
        "type": "Services"
      }
    ],
    "sg:phone": "+1 740 927 4985",
    "sg:postcode": "43062",
    "sg:province": "OH",
    "sg:tags": [
      "equipment",
      "installation"
    ],
    "wof:name": "R P M Rigging",
    "wof:placetype": "venue"
  },
  "geometry": {"coordinates":[-82.675394,39.992924],"type":"Point"}
}
