{
  "type": "Feature",
  "properties": {
    "iso:country":"US",
    "sg:address":"475 S Main St",
    "sg:city":"Pataskala",
    "sg:classifiers":[
        {
            "category":"Building & Trades",
            "subcategory":"Construction",
            "type":"Services"
        }
    ],
    "sg:phone":"+1 740 927 4985",
    "sg:postcode":"43062",
    "sg:province":"OH",
    "sg:tags":[
        "equipment",
        "installation"
    ],
    "wof:name":"R P M Rigging",
    "wof:placetype":"venue"
},
  "geometry": {"coordinates":[-82.675394,39.992924],"type":"Point"}
}