{
  "type": "Feature",
  "properties": {
    "iso:country":"US",
    "sg:address":"3560 McCartney Rd",
    "sg:city":"Youngstown",
    "sg:classifiers":[
        {
            "category":"Building & Trades",
            "subcategory":"Construction",
            "type":"Services"
        }
    ],
    "sg:phone":"+1 330 747 5739",
    "sg:postcode":"44505",
    "sg:province":"OH",
    "sg:tags":[
        "remodeling",
        "general"
    ],
    "wof:name":"Lory Enterprises Ltd",
    "wof:placetype":"venue"
},
  "geometry": {"coordinates":[-80.57492999999999,41.090477],"type":"Point"}
}