{
  "type": "Feature",
  "properties": {
    "addr:full":"3574 Karl Rd Columbus OH 43224",
    "addr:housenumber":"3574",
    "addr:postcode":"43224",
    "addr:street":"Karl Rd",
    "iso:country":"US",
    "sg:address":"3574 Karl Rd",
    "sg:city":"Columbus",
    "sg:classifiers":[
        {
            "category":"Building & Trades",
            "subcategory":"Electrical",
            "type":"Services"
        }
    ],
    "sg:phone":"+1 614 267 4911",
    "sg:postcode":"43224",
    "sg:province":"OH",
    "sg:tags":[
        "electrical",
        "electric",
        "contractor"
    ],
    "wof:name":"Mighty Electric Co",
    "wof:placetype":"venue"
},
  "geometry": {"coordinates":[-82.977557,40.038647],"type":"Point"}
}