{
  "type": "Feature",
  "properties": {
    "addr:full":"951 Park Ave Salem OH 44460",
    "addr:housenumber":"951",
    "addr:postcode":"44460",
    "addr:street":"Park Ave",
    "iso:country":"US",
    "sg:address":"951 Park Ave",
    "sg:city":"Salem",
    "sg:classifiers":[
        {
            "category":"Building & Trades",
            "subcategory":"Construction",
            "type":"Services"
        }
    ],
    "sg:phone":"+1 330 337 8486",
    "sg:postcode":"44460",
    "sg:province":"OH",
    "sg:tags":[
        "residential"
    ],
    "wof:name":"Jeffrey L Hardgrove",
    "wof:placetype":"venue"
},
  "geometry": {"coordinates":[-80.838487,40.895719],"type":"Point"}
}