{
  "type": "Feature",
  "properties": {
    "addr:full": "351 Steubenville Rd SE Carrollton OH 44615",
    "addr:housenumber": "351",
    "addr:postcode": "44615",
    "addr:street": "Steubenville Rd Se",
    "iso:country": "US",
    "sg:address": "351 Steubenville Rd SE",
    "sg:city": "Carrollton",
    "sg:classifiers": [
      {
        "category": "Autos \u0026 Motor Vehicles",
        "subcategory": "Auto Supplies",
        "type": "Retail Goods"
      }
    ],
    "sg:phone": "+1 330 627 2793",
    "sg:postcode": "44615",
    "sg:province": "OH",
    "sg:tags": [
      "tire"
    ],
    "wof:name": "H \u0026 M Tire",
    "wof:placetype": "venue"
  },
  "geometry": {"coordinates":[-81.071487,40.566357],"type":"Point"}
}
