{
  "type": "Feature",
  "properties": {
    "iso:country":"US",
    "sg:address":"351 Steubenville Rd SE",
    "sg:city":"Carrollton",
    "sg:classifiers":[
        {
            "category":"Autos & Motor Vehicles",
            "subcategory":"Auto Supplies",
            "type":"Retail Goods"
        }
    ],
    "sg:phone":"+1 330 627 2793",
    "sg:postcode":"44615",
    "sg:province":"OH",
    "sg:tags":[
        "tire"
    ],
    "wof:name":"H & M Tire",
    "wof:placetype":"venue"
},
  "geometry": {"coordinates":[-81.071487,40.566357],"type":"Point"}
}