{
  "type": "Feature",
  "properties": {
    "addr:full":"4499 Homelawn Ave Cincinnati OH 45211",
    "addr:housenumber":"4499",
    "addr:postcode":"45211",
    "addr:street":"Homelawn Ave",
    "iso:country":"US",
    "sg:address":"4499 Homelawn Ave",
    "sg:city":"Cincinnati",
    "sg:classifiers":[
        {
            "category":"Building & Trades",
            "subcategory":"Construction",
            "type":"Services"
        }
    ],
    "sg:phone":"+1 513 574 9936",
    "sg:postcode":"45211",
    "sg:province":"OH",
    "sg:tags":[
        "roofing",
        "contractor"
    ],
    "wof:name":"Strasser Roofing Inc",
    "wof:placetype":"venue"
},
  "geometry": {"coordinates":[-84.62661199999999,39.164459],"type":"Point"}
}