{
  "type": "Feature",
  "properties": {
    "addr:full": "6105 W Liberty St Hubbard OH 44425",
    "addr:housenumber": "6105",
    "addr:postcode": "44425",
    "addr:street": "W Liberty St",
    "iso:country": "US",
    "sg:address": "6105 W Liberty St",
    "sg:city": "Hubbard",
    "sg:classifiers": [
      {
        "category": "Sports \u0026 Exercise",
        "subcategory": "Bowling",
        "type": "Entertainment"
      }
    ],
    "sg:phone": "+1 330 534 1179",
    "sg:postcode": "44425",
    "sg:province": "OH",
    "sg:tags": [
      "pin",
      "ten",
      "center"
    ],
    "sg:website": "http://www.bellwickbowl.com",
    "wof:name": "Bell-Wick Bowl Inc",
    "wof:placetype": "venue"
  },
  "geometry": {"coordinates":[-80.597811,41.156656],"type":"Point"}
}
