{
  "type": "Feature",
  "properties": {
    "addr:full":"8342 Blackbird Ln Thornville OH 43076",
    "addr:housenumber":"8342",
    "addr:postcode":"43076",
    "addr:street":"Blackbird Ln",
    "iso:country":"US",
    "sg:address":"8342 Blackbird Ln",
    "sg:city":"Thornville",
    "sg:phone":"+1 740 246 6930",
    "sg:postcode":"43076",
    "sg:province":"OH",
    "sg:tags":[
        "farm",
        "grain",
        "cash"
    ],
    "wof:name":"Carlos Dean Boyer",
    "wof:placetype":"venue"
},
  "geometry": {"coordinates":[-82.39133099999999,39.910976],"type":"Point"}
}