{
  "type": "Feature",
  "properties": {
    "addr:full":"2235 W 110th St Cleveland OH 44102",
    "addr:housenumber":"2235",
    "addr:postcode":"44102",
    "addr:street":"W 110Th St",
    "iso:country":"US",
    "sg:address":"2235 W 110th St",
    "sg:city":"Cleveland",
    "sg:classifiers":[
        {
            "category":"Education",
            "subcategory":"School",
            "type":"Public Place"
        }
    ],
    "sg:phone":"+1 216 252 9946",
    "sg:postcode":"44102",
    "sg:province":"OH",
    "wof:name":"Youth Leaders Network",
    "wof:placetype":"venue"
},
  "geometry": {"coordinates":[-81.76268899999999,41.47246],"type":"Point"}
}