{
  "type": "Feature",
  "properties": {
    "iso:country":"US",
    "sg:address":"1529 Saint Clair Ave NE",
    "sg:city":"Cleveland",
    "sg:classifiers":[
        {
            "category":"Professional",
            "subcategory":"Accounting & Tax Preparation",
            "type":"Services"
        }
    ],
    "sg:phone":"+1 216 687 0220",
    "sg:postcode":"44114",
    "sg:province":"OH",
    "sg:tags":[
        "accountant"
    ],
    "wof:name":"Samuel Kellogg & Co",
    "wof:placetype":"venue"
},
  "geometry": {"coordinates":[-81.684183,41.506885],"type":"Point"}
}