{
  "type": "Feature",
  "properties": {
    "addr:full": "999 W 6th Ave Columbus OH 43212",
    "addr:housenumber": "999",
    "addr:postcode": "43212",
    "addr:street": "W 6Th Ave",
    "iso:country": "US",
    "sg:address": "999 W 6th Ave",
    "sg:city": "Columbus",
    "sg:classifiers": [
      {
        "category": "Insurance",
        "subcategory": "Insurance Agent",
        "type": "Services"
      }
    ],
    "sg:phone": "+1 614 291 4686",
    "sg:postcode": "43212",
    "sg:province": "OH",
    "wof:name": "Bates \u0026 Co",
    "wof:placetype": "venue"
  },
  "geometry": {"coordinates":[-83.031639,39.98907],"type":"Point"}
}
