{
  "type": "Feature",
  "properties": {
    "iso:country":"US",
    "sg:address":"2240 N Leavitt Rd",
    "sg:city":"Lorain",
    "sg:classifiers":[
        {
            "category":"Food & Beverages",
            "subcategory":"Meat & Fish",
            "type":"Retail Goods"
        }
    ],
    "sg:phone":"+1 440 282 7770",
    "sg:postcode":"44052",
    "sg:province":"OH",
    "wof:name":"Manuels Fish Market",
    "wof:placetype":"venue"
},
  "geometry": {"coordinates":[-82.202394,41.450251],"type":"Point"}
}