{
  "type": "Feature",
  "properties": {
    "addr:full": "1800 Stringtown Rd Grove City OH 43123",
    "addr:housenumber": "1800",
    "addr:postcode": "43123",
    "addr:street": "Stringtown Rd",
    "iso:country": "US",
    "sg:address": "1800 Stringtown Rd",
    "sg:city": "Grove City",
    "sg:classifiers": [
      {
        "category": "Travel",
        "subcategory": "Hotels \u0026 Motels",
        "type": "Entertainment"
      }
    ],
    "sg:phone": "+1 614 277 0705",
    "sg:postcode": "43123",
    "sg:province": "OH",
    "sg:tags": [
      "operation"
    ],
    "wof:name": "Microtel",
    "wof:placetype": "venue"
  },
  "geometry": {"coordinates":[-83.042382,39.878977],"type":"Point"}
}
