{
  "type": "Feature",
  "properties": {
    "iso:country":"US",
    "sg:address":"1800 Stringtown Rd",
    "sg:city":"Grove City",
    "sg:classifiers":[
        {
            "category":"Travel",
            "subcategory":"Hotels & Motels",
            "type":"Entertainment"
        }
    ],
    "sg:phone":"+1 614 277 0705",
    "sg:postcode":"43123",
    "sg:province":"OH",
    "sg:tags":[
        "operation"
    ],
    "wof:name":"Microtel",
    "wof:placetype":"venue"
},
  "geometry": {"coordinates":[-83.042382,39.878977],"type":"Point"}
}