{
  "type": "Feature",
  "properties": {
    "addr:full": "1201 E Stroop Rd Dayton OH 45429",
    "addr:housenumber": "1201",
    "addr:postcode": "45429",
    "addr:street": "E Stroop Rd",
    "iso:country": "US",
    "sg:address": "1201 E Stroop Rd",
    "sg:city": "Dayton",
    "sg:classifiers": [
      {
        "category": "Shopping",
        "subcategory": "Florist",
        "type": "Retail Goods"
      }
    ],
    "sg:phone": "+1 937 298 3141",
    "sg:postcode": "45429",
    "sg:province": "OH",
    "wof:name": "Jacque's Flowers",
    "wof:placetype": "venue"
  },
  "geometry": {"coordinates":[-84.144385,39.688714],"type":"Point"}
}
