{
  "type": "Feature",
  "properties": {
    "iso:country":"US",
    "sg:address":"55 Harriette Dr",
    "sg:city":"Shelby",
    "sg:classifiers":[
        {
            "category":"Organizations",
            "subcategory":"Religious Organization",
            "type":"Services"
        }
    ],
    "sg:phone":"+1 419 342 2726",
    "sg:postcode":"44875",
    "sg:province":"OH",
    "sg:tags":[
        "clergy"
    ],
    "wof:name":"Lester R Champer",
    "wof:placetype":"venue"
},
  "geometry": {"coordinates":[-82.64469,40.877696],"type":"Point"}
}