{
  "type": "Feature",
  "properties": {
    "addr:full":"5947 S Sunbury Rd Westerville OH 43081",
    "addr:housenumber":"5947",
    "addr:postcode":"43081",
    "addr:street":"S Sunbury Rd",
    "iso:country":"US",
    "sg:address":"5947 S Sunbury Rd",
    "sg:city":"Westerville",
    "sg:classifiers":[
        {
            "category":"Restaurant",
            "type":"Food & Drink"
        },
        {
            "category":"Wholesale",
            "subcategory":"Groceries",
            "type":"Manufacturing & Wholesale Goods"
        }
    ],
    "sg:phone":"+1 614 895 0089",
    "sg:postcode":"43081",
    "sg:province":"OH",
    "sg:tags":[
        "bakery"
    ],
    "wof:name":"Gena's Restaurant",
    "wof:placetype":"venue"
},
  "geometry": {"coordinates":[-82.89573,40.083198],"type":"Point"}
}