{
  "type": "Feature",
  "properties": {
    "addr:full": "637 N Jackson St Lima OH 45801",
    "addr:housenumber": "637",
    "addr:postcode": "45801",
    "addr:street": "N Jackson St",
    "iso:country": "US",
    "sg:address": "637 N Jackson St",
    "sg:city": "Lima",
    "sg:classifiers": [
      {
        "category": "Manufacturing",
        "subcategory": "Rubber \u0026 Plastics",
        "type": "Manufacturing \u0026 Wholesale Goods"
      }
    ],
    "sg:phone": "+1 419 228 4441",
    "sg:postcode": "45801",
    "sg:province": "OH",
    "sg:tags": [
      "belting"
    ],
    "wof:name": "BRP Mfg Co",
    "wof:placetype": "venue"
  },
  "geometry": {"coordinates":[-84.100044,40.747415],"type":"Point"}
}
