{
  "type": "Feature",
  "properties": {
    "iso:country":"US",
    "sg:address":"637 N Jackson St",
    "sg:city":"Lima",
    "sg:classifiers":[
        {
            "category":"Manufacturing",
            "subcategory":"Rubber & Plastics",
            "type":"Manufacturing & Wholesale Goods"
        }
    ],
    "sg:phone":"+1 419 228 4441",
    "sg:postcode":"45801",
    "sg:province":"OH",
    "sg:tags":[
        "belting"
    ],
    "wof:name":"BRP Mfg Co",
    "wof:placetype":"venue"
},
  "geometry": {"coordinates":[-84.100044,40.747415],"type":"Point"}
}