{
  "type": "Feature",
  "properties": {
    "addr:full":"200 N Market St Minerva OH 44657",
    "addr:housenumber":"200",
    "addr:postcode":"44657",
    "addr:street":"N Market St",
    "iso:country":"US",
    "sg:address":"200 N Market St",
    "sg:city":"Minerva",
    "sg:classifiers":[
        {
            "category":"Shopping",
            "subcategory":"Jewelry",
            "type":"Retail Goods"
        }
    ],
    "sg:phone":"+1 330 868 4855",
    "sg:postcode":"44657",
    "sg:province":"OH",
    "sg:tags":[
        "repair",
        "watch",
        "clock"
    ],
    "wof:name":"Canestrros Rssell Jwlers Gifts",
    "wof:placetype":"venue"
},
  "geometry": {"coordinates":[-81.103797,40.730062],"type":"Point"}
}