{
  "type": "Feature",
  "properties": {
    "addr:full":"7230 Solon Rd South Solon OH 45314",
    "addr:housenumber":"7230",
    "addr:postcode":"45314",
    "addr:street":"Solon Rd",
    "iso:country":"US",
    "sg:address":"7230 Solon Rd",
    "sg:city":"South Solon",
    "sg:classifiers":[
        {
            "category":"Government",
            "subcategory":"Post Office",
            "type":"Public Place"
        }
    ],
    "sg:phone":"+1 937 883 2283",
    "sg:postcode":"45314",
    "sg:province":"OH",
    "wof:name":"US Post Office",
    "wof:placetype":"venue"
},
  "geometry": {"coordinates":[-83.655935,39.741044],"type":"Point"}
}