{
  "type": "Feature",
  "properties": {
    "iso:country":"US",
    "sg:address":"7307 Avon Belden Rd",
    "sg:city":"North Ridgeville",
    "sg:classifiers":[
        {
            "category":"Government",
            "subcategory":"Police Station",
            "type":"Public Place"
        }
    ],
    "sg:phone":"+1 440 327 2191",
    "sg:postcode":"44039",
    "sg:province":"OH",
    "sg:tags":[
        "department"
    ],
    "sg:website":"www.nridgeville.com",
    "wof:name":"North Ridgeville Police Dept",
    "wof:placetype":"venue"
},
  "geometry": {"coordinates":[-82.018559,41.385589],"type":"Point"}
}