{
  "type": "Feature",
  "properties": {
    "iso:country":"US",
    "sg:address":"32 S 29th St",
    "sg:city":"Newark",
    "sg:classifiers":[
        {
            "category":"Education",
            "subcategory":"Dance Studio",
            "type":"Public Place"
        }
    ],
    "sg:phone":"+1 740 344 8789",
    "sg:postcode":"43055",
    "sg:province":"OH",
    "sg:tags":[
        "instruction",
        "dancing"
    ],
    "wof:name":"Joan Garrett Dance Arts",
    "wof:placetype":"venue"
},
  "geometry": {"coordinates":[-82.44024899999999,40.049046],"type":"Point"}
}