{
  "type": "Feature",
  "properties": {
    "addr:full":"1480 Edison Ave Hamilton OH 45011",
    "addr:housenumber":"1480",
    "addr:postcode":"45011",
    "addr:street":"Edison Ave",
    "iso:country":"US",
    "sg:address":"1480 Edison Ave",
    "sg:city":"Hamilton",
    "sg:classifiers":[
        {
            "category":"Manufacturing",
            "subcategory":"Tools & Machinery",
            "type":"Manufacturing & Wholesale Goods"
        }
    ],
    "sg:phone":"+1 513 892 4591",
    "sg:postcode":"45011",
    "sg:province":"OH",
    "sg:tags":[
        "shop",
        "die",
        "special"
    ],
    "wof:name":"Enterprise Machine & Tool",
    "wof:placetype":"venue"
},
  "geometry": {"coordinates":[-84.549052,39.386473],"type":"Point"}
}