{
  "type": "Feature",
  "properties": {
    "addr:full":"504 N 3rd St Coshocton OH 43812",
    "addr:housenumber":"504",
    "addr:postcode":"43812",
    "addr:street":"N 3Rd St",
    "iso:country":"US",
    "sg:address":"504 N 3rd St",
    "sg:city":"Coshocton",
    "sg:classifiers":[
        {
            "category":"Mining & Drilling",
            "type":"Manufacturing & Wholesale Goods"
        }
    ],
    "sg:phone":"+1 740 622 9560",
    "sg:postcode":"43812",
    "sg:province":"OH",
    "sg:tags":[
        "development",
        "gas",
        "oil",
        "exploration"
    ],
    "wof:name":"NGO Development Corp",
    "wof:placetype":"venue"
},
  "geometry": {"coordinates":[-81.866744,40.277859],"type":"Point"}
}