{
  "type": "Feature",
  "properties": {
    "addr:full": "24441 Detroit Rd Westlake OH 44145",
    "addr:housenumber": "24441",
    "addr:postcode": "44145",
    "addr:street": "Detroit Rd",
    "iso:country": "US",
    "sg:address": "24441 Detroit Rd",
    "sg:city": "Westlake",
    "sg:classifiers": [
      {
        "category": "Professional",
        "type": "Services"
      }
    ],
    "sg:phone": "+1 440 808 9228",
    "sg:postcode": "44145",
    "sg:province": "OH",
    "wof:name": "Mulligan Columbro \u0026 Greenberg",
    "wof:placetype": "venue"
  },
  "geometry": {"coordinates":[-81.890825,41.470855],"type":"Point"}
}
