{
  "type": "Feature",
  "properties": {
    "addr:full":"178 Solon Rd Chagrin Falls OH 44022",
    "addr:housenumber":"178",
    "addr:postcode":"44022",
    "addr:street":"Solon Rd",
    "iso:country":"US",
    "sg:address":"178 Solon Rd",
    "sg:city":"Chagrin Falls",
    "sg:classifiers":[
        {
            "category":"Home & Garden",
            "subcategory":"Home Furnishings",
            "type":"Retail Goods"
        }
    ],
    "sg:phone":"+1 440 247 1148",
    "sg:postcode":"44022",
    "sg:province":"OH",
    "wof:name":"Glazen Pottery",
    "wof:placetype":"venue"
},
  "geometry": {"coordinates":[-81.39690400000001,41.426633],"type":"Point"}
}