{
  "type": "Feature",
  "properties": {
    "addr:full":"3739 Karl Rd Columbus OH 43224",
    "addr:housenumber":"3739",
    "addr:postcode":"43224",
    "addr:street":"Karl Rd",
    "iso:country":"US",
    "sg:address":"3739 Karl Rd",
    "sg:city":"Columbus",
    "sg:classifiers":[
        {
            "category":"Restaurant",
            "type":"Food & Drink"
        }
    ],
    "sg:phone":"+1 614 267 3157",
    "sg:postcode":"43224",
    "sg:province":"OH",
    "wof:name":"B & B Pizza & Spaghetti",
    "wof:placetype":"venue"
},
  "geometry": {"coordinates":[-82.977367,40.042706],"type":"Point"}
}