{
  "type": "Feature",
  "properties": {
    "addr:full":"2901 Pearl Ave Lorain OH 44055",
    "addr:housenumber":"2901",
    "addr:postcode":"44055",
    "addr:street":"Pearl Ave",
    "iso:country":"US",
    "sg:address":"2901 Pearl Ave",
    "sg:city":"Lorain",
    "sg:classifiers":[
        {
            "category":"Food & Beverages",
            "subcategory":"Groceries & Convenience Stores",
            "type":"Retail Goods"
        }
    ],
    "sg:phone":"+1 440 277 9540",
    "sg:postcode":"44055",
    "sg:province":"OH",
    "wof:name":"Rainbow Bakery",
    "wof:placetype":"venue"
},
  "geometry": {"coordinates":[-82.13667599999999,41.443414],"type":"Point"}
}