{
  "type": "Feature",
  "properties": {
    "addr:full": "308 E Main St Lexington OH 44904",
    "addr:housenumber": "308",
    "addr:postcode": "44904",
    "addr:street": "E Main St",
    "iso:country": "US",
    "sg:address": "308 E Main St",
    "sg:city": "Lexington",
    "sg:classifiers": [
      {
        "category": "Personal",
        "subcategory": "Beauty Salon",
        "type": "Services"
      }
    ],
    "sg:phone": "+1 419 884 6266",
    "sg:postcode": "44904",
    "sg:province": "OH",
    "sg:tags": [
      "manicuring"
    ],
    "wof:name": "Nails For All Seasons-Tanning",
    "wof:placetype": "venue"
  },
  "geometry": {"coordinates":[-82.57009,40.680766],"type":"Point"}
}
