{
  "type": "Feature",
  "properties": {
    "addr:full": "1210 E Main St Ashland OH 44805",
    "addr:housenumber": "1210",
    "addr:postcode": "44805",
    "addr:street": "E Main St",
    "iso:country": "US",
    "sg:address": "1210 E Main St",
    "sg:city": "Ashland",
    "sg:classifiers": [
      {
        "category": "Banks \u0026 Credit Unions",
        "subcategory": "Bank",
        "type": "Services"
      }
    ],
    "sg:phone": "+1 419 281 9050",
    "sg:postcode": "44805",
    "sg:province": "OH",
    "sg:tags": [
      "loan"
    ],
    "wof:name": "Fast Payday Loans Of Ohio",
    "wof:placetype": "venue"
  },
  "geometry": {"coordinates":[-82.29097,40.864222],"type":"Point"}
}
