{
  "type": "Feature",
  "properties": {
    "addr:full": "8351 Troy Pike Dayton OH 45424",
    "addr:housenumber": "8351",
    "addr:postcode": "45424",
    "addr:street": "Troy Pike",
    "iso:country": "US",
    "sg:address": "8351 Troy Pike",
    "sg:city": "Dayton",
    "sg:classifiers": [
      {
        "category": "Home \u0026 Garden",
        "subcategory": "Carpets \u0026 Floor Coverings",
        "type": "Retail Goods"
      }
    ],
    "sg:phone": "+1 937 233 5960",
    "sg:postcode": "45424",
    "sg:province": "OH",
    "sg:tags": [
      "dealer",
      "rug"
    ],
    "wof:name": "Rite Rug",
    "wof:placetype": "venue"
  },
  "geometry": {"coordinates":[-84.137331,39.873525],"type":"Point"}
}
