{
  "type": "Feature",
  "properties": {
    "iso:country":"US",
    "sg:address":"977 Twp Rd 1806",
    "sg:city":"Ashland",
    "sg:classifiers":[
        {
            "category":"Farming",
            "subcategory":"Farm",
            "type":"Manufacturing & Wholesale Goods"
        }
    ],
    "sg:phone":"+1 419 368 4614",
    "sg:postcode":"44805",
    "sg:province":"OH",
    "sg:tags":[
        "crop",
        "general"
    ],
    "wof:name":"Stauffer Farm",
    "wof:placetype":"venue"
},
  "geometry": {"coordinates":[-82.30828700000001,40.798613],"type":"Point"}
}