{
  "type": "Feature",
  "properties": {
    "addr:full":"4330 W 150th St Cleveland OH 44135",
    "addr:housenumber":"4330",
    "addr:postcode":"44135",
    "addr:street":"W 150Th St",
    "iso:country":"US",
    "sg:address":"4330 W 150th St",
    "sg:city":"Cleveland",
    "sg:classifiers":[
        {
            "category":"Health Services",
            "subcategory":"Health Practitioner",
            "type":"Services"
        }
    ],
    "sg:phone":"+1 216 688 0901",
    "sg:postcode":"44135",
    "sg:province":"OH",
    "sg:tags":[
        "therapist",
        "physical"
    ],
    "wof:name":"Nova Care",
    "wof:placetype":"venue"
},
  "geometry": {"coordinates":[-81.80132500000001,41.438315],"type":"Point"}
}