{
  "type": "Feature",
  "properties": {
    "iso:country":"US",
    "sg:address":"4356 Eastway St",
    "sg:city":"Toledo",
    "sg:classifiers":[
        {
            "category":"Retail",
            "subcategory":"Auto Repair",
            "type":"Services"
        }
    ],
    "sg:phone":"+1 419 476 6414",
    "sg:postcode":"43612",
    "sg:province":"OH",
    "sg:tags":[
        "motorcycle"
    ],
    "wof:name":"JCR Powdercoating & Custom",
    "wof:placetype":"venue"
},
  "geometry": {"coordinates":[-83.571484,41.697288],"type":"Point"}
}