{
  "type": "Feature",
  "properties": {
    "iso:country":"US",
    "sg:address":"26032 Detroit Rd",
    "sg:city":"Cleveland",
    "sg:classifiers":[
        {
            "category":"Health Services",
            "subcategory":"Doctor",
            "type":"Services"
        }
    ],
    "sg:phone":"+1 440 835 4600",
    "sg:postcode":"44145",
    "sg:province":"OH",
    "sg:tags":[
        "dentist"
    ],
    "wof:name":"Westlake Periodontics",
    "wof:placetype":"venue"
},
  "geometry": {"coordinates":[-81.906308,41.46976],"type":"Point"}
}