{
  "type": "Feature",
  "properties": {
    "iso:country":"US",
    "sg:address":"212 E Church St",
    "sg:city":"Urbana",
    "sg:classifiers":[
        {
            "category":"Professional",
            "subcategory":"Business Services",
            "type":"Services"
        }
    ],
    "sg:phone":"+1 937 653 3068",
    "sg:postcode":"43078",
    "sg:province":"OH",
    "sg:tags":[
        "auctioneer"
    ],
    "wof:name":"Mabry Auction Svc",
    "wof:placetype":"venue"
},
  "geometry": {"coordinates":[-83.75049300000001,40.110241],"type":"Point"}
}