{
  "type": "Feature",
  "properties": {
    "addr:full":"118 W 15th St Cincinnati OH 45202",
    "addr:housenumber":"118",
    "addr:postcode":"45202",
    "addr:street":"W 15Th St",
    "iso:country":"US",
    "sg:address":"118 W 15th St",
    "sg:city":"Cincinnati",
    "sg:classifiers":[
        {
            "category":"Food & Beverages",
            "subcategory":"Groceries & Convenience Stores",
            "type":"Retail Goods"
        }
    ],
    "sg:phone":"+1 513 929 9222",
    "sg:postcode":"45202",
    "sg:province":"OH",
    "sg:tags":[
        "grocer"
    ],
    "wof:name":"Downtown of Grocery",
    "wof:placetype":"venue"
},
  "geometry": {"coordinates":[-84.518383,39.111405],"type":"Point"}
}