{
  "type": "Feature",
  "properties": {
    "addr:full":"4111 Bagdad Rd Medina OH 44256",
    "addr:housenumber":"4111",
    "addr:postcode":"44256",
    "addr:street":"Bagdad Rd",
    "iso:country":"US",
    "sg:address":"4111 Bagdad Rd",
    "sg:city":"Medina",
    "sg:classifiers":[
        {
            "category":"Building & Trades",
            "subcategory":"Plumbing",
            "type":"Services"
        }
    ],
    "sg:phone":"+1 330 725 7168",
    "sg:postcode":"44256",
    "sg:province":"OH",
    "sg:tags":[
        "conditioning",
        "air",
        "system",
        "contractor"
    ],
    "wof:name":"Winter Service Plumbing Inc",
    "wof:placetype":"venue"
},
  "geometry": {"coordinates":[-81.812141,41.162309],"type":"Point"}
}