{
  "type": "Feature",
  "properties": {
    "iso:country":"US",
    "sg:address":"7559 Ridge Rd",
    "sg:city":"Wadsworth",
    "sg:classifiers":[
        {
            "category":"Professional",
            "type":"Services"
        }
    ],
    "sg:phone":"+1 330 336 8412",
    "sg:postcode":"44281",
    "sg:province":"OH",
    "wof:name":"NW Devl Inc",
    "wof:placetype":"venue"
},
  "geometry": {"coordinates":[-81.735821,41.07404],"type":"Point"}
}