{
  "type": "Feature",
  "properties": {
    "iso:country":"US",
    "sg:address":"4154 Brogan Dr",
    "sg:city":"Toledo",
    "sg:classifiers":[
        {
            "category":"Utilities",
            "subcategory":"Telephone",
            "type":"Services"
        }
    ],
    "sg:phone":"+1 419 381 1903",
    "sg:postcode":"43614",
    "sg:province":"OH",
    "sg:tags":[
        "communications"
    ],
    "wof:name":"Data Track Internet Services",
    "wof:placetype":"venue"
},
  "geometry": {"coordinates":[-83.637655,41.591595],"type":"Point"}
}