{
  "type": "Feature",
  "properties": {
    "addr:full": "113 E Columbus St Pleasantville OH 43148",
    "addr:housenumber": "113",
    "addr:postcode": "43148",
    "addr:street": "E Columbus St",
    "iso:country": "US",
    "sg:address": "113 E Columbus St",
    "sg:city": "Pleasantville",
    "sg:classifiers": [
      {
        "category": "Retail",
        "subcategory": "Auto Repair",
        "type": "Services"
      }
    ],
    "sg:phone": "+1 740 468 2171",
    "sg:postcode": "43148",
    "sg:province": "OH",
    "sg:tags": [
      "repairing",
      "automobile"
    ],
    "wof:name": "George's Repair Svc",
    "wof:placetype": "venue"
  },
  "geometry": {"coordinates":[-82.520473,39.809404],"type":"Point"}
}
