{
  "type": "Feature",
  "properties": {
    "addr:full":"64 Pine Bluff Dr Dayton OH 45440",
    "addr:housenumber":"64",
    "addr:postcode":"45440",
    "addr:street":"Pine Bluff Dr",
    "iso:country":"US",
    "sg:address":"64 Pine Bluff Dr",
    "sg:city":"Dayton",
    "sg:classifiers":[
        {
            "category":"Building & Trades",
            "subcategory":"Construction",
            "type":"Services"
        }
    ],
    "sg:phone":"+1 937 426 7227",
    "sg:postcode":"45440",
    "sg:province":"OH",
    "sg:tags":[
        "house"
    ],
    "wof:name":"Kennedy Builders",
    "wof:placetype":"venue"
},
  "geometry": {"coordinates":[-84.058897,39.691438],"type":"Point"}
}