{
  "type": "Feature",
  "properties": {
    "iso:country":"US",
    "sg:address":"5680 US Hwy 30",
    "sg:city":"Crestline",
    "sg:classifiers":[
        {
            "category":"Retail",
            "subcategory":"Auto Repair",
            "type":"Services"
        }
    ],
    "sg:phone":"+1 419 683 1041",
    "sg:postcode":"44827",
    "sg:province":"OH",
    "sg:tags":[
        "truck"
    ],
    "wof:name":"Truck Shop",
    "wof:placetype":"venue"
},
  "geometry": {"coordinates":[-82.843346,40.813194],"type":"Point"}
}