{
  "type": "Feature",
  "properties": {
    "addr:full":"13660 Fairhill Rd Cleveland OH 44120",
    "addr:housenumber":"13660",
    "addr:postcode":"44120",
    "addr:street":"Fairhill Rd",
    "iso:country":"US",
    "sg:address":"13660 Fairhill Rd",
    "sg:city":"Cleveland",
    "sg:classifiers":[
        {
            "category":"Banks & Credit Unions",
            "subcategory":"Investment Brokerage",
            "type":"Services"
        }
    ],
    "sg:phone":"+1 216 421 4249",
    "sg:postcode":"44120",
    "sg:province":"OH",
    "sg:tags":[
        "advisory"
    ],
    "wof:name":"Rycor Investments",
    "wof:placetype":"venue"
},
  "geometry": {"coordinates":[-81.592415,41.492119],"type":"Point"}
}