{
  "type": "Feature",
  "properties": {
    "addr:full":"2597 Reeves Rd NE Warren OH 44483",
    "addr:housenumber":"2597",
    "addr:postcode":"44483",
    "addr:street":"Reeves Rd Ne",
    "iso:country":"US",
    "sg:address":"2597 Reeves Rd NE",
    "sg:city":"Warren",
    "sg:classifiers":[
        {
            "category":"Home & Garden",
            "subcategory":"Carpets & Floor Coverings",
            "type":"Retail Goods"
        }
    ],
    "sg:phone":"+1 330 372 1522",
    "sg:postcode":"44483",
    "sg:province":"OH",
    "wof:name":"C L B Carpeting",
    "wof:placetype":"venue"
},
  "geometry": {"coordinates":[-80.782709,41.253536],"type":"Point"}
}