{
  "type": "Feature",
  "properties": {
    "iso:country":"US",
    "sg:address":"5636 Wigmore Dr",
    "sg:city":"Columbus",
    "sg:classifiers":[
        {
            "category":"Freight",
            "type":"Transportation"
        }
    ],
    "sg:phone":"+1 614 459 4294",
    "sg:postcode":"43235",
    "sg:province":"OH",
    "sg:tags":[
        "courier"
    ],
    "wof:name":"Glaub Inc",
    "wof:placetype":"venue"
},
  "geometry": {"coordinates":[-83.077544,40.071376],"type":"Point"}
}