{
  "type": "Feature",
  "properties": {
    "iso:country":"US",
    "sg:address":"220 Shaw Rd",
    "sg:city":"Union",
    "sg:classifiers":[
        {
            "category":"Wholesale",
            "subcategory":"Construction Materials",
            "type":"Manufacturing & Wholesale Goods"
        }
    ],
    "sg:phone":"+1 937 836 1998",
    "sg:postcode":"45322",
    "sg:province":"OH",
    "sg:tags":[
        "sand",
        "gravel"
    ],
    "wof:name":"Northmont Sand & Gravel Co",
    "wof:placetype":"venue"
},
  "geometry": {"coordinates":[-84.32187999999999,39.90585],"type":"Point"}
}