{
  "type": "Feature",
  "properties": {
    "addr:full": "220 Shaw Rd Union OH 45322",
    "addr:housenumber": "220",
    "addr:postcode": "45322",
    "addr:street": "Shaw Rd",
    "iso:country": "US",
    "sg:address": "220 Shaw Rd",
    "sg:city": "Union",
    "sg:classifiers": [
      {
        "category": "Wholesale",
        "subcategory": "Construction Materials",
        "type": "Manufacturing \u0026 Wholesale Goods"
      }
    ],
    "sg:phone": "+1 937 836 1998",
    "sg:postcode": "45322",
    "sg:province": "OH",
    "sg:tags": [
      "sand",
      "gravel"
    ],
    "wof:name": "Northmont Sand \u0026 Gravel Co",
    "wof:placetype": "venue"
  },
  "geometry": {"coordinates":[-84.32188,39.90585],"type":"Point"}
}
