{
  "type": "Feature",
  "properties": {
    "addr:full":"13377 Smith Rd Cleveland OH 44130",
    "addr:housenumber":"13377",
    "addr:postcode":"44130",
    "addr:street":"Smith Rd",
    "iso:country":"US",
    "sg:address":"13377 Smith Rd",
    "sg:city":"Cleveland",
    "sg:classifiers":[
        {
            "category":"Personal",
            "subcategory":"Beauty Salon",
            "type":"Services"
        }
    ],
    "sg:phone":"+1 440 843 8810",
    "sg:postcode":"44130",
    "sg:province":"OH",
    "sg:tags":[
        "shop"
    ],
    "wof:name":"Grace College Of Cosmetology",
    "wof:placetype":"venue"
},
  "geometry": {"coordinates":[-81.79154,41.377455],"type":"Point"}
}