{
  "type": "Feature",
  "properties": {
    "addr:full":"3533 Sleepy Hollow Rd Brunswick OH 44212",
    "addr:housenumber":"3533",
    "addr:postcode":"44212",
    "addr:street":"Sleepy Hollow Rd",
    "iso:country":"US",
    "sg:address":"3533 Sleepy Hollow Rd",
    "sg:city":"Brunswick",
    "sg:classifiers":[
        {
            "category":"Building & Trades",
            "subcategory":"Construction",
            "type":"Services"
        }
    ],
    "sg:phone":"+1 330 220 3517",
    "sg:postcode":"44212",
    "sg:province":"OH",
    "sg:tags":[
        "concrete",
        "contractor"
    ],
    "wof:name":"Mike & Dona Okeefe",
    "wof:placetype":"venue"
},
  "geometry": {"coordinates":[-81.81246299999999,41.217003],"type":"Point"}
}