{
  "type": "Feature",
  "properties": {
    "addr:full": "1 State Rte 28 Milford OH 45150",
    "addr:housenumber": "1",
    "addr:postcode": "45150",
    "addr:street": "State Rte 28",
    "iso:country": "US",
    "sg:address": "1 State Rte 28",
    "sg:city": "Milford",
    "sg:classifiers": [
      {
        "category": "Retail",
        "subcategory": "Auto Repair",
        "type": "Services"
      }
    ],
    "sg:phone": "+1 513 831 5255",
    "sg:postcode": "45150",
    "sg:province": "OH",
    "sg:tags": [
      "automobile",
      "lubrication"
    ],
    "wof:name": "Jiffy Lube",
    "wof:placetype": "venue"
  },
  "geometry": {"coordinates":[-84.296204,39.172829],"type":"Point"}
}
