{
  "type": "Feature",
  "properties": {
    "iso:country":"US",
    "sg:address":"21776 State Rte 79",
    "sg:city":"Warsaw",
    "sg:classifiers":[
        {
            "category":"Organizations",
            "subcategory":"Religious Organization",
            "type":"Services"
        }
    ],
    "sg:phone":"+1 740 327 4402",
    "sg:postcode":"43844",
    "sg:province":"OH",
    "wof:name":"Least Of These Ministries",
    "wof:placetype":"venue"
},
  "geometry": {"coordinates":[-82.10254999999999,40.276903],"type":"Point"}
}