{
  "type": "Feature",
  "properties": {
    "addr:full": "535 E Dixie Dr Dayton OH 45449",
    "addr:housenumber": "535",
    "addr:postcode": "45449",
    "addr:street": "E Dixie Dr",
    "iso:country": "US",
    "sg:address": "535 E Dixie Dr",
    "sg:city": "Dayton",
    "sg:classifiers": [
      {
        "category": "Shopping",
        "type": "Retail Goods"
      }
    ],
    "sg:phone": "+1 937 898 5536",
    "sg:postcode": "45449",
    "sg:province": "OH",
    "sg:tags": [
      "merchandise"
    ],
    "wof:name": "Hocks Medical Supply",
    "wof:placetype": "venue"
  },
  "geometry": {"coordinates":[-84.24355,39.675124],"type":"Point"}
}
