{
  "type": "Feature",
  "properties": {
    "iso:country":"US",
    "sg:address":"200 W 5th St",
    "sg:city":"Dayton",
    "sg:classifiers":[
        {
            "category":"Real Estate",
            "subcategory":"Real Estate Agent",
            "type":"Services"
        }
    ],
    "sg:phone":"+1 937 223 7626",
    "sg:postcode":"45402",
    "sg:province":"OH",
    "sg:tags":[
        "management"
    ],
    "wof:name":"Federal Property Management",
    "wof:placetype":"venue"
},
  "geometry": {"coordinates":[-84.196623,39.755848],"type":"Point"}
}