{
  "type": "Feature",
  "properties": {
    "iso:country":"US",
    "sg:address":"1 Palmer St",
    "sg:city":"Athens",
    "sg:classifiers":[
        {
            "category":"Retail",
            "subcategory":"Repair Shop",
            "type":"Services"
        }
    ],
    "sg:phone":"+1 740 593 6366",
    "sg:postcode":"45701",
    "sg:province":"OH",
    "sg:tags":[
        "water",
        "equipment",
        "softening"
    ],
    "wof:name":"Culligan Water Conditioning",
    "wof:placetype":"venue"
},
  "geometry": {"coordinates":[-82.09537899999999,39.331289],"type":"Point"}
}