{
  "type": "Feature",
  "properties": {
    "addr:full": "5633 Woodridge Dr Toledo OH 43623",
    "addr:housenumber": "5633",
    "addr:postcode": "43623",
    "addr:street": "Woodridge Dr",
    "iso:country": "US",
    "sg:address": "5633 Woodridge Dr",
    "sg:city": "Toledo",
    "sg:classifiers": [
      {
        "category": "Wholesale",
        "subcategory": "Metals \u0026 Minerals",
        "type": "Manufacturing \u0026 Wholesale Goods"
      }
    ],
    "sg:phone": "+1 419 882 8922",
    "sg:postcode": "43623",
    "sg:province": "OH",
    "sg:tags": [
      "consulting",
      "management",
      "center"
    ],
    "wof:name": "Neutectic",
    "wof:placetype": "venue"
  },
  "geometry": {"coordinates":[-83.661788,41.716695],"type":"Point"}
}
