{
  "type": "Feature",
  "properties": {
    "iso:country":"US",
    "sg:address":"35 Bierly Rd",
    "sg:city":"Portsmouth",
    "sg:classifiers":[
        {
            "category":"Insurance",
            "subcategory":"Insurance Agent",
            "type":"Services"
        }
    ],
    "sg:phone":"+1 740 354 2848",
    "sg:postcode":"45662",
    "sg:province":"OH",
    "wof:name":"Western-Southern Life Ins Co",
    "wof:placetype":"venue"
},
  "geometry": {"coordinates":[-82.983823,38.802579],"type":"Point"}
}