{
  "type": "Feature",
  "properties": {
    "iso:country":"US",
    "sg:address":"1 Performance Pl",
    "sg:city":"Youngstown",
    "sg:classifiers":[
        {
            "category":"Manufacturing",
            "subcategory":"Metals",
            "type":"Manufacturing & Wholesale Goods"
        }
    ],
    "sg:phone":"+1 330 744 9505",
    "sg:postcode":"44502",
    "sg:province":"OH",
    "sg:tags":[
        "extruded",
        "product",
        "aluminum",
        "mfg"
    ],
    "sg:website":"http://www.exal.com",
    "wof:name":"Exal Corporation",
    "wof:placetype":"venue"
},
  "geometry": {"coordinates":[-80.64006000000001,41.091019],"type":"Point"}
}