{
  "type": "Feature",
  "properties": {
    "iso:country":"US",
    "sg:address":"4597 Belden Village St NW",
    "sg:city":"Canton",
    "sg:classifiers":[
        {
            "category":"Shopping",
            "subcategory":"Clothing, Apparel, & Fashions",
            "type":"Retail Goods"
        }
    ],
    "sg:phone":"+1 330 493 0117",
    "sg:postcode":"44718",
    "sg:province":"OH",
    "sg:tags":[
        "retailer",
        "furnishing"
    ],
    "wof:name":"Adam's Mens Clothier",
    "wof:placetype":"venue"
},
  "geometry": {"coordinates":[-81.434529,40.856538],"type":"Point"}
}