{
  "type": "Feature",
  "properties": {
    "iso:country":"US",
    "sg:address":"9506 Centerbrook Ct",
    "sg:city":"Dayton",
    "sg:classifiers":[
        {
            "category":"Professional",
            "subcategory":"Engineering",
            "type":"Services"
        }
    ],
    "sg:phone":"+1 937 885 1723",
    "sg:postcode":"45458",
    "sg:province":"OH",
    "sg:tags":[
        "engineer"
    ],
    "wof:name":"Scitech National",
    "wof:placetype":"venue"
},
  "geometry": {"coordinates":[-84.15655700000001,39.603351],"type":"Point"}
}