{
  "type": "Feature",
  "properties": {
    "addr:full": "9506 Centerbrook Ct Dayton OH 45458",
    "addr:housenumber": "9506",
    "addr:postcode": "45458",
    "addr:street": "Centerbrook Ct",
    "iso:country": "US",
    "sg:address": "9506 Centerbrook Ct",
    "sg:city": "Dayton",
    "sg:classifiers": [
      {
        "category": "Professional",
        "subcategory": "Engineering",
        "type": "Services"
      }
    ],
    "sg:phone": "+1 937 885 1723",
    "sg:postcode": "45458",
    "sg:province": "OH",
    "sg:tags": [
      "engineer"
    ],
    "wof:name": "Scitech National",
    "wof:placetype": "venue"
  },
  "geometry": {"coordinates":[-84.156557,39.603351],"type":"Point"}
}
