{
  "type": "Feature",
  "properties": {
    "iso:country":"US",
    "sg:address":"644 Linn St",
    "sg:city":"Cincinnati",
    "sg:classifiers":[
        {
            "category":"Professional",
            "subcategory":"Accounting & Tax Preparation",
            "type":"Services"
        }
    ],
    "sg:phone":"+1 513 621 2299",
    "sg:postcode":"45203",
    "sg:province":"OH",
    "sg:tags":[
        "accountant"
    ],
    "wof:name":"Andrew Littner Mancini",
    "wof:placetype":"venue"
},
  "geometry": {"coordinates":[-84.528935,39.104113],"type":"Point"}
}