{
  "type": "Feature",
  "properties": {
    "addr:full": "3760 Darrow Rd Stow OH 44224",
    "addr:housenumber": "3760",
    "addr:postcode": "44224",
    "addr:street": "Darrow Rd",
    "iso:country": "US",
    "sg:address": "3760 Darrow Rd",
    "sg:city": "Stow",
    "sg:classifiers": [
      {
        "category": "Government",
        "subcategory": "Office",
        "type": "Public Place"
      }
    ],
    "sg:phone": "+1 330 689 2869",
    "sg:postcode": "44224",
    "sg:province": "OH",
    "sg:tags": [
      "village"
    ],
    "wof:name": "Stow Law Dept",
    "wof:placetype": "venue"
  },
  "geometry": {"coordinates":[-81.440451,41.168327],"type":"Point"}
}
