{
  "type": "Feature",
  "properties": {
    "addr:full": "1101 Walnut Valley Ln Dayton OH 45458",
    "addr:housenumber": "1101",
    "addr:postcode": "45458",
    "addr:street": "Walnut Valley Ln",
    "iso:country": "US",
    "sg:address": "1101 Walnut Valley Ln",
    "sg:city": "Dayton",
    "sg:classifiers": [
      {
        "category": "Manufacturing",
        "subcategory": "Apparel",
        "type": "Manufacturing \u0026 Wholesale Goods"
      }
    ],
    "sg:phone": "+1 937 885 4571",
    "sg:postcode": "45458",
    "sg:province": "OH",
    "sg:tags": [
      "sewing",
      "contractor"
    ],
    "wof:name": "Sew Special Designs",
    "wof:placetype": "venue"
  },
  "geometry": {"coordinates":[-84.152022,39.591012],"type":"Point"}
}
