{
  "type": "Feature",
  "properties": {
    "iso:country":"US",
    "sg:address":"1101 Walnut Valley Ln",
    "sg:city":"Dayton",
    "sg:classifiers":[
        {
            "category":"Manufacturing",
            "subcategory":"Apparel",
            "type":"Manufacturing & Wholesale Goods"
        }
    ],
    "sg:phone":"+1 937 885 4571",
    "sg:postcode":"45458",
    "sg:province":"OH",
    "sg:tags":[
        "sewing",
        "contractor"
    ],
    "wof:name":"Sew Special Designs",
    "wof:placetype":"venue"
},
  "geometry": {"coordinates":[-84.152022,39.591012],"type":"Point"}
}