{
  "type": "Feature",
  "properties": {
    "addr:full": "200 Broadway St Jackson OH 45640",
    "addr:housenumber": "200",
    "addr:postcode": "45640",
    "addr:street": "Broadway St",
    "iso:country": "US",
    "sg:address": "200 Broadway St",
    "sg:city": "Jackson",
    "sg:classifiers": [
      {
        "category": "Government",
        "subcategory": "Office",
        "type": "Public Place"
      }
    ],
    "sg:phone": "+1 740 286 3970",
    "sg:postcode": "45640",
    "sg:province": "OH",
    "sg:tags": [
      "village"
    ],
    "wof:name": "Visitors Convention Commission",
    "wof:placetype": "venue"
  },
  "geometry": {"coordinates":[-82.636961,39.051975],"type":"Point"}
}
