{
  "type": "Feature",
  "properties": {
    "addr:full":"4651 Morse Centre Rd Columbus OH 43229",
    "addr:housenumber":"4651",
    "addr:postcode":"43229",
    "addr:street":"Morse Centre Rd",
    "iso:country":"US",
    "sg:address":"4651 Morse Centre Rd",
    "sg:city":"Columbus",
    "sg:classifiers":[
        {
            "category":"Banks & Credit Unions",
            "subcategory":"Bank",
            "type":"Services"
        }
    ],
    "sg:phone":"+1 614 433 9522",
    "sg:postcode":"43229",
    "sg:province":"OH",
    "sg:tags":[
        "personal",
        "institution"
    ],
    "wof:name":"Wells Fargo",
    "wof:placetype":"venue"
},
  "geometry": {"coordinates":[-82.96257799999999,40.06046],"type":"Point"}
}