{
  "type": "Feature",
  "properties": {
    "addr:full": "240 S Cassady Ave Columbus OH 43209",
    "addr:housenumber": "240",
    "addr:postcode": "43209",
    "addr:street": "S Cassady Ave",
    "iso:country": "US",
    "sg:address": "240 S Cassady Ave",
    "sg:city": "Columbus",
    "sg:classifiers": [
      {
        "category": "Home \u0026 Garden",
        "subcategory": "Building Materials",
        "type": "Retail Goods"
      }
    ],
    "sg:phone": "+1 614 338 8225",
    "sg:postcode": "43209",
    "sg:province": "OH",
    "sg:tags": [
      "paint"
    ],
    "wof:name": "Gateway Paint",
    "wof:placetype": "venue"
  },
  "geometry": {"coordinates":[-82.933366,39.964163],"type":"Point"}
}
