{
  "type": "Feature",
  "properties": {
    "iso:country":"US",
    "sg:address":"240 S Cassady Ave",
    "sg:city":"Columbus",
    "sg:classifiers":[
        {
            "category":"Home & Garden",
            "subcategory":"Building Materials",
            "type":"Retail Goods"
        }
    ],
    "sg:phone":"+1 614 338 8225",
    "sg:postcode":"43209",
    "sg:province":"OH",
    "sg:tags":[
        "paint"
    ],
    "wof:name":"Gateway Paint",
    "wof:placetype":"venue"
},
  "geometry": {"coordinates":[-82.93336600000001,39.964163],"type":"Point"}
}