{
  "type": "Feature",
  "properties": {
    "iso:country":"US",
    "sg:address":"16650 Chagrin Blvd",
    "sg:city":"Cleveland",
    "sg:classifiers":[
        {
            "category":"Shopping",
            "subcategory":"Clothing, Apparel, & Fashions",
            "type":"Retail Goods"
        }
    ],
    "sg:phone":"+1 216 751 9447",
    "sg:postcode":"44120",
    "sg:province":"OH",
    "sg:tags":[
        "wig",
        "toupee",
        "hairpiece"
    ],
    "wof:name":"Lowry's Wigs & Accessories",
    "wof:placetype":"venue"
},
  "geometry": {"coordinates":[-81.559577,41.464422],"type":"Point"}
}