{
  "type": "Feature",
  "properties": {
    "iso:country":"US",
    "sg:address":"2450 Performance Way",
    "sg:city":"Columbus",
    "sg:classifiers":[
        {
            "category":"Professional",
            "type":"Services"
        }
    ],
    "sg:phone":"+1 614 437 1166",
    "sg:postcode":"43207",
    "sg:province":"OH",
    "sg:tags":[
        "establishment"
    ],
    "wof:name":"Divine Inc",
    "wof:placetype":"venue"
},
  "geometry": {"coordinates":[-82.944522,39.916202],"type":"Point"}
}