{
  "type": "Feature",
  "properties": {
    "addr:full": "2125 E Harbor Rd Port Clinton OH 43452",
    "addr:housenumber": "2125 e",
    "addr:postcode": "43452",
    "addr:street": "Harbor Rd",
    "iso:country": "US",
    "sg:address": "2125 E Harbor Rd",
    "sg:city": "Port Clinton",
    "sg:classifiers": [
      {
        "category": "Building \u0026 Trades",
        "subcategory": "Construction",
        "type": "Services"
      }
    ],
    "sg:phone": "+1 419 732 3488",
    "sg:postcode": "43452",
    "sg:province": "OH",
    "sg:tags": [
      "general",
      "contractor"
    ],
    "wof:name": "Ken Gill Construction LLC",
    "wof:placetype": "venue"
  },
  "geometry": {"coordinates":[-82.897555,41.51657],"type":"Point"}
}
