{
  "type": "Feature",
  "properties": {
    "addr:full": "130 E 6th Ave Lancaster OH 43130",
    "addr:housenumber": "130",
    "addr:postcode": "43130",
    "addr:street": "E 6Th Ave",
    "iso:country": "US",
    "sg:address": "130 E 6th Ave",
    "sg:city": "Lancaster",
    "sg:classifiers": [
      {
        "category": "Shopping",
        "type": "Retail Goods"
      }
    ],
    "sg:phone": "+1 740 653 5555",
    "sg:postcode": "43130",
    "sg:province": "OH",
    "sg:tags": [
      "coin",
      "dealer",
      "supply"
    ],
    "wof:name": "Bigg Fredd's Coin \u0026 Stamp Shop",
    "wof:placetype": "venue"
  },
  "geometry": {"coordinates":[-82.600682,39.719817],"type":"Point"}
}
