{
  "type": "Feature",
  "properties": {
    "iso:country":"US",
    "sg:address":"1867 Millville Oxford Rd",
    "sg:city":"Hamilton",
    "sg:classifiers":[
        {
            "category":"Building & Trades",
            "subcategory":"Construction",
            "type":"Services"
        }
    ],
    "sg:phone":"+1 937 608 5158",
    "sg:postcode":"45013",
    "sg:province":"OH",
    "sg:tags":[
        "carpentry",
        "contractor"
    ],
    "wof:name":"Brunen & Cross Quality Custom",
    "wof:placetype":"venue"
},
  "geometry": {"coordinates":[-84.679832,39.436531],"type":"Point"}
}