{
  "type": "Feature",
  "properties": {
    "addr:full":"11385 Montgomery Rd Cincinnati OH 45249",
    "addr:housenumber":"11385",
    "addr:postcode":"45249",
    "addr:street":"Montgomery Rd",
    "iso:country":"US",
    "sg:address":"11385 Montgomery Rd",
    "sg:city":"Cincinnati",
    "sg:classifiers":[
        {
            "category":"Real Estate",
            "subcategory":"Real Estate Operator",
            "type":"Services"
        },
        {
            "category":"Restaurant",
            "type":"Food & Drink"
        }
    ],
    "sg:phone":"+1 513 605 4700",
    "sg:postcode":"45249",
    "sg:province":"OH",
    "sg:tags":[
        "property",
        "lessor"
    ],
    "wof:name":"Sanders Ventures Inc",
    "wof:placetype":"venue"
},
  "geometry": {"coordinates":[-84.328563,39.270473],"type":"Point"}
}