{
  "type": "Feature",
  "properties": {
    "iso:country":"US",
    "sg:address":"8059 Lewis Rd",
    "sg:city":"Berea",
    "sg:classifiers":[
        {
            "category":"Manufacturing",
            "subcategory":"Furniture",
            "type":"Manufacturing & Wholesale Goods"
        }
    ],
    "sg:phone":"+1 440 235 2759",
    "sg:postcode":"44017",
    "sg:province":"OH",
    "sg:tags":[
        "blind",
        "mfg"
    ],
    "wof:name":"House of Blinds",
    "wof:placetype":"venue"
},
  "geometry": {"coordinates":[-81.896517,41.374973],"type":"Point"}
}