{
  "type": "Feature",
  "properties": {
    "addr:full": "6311 Saint Clair Ave Cleveland OH 44103",
    "addr:housenumber": "6311",
    "addr:postcode": "44103",
    "addr:street": "Saint Clair Ave",
    "iso:country": "US",
    "sg:address": "6311 Saint Clair Ave",
    "sg:city": "Cleveland",
    "sg:classifiers": [
      {
        "category": "Social Services",
        "type": "Services"
      }
    ],
    "sg:phone": "+1 216 361 7950",
    "sg:postcode": "44103",
    "sg:province": "OH",
    "wof:name": "Hijos De Borinqun Spansh Amer",
    "wof:placetype": "venue"
  },
  "geometry": {"coordinates":[-81.646106,41.52493],"type":"Point"}
}
