{
  "type": "Feature",
  "properties": {
    "addr:full":"430 Reading Rd Cincinnati OH 45202",
    "addr:housenumber":"430",
    "addr:postcode":"45202",
    "addr:street":"Reading Rd",
    "iso:country":"US",
    "sg:address":"430 Reading Rd",
    "sg:city":"Cincinnati",
    "sg:classifiers":[
        {
            "category":"Professional",
            "subcategory":"Lawyer & Legal Services",
            "type":"Services"
        }
    ],
    "sg:phone":"+1 513 721 8880",
    "sg:postcode":"45202",
    "sg:province":"OH",
    "sg:tags":[
        "attorney"
    ],
    "wof:name":"Stanley Litz",
    "wof:placetype":"venue"
},
  "geometry": {"coordinates":[-84.50662699999999,39.1089],"type":"Point"}
}