{
  "type": "Feature",
  "properties": {
    "addr:full":"18 N Market St Girard OH 44420",
    "addr:housenumber":"18",
    "addr:postcode":"44420",
    "addr:street":"N Market St",
    "iso:country":"US",
    "sg:address":"18 N Market St",
    "sg:city":"Girard",
    "sg:classifiers":[
        {
            "category":"Insurance",
            "subcategory":"Insurance Agent",
            "type":"Services"
        }
    ],
    "sg:phone":"+1 330 545 5489",
    "sg:postcode":"44420",
    "sg:province":"OH",
    "wof:name":"Griffith Agency Inc",
    "wof:placetype":"venue"
},
  "geometry": {"coordinates":[-80.70276699999999,41.154344],"type":"Point"}
}