{
  "type": "Feature",
  "properties": {
    "addr:full": "6532 Solon Blvd Solon OH 44139",
    "addr:housenumber": "6532",
    "addr:postcode": "44139",
    "addr:street": "Solon Blvd",
    "iso:country": "US",
    "sg:address": "6532 Solon Blvd",
    "sg:city": "Solon",
    "sg:classifiers": [
      {
        "category": "Professional",
        "type": "Services"
      }
    ],
    "sg:phone": "+1 440 498 1357",
    "sg:postcode": "44139",
    "sg:province": "OH",
    "wof:name": "Bestinvest Ltd",
    "wof:placetype": "venue"
  },
  "geometry": {"coordinates":[-81.443155,41.380376],"type":"Point"}
}
