{
  "type": "Feature",
  "properties": {
    "addr:full":"29325 Chagrin Blvd Cleveland OH 44122",
    "addr:housenumber":"29325",
    "addr:postcode":"44122",
    "addr:street":"Chagrin Blvd",
    "iso:country":"US",
    "sg:address":"29325 Chagrin Blvd",
    "sg:city":"Cleveland",
    "sg:classifiers":[
        {
            "category":"Home & Garden",
            "subcategory":"Building Materials",
            "type":"Retail Goods"
        }
    ],
    "sg:phone":"+1 216 514 3500",
    "sg:postcode":"44122",
    "sg:province":"OH",
    "sg:tags":[
        "siding"
    ],
    "wof:name":"Gentek Building Products",
    "wof:placetype":"venue"
},
  "geometry": {"coordinates":[-81.473934,41.462429],"type":"Point"}
}