{
  "type": "Feature",
  "properties": {
    "iso:country":"US",
    "sg:address":"5412 Homegardner Rd",
    "sg:city":"Castalia",
    "sg:classifiers":[
        {
            "category":"Wholesale",
            "subcategory":"Machinery & Supplies",
            "type":"Manufacturing & Wholesale Goods"
        },
        {
            "category":"Professional",
            "subcategory":"Engineering",
            "type":"Services"
        }
    ],
    "sg:phone":"+1 419 684 7400",
    "sg:postcode":"44824",
    "sg:province":"OH",
    "sg:tags":[
        "machine",
        "repair",
        "fabricates",
        "parts",
        "design"
    ],
    "wof:name":"Sawyer & Smith Corporation",
    "wof:placetype":"venue"
},
  "geometry": {"coordinates":[-82.784408,41.42515],"type":"Point"}
}