{
  "type": "Feature",
  "properties": {
    "addr:full": "5412 Homegardner Rd Castalia OH 44824",
    "addr:housenumber": "5412",
    "addr:postcode": "44824",
    "addr:street": "Homegardner Rd",
    "iso:country": "US",
    "sg:address": "5412 Homegardner Rd",
    "sg:city": "Castalia",
    "sg:classifiers": [
      {
        "category": "Wholesale",
        "subcategory": "Machinery \u0026 Supplies",
        "type": "Manufacturing \u0026 Wholesale Goods"
      },
      {
        "category": "Professional",
        "subcategory": "Engineering",
        "type": "Services"
      }
    ],
    "sg:phone": "+1 419 684 7400",
    "sg:postcode": "44824",
    "sg:province": "OH",
    "sg:tags": [
      "machine",
      "repair",
      "fabricates",
      "parts",
      "design"
    ],
    "wof:name": "Sawyer \u0026 Smith Corporation",
    "wof:placetype": "venue"
  },
  "geometry": {"coordinates":[-82.784408,41.42515],"type":"Point"}
}
