{
  "type": "Feature",
  "properties": {
    "addr:full": "6011 Groveport Rd Groveport OH 43125",
    "addr:postcode": "6011;43125",
    "addr:street": "Groveport Rd",
    "iso:country": "US",
    "sg:address": "6011 Groveport Rd",
    "sg:city": "Groveport",
    "sg:classifiers": [
      {
        "category": "Food \u0026 Beverages",
        "subcategory": "Groceries \u0026 Convenience Stores",
        "type": "Retail Goods"
      }
    ],
    "sg:phone": "+1 614 830 2010",
    "sg:postcode": "43125",
    "sg:province": "OH",
    "sg:website": "www.kroger.com",
    "wof:name": "Kroger",
    "wof:placetype": "venue"
  },
  "geometry": {"coordinates":[-82.898142,39.855026],"type":"Point"}
}
