{
  "type": "Feature",
  "properties": {
    "addr:full":"11694 Hayden St Hiram OH 44234",
    "addr:housenumber":"11694",
    "addr:postcode":"44234",
    "addr:street":"Hayden St",
    "iso:country":"US",
    "sg:address":"11694 Hayden St",
    "sg:city":"Hiram",
    "sg:classifiers":[
        {
            "category":"Education",
            "subcategory":"Library",
            "type":"Public Place"
        }
    ],
    "sg:phone":"+1 330 569 5359",
    "sg:postcode":"44234",
    "sg:province":"OH",
    "wof:name":"Hiram College Library",
    "wof:placetype":"venue"
},
  "geometry": {"coordinates":[-81.144976,41.309528],"type":"Point"}
}