{
  "type": "Feature",
  "properties": {
    "iso:country":"US",
    "sg:address":"10418 Christina Dr",
    "sg:city":"Willoughby",
    "sg:classifiers":[
        {
            "category":"Food & Beverages",
            "subcategory":"Bakery",
            "type":"Retail Goods"
        }
    ],
    "sg:phone":"+1 440 256 4301",
    "sg:postcode":"44094",
    "sg:province":"OH",
    "wof:name":"Wojtila Bakery",
    "wof:placetype":"venue"
},
  "geometry": {"coordinates":[-81.326398,41.591382],"type":"Point"}
}