{
  "type": "Feature",
  "properties": {
    "addr:full": "4368 Dues Dr Cincinnati OH 45246",
    "addr:housenumber": "4368",
    "addr:postcode": "45246",
    "addr:street": "Dues Dr",
    "iso:country": "US",
    "sg:address": "4368 Dues Dr",
    "sg:city": "Cincinnati",
    "sg:classifiers": [
      {
        "category": "Wholesale",
        "subcategory": "Motor Vehicles",
        "type": "Manufacturing \u0026 Wholesale Goods"
      },
      {
        "category": "Travel",
        "subcategory": "Travel Agent",
        "type": "Entertainment"
      },
      {
        "category": "Retail",
        "subcategory": "Storage",
        "type": "Services"
      },
      {
        "category": "Retail",
        "subcategory": "Auto Repair",
        "type": "Services"
      }
    ],
    "sg:phone": "+1 513 874 9658",
    "sg:postcode": "45246",
    "sg:province": "OH",
    "sg:tags": [
      "campers-wholesale",
      "portable",
      "recreational",
      "trailers-repair",
      "truck",
      "trailer",
      "unit",
      "manufacturer"
    ],
    "wof:name": "Richter Repair Service",
    "wof:placetype": "venue"
  },
  "geometry": {"coordinates":[-84.476573,39.309929],"type":"Point"}
}
