{
  "type": "Feature",
  "properties": {
    "addr:full": "822 Sellars Dr Jackson OH 45640",
    "addr:housenumber": "822",
    "addr:postcode": "45640",
    "addr:street": "Sellars Dr",
    "iso:country": "US",
    "sg:address": "822 Sellars Dr",
    "sg:city": "Jackson",
    "sg:classifiers": [
      {
        "category": "Education",
        "subcategory": "School",
        "type": "Public Place"
      }
    ],
    "sg:phone": "+1 740 286 6491",
    "sg:postcode": "45640",
    "sg:province": "OH",
    "wof:name": "Hope Haven School",
    "wof:placetype": "venue"
  },
  "geometry": {"coordinates":[-82.630979,39.039007],"type":"Point"}
}
