{
  "type": "Feature",
  "properties": {
    "addr:full":"1234 S Shannon St Van Wert OH 45891",
    "addr:housenumber":"1234",
    "addr:postcode":"45891",
    "addr:street":"S Shannon St",
    "iso:country":"US",
    "sg:address":"1234 S Shannon St",
    "sg:city":"Van Wert",
    "sg:classifiers":[
        {
            "category":"Restaurant",
            "type":"Food & Drink"
        }
    ],
    "sg:menulink":"http://www.allmenus.com/oh/pleasant/164600-wendys/menu/",
    "sg:phone":"+1 419 238 2813",
    "sg:postcode":"45891",
    "sg:province":"OH",
    "sg:tags":[
        "burger",
        "american",
        "soup"
    ],
    "wof:name":"Wendy's",
    "wof:placetype":"venue"
},
  "geometry": {"coordinates":[-84.597847,40.857454],"type":"Point"}
}