{
  "type": "Feature",
  "properties": {
    "addr:full": "760 Dever Rd Oak Hill OH 45648",
    "addr:housenumber": "760",
    "addr:postcode": "45648",
    "addr:street": "Dever Rd",
    "iso:country": "US",
    "sg:address": "760 Dever Rd",
    "sg:city": "Oak Hill",
    "sg:classifiers": [
      {
        "category": "Manufacturing",
        "subcategory": "Rubber \u0026 Plastics",
        "type": "Manufacturing \u0026 Wholesale Goods"
      }
    ],
    "sg:phone": "+1 740 286 5858",
    "sg:postcode": "45648",
    "sg:province": "OH",
    "sg:tags": [
      "repair",
      "mfg",
      "mechanical"
    ],
    "wof:name": "Loftus Auto",
    "wof:placetype": "venue"
  },
  "geometry": {"coordinates":[-82.897099,38.926875],"type":"Point"}
}
