{
  "type": "Feature",
  "properties": {
    "addr:full": "26 Scioto St Ashville OH 43103",
    "addr:housenumber": "26",
    "addr:postcode": "43103",
    "addr:street": "Scioto St",
    "iso:country": "US",
    "sg:address": "26 Scioto St",
    "sg:city": "Ashville",
    "sg:classifiers": [
      {
        "category": "Professional",
        "subcategory": "Lawyer \u0026 Legal Services",
        "type": "Services"
      }
    ],
    "sg:phone": "+1 614 877 4730",
    "sg:postcode": "43103",
    "sg:province": "OH",
    "sg:tags": [
      "attorney"
    ],
    "wof:name": "Wildman Schooley LLC",
    "wof:placetype": "venue"
  },
  "geometry": {"coordinates":[-82.957251,39.713478],"type":"Point"}
}
