{
  "type": "Feature",
  "properties": {
    "addr:full": "16574 Broadway Ave Cleveland OH 44137",
    "addr:housenumber": "16574",
    "addr:postcode": "44137",
    "addr:street": "Broadway Ave",
    "iso:country": "US",
    "sg:address": "16574 Broadway Ave",
    "sg:city": "Cleveland",
    "sg:classifiers": [
      {
        "category": "Social Services",
        "subcategory": "Child Care",
        "type": "Services"
      }
    ],
    "sg:phone": "+1 216 475 6464",
    "sg:postcode": "44137",
    "sg:province": "OH",
    "wof:name": "Creative Playrooms",
    "wof:placetype": "venue"
  },
  "geometry": {"coordinates":[-81.563248,41.410448],"type":"Point"}
}
