{
  "type": "Feature",
  "properties": {
    "addr:full": "410 Elizabeth St Proctorville OH 45669",
    "addr:housenumber": "410",
    "addr:postcode": "45669",
    "addr:street": "Elizabeth St",
    "iso:country": "US",
    "sg:address": "410 Elizabeth St",
    "sg:city": "Proctorville",
    "sg:classifiers": [
      {
        "category": "Education",
        "subcategory": "Library",
        "type": "Public Place"
      }
    ],
    "sg:phone": "+1 740 886 6697",
    "sg:postcode": "45669",
    "sg:province": "OH",
    "sg:tags": [
      "executive"
    ],
    "sg:website": "www.briggslibrary.com",
    "wof:name": "Briggs Lawrence County Library",
    "wof:placetype": "venue"
  },
  "geometry": {"coordinates":[-82.377832,38.437246],"type":"Point"}
}
