{
  "type": "Feature",
  "properties": {
    "addr:full": "26415 Warns Dr Perrysburg OH 43551",
    "addr:postcode": "26415;43551",
    "addr:street": "Warns Dr",
    "iso:country": "US",
    "sg:address": "26415 Warns Dr",
    "sg:city": "Perrysburg",
    "sg:classifiers": [
      {
        "category": "Restaurant",
        "type": "Food \u0026 Drink"
      }
    ],
    "sg:phone": "+1 419 837 1065",
    "sg:postcode": "43551",
    "sg:province": "OH",
    "sg:tags": [
      "eating"
    ],
    "wof:name": "Cookery",
    "wof:placetype": "venue"
  },
  "geometry": {"coordinates":[-83.459059,41.535163],"type":"Point"}
}
