{
  "type": "Feature",
  "properties": {
    "iso:country":"US",
    "sg:address":"1553 W 102nd St",
    "sg:city":"Cleveland",
    "sg:classifiers":[
        {
            "category":"Home & Garden",
            "subcategory":"Building Materials",
            "type":"Retail Goods"
        }
    ],
    "sg:phone":"+1 216 281 6500",
    "sg:postcode":"44102",
    "sg:province":"OH",
    "sg:tags":[
        "glass",
        "window",
        "plate"
    ],
    "wof:name":"Bowen Auto Sales",
    "wof:placetype":"venue"
},
  "geometry": {"coordinates":[-81.755673,41.478406],"type":"Point"}
}