{
  "type": "Feature",
  "properties": {
    "addr:full":"75 E Gay St Columbus OH 43215",
    "addr:housenumber":"75",
    "addr:postcode":"43215",
    "addr:street":"E Gay St",
    "iso:country":"US",
    "sg:address":"75 E Gay St",
    "sg:city":"Columbus",
    "sg:classifiers":[
        {
            "category":"Organizations",
            "subcategory":"Political Organization",
            "type":"Services"
        }
    ],
    "sg:phone":"+1 614 224 9306",
    "sg:postcode":"43215",
    "sg:province":"OH",
    "wof:name":"Supreme Court Campaign",
    "wof:placetype":"venue"
},
  "geometry": {"coordinates":[-82.999342,39.963688],"type":"Point"}
}