{
  "type": "Feature",
  "properties": {
    "iso:country":"US",
    "sg:address":"2506 Beechmont Ave",
    "sg:city":"Cincinnati",
    "sg:phone":"+1 513 233 2900",
    "sg:postcode":"45230",
    "sg:province":"OH",
    "wof:name":"Berkshire Realty Group",
    "wof:placetype":"venue"
},
  "geometry": {"coordinates":[-84.386909,39.101096],"type":"Point"}
}