{
  "type": "Feature",
  "properties": {
    "addr:full":"4024 Hamilton Ave Cincinnati OH 45223",
    "addr:housenumber":"4024",
    "addr:postcode":"45223",
    "addr:street":"Hamilton Ave",
    "iso:country":"US",
    "sg:address":"4024 Hamilton Ave",
    "sg:city":"Cincinnati",
    "sg:classifiers":[
        {
            "category":"Shopping",
            "subcategory":"Used Merchandise",
            "type":"Retail Goods"
        }
    ],
    "sg:phone":"+1 513 542 3849",
    "sg:postcode":"45223",
    "sg:province":"OH",
    "sg:tags":[
        "antique"
    ],
    "wof:name":"Peersons Antiques",
    "wof:placetype":"venue"
},
  "geometry": {"coordinates":[-84.539306,39.160088],"type":"Point"}
}