{
  "type": "Feature",
  "properties": {
    "addr:full":"6077 Ashley Ct Cincinnati OH 45242",
    "addr:housenumber":"6077",
    "addr:postcode":"45242",
    "addr:street":"Ashley Ct",
    "iso:country":"US",
    "sg:address":"6077 Ashley Ct",
    "sg:city":"Cincinnati",
    "sg:classifiers":[
        {
            "category":"Building & Trades",
            "subcategory":"Construction",
            "type":"Services"
        }
    ],
    "sg:phone":"+1 513 793 7212",
    "sg:postcode":"45242",
    "sg:province":"OH",
    "sg:tags":[
        "steel",
        "fabrication",
        "welding"
    ],
    "wof:name":"International Mold Steel Inc",
    "wof:placetype":"venue"
},
  "geometry": {"coordinates":[-84.367367,39.242518],"type":"Point"}
}