{
  "type": "Feature",
  "properties": {
    "iso:country":"US",
    "sg:address":"125 W Main St",
    "sg:city":"Barnesville",
    "sg:classifiers":[
        {
            "category":"Personal",
            "subcategory":"Beauty Salon",
            "type":"Services"
        }
    ],
    "sg:phone":"+1 740 425 1866",
    "sg:postcode":"43713",
    "sg:province":"OH",
    "wof:name":"Chels LTD Beauty Salon",
    "wof:placetype":"venue"
},
  "geometry": {"coordinates":[-81.178476,39.988168],"type":"Point"}
}