{
  "type": "Feature",
  "properties": {
    "addr:full":"9 N 3rd St Newark OH 43055",
    "addr:housenumber":"9",
    "addr:postcode":"43055",
    "addr:street":"N 3Rd St",
    "iso:country":"US",
    "sg:address":"9 N 3rd St",
    "sg:city":"Newark",
    "sg:classifiers":[
        {
            "category":"Real Estate",
            "subcategory":"Real Estate Agent",
            "type":"Services"
        }
    ],
    "sg:phone":"+1 740 349 7844",
    "sg:postcode":"43055",
    "sg:province":"OH",
    "sg:website":"www.andersonlayman.com",
    "wof:name":"Anderson Layman Co",
    "wof:placetype":"venue"
},
  "geometry": {"coordinates":[-82.40275800000001,40.05806],"type":"Point"}
}