{
  "type": "Feature",
  "properties": {
    "addr:full":"4121 Westridge Dr Mason OH 45040",
    "addr:housenumber":"4121",
    "addr:postcode":"45040",
    "addr:street":"Westridge Dr",
    "iso:country":"US",
    "sg:address":"4121 Westridge Dr",
    "sg:city":"Mason",
    "sg:classifiers":[
        {
            "category":"Wholesale",
            "subcategory":"Non-durable Goods",
            "type":"Manufacturing & Wholesale Goods"
        }
    ],
    "sg:phone":"+1 513 754 3013",
    "sg:postcode":"45040",
    "sg:province":"OH",
    "sg:tags":[
        "distributing"
    ],
    "wof:name":"Smith Supply Company",
    "wof:placetype":"venue"
},
  "geometry": {"coordinates":[-84.33799999999999,39.380312],"type":"Point"}
}