{
  "type": "Feature",
  "properties": {
    "iso:country":"US",
    "sg:address":"1023 N Malone Rd",
    "sg:city":"Chillicothe",
    "sg:classifiers":[
        {
            "category":"Building & Trades",
            "subcategory":"Landscaping Services",
            "type":"Services"
        }
    ],
    "sg:phone":"+1 740 772 1798",
    "sg:postcode":"45601",
    "sg:province":"OH",
    "sg:tags":[
        "tree"
    ],
    "wof:name":"Rick's Tree Svc",
    "wof:placetype":"venue"
},
  "geometry": {"coordinates":[-82.990926,39.282057],"type":"Point"}
}