{
  "type": "Feature",
  "properties": {
    "addr:full": "122 Bridge St Warsaw OH 43844",
    "addr:housenumber": "122",
    "addr:postcode": "43844",
    "addr:street": "Bridge St",
    "iso:country": "US",
    "sg:address": "122 Bridge St",
    "sg:city": "Warsaw",
    "sg:classifiers": [
      {
        "category": "Food \u0026 Beverages",
        "subcategory": "Liquor \u0026 Beverages",
        "type": "Retail Goods"
      }
    ],
    "sg:phone": "+1 740 824 5163",
    "sg:postcode": "43844",
    "sg:province": "OH",
    "sg:tags": [
      "wine"
    ],
    "wof:name": "Wine \u0026 Son's Disposal",
    "wof:placetype": "venue"
  },
  "geometry": {"coordinates":[-82.005124,40.337576],"type":"Point"}
}
