{
  "type": "Feature",
  "properties": {
    "iso:country":"US",
    "sg:address":"122 Bridge St",
    "sg:city":"Warsaw",
    "sg:classifiers":[
        {
            "category":"Food & Beverages",
            "subcategory":"Liquor & Beverages",
            "type":"Retail Goods"
        }
    ],
    "sg:phone":"+1 740 824 5163",
    "sg:postcode":"43844",
    "sg:province":"OH",
    "sg:tags":[
        "wine"
    ],
    "wof:name":"Wine & Son's Disposal",
    "wof:placetype":"venue"
},
  "geometry": {"coordinates":[-82.005124,40.337576],"type":"Point"}
}