{
  "type": "Feature",
  "properties": {
    "iso:country":"US",
    "sg:address":"4985 Cinnamon Ct",
    "sg:city":"Cincinnati",
    "sg:classifiers":[
        {
            "category":"Banks & Credit Unions",
            "subcategory":"Investment Brokerage",
            "type":"Services"
        }
    ],
    "sg:phone":"+1 513 474 8777",
    "sg:postcode":"45244",
    "sg:province":"OH",
    "sg:tags":[
        "funds",
        "mutual"
    ],
    "wof:name":"Berger Mutual Funds",
    "wof:placetype":"venue"
},
  "geometry": {"coordinates":[-84.294116,39.136018],"type":"Point"}
}