{
  "type": "Feature",
  "properties": {
    "addr:full": "4985 Cinnamon Ct Cincinnati OH 45244",
    "addr:housenumber": "4985",
    "addr:postcode": "45244",
    "addr:street": "Cinnamon Ct",
    "iso:country": "US",
    "sg:address": "4985 Cinnamon Ct",
    "sg:city": "Cincinnati",
    "sg:classifiers": [
      {
        "category": "Banks \u0026 Credit Unions",
        "subcategory": "Investment Brokerage",
        "type": "Services"
      }
    ],
    "sg:phone": "+1 513 474 8777",
    "sg:postcode": "45244",
    "sg:province": "OH",
    "sg:tags": [
      "funds",
      "mutual"
    ],
    "wof:name": "Berger Mutual Funds",
    "wof:placetype": "venue"
  },
  "geometry": {"coordinates":[-84.294116,39.136018],"type":"Point"}
}
