{
  "type": "Feature",
  "properties": {
    "addr:full": "6220 Doewood Ct Columbus OH 43229",
    "addr:housenumber": "6220",
    "addr:postcode": "43229",
    "addr:street": "Doewood Ct",
    "iso:country": "US",
    "sg:address": "6220 Doewood Ct",
    "sg:city": "Columbus",
    "sg:classifiers": [
      {
        "category": "Freight",
        "type": "Transportation"
      }
    ],
    "sg:phone": "+1 614 523 3833",
    "sg:postcode": "43229",
    "sg:province": "OH",
    "wof:name": "C M Logistics",
    "wof:placetype": "venue"
  },
  "geometry": {"coordinates":[-82.953993,40.096531],"type":"Point"}
}
