{
  "type": "Feature",
  "properties": {
    "addr:full": "3604 Wilmington Pike Kettering OH 45429",
    "addr:housenumber": "3604",
    "addr:postcode": "45429",
    "addr:street": "Wilmington Pike",
    "iso:country": "US",
    "sg:address": "3604 Wilmington Pike",
    "sg:city": "Kettering",
    "sg:classifiers": [
      {
        "category": "Health Services",
        "subcategory": "Doctor",
        "type": "Services"
      }
    ],
    "sg:phone": "+1 937 294 0066",
    "sg:postcode": "45429",
    "sg:province": "OH",
    "sg:tags": [
      "physician",
      "surgeon"
    ],
    "wof:name": "Doctors Urgent Care Office",
    "wof:placetype": "venue"
  },
  "geometry": {"coordinates":[-84.138185,39.694497],"type":"Point"}
}
