{
  "type": "Feature",
  "properties": {
    "iso:country":"US",
    "sg:address":"1444 W 5th Ave",
    "sg:city":"Columbus",
    "sg:classifiers":[
        {
            "category":"Food & Beverages",
            "subcategory":"Specialty",
            "type":"Retail Goods"
        }
    ],
    "sg:phone":"+1 614 487 8555",
    "sg:postcode":"43212",
    "sg:province":"OH",
    "wof:name":"Treasure Baskets",
    "wof:placetype":"venue"
},
  "geometry": {"coordinates":[-83.045581,39.988917],"type":"Point"}
}