{
  "type": "Feature",
  "properties": {
    "iso:country":"US",
    "sg:address":"1700 E 13th St",
    "sg:city":"Cleveland",
    "sg:classifiers":[
        {
            "category":"Professional",
            "subcategory":"Lawyer & Legal Services",
            "type":"Services"
        }
    ],
    "sg:phone":"+1 216 928 1501",
    "sg:postcode":"44114",
    "sg:province":"OH",
    "sg:tags":[
        "attorney"
    ],
    "wof:name":"Reserve Square Law Office",
    "wof:placetype":"venue"
},
  "geometry": {"coordinates":[-81.68372599999999,41.502916],"type":"Point"}
}