{
  "type": "Feature",
  "properties": {
    "addr:full": "838 Cherry St Blanchester OH 45107",
    "addr:housenumber": "838",
    "addr:postcode": "45107",
    "addr:street": "Cherry St",
    "iso:country": "US",
    "sg:address": "838 Cherry St",
    "sg:city": "Blanchester",
    "sg:classifiers": [
      {
        "category": "Manufacturing",
        "subcategory": "Retail Goods",
        "type": "Manufacturing \u0026 Wholesale Goods"
      }
    ],
    "sg:phone": "+1 937 783 2476",
    "sg:postcode": "45107",
    "sg:province": "OH",
    "sg:tags": [
      "manufacturer"
    ],
    "sg:website": "www.ccpi-inc.com",
    "wof:name": "CCPI Inc",
    "wof:placetype": "venue"
  },
  "geometry": {"coordinates":[-83.976683,39.296085],"type":"Point"}
}
