{
  "type": "Feature",
  "properties": {
    "addr:full":"4730 Warner Rd Cleveland OH 44125",
    "addr:housenumber":"4730",
    "addr:postcode":"44125",
    "addr:street":"Warner Rd",
    "iso:country":"US",
    "sg:address":"4730 Warner Rd",
    "sg:city":"Cleveland",
    "sg:classifiers":[
        {
            "category":"Freight",
            "type":"Transportation"
        }
    ],
    "sg:phone":"+1 216 271 4488",
    "sg:postcode":"44125",
    "sg:province":"OH",
    "sg:tags":[
        "general"
    ],
    "wof:name":"Meech Warehousing",
    "wof:placetype":"venue"
},
  "geometry": {"coordinates":[-81.63376,41.42257],"type":"Point"}
}