{
  "type": "Feature",
  "properties": {
    "addr:full": "554 E Sandusky Ave Bellefontaine OH 43311",
    "addr:housenumber": "554",
    "addr:postcode": "43311",
    "addr:street": "E Sandusky Ave",
    "iso:country": "US",
    "sg:address": "554 E Sandusky Ave",
    "sg:city": "Bellefontaine",
    "sg:classifiers": [
      {
        "category": "Banks \u0026 Credit Unions",
        "subcategory": "Bank",
        "type": "Services"
      }
    ],
    "sg:phone": "+1 937 593 0270",
    "sg:postcode": "43311",
    "sg:province": "OH",
    "sg:tags": [
      "cashing",
      "check"
    ],
    "wof:name": "First Choice Cash Advance",
    "wof:placetype": "venue"
  },
  "geometry": {"coordinates":[-83.748651,40.363564],"type":"Point"}
}
