{
  "type": "Feature",
  "properties": {
    "iso:country":"US",
    "sg:address":"554 E Sandusky Ave",
    "sg:city":"Bellefontaine",
    "sg:classifiers":[
        {
            "category":"Banks & Credit Unions",
            "subcategory":"Bank",
            "type":"Services"
        }
    ],
    "sg:phone":"+1 937 593 0270",
    "sg:postcode":"43311",
    "sg:province":"OH",
    "sg:tags":[
        "cashing",
        "check"
    ],
    "wof:name":"First Choice Cash Advance",
    "wof:placetype":"venue"
},
  "geometry": {"coordinates":[-83.748651,40.363564],"type":"Point"}
}