{
  "type": "Feature",
  "properties": {
    "iso:country":"US",
    "sg:address":"2537 Romig Rd",
    "sg:city":"Akron",
    "sg:classifiers":[
        {
            "category":"Health Services",
            "subcategory":"Chiropractor",
            "type":"Services"
        }
    ],
    "sg:phone":"+1 330 745 8300",
    "sg:postcode":"44320",
    "sg:province":"OH",
    "sg:tags":[
        "chiropractic"
    ],
    "wof:name":"Shawn D Auck Dc",
    "wof:placetype":"venue"
},
  "geometry": {"coordinates":[-81.58130300000001,41.044106],"type":"Point"}
}