{
  "type": "Feature",
  "properties": {
    "addr:full": "2537 Romig Rd Akron OH 44320",
    "addr:housenumber": "2537",
    "addr:postcode": "44320",
    "addr:street": "Romig Rd",
    "iso:country": "US",
    "sg:address": "2537 Romig Rd",
    "sg:city": "Akron",
    "sg:classifiers": [
      {
        "category": "Health Services",
        "subcategory": "Chiropractor",
        "type": "Services"
      }
    ],
    "sg:phone": "+1 330 745 8300",
    "sg:postcode": "44320",
    "sg:province": "OH",
    "sg:tags": [
      "chiropractic"
    ],
    "wof:name": "Shawn D Auck Dc",
    "wof:placetype": "venue"
  },
  "geometry": {"coordinates":[-81.581303,41.044106],"type":"Point"}
}
