{
  "type": "Feature",
  "properties": {
    "iso:country":"US",
    "sg:address":"109 N Sandusky Ave",
    "sg:city":"Upper Sandusky",
    "sg:classifiers":[
        {
            "category":"Banks & Credit Unions",
            "subcategory":"Bank",
            "type":"Services"
        }
    ],
    "sg:phone":"+1 419 209 3012",
    "sg:postcode":"43351",
    "sg:province":"OH",
    "sg:tags":[
        "cashing",
        "check"
    ],
    "wof:name":"Sunset Cash Advance",
    "wof:placetype":"venue"
},
  "geometry": {"coordinates":[-83.281296,40.828782],"type":"Point"}
}