{
  "type": "Feature",
  "properties": {
    "addr:full":"478 2nd St Liberty Center OH 43532",
    "addr:housenumber":"478",
    "addr:postcode":"43532",
    "addr:street":"2Nd St",
    "iso:country":"US",
    "sg:address":"478 2nd St",
    "sg:city":"Liberty Center",
    "sg:classifiers":[
        {
            "category":"Utilities",
            "subcategory":"Refuse",
            "type":"Services"
        }
    ],
    "sg:phone":"+1 419 533 6885",
    "sg:postcode":"43532",
    "sg:province":"OH",
    "sg:tags":[
        "garbage",
        "collection"
    ],
    "wof:name":"Walt's Trash Away",
    "wof:placetype":"venue"
},
  "geometry": {"coordinates":[-83.950487,41.424553],"type":"Point"}
}