{
  "type": "Feature",
  "properties": {
    "addr:full":"325 Ohio St Huron OH 44839",
    "addr:housenumber":"325",
    "addr:postcode":"44839",
    "addr:street":"Ohio St",
    "iso:country":"US",
    "sg:address":"325 Ohio St",
    "sg:city":"Huron",
    "sg:classifiers":[
        {
            "category":"Education",
            "subcategory":"School",
            "type":"Public Place"
        }
    ],
    "sg:phone":"+1 419 433 5658",
    "sg:postcode":"44839",
    "sg:province":"OH",
    "sg:website":"www.huron-city.k12.oh.us",
    "wof:name":"Mc Cormick Junior High",
    "wof:placetype":"venue"
},
  "geometry": {"coordinates":[-82.558007,41.395642],"type":"Point"}
}