{
  "type": "Feature",
  "properties": {
    "iso:country":"US",
    "sg:address":"111 Westboro St",
    "sg:city":"Dayton",
    "sg:classifiers":[
        {
            "category":"Wholesale",
            "subcategory":"Metals & Minerals",
            "type":"Manufacturing & Wholesale Goods"
        }
    ],
    "sg:phone":"+1 937 224 7434",
    "sg:postcode":"45408",
    "sg:province":"OH",
    "sg:tags":[
        "finisher"
    ],
    "wof:name":"Ruco Supplys Inc",
    "wof:placetype":"venue"
},
  "geometry": {"coordinates":[-84.203447,39.7429],"type":"Point"}
}