{
  "type": "Feature",
  "properties": {
    "iso:country":"US",
    "sg:address":"1384 E 112th St",
    "sg:city":"Cleveland",
    "sg:classifiers":[
        {
            "category":"Wholesale",
            "subcategory":"Vending Machines",
            "type":"Manufacturing & Wholesale Goods"
        }
    ],
    "sg:phone":"+1 216 791 5278",
    "sg:postcode":"44106",
    "sg:province":"OH",
    "sg:tags":[
        "operator"
    ],
    "wof:name":"Ard Vending",
    "wof:placetype":"venue"
},
  "geometry": {"coordinates":[-81.607228,41.520149],"type":"Point"}
}