{
  "type": "Feature",
  "properties": {
    "addr:full": "6265 Glenway Ave Cincinnati OH 45211",
    "addr:housenumber": "6265",
    "addr:postcode": "45211",
    "addr:street": "Glenway Ave",
    "iso:country": "US",
    "sg:address": "6265 Glenway Ave",
    "sg:city": "Cincinnati",
    "sg:classifiers": [
      {
        "category": "Shopping",
        "type": "Retail Goods"
      }
    ],
    "sg:phone": "+1 513 661 1212",
    "sg:postcode": "45211",
    "sg:province": "OH",
    "sg:tags": [
      "merchandise"
    ],
    "wof:name": "ABC Coin Company",
    "wof:placetype": "venue"
  },
  "geometry": {"coordinates":[-84.626191,39.146761],"type":"Point"}
}
