{
  "type": "Feature",
  "properties": {
    "addr:full":"5923 Everwood Rd Toledo OH 43613",
    "addr:postcode":"5923;43613",
    "addr:street":"Everwood Rd",
    "iso:country":"US",
    "sg:address":"5923 Everwood Rd",
    "sg:city":"Toledo",
    "sg:classifiers":[
        {
            "category":"Social Services",
            "subcategory":"Adult Care",
            "type":"Services"
        }
    ],
    "sg:phone":"+1 419 474 5723",
    "sg:postcode":"43613",
    "sg:province":"OH",
    "sg:tags":[
        "residential"
    ],
    "wof:name":"Everwood Community Residence",
    "wof:placetype":"venue"
},
  "geometry": {"coordinates":[-83.609178,41.72296],"type":"Point"}
}