{
  "type": "Feature",
  "properties": {
    "iso:country":"US",
    "sg:address":"2405 N Columbus St",
    "sg:city":"Lancaster",
    "sg:classifiers":[
        {
            "category":"Health Services",
            "subcategory":"Doctor",
            "type":"Services"
        }
    ],
    "sg:phone":"+1 740 681 8300",
    "sg:postcode":"43130",
    "sg:province":"OH",
    "sg:tags":[
        "physician",
        "surgeon"
    ],
    "wof:name":"Riverview ENT Ctr",
    "wof:placetype":"venue"
},
  "geometry": {"coordinates":[-82.631824,39.740598],"type":"Point"}
}