{
  "type": "Feature",
  "properties": {
    "addr:full": "11779 State Rte 105 Oak Harbor OH 43449",
    "addr:housenumber": "11779",
    "addr:postcode": "43449",
    "addr:street": "State Rte 105",
    "iso:country": "US",
    "sg:address": "11779 State Rte 105",
    "sg:city": "Oak Harbor",
    "sg:classifiers": [
      {
        "category": "Real Estate",
        "subcategory": "Real Estate Agent",
        "type": "Services"
      }
    ],
    "sg:phone": "+1 419 898 7022",
    "sg:postcode": "43449",
    "sg:province": "OH",
    "wof:name": "Tina Kightlinger Realtor",
    "wof:placetype": "venue"
  },
  "geometry": {"coordinates":[-83.156312,41.507883],"type":"Point"}
}
