{
  "type": "Feature",
  "properties": {
    "addr:full":"6531 Paullin Rd Jamestown OH 45335",
    "addr:housenumber":"6531",
    "addr:postcode":"45335",
    "addr:street":"Paullin Rd",
    "iso:country":"US",
    "sg:address":"6531 Paullin Rd",
    "sg:city":"Jamestown",
    "sg:classifiers":[
        {
            "category":"Farming",
            "subcategory":"Farm",
            "type":"Manufacturing & Wholesale Goods"
        }
    ],
    "sg:phone":"+1 937 675 6298",
    "sg:postcode":"45335",
    "sg:province":"OH",
    "sg:tags":[
        "crop",
        "general"
    ],
    "wof:name":"Hartman Brothers Farm",
    "wof:placetype":"venue"
},
  "geometry": {"coordinates":[-83.685221,39.696871],"type":"Point"}
}