{
  "type": "Feature",
  "properties": {
    "addr:full": "505 Jefferson Ave Toledo OH 43604",
    "addr:housenumber": "505",
    "addr:postcode": "43604",
    "addr:street": "Jefferson Ave",
    "iso:country": "US",
    "sg:address": "505 Jefferson Ave",
    "sg:city": "Toledo",
    "sg:classifiers": [
      {
        "category": "Real Estate",
        "subcategory": "Real Estate Operator",
        "type": "Services"
      }
    ],
    "sg:phone": "+1 419 242 0500",
    "sg:postcode": "43604",
    "sg:province": "OH",
    "sg:tags": [
      "building",
      "apartment"
    ],
    "wof:name": "Small Ridge",
    "wof:placetype": "venue"
  },
  "geometry": {"coordinates":[-83.537922,41.650933],"type":"Point"}
}
