{
  "type": "Feature",
  "properties": {
    "iso:country":"US",
    "sg:address":"25811 State Rte 62",
    "sg:city":"Beloit",
    "sg:classifiers":[
        {
            "category":"Professional",
            "subcategory":"Employment Agencies",
            "type":"Services"
        }
    ],
    "sg:phone":"+1 330 938 6717",
    "sg:postcode":"44609",
    "sg:province":"OH",
    "sg:tags":[
        "help",
        "contractor"
    ],
    "wof:name":"Alliance Temporary Svc",
    "wof:placetype":"venue"
},
  "geometry": {"coordinates":[-81.01730000000001,40.901422],"type":"Point"}
}