{
  "type": "Feature",
  "properties": {
    "addr:full": "25811 State Rte 62 Beloit OH 44609",
    "addr:housenumber": "25811",
    "addr:postcode": "44609",
    "addr:street": "State Rte 62",
    "iso:country": "US",
    "sg:address": "25811 State Rte 62",
    "sg:city": "Beloit",
    "sg:classifiers": [
      {
        "category": "Professional",
        "subcategory": "Employment Agencies",
        "type": "Services"
      }
    ],
    "sg:phone": "+1 330 938 6717",
    "sg:postcode": "44609",
    "sg:province": "OH",
    "sg:tags": [
      "help",
      "contractor"
    ],
    "wof:name": "Alliance Temporary Svc",
    "wof:placetype": "venue"
  },
  "geometry": {"coordinates":[-81.0173,40.901422],"type":"Point"}
}
