{
  "type": "Feature",
  "properties": {
    "addr:full":"221 W Good Ave Wadsworth OH 44281",
    "addr:housenumber":"221",
    "addr:postcode":"44281",
    "addr:street":"W Good Ave",
    "iso:country":"US",
    "sg:address":"221 W Good Ave",
    "sg:city":"Wadsworth",
    "sg:classifiers":[
        {
            "category":"Food & Beverages",
            "subcategory":"Specialty",
            "type":"Retail Goods"
        }
    ],
    "sg:phone":"+1 330 334 9227",
    "sg:postcode":"44281",
    "sg:province":"OH",
    "wof:name":"J&W Distributors",
    "wof:placetype":"venue"
},
  "geometry": {"coordinates":[-81.736047,41.038878],"type":"Point"}
}