{
  "type": "Feature",
  "properties": {
    "iso:country":"US",
    "sg:address":"323 Princewood Ct",
    "sg:city":"Cincinnati",
    "sg:classifiers":[
        {
            "category":"Shopping",
            "subcategory":"Clothing, Apparel, & Fashions",
            "type":"Retail Goods"
        }
    ],
    "sg:phone":"+1 513 851 1400",
    "sg:postcode":"45246",
    "sg:province":"OH",
    "sg:tags":[
        "furnishing"
    ],
    "wof:name":"Step N Style",
    "wof:placetype":"venue"
},
  "geometry": {"coordinates":[-84.482376,39.293634],"type":"Point"}
}