{
  "type": "Feature",
  "properties": {
    "addr:full":"600 Church St Chillicothe OH 45601",
    "addr:housenumber":"600",
    "addr:postcode":"45601",
    "addr:street":"Church St",
    "iso:country":"US",
    "sg:address":"600 Church St",
    "sg:city":"Chillicothe",
    "sg:classifiers":[
        {
            "category":"Farming",
            "subcategory":"Farm",
            "type":"Manufacturing & Wholesale Goods"
        }
    ],
    "sg:phone":"+1 740 773 1482",
    "sg:postcode":"45601",
    "sg:province":"OH",
    "sg:tags":[
        "crop",
        "general"
    ],
    "wof:name":"Cooke John",
    "wof:placetype":"venue"
},
  "geometry": {"coordinates":[-82.992667,39.342586],"type":"Point"}
}