{
  "type": "Feature",
  "properties": {
    "addr:full": "51 S Souder Ave Columbus OH 43222",
    "addr:housenumber": "51",
    "addr:postcode": "43222",
    "addr:street": "S Souder Ave",
    "iso:country": "US",
    "sg:address": "51 S Souder Ave",
    "sg:city": "Columbus",
    "sg:classifiers": [
      {
        "category": "Social Services",
        "subcategory": "Job Training",
        "type": "Services"
      },
      {
        "category": "Health Services",
        "subcategory": "Doctor",
        "type": "Services"
      }
    ],
    "sg:phone": "+1 614 464 4020",
    "sg:postcode": "43222",
    "sg:province": "OH",
    "sg:tags": [
      "laboratory",
      "medical",
      "rehabilitation"
    ],
    "wof:name": "Emg \u0026 Rehabilitation Assoc",
    "wof:placetype": "venue"
  },
  "geometry": {"coordinates":[-83.022871,39.958728],"type":"Point"}
}
