{
  "type": "Feature",
  "properties": {
    "addr:full": "12302 Parkhill Ave Cleveland OH 44120",
    "addr:housenumber": "12302",
    "addr:postcode": "44120",
    "addr:street": "Parkhill Ave",
    "iso:country": "US",
    "sg:address": "12302 Parkhill Ave",
    "sg:city": "Cleveland",
    "sg:classifiers": [
      {
        "category": "Organizations",
        "subcategory": "Religious Organization",
        "type": "Services"
      }
    ],
    "sg:phone": "+1 216 751 3963",
    "sg:postcode": "44120",
    "sg:province": "OH",
    "sg:tags": [
      "church"
    ],
    "wof:name": "Second Trinity Baptist Church",
    "wof:placetype": "venue"
  },
  "geometry": {"coordinates":[-81.594834,41.47433],"type":"Point"}
}
