{
  "type": "Feature",
  "properties": {
    "addr:full": "705 N James Rd Columbus OH 43219",
    "addr:housenumber": "705",
    "addr:postcode": "43219",
    "addr:street": "N James Rd",
    "iso:country": "US",
    "sg:address": "705 N James Rd",
    "sg:city": "Columbus",
    "sg:classifiers": [
      {
        "category": "Manufacturing",
        "subcategory": "Metals",
        "type": "Manufacturing \u0026 Wholesale Goods"
      }
    ],
    "sg:phone": "+1 614 235 4577",
    "sg:postcode": "43219",
    "sg:province": "OH",
    "sg:tags": [
      "plate",
      "sheet",
      "mfg",
      "fabricated",
      "sh",
      "fabricator"
    ],
    "sg:website": "www.winfab.com",
    "wof:name": "Winchester Fabricators Inc",
    "wof:placetype": "venue"
  },
  "geometry": {"coordinates":[-82.903288,39.987945],"type":"Point"}
}
