{
  "type": "Feature",
  "properties": {
    "iso:country":"US",
    "sg:address":"705 N James Rd",
    "sg:city":"Columbus",
    "sg:classifiers":[
        {
            "category":"Manufacturing",
            "subcategory":"Metals",
            "type":"Manufacturing & Wholesale Goods"
        }
    ],
    "sg:phone":"+1 614 235 4577",
    "sg:postcode":"43219",
    "sg:province":"OH",
    "sg:tags":[
        "plate",
        "sheet",
        "mfg",
        "fabricated",
        "sh",
        "fabricator"
    ],
    "sg:website":"www.winfab.com",
    "wof:name":"Winchester Fabricators Inc",
    "wof:placetype":"venue"
},
  "geometry": {"coordinates":[-82.903288,39.987945],"type":"Point"}
}