{
  "type": "Feature",
  "properties": {
    "addr:full":"1317 E Broad St Columbus OH 43205",
    "addr:housenumber":"1317",
    "addr:postcode":"43205",
    "addr:street":"E Broad St",
    "iso:country":"US",
    "sg:address":"1317 E Broad St",
    "sg:city":"Columbus",
    "sg:classifiers":[
        {
            "category":"Professional",
            "type":"Services"
        }
    ],
    "sg:phone":"+1 614 251 6860",
    "sg:postcode":"43205",
    "sg:province":"OH",
    "sg:tags":[
        "establishment"
    ],
    "wof:name":"Traeger Capitaal Corp",
    "wof:placetype":"venue"
},
  "geometry": {"coordinates":[-82.964814,39.966262],"type":"Point"}
}