{
  "type": "Feature",
  "properties": {
    "iso:country":"US",
    "sg:address":"7117 Salem Rd",
    "sg:city":"Cincinnati",
    "sg:classifiers":[
        {
            "category":"Building & Trades",
            "subcategory":"Construction",
            "type":"Services"
        }
    ],
    "sg:phone":"+1 513 624 7980",
    "sg:postcode":"45230",
    "sg:province":"OH",
    "sg:tags":[
        "contractor"
    ],
    "wof:name":"Jerry Williams Masonry",
    "wof:placetype":"venue"
},
  "geometry": {"coordinates":[-84.360918,39.072879],"type":"Point"}
}