{
  "type": "Feature",
  "properties": {
    "addr:full": "310 W Cumberland St Lewisburg OH 45338",
    "addr:housenumber": "310",
    "addr:postcode": "45338",
    "addr:street": "W Cumberland St",
    "iso:country": "US",
    "sg:address": "310 W Cumberland St",
    "sg:city": "Lewisburg",
    "sg:classifiers": [
      {
        "category": "Retail",
        "subcategory": "Auto Repair",
        "type": "Services"
      }
    ],
    "sg:phone": "+1 937 962 4714",
    "sg:postcode": "45338",
    "sg:province": "OH",
    "sg:tags": [
      "repairing",
      "automobile"
    ],
    "wof:name": "Herschel's Auto \u0026 Towing Svc",
    "wof:placetype": "venue"
  },
  "geometry": {"coordinates":[-84.541032,39.854512],"type":"Point"}
}
