{
  "type": "Feature",
  "properties": {
    "addr:full": "305 E Main St Mansfield OH 44904",
    "addr:housenumber": "305",
    "addr:postcode": "44904",
    "addr:street": "E Main St",
    "iso:country": "US",
    "sg:address": "305 E Main St",
    "sg:city": "Mansfield",
    "sg:classifiers": [
      {
        "category": "Wholesale",
        "subcategory": "Machinery \u0026 Supplies",
        "type": "Manufacturing \u0026 Wholesale Goods"
      }
    ],
    "sg:phone": "+1 419 884 1350",
    "sg:postcode": "44904",
    "sg:province": "OH",
    "sg:tags": [
      "equipment",
      "industrial"
    ],
    "wof:name": "Jean Barbara Nutrition Center",
    "wof:placetype": "venue"
  },
  "geometry": {"coordinates":[-82.57007,40.680943],"type":"Point"}
}
