{
  "type": "Feature",
  "properties": {
    "iso:country":"US",
    "sg:address":"320 Market St",
    "sg:city":"East Liverpool",
    "sg:classifiers":[
        {
            "category":"Restaurant",
            "type":"Food & Drink"
        }
    ],
    "sg:phone":"+1 330 386 6688",
    "sg:postcode":"43920",
    "sg:province":"OH",
    "wof:name":"Hot Dog Shoppe",
    "wof:placetype":"venue"
},
  "geometry": {"coordinates":[-80.58066599999999,40.617608],"type":"Point"}
}