{
  "type": "Feature",
  "properties": {
    "addr:full": "320 Market St East Liverpool OH 43920",
    "addr:housenumber": "320",
    "addr:postcode": "43920",
    "addr:street": "Market St",
    "iso:country": "US",
    "sg:address": "320 Market St",
    "sg:city": "East Liverpool",
    "sg:classifiers": [
      {
        "category": "Restaurant",
        "type": "Food \u0026 Drink"
      }
    ],
    "sg:phone": "+1 330 386 6688",
    "sg:postcode": "43920",
    "sg:province": "OH",
    "wof:name": "Hot Dog Shoppe",
    "wof:placetype": "venue"
  },
  "geometry": {"coordinates":[-80.580666,40.617608],"type":"Point"}
}
