{
  "type": "Feature",
  "properties": {
    "iso:country":"US",
    "sg:address":"8968 High Rock Rd",
    "sg:city":"Leesburg",
    "sg:classifiers":[
        {
            "category":"Building & Trades",
            "subcategory":"Construction",
            "type":"Services"
        }
    ],
    "sg:phone":"+1 937 780 6393",
    "sg:postcode":"45135",
    "sg:province":"OH",
    "sg:tags":[
        "concrete",
        "contractor"
    ],
    "wof:name":"Jeff Cockerill",
    "wof:placetype":"venue"
},
  "geometry": {"coordinates":[-83.560276,39.354969],"type":"Point"}
}