{
  "type": "Feature",
  "properties": {
    "addr:full": "1670 Shatto Ave Akron OH 44313",
    "addr:housenumber": "1670",
    "addr:postcode": "44313",
    "addr:street": "Shatto Ave",
    "iso:country": "US",
    "sg:address": "1670 Shatto Ave",
    "sg:city": "Akron",
    "sg:classifiers": [
      {
        "category": "Social Services",
        "type": "Services"
      }
    ],
    "sg:phone": "+1 330 867 8715",
    "sg:postcode": "44313",
    "sg:province": "OH",
    "sg:tags": [
      "counselor",
      "marriage",
      "family"
    ],
    "wof:name": "Dial-A-Minute For Living",
    "wof:placetype": "venue"
  },
  "geometry": {"coordinates":[-81.57254,41.1166],"type":"Point"}
}
