{
  "type": "Feature",
  "properties": {
    "iso:country":"US",
    "sg:address":"301 Hawthorne Rd SW",
    "sg:city":"Pataskala",
    "sg:classifiers":[
        {
            "category":"Professional",
            "type":"Services"
        }
    ],
    "sg:phone":"+1 740 964 0180",
    "sg:postcode":"43062",
    "sg:province":"OH",
    "wof:name":"Teenas Craft Cupboard",
    "wof:placetype":"venue"
},
  "geometry": {"coordinates":[-82.637905,39.961889],"type":"Point"}
}