{
  "type": "Feature",
  "properties": {
    "addr:full": "6490 Glenn Hwy Cambridge OH 43725",
    "addr:housenumber": "6490",
    "addr:postcode": "43725",
    "addr:street": "Glenn Hwy",
    "iso:country": "US",
    "sg:address": "6490 Glenn Hwy",
    "sg:city": "Cambridge",
    "sg:classifiers": [
      {
        "category": "Building \u0026 Trades",
        "subcategory": "Construction",
        "type": "Services"
      }
    ],
    "sg:phone": "+1 740 432 7586",
    "sg:postcode": "43725",
    "sg:province": "OH",
    "sg:tags": [
      "road",
      "contractor"
    ],
    "sg:website": "www.dot.state.oh.us",
    "wof:name": "State Highway Garage",
    "wof:placetype": "venue"
  },
  "geometry": {"coordinates":[-81.620767,40.013044],"type":"Point"}
}
