{
  "type": "Feature",
  "properties": {
    "addr:full":"5885 Frazeysburg Rd Nashport OH 43830",
    "addr:housenumber":"5885",
    "addr:postcode":"43830",
    "addr:street":"Frazeysburg Rd",
    "iso:country":"US",
    "sg:address":"5885 Frazeysburg Rd",
    "sg:city":"Nashport",
    "sg:classifiers":[
        {
            "category":"Restaurant",
            "type":"Food & Drink"
        }
    ],
    "sg:phone":"+1 740 454 4473",
    "sg:postcode":"43830",
    "sg:province":"OH",
    "sg:tags":[
        "eating",
        "pizza"
    ],
    "wof:name":"Creno's Pizza",
    "wof:placetype":"venue"
},
  "geometry": {"coordinates":[-82.042293,40.028395],"type":"Point"}
}