{
  "type": "Feature",
  "properties": {
    "addr:full":"525 Rohm Dr Napoleon OH 43545",
    "addr:housenumber":"525",
    "addr:postcode":"43545",
    "addr:street":"Rohm Dr",
    "iso:country":"US",
    "sg:address":"525 Rohm Dr",
    "sg:city":"Napoleon",
    "sg:classifiers":[
        {
            "category":"Retail",
            "subcategory":"Repair Shop",
            "type":"Services"
        }
    ],
    "sg:phone":"+1 419 592 0888",
    "sg:postcode":"43545",
    "sg:province":"OH",
    "sg:tags":[
        "upholsterer"
    ],
    "wof:name":"Speiser Upholstery Shop",
    "wof:placetype":"venue"
},
  "geometry": {"coordinates":[-84.157133,41.373433],"type":"Point"}
}