{
  "type": "Feature",
  "properties": {
    "addr:full": "38501 Lake Shore Blvd Willoughby OH 44094",
    "addr:housenumber": "38501",
    "addr:postcode": "44094",
    "addr:street": "Lake Shore Blvd",
    "iso:country": "US",
    "sg:address": "38501 Lake Shore Blvd",
    "sg:city": "Willoughby",
    "sg:classifiers": [
      {
        "category": "Restaurant",
        "type": "Food \u0026 Drink"
      }
    ],
    "sg:phone": "+1 440 942 6520",
    "sg:postcode": "44094",
    "sg:province": "OH",
    "sg:tags": [
      "eating"
    ],
    "wof:name": "Kickers Bar \u0026 Grill Inc",
    "wof:placetype": "venue"
  },
  "geometry": {"coordinates":[-81.398739,41.695872],"type":"Point"}
}
