{
  "type": "Feature",
  "properties": {
    "iso:country":"US",
    "sg:address":"123 W Main St",
    "sg:city":"Eaton",
    "sg:classifiers":[
        {
            "category":"Banks & Credit Unions",
            "subcategory":"Investment Brokerage",
            "type":"Services"
        }
    ],
    "sg:phone":"+1 937 456 1155",
    "sg:postcode":"45320",
    "sg:province":"OH",
    "sg:tags":[
        "stock",
        "bond"
    ],
    "sg:website":"www.edwardjones.com",
    "wof:name":"Edward Jones",
    "wof:placetype":"venue"
},
  "geometry": {"coordinates":[-84.636782,39.743864],"type":"Point"}
}