{
  "type": "Feature",
  "properties": {
    "iso:country":"US",
    "sg:address":"8001 Technology Blvd",
    "sg:city":"Dayton",
    "sg:classifiers":[
        {
            "category":"Wholesale",
            "subcategory":"Machinery & Supplies",
            "type":"Manufacturing & Wholesale Goods"
        }
    ],
    "sg:phone":"+1 937 253 0640",
    "sg:postcode":"45424",
    "sg:province":"OH",
    "sg:tags":[
        "gage"
    ],
    "wof:name":"Lasermike",
    "wof:placetype":"venue"
},
  "geometry": {"coordinates":[-84.058745,39.8683],"type":"Point"}
}