{
  "type": "Feature",
  "properties": {
    "addr:full": "7825 Bechtol Rd Lima OH 45801",
    "addr:housenumber": "7825",
    "addr:postcode": "45801",
    "addr:street": "Bechtol Rd",
    "iso:country": "US",
    "sg:address": "7825 Bechtol Rd",
    "sg:city": "Lima",
    "sg:classifiers": [
      {
        "category": "Professional",
        "type": "Services"
      }
    ],
    "sg:phone": "+1 419 649 8473",
    "sg:postcode": "45801",
    "sg:province": "OH",
    "wof:name": "Tony Treglia",
    "wof:placetype": "venue"
  },
  "geometry": {"coordinates":[-83.95443,40.753511],"type":"Point"}
}
