{
  "type": "Feature",
  "properties": {
    "iso:country":"US",
    "sg:address":"33050 Webber Rd",
    "sg:city":"Avon Lake",
    "sg:classifiers":[
        {
            "category":"Organizations",
            "subcategory":"Membership Organization",
            "type":"Services"
        }
    ],
    "sg:phone":"+1 440 933 7896",
    "sg:postcode":"44012",
    "sg:province":"OH",
    "wof:name":"Erie Shores Photographic",
    "wof:placetype":"venue"
},
  "geometry": {"coordinates":[-82.031035,41.488808],"type":"Point"}
}