{
  "type": "Feature",
  "properties": {
    "addr:full": "7940 Thomas Rd Middletown OH 45042",
    "addr:housenumber": "7940",
    "addr:postcode": "45042",
    "addr:street": "Thomas Rd",
    "iso:country": "US",
    "sg:address": "7940 Thomas Rd",
    "sg:city": "Middletown",
    "sg:classifiers": [
      {
        "category": "Real Estate",
        "subcategory": "Real Estate Agent",
        "type": "Services"
      }
    ],
    "sg:phone": "+1 513 422 5297",
    "sg:postcode": "45042",
    "sg:province": "OH",
    "wof:name": "Re/Max",
    "wof:placetype": "venue"
  },
  "geometry": {"coordinates":[-84.391683,39.562014],"type":"Point"}
}
