{
  "type": "Feature",
  "properties": {
    "iso:country":"US",
    "sg:address":"2010 Madison Ave",
    "sg:city":"Toledo",
    "sg:classifiers":[
        {
            "category":"Wholesale",
            "subcategory":"Durable Goods & Equipment",
            "type":"Manufacturing & Wholesale Goods"
        }
    ],
    "sg:phone":"+1 419 243 7271",
    "sg:postcode":"43604",
    "sg:province":"OH",
    "sg:tags":[
        "professional",
        "repair"
    ],
    "wof:name":"City Blueprint of Toledo Inc",
    "wof:placetype":"venue"
},
  "geometry": {"coordinates":[-83.54952900000001,41.658449],"type":"Point"}
}