{
  "type": "Feature",
  "properties": {
    "addr:full": "2010 Madison Ave Toledo OH 43604",
    "addr:housenumber": "2010",
    "addr:postcode": "43604",
    "addr:street": "Madison Ave",
    "iso:country": "US",
    "sg:address": "2010 Madison Ave",
    "sg:city": "Toledo",
    "sg:classifiers": [
      {
        "category": "Wholesale",
        "subcategory": "Durable Goods \u0026 Equipment",
        "type": "Manufacturing \u0026 Wholesale Goods"
      }
    ],
    "sg:phone": "+1 419 243 7271",
    "sg:postcode": "43604",
    "sg:province": "OH",
    "sg:tags": [
      "professional",
      "repair"
    ],
    "wof:name": "City Blueprint of Toledo Inc",
    "wof:placetype": "venue"
  },
  "geometry": {"coordinates":[-83.549529,41.658449],"type":"Point"}
}
