{
  "type": "Feature",
  "properties": {
    "iso:country":"US",
    "sg:address":"11406 Clifton Blvd",
    "sg:city":"Cleveland",
    "sg:classifiers":[
        {
            "category":"Real Estate",
            "subcategory":"Real Estate Operator",
            "type":"Services"
        }
    ],
    "sg:phone":"+1 216 281 4967",
    "sg:postcode":"44102",
    "sg:province":"OH",
    "sg:tags":[
        "apartment"
    ],
    "wof:name":"Clifton Part House Apts",
    "wof:placetype":"venue"
},
  "geometry": {"coordinates":[-81.766066,41.487089],"type":"Point"}
}