{
  "type": "Feature",
  "properties": {
    "addr:full": "6144 Wedgewood Rd Medina OH 44256",
    "addr:housenumber": "6144",
    "addr:postcode": "44256",
    "addr:street": "Wedgewood Rd",
    "iso:country": "US",
    "sg:address": "6144 Wedgewood Rd",
    "sg:city": "Medina",
    "sg:classifiers": [
      {
        "category": "Social Services",
        "subcategory": "Adult Care",
        "type": "Services"
      }
    ],
    "sg:phone": "+1 330 723 9551",
    "sg:postcode": "44256",
    "sg:province": "OH",
    "sg:tags": [
      "residential",
      "executive"
    ],
    "wof:name": "Medina County Home",
    "wof:placetype": "venue"
  },
  "geometry": {"coordinates":[-81.912098,41.099175],"type":"Point"}
}
