{
  "type": "Feature",
  "properties": {
    "addr:full": "134 Northwoods Blvd Columbus OH 43235",
    "addr:housenumber": "134",
    "addr:postcode": "43235",
    "addr:street": "Northwoods Blvd",
    "iso:country": "US",
    "sg:address": "134 Northwoods Blvd",
    "sg:city": "Columbus",
    "sg:classifiers": [
      {
        "category": "Health Services",
        "subcategory": "Chiropractor",
        "type": "Services"
      }
    ],
    "sg:phone": "+1 614 885 6056",
    "sg:postcode": "43235",
    "sg:province": "OH",
    "wof:name": "Riverside Chiropractic Ctr",
    "wof:placetype": "venue"
  },
  "geometry": {"coordinates":[-83.019106,40.128823],"type":"Point"}
}
