{
  "type": "Feature",
  "properties": {
    "iso:country":"US",
    "sg:address":"134 Northwoods Blvd",
    "sg:city":"Columbus",
    "sg:classifiers":[
        {
            "category":"Health Services",
            "subcategory":"Chiropractor",
            "type":"Services"
        }
    ],
    "sg:phone":"+1 614 885 6056",
    "sg:postcode":"43235",
    "sg:province":"OH",
    "wof:name":"Riverside Chiropractic Ctr",
    "wof:placetype":"venue"
},
  "geometry": {"coordinates":[-83.01910599999999,40.128823],"type":"Point"}
}