{
  "type": "Feature",
  "properties": {
    "iso:country":"US",
    "sg:address":"68 College St",
    "sg:city":"Alexandria",
    "sg:classifiers":[
        {
            "category":"Education",
            "subcategory":"School",
            "type":"Public Place"
        }
    ],
    "sg:phone":"+1 740 924 2691",
    "sg:postcode":"43001",
    "sg:province":"OH",
    "wof:name":"Alexandria Elementary School",
    "wof:placetype":"venue"
},
  "geometry": {"coordinates":[-82.611772,40.090518],"type":"Point"}
}