{
  "type": "Feature",
  "properties": {
    "addr:full": "3315 Centennial Rd Sylvania OH 43560",
    "addr:housenumber": "3315",
    "addr:postcode": "43560",
    "addr:street": "Centennial Rd",
    "iso:country": "US",
    "sg:address": "3315 Centennial Rd",
    "sg:city": "Sylvania",
    "sg:classifiers": [
      {
        "category": "Wholesale",
        "subcategory": "Medical Equipment \u0026 Supplies",
        "type": "Manufacturing \u0026 Wholesale Goods"
      }
    ],
    "sg:phone": "+1 419 842 0250",
    "sg:postcode": "43560",
    "sg:province": "OH",
    "wof:name": "Kci",
    "wof:placetype": "venue"
  },
  "geometry": {"coordinates":[-83.742239,41.677412],"type":"Point"}
}
