{
  "type": "Feature",
  "properties": {
    "addr:full":"2145 N Fairfield Rd Dayton OH 45431",
    "addr:housenumber":"2145",
    "addr:postcode":"45431",
    "addr:street":"N Fairfield Rd",
    "iso:country":"US",
    "sg:address":"2145 N Fairfield Rd",
    "sg:city":"Dayton",
    "sg:classifiers":[
        {
            "category":"Building & Trades",
            "subcategory":"Construction",
            "type":"Services"
        },
        {
            "category":"Real Estate",
            "subcategory":"Real Estate Operator",
            "type":"Services"
        }
    ],
    "sg:phone":"+1 937 429 9835",
    "sg:postcode":"45431",
    "sg:province":"OH",
    "sg:tags":[
        "home",
        "builder",
        "nonresidential"
    ],
    "wof:name":"Home Acres Properties",
    "wof:placetype":"venue"
},
  "geometry": {"coordinates":[-84.054084,39.754776],"type":"Point"}
}