{
  "type": "Feature",
  "properties": {
    "iso:country":"US",
    "sg:address":"18000 Bagley Rd",
    "sg:city":"Cleveland",
    "sg:classifiers":[
        {
            "category":"Restaurant",
            "type":"Food & Drink"
        }
    ],
    "sg:menulink":"http://www.allmenus.com/oh/middleburg-heights/170337-burger-king/menu/",
    "sg:phone":"+1 440 243 4554",
    "sg:postcode":"44130",
    "sg:province":"OH",
    "sg:tags":[
        "burger",
        "american"
    ],
    "wof:name":"Burger King",
    "wof:placetype":"venue"
},
  "geometry": {"coordinates":[-81.826072,41.373042],"type":"Point"}
}