{
  "type": "Feature",
  "properties": {
    "iso:country":"US",
    "sg:address":"3919 Anderson Rd",
    "sg:city":"Morrow",
    "sg:classifiers":[
        {
            "category":"Wholesale",
            "subcategory":"Construction Materials",
            "type":"Manufacturing & Wholesale Goods"
        }
    ],
    "sg:phone":"+1 513 899 3946",
    "sg:postcode":"45152",
    "sg:province":"OH",
    "sg:tags":[
        "sand",
        "gravel"
    ],
    "wof:name":"Salts Trucking",
    "wof:placetype":"venue"
},
  "geometry": {"coordinates":[-84.122303,39.377125],"type":"Point"}
}