{
  "type": "Feature",
  "properties": {
    "addr:full": "3931 S Dixie Dr Dayton OH 45439",
    "addr:housenumber": "3931",
    "addr:postcode": "45439",
    "addr:street": "S Dixie Dr",
    "iso:country": "US",
    "sg:address": "3931 S Dixie Dr",
    "sg:city": "Dayton",
    "sg:classifiers": [
      {
        "category": "Insurance",
        "subcategory": "Insurance Agent",
        "type": "Services"
      }
    ],
    "sg:phone": "+1 937 293 1600",
    "sg:postcode": "45439",
    "sg:province": "OH",
    "sg:website": "www.mcgohanbrabender.com",
    "wof:name": "Mc Gohan Brabender Inc",
    "wof:placetype": "venue"
  },
  "geometry": {"coordinates":[-84.211541,39.694601],"type":"Point"}
}
