{
  "type": "Feature",
  "properties": {
    "addr:full": "1410 Mishler St Alliance OH 44601",
    "addr:housenumber": "1410",
    "addr:postcode": "44601",
    "addr:street": "Mishler St",
    "iso:country": "US",
    "sg:address": "1410 Mishler St",
    "sg:city": "Alliance",
    "sg:classifiers": [
      {
        "category": "Retail",
        "subcategory": "Laundry \u0026 Dry Cleaning",
        "type": "Services"
      }
    ],
    "sg:phone": "+1 330 823 9912",
    "sg:postcode": "44601",
    "sg:province": "OH",
    "sg:tags": [
      "cleaners",
      "rug",
      "carpet"
    ],
    "wof:name": "M \u0026 J Carpet Cleaning",
    "wof:placetype": "venue"
  },
  "geometry": {"coordinates":[-81.127567,40.927483],"type":"Point"}
}
