{
  "type": "Feature",
  "properties": {
    "iso:country":"US",
    "sg:address":"309 S Belmore St",
    "sg:city":"Leipsic",
    "sg:classifiers":[
        {
            "category":"Restaurant",
            "type":"Food & Drink"
        }
    ],
    "sg:menulink":"http://www.allmenus.com/oh/van-buren/134434-subway/menu/",
    "sg:phone":"+1 419 943 3000",
    "sg:postcode":"45856",
    "sg:province":"OH",
    "sg:tags":[
        "american",
        "sandwich"
    ],
    "wof:name":"Subway",
    "wof:placetype":"venue"
},
  "geometry": {"coordinates":[-83.98533999999999,41.097677],"type":"Point"}
}