{
  "type": "Feature",
  "properties": {
    "addr:full": "581 Woodland Ave Columbus OH 43203",
    "addr:housenumber": "581",
    "addr:postcode": "43203",
    "addr:street": "Woodland Ave",
    "iso:country": "US",
    "sg:address": "581 Woodland Ave",
    "sg:city": "Columbus",
    "sg:classifiers": [
      {
        "category": "Building \u0026 Trades",
        "subcategory": "Construction",
        "type": "Services"
      }
    ],
    "sg:phone": "+1 614 252 4041",
    "sg:postcode": "43203",
    "sg:province": "OH",
    "sg:tags": [
      "demolition",
      "contractor"
    ],
    "wof:name": "Ransom Co",
    "wof:placetype": "venue"
  },
  "geometry": {"coordinates":[-82.955585,39.978356],"type":"Point"}
}
