{
  "type": "Feature",
  "properties": {
    "addr:full": "1222 E Main St Columbus OH 43205",
    "addr:housenumber": "1222",
    "addr:postcode": "43205",
    "addr:street": "E Main St",
    "iso:country": "US",
    "sg:address": "1222 E Main St",
    "sg:city": "Columbus",
    "sg:classifiers": [
      {
        "category": "Professional",
        "subcategory": "Lawyer \u0026 Legal Services",
        "type": "Services"
      }
    ],
    "sg:phone": "+1 614 252 7824",
    "sg:postcode": "43205",
    "sg:province": "OH",
    "sg:tags": [
      "attorney"
    ],
    "wof:name": "Bruce Roth",
    "wof:placetype": "venue"
  },
  "geometry": {"coordinates":[-82.965362,39.957834],"type":"Point"}
}
