{
  "type": "Feature",
  "properties": {
    "iso:country":"US",
    "sg:address":"25200 Randolph Rd",
    "sg:city":"Bedford",
    "sg:classifiers":[
        {
            "category":"Professional",
            "type":"Services"
        }
    ],
    "sg:phone":"+1 440 786 8346",
    "sg:postcode":"44146",
    "sg:province":"OH",
    "wof:name":"Wax and Body Works",
    "wof:placetype":"venue"
},
  "geometry": {"coordinates":[-81.501356,41.394278],"type":"Point"}
}