{
  "type": "Feature",
  "properties": {
    "iso:country":"US",
    "sg:address":"1348 Kellerman Ct",
    "sg:city":"Columbus",
    "sg:classifiers":[
        {
            "category":"Shopping",
            "subcategory":"Clothing, Apparel, & Fashions",
            "type":"Retail Goods"
        }
    ],
    "sg:phone":"+1 614 870 8388",
    "sg:postcode":"43228",
    "sg:province":"OH",
    "wof:name":"Absolutley Aprons",
    "wof:placetype":"venue"
},
  "geometry": {"coordinates":[-83.126048,39.980292],"type":"Point"}
}