{
  "type": "Feature",
  "properties": {
    "addr:full": "3452 W 152nd St Cleveland OH 44111",
    "addr:housenumber": "3452",
    "addr:postcode": "44111",
    "addr:street": "W 152Nd St",
    "iso:country": "US",
    "sg:address": "3452 W 152nd St",
    "sg:city": "Cleveland",
    "sg:classifiers": [
      {
        "category": "Retail",
        "subcategory": "Auto Repair",
        "type": "Services"
      }
    ],
    "sg:phone": "+1 216 671 9444",
    "sg:postcode": "44111",
    "sg:province": "OH",
    "sg:tags": [
      "restoration",
      "boat"
    ],
    "wof:name": "Watkins Marine Repair \u0026 Rstrtn",
    "wof:placetype": "venue"
  },
  "geometry": {"coordinates":[-81.802217,41.45708],"type":"Point"}
}
