{
  "type": "Feature",
  "properties": {
    "iso:country":"US",
    "sg:address":"29 N 3rd St",
    "sg:city":"Zanesville",
    "sg:classifiers":[
        {
            "category":"Recreation",
            "type":"Entertainment"
        }
    ],
    "sg:phone":"+1 740 450 4541",
    "sg:postcode":"43701",
    "sg:province":"OH",
    "sg:tags":[
        "parlor",
        "billiard"
    ],
    "wof:name":"Y-City Billards",
    "wof:placetype":"venue"
},
  "geometry": {"coordinates":[-82.009066,39.940564],"type":"Point"}
}