{
  "type": "Feature",
  "properties": {
    "iso:country":"US",
    "sg:address":"500 E Aurora Rd",
    "sg:city":"Macedonia",
    "sg:classifiers":[
        {
            "category":"Shopping",
            "type":"Retail Goods"
        }
    ],
    "sg:phone":"+1 330 467 0844",
    "sg:postcode":"44056",
    "sg:province":"OH",
    "sg:tags":[
        "pet",
        "shop"
    ],
    "wof:name":"PETCO",
    "wof:placetype":"venue"
},
  "geometry": {"coordinates":[-81.520025,41.313883],"type":"Point"}
}