{
  "type": "Feature",
  "properties": {
    "addr:full": "131 Dilworth St Elyria OH 44035",
    "addr:housenumber": "131",
    "addr:postcode": "44035",
    "addr:street": "Dilworth St",
    "iso:country": "US",
    "sg:address": "131 Dilworth St",
    "sg:city": "Elyria",
    "sg:classifiers": [
      {
        "category": "Manufacturing",
        "subcategory": "Signs",
        "type": "Manufacturing \u0026 Wholesale Goods"
      }
    ],
    "sg:phone": "+1 440 366 0984",
    "sg:postcode": "44035",
    "sg:province": "OH",
    "sg:tags": [
      "advertising",
      "specialty"
    ],
    "wof:name": "John B Francis Signs",
    "wof:placetype": "venue"
  },
  "geometry": {"coordinates":[-82.091297,41.379574],"type":"Point"}
}
