{
  "type": "Feature",
  "properties": {
    "addr:full": "17275 State Rte 190 Fort Jennings OH 45844",
    "addr:housenumber": "17275",
    "addr:postcode": "45844",
    "addr:street": "State Rte 190 Fort",
    "iso:country": "US",
    "sg:address": "17275 State Rte 190",
    "sg:city": "Fort Jennings",
    "sg:classifiers": [
      {
        "category": "Personal",
        "type": "Services"
      }
    ],
    "sg:phone": "+1 419 286 2672",
    "sg:postcode": "45844",
    "sg:province": "OH",
    "sg:tags": [
      "electrologist"
    ],
    "wof:name": "Patti's Electrolysis",
    "wof:placetype": "venue"
  },
  "geometry": {"coordinates":[-84.275734,40.929992],"type":"Point"}
}
