{
  "type": "Feature",
  "properties": {
    "addr:full": "3510 Centennial Rd Sylvania OH 43560",
    "addr:housenumber": "3510",
    "addr:postcode": "43560",
    "addr:street": "Centennial Rd",
    "iso:country": "US",
    "sg:address": "3510 Centennial Rd",
    "sg:city": "Sylvania",
    "sg:classifiers": [
      {
        "category": "Building \u0026 Trades",
        "subcategory": "Construction",
        "type": "Services"
      }
    ],
    "sg:phone": "+1 419 841 3455",
    "sg:postcode": "43560",
    "sg:province": "OH",
    "sg:tags": [
      "paving",
      "contractor"
    ],
    "sg:website": "www.ebony.com",
    "wof:name": "Ebony Construction Co Inc",
    "wof:placetype": "venue"
  },
  "geometry": {"coordinates":[-83.742198,41.679631],"type":"Point"}
}
