{
  "type": "Feature",
  "properties": {
    "addr:full": "321 W Benson Ave Cincinnati OH 45215",
    "addr:housenumber": "321",
    "addr:postcode": "45215",
    "addr:street": "W Benson Ave",
    "iso:country": "US",
    "sg:address": "321 W Benson Ave",
    "sg:city": "Cincinnati",
    "sg:classifiers": [
      {
        "category": "Personal",
        "subcategory": "Beauty Salon",
        "type": "Services"
      }
    ],
    "sg:phone": "+1 513 821 1231",
    "sg:postcode": "45215",
    "sg:province": "OH",
    "wof:name": "LA Normandee Beauty Salon",
    "wof:placetype": "venue"
  },
  "geometry": {"coordinates":[-84.445858,39.223648],"type":"Point"}
}
