{
  "type": "Feature",
  "properties": {
    "iso:country":"US",
    "sg:address":"818 Morrison Rd",
    "sg:city":"Columbus",
    "sg:classifiers":[
        {
            "category":"Professional",
            "subcategory":"Computer Services",
            "type":"Services"
        }
    ],
    "sg:phone":"+1 614 759 9461",
    "sg:postcode":"43230",
    "sg:province":"OH",
    "sg:tags":[
        "related"
    ],
    "wof:name":"Cayman Technologies Inc",
    "wof:placetype":"venue"
},
  "geometry": {"coordinates":[-82.856264,39.998357],"type":"Point"}
}