{
  "type": "Feature",
  "properties": {
    "iso:country":"US",
    "sg:address":"10900 Euclid Ave",
    "sg:city":"Cleveland",
    "sg:classifiers":[
        {
            "category":"Professional",
            "subcategory":"Research",
            "type":"Services"
        }
    ],
    "sg:phone":"+1 216 368 5535",
    "sg:postcode":"44106",
    "sg:province":"OH",
    "sg:tags":[
        "nonphysical",
        "commercial"
    ],
    "wof:name":"Center Regional Economical ISS",
    "wof:placetype":"venue"
},
  "geometry": {"coordinates":[-81.609027,41.505931],"type":"Point"}
}