{
  "type": "Feature",
  "properties": {
    "addr:full": "8350 W Chester Rd West Chester OH 45069",
    "addr:housenumber": "8350",
    "addr:postcode": "45069",
    "addr:street": "W Chester Rd",
    "iso:country": "US",
    "sg:address": "8350 W Chester Rd",
    "sg:city": "West Chester",
    "sg:classifiers": [
      {
        "category": "Autos \u0026 Motor Vehicles",
        "subcategory": "Fuel \u0026 Gas Station",
        "type": "Retail Goods"
      }
    ],
    "sg:phone": "+1 513 759 1884",
    "sg:postcode": "45069",
    "sg:province": "OH",
    "sg:tags": [
      "convenience",
      "station",
      "gasoline",
      "store"
    ],
    "wof:name": "Speedway 3405",
    "wof:placetype": "venue"
  },
  "geometry": {"coordinates":[-84.352612,39.317653],"type":"Point"}
}
