{
  "type": "Feature",
  "properties": {
    "iso:country":"US",
    "sg:address":"2422 Kenny Rd",
    "sg:city":"Columbus",
    "sg:classifiers":[
        {
            "category":"Wholesale",
            "subcategory":"Plants",
            "type":"Manufacturing & Wholesale Goods"
        }
    ],
    "sg:phone":"+1 614 481 8600",
    "sg:postcode":"43221",
    "sg:province":"OH",
    "sg:tags":[
        "supply"
    ],
    "wof:name":"Foliage International",
    "wof:placetype":"venue"
},
  "geometry": {"coordinates":[-83.035507,40.009499],"type":"Point"}
}