{
  "type": "Feature",
  "properties": {
    "addr:full":"4280 Fulton Rd Cleveland OH 44144",
    "addr:housenumber":"4280",
    "addr:postcode":"44144",
    "addr:street":"Fulton Rd",
    "iso:country":"US",
    "sg:address":"4280 Fulton Rd",
    "sg:city":"Cleveland",
    "sg:classifiers":[
        {
            "category":"Cinema",
            "subcategory":"Movie Rental",
            "type":"Entertainment"
        }
    ],
    "sg:phone":"+1 216 741 0004",
    "sg:postcode":"44144",
    "sg:province":"OH",
    "sg:tags":[
        "leasing",
        "video",
        "disc",
        "tape"
    ],
    "wof:name":"York Video",
    "wof:placetype":"venue"
},
  "geometry": {"coordinates":[-81.723412,41.442648],"type":"Point"}
}