{
  "type": "Feature",
  "properties": {
    "addr:full":"11280 Cornell Park Dr Cincinnati OH 45242",
    "addr:housenumber":"11280",
    "addr:postcode":"45242",
    "addr:street":"Cornell Park Dr",
    "iso:country":"US",
    "sg:address":"11280 Cornell Park Dr",
    "sg:city":"Cincinnati",
    "sg:classifiers":[
        {
            "category":"Manufacturing",
            "subcategory":"Tools & Machinery",
            "type":"Manufacturing & Wholesale Goods"
        }
    ],
    "sg:phone":"+1 513 489 4949",
    "sg:postcode":"45242",
    "sg:province":"OH",
    "sg:tags":[
        "equipment",
        "stamping",
        "metal"
    ],
    "wof:name":"American Feintool Inc",
    "wof:placetype":"venue"
},
  "geometry": {"coordinates":[-84.37158599999999,39.273319],"type":"Point"}
}