{
  "type": "Feature",
  "properties": {
    "addr:full":"1100 State Rte 19 Oak Harbor OH 43449",
    "addr:housenumber":"1100",
    "addr:postcode":"43449",
    "addr:street":"State Rte 19",
    "iso:country":"US",
    "sg:address":"1100 State Rte 19",
    "sg:city":"Oak Harbor",
    "sg:classifiers":[
        {
            "category":"Real Estate",
            "subcategory":"Real Estate Agent",
            "type":"Services"
        }
    ],
    "sg:phone":"+1 419 898 3999",
    "sg:postcode":"43449",
    "sg:province":"OH",
    "sg:tags":[
        "inspection"
    ],
    "sg:website":"www.ncpropertyinspections.com",
    "wof:name":"North Coast Property Inspctns",
    "wof:placetype":"venue"
},
  "geometry": {"coordinates":[-83.145234,41.536571],"type":"Point"}
}