{
  "type": "Feature",
  "properties": {
    "addr:full": "861 Bellefontaine Ave Marion OH 43302",
    "addr:housenumber": "861",
    "addr:postcode": "43302",
    "addr:street": "Bellefontaine Ave",
    "iso:country": "US",
    "sg:address": "861 Bellefontaine Ave",
    "sg:city": "Marion",
    "sg:classifiers": [
      {
        "category": "Retail",
        "subcategory": "Auto Repair",
        "type": "Services"
      }
    ],
    "sg:phone": "+1 740 383 3003",
    "sg:postcode": "43302",
    "sg:province": "OH",
    "sg:tags": [
      "wrecker"
    ],
    "wof:name": "B \u0026 B Towing Svc",
    "wof:placetype": "venue"
  },
  "geometry": {"coordinates":[-83.1444,40.573474],"type":"Point"}
}
