{
  "type": "Feature",
  "properties": {
    "addr:full": "8111 Rockside Rd Cleveland OH 44125",
    "addr:housenumber": "8111",
    "addr:postcode": "44125",
    "addr:street": "Rockside Rd",
    "iso:country": "US",
    "sg:address": "8111 Rockside Rd",
    "sg:city": "Cleveland",
    "sg:phone": "+1 216 520 1250",
    "sg:postcode": "44125",
    "sg:province": "OH",
    "wof:name": "Millennia Housing Management",
    "wof:placetype": "venue"
  },
  "geometry": {"coordinates":[-81.628069,41.393655],"type":"Point"}
}
