{
  "type": "Feature",
  "properties": {
    "addr:full":"2250 S Belvoir Blvd Cleveland OH 44118",
    "addr:housenumber":"2250",
    "addr:postcode":"44118",
    "addr:street":"S Belvoir Blvd",
    "iso:country":"US",
    "sg:address":"2250 S Belvoir Blvd",
    "sg:city":"Cleveland",
    "sg:classifiers":[
        {
            "category":"Autos & Motor Vehicles",
            "subcategory":"Auto Supplies",
            "type":"Retail Goods"
        }
    ],
    "sg:phone":"+1 216 381 1314",
    "sg:postcode":"44118",
    "sg:province":"OH",
    "sg:tags":[
        "automobile",
        "parts"
    ],
    "wof:name":"All Nations Auto Parts",
    "wof:placetype":"venue"
},
  "geometry": {"coordinates":[-81.524669,41.50068],"type":"Point"}
}