{
  "type": "Feature",
  "properties": {
    "addr:full":"130 Akron Rd Wadsworth OH 44281",
    "addr:housenumber":"130",
    "addr:postcode":"44281",
    "addr:street":"Akron Rd",
    "iso:country":"US",
    "sg:address":"130 Akron Rd",
    "sg:city":"Wadsworth",
    "sg:classifiers":[
        {
            "category":"Retail",
            "subcategory":"Laundry & Dry Cleaning",
            "type":"Services"
        }
    ],
    "sg:phone":"+1 330 336 7550",
    "sg:postcode":"44281",
    "sg:province":"OH",
    "sg:tags":[
        "garment",
        "plant",
        "drycleaning",
        "agent",
        "cleaners"
    ],
    "wof:name":"Sun Way Cleaners",
    "wof:placetype":"venue"
},
  "geometry": {"coordinates":[-81.728514,41.035917],"type":"Point"}
}