{
  "type": "Feature",
  "properties": {
    "addr:full":"480 E Wilson Bridge Rd Columbus OH 43085",
    "addr:housenumber":"480",
    "addr:postcode":"43085",
    "addr:street":"E Wilson Bridge Rd",
    "iso:country":"US",
    "sg:address":"480 E Wilson Bridge Rd",
    "sg:city":"Columbus",
    "sg:classifiers":[
        {
            "category":"Manufacturing",
            "subcategory":"Printing",
            "type":"Manufacturing & Wholesale Goods"
        }
    ],
    "sg:phone":"+1 614 885 2005",
    "sg:postcode":"43085",
    "sg:province":"OH",
    "sg:tags":[
        "lithographic",
        "commercial",
        "business"
    ],
    "wof:name":"Minuteman Press",
    "wof:placetype":"venue"
},
  "geometry": {"coordinates":[-83.00008,40.109212],"type":"Point"}
}