{
  "type": "Feature",
  "properties": {
    "addr:full":"8064 E Broad St Reynoldsburg OH 43068",
    "addr:housenumber":"8064",
    "addr:postcode":"43068",
    "addr:street":"E Broad St",
    "iso:country":"US",
    "sg:address":"8064 E Broad St",
    "sg:city":"Reynoldsburg",
    "sg:classifiers":[
        {
            "category":"Restaurant",
            "type":"Food & Drink"
        }
    ],
    "sg:menulink":"http://www.allmenus.com/oh/columbus/240405-panda-express/menu/",
    "sg:phone":"+1 614 856 9670",
    "sg:postcode":"43068",
    "sg:province":"OH",
    "sg:tags":[
        "asian",
        "chinese"
    ],
    "wof:name":"Panda Express",
    "wof:placetype":"venue"
},
  "geometry": {"coordinates":[-82.785741,39.985876],"type":"Point"}
}