{
  "type": "Feature",
  "properties": {
    "addr:full":"225 N Dawson St Uhrichsville OH 44683",
    "addr:housenumber":"225",
    "addr:postcode":"44683",
    "addr:street":"N Dawson St",
    "iso:country":"US",
    "sg:address":"225 N Dawson St",
    "sg:city":"Uhrichsville",
    "sg:classifiers":[
        {
            "category":"Organizations",
            "subcategory":"Religious Organization",
            "type":"Services"
        }
    ],
    "sg:phone":"+1 740 922 3881",
    "sg:postcode":"44683",
    "sg:province":"OH",
    "sg:tags":[
        "church"
    ],
    "wof:name":"First United Methodist Church",
    "wof:placetype":"venue"
},
  "geometry": {"coordinates":[-81.34188399999999,40.390913],"type":"Point"}
}