{
  "type": "Feature",
  "properties": {
    "addr:full": "209 S Main St Akron OH 44308",
    "addr:housenumber": "209",
    "addr:postcode": "44308",
    "addr:street": "S Main St",
    "iso:country": "US",
    "sg:address": "209 S Main St",
    "sg:city": "Akron",
    "sg:classifiers": [
      {
        "category": "Professional",
        "subcategory": "Advertising",
        "type": "Services"
      }
    ],
    "sg:phone": "+1 330 376 2016",
    "sg:postcode": "44308",
    "sg:province": "OH",
    "sg:tags": [
      "counselor"
    ],
    "sg:website": "www.workerscompohio.com",
    "wof:name": "DST Inc",
    "wof:placetype": "venue"
  },
  "geometry": {"coordinates":[-81.519279,41.080462],"type":"Point"}
}
