{
  "type": "Feature",
  "properties": {
    "addr:full": "12076 Quarry Rd North Baltimore OH 45872",
    "addr:housenumber": "12076",
    "addr:postcode": "45872",
    "addr:street": "Quarry Rd",
    "iso:country": "US",
    "sg:address": "12076 Quarry Rd",
    "sg:city": "North Baltimore",
    "sg:classifiers": [
      {
        "category": "Building \u0026 Trades",
        "subcategory": "Landscaping Services",
        "type": "Services"
      }
    ],
    "sg:phone": "+1 419 425 0513",
    "sg:postcode": "45872",
    "sg:province": "OH",
    "sg:tags": [
      "lawn",
      "maintenance",
      "grounds"
    ],
    "wof:name": "Home Pro Lawn Care LTD",
    "wof:placetype": "venue"
  },
  "geometry": {"coordinates":[-83.631133,41.189484],"type":"Point"}
}
