{
  "type": "Feature",
  "properties": {
    "iso:country":"US",
    "sg:address":"2516 Germantown St",
    "sg:city":"Dayton",
    "sg:classifiers":[
        {
            "category":"Professional",
            "type":"Services"
        }
    ],
    "sg:phone":"+1 937 263 6798",
    "sg:postcode":"45408",
    "sg:province":"OH",
    "sg:tags":[
        "establishment"
    ],
    "wof:name":"Charle's",
    "wof:placetype":"venue"
},
  "geometry": {"coordinates":[-84.235327,39.740321],"type":"Point"}
}