{
  "type": "Feature",
  "properties": {
    "iso:country":"US",
    "sg:address":"2591 Miamisburg Centerville Rd",
    "sg:city":"Dayton",
    "sg:classifiers":[
        {
            "category":"Health Services",
            "subcategory":"Health Practitioner",
            "type":"Services"
        }
    ],
    "sg:phone":"+1 937 435 1509",
    "sg:postcode":"45459",
    "sg:province":"OH",
    "sg:tags":[
        "therapist",
        "physical"
    ],
    "wof:name":"Physio Theraputics Inc",
    "wof:placetype":"venue"
},
  "geometry": {"coordinates":[-84.217319,39.635972],"type":"Point"}
}