{
  "type": "Feature",
  "properties": {
    "iso:country":"US",
    "sg:address":"1252 Weathervane Ln",
    "sg:city":"Akron",
    "sg:classifiers":[
        {
            "category":"Health Services",
            "subcategory":"Doctor",
            "type":"Services"
        }
    ],
    "sg:phone":"+1 330 864 7996",
    "sg:postcode":"44313",
    "sg:province":"OH",
    "sg:tags":[
        "dentist"
    ],
    "wof:name":"G D Close DDS",
    "wof:placetype":"venue"
},
  "geometry": {"coordinates":[-81.55387500000001,41.137516],"type":"Point"}
}