{
  "type": "Feature",
  "properties": {
    "addr:full": "1510 E Market St Akron OH 44305",
    "addr:housenumber": "1510",
    "addr:postcode": "44305",
    "addr:street": "E Market St",
    "iso:country": "US",
    "sg:address": "1510 E Market St",
    "sg:city": "Akron",
    "sg:classifiers": [
      {
        "category": "Retail",
        "subcategory": "Auto Rental",
        "type": "Services"
      }
    ],
    "sg:phone": "+1 330 798 7659",
    "sg:postcode": "44305",
    "sg:province": "OH",
    "sg:tags": [
      "renting",
      "truck",
      "leasing"
    ],
    "wof:name": "U-Haul Co",
    "wof:placetype": "venue"
  },
  "geometry": {"coordinates":[-81.474045,41.06304],"type":"Point"}
}
