{
  "type": "Feature",
  "properties": {
    "addr:full":"2917 Sunset Blvd Steubenville OH 43952",
    "addr:housenumber":"2917",
    "addr:postcode":"43952",
    "addr:street":"Sunset Blvd",
    "iso:country":"US",
    "sg:address":"2917 Sunset Blvd",
    "sg:city":"Steubenville",
    "sg:classifiers":[
        {
            "category":"Recreation",
            "subcategory":"Arcade",
            "type":"Entertainment"
        }
    ],
    "sg:phone":"+1 740 266 7600",
    "sg:postcode":"43952",
    "sg:province":"OH",
    "sg:tags":[
        "casino"
    ],
    "wof:name":"Trips To Win",
    "wof:placetype":"venue"
},
  "geometry": {"coordinates":[-80.658745,40.374062],"type":"Point"}
}