{
  "type": "Feature",
  "properties": {
    "iso:country":"US",
    "sg:address":"777 S Wooster Ave",
    "sg:city":"Strasburg",
    "sg:classifiers":[
        {
            "category":"Wholesale",
            "subcategory":"Machinery & Supplies",
            "type":"Manufacturing & Wholesale Goods"
        }
    ],
    "sg:phone":"+1 330 878 7772",
    "sg:postcode":"44680",
    "sg:province":"OH",
    "sg:tags":[
        "equipment",
        "oil",
        "well"
    ],
    "wof:name":"Lincoln Manufacturing Inc",
    "wof:placetype":"venue"
},
  "geometry": {"coordinates":[-81.525114,40.589845],"type":"Point"}
}