{
  "type": "Feature",
  "properties": {
    "addr:full": "303 Hall Ave Sidney OH 45365",
    "addr:housenumber": "303",
    "addr:postcode": "45365",
    "addr:street": "Hall Ave",
    "iso:country": "US",
    "sg:address": "303 Hall Ave",
    "sg:city": "Sidney",
    "sg:classifiers": [
      {
        "category": "Home \u0026 Garden",
        "subcategory": "Building Materials",
        "type": "Retail Goods"
      },
      {
        "category": "Manufacturing",
        "subcategory": "Glass \u0026 Minerals",
        "type": "Manufacturing \u0026 Wholesale Goods"
      }
    ],
    "sg:phone": "+1 937 492 8493",
    "sg:postcode": "45365",
    "sg:province": "OH",
    "sg:tags": [
      "plate",
      "window",
      "cutting"
    ],
    "wof:name": "Holthaus Specialty Svcs Inc",
    "wof:placetype": "venue"
  },
  "geometry": {"coordinates":[-84.169966,40.28358],"type":"Point"}
}
