{
  "type": "Feature",
  "properties": {
    "addr:full":"3997 Mayfield Rd Cleveland OH 44121",
    "addr:housenumber":"3997",
    "addr:postcode":"44121",
    "addr:street":"Mayfield Rd",
    "iso:country":"US",
    "sg:address":"3997 Mayfield Rd",
    "sg:city":"Cleveland",
    "sg:classifiers":[
        {
            "category":"Autos & Motor Vehicles",
            "subcategory":"Auto Supplies",
            "type":"Retail Goods"
        }
    ],
    "sg:phone":"+1 216 381 4545",
    "sg:postcode":"44121",
    "sg:province":"OH",
    "sg:tags":[
        "tire"
    ],
    "sg:website":"www.tirekingdom.com",
    "wof:name":"Tire Kingdom",
    "wof:placetype":"venue"
},
  "geometry": {"coordinates":[-81.535859,41.520767],"type":"Point"}
}