{
  "type": "Feature",
  "properties": {
    "addr:full": "1147 Sweitzer Ave Akron OH 44301",
    "addr:housenumber": "1147",
    "addr:postcode": "44301",
    "addr:street": "Sweitzer Ave",
    "iso:country": "US",
    "sg:address": "1147 Sweitzer Ave",
    "sg:city": "Akron",
    "sg:classifiers": [
      {
        "category": "Professional",
        "subcategory": "Advertising",
        "type": "Services"
      }
    ],
    "sg:phone": "+1 330 434 9200",
    "sg:postcode": "44301",
    "sg:province": "OH",
    "sg:tags": [
      "mail"
    ],
    "sg:website": "www.millerspresort.com",
    "wof:name": "Miller's Presort Inc",
    "wof:placetype": "venue"
  },
  "geometry": {"coordinates":[-81.524745,41.055858],"type":"Point"}
}
