{
  "type": "Feature",
  "properties": {
    "addr:full": "8473 County Home Rd Lisbon OH 44432",
    "addr:housenumber": "8473",
    "addr:postcode": "44432",
    "addr:street": "County Home Rd",
    "iso:country": "US",
    "sg:address": "8473 County Home Rd",
    "sg:city": "Lisbon",
    "sg:classifiers": [
      {
        "category": "Government",
        "subcategory": "Police Station",
        "type": "Public Place"
      }
    ],
    "sg:phone": "+1 330 385 5564",
    "sg:postcode": "44432",
    "sg:province": "OH",
    "sg:tags": [
      "department"
    ],
    "wof:name": "Liverpool Township LA Croft",
    "wof:placetype": "venue"
  },
  "geometry": {"coordinates":[-80.828274,40.778172],"type":"Point"}
}
