{
  "type": "Feature",
  "properties": {
    "iso:country":"US",
    "sg:address":"6155 Chittenden Rd",
    "sg:city":"Hudson",
    "sg:classifiers":[
        {
            "category":"Building & Trades",
            "subcategory":"Construction",
            "type":"Services"
        }
    ],
    "sg:phone":"+1 330 650 1300",
    "sg:postcode":"44236",
    "sg:province":"OH",
    "wof:name":"Odot Dist 4",
    "wof:placetype":"venue"
},
  "geometry": {"coordinates":[-81.49012399999999,41.233256],"type":"Point"}
}