{
  "type": "Feature",
  "properties": {
    "addr:full": "6155 Chittenden Rd Hudson OH 44236",
    "addr:housenumber": "6155",
    "addr:postcode": "44236",
    "addr:street": "Chittenden Rd",
    "iso:country": "US",
    "sg:address": "6155 Chittenden Rd",
    "sg:city": "Hudson",
    "sg:classifiers": [
      {
        "category": "Building \u0026 Trades",
        "subcategory": "Construction",
        "type": "Services"
      }
    ],
    "sg:phone": "+1 330 650 1300",
    "sg:postcode": "44236",
    "sg:province": "OH",
    "wof:name": "Odot Dist 4",
    "wof:placetype": "venue"
  },
  "geometry": {"coordinates":[-81.490124,41.233256],"type":"Point"}
}
