{
  "type": "Feature",
  "properties": {
    "addr:full": "2921 Westbrook Dr Cincinnati OH 45238",
    "addr:housenumber": "2921",
    "addr:postcode": "45238",
    "addr:street": "Westbrook Dr",
    "iso:country": "US",
    "sg:address": "2921 Westbrook Dr",
    "sg:city": "Cincinnati",
    "sg:classifiers": [
      {
        "category": "Manufacturing",
        "subcategory": "Tools \u0026 Machinery",
        "type": "Manufacturing \u0026 Wholesale Goods"
      }
    ],
    "sg:phone": "+1 513 481 0254",
    "sg:postcode": "45238",
    "sg:province": "OH",
    "sg:tags": [
      "analytical",
      "instrument",
      "mfg"
    ],
    "wof:name": "Cardboard Attic Inc",
    "wof:placetype": "venue"
  },
  "geometry": {"coordinates":[-84.596163,39.138097],"type":"Point"}
}
