{
  "type": "Feature",
  "properties": {
    "iso:country":"US",
    "sg:address":"2921 Westbrook Dr",
    "sg:city":"Cincinnati",
    "sg:classifiers":[
        {
            "category":"Manufacturing",
            "subcategory":"Tools & Machinery",
            "type":"Manufacturing & Wholesale Goods"
        }
    ],
    "sg:phone":"+1 513 481 0254",
    "sg:postcode":"45238",
    "sg:province":"OH",
    "sg:tags":[
        "analytical",
        "instrument",
        "mfg"
    ],
    "wof:name":"Cardboard Attic Inc",
    "wof:placetype":"venue"
},
  "geometry": {"coordinates":[-84.596163,39.138097],"type":"Point"}
}