{
  "type": "Feature",
  "properties": {
    "iso:country":"US",
    "sg:address":"1558 Cedar Ln",
    "sg:city":"Wooster",
    "sg:classifiers":[
        {
            "category":"Food & Beverages",
            "subcategory":"Specialty",
            "type":"Retail Goods"
        }
    ],
    "sg:phone":"+1 330 262 6024",
    "sg:postcode":"44691",
    "sg:province":"OH",
    "wof:name":"Hoff Lrie Hlth Fd Supplements",
    "wof:placetype":"venue"
},
  "geometry": {"coordinates":[-81.917152,40.822763],"type":"Point"}
}