{
  "type": "Feature",
  "properties": {
    "addr:full":"4407 Kyle Rd Dorset OH 44032",
    "addr:housenumber":"4407",
    "addr:postcode":"44032",
    "addr:street":"Kyle Rd",
    "iso:country":"US",
    "sg:address":"4407 Kyle Rd",
    "sg:city":"Dorset",
    "sg:classifiers":[
        {
            "category":"Restaurant",
            "type":"Food & Drink"
        }
    ],
    "sg:phone":"+1 440 858 2230",
    "sg:postcode":"44032",
    "sg:province":"OH",
    "sg:tags":[
        "eating"
    ],
    "wof:name":"Lucys Country Kitchen",
    "wof:placetype":"venue"
},
  "geometry": {"coordinates":[-80.643388,41.70694],"type":"Point"}
}