{
  "type": "Feature",
  "properties": {
    "addr:full":"1005 Klotz Rd Bowling Green OH 43402",
    "addr:housenumber":"1005",
    "addr:postcode":"43402",
    "addr:street":"Klotz Rd",
    "iso:country":"US",
    "sg:address":"1005 Klotz Rd",
    "sg:city":"Bowling Green",
    "sg:classifiers":[
        {
            "category":"Health Services",
            "subcategory":"Nursing And Care Facility",
            "type":"Services"
        }
    ],
    "sg:phone":"+1 419 352 4505",
    "sg:postcode":"43402",
    "sg:province":"OH",
    "wof:name":"Dunn Family Home",
    "wof:placetype":"venue"
},
  "geometry": {"coordinates":[-83.63999200000001,41.35834],"type":"Point"}
}