{
  "type": "Feature",
  "properties": {
    "iso:country":"US",
    "sg:address":"3847 Southern Ave",
    "sg:city":"Cincinnati",
    "sg:classifiers":[
        {
            "category":"Education",
            "subcategory":"School",
            "type":"Public Place"
        }
    ],
    "sg:phone":"+1 513 272 7800",
    "sg:postcode":"45227",
    "sg:province":"OH",
    "wof:name":"Fairfax Elementary School",
    "wof:placetype":"venue"
},
  "geometry": {"coordinates":[-84.39493400000001,39.144432],"type":"Point"}
}