{
  "type": "Feature",
  "properties": {
    "addr:full":"907 Chillicothe St Portsmouth OH 45662",
    "addr:housenumber":"907",
    "addr:postcode":"45662",
    "addr:street":"Chillicothe St",
    "iso:country":"US",
    "sg:address":"907 Chillicothe St",
    "sg:city":"Portsmouth",
    "sg:classifiers":[
        {
            "category":"Banks & Credit Unions",
            "subcategory":"Bank",
            "type":"Services"
        }
    ],
    "sg:phone":"+1 740 354 3177",
    "sg:postcode":"45662",
    "sg:province":"OH",
    "wof:name":"American Savings Bank",
    "wof:placetype":"venue"
},
  "geometry": {"coordinates":[-82.996416,38.73823],"type":"Point"}
}