{
  "type": "Feature",
  "properties": {
    "addr:full": "3209 State Rte 3 Loveland OH 45140",
    "addr:housenumber": "3209",
    "addr:postcode": "45140",
    "addr:street": "State Rte 3",
    "iso:country": "US",
    "sg:address": "3209 State Rte 3",
    "sg:city": "Loveland",
    "sg:classifiers": [
      {
        "category": "Shopping",
        "subcategory": "Florist",
        "type": "Retail Goods"
      },
      {
        "category": "Shopping",
        "subcategory": "Gifts \u0026 Souvenirs",
        "type": "Retail Goods"
      }
    ],
    "sg:phone": "+1 513 697 7673",
    "sg:postcode": "45140",
    "sg:province": "OH",
    "wof:name": "Flowers of Landen",
    "wof:placetype": "venue"
  },
  "geometry": {"coordinates":[-84.282468,39.303948],"type":"Point"}
}
