{
  "type": "Feature",
  "properties": {
    "addr:full": "26306 Co Rd 93 Fresno OH 43824",
    "addr:housenumber": "26306;93",
    "addr:postcode": "43824",
    "addr:street": "Co Rd",
    "iso:country": "US",
    "sg:address": "26306 Co Rd 93",
    "sg:city": "Fresno",
    "sg:classifiers": [
      {
        "category": "Farming",
        "subcategory": "Farm",
        "type": "Manufacturing \u0026 Wholesale Goods"
      }
    ],
    "sg:phone": "+1 740 545 9745",
    "sg:postcode": "43824",
    "sg:province": "OH",
    "sg:tags": [
      "crop",
      "general"
    ],
    "wof:name": "Keith Stahl",
    "wof:placetype": "venue"
  },
  "geometry": {"coordinates":[-81.685627,40.336407],"type":"Point"}
}
