{
  "type": "Feature",
  "properties": {
    "iso:country":"US",
    "sg:address":"27212 Royalton Rd",
    "sg:city":"Columbia Station",
    "sg:classifiers":[
        {
            "category":"Retail",
            "subcategory":"Auto Repair",
            "type":"Services"
        }
    ],
    "sg:phone":"+1 440 236 6607",
    "sg:postcode":"44028",
    "sg:province":"OH",
    "sg:tags":[
        "wrecker"
    ],
    "wof:name":"Woody's Rex",
    "wof:placetype":"venue"
},
  "geometry": {"coordinates":[-81.935214,41.312929],"type":"Point"}
}