{
  "type": "Feature",
  "properties": {
    "iso:country":"US",
    "sg:address":"1422 S Breiel Blvd",
    "sg:city":"Middletown",
    "sg:classifiers":[
        {
            "category":"Food & Beverages",
            "subcategory":"Groceries & Convenience Stores",
            "type":"Retail Goods"
        }
    ],
    "sg:phone":"+1 513 424 1767",
    "sg:postcode":"45044",
    "sg:province":"OH",
    "wof:name":"Dairy Mart Convenience Store",
    "wof:placetype":"venue"
},
  "geometry": {"coordinates":[-84.355897,39.499075],"type":"Point"}
}