{
  "type": "Feature",
  "properties": {
    "addr:full": "1422 S Breiel Blvd Middletown OH 45044",
    "addr:housenumber": "1422",
    "addr:postcode": "45044",
    "addr:street": "S Breiel Blvd",
    "iso:country": "US",
    "sg:address": "1422 S Breiel Blvd",
    "sg:city": "Middletown",
    "sg:classifiers": [
      {
        "category": "Food \u0026 Beverages",
        "subcategory": "Groceries \u0026 Convenience Stores",
        "type": "Retail Goods"
      }
    ],
    "sg:phone": "+1 513 424 1767",
    "sg:postcode": "45044",
    "sg:province": "OH",
    "wof:name": "Dairy Mart Convenience Store",
    "wof:placetype": "venue"
  },
  "geometry": {"coordinates":[-84.355897,39.499075],"type":"Point"}
}
