{
  "type": "Feature",
  "properties": {
    "addr:full": "975 Eastwind Dr Westerville OH 43081",
    "addr:housenumber": "975",
    "addr:postcode": "43081",
    "addr:street": "Eastwind Dr",
    "iso:country": "US",
    "sg:address": "975 Eastwind Dr",
    "sg:city": "Westerville",
    "sg:phone": "+1 614 431 0070",
    "sg:postcode": "43081",
    "sg:province": "OH",
    "sg:tags": [
      "food",
      "equipment",
      "processing"
    ],
    "wof:name": "Masterleo \u0026 Assoc",
    "wof:placetype": "venue"
  },
  "geometry": {"coordinates":[-82.91668,40.100813],"type":"Point"}
}
