{
  "type": "Feature",
  "properties": {
    "iso:country":"US",
    "sg:address":"7770 Brecksville Rd",
    "sg:city":"Cleveland",
    "sg:classifiers":[
        {
            "category":"Insurance",
            "subcategory":"Insurance Agent",
            "type":"Services"
        }
    ],
    "sg:phone":"+1 440 526 6745",
    "sg:postcode":"44141",
    "sg:province":"OH",
    "wof:name":"State Farm Insurance",
    "wof:placetype":"venue"
},
  "geometry": {"coordinates":[-81.633231,41.349856],"type":"Point"}
}