{
  "type": "Feature",
  "properties": {
    "addr:full":"5916 Gillingham Dr Sylvania OH 43560",
    "addr:housenumber":"5916",
    "addr:postcode":"43560",
    "addr:street":"Gillingham Dr",
    "iso:country":"US",
    "sg:address":"5916 Gillingham Dr",
    "sg:city":"Sylvania",
    "sg:classifiers":[
        {
            "category":"Building & Trades",
            "subcategory":"Landscaping Services",
            "type":"Services"
        }
    ],
    "sg:phone":"+1 419 882 3751",
    "sg:postcode":"43560",
    "sg:province":"OH",
    "wof:name":"Snead Landscape Company",
    "wof:placetype":"venue"
},
  "geometry": {"coordinates":[-83.71775700000001,41.721555],"type":"Point"}
}