{
  "type": "Feature",
  "properties": {
    "iso:country":"US",
    "sg:address":"5722 Brandtmanor Dr",
    "sg:city":"Cincinnati",
    "sg:classifiers":[
        {
            "category":"Building & Trades",
            "subcategory":"Construction",
            "type":"Services"
        }
    ],
    "sg:phone":"+1 513 347 6662",
    "sg:postcode":"45248",
    "sg:province":"OH",
    "sg:tags":[
        "house"
    ],
    "wof:name":"Jbek Construction LLC",
    "wof:placetype":"venue"
},
  "geometry": {"coordinates":[-84.639048,39.147629],"type":"Point"}
}