{
  "type": "Feature",
  "properties": {
    "addr:full": "5722 Brandtmanor Dr Cincinnati OH 45248",
    "addr:postcode": "5722;45248",
    "addr:street": "Brandtmanor Dr",
    "iso:country": "US",
    "sg:address": "5722 Brandtmanor Dr",
    "sg:city": "Cincinnati",
    "sg:classifiers": [
      {
        "category": "Building \u0026 Trades",
        "subcategory": "Construction",
        "type": "Services"
      }
    ],
    "sg:phone": "+1 513 347 6662",
    "sg:postcode": "45248",
    "sg:province": "OH",
    "sg:tags": [
      "house"
    ],
    "wof:name": "Jbek Construction LLC",
    "wof:placetype": "venue"
  },
  "geometry": {"coordinates":[-84.639048,39.147629],"type":"Point"}
}
