{
  "type": "Feature",
  "properties": {
    "addr:full": "480 Hudson Run Rd Barberton OH 44203",
    "addr:housenumber": "480",
    "addr:postcode": "44203",
    "addr:street": "Hudson Run Rd",
    "iso:country": "US",
    "sg:address": "480 Hudson Run Rd",
    "sg:city": "Barberton",
    "sg:classifiers": [
      {
        "category": "Manufacturing",
        "subcategory": "Tools \u0026 Machinery",
        "type": "Manufacturing \u0026 Wholesale Goods"
      }
    ],
    "sg:phone": "+1 330 825 2772",
    "sg:postcode": "44203",
    "sg:province": "OH",
    "sg:tags": [
      "machine",
      "shop",
      "industrial",
      "mfg"
    ],
    "wof:name": "Harrold Machine Shop",
    "wof:placetype": "venue"
  },
  "geometry": {"coordinates":[-81.621097,41.002161],"type":"Point"}
}
