{
  "type": "Feature",
  "properties": {
    "iso:country":"US",
    "sg:address":"230 S South St",
    "sg:city":"Wilmington",
    "sg:classifiers":[
        {
            "category":"Insurance",
            "subcategory":"Insurance Agent",
            "type":"Services"
        }
    ],
    "sg:phone":"+1 937 382 2483",
    "sg:postcode":"45177",
    "sg:province":"OH",
    "wof:name":"G Wendell Compton Insurance",
    "wof:placetype":"venue"
},
  "geometry": {"coordinates":[-83.828788,39.442132],"type":"Point"}
}