{
  "type": "Feature",
  "properties": {
    "addr:full":"572 Glendora Rd Columbus OH 43207",
    "addr:housenumber":"572",
    "addr:postcode":"43207",
    "addr:street":"Glendora Rd",
    "iso:country":"US",
    "sg:address":"572 Glendora Rd",
    "sg:city":"Columbus",
    "sg:classifiers":[
        {
            "category":"Organizations",
            "subcategory":"Religious Organization",
            "type":"Services"
        }
    ],
    "sg:phone":"+1 614 497 0306",
    "sg:postcode":"43207",
    "sg:province":"OH",
    "sg:tags":[
        "church"
    ],
    "wof:name":"Parson's Baptist Church",
    "wof:placetype":"venue"
},
  "geometry": {"coordinates":[-82.985906,39.881107],"type":"Point"}
}