{
  "type": "Feature",
  "properties": {
    "addr:full": "12119 Raintree Ave Pickerington OH 43147",
    "addr:housenumber": "12119",
    "addr:postcode": "43147",
    "addr:street": "Raintree Ave",
    "iso:country": "US",
    "sg:address": "12119 Raintree Ave",
    "sg:city": "Pickerington",
    "sg:classifiers": [
      {
        "category": "Wholesale",
        "subcategory": "Hardware",
        "type": "Manufacturing \u0026 Wholesale Goods"
      }
    ],
    "sg:phone": "+1 614 861 8376",
    "sg:postcode": "43147",
    "sg:province": "OH",
    "sg:tags": [
      "caster",
      "glide"
    ],
    "wof:name": "Caster Connection Inc",
    "wof:placetype": "venue"
  },
  "geometry": {"coordinates":[-82.752119,39.908521],"type":"Point"}
}
