{
  "type": "Feature",
  "properties": {
    "iso:country":"US",
    "sg:address":"12119 Raintree Ave",
    "sg:city":"Pickerington",
    "sg:classifiers":[
        {
            "category":"Wholesale",
            "subcategory":"Hardware",
            "type":"Manufacturing & Wholesale Goods"
        }
    ],
    "sg:phone":"+1 614 861 8376",
    "sg:postcode":"43147",
    "sg:province":"OH",
    "sg:tags":[
        "caster",
        "glide"
    ],
    "wof:name":"Caster Connection Inc",
    "wof:placetype":"venue"
},
  "geometry": {"coordinates":[-82.75211899999999,39.908521],"type":"Point"}
}