{
  "type": "Feature",
  "properties": {
    "iso:country":"US",
    "sg:address":"223 S Main St",
    "sg:city":"Findlay",
    "sg:classifiers":[
        {
            "category":"Real Estate",
            "subcategory":"Surveying",
            "type":"Services"
        }
    ],
    "sg:phone":"+1 419 423 3856",
    "sg:postcode":"45840",
    "sg:province":"OH",
    "sg:tags":[
        "surveyor"
    ],
    "wof:name":"Perry Surveying",
    "wof:placetype":"venue"
},
  "geometry": {"coordinates":[-83.650153,41.039647],"type":"Point"}
}