{
  "type": "Feature",
  "properties": {
    "iso:country":"US",
    "sg:address":"608 4th St",
    "sg:city":"Toledo",
    "sg:classifiers":[
        {
            "category":"Professional",
            "subcategory":"Accounting & Tax Preparation",
            "type":"Services"
        }
    ],
    "sg:phone":"+1 419 693 2693",
    "sg:postcode":"43605",
    "sg:province":"OH",
    "sg:website":"www.tskbi.com",
    "wof:name":"Tucker Stein Kissling Bueltel",
    "wof:placetype":"venue"
},
  "geometry": {"coordinates":[-83.519863,41.646493],"type":"Point"}
}