{
  "type": "Feature",
  "properties": {
    "iso:country":"US",
    "sg:address":"8055 E Liberty St",
    "sg:city":"Hubbard",
    "sg:classifiers":[
        {
            "category":"Autos & Motor Vehicles",
            "subcategory":"Auto Supplies",
            "type":"Retail Goods"
        }
    ],
    "sg:phone":"+1 330 534 2975",
    "sg:postcode":"44425",
    "sg:province":"OH",
    "sg:tags":[
        "equipment",
        "racing",
        "car",
        "automobile"
    ],
    "wof:name":"Smokey's Racing Supplies",
    "wof:placetype":"venue"
},
  "geometry": {"coordinates":[-80.527018,41.168983],"type":"Point"}
}