{
  "type": "Feature",
  "properties": {
    "addr:full":"139 E Main St Somerset OH 43783",
    "addr:housenumber":"139",
    "addr:postcode":"43783",
    "addr:street":"E Main St",
    "iso:country":"US",
    "sg:address":"139 E Main St",
    "sg:city":"Somerset",
    "sg:classifiers":[
        {
            "category":"Organizations",
            "subcategory":"Religious Organization",
            "type":"Services"
        }
    ],
    "sg:phone":"+1 740 743 1029",
    "sg:postcode":"43783",
    "sg:province":"OH",
    "sg:tags":[
        "church"
    ],
    "sg:website":"www.netpluscom.com",
    "wof:name":"Somerset United Methodist Chr",
    "wof:placetype":"venue"
},
  "geometry": {"coordinates":[-82.29859999999999,39.807481],"type":"Point"}
}