{
  "type": "Feature",
  "properties": {
    "addr:full": "407 Short St Port Clinton OH 43452",
    "addr:housenumber": "407",
    "addr:postcode": "43452",
    "addr:street": "Short St",
    "iso:country": "US",
    "sg:address": "407 Short St",
    "sg:city": "Port Clinton",
    "sg:classifiers": [
      {
        "category": "Real Estate",
        "subcategory": "Real Estate Operator",
        "type": "Services"
      }
    ],
    "sg:phone": "+1 419 734 9100",
    "sg:postcode": "43452",
    "sg:province": "OH",
    "sg:tags": [
      "building",
      "beverage",
      "nonresidential",
      "alcoholic"
    ],
    "sg:website": "www.ohiowine.com",
    "wof:name": "Heineman Distributing",
    "wof:placetype": "venue"
  },
  "geometry": {"coordinates":[-82.931926,41.507909],"type":"Point"}
}
