{
  "type": "Feature",
  "properties": {
    "iso:country":"US",
    "sg:address":"1420 Whipple Ave NW",
    "sg:city":"Canton",
    "sg:classifiers":[
        {
            "category":"Building & Trades",
            "subcategory":"Cleaning & Sanitation",
            "type":"Services"
        }
    ],
    "sg:phone":"+1 330 493 9000",
    "sg:postcode":"44708",
    "sg:province":"OH",
    "sg:tags":[
        "janitor"
    ],
    "wof:name":"Shaheen Cleaning & Eqpt Supls",
    "wof:placetype":"venue"
},
  "geometry": {"coordinates":[-81.425207,40.814193],"type":"Point"}
}