{
  "type": "Feature",
  "properties": {
    "addr:full": "1046 N Perry St Napoleon OH 43545",
    "addr:housenumber": "1046",
    "addr:postcode": "43545",
    "addr:street": "N Perry St",
    "iso:country": "US",
    "sg:address": "1046 N Perry St",
    "sg:city": "Napoleon",
    "sg:classifiers": [
      {
        "category": "Building \u0026 Trades",
        "subcategory": "Construction",
        "type": "Services"
      }
    ],
    "sg:phone": "+1 419 599 1391",
    "sg:postcode": "43545",
    "sg:province": "OH",
    "sg:tags": [
      "home",
      "improvement"
    ],
    "wof:name": "C \u0026 C Home Repair",
    "wof:placetype": "venue"
  },
  "geometry": {"coordinates":[-84.127656,41.395399],"type":"Point"}
}
