{
  "type": "Feature",
  "properties": {
    "iso:country":"US",
    "sg:address":"1046 N Perry St",
    "sg:city":"Napoleon",
    "sg:classifiers":[
        {
            "category":"Building & Trades",
            "subcategory":"Construction",
            "type":"Services"
        }
    ],
    "sg:phone":"+1 419 599 1391",
    "sg:postcode":"43545",
    "sg:province":"OH",
    "sg:tags":[
        "home",
        "improvement"
    ],
    "wof:name":"C & C Home Repair",
    "wof:placetype":"venue"
},
  "geometry": {"coordinates":[-84.127656,41.395399],"type":"Point"}
}