{
  "type": "Feature",
  "properties": {
    "addr:full":"5399 Lancaster Dr Cleveland OH 44131",
    "addr:housenumber":"5399",
    "addr:postcode":"44131",
    "addr:street":"Lancaster Dr",
    "iso:country":"US",
    "sg:address":"5399 Lancaster Dr",
    "sg:city":"Cleveland",
    "sg:classifiers":[
        {
            "category":"Wholesale",
            "subcategory":"Construction Materials",
            "type":"Manufacturing & Wholesale Goods"
        }
    ],
    "sg:phone":"+1 216 661 4994",
    "sg:postcode":"44131",
    "sg:province":"OH",
    "sg:tags":[
        "tile",
        "ceramic"
    ],
    "wof:name":"Dal-Tile",
    "wof:placetype":"venue"
},
  "geometry": {"coordinates":[-81.665387,41.413165],"type":"Point"}
}