{
  "type": "Feature",
  "properties": {
    "iso:country":"US",
    "sg:address":"1239 Shanahan Rd",
    "sg:city":"Lewis Center",
    "sg:classifiers":[
        {
            "category":"Freight",
            "type":"Transportation"
        }
    ],
    "sg:phone":"+1 740 548 5450",
    "sg:postcode":"43035",
    "sg:province":"OH",
    "sg:tags":[
        "trucking"
    ],
    "wof:name":"Evans Farms Svc",
    "wof:placetype":"venue"
},
  "geometry": {"coordinates":[-83.016057,40.213218],"type":"Point"}
}