{
  "type": "Feature",
  "properties": {
    "iso:country":"US",
    "sg:address":"11707 Chesterdale Rd",
    "sg:city":"Cincinnati",
    "sg:classifiers":[
        {
            "category":"Manufacturing",
            "subcategory":"Retail Goods",
            "type":"Manufacturing & Wholesale Goods"
        }
    ],
    "sg:phone":"+1 513 772 7646",
    "sg:postcode":"45246",
    "sg:province":"OH",
    "sg:tags":[
        "product",
        "mfg"
    ],
    "wof:name":"Theatre Effects Inc",
    "wof:placetype":"venue"
},
  "geometry": {"coordinates":[-84.447964,39.288638],"type":"Point"}
}