{
  "type": "Feature",
  "properties": {
    "iso:country":"US",
    "sg:address":"449 S Meridian St",
    "sg:city":"Ravenna",
    "sg:classifiers":[
        {
            "category":"Government",
            "subcategory":"Office",
            "type":"Public Place"
        }
    ],
    "sg:phone":"+1 330 297 3444",
    "sg:postcode":"44266",
    "sg:province":"OH",
    "wof:name":"Portage County Coroner",
    "wof:placetype":"venue"
},
  "geometry": {"coordinates":[-81.244881,41.155162],"type":"Point"}
}