{
  "type": "Feature",
  "properties": {
    "iso:country":"US",
    "sg:address":"4912 Higbee Ave NW",
    "sg:city":"Canton",
    "sg:classifiers":[
        {
            "category":"Manufacturing",
            "subcategory":"Tools & Machinery",
            "type":"Manufacturing & Wholesale Goods"
        },
        {
            "category":"Health Services",
            "subcategory":"Medical Lab",
            "type":"Services"
        }
    ],
    "sg:phone":"+1 330 491 0480",
    "sg:postcode":"44718",
    "sg:province":"OH",
    "sg:tags":[
        "physician",
        "mobile",
        "outpatient",
        "diagnostic",
        "imaging",
        "surgeon"
    ],
    "sg:website":"www.sharedpet.com",
    "wof:name":"Shared Pet Imaging LLC",
    "wof:placetype":"venue"
},
  "geometry": {"coordinates":[-81.427604,40.853057],"type":"Point"}
}