{
  "type": "Feature",
  "properties": {
    "addr:full": "4912 Higbee Ave NW Canton OH 44718",
    "addr:postcode": "4912;44718",
    "addr:street": "Higbee Ave Nw",
    "iso:country": "US",
    "sg:address": "4912 Higbee Ave NW",
    "sg:city": "Canton",
    "sg:classifiers": [
      {
        "category": "Manufacturing",
        "subcategory": "Tools \u0026 Machinery",
        "type": "Manufacturing \u0026 Wholesale Goods"
      },
      {
        "category": "Health Services",
        "subcategory": "Medical Lab",
        "type": "Services"
      }
    ],
    "sg:phone": "+1 330 491 0480",
    "sg:postcode": "44718",
    "sg:province": "OH",
    "sg:tags": [
      "physician",
      "mobile",
      "outpatient",
      "diagnostic",
      "imaging",
      "surgeon"
    ],
    "sg:website": "www.sharedpet.com",
    "wof:name": "Shared Pet Imaging LLC",
    "wof:placetype": "venue"
  },
  "geometry": {"coordinates":[-81.427604,40.853057],"type":"Point"}
}
