{
  "type": "Feature",
  "properties": {
    "iso:country":"US",
    "sg:address":"8120 Storrow Dr",
    "sg:city":"Westerville",
    "sg:classifiers":[
        {
            "category":"Professional",
            "subcategory":"Employment Agencies",
            "type":"Services"
        }
    ],
    "sg:phone":"+1 614 785 9493",
    "sg:postcode":"43081",
    "sg:province":"OH",
    "sg:tags":[
        "opportunity"
    ],
    "wof:name":"Pam Metzler & Assoc",
    "wof:placetype":"venue"
},
  "geometry": {"coordinates":[-82.999465,40.130515],"type":"Point"}
}