{
  "type": "Feature",
  "properties": {
    "addr:full": "22285 Darby Pottersburg Rd Marysville OH 43040",
    "addr:postcode": "22285;43040",
    "addr:street": "Pottersburg Rd",
    "iso:country": "US",
    "sg:address": "22285 Darby Pottersburg Rd",
    "sg:city": "Marysville",
    "sg:classifiers": [
      {
        "category": "Freight",
        "type": "Transportation"
      }
    ],
    "sg:phone": "+1 937 642 2293",
    "sg:postcode": "43040",
    "sg:province": "OH",
    "sg:tags": [
      "packing",
      "crating"
    ],
    "wof:name": "Custom Crating Svc",
    "wof:placetype": "venue"
  },
  "geometry": {"coordinates":[-83.473523,40.283828],"type":"Point"}
}
