{
  "type": "Feature",
  "properties": {
    "iso:country":"US",
    "sg:address":"9913 Lynn Dr",
    "sg:city":"Cleveland",
    "sg:classifiers":[
        {
            "category":"Wholesale",
            "subcategory":"Machinery & Supplies",
            "type":"Manufacturing & Wholesale Goods"
        }
    ],
    "sg:phone":"+1 440 237 0465",
    "sg:postcode":"44133",
    "sg:province":"OH",
    "sg:tags":[
        "gage"
    ],
    "wof:name":"Paul's Measuring Instruments",
    "wof:placetype":"venue"
},
  "geometry": {"coordinates":[-81.768208,41.342619],"type":"Point"}
}