{
  "type": "Feature",
  "properties": {
    "iso:country":"US",
    "sg:address":"65 N Paint St",
    "sg:city":"Chillicothe",
    "sg:classifiers":[
        {
            "category":"Manufacturing",
            "subcategory":"Tools & Machinery",
            "type":"Manufacturing & Wholesale Goods"
        }
    ],
    "sg:phone":"+1 740 773 3111",
    "sg:postcode":"45601",
    "sg:province":"OH",
    "sg:tags":[
        "food",
        "product",
        "mfg"
    ],
    "wof:name":"Sheila Weathersbee",
    "wof:placetype":"venue"
},
  "geometry": {"coordinates":[-82.982619,39.335535],"type":"Point"}
}