{
  "type": "Feature",
  "properties": {
    "addr:full": "65 N Paint St Chillicothe OH 45601",
    "addr:housenumber": "65",
    "addr:postcode": "45601",
    "addr:street": "N Paint St",
    "iso:country": "US",
    "sg:address": "65 N Paint St",
    "sg:city": "Chillicothe",
    "sg:classifiers": [
      {
        "category": "Manufacturing",
        "subcategory": "Tools \u0026 Machinery",
        "type": "Manufacturing \u0026 Wholesale Goods"
      }
    ],
    "sg:phone": "+1 740 773 3111",
    "sg:postcode": "45601",
    "sg:province": "OH",
    "sg:tags": [
      "food",
      "product",
      "mfg"
    ],
    "wof:name": "Sheila Weathersbee",
    "wof:placetype": "venue"
  },
  "geometry": {"coordinates":[-82.982619,39.335535],"type":"Point"}
}
