{
  "type": "Feature",
  "properties": {
    "addr:full": "1131 N Main St Urbana OH 43078",
    "addr:housenumber": "1131",
    "addr:postcode": "43078",
    "addr:street": "N Main St",
    "iso:country": "US",
    "sg:address": "1131 N Main St",
    "sg:city": "Urbana",
    "sg:classifiers": [
      {
        "category": "Retail",
        "subcategory": "Car Wash",
        "type": "Services"
      }
    ],
    "sg:phone": "+1 937 652 4607",
    "sg:postcode": "43078",
    "sg:province": "OH",
    "sg:tags": [
      "carwash"
    ],
    "wof:name": "Urbana-Main Super Wash",
    "wof:placetype": "venue"
  },
  "geometry": {"coordinates":[-83.749425,40.123509],"type":"Point"}
}
