{
  "type": "Feature",
  "properties": {
    "addr:full": "1636 Russia-Versailles Rd Russia OH 45363",
    "addr:housenumber": "1636",
    "addr:postcode": "45363",
    "addr:street": "Russia-Versailles Rd",
    "iso:country": "US",
    "sg:address": "1636 Russia-Versailles Rd",
    "sg:city": "Russia",
    "sg:classifiers": [
      {
        "category": "Insurance",
        "subcategory": "Insurance Agent",
        "type": "Services"
      }
    ],
    "sg:phone": "+1 937 526 4898",
    "sg:postcode": "45363",
    "sg:province": "OH",
    "wof:name": "Francis-Condon Insurance",
    "wof:placetype": "venue"
  },
  "geometry": {"coordinates":[-84.402023,40.233722],"type":"Point"}
}
