{
  "type": "Feature",
  "properties": {
    "addr:full":"9055 W State Rte 2 Oak Harbor OH 43449",
    "addr:housenumber":"9055",
    "addr:postcode":"43449",
    "addr:street":"W State Rte 2",
    "iso:country":"US",
    "sg:address":"9055 W State Rte 2",
    "sg:city":"Oak Harbor",
    "sg:classifiers":[
        {
            "category":"Food & Beverages",
            "subcategory":"Groceries & Convenience Stores",
            "type":"Retail Goods"
        }
    ],
    "sg:phone":"+1 419 898 2005",
    "sg:postcode":"43449",
    "sg:province":"OH",
    "sg:tags":[
        "marina",
        "camp",
        "ground"
    ],
    "wof:name":"Wild Wings Inc",
    "wof:placetype":"venue"
},
  "geometry": {"coordinates":[-83.118967,41.603959],"type":"Point"}
}