{
  "type": "Feature",
  "properties": {
    "addr:full":"101 S 4th St Martins Ferry OH 43935",
    "addr:housenumber":"101",
    "addr:postcode":"43935",
    "addr:street":"S 4Th St Martins Ferry",
    "iso:country":"US",
    "sg:address":"101 S 4th St",
    "sg:city":"Martins Ferry",
    "sg:classifiers":[
        {
            "category":"Health Services",
            "subcategory":"Hospital",
            "type":"Services"
        }
    ],
    "sg:phone":"+1 740 633 5850",
    "sg:postcode":"43935",
    "sg:province":"OH",
    "sg:tags":[
        "mental"
    ],
    "wof:name":"New Visions",
    "wof:placetype":"venue"
},
  "geometry": {"coordinates":[-80.72542199999999,40.094846],"type":"Point"}
}