{
  "type": "Feature",
  "properties": {
    "iso:country":"US",
    "sg:address":"416 Sheridan Ave",
    "sg:city":"Dayton",
    "sg:classifiers":[
        {
            "category":"Building & Trades",
            "subcategory":"Construction",
            "type":"Services"
        }
    ],
    "sg:phone":"+1 937 254 5273",
    "sg:postcode":"45403",
    "sg:province":"OH",
    "sg:tags":[
        "hanging",
        "contractor"
    ],
    "wof:name":"Bill Dalton Painting Inc",
    "wof:placetype":"venue"
},
  "geometry": {"coordinates":[-84.14800099999999,39.75995],"type":"Point"}
}