{
  "type": "Feature",
  "properties": {
    "addr:full": "416 Sheridan Ave Dayton OH 45403",
    "addr:housenumber": "416",
    "addr:postcode": "45403",
    "addr:street": "Sheridan Ave",
    "iso:country": "US",
    "sg:address": "416 Sheridan Ave",
    "sg:city": "Dayton",
    "sg:classifiers": [
      {
        "category": "Building \u0026 Trades",
        "subcategory": "Construction",
        "type": "Services"
      }
    ],
    "sg:phone": "+1 937 254 5273",
    "sg:postcode": "45403",
    "sg:province": "OH",
    "sg:tags": [
      "hanging",
      "contractor"
    ],
    "wof:name": "Bill Dalton Painting Inc",
    "wof:placetype": "venue"
  },
  "geometry": {"coordinates":[-84.148001,39.75995],"type":"Point"}
}
