{
  "type": "Feature",
  "properties": {
    "addr:full":"1505 Amherst Rd NE Massillon OH 44646",
    "addr:housenumber":"1505",
    "addr:postcode":"44646",
    "addr:street":"Amherst Rd Ne",
    "iso:country":"US",
    "sg:address":"1505 Amherst Rd NE",
    "sg:city":"Massillon",
    "sg:classifiers":[
        {
            "category":"Shopping",
            "subcategory":"Gifts & Souvenirs",
            "type":"Retail Goods"
        }
    ],
    "sg:phone":"+1 330 832 4100",
    "sg:postcode":"44646",
    "sg:province":"OH",
    "sg:tags":[
        "cards",
        "greeting"
    ],
    "wof:name":"Mortons Of Massillon",
    "wof:placetype":"venue"
},
  "geometry": {"coordinates":[-81.51646100000001,40.814302],"type":"Point"}
}