{
  "type": "Feature",
  "properties": {
    "iso:country":"US",
    "sg:address":"11100 Edwards Rd",
    "sg:city":"Johnstown",
    "sg:classifiers":[
        {
            "category":"Real Estate",
            "subcategory":"Real Estate Agent",
            "type":"Services"
        }
    ],
    "sg:phone":"+1 740 587 1820",
    "sg:postcode":"43031",
    "sg:province":"OH",
    "wof:name":"11100 Edwards Road LLC",
    "wof:placetype":"venue"
},
  "geometry": {"coordinates":[-82.698758,40.155251],"type":"Point"}
}