{
  "type": "Feature",
  "properties": {
    "iso:country":"US",
    "sg:address":"5368 Fulton Dr NW",
    "sg:city":"Canton",
    "sg:classifiers":[
        {
            "category":"Insurance",
            "subcategory":"Insurance Agent",
            "type":"Services"
        }
    ],
    "sg:phone":"+1 330 837 3573",
    "sg:postcode":"44718",
    "sg:province":"OH",
    "sg:tags":[
        "agency"
    ],
    "wof:name":"Mark Hickey Insurnace Agency",
    "wof:placetype":"venue"
},
  "geometry": {"coordinates":[-81.45099399999999,40.854011],"type":"Point"}
}