{
  "type": "Feature",
  "properties": {
    "iso:country":"US",
    "sg:address":"449 W Olentangy St",
    "sg:city":"Powell",
    "sg:classifiers":[
        {
            "category":"Autos & Motor Vehicles",
            "subcategory":"Automobile Sales",
            "type":"Retail Goods"
        }
    ],
    "sg:phone":"+1 614 760 8717",
    "sg:postcode":"43065",
    "sg:province":"OH",
    "sg:tags":[
        "car",
        "dealer"
    ],
    "wof:name":"Wedgewood Sports & Imports",
    "wof:placetype":"venue"
},
  "geometry": {"coordinates":[-83.08749299999999,40.158386],"type":"Point"}
}