{
  "type": "Feature",
  "properties": {
    "addr:full": "449 W Olentangy St Powell OH 43065",
    "addr:housenumber": "449",
    "addr:postcode": "43065",
    "addr:street": "W Olentangy St",
    "iso:country": "US",
    "sg:address": "449 W Olentangy St",
    "sg:city": "Powell",
    "sg:classifiers": [
      {
        "category": "Autos \u0026 Motor Vehicles",
        "subcategory": "Automobile Sales",
        "type": "Retail Goods"
      }
    ],
    "sg:phone": "+1 614 760 8717",
    "sg:postcode": "43065",
    "sg:province": "OH",
    "sg:tags": [
      "car",
      "dealer"
    ],
    "wof:name": "Wedgewood Sports \u0026 Imports",
    "wof:placetype": "venue"
  },
  "geometry": {"coordinates":[-83.087493,40.158386],"type":"Point"}
}
