{
  "type": "Feature",
  "properties": {
    "addr:full": "1241 Hill Rd N Pickerington OH 43147",
    "addr:housenumber": "1241",
    "addr:postcode": "43147",
    "addr:street": "Hill Rd N",
    "iso:country": "US",
    "sg:address": "1241 Hill Rd N",
    "sg:city": "Pickerington",
    "sg:classifiers": [
      {
        "category": "Wholesale",
        "subcategory": "Medical Equipment \u0026 Supplies",
        "type": "Manufacturing \u0026 Wholesale Goods"
      },
      {
        "category": "Health Services",
        "subcategory": "Doctor",
        "type": "Services"
      }
    ],
    "sg:phone": "+1 614 575 8911",
    "sg:postcode": "43147",
    "sg:province": "OH",
    "sg:tags": [
      "physician",
      "surgeon"
    ],
    "wof:name": "Orthopedic Laser Technologies",
    "wof:placetype": "venue"
  },
  "geometry": {"coordinates":[-82.780096,39.915037],"type":"Point"}
}
