{
  "type": "Feature",
  "properties": {
    "addr:full": "1265 E 2nd St Franklin OH 45005",
    "addr:housenumber": "1265",
    "addr:postcode": "45005",
    "addr:street": "E 2Nd St",
    "iso:country": "US",
    "sg:address": "1265 E 2nd St",
    "sg:city": "Franklin",
    "sg:classifiers": [
      {
        "category": "Retail",
        "subcategory": "Auto Repair",
        "type": "Services"
      }
    ],
    "sg:phone": "+1 937 746 4222",
    "sg:postcode": "45005",
    "sg:province": "OH",
    "sg:tags": [
      "repairing",
      "automobile"
    ],
    "wof:name": "Muffler Brothers",
    "wof:placetype": "venue"
  },
  "geometry": {"coordinates":[-84.279784,39.563711],"type":"Point"}
}
