{
  "type": "Feature",
  "properties": {
    "iso:country":"US",
    "sg:address":"901 N High St",
    "sg:city":"Columbus",
    "sg:classifiers":[
        {
            "category":"Food & Beverages",
            "subcategory":"Bakery",
            "type":"Retail Goods"
        }
    ],
    "sg:phone":"+1 614 888 7437",
    "sg:postcode":"43085",
    "sg:province":"OH",
    "wof:name":"Mrs Goodmans Baking",
    "wof:placetype":"venue"
},
  "geometry": {"coordinates":[-83.017965,40.092054],"type":"Point"}
}