{
  "type": "Feature",
  "properties": {
    "addr:full":"726 Ravenhill Northfield OH 44067",
    "addr:housenumber":"726",
    "addr:postcode":"44067",
    "addr:street":"Ravenhill",
    "iso:country":"US",
    "sg:address":"726 Ravenhill",
    "sg:city":"Northfield",
    "sg:classifiers":[
        {
            "category":"Wholesale",
            "subcategory":"Electrical",
            "type":"Manufacturing & Wholesale Goods"
        }
    ],
    "sg:phone":"+1 330 468 3063",
    "sg:postcode":"44067",
    "sg:province":"OH",
    "sg:tags":[
        "electric",
        "motor"
    ],
    "wof:name":"Emerson Motor Co",
    "wof:placetype":"venue"
},
  "geometry": {"coordinates":[-81.561002,41.304902],"type":"Point"}
}