{
  "type": "Feature",
  "properties": {
    "addr:full": "430 Forest Ave Cincinnati OH 45229",
    "addr:housenumber": "430",
    "addr:postcode": "45229",
    "addr:street": "Forest Ave",
    "iso:country": "US",
    "sg:address": "430 Forest Ave",
    "sg:city": "Cincinnati",
    "sg:classifiers": [
      {
        "category": "Organizations",
        "subcategory": "Religious Organization",
        "type": "Services"
      }
    ],
    "sg:phone": "+1 513 221 1685",
    "sg:postcode": "45229",
    "sg:province": "OH",
    "sg:tags": [
      "church"
    ],
    "wof:name": "Church Of The Living God CWF",
    "wof:placetype": "venue"
  },
  "geometry": {"coordinates":[-84.497877,39.146179],"type":"Point"}
}
