{
  "type": "Feature",
  "properties": {
    "iso:country":"US",
    "sg:address":"718 Tracht Meadows Dr",
    "sg:city":"Huron",
    "sg:classifiers":[
        {
            "category":"Utilities",
            "subcategory":"Telephone",
            "type":"Services"
        }
    ],
    "sg:phone":"+1 419 625 0096",
    "sg:postcode":"44839",
    "sg:province":"OH",
    "sg:tags":[
        "communications"
    ],
    "wof:name":"Image Set",
    "wof:placetype":"venue"
},
  "geometry": {"coordinates":[-82.61254,41.413585],"type":"Point"}
}