{
  "type": "Feature",
  "properties": {
    "iso:country":"US",
    "sg:address":"20 Waterloo Rd",
    "sg:city":"Mogadore",
    "sg:classifiers":[
        {
            "category":"Building & Trades",
            "subcategory":"Construction",
            "type":"Services"
        }
    ],
    "sg:phone":"+1 330 628 5883",
    "sg:postcode":"44260",
    "sg:province":"OH",
    "sg:tags":[
        "general",
        "contractor"
    ],
    "wof:name":"Northland Construction Corp",
    "wof:placetype":"venue"
},
  "geometry": {"coordinates":[-81.38975499999999,41.024712],"type":"Point"}
}