{
  "type": "Feature",
  "properties": {
    "addr:full": "20 Waterloo Rd Mogadore OH 44260",
    "addr:housenumber": "20",
    "addr:postcode": "44260",
    "addr:street": "Waterloo Rd",
    "iso:country": "US",
    "sg:address": "20 Waterloo Rd",
    "sg:city": "Mogadore",
    "sg:classifiers": [
      {
        "category": "Building \u0026 Trades",
        "subcategory": "Construction",
        "type": "Services"
      }
    ],
    "sg:phone": "+1 330 628 5883",
    "sg:postcode": "44260",
    "sg:province": "OH",
    "sg:tags": [
      "general",
      "contractor"
    ],
    "wof:name": "Northland Construction Corp",
    "wof:placetype": "venue"
  },
  "geometry": {"coordinates":[-81.389755,41.024712],"type":"Point"}
}
