{
  "type": "Feature",
  "properties": {
    "addr:full": "2001 Collingwood Blvd Toledo OH 43620",
    "addr:housenumber": "2001",
    "addr:postcode": "43620",
    "addr:street": "Collingwood Blvd",
    "iso:country": "US",
    "sg:address": "2001 Collingwood Blvd",
    "sg:city": "Toledo",
    "sg:classifiers": [
      {
        "category": "Education",
        "subcategory": "School",
        "type": "Public Place"
      }
    ],
    "sg:phone": "+1 419 248 3585",
    "sg:postcode": "43620",
    "sg:province": "OH",
    "sg:tags": [
      "executive",
      "management",
      "sch",
      "se"
    ],
    "wof:name": "Toledo Administration Bldg",
    "wof:placetype": "venue"
  },
  "geometry": {"coordinates":[-83.554985,41.661227],"type":"Point"}
}
