{
  "type": "Feature",
  "properties": {
    "iso:country":"US",
    "sg:address":"25052 Sperry Dr",
    "sg:city":"Westlake",
    "sg:classifiers":[
        {
            "category":"Restaurant",
            "type":"Food & Drink"
        }
    ],
    "sg:phone":"+1 440 892 4275",
    "sg:postcode":"44145",
    "sg:province":"OH",
    "sg:tags":[
        "contract"
    ],
    "wof:name":"Sodexho Inc",
    "wof:placetype":"venue"
},
  "geometry": {"coordinates":[-81.894334,41.474801],"type":"Point"}
}