{
  "type": "Feature",
  "properties": {
    "addr:full": "325 Quadral Dr Wadsworth OH 44281",
    "addr:housenumber": "325",
    "addr:postcode": "44281",
    "addr:street": "Quadral Dr",
    "iso:country": "US",
    "sg:address": "325 Quadral Dr",
    "sg:city": "Wadsworth",
    "sg:classifiers": [
      {
        "category": "Manufacturing",
        "subcategory": "Furniture",
        "type": "Manufacturing \u0026 Wholesale Goods"
      }
    ],
    "sg:phone": "+1 330 336 0317",
    "sg:postcode": "44281",
    "sg:province": "OH",
    "sg:tags": [
      "wood",
      "mfg"
    ],
    "wof:name": "Accel Group Inc",
    "wof:placetype": "venue"
  },
  "geometry": {"coordinates":[-81.760041,41.022948],"type":"Point"}
}
