{
  "type": "Feature",
  "properties": {
    "iso:country":"US",
    "sg:address":"325 Quadral Dr",
    "sg:city":"Wadsworth",
    "sg:classifiers":[
        {
            "category":"Manufacturing",
            "subcategory":"Furniture",
            "type":"Manufacturing & Wholesale Goods"
        }
    ],
    "sg:phone":"+1 330 336 0317",
    "sg:postcode":"44281",
    "sg:province":"OH",
    "sg:tags":[
        "wood",
        "mfg"
    ],
    "wof:name":"Accel Group Inc",
    "wof:placetype":"venue"
},
  "geometry": {"coordinates":[-81.760041,41.022948],"type":"Point"}
}