{
  "type": "Feature",
  "properties": {
    "addr:full": "16505 Chibiabos Trl Doylestown OH 44230",
    "addr:housenumber": "16505",
    "addr:postcode": "44230",
    "addr:street": "Chibiabos Trl",
    "iso:country": "US",
    "sg:address": "16505 Chibiabos Trl",
    "sg:city": "Doylestown",
    "sg:classifiers": [
      {
        "category": "Health Services",
        "subcategory": "Chiropractor",
        "type": "Services"
      }
    ],
    "sg:phone": "+1 330 658 1101",
    "sg:postcode": "44230",
    "sg:province": "OH",
    "wof:name": "Pavkov Russell W DC",
    "wof:placetype": "venue"
  },
  "geometry": {"coordinates":[-81.693703,40.9468],"type":"Point"}
}
