{
  "type": "Feature",
  "properties": {
    "iso:country":"US",
    "sg:address":"1405 Duxberry Ave",
    "sg:city":"Columbus",
    "sg:classifiers":[
        {
            "category":"Organizations",
            "subcategory":"Religious Organization",
            "type":"Services"
        }
    ],
    "sg:phone":"+1 614 294 5770",
    "sg:postcode":"43211",
    "sg:province":"OH",
    "sg:tags":[
        "clergy"
    ],
    "wof:name":"B S Williams",
    "wof:placetype":"venue"
},
  "geometry": {"coordinates":[-82.97126299999999,40.008823],"type":"Point"}
}