{
  "type": "Feature",
  "properties": {
    "addr:full": "1405 Duxberry Ave Columbus OH 43211",
    "addr:housenumber": "1405",
    "addr:postcode": "43211",
    "addr:street": "Duxberry Ave",
    "iso:country": "US",
    "sg:address": "1405 Duxberry Ave",
    "sg:city": "Columbus",
    "sg:classifiers": [
      {
        "category": "Organizations",
        "subcategory": "Religious Organization",
        "type": "Services"
      }
    ],
    "sg:phone": "+1 614 294 5770",
    "sg:postcode": "43211",
    "sg:province": "OH",
    "sg:tags": [
      "clergy"
    ],
    "wof:name": "B S Williams",
    "wof:placetype": "venue"
  },
  "geometry": {"coordinates":[-82.971263,40.008823],"type":"Point"}
}
