{
  "type": "Feature",
  "properties": {
    "addr:full": "2300 Chester Ave Rm 158 Cleveland OH 44114",
    "addr:housenumber": "2300;158",
    "addr:postcode": "44114",
    "addr:street": "Chester Ave Rm",
    "iso:country": "US",
    "sg:address": "2300 Chester Ave Rm 158",
    "sg:city": "Cleveland",
    "sg:classifiers": [
      {
        "category": "Education",
        "subcategory": "University",
        "type": "Public Place"
      }
    ],
    "sg:phone": "+1 216 687 2544",
    "sg:postcode": "44114",
    "sg:province": "OH",
    "sg:tags": [
      "college"
    ],
    "sg:website": "http://www.csuohio.edu",
    "wof:name": "Cleveland State University",
    "wof:placetype": "venue"
  },
  "geometry": {"coordinates":[-81.674076,41.503818],"type":"Point"}
}
