{
  "type": "Feature",
  "properties": {
    "addr:full":"1476 State Rte 503 Arcanum OH 45304",
    "addr:housenumber":"1476",
    "addr:postcode":"45304",
    "addr:street":"State Rte 503",
    "iso:country":"US",
    "sg:address":"1476 State Rte 503",
    "sg:city":"Arcanum",
    "sg:classifiers":[
        {
            "category":"Sports & Exercise",
            "subcategory":"Golf",
            "type":"Entertainment"
        }
    ],
    "sg:phone":"+1 937 678 4422",
    "sg:postcode":"45304",
    "sg:province":"OH",
    "sg:tags":[
        "shop",
        "course",
        "pro",
        "public"
    ],
    "sg:website":"www.beechwoodgc.com",
    "wof:name":"Beechwood Golf Course",
    "wof:placetype":"venue"
},
  "geometry": {"coordinates":[-84.58113899999999,39.958984],"type":"Point"}
}