{
  "type": "Feature",
  "properties": {
    "addr:full":"1115 W Robb Ave Lima OH 45801",
    "addr:housenumber":"1115",
    "addr:postcode":"45801",
    "addr:street":"W Robb Ave",
    "iso:country":"US",
    "sg:address":"1115 W Robb Ave",
    "sg:city":"Lima",
    "sg:classifiers":[
        {
            "category":"Utilities",
            "subcategory":"Mobile Phone",
            "type":"Services"
        }
    ],
    "sg:phone":"+1 419 225 6337",
    "sg:postcode":"45801",
    "sg:province":"OH",
    "sg:tags":[
        "telephone",
        "cellular"
    ],
    "wof:name":"Royal Cellular Inc",
    "wof:placetype":"venue"
},
  "geometry": {"coordinates":[-84.124257,40.758794],"type":"Point"}
}