{
  "type": "Feature",
  "properties": {
    "addr:full": "16 N 6th St Zanesville OH 43701",
    "addr:housenumber": "16",
    "addr:postcode": "43701",
    "addr:street": "N 6Th St",
    "iso:country": "US",
    "sg:address": "16 N 6th St",
    "sg:city": "Zanesville",
    "sg:classifiers": [
      {
        "category": "Food \u0026 Beverages",
        "subcategory": "Groceries \u0026 Convenience Stores",
        "type": "Retail Goods"
      }
    ],
    "sg:phone": "+1 740 452 9160",
    "sg:postcode": "43701",
    "sg:province": "OH",
    "wof:name": "Cigarette Shop",
    "wof:placetype": "venue"
  },
  "geometry": {"coordinates":[-82.005075,39.940652],"type":"Point"}
}
