{
  "type": "Feature",
  "properties": {
    "iso:country":"US",
    "sg:address":"16 N 6th St",
    "sg:city":"Zanesville",
    "sg:classifiers":[
        {
            "category":"Food & Beverages",
            "subcategory":"Groceries & Convenience Stores",
            "type":"Retail Goods"
        }
    ],
    "sg:phone":"+1 740 452 9160",
    "sg:postcode":"43701",
    "sg:province":"OH",
    "wof:name":"Cigarette Shop",
    "wof:placetype":"venue"
},
  "geometry": {"coordinates":[-82.00507500000001,39.940652],"type":"Point"}
}