{
  "type": "Feature",
  "properties": {
    "iso:country":"US",
    "sg:address":"126 Twp Rd 1384",
    "sg:city":"Proctorville",
    "sg:classifiers":[
        {
            "category":"Building & Trades",
            "subcategory":"Construction",
            "type":"Services"
        }
    ],
    "sg:phone":"+1 740 886 9218",
    "sg:postcode":"45669",
    "sg:province":"OH",
    "sg:tags":[
        "contractor"
    ],
    "wof:name":"Curtain Concepts",
    "wof:placetype":"venue"
},
  "geometry": {"coordinates":[-82.345578,38.450345],"type":"Point"}
}