{
  "type": "Feature",
  "properties": {
    "iso:country":"US",
    "sg:address":"32705 Stony Brook Ln",
    "sg:city":"Cleveland",
    "sg:classifiers":[
        {
            "category":"Insurance",
            "subcategory":"Insurance Agent",
            "type":"Services"
        }
    ],
    "sg:phone":"+1 440 248 1737",
    "sg:postcode":"44139",
    "sg:province":"OH",
    "wof:name":"Irene Muro Insurance",
    "wof:placetype":"venue"
},
  "geometry": {"coordinates":[-81.446505,41.403309],"type":"Point"}
}