{
  "type": "Feature",
  "properties": {
    "iso:country":"US",
    "sg:address":"19642 Center Ridge Rd",
    "sg:city":"Cleveland",
    "sg:classifiers":[
        {
            "category":"Retail",
            "subcategory":"Laundry & Dry Cleaning",
            "type":"Services"
        }
    ],
    "sg:phone":"+1 440 333 6685",
    "sg:postcode":"44116",
    "sg:province":"OH",
    "wof:name":"Nu Look Tailors & Dry Cleaning",
    "wof:placetype":"venue"
},
  "geometry": {"coordinates":[-81.84071900000001,41.46526],"type":"Point"}
}