{
  "type": "Feature",
  "properties": {
    "addr:full": "1747 Chester Rd Pomeroy OH 45769",
    "addr:housenumber": "1747",
    "addr:postcode": "45769",
    "addr:street": "Chester Rd",
    "iso:country": "US",
    "sg:address": "1747 Chester Rd",
    "sg:city": "Pomeroy",
    "sg:classifiers": [
      {
        "category": "Shopping",
        "type": "Retail Goods"
      }
    ],
    "sg:phone": "+1 740 992 1600",
    "sg:postcode": "45769",
    "sg:province": "OH",
    "sg:tags": [
      "monument"
    ],
    "wof:name": "Beautiful Memorys Monument",
    "wof:placetype": "venue"
  },
  "geometry": {"coordinates":[-82.005555,39.034184],"type":"Point"}
}
