{
  "type": "Feature",
  "properties": {
    "addr:full": "1414 N Main St Orrville OH 44667",
    "addr:housenumber": "1414",
    "addr:postcode": "44667",
    "addr:street": "N Main St",
    "iso:country": "US",
    "sg:address": "1414 N Main St",
    "sg:city": "Orrville",
    "sg:classifiers": [
      {
        "category": "Government",
        "subcategory": "Fire Station",
        "type": "Public Place"
      }
    ],
    "sg:phone": "+1 330 000 1111",
    "sg:postcode": "44667",
    "sg:province": "OH",
    "sg:tags": [
      "department"
    ],
    "wof:name": "Ashland County Fire Dept",
    "wof:placetype": "venue"
  },
  "geometry": {"coordinates":[-81.763601,40.858618],"type":"Point"}
}
