{
  "type": "Feature",
  "properties": {
    "addr:full": "1005 E Long St Columbus OH 43203",
    "addr:housenumber": "1005",
    "addr:postcode": "43203",
    "addr:street": "E Long St",
    "iso:country": "US",
    "sg:address": "1005 E Long St",
    "sg:city": "Columbus",
    "sg:classifiers": [
      {
        "category": "Shopping",
        "subcategory": "Luggage \u0026 Leather Goods",
        "type": "Retail Goods"
      }
    ],
    "sg:phone": "+1 614 476 8559",
    "sg:postcode": "43203",
    "sg:province": "OH",
    "sg:tags": [
      "parlor",
      "shoe"
    ],
    "wof:name": "Fashions By Harry",
    "wof:placetype": "venue"
  },
  "geometry": {"coordinates":[-82.975051,39.967929],"type":"Point"}
}
