{
  "type": "Feature",
  "properties": {
    "iso:country":"US",
    "sg:address":"430 Oberlin Rd",
    "sg:city":"Elyria",
    "sg:classifiers":[
        {
            "category":"Autos & Motor Vehicles",
            "subcategory":"Fuel & Gas Station",
            "type":"Retail Goods"
        }
    ],
    "sg:phone":"+1 440 323 4262",
    "sg:postcode":"44035",
    "sg:province":"OH",
    "sg:tags":[
        "station",
        "gasoline"
    ],
    "wof:name":"Fuel Mart 719",
    "wof:placetype":"venue"
},
  "geometry": {"coordinates":[-82.11477499999999,41.345093],"type":"Point"}
}