{
  "type": "Feature",
  "properties": {
    "iso:country":"US",
    "sg:address":"1441 Wagar Ave",
    "sg:city":"Cleveland",
    "sg:classifiers":[
        {
            "category":"Building & Trades",
            "subcategory":"Construction",
            "type":"Services"
        }
    ],
    "sg:phone":"+1 216 228 0138",
    "sg:postcode":"44107",
    "sg:province":"OH",
    "sg:tags":[
        "hanging",
        "painter",
        "contractor"
    ],
    "wof:name":"Allure Painting",
    "wof:placetype":"venue"
},
  "geometry": {"coordinates":[-81.812798,41.478526],"type":"Point"}
}