{
  "type": "Feature",
  "properties": {
    "addr:full": "1441 Wagar Ave Cleveland OH 44107",
    "addr:housenumber": "1441",
    "addr:postcode": "44107",
    "addr:street": "Wagar Ave",
    "iso:country": "US",
    "sg:address": "1441 Wagar Ave",
    "sg:city": "Cleveland",
    "sg:classifiers": [
      {
        "category": "Building \u0026 Trades",
        "subcategory": "Construction",
        "type": "Services"
      }
    ],
    "sg:phone": "+1 216 228 0138",
    "sg:postcode": "44107",
    "sg:province": "OH",
    "sg:tags": [
      "hanging",
      "painter",
      "contractor"
    ],
    "wof:name": "Allure Painting",
    "wof:placetype": "venue"
  },
  "geometry": {"coordinates":[-81.812798,41.478526],"type":"Point"}
}
