{
  "type": "Feature",
  "properties": {
    "iso:country":"US",
    "sg:address":"2791 State Rte 44",
    "sg:city":"Rootstown",
    "sg:classifiers":[
        {
            "category":"Retail",
            "subcategory":"Repair Shop",
            "type":"Services"
        }
    ],
    "sg:phone":"+1 330 325 8886",
    "sg:postcode":"44272",
    "sg:province":"OH",
    "sg:tags":[
        "upholsterer"
    ],
    "wof:name":"Conley's Unlimited Upholstery",
    "wof:placetype":"venue"
},
  "geometry": {"coordinates":[-81.247398,41.06134],"type":"Point"}
}