{
  "type": "Feature",
  "properties": {
    "iso:country":"US",
    "sg:address":"1133 Highland Ave",
    "sg:city":"Napoleon",
    "sg:classifiers":[
        {
            "category":"Professional",
            "type":"Services"
        }
    ],
    "sg:phone":"+1 419 439 0829",
    "sg:postcode":"43545",
    "sg:province":"OH",
    "wof:name":"Network Guy",
    "wof:placetype":"venue"
},
  "geometry": {"coordinates":[-84.135677,41.395652],"type":"Point"}
}