{
  "type": "Feature",
  "properties": {
    "iso:country":"US",
    "sg:address":"50 E 3rd St",
    "sg:city":"Dayton",
    "sg:classifiers":[
        {
            "category":"Professional",
            "subcategory":"Lawyer & Legal Services",
            "type":"Services"
        }
    ],
    "sg:phone":"+1 937 223 0135",
    "sg:postcode":"45403",
    "sg:province":"OH",
    "sg:tags":[
        "attorney"
    ],
    "wof:name":"Gianuglou Skilken & Replogle",
    "wof:placetype":"venue"
},
  "geometry": {"coordinates":[-84.19085,39.75961],"type":"Point"}
}