{
  "type": "Feature",
  "properties": {
    "iso:country":"US",
    "sg:address":"9696 Colerain Ave",
    "sg:city":"Cincinnati",
    "sg:classifiers":[
        {
            "category":"Home & Garden",
            "subcategory":"Home Furnishings",
            "type":"Retail Goods"
        }
    ],
    "sg:phone":"+1 513 741 0700",
    "sg:postcode":"45251",
    "sg:province":"OH",
    "sg:tags":[
        "window",
        "covering"
    ],
    "wof:name":"Blinds Direct",
    "wof:placetype":"venue"
},
  "geometry": {"coordinates":[-84.59561100000001,39.2453],"type":"Point"}
}