{
  "type": "Feature",
  "properties": {
    "addr:full": "721 W Coshocton St Johnstown OH 43031",
    "addr:housenumber": "721",
    "addr:postcode": "43031",
    "addr:street": "W Coshocton St",
    "iso:country": "US",
    "sg:address": "721 W Coshocton St",
    "sg:city": "Johnstown",
    "sg:classifiers": [
      {
        "category": "Personal",
        "subcategory": "Beauty Salon",
        "type": "Services"
      }
    ],
    "sg:phone": "+1 740 966 5596",
    "sg:postcode": "43031",
    "sg:province": "OH",
    "wof:name": "G Q Nails Salon",
    "wof:placetype": "venue"
  },
  "geometry": {"coordinates":[-82.700358,40.147688],"type":"Point"}
}
