{
  "type": "Feature",
  "properties": {
    "addr:full":"3600 Regent Ave NE Canton OH 44705",
    "addr:housenumber":"3600",
    "addr:postcode":"44705",
    "addr:street":"Regent Ave Ne",
    "iso:country":"US",
    "sg:address":"3600 Regent Ave NE",
    "sg:city":"Canton",
    "sg:classifiers":[
        {
            "category":"Restaurant",
            "type":"Food & Drink"
        }
    ],
    "sg:phone":"+1 330 458 0691",
    "sg:postcode":"44705",
    "sg:province":"OH",
    "wof:name":"Denny's",
    "wof:placetype":"venue"
},
  "geometry": {"coordinates":[-81.33643499999999,40.836378],"type":"Point"}
}