{
  "type": "Feature",
  "properties": {
    "iso:country":"US",
    "sg:address":"1800 E State St",
    "sg:city":"Fremont",
    "sg:classifiers":[
        {
            "category":"Food & Beverages",
            "subcategory":"Groceries & Convenience Stores",
            "type":"Retail Goods"
        }
    ],
    "sg:phone":"+1 419 332 7200",
    "sg:postcode":"43420",
    "sg:province":"OH",
    "wof:name":"Seaway Food Town",
    "wof:placetype":"venue"
},
  "geometry": {"coordinates":[-83.084492,41.339621],"type":"Point"}
}