{
  "type": "Feature",
  "properties": {
    "addr:full": "1800 E State St Fremont OH 43420",
    "addr:housenumber": "1800",
    "addr:postcode": "43420",
    "addr:street": "E State St",
    "iso:country": "US",
    "sg:address": "1800 E State St",
    "sg:city": "Fremont",
    "sg:classifiers": [
      {
        "category": "Food \u0026 Beverages",
        "subcategory": "Groceries \u0026 Convenience Stores",
        "type": "Retail Goods"
      }
    ],
    "sg:phone": "+1 419 332 7200",
    "sg:postcode": "43420",
    "sg:province": "OH",
    "wof:name": "Seaway Food Town",
    "wof:placetype": "venue"
  },
  "geometry": {"coordinates":[-83.084492,41.339621],"type":"Point"}
}
