{
  "type": "Feature",
  "properties": {
    "addr:full": "230 Northland Blvd Cincinnati OH 45246",
    "addr:housenumber": "230",
    "addr:postcode": "45246",
    "addr:street": "Northland Blvd",
    "iso:country": "US",
    "sg:address": "230 Northland Blvd",
    "sg:city": "Cincinnati",
    "sg:classifiers": [
      {
        "category": "Banks \u0026 Credit Unions",
        "subcategory": "Bank",
        "type": "Services"
      }
    ],
    "sg:phone": "+1 513 771 2644",
    "sg:postcode": "45246",
    "sg:province": "OH",
    "sg:tags": [
      "loan",
      "real estate"
    ],
    "wof:name": "Prime Mortgage Us",
    "wof:placetype": "venue"
  },
  "geometry": {"coordinates":[-84.481279,39.282735],"type":"Point"}
}
