{
  "type": "Feature",
  "properties": {
    "iso:country":"US",
    "sg:address":"7706 W Chester Rd",
    "sg:city":"West Chester",
    "sg:classifiers":[
        {
            "category":"Restaurant",
            "type":"Food & Drink"
        }
    ],
    "sg:phone":"+1 513 755 2011",
    "sg:postcode":"45069",
    "sg:province":"OH",
    "sg:tags":[
        "barbecue"
    ],
    "wof:name":"City Bar B Que",
    "wof:placetype":"venue"
},
  "geometry": {"coordinates":[-84.375203,39.319242],"type":"Point"}
}