{
  "type": "Feature",
  "properties": {
    "addr:full": "5151 Warner Rd Cleveland OH 44125",
    "addr:housenumber": "5151",
    "addr:postcode": "44125",
    "addr:street": "Warner Rd",
    "iso:country": "US",
    "sg:address": "5151 Warner Rd",
    "sg:city": "Cleveland",
    "sg:classifiers": [
      {
        "category": "Wholesale",
        "subcategory": "Auto Parts",
        "type": "Manufacturing \u0026 Wholesale Goods"
      }
    ],
    "sg:phone": "+1 216 341 4944",
    "sg:postcode": "44125",
    "sg:province": "OH",
    "sg:tags": [
      "retreading",
      "tire",
      "supply"
    ],
    "wof:name": "Ziegler Tire Service",
    "wof:placetype": "venue"
  },
  "geometry": {"coordinates":[-81.633481,41.430779],"type":"Point"}
}
