{
  "type": "Feature",
  "properties": {
    "addr:full":"334 Mc Gregor Ave Cincinnati OH 45219",
    "addr:housenumber":"334",
    "addr:postcode":"45219",
    "addr:street":"Mc Gregor Ave",
    "iso:country":"US",
    "sg:address":"334 Mc Gregor Ave",
    "sg:city":"Cincinnati",
    "sg:classifiers":[
        {
            "category":"Health Services",
            "subcategory":"Clinic",
            "type":"Services"
        }
    ],
    "sg:phone":"+1 513 684 7960",
    "sg:postcode":"45219",
    "sg:province":"OH",
    "sg:tags":[
        "home"
    ],
    "sg:website":"www.talberthouse.org",
    "wof:name":"Mcgregor House",
    "wof:placetype":"venue"
},
  "geometry": {"coordinates":[-84.502044,39.122855],"type":"Point"}
}