{
  "type": "Feature",
  "properties": {
    "iso:country":"US",
    "sg:address":"3073 Diehl Rd",
    "sg:city":"Cincinnati",
    "sg:classifiers":[
        {
            "category":"Shopping",
            "subcategory":"Gifts & Souvenirs",
            "type":"Retail Goods"
        }
    ],
    "sg:phone":"+1 513 662 0425",
    "sg:postcode":"45211",
    "sg:province":"OH",
    "wof:name":"Pedal On Right",
    "wof:placetype":"venue"
},
  "geometry": {"coordinates":[-84.597317,39.169704],"type":"Point"}
}