{
  "type": "Feature",
  "properties": {
    "addr:full":"199 S Sandusky St Delaware OH 43015",
    "addr:housenumber":"199",
    "addr:postcode":"43015",
    "addr:street":"S Sandusky St",
    "iso:country":"US",
    "sg:address":"199 S Sandusky St",
    "sg:city":"Delaware",
    "sg:classifiers":[
        {
            "category":"Banks & Credit Unions",
            "subcategory":"Bank",
            "type":"Services"
        }
    ],
    "sg:phone":"+1 740 363 5300",
    "sg:postcode":"43015",
    "sg:province":"OH",
    "wof:name":"Delaware County Bank & Trust",
    "wof:placetype":"venue"
},
  "geometry": {"coordinates":[-83.068151,40.293534],"type":"Point"}
}