{
  "type": "Feature",
  "properties": {
    "iso:country":"US",
    "sg:address":"3012 Glenmore Ave",
    "sg:city":"Cincinnati",
    "sg:classifiers":[
        {
            "category":"Health Services",
            "subcategory":"Doctor",
            "type":"Services"
        }
    ],
    "sg:phone":"+1 513 661 4140",
    "sg:postcode":"45238",
    "sg:province":"OH",
    "sg:tags":[
        "physician",
        "surgeon"
    ],
    "wof:name":"Zalzal Bouchard Inc",
    "wof:placetype":"venue"
},
  "geometry": {"coordinates":[-84.613886,39.136705],"type":"Point"}
}