{
  "type": "Feature",
  "properties": {
    "addr:full":"7381 State Rte 3 Westerville OH 43082",
    "addr:housenumber":"7381",
    "addr:postcode":"43082",
    "addr:street":"State Rte 3",
    "iso:country":"US",
    "sg:address":"7381 State Rte 3",
    "sg:city":"Westerville",
    "sg:classifiers":[
        {
            "category":"Food & Beverages",
            "subcategory":"Specialty",
            "type":"Retail Goods"
        }
    ],
    "sg:phone":"+1 614 891 2502",
    "sg:postcode":"43082",
    "sg:province":"OH",
    "sg:tags":[
        "health",
        "diet"
    ],
    "wof:name":"GNC",
    "wof:placetype":"venue"
},
  "geometry": {"coordinates":[-82.920704,40.151959],"type":"Point"}
}