{
  "type": "Feature",
  "properties": {
    "addr:full": "27629 Chagrin Blvd Woodmere OH 44122",
    "addr:housenumber": "27629",
    "addr:postcode": "44122",
    "addr:street": "Chagrin Blvd",
    "iso:country": "US",
    "sg:address": "27629 Chagrin Blvd",
    "sg:city": "Woodmere",
    "sg:classifiers": [
      {
        "category": "Professional",
        "subcategory": "Lawyer \u0026 Legal Services",
        "type": "Services"
      }
    ],
    "sg:phone": "+1 216 831 2552",
    "sg:postcode": "44122",
    "sg:province": "OH",
    "sg:tags": [
      "personal",
      "injury"
    ],
    "wof:name": "Hoffman Gary H Atty",
    "wof:placetype": "venue"
  },
  "geometry": {"coordinates":[-81.483057,41.462789],"type":"Point"}
}
