{
  "type": "Feature",
  "properties": {
    "iso:country":"US",
    "sg:address":"727 8th St",
    "sg:city":"Portsmouth",
    "sg:classifiers":[
        {
            "category":"Health Services",
            "subcategory":"Clinic",
            "type":"Services"
        }
    ],
    "sg:phone":"+1 740 353 4183",
    "sg:postcode":"45662",
    "sg:province":"OH",
    "sg:tags":[
        "home"
    ],
    "sg:website":"www.somc.org",
    "wof:name":"Southern Ohio Caregivers",
    "wof:placetype":"venue"
},
  "geometry": {"coordinates":[-82.99809500000001,38.736538],"type":"Point"}
}