{
  "type": "Feature",
  "properties": {
    "addr:full": "401 W 21st St Lorain OH 44052",
    "addr:housenumber": "401",
    "addr:postcode": "44052",
    "addr:street": "W 21St St",
    "iso:country": "US",
    "sg:address": "401 W 21st St",
    "sg:city": "Lorain",
    "sg:classifiers": [
      {
        "category": "Insurance",
        "subcategory": "Insurance Agent",
        "type": "Services"
      }
    ],
    "sg:phone": "+1 440 244 2022",
    "sg:postcode": "44052",
    "sg:province": "OH",
    "wof:name": "Graziano Insurance Agency",
    "wof:placetype": "venue"
  },
  "geometry": {"coordinates":[-82.172822,41.450921],"type":"Point"}
}
