{
  "type": "Feature",
  "properties": {
    "iso:country":"US",
    "sg:address":"401 W 21st St",
    "sg:city":"Lorain",
    "sg:classifiers":[
        {
            "category":"Insurance",
            "subcategory":"Insurance Agent",
            "type":"Services"
        }
    ],
    "sg:phone":"+1 440 244 2022",
    "sg:postcode":"44052",
    "sg:province":"OH",
    "wof:name":"Graziano Insurance Agency",
    "wof:placetype":"venue"
},
  "geometry": {"coordinates":[-82.172822,41.450921],"type":"Point"}
}