{
  "type": "Feature",
  "properties": {
    "iso:country":"US",
    "sg:address":"6307 Busch Blvd",
    "sg:city":"Columbus",
    "sg:classifiers":[
        {
            "category":"Wholesale",
            "subcategory":"Electrical",
            "type":"Manufacturing & Wholesale Goods"
        }
    ],
    "sg:phone":"+1 614 841 0020",
    "sg:postcode":"43229",
    "sg:province":"OH",
    "sg:tags":[
        "battery",
        "repair",
        "industrial"
    ],
    "wof:name":"Capital Forklift & Battery",
    "wof:placetype":"venue"
},
  "geometry": {"coordinates":[-82.99369900000001,40.095553],"type":"Point"}
}