{
  "type": "Feature",
  "properties": {
    "addr:full": "6307 Busch Blvd Columbus OH 43229",
    "addr:housenumber": "6307",
    "addr:postcode": "43229",
    "addr:street": "Busch Blvd",
    "iso:country": "US",
    "sg:address": "6307 Busch Blvd",
    "sg:city": "Columbus",
    "sg:classifiers": [
      {
        "category": "Wholesale",
        "subcategory": "Electrical",
        "type": "Manufacturing \u0026 Wholesale Goods"
      }
    ],
    "sg:phone": "+1 614 841 0020",
    "sg:postcode": "43229",
    "sg:province": "OH",
    "sg:tags": [
      "battery",
      "repair",
      "industrial"
    ],
    "wof:name": "Capital Forklift \u0026 Battery",
    "wof:placetype": "venue"
  },
  "geometry": {"coordinates":[-82.993699,40.095553],"type":"Point"}
}
