{
  "type": "Feature",
  "properties": {
    "iso:country":"US",
    "sg:address":"5630 E Clinton St",
    "sg:city":"Albany",
    "sg:classifiers":[
        {
            "category":"Retail",
            "subcategory":"Repair Shop",
            "type":"Services"
        }
    ],
    "sg:phone":"+1 740 698 4491",
    "sg:postcode":"45710",
    "sg:province":"OH",
    "sg:tags":[
        "r",
        "machinery",
        "supply"
    ],
    "wof:name":"Dels Ford Tractor Sales",
    "wof:placetype":"venue"
},
  "geometry": {"coordinates":[-82.197565,39.227102],"type":"Point"}
}