{
  "type": "Feature",
  "properties": {
    "addr:full": "2229 Gardenland Ave Niles OH 44446",
    "addr:housenumber": "2229",
    "addr:postcode": "44446",
    "addr:street": "Gardenland Ave",
    "iso:country": "US",
    "sg:address": "2229 Gardenland Ave",
    "sg:city": "Niles",
    "sg:classifiers": [
      {
        "category": "Government",
        "subcategory": "Fire Station",
        "type": "Public Place"
      }
    ],
    "sg:phone": "+1 330 652 9711",
    "sg:postcode": "44446",
    "sg:province": "OH",
    "sg:tags": [
      "department"
    ],
    "wof:name": "Weathersfield Township Fire",
    "wof:placetype": "venue"
  },
  "geometry": {"coordinates":[-80.717169,41.1832],"type":"Point"}
}
