{
  "type": "Feature",
  "properties": {
    "iso:country":"US",
    "sg:address":"2229 Gardenland Ave",
    "sg:city":"Niles",
    "sg:classifiers":[
        {
            "category":"Government",
            "subcategory":"Fire Station",
            "type":"Public Place"
        }
    ],
    "sg:phone":"+1 330 652 9711",
    "sg:postcode":"44446",
    "sg:province":"OH",
    "sg:tags":[
        "department"
    ],
    "wof:name":"Weathersfield Township Fire",
    "wof:placetype":"venue"
},
  "geometry": {"coordinates":[-80.717169,41.1832],"type":"Point"}
}