{
  "type": "Feature",
  "properties": {
    "addr:full":"6961 Village Woods Pl Columbus OH 43085",
    "addr:housenumber":"6961",
    "addr:postcode":"43085",
    "addr:street":"Village Woods Pl",
    "iso:country":"US",
    "sg:address":"6961 Village Woods Pl",
    "sg:city":"Columbus",
    "sg:classifiers":[
        {
            "category":"Building & Trades",
            "subcategory":"Construction",
            "type":"Services"
        }
    ],
    "sg:phone":"+1 614 433 7326",
    "sg:postcode":"43085",
    "sg:province":"OH",
    "sg:tags":[
        "residential"
    ],
    "wof:name":"Fournier & Associates",
    "wof:placetype":"venue"
},
  "geometry": {"coordinates":[-83.007969,40.106748],"type":"Point"}
}