{
  "type": "Feature",
  "properties": {
    "addr:full": "6588 Old Hall Rd Galloway OH 43119",
    "addr:housenumber": "6588",
    "addr:postcode": "43119",
    "addr:street": "Old Hall Rd",
    "iso:country": "US",
    "sg:address": "6588 Old Hall Rd",
    "sg:city": "Galloway",
    "sg:classifiers": [
      {
        "category": "Professional",
        "subcategory": "Lawyer \u0026 Legal Services",
        "type": "Services"
      }
    ],
    "sg:phone": "+1 614 853 2795",
    "sg:postcode": "43119",
    "sg:province": "OH",
    "sg:tags": [
      "attorney"
    ],
    "wof:name": "Nicolle A Schlosser",
    "wof:placetype": "venue"
  },
  "geometry": {"coordinates":[-83.170954,39.932133],"type":"Point"}
}
