{
  "type": "Feature",
  "properties": {
    "iso:country":"US",
    "sg:address":"8845 Lake Rd",
    "sg:city":"Seville",
    "sg:classifiers":[
        {
            "category":"Autos & Motor Vehicles",
            "subcategory":"Automobile Sales",
            "type":"Retail Goods"
        }
    ],
    "sg:phone":"+1 330 769 8300",
    "sg:postcode":"44273",
    "sg:province":"OH",
    "sg:tags":[
        "used",
        "truck"
    ],
    "sg:website":"www.selecttrucksofcleveland.com",
    "wof:name":"Select Trucks Cleveland LLC",
    "wof:placetype":"venue"
},
  "geometry": {"coordinates":[-81.90621299999999,41.03383],"type":"Point"}
}