{
  "type": "Feature",
  "properties": {
    "addr:full": "2481 Sutter Pkwy Dublin OH 43016",
    "addr:housenumber": "2481",
    "addr:postcode": "43016",
    "addr:street": "Sutter Pkwy",
    "iso:country": "US",
    "sg:address": "2481 Sutter Pkwy",
    "sg:city": "Dublin",
    "sg:classifiers": [
      {
        "category": "Wholesale",
        "subcategory": "Electrical",
        "type": "Manufacturing \u0026 Wholesale Goods"
      }
    ],
    "sg:phone": "+1 614 799 8501",
    "sg:postcode": "43016",
    "sg:province": "OH",
    "sg:tags": [
      "control"
    ],
    "wof:name": "Control \u0026 Instrumentation Svc",
    "wof:placetype": "venue"
  },
  "geometry": {"coordinates":[-83.08292,40.121598],"type":"Point"}
}
