{
  "type": "Feature",
  "properties": {
    "iso:country":"US",
    "sg:address":"2481 Sutter Pkwy",
    "sg:city":"Dublin",
    "sg:classifiers":[
        {
            "category":"Wholesale",
            "subcategory":"Electrical",
            "type":"Manufacturing & Wholesale Goods"
        }
    ],
    "sg:phone":"+1 614 799 8501",
    "sg:postcode":"43016",
    "sg:province":"OH",
    "sg:tags":[
        "control"
    ],
    "wof:name":"Control & Instrumentation Svc",
    "wof:placetype":"venue"
},
  "geometry": {"coordinates":[-83.08292,40.121598],"type":"Point"}
}