{
  "type": "Feature",
  "properties": {
    "iso:country":"US",
    "sg:address":"320 Brentwood Dr",
    "sg:city":"Painesville",
    "sg:classifiers":[
        {
            "category":"Wholesale",
            "subcategory":"Non-durable Goods",
            "type":"Manufacturing & Wholesale Goods"
        }
    ],
    "sg:phone":"+1 440 639 0300",
    "sg:postcode":"44077",
    "sg:province":"OH",
    "sg:tags":[
        "bag",
        "multipurpose"
    ],
    "wof:name":"J&D Industries",
    "wof:placetype":"venue"
},
  "geometry": {"coordinates":[-81.25979599999999,41.707543],"type":"Point"}
}