{
  "type": "Feature",
  "properties": {
    "addr:full": "320 Brentwood Dr Painesville OH 44077",
    "addr:housenumber": "320",
    "addr:postcode": "44077",
    "addr:street": "Brentwood Dr",
    "iso:country": "US",
    "sg:address": "320 Brentwood Dr",
    "sg:city": "Painesville",
    "sg:classifiers": [
      {
        "category": "Wholesale",
        "subcategory": "Non-durable Goods",
        "type": "Manufacturing \u0026 Wholesale Goods"
      }
    ],
    "sg:phone": "+1 440 639 0300",
    "sg:postcode": "44077",
    "sg:province": "OH",
    "sg:tags": [
      "bag",
      "multipurpose"
    ],
    "wof:name": "J\u0026D Industries",
    "wof:placetype": "venue"
  },
  "geometry": {"coordinates":[-81.259796,41.707543],"type":"Point"}
}
