{
  "type": "Feature",
  "properties": {
    "addr:full":"3740 Easton Market Columbus OH 43219",
    "addr:housenumber":"3740",
    "addr:postcode":"43219",
    "addr:street":"Easton",
    "iso:country":"US",
    "sg:address":"3740 Easton Market",
    "sg:city":"Columbus",
    "sg:classifiers":[
        {
            "category":"Home & Garden",
            "subcategory":"Furniture",
            "type":"Retail Goods"
        }
    ],
    "sg:phone":"+1 614 418 9855",
    "sg:postcode":"43219",
    "sg:province":"OH",
    "sg:website":"www.kittlesfurniture.com",
    "wof:name":"Kittle's Home Furnishings",
    "wof:placetype":"venue"
},
  "geometry": {"coordinates":[-82.92187699999999,40.051411],"type":"Point"}
}