{
  "type": "Feature",
  "properties": {
    "iso:country":"US",
    "sg:address":"307 W Johnson St",
    "sg:city":"Upper Sandusky",
    "sg:classifiers":[
        {
            "category":"Banks & Credit Unions",
            "subcategory":"Financial Services",
            "type":"Services"
        }
    ],
    "sg:phone":"+1 419 294 3915",
    "sg:postcode":"43351",
    "sg:province":"OH",
    "sg:tags":[
        "trust",
        "management"
    ],
    "wof:name":"Bonnie J Menninggen",
    "wof:placetype":"venue"
},
  "geometry": {"coordinates":[-83.2847,40.826046],"type":"Point"}
}