{
  "type": "Feature",
  "properties": {
    "addr:full": "1121 State Rte 131 Milford OH 45150",
    "addr:housenumber": "1121",
    "addr:postcode": "45150",
    "addr:street": "State Rte 131",
    "iso:country": "US",
    "sg:address": "1121 State Rte 131",
    "sg:city": "Milford",
    "sg:classifiers": [
      {
        "category": "Health Services",
        "subcategory": "Doctor",
        "type": "Services"
      }
    ],
    "sg:phone": "+1 513 576 1711",
    "sg:postcode": "45150",
    "sg:province": "OH",
    "sg:tags": [
      "dentist"
    ],
    "wof:name": "Cosmetic Dentistry-Cinncinati",
    "wof:placetype": "venue"
  },
  "geometry": {"coordinates":[-84.236572,39.174981],"type":"Point"}
}
