{
  "type": "Feature",
  "properties": {
    "addr:full": "208 Galewood Dr New Carlisle OH 45344",
    "addr:housenumber": "208",
    "addr:postcode": "45344",
    "addr:street": "Galewood Dr",
    "iso:country": "US",
    "sg:address": "208 Galewood Dr",
    "sg:city": "New Carlisle",
    "sg:classifiers": [
      {
        "category": "Manufacturing",
        "subcategory": "Chemicals \u0026 Compounds",
        "type": "Manufacturing \u0026 Wholesale Goods"
      }
    ],
    "sg:phone": "+1 937 845 1285",
    "sg:postcode": "45344",
    "sg:province": "OH",
    "sg:tags": [
      "product",
      "mfg"
    ],
    "wof:name": "Realms of Magic",
    "wof:placetype": "venue"
  },
  "geometry": {"coordinates":[-84.02605,39.945425],"type":"Point"}
}
