{
  "type": "Feature",
  "properties": {
    "addr:full": "3299 Evans Rd Fredericksburg OH 44627",
    "addr:housenumber": "3299",
    "addr:postcode": "44627",
    "addr:street": "Evans Rd",
    "iso:country": "US",
    "sg:address": "3299 Evans Rd",
    "sg:city": "Fredericksburg",
    "sg:classifiers": [
      {
        "category": "Real Estate",
        "subcategory": "Real Estate Operator",
        "type": "Services"
      }
    ],
    "sg:phone": "+1 330 695 3032",
    "sg:postcode": "44627",
    "sg:province": "OH",
    "sg:tags": [
      "building",
      "apartment"
    ],
    "wof:name": "Larry Lastohkein Apts",
    "wof:placetype": "venue"
  },
  "geometry": {"coordinates":[-81.902217,40.696201],"type":"Point"}
}
