{
  "type": "Feature",
  "properties": {
    "addr:full":"1029 Harrisburg Pike Columbus OH 43223",
    "addr:housenumber":"1029",
    "addr:postcode":"43223",
    "addr:street":"Harrisburg Pike",
    "iso:country":"US",
    "sg:address":"1029 Harrisburg Pike",
    "sg:city":"Columbus",
    "sg:classifiers":[
        {
            "category":"Organizations",
            "subcategory":"Labor Organization",
            "type":"Services"
        }
    ],
    "sg:phone":"+1 614 279 2778",
    "sg:postcode":"43223",
    "sg:province":"OH",
    "sg:website":"www.nalc.org",
    "wof:name":"National Assn-Letter Carriers",
    "wof:placetype":"venue"
},
  "geometry": {"coordinates":[-83.04306800000001,39.936634],"type":"Point"}
}