{
  "type": "Feature",
  "properties": {
    "iso:country":"US",
    "sg:address":"7547 N Ridge Rd",
    "sg:city":"Madison",
    "sg:classifiers":[
        {
            "category":"Professional",
            "subcategory":"Lawyer & Legal Services",
            "type":"Services"
        }
    ],
    "sg:phone":"+1 440 428 1250",
    "sg:postcode":"44057",
    "sg:province":"OH",
    "sg:tags":[
        "attorney"
    ],
    "wof:name":"David W Per Due",
    "wof:placetype":"venue"
},
  "geometry": {"coordinates":[-81.016077,41.798417],"type":"Point"}
}