{
  "type": "Feature",
  "properties": {
    "iso:country":"US",
    "sg:address":"5916 W Sylvania Ave",
    "sg:city":"Toledo",
    "sg:classifiers":[
        {
            "category":"Retail",
            "subcategory":"Auto Repair",
            "type":"Services"
        }
    ],
    "sg:phone":"+1 419 682 4991",
    "sg:postcode":"43623",
    "sg:province":"OH",
    "sg:tags":[
        "automotive"
    ],
    "wof:name":"City Automotive Service",
    "wof:placetype":"venue"
},
  "geometry": {"coordinates":[-83.67366,41.691006],"type":"Point"}
}