{
  "type": "Feature",
  "properties": {
    "iso:country":"US",
    "sg:address":"3307 Kirkham Rd",
    "sg:city":"Columbus",
    "sg:classifiers":[
        {
            "category":"Professional",
            "subcategory":"Lawyer & Legal Services",
            "type":"Services"
        }
    ],
    "sg:phone":"+1 614 442 7937",
    "sg:postcode":"43221",
    "sg:province":"OH",
    "sg:tags":[
        "attorney"
    ],
    "wof:name":"David J Chakeres",
    "wof:placetype":"venue"
},
  "geometry": {"coordinates":[-83.064143,40.025258],"type":"Point"}
}