{
  "type": "Feature",
  "properties": {
    "addr:full": "3491 Latcha Rd Millbury OH 43447",
    "addr:housenumber": "3491",
    "addr:postcode": "43447",
    "addr:street": "Latcha Rd",
    "iso:country": "US",
    "sg:address": "3491 Latcha Rd",
    "sg:city": "Millbury",
    "sg:classifiers": [
      {
        "category": "Shopping",
        "subcategory": "Computers \u0026 Home Electronics",
        "type": "Retail Goods"
      }
    ],
    "sg:phone": "+1 419 837 2800",
    "sg:postcode": "43447",
    "sg:province": "OH",
    "sg:tags": [
      "band",
      "radio"
    ],
    "wof:name": "Phoenix Cb Shop",
    "wof:placetype": "venue"
  },
  "geometry": {"coordinates":[-83.466039,41.544025],"type":"Point"}
}
