{
  "type": "Feature",
  "properties": {
    "addr:full": "212 S Main St Ada OH 45810",
    "addr:housenumber": "212",
    "addr:postcode": "45810",
    "addr:street": "S Main St",
    "iso:country": "US",
    "sg:address": "212 S Main St",
    "sg:city": "Ada",
    "sg:classifiers": [
      {
        "category": "Real Estate",
        "subcategory": "Real Estate Agent",
        "type": "Services"
      }
    ],
    "sg:phone": "+1 419 634 2613",
    "sg:postcode": "45810",
    "sg:province": "OH",
    "wof:name": "Kraft",
    "wof:placetype": "venue"
  },
  "geometry": {"coordinates":[-83.823137,40.769307],"type":"Point"}
}
