{
  "type": "Feature",
  "properties": {
    "addr:full": "1530 36th St NW Canton OH 44709",
    "addr:housenumber": "1530",
    "addr:postcode": "44709",
    "addr:street": "36Th St Nw",
    "iso:country": "US",
    "sg:address": "1530 36th St NW",
    "sg:city": "Canton",
    "sg:classifiers": [
      {
        "category": "Building \u0026 Trades",
        "subcategory": "Construction",
        "type": "Services"
      }
    ],
    "sg:phone": "+1 330 492 5916",
    "sg:postcode": "44709",
    "sg:province": "OH",
    "sg:tags": [
      "floor",
      "laying",
      "contractor"
    ],
    "wof:name": "Estep Contracting",
    "wof:placetype": "venue"
  },
  "geometry": {"coordinates":[-81.389815,40.838225],"type":"Point"}
}
