{
  "type": "Feature",
  "properties": {
    "iso:country":"US",
    "sg:address":"16480 Botkins Rd",
    "sg:city":"Botkins",
    "sg:classifiers":[
        {
            "category":"Professional",
            "type":"Services"
        }
    ],
    "sg:phone":"+1 937 693 3605",
    "sg:postcode":"45306",
    "sg:province":"OH",
    "wof:name":"Caleb Thomas",
    "wof:placetype":"venue"
},
  "geometry": {"coordinates":[-84.122232,40.468178],"type":"Point"}
}