{
  "type": "Feature",
  "properties": {
    "iso:country":"US",
    "sg:address":"37739 Capel Rd",
    "sg:city":"Grafton",
    "sg:classifiers":[
        {
            "category":"Building & Trades",
            "subcategory":"Construction",
            "type":"Services"
        }
    ],
    "sg:phone":"+1 440 748 0336",
    "sg:postcode":"44044",
    "sg:province":"OH",
    "sg:tags":[
        "builder",
        "repairer",
        "chimney",
        "contractor"
    ],
    "wof:name":"Mark's Custom Masonry",
    "wof:placetype":"venue"
},
  "geometry": {"coordinates":[-82.054149,41.302447],"type":"Point"}
}