{
  "type": "Feature",
  "properties": {
    "addr:full": "4005 E Broad St Columbus OH 43213",
    "addr:housenumber": "4005",
    "addr:postcode": "43213",
    "addr:street": "E Broad St",
    "iso:country": "US",
    "sg:address": "4005 E Broad St",
    "sg:city": "Columbus",
    "sg:classifiers": [
      {
        "category": "Professional",
        "subcategory": "Accounting \u0026 Tax Preparation",
        "type": "Services"
      }
    ],
    "sg:phone": "+1 614 236 1924",
    "sg:postcode": "43213",
    "sg:province": "OH",
    "sg:tags": [
      "return",
      "filing"
    ],
    "sg:website": "www.hrblock.com",
    "wof:name": "H \u0026 R Block Tax Svc",
    "wof:placetype": "venue"
  },
  "geometry": {"coordinates":[-82.895436,39.973818],"type":"Point"}
}
