{
  "type": "Feature",
  "properties": {
    "iso:country":"US",
    "sg:address":"4005 E Broad St",
    "sg:city":"Columbus",
    "sg:classifiers":[
        {
            "category":"Professional",
            "subcategory":"Accounting & Tax Preparation",
            "type":"Services"
        }
    ],
    "sg:phone":"+1 614 236 1924",
    "sg:postcode":"43213",
    "sg:province":"OH",
    "sg:tags":[
        "return",
        "filing"
    ],
    "sg:website":"www.hrblock.com",
    "wof:name":"H & R Block Tax Svc",
    "wof:placetype":"venue"
},
  "geometry": {"coordinates":[-82.895436,39.973818],"type":"Point"}
}