{
  "type": "Feature",
  "properties": {
    "addr:full": "933 E 146th St Cleveland OH 44110",
    "addr:housenumber": "933",
    "addr:postcode": "44110",
    "addr:street": "E 146Th St",
    "iso:country": "US",
    "sg:address": "933 E 146th St",
    "sg:city": "Cleveland",
    "sg:classifiers": [
      {
        "category": "Personal",
        "subcategory": "Beauty Salon",
        "type": "Services"
      }
    ],
    "sg:phone": "+1 216 761 3775",
    "sg:postcode": "44110",
    "sg:province": "OH",
    "wof:name": "Lady Moe's Hair Salon",
    "wof:placetype": "venue"
  },
  "geometry": {"coordinates":[-81.580396,41.553514],"type":"Point"}
}
