{
  "type": "Feature",
  "properties": {
    "addr:full": "619 30th St NW Canton OH 44709",
    "addr:housenumber": "619",
    "addr:postcode": "44709",
    "addr:street": "30Th St Nw",
    "iso:country": "US",
    "sg:address": "619 30th St NW",
    "sg:city": "Canton",
    "sg:classifiers": [
      {
        "category": "Home \u0026 Garden",
        "subcategory": "Garden Supply",
        "type": "Retail Goods"
      }
    ],
    "sg:phone": "+1 330 492 0204",
    "sg:postcode": "44709",
    "sg:province": "OH",
    "sg:tags": [
      "equipment",
      "lawn",
      "nursery",
      "christmas",
      "center"
    ],
    "wof:name": "Dumont's Seed Co",
    "wof:placetype": "venue"
  },
  "geometry": {"coordinates":[-81.376891,40.831356],"type":"Point"}
}
