{
  "type": "Feature",
  "properties": {
    "addr:full": "12345 Springfield Rd New Springfield OH 44443",
    "addr:housenumber": "12345",
    "addr:postcode": "44443",
    "addr:street": "Springfield Rd",
    "iso:country": "US",
    "sg:address": "12345 Springfield Rd",
    "sg:city": "New Springfield",
    "sg:classifiers": [
      {
        "category": "Building \u0026 Trades",
        "subcategory": "Cleaning \u0026 Sanitation",
        "type": "Services"
      }
    ],
    "sg:phone": "+1 330 782 4356",
    "sg:postcode": "44443",
    "sg:province": "OH",
    "sg:tags": [
      "maintenance"
    ],
    "wof:name": "Ameriblast Inc",
    "wof:placetype": "venue"
  },
  "geometry": {"coordinates":[-80.614786,40.93939],"type":"Point"}
}
