{
  "type": "Feature",
  "properties": {
    "iso:country":"US",
    "sg:address":"12345 Springfield Rd",
    "sg:city":"New Springfield",
    "sg:classifiers":[
        {
            "category":"Building & Trades",
            "subcategory":"Cleaning & Sanitation",
            "type":"Services"
        }
    ],
    "sg:phone":"+1 330 782 4356",
    "sg:postcode":"44443",
    "sg:province":"OH",
    "sg:tags":[
        "maintenance"
    ],
    "wof:name":"Ameriblast Inc",
    "wof:placetype":"venue"
},
  "geometry": {"coordinates":[-80.614786,40.93939],"type":"Point"}
}