{
  "type": "Feature",
  "properties": {
    "addr:full": "3175 N High St Columbus OH 43202",
    "addr:housenumber": "3175",
    "addr:postcode": "43202",
    "addr:street": "N High St",
    "iso:country": "US",
    "sg:address": "3175 N High St",
    "sg:city": "Columbus",
    "sg:classifiers": [
      {
        "category": "Building \u0026 Trades",
        "subcategory": "Cleaning \u0026 Sanitation",
        "type": "Services"
      }
    ],
    "sg:phone": "+1 614 262 1991",
    "sg:postcode": "43202",
    "sg:province": "OH",
    "sg:tags": [
      "window",
      "janitorial"
    ],
    "wof:name": "Williams Buckeye State Win Clg",
    "wof:placetype": "venue"
  },
  "geometry": {"coordinates":[-83.014761,40.027038],"type":"Point"}
}
