{
  "type": "Feature",
  "properties": {
    "iso:country":"US",
    "sg:address":"3175 N High St",
    "sg:city":"Columbus",
    "sg:classifiers":[
        {
            "category":"Building & Trades",
            "subcategory":"Cleaning & Sanitation",
            "type":"Services"
        }
    ],
    "sg:phone":"+1 614 262 1991",
    "sg:postcode":"43202",
    "sg:province":"OH",
    "sg:tags":[
        "window",
        "janitorial"
    ],
    "wof:name":"Williams Buckeye State Win Clg",
    "wof:placetype":"venue"
},
  "geometry": {"coordinates":[-83.01476099999999,40.027038],"type":"Point"}
}