{
  "type": "Feature",
  "properties": {
    "addr:full": "375 Lear Rd Avon Lake OH 44012",
    "addr:housenumber": "375",
    "addr:postcode": "44012",
    "addr:street": "Lear Rd",
    "iso:country": "US",
    "sg:address": "375 Lear Rd",
    "sg:city": "Avon Lake",
    "sg:classifiers": [
      {
        "category": "Restaurant",
        "type": "Food \u0026 Drink"
      }
    ],
    "sg:menulink": "http://www.allmenus.com/oh/avon-lake/134514-subway/menu/",
    "sg:phone": "+1 440 933 9099",
    "sg:postcode": "44012",
    "sg:province": "OH",
    "sg:tags": [
      "american",
      "sandwich"
    ],
    "wof:name": "Subway",
    "wof:placetype": "venue"
  },
  "geometry": {"coordinates":[-81.988488,41.496165],"type":"Point"}
}
