{
  "type": "Feature",
  "properties": {
    "addr:full": "363 E Torrence Rd Columbus OH 43214",
    "addr:housenumber": "363",
    "addr:postcode": "43214",
    "addr:street": "E Torrence Rd",
    "iso:country": "US",
    "sg:address": "363 E Torrence Rd",
    "sg:city": "Columbus",
    "sg:classifiers": [
      {
        "category": "Wholesale",
        "subcategory": "Computers",
        "type": "Manufacturing \u0026 Wholesale Goods"
      }
    ],
    "sg:phone": "+1 614 447 9214",
    "sg:postcode": "43214",
    "sg:province": "OH",
    "wof:name": "Westward Technologies Inc",
    "wof:placetype": "venue"
  },
  "geometry": {"coordinates":[-83.006411,40.036772],"type":"Point"}
}
