{
  "type": "Feature",
  "properties": {
    "iso:country":"US",
    "sg:address":"3990 E Harbor Rd",
    "sg:city":"Port Clinton",
    "sg:classifiers":[
        {
            "category":"Restaurant",
            "type":"Food & Drink"
        }
    ],
    "sg:menulink":"http://www.allmenus.com/oh/portage/213917-taco-bell/menu/",
    "sg:phone":"+1 419 734 6545",
    "sg:postcode":"43452",
    "sg:province":"OH",
    "sg:tags":[
        "mexican"
    ],
    "wof:name":"Taco Bell",
    "wof:placetype":"venue"
},
  "geometry": {"coordinates":[-82.861141,41.523315],"type":"Point"}
}