{
  "type": "Feature",
  "properties": {
    "addr:full":"130 E Wooster St Bowling Green OH 43402",
    "addr:housenumber":"130",
    "addr:postcode":"43402",
    "addr:street":"E Wooster St",
    "iso:country":"US",
    "sg:address":"130 E Wooster St",
    "sg:city":"Bowling Green",
    "sg:classifiers":[
        {
            "category":"Shopping",
            "type":"Retail Goods"
        }
    ],
    "sg:phone":"+1 419 354 4696",
    "sg:postcode":"43402",
    "sg:province":"OH",
    "sg:tags":[
        "merchandise"
    ],
    "wof:name":"Ryomyo Cigarette Shop",
    "wof:placetype":"venue"
},
  "geometry": {"coordinates":[-83.65003299999999,41.374813],"type":"Point"}
}