{
  "type": "Feature",
  "properties": {
    "addr:full": "20500 Saint Clair Ave Cleveland OH 44117",
    "addr:housenumber": "20500",
    "addr:postcode": "44117",
    "addr:street": "Saint Clair Ave",
    "iso:country": "US",
    "sg:address": "20500 Saint Clair Ave",
    "sg:city": "Cleveland",
    "sg:classifiers": [
      {
        "category": "Building \u0026 Trades",
        "subcategory": "Plumbing",
        "type": "Services"
      }
    ],
    "sg:phone": "+1 216 486 2878",
    "sg:postcode": "44117",
    "sg:province": "OH",
    "sg:tags": [
      "plumbing",
      "contractor"
    ],
    "wof:name": "Rooter King Plumbing \u0026 Drain",
    "wof:placetype": "venue"
  },
  "geometry": {"coordinates":[-81.529481,41.584499],"type":"Point"}
}
