{
  "type": "Feature",
  "properties": {
    "iso:country":"US",
    "sg:address":"20500 Saint Clair Ave",
    "sg:city":"Cleveland",
    "sg:classifiers":[
        {
            "category":"Building & Trades",
            "subcategory":"Plumbing",
            "type":"Services"
        }
    ],
    "sg:phone":"+1 216 486 2878",
    "sg:postcode":"44117",
    "sg:province":"OH",
    "sg:tags":[
        "plumbing",
        "contractor"
    ],
    "wof:name":"Rooter King Plumbing & Drain",
    "wof:placetype":"venue"
},
  "geometry": {"coordinates":[-81.529481,41.584499],"type":"Point"}
}