{
  "type": "Feature",
  "properties": {
    "addr:full":"695 High St Minford OH 45653",
    "addr:housenumber":"695",
    "addr:postcode":"45653",
    "addr:street":"High St",
    "iso:country":"US",
    "sg:address":"695 High St",
    "sg:city":"Minford",
    "sg:classifiers":[
        {
            "category":"Organizations",
            "subcategory":"Religious Organization",
            "type":"Services"
        }
    ],
    "sg:phone":"+1 740 820 2194",
    "sg:postcode":"45653",
    "sg:province":"OH",
    "sg:tags":[
        "church"
    ],
    "wof:name":"Nazarene Church",
    "wof:placetype":"venue"
},
  "geometry": {"coordinates":[-82.863494,38.862876],"type":"Point"}
}