{
  "type": "Feature",
  "properties": {
    "iso:country":"US",
    "sg:address":"400 W Market St",
    "sg:city":"Akron",
    "sg:classifiers":[
        {
            "category":"Health Services",
            "subcategory":"Doctor",
            "type":"Services"
        }
    ],
    "sg:phone":"+1 330 996 8400",
    "sg:postcode":"44303",
    "sg:province":"OH",
    "sg:tags":[
        "medical",
        "datum",
        "ins"
    ],
    "wof:name":"Summa Care",
    "wof:placetype":"venue"
},
  "geometry": {"coordinates":[-81.532068,41.091743],"type":"Point"}
}