{
  "type": "Feature",
  "properties": {
    "addr:full":"188 W Hebble Ave Fairborn OH 45324",
    "addr:housenumber":"188",
    "addr:postcode":"45324",
    "addr:street":"W Hebble Ave",
    "iso:country":"US",
    "sg:address":"188 W Hebble Ave",
    "sg:city":"Fairborn",
    "sg:classifiers":[
        {
            "category":"Health Services",
            "subcategory":"Doctor",
            "type":"Services"
        }
    ],
    "sg:phone":"+1 937 879 3579",
    "sg:postcode":"45324",
    "sg:province":"OH",
    "sg:tags":[
        "dentist"
    ],
    "wof:name":"Lowell B Heck DDS Inc",
    "wof:placetype":"venue"
},
  "geometry": {"coordinates":[-84.02455500000001,39.828243],"type":"Point"}
}