{
  "type": "Feature",
  "properties": {
    "addr:full": "2976 Stiegler Rd Medina OH 44256",
    "addr:housenumber": "2976",
    "addr:postcode": "44256",
    "addr:street": "Stiegler Rd",
    "iso:country": "US",
    "sg:address": "2976 Stiegler Rd",
    "sg:city": "Medina",
    "sg:classifiers": [
      {
        "category": "Building \u0026 Trades",
        "subcategory": "Construction",
        "type": "Services"
      }
    ],
    "sg:phone": "+1 330 725 5490",
    "sg:postcode": "44256",
    "sg:province": "OH",
    "sg:tags": [
      "residential"
    ],
    "wof:name": "Mosley Building Corp",
    "wof:placetype": "venue"
  },
  "geometry": {"coordinates":[-81.907198,41.199785],"type":"Point"}
}
