{
  "type": "Feature",
  "properties": {
    "addr:full":"820 E Main St Springfield OH 45503",
    "addr:housenumber":"820",
    "addr:postcode":"45503",
    "addr:street":"E Main St",
    "iso:country":"US",
    "sg:address":"820 E Main St",
    "sg:city":"Springfield",
    "sg:classifiers":[
        {
            "category":"Bars & Pubs",
            "type":"Food & Drink"
        }
    ],
    "sg:phone":"+1 937 323 9833",
    "sg:postcode":"45503",
    "sg:province":"OH",
    "wof:name":"Kinsler's Cafe",
    "wof:placetype":"venue"
},
  "geometry": {"coordinates":[-83.796558,39.923852],"type":"Point"}
}