{
  "type": "Feature",
  "properties": {
    "iso:country":"US",
    "sg:address":"5171 Jisco West Rd",
    "sg:city":"Jackson",
    "sg:classifiers":[
        {
            "category":"Wholesale",
            "subcategory":"Vending Machines",
            "type":"Manufacturing & Wholesale Goods"
        }
    ],
    "sg:phone":"+1 740 286 6048",
    "sg:postcode":"45640",
    "sg:province":"OH",
    "sg:tags":[
        "operator"
    ],
    "wof:name":"SM Vending",
    "wof:placetype":"venue"
},
  "geometry": {"coordinates":[-82.66979,39.043382],"type":"Point"}
}