{
  "type": "Feature",
  "properties": {
    "addr:full": "3581 Lee Rd Cleveland OH 44120",
    "addr:housenumber": "3581",
    "addr:postcode": "44120",
    "addr:street": "Lee Rd",
    "iso:country": "US",
    "sg:address": "3581 Lee Rd",
    "sg:city": "Cleveland",
    "sg:classifiers": [
      {
        "category": "Banks \u0026 Credit Unions",
        "subcategory": "Bank",
        "type": "Services"
      }
    ],
    "sg:phone": "+1 216 752 6111",
    "sg:postcode": "44120",
    "sg:province": "OH",
    "sg:tags": [
      "state"
    ],
    "wof:name": "Shacker Height Teachers Cr Un",
    "wof:placetype": "venue"
  },
  "geometry": {"coordinates":[-81.564856,41.461943],"type":"Point"}
}
