{
  "type": "Feature",
  "properties": {
    "addr:full":"6187 Lisbon Rd Lisbon OH 44432",
    "addr:housenumber":"6187",
    "addr:postcode":"44432",
    "addr:street":"Lisbon Rd",
    "iso:country":"US",
    "sg:address":"6187 Lisbon Rd",
    "sg:city":"Lisbon",
    "sg:classifiers":[
        {
            "category":"Building & Trades",
            "subcategory":"Construction",
            "type":"Services"
        }
    ],
    "sg:phone":"+1 330 424 3334",
    "sg:postcode":"44432",
    "sg:province":"OH",
    "sg:tags":[
        "contractor"
    ],
    "wof:name":"Matthew R Weaver",
    "wof:placetype":"venue"
},
  "geometry": {"coordinates":[-80.783546,40.808482],"type":"Point"}
}