{
  "type": "Feature",
  "properties": {
    "addr:full": "105 Public Sq Somerset OH 43783",
    "addr:housenumber": "105",
    "addr:postcode": "43783",
    "addr:street": "Public Sq",
    "iso:country": "US",
    "sg:address": "105 Public Sq",
    "sg:city": "Somerset",
    "sg:classifiers": [
      {
        "category": "Banks \u0026 Credit Unions",
        "subcategory": "Bank",
        "type": "Services"
      }
    ],
    "sg:phone": "+1 740 743 1313",
    "sg:postcode": "43783",
    "sg:province": "OH",
    "wof:name": "US Bank",
    "wof:placetype": "venue"
  },
  "geometry": {"coordinates":[-82.299203,39.807165],"type":"Point"}
}
