{
  "type": "Feature",
  "properties": {
    "iso:country":"US",
    "sg:address":"105 Public Sq",
    "sg:city":"Somerset",
    "sg:classifiers":[
        {
            "category":"Banks & Credit Unions",
            "subcategory":"Bank",
            "type":"Services"
        }
    ],
    "sg:phone":"+1 740 743 1313",
    "sg:postcode":"43783",
    "sg:province":"OH",
    "wof:name":"US Bank",
    "wof:placetype":"venue"
},
  "geometry": {"coordinates":[-82.29920300000001,39.807165],"type":"Point"}
}