{
  "type": "Feature",
  "properties": {
    "addr:full":"567 W Shore Blvd Sheffield Lake OH 44054",
    "addr:housenumber":"567",
    "addr:postcode":"44054",
    "addr:street":"W Shore Blvd",
    "iso:country":"US",
    "sg:address":"567 W Shore Blvd",
    "sg:city":"Sheffield Lake",
    "sg:classifiers":[
        {
            "category":"Professional",
            "type":"Services"
        }
    ],
    "sg:phone":"+1 440 949 2532",
    "sg:postcode":"44054",
    "sg:province":"OH",
    "wof:name":"Daughters of Isis of Nort",
    "wof:placetype":"venue"
},
  "geometry": {"coordinates":[-82.09733,41.491585],"type":"Point"}
}