{
  "type": "Feature",
  "properties": {
    "addr:full": "928 E 222nd St Cleveland OH 44123",
    "addr:housenumber": "928",
    "addr:postcode": "44123",
    "addr:street": "E 222Nd St",
    "iso:country": "US",
    "sg:address": "928 E 222nd St",
    "sg:city": "Cleveland",
    "sg:classifiers": [
      {
        "category": "Shopping",
        "subcategory": "Clothing, Apparel, \u0026 Fashions",
        "type": "Retail Goods"
      }
    ],
    "sg:phone": "+1 216 797 4688",
    "sg:postcode": "44123",
    "sg:province": "OH",
    "sg:tags": [
      "lingerie"
    ],
    "wof:name": "Sensual Images",
    "wof:placetype": "venue"
  },
  "geometry": {"coordinates":[-81.526836,41.59026],"type":"Point"}
}
