{
  "type": "Feature",
  "properties": {
    "addr:full":"11856 State Rte 41 West Union OH 45693",
    "addr:housenumber":"11856",
    "addr:postcode":"45693",
    "addr:street":"State Rte 41 West",
    "iso:country":"US",
    "sg:address":"11856 State Rte 41",
    "sg:city":"West Union",
    "sg:classifiers":[
        {
            "category":"Home & Garden",
            "subcategory":"Building Materials",
            "type":"Retail Goods"
        }
    ],
    "sg:phone":"+1 937 544 3987",
    "sg:postcode":"45693",
    "sg:province":"OH",
    "sg:website":"www.carterlumber.com",
    "wof:name":"Carter Lumber",
    "wof:placetype":"venue"
},
  "geometry": {"coordinates":[-83.55112,38.792444],"type":"Point"}
}