{
  "type": "Feature",
  "properties": {
    "addr:full": "101 N Market St St Clairsville OH 43950",
    "addr:housenumber": "101",
    "addr:postcode": "43950",
    "addr:street": "N Market St",
    "iso:country": "US",
    "sg:address": "101 N Market St",
    "sg:city": "St Clairsville",
    "sg:classifiers": [
      {
        "category": "Education",
        "subcategory": "Special Training",
        "type": "Public Place"
      }
    ],
    "sg:phone": "+1 740 695 1171",
    "sg:postcode": "43950",
    "sg:province": "OH",
    "sg:tags": [
      "center"
    ],
    "wof:name": "Ohio State University Ext Belm",
    "wof:placetype": "venue"
  },
  "geometry": {"coordinates":[-80.901563,40.082643],"type":"Point"}
}
