{
  "type": "Feature",
  "properties": {
    "addr:full": "5523 du Bonnet Dr Fairfield OH 45014",
    "addr:housenumber": "5523",
    "addr:postcode": "45014",
    "addr:street": "Du Bonnet Dr",
    "iso:country": "US",
    "sg:address": "5523 du Bonnet Dr",
    "sg:city": "Fairfield",
    "sg:classifiers": [
      {
        "category": "Building \u0026 Trades",
        "subcategory": "Construction",
        "type": "Services"
      }
    ],
    "sg:phone": "+1 513 939 2080",
    "sg:postcode": "45014",
    "sg:province": "OH",
    "sg:tags": [
      "roofing",
      "contractor"
    ],
    "wof:name": "America's Roofing Co",
    "wof:placetype": "venue"
  },
  "geometry": {"coordinates":[-84.584303,39.327861],"type":"Point"}
}
