{
  "type": "Feature",
  "properties": {
    "iso:country":"US",
    "sg:address":"233 W Madison St",
    "sg:city":"Gibsonburg",
    "sg:classifiers":[
        {
            "category":"Freight",
            "type":"Transportation"
        }
    ],
    "sg:phone":"+1 419 637 2204",
    "sg:postcode":"43431",
    "sg:province":"OH",
    "sg:tags":[
        "grain",
        "elevator"
    ],
    "wof:name":"Countyline Co-Op Inc",
    "wof:placetype":"venue"
},
  "geometry": {"coordinates":[-83.32277000000001,41.384459],"type":"Point"}
}