{
  "type": "Feature",
  "properties": {
    "iso:country":"US",
    "sg:address":"5364 Pearl Rd",
    "sg:city":"Cleveland",
    "sg:classifiers":[
        {
            "category":"Shopping",
            "subcategory":"Florist",
            "type":"Retail Goods"
        }
    ],
    "sg:phone":"+1 440 888 1771",
    "sg:postcode":"44129",
    "sg:province":"OH",
    "wof:name":"Kay's Floral Shoppe LTD",
    "wof:placetype":"venue"
},
  "geometry": {"coordinates":[-81.732426,41.415094],"type":"Point"}
}