{
  "type": "Feature",
  "properties": {
    "iso:country":"US",
    "sg:address":"5984 Macewen Ct",
    "sg:city":"Dublin",
    "sg:classifiers":[
        {
            "category":"Professional",
            "subcategory":"Business Services",
            "type":"Services"
        }
    ],
    "sg:phone":"+1 614 798 9857",
    "sg:postcode":"43017",
    "sg:province":"OH",
    "sg:tags":[
        "event"
    ],
    "wof:name":"Destinations By Design",
    "wof:placetype":"venue"
},
  "geometry": {"coordinates":[-83.150032,40.145766],"type":"Point"}
}