{
  "type": "Feature",
  "properties": {
    "iso:country":"US",
    "sg:address":"9231 Chillicothe Rd",
    "sg:city":"Willoughby",
    "sg:classifiers":[
        {
            "category":"Banks & Credit Unions",
            "subcategory":"Bank",
            "type":"Services"
        }
    ],
    "sg:phone":"+1 440 256 1458",
    "sg:postcode":"44094",
    "sg:province":"OH",
    "wof:name":"Charter One Bank",
    "wof:placetype":"venue"
},
  "geometry": {"coordinates":[-81.356764,41.616928],"type":"Point"}
}