{
  "type": "Feature",
  "properties": {
    "addr:full":"4407 Roosevelt Blvd Middletown OH 45044",
    "addr:housenumber":"4407",
    "addr:postcode":"45044",
    "addr:street":"Roosevelt Blvd",
    "iso:country":"US",
    "sg:address":"4407 Roosevelt Blvd",
    "sg:city":"Middletown",
    "sg:classifiers":[
        {
            "category":"Building & Trades",
            "subcategory":"Plumbing",
            "type":"Services"
        }
    ],
    "sg:phone":"+1 513 423 2986",
    "sg:postcode":"45044",
    "sg:province":"OH",
    "sg:tags":[
        "cooling",
        "heating",
        "contractor"
    ],
    "wof:name":"General Heating & Cooling",
    "wof:placetype":"venue"
},
  "geometry": {"coordinates":[-84.35099599999999,39.499365],"type":"Point"}
}