{
  "type": "Feature",
  "properties": {
    "addr:full": "340 Gargrave Rd Dayton OH 45449",
    "addr:housenumber": "340",
    "addr:postcode": "45449",
    "addr:street": "Gargrave Rd",
    "iso:country": "US",
    "sg:address": "340 Gargrave Rd",
    "sg:city": "Dayton",
    "sg:classifiers": [
      {
        "category": "Wholesale",
        "subcategory": "Machinery \u0026 Supplies",
        "type": "Manufacturing \u0026 Wholesale Goods"
      },
      {
        "category": "Manufacturing",
        "subcategory": "Chemicals \u0026 Compounds",
        "type": "Manufacturing \u0026 Wholesale Goods"
      }
    ],
    "sg:phone": "+1 937 866 7805",
    "sg:postcode": "45449",
    "sg:province": "OH",
    "sg:tags": [
      "industrial",
      "lithographing",
      "ink"
    ],
    "wof:name": "American Water Graphics",
    "wof:placetype": "venue"
  },
  "geometry": {"coordinates":[-84.237723,39.652722],"type":"Point"}
}
