{
  "type": "Feature",
  "properties": {
    "iso:country":"US",
    "sg:address":"2141 E 3rd St",
    "sg:city":"Dayton",
    "sg:classifiers":[
        {
            "category":"Building & Trades",
            "subcategory":"Plumbing",
            "type":"Services"
        }
    ],
    "sg:phone":"+1 937 252 9945",
    "sg:postcode":"45403",
    "sg:province":"OH",
    "sg:tags":[
        "sheet",
        "metal",
        "heating",
        "air",
        "warm",
        "conditioning"
    ],
    "wof:name":"Detmer & Sons Heating & AC",
    "wof:placetype":"venue"
},
  "geometry": {"coordinates":[-84.16586100000001,39.763756],"type":"Point"}
}