{
  "type": "Feature",
  "properties": {
    "addr:full": "2141 E 3rd St Dayton OH 45403",
    "addr:housenumber": "2141",
    "addr:postcode": "45403",
    "addr:street": "E 3Rd St",
    "iso:country": "US",
    "sg:address": "2141 E 3rd St",
    "sg:city": "Dayton",
    "sg:classifiers": [
      {
        "category": "Building \u0026 Trades",
        "subcategory": "Plumbing",
        "type": "Services"
      }
    ],
    "sg:phone": "+1 937 252 9945",
    "sg:postcode": "45403",
    "sg:province": "OH",
    "sg:tags": [
      "sheet",
      "metal",
      "heating",
      "air",
      "warm",
      "conditioning"
    ],
    "wof:name": "Detmer \u0026 Sons Heating \u0026 AC",
    "wof:placetype": "venue"
  },
  "geometry": {"coordinates":[-84.165861,39.763756],"type":"Point"}
}
