{
  "type": "Feature",
  "properties": {
    "addr:full":"2222 Rockefeller Rd Wickliffe OH 44092",
    "addr:housenumber":"2222",
    "addr:postcode":"44092",
    "addr:street":"Rockefeller Rd",
    "iso:country":"US",
    "sg:address":"2222 Rockefeller Rd",
    "sg:city":"Wickliffe",
    "sg:classifiers":[
        {
            "category":"Building & Trades",
            "subcategory":"Landscaping Services",
            "type":"Services"
        }
    ],
    "sg:phone":"+1 440 944 1735",
    "sg:postcode":"44092",
    "sg:province":"OH",
    "sg:tags":[
        "tree"
    ],
    "wof:name":"Acorn Tree Svc Inc",
    "wof:placetype":"venue"
},
  "geometry": {"coordinates":[-81.46503800000001,41.599727],"type":"Point"}
}