{
  "type": "Feature",
  "properties": {
    "iso:country":"US",
    "sg:address":"5725 Baughman Rd",
    "sg:city":"Zanesville",
    "sg:phone":"+1 740 452 2835",
    "sg:postcode":"43701",
    "sg:province":"OH",
    "sg:tags":[
        "farm",
        "corn",
        "soybean"
    ],
    "wof:name":"Tunis Farms",
    "wof:placetype":"venue"
},
  "geometry": {"coordinates":[-82.070701,40.027396],"type":"Point"}
}