{
  "type": "Feature",
  "properties": {
    "addr:full": "4560 Journal St Columbus OH 43228",
    "addr:postcode": "4560;43228",
    "addr:street": "Journal St",
    "iso:country": "US",
    "sg:address": "4560 Journal St",
    "sg:city": "Columbus",
    "sg:classifiers": [
      {
        "category": "Freight",
        "type": "Transportation"
      }
    ],
    "sg:phone": "+1 614 876 4006",
    "sg:postcode": "43228",
    "sg:province": "OH",
    "sg:tags": [
      "trucking"
    ],
    "wof:name": "Tri-State Express Inc",
    "wof:placetype": "venue"
  },
  "geometry": {"coordinates":[-83.133788,40.015359],"type":"Point"}
}
