{
  "type": "Feature",
  "properties": {
    "addr:full": "42774 Helwig Ridge Rd Shade OH 45776",
    "addr:postcode": "42774;45776",
    "addr:street": "Helwig Ridge Rd",
    "iso:country": "US",
    "sg:address": "42774 Helwig Ridge Rd",
    "sg:city": "Shade",
    "sg:classifiers": [
      {
        "category": "Government",
        "subcategory": "Office",
        "type": "Public Place"
      }
    ],
    "sg:phone": "+1 740 696 1244",
    "sg:postcode": "45776",
    "sg:province": "OH",
    "sg:tags": [
      "executive"
    ],
    "wof:name": "Bedford Township",
    "wof:placetype": "venue"
  },
  "geometry": {"coordinates":[-82.042094,39.177601],"type":"Point"}
}
