{
  "type": "Feature",
  "properties": {
    "iso:country":"US",
    "sg:address":"19 South St",
    "sg:city":"Cedarville",
    "sg:classifiers":[
        {
            "category":"Government",
            "subcategory":"Fire Station",
            "type":"Public Place"
        }
    ],
    "sg:phone":"+1 937 766 5851",
    "sg:postcode":"45314",
    "sg:province":"OH",
    "sg:tags":[
        "department"
    ],
    "wof:name":"Cedarville Fire Dept",
    "wof:placetype":"venue"
},
  "geometry": {"coordinates":[-83.805347,39.74375],"type":"Point"}
}