{
  "type": "Feature",
  "properties": {
    "addr:full": "9518 Cassius Ave Cleveland OH 44105",
    "addr:postcode": "9518;44105",
    "addr:street": "Cassius Ave",
    "iso:country": "US",
    "sg:address": "9518 Cassius Ave",
    "sg:city": "Cleveland",
    "sg:classifiers": [
      {
        "category": "Wholesale",
        "subcategory": "Machinery \u0026 Supplies",
        "type": "Manufacturing \u0026 Wholesale Goods"
      }
    ],
    "sg:phone": "+1 216 641 1101",
    "sg:postcode": "44105",
    "sg:province": "OH",
    "sg:tags": [
      "bearing"
    ],
    "wof:name": "Green Bearing",
    "wof:placetype": "venue"
  },
  "geometry": {"coordinates":[-81.618982,41.449518],"type":"Point"}
}
