{
  "type": "Feature",
  "properties": {
    "addr:full": "206 7th St SW New Philadelphia OH 44663",
    "addr:housenumber": "206",
    "addr:postcode": "44663",
    "addr:street": "7Th St Sw",
    "iso:country": "US",
    "sg:address": "206 7th St SW",
    "sg:city": "New Philadelphia",
    "sg:classifiers": [
      {
        "category": "Shopping",
        "subcategory": "Bicycles \u0026 Sporting Goods",
        "type": "Retail Goods"
      }
    ],
    "sg:phone": "+1 330 339 1134",
    "sg:postcode": "44663",
    "sg:province": "OH",
    "sg:tags": [
      "repair",
      "gun",
      "gunsmith"
    ],
    "wof:name": "P J's Arms \u0026 Archery",
    "wof:placetype": "venue"
  },
  "geometry": {"coordinates":[-81.459236,40.490036],"type":"Point"}
}
