{
  "type": "Feature",
  "properties": {
    "iso:country":"US",
    "sg:address":"206 7th St SW",
    "sg:city":"New Philadelphia",
    "sg:classifiers":[
        {
            "category":"Shopping",
            "subcategory":"Bicycles & Sporting Goods",
            "type":"Retail Goods"
        }
    ],
    "sg:phone":"+1 330 339 1134",
    "sg:postcode":"44663",
    "sg:province":"OH",
    "sg:tags":[
        "repair",
        "gun",
        "gunsmith"
    ],
    "wof:name":"P J's Arms & Archery",
    "wof:placetype":"venue"
},
  "geometry": {"coordinates":[-81.459236,40.490036],"type":"Point"}
}