{
  "type": "Feature",
  "properties": {
    "addr:full":"718 Shetland Cir Berea OH 44017",
    "addr:housenumber":"718",
    "addr:postcode":"44017",
    "addr:street":"Shetland Cir",
    "iso:country":"US",
    "sg:address":"718 Shetland Cir",
    "sg:city":"Berea",
    "sg:classifiers":[
        {
            "category":"Building & Trades",
            "subcategory":"Construction",
            "type":"Services"
        }
    ],
    "sg:phone":"+1 440 243 1634",
    "sg:postcode":"44017",
    "sg:province":"OH",
    "sg:tags":[
        "house"
    ],
    "wof:name":"Jaguar Construction Co",
    "wof:placetype":"venue"
},
  "geometry": {"coordinates":[-81.87464300000001,41.352899],"type":"Point"}
}