{
  "type": "Feature",
  "properties": {
    "addr:full":"11909 Buckeye Rd Cleveland OH 44120",
    "addr:housenumber":"11909",
    "addr:postcode":"44120",
    "addr:street":"Buckeye Rd",
    "iso:country":"US",
    "sg:address":"11909 Buckeye Rd",
    "sg:city":"Cleveland",
    "sg:classifiers":[
        {
            "category":"Organizations",
            "subcategory":"Religious Organization",
            "type":"Services"
        }
    ],
    "sg:phone":"+1 216 751 4326",
    "sg:postcode":"44120",
    "sg:province":"OH",
    "sg:tags":[
        "church"
    ],
    "wof:name":"Grace Fellowship Assembly Chr",
    "wof:placetype":"venue"
},
  "geometry": {"coordinates":[-81.59939199999999,41.480701],"type":"Point"}
}