{
  "type": "Feature",
  "properties": {
    "iso:country":"US",
    "sg:address":"8103 Marlborough Ave",
    "sg:city":"Cleveland",
    "sg:classifiers":[
        {
            "category":"Real Estate",
            "subcategory":"Real Estate Agent",
            "type":"Services"
        }
    ],
    "sg:phone":"+1 440 842 9907",
    "sg:postcode":"44129",
    "sg:province":"OH",
    "wof:name":"State Certified Appraisal Serv",
    "wof:placetype":"venue"
},
  "geometry": {"coordinates":[-81.741817,41.414868],"type":"Point"}
}