{
  "type": "Feature",
  "properties": {
    "addr:full": "7504 Gracely Dr Cincinnati OH 45233",
    "addr:housenumber": "7504",
    "addr:postcode": "45233",
    "addr:street": "Gracely Dr",
    "iso:country": "US",
    "sg:address": "7504 Gracely Dr",
    "sg:city": "Cincinnati",
    "sg:classifiers": [
      {
        "category": "Retail",
        "subcategory": "Self-service Laundry",
        "type": "Services"
      }
    ],
    "sg:phone": "+1 513 922 9928",
    "sg:postcode": "45233",
    "sg:province": "OH",
    "wof:name": "Delhi Highlander Ctr",
    "wof:placetype": "venue"
  },
  "geometry": {"coordinates":[-84.70699,39.132157],"type":"Point"}
}
