{
  "type": "Feature",
  "properties": {
    "addr:full":"4690 N Sulphur Springs Rd Brookville OH 45309",
    "addr:housenumber":"4690",
    "addr:postcode":"45309",
    "addr:street":"N Sulphur Springs Rd",
    "iso:country":"US",
    "sg:address":"4690 N Sulphur Springs Rd",
    "sg:city":"Brookville",
    "sg:classifiers":[
        {
            "category":"Organizations",
            "subcategory":"Religious Organization",
            "type":"Services"
        }
    ],
    "sg:phone":"+1 937 833 2778",
    "sg:postcode":"45309",
    "sg:province":"OH",
    "sg:tags":[
        "church"
    ],
    "wof:name":"Pyrmont United Methodist",
    "wof:placetype":"venue"
},
  "geometry": {"coordinates":[-84.46122200000001,39.814125],"type":"Point"}
}