{
  "type": "Feature",
  "properties": {
    "iso:country":"US",
    "sg:address":"958 Shaw Ct",
    "sg:city":"Newark",
    "sg:classifiers":[
        {
            "category":"Professional",
            "type":"Services"
        }
    ],
    "sg:phone":"+1 740 344 5734",
    "sg:postcode":"43055",
    "sg:province":"OH",
    "wof:name":"Carmen Paul",
    "wof:placetype":"venue"
},
  "geometry": {"coordinates":[-82.436105,40.061183],"type":"Point"}
}