{
  "type": "Feature",
  "properties": {
    "addr:full": "1415 Barcelona Dr Akron OH 44313",
    "addr:housenumber": "1415",
    "addr:postcode": "44313",
    "addr:street": "Barcelona Dr",
    "iso:country": "US",
    "sg:address": "1415 Barcelona Dr",
    "sg:city": "Akron",
    "sg:classifiers": [
      {
        "category": "Shopping",
        "subcategory": "Books",
        "type": "Retail Goods"
      }
    ],
    "sg:phone": "+1 330 835 3748",
    "sg:postcode": "44313",
    "sg:province": "OH",
    "wof:name": "Dragon Magic",
    "wof:placetype": "venue"
  },
  "geometry": {"coordinates":[-81.557587,41.134893],"type":"Point"}
}
