{
  "type": "Feature",
  "properties": {
    "addr:full":"11 Bowers Ave Newark OH 43055",
    "addr:housenumber":"11",
    "addr:postcode":"43055",
    "addr:street":"Bowers Ave",
    "iso:country":"US",
    "sg:address":"11 Bowers Ave",
    "sg:city":"Newark",
    "sg:classifiers":[
        {
            "category":"Shopping",
            "subcategory":"Music",
            "type":"Retail Goods"
        }
    ],
    "sg:phone":"+1 740 344 2400",
    "sg:postcode":"43055",
    "sg:province":"OH",
    "sg:tags":[
        "video",
        "disc",
        "tape",
        "cassette"
    ],
    "wof:name":"Legend Valley Video",
    "wof:placetype":"venue"
},
  "geometry": {"coordinates":[-82.42297499999999,40.054061],"type":"Point"}
}