{
  "type": "Feature",
  "properties": {
    "addr:full":"1597 Youngstown Kingsville Rd Vienna OH 44473",
    "addr:housenumber":"1597",
    "addr:postcode":"44473",
    "addr:street":"Youngstown Kingsville Rd",
    "iso:country":"US",
    "sg:address":"1597 Youngstown Kingsville Rd",
    "sg:city":"Vienna",
    "sg:classifiers":[
        {
            "category":"Education",
            "subcategory":"Special Training",
            "type":"Public Place"
        }
    ],
    "sg:phone":"+1 330 856 3949",
    "sg:postcode":"44473",
    "sg:province":"OH",
    "sg:tags":[
        "aircraft",
        "school"
    ],
    "sg:website":"www.alphaairltd.com",
    "wof:name":"A M Air Flight Ctr LTD",
    "wof:placetype":"venue"
},
  "geometry": {"coordinates":[-80.66384100000001,41.265515],"type":"Point"}
}