{
  "type": "Feature",
  "properties": {
    "addr:full": "708 S Cleveland Massillon Rd Fairlawn OH 44333",
    "addr:housenumber": "708",
    "addr:postcode": "44333",
    "addr:street": "S Cleveland Massillon Rd",
    "iso:country": "US",
    "sg:address": "708 S Cleveland Massillon Rd",
    "sg:city": "Fairlawn",
    "sg:classifiers": [
      {
        "category": "Building \u0026 Trades",
        "subcategory": "Landscaping Services",
        "type": "Services"
      }
    ],
    "sg:phone": "+1 330 666 1241",
    "sg:postcode": "44333",
    "sg:province": "OH",
    "sg:tags": [
      "landscape",
      "contractor"
    ],
    "wof:name": "New Creation Landscaping",
    "wof:placetype": "venue"
  },
  "geometry": {"coordinates":[-81.642813,41.113506],"type":"Point"}
}
