{
  "type": "Feature",
  "properties": {
    "addr:full":"2194 Romig Rd Akron OH 44320",
    "addr:housenumber":"2194",
    "addr:postcode":"44320",
    "addr:street":"Romig Rd",
    "iso:country":"US",
    "sg:address":"2194 Romig Rd",
    "sg:city":"Akron",
    "sg:classifiers":[
        {
            "category":"Shopping",
            "subcategory":"Clothing, Apparel, & Fashions",
            "type":"Retail Goods"
        }
    ],
    "sg:phone":"+1 330 745 5007",
    "sg:postcode":"44320",
    "sg:province":"OH",
    "wof:name":"Catherines",
    "wof:placetype":"venue"
},
  "geometry": {"coordinates":[-81.581236,41.05715],"type":"Point"}
}