{
  "type": "Feature",
  "properties": {
    "iso:country":"US",
    "sg:address":"771 Western College Dr",
    "sg:city":"Oxford",
    "sg:classifiers":[
        {
            "category":"Building & Trades",
            "subcategory":"Construction",
            "type":"Services"
        }
    ],
    "sg:phone":"+1 513 523 0247",
    "sg:postcode":"45056",
    "sg:province":"OH",
    "sg:tags":[
        "house"
    ],
    "wof:name":"Dag Construction Co",
    "wof:placetype":"venue"
},
  "geometry": {"coordinates":[-84.728603,39.501338],"type":"Point"}
}