{
  "type": "Feature",
  "properties": {
    "addr:full": "3928 Avon Lake Rd Litchfield OH 44253",
    "addr:housenumber": "3928",
    "addr:postcode": "44253",
    "addr:street": "Avon Lake Rd",
    "iso:country": "US",
    "sg:address": "3928 Avon Lake Rd",
    "sg:city": "Litchfield",
    "sg:classifiers": [
      {
        "category": "Organizations",
        "subcategory": "Religious Organization",
        "type": "Services"
      }
    ],
    "sg:phone": "+1 330 723 5835",
    "sg:postcode": "44253",
    "sg:province": "OH",
    "sg:tags": [
      "church"
    ],
    "wof:name": "Litchfield United Chr-Christ",
    "wof:placetype": "venue"
  },
  "geometry": {"coordinates":[-82.023115,41.16627],"type":"Point"}
}
