{
  "type": "Feature",
  "properties": {
    "addr:full": "2808 Ramblingwood Ln Dayton OH 45458",
    "addr:housenumber": "2808",
    "addr:postcode": "45458",
    "addr:street": "Ramblingwood Ln",
    "iso:country": "US",
    "sg:address": "2808 Ramblingwood Ln",
    "sg:city": "Dayton",
    "sg:classifiers": [
      {
        "category": "Shopping",
        "subcategory": "Discount \u0026 Variety Stores",
        "type": "Retail Goods"
      }
    ],
    "sg:phone": "+1 937 885 5200",
    "sg:postcode": "45458",
    "sg:province": "OH",
    "sg:tags": [
      "gift",
      "merchandise"
    ],
    "wof:name": "Anythings Possible Cstm Bskts",
    "wof:placetype": "venue"
  },
  "geometry": {"coordinates":[-84.11892,39.601796],"type":"Point"}
}
