{
  "type": "Feature",
  "properties": {
    "addr:full":"6974 Zenith Ct Hamilton OH 45011",
    "addr:housenumber":"6974",
    "addr:postcode":"45011",
    "addr:street":"Zenith Ct",
    "iso:country":"US",
    "sg:address":"6974 Zenith Ct",
    "sg:city":"Hamilton",
    "sg:classifiers":[
        {
            "category":"Manufacturing",
            "subcategory":"Metals",
            "type":"Manufacturing & Wholesale Goods"
        }
    ],
    "sg:phone":"+1 513 737 9911",
    "sg:postcode":"45011",
    "sg:province":"OH",
    "sg:tags":[
        "steel",
        "product",
        "consulting",
        "business",
        "mfg"
    ],
    "wof:name":"D M L Steel Tech",
    "wof:placetype":"venue"
},
  "geometry": {"coordinates":[-84.462614,39.379627],"type":"Point"}
}