{
  "type": "Feature",
  "properties": {
    "iso:country":"US",
    "sg:address":"1316 E High St",
    "sg:city":"Springfield",
    "sg:classifiers":[
        {
            "category":"Organizations",
            "subcategory":"Non-profit Organization",
            "type":"Services"
        }
    ],
    "sg:phone":"+1 937 328 5308",
    "sg:postcode":"45505",
    "sg:province":"OH",
    "wof:name":"Project Woman",
    "wof:placetype":"venue"
},
  "geometry": {"coordinates":[-83.789362,39.921092],"type":"Point"}
}