{
  "type": "Feature",
  "properties": {
    "addr:full": "36774 Detroit Rd Avon OH 44011",
    "addr:housenumber": "36774",
    "addr:postcode": "44011",
    "addr:street": "Detroit Rd",
    "iso:country": "US",
    "sg:address": "36774 Detroit Rd",
    "sg:city": "Avon",
    "sg:classifiers": [
      {
        "category": "Building \u0026 Trades",
        "subcategory": "Construction",
        "type": "Services"
      }
    ],
    "sg:phone": "+1 440 934 1088",
    "sg:postcode": "44011",
    "sg:province": "OH",
    "sg:tags": [
      "house"
    ],
    "wof:name": "Martini Construction",
    "wof:placetype": "venue"
  },
  "geometry": {"coordinates":[-82.032001,41.454233],"type":"Point"}
}
