{
  "type": "Feature",
  "properties": {
    "iso:country":"US",
    "sg:address":"4073 Tollgate Rd",
    "sg:city":"Batavia",
    "sg:classifiers":[
        {
            "category":"Health Services",
            "subcategory":"Clinic",
            "type":"Services"
        }
    ],
    "sg:phone":"+1 513 724 3841",
    "sg:postcode":"45103",
    "sg:province":"OH",
    "sg:tags":[
        "home",
        "care"
    ],
    "wof:name":"Residential Concepts Inc",
    "wof:placetype":"venue"
},
  "geometry": {"coordinates":[-84.07037800000001,39.05517],"type":"Point"}
}