{
  "type": "Feature",
  "properties": {
    "addr:full": "4073 Tollgate Rd Batavia OH 45103",
    "addr:housenumber": "4073",
    "addr:postcode": "45103",
    "addr:street": "Tollgate Rd",
    "iso:country": "US",
    "sg:address": "4073 Tollgate Rd",
    "sg:city": "Batavia",
    "sg:classifiers": [
      {
        "category": "Health Services",
        "subcategory": "Clinic",
        "type": "Services"
      }
    ],
    "sg:phone": "+1 513 724 3841",
    "sg:postcode": "45103",
    "sg:province": "OH",
    "sg:tags": [
      "home",
      "care"
    ],
    "wof:name": "Residential Concepts Inc",
    "wof:placetype": "venue"
  },
  "geometry": {"coordinates":[-84.070378,39.05517],"type":"Point"}
}
