{
  "type": "Feature",
  "properties": {
    "addr:full":"1960 Case Pkwy S Twinsburg OH 44087",
    "addr:housenumber":"1960",
    "addr:postcode":"44087",
    "addr:street":"Case Pkwy S",
    "iso:country":"US",
    "sg:address":"1960 Case Pkwy S",
    "sg:city":"Twinsburg",
    "sg:classifiers":[
        {
            "category":"Wholesale",
            "subcategory":"Machinery & Supplies",
            "type":"Manufacturing & Wholesale Goods"
        }
    ],
    "sg:phone":"+1 330 425 1210",
    "sg:postcode":"44087",
    "sg:province":"OH",
    "sg:tags":[
        "industrial",
        "component"
    ],
    "wof:name":"Keystone Components Inc",
    "wof:placetype":"venue"
},
  "geometry": {"coordinates":[-81.442564,41.287734],"type":"Point"}
}