{
  "type": "Feature",
  "properties": {
    "iso:country":"US",
    "sg:address":"815 Busch Ct",
    "sg:city":"Columbus",
    "sg:classifiers":[
        {
            "category":"Professional",
            "subcategory":"Business Services",
            "type":"Services"
        }
    ],
    "sg:phone":"+1 614 431 0771",
    "sg:postcode":"43229",
    "sg:province":"OH",
    "sg:tags":[
        "telemarketing"
    ],
    "sg:website":"www.safetypub.com",
    "wof:name":"Innovative Publishing Inc",
    "wof:placetype":"venue"
},
  "geometry": {"coordinates":[-82.99481,40.095927],"type":"Point"}
}