{
  "type": "Feature",
  "properties": {
    "addr:full":"751 S Main St Georgetown OH 45121",
    "addr:housenumber":"751",
    "addr:postcode":"45121",
    "addr:street":"S Main St",
    "iso:country":"US",
    "sg:address":"751 S Main St",
    "sg:city":"Georgetown",
    "sg:classifiers":[
        {
            "category":"Insurance",
            "subcategory":"Insurance Agent",
            "type":"Services"
        }
    ],
    "sg:phone":"+1 937 378 6551",
    "sg:postcode":"45121",
    "sg:province":"OH",
    "wof:name":"New York Life Insurance Co",
    "wof:placetype":"venue"
},
  "geometry": {"coordinates":[-83.90215499999999,38.85898],"type":"Point"}
}