{
  "type": "Feature",
  "properties": {
    "addr:full": "3600 Pobst Dr Dayton OH 45420",
    "addr:housenumber": "3600",
    "addr:postcode": "45420",
    "addr:street": "Pobst Dr",
    "iso:country": "US",
    "sg:address": "3600 Pobst Dr",
    "sg:city": "Dayton",
    "sg:classifiers": [
      {
        "category": "Building \u0026 Trades",
        "subcategory": "Construction",
        "type": "Services"
      }
    ],
    "sg:phone": "+1 937 433 4460",
    "sg:postcode": "45420",
    "sg:province": "OH",
    "sg:tags": [
      "product",
      "asphalt"
    ],
    "wof:name": "Air City Asphalt \u0026 Sealcoating",
    "wof:placetype": "venue"
  },
  "geometry": {"coordinates":[-84.121493,39.693999],"type":"Point"}
}
