{
  "type": "Feature",
  "properties": {
    "iso:country":"US",
    "sg:address":"11977 State Rd",
    "sg:city":"North Royalton",
    "sg:classifiers":[
        {
            "category":"Building & Trades",
            "subcategory":"Construction",
            "type":"Services"
        }
    ],
    "sg:phone":"+1 440 582 1160",
    "sg:postcode":"44133",
    "sg:province":"OH",
    "sg:tags":[
        "house",
        "construct",
        "contractor"
    ],
    "wof:name":"D&L Aluminum",
    "wof:placetype":"venue"
},
  "geometry": {"coordinates":[-81.724614,41.326594],"type":"Point"}
}