{
  "type": "Feature",
  "properties": {
    "addr:full": "11977 State Rd North Royalton OH 44133",
    "addr:housenumber": "11977",
    "addr:postcode": "44133",
    "addr:street": "State Rd",
    "iso:country": "US",
    "sg:address": "11977 State Rd",
    "sg:city": "North Royalton",
    "sg:classifiers": [
      {
        "category": "Building \u0026 Trades",
        "subcategory": "Construction",
        "type": "Services"
      }
    ],
    "sg:phone": "+1 440 582 1160",
    "sg:postcode": "44133",
    "sg:province": "OH",
    "sg:tags": [
      "house",
      "construct",
      "contractor"
    ],
    "wof:name": "D\u0026L Aluminum",
    "wof:placetype": "venue"
  },
  "geometry": {"coordinates":[-81.724614,41.326594],"type":"Point"}
}
