{
  "type": "Feature",
  "properties": {
    "addr:full":"2400 Zuercher Rd Dalton OH 44618",
    "addr:housenumber":"2400",
    "addr:postcode":"44618",
    "addr:street":"Zuercher Rd",
    "iso:country":"US",
    "sg:address":"2400 Zuercher Rd",
    "sg:city":"Dalton",
    "sg:phone":"+1 330 857 4703",
    "sg:postcode":"44618",
    "sg:province":"OH",
    "sg:tags":[
        "farm",
        "corn",
        "crop",
        "general"
    ],
    "wof:name":"Miller Veal Farm",
    "wof:placetype":"venue"
},
  "geometry": {"coordinates":[-81.72166,40.770942],"type":"Point"}
}