{
  "type": "Feature",
  "properties": {
    "addr:full":"9 Valley St Lucasville OH 45648",
    "addr:housenumber":"9",
    "addr:postcode":"45648",
    "addr:street":"Valley St",
    "iso:country":"US",
    "sg:address":"9 Valley St",
    "sg:city":"Lucasville",
    "sg:classifiers":[
        {
            "category":"Education",
            "subcategory":"Dance Studio",
            "type":"Public Place"
        }
    ],
    "sg:phone":"+1 740 259 2290",
    "sg:postcode":"45648",
    "sg:province":"OH",
    "sg:tags":[
        "instruction",
        "dancing"
    ],
    "wof:name":"Studio 104 For Gymnastics",
    "wof:placetype":"venue"
},
  "geometry": {"coordinates":[-82.922079,38.828241],"type":"Point"}
}