{
  "type": "Feature",
  "properties": {
    "iso:country":"US",
    "sg:address":"524 Bogus Rd SE",
    "sg:city":"Washington Ct Hs",
    "sg:classifiers":[
        {
            "category":"Health Services",
            "subcategory":"Nursing And Care Facility",
            "type":"Services"
        }
    ],
    "sg:phone":"+1 740 335 7709",
    "sg:postcode":"43160",
    "sg:province":"OH",
    "sg:tags":[
        "home",
        "retirement",
        "community"
    ],
    "wof:name":"Shonkwiler Family Care Home",
    "wof:placetype":"venue"
},
  "geometry": {"coordinates":[-83.377638,39.535683],"type":"Point"}
}