{
  "type": "Feature",
  "properties": {
    "addr:full": "57005 Seneca Dam Rd Senecaville OH 43780",
    "addr:housenumber": "57005",
    "addr:postcode": "43780",
    "addr:street": "Seneca Dam Rd",
    "iso:country": "US",
    "sg:address": "57005 Seneca Dam Rd",
    "sg:city": "Senecaville",
    "sg:classifiers": [
      {
        "category": "Government",
        "subcategory": "Office",
        "type": "Public Place"
      }
    ],
    "sg:phone": "+1 740 685 5585",
    "sg:postcode": "43780",
    "sg:province": "OH",
    "sg:tags": [
      "engineering"
    ],
    "wof:name": "US Army Corps Of Engineers",
    "wof:placetype": "venue"
  },
  "geometry": {"coordinates":[-81.435342,39.925243],"type":"Point"}
}
