{
  "type": "Feature",
  "properties": {
    "iso:country":"US",
    "sg:address":"57005 Seneca Dam Rd",
    "sg:city":"Senecaville",
    "sg:classifiers":[
        {
            "category":"Government",
            "subcategory":"Office",
            "type":"Public Place"
        }
    ],
    "sg:phone":"+1 740 685 5585",
    "sg:postcode":"43780",
    "sg:province":"OH",
    "sg:tags":[
        "engineering"
    ],
    "wof:name":"US Army Corps Of Engineers",
    "wof:placetype":"venue"
},
  "geometry": {"coordinates":[-81.43534200000001,39.925243],"type":"Point"}
}