{
  "type": "Feature",
  "properties": {
    "iso:country":"US",
    "sg:address":"6212 Freewood Dr",
    "sg:city":"Hilliard",
    "sg:classifiers":[
        {
            "category":"Utilities",
            "subcategory":"Fuel Oil & Lpg",
            "type":"Services"
        }
    ],
    "sg:phone":"+1 614 325 4637",
    "sg:postcode":"43026",
    "sg:province":"OH",
    "sg:tags":[
        "wood"
    ],
    "sg:website":"www.ohiolandscaping.com",
    "wof:name":"OHIOLANDSCAPING.COM",
    "wof:placetype":"venue"
},
  "geometry": {"coordinates":[-83.175349,40.007783],"type":"Point"}
}