{
  "type": "Feature",
  "properties": {
    "iso:country":"US",
    "sg:address":"915 Mull Ave",
    "sg:city":"Akron",
    "sg:classifiers":[
        {
            "category":"Shopping",
            "subcategory":"Jewelry",
            "type":"Retail Goods"
        }
    ],
    "sg:phone":"+1 330 836 6039",
    "sg:postcode":"44313",
    "sg:province":"OH",
    "wof:name":"Truchan Gem Services",
    "wof:placetype":"venue"
},
  "geometry": {"coordinates":[-81.585757,41.099956],"type":"Point"}
}