{
  "type": "Feature",
  "properties": {
    "addr:full": "637 Ohio Pike Ste F Cincinnati OH 45245",
    "addr:housenumber": "637",
    "addr:postcode": "45245",
    "addr:street": "Ohio Pike Ste F",
    "iso:country": "US",
    "sg:address": "637 Ohio Pike Ste F",
    "sg:city": "Cincinnati",
    "sg:classifiers": [
      {
        "category": "Personal",
        "type": "Services"
      },
      {
        "category": "Banks \u0026 Credit Unions",
        "subcategory": "Financial Services",
        "type": "Services"
      }
    ],
    "sg:phone": "+1 513 752 5500",
    "sg:postcode": "45245",
    "sg:province": "OH",
    "sg:tags": [
      "towing",
      "broker",
      "mortgage"
    ],
    "wof:name": "Liberty Mortge Group",
    "wof:placetype": "venue"
  },
  "geometry": {"coordinates":[-84.295502,39.065498],"type":"Point"}
}
