{
  "type": "Feature",
  "properties": {
    "addr:full":"1551 Canton Rd Akron OH 44312",
    "addr:housenumber":"1551",
    "addr:postcode":"44312",
    "addr:street":"Canton Rd",
    "iso:country":"US",
    "sg:address":"1551 Canton Rd",
    "sg:city":"Akron",
    "sg:classifiers":[
        {
            "category":"Organizations",
            "subcategory":"Religious Organization",
            "type":"Services"
        }
    ],
    "sg:phone":"+1 330 733 8701",
    "sg:postcode":"44312",
    "sg:province":"OH",
    "sg:tags":[
        "church"
    ],
    "wof:name":"Akron Springfield Assembly God",
    "wof:placetype":"venue"
},
  "geometry": {"coordinates":[-81.423536,41.027606],"type":"Point"}
}