{
  "type": "Feature",
  "properties": {
    "addr:full": "16363 Pearl Rd Cleveland OH 44136",
    "addr:housenumber": "16363",
    "addr:postcode": "44136",
    "addr:street": "Pearl Rd",
    "iso:country": "US",
    "sg:address": "16363 Pearl Rd",
    "sg:city": "Cleveland",
    "sg:classifiers": [
      {
        "category": "Insurance",
        "subcategory": "Insurance Agent",
        "type": "Services"
      }
    ],
    "sg:phone": "+1 440 878 1920",
    "sg:postcode": "44136",
    "sg:province": "OH",
    "wof:name": "First National Financial Ntwrk",
    "wof:placetype": "venue"
  },
  "geometry": {"coordinates":[-81.835124,41.300304],"type":"Point"}
}
