{
  "type": "Feature",
  "properties": {
    "addr:full":"753 Avon Belden Rd Avon Lake OH 44012",
    "addr:housenumber":"753",
    "addr:postcode":"44012",
    "addr:street":"Avon Belden Rd",
    "iso:country":"US",
    "sg:address":"753 Avon Belden Rd",
    "sg:city":"Avon Lake",
    "sg:classifiers":[
        {
            "category":"Building & Trades",
            "subcategory":"Construction",
            "type":"Services"
        }
    ],
    "sg:phone":"+1 440 930 5672",
    "sg:postcode":"44012",
    "sg:province":"OH",
    "sg:tags":[
        "general",
        "contractor"
    ],
    "wof:name":"Crooked River Contracting",
    "wof:placetype":"venue"
},
  "geometry": {"coordinates":[-82.019205,41.480225],"type":"Point"}
}