{
  "type": "Feature",
  "properties": {
    "addr:full": "7974 Africa Rd Westerville OH 43082",
    "addr:housenumber": "7974",
    "addr:postcode": "43082",
    "addr:street": "Africa Rd",
    "iso:country": "US",
    "sg:address": "7974 Africa Rd",
    "sg:city": "Westerville",
    "sg:classifiers": [
      {
        "category": "Wholesale",
        "subcategory": "Farm Supplies",
        "type": "Manufacturing \u0026 Wholesale Goods"
      }
    ],
    "sg:phone": "+1 614 895 0443",
    "sg:postcode": "43082",
    "sg:province": "OH",
    "wof:name": "Westervelt Hay Straw",
    "wof:placetype": "venue"
  },
  "geometry": {"coordinates":[-82.939414,40.14267],"type":"Point"}
}
