{
  "type": "Feature",
  "properties": {
    "addr:full": "1375 E 9th St Cleveland OH 44114",
    "addr:housenumber": "1375",
    "addr:postcode": "44114",
    "addr:street": "E 9Th St",
    "iso:country": "US",
    "sg:address": "1375 E 9th St",
    "sg:city": "Cleveland",
    "sg:classifiers": [
      {
        "category": "Professional",
        "subcategory": "Lawyer \u0026 Legal Services",
        "type": "Services"
      }
    ],
    "sg:phone": "+1 216 615 4852",
    "sg:postcode": "44114",
    "sg:province": "OH",
    "sg:tags": [
      "attorney"
    ],
    "wof:name": "Christine M Faranda",
    "wof:placetype": "venue"
  },
  "geometry": {"coordinates":[-81.689731,41.503815],"type":"Point"}
}
