{
  "type": "Feature",
  "properties": {
    "addr:full": "13915 Sperry Rd Novelty OH 44072",
    "addr:housenumber": "13915",
    "addr:postcode": "44072",
    "addr:street": "Sperry Rd",
    "iso:country": "US",
    "sg:address": "13915 Sperry Rd",
    "sg:city": "Novelty",
    "sg:classifiers": [
      {
        "category": "Building \u0026 Trades",
        "subcategory": "Landscaping Services",
        "type": "Services"
      }
    ],
    "sg:phone": "+1 440 338 1478",
    "sg:postcode": "44072",
    "sg:province": "OH",
    "sg:tags": [
      "landscape"
    ],
    "wof:name": "Andy Csepi Landscaping Inc",
    "wof:placetype": "venue"
  },
  "geometry": {"coordinates":[-81.288367,41.480098],"type":"Point"}
}
