{
  "type": "Feature",
  "properties": {
    "addr:full": "37 Cascade Dr Chagrin Falls OH 44022",
    "addr:housenumber": "37",
    "addr:postcode": "44022",
    "addr:street": "Cascade Dr",
    "iso:country": "US",
    "sg:address": "37 Cascade Dr",
    "sg:city": "Chagrin Falls",
    "sg:classifiers": [
      {
        "category": "Government",
        "subcategory": "Office",
        "type": "Public Place"
      }
    ],
    "sg:phone": "+1 440 338 6948",
    "sg:postcode": "44022",
    "sg:province": "OH",
    "sg:tags": [
      "development"
    ],
    "wof:name": "Louise Lake Assoc",
    "wof:placetype": "venue"
  },
  "geometry": {"coordinates":[-81.315064,41.426327],"type":"Point"}
}
