{
  "type": "Feature",
  "properties": {
    "iso:country":"US",
    "sg:address":"37 Cascade Dr",
    "sg:city":"Chagrin Falls",
    "sg:classifiers":[
        {
            "category":"Government",
            "subcategory":"Office",
            "type":"Public Place"
        }
    ],
    "sg:phone":"+1 440 338 6948",
    "sg:postcode":"44022",
    "sg:province":"OH",
    "sg:tags":[
        "development"
    ],
    "wof:name":"Louise Lake Assoc",
    "wof:placetype":"venue"
},
  "geometry": {"coordinates":[-81.31506400000001,41.426327],"type":"Point"}
}