{
  "type": "Feature",
  "properties": {
    "addr:full":"171 Kelly Ave Akron OH 44306",
    "addr:housenumber":"171",
    "addr:postcode":"44306",
    "addr:street":"Kelly Ave",
    "iso:country":"US",
    "sg:address":"171 Kelly Ave",
    "sg:city":"Akron",
    "sg:classifiers":[
        {
            "category":"Retail",
            "subcategory":"Auto Repair",
            "type":"Services"
        }
    ],
    "sg:phone":"+1 330 773 3388",
    "sg:postcode":"44306",
    "sg:province":"OH",
    "sg:tags":[
        "wrecker"
    ],
    "wof:name":"Bondurant Service & Towing Inc",
    "wof:placetype":"venue"
},
  "geometry": {"coordinates":[-81.481385,41.060378],"type":"Point"}
}