{
  "type": "Feature",
  "properties": {
    "addr:full": "10359 Hardins Creek Rd Leesburg OH 45135",
    "addr:housenumber": "10359",
    "addr:postcode": "45135",
    "addr:street": "Hardins Creek Rd",
    "iso:country": "US",
    "sg:address": "10359 Hardins Creek Rd",
    "sg:city": "Leesburg",
    "sg:classifiers": [
      {
        "category": "Farming",
        "subcategory": "Farm",
        "type": "Manufacturing \u0026 Wholesale Goods"
      }
    ],
    "sg:phone": "+1 937 780 1020",
    "sg:postcode": "45135",
    "sg:province": "OH",
    "sg:tags": [
      "crop",
      "general"
    ],
    "wof:name": "Back Farms",
    "wof:placetype": "venue"
  },
  "geometry": {"coordinates":[-83.495359,39.29934],"type":"Point"}
}
