{
  "type": "Feature",
  "properties": {
    "addr:full": "4291 Hamilton Scipio Rd Hamilton IN 45013",
    "addr:housenumber": "4291",
    "addr:postcode": "45013",
    "addr:street": "Scipio Rd",
    "iso:country": "US",
    "sg:address": "4291 Hamilton Scipio Rd",
    "sg:city": "Hamilton",
    "sg:classifiers": [
      {
        "category": "Building \u0026 Trades",
        "subcategory": "Construction",
        "type": "Services"
      }
    ],
    "sg:phone": "+1 513 867 1716",
    "sg:postcode": "45013",
    "sg:province": "IN",
    "sg:tags": [
      "commercial"
    ],
    "wof:name": "Laa Builders Inc",
    "wof:placetype": "venue"
  },
  "geometry": {"coordinates":[-84.69996,39.39109],"type":"Point"}
}
