{
  "type": "Feature",
  "properties": {
    "iso:country":"US",
    "sg:address":"4500 Dublin Rd",
    "sg:city":"Columbus",
    "sg:classifiers":[
        {
            "category":"Real Estate",
            "subcategory":"Real Estate Operator",
            "type":"Services"
        }
    ],
    "sg:phone":"+1 614 529 7073",
    "sg:postcode":"43221",
    "sg:province":"OH",
    "sg:tags":[
        "building",
        "nonresidential"
    ],
    "wof:name":"Foxtrail Properties Ltd",
    "wof:placetype":"venue"
},
  "geometry": {"coordinates":[-83.108061,40.05636],"type":"Point"}
}