{
  "type": "Feature",
  "properties": {
    "addr:full": "1435 Kensington St NW Warren OH 44485",
    "addr:housenumber": "1435",
    "addr:postcode": "44485",
    "addr:street": "Kensington St Nw",
    "iso:country": "US",
    "sg:address": "1435 Kensington St NW",
    "sg:city": "Warren",
    "sg:classifiers": [
      {
        "category": "Communications",
        "subcategory": "Film \u0026 Video Production",
        "type": "Services"
      }
    ],
    "sg:phone": "+1 330 399 1239",
    "sg:postcode": "44485",
    "sg:province": "OH",
    "sg:tags": [
      "taping"
    ],
    "wof:name": "Picture This Video",
    "wof:placetype": "venue"
  },
  "geometry": {"coordinates":[-80.839402,41.249979],"type":"Point"}
}
