{
  "type": "Feature",
  "properties": {
    "addr:full":"1116 S High St Ste C Columbus OH 43206",
    "addr:housenumber":"1116",
    "addr:postcode":"43206",
    "addr:street":"S High St Ste C",
    "iso:country":"US",
    "sg:address":"1116 S High St Ste C",
    "sg:city":"Columbus",
    "sg:classifiers":[
        {
            "category":"Wholesale",
            "subcategory":"Medical Equipment & Supplies",
            "type":"Manufacturing & Wholesale Goods"
        },
        {
            "category":"Shopping",
            "subcategory":"Pharmacy",
            "type":"Retail Goods"
        }
    ],
    "sg:phone":"+1 614 444 0064",
    "sg:postcode":"43206",
    "sg:province":"OH",
    "sg:tags":[
        "home",
        "health",
        "care"
    ],
    "wof:name":"Home Healthcare Systems",
    "wof:placetype":"venue"
},
  "geometry": {"coordinates":[-82.996174,39.939159],"type":"Point"}
}