{
  "type": "Feature",
  "properties": {
    "addr:full": "823 E Hudson St Columbus OH 43211",
    "addr:housenumber": "823",
    "addr:postcode": "43211",
    "addr:street": "E Hudson St",
    "iso:country": "US",
    "sg:address": "823 E Hudson St",
    "sg:city": "Columbus",
    "sg:classifiers": [
      {
        "category": "Personal",
        "subcategory": "Beauty Salon",
        "type": "Services"
      }
    ],
    "sg:phone": "+1 614 263 9696",
    "sg:postcode": "43211",
    "sg:province": "OH",
    "wof:name": "Hair Styles With An Attitude",
    "wof:placetype": "venue"
  },
  "geometry": {"coordinates":[-82.988588,40.014533],"type":"Point"}
}
