{
  "type": "Feature",
  "properties": {
    "addr:full":"1230 Ellen Dr Middletown OH 45042",
    "addr:housenumber":"1230",
    "addr:postcode":"45042",
    "addr:street":"Ellen Dr",
    "iso:country":"US",
    "sg:address":"1230 Ellen Dr",
    "sg:city":"Middletown",
    "sg:classifiers":[
        {
            "category":"Freight",
            "type":"Transportation"
        }
    ],
    "sg:phone":"+1 513 422 8054",
    "sg:postcode":"45042",
    "sg:province":"OH",
    "sg:tags":[
        "mover"
    ],
    "wof:name":"Extreme Moving",
    "wof:placetype":"venue"
},
  "geometry": {"coordinates":[-84.369347,39.526472],"type":"Point"}
}