{
  "type": "Feature",
  "properties": {
    "addr:full": "388 Mc Clurg Rd Youngstown OH 44512",
    "addr:housenumber": "388",
    "addr:postcode": "44512",
    "addr:street": "Mc Clurg Rd",
    "iso:country": "US",
    "sg:address": "388 Mc Clurg Rd",
    "sg:city": "Youngstown",
    "sg:classifiers": [
      {
        "category": "Freight",
        "type": "Transportation"
      }
    ],
    "sg:phone": "+1 330 965 9287",
    "sg:postcode": "44512",
    "sg:province": "OH",
    "sg:tags": [
      "shipping",
      "agent"
    ],
    "wof:name": "Acme Mattress",
    "wof:placetype": "venue"
  },
  "geometry": {"coordinates":[-80.645528,40.99532],"type":"Point"}
}
