{
  "type": "Feature",
  "properties": {
    "iso:country":"US",
    "sg:address":"3922 Sonora Rd",
    "sg:city":"Miamisburg",
    "sg:classifiers":[
        {
            "category":"Wholesale",
            "subcategory":"Machinery & Supplies",
            "type":"Manufacturing & Wholesale Goods"
        }
    ],
    "sg:phone":"+1 937 384 0324",
    "sg:postcode":"45338",
    "sg:province":"OH",
    "sg:tags":[
        "operator",
        "industrial",
        "dwelling",
        "used"
    ],
    "wof:name":"Gessner C W & Son",
    "wof:placetype":"venue"
},
  "geometry": {"coordinates":[-84.559517,39.887688],"type":"Point"}
}