{
  "type": "Feature",
  "properties": {
    "addr:full": "7221 Manore Rd Whitehouse OH 43571",
    "addr:housenumber": "7221",
    "addr:postcode": "43571",
    "addr:street": "Manore Rd",
    "iso:country": "US",
    "sg:address": "7221 Manore Rd",
    "sg:city": "Whitehouse",
    "sg:classifiers": [
      {
        "category": "Shopping",
        "type": "Retail Goods"
      }
    ],
    "sg:phone": "+1 419 875 6589",
    "sg:postcode": "43571",
    "sg:province": "OH",
    "sg:tags": [
      "merchandise"
    ],
    "wof:name": "Cherished Daze",
    "wof:placetype": "venue"
  },
  "geometry": {"coordinates":[-83.865469,41.508632],"type":"Point"}
}
