{
  "type": "Feature",
  "properties": {
    "iso:country":"US",
    "sg:address":"169 N 4th St",
    "sg:city":"Steubenville",
    "sg:classifiers":[
        {
            "category":"Bars & Pubs",
            "type":"Food & Drink"
        }
    ],
    "sg:phone":"+1 740 283 2747",
    "sg:postcode":"43952",
    "sg:province":"OH",
    "wof:name":"P J's At The Fed",
    "wof:placetype":"venue"
},
  "geometry": {"coordinates":[-80.614711,40.360952],"type":"Point"}
}