{
  "type": "Feature",
  "properties": {
    "addr:full": "169 N 4th St Steubenville OH 43952",
    "addr:housenumber": "169",
    "addr:postcode": "43952",
    "addr:street": "N 4Th St",
    "iso:country": "US",
    "sg:address": "169 N 4th St",
    "sg:city": "Steubenville",
    "sg:classifiers": [
      {
        "category": "Bars \u0026 Pubs",
        "type": "Food \u0026 Drink"
      }
    ],
    "sg:phone": "+1 740 283 2747",
    "sg:postcode": "43952",
    "sg:province": "OH",
    "wof:name": "P J's At The Fed",
    "wof:placetype": "venue"
  },
  "geometry": {"coordinates":[-80.614711,40.360952],"type":"Point"}
}
