{
  "type": "Feature",
  "properties": {
    "addr:full": "201 E 4th St Cincinnati OH 45202",
    "addr:housenumber": "201",
    "addr:postcode": "45202",
    "addr:street": "E 4Th St",
    "iso:country": "US",
    "sg:address": "201 E 4th St",
    "sg:city": "Cincinnati",
    "sg:classifiers": [
      {
        "category": "Banks \u0026 Credit Unions",
        "subcategory": "Investment Brokerage",
        "type": "Services"
      }
    ],
    "sg:phone": "+1 513 762 8000",
    "sg:postcode": "45202",
    "sg:province": "OH",
    "sg:tags": [
      "stock",
      "bond"
    ],
    "wof:name": "Kidder Peabody \u0026 Co Inc",
    "wof:placetype": "venue"
  },
  "geometry": {"coordinates":[-84.508546,39.100561],"type":"Point"}
}
