{
  "type": "Feature",
  "properties": {
    "addr:full":"719 Boulevard St Dover OH 44622",
    "addr:housenumber":"719",
    "addr:postcode":"44622",
    "addr:street":"Boulevard St",
    "iso:country":"US",
    "sg:address":"719 Boulevard St",
    "sg:city":"Dover",
    "sg:classifiers":[
        {
            "category":"Autos & Motor Vehicles",
            "subcategory":"Automobile Sales",
            "type":"Retail Goods"
        }
    ],
    "sg:phone":"+1 330 343 8878",
    "sg:postcode":"44622",
    "sg:province":"OH",
    "sg:tags":[
        "used"
    ],
    "wof:name":"Wheeler Oldsmobile Inc",
    "wof:placetype":"venue"
},
  "geometry": {"coordinates":[-81.455697,40.513456],"type":"Point"}
}