{
  "type": "Feature",
  "properties": {
    "addr:full":"2519 S Smithville Rd Dayton OH 45420",
    "addr:housenumber":"2519",
    "addr:postcode":"45420",
    "addr:street":"S Smithville Rd",
    "iso:country":"US",
    "sg:address":"2519 S Smithville Rd",
    "sg:city":"Dayton",
    "sg:classifiers":[
        {
            "category":"Professional",
            "subcategory":"Accounting & Tax Preparation",
            "type":"Services"
        }
    ],
    "sg:phone":"+1 937 252 3152",
    "sg:postcode":"45420",
    "sg:province":"OH",
    "sg:tags":[
        "return"
    ],
    "wof:name":"H & R Block",
    "wof:placetype":"venue"
},
  "geometry": {"coordinates":[-84.141248,39.729894],"type":"Point"}
}