{
  "type": "Feature",
  "properties": {
    "addr:full":"4 E High Ct Youngstown OH 44505",
    "addr:housenumber":"4",
    "addr:postcode":"44505",
    "addr:street":"E High Ct",
    "iso:country":"US",
    "sg:address":"4 E High Ct",
    "sg:city":"Youngstown",
    "sg:classifiers":[
        {
            "category":"Building & Trades",
            "subcategory":"Construction",
            "type":"Services"
        }
    ],
    "sg:phone":"+1 330 747 3261",
    "sg:postcode":"44505",
    "sg:province":"OH",
    "sg:tags":[
        "wallcoverings-installation",
        "wallpaper",
        "painting",
        "contractor"
    ],
    "wof:name":"Jesse Jas Paunting",
    "wof:placetype":"venue"
},
  "geometry": {"coordinates":[-80.623254,41.10205],"type":"Point"}
}