{
  "type": "Feature",
  "properties": {
    "addr:full": "216 Oakdale Ave Toledo OH 43605",
    "addr:housenumber": "216",
    "addr:postcode": "43605",
    "addr:street": "Oakdale Ave",
    "iso:country": "US",
    "sg:address": "216 Oakdale Ave",
    "sg:city": "Toledo",
    "sg:classifiers": [
      {
        "category": "Retail",
        "subcategory": "Auto Repair",
        "type": "Services"
      }
    ],
    "sg:phone": "+1 419 693 8682",
    "sg:postcode": "43605",
    "sg:province": "OH",
    "sg:tags": [
      "wrecker"
    ],
    "wof:name": "Merle's Automotive Inc",
    "wof:placetype": "venue"
  },
  "geometry": {"coordinates":[-83.526779,41.621624],"type":"Point"}
}
