{
  "type": "Feature",
  "properties": {
    "iso:country":"US",
    "sg:address":"12 Hillwyck Dr",
    "sg:city":"Toledo",
    "sg:classifiers":[
        {
            "category":"Restaurant",
            "type":"Food & Drink"
        }
    ],
    "sg:phone":"+1 419 537 0880",
    "sg:postcode":"43615",
    "sg:province":"OH",
    "sg:tags":[
        "eating",
        "caterer"
    ],
    "wof:name":"Shaffer's Catering",
    "wof:placetype":"venue"
},
  "geometry": {"coordinates":[-83.66649700000001,41.637467],"type":"Point"}
}