{
  "type": "Feature",
  "properties": {
    "addr:full": "12 Hillwyck Dr Toledo OH 43615",
    "addr:housenumber": "12",
    "addr:postcode": "43615",
    "addr:street": "Hillwyck Dr",
    "iso:country": "US",
    "sg:address": "12 Hillwyck Dr",
    "sg:city": "Toledo",
    "sg:classifiers": [
      {
        "category": "Restaurant",
        "type": "Food \u0026 Drink"
      }
    ],
    "sg:phone": "+1 419 537 0880",
    "sg:postcode": "43615",
    "sg:province": "OH",
    "sg:tags": [
      "eating",
      "caterer"
    ],
    "wof:name": "Shaffer's Catering",
    "wof:placetype": "venue"
  },
  "geometry": {"coordinates":[-83.666497,41.637467],"type":"Point"}
}
