{
  "type": "Feature",
  "properties": {
    "addr:full": "6865 Cochran Rd Cleveland OH 44139",
    "addr:housenumber": "6865",
    "addr:postcode": "44139",
    "addr:street": "Cochran Rd",
    "iso:country": "US",
    "sg:address": "6865 Cochran Rd",
    "sg:city": "Cleveland",
    "sg:classifiers": [
      {
        "category": "Manufacturing",
        "subcategory": "Tools \u0026 Machinery",
        "type": "Manufacturing \u0026 Wholesale Goods"
      }
    ],
    "sg:phone": "+1 440 349 5151",
    "sg:postcode": "44139",
    "sg:province": "OH",
    "sg:tags": [
      "machine",
      "mfg",
      "accessory"
    ],
    "wof:name": "Kennametal Inc",
    "wof:placetype": "venue"
  },
  "geometry": {"coordinates":[-81.46954,41.370633],"type":"Point"}
}
