{
  "type": "Feature",
  "properties": {
    "iso:country":"US",
    "sg:address":"6865 Cochran Rd",
    "sg:city":"Cleveland",
    "sg:classifiers":[
        {
            "category":"Manufacturing",
            "subcategory":"Tools & Machinery",
            "type":"Manufacturing & Wholesale Goods"
        }
    ],
    "sg:phone":"+1 440 349 5151",
    "sg:postcode":"44139",
    "sg:province":"OH",
    "sg:tags":[
        "machine",
        "mfg",
        "accessory"
    ],
    "wof:name":"Kennametal Inc",
    "wof:placetype":"venue"
},
  "geometry": {"coordinates":[-81.46953999999999,41.370633],"type":"Point"}
}