{
  "type": "Feature",
  "properties": {
    "addr:full": "3130 N High St Columbus OH 43202",
    "addr:housenumber": "3130",
    "addr:postcode": "43202",
    "addr:street": "N High St",
    "iso:country": "US",
    "sg:address": "3130 N High St",
    "sg:city": "Columbus",
    "sg:classifiers": [
      {
        "category": "Manufacturing",
        "subcategory": "Signs",
        "type": "Manufacturing \u0026 Wholesale Goods"
      }
    ],
    "sg:phone": "+1 614 267 1156",
    "sg:postcode": "43202",
    "sg:province": "OH",
    "sg:tags": [
      "mfg"
    ],
    "wof:name": "Skyline Graphics Inc",
    "wof:placetype": "venue"
  },
  "geometry": {"coordinates":[-83.014374,40.026125],"type":"Point"}
}
