{
  "type": "Feature",
  "properties": {
    "iso:country":"US",
    "sg:address":"615 Lancaster Pike",
    "sg:city":"Circleville",
    "sg:classifiers":[
        {
            "category":"Retail",
            "subcategory":"Veterinary Services",
            "type":"Services"
        }
    ],
    "sg:phone":"+1 740 474 8569",
    "sg:postcode":"43113",
    "sg:province":"OH",
    "wof:name":"Brookehill Animal Clinic",
    "wof:placetype":"venue"
},
  "geometry": {"coordinates":[-82.920237,39.603534],"type":"Point"}
}