{
  "type": "Feature",
  "properties": {
    "addr:full":"1275 Lancaster-Kirkersville Rd NW Lancaster OH 43130",
    "addr:housenumber":"1275",
    "addr:postcode":"43130",
    "addr:street":"Lancaster-Kirkersville Rd Nw",
    "iso:country":"US",
    "sg:address":"1275 Lancaster-Kirkersville Rd NW",
    "sg:city":"Lancaster",
    "sg:classifiers":[
        {
            "category":"Building & Trades",
            "subcategory":"Electrical",
            "type":"Services"
        }
    ],
    "sg:phone":"+1 740 653 5683",
    "sg:postcode":"43130",
    "sg:province":"OH",
    "sg:tags":[
        "electric",
        "contractor"
    ],
    "wof:name":"Claypool Electric Inc",
    "wof:placetype":"venue"
},
  "geometry": {"coordinates":[-82.614407,39.74339],"type":"Point"}
}