{
  "type": "Feature",
  "properties": {
    "iso:country":"US",
    "sg:address":"640 Park Ave W",
    "sg:city":"Mansfield",
    "sg:classifiers":[
        {
            "category":"Insurance",
            "subcategory":"Insurance Agent",
            "type":"Services"
        }
    ],
    "sg:phone":"+1 419 524 3661",
    "sg:postcode":"44906",
    "sg:province":"OH",
    "wof:name":"Ohio State Life Insurance",
    "wof:placetype":"venue"
},
  "geometry": {"coordinates":[-82.54113599999999,40.759114],"type":"Point"}
}