{
  "type": "Feature",
  "properties": {
    "addr:full":"16 Dorset Ct Cleveland OH 44122",
    "addr:housenumber":"16",
    "addr:postcode":"44122",
    "addr:street":"Dorset Ct",
    "iso:country":"US",
    "sg:address":"16 Dorset Ct",
    "sg:city":"Cleveland",
    "sg:classifiers":[
        {
            "category":"Professional",
            "type":"Services"
        }
    ],
    "sg:phone":"+1 216 831 1533",
    "sg:postcode":"44122",
    "sg:province":"OH",
    "wof:name":"Ernest & Renee Dworkin",
    "wof:placetype":"venue"
},
  "geometry": {"coordinates":[-81.495715,41.494428],"type":"Point"}
}