{
  "type": "Feature",
  "properties": {
    "iso:country":"US",
    "sg:address":"2664 Harrisburg Rd NE",
    "sg:city":"Canton",
    "sg:classifiers":[
        {
            "category":"Utilities",
            "subcategory":"Water",
            "type":"Services"
        }
    ],
    "sg:phone":"+1 330 489 3310",
    "sg:postcode":"44705",
    "sg:province":"OH",
    "sg:tags":[
        "company",
        "sewage"
    ],
    "sg:website":"www.cityofcanton.com",
    "wof:name":"Canton Water Dept",
    "wof:placetype":"venue"
},
  "geometry": {"coordinates":[-81.34834499999999,40.824746],"type":"Point"}
}