{
  "type": "Feature",
  "properties": {
    "addr:full": "2664 Harrisburg Rd NE Canton OH 44705",
    "addr:housenumber": "2664",
    "addr:postcode": "44705",
    "addr:street": "Harrisburg Rd Ne",
    "iso:country": "US",
    "sg:address": "2664 Harrisburg Rd NE",
    "sg:city": "Canton",
    "sg:classifiers": [
      {
        "category": "Utilities",
        "subcategory": "Water",
        "type": "Services"
      }
    ],
    "sg:phone": "+1 330 489 3310",
    "sg:postcode": "44705",
    "sg:province": "OH",
    "sg:tags": [
      "company",
      "sewage"
    ],
    "sg:website": "www.cityofcanton.com",
    "wof:name": "Canton Water Dept",
    "wof:placetype": "venue"
  },
  "geometry": {"coordinates":[-81.348345,40.824746],"type":"Point"}
}
