{
  "type": "Feature",
  "properties": {
    "addr:full": "6542 Kirk Rd Canfield OH 44406",
    "addr:housenumber": "6542",
    "addr:postcode": "44406",
    "addr:street": "Kirk Rd",
    "iso:country": "US",
    "sg:address": "6542 Kirk Rd",
    "sg:city": "Canfield",
    "sg:classifiers": [
      {
        "category": "Professional",
        "subcategory": "Management \u0026 Consulting",
        "type": "Services"
      }
    ],
    "sg:phone": "+1 330 799 5579",
    "sg:postcode": "44406",
    "sg:province": "OH",
    "sg:tags": [
      "retail",
      "direct",
      "sales"
    ],
    "wof:name": "Amway",
    "wof:placetype": "venue"
  },
  "geometry": {"coordinates":[-80.779598,41.069056],"type":"Point"}
}
