{
  "type": "Feature",
  "properties": {
    "iso:country":"US",
    "sg:address":"6542 Kirk Rd",
    "sg:city":"Canfield",
    "sg:classifiers":[
        {
            "category":"Professional",
            "subcategory":"Management & Consulting",
            "type":"Services"
        }
    ],
    "sg:phone":"+1 330 799 5579",
    "sg:postcode":"44406",
    "sg:province":"OH",
    "sg:tags":[
        "retail",
        "direct",
        "sales"
    ],
    "wof:name":"Amway",
    "wof:placetype":"venue"
},
  "geometry": {"coordinates":[-80.77959799999999,41.069056],"type":"Point"}
}