{
  "type": "Feature",
  "properties": {
    "iso:country":"US",
    "sg:address":"311 Drury Ln",
    "sg:city":"Troy",
    "sg:classifiers":[
        {
            "category":"Professional",
            "subcategory":"Business Services",
            "type":"Services"
        }
    ],
    "sg:phone":"+1 937 339 0850",
    "sg:postcode":"45373",
    "sg:province":"OH",
    "sg:tags":[
        "auctioneer"
    ],
    "wof:name":"Anderson Auction",
    "wof:placetype":"venue"
},
  "geometry": {"coordinates":[-84.209181,40.037059],"type":"Point"}
}