{
  "type": "Feature",
  "properties": {
    "iso:country":"US",
    "sg:address":"4925 Jackman Rd",
    "sg:city":"Toledo",
    "sg:classifiers":[
        {
            "category":"Shopping",
            "subcategory":"Crafts & Fabrics",
            "type":"Retail Goods"
        }
    ],
    "sg:phone":"+1 419 474 0224",
    "sg:postcode":"43613",
    "sg:province":"OH",
    "sg:tags":[
        "shop",
        "sewing"
    ],
    "wof:name":"Jo-Ann Fabrics & Crafts",
    "wof:placetype":"venue"
},
  "geometry": {"coordinates":[-83.585474,41.704461],"type":"Point"}
}