{
  "type": "Feature",
  "properties": {
    "addr:full": "4686 Douglas Cir NW Canton OH 44718",
    "addr:housenumber": "4686",
    "addr:postcode": "44718",
    "addr:street": "Douglas Cir Nw",
    "iso:country": "US",
    "sg:address": "4686 Douglas Cir NW",
    "sg:city": "Canton",
    "sg:classifiers": [
      {
        "category": "Professional",
        "subcategory": "Business Services",
        "type": "Services"
      }
    ],
    "sg:phone": "+1 330 497 1600",
    "sg:postcode": "44718",
    "sg:province": "OH",
    "sg:tags": [
      "auctioneer"
    ],
    "wof:name": "Tom A Baier \u0026 Assoc Auctioneer",
    "wof:placetype": "venue"
  },
  "geometry": {"coordinates":[-81.439444,40.848822],"type":"Point"}
}
