{
  "type": "Feature",
  "properties": {
    "addr:full": "1681 N Trend Dr Zanesville OH 43701",
    "addr:housenumber": "1681",
    "addr:postcode": "43701",
    "addr:street": "N Trend Dr",
    "iso:country": "US",
    "sg:address": "1681 N Trend Dr",
    "sg:city": "Zanesville",
    "sg:classifiers": [
      {
        "category": "Building \u0026 Trades",
        "subcategory": "Electrical",
        "type": "Services"
      }
    ],
    "sg:phone": "+1 740 454 6352",
    "sg:postcode": "43701",
    "sg:province": "OH",
    "sg:tags": [
      "electrical",
      "contractor"
    ],
    "wof:name": "D\u0026S Electrical Services Inc",
    "wof:placetype": "venue"
  },
  "geometry": {"coordinates":[-82.036445,39.986025],"type":"Point"}
}
