{
  "type": "Feature",
  "properties": {
    "addr:full": "121 E Main St Circleville OH 43113",
    "addr:housenumber": "121",
    "addr:postcode": "43113",
    "addr:street": "E Main St",
    "iso:country": "US",
    "sg:address": "121 E Main St",
    "sg:city": "Circleville",
    "sg:classifiers": [
      {
        "category": "Personal",
        "subcategory": "Tattoo Parlor",
        "type": "Services"
      }
    ],
    "sg:phone": "+1 740 420 7213",
    "sg:postcode": "43113",
    "sg:province": "OH",
    "sg:tags": [
      "tattooing"
    ],
    "wof:name": "American Tradition Tattoo",
    "wof:placetype": "venue"
  },
  "geometry": {"coordinates":[-82.944612,39.601649],"type":"Point"}
}
