{
  "type": "Feature",
  "properties": {
    "addr:full":"6 Meadow Lane Dr Delta OH 43515",
    "addr:housenumber":"6",
    "addr:postcode":"43515",
    "addr:street":"Meadow Lane Dr",
    "iso:country":"US",
    "sg:address":"6 Meadow Lane Dr",
    "sg:city":"Delta",
    "sg:classifiers":[
        {
            "category":"Professional",
            "type":"Services"
        }
    ],
    "sg:phone":"+1 419 822 8365",
    "sg:postcode":"43515",
    "sg:province":"OH",
    "sg:tags":[
        "establishment"
    ],
    "wof:name":"Churchhill & Churchhill",
    "wof:placetype":"venue"
},
  "geometry": {"coordinates":[-83.99683400000001,41.578217],"type":"Point"}
}