{
  "type": "Feature",
  "properties": {
    "addr:full":"7 Kings Dr SW Warren OH 44481",
    "addr:housenumber":"7",
    "addr:postcode":"44481",
    "addr:street":"Kings Dr Sw",
    "iso:country":"US",
    "sg:address":"7 Kings Dr SW",
    "sg:city":"Warren",
    "sg:classifiers":[
        {
            "category":"Organizations",
            "subcategory":"Community Association",
            "type":"Services"
        }
    ],
    "sg:phone":"+1 330 824 8909",
    "sg:postcode":"44481",
    "sg:province":"OH",
    "wof:name":"Toastmasters International",
    "wof:placetype":"venue"
},
  "geometry": {"coordinates":[-80.91771199999999,41.164159],"type":"Point"}
}