{
  "type": "Feature",
  "properties": {
    "iso:country":"US",
    "sg:address":"3023 Co Rd 91",
    "sg:city":"Bellefontaine",
    "sg:classifiers":[
        {
            "category":"Social Services",
            "subcategory":"Job Training",
            "type":"Services"
        }
    ],
    "sg:phone":"+1 937 592 0756",
    "sg:postcode":"43311",
    "sg:province":"OH",
    "sg:tags":[
        "rehabilitation"
    ],
    "wof:name":"Concept Rehab",
    "wof:placetype":"venue"
},
  "geometry": {"coordinates":[-83.800796,40.398265],"type":"Point"}
}