{
  "type": "Feature",
  "properties": {
    "addr:full": "1701 E Main St Columbus OH 43205",
    "addr:housenumber": "1701",
    "addr:postcode": "43205",
    "addr:street": "E Main St",
    "iso:country": "US",
    "sg:address": "1701 E Main St",
    "sg:city": "Columbus",
    "sg:classifiers": [
      {
        "category": "Autos \u0026 Motor Vehicles",
        "subcategory": "Automobile Sales",
        "type": "Retail Goods"
      }
    ],
    "sg:phone": "+1 614 252 1519",
    "sg:postcode": "43205",
    "sg:province": "OH",
    "sg:tags": [
      "car",
      "dealer"
    ],
    "wof:name": "D \u0026 P Auto Sales",
    "wof:placetype": "venue"
  },
  "geometry": {"coordinates":[-82.953257,39.957445],"type":"Point"}
}
