{
  "type": "Feature",
  "properties": {
    "iso:country":"US",
    "sg:address":"1701 E Main St",
    "sg:city":"Columbus",
    "sg:classifiers":[
        {
            "category":"Autos & Motor Vehicles",
            "subcategory":"Automobile Sales",
            "type":"Retail Goods"
        }
    ],
    "sg:phone":"+1 614 252 1519",
    "sg:postcode":"43205",
    "sg:province":"OH",
    "sg:tags":[
        "car",
        "dealer"
    ],
    "wof:name":"D & P Auto Sales",
    "wof:placetype":"venue"
},
  "geometry": {"coordinates":[-82.95325699999999,39.957445],"type":"Point"}
}