{
  "type": "Feature",
  "properties": {
    "addr:full":"1832 E Main St Springfield OH 45503",
    "addr:housenumber":"1832",
    "addr:postcode":"45503",
    "addr:street":"E Main St",
    "iso:country":"US",
    "sg:address":"1832 E Main St",
    "sg:city":"Springfield",
    "sg:classifiers":[
        {
            "category":"Cinema",
            "subcategory":"Movie Rental",
            "type":"Entertainment"
        }
    ],
    "sg:phone":"+1 937 324 0211",
    "sg:postcode":"45503",
    "sg:province":"OH",
    "sg:tags":[
        "leasing",
        "video",
        "disc",
        "tape"
    ],
    "wof:name":"Blockbuster Video",
    "wof:placetype":"venue"
},
  "geometry": {"coordinates":[-83.78151200000001,39.923397],"type":"Point"}
}