{
  "type": "Feature",
  "properties": {
    "addr:full":"451 Front St Berea OH 44017",
    "addr:housenumber":"451",
    "addr:postcode":"44017",
    "addr:street":"Front St",
    "iso:country":"US",
    "sg:address":"451 Front St",
    "sg:city":"Berea",
    "sg:classifiers":[
        {
            "category":"Government",
            "subcategory":"Office",
            "type":"Public Place"
        }
    ],
    "sg:phone":"+1 440 826 5891",
    "sg:postcode":"44017",
    "sg:province":"OH",
    "sg:tags":[
        "conservation"
    ],
    "wof:name":"Berea Rcrtion Dept Humn Rsrces",
    "wof:placetype":"venue"
},
  "geometry": {"coordinates":[-81.853149,41.377451],"type":"Point"}
}