{
  "type": "Feature",
  "properties": {
    "addr:full": "412 Nauvoo Rd Clarksville OH 45113",
    "addr:housenumber": "412",
    "addr:postcode": "45113",
    "addr:street": "Nauvoo Rd",
    "iso:country": "US",
    "sg:address": "412 Nauvoo Rd",
    "sg:city": "Clarksville",
    "sg:classifiers": [
      {
        "category": "Building \u0026 Trades",
        "subcategory": "Construction",
        "type": "Services"
      }
    ],
    "sg:phone": "+1 937 289 3201",
    "sg:postcode": "45113",
    "sg:province": "OH",
    "sg:tags": [
      "house",
      "construct",
      "contractor"
    ],
    "wof:name": "Newton R L Sons Roofg \u0026 Siding",
    "wof:placetype": "venue"
  },
  "geometry": {"coordinates":[-83.975528,39.365457],"type":"Point"}
}
