{
  "type": "Feature",
  "properties": {
    "addr:full": "645 Oakland Park Ave Columbus OH 43214",
    "addr:housenumber": "645",
    "addr:postcode": "43214",
    "addr:street": "Oakland Park Ave",
    "iso:country": "US",
    "sg:address": "645 Oakland Park Ave",
    "sg:city": "Columbus",
    "sg:classifiers": [
      {
        "category": "Wholesale",
        "subcategory": "Scrap",
        "type": "Manufacturing \u0026 Wholesale Goods"
      }
    ],
    "sg:phone": "+1 614 263 8000",
    "sg:postcode": "43214",
    "sg:province": "OH",
    "sg:tags": [
      "waste"
    ],
    "wof:name": "Econo Haul Inc",
    "wof:placetype": "venue"
  },
  "geometry": {"coordinates":[-83.00015,40.032874],"type":"Point"}
}
