{
  "type": "Feature",
  "properties": {
    "iso:country":"US",
    "sg:address":"645 Oakland Park Ave",
    "sg:city":"Columbus",
    "sg:classifiers":[
        {
            "category":"Wholesale",
            "subcategory":"Scrap",
            "type":"Manufacturing & Wholesale Goods"
        }
    ],
    "sg:phone":"+1 614 263 8000",
    "sg:postcode":"43214",
    "sg:province":"OH",
    "sg:tags":[
        "waste"
    ],
    "wof:name":"Econo Haul Inc",
    "wof:placetype":"venue"
},
  "geometry": {"coordinates":[-83.00015,40.032874],"type":"Point"}
}