{
  "type": "Feature",
  "properties": {
    "addr:full":"117 S Water St Kent OH 44240",
    "addr:housenumber":"117",
    "addr:postcode":"44240",
    "addr:street":"S Water St",
    "iso:country":"US",
    "sg:address":"117 S Water St",
    "sg:city":"Kent",
    "sg:classifiers":[
        {
            "category":"Professional",
            "type":"Services"
        }
    ],
    "sg:phone":"+1 330 678 7865",
    "sg:postcode":"44240",
    "sg:province":"OH",
    "wof:name":"Invictus",
    "wof:placetype":"venue"
},
  "geometry": {"coordinates":[-81.358104,41.152881],"type":"Point"}
}