{
  "type": "Feature",
  "properties": {
    "addr:full": "2171 E 49th St Cleveland OH 44103",
    "addr:housenumber": "2171",
    "addr:postcode": "44103",
    "addr:street": "E 49Th St",
    "iso:country": "US",
    "sg:address": "2171 E 49th St",
    "sg:city": "Cleveland",
    "sg:classifiers": [
      {
        "category": "Organizations",
        "subcategory": "Religious Organization",
        "type": "Services"
      }
    ],
    "sg:phone": "+1 216 391 2632",
    "sg:postcode": "44103",
    "sg:province": "OH",
    "sg:tags": [
      "church"
    ],
    "sg:website": "www.standrewscleveland.org",
    "wof:name": "St Andrew's Episcopal Church",
    "wof:placetype": "venue"
  },
  "geometry": {"coordinates":[-81.652638,41.496808],"type":"Point"}
}
