{
  "type": "Feature",
  "properties": {
    "iso:country":"US",
    "sg:address":"4235 Secor Rd",
    "sg:city":"Toledo",
    "sg:classifiers":[
        {
            "category":"Health Services",
            "subcategory":"Doctor",
            "type":"Services"
        }
    ],
    "sg:phone":"+1 419 479 5660",
    "sg:postcode":"43623",
    "sg:province":"OH",
    "sg:tags":[
        "physician",
        "surgeon"
    ],
    "wof:name":"Syed I Mobin MD",
    "wof:placetype":"venue"
},
  "geometry": {"coordinates":[-83.623347,41.695885],"type":"Point"}
}