{
  "type": "Feature",
  "properties": {
    "iso:country":"US",
    "sg:address":"2556 Coral Ridge Ave",
    "sg:city":"Grove City",
    "sg:classifiers":[
        {
            "category":"Wholesale",
            "subcategory":"Office Equipment",
            "type":"Manufacturing & Wholesale Goods"
        }
    ],
    "sg:phone":"+1 614 242 0502",
    "sg:postcode":"43123",
    "sg:province":"OH",
    "wof:name":"Dick S Cash Register",
    "wof:placetype":"venue"
},
  "geometry": {"coordinates":[-83.06453500000001,39.908694],"type":"Point"}
}