{
  "type": "Feature",
  "properties": {
    "addr:full":"2787 State Rte 589 Casstown OH 45312",
    "addr:housenumber":"2787",
    "addr:postcode":"45312",
    "addr:street":"State Rte 589",
    "iso:country":"US",
    "sg:address":"2787 State Rte 589",
    "sg:city":"Casstown",
    "sg:phone":"+1 937 335 6978",
    "sg:postcode":"45312",
    "sg:province":"OH",
    "sg:tags":[
        "farm",
        "corn",
        "soybean"
    ],
    "wof:name":"Bodenmiller Farms",
    "wof:placetype":"venue"
},
  "geometry": {"coordinates":[-84.11821399999999,40.070946],"type":"Point"}
}