{
  "type": "Feature",
  "properties": {
    "addr:full":"10273 Co Rd 3 Swanton OH 43558",
    "addr:housenumber":"10273;3",
    "addr:postcode":"43558",
    "addr:street":"Co Rd",
    "iso:country":"US",
    "sg:address":"10273 Co Rd 3",
    "sg:city":"Swanton",
    "sg:classifiers":[
        {
            "category":"Manufacturing",
            "subcategory":"Motor Vehicles & Parts",
            "type":"Manufacturing & Wholesale Goods"
        }
    ],
    "sg:phone":"+1 419 825 7263",
    "sg:postcode":"43558",
    "sg:province":"OH",
    "sg:tags":[
        "truck",
        "trailer",
        "mfg"
    ],
    "wof:name":"J & B Bailey Trucking Co LLC",
    "wof:placetype":"venue"
},
  "geometry": {"coordinates":[-83.9217,41.621318],"type":"Point"}
}