{
  "type": "Feature",
  "properties": {
    "addr:full":"351 Lowery Ct Groveport OH 43125",
    "addr:housenumber":"351",
    "addr:postcode":"43125",
    "addr:street":"Lowery Ct",
    "iso:country":"US",
    "sg:address":"351 Lowery Ct",
    "sg:city":"Groveport",
    "sg:classifiers":[
        {
            "category":"Wholesale",
            "subcategory":"Vending Machines",
            "type":"Manufacturing & Wholesale Goods"
        }
    ],
    "sg:phone":"+1 614 836 7615",
    "sg:postcode":"43125",
    "sg:province":"OH",
    "wof:name":"Apollo Vending",
    "wof:placetype":"venue"
},
  "geometry": {"coordinates":[-82.88712,39.860184],"type":"Point"}
}