{
  "type": "Feature",
  "properties": {
    "iso:country":"US",
    "sg:address":"5191 Natorp Blvd",
    "sg:city":"Mason",
    "sg:classifiers":[
        {
            "category":"Professional",
            "subcategory":"Management & Consulting",
            "type":"Services"
        }
    ],
    "sg:phone":"+1 513 229 1000",
    "sg:postcode":"45040",
    "sg:province":"OH",
    "sg:tags":[
        "consultant",
        "educational"
    ],
    "wof:name":"Thomson Learning",
    "wof:placetype":"venue"
},
  "geometry": {"coordinates":[-84.320678,39.301407],"type":"Point"}
}