{
  "type": "Feature",
  "properties": {
    "addr:full": "4225 Beal Rd SE Newark OH 43056",
    "addr:housenumber": "4225",
    "addr:postcode": "43056",
    "addr:street": "Beal Rd Se",
    "iso:country": "US",
    "sg:address": "4225 Beal Rd SE",
    "sg:city": "Newark",
    "sg:classifiers": [
      {
        "category": "Farming",
        "subcategory": "Livestock Farm",
        "type": "Manufacturing \u0026 Wholesale Goods"
      }
    ],
    "sg:phone": "+1 740 323 1584",
    "sg:postcode": "43056",
    "sg:province": "OH",
    "sg:tags": [
      "beef",
      "feedlot",
      "cattle"
    ],
    "wof:name": "Johnson Farm",
    "wof:placetype": "venue"
  },
  "geometry": {"coordinates":[-82.336186,40.01807],"type":"Point"}
}
