{
  "type": "Feature",
  "properties": {
    "addr:full":"4507 W Pleasant Valley Rd Cleveland OH 44134",
    "addr:housenumber":"4507",
    "addr:postcode":"44134",
    "addr:street":"W Pleasant Valley Rd",
    "iso:country":"US",
    "sg:address":"4507 W Pleasant Valley Rd",
    "sg:city":"Cleveland",
    "sg:classifiers":[
        {
            "category":"Home & Garden",
            "subcategory":"Carpets & Floor Coverings",
            "type":"Retail Goods"
        }
    ],
    "sg:phone":"+1 440 845 1880",
    "sg:postcode":"44134",
    "sg:province":"OH",
    "sg:tags":[
        "clean",
        "upholstery",
        "rug",
        "carpeting",
        "dealer"
    ],
    "wof:name":"Frederick's Floor Coverings",
    "wof:placetype":"venue"
},
  "geometry": {"coordinates":[-81.710183,41.363721],"type":"Point"}
}