{
  "type": "Feature",
  "properties": {
    "addr:full": "100 S 12th St Sebring OH 44672",
    "addr:housenumber": "100",
    "addr:postcode": "44672",
    "addr:street": "S 12Th St",
    "iso:country": "US",
    "sg:address": "100 S 12th St",
    "sg:city": "Sebring",
    "sg:classifiers": [
      {
        "category": "Manufacturing",
        "subcategory": "Rubber \u0026 Plastics",
        "type": "Manufacturing \u0026 Wholesale Goods"
      }
    ],
    "sg:phone": "+1 330 938 9674",
    "sg:postcode": "44672",
    "sg:province": "OH",
    "sg:tags": [
      "forming"
    ],
    "sg:website": "www.vacuforminc.com",
    "wof:name": "Vacuform Inc",
    "wof:placetype": "venue"
  },
  "geometry": {"coordinates":[-81.012795,40.919446],"type":"Point"}
}
