{
  "type": "Feature",
  "properties": {
    "iso:country":"US",
    "sg:address":"100 S 12th St",
    "sg:city":"Sebring",
    "sg:classifiers":[
        {
            "category":"Manufacturing",
            "subcategory":"Rubber & Plastics",
            "type":"Manufacturing & Wholesale Goods"
        }
    ],
    "sg:phone":"+1 330 938 9674",
    "sg:postcode":"44672",
    "sg:province":"OH",
    "sg:tags":[
        "forming"
    ],
    "sg:website":"www.vacuforminc.com",
    "wof:name":"Vacuform Inc",
    "wof:placetype":"venue"
},
  "geometry": {"coordinates":[-81.012795,40.919446],"type":"Point"}
}