{
  "type": "Feature",
  "properties": {
    "addr:full":"2757 N Jefferson Blvd Lorain OH 44052",
    "addr:housenumber":"2757",
    "addr:postcode":"44052",
    "addr:street":"N Jefferson Blvd",
    "iso:country":"US",
    "sg:address":"2757 N Jefferson Blvd",
    "sg:city":"Lorain",
    "sg:classifiers":[
        {
            "category":"Building & Trades",
            "subcategory":"Electrical",
            "type":"Services"
        }
    ],
    "sg:phone":"+1 440 288 2622",
    "sg:postcode":"44052",
    "sg:province":"OH",
    "sg:tags":[
        "electrical",
        "contractor"
    ],
    "wof:name":"Verns Electrical Service",
    "wof:placetype":"venue"
},
  "geometry": {"coordinates":[-82.142222,41.478293],"type":"Point"}
}