{
  "type": "Feature",
  "properties": {
    "iso:country":"US",
    "sg:address":"513 3rd St",
    "sg:city":"Painesville",
    "sg:classifiers":[
        {
            "category":"Shopping",
            "subcategory":"Clothing, Apparel, & Fashions",
            "type":"Retail Goods"
        }
    ],
    "sg:phone":"+1 440 354 5384",
    "sg:postcode":"44077",
    "sg:province":"OH",
    "wof:name":"At Harbor Design",
    "wof:placetype":"venue"
},
  "geometry": {"coordinates":[-81.271046,41.755795],"type":"Point"}
}