{
  "type": "Feature",
  "properties": {
    "addr:full": "976 Rakestraw Rd Cedarville OH 45314",
    "addr:housenumber": "976",
    "addr:postcode": "45314",
    "addr:street": "Rakestraw Rd",
    "iso:country": "US",
    "sg:address": "976 Rakestraw Rd",
    "sg:city": "Cedarville",
    "sg:phone": "+1 937 766 4777",
    "sg:postcode": "45314",
    "sg:province": "OH",
    "sg:tags": [
      "hog",
      "farm",
      "cash",
      "grain",
      "or",
      "feedlot"
    ],
    "wof:name": "Witt Farms Ltd",
    "wof:placetype": "venue"
  },
  "geometry": {"coordinates":[-83.79219,39.705393],"type":"Point"}
}
