{
  "type": "Feature",
  "properties": {
    "iso:country":"US",
    "sg:address":"976 Rakestraw Rd",
    "sg:city":"Cedarville",
    "sg:phone":"+1 937 766 4777",
    "sg:postcode":"45314",
    "sg:province":"OH",
    "sg:tags":[
        "hog",
        "farm",
        "cash",
        "grain",
        "or",
        "feedlot"
    ],
    "wof:name":"Witt Farms Ltd",
    "wof:placetype":"venue"
},
  "geometry": {"coordinates":[-83.79219000000001,39.705393],"type":"Point"}
}