{
  "type": "Feature",
  "properties": {
    "addr:full":"980 State Rte 53 Tiffin OH 44883",
    "addr:housenumber":"980",
    "addr:postcode":"44883",
    "addr:street":"State Rte 53",
    "iso:country":"US",
    "sg:address":"980 State Rte 53",
    "sg:city":"Tiffin",
    "sg:classifiers":[
        {
            "category":"Building & Trades",
            "subcategory":"Construction",
            "type":"Services"
        }
    ],
    "sg:phone":"+1 419 448 8525",
    "sg:postcode":"44883",
    "sg:province":"OH",
    "sg:tags":[
        "contractor"
    ],
    "wof:name":"First Gen Svcs Cntl Nthrn Ohio",
    "wof:placetype":"venue"
},
  "geometry": {"coordinates":[-83.169088,41.138499],"type":"Point"}
}