{
  "type": "Feature",
  "properties": {
    "iso:country":"US",
    "sg:address":"4696 Gallia Pike",
    "sg:city":"Franklin Furnace",
    "sg:classifiers":[
        {
            "category":"Social Services",
            "type":"Services"
        }
    ],
    "sg:phone":"+1 740 354 9799",
    "sg:postcode":"45629",
    "sg:province":"OH",
    "sg:tags":[
        "government"
    ],
    "wof:name":"Ohio River Valley Youth Svc",
    "wof:placetype":"venue"
},
  "geometry": {"coordinates":[-82.843793,38.622376],"type":"Point"}
}