{
  "type": "Feature",
  "properties": {
    "addr:full": "15339 Munn Rd Newbury OH 44065",
    "addr:housenumber": "15339",
    "addr:postcode": "44065",
    "addr:street": "Munn Rd",
    "iso:country": "US",
    "sg:address": "15339 Munn Rd",
    "sg:city": "Newbury",
    "sg:phone": "+1 440 564 7368",
    "sg:postcode": "44065",
    "sg:province": "OH",
    "sg:tags": [
      "beef",
      "farm",
      "corn",
      "crop",
      "field",
      "cattle",
      "feedlot"
    ],
    "wof:name": "Rolling Meadows",
    "wof:placetype": "venue"
  },
  "geometry": {"coordinates":[-81.273459,41.463241],"type":"Point"}
}
