{
  "type": "Feature",
  "properties": {
    "addr:full":"559 Liberty Hill Cincinnati OH 45210",
    "addr:housenumber":"559",
    "addr:postcode":"45210",
    "addr:street":"Liberty Hill",
    "iso:country":"US",
    "sg:address":"559 Liberty Hill",
    "sg:city":"Cincinnati",
    "sg:classifiers":[
        {
            "category":"Professional",
            "subcategory":"Computer Services",
            "type":"Services"
        }
    ],
    "sg:phone":"+1 513 333 0211",
    "sg:postcode":"45210",
    "sg:province":"OH",
    "sg:tags":[
        "website",
        "design"
    ],
    "sg:website":"www.innersync.net",
    "wof:name":"Innersync",
    "wof:placetype":"venue"
},
  "geometry": {"coordinates":[-84.5051,39.112235],"type":"Point"}
}