{
  "type": "Feature",
  "properties": {
    "iso:country":"US",
    "sg:address":"2637 Glenwood Ave",
    "sg:city":"Youngstown",
    "sg:classifiers":[
        {
            "category":"Autos & Motor Vehicles",
            "subcategory":"Fuel & Gas Station",
            "type":"Retail Goods"
        }
    ],
    "sg:phone":"+1 330 788 0983",
    "sg:postcode":"44511",
    "sg:province":"OH",
    "sg:tags":[
        "oil"
    ],
    "wof:name":"Scott's Amoco",
    "wof:placetype":"venue"
},
  "geometry": {"coordinates":[-80.67525,41.073215],"type":"Point"}
}