{
  "type": "Feature",
  "properties": {
    "addr:full": "4020 Milan Rd Sandusky OH 44870",
    "addr:housenumber": "4020",
    "addr:postcode": "44870",
    "addr:street": "Milan Rd",
    "iso:country": "US",
    "sg:address": "4020 Milan Rd",
    "sg:city": "Sandusky",
    "sg:classifiers": [
      {
        "category": "Wholesale",
        "subcategory": "Machinery \u0026 Supplies",
        "type": "Manufacturing \u0026 Wholesale Goods"
      },
      {
        "category": "Shopping",
        "subcategory": "Beauty \u0026 Cosmetics",
        "type": "Retail Goods"
      }
    ],
    "sg:phone": "+1 419 624 0076",
    "sg:postcode": "44870",
    "sg:province": "OH",
    "sg:tags": [
      "equipment",
      "salon"
    ],
    "wof:name": "Barnum Beauty Supply",
    "wof:placetype": "venue"
  },
  "geometry": {"coordinates":[-82.676808,41.420985],"type":"Point"}
}
