{
  "type": "Feature",
  "properties": {
    "iso:country":"US",
    "sg:address":"4020 Milan Rd",
    "sg:city":"Sandusky",
    "sg:classifiers":[
        {
            "category":"Wholesale",
            "subcategory":"Machinery & Supplies",
            "type":"Manufacturing & Wholesale Goods"
        },
        {
            "category":"Shopping",
            "subcategory":"Beauty & Cosmetics",
            "type":"Retail Goods"
        }
    ],
    "sg:phone":"+1 419 624 0076",
    "sg:postcode":"44870",
    "sg:province":"OH",
    "sg:tags":[
        "equipment",
        "salon"
    ],
    "wof:name":"Barnum Beauty Supply",
    "wof:placetype":"venue"
},
  "geometry": {"coordinates":[-82.67680799999999,41.420985],"type":"Point"}
}