{
  "type": "Feature",
  "properties": {
    "iso:country":"US",
    "sg:address":"2801 N High St",
    "sg:city":"Columbus",
    "sg:classifiers":[
        {
            "category":"Banks & Credit Unions",
            "subcategory":"Bank",
            "type":"Services"
        }
    ],
    "sg:phone":"+1 614 248 2111",
    "sg:postcode":"43202",
    "sg:province":"OH",
    "wof:name":"Chase",
    "wof:placetype":"venue"
},
  "geometry": {"coordinates":[-83.01271199999999,40.019631],"type":"Point"}
}