{
  "type": "Feature",
  "properties": {
    "iso:country":"US",
    "sg:address":"2622 S Denmark Rd",
    "sg:city":"Jefferson",
    "sg:classifiers":[
        {
            "category":"Restaurant",
            "type":"Food & Drink"
        }
    ],
    "sg:phone":"+1 440 858 9524",
    "sg:postcode":"44047",
    "sg:province":"OH",
    "wof:name":"Simply Cheesecakes",
    "wof:placetype":"venue"
},
  "geometry": {"coordinates":[-80.693292,41.717661],"type":"Point"}
}