{
  "type": "Feature",
  "properties": {
    "addr:full": "4521 Willow Pkwy Cleveland OH 44125",
    "addr:housenumber": "4521",
    "addr:postcode": "44125",
    "addr:street": "Willow Pkwy",
    "iso:country": "US",
    "sg:address": "4521 Willow Pkwy",
    "sg:city": "Cleveland",
    "sg:classifiers": [
      {
        "category": "Wholesale",
        "subcategory": "Metals \u0026 Minerals",
        "type": "Manufacturing \u0026 Wholesale Goods"
      }
    ],
    "sg:phone": "+1 216 641 9339",
    "sg:postcode": "44125",
    "sg:province": "OH",
    "sg:tags": [
      "steel",
      "warehouse"
    ],
    "sg:website": "www.victorytube.com",
    "wof:name": "Victory Tube Co",
    "wof:placetype": "venue"
  },
  "geometry": {"coordinates":[-81.651597,41.437976],"type":"Point"}
}
