{
  "type": "Feature",
  "properties": {
    "addr:full": "123 S Broad St Lancaster OH 43130",
    "addr:housenumber": "123",
    "addr:postcode": "43130",
    "addr:street": "S Broad St",
    "iso:country": "US",
    "sg:address": "123 S Broad St",
    "sg:city": "Lancaster",
    "sg:classifiers": [
      {
        "category": "Government",
        "subcategory": "Office",
        "type": "Public Place"
      }
    ],
    "sg:phone": "+1 740 653 6285",
    "sg:postcode": "43130",
    "sg:province": "OH",
    "sg:tags": [
      "armed",
      "force",
      "recruiting"
    ],
    "wof:name": "US Army Recruiting",
    "wof:placetype": "venue"
  },
  "geometry": {"coordinates":[-82.602017,39.713444],"type":"Point"}
}
