{
  "type": "Feature",
  "properties": {
    "addr:full":"3337 W Erie Ave Lorain OH 44053",
    "addr:housenumber":"3337",
    "addr:postcode":"44053",
    "addr:street":"W Erie Ave",
    "iso:country":"US",
    "sg:address":"3337 W Erie Ave",
    "sg:city":"Lorain",
    "sg:classifiers":[
        {
            "category":"Manufacturing",
            "subcategory":"Metals",
            "type":"Manufacturing & Wholesale Goods"
        }
    ],
    "sg:phone":"+1 440 244 4392",
    "sg:postcode":"44053",
    "sg:province":"OH",
    "sg:tags":[
        "pipeline",
        "mfg",
        "valve",
        "regulator",
        "pressure",
        "s",
        "trap",
        "steam"
    ],
    "wof:name":"Spirax Sarco Inc",
    "wof:placetype":"venue"
},
  "geometry": {"coordinates":[-82.21516200000001,41.452215],"type":"Point"}
}