{
  "type": "Feature",
  "properties": {
    "iso:country":"US",
    "sg:address":"920 Clairmont Ave",
    "sg:city":"Napoleon",
    "sg:classifiers":[
        {
            "category":"Professional",
            "type":"Services"
        }
    ],
    "sg:phone":"+1 419 599 8430",
    "sg:postcode":"43545",
    "sg:province":"OH",
    "wof:name":"Dave Schlade Bldg",
    "wof:placetype":"venue"
},
  "geometry": {"coordinates":[-84.141341,41.391537],"type":"Point"}
}