{
  "type": "Feature",
  "properties": {
    "addr:full": "920 Clairmont Ave Napoleon OH 43545",
    "addr:housenumber": "920",
    "addr:postcode": "43545",
    "addr:street": "Clairmont Ave",
    "iso:country": "US",
    "sg:address": "920 Clairmont Ave",
    "sg:city": "Napoleon",
    "sg:classifiers": [
      {
        "category": "Professional",
        "type": "Services"
      }
    ],
    "sg:phone": "+1 419 599 8430",
    "sg:postcode": "43545",
    "sg:province": "OH",
    "wof:name": "Dave Schlade Bldg",
    "wof:placetype": "venue"
  },
  "geometry": {"coordinates":[-84.141341,41.391537],"type":"Point"}
}
