{
  "type": "Feature",
  "properties": {
    "addr:full": "9150 Broadview Rd Broadview Heights OH 44147",
    "addr:housenumber": "9150",
    "addr:postcode": "44147",
    "addr:street": "Broadview Rd",
    "iso:country": "US",
    "sg:address": "9150 Broadview Rd",
    "sg:city": "Broadview Heights",
    "sg:classifiers": [
      {
        "category": "Banks \u0026 Credit Unions",
        "subcategory": "Bank",
        "type": "Services"
      }
    ],
    "sg:phone": "+1 516 812 4201",
    "sg:postcode": "44147",
    "sg:province": "OH",
    "sg:tags": [
      "banker",
      "mortgage"
    ],
    "wof:name": "Fidelity Mortgage Inc",
    "wof:placetype": "venue"
  },
  "geometry": {"coordinates":[-81.684762,41.314926],"type":"Point"}
}
