{
  "type": "Feature",
  "properties": {
    "iso:country":"US",
    "sg:address":"143 Foxfield Ct",
    "sg:city":"Lima",
    "sg:classifiers":[
        {
            "category":"Freight",
            "type":"Transportation"
        }
    ],
    "sg:phone":"+1 419 228 8399",
    "sg:postcode":"45804",
    "sg:province":"OH",
    "wof:name":"Ju Mar Transportation Inc",
    "wof:placetype":"venue"
},
  "geometry": {"coordinates":[-84.05398,40.733604],"type":"Point"}
}