{
  "type": "Feature",
  "properties": {
    "addr:full": "7420 Harrison Ave Cincinnati OH 45231",
    "addr:housenumber": "7420",
    "addr:postcode": "45231",
    "addr:street": "Harrison Ave",
    "iso:country": "US",
    "sg:address": "7420 Harrison Ave",
    "sg:city": "Cincinnati",
    "sg:classifiers": [
      {
        "category": "Building \u0026 Trades",
        "subcategory": "Construction",
        "type": "Services"
      }
    ],
    "sg:phone": "+1 513 521 7665",
    "sg:postcode": "45231",
    "sg:province": "OH",
    "sg:tags": [
      "new",
      "general",
      "commercial",
      "contractor"
    ],
    "wof:name": "Bittner Construction Inc",
    "wof:placetype": "venue"
  },
  "geometry": {"coordinates":[-84.549524,39.231274],"type":"Point"}
}
