{
  "type": "Feature",
  "properties": {
    "iso:country":"US",
    "sg:address":"7420 Harrison Ave",
    "sg:city":"Cincinnati",
    "sg:classifiers":[
        {
            "category":"Building & Trades",
            "subcategory":"Construction",
            "type":"Services"
        }
    ],
    "sg:phone":"+1 513 521 7665",
    "sg:postcode":"45231",
    "sg:province":"OH",
    "sg:tags":[
        "new",
        "general",
        "commercial",
        "contractor"
    ],
    "wof:name":"Bittner Construction Inc",
    "wof:placetype":"venue"
},
  "geometry": {"coordinates":[-84.54952400000001,39.231274],"type":"Point"}
}