{
  "type": "Feature",
  "properties": {
    "addr:full": "517 Carson Ave Grand River OH 44045",
    "addr:housenumber": "517",
    "addr:postcode": "44045",
    "addr:street": "Carson Ave",
    "iso:country": "US",
    "sg:address": "517 Carson Ave",
    "sg:city": "Grand River",
    "sg:classifiers": [
      {
        "category": "Freight",
        "type": "Transportation"
      }
    ],
    "sg:phone": "+1 440 357 6704",
    "sg:postcode": "44045",
    "sg:province": "OH",
    "sg:tags": [
      "trucking"
    ],
    "wof:name": "Joseph Rini \u0026 Daughter",
    "wof:placetype": "venue"
  },
  "geometry": {"coordinates":[-81.282613,41.735071],"type":"Point"}
}
