{
  "type": "Feature",
  "properties": {
    "addr:full":"191 E Market St Tiffin OH 44883",
    "addr:housenumber":"191",
    "addr:postcode":"44883",
    "addr:street":"E Market St",
    "iso:country":"US",
    "sg:address":"191 E Market St",
    "sg:city":"Tiffin",
    "sg:classifiers":[
        {
            "category":"Organizations",
            "subcategory":"Membership Organization",
            "type":"Services"
        }
    ],
    "sg:phone":"+1 419 447 0551",
    "sg:postcode":"44883",
    "sg:province":"OH",
    "sg:tags":[
        "travel",
        "agency"
    ],
    "wof:name":"AAA Travel Agency",
    "wof:placetype":"venue"
},
  "geometry": {"coordinates":[-83.174362,41.114819],"type":"Point"}
}