{
  "type": "Feature",
  "properties": {
    "addr:full":"2713 Fulton Dr NW Canton OH 44718",
    "addr:housenumber":"2713",
    "addr:postcode":"44718",
    "addr:street":"Fulton Dr Nw",
    "iso:country":"US",
    "sg:address":"2713 Fulton Dr NW",
    "sg:city":"Canton",
    "sg:classifiers":[
        {
            "category":"Retail",
            "subcategory":"Repair Shop",
            "type":"Services"
        }
    ],
    "sg:phone":"+1 330 452 9194",
    "sg:postcode":"44718",
    "sg:province":"OH",
    "sg:tags":[
        "lock",
        "locksmith"
    ],
    "wof:name":"M & N Bierlys Lock & Door",
    "wof:placetype":"venue"
},
  "geometry": {"coordinates":[-81.40242499999999,40.826763],"type":"Point"}
}