{
  "type": "Feature",
  "properties": {
    "addr:full": "923 Walnut St New Bavaria OH 43548",
    "addr:housenumber": "923",
    "addr:postcode": "43548",
    "addr:street": "Walnut St",
    "iso:country": "US",
    "sg:address": "923 Walnut St",
    "sg:city": "New Bavaria",
    "sg:classifiers": [
      {
        "category": "Retail",
        "subcategory": "Auto Repair",
        "type": "Services"
      }
    ],
    "sg:phone": "+1 419 653 4181",
    "sg:postcode": "43548",
    "sg:province": "OH",
    "sg:tags": [
      "repairing",
      "automobile"
    ],
    "wof:name": "Chuck's Svc",
    "wof:placetype": "venue"
  },
  "geometry": {"coordinates":[-84.169338,41.204085],"type":"Point"}
}
