{
  "type": "Feature",
  "properties": {
    "addr:full": "31 S Norwich Rd Troy OH 45373",
    "addr:housenumber": "31",
    "addr:postcode": "45373",
    "addr:street": "S Norwich Rd",
    "iso:country": "US",
    "sg:address": "31 S Norwich Rd",
    "sg:city": "Troy",
    "sg:classifiers": [
      {
        "category": "Real Estate",
        "subcategory": "Real Estate Agent",
        "type": "Services"
      }
    ],
    "sg:phone": "+1 937 335 2522",
    "sg:postcode": "45373",
    "sg:province": "OH",
    "wof:name": "Garden Gate Realty Inc",
    "wof:placetype": "venue"
  },
  "geometry": {"coordinates":[-84.22568,40.049044],"type":"Point"}
}
