{
  "type": "Feature",
  "properties": {
    "addr:full": "14221 Co Rd 12 Rawson OH 45817",
    "addr:housenumber": "14221;12",
    "addr:postcode": "45817",
    "addr:street": "Co Rd",
    "iso:country": "US",
    "sg:address": "14221 Co Rd 12",
    "sg:city": "Rawson",
    "sg:classifiers": [
      {
        "category": "Organizations",
        "subcategory": "Religious Organization",
        "type": "Services"
      }
    ],
    "sg:phone": "+1 419 963 2842",
    "sg:postcode": "45817",
    "sg:province": "OH",
    "sg:tags": [
      "church"
    ],
    "wof:name": "New Hope United Methodist",
    "wof:placetype": "venue"
  },
  "geometry": {"coordinates":[-83.785143,40.963376],"type":"Point"}
}
