{
  "type": "Feature",
  "properties": {
    "iso:country":"US",
    "sg:address":"5135 Urbana Moorefield Pike",
    "sg:city":"Urbana",
    "sg:classifiers":[
        {
            "category":"Shopping",
            "subcategory":"Catalog Store",
            "type":"Retail Goods"
        }
    ],
    "sg:phone":"+1 937 484 3322",
    "sg:postcode":"43078",
    "sg:province":"OH",
    "sg:tags":[
        "mail",
        "house"
    ],
    "wof:name":"Gradys Gun Shop",
    "wof:placetype":"venue"
},
  "geometry": {"coordinates":[-83.729427,40.03429],"type":"Point"}
}