{
  "type": "Feature",
  "properties": {
    "iso:country":"US",
    "sg:address":"7121 Hart St",
    "sg:city":"Mentor",
    "sg:classifiers":[
        {
            "category":"Retail",
            "subcategory":"Auto Rental",
            "type":"Services"
        }
    ],
    "sg:phone":"+1 440 974 8361",
    "sg:postcode":"44060",
    "sg:province":"OH",
    "sg:tags":[
        "renting",
        "truck",
        "leasing"
    ],
    "wof:name":"U-Haul Co",
    "wof:placetype":"venue"
},
  "geometry": {"coordinates":[-81.338264,41.678484],"type":"Point"}
}