{
  "type": "Feature",
  "properties": {
    "iso:country":"US",
    "sg:address":"1248 W 3rd Ave",
    "sg:city":"Columbus",
    "sg:classifiers":[
        {
            "category":"Bars & Pubs",
            "type":"Food & Drink"
        }
    ],
    "sg:phone":"+1 614 486 4722",
    "sg:postcode":"43212",
    "sg:province":"OH",
    "wof:name":"Byrne's Pub",
    "wof:placetype":"venue"
},
  "geometry": {"coordinates":[-83.038625,39.984917],"type":"Point"}
}