{
  "type": "Feature",
  "properties": {
    "iso:country":"US",
    "sg:address":"634 Infantry Dr",
    "sg:city":"Galloway",
    "sg:classifiers":[
        {
            "category":"Professional",
            "subcategory":"Management & Consulting",
            "type":"Services"
        }
    ],
    "sg:phone":"+1 614 851 1006",
    "sg:postcode":"43119",
    "sg:province":"OH",
    "sg:tags":[
        "personnel",
        "consultant"
    ],
    "wof:name":"M D Staffing",
    "wof:placetype":"venue"
},
  "geometry": {"coordinates":[-83.226692,39.962155],"type":"Point"}
}