{
  "type": "Feature",
  "properties": {
    "iso:country":"US",
    "sg:address":"1553 Cambridge Blvd",
    "sg:city":"Columbus",
    "sg:classifiers":[
        {
            "category":"Freight",
            "type":"Transportation"
        }
    ],
    "sg:phone":"+1 614 246 5771",
    "sg:postcode":"43212",
    "sg:province":"OH",
    "sg:tags":[
        "hauling",
        "trucking"
    ],
    "wof:name":"LYT Expedite",
    "wof:placetype":"venue"
},
  "geometry": {"coordinates":[-83.057824,39.987929],"type":"Point"}
}