{
  "type": "Feature",
  "properties": {
    "iso:country":"US",
    "sg:address":"1915 Central Ave",
    "sg:city":"Middletown",
    "sg:classifiers":[
        {
            "category":"Shopping",
            "subcategory":"Pharmacy",
            "type":"Retail Goods"
        }
    ],
    "sg:phone":"+1 513 420 2546",
    "sg:postcode":"45044",
    "sg:province":"OH",
    "wof:name":"Rite Aid Pharmacy",
    "wof:placetype":"venue"
},
  "geometry": {"coordinates":[-84.391791,39.513196],"type":"Point"}
}