{
  "type": "Feature",
  "properties": {
    "iso:country":"US",
    "sg:address":"10643 Saint Clair Ave",
    "sg:city":"Cleveland",
    "sg:classifiers":[
        {
            "category":"Manufacturing",
            "subcategory":"Motor Vehicles & Parts",
            "type":"Manufacturing & Wholesale Goods"
        }
    ],
    "sg:phone":"+1 216 451 5060",
    "sg:postcode":"44108",
    "sg:province":"OH",
    "sg:tags":[
        "mfg"
    ],
    "wof:name":"Strictly Bus Auto Accessorie",
    "wof:placetype":"venue"
},
  "geometry": {"coordinates":[-81.612262,41.540069],"type":"Point"}
}