{
  "type": "Feature",
  "properties": {
    "addr:full":"68 Olive St Chagrin Falls OH 44022",
    "addr:housenumber":"68",
    "addr:postcode":"44022",
    "addr:street":"Olive St",
    "iso:country":"US",
    "sg:address":"68 Olive St",
    "sg:city":"Chagrin Falls",
    "sg:classifiers":[
        {
            "category":"Professional",
            "subcategory":"Advertising",
            "type":"Services"
        }
    ],
    "sg:phone":"+1 440 247 6096",
    "sg:postcode":"44022",
    "sg:province":"OH",
    "wof:name":"60 Second Street Advertising",
    "wof:placetype":"venue"
},
  "geometry": {"coordinates":[-81.39366099999999,41.425394],"type":"Point"}
}