{
  "type": "Feature",
  "properties": {
    "addr:full": "15 S 2nd St Ripley OH 45167",
    "addr:housenumber": "15",
    "addr:postcode": "45167",
    "addr:street": "S 2Nd St",
    "iso:country": "US",
    "sg:address": "15 S 2nd St",
    "sg:city": "Ripley",
    "sg:classifiers": [
      {
        "category": "Restaurant",
        "type": "Food \u0026 Drink"
      }
    ],
    "sg:phone": "+1 937 392 9328",
    "sg:postcode": "45167",
    "sg:province": "OH",
    "sg:tags": [
      "eating"
    ],
    "wof:name": "50s Diner",
    "wof:placetype": "venue"
  },
  "geometry": {"coordinates":[-83.845255,38.745419],"type":"Point"}
}
