{
  "type": "Feature",
  "properties": {
    "addr:full": "206 Infirmary Rd Dayton OH 45427",
    "addr:housenumber": "206",
    "addr:postcode": "45427",
    "addr:street": "Infirmary Rd",
    "iso:country": "US",
    "sg:address": "206 Infirmary Rd",
    "sg:city": "Dayton",
    "sg:classifiers": [
      {
        "category": "Wholesale",
        "subcategory": "Auto Parts",
        "type": "Manufacturing \u0026 Wholesale Goods"
      }
    ],
    "sg:phone": "+1 937 263 5568",
    "sg:postcode": "45427",
    "sg:province": "OH",
    "sg:tags": [
      "used"
    ],
    "wof:name": "Imports Only",
    "wof:placetype": "venue"
  },
  "geometry": {"coordinates":[-84.281172,39.744747],"type":"Point"}
}
