{
  "type": "Feature",
  "properties": {
    "iso:country":"US",
    "sg:address":"2774 Bailey Rd",
    "sg:city":"Cuyahoga Falls",
    "sg:classifiers":[
        {
            "category":"Building & Trades",
            "subcategory":"Construction",
            "type":"Services"
        }
    ],
    "sg:phone":"+1 330 929 9271",
    "sg:postcode":"44221",
    "sg:province":"OH",
    "sg:tags":[
        "contractor"
    ],
    "wof:name":"Christine & Bradley Matts",
    "wof:placetype":"venue"
},
  "geometry": {"coordinates":[-81.478445,41.148589],"type":"Point"}
}