{
  "type": "Feature",
  "properties": {
    "iso:country":"US",
    "sg:address":"7188 State Rte 39",
    "sg:city":"Millersburg",
    "sg:classifiers":[
        {
            "category":"Mining & Drilling",
            "type":"Manufacturing & Wholesale Goods"
        }
    ],
    "sg:phone":"+1 330 674 0322",
    "sg:postcode":"44654",
    "sg:province":"OH",
    "sg:tags":[
        "oil",
        "gas",
        "producer"
    ],
    "wof:name":"Bijoe Development",
    "wof:placetype":"venue"
},
  "geometry": {"coordinates":[-81.88233099999999,40.555043],"type":"Point"}
}