{
  "type": "Feature",
  "properties": {
    "addr:full": "7188 State Rte 39 Millersburg OH 44654",
    "addr:housenumber": "7188",
    "addr:postcode": "44654",
    "addr:street": "State Rte 39",
    "iso:country": "US",
    "sg:address": "7188 State Rte 39",
    "sg:city": "Millersburg",
    "sg:classifiers": [
      {
        "category": "Mining \u0026 Drilling",
        "type": "Manufacturing \u0026 Wholesale Goods"
      }
    ],
    "sg:phone": "+1 330 674 0322",
    "sg:postcode": "44654",
    "sg:province": "OH",
    "sg:tags": [
      "oil",
      "gas",
      "producer"
    ],
    "wof:name": "Bijoe Development",
    "wof:placetype": "venue"
  },
  "geometry": {"coordinates":[-81.882331,40.555043],"type":"Point"}
}
