{
  "type": "Feature",
  "properties": {
    "addr:full": "1391 S Union Rd Dayton OH 45427",
    "addr:housenumber": "1391",
    "addr:postcode": "45427",
    "addr:street": "S Union Rd",
    "iso:country": "US",
    "sg:address": "1391 S Union Rd",
    "sg:city": "Dayton",
    "sg:classifiers": [
      {
        "category": "Shopping",
        "type": "Retail Goods"
      }
    ],
    "sg:phone": "+1 937 835 3419",
    "sg:postcode": "45427",
    "sg:province": "OH",
    "sg:tags": [
      "pet",
      "shop"
    ],
    "wof:name": "Allbreed Dog Obedience Trng",
    "wof:placetype": "venue"
  },
  "geometry": {"coordinates":[-84.309331,39.726724],"type":"Point"}
}
