{
  "type": "Feature",
  "properties": {
    "iso:country":"US",
    "sg:address":"131 Main St",
    "sg:city":"Steubenville",
    "sg:classifiers":[
        {
            "category":"Restaurant",
            "type":"Food & Drink"
        }
    ],
    "sg:phone":"+1 740 264 4042",
    "sg:postcode":"43953",
    "sg:province":"OH",
    "sg:tags":[
        "eating"
    ],
    "wof:name":"Dippity Dawg",
    "wof:placetype":"venue"
},
  "geometry": {"coordinates":[-80.687148,40.371429],"type":"Point"}
}