{
  "type": "Feature",
  "properties": {
    "addr:full": "131 Main St Steubenville OH 43953",
    "addr:housenumber": "131",
    "addr:postcode": "43953",
    "addr:street": "Main St",
    "iso:country": "US",
    "sg:address": "131 Main St",
    "sg:city": "Steubenville",
    "sg:classifiers": [
      {
        "category": "Restaurant",
        "type": "Food \u0026 Drink"
      }
    ],
    "sg:phone": "+1 740 264 4042",
    "sg:postcode": "43953",
    "sg:province": "OH",
    "sg:tags": [
      "eating"
    ],
    "wof:name": "Dippity Dawg",
    "wof:placetype": "venue"
  },
  "geometry": {"coordinates":[-80.687148,40.371429],"type":"Point"}
}
