{
  "type": "Feature",
  "properties": {
    "addr:full":"6772 State Rte 4 Attica OH 44807",
    "addr:housenumber":"6772",
    "addr:postcode":"44807",
    "addr:street":"State Rte 4",
    "iso:country":"US",
    "sg:address":"6772 State Rte 4",
    "sg:city":"Attica",
    "sg:classifiers":[
        {
            "category":"Government",
            "subcategory":"Office",
            "type":"Public Place"
        }
    ],
    "sg:phone":"+1 419 426 1010",
    "sg:postcode":"44807",
    "sg:province":"OH",
    "sg:tags":[
        "state",
        "program"
    ],
    "wof:name":"Transportation Dept",
    "wof:placetype":"venue"
},
  "geometry": {"coordinates":[-82.905312,41.028744],"type":"Point"}
}