{
  "type": "Feature",
  "properties": {
    "iso:country":"US",
    "sg:address":"2125 Sandston Rd",
    "sg:city":"Columbus",
    "sg:classifiers":[
        {
            "category":"Building & Trades",
            "subcategory":"Construction",
            "type":"Services"
        }
    ],
    "sg:phone":"+1 614 459 4179",
    "sg:postcode":"43220",
    "sg:province":"OH",
    "sg:tags":[
        "commercial",
        "contractor"
    ],
    "wof:name":"Professional Property Maint",
    "wof:placetype":"venue"
},
  "geometry": {"coordinates":[-83.07933,40.05433],"type":"Point"}
}