{
  "type": "Feature",
  "properties": {
    "addr:full":"620 Lovers Ln Wintersville OH 43953",
    "addr:housenumber":"620",
    "addr:postcode":"43953",
    "addr:street":"Lovers Ln",
    "iso:country":"US",
    "sg:address":"620 Lovers Ln",
    "sg:city":"Wintersville",
    "sg:classifiers":[
        {
            "category":"Organizations",
            "subcategory":"Religious Organization",
            "type":"Services"
        }
    ],
    "sg:phone":"+1 740 266 2748",
    "sg:postcode":"43953",
    "sg:province":"OH",
    "sg:tags":[
        "clergy"
    ],
    "wof:name":"Stephen A Modranski III",
    "wof:placetype":"venue"
},
  "geometry": {"coordinates":[-80.66573099999999,40.356635],"type":"Point"}
}