{
  "type": "Feature",
  "properties": {
    "addr:full":"7433 State Rte 101 Clyde OH 43410",
    "addr:housenumber":"7433",
    "addr:postcode":"43410",
    "addr:street":"State Rte 101",
    "iso:country":"US",
    "sg:address":"7433 State Rte 101",
    "sg:city":"Clyde",
    "sg:classifiers":[
        {
            "category":"Utilities",
            "subcategory":"Refuse",
            "type":"Services"
        }
    ],
    "sg:phone":"+1 419 547 9219",
    "sg:postcode":"43410",
    "sg:province":"OH",
    "sg:tags":[
        "system"
    ],
    "wof:name":"American Plastics",
    "wof:placetype":"venue"
},
  "geometry": {"coordinates":[-82.85298400000001,41.36888],"type":"Point"}
}