{
  "type": "Feature",
  "properties": {
    "addr:full":"11330 Mosteller Rd Cincinnati OH 45241",
    "addr:housenumber":"11330",
    "addr:postcode":"45241",
    "addr:street":"Mosteller Rd",
    "iso:country":"US",
    "sg:address":"11330 Mosteller Rd",
    "sg:city":"Cincinnati",
    "sg:classifiers":[
        {
            "category":"Wholesale",
            "subcategory":"Machinery & Supplies",
            "type":"Manufacturing & Wholesale Goods"
        }
    ],
    "sg:phone":"+1 513 771 0515",
    "sg:postcode":"45241",
    "sg:province":"OH",
    "sg:tags":[
        "equipment"
    ],
    "wof:name":"Ohio Machinery Co",
    "wof:placetype":"venue"
},
  "geometry": {"coordinates":[-84.430053,39.275947],"type":"Point"}
}