{
  "type": "Feature",
  "properties": {
    "iso:country":"US",
    "sg:address":"400 Greenback Rd",
    "sg:city":"Fort Loramie",
    "sg:classifiers":[
        {
            "category":"Building & Trades",
            "subcategory":"Electrical",
            "type":"Services"
        }
    ],
    "sg:phone":"+1 937 295 3381",
    "sg:postcode":"45845",
    "sg:province":"OH",
    "sg:tags":[
        "electrical",
        "electric",
        "contractor"
    ],
    "wof:name":"Boerger Electric Inc",
    "wof:placetype":"venue"
},
  "geometry": {"coordinates":[-84.36417,40.343283],"type":"Point"}
}