{
  "type": "Feature",
  "properties": {
    "addr:full": "150 S Park Ave Warren OH 44481",
    "addr:housenumber": "150",
    "addr:postcode": "44481",
    "addr:street": "S Park Ave",
    "iso:country": "US",
    "sg:address": "150 S Park Ave",
    "sg:city": "Warren",
    "sg:classifiers": [
      {
        "category": "Government",
        "subcategory": "Office",
        "type": "Public Place"
      }
    ],
    "sg:phone": "+1 330 675 2000",
    "sg:postcode": "44481",
    "sg:province": "OH",
    "sg:tags": [
      "county",
      "resource"
    ],
    "wof:name": "Trumbull County Welfare Dept",
    "wof:placetype": "venue"
  },
  "geometry": {"coordinates":[-80.817964,41.2355],"type":"Point"}
}
