{
  "type": "Feature",
  "properties": {
    "addr:full": "6235 Virginia Rd Nashport OH 43830",
    "addr:housenumber": "6235",
    "addr:postcode": "43830",
    "addr:street": "Virginia Rd",
    "iso:country": "US",
    "sg:address": "6235 Virginia Rd",
    "sg:city": "Nashport",
    "sg:classifiers": [
      {
        "category": "Organizations",
        "subcategory": "Religious Organization",
        "type": "Services"
      }
    ],
    "sg:phone": "+1 740 454 7105",
    "sg:postcode": "43830",
    "sg:province": "OH",
    "sg:tags": [
      "clergy"
    ],
    "wof:name": "A Scott Robinson",
    "wof:placetype": "venue"
  },
  "geometry": {"coordinates":[-82.045636,40.036377],"type":"Point"}
}
