{
  "type": "Feature",
  "properties": {
    "addr:full": "4350 Knoll Crest Dr Grove City OH 43123",
    "addr:housenumber": "4350",
    "addr:postcode": "43123",
    "addr:street": "Knoll Crest Dr",
    "iso:country": "US",
    "sg:address": "4350 Knoll Crest Dr",
    "sg:city": "Grove City",
    "sg:classifiers": [
      {
        "category": "Building \u0026 Trades",
        "subcategory": "Construction",
        "type": "Services"
      }
    ],
    "sg:phone": "+1 614 277 9291",
    "sg:postcode": "43123",
    "sg:province": "OH",
    "sg:tags": [
      "home",
      "builder"
    ],
    "wof:name": "Rockford Homes",
    "wof:placetype": "venue"
  },
  "geometry": {"coordinates":[-83.116582,39.905637],"type":"Point"}
}
