{
  "type": "Feature",
  "properties": {
    "iso:country":"US",
    "sg:address":"4350 Knoll Crest Dr",
    "sg:city":"Grove City",
    "sg:classifiers":[
        {
            "category":"Building & Trades",
            "subcategory":"Construction",
            "type":"Services"
        }
    ],
    "sg:phone":"+1 614 277 9291",
    "sg:postcode":"43123",
    "sg:province":"OH",
    "sg:tags":[
        "home",
        "builder"
    ],
    "wof:name":"Rockford Homes",
    "wof:placetype":"venue"
},
  "geometry": {"coordinates":[-83.11658199999999,39.905637],"type":"Point"}
}