{
  "type": "Feature",
  "properties": {
    "addr:full": "9 Sheridan Rd Youngstown OH 44514",
    "addr:housenumber": "9",
    "addr:postcode": "44514",
    "addr:street": "Sheridan Rd",
    "iso:country": "US",
    "sg:address": "9 Sheridan Rd",
    "sg:city": "Youngstown",
    "sg:classifiers": [
      {
        "category": "Retail",
        "subcategory": "Laundry \u0026 Dry Cleaning",
        "type": "Services"
      }
    ],
    "sg:phone": "+1 330 757 2522",
    "sg:postcode": "44514",
    "sg:province": "OH",
    "sg:tags": [
      "drycleaning",
      "plant"
    ],
    "wof:name": "Towne \u0026 Country Dry Cleaners",
    "wof:placetype": "venue"
  },
  "geometry": {"coordinates":[-80.618811,41.028113],"type":"Point"}
}
