{
  "type": "Feature",
  "properties": {
    "iso:country":"US",
    "sg:address":"9 Sheridan Rd",
    "sg:city":"Youngstown",
    "sg:classifiers":[
        {
            "category":"Retail",
            "subcategory":"Laundry & Dry Cleaning",
            "type":"Services"
        }
    ],
    "sg:phone":"+1 330 757 2522",
    "sg:postcode":"44514",
    "sg:province":"OH",
    "sg:tags":[
        "drycleaning",
        "plant"
    ],
    "wof:name":"Towne & Country Dry Cleaners",
    "wof:placetype":"venue"
},
  "geometry": {"coordinates":[-80.618811,41.028113],"type":"Point"}
}