{
  "type": "Feature",
  "properties": {
    "iso:country":"US",
    "sg:address":"2388 County Line Rd",
    "sg:city":"Madison",
    "sg:classifiers":[
        {
            "category":"Building & Trades",
            "subcategory":"Construction",
            "type":"Services"
        }
    ],
    "sg:phone":"+1 440 466 1776",
    "sg:postcode":"44057",
    "sg:province":"OH",
    "sg:tags":[
        "excavating",
        "contractor"
    ],
    "wof:name":"Eagle Excavating Inc",
    "wof:placetype":"venue"
},
  "geometry": {"coordinates":[-81.002492,41.78826],"type":"Point"}
}