{
  "type": "Feature",
  "properties": {
    "addr:full": "226 Wengler Ave Sharon OH 16146",
    "addr:housenumber": "226",
    "addr:postcode": "16146",
    "addr:street": "Wengler Ave",
    "iso:country": "US",
    "sg:address": "226 Wengler Ave",
    "sg:city": "Sharon",
    "sg:classifiers": [
      {
        "category": "Building \u0026 Trades",
        "subcategory": "Landscaping Services",
        "type": "Services"
      }
    ],
    "sg:phone": "+1 724 981 2266",
    "sg:postcode": "16146",
    "sg:province": "OH",
    "sg:tags": [
      "landscape",
      "contractor"
    ],
    "wof:name": "Sunshine \u0026 Co",
    "wof:placetype": "venue"
  },
  "geometry": {"coordinates":[-80.491211,41.229652],"type":"Point"}
}
