{
  "type": "Feature",
  "properties": {
    "iso:country":"US",
    "sg:address":"226 Wengler Ave",
    "sg:city":"Sharon",
    "sg:classifiers":[
        {
            "category":"Building & Trades",
            "subcategory":"Landscaping Services",
            "type":"Services"
        }
    ],
    "sg:phone":"+1 724 981 2266",
    "sg:postcode":"16146",
    "sg:province":"OH",
    "sg:tags":[
        "landscape",
        "contractor"
    ],
    "wof:name":"Sunshine & Co",
    "wof:placetype":"venue"
},
  "geometry": {"coordinates":[-80.49121100000001,41.229652],"type":"Point"}
}