{
  "type": "Feature",
  "properties": {
    "addr:full": "4169 State Rte 122 Franklin OH 45005",
    "addr:housenumber": "4169",
    "addr:postcode": "45005",
    "addr:street": "State Rte 122",
    "iso:country": "US",
    "sg:address": "4169 State Rte 122",
    "sg:city": "Franklin",
    "sg:classifiers": [
      {
        "category": "Shopping",
        "subcategory": "Computers \u0026 Home Electronics",
        "type": "Retail Goods"
      }
    ],
    "sg:phone": "+1 937 746 4911",
    "sg:postcode": "45005",
    "sg:province": "OH",
    "sg:tags": [
      "electronic"
    ],
    "wof:name": "Aqua Doc",
    "wof:placetype": "venue"
  },
  "geometry": {"coordinates":[-84.280917,39.492656],"type":"Point"}
}
