{
  "type": "Feature",
  "properties": {
    "iso:country":"US",
    "sg:address":"7885 E Kemper Rd",
    "sg:city":"Cincinnati",
    "sg:classifiers":[
        {
            "category":"Home & Garden",
            "subcategory":"Furniture",
            "type":"Retail Goods"
        }
    ],
    "sg:phone":"+1 513 489 3887",
    "sg:postcode":"45249",
    "sg:province":"OH",
    "sg:tags":[
        "interior",
        "designer",
        "store"
    ],
    "sg:website":"www.davidamillett.com",
    "wof:name":"David A Millett Inc",
    "wof:placetype":"venue"
},
  "geometry": {"coordinates":[-84.347068,39.279489],"type":"Point"}
}