{
  "type": "Feature",
  "properties": {
    "addr:full":"1187 Valley Forge Dr Milford OH 45150",
    "addr:housenumber":"1187",
    "addr:postcode":"45150",
    "addr:street":"Valley Forge Dr",
    "iso:country":"US",
    "sg:address":"1187 Valley Forge Dr",
    "sg:city":"Milford",
    "sg:classifiers":[
        {
            "category":"Building & Trades",
            "subcategory":"Construction",
            "type":"Services"
        }
    ],
    "sg:phone":"+1 513 248 1187",
    "sg:postcode":"45150",
    "sg:province":"OH",
    "sg:tags":[
        "house"
    ],
    "wof:name":"French Construction LLC Smllc",
    "wof:placetype":"venue"
},
  "geometry": {"coordinates":[-84.232511,39.168942],"type":"Point"}
}