{
  "type": "Feature",
  "properties": {
    "addr:full":"910 River Rd Maumee OH 43537",
    "addr:housenumber":"910",
    "addr:postcode":"43537",
    "addr:street":"River Rd",
    "iso:country":"US",
    "sg:address":"910 River Rd",
    "sg:city":"Maumee",
    "sg:classifiers":[
        {
            "category":"Personal",
            "subcategory":"Beauty Salon",
            "type":"Services"
        }
    ],
    "sg:phone":"+1 419 893 9091",
    "sg:postcode":"43537",
    "sg:province":"OH",
    "sg:tags":[
        "shop"
    ],
    "wof:name":"John Roberts Beauty Salon",
    "wof:placetype":"venue"
},
  "geometry": {"coordinates":[-83.63889399999999,41.571894],"type":"Point"}
}