{
  "type": "Feature",
  "properties": {
    "addr:full":"5050 Middlebranch Ave NE Canton OH 44705",
    "addr:housenumber":"5050",
    "addr:postcode":"44705",
    "addr:street":"Middlebranch Ave Ne",
    "iso:country":"US",
    "sg:address":"5050 Middlebranch Ave NE",
    "sg:city":"Canton",
    "sg:classifiers":[
        {
            "category":"Organizations",
            "subcategory":"Religious Organization",
            "type":"Services"
        }
    ],
    "sg:phone":"+1 330 492 7144",
    "sg:postcode":"44705",
    "sg:province":"OH",
    "sg:tags":[
        "church"
    ],
    "sg:website":"www.gracebaptistcanton.com",
    "wof:name":"Grace Baptist Church",
    "wof:placetype":"venue"
},
  "geometry": {"coordinates":[-81.3377,40.850209],"type":"Point"}
}