{
  "type": "Feature",
  "properties": {
    "addr:full": "1029 Sunbury Lake Dr Westerville OH 43082",
    "addr:housenumber": "1029",
    "addr:postcode": "43082",
    "addr:street": "Sunbury Lake Dr",
    "iso:country": "US",
    "sg:address": "1029 Sunbury Lake Dr",
    "sg:city": "Westerville",
    "sg:classifiers": [
      {
        "category": "Real Estate",
        "subcategory": "Real Estate Agent",
        "type": "Services"
      }
    ],
    "sg:phone": "+1 614 899 1637",
    "sg:postcode": "43082",
    "sg:province": "OH",
    "wof:name": "Greenwell Group Ltd",
    "wof:placetype": "venue"
  },
  "geometry": {"coordinates":[-82.891912,40.140358],"type":"Point"}
}
