{
  "type": "Feature",
  "properties": {
    "addr:full": "110 Baker Ln Franklin OH 45005",
    "addr:housenumber": "110",
    "addr:postcode": "45005",
    "addr:street": "Baker Ln",
    "iso:country": "US",
    "sg:address": "110 Baker Ln",
    "sg:city": "Franklin",
    "sg:classifiers": [
      {
        "category": "Wholesale",
        "subcategory": "Vending Machines",
        "type": "Manufacturing \u0026 Wholesale Goods"
      }
    ],
    "sg:phone": "+1 937 746 8438",
    "sg:postcode": "45005",
    "sg:province": "OH",
    "sg:tags": [
      "operator"
    ],
    "wof:name": "Grab A Snack Vending",
    "wof:placetype": "venue"
  },
  "geometry": {"coordinates":[-84.339778,39.570018],"type":"Point"}
}
