{
  "type": "Feature",
  "properties": {
    "addr:full":"4530 W Mitchell Ave Cincinnati OH 45232",
    "addr:housenumber":"4530",
    "addr:postcode":"45232",
    "addr:street":"W Mitchell Ave",
    "iso:country":"US",
    "sg:address":"4530 W Mitchell Ave",
    "sg:city":"Cincinnati",
    "sg:classifiers":[
        {
            "category":"Wholesale",
            "subcategory":"Meat",
            "type":"Manufacturing & Wholesale Goods"
        }
    ],
    "sg:phone":"+1 513 541 6767",
    "sg:postcode":"45232",
    "sg:province":"OH",
    "wof:name":"HMI Distributors",
    "wof:placetype":"venue"
},
  "geometry": {"coordinates":[-84.51430499999999,39.169832],"type":"Point"}
}