{
  "type": "Feature",
  "properties": {
    "addr:full": "1110 Napoleon St Fremont OH 43420",
    "addr:housenumber": "1110",
    "addr:postcode": "43420",
    "addr:street": "Napoleon St",
    "iso:country": "US",
    "sg:address": "1110 Napoleon St",
    "sg:city": "Fremont",
    "sg:classifiers": [
      {
        "category": "Retail",
        "subcategory": "Auto Repair",
        "type": "Services"
      }
    ],
    "sg:phone": "+1 419 333 1200",
    "sg:postcode": "43420",
    "sg:province": "OH",
    "sg:tags": [
      "transmission"
    ],
    "wof:name": "Parker Sap",
    "wof:placetype": "venue"
  },
  "geometry": {"coordinates":[-83.125025,41.348566],"type":"Point"}
}
