{
  "type": "Feature",
  "properties": {
    "addr:full":"9551 Webb Summit Rd SE Bremen OH 43107",
    "addr:housenumber":"9551",
    "addr:postcode":"43107",
    "addr:street":"Webb Summit Rd Se",
    "iso:country":"US",
    "sg:address":"9551 Webb Summit Rd SE",
    "sg:city":"Bremen",
    "sg:classifiers":[
        {
            "category":"Shopping",
            "type":"Retail Goods"
        }
    ],
    "sg:phone":"+1 740 569 7603",
    "sg:postcode":"43107",
    "sg:province":"OH",
    "sg:tags":[
        "merchandise"
    ],
    "wof:name":"Roys Novelty Shop",
    "wof:placetype":"venue"
},
  "geometry": {"coordinates":[-82.417771,39.679057],"type":"Point"}
}