{
  "type": "Feature",
  "properties": {
    "addr:full": "1951 Edenhall Dr Cleveland OH 44124",
    "addr:housenumber": "1951",
    "addr:postcode": "44124",
    "addr:street": "Edenhall Dr",
    "iso:country": "US",
    "sg:address": "1951 Edenhall Dr",
    "sg:city": "Cleveland",
    "sg:classifiers": [
      {
        "category": "Real Estate",
        "subcategory": "Real Estate Agent",
        "type": "Services"
      }
    ],
    "sg:phone": "+1 440 461 0021",
    "sg:postcode": "44124",
    "sg:province": "OH",
    "wof:name": "Fixler Realty Group Inc",
    "wof:placetype": "venue"
  },
  "geometry": {"coordinates":[-81.482242,41.509248],"type":"Point"}
}
