{
  "type": "Feature",
  "properties": {
    "iso:country":"US",
    "sg:address":"30195 Chagrin Blvd",
    "sg:city":"Cleveland",
    "sg:classifiers":[
        {
            "category":"Banks & Credit Unions",
            "subcategory":"Investment Brokerage",
            "type":"Services"
        },
        {
            "category":"Professional",
            "subcategory":"Management & Consulting",
            "type":"Services"
        }
    ],
    "sg:phone":"+1 216 514 0060",
    "sg:postcode":"44124",
    "sg:province":"OH",
    "sg:tags":[
        "consultant",
        "planning",
        "financial"
    ],
    "wof:name":"H T V Industries Inc",
    "wof:placetype":"venue"
},
  "geometry": {"coordinates":[-81.456829,41.46021],"type":"Point"}
}