{
  "type": "Feature",
  "properties": {
    "iso:country":"US",
    "sg:address":"3659 Dixie Hwy",
    "sg:city":"Hamilton",
    "sg:classifiers":[
        {
            "category":"Autos & Motor Vehicles",
            "subcategory":"Automobile Sales",
            "type":"Retail Goods"
        }
    ],
    "sg:phone":"+1 513 737 1126",
    "sg:postcode":"45015",
    "sg:province":"OH",
    "sg:tags":[
        "car",
        "dealer"
    ],
    "wof:name":"Auto Land",
    "wof:placetype":"venue"
},
  "geometry": {"coordinates":[-84.541972,39.359456],"type":"Point"}
}