{
  "type": "Feature",
  "properties": {
    "addr:full": "1681 Burbank Rd Wooster OH 44691",
    "addr:housenumber": "1681",
    "addr:postcode": "44691",
    "addr:street": "Burbank Rd",
    "iso:country": "US",
    "sg:address": "1681 Burbank Rd",
    "sg:city": "Wooster",
    "sg:classifiers": [
      {
        "category": "Real Estate",
        "subcategory": "Real Estate Agent",
        "type": "Services"
      }
    ],
    "sg:phone": "+1 330 264 3857",
    "sg:postcode": "44691",
    "sg:province": "OH",
    "sg:tags": [
      "investment"
    ],
    "wof:name": "GKI",
    "wof:placetype": "venue"
  },
  "geometry": {"coordinates":[-81.938442,40.818571],"type":"Point"}
}
