{
  "type": "Feature",
  "properties": {
    "addr:full":"1423 Grandview Ave Portsmouth OH 45662",
    "addr:housenumber":"1423",
    "addr:postcode":"45662",
    "addr:street":"Grandview Ave",
    "iso:country":"US",
    "sg:address":"1423 Grandview Ave",
    "sg:city":"Portsmouth",
    "sg:classifiers":[
        {
            "category":"Personal",
            "subcategory":"Tanning Parlor",
            "type":"Services"
        }
    ],
    "sg:phone":"+1 740 354 5220",
    "sg:postcode":"45662",
    "sg:province":"OH",
    "sg:tags":[
        "salon"
    ],
    "wof:name":"Sun Spot",
    "wof:placetype":"venue"
},
  "geometry": {"coordinates":[-82.975328,38.741316],"type":"Point"}
}