{
  "type": "Feature",
  "properties": {
    "addr:full":"2525 Ivy Hill Cir Cortland OH 44410",
    "addr:housenumber":"2525",
    "addr:postcode":"44410",
    "addr:street":"Ivy Hill Cir",
    "iso:country":"US",
    "sg:address":"2525 Ivy Hill Cir",
    "sg:city":"Cortland",
    "sg:classifiers":[
        {
            "category":"Professional",
            "subcategory":"Advertising",
            "type":"Services"
        }
    ],
    "sg:phone":"+1 330 732 5554",
    "sg:postcode":"44410",
    "sg:province":"OH",
    "sg:tags":[
        "counselor"
    ],
    "wof:name":"Mark V Advertising",
    "wof:placetype":"venue"
},
  "geometry": {"coordinates":[-80.758194,41.285711],"type":"Point"}
}