{
  "type": "Feature",
  "properties": {
    "addr:full": "1708 Linn St Cincinnati OH 45214",
    "addr:housenumber": "1708",
    "addr:postcode": "45214",
    "addr:street": "Linn St",
    "iso:country": "US",
    "sg:address": "1708 Linn St",
    "sg:city": "Cincinnati",
    "sg:classifiers": [
      {
        "category": "Personal",
        "subcategory": "Barber",
        "type": "Services"
      }
    ],
    "sg:phone": "+1 513 723 1512",
    "sg:postcode": "45214",
    "sg:province": "OH",
    "wof:name": "Jay's Cutting",
    "wof:placetype": "venue"
  },
  "geometry": {"coordinates":[-84.527225,39.115195],"type":"Point"}
}
