{
  "type": "Feature",
  "properties": {
    "addr:full": "1402 Laidlaw Ave Cincinnati OH 45237",
    "addr:housenumber": "1402",
    "addr:postcode": "45237",
    "addr:street": "Laidlaw Ave",
    "iso:country": "US",
    "sg:address": "1402 Laidlaw Ave",
    "sg:city": "Cincinnati",
    "sg:classifiers": [
      {
        "category": "Organizations",
        "subcategory": "Religious Organization",
        "type": "Services"
      }
    ],
    "sg:phone": "+1 513 641 0754",
    "sg:postcode": "45237",
    "sg:province": "OH",
    "sg:tags": [
      "church"
    ],
    "wof:name": "Second Baptist Church",
    "wof:placetype": "venue"
  },
  "geometry": {"coordinates":[-84.472047,39.177738],"type":"Point"}
}
