{
  "type": "Feature",
  "properties": {
    "addr:full": "1850 E Market St Akron OH 44305",
    "addr:housenumber": "1850",
    "addr:postcode": "44305",
    "addr:street": "E Market St",
    "iso:country": "US",
    "sg:address": "1850 E Market St",
    "sg:city": "Akron",
    "sg:phone": "+1 330 296 1224",
    "sg:postcode": "44305",
    "sg:province": "OH",
    "sg:tags": [
      "oil"
    ],
    "wof:name": "Thomas Burch Oil Co",
    "wof:placetype": "venue"
  },
  "geometry": {"coordinates":[-81.459347,41.061498],"type":"Point"}
}
