{
  "type": "Feature",
  "properties": {
    "addr:full": "2900 Columbus Ave Sandusky OH 44870",
    "addr:housenumber": "2900",
    "addr:postcode": "44870",
    "addr:street": "Columbus Ave",
    "iso:country": "US",
    "sg:address": "2900 Columbus Ave",
    "sg:city": "Sandusky",
    "sg:classifiers": [
      {
        "category": "Professional",
        "subcategory": "Management \u0026 Consulting",
        "type": "Services"
      }
    ],
    "sg:phone": "+1 419 627 7792",
    "sg:postcode": "44870",
    "sg:province": "OH",
    "sg:tags": [
      "executive"
    ],
    "wof:name": "Regional Planning",
    "wof:placetype": "venue"
  },
  "geometry": {"coordinates":[-82.694407,41.426797],"type":"Point"}
}
