{
  "type": "Feature",
  "properties": {
    "addr:full": "19 W Main St Ashland OH 44805",
    "addr:housenumber": "19",
    "addr:postcode": "44805",
    "addr:street": "W Main St",
    "iso:country": "US",
    "sg:address": "19 W Main St",
    "sg:city": "Ashland",
    "sg:classifiers": [
      {
        "category": "Real Estate",
        "subcategory": "Real Estate Agent",
        "type": "Services"
      }
    ],
    "sg:phone": "+1 419 281 2700",
    "sg:postcode": "44805",
    "sg:province": "OH",
    "sg:website": "www.ashland-oh-homes.com",
    "wof:name": "Ashland Board Of Realtors",
    "wof:placetype": "venue"
  },
  "geometry": {"coordinates":[-82.315195,40.8686],"type":"Point"}
}
