{
  "type": "Feature",
  "properties": {
    "addr:full":"537 Frys Valley Rd SE Gnadenhutten OH 44629",
    "addr:housenumber":"537",
    "addr:postcode":"44629",
    "addr:street":"Frys Valley Rd Se",
    "iso:country":"US",
    "sg:address":"537 Frys Valley Rd SE",
    "sg:city":"Gnadenhutten",
    "sg:classifiers":[
        {
            "category":"Freight",
            "type":"Transportation"
        }
    ],
    "sg:phone":"+1 740 254 4083",
    "sg:postcode":"44629",
    "sg:province":"OH",
    "sg:tags":[
        "hauling",
        "trucking"
    ],
    "wof:name":"Stocker Trucking Inc",
    "wof:placetype":"venue"
},
  "geometry": {"coordinates":[-81.453248,40.367977],"type":"Point"}
}