{
  "type": "Feature",
  "properties": {
    "iso:country":"US",
    "sg:address":"3972 E Main St",
    "sg:city":"Columbus",
    "sg:classifiers":[
        {
            "category":"Food & Beverages",
            "subcategory":"Bakery",
            "type":"Retail Goods"
        }
    ],
    "sg:phone":"+1 614 238 9124",
    "sg:postcode":"43213",
    "sg:province":"OH",
    "wof:name":"Awash Enjera Bakery & Dist",
    "wof:placetype":"venue"
},
  "geometry": {"coordinates":[-82.888793,39.955893],"type":"Point"}
}