{
  "type": "Feature",
  "properties": {
    "iso:country":"US",
    "sg:address":"1410 Sheridan Dr",
    "sg:city":"Lancaster",
    "sg:classifiers":[
        {
            "category":"Real Estate",
            "subcategory":"Real Estate Operator",
            "type":"Services"
        }
    ],
    "sg:phone":"+1 740 653 0501",
    "sg:postcode":"43130",
    "sg:province":"OH",
    "sg:tags":[
        "apartment",
        "complex"
    ],
    "wof:name":"Equity Residential",
    "wof:placetype":"venue"
},
  "geometry": {"coordinates":[-82.570205,39.735023],"type":"Point"}
}