{
  "type": "Feature",
  "properties": {
    "addr:full": "13668 Oak Tree Trl Chardon OH 44024",
    "addr:housenumber": "13668",
    "addr:postcode": "44024",
    "addr:street": "Oak Tree Trl",
    "iso:country": "US",
    "sg:address": "13668 Oak Tree Trl",
    "sg:city": "Chardon",
    "sg:classifiers": [
      {
        "category": "Building \u0026 Trades",
        "subcategory": "Electrical",
        "type": "Services"
      }
    ],
    "sg:phone": "+1 440 564 8223",
    "sg:postcode": "44024",
    "sg:province": "OH",
    "sg:tags": [
      "electrical",
      "contractor"
    ],
    "wof:name": "Good News Electric",
    "wof:placetype": "venue"
  },
  "geometry": {"coordinates":[-81.224007,41.490505],"type":"Point"}
}
