{
  "type": "Feature",
  "properties": {
    "iso:country":"US",
    "sg:address":"3050 Guernsey St",
    "sg:city":"Bellaire",
    "sg:classifiers":[
        {
            "category":"Food & Beverages",
            "subcategory":"Groceries & Convenience Stores",
            "type":"Retail Goods"
        }
    ],
    "sg:phone":"+1 740 671 9216",
    "sg:postcode":"43906",
    "sg:province":"OH",
    "sg:tags":[
        "grocer"
    ],
    "wof:name":"More For Less",
    "wof:placetype":"venue"
},
  "geometry": {"coordinates":[-80.745042,40.012808],"type":"Point"}
}