{
  "type": "Feature",
  "properties": {
    "iso:country":"US",
    "sg:address":"1034 Grace St",
    "sg:city":"Mansfield",
    "sg:classifiers":[
        {
            "category":"Organizations",
            "subcategory":"Religious Organization",
            "type":"Services"
        }
    ],
    "sg:phone":"+1 419 589 6467",
    "sg:postcode":"44905",
    "sg:province":"OH",
    "sg:tags":[
        "church"
    ],
    "wof:name":"Living Word Church",
    "wof:placetype":"venue"
},
  "geometry": {"coordinates":[-82.476622,40.770261],"type":"Point"}
}