{
  "type": "Feature",
  "properties": {
    "iso:country":"US",
    "sg:address":"6332 Surrey Dr",
    "sg:city":"North Olmsted",
    "sg:classifiers":[
        {
            "category":"Wholesale",
            "subcategory":"Hardware",
            "type":"Manufacturing & Wholesale Goods"
        }
    ],
    "sg:phone":"+1 440 734 2560",
    "sg:postcode":"44070",
    "sg:province":"OH",
    "sg:tags":[
        "cooling",
        "representative",
        "unit",
        "heating"
    ],
    "wof:name":"Energy Resource Control Inc",
    "wof:placetype":"venue"
},
  "geometry": {"coordinates":[-81.950159,41.396851],"type":"Point"}
}