{
  "type": "Feature",
  "properties": {
    "addr:full": "6332 Surrey Dr North Olmsted OH 44070",
    "addr:housenumber": "6332",
    "addr:postcode": "44070",
    "addr:street": "Surrey Dr",
    "iso:country": "US",
    "sg:address": "6332 Surrey Dr",
    "sg:city": "North Olmsted",
    "sg:classifiers": [
      {
        "category": "Wholesale",
        "subcategory": "Hardware",
        "type": "Manufacturing \u0026 Wholesale Goods"
      }
    ],
    "sg:phone": "+1 440 734 2560",
    "sg:postcode": "44070",
    "sg:province": "OH",
    "sg:tags": [
      "cooling",
      "representative",
      "unit",
      "heating"
    ],
    "wof:name": "Energy Resource Control Inc",
    "wof:placetype": "venue"
  },
  "geometry": {"coordinates":[-81.950159,41.396851],"type":"Point"}
}
