{
  "type": "Feature",
  "properties": {
    "addr:full": "4253 Portage St NW North Canton OH 44720",
    "addr:housenumber": "4253",
    "addr:postcode": "44720",
    "addr:street": "Portage St Nw",
    "iso:country": "US",
    "sg:address": "4253 Portage St NW",
    "sg:city": "North Canton",
    "sg:classifiers": [
      {
        "category": "Professional",
        "subcategory": "Management \u0026 Consulting",
        "type": "Services"
      }
    ],
    "sg:phone": "+1 330 497 8960",
    "sg:postcode": "44720",
    "sg:province": "OH",
    "sg:tags": [
      "consultant",
      "safety"
    ],
    "sg:website": "www.safetyresourcecompany.com",
    "wof:name": "Safety Resources Co",
    "wof:placetype": "venue"
  },
  "geometry": {"coordinates":[-81.426855,40.881867],"type":"Point"}
}
