{
  "type": "Feature",
  "properties": {
    "iso:country":"US",
    "sg:address":"10318 State Rte 269",
    "sg:city":"Bellevue",
    "sg:classifiers":[
        {
            "category":"Wholesale",
            "subcategory":"Durable Goods & Equipment",
            "type":"Manufacturing & Wholesale Goods"
        }
    ],
    "sg:phone":"+1 419 483 7154",
    "sg:postcode":"44811",
    "sg:province":"OH",
    "sg:tags":[
        "fire",
        "extinguisher"
    ],
    "wof:name":"Fire Safety Equipment",
    "wof:placetype":"venue"
},
  "geometry": {"coordinates":[-82.829363,41.31384],"type":"Point"}
}