{
  "type": "Feature",
  "properties": {
    "addr:full": "5050 Oaklawn Dr Cincinnati OH 45227",
    "addr:housenumber": "5050",
    "addr:postcode": "45227",
    "addr:street": "Oaklawn Dr",
    "iso:country": "US",
    "sg:address": "5050 Oaklawn Dr",
    "sg:city": "Cincinnati",
    "sg:classifiers": [
      {
        "category": "Professional",
        "subcategory": "Accounting \u0026 Tax Preparation",
        "type": "Services"
      }
    ],
    "sg:phone": "+1 513 841 4706",
    "sg:postcode": "45227",
    "sg:province": "OH",
    "sg:tags": [
      "accountant"
    ],
    "wof:name": "Netherwood \u0026 Co",
    "wof:placetype": "venue"
  },
  "geometry": {"coordinates":[-84.414098,39.163514],"type":"Point"}
}
