{
  "type": "Feature",
  "properties": {
    "addr:full":"912 Parkside Pl Findlay OH 45840",
    "addr:housenumber":"912",
    "addr:postcode":"45840",
    "addr:street":"Parkside Pl",
    "iso:country":"US",
    "sg:address":"912 Parkside Pl",
    "sg:city":"Findlay",
    "sg:classifiers":[
        {
            "category":"Professional",
            "subcategory":"Business Services",
            "type":"Services"
        }
    ],
    "sg:phone":"+1 419 425 5705",
    "sg:postcode":"45840",
    "sg:province":"OH",
    "sg:tags":[
        "mail",
        "voice",
        "messaging"
    ],
    "wof:name":"Computer Link Plus",
    "wof:placetype":"venue"
},
  "geometry": {"coordinates":[-83.633189,41.05432],"type":"Point"}
}