{
  "type": "Feature",
  "properties": {
    "addr:full":"895 Lorain Blvd Elyria OH 44035",
    "addr:housenumber":"895",
    "addr:postcode":"44035",
    "addr:street":"Lorain Blvd",
    "iso:country":"US",
    "sg:address":"895 Lorain Blvd",
    "sg:city":"Elyria",
    "sg:classifiers":[
        {
            "category":"Autos & Motor Vehicles",
            "subcategory":"Fuel & Gas Station",
            "type":"Retail Goods"
        }
    ],
    "sg:phone":"+1 440 323 6660",
    "sg:postcode":"44035",
    "sg:province":"OH",
    "sg:tags":[
        "grocery",
        "station",
        "gasoline"
    ],
    "wof:name":"Speedway 8556",
    "wof:placetype":"venue"
},
  "geometry": {"coordinates":[-82.116697,41.384596],"type":"Point"}
}