{
  "type": "Feature",
  "properties": {
    "addr:full": "16 Delaware Dr Chillicothe OH 45601",
    "addr:housenumber": "16",
    "addr:postcode": "45601",
    "addr:street": "Delaware Dr",
    "iso:country": "US",
    "sg:address": "16 Delaware Dr",
    "sg:city": "Chillicothe",
    "sg:classifiers": [
      {
        "category": "Building \u0026 Trades",
        "subcategory": "Plumbing",
        "type": "Services"
      }
    ],
    "sg:phone": "+1 740 772 1061",
    "sg:postcode": "45601",
    "sg:province": "OH",
    "sg:tags": [
      "plumbing",
      "contractor"
    ],
    "wof:name": "Kuntz Plumbing \u0026 Construction",
    "wof:placetype": "venue"
  },
  "geometry": {"coordinates":[-82.982955,39.364188],"type":"Point"}
}
