{
  "type": "Feature",
  "properties": {
    "addr:full": "6200 Quarry Ln Cleveland OH 44131",
    "addr:housenumber": "6200",
    "addr:postcode": "44131",
    "addr:street": "Quarry Ln",
    "iso:country": "US",
    "sg:address": "6200 Quarry Ln",
    "sg:city": "Cleveland",
    "sg:classifiers": [
      {
        "category": "Building \u0026 Trades",
        "subcategory": "Equipment Rental",
        "type": "Services"
      }
    ],
    "sg:phone": "+1 216 524 4066",
    "sg:postcode": "44131",
    "sg:province": "OH",
    "sg:tags": [
      "audio",
      "leasing"
    ],
    "wof:name": "Swank Audio Visuals Inc",
    "wof:placetype": "venue"
  },
  "geometry": {"coordinates":[-81.649661,41.393964],"type":"Point"}
}
