{
  "type": "Feature",
  "properties": {
    "iso:country":"US",
    "sg:address":"6200 Quarry Ln",
    "sg:city":"Cleveland",
    "sg:classifiers":[
        {
            "category":"Building & Trades",
            "subcategory":"Equipment Rental",
            "type":"Services"
        }
    ],
    "sg:phone":"+1 216 524 4066",
    "sg:postcode":"44131",
    "sg:province":"OH",
    "sg:tags":[
        "audio",
        "leasing"
    ],
    "wof:name":"Swank Audio Visuals Inc",
    "wof:placetype":"venue"
},
  "geometry": {"coordinates":[-81.64966099999999,41.393964],"type":"Point"}
}