{
  "type": "Feature",
  "properties": {
    "addr:full":"5534 Desert Gold Dr Cincinnati OH 45247",
    "addr:housenumber":"5534",
    "addr:postcode":"45247",
    "addr:street":"Desert Gold Dr",
    "iso:country":"US",
    "sg:address":"5534 Desert Gold Dr",
    "sg:city":"Cincinnati",
    "sg:classifiers":[
        {
            "category":"Manufacturing",
            "subcategory":"Food",
            "type":"Manufacturing & Wholesale Goods"
        }
    ],
    "sg:phone":"+1 513 245 1940",
    "sg:postcode":"45247",
    "sg:province":"OH",
    "sg:tags":[
        "nut",
        "snack",
        "market",
        "candy",
        "mfg"
    ],
    "wof:name":"Nabisco",
    "wof:placetype":"venue"
},
  "geometry": {"coordinates":[-84.62843599999999,39.223219],"type":"Point"}
}