{
  "type": "Feature",
  "properties": {
    "addr:full": "1051 N Canfield Niles Rd Youngstown OH 44515",
    "addr:housenumber": "1051",
    "addr:postcode": "44515",
    "addr:street": "N Canfield Niles Rd",
    "iso:country": "US",
    "sg:address": "1051 N Canfield Niles Rd",
    "sg:city": "Youngstown",
    "sg:classifiers": [
      {
        "category": "Travel",
        "subcategory": "Hotels \u0026 Motels",
        "type": "Entertainment"
      }
    ],
    "sg:phone": "+1 330 792 3715",
    "sg:postcode": "44515",
    "sg:province": "OH",
    "wof:name": "Youngstown Inn",
    "wof:placetype": "venue"
  },
  "geometry": {"coordinates":[-80.76827,41.126217],"type":"Point"}
}
