{
  "type": "Feature",
  "properties": {
    "iso:country":"US",
    "sg:address":"1051 N Canfield Niles Rd",
    "sg:city":"Youngstown",
    "sg:classifiers":[
        {
            "category":"Travel",
            "subcategory":"Hotels & Motels",
            "type":"Entertainment"
        }
    ],
    "sg:phone":"+1 330 792 3715",
    "sg:postcode":"44515",
    "sg:province":"OH",
    "wof:name":"Youngstown Inn",
    "wof:placetype":"venue"
},
  "geometry": {"coordinates":[-80.76827,41.126217],"type":"Point"}
}