{
  "type": "Feature",
  "properties": {
    "iso:country":"US",
    "sg:address":"678 E Taggart St",
    "sg:city":"East Palestine",
    "sg:classifiers":[
        {
            "category":"Personal",
            "subcategory":"Beauty Salon",
            "type":"Services"
        }
    ],
    "sg:phone":"+1 330 426 3337",
    "sg:postcode":"44413",
    "sg:province":"OH",
    "wof:name":"Skilz Salon & Tanning",
    "wof:placetype":"venue"
},
  "geometry": {"coordinates":[-80.527824,40.834589],"type":"Point"}
}