{
  "type": "Feature",
  "properties": {
    "addr:full":"400 W 9th St Cincinnati OH 45203",
    "addr:housenumber":"400",
    "addr:postcode":"45203",
    "addr:street":"W 9Th St",
    "iso:country":"US",
    "sg:address":"400 W 9th St",
    "sg:city":"Cincinnati",
    "sg:classifiers":[
        {
            "category":"Personal",
            "subcategory":"Beauty Salon",
            "type":"Services"
        }
    ],
    "sg:phone":"+1 513 241 5758",
    "sg:postcode":"45203",
    "sg:province":"OH",
    "wof:name":"Calloway's Touch Of Class",
    "wof:placetype":"venue"
},
  "geometry": {"coordinates":[-84.52173999999999,39.104071],"type":"Point"}
}