{
  "type": "Feature",
  "properties": {
    "addr:full": "7850 Mentor Ave Mentor OH 44060",
    "addr:housenumber": "7850",
    "addr:postcode": "44060",
    "addr:street": "Mentor Ave",
    "iso:country": "US",
    "sg:address": "7850 Mentor Ave",
    "sg:city": "Mentor",
    "sg:classifiers": [
      {
        "category": "Shopping",
        "subcategory": "Clothing, Apparel, \u0026 Fashions",
        "type": "Retail Goods"
      }
    ],
    "sg:phone": "+1 440 205 0102",
    "sg:postcode": "44060",
    "sg:province": "OH",
    "wof:name": "Gymboree Corporation",
    "wof:placetype": "venue"
  },
  "geometry": {"coordinates":[-81.362095,41.660627],"type":"Point"}
}
