{
  "type": "Feature",
  "properties": {
    "addr:full": "3231 Springdale Rd Cincinnati OH 45251",
    "addr:housenumber": "3231",
    "addr:postcode": "45251",
    "addr:street": "Springdale Rd",
    "iso:country": "US",
    "sg:address": "3231 Springdale Rd",
    "sg:city": "Cincinnati",
    "sg:classifiers": [
      {
        "category": "Real Estate",
        "subcategory": "Real Estate Operator",
        "type": "Services"
      }
    ],
    "sg:phone": "+1 513 851 1101",
    "sg:postcode": "45251",
    "sg:province": "OH",
    "sg:tags": [
      "building",
      "apartment"
    ],
    "wof:name": "Leslie Marie Apartments",
    "wof:placetype": "venue"
  },
  "geometry": {"coordinates":[-84.588236,39.254838],"type":"Point"}
}
