{
  "type": "Feature",
  "properties": {
    "addr:full":"74 River St Ripley OH 45167",
    "addr:housenumber":"74",
    "addr:postcode":"45167",
    "addr:street":"River St",
    "iso:country":"US",
    "sg:address":"74 River St",
    "sg:city":"Ripley",
    "sg:classifiers":[
        {
            "category":"Building & Trades",
            "subcategory":"Construction",
            "type":"Services"
        }
    ],
    "sg:phone":"+1 937 392 1616",
    "sg:postcode":"45167",
    "sg:province":"OH",
    "sg:tags":[
        "roofing",
        "contractor"
    ],
    "wof:name":"Gary E St Clair Tin Shop",
    "wof:placetype":"venue"
},
  "geometry": {"coordinates":[-83.84229999999999,38.73966],"type":"Point"}
}