{
  "type": "Feature",
  "properties": {
    "addr:full": "317 Railroad St Edgerton OH 43517",
    "addr:housenumber": "317",
    "addr:postcode": "43517",
    "addr:street": "Railroad St",
    "iso:country": "US",
    "sg:address": "317 Railroad St",
    "sg:city": "Edgerton",
    "sg:classifiers": [
      {
        "category": "Government",
        "subcategory": "Office",
        "type": "Public Place"
      }
    ],
    "sg:phone": "+1 419 298 3445",
    "sg:postcode": "43517",
    "sg:province": "OH",
    "sg:tags": [
      "village"
    ],
    "wof:name": "St Joseph Township Hall",
    "wof:placetype": "venue"
  },
  "geometry": {"coordinates":[-84.751168,41.446895],"type":"Point"}
}
