{
  "type": "Feature",
  "properties": {
    "addr:full":"117 Columbus Rd Fredericktown OH 43019",
    "addr:housenumber":"117",
    "addr:postcode":"43019",
    "addr:street":"Columbus Rd",
    "iso:country":"US",
    "sg:address":"117 Columbus Rd",
    "sg:city":"Fredericktown",
    "sg:classifiers":[
        {
            "category":"Education",
            "subcategory":"School",
            "type":"Public Place"
        }
    ],
    "sg:phone":"+1 740 694 2726",
    "sg:postcode":"43019",
    "sg:province":"OH",
    "sg:website":"www.fredericktown.net",
    "wof:name":"Fredericktown High School",
    "wof:placetype":"venue"
},
  "geometry": {"coordinates":[-82.548481,40.47339],"type":"Point"}
}