{
  "type": "Feature",
  "properties": {
    "addr:full": "5103 Parks West Rd Middlefield OH 44062",
    "addr:housenumber": "5103",
    "addr:postcode": "44062",
    "addr:street": "Parks West Rd",
    "iso:country": "US",
    "sg:address": "5103 Parks West Rd",
    "sg:city": "Middlefield",
    "sg:classifiers": [
      {
        "category": "Utilities",
        "subcategory": "Fuel Oil \u0026 Lpg",
        "type": "Services"
      }
    ],
    "sg:phone": "+1 440 693 4300",
    "sg:postcode": "44062",
    "sg:province": "OH",
    "sg:tags": [
      "firewood"
    ],
    "wof:name": "Land Resource",
    "wof:placetype": "venue"
  },
  "geometry": {"coordinates":[-80.980022,41.442493],"type":"Point"}
}
