{
  "type": "Feature",
  "properties": {
    "addr:full":"26998 Schady Rd Olmsted Falls OH 44138",
    "addr:housenumber":"26998",
    "addr:postcode":"44138",
    "addr:street":"Schady Rd",
    "iso:country":"US",
    "sg:address":"26998 Schady Rd",
    "sg:city":"Olmsted Falls",
    "sg:classifiers":[
        {
            "category":"Food & Beverages",
            "subcategory":"Specialty",
            "type":"Retail Goods"
        }
    ],
    "sg:phone":"+1 440 427 1221",
    "sg:postcode":"44138",
    "sg:province":"OH",
    "wof:name":"Wicked Salsa Company",
    "wof:placetype":"venue"
},
  "geometry": {"coordinates":[-81.942189,41.363471],"type":"Point"}
}