{
  "type": "Feature",
  "properties": {
    "iso:country":"US",
    "sg:address":"5681 E Harbor Rd",
    "sg:city":"Lakeside Marblhd",
    "sg:classifiers":[
        {
            "category":"Real Estate",
            "subcategory":"Real Estate Agent",
            "type":"Services"
        }
    ],
    "sg:phone":"+1 419 797 9995",
    "sg:postcode":"43440",
    "sg:province":"OH",
    "wof:name":"Routh Realty",
    "wof:placetype":"venue"
},
  "geometry": {"coordinates":[-82.824938,41.531438],"type":"Point"}
}