{
  "type": "Feature",
  "properties": {
    "iso:country":"US",
    "sg:address":"1742 Tib Day Ln",
    "sg:city":"Amelia",
    "sg:classifiers":[
        {
            "category":"Real Estate",
            "subcategory":"Architect",
            "type":"Services"
        }
    ],
    "sg:phone":"+1 513 947 9818",
    "sg:postcode":"45102",
    "sg:province":"OH",
    "sg:website":"www.jwmooney.com",
    "wof:name":"Acoustics By JW Mooney",
    "wof:placetype":"venue"
},
  "geometry": {"coordinates":[-84.205839,39.011193],"type":"Point"}
}