{
  "type": "Feature",
  "properties": {
    "addr:full":"40 N Main St Springboro OH 45066",
    "addr:housenumber":"40",
    "addr:postcode":"45066",
    "addr:street":"N Main St",
    "iso:country":"US",
    "sg:address":"40 N Main St",
    "sg:city":"Springboro",
    "sg:classifiers":[
        {
            "category":"Retail",
            "subcategory":"Funeral Services",
            "type":"Services"
        }
    ],
    "sg:phone":"+1 937 748 6455",
    "sg:postcode":"45066",
    "sg:province":"OH",
    "sg:tags":[
        "director"
    ],
    "wof:name":"Anderson Funeral Home",
    "wof:placetype":"venue"
},
  "geometry": {"coordinates":[-84.232912,39.556696],"type":"Point"}
}