{
  "type": "Feature",
  "properties": {
    "addr:full": "8009 Hamilton Ave Cincinnati OH 45231",
    "addr:housenumber": "8009",
    "addr:postcode": "45231",
    "addr:street": "Hamilton Ave",
    "iso:country": "US",
    "sg:address": "8009 Hamilton Ave",
    "sg:city": "Cincinnati",
    "sg:classifiers": [
      {
        "category": "Real Estate",
        "subcategory": "Real Estate Operator",
        "type": "Services"
      }
    ],
    "sg:phone": "+1 513 729 0135",
    "sg:postcode": "45231",
    "sg:province": "OH",
    "sg:tags": [
      "mobile",
      "home",
      "community"
    ],
    "wof:name": "Hazelhurst M Hc",
    "wof:placetype": "venue"
  },
  "geometry": {"coordinates":[-84.547496,39.241058],"type":"Point"}
}
