{
  "type": "Feature",
  "properties": {
    "addr:full":"9545 Midwest Ave Cleveland OH 44125",
    "addr:housenumber":"9545",
    "addr:postcode":"44125",
    "addr:street":"Midwest Ave",
    "iso:country":"US",
    "sg:address":"9545 Midwest Ave",
    "sg:city":"Cleveland",
    "sg:classifiers":[
        {
            "category":"Health Services",
            "subcategory":"Doctor",
            "type":"Services"
        }
    ],
    "sg:phone":"+1 216 581 6556",
    "sg:postcode":"44125",
    "sg:province":"OH",
    "sg:tags":[
        "medical",
        "imaging"
    ],
    "sg:website":"www.llsa.com",
    "wof:name":"Life Line Screening",
    "wof:placetype":"venue"
},
  "geometry": {"coordinates":[-81.619471,41.419653],"type":"Point"}
}