{
  "type": "Feature",
  "properties": {
    "addr:full": "3787 E 144th St Cleveland OH 44128",
    "addr:housenumber": "3787",
    "addr:postcode": "44128",
    "addr:street": "E 144Th St",
    "iso:country": "US",
    "sg:address": "3787 E 144th St",
    "sg:city": "Cleveland",
    "sg:classifiers": [
      {
        "category": "Personal",
        "subcategory": "Barber",
        "type": "Services"
      }
    ],
    "sg:phone": "+1 216 881 2646",
    "sg:postcode": "44128",
    "sg:province": "OH",
    "wof:name": "E Ast 144th Street Barber",
    "wof:placetype": "venue"
  },
  "geometry": {"coordinates":[-81.581328,41.457505],"type":"Point"}
}
