{
  "type": "Feature",
  "properties": {
    "addr:full":"957 Averill Ave Mansfield OH 44906",
    "addr:housenumber":"957",
    "addr:postcode":"44906",
    "addr:street":"Averill Ave",
    "iso:country":"US",
    "sg:address":"957 Averill Ave",
    "sg:city":"Mansfield",
    "sg:classifiers":[
        {
            "category":"Restaurant",
            "type":"Food & Drink"
        }
    ],
    "sg:phone":"+1 419 747 2695",
    "sg:postcode":"44906",
    "sg:province":"OH",
    "sg:tags":[
        "caterer"
    ],
    "wof:name":"Simply Scrumptious Catering",
    "wof:placetype":"venue"
},
  "geometry": {"coordinates":[-82.54490800000001,40.785306],"type":"Point"}
}