{
  "type": "Feature",
  "properties": {
    "iso:country":"US",
    "sg:address":"10519 Reading Rd",
    "sg:city":"Cincinnati",
    "sg:classifiers":[
        {
            "category":"Retail",
            "subcategory":"Veterinary Services",
            "type":"Services"
        }
    ],
    "sg:phone":"+1 513 563 0410",
    "sg:postcode":"45241",
    "sg:province":"OH",
    "sg:tags":[
        "veterinarian"
    ],
    "wof:name":"Evendale Blue Ash Pet Hospital",
    "wof:placetype":"venue"
},
  "geometry": {"coordinates":[-84.42211399999999,39.254915],"type":"Point"}
}