{
  "type": "Feature",
  "properties": {
    "addr:full": "10519 Reading Rd Cincinnati OH 45241",
    "addr:housenumber": "10519",
    "addr:postcode": "45241",
    "addr:street": "Reading Rd",
    "iso:country": "US",
    "sg:address": "10519 Reading Rd",
    "sg:city": "Cincinnati",
    "sg:classifiers": [
      {
        "category": "Retail",
        "subcategory": "Veterinary Services",
        "type": "Services"
      }
    ],
    "sg:phone": "+1 513 563 0410",
    "sg:postcode": "45241",
    "sg:province": "OH",
    "sg:tags": [
      "veterinarian"
    ],
    "wof:name": "Evendale Blue Ash Pet Hospital",
    "wof:placetype": "venue"
  },
  "geometry": {"coordinates":[-84.422114,39.254915],"type":"Point"}
}
