{
  "type": "Feature",
  "properties": {
    "addr:full":"8111 Quincy Ave Cleveland OH 44104",
    "addr:housenumber":"8111",
    "addr:postcode":"44104",
    "addr:street":"Quincy Ave",
    "iso:country":"US",
    "sg:address":"8111 Quincy Ave",
    "sg:city":"Cleveland",
    "sg:classifiers":[
        {
            "category":"Government",
            "subcategory":"Office",
            "type":"Public Place"
        }
    ],
    "sg:phone":"+1 216 391 5847",
    "sg:postcode":"44104",
    "sg:province":"OH",
    "wof:name":"Cuyahoga County Workforce Dev",
    "wof:placetype":"venue"
},
  "geometry": {"coordinates":[-81.63227999999999,41.493465],"type":"Point"}
}