{
  "type": "Feature",
  "properties": {
    "addr:full": "5450 Avion Park Dr Cleveland OH 44143",
    "addr:housenumber": "5450",
    "addr:postcode": "44143",
    "addr:street": "Avion Park Dr",
    "iso:country": "US",
    "sg:address": "5450 Avion Park Dr",
    "sg:city": "Cleveland",
    "sg:classifiers": [
      {
        "category": "Building \u0026 Trades",
        "subcategory": "Electrical",
        "type": "Services"
      }
    ],
    "sg:phone": "+1 440 995 5900",
    "sg:postcode": "44143",
    "sg:province": "OH",
    "sg:tags": [
      "sound",
      "production",
      "provides"
    ],
    "sg:website": "www.8thdaysound.com",
    "wof:name": "Eighth Day Sound Systems Inc",
    "wof:placetype": "venue"
  },
  "geometry": {"coordinates":[-81.483573,41.559392],"type":"Point"}
}
