{
  "type": "Feature",
  "properties": {
    "iso:country":"US",
    "sg:address":"5450 Avion Park Dr",
    "sg:city":"Cleveland",
    "sg:classifiers":[
        {
            "category":"Building & Trades",
            "subcategory":"Electrical",
            "type":"Services"
        }
    ],
    "sg:phone":"+1 440 995 5900",
    "sg:postcode":"44143",
    "sg:province":"OH",
    "sg:tags":[
        "sound",
        "production",
        "provides"
    ],
    "sg:website":"www.8thdaysound.com",
    "wof:name":"Eighth Day Sound Systems Inc",
    "wof:placetype":"venue"
},
  "geometry": {"coordinates":[-81.48357300000001,41.559392],"type":"Point"}
}