{
  "type": "Feature",
  "properties": {
    "addr:full":"13287 State Rte 29 Anna OH 45302",
    "addr:housenumber":"13287",
    "addr:postcode":"45302",
    "addr:street":"State Rte 29",
    "iso:country":"US",
    "sg:address":"13287 State Rte 29",
    "sg:city":"Anna",
    "sg:classifiers":[
        {
            "category":"Farming",
            "subcategory":"Dairy Farm",
            "type":"Manufacturing & Wholesale Goods"
        }
    ],
    "sg:phone":"+1 937 394 7641",
    "sg:postcode":"45302",
    "sg:province":"OH",
    "wof:name":"Mike Pleiman",
    "wof:placetype":"venue"
},
  "geometry": {"coordinates":[-84.25473100000001,40.392102],"type":"Point"}
}