{
  "type": "Feature",
  "properties": {
    "iso:country":"US",
    "sg:address":"213 S Sandusky Ave",
    "sg:city":"Bucyrus",
    "sg:classifiers":[
        {
            "category":"Shopping",
            "subcategory":"Clothing, Apparel, & Fashions",
            "type":"Retail Goods"
        }
    ],
    "sg:phone":"+1 419 562 5551",
    "sg:postcode":"44820",
    "sg:province":"OH",
    "sg:tags":[
        "shop",
        "bridal"
    ],
    "wof:name":"Special Moments Bridal & Tux",
    "wof:placetype":"venue"
},
  "geometry": {"coordinates":[-82.975668,40.807456],"type":"Point"}
}