{
  "type": "Feature",
  "properties": {
    "addr:full": "607 N Main St Englewood OH 45322",
    "addr:housenumber": "607",
    "addr:postcode": "45322",
    "addr:street": "N Main St",
    "iso:country": "US",
    "sg:address": "607 N Main St",
    "sg:city": "Englewood",
    "sg:classifiers": [
      {
        "category": "Shopping",
        "subcategory": "Gifts \u0026 Souvenirs",
        "type": "Retail Goods"
      }
    ],
    "sg:phone": "+1 937 836 3375",
    "sg:postcode": "45322",
    "sg:province": "OH",
    "sg:tags": [
      "shop"
    ],
    "wof:name": "Glenn Cove Farms Market LLC",
    "wof:placetype": "venue"
  },
  "geometry": {"coordinates":[-84.306378,39.893776],"type":"Point"}
}
