{
  "type": "Feature",
  "properties": {
    "iso:country":"US",
    "sg:address":"1212 Washington Blvd",
    "sg:city":"Belpre",
    "sg:classifiers":[
        {
            "category":"Personal",
            "subcategory":"Barber",
            "type":"Services"
        }
    ],
    "sg:phone":"+1 740 423 9450",
    "sg:postcode":"45714",
    "sg:province":"OH",
    "wof:name":"Garry Barlow",
    "wof:placetype":"venue"
},
  "geometry": {"coordinates":[-81.584469,39.274475],"type":"Point"}
}