{
  "type": "Feature",
  "properties": {
    "addr:full": "5320 Youngstown Warren Rd Niles OH 44446",
    "addr:housenumber": "5320",
    "addr:postcode": "44446",
    "addr:street": "Youngstown Warren Rd",
    "iso:country": "US",
    "sg:address": "5320 Youngstown Warren Rd",
    "sg:city": "Niles",
    "sg:classifiers": [
      {
        "category": "Food \u0026 Beverages",
        "subcategory": "Specialty",
        "type": "Retail Goods"
      }
    ],
    "sg:phone": "+1 330 652 1671",
    "sg:postcode": "44446",
    "sg:province": "OH",
    "wof:name": "GNC",
    "wof:placetype": "venue"
  },
  "geometry": {"coordinates":[-80.756838,41.211972],"type":"Point"}
}
