{
  "type": "Feature",
  "properties": {
    "addr:full": "623 Griswold Rd Elyria OH 44035",
    "addr:housenumber": "623",
    "addr:postcode": "44035",
    "addr:street": "Griswold Rd",
    "iso:country": "US",
    "sg:address": "623 Griswold Rd",
    "sg:city": "Elyria",
    "sg:classifiers": [
      {
        "category": "Home \u0026 Garden",
        "subcategory": "Furniture",
        "type": "Retail Goods"
      }
    ],
    "sg:phone": "+1 440 324 2320",
    "sg:postcode": "44035",
    "sg:province": "OH",
    "sg:tags": [
      "household",
      "furnishing"
    ],
    "wof:name": "Johnathans Furniture",
    "wof:placetype": "venue"
  },
  "geometry": {"coordinates":[-82.116948,41.400325],"type":"Point"}
}
