{
  "type": "Feature",
  "properties": {
    "iso:country":"US",
    "sg:address":"314 Pike St",
    "sg:city":"Marietta",
    "sg:classifiers":[
        {
            "category":"Autos & Motor Vehicles",
            "subcategory":"Automobile Sales",
            "type":"Retail Goods"
        }
    ],
    "sg:phone":"+1 740 373 8212",
    "sg:postcode":"45750",
    "sg:province":"OH",
    "sg:tags":[
        "used",
        "car",
        "dealers-used",
        "new",
        "cars-wholesale"
    ],
    "wof:name":"Dave Lafayette Parker Motors",
    "wof:placetype":"venue"
},
  "geometry": {"coordinates":[-81.437422,39.413168],"type":"Point"}
}