{
  "type": "Feature",
  "properties": {
    "addr:full": "1604 Prosperity Rd Toledo OH 43612",
    "addr:housenumber": "1604",
    "addr:postcode": "43612",
    "addr:street": "Prosperity Rd",
    "iso:country": "US",
    "sg:address": "1604 Prosperity Rd",
    "sg:city": "Toledo",
    "sg:classifiers": [
      {
        "category": "Wholesale",
        "subcategory": "Metals \u0026 Minerals",
        "type": "Manufacturing \u0026 Wholesale Goods"
      }
    ],
    "sg:phone": "+1 419 470 8406",
    "sg:postcode": "43612",
    "sg:province": "OH",
    "sg:tags": [
      "steel",
      "broker"
    ],
    "wof:name": "Ciralsky \u0026 Associates II Inc",
    "wof:placetype": "venue"
  },
  "geometry": {"coordinates":[-83.584193,41.712638],"type":"Point"}
}
