{
  "type": "Feature",
  "properties": {
    "iso:country":"US",
    "sg:address":"1604 Prosperity Rd",
    "sg:city":"Toledo",
    "sg:classifiers":[
        {
            "category":"Wholesale",
            "subcategory":"Metals & Minerals",
            "type":"Manufacturing & Wholesale Goods"
        }
    ],
    "sg:phone":"+1 419 470 8406",
    "sg:postcode":"43612",
    "sg:province":"OH",
    "sg:tags":[
        "steel",
        "broker"
    ],
    "wof:name":"Ciralsky & Associates II Inc",
    "wof:placetype":"venue"
},
  "geometry": {"coordinates":[-83.584193,41.712638],"type":"Point"}
}