{
  "type": "Feature",
  "properties": {
    "iso:country":"US",
    "sg:address":"893 Ohio Pike",
    "sg:city":"Cincinnati",
    "sg:classifiers":[
        {
            "category":"Retail",
            "subcategory":"Auto Repair",
            "type":"Services"
        }
    ],
    "sg:phone":"+1 513 752 0955",
    "sg:postcode":"45245",
    "sg:province":"OH",
    "sg:website":"www.vioc.com",
    "wof:name":"Valvoline Instant Oil Change",
    "wof:placetype":"venue"
},
  "geometry": {"coordinates":[-84.27359800000001,39.062401],"type":"Point"}
}