{
  "type": "Feature",
  "properties": {
    "addr:full": "893 Ohio Pike Cincinnati OH 45245",
    "addr:housenumber": "893",
    "addr:postcode": "45245",
    "addr:street": "Ohio Pike",
    "iso:country": "US",
    "sg:address": "893 Ohio Pike",
    "sg:city": "Cincinnati",
    "sg:classifiers": [
      {
        "category": "Retail",
        "subcategory": "Auto Repair",
        "type": "Services"
      }
    ],
    "sg:phone": "+1 513 752 0955",
    "sg:postcode": "45245",
    "sg:province": "OH",
    "sg:website": "www.vioc.com",
    "wof:name": "Valvoline Instant Oil Change",
    "wof:placetype": "venue"
  },
  "geometry": {"coordinates":[-84.273598,39.062401],"type":"Point"}
}
