{
  "type": "Feature",
  "properties": {
    "addr:full":"450 Lake Ave NE Massillon OH 44646",
    "addr:housenumber":"450",
    "addr:postcode":"44646",
    "addr:street":"Lake Ave Ne",
    "iso:country":"US",
    "sg:address":"450 Lake Ave NE",
    "sg:city":"Massillon",
    "sg:classifiers":[
        {
            "category":"Banks & Credit Unions",
            "subcategory":"Bank",
            "type":"Services"
        }
    ],
    "sg:phone":"+1 330 830 7290",
    "sg:postcode":"44646",
    "sg:province":"OH",
    "wof:name":"Huntington National Bank",
    "wof:placetype":"venue"
},
  "geometry": {"coordinates":[-81.51776099999999,40.812955],"type":"Point"}
}