{
  "type": "Feature",
  "properties": {
    "addr:full":"411 Defiance Ave Hicksville OH 43526",
    "addr:housenumber":"411",
    "addr:postcode":"43526",
    "addr:street":"Defiance Ave",
    "iso:country":"US",
    "sg:address":"411 Defiance Ave",
    "sg:city":"Hicksville",
    "sg:classifiers":[
        {
            "category":"Organizations",
            "subcategory":"Religious Organization",
            "type":"Services"
        }
    ],
    "sg:phone":"+1 419 542 9033",
    "sg:postcode":"43526",
    "sg:province":"OH",
    "sg:tags":[
        "church"
    ],
    "wof:name":"First Baptist Church",
    "wof:placetype":"venue"
},
  "geometry": {"coordinates":[-84.749985,41.296019],"type":"Point"}
}