{
  "type": "Feature",
  "properties": {
    "addr:full":"204 Fulton Ln Middletown OH 45044",
    "addr:housenumber":"204",
    "addr:postcode":"45044",
    "addr:street":"Fulton Ln",
    "iso:country":"US",
    "sg:address":"204 Fulton Ln",
    "sg:city":"Middletown",
    "sg:classifiers":[
        {
            "category":"Retail",
            "subcategory":"Repair Shop",
            "type":"Services"
        }
    ],
    "sg:phone":"+1 513 423 3566",
    "sg:postcode":"45044",
    "sg:province":"OH",
    "sg:tags":[
        "repairing",
        "piano",
        "refinishing"
    ],
    "wof:name":"Marnie Squire",
    "wof:placetype":"venue"
},
  "geometry": {"coordinates":[-84.362737,39.508517],"type":"Point"}
}