{
  "type": "Feature",
  "properties": {
    "addr:full": "175 W River Rd Newton Falls OH 44444",
    "addr:housenumber": "175",
    "addr:postcode": "44444",
    "addr:street": "W River Rd",
    "iso:country": "US",
    "sg:address": "175 W River Rd",
    "sg:city": "Newton Falls",
    "sg:classifiers": [
      {
        "category": "Government",
        "subcategory": "Office",
        "type": "Public Place"
      }
    ],
    "sg:phone": "+1 330 872 1808",
    "sg:postcode": "44444",
    "sg:province": "OH",
    "sg:tags": [
      "govt",
      "city"
    ],
    "wof:name": "Newton Falls Water Treatment",
    "wof:placetype": "venue"
  },
  "geometry": {"coordinates":[-80.973081,41.186554],"type":"Point"}
}
