{
  "type": "Feature",
  "properties": {
    "iso:country":"US",
    "sg:address":"418 W Market St",
    "sg:city":"Lima",
    "sg:classifiers":[
        {
            "category":"Travel",
            "subcategory":"Hotels & Motels",
            "type":"Entertainment"
        }
    ],
    "sg:phone":"+1 419 228 2525",
    "sg:postcode":"45801",
    "sg:province":"OH",
    "wof:name":"Royal Inn Motel",
    "wof:placetype":"venue"
},
  "geometry": {"coordinates":[-84.10975500000001,40.740073],"type":"Point"}
}