{
  "type": "Feature",
  "properties": {
    "addr:full": "156 Spring Valley Pike Dayton OH 45458",
    "addr:housenumber": "156",
    "addr:postcode": "45458",
    "addr:street": "Spring Valley Pike",
    "iso:country": "US",
    "sg:address": "156 Spring Valley Pike",
    "sg:city": "Dayton",
    "sg:classifiers": [
      {
        "category": "Building \u0026 Trades",
        "subcategory": "Construction",
        "type": "Services"
      }
    ],
    "sg:phone": "+1 937 285 0800",
    "sg:postcode": "45458",
    "sg:province": "OH",
    "sg:tags": [
      "paving",
      "contractor"
    ],
    "wof:name": "Apple Paving",
    "wof:placetype": "venue"
  },
  "geometry": {"coordinates":[-84.159023,39.613511],"type":"Point"}
}
