{
  "type": "Feature",
  "properties": {
    "iso:country":"US",
    "sg:address":"156 Spring Valley Pike",
    "sg:city":"Dayton",
    "sg:classifiers":[
        {
            "category":"Building & Trades",
            "subcategory":"Construction",
            "type":"Services"
        }
    ],
    "sg:phone":"+1 937 285 0800",
    "sg:postcode":"45458",
    "sg:province":"OH",
    "sg:tags":[
        "paving",
        "contractor"
    ],
    "wof:name":"Apple Paving",
    "wof:placetype":"venue"
},
  "geometry": {"coordinates":[-84.159023,39.613511],"type":"Point"}
}