{
  "type": "Feature",
  "properties": {
    "addr:full":"412 W Campbell St Loudonville OH 44842",
    "addr:housenumber":"412",
    "addr:postcode":"44842",
    "addr:street":"W Campbell St",
    "iso:country":"US",
    "sg:address":"412 W Campbell St",
    "sg:city":"Loudonville",
    "sg:classifiers":[
        {
            "category":"Building & Trades",
            "subcategory":"Plumbing",
            "type":"Services"
        }
    ],
    "sg:phone":"+1 419 994 4082",
    "sg:postcode":"44842",
    "sg:province":"OH",
    "sg:tags":[
        "contractor"
    ],
    "wof:name":"Fisher Mechanical",
    "wof:placetype":"venue"
},
  "geometry": {"coordinates":[-82.239013,40.640751],"type":"Point"}
}