{
  "type": "Feature",
  "properties": {
    "addr:full":"4589 Copley Rd Akron OH 44321",
    "addr:housenumber":"4589",
    "addr:postcode":"44321",
    "addr:street":"Copley Rd",
    "iso:country":"US",
    "sg:address":"4589 Copley Rd",
    "sg:city":"Akron",
    "sg:classifiers":[
        {
            "category":"Shopping",
            "subcategory":"Catalog Store",
            "type":"Retail Goods"
        },
        {
            "category":"Building & Trades",
            "subcategory":"Construction",
            "type":"Services"
        }
    ],
    "sg:phone":"+1 330 666 9054",
    "sg:postcode":"44321",
    "sg:province":"OH",
    "sg:tags":[
        "mail",
        "wood",
        "order",
        "accessory"
    ],
    "wof:name":"Towne Cooper",
    "wof:placetype":"venue"
},
  "geometry": {"coordinates":[-81.68432300000001,41.093847],"type":"Point"}
}