{
  "type": "Feature",
  "properties": {
    "addr:full": "2125 Idle Hour Dr Uniontown OH 44685",
    "addr:housenumber": "2125",
    "addr:postcode": "44685",
    "addr:street": "Idle Hour Dr",
    "iso:country": "US",
    "sg:address": "2125 Idle Hour Dr",
    "sg:city": "Uniontown",
    "sg:classifiers": [
      {
        "category": "Organizations",
        "subcategory": "Community Association",
        "type": "Services"
      }
    ],
    "sg:phone": "+1 330 699 9967",
    "sg:postcode": "44685",
    "sg:province": "OH",
    "sg:tags": [
      "club"
    ],
    "wof:name": "Country Club Twnhses North",
    "wof:placetype": "venue"
  },
  "geometry": {"coordinates":[-81.443713,40.965063],"type":"Point"}
}
