{
  "type": "Feature",
  "properties": {
    "iso:country":"US",
    "sg:address":"5266 Loeffler Dr",
    "sg:city":"Groveport",
    "sg:classifiers":[
        {
            "category":"Building & Trades",
            "subcategory":"Construction",
            "type":"Services"
        }
    ],
    "sg:phone":"+1 614 836 8302",
    "sg:postcode":"43125",
    "sg:province":"OH",
    "sg:tags":[
        "repairing",
        "general",
        "remodeling",
        "contractor"
    ],
    "sg:website":"www.clear-choice-renovations.com",
    "wof:name":"Clear Choice Bldg Renovations",
    "wof:placetype":"venue"
},
  "geometry": {"coordinates":[-82.865039,39.862184],"type":"Point"}
}