{
  "type": "Feature",
  "properties": {
    "iso:country":"US",
    "sg:address":"4187 Pearl Rd",
    "sg:city":"Cleveland",
    "sg:classifiers":[
        {
            "category":"Health Services",
            "subcategory":"Doctor",
            "type":"Services"
        }
    ],
    "sg:phone":"+1 216 741 1980",
    "sg:postcode":"44109",
    "sg:province":"OH",
    "sg:tags":[
        "dentist"
    ],
    "wof:name":"Gwyn A Galan DDS",
    "wof:placetype":"venue"
},
  "geometry": {"coordinates":[-81.70529000000001,41.440919],"type":"Point"}
}