{
  "type": "Feature",
  "properties": {
    "addr:full":"2154 Jewett Dr Columbus OH 43229",
    "addr:housenumber":"2154",
    "addr:postcode":"43229",
    "addr:street":"Jewett Dr",
    "iso:country":"US",
    "sg:address":"2154 Jewett Dr",
    "sg:city":"Columbus",
    "sg:classifiers":[
        {
            "category":"Freight",
            "type":"Transportation"
        }
    ],
    "sg:phone":"+1 614 895 3798",
    "sg:postcode":"43229",
    "sg:province":"OH",
    "sg:tags":[
        "operator",
        "trucking"
    ],
    "wof:name":"Jl Drivers Leasing",
    "wof:placetype":"venue"
},
  "geometry": {"coordinates":[-82.962677,40.097489],"type":"Point"}
}