{
  "type": "Feature",
  "properties": {
    "iso:country":"US",
    "sg:address":"6819 W Central Ave",
    "sg:city":"Toledo",
    "sg:classifiers":[
        {
            "category":"Personal",
            "subcategory":"Beauty Salon",
            "type":"Services"
        }
    ],
    "sg:phone":"+1 419 491 4317",
    "sg:postcode":"43617",
    "sg:province":"OH",
    "sg:tags":[
        "care",
        "skin"
    ],
    "sg:website":"http://www.salonhazelton.com",
    "wof:name":"Flux - A Salon by Hazelton",
    "wof:placetype":"venue"
},
  "geometry": {"coordinates":[-83.70474299999999,41.675],"type":"Point"}
}