{
  "type": "Feature",
  "properties": {
    "addr:full": "1275 Norton Ave Barberton OH 44203",
    "addr:housenumber": "1275",
    "addr:postcode": "44203",
    "addr:street": "Norton Ave",
    "iso:country": "US",
    "sg:address": "1275 Norton Ave",
    "sg:city": "Barberton",
    "sg:classifiers": [
      {
        "category": "Building \u0026 Trades",
        "subcategory": "Electrical",
        "type": "Services"
      }
    ],
    "sg:phone": "+1 330 825 9324",
    "sg:postcode": "44203",
    "sg:province": "OH",
    "sg:tags": [
      "electrical",
      "contractor"
    ],
    "wof:name": "Guidebore Services Inc",
    "wof:placetype": "venue"
  },
  "geometry": {"coordinates":[-81.635589,41.025892],"type":"Point"}
}
