{
  "type": "Feature",
  "properties": {
    "addr:full": "3562 State Rte 774 Bethel OH 45106",
    "addr:housenumber": "3562",
    "addr:postcode": "45106",
    "addr:street": "State Rte 774",
    "iso:country": "US",
    "sg:address": "3562 State Rte 774",
    "sg:city": "Bethel",
    "sg:classifiers": [
      {
        "category": "Farming",
        "subcategory": "Livestock Farm",
        "type": "Manufacturing \u0026 Wholesale Goods"
      }
    ],
    "sg:phone": "+1 513 733 3368",
    "sg:postcode": "45106",
    "sg:province": "OH",
    "sg:tags": [
      "beef",
      "feedlot",
      "cattle"
    ],
    "wof:name": "Robert Niehaus",
    "wof:placetype": "venue"
  },
  "geometry": {"coordinates":[-84.061368,38.886541],"type":"Point"}
}
