{
  "type": "Feature",
  "properties": {
    "addr:full":"1200 Buckeye Ave Salem OH 44460",
    "addr:housenumber":"1200",
    "addr:postcode":"44460",
    "addr:street":"Buckeye Ave",
    "iso:country":"US",
    "sg:address":"1200 Buckeye Ave",
    "sg:city":"Salem",
    "sg:classifiers":[
        {
            "category":"Education",
            "subcategory":"School",
            "type":"Public Place"
        }
    ],
    "sg:phone":"+1 330 332 8917",
    "sg:postcode":"44460",
    "sg:province":"OH",
    "wof:name":"Buckeye Elementary School",
    "wof:placetype":"venue"
},
  "geometry": {"coordinates":[-80.85964800000001,40.911672],"type":"Point"}
}