{
  "type": "Feature",
  "properties": {
    "addr:full":"4881 Mahoning Ave Youngstown OH 44515",
    "addr:housenumber":"4881",
    "addr:postcode":"44515",
    "addr:street":"Mahoning Ave",
    "iso:country":"US",
    "sg:address":"4881 Mahoning Ave",
    "sg:city":"Youngstown",
    "sg:classifiers":[
        {
            "category":"Retail",
            "subcategory":"Auto Repair",
            "type":"Services"
        }
    ],
    "sg:phone":"+1 330 793 1309",
    "sg:postcode":"44515",
    "sg:province":"OH",
    "sg:tags":[
        "repairing",
        "automobile"
    ],
    "wof:name":"West Side Tire & Svc",
    "wof:placetype":"venue"
},
  "geometry": {"coordinates":[-80.747041,41.100197],"type":"Point"}
}