{
  "type": "Feature",
  "properties": {
    "addr:full": "120 Seminary Ave Dayton OH 45403",
    "addr:housenumber": "120",
    "addr:postcode": "45403",
    "addr:street": "Seminary Ave",
    "iso:country": "US",
    "sg:address": "120 Seminary Ave",
    "sg:city": "Dayton",
    "sg:classifiers": [
      {
        "category": "Building \u0026 Trades",
        "subcategory": "Construction",
        "type": "Services"
      }
    ],
    "sg:phone": "+1 937 254 0936",
    "sg:postcode": "45403",
    "sg:province": "OH",
    "sg:tags": [
      "siding",
      "contractor"
    ],
    "wof:name": "Greater Dayton Aluminum",
    "wof:placetype": "venue"
  },
  "geometry": {"coordinates":[-84.146191,39.754896],"type":"Point"}
}
