{
  "type": "Feature",
  "properties": {
    "addr:full": "701 N Miami St West Milton OH 45383",
    "addr:housenumber": "701",
    "addr:postcode": "45383",
    "addr:street": "N Miami St West",
    "iso:country": "US",
    "sg:address": "701 N Miami St",
    "sg:city": "West Milton",
    "sg:classifiers": [
      {
        "category": "Government",
        "subcategory": "Fire Station",
        "type": "Public Place"
      }
    ],
    "sg:phone": "+1 937 698 9633",
    "sg:postcode": "45383",
    "sg:province": "OH",
    "sg:tags": [
      "department"
    ],
    "wof:name": "Fire Station",
    "wof:placetype": "venue"
  },
  "geometry": {"coordinates":[-84.329968,39.972268],"type":"Point"}
}
