{
  "type": "Feature",
  "properties": {
    "iso:country":"US",
    "sg:address":"7071 Corporate Way",
    "sg:city":"Dayton",
    "sg:classifiers":[
        {
            "category":"Professional",
            "subcategory":"Computer Services",
            "type":"Services"
        }
    ],
    "sg:phone":"+1 937 435 9355",
    "sg:postcode":"45459",
    "sg:province":"OH",
    "sg:tags":[
        "repair"
    ],
    "wof:name":"MCC Computers",
    "wof:placetype":"venue"
},
  "geometry": {"coordinates":[-84.160811,39.641704],"type":"Point"}
}