{
  "type": "Feature",
  "properties": {
    "iso:country":"US",
    "sg:address":"2014 Zettler Rd",
    "sg:city":"Columbus",
    "sg:classifiers":[
        {
            "category":"Building & Trades",
            "subcategory":"Construction",
            "type":"Services"
        }
    ],
    "sg:phone":"+1 614 231 3944",
    "sg:postcode":"43232",
    "sg:province":"OH",
    "sg:tags":[
        "garage",
        "builder"
    ],
    "wof:name":"Just Garages",
    "wof:placetype":"venue"
},
  "geometry": {"coordinates":[-82.91183,39.932554],"type":"Point"}
}