{
  "type": "Feature",
  "properties": {
    "iso:country":"US",
    "sg:address":"8511 Shiloh-Norwalk Rd",
    "sg:city":"Shiloh",
    "sg:classifiers":[
        {
            "category":"Manufacturing",
            "subcategory":"Lumber",
            "type":"Manufacturing & Wholesale Goods"
        }
    ],
    "sg:phone":"+1 419 896 2231",
    "sg:postcode":"44878",
    "sg:province":"OH",
    "sg:tags":[
        "hardwood",
        "mill",
        "wood",
        "mfg"
    ],
    "wof:name":"Kaple Lumber Co",
    "wof:placetype":"venue"
},
  "geometry": {"coordinates":[-82.605401,40.986558],"type":"Point"}
}