{
  "type": "Feature",
  "properties": {
    "addr:full": "2935 E 14th Ave Columbus OH 43219",
    "addr:housenumber": "2935",
    "addr:postcode": "43219",
    "addr:street": "E 14Th Ave",
    "iso:country": "US",
    "sg:address": "2935 E 14th Ave",
    "sg:city": "Columbus",
    "sg:classifiers": [
      {
        "category": "Building \u0026 Trades",
        "subcategory": "Construction",
        "type": "Services"
      }
    ],
    "sg:phone": "+1 614 253 8850",
    "sg:postcode": "43219",
    "sg:province": "OH",
    "sg:tags": [
      "hanging",
      "general",
      "contractor"
    ],
    "wof:name": "Journeyman Construction Svcs",
    "wof:placetype": "venue"
  },
  "geometry": {"coordinates":[-82.924835,39.99372],"type":"Point"}
}
