{
  "type": "Feature",
  "properties": {
    "addr:full":"845 Lookout Point Dr Columbus OH 43235",
    "addr:housenumber":"845",
    "addr:postcode":"43235",
    "addr:street":"Lookout Point Dr",
    "iso:country":"US",
    "sg:address":"845 Lookout Point Dr",
    "sg:city":"Columbus",
    "sg:classifiers":[
        {
            "category":"Real Estate",
            "subcategory":"Real Estate Agent",
            "type":"Services"
        }
    ],
    "sg:phone":"+1 614 848 3320",
    "sg:postcode":"43235",
    "sg:province":"OH",
    "wof:name":"Condominium Administrators",
    "wof:placetype":"venue"
},
  "geometry": {"coordinates":[-83.039293,40.125832],"type":"Point"}
}