{
  "type": "Feature",
  "properties": {
    "addr:full": "4991 Patricia Dr Akron OH 44319",
    "addr:housenumber": "4991",
    "addr:postcode": "44319",
    "addr:street": "Patricia Dr",
    "iso:country": "US",
    "sg:address": "4991 Patricia Dr",
    "sg:city": "Akron",
    "sg:classifiers": [
      {
        "category": "Building \u0026 Trades",
        "subcategory": "Landscaping Services",
        "type": "Services"
      }
    ],
    "sg:phone": "+1 330 848 0864",
    "sg:postcode": "44319",
    "sg:province": "OH",
    "sg:tags": [
      "lawn",
      "garden"
    ],
    "wof:name": "Wesig Landscape",
    "wof:placetype": "venue"
  },
  "geometry": {"coordinates":[-81.562651,40.967623],"type":"Point"}
}
