{
  "type": "Feature",
  "properties": {
    "addr:full": "24656 Brimstone Rd Coolville OH 45723",
    "addr:postcode": "24656;45723",
    "addr:street": "Brimstone Rd",
    "iso:country": "US",
    "sg:address": "24656 Brimstone Rd",
    "sg:city": "Coolville",
    "sg:classifiers": [
      {
        "category": "Recreation",
        "type": "Entertainment"
      }
    ],
    "sg:phone": "+1 740 667 6117",
    "sg:postcode": "45723",
    "sg:province": "OH",
    "sg:tags": [
      "club",
      "membership"
    ],
    "wof:name": "Gold Wing Road Riders Assn",
    "wof:placetype": "venue"
  },
  "geometry": {"coordinates":[-81.826555,39.239291],"type":"Point"}
}
