{
  "type": "Feature",
  "properties": {
    "addr:full":"5702 Perkins Rd Cleveland OH 44146",
    "addr:housenumber":"5702",
    "addr:postcode":"44146",
    "addr:street":"Perkins Rd",
    "iso:country":"US",
    "sg:address":"5702 Perkins Rd",
    "sg:city":"Cleveland",
    "sg:classifiers":[
        {
            "category":"Professional",
            "type":"Services"
        }
    ],
    "sg:phone":"+1 440 786 7219",
    "sg:postcode":"44146",
    "sg:province":"OH",
    "sg:tags":[
        "establishment"
    ],
    "wof:name":"Donald Pate & Assoc",
    "wof:placetype":"venue"
},
  "geometry": {"coordinates":[-81.49862400000001,41.402824],"type":"Point"}
}