{
  "type": "Feature",
  "properties": {
    "addr:full":"200 Howard St Bridgeport OH 43912",
    "addr:housenumber":"200",
    "addr:postcode":"43912",
    "addr:street":"Howard St",
    "iso:country":"US",
    "sg:address":"200 Howard St",
    "sg:city":"Bridgeport",
    "sg:classifiers":[
        {
            "category":"Organizations",
            "subcategory":"Religious Organization",
            "type":"Services"
        }
    ],
    "sg:phone":"+1 740 633 0799",
    "sg:postcode":"43912",
    "sg:province":"OH",
    "sg:tags":[
        "church"
    ],
    "wof:name":"Mt Zion Baptist Church",
    "wof:placetype":"venue"
},
  "geometry": {"coordinates":[-80.740774,40.069882],"type":"Point"}
}