{
  "type": "Feature",
  "properties": {
    "addr:full": "11950 Lagrange Rd Elyria OH 44035",
    "addr:housenumber": "11950",
    "addr:postcode": "44035",
    "addr:street": "Lagrange Rd",
    "iso:country": "US",
    "sg:address": "11950 Lagrange Rd",
    "sg:city": "Elyria",
    "sg:classifiers": [
      {
        "category": "Government",
        "subcategory": "Fire Station",
        "type": "Public Place"
      }
    ],
    "sg:phone": "+1 440 458 5177",
    "sg:postcode": "44035",
    "sg:province": "OH",
    "sg:tags": [
      "department"
    ],
    "wof:name": "Carlisle Township Fire Station",
    "wof:placetype": "venue"
  },
  "geometry": {"coordinates":[-82.117657,41.323511],"type":"Point"}
}
