{
  "type": "Feature",
  "properties": {
    "iso:country":"US",
    "sg:address":"5757 Whiteford Rd",
    "sg:city":"Sylvania",
    "sg:classifiers":[
        {
            "category":"Communications",
            "type":"Services"
        }
    ],
    "sg:phone":"+1 419 824 2700",
    "sg:postcode":"43560",
    "sg:province":"OH",
    "wof:name":"American Communications",
    "wof:placetype":"venue"
},
  "geometry": {"coordinates":[-83.666068,41.720349],"type":"Point"}
}