{
  "type": "Feature",
  "properties": {
    "addr:full": "2601 Tuscarawas St W Canton OH 44708",
    "addr:housenumber": "2601",
    "addr:postcode": "44708",
    "addr:street": "Tuscarawas St W",
    "iso:country": "US",
    "sg:address": "2601 Tuscarawas St W",
    "sg:city": "Canton",
    "sg:classifiers": [
      {
        "category": "Shopping",
        "subcategory": "Pharmacy",
        "type": "Retail Goods"
      }
    ],
    "sg:phone": "+1 330 438 1730",
    "sg:postcode": "44708",
    "sg:province": "OH",
    "wof:name": "Medicine Shoppe",
    "wof:placetype": "venue"
  },
  "geometry": {"coordinates":[-81.40471,40.798915],"type":"Point"}
}
