{
  "type": "Feature",
  "properties": {
    "iso:country":"US",
    "sg:address":"2601 Tuscarawas St W",
    "sg:city":"Canton",
    "sg:classifiers":[
        {
            "category":"Shopping",
            "subcategory":"Pharmacy",
            "type":"Retail Goods"
        }
    ],
    "sg:phone":"+1 330 438 1730",
    "sg:postcode":"44708",
    "sg:province":"OH",
    "wof:name":"Medicine Shoppe",
    "wof:placetype":"venue"
},
  "geometry": {"coordinates":[-81.40470999999999,40.798915],"type":"Point"}
}