{
  "type": "Feature",
  "properties": {
    "iso:country":"US",
    "sg:address":"2022 Waite Ave",
    "sg:city":"Toledo",
    "sg:classifiers":[
        {
            "category":"Social Services",
            "type":"Services"
        }
    ],
    "sg:phone":"+1 419 242 8412",
    "sg:postcode":"43606",
    "sg:province":"OH",
    "sg:tags":[
        "organization",
        "welfare"
    ],
    "wof:name":"Open Arms Community Church",
    "wof:placetype":"venue"
},
  "geometry": {"coordinates":[-83.568053,41.662701],"type":"Point"}
}