{
  "type": "Feature",
  "properties": {
    "addr:full":"168 Solon Rd Chagrin Falls OH 44022",
    "addr:housenumber":"168",
    "addr:postcode":"44022",
    "addr:street":"Solon Rd",
    "iso:country":"US",
    "sg:address":"168 Solon Rd",
    "sg:city":"Chagrin Falls",
    "sg:classifiers":[
        {
            "category":"Insurance",
            "subcategory":"Insurance Agent",
            "type":"Services"
        }
    ],
    "sg:phone":"+1 440 247 5787",
    "sg:postcode":"44022",
    "sg:province":"OH",
    "wof:name":"Jerry Stackpole",
    "wof:placetype":"venue"
},
  "geometry": {"coordinates":[-81.39690400000001,41.426542],"type":"Point"}
}