{
  "type": "Feature",
  "properties": {
    "addr:full": "7731 Alvamar Ct Pickerington OH 43147",
    "addr:housenumber": "7731",
    "addr:postcode": "43147",
    "addr:street": "Alvamar Ct",
    "iso:country": "US",
    "sg:address": "7731 Alvamar Ct",
    "sg:city": "Pickerington",
    "sg:classifiers": [
      {
        "category": "Building \u0026 Trades",
        "subcategory": "Plumbing",
        "type": "Services"
      }
    ],
    "sg:phone": "+1 614 866 0228",
    "sg:postcode": "43147",
    "sg:province": "OH",
    "sg:tags": [
      "cooling",
      "heating",
      "contractor"
    ],
    "wof:name": "Total Temperature Mechanical",
    "wof:placetype": "venue"
  },
  "geometry": {"coordinates":[-82.793796,39.922492],"type":"Point"}
}
