{
  "type": "Feature",
  "properties": {
    "addr:full": "9123 Broadview Rd Broadview Heights OH 44147",
    "addr:housenumber": "9123",
    "addr:postcode": "44147",
    "addr:street": "Broadview Rd",
    "iso:country": "US",
    "sg:address": "9123 Broadview Rd",
    "sg:city": "Broadview Heights",
    "sg:classifiers": [
      {
        "category": "Building \u0026 Trades",
        "subcategory": "Construction",
        "type": "Services"
      }
    ],
    "sg:phone": "+1 440 526 4179",
    "sg:postcode": "44147",
    "sg:province": "OH",
    "sg:tags": [
      "house"
    ],
    "wof:name": "First Choice Home Remodelers",
    "wof:placetype": "venue"
  },
  "geometry": {"coordinates":[-81.684611,41.315614],"type":"Point"}
}
