{
  "type": "Feature",
  "properties": {
    "addr:full": "1488 Mount Pleasant St NW North Canton OH 44720",
    "addr:housenumber": "1488",
    "addr:postcode": "44720",
    "addr:street": "Mount Pleasant St Nw",
    "iso:country": "US",
    "sg:address": "1488 Mount Pleasant St NW",
    "sg:city": "North Canton",
    "sg:classifiers": [
      {
        "category": "Building \u0026 Trades",
        "subcategory": "Landscaping Services",
        "type": "Services"
      }
    ],
    "sg:phone": "+1 330 499 3366",
    "sg:postcode": "44720",
    "sg:province": "OH",
    "sg:tags": [
      "lawn",
      "maintenance",
      "grounds"
    ],
    "wof:name": "Sample's Lawn Care",
    "wof:placetype": "venue"
  },
  "geometry": {"coordinates":[-81.370266,40.904971],"type":"Point"}
}
