{
  "type": "Feature",
  "properties": {
    "iso:country":"US",
    "sg:address":"2815 S Gettysburg Ave",
    "sg:city":"Dayton",
    "sg:classifiers":[
        {
            "category":"Professional",
            "type":"Services"
        }
    ],
    "sg:phone":"+1 937 268 0335",
    "sg:postcode":"45418",
    "sg:province":"OH",
    "sg:tags":[
        "establishment"
    ],
    "wof:name":"Miller Valentine Group",
    "wof:placetype":"venue"
},
  "geometry": {"coordinates":[-84.252173,39.708492],"type":"Point"}
}