{
  "type": "Feature",
  "properties": {
    "addr:full": "200 W Lorain St Oberlin OH 44074",
    "addr:housenumber": "200",
    "addr:postcode": "44074",
    "addr:street": "W Lorain St",
    "iso:country": "US",
    "sg:address": "200 W Lorain St",
    "sg:city": "Oberlin",
    "sg:classifiers": [
      {
        "category": "Health Services",
        "subcategory": "Doctor",
        "type": "Services"
      },
      {
        "category": "Health Services",
        "subcategory": "Hospital",
        "type": "Services"
      },
      {
        "category": "Health Services",
        "subcategory": "Medical Lab",
        "type": "Services"
      },
      {
        "category": "Community Center",
        "type": "Public Place"
      }
    ],
    "sg:phone": "+1 440 775 1211",
    "sg:postcode": "44074",
    "sg:province": "OH",
    "sg:tags": [
      "physician",
      "surgeon",
      "laboratory"
    ],
    "sg:website": "http://www.community-health-partners.com",
    "wof:name": "Allen Community Hospital",
    "wof:placetype": "venue"
  },
  "geometry": {"coordinates":[-82.209929,41.294105],"type":"Point"}
}
