{
  "type": "Feature",
  "properties": {
    "iso:country":"US",
    "sg:address":"1988 Parkman Rd NW",
    "sg:city":"Warren",
    "sg:classifiers":[
        {
            "category":"Health Services",
            "subcategory":"Doctor",
            "type":"Services"
        }
    ],
    "sg:phone":"+1 330 399 4243",
    "sg:postcode":"44485",
    "sg:province":"OH",
    "sg:tags":[
        "physician",
        "surgeon",
        "medical"
    ],
    "wof:name":"Cecil F Desai MD",
    "wof:placetype":"venue"
},
  "geometry": {"coordinates":[-80.848108,41.247574],"type":"Point"}
}