{
  "type": "Feature",
  "properties": {
    "iso:country":"US",
    "sg:address":"1940 Cherry Valley Rd NE",
    "sg:city":"Newark",
    "sg:classifiers":[
        {
            "category":"Real Estate",
            "subcategory":"Real Estate Agent",
            "type":"Services"
        }
    ],
    "sg:phone":"+1 740 522 1899",
    "sg:postcode":"43055",
    "sg:province":"OH",
    "wof:name":"Shurtz Management Corp",
    "wof:placetype":"venue"
},
  "geometry": {"coordinates":[-82.47065499999999,40.043443],"type":"Point"}
}