{
  "type": "Feature",
  "properties": {
    "addr:full": "753 Ewart Rd Akron OH 44312",
    "addr:housenumber": "753",
    "addr:postcode": "44312",
    "addr:street": "Ewart Rd",
    "iso:country": "US",
    "sg:address": "753 Ewart Rd",
    "sg:city": "Akron",
    "sg:classifiers": [
      {
        "category": "Building \u0026 Trades",
        "subcategory": "Construction",
        "type": "Services"
      }
    ],
    "sg:phone": "+1 330 628 3582",
    "sg:postcode": "44312",
    "sg:province": "OH",
    "sg:tags": [
      "resurfacing",
      "laying",
      "refinishing",
      "floor"
    ],
    "wof:name": "Wuorinen Interiors",
    "wof:placetype": "venue"
  },
  "geometry": {"coordinates":[-81.413721,41.032732],"type":"Point"}
}
