{
  "type": "Feature",
  "properties": {
    "addr:full": "1013 Dover Ave Akron OH 44320",
    "addr:housenumber": "1013",
    "addr:postcode": "44320",
    "addr:street": "Dover Ave",
    "iso:country": "US",
    "sg:address": "1013 Dover Ave",
    "sg:city": "Akron",
    "sg:classifiers": [
      {
        "category": "Shopping",
        "type": "Retail Goods"
      }
    ],
    "sg:phone": "+1 330 869 9920",
    "sg:postcode": "44320",
    "sg:province": "OH",
    "sg:tags": [
      "make"
    ],
    "wof:name": "Mary Kay Cosmetics",
    "wof:placetype": "venue"
  },
  "geometry": {"coordinates":[-81.561803,41.079513],"type":"Point"}
}
