{
  "type": "Feature",
  "properties": {
    "addr:full":"6491 Beechwood Ln Hillsboro OH 45133",
    "addr:housenumber":"6491",
    "addr:postcode":"45133",
    "addr:street":"Beechwood Ln",
    "iso:country":"US",
    "sg:address":"6491 Beechwood Ln",
    "sg:city":"Hillsboro",
    "sg:classifiers":[
        {
            "category":"Restaurant",
            "type":"Food & Drink"
        }
    ],
    "sg:phone":"+1 937 393 3774",
    "sg:postcode":"45133",
    "sg:province":"OH",
    "sg:tags":[
        "eating"
    ],
    "wof:name":"Chit Chat Restaurant",
    "wof:placetype":"venue"
},
  "geometry": {"coordinates":[-83.501813,39.19013],"type":"Point"}
}