{
  "type": "Feature",
  "properties": {
    "addr:full": "5501 E Foxhaven Dr Port Clinton OH 43452",
    "addr:housenumber": "5501",
    "addr:postcode": "43452",
    "addr:street": "E Foxhaven Dr",
    "iso:country": "US",
    "sg:address": "5501 E Foxhaven Dr",
    "sg:city": "Port Clinton",
    "sg:classifiers": [
      {
        "category": "Professional",
        "subcategory": "Accounting \u0026 Tax Preparation",
        "type": "Services"
      }
    ],
    "sg:phone": "+1 419 797 4848",
    "sg:postcode": "43452",
    "sg:province": "OH",
    "sg:tags": [
      "bookkeeping",
      "general"
    ],
    "wof:name": "North Coast Bookkeeping",
    "wof:placetype": "venue"
  },
  "geometry": {"coordinates":[-82.829139,41.564549],"type":"Point"}
}
