{
  "type": "Feature",
  "properties": {
    "iso:country":"US",
    "sg:address":"1289 Edison St NW",
    "sg:city":"Hartville",
    "sg:classifiers":[
        {
            "category":"Shopping",
            "subcategory":"Gifts & Souvenirs",
            "type":"Retail Goods"
        }
    ],
    "sg:phone":"+1 330 587 0053",
    "sg:postcode":"44632",
    "sg:province":"OH",
    "sg:tags":[
        "collectible"
    ],
    "wof:name":"Hartville Collectibles",
    "wof:placetype":"venue"
},
  "geometry": {"coordinates":[-81.356981,40.970206],"type":"Point"}
}