{
  "type": "Feature",
  "properties": {
    "iso:country":"US",
    "sg:address":"16 S Highland Ave",
    "sg:city":"Akron",
    "sg:classifiers":[
        {
            "category":"Personal",
            "subcategory":"Beauty Salon",
            "type":"Services"
        }
    ],
    "sg:phone":"+1 330 535 9905",
    "sg:postcode":"44303",
    "sg:province":"OH",
    "wof:name":"J C's Hair Designs",
    "wof:placetype":"venue"
},
  "geometry": {"coordinates":[-81.544454,41.094827],"type":"Point"}
}