{
  "type": "Feature",
  "properties": {
    "iso:country":"US",
    "sg:address":"8040 Conservancy Rd",
    "sg:city":"Germantown",
    "sg:classifiers":[
        {
            "category":"Freight",
            "type":"Transportation"
        }
    ],
    "sg:phone":"+1 937 855 4128",
    "sg:postcode":"45327",
    "sg:province":"OH",
    "sg:tags":[
        "grain",
        "elevator"
    ],
    "wof:name":"Ro-Lin Farms",
    "wof:placetype":"venue"
},
  "geometry": {"coordinates":[-84.41226399999999,39.631891],"type":"Point"}
}