{
  "type": "Feature",
  "properties": {
    "addr:full": "8040 Conservancy Rd Germantown OH 45327",
    "addr:housenumber": "8040",
    "addr:postcode": "45327",
    "addr:street": "Conservancy Rd",
    "iso:country": "US",
    "sg:address": "8040 Conservancy Rd",
    "sg:city": "Germantown",
    "sg:classifiers": [
      {
        "category": "Freight",
        "type": "Transportation"
      }
    ],
    "sg:phone": "+1 937 855 4128",
    "sg:postcode": "45327",
    "sg:province": "OH",
    "sg:tags": [
      "grain",
      "elevator"
    ],
    "wof:name": "Ro-Lin Farms",
    "wof:placetype": "venue"
  },
  "geometry": {"coordinates":[-84.412264,39.631891],"type":"Point"}
}
