{
  "type": "Feature",
  "properties": {
    "addr:full": "100 Pine Ave Saint Clairsville OH 43950",
    "addr:housenumber": "100",
    "addr:postcode": "43950",
    "addr:street": "Pine Ave Saint",
    "iso:country": "US",
    "sg:address": "100 Pine Ave",
    "sg:city": "Saint Clairsville",
    "sg:classifiers": [
      {
        "category": "Health Services",
        "subcategory": "Nursing And Care Facility",
        "type": "Services"
      }
    ],
    "sg:phone": "+1 740 695 4925",
    "sg:postcode": "43950",
    "sg:province": "OH",
    "sg:tags": [
      "home",
      "skilled"
    ],
    "wof:name": "Park Health Center",
    "wof:placetype": "venue"
  },
  "geometry": {"coordinates":[-80.913769,40.08043],"type":"Point"}
}
