{
  "type": "Feature",
  "properties": {
    "addr:full": "10304 Miles Ave Cleveland OH 44105",
    "addr:housenumber": "10304",
    "addr:postcode": "44105",
    "addr:street": "Miles Ave",
    "iso:country": "US",
    "sg:address": "10304 Miles Ave",
    "sg:city": "Cleveland",
    "sg:classifiers": [
      {
        "category": "Government",
        "subcategory": "Office",
        "type": "Public Place"
      }
    ],
    "sg:phone": "+1 216 441 8432",
    "sg:postcode": "44105",
    "sg:province": "OH",
    "sg:tags": [
      "housing",
      "program",
      "administration",
      "agency"
    ],
    "wof:name": "Cuyahoga Housing Authority",
    "wof:placetype": "venue"
  },
  "geometry": {"coordinates":[-81.612377,41.44507],"type":"Point"}
}
