{
  "type": "Feature",
  "properties": {
    "addr:full": "2523 Hamilton Ave Cleveland OH 44114",
    "addr:housenumber": "2523",
    "addr:postcode": "44114",
    "addr:street": "Hamilton Ave",
    "iso:country": "US",
    "sg:address": "2523 Hamilton Ave",
    "sg:city": "Cleveland",
    "sg:phone": "+1 216 622 2920",
    "sg:postcode": "44114",
    "sg:province": "OH",
    "sg:tags": [
      "business"
    ],
    "wof:name": "Psx Inc",
    "wof:placetype": "venue"
  },
  "geometry": {"coordinates":[-81.676829,41.511345],"type":"Point"}
}
