{
  "type": "Feature",
  "properties": {
    "iso:country":"US",
    "sg:address":"2523 Hamilton Ave",
    "sg:city":"Cleveland",
    "sg:phone":"+1 216 622 2920",
    "sg:postcode":"44114",
    "sg:province":"OH",
    "sg:tags":[
        "business"
    ],
    "wof:name":"Psx Inc",
    "wof:placetype":"venue"
},
  "geometry": {"coordinates":[-81.676829,41.511345],"type":"Point"}
}