{
  "type": "Feature",
  "properties": {
    "addr:full":"5788 Ridge Rd Cleveland OH 44129",
    "addr:housenumber":"5788",
    "addr:postcode":"44129",
    "addr:street":"Ridge Rd",
    "iso:country":"US",
    "sg:address":"5788 Ridge Rd",
    "sg:city":"Cleveland",
    "sg:classifiers":[
        {
            "category":"Real Estate",
            "subcategory":"Real Estate Agent",
            "type":"Services"
        }
    ],
    "sg:phone":"+1 440 888 3676",
    "sg:postcode":"44129",
    "sg:province":"OH",
    "wof:name":"Snow Ridge Partners LTD",
    "wof:placetype":"venue"
},
  "geometry": {"coordinates":[-81.734641,41.405477],"type":"Point"}
}