{
  "type": "Feature",
  "properties": {
    "addr:full": "548 Greenbriar Dr Ravenna OH 44266",
    "addr:housenumber": "548",
    "addr:postcode": "44266",
    "addr:street": "Greenbriar Dr",
    "iso:country": "US",
    "sg:address": "548 Greenbriar Dr",
    "sg:city": "Ravenna",
    "sg:classifiers": [
      {
        "category": "Manufacturing",
        "subcategory": "Tools \u0026 Machinery",
        "type": "Manufacturing \u0026 Wholesale Goods"
      }
    ],
    "sg:phone": "+1 330 296 3616",
    "sg:postcode": "44266",
    "sg:province": "OH",
    "sg:tags": [
      "mfg",
      "industrial",
      "general"
    ],
    "wof:name": "Ralph E Kelley",
    "wof:placetype": "venue"
  },
  "geometry": {"coordinates":[-81.222295,41.162208],"type":"Point"}
}
