{
  "type": "Feature",
  "properties": {
    "addr:full":"4193 Center Rd Brunswick OH 44212",
    "addr:housenumber":"4193",
    "addr:postcode":"44212",
    "addr:street":"Center Rd",
    "iso:country":"US",
    "sg:address":"4193 Center Rd",
    "sg:city":"Brunswick",
    "sg:classifiers":[
        {
            "category":"Real Estate",
            "subcategory":"Real Estate Agent",
            "type":"Services"
        }
    ],
    "sg:phone":"+1 330 225 7777",
    "sg:postcode":"44212",
    "sg:province":"OH",
    "sg:website":"www.realtyone.com",
    "wof:name":"Realty One",
    "wof:placetype":"venue"
},
  "geometry": {"coordinates":[-81.837253,41.238342],"type":"Point"}
}