{
  "type": "Feature",
  "properties": {
    "iso:country":"US",
    "sg:address":"117 E Main St",
    "sg:city":"Pandora",
    "sg:classifiers":[
        {
            "category":"Real Estate",
            "subcategory":"Real Estate Agent",
            "type":"Services"
        }
    ],
    "sg:phone":"+1 419 384 7653",
    "sg:postcode":"45877",
    "sg:province":"OH",
    "wof:name":"Kimmet Realty LLC",
    "wof:placetype":"venue"
},
  "geometry": {"coordinates":[-83.961825,40.948245],"type":"Point"}
}