{
  "type": "Feature",
  "properties": {
    "iso:country":"US",
    "sg:address":"2222 Madison Rd",
    "sg:city":"Cincinnati",
    "sg:classifiers":[
        {
            "category":"Professional",
            "subcategory":"Art Services",
            "type":"Services"
        }
    ],
    "sg:phone":"+1 513 871 6660",
    "sg:postcode":"45208",
    "sg:province":"OH",
    "sg:tags":[
        "photographer"
    ],
    "wof:name":"Joseph Galli Photography",
    "wof:placetype":"venue"
},
  "geometry": {"coordinates":[-84.458843,39.133676],"type":"Point"}
}