{
  "type": "Feature",
  "properties": {
    "addr:full": "14605 Granger Rd Cleveland OH 44137",
    "addr:housenumber": "14605",
    "addr:postcode": "44137",
    "addr:street": "Granger Rd",
    "iso:country": "US",
    "sg:address": "14605 Granger Rd",
    "sg:city": "Cleveland",
    "sg:classifiers": [
      {
        "category": "Education",
        "subcategory": "School",
        "type": "Public Place"
      }
    ],
    "sg:phone": "+1 216 587 6130",
    "sg:postcode": "44137",
    "sg:province": "OH",
    "sg:website": "www.mapleheightsk12.com",
    "wof:name": "Maple Hts Board-Ed Psychlgst",
    "wof:placetype": "venue"
  },
  "geometry": {"coordinates":[-81.58033,41.416754],"type":"Point"}
}
