{
  "type": "Feature",
  "properties": {
    "addr:full": "2546 Romig Rd Akron OH 44320",
    "addr:housenumber": "2546",
    "addr:postcode": "44320",
    "addr:street": "Romig Rd",
    "iso:country": "US",
    "sg:address": "2546 Romig Rd",
    "sg:city": "Akron",
    "sg:classifiers": [
      {
        "category": "Restaurant",
        "type": "Food \u0026 Drink"
      }
    ],
    "sg:menulink": "http://www.allmenus.com/oh/akron/164576-wendys/menu/",
    "sg:phone": "+1 330 753 4954",
    "sg:postcode": "44320",
    "sg:province": "OH",
    "sg:tags": [
      "burger",
      "american",
      "soup"
    ],
    "wof:name": "Wendy's",
    "wof:placetype": "venue"
  },
  "geometry": {"coordinates":[-81.58115,41.045125],"type":"Point"}
}
