{
  "type": "Feature",
  "properties": {
    "addr:full":"325 Front St Portsmouth OH 45662",
    "addr:housenumber":"325",
    "addr:postcode":"45662",
    "addr:street":"Front St",
    "iso:country":"US",
    "sg:address":"325 Front St",
    "sg:city":"Portsmouth",
    "sg:classifiers":[
        {
            "category":"Farming",
            "subcategory":"Nursery",
            "type":"Manufacturing & Wholesale Goods"
        }
    ],
    "sg:phone":"+1 740 353 2564",
    "sg:postcode":"45662",
    "sg:province":"OH",
    "sg:tags":[
        "greenhouse"
    ],
    "wof:name":"Deatley's Greenhouse",
    "wof:placetype":"venue"
},
  "geometry": {"coordinates":[-83.006811,38.730932],"type":"Point"}
}