{
  "type": "Feature",
  "properties": {
    "iso:country":"US",
    "sg:address":"832 S 30th St",
    "sg:city":"Newark",
    "sg:classifiers":[
        {
            "category":"Personal",
            "subcategory":"Barber",
            "type":"Services"
        }
    ],
    "sg:phone":"+1 740 522 8570",
    "sg:postcode":"43056",
    "sg:province":"OH",
    "sg:tags":[
        "shop",
        "beauty"
    ],
    "wof:name":"Attitudz Hair",
    "wof:placetype":"venue"
},
  "geometry": {"coordinates":[-82.443237,40.0299],"type":"Point"}
}