{
  "type": "Feature",
  "properties": {
    "iso:country":"US",
    "sg:address":"29287 Grande Ct",
    "sg:city":"Cleveland",
    "sg:classifiers":[
        {
            "category":"Professional",
            "type":"Services"
        }
    ],
    "sg:phone":"+1 440 835 3433",
    "sg:postcode":"44145",
    "sg:province":"OH",
    "sg:tags":[
        "establishment"
    ],
    "wof:name":"Robert Fairchild Enterprises",
    "wof:placetype":"venue"
},
  "geometry": {"coordinates":[-81.94293,41.44661],"type":"Point"}
}