{
  "type": "Feature",
  "properties": {
    "iso:country":"US",
    "sg:address":"16 Mohican St",
    "sg:city":"Shelby",
    "sg:classifiers":[
        {
            "category":"Bars & Pubs",
            "type":"Food & Drink"
        }
    ],
    "sg:phone":"+1 419 347 8088",
    "sg:postcode":"44875",
    "sg:province":"OH",
    "sg:tags":[
        "drinking"
    ],
    "wof:name":"Parrothead Paradise",
    "wof:placetype":"venue"
},
  "geometry": {"coordinates":[-82.659172,40.882],"type":"Point"}
}