{
  "type": "Feature",
  "properties": {
    "addr:full": "16 Mohican St Shelby OH 44875",
    "addr:housenumber": "16",
    "addr:postcode": "44875",
    "addr:street": "Mohican St",
    "iso:country": "US",
    "sg:address": "16 Mohican St",
    "sg:city": "Shelby",
    "sg:classifiers": [
      {
        "category": "Bars \u0026 Pubs",
        "type": "Food \u0026 Drink"
      }
    ],
    "sg:phone": "+1 419 347 8088",
    "sg:postcode": "44875",
    "sg:province": "OH",
    "sg:tags": [
      "drinking"
    ],
    "wof:name": "Parrothead Paradise",
    "wof:placetype": "venue"
  },
  "geometry": {"coordinates":[-82.659172,40.882],"type":"Point"}
}
