{
  "type": "Feature",
  "properties": {
    "addr:full":"3729 John Wayne Dr Hamilton OH 45011",
    "addr:housenumber":"3729",
    "addr:postcode":"45011",
    "addr:street":"John Wayne Dr",
    "iso:country":"US",
    "sg:address":"3729 John Wayne Dr",
    "sg:city":"Hamilton",
    "sg:classifiers":[
        {
            "category":"Building & Trades",
            "subcategory":"Construction",
            "type":"Services"
        }
    ],
    "sg:phone":"+1 513 726 4663",
    "sg:postcode":"45011",
    "sg:province":"OH",
    "sg:tags":[
        "house",
        "builder",
        "home"
    ],
    "wof:name":"Reynolds Custom Homes Inc",
    "wof:placetype":"venue"
},
  "geometry": {"coordinates":[-84.52783100000001,39.483292],"type":"Point"}
}