{
  "type": "Feature",
  "properties": {
    "addr:full": "4240 Peru Center Rd N Monroeville OH 44847",
    "addr:housenumber": "4240",
    "addr:postcode": "44847",
    "addr:street": "Peru Center Rd N",
    "iso:country": "US",
    "sg:address": "4240 Peru Center Rd N",
    "sg:city": "Monroeville",
    "sg:phone": "+1 419 465 2090",
    "sg:postcode": "44847",
    "sg:province": "OH",
    "sg:tags": [
      "farm",
      "corn"
    ],
    "wof:name": "Charles Bauer",
    "wof:placetype": "venue"
  },
  "geometry": {"coordinates":[-82.674579,41.289647],"type":"Point"}
}
