{
  "type": "Feature",
  "properties": {
    "addr:full": "4703 Foote Rd Medina OH 44256",
    "addr:housenumber": "4703",
    "addr:postcode": "44256",
    "addr:street": "Foote Rd",
    "iso:country": "US",
    "sg:address": "4703 Foote Rd",
    "sg:city": "Medina",
    "sg:classifiers": [
      {
        "category": "Shopping",
        "subcategory": "Gifts \u0026 Souvenirs",
        "type": "Retail Goods"
      }
    ],
    "sg:phone": "+1 330 725 5695",
    "sg:postcode": "44256",
    "sg:province": "OH",
    "sg:tags": [
      "balloon",
      "artist"
    ],
    "wof:name": "Balloon Designs By Kay",
    "wof:placetype": "venue"
  },
  "geometry": {"coordinates":[-81.835087,41.150389],"type":"Point"}
}
