{
  "type": "Feature",
  "properties": {
    "addr:full":"99 Twp Rd 1233 Proctorville OH 45669",
    "addr:housenumber":"99;1233",
    "addr:postcode":"45669",
    "addr:street":"Twp Rd",
    "iso:country":"US",
    "sg:address":"99 Twp Rd 1233",
    "sg:city":"Proctorville",
    "sg:classifiers":[
        {
            "category":"Wholesale",
            "subcategory":"Non-durable Goods",
            "type":"Manufacturing & Wholesale Goods"
        }
    ],
    "sg:phone":"+1 740 886 6277",
    "sg:postcode":"45669",
    "sg:province":"OH",
    "sg:tags":[
        "advertising"
    ],
    "wof:name":"Tri State Advertising Corp",
    "wof:placetype":"venue"
},
  "geometry": {"coordinates":[-82.34272300000001,38.44411],"type":"Point"}
}