{
  "type": "Feature",
  "properties": {
    "addr:full": "7824 State Rte 49 Arcanum OH 45304",
    "addr:housenumber": "7824",
    "addr:postcode": "45304",
    "addr:street": "State Rte 49",
    "iso:country": "US",
    "sg:address": "7824 State Rte 49",
    "sg:city": "Arcanum",
    "sg:classifiers": [
      {
        "category": "Building \u0026 Trades",
        "subcategory": "Construction",
        "type": "Services"
      }
    ],
    "sg:phone": "+1 937 692 6330",
    "sg:postcode": "45304",
    "sg:province": "OH",
    "sg:tags": [
      "general",
      "contractor"
    ],
    "wof:name": "Arcon Builders",
    "wof:placetype": "venue"
  },
  "geometry": {"coordinates":[-84.514757,39.990803],"type":"Point"}
}
