{
  "type": "Feature",
  "properties": {
    "iso:country":"US",
    "sg:address":"4588 State Rte 82",
    "sg:city":"Mantua",
    "sg:phone":"+1 330 274 0820",
    "sg:postcode":"44255",
    "sg:province":"OH",
    "sg:tags":[
        "farm",
        "ornamental",
        "nursery"
    ],
    "wof:name":"Mantua Gardens",
    "wof:placetype":"venue"
},
  "geometry": {"coordinates":[-81.229293,41.310251],"type":"Point"}
}