{
  "type": "Feature",
  "properties": {
    "addr:full":"7360 Twp Rd 319 Millersburg OH 44654",
    "addr:housenumber":"7360",
    "addr:postcode":"44654",
    "addr:street":"Twp Rd 319",
    "iso:country":"US",
    "sg:address":"7360 Twp Rd 319",
    "sg:city":"Millersburg",
    "sg:classifiers":[
        {
            "category":"Mining & Drilling",
            "type":"Manufacturing & Wholesale Goods"
        }
    ],
    "sg:phone":"+1 330 674 4926",
    "sg:postcode":"44654",
    "sg:province":"OH",
    "sg:tags":[
        "coal",
        "strip"
    ],
    "wof:name":"R & R Minerals Inc",
    "wof:placetype":"venue"
},
  "geometry": {"coordinates":[-81.887494,40.562261],"type":"Point"}
}