{
  "type": "Feature",
  "properties": {
    "iso:country":"US",
    "sg:address":"1785 O Brien Rd",
    "sg:city":"Columbus",
    "sg:classifiers":[
        {
            "category":"Professional",
            "type":"Services"
        }
    ],
    "sg:phone":"+1 614 777 8538",
    "sg:postcode":"43228",
    "sg:province":"OH",
    "sg:tags":[
        "establishment"
    ],
    "wof:name":"F X Source",
    "wof:placetype":"venue"
},
  "geometry": {"coordinates":[-83.14085300000001,39.951512],"type":"Point"}
}