{
  "type": "Feature",
  "properties": {
    "addr:full":"17529 S Miles Rd Cleveland OH 44128",
    "addr:housenumber":"17529",
    "addr:postcode":"44128",
    "addr:street":"S Miles Rd",
    "iso:country":"US",
    "sg:address":"17529 S Miles Rd",
    "sg:city":"Cleveland",
    "sg:phone":"+1 216 475 2400",
    "sg:postcode":"44128",
    "sg:province":"OH",
    "wof:name":"B & D Restoration",
    "wof:placetype":"venue"
},
  "geometry": {"coordinates":[-81.556319,41.435285],"type":"Point"}
}