{
  "type": "Feature",
  "properties": {
    "addr:full":"2744 State Rte 307 Austinburg OH 44010",
    "addr:housenumber":"2744",
    "addr:postcode":"44010",
    "addr:street":"State Rte 307",
    "iso:country":"US",
    "sg:address":"2744 State Rte 307",
    "sg:city":"Austinburg",
    "sg:classifiers":[
        {
            "category":"Manufacturing",
            "subcategory":"Metals",
            "type":"Manufacturing & Wholesale Goods"
        }
    ],
    "sg:phone":"+1 440 275 3109",
    "sg:postcode":"44010",
    "sg:province":"OH",
    "sg:tags":[
        "steel"
    ],
    "wof:name":"Fab-Tech",
    "wof:placetype":"venue"
},
  "geometry": {"coordinates":[-80.835311,41.769208],"type":"Point"}
}