{
  "type": "Feature",
  "properties": {
    "addr:full": "3250 W Henderson Rd Columbus OH 43220",
    "addr:housenumber": "3250",
    "addr:postcode": "43220",
    "addr:street": "W Henderson Rd",
    "iso:country": "US",
    "sg:address": "3250 W Henderson Rd",
    "sg:city": "Columbus",
    "sg:classifiers": [
      {
        "category": "Education",
        "subcategory": "Vocational School",
        "type": "Public Place"
      },
      {
        "category": "Shopping",
        "subcategory": "Computers \u0026 Home Electronics",
        "type": "Retail Goods"
      }
    ],
    "sg:phone": "+1 614 451 6671",
    "sg:postcode": "43220",
    "sg:province": "OH",
    "sg:tags": [
      "training",
      "software"
    ],
    "wof:name": "Prosoft Inc",
    "wof:placetype": "venue"
  },
  "geometry": {"coordinates":[-83.081398,40.059612],"type":"Point"}
}
