{
  "type": "Feature",
  "properties": {
    "addr:full": "3700 Dixie Hwy Fairfield OH 45014",
    "addr:housenumber": "3700",
    "addr:postcode": "45014",
    "addr:street": "Dixie Hwy",
    "iso:country": "US",
    "sg:address": "3700 Dixie Hwy",
    "sg:city": "Fairfield",
    "sg:classifiers": [
      {
        "category": "Wholesale",
        "subcategory": "Chemicals \u0026 Plastics",
        "type": "Manufacturing \u0026 Wholesale Goods"
      }
    ],
    "sg:phone": "+1 513 737 7100",
    "sg:postcode": "45014",
    "sg:province": "OH",
    "wof:name": "United States Aluminate Co",
    "wof:placetype": "venue"
  },
  "geometry": {"coordinates":[-84.54185,39.359628],"type":"Point"}
}
