{
  "type": "Feature",
  "properties": {
    "iso:country":"US",
    "sg:address":"3700 Dixie Hwy",
    "sg:city":"Fairfield",
    "sg:classifiers":[
        {
            "category":"Wholesale",
            "subcategory":"Chemicals & Plastics",
            "type":"Manufacturing & Wholesale Goods"
        }
    ],
    "sg:phone":"+1 513 737 7100",
    "sg:postcode":"45014",
    "sg:province":"OH",
    "wof:name":"United States Aluminate Co",
    "wof:placetype":"venue"
},
  "geometry": {"coordinates":[-84.54185,39.359628],"type":"Point"}
}