{
  "type": "Feature",
  "properties": {
    "iso:country":"US",
    "sg:address":"1122 Taylor St",
    "sg:city":"Zanesville",
    "sg:classifiers":[
        {
            "category":"Health Services",
            "subcategory":"Nursing And Care Facility",
            "type":"Services"
        }
    ],
    "sg:phone":"+1 740 454 1400",
    "sg:postcode":"43701",
    "sg:province":"OH",
    "sg:tags":[
        "home",
        "convalescent"
    ],
    "wof:name":"Zandex Health Care Corp",
    "wof:placetype":"venue"
},
  "geometry": {"coordinates":[-82.023405,39.968102],"type":"Point"}
}