{
  "type": "Feature",
  "properties": {
    "addr:full": "954 State Rte 28 Milford OH 45150",
    "addr:housenumber": "954",
    "addr:postcode": "45150",
    "addr:street": "State Rte 28",
    "iso:country": "US",
    "sg:address": "954 State Rte 28",
    "sg:city": "Milford",
    "sg:classifiers": [
      {
        "category": "Restaurant",
        "type": "Food \u0026 Drink"
      }
    ],
    "sg:phone": "+1 513 831 2914",
    "sg:postcode": "45150",
    "sg:province": "OH",
    "sg:tags": [
      "eating"
    ],
    "wof:name": "McDonalds",
    "wof:placetype": "venue"
  },
  "geometry": {"coordinates":[-84.25178,39.191604],"type":"Point"}
}
