{
  "type": "Feature",
  "properties": {
    "addr:full":"1221 E Hudson St Columbus OH 43211",
    "addr:housenumber":"1221",
    "addr:postcode":"43211",
    "addr:street":"E Hudson St",
    "iso:country":"US",
    "sg:address":"1221 E Hudson St",
    "sg:city":"Columbus",
    "sg:classifiers":[
        {
            "category":"Autos & Motor Vehicles",
            "subcategory":"Fuel & Gas Station",
            "type":"Retail Goods"
        },
        {
            "category":"Food & Beverages",
            "subcategory":"Groceries & Convenience Stores",
            "type":"Retail Goods"
        }
    ],
    "sg:phone":"+1 614 447 2011",
    "sg:postcode":"43211",
    "sg:province":"OH",
    "wof:name":"Uncle Max Gas & Food",
    "wof:placetype":"venue"
},
  "geometry": {"coordinates":[-82.977501,40.014112],"type":"Point"}
}