{
  "type": "Feature",
  "properties": {
    "iso:country":"US",
    "sg:address":"2724 Mariner Ave",
    "sg:city":"Youngstown",
    "sg:classifiers":[
        {
            "category":"Education",
            "subcategory":"School",
            "type":"Public Place"
        }
    ],
    "sg:phone":"+1 330 744 7823",
    "sg:postcode":"44505",
    "sg:province":"OH",
    "sg:tags":[
        "elementary"
    ],
    "wof:name":"North Elementary School",
    "wof:placetype":"venue"
},
  "geometry": {"coordinates":[-80.59398899999999,41.112072],"type":"Point"}
}