{
  "type": "Feature",
  "properties": {
    "addr:full": "464 Co Rd 37 Scottown OH 45678",
    "addr:housenumber": "464;37",
    "addr:postcode": "45678",
    "addr:street": "Co Rd",
    "iso:country": "US",
    "sg:address": "464 Co Rd 37",
    "sg:city": "Scottown",
    "sg:classifiers": [
      {
        "category": "Personal",
        "subcategory": "Beauty Salon",
        "type": "Services"
      }
    ],
    "sg:phone": "+1 740 643 2522",
    "sg:postcode": "45678",
    "sg:province": "OH",
    "wof:name": "Dial Hilda Beauty Salon",
    "wof:placetype": "venue"
  },
  "geometry": {"coordinates":[-82.384123,38.556498],"type":"Point"}
}
