{
  "type": "Feature",
  "properties": {
    "iso:country":"US",
    "sg:address":"30092 Tracy Rd",
    "sg:city":"Walbridge",
    "sg:classifiers":[
        {
            "category":"Utilities",
            "subcategory":"Cable",
            "type":"Services"
        }
    ],
    "sg:phone":"+1 419 662 9264",
    "sg:postcode":"43465",
    "sg:province":"OH",
    "sg:tags":[
        "television"
    ],
    "wof:name":"Time Warner",
    "wof:placetype":"venue"
},
  "geometry": {"coordinates":[-83.52779,41.586745],"type":"Point"}
}