{
  "type": "Feature",
  "properties": {
    "addr:full": "15 E Main St Lexington OH 44904",
    "addr:housenumber": "15",
    "addr:postcode": "44904",
    "addr:street": "E Main St",
    "iso:country": "US",
    "sg:address": "15 E Main St",
    "sg:city": "Lexington",
    "sg:classifiers": [
      {
        "category": "Organizations",
        "subcategory": "Religious Organization",
        "type": "Services"
      }
    ],
    "sg:phone": "+1 419 884 2633",
    "sg:postcode": "44904",
    "sg:province": "OH",
    "sg:tags": [
      "church"
    ],
    "wof:name": "Orchard Foundation",
    "wof:placetype": "venue"
  },
  "geometry": {"coordinates":[-82.582355,40.678698],"type":"Point"}
}
