{
  "type": "Feature",
  "properties": {
    "iso:country":"US",
    "sg:address":"15 E Main St",
    "sg:city":"Lexington",
    "sg:classifiers":[
        {
            "category":"Organizations",
            "subcategory":"Religious Organization",
            "type":"Services"
        }
    ],
    "sg:phone":"+1 419 884 2633",
    "sg:postcode":"44904",
    "sg:province":"OH",
    "sg:tags":[
        "church"
    ],
    "wof:name":"Orchard Foundation",
    "wof:placetype":"venue"
},
  "geometry": {"coordinates":[-82.58235500000001,40.678698],"type":"Point"}
}