{
  "type": "Feature",
  "properties": {
    "addr:full": "32730 Walker Rd Avon Lake OH 44012",
    "addr:housenumber": "32730",
    "addr:postcode": "44012",
    "addr:street": "Walker Rd",
    "iso:country": "US",
    "sg:address": "32730 Walker Rd",
    "sg:city": "Avon Lake",
    "sg:classifiers": [
      {
        "category": "Health Services",
        "subcategory": "Doctor",
        "type": "Services"
      }
    ],
    "sg:phone": "+1 440 930 4955",
    "sg:postcode": "44012",
    "sg:province": "OH",
    "sg:tags": [
      "physician",
      "medical",
      "surgeon"
    ],
    "wof:name": "West Shore Primary Care Assn",
    "wof:placetype": "venue"
  },
  "geometry": {"coordinates":[-82.021272,41.49324],"type":"Point"}
}
