{
  "type": "Feature",
  "properties": {
    "addr:full": "134 Fieldcrest Dr Delaware OH 43015",
    "addr:housenumber": "134",
    "addr:postcode": "43015",
    "addr:street": "Fieldcrest Dr",
    "iso:country": "US",
    "sg:address": "134 Fieldcrest Dr",
    "sg:city": "Delaware",
    "sg:classifiers": [
      {
        "category": "Professional",
        "subcategory": "Accounting \u0026 Tax Preparation",
        "type": "Services"
      }
    ],
    "sg:phone": "+1 740 369 6138",
    "sg:postcode": "43015",
    "sg:province": "OH",
    "sg:tags": [
      "accountant"
    ],
    "wof:name": "George Klepec",
    "wof:placetype": "venue"
  },
  "geometry": {"coordinates":[-83.035463,40.29908],"type":"Point"}
}
