{
  "type": "Feature",
  "properties": {
    "iso:country":"US",
    "sg:address":"134 Fieldcrest Dr",
    "sg:city":"Delaware",
    "sg:classifiers":[
        {
            "category":"Professional",
            "subcategory":"Accounting & Tax Preparation",
            "type":"Services"
        }
    ],
    "sg:phone":"+1 740 369 6138",
    "sg:postcode":"43015",
    "sg:province":"OH",
    "sg:tags":[
        "accountant"
    ],
    "wof:name":"George Klepec",
    "wof:placetype":"venue"
},
  "geometry": {"coordinates":[-83.03546299999999,40.29908],"type":"Point"}
}