{
  "type": "Feature",
  "properties": {
    "addr:full": "11501 Simms Rd Athens OH 45701",
    "addr:housenumber": "11501",
    "addr:postcode": "45701",
    "addr:street": "Simms Rd",
    "iso:country": "US",
    "sg:address": "11501 Simms Rd",
    "sg:city": "Athens",
    "sg:classifiers": [
      {
        "category": "Wholesale",
        "subcategory": "Toys \u0026 Hobbies",
        "type": "Manufacturing \u0026 Wholesale Goods"
      }
    ],
    "sg:phone": "+1 740 592 4256",
    "sg:postcode": "45701",
    "sg:province": "OH",
    "wof:name": "Jps Crafts N More",
    "wof:placetype": "venue"
  },
  "geometry": {"coordinates":[-82.081752,39.372868],"type":"Point"}
}
