{
  "type": "Feature",
  "properties": {
    "addr:full": "985 Stover Rd West Alexandria OH 45381",
    "addr:housenumber": "985",
    "addr:postcode": "45381",
    "addr:street": "Stover Rd",
    "iso:country": "US",
    "sg:address": "985 Stover Rd",
    "sg:city": "West Alexandria",
    "sg:classifiers": [
      {
        "category": "Building \u0026 Trades",
        "subcategory": "Landscaping Services",
        "type": "Services"
      }
    ],
    "sg:phone": "+1 937 884 7700",
    "sg:postcode": "45381",
    "sg:province": "OH",
    "wof:name": "Fetters Lawn Service",
    "wof:placetype": "venue"
  },
  "geometry": {"coordinates":[-84.566625,39.743426],"type":"Point"}
}
