{
  "type": "Feature",
  "properties": {
    "iso:country":"US",
    "sg:address":"543 State Rte 376",
    "sg:city":"Mc Connelsville",
    "sg:classifiers":[
        {
            "category":"Government",
            "subcategory":"Office",
            "type":"Public Place"
        }
    ],
    "sg:phone":"+1 740 962 2724",
    "sg:postcode":"43756",
    "sg:province":"OH",
    "wof:name":"Muskingum River Lock No 7",
    "wof:placetype":"venue"
},
  "geometry": {"coordinates":[-81.847281,39.644538],"type":"Point"}
}