{
  "type": "Feature",
  "properties": {
    "addr:full": "6504 Woodland Ave Cleveland OH 44104",
    "addr:housenumber": "6504",
    "addr:postcode": "44104",
    "addr:street": "Woodland Ave",
    "iso:country": "US",
    "sg:address": "6504 Woodland Ave",
    "sg:city": "Cleveland",
    "sg:classifiers": [
      {
        "category": "Organizations",
        "subcategory": "Religious Organization",
        "type": "Services"
      }
    ],
    "sg:phone": "+1 216 361 3358",
    "sg:postcode": "44104",
    "sg:province": "OH",
    "sg:tags": [
      "church"
    ],
    "wof:name": "New Bethlehem Baptist Church",
    "wof:placetype": "venue"
  },
  "geometry": {"coordinates":[-81.644367,41.488009],"type":"Point"}
}
