{
  "type": "Feature",
  "properties": {
    "addr:full":"1038 Kinneys Ln Portsmouth OH 45662",
    "addr:housenumber":"1038",
    "addr:postcode":"45662",
    "addr:street":"Kinneys Ln",
    "iso:country":"US",
    "sg:address":"1038 Kinneys Ln",
    "sg:city":"Portsmouth",
    "sg:classifiers":[
        {
            "category":"Health Services",
            "subcategory":"Medical Lab",
            "type":"Services"
        }
    ],
    "sg:phone":"+1 740 354 1711",
    "sg:postcode":"45662",
    "sg:province":"OH",
    "sg:tags":[
        "laboratory"
    ],
    "wof:name":"Valley Diagnostic Labs",
    "wof:placetype":"venue"
},
  "geometry": {"coordinates":[-82.991697,38.747074],"type":"Point"}
}