{
  "type": "Feature",
  "properties": {
    "addr:full":"325 Phillipi Rd Columbus OH 43228",
    "addr:housenumber":"325",
    "addr:postcode":"43228",
    "addr:street":"Phillipi Rd",
    "iso:country":"US",
    "sg:address":"325 Phillipi Rd",
    "sg:city":"Columbus",
    "sg:classifiers":[
        {
            "category":"Shopping",
            "type":"Retail Goods"
        }
    ],
    "sg:phone":"+1 614 351 1111",
    "sg:postcode":"43228",
    "sg:province":"OH",
    "sg:tags":[
        "merchandise"
    ],
    "wof:name":"SRS Communications",
    "wof:placetype":"venue"
},
  "geometry": {"coordinates":[-83.111288,39.964268],"type":"Point"}
}