{
  "type": "Feature",
  "properties": {
    "addr:full": "1401 N Main St North Canton OH 44720",
    "addr:housenumber": "1401",
    "addr:postcode": "44720",
    "addr:street": "N Main St",
    "iso:country": "US",
    "sg:address": "1401 N Main St",
    "sg:city": "North Canton",
    "sg:classifiers": [
      {
        "category": "Building \u0026 Trades",
        "subcategory": "Construction",
        "type": "Services"
      }
    ],
    "sg:phone": "+1 330 497 2222",
    "sg:postcode": "44720",
    "sg:province": "OH",
    "sg:tags": [
      "general",
      "contractor"
    ],
    "wof:name": "St Clair-Pavlis Group",
    "wof:placetype": "venue"
  },
  "geometry": {"coordinates":[-81.406336,40.89534],"type":"Point"}
}
