{
  "type": "Feature",
  "properties": {
    "addr:full": "20 E South St West Alexandria OH 45381",
    "addr:housenumber": "20 e",
    "addr:postcode": "45381",
    "addr:street": "South St West",
    "iso:country": "US",
    "sg:address": "20 E South St",
    "sg:city": "West Alexandria",
    "sg:classifiers": [
      {
        "category": "Banks \u0026 Credit Unions",
        "subcategory": "Bank",
        "type": "Services"
      }
    ],
    "sg:phone": "+1 937 839 1615",
    "sg:postcode": "45381",
    "sg:province": "OH",
    "sg:tags": [
      "national",
      "commercial"
    ],
    "wof:name": "Alexandria West Food Bank",
    "wof:placetype": "venue"
  },
  "geometry": {"coordinates":[-84.531215,39.743549],"type":"Point"}
}
