{
  "type": "Feature",
  "properties": {
    "iso:country":"US",
    "sg:address":"20 E South St",
    "sg:city":"West Alexandria",
    "sg:classifiers":[
        {
            "category":"Banks & Credit Unions",
            "subcategory":"Bank",
            "type":"Services"
        }
    ],
    "sg:phone":"+1 937 839 1615",
    "sg:postcode":"45381",
    "sg:province":"OH",
    "sg:tags":[
        "national",
        "commercial"
    ],
    "wof:name":"Alexandria West Food Bank",
    "wof:placetype":"venue"
},
  "geometry": {"coordinates":[-84.531215,39.743549],"type":"Point"}
}