{
  "type": "Feature",
  "properties": {
    "iso:country":"US",
    "sg:address":"5704 Mayfield Rd",
    "sg:city":"Cleveland",
    "sg:classifiers":[
        {
            "category":"Retail",
            "subcategory":"Laundry & Dry Cleaning",
            "type":"Services"
        }
    ],
    "sg:phone":"+1 440 442 1470",
    "sg:postcode":"44124",
    "sg:province":"OH",
    "sg:tags":[
        "cleaners"
    ],
    "wof:name":"Campese's Dry Cleaners",
    "wof:placetype":"venue"
},
  "geometry": {"coordinates":[-81.473304,41.519948],"type":"Point"}
}