{
  "type": "Feature",
  "properties": {
    "iso:country":"US",
    "sg:address":"915 W 8th St",
    "sg:city":"Cincinnati",
    "sg:classifiers":[
        {
            "category":"Professional",
            "subcategory":"Business Services",
            "type":"Services"
        },
        {
            "category":"Professional",
            "subcategory":"Management & Consulting",
            "type":"Services"
        }
    ],
    "sg:phone":"+1 513 721 8687",
    "sg:postcode":"45203",
    "sg:province":"OH",
    "sg:tags":[
        "convention",
        "party",
        "planning",
        "consultant"
    ],
    "sg:website":"www.accentcinti.com",
    "wof:name":"Accent On Cincinnati Inc",
    "wof:placetype":"venue"
},
  "geometry": {"coordinates":[-84.531175,39.103396],"type":"Point"}
}