{
  "type": "Feature",
  "properties": {
    "addr:full": "5036 Eschelman Ave Louisville OH 44641",
    "addr:housenumber": "5036",
    "addr:postcode": "44641",
    "addr:street": "Eschelman Ave",
    "iso:country": "US",
    "sg:address": "5036 Eschelman Ave",
    "sg:city": "Louisville",
    "sg:phone": "+1 330 875 3015",
    "sg:postcode": "44641",
    "sg:province": "OH",
    "sg:tags": [
      "farm",
      "corn",
      "soybean"
    ],
    "wof:name": "Steve Miller",
    "wof:placetype": "venue"
  },
  "geometry": {"coordinates":[-81.225778,40.83892],"type":"Point"}
}
