{
  "type": "Feature",
  "properties": {
    "iso:country":"US",
    "sg:address":"5036 Eschelman Ave",
    "sg:city":"Louisville",
    "sg:phone":"+1 330 875 3015",
    "sg:postcode":"44641",
    "sg:province":"OH",
    "sg:tags":[
        "farm",
        "corn",
        "soybean"
    ],
    "wof:name":"Steve Miller",
    "wof:placetype":"venue"
},
  "geometry": {"coordinates":[-81.22577800000001,40.83892],"type":"Point"}
}