{
  "type": "Feature",
  "properties": {
    "addr:full": "5373 Enlow Rd Athens OH 45701",
    "addr:housenumber": "5373",
    "addr:postcode": "45701",
    "addr:street": "Enlow Rd",
    "iso:country": "US",
    "sg:address": "5373 Enlow Rd",
    "sg:city": "Athens",
    "sg:classifiers": [
      {
        "category": "Building \u0026 Trades",
        "subcategory": "Construction",
        "type": "Services"
      }
    ],
    "sg:phone": "+1 740 698 7252",
    "sg:postcode": "45701",
    "sg:province": "OH",
    "sg:tags": [
      "carpentry",
      "contractor"
    ],
    "wof:name": "Crossley Construction",
    "wof:placetype": "venue"
  },
  "geometry": {"coordinates":[-82.188931,39.287018],"type":"Point"}
}
