{
  "type": "Feature",
  "properties": {
    "addr:full":"4117 S Beechgrove Rd Wilmington OH 45177",
    "addr:housenumber":"4117",
    "addr:postcode":"45177",
    "addr:street":"S Beechgrove Rd",
    "iso:country":"US",
    "sg:address":"4117 S Beechgrove Rd",
    "sg:city":"Wilmington",
    "sg:classifiers":[
        {
            "category":"Real Estate",
            "subcategory":"Real Estate Operator",
            "type":"Services"
        }
    ],
    "sg:phone":"+1 937 382 8314",
    "sg:postcode":"45177",
    "sg:province":"OH",
    "sg:tags":[
        "property",
        "lessor"
    ],
    "wof:name":"Rental Properties",
    "wof:placetype":"venue"
},
  "geometry": {"coordinates":[-83.874156,39.422559],"type":"Point"}
}