{
  "type": "Feature",
  "properties": {
    "iso:country":"US",
    "sg:address":"3910 Co Hwy 1",
    "sg:city":"Bellefontaine",
    "sg:classifiers":[
        {
            "category":"Professional",
            "type":"Services"
        }
    ],
    "sg:phone":"+1 937 592 8351",
    "sg:postcode":"43311",
    "sg:province":"OH",
    "wof:name":"Ronda D Hunter",
    "wof:placetype":"venue"
},
  "geometry": {"coordinates":[-83.735542,40.308714],"type":"Point"}
}