{
  "type": "Feature",
  "properties": {
    "addr:full":"5217 Monroe St Toledo OH 43606",
    "addr:housenumber":"5217",
    "addr:postcode":"43606",
    "addr:street":"Monroe St",
    "iso:country":"US",
    "sg:address":"5217 Monroe St",
    "sg:city":"Toledo",
    "sg:classifiers":[
        {
            "category":"Real Estate",
            "subcategory":"Real Estate Agent",
            "type":"Services"
        },
        {
            "category":"Manufacturing",
            "subcategory":"Printing",
            "type":"Manufacturing & Wholesale Goods"
        }
    ],
    "sg:phone":"+1 419 841 6201",
    "sg:postcode":"43606",
    "sg:province":"OH",
    "sg:tags":[
        "newspaper"
    ],
    "sg:website":"www.flexrealty.com",
    "wof:name":"My Way Home Finder Magazine",
    "wof:placetype":"venue"
},
  "geometry": {"coordinates":[-83.650818,41.700634],"type":"Point"}
}