{
  "type": "Feature",
  "properties": {
    "addr:full": "40 E Laskey Rd Toledo OH 43612",
    "addr:housenumber": "40",
    "addr:postcode": "43612",
    "addr:street": "E Laskey Rd",
    "iso:country": "US",
    "sg:address": "40 E Laskey Rd",
    "sg:city": "Toledo",
    "sg:classifiers": [
      {
        "category": "Wholesale",
        "subcategory": "Auto Parts",
        "type": "Manufacturing \u0026 Wholesale Goods"
      }
    ],
    "sg:phone": "+1 419 478 9727",
    "sg:postcode": "43612",
    "sg:province": "OH",
    "sg:tags": [
      "automobile",
      "rebuilt"
    ],
    "wof:name": "Rada \u0026 Sons Used Truck Parts",
    "wof:placetype": "venue"
  },
  "geometry": {"coordinates":[-83.546831,41.70869],"type":"Point"}
}
