{
  "type": "Feature",
  "properties": {
    "addr:full": "245 W Main St Plain City OH 43064",
    "addr:housenumber": "245",
    "addr:postcode": "43064",
    "addr:street": "W Main St",
    "iso:country": "US",
    "sg:address": "245 W Main St",
    "sg:city": "Plain City",
    "sg:classifiers": [
      {
        "category": "Real Estate",
        "subcategory": "Real Estate Services",
        "type": "Services"
      }
    ],
    "sg:phone": "+1 614 873 8282",
    "sg:postcode": "43064",
    "sg:province": "OH",
    "sg:tags": [
      "company",
      "title"
    ],
    "wof:name": "ACS Northwest",
    "wof:placetype": "venue"
  },
  "geometry": {"coordinates":[-83.269591,40.108156],"type":"Point"}
}
