{
  "type": "Feature",
  "properties": {
    "iso:country":"US",
    "sg:address":"2368 Victory Pkwy",
    "sg:city":"Cincinnati",
    "sg:classifiers":[
        {
            "category":"Professional",
            "subcategory":"Accounting & Tax Preparation",
            "type":"Services"
        }
    ],
    "sg:phone":"+1 513 281 0555",
    "sg:postcode":"45206",
    "sg:province":"OH",
    "sg:tags":[
        "accountant"
    ],
    "wof:name":"Andrew Littner",
    "wof:placetype":"venue"
},
  "geometry": {"coordinates":[-84.48451,39.124525],"type":"Point"}
}