{
  "type": "Feature",
  "properties": {
    "addr:full":"1175 Greensview Dr Wooster OH 44691",
    "addr:housenumber":"1175",
    "addr:postcode":"44691",
    "addr:street":"Greensview Dr",
    "iso:country":"US",
    "sg:address":"1175 Greensview Dr",
    "sg:city":"Wooster",
    "sg:classifiers":[
        {
            "category":"Professional",
            "subcategory":"Management & Consulting",
            "type":"Services"
        }
    ],
    "sg:phone":"+1 330 264 9122",
    "sg:postcode":"44691",
    "sg:province":"OH",
    "sg:tags":[
        "marketing",
        "consultant"
    ],
    "wof:name":"Keystone Marketing Group",
    "wof:placetype":"venue"
},
  "geometry": {"coordinates":[-81.95631299999999,40.813112],"type":"Point"}
}