{
  "type": "Feature",
  "properties": {
    "addr:full": "7145 Scarlet Oak Ct Mason OH 45040",
    "addr:housenumber": "7145",
    "addr:postcode": "45040",
    "addr:street": "Scarlet Oak Ct",
    "iso:country": "US",
    "sg:address": "7145 Scarlet Oak Ct",
    "sg:city": "Mason",
    "sg:classifiers": [
      {
        "category": "Shopping",
        "subcategory": "Computers \u0026 Home Electronics",
        "type": "Retail Goods"
      }
    ],
    "sg:phone": "+1 513 754 8561",
    "sg:postcode": "45040",
    "sg:province": "OH",
    "wof:name": "Computer Assisted Services",
    "wof:placetype": "venue"
  },
  "geometry": {"coordinates":[-84.299598,39.335392],"type":"Point"}
}
