{
  "type": "Feature",
  "properties": {
    "iso:country":"US",
    "sg:address":"5580 Gault Rd",
    "sg:city":"North Jackson",
    "sg:classifiers":[
        {
            "category":"Manufacturing",
            "subcategory":"Printing",
            "type":"Manufacturing & Wholesale Goods"
        }
    ],
    "sg:phone":"+1 330 538 2215",
    "sg:postcode":"44451",
    "sg:province":"OH",
    "sg:tags":[
        "comm",
        "commercial",
        "design",
        "graphic",
        "art"
    ],
    "wof:name":"D C Press",
    "wof:placetype":"venue"
},
  "geometry": {"coordinates":[-80.838506,41.043172],"type":"Point"}
}