{
  "type": "Feature",
  "properties": {
    "addr:full": "5580 Gault Rd North Jackson OH 44451",
    "addr:housenumber": "5580",
    "addr:postcode": "44451",
    "addr:street": "Gault Rd",
    "iso:country": "US",
    "sg:address": "5580 Gault Rd",
    "sg:city": "North Jackson",
    "sg:classifiers": [
      {
        "category": "Manufacturing",
        "subcategory": "Printing",
        "type": "Manufacturing \u0026 Wholesale Goods"
      }
    ],
    "sg:phone": "+1 330 538 2215",
    "sg:postcode": "44451",
    "sg:province": "OH",
    "sg:tags": [
      "comm",
      "commercial",
      "design",
      "graphic",
      "art"
    ],
    "wof:name": "D C Press",
    "wof:placetype": "venue"
  },
  "geometry": {"coordinates":[-80.838506,41.043172],"type":"Point"}
}
