{
  "type": "Feature",
  "properties": {
    "iso:country":"US",
    "sg:address":"5503 Milan Rd",
    "sg:city":"Sandusky",
    "sg:classifiers":[
        {
            "category":"Restaurant",
            "type":"Food & Drink"
        }
    ],
    "sg:phone":"+1 419 627 2777",
    "sg:postcode":"44870",
    "sg:province":"OH",
    "sg:tags":[
        "drinking",
        "eating"
    ],
    "wof:name":"Applebees",
    "wof:placetype":"venue"
},
  "geometry": {"coordinates":[-82.652845,41.396909],"type":"Point"}
}