{
  "type": "Feature",
  "properties": {
    "addr:full": "5503 Milan Rd Sandusky OH 44870",
    "addr:housenumber": "5503",
    "addr:postcode": "44870",
    "addr:street": "Milan Rd",
    "iso:country": "US",
    "sg:address": "5503 Milan Rd",
    "sg:city": "Sandusky",
    "sg:classifiers": [
      {
        "category": "Restaurant",
        "type": "Food \u0026 Drink"
      }
    ],
    "sg:phone": "+1 419 627 2777",
    "sg:postcode": "44870",
    "sg:province": "OH",
    "sg:tags": [
      "drinking",
      "eating"
    ],
    "wof:name": "Applebees",
    "wof:placetype": "venue"
  },
  "geometry": {"coordinates":[-82.652845,41.396909],"type":"Point"}
}
