{
  "type": "Feature",
  "properties": {
    "addr:full": "304 2nd St Columbus OH 43215",
    "addr:housenumber": "304",
    "addr:postcode": "43215",
    "addr:street": "2Nd St",
    "iso:country": "US",
    "sg:address": "304 2nd St",
    "sg:city": "Columbus",
    "sg:classifiers": [
      {
        "category": "Retail",
        "subcategory": "Funeral Services",
        "type": "Services"
      }
    ],
    "sg:phone": "+1 614 627 2121",
    "sg:postcode": "43215",
    "sg:province": "OH",
    "sg:tags": [
      "director"
    ],
    "wof:name": "Allmon Dugger \u0026 Hively Funeral",
    "wof:placetype": "venue"
  },
  "geometry": {"coordinates":[-83.002772,39.955381],"type":"Point"}
}
