{
  "type": "Feature",
  "properties": {
    "addr:full":"106 Grant St Greenville OH 45331",
    "addr:housenumber":"106",
    "addr:postcode":"45331",
    "addr:street":"Grant St",
    "iso:country":"US",
    "sg:address":"106 Grant St",
    "sg:city":"Greenville",
    "sg:classifiers":[
        {
            "category":"Professional",
            "subcategory":"Accounting & Tax Preparation",
            "type":"Services"
        }
    ],
    "sg:phone":"+1 937 548 0212",
    "sg:postcode":"45331",
    "sg:province":"OH",
    "sg:tags":[
        "return",
        "filing"
    ],
    "wof:name":"H & R Block Tax Svc",
    "wof:placetype":"venue"
},
  "geometry": {"coordinates":[-84.62690000000001,40.106594],"type":"Point"}
}