{
  "type": "Feature",
  "properties": {
    "iso:country":"US",
    "sg:address":"810 N 7th St",
    "sg:city":"Steubenville",
    "sg:classifiers":[
        {
            "category":"Building & Trades",
            "subcategory":"Plumbing",
            "type":"Services"
        }
    ],
    "sg:phone":"+1 740 283 4890",
    "sg:postcode":"43952",
    "sg:province":"OH",
    "sg:tags":[
        "plumbing",
        "contractor"
    ],
    "wof:name":"Fort Steuben Maintenance Inc",
    "wof:placetype":"venue"
},
  "geometry": {"coordinates":[-80.614187,40.371512],"type":"Point"}
}