{
  "type": "Feature",
  "properties": {
    "addr:full": "4315 Talmadge Rd Toledo OH 43623",
    "addr:housenumber": "4315",
    "addr:postcode": "43623",
    "addr:street": "Talmadge Rd",
    "iso:country": "US",
    "sg:address": "4315 Talmadge Rd",
    "sg:city": "Toledo",
    "sg:classifiers": [
      {
        "category": "Restaurant",
        "type": "Food \u0026 Drink"
      }
    ],
    "sg:menulink": "http://www.allmenus.com/oh/toledo/11904-j-alexanders/menu/",
    "sg:phone": "+1 419 474 8620",
    "sg:postcode": "43623",
    "sg:province": "OH",
    "sg:tags": [
      "american"
    ],
    "wof:name": "J. Alexander's",
    "wof:placetype": "venue"
  },
  "geometry": {"coordinates":[-83.644795,41.696211],"type":"Point"}
}
