{
  "type": "Feature",
  "properties": {
    "iso:country":"US",
    "sg:address":"29550 Detroit Rd",
    "sg:city":"Cleveland",
    "sg:classifiers":[
        {
            "category":"Professional",
            "type":"Services"
        }
    ],
    "sg:phone":"+1 440 871 4479",
    "sg:postcode":"44145",
    "sg:province":"OH",
    "sg:tags":[
        "establishment"
    ],
    "wof:name":"Brouse & Mc Dowell",
    "wof:placetype":"venue"
},
  "geometry": {"coordinates":[-81.950469,41.463885],"type":"Point"}
}