{
  "type": "Feature",
  "properties": {
    "addr:full": "29550 Detroit Rd Cleveland OH 44145",
    "addr:housenumber": "29550",
    "addr:postcode": "44145",
    "addr:street": "Detroit Rd",
    "iso:country": "US",
    "sg:address": "29550 Detroit Rd",
    "sg:city": "Cleveland",
    "sg:classifiers": [
      {
        "category": "Professional",
        "type": "Services"
      }
    ],
    "sg:phone": "+1 440 871 4479",
    "sg:postcode": "44145",
    "sg:province": "OH",
    "sg:tags": [
      "establishment"
    ],
    "wof:name": "Brouse \u0026 Mc Dowell",
    "wof:placetype": "venue"
  },
  "geometry": {"coordinates":[-81.950469,41.463885],"type":"Point"}
}
