{
  "type": "Feature",
  "properties": {
    "addr:full": "5271 Yellowstone Dr Medina OH 44256",
    "addr:housenumber": "5271",
    "addr:postcode": "44256",
    "addr:street": "Yellowstone Dr",
    "iso:country": "US",
    "sg:address": "5271 Yellowstone Dr",
    "sg:city": "Medina",
    "sg:classifiers": [
      {
        "category": "Professional",
        "subcategory": "Management \u0026 Consulting",
        "type": "Services"
      }
    ],
    "sg:phone": "+1 330 721 6556",
    "sg:postcode": "44256",
    "sg:province": "OH",
    "sg:tags": [
      "consultant",
      "training"
    ],
    "wof:name": "Gold Star Dog Training",
    "wof:placetype": "venue"
  },
  "geometry": {"coordinates":[-81.876358,41.153858],"type":"Point"}
}
