{
  "type": "Feature",
  "properties": {
    "iso:country":"US",
    "sg:address":"3990 Blacklick Rd",
    "sg:city":"Baltimore",
    "sg:classifiers":[
        {
            "category":"Building & Trades",
            "subcategory":"Landscaping Services",
            "type":"Services"
        }
    ],
    "sg:phone":"+1 740 862 6321",
    "sg:postcode":"43105",
    "sg:province":"OH",
    "sg:tags":[
        "landscape",
        "contractor"
    ],
    "wof:name":"Absolute Lawn Care Inc",
    "wof:placetype":"venue"
},
  "geometry": {"coordinates":[-82.658058,39.926006],"type":"Point"}
}