{
  "type": "Feature",
  "properties": {
    "iso:country":"US",
    "sg:address":"531 Brown Ave",
    "sg:city":"Cambridge",
    "sg:classifiers":[
        {
            "category":"Building & Trades",
            "subcategory":"Construction",
            "type":"Services"
        }
    ],
    "sg:phone":"+1 740 432 8806",
    "sg:postcode":"43725",
    "sg:province":"OH",
    "sg:tags":[
        "roofing",
        "contractor"
    ],
    "wof:name":"Mosholder Roof & Siding",
    "wof:placetype":"venue"
},
  "geometry": {"coordinates":[-81.594629,40.025628],"type":"Point"}
}