{
  "type": "Feature",
  "properties": {
    "addr:full": "531 Brown Ave Cambridge OH 43725",
    "addr:housenumber": "531",
    "addr:postcode": "43725",
    "addr:street": "Brown Ave",
    "iso:country": "US",
    "sg:address": "531 Brown Ave",
    "sg:city": "Cambridge",
    "sg:classifiers": [
      {
        "category": "Building \u0026 Trades",
        "subcategory": "Construction",
        "type": "Services"
      }
    ],
    "sg:phone": "+1 740 432 8806",
    "sg:postcode": "43725",
    "sg:province": "OH",
    "sg:tags": [
      "roofing",
      "contractor"
    ],
    "wof:name": "Mosholder Roof \u0026 Siding",
    "wof:placetype": "venue"
  },
  "geometry": {"coordinates":[-81.594629,40.025628],"type":"Point"}
}
