{
  "type": "Feature",
  "properties": {
    "addr:full": "727 E Ash St Piqua OH 45356",
    "addr:housenumber": "727",
    "addr:postcode": "45356",
    "addr:street": "E Ash St",
    "iso:country": "US",
    "sg:address": "727 E Ash St",
    "sg:city": "Piqua",
    "sg:classifiers": [
      {
        "category": "Autos \u0026 Motor Vehicles",
        "subcategory": "Motorcycle Sales",
        "type": "Retail Goods"
      }
    ],
    "sg:phone": "+1 937 773 2220",
    "sg:postcode": "45356",
    "sg:province": "OH",
    "wof:name": "2fmscom",
    "wof:placetype": "venue"
  },
  "geometry": {"coordinates":[-84.228584,40.150363],"type":"Point"}
}
