{
  "type": "Feature",
  "properties": {
    "addr:full":"6750 Oak Field Dr Dayton OH 45415",
    "addr:housenumber":"6750",
    "addr:postcode":"45415",
    "addr:street":"Oak Field Dr",
    "iso:country":"US",
    "sg:address":"6750 Oak Field Dr",
    "sg:city":"Dayton",
    "sg:classifiers":[
        {
            "category":"Arena",
            "subcategory":"Sports Club",
            "type":"Entertainment"
        }
    ],
    "sg:phone":"+1 937 832 2729",
    "sg:postcode":"45415",
    "sg:province":"OH",
    "wof:name":"Northmont S A Y Soccer",
    "wof:placetype":"venue"
},
  "geometry": {"coordinates":[-84.280888,39.843597],"type":"Point"}
}