{
  "type": "Feature",
  "properties": {
    "addr:full":"4212 Westland Mall Columbus OH 43228",
    "addr:housenumber":"4212",
    "addr:postcode":"43228",
    "addr:street":"Westland Mall",
    "iso:country":"US",
    "sg:address":"4212 Westland Mall",
    "sg:city":"Columbus",
    "sg:classifiers":[
        {
            "category":"Shopping",
            "subcategory":"Clothing, Apparel, & Fashions",
            "type":"Retail Goods"
        }
    ],
    "sg:phone":"+1 614 272 8711",
    "sg:postcode":"43228",
    "sg:province":"OH",
    "sg:tags":[
        "sportswear"
    ],
    "wof:name":"Westland Mall Sports",
    "wof:placetype":"venue"
},
  "geometry": {"coordinates":[-83.11530399999999,39.952891],"type":"Point"}
}