{
  "type": "Feature",
  "properties": {
    "iso:country":"US",
    "sg:address":"20601 Aurora Rd",
    "sg:city":"Cleveland",
    "sg:classifiers":[
        {
            "category":"Wholesale",
            "subcategory":"Groceries",
            "type":"Manufacturing & Wholesale Goods"
        }
    ],
    "sg:phone":"+1 216 475 2300",
    "sg:postcode":"44146",
    "sg:province":"OH",
    "sg:tags":[
        "food",
        "product"
    ],
    "sg:website":"www.heinensonline.com",
    "wof:name":"Heinen's Warehouse",
    "wof:placetype":"venue"
},
  "geometry": {"coordinates":[-81.532692,41.426666],"type":"Point"}
}