{
  "type": "Feature",
  "properties": {
    "addr:full":"16 Clinton St Hudson OH 44236",
    "addr:housenumber":"16",
    "addr:postcode":"44236",
    "addr:street":"Clinton St",
    "iso:country":"US",
    "sg:address":"16 Clinton St",
    "sg:city":"Hudson",
    "sg:classifiers":[
        {
            "category":"Shopping",
            "subcategory":"Gifts & Souvenirs",
            "type":"Retail Goods"
        }
    ],
    "sg:phone":"+1 330 650 1517",
    "sg:postcode":"44236",
    "sg:province":"OH",
    "sg:tags":[
        "cards",
        "greeting"
    ],
    "wof:name":"Cartoleria LLC",
    "wof:placetype":"venue"
},
  "geometry": {"coordinates":[-81.441913,41.242242],"type":"Point"}
}