{
  "type": "Feature",
  "properties": {
    "iso:country":"US",
    "sg:address":"925 E Maple St",
    "sg:city":"North Canton",
    "sg:classifiers":[
        {
            "category":"Restaurant",
            "type":"Food & Drink"
        }
    ],
    "sg:phone":"+1 330 877 8333",
    "sg:postcode":"44720",
    "sg:province":"OH",
    "wof:name":"Pizza Hut",
    "wof:placetype":"venue"
},
  "geometry": {"coordinates":[-81.389252,40.875537],"type":"Point"}
}