{
  "type": "Feature",
  "properties": {
    "addr:full":"912 King Ave Columbus OH 43212",
    "addr:housenumber":"912",
    "addr:postcode":"43212",
    "addr:street":"King Ave",
    "iso:country":"US",
    "sg:address":"912 King Ave",
    "sg:city":"Columbus",
    "sg:classifiers":[
        {
            "category":"Real Estate",
            "subcategory":"Real Estate Agent",
            "type":"Services"
        }
    ],
    "sg:phone":"+1 614 291 1200",
    "sg:postcode":"43212",
    "sg:province":"OH",
    "wof:name":"GMAC",
    "wof:placetype":"venue"
},
  "geometry": {"coordinates":[-83.031318,39.991161],"type":"Point"}
}