{
  "type": "Feature",
  "properties": {
    "addr:full": "316 Pristine Path Blacklick OH 43004",
    "addr:housenumber": "316",
    "addr:postcode": "43004",
    "addr:street": "Pristine Path",
    "iso:country": "US",
    "sg:address": "316 Pristine Path",
    "sg:city": "Blacklick",
    "sg:classifiers": [
      {
        "category": "Shopping",
        "subcategory": "Gifts \u0026 Souvenirs",
        "type": "Retail Goods"
      }
    ],
    "sg:phone": "+1 614 846 6200",
    "sg:postcode": "43004",
    "sg:province": "OH",
    "sg:tags": [
      "shop"
    ],
    "wof:name": "Debis Hallmark",
    "wof:placetype": "venue"
  },
  "geometry": {"coordinates":[-82.781808,39.992134],"type":"Point"}
}
