{
  "type": "Feature",
  "properties": {
    "iso:country":"US",
    "sg:address":"4362 Indian Ripple Rd",
    "sg:city":"Dayton",
    "sg:classifiers":[
        {
            "category":"Autos & Motor Vehicles",
            "subcategory":"Fuel & Gas Station",
            "type":"Retail Goods"
        }
    ],
    "sg:phone":"+1 937 426 1923",
    "sg:postcode":"45430",
    "sg:province":"OH",
    "sg:tags":[
        "oil"
    ],
    "wof:name":"BP Oil Co",
    "wof:placetype":"venue"
},
  "geometry": {"coordinates":[-84.102241,39.696312],"type":"Point"}
}