{
  "type": "Feature",
  "properties": {
    "addr:full": "47281 State Rte 18 Wellington OH 44090",
    "addr:housenumber": "47281",
    "addr:postcode": "44090",
    "addr:street": "State Rte 18",
    "iso:country": "US",
    "sg:address": "47281 State Rte 18",
    "sg:city": "Wellington",
    "sg:classifiers": [
      {
        "category": "Retail",
        "subcategory": "Auto Repair",
        "type": "Services"
      }
    ],
    "sg:phone": "+1 440 647 2905",
    "sg:postcode": "44090",
    "sg:province": "OH",
    "sg:tags": [
      "transmission"
    ],
    "wof:name": "Harry's Auto Body",
    "wof:placetype": "venue"
  },
  "geometry": {"coordinates":[-82.235962,41.168852],"type":"Point"}
}
