{
  "type": "Feature",
  "properties": {
    "addr:full":"16377 Lashley Rd Senecaville OH 43780",
    "addr:housenumber":"16377",
    "addr:postcode":"43780",
    "addr:street":"Lashley Rd",
    "iso:country":"US",
    "sg:address":"16377 Lashley Rd",
    "sg:city":"Senecaville",
    "sg:classifiers":[
        {
            "category":"Autos & Motor Vehicles",
            "subcategory":"Boat Sales",
            "type":"Retail Goods"
        }
    ],
    "sg:phone":"+1 740 685 2752",
    "sg:postcode":"43780",
    "sg:province":"OH",
    "sg:tags":[
        "repair",
        "dealer",
        "sales"
    ],
    "wof:name":"Bobo's Boat Shop",
    "wof:placetype":"venue"
},
  "geometry": {"coordinates":[-81.43717100000001,39.932109],"type":"Point"}
}