{
  "type": "Feature",
  "properties": {
    "iso:country":"US",
    "sg:address":"3430 Highland Ave",
    "sg:city":"Cincinnati",
    "sg:classifiers":[
        {
            "category":"Professional",
            "subcategory":"Accounting & Tax Preparation",
            "type":"Services"
        }
    ],
    "sg:phone":"+1 513 531 3090",
    "sg:postcode":"45213",
    "sg:province":"OH",
    "sg:tags":[
        "return",
        "filing"
    ],
    "wof:name":"H & R Block Tax Svc",
    "wof:placetype":"venue"
},
  "geometry": {"coordinates":[-84.422066,39.170443],"type":"Point"}
}