{
  "type": "Feature",
  "properties": {
    "iso:country":"US",
    "sg:address":"9615 Co Rd 54",
    "sg:city":"Lewistown",
    "sg:classifiers":[
        {
            "category":"Building & Trades",
            "subcategory":"Construction",
            "type":"Services"
        }
    ],
    "sg:phone":"+1 937 686 8301",
    "sg:postcode":"43333",
    "sg:province":"OH",
    "sg:tags":[
        "heavy"
    ],
    "wof:name":"Reichert Farm Drainage Inc",
    "wof:placetype":"venue"
},
  "geometry": {"coordinates":[-83.91499899999999,40.420492],"type":"Point"}
}