{
  "type": "Feature",
  "properties": {
    "addr:full": "9615 Co Rd 54 Lewistown OH 43333",
    "addr:housenumber": "9615;54",
    "addr:postcode": "43333",
    "addr:street": "Co Rd",
    "iso:country": "US",
    "sg:address": "9615 Co Rd 54",
    "sg:city": "Lewistown",
    "sg:classifiers": [
      {
        "category": "Building \u0026 Trades",
        "subcategory": "Construction",
        "type": "Services"
      }
    ],
    "sg:phone": "+1 937 686 8301",
    "sg:postcode": "43333",
    "sg:province": "OH",
    "sg:tags": [
      "heavy"
    ],
    "wof:name": "Reichert Farm Drainage Inc",
    "wof:placetype": "venue"
  },
  "geometry": {"coordinates":[-83.914999,40.420492],"type":"Point"}
}
