{
  "type": "Feature",
  "properties": {
    "addr:full": "30900 Hilliard Blvd Cleveland OH 44145",
    "addr:housenumber": "30900",
    "addr:postcode": "44145",
    "addr:street": "Hilliard Blvd",
    "iso:country": "US",
    "sg:address": "30900 Hilliard Blvd",
    "sg:city": "Cleveland",
    "sg:classifiers": [
      {
        "category": "Building \u0026 Trades",
        "subcategory": "Plumbing",
        "type": "Services"
      }
    ],
    "sg:phone": "+1 440 871 3090",
    "sg:postcode": "44145",
    "sg:province": "OH",
    "sg:tags": [
      "conditioning",
      "air",
      "system",
      "contractor"
    ],
    "wof:name": "Westlake Mechanical Inc",
    "wof:placetype": "venue"
  },
  "geometry": {"coordinates":[-81.965847,41.435486],"type":"Point"}
}
