{
  "type": "Feature",
  "properties": {
    "iso:country":"US",
    "sg:address":"4863 Dorset Dr",
    "sg:city":"Cleveland",
    "sg:classifiers":[
        {
            "category":"Building & Trades",
            "subcategory":"Construction",
            "type":"Services"
        }
    ],
    "sg:phone":"+1 216 524 7252",
    "sg:postcode":"44131",
    "sg:province":"OH",
    "sg:tags":[
        "concrete",
        "contractor"
    ],
    "wof:name":"Mardan Cement",
    "wof:placetype":"venue"
},
  "geometry": {"coordinates":[-81.65835800000001,41.40774],"type":"Point"}
}