{
  "type": "Feature",
  "properties": {
    "addr:full":"1525 Northview Cir Fairfield OH 45014",
    "addr:housenumber":"1525",
    "addr:postcode":"45014",
    "addr:street":"Northview Cir",
    "iso:country":"US",
    "sg:address":"1525 Northview Cir",
    "sg:city":"Fairfield",
    "sg:classifiers":[
        {
            "category":"Organizations",
            "subcategory":"Community Association",
            "type":"Services"
        }
    ],
    "sg:phone":"+1 513 829 2516",
    "sg:postcode":"45014",
    "sg:province":"OH",
    "wof:name":"Kiwanis International Inc",
    "wof:placetype":"venue"
},
  "geometry": {"coordinates":[-84.56028000000001,39.329901],"type":"Point"}
}