{
  "type": "Feature",
  "properties": {
    "iso:country":"US",
    "sg:address":"9956 Akins Rd",
    "sg:city":"North Royalton",
    "sg:classifiers":[
        {
            "category":"Building & Trades",
            "subcategory":"Landscaping Services",
            "type":"Services"
        }
    ],
    "sg:phone":"+1 440 237 5394",
    "sg:postcode":"44133",
    "sg:province":"OH",
    "sg:tags":[
        "sanitary"
    ],
    "wof:name":"Monteleone Landscaping Company",
    "wof:placetype":"venue"
},
  "geometry": {"coordinates":[-81.759452,41.306511],"type":"Point"}
}