{
  "type": "Feature",
  "properties": {
    "addr:full": "1008 Co Rd 29 Ironton OH 45614",
    "addr:housenumber": "1008;29",
    "addr:postcode": "45614",
    "addr:street": "Co Rd",
    "iso:country": "US",
    "sg:address": "1008 Co Rd 29",
    "sg:city": "Ironton",
    "sg:classifiers": [
      {
        "category": "Recreation",
        "type": "Entertainment"
      }
    ],
    "sg:phone": "+1 740 532 4600",
    "sg:postcode": "45614",
    "sg:province": "OH",
    "sg:tags": [
      "parks"
    ],
    "wof:name": "Ohio University Nature Ctr",
    "wof:placetype": "venue"
  },
  "geometry": {"coordinates":[-82.247559,38.875263],"type":"Point"}
}
