{
  "type": "Feature",
  "properties": {
    "addr:full": "230 Oakham Ct Powell OH 43065",
    "addr:housenumber": "230",
    "addr:postcode": "43065",
    "addr:street": "Oakham Ct",
    "iso:country": "US",
    "sg:address": "230 Oakham Ct",
    "sg:city": "Powell",
    "sg:classifiers": [
      {
        "category": "Sports \u0026 Exercise",
        "subcategory": "Golf",
        "type": "Entertainment"
      }
    ],
    "sg:phone": "+1 614 433 0230",
    "sg:postcode": "43065",
    "sg:province": "OH",
    "sg:tags": [
      "course",
      "public"
    ],
    "wof:name": "On Course Management LLC",
    "wof:placetype": "venue"
  },
  "geometry": {"coordinates":[-83.068755,40.151263],"type":"Point"}
}
