{
  "type": "Feature",
  "properties": {
    "addr:full": "8313 Kimmel Rd Clayton OH 45315",
    "addr:housenumber": "8313",
    "addr:postcode": "45315",
    "addr:street": "Kimmel Rd",
    "iso:country": "US",
    "sg:address": "8313 Kimmel Rd",
    "sg:city": "Clayton",
    "sg:classifiers": [
      {
        "category": "Professional",
        "type": "Services"
      },
      {
        "category": "Real Estate",
        "subcategory": "Real Estate Agent",
        "type": "Services"
      }
    ],
    "sg:phone": "+1 937 836 9024",
    "sg:postcode": "45315",
    "sg:province": "OH",
    "wof:name": "First General Serv of Dayton",
    "wof:placetype": "venue"
  },
  "geometry": {"coordinates":[-84.358544,39.853109],"type":"Point"}
}
