{
  "type": "Feature",
  "properties": {
    "iso:country":"US",
    "sg:address":"4700 Rockside Rd",
    "sg:city":"Independence",
    "sg:classifiers":[
        {
            "category":"Health Services",
            "subcategory":"Clinic",
            "type":"Services"
        },
        {
            "category":"Insurance",
            "subcategory":"Health Insurance",
            "type":"Services"
        },
        {
            "category":"Organizations",
            "subcategory":"Non-profit Organization",
            "type":"Services"
        }
    ],
    "sg:phone":"+1 216 524 2842",
    "sg:postcode":"44131",
    "sg:province":"OH",
    "sg:tags":[
        "charity",
        "maintenance",
        "welfare"
    ],
    "wof:name":"Autism Speaks",
    "wof:placetype":"venue"
},
  "geometry": {"coordinates":[-81.658146,41.397945],"type":"Point"}
}