{
  "type": "Feature",
  "properties": {
    "addr:full":"592 Oakland Ter Circleville OH 43113",
    "addr:housenumber":"592",
    "addr:postcode":"43113",
    "addr:street":"Oakland Ter",
    "iso:country":"US",
    "sg:address":"592 Oakland Ter",
    "sg:city":"Circleville",
    "sg:classifiers":[
        {
            "category":"Freight",
            "type":"Transportation"
        }
    ],
    "sg:phone":"+1 740 477 9779",
    "sg:postcode":"43113",
    "sg:province":"OH",
    "sg:tags":[
        "broker"
    ],
    "wof:name":"Ready Transport Service Inc",
    "wof:placetype":"venue"
},
  "geometry": {"coordinates":[-82.92482699999999,39.621262],"type":"Point"}
}