{
  "type": "Feature",
  "properties": {
    "addr:full": "2055 Weil Rd Moscow OH 45153",
    "addr:housenumber": "2055",
    "addr:postcode": "45153",
    "addr:street": "Weil Rd",
    "iso:country": "US",
    "sg:address": "2055 Weil Rd",
    "sg:city": "Moscow",
    "sg:classifiers": [
      {
        "category": "Professional",
        "subcategory": "Engineering",
        "type": "Services"
      }
    ],
    "sg:phone": "+1 513 553 4646",
    "sg:postcode": "45153",
    "sg:province": "OH",
    "sg:tags": [
      "machine",
      "consultant",
      "design"
    ],
    "wof:name": "Sabel Plastechs Inc",
    "wof:placetype": "venue"
  },
  "geometry": {"coordinates":[-84.189412,38.903264],"type":"Point"}
}
