{
  "type": "Feature",
  "properties": {
    "addr:full": "5685 E Walnut Grove Troy OH 45373",
    "addr:housenumber": "5685",
    "addr:postcode": "45373",
    "addr:street": "E Walnut Grove",
    "iso:country": "US",
    "sg:address": "5685 E Walnut Grove",
    "sg:city": "Troy",
    "sg:classifiers": [
      {
        "category": "Shopping",
        "subcategory": "Stationery \u0026 Office Supplies",
        "type": "Retail Goods"
      }
    ],
    "sg:phone": "+1 937 339 7325",
    "sg:postcode": "45373",
    "sg:province": "OH",
    "wof:name": "Ecalcom",
    "wof:placetype": "venue"
  },
  "geometry": {"coordinates":[-84.100975,39.999563],"type":"Point"}
}
