{
  "type": "Feature",
  "properties": {
    "iso:country":"US",
    "sg:address":"5685 E Walnut Grove",
    "sg:city":"Troy",
    "sg:classifiers":[
        {
            "category":"Shopping",
            "subcategory":"Stationery & Office Supplies",
            "type":"Retail Goods"
        }
    ],
    "sg:phone":"+1 937 339 7325",
    "sg:postcode":"45373",
    "sg:province":"OH",
    "wof:name":"Ecalcom",
    "wof:placetype":"venue"
},
  "geometry": {"coordinates":[-84.10097500000001,39.999563],"type":"Point"}
}