{
  "type": "Feature",
  "properties": {
    "addr:full":"106 Butternut Ave Pomeroy OH 45769",
    "addr:housenumber":"106",
    "addr:postcode":"45769",
    "addr:street":"Butternut Ave",
    "iso:country":"US",
    "sg:address":"106 Butternut Ave",
    "sg:city":"Pomeroy",
    "sg:classifiers":[
        {
            "category":"Shopping",
            "subcategory":"Florist",
            "type":"Retail Goods"
        }
    ],
    "sg:phone":"+1 740 992 6454",
    "sg:postcode":"45769",
    "sg:province":"OH",
    "wof:name":"Pomeroy Flower Shop",
    "wof:placetype":"venue"
},
  "geometry": {"coordinates":[-82.03558700000001,39.026512],"type":"Point"}
}