{
  "type": "Feature",
  "properties": {
    "addr:full": "2144 Schappelle Ln Cincinnati OH 45240",
    "addr:housenumber": "2144",
    "addr:postcode": "45240",
    "addr:street": "Schappelle Ln",
    "iso:country": "US",
    "sg:address": "2144 Schappelle Ln",
    "sg:city": "Cincinnati",
    "sg:classifiers": [
      {
        "category": "Manufacturing",
        "subcategory": "Retail Goods",
        "type": "Manufacturing \u0026 Wholesale Goods"
      }
    ],
    "sg:phone": "+1 513 825 8888",
    "sg:postcode": "45240",
    "sg:province": "OH",
    "sg:tags": [
      "manufacturer"
    ],
    "wof:name": "Cincinnati Interface",
    "wof:placetype": "venue"
  },
  "geometry": {"coordinates":[-84.558028,39.283404],"type":"Point"}
}
