{
  "type": "Feature",
  "properties": {
    "addr:full": "18069 State Rte 327 Wellston OH 45692",
    "addr:housenumber": "18069",
    "addr:postcode": "45692",
    "addr:street": "State Rte 327",
    "iso:country": "US",
    "sg:address": "18069 State Rte 327",
    "sg:city": "Wellston",
    "sg:classifiers": [
      {
        "category": "Building \u0026 Trades",
        "subcategory": "Construction",
        "type": "Services"
      }
    ],
    "sg:phone": "+1 740 286 9661",
    "sg:postcode": "45692",
    "sg:province": "OH",
    "sg:tags": [
      "steel",
      "erection",
      "structural"
    ],
    "wof:name": "Pigeon Creek Auto Salvage",
    "wof:placetype": "venue"
  },
  "geometry": {"coordinates":[-82.644056,39.18587],"type":"Point"}
}
