{
  "type": "Feature",
  "properties": {
    "addr:full": "15050 E River Rd Columbia Station OH 44028",
    "addr:housenumber": "15050",
    "addr:postcode": "44028",
    "addr:street": "E River Rd",
    "iso:country": "US",
    "sg:address": "15050 E River Rd",
    "sg:city": "Columbia Station",
    "sg:classifiers": [
      {
        "category": "Building \u0026 Trades",
        "subcategory": "Construction",
        "type": "Services"
      }
    ],
    "sg:phone": "+1 440 236 5035",
    "sg:postcode": "44028",
    "sg:province": "OH",
    "sg:tags": [
      "product",
      "asphalt"
    ],
    "wof:name": "American Asphalt Seal Coating",
    "wof:placetype": "venue"
  },
  "geometry": {"coordinates":[-81.915108,41.311445],"type":"Point"}
}
