{
  "type": "Feature",
  "properties": {
    "addr:full": "111 S Main St Hicksville OH 43526",
    "addr:housenumber": "111",
    "addr:postcode": "43526",
    "addr:street": "S Main St",
    "iso:country": "US",
    "sg:address": "111 S Main St",
    "sg:city": "Hicksville",
    "sg:classifiers": [
      {
        "category": "Communications",
        "subcategory": "Television Station",
        "type": "Services"
      }
    ],
    "sg:phone": "+1 419 542 9312",
    "sg:postcode": "43526",
    "sg:province": "OH",
    "wof:name": "Hix Tv9",
    "wof:placetype": "venue"
  },
  "geometry": {"coordinates":[-84.762352,41.293118],"type":"Point"}
}
