{
  "type": "Feature",
  "properties": {
    "iso:country":"US",
    "sg:address":"5911 Wolf Creek Pike",
    "sg:city":"Dayton",
    "sg:classifiers":[
        {
            "category":"Manufacturing",
            "subcategory":"Tools & Machinery",
            "type":"Manufacturing & Wholesale Goods"
        }
    ],
    "sg:phone":"+1 937 854 8875",
    "sg:postcode":"45426",
    "sg:province":"OH",
    "sg:tags":[
        "machine",
        "shop"
    ],
    "wof:name":"Kasel Engineering",
    "wof:placetype":"venue"
},
  "geometry": {"coordinates":[-84.28292500000001,39.794664],"type":"Point"}
}