{
  "type": "Feature",
  "properties": {
    "addr:full": "5911 Wolf Creek Pike Dayton OH 45426",
    "addr:housenumber": "5911",
    "addr:postcode": "45426",
    "addr:street": "Wolf Creek Pike",
    "iso:country": "US",
    "sg:address": "5911 Wolf Creek Pike",
    "sg:city": "Dayton",
    "sg:classifiers": [
      {
        "category": "Manufacturing",
        "subcategory": "Tools \u0026 Machinery",
        "type": "Manufacturing \u0026 Wholesale Goods"
      }
    ],
    "sg:phone": "+1 937 854 8875",
    "sg:postcode": "45426",
    "sg:province": "OH",
    "sg:tags": [
      "machine",
      "shop"
    ],
    "wof:name": "Kasel Engineering",
    "wof:placetype": "venue"
  },
  "geometry": {"coordinates":[-84.282925,39.794664],"type":"Point"}
}
