{
  "type": "Feature",
  "properties": {
    "addr:full":"33381 Aurora Rd Cleveland OH 44139",
    "addr:housenumber":"33381",
    "addr:postcode":"44139",
    "addr:street":"Aurora Rd",
    "iso:country":"US",
    "sg:address":"33381 Aurora Rd",
    "sg:city":"Cleveland",
    "sg:classifiers":[
        {
            "category":"Personal",
            "subcategory":"Beauty Salon",
            "type":"Services"
        }
    ],
    "sg:phone":"+1 440 349 0245",
    "sg:postcode":"44139",
    "sg:province":"OH",
    "wof:name":"Blade Hue",
    "wof:placetype":"venue"
},
  "geometry": {"coordinates":[-81.438256,41.385075],"type":"Point"}
}