{
  "type": "Feature",
  "properties": {
    "iso:country":"US",
    "sg:address":"15 W Oak St",
    "sg:city":"Canal Winchester",
    "sg:classifiers":[
        {
            "category":"Manufacturing",
            "subcategory":"Printing",
            "type":"Manufacturing & Wholesale Goods"
        }
    ],
    "sg:phone":"+1 614 833 0499",
    "sg:postcode":"43110",
    "sg:province":"OH",
    "sg:tags":[
        "book"
    ],
    "wof:name":"North Stream Publishing Inc",
    "wof:placetype":"venue"
},
  "geometry": {"coordinates":[-82.807301,39.845234],"type":"Point"}
}