{
  "type": "Feature",
  "properties": {
    "addr:full": "15 W Oak St Canal Winchester OH 43110",
    "addr:housenumber": "15",
    "addr:postcode": "43110",
    "addr:street": "W Oak St",
    "iso:country": "US",
    "sg:address": "15 W Oak St",
    "sg:city": "Canal Winchester",
    "sg:classifiers": [
      {
        "category": "Manufacturing",
        "subcategory": "Printing",
        "type": "Manufacturing \u0026 Wholesale Goods"
      }
    ],
    "sg:phone": "+1 614 833 0499",
    "sg:postcode": "43110",
    "sg:province": "OH",
    "sg:tags": [
      "book"
    ],
    "wof:name": "North Stream Publishing Inc",
    "wof:placetype": "venue"
  },
  "geometry": {"coordinates":[-82.807301,39.845234],"type":"Point"}
}
