{
  "type": "Feature",
  "properties": {
    "addr:full":"2070 Walker Lake Rd Ontario OH 44906",
    "addr:housenumber":"2070",
    "addr:postcode":"44906",
    "addr:street":"Walker Lake Rd",
    "iso:country":"US",
    "sg:address":"2070 Walker Lake Rd",
    "sg:city":"Ontario",
    "sg:classifiers":[
        {
            "category":"Fast Food",
            "type":"Food & Drink"
        },
        {
            "category":"Coffee & Tea",
            "type":"Food & Drink"
        },
        {
            "category":"Restaurant",
            "type":"Food & Drink"
        },
        {
            "category":"Bakery",
            "type":"Food & Drink"
        },
        {
            "category":"Food & Beverages",
            "subcategory":"Groceries & Convenience Stores",
            "type":"Retail Goods"
        }
    ],
    "sg:phone":"+1 419 774 9700",
    "sg:postcode":"44906",
    "sg:province":"OH",
    "sg:tags":[
        "shop",
        "sandwich",
        "espresso",
        "take"
    ],
    "sg:website":"http://www.panerabread.com",
    "wof:name":"Panera Bread",
    "wof:placetype":"venue"
},
  "geometry": {"coordinates":[-82.585241,40.787285],"type":"Point"}
}