{
  "type": "Feature",
  "properties": {
    "addr:full": "5757 Monclova Rd Maumee OH 43537",
    "addr:housenumber": "5757",
    "addr:postcode": "43537",
    "addr:street": "Monclova Rd",
    "iso:country": "US",
    "sg:address": "5757 Monclova Rd",
    "sg:city": "Maumee",
    "sg:classifiers": [
      {
        "category": "Health Services",
        "subcategory": "Health Practitioner",
        "type": "Services"
      }
    ],
    "sg:phone": "+1 419 893 1222",
    "sg:postcode": "43537",
    "sg:province": "OH",
    "sg:tags": [
      "therapist",
      "physical"
    ],
    "wof:name": "Heartland Rehabilitation Svc",
    "wof:placetype": "venue"
  },
  "geometry": {"coordinates":[-83.679833,41.558659],"type":"Point"}
}
