{
  "type": "Feature",
  "properties": {
    "iso:country":"US",
    "sg:address":"600 N Main St",
    "sg:city":"Piqua",
    "sg:classifiers":[
        {
            "category":"Autos & Motor Vehicles",
            "subcategory":"Fuel & Gas Station",
            "type":"Retail Goods"
        }
    ],
    "sg:phone":"+1 937 773 7688",
    "sg:postcode":"45356",
    "sg:province":"OH",
    "sg:tags":[
        "station",
        "gasoline"
    ],
    "wof:name":"BP",
    "wof:placetype":"venue"
},
  "geometry": {"coordinates":[-84.239746,40.15284],"type":"Point"}
}