{
  "type": "Feature",
  "properties": {
    "addr:full": "600 N Main St Piqua OH 45356",
    "addr:housenumber": "600",
    "addr:postcode": "45356",
    "addr:street": "N Main St",
    "iso:country": "US",
    "sg:address": "600 N Main St",
    "sg:city": "Piqua",
    "sg:classifiers": [
      {
        "category": "Autos \u0026 Motor Vehicles",
        "subcategory": "Fuel \u0026 Gas Station",
        "type": "Retail Goods"
      }
    ],
    "sg:phone": "+1 937 773 7688",
    "sg:postcode": "45356",
    "sg:province": "OH",
    "sg:tags": [
      "station",
      "gasoline"
    ],
    "wof:name": "BP",
    "wof:placetype": "venue"
  },
  "geometry": {"coordinates":[-84.239746,40.15284],"type":"Point"}
}
