{
  "type": "Feature",
  "properties": {
    "addr:full":"3880 Indian Ripple Rd Dayton OH 45440",
    "addr:housenumber":"3880",
    "addr:postcode":"45440",
    "addr:street":"Indian Ripple Rd",
    "iso:country":"US",
    "sg:address":"3880 Indian Ripple Rd",
    "sg:city":"Dayton",
    "sg:classifiers":[
        {
            "category":"Health Services",
            "subcategory":"Clinic",
            "type":"Services"
        }
    ],
    "sg:phone":"+1 937 320 5901",
    "sg:postcode":"45440",
    "sg:province":"OH",
    "wof:name":"Axis Healthcare Staffing",
    "wof:placetype":"venue"
},
  "geometry": {"coordinates":[-84.07945599999999,39.694926],"type":"Point"}
}