{
  "type": "Feature",
  "properties": {
    "addr:full":"2984 Northern Rd Somerville OH 45064",
    "addr:housenumber":"2984",
    "addr:postcode":"45064",
    "addr:street":"Northern Rd",
    "iso:country":"US",
    "sg:address":"2984 Northern Rd",
    "sg:city":"Somerville",
    "sg:classifiers":[
        {
            "category":"Farming",
            "subcategory":"Farm",
            "type":"Manufacturing & Wholesale Goods"
        }
    ],
    "sg:phone":"+1 937 456 2270",
    "sg:postcode":"45064",
    "sg:province":"OH",
    "sg:tags":[
        "crop",
        "general"
    ],
    "wof:name":"Susan Howard",
    "wof:placetype":"venue"
},
  "geometry": {"coordinates":[-84.59744999999999,39.586015],"type":"Point"}
}