{
  "type": "Feature",
  "properties": {
    "addr:full": "5328 N High St Columbus OH 43214",
    "addr:housenumber": "5328",
    "addr:postcode": "43214",
    "addr:street": "N High St",
    "iso:country": "US",
    "sg:address": "5328 N High St",
    "sg:city": "Columbus",
    "sg:classifiers": [
      {
        "category": "Restaurant",
        "type": "Food \u0026 Drink"
      }
    ],
    "sg:phone": "+1 614 888 7728",
    "sg:postcode": "43214",
    "sg:province": "OH",
    "sg:tags": [
      "greek",
      "other"
    ],
    "wof:name": "Acropolis Gyro Palace",
    "wof:placetype": "venue"
  },
  "geometry": {"coordinates":[-83.018996,40.072058],"type":"Point"}
}
