{
  "type": "Feature",
  "properties": {
    "iso:country":"US",
    "sg:address":"4412 W 130th St",
    "sg:city":"Cleveland",
    "sg:classifiers":[
        {
            "category":"Manufacturing",
            "subcategory":"Tools & Machinery",
            "type":"Manufacturing & Wholesale Goods"
        }
    ],
    "sg:phone":"+1 216 476 0654",
    "sg:postcode":"44135",
    "sg:province":"OH",
    "sg:tags":[
        "equipment",
        "mfg",
        "lubricating"
    ],
    "wof:name":"A-S Manufacturing Inc",
    "wof:placetype":"venue"
},
  "geometry": {"coordinates":[-81.78003099999999,41.43391],"type":"Point"}
}