{
  "type": "Feature",
  "properties": {
    "addr:full": "9207 Bruce Dr Franklin OH 45005",
    "addr:housenumber": "9207",
    "addr:postcode": "45005",
    "addr:street": "Bruce Dr",
    "iso:country": "US",
    "sg:address": "9207 Bruce Dr",
    "sg:city": "Franklin",
    "sg:classifiers": [
      {
        "category": "Manufacturing",
        "subcategory": "Textiles",
        "type": "Manufacturing \u0026 Wholesale Goods"
      }
    ],
    "sg:phone": "+1 937 743 9060",
    "sg:postcode": "45005",
    "sg:province": "OH",
    "sg:tags": [
      "finishing",
      "plant",
      "cotton"
    ],
    "wof:name": "Player S Choice",
    "wof:placetype": "venue"
  },
  "geometry": {"coordinates":[-84.261417,39.575793],"type":"Point"}
}
