{
  "type": "Feature",
  "properties": {
    "iso:country":"US",
    "sg:address":"9207 Bruce Dr",
    "sg:city":"Franklin",
    "sg:classifiers":[
        {
            "category":"Manufacturing",
            "subcategory":"Textiles",
            "type":"Manufacturing & Wholesale Goods"
        }
    ],
    "sg:phone":"+1 937 743 9060",
    "sg:postcode":"45005",
    "sg:province":"OH",
    "sg:tags":[
        "finishing",
        "plant",
        "cotton"
    ],
    "wof:name":"Player S Choice",
    "wof:placetype":"venue"
},
  "geometry": {"coordinates":[-84.26141699999999,39.575793],"type":"Point"}
}