{
  "type": "Feature",
  "properties": {
    "addr:full": "107 Clay St Dayton OH 45402",
    "addr:housenumber": "107",
    "addr:postcode": "45402",
    "addr:street": "Clay St",
    "iso:country": "US",
    "sg:address": "107 Clay St",
    "sg:city": "Dayton",
    "sg:classifiers": [
      {
        "category": "Retail",
        "subcategory": "Laundry \u0026 Dry Cleaning",
        "type": "Services"
      }
    ],
    "sg:phone": "+1 937 534 4101",
    "sg:postcode": "45402",
    "sg:province": "OH",
    "sg:tags": [
      "cleaners",
      "rug",
      "carpet"
    ],
    "wof:name": "Women Owned Workplaces",
    "wof:placetype": "venue"
  },
  "geometry": {"coordinates":[-84.182337,39.755716],"type":"Point"}
}
