{
  "type": "Feature",
  "properties": {
    "iso:country":"US",
    "sg:address":"107 Clay St",
    "sg:city":"Dayton",
    "sg:classifiers":[
        {
            "category":"Retail",
            "subcategory":"Laundry & Dry Cleaning",
            "type":"Services"
        }
    ],
    "sg:phone":"+1 937 534 4101",
    "sg:postcode":"45402",
    "sg:province":"OH",
    "sg:tags":[
        "cleaners",
        "rug",
        "carpet"
    ],
    "wof:name":"Women Owned Workplaces",
    "wof:placetype":"venue"
},
  "geometry": {"coordinates":[-84.182337,39.755716],"type":"Point"}
}