{
  "type": "Feature",
  "properties": {
    "iso:country":"US",
    "sg:address":"6100 Channingway Blvd",
    "sg:city":"Columbus",
    "sg:classifiers":[
        {
            "category":"Organizations",
            "subcategory":"Non-profit Organization",
            "type":"Services"
        }
    ],
    "sg:phone":"+1 614 751 7777",
    "sg:postcode":"43232",
    "sg:province":"OH",
    "sg:website":"www.carestar.com",
    "wof:name":"Care Star",
    "wof:placetype":"venue"
},
  "geometry": {"coordinates":[-82.832392,39.938531],"type":"Point"}
}