{
  "type": "Feature",
  "properties": {
    "addr:full": "900 Hilton Dr Reynoldsburg OH 43068",
    "addr:housenumber": "900",
    "addr:postcode": "43068",
    "addr:street": "Hilton Dr",
    "iso:country": "US",
    "sg:address": "900 Hilton Dr",
    "sg:city": "Reynoldsburg",
    "sg:classifiers": [
      {
        "category": "Recreation",
        "type": "Entertainment"
      }
    ],
    "sg:phone": "+1 614 501 0385",
    "sg:postcode": "43068",
    "sg:province": "OH",
    "sg:tags": [
      "course",
      "golf"
    ],
    "wof:name": "Ritz Concessions At Airport",
    "wof:placetype": "venue"
  },
  "geometry": {"coordinates":[-82.780855,39.967155],"type":"Point"}
}
