{
  "type": "Feature",
  "properties": {
    "iso:country":"US",
    "sg:address":"2 Scott St",
    "sg:city":"Savannah",
    "sg:classifiers":[
        {
            "category":"Building & Trades",
            "subcategory":"Construction",
            "type":"Services"
        }
    ],
    "sg:phone":"+1 419 962 4434",
    "sg:postcode":"44874",
    "sg:province":"OH",
    "sg:tags":[
        "painter"
    ],
    "wof:name":"D J Home Improvement",
    "wof:placetype":"venue"
},
  "geometry": {"coordinates":[-82.365782,40.966713],"type":"Point"}
}