{
  "type": "Feature",
  "properties": {
    "addr:full": "2 Scott St Savannah OH 44874",
    "addr:housenumber": "2",
    "addr:postcode": "44874",
    "addr:street": "Scott St",
    "iso:country": "US",
    "sg:address": "2 Scott St",
    "sg:city": "Savannah",
    "sg:classifiers": [
      {
        "category": "Building \u0026 Trades",
        "subcategory": "Construction",
        "type": "Services"
      }
    ],
    "sg:phone": "+1 419 962 4434",
    "sg:postcode": "44874",
    "sg:province": "OH",
    "sg:tags": [
      "painter"
    ],
    "wof:name": "D J Home Improvement",
    "wof:placetype": "venue"
  },
  "geometry": {"coordinates":[-82.365782,40.966713],"type":"Point"}
}
