{
  "type": "Feature",
  "properties": {
    "addr:full": "20100 Saint Clair Ave Cleveland OH 44117",
    "addr:housenumber": "20100",
    "addr:postcode": "44117",
    "addr:street": "Saint Clair Ave",
    "iso:country": "US",
    "sg:address": "20100 Saint Clair Ave",
    "sg:city": "Cleveland",
    "sg:classifiers": [
      {
        "category": "Manufacturing",
        "subcategory": "Tools \u0026 Machinery",
        "type": "Manufacturing \u0026 Wholesale Goods"
      }
    ],
    "sg:phone": "+1 216 531 4100",
    "sg:postcode": "44117",
    "sg:province": "OH",
    "sg:tags": [
      "construction"
    ],
    "sg:website": "www.cleveland-trencher.com",
    "wof:name": "Cleveland Trencher Co",
    "wof:placetype": "venue"
  },
  "geometry": {"coordinates":[-81.52723,41.5855],"type":"Point"}
}
