{
  "type": "Feature",
  "properties": {
    "iso:country":"US",
    "sg:address":"20100 Saint Clair Ave",
    "sg:city":"Cleveland",
    "sg:classifiers":[
        {
            "category":"Manufacturing",
            "subcategory":"Tools & Machinery",
            "type":"Manufacturing & Wholesale Goods"
        }
    ],
    "sg:phone":"+1 216 531 4100",
    "sg:postcode":"44117",
    "sg:province":"OH",
    "sg:tags":[
        "construction"
    ],
    "sg:website":"www.cleveland-trencher.com",
    "wof:name":"Cleveland Trencher Co",
    "wof:placetype":"venue"
},
  "geometry": {"coordinates":[-81.52723,41.5855],"type":"Point"}
}