{
  "type": "Feature",
  "properties": {
    "addr:full": "1555 Baltzley Valley Rd SE New Philadelphia OH 44663",
    "addr:housenumber": "1555",
    "addr:postcode": "44663",
    "addr:street": "Baltzley Valley Rd Se New",
    "iso:country": "US",
    "sg:address": "1555 Baltzley Valley Rd SE",
    "sg:city": "New Philadelphia",
    "sg:classifiers": [
      {
        "category": "Building \u0026 Trades",
        "subcategory": "Construction",
        "type": "Services"
      }
    ],
    "sg:phone": "+1 330 339 9498",
    "sg:postcode": "44663",
    "sg:province": "OH",
    "sg:tags": [
      "carpentry",
      "contractor"
    ],
    "wof:name": "Brett Sulzener Contractor",
    "wof:placetype": "venue"
  },
  "geometry": {"coordinates":[-81.390729,40.45812],"type":"Point"}
}
