{
  "type": "Feature",
  "properties": {
    "iso:country":"US",
    "sg:address":"1555 Baltzley Valley Rd SE",
    "sg:city":"New Philadelphia",
    "sg:classifiers":[
        {
            "category":"Building & Trades",
            "subcategory":"Construction",
            "type":"Services"
        }
    ],
    "sg:phone":"+1 330 339 9498",
    "sg:postcode":"44663",
    "sg:province":"OH",
    "sg:tags":[
        "carpentry",
        "contractor"
    ],
    "wof:name":"Brett Sulzener Contractor",
    "wof:placetype":"venue"
},
  "geometry": {"coordinates":[-81.39072899999999,40.45812],"type":"Point"}
}