{
  "type": "Feature",
  "properties": {
    "addr:full": "2426 Sir Martin Dr Hamilton IN 45013",
    "addr:housenumber": "2426",
    "addr:postcode": "45013",
    "addr:street": "Sir Martin Dr",
    "iso:country": "US",
    "sg:address": "2426 Sir Martin Dr",
    "sg:city": "Hamilton",
    "sg:classifiers": [
      {
        "category": "Building \u0026 Trades",
        "subcategory": "Construction",
        "type": "Services"
      }
    ],
    "sg:phone": "+1 513 896 7884",
    "sg:postcode": "45013",
    "sg:province": "IN",
    "sg:tags": [
      "new",
      "builder",
      "home"
    ],
    "wof:name": "F V Honchell Construction Co",
    "wof:placetype": "venue"
  },
  "geometry": {"coordinates":[-84.641563,39.39925],"type":"Point"}
}
