{
  "type": "Feature",
  "properties": {
    "iso:country":"US",
    "sg:address":"216 1st Dr SE",
    "sg:city":"New Philadelphia",
    "sg:classifiers":[
        {
            "category":"Retail",
            "subcategory":"Car Wash",
            "type":"Services"
        }
    ],
    "sg:phone":"+1 330 364 6722",
    "sg:postcode":"44663",
    "sg:province":"OH",
    "sg:tags":[
        "polishing",
        "washing"
    ],
    "wof:name":"Greg's Car Cleaning",
    "wof:placetype":"venue"
},
  "geometry": {"coordinates":[-81.44511300000001,40.487237],"type":"Point"}
}