{
  "type": "Feature",
  "properties": {
    "addr:full": "216 1st Dr SE New Philadelphia OH 44663",
    "addr:housenumber": "216",
    "addr:postcode": "44663",
    "addr:street": "1St Dr Se",
    "iso:country": "US",
    "sg:address": "216 1st Dr SE",
    "sg:city": "New Philadelphia",
    "sg:classifiers": [
      {
        "category": "Retail",
        "subcategory": "Car Wash",
        "type": "Services"
      }
    ],
    "sg:phone": "+1 330 364 6722",
    "sg:postcode": "44663",
    "sg:province": "OH",
    "sg:tags": [
      "polishing",
      "washing"
    ],
    "wof:name": "Greg's Car Cleaning",
    "wof:placetype": "venue"
  },
  "geometry": {"coordinates":[-81.445113,40.487237],"type":"Point"}
}
