{
  "type": "Feature",
  "properties": {
    "addr:full": "11331 Buckeye Rd Cleveland OH 44104",
    "addr:housenumber": "11331",
    "addr:postcode": "44104",
    "addr:street": "Buckeye Rd",
    "iso:country": "US",
    "sg:address": "11331 Buckeye Rd",
    "sg:city": "Cleveland",
    "sg:classifiers": [
      {
        "category": "Shopping",
        "subcategory": "Clothing, Apparel, \u0026 Fashions",
        "type": "Retail Goods"
      }
    ],
    "sg:phone": "+1 216 229 1407",
    "sg:postcode": "44104",
    "sg:province": "OH",
    "sg:tags": [
      "garment"
    ],
    "sg:website": "www.rainbowshops.com",
    "wof:name": "Rainbow",
    "wof:placetype": "venue"
  },
  "geometry": {"coordinates":[-81.606586,41.48152],"type":"Point"}
}
