{
  "type": "Feature",
  "properties": {
    "iso:country":"US",
    "sg:address":"11331 Buckeye Rd",
    "sg:city":"Cleveland",
    "sg:classifiers":[
        {
            "category":"Shopping",
            "subcategory":"Clothing, Apparel, & Fashions",
            "type":"Retail Goods"
        }
    ],
    "sg:phone":"+1 216 229 1407",
    "sg:postcode":"44104",
    "sg:province":"OH",
    "sg:tags":[
        "garment"
    ],
    "sg:website":"www.rainbowshops.com",
    "wof:name":"Rainbow",
    "wof:placetype":"venue"
},
  "geometry": {"coordinates":[-81.60658599999999,41.48152],"type":"Point"}
}