{
  "type": "Feature",
  "properties": {
    "addr:full":"796 Cincinnati Batavia Pike 100 Cincinnati OH 45245",
    "addr:housenumber":"796;100",
    "addr:postcode":"45245",
    "addr:street":"Cincinnati Batavia Pike",
    "iso:country":"US",
    "sg:address":"796 Cincinnati Batavia Pike 100",
    "sg:city":"Cincinnati",
    "sg:classifiers":[
        {
            "category":"Health Services",
            "subcategory":"Doctor",
            "type":"Services"
        },
        {
            "category":"Health Services",
            "subcategory":"Clinic",
            "type":"Services"
        },
        {
            "category":"Health Services",
            "subcategory":"Nursing And Care Facility",
            "type":"Services"
        },
        {
            "category":"Health Services",
            "subcategory":"Hospital",
            "type":"Services"
        }
    ],
    "sg:phone":"+1 513 752 5800",
    "sg:postcode":"45245",
    "sg:province":"OH",
    "sg:tags":[
        "physician",
        "emergency",
        "medical",
        "surgeons",
        "urgent",
        "internal",
        "medicine"
    ],
    "wof:name":"Medical Associates-Eastern",
    "wof:placetype":"venue"
},
  "geometry": {"coordinates":[-84.273838,39.10611],"type":"Point"}
}