{
  "type": "Feature",
  "properties": {
    "addr:full":"4536 S Warwick Dr Canfield OH 44406",
    "addr:housenumber":"4536",
    "addr:postcode":"44406",
    "addr:street":"S Warwick Dr",
    "iso:country":"US",
    "sg:address":"4536 S Warwick Dr",
    "sg:city":"Canfield",
    "sg:classifiers":[
        {
            "category":"Restaurant",
            "type":"Food & Drink"
        }
    ],
    "sg:phone":"+1 330 518 8998",
    "sg:postcode":"44406",
    "sg:province":"OH",
    "sg:tags":[
        "operation",
        "eating"
    ],
    "wof:name":"Once Again Inn",
    "wof:placetype":"venue"
},
  "geometry": {"coordinates":[-80.73729299999999,41.062862],"type":"Point"}
}