{
  "type": "Feature",
  "properties": {
    "addr:full": "1357 E 105th St Cleveland OH 44106",
    "addr:housenumber": "1357",
    "addr:postcode": "44106",
    "addr:street": "E 105Th St",
    "iso:country": "US",
    "sg:address": "1357 E 105th St",
    "sg:city": "Cleveland",
    "sg:classifiers": [
      {
        "category": "Organizations",
        "subcategory": "Religious Organization",
        "type": "Services"
      }
    ],
    "sg:phone": "+1 216 231 7246",
    "sg:postcode": "44106",
    "sg:province": "OH",
    "sg:tags": [
      "church"
    ],
    "wof:name": "Greater Christian Unity Bapt",
    "wof:placetype": "venue"
  },
  "geometry": {"coordinates":[-81.615399,41.52068],"type":"Point"}
}
