{
  "type": "Feature",
  "properties": {
    "addr:full":"2301 Co Rd 23 Burgoon OH 43407",
    "addr:housenumber":"2301;23",
    "addr:postcode":"43407",
    "addr:street":"Co Rd",
    "iso:country":"US",
    "sg:address":"2301 Co Rd 23",
    "sg:city":"Burgoon",
    "sg:classifiers":[
        {
            "category":"Building & Trades",
            "subcategory":"Construction",
            "type":"Services"
        }
    ],
    "sg:phone":"+1 419 334 8080",
    "sg:postcode":"43407",
    "sg:province":"OH",
    "sg:tags":[
        "residential",
        "nonresidential"
    ],
    "wof:name":"Ochs Contracting Ltd",
    "wof:placetype":"venue"
},
  "geometry": {"coordinates":[-83.21477899999999,41.282461],"type":"Point"}
}