{
  "type": "Feature",
  "properties": {
    "addr:full": "1303 Brighton St Youngstown OH 44505",
    "addr:housenumber": "1303",
    "addr:postcode": "44505",
    "addr:street": "Brighton St",
    "iso:country": "US",
    "sg:address": "1303 Brighton St",
    "sg:city": "Youngstown",
    "sg:classifiers": [
      {
        "category": "Organizations",
        "subcategory": "Religious Organization",
        "type": "Services"
      }
    ],
    "sg:phone": "+1 330 747 1216",
    "sg:postcode": "44505",
    "sg:province": "OH",
    "sg:tags": [
      "church"
    ],
    "wof:name": "Roundup Church-God In Christ",
    "wof:placetype": "venue"
  },
  "geometry": {"coordinates":[-80.586347,41.119442],"type":"Point"}
}
