{
  "type": "Feature",
  "properties": {
    "iso:country":"US",
    "sg:address":"1364 State Rte 61",
    "sg:city":"Marengo",
    "sg:classifiers":[
        {
            "category":"Retail",
            "subcategory":"Auto Repair",
            "type":"Services"
        }
    ],
    "sg:phone":"+1 419 253 3811",
    "sg:postcode":"43334",
    "sg:province":"OH",
    "sg:tags":[
        "body",
        "automobile",
        "painting"
    ],
    "wof:name":"Ron's Body Shop",
    "wof:placetype":"venue"
},
  "geometry": {"coordinates":[-82.82622600000001,40.409622],"type":"Point"}
}