{
  "type": "Feature",
  "properties": {
    "iso:country":"US",
    "sg:address":"1060 Salem Ave",
    "sg:city":"Dayton",
    "sg:classifiers":[
        {
            "category":"Organizations",
            "subcategory":"Non-profit Organization",
            "type":"Services"
        }
    ],
    "sg:phone":"+1 937 837 4345",
    "sg:postcode":"45406",
    "sg:province":"OH",
    "sg:tags":[
        "action",
        "agency",
        "community"
    ],
    "wof:name":"Workplace Reconnections",
    "wof:placetype":"venue"
},
  "geometry": {"coordinates":[-84.21653000000001,39.774457],"type":"Point"}
}