{
  "type": "Feature",
  "properties": {
    "iso:country":"US",
    "sg:address":"7439 Montgomery Rd",
    "sg:city":"Cincinnati",
    "sg:classifiers":[
        {
            "category":"Professional",
            "subcategory":"Business Services",
            "type":"Services"
        }
    ],
    "sg:phone":"+1 513 984 8838",
    "sg:postcode":"45236",
    "sg:province":"OH",
    "sg:tags":[
        "embroidery"
    ],
    "sg:website":"www.awardsbydesign.com",
    "wof:name":"Awards By Design",
    "wof:placetype":"venue"
},
  "geometry": {"coordinates":[-84.395631,39.194027],"type":"Point"}
}