{
  "type": "Feature",
  "properties": {
    "iso:country":"US",
    "sg:address":"427 Peddicord Ave",
    "sg:city":"Washington Ct Hs",
    "sg:classifiers":[
        {
            "category":"Autos & Motor Vehicles",
            "subcategory":"Automobile Sales",
            "type":"Retail Goods"
        }
    ],
    "sg:phone":"+1 740 333 3305",
    "sg:postcode":"43160",
    "sg:province":"OH",
    "sg:tags":[
        "car",
        "dealer"
    ],
    "wof:name":"Stone's Auto Sales",
    "wof:placetype":"venue"
},
  "geometry": {"coordinates":[-83.447749,39.549465],"type":"Point"}
}