{
  "type": "Feature",
  "properties": {
    "addr:full":"2794 Maple Ave Zanesville OH 43701",
    "addr:housenumber":"2794",
    "addr:postcode":"43701",
    "addr:street":"Maple Ave",
    "iso:country":"US",
    "sg:address":"2794 Maple Ave",
    "sg:city":"Zanesville",
    "sg:classifiers":[
        {
            "category":"Banks & Credit Unions",
            "subcategory":"Investment Brokerage",
            "type":"Services"
        }
    ],
    "sg:phone":"+1 740 455 2270",
    "sg:postcode":"43701",
    "sg:province":"OH",
    "sg:tags":[
        "advisory",
        "financial"
    ],
    "wof:name":"Thrivent Financial-Lutherans",
    "wof:placetype":"venue"
},
  "geometry": {"coordinates":[-82.011565,39.973232],"type":"Point"}
}