{
  "type": "Feature",
  "properties": {
    "addr:full":"342 West Ave Tallmadge OH 44278",
    "addr:housenumber":"342",
    "addr:postcode":"44278",
    "addr:street":"West Ave",
    "iso:country":"US",
    "sg:address":"342 West Ave",
    "sg:city":"Tallmadge",
    "sg:classifiers":[
        {
            "category":"Manufacturing",
            "subcategory":"Metals",
            "type":"Manufacturing & Wholesale Goods"
        }
    ],
    "sg:phone":"+1 330 633 3278",
    "sg:postcode":"44278",
    "sg:province":"OH",
    "sg:tags":[
        "wheel"
    ],
    "wof:name":"Martin Wheel Co Inc",
    "wof:placetype":"venue"
},
  "geometry": {"coordinates":[-81.452422,41.101697],"type":"Point"}
}