{
  "type": "Feature",
  "properties": {
    "addr:full":"9241 Ravenna Rd Twinsburg OH 44087",
    "addr:housenumber":"9241",
    "addr:postcode":"44087",
    "addr:street":"Ravenna Rd",
    "iso:country":"US",
    "sg:address":"9241 Ravenna Rd",
    "sg:city":"Twinsburg",
    "sg:classifiers":[
        {
            "category":"Manufacturing",
            "subcategory":"Tools & Machinery",
            "type":"Manufacturing & Wholesale Goods"
        }
    ],
    "sg:phone":"+1 330 963 0990",
    "sg:postcode":"44087",
    "sg:province":"OH",
    "sg:tags":[
        "development",
        "industrial",
        "co",
        "software"
    ],
    "wof:name":"Primape",
    "wof:placetype":"venue"
},
  "geometry": {"coordinates":[-81.423558,41.305485],"type":"Point"}
}