{
  "type": "Feature",
  "properties": {
    "iso:country":"US",
    "sg:address":"74 W Union St",
    "sg:city":"Athens",
    "sg:classifiers":[
        {
            "category":"Restaurant",
            "type":"Food & Drink"
        }
    ],
    "sg:phone":"+1 740 592 4925",
    "sg:postcode":"45701",
    "sg:province":"OH",
    "sg:tags":[
        "quick",
        "serve"
    ],
    "wof:name":"Gold Star Chili",
    "wof:placetype":"venue"
},
  "geometry": {"coordinates":[-82.104416,39.328541],"type":"Point"}
}