{
  "type": "Feature",
  "properties": {
    "iso:country":"US",
    "sg:address":"3980 Delmar Ave",
    "sg:city":"Cincinnati",
    "sg:classifiers":[
        {
            "category":"Personal",
            "type":"Services"
        }
    ],
    "sg:phone":"+1 513 542 3912",
    "sg:postcode":"45211",
    "sg:province":"OH",
    "sg:tags":[
        "therapist",
        "massage"
    ],
    "wof:name":"Candee Lawson",
    "wof:placetype":"venue"
},
  "geometry": {"coordinates":[-84.609525,39.161672],"type":"Point"}
}