{
  "type": "Feature",
  "properties": {
    "iso:country":"US",
    "sg:address":"77 W Thornton St",
    "sg:city":"Akron",
    "sg:classifiers":[
        {
            "category":"Education",
            "subcategory":"School",
            "type":"Public Place"
        }
    ],
    "sg:phone":"+1 330 761 1345",
    "sg:postcode":"44311",
    "sg:province":"OH",
    "wof:name":"Riedinger Middle School",
    "wof:placetype":"venue"
},
  "geometry": {"coordinates":[-81.527833,41.066001],"type":"Point"}
}