{
  "type": "Feature",
  "properties": {
    "iso:country":"US",
    "sg:address":"5151 Monroe St",
    "sg:city":"Toledo",
    "sg:classifiers":[
        {
            "category":"Professional",
            "subcategory":"Lawyer & Legal Services",
            "type":"Services"
        }
    ],
    "sg:phone":"+1 419 882 6054",
    "sg:postcode":"43606",
    "sg:province":"OH",
    "sg:tags":[
        "attorney"
    ],
    "wof:name":"Norton Gutowitz",
    "wof:placetype":"venue"
},
  "geometry": {"coordinates":[-83.653411,41.701846],"type":"Point"}
}