{
  "type": "Feature",
  "properties": {
    "addr:full":"3951 Venice Rd Sandusky OH 44870",
    "addr:housenumber":"3951",
    "addr:postcode":"44870",
    "addr:street":"Venice Rd",
    "iso:country":"US",
    "sg:address":"3951 Venice Rd",
    "sg:city":"Sandusky",
    "sg:classifiers":[
        {
            "category":"Building & Trades",
            "subcategory":"Construction",
            "type":"Services"
        }
    ],
    "sg:phone":"+1 419 626 6635",
    "sg:postcode":"44870",
    "sg:province":"OH",
    "sg:tags":[
        "interior",
        "design"
    ],
    "wof:name":"Slater & Sons Custom Design & Remodel",
    "wof:placetype":"venue"
},
  "geometry": {"coordinates":[-82.756401,41.442101],"type":"Point"}
}