{
  "type": "Feature",
  "properties": {
    "iso:country":"US",
    "sg:address":"10396 Harrison Ave",
    "sg:city":"Harrison",
    "sg:classifiers":[
        {
            "category":"Shopping",
            "subcategory":"Bicycles & Sporting Goods",
            "type":"Retail Goods"
        }
    ],
    "sg:phone":"+1 513 367 5415",
    "sg:postcode":"45030",
    "sg:province":"OH",
    "wof:name":"Landscape Connections",
    "wof:placetype":"venue"
},
  "geometry": {"coordinates":[-84.78528300000001,39.247336],"type":"Point"}
}