{
  "type": "Feature",
  "properties": {
    "addr:full": "10396 Harrison Ave Harrison OH 45030",
    "addr:housenumber": "10396",
    "addr:postcode": "45030",
    "addr:street": "Harrison Ave",
    "iso:country": "US",
    "sg:address": "10396 Harrison Ave",
    "sg:city": "Harrison",
    "sg:classifiers": [
      {
        "category": "Shopping",
        "subcategory": "Bicycles \u0026 Sporting Goods",
        "type": "Retail Goods"
      }
    ],
    "sg:phone": "+1 513 367 5415",
    "sg:postcode": "45030",
    "sg:province": "OH",
    "wof:name": "Landscape Connections",
    "wof:placetype": "venue"
  },
  "geometry": {"coordinates":[-84.785283,39.247336],"type":"Point"}
}
