{
  "type": "Feature",
  "properties": {
    "addr:full":"205 Main St Byesville OH 43723",
    "addr:housenumber":"205",
    "addr:postcode":"43723",
    "addr:street":"Main St",
    "iso:country":"US",
    "sg:address":"205 Main St",
    "sg:city":"Byesville",
    "sg:classifiers":[
        {
            "category":"Food & Beverages",
            "subcategory":"Groceries & Convenience Stores",
            "type":"Retail Goods"
        }
    ],
    "sg:phone":"+1 740 685 8301",
    "sg:postcode":"43723",
    "sg:province":"OH",
    "wof:name":"Byesville IGA",
    "wof:placetype":"venue"
},
  "geometry": {"coordinates":[-81.53452299999999,39.970091],"type":"Point"}
}