{
  "type": "Feature",
  "properties": {
    "iso:country":"US",
    "sg:address":"2905 Mahoning Ave",
    "sg:city":"Youngstown",
    "sg:classifiers":[
        {
            "category":"Personal",
            "subcategory":"Beauty Salon",
            "type":"Services"
        }
    ],
    "sg:phone":"+1 330 793 5112",
    "sg:postcode":"44509",
    "sg:province":"OH",
    "wof:name":"Patty's Hair Design",
    "wof:placetype":"venue"
},
  "geometry": {"coordinates":[-80.703002,41.102999],"type":"Point"}
}