{
  "type": "Feature",
  "properties": {
    "addr:full": "3025 Valley Lane Dr Cleveland OH 44133",
    "addr:housenumber": "3025",
    "addr:postcode": "44133",
    "addr:street": "Valley Lane Dr",
    "iso:country": "US",
    "sg:address": "3025 Valley Lane Dr",
    "sg:city": "Cleveland",
    "sg:classifiers": [
      {
        "category": "Insurance",
        "subcategory": "Insurance Agent",
        "type": "Services"
      }
    ],
    "sg:phone": "+1 440 237 3595",
    "sg:postcode": "44133",
    "sg:province": "OH",
    "wof:name": "Nationwide Insurance",
    "wof:placetype": "venue"
  },
  "geometry": {"coordinates":[-81.707474,41.343577],"type":"Point"}
}
