{
  "type": "Feature",
  "properties": {
    "iso:country":"US",
    "sg:address":"3025 Valley Lane Dr",
    "sg:city":"Cleveland",
    "sg:classifiers":[
        {
            "category":"Insurance",
            "subcategory":"Insurance Agent",
            "type":"Services"
        }
    ],
    "sg:phone":"+1 440 237 3595",
    "sg:postcode":"44133",
    "sg:province":"OH",
    "wof:name":"Nationwide Insurance",
    "wof:placetype":"venue"
},
  "geometry": {"coordinates":[-81.707474,41.343577],"type":"Point"}
}