{
  "type": "Feature",
  "properties": {
    "iso:country":"US",
    "sg:address":"26391 Curtiss Wright Pkwy",
    "sg:city":"Cleveland",
    "sg:classifiers":[
        {
            "category":"Insurance",
            "subcategory":"Hazard Insurance",
            "type":"Services"
        }
    ],
    "sg:phone":"+1 216 731 8215",
    "sg:postcode":"44143",
    "sg:province":"OH",
    "sg:tags":[
        "compensation",
        "worker"
    ],
    "wof:name":"Assocted Cmpensation Resources",
    "wof:placetype":"venue"
},
  "geometry": {"coordinates":[-81.49516300000001,41.565088],"type":"Point"}
}