{
  "type": "Feature",
  "properties": {
    "addr:full": "26391 Curtiss Wright Pkwy Cleveland OH 44143",
    "addr:postcode": "26391;44143",
    "addr:street": "Wright Pkwy",
    "iso:country": "US",
    "sg:address": "26391 Curtiss Wright Pkwy",
    "sg:city": "Cleveland",
    "sg:classifiers": [
      {
        "category": "Insurance",
        "subcategory": "Hazard Insurance",
        "type": "Services"
      }
    ],
    "sg:phone": "+1 216 731 8215",
    "sg:postcode": "44143",
    "sg:province": "OH",
    "sg:tags": [
      "compensation",
      "worker"
    ],
    "wof:name": "Assocted Cmpensation Resources",
    "wof:placetype": "venue"
  },
  "geometry": {"coordinates":[-81.495163,41.565088],"type":"Point"}
}
