{
  "type": "Feature",
  "properties": {
    "iso:country":"US",
    "sg:address":"71 E Mound St",
    "sg:city":"Canal Winchester",
    "sg:classifiers":[
        {
            "category":"Professional",
            "subcategory":"Business Services",
            "type":"Services"
        }
    ],
    "sg:phone":"+1 614 833 2497",
    "sg:postcode":"43110",
    "sg:province":"OH",
    "wof:name":"M G Home Maintenance",
    "wof:placetype":"venue"
},
  "geometry": {"coordinates":[-82.80422,39.844072],"type":"Point"}
}