{
  "type": "Feature",
  "properties": {
    "addr:full": "4515 286th St Toledo OH 43611",
    "addr:housenumber": "4515",
    "addr:postcode": "43611",
    "addr:street": "286Th St",
    "iso:country": "US",
    "sg:address": "4515 286th St",
    "sg:city": "Toledo",
    "sg:classifiers": [
      {
        "category": "Professional",
        "subcategory": "Engineering",
        "type": "Services"
      }
    ],
    "sg:phone": "+1 419 727 3539",
    "sg:postcode": "43611",
    "sg:province": "OH",
    "sg:tags": [
      "engineer"
    ],
    "wof:name": "Engineering Cad Svc",
    "wof:placetype": "venue"
  },
  "geometry": {"coordinates":[-83.48979,41.706846],"type":"Point"}
}
