{
  "type": "Feature",
  "properties": {
    "addr:full":"61322 Southgate Rd Cambridge OH 43725",
    "addr:housenumber":"61322",
    "addr:postcode":"43725",
    "addr:street":"Southgate Rd",
    "iso:country":"US",
    "sg:address":"61322 Southgate Rd",
    "sg:city":"Cambridge",
    "sg:classifiers":[
        {
            "category":"Utilities",
            "subcategory":"Mobile Phone",
            "type":"Services"
        }
    ],
    "sg:phone":"+1 740 439 7132",
    "sg:postcode":"43725",
    "sg:province":"OH",
    "sg:tags":[
        "telephone",
        "cellular"
    ],
    "wof:name":"Cellular Central",
    "wof:placetype":"venue"
},
  "geometry": {"coordinates":[-81.573324,39.989847],"type":"Point"}
}