{
  "type": "Feature",
  "properties": {
    "addr:full":"5371 S Milford Rd Milford OH 45150",
    "addr:housenumber":"5371",
    "addr:postcode":"45150",
    "addr:street":"S Milford Rd",
    "iso:country":"US",
    "sg:address":"5371 S Milford Rd",
    "sg:city":"Milford",
    "sg:classifiers":[
        {
            "category":"Health Services",
            "subcategory":"Clinic",
            "type":"Services"
        }
    ],
    "sg:phone":"+1 513 248 8988",
    "sg:postcode":"45150",
    "sg:province":"OH",
    "sg:tags":[
        "home",
        "care"
    ],
    "wof:name":"Little Miami Home Care Inc",
    "wof:placetype":"venue"
},
  "geometry": {"coordinates":[-84.293678,39.158444],"type":"Point"}
}