{
  "type": "Feature",
  "properties": {
    "addr:full": "3043 Park Ave W Mansfield OH 44906",
    "addr:housenumber": "3043",
    "addr:postcode": "44906",
    "addr:street": "Park Ave W",
    "iso:country": "US",
    "sg:address": "3043 Park Ave W",
    "sg:city": "Mansfield",
    "sg:classifiers": [
      {
        "category": "Retail",
        "subcategory": "Animal Services",
        "type": "Services"
      }
    ],
    "sg:phone": "+1 419 529 5444",
    "sg:postcode": "44906",
    "sg:province": "OH",
    "sg:tags": [
      "kennel"
    ],
    "wof:name": "Lindaire Kennels",
    "wof:placetype": "venue"
  },
  "geometry": {"coordinates":[-82.624149,40.760063],"type":"Point"}
}
