{
  "type": "Feature",
  "properties": {
    "iso:country":"US",
    "sg:address":"15360 State Rte 613",
    "sg:city":"Paulding",
    "sg:classifiers":[
        {
            "category":"Food & Beverages",
            "subcategory":"Groceries & Convenience Stores",
            "type":"Retail Goods"
        }
    ],
    "sg:phone":"+1 419 399 5947",
    "sg:postcode":"45879",
    "sg:province":"OH",
    "sg:tags":[
        "grocer"
    ],
    "wof:name":"Broughton Market",
    "wof:placetype":"venue"
},
  "geometry": {"coordinates":[-84.524141,41.091887],"type":"Point"}
}