{
  "type": "Feature",
  "properties": {
    "addr:full": "100 E Business Way Cincinnati OH 45241",
    "addr:housenumber": "100",
    "addr:postcode": "45241",
    "addr:street": "E Business Way",
    "iso:country": "US",
    "sg:address": "100 E Business Way",
    "sg:city": "Cincinnati",
    "sg:classifiers": [
      {
        "category": "Insurance",
        "subcategory": "Life Insurance",
        "type": "Services"
      }
    ],
    "sg:phone": "+1 513 721 2332",
    "sg:postcode": "45241",
    "sg:province": "OH",
    "sg:tags": [
      "security",
      "carrier"
    ],
    "wof:name": "Nationwide",
    "wof:placetype": "venue"
  },
  "geometry": {"coordinates":[-84.363328,39.281573],"type":"Point"}
}
