{
  "type": "Feature",
  "properties": {
    "addr:full": "3040 Riverside Dr Columbus OH 43221",
    "addr:housenumber": "3040",
    "addr:postcode": "43221",
    "addr:street": "Riverside Dr",
    "iso:country": "US",
    "sg:address": "3040 Riverside Dr",
    "sg:city": "Columbus",
    "sg:classifiers": [
      {
        "category": "Social Services",
        "type": "Services"
      }
    ],
    "sg:phone": "+1 614 486 2911",
    "sg:postcode": "43221",
    "sg:province": "OH",
    "sg:tags": [
      "counselor",
      "marriage",
      "family"
    ],
    "wof:name": "Joanne Haefele",
    "wof:placetype": "venue"
  },
  "geometry": {"coordinates":[-83.090482,40.014934],"type":"Point"}
}
