{
  "type": "Feature",
  "properties": {
    "iso:country":"US",
    "sg:address":"360 E Waterloo Rd",
    "sg:city":"Akron",
    "sg:classifiers":[
        {
            "category":"Food & Beverages",
            "subcategory":"Groceries & Convenience Stores",
            "type":"Retail Goods"
        }
    ],
    "sg:phone":"+1 330 773 9339",
    "sg:postcode":"44319",
    "sg:province":"OH",
    "sg:tags":[
        "grocer"
    ],
    "sg:website":"www.topsmarkets.com",
    "wof:name":"Tops Friendly Market",
    "wof:placetype":"venue"
},
  "geometry": {"coordinates":[-81.513412,41.028779],"type":"Point"}
}