{
  "type": "Feature",
  "properties": {
    "iso:country":"US",
    "sg:address":"238 Euclid Square Mall",
    "sg:city":"Euclid",
    "sg:classifiers":[
        {
            "category":"Shopping",
            "subcategory":"Shoes",
            "type":"Retail Goods"
        }
    ],
    "sg:phone":"+1 216 289 2126",
    "sg:postcode":"44132",
    "sg:province":"OH",
    "sg:tags":[
        "athletic"
    ],
    "wof:name":"Foot Locker",
    "wof:placetype":"venue"
},
  "geometry": {"coordinates":[-81.506744,41.596617],"type":"Point"}
}