{
  "type": "Feature",
  "properties": {
    "addr:full": "1456 S Holland Sylvania Rd Holland OH 43615",
    "addr:housenumber": "1456",
    "addr:postcode": "43615",
    "addr:street": "S Holland Sylvania Rd",
    "iso:country": "US",
    "sg:address": "1456 S Holland Sylvania Rd",
    "sg:city": "Holland",
    "sg:classifiers": [
      {
        "category": "Autos \u0026 Motor Vehicles",
        "subcategory": "Fuel \u0026 Gas Station",
        "type": "Retail Goods"
      }
    ],
    "sg:phone": "+1 419 865 7842",
    "sg:postcode": "43615",
    "sg:province": "OH",
    "sg:tags": [
      "oil"
    ],
    "wof:name": "BP Oil Co",
    "wof:placetype": "venue"
  },
  "geometry": {"coordinates":[-83.684274,41.614069],"type":"Point"}
}
