{
  "type": "Feature",
  "properties": {
    "iso:country":"US",
    "sg:address":"1456 S Holland Sylvania Rd",
    "sg:city":"Holland",
    "sg:classifiers":[
        {
            "category":"Autos & Motor Vehicles",
            "subcategory":"Fuel & Gas Station",
            "type":"Retail Goods"
        }
    ],
    "sg:phone":"+1 419 865 7842",
    "sg:postcode":"43615",
    "sg:province":"OH",
    "sg:tags":[
        "oil"
    ],
    "wof:name":"BP Oil Co",
    "wof:placetype":"venue"
},
  "geometry": {"coordinates":[-83.684274,41.614069],"type":"Point"}
}