{
  "type": "Feature",
  "properties": {
    "addr:full":"3256 W 25th St Cleveland OH 44109",
    "addr:housenumber":"3256",
    "addr:postcode":"44109",
    "addr:street":"W 25Th St",
    "iso:country":"US",
    "sg:address":"3256 W 25th St",
    "sg:city":"Cleveland",
    "sg:classifiers":[
        {
            "category":"Retail",
            "subcategory":"Auto Rental",
            "type":"Services"
        }
    ],
    "sg:phone":"+1 216 351 6670",
    "sg:postcode":"44109",
    "sg:province":"OH",
    "sg:tags":[
        "renting",
        "truck",
        "leasing"
    ],
    "wof:name":"U-Haul Co",
    "wof:placetype":"venue"
},
  "geometry": {"coordinates":[-81.700152,41.466703],"type":"Point"}
}