{
  "type": "Feature",
  "properties": {
    "addr:full": "14625 Puritas Ave Cleveland OH 44135",
    "addr:postcode": "14625;44135",
    "addr:street": "Puritas Ave",
    "iso:country": "US",
    "sg:address": "14625 Puritas Ave",
    "sg:city": "Cleveland",
    "sg:classifiers": [
      {
        "category": "Retail",
        "subcategory": "Repair Shop",
        "type": "Services"
      }
    ],
    "sg:phone": "+1 216 476 0072",
    "sg:postcode": "44135",
    "sg:province": "OH",
    "sg:tags": [
      "equipment",
      "electronic",
      "supply"
    ],
    "wof:name": "Vogt Technology",
    "wof:placetype": "venue"
  },
  "geometry": {"coordinates":[-81.797934,41.433554],"type":"Point"}
}
