{
  "type": "Feature",
  "properties": {
    "iso:country":"US",
    "sg:address":"14625 Puritas Ave",
    "sg:city":"Cleveland",
    "sg:classifiers":[
        {
            "category":"Retail",
            "subcategory":"Repair Shop",
            "type":"Services"
        }
    ],
    "sg:phone":"+1 216 476 0072",
    "sg:postcode":"44135",
    "sg:province":"OH",
    "sg:tags":[
        "equipment",
        "electronic",
        "supply"
    ],
    "wof:name":"Vogt Technology",
    "wof:placetype":"venue"
},
  "geometry": {"coordinates":[-81.797934,41.433554],"type":"Point"}
}