{
  "type": "Feature",
  "properties": {
    "addr:full": "20820 Southgate Park Blvd Cleveland OH 44137",
    "addr:housenumber": "20820",
    "addr:postcode": "44137",
    "addr:street": "Southgate Park Blvd",
    "iso:country": "US",
    "sg:address": "20820 Southgate Park Blvd",
    "sg:city": "Cleveland",
    "sg:classifiers": [
      {
        "category": "Government",
        "subcategory": "Office",
        "type": "Public Place"
      }
    ],
    "sg:phone": "+1 216 475 6855",
    "sg:postcode": "44137",
    "sg:province": "OH",
    "wof:name": "Cuyahoga County Auto \u0026 Boat",
    "wof:placetype": "venue"
  },
  "geometry": {"coordinates":[-81.52824,41.413779],"type":"Point"}
}
