{
  "type": "Feature",
  "properties": {
    "addr:full": "1225 E McMillan St Cincinnati OH 45206",
    "addr:housenumber": "1225",
    "addr:postcode": "45206",
    "addr:street": "E Mcmillan St",
    "iso:country": "US",
    "sg:address": "1225 E McMillan St",
    "sg:city": "Cincinnati",
    "sg:classifiers": [
      {
        "category": "Social Services",
        "type": "Services"
      }
    ],
    "sg:phone": "+1 513 221 0033",
    "sg:postcode": "45206",
    "sg:province": "OH",
    "wof:name": "4c For Children",
    "wof:placetype": "venue"
  },
  "geometry": {"coordinates":[-84.483407,39.125411],"type":"Point"}
}
