{
  "type": "Feature",
  "properties": {
    "addr:full": "235 19th St Findlay OH 45840",
    "addr:housenumber": "235",
    "addr:postcode": "45840",
    "addr:street": "19Th St",
    "iso:country": "US",
    "sg:address": "235 19th St",
    "sg:city": "Findlay",
    "sg:classifiers": [
      {
        "category": "Building \u0026 Trades",
        "subcategory": "Construction",
        "type": "Services"
      }
    ],
    "sg:phone": "+1 419 424 1960",
    "sg:postcode": "45840",
    "sg:province": "OH",
    "sg:tags": [
      "hanging",
      "painter",
      "contractor"
    ],
    "wof:name": "Fleck Painting Inc",
    "wof:placetype": "venue"
  },
  "geometry": {"coordinates":[-83.646458,41.062449],"type":"Point"}
}
