{
  "type": "Feature",
  "properties": {
    "iso:country":"US",
    "sg:address":"235 19th St",
    "sg:city":"Findlay",
    "sg:classifiers":[
        {
            "category":"Building & Trades",
            "subcategory":"Construction",
            "type":"Services"
        }
    ],
    "sg:phone":"+1 419 424 1960",
    "sg:postcode":"45840",
    "sg:province":"OH",
    "sg:tags":[
        "hanging",
        "painter",
        "contractor"
    ],
    "wof:name":"Fleck Painting Inc",
    "wof:placetype":"venue"
},
  "geometry": {"coordinates":[-83.646458,41.062449],"type":"Point"}
}