{
  "type": "Feature",
  "properties": {
    "iso:country":"US",
    "sg:address":"160 E Market St",
    "sg:city":"Sandusky",
    "sg:classifiers":[
        {
            "category":"Food & Beverages",
            "subcategory":"Candy",
            "type":"Retail Goods"
        }
    ],
    "sg:phone":"+1 419 625 8088",
    "sg:postcode":"44870",
    "sg:province":"OH",
    "sg:tags":[
        "confectionery"
    ],
    "wof:name":"Sparky Gourmet Candies",
    "wof:placetype":"venue"
},
  "geometry": {"coordinates":[-82.710882,41.456323],"type":"Point"}
}