{
  "type": "Feature",
  "properties": {
    "addr:full":"265 E 197th St Cleveland OH 44119",
    "addr:housenumber":"265",
    "addr:postcode":"44119",
    "addr:street":"E 197Th St",
    "iso:country":"US",
    "sg:address":"265 E 197th St",
    "sg:city":"Cleveland",
    "sg:classifiers":[
        {
            "category":"Real Estate",
            "subcategory":"Real Estate Operator",
            "type":"Services"
        }
    ],
    "sg:phone":"+1 216 481 9273",
    "sg:postcode":"44119",
    "sg:province":"OH",
    "sg:tags":[
        "building",
        "nonresidential"
    ],
    "wof:name":"Eastlawn Property Owners",
    "wof:placetype":"venue"
},
  "geometry": {"coordinates":[-81.541309,41.597247],"type":"Point"}
}