{
  "type": "Feature",
  "properties": {
    "iso:country":"US",
    "sg:address":"6071 Gifford Dr",
    "sg:city":"Cleveland",
    "sg:classifiers":[
        {
            "category":"Organizations",
            "subcategory":"Religious Organization",
            "type":"Services"
        }
    ],
    "sg:phone":"+1 216 351 4184",
    "sg:postcode":"44144",
    "sg:province":"OH",
    "sg:tags":[
        "clergy"
    ],
    "wof:name":"Marc Kepler",
    "wof:placetype":"venue"
},
  "geometry": {"coordinates":[-81.72810800000001,41.433945],"type":"Point"}
}