{
  "type": "Feature",
  "properties": {
    "iso:country":"US",
    "sg:address":"815 Liberty St",
    "sg:city":"Findlay",
    "sg:classifiers":[
        {
            "category":"Insurance",
            "subcategory":"Insurance Agent",
            "type":"Services"
        }
    ],
    "sg:phone":"+1 419 422 7997",
    "sg:postcode":"45840",
    "sg:province":"OH",
    "wof:name":"Wortman Insurance Services",
    "wof:placetype":"venue"
},
  "geometry": {"coordinates":[-83.65499800000001,41.032416],"type":"Point"}
}