{
  "type": "Feature",
  "properties": {
    "addr:full": "815 Liberty St Findlay OH 45840",
    "addr:housenumber": "815",
    "addr:postcode": "45840",
    "addr:street": "Liberty St",
    "iso:country": "US",
    "sg:address": "815 Liberty St",
    "sg:city": "Findlay",
    "sg:classifiers": [
      {
        "category": "Insurance",
        "subcategory": "Insurance Agent",
        "type": "Services"
      }
    ],
    "sg:phone": "+1 419 422 7997",
    "sg:postcode": "45840",
    "sg:province": "OH",
    "wof:name": "Wortman Insurance Services",
    "wof:placetype": "venue"
  },
  "geometry": {"coordinates":[-83.654998,41.032416],"type":"Point"}
}
