{
  "type": "Feature",
  "properties": {
    "addr:full": "34490 Melinz Pkwy Willoughby OH 44095",
    "addr:postcode": "34490;44095",
    "addr:street": "Melinz Pkwy",
    "iso:country": "US",
    "sg:address": "34490 Melinz Pkwy",
    "sg:city": "Willoughby",
    "sg:classifiers": [
      {
        "category": "Professional",
        "subcategory": "Accounting \u0026 Tax Preparation",
        "type": "Services"
      }
    ],
    "sg:phone": "+1 440 602 9884",
    "sg:postcode": "44095",
    "sg:province": "OH",
    "sg:tags": [
      "bookkeeping",
      "general"
    ],
    "wof:name": "Cunningham \u0026 Assoc",
    "wof:placetype": "venue"
  },
  "geometry": {"coordinates":[-81.44362,41.636414],"type":"Point"}
}
