{
  "type": "Feature",
  "properties": {
    "iso:country":"US",
    "sg:address":"34490 Melinz Pkwy",
    "sg:city":"Willoughby",
    "sg:classifiers":[
        {
            "category":"Professional",
            "subcategory":"Accounting & Tax Preparation",
            "type":"Services"
        }
    ],
    "sg:phone":"+1 440 602 9884",
    "sg:postcode":"44095",
    "sg:province":"OH",
    "sg:tags":[
        "bookkeeping",
        "general"
    ],
    "wof:name":"Cunningham & Assoc",
    "wof:placetype":"venue"
},
  "geometry": {"coordinates":[-81.44362,41.636414],"type":"Point"}
}