{
  "type": "Feature",
  "properties": {
    "iso:country":"US",
    "sg:address":"3074 Derby Rd",
    "sg:city":"Columbus",
    "sg:classifiers":[
        {
            "category":"Building & Trades",
            "subcategory":"Construction",
            "type":"Services"
        }
    ],
    "sg:phone":"+1 614 487 1682",
    "sg:postcode":"43221",
    "sg:province":"OH",
    "sg:tags":[
        "house"
    ],
    "wof:name":"Jims Maintenace & Cnstr Svcs",
    "wof:placetype":"venue"
},
  "geometry": {"coordinates":[-83.077679,40.018133],"type":"Point"}
}