{
  "type": "Feature",
  "properties": {
    "addr:full": "3074 Derby Rd Columbus OH 43221",
    "addr:housenumber": "3074",
    "addr:postcode": "43221",
    "addr:street": "Derby Rd",
    "iso:country": "US",
    "sg:address": "3074 Derby Rd",
    "sg:city": "Columbus",
    "sg:classifiers": [
      {
        "category": "Building \u0026 Trades",
        "subcategory": "Construction",
        "type": "Services"
      }
    ],
    "sg:phone": "+1 614 487 1682",
    "sg:postcode": "43221",
    "sg:province": "OH",
    "sg:tags": [
      "house"
    ],
    "wof:name": "Jims Maintenace \u0026 Cnstr Svcs",
    "wof:placetype": "venue"
  },
  "geometry": {"coordinates":[-83.077679,40.018133],"type":"Point"}
}
