{
  "type": "Feature",
  "properties": {
    "addr:full": "172 E State St Columbus OH 43215",
    "addr:housenumber": "172",
    "addr:postcode": "43215",
    "addr:street": "E State St",
    "iso:country": "US",
    "sg:address": "172 E State St",
    "sg:city": "Columbus",
    "sg:classifiers": [
      {
        "category": "Professional",
        "subcategory": "Management \u0026 Consulting",
        "type": "Services"
      },
      {
        "category": "Government",
        "subcategory": "Office",
        "type": "Public Place"
      }
    ],
    "sg:phone": "+1 614 221 5800",
    "sg:postcode": "43215",
    "sg:province": "OH",
    "sg:tags": [
      "lobbyist",
      "general"
    ],
    "wof:name": "Ohio Capital Policy Cons",
    "wof:placetype": "venue"
  },
  "geometry": {"coordinates":[-82.995261,39.960783],"type":"Point"}
}
