{
  "type": "Feature",
  "properties": {
    "iso:country":"US",
    "sg:address":"172 E State St",
    "sg:city":"Columbus",
    "sg:classifiers":[
        {
            "category":"Professional",
            "subcategory":"Management & Consulting",
            "type":"Services"
        },
        {
            "category":"Government",
            "subcategory":"Office",
            "type":"Public Place"
        }
    ],
    "sg:phone":"+1 614 221 5800",
    "sg:postcode":"43215",
    "sg:province":"OH",
    "sg:tags":[
        "lobbyist",
        "general"
    ],
    "wof:name":"Ohio Capital Policy Cons",
    "wof:placetype":"venue"
},
  "geometry": {"coordinates":[-82.995261,39.960783],"type":"Point"}
}