{
  "type": "Feature",
  "properties": {
    "addr:full": "6061 Ashland Rd Wooster OH 44691",
    "addr:housenumber": "6061",
    "addr:postcode": "44691",
    "addr:street": "Ashland Rd",
    "iso:country": "US",
    "sg:address": "6061 Ashland Rd",
    "sg:city": "Wooster",
    "sg:classifiers": [
      {
        "category": "Freight",
        "type": "Transportation"
      }
    ],
    "sg:phone": "+1 330 263 4165",
    "sg:postcode": "44691",
    "sg:province": "OH",
    "sg:tags": [
      "trucking"
    ],
    "wof:name": "Becker Farms Inc",
    "wof:placetype": "venue"
  },
  "geometry": {"coordinates":[-82.046115,40.817858],"type":"Point"}
}
