{
  "type": "Feature",
  "properties": {
    "iso:country":"US",
    "sg:address":"404 S Pickaway St",
    "sg:city":"Circleville",
    "sg:classifiers":[
        {
            "category":"Professional",
            "subcategory":"Lawyer & Legal Services",
            "type":"Services"
        }
    ],
    "sg:phone":"+1 740 474 9700",
    "sg:postcode":"43113",
    "sg:province":"OH",
    "sg:tags":[
        "attorney"
    ],
    "wof:name":"Lori Pritchard Clar",
    "wof:placetype":"venue"
},
  "geometry": {"coordinates":[-82.943901,39.597906],"type":"Point"}
}