{
  "type": "Feature",
  "properties": {
    "addr:full":"8241 US Hwy 127 Greenville OH 45331",
    "addr:housenumber":"8241",
    "addr:postcode":"45331",
    "addr:street":"Us Hwy 127",
    "iso:country":"US",
    "sg:address":"8241 US Hwy 127",
    "sg:city":"Greenville",
    "sg:classifiers":[
        {
            "category":"Autos & Motor Vehicles",
            "subcategory":"Automobile Sales",
            "type":"Retail Goods"
        }
    ],
    "sg:phone":"+1 937 547 1011",
    "sg:postcode":"45331",
    "sg:province":"OH",
    "sg:tags":[
        "car",
        "dealer"
    ],
    "wof:name":"Larimer Auto Sales",
    "wof:placetype":"venue"
},
  "geometry": {"coordinates":[-84.61074000000001,40.152212],"type":"Point"}
}