{
  "type": "Feature",
  "properties": {
    "iso:country":"US",
    "sg:address":"14282 Butternut Rd",
    "sg:city":"Burton",
    "sg:classifiers":[
        {
            "category":"Travel",
            "subcategory":"Campground",
            "type":"Entertainment"
        }
    ],
    "sg:phone":"+1 440 834 8984",
    "sg:postcode":"44021",
    "sg:province":"OH",
    "sg:tags":[
        "camp"
    ],
    "sg:website":"www.campburton.org",
    "wof:name":"Camp Burton",
    "wof:placetype":"venue"
},
  "geometry": {"coordinates":[-81.13966000000001,41.497234],"type":"Point"}
}