{
  "type": "Feature",
  "properties": {
    "addr:full": "6163 Glenway Ave Cincinnati OH 45211",
    "addr:housenumber": "6163",
    "addr:postcode": "45211",
    "addr:street": "Glenway Ave",
    "iso:country": "US",
    "sg:address": "6163 Glenway Ave",
    "sg:city": "Cincinnati",
    "sg:classifiers": [
      {
        "category": "Retail",
        "subcategory": "Repair Shop",
        "type": "Services"
      }
    ],
    "sg:phone": "+1 513 662 6515",
    "sg:postcode": "45211",
    "sg:province": "OH",
    "sg:tags": [
      "lock",
      "locksmith"
    ],
    "wof:name": "Golden Key Locksmith Inc",
    "wof:placetype": "venue"
  },
  "geometry": {"coordinates":[-84.624649,39.145593],"type":"Point"}
}
