{
  "type": "Feature",
  "properties": {
    "iso:country":"US",
    "sg:address":"20563 Holly Cir",
    "sg:city":"Strongsville",
    "sg:classifiers":[
        {
            "category":"Shopping",
            "type":"Retail Goods"
        }
    ],
    "sg:phone":"+1 440 238 7582",
    "sg:postcode":"44149",
    "sg:province":"OH",
    "sg:tags":[
        "merchandise"
    ],
    "wof:name":"Bb Crafts",
    "wof:placetype":"venue"
},
  "geometry": {"coordinates":[-81.85342900000001,41.301126],"type":"Point"}
}