{
  "type": "Feature",
  "properties": {
    "addr:full": "20563 Holly Cir Strongsville OH 44149",
    "addr:housenumber": "20563",
    "addr:postcode": "44149",
    "addr:street": "Holly Cir",
    "iso:country": "US",
    "sg:address": "20563 Holly Cir",
    "sg:city": "Strongsville",
    "sg:classifiers": [
      {
        "category": "Shopping",
        "type": "Retail Goods"
      }
    ],
    "sg:phone": "+1 440 238 7582",
    "sg:postcode": "44149",
    "sg:province": "OH",
    "sg:tags": [
      "merchandise"
    ],
    "wof:name": "Bb Crafts",
    "wof:placetype": "venue"
  },
  "geometry": {"coordinates":[-81.853429,41.301126],"type":"Point"}
}
