{
  "type": "Feature",
  "properties": {
    "addr:full": "255 E 5th St Cincinnati OH 45202",
    "addr:housenumber": "255",
    "addr:postcode": "45202",
    "addr:street": "E 5Th St",
    "iso:country": "US",
    "sg:address": "255 E 5th St",
    "sg:city": "Cincinnati",
    "sg:classifiers": [
      {
        "category": "Professional",
        "subcategory": "Management \u0026 Consulting",
        "type": "Services"
      }
    ],
    "sg:phone": "+1 513 381 1184",
    "sg:postcode": "45202",
    "sg:province": "OH",
    "sg:tags": [
      "consultant",
      "business"
    ],
    "wof:name": "Midwest Manufacturing Sltns",
    "wof:placetype": "venue"
  },
  "geometry": {"coordinates":[-84.50833,39.101769],"type":"Point"}
}
