{
  "type": "Feature",
  "properties": {
    "addr:full":"436 E 2nd St Salem OH 44460",
    "addr:housenumber":"436",
    "addr:postcode":"44460",
    "addr:street":"E 2Nd St",
    "iso:country":"US",
    "sg:address":"436 E 2nd St",
    "sg:city":"Salem",
    "sg:classifiers":[
        {
            "category":"Organizations",
            "subcategory":"Religious Organization",
            "type":"Services"
        }
    ],
    "sg:phone":"+1 330 337 9555",
    "sg:postcode":"44460",
    "sg:province":"OH",
    "sg:tags":[
        "church"
    ],
    "wof:name":"First Presbyterian Church",
    "wof:placetype":"venue"
},
  "geometry": {"coordinates":[-80.854434,40.902172],"type":"Point"}
}