{
  "type": "Feature",
  "properties": {
    "addr:full": "8665 Factory Shops Blvd Jeffersonville OH 43128",
    "addr:housenumber": "8665",
    "addr:postcode": "43128",
    "addr:street": "Factory Shops Blvd",
    "iso:country": "US",
    "sg:address": "8665 Factory Shops Blvd",
    "sg:city": "Jeffersonville",
    "sg:classifiers": [
      {
        "category": "Shopping",
        "subcategory": "Shoes",
        "type": "Retail Goods"
      }
    ],
    "sg:phone": "+1 740 948 9033",
    "sg:postcode": "43128",
    "sg:province": "OH",
    "sg:website": "www.allenedmonds.com",
    "wof:name": "Allen-Edmonds Co Shoe Store",
    "wof:placetype": "venue"
  },
  "geometry": {"coordinates":[-83.601943,39.617226],"type":"Point"}
}
