{
  "type": "Feature",
  "properties": {
    "addr:full":"5417 E 132nd St Cleveland OH 44125",
    "addr:housenumber":"5417",
    "addr:postcode":"44125",
    "addr:street":"E 132Nd St",
    "iso:country":"US",
    "sg:address":"5417 E 132nd St",
    "sg:city":"Cleveland",
    "sg:classifiers":[
        {
            "category":"Home & Garden",
            "subcategory":"Carpets & Floor Coverings",
            "type":"Retail Goods"
        }
    ],
    "sg:phone":"+1 216 475 2401",
    "sg:postcode":"44125",
    "sg:province":"OH",
    "sg:tags":[
        "dealer",
        "rug"
    ],
    "wof:name":"Royal Carpet Solutions",
    "wof:placetype":"venue"
},
  "geometry": {"coordinates":[-81.591258,41.416438],"type":"Point"}
}