{
  "type": "Feature",
  "properties": {
    "iso:country":"US",
    "sg:address":"120 Shoup Mill Rd",
    "sg:city":"Dayton",
    "sg:classifiers":[
        {
            "category":"Bars & Pubs",
            "type":"Food & Drink"
        }
    ],
    "sg:phone":"+1 937 274 2384",
    "sg:postcode":"45415",
    "sg:province":"OH",
    "sg:tags":[
        "club",
        "night"
    ],
    "wof:name":"Frogs Nightclub",
    "wof:placetype":"venue"
},
  "geometry": {"coordinates":[-84.22579899999999,39.812698],"type":"Point"}
}