{
  "type": "Feature",
  "properties": {
    "addr:full": "120 Shoup Mill Rd Dayton OH 45415",
    "addr:housenumber": "120",
    "addr:postcode": "45415",
    "addr:street": "Shoup Mill Rd",
    "iso:country": "US",
    "sg:address": "120 Shoup Mill Rd",
    "sg:city": "Dayton",
    "sg:classifiers": [
      {
        "category": "Bars \u0026 Pubs",
        "type": "Food \u0026 Drink"
      }
    ],
    "sg:phone": "+1 937 274 2384",
    "sg:postcode": "45415",
    "sg:province": "OH",
    "sg:tags": [
      "club",
      "night"
    ],
    "wof:name": "Frogs Nightclub",
    "wof:placetype": "venue"
  },
  "geometry": {"coordinates":[-84.225799,39.812698],"type":"Point"}
}
