{
  "type": "Feature",
  "properties": {
    "iso:country":"US",
    "sg:address":"7049 State Rte 108",
    "sg:city":"Wauseon",
    "sg:phone":"+1 419 335 7616",
    "sg:postcode":"43567",
    "sg:province":"OH",
    "sg:tags":[
        "farm",
        "corn",
        "soybean"
    ],
    "wof:name":"Craig Myers",
    "wof:placetype":"venue"
},
  "geometry": {"coordinates":[-84.148636,41.573285],"type":"Point"}
}