{
  "type": "Feature",
  "properties": {
    "iso:country":"US",
    "sg:address":"4725 Lorain Ave",
    "sg:city":"Cleveland",
    "sg:classifiers":[
        {
            "category":"Autos & Motor Vehicles",
            "subcategory":"Automobile Sales",
            "type":"Retail Goods"
        }
    ],
    "sg:phone":"+1 216 351 7113",
    "sg:postcode":"44102",
    "sg:province":"OH",
    "sg:tags":[
        "dealers-used",
        "car",
        "used",
        "cars-wholesale",
        "new"
    ],
    "wof:name":"United Auto Sales",
    "wof:placetype":"venue"
},
  "geometry": {"coordinates":[-81.719205,41.478294],"type":"Point"}
}