{
  "type": "Feature",
  "properties": {
    "iso:country":"US",
    "sg:address":"4601 Eastgate Blvd",
    "sg:city":"Cincinnati",
    "sg:classifiers":[
        {
            "category":"Restaurant",
            "type":"Food & Drink"
        }
    ],
    "sg:phone":"+1 513 752 0108",
    "sg:postcode":"45245",
    "sg:province":"OH",
    "sg:website":"www.goldstarchili.com",
    "wof:name":"Gold Star Chili",
    "wof:placetype":"venue"
},
  "geometry": {"coordinates":[-84.27309099999999,39.10214],"type":"Point"}
}