{
  "type": "Feature",
  "properties": {
    "addr:full": "458 W Main St Batavia OH 45103",
    "addr:housenumber": "458",
    "addr:postcode": "45103",
    "addr:street": "W Main St",
    "iso:country": "US",
    "sg:address": "458 W Main St",
    "sg:city": "Batavia",
    "sg:classifiers": [
      {
        "category": "Manufacturing",
        "subcategory": "Chemicals \u0026 Compounds",
        "type": "Manufacturing \u0026 Wholesale Goods"
      }
    ],
    "sg:phone": "+1 513 732 2464",
    "sg:postcode": "45103",
    "sg:province": "OH",
    "sg:tags": [
      "processing",
      "custom"
    ],
    "wof:name": "Cincinnati Chemical Processing",
    "wof:placetype": "venue"
  },
  "geometry": {"coordinates":[-84.185465,39.081652],"type":"Point"}
}
