{
  "type": "Feature",
  "properties": {
    "iso:country":"US",
    "sg:address":"458 W Main St",
    "sg:city":"Batavia",
    "sg:classifiers":[
        {
            "category":"Manufacturing",
            "subcategory":"Chemicals & Compounds",
            "type":"Manufacturing & Wholesale Goods"
        }
    ],
    "sg:phone":"+1 513 732 2464",
    "sg:postcode":"45103",
    "sg:province":"OH",
    "sg:tags":[
        "processing",
        "custom"
    ],
    "wof:name":"Cincinnati Chemical Processing",
    "wof:placetype":"venue"
},
  "geometry": {"coordinates":[-84.18546499999999,39.081652],"type":"Point"}
}