{
  "type": "Feature",
  "properties": {
    "addr:full": "215 N Clinton St Defiance OH 43512",
    "addr:housenumber": "215",
    "addr:postcode": "43512",
    "addr:street": "N Clinton St",
    "iso:country": "US",
    "sg:address": "215 N Clinton St",
    "sg:city": "Defiance",
    "sg:classifiers": [
      {
        "category": "Home \u0026 Garden",
        "subcategory": "Carpets \u0026 Floor Coverings",
        "type": "Retail Goods"
      }
    ],
    "sg:phone": "+1 419 782 5330",
    "sg:postcode": "43512",
    "sg:province": "OH",
    "sg:tags": [
      "laying",
      "contractor"
    ],
    "wof:name": "Carpet Unlimited",
    "wof:placetype": "venue"
  },
  "geometry": {"coordinates":[-84.360609,41.291721],"type":"Point"}
}
