{
  "type": "Feature",
  "properties": {
    "addr:full":"25932 Twp Rd 59 Warsaw OH 43844",
    "addr:housenumber":"59",
    "addr:postcode":"25932;43844",
    "addr:street":"Twp Rd",
    "iso:country":"US",
    "sg:address":"25932 Twp Rd 59",
    "sg:city":"Warsaw",
    "sg:phone":"+1 740 824 3247",
    "sg:postcode":"43844",
    "sg:province":"OH",
    "sg:tags":[
        "farm",
        "corn",
        "soybean"
    ],
    "wof:name":"Francis Buxton Farm",
    "wof:placetype":"venue"
},
  "geometry": {"coordinates":[-82.052401,40.32011],"type":"Point"}
}