{
  "type": "Feature",
  "properties": {
    "addr:full":"64 W Main St Mc Connelsville OH 43756",
    "addr:housenumber":"64",
    "addr:postcode":"43756",
    "addr:street":"W Main St",
    "iso:country":"US",
    "sg:address":"64 W Main St",
    "sg:city":"Mc Connelsville",
    "sg:classifiers":[
        {
            "category":"Personal",
            "subcategory":"Beauty Salon",
            "type":"Services"
        }
    ],
    "sg:phone":"+1 740 962 4118",
    "sg:postcode":"43756",
    "sg:province":"OH",
    "wof:name":"Dynamic Designs",
    "wof:placetype":"venue"
},
  "geometry": {"coordinates":[-81.85440800000001,39.648802],"type":"Point"}
}