{
  "type": "Feature",
  "properties": {
    "addr:full":"25 Industrial Dr Lexington OH 44904",
    "addr:housenumber":"25",
    "addr:postcode":"44904",
    "addr:street":"Industrial Dr",
    "iso:country":"US",
    "sg:address":"25 Industrial Dr",
    "sg:city":"Lexington",
    "sg:classifiers":[
        {
            "category":"Manufacturing",
            "subcategory":"Motor Vehicles & Parts",
            "type":"Manufacturing & Wholesale Goods"
        }
    ],
    "sg:phone":"+1 419 884 9788",
    "sg:postcode":"44904",
    "sg:province":"OH",
    "sg:tags":[
        "automobile",
        "supply"
    ],
    "wof:name":"Contact Industries",
    "wof:placetype":"venue"
},
  "geometry": {"coordinates":[-82.56856500000001,40.678659],"type":"Point"}
}