{
  "type": "Feature",
  "properties": {
    "iso:country":"US",
    "sg:address":"265 N Main St",
    "sg:city":"Munroe Falls",
    "sg:classifiers":[
        {
            "category":"Arts & Performance",
            "subcategory":"Theater",
            "type":"Entertainment"
        }
    ],
    "sg:phone":"+1 330 688 6065",
    "sg:postcode":"44262",
    "sg:province":"OH",
    "sg:tags":[
        "dance",
        "company"
    ],
    "sg:website":"www.childrensballettheatre.org",
    "wof:name":"Children's Ballet Theater",
    "wof:placetype":"venue"
},
  "geometry": {"coordinates":[-81.440521,41.146498],"type":"Point"}
}