{
  "type": "Feature",
  "properties": {
    "addr:full":"416 Morrison Rd Columbus OH 43213",
    "addr:housenumber":"416",
    "addr:postcode":"43213",
    "addr:street":"Morrison Rd",
    "iso:country":"US",
    "sg:address":"416 Morrison Rd",
    "sg:city":"Columbus",
    "sg:phone":"+1 614 864 6900",
    "sg:postcode":"43213",
    "sg:province":"OH",
    "sg:tags":[
        "scale"
    ],
    "wof:name":"Worthington Weighing Systems",
    "wof:placetype":"venue"
},
  "geometry": {"coordinates":[-82.85493099999999,39.984319],"type":"Point"}
}