{
  "type": "Feature",
  "properties": {
    "iso:country":"US",
    "sg:address":"12 E Dresden Ave",
    "sg:city":"Akron",
    "sg:classifiers":[
        {
            "category":"Restaurant",
            "type":"Food & Drink"
        }
    ],
    "sg:phone":"+1 330 773 2320",
    "sg:postcode":"44301",
    "sg:province":"OH",
    "sg:tags":[
        "caterer"
    ],
    "wof:name":"Horning's Food Svc & Catering",
    "wof:placetype":"venue"
},
  "geometry": {"coordinates":[-81.52522999999999,41.032493],"type":"Point"}
}