{
  "type": "Feature",
  "properties": {
    "addr:full":"2855 W Market St Fairlawn OH 44333",
    "addr:housenumber":"2855",
    "addr:postcode":"44333",
    "addr:street":"W Market St",
    "iso:country":"US",
    "sg:address":"2855 W Market St",
    "sg:city":"Fairlawn",
    "sg:classifiers":[
        {
            "category":"Professional",
            "type":"Services"
        }
    ],
    "sg:phone":"+1 330 869 0465",
    "sg:postcode":"44333",
    "sg:province":"OH",
    "sg:tags":[
        "establishment"
    ],
    "wof:name":"BFS",
    "wof:placetype":"venue"
},
  "geometry": {"coordinates":[-81.606709,41.126673],"type":"Point"}
}