{
  "type": "Feature",
  "properties": {
    "addr:full": "5335 Loma Linda Ln NE Canton OH 44714",
    "addr:housenumber": "5335",
    "addr:postcode": "44714",
    "addr:street": "Loma Linda Ln Ne",
    "iso:country": "US",
    "sg:address": "5335 Loma Linda Ln NE",
    "sg:city": "Canton",
    "sg:classifiers": [
      {
        "category": "Freight",
        "type": "Transportation"
      }
    ],
    "sg:phone": "+1 330 494 9435",
    "sg:postcode": "44714",
    "sg:province": "OH",
    "wof:name": "Singer \u0026 Assoc",
    "wof:placetype": "venue"
  },
  "geometry": {"coordinates":[-81.358756,40.858437],"type":"Point"}
}
