{
  "type": "Feature",
  "properties": {
    "addr:full":"53 S Champion St Youngstown OH 44503",
    "addr:housenumber":"53",
    "addr:postcode":"44503",
    "addr:street":"S Champion St",
    "iso:country":"US",
    "sg:address":"53 S Champion St",
    "sg:city":"Youngstown",
    "sg:classifiers":[
        {
            "category":"Parking",
            "type":"Transportation"
        }
    ],
    "sg:phone":"+1 330 746 7275",
    "sg:postcode":"44503",
    "sg:province":"OH",
    "sg:tags":[
        "garage"
    ],
    "sg:website":"www.usaparking.com",
    "wof:name":"USA Parking Youngstown",
    "wof:placetype":"venue"
},
  "geometry": {"coordinates":[-80.648478,41.099089],"type":"Point"}
}