{
  "type": "Feature",
  "properties": {
    "addr:full": "30008 Standley Rd Holgate OH 43527",
    "addr:postcode": "30008;43527",
    "addr:street": "Standley Rd",
    "iso:country": "US",
    "sg:address": "30008 Standley Rd",
    "sg:city": "Holgate",
    "sg:phone": "+1 419 395 1571",
    "sg:postcode": "43527",
    "sg:province": "OH",
    "sg:tags": [
      "farm",
      "corn",
      "soybean"
    ],
    "wof:name": "Donald E Engel",
    "wof:placetype": "venue"
  },
  "geometry": {"coordinates":[-84.24659,41.267707],"type":"Point"}
}
