{
  "type": "Feature",
  "properties": {
    "addr:full":"5639 Main St Sylvania OH 43560",
    "addr:housenumber":"5639",
    "addr:postcode":"43560",
    "addr:street":"Main St",
    "iso:country":"US",
    "sg:address":"5639 Main St",
    "sg:city":"Sylvania",
    "sg:classifiers":[
        {
            "category":"Food & Beverages",
            "subcategory":"Bakery",
            "type":"Retail Goods"
        }
    ],
    "sg:phone":"+1 419 882 2302",
    "sg:postcode":"43560",
    "sg:province":"OH",
    "sg:tags":[
        "baker"
    ],
    "wof:name":"Brieschke's Bakery",
    "wof:placetype":"venue"
},
  "geometry": {"coordinates":[-83.703166,41.717102],"type":"Point"}
}