{
  "type": "Feature",
  "properties": {
    "addr:full":"147 N 5th St Steubenville OH 43952",
    "addr:housenumber":"147",
    "addr:postcode":"43952",
    "addr:street":"N 5Th St",
    "iso:country":"US",
    "sg:address":"147 N 5th St",
    "sg:city":"Steubenville",
    "sg:classifiers":[
        {
            "category":"Food & Beverages",
            "subcategory":"Specialty",
            "type":"Retail Goods"
        }
    ],
    "sg:phone":"+1 740 284 0111",
    "sg:postcode":"43952",
    "sg:province":"OH",
    "sg:tags":[
        "water",
        "bulk",
        "company"
    ],
    "wof:name":"Vita Genesis",
    "wof:placetype":"venue"
},
  "geometry": {"coordinates":[-80.615842,40.361693],"type":"Point"}
}