{
  "type": "Feature",
  "properties": {
    "iso:country":"US",
    "sg:address":"127 S Columbus St",
    "sg:city":"Galion",
    "sg:classifiers":[
        {
            "category":"Organizations",
            "subcategory":"Religious Organization",
            "type":"Services"
        }
    ],
    "sg:phone":"+1 419 468 3107",
    "sg:postcode":"44833",
    "sg:province":"OH",
    "sg:tags":[
        "church"
    ],
    "sg:website":"www.galionfirstlutheran.org",
    "wof:name":"First Lutheran Church-ELCA",
    "wof:placetype":"venue"
},
  "geometry": {"coordinates":[-82.78765199999999,40.733495],"type":"Point"}
}