{
  "type": "Feature",
  "properties": {
    "iso:country":"US",
    "sg:address":"1236 Fareharm Dr",
    "sg:city":"New Albany",
    "sg:classifiers":[
        {
            "category":"Retail",
            "subcategory":"Portrait Studio",
            "type":"Services"
        }
    ],
    "sg:phone":"+1 614 933 9700",
    "sg:postcode":"43054",
    "sg:province":"OH",
    "sg:tags":[
        "photographer"
    ],
    "wof:name":"Coast To Coast Studios",
    "wof:placetype":"venue"
},
  "geometry": {"coordinates":[-82.817555,40.048833],"type":"Point"}
}