{
  "type": "Feature",
  "properties": {
    "addr:full": "14993 Sperry Rd Novelty OH 44072",
    "addr:housenumber": "14993",
    "addr:postcode": "44072",
    "addr:street": "Sperry Rd",
    "iso:country": "US",
    "sg:address": "14993 Sperry Rd",
    "sg:city": "Novelty",
    "sg:classifiers": [
      {
        "category": "Building \u0026 Trades",
        "subcategory": "Landscaping Services",
        "type": "Services"
      }
    ],
    "sg:phone": "+1 440 338 1570",
    "sg:postcode": "44072",
    "sg:province": "OH",
    "wof:name": "Hawthorne Hill Landscaping",
    "wof:placetype": "venue"
  },
  "geometry": {"coordinates":[-81.288128,41.45846],"type":"Point"}
}
