{
  "type": "Feature",
  "properties": {
    "iso:country":"US",
    "sg:address":"8668 State Rte 93",
    "sg:city":"Jackson",
    "sg:classifiers":[
        {
            "category":"Health Services",
            "subcategory":"Nursing And Care Facility",
            "type":"Services"
        }
    ],
    "sg:phone":"+1 740 286 5026",
    "sg:postcode":"45640",
    "sg:province":"OH",
    "sg:tags":[
        "skilled"
    ],
    "wof:name":"Heartland of Jackson",
    "wof:placetype":"venue"
},
  "geometry": {"coordinates":[-82.573791,38.96209],"type":"Point"}
}