{
  "type": "Feature",
  "properties": {
    "addr:full": "1745 Front St Cuyahoga Falls OH 44221",
    "addr:housenumber": "1745",
    "addr:postcode": "44221",
    "addr:street": "Front St",
    "iso:country": "US",
    "sg:address": "1745 Front St",
    "sg:city": "Cuyahoga Falls",
    "sg:classifiers": [
      {
        "category": "Retail",
        "subcategory": "Auto Repair",
        "type": "Services"
      }
    ],
    "sg:phone": "+1 330 945 4911",
    "sg:postcode": "44221",
    "sg:province": "OH",
    "sg:tags": [
      "truck"
    ],
    "wof:name": "Thomas Trucks",
    "wof:placetype": "venue"
  },
  "geometry": {"coordinates":[-81.484724,41.12878],"type":"Point"}
}
