{
  "type": "Feature",
  "properties": {
    "addr:full": "1834 Section Rd Cincinnati OH 45237",
    "addr:housenumber": "1834",
    "addr:postcode": "45237",
    "addr:street": "Section Rd",
    "iso:country": "US",
    "sg:address": "1834 Section Rd",
    "sg:city": "Cincinnati",
    "sg:classifiers": [
      {
        "category": "Organizations",
        "subcategory": "Religious Organization",
        "type": "Services"
      }
    ],
    "sg:phone": "+1 513 531 7283",
    "sg:postcode": "45237",
    "sg:province": "OH",
    "sg:tags": [
      "church"
    ],
    "wof:name": "Beulah Baptist Church",
    "wof:placetype": "venue"
  },
  "geometry": {"coordinates":[-84.457041,39.197391],"type":"Point"}
}
