{
  "type": "Feature",
  "properties": {
    "iso:country":"US",
    "sg:address":"1834 Section Rd",
    "sg:city":"Cincinnati",
    "sg:classifiers":[
        {
            "category":"Organizations",
            "subcategory":"Religious Organization",
            "type":"Services"
        }
    ],
    "sg:phone":"+1 513 531 7283",
    "sg:postcode":"45237",
    "sg:province":"OH",
    "sg:tags":[
        "church"
    ],
    "wof:name":"Beulah Baptist Church",
    "wof:placetype":"venue"
},
  "geometry": {"coordinates":[-84.457041,39.197391],"type":"Point"}
}