{
  "type": "Feature",
  "properties": {
    "addr:full": "12079 Hackett Rd Apple Creek OH 44606",
    "addr:postcode": "12079;44606",
    "addr:street": "Hackett Rd",
    "iso:country": "US",
    "sg:address": "12079 Hackett Rd",
    "sg:city": "Apple Creek",
    "sg:classifiers": [
      {
        "category": "Freight",
        "type": "Transportation"
      }
    ],
    "sg:phone": "+1 330 465 2433",
    "sg:postcode": "44606",
    "sg:province": "OH",
    "wof:name": "Hope Morning Services",
    "wof:placetype": "venue"
  },
  "geometry": {"coordinates":[-81.764484,40.755731],"type":"Point"}
}
