{
  "type": "Feature",
  "properties": {
    "addr:full":"11 Pawnee Trl Malvern OH 44644",
    "addr:housenumber":"11",
    "addr:postcode":"44644",
    "addr:street":"Pawnee Trl",
    "iso:country":"US",
    "sg:address":"11 Pawnee Trl",
    "sg:city":"Malvern",
    "sg:classifiers":[
        {
            "category":"Food & Beverages",
            "subcategory":"Specialty",
            "type":"Retail Goods"
        }
    ],
    "sg:phone":"+1 330 863 0372",
    "sg:postcode":"44644",
    "sg:province":"OH",
    "wof:name":"Vicars Nutrition",
    "wof:placetype":"venue"
},
  "geometry": {"coordinates":[-81.178979,40.662161],"type":"Point"}
}