{
  "type": "Feature",
  "properties": {
    "iso:country":"US",
    "sg:address":"1637 Lee Rd",
    "sg:city":"Cleveland",
    "sg:classifiers":[
        {
            "category":"Shopping",
            "subcategory":"Used Merchandise",
            "type":"Retail Goods"
        }
    ],
    "sg:phone":"+1 216 308 1086",
    "sg:postcode":"44118",
    "sg:province":"OH",
    "sg:tags":[
        "antique"
    ],
    "wof:name":"Gatsby Gallery Antiques",
    "wof:placetype":"venue"
},
  "geometry": {"coordinates":[-81.568787,41.515518],"type":"Point"}
}