{
  "type": "Feature",
  "properties": {
    "addr:full": "5309 Dellbrook Dr Fairfield OH 45014",
    "addr:housenumber": "5309",
    "addr:postcode": "45014",
    "addr:street": "Dellbrook Dr",
    "iso:country": "US",
    "sg:address": "5309 Dellbrook Dr",
    "sg:city": "Fairfield",
    "sg:classifiers": [
      {
        "category": "Social Services",
        "type": "Services"
      }
    ],
    "sg:phone": "+1 513 893 7000",
    "sg:postcode": "45014",
    "sg:province": "OH",
    "sg:tags": [
      "counseling"
    ],
    "wof:name": "Heartmender Counseling Ctr",
    "wof:placetype": "venue"
  },
  "geometry": {"coordinates":[-84.577525,39.333998],"type":"Point"}
}
