{
  "type": "Feature",
  "properties": {
    "iso:country":"US",
    "sg:address":"5309 Dellbrook Dr",
    "sg:city":"Fairfield",
    "sg:classifiers":[
        {
            "category":"Social Services",
            "type":"Services"
        }
    ],
    "sg:phone":"+1 513 893 7000",
    "sg:postcode":"45014",
    "sg:province":"OH",
    "sg:tags":[
        "counseling"
    ],
    "wof:name":"Heartmender Counseling Ctr",
    "wof:placetype":"venue"
},
  "geometry": {"coordinates":[-84.57752499999999,39.333998],"type":"Point"}
}