{
  "type": "Feature",
  "properties": {
    "addr:full": "4363 Manchester Ave SW Navarre OH 44662",
    "addr:housenumber": "4363",
    "addr:postcode": "44662",
    "addr:street": "Manchester Ave Sw",
    "iso:country": "US",
    "sg:address": "4363 Manchester Ave SW",
    "sg:city": "Navarre",
    "sg:classifiers": [
      {
        "category": "Organizations",
        "subcategory": "Religious Organization",
        "type": "Services"
      }
    ],
    "sg:phone": "+1 330 833 6313",
    "sg:postcode": "44662",
    "sg:province": "OH",
    "sg:tags": [
      "church"
    ],
    "wof:name": "Christ's Community Church",
    "wof:placetype": "venue"
  },
  "geometry": {"coordinates":[-81.595755,40.743584],"type":"Point"}
}
