{
  "type": "Feature",
  "properties": {
    "iso:country":"US",
    "sg:address":"4199 Wilton Pl",
    "sg:city":"Columbus",
    "sg:classifiers":[
        {
            "category":"Building & Trades",
            "subcategory":"Construction",
            "type":"Services"
        }
    ],
    "sg:phone":"+1 614 237 2844",
    "sg:postcode":"43227",
    "sg:province":"OH",
    "sg:tags":[
        "hanging",
        "contractor"
    ],
    "wof:name":"Accurate Star Painting",
    "wof:placetype":"venue"
},
  "geometry": {"coordinates":[-82.881725,39.939352],"type":"Point"}
}