{
  "type": "Feature",
  "properties": {
    "addr:full": "3989 Orchard Rd Cleveland OH 44121",
    "addr:housenumber": "3989",
    "addr:postcode": "44121",
    "addr:street": "Orchard Rd",
    "iso:country": "US",
    "sg:address": "3989 Orchard Rd",
    "sg:city": "Cleveland",
    "sg:classifiers": [
      {
        "category": "Professional",
        "type": "Services"
      }
    ],
    "sg:phone": "+1 216 381 1349",
    "sg:postcode": "44121",
    "sg:province": "OH",
    "wof:name": "Bill Porozynski",
    "wof:placetype": "venue"
  },
  "geometry": {"coordinates":[-81.540316,41.529375],"type":"Point"}
}
