{
  "type": "Feature",
  "properties": {
    "addr:full": "9644 Co Rd 153 East Liberty OH 43319",
    "addr:housenumber": "9644",
    "addr:postcode": "43319",
    "addr:street": "Co Rd 153",
    "iso:country": "US",
    "sg:address": "9644 Co Rd 153",
    "sg:city": "East Liberty",
    "sg:phone": "+1 937 666 2072",
    "sg:postcode": "43319",
    "sg:province": "OH",
    "sg:tags": [
      "farm",
      "soybean"
    ],
    "wof:name": "Roger Losey",
    "wof:placetype": "venue"
  },
  "geometry": {"coordinates":[-83.59783,40.299723],"type":"Point"}
}
