{
  "type": "Feature",
  "properties": {
    "addr:full": "38240 Capel Rd Grafton OH 44044",
    "addr:postcode": "38240;44044",
    "addr:street": "Capel Rd",
    "iso:country": "US",
    "sg:address": "38240 Capel Rd",
    "sg:city": "Grafton",
    "sg:classifiers": [
      {
        "category": "Shopping",
        "subcategory": "Computers \u0026 Home Electronics",
        "type": "Retail Goods"
      }
    ],
    "sg:phone": "+1 440 748 2472",
    "sg:postcode": "44044",
    "sg:province": "OH",
    "sg:tags": [
      "supply"
    ],
    "wof:name": "William W Taylor Enterprises",
    "wof:placetype": "venue"
  },
  "geometry": {"coordinates":[-82.060263,41.30344],"type":"Point"}
}
