{
  "type": "Feature",
  "properties": {
    "iso:country":"US",
    "sg:address":"38240 Capel Rd",
    "sg:city":"Grafton",
    "sg:classifiers":[
        {
            "category":"Shopping",
            "subcategory":"Computers & Home Electronics",
            "type":"Retail Goods"
        }
    ],
    "sg:phone":"+1 440 748 2472",
    "sg:postcode":"44044",
    "sg:province":"OH",
    "sg:tags":[
        "supply"
    ],
    "wof:name":"William W Taylor Enterprises",
    "wof:placetype":"venue"
},
  "geometry": {"coordinates":[-82.06026300000001,41.30344],"type":"Point"}
}