{
  "type": "Feature",
  "properties": {
    "addr:full": "6750 Wishart St Huntsville OH 43324",
    "addr:housenumber": "6750",
    "addr:postcode": "43324",
    "addr:street": "Wishart St",
    "iso:country": "US",
    "sg:address": "6750 Wishart St",
    "sg:city": "Huntsville",
    "sg:classifiers": [
      {
        "category": "Government",
        "subcategory": "Fire Station",
        "type": "Public Place"
      }
    ],
    "sg:phone": "+1 937 599 2222",
    "sg:postcode": "43324",
    "sg:province": "OH",
    "sg:tags": [
      "department"
    ],
    "wof:name": "Huntsville Rescue Squad",
    "wof:placetype": "venue"
  },
  "geometry": {"coordinates":[-83.805231,40.443539],"type":"Point"}
}
