{
  "type": "Feature",
  "properties": {
    "addr:full":"1350 Broadway St Toledo OH 43609",
    "addr:housenumber":"1350",
    "addr:postcode":"43609",
    "addr:street":"Broadway St",
    "iso:country":"US",
    "sg:address":"1350 Broadway St",
    "sg:city":"Toledo",
    "sg:classifiers":[
        {
            "category":"Autos & Motor Vehicles",
            "subcategory":"Fuel & Gas Station",
            "type":"Retail Goods"
        }
    ],
    "sg:phone":"+1 419 241 8401",
    "sg:postcode":"43609",
    "sg:province":"OH",
    "sg:tags":[
        "grocery",
        "station",
        "gasoline"
    ],
    "wof:name":"BP",
    "wof:placetype":"venue"
},
  "geometry": {"coordinates":[-83.55429100000001,41.632376],"type":"Point"}
}