{
  "type": "Feature",
  "properties": {
    "addr:full": "10391 Hollow Rd SW Pataskala OH 43062",
    "addr:housenumber": "10391",
    "addr:postcode": "43062",
    "addr:street": "Hollow Rd Sw",
    "iso:country": "US",
    "sg:address": "10391 Hollow Rd SW",
    "sg:city": "Pataskala",
    "sg:classifiers": [
      {
        "category": "Recreation",
        "type": "Entertainment"
      }
    ],
    "sg:phone": "+1 740 927 4021",
    "sg:postcode": "43062",
    "sg:province": "OH",
    "sg:tags": [
      "course",
      "golf"
    ],
    "wof:name": "High Lands Golf Course",
    "wof:placetype": "venue"
  },
  "geometry": {"coordinates":[-82.682619,40.03875],"type":"Point"}
}
