{
  "type": "Feature",
  "properties": {
    "iso:country":"US",
    "sg:address":"10391 Hollow Rd SW",
    "sg:city":"Pataskala",
    "sg:classifiers":[
        {
            "category":"Recreation",
            "type":"Entertainment"
        }
    ],
    "sg:phone":"+1 740 927 4021",
    "sg:postcode":"43062",
    "sg:province":"OH",
    "sg:tags":[
        "course",
        "golf"
    ],
    "wof:name":"High Lands Golf Course",
    "wof:placetype":"venue"
},
  "geometry": {"coordinates":[-82.682619,40.03875],"type":"Point"}
}