{
  "type": "Feature",
  "properties": {
    "addr:full": "8531 Torwoodlee Ct Dublin OH 43017",
    "addr:housenumber": "8531",
    "addr:postcode": "43017",
    "addr:street": "Torwoodlee Ct",
    "iso:country": "US",
    "sg:address": "8531 Torwoodlee Ct",
    "sg:city": "Dublin",
    "sg:classifiers": [
      {
        "category": "Professional",
        "subcategory": "Computer Services",
        "type": "Services"
      }
    ],
    "sg:phone": "+1 614 717 9659",
    "sg:postcode": "43017",
    "sg:province": "OH",
    "sg:tags": [
      "related",
      "programing",
      "custom"
    ],
    "wof:name": "Nphase",
    "wof:placetype": "venue"
  },
  "geometry": {"coordinates":[-83.13764,40.139706],"type":"Point"}
}
