{
  "type": "Feature",
  "properties": {
    "iso:country":"US",
    "sg:address":"2265 S Green Rd",
    "sg:city":"Cleveland",
    "sg:classifiers":[
        {
            "category":"Professional",
            "subcategory":"Accounting & Tax Preparation",
            "type":"Services"
        }
    ],
    "sg:phone":"+1 216 691 9208",
    "sg:postcode":"44122",
    "sg:province":"OH",
    "wof:name":"William Mc Donald CPA",
    "wof:placetype":"venue"
},
  "geometry": {"coordinates":[-81.51694,41.497966],"type":"Point"}
}