{
  "type": "Feature",
  "properties": {
    "iso:country":"US",
    "sg:address":"4656 Cemetery Rd",
    "sg:city":"Hilliard",
    "sg:classifiers":[
        {
            "category":"Banks & Credit Unions",
            "subcategory":"Bank",
            "type":"Services"
        }
    ],
    "sg:phone":"+1 614 529 2300",
    "sg:postcode":"43026",
    "sg:province":"OH",
    "sg:tags":[
        "national"
    ],
    "wof:name":"Firstar Bank",
    "wof:placetype":"venue"
},
  "geometry": {"coordinates":[-83.137246,40.032055],"type":"Point"}
}