{
  "type": "Feature",
  "properties": {
    "iso:country":"US",
    "sg:address":"8100 Factory Shops Blvd",
    "sg:city":"Jeffersonville",
    "sg:classifiers":[
        {
            "category":"Wholesale",
            "subcategory":"Home Furnishings",
            "type":"Manufacturing & Wholesale Goods"
        }
    ],
    "sg:phone":"+1 740 948 2004",
    "sg:postcode":"43128",
    "sg:province":"OH",
    "sg:website":"www.potterybarn.com",
    "wof:name":"Pottery Barn",
    "wof:placetype":"venue"
},
  "geometry": {"coordinates":[-83.601106,39.618109],"type":"Point"}
}