{
  "type": "Feature",
  "properties": {
    "addr:full": "3539 State Rte 5 Cortland OH 44410",
    "addr:housenumber": "3539",
    "addr:postcode": "44410",
    "addr:street": "State Rte 5",
    "iso:country": "US",
    "sg:address": "3539 State Rte 5",
    "sg:city": "Cortland",
    "sg:classifiers": [
      {
        "category": "Shopping",
        "subcategory": "Tobacco",
        "type": "Retail Goods"
      }
    ],
    "sg:phone": "+1 330 638 3810",
    "sg:postcode": "44410",
    "sg:province": "OH",
    "sg:tags": [
      "cigarette",
      "cigar",
      "dealer"
    ],
    "wof:name": "R Cigars",
    "wof:placetype": "venue"
  },
  "geometry": {"coordinates":[-80.740068,41.310023],"type":"Point"}
}
