{
  "type": "Feature",
  "properties": {
    "addr:full": "1911 36th St NE Canton OH 44705",
    "addr:housenumber": "1911",
    "addr:postcode": "44705",
    "addr:street": "36Th St Ne",
    "iso:country": "US",
    "sg:address": "1911 36th St NE",
    "sg:city": "Canton",
    "sg:classifiers": [
      {
        "category": "Manufacturing",
        "subcategory": "Tools \u0026 Machinery",
        "type": "Manufacturing \u0026 Wholesale Goods"
      }
    ],
    "sg:phone": "+1 330 453 9100",
    "sg:postcode": "44705",
    "sg:province": "OH",
    "sg:tags": [
      "industry",
      "special"
    ],
    "sg:website": "www.batchoff.com",
    "wof:name": "Midlands Millroom Supply",
    "wof:placetype": "venue"
  },
  "geometry": {"coordinates":[-81.346563,40.836864],"type":"Point"}
}
