{
  "type": "Feature",
  "properties": {
    "addr:full": "5342 Meadow Lane Ct Elyria OH 44035",
    "addr:housenumber": "5342",
    "addr:postcode": "44035",
    "addr:street": "Meadow Lane Ct",
    "iso:country": "US",
    "sg:address": "5342 Meadow Lane Ct",
    "sg:city": "Elyria",
    "sg:classifiers": [
      {
        "category": "Health Services",
        "subcategory": "Doctor",
        "type": "Services"
      }
    ],
    "sg:phone": "+1 440 934 2200",
    "sg:postcode": "44035",
    "sg:province": "OH",
    "sg:tags": [
      "physician",
      "surgeon",
      "medical"
    ],
    "wof:name": "Robert S Perhala MD Facr",
    "wof:placetype": "venue"
  },
  "geometry": {"coordinates":[-82.074975,41.420927],"type":"Point"}
}
