{
  "type": "Feature",
  "properties": {
    "addr:full":"2335 Section Rd Cincinnati OH 45237",
    "addr:housenumber":"2335",
    "addr:postcode":"45237",
    "addr:street":"Section Rd",
    "iso:country":"US",
    "sg:address":"2335 Section Rd",
    "sg:city":"Cincinnati",
    "sg:classifiers":[
        {
            "category":"Shopping",
            "subcategory":"Books",
            "type":"Retail Goods"
        }
    ],
    "sg:phone":"+1 513 531 0808",
    "sg:postcode":"45237",
    "sg:province":"OH",
    "sg:tags":[
        "gift"
    ],
    "wof:name":"Yaacovs Place",
    "wof:placetype":"venue"
},
  "geometry": {"coordinates":[-84.44825,39.196689],"type":"Point"}
}