{
  "type": "Feature",
  "properties": {
    "addr:full": "11293 Royalton Rd North Royalton OH 44133",
    "addr:housenumber": "11293",
    "addr:postcode": "44133",
    "addr:street": "Royalton Rd",
    "iso:country": "US",
    "sg:address": "11293 Royalton Rd",
    "sg:city": "North Royalton",
    "sg:classifiers": [
      {
        "category": "Building \u0026 Trades",
        "subcategory": "Construction",
        "type": "Services"
      }
    ],
    "sg:phone": "+1 440 237 1978",
    "sg:postcode": "44133",
    "sg:province": "OH",
    "sg:tags": [
      "water",
      "excavation",
      "sewer",
      "contractor"
    ],
    "wof:name": "Digioia Suburban Excvtg LLC",
    "wof:placetype": "venue"
  },
  "geometry": {"coordinates":[-81.768855,41.315496],"type":"Point"}
}
