{
  "type": "Feature",
  "properties": {
    "iso:country":"US",
    "sg:address":"11293 Royalton Rd",
    "sg:city":"North Royalton",
    "sg:classifiers":[
        {
            "category":"Building & Trades",
            "subcategory":"Construction",
            "type":"Services"
        }
    ],
    "sg:phone":"+1 440 237 1978",
    "sg:postcode":"44133",
    "sg:province":"OH",
    "sg:tags":[
        "water",
        "excavation",
        "sewer",
        "contractor"
    ],
    "wof:name":"Digioia Suburban Excvtg LLC",
    "wof:placetype":"venue"
},
  "geometry": {"coordinates":[-81.768855,41.315496],"type":"Point"}
}