{
  "type": "Feature",
  "properties": {
    "addr:full": "7674 Milsboro Rd Galion OH 44833",
    "addr:housenumber": "7674",
    "addr:postcode": "44833",
    "addr:street": "Milsboro Rd",
    "iso:country": "US",
    "sg:address": "7674 Milsboro Rd",
    "sg:city": "Galion",
    "sg:classifiers": [
      {
        "category": "Airport",
        "type": "Transportation"
      }
    ],
    "sg:phone": "+1 419 468 5342",
    "sg:postcode": "44833",
    "sg:province": "OH",
    "wof:name": "Horning Air Strip and Repair",
    "wof:placetype": "venue"
  },
  "geometry": {"coordinates":[-82.738325,40.733237],"type":"Point"}
}
