{
  "type": "Feature",
  "properties": {
    "iso:country":"US",
    "sg:address":"7674 Milsboro Rd",
    "sg:city":"Galion",
    "sg:classifiers":[
        {
            "category":"Airport",
            "type":"Transportation"
        }
    ],
    "sg:phone":"+1 419 468 5342",
    "sg:postcode":"44833",
    "sg:province":"OH",
    "wof:name":"Horning Air Strip and Repair",
    "wof:placetype":"venue"
},
  "geometry": {"coordinates":[-82.738325,40.733237],"type":"Point"}
}