{
  "type": "Feature",
  "properties": {
    "iso:country":"US",
    "sg:address":"38345 Apollo Pkwy",
    "sg:city":"Willoughby",
    "sg:classifiers":[
        {
            "category":"Food & Beverages",
            "subcategory":"Meat & Fish",
            "type":"Retail Goods"
        }
    ],
    "sg:phone":"+1 440 951 6280",
    "sg:postcode":"44094",
    "sg:province":"OH",
    "sg:tags":[
        "plan"
    ],
    "wof:name":"Lauren Home Grocery Svc",
    "wof:placetype":"venue"
},
  "geometry": {"coordinates":[-81.402385,41.650495],"type":"Point"}
}