{
  "type": "Feature",
  "properties": {
    "iso:country":"US",
    "sg:address":"2181 Haviland Dr",
    "sg:city":"Columbus",
    "sg:classifiers":[
        {
            "category":"Building & Trades",
            "subcategory":"Construction",
            "type":"Services"
        }
    ],
    "sg:phone":"+1 614 444 6841",
    "sg:postcode":"43207",
    "sg:province":"OH",
    "sg:tags":[
        "handyman"
    ],
    "wof:name":"Joe Black's Handyman Svc",
    "wof:placetype":"venue"
},
  "geometry": {"coordinates":[-82.93770000000001,39.924733],"type":"Point"}
}