{
  "type": "Feature",
  "properties": {
    "addr:full": "2181 Haviland Dr Columbus OH 43207",
    "addr:housenumber": "2181",
    "addr:postcode": "43207",
    "addr:street": "Haviland Dr",
    "iso:country": "US",
    "sg:address": "2181 Haviland Dr",
    "sg:city": "Columbus",
    "sg:classifiers": [
      {
        "category": "Building \u0026 Trades",
        "subcategory": "Construction",
        "type": "Services"
      }
    ],
    "sg:phone": "+1 614 444 6841",
    "sg:postcode": "43207",
    "sg:province": "OH",
    "sg:tags": [
      "handyman"
    ],
    "wof:name": "Joe Black's Handyman Svc",
    "wof:placetype": "venue"
  },
  "geometry": {"coordinates":[-82.9377,39.924733],"type":"Point"}
}
