{
  "type": "Feature",
  "properties": {
    "addr:full":"5158 Honora Dr Sylvania OH 43560",
    "addr:housenumber":"5158",
    "addr:postcode":"43560",
    "addr:street":"Honora Dr",
    "iso:country":"US",
    "sg:address":"5158 Honora Dr",
    "sg:city":"Sylvania",
    "sg:classifiers":[
        {
            "category":"Shopping",
            "subcategory":"Musical Instruments",
            "type":"Retail Goods"
        }
    ],
    "sg:phone":"+1 419 824 8491",
    "sg:postcode":"43560",
    "sg:province":"OH",
    "sg:tags":[
        "piano"
    ],
    "wof:name":"Chris Zagoric Piano Tuning",
    "wof:placetype":"venue"
},
  "geometry": {"coordinates":[-83.720067,41.706188],"type":"Point"}
}