{
  "type": "Feature",
  "properties": {
    "addr:full":"567 W Staunton Rd Troy OH 45373",
    "addr:housenumber":"567",
    "addr:postcode":"45373",
    "addr:street":"W Staunton Rd",
    "iso:country":"US",
    "sg:address":"567 W Staunton Rd",
    "sg:city":"Troy",
    "sg:classifiers":[
        {
            "category":"Restaurant",
            "type":"Food & Drink"
        }
    ],
    "sg:phone":"+1 937 335 8077",
    "sg:postcode":"45373",
    "sg:province":"OH",
    "sg:tags":[
        "catering"
    ],
    "wof:name":"Arnolds Canteen Inc",
    "wof:placetype":"venue"
},
  "geometry": {"coordinates":[-84.202613,40.045428],"type":"Point"}
}