{
  "type": "Feature",
  "properties": {
    "addr:full":"5430 Mechanicsburg Rd Wooster OH 44691",
    "addr:postcode":"5430;44691",
    "addr:street":"Mechanicsburg Rd",
    "iso:country":"US",
    "sg:address":"5430 Mechanicsburg Rd",
    "sg:city":"Wooster",
    "sg:classifiers":[
        {
            "category":"Professional",
            "type":"Services"
        }
    ],
    "sg:phone":"+1 330 345 4774",
    "sg:postcode":"44691",
    "sg:province":"OH",
    "wof:name":"Sunset View LLC",
    "wof:placetype":"venue"
},
  "geometry": {"coordinates":[-81.995215,40.865025],"type":"Point"}
}