{
  "type": "Feature",
  "properties": {
    "iso:country":"US",
    "sg:address":"1992 Springfield Lake Blvd",
    "sg:city":"Akron",
    "sg:classifiers":[
        {
            "category":"Building & Trades",
            "subcategory":"Plumbing",
            "type":"Services"
        }
    ],
    "sg:phone":"+1 330 733 5496",
    "sg:postcode":"44312",
    "sg:province":"OH",
    "sg:tags":[
        "conditioning",
        "air",
        "system",
        "contractor"
    ],
    "wof:name":"Bud's Heating & Cooling",
    "wof:placetype":"venue"
},
  "geometry": {"coordinates":[-81.461333,41.031184],"type":"Point"}
}