{
  "type": "Feature",
  "properties": {
    "addr:full": "199 Milliken Dr Hebron OH 43025",
    "addr:housenumber": "199",
    "addr:postcode": "43025",
    "addr:street": "Milliken Dr",
    "iso:country": "US",
    "sg:address": "199 Milliken Dr",
    "sg:city": "Hebron",
    "sg:classifiers": [
      {
        "category": "Wholesale",
        "subcategory": "Chemicals \u0026 Plastics",
        "type": "Manufacturing \u0026 Wholesale Goods"
      }
    ],
    "sg:phone": "+1 740 928 3000",
    "sg:postcode": "43025",
    "sg:province": "OH",
    "wof:name": "Brenntag Mid-South Inc",
    "wof:placetype": "venue"
  },
  "geometry": {"coordinates":[-82.482343,39.981736],"type":"Point"}
}
