{
  "type": "Feature",
  "properties": {
    "addr:full": "6893 Chaffee Ct Cleveland OH 44141",
    "addr:housenumber": "6893",
    "addr:postcode": "44141",
    "addr:street": "Chaffee Ct",
    "iso:country": "US",
    "sg:address": "6893 Chaffee Ct",
    "sg:city": "Cleveland",
    "sg:classifiers": [
      {
        "category": "Professional",
        "type": "Services"
      }
    ],
    "sg:phone": "+1 216 403 2734",
    "sg:postcode": "44141",
    "sg:province": "OH",
    "sg:tags": [
      "arts",
      "artist"
    ],
    "wof:name": "Portraits In Oil \u0026 Pastel",
    "wof:placetype": "venue"
  },
  "geometry": {"coordinates":[-81.631921,41.318687],"type":"Point"}
}
