{
  "type": "Feature",
  "properties": {
    "addr:full":"4427 Talmadge Rd Toledo OH 43623",
    "addr:housenumber":"4427",
    "addr:postcode":"43623",
    "addr:street":"Talmadge Rd",
    "iso:country":"US",
    "sg:address":"4427 Talmadge Rd",
    "sg:city":"Toledo",
    "sg:classifiers":[
        {
            "category":"Insurance",
            "subcategory":"Insurance Agent",
            "type":"Services"
        }
    ],
    "sg:phone":"+1 419 472 7820",
    "sg:postcode":"43623",
    "sg:province":"OH",
    "sg:tags":[
        "advisory",
        "investment"
    ],
    "wof:name":"Le Strange & Sons",
    "wof:placetype":"venue"
},
  "geometry": {"coordinates":[-83.644874,41.695377],"type":"Point"}
}