{
  "type": "Feature",
  "properties": {
    "addr:full":"2445 S Arlington Rd Akron OH 44319",
    "addr:housenumber":"2445",
    "addr:postcode":"44319",
    "addr:street":"S Arlington Rd",
    "iso:country":"US",
    "sg:address":"2445 S Arlington Rd",
    "sg:city":"Akron",
    "sg:classifiers":[
        {
            "category":"Organizations",
            "subcategory":"Religious Organization",
            "type":"Services"
        }
    ],
    "sg:phone":"+1 330 644 8724",
    "sg:postcode":"44319",
    "sg:province":"OH",
    "sg:tags":[
        "church"
    ],
    "sg:website":"www.christcommunitychurchakron.org",
    "wof:name":"Christ Community Church",
    "wof:placetype":"venue"
},
  "geometry": {"coordinates":[-81.49200999999999,41.005932],"type":"Point"}
}