{
  "type": "Feature",
  "properties": {
    "addr:full":"5405 Dixie Hwy Fairfield OH 45014",
    "addr:housenumber":"5405",
    "addr:postcode":"45014",
    "addr:street":"Dixie Hwy",
    "iso:country":"US",
    "sg:address":"5405 Dixie Hwy",
    "sg:city":"Fairfield",
    "sg:classifiers":[
        {
            "category":"Wholesale",
            "subcategory":"Sporting Goods",
            "type":"Manufacturing & Wholesale Goods"
        }
    ],
    "sg:phone":"+1 513 829 8060",
    "sg:postcode":"45014",
    "sg:province":"OH",
    "sg:tags":[
        "equipment",
        "lane",
        "bowling",
        "supply"
    ],
    "wof:name":"Tri State Bowling Supply Co",
    "wof:placetype":"venue"
},
  "geometry": {"coordinates":[-84.523946,39.333729],"type":"Point"}
}