{
  "type": "Feature",
  "properties": {
    "addr:full":"3518 South Ave Youngstown OH 44502",
    "addr:housenumber":"3518",
    "addr:postcode":"44502",
    "addr:street":"South Ave",
    "iso:country":"US",
    "sg:address":"3518 South Ave",
    "sg:city":"Youngstown",
    "sg:classifiers":[
        {
            "category":"Food & Beverages",
            "subcategory":"Groceries & Convenience Stores",
            "type":"Retail Goods"
        }
    ],
    "sg:phone":"+1 330 782 1424",
    "sg:postcode":"44502",
    "sg:province":"OH",
    "wof:name":"Daily Mart",
    "wof:placetype":"venue"
},
  "geometry": {"coordinates":[-80.646201,41.064042],"type":"Point"}
}