{
  "type": "Feature",
  "properties": {
    "iso:country":"US",
    "sg:address":"2026 Murray Hill Rd",
    "sg:city":"Cleveland",
    "sg:classifiers":[
        {
            "category":"Shopping",
            "type":"Retail Goods"
        }
    ],
    "sg:phone":"+1 216 229 2669",
    "sg:postcode":"44106",
    "sg:province":"OH",
    "sg:tags":[
        "picture",
        "frame",
        "merchandise"
    ],
    "wof:name":"Joe Arko Picture Framing Co",
    "wof:placetype":"venue"
},
  "geometry": {"coordinates":[-81.597986,41.508536],"type":"Point"}
}