{
  "type": "Feature",
  "properties": {
    "iso:country":"US",
    "sg:address":"6114 Miller Ln",
    "sg:city":"Dayton",
    "sg:classifiers":[
        {
            "category":"Building & Trades",
            "subcategory":"Construction",
            "type":"Services"
        }
    ],
    "sg:phone":"+1 937 898 4229",
    "sg:postcode":"45414",
    "sg:province":"OH",
    "sg:tags":[
        "contractor"
    ],
    "wof:name":"J & S Seamless Gutters",
    "wof:placetype":"venue"
},
  "geometry": {"coordinates":[-84.19210699999999,39.841465],"type":"Point"}
}