{
  "type": "Feature",
  "properties": {
    "addr:full": "6114 Miller Ln Dayton OH 45414",
    "addr:housenumber": "6114",
    "addr:postcode": "45414",
    "addr:street": "Miller Ln",
    "iso:country": "US",
    "sg:address": "6114 Miller Ln",
    "sg:city": "Dayton",
    "sg:classifiers": [
      {
        "category": "Building \u0026 Trades",
        "subcategory": "Construction",
        "type": "Services"
      }
    ],
    "sg:phone": "+1 937 898 4229",
    "sg:postcode": "45414",
    "sg:province": "OH",
    "sg:tags": [
      "contractor"
    ],
    "wof:name": "J \u0026 S Seamless Gutters",
    "wof:placetype": "venue"
  },
  "geometry": {"coordinates":[-84.192107,39.841465],"type":"Point"}
}
