{
  "type": "Feature",
  "properties": {
    "iso:country":"US",
    "sg:address":"535 Chestnut St",
    "sg:city":"Coshocton",
    "sg:classifiers":[
        {
            "category":"Health Services",
            "subcategory":"Optometrist",
            "type":"Services"
        }
    ],
    "sg:phone":"+1 740 622 2270",
    "sg:postcode":"43812",
    "sg:province":"OH",
    "wof:name":"David A Erwin & Assoc Inc",
    "wof:placetype":"venue"
},
  "geometry": {"coordinates":[-81.86295,40.274854],"type":"Point"}
}