{
  "type": "Feature",
  "properties": {
    "addr:full": "37414 State Rte 7 Sardis OH 43946",
    "addr:housenumber": "37414",
    "addr:postcode": "43946",
    "addr:street": "State Rte 7",
    "iso:country": "US",
    "sg:address": "37414 State Rte 7",
    "sg:city": "Sardis",
    "sg:classifiers": [
      {
        "category": "Utilities",
        "subcategory": "Water",
        "type": "Services"
      }
    ],
    "sg:phone": "+1 740 483 1542",
    "sg:postcode": "43946",
    "sg:province": "OH",
    "sg:tags": [
      "company",
      "sewage"
    ],
    "wof:name": "Ohio \u0026 Lee Water \u0026 Sewer",
    "wof:placetype": "venue"
  },
  "geometry": {"coordinates":[-80.905043,39.622659],"type":"Point"}
}
