{
  "type": "Feature",
  "properties": {
    "iso:country":"US",
    "sg:address":"37414 State Rte 7",
    "sg:city":"Sardis",
    "sg:classifiers":[
        {
            "category":"Utilities",
            "subcategory":"Water",
            "type":"Services"
        }
    ],
    "sg:phone":"+1 740 483 1542",
    "sg:postcode":"43946",
    "sg:province":"OH",
    "sg:tags":[
        "company",
        "sewage"
    ],
    "wof:name":"Ohio & Lee Water & Sewer",
    "wof:placetype":"venue"
},
  "geometry": {"coordinates":[-80.905043,39.622659],"type":"Point"}
}