{
  "type": "Feature",
  "properties": {
    "iso:country":"US",
    "sg:address":"603 Cumberland St",
    "sg:city":"Caldwell",
    "sg:classifiers":[
        {
            "category":"Wholesale",
            "subcategory":"Farm Supplies",
            "type":"Manufacturing & Wholesale Goods"
        }
    ],
    "sg:phone":"+1 740 732 4135",
    "sg:postcode":"43724",
    "sg:province":"OH",
    "sg:tags":[
        "feed"
    ],
    "wof:name":"Jones Feed and Supply",
    "wof:placetype":"venue"
},
  "geometry": {"coordinates":[-81.515629,39.74944],"type":"Point"}
}