{
  "type": "Feature",
  "properties": {
    "iso:country":"US",
    "sg:address":"114 N West St",
    "sg:city":"Lima",
    "sg:classifiers":[
        {
            "category":"Professional",
            "subcategory":"Detective & Security Services",
            "type":"Services"
        }
    ],
    "sg:phone":"+1 419 229 2872",
    "sg:postcode":"45801",
    "sg:province":"OH",
    "sg:tags":[
        "polygraph"
    ],
    "wof:name":"International Association",
    "wof:placetype":"venue"
},
  "geometry": {"coordinates":[-84.107708,40.741161],"type":"Point"}
}