{
  "type": "Feature",
  "properties": {
    "iso:country":"US",
    "sg:address":"2030 Higby Dr",
    "sg:city":"Stow",
    "sg:classifiers":[
        {
            "category":"Shopping",
            "subcategory":"Computers & Home Electronics",
            "type":"Retail Goods"
        }
    ],
    "sg:phone":"+1 330 688 1380",
    "sg:postcode":"44224",
    "sg:province":"OH",
    "sg:tags":[
        "software"
    ],
    "wof:name":"Synergy Solutions",
    "wof:placetype":"venue"
},
  "geometry": {"coordinates":[-81.43280900000001,41.191885],"type":"Point"}
}