{
  "type": "Feature",
  "properties": {
    "iso:country":"US",
    "sg:address":"23102 Morse Rd",
    "sg:city":"Raymond",
    "sg:classifiers":[
        {
            "category":"Organizations",
            "subcategory":"Community Association",
            "type":"Services"
        }
    ],
    "sg:phone":"+1 937 358 2473",
    "sg:postcode":"43067",
    "sg:province":"OH",
    "sg:tags":[
        "club"
    ],
    "wof:name":"Union County Draft Assn",
    "wof:placetype":"venue"
},
  "geometry": {"coordinates":[-83.495982,40.372348],"type":"Point"}
}