{
  "type": "Feature",
  "properties": {
    "addr:full": "9850 Princeton Glendale Rd Cincinnati OH 45246",
    "addr:housenumber": "9850",
    "addr:postcode": "45246",
    "addr:street": "Princeton Glendale Rd",
    "iso:country": "US",
    "sg:address": "9850 Princeton Glendale Rd",
    "sg:city": "Cincinnati",
    "sg:classifiers": [
      {
        "category": "Manufacturing",
        "subcategory": "Lumber",
        "type": "Manufacturing \u0026 Wholesale Goods"
      }
    ],
    "sg:phone": "+1 513 874 1177",
    "sg:postcode": "45246",
    "sg:province": "OH",
    "sg:tags": [
      "mfg",
      "hardwood",
      "cabinet",
      "wood",
      "mill",
      "kitchen"
    ],
    "wof:name": "Armstrong",
    "wof:placetype": "venue"
  },
  "geometry": {"coordinates":[-84.464744,39.310975],"type":"Point"}
}
