{
  "type": "Feature",
  "properties": {
    "addr:full": "9663 Swigert Rd Loveland OH 45140",
    "addr:housenumber": "9663",
    "addr:postcode": "45140",
    "addr:street": "Swigert Rd",
    "iso:country": "US",
    "sg:address": "9663 Swigert Rd",
    "sg:city": "Loveland",
    "sg:classifiers": [
      {
        "category": "Building \u0026 Trades",
        "subcategory": "Landscaping Services",
        "type": "Services"
      }
    ],
    "sg:phone": "+1 513 899 9933",
    "sg:postcode": "45140",
    "sg:province": "OH",
    "sg:tags": [
      "landscape",
      "contractor"
    ],
    "wof:name": "A Cut Above Lawncare \u0026 Lndscpg",
    "wof:placetype": "venue"
  },
  "geometry": {"coordinates":[-84.165153,39.291888],"type":"Point"}
}
