{
  "type": "Feature",
  "properties": {
    "iso:country":"US",
    "sg:address":"639 Broad Blvd",
    "sg:city":"Cuyahoga Falls",
    "sg:classifiers":[
        {
            "category":"Building & Trades",
            "subcategory":"Construction",
            "type":"Services"
        }
    ],
    "sg:phone":"+1 330 929 3112",
    "sg:postcode":"44221",
    "sg:province":"OH",
    "sg:tags":[
        "house"
    ],
    "wof:name":"Renovation",
    "wof:placetype":"venue"
},
  "geometry": {"coordinates":[-81.491345,41.13447],"type":"Point"}
}