{
  "type": "Feature",
  "properties": {
    "addr:full":"3110 Bardshar Rd Sandusky OH 44870",
    "addr:housenumber":"3110",
    "addr:postcode":"44870",
    "addr:street":"Bardshar Rd",
    "iso:country":"US",
    "sg:address":"3110 Bardshar Rd",
    "sg:city":"Sandusky",
    "sg:classifiers":[
        {
            "category":"Wholesale",
            "subcategory":"Stationery",
            "type":"Manufacturing & Wholesale Goods"
        }
    ],
    "sg:phone":"+1 419 625 5558",
    "sg:postcode":"44870",
    "sg:province":"OH",
    "sg:tags":[
        "cards",
        "greeting"
    ],
    "wof:name":"Guess Who Greetings",
    "wof:placetype":"venue"
},
  "geometry": {"coordinates":[-82.771283,41.406117],"type":"Point"}
}