{
  "type": "Feature",
  "properties": {
    "addr:full":"270 E State St Columbus OH 43215",
    "addr:housenumber":"270",
    "addr:postcode":"43215",
    "addr:street":"E State St",
    "iso:country":"US",
    "sg:address":"270 E State St",
    "sg:city":"Columbus",
    "sg:classifiers":[
        {
            "category":"Education",
            "subcategory":"School",
            "type":"Public Place"
        }
    ],
    "sg:phone":"+1 614 365 6420",
    "sg:postcode":"43215",
    "sg:province":"OH",
    "wof:name":"Columbus City Schools",
    "wof:placetype":"venue"
},
  "geometry": {"coordinates":[-82.993109,39.961014],"type":"Point"}
}