{
  "type": "Feature",
  "properties": {
    "iso:country":"US",
    "sg:address":"792 E McMillan St",
    "sg:city":"Cincinnati",
    "sg:classifiers":[
        {
            "category":"Professional",
            "subcategory":"Business Services",
            "type":"Services"
        }
    ],
    "sg:phone":"+1 513 556 5655",
    "sg:postcode":"45206",
    "sg:province":"OH",
    "sg:tags":[
        "central"
    ],
    "wof:name":"Central Recieving",
    "wof:placetype":"venue"
},
  "geometry": {"coordinates":[-84.491664,39.126011],"type":"Point"}
}