{
  "type": "Feature",
  "properties": {
    "addr:full":"8311 Stratford Dr Cleveland OH 44129",
    "addr:housenumber":"8311",
    "addr:postcode":"44129",
    "addr:street":"Stratford Dr",
    "iso:country":"US",
    "sg:address":"8311 Stratford Dr",
    "sg:city":"Cleveland",
    "sg:classifiers":[
        {
            "category":"Professional",
            "subcategory":"Computer Services",
            "type":"Services"
        }
    ],
    "sg:phone":"+1 216 695 8042",
    "sg:postcode":"44129",
    "sg:province":"OH",
    "sg:tags":[
        "internet"
    ],
    "wof:name":"Buysell On The Net Inc",
    "wof:placetype":"venue"
},
  "geometry": {"coordinates":[-81.74263000000001,41.3854],"type":"Point"}
}