{
  "type": "Feature",
  "properties": {
    "iso:country":"US",
    "sg:address":"1810 E 12th St",
    "sg:city":"Cleveland",
    "sg:classifiers":[
        {
            "category":"Restaurant",
            "type":"Food & Drink"
        }
    ],
    "sg:phone":"+1 216 696 4256",
    "sg:postcode":"44114",
    "sg:province":"OH",
    "sg:tags":[
        "drinking",
        "eating"
    ],
    "wof:name":"New Yorker Restaurant & Deli",
    "wof:placetype":"venue"
},
  "geometry": {"coordinates":[-81.684911,41.501797],"type":"Point"}
}