{
  "type": "Feature",
  "properties": {
    "iso:country":"US",
    "sg:address":"2518 S Reynolds Rd",
    "sg:city":"Toledo",
    "sg:classifiers":[
        {
            "category":"Bars & Pubs",
            "type":"Food & Drink"
        }
    ],
    "sg:phone":"+1 419 867 7006",
    "sg:postcode":"43614",
    "sg:province":"OH",
    "sg:tags":[
        "club",
        "night"
    ],
    "wof:name":"Kipp's",
    "wof:placetype":"venue"
},
  "geometry": {"coordinates":[-83.664756,41.594177],"type":"Point"}
}