{
  "type": "Feature",
  "properties": {
    "iso:country":"US",
    "sg:address":"6923 New Delaware Rd",
    "sg:city":"Mount Vernon",
    "sg:classifiers":[
        {
            "category":"Restaurant",
            "type":"Food & Drink"
        }
    ],
    "sg:phone":"+1 740 397 3833",
    "sg:postcode":"43050",
    "sg:province":"OH",
    "sg:tags":[
        "eating"
    ],
    "wof:name":"Barbs Diner",
    "wof:placetype":"venue"
},
  "geometry": {"coordinates":[-82.626713,40.374881],"type":"Point"}
}