{
  "type": "Feature",
  "properties": {
    "iso:country":"US",
    "sg:address":"661 Mahoning Ave NW",
    "sg:city":"Warren",
    "sg:classifiers":[
        {
            "category":"Social Services",
            "type":"Services"
        }
    ],
    "sg:phone":"+1 330 392 2551",
    "sg:postcode":"44483",
    "sg:province":"OH",
    "sg:tags":[
        "organization",
        "welfare"
    ],
    "sg:website":"www.trumbull-redcross.org",
    "wof:name":"American Red Cross",
    "wof:placetype":"venue"
},
  "geometry": {"coordinates":[-80.824482,41.241004],"type":"Point"}
}