{
  "type": "Feature",
  "properties": {
    "addr:full":"6643 Quail Lake Mason OH 45040",
    "addr:housenumber":"6643",
    "addr:postcode":"45040",
    "addr:street":"Quail Lake",
    "iso:country":"US",
    "sg:address":"6643 Quail Lake",
    "sg:city":"Mason",
    "sg:classifiers":[
        {
            "category":"Real Estate",
            "subcategory":"Real Estate Operator",
            "type":"Services"
        }
    ],
    "sg:phone":"+1 513 573 9633",
    "sg:postcode":"45040",
    "sg:province":"OH",
    "sg:tags":[
        "condominium"
    ],
    "wof:name":"Villa's Of Hunters Green LTD",
    "wof:placetype":"venue"
},
  "geometry": {"coordinates":[-84.343638,39.328086],"type":"Point"}
}