{
  "type": "Feature",
  "properties": {
    "iso:country":"US",
    "sg:address":"3120 S Verity Pkwy",
    "sg:city":"Middletown",
    "sg:classifiers":[
        {
            "category":"Freight",
            "type":"Transportation"
        }
    ],
    "sg:phone":"+1 513 705 1460",
    "sg:postcode":"45044",
    "sg:province":"OH",
    "wof:name":"R S Transportation Svc",
    "wof:placetype":"venue"
},
  "geometry": {"coordinates":[-84.415229,39.484282],"type":"Point"}
}