{
  "type": "Feature",
  "properties": {
    "addr:full":"8916 Saint Clair Ave Cleveland OH 44108",
    "addr:housenumber":"8916",
    "addr:postcode":"44108",
    "addr:street":"Saint Clair Ave",
    "iso:country":"US",
    "sg:address":"8916 Saint Clair Ave",
    "sg:city":"Cleveland",
    "sg:classifiers":[
        {
            "category":"Autos & Motor Vehicles",
            "subcategory":"Automobile Sales",
            "type":"Retail Goods"
        }
    ],
    "sg:phone":"+1 216 761 0441",
    "sg:postcode":"44108",
    "sg:province":"OH",
    "sg:tags":[
        "dealers-used",
        "car",
        "used",
        "cars-wholesale"
    ],
    "wof:name":"JO Motors Inc",
    "wof:placetype":"venue"
},
  "geometry": {"coordinates":[-81.62593,41.534046],"type":"Point"}
}