{
  "type": "Feature",
  "properties": {
    "iso:country":"US",
    "sg:address":"3322 Anderson Ave NE",
    "sg:city":"Minerva",
    "sg:classifiers":[
        {
            "category":"Professional",
            "type":"Services"
        }
    ],
    "sg:phone":"+1 330 862 4805",
    "sg:postcode":"44657",
    "sg:province":"OH",
    "wof:name":"Kenneth M Hardesty",
    "wof:placetype":"venue"
},
  "geometry": {"coordinates":[-81.115424,40.817739],"type":"Point"}
}