{
  "type": "Feature",
  "properties": {
    "addr:full":"123 E Main St Troy OH 45373",
    "addr:housenumber":"123",
    "addr:postcode":"45373",
    "addr:street":"E Main St",
    "iso:country":"US",
    "sg:address":"123 E Main St",
    "sg:city":"Troy",
    "sg:classifiers":[
        {
            "category":"Banks & Credit Unions",
            "subcategory":"Bank",
            "type":"Services"
        }
    ],
    "sg:phone":"+1 937 332 1699",
    "sg:postcode":"45373",
    "sg:province":"OH",
    "sg:tags":[
        "loan",
        "real estate"
    ],
    "wof:name":"Renaissance National Mtg Inc",
    "wof:placetype":"venue"
},
  "geometry": {"coordinates":[-84.201505,40.038938],"type":"Point"}
}