{
  "type": "Feature",
  "properties": {
    "addr:full": "6233 Riverside Dr Dublin OH 43017",
    "addr:housenumber": "6233",
    "addr:postcode": "43017",
    "addr:street": "Riverside Dr",
    "iso:country": "US",
    "sg:address": "6233 Riverside Dr",
    "sg:city": "Dublin",
    "sg:classifiers": [
      {
        "category": "Banks \u0026 Credit Unions",
        "subcategory": "Investment Brokerage",
        "type": "Services"
      }
    ],
    "sg:phone": "+1 614 760 0720",
    "sg:postcode": "43017",
    "sg:province": "OH",
    "sg:tags": [
      "consultant",
      "planning",
      "financial"
    ],
    "wof:name": "Raymond James Financial Svc",
    "wof:placetype": "venue"
  },
  "geometry": {"coordinates":[-83.10844,40.092484],"type":"Point"}
}
