{
  "type": "Feature",
  "properties": {
    "addr:full":"3718 Northwest Rd Castalia OH 44824",
    "addr:housenumber":"3718",
    "addr:postcode":"44824",
    "addr:street":"Northwest Rd",
    "iso:country":"US",
    "sg:address":"3718 Northwest Rd",
    "sg:city":"Castalia",
    "sg:classifiers":[
        {
            "category":"Building & Trades",
            "subcategory":"Construction",
            "type":"Services"
        }
    ],
    "sg:phone":"+1 419 684 9844",
    "sg:postcode":"44824",
    "sg:province":"OH",
    "sg:tags":[
        "contractor"
    ],
    "wof:name":"Mainly Masonry/Land Build",
    "wof:placetype":"venue"
},
  "geometry": {"coordinates":[-82.84558199999999,41.386644],"type":"Point"}
}