{
  "type": "Feature",
  "properties": {
    "addr:full": "5846 Mayfield Rd Cleveland OH 44124",
    "addr:housenumber": "5846",
    "addr:postcode": "44124",
    "addr:street": "Mayfield Rd",
    "iso:country": "US",
    "sg:address": "5846 Mayfield Rd",
    "sg:city": "Cleveland",
    "sg:classifiers": [
      {
        "category": "Insurance",
        "subcategory": "Insurance Agent",
        "type": "Services"
      }
    ],
    "sg:phone": "+1 440 461 7914",
    "sg:postcode": "44124",
    "sg:province": "OH",
    "wof:name": "J V Rensel \u0026 Sons Insurance",
    "wof:placetype": "venue"
  },
  "geometry": {"coordinates":[-81.468563,41.519967],"type":"Point"}
}
