{
  "type": "Feature",
  "properties": {
    "addr:full":"15040 State Rte 31 Kenton OH 43326",
    "addr:housenumber":"15040",
    "addr:postcode":"43326",
    "addr:street":"State Rte 31",
    "iso:country":"US",
    "sg:address":"15040 State Rte 31",
    "sg:city":"Kenton",
    "sg:classifiers":[
        {
            "category":"Farming",
            "subcategory":"Farm",
            "type":"Manufacturing & Wholesale Goods"
        }
    ],
    "sg:phone":"+1 419 673 8205",
    "sg:postcode":"43326",
    "sg:province":"OH",
    "wof:name":"Mc Cullough Farms",
    "wof:placetype":"venue"
},
  "geometry": {"coordinates":[-83.57841500000001,40.604692],"type":"Point"}
}