{
  "type": "Feature",
  "properties": {
    "addr:full":"2250 Tiffin Ave Findlay OH 45840",
    "addr:housenumber":"2250",
    "addr:postcode":"45840",
    "addr:street":"Tiffin Ave",
    "iso:country":"US",
    "sg:address":"2250 Tiffin Ave",
    "sg:city":"Findlay",
    "sg:classifiers":[
        {
            "category":"Shopping",
            "subcategory":"Computers & Home Electronics",
            "type":"Retail Goods"
        }
    ],
    "sg:phone":"+1 419 425 1634",
    "sg:postcode":"45840",
    "sg:province":"OH",
    "sg:tags":[
        "equipment",
        "electronic",
        "supply"
    ],
    "wof:name":"Rex TV & Appliances",
    "wof:placetype":"venue"
},
  "geometry": {"coordinates":[-83.60172,41.054719],"type":"Point"}
}