{
  "type": "Feature",
  "properties": {
    "addr:full": "444 Independence Dr Medina OH 44256",
    "addr:housenumber": "444",
    "addr:postcode": "44256",
    "addr:street": "Independence Dr",
    "iso:country": "US",
    "sg:address": "444 Independence Dr",
    "sg:city": "Medina",
    "sg:classifiers": [
      {
        "category": "Home \u0026 Garden",
        "subcategory": "Hardware",
        "type": "Retail Goods"
      },
      {
        "category": "Wholesale",
        "subcategory": "Hardware",
        "type": "Manufacturing \u0026 Wholesale Goods"
      }
    ],
    "sg:phone": "+1 330 722 4242",
    "sg:postcode": "44256",
    "sg:province": "OH",
    "wof:name": "Hardware Wholesalers Inc",
    "wof:placetype": "venue"
  },
  "geometry": {"coordinates":[-81.888629,41.130339],"type":"Point"}
}
