{
  "type": "Feature",
  "properties": {
    "iso:country":"US",
    "sg:address":"444 Independence Dr",
    "sg:city":"Medina",
    "sg:classifiers":[
        {
            "category":"Home & Garden",
            "subcategory":"Hardware",
            "type":"Retail Goods"
        },
        {
            "category":"Wholesale",
            "subcategory":"Hardware",
            "type":"Manufacturing & Wholesale Goods"
        }
    ],
    "sg:phone":"+1 330 722 4242",
    "sg:postcode":"44256",
    "sg:province":"OH",
    "wof:name":"Hardware Wholesalers Inc",
    "wof:placetype":"venue"
},
  "geometry": {"coordinates":[-81.888629,41.130339],"type":"Point"}
}