{
  "type": "Feature",
  "properties": {
    "addr:full":"351 Center St Ashtabula OH 44004",
    "addr:housenumber":"351",
    "addr:postcode":"44004",
    "addr:street":"Center St",
    "iso:country":"US",
    "sg:address":"351 Center St",
    "sg:city":"Ashtabula",
    "sg:classifiers":[
        {
            "category":"Organizations",
            "subcategory":"Labor Organization",
            "type":"Services"
        }
    ],
    "sg:phone":"+1 440 993 4101",
    "sg:postcode":"44004",
    "sg:province":"OH",
    "wof:name":"UAW Local",
    "wof:placetype":"venue"
},
  "geometry": {"coordinates":[-80.785229,41.864946],"type":"Point"}
}