{
  "type": "Feature",
  "properties": {
    "addr:full": "161 W Dublin Granville Rd Columbus OH 43085",
    "addr:housenumber": "161",
    "addr:postcode": "43085",
    "addr:street": "W Dublin Granville Rd",
    "iso:country": "US",
    "sg:address": "161 W Dublin Granville Rd",
    "sg:city": "Columbus",
    "sg:classifiers": [
      {
        "category": "Wholesale",
        "subcategory": "Auto Parts",
        "type": "Manufacturing \u0026 Wholesale Goods"
      }
    ],
    "sg:phone": "+1 614 457 0450",
    "sg:postcode": "43085",
    "sg:province": "OH",
    "wof:name": "NAPA Auto Parts",
    "wof:placetype": "venue"
  },
  "geometry": {"coordinates":[-83.02625,40.089058],"type":"Point"}
}
