{
  "type": "Feature",
  "properties": {
    "iso:country":"US",
    "sg:address":"161 W Dublin Granville Rd",
    "sg:city":"Columbus",
    "sg:classifiers":[
        {
            "category":"Wholesale",
            "subcategory":"Auto Parts",
            "type":"Manufacturing & Wholesale Goods"
        }
    ],
    "sg:phone":"+1 614 457 0450",
    "sg:postcode":"43085",
    "sg:province":"OH",
    "wof:name":"NAPA Auto Parts",
    "wof:placetype":"venue"
},
  "geometry": {"coordinates":[-83.02625,40.089058],"type":"Point"}
}