{
  "type": "Feature",
  "properties": {
    "addr:full": "4467 Monticello Blvd Cleveland OH 44143",
    "addr:housenumber": "4467",
    "addr:postcode": "44143",
    "addr:street": "Monticello Blvd",
    "iso:country": "US",
    "sg:address": "4467 Monticello Blvd",
    "sg:city": "Cleveland",
    "sg:classifiers": [
      {
        "category": "Building \u0026 Trades",
        "subcategory": "Landscaping Services",
        "type": "Services"
      }
    ],
    "sg:phone": "+1 216 382 5427",
    "sg:postcode": "44143",
    "sg:province": "OH",
    "sg:tags": [
      "contractor"
    ],
    "wof:name": "Gehlfuss Landscaping",
    "wof:placetype": "venue"
  },
  "geometry": {"coordinates":[-81.515326,41.539437],"type":"Point"}
}
