{
  "type": "Feature",
  "properties": {
    "iso:country":"US",
    "sg:address":"8102 Cedar Ave",
    "sg:city":"Cleveland",
    "sg:classifiers":[
        {
            "category":"Social Services",
            "type":"Services"
        }
    ],
    "sg:phone":"+1 216 431 4920",
    "sg:postcode":"44103",
    "sg:province":"OH",
    "sg:tags":[
        "organization",
        "welfare"
    ],
    "wof:name":"Mates In Minstry-Joshua House",
    "wof:placetype":"venue"
},
  "geometry": {"coordinates":[-81.630835,41.499944],"type":"Point"}
}