{
  "type": "Feature",
  "properties": {
    "addr:full":"1251 Bryden Rd Columbus OH 43205",
    "addr:housenumber":"1251",
    "addr:postcode":"43205",
    "addr:street":"Bryden Rd",
    "iso:country":"US",
    "sg:address":"1251 Bryden Rd",
    "sg:city":"Columbus",
    "sg:classifiers":[
        {
            "category":"Social Services",
            "type":"Services"
        }
    ],
    "sg:phone":"+1 614 252 3157",
    "sg:postcode":"43205",
    "sg:province":"OH",
    "sg:tags":[
        "organization",
        "welfare"
    ],
    "sg:website":"www.cchouse.org",
    "wof:name":"Central Community House",
    "wof:placetype":"venue"
},
  "geometry": {"coordinates":[-82.965723,39.960319],"type":"Point"}
}