{
  "type": "Feature",
  "properties": {
    "addr:full": "4389 Mount Carmel Tobasco Rd Cincinnati OH 45244",
    "addr:housenumber": "4389",
    "addr:postcode": "45244",
    "addr:street": "Mount Carmel Tobasco Rd",
    "iso:country": "US",
    "sg:address": "4389 Mount Carmel Tobasco Rd",
    "sg:city": "Cincinnati",
    "sg:classifiers": [
      {
        "category": "Retail",
        "subcategory": "Repair Shop",
        "type": "Services"
      }
    ],
    "sg:phone": "+1 513 528 9500",
    "sg:postcode": "45244",
    "sg:province": "OH",
    "sg:tags": [
      "equipment",
      "television",
      "electronic",
      "radio"
    ],
    "wof:name": "Blue Chip Electronics Svc",
    "wof:placetype": "venue"
  },
  "geometry": {"coordinates":[-84.300606,39.093672],"type":"Point"}
}
