{
  "type": "Feature",
  "properties": {
    "addr:full":"1560 NW Catawba Rd Port Clinton OH 43452",
    "addr:housenumber":"1560",
    "addr:postcode":"43452",
    "addr:street":"Nw Catawba Rd",
    "iso:country":"US",
    "sg:address":"1560 NW Catawba Rd",
    "sg:city":"Port Clinton",
    "sg:classifiers":[
        {
            "category":"Recreation",
            "subcategory":"Marina",
            "type":"Entertainment"
        }
    ],
    "sg:phone":"+1 419 797 4680",
    "sg:postcode":"43452",
    "sg:province":"OH",
    "wof:name":"Northwest Catawba Marina",
    "wof:placetype":"venue"
},
  "geometry": {"coordinates":[-82.85653000000001,41.544614],"type":"Point"}
}