{
  "type": "Feature",
  "properties": {
    "iso:country":"US",
    "sg:address":"8420 Georgetown Rd",
    "sg:city":"Cambridge",
    "sg:classifiers":[
        {
            "category":"Health Services",
            "subcategory":"Nursing And Care Facility",
            "type":"Services"
        }
    ],
    "sg:phone":"+1 740 439 4401",
    "sg:postcode":"43725",
    "sg:province":"OH",
    "sg:tags":[
        "home",
        "convalescent"
    ],
    "wof:name":"Red Carpet Health Care Ctr",
    "wof:placetype":"venue"
},
  "geometry": {"coordinates":[-81.59462,40.004665],"type":"Point"}
}