{
  "type": "Feature",
  "properties": {
    "iso:country":"US",
    "sg:address":"431 Western Ave",
    "sg:city":"Chillicothe",
    "sg:classifiers":[
        {
            "category":"Food & Beverages",
            "subcategory":"Liquor & Beverages",
            "type":"Retail Goods"
        }
    ],
    "sg:phone":"+1 740 773 3382",
    "sg:postcode":"45601",
    "sg:province":"OH",
    "sg:tags":[
        "beer",
        "ale"
    ],
    "wof:name":"Brew Thru",
    "wof:placetype":"venue"
},
  "geometry": {"coordinates":[-83.000224,39.334891],"type":"Point"}
}