{
  "type": "Feature",
  "properties": {
    "iso:country":"US",
    "sg:address":"140 S Chestnut St",
    "sg:city":"St Marys",
    "sg:classifiers":[
        {
            "category":"Education",
            "subcategory":"Library",
            "type":"Public Place"
        }
    ],
    "sg:phone":"+1 419 394 7471",
    "sg:postcode":"45885",
    "sg:province":"OH",
    "sg:website":"www.stmarys.lib.oh.us",
    "wof:name":"St Marys Community Public Lib",
    "wof:placetype":"venue"
},
  "geometry": {"coordinates":[-84.386092,40.543479],"type":"Point"}
}