{
  "type": "Feature",
  "properties": {
    "addr:full":"6665 Creek Rd Cincinnati OH 45242",
    "addr:housenumber":"6665",
    "addr:postcode":"45242",
    "addr:street":"Creek Rd",
    "iso:country":"US",
    "sg:address":"6665 Creek Rd",
    "sg:city":"Cincinnati",
    "sg:classifiers":[
        {
            "category":"Professional",
            "subcategory":"Advertising",
            "type":"Services"
        }
    ],
    "sg:phone":"+1 513 541 4800",
    "sg:postcode":"45242",
    "sg:province":"OH",
    "sg:tags":[
        "mail"
    ],
    "sg:website":"www.bluechipmailing.com",
    "wof:name":"Blue Chip Mailing Svc",
    "wof:placetype":"venue"
},
  "geometry": {"coordinates":[-84.361604,39.261342],"type":"Point"}
}