{
  "type": "Feature",
  "properties": {
    "addr:full": "60700 Quartz Rd Byesville OH 43723",
    "addr:housenumber": "60700",
    "addr:postcode": "43723",
    "addr:street": "Quartz Rd",
    "iso:country": "US",
    "sg:address": "60700 Quartz Rd",
    "sg:city": "Byesville",
    "sg:classifiers": [
      {
        "category": "Freight",
        "type": "Transportation"
      }
    ],
    "sg:phone": "+1 740 685 5679",
    "sg:postcode": "43723",
    "sg:province": "OH",
    "sg:tags": [
      "operator",
      "trucking"
    ],
    "wof:name": "R C Dispatch",
    "wof:placetype": "venue"
  },
  "geometry": {"coordinates":[-81.508114,39.980024],"type":"Point"}
}
