{
  "type": "Feature",
  "properties": {
    "addr:full": "9055 State Rte 66 Piqua OH 45356",
    "addr:housenumber": "9055",
    "addr:postcode": "45356",
    "addr:street": "State Rte 66",
    "iso:country": "US",
    "sg:address": "9055 State Rte 66",
    "sg:city": "Piqua",
    "sg:classifiers": [
      {
        "category": "Manufacturing",
        "subcategory": "Tools \u0026 Machinery",
        "type": "Manufacturing \u0026 Wholesale Goods"
      }
    ],
    "sg:phone": "+1 937 773 3388",
    "sg:postcode": "45356",
    "sg:province": "OH",
    "sg:tags": [
      "mold"
    ],
    "wof:name": "R Dunn Mold Inc",
    "wof:placetype": "venue"
  },
  "geometry": {"coordinates":[-84.257973,40.170517],"type":"Point"}
}
