{
  "type": "Feature",
  "properties": {
    "addr:full":"2908 Navarre Ave Oregon OH 43616",
    "addr:housenumber":"2908",
    "addr:postcode":"43616",
    "addr:street":"Navarre Ave",
    "iso:country":"US",
    "sg:address":"2908 Navarre Ave",
    "sg:city":"Oregon",
    "sg:classifiers":[
        {
            "category":"Restaurant",
            "type":"Food & Drink"
        }
    ],
    "sg:menulink":"http://www.allmenus.com/oh/oregon/195147-mcdonalds/menu/",
    "sg:postcode":"43616",
    "sg:province":"OH",
    "sg:tags":[
        "burger",
        "american"
    ],
    "wof:name":"McDonald's",
    "wof:placetype":"venue"
},
  "geometry": {"coordinates":[-83.478719,41.636811],"type":"Point"}
}