{
  "type": "Feature",
  "properties": {
    "iso:country":"US",
    "sg:address":"1900 Cobblestone Dr",
    "sg:city":"Findlay",
    "sg:classifiers":[
        {
            "category":"Building & Trades",
            "subcategory":"Construction",
            "type":"Services"
        }
    ],
    "sg:phone":"+1 419 423 9018",
    "sg:postcode":"45840",
    "sg:province":"OH",
    "sg:tags":[
        "residential",
        "house"
    ],
    "wof:name":"Petti Construction Co Inc",
    "wof:placetype":"venue"
},
  "geometry": {"coordinates":[-83.601854,41.063668],"type":"Point"}
}