{
  "type": "Feature",
  "properties": {
    "addr:full": "2981 Morse Rd Columbus OH 43231",
    "addr:housenumber": "2981",
    "addr:postcode": "43231",
    "addr:street": "Morse Rd",
    "iso:country": "US",
    "sg:address": "2981 Morse Rd",
    "sg:city": "Columbus",
    "sg:classifiers": [
      {
        "category": "Manufacturing",
        "subcategory": "Retail Goods",
        "type": "Manufacturing \u0026 Wholesale Goods"
      }
    ],
    "sg:phone": "+1 614 418 7513",
    "sg:postcode": "43231",
    "sg:province": "OH",
    "sg:tags": [
      "manufacturer"
    ],
    "wof:name": "Johnson Industries",
    "wof:placetype": "venue"
  },
  "geometry": {"coordinates":[-82.936566,40.058854],"type":"Point"}
}
