{
  "type": "Feature",
  "properties": {
    "iso:country":"US",
    "sg:address":"2981 Morse Rd",
    "sg:city":"Columbus",
    "sg:classifiers":[
        {
            "category":"Manufacturing",
            "subcategory":"Retail Goods",
            "type":"Manufacturing & Wholesale Goods"
        }
    ],
    "sg:phone":"+1 614 418 7513",
    "sg:postcode":"43231",
    "sg:province":"OH",
    "sg:tags":[
        "manufacturer"
    ],
    "wof:name":"Johnson Industries",
    "wof:placetype":"venue"
},
  "geometry": {"coordinates":[-82.936566,40.058854],"type":"Point"}
}