{
  "type": "Feature",
  "properties": {
    "iso:country":"US",
    "sg:address":"7308 Associate Ave",
    "sg:city":"Cleveland",
    "sg:classifiers":[
        {
            "category":"Building & Trades",
            "subcategory":"Construction",
            "type":"Services"
        }
    ],
    "sg:phone":"+1 216 529 5885",
    "sg:postcode":"44144",
    "sg:province":"OH",
    "sg:tags":[
        "hanging",
        "contractor"
    ],
    "wof:name":"Falcon Painting Inc",
    "wof:placetype":"venue"
},
  "geometry": {"coordinates":[-81.74168400000001,41.453485],"type":"Point"}
}