{
  "type": "Feature",
  "properties": {
    "addr:full":"26906 Cook Rd Olmsted Falls OH 44138",
    "addr:housenumber":"26906",
    "addr:postcode":"44138",
    "addr:street":"Cook Rd",
    "iso:country":"US",
    "sg:address":"26906 Cook Rd",
    "sg:city":"Olmsted Falls",
    "sg:classifiers":[
        {
            "category":"Restaurant",
            "type":"Food & Drink"
        }
    ],
    "sg:phone":"+1 440 235 1338",
    "sg:postcode":"44138",
    "sg:province":"OH",
    "sg:tags":[
        "eating"
    ],
    "wof:name":"Jaks Bar and Grille",
    "wof:placetype":"venue"
},
  "geometry": {"coordinates":[-81.92671199999999,41.38278],"type":"Point"}
}