{
  "type": "Feature",
  "properties": {
    "iso:country":"US",
    "sg:address":"5446 Dorr St",
    "sg:city":"Toledo",
    "sg:classifiers":[
        {
            "category":"Real Estate",
            "subcategory":"Real Estate Operator",
            "type":"Services"
        }
    ],
    "sg:phone":"+1 419 537 1440",
    "sg:postcode":"43615",
    "sg:province":"OH",
    "sg:tags":[
        "apartment"
    ],
    "wof:name":"Longwood Park Leasing Office",
    "wof:placetype":"venue"
},
  "geometry": {"coordinates":[-83.670677,41.653562],"type":"Point"}
}