{
  "type": "Feature",
  "properties": {
    "addr:full": "8845 State Rte 66 Defiance OH 43512",
    "addr:housenumber": "8845",
    "addr:postcode": "43512",
    "addr:street": "State Rte 66",
    "iso:country": "US",
    "sg:address": "8845 State Rte 66",
    "sg:city": "Defiance",
    "sg:classifiers": [
      {
        "category": "Home \u0026 Garden",
        "subcategory": "Building Materials",
        "type": "Retail Goods"
      }
    ],
    "sg:phone": "+1 419 782 0436",
    "sg:postcode": "43512",
    "sg:province": "OH",
    "wof:name": "Menard Inc",
    "wof:placetype": "venue"
  },
  "geometry": {"coordinates":[-84.360766,41.31394],"type":"Point"}
}
