{
  "type": "Feature",
  "properties": {
    "iso:country":"US",
    "sg:address":"2235 N West St",
    "sg:city":"Lima",
    "sg:classifiers":[
        {
            "category":"Government",
            "subcategory":"Office",
            "type":"Public Place"
        }
    ],
    "sg:phone":"+1 419 228 9265",
    "sg:postcode":"45801",
    "sg:province":"OH",
    "wof:name":"Penal Industries",
    "wof:placetype":"venue"
},
  "geometry": {"coordinates":[-84.108795,40.772624],"type":"Point"}
}