{
  "type": "Feature",
  "properties": {
    "iso:country":"US",
    "sg:address":"4170 Bright Rd",
    "sg:city":"Dublin",
    "sg:classifiers":[
        {
            "category":"Shopping",
            "subcategory":"Gifts & Souvenirs",
            "type":"Retail Goods"
        }
    ],
    "sg:phone":"+1 614 793 1244",
    "sg:postcode":"43016",
    "sg:province":"OH",
    "sg:tags":[
        "announcement",
        "invitation"
    ],
    "wof:name":"D K Photographic",
    "wof:placetype":"venue"
},
  "geometry": {"coordinates":[-83.09229,40.114298],"type":"Point"}
}