{
  "type": "Feature",
  "properties": {
    "addr:full": "1554 N Co Rd 25A Troy OH 45373",
    "addr:housenumber": "1554;25a",
    "addr:postcode": "45373",
    "addr:street": "N Co Rd",
    "iso:country": "US",
    "sg:address": "1554 N Co Rd 25A",
    "sg:city": "Troy",
    "sg:classifiers": [
      {
        "category": "Building \u0026 Trades",
        "subcategory": "Landscaping Services",
        "type": "Services"
      }
    ],
    "sg:phone": "+1 937 339 5082",
    "sg:postcode": "45373",
    "sg:province": "OH",
    "sg:tags": [
      "landscape",
      "contractor"
    ],
    "wof:name": "Shields Lawn Tamers",
    "wof:placetype": "venue"
  },
  "geometry": {"coordinates":[-84.21422,40.063112],"type":"Point"}
}
