{
  "type": "Feature",
  "properties": {
    "iso:country":"US",
    "sg:address":"1554 N Co Rd 25A",
    "sg:city":"Troy",
    "sg:classifiers":[
        {
            "category":"Building & Trades",
            "subcategory":"Landscaping Services",
            "type":"Services"
        }
    ],
    "sg:phone":"+1 937 339 5082",
    "sg:postcode":"45373",
    "sg:province":"OH",
    "sg:tags":[
        "landscape",
        "contractor"
    ],
    "wof:name":"Shields Lawn Tamers",
    "wof:placetype":"venue"
},
  "geometry": {"coordinates":[-84.21422,40.063112],"type":"Point"}
}