{
  "type": "Feature",
  "properties": {
    "addr:full": "1115 Dayton St Cincinnati OH 45214",
    "addr:housenumber": "1115",
    "addr:postcode": "45214",
    "addr:street": "Dayton St",
    "iso:country": "US",
    "sg:address": "1115 Dayton St",
    "sg:city": "Cincinnati",
    "sg:classifiers": [
      {
        "category": "Professional",
        "subcategory": "Accounting \u0026 Tax Preparation",
        "type": "Services"
      }
    ],
    "sg:phone": "+1 513 241 5100",
    "sg:postcode": "45214",
    "sg:province": "OH",
    "sg:tags": [
      "return",
      "filing"
    ],
    "wof:name": "Magna Tax Consultant",
    "wof:placetype": "venue"
  },
  "geometry": {"coordinates":[-84.53439,39.118564],"type":"Point"}
}
