{
  "type": "Feature",
  "properties": {
    "addr:full": "14450 Industrial Ave N Cleveland OH 44137",
    "addr:housenumber": "14450",
    "addr:postcode": "44137",
    "addr:street": "Industrial Ave N",
    "iso:country": "US",
    "sg:address": "14450 Industrial Ave N",
    "sg:city": "Cleveland",
    "sg:classifiers": [
      {
        "category": "Manufacturing",
        "subcategory": "Metals",
        "type": "Manufacturing \u0026 Wholesale Goods"
      }
    ],
    "sg:phone": "+1 216 662 0800",
    "sg:postcode": "44137",
    "sg:province": "OH",
    "sg:tags": [
      "treating",
      "heat"
    ],
    "wof:name": "Non-Ferrous Heat Treating Inc",
    "wof:placetype": "venue"
  },
  "geometry": {"coordinates":[-81.581812,41.411902],"type":"Point"}
}
