{
  "type": "Feature",
  "properties": {
    "addr:full": "4634 Salem Ave Dayton OH 45416",
    "addr:housenumber": "4634",
    "addr:postcode": "45416",
    "addr:street": "Salem Ave",
    "iso:country": "US",
    "sg:address": "4634 Salem Ave",
    "sg:city": "Dayton",
    "sg:classifiers": [
      {
        "category": "Shopping",
        "subcategory": "Clothing, Apparel, \u0026 Fashions",
        "type": "Retail Goods"
      }
    ],
    "sg:phone": "+1 937 274 7107",
    "sg:postcode": "45416",
    "sg:province": "OH",
    "wof:name": "Henry's Fashions",
    "wof:placetype": "venue"
  },
  "geometry": {"coordinates":[-84.265983,39.811057],"type":"Point"}
}
