{
  "type": "Feature",
  "properties": {
    "iso:country":"US",
    "sg:address":"340 W Prospect St",
    "sg:city":"Painesville",
    "sg:classifiers":[
        {
            "category":"Building & Trades",
            "subcategory":"Plumbing",
            "type":"Services"
        }
    ],
    "sg:phone":"+1 440 352 4949",
    "sg:postcode":"44077",
    "sg:province":"OH",
    "sg:tags":[
        "plumbing",
        "contractor"
    ],
    "sg:website":"www.edgellplumbinginc.com",
    "wof:name":"Edgell Plumbing",
    "wof:placetype":"venue"
},
  "geometry": {"coordinates":[-81.254299,41.72566],"type":"Point"}
}