{
  "type": "Feature",
  "properties": {
    "addr:full": "340 W Prospect St Painesville OH 44077",
    "addr:housenumber": "340",
    "addr:postcode": "44077",
    "addr:street": "W Prospect St",
    "iso:country": "US",
    "sg:address": "340 W Prospect St",
    "sg:city": "Painesville",
    "sg:classifiers": [
      {
        "category": "Building \u0026 Trades",
        "subcategory": "Plumbing",
        "type": "Services"
      }
    ],
    "sg:phone": "+1 440 352 4949",
    "sg:postcode": "44077",
    "sg:province": "OH",
    "sg:tags": [
      "plumbing",
      "contractor"
    ],
    "sg:website": "www.edgellplumbinginc.com",
    "wof:name": "Edgell Plumbing",
    "wof:placetype": "venue"
  },
  "geometry": {"coordinates":[-81.254299,41.72566],"type":"Point"}
}
