{
  "type": "Feature",
  "properties": {
    "addr:full": "1900 Case Pkwy S Twinsburg OH 44087",
    "addr:housenumber": "1900",
    "addr:postcode": "44087",
    "addr:street": "Case Pkwy S",
    "iso:country": "US",
    "sg:address": "1900 Case Pkwy S",
    "sg:city": "Twinsburg",
    "sg:classifiers": [
      {
        "category": "Manufacturing",
        "subcategory": "Tools \u0026 Machinery",
        "type": "Manufacturing \u0026 Wholesale Goods"
      }
    ],
    "sg:phone": "+1 216 268 4200",
    "sg:postcode": "44087",
    "sg:province": "OH",
    "sg:tags": [
      "machine",
      "mfg"
    ],
    "wof:name": "National Acme Company The",
    "wof:placetype": "venue"
  },
  "geometry": {"coordinates":[-81.440412,41.287757],"type":"Point"}
}
