{
  "type": "Feature",
  "properties": {
    "iso:country":"US",
    "sg:address":"1900 Case Pkwy S",
    "sg:city":"Twinsburg",
    "sg:classifiers":[
        {
            "category":"Manufacturing",
            "subcategory":"Tools & Machinery",
            "type":"Manufacturing & Wholesale Goods"
        }
    ],
    "sg:phone":"+1 216 268 4200",
    "sg:postcode":"44087",
    "sg:province":"OH",
    "sg:tags":[
        "machine",
        "mfg"
    ],
    "wof:name":"National Acme Company The",
    "wof:placetype":"venue"
},
  "geometry": {"coordinates":[-81.44041199999999,41.287757],"type":"Point"}
}