{
  "type": "Feature",
  "properties": {
    "iso:country":"US",
    "sg:address":"3250 Rowena St",
    "sg:city":"Barberton",
    "sg:classifiers":[
        {
            "category":"Building & Trades",
            "subcategory":"Construction",
            "type":"Services"
        }
    ],
    "sg:phone":"+1 330 645 6233",
    "sg:postcode":"44203",
    "sg:province":"OH",
    "sg:tags":[
        "hanging",
        "contractor"
    ],
    "wof:name":"Cinko Painting",
    "wof:placetype":"venue"
},
  "geometry": {"coordinates":[-81.55912499999999,41.010494],"type":"Point"}
}