{
  "type": "Feature",
  "properties": {
    "addr:full": "2455 Charles Rd Mansfield OH 44903",
    "addr:housenumber": "2455",
    "addr:postcode": "44903",
    "addr:street": "Charles Rd",
    "iso:country": "US",
    "sg:address": "2455 Charles Rd",
    "sg:city": "Mansfield",
    "sg:phone": "+1 419 589 8602",
    "sg:postcode": "44903",
    "sg:province": "OH",
    "sg:tags": [
      "farm",
      "corn",
      "crop",
      "field",
      "dairy",
      "soybean"
    ],
    "wof:name": "Roger Fulk",
    "wof:placetype": "venue"
  },
  "geometry": {"coordinates":[-82.425896,40.853389],"type":"Point"}
}
