{
  "type": "Feature",
  "properties": {
    "iso:country":"US",
    "sg:address":"2455 Charles Rd",
    "sg:city":"Mansfield",
    "sg:phone":"+1 419 589 8602",
    "sg:postcode":"44903",
    "sg:province":"OH",
    "sg:tags":[
        "farm",
        "corn",
        "crop",
        "field",
        "dairy",
        "soybean"
    ],
    "wof:name":"Roger Fulk",
    "wof:placetype":"venue"
},
  "geometry": {"coordinates":[-82.42589599999999,40.853389],"type":"Point"}
}