{
  "type": "Feature",
  "properties": {
    "addr:full":"165 Union St Ashland OH 44805",
    "addr:housenumber":"165",
    "addr:postcode":"44805",
    "addr:street":"Union St",
    "iso:country":"US",
    "sg:address":"165 Union St",
    "sg:city":"Ashland",
    "sg:classifiers":[
        {
            "category":"Bars & Pubs",
            "type":"Food & Drink"
        }
    ],
    "sg:phone":"+1 419 289 9092",
    "sg:postcode":"44805",
    "sg:province":"OH",
    "sg:tags":[
        "drinking"
    ],
    "wof:name":"Old Time Tavern",
    "wof:placetype":"venue"
},
  "geometry": {"coordinates":[-82.312884,40.86934],"type":"Point"}
}