{
  "type": "Feature",
  "properties": {
    "addr:full": "10417 Juniper Ct Cleveland OH 44136",
    "addr:housenumber": "10417",
    "addr:postcode": "44136",
    "addr:street": "Juniper Ct",
    "iso:country": "US",
    "sg:address": "10417 Juniper Ct",
    "sg:city": "Cleveland",
    "sg:classifiers": [
      {
        "category": "Manufacturing",
        "subcategory": "Printing",
        "type": "Manufacturing \u0026 Wholesale Goods"
      }
    ],
    "sg:phone": "+1 216 635 1088",
    "sg:postcode": "44136",
    "sg:province": "OH",
    "sg:tags": [
      "multimedia"
    ],
    "wof:name": "Ukrainian Media LTD",
    "wof:placetype": "venue"
  },
  "geometry": {"coordinates":[-81.792747,41.335706],"type":"Point"}
}
