{
  "type": "Feature",
  "properties": {
    "iso:country":"US",
    "sg:address":"11303 Fulton Rd",
    "sg:city":"Marshallville",
    "sg:classifiers":[
        {
            "category":"Manufacturing",
            "subcategory":"Printing",
            "type":"Manufacturing & Wholesale Goods"
        }
    ],
    "sg:phone":"+1 330 855 1160",
    "sg:postcode":"44645",
    "sg:province":"OH",
    "sg:tags":[
        "lithographic",
        "commercial"
    ],
    "wof:name":"Lindas Printing Service",
    "wof:placetype":"venue"
},
  "geometry": {"coordinates":[-81.780126,40.901947],"type":"Point"}
}