{
  "type": "Feature",
  "properties": {
    "addr:full":"724 Tinkers Ln Northfield OH 44067",
    "addr:housenumber":"724",
    "addr:postcode":"44067",
    "addr:street":"Tinkers Ln",
    "iso:country":"US",
    "sg:address":"724 Tinkers Ln",
    "sg:city":"Northfield",
    "sg:classifiers":[
        {
            "category":"Professional",
            "type":"Services"
        }
    ],
    "sg:phone":"+1 330 468 1328",
    "sg:postcode":"44067",
    "sg:province":"OH",
    "wof:name":"National Jr Tennis League",
    "wof:placetype":"venue"
},
  "geometry": {"coordinates":[-81.56376899999999,41.312105],"type":"Point"}
}