{
  "type": "Feature",
  "properties": {
    "addr:full":"1219 E High Ave New Philadelphia OH 44663",
    "addr:housenumber":"1219",
    "addr:postcode":"44663",
    "addr:street":"E High Ave",
    "iso:country":"US",
    "sg:address":"1219 E High Ave",
    "sg:city":"New Philadelphia",
    "sg:classifiers":[
        {
            "category":"Autos & Motor Vehicles",
            "subcategory":"Fuel & Gas Station",
            "type":"Retail Goods"
        }
    ],
    "sg:phone":"+1 330 364 7733",
    "sg:postcode":"44663",
    "sg:province":"OH",
    "sg:tags":[
        "oil"
    ],
    "wof:name":"Fuel Depot",
    "wof:placetype":"venue"
},
  "geometry": {"coordinates":[-81.42785000000001,40.480426],"type":"Point"}
}