{
  "type": "Feature",
  "properties": {
    "addr:full":"748 State Rte 95 Loudonville OH 44842",
    "addr:housenumber":"748",
    "addr:postcode":"44842",
    "addr:street":"State Rte 95",
    "iso:country":"US",
    "sg:address":"748 State Rte 95",
    "sg:city":"Loudonville",
    "sg:classifiers":[
        {
            "category":"Freight",
            "type":"Transportation"
        }
    ],
    "sg:phone":"+1 419 938 8805",
    "sg:postcode":"44842",
    "sg:province":"OH",
    "wof:name":"Mercer Transportation",
    "wof:placetype":"venue"
},
  "geometry": {"coordinates":[-82.264662,40.692306],"type":"Point"}
}