{
  "type": "Feature",
  "properties": {
    "iso:country":"US",
    "sg:address":"33 Willow Dr",
    "sg:city":"Youngstown",
    "sg:classifiers":[
        {
            "category":"Retail",
            "subcategory":"Laundry & Dry Cleaning",
            "type":"Services"
        }
    ],
    "sg:phone":"+1 330 782 3345",
    "sg:postcode":"44512",
    "sg:province":"OH",
    "sg:tags":[
        "cleaners",
        "rug",
        "carpet"
    ],
    "wof:name":"Dual Method",
    "wof:placetype":"venue"
},
  "geometry": {"coordinates":[-80.661451,41.047496],"type":"Point"}
}