{
  "type": "Feature",
  "properties": {
    "addr:full": "33 Willow Dr Youngstown OH 44512",
    "addr:housenumber": "33",
    "addr:postcode": "44512",
    "addr:street": "Willow Dr",
    "iso:country": "US",
    "sg:address": "33 Willow Dr",
    "sg:city": "Youngstown",
    "sg:classifiers": [
      {
        "category": "Retail",
        "subcategory": "Laundry \u0026 Dry Cleaning",
        "type": "Services"
      }
    ],
    "sg:phone": "+1 330 782 3345",
    "sg:postcode": "44512",
    "sg:province": "OH",
    "sg:tags": [
      "cleaners",
      "rug",
      "carpet"
    ],
    "wof:name": "Dual Method",
    "wof:placetype": "venue"
  },
  "geometry": {"coordinates":[-80.661451,41.047496],"type":"Point"}
}
