{
  "type": "Feature",
  "properties": {
    "addr:full":"61690 Southgate Rd Cambridge OH 43725",
    "addr:housenumber":"61690",
    "addr:postcode":"43725",
    "addr:street":"Southgate Rd",
    "iso:country":"US",
    "sg:address":"61690 Southgate Rd",
    "sg:city":"Cambridge",
    "sg:classifiers":[
        {
            "category":"Retail",
            "subcategory":"Portrait Studio",
            "type":"Services"
        }
    ],
    "sg:phone":"+1 740 435 3373",
    "sg:postcode":"43725",
    "sg:province":"OH",
    "sg:tags":[
        "photo"
    ],
    "wof:name":"Olan Mills Studios",
    "wof:placetype":"venue"
},
  "geometry": {"coordinates":[-81.572979,39.991151],"type":"Point"}
}