{
  "type": "Feature",
  "properties": {
    "addr:full":"57 N Westwood Ave Toledo OH 43607",
    "addr:housenumber":"57",
    "addr:postcode":"43607",
    "addr:street":"N Westwood Ave",
    "iso:country":"US",
    "sg:address":"57 N Westwood Ave",
    "sg:city":"Toledo",
    "sg:classifiers":[
        {
            "category":"Wholesale",
            "subcategory":"Electrical",
            "type":"Manufacturing & Wholesale Goods"
        }
    ],
    "sg:phone":"+1 419 535 3163",
    "sg:postcode":"43607",
    "sg:province":"OH",
    "sg:tags":[
        "control"
    ],
    "sg:website":"www.seagatecontrols.com",
    "wof:name":"Seagate Control Systems Inc",
    "wof:placetype":"venue"
},
  "geometry": {"coordinates":[-83.60672,41.63882],"type":"Point"}
}