{
  "type": "Feature",
  "properties": {
    "iso:country":"US",
    "sg:address":"181 N Washington St",
    "sg:city":"Millersburg",
    "sg:classifiers":[
        {
            "category":"Banks & Credit Unions",
            "subcategory":"Bank",
            "type":"Services"
        }
    ],
    "sg:phone":"+1 330 674 2524",
    "sg:postcode":"44654",
    "sg:province":"OH",
    "wof:name":"Killbuck Savings Bank Co",
    "wof:placetype":"venue"
},
  "geometry": {"coordinates":[-81.918362,40.555662],"type":"Point"}
}