{
  "type": "Feature",
  "properties": {
    "addr:full": "181 N Washington St Millersburg OH 44654",
    "addr:housenumber": "181",
    "addr:postcode": "44654",
    "addr:street": "N Washington St",
    "iso:country": "US",
    "sg:address": "181 N Washington St",
    "sg:city": "Millersburg",
    "sg:classifiers": [
      {
        "category": "Banks \u0026 Credit Unions",
        "subcategory": "Bank",
        "type": "Services"
      }
    ],
    "sg:phone": "+1 330 674 2524",
    "sg:postcode": "44654",
    "sg:province": "OH",
    "wof:name": "Killbuck Savings Bank Co",
    "wof:placetype": "venue"
  },
  "geometry": {"coordinates":[-81.918362,40.555662],"type":"Point"}
}
