{
  "type": "Feature",
  "properties": {
    "addr:full": "185 N State St Marion OH 43302",
    "addr:housenumber": "185",
    "addr:postcode": "43302",
    "addr:street": "N State St",
    "iso:country": "US",
    "sg:address": "185 N State St",
    "sg:city": "Marion",
    "sg:classifiers": [
      {
        "category": "Manufacturing",
        "subcategory": "Toys \u0026 Sporting Goods",
        "type": "Manufacturing \u0026 Wholesale Goods"
      },
      {
        "category": "Manufacturing",
        "subcategory": "Motor Vehicles \u0026 Parts",
        "type": "Manufacturing \u0026 Wholesale Goods"
      }
    ],
    "sg:phone": "+1 740 382 0605",
    "sg:postcode": "43302",
    "sg:province": "OH",
    "sg:tags": [
      "athletic",
      "drawn",
      "horse",
      "mfg"
    ],
    "wof:name": "Houghton Sulky Co Inc",
    "wof:placetype": "venue"
  },
  "geometry": {"coordinates":[-83.127585,40.590547],"type":"Point"}
}
