{
  "type": "Feature",
  "properties": {
    "addr:full":"217 Steiner Rd Chillicothe OH 45601",
    "addr:housenumber":"217",
    "addr:postcode":"45601",
    "addr:street":"Steiner Rd",
    "iso:country":"US",
    "sg:address":"217 Steiner Rd",
    "sg:city":"Chillicothe",
    "sg:classifiers":[
        {
            "category":"Building & Trades",
            "subcategory":"Construction",
            "type":"Services"
        }
    ],
    "sg:phone":"+1 740 773 7550",
    "sg:postcode":"45601",
    "sg:province":"OH",
    "sg:tags":[
        "house"
    ],
    "wof:name":"Floyd Bldrs Design Consulting",
    "wof:placetype":"venue"
},
  "geometry": {"coordinates":[-83.107463,39.37287],"type":"Point"}
}