{
  "type": "Feature",
  "properties": {
    "iso:country":"US",
    "sg:address":"62 2nd St NW",
    "sg:city":"Carrollton",
    "sg:classifiers":[
        {
            "category":"Retail",
            "subcategory":"Laundry & Dry Cleaning",
            "type":"Services"
        }
    ],
    "sg:phone":"+1 330 627 4685",
    "sg:postcode":"44615",
    "sg:province":"OH",
    "sg:tags":[
        "cleaners"
    ],
    "wof:name":"Peacock Cleaners & Coin Lndry",
    "wof:placetype":"venue"
},
  "geometry": {"coordinates":[-81.08583299999999,40.574013],"type":"Point"}
}