{
  "type": "Feature",
  "properties": {
    "addr:full":"106 S Highview Rd Middletown OH 45044",
    "addr:housenumber":"106",
    "addr:postcode":"45044",
    "addr:street":"S Highview Rd",
    "iso:country":"US",
    "sg:address":"106 S Highview Rd",
    "sg:city":"Middletown",
    "sg:classifiers":[
        {
            "category":"Building & Trades",
            "subcategory":"Construction",
            "type":"Services"
        }
    ],
    "sg:phone":"+1 513 423 8254",
    "sg:postcode":"45044",
    "sg:province":"OH",
    "sg:tags":[
        "general",
        "contractor"
    ],
    "wof:name":"Ferguson Construction Co",
    "wof:placetype":"venue"
},
  "geometry": {"coordinates":[-84.365157,39.508675],"type":"Point"}
}