{
  "type": "Feature",
  "properties": {
    "addr:full": "3625 Shiloh Springs Rd Dayton OH 45426",
    "addr:housenumber": "3625",
    "addr:postcode": "45426",
    "addr:street": "Shiloh Springs Rd",
    "iso:country": "US",
    "sg:address": "3625 Shiloh Springs Rd",
    "sg:city": "Dayton",
    "sg:classifiers": [
      {
        "category": "Professional",
        "type": "Services"
      }
    ],
    "sg:phone": "+1 937 837 2193",
    "sg:postcode": "45426",
    "sg:province": "OH",
    "sg:tags": [
      "establishment"
    ],
    "wof:name": "Mama Sally's TL Home",
    "wof:placetype": "venue"
  },
  "geometry": {"coordinates":[-84.303745,39.818365],"type":"Point"}
}
