{
  "type": "Feature",
  "properties": {
    "iso:country":"US",
    "sg:address":"4873 Liberty Ave",
    "sg:city":"Vermilion",
    "sg:classifiers":[
        {
            "category":"Restaurant",
            "type":"Food & Drink"
        }
    ],
    "sg:phone":"+1 440 967 4210",
    "sg:postcode":"44089",
    "sg:province":"OH",
    "wof:name":"Mc Donald's",
    "wof:placetype":"venue"
},
  "geometry": {"coordinates":[-82.352053,41.424413],"type":"Point"}
}