{
  "type": "Feature",
  "properties": {
    "iso:country":"US",
    "sg:address":"5391 Winetavern Ln",
    "sg:city":"Dublin",
    "sg:classifiers":[
        {
            "category":"Professional",
            "subcategory":"Computer Services",
            "type":"Services"
        }
    ],
    "sg:phone":"+1 614 799 1591",
    "sg:postcode":"43017",
    "sg:province":"OH",
    "sg:tags":[
        "consultant",
        "designer"
    ],
    "wof:name":"Desktop Concepts",
    "wof:placetype":"venue"
},
  "geometry": {"coordinates":[-83.136855,40.11514],"type":"Point"}
}