{
  "type": "Feature",
  "properties": {
    "addr:full":"2821 Co Hwy 182 Nevada OH 44849",
    "addr:housenumber":"2821",
    "addr:postcode":"44849",
    "addr:street":"Co Hwy 182",
    "iso:country":"US",
    "sg:address":"2821 Co Hwy 182",
    "sg:city":"Nevada",
    "sg:classifiers":[
        {
            "category":"Organizations",
            "subcategory":"Professional Association",
            "type":"Services"
        },
        {
            "category":"Farming",
            "subcategory":"Farm & Veterinary Services",
            "type":"Manufacturing & Wholesale Goods"
        }
    ],
    "sg:phone":"+1 740 482 2608",
    "sg:postcode":"44849",
    "sg:province":"OH",
    "sg:tags":[
        "livestock",
        "animal"
    ],
    "wof:name":"Columbia Sheep Breeders Assoc",
    "wof:placetype":"venue"
},
  "geometry": {"coordinates":[-83.167114,40.826028],"type":"Point"}
}