{
  "type": "Feature",
  "properties": {
    "iso:country":"US",
    "sg:address":"39199 Short Rd",
    "sg:city":"Elyria",
    "sg:classifiers":[
        {
            "category":"Retail",
            "subcategory":"Portrait Studio",
            "type":"Services"
        }
    ],
    "sg:phone":"+1 440 366 1891",
    "sg:postcode":"44044",
    "sg:province":"OH",
    "sg:tags":[
        "photographer"
    ],
    "wof:name":"Elyria Photography Svc",
    "wof:placetype":"venue"
},
  "geometry": {"coordinates":[-82.084143,41.189479],"type":"Point"}
}