{
  "type": "Feature",
  "properties": {
    "iso:country":"US",
    "sg:address":"120 E South St",
    "sg:city":"Sidney",
    "sg:classifiers":[
        {
            "category":"Professional",
            "subcategory":"Employment Agencies",
            "type":"Services"
        }
    ],
    "sg:phone":"+1 937 498 9444",
    "sg:postcode":"45365",
    "sg:province":"OH",
    "sg:tags":[
        "opportunity"
    ],
    "wof:name":"Allstaf",
    "wof:placetype":"venue"
},
  "geometry": {"coordinates":[-84.156368,40.283241],"type":"Point"}
}