{
  "type": "Feature",
  "properties": {
    "addr:full":"16550 Burrows Rd Thompson OH 44086",
    "addr:housenumber":"16550",
    "addr:postcode":"44086",
    "addr:street":"Burrows Rd",
    "iso:country":"US",
    "sg:address":"16550 Burrows Rd",
    "sg:city":"Thompson",
    "sg:classifiers":[
        {
            "category":"Farming",
            "subcategory":"Farm",
            "type":"Manufacturing & Wholesale Goods"
        }
    ],
    "sg:phone":"+1 440 298 3158",
    "sg:postcode":"44086",
    "sg:province":"OH",
    "sg:tags":[
        "crop",
        "general"
    ],
    "wof:name":"Tom Robison",
    "wof:placetype":"venue"
},
  "geometry": {"coordinates":[-81.05497699999999,41.641777],"type":"Point"}
}