{
  "type": "Feature",
  "properties": {
    "iso:country":"US",
    "sg:address":"243 Main St",
    "sg:city":"Byesville",
    "sg:classifiers":[
        {
            "category":"Shopping",
            "subcategory":"Discount & Variety Stores",
            "type":"Retail Goods"
        }
    ],
    "sg:phone":"+1 740 685 6007",
    "sg:postcode":"43723",
    "sg:province":"OH",
    "wof:name":"Family Dollar Stores",
    "wof:placetype":"venue"
},
  "geometry": {"coordinates":[-81.53791,39.97021],"type":"Point"}
}