{
  "type": "Feature",
  "properties": {
    "addr:full":"5508 Tri Township Rd New Bremen OH 45869",
    "addr:housenumber":"5508",
    "addr:postcode":"45869",
    "addr:street":"Tri Township Rd",
    "iso:country":"US",
    "sg:address":"5508 Tri Township Rd",
    "sg:city":"New Bremen",
    "sg:phone":"+1 419 629 3970",
    "sg:postcode":"45869",
    "sg:province":"OH",
    "sg:tags":[
        "farm",
        "corn",
        "wheat",
        "soybean"
    ],
    "wof:name":"Steven Flaute",
    "wof:placetype":"venue"
},
  "geometry": {"coordinates":[-84.414558,40.436139],"type":"Point"}
}