{
  "type": "Feature",
  "properties": {
    "addr:full": "2845 Bell St Zanesville OH 43701",
    "addr:housenumber": "2845",
    "addr:postcode": "43701",
    "addr:street": "Bell St",
    "iso:country": "US",
    "sg:address": "2845 Bell St",
    "sg:city": "Zanesville",
    "sg:classifiers": [
      {
        "category": "Health Services",
        "subcategory": "Hospital",
        "type": "Services"
      }
    ],
    "sg:phone": "+1 740 588 6426",
    "sg:postcode": "43701",
    "sg:province": "OH",
    "sg:tags": [
      "mental"
    ],
    "wof:name": "Source One Assoc",
    "wof:placetype": "venue"
  },
  "geometry": {"coordinates":[-82.01292,39.974338],"type":"Point"}
}
