{
  "type": "Feature",
  "properties": {
    "iso:country":"US",
    "sg:address":"530 N Lincoln Ave",
    "sg:city":"Alliance",
    "sg:classifiers":[
        {
            "category":"Government",
            "subcategory":"Office",
            "type":"Public Place"
        }
    ],
    "sg:phone":"+1 330 829 2257",
    "sg:postcode":"44601",
    "sg:province":"OH",
    "sg:tags":[
        "city"
    ],
    "sg:website":"www.alliancelink.com",
    "wof:name":"Alliance City Sch Adult Prgm",
    "wof:placetype":"venue"
},
  "geometry": {"coordinates":[-81.111897,40.926831],"type":"Point"}
}