{
  "type": "Feature",
  "properties": {
    "addr:full":"85 S Main St Oberlin OH 44074",
    "addr:housenumber":"85",
    "addr:postcode":"44074",
    "addr:street":"S Main St",
    "iso:country":"US",
    "sg:address":"85 S Main St",
    "sg:city":"Oberlin",
    "sg:classifiers":[
        {
            "category":"Government",
            "subcategory":"Court House",
            "type":"Public Place"
        }
    ],
    "sg:phone":"+1 440 775 7229",
    "sg:postcode":"44074",
    "sg:province":"OH",
    "sg:tags":[
        "city"
    ],
    "wof:name":"Clerk Of Court",
    "wof:placetype":"venue"
},
  "geometry": {"coordinates":[-82.217253,41.293824],"type":"Point"}
}