{
  "type": "Feature",
  "properties": {
    "addr:full":"611 Main St Genoa OH 43430",
    "addr:housenumber":"611",
    "addr:postcode":"43430",
    "addr:street":"Main St",
    "iso:country":"US",
    "sg:address":"611 Main St",
    "sg:city":"Genoa",
    "sg:classifiers":[
        {
            "category":"Shopping",
            "subcategory":"Jewelry",
            "type":"Retail Goods"
        }
    ],
    "sg:phone":"+1 419 855 8411",
    "sg:postcode":"43430",
    "sg:province":"OH",
    "wof:name":"Genoa Jewelers",
    "wof:placetype":"venue"
},
  "geometry": {"coordinates":[-83.358576,41.519823],"type":"Point"}
}