{
  "type": "Feature",
  "properties": {
    "addr:full": "140 Greentree Rd Chagrin Falls OH 44022",
    "addr:housenumber": "140",
    "addr:postcode": "44022",
    "addr:street": "Greentree Rd",
    "iso:country": "US",
    "sg:address": "140 Greentree Rd",
    "sg:city": "Chagrin Falls",
    "sg:classifiers": [
      {
        "category": "Real Estate",
        "subcategory": "Real Estate Agent",
        "type": "Services"
      }
    ],
    "sg:phone": "+1 440 247 6029",
    "sg:postcode": "44022",
    "sg:province": "OH",
    "wof:name": "Ted Properties",
    "wof:placetype": "venue"
  },
  "geometry": {"coordinates":[-81.407787,41.430111],"type":"Point"}
}
