{
  "type": "Feature",
  "properties": {
    "iso:country":"US",
    "sg:address":"17100 Miles Ave",
    "sg:city":"Cleveland",
    "sg:classifiers":[
        {
            "category":"Organizations",
            "subcategory":"Religious Organization",
            "type":"Services"
        }
    ],
    "sg:phone":"+1 216 752 4713",
    "sg:postcode":"44128",
    "sg:province":"OH",
    "sg:tags":[
        "church"
    ],
    "wof:name":"Solomon's Temple COGIC",
    "wof:placetype":"venue"
},
  "geometry": {"coordinates":[-81.559349,41.438745],"type":"Point"}
}