{
  "type": "Feature",
  "properties": {
    "iso:country":"US",
    "sg:address":"211 Aston Ct",
    "sg:city":"Pataskala",
    "sg:classifiers":[
        {
            "category":"Professional",
            "type":"Services"
        }
    ],
    "sg:phone":"+1 740 927 8865",
    "sg:postcode":"43062",
    "sg:province":"OH",
    "sg:tags":[
        "establishment"
    ],
    "wof:name":"HWH Project Solutions",
    "wof:placetype":"venue"
},
  "geometry": {"coordinates":[-82.644502,40.010351],"type":"Point"}
}