{
  "type": "Feature",
  "properties": {
    "addr:full":"4764 Tuscarawas St W Canton OH 44708",
    "addr:housenumber":"4764",
    "addr:postcode":"44708",
    "addr:street":"Tuscarawas St W",
    "iso:country":"US",
    "sg:address":"4764 Tuscarawas St W",
    "sg:city":"Canton",
    "sg:classifiers":[
        {
            "category":"Shopping",
            "subcategory":"Discount & Variety Stores",
            "type":"Retail Goods"
        }
    ],
    "sg:phone":"+1 330 479 9210",
    "sg:postcode":"44708",
    "sg:province":"OH",
    "wof:name":"Dollar Tree",
    "wof:placetype":"venue"
},
  "geometry": {"coordinates":[-81.435372,40.79481],"type":"Point"}
}