{
  "type": "Feature",
  "properties": {
    "addr:full":"3496 E Dublin Granville Rd Westerville OH 43081",
    "addr:housenumber":"3496",
    "addr:postcode":"43081",
    "addr:street":"E Dublin Granville Rd",
    "iso:country":"US",
    "sg:address":"3496 E Dublin Granville Rd",
    "sg:city":"Westerville",
    "sg:classifiers":[
        {
            "category":"Wholesale",
            "subcategory":"Metals & Minerals",
            "type":"Manufacturing & Wholesale Goods"
        }
    ],
    "sg:phone":"+1 614 899 3177",
    "sg:postcode":"43081",
    "sg:province":"OH",
    "sg:tags":[
        "water",
        "dist",
        "supply"
    ],
    "wof:name":"U S Filter",
    "wof:placetype":"venue"
},
  "geometry": {"coordinates":[-82.928544,40.079903],"type":"Point"}
}