{
  "type": "Feature",
  "properties": {
    "addr:full":"4101 E Galbraith Rd Cincinnati OH 45236",
    "addr:housenumber":"4101",
    "addr:postcode":"45236",
    "addr:street":"E Galbraith Rd",
    "iso:country":"US",
    "sg:address":"4101 E Galbraith Rd",
    "sg:city":"Cincinnati",
    "sg:classifiers":[
        {
            "category":"Autos & Motor Vehicles",
            "subcategory":"Fuel & Gas Station",
            "type":"Retail Goods"
        }
    ],
    "sg:phone":"+1 513 793 9677",
    "sg:postcode":"45236",
    "sg:province":"OH",
    "sg:tags":[
        "grocery",
        "station",
        "gasoline"
    ],
    "wof:name":"Waco 23",
    "wof:placetype":"venue"
},
  "geometry": {"coordinates":[-84.396602,39.208234],"type":"Point"}
}