{
  "type": "Feature",
  "properties": {
    "addr:full": "451 Griswold Rd Elyria OH 44035",
    "addr:housenumber": "451",
    "addr:postcode": "44035",
    "addr:street": "Griswold Rd",
    "iso:country": "US",
    "sg:address": "451 Griswold Rd",
    "sg:city": "Elyria",
    "sg:classifiers": [
      {
        "category": "Restaurant",
        "type": "Food \u0026 Drink"
      }
    ],
    "sg:phone": "+1 440 324 1228",
    "sg:postcode": "44035",
    "sg:province": "OH",
    "sg:tags": [
      "buffet"
    ],
    "wof:name": "Jumbo Buffet \u0026 Restaurant Inc",
    "wof:placetype": "venue"
  },
  "geometry": {"coordinates":[-82.11178,41.400539],"type":"Point"}
}
