{
  "type": "Feature",
  "properties": {
    "iso:country":"US",
    "sg:address":"531 Greenacre Cir",
    "sg:city":"Howard",
    "sg:classifiers":[
        {
            "category":"Building & Trades",
            "subcategory":"Construction",
            "type":"Services"
        }
    ],
    "sg:phone":"+1 740 397 4156",
    "sg:postcode":"43028",
    "sg:province":"OH",
    "sg:tags":[
        "house"
    ],
    "wof:name":"Smith Builders",
    "wof:placetype":"venue"
},
  "geometry": {"coordinates":[-82.351116,40.433355],"type":"Point"}
}