{
  "type": "Feature",
  "properties": {
    "addr:full": "1923 Southland Rd New Bremen OH 45869",
    "addr:housenumber": "1923",
    "addr:postcode": "45869",
    "addr:street": "Southland Rd",
    "iso:country": "US",
    "sg:address": "1923 Southland Rd",
    "sg:city": "New Bremen",
    "sg:phone": "+1 419 629 3027",
    "sg:postcode": "45869",
    "sg:province": "OH",
    "sg:tags": [
      "farm",
      "corn",
      "soybean"
    ],
    "wof:name": "Jim Nieter",
    "wof:placetype": "venue"
  },
  "geometry": {"coordinates":[-84.415466,40.48035],"type":"Point"}
}
