{
  "type": "Feature",
  "properties": {
    "addr:full": "1555 Deist Rd Middle Bass OH 43446",
    "addr:housenumber": "1555",
    "addr:postcode": "43446",
    "addr:street": "Deist Rd",
    "iso:country": "US",
    "sg:address": "1555 Deist Rd",
    "sg:city": "Middle Bass",
    "sg:classifiers": [
      {
        "category": "Travel",
        "subcategory": "Hotels \u0026 Motels",
        "type": "Entertainment"
      }
    ],
    "sg:phone": "+1 419 285 2314",
    "sg:postcode": "43446",
    "sg:province": "OH",
    "wof:name": "Johnstons Lakefront Cottage",
    "wof:placetype": "venue"
  },
  "geometry": {"coordinates":[-82.790647,41.693359],"type":"Point"}
}
