{
  "type": "Feature",
  "properties": {
    "iso:country":"US",
    "sg:address":"6 S Franklin St",
    "sg:city":"Richwood",
    "sg:classifiers":[
        {
            "category":"Insurance",
            "subcategory":"Insurance Agent",
            "type":"Services"
        }
    ],
    "sg:phone":"+1 740 943 2510",
    "sg:postcode":"43344",
    "sg:province":"OH",
    "sg:website":"www.mjknapp.com",
    "wof:name":"M J Knapp Insurance",
    "wof:placetype":"venue"
},
  "geometry": {"coordinates":[-83.296642,40.426482],"type":"Point"}
}