{
  "type": "Feature",
  "properties": {
    "iso:country":"US",
    "sg:address":"959 Columbia Rd",
    "sg:city":"Hamilton",
    "sg:classifiers":[
        {
            "category":"Building & Trades",
            "subcategory":"Cleaning & Sanitation",
            "type":"Services"
        }
    ],
    "sg:phone":"+1 513 887 2651",
    "sg:postcode":"45013",
    "sg:province":"OH",
    "sg:tags":[
        "maintenance"
    ],
    "wof:name":"Handy Helpers",
    "wof:placetype":"venue"
},
  "geometry": {"coordinates":[-84.595647,39.391534],"type":"Point"}
}