{
  "type": "Feature",
  "properties": {
    "addr:full": "1378 Jackson Pike Gallipolis OH 45631",
    "addr:housenumber": "1378",
    "addr:postcode": "45631",
    "addr:street": "Jackson Pike",
    "iso:country": "US",
    "sg:address": "1378 Jackson Pike",
    "sg:city": "Gallipolis",
    "sg:classifiers": [
      {
        "category": "Home \u0026 Garden",
        "subcategory": "Carpets \u0026 Floor Coverings",
        "type": "Retail Goods"
      }
    ],
    "sg:phone": "+1 740 446 0137",
    "sg:postcode": "45631",
    "sg:province": "OH",
    "wof:name": "Vanco Floor Covering",
    "wof:placetype": "venue"
  },
  "geometry": {"coordinates":[-82.259885,38.842216],"type":"Point"}
}
