{
  "type": "Feature",
  "properties": {
    "iso:country":"US",
    "sg:address":"1378 Jackson Pike",
    "sg:city":"Gallipolis",
    "sg:classifiers":[
        {
            "category":"Home & Garden",
            "subcategory":"Carpets & Floor Coverings",
            "type":"Retail Goods"
        }
    ],
    "sg:phone":"+1 740 446 0137",
    "sg:postcode":"45631",
    "sg:province":"OH",
    "wof:name":"Vanco Floor Covering",
    "wof:placetype":"venue"
},
  "geometry": {"coordinates":[-82.259885,38.842216],"type":"Point"}
}