{
  "type": "Feature",
  "properties": {
    "addr:full": "232 Tanglewood Dr Urbana OH 43078",
    "addr:housenumber": "232",
    "addr:postcode": "43078",
    "addr:street": "Tanglewood Dr",
    "iso:country": "US",
    "sg:address": "232 Tanglewood Dr",
    "sg:city": "Urbana",
    "sg:classifiers": [
      {
        "category": "Retail",
        "subcategory": "Animal Services",
        "type": "Services"
      }
    ],
    "sg:phone": "+1 937 484 8047",
    "sg:postcode": "43078",
    "sg:province": "OH",
    "wof:name": "D Bar M Performance Horses",
    "wof:placetype": "venue"
  },
  "geometry": {"coordinates":[-83.725338,40.103614],"type":"Point"}
}
