{
  "type": "Feature",
  "properties": {
    "iso:country":"US",
    "sg:address":"33001 Solon Rd",
    "sg:city":"Solon",
    "sg:classifiers":[
        {
            "category":"Health Services",
            "subcategory":"Doctor",
            "type":"Services"
        }
    ],
    "sg:phone":"+1 440 349 4714",
    "sg:postcode":"44139",
    "sg:province":"OH",
    "wof:name":"Hertz Andrew MD",
    "wof:placetype":"venue"
},
  "geometry": {"coordinates":[-81.44270299999999,41.389301],"type":"Point"}
}