{
  "type": "Feature",
  "properties": {
    "addr:full": "8358 Hayport Rd Wheelersburg OH 45694",
    "addr:housenumber": "8358",
    "addr:postcode": "45694",
    "addr:street": "Hayport Rd",
    "iso:country": "US",
    "sg:address": "8358 Hayport Rd",
    "sg:city": "Wheelersburg",
    "sg:classifiers": [
      {
        "category": "Shopping",
        "subcategory": "Gifts \u0026 Souvenirs",
        "type": "Retail Goods"
      }
    ],
    "sg:phone": "+1 740 574 0599",
    "sg:postcode": "45694",
    "sg:province": "OH",
    "sg:tags": [
      "balloon",
      "artist"
    ],
    "wof:name": "Balloon Creations",
    "wof:placetype": "venue"
  },
  "geometry": {"coordinates":[-82.860952,38.723837],"type":"Point"}
}
