{
  "type": "Feature",
  "properties": {
    "addr:full": "900 Pvt Rd 4157 Chesapeake OH 45619",
    "addr:housenumber": "900;4157",
    "addr:postcode": "45619",
    "addr:street": "Pvt Rd",
    "iso:country": "US",
    "sg:address": "900 Pvt Rd 4157",
    "sg:city": "Chesapeake",
    "sg:classifiers": [
      {
        "category": "Professional",
        "type": "Services"
      }
    ],
    "sg:phone": "+1 740 867 6479",
    "sg:postcode": "45619",
    "sg:province": "OH",
    "sg:tags": [
      "establishment"
    ],
    "wof:name": "Vista View Originials",
    "wof:placetype": "venue"
  },
  "geometry": {"coordinates":[-82.417393,38.437427],"type":"Point"}
}
