{
  "type": "Feature",
  "properties": {
    "addr:full": "4170 Fulton Rd Cleveland OH 44144",
    "addr:housenumber": "4170",
    "addr:postcode": "44144",
    "addr:street": "Fulton Rd",
    "iso:country": "US",
    "sg:address": "4170 Fulton Rd",
    "sg:city": "Cleveland",
    "sg:classifiers": [
      {
        "category": "Shopping",
        "subcategory": "Pharmacy",
        "type": "Retail Goods"
      }
    ],
    "sg:phone": "+1 216 741 3993",
    "sg:postcode": "44144",
    "sg:province": "OH",
    "sg:website": "www.discount-drugmart.com",
    "wof:name": "Discount Drug Mart Inc",
    "wof:placetype": "venue"
  },
  "geometry": {"coordinates":[-81.723431,41.444949],"type":"Point"}
}
