{
  "type": "Feature",
  "properties": {
    "addr:full": "9200 Wade Park Ave Cleveland OH 44106",
    "addr:housenumber": "9200",
    "addr:postcode": "44106",
    "addr:street": "Wade Park Ave",
    "iso:country": "US",
    "sg:address": "9200 Wade Park Ave",
    "sg:city": "Cleveland",
    "sg:classifiers": [
      {
        "category": "Shopping",
        "subcategory": "Gifts \u0026 Souvenirs",
        "type": "Retail Goods"
      }
    ],
    "sg:phone": "+1 216 229 4000",
    "sg:postcode": "44106",
    "sg:province": "OH",
    "wof:name": "A Touch of Africa",
    "wof:placetype": "venue"
  },
  "geometry": {"coordinates":[-81.622366,41.515833],"type":"Point"}
}
