{
  "type": "Feature",
  "properties": {
    "addr:full":"1300 E 49th St Cleveland OH 44114",
    "addr:housenumber":"1300",
    "addr:postcode":"44114",
    "addr:street":"E 49Th St",
    "iso:country":"US",
    "sg:address":"1300 E 49th St",
    "sg:city":"Cleveland",
    "sg:classifiers":[
        {
            "category":"Building & Trades",
            "subcategory":"Construction",
            "type":"Services"
        }
    ],
    "sg:phone":"+1 216 432 1202",
    "sg:postcode":"44114",
    "sg:province":"OH",
    "sg:tags":[
        "industrial",
        "contractor"
    ],
    "wof:name":"Tru-Trac Services Inc",
    "wof:placetype":"venue"
},
  "geometry": {"coordinates":[-81.659235,41.519596],"type":"Point"}
}