{
  "type": "Feature",
  "properties": {
    "addr:full":"184 E 5th Ave Columbus OH 43201",
    "addr:housenumber":"184",
    "addr:postcode":"43201",
    "addr:street":"E 5Th Ave",
    "iso:country":"US",
    "sg:address":"184 E 5th Ave",
    "sg:city":"Columbus",
    "sg:classifiers":[
        {
            "category":"Building & Trades",
            "subcategory":"Plumbing",
            "type":"Services"
        }
    ],
    "sg:phone":"+1 614 299 5911",
    "sg:postcode":"43201",
    "sg:province":"OH",
    "sg:tags":[
        "conditioning",
        "air",
        "system",
        "contractor"
    ],
    "wof:name":"Columbus Climate Controls Co",
    "wof:placetype":"venue"
},
  "geometry": {"coordinates":[-82.999836,39.986964],"type":"Point"}
}