{
  "type": "Feature",
  "properties": {
    "iso:country":"US",
    "sg:address":"1415 Lexington Springmill Rd S",
    "sg:city":"Mansfield",
    "sg:classifiers":[
        {
            "category":"Retail",
            "subcategory":"Animal Services",
            "type":"Services"
        }
    ],
    "sg:phone":"+1 419 529 9663",
    "sg:postcode":"44903",
    "sg:province":"OH",
    "sg:tags":[
        "pet",
        "grooming",
        "washing"
    ],
    "wof:name":"Pooch Parlor",
    "wof:placetype":"venue"
},
  "geometry": {"coordinates":[-82.581064,40.711206],"type":"Point"}
}