{
  "type": "Feature",
  "properties": {
    "addr:full": "11 S Park St Croton OH 43013",
    "addr:housenumber": "11",
    "addr:postcode": "43013",
    "addr:street": "S Park St",
    "iso:country": "US",
    "sg:address": "11 S Park St",
    "sg:city": "Croton",
    "sg:classifiers": [
      {
        "category": "Education",
        "subcategory": "Library",
        "type": "Public Place"
      }
    ],
    "sg:phone": "+1 740 893 3602",
    "sg:postcode": "43013",
    "sg:province": "OH",
    "wof:name": "Hartford Library Assn",
    "wof:placetype": "venue"
  },
  "geometry": {"coordinates":[-82.686927,40.238862],"type":"Point"}
}
