{
  "type": "Feature",
  "properties": {
    "addr:full": "2814 Lincoln Way E Massillon OH 44646",
    "addr:housenumber": "2814",
    "addr:postcode": "44646",
    "addr:street": "Lincoln Way E",
    "iso:country": "US",
    "sg:address": "2814 Lincoln Way E",
    "sg:city": "Massillon",
    "sg:classifiers": [
      {
        "category": "Education",
        "subcategory": "Special Training",
        "type": "Public Place"
      }
    ],
    "sg:phone": "+1 330 837 4636",
    "sg:postcode": "44646",
    "sg:province": "OH",
    "sg:tags": [
      "instruction",
      "driving"
    ],
    "wof:name": "Perry Driving School",
    "wof:placetype": "venue"
  },
  "geometry": {"coordinates":[-81.482395,40.796579],"type":"Point"}
}
