{
  "type": "Feature",
  "properties": {
    "addr:full":"316 E Ash St Piqua OH 45356",
    "addr:housenumber":"316",
    "addr:postcode":"45356",
    "addr:street":"E Ash St",
    "iso:country":"US",
    "sg:address":"316 E Ash St",
    "sg:city":"Piqua",
    "sg:classifiers":[
        {
            "category":"Retail",
            "subcategory":"Auto Repair",
            "type":"Services"
        }
    ],
    "sg:phone":"+1 937 418 1523",
    "sg:postcode":"45356",
    "sg:province":"OH",
    "sg:tags":[
        "automobile",
        "top",
        "upholstery"
    ],
    "wof:name":"Mike Kiamy's Upholstery Inc",
    "wof:placetype":"venue"
},
  "geometry": {"coordinates":[-84.237814,40.149854],"type":"Point"}
}