{
  "type": "Feature",
  "properties": {
    "addr:full": "6749 Engle Rd Cleveland OH 44130",
    "addr:housenumber": "6749",
    "addr:postcode": "44130",
    "addr:street": "Engle Rd",
    "iso:country": "US",
    "sg:address": "6749 Engle Rd",
    "sg:city": "Cleveland",
    "sg:classifiers": [
      {
        "category": "Manufacturing",
        "subcategory": "Tools \u0026 Machinery",
        "type": "Manufacturing \u0026 Wholesale Goods"
      }
    ],
    "sg:phone": "+1 440 239 8510",
    "sg:postcode": "44130",
    "sg:province": "OH",
    "sg:tags": [
      "cleaners",
      "household",
      "vacuum"
    ],
    "wof:name": "Tri Star Cleaning Systems",
    "wof:placetype": "venue"
  },
  "geometry": {"coordinates":[-81.823792,41.388113],"type":"Point"}
}
