{
  "type": "Feature",
  "properties": {
    "addr:full":"3334 Sandy Ln Avon OH 44011",
    "addr:housenumber":"3334",
    "addr:postcode":"44011",
    "addr:street":"Sandy Ln",
    "iso:country":"US",
    "sg:address":"3334 Sandy Ln",
    "sg:city":"Avon",
    "sg:classifiers":[
        {
            "category":"Building & Trades",
            "subcategory":"Construction",
            "type":"Services"
        }
    ],
    "sg:phone":"+1 440 899 1161",
    "sg:postcode":"44011",
    "sg:province":"OH",
    "sg:tags":[
        "contractor"
    ],
    "wof:name":"Premier Roofing",
    "wof:placetype":"venue"
},
  "geometry": {"coordinates":[-81.993253,41.434486],"type":"Point"}
}