{
  "type": "Feature",
  "properties": {
    "iso:country":"US",
    "sg:address":"1979 W 25th St",
    "sg:city":"Cleveland",
    "sg:classifiers":[
        {
            "category":"Food & Beverages",
            "subcategory":"Fruits & Vegetables",
            "type":"Retail Goods"
        }
    ],
    "sg:phone":"+1 216 621 9040",
    "sg:postcode":"44113",
    "sg:province":"OH",
    "wof:name":"Romano Franks Produce Inc",
    "wof:placetype":"venue"
},
  "geometry": {"coordinates":[-81.70335900000001,41.484279],"type":"Point"}
}