{
  "type": "Feature",
  "properties": {
    "iso:country":"US",
    "sg:address":"6409 Clark Ave",
    "sg:city":"Cleveland",
    "sg:classifiers":[
        {
            "category":"Retail",
            "subcategory":"Auto Repair",
            "type":"Services"
        }
    ],
    "sg:phone":"+1 216 961 4108",
    "sg:postcode":"44102",
    "sg:province":"OH",
    "sg:tags":[
        "wrecker"
    ],
    "wof:name":"Webbs Towing",
    "wof:placetype":"venue"
},
  "geometry": {"coordinates":[-81.730108,41.469557],"type":"Point"}
}