{
  "type": "Feature",
  "properties": {
    "addr:full":"2550 Sullivant Ave Columbus OH 43204",
    "addr:housenumber":"2550",
    "addr:postcode":"43204",
    "addr:street":"Sullivant Ave",
    "iso:country":"US",
    "sg:address":"2550 Sullivant Ave",
    "sg:city":"Columbus",
    "sg:classifiers":[
        {
            "category":"Organizations",
            "subcategory":"Religious Organization",
            "type":"Services"
        }
    ],
    "sg:phone":"+1 614 274 3033",
    "sg:postcode":"43204",
    "sg:province":"OH",
    "sg:tags":[
        "church"
    ],
    "wof:name":"St Matthew's Fire Baptized",
    "wof:placetype":"venue"
},
  "geometry": {"coordinates":[-83.06655600000001,39.944923],"type":"Point"}
}