{
  "type": "Feature",
  "properties": {
    "addr:full": "5483 Lake Rd E Geneva OH 44041",
    "addr:housenumber": "5483",
    "addr:postcode": "44041",
    "addr:street": "Lake Rd E",
    "iso:country": "US",
    "sg:address": "5483 Lake Rd E",
    "sg:city": "Geneva",
    "sg:classifiers": [
      {
        "category": "Recreation",
        "subcategory": "Amusement Park",
        "type": "Entertainment"
      }
    ],
    "sg:phone": "+1 440 466 8650",
    "sg:postcode": "44041",
    "sg:province": "OH",
    "sg:website": "www.erieviewpark.com",
    "wof:name": "Erieview Park",
    "wof:placetype": "venue"
  },
  "geometry": {"coordinates":[-80.948978,41.860807],"type":"Point"}
}
