{
  "type": "Feature",
  "properties": {
    "iso:country":"US",
    "sg:address":"32915 Aurora Rd",
    "sg:city":"Cleveland",
    "sg:classifiers":[
        {
            "category":"Banks & Credit Unions",
            "subcategory":"Investment Brokerage",
            "type":"Services"
        },
        {
            "category":"Professional",
            "subcategory":"Accounting & Tax Preparation",
            "type":"Services"
        }
    ],
    "sg:phone":"+1 440 248 5202",
    "sg:postcode":"44139",
    "sg:province":"OH",
    "sg:tags":[
        "consultant",
        "financial",
        "planning",
        "return"
    ],
    "sg:website":"www.rhallidaycpa.com",
    "wof:name":"Robert Halliday Company",
    "wof:placetype":"venue"
},
  "geometry": {"coordinates":[-81.445161,41.386562],"type":"Point"}
}