{
  "type": "Feature",
  "properties": {
    "addr:full":"1044 N Main St Akron OH 44310",
    "addr:housenumber":"1044",
    "addr:postcode":"44310",
    "addr:street":"N Main St",
    "iso:country":"US",
    "sg:address":"1044 N Main St",
    "sg:city":"Akron",
    "sg:classifiers":[
        {
            "category":"Retail",
            "subcategory":"Laundry & Dry Cleaning",
            "type":"Services"
        }
    ],
    "sg:phone":"+1 330 923 2444",
    "sg:postcode":"44310",
    "sg:province":"OH",
    "sg:tags":[
        "zipper"
    ],
    "wof:name":"Zipper Hospital",
    "wof:placetype":"venue"
},
  "geometry": {"coordinates":[-81.51016799999999,41.115125],"type":"Point"}
}