{
  "type": "Feature",
  "properties": {
    "addr:full": "7019 Lake Ave Elyria OH 44035",
    "addr:housenumber": "7019",
    "addr:postcode": "44035",
    "addr:street": "Lake Ave",
    "iso:country": "US",
    "sg:address": "7019 Lake Ave",
    "sg:city": "Elyria",
    "sg:classifiers": [
      {
        "category": "Shopping",
        "subcategory": "Stationery \u0026 Office Supplies",
        "type": "Retail Goods"
      }
    ],
    "sg:phone": "+1 440 324 0017",
    "sg:postcode": "44035",
    "sg:province": "OH",
    "wof:name": "J \u0026 S Systems Inc",
    "wof:placetype": "venue"
  },
  "geometry": {"coordinates":[-82.131134,41.397943],"type":"Point"}
}
