{
  "type": "Feature",
  "properties": {
    "iso:country":"US",
    "sg:address":"68700 Mall Rd",
    "sg:city":"Saint Clairsville",
    "sg:classifiers":[
        {
            "category":"Food & Beverages",
            "subcategory":"Specialty",
            "type":"Retail Goods"
        }
    ],
    "sg:phone":"+1 740 695 7212",
    "sg:postcode":"43950",
    "sg:province":"OH",
    "wof:name":"GNC",
    "wof:placetype":"venue"
},
  "geometry": {"coordinates":[-80.869771,40.076201],"type":"Point"}
}