{
  "type": "Feature",
  "properties": {
    "addr:full": "433 N Raccoon Rd Youngstown OH 44515",
    "addr:housenumber": "433",
    "addr:postcode": "44515",
    "addr:street": "N Raccoon Rd",
    "iso:country": "US",
    "sg:address": "433 N Raccoon Rd",
    "sg:city": "Youngstown",
    "sg:classifiers": [
      {
        "category": "Building \u0026 Trades",
        "subcategory": "Landscaping Services",
        "type": "Services"
      }
    ],
    "sg:phone": "+1 330 792 2942",
    "sg:postcode": "44515",
    "sg:province": "OH",
    "sg:tags": [
      "lawn",
      "snow",
      "contractor",
      "maintenance",
      "removal",
      "landscape"
    ],
    "wof:name": "Cross lawn \u0026 Landscaping",
    "wof:placetype": "venue"
  },
  "geometry": {"coordinates":[-80.732208,41.112596],"type":"Point"}
}
