{
  "type": "Feature",
  "properties": {
    "addr:full": "730 E Main St Ney OH 43549",
    "addr:housenumber": "730",
    "addr:postcode": "43549",
    "addr:street": "E Main St",
    "iso:country": "US",
    "sg:address": "730 E Main St",
    "sg:city": "Ney",
    "sg:classifiers": [
      {
        "category": "Organizations",
        "subcategory": "Religious Organization",
        "type": "Services"
      }
    ],
    "sg:phone": "+1 419 658 2730",
    "sg:postcode": "43549",
    "sg:province": "OH",
    "sg:tags": [
      "church"
    ],
    "wof:name": "Christian Mercy Fellowship Chr",
    "wof:placetype": "venue"
  },
  "geometry": {"coordinates":[-84.518053,41.380422],"type":"Point"}
}
