{
  "type": "Feature",
  "properties": {
    "addr:full":"7803 Brookpark Rd Cleveland OH 44129",
    "addr:housenumber":"7803",
    "addr:postcode":"44129",
    "addr:street":"Brookpark Rd",
    "iso:country":"US",
    "sg:address":"7803 Brookpark Rd",
    "sg:city":"Cleveland",
    "sg:classifiers":[
        {
            "category":"Professional",
            "subcategory":"Detective & Security Services",
            "type":"Services"
        }
    ],
    "sg:phone":"+1 216 635 2776",
    "sg:postcode":"44129",
    "sg:province":"OH",
    "wof:name":"Gracetech Agency",
    "wof:placetype":"venue"
},
  "geometry": {"coordinates":[-81.74237100000001,41.41848],"type":"Point"}
}