{
  "type": "Feature",
  "properties": {
    "addr:full": "8512 Winton Rd Cincinnati OH 45231",
    "addr:housenumber": "8512",
    "addr:postcode": "45231",
    "addr:street": "Winton Rd",
    "iso:country": "US",
    "sg:address": "8512 Winton Rd",
    "sg:city": "Cincinnati",
    "sg:classifiers": [
      {
        "category": "Autos \u0026 Motor Vehicles",
        "subcategory": "Auto Supplies",
        "type": "Retail Goods"
      }
    ],
    "sg:phone": "+1 513 521 9999",
    "sg:postcode": "45231",
    "sg:province": "OH",
    "sg:tags": [
      "tire"
    ],
    "wof:name": "Tire Discounters",
    "wof:placetype": "venue"
  },
  "geometry": {"coordinates":[-84.517497,39.222149],"type":"Point"}
}
