{
  "type": "Feature",
  "properties": {
    "addr:full": "311 E Market St Lima OH 45801",
    "addr:housenumber": "311",
    "addr:postcode": "45801",
    "addr:street": "E Market St",
    "iso:country": "US",
    "sg:address": "311 E Market St",
    "sg:city": "Lima",
    "sg:classifiers": [
      {
        "category": "Building \u0026 Trades",
        "subcategory": "Construction",
        "type": "Services"
      }
    ],
    "sg:phone": "+1 419 331 7331",
    "sg:postcode": "45801",
    "sg:province": "OH",
    "sg:tags": [
      "residential",
      "commercial",
      "cont",
      "remodeling"
    ],
    "wof:name": "Quality Construction Systems",
    "wof:placetype": "venue"
  },
  "geometry": {"coordinates":[-84.101551,40.740108],"type":"Point"}
}
