{
  "type": "Feature",
  "properties": {
    "addr:full": "1060 Nimitzview Dr Ste 200 Cincinnati OH 45230",
    "addr:housenumber": "1060",
    "addr:postcode": "45230",
    "addr:street": "Nimitzview Dr Ste 200",
    "iso:country": "US",
    "sg:address": "1060 Nimitzview Dr Ste 200",
    "sg:city": "Cincinnati",
    "sg:classifiers": [
      {
        "category": "Professional",
        "subcategory": "Lawyer \u0026 Legal Services",
        "type": "Services"
      }
    ],
    "sg:phone": "+1 513 232 2000",
    "sg:postcode": "45230",
    "sg:province": "OH",
    "sg:tags": [
      "personal",
      "injury"
    ],
    "sg:website": "www.moorelaw.com",
    "wof:name": "Moore Law Firm the",
    "wof:placetype": "venue"
  },
  "geometry": {"coordinates":[-84.35308,39.06927],"type":"Point"}
}
