{
  "type": "Feature",
  "properties": {
    "addr:full": "2019 Dryden Rd Dayton OH 45439",
    "addr:housenumber": "2019",
    "addr:postcode": "45439",
    "addr:street": "Dryden Rd",
    "iso:country": "US",
    "sg:address": "2019 Dryden Rd",
    "sg:city": "Dayton",
    "sg:classifiers": [
      {
        "category": "Building \u0026 Trades",
        "subcategory": "Construction",
        "type": "Services"
      }
    ],
    "sg:phone": "+1 937 847 8566",
    "sg:postcode": "45439",
    "sg:province": "OH",
    "sg:tags": [
      "painter"
    ],
    "wof:name": "Overstreet Painting \u0026 Deco",
    "wof:placetype": "venue"
  },
  "geometry": {"coordinates":[-84.216964,39.727109],"type":"Point"}
}
