{
  "type": "Feature",
  "properties": {
    "iso:country":"US",
    "sg:address":"15710 Clifton Blvd",
    "sg:city":"Lakewood",
    "sg:classifiers":[
        {
            "category":"Building & Trades",
            "subcategory":"Construction",
            "type":"Services"
        }
    ],
    "sg:phone":"+1 216 228 6950",
    "sg:postcode":"44107",
    "sg:province":"OH",
    "sg:tags":[
        "painting",
        "contractor"
    ],
    "wof:name":"Design Four Contracting Inc",
    "wof:placetype":"venue"
},
  "geometry": {"coordinates":[-81.808526,41.491876],"type":"Point"}
}