{
  "type": "Feature",
  "properties": {
    "iso:country":"US",
    "sg:address":"3117 Detroit Ave",
    "sg:city":"Cleveland",
    "sg:classifiers":[
        {
            "category":"Wholesale",
            "subcategory":"Groceries",
            "type":"Manufacturing & Wholesale Goods"
        }
    ],
    "sg:phone":"+1 216 696 3388",
    "sg:postcode":"44113",
    "sg:province":"OH",
    "sg:tags":[
        "food",
        "product"
    ],
    "wof:name":"Ohio City Pasta",
    "wof:placetype":"venue"
},
  "geometry": {"coordinates":[-81.711904,41.489518],"type":"Point"}
}