{
  "type": "Feature",
  "properties": {
    "addr:full": "3117 Detroit Ave Cleveland OH 44113",
    "addr:housenumber": "3117",
    "addr:postcode": "44113",
    "addr:street": "Detroit Ave",
    "iso:country": "US",
    "sg:address": "3117 Detroit Ave",
    "sg:city": "Cleveland",
    "sg:classifiers": [
      {
        "category": "Wholesale",
        "subcategory": "Groceries",
        "type": "Manufacturing \u0026 Wholesale Goods"
      }
    ],
    "sg:phone": "+1 216 696 3388",
    "sg:postcode": "44113",
    "sg:province": "OH",
    "sg:tags": [
      "food",
      "product"
    ],
    "wof:name": "Ohio City Pasta",
    "wof:placetype": "venue"
  },
  "geometry": {"coordinates":[-81.711904,41.489518],"type":"Point"}
}
