{
  "type": "Feature",
  "properties": {
    "addr:full":"680 N Pearl St Columbus OH 43215",
    "addr:housenumber":"680",
    "addr:postcode":"43215",
    "addr:street":"N Pearl St",
    "iso:country":"US",
    "sg:address":"680 N Pearl St",
    "sg:city":"Columbus",
    "sg:classifiers":[
        {
            "category":"Food & Beverages",
            "subcategory":"Bakery",
            "type":"Retail Goods"
        }
    ],
    "sg:phone":"+1 614 220 9070",
    "sg:postcode":"43215",
    "sg:province":"OH",
    "sg:tags":[
        "baker"
    ],
    "wof:name":"Pistachio",
    "wof:placetype":"venue"
},
  "geometry": {"coordinates":[-83.00273,39.977146],"type":"Point"}
}