{
  "type": "Feature",
  "properties": {
    "iso:country":"US",
    "sg:address":"7922 N Main St",
    "sg:city":"Vandalia",
    "sg:classifiers":[
        {
            "category":"Personal",
            "subcategory":"Beauty Salon",
            "type":"Services"
        }
    ],
    "sg:phone":"+1 937 898 9618",
    "sg:postcode":"45338",
    "sg:province":"OH",
    "wof:name":"Professional Hair Designer Phd",
    "wof:placetype":"venue"
},
  "geometry": {"coordinates":[-84.540355,39.856025],"type":"Point"}
}