{
  "type": "Feature",
  "properties": {
    "addr:full": "26020 Hilliard Blvd Westlake OH 44145",
    "addr:housenumber": "26020",
    "addr:postcode": "44145",
    "addr:street": "Hilliard Blvd",
    "iso:country": "US",
    "sg:address": "26020 Hilliard Blvd",
    "sg:city": "Westlake",
    "sg:classifiers": [
      {
        "category": "Building \u0026 Trades",
        "subcategory": "Construction",
        "type": "Services"
      }
    ],
    "sg:phone": "+1 440 808 8645",
    "sg:postcode": "44145",
    "sg:province": "OH",
    "sg:tags": [
      "general"
    ],
    "wof:name": "Ramah Inc",
    "wof:placetype": "venue"
  },
  "geometry": {"coordinates":[-81.90715,41.462769],"type":"Point"}
}
