{
  "type": "Feature",
  "properties": {
    "iso:country":"US",
    "sg:address":"6692 Mill Rd",
    "sg:city":"Cleveland",
    "sg:classifiers":[
        {
            "category":"Freight",
            "type":"Transportation"
        }
    ],
    "sg:phone":"+1 440 717 2090",
    "sg:postcode":"44141",
    "sg:province":"OH",
    "sg:tags":[
        "trucking"
    ],
    "wof:name":"Bear Construction Svc Inc",
    "wof:placetype":"venue"
},
  "geometry": {"coordinates":[-81.635438,41.328915],"type":"Point"}
}