{
  "type": "Feature",
  "properties": {
    "iso:country":"US",
    "sg:address":"2000 Ford Cir",
    "sg:city":"Milford",
    "sg:classifiers":[
        {
            "category":"Shopping",
            "type":"Retail Goods"
        }
    ],
    "sg:phone":"+1 513 248 2320",
    "sg:postcode":"45150",
    "sg:province":"OH",
    "sg:tags":[
        "equipment",
        "telephone",
        "supply"
    ],
    "wof:name":"GTE Customer Networks",
    "wof:placetype":"venue"
},
  "geometry": {"coordinates":[-84.25117400000001,39.154652],"type":"Point"}
}