{
  "type": "Feature",
  "properties": {
    "addr:full": "2000 Ford Cir Milford OH 45150",
    "addr:housenumber": "2000",
    "addr:postcode": "45150",
    "addr:street": "Ford Cir",
    "iso:country": "US",
    "sg:address": "2000 Ford Cir",
    "sg:city": "Milford",
    "sg:classifiers": [
      {
        "category": "Shopping",
        "type": "Retail Goods"
      }
    ],
    "sg:phone": "+1 513 248 2320",
    "sg:postcode": "45150",
    "sg:province": "OH",
    "sg:tags": [
      "equipment",
      "telephone",
      "supply"
    ],
    "wof:name": "GTE Customer Networks",
    "wof:placetype": "venue"
  },
  "geometry": {"coordinates":[-84.251174,39.154652],"type":"Point"}
}
