{
  "type": "Feature",
  "properties": {
    "addr:full":"2396 Riegel Ridge Rd Jackson OH 45640",
    "addr:housenumber":"2396",
    "addr:postcode":"45640",
    "addr:street":"Riegel Ridge Rd",
    "iso:country":"US",
    "sg:address":"2396 Riegel Ridge Rd",
    "sg:city":"Jackson",
    "sg:classifiers":[
        {
            "category":"Food & Beverages",
            "subcategory":"Specialty",
            "type":"Retail Goods"
        },
        {
            "category":"Building & Trades",
            "subcategory":"Landscaping Services",
            "type":"Services"
        }
    ],
    "sg:phone":"+1 740 286 5927",
    "sg:postcode":"45640",
    "sg:province":"OH",
    "sg:tags":[
        "landscape",
        "contractor"
    ],
    "wof:name":"Second Nature Co",
    "wof:placetype":"venue"
},
  "geometry": {"coordinates":[-82.72823,38.935277],"type":"Point"}
}