{
  "type": "Feature",
  "properties": {
    "iso:country":"US",
    "sg:address":"4335 E Center St",
    "sg:city":"Conneaut",
    "sg:classifiers":[
        {
            "category":"Personal",
            "subcategory":"Beauty Salon",
            "type":"Services"
        }
    ],
    "sg:phone":"+1 440 599 8470",
    "sg:postcode":"44030",
    "sg:province":"OH",
    "wof:name":"Finishing Touch",
    "wof:placetype":"venue"
},
  "geometry": {"coordinates":[-80.63716599999999,41.923198],"type":"Point"}
}