{
  "type": "Feature",
  "properties": {
    "addr:full": "4335 E Center St Conneaut OH 44030",
    "addr:housenumber": "4335",
    "addr:postcode": "44030",
    "addr:street": "E Center St",
    "iso:country": "US",
    "sg:address": "4335 E Center St",
    "sg:city": "Conneaut",
    "sg:classifiers": [
      {
        "category": "Personal",
        "subcategory": "Beauty Salon",
        "type": "Services"
      }
    ],
    "sg:phone": "+1 440 599 8470",
    "sg:postcode": "44030",
    "sg:province": "OH",
    "wof:name": "Finishing Touch",
    "wof:placetype": "venue"
  },
  "geometry": {"coordinates":[-80.637166,41.923198],"type":"Point"}
}
