{
  "type": "Feature",
  "properties": {
    "iso:country":"US",
    "sg:address":"8443 Dow Cir",
    "sg:city":"Cleveland",
    "sg:classifiers":[
        {
            "category":"Manufacturing",
            "subcategory":"Tools & Machinery",
            "type":"Manufacturing & Wholesale Goods"
        }
    ],
    "sg:phone":"+1 440 243 8401",
    "sg:postcode":"44136",
    "sg:province":"OH",
    "sg:tags":[
        "physician",
        "surgeon"
    ],
    "sg:website":"www.lumitex.com",
    "wof:name":"Lumitex Inc",
    "wof:placetype":"venue"
},
  "geometry": {"coordinates":[-81.804084,41.350716],"type":"Point"}
}