{
  "type": "Feature",
  "properties": {
    "iso:country":"US",
    "sg:address":"3532 Pinney Topper Rd",
    "sg:city":"Ashtabula",
    "sg:classifiers":[
        {
            "category":"Building & Trades",
            "subcategory":"Landscaping Services",
            "type":"Services"
        }
    ],
    "sg:phone":"+1 440 998 4751",
    "sg:postcode":"44004",
    "sg:province":"OH",
    "sg:tags":[
        "tree"
    ],
    "wof:name":"Randolph's Stump Remvl & Trm",
    "wof:placetype":"venue"
},
  "geometry": {"coordinates":[-80.736174,41.824331],"type":"Point"}
}