{
  "type": "Feature",
  "properties": {
    "addr:full": "3532 Pinney Topper Rd Ashtabula OH 44004",
    "addr:housenumber": "3532",
    "addr:postcode": "44004",
    "addr:street": "Pinney Topper Rd",
    "iso:country": "US",
    "sg:address": "3532 Pinney Topper Rd",
    "sg:city": "Ashtabula",
    "sg:classifiers": [
      {
        "category": "Building \u0026 Trades",
        "subcategory": "Landscaping Services",
        "type": "Services"
      }
    ],
    "sg:phone": "+1 440 998 4751",
    "sg:postcode": "44004",
    "sg:province": "OH",
    "sg:tags": [
      "tree"
    ],
    "wof:name": "Randolph's Stump Remvl \u0026 Trm",
    "wof:placetype": "venue"
  },
  "geometry": {"coordinates":[-80.736174,41.824331],"type":"Point"}
}
