{
  "type": "Feature",
  "properties": {
    "addr:full": "1032 State Rte 775 Proctorville OH 45669",
    "addr:housenumber": "1032",
    "addr:postcode": "45669",
    "addr:street": "State Rte 775",
    "iso:country": "US",
    "sg:address": "1032 State Rte 775",
    "sg:city": "Proctorville",
    "sg:classifiers": [
      {
        "category": "Government",
        "subcategory": "Office",
        "type": "Public Place"
      }
    ],
    "sg:phone": "+1 740 886 5897",
    "sg:postcode": "45669",
    "sg:province": "OH",
    "sg:tags": [
      "state",
      "program"
    ],
    "sg:website": "www.dot.state.oh.us",
    "wof:name": "Transportation Dept",
    "wof:placetype": "venue"
  },
  "geometry": {"coordinates":[-82.375412,38.452047],"type":"Point"}
}
