{
  "type": "Feature",
  "properties": {
    "addr:full":"5829 State Rte 788 Wellston OH 45692",
    "addr:housenumber":"5829",
    "addr:postcode":"45692",
    "addr:street":"State Rte 788",
    "iso:country":"US",
    "sg:address":"5829 State Rte 788",
    "sg:city":"Wellston",
    "sg:classifiers":[
        {
            "category":"Farming",
            "subcategory":"Livestock Farm",
            "type":"Manufacturing & Wholesale Goods"
        }
    ],
    "sg:phone":"+1 740 384 2400",
    "sg:postcode":"45692",
    "sg:province":"OH",
    "sg:tags":[
        "beef",
        "feedlot",
        "cattle"
    ],
    "wof:name":"Larry A Loudner",
    "wof:placetype":"venue"
},
  "geometry": {"coordinates":[-82.56139,39.115798],"type":"Point"}
}