{
  "type": "Feature",
  "properties": {
    "iso:country":"US",
    "sg:address":"25 N Navarre Ave",
    "sg:city":"Youngstown",
    "sg:classifiers":[
        {
            "category":"Building & Trades",
            "subcategory":"Construction",
            "type":"Services"
        }
    ],
    "sg:phone":"+1 330 448 2999",
    "sg:postcode":"44515",
    "sg:province":"OH",
    "sg:tags":[
        "concrete",
        "contractor"
    ],
    "wof:name":"Precision Concrete ENT Inc",
    "wof:placetype":"venue"
},
  "geometry": {"coordinates":[-80.721114,41.104355],"type":"Point"}
}