{
  "type": "Feature",
  "properties": {
    "iso:country":"US",
    "sg:address":"1212 US Hwy 42",
    "sg:city":"Ashland",
    "sg:classifiers":[
        {
            "category":"Home & Garden",
            "subcategory":"Building Materials",
            "type":"Retail Goods"
        }
    ],
    "sg:phone":"+1 419 289 3141",
    "sg:postcode":"44805",
    "sg:province":"OH",
    "wof:name":"Brightview Windows & Doors",
    "wof:placetype":"venue"
},
  "geometry": {"coordinates":[-82.36621,40.837161],"type":"Point"}
}