{
  "type": "Feature",
  "properties": {
    "addr:full": "1212 US Hwy 42 Ashland OH 44805",
    "addr:housenumber": "1212",
    "addr:postcode": "44805",
    "addr:street": "Us Hwy 42",
    "iso:country": "US",
    "sg:address": "1212 US Hwy 42",
    "sg:city": "Ashland",
    "sg:classifiers": [
      {
        "category": "Home \u0026 Garden",
        "subcategory": "Building Materials",
        "type": "Retail Goods"
      }
    ],
    "sg:phone": "+1 419 289 3141",
    "sg:postcode": "44805",
    "sg:province": "OH",
    "wof:name": "Brightview Windows \u0026 Doors",
    "wof:placetype": "venue"
  },
  "geometry": {"coordinates":[-82.36621,40.837161],"type":"Point"}
}
