{
  "type": "Feature",
  "properties": {
    "iso:country":"US",
    "sg:address":"5213 Grant Ave",
    "sg:city":"Cleveland",
    "sg:classifiers":[
        {
            "category":"Wholesale",
            "subcategory":"Electrical",
            "type":"Manufacturing & Wholesale Goods"
        }
    ],
    "sg:phone":"+1 216 641 0450",
    "sg:postcode":"44125",
    "sg:province":"OH",
    "sg:tags":[
        "product",
        "dishwasher",
        "maintenance",
        "cleaning"
    ],
    "wof:name":"Warewashing Systems of Ohio",
    "wof:placetype":"venue"
},
  "geometry": {"coordinates":[-81.651532,41.439643],"type":"Point"}
}