{
  "type": "Feature",
  "properties": {
    "addr:full": "5213 Grant Ave Cleveland OH 44125",
    "addr:housenumber": "5213",
    "addr:postcode": "44125",
    "addr:street": "Grant Ave",
    "iso:country": "US",
    "sg:address": "5213 Grant Ave",
    "sg:city": "Cleveland",
    "sg:classifiers": [
      {
        "category": "Wholesale",
        "subcategory": "Electrical",
        "type": "Manufacturing \u0026 Wholesale Goods"
      }
    ],
    "sg:phone": "+1 216 641 0450",
    "sg:postcode": "44125",
    "sg:province": "OH",
    "sg:tags": [
      "product",
      "dishwasher",
      "maintenance",
      "cleaning"
    ],
    "wof:name": "Warewashing Systems of Ohio",
    "wof:placetype": "venue"
  },
  "geometry": {"coordinates":[-81.651532,41.439643],"type":"Point"}
}
