{
  "type": "Feature",
  "properties": {
    "addr:full":"147 Navajo Dr Sardinia OH 45171",
    "addr:housenumber":"147",
    "addr:postcode":"45171",
    "addr:street":"Navajo Dr",
    "iso:country":"US",
    "sg:address":"147 Navajo Dr",
    "sg:city":"Sardinia",
    "sg:classifiers":[
        {
            "category":"Building & Trades",
            "subcategory":"Construction",
            "type":"Services"
        }
    ],
    "sg:phone":"+1 937 446 4648",
    "sg:postcode":"45171",
    "sg:province":"OH",
    "sg:tags":[
        "excavation",
        "contractor"
    ],
    "wof:name":"Kenneth L Meyers",
    "wof:placetype":"venue"
},
  "geometry": {"coordinates":[-83.791917,38.92683],"type":"Point"}
}