{
  "type": "Feature",
  "properties": {
    "iso:country":"US",
    "sg:address":"11310 Detroit Ave",
    "sg:city":"Cleveland",
    "sg:classifiers":[
        {
            "category":"Shopping",
            "subcategory":"Clothing, Apparel, & Fashions",
            "type":"Retail Goods"
        }
    ],
    "sg:phone":"+1 216 521 3838",
    "sg:postcode":"44102",
    "sg:province":"OH",
    "sg:tags":[
        "repair",
        "fur",
        "clean",
        "store"
    ],
    "wof:name":"Sabau Furs Inc",
    "wof:placetype":"venue"
},
  "geometry": {"coordinates":[-81.765678,41.482873],"type":"Point"}
}