{
  "type": "Feature",
  "properties": {
    "addr:full": "11310 Detroit Ave Cleveland OH 44102",
    "addr:housenumber": "11310",
    "addr:postcode": "44102",
    "addr:street": "Detroit Ave",
    "iso:country": "US",
    "sg:address": "11310 Detroit Ave",
    "sg:city": "Cleveland",
    "sg:classifiers": [
      {
        "category": "Shopping",
        "subcategory": "Clothing, Apparel, \u0026 Fashions",
        "type": "Retail Goods"
      }
    ],
    "sg:phone": "+1 216 521 3838",
    "sg:postcode": "44102",
    "sg:province": "OH",
    "sg:tags": [
      "repair",
      "fur",
      "clean",
      "store"
    ],
    "wof:name": "Sabau Furs Inc",
    "wof:placetype": "venue"
  },
  "geometry": {"coordinates":[-81.765678,41.482873],"type":"Point"}
}
