{
  "type": "Feature",
  "properties": {
    "iso:country":"US",
    "sg:address":"7613 Production Dr",
    "sg:city":"Cincinnati",
    "sg:classifiers":[
        {
            "category":"Shopping",
            "subcategory":"Musical Instruments",
            "type":"Retail Goods"
        }
    ],
    "sg:phone":"+1 513 679 7747",
    "sg:postcode":"45237",
    "sg:province":"OH",
    "wof:name":"Amati's Fine Instruments",
    "wof:placetype":"venue"
},
  "geometry": {"coordinates":[-84.454685,39.197939],"type":"Point"}
}