{
  "type": "Feature",
  "properties": {
    "iso:country":"US",
    "sg:address":"37841 Euclid Ave",
    "sg:city":"Willoughby",
    "sg:classifiers":[
        {
            "category":"Professional",
            "subcategory":"Lawyer & Legal Services",
            "type":"Services"
        }
    ],
    "sg:phone":"+1 440 942 9711",
    "sg:postcode":"44094",
    "sg:province":"OH",
    "sg:tags":[
        "attorney"
    ],
    "wof:name":"Joy Zeiler Courtright Esquire",
    "wof:placetype":"venue"
},
  "geometry": {"coordinates":[-81.412004,41.632761],"type":"Point"}
}