{
  "type": "Feature",
  "properties": {
    "iso:country":"US",
    "sg:address":"547 Broad St",
    "sg:city":"Elyria",
    "sg:classifiers":[
        {
            "category":"Wholesale",
            "subcategory":"Electrical",
            "type":"Manufacturing & Wholesale Goods"
        }
    ],
    "sg:phone":"+1 440 322 9635",
    "sg:postcode":"44035",
    "sg:province":"OH",
    "sg:tags":[
        "operated",
        "telephone",
        "card"
    ],
    "wof:name":"Telaleasing Enterprises Inc",
    "wof:placetype":"venue"
},
  "geometry": {"coordinates":[-82.109691,41.367823],"type":"Point"}
}