{
  "type": "Feature",
  "properties": {
    "iso:country":"US",
    "sg:address":"159 E Schreyer Pl",
    "sg:city":"Columbus",
    "sg:classifiers":[
        {
            "category":"Professional",
            "subcategory":"Accounting & Tax Preparation",
            "type":"Services"
        }
    ],
    "sg:phone":"+1 614 267 7006",
    "sg:postcode":"43214",
    "sg:province":"OH",
    "sg:tags":[
        "accountant"
    ],
    "wof:name":"Spangler & Baird",
    "wof:placetype":"venue"
},
  "geometry": {"coordinates":[-83.015404,40.052195],"type":"Point"}
}