{
  "type": "Feature",
  "properties": {
    "iso:country":"US",
    "sg:address":"8065 State Rte 7",
    "sg:city":"Kinsman",
    "sg:classifiers":[
        {
            "category":"Autos & Motor Vehicles",
            "subcategory":"Fuel & Gas Station",
            "type":"Retail Goods"
        }
    ],
    "sg:phone":"+1 330 876 6055",
    "sg:postcode":"44428",
    "sg:province":"OH",
    "sg:tags":[
        "oil"
    ],
    "wof:name":"Kinsman BP",
    "wof:placetype":"venue"
},
  "geometry": {"coordinates":[-80.588376,41.426595],"type":"Point"}
}