{
  "type": "Feature",
  "properties": {
    "iso:country":"US",
    "sg:address":"9725 Co Rd 53",
    "sg:city":"Findlay",
    "sg:classifiers":[
        {
            "category":"Farming",
            "subcategory":"Farm",
            "type":"Manufacturing & Wholesale Goods"
        }
    ],
    "sg:phone":"+1 419 859 3594",
    "sg:postcode":"45840",
    "sg:province":"OH",
    "sg:tags":[
        "crop",
        "general"
    ],
    "wof:name":"Marion Inbody",
    "wof:placetype":"venue"
},
  "geometry": {"coordinates":[-83.846874,41.028854],"type":"Point"}
}