{
  "type": "Feature",
  "properties": {
    "iso:country":"US",
    "sg:address":"265 Portage Trail Extended W",
    "sg:city":"Cuyahoga Falls",
    "sg:classifiers":[
        {
            "category":"Real Estate",
            "subcategory":"Real Estate Agent",
            "type":"Services"
        }
    ],
    "sg:phone":"+1 330 929 0707",
    "sg:postcode":"44223",
    "sg:province":"OH",
    "sg:website":"www.karamsimonrealty.com",
    "wof:name":"Karam Co",
    "wof:placetype":"venue"
},
  "geometry": {"coordinates":[-81.515659,41.144168],"type":"Point"}
}