{
  "type": "Feature",
  "properties": {
    "addr:full":"4339 Ridge Rd Cleveland OH 44144",
    "addr:housenumber":"4339",
    "addr:postcode":"44144",
    "addr:street":"Ridge Rd",
    "iso:country":"US",
    "sg:address":"4339 Ridge Rd",
    "sg:city":"Cleveland",
    "sg:classifiers":[
        {
            "category":"Education",
            "subcategory":"Vocational School",
            "type":"Public Place"
        }
    ],
    "sg:phone":"+1 216 768 2500",
    "sg:postcode":"44144",
    "sg:province":"OH",
    "sg:tags":[
        "technical",
        "trade"
    ],
    "wof:name":"Law Enforcement-Firearms Trng",
    "wof:placetype":"venue"
},
  "geometry": {"coordinates":[-81.735293,41.439074],"type":"Point"}
}