{
  "type": "Feature",
  "properties": {
    "addr:full": "106 Hiddenwood Dr Steubenville OH 43953",
    "addr:housenumber": "106",
    "addr:postcode": "43953",
    "addr:street": "Hiddenwood Dr",
    "iso:country": "US",
    "sg:address": "106 Hiddenwood Dr",
    "sg:city": "Steubenville",
    "sg:classifiers": [
      {
        "category": "Government",
        "subcategory": "Office",
        "type": "Public Place"
      }
    ],
    "sg:phone": "+1 740 264 1143",
    "sg:postcode": "43953",
    "sg:province": "OH",
    "sg:tags": [
      "educational",
      "program",
      "administrative"
    ],
    "wof:name": "Jennie Avoli",
    "wof:placetype": "venue"
  },
  "geometry": {"coordinates":[-80.685196,40.363708],"type":"Point"}
}
