{
  "type": "Feature",
  "properties": {
    "addr:full": "1902 Needmore Rd Dayton OH 45414",
    "addr:housenumber": "1902",
    "addr:postcode": "45414",
    "addr:street": "Needmore Rd",
    "iso:country": "US",
    "sg:address": "1902 Needmore Rd",
    "sg:city": "Dayton",
    "sg:classifiers": [
      {
        "category": "Wholesale",
        "subcategory": "Machinery \u0026 Supplies",
        "type": "Manufacturing \u0026 Wholesale Goods"
      }
    ],
    "sg:phone": "+1 937 278 7699",
    "sg:postcode": "45414",
    "sg:province": "OH",
    "sg:tags": [
      "equipment",
      "establishment"
    ],
    "wof:name": "Valentinos V B Buty Sup \u0026 Eqp",
    "wof:placetype": "venue"
  },
  "geometry": {"coordinates":[-84.201008,39.819537],"type":"Point"}
}
