{
  "type": "Feature",
  "properties": {
    "addr:full": "4889 Wingston Rd Cygnet OH 43413",
    "addr:housenumber": "4889",
    "addr:postcode": "43413",
    "addr:street": "Wingston Rd",
    "iso:country": "US",
    "sg:address": "4889 Wingston Rd",
    "sg:city": "Cygnet",
    "sg:classifiers": [
      {
        "category": "Retail",
        "subcategory": "Auto Repair",
        "type": "Services"
      }
    ],
    "sg:phone": "+1 419 655 2224",
    "sg:postcode": "43413",
    "sg:province": "OH",
    "sg:tags": [
      "repairing",
      "automobile"
    ],
    "wof:name": "Cygnet Automotive",
    "wof:placetype": "venue"
  },
  "geometry": {"coordinates":[-83.72715,41.219438],"type":"Point"}
}
