{
  "type": "Feature",
  "properties": {
    "iso:country":"US",
    "sg:address":"4889 Wingston Rd",
    "sg:city":"Cygnet",
    "sg:classifiers":[
        {
            "category":"Retail",
            "subcategory":"Auto Repair",
            "type":"Services"
        }
    ],
    "sg:phone":"+1 419 655 2224",
    "sg:postcode":"43413",
    "sg:province":"OH",
    "sg:tags":[
        "repairing",
        "automobile"
    ],
    "wof:name":"Cygnet Automotive",
    "wof:placetype":"venue"
},
  "geometry": {"coordinates":[-83.72714999999999,41.219438],"type":"Point"}
}