{
  "type": "Feature",
  "properties": {
    "addr:full": "209 Carroll St Akron OH 44304",
    "addr:housenumber": "209",
    "addr:postcode": "44304",
    "addr:street": "Carroll St",
    "iso:country": "US",
    "sg:address": "209 Carroll St",
    "sg:city": "Akron",
    "sg:classifiers": [
      {
        "category": "Health Services",
        "subcategory": "Nursing And Care Facility",
        "type": "Services"
      }
    ],
    "sg:phone": "+1 330 972 5103",
    "sg:postcode": "44304",
    "sg:province": "OH",
    "sg:tags": [
      "skilled",
      "association"
    ],
    "wof:name": "Collegiate Nursing Home",
    "wof:placetype": "venue"
  },
  "geometry": {"coordinates":[-81.514428,41.075348],"type":"Point"}
}
