{
  "type": "Feature",
  "properties": {
    "addr:full": "2860 Bishop Rd Wickliffe OH 44092",
    "addr:housenumber": "2860",
    "addr:postcode": "44092",
    "addr:street": "Bishop Rd",
    "iso:country": "US",
    "sg:address": "2860 Bishop Rd",
    "sg:city": "Wickliffe",
    "sg:classifiers": [
      {
        "category": "Insurance",
        "subcategory": "Insurance Agent",
        "type": "Services"
      }
    ],
    "sg:phone": "+1 440 516 4600",
    "sg:postcode": "44092",
    "sg:province": "OH",
    "wof:name": "John P Mulhall",
    "wof:placetype": "venue"
  },
  "geometry": {"coordinates":[-81.479692,41.581827],"type":"Point"}
}
