{
  "type": "Feature",
  "properties": {
    "addr:full": "5670 Webster St Dayton OH 45414",
    "addr:housenumber": "5670",
    "addr:postcode": "45414",
    "addr:street": "Webster St",
    "iso:country": "US",
    "sg:address": "5670 Webster St",
    "sg:city": "Dayton",
    "sg:classifiers": [
      {
        "category": "Retail",
        "subcategory": "Auto Repair",
        "type": "Services"
      }
    ],
    "sg:phone": "+1 937 890 5226",
    "sg:postcode": "45414",
    "sg:province": "OH",
    "sg:tags": [
      "repairing",
      "automobile"
    ],
    "wof:name": "Acme Spring Inc",
    "wof:placetype": "venue"
  },
  "geometry": {"coordinates":[-84.179514,39.825841],"type":"Point"}
}
