{
  "type": "Feature",
  "properties": {
    "addr:full":"1401 Sullivant Ave Columbus OH 43223",
    "addr:housenumber":"1401",
    "addr:postcode":"43223",
    "addr:street":"Sullivant Ave",
    "iso:country":"US",
    "sg:address":"1401 Sullivant Ave",
    "sg:city":"Columbus",
    "sg:classifiers":[
        {
            "category":"Food & Beverages",
            "subcategory":"Groceries & Convenience Stores",
            "type":"Retail Goods"
        }
    ],
    "sg:phone":"+1 614 351 1838",
    "sg:postcode":"43223",
    "sg:province":"OH",
    "sg:tags":[
        "nozzle",
        "gasoline",
        "6"
    ],
    "wof:name":"Mr Torpedo Sub Shop",
    "wof:placetype":"venue"
},
  "geometry": {"coordinates":[-83.035956,39.950526],"type":"Point"}
}