{
  "type": "Feature",
  "properties": {
    "addr:full": "820 W Strub Rd Sandusky OH 44870",
    "addr:housenumber": "820",
    "addr:postcode": "44870",
    "addr:street": "W Strub Rd",
    "iso:country": "US",
    "sg:address": "820 W Strub Rd",
    "sg:city": "Sandusky",
    "sg:classifiers": [
      {
        "category": "Building \u0026 Trades",
        "subcategory": "Construction",
        "type": "Services"
      }
    ],
    "sg:phone": "+1 419 626 9023",
    "sg:postcode": "44870",
    "sg:province": "OH",
    "sg:tags": [
      "hanging",
      "contractor"
    ],
    "wof:name": "Bay Painting \u0026 Decorati",
    "wof:placetype": "venue"
  },
  "geometry": {"coordinates":[-82.697974,41.409254],"type":"Point"}
}
