{
  "type": "Feature",
  "properties": {
    "iso:country":"US",
    "sg:address":"645 Golden Oak Pkwy",
    "sg:city":"Cleveland",
    "sg:classifiers":[
        {
            "category":"Retail",
            "subcategory":"Auto Repair",
            "type":"Services"
        }
    ],
    "sg:phone":"+1 440 232 1983",
    "sg:postcode":"44146",
    "sg:province":"OH",
    "sg:tags":[
        "repairing",
        "automobile"
    ],
    "wof:name":"Frank's Towing Svc & Repair",
    "wof:placetype":"venue"
},
  "geometry": {"coordinates":[-81.499343,41.353773],"type":"Point"}
}