{
  "type": "Feature",
  "properties": {
    "addr:full": "9058 Regency Woods Dr Willoughby OH 44094",
    "addr:housenumber": "9058",
    "addr:postcode": "44094",
    "addr:street": "Regency Woods Dr",
    "iso:country": "US",
    "sg:address": "9058 Regency Woods Dr",
    "sg:city": "Willoughby",
    "sg:classifiers": [
      {
        "category": "Professional",
        "subcategory": "Business Services",
        "type": "Services"
      }
    ],
    "sg:phone": "+1 440 256 2912",
    "sg:postcode": "44094",
    "sg:province": "OH",
    "sg:tags": [
      "interior",
      "consultant",
      "design",
      "decorator"
    ],
    "wof:name": "Denise Kaehler Interiors Inc",
    "wof:placetype": "venue"
  },
  "geometry": {"coordinates":[-81.340645,41.6251],"type":"Point"}
}
