{
  "type": "Feature",
  "properties": {
    "iso:country":"US",
    "sg:address":"5519 Oslo Dr",
    "sg:city":"Westerville",
    "sg:classifiers":[
        {
            "category":"Building & Trades",
            "subcategory":"Electrical",
            "type":"Services"
        }
    ],
    "sg:phone":"+1 614 891 1203",
    "sg:postcode":"43081",
    "sg:province":"OH",
    "sg:tags":[
        "electrical",
        "contractor"
    ],
    "wof:name":"Smocks Electric",
    "wof:placetype":"venue"
},
  "geometry": {"coordinates":[-82.917609,40.08739],"type":"Point"}
}