{
  "type": "Feature",
  "properties": {
    "iso:country":"US",
    "sg:address":"143 E Main St",
    "sg:city":"Circleville",
    "sg:classifiers":[
        {
            "category":"Personal",
            "subcategory":"Beauty Salon",
            "type":"Services"
        }
    ],
    "sg:phone":"+1 740 477 2576",
    "sg:postcode":"43113",
    "sg:province":"OH",
    "wof:name":"Hair We Go Again",
    "wof:placetype":"venue"
},
  "geometry": {"coordinates":[-82.943997,39.60146],"type":"Point"}
}