{
  "type": "Feature",
  "properties": {
    "iso:country":"US",
    "sg:address":"600 Augspurger Rd",
    "sg:city":"Hamilton",
    "sg:classifiers":[
        {
            "category":"Building & Trades",
            "subcategory":"Construction",
            "type":"Services"
        }
    ],
    "sg:phone":"+1 513 863 9544",
    "sg:postcode":"45011",
    "sg:province":"OH",
    "sg:tags":[
        "concrete",
        "contractor"
    ],
    "wof:name":"ABC Concrete Inc",
    "wof:placetype":"venue"
},
  "geometry": {"coordinates":[-84.53294200000001,39.432912],"type":"Point"}
}