{
  "type": "Feature",
  "properties": {
    "addr:full":"4925 Fishburg Rd Dayton OH 45424",
    "addr:housenumber":"4925",
    "addr:postcode":"45424",
    "addr:street":"Fishburg Rd",
    "iso:country":"US",
    "sg:address":"4925 Fishburg Rd",
    "sg:city":"Dayton",
    "sg:classifiers":[
        {
            "category":"Organizations",
            "subcategory":"Religious Organization",
            "type":"Services"
        }
    ],
    "sg:phone":"+1 937 233 4830",
    "sg:postcode":"45424",
    "sg:province":"OH",
    "sg:tags":[
        "church"
    ],
    "wof:name":"Huber Heights Church Of Christ",
    "wof:placetype":"venue"
},
  "geometry": {"coordinates":[-84.129852,39.840564],"type":"Point"}
}