{
  "type": "Feature",
  "properties": {
    "iso:country":"US",
    "sg:address":"300 W 4th St",
    "sg:city":"Cincinnati",
    "sg:classifiers":[
        {
            "category":"Professional",
            "subcategory":"Engineering",
            "type":"Services"
        }
    ],
    "sg:phone":"+1 513 621 5400",
    "sg:postcode":"45202",
    "sg:province":"OH",
    "sg:tags":[
        "mechanical",
        "electrical",
        "engineer"
    ],
    "sg:website":"www.motzce.com",
    "wof:name":"Motz Consulting Engineers Inc",
    "wof:placetype":"venue"
},
  "geometry": {"coordinates":[-84.520462,39.098799],"type":"Point"}
}