{
  "type": "Feature",
  "properties": {
    "addr:full":"2361 Rockspring Rd Toledo OH 43614",
    "addr:housenumber":"2361",
    "addr:postcode":"43614",
    "addr:street":"Rockspring Rd",
    "iso:country":"US",
    "sg:address":"2361 Rockspring Rd",
    "sg:city":"Toledo",
    "sg:classifiers":[
        {
            "category":"Shopping",
            "subcategory":"Clothing, Apparel, & Fashions",
            "type":"Retail Goods"
        }
    ],
    "sg:phone":"+1 419 482 0516",
    "sg:postcode":"43614",
    "sg:province":"OH",
    "sg:tags":[
        "sportswear"
    ],
    "wof:name":"Big Dog Sportswear",
    "wof:placetype":"venue"
},
  "geometry": {"coordinates":[-83.671791,41.595931],"type":"Point"}
}