{
  "type": "Feature",
  "properties": {
    "iso:country":"US",
    "sg:address":"502 Pike St",
    "sg:city":"Marietta",
    "sg:classifiers":[
        {
            "category":"Shopping",
            "subcategory":"Department Store",
            "type":"Retail Goods"
        }
    ],
    "sg:phone":"+1 740 374 8019",
    "sg:postcode":"45750",
    "sg:province":"OH",
    "sg:tags":[
        "discount"
    ],
    "wof:name":"Kmart",
    "wof:placetype":"venue"
},
  "geometry": {"coordinates":[-81.427663,39.409955],"type":"Point"}
}