{
  "type": "Feature",
  "properties": {
    "iso:country":"US",
    "sg:address":"9018 Independence Rd",
    "sg:city":"Defiance",
    "sg:classifiers":[
        {
            "category":"Farming",
            "subcategory":"Farm",
            "type":"Manufacturing & Wholesale Goods"
        }
    ],
    "sg:phone":"+1 419 497 3735",
    "sg:postcode":"43512",
    "sg:province":"OH",
    "sg:tags":[
        "crop",
        "general"
    ],
    "wof:name":"Jim Helmke",
    "wof:placetype":"venue"
},
  "geometry": {"coordinates":[-84.28514699999999,41.311127],"type":"Point"}
}