{
  "type": "Feature",
  "properties": {
    "addr:full": "9018 Independence Rd Defiance OH 43512",
    "addr:housenumber": "9018",
    "addr:postcode": "43512",
    "addr:street": "Independence Rd",
    "iso:country": "US",
    "sg:address": "9018 Independence Rd",
    "sg:city": "Defiance",
    "sg:classifiers": [
      {
        "category": "Farming",
        "subcategory": "Farm",
        "type": "Manufacturing \u0026 Wholesale Goods"
      }
    ],
    "sg:phone": "+1 419 497 3735",
    "sg:postcode": "43512",
    "sg:province": "OH",
    "sg:tags": [
      "crop",
      "general"
    ],
    "wof:name": "Jim Helmke",
    "wof:placetype": "venue"
  },
  "geometry": {"coordinates":[-84.285147,41.311127],"type":"Point"}
}
