{
  "type": "Feature",
  "properties": {
    "addr:full": "243 N 5th St Columbus OH 43215",
    "addr:housenumber": "243",
    "addr:postcode": "43215",
    "addr:street": "N 5Th St",
    "iso:country": "US",
    "sg:address": "243 N 5th St",
    "sg:city": "Columbus",
    "sg:classifiers": [
      {
        "category": "Professional",
        "subcategory": "Business Services",
        "type": "Services"
      }
    ],
    "sg:phone": "+1 614 220 9040",
    "sg:postcode": "43215",
    "sg:province": "OH",
    "sg:tags": [
      "merchandising"
    ],
    "wof:name": "Zengenius",
    "wof:placetype": "venue"
  },
  "geometry": {"coordinates":[-82.996003,39.968168],"type":"Point"}
}
