{
  "type": "Feature",
  "properties": {
    "iso:country":"US",
    "sg:address":"932 Carrie Ln",
    "sg:city":"Brunswick",
    "sg:classifiers":[
        {
            "category":"Wholesale",
            "subcategory":"Chemicals & Plastics",
            "type":"Manufacturing & Wholesale Goods"
        }
    ],
    "sg:phone":"+1 330 225 1881",
    "sg:postcode":"44212",
    "sg:province":"OH",
    "wof:name":"Yellowbeard Flr Safety Systems",
    "wof:placetype":"venue"
},
  "geometry": {"coordinates":[-81.81187199999999,41.251464],"type":"Point"}
}