{
  "type": "Feature",
  "properties": {
    "addr:full": "1908 Cleveland Rd Wooster OH 44691",
    "addr:housenumber": "1908",
    "addr:postcode": "44691",
    "addr:street": "Cleveland Rd",
    "iso:country": "US",
    "sg:address": "1908 Cleveland Rd",
    "sg:city": "Wooster",
    "sg:classifiers": [
      {
        "category": "Banks \u0026 Credit Unions",
        "subcategory": "Bank",
        "type": "Services"
      }
    ],
    "sg:phone": "+1 330 262 5988",
    "sg:postcode": "44691",
    "sg:province": "OH",
    "sg:tags": [
      "savings",
      "loan",
      "association"
    ],
    "sg:website": "www.waynesavings.com",
    "wof:name": "Wayne Savings Community Bank",
    "wof:placetype": "venue"
  },
  "geometry": {"coordinates":[-81.933998,40.823786],"type":"Point"}
}
