{
  "type": "Feature",
  "properties": {
    "iso:country":"US",
    "sg:address":"6039 Holliday Dr",
    "sg:city":"Toledo",
    "sg:classifiers":[
        {
            "category":"Shopping",
            "subcategory":"Used Merchandise",
            "type":"Retail Goods"
        }
    ],
    "sg:phone":"+1 419 729 5553",
    "sg:postcode":"43611",
    "sg:province":"OH",
    "wof:name":"Nowalk Equipment",
    "wof:placetype":"venue"
},
  "geometry": {"coordinates":[-83.47764100000001,41.729516],"type":"Point"}
}