{
  "type": "Feature",
  "properties": {
    "addr:full": "2130 Woodgate St Youngstown OH 44515",
    "addr:housenumber": "2130",
    "addr:postcode": "44515",
    "addr:street": "Woodgate St",
    "iso:country": "US",
    "sg:address": "2130 Woodgate St",
    "sg:city": "Youngstown",
    "sg:classifiers": [
      {
        "category": "Social Services",
        "subcategory": "Child Care",
        "type": "Services"
      }
    ],
    "sg:phone": "+1 330 270 0168",
    "sg:postcode": "44515",
    "sg:province": "OH",
    "sg:tags": [
      "day"
    ],
    "wof:name": "Child First Day Care Ltd",
    "wof:placetype": "venue"
  },
  "geometry": {"coordinates":[-80.79472,41.079462],"type":"Point"}
}
