{
  "type": "Feature",
  "properties": {
    "addr:full":"9449 Brenrick Dr Piqua OH 45356",
    "addr:housenumber":"9449",
    "addr:postcode":"45356",
    "addr:street":"Brenrick Dr",
    "iso:country":"US",
    "sg:address":"9449 Brenrick Dr",
    "sg:city":"Piqua",
    "sg:classifiers":[
        {
            "category":"Insurance",
            "subcategory":"Hazard Insurance",
            "type":"Services"
        }
    ],
    "sg:phone":"+1 937 773 4447",
    "sg:postcode":"45356",
    "sg:province":"OH",
    "sg:tags":[
        "carrier"
    ],
    "wof:name":"Fred Wright Ins",
    "wof:placetype":"venue"
},
  "geometry": {"coordinates":[-84.224789,40.172801],"type":"Point"}
}