{
  "type": "Feature",
  "properties": {
    "addr:full":"9406 Avemore Ct Dublin OH 43017",
    "addr:housenumber":"9406",
    "addr:postcode":"43017",
    "addr:street":"Avemore Ct",
    "iso:country":"US",
    "sg:address":"9406 Avemore Ct",
    "sg:city":"Dublin",
    "sg:classifiers":[
        {
            "category":"Building & Trades",
            "subcategory":"Cleaning & Sanitation",
            "type":"Services"
        }
    ],
    "sg:phone":"+1 614 336 8816",
    "sg:postcode":"43017",
    "sg:province":"OH",
    "sg:tags":[
        "janitor"
    ],
    "wof:name":"Precision Cleaning Of Columbus",
    "wof:placetype":"venue"
},
  "geometry": {"coordinates":[-83.145629,40.155127],"type":"Point"}
}