{
  "type": "Feature",
  "properties": {
    "addr:full": "1526 Republic St Cincinnati OH 45202",
    "addr:housenumber": "1526",
    "addr:postcode": "45202",
    "addr:street": "Republic St",
    "iso:country": "US",
    "sg:address": "1526 Republic St",
    "sg:city": "Cincinnati",
    "sg:classifiers": [
      {
        "category": "Social Services",
        "type": "Services"
      }
    ],
    "sg:phone": "+1 513 241 4701",
    "sg:postcode": "45202",
    "sg:province": "OH",
    "wof:name": "Moses House Inc",
    "wof:placetype": "venue"
  },
  "geometry": {"coordinates":[-84.51654,39.11212],"type":"Point"}
}
