{
  "type": "Feature",
  "properties": {
    "iso:country":"US",
    "sg:address":"52040 Twp Rd 964",
    "sg:city":"Powhatan Point",
    "sg:classifiers":[
        {
            "category":"Utilities",
            "subcategory":"Natural Gas",
            "type":"Services"
        }
    ],
    "sg:phone":"+1 740 458 1514",
    "sg:postcode":"43942",
    "sg:province":"OH",
    "sg:tags":[
        "company"
    ],
    "wof:name":"Dominion Transmission Inc",
    "wof:placetype":"venue"
},
  "geometry": {"coordinates":[-80.87446300000001,39.834864],"type":"Point"}
}