{
  "type": "Feature",
  "properties": {
    "addr:full":"507 S College Ave Oxford IN 45056",
    "addr:housenumber":"507",
    "addr:postcode":"45056",
    "addr:street":"S College Ave",
    "iso:country":"US",
    "sg:address":"507 S College Ave",
    "sg:city":"Oxford",
    "sg:classifiers":[
        {
            "category":"Real Estate",
            "subcategory":"Architect",
            "type":"Services"
        }
    ],
    "sg:phone":"+1 513 523 5900",
    "sg:postcode":"45056",
    "sg:province":"IN",
    "sg:tags":[
        "engineer"
    ],
    "wof:name":"Delbert Ogle Pe LLC",
    "wof:placetype":"venue"
},
  "geometry": {"coordinates":[-84.745609,39.505294],"type":"Point"}
}