{
  "type": "Feature",
  "properties": {
    "addr:full":"615 Dennison Ave Akron OH 44312",
    "addr:housenumber":"615",
    "addr:postcode":"44312",
    "addr:street":"Dennison Ave",
    "iso:country":"US",
    "sg:address":"615 Dennison Ave",
    "sg:city":"Akron",
    "sg:classifiers":[
        {
            "category":"Freight",
            "type":"Transportation"
        }
    ],
    "sg:phone":"+1 330 733 9533",
    "sg:postcode":"44312",
    "sg:province":"OH",
    "sg:tags":[
        "operator",
        "local",
        "trucking"
    ],
    "wof:name":"Bailey Brothers Trucking",
    "wof:placetype":"venue"
},
  "geometry": {"coordinates":[-81.428512,41.042129],"type":"Point"}
}