{
  "type": "Feature",
  "properties": {
    "addr:full": "1 W Nationwide Blvd Columbus OH 43215",
    "addr:housenumber": "1",
    "addr:postcode": "43215",
    "addr:street": "W Nationwide Blvd",
    "iso:country": "US",
    "sg:address": "1 W Nationwide Blvd",
    "sg:city": "Columbus",
    "sg:classifiers": [
      {
        "category": "Shopping",
        "subcategory": "Clothing, Apparel, \u0026 Fashions",
        "type": "Retail Goods"
      }
    ],
    "sg:phone": "+1 614 461 8310",
    "sg:postcode": "43215",
    "sg:province": "OH",
    "sg:tags": [
      "tailor"
    ],
    "wof:name": "G Georgovski Custom Tailors",
    "wof:placetype": "venue"
  },
  "geometry": {"coordinates":[-83.00301,39.968899],"type":"Point"}
}
