{
  "type": "Feature",
  "properties": {
    "iso:country":"US",
    "sg:address":"1 W Nationwide Blvd",
    "sg:city":"Columbus",
    "sg:classifiers":[
        {
            "category":"Shopping",
            "subcategory":"Clothing, Apparel, & Fashions",
            "type":"Retail Goods"
        }
    ],
    "sg:phone":"+1 614 461 8310",
    "sg:postcode":"43215",
    "sg:province":"OH",
    "sg:tags":[
        "tailor"
    ],
    "wof:name":"G Georgovski Custom Tailors",
    "wof:placetype":"venue"
},
  "geometry": {"coordinates":[-83.00301,39.968899],"type":"Point"}
}