{
  "type": "Feature",
  "properties": {
    "addr:full":"7535 State Rte 364 New Bremen OH 45869",
    "addr:housenumber":"7535",
    "addr:postcode":"45869",
    "addr:street":"State Rte 364 New",
    "iso:country":"US",
    "sg:address":"7535 State Rte 364",
    "sg:city":"New Bremen",
    "sg:phone":"+1 419 629 2570",
    "sg:postcode":"45869",
    "sg:province":"OH",
    "sg:tags":[
        "farm",
        "corn",
        "dairy"
    ],
    "wof:name":"Louis Brown",
    "wof:placetype":"venue"
},
  "geometry": {"coordinates":[-84.43409699999999,40.457764],"type":"Point"}
}