{
  "type": "Feature",
  "properties": {
    "addr:full": "1380 W 117th St Cleveland OH 44107",
    "addr:housenumber": "1380",
    "addr:postcode": "44107",
    "addr:street": "W 117Th St",
    "iso:country": "US",
    "sg:address": "1380 W 117th St",
    "sg:city": "Cleveland",
    "sg:classifiers": [
      {
        "category": "Government",
        "subcategory": "Post Office",
        "type": "Public Place"
      }
    ],
    "sg:phone": "+1 216 521 3737",
    "sg:postcode": "44107",
    "sg:province": "OH",
    "sg:tags": [
      "postal",
      "us"
    ],
    "wof:name": "US Post Office",
    "wof:placetype": "venue"
  },
  "geometry": {"coordinates":[-81.76882,41.484748],"type":"Point"}
}
