{
  "type": "Feature",
  "properties": {
    "iso:country":"US",
    "sg:address":"1380 W 117th St",
    "sg:city":"Cleveland",
    "sg:classifiers":[
        {
            "category":"Government",
            "subcategory":"Post Office",
            "type":"Public Place"
        }
    ],
    "sg:phone":"+1 216 521 3737",
    "sg:postcode":"44107",
    "sg:province":"OH",
    "sg:tags":[
        "postal",
        "us"
    ],
    "wof:name":"US Post Office",
    "wof:placetype":"venue"
},
  "geometry": {"coordinates":[-81.76882000000001,41.484748],"type":"Point"}
}