{
  "type": "Feature",
  "properties": {
    "addr:full":"235 Ludlow St Hamilton OH 45011",
    "addr:housenumber":"235",
    "addr:postcode":"45011",
    "addr:street":"Ludlow St",
    "iso:country":"US",
    "sg:address":"235 Ludlow St",
    "sg:city":"Hamilton",
    "sg:classifiers":[
        {
            "category":"Organizations",
            "subcategory":"Religious Organization",
            "type":"Services"
        }
    ],
    "sg:phone":"+1 513 863 1445",
    "sg:postcode":"45011",
    "sg:province":"OH",
    "sg:tags":[
        "church"
    ],
    "wof:name":"Salvation Army",
    "wof:placetype":"venue"
},
  "geometry": {"coordinates":[-84.561853,39.397429],"type":"Point"}
}