{
  "type": "Feature",
  "properties": {
    "iso:country":"US",
    "sg:address":"379 W Olentangy St",
    "sg:city":"Powell",
    "sg:classifiers":[
        {
            "category":"Real Estate",
            "subcategory":"Real Estate Agent",
            "type":"Services"
        }
    ],
    "sg:phone":"+1 614 793 7400",
    "sg:postcode":"43065",
    "sg:province":"OH",
    "sg:website":"www.herrealtors.com",
    "wof:name":"HER Realtors",
    "wof:placetype":"venue"
},
  "geometry": {"coordinates":[-83.086012,40.158275],"type":"Point"}
}