{
  "type": "Feature",
  "properties": {
    "addr:full": "104 W Pointe Ct Chardon OH 44024",
    "addr:housenumber": "104",
    "addr:postcode": "44024",
    "addr:street": "W Pointe Ct",
    "iso:country": "US",
    "sg:address": "104 W Pointe Ct",
    "sg:city": "Chardon",
    "sg:classifiers": [
      {
        "category": "Building \u0026 Trades",
        "subcategory": "Construction",
        "type": "Services"
      }
    ],
    "sg:phone": "+1 440 286 1333",
    "sg:postcode": "44024",
    "sg:province": "OH",
    "sg:tags": [
      "general",
      "contractor"
    ],
    "wof:name": "Fox Pointe Builders",
    "wof:placetype": "venue"
  },
  "geometry": {"coordinates":[-81.194562,41.566914],"type":"Point"}
}
