{
  "type": "Feature",
  "properties": {
    "addr:full": "1012 Sumner Ave Cleveland OH 44115",
    "addr:housenumber": "1012",
    "addr:postcode": "44115",
    "addr:street": "Sumner Ave",
    "iso:country": "US",
    "sg:address": "1012 Sumner Ave",
    "sg:city": "Cleveland",
    "sg:classifiers": [
      {
        "category": "Bars \u0026 Pubs",
        "type": "Food \u0026 Drink"
      }
    ],
    "sg:phone": "+1 216 263 8000",
    "sg:postcode": "44115",
    "sg:province": "OH",
    "sg:tags": [
      "club",
      "night"
    ],
    "wof:name": "Millennium Night Club",
    "wof:placetype": "venue"
  },
  "geometry": {"coordinates":[-81.683133,41.496476],"type":"Point"}
}
