{
  "type": "Feature",
  "properties": {
    "addr:full":"2217 N James H McGee Blvd Dayton OH 45427",
    "addr:housenumber":"2217",
    "addr:postcode":"45427",
    "addr:street":"N James H Mcgee Blvd",
    "iso:country":"US",
    "sg:address":"2217 N James H McGee Blvd",
    "sg:city":"Dayton",
    "sg:classifiers":[
        {
            "category":"Bars & Pubs",
            "type":"Food & Drink"
        }
    ],
    "sg:phone":"+1 937 268 2764",
    "sg:postcode":"45427",
    "sg:province":"OH",
    "sg:tags":[
        "club",
        "night"
    ],
    "wof:name":"Fox 2000",
    "wof:placetype":"venue"
},
  "geometry": {"coordinates":[-84.25246,39.771892],"type":"Point"}
}