{
  "type": "Feature",
  "properties": {
    "addr:full":"227 Forest Ave Seaman OH 45679",
    "addr:housenumber":"227",
    "addr:postcode":"45679",
    "addr:street":"Forest Ave",
    "iso:country":"US",
    "sg:address":"227 Forest Ave",
    "sg:city":"Seaman",
    "sg:classifiers":[
        {
            "category":"Building & Trades",
            "subcategory":"Construction",
            "type":"Services"
        }
    ],
    "sg:phone":"+1 937 386 3311",
    "sg:postcode":"45679",
    "sg:province":"OH",
    "sg:tags":[
        "builder"
    ],
    "wof:name":"C & R Builders",
    "wof:placetype":"venue"
},
  "geometry": {"coordinates":[-83.569895,38.939472],"type":"Point"}
}