{
  "type": "Feature",
  "properties": {
    "iso:country":"US",
    "sg:address":"13520 Thraves Ave",
    "sg:city":"Cleveland",
    "sg:classifiers":[
        {
            "category":"Shopping",
            "subcategory":"Used Merchandise",
            "type":"Retail Goods"
        }
    ],
    "sg:phone":"+1 216 663 0046",
    "sg:postcode":"44125",
    "sg:province":"OH",
    "wof:name":"Yours N Mine Inc",
    "wof:placetype":"venue"
},
  "geometry": {"coordinates":[-81.588347,41.405383],"type":"Point"}
}