{
  "type": "Feature",
  "properties": {
    "addr:full":"19001 State Rte 613 Bloomdale OH 44817",
    "addr:housenumber":"19001",
    "addr:postcode":"44817",
    "addr:street":"State Rte 613",
    "iso:country":"US",
    "sg:address":"19001 State Rte 613",
    "sg:city":"Bloomdale",
    "sg:classifiers":[
        {
            "category":"Real Estate",
            "subcategory":"Real Estate Operator",
            "type":"Services"
        }
    ],
    "sg:phone":"+1 419 894 6973",
    "sg:postcode":"44817",
    "sg:province":"OH",
    "sg:tags":[
        "owner",
        "residential",
        "property",
        "commercial"
    ],
    "wof:name":"McCracken Enterprise",
    "wof:placetype":"venue"
},
  "geometry": {"coordinates":[-83.529107,41.155579],"type":"Point"}
}