{
  "type": "Feature",
  "properties": {
    "addr:full":"701 N Park Ave Warren OH 44483",
    "addr:housenumber":"701",
    "addr:postcode":"44483",
    "addr:street":"N Park Ave",
    "iso:country":"US",
    "sg:address":"701 N Park Ave",
    "sg:city":"Warren",
    "sg:classifiers":[
        {
            "category":"Retail",
            "subcategory":"Portrait Studio",
            "type":"Services"
        }
    ],
    "sg:phone":"+1 330 395 9950",
    "sg:postcode":"44483",
    "sg:province":"OH",
    "sg:tags":[
        "photographer"
    ],
    "wof:name":"Diana Lynne Photography",
    "wof:placetype":"venue"
},
  "geometry": {"coordinates":[-80.81827800000001,41.242884],"type":"Point"}
}