{
  "type": "Feature",
  "properties": {
    "addr:full":"10075 Ravenna Rd Twinsburg OH 44087",
    "addr:housenumber":"10075",
    "addr:postcode":"44087",
    "addr:street":"Ravenna Rd",
    "iso:country":"US",
    "sg:address":"10075 Ravenna Rd",
    "sg:city":"Twinsburg",
    "sg:classifiers":[
        {
            "category":"Government",
            "subcategory":"Office",
            "type":"Public Place"
        },
        {
            "category":"Sports & Exercise",
            "subcategory":"Gym",
            "type":"Entertainment"
        }
    ],
    "sg:phone":"+1 330 405 5757",
    "sg:postcode":"44087",
    "sg:province":"OH",
    "sg:tags":[
        "club",
        "health",
        "studio",
        "gymnasium",
        "village"
    ],
    "wof:name":"Twinsburg Fitness Ctr",
    "wof:placetype":"venue"
},
  "geometry": {"coordinates":[-81.448117,41.317879],"type":"Point"}
}