{
  "type": "Feature",
  "properties": {
    "iso:country":"US",
    "sg:address":"5462 Mahoning Ave",
    "sg:city":"Youngstown",
    "sg:classifiers":[
        {
            "category":"Retail",
            "subcategory":"Repair Shop",
            "type":"Services"
        }
    ],
    "sg:phone":"+1 330 799 5252",
    "sg:postcode":"44515",
    "sg:province":"OH",
    "sg:tags":[
        "equipment",
        "golf",
        "refinishing"
    ],
    "wof:name":"Tim's On The Green Custom Golf",
    "wof:placetype":"venue"
},
  "geometry": {"coordinates":[-80.76247100000001,41.099692],"type":"Point"}
}