{
  "type": "Feature",
  "properties": {
    "iso:country":"US",
    "sg:address":"559 Roxbury Ave",
    "sg:city":"Youngstown",
    "sg:classifiers":[
        {
            "category":"Autos & Motor Vehicles",
            "subcategory":"Motorcycle Sales",
            "type":"Retail Goods"
        }
    ],
    "sg:phone":"+1 330 788 1376",
    "sg:postcode":"44502",
    "sg:province":"OH",
    "sg:tags":[
        "scooter"
    ],
    "wof:name":"Dz Custom Hoggs",
    "wof:placetype":"venue"
},
  "geometry": {"coordinates":[-80.643479,41.062857],"type":"Point"}
}