{
  "type": "Feature",
  "properties": {
    "addr:full":"8610 Hough Ave Cleveland OH 44106",
    "addr:postcode":"8610;44106",
    "addr:street":"Hough Ave",
    "iso:country":"US",
    "sg:address":"8610 Hough Ave",
    "sg:city":"Cleveland",
    "sg:classifiers":[
        {
            "category":"Professional",
            "subcategory":"Management & Consulting",
            "type":"Services"
        }
    ],
    "sg:phone":"+1 216 791 5016",
    "sg:postcode":"44106",
    "sg:province":"OH",
    "wof:name":"For Hope Corporation",
    "wof:placetype":"venue"
},
  "geometry": {"coordinates":[-81.626501,41.509394],"type":"Point"}
}