{
  "type": "Feature",
  "properties": {
    "addr:full": "7781 Dudley Dr West Chester OH 45069",
    "addr:housenumber": "7781",
    "addr:postcode": "45069",
    "addr:street": "Dudley Dr",
    "iso:country": "US",
    "sg:address": "7781 Dudley Dr",
    "sg:city": "West Chester",
    "sg:classifiers": [
      {
        "category": "Restaurant",
        "type": "Food \u0026 Drink"
      }
    ],
    "sg:menulink": "http://www.allmenus.com/oh/west-chester/44048-bob-evans/menu/",
    "sg:phone": "+1 513 779 4386",
    "sg:postcode": "45069",
    "sg:province": "OH",
    "sg:tags": [
      "american"
    ],
    "wof:name": "Bob Evans",
    "wof:placetype": "venue"
  },
  "geometry": {"coordinates":[-84.369704,39.353968],"type":"Point"}
}
