{
  "type": "Feature",
  "properties": {
    "iso:country":"US",
    "sg:address":"148 Dover St",
    "sg:city":"Dayton",
    "sg:classifiers":[
        {
            "category":"Farming",
            "subcategory":"Fish & Marine Products",
            "type":"Manufacturing & Wholesale Goods"
        }
    ],
    "sg:phone":"+1 937 718 4347",
    "sg:postcode":"45410",
    "sg:province":"OH",
    "sg:tags":[
        "gaming"
    ],
    "wof:name":"Playin Gamez Tge",
    "wof:placetype":"venue"
},
  "geometry": {"coordinates":[-84.166799,39.748072],"type":"Point"}
}