{
  "type": "Feature",
  "properties": {
    "addr:full":"6 S 2nd St Hamilton OH 45011",
    "addr:housenumber":"6",
    "addr:postcode":"45011",
    "addr:street":"S 2Nd St",
    "iso:country":"US",
    "sg:address":"6 S 2nd St",
    "sg:city":"Hamilton",
    "sg:classifiers":[
        {
            "category":"Professional",
            "subcategory":"Lawyer & Legal Services",
            "type":"Services"
        }
    ],
    "sg:phone":"+1 513 895 2451",
    "sg:postcode":"45011",
    "sg:province":"OH",
    "sg:tags":[
        "attorney"
    ],
    "wof:name":"Patrick E Mc Knight Attorney",
    "wof:placetype":"venue"
},
  "geometry": {"coordinates":[-84.562184,39.399046],"type":"Point"}
}