{
  "type": "Feature",
  "properties": {
    "addr:full":"541 W Tuscarawas Ave Wadsworth OH 44203",
    "addr:housenumber":"541",
    "addr:postcode":"44203",
    "addr:street":"W Tuscarawas Ave",
    "iso:country":"US",
    "sg:address":"541 W Tuscarawas Ave",
    "sg:city":"Wadsworth",
    "sg:classifiers":[
        {
            "category":"Insurance",
            "subcategory":"Insurance Agent",
            "type":"Services"
        }
    ],
    "sg:phone":"+1 330 753 8331",
    "sg:postcode":"44203",
    "sg:province":"OH",
    "wof:name":"Primerica Financial Svc",
    "wof:placetype":"venue"
},
  "geometry": {"coordinates":[-81.609139,41.012944],"type":"Point"}
}