{
  "type": "Feature",
  "properties": {
    "addr:full": "9741 State Rte 120 Lyons OH 43533",
    "addr:housenumber": "9741",
    "addr:postcode": "43533",
    "addr:street": "State Rte 120",
    "iso:country": "US",
    "sg:address": "9741 State Rte 120",
    "sg:city": "Lyons",
    "sg:classifiers": [
      {
        "category": "Home \u0026 Garden",
        "subcategory": "Garden Supply",
        "type": "Retail Goods"
      }
    ],
    "sg:phone": "+1 419 923 2761",
    "sg:postcode": "43533",
    "sg:province": "OH",
    "sg:tags": [
      "lawn",
      "mower"
    ],
    "wof:name": "John O'Neil Implement Co",
    "wof:placetype": "venue"
  },
  "geometry": {"coordinates":[-84.051258,41.699602],"type":"Point"}
}
