{
  "type": "Feature",
  "properties": {
    "addr:full": "2503 Mogadore Rd Akron OH 44312",
    "addr:housenumber": "2503",
    "addr:postcode": "44312",
    "addr:street": "Mogadore Rd",
    "iso:country": "US",
    "sg:address": "2503 Mogadore Rd",
    "sg:city": "Akron",
    "sg:classifiers": [
      {
        "category": "Utilities",
        "subcategory": "Mobile Phone",
        "type": "Services"
      }
    ],
    "sg:phone": "+1 330 794 9515",
    "sg:postcode": "44312",
    "sg:province": "OH",
    "sg:tags": [
      "telephone",
      "cellular"
    ],
    "sg:website": "www.buyanythingwireless.com",
    "wof:name": "BUYANYTHINGWIRELESS.COM",
    "wof:placetype": "venue"
  },
  "geometry": {"coordinates":[-81.437616,41.06262],"type":"Point"}
}
