{
  "type": "Feature",
  "properties": {
    "addr:full":"712 N Eastown Rd Lima OH 45807",
    "addr:housenumber":"712",
    "addr:postcode":"45807",
    "addr:street":"N Eastown Rd",
    "iso:country":"US",
    "sg:address":"712 N Eastown Rd",
    "sg:city":"Lima",
    "sg:classifiers":[
        {
            "category":"Retail",
            "subcategory":"Repair Shop",
            "type":"Services"
        }
    ],
    "sg:phone":"+1 419 229 3646",
    "sg:postcode":"45807",
    "sg:province":"OH",
    "sg:tags":[
        "television",
        "radio"
    ],
    "wof:name":"Hefner's TV Inc",
    "wof:placetype":"venue"
},
  "geometry": {"coordinates":[-84.164907,40.750027],"type":"Point"}
}