{
  "type": "Feature",
  "properties": {
    "addr:full": "10635 Mount Royal Dr Painesville OH 44077",
    "addr:housenumber": "10635",
    "addr:postcode": "44077",
    "addr:street": "Mount Royal Dr",
    "iso:country": "US",
    "sg:address": "10635 Mount Royal Dr",
    "sg:city": "Painesville",
    "sg:classifiers": [
      {
        "category": "Building \u0026 Trades",
        "subcategory": "Construction",
        "type": "Services"
      }
    ],
    "sg:phone": "+1 440 357 0298",
    "sg:postcode": "44077",
    "sg:province": "OH",
    "sg:tags": [
      "concrete",
      "contractor"
    ],
    "wof:name": "Short Concrete Construction",
    "wof:placetype": "venue"
  },
  "geometry": {"coordinates":[-81.257069,41.646531],"type":"Point"}
}
