{
  "type": "Feature",
  "properties": {
    "addr:full": "4045 Leesburg Ln Cincinnati OH 45209",
    "addr:housenumber": "4045",
    "addr:postcode": "45209",
    "addr:street": "Leesburg Ln",
    "iso:country": "US",
    "sg:address": "4045 Leesburg Ln",
    "sg:city": "Cincinnati",
    "sg:classifiers": [
      {
        "category": "Real Estate",
        "subcategory": "Real Estate Operator",
        "type": "Services"
      }
    ],
    "sg:phone": "+1 866 789 7846",
    "sg:postcode": "45209",
    "sg:province": "OH",
    "sg:tags": [
      "apartment",
      "rental",
      "finder"
    ],
    "sg:website": "http://cincinnati.citysearch.com/profile/external/8160789/cincinnati_oh/leesburg_lane_apts.html?publisher=yellowpages\u0026reference_id=1\u0026placement=ypwebsitemip",
    "wof:name": "Leesburg Lane Apts",
    "wof:placetype": "venue"
  },
  "geometry": {"coordinates":[-84.412281,39.152997],"type":"Point"}
}
