{
  "type": "Feature",
  "properties": {
    "addr:full":"24 Public Sq Cleveland OH 44113",
    "addr:housenumber":"24",
    "addr:postcode":"44113",
    "addr:street":"Public Sq",
    "iso:country":"US",
    "sg:address":"24 Public Sq",
    "sg:city":"Cleveland",
    "sg:classifiers":[
        {
            "category":"Organizations",
            "subcategory":"Membership Organization",
            "type":"Services"
        }
    ],
    "sg:phone":"+1 216 566 4622",
    "sg:postcode":"44113",
    "sg:province":"OH",
    "sg:tags":[
        "intercollegiate",
        "athletic",
        "regulatory",
        "association"
    ],
    "sg:website":"www.mac-sports.com",
    "wof:name":"Mid American Conference",
    "wof:placetype":"venue"
},
  "geometry": {"coordinates":[-81.694654,41.499511],"type":"Point"}
}