{
  "type": "Feature",
  "properties": {
    "addr:full": "1460 Timber Trl Stow OH 44236",
    "addr:housenumber": "1460",
    "addr:postcode": "44236",
    "addr:street": "Timber Trl",
    "iso:country": "US",
    "sg:address": "1460 Timber Trl",
    "sg:city": "Stow",
    "sg:classifiers": [
      {
        "category": "Real Estate",
        "subcategory": "Real Estate Operator",
        "type": "Services"
      }
    ],
    "sg:phone": "+1 330 928 5635",
    "sg:postcode": "44236",
    "sg:province": "OH",
    "sg:tags": [
      "building",
      "apartment"
    ],
    "wof:name": "Timberland Village Apartments",
    "wof:placetype": "venue"
  },
  "geometry": {"coordinates":[-81.459662,41.277257],"type":"Point"}
}
