{
  "type": "Feature",
  "properties": {
    "iso:country":"US",
    "sg:address":"3629 E 149th St",
    "sg:city":"Cleveland",
    "sg:classifiers":[
        {
            "category":"Building & Trades",
            "subcategory":"Construction",
            "type":"Services"
        }
    ],
    "sg:phone":"+1 216 214 2629",
    "sg:postcode":"44120",
    "sg:province":"OH",
    "sg:tags":[
        "excavation"
    ],
    "wof:name":"Tri-TEC Excavating Inc",
    "wof:placetype":"venue"
},
  "geometry": {"coordinates":[-81.577048,41.457582],"type":"Point"}
}