{
  "type": "Feature",
  "properties": {
    "addr:full":"906 Greenville Rd NE Cortland OH 44410",
    "addr:housenumber":"906",
    "addr:postcode":"44410",
    "addr:street":"Greenville Rd Ne",
    "iso:country":"US",
    "sg:address":"906 Greenville Rd NE",
    "sg:city":"Cortland",
    "sg:classifiers":[
        {
            "category":"Wholesale",
            "subcategory":"Motor Vehicles",
            "type":"Manufacturing & Wholesale Goods"
        }
    ],
    "sg:phone":"+1 330 638 2275",
    "sg:postcode":"44410",
    "sg:province":"OH",
    "sg:tags":[
        "automobile",
        "dealer"
    ],
    "wof:name":"88 Auto",
    "wof:placetype":"venue"
},
  "geometry": {"coordinates":[-80.776921,41.390411],"type":"Point"}
}