{
  "type": "Feature",
  "properties": {
    "iso:country":"US",
    "sg:address":"251 W Central Ave",
    "sg:city":"Springboro",
    "sg:classifiers":[
        {
            "category":"Building & Trades",
            "subcategory":"Construction",
            "type":"Services"
        }
    ],
    "sg:phone":"+1 937 746 7377",
    "sg:postcode":"45066",
    "sg:province":"OH",
    "sg:tags":[
        "contractor"
    ],
    "wof:name":"Rembrandt Enterprises Inc",
    "wof:placetype":"venue"
},
  "geometry": {"coordinates":[-84.23963500000001,39.558585],"type":"Point"}
}