{
  "type": "Feature",
  "properties": {
    "addr:full":"823 Haynes St Fremont OH 43420",
    "addr:housenumber":"823",
    "addr:postcode":"43420",
    "addr:street":"Haynes St",
    "iso:country":"US",
    "sg:address":"823 Haynes St",
    "sg:city":"Fremont",
    "sg:classifiers":[
        {
            "category":"Building & Trades",
            "subcategory":"Construction",
            "type":"Services"
        }
    ],
    "sg:phone":"+1 419 334 7376",
    "sg:postcode":"43420",
    "sg:province":"OH",
    "sg:tags":[
        "hanging",
        "painter",
        "contractor"
    ],
    "wof:name":"Brown Painting and Wallpaper",
    "wof:placetype":"venue"
},
  "geometry": {"coordinates":[-83.118604,41.357715],"type":"Point"}
}