{
  "type": "Feature",
  "properties": {
    "addr:full":"360 W Main St Conneaut OH 44030",
    "addr:housenumber":"360",
    "addr:postcode":"44030",
    "addr:street":"W Main St",
    "iso:country":"US",
    "sg:address":"360 W Main St",
    "sg:city":"Conneaut",
    "sg:classifiers":[
        {
            "category":"Shopping",
            "subcategory":"Tobacco",
            "type":"Retail Goods"
        }
    ],
    "sg:phone":"+1 440 593 6773",
    "sg:postcode":"44030",
    "sg:province":"OH",
    "sg:tags":[
        "product"
    ],
    "wof:name":"Cheap Tobacco",
    "wof:placetype":"venue"
},
  "geometry": {"coordinates":[-80.60260700000001,41.932886],"type":"Point"}
}