{
  "type": "Feature",
  "properties": {
    "iso:country":"US",
    "sg:address":"104 S Adams St",
    "sg:city":"Middle Point",
    "sg:classifiers":[
        {
            "category":"Bars & Pubs",
            "type":"Food & Drink"
        }
    ],
    "sg:phone":"+1 419 968 2493",
    "sg:postcode":"45863",
    "sg:province":"OH",
    "sg:tags":[
        "drinking"
    ],
    "wof:name":"Club II Tavern",
    "wof:placetype":"venue"
},
  "geometry": {"coordinates":[-84.446118,40.854351],"type":"Point"}
}