{
  "type": "Feature",
  "properties": {
    "addr:full": "104 S Adams St Middle Point OH 45863",
    "addr:housenumber": "104",
    "addr:postcode": "45863",
    "addr:street": "S Adams St",
    "iso:country": "US",
    "sg:address": "104 S Adams St",
    "sg:city": "Middle Point",
    "sg:classifiers": [
      {
        "category": "Bars \u0026 Pubs",
        "type": "Food \u0026 Drink"
      }
    ],
    "sg:phone": "+1 419 968 2493",
    "sg:postcode": "45863",
    "sg:province": "OH",
    "sg:tags": [
      "drinking"
    ],
    "wof:name": "Club II Tavern",
    "wof:placetype": "venue"
  },
  "geometry": {"coordinates":[-84.446118,40.854351],"type":"Point"}
}
