{
  "type": "Feature",
  "properties": {
    "iso:country":"US",
    "sg:address":"2028 Tiffin Ave",
    "sg:city":"Findlay",
    "sg:classifiers":[
        {
            "category":"Retail",
            "subcategory":"Auto Rental",
            "type":"Services"
        }
    ],
    "sg:phone":"+1 419 424 9626",
    "sg:postcode":"45840",
    "sg:province":"OH",
    "sg:tags":[
        "renting",
        "automobile"
    ],
    "sg:website":"www.enterprise.com",
    "wof:name":"Enterprise Rent A Car",
    "wof:placetype":"venue"
},
  "geometry": {"coordinates":[-83.604777,41.054325],"type":"Point"}
}