{
  "type": "Feature",
  "properties": {
    "addr:full": "4 W Main St Donnelsville OH 45371",
    "addr:housenumber": "4",
    "addr:postcode": "45371",
    "addr:street": "W Main St",
    "iso:country": "US",
    "sg:address": "4 W Main St",
    "sg:city": "Donnelsville",
    "sg:classifiers": [
      {
        "category": "Food \u0026 Beverages",
        "subcategory": "Groceries \u0026 Convenience Stores",
        "type": "Retail Goods"
      }
    ],
    "sg:phone": "+1 937 882 6901",
    "sg:postcode": "45371",
    "sg:province": "OH",
    "wof:name": "Donnelsville Mall",
    "wof:placetype": "venue"
  },
  "geometry": {"coordinates":[-84.171339,39.961155],"type":"Point"}
}
