{
  "type": "Feature",
  "properties": {
    "addr:full": "6131 Campus Ln Cincinnati OH 45230",
    "addr:housenumber": "6131",
    "addr:postcode": "45230",
    "addr:street": "Campus Ln",
    "iso:country": "US",
    "sg:address": "6131 Campus Ln",
    "sg:city": "Cincinnati",
    "sg:classifiers": [
      {
        "category": "Education",
        "subcategory": "Special Training",
        "type": "Public Place"
      }
    ],
    "sg:phone": "+1 513 231 2303",
    "sg:postcode": "45230",
    "sg:province": "OH",
    "sg:tags": [
      "instruction",
      "music"
    ],
    "wof:name": "Music Makers",
    "wof:placetype": "venue"
  },
  "geometry": {"coordinates":[-84.389597,39.091778],"type":"Point"}
}
