{
  "type": "Feature",
  "properties": {
    "addr:full":"1244 5th St SW Warren OH 44485",
    "addr:housenumber":"1244",
    "addr:postcode":"44485",
    "addr:street":"5Th St Sw",
    "iso:country":"US",
    "sg:address":"1244 5th St SW",
    "sg:city":"Warren",
    "sg:classifiers":[
        {
            "category":"Real Estate",
            "subcategory":"Real Estate Operator",
            "type":"Services"
        }
    ],
    "sg:phone":"+1 330 393 8900",
    "sg:postcode":"44485",
    "sg:province":"OH",
    "sg:tags":[
        "apartment"
    ],
    "wof:name":"Hampshire House",
    "wof:placetype":"venue"
},
  "geometry": {"coordinates":[-80.838745,41.22157],"type":"Point"}
}