{
  "type": "Feature",
  "properties": {
    "addr:full": "7100 Kepler Rd Clinton OH 44216",
    "addr:housenumber": "7100",
    "addr:postcode": "44216",
    "addr:street": "Kepler Rd",
    "iso:country": "US",
    "sg:address": "7100 Kepler Rd",
    "sg:city": "Clinton",
    "sg:classifiers": [
      {
        "category": "Building \u0026 Trades",
        "subcategory": "Construction",
        "type": "Services"
      }
    ],
    "sg:phone": "+1 330 494 4278",
    "sg:postcode": "44216",
    "sg:province": "OH",
    "sg:tags": [
      "downspouts",
      "gutter"
    ],
    "wof:name": "K-Solution Leaf Guard",
    "wof:placetype": "venue"
  },
  "geometry": {"coordinates":[-81.603233,40.931204],"type":"Point"}
}
