{
  "type": "Feature",
  "properties": {
    "addr:full":"39141 Farrington Rd Leetonia OH 44431",
    "addr:housenumber":"39141",
    "addr:postcode":"44431",
    "addr:street":"Farrington Rd",
    "iso:country":"US",
    "sg:address":"39141 Farrington Rd",
    "sg:city":"Leetonia",
    "sg:classifiers":[
        {
            "category":"Building & Trades",
            "subcategory":"Construction",
            "type":"Services"
        }
    ],
    "sg:phone":"+1 330 427 2561",
    "sg:postcode":"44431",
    "sg:province":"OH",
    "sg:tags":[
        "house"
    ],
    "wof:name":"Mitchell E Medved",
    "wof:placetype":"venue"
},
  "geometry": {"coordinates":[-80.76241899999999,40.854502],"type":"Point"}
}