{
  "type": "Feature",
  "properties": {
    "iso:country":"US",
    "sg:address":"807 Scioto St",
    "sg:city":"Urbana",
    "sg:classifiers":[
        {
            "category":"Banks & Credit Unions",
            "subcategory":"Bank",
            "type":"Services"
        }
    ],
    "sg:phone":"+1 937 484 5400",
    "sg:postcode":"43078",
    "sg:province":"OH",
    "sg:tags":[
        "cashing",
        "institution",
        "business",
        "check"
    ],
    "wof:name":"K Y Check Exchange",
    "wof:placetype":"venue"
},
  "geometry": {"coordinates":[-83.735001,40.107017],"type":"Point"}
}