{
  "type": "Feature",
  "properties": {
    "addr:full": "164 Millfield Ave Westerville OH 43081",
    "addr:housenumber": "164",
    "addr:postcode": "43081",
    "addr:street": "Millfield Ave",
    "iso:country": "US",
    "sg:address": "164 Millfield Ave",
    "sg:city": "Westerville",
    "sg:classifiers": [
      {
        "category": "Home \u0026 Garden",
        "subcategory": "Furniture",
        "type": "Retail Goods"
      }
    ],
    "sg:phone": "+1 614 440 3779",
    "sg:postcode": "43081",
    "sg:province": "OH",
    "sg:tags": [
      "bed"
    ],
    "wof:name": "Bunk Bed Bonanza",
    "wof:placetype": "venue"
  },
  "geometry": {"coordinates":[-82.955309,40.127364],"type":"Point"}
}
