{
  "type": "Feature",
  "properties": {
    "addr:full":"1990 Higby Rd Chillicothe OH 45601",
    "addr:housenumber":"1990",
    "addr:postcode":"45601",
    "addr:street":"Higby Rd",
    "iso:country":"US",
    "sg:address":"1990 Higby Rd",
    "sg:city":"Chillicothe",
    "sg:phone":"+1 740 947 5156",
    "sg:postcode":"45601",
    "sg:province":"OH",
    "sg:tags":[
        "farm",
        "corn"
    ],
    "wof:name":"Graves Brothers",
    "wof:placetype":"venue"
},
  "geometry": {"coordinates":[-82.894391,39.17014],"type":"Point"}
}