{
  "type": "Feature",
  "properties": {
    "iso:country":"US",
    "sg:address":"15919 Industrial Pkwy",
    "sg:city":"Cleveland",
    "sg:classifiers":[
        {
            "category":"Manufacturing",
            "subcategory":"Apparel",
            "type":"Manufacturing & Wholesale Goods"
        }
    ],
    "sg:phone":"+1 216 267 0664",
    "sg:postcode":"44135",
    "sg:province":"OH",
    "sg:tags":[
        "cap",
        "hat",
        "millinery"
    ],
    "wof:name":"Big Play",
    "wof:placetype":"venue"
},
  "geometry": {"coordinates":[-81.811682,41.425346],"type":"Point"}
}