{
  "type": "Feature",
  "properties": {
    "iso:country":"US",
    "sg:address":"600 Cherry Fork Ave",
    "sg:city":"Leetonia",
    "sg:classifiers":[
        {
            "category":"Professional",
            "subcategory":"Engineering",
            "type":"Services"
        }
    ],
    "sg:phone":"+1 330 427 2729",
    "sg:postcode":"44431",
    "sg:province":"OH",
    "sg:tags":[
        "engineer"
    ],
    "wof:name":"DMS Bliss",
    "wof:placetype":"venue"
},
  "geometry": {"coordinates":[-80.743104,40.878191],"type":"Point"}
}