{
  "type": "Feature",
  "properties": {
    "addr:full":"441 Fairgrounds Rd Painesville OH 44077",
    "addr:housenumber":"441",
    "addr:postcode":"44077",
    "addr:street":"Fairgrounds Rd",
    "iso:country":"US",
    "sg:address":"441 Fairgrounds Rd",
    "sg:city":"Painesville",
    "sg:classifiers":[
        {
            "category":"Building & Trades",
            "subcategory":"Plumbing",
            "type":"Services"
        }
    ],
    "sg:phone":"+1 440 350 1200",
    "sg:postcode":"44077",
    "sg:province":"OH",
    "sg:tags":[
        "heating",
        "contractor"
    ],
    "wof:name":"Shore Mechanical",
    "wof:placetype":"venue"
},
  "geometry": {"coordinates":[-81.268016,41.695804],"type":"Point"}
}