{
  "type": "Feature",
  "properties": {
    "iso:country":"US",
    "sg:address":"2223 Auburn Ave",
    "sg:city":"Cincinnati",
    "sg:classifiers":[
        {
            "category":"Health Services",
            "subcategory":"Doctor",
            "type":"Services"
        }
    ],
    "sg:phone":"+1 513 721 2024",
    "sg:postcode":"45219",
    "sg:province":"OH",
    "sg:tags":[
        "physician",
        "surgeon"
    ],
    "wof:name":"Martin W Brueggemann MD",
    "wof:placetype":"venue"
},
  "geometry": {"coordinates":[-84.508521,39.122332],"type":"Point"}
}