{
  "type": "Feature",
  "properties": {
    "addr:full": "2223 Auburn Ave Cincinnati OH 45219",
    "addr:housenumber": "2223",
    "addr:postcode": "45219",
    "addr:street": "Auburn Ave",
    "iso:country": "US",
    "sg:address": "2223 Auburn Ave",
    "sg:city": "Cincinnati",
    "sg:classifiers": [
      {
        "category": "Health Services",
        "subcategory": "Doctor",
        "type": "Services"
      }
    ],
    "sg:phone": "+1 513 721 2024",
    "sg:postcode": "45219",
    "sg:province": "OH",
    "sg:tags": [
      "physician",
      "surgeon"
    ],
    "wof:name": "Martin W Brueggemann MD",
    "wof:placetype": "venue"
  },
  "geometry": {"coordinates":[-84.508521,39.122332],"type":"Point"}
}
