{
  "type": "Feature",
  "properties": {
    "iso:country":"US",
    "sg:address":"2812 Shadow Falls Ln",
    "sg:city":"Columbus",
    "sg:classifiers":[
        {
            "category":"Home & Garden",
            "subcategory":"Home Furnishings",
            "type":"Retail Goods"
        }
    ],
    "sg:phone":"+1 614 899 2549",
    "sg:postcode":"43231",
    "sg:province":"OH",
    "sg:tags":[
        "blanket"
    ],
    "wof:name":"Quilt Trends",
    "wof:placetype":"venue"
},
  "geometry": {"coordinates":[-82.94195999999999,40.096902],"type":"Point"}
}