{
  "type": "Feature",
  "properties": {
    "iso:country":"US",
    "sg:address":"1825 Homewood Dr",
    "sg:city":"Lorain",
    "sg:classifiers":[
        {
            "category":"Government",
            "subcategory":"Office",
            "type":"Public Place"
        }
    ],
    "sg:phone":"+1 440 277 0290",
    "sg:postcode":"44055",
    "sg:province":"OH",
    "sg:tags":[
        "building",
        "operator",
        "apartment"
    ],
    "wof:name":"International Plaza",
    "wof:placetype":"venue"
},
  "geometry": {"coordinates":[-82.135885,41.435823],"type":"Point"}
}