{
  "type": "Feature",
  "properties": {
    "addr:full": "123 Rustic Rook Dr Willard OH 44890",
    "addr:housenumber": "123",
    "addr:postcode": "44890",
    "addr:street": "Rustic Rook Dr",
    "iso:country": "US",
    "sg:address": "123 Rustic Rook Dr",
    "sg:city": "Willard",
    "sg:classifiers": [
      {
        "category": "Professional",
        "type": "Services"
      }
    ],
    "sg:phone": "+1 419 935 0121",
    "sg:postcode": "44890",
    "sg:province": "OH",
    "sg:tags": [
      "establishment"
    ],
    "wof:name": "VHD LTD",
    "wof:placetype": "venue"
  },
  "geometry": {"coordinates":[-82.736543,41.093171],"type":"Point"}
}
