{
  "type": "Feature",
  "properties": {
    "addr:full":"502 Beamsville-Union City Rd Union City OH 45390",
    "addr:housenumber":"502",
    "addr:postcode":"45390",
    "addr:street":"Beamsville-Union City Rd",
    "iso:country":"US",
    "sg:address":"502 Beamsville-Union City Rd",
    "sg:city":"Union City",
    "sg:classifiers":[
        {
            "category":"Government",
            "subcategory":"Office",
            "type":"Public Place"
        }
    ],
    "sg:phone":"+1 937 968 6198",
    "sg:postcode":"45390",
    "sg:province":"OH",
    "sg:tags":[
        "village"
    ],
    "wof:name":"Union City Sewage Plant",
    "wof:placetype":"venue"
},
  "geometry": {"coordinates":[-84.78448899999999,40.193715],"type":"Point"}
}