{
  "type": "Feature",
  "properties": {
    "addr:full": "232 Rigrish Rd Portsmouth OH 45662",
    "addr:housenumber": "232",
    "addr:postcode": "45662",
    "addr:street": "Rigrish Rd",
    "iso:country": "US",
    "sg:address": "232 Rigrish Rd",
    "sg:city": "Portsmouth",
    "sg:classifiers": [
      {
        "category": "Professional",
        "type": "Services"
      }
    ],
    "sg:phone": "+1 740 776 7533",
    "sg:postcode": "45662",
    "sg:province": "OH",
    "wof:name": "Holbrook John",
    "wof:placetype": "venue"
  },
  "geometry": {"coordinates":[-82.857293,38.776369],"type":"Point"}
}
