{
  "type": "Feature",
  "properties": {
    "iso:country":"US",
    "sg:address":"7880 Market St",
    "sg:city":"Youngstown",
    "sg:classifiers":[
        {
            "category":"Retail",
            "subcategory":"Auto Repair",
            "type":"Services"
        }
    ],
    "sg:phone":"+1 330 965 7360",
    "sg:postcode":"44512",
    "sg:province":"OH",
    "sg:tags":[
        "automobile",
        "rustproofing",
        "undercoating"
    ],
    "wof:name":"Ziebart Boardman",
    "wof:placetype":"venue"
},
  "geometry": {"coordinates":[-80.662827,41.007174],"type":"Point"}
}