{
  "type": "Feature",
  "properties": {
    "addr:full": "4205 Stow Rd Stow OH 44224",
    "addr:housenumber": "4205",
    "addr:postcode": "44224",
    "addr:street": "Stow Rd",
    "iso:country": "US",
    "sg:address": "4205 Stow Rd",
    "sg:city": "Stow",
    "sg:classifiers": [
      {
        "category": "Manufacturing",
        "subcategory": "Tools \u0026 Machinery",
        "type": "Manufacturing \u0026 Wholesale Goods"
      }
    ],
    "sg:phone": "+1 330 688 6704",
    "sg:postcode": "44224",
    "sg:province": "OH",
    "sg:tags": [
      "die",
      "cutting"
    ],
    "wof:name": "All Ways Packaging",
    "wof:placetype": "venue"
  },
  "geometry": {"coordinates":[-81.430785,41.178018],"type":"Point"}
}
