{
  "type": "Feature",
  "properties": {
    "iso:country":"US",
    "sg:address":"4205 Stow Rd",
    "sg:city":"Stow",
    "sg:classifiers":[
        {
            "category":"Manufacturing",
            "subcategory":"Tools & Machinery",
            "type":"Manufacturing & Wholesale Goods"
        }
    ],
    "sg:phone":"+1 330 688 6704",
    "sg:postcode":"44224",
    "sg:province":"OH",
    "sg:tags":[
        "die",
        "cutting"
    ],
    "wof:name":"All Ways Packaging",
    "wof:placetype":"venue"
},
  "geometry": {"coordinates":[-81.430785,41.178018],"type":"Point"}
}