{
  "type": "Feature",
  "properties": {
    "addr:full":"5245 N Bend Rd Cincinnati OH 45247",
    "addr:housenumber":"5245",
    "addr:postcode":"45247",
    "addr:street":"N Bend Rd",
    "iso:country":"US",
    "sg:address":"5245 N Bend Rd",
    "sg:city":"Cincinnati",
    "sg:classifiers":[
        {
            "category":"Restaurant",
            "type":"Food & Drink"
        }
    ],
    "sg:menulink":"http://www.allmenus.com/oh/bridgetown-north/41809-bob-evans/menu/",
    "sg:phone":"+1 513 661 3321",
    "sg:postcode":"45247",
    "sg:province":"OH",
    "sg:tags":[
        "american"
    ],
    "wof:name":"Bob Evans",
    "wof:placetype":"venue"
},
  "geometry": {"coordinates":[-84.60424500000001,39.183174],"type":"Point"}
}