{
  "type": "Feature",
  "properties": {
    "iso:country":"US",
    "sg:address":"311 Laquineo St",
    "sg:city":"Findlay",
    "sg:classifiers":[
        {
            "category":"Wholesale",
            "subcategory":"Metals & Minerals",
            "type":"Manufacturing & Wholesale Goods"
        }
    ],
    "sg:phone":"+1 419 422 9632",
    "sg:postcode":"45840",
    "sg:province":"OH",
    "sg:tags":[
        "steel",
        "warehouse"
    ],
    "wof:name":"Sausser Steel Co",
    "wof:placetype":"venue"
},
  "geometry": {"coordinates":[-83.64505800000001,41.052465],"type":"Point"}
}