{
  "type": "Feature",
  "properties": {
    "addr:full": "311 Laquineo St Findlay OH 45840",
    "addr:housenumber": "311",
    "addr:postcode": "45840",
    "addr:street": "Laquineo St",
    "iso:country": "US",
    "sg:address": "311 Laquineo St",
    "sg:city": "Findlay",
    "sg:classifiers": [
      {
        "category": "Wholesale",
        "subcategory": "Metals \u0026 Minerals",
        "type": "Manufacturing \u0026 Wholesale Goods"
      }
    ],
    "sg:phone": "+1 419 422 9632",
    "sg:postcode": "45840",
    "sg:province": "OH",
    "sg:tags": [
      "steel",
      "warehouse"
    ],
    "wof:name": "Sausser Steel Co",
    "wof:placetype": "venue"
  },
  "geometry": {"coordinates":[-83.645058,41.052465],"type":"Point"}
}
