{
  "type": "Feature",
  "properties": {
    "addr:full": "3610 Columbia Pkwy Cincinnati OH 45226",
    "addr:housenumber": "3610",
    "addr:postcode": "45226",
    "addr:street": "Columbia Pkwy",
    "iso:country": "US",
    "sg:address": "3610 Columbia Pkwy",
    "sg:city": "Cincinnati",
    "sg:classifiers": [
      {
        "category": "Building \u0026 Trades",
        "subcategory": "Construction",
        "type": "Services"
      }
    ],
    "sg:phone": "+1 513 577 0213",
    "sg:postcode": "45226",
    "sg:province": "OH",
    "sg:tags": [
      "roofing",
      "contractor"
    ],
    "wof:name": "Mike's Roofing",
    "wof:placetype": "venue"
  },
  "geometry": {"coordinates":[-84.43533,39.113937],"type":"Point"}
}
