{
  "type": "Feature",
  "properties": {
    "iso:country":"US",
    "sg:address":"3610 Columbia Pkwy",
    "sg:city":"Cincinnati",
    "sg:classifiers":[
        {
            "category":"Building & Trades",
            "subcategory":"Construction",
            "type":"Services"
        }
    ],
    "sg:phone":"+1 513 577 0213",
    "sg:postcode":"45226",
    "sg:province":"OH",
    "sg:tags":[
        "roofing",
        "contractor"
    ],
    "wof:name":"Mike's Roofing",
    "wof:placetype":"venue"
},
  "geometry": {"coordinates":[-84.43532999999999,39.113937],"type":"Point"}
}