{
  "type": "Feature",
  "properties": {
    "iso:country":"US",
    "sg:address":"480 Randy Ln",
    "sg:city":"Monroe",
    "sg:classifiers":[
        {
            "category":"Shopping",
            "type":"Retail Goods"
        }
    ],
    "sg:phone":"+1 513 777 9798",
    "sg:postcode":"45050",
    "sg:province":"OH",
    "sg:tags":[
        "fire",
        "repair",
        "installation",
        "sprinkler"
    ],
    "wof:name":"Guardian Fire Protection LLC",
    "wof:placetype":"venue"
},
  "geometry": {"coordinates":[-84.355666,39.42527],"type":"Point"}
}