{
  "type": "Feature",
  "properties": {
    "addr:full":"1150 S Metcalf St Lima OH 45804",
    "addr:housenumber":"1150",
    "addr:postcode":"45804",
    "addr:street":"S Metcalf St",
    "iso:country":"US",
    "sg:address":"1150 S Metcalf St",
    "sg:city":"Lima",
    "sg:classifiers":[
        {
            "category":"Freight",
            "type":"Transportation"
        },
        {
            "category":"Building & Trades",
            "subcategory":"Construction",
            "type":"Services"
        }
    ],
    "sg:phone":"+1 419 227 5111",
    "sg:postcode":"45804",
    "sg:province":"OH",
    "sg:tags":[
        "repair",
        "railroad",
        "car",
        "contractor"
    ],
    "wof:name":"Rescar Inc",
    "wof:placetype":"venue"
},
  "geometry": {"coordinates":[-84.113191,40.722029],"type":"Point"}
}