{
  "type": "Feature",
  "properties": {
    "iso:country":"US",
    "sg:address":"81 S 4th St",
    "sg:city":"Columbus",
    "sg:classifiers":[
        {
            "category":"Health Services",
            "subcategory":"Doctor",
            "type":"Services"
        }
    ],
    "sg:phone":"+1 614 224 5294",
    "sg:postcode":"43215",
    "sg:province":"OH",
    "sg:tags":[
        "physician",
        "surgeon"
    ],
    "wof:name":"Raymond De Levie MD",
    "wof:placetype":"venue"
},
  "geometry": {"coordinates":[-82.995972,39.960964],"type":"Point"}
}