{
  "type": "Feature",
  "properties": {
    "addr:full":"6368 Nave St SW Canton OH 44706",
    "addr:housenumber":"6368",
    "addr:postcode":"44706",
    "addr:street":"Nave St Sw",
    "iso:country":"US",
    "sg:address":"6368 Nave St SW",
    "sg:city":"Canton",
    "sg:classifiers":[
        {
            "category":"Retail",
            "subcategory":"Veterinary Services",
            "type":"Services"
        }
    ],
    "sg:phone":"+1 330 833 0037",
    "sg:postcode":"44706",
    "sg:province":"OH",
    "wof:name":"Hill-Crest Veterinary Hospital",
    "wof:placetype":"venue"
},
  "geometry": {"coordinates":[-81.470698,40.767994],"type":"Point"}
}