{
  "type": "Feature",
  "properties": {
    "addr:full": "5834 Monroe St Sylvania OH 43560",
    "addr:housenumber": "5834",
    "addr:postcode": "43560",
    "addr:street": "Monroe St",
    "iso:country": "US",
    "sg:address": "5834 Monroe St",
    "sg:city": "Sylvania",
    "sg:classifiers": [
      {
        "category": "Building \u0026 Trades",
        "subcategory": "Construction",
        "type": "Services"
      }
    ],
    "sg:phone": "+1 419 475 1996",
    "sg:postcode": "43560",
    "sg:province": "OH",
    "sg:tags": [
      "contractor"
    ],
    "wof:name": "Construction Management Plus",
    "wof:placetype": "venue"
  },
  "geometry": {"coordinates":[-83.68084,41.711628],"type":"Point"}
}
