{
  "type": "Feature",
  "properties": {
    "addr:full": "927 W Main St Louisville OH 44641",
    "addr:housenumber": "927",
    "addr:postcode": "44641",
    "addr:street": "W Main St",
    "iso:country": "US",
    "sg:address": "927 W Main St",
    "sg:city": "Louisville",
    "sg:classifiers": [
      {
        "category": "Retail",
        "subcategory": "Portrait Studio",
        "type": "Services"
      }
    ],
    "sg:phone": "+1 330 875 5800",
    "sg:postcode": "44641",
    "sg:province": "OH",
    "sg:tags": [
      "photographer"
    ],
    "sg:website": "www.rickblackphoto.com",
    "wof:name": "Rick Black Photography",
    "wof:placetype": "venue"
  },
  "geometry": {"coordinates":[-81.269814,40.836633],"type":"Point"}
}
