{
  "type": "Feature",
  "properties": {
    "addr:full":"4500 Groves Rd Columbus OH 43232",
    "addr:housenumber":"4500",
    "addr:postcode":"43232",
    "addr:street":"Groves Rd",
    "iso:country":"US",
    "sg:address":"4500 Groves Rd",
    "sg:city":"Columbus",
    "sg:classifiers":[
        {
            "category":"Wholesale",
            "subcategory":"Groceries",
            "type":"Manufacturing & Wholesale Goods"
        }
    ],
    "sg:phone":"+1 614 863 7200",
    "sg:postcode":"43232",
    "sg:province":"OH",
    "wof:name":"Coca-Cola",
    "wof:placetype":"venue"
},
  "geometry": {"coordinates":[-82.873542,39.929949],"type":"Point"}
}