{
  "type": "Feature",
  "properties": {
    "iso:country":"US",
    "sg:address":"4601 Vine St",
    "sg:city":"Cincinnati",
    "sg:classifiers":[
        {
            "category":"Restaurant",
            "type":"Food & Drink"
        }
    ],
    "sg:phone":"+1 513 347 1111",
    "sg:postcode":"45217",
    "sg:province":"OH",
    "sg:website":"www.larosas.com",
    "wof:name":"LA Rosa's Inc",
    "wof:placetype":"venue"
},
  "geometry": {"coordinates":[-84.500348,39.166067],"type":"Point"}
}