{
  "type": "Feature",
  "properties": {
    "iso:country":"US",
    "sg:address":"23151 State Rte 56",
    "sg:city":"S Bloomingville",
    "sg:classifiers":[
        {
            "category":"Utilities",
            "subcategory":"Natural Gas",
            "type":"Services"
        }
    ],
    "sg:phone":"+1 740 332 7102",
    "sg:postcode":"43152",
    "sg:province":"OH",
    "sg:tags":[
        "company"
    ],
    "wof:name":"Columbia Gas Transmission Corp",
    "wof:placetype":"venue"
},
  "geometry": {"coordinates":[-82.606943,39.41403],"type":"Point"}
}