{
  "type": "Feature",
  "properties": {
    "iso:country":"US",
    "sg:address":"1637 E US Hwy 36",
    "sg:city":"Urbana",
    "sg:classifiers":[
        {
            "category":"Shopping",
            "subcategory":"Books",
            "type":"Retail Goods"
        }
    ],
    "sg:phone":"+1 937 652 1531",
    "sg:postcode":"43078",
    "sg:province":"OH",
    "sg:tags":[
        "dealer"
    ],
    "wof:name":"Ole Book Nook",
    "wof:placetype":"venue"
},
  "geometry": {"coordinates":[-83.721406,40.106148],"type":"Point"}
}