{
  "type": "Feature",
  "properties": {
    "addr:full": "4597 Riegel Ridge Rd Jackson OH 45640",
    "addr:housenumber": "4597",
    "addr:postcode": "45640",
    "addr:street": "Riegel Ridge Rd",
    "iso:country": "US",
    "sg:address": "4597 Riegel Ridge Rd",
    "sg:city": "Jackson",
    "sg:classifiers": [
      {
        "category": "Farming",
        "subcategory": "Farm",
        "type": "Manufacturing \u0026 Wholesale Goods"
      }
    ],
    "sg:phone": "+1 740 286 5454",
    "sg:postcode": "45640",
    "sg:province": "OH",
    "sg:tags": [
      "crop",
      "general"
    ],
    "wof:name": "J \u0026 J Farms",
    "wof:placetype": "venue"
  },
  "geometry": {"coordinates":[-82.705805,38.945553],"type":"Point"}
}
