{
  "type": "Feature",
  "properties": {
    "iso:country":"US",
    "sg:address":"4597 Riegel Ridge Rd",
    "sg:city":"Jackson",
    "sg:classifiers":[
        {
            "category":"Farming",
            "subcategory":"Farm",
            "type":"Manufacturing & Wholesale Goods"
        }
    ],
    "sg:phone":"+1 740 286 5454",
    "sg:postcode":"45640",
    "sg:province":"OH",
    "sg:tags":[
        "crop",
        "general"
    ],
    "wof:name":"J & J Farms",
    "wof:placetype":"venue"
},
  "geometry": {"coordinates":[-82.705805,38.945553],"type":"Point"}
}