{
  "type": "Feature",
  "properties": {
    "addr:full": "2 E Main St Norwalk OH 44857",
    "addr:housenumber": "2",
    "addr:postcode": "44857",
    "addr:street": "E Main St",
    "iso:country": "US",
    "sg:address": "2 E Main St",
    "sg:city": "Norwalk",
    "sg:classifiers": [
      {
        "category": "Government",
        "subcategory": "Court House",
        "type": "Public Place"
      }
    ],
    "sg:phone": "+1 419 668 1616",
    "sg:postcode": "44857",
    "sg:province": "OH",
    "wof:name": "County of Huron",
    "wof:placetype": "venue"
  },
  "geometry": {"coordinates":[-82.614586,41.242813],"type":"Point"}
}
