{
  "type": "Feature",
  "properties": {
    "iso:country":"US",
    "sg:address":"193 Taylor James Blvd",
    "sg:city":"Wadsworth",
    "sg:classifiers":[
        {
            "category":"Professional",
            "subcategory":"Lawyer & Legal Services",
            "type":"Services"
        }
    ],
    "sg:phone":"+1 330 239 2951",
    "sg:postcode":"44281",
    "sg:province":"OH",
    "sg:tags":[
        "attorney"
    ],
    "wof:name":"Andrew Michaels Attorney",
    "wof:placetype":"venue"
},
  "geometry": {"coordinates":[-81.68832500000001,41.106406],"type":"Point"}
}