{
  "type": "Feature",
  "properties": {
    "addr:full": "193 Taylor James Blvd Wadsworth OH 44281",
    "addr:housenumber": "193",
    "addr:postcode": "44281",
    "addr:street": "Taylor James Blvd",
    "iso:country": "US",
    "sg:address": "193 Taylor James Blvd",
    "sg:city": "Wadsworth",
    "sg:classifiers": [
      {
        "category": "Professional",
        "subcategory": "Lawyer \u0026 Legal Services",
        "type": "Services"
      }
    ],
    "sg:phone": "+1 330 239 2951",
    "sg:postcode": "44281",
    "sg:province": "OH",
    "sg:tags": [
      "attorney"
    ],
    "wof:name": "Andrew Michaels Attorney",
    "wof:placetype": "venue"
  },
  "geometry": {"coordinates":[-81.688325,41.106406],"type":"Point"}
}
