{
  "type": "Feature",
  "properties": {
    "addr:full":"9479 Co Rd 550 Chillicothe OH 45601",
    "addr:housenumber":"9479;550",
    "addr:postcode":"45601",
    "addr:street":"Co Rd",
    "iso:country":"US",
    "sg:address":"9479 Co Rd 550",
    "sg:city":"Chillicothe",
    "sg:classifiers":[
        {
            "category":"Building & Trades",
            "subcategory":"Construction",
            "type":"Services"
        }
    ],
    "sg:phone":"+1 740 773 8047",
    "sg:postcode":"45601",
    "sg:province":"OH",
    "sg:tags":[
        "excavation",
        "contractor"
    ],
    "wof:name":"Page Excavating",
    "wof:placetype":"venue"
},
  "geometry": {"coordinates":[-83.09798499999999,39.384142],"type":"Point"}
}