{
  "type": "Feature",
  "properties": {
    "iso:country":"US",
    "sg:address":"710 Elm St",
    "sg:city":"Cincinnati",
    "sg:classifiers":[
        {
            "category":"Parking",
            "type":"Transportation"
        }
    ],
    "sg:phone":"+1 513 651 0715",
    "sg:postcode":"45202",
    "sg:province":"OH",
    "sg:tags":[
        "garage"
    ],
    "wof:name":"Gramercy Garage",
    "wof:placetype":"venue"
},
  "geometry": {"coordinates":[-84.516808,39.10333],"type":"Point"}
}