{
  "type": "Feature",
  "properties": {
    "addr:full": "710 Elm St Cincinnati OH 45202",
    "addr:housenumber": "710",
    "addr:postcode": "45202",
    "addr:street": "Elm St",
    "iso:country": "US",
    "sg:address": "710 Elm St",
    "sg:city": "Cincinnati",
    "sg:classifiers": [
      {
        "category": "Parking",
        "type": "Transportation"
      }
    ],
    "sg:phone": "+1 513 651 0715",
    "sg:postcode": "45202",
    "sg:province": "OH",
    "sg:tags": [
      "garage"
    ],
    "wof:name": "Gramercy Garage",
    "wof:placetype": "venue"
  },
  "geometry": {"coordinates":[-84.516808,39.10333],"type":"Point"}
}
