{
  "type": "Feature",
  "properties": {
    "iso:country":"US",
    "sg:address":"4410 Simon Rd",
    "sg:city":"Youngstown",
    "sg:classifiers":[
        {
            "category":"Manufacturing",
            "subcategory":"Tools & Machinery",
            "type":"Manufacturing & Wholesale Goods"
        }
    ],
    "sg:phone":"+1 330 782 8139",
    "sg:postcode":"44512",
    "sg:province":"OH",
    "sg:tags":[
        "die",
        "maker"
    ],
    "wof:name":"Fabco Tool & Machine Inc",
    "wof:placetype":"venue"
},
  "geometry": {"coordinates":[-80.637868,41.05653],"type":"Point"}
}