{
  "type": "Feature",
  "properties": {
    "addr:full": "4410 Simon Rd Youngstown OH 44512",
    "addr:housenumber": "4410",
    "addr:postcode": "44512",
    "addr:street": "Simon Rd",
    "iso:country": "US",
    "sg:address": "4410 Simon Rd",
    "sg:city": "Youngstown",
    "sg:classifiers": [
      {
        "category": "Manufacturing",
        "subcategory": "Tools \u0026 Machinery",
        "type": "Manufacturing \u0026 Wholesale Goods"
      }
    ],
    "sg:phone": "+1 330 782 8139",
    "sg:postcode": "44512",
    "sg:province": "OH",
    "sg:tags": [
      "die",
      "maker"
    ],
    "wof:name": "Fabco Tool \u0026 Machine Inc",
    "wof:placetype": "venue"
  },
  "geometry": {"coordinates":[-80.637868,41.05653],"type":"Point"}
}
