{
  "type": "Feature",
  "properties": {
    "addr:full": "530 W Hicks St Upper Sandusky OH 43351",
    "addr:housenumber": "530",
    "addr:postcode": "43351",
    "addr:street": "W Hicks St",
    "iso:country": "US",
    "sg:address": "530 W Hicks St",
    "sg:city": "Upper Sandusky",
    "sg:classifiers": [
      {
        "category": "Building \u0026 Trades",
        "subcategory": "Landscaping Services",
        "type": "Services"
      }
    ],
    "sg:phone": "+1 419 294 3967",
    "sg:postcode": "43351",
    "sg:province": "OH",
    "wof:name": "Baldwins Tree Service",
    "wof:placetype": "venue"
  },
  "geometry": {"coordinates":[-83.289665,40.82496],"type":"Point"}
}
