{
  "type": "Feature",
  "properties": {
    "iso:country":"US",
    "sg:address":"655 Robinwood Ave",
    "sg:city":"Sheffield Lake",
    "sg:classifiers":[
        {
            "category":"Professional",
            "type":"Services"
        }
    ],
    "sg:phone":"+1 440 949 2427",
    "sg:postcode":"44054",
    "sg:province":"OH",
    "wof:name":"Ragon Systems Inc",
    "wof:placetype":"venue"
},
  "geometry": {"coordinates":[-82.095511,41.488291],"type":"Point"}
}