{
  "type": "Feature",
  "properties": {
    "iso:country":"US",
    "sg:address":"1110 Castalia St",
    "sg:city":"Bellevue",
    "sg:classifiers":[
        {
            "category":"Health Services",
            "subcategory":"Health Practitioner",
            "type":"Services"
        }
    ],
    "sg:phone":"+1 419 483 1518",
    "sg:postcode":"44811",
    "sg:province":"OH",
    "sg:tags":[
        "therapist",
        "physical"
    ],
    "wof:name":"P T Svc Rehabilitation Inc",
    "wof:placetype":"venue"
},
  "geometry": {"coordinates":[-82.836286,41.288432],"type":"Point"}
}