{
  "type": "Feature",
  "properties": {
    "iso:country":"US",
    "sg:address":"9217 Granville Rd",
    "sg:city":"Mount Vernon",
    "sg:classifiers":[
        {
            "category":"Health Services",
            "subcategory":"Clinic",
            "type":"Services"
        }
    ],
    "sg:phone":"+1 740 393 0111",
    "sg:postcode":"43050",
    "sg:province":"OH",
    "sg:tags":[
        "home",
        "care"
    ],
    "wof:name":"Heartland Healthcare Services",
    "wof:placetype":"venue"
},
  "geometry": {"coordinates":[-82.489345,40.369076],"type":"Point"}
}