{
  "type": "Feature",
  "properties": {
    "addr:full":"2021 Sunset Blvd Steubenville OH 43952",
    "addr:housenumber":"2021",
    "addr:postcode":"43952",
    "addr:street":"Sunset Blvd",
    "iso:country":"US",
    "sg:address":"2021 Sunset Blvd",
    "sg:city":"Steubenville",
    "sg:classifiers":[
        {
            "category":"Professional",
            "subcategory":"Lawyer & Legal Services",
            "type":"Services"
        },
        {
            "category":"Banks & Credit Unions",
            "subcategory":"Financial Services",
            "type":"Services"
        },
        {
            "category":"Home & Garden",
            "subcategory":"Carpets & Floor Coverings",
            "type":"Retail Goods"
        }
    ],
    "sg:phone":"+1 740 314 1923",
    "sg:postcode":"43952",
    "sg:province":"OH",
    "sg:tags":[
        "attorney",
        "retirement",
        "estate",
        "wills",
        "elder",
        "planning",
        "security",
        "trust",
        "probate",
        "investment",
        "law"
    ],
    "sg:website":"http://www.elderlyplanningsvcs.com",
    "wof:name":"LaRue David A Esq PLLC",
    "wof:placetype":"venue"
},
  "geometry": {"coordinates":[-80.63601300000001,40.369552],"type":"Point"}
}