{
  "type": "Feature",
  "properties": {
    "addr:full": "9651 State Rte 202 Tipp City OH 45371",
    "addr:housenumber": "9651",
    "addr:postcode": "45371",
    "addr:street": "State Rte 202",
    "iso:country": "US",
    "sg:address": "9651 State Rte 202",
    "sg:city": "Tipp City",
    "sg:classifiers": [
      {
        "category": "Real Estate",
        "subcategory": "Real Estate Operator",
        "type": "Services"
      }
    ],
    "sg:phone": "+1 937 667 0012",
    "sg:postcode": "45371",
    "sg:province": "OH",
    "sg:tags": [
      "condominium"
    ],
    "wof:name": "Villas At Benchrock",
    "wof:placetype": "venue"
  },
  "geometry": {"coordinates":[-84.135377,39.892071],"type":"Point"}
}
