{
  "type": "Feature",
  "properties": {
    "iso:country":"US",
    "sg:address":"10 N 2nd St",
    "sg:city":"Batavia",
    "sg:classifiers":[
        {
            "category":"Organizations",
            "subcategory":"Professional Association",
            "type":"Services"
        }
    ],
    "sg:phone":"+1 513 732 2378",
    "sg:postcode":"45103",
    "sg:province":"OH",
    "wof:name":"Clermont County Democratic",
    "wof:placetype":"venue"
},
  "geometry": {"coordinates":[-84.17711199999999,39.077428],"type":"Point"}
}