{
  "type": "Feature",
  "properties": {
    "addr:full":"10342 State Rte 305 Garrettsville OH 44231",
    "addr:housenumber":"10342",
    "addr:postcode":"44231",
    "addr:street":"State Rte 305",
    "iso:country":"US",
    "sg:address":"10342 State Rte 305",
    "sg:city":"Garrettsville",
    "sg:classifiers":[
        {
            "category":"Recreation",
            "type":"Entertainment"
        }
    ],
    "sg:phone":"+1 440 548 8551",
    "sg:postcode":"44231",
    "sg:province":"OH",
    "sg:tags":[
        "amusement"
    ],
    "wof:name":"Nelson Ledges Road Course",
    "wof:placetype":"venue"
},
  "geometry": {"coordinates":[-81.013514,41.309923],"type":"Point"}
}