{
  "type": "Feature",
  "properties": {
    "addr:full": "3619 Walton Ave Cleveland OH 44113",
    "addr:housenumber": "3619",
    "addr:postcode": "44113",
    "addr:street": "Walton Ave",
    "iso:country": "US",
    "sg:address": "3619 Walton Ave",
    "sg:city": "Cleveland",
    "sg:classifiers": [
      {
        "category": "Manufacturing",
        "subcategory": "Tools \u0026 Machinery",
        "type": "Manufacturing \u0026 Wholesale Goods"
      },
      {
        "category": "Wholesale",
        "subcategory": "Chemicals \u0026 Plastics",
        "type": "Manufacturing \u0026 Wholesale Goods"
      }
    ],
    "sg:phone": "+1 216 651 5445",
    "sg:postcode": "44113",
    "sg:province": "OH",
    "wof:name": "Associated Finishing Products",
    "wof:placetype": "venue"
  },
  "geometry": {"coordinates":[-81.709772,41.470899],"type":"Point"}
}
