{
  "type": "Feature",
  "properties": {
    "iso:country":"US",
    "sg:address":"3619 Walton Ave",
    "sg:city":"Cleveland",
    "sg:classifiers":[
        {
            "category":"Manufacturing",
            "subcategory":"Tools & Machinery",
            "type":"Manufacturing & Wholesale Goods"
        },
        {
            "category":"Wholesale",
            "subcategory":"Chemicals & Plastics",
            "type":"Manufacturing & Wholesale Goods"
        }
    ],
    "sg:phone":"+1 216 651 5445",
    "sg:postcode":"44113",
    "sg:province":"OH",
    "wof:name":"Associated Finishing Products",
    "wof:placetype":"venue"
},
  "geometry": {"coordinates":[-81.709772,41.470899],"type":"Point"}
}