{
  "type": "Feature",
  "properties": {
    "addr:full": "117 N High St Columbus Grove OH 45830",
    "addr:housenumber": "117",
    "addr:postcode": "45830",
    "addr:street": "N High St",
    "iso:country": "US",
    "sg:address": "117 N High St",
    "sg:city": "Columbus Grove",
    "sg:classifiers": [
      {
        "category": "Bars \u0026 Pubs",
        "type": "Food \u0026 Drink"
      }
    ],
    "sg:phone": "+1 419 659 2747",
    "sg:postcode": "45830",
    "sg:province": "OH",
    "sg:tags": [
      "drinking"
    ],
    "wof:name": "Millers Bar",
    "wof:placetype": "venue"
  },
  "geometry": {"coordinates":[-84.057167,40.919648],"type":"Point"}
}
