{
  "type": "Feature",
  "properties": {
    "addr:full": "3452 E Livingston Ave Columbus OH 43227",
    "addr:housenumber": "3452",
    "addr:postcode": "43227",
    "addr:street": "E Livingston Ave",
    "iso:country": "US",
    "sg:address": "3452 E Livingston Ave",
    "sg:city": "Columbus",
    "sg:classifiers": [
      {
        "category": "Shopping",
        "subcategory": "Clothing, Apparel, \u0026 Fashions",
        "type": "Retail Goods"
      }
    ],
    "sg:phone": "+1 614 238 0413",
    "sg:postcode": "43227",
    "sg:province": "OH",
    "sg:tags": [
      "salvage",
      "surplus",
      "merchandise"
    ],
    "wof:name": "Dircksen \u0026 Assoc Inc",
    "wof:placetype": "venue"
  },
  "geometry": {"coordinates":[-82.906313,39.946394],"type":"Point"}
}
