{
  "type": "Feature",
  "properties": {
    "addr:full":"1564 E 23rd St Cleveland OH 44114",
    "addr:housenumber":"1564",
    "addr:postcode":"44114",
    "addr:street":"E 23Rd St",
    "iso:country":"US",
    "sg:address":"1564 E 23rd St",
    "sg:city":"Cleveland",
    "sg:classifiers":[
        {
            "category":"Organizations",
            "subcategory":"Non-profit Organization",
            "type":"Services"
        }
    ],
    "sg:phone":"+1 216 241 6584",
    "sg:postcode":"44114",
    "sg:province":"OH",
    "wof:name":"Iron Workers Pension Fund",
    "wof:placetype":"venue"
},
  "geometry": {"coordinates":[-81.67505,41.506867],"type":"Point"}
}