{
  "type": "Feature",
  "properties": {
    "iso:country":"US",
    "sg:address":"29 N Main St",
    "sg:city":"Englewood",
    "sg:classifiers":[
        {
            "category":"Restaurant",
            "type":"Food & Drink"
        }
    ],
    "sg:phone":"+1 937 836 2473",
    "sg:postcode":"45322",
    "sg:province":"OH",
    "sg:tags":[
        "eating"
    ],
    "wof:name":"Dairy Queen",
    "wof:placetype":"venue"
},
  "geometry": {"coordinates":[-84.302311,39.877781],"type":"Point"}
}