{
  "type": "Feature",
  "properties": {
    "addr:full": "215 E Summit St Kent OH 44240",
    "addr:housenumber": "215",
    "addr:postcode": "44240",
    "addr:street": "E Summit St",
    "iso:country": "US",
    "sg:address": "215 E Summit St",
    "sg:city": "Kent",
    "sg:classifiers": [
      {
        "category": "Government",
        "subcategory": "Office",
        "type": "Public Place"
      }
    ],
    "sg:phone": "+1 330 678 8619",
    "sg:postcode": "44240",
    "sg:province": "OH",
    "sg:tags": [
      "village"
    ],
    "wof:name": "Kent City Law Dept",
    "wof:placetype": "venue"
  },
  "geometry": {"coordinates":[-81.355307,41.150159],"type":"Point"}
}
