{
  "type": "Feature",
  "properties": {
    "addr:full": "4451 Race Rd Cincinnati OH 45211",
    "addr:housenumber": "4451",
    "addr:postcode": "45211",
    "addr:street": "Race Rd",
    "iso:country": "US",
    "sg:address": "4451 Race Rd",
    "sg:city": "Cincinnati",
    "sg:classifiers": [
      {
        "category": "Professional",
        "subcategory": "Accounting \u0026 Tax Preparation",
        "type": "Services"
      }
    ],
    "sg:phone": "+1 513 598 5678",
    "sg:postcode": "45211",
    "sg:province": "OH",
    "sg:tags": [
      "accountant"
    ],
    "wof:name": "Comprehensive Business Sltns",
    "wof:placetype": "venue"
  },
  "geometry": {"coordinates":[-84.629883,39.173976],"type":"Point"}
}
