{
  "type": "Feature",
  "properties": {
    "addr:full": "6810 N Ridge Rd W Geneva OH 44041",
    "addr:housenumber": "6810",
    "addr:postcode": "44041",
    "addr:street": "N Ridge Rd W",
    "iso:country": "US",
    "sg:address": "6810 N Ridge Rd W",
    "sg:city": "Geneva",
    "sg:classifiers": [
      {
        "category": "Food \u0026 Beverages",
        "subcategory": "Specialty",
        "type": "Retail Goods"
      }
    ],
    "sg:phone": "+1 440 466 7449",
    "sg:postcode": "44041",
    "sg:province": "OH",
    "sg:tags": [
      "health",
      "diet"
    ],
    "wof:name": "Roesch's Natural Foods",
    "wof:placetype": "venue"
  },
  "geometry": {"coordinates":[-80.878518,41.824425],"type":"Point"}
}
