{
  "type": "Feature",
  "properties": {
    "addr:full": "17444 Norton Ave Lakewood OH 44107",
    "addr:housenumber": "17444",
    "addr:postcode": "44107",
    "addr:street": "Norton Ave",
    "iso:country": "US",
    "sg:address": "17444 Norton Ave",
    "sg:city": "Lakewood",
    "sg:classifiers": [
      {
        "category": "Professional",
        "subcategory": "Business Services",
        "type": "Services"
      }
    ],
    "sg:phone": "+1 216 521 8954",
    "sg:postcode": "44107",
    "sg:province": "OH",
    "wof:name": "Roger Bilak",
    "wof:placetype": "venue"
  },
  "geometry": {"coordinates":[-81.819099,41.490154],"type":"Point"}
}
