{
  "type": "Feature",
  "properties": {
    "addr:full": "63 S Hedges St Dayton OH 45403",
    "addr:housenumber": "63",
    "addr:postcode": "45403",
    "addr:street": "S Hedges St",
    "iso:country": "US",
    "sg:address": "63 S Hedges St",
    "sg:city": "Dayton",
    "sg:classifiers": [
      {
        "category": "Building \u0026 Trades",
        "subcategory": "Plumbing",
        "type": "Services"
      }
    ],
    "sg:phone": "+1 937 254 4123",
    "sg:postcode": "45403",
    "sg:province": "OH",
    "sg:tags": [
      "contractor"
    ],
    "wof:name": "Walker",
    "wof:placetype": "venue"
  },
  "geometry": {"coordinates":[-84.148625,39.765763],"type":"Point"}
}
