{
  "type": "Feature",
  "properties": {
    "addr:full":"13725 Wones Rd Maplewood OH 45340",
    "addr:housenumber":"13725",
    "addr:postcode":"45340",
    "addr:street":"Wones Rd",
    "iso:country":"US",
    "sg:address":"13725 Wones Rd",
    "sg:city":"Maplewood",
    "sg:classifiers":[
        {
            "category":"Building & Trades",
            "subcategory":"Landscaping Services",
            "type":"Services"
        }
    ],
    "sg:phone":"+1 937 596 6601",
    "sg:postcode":"45340",
    "sg:province":"OH",
    "wof:name":"Countryside Lawncare",
    "wof:placetype":"venue"
},
  "geometry": {"coordinates":[-84.069136,40.398165],"type":"Point"}
}