{
  "type": "Feature",
  "properties": {
    "addr:full": "202 S Sullivan Dr Haskins OH 43525",
    "addr:housenumber": "202",
    "addr:postcode": "43525",
    "addr:street": "S Sullivan Dr",
    "iso:country": "US",
    "sg:address": "202 S Sullivan Dr",
    "sg:city": "Haskins",
    "sg:classifiers": [
      {
        "category": "Shopping",
        "subcategory": "Computers \u0026 Home Electronics",
        "type": "Retail Goods"
      }
    ],
    "sg:phone": "+1 419 823 3117",
    "sg:postcode": "43525",
    "sg:province": "OH",
    "sg:tags": [
      "software"
    ],
    "wof:name": "Orbit Technologies",
    "wof:placetype": "venue"
  },
  "geometry": {"coordinates":[-83.701835,41.463718],"type":"Point"}
}
