{
  "type": "Feature",
  "properties": {
    "addr:full":"11015 Kenwood Rd Cincinnati OH 45242",
    "addr:housenumber":"11015",
    "addr:postcode":"45242",
    "addr:street":"Kenwood Rd",
    "iso:country":"US",
    "sg:address":"11015 Kenwood Rd",
    "sg:city":"Cincinnati",
    "sg:classifiers":[
        {
            "category":"Wholesale",
            "subcategory":"Chemicals & Plastics",
            "type":"Manufacturing & Wholesale Goods"
        }
    ],
    "sg:phone":"+1 513 984 5444",
    "sg:postcode":"45242",
    "sg:province":"OH",
    "wof:name":"Global Environmental Products",
    "wof:placetype":"venue"
},
  "geometry": {"coordinates":[-84.373819,39.264237],"type":"Point"}
}