{
  "type": "Feature",
  "properties": {
    "iso:country":"US",
    "sg:address":"1415 S Main St",
    "sg:city":"Akron",
    "sg:classifiers":[
        {
            "category":"Building & Trades",
            "subcategory":"Construction",
            "type":"Services"
        }
    ],
    "sg:phone":"+1 330 724 2877",
    "sg:postcode":"44301",
    "sg:province":"OH",
    "sg:tags":[
        "waterproofing",
        "contractor"
    ],
    "wof:name":"Northeastern Basement Watrprfn",
    "wof:placetype":"venue"
},
  "geometry": {"coordinates":[-81.52794799999999,41.049322],"type":"Point"}
}