{
  "type": "Feature",
  "properties": {
    "addr:full": "1415 S Main St Akron OH 44301",
    "addr:housenumber": "1415",
    "addr:postcode": "44301",
    "addr:street": "S Main St",
    "iso:country": "US",
    "sg:address": "1415 S Main St",
    "sg:city": "Akron",
    "sg:classifiers": [
      {
        "category": "Building \u0026 Trades",
        "subcategory": "Construction",
        "type": "Services"
      }
    ],
    "sg:phone": "+1 330 724 2877",
    "sg:postcode": "44301",
    "sg:province": "OH",
    "sg:tags": [
      "waterproofing",
      "contractor"
    ],
    "wof:name": "Northeastern Basement Watrprfn",
    "wof:placetype": "venue"
  },
  "geometry": {"coordinates":[-81.527948,41.049322],"type":"Point"}
}
