{
  "type": "Feature",
  "properties": {
    "iso:country":"US",
    "sg:address":"1705 Commerce Rd",
    "sg:city":"Holland",
    "sg:classifiers":[
        {
            "category":"Manufacturing",
            "subcategory":"Tools & Machinery",
            "type":"Manufacturing & Wholesale Goods"
        }
    ],
    "sg:phone":"+1 419 865 0249",
    "sg:postcode":"43528",
    "sg:province":"OH",
    "sg:tags":[
        "equipment",
        "die",
        "cutting",
        "supply"
    ],
    "sg:website":"www.dynamicdies.com",
    "wof:name":"Dynamic Dies Inc",
    "wof:placetype":"venue"
},
  "geometry": {"coordinates":[-83.793149,41.609922],"type":"Point"}
}