{
  "type": "Feature",
  "properties": {
    "addr:full":"117 Erie St N Massillon OH 44646",
    "addr:housenumber":"117",
    "addr:postcode":"44646",
    "addr:street":"Erie St N",
    "iso:country":"US",
    "sg:address":"117 Erie St N",
    "sg:city":"Massillon",
    "sg:classifiers":[
        {
            "category":"Personal",
            "subcategory":"Barber",
            "type":"Services"
        }
    ],
    "sg:phone":"+1 330 833 7047",
    "sg:postcode":"44646",
    "sg:province":"OH",
    "wof:name":"Tiger Town Barber Shop",
    "wof:placetype":"venue"
},
  "geometry": {"coordinates":[-81.52398599999999,40.797829],"type":"Point"}
}