{
  "type": "Feature",
  "properties": {
    "addr:full": "4029 Westlake Dr Cortland OH 44410",
    "addr:housenumber": "4029",
    "addr:postcode": "44410",
    "addr:street": "Westlake Dr",
    "iso:country": "US",
    "sg:address": "4029 Westlake Dr",
    "sg:city": "Cortland",
    "sg:classifiers": [
      {
        "category": "Building \u0026 Trades",
        "subcategory": "Cleaning \u0026 Sanitation",
        "type": "Services"
      }
    ],
    "sg:phone": "+1 330 638 8510",
    "sg:postcode": "44410",
    "sg:province": "OH",
    "sg:tags": [
      "janitor"
    ],
    "wof:name": "A C Cleaning Svc",
    "wof:placetype": "venue"
  },
  "geometry": {"coordinates":[-80.769296,41.327779],"type":"Point"}
}
