{
  "type": "Feature",
  "properties": {
    "addr:full": "1105 N Plum St Springfield OH 45504",
    "addr:housenumber": "1105",
    "addr:postcode": "45504",
    "addr:street": "N Plum St",
    "iso:country": "US",
    "sg:address": "1105 N Plum St",
    "sg:city": "Springfield",
    "sg:classifiers": [
      {
        "category": "Restaurant",
        "type": "Food \u0026 Drink"
      }
    ],
    "sg:phone": "+1 937 324 3600",
    "sg:postcode": "45504",
    "sg:province": "OH",
    "sg:tags": [
      "eating"
    ],
    "wof:name": "Leithauser Simply Delicious",
    "wof:placetype": "venue"
  },
  "geometry": {"coordinates":[-83.816573,39.938715],"type":"Point"}
}
