{
  "type": "Feature",
  "properties": {
    "addr:full": "232 W 3rd St Dover OH 44622",
    "addr:housenumber": "232",
    "addr:postcode": "44622",
    "addr:street": "W 3Rd St",
    "iso:country": "US",
    "sg:address": "232 W 3rd St",
    "sg:city": "Dover",
    "sg:classifiers": [
      {
        "category": "Professional",
        "subcategory": "Research",
        "type": "Services"
      }
    ],
    "sg:phone": "+1 330 364 4660",
    "sg:postcode": "44622",
    "sg:province": "OH",
    "sg:tags": [
      "foundation",
      "philanthropic"
    ],
    "wof:name": "Reeves Foundation",
    "wof:placetype": "venue"
  },
  "geometry": {"coordinates":[-81.47896,40.520579],"type":"Point"}
}
