{
  "type": "Feature",
  "properties": {
    "iso:country":"US",
    "sg:address":"133 N Main St",
    "sg:city":"Orrville",
    "sg:classifiers":[
        {
            "category":"Banks & Credit Unions",
            "subcategory":"Investment Brokerage",
            "type":"Services"
        }
    ],
    "sg:phone":"+1 330 682 7788",
    "sg:postcode":"44667",
    "sg:province":"OH",
    "sg:tags":[
        "security"
    ],
    "wof:name":"Raymond James",
    "wof:placetype":"venue"
},
  "geometry": {"coordinates":[-81.764285,40.841208],"type":"Point"}
}