{
  "type": "Feature",
  "properties": {
    "iso:country":"US",
    "sg:address":"170 Walton St",
    "sg:city":"Struthers",
    "sg:classifiers":[
        {
            "category":"Restaurant",
            "type":"Food & Drink"
        }
    ],
    "sg:phone":"+1 330 755 5366",
    "sg:postcode":"44471",
    "sg:province":"OH",
    "sg:tags":[
        "eating"
    ],
    "wof:name":"Elm Tree Catering Inc",
    "wof:placetype":"venue"
},
  "geometry": {"coordinates":[-80.60241499999999,41.063128],"type":"Point"}
}