{
  "type": "Feature",
  "properties": {
    "addr:full": "170 Walton St Struthers OH 44471",
    "addr:housenumber": "170",
    "addr:postcode": "44471",
    "addr:street": "Walton St",
    "iso:country": "US",
    "sg:address": "170 Walton St",
    "sg:city": "Struthers",
    "sg:classifiers": [
      {
        "category": "Restaurant",
        "type": "Food \u0026 Drink"
      }
    ],
    "sg:phone": "+1 330 755 5366",
    "sg:postcode": "44471",
    "sg:province": "OH",
    "sg:tags": [
      "eating"
    ],
    "wof:name": "Elm Tree Catering Inc",
    "wof:placetype": "venue"
  },
  "geometry": {"coordinates":[-80.602415,41.063128],"type":"Point"}
}
