{
  "type": "Feature",
  "properties": {
    "addr:full": "5475 White Chapel Rd SE Newark OH 43056",
    "addr:housenumber": "5475",
    "addr:postcode": "43056",
    "addr:street": "White Chapel Rd Se",
    "iso:country": "US",
    "sg:address": "5475 White Chapel Rd SE",
    "sg:city": "Newark",
    "sg:classifiers": [
      {
        "category": "Building \u0026 Trades",
        "subcategory": "Construction",
        "type": "Services"
      }
    ],
    "sg:phone": "+1 740 522 0602",
    "sg:postcode": "43056",
    "sg:province": "OH",
    "sg:tags": [
      "carpentry",
      "contractor"
    ],
    "wof:name": "Morrison By Designs",
    "wof:placetype": "venue"
  },
  "geometry": {"coordinates":[-82.436492,40.002678],"type":"Point"}
}
