{
  "type": "Feature",
  "properties": {
    "addr:full": "8900 Mentor Ave Mentor OH 44060",
    "addr:housenumber": "8900",
    "addr:postcode": "44060",
    "addr:street": "Mentor Ave",
    "iso:country": "US",
    "sg:address": "8900 Mentor Ave",
    "sg:city": "Mentor",
    "sg:classifiers": [
      {
        "category": "Restaurant",
        "type": "Food \u0026 Drink"
      }
    ],
    "sg:phone": "+1 440 974 0055",
    "sg:postcode": "44060",
    "sg:province": "OH",
    "sg:tags": [
      "delicatessen"
    ],
    "sg:website": "www.mentorave.com",
    "wof:name": "Manhattan Deli",
    "wof:placetype": "venue"
  },
  "geometry": {"coordinates":[-81.322131,41.674361],"type":"Point"}
}
