{
  "type": "Feature",
  "properties": {
    "addr:full":"4126 Summit Rd Barberton OH 44203",
    "addr:housenumber":"4126",
    "addr:postcode":"44203",
    "addr:street":"Summit Rd",
    "iso:country":"US",
    "sg:address":"4126 Summit Rd",
    "sg:city":"Barberton",
    "sg:classifiers":[
        {
            "category":"Retail",
            "subcategory":"Repair Shop",
            "type":"Services"
        }
    ],
    "sg:phone":"+1 330 745 3351",
    "sg:postcode":"44203",
    "sg:province":"OH",
    "sg:tags":[
        "operation",
        "timber",
        "tract"
    ],
    "wof:name":"Gs & G",
    "wof:placetype":"venue"
},
  "geometry": {"coordinates":[-81.59544200000001,41.043222],"type":"Point"}
}