{
  "type": "Feature",
  "properties": {
    "iso:country":"US",
    "sg:address":"718 Market St",
    "sg:city":"Brookville",
    "sg:classifiers":[
        {
            "category":"Manufacturing",
            "subcategory":"Retail Goods",
            "type":"Manufacturing & Wholesale Goods"
        }
    ],
    "sg:phone":"+1 937 833 6768",
    "sg:postcode":"45309",
    "sg:province":"OH",
    "sg:tags":[
        "assembly",
        "fabricating"
    ],
    "wof:name":"Surmount Corp",
    "wof:placetype":"venue"
},
  "geometry": {"coordinates":[-84.411161,39.840917],"type":"Point"}
}