{
  "type": "Feature",
  "properties": {
    "addr:full":"700 W Cherry St Sunbury OH 43074",
    "addr:housenumber":"700",
    "addr:postcode":"43074",
    "addr:street":"W Cherry St",
    "iso:country":"US",
    "sg:address":"700 W Cherry St",
    "sg:city":"Sunbury",
    "sg:classifiers":[
        {
            "category":"Banks & Credit Unions",
            "subcategory":"Bank",
            "type":"Services"
        }
    ],
    "sg:phone":"+1 740 965 9174",
    "sg:postcode":"43074",
    "sg:province":"OH",
    "sg:tags":[
        "loan",
        "real estate"
    ],
    "wof:name":"Heartwell Mortgage",
    "wof:placetype":"venue"
},
  "geometry": {"coordinates":[-82.868127,40.24791],"type":"Point"}
}