{
  "type": "Feature",
  "properties": {
    "addr:full":"41 Robin Hood Ln Troy OH 45373",
    "addr:housenumber":"41",
    "addr:postcode":"45373",
    "addr:street":"Robin Hood Ln",
    "iso:country":"US",
    "sg:address":"41 Robin Hood Ln",
    "sg:city":"Troy",
    "sg:classifiers":[
        {
            "category":"Banks & Credit Unions",
            "subcategory":"Bank",
            "type":"Services"
        }
    ],
    "sg:phone":"+1 937 335 9028",
    "sg:postcode":"45373",
    "sg:province":"OH",
    "sg:tags":[
        "mortgage"
    ],
    "wof:name":"Mortgage Banc Corp",
    "wof:placetype":"venue"
},
  "geometry": {"coordinates":[-84.19310299999999,40.051323],"type":"Point"}
}