{
  "type": "Feature",
  "properties": {
    "iso:country":"US",
    "sg:address":"41 Robin Hood Ln",
    "sg:city":"Troy",
    "sg:classifiers":[
        {
            "category":"Banks & Credit Unions",
            "subcategory":"Bank",
            "type":"Services"
        }
    ],
    "sg:phone":"+1 937 335 9028",
    "sg:postcode":"45373",
    "sg:province":"OH",
    "sg:tags":[
        "mortgage"
    ],
    "wof:name":"Mortgage Banc Corp",
    "wof:placetype":"venue"
},
  "geometry": {"coordinates":[-84.193103,40.051323],"type":"Point"}
}