{
  "type": "Feature",
  "properties": {
    "addr:full":"41 S Marion St Bloomville OH 44818",
    "addr:housenumber":"41",
    "addr:postcode":"44818",
    "addr:street":"S Marion St",
    "iso:country":"US",
    "sg:address":"41 S Marion St",
    "sg:city":"Bloomville",
    "sg:classifiers":[
        {
            "category":"Personal",
            "subcategory":"Beauty Salon",
            "type":"Services"
        }
    ],
    "sg:phone":"+1 419 983 5871",
    "sg:postcode":"44818",
    "sg:province":"OH",
    "wof:name":"KUT & KURL Hair Fashions",
    "wof:placetype":"venue"
},
  "geometry": {"coordinates":[-83.015283,41.050897],"type":"Point"}
}