{
  "type": "Feature",
  "properties": {
    "addr:full":"813 Lovers Ln Akron OH 44306",
    "addr:housenumber":"813",
    "addr:postcode":"44306",
    "addr:street":"Lovers Ln",
    "iso:country":"US",
    "sg:address":"813 Lovers Ln",
    "sg:city":"Akron",
    "sg:classifiers":[
        {
            "category":"Autos & Motor Vehicles",
            "subcategory":"Fuel & Gas Station",
            "type":"Retail Goods"
        }
    ],
    "sg:phone":"+1 330 785 2785",
    "sg:postcode":"44306",
    "sg:province":"OH",
    "sg:tags":[
        "station",
        "gasoline",
        "oil"
    ],
    "wof:name":"Max's Express",
    "wof:placetype":"venue"
},
  "geometry": {"coordinates":[-81.499635,41.054531],"type":"Point"}
}