{
  "type": "Feature",
  "properties": {
    "addr:full": "740 W Main St Plain City OH 43064",
    "addr:housenumber": "740",
    "addr:postcode": "43064",
    "addr:street": "W Main St",
    "iso:country": "US",
    "sg:address": "740 W Main St",
    "sg:city": "Plain City",
    "sg:classifiers": [
      {
        "category": "Building \u0026 Trades",
        "subcategory": "Plumbing",
        "type": "Services"
      }
    ],
    "sg:phone": "+1 614 873 8012",
    "sg:postcode": "43064",
    "sg:province": "OH",
    "sg:tags": [
      "plumbing",
      "contractor",
      "supply"
    ],
    "wof:name": "Plain City Plmbng",
    "wof:placetype": "venue"
  },
  "geometry": {"coordinates":[-83.279065,40.111136],"type":"Point"}
}
