{
  "type": "Feature",
  "properties": {
    "addr:full": "2204 Tallmadge Rd Ravenna OH 44266",
    "addr:housenumber": "2204",
    "addr:postcode": "44266",
    "addr:street": "Tallmadge Rd",
    "iso:country": "US",
    "sg:address": "2204 Tallmadge Rd",
    "sg:city": "Ravenna",
    "sg:classifiers": [
      {
        "category": "Wholesale",
        "subcategory": "Medical Equipment \u0026 Supplies",
        "type": "Manufacturing \u0026 Wholesale Goods"
      }
    ],
    "sg:phone": "+1 330 678 9448",
    "sg:postcode": "44266",
    "sg:province": "OH",
    "sg:tags": [
      "wheel",
      "chair",
      "lift",
      "ramp"
    ],
    "wof:name": "Ohio Access Products",
    "wof:placetype": "venue"
  },
  "geometry": {"coordinates":[-81.317081,41.09975],"type":"Point"}
}
