{
  "type": "Feature",
  "properties": {
    "iso:country":"US",
    "sg:address":"2204 Tallmadge Rd",
    "sg:city":"Ravenna",
    "sg:classifiers":[
        {
            "category":"Wholesale",
            "subcategory":"Medical Equipment & Supplies",
            "type":"Manufacturing & Wholesale Goods"
        }
    ],
    "sg:phone":"+1 330 678 9448",
    "sg:postcode":"44266",
    "sg:province":"OH",
    "sg:tags":[
        "wheel",
        "chair",
        "lift",
        "ramp"
    ],
    "wof:name":"Ohio Access Products",
    "wof:placetype":"venue"
},
  "geometry": {"coordinates":[-81.317081,41.09975],"type":"Point"}
}