{
  "type": "Feature",
  "properties": {
    "addr:full": "1890 Mc Kinley Ave Columbus OH 43222",
    "addr:housenumber": "1890",
    "addr:postcode": "43222",
    "addr:street": "Mc Kinley Ave",
    "iso:country": "US",
    "sg:address": "1890 Mc Kinley Ave",
    "sg:city": "Columbus",
    "sg:classifiers": [
      {
        "category": "Manufacturing",
        "subcategory": "Metals",
        "type": "Manufacturing \u0026 Wholesale Goods"
      }
    ],
    "sg:phone": "+1 614 279 4498",
    "sg:postcode": "43222",
    "sg:province": "OH",
    "sg:tags": [
      "casting",
      "aluminum",
      "mfg",
      "foundry",
      "brass",
      "bronze"
    ],
    "wof:name": "Industrial Aluminum Foundry Co",
    "wof:placetype": "venue"
  },
  "geometry": {"coordinates":[-83.050975,39.96434],"type":"Point"}
}
