{
  "type": "Feature",
  "properties": {
    "addr:full":"537 W Lakeshore Dr Port Clinton OH 43452",
    "addr:housenumber":"537",
    "addr:postcode":"43452",
    "addr:street":"W Lakeshore Dr",
    "iso:country":"US",
    "sg:address":"537 W Lakeshore Dr",
    "sg:city":"Port Clinton",
    "sg:classifiers":[
        {
            "category":"Shopping",
            "subcategory":"Gifts & Souvenirs",
            "type":"Retail Goods"
        }
    ],
    "sg:phone":"+1 419 732 1521",
    "sg:postcode":"43452",
    "sg:province":"OH",
    "sg:tags":[
        "party",
        "supply"
    ],
    "wof:name":"Let's Celebrate Again",
    "wof:placetype":"venue"
},
  "geometry": {"coordinates":[-82.949776,41.518814],"type":"Point"}
}