{
  "type": "Feature",
  "properties": {
    "iso:country":"US",
    "sg:address":"667 N Ellsworth Ave",
    "sg:city":"Salem",
    "sg:classifiers":[
        {
            "category":"Social Services",
            "type":"Services"
        }
    ],
    "sg:phone":"+1 330 332 0028",
    "sg:postcode":"44460",
    "sg:province":"OH",
    "wof:name":"Red Cross",
    "wof:placetype":"venue"
},
  "geometry": {"coordinates":[-80.856785,40.906808],"type":"Point"}
}