{
  "type": "Feature",
  "properties": {
    "addr:full": "10700 Campbell Rd Harrison IN 45030",
    "addr:housenumber": "10700",
    "addr:postcode": "45030",
    "addr:street": "Campbell Rd",
    "iso:country": "US",
    "sg:address": "10700 Campbell Rd",
    "sg:city": "Harrison",
    "sg:classifiers": [
      {
        "category": "Organizations",
        "subcategory": "Community Association",
        "type": "Services"
      }
    ],
    "sg:phone": "+1 513 367 9180",
    "sg:postcode": "45030",
    "sg:province": "IN",
    "sg:tags": [
      "military"
    ],
    "wof:name": "American Legion",
    "wof:placetype": "venue"
  },
  "geometry": {"coordinates":[-84.807899,39.247424],"type":"Point"}
}
