{
  "type": "Feature",
  "properties": {
    "addr:full": "7953 US Hwy 62 SW Washington Ct Hs OH 43160",
    "addr:housenumber": "7953",
    "addr:postcode": "43160",
    "addr:street": "Us Hwy 62 Sw",
    "iso:country": "US",
    "sg:address": "7953 US Hwy 62 SW",
    "sg:city": "Washington Ct Hs",
    "sg:classifiers": [
      {
        "category": "Wholesale",
        "subcategory": "Farm Supplies",
        "type": "Manufacturing \u0026 Wholesale Goods"
      },
      {
        "category": "Home \u0026 Garden",
        "subcategory": "Garden Supply",
        "type": "Retail Goods"
      }
    ],
    "sg:phone": "+1 740 335 3142",
    "sg:postcode": "43160",
    "sg:province": "OH",
    "sg:tags": [
      "fertilizer"
    ],
    "sg:website": "www.roysterclark.com",
    "wof:name": "Royster-Clark Inc",
    "wof:placetype": "venue"
  },
  "geometry": {"coordinates":[-83.512045,39.433841],"type":"Point"}
}
