{
  "type": "Feature",
  "properties": {
    "iso:country":"US",
    "sg:address":"68 Olive St",
    "sg:city":"Chagrin Falls",
    "sg:classifiers":[
        {
            "category":"Banks & Credit Unions",
            "subcategory":"Investment Brokerage",
            "type":"Services"
        },
        {
            "category":"Recreation",
            "type":"Entertainment"
        }
    ],
    "sg:phone":"+1 440 247 0276",
    "sg:postcode":"44022",
    "sg:province":"OH",
    "sg:tags":[
        "advisory",
        "amusement"
    ],
    "wof:name":"R C V Investments",
    "wof:placetype":"venue"
},
  "geometry": {"coordinates":[-81.39366099999999,41.425394],"type":"Point"}
}