{
  "type": "Feature",
  "properties": {
    "iso:country":"US",
    "sg:address":"2200 Philadelphia Dr",
    "sg:city":"Dayton",
    "sg:classifiers":[
        {
            "category":"Health Services",
            "subcategory":"Doctor",
            "type":"Services"
        }
    ],
    "sg:phone":"+1 937 278 4784",
    "sg:postcode":"45406",
    "sg:province":"OH",
    "sg:tags":[
        "medical"
    ],
    "wof:name":"Montgomery Orthopedic Surgens",
    "wof:placetype":"venue"
},
  "geometry": {"coordinates":[-84.235013,39.789189],"type":"Point"}
}