{
  "type": "Feature",
  "properties": {
    "iso:country":"US",
    "sg:address":"422 W Main St",
    "sg:city":"Fairborn",
    "sg:classifiers":[
        {
            "category":"Real Estate",
            "subcategory":"Real Estate Agent",
            "type":"Services"
        }
    ],
    "sg:phone":"+1 937 879 1122",
    "sg:postcode":"45324",
    "sg:province":"OH",
    "wof:name":"One Realty",
    "wof:placetype":"venue"
},
  "geometry": {"coordinates":[-84.026354,39.8218],"type":"Point"}
}