{
  "type": "Feature",
  "properties": {
    "addr:full":"248 Jessie Creek Rd Cheshire OH 45620",
    "addr:housenumber":"248",
    "addr:postcode":"45620",
    "addr:street":"Jessie Creek Rd",
    "iso:country":"US",
    "sg:address":"248 Jessie Creek Rd",
    "sg:city":"Cheshire",
    "sg:classifiers":[
        {
            "category":"Farming",
            "subcategory":"Farm",
            "type":"Manufacturing & Wholesale Goods"
        }
    ],
    "sg:phone":"+1 740 367 7646",
    "sg:postcode":"45620",
    "sg:province":"OH",
    "sg:tags":[
        "crop",
        "general"
    ],
    "wof:name":"Robert Conkle",
    "wof:placetype":"venue"
},
  "geometry": {"coordinates":[-82.143457,38.987507],"type":"Point"}
}