{
  "type": "Feature",
  "properties": {
    "addr:full":"878 Commercial Ave SW New Philadelphia OH 44663",
    "addr:housenumber":"878",
    "addr:postcode":"44663",
    "addr:street":"Commercial Ave Sw",
    "iso:country":"US",
    "sg:address":"878 Commercial Ave SW",
    "sg:city":"New Philadelphia",
    "sg:classifiers":[
        {
            "category":"Organizations",
            "subcategory":"Religious Organization",
            "type":"Services"
        }
    ],
    "sg:phone":"+1 330 339 1141",
    "sg:postcode":"44663",
    "sg:province":"OH",
    "wof:name":"First Baptist Church",
    "wof:placetype":"venue"
},
  "geometry": {"coordinates":[-81.46314,40.48273],"type":"Point"}
}