{
  "type": "Feature",
  "properties": {
    "iso:country":"US",
    "sg:address":"1860 Otter Creek Rd",
    "sg:city":"Oregon",
    "sg:classifiers":[
        {
            "category":"Building & Trades",
            "subcategory":"Construction",
            "type":"Services"
        }
    ],
    "sg:phone":"+1 419 691 5786",
    "sg:postcode":"43616",
    "sg:province":"OH",
    "wof:name":"RMF Nooter Inc",
    "wof:placetype":"venue"
},
  "geometry": {"coordinates":[-83.45299,41.689492],"type":"Point"}
}