{
  "type": "Feature",
  "properties": {
    "iso:country":"US",
    "sg:address":"6446 E Main St",
    "sg:city":"Reynoldsburg",
    "sg:classifiers":[
        {
            "category":"Freight",
            "type":"Transportation"
        }
    ],
    "sg:phone":"+1 614 861 7720",
    "sg:postcode":"43068",
    "sg:province":"OH",
    "sg:tags":[
        "commercial",
        "storage"
    ],
    "wof:name":"Reynoldsburg Mini Storage",
    "wof:placetype":"venue"
},
  "geometry": {"coordinates":[-82.82268999999999,39.954969],"type":"Point"}
}