{
  "type": "Feature",
  "properties": {
    "iso:country":"US",
    "sg:address":"4950 East Pike",
    "sg:city":"Zanesville",
    "sg:classifiers":[
        {
            "category":"Autos & Motor Vehicles",
            "subcategory":"Fuel & Gas Station",
            "type":"Retail Goods"
        }
    ],
    "sg:phone":"+1 740 450 8455",
    "sg:postcode":"43701",
    "sg:province":"OH",
    "sg:tags":[
        "oil"
    ],
    "wof:name":"Airport Exxon",
    "wof:placetype":"venue"
},
  "geometry": {"coordinates":[-81.900383,39.964844],"type":"Point"}
}