{
  "type": "Feature",
  "properties": {
    "addr:full": "7925 Leaview Dr Columbus OH 43235",
    "addr:housenumber": "7925",
    "addr:postcode": "43235",
    "addr:street": "Leaview Dr",
    "iso:country": "US",
    "sg:address": "7925 Leaview Dr",
    "sg:city": "Columbus",
    "sg:classifiers": [
      {
        "category": "Professional",
        "type": "Services"
      }
    ],
    "sg:phone": "+1 614 885 8913",
    "sg:postcode": "43235",
    "sg:province": "OH",
    "wof:name": "Andre L Austin",
    "wof:placetype": "venue"
  },
  "geometry": {"coordinates":[-83.009025,40.125321],"type":"Point"}
}
