{
  "type": "Feature",
  "properties": {
    "iso:country":"US",
    "sg:address":"2687 Darke Ct",
    "sg:city":"Cincinnati",
    "sg:classifiers":[
        {
            "category":"Building & Trades",
            "subcategory":"Construction",
            "type":"Services"
        }
    ],
    "sg:phone":"+1 513 351 2275",
    "sg:postcode":"45233",
    "sg:province":"OH",
    "sg:tags":[
        "general",
        "contractor"
    ],
    "wof:name":"Paul Construction Co",
    "wof:placetype":"venue"
},
  "geometry": {"coordinates":[-84.691984,39.139346],"type":"Point"}
}