{
  "type": "Feature",
  "properties": {
    "addr:full": "19917 Lanbury Ave Cleveland OH 44122",
    "addr:housenumber": "19917",
    "addr:postcode": "44122",
    "addr:street": "Lanbury Ave",
    "iso:country": "US",
    "sg:address": "19917 Lanbury Ave",
    "sg:city": "Cleveland",
    "sg:classifiers": [
      {
        "category": "Organizations",
        "subcategory": "Religious Organization",
        "type": "Services"
      }
    ],
    "sg:phone": "+1 216 921 3043",
    "sg:postcode": "44122",
    "sg:province": "OH",
    "sg:tags": [
      "clergy"
    ],
    "wof:name": "Robert Marbury",
    "wof:placetype": "venue"
  },
  "geometry": {"coordinates":[-81.537499,41.455864],"type":"Point"}
}
