{
  "type": "Feature",
  "properties": {
    "iso:country":"US",
    "sg:address":"3631 Hamilton Rd",
    "sg:city":"Medina",
    "sg:classifiers":[
        {
            "category":"Organizations",
            "subcategory":"Religious Organization",
            "type":"Services"
        }
    ],
    "sg:phone":"+1 330 723 6046",
    "sg:postcode":"44256",
    "sg:province":"OH",
    "sg:tags":[
        "church"
    ],
    "sg:website":"www.livingwordmedina.com",
    "wof:name":"Living Word Lutheran Church",
    "wof:placetype":"venue"
},
  "geometry": {"coordinates":[-81.81275599999999,41.192807],"type":"Point"}
}