{
  "type": "Feature",
  "properties": {
    "addr:full": "3631 Hamilton Rd Medina OH 44256",
    "addr:housenumber": "3631",
    "addr:postcode": "44256",
    "addr:street": "Hamilton Rd",
    "iso:country": "US",
    "sg:address": "3631 Hamilton Rd",
    "sg:city": "Medina",
    "sg:classifiers": [
      {
        "category": "Organizations",
        "subcategory": "Religious Organization",
        "type": "Services"
      }
    ],
    "sg:phone": "+1 330 723 6046",
    "sg:postcode": "44256",
    "sg:province": "OH",
    "sg:tags": [
      "church"
    ],
    "sg:website": "www.livingwordmedina.com",
    "wof:name": "Living Word Lutheran Church",
    "wof:placetype": "venue"
  },
  "geometry": {"coordinates":[-81.812756,41.192807],"type":"Point"}
}
