{
  "type": "Feature",
  "properties": {
    "addr:full":"501 W Schrock Rd Westerville OH 43081",
    "addr:housenumber":"501",
    "addr:postcode":"43081",
    "addr:street":"W Schrock Rd",
    "iso:country":"US",
    "sg:address":"501 W Schrock Rd",
    "sg:city":"Westerville",
    "sg:classifiers":[
        {
            "category":"Banks & Credit Unions",
            "subcategory":"Bank",
            "type":"Services"
        }
    ],
    "sg:phone":"+1 614 583 8259",
    "sg:postcode":"43081",
    "sg:province":"OH",
    "sg:tags":[
        "state"
    ],
    "wof:name":"Sky Bank",
    "wof:placetype":"venue"
},
  "geometry": {"coordinates":[-82.94283299999999,40.110614],"type":"Point"}
}