{
  "type": "Feature",
  "properties": {
    "addr:full": "2751 Orders Rd Grove City OH 43123",
    "addr:housenumber": "2751",
    "addr:postcode": "43123",
    "addr:street": "Orders Rd",
    "iso:country": "US",
    "sg:address": "2751 Orders Rd",
    "sg:city": "Grove City",
    "sg:classifiers": [
      {
        "category": "Wholesale",
        "subcategory": "Durable Goods \u0026 Equipment",
        "type": "Manufacturing \u0026 Wholesale Goods"
      }
    ],
    "sg:phone": "+1 614 871 1154",
    "sg:postcode": "43123",
    "sg:province": "OH",
    "wof:name": "Pine Row LLC",
    "wof:placetype": "venue"
  },
  "geometry": {"coordinates":[-83.073697,39.85942],"type":"Point"}
}
