{
  "type": "Feature",
  "properties": {
    "addr:full": "7571 Saunderlane Rd Columbus OH 43235",
    "addr:housenumber": "7571",
    "addr:postcode": "43235",
    "addr:street": "Saunderlane Rd",
    "iso:country": "US",
    "sg:address": "7571 Saunderlane Rd",
    "sg:city": "Columbus",
    "sg:classifiers": [
      {
        "category": "Wholesale",
        "subcategory": "Durable Goods \u0026 Equipment",
        "type": "Manufacturing \u0026 Wholesale Goods"
      }
    ],
    "sg:phone": "+1 614 764 4645",
    "sg:postcode": "43235",
    "sg:province": "OH",
    "sg:tags": [
      "science",
      "school",
      "supply",
      "scientific",
      "instr"
    ],
    "wof:name": "Science Kit",
    "wof:placetype": "venue"
  },
  "geometry": {"coordinates":[-83.073159,40.114917],"type":"Point"}
}
