{
  "type": "Feature",
  "properties": {
    "iso:country":"US",
    "sg:address":"170 Plymouth St",
    "sg:city":"Bucyrus",
    "sg:classifiers":[
        {
            "category":"Education",
            "subcategory":"School",
            "type":"Public Place"
        }
    ],
    "sg:phone":"+1 419 562 9081",
    "sg:postcode":"44820",
    "sg:province":"OH",
    "wof:name":"Lincoln Elementary School",
    "wof:placetype":"venue"
},
  "geometry": {"coordinates":[-82.973539,40.815728],"type":"Point"}
}