{
  "type": "Feature",
  "properties": {
    "addr:full": "5675 Arlyne Ln Medina OH 44256",
    "addr:housenumber": "5675",
    "addr:postcode": "44256",
    "addr:street": "Arlyne Ln",
    "iso:country": "US",
    "sg:address": "5675 Arlyne Ln",
    "sg:city": "Medina",
    "sg:classifiers": [
      {
        "category": "Wholesale",
        "subcategory": "Machinery \u0026 Supplies",
        "type": "Manufacturing \u0026 Wholesale Goods"
      },
      {
        "category": "Wholesale",
        "subcategory": "Auto Parts",
        "type": "Manufacturing \u0026 Wholesale Goods"
      }
    ],
    "sg:phone": "+1 330 725 3330",
    "sg:postcode": "44256",
    "sg:province": "OH",
    "sg:tags": [
      "equipment",
      "industrial"
    ],
    "wof:name": "Blaster Fullfillment",
    "wof:placetype": "venue"
  },
  "geometry": {"coordinates":[-81.798927,41.120396],"type":"Point"}
}
