{
  "type": "Feature",
  "properties": {
    "iso:country":"US",
    "sg:address":"930 W Ash St",
    "sg:city":"Piqua",
    "sg:classifiers":[
        {
            "category":"Building & Trades",
            "subcategory":"Construction",
            "type":"Services"
        }
    ],
    "sg:phone":"+1 937 773 4446",
    "sg:postcode":"45356",
    "sg:province":"OH",
    "sg:tags":[
        "contractor"
    ],
    "wof:name":"Miami Valley Pools of Ohio",
    "wof:placetype":"venue"
},
  "geometry": {"coordinates":[-84.252295,40.149581],"type":"Point"}
}