{
  "type": "Feature",
  "properties": {
    "addr:full": "109 E 2nd St Waverly OH 45690",
    "addr:housenumber": "109",
    "addr:postcode": "45690",
    "addr:street": "E 2Nd St",
    "iso:country": "US",
    "sg:address": "109 E 2nd St",
    "sg:city": "Waverly",
    "sg:classifiers": [
      {
        "category": "Shopping",
        "subcategory": "Bicycles \u0026 Sporting Goods",
        "type": "Retail Goods"
      }
    ],
    "sg:phone": "+1 740 947 5294",
    "sg:postcode": "45690",
    "sg:province": "OH",
    "wof:name": "C J L Sports",
    "wof:placetype": "venue"
  },
  "geometry": {"coordinates":[-82.983403,39.126964],"type":"Point"}
}
