{
  "type": "Feature",
  "properties": {
    "addr:full": "22480 Lake Rd Cleveland OH 44116",
    "addr:housenumber": "22480",
    "addr:postcode": "44116",
    "addr:street": "Lake Rd",
    "iso:country": "US",
    "sg:address": "22480 Lake Rd",
    "sg:city": "Cleveland",
    "sg:classifiers": [
      {
        "category": "Shopping",
        "type": "Retail Goods"
      },
      {
        "category": "Wholesale",
        "subcategory": "Chemicals \u0026 Plastics",
        "type": "Manufacturing \u0026 Wholesale Goods"
      }
    ],
    "sg:phone": "+1 440 331 0350",
    "sg:postcode": "44116",
    "sg:province": "OH",
    "sg:tags": [
      "rep",
      "industrial"
    ],
    "wof:name": "Deery Chemical Inc",
    "wof:placetype": "venue"
  },
  "geometry": {"coordinates":[-81.868185,41.481673],"type":"Point"}
}
