{
  "type": "Feature",
  "properties": {
    "iso:country":"US",
    "sg:address":"22480 Lake Rd",
    "sg:city":"Cleveland",
    "sg:classifiers":[
        {
            "category":"Shopping",
            "type":"Retail Goods"
        },
        {
            "category":"Wholesale",
            "subcategory":"Chemicals & Plastics",
            "type":"Manufacturing & Wholesale Goods"
        }
    ],
    "sg:phone":"+1 440 331 0350",
    "sg:postcode":"44116",
    "sg:province":"OH",
    "sg:tags":[
        "rep",
        "industrial"
    ],
    "wof:name":"Deery Chemical Inc",
    "wof:placetype":"venue"
},
  "geometry": {"coordinates":[-81.868185,41.481673],"type":"Point"}
}