{
  "type": "Feature",
  "properties": {
    "addr:full": "404 Kings Mills Rd Mason OH 45040",
    "addr:housenumber": "404",
    "addr:postcode": "45040",
    "addr:street": "Kings Mills Rd",
    "iso:country": "US",
    "sg:address": "404 Kings Mills Rd",
    "sg:city": "Mason",
    "sg:classifiers": [
      {
        "category": "Arts \u0026 Performance",
        "subcategory": "Theater",
        "type": "Entertainment"
      }
    ],
    "sg:phone": "+1 513 398 1737",
    "sg:postcode": "45040",
    "sg:province": "OH",
    "sg:tags": [
      "musician"
    ],
    "wof:name": "Mason Chorale Inc",
    "wof:placetype": "venue"
  },
  "geometry": {"coordinates":[-84.284267,39.356157],"type":"Point"}
}
