{
  "type": "Feature",
  "properties": {
    "addr:full": "519 N Jackson St Lima OH 45801",
    "addr:housenumber": "519",
    "addr:postcode": "45801",
    "addr:street": "N Jackson St",
    "iso:country": "US",
    "sg:address": "519 N Jackson St",
    "sg:city": "Lima",
    "sg:classifiers": [
      {
        "category": "Retail",
        "subcategory": "Repair Shop",
        "type": "Services"
      }
    ],
    "sg:phone": "+1 419 222 7222",
    "sg:postcode": "45801",
    "sg:province": "OH",
    "sg:tags": [
      "material",
      "handling",
      "machinery"
    ],
    "wof:name": "El Industrial Systems Inc",
    "wof:placetype": "venue"
  },
  "geometry": {"coordinates":[-84.100028,40.746337],"type":"Point"}
}
