{
  "type": "Feature",
  "properties": {
    "iso:country":"US",
    "sg:address":"4600 Valley Pkwy",
    "sg:city":"Cleveland",
    "sg:classifiers":[
        {
            "category":"Recreation",
            "type":"Entertainment"
        }
    ],
    "sg:phone":"+1 440 243 7860",
    "sg:postcode":"44126",
    "sg:province":"OH",
    "sg:tags":[
        "parks"
    ],
    "wof:name":"Cleveland Metroparks Ranger",
    "wof:placetype":"venue"
},
  "geometry": {"coordinates":[-81.839592,41.448819],"type":"Point"}
}