{
  "type": "Feature",
  "properties": {
    "addr:full":"67 N Market St East Palestine OH 44413",
    "addr:housenumber":"67",
    "addr:postcode":"44413",
    "addr:street":"N Market St",
    "iso:country":"US",
    "sg:address":"67 N Market St",
    "sg:city":"East Palestine",
    "sg:classifiers":[
        {
            "category":"Professional",
            "subcategory":"Accounting & Tax Preparation",
            "type":"Services"
        }
    ],
    "sg:phone":"+1 330 426 9666",
    "sg:postcode":"44413",
    "sg:province":"OH",
    "sg:tags":[
        "return",
        "filing"
    ],
    "wof:name":"H & R Block Tax Svc",
    "wof:placetype":"venue"
},
  "geometry": {"coordinates":[-80.539978,40.833398],"type":"Point"}
}