{
  "type": "Feature",
  "properties": {
    "addr:full":"5375 Navarre Rd SW Canton OH 44706",
    "addr:housenumber":"5375",
    "addr:postcode":"44706",
    "addr:street":"Navarre Rd Sw",
    "iso:country":"US",
    "sg:address":"5375 Navarre Rd SW",
    "sg:city":"Canton",
    "sg:classifiers":[
        {
            "category":"Retail",
            "subcategory":"Auto Repair",
            "type":"Services"
        }
    ],
    "sg:phone":"+1 330 477 1112",
    "sg:postcode":"44706",
    "sg:province":"OH",
    "sg:tags":[
        "wrecker"
    ],
    "wof:name":"Central Ohio Recovery Inc",
    "wof:placetype":"venue"
},
  "geometry": {"coordinates":[-81.453307,40.763698],"type":"Point"}
}