{
  "type": "Feature",
  "properties": {
    "iso:country":"US",
    "sg:address":"237 S Elm St",
    "sg:city":"Jefferson",
    "sg:classifiers":[
        {
            "category":"Food & Beverages",
            "subcategory":"Dairy",
            "type":"Retail Goods"
        }
    ],
    "sg:phone":"+1 440 576 0945",
    "sg:postcode":"44047",
    "sg:province":"OH",
    "sg:tags":[
        "product"
    ],
    "wof:name":"Edgewood Dairy Queen",
    "wof:placetype":"venue"
},
  "geometry": {"coordinates":[-80.774682,41.732747],"type":"Point"}
}