{
  "type": "Feature",
  "properties": {
    "addr:full": "15018 Madison Ave Cleveland OH 44107",
    "addr:housenumber": "15018",
    "addr:postcode": "44107",
    "addr:street": "Madison Ave",
    "iso:country": "US",
    "sg:address": "15018 Madison Ave",
    "sg:city": "Cleveland",
    "sg:classifiers": [
      {
        "category": "Manufacturing",
        "subcategory": "Aerospace",
        "type": "Manufacturing \u0026 Wholesale Goods"
      }
    ],
    "sg:phone": "+1 216 221 1714",
    "sg:postcode": "44107",
    "sg:province": "OH",
    "sg:tags": [
      "aircraft",
      "component"
    ],
    "wof:name": "Indupro Associates",
    "wof:placetype": "venue"
  },
  "geometry": {"coordinates":[-81.80217,41.477367],"type":"Point"}
}
