{
  "type": "Feature",
  "properties": {
    "addr:full": "116 S Meridian Rd Youngstown OH 44509",
    "addr:housenumber": "116",
    "addr:postcode": "44509",
    "addr:street": "S Meridian Rd",
    "iso:country": "US",
    "sg:address": "116 S Meridian Rd",
    "sg:city": "Youngstown",
    "sg:classifiers": [
      {
        "category": "Manufacturing",
        "subcategory": "Rubber \u0026 Plastics",
        "type": "Manufacturing \u0026 Wholesale Goods"
      },
      {
        "category": "Autos \u0026 Motor Vehicles",
        "subcategory": "Auto Supplies",
        "type": "Retail Goods"
      },
      {
        "category": "Retail",
        "subcategory": "Auto Repair",
        "type": "Services"
      }
    ],
    "sg:phone": "+1 330 799 9274",
    "sg:postcode": "44509",
    "sg:province": "OH",
    "sg:tags": [
      "tires-wholesale",
      "tire",
      "retread",
      "recap",
      "manufacturer"
    ],
    "sg:website": "http://www.coopertire.com/html/",
    "wof:name": "B\u0026R Wholesale Tire",
    "wof:placetype": "venue"
  },
  "geometry": {"coordinates":[-80.711065,41.099552],"type":"Point"}
}
