{
  "type": "Feature",
  "properties": {
    "iso:country":"US",
    "sg:address":"116 S Meridian Rd",
    "sg:city":"Youngstown",
    "sg:classifiers":[
        {
            "category":"Manufacturing",
            "subcategory":"Rubber & Plastics",
            "type":"Manufacturing & Wholesale Goods"
        },
        {
            "category":"Autos & Motor Vehicles",
            "subcategory":"Auto Supplies",
            "type":"Retail Goods"
        },
        {
            "category":"Retail",
            "subcategory":"Auto Repair",
            "type":"Services"
        }
    ],
    "sg:phone":"+1 330 799 9274",
    "sg:postcode":"44509",
    "sg:province":"OH",
    "sg:tags":[
        "tires-wholesale",
        "tire",
        "retread",
        "recap",
        "manufacturer"
    ],
    "sg:website":"http://www.coopertire.com/html/",
    "wof:name":"B&R Wholesale Tire",
    "wof:placetype":"venue"
},
  "geometry": {"coordinates":[-80.711065,41.099552],"type":"Point"}
}