{
  "type": "Feature",
  "properties": {
    "addr:full": "10145 Avon Lake Rd Burbank OH 44214",
    "addr:housenumber": "10145",
    "addr:postcode": "44214",
    "addr:street": "Avon Lake Rd",
    "iso:country": "US",
    "sg:address": "10145 Avon Lake Rd",
    "sg:city": "Burbank",
    "sg:classifiers": [
      {
        "category": "Autos \u0026 Motor Vehicles",
        "subcategory": "Fuel \u0026 Gas Station",
        "type": "Retail Goods"
      }
    ],
    "sg:phone": "+1 330 624 2701",
    "sg:postcode": "44214",
    "sg:province": "OH",
    "wof:name": "Duke Oil Co",
    "wof:placetype": "venue"
  },
  "geometry": {"coordinates":[-81.996498,40.9991],"type":"Point"}
}
