{
  "type": "Feature",
  "properties": {
    "iso:country":"US",
    "sg:address":"10145 Avon Lake Rd",
    "sg:city":"Burbank",
    "sg:classifiers":[
        {
            "category":"Autos & Motor Vehicles",
            "subcategory":"Fuel & Gas Station",
            "type":"Retail Goods"
        }
    ],
    "sg:phone":"+1 330 624 2701",
    "sg:postcode":"44214",
    "sg:province":"OH",
    "wof:name":"Duke Oil Co",
    "wof:placetype":"venue"
},
  "geometry": {"coordinates":[-81.996498,40.9991],"type":"Point"}
}