{
  "type": "Feature",
  "properties": {
    "addr:full": "9090 Cox Rd West Chester OH 45069",
    "addr:housenumber": "9090",
    "addr:postcode": "45069",
    "addr:street": "Cox Rd",
    "iso:country": "US",
    "sg:address": "9090 Cox Rd",
    "sg:city": "West Chester",
    "sg:classifiers": [
      {
        "category": "Social Services",
        "subcategory": "Adult Care",
        "type": "Services"
      }
    ],
    "sg:phone": "+1 513 867 1998",
    "sg:postcode": "45069",
    "sg:province": "OH",
    "sg:tags": [
      "organization",
      "senior",
      "citizen"
    ],
    "wof:name": "Senior Citizens Inc",
    "wof:placetype": "venue"
  },
  "geometry": {"coordinates":[-84.3679,39.3213],"type":"Point"}
}
