{
  "type": "Feature",
  "properties": {
    "iso:country":"US",
    "sg:address":"3948 Holman Cir",
    "sg:city":"Cincinnati",
    "sg:classifiers":[
        {
            "category":"Building & Trades",
            "subcategory":"Cleaning & Sanitation",
            "type":"Services"
        }
    ],
    "sg:phone":"+1 513 221 2700",
    "sg:postcode":"45236",
    "sg:province":"OH",
    "sg:tags":[
        "janitor"
    ],
    "wof:name":"L & B Cleaning Svc LLC",
    "wof:placetype":"venue"
},
  "geometry": {"coordinates":[-84.40308400000001,39.188277],"type":"Point"}
}