{
  "type": "Feature",
  "properties": {
    "addr:full": "35546 Vickers Rd Union Furnace OH 43158",
    "addr:postcode": "35546;43158",
    "addr:street": "Vickers Rd",
    "iso:country": "US",
    "sg:address": "35546 Vickers Rd",
    "sg:city": "Union Furnace",
    "sg:classifiers": [
      {
        "category": "Building \u0026 Trades",
        "subcategory": "Construction",
        "type": "Services"
      }
    ],
    "sg:phone": "+1 740 385 5586",
    "sg:postcode": "43158",
    "sg:province": "OH",
    "sg:tags": [
      "roofing",
      "contractor"
    ],
    "wof:name": "B \u0026 B Roofing",
    "wof:placetype": "venue"
  },
  "geometry": {"coordinates":[-82.366744,39.454672],"type":"Point"}
}
