{
  "type": "Feature",
  "properties": {
    "addr:full": "1737 E Ohio Pike Amelia OH 45102",
    "addr:housenumber": "1737",
    "addr:postcode": "45102",
    "addr:street": "E Ohio Pike",
    "iso:country": "US",
    "sg:address": "1737 E Ohio Pike",
    "sg:city": "Amelia",
    "sg:classifiers": [
      {
        "category": "Shopping",
        "subcategory": "Computers \u0026 Home Electronics",
        "type": "Retail Goods"
      }
    ],
    "sg:phone": "+1 513 797 8439",
    "sg:postcode": "45102",
    "sg:province": "OH",
    "sg:tags": [
      "equipment",
      "satellite",
      "system"
    ],
    "wof:name": "Home Satellite Express",
    "wof:placetype": "venue"
  },
  "geometry": {"coordinates":[-84.205811,39.019799],"type":"Point"}
}
