{
  "type": "Feature",
  "properties": {
    "iso:country":"US",
    "sg:address":"1701 E 12th St",
    "sg:city":"Cleveland",
    "sg:classifiers":[
        {
            "category":"Building & Trades",
            "subcategory":"Construction",
            "type":"Services"
        }
    ],
    "sg:phone":"+1 216 861 3960",
    "sg:postcode":"44114",
    "sg:province":"OH",
    "sg:tags":[
        "general",
        "contractor"
    ],
    "wof:name":"G Properties Inc",
    "wof:placetype":"venue"
},
  "geometry": {"coordinates":[-81.68615200000001,41.50345],"type":"Point"}
}