{
  "type": "Feature",
  "properties": {
    "addr:full": "1701 E 12th St Cleveland OH 44114",
    "addr:housenumber": "1701",
    "addr:postcode": "44114",
    "addr:street": "E 12Th St",
    "iso:country": "US",
    "sg:address": "1701 E 12th St",
    "sg:city": "Cleveland",
    "sg:classifiers": [
      {
        "category": "Building \u0026 Trades",
        "subcategory": "Construction",
        "type": "Services"
      }
    ],
    "sg:phone": "+1 216 861 3960",
    "sg:postcode": "44114",
    "sg:province": "OH",
    "sg:tags": [
      "general",
      "contractor"
    ],
    "wof:name": "G Properties Inc",
    "wof:placetype": "venue"
  },
  "geometry": {"coordinates":[-81.686152,41.50345],"type":"Point"}
}
