{
  "type": "Feature",
  "properties": {
    "addr:full": "11735 Detroit Ave Cleveland OH 44107",
    "addr:housenumber": "11735",
    "addr:postcode": "44107",
    "addr:street": "Detroit Ave",
    "iso:country": "US",
    "sg:address": "11735 Detroit Ave",
    "sg:city": "Cleveland",
    "sg:classifiers": [
      {
        "category": "Autos \u0026 Motor Vehicles",
        "subcategory": "Automobile Sales",
        "type": "Retail Goods"
      }
    ],
    "sg:phone": "+1 216 228 2290",
    "sg:postcode": "44107",
    "sg:province": "OH",
    "sg:tags": [
      "car",
      "dealer"
    ],
    "wof:name": "American Coach Sales",
    "wof:placetype": "venue"
  },
  "geometry": {"coordinates":[-81.76983,41.48363],"type":"Point"}
}
