{
  "type": "Feature",
  "properties": {
    "addr:full":"461 Bedford Rd SE Brookfield OH 44403",
    "addr:housenumber":"461",
    "addr:postcode":"44403",
    "addr:street":"Bedford Rd Se",
    "iso:country":"US",
    "sg:address":"461 Bedford Rd SE",
    "sg:city":"Brookfield",
    "sg:classifiers":[
        {
            "category":"Retail",
            "subcategory":"Auto Repair",
            "type":"Services"
        }
    ],
    "sg:phone":"+1 330 448 4400",
    "sg:postcode":"44403",
    "sg:province":"OH",
    "sg:tags":[
        "wrecker"
    ],
    "wof:name":"Carpenter's Towing",
    "wof:placetype":"venue"
},
  "geometry": {"coordinates":[-80.56269399999999,41.232254],"type":"Point"}
}