{
  "type": "Feature",
  "properties": {
    "addr:full":"3422 South Ave Youngstown OH 44502",
    "addr:housenumber":"3422",
    "addr:postcode":"44502",
    "addr:street":"South Ave",
    "iso:country":"US",
    "sg:address":"3422 South Ave",
    "sg:city":"Youngstown",
    "sg:classifiers":[
        {
            "category":"Retail",
            "subcategory":"Auto Repair",
            "type":"Services"
        }
    ],
    "sg:phone":"+1 330 781 0952",
    "sg:postcode":"44502",
    "sg:province":"OH",
    "sg:tags":[
        "repairing",
        "automobile"
    ],
    "wof:name":"Vargo's Automotive & To",
    "wof:placetype":"venue"
},
  "geometry": {"coordinates":[-80.646207,41.064482],"type":"Point"}
}