{
  "type": "Feature",
  "properties": {
    "iso:country":"US",
    "sg:address":"1101 Bellefontaine St",
    "sg:city":"Wapakoneta",
    "sg:classifiers":[
        {
            "category":"Home & Garden",
            "subcategory":"Furniture",
            "type":"Retail Goods"
        }
    ],
    "sg:phone":"+1 419 738 2273",
    "sg:postcode":"45895",
    "sg:province":"OH",
    "wof:name":"Bed Rock Beds",
    "wof:placetype":"venue"
},
  "geometry": {"coordinates":[-84.179757,40.565646],"type":"Point"}
}