{
  "type": "Feature",
  "properties": {
    "addr:full": "4376 Glendale Milford Rd Cincinnati OH 45242",
    "addr:housenumber": "4376",
    "addr:postcode": "45242",
    "addr:street": "Glendale Milford Rd",
    "iso:country": "US",
    "sg:address": "4376 Glendale Milford Rd",
    "sg:city": "Cincinnati",
    "sg:classifiers": [
      {
        "category": "Communications",
        "subcategory": "Newspaper",
        "type": "Services"
      },
      {
        "category": "Wholesale",
        "subcategory": "Books, Periodicals, \u0026 Newspapers",
        "type": "Manufacturing \u0026 Wholesale Goods"
      }
    ],
    "sg:phone": "+1 513 733 3386",
    "sg:postcode": "45242",
    "sg:province": "OH",
    "sg:tags": [
      "dealers-wholesale",
      "news"
    ],
    "sg:website": "http://www.jconline.com",
    "wof:name": "U S A Today",
    "wof:placetype": "venue"
  },
  "geometry": {"coordinates":[-84.386936,39.251956],"type":"Point"}
}
