{
  "type": "Feature",
  "properties": {
    "iso:country":"US",
    "sg:address":"2205 Pavonia Rd",
    "sg:city":"Mansfield",
    "sg:classifiers":[
        {
            "category":"Manufacturing",
            "subcategory":"Retail Goods",
            "type":"Manufacturing & Wholesale Goods"
        }
    ],
    "sg:phone":"+1 419 589 4500",
    "sg:postcode":"44903",
    "sg:province":"OH",
    "sg:tags":[
        "candle"
    ],
    "wof:name":"Cameo Candles",
    "wof:placetype":"venue"
},
  "geometry": {"coordinates":[-82.435626,40.814635],"type":"Point"}
}