{
  "type": "Feature",
  "properties": {
    "addr:full": "2340 Victory Pkwy Cincinnati OH 45206",
    "addr:housenumber": "2340",
    "addr:postcode": "45206",
    "addr:street": "Victory Pkwy",
    "iso:country": "US",
    "sg:address": "2340 Victory Pkwy",
    "sg:city": "Cincinnati",
    "sg:classifiers": [
      {
        "category": "Professional",
        "type": "Services"
      }
    ],
    "sg:phone": "+1 513 961 6626",
    "sg:postcode": "45206",
    "sg:province": "OH",
    "wof:name": "New Orphan Asylum Scholar",
    "wof:placetype": "venue"
  },
  "geometry": {"coordinates":[-84.484481,39.124945],"type":"Point"}
}
