{
  "type": "Feature",
  "properties": {
    "iso:country":"US",
    "sg:address":"1814 Brice Rd",
    "sg:city":"Reynoldsburg",
    "sg:classifiers":[
        {
            "category":"Building & Trades",
            "subcategory":"Electrical",
            "type":"Services"
        },
        {
            "category":"Wholesale",
            "subcategory":"Electrical",
            "type":"Manufacturing & Wholesale Goods"
        }
    ],
    "sg:phone":"+1 614 759 9525",
    "sg:postcode":"43068",
    "sg:province":"OH",
    "sg:tags":[
        "equipment",
        "supply",
        "electric",
        "contractor"
    ],
    "wof:name":"Loeb Electric Company",
    "wof:placetype":"venue"
},
  "geometry": {"coordinates":[-82.829793,39.942344],"type":"Point"}
}