{
  "type": "Feature",
  "properties": {
    "addr:full":"367 Woodland Ave Elyria OH 44035",
    "addr:housenumber":"367",
    "addr:postcode":"44035",
    "addr:street":"Woodland Ave",
    "iso:country":"US",
    "sg:address":"367 Woodland Ave",
    "sg:city":"Elyria",
    "sg:classifiers":[
        {
            "category":"Wholesale",
            "subcategory":"Non-durable Goods",
            "type":"Manufacturing & Wholesale Goods"
        }
    ],
    "sg:phone":"+1 440 322 4581",
    "sg:postcode":"44035",
    "sg:province":"OH",
    "wof:name":"Lorain Imports",
    "wof:placetype":"venue"
},
  "geometry": {"coordinates":[-82.127938,41.376208],"type":"Point"}
}