{
  "type": "Feature",
  "properties": {
    "addr:full": "192 E Main St Lexington OH 44904",
    "addr:housenumber": "192",
    "addr:postcode": "44904",
    "addr:street": "E Main St",
    "iso:country": "US",
    "sg:address": "192 E Main St",
    "sg:city": "Lexington",
    "sg:classifiers": [
      {
        "category": "Bars \u0026 Pubs",
        "type": "Food \u0026 Drink"
      }
    ],
    "sg:menulink": "http://www.allmenus.com/oh/troy/245153-bucks-bar--grill/menu/",
    "sg:phone": "+1 419 884 2825",
    "sg:postcode": "44904",
    "sg:province": "OH",
    "sg:tags": [
      "american"
    ],
    "wof:name": "Buck's Bar \u0026 Grill",
    "wof:placetype": "venue"
  },
  "geometry": {"coordinates":[-82.575894,40.678598],"type":"Point"}
}
