{
  "type": "Feature",
  "properties": {
    "iso:country":"US",
    "sg:address":"192 E Main St",
    "sg:city":"Lexington",
    "sg:classifiers":[
        {
            "category":"Bars & Pubs",
            "type":"Food & Drink"
        }
    ],
    "sg:menulink":"http://www.allmenus.com/oh/troy/245153-bucks-bar--grill/menu/",
    "sg:phone":"+1 419 884 2825",
    "sg:postcode":"44904",
    "sg:province":"OH",
    "sg:tags":[
        "american"
    ],
    "wof:name":"Buck's Bar & Grill",
    "wof:placetype":"venue"
},
  "geometry": {"coordinates":[-82.57589400000001,40.678598],"type":"Point"}
}