{
  "type": "Feature",
  "properties": {
    "iso:country":"US",
    "sg:address":"6845 Lexington Park Blvd",
    "sg:city":"Mason",
    "sg:classifiers":[
        {
            "category":"Shopping",
            "subcategory":"Gifts & Souvenirs",
            "type":"Retail Goods"
        }
    ],
    "sg:phone":"+1 513 573 0330",
    "sg:postcode":"45040",
    "sg:province":"OH",
    "wof:name":"Simple Gifts By Darla",
    "wof:placetype":"venue"
},
  "geometry": {"coordinates":[-84.314272,39.341623],"type":"Point"}
}