{
  "type": "Feature",
  "properties": {
    "addr:full":"10611 Lorain Ave Cleveland OH 44111",
    "addr:housenumber":"10611",
    "addr:postcode":"44111",
    "addr:street":"Lorain Ave",
    "iso:country":"US",
    "sg:address":"10611 Lorain Ave",
    "sg:city":"Cleveland",
    "sg:classifiers":[
        {
            "category":"Shopping",
            "type":"Retail Goods"
        }
    ],
    "sg:phone":"+1 216 252 5000",
    "sg:postcode":"44111",
    "sg:province":"OH",
    "sg:tags":[
        "telephone",
        "cellular"
    ],
    "wof:name":"Perfect Cellular",
    "wof:placetype":"venue"
},
  "geometry": {"coordinates":[-81.76195199999999,41.46411],"type":"Point"}
}