{
  "type": "Feature",
  "properties": {
    "addr:full": "7666 Greenville-Celina Rd Greenville OH 45331",
    "addr:housenumber": "7666",
    "addr:postcode": "45331",
    "addr:street": "Greenville-Celina Rd",
    "iso:country": "US",
    "sg:address": "7666 Greenville-Celina Rd",
    "sg:city": "Greenville",
    "sg:classifiers": [
      {
        "category": "Government",
        "subcategory": "Office",
        "type": "Public Place"
      }
    ],
    "sg:phone": "+1 937 548 3445",
    "sg:postcode": "45331",
    "sg:province": "OH",
    "sg:tags": [
      "general"
    ],
    "wof:name": "Darke County Ditch Maintenance",
    "wof:placetype": "venue"
  },
  "geometry": {"coordinates":[-84.61514,40.13977],"type":"Point"}
}
