{
  "type": "Feature",
  "properties": {
    "iso:country":"US",
    "sg:address":"6195 Colerain Ave",
    "sg:city":"Cincinnati",
    "sg:classifiers":[
        {
            "category":"Building & Trades",
            "subcategory":"Plumbing",
            "type":"Services"
        }
    ],
    "sg:phone":"+1 513 923 1962",
    "sg:postcode":"45239",
    "sg:province":"OH",
    "sg:tags":[
        "commercial",
        "refrigeration",
        "contractor"
    ],
    "wof:name":"Hamilton County Refrigeration",
    "wof:placetype":"venue"
},
  "geometry": {"coordinates":[-84.582498,39.204772],"type":"Point"}
}