{
  "type": "Feature",
  "properties": {
    "iso:country":"US",
    "sg:address":"1220 E Elm St",
    "sg:city":"Lima",
    "sg:classifiers":[
        {
            "category":"Health Services",
            "subcategory":"Doctor",
            "type":"Services"
        }
    ],
    "sg:phone":"+1 419 224 1500",
    "sg:postcode":"45804",
    "sg:province":"OH",
    "sg:tags":[
        "medical"
    ],
    "wof:name":"Medina Rhonda MD LLC",
    "wof:placetype":"venue"
},
  "geometry": {"coordinates":[-84.08722,40.73769],"type":"Point"}
}