{
  "type": "Feature",
  "properties": {
    "addr:full": "1666 N High St Columbus OH 43201",
    "addr:housenumber": "1666",
    "addr:postcode": "43201",
    "addr:street": "N High St",
    "iso:country": "US",
    "sg:address": "1666 N High St",
    "sg:city": "Columbus",
    "sg:classifiers": [
      {
        "category": "Restaurant",
        "type": "Food \u0026 Drink"
      }
    ],
    "sg:menulink": "http://www.allmenus.com/oh/columbus/19530-wg-grinders/menu/",
    "sg:phone": "+1 614 294 3257",
    "sg:postcode": "43201",
    "sg:province": "OH",
    "sg:tags": [
      "wrap",
      "american",
      "sandwich",
      "pizza"
    ],
    "wof:name": "W.G. Grinders",
    "wof:placetype": "venue"
  },
  "geometry": {"coordinates":[-83.007154,39.996213],"type":"Point"}
}
