{
  "type": "Feature",
  "properties": {
    "addr:full": "92 Main St Bellville OH 44813",
    "addr:housenumber": "92",
    "addr:postcode": "44813",
    "addr:street": "Main St",
    "iso:country": "US",
    "sg:address": "92 Main St",
    "sg:city": "Bellville",
    "sg:classifiers": [
      {
        "category": "Shopping",
        "subcategory": "Florist",
        "type": "Retail Goods"
      }
    ],
    "sg:phone": "+1 419 886 4810",
    "sg:postcode": "44813",
    "sg:province": "OH",
    "wof:name": "Bellville Flowers \u0026 Gifts",
    "wof:placetype": "venue"
  },
  "geometry": {"coordinates":[-82.51137,40.621484],"type":"Point"}
}
