{
  "type": "Feature",
  "properties": {
    "iso:country":"US",
    "sg:address":"8000 Tyler Blvd",
    "sg:city":"Mentor",
    "sg:classifiers":[
        {
            "category":"Wholesale",
            "subcategory":"Medical Equipment & Supplies",
            "type":"Manufacturing & Wholesale Goods"
        },
        {
            "category":"Health Services",
            "subcategory":"Clinic",
            "type":"Services"
        }
    ],
    "sg:phone":"+1 440 701 1200",
    "sg:postcode":"44060",
    "sg:province":"OH",
    "wof:name":"Sourceone Healthcare Tech OH",
    "wof:placetype":"venue"
},
  "geometry": {"coordinates":[-81.354562,41.682269],"type":"Point"}
}