{
  "type": "Feature",
  "properties": {
    "iso:country":"US",
    "sg:address":"9134 Union Cemetery Rd",
    "sg:city":"Cincinnati",
    "sg:classifiers":[
        {
            "category":"Restaurant",
            "type":"Food & Drink"
        }
    ],
    "sg:phone":"+1 513 677 6253",
    "sg:postcode":"45249",
    "sg:province":"OH",
    "wof:name":"China House",
    "wof:placetype":"venue"
},
  "geometry": {"coordinates":[-84.305458,39.2885],"type":"Point"}
}