{
  "type": "Feature",
  "properties": {
    "addr:full": "42 N Sandusky St Delaware OH 43015",
    "addr:housenumber": "42",
    "addr:postcode": "43015",
    "addr:street": "N Sandusky St",
    "iso:country": "US",
    "sg:address": "42 N Sandusky St",
    "sg:city": "Delaware",
    "sg:classifiers": [
      {
        "category": "Insurance",
        "subcategory": "Insurance Agent",
        "type": "Services"
      }
    ],
    "sg:phone": "+1 740 369 9641",
    "sg:postcode": "43015",
    "sg:province": "OH",
    "wof:name": "Hilborn Insurance",
    "wof:placetype": "venue"
  },
  "geometry": {"coordinates":[-83.067471,40.30142],"type":"Point"}
}
