{
  "type": "Feature",
  "properties": {
    "iso:country":"US",
    "sg:address":"64322 Wintergreen Rd",
    "sg:city":"Lore City",
    "sg:classifiers":[
        {
            "category":"Food & Beverages",
            "subcategory":"Groceries & Convenience Stores",
            "type":"Retail Goods"
        }
    ],
    "sg:phone":"+1 740 489 5566",
    "sg:postcode":"43755",
    "sg:province":"OH",
    "sg:tags":[
        "station",
        "gas"
    ],
    "wof:name":"Go-Mart 57",
    "wof:placetype":"venue"
},
  "geometry": {"coordinates":[-81.455432,40.021217],"type":"Point"}
}