{
  "type": "Feature",
  "properties": {
    "iso:country":"US",
    "sg:address":"5179 Miller-Paul Rd",
    "sg:city":"Westerville",
    "sg:classifiers":[
        {
            "category":"Banks & Credit Unions",
            "subcategory":"Financial Services",
            "type":"Services"
        }
    ],
    "sg:phone":"+1 740 965 1957",
    "sg:postcode":"43082",
    "sg:province":"OH",
    "sg:tags":[
        "house",
        "construction",
        "investor"
    ],
    "wof:name":"Becker Capital Corp",
    "wof:placetype":"venue"
},
  "geometry": {"coordinates":[-82.826393,40.156792],"type":"Point"}
}