{
  "type": "Feature",
  "properties": {
    "addr:full":"720 Mound Rd Miamisburg OH 45342",
    "addr:housenumber":"720",
    "addr:postcode":"45342",
    "addr:street":"Mound Rd",
    "iso:country":"US",
    "sg:address":"720 Mound Rd",
    "sg:city":"Miamisburg",
    "sg:classifiers":[
        {
            "category":"Professional",
            "subcategory":"Research",
            "type":"Services"
        }
    ],
    "sg:phone":"+1 937 865 4491",
    "sg:postcode":"45342",
    "sg:province":"OH",
    "sg:tags":[
        "development",
        "laboratory"
    ],
    "wof:name":"Inorganic Specialists",
    "wof:placetype":"venue"
},
  "geometry": {"coordinates":[-84.27851099999999,39.621828],"type":"Point"}
}