{
  "type": "Feature",
  "properties": {
    "addr:full": "8115 Springer Dr Willoughby OH 44094",
    "addr:housenumber": "8115",
    "addr:postcode": "44094",
    "addr:street": "Springer Dr",
    "iso:country": "US",
    "sg:address": "8115 Springer Dr",
    "sg:city": "Willoughby",
    "sg:classifiers": [
      {
        "category": "Home \u0026 Garden",
        "subcategory": "Building Materials",
        "type": "Retail Goods"
      }
    ],
    "sg:phone": "+1 440 256 8841",
    "sg:postcode": "44094",
    "sg:province": "OH",
    "sg:tags": [
      "plumbing",
      "fixture",
      "supply"
    ],
    "wof:name": "Cover Plumbing \u0026 Heating Inc",
    "wof:placetype": "venue"
  },
  "geometry": {"coordinates":[-81.350749,41.588848],"type":"Point"}
}
