{
  "type": "Feature",
  "properties": {
    "addr:full": "130 W 2nd St Dayton OH 45402",
    "addr:housenumber": "130",
    "addr:postcode": "45402",
    "addr:street": "W 2Nd St",
    "iso:country": "US",
    "sg:address": "130 W 2nd St",
    "sg:city": "Dayton",
    "sg:classifiers": [
      {
        "category": "Professional",
        "subcategory": "Lawyer \u0026 Legal Services",
        "type": "Services"
      }
    ],
    "sg:phone": "+1 937 223 2200",
    "sg:postcode": "45402",
    "sg:province": "OH",
    "sg:tags": [
      "attorney"
    ],
    "wof:name": "Sam G Caras Co",
    "wof:placetype": "venue"
  },
  "geometry": {"coordinates":[-84.195181,39.760428],"type":"Point"}
}
