{
  "type": "Feature",
  "properties": {
    "iso:country":"US",
    "sg:address":"2712 W Sylvania Ave",
    "sg:city":"Toledo",
    "sg:classifiers":[
        {
            "category":"Shopping",
            "type":"Retail Goods"
        }
    ],
    "sg:phone":"+1 419 474 1291",
    "sg:postcode":"43613",
    "sg:province":"OH",
    "sg:tags":[
        "merchandise"
    ],
    "wof:name":"Framed Art Factory Outlet",
    "wof:placetype":"venue"
},
  "geometry": {"coordinates":[-83.609032,41.692138],"type":"Point"}
}