{
  "type": "Feature",
  "properties": {
    "addr:full": "7015 Krick Rd Bedford OH 44146",
    "addr:housenumber": "7015",
    "addr:postcode": "44146",
    "addr:street": "Krick Rd",
    "iso:country": "US",
    "sg:address": "7015 Krick Rd",
    "sg:city": "Bedford",
    "sg:classifiers": [
      {
        "category": "Building \u0026 Trades",
        "subcategory": "Construction",
        "type": "Services"
      }
    ],
    "sg:phone": "+1 440 439 4404",
    "sg:postcode": "44146",
    "sg:province": "OH",
    "sg:tags": [
      "roofing",
      "sheet",
      "metal",
      "contractor"
    ],
    "wof:name": "A C Holding Co",
    "wof:placetype": "venue"
  },
  "geometry": {"coordinates":[-81.529577,41.372794],"type":"Point"}
}
