{
  "type": "Feature",
  "properties": {
    "addr:full": "7251 Engle Rd Cleveland OH 44130",
    "addr:housenumber": "7251",
    "addr:postcode": "44130",
    "addr:street": "Engle Rd",
    "iso:country": "US",
    "sg:address": "7251 Engle Rd",
    "sg:city": "Cleveland",
    "sg:classifiers": [
      {
        "category": "Health Services",
        "subcategory": "Health Practitioner",
        "type": "Services"
      }
    ],
    "sg:phone": "+1 440 234 5515",
    "sg:postcode": "44130",
    "sg:province": "OH",
    "sg:tags": [
      "audiologists"
    ],
    "wof:name": "Hearing Doctors Of Ohio",
    "wof:placetype": "venue"
  },
  "geometry": {"coordinates":[-81.825074,41.365029],"type":"Point"}
}
