{
  "type": "Feature",
  "properties": {
    "addr:full":"9620 Diamond Centre Dr Mentor OH 44060",
    "addr:housenumber":"9620",
    "addr:postcode":"44060",
    "addr:street":"Diamond Centre",
    "iso:country":"US",
    "sg:address":"9620 Diamond Centre Dr",
    "sg:city":"Mentor",
    "sg:classifiers":[
        {
            "category":"Shopping",
            "subcategory":"Department Store",
            "type":"Retail Goods"
        },
        {
            "category":"Shopping",
            "subcategory":"Bicycles & Sporting Goods",
            "type":"Retail Goods"
        }
    ],
    "sg:phone":"+1 440 639 8545",
    "sg:postcode":"44060",
    "sg:province":"OH",
    "sg:website":"www.gandermountain.com",
    "wof:name":"Gander Mountain 304",
    "wof:placetype":"venue"
},
  "geometry": {"coordinates":[-81.295008,41.714685],"type":"Point"}
}