{
  "type": "Feature",
  "properties": {
    "addr:full": "3725 Evansville Ave Dayton OH 45406",
    "addr:housenumber": "3725",
    "addr:postcode": "45406",
    "addr:street": "Evansville Ave",
    "iso:country": "US",
    "sg:address": "3725 Evansville Ave",
    "sg:city": "Dayton",
    "sg:classifiers": [
      {
        "category": "Building \u0026 Trades",
        "subcategory": "Construction",
        "type": "Services"
      }
    ],
    "sg:phone": "+1 937 277 7615",
    "sg:postcode": "45406",
    "sg:province": "OH",
    "sg:tags": [
      "general",
      "contractor"
    ],
    "sg:website": "www.kokosing-inc.com",
    "wof:name": "Kokosing Construction",
    "wof:placetype": "venue"
  },
  "geometry": {"coordinates":[-84.252612,39.799964],"type":"Point"}
}
