{
  "type": "Feature",
  "properties": {
    "addr:full": "4621 Hinckley Industrial Pkwy Cleveland OH 44109",
    "addr:postcode": "4621;44109",
    "addr:street": "Hinckley Industrial Pkwy",
    "iso:country": "US",
    "sg:address": "4621 Hinckley Industrial Pkwy",
    "sg:city": "Cleveland",
    "sg:classifiers": [
      {
        "category": "Building \u0026 Trades",
        "subcategory": "Landscaping Services",
        "type": "Services"
      },
      {
        "category": "Building \u0026 Trades",
        "subcategory": "Pest Control",
        "type": "Services"
      }
    ],
    "sg:phone": "+1 216 741 0550",
    "sg:postcode": "44109",
    "sg:province": "OH",
    "sg:tags": [
      "lawn",
      "landscape",
      "maintenance",
      "contractor"
    ],
    "sg:website": "http://iyp.scottslawnservice.com",
    "wof:name": "Scotts LawnService",
    "wof:placetype": "venue"
  },
  "geometry": {"coordinates":[-81.679816,41.433212],"type":"Point"}
}
