{
  "type": "Feature",
  "properties": {
    "addr:full":"1895 Cooper Foster Park Rd Amherst OH 44001",
    "addr:housenumber":"1895",
    "addr:postcode":"44001",
    "addr:street":"Cooper Foster Park Rd",
    "iso:country":"US",
    "sg:address":"1895 Cooper Foster Park Rd",
    "sg:city":"Amherst",
    "sg:classifiers":[
        {
            "category":"Personal",
            "subcategory":"Beauty Salon",
            "type":"Services"
        }
    ],
    "sg:phone":"+1 440 960 9144",
    "sg:postcode":"44001",
    "sg:province":"OH",
    "wof:name":"J Taylor Salon",
    "wof:placetype":"venue"
},
  "geometry": {"coordinates":[-82.21008500000001,41.418237],"type":"Point"}
}