{
  "type": "Feature",
  "properties": {
    "addr:full": "14158 Triskett Rd Cleveland OH 44111",
    "addr:housenumber": "14158",
    "addr:postcode": "44111",
    "addr:street": "Triskett Rd",
    "iso:country": "US",
    "sg:address": "14158 Triskett Rd",
    "sg:city": "Cleveland",
    "sg:classifiers": [
      {
        "category": "Personal",
        "subcategory": "Barber",
        "type": "Services"
      }
    ],
    "sg:phone": "+1 216 941 4047",
    "sg:postcode": "44111",
    "sg:province": "OH",
    "wof:name": "Trisket Barber Shop",
    "wof:placetype": "venue"
  },
  "geometry": {"coordinates":[-81.791651,41.463286],"type":"Point"}
}
