{
  "type": "Feature",
  "properties": {
    "iso:country":"US",
    "sg:address":"12706 Watterson Ave",
    "sg:city":"Cleveland",
    "sg:classifiers":[
        {
            "category":"Freight",
            "type":"Transportation"
        }
    ],
    "sg:phone":"+1 216 991 7922",
    "sg:postcode":"44105",
    "sg:province":"OH",
    "sg:tags":[
        "trucking"
    ],
    "wof:name":"Ellis Trucking",
    "wof:placetype":"venue"
},
  "geometry": {"coordinates":[-81.593288,41.451474],"type":"Point"}
}