{
  "type": "Feature",
  "properties": {
    "addr:full":"3553 Larkspur Ave Cincinnati OH 45208",
    "addr:housenumber":"3553",
    "addr:postcode":"45208",
    "addr:street":"Larkspur Ave",
    "iso:country":"US",
    "sg:address":"3553 Larkspur Ave",
    "sg:city":"Cincinnati",
    "sg:classifiers":[
        {
            "category":"Banks & Credit Unions",
            "subcategory":"Investment Brokerage",
            "type":"Services"
        }
    ],
    "sg:phone":"+1 513 871 1078",
    "sg:postcode":"45208",
    "sg:province":"OH",
    "sg:tags":[
        "advisory",
        "financial"
    ],
    "wof:name":"Celtic Capital",
    "wof:placetype":"venue"
},
  "geometry": {"coordinates":[-84.455692,39.143251],"type":"Point"}
}