{
  "type": "Feature",
  "properties": {
    "addr:full": "4520 Whipple Ave NW Canton OH 44718",
    "addr:housenumber": "4520",
    "addr:postcode": "44718",
    "addr:street": "Whipple Ave Nw",
    "iso:country": "US",
    "sg:address": "4520 Whipple Ave NW",
    "sg:city": "Canton",
    "sg:classifiers": [
      {
        "category": "Retail",
        "subcategory": "Car Wash",
        "type": "Services"
      }
    ],
    "sg:phone": "+1 330 493 4870",
    "sg:postcode": "44718",
    "sg:province": "OH",
    "sg:tags": [
      "truck",
      "cleaning"
    ],
    "wof:name": "Mobil Pressure Wash",
    "wof:placetype": "venue"
  },
  "geometry": {"coordinates":[-81.423263,40.848565],"type":"Point"}
}
