{
  "type": "Feature",
  "properties": {
    "addr:full": "1492 E Broad St Columbus OH 43205",
    "addr:housenumber": "1492",
    "addr:postcode": "43205",
    "addr:street": "E Broad St",
    "iso:country": "US",
    "sg:address": "1492 E Broad St",
    "sg:city": "Columbus",
    "sg:classifiers": [
      {
        "category": "Health Services",
        "subcategory": "Doctor",
        "type": "Services"
      }
    ],
    "sg:phone": "+1 614 252 1500",
    "sg:postcode": "43205",
    "sg:province": "OH",
    "sg:tags": [
      "physician",
      "surgeon"
    ],
    "wof:name": "Pain Management Consortium",
    "wof:placetype": "venue"
  },
  "geometry": {"coordinates":[-82.961779,39.966694],"type":"Point"}
}
