{
  "type": "Feature",
  "properties": {
    "addr:full": "4007 Bach Buxton Rd Amelia OH 45102",
    "addr:postcode": "4007;45102",
    "addr:street": "Buxton Rd",
    "iso:country": "US",
    "sg:address": "4007 Bach Buxton Rd",
    "sg:city": "Amelia",
    "sg:classifiers": [
      {
        "category": "Wholesale",
        "subcategory": "Machinery \u0026 Supplies",
        "type": "Manufacturing \u0026 Wholesale Goods"
      }
    ],
    "sg:phone": "+1 513 752 5600",
    "sg:postcode": "45102",
    "sg:province": "OH",
    "sg:tags": [
      "valve"
    ],
    "wof:name": "Ohio Valve Co",
    "wof:placetype": "venue"
  },
  "geometry": {"coordinates":[-84.245368,39.065789],"type":"Point"}
}
