{
  "type": "Feature",
  "properties": {
    "iso:country":"US",
    "sg:address":"4007 Bach Buxton Rd",
    "sg:city":"Amelia",
    "sg:classifiers":[
        {
            "category":"Wholesale",
            "subcategory":"Machinery & Supplies",
            "type":"Manufacturing & Wholesale Goods"
        }
    ],
    "sg:phone":"+1 513 752 5600",
    "sg:postcode":"45102",
    "sg:province":"OH",
    "sg:tags":[
        "valve"
    ],
    "wof:name":"Ohio Valve Co",
    "wof:placetype":"venue"
},
  "geometry": {"coordinates":[-84.245368,39.065789],"type":"Point"}
}