{
  "type": "Feature",
  "properties": {
    "addr:full":"9076 Neil Dr Cincinnati OH 45231",
    "addr:housenumber":"9076",
    "addr:postcode":"45231",
    "addr:street":"Neil Dr",
    "iso:country":"US",
    "sg:address":"9076 Neil Dr",
    "sg:city":"Cincinnati",
    "sg:classifiers":[
        {
            "category":"Wholesale",
            "subcategory":"Sporting Goods",
            "type":"Manufacturing & Wholesale Goods"
        }
    ],
    "sg:phone":"+1 513 729 1369",
    "sg:postcode":"45231",
    "sg:province":"OH",
    "wof:name":"Liner Specialist",
    "wof:placetype":"venue"
},
  "geometry": {"coordinates":[-84.570499,39.235414],"type":"Point"}
}