{
  "type": "Feature",
  "properties": {
    "addr:full": "13896 Cochran Rd New Weston OH 45348",
    "addr:housenumber": "13896",
    "addr:postcode": "45348",
    "addr:street": "Cochran Rd",
    "iso:country": "US",
    "sg:address": "13896 Cochran Rd",
    "sg:city": "New Weston",
    "sg:classifiers": [
      {
        "category": "Farming",
        "subcategory": "Farm",
        "type": "Manufacturing \u0026 Wholesale Goods"
      }
    ],
    "sg:phone": "+1 937 338 3771",
    "sg:postcode": "45348",
    "sg:province": "OH",
    "sg:tags": [
      "crop",
      "general"
    ],
    "wof:name": "Steven Keller",
    "wof:placetype": "venue"
  },
  "geometry": {"coordinates":[-84.693961,40.316802],"type":"Point"}
}
