{
  "type": "Feature",
  "properties": {
    "iso:country":"US",
    "sg:address":"608 W High St",
    "sg:city":"Lima",
    "sg:classifiers":[
        {
            "category":"Health Services",
            "subcategory":"Clinic",
            "type":"Services"
        }
    ],
    "sg:phone":"+1 419 222 4474",
    "sg:postcode":"45801",
    "sg:province":"OH",
    "sg:tags":[
        "alcohol",
        "tobacco",
        "violence",
        "drug",
        "other",
        "educ",
        "prevention"
    ],
    "wof:name":"Lima Umadaop",
    "wof:placetype":"venue"
},
  "geometry": {"coordinates":[-84.113264,40.741436],"type":"Point"}
}