{
  "type": "Feature",
  "properties": {
    "iso:country":"US",
    "sg:address":"9950 Johnnycake Ridge Rd",
    "sg:city":"Painesville",
    "sg:classifiers":[
        {
            "category":"Restaurant",
            "type":"Food & Drink"
        }
    ],
    "sg:menulink":"http://www.allmenus.com/oh/concord/85890-zeppes-pizzeria/menu/",
    "sg:phone":"+1 440 357 5100",
    "sg:postcode":"44077",
    "sg:province":"OH",
    "sg:tags":[
        "american",
        "pizza"
    ],
    "wof:name":"Zeppe's Pizzeria",
    "wof:placetype":"venue"
},
  "geometry": {"coordinates":[-81.282923,41.680657],"type":"Point"}
}