{
  "type": "Feature",
  "properties": {
    "addr:full": "1230 Eastland Ave Akron OH 44305",
    "addr:housenumber": "1230",
    "addr:postcode": "44305",
    "addr:street": "Eastland Ave",
    "iso:country": "US",
    "sg:address": "1230 Eastland Ave",
    "sg:city": "Akron",
    "sg:classifiers": [
      {
        "category": "Shopping",
        "subcategory": "Clothing, Apparel, \u0026 Fashions",
        "type": "Retail Goods"
      }
    ],
    "sg:phone": "+1 330 630 5889",
    "sg:postcode": "44305",
    "sg:province": "OH",
    "sg:tags": [
      "alteration"
    ],
    "wof:name": "Alterations \u0026 Repair On Wheels",
    "wof:placetype": "venue"
  },
  "geometry": {"coordinates":[-81.454605,41.092898],"type":"Point"}
}
