{
  "type": "Feature",
  "properties": {
    "addr:full": "4066 Farrington Rd Covington OH 45318",
    "addr:housenumber": "4066",
    "addr:postcode": "45318",
    "addr:street": "Farrington Rd",
    "iso:country": "US",
    "sg:address": "4066 Farrington Rd",
    "sg:city": "Covington",
    "sg:classifiers": [
      {
        "category": "Home \u0026 Garden",
        "subcategory": "Garden Supply",
        "type": "Retail Goods"
      }
    ],
    "sg:phone": "+1 937 773 4292",
    "sg:postcode": "45318",
    "sg:province": "OH",
    "wof:name": "Dougs Lawnmowers",
    "wof:placetype": "venue"
  },
  "geometry": {"coordinates":[-84.279032,40.103621],"type":"Point"}
}
