{
  "type": "Feature",
  "properties": {
    "addr:full":"167 Beacon Hill Blvd Northfield OH 44067",
    "addr:housenumber":"167",
    "addr:postcode":"44067",
    "addr:street":"Beacon Hill Blvd",
    "iso:country":"US",
    "sg:address":"167 Beacon Hill Blvd",
    "sg:city":"Northfield",
    "sg:classifiers":[
        {
            "category":"Building & Trades",
            "subcategory":"Construction",
            "type":"Services"
        }
    ],
    "sg:phone":"+1 330 467 3390",
    "sg:postcode":"44067",
    "sg:province":"OH",
    "sg:tags":[
        "remodeling",
        "contractor"
    ],
    "wof:name":"Four Points Home Improvement",
    "wof:placetype":"venue"
},
  "geometry": {"coordinates":[-81.53174199999999,41.29654],"type":"Point"}
}