{
  "type": "Feature",
  "properties": {
    "addr:full": "3171 Republic Blvd N Toledo OH 43615",
    "addr:housenumber": "3171",
    "addr:postcode": "43615",
    "addr:street": "Republic Blvd N",
    "iso:country": "US",
    "sg:address": "3171 Republic Blvd N",
    "sg:city": "Toledo",
    "sg:classifiers": [
      {
        "category": "Autos \u0026 Motor Vehicles",
        "subcategory": "Auto Supplies",
        "type": "Retail Goods"
      }
    ],
    "sg:phone": "+1 419 841 7889",
    "sg:postcode": "43615",
    "sg:province": "OH",
    "sg:tags": [
      "filter",
      "gas"
    ],
    "wof:name": "Johnson Equipment Co",
    "wof:placetype": "venue"
  },
  "geometry": {"coordinates":[-83.674934,41.677137],"type":"Point"}
}
