{
  "type": "Feature",
  "properties": {
    "iso:country":"US",
    "sg:address":"19621 Euclid Ave",
    "sg:city":"Cleveland",
    "sg:classifiers":[
        {
            "category":"Autos & Motor Vehicles",
            "subcategory":"Auto Supplies",
            "type":"Retail Goods"
        },
        {
            "category":"Retail",
            "subcategory":"Auto Repair",
            "type":"Services"
        }
    ],
    "sg:phone":"+1 216 486 8743",
    "sg:postcode":"44117",
    "sg:province":"OH",
    "sg:tags":[
        "repairing",
        "automobile"
    ],
    "wof:name":"3 Way Automotive Inc",
    "wof:placetype":"venue"
},
  "geometry": {"coordinates":[-81.540936,41.563871],"type":"Point"}
}