{
  "type": "Feature",
  "properties": {
    "iso:country":"US",
    "sg:address":"597 Stewart Ln",
    "sg:city":"Mansfield",
    "sg:classifiers":[
        {
            "category":"Professional",
            "subcategory":"Advertising",
            "type":"Services"
        }
    ],
    "sg:phone":"+1 419 756 2940",
    "sg:postcode":"44907",
    "sg:province":"OH",
    "sg:tags":[
        "marketing",
        "agency"
    ],
    "wof:name":"Creative Associates Inc",
    "wof:placetype":"venue"
},
  "geometry": {"coordinates":[-82.538483,40.736504],"type":"Point"}
}