{
  "type": "Feature",
  "properties": {
    "addr:full": "1775 Cedar Hill Rd Lancaster OH 43130",
    "addr:housenumber": "1775",
    "addr:postcode": "43130",
    "addr:street": "Cedar Hill Rd",
    "iso:country": "US",
    "sg:address": "1775 Cedar Hill Rd",
    "sg:city": "Lancaster",
    "sg:classifiers": [
      {
        "category": "Shopping",
        "type": "Retail Goods"
      }
    ],
    "sg:phone": "+1 740 653 8411",
    "sg:postcode": "43130",
    "sg:province": "OH",
    "sg:tags": [
      "farm",
      "merchandise",
      "supply"
    ],
    "wof:name": "Henrys Feed Mill",
    "wof:placetype": "venue"
  },
  "geometry": {"coordinates":[-82.628758,39.714076],"type":"Point"}
}
