{
  "type": "Feature",
  "properties": {
    "addr:full":"2900 Woodville Rd Northwood OH 43619",
    "addr:housenumber":"2900",
    "addr:postcode":"43619",
    "addr:street":"Woodville Rd",
    "iso:country":"US",
    "sg:address":"2900 Woodville Rd",
    "sg:city":"Northwood",
    "sg:classifiers":[
        {
            "category":"Restaurant",
            "type":"Food & Drink"
        }
    ],
    "sg:phone":"+1 419 693 7887",
    "sg:postcode":"43619",
    "sg:province":"OH",
    "sg:tags":[
        "eating"
    ],
    "wof:name":"Sallocks Steakhouse Inc",
    "wof:placetype":"venue"
},
  "geometry": {"coordinates":[-83.48324599999999,41.614435],"type":"Point"}
}