{
  "type": "Feature",
  "properties": {
    "iso:country":"US",
    "sg:address":"345 Oakhill Ave NE",
    "sg:city":"Youngstown",
    "sg:classifiers":[
        {
            "category":"Health Services",
            "subcategory":"Doctor",
            "type":"Services"
        }
    ],
    "sg:phone":"+1 330 740 6668",
    "sg:postcode":"44502",
    "sg:province":"OH",
    "sg:tags":[
        "clinic"
    ],
    "wof:name":"Southside CDC",
    "wof:placetype":"venue"
},
  "geometry": {"coordinates":[-80.659435,41.09706],"type":"Point"}
}