{
  "type": "Feature",
  "properties": {
    "addr:full":"18730 Rd R Columbus Grove OH 45830",
    "addr:housenumber":"18730",
    "addr:postcode":"45830",
    "addr:street":"Rd;Columbus Grove",
    "iso:country":"US",
    "sg:address":"18730 Rd R",
    "sg:city":"Columbus Grove",
    "sg:phone":"+1 419 642 5551",
    "sg:postcode":"45830",
    "sg:province":"OH",
    "sg:tags":[
        "farm",
        "corn",
        "soybean"
    ],
    "wof:name":"Krietemeyer Brothers",
    "wof:placetype":"venue"
},
  "geometry": {"coordinates":[-84.219553,40.918458],"type":"Point"}
}