{
  "type": "Feature",
  "properties": {
    "addr:full": "2910 W Central Ave Toledo OH 43606",
    "addr:housenumber": "2910",
    "addr:postcode": "43606",
    "addr:street": "W Central Ave",
    "iso:country": "US",
    "sg:address": "2910 W Central Ave",
    "sg:city": "Toledo",
    "sg:classifiers": [
      {
        "category": "Health Services",
        "subcategory": "Doctor",
        "type": "Services"
      }
    ],
    "sg:phone": "+1 419 531 6444",
    "sg:postcode": "43606",
    "sg:province": "OH",
    "sg:tags": [
      "dentist"
    ],
    "wof:name": "Kenneth Krakoff DDS",
    "wof:placetype": "venue"
  },
  "geometry": {"coordinates":[-83.614183,41.677548],"type":"Point"}
}
