{
  "type": "Feature",
  "properties": {
    "addr:full":"977 Bluffpoint Dr Columbus OH 43235",
    "addr:housenumber":"977",
    "addr:postcode":"43235",
    "addr:street":"Bluffpoint Dr",
    "iso:country":"US",
    "sg:address":"977 Bluffpoint Dr",
    "sg:city":"Columbus",
    "sg:classifiers":[
        {
            "category":"Professional",
            "type":"Services"
        }
    ],
    "sg:phone":"+1 614 844 6869",
    "sg:postcode":"43235",
    "sg:province":"OH",
    "wof:name":"P Lepianka",
    "wof:placetype":"venue"
},
  "geometry": {"coordinates":[-83.043769,40.109763],"type":"Point"}
}