{
  "type": "Feature",
  "properties": {
    "addr:full": "574 Tecumseh St Toledo OH 43604",
    "addr:housenumber": "574",
    "addr:postcode": "43604",
    "addr:street": "Tecumseh St",
    "iso:country": "US",
    "sg:address": "574 Tecumseh St",
    "sg:city": "Toledo",
    "sg:classifiers": [
      {
        "category": "Restaurant",
        "type": "Food \u0026 Drink"
      }
    ],
    "sg:phone": "+1 419 243 6850",
    "sg:postcode": "43604",
    "sg:province": "OH",
    "sg:tags": [
      "eating"
    ],
    "wof:name": "B \u0026 J Cafe",
    "wof:placetype": "venue"
  },
  "geometry": {"coordinates":[-83.555804,41.64452],"type":"Point"}
}
