{
  "type": "Feature",
  "properties": {
    "iso:country":"US",
    "sg:address":"574 Tecumseh St",
    "sg:city":"Toledo",
    "sg:classifiers":[
        {
            "category":"Restaurant",
            "type":"Food & Drink"
        }
    ],
    "sg:phone":"+1 419 243 6850",
    "sg:postcode":"43604",
    "sg:province":"OH",
    "sg:tags":[
        "eating"
    ],
    "wof:name":"B & J Cafe",
    "wof:placetype":"venue"
},
  "geometry": {"coordinates":[-83.555804,41.64452],"type":"Point"}
}