{
  "type": "Feature",
  "properties": {
    "addr:full": "14573 State Rte 274 Botkins OH 45306",
    "addr:housenumber": "14573",
    "addr:postcode": "45306",
    "addr:street": "State Rte 274",
    "iso:country": "US",
    "sg:address": "14573 State Rte 274",
    "sg:city": "Botkins",
    "sg:classifiers": [
      {
        "category": "Real Estate",
        "subcategory": "Real Estate Operator",
        "type": "Services"
      }
    ],
    "sg:phone": "+1 937 693 4779",
    "sg:postcode": "45306",
    "sg:province": "OH",
    "sg:tags": [
      "property",
      "lessor"
    ],
    "wof:name": "Edna Fullenkamp",
    "wof:placetype": "venue"
  },
  "geometry": {"coordinates":[-84.157611,40.438887],"type":"Point"}
}
