{
  "type": "Feature",
  "properties": {
    "iso:country":"US",
    "sg:address":"7899 W Ridgewood Dr",
    "sg:city":"Cleveland",
    "sg:classifiers":[
        {
            "category":"Shopping",
            "type":"Retail Goods"
        }
    ],
    "sg:phone":"+1 440 887 1302",
    "sg:postcode":"44129",
    "sg:province":"OH",
    "sg:tags":[
        "telephone",
        "cellular"
    ],
    "wof:name":"North Coast PCS",
    "wof:placetype":"venue"
},
  "geometry": {"coordinates":[-81.7392,41.38445],"type":"Point"}
}