{
  "type": "Feature",
  "properties": {
    "addr:full":"39239 Church Hill Rd Lisbon OH 44432",
    "addr:housenumber":"39239",
    "addr:postcode":"44432",
    "addr:street":"Church Hill Rd",
    "iso:country":"US",
    "sg:address":"39239 Church Hill Rd",
    "sg:city":"Lisbon",
    "sg:classifiers":[
        {
            "category":"Wholesale",
            "subcategory":"Chemicals & Plastics",
            "type":"Manufacturing & Wholesale Goods"
        }
    ],
    "sg:phone":"+1 330 424 1401",
    "sg:postcode":"44432",
    "sg:province":"OH",
    "sg:tags":[
        "explosive"
    ],
    "wof:name":"Hilltop Energy Inc",
    "wof:placetype":"venue"
},
  "geometry": {"coordinates":[-80.760062,40.783605],"type":"Point"}
}