{
  "type": "Feature",
  "properties": {
    "addr:full": "1012 E Dorothy Ln Dayton OH 45419",
    "addr:housenumber": "1012",
    "addr:postcode": "45419",
    "addr:street": "E Dorothy Ln",
    "iso:country": "US",
    "sg:address": "1012 E Dorothy Ln",
    "sg:city": "Dayton",
    "sg:classifiers": [
      {
        "category": "Shopping",
        "subcategory": "Stationery \u0026 Office Supplies",
        "type": "Retail Goods"
      },
      {
        "category": "Wholesale",
        "subcategory": "Stationery",
        "type": "Manufacturing \u0026 Wholesale Goods"
      }
    ],
    "sg:phone": "+1 937 294 1224",
    "sg:postcode": "45419",
    "sg:province": "OH",
    "sg:tags": [
      "school"
    ],
    "sg:website": "www.fsschoolsupply.com",
    "wof:name": "F \u0026 S School \u0026 Office Supply",
    "wof:placetype": "venue"
  },
  "geometry": {"coordinates":[-84.149565,39.703767],"type":"Point"}
}
