{
  "type": "Feature",
  "properties": {
    "iso:country":"US",
    "sg:address":"1012 E Dorothy Ln",
    "sg:city":"Dayton",
    "sg:classifiers":[
        {
            "category":"Shopping",
            "subcategory":"Stationery & Office Supplies",
            "type":"Retail Goods"
        },
        {
            "category":"Wholesale",
            "subcategory":"Stationery",
            "type":"Manufacturing & Wholesale Goods"
        }
    ],
    "sg:phone":"+1 937 294 1224",
    "sg:postcode":"45419",
    "sg:province":"OH",
    "sg:tags":[
        "school"
    ],
    "sg:website":"www.fsschoolsupply.com",
    "wof:name":"F & S School & Office Supply",
    "wof:placetype":"venue"
},
  "geometry": {"coordinates":[-84.149565,39.703767],"type":"Point"}
}