{
  "type": "Feature",
  "properties": {
    "addr:full": "14900 Chillicothe Rd Novelty OH 44072",
    "addr:housenumber": "14900",
    "addr:postcode": "44072",
    "addr:street": "Chillicothe Rd",
    "iso:country": "US",
    "sg:address": "14900 Chillicothe Rd",
    "sg:city": "Novelty",
    "sg:classifiers": [
      {
        "category": "Autos \u0026 Motor Vehicles",
        "subcategory": "Fuel \u0026 Gas Station",
        "type": "Retail Goods"
      },
      {
        "category": "Personal",
        "type": "Services"
      },
      {
        "category": "Retail",
        "subcategory": "Auto Repair",
        "type": "Services"
      }
    ],
    "sg:phone": "+1 440 338 8818",
    "sg:postcode": "44072",
    "sg:province": "OH",
    "sg:tags": [
      "towing"
    ],
    "wof:name": "O'reilly \u0026 Brooks Shell Service",
    "wof:placetype": "venue"
  },
  "geometry": {"coordinates":[-81.340202,41.4631],"type":"Point"}
}
