{
  "type": "Feature",
  "properties": {
    "iso:country":"US",
    "sg:address":"14900 Chillicothe Rd",
    "sg:city":"Novelty",
    "sg:classifiers":[
        {
            "category":"Autos & Motor Vehicles",
            "subcategory":"Fuel & Gas Station",
            "type":"Retail Goods"
        },
        {
            "category":"Personal",
            "type":"Services"
        },
        {
            "category":"Retail",
            "subcategory":"Auto Repair",
            "type":"Services"
        }
    ],
    "sg:phone":"+1 440 338 8818",
    "sg:postcode":"44072",
    "sg:province":"OH",
    "sg:tags":[
        "towing"
    ],
    "wof:name":"O'reilly & Brooks Shell Service",
    "wof:placetype":"venue"
},
  "geometry": {"coordinates":[-81.34020200000001,41.4631],"type":"Point"}
}