{
  "type": "Feature",
  "properties": {
    "iso:country":"US",
    "sg:address":"1205 N Barron St",
    "sg:city":"Eaton",
    "sg:classifiers":[
        {
            "category":"Restaurant",
            "type":"Food & Drink"
        }
    ],
    "sg:menulink":"http://www.allmenus.com/oh/eaton/67853-foxs-pizza-den/menu/",
    "sg:phone":"+1 937 472 3697",
    "sg:postcode":"45320",
    "sg:province":"OH",
    "sg:tags":[
        "american",
        "pizza"
    ],
    "wof:name":"Fox's Pizza Den",
    "wof:placetype":"venue"
},
  "geometry": {"coordinates":[-84.636397,39.755323],"type":"Point"}
}