{
  "type": "Feature",
  "properties": {
    "iso:country":"US",
    "sg:address":"528 N Washington St",
    "sg:city":"Delphos",
    "sg:classifiers":[
        {
            "category":"Freight",
            "type":"Transportation"
        },
        {
            "category":"Food & Beverages",
            "subcategory":"Meat & Fish",
            "type":"Retail Goods"
        }
    ],
    "sg:phone":"+1 419 692 6891",
    "sg:postcode":"45833",
    "sg:province":"OH",
    "sg:tags":[
        "refrigeration",
        "livestock"
    ],
    "sg:website":"www.delphosfoodlocker.com",
    "wof:name":"Delphos Food Lockers Inc",
    "wof:placetype":"venue"
},
  "geometry": {"coordinates":[-84.33839999999999,40.847363],"type":"Point"}
}