{
  "type": "Feature",
  "properties": {
    "addr:full":"50890 Rice Run Rd Reedsville OH 45772",
    "addr:housenumber":"50890",
    "addr:postcode":"45772",
    "addr:street":"Rice Run Rd",
    "iso:country":"US",
    "sg:address":"50890 Rice Run Rd",
    "sg:city":"Reedsville",
    "sg:classifiers":[
        {
            "category":"Farming",
            "subcategory":"Farm",
            "type":"Manufacturing & Wholesale Goods"
        }
    ],
    "sg:phone":"+1 740 667 3785",
    "sg:postcode":"45772",
    "sg:province":"OH",
    "sg:tags":[
        "crop",
        "general"
    ],
    "wof:name":"William Francis",
    "wof:placetype":"venue"
},
  "geometry": {"coordinates":[-81.82424399999999,39.174323],"type":"Point"}
}