{
  "type": "Feature",
  "properties": {
    "iso:country":"US",
    "sg:address":"8395 Beechmont Ave",
    "sg:city":"Cincinnati",
    "sg:classifiers":[
        {
            "category":"Retail",
            "subcategory":"Auto Repair",
            "type":"Services"
        }
    ],
    "sg:phone":"+1 513 474 2203",
    "sg:postcode":"45255",
    "sg:province":"OH",
    "sg:tags":[
        "automotive",
        "lubrication"
    ],
    "sg:website":"www.jiffylube.com",
    "wof:name":"Jiffy Lube",
    "wof:placetype":"venue"
},
  "geometry": {"coordinates":[-84.322174,39.072332],"type":"Point"}
}