{
  "type": "Feature",
  "properties": {
    "iso:country":"US",
    "sg:address":"1250 S Front St",
    "sg:city":"Columbus",
    "sg:classifiers":[
        {
            "category":"Manufacturing",
            "subcategory":"Printing",
            "type":"Manufacturing & Wholesale Goods"
        }
    ],
    "sg:phone":"+1 614 444 1010",
    "sg:postcode":"43206",
    "sg:province":"OH",
    "sg:tags":[
        "printer"
    ],
    "wof:name":"Mathews Printing Co",
    "wof:placetype":"venue"
},
  "geometry": {"coordinates":[-82.997311,39.93627],"type":"Point"}
}