{
  "type": "Feature",
  "properties": {
    "addr:full":"206 Kenec Dr Middletown OH 45042",
    "addr:housenumber":"206",
    "addr:postcode":"45042",
    "addr:street":"Kenec Dr",
    "iso:country":"US",
    "sg:address":"206 Kenec Dr",
    "sg:city":"Middletown",
    "sg:classifiers":[
        {
            "category":"Freight",
            "type":"Transportation"
        }
    ],
    "sg:phone":"+1 513 422 5958",
    "sg:postcode":"45042",
    "sg:province":"OH",
    "sg:tags":[
        "trucking"
    ],
    "wof:name":"Nightflight Logistics",
    "wof:placetype":"venue"
},
  "geometry": {"coordinates":[-84.335759,39.51631],"type":"Point"}
}