{
  "type": "Feature",
  "properties": {
    "iso:country":"US",
    "sg:address":"923 E Broad St",
    "sg:city":"Columbus",
    "sg:classifiers":[
        {
            "category":"Professional",
            "subcategory":"Lawyer & Legal Services",
            "type":"Services"
        }
    ],
    "sg:phone":"+1 614 258 9300",
    "sg:postcode":"43205",
    "sg:province":"OH",
    "sg:tags":[
        "attorney"
    ],
    "wof:name":"Irving B Marks & Assoc",
    "wof:placetype":"venue"
},
  "geometry": {"coordinates":[-82.97519200000001,39.965073],"type":"Point"}
}