{
  "type": "Feature",
  "properties": {
    "addr:full": "923 E Broad St Columbus OH 43205",
    "addr:housenumber": "923",
    "addr:postcode": "43205",
    "addr:street": "E Broad St",
    "iso:country": "US",
    "sg:address": "923 E Broad St",
    "sg:city": "Columbus",
    "sg:classifiers": [
      {
        "category": "Professional",
        "subcategory": "Lawyer \u0026 Legal Services",
        "type": "Services"
      }
    ],
    "sg:phone": "+1 614 258 9300",
    "sg:postcode": "43205",
    "sg:province": "OH",
    "sg:tags": [
      "attorney"
    ],
    "wof:name": "Irving B Marks \u0026 Assoc",
    "wof:placetype": "venue"
  },
  "geometry": {"coordinates":[-82.975192,39.965073],"type":"Point"}
}
