{
  "type": "Feature",
  "properties": {
    "addr:full": "7 E Chestnut St Oxford OH 45056",
    "addr:housenumber": "7",
    "addr:postcode": "45056",
    "addr:street": "E Chestnut St",
    "iso:country": "US",
    "sg:address": "7 E Chestnut St",
    "sg:city": "Oxford",
    "sg:classifiers": [
      {
        "category": "Restaurant",
        "type": "Food \u0026 Drink"
      }
    ],
    "sg:menulink": "http://www.allmenus.com/oh/oxford/280062-sds-pizza/menu/",
    "sg:phone": "+1 513 523 1059",
    "sg:postcode": "45056",
    "sg:province": "OH",
    "sg:tags": [
      "american",
      "pizza"
    ],
    "wof:name": "Sds Pizza",
    "wof:placetype": "venue"
  },
  "geometry": {"coordinates":[-84.742521,39.500544],"type":"Point"}
}
