{
  "type": "Feature",
  "properties": {
    "addr:full": "5264 Huber Rd Norwalk OH 44857",
    "addr:housenumber": "5264",
    "addr:postcode": "44857",
    "addr:street": "Huber Rd",
    "iso:country": "US",
    "sg:address": "5264 Huber Rd",
    "sg:city": "Norwalk",
    "sg:classifiers": [
      {
        "category": "Farming",
        "subcategory": "Farm",
        "type": "Manufacturing \u0026 Wholesale Goods"
      }
    ],
    "sg:phone": "+1 419 668 0242",
    "sg:postcode": "44857",
    "sg:province": "OH",
    "sg:tags": [
      "operator",
      "general",
      "crop",
      "trucking"
    ],
    "wof:name": "Enterprise Hill Farm Inc",
    "wof:placetype": "venue"
  },
  "geometry": {"coordinates":[-82.660585,41.279363],"type":"Point"}
}
