{
  "type": "Feature",
  "properties": {
    "iso:country":"US",
    "sg:address":"3477 Commerce Park",
    "sg:city":"Wooster",
    "sg:classifiers":[
        {
            "category":"Professional",
            "subcategory":"Engineering",
            "type":"Services"
        }
    ],
    "sg:phone":"+1 330 345 6377",
    "sg:postcode":"44691",
    "sg:province":"OH",
    "sg:tags":[
        "engineer"
    ],
    "wof:name":"Shaffer Johnston Lichtenwalter",
    "wof:placetype":"venue"
},
  "geometry": {"coordinates":[-81.947007,40.842701],"type":"Point"}
}