{
  "type": "Feature",
  "properties": {
    "iso:country":"US",
    "sg:address":"3742 Bonfield Dr",
    "sg:city":"Cincinnati",
    "sg:classifiers":[
        {
            "category":"Restaurant",
            "type":"Food & Drink"
        }
    ],
    "sg:phone":"+1 513 861 5777",
    "sg:postcode":"45220",
    "sg:province":"OH",
    "sg:tags":[
        "caterer"
    ],
    "wof:name":"Cincinnati Master Caterers",
    "wof:placetype":"venue"
},
  "geometry": {"coordinates":[-84.50342000000001,39.151735],"type":"Point"}
}