{
  "type": "Feature",
  "properties": {
    "iso:country":"US",
    "sg:address":"115 W 5th St",
    "sg:city":"Port Clinton",
    "sg:classifiers":[
        {
            "category":"Utilities",
            "subcategory":"Telephone",
            "type":"Services"
        }
    ],
    "sg:phone":"+1 419 539 9862",
    "sg:postcode":"43452",
    "sg:province":"OH",
    "sg:tags":[
        "communications"
    ],
    "wof:name":"Virtuaweb",
    "wof:placetype":"venue"
},
  "geometry": {"coordinates":[-82.94273,41.50762],"type":"Point"}
}