{
  "type": "Feature",
  "properties": {
    "iso:country":"US",
    "sg:address":"510 Ohio Pike",
    "sg:city":"Cincinnati",
    "sg:classifiers":[
        {
            "category":"Restaurant",
            "type":"Food & Drink"
        }
    ],
    "sg:phone":"+1 513 528 5407",
    "sg:postcode":"45255",
    "sg:province":"OH",
    "wof:name":"Bob Evans Restrnts",
    "wof:placetype":"venue"
},
  "geometry": {"coordinates":[-84.30740400000001,39.071301],"type":"Point"}
}