{
  "type": "Feature",
  "properties": {
    "iso:country":"US",
    "sg:address":"31 Front",
    "sg:city":"Burbank",
    "sg:classifiers":[
        {
            "category":"Home & Garden",
            "subcategory":"Furniture",
            "type":"Retail Goods"
        }
    ],
    "sg:phone":"+1 330 624 6246",
    "sg:postcode":"44214",
    "sg:province":"OH",
    "sg:tags":[
        "store"
    ],
    "sg:website":"www.amishcraftedoak.com",
    "wof:name":"Amish Crafted Oak Inc",
    "wof:placetype":"venue"
},
  "geometry": {"coordinates":[-81.99279799999999,40.9403],"type":"Point"}
}