{
  "type": "Feature",
  "properties": {
    "addr:full": "31 Front Burbank OH 44214",
    "addr:housenumber": "31 front",
    "addr:postcode": "44214",
    "iso:country": "US",
    "sg:address": "31 Front",
    "sg:city": "Burbank",
    "sg:classifiers": [
      {
        "category": "Home \u0026 Garden",
        "subcategory": "Furniture",
        "type": "Retail Goods"
      }
    ],
    "sg:phone": "+1 330 624 6246",
    "sg:postcode": "44214",
    "sg:province": "OH",
    "sg:tags": [
      "store"
    ],
    "sg:website": "www.amishcraftedoak.com",
    "wof:name": "Amish Crafted Oak Inc",
    "wof:placetype": "venue"
  },
  "geometry": {"coordinates":[-81.992798,40.9403],"type":"Point"}
}
