{
  "type": "Feature",
  "properties": {
    "addr:full":"312 S Arch St Fremont OH 43420",
    "addr:housenumber":"312",
    "addr:postcode":"43420",
    "addr:street":"S Arch St",
    "iso:country":"US",
    "sg:address":"312 S Arch St",
    "sg:city":"Fremont",
    "sg:classifiers":[
        {
            "category":"Insurance",
            "subcategory":"Insurance Agent",
            "type":"Services"
        }
    ],
    "sg:phone":"+1 419 332 7353",
    "sg:postcode":"43420",
    "sg:province":"OH",
    "sg:tags":[
        "consulting",
        "management",
        "b"
    ],
    "wof:name":"White Financial Services",
    "wof:placetype":"venue"
},
  "geometry": {"coordinates":[-83.11493400000001,41.344228],"type":"Point"}
}