{
  "type": "Feature",
  "properties": {
    "addr:full": "10 Glenwood Blvd Mansfield OH 44906",
    "addr:housenumber": "10",
    "addr:postcode": "44906",
    "addr:street": "Glenwood Blvd",
    "iso:country": "US",
    "sg:address": "10 Glenwood Blvd",
    "sg:city": "Mansfield",
    "sg:classifiers": [
      {
        "category": "Organizations",
        "subcategory": "Religious Organization",
        "type": "Services"
      }
    ],
    "sg:phone": "+1 419 529 3572",
    "sg:postcode": "44906",
    "sg:province": "OH",
    "sg:tags": [
      "church"
    ],
    "wof:name": "Bethel Ev Congregational Ch",
    "wof:placetype": "venue"
  },
  "geometry": {"coordinates":[-82.537895,40.75788],"type":"Point"}
}
