{
  "type": "Feature",
  "properties": {
    "iso:country":"US",
    "sg:address":"10 Glenwood Blvd",
    "sg:city":"Mansfield",
    "sg:classifiers":[
        {
            "category":"Organizations",
            "subcategory":"Religious Organization",
            "type":"Services"
        }
    ],
    "sg:phone":"+1 419 529 3572",
    "sg:postcode":"44906",
    "sg:province":"OH",
    "sg:tags":[
        "church"
    ],
    "wof:name":"Bethel Ev Congregational Ch",
    "wof:placetype":"venue"
},
  "geometry": {"coordinates":[-82.53789500000001,40.75788],"type":"Point"}
}