{
  "type": "Feature",
  "properties": {
    "addr:full": "380 King Ave South Lebanon OH 45065",
    "addr:housenumber": "380",
    "addr:postcode": "45065",
    "addr:street": "King Ave South",
    "iso:country": "US",
    "sg:address": "380 King Ave",
    "sg:city": "South Lebanon",
    "sg:classifiers": [
      {
        "category": "Shopping",
        "subcategory": "Used Merchandise",
        "type": "Retail Goods"
      }
    ],
    "sg:phone": "+1 513 494 2598",
    "sg:postcode": "45065",
    "sg:province": "OH",
    "sg:tags": [
      "antique",
      "retailer"
    ],
    "wof:name": "John K Spicer \u0026 Son",
    "wof:placetype": "venue"
  },
  "geometry": {"coordinates":[-84.208637,39.366528],"type":"Point"}
}
