{
  "type": "Feature",
  "properties": {
    "addr:full":"200 Laurel Lake Dr Hudson OH 44236",
    "addr:housenumber":"200",
    "addr:postcode":"44236",
    "addr:street":"Laurel Lake Dr",
    "iso:country":"US",
    "sg:address":"200 Laurel Lake Dr",
    "sg:city":"Hudson",
    "sg:phone":"+1 330 656 2145",
    "sg:postcode":"44236",
    "sg:province":"OH",
    "sg:tags":[
        "farm",
        "corn",
        "soybean"
    ],
    "wof:name":"Watts Family Trust The",
    "wof:placetype":"venue"
},
  "geometry": {"coordinates":[-81.46854999999999,41.243882],"type":"Point"}
}