{
  "type": "Feature",
  "properties": {
    "addr:full":"9555 Colerain Ave Cincinnati OH 45251",
    "addr:housenumber":"9555",
    "addr:postcode":"45251",
    "addr:street":"Colerain Ave",
    "iso:country":"US",
    "sg:address":"9555 Colerain Ave",
    "sg:city":"Cincinnati",
    "sg:classifiers":[
        {
            "category":"Shopping",
            "subcategory":"Jewelry",
            "type":"Retail Goods"
        }
    ],
    "sg:phone":"+1 513 741 1422",
    "sg:postcode":"45251",
    "sg:province":"OH",
    "sg:tags":[
        "store"
    ],
    "wof:name":"Osterman Jewelers",
    "wof:placetype":"venue"
},
  "geometry": {"coordinates":[-84.59663399999999,39.24781],"type":"Point"}
}