{
  "type": "Feature",
  "properties": {
    "iso:country":"US",
    "sg:address":"2985 Sullivant Ave",
    "sg:city":"Columbus",
    "sg:classifiers":[
        {
            "category":"Professional",
            "type":"Services"
        }
    ],
    "sg:phone":"+1 614 405 9151",
    "sg:postcode":"43204",
    "sg:province":"OH",
    "wof:name":"Fabian Ashley",
    "wof:placetype":"venue"
},
  "geometry": {"coordinates":[-83.07941599999999,39.9434],"type":"Point"}
}