{
  "type": "Feature",
  "properties": {
    "iso:country":"US",
    "sg:address":"6201 Sharon Woods Blvd",
    "sg:city":"Columbus",
    "sg:classifiers":[
        {
            "category":"Travel",
            "subcategory":"Travel Agent",
            "type":"Entertainment"
        }
    ],
    "sg:phone":"+1 614 901 3000",
    "sg:postcode":"43229",
    "sg:province":"OH",
    "sg:tags":[
        "agency",
        "services-commercial"
    ],
    "wof:name":"Aloha Travel",
    "wof:placetype":"venue"
},
  "geometry": {"coordinates":[-82.966582,40.09458],"type":"Point"}
}