{
  "type": "Feature",
  "properties": {
    "addr:full":"5531 Clay Pike Chandlersville OH 43727",
    "addr:housenumber":"5531",
    "addr:postcode":"43727",
    "addr:street":"Clay Pike",
    "iso:country":"US",
    "sg:address":"5531 Clay Pike",
    "sg:city":"Chandlersville",
    "sg:classifiers":[
        {
            "category":"Home & Garden",
            "subcategory":"Furniture",
            "type":"Retail Goods"
        }
    ],
    "sg:phone":"+1 740 454 3906",
    "sg:postcode":"43727",
    "sg:province":"OH",
    "sg:tags":[
        "top",
        "counter"
    ],
    "wof:name":"Countertops By Marcus",
    "wof:placetype":"venue"
},
  "geometry": {"coordinates":[-81.88889500000001,39.931737],"type":"Point"}
}