{
  "type": "Feature",
  "properties": {
    "iso:country":"US",
    "sg:address":"7859 Battles Rd",
    "sg:city":"Gates Mills",
    "sg:classifiers":[
        {
            "category":"Real Estate",
            "subcategory":"Real Estate Agent",
            "type":"Services"
        }
    ],
    "sg:phone":"+1 440 423 0738",
    "sg:postcode":"44040",
    "sg:province":"OH",
    "sg:tags":[
        "manager"
    ],
    "wof:name":"Gardner Kennedy Group Inc",
    "wof:placetype":"venue"
},
  "geometry": {"coordinates":[-81.396872,41.556149],"type":"Point"}
}