{
  "type": "Feature",
  "properties": {
    "iso:country":"US",
    "sg:address":"154 Vance St",
    "sg:city":"Bluffton",
    "sg:classifiers":[
        {
            "category":"Food & Beverages",
            "subcategory":"Groceries & Convenience Stores",
            "type":"Retail Goods"
        }
    ],
    "sg:phone":"+1 419 358 2901",
    "sg:postcode":"45817",
    "sg:province":"OH",
    "sg:tags":[
        "grocer"
    ],
    "wof:name":"Community Market",
    "wof:placetype":"venue"
},
  "geometry": {"coordinates":[-83.888949,40.892751],"type":"Point"}
}