{
  "type": "Feature",
  "properties": {
    "addr:full": "154 Vance St Bluffton OH 45817",
    "addr:housenumber": "154",
    "addr:postcode": "45817",
    "addr:street": "Vance St",
    "iso:country": "US",
    "sg:address": "154 Vance St",
    "sg:city": "Bluffton",
    "sg:classifiers": [
      {
        "category": "Food \u0026 Beverages",
        "subcategory": "Groceries \u0026 Convenience Stores",
        "type": "Retail Goods"
      }
    ],
    "sg:phone": "+1 419 358 2901",
    "sg:postcode": "45817",
    "sg:province": "OH",
    "sg:tags": [
      "grocer"
    ],
    "wof:name": "Community Market",
    "wof:placetype": "venue"
  },
  "geometry": {"coordinates":[-83.888949,40.892751],"type":"Point"}
}
