{
  "type": "Feature",
  "properties": {
    "addr:full": "744 Carle Ave Lewis Center OH 43035",
    "addr:housenumber": "744",
    "addr:postcode": "43035",
    "addr:street": "Carle Ave",
    "iso:country": "US",
    "sg:address": "744 Carle Ave",
    "sg:city": "Lewis Center",
    "sg:classifiers": [
      {
        "category": "Wholesale",
        "subcategory": "Auto Parts",
        "type": "Manufacturing \u0026 Wholesale Goods"
      }
    ],
    "sg:phone": "+1 740 917 2270",
    "sg:postcode": "43035",
    "sg:province": "OH",
    "sg:tags": [
      "equipment",
      "truck"
    ],
    "wof:name": "Rhino Linings",
    "wof:placetype": "venue"
  },
  "geometry": {"coordinates":[-83.008769,40.159791],"type":"Point"}
}
