{
  "type": "Feature",
  "properties": {
    "iso:country":"US",
    "sg:address":"744 Carle Ave",
    "sg:city":"Lewis Center",
    "sg:classifiers":[
        {
            "category":"Wholesale",
            "subcategory":"Auto Parts",
            "type":"Manufacturing & Wholesale Goods"
        }
    ],
    "sg:phone":"+1 740 917 2270",
    "sg:postcode":"43035",
    "sg:province":"OH",
    "sg:tags":[
        "equipment",
        "truck"
    ],
    "wof:name":"Rhino Linings",
    "wof:placetype":"venue"
},
  "geometry": {"coordinates":[-83.008769,40.159791],"type":"Point"}
}