{
  "type": "Feature",
  "properties": {
    "iso:country":"US",
    "sg:address":"22 Boardman Canfield Rd",
    "sg:city":"Youngstown",
    "sg:classifiers":[
        {
            "category":"Professional",
            "type":"Services"
        }
    ],
    "sg:phone":"+1 330 965 0808",
    "sg:postcode":"44512",
    "sg:province":"OH",
    "wof:name":"P J Kulow Inc",
    "wof:placetype":"venue"
},
  "geometry": {"coordinates":[-80.664455,41.024456],"type":"Point"}
}