{
  "type": "Feature",
  "properties": {
    "addr:full":"895 Eastwind Dr Westerville OH 43081",
    "addr:housenumber":"895",
    "addr:postcode":"43081",
    "addr:street":"Eastwind Dr",
    "iso:country":"US",
    "sg:address":"895 Eastwind Dr",
    "sg:city":"Westerville",
    "sg:classifiers":[
        {
            "category":"Shopping",
            "subcategory":"Pharmacy",
            "type":"Retail Goods"
        }
    ],
    "sg:phone":"+1 614 882 3700",
    "sg:postcode":"43081",
    "sg:province":"OH",
    "sg:tags":[
        "pharmaceutical",
        "consultant"
    ],
    "wof:name":"Blackburn International",
    "wof:placetype":"venue"
},
  "geometry": {"coordinates":[-82.914766,40.101081],"type":"Point"}
}