{
  "type": "Feature",
  "properties": {
    "addr:full":"2310 2nd St Cuyahoga Falls OH 44221",
    "addr:housenumber":"2310",
    "addr:postcode":"44221",
    "addr:street":"2Nd St",
    "iso:country":"US",
    "sg:address":"2310 2nd St",
    "sg:city":"Cuyahoga Falls",
    "sg:classifiers":[
        {
            "category":"Government",
            "subcategory":"Office",
            "type":"Public Place"
        }
    ],
    "sg:phone":"+1 330 971 8240",
    "sg:postcode":"44221",
    "sg:province":"OH",
    "sg:tags":[
        "city",
        "council"
    ],
    "wof:name":"City Council",
    "wof:placetype":"venue"
},
  "geometry": {"coordinates":[-81.483711,41.138461],"type":"Point"}
}