{
  "type": "Feature",
  "properties": {
    "addr:full": "1211 E Main St Ashland OH 44805",
    "addr:housenumber": "1211",
    "addr:postcode": "44805",
    "addr:street": "E Main St",
    "iso:country": "US",
    "sg:address": "1211 E Main St",
    "sg:city": "Ashland",
    "sg:classifiers": [
      {
        "category": "Government",
        "subcategory": "Police Station",
        "type": "Public Place"
      }
    ],
    "sg:phone": "+1 419 289 3639",
    "sg:postcode": "44805",
    "sg:province": "OH",
    "sg:tags": [
      "department",
      "protection"
    ],
    "wof:name": "Ashland Police Department",
    "wof:placetype": "venue"
  },
  "geometry": {"coordinates":[-82.290938,40.864057],"type":"Point"}
}
