{
  "type": "Feature",
  "properties": {
    "iso:country":"US",
    "sg:address":"1433 Oakland Park Ave",
    "sg:city":"Columbus",
    "sg:classifiers":[
        {
            "category":"Personal",
            "subcategory":"Barber",
            "type":"Services"
        }
    ],
    "sg:phone":"+1 614 268 9330",
    "sg:postcode":"43224",
    "sg:province":"OH",
    "wof:name":"Custom Cutts",
    "wof:placetype":"venue"
},
  "geometry": {"coordinates":[-82.97373,40.031701],"type":"Point"}
}