{
  "type": "Feature",
  "properties": {
    "iso:country":"US",
    "sg:address":"4486 W 152nd St",
    "sg:city":"Cleveland",
    "sg:classifiers":[
        {
            "category":"Professional",
            "subcategory":"Lawyer & Legal Services",
            "type":"Services"
        }
    ],
    "sg:phone":"+1 216 676 5400",
    "sg:postcode":"44135",
    "sg:province":"OH",
    "sg:tags":[
        "divorce",
        "assistance"
    ],
    "wof:name":"Divorce 4 Less",
    "wof:placetype":"venue"
},
  "geometry": {"coordinates":[-81.802638,41.432058],"type":"Point"}
}