{
  "type": "Feature",
  "properties": {
    "addr:full": "4486 W 152nd St Cleveland OH 44135",
    "addr:housenumber": "4486",
    "addr:postcode": "44135",
    "addr:street": "W 152Nd St",
    "iso:country": "US",
    "sg:address": "4486 W 152nd St",
    "sg:city": "Cleveland",
    "sg:classifiers": [
      {
        "category": "Professional",
        "subcategory": "Lawyer \u0026 Legal Services",
        "type": "Services"
      }
    ],
    "sg:phone": "+1 216 676 5400",
    "sg:postcode": "44135",
    "sg:province": "OH",
    "sg:tags": [
      "divorce",
      "assistance"
    ],
    "wof:name": "Divorce 4 Less",
    "wof:placetype": "venue"
  },
  "geometry": {"coordinates":[-81.802638,41.432058],"type":"Point"}
}
