{
  "type": "Feature",
  "properties": {
    "iso:country":"US",
    "sg:address":"2242 E 81st St",
    "sg:city":"Cleveland",
    "sg:classifiers":[
        {
            "category":"Home & Garden",
            "subcategory":"Household Appliances",
            "type":"Retail Goods"
        }
    ],
    "sg:phone":"+1 216 431 7910",
    "sg:postcode":"44103",
    "sg:province":"OH",
    "wof:name":"T's Appliances",
    "wof:placetype":"venue"
},
  "geometry": {"coordinates":[-81.631697,41.500067],"type":"Point"}
}