{
  "type": "Feature",
  "properties": {
    "addr:full": "66300 Pisgah Rd Quaker City OH 43773",
    "addr:postcode": "66300;43773",
    "addr:street": "Pisgah Rd",
    "iso:country": "US",
    "sg:address": "66300 Pisgah Rd",
    "sg:city": "Quaker City",
    "sg:classifiers": [
      {
        "category": "Home \u0026 Garden",
        "subcategory": "Building Materials",
        "type": "Retail Goods"
      }
    ],
    "sg:phone": "+1 740 758 5372",
    "sg:postcode": "43773",
    "sg:province": "OH",
    "wof:name": "Pisgah Logging \u0026 Forest Pdts",
    "wof:placetype": "venue"
  },
  "geometry": {"coordinates":[-81.289407,40.056788],"type":"Point"}
}
