{
  "type": "Feature",
  "properties": {
    "iso:country":"US",
    "sg:address":"66300 Pisgah Rd",
    "sg:city":"Quaker City",
    "sg:classifiers":[
        {
            "category":"Home & Garden",
            "subcategory":"Building Materials",
            "type":"Retail Goods"
        }
    ],
    "sg:phone":"+1 740 758 5372",
    "sg:postcode":"43773",
    "sg:province":"OH",
    "wof:name":"Pisgah Logging & Forest Pdts",
    "wof:placetype":"venue"
},
  "geometry": {"coordinates":[-81.289407,40.056788],"type":"Point"}
}