{
  "type": "Feature",
  "properties": {
    "addr:full": "7700 Hamilton Ave Cincinnati OH 45231",
    "addr:housenumber": "7700",
    "addr:postcode": "45231",
    "addr:street": "Hamilton Ave",
    "iso:country": "US",
    "sg:address": "7700 Hamilton Ave",
    "sg:city": "Cincinnati",
    "sg:classifiers": [
      {
        "category": "Shopping",
        "subcategory": "Pharmacy",
        "type": "Retail Goods"
      }
    ],
    "sg:phone": "+1 513 729 0210",
    "sg:postcode": "45231",
    "sg:province": "OH",
    "wof:name": "CVS Pharmacy",
    "wof:placetype": "venue"
  },
  "geometry": {"coordinates":[-84.548026,39.234499],"type":"Point"}
}
