{
  "type": "Feature",
  "properties": {
    "iso:country":"US",
    "sg:address":"11651 Glenmore Rd",
    "sg:city":"Ohio City",
    "sg:phone":"+1 419 965 2018",
    "sg:postcode":"45874",
    "sg:province":"OH",
    "sg:tags":[
        "farm",
        "corn",
        "soybean"
    ],
    "wof:name":"David Rhoades",
    "wof:placetype":"venue"
},
  "geometry": {"coordinates":[-84.597387,40.78611],"type":"Point"}
}