{
  "type": "Feature",
  "properties": {
    "addr:full":"530 Riverside Dr Piqua OH 45356",
    "addr:housenumber":"530",
    "addr:postcode":"45356",
    "addr:street":"Riverside Dr",
    "iso:country":"US",
    "sg:address":"530 Riverside Dr",
    "sg:city":"Piqua",
    "sg:classifiers":[
        {
            "category":"Building & Trades",
            "subcategory":"Construction",
            "type":"Services"
        }
    ],
    "sg:phone":"+1 937 248 6152",
    "sg:postcode":"45356",
    "sg:province":"OH",
    "sg:tags":[
        "house"
    ],
    "wof:name":"Done Right Home Repair & Maint",
    "wof:placetype":"venue"
},
  "geometry": {"coordinates":[-84.24716100000001,40.158684],"type":"Point"}
}