{
  "type": "Feature",
  "properties": {
    "addr:full": "6754 Cleveland Ave Columbus OH 43231",
    "addr:housenumber": "6754",
    "addr:postcode": "43231",
    "addr:street": "Cleveland Ave",
    "iso:country": "US",
    "sg:address": "6754 Cleveland Ave",
    "sg:city": "Columbus",
    "sg:classifiers": [
      {
        "category": "Professional",
        "subcategory": "Printing \u0026 Photocopies",
        "type": "Services"
      }
    ],
    "sg:phone": "+1 614 882 7991",
    "sg:postcode": "43231",
    "sg:province": "OH",
    "sg:tags": [
      "duplicating",
      "copying"
    ],
    "wof:name": "Copies Plus",
    "wof:placetype": "venue"
  },
  "geometry": {"coordinates":[-82.949123,40.109954],"type":"Point"}
}
