{
  "type": "Feature",
  "properties": {
    "iso:country":"US",
    "sg:address":"6754 Cleveland Ave",
    "sg:city":"Columbus",
    "sg:classifiers":[
        {
            "category":"Professional",
            "subcategory":"Printing & Photocopies",
            "type":"Services"
        }
    ],
    "sg:phone":"+1 614 882 7991",
    "sg:postcode":"43231",
    "sg:province":"OH",
    "sg:tags":[
        "duplicating",
        "copying"
    ],
    "wof:name":"Copies Plus",
    "wof:placetype":"venue"
},
  "geometry": {"coordinates":[-82.949123,40.109954],"type":"Point"}
}