{
  "type": "Feature",
  "properties": {
    "iso:country":"US",
    "sg:address":"1945 Jackson Rd",
    "sg:city":"Columbus",
    "sg:classifiers":[
        {
            "category":"Manufacturing",
            "subcategory":"Metals",
            "type":"Manufacturing & Wholesale Goods"
        }
    ],
    "sg:phone":"+1 614 879 6772",
    "sg:postcode":"43223",
    "sg:province":"OH",
    "sg:tags":[
        "manufacture",
        "spring",
        "wire"
    ],
    "wof:name":"Regal Spring Co",
    "wof:placetype":"venue"
},
  "geometry": {"coordinates":[-83.04827899999999,39.937529],"type":"Point"}
}