{
  "type": "Feature",
  "properties": {
    "addr:full": "1945 Jackson Rd Columbus OH 43223",
    "addr:housenumber": "1945",
    "addr:postcode": "43223",
    "addr:street": "Jackson Rd",
    "iso:country": "US",
    "sg:address": "1945 Jackson Rd",
    "sg:city": "Columbus",
    "sg:classifiers": [
      {
        "category": "Manufacturing",
        "subcategory": "Metals",
        "type": "Manufacturing \u0026 Wholesale Goods"
      }
    ],
    "sg:phone": "+1 614 879 6772",
    "sg:postcode": "43223",
    "sg:province": "OH",
    "sg:tags": [
      "manufacture",
      "spring",
      "wire"
    ],
    "wof:name": "Regal Spring Co",
    "wof:placetype": "venue"
  },
  "geometry": {"coordinates":[-83.048279,39.937529],"type":"Point"}
}
