{
  "type": "Feature",
  "properties": {
    "addr:full":"12199 Deerhorn Dr Cincinnati OH 45240",
    "addr:housenumber":"12199",
    "addr:postcode":"45240",
    "addr:street":"Deerhorn Dr",
    "iso:country":"US",
    "sg:address":"12199 Deerhorn Dr",
    "sg:city":"Cincinnati",
    "sg:classifiers":[
        {
            "category":"Professional",
            "subcategory":"Computer Services",
            "type":"Services"
        }
    ],
    "sg:phone":"+1 513 851 5634",
    "sg:postcode":"45240",
    "sg:province":"OH",
    "sg:tags":[
        "technician"
    ],
    "wof:name":"GE",
    "wof:placetype":"venue"
},
  "geometry": {"coordinates":[-84.55142600000001,39.306084],"type":"Point"}
}