{
  "type": "Feature",
  "properties": {
    "iso:country":"US",
    "sg:address":"2719 Washington Blvd",
    "sg:city":"Belpre",
    "sg:classifiers":[
        {
            "category":"Building & Trades",
            "subcategory":"Construction",
            "type":"Services"
        }
    ],
    "sg:phone":"+1 740 423 7468",
    "sg:postcode":"45714",
    "sg:province":"OH",
    "sg:tags":[
        "contractor"
    ],
    "wof:name":"Branchs",
    "wof:placetype":"venue"
},
  "geometry": {"coordinates":[-81.617019,39.279558],"type":"Point"}
}