{
  "type": "Feature",
  "properties": {
    "iso:country":"US",
    "sg:address":"10532 Cleveland Ave NW",
    "sg:city":"Uniontown",
    "sg:classifiers":[
        {
            "category":"Building & Trades",
            "subcategory":"Construction",
            "type":"Services"
        }
    ],
    "sg:phone":"+1 330 305 6700",
    "sg:postcode":"44685",
    "sg:province":"OH",
    "sg:tags":[
        "general",
        "contractor"
    ],
    "sg:website":"www.dutchheritagehomes.com",
    "wof:name":"Dutch Heritage Homes",
    "wof:placetype":"venue"
},
  "geometry": {"coordinates":[-81.402367,40.932358],"type":"Point"}
}