{
  "type": "Feature",
  "properties": {
    "addr:full": "3666 Mahoning Ave Youngstown OH 44515",
    "addr:housenumber": "3666",
    "addr:postcode": "44515",
    "addr:street": "Mahoning Ave",
    "iso:country": "US",
    "sg:address": "3666 Mahoning Ave",
    "sg:city": "Youngstown",
    "sg:classifiers": [
      {
        "category": "Professional",
        "type": "Services"
      }
    ],
    "sg:phone": "+1 330 270 7041",
    "sg:postcode": "44515",
    "sg:province": "OH",
    "wof:name": "Vansickle Corporation",
    "wof:placetype": "venue"
  },
  "geometry": {"coordinates":[-80.713198,41.102597],"type":"Point"}
}
