{
  "type": "Feature",
  "properties": {
    "addr:full":"333 E Market St Akron OH 44304",
    "addr:housenumber":"333",
    "addr:postcode":"44304",
    "addr:street":"E Market St",
    "iso:country":"US",
    "sg:address":"333 E Market St",
    "sg:city":"Akron",
    "sg:classifiers":[
        {
            "category":"Autos & Motor Vehicles",
            "subcategory":"Automobile Sales",
            "type":"Retail Goods"
        }
    ],
    "sg:phone":"+1 330 535 4161",
    "sg:postcode":"44304",
    "sg:province":"OH",
    "sg:tags":[
        "car",
        "dealer"
    ],
    "sg:website":"www.fredmartinchevrolet.com",
    "wof:name":"Martin Fred Chevrolet Inc",
    "wof:placetype":"venue"
},
  "geometry": {"coordinates":[-81.506069,41.080958],"type":"Point"}
}