{
  "type": "Feature",
  "properties": {
    "iso:country":"US",
    "sg:address":"939 Hempstead Dr",
    "sg:city":"Cincinnati",
    "sg:classifiers":[
        {
            "category":"Banks & Credit Unions",
            "subcategory":"Bank",
            "type":"Services"
        }
    ],
    "sg:phone":"+1 513 521 1600",
    "sg:postcode":"45231",
    "sg:province":"OH",
    "wof:name":"Pnc Bank",
    "wof:placetype":"venue"
},
  "geometry": {"coordinates":[-84.520105,39.223693],"type":"Point"}
}