{
  "type": "Feature",
  "properties": {
    "iso:country":"US",
    "sg:address":"6748 E Main St",
    "sg:city":"Reynoldsburg",
    "sg:classifiers":[
        {
            "category":"Autos & Motor Vehicles",
            "subcategory":"Fuel & Gas Station",
            "type":"Retail Goods"
        }
    ],
    "sg:phone":"+1 614 861 9262",
    "sg:postcode":"43068",
    "sg:province":"OH",
    "sg:tags":[
        "oil"
    ],
    "wof:name":"Marathon Service Station",
    "wof:placetype":"venue"
},
  "geometry": {"coordinates":[-82.816732,39.955071],"type":"Point"}
}