{
  "type": "Feature",
  "properties": {
    "addr:full": "11622 Co Rd M Napoleon OH 43545",
    "addr:housenumber": "11622",
    "addr:postcode": "43545",
    "addr:street": "Co Rd",
    "iso:country": "US",
    "sg:address": "11622 Co Rd M",
    "sg:city": "Napoleon",
    "sg:classifiers": [
      {
        "category": "Building \u0026 Trades",
        "subcategory": "Construction",
        "type": "Services"
      }
    ],
    "sg:phone": "+1 419 592 8307",
    "sg:postcode": "43545",
    "sg:province": "OH",
    "sg:tags": [
      "contractor"
    ],
    "sg:website": "www.becksconstruction.com",
    "wof:name": "Beck's Construction Co",
    "wof:placetype": "venue"
  },
  "geometry": {"coordinates":[-84.088697,41.341555],"type":"Point"}
}
