{
  "type": "Feature",
  "properties": {
    "addr:full":"840 Old Furnace Rd Youngstown OH 44511",
    "addr:housenumber":"840",
    "addr:postcode":"44511",
    "addr:street":"Old Furnace Rd",
    "iso:country":"US",
    "sg:address":"840 Old Furnace Rd",
    "sg:city":"Youngstown",
    "sg:classifiers":[
        {
            "category":"Recreation",
            "type":"Entertainment"
        }
    ],
    "sg:phone":"+1 330 740 7107",
    "sg:postcode":"44511",
    "sg:province":"OH",
    "sg:tags":[
        "attraction",
        "tourist"
    ],
    "wof:name":"Ford Nature Education Ctr",
    "wof:placetype":"venue"
},
  "geometry": {"coordinates":[-80.67824400000001,41.084905],"type":"Point"}
}