{
  "type": "Feature",
  "properties": {
    "iso:country":"US",
    "sg:address":"56 Townsend Ave SE",
    "sg:city":"Girard",
    "sg:classifiers":[
        {
            "category":"Shopping",
            "subcategory":"Catalog Store",
            "type":"Retail Goods"
        }
    ],
    "sg:phone":"+1 330 545 0490",
    "sg:postcode":"44420",
    "sg:province":"OH",
    "sg:tags":[
        "mail",
        "house"
    ],
    "wof:name":"Jim Forte Colctbls & Mre",
    "wof:placetype":"venue"
},
  "geometry": {"coordinates":[-80.703359,41.162958],"type":"Point"}
}