{
  "type": "Feature",
  "properties": {
    "addr:full": "56 Townsend Ave SE Girard OH 44420",
    "addr:housenumber": "56",
    "addr:postcode": "44420",
    "addr:street": "Townsend Ave Se",
    "iso:country": "US",
    "sg:address": "56 Townsend Ave SE",
    "sg:city": "Girard",
    "sg:classifiers": [
      {
        "category": "Shopping",
        "subcategory": "Catalog Store",
        "type": "Retail Goods"
      }
    ],
    "sg:phone": "+1 330 545 0490",
    "sg:postcode": "44420",
    "sg:province": "OH",
    "sg:tags": [
      "mail",
      "house"
    ],
    "wof:name": "Jim Forte Colctbls \u0026 Mre",
    "wof:placetype": "venue"
  },
  "geometry": {"coordinates":[-80.703359,41.162958],"type":"Point"}
}
