{
  "type": "Feature",
  "properties": {
    "addr:full": "200 W Geneva St Dunkirk OH 45836",
    "addr:housenumber": "200",
    "addr:postcode": "45836",
    "addr:street": "W Geneva St",
    "iso:country": "US",
    "sg:address": "200 W Geneva St",
    "sg:city": "Dunkirk",
    "sg:classifiers": [
      {
        "category": "Building \u0026 Trades",
        "subcategory": "Construction",
        "type": "Services"
      }
    ],
    "sg:phone": "+1 419 759 2800",
    "sg:postcode": "45836",
    "sg:province": "OH",
    "sg:tags": [
      "painter"
    ],
    "wof:name": "Mc Coy Painting",
    "wof:placetype": "venue"
  },
  "geometry": {"coordinates":[-83.64575,40.783016],"type":"Point"}
}
