{
  "type": "Feature",
  "properties": {
    "addr:full": "1799 E State St Fremont OH 43420",
    "addr:housenumber": "1799",
    "addr:postcode": "43420",
    "addr:street": "E State St",
    "iso:country": "US",
    "sg:address": "1799 E State St",
    "sg:city": "Fremont",
    "sg:classifiers": [
      {
        "category": "Shopping",
        "subcategory": "Used Merchandise",
        "type": "Retail Goods"
      }
    ],
    "sg:phone": "+1 419 333 0092",
    "sg:postcode": "43420",
    "sg:province": "OH",
    "sg:tags": [
      "shop",
      "consignment"
    ],
    "wof:name": "Just For Kids \u0026 Mom To Be",
    "wof:placetype": "venue"
  },
  "geometry": {"coordinates":[-83.087113,41.340322],"type":"Point"}
}
