{
  "type": "Feature",
  "properties": {
    "addr:full": "800 Oak St Columbus OH 43205",
    "addr:housenumber": "800",
    "addr:postcode": "43205",
    "addr:street": "Oak St",
    "iso:country": "US",
    "sg:address": "800 Oak St",
    "sg:city": "Columbus",
    "sg:classifiers": [
      {
        "category": "Taxi",
        "type": "Transportation"
      }
    ],
    "sg:phone": "+1 614 224 8888",
    "sg:postcode": "43205",
    "sg:province": "OH",
    "sg:tags": [
      "taxicab"
    ],
    "wof:name": "Central Ohio German Vlg Taxi",
    "wof:placetype": "venue"
  },
  "geometry": {"coordinates":[-82.979928,39.963089],"type":"Point"}
}
