{
  "type": "Feature",
  "properties": {
    "addr:full": "263 S Main St Akron OH 44308",
    "addr:housenumber": "263",
    "addr:postcode": "44308",
    "addr:street": "S Main St",
    "iso:country": "US",
    "sg:address": "263 S Main St",
    "sg:city": "Akron",
    "sg:classifiers": [
      {
        "category": "Real Estate",
        "subcategory": "Real Estate Operator",
        "type": "Services"
      }
    ],
    "sg:phone": "+1 330 762 7518",
    "sg:postcode": "44308",
    "sg:province": "OH",
    "sg:tags": [
      "apartment",
      "complex"
    ],
    "wof:name": "Mayflower Manor Apartments",
    "wof:placetype": "venue"
  },
  "geometry": {"coordinates":[-81.521171,41.077853],"type":"Point"}
}
