{
  "type": "Feature",
  "properties": {
    "addr:full":"3300 Shepler Church Ave SW Canton OH 44706",
    "addr:postcode":"3300;44706",
    "addr:street":"Church Ave Sw",
    "iso:country":"US",
    "sg:address":"3300 Shepler Church Ave SW",
    "sg:city":"Canton",
    "sg:classifiers":[
        {
            "category":"Building & Trades",
            "subcategory":"Plumbing",
            "type":"Services"
        }
    ],
    "sg:phone":"+1 330 484 4328",
    "sg:postcode":"44706",
    "sg:province":"OH",
    "sg:tags":[
        "heating",
        "contractor"
    ],
    "wof:name":"GMC Heating & Cooling",
    "wof:placetype":"venue"
},
  "geometry": {"coordinates":[-81.420261,40.760456],"type":"Point"}
}