{
  "type": "Feature",
  "properties": {
    "iso:country":"US",
    "sg:address":"111 Water St",
    "sg:city":"Chardon",
    "sg:classifiers":[
        {
            "category":"Government",
            "subcategory":"Office",
            "type":"Public Place"
        }
    ],
    "sg:phone":"+1 440 286 2655",
    "sg:postcode":"44024",
    "sg:province":"OH",
    "sg:tags":[
        "village"
    ],
    "wof:name":"Chardon Vlg Public Svc Dept",
    "wof:placetype":"venue"
},
  "geometry": {"coordinates":[-81.204462,41.580876],"type":"Point"}
}