{
  "type": "Feature",
  "properties": {
    "iso:country":"US",
    "sg:address":"1534 Brittain Rd",
    "sg:city":"Akron",
    "sg:classifiers":[
        {
            "category":"Manufacturing",
            "subcategory":"Tools & Machinery",
            "type":"Manufacturing & Wholesale Goods"
        }
    ],
    "sg:phone":"+1 330 630 9200",
    "sg:postcode":"44310",
    "sg:province":"OH",
    "sg:tags":[
        "peripheral",
        "computer",
        "compute",
        "mfg"
    ],
    "sg:website":"www.lazeraction.com",
    "wof:name":"Lazer Action Inc",
    "wof:placetype":"venue"
},
  "geometry": {"coordinates":[-81.466205,41.108125],"type":"Point"}
}