{
  "type": "Feature",
  "properties": {
    "iso:country":"US",
    "sg:address":"100 W Middle St",
    "sg:city":"Burbank",
    "sg:classifiers":[
        {
            "category":"Government",
            "subcategory":"Office",
            "type":"Public Place"
        }
    ],
    "sg:phone":"+1 330 624 3232",
    "sg:postcode":"44214",
    "sg:province":"OH",
    "sg:tags":[
        "village"
    ],
    "wof:name":"Burbank Village Council Room",
    "wof:placetype":"venue"
},
  "geometry": {"coordinates":[-81.99828599999999,40.988952],"type":"Point"}
}