{
  "type": "Feature",
  "properties": {
    "addr:full":"3231 Lincoln Way Wooster OH 44691",
    "addr:housenumber":"3231",
    "addr:postcode":"44691",
    "addr:street":"Lincoln Way",
    "iso:country":"US",
    "sg:address":"3231 Lincoln Way",
    "sg:city":"Wooster",
    "sg:classifiers":[
        {
            "category":"Autos & Motor Vehicles",
            "subcategory":"Automobile Sales",
            "type":"Retail Goods"
        }
    ],
    "sg:phone":"+1 330 264 4538",
    "sg:postcode":"44691",
    "sg:province":"OH",
    "sg:tags":[
        "used"
    ],
    "wof:name":"Weidner Motors Liquidation Stn",
    "wof:placetype":"venue"
},
  "geometry": {"coordinates":[-81.90173799999999,40.795704],"type":"Point"}
}