{
  "type": "Feature",
  "properties": {
    "iso:country":"US",
    "sg:address":"1213 Spruce St",
    "sg:city":"Troy",
    "sg:classifiers":[
        {
            "category":"Taxi",
            "type":"Transportation"
        }
    ],
    "sg:phone":"+1 937 339 2367",
    "sg:postcode":"45373",
    "sg:province":"OH",
    "sg:tags":[
        "taxicab"
    ],
    "wof:name":"Area Wide Taxi & Delivery Co",
    "wof:placetype":"venue"
},
  "geometry": {"coordinates":[-84.224253,40.020345],"type":"Point"}
}