{
  "type": "Feature",
  "properties": {
    "addr:full": "1213 Spruce St Troy OH 45373",
    "addr:housenumber": "1213",
    "addr:postcode": "45373",
    "addr:street": "Spruce St",
    "iso:country": "US",
    "sg:address": "1213 Spruce St",
    "sg:city": "Troy",
    "sg:classifiers": [
      {
        "category": "Taxi",
        "type": "Transportation"
      }
    ],
    "sg:phone": "+1 937 339 2367",
    "sg:postcode": "45373",
    "sg:province": "OH",
    "sg:tags": [
      "taxicab"
    ],
    "wof:name": "Area Wide Taxi \u0026 Delivery Co",
    "wof:placetype": "venue"
  },
  "geometry": {"coordinates":[-84.224253,40.020345],"type":"Point"}
}
