{
  "type": "Feature",
  "properties": {
    "addr:full":"5914 Rd R Pandora OH 45877",
    "addr:postcode":"5914;45877",
    "addr:street":"Rd",
    "iso:country":"US",
    "sg:address":"5914 Rd R",
    "sg:city":"Pandora",
    "sg:classifiers":[
        {
            "category":"Farming",
            "subcategory":"Farm",
            "type":"Manufacturing & Wholesale Goods"
        }
    ],
    "sg:phone":"+1 419 384 3768",
    "sg:postcode":"45877",
    "sg:province":"OH",
    "sg:tags":[
        "crop",
        "general"
    ],
    "wof:name":"TNT Farms Partner",
    "wof:placetype":"venue"
},
  "geometry": {"coordinates":[-83.974301,40.920032],"type":"Point"}
}