{
  "type": "Feature",
  "properties": {
    "iso:country":"US",
    "sg:address":"555 N Meridian Rd",
    "sg:city":"Youngstown",
    "sg:classifiers":[
        {
            "category":"Freight",
            "type":"Transportation"
        }
    ],
    "sg:phone":"+1 330 793 9331",
    "sg:postcode":"44509",
    "sg:province":"OH",
    "sg:tags":[
        "trucking"
    ],
    "wof:name":"Great Lakes Cartage Co",
    "wof:placetype":"venue"
},
  "geometry": {"coordinates":[-80.711084,41.11761],"type":"Point"}
}