{
  "type": "Feature",
  "properties": {
    "iso:country":"US",
    "sg:address":"4461 W Alexis Rd",
    "sg:city":"Toledo",
    "sg:classifiers":[
        {
            "category":"Professional",
            "subcategory":"Management & Consulting",
            "type":"Services"
        },
        {
            "category":"Professional",
            "subcategory":"Art Services",
            "type":"Services"
        }
    ],
    "sg:phone":"+1 419 472 8808",
    "sg:postcode":"43623",
    "sg:province":"OH",
    "sg:tags":[
        "marketing",
        "graphic",
        "group",
        "designer",
        "communications"
    ],
    "wof:name":"Hoeck Associates Inc",
    "wof:placetype":"venue"
},
  "geometry": {"coordinates":[-83.648447,41.720086],"type":"Point"}
}