{
  "type": "Feature",
  "properties": {
    "addr:full": "105 Park Dr Richmond OH 43944",
    "addr:housenumber": "105",
    "addr:postcode": "43944",
    "addr:street": "Park Dr",
    "iso:country": "US",
    "sg:address": "105 Park Dr",
    "sg:city": "Richmond",
    "sg:classifiers": [
      {
        "category": "Retail",
        "subcategory": "Auto Repair",
        "type": "Services"
      }
    ],
    "sg:phone": "+1 740 765 4232",
    "sg:postcode": "43944",
    "sg:province": "OH",
    "sg:tags": [
      "repairing",
      "automobile"
    ],
    "wof:name": "Topper's Auto Repair",
    "wof:placetype": "venue"
  },
  "geometry": {"coordinates":[-80.748751,40.421582],"type":"Point"}
}
