{
  "type": "Feature",
  "properties": {
    "iso:country":"US",
    "sg:address":"185 W Main St",
    "sg:city":"St Clairsville",
    "sg:classifiers":[
        {
            "category":"Utilities",
            "subcategory":"Fuel Oil & Lpg",
            "type":"Services"
        }
    ],
    "sg:phone":"+1 740 695 6477",
    "sg:postcode":"43950",
    "sg:province":"OH",
    "sg:tags":[
        "coal",
        "coke"
    ],
    "wof:name":"Coal Network",
    "wof:placetype":"venue"
},
  "geometry": {"coordinates":[-80.904623,40.079723],"type":"Point"}
}