{
  "type": "Feature",
  "properties": {
    "addr:full": "6906 E Front St Portsmouth OH 45662",
    "addr:housenumber": "6906",
    "addr:postcode": "45662",
    "addr:street": "E Front St",
    "iso:country": "US",
    "sg:address": "6906 E Front St",
    "sg:city": "Portsmouth",
    "sg:classifiers": [
      {
        "category": "Restaurant",
        "type": "Food \u0026 Drink"
      }
    ],
    "sg:phone": "+1 740 776 6231",
    "sg:postcode": "45662",
    "sg:province": "OH",
    "sg:tags": [
      "pizza"
    ],
    "wof:name": "Dick's Pizza",
    "wof:placetype": "venue"
  },
  "geometry": {"coordinates":[-82.872769,38.745903],"type":"Point"}
}
