{
  "type": "Feature",
  "properties": {
    "addr:full":"18927 Saint Clair Ave Cleveland OH 44110",
    "addr:housenumber":"18927",
    "addr:postcode":"44110",
    "addr:street":"Saint Clair Ave Cleveland",
    "iso:country":"US",
    "sg:address":"18927 Saint Clair Ave",
    "sg:city":"Cleveland",
    "sg:classifiers":[
        {
            "category":"Retail",
            "subcategory":"Auto Repair",
            "type":"Services"
        }
    ],
    "sg:phone":"+1 216 481 0007",
    "sg:postcode":"44110",
    "sg:province":"OH",
    "sg:tags":[
        "automobile",
        "customizing"
    ],
    "wof:name":"Technical Craft Auto Svc",
    "wof:placetype":"venue"
},
  "geometry": {"coordinates":[-81.547449,41.574396],"type":"Point"}
}