{
  "type": "Feature",
  "properties": {
    "addr:full": "1053 Belmont Ave Youngstown OH 44504",
    "addr:housenumber": "1053",
    "addr:postcode": "44504",
    "addr:street": "Belmont Ave",
    "iso:country": "US",
    "sg:address": "1053 Belmont Ave",
    "sg:city": "Youngstown",
    "sg:classifiers": [
      {
        "category": "Health Services",
        "subcategory": "Health Practitioner",
        "type": "Services"
      }
    ],
    "sg:phone": "+1 330 744 2649",
    "sg:postcode": "44504",
    "sg:province": "OH",
    "sg:tags": [
      "psychologist"
    ],
    "wof:name": "St Elizabeth Family Health Ctr",
    "wof:placetype": "venue"
  },
  "geometry": {"coordinates":[-80.655892,41.114978],"type":"Point"}
}
