{
  "type": "Feature",
  "properties": {
    "iso:country":"US",
    "sg:address":"2165 Montero Rd NE",
    "sg:city":"Carrollton",
    "sg:classifiers":[
        {
            "category":"Wholesale",
            "subcategory":"Farm Supplies",
            "type":"Manufacturing & Wholesale Goods"
        }
    ],
    "sg:phone":"+1 330 627 3827",
    "sg:postcode":"44615",
    "sg:province":"OH",
    "sg:tags":[
        "livestock"
    ],
    "wof:name":"Buttercup Field",
    "wof:placetype":"venue"
},
  "geometry": {"coordinates":[-81.013791,40.618157],"type":"Point"}
}