{
  "type": "Feature",
  "properties": {
    "iso:country":"US",
    "sg:address":"1715 53rd St SW",
    "sg:city":"Canton",
    "sg:classifiers":[
        {
            "category":"Building & Trades",
            "subcategory":"Construction",
            "type":"Services"
        }
    ],
    "sg:phone":"+1 330 484 4079",
    "sg:postcode":"44706",
    "sg:province":"OH",
    "sg:tags":[
        "carpentry",
        "contractor"
    ],
    "wof:name":"Ronald E May",
    "wof:placetype":"venue"
},
  "geometry": {"coordinates":[-81.385319,40.735674],"type":"Point"}
}