{
  "type": "Feature",
  "properties": {
    "addr:full": "1715 53rd St SW Canton OH 44706",
    "addr:housenumber": "1715",
    "addr:postcode": "44706",
    "addr:street": "53Rd St Sw",
    "iso:country": "US",
    "sg:address": "1715 53rd St SW",
    "sg:city": "Canton",
    "sg:classifiers": [
      {
        "category": "Building \u0026 Trades",
        "subcategory": "Construction",
        "type": "Services"
      }
    ],
    "sg:phone": "+1 330 484 4079",
    "sg:postcode": "44706",
    "sg:province": "OH",
    "sg:tags": [
      "carpentry",
      "contractor"
    ],
    "wof:name": "Ronald E May",
    "wof:placetype": "venue"
  },
  "geometry": {"coordinates":[-81.385319,40.735674],"type":"Point"}
}
