{
  "type": "Feature",
  "properties": {
    "iso:country":"US",
    "sg:address":"25900 Euclid Ave",
    "sg:city":"Cleveland",
    "sg:classifiers":[
        {
            "category":"Health Services",
            "subcategory":"Nursing And Care Facility",
            "type":"Services"
        }
    ],
    "sg:phone":"+1 216 261 8383",
    "sg:postcode":"44132",
    "sg:province":"OH",
    "sg:tags":[
        "home",
        "retirement",
        "community"
    ],
    "sg:website":"www.hilltopvillage.com",
    "wof:name":"Hilltop Village-A Retirement",
    "wof:placetype":"venue"
},
  "geometry": {"coordinates":[-81.502027,41.587753],"type":"Point"}
}