{
  "type": "Feature",
  "properties": {
    "addr:full": "892 E Main St Versailles OH 45380",
    "addr:housenumber": "892",
    "addr:postcode": "45380",
    "addr:street": "E Main St",
    "iso:country": "US",
    "sg:address": "892 E Main St",
    "sg:city": "Versailles",
    "sg:classifiers": [
      {
        "category": "Food \u0026 Beverages",
        "subcategory": "Dairy",
        "type": "Retail Goods"
      }
    ],
    "sg:phone": "+1 937 526 9950",
    "sg:postcode": "45380",
    "sg:province": "OH",
    "sg:tags": [
      "product"
    ],
    "wof:name": "Alice's Dairy Bar",
    "wof:placetype": "venue"
  },
  "geometry": {"coordinates":[-84.472616,40.223407],"type":"Point"}
}
