{
  "type": "Feature",
  "properties": {
    "addr:full":"4511 Rockside Rd Cleveland OH 44131",
    "addr:housenumber":"4511",
    "addr:postcode":"44131",
    "addr:street":"Rockside Rd",
    "iso:country":"US",
    "sg:address":"4511 Rockside Rd",
    "sg:city":"Cleveland",
    "sg:classifiers":[
        {
            "category":"Utilities",
            "subcategory":"Telephone",
            "type":"Services"
        }
    ],
    "sg:phone":"+1 216 573 1111",
    "sg:postcode":"44131",
    "sg:province":"OH",
    "sg:tags":[
        "communications",
        "telecommunication"
    ],
    "wof:name":"Worldwide Telecom Solutions",
    "wof:placetype":"venue"
},
  "geometry": {"coordinates":[-81.660726,41.39899],"type":"Point"}
}