{
  "type": "Feature",
  "properties": {
    "iso:country":"US",
    "sg:address":"2779 Pike Lake Rd",
    "sg:city":"Bainbridge",
    "sg:classifiers":[
        {
            "category":"Restaurant",
            "type":"Food & Drink"
        }
    ],
    "sg:phone":"+1 740 493 4300",
    "sg:postcode":"45612",
    "sg:province":"OH",
    "wof:name":"Trails End Restaurant",
    "wof:placetype":"venue"
},
  "geometry": {"coordinates":[-83.227986,39.173638],"type":"Point"}
}