{
  "type": "Feature",
  "properties": {
    "addr:full": "2779 Pike Lake Rd Bainbridge OH 45612",
    "addr:housenumber": "2779",
    "addr:postcode": "45612",
    "addr:street": "Pike Lake Rd",
    "iso:country": "US",
    "sg:address": "2779 Pike Lake Rd",
    "sg:city": "Bainbridge",
    "sg:classifiers": [
      {
        "category": "Restaurant",
        "type": "Food \u0026 Drink"
      }
    ],
    "sg:phone": "+1 740 493 4300",
    "sg:postcode": "45612",
    "sg:province": "OH",
    "wof:name": "Trails End Restaurant",
    "wof:placetype": "venue"
  },
  "geometry": {"coordinates":[-83.227986,39.173638],"type":"Point"}
}
