{
  "type": "Feature",
  "properties": {
    "iso:country":"US",
    "sg:address":"7470 Meadowbrook Rd",
    "sg:city":"Albany",
    "sg:classifiers":[
        {
            "category":"Retail",
            "subcategory":"Laundry & Dry Cleaning",
            "type":"Services"
        }
    ],
    "sg:phone":"+1 740 698 7040",
    "sg:postcode":"45710",
    "sg:province":"OH",
    "sg:tags":[
        "cleaners",
        "rug",
        "carpet"
    ],
    "wof:name":"Captain Steamer Carpet Clng",
    "wof:placetype":"venue"
},
  "geometry": {"coordinates":[-82.159858,39.230831],"type":"Point"}
}