{
  "type": "Feature",
  "properties": {
    "iso:country":"US",
    "sg:address":"1255 Columbus Ave",
    "sg:city":"Marysville",
    "sg:classifiers":[
        {
            "category":"Autos & Motor Vehicles",
            "subcategory":"Automobile Sales",
            "type":"Retail Goods"
        }
    ],
    "sg:phone":"+1 937 642 0015",
    "sg:postcode":"43040",
    "sg:province":"OH",
    "sg:tags":[
        "car",
        "dealer"
    ],
    "sg:website":"www.bobchapmanford.com",
    "wof:name":"Bob Chapman Ford Mercury",
    "wof:placetype":"venue"
},
  "geometry": {"coordinates":[-83.34749100000001,40.229398],"type":"Point"}
}