{
  "type": "Feature",
  "properties": {
    "addr:full":"3305 Canterbury Rd Westlake OH 44145",
    "addr:housenumber":"3305",
    "addr:postcode":"44145",
    "addr:street":"Canterbury Rd",
    "iso:country":"US",
    "sg:address":"3305 Canterbury Rd",
    "sg:city":"Westlake",
    "sg:classifiers":[
        {
            "category":"Professional",
            "subcategory":"Management & Consulting",
            "type":"Services"
        }
    ],
    "sg:phone":"+1 440 899 9136",
    "sg:postcode":"44145",
    "sg:province":"OH",
    "sg:tags":[
        "consultant"
    ],
    "wof:name":"Brainstorm",
    "wof:placetype":"venue"
},
  "geometry": {"coordinates":[-81.91281499999999,41.439642],"type":"Point"}
}