{
  "type": "Feature",
  "properties": {
    "iso:country":"US",
    "sg:address":"2866 E High St",
    "sg:city":"Springfield",
    "sg:classifiers":[
        {
            "category":"Personal",
            "subcategory":"Tanning Parlor",
            "type":"Services"
        }
    ],
    "sg:phone":"+1 937 325 8826",
    "sg:postcode":"45505",
    "sg:province":"OH",
    "sg:tags":[
        "salon"
    ],
    "wof:name":"Lectrasun",
    "wof:placetype":"venue"
},
  "geometry": {"coordinates":[-83.763169,39.918205],"type":"Point"}
}