{
  "type": "Feature",
  "properties": {
    "addr:full":"16100 Lake Shore Blvd Cleveland OH 44110",
    "addr:housenumber":"16100",
    "addr:postcode":"44110",
    "addr:street":"Lake Shore Blvd",
    "iso:country":"US",
    "sg:address":"16100 Lake Shore Blvd",
    "sg:city":"Cleveland",
    "sg:classifiers":[
        {
            "category":"Restaurant",
            "type":"Food & Drink"
        }
    ],
    "sg:phone":"+1 216 738 0501",
    "sg:postcode":"44110",
    "sg:province":"OH",
    "wof:name":"Popeyes Chicken & Biscuits",
    "wof:placetype":"venue"
},
  "geometry": {"coordinates":[-81.567132,41.579885],"type":"Point"}
}