{
  "type": "Feature",
  "properties": {
    "iso:country":"US",
    "sg:address":"27800 Lemoyne Rd",
    "sg:city":"Millbury",
    "sg:classifiers":[
        {
            "category":"Professional",
            "subcategory":"Engineering",
            "type":"Services"
        }
    ],
    "sg:phone":"+1 419 837 9783",
    "sg:postcode":"43447",
    "sg:province":"OH",
    "sg:tags":[
        "engineer"
    ],
    "wof:name":"Spectra Group LTD",
    "wof:placetype":"venue"
},
  "geometry": {"coordinates":[-83.472961,41.556721],"type":"Point"}
}