{
  "type": "Feature",
  "properties": {
    "addr:full":"15030 Terrace Rd Cleveland OH 44112",
    "addr:housenumber":"15030",
    "addr:postcode":"44112",
    "addr:street":"Terrace Rd",
    "iso:country":"US",
    "sg:address":"15030 Terrace Rd",
    "sg:city":"Cleveland",
    "sg:classifiers":[
        {
            "category":"Professional",
            "type":"Services"
        }
    ],
    "sg:phone":"+1 216 761 9226",
    "sg:postcode":"44112",
    "sg:province":"OH",
    "wof:name":"Maren M Hill",
    "wof:placetype":"venue"
},
  "geometry": {"coordinates":[-81.57319099999999,41.534257],"type":"Point"}
}