{
  "type": "Feature",
  "properties": {
    "addr:full": "4047 Beechwood Ave Cincinnati OH 45229",
    "addr:housenumber": "4047",
    "addr:postcode": "45229",
    "addr:street": "Beechwood Ave",
    "iso:country": "US",
    "sg:address": "4047 Beechwood Ave",
    "sg:city": "Cincinnati",
    "sg:classifiers": [
      {
        "category": "Organizations",
        "subcategory": "Religious Organization",
        "type": "Services"
      }
    ],
    "sg:phone": "+1 513 861 6894",
    "sg:postcode": "45229",
    "sg:province": "OH",
    "sg:tags": [
      "clergy"
    ],
    "wof:name": "Samuel K Joseph Rabbi",
    "wof:placetype": "venue"
  },
  "geometry": {"coordinates":[-84.485354,39.159069],"type":"Point"}
}
