{
  "type": "Feature",
  "properties": {
    "iso:country":"US",
    "sg:address":"3200 Berlin Station Rd",
    "sg:city":"Delaware",
    "sg:classifiers":[
        {
            "category":"Building & Trades",
            "subcategory":"Construction",
            "type":"Services"
        }
    ],
    "sg:phone":"+1 740 548 6232",
    "sg:postcode":"43015",
    "sg:province":"OH",
    "sg:tags":[
        "general",
        "contractor"
    ],
    "wof:name":"Henry Dirienzo & Sons Inc",
    "wof:placetype":"venue"
},
  "geometry": {"coordinates":[-83.004143,40.255666],"type":"Point"}
}