{
  "type": "Feature",
  "properties": {
    "addr:full":"4541 Main Ave Ashtabula OH 44004",
    "addr:housenumber":"4541",
    "addr:postcode":"44004",
    "addr:street":"Main Ave",
    "iso:country":"US",
    "sg:address":"4541 Main Ave",
    "sg:city":"Ashtabula",
    "sg:classifiers":[
        {
            "category":"Recreation",
            "type":"Entertainment"
        }
    ],
    "sg:phone":"+1 440 992 1609",
    "sg:postcode":"44004",
    "sg:province":"OH",
    "sg:tags":[
        "martial",
        "arts",
        "instruction"
    ],
    "wof:name":"Iron Dragon Martial Arts Acad",
    "wof:placetype":"venue"
},
  "geometry": {"coordinates":[-80.782088,41.86588],"type":"Point"}
}