{
  "type": "Feature",
  "properties": {
    "addr:full": "1314 Findlay Rd Lima OH 45801",
    "addr:housenumber": "1314",
    "addr:postcode": "45801",
    "addr:street": "Findlay Rd",
    "iso:country": "US",
    "sg:address": "1314 Findlay Rd",
    "sg:city": "Lima",
    "sg:classifiers": [
      {
        "category": "Home \u0026 Garden",
        "subcategory": "Building Materials",
        "type": "Retail Goods"
      }
    ],
    "sg:phone": "+1 419 228 3434",
    "sg:postcode": "45801",
    "sg:province": "OH",
    "sg:tags": [
      "stone"
    ],
    "wof:name": "National Lime \u0026 Stone Co",
    "wof:placetype": "venue"
  },
  "geometry": {"coordinates":[-84.087653,40.753562],"type":"Point"}
}
