{
  "type": "Feature",
  "properties": {
    "iso:country":"US",
    "sg:address":"1314 Findlay Rd",
    "sg:city":"Lima",
    "sg:classifiers":[
        {
            "category":"Home & Garden",
            "subcategory":"Building Materials",
            "type":"Retail Goods"
        }
    ],
    "sg:phone":"+1 419 228 3434",
    "sg:postcode":"45801",
    "sg:province":"OH",
    "sg:tags":[
        "stone"
    ],
    "wof:name":"National Lime & Stone Co",
    "wof:placetype":"venue"
},
  "geometry": {"coordinates":[-84.087653,40.753562],"type":"Point"}
}