{
  "type": "Feature",
  "properties": {
    "addr:full": "1934 W Market St Akron OH 44313",
    "addr:housenumber": "1934",
    "addr:postcode": "44313",
    "addr:street": "W Market St",
    "iso:country": "US",
    "sg:address": "1934 W Market St",
    "sg:city": "Akron",
    "sg:classifiers": [
      {
        "category": "Shopping",
        "type": "Retail Goods"
      }
    ],
    "sg:phone": "+1 330 836 0727",
    "sg:postcode": "44313",
    "sg:province": "OH",
    "sg:tags": [
      "sporting",
      "merchandise"
    ],
    "wof:name": "Exercare Fitness Equipment",
    "wof:placetype": "venue"
  },
  "geometry": {"coordinates":[-81.577308,41.112926],"type":"Point"}
}
