{
  "type": "Feature",
  "properties": {
    "addr:full":"6460 Hetzler Rd Middletown OH 45042",
    "addr:postcode":"6460;45042",
    "addr:street":"Hetzler Rd",
    "iso:country":"US",
    "sg:address":"6460 Hetzler Rd",
    "sg:city":"Middletown",
    "sg:classifiers":[
        {
            "category":"Building & Trades",
            "subcategory":"Plumbing",
            "type":"Services"
        }
    ],
    "sg:phone":"+1 513 422 4155",
    "sg:postcode":"45042",
    "sg:province":"OH",
    "sg:tags":[
        "contractor"
    ],
    "wof:name":"Quality Plumbing",
    "wof:placetype":"venue"
},
  "geometry": {"coordinates":[-84.434212,39.56348],"type":"Point"}
}