{
  "type": "Feature",
  "properties": {
    "addr:full": "44 Greenfield St Tiffin OH 44883",
    "addr:housenumber": "44",
    "addr:postcode": "44883",
    "addr:street": "Greenfield St",
    "iso:country": "US",
    "sg:address": "44 Greenfield St",
    "sg:city": "Tiffin",
    "sg:classifiers": [
      {
        "category": "Shopping",
        "subcategory": "Books",
        "type": "Retail Goods"
      }
    ],
    "sg:phone": "+1 419 448 2012",
    "sg:postcode": "44883",
    "sg:province": "OH",
    "sg:tags": [
      "dealer"
    ],
    "sg:website": "www.heidelberg.edu",
    "wof:name": "Heidelberg College Bookstore",
    "wof:placetype": "venue"
  },
  "geometry": {"coordinates":[-83.168237,41.115678],"type":"Point"}
}
