{
  "type": "Feature",
  "properties": {
    "addr:full":"22468 Holycross-Epps Rd Marysville OH 43040",
    "addr:postcode":"22468;43040",
    "addr:street":"Holycross-Epps Rd",
    "iso:country":"US",
    "sg:address":"22468 Holycross-Epps Rd",
    "sg:city":"Marysville",
    "sg:classifiers":[
        {
            "category":"Building & Trades",
            "subcategory":"Construction",
            "type":"Services"
        }
    ],
    "sg:phone":"+1 937 642 0544",
    "sg:postcode":"43040",
    "sg:province":"OH",
    "sg:tags":[
        "excavation",
        "contractor",
        "general"
    ],
    "wof:name":"Chapman Ron Excavating LLC",
    "wof:placetype":"venue"
},
  "geometry": {"coordinates":[-83.48093299999999,40.261287],"type":"Point"}
}