{
  "type": "Feature",
  "properties": {
    "iso:country":"US",
    "sg:address":"31 W Main St",
    "sg:city":"Xenia",
    "sg:classifiers":[
        {
            "category":"Personal",
            "subcategory":"Beauty Salon",
            "type":"Services"
        }
    ],
    "sg:phone":"+1 937 372 9004",
    "sg:postcode":"45385",
    "sg:province":"OH",
    "wof:name":"Total Look Hair Design",
    "wof:placetype":"venue"
},
  "geometry": {"coordinates":[-83.93059,39.684799],"type":"Point"}
}