{
  "type": "Feature",
  "properties": {
    "addr:full": "1234 State Rd Hinckley OH 44233",
    "addr:housenumber": "1234",
    "addr:postcode": "44233",
    "addr:street": "State Rd",
    "iso:country": "US",
    "sg:address": "1234 State Rd",
    "sg:city": "Hinckley",
    "sg:classifiers": [
      {
        "category": "Real Estate",
        "subcategory": "Real Estate Agent",
        "type": "Services"
      }
    ],
    "sg:phone": "+1 330 278 2733",
    "sg:postcode": "44233",
    "sg:province": "OH",
    "wof:name": "First Amercn RE Solutions LLC",
    "wof:placetype": "venue"
  },
  "geometry": {"coordinates":[-81.703109,41.244275],"type":"Point"}
}
