{
  "type": "Feature",
  "properties": {
    "addr:full": "5405 Miami Ave Cincinnati OH 45226",
    "addr:housenumber": "5405",
    "addr:postcode": "45226",
    "addr:street": "Miami Ave",
    "iso:country": "US",
    "sg:address": "5405 Miami Ave",
    "sg:city": "Cincinnati",
    "sg:classifiers": [
      {
        "category": "Freight",
        "type": "Transportation"
      }
    ],
    "sg:phone": "+1 513 871 7205",
    "sg:postcode": "45226",
    "sg:province": "OH",
    "sg:tags": [
      "arrangement"
    ],
    "wof:name": "G \u0026 J Koch Trucking",
    "wof:placetype": "venue"
  },
  "geometry": {"coordinates":[-84.401461,39.131966],"type":"Point"}
}
