{
  "type": "Feature",
  "properties": {
    "iso:country":"US",
    "sg:address":"3093 Westboro Rd",
    "sg:city":"Blanchester",
    "sg:classifiers":[
        {
            "category":"Farming",
            "subcategory":"Farm",
            "type":"Manufacturing & Wholesale Goods"
        }
    ],
    "sg:phone":"+1 937 783 2794",
    "sg:postcode":"45107",
    "sg:province":"OH",
    "sg:tags":[
        "crop",
        "general"
    ],
    "wof:name":"P Griffith",
    "wof:placetype":"venue"
},
  "geometry": {"coordinates":[-83.952481,39.279931],"type":"Point"}
}