{
  "type": "Feature",
  "properties": {
    "addr:full": "3093 Westboro Rd Blanchester OH 45107",
    "addr:housenumber": "3093",
    "addr:postcode": "45107",
    "addr:street": "Westboro Rd",
    "iso:country": "US",
    "sg:address": "3093 Westboro Rd",
    "sg:city": "Blanchester",
    "sg:classifiers": [
      {
        "category": "Farming",
        "subcategory": "Farm",
        "type": "Manufacturing \u0026 Wholesale Goods"
      }
    ],
    "sg:phone": "+1 937 783 2794",
    "sg:postcode": "45107",
    "sg:province": "OH",
    "sg:tags": [
      "crop",
      "general"
    ],
    "wof:name": "P Griffith",
    "wof:placetype": "venue"
  },
  "geometry": {"coordinates":[-83.952481,39.279931],"type":"Point"}
}
