{
  "type": "Feature",
  "properties": {
    "iso:country":"US",
    "sg:address":"1686 Williams Rd",
    "sg:city":"Columbus",
    "sg:classifiers":[
        {
            "category":"Building & Trades",
            "subcategory":"Construction",
            "type":"Services"
        }
    ],
    "sg:phone":"+1 614 497 0020",
    "sg:postcode":"43207",
    "sg:province":"OH",
    "sg:tags":[
        "excavating",
        "contractor"
    ],
    "wof:name":"John Eramo & Sons Inc",
    "wof:placetype":"venue"
},
  "geometry": {"coordinates":[-82.94642899999999,39.889605],"type":"Point"}
}