{
  "type": "Feature",
  "properties": {
    "addr:full":"7422 Normandy Ln Dayton OH 45459",
    "addr:housenumber":"7422",
    "addr:postcode":"45459",
    "addr:street":"Normandy Ln",
    "iso:country":"US",
    "sg:address":"7422 Normandy Ln",
    "sg:city":"Dayton",
    "sg:classifiers":[
        {
            "category":"Education",
            "subcategory":"School",
            "type":"Public Place"
        }
    ],
    "sg:phone":"+1 937 436 0578",
    "sg:postcode":"45459",
    "sg:province":"OH",
    "wof:name":"Ohio Assoc For Gifted CHI",
    "wof:placetype":"venue"
},
  "geometry": {"coordinates":[-84.16788699999999,39.637881],"type":"Point"}
}