{
  "type": "Feature",
  "properties": {
    "iso:country":"US",
    "sg:address":"11072 Shetler Rd NW",
    "sg:city":"Bolivar",
    "sg:classifiers":[
        {
            "category":"Building & Trades",
            "subcategory":"Construction",
            "type":"Services"
        }
    ],
    "sg:phone":"+1 330 878 7290",
    "sg:postcode":"44612",
    "sg:province":"OH",
    "sg:tags":[
        "water",
        "well",
        "drilling"
    ],
    "wof:name":"Bloo Excavating & Water Well",
    "wof:placetype":"venue"
},
  "geometry": {"coordinates":[-81.51863,40.640907],"type":"Point"}
}