{
  "type": "Feature",
  "properties": {
    "iso:country":"US",
    "sg:address":"1884 Walnut St",
    "sg:city":"Goshen",
    "sg:classifiers":[
        {
            "category":"Government",
            "subcategory":"Police Station",
            "type":"Public Place"
        }
    ],
    "sg:phone":"+1 513 722 3200",
    "sg:postcode":"45122",
    "sg:province":"OH",
    "sg:tags":[
        "department"
    ],
    "wof:name":"Goshen Police Dept",
    "wof:placetype":"venue"
},
  "geometry": {"coordinates":[-84.161462,39.235005],"type":"Point"}
}