{
  "type": "Feature",
  "properties": {
    "addr:full":"925 Hamilton Cleves Rd Hamilton IN 45013",
    "addr:housenumber":"925",
    "addr:postcode":"45013",
    "addr:street":"Hamilton Cleves Rd",
    "iso:country":"US",
    "sg:address":"925 Hamilton Cleves Rd",
    "sg:city":"Hamilton",
    "sg:classifiers":[
        {
            "category":"Organizations",
            "subcategory":"Community Association",
            "type":"Services"
        }
    ],
    "sg:phone":"+1 513 737 3354",
    "sg:postcode":"45013",
    "sg:province":"IN",
    "sg:tags":[
        "fraternal"
    ],
    "wof:name":"Loyal Order Of Moose",
    "wof:placetype":"venue"
},
  "geometry": {"coordinates":[-84.574279,39.387576],"type":"Point"}
}