{
  "type": "Feature",
  "properties": {
    "addr:full": "3800 King Ave Cleveland OH 44114",
    "addr:housenumber": "3800",
    "addr:postcode": "44114",
    "addr:street": "King Ave",
    "iso:country": "US",
    "sg:address": "3800 King Ave",
    "sg:city": "Cleveland",
    "sg:classifiers": [
      {
        "category": "Food \u0026 Beverages",
        "subcategory": "Liquor \u0026 Beverages",
        "type": "Retail Goods"
      },
      {
        "category": "Wholesale",
        "subcategory": "Beer",
        "type": "Manufacturing \u0026 Wholesale Goods"
      }
    ],
    "sg:phone": "+1 216 431 1600",
    "sg:postcode": "44114",
    "sg:province": "OH",
    "sg:tags": [
      "ale"
    ],
    "sg:website": "www.beveragedist.com",
    "wof:name": "Beverage Distributors Inc",
    "wof:placetype": "venue"
  },
  "geometry": {"coordinates":[-81.666744,41.519328],"type":"Point"}
}
