{
  "type": "Feature",
  "properties": {
    "iso:country":"US",
    "sg:address":"3800 King Ave",
    "sg:city":"Cleveland",
    "sg:classifiers":[
        {
            "category":"Food & Beverages",
            "subcategory":"Liquor & Beverages",
            "type":"Retail Goods"
        },
        {
            "category":"Wholesale",
            "subcategory":"Beer",
            "type":"Manufacturing & Wholesale Goods"
        }
    ],
    "sg:phone":"+1 216 431 1600",
    "sg:postcode":"44114",
    "sg:province":"OH",
    "sg:tags":[
        "ale"
    ],
    "sg:website":"www.beveragedist.com",
    "wof:name":"Beverage Distributors Inc",
    "wof:placetype":"venue"
},
  "geometry": {"coordinates":[-81.666744,41.519328],"type":"Point"}
}