{
  "type": "Feature",
  "properties": {
    "addr:full":"3136 Broadway Grove City OH 43123",
    "addr:housenumber":"3136",
    "addr:postcode":"43123",
    "addr:street":"Broadway",
    "iso:country":"US",
    "sg:address":"3136 Broadway",
    "sg:city":"Grove City",
    "sg:classifiers":[
        {
            "category":"Real Estate",
            "subcategory":"Real Estate Agent",
            "type":"Services"
        }
    ],
    "sg:phone":"+1 614 539 8249",
    "sg:postcode":"43123",
    "sg:province":"OH",
    "wof:name":"Homz Biz Realty LLC",
    "wof:placetype":"venue"
},
  "geometry": {"coordinates":[-83.07811599999999,39.901012],"type":"Point"}
}