{
  "type": "Feature",
  "properties": {
    "iso:country":"US",
    "sg:address":"8500 16th Rd SW",
    "sg:city":"Amanda",
    "sg:classifiers":[
        {
            "category":"Shopping",
            "subcategory":"Hobbies, Toys, & Games",
            "type":"Retail Goods"
        }
    ],
    "sg:phone":"+1 740 969 4002",
    "sg:postcode":"43102",
    "sg:province":"OH",
    "sg:tags":[
        "craft"
    ],
    "wof:name":"George's Crafts",
    "wof:placetype":"venue"
},
  "geometry": {"coordinates":[-82.78313199999999,39.608165],"type":"Point"}
}