{
  "type": "Feature",
  "properties": {
    "addr:full":"2540 Mount Vernon Rd Newark OH 43055",
    "addr:housenumber":"2540",
    "addr:postcode":"43055",
    "addr:street":"Mount Vernon Rd",
    "iso:country":"US",
    "sg:address":"2540 Mount Vernon Rd",
    "sg:city":"Newark",
    "sg:classifiers":[
        {
            "category":"Freight",
            "type":"Transportation"
        }
    ],
    "sg:phone":"+1 740 745 5771",
    "sg:postcode":"43055",
    "sg:province":"OH",
    "sg:tags":[
        "special"
    ],
    "wof:name":"C W Storage",
    "wof:placetype":"venue"
},
  "geometry": {"coordinates":[-82.429333,40.125222],"type":"Point"}
}