{
  "type": "Feature",
  "properties": {
    "iso:country":"US",
    "sg:address":"1004 Greystone Dr",
    "sg:city":"Bryan",
    "sg:classifiers":[
        {
            "category":"Professional",
            "type":"Services"
        }
    ],
    "sg:phone":"+1 419 636 2254",
    "sg:postcode":"43506",
    "sg:province":"OH",
    "sg:tags":[
        "establishment"
    ],
    "wof:name":"Johnson Michael L & Cheryl Res",
    "wof:placetype":"venue"
},
  "geometry": {"coordinates":[-84.572784,41.462479],"type":"Point"}
}