{
  "type": "Feature",
  "properties": {
    "addr:full": "1004 Greystone Dr Bryan OH 43506",
    "addr:housenumber": "1004",
    "addr:postcode": "43506",
    "addr:street": "Greystone Dr",
    "iso:country": "US",
    "sg:address": "1004 Greystone Dr",
    "sg:city": "Bryan",
    "sg:classifiers": [
      {
        "category": "Professional",
        "type": "Services"
      }
    ],
    "sg:phone": "+1 419 636 2254",
    "sg:postcode": "43506",
    "sg:province": "OH",
    "sg:tags": [
      "establishment"
    ],
    "wof:name": "Johnson Michael L \u0026 Cheryl Res",
    "wof:placetype": "venue"
  },
  "geometry": {"coordinates":[-84.572784,41.462479],"type":"Point"}
}
