{
  "type": "Feature",
  "properties": {
    "addr:full": "5125 Beacon Hill Rd Columbus OH 43228",
    "addr:housenumber": "5125",
    "addr:postcode": "43228",
    "addr:street": "Beacon Hill Rd",
    "iso:country": "US",
    "sg:address": "5125 Beacon Hill Rd",
    "sg:city": "Columbus",
    "sg:classifiers": [
      {
        "category": "Health Services",
        "subcategory": "Doctor",
        "type": "Services"
      }
    ],
    "sg:phone": "+1 614 898 2618",
    "sg:postcode": "43228",
    "sg:province": "OH",
    "sg:tags": [
      "physician",
      "surgeon"
    ],
    "wof:name": "Alvin Pelt MD",
    "wof:placetype": "venue"
  },
  "geometry": {"coordinates":[-83.136704,39.954255],"type":"Point"}
}
