{
  "type": "Feature",
  "properties": {
    "iso:country":"US",
    "sg:address":"274 Brookforest Dr",
    "sg:city":"Cincinnati",
    "sg:classifiers":[
        {
            "category":"Manufacturing",
            "subcategory":"Paper Products",
            "type":"Manufacturing & Wholesale Goods"
        }
    ],
    "sg:phone":"+1 513 451 1272",
    "sg:postcode":"45238",
    "sg:province":"OH",
    "sg:tags":[
        "mill"
    ],
    "wof:name":"T M Gay Wallcovering",
    "wof:placetype":"venue"
},
  "geometry": {"coordinates":[-84.622264,39.086872],"type":"Point"}
}