{
  "type": "Feature",
  "properties": {
    "addr:full": "274 Brookforest Dr Cincinnati OH 45238",
    "addr:housenumber": "274",
    "addr:postcode": "45238",
    "addr:street": "Brookforest Dr",
    "iso:country": "US",
    "sg:address": "274 Brookforest Dr",
    "sg:city": "Cincinnati",
    "sg:classifiers": [
      {
        "category": "Manufacturing",
        "subcategory": "Paper Products",
        "type": "Manufacturing \u0026 Wholesale Goods"
      }
    ],
    "sg:phone": "+1 513 451 1272",
    "sg:postcode": "45238",
    "sg:province": "OH",
    "sg:tags": [
      "mill"
    ],
    "wof:name": "T M Gay Wallcovering",
    "wof:placetype": "venue"
  },
  "geometry": {"coordinates":[-84.622264,39.086872],"type":"Point"}
}
