{
  "type": "Feature",
  "properties": {
    "addr:full": "10555 Montgomery Rd Cincinnati OH 45242",
    "addr:housenumber": "10555",
    "addr:postcode": "45242",
    "addr:street": "Montgomery Rd",
    "iso:country": "US",
    "sg:address": "10555 Montgomery Rd",
    "sg:city": "Cincinnati",
    "sg:classifiers": [
      {
        "category": "Professional",
        "subcategory": "Accounting \u0026 Tax Preparation",
        "type": "Services"
      }
    ],
    "sg:phone": "+1 513 482 4294",
    "sg:postcode": "45242",
    "sg:province": "OH",
    "sg:tags": [
      "accountant"
    ],
    "wof:name": "Semue P Chapman",
    "wof:placetype": "venue"
  },
  "geometry": {"coordinates":[-84.343971,39.25231],"type":"Point"}
}
