{
  "type": "Feature",
  "properties": {
    "iso:country":"US",
    "sg:address":"1600 Bethel Rd",
    "sg:city":"Columbus",
    "sg:classifiers":[
        {
            "category":"Banks & Credit Unions",
            "subcategory":"Bank",
            "type":"Services"
        }
    ],
    "sg:phone":"+1 614 545 4201",
    "sg:postcode":"43220",
    "sg:province":"OH",
    "sg:website":"www.prospectbank.com",
    "wof:name":"Sky Bank",
    "wof:placetype":"venue"
},
  "geometry": {"coordinates":[-83.06317199999999,40.06393],"type":"Point"}
}