{
  "type": "Feature",
  "properties": {
    "addr:full": "6325 Cochran Rd Cleveland OH 44139",
    "addr:housenumber": "6325",
    "addr:postcode": "44139",
    "addr:street": "Cochran Rd",
    "iso:country": "US",
    "sg:address": "6325 Cochran Rd",
    "sg:city": "Cleveland",
    "sg:classifiers": [
      {
        "category": "Insurance",
        "subcategory": "Insurance Agent",
        "type": "Services"
      }
    ],
    "sg:phone": "+1 440 498 9367",
    "sg:postcode": "44139",
    "sg:province": "OH",
    "sg:website": "www.loanprotector.com",
    "wof:name": "Loan Protector Agency",
    "wof:placetype": "venue"
  },
  "geometry": {"coordinates":[-81.469124,41.381352],"type":"Point"}
}
