{
  "type": "Feature",
  "properties": {
    "addr:full": "300 Hamilton Ave Dayton OH 45403",
    "addr:housenumber": "300",
    "addr:postcode": "45403",
    "addr:street": "Hamilton Ave",
    "iso:country": "US",
    "sg:address": "300 Hamilton Ave",
    "sg:city": "Dayton",
    "sg:classifiers": [
      {
        "category": "Manufacturing",
        "subcategory": "Signs",
        "type": "Manufacturing \u0026 Wholesale Goods"
      },
      {
        "category": "Professional",
        "subcategory": "Business Services",
        "type": "Services"
      }
    ],
    "sg:phone": "+1 937 253 2246",
    "sg:postcode": "45403",
    "sg:province": "OH",
    "sg:tags": [
      "manufacture",
      "electric",
      "painter"
    ],
    "sg:website": "www.wilsonsigncompany.com",
    "wof:name": "Wilson Sign Co Inc",
    "wof:placetype": "venue"
  },
  "geometry": {"coordinates":[-84.161532,39.757827],"type":"Point"}
}
