{
  "type": "Feature",
  "properties": {
    "addr:full": "4972 E 71st St Cleveland OH 44125",
    "addr:housenumber": "4972",
    "addr:postcode": "44125",
    "addr:street": "E 71St St",
    "iso:country": "US",
    "sg:address": "4972 E 71st St",
    "sg:city": "Cleveland",
    "sg:classifiers": [
      {
        "category": "Restaurant",
        "type": "Food \u0026 Drink"
      }
    ],
    "sg:phone": "+1 216 341 9850",
    "sg:postcode": "44125",
    "sg:province": "OH",
    "sg:tags": [
      "eating"
    ],
    "wof:name": "Peppis Classic Catering",
    "wof:placetype": "venue"
  },
  "geometry": {"coordinates":[-81.64228,41.422494],"type":"Point"}
}
