{
  "type": "Feature",
  "properties": {
    "addr:full":"315 Industrial Dr Franklin OH 45005",
    "addr:housenumber":"315",
    "addr:postcode":"45005",
    "addr:street":"Industrial Dr",
    "iso:country":"US",
    "sg:address":"315 Industrial Dr",
    "sg:city":"Franklin",
    "sg:classifiers":[
        {
            "category":"Manufacturing",
            "subcategory":"Tools & Machinery",
            "type":"Manufacturing & Wholesale Goods"
        }
    ],
    "sg:phone":"+1 937 746 4069",
    "sg:postcode":"45005",
    "sg:province":"OH",
    "sg:tags":[
        "mfg",
        "printing",
        "trade"
    ],
    "wof:name":"Ideal Roller",
    "wof:placetype":"venue"
},
  "geometry": {"coordinates":[-84.300718,39.535435],"type":"Point"}
}