{
  "type": "Feature",
  "properties": {
    "addr:full": "150 Court St Marion OH 43302",
    "addr:housenumber": "150",
    "addr:postcode": "43302",
    "addr:street": "Court St",
    "iso:country": "US",
    "sg:address": "150 Court St",
    "sg:city": "Marion",
    "sg:classifiers": [
      {
        "category": "Manufacturing",
        "subcategory": "Printing",
        "type": "Manufacturing \u0026 Wholesale Goods"
      }
    ],
    "sg:phone": "+1 740 387 0400",
    "sg:postcode": "43302",
    "sg:province": "OH",
    "sg:tags": [
      "newspaper"
    ],
    "sg:website": "www.marionstar.com",
    "wof:name": "Marion Star",
    "wof:placetype": "venue"
  },
  "geometry": {"coordinates":[-83.128134,40.58926],"type":"Point"}
}
