{
  "type": "Feature",
  "properties": {
    "iso:country":"US",
    "sg:address":"1640 S Co Rd 25A",
    "sg:city":"Troy",
    "sg:classifiers":[
        {
            "category":"Home & Garden",
            "subcategory":"Building Materials",
            "type":"Retail Goods"
        }
    ],
    "sg:phone":"+1 937 773 7787",
    "sg:postcode":"45373",
    "sg:province":"OH",
    "sg:tags":[
        "repair",
        "door",
        "garage",
        "overhead",
        "storm",
        "entry"
    ],
    "wof:name":"Overhead Door Co Troy/Pickler",
    "wof:placetype":"venue"
},
  "geometry": {"coordinates":[-84.200833,40.014255],"type":"Point"}
}