{
  "type": "Feature",
  "properties": {
    "addr:full": "1640 S Co Rd 25A Troy OH 45373",
    "addr:housenumber": "1640;25a",
    "addr:postcode": "45373",
    "addr:street": "S Co Rd",
    "iso:country": "US",
    "sg:address": "1640 S Co Rd 25A",
    "sg:city": "Troy",
    "sg:classifiers": [
      {
        "category": "Home \u0026 Garden",
        "subcategory": "Building Materials",
        "type": "Retail Goods"
      }
    ],
    "sg:phone": "+1 937 773 7787",
    "sg:postcode": "45373",
    "sg:province": "OH",
    "sg:tags": [
      "repair",
      "door",
      "garage",
      "overhead",
      "storm",
      "entry"
    ],
    "wof:name": "Overhead Door Co Troy/Pickler",
    "wof:placetype": "venue"
  },
  "geometry": {"coordinates":[-84.200833,40.014255],"type":"Point"}
}
