{
  "type": "Feature",
  "properties": {
    "iso:country":"US",
    "sg:address":"5555 Frantz Rd",
    "sg:city":"Dublin",
    "sg:classifiers":[
        {
            "category":"Organizations",
            "subcategory":"Professional Association",
            "type":"Services"
        }
    ],
    "sg:phone":"+1 614 889 9565",
    "sg:postcode":"43017",
    "sg:province":"OH",
    "sg:website":"www.cancer.org",
    "wof:name":"American Cancer Society Oh Div",
    "wof:placetype":"venue"
},
  "geometry": {"coordinates":[-83.12304399999999,40.079291],"type":"Point"}
}