{
  "type": "Feature",
  "properties": {
    "addr:full": "5589 State Rte 15 Bryan OH 43506",
    "addr:housenumber": "5589",
    "addr:postcode": "43506",
    "addr:street": "State Rte 15",
    "iso:country": "US",
    "sg:address": "5589 State Rte 15",
    "sg:city": "Bryan",
    "sg:classifiers": [
      {
        "category": "Professional",
        "subcategory": "Business Services",
        "type": "Services"
      }
    ],
    "sg:phone": "+1 419 636 1191",
    "sg:postcode": "43506",
    "sg:province": "OH",
    "sg:tags": [
      "interior",
      "consultant",
      "design",
      "decorator"
    ],
    "wof:name": "J Kay Design",
    "wof:placetype": "venue"
  },
  "geometry": {"coordinates":[-84.553811,41.493986],"type":"Point"}
}
