{
  "type": "Feature",
  "properties": {
    "addr:full": "370 E 161st St Cleveland OH 44110",
    "addr:housenumber": "370",
    "addr:postcode": "44110",
    "addr:street": "E 161St St",
    "iso:country": "US",
    "sg:address": "370 E 161st St",
    "sg:city": "Cleveland",
    "sg:classifiers": [
      {
        "category": "Shopping",
        "subcategory": "Hobbies, Toys, \u0026 Games",
        "type": "Retail Goods"
      }
    ],
    "sg:phone": "+1 216 481 9981",
    "sg:postcode": "44110",
    "sg:province": "OH",
    "sg:tags": [
      "doll"
    ],
    "wof:name": "Collectible Dolls",
    "wof:placetype": "venue"
  },
  "geometry": {"coordinates":[-81.568441,41.572818],"type":"Point"}
}
