{
  "type": "Feature",
  "properties": {
    "iso:country":"US",
    "sg:address":"370 E 161st St",
    "sg:city":"Cleveland",
    "sg:classifiers":[
        {
            "category":"Shopping",
            "subcategory":"Hobbies, Toys, & Games",
            "type":"Retail Goods"
        }
    ],
    "sg:phone":"+1 216 481 9981",
    "sg:postcode":"44110",
    "sg:province":"OH",
    "sg:tags":[
        "doll"
    ],
    "wof:name":"Collectible Dolls",
    "wof:placetype":"venue"
},
  "geometry": {"coordinates":[-81.56844100000001,41.572818],"type":"Point"}
}