{
  "type": "Feature",
  "properties": {
    "addr:full": "115 N 6th St Hamilton OH 45011",
    "addr:housenumber": "115",
    "addr:postcode": "45011",
    "addr:street": "N 6Th St",
    "iso:country": "US",
    "sg:address": "115 N 6th St",
    "sg:city": "Hamilton",
    "sg:classifiers": [
      {
        "category": "Organizations",
        "subcategory": "Religious Organization",
        "type": "Services"
      }
    ],
    "sg:phone": "+1 513 896 6755",
    "sg:postcode": "45011",
    "sg:province": "OH",
    "sg:tags": [
      "church"
    ],
    "sg:website": "www.episcopalian.org/trinityhamilton",
    "wof:name": "Trinity Episcopal Church",
    "wof:placetype": "venue"
  },
  "geometry": {"coordinates":[-84.55487,39.400246],"type":"Point"}
}
