{
  "type": "Feature",
  "properties": {
    "iso:country":"US",
    "sg:address":"352 Howell Ave",
    "sg:city":"Cincinnati",
    "sg:classifiers":[
        {
            "category":"Professional",
            "subcategory":"Business Services",
            "type":"Services"
        }
    ],
    "sg:phone":"+1 513 872 0880",
    "sg:postcode":"45220",
    "sg:province":"OH",
    "sg:tags":[
        "translator",
        "interpreter"
    ],
    "wof:name":"Renaissance Properties",
    "wof:placetype":"venue"
},
  "geometry": {"coordinates":[-84.523861,39.143028],"type":"Point"}
}