{
  "type": "Feature",
  "properties": {
    "addr:full": "513 Amoy East Rd Mansfield OH 44903",
    "addr:housenumber": "513",
    "addr:postcode": "44903",
    "addr:street": "Amoy East Rd",
    "iso:country": "US",
    "sg:address": "513 Amoy East Rd",
    "sg:city": "Mansfield",
    "sg:classifiers": [
      {
        "category": "Real Estate",
        "subcategory": "Surveying",
        "type": "Services"
      }
    ],
    "sg:phone": "+1 419 747 7155",
    "sg:postcode": "44903",
    "sg:province": "OH",
    "sg:tags": [
      "surveyor"
    ],
    "wof:name": "Weigler Land Surveying",
    "wof:placetype": "venue"
  },
  "geometry": {"coordinates":[-82.531644,40.828737],"type":"Point"}
}
