{
  "type": "Feature",
  "properties": {
    "iso:country":"US",
    "sg:address":"142 Great Oaks Trl",
    "sg:city":"Wadsworth",
    "sg:classifiers":[
        {
            "category":"Restaurant",
            "type":"Food & Drink"
        }
    ],
    "sg:menulink":"http://www.allmenus.com/oh/wadsworth/79160-pizza-hut/menu/",
    "sg:phone":"+1 330 336 5700",
    "sg:postcode":"44281",
    "sg:province":"OH",
    "sg:tags":[
        "american",
        "pizza"
    ],
    "wof:name":"Pizza Hut",
    "wof:placetype":"venue"
},
  "geometry": {"coordinates":[-81.73053899999999,41.048961],"type":"Point"}
}