{
  "type": "Feature",
  "properties": {
    "addr:full":"124 N Summit St Toledo OH 43604",
    "addr:housenumber":"124",
    "addr:postcode":"43604",
    "addr:street":"N Summit St",
    "iso:country":"US",
    "sg:address":"124 N Summit St",
    "sg:city":"Toledo",
    "sg:classifiers":[
        {
            "category":"Communications",
            "subcategory":"Radio Station",
            "type":"Services"
        }
    ],
    "sg:phone":"+1 419 240 1047",
    "sg:postcode":"43604",
    "sg:province":"OH",
    "sg:tags":[
        "broadcast"
    ],
    "wof:name":"FM 104 7 Request Line",
    "wof:placetype":"venue"
},
  "geometry": {"coordinates":[-83.535037,41.649226],"type":"Point"}
}