{
  "type": "Feature",
  "properties": {
    "addr:full":"65 N 2nd St Batavia OH 45103",
    "addr:housenumber":"65",
    "addr:postcode":"45103",
    "addr:street":"N 2Nd St",
    "iso:country":"US",
    "sg:address":"65 N 2nd St",
    "sg:city":"Batavia",
    "sg:classifiers":[
        {
            "category":"Professional",
            "subcategory":"Lawyer & Legal Services",
            "type":"Services"
        }
    ],
    "sg:phone":"+1 513 735 0800",
    "sg:postcode":"45103",
    "sg:province":"OH",
    "sg:tags":[
        "attorney",
        "law",
        "juvenile",
        "family"
    ],
    "sg:website":"http://www.susanmineer.com",
    "wof:name":"Mineer Susan Attorney At Law",
    "wof:placetype":"venue"
},
  "geometry": {"coordinates":[-84.17698900000001,39.077657],"type":"Point"}
}