{
  "type": "Feature",
  "properties": {
    "addr:full": "105 E High St Glenford OH 43739",
    "addr:housenumber": "105",
    "addr:postcode": "43739",
    "addr:street": "E High St",
    "iso:country": "US",
    "sg:address": "105 E High St",
    "sg:city": "Glenford",
    "sg:classifiers": [
      {
        "category": "Retail",
        "subcategory": "Auto Repair",
        "type": "Services"
      }
    ],
    "sg:phone": "+1 740 659 2303",
    "sg:postcode": "43739",
    "sg:province": "OH",
    "sg:tags": [
      "repairing",
      "automobile"
    ],
    "wof:name": "Jeff's Automotive",
    "wof:placetype": "venue"
  },
  "geometry": {"coordinates":[-82.314756,39.8873],"type":"Point"}
}
