{
  "type": "Feature",
  "properties": {
    "iso:country":"US",
    "sg:address":"4900 Jackman Rd",
    "sg:city":"Toledo",
    "sg:classifiers":[
        {
            "category":"Home & Garden",
            "subcategory":"Building Materials",
            "type":"Retail Goods"
        }
    ],
    "sg:phone":"+1 419 478 0550",
    "sg:postcode":"43613",
    "sg:province":"OH",
    "sg:tags":[
        "paint"
    ],
    "wof:name":"Sherwin-Williams Paints",
    "wof:placetype":"venue"
},
  "geometry": {"coordinates":[-83.58533,41.704765],"type":"Point"}
}