{
  "type": "Feature",
  "properties": {
    "iso:country":"US",
    "sg:address":"191 S High St",
    "sg:city":"Columbus",
    "sg:classifiers":[
        {
            "category":"Restaurant",
            "type":"Food & Drink"
        }
    ],
    "sg:phone":"+1 614 221 0302",
    "sg:postcode":"43215",
    "sg:province":"OH",
    "sg:tags":[
        "eating"
    ],
    "wof:name":"Psn Fed Liquors",
    "wof:placetype":"venue"
},
  "geometry": {"coordinates":[-83.000017,39.958753],"type":"Point"}
}