{
  "type": "Feature",
  "properties": {
    "iso:country":"US",
    "sg:address":"851 High St",
    "sg:city":"Hamilton",
    "sg:classifiers":[
        {
            "category":"Restaurant",
            "type":"Food & Drink"
        }
    ],
    "sg:phone":"+1 513 863 9993",
    "sg:postcode":"45011",
    "sg:province":"OH",
    "sg:tags":[
        "eating"
    ],
    "wof:name":"Shanghai Chinese Restaurant",
    "wof:placetype":"venue"
},
  "geometry": {"coordinates":[-84.552426,39.3969],"type":"Point"}
}