{
  "type": "Feature",
  "properties": {
    "iso:country":"US",
    "sg:address":"6051 Telegraph Rd",
    "sg:city":"Toledo",
    "sg:classifiers":[
        {
            "category":"Autos & Motor Vehicles",
            "subcategory":"Auto Supplies",
            "type":"Retail Goods"
        }
    ],
    "sg:phone":"+1 419 476 0796",
    "sg:postcode":"43612",
    "sg:province":"OH",
    "wof:name":"Maaco Auto Painting",
    "wof:placetype":"venue"
},
  "geometry": {"coordinates":[-83.547614,41.725161],"type":"Point"}
}