{
  "type": "Feature",
  "properties": {
    "addr:full": "2329 W Clifton Ave Cincinnati OH 45219",
    "addr:housenumber": "2329",
    "addr:postcode": "45219",
    "addr:street": "W Clifton Ave",
    "iso:country": "US",
    "sg:address": "2329 W Clifton Ave",
    "sg:city": "Cincinnati",
    "sg:classifiers": [
      {
        "category": "Bars \u0026 Pubs",
        "type": "Food \u0026 Drink"
      }
    ],
    "sg:phone": "+1 513 721 6148",
    "sg:postcode": "45219",
    "sg:province": "OH",
    "sg:tags": [
      "club",
      "drinking",
      "night"
    ],
    "sg:website": "www.murphys-pub.com",
    "wof:name": "Murphy's Pub",
    "wof:placetype": "venue"
  },
  "geometry": {"coordinates":[-84.519196,39.127824],"type":"Point"}
}
