{
  "type": "Feature",
  "properties": {
    "iso:country":"US",
    "sg:address":"2329 W Clifton Ave",
    "sg:city":"Cincinnati",
    "sg:classifiers":[
        {
            "category":"Bars & Pubs",
            "type":"Food & Drink"
        }
    ],
    "sg:phone":"+1 513 721 6148",
    "sg:postcode":"45219",
    "sg:province":"OH",
    "sg:tags":[
        "club",
        "drinking",
        "night"
    ],
    "sg:website":"www.murphys-pub.com",
    "wof:name":"Murphy's Pub",
    "wof:placetype":"venue"
},
  "geometry": {"coordinates":[-84.51919599999999,39.127824],"type":"Point"}
}