{
  "type": "Feature",
  "properties": {
    "addr:full":"2644 State Rte 60 Loudonville OH 44842",
    "addr:housenumber":"2644",
    "addr:postcode":"44842",
    "addr:street":"State Rte 60",
    "iso:country":"US",
    "sg:address":"2644 State Rte 60",
    "sg:city":"Loudonville",
    "sg:classifiers":[
        {
            "category":"Farming",
            "subcategory":"Farm",
            "type":"Manufacturing & Wholesale Goods"
        }
    ],
    "sg:phone":"+1 419 994 4486",
    "sg:postcode":"44842",
    "sg:province":"OH",
    "sg:tags":[
        "crop",
        "general"
    ],
    "wof:name":"James Smithhisler",
    "wof:placetype":"venue"
},
  "geometry": {"coordinates":[-82.237313,40.678696],"type":"Point"}
}