{
  "type": "Feature",
  "properties": {
    "iso:country":"US",
    "sg:address":"8700 Harvard Ave",
    "sg:city":"Cleveland",
    "sg:classifiers":[
        {
            "category":"Professional",
            "subcategory":"Business Services",
            "type":"Services"
        }
    ],
    "sg:phone":"+1 216 883 0800",
    "sg:postcode":"44105",
    "sg:province":"OH",
    "sg:tags":[
        "packaging"
    ],
    "wof:name":"Paragon Packaging Corp",
    "wof:placetype":"venue"
},
  "geometry": {"coordinates":[-81.62584699999999,41.448744],"type":"Point"}
}