{
  "type": "Feature",
  "properties": {
    "addr:full": "204 E 16th St Dover OH 44622",
    "addr:housenumber": "204",
    "addr:postcode": "44622",
    "addr:street": "E 16Th St",
    "iso:country": "US",
    "sg:address": "204 E 16th St",
    "sg:city": "Dover",
    "sg:classifiers": [
      {
        "category": "Personal",
        "type": "Services"
      }
    ],
    "sg:phone": "+1 330 364 2479",
    "sg:postcode": "44622",
    "sg:province": "OH",
    "sg:tags": [
      "electrologist"
    ],
    "wof:name": "Andrea White Electrolysis",
    "wof:placetype": "venue"
  },
  "geometry": {"coordinates":[-81.48471,40.536409],"type":"Point"}
}
