{
  "type": "Feature",
  "properties": {
    "iso:country":"US",
    "sg:address":"3708 Burbridge Rd",
    "sg:city":"Cleveland",
    "sg:classifiers":[
        {
            "category":"Building & Trades",
            "subcategory":"Construction",
            "type":"Services"
        }
    ],
    "sg:phone":"+1 216 381 0431",
    "sg:postcode":"44121",
    "sg:province":"OH",
    "sg:tags":[
        "house"
    ],
    "wof:name":"Nustart Construction Ent",
    "wof:placetype":"venue"
},
  "geometry": {"coordinates":[-81.54996199999999,41.539325],"type":"Point"}
}