{
  "type": "Feature",
  "properties": {
    "addr:full":"1271 Eastern Ave Gallipolis OH 45631",
    "addr:housenumber":"1271",
    "addr:postcode":"45631",
    "addr:street":"Eastern Ave",
    "iso:country":"US",
    "sg:address":"1271 Eastern Ave",
    "sg:city":"Gallipolis",
    "sg:classifiers":[
        {
            "category":"Education",
            "subcategory":"Dance Studio",
            "type":"Public Place"
        }
    ],
    "sg:phone":"+1 740 441 1988",
    "sg:postcode":"45631",
    "sg:province":"OH",
    "sg:tags":[
        "instruction",
        "dancing"
    ],
    "wof:name":"Art School",
    "wof:placetype":"venue"
},
  "geometry": {"coordinates":[-82.188671,38.8168],"type":"Point"}
}