{
  "type": "Feature",
  "properties": {
    "iso:country":"US",
    "sg:address":"7005 Krick Rd",
    "sg:city":"Cleveland",
    "sg:classifiers":[
        {
            "category":"Retail",
            "subcategory":"Repair Shop",
            "type":"Services"
        }
    ],
    "sg:phone":"+1 440 729 7122",
    "sg:postcode":"44146",
    "sg:province":"OH",
    "sg:tags":[
        "refinishing",
        "furniture"
    ],
    "wof:name":"Windsor House Furniture",
    "wof:placetype":"venue"
},
  "geometry": {"coordinates":[-81.530312,41.372878],"type":"Point"}
}