{
  "type": "Feature",
  "properties": {
    "addr:full":"125 S Cooper Ave Cincinnati OH 45215",
    "addr:housenumber":"125",
    "addr:postcode":"45215",
    "addr:street":"S Cooper Ave",
    "iso:country":"US",
    "sg:address":"125 S Cooper Ave",
    "sg:city":"Cincinnati",
    "sg:classifiers":[
        {
            "category":"Organizations",
            "subcategory":"Religious Organization",
            "type":"Services"
        }
    ],
    "sg:phone":"+1 513 821 9002",
    "sg:postcode":"45215",
    "sg:province":"OH",
    "wof:name":"Reading Presbytarian Church",
    "wof:placetype":"venue"
},
  "geometry": {"coordinates":[-84.45486699999999,39.22502],"type":"Point"}
}