{
  "type": "Feature",
  "properties": {
    "addr:full":"11 W New England Ave Worthington OH 43085",
    "addr:housenumber":"11",
    "addr:postcode":"43085",
    "addr:street":"W New England Ave",
    "iso:country":"US",
    "sg:address":"11 W New England Ave",
    "sg:city":"Worthington",
    "sg:classifiers":[
        {
            "category":"Personal",
            "subcategory":"Beauty Salon",
            "type":"Services"
        }
    ],
    "sg:phone":"+1 614 880 9225",
    "sg:postcode":"43085",
    "sg:province":"OH",
    "wof:name":"Wacked Hair Salon",
    "wof:placetype":"venue"
},
  "geometry": {"coordinates":[-83.020043,40.086776],"type":"Point"}
}