{
  "type": "Feature",
  "properties": {
    "addr:full": "4394 Eastgate Square Dr Cincinnati OH 45245",
    "addr:housenumber": "4394",
    "addr:postcode": "45245",
    "addr:street": "Eastgate Square Dr",
    "iso:country": "US",
    "sg:address": "4394 Eastgate Square Dr",
    "sg:city": "Cincinnati",
    "sg:classifiers": [
      {
        "category": "Personal",
        "subcategory": "Beauty Salon",
        "type": "Services"
      }
    ],
    "sg:phone": "+1 513 753 9530",
    "sg:postcode": "45245",
    "sg:province": "OH",
    "wof:name": "Fiesta Hair \u0026 Tanning",
    "wof:placetype": "venue"
  },
  "geometry": {"coordinates":[-84.268761,39.095251],"type":"Point"}
}
