{
  "type": "Feature",
  "properties": {
    "addr:full": "9439 Broadview Rd Broadview Heights OH 44147",
    "addr:housenumber": "9439",
    "addr:postcode": "44147",
    "addr:street": "Broadview Rd",
    "iso:country": "US",
    "sg:address": "9439 Broadview Rd",
    "sg:city": "Broadview Heights",
    "sg:classifiers": [
      {
        "category": "Wholesale",
        "subcategory": "Painting Supplies",
        "type": "Manufacturing \u0026 Wholesale Goods"
      }
    ],
    "sg:phone": "+1 440 838 1082",
    "sg:postcode": "44147",
    "sg:province": "OH",
    "wof:name": "Ronjo Enterprises Inc",
    "wof:placetype": "venue"
  },
  "geometry": {"coordinates":[-81.684605,41.31093],"type":"Point"}
}
