{
  "type": "Feature",
  "properties": {
    "iso:country":"US",
    "sg:address":"225 W Washington Row",
    "sg:city":"Sandusky",
    "sg:classifiers":[
        {
            "category":"Organizations",
            "subcategory":"Professional Association",
            "type":"Services"
        }
    ],
    "sg:phone":"+1 419 625 6421",
    "sg:postcode":"44870",
    "sg:province":"OH",
    "sg:tags":[
        "chambers",
        "commerce"
    ],
    "sg:website":"www.eriecountyohiocofc.com",
    "wof:name":"Erie County Chamber-Commerce",
    "wof:placetype":"venue"
},
  "geometry": {"coordinates":[-82.71204299999999,41.454992],"type":"Point"}
}