{
  "type": "Feature",
  "properties": {
    "iso:country":"US",
    "sg:address":"4555 Groves Rd",
    "sg:city":"Columbus",
    "sg:classifiers":[
        {
            "category":"Building & Trades",
            "subcategory":"Construction",
            "type":"Services"
        }
    ],
    "sg:phone":"+1 614 868 0900",
    "sg:postcode":"43232",
    "sg:province":"OH",
    "sg:tags":[
        "home",
        "improvement",
        "general",
        "contractor"
    ],
    "wof:name":"ION Inc",
    "wof:placetype":"venue"
},
  "geometry": {"coordinates":[-82.874067,39.929839],"type":"Point"}
}