{
  "type": "Feature",
  "properties": {
    "addr:full": "861 Washington St Bergholz OH 43908",
    "addr:housenumber": "861",
    "addr:postcode": "43908",
    "addr:street": "Washington St",
    "iso:country": "US",
    "sg:address": "861 Washington St",
    "sg:city": "Bergholz",
    "sg:classifiers": [
      {
        "category": "Food \u0026 Beverages",
        "subcategory": "Groceries \u0026 Convenience Stores",
        "type": "Retail Goods"
      }
    ],
    "sg:phone": "+1 740 768 1018",
    "sg:postcode": "43908",
    "sg:province": "OH",
    "wof:name": "Supermart",
    "wof:placetype": "venue"
  },
  "geometry": {"coordinates":[-80.88682,40.518998],"type":"Point"}
}
