{
  "type": "Feature",
  "properties": {
    "iso:country":"US",
    "sg:address":"861 Washington St",
    "sg:city":"Bergholz",
    "sg:classifiers":[
        {
            "category":"Food & Beverages",
            "subcategory":"Groceries & Convenience Stores",
            "type":"Retail Goods"
        }
    ],
    "sg:phone":"+1 740 768 1018",
    "sg:postcode":"43908",
    "sg:province":"OH",
    "wof:name":"Supermart",
    "wof:placetype":"venue"
},
  "geometry": {"coordinates":[-80.88682,40.518998],"type":"Point"}
}