{
  "type": "Feature",
  "properties": {
    "iso:country":"US",
    "sg:address":"2565 E Main St",
    "sg:city":"Springfield",
    "sg:classifiers":[
        {
            "category":"Shopping",
            "subcategory":"Pharmacy",
            "type":"Retail Goods"
        }
    ],
    "sg:phone":"+1 937 323 6423",
    "sg:postcode":"45503",
    "sg:province":"OH",
    "sg:website":"www.cvs.com",
    "wof:name":"CVS Pharmacy",
    "wof:placetype":"venue"
},
  "geometry": {"coordinates":[-83.76996800000001,39.923277],"type":"Point"}
}