{
  "type": "Feature",
  "properties": {
    "iso:country":"US",
    "sg:address":"9849 Knowlton Rd",
    "sg:city":"Garrettsville",
    "sg:classifiers":[
        {
            "category":"Wholesale",
            "subcategory":"Scrap",
            "type":"Manufacturing & Wholesale Goods"
        }
    ],
    "sg:phone":"+1 330 527 5835",
    "sg:postcode":"44231",
    "sg:province":"OH",
    "sg:tags":[
        "material"
    ],
    "wof:name":"P & H Auto Wrecking",
    "wof:placetype":"venue"
},
  "geometry": {"coordinates":[-81.03865399999999,41.301628],"type":"Point"}
}