{
  "type": "Feature",
  "properties": {
    "addr:full": "9849 Knowlton Rd Garrettsville OH 44231",
    "addr:housenumber": "9849",
    "addr:postcode": "44231",
    "addr:street": "Knowlton Rd",
    "iso:country": "US",
    "sg:address": "9849 Knowlton Rd",
    "sg:city": "Garrettsville",
    "sg:classifiers": [
      {
        "category": "Wholesale",
        "subcategory": "Scrap",
        "type": "Manufacturing \u0026 Wholesale Goods"
      }
    ],
    "sg:phone": "+1 330 527 5835",
    "sg:postcode": "44231",
    "sg:province": "OH",
    "sg:tags": [
      "material"
    ],
    "wof:name": "P \u0026 H Auto Wrecking",
    "wof:placetype": "venue"
  },
  "geometry": {"coordinates":[-81.038654,41.301628],"type":"Point"}
}
