{
  "type": "Feature",
  "properties": {
    "addr:full": "4966 Darrow Rd Cuyahoga Falls OH 44224",
    "addr:housenumber": "4966",
    "addr:postcode": "44224",
    "addr:street": "Darrow Rd",
    "iso:country": "US",
    "sg:address": "4966 Darrow Rd",
    "sg:city": "Cuyahoga Falls",
    "sg:classifiers": [
      {
        "category": "Real Estate",
        "subcategory": "Real Estate Agent",
        "type": "Services"
      },
      {
        "category": "Real Estate",
        "subcategory": "Real Estate Operator",
        "type": "Services"
      }
    ],
    "sg:phone": "+1 330 655 1533",
    "sg:postcode": "44224",
    "sg:province": "OH",
    "sg:tags": [
      "building",
      "management",
      "apartment"
    ],
    "wof:name": "Crossroad Management Co",
    "wof:placetype": "venue"
  },
  "geometry": {"coordinates":[-81.440531,41.197376],"type":"Point"}
}
