{
  "type": "Feature",
  "properties": {
    "addr:full":"9965 Meldon Dr Streetsboro OH 44241",
    "addr:housenumber":"9965",
    "addr:postcode":"44241",
    "addr:street":"Meldon Dr",
    "iso:country":"US",
    "sg:address":"9965 Meldon Dr",
    "sg:city":"Streetsboro",
    "sg:classifiers":[
        {
            "category":"Building & Trades",
            "subcategory":"Construction",
            "type":"Services"
        }
    ],
    "sg:phone":"+1 330 626 2777",
    "sg:postcode":"44241",
    "sg:province":"OH",
    "sg:tags":[
        "residential",
        "real estate"
    ],
    "wof:name":"Woodview Phase III",
    "wof:placetype":"venue"
},
  "geometry": {"coordinates":[-81.35142500000001,41.259924],"type":"Point"}
}