{
  "type": "Feature",
  "properties": {
    "addr:full":"791 Pennwood Dr Tallmadge OH 44278",
    "addr:housenumber":"791",
    "addr:postcode":"44278",
    "addr:street":"Pennwood Dr",
    "iso:country":"US",
    "sg:address":"791 Pennwood Dr",
    "sg:city":"Tallmadge",
    "sg:classifiers":[
        {
            "category":"Professional",
            "subcategory":"Accounting & Tax Preparation",
            "type":"Services"
        }
    ],
    "sg:phone":"+1 330 633 7273",
    "sg:postcode":"44278",
    "sg:province":"OH",
    "sg:tags":[
        "billing"
    ],
    "wof:name":"K C Medical Billing LLC",
    "wof:placetype":"venue"
},
  "geometry": {"coordinates":[-81.411057,41.096691],"type":"Point"}
}