{
  "type": "Feature",
  "properties": {
    "iso:country":"US",
    "sg:address":"2819 Sodom Hutchings Rd",
    "sg:city":"Fowler",
    "sg:classifiers":[
        {
            "category":"Real Estate",
            "subcategory":"Real Estate Operator",
            "type":"Services"
        }
    ],
    "sg:phone":"+1 330 637 8641",
    "sg:postcode":"44418",
    "sg:province":"OH",
    "sg:tags":[
        "mobile",
        "home",
        "site",
        "community"
    ],
    "wof:name":"Fowler Mobile Homes Park",
    "wof:placetype":"venue"
},
  "geometry": {"coordinates":[-80.636616,41.294883],"type":"Point"}
}