{
  "type": "Feature",
  "properties": {
    "addr:full":"12443 Bates Rd Irwin OH 43029",
    "addr:housenumber":"12443",
    "addr:postcode":"43029",
    "addr:street":"Bates Rd",
    "iso:country":"US",
    "sg:address":"12443 Bates Rd",
    "sg:city":"Irwin",
    "sg:phone":"+1 740 857 1721",
    "sg:postcode":"43029",
    "sg:province":"OH",
    "sg:tags":[
        "farm",
        "corn"
    ],
    "wof:name":"Robert Strausbaugh",
    "wof:placetype":"venue"
},
  "geometry": {"coordinates":[-83.469549,40.116116],"type":"Point"}
}