{
  "type": "Feature",
  "properties": {
    "addr:full":"641 Rust Ln Cincinnati OH 45244",
    "addr:housenumber":"641",
    "addr:postcode":"45244",
    "addr:street":"Rust Ln",
    "iso:country":"US",
    "sg:address":"641 Rust Ln",
    "sg:city":"Cincinnati",
    "sg:classifiers":[
        {
            "category":"Building & Trades",
            "subcategory":"Electrical",
            "type":"Services"
        }
    ],
    "sg:phone":"+1 513 528 0378",
    "sg:postcode":"45244",
    "sg:province":"OH",
    "sg:tags":[
        "electrical",
        "contractor"
    ],
    "wof:name":"Shields Electric Company",
    "wof:placetype":"venue"
},
  "geometry": {"coordinates":[-84.292035,39.103367],"type":"Point"}
}