{
  "type": "Feature",
  "properties": {
    "addr:full":"100 S 17th St Sebring OH 44672",
    "addr:housenumber":"100",
    "addr:postcode":"44672",
    "addr:street":"S 17Th St",
    "iso:country":"US",
    "sg:address":"100 S 17th St",
    "sg:city":"Sebring",
    "sg:classifiers":[
        {
            "category":"Manufacturing",
            "subcategory":"Tools & Machinery",
            "type":"Manufacturing & Wholesale Goods"
        }
    ],
    "sg:phone":"+1 330 938 6141",
    "sg:postcode":"44672",
    "sg:province":"OH",
    "sg:tags":[
        "mold",
        "special"
    ],
    "sg:website":"www.uniteddiemfg.com",
    "wof:name":"United Die & Mfg Co",
    "wof:placetype":"venue"
},
  "geometry": {"coordinates":[-81.023032,40.919582],"type":"Point"}
}