{
  "type": "Feature",
  "properties": {
    "iso:country":"US",
    "sg:address":"665 Loveland Madeira Rd",
    "sg:city":"Loveland",
    "sg:classifiers":[
        {
            "category":"Restaurant",
            "type":"Food & Drink"
        }
    ],
    "sg:phone":"+1 513 683 2599",
    "sg:postcode":"45140",
    "sg:province":"OH",
    "wof:name":"Little Chan Hi",
    "wof:placetype":"venue"
},
  "geometry": {"coordinates":[-84.26813,39.264876],"type":"Point"}
}