{
  "type": "Feature",
  "properties": {
    "addr:full":"292 Citation Rd SW Pataskala OH 43062",
    "addr:housenumber":"292",
    "addr:postcode":"43062",
    "addr:street":"Citation Rd Sw",
    "iso:country":"US",
    "sg:address":"292 Citation Rd SW",
    "sg:city":"Pataskala",
    "sg:classifiers":[
        {
            "category":"Building & Trades",
            "subcategory":"Plumbing",
            "type":"Services"
        }
    ],
    "sg:phone":"+1 740 927 0132",
    "sg:postcode":"43062",
    "sg:province":"OH",
    "sg:tags":[
        "conditioning",
        "air",
        "system",
        "contractor"
    ],
    "wof:name":"Reynoldsburg Heating & AC",
    "wof:placetype":"venue"
},
  "geometry": {"coordinates":[-82.64851,40.020434],"type":"Point"}
}