{
  "type": "Feature",
  "properties": {
    "addr:full":"3174 State Rte 82 Mantua OH 44255",
    "addr:housenumber":"3174",
    "addr:postcode":"44255",
    "addr:street":"State Rte 82",
    "iso:country":"US",
    "sg:address":"3174 State Rte 82",
    "sg:city":"Mantua",
    "sg:classifiers":[
        {
            "category":"Communications",
            "type":"Services"
        }
    ],
    "sg:phone":"+1 330 562 0851",
    "sg:postcode":"44255",
    "sg:province":"OH",
    "sg:tags":[
        "carrier"
    ],
    "wof:name":"TCP Communications Inc",
    "wof:placetype":"venue"
},
  "geometry": {"coordinates":[-81.273786,41.308979],"type":"Point"}
}