{
  "type": "Feature",
  "properties": {
    "iso:country":"US",
    "sg:address":"1506 Ferman Ave",
    "sg:city":"Cleveland",
    "sg:classifiers":[
        {
            "category":"Manufacturing",
            "subcategory":"Printing",
            "type":"Manufacturing & Wholesale Goods"
        }
    ],
    "sg:phone":"+1 216 398 3716",
    "sg:postcode":"44109",
    "sg:province":"OH",
    "wof:name":"L M's Mailing House",
    "wof:placetype":"venue"
},
  "geometry": {"coordinates":[-81.691154,41.435993],"type":"Point"}
}