{
  "type": "Feature",
  "properties": {
    "addr:full":"3627 W Fork Rd Cincinnati OH 45247",
    "addr:housenumber":"3627",
    "addr:postcode":"45247",
    "addr:street":"W Fork Rd",
    "iso:country":"US",
    "sg:address":"3627 W Fork Rd",
    "sg:city":"Cincinnati",
    "sg:classifiers":[
        {
            "category":"Real Estate",
            "subcategory":"Architect",
            "type":"Services"
        }
    ],
    "sg:phone":"+1 513 661 2565",
    "sg:postcode":"45247",
    "sg:province":"OH",
    "sg:tags":[
        "architectural"
    ],
    "sg:website":"www.pda-ae.com",
    "wof:name":"Professional Design Associates",
    "wof:placetype":"venue"
},
  "geometry": {"coordinates":[-84.60283200000001,39.188335],"type":"Point"}
}