{
  "type": "Feature",
  "properties": {
    "addr:full": "3436 Beechwood Ave Cleveland OH 44118",
    "addr:housenumber": "3436",
    "addr:postcode": "44118",
    "addr:street": "Beechwood Ave",
    "iso:country": "US",
    "sg:address": "3436 Beechwood Ave",
    "sg:city": "Cleveland",
    "sg:classifiers": [
      {
        "category": "Retail",
        "subcategory": "Repair Shop",
        "type": "Services"
      }
    ],
    "sg:phone": "+1 216 321 2590",
    "sg:postcode": "44118",
    "sg:province": "OH",
    "sg:tags": [
      "television",
      "radio"
    ],
    "wof:name": "T V Shop On Wheels",
    "wof:placetype": "venue"
  },
  "geometry": {"coordinates":[-81.55748,41.512359],"type":"Point"}
}
