{
  "type": "Feature",
  "properties": {
    "iso:country":"US",
    "sg:address":"673 N High St",
    "sg:city":"Columbus",
    "sg:classifiers":[
        {
            "category":"Real Estate",
            "subcategory":"Architect",
            "type":"Services"
        }
    ],
    "sg:phone":"+1 614 436 0555",
    "sg:postcode":"43085",
    "sg:province":"OH",
    "sg:tags":[
        "architectural"
    ],
    "wof:name":"Baker & Associates Architects",
    "wof:placetype":"venue"
},
  "geometry": {"coordinates":[-83.018236,40.087354],"type":"Point"}
}