{
  "type": "Feature",
  "properties": {
    "addr:full": "764 Hebron Rd Heath OH 43056",
    "addr:housenumber": "764",
    "addr:postcode": "43056",
    "addr:street": "Hebron Rd",
    "iso:country": "US",
    "sg:address": "764 Hebron Rd",
    "sg:city": "Heath",
    "sg:classifiers": [
      {
        "category": "Professional",
        "subcategory": "Management \u0026 Consulting",
        "type": "Services"
      },
      {
        "category": "Restaurant",
        "type": "Food \u0026 Drink"
      }
    ],
    "sg:phone": "+1 740 522 3085",
    "sg:postcode": "43056",
    "sg:province": "OH",
    "wof:name": "Frisch's Big Boy Restaurant",
    "wof:placetype": "venue"
  },
  "geometry": {"coordinates":[-82.437871,40.031373],"type":"Point"}
}
