{
  "type": "Feature",
  "properties": {
    "addr:full": "11764 Percivale Ct Cincinnati OH 45241",
    "addr:housenumber": "11764",
    "addr:postcode": "45241",
    "addr:street": "Percivale Ct",
    "iso:country": "US",
    "sg:address": "11764 Percivale Ct",
    "sg:city": "Cincinnati",
    "sg:classifiers": [
      {
        "category": "Manufacturing",
        "subcategory": "Petroleum Products",
        "type": "Manufacturing \u0026 Wholesale Goods"
      }
    ],
    "sg:phone": "+1 513 247 9787",
    "sg:postcode": "45241",
    "sg:province": "OH",
    "sg:tags": [
      "refining"
    ],
    "wof:name": "Penreco",
    "wof:placetype": "venue"
  },
  "geometry": {"coordinates":[-84.381426,39.289442],"type":"Point"}
}
