{
  "type": "Feature",
  "properties": {
    "iso:country":"US",
    "sg:address":"1776 Mentor Ave",
    "sg:city":"Cincinnati",
    "sg:classifiers":[
        {
            "category":"Professional",
            "subcategory":"Management & Consulting",
            "type":"Services"
        },
        {
            "category":"Professional",
            "subcategory":"Computer Services",
            "type":"Services"
        }
    ],
    "sg:phone":"+1 513 396 6300",
    "sg:postcode":"45212",
    "sg:province":"OH",
    "sg:tags":[
        "marketing",
        "program",
        "datum"
    ],
    "wof:name":"Lagnia PPE Marketing Inc",
    "wof:placetype":"venue"
},
  "geometry": {"coordinates":[-84.46717599999999,39.151932],"type":"Point"}
}