{
  "type": "Feature",
  "properties": {
    "addr:full": "2344 Prospect Ave E Cleveland OH 44115",
    "addr:housenumber": "2344",
    "addr:postcode": "44115",
    "addr:street": "Prospect Ave E",
    "iso:country": "US",
    "sg:address": "2344 Prospect Ave E",
    "sg:city": "Cleveland",
    "sg:classifiers": [
      {
        "category": "Manufacturing",
        "subcategory": "Metals",
        "type": "Manufacturing \u0026 Wholesale Goods"
      }
    ],
    "sg:phone": "+1 216 241 7285",
    "sg:postcode": "44115",
    "sg:province": "OH",
    "sg:tags": [
      "nonferrous"
    ],
    "wof:name": "Todays Home Office",
    "wof:placetype": "venue"
  },
  "geometry": {"coordinates":[-81.670418,41.500743],"type":"Point"}
}
