{
  "type": "Feature",
  "properties": {
    "addr:full":"20 Bronson Ave Toledo OH 43608",
    "addr:housenumber":"20",
    "addr:postcode":"43608",
    "addr:street":"Bronson Ave",
    "iso:country":"US",
    "sg:address":"20 Bronson Ave",
    "sg:city":"Toledo",
    "sg:classifiers":[
        {
            "category":"Building & Trades",
            "subcategory":"Construction",
            "type":"Services"
        }
    ],
    "sg:phone":"+1 419 346 7521",
    "sg:postcode":"43608",
    "sg:province":"OH",
    "sg:tags":[
        "handyman"
    ],
    "wof:name":"A Plus Building Maintenance",
    "wof:placetype":"venue"
},
  "geometry": {"coordinates":[-83.54378199999999,41.677493],"type":"Point"}
}