{
  "type": "Feature",
  "properties": {
    "addr:full": "33 Lutz Dr Bucyrus OH 44820",
    "addr:housenumber": "33",
    "addr:postcode": "44820",
    "addr:street": "Lutz Dr",
    "iso:country": "US",
    "sg:address": "33 Lutz Dr",
    "sg:city": "Bucyrus",
    "sg:classifiers": [
      {
        "category": "Real Estate",
        "subcategory": "Real Estate Operator",
        "type": "Services"
      }
    ],
    "sg:phone": "+1 419 562 5512",
    "sg:postcode": "44820",
    "sg:province": "OH",
    "sg:tags": [
      "apartment"
    ],
    "wof:name": "Indian Valley",
    "wof:placetype": "venue"
  },
  "geometry": {"coordinates":[-82.967085,40.814378],"type":"Point"}
}
