{
  "type": "Feature",
  "properties": {
    "iso:country":"US",
    "sg:address":"23901 Rogers Rd",
    "sg:city":"Raymond",
    "sg:classifiers":[
        {
            "category":"Professional",
            "subcategory":"Business Services",
            "type":"Services"
        }
    ],
    "sg:phone":"+1 937 644 8589",
    "sg:postcode":"43067",
    "sg:province":"OH",
    "wof:name":"Ramp Master of Ohio Inc",
    "wof:placetype":"venue"
},
  "geometry": {"coordinates":[-83.541853,40.340452],"type":"Point"}
}