{
  "type": "Feature",
  "properties": {
    "addr:full":"3731 Pearl Rd Cleveland OH 44109",
    "addr:housenumber":"3731",
    "addr:postcode":"44109",
    "addr:street":"Pearl Rd",
    "iso:country":"US",
    "sg:address":"3731 Pearl Rd",
    "sg:city":"Cleveland",
    "sg:classifiers":[
        {
            "category":"Health Services",
            "subcategory":"Podiatrist",
            "type":"Services"
        }
    ],
    "sg:phone":"+1 216 459 8616",
    "sg:postcode":"44109",
    "sg:province":"OH",
    "wof:name":"Donahue Foot & Ankle Ctr Inc",
    "wof:placetype":"venue"
},
  "geometry": {"coordinates":[-81.701295,41.453737],"type":"Point"}
}