{
  "type": "Feature",
  "properties": {
    "iso:country":"US",
    "sg:address":"11575 Brookpark Rd",
    "sg:city":"Cleveland",
    "sg:classifiers":[
        {
            "category":"Restaurant",
            "type":"Food & Drink"
        }
    ],
    "sg:menulink":"http://www.allmenus.com/oh/parma/38145-jordans-family-restaurant/menu/",
    "sg:phone":"+1 216 676 8588",
    "sg:postcode":"44130",
    "sg:province":"OH",
    "sg:tags":[
        "american"
    ],
    "wof:name":"Jordan's Family Restaurant",
    "wof:placetype":"venue"
},
  "geometry": {"coordinates":[-81.767188,41.417765],"type":"Point"}
}