{
  "type": "Feature",
  "properties": {
    "addr:full":"1505 Euclid Ave Cleveland OH 44115",
    "addr:housenumber":"1505",
    "addr:postcode":"44115",
    "addr:street":"Euclid Ave",
    "iso:country":"US",
    "sg:address":"1505 Euclid Ave",
    "sg:city":"Cleveland",
    "sg:classifiers":[
        {
            "category":"Restaurant",
            "type":"Food & Drink"
        }
    ],
    "sg:phone":"+1 216 583 0411",
    "sg:postcode":"44115",
    "sg:province":"OH",
    "sg:tags":[
        "shop",
        "coffee"
    ],
    "wof:name":"Hookah Lounge & Cafe",
    "wof:placetype":"venue"
},
  "geometry": {"coordinates":[-81.681828,41.500885],"type":"Point"}
}