{
  "type": "Feature",
  "properties": {
    "addr:full":"17001 Holland Rd Cleveland OH 44142",
    "addr:housenumber":"17001",
    "addr:postcode":"44142",
    "addr:street":"Holland Rd",
    "iso:country":"US",
    "sg:address":"17001 Holland Rd",
    "sg:city":"Cleveland",
    "sg:classifiers":[
        {
            "category":"Education",
            "subcategory":"School",
            "type":"Public Place"
        }
    ],
    "sg:phone":"+1 216 433 1133",
    "sg:postcode":"44142",
    "sg:province":"OH",
    "sg:website":"www.berea.k12.oh.us",
    "wof:name":"Ford Middle School",
    "wof:placetype":"venue"
},
  "geometry": {"coordinates":[-81.81586299999999,41.395624],"type":"Point"}
}