{
  "type": "Feature",
  "properties": {
    "iso:country":"US",
    "sg:address":"3801 Wright Dr",
    "sg:city":"Vandalia",
    "sg:classifiers":[
        {
            "category":"Retail",
            "subcategory":"Repair Shop",
            "type":"Services"
        }
    ],
    "sg:phone":"+1 937 454 1238",
    "sg:postcode":"45377",
    "sg:province":"OH",
    "sg:tags":[
        "equipment",
        "telephone",
        "system"
    ],
    "wof:name":"Denro Inc",
    "wof:placetype":"venue"
},
  "geometry": {"coordinates":[-84.205128,39.904502],"type":"Point"}
}