{
  "type": "Feature",
  "properties": {
    "addr:full": "972 E 19th Ave Columbus OH 43211",
    "addr:housenumber": "972",
    "addr:postcode": "43211",
    "addr:street": "E 19Th Ave",
    "iso:country": "US",
    "sg:address": "972 E 19th Ave",
    "sg:city": "Columbus",
    "sg:classifiers": [
      {
        "category": "Professional",
        "subcategory": "Art Services",
        "type": "Services"
      }
    ],
    "sg:phone": "+1 614 483 0869",
    "sg:postcode": "43211",
    "sg:province": "OH",
    "sg:tags": [
      "graphic",
      "designer"
    ],
    "sg:website": "http://www.columbusadministrativeservices.com",
    "wof:name": "Columbus Administrative Services",
    "wof:placetype": "venue"
  },
  "geometry": {"coordinates":[-82.981897,40.002692],"type":"Point"}
}
