{
  "type": "Feature",
  "properties": {
    "addr:full": "22709 Wintergreen Rd Grand Rapids OH 43522",
    "addr:housenumber": "22709",
    "addr:postcode": "43522",
    "addr:street": "Wintergreen Rd",
    "iso:country": "US",
    "sg:address": "22709 Wintergreen Rd",
    "sg:city": "Grand Rapids",
    "sg:phone": "+1 419 832 6254",
    "sg:postcode": "43522",
    "sg:province": "OH",
    "sg:tags": [
      "farm",
      "corn",
      "wheat",
      "soybean"
    ],
    "wof:name": "Phillip Dewese",
    "wof:placetype": "venue"
  },
  "geometry": {"coordinates":[-83.838852,41.393638],"type":"Point"}
}
