{
  "type": "Feature",
  "properties": {
    "addr:full": "423 S Lundy Ave Salem OH 44460",
    "addr:housenumber": "423",
    "addr:postcode": "44460",
    "addr:street": "S Lundy Ave",
    "iso:country": "US",
    "sg:address": "423 S Lundy Ave",
    "sg:city": "Salem",
    "sg:classifiers": [
      {
        "category": "Shopping",
        "subcategory": "Gifts \u0026 Souvenirs",
        "type": "Retail Goods"
      }
    ],
    "sg:phone": "+1 330 332 2969",
    "sg:postcode": "44460",
    "sg:province": "OH",
    "sg:tags": [
      "florist"
    ],
    "wof:name": "Lemon Tree Flowers \u0026 Things",
    "wof:placetype": "venue"
  },
  "geometry": {"coordinates":[-80.853681,40.897565],"type":"Point"}
}
