{
  "type": "Feature",
  "properties": {
    "iso:country":"US",
    "sg:address":"423 S Lundy Ave",
    "sg:city":"Salem",
    "sg:classifiers":[
        {
            "category":"Shopping",
            "subcategory":"Gifts & Souvenirs",
            "type":"Retail Goods"
        }
    ],
    "sg:phone":"+1 330 332 2969",
    "sg:postcode":"44460",
    "sg:province":"OH",
    "sg:tags":[
        "florist"
    ],
    "wof:name":"Lemon Tree Flowers & Things",
    "wof:placetype":"venue"
},
  "geometry": {"coordinates":[-80.85368099999999,40.897565],"type":"Point"}
}