{
  "type": "Feature",
  "properties": {
    "iso:country":"US",
    "sg:address":"14990 Back Massillon Rd",
    "sg:city":"Orrville",
    "sg:classifiers":[
        {
            "category":"Real Estate",
            "subcategory":"Real Estate Operator",
            "type":"Services"
        }
    ],
    "sg:phone":"+1 330 682 0122",
    "sg:postcode":"44667",
    "sg:province":"OH",
    "sg:tags":[
        "property",
        "lessor"
    ],
    "wof:name":"Wendell Douglass",
    "wof:placetype":"venue"
},
  "geometry": {"coordinates":[-81.718649,40.873974],"type":"Point"}
}