{
  "type": "Feature",
  "properties": {
    "iso:country":"US",
    "sg:address":"5870 Sawmill Rd",
    "sg:city":"Dublin",
    "sg:classifiers":[
        {
            "category":"Shopping",
            "subcategory":"Department Store",
            "type":"Retail Goods"
        }
    ],
    "sg:phone":"+1 614 760 7771",
    "sg:postcode":"43017",
    "sg:province":"OH",
    "sg:tags":[
        "club",
        "wholesale"
    ],
    "sg:website":"www.samsclub.com",
    "wof:name":"Sam's Club",
    "wof:placetype":"venue"
},
  "geometry": {"coordinates":[-83.09194100000001,40.086101],"type":"Point"}
}