{
  "type": "Feature",
  "properties": {
    "addr:full": "5870 Sawmill Rd Dublin OH 43017",
    "addr:housenumber": "5870",
    "addr:postcode": "43017",
    "addr:street": "Sawmill Rd",
    "iso:country": "US",
    "sg:address": "5870 Sawmill Rd",
    "sg:city": "Dublin",
    "sg:classifiers": [
      {
        "category": "Shopping",
        "subcategory": "Department Store",
        "type": "Retail Goods"
      }
    ],
    "sg:phone": "+1 614 760 7771",
    "sg:postcode": "43017",
    "sg:province": "OH",
    "sg:tags": [
      "club",
      "wholesale"
    ],
    "sg:website": "www.samsclub.com",
    "wof:name": "Sam's Club",
    "wof:placetype": "venue"
  },
  "geometry": {"coordinates":[-83.091941,40.086101],"type":"Point"}
}
