{
  "type": "Feature",
  "properties": {
    "iso:country":"US",
    "sg:address":"29125 Chagrin Blvd",
    "sg:city":"Cleveland",
    "sg:classifiers":[
        {
            "category":"Professional",
            "subcategory":"Accounting & Tax Preparation",
            "type":"Services"
        }
    ],
    "sg:phone":"+1 216 595 3232",
    "sg:postcode":"44122",
    "sg:province":"OH",
    "sg:tags":[
        "accountant"
    ],
    "wof:name":"Greenberg & Wells",
    "wof:placetype":"venue"
},
  "geometry": {"coordinates":[-81.473762,41.462429],"type":"Point"}
}