{
  "type": "Feature",
  "properties": {
    "addr:full": "2131 N Wooster Ave Dover OH 44622",
    "addr:housenumber": "2131",
    "addr:postcode": "44622",
    "addr:street": "N Wooster Ave",
    "iso:country": "US",
    "sg:address": "2131 N Wooster Ave",
    "sg:city": "Dover",
    "sg:classifiers": [
      {
        "category": "Education",
        "subcategory": "School",
        "type": "Public Place"
      }
    ],
    "sg:phone": "+1 330 364 7121",
    "sg:postcode": "44622",
    "sg:province": "OH",
    "sg:tags": [
      "elementary",
      "secondary"
    ],
    "sg:website": "www.dover.k12.oh.us",
    "wof:name": "Dover Middle School",
    "wof:placetype": "venue"
  },
  "geometry": {"coordinates":[-81.489625,40.541563],"type":"Point"}
}
