{
  "type": "Feature",
  "properties": {
    "addr:full": "1317 Linden Ave Zanesville OH 43701",
    "addr:housenumber": "1317",
    "addr:postcode": "43701",
    "addr:street": "Linden Ave",
    "iso:country": "US",
    "sg:address": "1317 Linden Ave",
    "sg:city": "Zanesville",
    "sg:classifiers": [
      {
        "category": "Restaurant",
        "type": "Food \u0026 Drink"
      }
    ],
    "sg:phone": "+1 740 452 5624",
    "sg:postcode": "43701",
    "sg:province": "OH",
    "wof:name": "Carini Pub",
    "wof:placetype": "venue"
  },
  "geometry": {"coordinates":[-82.004423,39.955683],"type":"Point"}
}
