{
  "type": "Feature",
  "properties": {
    "iso:country":"US",
    "sg:address":"1317 Linden Ave",
    "sg:city":"Zanesville",
    "sg:classifiers":[
        {
            "category":"Restaurant",
            "type":"Food & Drink"
        }
    ],
    "sg:phone":"+1 740 452 5624",
    "sg:postcode":"43701",
    "sg:province":"OH",
    "wof:name":"Carini Pub",
    "wof:placetype":"venue"
},
  "geometry": {"coordinates":[-82.004423,39.955683],"type":"Point"}
}