{
  "type": "Feature",
  "properties": {
    "addr:full": "5250 Warrensville Center Rd Cleveland OH 44137",
    "addr:housenumber": "5250",
    "addr:postcode": "44137",
    "addr:street": "Warrensville Center Rd",
    "iso:country": "US",
    "sg:address": "5250 Warrensville Center Rd",
    "sg:city": "Cleveland",
    "sg:classifiers": [
      {
        "category": "Professional",
        "type": "Services"
      }
    ],
    "sg:phone": "+1 216 475 5010",
    "sg:postcode": "44137",
    "sg:province": "OH",
    "sg:tags": [
      "establishment"
    ],
    "wof:name": "Checkstar Payday Advance",
    "wof:placetype": "venue"
  },
  "geometry": {"coordinates":[-81.537407,41.418521],"type":"Point"}
}
