{
  "type": "Feature",
  "properties": {
    "iso:country":"US",
    "sg:address":"34 Eswin St",
    "sg:city":"Cincinnati",
    "sg:classifiers":[
        {
            "category":"Personal",
            "subcategory":"Barber",
            "type":"Services"
        }
    ],
    "sg:phone":"+1 513 825 1683",
    "sg:postcode":"45218",
    "sg:province":"OH",
    "wof:name":"Greenhills Barber Shop",
    "wof:placetype":"venue"
},
  "geometry": {"coordinates":[-84.522694,39.270069],"type":"Point"}
}