{
  "type": "Feature",
  "properties": {
    "addr:full":"200 Biggs Blvd Harrison OH 45030",
    "addr:housenumber":"200",
    "addr:postcode":"45030",
    "addr:street":"Biggs Blvd",
    "iso:country":"US",
    "sg:address":"200 Biggs Blvd",
    "sg:city":"Harrison",
    "sg:classifiers":[
        {
            "category":"Restaurant",
            "type":"Food & Drink"
        }
    ],
    "sg:phone":"+1 513 202 9464",
    "sg:postcode":"45030",
    "sg:province":"OH",
    "sg:website":"www.buffalowildwings.com",
    "wof:name":"Buffalo Wild Wings Grill & Bar",
    "wof:placetype":"venue"
},
  "geometry": {"coordinates":[-84.79638799999999,39.259859],"type":"Point"}
}