{
  "type": "Feature",
  "properties": {
    "addr:full": "1006 N Burnett Rd Springfield OH 45503",
    "addr:housenumber": "1006",
    "addr:postcode": "45503",
    "addr:street": "N Burnett Rd",
    "iso:country": "US",
    "sg:address": "1006 N Burnett Rd",
    "sg:city": "Springfield",
    "sg:classifiers": [
      {
        "category": "Building \u0026 Trades",
        "subcategory": "Construction",
        "type": "Services"
      }
    ],
    "sg:phone": "+1 937 322 4469",
    "sg:postcode": "45503",
    "sg:province": "OH",
    "sg:tags": [
      "contractor"
    ],
    "wof:name": "True Seal Roofing \u0026 Siding",
    "wof:placetype": "venue"
  },
  "geometry": {"coordinates":[-83.768952,39.933739],"type":"Point"}
}
