{
  "type": "Feature",
  "properties": {
    "addr:full":"50 S Maple St Akron OH 44303",
    "addr:housenumber":"50",
    "addr:postcode":"44303",
    "addr:street":"S Maple St",
    "iso:country":"US",
    "sg:address":"50 S Maple St",
    "sg:city":"Akron",
    "sg:classifiers":[
        {
            "category":"Professional",
            "type":"Services"
        }
    ],
    "sg:phone":"+1 330 258 1080",
    "sg:postcode":"44303",
    "sg:province":"OH",
    "sg:tags":[
        "establishment"
    ],
    "wof:name":"Saloma International Co",
    "wof:placetype":"venue"
},
  "geometry": {"coordinates":[-81.524286,41.087081],"type":"Point"}
}