{
  "type": "Feature",
  "properties": {
    "addr:full":"101 W Sandusky St Findlay OH 45840",
    "addr:housenumber":"101",
    "addr:postcode":"45840",
    "addr:street":"W Sandusky St",
    "iso:country":"US",
    "sg:address":"101 W Sandusky St",
    "sg:city":"Findlay",
    "sg:classifiers":[
        {
            "category":"Wholesale",
            "subcategory":"Electrical",
            "type":"Manufacturing & Wholesale Goods"
        }
    ],
    "sg:phone":"+1 419 423 5653",
    "sg:postcode":"45840",
    "sg:province":"OH",
    "sg:tags":[
        "equipment",
        "electric",
        "supply"
    ],
    "wof:name":"Square D",
    "wof:placetype":"venue"
},
  "geometry": {"coordinates":[-83.650272,41.037039],"type":"Point"}
}