{
  "type": "Feature",
  "properties": {
    "addr:full": "7247 Center St Mentor OH 44060",
    "addr:housenumber": "7247",
    "addr:postcode": "44060",
    "addr:street": "Center St",
    "iso:country": "US",
    "sg:address": "7247 Center St",
    "sg:city": "Mentor",
    "sg:classifiers": [
      {
        "category": "Retail",
        "subcategory": "Repair Shop",
        "type": "Services"
      }
    ],
    "sg:phone": "+1 440 974 0550",
    "sg:postcode": "44060",
    "sg:province": "OH",
    "sg:tags": [
      "lock",
      "locksmith",
      "supply"
    ],
    "wof:name": "G \u0026 L Locksmiths",
    "wof:placetype": "venue"
  },
  "geometry": {"coordinates":[-81.339719,41.673557],"type":"Point"}
}
