{
  "type": "Feature",
  "properties": {
    "iso:country":"US",
    "sg:address":"4175 Karg Industrial Pkwy",
    "sg:city":"Kent",
    "sg:classifiers":[
        {
            "category":"Building & Trades",
            "subcategory":"Plumbing",
            "type":"Services"
        }
    ],
    "sg:phone":"+1 330 628 5091",
    "sg:postcode":"44240",
    "sg:province":"OH",
    "sg:tags":[
        "air",
        "heating",
        "conditioning",
        "contractor"
    ],
    "wof:name":"Cool Breeze Corp",
    "wof:placetype":"venue"
},
  "geometry": {"coordinates":[-81.358564,41.102604],"type":"Point"}
}