{
  "type": "Feature",
  "properties": {
    "addr:full": "1274 Lincoln Ave Steubenville OH 43952",
    "addr:housenumber": "1274",
    "addr:postcode": "43952",
    "addr:street": "Lincoln Ave",
    "iso:country": "US",
    "sg:address": "1274 Lincoln Ave",
    "sg:city": "Steubenville",
    "sg:classifiers": [
      {
        "category": "Building \u0026 Trades",
        "subcategory": "Construction",
        "type": "Services"
      }
    ],
    "sg:phone": "+1 740 381 4290",
    "sg:postcode": "43952",
    "sg:province": "OH",
    "sg:tags": [
      "contractor"
    ],
    "wof:name": "E \u0026 M Sub Contracting",
    "wof:placetype": "venue"
  },
  "geometry": {"coordinates":[-80.636956,40.350107],"type":"Point"}
}
