{
  "type": "Feature",
  "properties": {
    "iso:country":"US",
    "sg:address":"1274 Lincoln Ave",
    "sg:city":"Steubenville",
    "sg:classifiers":[
        {
            "category":"Building & Trades",
            "subcategory":"Construction",
            "type":"Services"
        }
    ],
    "sg:phone":"+1 740 381 4290",
    "sg:postcode":"43952",
    "sg:province":"OH",
    "sg:tags":[
        "contractor"
    ],
    "wof:name":"E & M Sub Contracting",
    "wof:placetype":"venue"
},
  "geometry": {"coordinates":[-80.636956,40.350107],"type":"Point"}
}