{
  "type": "Feature",
  "properties": {
    "addr:full": "175 Ashwood Dr Avon Lake OH 44012",
    "addr:housenumber": "175",
    "addr:postcode": "44012",
    "addr:street": "Ashwood Dr",
    "iso:country": "US",
    "sg:address": "175 Ashwood Dr",
    "sg:city": "Avon Lake",
    "sg:classifiers": [
      {
        "category": "Professional",
        "type": "Services"
      }
    ],
    "sg:phone": "+1 440 933 3068",
    "sg:postcode": "44012",
    "sg:province": "OH",
    "wof:name": "Dalgleish T R M",
    "wof:placetype": "venue"
  },
  "geometry": {"coordinates":[-82.041901,41.500062],"type":"Point"}
}
