{
  "type": "Feature",
  "properties": {
    "iso:country":"US",
    "sg:address":"2061 Elm Rd NE",
    "sg:city":"Warren",
    "sg:classifiers":[
        {
            "category":"Banks & Credit Unions",
            "subcategory":"Bank",
            "type":"Services"
        }
    ],
    "sg:phone":"+1 330 372 2813",
    "sg:postcode":"44483",
    "sg:province":"OH",
    "sg:tags":[
        "commercial"
    ],
    "wof:name":"Star Bank",
    "wof:placetype":"venue"
},
  "geometry": {"coordinates":[-80.791995,41.253876],"type":"Point"}
}