{
  "type": "Feature",
  "properties": {
    "addr:full":"33723 State Rte 78 Lewisville OH 43754",
    "addr:housenumber":"33723",
    "addr:postcode":"43754",
    "addr:street":"State Rte 78",
    "iso:country":"US",
    "sg:address":"33723 State Rte 78",
    "sg:city":"Lewisville",
    "sg:classifiers":[
        {
            "category":"Building & Trades",
            "subcategory":"Construction",
            "type":"Services"
        }
    ],
    "sg:phone":"+1 740 567 3281",
    "sg:postcode":"43754",
    "sg:province":"OH",
    "sg:tags":[
        "house"
    ],
    "wof:name":"Betts Ronald Bldg & Rmdlg Co",
    "wof:placetype":"venue"
},
  "geometry": {"coordinates":[-81.21231899999999,39.764703],"type":"Point"}
}