{
  "type": "Feature",
  "properties": {
    "addr:full": "206 Infirmary Rd Dayton OH 45427",
    "addr:housenumber": "206",
    "addr:postcode": "45427",
    "addr:street": "Infirmary Rd",
    "iso:country": "US",
    "sg:address": "206 Infirmary Rd",
    "sg:city": "Dayton",
    "sg:classifiers": [
      {
        "category": "Autos \u0026 Motor Vehicles",
        "subcategory": "Automobile Sales",
        "type": "Retail Goods"
      }
    ],
    "sg:phone": "+1 937 263 6416",
    "sg:postcode": "45427",
    "sg:province": "OH",
    "sg:tags": [
      "car",
      "used",
      "dealer"
    ],
    "wof:name": "Debbie O's Auto Sales",
    "wof:placetype": "venue"
  },
  "geometry": {"coordinates":[-84.281172,39.744747],"type":"Point"}
}
