{
  "type": "Feature",
  "properties": {
    "addr:full": "12518 Edmonton Ave Cleveland OH 44108",
    "addr:housenumber": "12518",
    "addr:postcode": "44108",
    "addr:street": "Edmonton Ave",
    "iso:country": "US",
    "sg:address": "12518 Edmonton Ave",
    "sg:city": "Cleveland",
    "sg:classifiers": [
      {
        "category": "Arts \u0026 Performance",
        "subcategory": "Theater",
        "type": "Entertainment"
      }
    ],
    "sg:phone": "+1 216 541 4566",
    "sg:postcode": "44108",
    "sg:province": "OH",
    "sg:tags": [
      "bureau"
    ],
    "wof:name": "Come N Talk Adult Entrtn",
    "wof:placetype": "venue"
  },
  "geometry": {"coordinates":[-81.59449,41.535285],"type":"Point"}
}
