{
  "type": "Feature",
  "properties": {
    "iso:country":"US",
    "sg:address":"12518 Edmonton Ave",
    "sg:city":"Cleveland",
    "sg:classifiers":[
        {
            "category":"Arts & Performance",
            "subcategory":"Theater",
            "type":"Entertainment"
        }
    ],
    "sg:phone":"+1 216 541 4566",
    "sg:postcode":"44108",
    "sg:province":"OH",
    "sg:tags":[
        "bureau"
    ],
    "wof:name":"Come N Talk Adult Entrtn",
    "wof:placetype":"venue"
},
  "geometry": {"coordinates":[-81.59448999999999,41.535285],"type":"Point"}
}