{
  "type": "Feature",
  "properties": {
    "iso:country":"US",
    "sg:address":"7640 Whipple Ave NW",
    "sg:city":"Canton",
    "sg:classifiers":[
        {
            "category":"Building & Trades",
            "subcategory":"Construction",
            "type":"Services"
        }
    ],
    "sg:phone":"+1 330 494 6226",
    "sg:postcode":"44720",
    "sg:province":"OH",
    "sg:tags":[
        "concrete",
        "industrial",
        "commercial",
        "contractor"
    ],
    "wof:name":"Northern Valley Contractors",
    "wof:placetype":"venue"
},
  "geometry": {"coordinates":[-81.424977,40.891494],"type":"Point"}
}