{
  "type": "Feature",
  "properties": {
    "addr:full":"10502 Avon Ave Cleveland OH 44105",
    "addr:housenumber":"10502",
    "addr:postcode":"44105",
    "addr:street":"Avon Ave",
    "iso:country":"US",
    "sg:address":"10502 Avon Ave",
    "sg:city":"Cleveland",
    "sg:classifiers":[
        {
            "category":"Food & Beverages",
            "subcategory":"Groceries & Convenience Stores",
            "type":"Retail Goods"
        }
    ],
    "sg:phone":"+1 216 341 4918",
    "sg:postcode":"44105",
    "sg:province":"OH",
    "wof:name":"Sals Flea Mkt",
    "wof:placetype":"venue"
},
  "geometry": {"coordinates":[-81.609126,41.451269],"type":"Point"}
}