{
  "type": "Feature",
  "properties": {
    "iso:country":"US",
    "sg:address":"405 N River Rd NW",
    "sg:city":"Warren",
    "sg:classifiers":[
        {
            "category":"Manufacturing",
            "subcategory":"Tools & Machinery",
            "type":"Manufacturing & Wholesale Goods"
        }
    ],
    "sg:phone":"+1 330 399 2862",
    "sg:postcode":"44483",
    "sg:province":"OH",
    "sg:tags":[
        "machine",
        "shop"
    ],
    "wof:name":"Garvey Corp",
    "wof:placetype":"venue"
},
  "geometry": {"coordinates":[-80.81951599999999,41.265583],"type":"Point"}
}