{
  "type": "Feature",
  "properties": {
    "addr:full": "405 N River Rd NW Warren OH 44483",
    "addr:housenumber": "405",
    "addr:postcode": "44483",
    "addr:street": "N River Rd Nw",
    "iso:country": "US",
    "sg:address": "405 N River Rd NW",
    "sg:city": "Warren",
    "sg:classifiers": [
      {
        "category": "Manufacturing",
        "subcategory": "Tools \u0026 Machinery",
        "type": "Manufacturing \u0026 Wholesale Goods"
      }
    ],
    "sg:phone": "+1 330 399 2862",
    "sg:postcode": "44483",
    "sg:province": "OH",
    "sg:tags": [
      "machine",
      "shop"
    ],
    "wof:name": "Garvey Corp",
    "wof:placetype": "venue"
  },
  "geometry": {"coordinates":[-80.819516,41.265583],"type":"Point"}
}
