{
  "type": "Feature",
  "properties": {
    "iso:country":"US",
    "sg:address":"3700 Montgomery Rd",
    "sg:city":"Cincinnati",
    "sg:classifiers":[
        {
            "category":"Autos & Motor Vehicles",
            "subcategory":"Motorcycle Sales",
            "type":"Retail Goods"
        }
    ],
    "sg:phone":"+1 513 631 6637",
    "sg:postcode":"45207",
    "sg:province":"OH",
    "sg:tags":[
        "scooter"
    ],
    "wof:name":"Metro Scooter",
    "wof:placetype":"venue"
},
  "geometry": {"coordinates":[-84.467252,39.146944],"type":"Point"}
}