{
  "type": "Feature",
  "properties": {
    "addr:full":"5222 Werner Rd Convoy OH 45832",
    "addr:housenumber":"5222",
    "addr:postcode":"45832",
    "addr:street":"Werner Rd",
    "iso:country":"US",
    "sg:address":"5222 Werner Rd",
    "sg:city":"Convoy",
    "sg:phone":"+1 419 749 2852",
    "sg:postcode":"45832",
    "sg:province":"OH",
    "sg:tags":[
        "farm",
        "corn",
        "wheat",
        "soybean"
    ],
    "wof:name":"Orville Whittenbarge",
    "wof:placetype":"venue"
},
  "geometry": {"coordinates":[-84.789072,40.928743],"type":"Point"}
}