{
  "type": "Feature",
  "properties": {
    "addr:full": "2360 Shawnee Rd Lima OH 45805",
    "addr:housenumber": "2360",
    "addr:postcode": "45805",
    "addr:street": "Shawnee Rd",
    "iso:country": "US",
    "sg:address": "2360 Shawnee Rd",
    "sg:city": "Lima",
    "sg:classifiers": [
      {
        "category": "Real Estate",
        "subcategory": "Real Estate Agent",
        "type": "Services"
      }
    ],
    "sg:phone": "+1 419 225 4341",
    "sg:postcode": "45805",
    "sg:province": "OH",
    "wof:name": "White Bros Builders Inc",
    "wof:placetype": "venue"
  },
  "geometry": {"coordinates":[-84.151549,40.706091],"type":"Point"}
}
