{
  "type": "Feature",
  "properties": {
    "addr:full": "3750 Courtright Ct Columbus OH 43227",
    "addr:housenumber": "3750",
    "addr:postcode": "43227",
    "addr:street": "Courtright Ct",
    "iso:country": "US",
    "sg:address": "3750 Courtright Ct",
    "sg:city": "Columbus",
    "sg:classifiers": [
      {
        "category": "Building \u0026 Trades",
        "subcategory": "Construction",
        "type": "Services"
      }
    ],
    "sg:phone": "+1 614 237 8456",
    "sg:postcode": "43227",
    "sg:province": "OH",
    "sg:tags": [
      "general",
      "contractor"
    ],
    "wof:name": "General Theming Contractors",
    "wof:placetype": "venue"
  },
  "geometry": {"coordinates":[-82.896621,39.943834],"type":"Point"}
}
