{
  "type": "Feature",
  "properties": {
    "iso:country":"US",
    "sg:address":"3750 Courtright Ct",
    "sg:city":"Columbus",
    "sg:classifiers":[
        {
            "category":"Building & Trades",
            "subcategory":"Construction",
            "type":"Services"
        }
    ],
    "sg:phone":"+1 614 237 8456",
    "sg:postcode":"43227",
    "sg:province":"OH",
    "sg:tags":[
        "general",
        "contractor"
    ],
    "wof:name":"General Theming Contractors",
    "wof:placetype":"venue"
},
  "geometry": {"coordinates":[-82.896621,39.943834],"type":"Point"}
}