{
  "type": "Feature",
  "properties": {
    "iso:country":"US",
    "sg:address":"7505 Leavitt Rd",
    "sg:city":"Amherst",
    "sg:classifiers":[
        {
            "category":"Retail",
            "subcategory":"Auto Repair",
            "type":"Services"
        }
    ],
    "sg:phone":"+1 440 988 9203",
    "sg:postcode":"44001",
    "sg:province":"OH",
    "sg:tags":[
        "exhaust"
    ],
    "wof:name":"G & G Auto Parts",
    "wof:placetype":"venue"
},
  "geometry": {"coordinates":[-82.209938,41.38838],"type":"Point"}
}