{
  "type": "Feature",
  "properties": {
    "iso:country":"US",
    "sg:address":"230 E Main St",
    "sg:city":"Union City",
    "sg:classifiers":[
        {
            "category":"Personal",
            "subcategory":"Beauty Salon",
            "type":"Services"
        }
    ],
    "sg:phone":"+1 937 878 5144",
    "sg:postcode":"45390",
    "sg:province":"OH",
    "sg:tags":[
        "shop"
    ],
    "wof:name":"Fotinis Hair Designs",
    "wof:placetype":"venue"
},
  "geometry": {"coordinates":[-84.803797,40.197216],"type":"Point"}
}