{
  "type": "Feature",
  "properties": {
    "addr:full":"103 Twp Rd 248 N Kitts Hill OH 45645",
    "addr:housenumber":"103",
    "addr:postcode":"45645",
    "addr:street":"Twp Rd 248 N Kitts Hill",
    "iso:country":"US",
    "sg:address":"103 Twp Rd 248 N",
    "sg:city":"Kitts Hill",
    "sg:classifiers":[
        {
            "category":"Autos & Motor Vehicles",
            "subcategory":"Auto Supplies",
            "type":"Retail Goods"
        }
    ],
    "sg:phone":"+1 740 532 0139",
    "sg:postcode":"45645",
    "sg:province":"OH",
    "wof:name":"Power Line Auto Parts",
    "wof:placetype":"venue"
},
  "geometry": {"coordinates":[-82.509199,38.544622],"type":"Point"}
}