{
  "type": "Feature",
  "properties": {
    "addr:full":"10553 Harrison Ave Harrison IN 45030",
    "addr:housenumber":"10553",
    "addr:postcode":"45030",
    "addr:street":"Harrison Ave",
    "iso:country":"US",
    "sg:address":"10553 Harrison Ave",
    "sg:city":"Harrison",
    "sg:classifiers":[
        {
            "category":"Building & Trades",
            "subcategory":"Construction",
            "type":"Services"
        }
    ],
    "sg:phone":"+1 513 367 1369",
    "sg:postcode":"45030",
    "sg:province":"IN",
    "sg:tags":[
        "new",
        "general",
        "commercial",
        "renovation",
        "contractor"
    ],
    "wof:name":"Wurster Builders Inc",
    "wof:placetype":"venue"
},
  "geometry": {"coordinates":[-84.794971,39.252823],"type":"Point"}
}