{
  "type": "Feature",
  "properties": {
    "addr:full":"3433 Belmont Ave Youngstown OH 44505",
    "addr:housenumber":"3433",
    "addr:postcode":"44505",
    "addr:street":"Belmont Ave",
    "iso:country":"US",
    "sg:address":"3433 Belmont Ave",
    "sg:city":"Youngstown",
    "sg:classifiers":[
        {
            "category":"Retail",
            "subcategory":"Laundry & Dry Cleaning",
            "type":"Services"
        }
    ],
    "sg:phone":"+1 330 759 9199",
    "sg:postcode":"44505",
    "sg:province":"OH",
    "sg:tags":[
        "cleaners"
    ],
    "wof:name":"LA France Dry Cleaners",
    "wof:placetype":"venue"
},
  "geometry": {"coordinates":[-80.665361,41.144641],"type":"Point"}
}