{
  "type": "Feature",
  "properties": {
    "iso:country":"US",
    "sg:address":"13423 Johnstown-Utica Rd NW",
    "sg:city":"Johnstown",
    "sg:classifiers":[
        {
            "category":"Building & Trades",
            "subcategory":"Plumbing",
            "type":"Services"
        }
    ],
    "sg:phone":"+1 740 966 5151",
    "sg:postcode":"43031",
    "sg:province":"OH",
    "sg:tags":[
        "contractor"
    ],
    "wof:name":"Furnace Services Inc",
    "wof:placetype":"venue"
},
  "geometry": {"coordinates":[-82.742694,40.128208],"type":"Point"}
}