{
  "type": "Feature",
  "properties": {
    "addr:full": "1018 Lakeshore Walk Medina OH 44256",
    "addr:housenumber": "1018",
    "addr:postcode": "44256",
    "addr:street": "Lakeshore Walk",
    "iso:country": "US",
    "sg:address": "1018 Lakeshore Walk",
    "sg:city": "Medina",
    "sg:classifiers": [
      {
        "category": "Banks \u0026 Credit Unions",
        "subcategory": "Financial Services",
        "type": "Services"
      }
    ],
    "sg:phone": "+1 330 722 4752",
    "sg:postcode": "44256",
    "sg:province": "OH",
    "sg:tags": [
      "company",
      "holding"
    ],
    "wof:name": "Alpha Holdings LLC",
    "wof:placetype": "venue"
  },
  "geometry": {"coordinates":[-81.853417,41.154064],"type":"Point"}
}
