{
  "type": "Feature",
  "properties": {
    "addr:full":"3461 Towne Blvd Franklin OH 45005",
    "addr:housenumber":"3461",
    "addr:postcode":"45005",
    "addr:street":"Towne Blvd",
    "iso:country":"US",
    "sg:address":"3461 Towne Blvd",
    "sg:city":"Franklin",
    "sg:classifiers":[
        {
            "category":"Shopping",
            "subcategory":"Computers & Home Electronics",
            "type":"Retail Goods"
        }
    ],
    "sg:phone":"+1 513 423 8468",
    "sg:postcode":"45005",
    "sg:province":"OH",
    "sg:tags":[
        "equipment",
        "electronic",
        "supply"
    ],
    "sg:website":"www.radioshack.com",
    "wof:name":"Radio Shack",
    "wof:placetype":"venue"
},
  "geometry": {"coordinates":[-84.330206,39.501285],"type":"Point"}
}