{
  "type": "Feature",
  "properties": {
    "addr:full": "445 N High St Columbus OH 43215",
    "addr:housenumber": "445",
    "addr:postcode": "43215",
    "addr:street": "N High St",
    "iso:country": "US",
    "sg:address": "445 N High St",
    "sg:city": "Columbus",
    "sg:classifiers": [
      {
        "category": "Professional",
        "subcategory": "Research",
        "type": "Services"
      }
    ],
    "sg:phone": "+1 614 228 8442",
    "sg:postcode": "43215",
    "sg:province": "OH",
    "sg:tags": [
      "market",
      "analysis"
    ],
    "sg:website": "www.advantageresearch.net",
    "wof:name": "Advantage Research-Columbus",
    "wof:placetype": "venue"
  },
  "geometry": {"coordinates":[-83.002395,39.971238],"type":"Point"}
}
