{
  "type": "Feature",
  "properties": {
    "addr:full": "1083 Long Rd Xenia OH 45385",
    "addr:housenumber": "1083",
    "addr:postcode": "45385",
    "addr:street": "Long Rd",
    "iso:country": "US",
    "sg:address": "1083 Long Rd",
    "sg:city": "Xenia",
    "sg:classifiers": [
      {
        "category": "Building \u0026 Trades",
        "subcategory": "Landscaping Services",
        "type": "Services"
      }
    ],
    "sg:phone": "+1 937 372 4664",
    "sg:postcode": "45385",
    "sg:province": "OH",
    "sg:tags": [
      "sod",
      "sodding"
    ],
    "wof:name": "Pleasant View Farm Custom Lawn",
    "wof:placetype": "venue"
  },
  "geometry": {"coordinates":[-83.841666,39.648491],"type":"Point"}
}
