{
  "type": "Feature",
  "properties": {
    "addr:full":"4250 International Gtwy Columbus OH 43219",
    "addr:housenumber":"4250",
    "addr:postcode":"43219",
    "addr:street":"International Gtwy",
    "iso:country":"US",
    "sg:address":"4250 International Gtwy",
    "sg:city":"Columbus",
    "sg:classifiers":[
        {
            "category":"Restaurant",
            "type":"Food & Drink"
        }
    ],
    "sg:menulink":"http://www.allmenus.com/oh/columbus/195268-mcdonalds/menu/",
    "sg:postcode":"43219",
    "sg:province":"OH",
    "sg:tags":[
        "burger",
        "american"
    ],
    "wof:name":"McDonald's",
    "wof:placetype":"venue"
},
  "geometry": {"coordinates":[-82.89422999999999,39.998721],"type":"Point"}
}