{
  "type": "Feature",
  "properties": {
    "addr:full": "9250 Armstrong Rd Spencerville OH 45887",
    "addr:housenumber": "9250",
    "addr:postcode": "45887",
    "addr:street": "Armstrong Rd",
    "iso:country": "US",
    "sg:address": "9250 Armstrong Rd",
    "sg:city": "Spencerville",
    "sg:classifiers": [
      {
        "category": "Organizations",
        "subcategory": "Religious Organization",
        "type": "Services"
      }
    ],
    "sg:phone": "+1 419 647 4260",
    "sg:postcode": "45887",
    "sg:province": "OH",
    "sg:tags": [
      "church"
    ],
    "wof:name": "Agape Fellowship Ministries",
    "wof:placetype": "venue"
  },
  "geometry": {"coordinates":[-84.279083,40.707832],"type":"Point"}
}
