{
  "type": "Feature",
  "properties": {
    "addr:full": "3992 Superior Ave Cincinnati OH 45236",
    "addr:housenumber": "3992",
    "addr:postcode": "45236",
    "addr:street": "Superior Ave",
    "iso:country": "US",
    "sg:address": "3992 Superior Ave",
    "sg:city": "Cincinnati",
    "sg:classifiers": [
      {
        "category": "Professional",
        "type": "Services"
      }
    ],
    "sg:phone": "+1 513 984 8025",
    "sg:postcode": "45236",
    "sg:province": "OH",
    "wof:name": "Mint 6 Ten",
    "wof:placetype": "venue"
  },
  "geometry": {"coordinates":[-84.402736,39.20087],"type":"Point"}
}
