{
  "type": "Feature",
  "properties": {
    "addr:full": "1001 Market Ave N Canton OH 44702",
    "addr:housenumber": "1001",
    "addr:postcode": "44702",
    "addr:street": "Market Ave N",
    "iso:country": "US",
    "sg:address": "1001 Market Ave N",
    "sg:city": "Canton",
    "sg:classifiers": [
      {
        "category": "Arts \u0026 Performance",
        "subcategory": "Theater",
        "type": "Entertainment"
      }
    ],
    "sg:phone": "+1 330 452 4096",
    "sg:postcode": "44702",
    "sg:province": "OH",
    "sg:tags": [
      "cultural",
      "association"
    ],
    "wof:name": "Canton Players Guild",
    "wof:placetype": "venue"
  },
  "geometry": {"coordinates":[-81.372549,40.805958],"type":"Point"}
}
