{
  "type": "Feature",
  "properties": {
    "iso:country":"US",
    "sg:address":"563 Ternes Ln",
    "sg:city":"Elyria",
    "sg:classifiers":[
        {
            "category":"Building & Trades",
            "subcategory":"Construction",
            "type":"Services"
        }
    ],
    "sg:phone":"+1 440 365 0705",
    "sg:postcode":"44035",
    "sg:province":"OH",
    "sg:tags":[
        "pipe",
        "line",
        "contractor"
    ],
    "wof:name":"Specialty Fitters Inc",
    "wof:placetype":"venue"
},
  "geometry": {"coordinates":[-82.071001,41.363981],"type":"Point"}
}