{
  "type": "Feature",
  "properties": {
    "addr:full":"431 Ohio Pike Cincinnati OH 45255",
    "addr:housenumber":"431",
    "addr:postcode":"45255",
    "addr:street":"Ohio Pike",
    "iso:country":"US",
    "sg:address":"431 Ohio Pike",
    "sg:city":"Cincinnati",
    "sg:classifiers":[
        {
            "category":"Shopping",
            "subcategory":"Computers & Home Electronics",
            "type":"Retail Goods"
        }
    ],
    "sg:phone":"+1 513 528 2941",
    "sg:postcode":"45255",
    "sg:province":"OH",
    "sg:tags":[
        "equipment",
        "dealer"
    ],
    "wof:name":"Patrick Consult Inc",
    "wof:placetype":"venue"
},
  "geometry": {"coordinates":[-84.312439,39.071722],"type":"Point"}
}