{
  "type": "Feature",
  "properties": {
    "iso:country":"US",
    "sg:address":"1030 Main St",
    "sg:city":"Milford",
    "sg:classifiers":[
        {
            "category":"Personal",
            "type":"Services"
        }
    ],
    "sg:phone":"+1 513 677 0032",
    "sg:postcode":"45150",
    "sg:province":"OH",
    "sg:tags":[
        "therapist",
        "massage"
    ],
    "sg:website":"www.relaxationcenter.com",
    "wof:name":"Relaxation Center",
    "wof:placetype":"venue"
},
  "geometry": {"coordinates":[-84.276021,39.180964],"type":"Point"}
}