{
  "type": "Feature",
  "properties": {
    "addr:full":"8421 Timber Trl Chagrin Falls OH 44023",
    "addr:housenumber":"8421",
    "addr:postcode":"44023",
    "addr:street":"Timber Trl",
    "iso:country":"US",
    "sg:address":"8421 Timber Trl",
    "sg:city":"Chagrin Falls",
    "sg:classifiers":[
        {
            "category":"Real Estate",
            "subcategory":"Real Estate Operator",
            "type":"Services"
        }
    ],
    "sg:phone":"+1 440 543 0567",
    "sg:postcode":"44023",
    "sg:province":"OH",
    "sg:tags":[
        "building",
        "nonresidential"
    ],
    "wof:name":"Ribic Properties LLC",
    "wof:placetype":"venue"
},
  "geometry": {"coordinates":[-81.34242,41.353905],"type":"Point"}
}