{
  "type": "Feature",
  "properties": {
    "addr:full":"33 W Church St Oxford IN 45056",
    "addr:housenumber":"33",
    "addr:postcode":"45056",
    "addr:street":"W Church St",
    "iso:country":"US",
    "sg:address":"33 W Church St",
    "sg:city":"Oxford",
    "sg:classifiers":[
        {
            "category":"Professional",
            "subcategory":"Management & Consulting",
            "type":"Services"
        }
    ],
    "sg:phone":"+1 513 523 0227",
    "sg:postcode":"45056",
    "sg:province":"IN",
    "sg:tags":[
        "communications",
        "consultant"
    ],
    "wof:name":"Advocacy Unlimited",
    "wof:placetype":"venue"
},
  "geometry": {"coordinates":[-84.74287,39.511473],"type":"Point"}
}