{
  "type": "Feature",
  "properties": {
    "addr:full": "4201 Wichita Ave Cleveland OH 44109",
    "addr:housenumber": "4201",
    "addr:postcode": "44109",
    "addr:street": "Wichita Ave",
    "iso:country": "US",
    "sg:address": "4201 Wichita Ave",
    "sg:city": "Cleveland",
    "sg:classifiers": [
      {
        "category": "Building \u0026 Trades",
        "subcategory": "Construction",
        "type": "Services"
      }
    ],
    "sg:phone": "+1 216 324 5646",
    "sg:postcode": "44109",
    "sg:province": "OH",
    "sg:tags": [
      "home",
      "improvement"
    ],
    "wof:name": "Custom Painting \u0026 Remodeling",
    "wof:placetype": "venue"
  },
  "geometry": {"coordinates":[-81.712583,41.432889],"type":"Point"}
}
