{
  "type": "Feature",
  "properties": {
    "iso:country":"US",
    "sg:address":"4201 Wichita Ave",
    "sg:city":"Cleveland",
    "sg:classifiers":[
        {
            "category":"Building & Trades",
            "subcategory":"Construction",
            "type":"Services"
        }
    ],
    "sg:phone":"+1 216 324 5646",
    "sg:postcode":"44109",
    "sg:province":"OH",
    "sg:tags":[
        "home",
        "improvement"
    ],
    "wof:name":"Custom Painting & Remodeling",
    "wof:placetype":"venue"
},
  "geometry": {"coordinates":[-81.712583,41.432889],"type":"Point"}
}