{
  "type": "Feature",
  "properties": {
    "iso:country":"US",
    "sg:address":"28699 Chagrin Blvd Ste 425",
    "sg:city":"Beachwood",
    "sg:classifiers":[
        {
            "category":"Banks & Credit Unions",
            "subcategory":"Investment Brokerage",
            "type":"Services"
        }
    ],
    "sg:phone":"+1 216 591 9500",
    "sg:postcode":"44122",
    "sg:province":"OH",
    "sg:tags":[
        "investing"
    ],
    "sg:website":"www.fidelity.com",
    "wof:name":"Fidelity Investments",
    "wof:placetype":"venue"
},
  "geometry": {"coordinates":[-81.47676,41.462497],"type":"Point"}
}