{
  "type": "Feature",
  "properties": {
    "addr:full":"7 W Bowery St Akron OH 44308",
    "addr:housenumber":"7",
    "addr:postcode":"44308",
    "addr:street":"W Bowery St",
    "iso:country":"US",
    "sg:address":"7 W Bowery St",
    "sg:city":"Akron",
    "sg:classifiers":[
        {
            "category":"Professional",
            "subcategory":"Lawyer & Legal Services",
            "type":"Services"
        }
    ],
    "sg:phone":"+1 330 996 4099",
    "sg:postcode":"44308",
    "sg:province":"OH",
    "sg:tags":[
        "attorney"
    ],
    "wof:name":"Melissa Graham-Hurd",
    "wof:placetype":"venue"
},
  "geometry": {"coordinates":[-81.519807,41.081314],"type":"Point"}
}