{
  "type": "Feature",
  "properties": {
    "iso:country":"US",
    "sg:address":"1716 Enterprise Pkwy",
    "sg:city":"Twinsburg",
    "sg:classifiers":[
        {
            "category":"Manufacturing",
            "subcategory":"Printing",
            "type":"Manufacturing & Wholesale Goods"
        }
    ],
    "sg:phone":"+1 330 405 3770",
    "sg:postcode":"44087",
    "sg:province":"OH",
    "sg:tags":[
        "printer",
        "commercial"
    ],
    "wof:name":"Direct Digital Graphics Inc",
    "wof:placetype":"venue"
},
  "geometry": {"coordinates":[-81.458634,41.291521],"type":"Point"}
}