{
  "type": "Feature",
  "properties": {
    "addr:full": "1716 Enterprise Pkwy Twinsburg OH 44087",
    "addr:housenumber": "1716",
    "addr:postcode": "44087",
    "addr:street": "Enterprise Pkwy",
    "iso:country": "US",
    "sg:address": "1716 Enterprise Pkwy",
    "sg:city": "Twinsburg",
    "sg:classifiers": [
      {
        "category": "Manufacturing",
        "subcategory": "Printing",
        "type": "Manufacturing \u0026 Wholesale Goods"
      }
    ],
    "sg:phone": "+1 330 405 3770",
    "sg:postcode": "44087",
    "sg:province": "OH",
    "sg:tags": [
      "printer",
      "commercial"
    ],
    "wof:name": "Direct Digital Graphics Inc",
    "wof:placetype": "venue"
  },
  "geometry": {"coordinates":[-81.458634,41.291521],"type":"Point"}
}
