{
  "type": "Feature",
  "properties": {
    "addr:full": "13202 Enterprise Ave Cleveland OH 44135",
    "addr:housenumber": "13202",
    "addr:postcode": "44135",
    "addr:street": "Enterprise Ave",
    "iso:country": "US",
    "sg:address": "13202 Enterprise Ave",
    "sg:city": "Cleveland",
    "sg:classifiers": [
      {
        "category": "Manufacturing",
        "subcategory": "Printing",
        "type": "Manufacturing \u0026 Wholesale Goods"
      }
    ],
    "sg:phone": "+1 216 433 7172",
    "sg:postcode": "44135",
    "sg:province": "OH",
    "sg:tags": [
      "printer"
    ],
    "wof:name": "AM Industrial",
    "wof:placetype": "venue"
  },
  "geometry": {"coordinates":[-81.783746,41.422965],"type":"Point"}
}
