{
  "type": "Feature",
  "properties": {
    "iso:country":"US",
    "sg:address":"13202 Enterprise Ave",
    "sg:city":"Cleveland",
    "sg:classifiers":[
        {
            "category":"Manufacturing",
            "subcategory":"Printing",
            "type":"Manufacturing & Wholesale Goods"
        }
    ],
    "sg:phone":"+1 216 433 7172",
    "sg:postcode":"44135",
    "sg:province":"OH",
    "sg:tags":[
        "printer"
    ],
    "wof:name":"AM Industrial",
    "wof:placetype":"venue"
},
  "geometry": {"coordinates":[-81.78374599999999,41.422965],"type":"Point"}
}