{
  "type": "Feature",
  "properties": {
    "iso:country":"US",
    "sg:address":"5242 Center St",
    "sg:city":"Hilliard",
    "sg:classifiers":[
        {
            "category":"Building & Trades",
            "subcategory":"Construction",
            "type":"Services"
        }
    ],
    "sg:phone":"+1 614 876 2089",
    "sg:postcode":"43026",
    "sg:province":"OH",
    "sg:tags":[
        "painting",
        "contractor"
    ],
    "wof:name":"R J Buoni Painting",
    "wof:placetype":"venue"
},
  "geometry": {"coordinates":[-83.157635,40.032528],"type":"Point"}
}