{
  "type": "Feature",
  "properties": {
    "iso:country":"US",
    "sg:address":"67 W Canal St",
    "sg:city":"Navarre",
    "sg:classifiers":[
        {
            "category":"Freight",
            "type":"Transportation"
        }
    ],
    "sg:phone":"+1 330 879 0042",
    "sg:postcode":"44662",
    "sg:province":"OH",
    "sg:tags":[
        "operator",
        "local",
        "trucking"
    ],
    "wof:name":"Maverick Trucking Inc",
    "wof:placetype":"venue"
},
  "geometry": {"coordinates":[-81.524686,40.719613],"type":"Point"}
}