{
  "type": "Feature",
  "properties": {
    "addr:full":"34 E 2nd St Ashland OH 44805",
    "addr:housenumber":"34",
    "addr:postcode":"44805",
    "addr:street":"E 2Nd St",
    "iso:country":"US",
    "sg:address":"34 E 2nd St",
    "sg:city":"Ashland",
    "sg:classifiers":[
        {
            "category":"Manufacturing",
            "subcategory":"Glass & Minerals",
            "type":"Manufacturing & Wholesale Goods"
        }
    ],
    "sg:phone":"+1 419 281 2688",
    "sg:postcode":"44805",
    "sg:province":"OH",
    "sg:tags":[
        "marker",
        "grave",
        "mfg"
    ],
    "wof:name":"Ashland Monument Company Inc",
    "wof:placetype":"venue"
},
  "geometry": {"coordinates":[-82.31496799999999,40.869323],"type":"Point"}
}