{
  "type": "Feature",
  "properties": {
    "addr:full": "9801 Weik Rd Cincinnati OH 45252",
    "addr:housenumber": "9801",
    "addr:postcode": "45252",
    "addr:street": "Weik Rd",
    "iso:country": "US",
    "sg:address": "9801 Weik Rd",
    "sg:city": "Cincinnati",
    "sg:classifiers": [
      {
        "category": "Building \u0026 Trades",
        "subcategory": "Cleaning \u0026 Sanitation",
        "type": "Services"
      }
    ],
    "sg:phone": "+1 513 741 8805",
    "sg:postcode": "45252",
    "sg:province": "OH",
    "sg:tags": [
      "janitor"
    ],
    "wof:name": "Sparkling Interiors",
    "wof:placetype": "venue"
  },
  "geometry": {"coordinates":[-84.651125,39.255472],"type":"Point"}
}
