{
  "type": "Feature",
  "properties": {
    "addr:full":"574 Ternes Ln Elyria OH 44035",
    "addr:housenumber":"574",
    "addr:postcode":"44035",
    "addr:street":"Ternes Ln",
    "iso:country":"US",
    "sg:address":"574 Ternes Ln",
    "sg:city":"Elyria",
    "sg:classifiers":[
        {
            "category":"Building & Trades",
            "subcategory":"Electrical",
            "type":"Services"
        }
    ],
    "sg:phone":"+1 440 366 3413",
    "sg:postcode":"44035",
    "sg:province":"OH",
    "sg:tags":[
        "electric",
        "contractor"
    ],
    "wof:name":"Novak Electric Co",
    "wof:placetype":"venue"
},
  "geometry": {"coordinates":[-82.070832,41.36513],"type":"Point"}
}