{
  "type": "Feature",
  "properties": {
    "addr:full":"1864 Scottsdale Ave Columbus OH 43235",
    "addr:housenumber":"1864",
    "addr:postcode":"43235",
    "addr:street":"Scottsdale Ave",
    "iso:country":"US",
    "sg:address":"1864 Scottsdale Ave",
    "sg:city":"Columbus",
    "sg:classifiers":[
        {
            "category":"Manufacturing",
            "subcategory":"Paper Products",
            "type":"Manufacturing & Wholesale Goods"
        }
    ],
    "sg:phone":"+1 614 326 3444",
    "sg:postcode":"43235",
    "sg:province":"OH",
    "sg:tags":[
        "stationery",
        "mfg"
    ],
    "wof:name":"Personalizzied",
    "wof:placetype":"venue"
},
  "geometry": {"coordinates":[-83.06407299999999,40.070959],"type":"Point"}
}