{
  "type": "Feature",
  "properties": {
    "iso:country":"US",
    "sg:address":"3150 E Sharon Rd",
    "sg:city":"Cincinnati",
    "sg:classifiers":[
        {
            "category":"Freight",
            "type":"Transportation"
        }
    ],
    "sg:phone":"+1 513 771 3252",
    "sg:postcode":"45241",
    "sg:province":"OH",
    "sg:tags":[
        "trucking"
    ],
    "wof:name":"Containerport Group Inc",
    "wof:placetype":"venue"
},
  "geometry": {"coordinates":[-84.41729100000001,39.268595],"type":"Point"}
}