{
  "type": "Feature",
  "properties": {
    "addr:full": "6817 Buckingham Ln West Alexandria OH 45381",
    "addr:housenumber": "6817",
    "addr:postcode": "45381",
    "addr:street": "Buckingham Ln",
    "iso:country": "US",
    "sg:address": "6817 Buckingham Ln",
    "sg:city": "West Alexandria",
    "sg:classifiers": [
      {
        "category": "Real Estate",
        "subcategory": "Real Estate Operator",
        "type": "Services"
      }
    ],
    "sg:phone": "+1 937 839 4437",
    "sg:postcode": "45381",
    "sg:province": "OH",
    "sg:tags": [
      "property",
      "lessor"
    ],
    "wof:name": "Jane Buckingham Farm",
    "wof:placetype": "venue"
  },
  "geometry": {"coordinates":[-84.520046,39.748367],"type":"Point"}
}
