{
  "type": "Feature",
  "properties": {
    "iso:country":"US",
    "sg:address":"6817 Buckingham Ln",
    "sg:city":"West Alexandria",
    "sg:classifiers":[
        {
            "category":"Real Estate",
            "subcategory":"Real Estate Operator",
            "type":"Services"
        }
    ],
    "sg:phone":"+1 937 839 4437",
    "sg:postcode":"45381",
    "sg:province":"OH",
    "sg:tags":[
        "property",
        "lessor"
    ],
    "wof:name":"Jane Buckingham Farm",
    "wof:placetype":"venue"
},
  "geometry": {"coordinates":[-84.52004599999999,39.748367],"type":"Point"}
}