{
  "type": "Feature",
  "properties": {
    "addr:full": "924 Gallia St Portsmouth OH 45662",
    "addr:housenumber": "924",
    "addr:postcode": "45662",
    "addr:street": "Gallia St",
    "iso:country": "US",
    "sg:address": "924 Gallia St",
    "sg:city": "Portsmouth",
    "sg:classifiers": [
      {
        "category": "Banks \u0026 Credit Unions",
        "subcategory": "Bank",
        "type": "Services"
      }
    ],
    "sg:phone": "+1 740 353 2698",
    "sg:postcode": "45662",
    "sg:province": "OH",
    "wof:name": "Oak Hill Banks",
    "wof:placetype": "venue"
  },
  "geometry": {"coordinates":[-82.994096,38.734127],"type":"Point"}
}
