{
  "type": "Feature",
  "properties": {
    "addr:full": "254 Canton Rd Steubenville OH 43953",
    "addr:housenumber": "254",
    "addr:postcode": "43953",
    "addr:street": "Canton Rd",
    "iso:country": "US",
    "sg:address": "254 Canton Rd",
    "sg:city": "Steubenville",
    "sg:classifiers": [
      {
        "category": "Freight",
        "type": "Transportation"
      }
    ],
    "sg:phone": "+1 740 769 2303",
    "sg:postcode": "43953",
    "sg:province": "OH",
    "sg:tags": [
      "local",
      "landscaper",
      "trucking"
    ],
    "wof:name": "Novacks Gardenscaping \u0026 Grnhse",
    "wof:placetype": "venue"
  },
  "geometry": {"coordinates":[-80.705961,40.37965],"type":"Point"}
}
