{
  "type": "Feature",
  "properties": {
    "addr:full": "5166 Spanson Dr SE Uhrichsville OH 44683",
    "addr:housenumber": "5166",
    "addr:postcode": "44683",
    "addr:street": "Spanson Dr Se",
    "iso:country": "US",
    "sg:address": "5166 Spanson Dr SE",
    "sg:city": "Uhrichsville",
    "sg:classifiers": [
      {
        "category": "Health Services",
        "subcategory": "Nursing And Care Facility",
        "type": "Services"
      }
    ],
    "sg:phone": "+1 740 922 2208",
    "sg:postcode": "44683",
    "sg:province": "OH",
    "sg:tags": [
      "home"
    ],
    "wof:name": "Beacon Point Rehab",
    "wof:placetype": "venue"
  },
  "geometry": {"coordinates":[-81.367794,40.395324],"type":"Point"}
}
