{
  "type": "Feature",
  "properties": {
    "iso:country":"US",
    "sg:address":"1761 Tennessee Ave",
    "sg:city":"Cincinnati",
    "sg:classifiers":[
        {
            "category":"Manufacturing",
            "subcategory":"Chemicals & Compounds",
            "type":"Manufacturing & Wholesale Goods"
        }
    ],
    "sg:phone":"+1 513 861 2329",
    "sg:postcode":"45229",
    "sg:province":"OH",
    "sg:tags":[
        "miller",
        "drug"
    ],
    "wof:name":"Ziks Nnodum",
    "wof:placetype":"venue"
},
  "geometry": {"coordinates":[-84.466351,39.167215],"type":"Point"}
}