{
  "type": "Feature",
  "properties": {
    "iso:country":"US",
    "sg:address":"5580 Cypress Rd",
    "sg:city":"Thornville",
    "sg:classifiers":[
        {
            "category":"Manufacturing",
            "subcategory":"Textiles",
            "type":"Manufacturing & Wholesale Goods"
        }
    ],
    "sg:phone":"+1 740 246 6261",
    "sg:postcode":"43076",
    "sg:province":"OH",
    "sg:tags":[
        "mfg"
    ],
    "wof:name":"Patrick Walsh",
    "wof:placetype":"venue"
},
  "geometry": {"coordinates":[-82.47371099999999,39.915485],"type":"Point"}
}