{
  "type": "Feature",
  "properties": {
    "addr:full": "14428 US Hwy 127 New Weston OH 45348",
    "addr:housenumber": "14428",
    "addr:postcode": "45348",
    "addr:street": "Us Hwy 127",
    "iso:country": "US",
    "sg:address": "14428 US Hwy 127",
    "sg:city": "New Weston",
    "sg:classifiers": [
      {
        "category": "Food \u0026 Beverages",
        "subcategory": "Groceries \u0026 Convenience Stores",
        "type": "Retail Goods"
      }
    ],
    "sg:phone": "+1 419 336 5008",
    "sg:postcode": "45348",
    "sg:province": "OH",
    "wof:name": "Pak A Sak",
    "wof:placetype": "venue"
  },
  "geometry": {"coordinates":[-84.571314,40.338098],"type":"Point"}
}
