{
  "type": "Feature",
  "properties": {
    "iso:country":"US",
    "sg:address":"14428 US Hwy 127",
    "sg:city":"New Weston",
    "sg:classifiers":[
        {
            "category":"Food & Beverages",
            "subcategory":"Groceries & Convenience Stores",
            "type":"Retail Goods"
        }
    ],
    "sg:phone":"+1 419 336 5008",
    "sg:postcode":"45348",
    "sg:province":"OH",
    "wof:name":"Pak A Sak",
    "wof:placetype":"venue"
},
  "geometry": {"coordinates":[-84.571314,40.338098],"type":"Point"}
}