{
  "type": "Feature",
  "properties": {
    "iso:country":"US",
    "sg:address":"21170 Ellacott Pkwy",
    "sg:city":"Cleveland",
    "sg:classifiers":[
        {
            "category":"Real Estate",
            "subcategory":"Real Estate Operator",
            "type":"Services"
        }
    ],
    "sg:phone":"+1 216 662 9222",
    "sg:postcode":"44128",
    "sg:province":"OH",
    "sg:tags":[
        "apartment"
    ],
    "sg:website":"www.ellacottparkway.com",
    "wof:name":"Ellacott Parkway Apts",
    "wof:placetype":"venue"
},
  "geometry": {"coordinates":[-81.53208100000001,41.441462],"type":"Point"}
}