{
  "type": "Feature",
  "properties": {
    "iso:country":"US",
    "sg:address":"1459 Mentor Ave",
    "sg:city":"Painesville",
    "sg:classifiers":[
        {
            "category":"Home & Garden",
            "subcategory":"Building Materials",
            "type":"Retail Goods"
        }
    ],
    "sg:phone":"+1 440 946 3731",
    "sg:postcode":"44077",
    "sg:province":"OH",
    "sg:tags":[
        "farm",
        "paint",
        "supply"
    ],
    "wof:name":"Sherwin-Williams Paints",
    "wof:placetype":"venue"
},
  "geometry": {"coordinates":[-81.275019,41.701222],"type":"Point"}
}