{
  "type": "Feature",
  "properties": {
    "addr:full":"65515 Larrick Ridge Rd Cambridge OH 43725",
    "addr:postcode":"65515;43725",
    "addr:street":"Larrick Ridge Rd",
    "iso:country":"US",
    "sg:address":"65515 Larrick Ridge Rd",
    "sg:city":"Cambridge",
    "sg:classifiers":[
        {
            "category":"Professional",
            "type":"Services"
        }
    ],
    "sg:phone":"+1 740 435 9570",
    "sg:postcode":"43725",
    "sg:province":"OH",
    "wof:name":"Shirley A Kenney",
    "wof:placetype":"venue"
},
  "geometry": {"coordinates":[-81.51812,40.048919],"type":"Point"}
}