{
  "type": "Feature",
  "properties": {
    "addr:full": "542 E 12th St Cincinnati OH 45202",
    "addr:housenumber": "542",
    "addr:postcode": "45202",
    "addr:street": "E 12Th St",
    "iso:country": "US",
    "sg:address": "542 E 12th St",
    "sg:city": "Cincinnati",
    "sg:classifiers": [
      {
        "category": "Real Estate",
        "subcategory": "Architect",
        "type": "Services"
      }
    ],
    "sg:phone": "+1 513 665 4430",
    "sg:postcode": "45202",
    "sg:province": "OH",
    "wof:name": "Vox Architects Plus Builders",
    "wof:placetype": "venue"
  },
  "geometry": {"coordinates":[-84.505581,39.110102],"type":"Point"}
}
