{
  "type": "Feature",
  "properties": {
    "iso:country":"US",
    "sg:address":"542 E 12th St",
    "sg:city":"Cincinnati",
    "sg:classifiers":[
        {
            "category":"Real Estate",
            "subcategory":"Architect",
            "type":"Services"
        }
    ],
    "sg:phone":"+1 513 665 4430",
    "sg:postcode":"45202",
    "sg:province":"OH",
    "wof:name":"Vox Architects Plus Builders",
    "wof:placetype":"venue"
},
  "geometry": {"coordinates":[-84.50558100000001,39.110102],"type":"Point"}
}