{
  "type": "Feature",
  "properties": {
    "addr:full": "5024 Katzenberger Rd Greenville OH 45331",
    "addr:postcode": "5024;45331",
    "addr:street": "Katzenberger Rd",
    "iso:country": "US",
    "sg:address": "5024 Katzenberger Rd",
    "sg:city": "Greenville",
    "sg:classifiers": [
      {
        "category": "Building \u0026 Trades",
        "subcategory": "Construction",
        "type": "Services"
      }
    ],
    "sg:phone": "+1 937 316 5296",
    "sg:postcode": "45331",
    "sg:province": "OH",
    "sg:tags": [
      "contractor"
    ],
    "wof:name": "Scotts Masonary",
    "wof:placetype": "venue"
  },
  "geometry": {"coordinates":[-84.614437,40.087881],"type":"Point"}
}
