{
  "type": "Feature",
  "properties": {
    "iso:country":"US",
    "sg:address":"5024 Katzenberger Rd",
    "sg:city":"Greenville",
    "sg:classifiers":[
        {
            "category":"Building & Trades",
            "subcategory":"Construction",
            "type":"Services"
        }
    ],
    "sg:phone":"+1 937 316 5296",
    "sg:postcode":"45331",
    "sg:province":"OH",
    "sg:tags":[
        "contractor"
    ],
    "wof:name":"Scotts Masonary",
    "wof:placetype":"venue"
},
  "geometry": {"coordinates":[-84.614437,40.087881],"type":"Point"}
}