{
  "type": "Feature",
  "properties": {
    "addr:full":"5905 Green Pointe Dr S Groveport OH 43125",
    "addr:housenumber":"5905",
    "addr:postcode":"43125",
    "addr:street":"Green Pointe Dr S",
    "iso:country":"US",
    "sg:address":"5905 Green Pointe Dr S",
    "sg:city":"Groveport",
    "sg:classifiers":[
        {
            "category":"Wholesale",
            "subcategory":"Machinery & Supplies",
            "type":"Manufacturing & Wholesale Goods"
        }
    ],
    "sg:phone":"+1 614 409 1998",
    "sg:postcode":"43125",
    "sg:province":"OH",
    "sg:tags":[
        "rubber",
        "industrial",
        "mechanical"
    ],
    "wof:name":"Hart Products & Service",
    "wof:placetype":"venue"
},
  "geometry": {"coordinates":[-82.906615,39.846895],"type":"Point"}
}