{
  "type": "Feature",
  "properties": {
    "addr:full": "710 Griswold Rd Elyria OH 44035",
    "addr:housenumber": "710",
    "addr:postcode": "44035",
    "addr:street": "Griswold Rd",
    "iso:country": "US",
    "sg:address": "710 Griswold Rd",
    "sg:city": "Elyria",
    "sg:classifiers": [
      {
        "category": "Autos \u0026 Motor Vehicles",
        "subcategory": "Fuel \u0026 Gas Station",
        "type": "Retail Goods"
      }
    ],
    "sg:phone": "+1 440 324 4915",
    "sg:postcode": "44035",
    "sg:province": "OH",
    "sg:tags": [
      "oil"
    ],
    "wof:name": "Speedway",
    "wof:placetype": "venue"
  },
  "geometry": {"coordinates":[-82.120807,41.400331],"type":"Point"}
}
