{
  "type": "Feature",
  "properties": {
    "addr:full":"1130 Old Orchard Dr Wauseon OH 43567",
    "addr:housenumber":"1130",
    "addr:postcode":"43567",
    "addr:street":"Old Orchard Dr",
    "iso:country":"US",
    "sg:address":"1130 Old Orchard Dr",
    "sg:city":"Wauseon",
    "sg:classifiers":[
        {
            "category":"Real Estate",
            "subcategory":"Real Estate Agent",
            "type":"Services"
        }
    ],
    "sg:phone":"+1 419 335 7512",
    "sg:postcode":"43567",
    "sg:province":"OH",
    "wof:name":"Leisure Rentals Ltd",
    "wof:placetype":"venue"
},
  "geometry": {"coordinates":[-84.139135,41.561946],"type":"Point"}
}