{
  "type": "Feature",
  "properties": {
    "addr:full":"3225 Pickle Rd Oregon OH 43616",
    "addr:housenumber":"3225",
    "addr:postcode":"43616",
    "addr:street":"Pickle Rd",
    "iso:country":"US",
    "sg:address":"3225 Pickle Rd",
    "sg:city":"Oregon",
    "sg:classifiers":[
        {
            "category":"Education",
            "subcategory":"School",
            "type":"Public Place"
        }
    ],
    "sg:phone":"+1 419 693 0465",
    "sg:postcode":"43616",
    "sg:province":"OH",
    "sg:website":"www.cardinalstritch.org",
    "wof:name":"Cardinal Stritch High School",
    "wof:placetype":"venue"
},
  "geometry": {"coordinates":[-83.474886,41.629675],"type":"Point"}
}