{
  "type": "Feature",
  "properties": {
    "addr:full": "843 N Cleveland Massillon Rd Akron OH 44333",
    "addr:housenumber": "843",
    "addr:postcode": "44333",
    "addr:street": "N Cleveland Massillon Rd",
    "iso:country": "US",
    "sg:address": "843 N Cleveland Massillon Rd",
    "sg:city": "Akron",
    "sg:classifiers": [
      {
        "category": "Retail",
        "subcategory": "Repair Shop",
        "type": "Services"
      },
      {
        "category": "Shopping",
        "subcategory": "Jewelry",
        "type": "Retail Goods"
      }
    ],
    "sg:phone": "+1 330 665 5550",
    "sg:postcode": "44333",
    "sg:province": "OH",
    "wof:name": "Jewellers Shop",
    "wof:placetype": "venue"
  },
  "geometry": {"coordinates":[-81.63684,41.158958],"type":"Point"}
}
