{
  "type": "Feature",
  "properties": {
    "iso:country":"US",
    "sg:address":"2581 3rd St",
    "sg:city":"Syracuse",
    "sg:classifiers":[
        {
            "category":"Government",
            "subcategory":"Office",
            "type":"Public Place"
        }
    ],
    "sg:phone":"+1 740 992 7777",
    "sg:postcode":"45779",
    "sg:province":"OH",
    "sg:tags":[
        "village"
    ],
    "wof:name":"Syracuse Village Office",
    "wof:placetype":"venue"
},
  "geometry": {"coordinates":[-81.97666,38.997302],"type":"Point"}
}