{
  "type": "Feature",
  "properties": {
    "addr:full":"5795 Meadowview Dr Milford OH 45150",
    "addr:housenumber":"5795",
    "addr:postcode":"oh 45150",
    "addr:street":"Meadowview Dr",
    "iso:country":"US",
    "sg:address":"5795 Meadowview Dr",
    "sg:city":"Milford",
    "sg:classifiers":[
        {
            "category":"Farming",
            "subcategory":"Nursery",
            "type":"Manufacturing & Wholesale Goods"
        }
    ],
    "sg:phone":"+1 513 576 1296",
    "sg:postcode":"45150",
    "sg:province":"OH",
    "sg:tags":[
        "ornamental"
    ],
    "wof:name":"Sod Techs Inc",
    "wof:placetype":"venue"
},
  "geometry": {"coordinates":[-84.24470599999999,39.187533],"type":"Point"}
}