{
  "type": "Feature",
  "properties": {
    "addr:full":"8162 Market St Youngstown OH 44512",
    "addr:housenumber":"8162",
    "addr:postcode":"44512",
    "addr:street":"Market St",
    "iso:country":"US",
    "sg:address":"8162 Market St",
    "sg:city":"Youngstown",
    "sg:classifiers":[
        {
            "category":"Retail",
            "subcategory":"Auto Rental",
            "type":"Services"
        }
    ],
    "sg:phone":"+1 330 965 9443",
    "sg:postcode":"44512",
    "sg:province":"OH",
    "sg:tags":[
        "renting",
        "automobile"
    ],
    "wof:name":"Hertz Rent A Car",
    "wof:placetype":"venue"
},
  "geometry": {"coordinates":[-80.66281499999999,41.002855],"type":"Point"}
}