{
  "type": "Feature",
  "properties": {
    "addr:full": "2523 Essex Pl Cincinnati OH 45206",
    "addr:housenumber": "2523",
    "addr:postcode": "45206",
    "addr:street": "Essex Pl",
    "iso:country": "US",
    "sg:address": "2523 Essex Pl",
    "sg:city": "Cincinnati",
    "sg:classifiers": [
      {
        "category": "Manufacturing",
        "subcategory": "Tools \u0026 Machinery",
        "type": "Manufacturing \u0026 Wholesale Goods"
      }
    ],
    "sg:phone": "+1 513 559 9194",
    "sg:postcode": "45206",
    "sg:province": "OH",
    "sg:tags": [
      "machine",
      "shop"
    ],
    "wof:name": "Vulkane LLC",
    "wof:placetype": "venue"
  },
  "geometry": {"coordinates":[-84.498375,39.126453],"type":"Point"}
}
