{
  "type": "Feature",
  "properties": {
    "addr:full": "743 Co Rd 11 Napoleon OH 43545",
    "addr:housenumber": "743;11",
    "addr:postcode": "43545",
    "addr:street": "Co Rd",
    "iso:country": "US",
    "sg:address": "743 Co Rd 11",
    "sg:city": "Napoleon",
    "sg:phone": "+1 419 592 4510",
    "sg:postcode": "43545",
    "sg:province": "OH",
    "sg:tags": [
      "farm",
      "corn",
      "wheat",
      "soybean"
    ],
    "wof:name": "Leon Panning",
    "wof:placetype": "venue"
  },
  "geometry": {"coordinates":[-84.077089,41.367289],"type":"Point"}
}
