{
  "type": "Feature",
  "properties": {
    "addr:full": "439 Springdale Ave Wadsworth OH 44281",
    "addr:housenumber": "439",
    "addr:postcode": "44281",
    "addr:street": "Springdale Ave",
    "iso:country": "US",
    "sg:address": "439 Springdale Ave",
    "sg:city": "Wadsworth",
    "sg:classifiers": [
      {
        "category": "Professional",
        "type": "Services"
      }
    ],
    "sg:phone": "+1 330 336 4040",
    "sg:postcode": "44281",
    "sg:province": "OH",
    "wof:name": "Enviro-Maids LLC",
    "wof:placetype": "venue"
  },
  "geometry": {"coordinates":[-81.718176,41.021873],"type":"Point"}
}
