{
  "type": "Feature",
  "properties": {
    "iso:country":"US",
    "sg:address":"7760 Morley Rd",
    "sg:city":"Mentor",
    "sg:classifiers":[
        {
            "category":"Retail",
            "subcategory":"Animal Services",
            "type":"Services"
        }
    ],
    "sg:phone":"+1 440 352 1485",
    "sg:postcode":"44060",
    "sg:province":"OH",
    "wof:name":"Concord Farms",
    "wof:placetype":"venue"
},
  "geometry": {"coordinates":[-81.274163,41.659894],"type":"Point"}
}