{
  "type": "Feature",
  "properties": {
    "iso:country":"US",
    "sg:address":"1190 Chambers Rd",
    "sg:city":"Columbus",
    "sg:classifiers":[
        {
            "category":"Real Estate",
            "subcategory":"Real Estate Operator",
            "type":"Services"
        }
    ],
    "sg:phone":"+1 614 488 4817",
    "sg:postcode":"43212",
    "sg:province":"OH",
    "sg:tags":[
        "apartment"
    ],
    "sg:website":"www.colonyclubohio.com",
    "wof:name":"Colony Club Apartments",
    "wof:placetype":"venue"
},
  "geometry": {"coordinates":[-83.04236299999999,39.993739],"type":"Point"}
}