{
  "type": "Feature",
  "properties": {
    "iso:country":"US",
    "sg:address":"254 Main St",
    "sg:city":"Byesville",
    "sg:classifiers":[
        {
            "category":"Shopping",
            "subcategory":"Hobbies, Toys, & Games",
            "type":"Retail Goods"
        }
    ],
    "sg:phone":"+1 740 685 8586",
    "sg:postcode":"43723",
    "sg:province":"OH",
    "sg:tags":[
        "model",
        "supply"
    ],
    "wof:name":"Roffee's Hobby Shop",
    "wof:placetype":"venue"
},
  "geometry": {"coordinates":[-81.53727499999999,39.970203],"type":"Point"}
}