{
  "type": "Feature",
  "properties": {
    "addr:full": "200 W Main Cross St Findlay OH 45840",
    "addr:housenumber": "200",
    "addr:postcode": "45840",
    "addr:street": "W Main Cross St",
    "iso:country": "US",
    "sg:address": "200 W Main Cross St",
    "sg:city": "Findlay",
    "sg:classifiers": [
      {
        "category": "Education",
        "subcategory": "School",
        "type": "Public Place"
      }
    ],
    "sg:phone": "+1 419 425 8257",
    "sg:postcode": "45840",
    "sg:province": "OH",
    "wof:name": "Central Middle School",
    "wof:placetype": "venue"
  },
  "geometry": {"coordinates":[-83.65199,41.039156],"type":"Point"}
}
