{
  "type": "Feature",
  "properties": {
    "addr:full": "3111 Glenmore Ave Cincinnati OH 45211",
    "addr:housenumber": "3111",
    "addr:postcode": "45211",
    "addr:street": "Glenmore Ave",
    "iso:country": "US",
    "sg:address": "3111 Glenmore Ave",
    "sg:city": "Cincinnati",
    "sg:classifiers": [
      {
        "category": "Food \u0026 Beverages",
        "subcategory": "Meat \u0026 Fish",
        "type": "Retail Goods"
      }
    ],
    "sg:phone": "+1 513 662 1881",
    "sg:postcode": "45211",
    "sg:province": "OH",
    "wof:name": "Humbert's Meats",
    "wof:placetype": "venue"
  },
  "geometry": {"coordinates":[-84.613534,39.142165],"type":"Point"}
}
