{
  "type": "Feature",
  "properties": {
    "iso:country":"US",
    "sg:address":"3834 Pearl Ave",
    "sg:city":"Lorain",
    "sg:classifiers":[
        {
            "category":"Building & Trades",
            "subcategory":"Construction",
            "type":"Services"
        }
    ],
    "sg:phone":"+1 440 277 5935",
    "sg:postcode":"44055",
    "sg:province":"OH",
    "sg:tags":[
        "waterproofing",
        "contractor"
    ],
    "wof:name":"Logsdon & Sons Inc",
    "wof:placetype":"venue"
},
  "geometry": {"coordinates":[-82.136487,41.434024],"type":"Point"}
}