{
  "type": "Feature",
  "properties": {
    "iso:country":"US",
    "sg:address":"1360 Ontario St",
    "sg:city":"Cleveland",
    "sg:classifiers":[
        {
            "category":"Banks & Credit Unions",
            "subcategory":"Bank",
            "type":"Services"
        }
    ],
    "sg:phone":"+1 216 781 0942",
    "sg:postcode":"44113",
    "sg:province":"OH",
    "sg:website":"http://www.pnc.com",
    "wof:name":"PNC",
    "wof:placetype":"venue"
},
  "geometry": {"coordinates":[-81.69515199999999,41.50135],"type":"Point"}
}