{
  "type": "Feature",
  "properties": {
    "iso:country":"US",
    "sg:address":"4516 Lucerne Ave",
    "sg:city":"Cincinnati",
    "sg:classifiers":[
        {
            "category":"Organizations",
            "subcategory":"Religious Organization",
            "type":"Services"
        }
    ],
    "sg:phone":"+1 513 561 0276",
    "sg:postcode":"45227",
    "sg:province":"OH",
    "sg:tags":[
        "church"
    ],
    "wof:name":"Macedonia Primitive Baptist Ch",
    "wof:placetype":"venue"
},
  "geometry": {"coordinates":[-84.394882,39.155739],"type":"Point"}
}