{
  "type": "Feature",
  "properties": {
    "addr:full": "3227 Church St Cincinnati OH 45244",
    "addr:housenumber": "3227",
    "addr:postcode": "45244",
    "addr:street": "Church St",
    "iso:country": "US",
    "sg:address": "3227 Church St",
    "sg:city": "Cincinnati",
    "sg:classifiers": [
      {
        "category": "Organizations",
        "subcategory": "Religious Organization",
        "type": "Services"
      }
    ],
    "sg:phone": "+1 513 561 9431",
    "sg:postcode": "45244",
    "sg:province": "OH",
    "sg:tags": [
      "place",
      "worship",
      "church"
    ],
    "sg:website": "http://www.mtsm.org",
    "wof:name": "St John Fisher Church",
    "wof:placetype": "venue"
  },
  "geometry": {"coordinates":[-84.365632,39.119224],"type":"Point"}
}
