{
  "type": "Feature",
  "properties": {
    "addr:full": "417 Osage Dr Maumee OH 43537",
    "addr:housenumber": "417",
    "addr:postcode": "43537",
    "addr:street": "Osage Dr",
    "iso:country": "US",
    "sg:address": "417 Osage Dr",
    "sg:city": "Maumee",
    "sg:classifiers": [
      {
        "category": "Manufacturing",
        "subcategory": "Metals",
        "type": "Manufacturing \u0026 Wholesale Goods"
      },
      {
        "category": "Manufacturing",
        "subcategory": "Tools \u0026 Machinery",
        "type": "Manufacturing \u0026 Wholesale Goods"
      }
    ],
    "sg:phone": "+1 419 897 2883",
    "sg:postcode": "43537",
    "sg:province": "OH",
    "sg:tags": [
      "blast",
      "furnace",
      "works"
    ],
    "wof:name": "Frank W Schaefer Inc",
    "wof:placetype": "venue"
  },
  "geometry": {"coordinates":[-83.675201,41.5823],"type":"Point"}
}
