{
  "type": "Feature",
  "properties": {
    "iso:country":"US",
    "sg:address":"417 Osage Dr",
    "sg:city":"Maumee",
    "sg:classifiers":[
        {
            "category":"Manufacturing",
            "subcategory":"Metals",
            "type":"Manufacturing & Wholesale Goods"
        },
        {
            "category":"Manufacturing",
            "subcategory":"Tools & Machinery",
            "type":"Manufacturing & Wholesale Goods"
        }
    ],
    "sg:phone":"+1 419 897 2883",
    "sg:postcode":"43537",
    "sg:province":"OH",
    "sg:tags":[
        "blast",
        "furnace",
        "works"
    ],
    "wof:name":"Frank W Schaefer Inc",
    "wof:placetype":"venue"
},
  "geometry": {"coordinates":[-83.675201,41.5823],"type":"Point"}
}