{
  "type": "Feature",
  "properties": {
    "addr:full":"5202 Mahoning Ave Austintown OH 44515",
    "addr:housenumber":"5202",
    "addr:postcode":"44515",
    "addr:street":"Mahoning Ave",
    "iso:country":"US",
    "sg:address":"5202 Mahoning Ave",
    "sg:city":"Austintown",
    "sg:classifiers":[
        {
            "category":"Autos & Motor Vehicles",
            "subcategory":"Automobile Sales",
            "type":"Retail Goods"
        },
        {
            "category":"Retail",
            "subcategory":"Auto Repair",
            "type":"Services"
        }
    ],
    "sg:phone":"+1 330 270 3649",
    "sg:postcode":"44515",
    "sg:province":"OH",
    "sg:tags":[
        "repairing",
        "car",
        "dealer"
    ],
    "wof:name":"Car Care Connection Inc",
    "wof:placetype":"venue"
},
  "geometry": {"coordinates":[-80.75556899999999,41.099671],"type":"Point"}
}