{
  "type": "Feature",
  "properties": {
    "addr:full":"30 W 11th St Ashland OH 44805",
    "addr:housenumber":"30",
    "addr:postcode":"44805",
    "addr:street":"W 11Th St",
    "iso:country":"US",
    "sg:address":"30 W 11th St",
    "sg:city":"Ashland",
    "sg:classifiers":[
        {
            "category":"Education",
            "subcategory":"School",
            "type":"Public Place"
        }
    ],
    "sg:phone":"+1 419 289 3790",
    "sg:postcode":"44805",
    "sg:province":"OH",
    "wof:name":"Lincoln Elementary School",
    "wof:placetype":"venue"
},
  "geometry": {"coordinates":[-82.316231,40.876936],"type":"Point"}
}