{
  "type": "Feature",
  "properties": {
    "addr:full":"2330 W State St Alliance OH 44601",
    "addr:housenumber":"2330",
    "addr:postcode":"44601",
    "addr:street":"W State St",
    "iso:country":"US",
    "sg:address":"2330 W State St",
    "sg:city":"Alliance",
    "sg:classifiers":[
        {
            "category":"Travel",
            "subcategory":"Hotels & Motels",
            "type":"Entertainment"
        }
    ],
    "sg:phone":"+1 330 821 5688",
    "sg:postcode":"44601",
    "sg:province":"OH",
    "sg:website":"www.super8.com",
    "wof:name":"Super 8 Motel",
    "wof:placetype":"venue"
},
  "geometry": {"coordinates":[-81.14693,40.901871],"type":"Point"}
}