{
  "type": "Feature",
  "properties": {
    "iso:country":"US",
    "sg:address":"628 Dresden Ave ",
    "sg:city":"East Liverpool",
    "sg:classifiers":[
        {
            "category":"Restaurant",
            "type":"Food & Drink"
        }
    ],
    "sg:menulink":"http://www.allmenus.com/oh/east-liverpool/144013-wolf-den-pizza/menu/",
    "sg:phone":"+1 330 386 3330",
    "sg:postcode":"43920",
    "sg:province":"OH",
    "sg:tags":[
        "american",
        "pizza"
    ],
    "wof:name":"Wolf Den Pizza",
    "wof:placetype":"venue"
},
  "geometry": {"coordinates":[-80.58022800000001,40.623381],"type":"Point"}
}