{
  "type": "Feature",
  "properties": {
    "addr:full": "628 Dresden Ave  East Liverpool OH 43920",
    "addr:housenumber": "628",
    "addr:postcode": "43920",
    "addr:street": "Dresden Ave",
    "iso:country": "US",
    "sg:address": "628 Dresden Ave ",
    "sg:city": "East Liverpool",
    "sg:classifiers": [
      {
        "category": "Restaurant",
        "type": "Food \u0026 Drink"
      }
    ],
    "sg:menulink": "http://www.allmenus.com/oh/east-liverpool/144013-wolf-den-pizza/menu/",
    "sg:phone": "+1 330 386 3330",
    "sg:postcode": "43920",
    "sg:province": "OH",
    "sg:tags": [
      "american",
      "pizza"
    ],
    "wof:name": "Wolf Den Pizza",
    "wof:placetype": "venue"
  },
  "geometry": {"coordinates":[-80.580228,40.623381],"type":"Point"}
}
