{
  "type": "Feature",
  "properties": {
    "iso:country":"US",
    "sg:address":"601 Mill St",
    "sg:city":"Cincinnati",
    "sg:classifiers":[
        {
            "category":"Building & Trades",
            "subcategory":"Construction",
            "type":"Services"
        }
    ],
    "sg:phone":"+1 513 679 4211",
    "sg:postcode":"45215",
    "sg:province":"OH",
    "sg:tags":[
        "concrete",
        "contractor"
    ],
    "wof:name":"BND Construction",
    "wof:placetype":"venue"
},
  "geometry": {"coordinates":[-84.452412,39.218672],"type":"Point"}
}