{
  "type": "Feature",
  "properties": {
    "iso:country":"US",
    "sg:address":"701 W High St",
    "sg:city":"Mt Vernon",
    "sg:classifiers":[
        {
            "category":"Health Services",
            "subcategory":"Chiropractor",
            "type":"Services"
        }
    ],
    "sg:phone":"+1 740 393 3107",
    "sg:postcode":"43050",
    "sg:province":"OH",
    "wof:name":"Advantage Health & Rehab Ctr",
    "wof:placetype":"venue"
},
  "geometry": {"coordinates":[-82.495361,40.394087],"type":"Point"}
}