{
  "type": "Feature",
  "properties": {
    "addr:full": "701 W High St Mt Vernon OH 43050",
    "addr:housenumber": "701",
    "addr:postcode": "43050",
    "addr:street": "W High St",
    "iso:country": "US",
    "sg:address": "701 W High St",
    "sg:city": "Mt Vernon",
    "sg:classifiers": [
      {
        "category": "Health Services",
        "subcategory": "Chiropractor",
        "type": "Services"
      }
    ],
    "sg:phone": "+1 740 393 3107",
    "sg:postcode": "43050",
    "sg:province": "OH",
    "wof:name": "Advantage Health \u0026 Rehab Ctr",
    "wof:placetype": "venue"
  },
  "geometry": {"coordinates":[-82.495361,40.394087],"type":"Point"}
}
