{
  "type": "Feature",
  "properties": {
    "addr:full": "108 S Morningside Dr Port Clinton OH 43452",
    "addr:housenumber": "108",
    "addr:postcode": "43452",
    "addr:street": "S Morningside Dr",
    "iso:country": "US",
    "sg:address": "108 S Morningside Dr",
    "sg:city": "Port Clinton",
    "sg:classifiers": [
      {
        "category": "Shopping",
        "subcategory": "Optical Goods",
        "type": "Retail Goods"
      }
    ],
    "sg:phone": "+1 419 734 5310",
    "sg:postcode": "43452",
    "sg:province": "OH",
    "wof:name": "Eye Deal Charters",
    "wof:placetype": "venue"
  },
  "geometry": {"coordinates":[-82.91662,41.509929],"type":"Point"}
}
