{
  "type": "Feature",
  "properties": {
    "addr:full":"723 Delaware St Washington Ct Hs OH 43160",
    "addr:housenumber":"723",
    "addr:postcode":"43160",
    "addr:street":"Delaware St",
    "iso:country":"US",
    "sg:address":"723 Delaware St",
    "sg:city":"Washington Ct Hs",
    "sg:classifiers":[
        {
            "category":"Organizations",
            "subcategory":"Professional Association",
            "type":"Services"
        }
    ],
    "sg:phone":"+1 740 335 4868",
    "sg:postcode":"43160",
    "sg:province":"OH",
    "wof:name":"Senior Citizens Inc",
    "wof:placetype":"venue"
},
  "geometry": {"coordinates":[-83.440003,39.545927],"type":"Point"}
}