{
  "type": "Feature",
  "properties": {
    "addr:full": "11111 Detroit Ave Cleveland OH 44102",
    "addr:housenumber": "11111",
    "addr:postcode": "44102",
    "addr:street": "Detroit Ave",
    "iso:country": "US",
    "sg:address": "11111 Detroit Ave",
    "sg:city": "Cleveland",
    "sg:classifiers": [
      {
        "category": "Building \u0026 Trades",
        "subcategory": "Construction",
        "type": "Services"
      }
    ],
    "sg:phone": "+1 216 221 1284",
    "sg:postcode": "44102",
    "sg:province": "OH",
    "sg:tags": [
      "house",
      "industrial",
      "co"
    ],
    "wof:name": "Bentley Restoration and Rmdlg",
    "wof:placetype": "venue"
  },
  "geometry": {"coordinates":[-81.764833,41.482529],"type":"Point"}
}
