{
  "type": "Feature",
  "properties": {
    "addr:full": "1610 W Market St Akron OH 44313",
    "addr:housenumber": "1610",
    "addr:postcode": "44313",
    "addr:street": "W Market St",
    "iso:country": "US",
    "sg:address": "1610 W Market St",
    "sg:city": "Akron",
    "sg:classifiers": [
      {
        "category": "Retail",
        "subcategory": "Repair Shop",
        "type": "Services"
      }
    ],
    "sg:phone": "+1 330 836 0091",
    "sg:postcode": "44313",
    "sg:province": "OH",
    "sg:tags": [
      "television",
      "radio"
    ],
    "wof:name": "Portage Electronics",
    "wof:placetype": "venue"
  },
  "geometry": {"coordinates":[-81.568831,41.109212],"type":"Point"}
}
