{
  "type": "Feature",
  "properties": {
    "iso:country":"US",
    "sg:address":"2195 Victory Pkwy",
    "sg:city":"Cincinnati",
    "sg:classifiers":[
        {
            "category":"Professional",
            "subcategory":"Art Services",
            "type":"Services"
        }
    ],
    "sg:phone":"+1 513 861 3000",
    "sg:postcode":"45206",
    "sg:province":"OH",
    "sg:tags":[
        "artist"
    ],
    "wof:name":"Colophon",
    "wof:placetype":"venue"
},
  "geometry": {"coordinates":[-84.486756,39.120234],"type":"Point"}
}