{
  "type": "Feature",
  "properties": {
    "addr:full":"1722 N Limestone St Springfield OH 45503",
    "addr:housenumber":"1722",
    "addr:postcode":"45503",
    "addr:street":"N Limestone St",
    "iso:country":"US",
    "sg:address":"1722 N Limestone St",
    "sg:city":"Springfield",
    "sg:classifiers":[
        {
            "category":"Home & Garden",
            "subcategory":"Building Materials",
            "type":"Retail Goods"
        }
    ],
    "sg:phone":"+1 937 390 3680",
    "sg:postcode":"45503",
    "sg:province":"OH",
    "sg:tags":[
        "paint"
    ],
    "wof:name":"Mab Paints",
    "wof:placetype":"venue"
},
  "geometry": {"coordinates":[-83.80464499999999,39.945377],"type":"Point"}
}