{
  "type": "Feature",
  "properties": {
    "addr:full":"42 W 2nd St Chillicothe OH 45601",
    "addr:housenumber":"42",
    "addr:postcode":"45601",
    "addr:street":"W 2Nd St",
    "iso:country":"US",
    "sg:address":"42 W 2nd St",
    "sg:city":"Chillicothe",
    "sg:classifiers":[
        {
            "category":"Organizations",
            "subcategory":"Community Association",
            "type":"Services"
        }
    ],
    "sg:phone":"+1 740 773 2310",
    "sg:postcode":"45601",
    "sg:province":"OH",
    "sg:tags":[
        "fraternal"
    ],
    "wof:name":"Elks Lodge",
    "wof:placetype":"venue"
},
  "geometry": {"coordinates":[-82.983644,39.334252],"type":"Point"}
}