{
  "type": "Feature",
  "properties": {
    "addr:full":"231 Mc Kinley Ave NW Canton OH 44702",
    "addr:housenumber":"231",
    "addr:postcode":"44702",
    "addr:street":"Mc Kinley Ave Nw",
    "iso:country":"US",
    "sg:address":"231 Mc Kinley Ave NW",
    "sg:city":"Canton",
    "sg:classifiers":[
        {
            "category":"Social Services",
            "type":"Services"
        }
    ],
    "sg:phone":"+1 330 456 0124",
    "sg:postcode":"44702",
    "sg:province":"OH",
    "sg:tags":[
        "counseling"
    ],
    "wof:name":"Rainbow Pastoral Counseling",
    "wof:placetype":"venue"
},
  "geometry": {"coordinates":[-81.37795199999999,40.800382],"type":"Point"}
}