{
  "type": "Feature",
  "properties": {
    "addr:full":"806 Ohio Pike Cincinnati OH 45245",
    "addr:housenumber":"806",
    "addr:postcode":"45245",
    "addr:street":"Ohio Pike",
    "iso:country":"US",
    "sg:address":"806 Ohio Pike",
    "sg:city":"Cincinnati",
    "sg:classifiers":[
        {
            "category":"Shopping",
            "subcategory":"Bicycles & Sporting Goods",
            "type":"Retail Goods"
        }
    ],
    "sg:phone":"+1 513 752 3512",
    "sg:postcode":"45245",
    "sg:province":"OH",
    "wof:name":"Eastside Sports",
    "wof:placetype":"venue"
},
  "geometry": {"coordinates":[-84.280502,39.064602],"type":"Point"}
}