{
  "type": "Feature",
  "properties": {
    "addr:full": "328 E Kibby St Lima OH 45804",
    "addr:housenumber": "328",
    "addr:postcode": "45804",
    "addr:street": "E Kibby St",
    "iso:country": "US",
    "sg:address": "328 E Kibby St",
    "sg:city": "Lima",
    "sg:classifiers": [
      {
        "category": "Building \u0026 Trades",
        "subcategory": "Construction",
        "type": "Services"
      }
    ],
    "sg:phone": "+1 419 227 8646",
    "sg:postcode": "45804",
    "sg:province": "OH",
    "sg:tags": [
      "general",
      "contractor"
    ],
    "wof:name": "Quoin Enterprises \u0026 Devmnt",
    "wof:placetype": "venue"
  },
  "geometry": {"coordinates":[-84.100462,40.730329],"type":"Point"}
}
