{
  "type": "Feature",
  "properties": {
    "addr:full": "2450 Dryden Rd Dayton OH 45439",
    "addr:housenumber": "2450",
    "addr:postcode": "45439",
    "addr:street": "Dryden Rd",
    "iso:country": "US",
    "sg:address": "2450 Dryden Rd",
    "sg:city": "Dayton",
    "sg:classifiers": [
      {
        "category": "Travel",
        "subcategory": "Hotels \u0026 Motels",
        "type": "Entertainment"
      }
    ],
    "sg:phone": "+1 937 298 0380",
    "sg:postcode": "45439",
    "sg:province": "OH",
    "sg:tags": [
      "operation"
    ],
    "wof:name": "Super 8 Motel",
    "wof:placetype": "venue"
  },
  "geometry": {"coordinates":[-84.217622,39.721517],"type":"Point"}
}
