{
  "type": "Feature",
  "properties": {
    "addr:full": "955 Curtis St Cincinnati OH 45206",
    "addr:housenumber": "955",
    "addr:postcode": "45206",
    "addr:street": "Curtis St",
    "iso:country": "US",
    "sg:address": "955 Curtis St",
    "sg:city": "Cincinnati",
    "sg:classifiers": [
      {
        "category": "Manufacturing",
        "subcategory": "Rubber \u0026 Plastics",
        "type": "Manufacturing \u0026 Wholesale Goods"
      }
    ],
    "sg:phone": "+1 513 541 4591",
    "sg:postcode": "45206",
    "sg:province": "OH",
    "sg:tags": [
      "product",
      "mfg",
      "fixture",
      "material",
      "commercial",
      "equipment",
      "display"
    ],
    "wof:name": "Starks Plastics",
    "wof:placetype": "venue"
  },
  "geometry": {"coordinates":[-84.488277,39.125098],"type":"Point"}
}
