{
  "type": "Feature",
  "properties": {
    "iso:country":"US",
    "sg:address":"955 Curtis St",
    "sg:city":"Cincinnati",
    "sg:classifiers":[
        {
            "category":"Manufacturing",
            "subcategory":"Rubber & Plastics",
            "type":"Manufacturing & Wholesale Goods"
        }
    ],
    "sg:phone":"+1 513 541 4591",
    "sg:postcode":"45206",
    "sg:province":"OH",
    "sg:tags":[
        "product",
        "mfg",
        "fixture",
        "material",
        "commercial",
        "equipment",
        "display"
    ],
    "wof:name":"Starks Plastics",
    "wof:placetype":"venue"
},
  "geometry": {"coordinates":[-84.488277,39.125098],"type":"Point"}
}