{
  "type": "Feature",
  "properties": {
    "addr:full": "2647 Mount Vernon Rd Newark OH 43055",
    "addr:housenumber": "2647",
    "addr:postcode": "43055",
    "addr:street": "Mount Vernon Rd",
    "iso:country": "US",
    "sg:address": "2647 Mount Vernon Rd",
    "sg:city": "Newark",
    "sg:classifiers": [
      {
        "category": "Autos \u0026 Motor Vehicles",
        "subcategory": "Automobile Sales",
        "type": "Retail Goods"
      }
    ],
    "sg:phone": "+1 740 745 2336",
    "sg:postcode": "43055",
    "sg:province": "OH",
    "sg:tags": [
      "car",
      "used",
      "dealer"
    ],
    "wof:name": "Fred's Used Cars",
    "wof:placetype": "venue"
  },
  "geometry": {"coordinates":[-82.428969,40.127435],"type":"Point"}
}
