{
  "type": "Feature",
  "properties": {
    "iso:country":"US",
    "sg:address":"395 Lantz Rd",
    "sg:city":"Mansfield",
    "sg:classifiers":[
        {
            "category":"Organizations",
            "subcategory":"Membership Organization",
            "type":"Services"
        }
    ],
    "sg:phone":"+1 419 774 4795",
    "sg:postcode":"44906",
    "sg:province":"OH",
    "sg:tags":[
        "society",
        "humane"
    ],
    "sg:website":"www.adoptourstrays.com",
    "wof:name":"Richland County Humane Society",
    "wof:placetype":"venue"
},
  "geometry": {"coordinates":[-82.564751,40.784977],"type":"Point"}
}