{
  "type": "Feature",
  "properties": {
    "addr:full":"845 East Ave Hamilton OH 45011",
    "addr:housenumber":"845",
    "addr:postcode":"45011",
    "addr:street":"East Ave",
    "iso:country":"US",
    "sg:address":"845 East Ave",
    "sg:city":"Hamilton",
    "sg:classifiers":[
        {
            "category":"Freight",
            "type":"Transportation"
        }
    ],
    "sg:phone":"+1 513 896 5234",
    "sg:postcode":"45011",
    "sg:province":"OH",
    "sg:tags":[
        "general"
    ],
    "wof:name":"3-D Distributing",
    "wof:placetype":"venue"
},
  "geometry": {"coordinates":[-84.553557,39.386752],"type":"Point"}
}