{
  "type": "Feature",
  "properties": {
    "addr:full": "14957 Snow Rd Cleveland OH 44142",
    "addr:housenumber": "14957",
    "addr:postcode": "44142",
    "addr:street": "Snow Rd",
    "iso:country": "US",
    "sg:address": "14957 Snow Rd",
    "sg:city": "Cleveland",
    "sg:classifiers": [
      {
        "category": "Restaurant",
        "type": "Food \u0026 Drink"
      }
    ],
    "sg:phone": "+1 216 267 5573",
    "sg:postcode": "44142",
    "sg:province": "OH",
    "wof:name": "Garden Restaurant",
    "wof:placetype": "venue"
  },
  "geometry": {"coordinates":[-81.80357,41.403743],"type":"Point"}
}
