{
  "type": "Feature",
  "properties": {
    "iso:country":"US",
    "sg:address":"14957 Snow Rd",
    "sg:city":"Cleveland",
    "sg:classifiers":[
        {
            "category":"Restaurant",
            "type":"Food & Drink"
        }
    ],
    "sg:phone":"+1 216 267 5573",
    "sg:postcode":"44142",
    "sg:province":"OH",
    "wof:name":"Garden Restaurant",
    "wof:placetype":"venue"
},
  "geometry": {"coordinates":[-81.80356999999999,41.403743],"type":"Point"}
}