{
  "type": "Feature",
  "properties": {
    "addr:full": "7111 Bachman Rd Sardinia OH 45167",
    "addr:housenumber": "7111",
    "addr:postcode": "45167",
    "addr:street": "Bachman Rd",
    "iso:country": "US",
    "sg:address": "7111 Bachman Rd",
    "sg:city": "Sardinia",
    "sg:classifiers": [
      {
        "category": "Food \u0026 Beverages",
        "subcategory": "Groceries \u0026 Convenience Stores",
        "type": "Retail Goods"
      }
    ],
    "sg:phone": "+1 937 446 3008",
    "sg:postcode": "45167",
    "sg:province": "OH",
    "wof:name": "Sardinia First Stop",
    "wof:placetype": "venue"
  },
  "geometry": {"coordinates":[-83.808574,39.013647],"type":"Point"}
}
