{
  "type": "Feature",
  "properties": {
    "iso:country":"US",
    "sg:address":"7111 Bachman Rd",
    "sg:city":"Sardinia",
    "sg:classifiers":[
        {
            "category":"Food & Beverages",
            "subcategory":"Groceries & Convenience Stores",
            "type":"Retail Goods"
        }
    ],
    "sg:phone":"+1 937 446 3008",
    "sg:postcode":"45167",
    "sg:province":"OH",
    "wof:name":"Sardinia First Stop",
    "wof:placetype":"venue"
},
  "geometry": {"coordinates":[-83.80857399999999,39.013647],"type":"Point"}
}