{
  "type": "Feature",
  "properties": {
    "addr:full":"1056 Rd I Mc Comb OH 45856",
    "addr:housenumber":"1056",
    "addr:postcode":"45856",
    "addr:street":"Rd;Mc",
    "iso:country":"US",
    "sg:address":"1056 Rd I",
    "sg:city":"Mc Comb",
    "sg:classifiers":[
        {
            "category":"Farming",
            "subcategory":"Farm",
            "type":"Manufacturing & Wholesale Goods"
        }
    ],
    "sg:phone":"+1 419 943 3163",
    "sg:postcode":"45856",
    "sg:province":"OH",
    "sg:tags":[
        "crop",
        "general"
    ],
    "wof:name":"Stevenson Dorvan",
    "wof:placetype":"venue"
},
  "geometry": {"coordinates":[-83.892039,41.051294],"type":"Point"}
}