{
  "type": "Feature",
  "properties": {
    "addr:full": "2208 E 103rd St Cleveland OH 44106",
    "addr:housenumber": "2208",
    "addr:postcode": "44106",
    "addr:street": "E 103Rd St",
    "iso:country": "US",
    "sg:address": "2208 E 103rd St",
    "sg:city": "Cleveland",
    "sg:classifiers": [
      {
        "category": "Travel",
        "subcategory": "Travel Agent",
        "type": "Entertainment"
      }
    ],
    "sg:phone": "+1 216 721 4125",
    "sg:postcode": "44106",
    "sg:province": "OH",
    "sg:tags": [
      "operator",
      "tour"
    ],
    "wof:name": "Glenn Brakens",
    "wof:placetype": "venue"
  },
  "geometry": {"coordinates":[-81.616366,41.49927],"type":"Point"}
}
