{
  "type": "Feature",
  "properties": {
    "addr:full": "2204 East Ave Akron OH 44314",
    "addr:housenumber": "2204",
    "addr:postcode": "44314",
    "addr:street": "East Ave",
    "iso:country": "US",
    "sg:address": "2204 East Ave",
    "sg:city": "Akron",
    "sg:classifiers": [
      {
        "category": "Personal",
        "subcategory": "Beauty Salon",
        "type": "Services"
      }
    ],
    "sg:phone": "+1 330 745 1551",
    "sg:postcode": "44314",
    "sg:province": "OH",
    "wof:name": "Permanent Solutions",
    "wof:placetype": "venue"
  },
  "geometry": {"coordinates":[-81.572593,41.043678],"type":"Point"}
}
