{
  "type": "Feature",
  "properties": {
    "iso:country":"US",
    "sg:address":"2204 East Ave",
    "sg:city":"Akron",
    "sg:classifiers":[
        {
            "category":"Personal",
            "subcategory":"Beauty Salon",
            "type":"Services"
        }
    ],
    "sg:phone":"+1 330 745 1551",
    "sg:postcode":"44314",
    "sg:province":"OH",
    "wof:name":"Permanent Solutions",
    "wof:placetype":"venue"
},
  "geometry": {"coordinates":[-81.572593,41.043678],"type":"Point"}
}