{
  "type": "Feature",
  "properties": {
    "addr:full":"8570 W Pine Lake Rd Salem OH 44460",
    "addr:housenumber":"8570",
    "addr:postcode":"44460",
    "addr:street":"W Pine Lake Rd",
    "iso:country":"US",
    "sg:address":"8570 W Pine Lake Rd",
    "sg:city":"Salem",
    "sg:classifiers":[
        {
            "category":"Wholesale",
            "subcategory":"Furniture",
            "type":"Manufacturing & Wholesale Goods"
        }
    ],
    "sg:phone":"+1 330 533 9986",
    "sg:postcode":"44460",
    "sg:province":"OH",
    "wof:name":"Blue Furniture Barn",
    "wof:placetype":"venue"
},
  "geometry": {"coordinates":[-80.81250900000001,40.929815],"type":"Point"}
}