{
  "type": "Feature",
  "properties": {
    "addr:full":"1465 Osborn Dr Columbus OH 43221",
    "addr:housenumber":"1465",
    "addr:postcode":"43221",
    "addr:street":"Osborn Dr",
    "iso:country":"US",
    "sg:address":"1465 Osborn Dr",
    "sg:city":"Columbus",
    "sg:classifiers":[
        {
            "category":"Education",
            "subcategory":"Library",
            "type":"Public Place"
        }
    ],
    "sg:phone":"+1 614 486 5028",
    "sg:postcode":"43221",
    "sg:province":"OH",
    "sg:tags":[
        "special",
        "interest"
    ],
    "wof:name":"Irene Holm Memorial Library",
    "wof:placetype":"venue"
},
  "geometry": {"coordinates":[-83.049661,40.008291],"type":"Point"}
}