{
  "type": "Feature",
  "properties": {
    "addr:full":"10235 Spartan Dr Cincinnati OH 45215",
    "addr:housenumber":"10235",
    "addr:postcode":"45215",
    "addr:street":"Spartan Dr",
    "iso:country":"US",
    "sg:address":"10235 Spartan Dr",
    "sg:city":"Cincinnati",
    "sg:classifiers":[
        {
            "category":"Home & Garden",
            "subcategory":"Home Furnishings",
            "type":"Retail Goods"
        }
    ],
    "sg:phone":"+1 513 772 8868",
    "sg:postcode":"45215",
    "sg:province":"OH",
    "sg:tags":[
        "shelving",
        "furniture"
    ],
    "wof:name":"Closet Concepts Inc",
    "wof:placetype":"venue"
},
  "geometry": {"coordinates":[-84.449837,39.254361],"type":"Point"}
}