{
  "type": "Feature",
  "properties": {
    "addr:full": "1171 N Broad St Fairborn OH 45324",
    "addr:housenumber": "1171",
    "addr:postcode": "45324",
    "addr:street": "N Broad St",
    "iso:country": "US",
    "sg:address": "1171 N Broad St",
    "sg:city": "Fairborn",
    "sg:classifiers": [
      {
        "category": "Autos \u0026 Motor Vehicles",
        "subcategory": "Fuel \u0026 Gas Station",
        "type": "Retail Goods"
      }
    ],
    "sg:phone": "+1 937 879 0551",
    "sg:postcode": "45324",
    "sg:province": "OH",
    "sg:tags": [
      "oil"
    ],
    "wof:name": "Speedway",
    "wof:placetype": "venue"
  },
  "geometry": {"coordinates":[-84.015391,39.833664],"type":"Point"}
}
