{
  "type": "Feature",
  "properties": {
    "iso:country":"US",
    "sg:address":"1171 N Broad St",
    "sg:city":"Fairborn",
    "sg:classifiers":[
        {
            "category":"Autos & Motor Vehicles",
            "subcategory":"Fuel & Gas Station",
            "type":"Retail Goods"
        }
    ],
    "sg:phone":"+1 937 879 0551",
    "sg:postcode":"45324",
    "sg:province":"OH",
    "sg:tags":[
        "oil"
    ],
    "wof:name":"Speedway",
    "wof:placetype":"venue"
},
  "geometry": {"coordinates":[-84.015391,39.833664],"type":"Point"}
}