{
  "type": "Feature",
  "properties": {
    "addr:full": "12001 Carrington Ln Loveland OH 45140",
    "addr:housenumber": "12001",
    "addr:postcode": "45140",
    "addr:street": "Carrington Ln",
    "iso:country": "US",
    "sg:address": "12001 Carrington Ln",
    "sg:city": "Loveland",
    "sg:classifiers": [
      {
        "category": "Personal",
        "type": "Services"
      }
    ],
    "sg:phone": "+1 513 677 8222",
    "sg:postcode": "45140",
    "sg:province": "OH",
    "wof:name": "Paws and Claws Pet Sitter",
    "wof:placetype": "venue"
  },
  "geometry": {"coordinates":[-84.298828,39.287271],"type":"Point"}
}
