{
  "type": "Feature",
  "properties": {
    "addr:full": "135 Fir Hill Akron OH 44304",
    "addr:housenumber": "135",
    "addr:postcode": "44304",
    "addr:street": "Fir Hill",
    "iso:country": "US",
    "sg:address": "135 Fir Hill",
    "sg:city": "Akron",
    "sg:classifiers": [
      {
        "category": "Organizations",
        "subcategory": "Religious Organization",
        "type": "Services"
      }
    ],
    "sg:phone": "+1 330 376 6400",
    "sg:postcode": "44304",
    "sg:province": "OH",
    "sg:tags": [
      "church"
    ],
    "sg:website": "www.the-chapel.org",
    "wof:name": "Chapel",
    "wof:placetype": "venue"
  },
  "geometry": {"coordinates":[-81.50718,41.079356],"type":"Point"}
}
