{
  "type": "Feature",
  "properties": {
    "addr:full":"5128 Mallet Club Dr Dayton OH 45439",
    "addr:housenumber":"5128",
    "addr:postcode":"45439",
    "addr:street":"Mallet Club Dr",
    "iso:country":"US",
    "sg:address":"5128 Mallet Club Dr",
    "sg:city":"Dayton",
    "sg:classifiers":[
        {
            "category":"Manufacturing",
            "subcategory":"Rubber & Plastics",
            "type":"Manufacturing & Wholesale Goods"
        }
    ],
    "sg:phone":"+1 937 293 6888",
    "sg:postcode":"45439",
    "sg:province":"OH",
    "sg:tags":[
        "product",
        "fabricated",
        "mfg"
    ],
    "wof:name":"Air Bounce LLC",
    "wof:placetype":"venue"
},
  "geometry": {"coordinates":[-84.20836,39.675526],"type":"Point"}
}