{
  "type": "Feature",
  "properties": {
    "iso:country":"US",
    "sg:address":"2844 Sherman Rd",
    "sg:city":"Portsmouth",
    "sg:classifiers":[
        {
            "category":"Building & Trades",
            "subcategory":"Electrical",
            "type":"Services"
        }
    ],
    "sg:phone":"+1 740 354 3807",
    "sg:postcode":"45662",
    "sg:province":"OH",
    "sg:tags":[
        "electrical",
        "contractor"
    ],
    "wof:name":"Leigh Throckmorton",
    "wof:placetype":"venue"
},
  "geometry": {"coordinates":[-82.98098899999999,38.758081],"type":"Point"}
}