{
  "type": "Feature",
  "properties": {
    "addr:full": "2844 Sherman Rd Portsmouth OH 45662",
    "addr:housenumber": "2844",
    "addr:postcode": "45662",
    "addr:street": "Sherman Rd",
    "iso:country": "US",
    "sg:address": "2844 Sherman Rd",
    "sg:city": "Portsmouth",
    "sg:classifiers": [
      {
        "category": "Building \u0026 Trades",
        "subcategory": "Electrical",
        "type": "Services"
      }
    ],
    "sg:phone": "+1 740 354 3807",
    "sg:postcode": "45662",
    "sg:province": "OH",
    "sg:tags": [
      "electrical",
      "contractor"
    ],
    "wof:name": "Leigh Throckmorton",
    "wof:placetype": "venue"
  },
  "geometry": {"coordinates":[-82.980989,38.758081],"type":"Point"}
}
