{
  "type": "Feature",
  "properties": {
    "addr:full": "222 Portland Way N Galion OH 44833",
    "addr:housenumber": "222",
    "addr:postcode": "44833",
    "addr:street": "Portland Way N",
    "iso:country": "US",
    "sg:address": "222 Portland Way N",
    "sg:city": "Galion",
    "sg:classifiers": [
      {
        "category": "Organizations",
        "subcategory": "Membership Organization",
        "type": "Services"
      }
    ],
    "sg:phone": "+1 419 468 1122",
    "sg:postcode": "44833",
    "sg:province": "OH",
    "wof:name": "Galion AAA",
    "wof:placetype": "venue"
  },
  "geometry": {"coordinates":[-82.801952,40.735631],"type":"Point"}
}
