{
  "type": "Feature",
  "properties": {
    "addr:full": "291 E 222nd St Euclid OH 44123",
    "addr:housenumber": "291",
    "addr:postcode": "44123",
    "addr:street": "E 222Nd St",
    "iso:country": "US",
    "sg:address": "291 E 222nd St",
    "sg:city": "Euclid",
    "sg:classifiers": [
      {
        "category": "Personal",
        "type": "Services"
      }
    ],
    "sg:phone": "+1 248 553 8555",
    "sg:postcode": "44123",
    "sg:province": "OH",
    "wof:name": "Weight Watchers",
    "wof:placetype": "venue"
  },
  "geometry": {"coordinates":[-81.526771,41.607695],"type":"Point"}
}
