{
  "type": "Feature",
  "properties": {
    "addr:full":"37 E Granville St New Albany OH 43074",
    "addr:housenumber":"37",
    "addr:postcode":"43074",
    "addr:street":"E Granville St",
    "iso:country":"US",
    "sg:address":"37 E Granville St",
    "sg:city":"New Albany",
    "sg:classifiers":[
        {
            "category":"Banks & Credit Unions",
            "subcategory":"Bank",
            "type":"Services"
        }
    ],
    "sg:phone":"+1 614 939 0825",
    "sg:postcode":"43074",
    "sg:province":"OH",
    "sg:tags":[
        "machine",
        "teller",
        "automated"
    ],
    "wof:name":"ATMUSALLC",
    "wof:placetype":"venue"
},
  "geometry": {"coordinates":[-82.858794,40.241758],"type":"Point"}
}