{
  "type": "Feature",
  "properties": {
    "addr:full":"821 Gallia St Portsmouth OH 45662",
    "addr:housenumber":"821",
    "addr:postcode":"45662",
    "addr:street":"Gallia St",
    "iso:country":"US",
    "sg:address":"821 Gallia St",
    "sg:city":"Portsmouth",
    "sg:classifiers":[
        {
            "category":"Restaurant",
            "type":"Food & Drink"
        }
    ],
    "sg:phone":"+1 740 355 1166",
    "sg:postcode":"45662",
    "sg:province":"OH",
    "sg:tags":[
        "eating"
    ],
    "wof:name":"Dusty Mug",
    "wof:placetype":"venue"
},
  "geometry": {"coordinates":[-82.996222,38.734168],"type":"Point"}
}