{
  "type": "Feature",
  "properties": {
    "addr:full": "1460 State Rte 28 E Greenfield OH 45123",
    "addr:housenumber": "1460",
    "addr:postcode": "45123",
    "addr:street": "State Rte 28 E",
    "iso:country": "US",
    "sg:address": "1460 State Rte 28 E",
    "sg:city": "Greenfield",
    "sg:classifiers": [
      {
        "category": "Shopping",
        "subcategory": "Hobbies, Toys, \u0026 Games",
        "type": "Retail Goods"
      }
    ],
    "sg:phone": "+1 937 981 2422",
    "sg:postcode": "45123",
    "sg:province": "OH",
    "sg:tags": [
      "craft"
    ],
    "wof:name": "Stuck On Scrapppin'",
    "wof:placetype": "venue"
  },
  "geometry": {"coordinates":[-83.348721,39.353209],"type":"Point"}
}
