{
  "type": "Feature",
  "properties": {
    "iso:country":"US",
    "sg:address":"201 E Lincoln St",
    "sg:city":"Findlay",
    "sg:classifiers":[
        {
            "category":"Banks & Credit Unions",
            "subcategory":"Bank",
            "type":"Services"
        }
    ],
    "sg:phone":"+1 419 423 3057",
    "sg:postcode":"45840",
    "sg:province":"OH",
    "sg:website":"www.csbanking.com",
    "wof:name":"Commercial Savings Bank",
    "wof:placetype":"venue"
},
  "geometry": {"coordinates":[-83.64852999999999,41.034365],"type":"Point"}
}