{
  "type": "Feature",
  "properties": {
    "addr:full": "201 E Lincoln St Findlay OH 45840",
    "addr:housenumber": "201",
    "addr:postcode": "45840",
    "addr:street": "E Lincoln St",
    "iso:country": "US",
    "sg:address": "201 E Lincoln St",
    "sg:city": "Findlay",
    "sg:classifiers": [
      {
        "category": "Banks \u0026 Credit Unions",
        "subcategory": "Bank",
        "type": "Services"
      }
    ],
    "sg:phone": "+1 419 423 3057",
    "sg:postcode": "45840",
    "sg:province": "OH",
    "sg:website": "www.csbanking.com",
    "wof:name": "Commercial Savings Bank",
    "wof:placetype": "venue"
  },
  "geometry": {"coordinates":[-83.64853,41.034365],"type":"Point"}
}
