{
  "type": "Feature",
  "properties": {
    "addr:full": "10134 W Ridge Rd Elyria OH 44035",
    "addr:housenumber": "10134",
    "addr:postcode": "44035",
    "addr:street": "W Ridge Rd",
    "iso:country": "US",
    "sg:address": "10134 W Ridge Rd",
    "sg:city": "Elyria",
    "sg:classifiers": [
      {
        "category": "Building \u0026 Trades",
        "subcategory": "Construction",
        "type": "Services"
      }
    ],
    "sg:phone": "+1 440 284 6178",
    "sg:postcode": "44035",
    "sg:province": "OH",
    "sg:tags": [
      "general",
      "contractor"
    ],
    "wof:name": "TRP Construction",
    "wof:placetype": "venue"
  },
  "geometry": {"coordinates":[-82.155163,41.345933],"type":"Point"}
}
