{
  "type": "Feature",
  "properties": {
    "addr:full":"628 Race St Cincinnati OH 45202",
    "addr:housenumber":"628",
    "addr:postcode":"45202",
    "addr:street":"Race St",
    "iso:country":"US",
    "sg:address":"628 Race St",
    "sg:city":"Cincinnati",
    "sg:classifiers":[
        {
            "category":"Shopping",
            "subcategory":"Clothing, Apparel, & Fashions",
            "type":"Retail Goods"
        }
    ],
    "sg:phone":"+1 513 621 6056",
    "sg:postcode":"45202",
    "sg:province":"OH",
    "sg:tags":[
        "electronics",
        "consumer",
        "sportswear"
    ],
    "wof:name":"Chong Co Inc",
    "wof:placetype":"venue"
},
  "geometry": {"coordinates":[-84.515083,39.103108],"type":"Point"}
}