{
  "type": "Feature",
  "properties": {
    "addr:full": "4256 Knapp Dr Grove City OH 43123",
    "addr:housenumber": "4256",
    "addr:postcode": "43123",
    "addr:street": "Knapp Dr",
    "iso:country": "US",
    "sg:address": "4256 Knapp Dr",
    "sg:city": "Grove City",
    "sg:phone": "+1 614 875 3291",
    "sg:postcode": "43123",
    "sg:province": "OH",
    "sg:tags": [
      "farm",
      "corn",
      "soybean"
    ],
    "wof:name": "Weyer Farm",
    "wof:placetype": "venue"
  },
  "geometry": {"coordinates":[-83.071333,39.876723],"type":"Point"}
}
