{
  "type": "Feature",
  "properties": {
    "iso:country":"US",
    "sg:address":"4256 Knapp Dr",
    "sg:city":"Grove City",
    "sg:phone":"+1 614 875 3291",
    "sg:postcode":"43123",
    "sg:province":"OH",
    "sg:tags":[
        "farm",
        "corn",
        "soybean"
    ],
    "wof:name":"Weyer Farm",
    "wof:placetype":"venue"
},
  "geometry": {"coordinates":[-83.071333,39.876723],"type":"Point"}
}