{
  "type": "Feature",
  "properties": {
    "addr:full":"576 Edinborough Dr Cleveland OH 44140",
    "addr:housenumber":"576",
    "addr:postcode":"44140",
    "addr:street":"Edinborough Dr",
    "iso:country":"US",
    "sg:address":"576 Edinborough Dr",
    "sg:city":"Cleveland",
    "sg:classifiers":[
        {
            "category":"Professional",
            "subcategory":"Advertising",
            "type":"Services"
        }
    ],
    "sg:phone":"+1 440 356 3885",
    "sg:postcode":"44140",
    "sg:province":"OH",
    "sg:tags":[
        "counselor"
    ],
    "wof:name":"Auto Ads Inc",
    "wof:placetype":"venue"
},
  "geometry": {"coordinates":[-81.87897,41.478317],"type":"Point"}
}