{
  "type": "Feature",
  "properties": {
    "iso:country":"US",
    "sg:address":"127 W Main St",
    "sg:city":"Hillsboro",
    "sg:classifiers":[
        {
            "category":"Shopping",
            "subcategory":"Shoes",
            "type":"Retail Goods"
        }
    ],
    "sg:phone":"+1 937 393 1202",
    "sg:postcode":"45133",
    "sg:province":"OH",
    "sg:tags":[
        "family"
    ],
    "wof:name":"Shoe Station",
    "wof:placetype":"venue"
},
  "geometry": {"coordinates":[-83.612224,39.202215],"type":"Point"}
}