{
  "type": "Feature",
  "properties": {
    "addr:full":"10525 Harrison Ave Harrison OH 45030",
    "addr:housenumber":"10525",
    "addr:postcode":"45030",
    "addr:street":"Harrison Ave",
    "iso:country":"US",
    "sg:address":"10525 Harrison Ave",
    "sg:city":"Harrison",
    "sg:classifiers":[
        {
            "category":"Shopping",
            "subcategory":"Clothing, Apparel, & Fashions",
            "type":"Retail Goods"
        }
    ],
    "sg:phone":"+1 513 367 1996",
    "sg:postcode":"45030",
    "sg:province":"OH",
    "wof:name":"Fashion Bug",
    "wof:placetype":"venue"
},
  "geometry": {"coordinates":[-84.795351,39.253113],"type":"Point"}
}