{
  "type": "Feature",
  "properties": {
    "iso:country":"US",
    "sg:address":"3770 W Broad St",
    "sg:city":"Columbus",
    "sg:classifiers":[
        {
            "category":"Shopping",
            "subcategory":"Clothing, Apparel, & Fashions",
            "type":"Retail Goods"
        }
    ],
    "sg:phone":"+1 614 577 1300",
    "sg:postcode":"43228",
    "sg:province":"OH",
    "wof:name":"Risque Lingerie",
    "wof:placetype":"venue"
},
  "geometry": {"coordinates":[-83.100329,39.953614],"type":"Point"}
}