{
  "type": "Feature",
  "properties": {
    "iso:country":"US",
    "sg:address":"28 S Broadway St",
    "sg:city":"Lebanon",
    "sg:classifiers":[
        {
            "category":"Shopping",
            "subcategory":"Clothing, Apparel, & Fashions",
            "type":"Retail Goods"
        }
    ],
    "sg:phone":"+1 513 932 9936",
    "sg:postcode":"45036",
    "sg:province":"OH",
    "wof:name":"Fella Bell A Shop",
    "wof:placetype":"venue"
},
  "geometry": {"coordinates":[-84.208254,39.433685],"type":"Point"}
}