{
  "type": "Feature",
  "properties": {
    "addr:full": "7135 S Co Rd 25A Tipp City OH 45371",
    "addr:housenumber": "7135;25a",
    "addr:postcode": "45371",
    "addr:street": "S Co Rd",
    "iso:country": "US",
    "sg:address": "7135 S Co Rd 25A",
    "sg:city": "Tipp City",
    "sg:classifiers": [
      {
        "category": "Building \u0026 Trades",
        "subcategory": "Plumbing",
        "type": "Services"
      }
    ],
    "sg:phone": "+1 937 669 4442",
    "sg:postcode": "45371",
    "sg:province": "OH",
    "sg:tags": [
      "contractor"
    ],
    "wof:name": "Garlitz Plumbing",
    "wof:placetype": "venue"
  },
  "geometry": {"coordinates":[-84.198863,39.936351],"type":"Point"}
}
