{
  "type": "Feature",
  "properties": {
    "addr:full": "218 East Ave Elyria OH 44035",
    "addr:housenumber": "218",
    "addr:postcode": "44035",
    "addr:street": "East Ave",
    "iso:country": "US",
    "sg:address": "218 East Ave",
    "sg:city": "Elyria",
    "sg:classifiers": [
      {
        "category": "Organizations",
        "subcategory": "Community Association",
        "type": "Services"
      }
    ],
    "sg:phone": "+1 440 322 0524",
    "sg:postcode": "44035",
    "sg:province": "OH",
    "sg:tags": [
      "club"
    ],
    "wof:name": "Elyria Womans' Club Inc",
    "wof:placetype": "venue"
  },
  "geometry": {"coordinates":[-82.103917,41.365379],"type":"Point"}
}
