{
  "type": "Feature",
  "properties": {
    "addr:full":"15 Triangle Park Dr Cincinnati OH 45246",
    "addr:housenumber":"15",
    "addr:postcode":"45246",
    "addr:street":"Triangle Park Dr",
    "iso:country":"US",
    "sg:address":"15 Triangle Park Dr",
    "sg:city":"Cincinnati",
    "sg:classifiers":[
        {
            "category":"Government",
            "subcategory":"Office",
            "type":"Public Place"
        }
    ],
    "sg:phone":"+1 513 771 4602",
    "sg:postcode":"45246",
    "sg:province":"OH",
    "sg:tags":[
        "station",
        "recruiting"
    ],
    "wof:name":"Recruiting Station Cincinnati",
    "wof:placetype":"venue"
},
  "geometry": {"coordinates":[-84.44664899999999,39.290786],"type":"Point"}
}