{
  "type": "Feature",
  "properties": {
    "iso:country":"US",
    "sg:address":"16910 Twp Hwy 22",
    "sg:city":"Carey",
    "sg:classifiers":[
        {
            "category":"Building & Trades",
            "subcategory":"Construction",
            "type":"Services"
        }
    ],
    "sg:phone":"+1 419 396 7101",
    "sg:postcode":"43316",
    "sg:province":"OH",
    "sg:tags":[
        "heavy"
    ],
    "wof:name":"J and B Blasting Inc",
    "wof:placetype":"venue"
},
  "geometry": {"coordinates":[-83.442545,40.971774],"type":"Point"}
}