{
  "type": "Feature",
  "properties": {
    "addr:full": "25 S Mulberry St Mansfield OH 44902",
    "addr:housenumber": "25",
    "addr:postcode": "44902",
    "addr:street": "S Mulberry St",
    "iso:country": "US",
    "sg:address": "25 S Mulberry St",
    "sg:city": "Mansfield",
    "sg:classifiers": [
      {
        "category": "Personal",
        "subcategory": "Beauty Salon",
        "type": "Services"
      }
    ],
    "sg:phone": "+1 419 525 1050",
    "sg:postcode": "44902",
    "sg:province": "OH",
    "wof:name": "Skin Care \u0026 Beauty Products",
    "wof:placetype": "venue"
  },
  "geometry": {"coordinates":[-82.517973,40.757708],"type":"Point"}
}
