{
  "type": "Feature",
  "properties": {
    "addr:full":"8613 Winton Rd Cincinnati OH 45231",
    "addr:housenumber":"8613",
    "addr:postcode":"45231",
    "addr:street":"Winton Rd",
    "iso:country":"US",
    "sg:address":"8613 Winton Rd",
    "sg:city":"Cincinnati",
    "sg:classifiers":[
        {
            "category":"Wholesale",
            "subcategory":"Painting Supplies",
            "type":"Manufacturing & Wholesale Goods"
        }
    ],
    "sg:phone":"+1 513 729 4511",
    "sg:postcode":"45231",
    "sg:province":"OH",
    "sg:tags":[
        "paint"
    ],
    "wof:name":"Aspery Products",
    "wof:placetype":"venue"
},
  "geometry": {"coordinates":[-84.516256,39.224783],"type":"Point"}
}