{
  "type": "Feature",
  "properties": {
    "addr:full": "631 Meredith Ln Cuyahoga Falls OH 44223",
    "addr:housenumber": "631",
    "addr:postcode": "44223",
    "addr:street": "Meredith Ln",
    "iso:country": "US",
    "sg:address": "631 Meredith Ln",
    "sg:city": "Cuyahoga Falls",
    "sg:classifiers": [
      {
        "category": "Building \u0026 Trades",
        "subcategory": "Construction",
        "type": "Services"
      }
    ],
    "sg:phone": "+1 330 929 3828",
    "sg:postcode": "44223",
    "sg:province": "OH",
    "sg:tags": [
      "general",
      "contractor"
    ],
    "wof:name": "Dales Development Co",
    "wof:placetype": "venue"
  },
  "geometry": {"coordinates":[-81.52196,41.148123],"type":"Point"}
}
