{
  "type": "Feature",
  "properties": {
    "iso:country":"US",
    "sg:address":"631 Meredith Ln",
    "sg:city":"Cuyahoga Falls",
    "sg:classifiers":[
        {
            "category":"Building & Trades",
            "subcategory":"Construction",
            "type":"Services"
        }
    ],
    "sg:phone":"+1 330 929 3828",
    "sg:postcode":"44223",
    "sg:province":"OH",
    "sg:tags":[
        "general",
        "contractor"
    ],
    "wof:name":"Dales Development Co",
    "wof:placetype":"venue"
},
  "geometry": {"coordinates":[-81.52196000000001,41.148123],"type":"Point"}
}