{
  "type": "Feature",
  "properties": {
    "addr:full": "658 Cincinnati St Dayton OH 45408",
    "addr:housenumber": "658",
    "addr:postcode": "45408",
    "addr:street": "Cincinnati St",
    "iso:country": "US",
    "sg:address": "658 Cincinnati St",
    "sg:city": "Dayton",
    "sg:classifiers": [
      {
        "category": "Building \u0026 Trades",
        "subcategory": "Plumbing",
        "type": "Services"
      }
    ],
    "sg:phone": "+1 937 429 1888",
    "sg:postcode": "45408",
    "sg:province": "OH",
    "sg:tags": [
      "conditioning",
      "air",
      "system",
      "contractor"
    ],
    "wof:name": "Shawnee Enterprises",
    "wof:placetype": "venue"
  },
  "geometry": {"coordinates":[-84.2013,39.743153],"type":"Point"}
}
