{
  "type": "Feature",
  "properties": {
    "addr:full": "406 W Irving St Bucyrus OH 44820",
    "addr:housenumber": "406",
    "addr:postcode": "44820",
    "addr:street": "W Irving St",
    "iso:country": "US",
    "sg:address": "406 W Irving St",
    "sg:city": "Bucyrus",
    "sg:classifiers": [
      {
        "category": "Building \u0026 Trades",
        "subcategory": "Plumbing",
        "type": "Services"
      }
    ],
    "sg:phone": "+1 419 562 0600",
    "sg:postcode": "44820",
    "sg:province": "OH",
    "sg:tags": [
      "conditioning",
      "air",
      "system",
      "contractor"
    ],
    "wof:name": "Kee Plumbing Heating \u0026 AC",
    "wof:placetype": "venue"
  },
  "geometry": {"coordinates":[-82.979937,40.819706],"type":"Point"}
}
