{
  "type": "Feature",
  "properties": {
    "iso:country":"US",
    "sg:address":"406 W Irving St",
    "sg:city":"Bucyrus",
    "sg:classifiers":[
        {
            "category":"Building & Trades",
            "subcategory":"Plumbing",
            "type":"Services"
        }
    ],
    "sg:phone":"+1 419 562 0600",
    "sg:postcode":"44820",
    "sg:province":"OH",
    "sg:tags":[
        "conditioning",
        "air",
        "system",
        "contractor"
    ],
    "wof:name":"Kee Plumbing Heating & AC",
    "wof:placetype":"venue"
},
  "geometry": {"coordinates":[-82.979937,40.819706],"type":"Point"}
}