{
  "type": "Feature",
  "properties": {
    "iso:country":"US",
    "sg:address":"4700 Smith Rd",
    "sg:city":"Cincinnati",
    "sg:classifiers":[
        {
            "category":"Insurance",
            "subcategory":"Insurance Agent",
            "type":"Services"
        }
    ],
    "sg:phone":"+1 513 458 6400",
    "sg:postcode":"45212",
    "sg:province":"OH",
    "wof:name":"Progressive Insurance Co",
    "wof:placetype":"venue"
},
  "geometry": {"coordinates":[-84.454005,39.161466],"type":"Point"}
}