{
  "type": "Feature",
  "properties": {
    "addr:full": "111 E Columbus St Pleasantville OH 43148",
    "addr:housenumber": "111",
    "addr:postcode": "43148",
    "addr:street": "E Columbus St",
    "iso:country": "US",
    "sg:address": "111 E Columbus St",
    "sg:city": "Pleasantville",
    "sg:classifiers": [
      {
        "category": "Personal",
        "subcategory": "Beauty Salon",
        "type": "Services"
      }
    ],
    "sg:phone": "+1 740 468 9384",
    "sg:postcode": "43148",
    "sg:province": "OH",
    "wof:name": "Pleasantville Family Hair",
    "wof:placetype": "venue"
  },
  "geometry": {"coordinates":[-82.520481,39.809405],"type":"Point"}
}
