{
  "type": "Feature",
  "properties": {
    "addr:full": "7408 Denison Ave Cleveland OH 44102",
    "addr:housenumber": "7408",
    "addr:postcode": "44102",
    "addr:street": "Denison Ave",
    "iso:country": "US",
    "sg:address": "7408 Denison Ave",
    "sg:city": "Cleveland",
    "sg:classifiers": [
      {
        "category": "Retail",
        "subcategory": "Auto Repair",
        "type": "Services"
      }
    ],
    "sg:phone": "+1 216 281 0555",
    "sg:postcode": "44102",
    "sg:province": "OH",
    "sg:tags": [
      "body",
      "repairing",
      "painting",
      "automobile"
    ],
    "sg:website": "www.rentnational.com",
    "wof:name": "Warner Auto Body",
    "wof:placetype": "venue"
  },
  "geometry": {"coordinates":[-81.738969,41.462644],"type":"Point"}
}
