{
  "type": "Feature",
  "properties": {
    "addr:full":"11580 Euclid Ave Cleveland OH 44106",
    "addr:housenumber":"11580",
    "addr:postcode":"44106",
    "addr:street":"Euclid Ave",
    "iso:country":"US",
    "sg:address":"11580 Euclid Ave",
    "sg:city":"Cleveland",
    "sg:classifiers":[
        {
            "category":"Restaurant",
            "type":"Food & Drink"
        }
    ],
    "sg:menulink":"http://www.allmenus.com/oh/cleveland/194888-mcdonalds/menu/",
    "sg:postcode":"44106",
    "sg:province":"OH",
    "sg:tags":[
        "burger",
        "american"
    ],
    "wof:name":"McDonald's",
    "wof:placetype":"venue"
},
  "geometry": {"coordinates":[-81.60368699999999,41.510133],"type":"Point"}
}