{
  "type": "Feature",
  "properties": {
    "addr:full": "4140 Prospect Church Rd Adamsville OH 43802",
    "addr:housenumber": "4140",
    "addr:postcode": "43802",
    "addr:street": "Prospect Church Rd",
    "iso:country": "US",
    "sg:address": "4140 Prospect Church Rd",
    "sg:city": "Adamsville",
    "sg:classifiers": [
      {
        "category": "Freight",
        "type": "Transportation"
      }
    ],
    "sg:phone": "+1 740 754 1446",
    "sg:postcode": "43802",
    "sg:province": "OH",
    "wof:name": "Sol Ltd",
    "wof:placetype": "venue"
  },
  "geometry": {"coordinates":[-81.91165,40.095794],"type":"Point"}
}
