{
  "type": "Feature",
  "properties": {
    "addr:full":"419 E William St Maumee OH 43537",
    "addr:housenumber":"419",
    "addr:postcode":"43537",
    "addr:street":"E William St",
    "iso:country":"US",
    "sg:address":"419 E William St",
    "sg:city":"Maumee",
    "sg:classifiers":[
        {
            "category":"Building & Trades",
            "subcategory":"Construction",
            "type":"Services"
        }
    ],
    "sg:phone":"+1 419 891 0720",
    "sg:postcode":"43537",
    "sg:province":"OH",
    "sg:tags":[
        "house"
    ],
    "wof:name":"Basement Tech",
    "wof:placetype":"venue"
},
  "geometry": {"coordinates":[-83.648155,41.566836],"type":"Point"}
}