{
  "type": "Feature",
  "properties": {
    "addr:full": "144 W Shoreway Dr Sandusky OH 44870",
    "addr:housenumber": "144",
    "addr:postcode": "44870",
    "addr:street": "W Shoreway Dr",
    "iso:country": "US",
    "sg:address": "144 W Shoreway Dr",
    "sg:city": "Sandusky",
    "sg:classifiers": [
      {
        "category": "Building \u0026 Trades",
        "subcategory": "Construction",
        "type": "Services"
      }
    ],
    "sg:phone": "+1 419 624 9670",
    "sg:postcode": "44870",
    "sg:province": "OH",
    "sg:tags": [
      "roofing",
      "contractor"
    ],
    "wof:name": "Brown's Roofing",
    "wof:placetype": "venue"
  },
  "geometry": {"coordinates":[-82.669477,41.439698],"type":"Point"}
}
