{
  "type": "Feature",
  "properties": {
    "iso:country":"US",
    "sg:address":"699 N Valley Rd",
    "sg:city":"Xenia",
    "sg:classifiers":[
        {
            "category":"Professional",
            "subcategory":"Advertising",
            "type":"Services"
        }
    ],
    "sg:phone":"+1 937 320 1678",
    "sg:postcode":"45385",
    "sg:province":"OH",
    "sg:tags":[
        "mailing",
        "shipping"
    ],
    "wof:name":"Nationwide Mailing Svc",
    "wof:placetype":"venue"
},
  "geometry": {"coordinates":[-83.997115,39.702098],"type":"Point"}
}