{
  "type": "Feature",
  "properties": {
    "addr:full":"2623 Holtz Rd Shelby OH 44875",
    "addr:postcode":"2623;44875",
    "addr:street":"Holtz Rd",
    "iso:country":"US",
    "sg:address":"2623 Holtz Rd",
    "sg:city":"Shelby",
    "sg:classifiers":[
        {
            "category":"Professional",
            "type":"Services"
        }
    ],
    "sg:phone":"+1 419 347 6338",
    "sg:postcode":"44875",
    "sg:province":"OH",
    "wof:name":"Dorothy Pifer",
    "wof:placetype":"venue"
},
  "geometry": {"coordinates":[-82.609635,40.872275],"type":"Point"}
}