{
  "type": "Feature",
  "properties": {
    "iso:country":"US",
    "sg:address":"900 W Boundary St",
    "sg:city":"Perrysburg",
    "sg:classifiers":[
        {
            "category":"Building & Trades",
            "subcategory":"Construction",
            "type":"Services"
        }
    ],
    "sg:phone":"+1 419 874 8886",
    "sg:postcode":"43551",
    "sg:province":"OH",
    "sg:tags":[
        "contractor"
    ],
    "wof:name":"Melchior Building Co",
    "wof:placetype":"venue"
},
  "geometry": {"coordinates":[-83.634492,41.543332],"type":"Point"}
}