{
  "type": "Feature",
  "properties": {
    "iso:country":"US",
    "sg:address":"1805 Styer Dr",
    "sg:city":"Medway",
    "sg:classifiers":[
        {
            "category":"Food & Beverages",
            "subcategory":"Groceries & Convenience Stores",
            "type":"Retail Goods"
        },
        {
            "category":"Shopping",
            "type":"Retail Goods"
        }
    ],
    "sg:phone":"+1 937 849 0194",
    "sg:postcode":"45344",
    "sg:province":"OH",
    "sg:tags":[
        "mexican"
    ],
    "wof:name":"Guadalupana",
    "wof:placetype":"venue"
},
  "geometry": {"coordinates":[-84.046476,39.890177],"type":"Point"}
}