{
  "type": "Feature",
  "properties": {
    "addr:full": "3657 E Livingston Ave Columbus OH 43227",
    "addr:housenumber": "3657",
    "addr:postcode": "43227",
    "addr:street": "E Livingston Ave",
    "iso:country": "US",
    "sg:address": "3657 E Livingston Ave",
    "sg:city": "Columbus",
    "sg:classifiers": [
      {
        "category": "Bars \u0026 Pubs",
        "type": "Food \u0026 Drink"
      }
    ],
    "sg:phone": "+1 614 235 0011",
    "sg:postcode": "43227",
    "sg:province": "OH",
    "wof:name": "Next Page Lounge",
    "wof:placetype": "venue"
  },
  "geometry": {"coordinates":[-82.897996,39.945843],"type":"Point"}
}
