{
  "type": "Feature",
  "properties": {
    "iso:country":"US",
    "sg:address":"3657 E Livingston Ave",
    "sg:city":"Columbus",
    "sg:classifiers":[
        {
            "category":"Bars & Pubs",
            "type":"Food & Drink"
        }
    ],
    "sg:phone":"+1 614 235 0011",
    "sg:postcode":"43227",
    "sg:province":"OH",
    "wof:name":"Next Page Lounge",
    "wof:placetype":"venue"
},
  "geometry": {"coordinates":[-82.89799600000001,39.945843],"type":"Point"}
}