{
  "type": "Feature",
  "properties": {
    "addr:full":"293 Fountain St Akron OH 44306",
    "addr:housenumber":"293",
    "addr:postcode":"44306",
    "addr:street":"Fountain St",
    "iso:country":"US",
    "sg:address":"293 Fountain St",
    "sg:city":"Akron",
    "sg:classifiers":[
        {
            "category":"Shopping",
            "subcategory":"Hobbies, Toys, & Games",
            "type":"Retail Goods"
        }
    ],
    "sg:phone":"+1 330 253 5782",
    "sg:postcode":"44306",
    "sg:province":"OH",
    "sg:tags":[
        "craft"
    ],
    "wof:name":"Pinestones",
    "wof:placetype":"venue"
},
  "geometry": {"coordinates":[-81.503575,41.071449],"type":"Point"}
}