{
  "type": "Feature",
  "properties": {
    "iso:country":"US",
    "sg:address":"2979 Southfield Dr",
    "sg:city":"Dayton",
    "sg:classifiers":[
        {
            "category":"Building & Trades",
            "subcategory":"Construction",
            "type":"Services"
        }
    ],
    "sg:phone":"+1 937 454 2205",
    "sg:postcode":"45434",
    "sg:province":"OH",
    "sg:tags":[
        "residential",
        "remodeling",
        "home"
    ],
    "wof:name":"Gary L White Construction",
    "wof:placetype":"venue"
},
  "geometry": {"coordinates":[-84.04413599999999,39.6972],"type":"Point"}
}