{
  "type": "Feature",
  "properties": {
    "iso:country":"US",
    "sg:address":"401 Market St",
    "sg:city":"Zanesville",
    "sg:classifiers":[
        {
            "category":"Government",
            "subcategory":"Office",
            "type":"Public Place"
        }
    ],
    "sg:phone":"+1 740 455 0603",
    "sg:postcode":"43701",
    "sg:province":"OH",
    "sg:tags":[
        "city"
    ],
    "sg:website":"www.coz.org",
    "wof:name":"Zanesville Mayor's Ofc",
    "wof:placetype":"venue"
},
  "geometry": {"coordinates":[-82.00766299999999,39.941858],"type":"Point"}
}