{
  "type": "Feature",
  "properties": {
    "addr:full": "401 Market St Zanesville OH 43701",
    "addr:housenumber": "401",
    "addr:postcode": "43701",
    "addr:street": "Market St",
    "iso:country": "US",
    "sg:address": "401 Market St",
    "sg:city": "Zanesville",
    "sg:classifiers": [
      {
        "category": "Government",
        "subcategory": "Office",
        "type": "Public Place"
      }
    ],
    "sg:phone": "+1 740 455 0603",
    "sg:postcode": "43701",
    "sg:province": "OH",
    "sg:tags": [
      "city"
    ],
    "sg:website": "www.coz.org",
    "wof:name": "Zanesville Mayor's Ofc",
    "wof:placetype": "venue"
  },
  "geometry": {"coordinates":[-82.007663,39.941858],"type":"Point"}
}
