{
  "type": "Feature",
  "properties": {
    "addr:full":"253 Whitetail Run Cortland OH 44410",
    "addr:housenumber":"253",
    "addr:postcode":"44410",
    "addr:street":"Whitetail Run",
    "iso:country":"US",
    "sg:address":"253 Whitetail Run",
    "sg:city":"Cortland",
    "sg:classifiers":[
        {
            "category":"Manufacturing",
            "subcategory":"Textiles",
            "type":"Manufacturing & Wholesale Goods"
        }
    ],
    "sg:phone":"+1 330 637 6237",
    "sg:postcode":"44410",
    "sg:province":"OH",
    "sg:tags":[
        "mill",
        "fabric",
        "cotton"
    ],
    "wof:name":"Flying Colors Pinstriping",
    "wof:placetype":"venue"
},
  "geometry": {"coordinates":[-80.7197,41.310935],"type":"Point"}
}