{
  "type": "Feature",
  "properties": {
    "iso:country":"US",
    "sg:address":"119 Gordon St",
    "sg:city":"Piqua",
    "sg:classifiers":[
        {
            "category":"Manufacturing",
            "subcategory":"Metals",
            "type":"Manufacturing & Wholesale Goods"
        }
    ],
    "sg:phone":"+1 937 773 0191",
    "sg:postcode":"45356",
    "sg:province":"OH",
    "sg:tags":[
        "die",
        "mfg",
        "nonferrous"
    ],
    "wof:name":"W L Stephan Inc",
    "wof:placetype":"venue"
},
  "geometry": {"coordinates":[-84.251259,40.14624],"type":"Point"}
}