{
  "type": "Feature",
  "properties": {
    "addr:full": "579 E Jackson St Millersburg OH 44654",
    "addr:housenumber": "579",
    "addr:postcode": "44654",
    "addr:street": "E Jackson St",
    "iso:country": "US",
    "sg:address": "579 E Jackson St",
    "sg:city": "Millersburg",
    "sg:classifiers": [
      {
        "category": "Farming",
        "subcategory": "Farm",
        "type": "Manufacturing \u0026 Wholesale Goods"
      }
    ],
    "sg:phone": "+1 330 674 4437",
    "sg:postcode": "44654",
    "sg:province": "OH",
    "sg:tags": [
      "crop",
      "general"
    ],
    "wof:name": "Julia Gray",
    "wof:placetype": "venue"
  },
  "geometry": {"coordinates":[-81.91068,40.554323],"type":"Point"}
}
