{
  "type": "Feature",
  "properties": {
    "iso:country":"US",
    "sg:address":"1865 Tamarack Rd",
    "sg:city":"Newark",
    "sg:classifiers":[
        {
            "category":"Health Services",
            "subcategory":"Health Practitioner",
            "type":"Services"
        }
    ],
    "sg:phone":"+1 740 348 4972",
    "sg:postcode":"43055",
    "sg:province":"OH",
    "sg:tags":[
        "occupational",
        "safety"
    ],
    "wof:name":"Company Care",
    "wof:placetype":"venue"
},
  "geometry": {"coordinates":[-82.464923,40.038525],"type":"Point"}
}