{
  "type": "Feature",
  "properties": {
    "addr:full":"8009 W Bancroft St Toledo OH 43617",
    "addr:housenumber":"8009",
    "addr:postcode":"43617",
    "addr:street":"W Bancroft St",
    "iso:country":"US",
    "sg:address":"8009 W Bancroft St",
    "sg:city":"Toledo",
    "sg:classifiers":[
        {
            "category":"Retail",
            "subcategory":"Repair Shop",
            "type":"Services"
        }
    ],
    "sg:phone":"+1 419 382 2311",
    "sg:postcode":"43617",
    "sg:province":"OH",
    "sg:tags":[
        "appliance"
    ],
    "wof:name":"Home Gas & Electric Inc",
    "wof:placetype":"venue"
},
  "geometry": {"coordinates":[-83.73460300000001,41.659243],"type":"Point"}
}