{
  "type": "Feature",
  "properties": {
    "iso:country":"US",
    "sg:address":"2722 Willard Ave",
    "sg:city":"Cincinnati",
    "sg:classifiers":[
        {
            "category":"Wholesale",
            "subcategory":"Durable Goods & Equipment",
            "type":"Manufacturing & Wholesale Goods"
        }
    ],
    "sg:phone":"+1 513 841 9353",
    "sg:postcode":"45209",
    "sg:province":"OH",
    "sg:tags":[
        "engineering",
        "scientific",
        "supply"
    ],
    "wof:name":"Jma Equipment Comp",
    "wof:placetype":"venue"
},
  "geometry": {"coordinates":[-84.440664,39.146834],"type":"Point"}
}