{
  "type": "Feature",
  "properties": {
    "addr:full": "8527 Pringle Dr Cincinnati OH 45231",
    "addr:housenumber": "8527",
    "addr:postcode": "45231",
    "addr:street": "Pringle Dr",
    "iso:country": "US",
    "sg:address": "8527 Pringle Dr",
    "sg:city": "Cincinnati",
    "sg:classifiers": [
      {
        "category": "Recreation",
        "subcategory": "Gun Range",
        "type": "Entertainment"
      }
    ],
    "sg:phone": "+1 513 407 9095",
    "sg:postcode": "45231",
    "sg:province": "OH",
    "sg:tags": [
      "ammunition"
    ],
    "wof:name": "Kyle's Gunshop",
    "wof:placetype": "venue"
  },
  "geometry": {"coordinates":[-84.513758,39.22291],"type":"Point"}
}
