{
  "type": "Feature",
  "properties": {
    "addr:full":"756 Bernhard Rd Columbus OH 43213",
    "addr:housenumber":"756",
    "addr:postcode":"43213",
    "addr:street":"Bernhard Rd",
    "iso:country":"US",
    "sg:address":"756 Bernhard Rd",
    "sg:city":"Columbus",
    "sg:classifiers":[
        {
            "category":"Building & Trades",
            "subcategory":"Construction",
            "type":"Services"
        }
    ],
    "sg:phone":"+1 614 237 7941",
    "sg:postcode":"43213",
    "sg:province":"OH",
    "sg:tags":[
        "repairing",
        "remodeling",
        "contractor"
    ],
    "wof:name":"Drummond Restoration",
    "wof:placetype":"venue"
},
  "geometry": {"coordinates":[-82.88030500000001,39.959307],"type":"Point"}
}