{
  "type": "Feature",
  "properties": {
    "addr:full":"17448 Lorain Ave Cleveland OH 44111",
    "addr:housenumber":"17448",
    "addr:postcode":"44111",
    "addr:street":"Lorain Ave",
    "iso:country":"US",
    "sg:address":"17448 Lorain Ave",
    "sg:city":"Cleveland",
    "sg:classifiers":[
        {
            "category":"Shopping",
            "subcategory":"Gifts & Souvenirs",
            "type":"Retail Goods"
        }
    ],
    "sg:phone":"+1 216 252 0010",
    "sg:postcode":"44111",
    "sg:province":"OH",
    "sg:tags":[
        "cards",
        "greeting"
    ],
    "wof:name":"Hello Shop",
    "wof:placetype":"venue"
},
  "geometry": {"coordinates":[-81.81869500000001,41.450122],"type":"Point"}
}