{
  "type": "Feature",
  "properties": {
    "iso:country":"US",
    "sg:address":"2221 Cogswell Ct",
    "sg:city":"Miamisburg",
    "sg:classifiers":[
        {
            "category":"Shopping",
            "subcategory":"Gifts & Souvenirs",
            "type":"Retail Goods"
        }
    ],
    "sg:phone":"+1 937 865 9121",
    "sg:postcode":"45342",
    "sg:province":"OH",
    "wof:name":"Gourmet Goodies",
    "wof:placetype":"venue"
},
  "geometry": {"coordinates":[-84.249184,39.623431],"type":"Point"}
}