{
  "type": "Feature",
  "properties": {
    "addr:full": "2221 Cogswell Ct Miamisburg OH 45342",
    "addr:housenumber": "2221",
    "addr:postcode": "45342",
    "addr:street": "Cogswell Ct",
    "iso:country": "US",
    "sg:address": "2221 Cogswell Ct",
    "sg:city": "Miamisburg",
    "sg:classifiers": [
      {
        "category": "Shopping",
        "subcategory": "Gifts \u0026 Souvenirs",
        "type": "Retail Goods"
      }
    ],
    "sg:phone": "+1 937 865 9121",
    "sg:postcode": "45342",
    "sg:province": "OH",
    "wof:name": "Gourmet Goodies",
    "wof:placetype": "venue"
  },
  "geometry": {"coordinates":[-84.249184,39.623431],"type":"Point"}
}
