{
  "type": "Feature",
  "properties": {
    "addr:full":"26485 US Hwy 20A Archbold OH 43502",
    "addr:postcode":"26485;43502",
    "addr:street":"Us Hwy 20A",
    "iso:country":"US",
    "sg:address":"26485 US Hwy 20A",
    "sg:city":"Archbold",
    "sg:phone":"+1 419 924 2754",
    "sg:postcode":"43502",
    "sg:province":"OH",
    "sg:tags":[
        "farm",
        "corn",
        "wheat",
        "soybean"
    ],
    "wof:name":"Bob Rohlf",
    "wof:placetype":"venue"
},
  "geometry": {"coordinates":[-84.37087099999999,41.586528],"type":"Point"}
}