{
  "type": "Feature",
  "properties": {
    "iso:country":"US",
    "sg:address":"8600 Navarre Rd SW",
    "sg:city":"Massillon",
    "sg:classifiers":[
        {
            "category":"Autos & Motor Vehicles",
            "subcategory":"Automobile Sales",
            "type":"Retail Goods"
        }
    ],
    "sg:phone":"+1 330 879 0017",
    "sg:postcode":"44646",
    "sg:province":"OH",
    "sg:tags":[
        "car",
        "dealer"
    ],
    "wof:name":"Rabbit's Auto Sales",
    "wof:placetype":"venue"
},
  "geometry": {"coordinates":[-81.51629,40.747212],"type":"Point"}
}