{
  "type": "Feature",
  "properties": {
    "addr:full": "2001 E Royalton Rd Cleveland OH 44147",
    "addr:housenumber": "2001",
    "addr:postcode": "44147",
    "addr:street": "E Royalton Rd",
    "iso:country": "US",
    "sg:address": "2001 E Royalton Rd",
    "sg:city": "Cleveland",
    "sg:classifiers": [
      {
        "category": "Health Services",
        "subcategory": "Podiatrist",
        "type": "Services"
      }
    ],
    "sg:phone": "+1 440 884 4100",
    "sg:postcode": "44147",
    "sg:province": "OH",
    "wof:name": "Jeffrey A Halpert DPM",
    "wof:placetype": "venue"
  },
  "geometry": {"coordinates":[-81.672727,41.313941],"type":"Point"}
}
