{
  "type": "Feature",
  "properties": {
    "iso:country":"US",
    "sg:address":"2001 E Royalton Rd",
    "sg:city":"Cleveland",
    "sg:classifiers":[
        {
            "category":"Health Services",
            "subcategory":"Podiatrist",
            "type":"Services"
        }
    ],
    "sg:phone":"+1 440 884 4100",
    "sg:postcode":"44147",
    "sg:province":"OH",
    "wof:name":"Jeffrey A Halpert DPM",
    "wof:placetype":"venue"
},
  "geometry": {"coordinates":[-81.67272699999999,41.313941],"type":"Point"}
}