{
  "type": "Feature",
  "properties": {
    "iso:country":"US",
    "sg:address":"5683 Tallawanda Dr",
    "sg:city":"Fairfield",
    "sg:classifiers":[
        {
            "category":"Freight",
            "type":"Transportation"
        }
    ],
    "sg:phone":"+1 513 858 2955",
    "sg:postcode":"45014",
    "sg:province":"OH",
    "sg:tags":[
        "operator",
        "local",
        "trucking"
    ],
    "wof:name":"Mark Martin Trucking",
    "wof:placetype":"venue"
},
  "geometry": {"coordinates":[-84.573536,39.327417],"type":"Point"}
}