{
  "type": "Feature",
  "properties": {
    "addr:full": "3720 Park St Grove City OH 43123",
    "addr:housenumber": "3720",
    "addr:postcode": "43123",
    "addr:street": "Park St",
    "iso:country": "US",
    "sg:address": "3720 Park St",
    "sg:city": "Grove City",
    "sg:classifiers": [
      {
        "category": "Shopping",
        "subcategory": "Bicycles \u0026 Sporting Goods",
        "type": "Retail Goods"
      }
    ],
    "sg:phone": "+1 614 871 2535",
    "sg:postcode": "43123",
    "sg:province": "OH",
    "sg:tags": [
      "horse",
      "furnishing"
    ],
    "wof:name": "Hobson Turf Supply",
    "wof:placetype": "venue"
  },
  "geometry": {"coordinates":[-83.100158,39.885538],"type":"Point"}
}
