{
  "type": "Feature",
  "properties": {
    "iso:country":"US",
    "sg:address":"3720 Park St",
    "sg:city":"Grove City",
    "sg:classifiers":[
        {
            "category":"Shopping",
            "subcategory":"Bicycles & Sporting Goods",
            "type":"Retail Goods"
        }
    ],
    "sg:phone":"+1 614 871 2535",
    "sg:postcode":"43123",
    "sg:province":"OH",
    "sg:tags":[
        "horse",
        "furnishing"
    ],
    "wof:name":"Hobson Turf Supply",
    "wof:placetype":"venue"
},
  "geometry": {"coordinates":[-83.10015799999999,39.885538],"type":"Point"}
}