{
  "type": "Feature",
  "properties": {
    "addr:full": "1116 E Farwell St Sandusky OH 44870",
    "addr:housenumber": "1116",
    "addr:postcode": "44870",
    "addr:street": "E Farwell St",
    "iso:country": "US",
    "sg:address": "1116 E Farwell St",
    "sg:city": "Sandusky",
    "sg:classifiers": [
      {
        "category": "Personal",
        "subcategory": "Beauty Salon",
        "type": "Services"
      }
    ],
    "sg:phone": "+1 419 625 8098",
    "sg:postcode": "44870",
    "sg:province": "OH",
    "wof:name": "Tazie's Hair",
    "wof:placetype": "venue"
  },
  "geometry": {"coordinates":[-82.682831,41.447402],"type":"Point"}
}
