{
  "type": "Feature",
  "properties": {
    "iso:country":"US",
    "sg:address":"27080 Cedar Rd",
    "sg:city":"Cleveland",
    "sg:classifiers":[
        {
            "category":"Organizations",
            "subcategory":"Non-profit Organization",
            "type":"Services"
        }
    ],
    "sg:phone":"+1 216 360 9080",
    "sg:postcode":"44122",
    "sg:province":"OH",
    "sg:website":"www.montefiorecare.org",
    "wof:name":"Montefiore",
    "wof:placetype":"venue"
},
  "geometry": {"coordinates":[-81.488924,41.501094],"type":"Point"}
}