{
  "type": "Feature",
  "properties": {
    "addr:full":"351 Chilton Pl Gahanna OH 43230",
    "addr:housenumber":"351",
    "addr:postcode":"43230",
    "addr:street":"Chilton Pl",
    "iso:country":"US",
    "sg:address":"351 Chilton Pl",
    "sg:city":"Gahanna",
    "sg:classifiers":[
        {
            "category":"Organizations",
            "subcategory":"Community Association",
            "type":"Services"
        }
    ],
    "sg:phone":"+1 614 418 9524",
    "sg:postcode":"43230",
    "sg:province":"OH",
    "wof:name":"Special Ties",
    "wof:placetype":"venue"
},
  "geometry": {"coordinates":[-82.84666900000001,40.009096],"type":"Point"}
}