{
  "type": "Feature",
  "properties": {
    "iso:country":"US",
    "sg:address":"715 Sunnymead Dr",
    "sg:city":"Fairborn",
    "sg:classifiers":[
        {
            "category":"Shopping",
            "subcategory":"Books",
            "type":"Retail Goods"
        }
    ],
    "sg:phone":"+1 937 873 9693",
    "sg:postcode":"45324",
    "sg:province":"OH",
    "wof:name":"Wolf Creek Books LLC",
    "wof:placetype":"venue"
},
  "geometry": {"coordinates":[-83.99091799999999,39.832811],"type":"Point"}
}