{
  "type": "Feature",
  "properties": {
    "addr:full": "126 N Adrian St Lyons OH 43533",
    "addr:housenumber": "126",
    "addr:postcode": "43533",
    "addr:street": "N Adrian St",
    "iso:country": "US",
    "sg:address": "126 N Adrian St",
    "sg:city": "Lyons",
    "sg:classifiers": [
      {
        "category": "Government",
        "subcategory": "Fire Station",
        "type": "Public Place"
      }
    ],
    "sg:phone": "+1 419 923 2222",
    "sg:postcode": "43533",
    "sg:province": "OH",
    "sg:tags": [
      "department"
    ],
    "wof:name": "Lyons Rescue Squad",
    "wof:placetype": "venue"
  },
  "geometry": {"coordinates":[-84.070783,41.700014],"type":"Point"}
}
