{
  "type": "Feature",
  "properties": {
    "iso:country":"US",
    "sg:address":"126 N Adrian St",
    "sg:city":"Lyons",
    "sg:classifiers":[
        {
            "category":"Government",
            "subcategory":"Fire Station",
            "type":"Public Place"
        }
    ],
    "sg:phone":"+1 419 923 2222",
    "sg:postcode":"43533",
    "sg:province":"OH",
    "sg:tags":[
        "department"
    ],
    "wof:name":"Lyons Rescue Squad",
    "wof:placetype":"venue"
},
  "geometry": {"coordinates":[-84.07078300000001,41.700014],"type":"Point"}
}