{
  "type": "Feature",
  "properties": {
    "iso:country":"US",
    "sg:address":"7850 Mentor Ave",
    "sg:city":"Mentor",
    "sg:classifiers":[
        {
            "category":"Shopping",
            "subcategory":"Gifts & Souvenirs",
            "type":"Retail Goods"
        }
    ],
    "sg:phone":"+1 440 974 8701",
    "sg:postcode":"44060",
    "sg:province":"OH",
    "sg:tags":[
        "shop",
        "greeting",
        "card"
    ],
    "wof:name":"Abbott's Cards & Gifts",
    "wof:placetype":"venue"
},
  "geometry": {"coordinates":[-81.359627,41.661388],"type":"Point"}
}