{
  "type": "Feature",
  "properties": {
    "iso:country":"US",
    "sg:address":"2050 Crocker Rd",
    "sg:city":"Westlake",
    "sg:classifiers":[
        {
            "category":"Building & Trades",
            "subcategory":"Construction",
            "type":"Services"
        }
    ],
    "sg:phone":"+1 440 871 7229",
    "sg:postcode":"44145",
    "sg:province":"OH",
    "sg:tags":[
        "nonresidential"
    ],
    "wof:name":"Multi Phase Inc",
    "wof:placetype":"venue"
},
  "geometry": {"coordinates":[-81.949291,41.452275],"type":"Point"}
}