{
  "type": "Feature",
  "properties": {
    "addr:full": "1290 Crescent St Youngstown OH 44502",
    "addr:housenumber": "1290",
    "addr:postcode": "44502",
    "addr:street": "Crescent St",
    "iso:country": "US",
    "sg:address": "1290 Crescent St",
    "sg:city": "Youngstown",
    "sg:classifiers": [
      {
        "category": "Wholesale",
        "subcategory": "Hardware",
        "type": "Manufacturing \u0026 Wholesale Goods"
      }
    ],
    "sg:phone": "+1 330 743 1143",
    "sg:postcode": "44502",
    "sg:province": "OH",
    "sg:tags": [
      "plumbing",
      "fixture",
      "supply"
    ],
    "sg:website": "www.rhs1.com",
    "wof:name": "Robertson Heating Supply Co",
    "wof:placetype": "venue"
  },
  "geometry": {"coordinates":[-80.672793,41.107689],"type":"Point"}
}
