{
  "type": "Feature",
  "properties": {
    "addr:full":"315 Galena St Toledo OH 43611",
    "addr:housenumber":"315",
    "addr:postcode":"43611",
    "addr:street":"Galena St",
    "iso:country":"US",
    "sg:address":"315 Galena St",
    "sg:city":"Toledo",
    "sg:classifiers":[
        {
            "category":"Organizations",
            "subcategory":"Religious Organization",
            "type":"Services"
        }
    ],
    "sg:phone":"+1 419 726 2186",
    "sg:postcode":"43611",
    "sg:province":"OH",
    "sg:tags":[
        "church"
    ],
    "wof:name":"Lighthouse Baptist Church",
    "wof:placetype":"venue"
},
  "geometry": {"coordinates":[-83.508257,41.66986],"type":"Point"}
}