{
  "type": "Feature",
  "properties": {
    "iso:country":"US",
    "sg:address":"900 W Boundary St",
    "sg:city":"Perrysburg",
    "sg:classifiers":[
        {
            "category":"Professional",
            "subcategory":"Accounting & Tax Preparation",
            "type":"Services"
        }
    ],
    "sg:phone":"+1 419 872 3700",
    "sg:postcode":"43551",
    "sg:province":"OH",
    "sg:tags":[
        "return",
        "filing"
    ],
    "wof:name":"H & R Block Premium Tax Svc",
    "wof:placetype":"venue"
},
  "geometry": {"coordinates":[-83.63449199999999,41.543332],"type":"Point"}
}