{
  "type": "Feature",
  "properties": {
    "iso:country":"US",
    "sg:address":"110 Park St",
    "sg:city":"Circleville",
    "sg:classifiers":[
        {
            "category":"Utilities",
            "subcategory":"Sewage",
            "type":"Services"
        }
    ],
    "sg:phone":"+1 740 474 6253",
    "sg:postcode":"43113",
    "sg:province":"OH",
    "sg:tags":[
        "water"
    ],
    "wof:name":"Lakeland Utilities Company",
    "wof:placetype":"venue"
},
  "geometry": {"coordinates":[-82.937687,39.616361],"type":"Point"}
}