{
  "type": "Feature",
  "properties": {
    "addr:full": "5594 N High St Worthington OH 43085",
    "addr:housenumber": "5594",
    "addr:postcode": "43085",
    "addr:street": "N High St",
    "iso:country": "US",
    "sg:address": "5594 N High St",
    "sg:city": "Worthington",
    "sg:classifiers": [
      {
        "category": "Personal",
        "subcategory": "Beauty Salon",
        "type": "Services"
      }
    ],
    "sg:phone": "+1 614 885 4551",
    "sg:postcode": "43085",
    "sg:province": "OH",
    "wof:name": "Just Hair",
    "wof:placetype": "venue"
  },
  "geometry": {"coordinates":[-83.018646,40.077168],"type":"Point"}
}
