{
  "type": "Feature",
  "properties": {
    "addr:full": "22906 Lorain Rd Cleveland OH 44126",
    "addr:housenumber": "22906",
    "addr:postcode": "44126",
    "addr:street": "Lorain Rd",
    "iso:country": "US",
    "sg:address": "22906 Lorain Rd",
    "sg:city": "Cleveland",
    "sg:classifiers": [
      {
        "category": "Retail",
        "subcategory": "Laundry \u0026 Dry Cleaning",
        "type": "Services"
      }
    ],
    "sg:phone": "+1 440 686 0165",
    "sg:postcode": "44126",
    "sg:province": "OH",
    "sg:tags": [
      "cleaners"
    ],
    "wof:name": "Kwick-N-Clean",
    "wof:placetype": "venue"
  },
  "geometry": {"coordinates":[-81.87506,41.437198],"type":"Point"}
}
