{
  "type": "Feature",
  "properties": {
    "addr:full":"4195 Mahoning Ave Youngstown OH 44515",
    "addr:housenumber":"4195",
    "addr:postcode":"44515",
    "addr:street":"Mahoning Ave",
    "iso:country":"US",
    "sg:address":"4195 Mahoning Ave",
    "sg:city":"Youngstown",
    "sg:classifiers":[
        {
            "category":"Shopping",
            "subcategory":"Florist",
            "type":"Retail Goods"
        }
    ],
    "sg:phone":"+1 330 799 8920",
    "sg:postcode":"44515",
    "sg:province":"OH",
    "wof:name":"Dick Adgate Florist Inc",
    "wof:placetype":"venue"
},
  "geometry": {"coordinates":[-80.724329,41.102497],"type":"Point"}
}