{
  "type": "Feature",
  "properties": {
    "addr:full":"5001 Greenville-Palestine Rd Greenville OH 45331",
    "addr:housenumber":"5001",
    "addr:postcode":"45331",
    "addr:street":"Greenville-Palestine Rd",
    "iso:country":"US",
    "sg:address":"5001 Greenville-Palestine Rd",
    "sg:city":"Greenville",
    "sg:classifiers":[
        {
            "category":"Retail",
            "subcategory":"Animal Services",
            "type":"Services"
        }
    ],
    "sg:phone":"+1 937 548 3065",
    "sg:postcode":"45331",
    "sg:province":"OH",
    "sg:tags":[
        "breeder",
        "dog"
    ],
    "sg:website":"www.ravinesgsd.com",
    "wof:name":"Ravine's German Shepherds LTD",
    "wof:placetype":"venue"
},
  "geometry": {"coordinates":[-84.697366,40.067023],"type":"Point"}
}