{
  "type": "Feature",
  "properties": {
    "addr:full":"197 E Broad St Columbus OH 43215",
    "addr:housenumber":"197",
    "addr:postcode":"43215",
    "addr:street":"E Broad St",
    "iso:country":"US",
    "sg:address":"197 E Broad St",
    "sg:city":"Columbus",
    "sg:classifiers":[
        {
            "category":"Banks & Credit Unions",
            "subcategory":"Bank",
            "type":"Services"
        }
    ],
    "sg:phone":"+1 614 222 2470",
    "sg:postcode":"43215",
    "sg:province":"OH",
    "sg:tags":[
        "loan",
        "real estate"
    ],
    "wof:name":"CFIC",
    "wof:placetype":"venue"
},
  "geometry": {"coordinates":[-82.994625,39.962823],"type":"Point"}
}