{
  "type": "Feature",
  "properties": {
    "iso:country":"US",
    "sg:address":"8188 State Rte 123",
    "sg:city":"Franklin",
    "sg:classifiers":[
        {
            "category":"Autos & Motor Vehicles",
            "subcategory":"Fuel & Gas Station",
            "type":"Retail Goods"
        }
    ],
    "sg:phone":"+1 937 743 0752",
    "sg:postcode":"45005",
    "sg:province":"OH",
    "sg:tags":[
        "station",
        "gasoline"
    ],
    "wof:name":"Ashland Service",
    "wof:placetype":"venue"
},
  "geometry": {"coordinates":[-84.30928299999999,39.576761],"type":"Point"}
}