{
  "type": "Feature",
  "properties": {
    "addr:full": "8188 State Rte 123 Franklin OH 45005",
    "addr:housenumber": "8188",
    "addr:postcode": "45005",
    "addr:street": "State Rte 123",
    "iso:country": "US",
    "sg:address": "8188 State Rte 123",
    "sg:city": "Franklin",
    "sg:classifiers": [
      {
        "category": "Autos \u0026 Motor Vehicles",
        "subcategory": "Fuel \u0026 Gas Station",
        "type": "Retail Goods"
      }
    ],
    "sg:phone": "+1 937 743 0752",
    "sg:postcode": "45005",
    "sg:province": "OH",
    "sg:tags": [
      "station",
      "gasoline"
    ],
    "wof:name": "Ashland Service",
    "wof:placetype": "venue"
  },
  "geometry": {"coordinates":[-84.309283,39.576761],"type":"Point"}
}
