{
  "type": "Feature",
  "properties": {
    "addr:full":"3209 Chester Ave Cleveland OH 44114",
    "addr:housenumber":"3209",
    "addr:postcode":"44114",
    "addr:street":"Chester Ave",
    "iso:country":"US",
    "sg:address":"3209 Chester Ave",
    "sg:city":"Cleveland",
    "sg:classifiers":[
        {
            "category":"Wholesale",
            "subcategory":"Hardware",
            "type":"Manufacturing & Wholesale Goods"
        }
    ],
    "sg:phone":"+1 216 431 2300",
    "sg:postcode":"44114",
    "sg:province":"OH",
    "sg:tags":[
        "beverage",
        "dispensing"
    ],
    "wof:name":"Pepsi-Cola General Bottlers",
    "wof:placetype":"venue"
},
  "geometry": {"coordinates":[-81.666634,41.5047],"type":"Point"}
}