{
  "type": "Feature",
  "properties": {
    "addr:full": "2841 Wapakoneta Ave Sidney OH 45365",
    "addr:housenumber": "2841",
    "addr:postcode": "45365",
    "addr:street": "Wapakoneta Ave",
    "iso:country": "US",
    "sg:address": "2841 Wapakoneta Ave",
    "sg:city": "Sidney",
    "sg:classifiers": [
      {
        "category": "Organizations",
        "subcategory": "Community Association",
        "type": "Services"
      }
    ],
    "sg:phone": "+1 937 492 3878",
    "sg:postcode": "45365",
    "sg:province": "OH",
    "wof:name": "VFW Post 4239",
    "wof:placetype": "venue"
  },
  "geometry": {"coordinates":[-84.162701,40.322075],"type":"Point"}
}
