{
  "type": "Feature",
  "properties": {
    "addr:full": "1290 Waterville Monclova Rd Waterville OH 43566",
    "addr:housenumber": "1290",
    "addr:postcode": "43566",
    "addr:street": "Waterville Monclova Rd",
    "iso:country": "US",
    "sg:address": "1290 Waterville Monclova Rd",
    "sg:city": "Waterville",
    "sg:classifiers": [
      {
        "category": "Wholesale",
        "subcategory": "Machinery \u0026 Supplies",
        "type": "Manufacturing \u0026 Wholesale Goods"
      }
    ],
    "sg:phone": "+1 419 878 7000",
    "sg:postcode": "43566",
    "sg:province": "OH",
    "sg:tags": [
      "equipment",
      "industrial"
    ],
    "sg:website": "www.parker.com",
    "wof:name": "Parker-Hannifin Corp",
    "wof:placetype": "venue"
  },
  "geometry": {"coordinates":[-83.738253,41.491641],"type":"Point"}
}
