{
  "type": "Feature",
  "properties": {
    "iso:country":"US",
    "sg:address":"4221 Wyncote Rd",
    "sg:city":"Cleveland",
    "sg:classifiers":[
        {
            "category":"Organizations",
            "subcategory":"Membership Organization",
            "type":"Services"
        }
    ],
    "sg:phone":"+1 216 382 7387",
    "sg:postcode":"44121",
    "sg:province":"OH",
    "sg:tags":[
        "society",
        "humane"
    ],
    "wof:name":"Cleveland Animal Life Line",
    "wof:placetype":"venue"
},
  "geometry": {"coordinates":[-81.530216,41.505399],"type":"Point"}
}