{
  "type": "Feature",
  "properties": {
    "addr:full": "11311 Shaker Blvd Cleveland OH 44104",
    "addr:housenumber": "11311",
    "addr:postcode": "44104",
    "addr:street": "Shaker Blvd",
    "iso:country": "US",
    "sg:address": "11311 Shaker Blvd",
    "sg:city": "Cleveland",
    "sg:classifiers": [
      {
        "category": "Government",
        "subcategory": "Office",
        "type": "Public Place"
      }
    ],
    "sg:phone": "+1 216 368 7819",
    "sg:postcode": "44104",
    "sg:province": "OH",
    "sg:tags": [
      "state",
      "program",
      "health"
    ],
    "wof:name": "WIC Program",
    "wof:placetype": "venue"
  },
  "geometry": {"coordinates":[-81.605918,41.484334],"type":"Point"}
}
