{
  "type": "Feature",
  "properties": {
    "iso:country":"US",
    "sg:address":"13993 Cedar Rd",
    "sg:city":"Cleveland",
    "sg:classifiers":[
        {
            "category":"Coffee & Tea",
            "type":"Food & Drink"
        }
    ],
    "sg:menulink":"http://www.allmenus.com/oh/south-euclid/124873-starbucks-coffee/menu/",
    "sg:phone":"+1 216 371 5438",
    "sg:postcode":"44118",
    "sg:province":"OH",
    "sg:tags":[
        "american"
    ],
    "wof:name":"Starbucks Coffee",
    "wof:placetype":"venue"
},
  "geometry": {"coordinates":[-81.536945,41.501694],"type":"Point"}
}