{
  "type": "Feature",
  "properties": {
    "addr:full": "344 Aurora Commons Cir Aurora OH 44202",
    "addr:housenumber": "344",
    "addr:postcode": "44202",
    "addr:street": "Aurora Commons Cir",
    "iso:country": "US",
    "sg:address": "344 Aurora Commons Cir",
    "sg:city": "Aurora",
    "sg:classifiers": [
      {
        "category": "Personal",
        "subcategory": "Tanning Parlor",
        "type": "Services"
      }
    ],
    "sg:phone": "+1 330 562 6905",
    "sg:postcode": "44202",
    "sg:province": "OH",
    "sg:tags": [
      "salon"
    ],
    "wof:name": "Acapulco Golden Tan",
    "wof:placetype": "venue"
  },
  "geometry": {"coordinates":[-81.357925,41.315852],"type":"Point"}
}
