{
  "type": "Feature",
  "properties": {
    "addr:full":"628 Taylor St Sandusky OH 44870",
    "addr:housenumber":"628",
    "addr:postcode":"44870",
    "addr:street":"Taylor St",
    "iso:country":"US",
    "sg:address":"628 Taylor St",
    "sg:city":"Sandusky",
    "sg:classifiers":[
        {
            "category":"Personal",
            "subcategory":"Beauty Salon",
            "type":"Services"
        }
    ],
    "sg:phone":"+1 419 625 0771",
    "sg:postcode":"44870",
    "sg:province":"OH",
    "wof:name":"Central Styling",
    "wof:placetype":"venue"
},
  "geometry": {"coordinates":[-82.70941500000001,41.441136],"type":"Point"}
}