{
  "type": "Feature",
  "properties": {
    "addr:full": "752 Ashland Rd Mansfield OH 44905",
    "addr:housenumber": "752",
    "addr:postcode": "44905",
    "addr:street": "Ashland Rd",
    "iso:country": "US",
    "sg:address": "752 Ashland Rd",
    "sg:city": "Mansfield",
    "sg:classifiers": [
      {
        "category": "Shopping",
        "subcategory": "Used Merchandise",
        "type": "Retail Goods"
      }
    ],
    "sg:phone": "+1 419 522 3217",
    "sg:postcode": "44905",
    "sg:province": "OH",
    "wof:name": "Salvation Army Thrift Store",
    "wof:placetype": "venue"
  },
  "geometry": {"coordinates":[-82.485549,40.770543],"type":"Point"}
}
