{
  "type": "Feature",
  "properties": {
    "addr:full":"3403 Mautz-Yeager Rd Marion OH 43302",
    "addr:housenumber":"3403",
    "addr:postcode":"43302",
    "addr:street":"Mautz-Yeager Rd",
    "iso:country":"US",
    "sg:address":"3403 Mautz-Yeager Rd",
    "sg:city":"Marion",
    "sg:classifiers":[
        {
            "category":"Farming",
            "subcategory":"Livestock Farm",
            "type":"Manufacturing & Wholesale Goods"
        }
    ],
    "sg:phone":"+1 740 389 4740",
    "sg:postcode":"43302",
    "sg:province":"OH",
    "sg:tags":[
        "beef",
        "feedlot",
        "cattle"
    ],
    "wof:name":"Tim Sharrock",
    "wof:placetype":"venue"
},
  "geometry": {"coordinates":[-83.043172,40.522438],"type":"Point"}
}