{
  "type": "Feature",
  "properties": {
    "addr:full":"316 W Wenger Rd Englewood OH 45322",
    "addr:housenumber":"316",
    "addr:postcode":"45322",
    "addr:street":"W Wenger Rd",
    "iso:country":"US",
    "sg:address":"316 W Wenger Rd",
    "sg:city":"Englewood",
    "sg:classifiers":[
        {
            "category":"Organizations",
            "subcategory":"Community Association",
            "type":"Services"
        }
    ],
    "sg:phone":"+1 937 832 3126",
    "sg:postcode":"45322",
    "sg:province":"OH",
    "wof:name":"Optimist International",
    "wof:placetype":"venue"
},
  "geometry": {"coordinates":[-84.29597,39.862173],"type":"Point"}
}