{
  "type": "Feature",
  "properties": {
    "iso:country":"US",
    "sg:address":"19731 Seminole Rd",
    "sg:city":"Euclid",
    "sg:classifiers":[
        {
            "category":"Shopping",
            "type":"Retail Goods"
        }
    ],
    "sg:phone":"+1 216 486 4191",
    "sg:postcode":"44117",
    "sg:province":"OH",
    "sg:tags":[
        "merchandise"
    ],
    "wof:name":"Renee Gilliam",
    "wof:placetype":"venue"
},
  "geometry": {"coordinates":[-81.543184,41.556735],"type":"Point"}
}