{
  "type": "Feature",
  "properties": {
    "iso:country":"US",
    "sg:address":"12139 Royal Point Dr",
    "sg:city":"Cincinnati",
    "sg:classifiers":[
        {
            "category":"Retail",
            "subcategory":"Laundry & Dry Cleaning",
            "type":"Services"
        }
    ],
    "sg:phone":"+1 513 677 6777",
    "sg:postcode":"45249",
    "sg:province":"OH",
    "sg:tags":[
        "cleaners"
    ],
    "wof:name":"Mason Cleaners",
    "wof:placetype":"venue"
},
  "geometry": {"coordinates":[-84.31124199999999,39.291742],"type":"Point"}
}