{
  "type": "Feature",
  "properties": {
    "addr:full":"7634 Rivers Edge Dr Columbus OH 43235",
    "addr:housenumber":"7634",
    "addr:postcode":"43235",
    "addr:street":"Rivers Edge Dr",
    "iso:country":"US",
    "sg:address":"7634 Rivers Edge Dr",
    "sg:city":"Columbus",
    "sg:classifiers":[
        {
            "category":"Professional",
            "subcategory":"Management & Consulting",
            "type":"Services"
        }
    ],
    "sg:phone":"+1 614 566 9700",
    "sg:postcode":"43235",
    "sg:province":"OH",
    "sg:tags":[
        "construction",
        "health",
        "center",
        "care"
    ],
    "wof:name":"Prime Medical Group Inc",
    "wof:placetype":"venue"
},
  "geometry": {"coordinates":[-83.03415,40.121874],"type":"Point"}
}