{
  "type": "Feature",
  "properties": {
    "addr:full":"8354 Tallmadge Rd Ravenna OH 44266",
    "addr:postcode":"8354;44266",
    "addr:street":"Tallmadge Rd",
    "iso:country":"US",
    "sg:address":"8354 Tallmadge Rd",
    "sg:city":"Ravenna",
    "sg:classifiers":[
        {
            "category":"Farming",
            "subcategory":"Livestock Farm",
            "type":"Manufacturing & Wholesale Goods"
        }
    ],
    "sg:phone":"+1 330 654 5446",
    "sg:postcode":"44266",
    "sg:province":"OH",
    "sg:tags":[
        "hog",
        "corn",
        "or",
        "feedlot"
    ],
    "wof:name":"Albert Ahrens",
    "wof:placetype":"venue"
},
  "geometry": {"coordinates":[-81.08956000000001,41.09897],"type":"Point"}
}