{
  "type": "Feature",
  "properties": {
    "addr:full":"5988 Rosalie Rd Dayton OH 45424",
    "addr:housenumber":"5988",
    "addr:postcode":"45424",
    "addr:street":"Rosalie Rd",
    "iso:country":"US",
    "sg:address":"5988 Rosalie Rd",
    "sg:city":"Dayton",
    "sg:classifiers":[
        {
            "category":"Organizations",
            "subcategory":"Religious Organization",
            "type":"Services"
        }
    ],
    "sg:phone":"+1 937 233 4608",
    "sg:postcode":"45424",
    "sg:province":"OH",
    "sg:tags":[
        "clergy"
    ],
    "wof:name":"William D Tallman",
    "wof:placetype":"venue"
},
  "geometry": {"coordinates":[-84.12060099999999,39.83799],"type":"Point"}
}