{
  "type": "Feature",
  "properties": {
    "addr:full":"33493 Aurora Rd Cleveland OH 44139",
    "addr:housenumber":"33493",
    "addr:postcode":"44139",
    "addr:street":"Aurora Rd",
    "iso:country":"US",
    "sg:address":"33493 Aurora Rd",
    "sg:city":"Cleveland",
    "sg:classifiers":[
        {
            "category":"Cinema",
            "subcategory":"Movie Rental",
            "type":"Entertainment"
        }
    ],
    "sg:phone":"+1 440 498 9582",
    "sg:postcode":"44139",
    "sg:province":"OH",
    "sg:tags":[
        "leasing",
        "video",
        "disc",
        "tape"
    ],
    "wof:name":"Video For All",
    "wof:placetype":"venue"
},
  "geometry": {"coordinates":[-81.438638,41.385074],"type":"Point"}
}