{
  "type": "Feature",
  "properties": {
    "addr:full": "2259 West Ave Ashtabula OH 44004",
    "addr:housenumber": "2259",
    "addr:postcode": "44004",
    "addr:street": "West Ave",
    "iso:country": "US",
    "sg:address": "2259 West Ave",
    "sg:city": "Ashtabula",
    "sg:classifiers": [
      {
        "category": "Shopping",
        "subcategory": "Gifts \u0026 Souvenirs",
        "type": "Retail Goods"
      }
    ],
    "sg:phone": "+1 440 964 7476",
    "sg:postcode": "44004",
    "sg:province": "OH",
    "sg:tags": [
      "party",
      "supply"
    ],
    "wof:name": "Andrus Party Ctr",
    "wof:placetype": "venue"
  },
  "geometry": {"coordinates":[-80.801334,41.882035],"type":"Point"}
}
