{
  "type": "Feature",
  "properties": {
    "addr:full": "541 Bull Creek Rd Jerry City OH 43437",
    "addr:housenumber": "541",
    "addr:postcode": "43437",
    "addr:street": "Bull Creek Rd",
    "iso:country": "US",
    "sg:address": "541 Bull Creek Rd",
    "sg:city": "Jerry City",
    "sg:classifiers": [
      {
        "category": "Professional",
        "type": "Services"
      }
    ],
    "sg:phone": "+1 419 655 2907",
    "sg:postcode": "43437",
    "sg:province": "OH",
    "sg:tags": [
      "establishment"
    ],
    "wof:name": "Puco",
    "wof:placetype": "venue"
  },
  "geometry": {"coordinates":[-83.612009,41.255702],"type":"Point"}
}
