{
  "type": "Feature",
  "properties": {
    "addr:full": "9614 Tamarack Ter Cincinnati OH 45241",
    "addr:housenumber": "9614",
    "addr:postcode": "45241",
    "addr:street": "Tamarack Ter",
    "iso:country": "US",
    "sg:address": "9614 Tamarack Ter",
    "sg:city": "Cincinnati",
    "sg:classifiers": [
      {
        "category": "Banks \u0026 Credit Unions",
        "subcategory": "Investment Brokerage",
        "type": "Services"
      }
    ],
    "sg:phone": "+1 513 777 2117",
    "sg:postcode": "45241",
    "sg:province": "OH",
    "sg:tags": [
      "consultant",
      "planning",
      "financial"
    ],
    "wof:name": "George Loeber \u0026 Co",
    "wof:placetype": "venue"
  },
  "geometry": {"coordinates":[-84.369154,39.30759],"type":"Point"}
}
