{
  "type": "Feature",
  "properties": {
    "addr:full":"5510 Glenhill Ave NE Canton OH 44721",
    "addr:housenumber":"5510",
    "addr:postcode":"44721",
    "addr:street":"Glenhill Ave Ne",
    "iso:country":"US",
    "sg:address":"5510 Glenhill Ave NE",
    "sg:city":"Canton",
    "sg:classifiers":[
        {
            "category":"Food & Beverages",
            "subcategory":"Bakery",
            "type":"Retail Goods"
        }
    ],
    "sg:phone":"+1 330 966 2253",
    "sg:postcode":"44721",
    "sg:province":"OH",
    "sg:tags":[
        "baker"
    ],
    "wof:name":"Cookie Boutique",
    "wof:placetype":"venue"
},
  "geometry": {"coordinates":[-81.34143400000001,40.862148],"type":"Point"}
}