{
  "type": "Feature",
  "properties": {
    "addr:full": "2001 Crocker Rd Cleveland OH 44145",
    "addr:housenumber": "2001",
    "addr:postcode": "44145",
    "addr:street": "Crocker Rd",
    "iso:country": "US",
    "sg:address": "2001 Crocker Rd",
    "sg:city": "Cleveland",
    "sg:classifiers": [
      {
        "category": "Recreation",
        "type": "Entertainment"
      }
    ],
    "sg:phone": "+1 440 899 1535",
    "sg:postcode": "44145",
    "sg:province": "OH",
    "sg:tags": [
      "skating",
      "rink"
    ],
    "wof:name": "V C Ice",
    "wof:placetype": "venue"
  },
  "geometry": {"coordinates":[-81.950548,41.461477],"type":"Point"}
}
