{
  "type": "Feature",
  "properties": {
    "iso:country":"US",
    "sg:address":"241 W Bancroft St",
    "sg:city":"Toledo",
    "sg:classifiers":[
        {
            "category":"Food & Beverages",
            "subcategory":"Groceries & Convenience Stores",
            "type":"Retail Goods"
        }
    ],
    "sg:phone":"+1 419 243 4538",
    "sg:postcode":"43620",
    "sg:province":"OH",
    "sg:tags":[
        "grocer"
    ],
    "wof:name":"Holston's Supermarket",
    "wof:placetype":"venue"
},
  "geometry": {"coordinates":[-83.549978,41.663966],"type":"Point"}
}