{
  "type": "Feature",
  "properties": {
    "addr:full": "241 W Bancroft St Toledo OH 43620",
    "addr:housenumber": "241",
    "addr:postcode": "43620",
    "addr:street": "W Bancroft St",
    "iso:country": "US",
    "sg:address": "241 W Bancroft St",
    "sg:city": "Toledo",
    "sg:classifiers": [
      {
        "category": "Food \u0026 Beverages",
        "subcategory": "Groceries \u0026 Convenience Stores",
        "type": "Retail Goods"
      }
    ],
    "sg:phone": "+1 419 243 4538",
    "sg:postcode": "43620",
    "sg:province": "OH",
    "sg:tags": [
      "grocer"
    ],
    "wof:name": "Holston's Supermarket",
    "wof:placetype": "venue"
  },
  "geometry": {"coordinates":[-83.549978,41.663966],"type":"Point"}
}
