{
  "type": "Feature",
  "properties": {
    "iso:country":"US",
    "sg:address":"192 Quarry Rd SE",
    "sg:city":"Lancaster",
    "sg:classifiers":[
        {
            "category":"Wholesale",
            "subcategory":"Hardware",
            "type":"Manufacturing & Wholesale Goods"
        }
    ],
    "sg:phone":"+1 740 653 0541",
    "sg:postcode":"43130",
    "sg:province":"OH",
    "sg:tags":[
        "fastener"
    ],
    "wof:name":"Calandra Industrial Supply Co",
    "wof:placetype":"venue"
},
  "geometry": {"coordinates":[-82.543254,39.71715],"type":"Point"}
}