{
  "type": "Feature",
  "properties": {
    "iso:country":"US",
    "sg:address":"6932 Bogue Rd",
    "sg:city":"Orwell",
    "sg:classifiers":[
        {
            "category":"Food & Beverages",
            "subcategory":"Groceries & Convenience Stores",
            "type":"Retail Goods"
        }
    ],
    "sg:phone":"+1 440 437 5714",
    "sg:postcode":"44076",
    "sg:province":"OH",
    "sg:tags":[
        "grocer"
    ],
    "wof:name":"M & L Salvage",
    "wof:placetype":"venue"
},
  "geometry": {"coordinates":[-80.829786,41.561756],"type":"Point"}
}