{
  "type": "Feature",
  "properties": {
    "addr:full": "6932 Bogue Rd Orwell OH 44076",
    "addr:housenumber": "6932",
    "addr:postcode": "44076",
    "addr:street": "Bogue Rd",
    "iso:country": "US",
    "sg:address": "6932 Bogue Rd",
    "sg:city": "Orwell",
    "sg:classifiers": [
      {
        "category": "Food \u0026 Beverages",
        "subcategory": "Groceries \u0026 Convenience Stores",
        "type": "Retail Goods"
      }
    ],
    "sg:phone": "+1 440 437 5714",
    "sg:postcode": "44076",
    "sg:province": "OH",
    "sg:tags": [
      "grocer"
    ],
    "wof:name": "M \u0026 L Salvage",
    "wof:placetype": "venue"
  },
  "geometry": {"coordinates":[-80.829786,41.561756],"type":"Point"}
}
