{
  "type": "Feature",
  "properties": {
    "iso:country":"US",
    "sg:address":"1925 9th St SW",
    "sg:city":"Akron",
    "sg:classifiers":[
        {
            "category":"Building & Trades",
            "subcategory":"Electrical",
            "type":"Services"
        }
    ],
    "sg:phone":"+1 330 753 9464",
    "sg:postcode":"44314",
    "sg:province":"OH",
    "sg:tags":[
        "electric",
        "contractor"
    ],
    "wof:name":"Kenmore Electric Inc",
    "wof:placetype":"venue"
},
  "geometry": {"coordinates":[-81.55317599999999,41.051481],"type":"Point"}
}