{
  "type": "Feature",
  "properties": {
    "iso:country":"US",
    "sg:address":"10121 Northfield Rd",
    "sg:city":"Northfield",
    "sg:classifiers":[
        {
            "category":"Retail",
            "subcategory":"Car Wash",
            "type":"Services"
        }
    ],
    "sg:phone":"+1 330 467 5758",
    "sg:postcode":"44067",
    "sg:province":"OH",
    "sg:tags":[
        "mini",
        "self",
        "storage"
    ],
    "sg:website":"www.redistorage.com",
    "wof:name":"Redi Storage",
    "wof:placetype":"venue"
},
  "geometry": {"coordinates":[-81.531689,41.332923],"type":"Point"}
}