{
  "type": "Feature",
  "properties": {
    "iso:country":"US",
    "sg:address":"549 E Manhattan Blvd",
    "sg:city":"Toledo",
    "sg:classifiers":[
        {
            "category":"Food & Beverages",
            "subcategory":"Liquor & Beverages",
            "type":"Retail Goods"
        }
    ],
    "sg:phone":"+1 419 726 6732",
    "sg:postcode":"43608",
    "sg:province":"OH",
    "sg:tags":[
        "alcoholic"
    ],
    "wof:name":"Manhattan Liquor Agency",
    "wof:placetype":"venue"
},
  "geometry": {"coordinates":[-83.53343099999999,41.686426],"type":"Point"}
}