{
  "type": "Feature",
  "properties": {
    "addr:full": "549 E Manhattan Blvd Toledo OH 43608",
    "addr:housenumber": "549",
    "addr:postcode": "43608",
    "addr:street": "E Manhattan Blvd",
    "iso:country": "US",
    "sg:address": "549 E Manhattan Blvd",
    "sg:city": "Toledo",
    "sg:classifiers": [
      {
        "category": "Food \u0026 Beverages",
        "subcategory": "Liquor \u0026 Beverages",
        "type": "Retail Goods"
      }
    ],
    "sg:phone": "+1 419 726 6732",
    "sg:postcode": "43608",
    "sg:province": "OH",
    "sg:tags": [
      "alcoholic"
    ],
    "wof:name": "Manhattan Liquor Agency",
    "wof:placetype": "venue"
  },
  "geometry": {"coordinates":[-83.533431,41.686426],"type":"Point"}
}
