{
  "type": "Feature",
  "properties": {
    "iso:country":"US",
    "sg:address":"1829 Losantiville Ave",
    "sg:city":"Cincinnati",
    "sg:classifiers":[
        {
            "category":"Personal",
            "subcategory":"Beauty Salon",
            "type":"Services"
        }
    ],
    "sg:phone":"+1 513 351 1645",
    "sg:postcode":"45237",
    "sg:province":"OH",
    "wof:name":"Ramona Craig Hair Stylist",
    "wof:placetype":"venue"
},
  "geometry": {"coordinates":[-84.455967,39.192034],"type":"Point"}
}