{
  "type": "Feature",
  "properties": {
    "addr:full":"4460 Lockwood Rd Perry OH 44081",
    "addr:housenumber":"4460",
    "addr:postcode":"44081",
    "addr:street":"Lockwood Rd",
    "iso:country":"US",
    "sg:address":"4460 Lockwood Rd",
    "sg:city":"Perry",
    "sg:classifiers":[
        {
            "category":"Freight",
            "type":"Transportation"
        }
    ],
    "sg:phone":"+1 440 259 5343",
    "sg:postcode":"44081",
    "sg:province":"OH",
    "sg:tags":[
        "operator",
        "local",
        "trucking"
    ],
    "wof:name":"Fiorenza Trucking Inc",
    "wof:placetype":"venue"
},
  "geometry": {"coordinates":[-81.133133,41.80733],"type":"Point"}
}