{
  "type": "Feature",
  "properties": {
    "addr:full": "1006 Tiffin Ave Sandusky OH 44870",
    "addr:housenumber": "1006",
    "addr:postcode": "44870",
    "addr:street": "Tiffin Ave",
    "iso:country": "US",
    "sg:address": "1006 Tiffin Ave",
    "sg:city": "Sandusky",
    "sg:classifiers": [
      {
        "category": "Real Estate",
        "subcategory": "Real Estate Services",
        "type": "Services"
      }
    ],
    "sg:phone": "+1 419 626 6900",
    "sg:postcode": "44870",
    "sg:province": "OH",
    "sg:tags": [
      "home",
      "inspector"
    ],
    "wof:name": "Kerber Exterminating",
    "wof:placetype": "venue"
  },
  "geometry": {"coordinates":[-82.727303,41.446201],"type":"Point"}
}
