{
  "type": "Feature",
  "properties": {
    "iso:country":"US",
    "sg:address":"1006 Tiffin Ave",
    "sg:city":"Sandusky",
    "sg:classifiers":[
        {
            "category":"Real Estate",
            "subcategory":"Real Estate Services",
            "type":"Services"
        }
    ],
    "sg:phone":"+1 419 626 6900",
    "sg:postcode":"44870",
    "sg:province":"OH",
    "sg:tags":[
        "home",
        "inspector"
    ],
    "wof:name":"Kerber Exterminating",
    "wof:placetype":"venue"
},
  "geometry": {"coordinates":[-82.72730300000001,41.446201],"type":"Point"}
}