{
  "type": "Feature",
  "properties": {
    "addr:full": "8023 Crile Rd Concord Twp OH 44077",
    "addr:housenumber": "8023",
    "addr:postcode": "44077",
    "addr:street": "Crile Rd",
    "iso:country": "US",
    "sg:address": "8023 Crile Rd",
    "sg:city": "Concord Twp",
    "sg:classifiers": [
      {
        "category": "Autos \u0026 Motor Vehicles",
        "subcategory": "Recreational Vehicle Sales",
        "type": "Retail Goods"
      }
    ],
    "sg:phone": "+1 440 354 8152",
    "sg:postcode": "44077",
    "sg:province": "OH",
    "wof:name": "Mentor Rv \u0026 Storage",
    "wof:placetype": "venue"
  },
  "geometry": {"coordinates":[-81.239798,41.654039],"type":"Point"}
}
