{
  "type": "Feature",
  "properties": {
    "iso:country":"US",
    "sg:address":"8023 Crile Rd",
    "sg:city":"Concord Twp",
    "sg:classifiers":[
        {
            "category":"Autos & Motor Vehicles",
            "subcategory":"Recreational Vehicle Sales",
            "type":"Retail Goods"
        }
    ],
    "sg:phone":"+1 440 354 8152",
    "sg:postcode":"44077",
    "sg:province":"OH",
    "wof:name":"Mentor Rv & Storage",
    "wof:placetype":"venue"
},
  "geometry": {"coordinates":[-81.23979799999999,41.654039],"type":"Point"}
}