{
  "type": "Feature",
  "properties": {
    "iso:country":"US",
    "sg:address":"955 W Walnut St",
    "sg:city":"Canal Winchester",
    "sg:classifiers":[
        {
            "category":"Manufacturing",
            "subcategory":"Tools & Machinery",
            "type":"Manufacturing & Wholesale Goods"
        }
    ],
    "sg:phone":"+1 614 834 5000",
    "sg:postcode":"43110",
    "sg:province":"OH",
    "sg:tags":[
        "equipment",
        "conveyor",
        "conveying"
    ],
    "wof:name":"Princeton Delivery Systems Inc",
    "wof:placetype":"venue"
},
  "geometry": {"coordinates":[-82.832061,39.848125],"type":"Point"}
}