{
  "type": "Feature",
  "properties": {
    "addr:full":"7725 Hub Pkwy Cleveland OH 44125",
    "addr:housenumber":"7725",
    "addr:postcode":"44125",
    "addr:street":"Hub Pkwy",
    "iso:country":"US",
    "sg:address":"7725 Hub Pkwy",
    "sg:city":"Cleveland",
    "sg:classifiers":[
        {
            "category":"Wholesale",
            "subcategory":"Machinery & Supplies",
            "type":"Manufacturing & Wholesale Goods"
        }
    ],
    "sg:phone":"+1 216 524 5750",
    "sg:postcode":"44125",
    "sg:province":"OH",
    "sg:tags":[
        "hardware",
        "equipment",
        "industrial"
    ],
    "wof:name":"Tipton Machinery Company Inc",
    "wof:placetype":"venue"
},
  "geometry": {"coordinates":[-81.59061800000001,41.363961],"type":"Point"}
}