{
  "type": "Feature",
  "properties": {
    "iso:country":"US",
    "sg:address":"1475 Upper Valley Pike",
    "sg:city":"Springfield",
    "sg:classifiers":[
        {
            "category":"Shopping",
            "subcategory":"Department Store",
            "type":"Retail Goods"
        }
    ],
    "sg:phone":"+1 937 327 4800",
    "sg:postcode":"45504",
    "sg:province":"OH",
    "wof:name":"Sears",
    "wof:placetype":"venue"
},
  "geometry": {"coordinates":[-83.851872,39.947477],"type":"Point"}
}