{
  "type": "Feature",
  "properties": {
    "iso:country":"US",
    "sg:address":"1939 Bordeaux Rue",
    "sg:city":"Northwood",
    "sg:classifiers":[
        {
            "category":"Retail",
            "subcategory":"Repair Shop",
            "type":"Services"
        }
    ],
    "sg:phone":"+1 419 837 5550",
    "sg:postcode":"43619",
    "sg:province":"OH",
    "sg:tags":[
        "welding"
    ],
    "wof:name":"A-1 PM Svc",
    "wof:placetype":"venue"
},
  "geometry": {"coordinates":[-83.471661,41.616118],"type":"Point"}
}