{
  "type": "Feature",
  "properties": {
    "iso:country":"US",
    "sg:address":"2842 Bellwood Ave",
    "sg:city":"Columbus",
    "sg:classifiers":[
        {
            "category":"Health Services",
            "subcategory":"Nursing And Care Facility",
            "type":"Services"
        }
    ],
    "sg:phone":"+1 614 235 4877",
    "sg:postcode":"43209",
    "sg:province":"OH",
    "wof:name":"Uniquecare Inc",
    "wof:placetype":"venue"
},
  "geometry": {"coordinates":[-82.926289,39.979963],"type":"Point"}
}