{
  "type": "Feature",
  "properties": {
    "iso:country":"US",
    "sg:address":"967 Stover Rd",
    "sg:city":"West Alexandria",
    "sg:classifiers":[
        {
            "category":"Banks & Credit Unions",
            "subcategory":"Financial Services",
            "type":"Services"
        }
    ],
    "sg:phone":"+1 937 839 1145",
    "sg:postcode":"45381",
    "sg:province":"OH",
    "sg:tags":[
        "investment",
        "closed"
    ],
    "wof:name":"Marion A Singleton",
    "wof:placetype":"venue"
},
  "geometry": {"coordinates":[-84.566614,39.743019],"type":"Point"}
}