{
  "type": "Feature",
  "properties": {
    "addr:full": "967 Stover Rd West Alexandria OH 45381",
    "addr:housenumber": "967",
    "addr:postcode": "45381",
    "addr:street": "Stover Rd",
    "iso:country": "US",
    "sg:address": "967 Stover Rd",
    "sg:city": "West Alexandria",
    "sg:classifiers": [
      {
        "category": "Banks \u0026 Credit Unions",
        "subcategory": "Financial Services",
        "type": "Services"
      }
    ],
    "sg:phone": "+1 937 839 1145",
    "sg:postcode": "45381",
    "sg:province": "OH",
    "sg:tags": [
      "investment",
      "closed"
    ],
    "wof:name": "Marion A Singleton",
    "wof:placetype": "venue"
  },
  "geometry": {"coordinates":[-84.566614,39.743019],"type":"Point"}
}
