{
  "type": "Feature",
  "properties": {
    "addr:full":"3725 W 3rd St Dayton OH 45417",
    "addr:housenumber":"3725",
    "addr:postcode":"45417",
    "addr:street":"W 3Rd St",
    "iso:country":"US",
    "sg:address":"3725 W 3rd St",
    "sg:city":"Dayton",
    "sg:classifiers":[
        {
            "category":"Manufacturing",
            "subcategory":"Electronics",
            "type":"Manufacturing & Wholesale Goods"
        }
    ],
    "sg:phone":"+1 937 268 0320",
    "sg:postcode":"45417",
    "sg:province":"OH",
    "sg:tags":[
        "equipment",
        "durable",
        "mfg",
        "home"
    ],
    "wof:name":"Bobs Custom Audio",
    "wof:placetype":"venue"
},
  "geometry": {"coordinates":[-84.249182,39.750132],"type":"Point"}
}