{
  "type": "Feature",
  "properties": {
    "addr:full": "1999 Morse Rd Columbus OH 43229",
    "addr:housenumber": "1999",
    "addr:postcode": "43229",
    "addr:street": "Morse Rd",
    "iso:country": "US",
    "sg:address": "1999 Morse Rd",
    "sg:city": "Columbus",
    "sg:classifiers": [
      {
        "category": "Retail",
        "subcategory": "Auto Rental",
        "type": "Services"
      }
    ],
    "sg:phone": "+1 614 261 3646",
    "sg:postcode": "43229",
    "sg:province": "OH",
    "sg:tags": [
      "renting",
      "automobile"
    ],
    "wof:name": "Enterprise Rent A Car",
    "wof:placetype": "venue"
  },
  "geometry": {"coordinates":[-82.966878,40.060149],"type":"Point"}
}
