{
  "type": "Feature",
  "properties": {
    "addr:full":"4968 S R 66 New Bremen OH 45869",
    "addr:housenumber":"4968;66",
    "addr:postcode":"45869",
    "addr:street":"S R",
    "iso:country":"US",
    "sg:address":"4968 S R 66",
    "sg:city":"New Bremen",
    "sg:classifiers":[
        {
            "category":"Restaurant",
            "type":"Food & Drink"
        }
    ],
    "sg:menulink":"http://www.allmenus.com/oh/jackson/78402-dominos-pizza/menu/",
    "sg:phone":"+1 419 629 2400",
    "sg:postcode":"45869",
    "sg:province":"OH",
    "sg:tags":[
        "american",
        "wing",
        "pizza"
    ],
    "wof:name":"Domino's Pizza",
    "wof:placetype":"venue"
},
  "geometry": {"coordinates":[-84.37808699999999,40.421998],"type":"Point"}
}