{
  "type": "Feature",
  "properties": {
    "iso:country":"US",
    "sg:address":"65 Pinewood Dr",
    "sg:city":"Fremont",
    "sg:classifiers":[
        {
            "category":"Building & Trades",
            "subcategory":"Plumbing",
            "type":"Services"
        }
    ],
    "sg:phone":"+1 419 332 6237",
    "sg:postcode":"43420",
    "sg:province":"OH",
    "sg:tags":[
        "contractor"
    ],
    "wof:name":"Watruba Fire Sprinkler Design",
    "wof:placetype":"venue"
},
  "geometry": {"coordinates":[-83.134078,41.335587],"type":"Point"}
}