{
  "type": "Feature",
  "properties": {
    "addr:full":"440 High St Fairport Harbor OH 44077",
    "addr:housenumber":"440",
    "addr:postcode":"44077",
    "addr:street":"High St",
    "iso:country":"US",
    "sg:address":"440 High St",
    "sg:city":"Fairport Harbor",
    "sg:classifiers":[
        {
            "category":"Health Services",
            "subcategory":"Medical Lab",
            "type":"Services"
        }
    ],
    "sg:phone":"+1 440 352 0008",
    "sg:postcode":"44077",
    "sg:province":"OH",
    "sg:tags":[
        "laboratory"
    ],
    "wof:name":"Advanced Dental Works",
    "wof:placetype":"venue"
},
  "geometry": {"coordinates":[-81.276982,41.752956],"type":"Point"}
}