{
  "type": "Feature",
  "properties": {
    "iso:country":"US",
    "sg:address":"639 Wooster Rd W",
    "sg:city":"Barberton",
    "sg:classifiers":[
        {
            "category":"Organizations",
            "subcategory":"Religious Organization",
            "type":"Services"
        }
    ],
    "sg:phone":"+1 330 753 9679",
    "sg:postcode":"44203",
    "sg:province":"OH",
    "sg:tags":[
        "church"
    ],
    "wof:name":"Church Chapel Of Faith",
    "wof:placetype":"venue"
},
  "geometry": {"coordinates":[-81.61333500000001,41.012168],"type":"Point"}
}