{
  "type": "Feature",
  "properties": {
    "addr:full": "6652 Ayleshire Dr Cleveland OH 44139",
    "addr:housenumber": "6652",
    "addr:postcode": "44139",
    "addr:street": "Ayleshire Dr",
    "iso:country": "US",
    "sg:address": "6652 Ayleshire Dr",
    "sg:city": "Cleveland",
    "sg:classifiers": [
      {
        "category": "Manufacturing",
        "subcategory": "Metals",
        "type": "Manufacturing \u0026 Wholesale Goods"
      }
    ],
    "sg:phone": "+1 216 681 2334",
    "sg:postcode": "44139",
    "sg:province": "OH",
    "sg:tags": [
      "fabricator",
      "sheet"
    ],
    "wof:name": "Medco Metal Fabricators Inc",
    "wof:placetype": "venue"
  },
  "geometry": {"coordinates":[-81.426658,41.378445],"type":"Point"}
}
