{
  "type": "Feature",
  "properties": {
    "iso:country":"US",
    "sg:address":"6652 Ayleshire Dr",
    "sg:city":"Cleveland",
    "sg:classifiers":[
        {
            "category":"Manufacturing",
            "subcategory":"Metals",
            "type":"Manufacturing & Wholesale Goods"
        }
    ],
    "sg:phone":"+1 216 681 2334",
    "sg:postcode":"44139",
    "sg:province":"OH",
    "sg:tags":[
        "fabricator",
        "sheet"
    ],
    "wof:name":"Medco Metal Fabricators Inc",
    "wof:placetype":"venue"
},
  "geometry": {"coordinates":[-81.426658,41.378445],"type":"Point"}
}