{
  "type": "Feature",
  "properties": {
    "addr:full": "1150 Rustic Run Rd Tipp City OH 45371",
    "addr:housenumber": "1150",
    "addr:postcode": "45371",
    "addr:street": "Rustic Run Rd",
    "iso:country": "US",
    "sg:address": "1150 Rustic Run Rd",
    "sg:city": "Tipp City",
    "sg:classifiers": [
      {
        "category": "Building \u0026 Trades",
        "subcategory": "Construction",
        "type": "Services"
      }
    ],
    "sg:phone": "+1 937 667 9925",
    "sg:postcode": "45371",
    "sg:province": "OH",
    "sg:tags": [
      "home",
      "family",
      "contractor"
    ],
    "wof:name": "Noble Construction",
    "wof:placetype": "venue"
  },
  "geometry": {"coordinates":[-84.17727,39.928045],"type":"Point"}
}
