{
  "type": "Feature",
  "properties": {
    "iso:country":"US",
    "sg:address":"1150 Rustic Run Rd",
    "sg:city":"Tipp City",
    "sg:classifiers":[
        {
            "category":"Building & Trades",
            "subcategory":"Construction",
            "type":"Services"
        }
    ],
    "sg:phone":"+1 937 667 9925",
    "sg:postcode":"45371",
    "sg:province":"OH",
    "sg:tags":[
        "home",
        "family",
        "contractor"
    ],
    "wof:name":"Noble Construction",
    "wof:placetype":"venue"
},
  "geometry": {"coordinates":[-84.17726999999999,39.928045],"type":"Point"}
}