{
  "type": "Feature",
  "properties": {
    "addr:full": "6440 Som Center Rd Cleveland OH 44139",
    "addr:postcode": "6440;44139",
    "addr:street": "Som Center Rd",
    "iso:country": "US",
    "sg:address": "6440 Som Center Rd",
    "sg:city": "Cleveland",
    "sg:classifiers": [
      {
        "category": "Home \u0026 Garden",
        "subcategory": "Furniture",
        "type": "Retail Goods"
      }
    ],
    "sg:phone": "+1 440 349 2900",
    "sg:postcode": "44139",
    "sg:province": "OH",
    "sg:tags": [
      "equipment",
      "kitchen",
      "cabinet"
    ],
    "wof:name": "All Elite Sales Inc",
    "wof:placetype": "venue"
  },
  "geometry": {"coordinates":[-81.437814,41.384805],"type":"Point"}
}
