{
  "type": "Feature",
  "properties": {
    "iso:country":"US",
    "sg:address":"6724 E Main St",
    "sg:city":"Reynoldsburg",
    "sg:classifiers":[
        {
            "category":"Retail",
            "subcategory":"Veterinary Services",
            "type":"Services"
        }
    ],
    "sg:phone":"+1 614 868 5000",
    "sg:postcode":"43068",
    "sg:province":"OH",
    "sg:tags":[
        "veterinarian"
    ],
    "wof:name":"Rose Hill Veterinary Hospital",
    "wof:placetype":"venue"
},
  "geometry": {"coordinates":[-82.816014,39.955085],"type":"Point"}
}