{
  "type": "Feature",
  "properties": {
    "addr:full":"14600 Detroit Ave Cleveland OH 44107",
    "addr:housenumber":"14600",
    "addr:postcode":"44107",
    "addr:street":"Detroit Ave",
    "iso:country":"US",
    "sg:address":"14600 Detroit Ave",
    "sg:city":"Cleveland",
    "sg:classifiers":[
        {
            "category":"Professional",
            "subcategory":"Computer Services",
            "type":"Services"
        }
    ],
    "sg:phone":"+1 216 226 7101",
    "sg:postcode":"44107",
    "sg:province":"OH",
    "sg:website":"www.lazorpoint.com",
    "wof:name":"Lazorpoint Inc",
    "wof:placetype":"venue"
},
  "geometry": {"coordinates":[-81.798293,41.485175],"type":"Point"}
}