{
  "type": "Feature",
  "properties": {
    "addr:full": "2727 Youngstown Rd SE Warren OH 44484",
    "addr:housenumber": "2727",
    "addr:postcode": "44484",
    "addr:street": "Youngstown Rd Se",
    "iso:country": "US",
    "sg:address": "2727 Youngstown Rd SE",
    "sg:city": "Warren",
    "sg:classifiers": [
      {
        "category": "Restaurant",
        "type": "Food \u0026 Drink"
      }
    ],
    "sg:phone": "+1 330 369 4370",
    "sg:postcode": "44484",
    "sg:province": "OH",
    "sg:tags": [
      "eating"
    ],
    "wof:name": "Mr R's Food Carry Out",
    "wof:placetype": "venue"
  },
  "geometry": {"coordinates":[-80.783168,41.221832],"type":"Point"}
}
