{
  "type": "Feature",
  "properties": {
    "iso:country":"US",
    "sg:address":"2727 Youngstown Rd SE",
    "sg:city":"Warren",
    "sg:classifiers":[
        {
            "category":"Restaurant",
            "type":"Food & Drink"
        }
    ],
    "sg:phone":"+1 330 369 4370",
    "sg:postcode":"44484",
    "sg:province":"OH",
    "sg:tags":[
        "eating"
    ],
    "wof:name":"Mr R's Food Carry Out",
    "wof:placetype":"venue"
},
  "geometry": {"coordinates":[-80.783168,41.221832],"type":"Point"}
}