{
  "type": "Feature",
  "properties": {
    "iso:country":"US",
    "sg:address":"535 W Loveland Ave",
    "sg:city":"Loveland",
    "sg:classifiers":[
        {
            "category":"Cinema",
            "subcategory":"Movie Rental",
            "type":"Entertainment"
        }
    ],
    "sg:phone":"+1 513 583 0611",
    "sg:postcode":"45140",
    "sg:province":"OH",
    "sg:tags":[
        "video"
    ],
    "wof:name":"Movie Gallery 793",
    "wof:placetype":"venue"
},
  "geometry": {"coordinates":[-84.265235,39.268964],"type":"Point"}
}