{
  "type": "Feature",
  "properties": {
    "addr:full":"23280 Wainwright Ter Olmsted Falls OH 44138",
    "addr:housenumber":"23280",
    "addr:postcode":"44138",
    "addr:street":"Wainwright Ter",
    "iso:country":"US",
    "sg:address":"23280 Wainwright Ter",
    "sg:city":"Olmsted Falls",
    "sg:classifiers":[
        {
            "category":"Professional",
            "type":"Services"
        }
    ],
    "sg:phone":"+1 440 891 0717",
    "sg:postcode":"44138",
    "sg:province":"OH",
    "wof:name":"Kirk S Dickman",
    "wof:placetype":"venue"
},
  "geometry": {"coordinates":[-81.88031100000001,41.353965],"type":"Point"}
}