{
  "type": "Feature",
  "properties": {
    "addr:full":"5330 Ridge Ave Cincinnati OH 45213",
    "addr:housenumber":"5330",
    "addr:postcode":"45213",
    "addr:street":"Ridge Ave",
    "iso:country":"US",
    "sg:address":"5330 Ridge Ave",
    "sg:city":"Cincinnati",
    "sg:classifiers":[
        {
            "category":"Restaurant",
            "type":"Food & Drink"
        }
    ],
    "sg:phone":"+1 513 531 3389",
    "sg:postcode":"45213",
    "sg:province":"OH",
    "sg:tags":[
        "eating"
    ],
    "wof:name":"Wendys",
    "wof:placetype":"venue"
},
  "geometry": {"coordinates":[-84.42433,39.169027],"type":"Point"}
}