{
  "type": "Feature",
  "properties": {
    "addr:full": "11385 Montgomery Rd Cincinnati OH 45249",
    "addr:housenumber": "11385",
    "addr:postcode": "45249",
    "addr:street": "Montgomery Rd",
    "iso:country": "US",
    "sg:address": "11385 Montgomery Rd",
    "sg:city": "Cincinnati",
    "sg:classifiers": [
      {
        "category": "Social Services",
        "type": "Services"
      }
    ],
    "sg:phone": "+1 513 469 6226",
    "sg:postcode": "45249",
    "sg:province": "OH",
    "sg:tags": [
      "counselor",
      "marriage",
      "family"
    ],
    "wof:name": "Clinical Counseling Svc",
    "wof:placetype": "venue"
  },
  "geometry": {"coordinates":[-84.328563,39.270473],"type":"Point"}
}
