{
  "type": "Feature",
  "properties": {
    "addr:full":"830 Tryon Ave Akron OH 44310",
    "addr:housenumber":"830",
    "addr:postcode":"44310",
    "addr:street":"Tryon Ave",
    "iso:country":"US",
    "sg:address":"830 Tryon Ave",
    "sg:city":"Akron",
    "sg:classifiers":[
        {
            "category":"Wholesale",
            "subcategory":"Auto Parts",
            "type":"Manufacturing & Wholesale Goods"
        }
    ],
    "sg:phone":"+1 330 374 0209",
    "sg:postcode":"44310",
    "sg:province":"OH",
    "sg:tags":[
        "material",
        "used"
    ],
    "wof:name":"Pacific Core Supply",
    "wof:placetype":"venue"
},
  "geometry": {"coordinates":[-81.487442,41.094143],"type":"Point"}
}