{
  "type": "Feature",
  "properties": {
    "addr:full":"6911 Main St Cincinnati OH 45244",
    "addr:housenumber":"6911",
    "addr:postcode":"45244",
    "addr:street":"Main St",
    "iso:country":"US",
    "sg:address":"6911 Main St",
    "sg:city":"Cincinnati",
    "sg:classifiers":[
        {
            "category":"Shopping",
            "subcategory":"Used Merchandise",
            "type":"Retail Goods"
        }
    ],
    "sg:phone":"+1 513 271 0278",
    "sg:postcode":"45244",
    "sg:province":"OH",
    "wof:name":"Winfield House",
    "wof:placetype":"venue"
},
  "geometry": {"coordinates":[-84.359523,39.124477],"type":"Point"}
}