{
  "type": "Feature",
  "properties": {
    "iso:country":"US",
    "sg:address":"6991 Springledge Rd",
    "sg:city":"Northfield",
    "sg:classifiers":[
        {
            "category":"Professional",
            "type":"Services"
        }
    ],
    "sg:phone":"+1 330 467 0603",
    "sg:postcode":"44067",
    "sg:province":"OH",
    "wof:name":"Marteting Alternatives",
    "wof:placetype":"venue"
},
  "geometry": {"coordinates":[-81.550291,41.319508],"type":"Point"}
}