{
  "type": "Feature",
  "properties": {
    "iso:country":"US",
    "sg:address":"5615 Chevrolet Blvd",
    "sg:city":"Cleveland",
    "sg:classifiers":[
        {
            "category":"Shopping",
            "subcategory":"Gifts & Souvenirs",
            "type":"Retail Goods"
        }
    ],
    "sg:phone":"+1 216 265 5002",
    "sg:postcode":"44130",
    "sg:province":"OH",
    "wof:name":"Caddy Shack Incthe",
    "wof:placetype":"venue"
},
  "geometry": {"coordinates":[-81.768884,41.40643],"type":"Point"}
}