{
  "type": "Feature",
  "properties": {
    "addr:full":"2058 Oregon Rd Celina OH 45822",
    "addr:housenumber":"2058",
    "addr:postcode":"45822",
    "addr:street":"Oregon Rd",
    "iso:country":"US",
    "sg:address":"2058 Oregon Rd",
    "sg:city":"Celina",
    "sg:classifiers":[
        {
            "category":"Retail",
            "subcategory":"Repair Shop",
            "type":"Services"
        }
    ],
    "sg:phone":"+1 419 942 1098",
    "sg:postcode":"45822",
    "sg:province":"OH",
    "sg:tags":[
        "taxidermist"
    ],
    "wof:name":"Mike's Taxidermy",
    "wof:placetype":"venue"
},
  "geometry": {"coordinates":[-84.724906,40.611202],"type":"Point"}
}