{
  "type": "Feature",
  "properties": {
    "iso:country":"US",
    "sg:address":"267 E State St",
    "sg:city":"Salem",
    "sg:classifiers":[
        {
            "category":"Wholesale",
            "subcategory":"Farm Supplies",
            "type":"Manufacturing & Wholesale Goods"
        }
    ],
    "sg:phone":"+1 330 332 0776",
    "sg:postcode":"44460",
    "sg:province":"OH",
    "wof:name":"Aid Pest Control",
    "wof:placetype":"venue"
},
  "geometry": {"coordinates":[-80.85652899999999,40.900878],"type":"Point"}
}