{
  "type": "Feature",
  "properties": {
    "addr:full": "267 E State St Salem OH 44460",
    "addr:housenumber": "267",
    "addr:postcode": "44460",
    "addr:street": "E State St",
    "iso:country": "US",
    "sg:address": "267 E State St",
    "sg:city": "Salem",
    "sg:classifiers": [
      {
        "category": "Wholesale",
        "subcategory": "Farm Supplies",
        "type": "Manufacturing \u0026 Wholesale Goods"
      }
    ],
    "sg:phone": "+1 330 332 0776",
    "sg:postcode": "44460",
    "sg:province": "OH",
    "wof:name": "Aid Pest Control",
    "wof:placetype": "venue"
  },
  "geometry": {"coordinates":[-80.856529,40.900878],"type":"Point"}
}
