{
  "type": "Feature",
  "properties": {
    "addr:full": "39825 State Rte 143 Pomeroy OH 45769",
    "addr:housenumber": "39825",
    "addr:postcode": "45769",
    "addr:street": "State Rte 143",
    "iso:country": "US",
    "sg:address": "39825 State Rte 143",
    "sg:city": "Pomeroy",
    "sg:classifiers": [
      {
        "category": "Bars \u0026 Pubs",
        "type": "Food \u0026 Drink"
      }
    ],
    "sg:phone": "+1 740 992 6870",
    "sg:postcode": "45769",
    "sg:province": "OH",
    "sg:tags": [
      "drinking"
    ],
    "wof:name": "Mizway Tavern Inc",
    "wof:placetype": "venue"
  },
  "geometry": {"coordinates":[-82.063075,39.043631],"type":"Point"}
}
