{
  "type": "Feature",
  "properties": {
    "iso:country":"US",
    "sg:address":"39825 State Rte 143",
    "sg:city":"Pomeroy",
    "sg:classifiers":[
        {
            "category":"Bars & Pubs",
            "type":"Food & Drink"
        }
    ],
    "sg:phone":"+1 740 992 6870",
    "sg:postcode":"45769",
    "sg:province":"OH",
    "sg:tags":[
        "drinking"
    ],
    "wof:name":"Mizway Tavern Inc",
    "wof:placetype":"venue"
},
  "geometry": {"coordinates":[-82.063075,39.043631],"type":"Point"}
}