{
  "type": "Feature",
  "properties": {
    "addr:full": "405 N 3rd St Hamilton OH 45011",
    "addr:housenumber": "405",
    "addr:postcode": "45011",
    "addr:street": "N 3Rd St",
    "iso:country": "US",
    "sg:address": "405 N 3rd St",
    "sg:city": "Hamilton",
    "sg:classifiers": [
      {
        "category": "Personal",
        "type": "Services"
      }
    ],
    "sg:phone": "+1 513 892 1777",
    "sg:postcode": "45011",
    "sg:province": "OH",
    "sg:tags": [
      "therapist",
      "massage"
    ],
    "wof:name": "Heaven On Seventh",
    "wof:placetype": "venue"
  },
  "geometry": {"coordinates":[-84.557913,39.404396],"type":"Point"}
}
