{
  "type": "Feature",
  "properties": {
    "iso:country":"US",
    "sg:address":"8809 Castleford Ln",
    "sg:city":"Cincinnati",
    "sg:classifiers":[
        {
            "category":"Wholesale",
            "subcategory":"Machinery & Supplies",
            "type":"Manufacturing & Wholesale Goods"
        }
    ],
    "sg:phone":"+1 513 984 1943",
    "sg:postcode":"45242",
    "sg:province":"OH",
    "sg:tags":[
        "pump"
    ],
    "wof:name":"Mechanical Equip Distributors",
    "wof:placetype":"venue"
},
  "geometry": {"coordinates":[-84.368172,39.239405],"type":"Point"}
}