{
  "type": "Feature",
  "properties": {
    "addr:full": "8809 Castleford Ln Cincinnati OH 45242",
    "addr:housenumber": "8809",
    "addr:postcode": "45242",
    "addr:street": "Castleford Ln",
    "iso:country": "US",
    "sg:address": "8809 Castleford Ln",
    "sg:city": "Cincinnati",
    "sg:classifiers": [
      {
        "category": "Wholesale",
        "subcategory": "Machinery \u0026 Supplies",
        "type": "Manufacturing \u0026 Wholesale Goods"
      }
    ],
    "sg:phone": "+1 513 984 1943",
    "sg:postcode": "45242",
    "sg:province": "OH",
    "sg:tags": [
      "pump"
    ],
    "wof:name": "Mechanical Equip Distributors",
    "wof:placetype": "venue"
  },
  "geometry": {"coordinates":[-84.368172,39.239405],"type":"Point"}
}
