{
  "type": "Feature",
  "properties": {
    "addr:full": "448 E Tiffin St Willard OH 44890",
    "addr:housenumber": "448",
    "addr:postcode": "44890",
    "addr:street": "E Tiffin St",
    "iso:country": "US",
    "sg:address": "448 E Tiffin St",
    "sg:city": "Willard",
    "sg:classifiers": [
      {
        "category": "Building \u0026 Trades",
        "subcategory": "Plumbing",
        "type": "Services"
      }
    ],
    "sg:phone": "+1 419 933 6666",
    "sg:postcode": "44890",
    "sg:province": "OH",
    "sg:tags": [
      "plumbing",
      "contractor"
    ],
    "wof:name": "Harold J Schodorf \u0026 Assoc",
    "wof:placetype": "venue"
  },
  "geometry": {"coordinates":[-82.718323,41.053109],"type":"Point"}
}
