{
  "type": "Feature",
  "properties": {
    "iso:country":"US",
    "sg:address":"6111 Highton St SW",
    "sg:city":"Navarre",
    "sg:classifiers":[
        {
            "category":"Organizations",
            "subcategory":"Labor Organization",
            "type":"Services"
        }
    ],
    "sg:phone":"+1 330 833 4753",
    "sg:postcode":"44662",
    "sg:province":"OH",
    "wof:name":"United Steel Workers",
    "wof:placetype":"venue"
},
  "geometry": {"coordinates":[-81.469452,40.747093],"type":"Point"}
}