{
  "type": "Feature",
  "properties": {
    "iso:country":"US",
    "sg:address":"56120 National Rd",
    "sg:city":"Bridgeport",
    "sg:classifiers":[
        {
            "category":"Restaurant",
            "type":"Food & Drink"
        }
    ],
    "sg:phone":"+1 740 635 1613",
    "sg:postcode":"43912",
    "sg:province":"OH",
    "sg:tags":[
        "eating"
    ],
    "wof:name":"Wendys",
    "wof:placetype":"venue"
},
  "geometry": {"coordinates":[-80.768361,40.068539],"type":"Point"}
}