{
  "type": "Feature",
  "properties": {
    "addr:full":"277 Kearney St Cincinnati OH 45216",
    "addr:housenumber":"277",
    "addr:postcode":"45216",
    "addr:street":"Kearney St",
    "iso:country":"US",
    "sg:address":"277 Kearney St",
    "sg:city":"Cincinnati",
    "sg:classifiers":[
        {
            "category":"Building & Trades",
            "subcategory":"Construction",
            "type":"Services"
        }
    ],
    "sg:phone":"+1 513 616 3069",
    "sg:postcode":"45216",
    "sg:province":"OH",
    "wof:name":"Five Star Home Improvement",
    "wof:placetype":"venue"
},
  "geometry": {"coordinates":[-84.46773899999999,39.210171],"type":"Point"}
}