{
  "type": "Feature",
  "properties": {
    "iso:country":"US",
    "sg:address":"7572 State Rte 241",
    "sg:city":"Millersburg",
    "sg:classifiers":[
        {
            "category":"Bus Charters",
            "type":"Transportation"
        }
    ],
    "sg:phone":"+1 330 674 1234",
    "sg:postcode":"44654",
    "sg:province":"OH",
    "sg:tags":[
        "rental"
    ],
    "sg:website":"www.pioneertrailsbus.com",
    "wof:name":"Pioneer Trails",
    "wof:placetype":"venue"
},
  "geometry": {"coordinates":[-81.816655,40.620269],"type":"Point"}
}