{
  "type": "Feature",
  "properties": {
    "addr:full":"776 N Main St Springboro OH 45066",
    "addr:housenumber":"776",
    "addr:postcode":"45066",
    "addr:street":"N Main St",
    "iso:country":"US",
    "sg:address":"776 N Main St",
    "sg:city":"Springboro",
    "sg:classifiers":[
        {
            "category":"Restaurant",
            "type":"Food & Drink"
        }
    ],
    "sg:phone":"+1 937 748 8877",
    "sg:postcode":"45066",
    "sg:province":"OH",
    "wof:name":"Paul Sturkey's Encore",
    "wof:placetype":"venue"
},
  "geometry": {"coordinates":[-84.231253,39.572492],"type":"Point"}
}