{
  "type": "Feature",
  "properties": {
    "iso:country":"US",
    "sg:address":"3025 Olentangy River Rd",
    "sg:city":"Columbus",
    "sg:classifiers":[
        {
            "category":"Restaurant",
            "type":"Food & Drink"
        }
    ],
    "sg:menulink":"http://www.allmenus.com/oh/columbus/16994-damons-grill/menu/",
    "sg:phone":"+1 614 262 6208",
    "sg:postcode":"43202",
    "sg:province":"OH",
    "sg:tags":[
        "barbecue",
        "american",
        "steakhouse",
        "burger"
    ],
    "wof:name":"Damon's Grill",
    "wof:placetype":"venue"
},
  "geometry": {"coordinates":[-83.025452,40.022561],"type":"Point"}
}