{
  "type": "Feature",
  "properties": {
    "addr:full": "11033 Reed Hartman Hwy Cincinnati OH 45242",
    "addr:housenumber": "11033",
    "addr:postcode": "45242",
    "addr:street": "Reed Hartman Hwy",
    "iso:country": "US",
    "sg:address": "11033 Reed Hartman Hwy",
    "sg:city": "Cincinnati",
    "sg:classifiers": [
      {
        "category": "Professional",
        "subcategory": "Employment Agencies",
        "type": "Services"
      }
    ],
    "sg:phone": "+1 513 733 8655",
    "sg:postcode": "45242",
    "sg:province": "OH",
    "sg:tags": [
      "temporary"
    ],
    "wof:name": "Manpower",
    "wof:placetype": "venue"
  },
  "geometry": {"coordinates":[-84.379877,39.264499],"type":"Point"}
}
