{
  "type": "Feature",
  "properties": {
    "addr:full":"914 Delhi Dr Trenton OH 45067",
    "addr:housenumber":"914",
    "addr:postcode":"45067",
    "addr:street":"Delhi Dr",
    "iso:country":"US",
    "sg:address":"914 Delhi Dr",
    "sg:city":"Trenton",
    "sg:classifiers":[
        {
            "category":"Insurance",
            "subcategory":"Insurance Agent",
            "type":"Services"
        }
    ],
    "sg:phone":"+1 513 738 1117",
    "sg:postcode":"45067",
    "sg:province":"OH",
    "wof:name":"Conrad Insurance",
    "wof:placetype":"venue"
},
  "geometry": {"coordinates":[-84.456582,39.468164],"type":"Point"}
}