{
  "type": "Feature",
  "properties": {
    "iso:country":"US",
    "sg:address":"2920 Douglas Rd",
    "sg:city":"Toledo",
    "sg:classifiers":[
        {
            "category":"Wholesale",
            "subcategory":"Construction Materials",
            "type":"Manufacturing & Wholesale Goods"
        },
        {
            "category":"Home & Garden",
            "subcategory":"Building Materials",
            "type":"Retail Goods"
        }
    ],
    "sg:phone":"+1 419 475 2477",
    "sg:postcode":"43606",
    "sg:province":"OH",
    "sg:tags":[
        "roofing",
        "consulting",
        "business"
    ],
    "sg:website":"www.nccr.com",
    "wof:name":"North Coast Commercial Roofing",
    "wof:placetype":"venue"
},
  "geometry": {"coordinates":[-83.60774000000001,41.673182],"type":"Point"}
}