{
  "type": "Feature",
  "properties": {
    "addr:full": "7913 Chardon Rd Kirtland OH 44094",
    "addr:housenumber": "7913",
    "addr:postcode": "44094",
    "addr:street": "Chardon Rd",
    "iso:country": "US",
    "sg:address": "7913 Chardon Rd",
    "sg:city": "Kirtland",
    "sg:classifiers": [
      {
        "category": "Retail",
        "subcategory": "Car Wash",
        "type": "Services"
      }
    ],
    "sg:phone": "+1 440 256 0121",
    "sg:postcode": "44094",
    "sg:province": "OH",
    "sg:tags": [
      "automobile",
      "detail",
      "clean"
    ],
    "wof:name": "Kirtland Auto Detailing",
    "wof:placetype": "venue"
  },
  "geometry": {"coordinates":[-81.362647,41.583987],"type":"Point"}
}
