{
  "type": "Feature",
  "properties": {
    "iso:country":"US",
    "sg:address":"2226 E Main St",
    "sg:city":"Columbus",
    "sg:classifiers":[
        {
            "category":"Manufacturing",
            "subcategory":"Printing",
            "type":"Manufacturing & Wholesale Goods"
        }
    ],
    "sg:phone":"+1 614 237 0396",
    "sg:postcode":"43209",
    "sg:province":"OH",
    "sg:tags":[
        "lithographic",
        "commercial"
    ],
    "wof:name":"Bexley Copy Shop",
    "wof:placetype":"venue"
},
  "geometry": {"coordinates":[-82.938501,39.957272],"type":"Point"}
}