{
  "type": "Feature",
  "properties": {
    "addr:full":"116 Douglas Ave Chillicothe OH 45601",
    "addr:housenumber":"116",
    "addr:postcode":"45601",
    "addr:street":"Douglas Ave",
    "iso:country":"US",
    "sg:address":"116 Douglas Ave",
    "sg:city":"Chillicothe",
    "sg:classifiers":[
        {
            "category":"Building & Trades",
            "subcategory":"Landscaping Services",
            "type":"Services"
        }
    ],
    "sg:phone":"+1 740 775 0263",
    "sg:postcode":"45601",
    "sg:province":"OH",
    "sg:tags":[
        "tree"
    ],
    "wof:name":"Eblin's Tree Svc",
    "wof:placetype":"venue"
},
  "geometry": {"coordinates":[-82.95628600000001,39.333988],"type":"Point"}
}