{
  "type": "Feature",
  "properties": {
    "addr:full":"422 Deep Cut Rd Spencerville OH 45887",
    "addr:housenumber":"422",
    "addr:postcode":"45887",
    "addr:street":"Deep Cut Rd",
    "iso:country":"US",
    "sg:address":"422 Deep Cut Rd",
    "sg:city":"Spencerville",
    "sg:phone":"+1 419 647 6120",
    "sg:postcode":"45887",
    "sg:province":"OH",
    "sg:tags":[
        "farm",
        "corn",
        "wheat",
        "soybean"
    ],
    "wof:name":"Norris Sawmiller",
    "wof:placetype":"venue"
},
  "geometry": {"coordinates":[-84.444754,40.677344],"type":"Point"}
}