{
  "type": "Feature",
  "properties": {
    "addr:full": "419 E Union St Circleville OH 43113",
    "addr:housenumber": "419",
    "addr:postcode": "43113",
    "addr:street": "E Union St",
    "iso:country": "US",
    "sg:address": "419 E Union St",
    "sg:city": "Circleville",
    "sg:classifiers": [
      {
        "category": "Banks \u0026 Credit Unions",
        "subcategory": "Financial Services",
        "type": "Services"
      }
    ],
    "sg:phone": "+1 740 474 2264",
    "sg:postcode": "43113",
    "sg:province": "OH",
    "sg:tags": [
      "trust",
      "management"
    ],
    "wof:name": "Elliott Family Trust",
    "wof:placetype": "venue"
  },
  "geometry": {"coordinates":[-82.938961,39.596369],"type":"Point"}
}
