{
  "type": "Feature",
  "properties": {
    "addr:full": "4628 Dogwood Dr Brunswick OH 44212",
    "addr:housenumber": "4628",
    "addr:postcode": "44212",
    "addr:street": "Dogwood Dr",
    "iso:country": "US",
    "sg:address": "4628 Dogwood Dr",
    "sg:city": "Brunswick",
    "sg:classifiers": [
      {
        "category": "Building \u0026 Trades",
        "subcategory": "Electrical",
        "type": "Services"
      }
    ],
    "sg:phone": "+1 330 558 0066",
    "sg:postcode": "44212",
    "sg:province": "OH",
    "sg:tags": [
      "telecommunication",
      "contractor"
    ],
    "wof:name": "Symon Communications",
    "wof:placetype": "venue"
  },
  "geometry": {"coordinates":[-81.853136,41.2536],"type":"Point"}
}
