{
  "type": "Feature",
  "properties": {
    "iso:country":"US",
    "sg:address":"4628 Dogwood Dr",
    "sg:city":"Brunswick",
    "sg:classifiers":[
        {
            "category":"Building & Trades",
            "subcategory":"Electrical",
            "type":"Services"
        }
    ],
    "sg:phone":"+1 330 558 0066",
    "sg:postcode":"44212",
    "sg:province":"OH",
    "sg:tags":[
        "telecommunication",
        "contractor"
    ],
    "wof:name":"Symon Communications",
    "wof:placetype":"venue"
},
  "geometry": {"coordinates":[-81.85313600000001,41.2536],"type":"Point"}
}