{
  "type": "Feature",
  "properties": {
    "addr:full":"775 W Schrock Rd Columbus OH 43229",
    "addr:housenumber":"775",
    "addr:postcode":"43229",
    "addr:street":"W Schrock Rd",
    "iso:country":"US",
    "sg:address":"775 W Schrock Rd",
    "sg:city":"Columbus",
    "sg:classifiers":[
        {
            "category":"Retail",
            "subcategory":"Auto Rental",
            "type":"Services"
        }
    ],
    "sg:phone":"+1 614 846 6780",
    "sg:postcode":"43229",
    "sg:province":"OH",
    "sg:tags":[
        "renting",
        "truck",
        "leasing"
    ],
    "wof:name":"Budget Truck Rental",
    "wof:placetype":"venue"
},
  "geometry": {"coordinates":[-82.99189800000001,40.102018],"type":"Point"}
}