{
  "type": "Feature",
  "properties": {
    "addr:full": "1199 Corrugated Way Columbus OH 43201",
    "addr:housenumber": "1199",
    "addr:postcode": "43201",
    "addr:street": "Corrugated Way",
    "iso:country": "US",
    "sg:address": "1199 Corrugated Way",
    "sg:city": "Columbus",
    "sg:classifiers": [
      {
        "category": "Banks \u0026 Credit Unions",
        "subcategory": "Bank",
        "type": "Services"
      }
    ],
    "sg:phone": "+1 614 248 2083",
    "sg:postcode": "43201",
    "sg:province": "OH",
    "wof:name": "Bank One",
    "wof:placetype": "venue"
  },
  "geometry": {"coordinates":[-82.990513,39.989299],"type":"Point"}
}
