{
  "type": "Feature",
  "properties": {
    "addr:full": "2500 Metrohealth Dr Cleveland OH 44109",
    "addr:postcode": "2500;44109",
    "addr:street": "Metrohealth Dr",
    "iso:country": "US",
    "sg:address": "2500 Metrohealth Dr",
    "sg:city": "Cleveland",
    "sg:classifiers": [
      {
        "category": "Health Services",
        "subcategory": "Doctor",
        "type": "Services"
      }
    ],
    "sg:phone": "+1 216 778 4982",
    "sg:postcode": "44109",
    "sg:province": "OH",
    "sg:tags": [
      "physician",
      "surgeon"
    ],
    "wof:name": "Metro Health Dental Associates",
    "wof:placetype": "venue"
  },
  "geometry": {"coordinates":[-81.696854,41.462116],"type":"Point"}
}
