{
  "type": "Feature",
  "properties": {
    "addr:full":"42925 Jones Rd Wellington OH 44090",
    "addr:housenumber":"42925",
    "addr:postcode":"44090",
    "addr:street":"Jones Rd",
    "iso:country":"US",
    "sg:address":"42925 Jones Rd",
    "sg:city":"Wellington",
    "sg:classifiers":[
        {
            "category":"Farming",
            "subcategory":"Nursery",
            "type":"Manufacturing & Wholesale Goods"
        }
    ],
    "sg:phone":"+1 440 647 2045",
    "sg:postcode":"44090",
    "sg:province":"OH",
    "sg:tags":[
        "ornamental"
    ],
    "wof:name":"Days Of Yore",
    "wof:placetype":"venue"
},
  "geometry": {"coordinates":[-82.15820100000001,41.154225],"type":"Point"}
}