{
  "type": "Feature",
  "properties": {
    "addr:full": "1100 E Summit St Kent OH 44240",
    "addr:housenumber": "1100",
    "addr:postcode": "44240",
    "addr:street": "E Summit St",
    "iso:country": "US",
    "sg:address": "1100 E Summit St",
    "sg:city": "Kent",
    "sg:classifiers": [
      {
        "category": "Education",
        "subcategory": "Library",
        "type": "Public Place"
      }
    ],
    "sg:phone": "+1 330 677 5008",
    "sg:postcode": "44240",
    "sg:province": "OH",
    "sg:tags": [
      "special",
      "interest"
    ],
    "wof:name": "National Association Inc Libr",
    "wof:placetype": "venue"
  },
  "geometry": {"coordinates":[-81.344544,41.145693],"type":"Point"}
}
