{
  "type": "Feature",
  "properties": {
    "addr:full":"3820 N High St Columbus OH 43214",
    "addr:housenumber":"3820",
    "addr:postcode":"43214",
    "addr:street":"N High St",
    "iso:country":"US",
    "sg:address":"3820 N High St",
    "sg:city":"Columbus",
    "sg:classifiers":[
        {
            "category":"Real Estate",
            "subcategory":"Architect",
            "type":"Services"
        }
    ],
    "sg:phone":"+1 614 545 1147",
    "sg:postcode":"43214",
    "sg:province":"OH",
    "wof:name":"Manley Architecture Group",
    "wof:placetype":"venue"
},
  "geometry": {"coordinates":[-83.017914,40.039514],"type":"Point"}
}