{
  "type": "Feature",
  "properties": {
    "addr:full": "1041 N River Rd NW Warren OH 44483",
    "addr:housenumber": "1041",
    "addr:postcode": "44483",
    "addr:street": "N River Rd Nw",
    "iso:country": "US",
    "sg:address": "1041 N River Rd NW",
    "sg:city": "Warren",
    "sg:classifiers": [
      {
        "category": "Personal",
        "subcategory": "Nail Salon",
        "type": "Services"
      }
    ],
    "sg:phone": "+1 330 394 0872",
    "sg:postcode": "44483",
    "sg:province": "OH",
    "wof:name": "Nails With Sherry",
    "wof:placetype": "venue"
  },
  "geometry": {"coordinates":[-80.838085,41.268136],"type":"Point"}
}
