{
  "type": "Feature",
  "properties": {
    "addr:full": "1303 Prospect Ave E Cleveland OH 44115",
    "addr:housenumber": "1303",
    "addr:postcode": "44115",
    "addr:street": "Prospect Ave E",
    "iso:country": "US",
    "sg:address": "1303 Prospect Ave E",
    "sg:city": "Cleveland",
    "sg:classifiers": [
      {
        "category": "Social Services",
        "type": "Services"
      }
    ],
    "sg:phone": "+1 216 781 4111",
    "sg:postcode": "44115",
    "sg:province": "OH",
    "sg:tags": [
      "organization",
      "welfare"
    ],
    "wof:name": "Women Helping Women Succeed",
    "wof:placetype": "venue"
  },
  "geometry": {"coordinates":[-81.680846,41.499733],"type":"Point"}
}
