{
  "type": "Feature",
  "properties": {
    "addr:full":"11342 Terrapin Rd Cambridge OH 43725",
    "addr:housenumber":"11342",
    "addr:postcode":"43725",
    "addr:street":"Terrapin Rd",
    "iso:country":"US",
    "sg:address":"11342 Terrapin Rd",
    "sg:city":"Cambridge",
    "sg:classifiers":[
        {
            "category":"Manufacturing",
            "subcategory":"Tools & Machinery",
            "type":"Manufacturing & Wholesale Goods"
        }
    ],
    "sg:phone":"+1 740 439 1777",
    "sg:postcode":"43725",
    "sg:province":"OH",
    "sg:tags":[
        "industrial",
        "mfg"
    ],
    "wof:name":"Murray Tool & Die",
    "wof:placetype":"venue"
},
  "geometry": {"coordinates":[-81.52501599999999,40.07936],"type":"Point"}
}