{
  "type": "Feature",
  "properties": {
    "addr:full": "11342 Terrapin Rd Cambridge OH 43725",
    "addr:housenumber": "11342",
    "addr:postcode": "43725",
    "addr:street": "Terrapin Rd",
    "iso:country": "US",
    "sg:address": "11342 Terrapin Rd",
    "sg:city": "Cambridge",
    "sg:classifiers": [
      {
        "category": "Manufacturing",
        "subcategory": "Tools \u0026 Machinery",
        "type": "Manufacturing \u0026 Wholesale Goods"
      }
    ],
    "sg:phone": "+1 740 439 1777",
    "sg:postcode": "43725",
    "sg:province": "OH",
    "sg:tags": [
      "industrial",
      "mfg"
    ],
    "wof:name": "Murray Tool \u0026 Die",
    "wof:placetype": "venue"
  },
  "geometry": {"coordinates":[-81.525016,40.07936],"type":"Point"}
}
