{
  "type": "Feature",
  "properties": {
    "addr:full": "7217 Market St Youngstown OH 44512",
    "addr:housenumber": "7217",
    "addr:postcode": "44512",
    "addr:street": "Market St",
    "iso:country": "US",
    "sg:address": "7217 Market St",
    "sg:city": "Youngstown",
    "sg:classifiers": [
      {
        "category": "Home \u0026 Garden",
        "subcategory": "Household Appliances",
        "type": "Retail Goods"
      }
    ],
    "sg:phone": "+1 330 726 8891",
    "sg:postcode": "44512",
    "sg:province": "OH",
    "sg:tags": [
      "machine",
      "sewing"
    ],
    "wof:name": "Mc Cormick Vac-N-Sew",
    "wof:placetype": "venue"
  },
  "geometry": {"coordinates":[-80.662661,41.024608],"type":"Point"}
}
