{
  "type": "Feature",
  "properties": {
    "iso:country":"US",
    "sg:address":"874 E Aurora Rd",
    "sg:city":"Macedonia",
    "sg:classifiers":[
        {
            "category":"Home & Garden",
            "subcategory":"Carpets & Floor Coverings",
            "type":"Retail Goods"
        }
    ],
    "sg:phone":"+1 330 468 3449",
    "sg:postcode":"44056",
    "sg:province":"OH",
    "sg:tags":[
        "tile",
        "linoleum"
    ],
    "wof:name":"Alan Carpet Outlet",
    "wof:placetype":"venue"
},
  "geometry": {"coordinates":[-81.50582,41.313709],"type":"Point"}
}