{
  "type": "Feature",
  "properties": {
    "addr:full": "3534 Pinehurst Ave Cincinnati OH 45208",
    "addr:housenumber": "3534",
    "addr:postcode": "45208",
    "addr:street": "Pinehurst Ave",
    "iso:country": "US",
    "sg:address": "3534 Pinehurst Ave",
    "sg:city": "Cincinnati",
    "sg:classifiers": [
      {
        "category": "Insurance",
        "subcategory": "Insurance Agent",
        "type": "Services"
      }
    ],
    "sg:phone": "+1 513 321 9292",
    "sg:postcode": "45208",
    "sg:province": "OH",
    "wof:name": "Dennis J Sweeney Co",
    "wof:placetype": "venue"
  },
  "geometry": {"coordinates":[-84.418542,39.140762],"type":"Point"}
}
