{
  "type": "Feature",
  "properties": {
    "iso:country":"US",
    "sg:address":"151 S Four Mile Run Rd",
    "sg:city":"Youngstown",
    "sg:classifiers":[
        {
            "category":"Building & Trades",
            "subcategory":"Construction",
            "type":"Services"
        }
    ],
    "sg:phone":"+1 330 797 9020",
    "sg:postcode":"44515",
    "sg:province":"OH",
    "sg:tags":[
        "painting",
        "contractor"
    ],
    "wof:name":"Lakeshore Painting Co",
    "wof:placetype":"venue"
},
  "geometry": {"coordinates":[-80.714737,41.098911],"type":"Point"}
}