{
  "type": "Feature",
  "properties": {
    "addr:full":"3367 E 142nd St Cleveland OH 44120",
    "addr:housenumber":"3367",
    "addr:postcode":"44120",
    "addr:street":"E 142Nd St",
    "iso:country":"US",
    "sg:address":"3367 E 142nd St",
    "sg:city":"Cleveland",
    "sg:classifiers":[
        {
            "category":"Personal",
            "type":"Services"
        }
    ],
    "sg:phone":"+1 216 752 9820",
    "sg:postcode":"44120",
    "sg:province":"OH",
    "sg:tags":[
        "credit",
        "debt",
        "counseling"
    ],
    "wof:name":"First Step Credit Solutions",
    "wof:placetype":"venue"
},
  "geometry": {"coordinates":[-81.583389,41.464795],"type":"Point"}
}