{
  "type": "Feature",
  "properties": {
    "addr:full":"3322 Richland Rd Marion OH 43302",
    "addr:housenumber":"3322",
    "addr:postcode":"43302",
    "addr:street":"Richland Rd",
    "iso:country":"US",
    "sg:address":"3322 Richland Rd",
    "sg:city":"Marion",
    "sg:classifiers":[
        {
            "category":"Real Estate",
            "subcategory":"Real Estate Agent",
            "type":"Services"
        }
    ],
    "sg:phone":"+1 740 386 2204",
    "sg:postcode":"43302",
    "sg:province":"OH",
    "sg:tags":[
        "inspection"
    ],
    "wof:name":"Tobin Home & Building Inspctns",
    "wof:placetype":"venue"
},
  "geometry": {"coordinates":[-83.062684,40.519735],"type":"Point"}
}