{
  "type": "Feature",
  "properties": {
    "addr:full":"802 E 305th St Willoughby OH 44095",
    "addr:housenumber":"802",
    "addr:postcode":"44095",
    "addr:street":"E 305Th St",
    "iso:country":"US",
    "sg:address":"802 E 305th St",
    "sg:city":"Willoughby",
    "sg:classifiers":[
        {
            "category":"Professional",
            "type":"Services"
        }
    ],
    "sg:phone":"+1 440 944 3625",
    "sg:postcode":"44095",
    "sg:province":"OH",
    "wof:name":"Spencer L Brady LLC",
    "wof:placetype":"venue"
},
  "geometry": {"coordinates":[-81.462012,41.626924],"type":"Point"}
}