{
  "type": "Feature",
  "properties": {
    "iso:country":"US",
    "sg:address":"36420 Biltmore Pl",
    "sg:city":"Willoughby",
    "sg:classifiers":[
        {
            "category":"Retail",
            "subcategory":"Laundry & Dry Cleaning",
            "type":"Services"
        }
    ],
    "sg:phone":"+1 440 975 1420",
    "sg:postcode":"44094",
    "sg:province":"OH",
    "sg:tags":[
        "cleaners",
        "rug",
        "carpet"
    ],
    "wof:name":"Carpet Advantage",
    "wof:placetype":"venue"
},
  "geometry": {"coordinates":[-81.42496,41.632501],"type":"Point"}
}