{
  "type": "Feature",
  "properties": {
    "addr:full":"1101 N 4th St Columbus OH 43201",
    "addr:housenumber":"1101",
    "addr:postcode":"43201",
    "addr:street":"N 4Th St",
    "iso:country":"US",
    "sg:address":"1101 N 4th St",
    "sg:city":"Columbus",
    "sg:classifiers":[
        {
            "category":"Wholesale",
            "subcategory":"Auto Parts",
            "type":"Manufacturing & Wholesale Goods"
        }
    ],
    "sg:phone":"+1 614 297 8366",
    "sg:postcode":"43201",
    "sg:province":"OH",
    "sg:tags":[
        "tire"
    ],
    "wof:name":"Phainan Tire Svc",
    "wof:placetype":"venue"
},
  "geometry": {"coordinates":[-82.999301,39.984825],"type":"Point"}
}