{
  "type": "Feature",
  "properties": {
    "addr:full": "5130 Arbor Way Sylvania OH 43560",
    "addr:housenumber": "5130",
    "addr:postcode": "43560",
    "addr:street": "Arbor Way",
    "iso:country": "US",
    "sg:address": "5130 Arbor Way",
    "sg:city": "Sylvania",
    "sg:classifiers": [
      {
        "category": "Building \u0026 Trades",
        "subcategory": "Landscaping Services",
        "type": "Services"
      }
    ],
    "sg:phone": "+1 419 882 0720",
    "sg:postcode": "43560",
    "sg:province": "OH",
    "sg:tags": [
      "lawn",
      "maintenance",
      "grounds"
    ],
    "wof:name": "Ohio Mowing Co LLC",
    "wof:placetype": "venue"
  },
  "geometry": {"coordinates":[-83.667494,41.710656],"type":"Point"}
}
