{
  "type": "Feature",
  "properties": {
    "iso:country":"US",
    "sg:address":"600 E Comet Rd",
    "sg:city":"Clinton",
    "sg:classifiers":[
        {
            "category":"Wholesale",
            "subcategory":"Non-durable Goods",
            "type":"Manufacturing & Wholesale Goods"
        }
    ],
    "sg:phone":"+1 330 896 1770",
    "sg:postcode":"44216",
    "sg:province":"OH",
    "sg:tags":[
        "live",
        "bait"
    ],
    "wof:name":"Eddies Bates",
    "wof:placetype":"venue"
},
  "geometry": {"coordinates":[-81.522227,40.924338],"type":"Point"}
}