{
  "type": "Feature",
  "properties": {
    "iso:country":"US",
    "sg:address":"795 Gorge Blvd",
    "sg:city":"Akron",
    "sg:classifiers":[
        {
            "category":"Professional",
            "type":"Services"
        }
    ],
    "sg:phone":"+1 330 253 5201",
    "sg:postcode":"44310",
    "sg:province":"OH",
    "wof:name":"L Ectrik Beach",
    "wof:placetype":"venue"
},
  "geometry": {"coordinates":[-81.499527,41.098042],"type":"Point"}
}