{
  "type": "Feature",
  "properties": {
    "addr:full": "7 W 7th St Cincinnati OH 45202",
    "addr:housenumber": "7",
    "addr:postcode": "45202",
    "addr:street": "W 7Th St",
    "iso:country": "US",
    "sg:address": "7 W 7th St",
    "sg:city": "Cincinnati",
    "sg:classifiers": [
      {
        "category": "Arts \u0026 Performance",
        "subcategory": "Theater",
        "type": "Entertainment"
      }
    ],
    "sg:phone": "+1 513 723 1180",
    "sg:postcode": "45202",
    "sg:province": "OH",
    "wof:name": "Esquire Theatre LTD Prtnrshp",
    "wof:placetype": "venue"
  },
  "geometry": {"coordinates":[-84.513966,39.103569],"type":"Point"}
}
