{
  "type": "Feature",
  "properties": {
    "addr:full":"629 Chestnut St Coshocton OH 43812",
    "addr:housenumber":"629",
    "addr:postcode":"43812",
    "addr:street":"Chestnut St",
    "iso:country":"US",
    "sg:address":"629 Chestnut St",
    "sg:city":"Coshocton",
    "sg:classifiers":[
        {
            "category":"Professional",
            "type":"Services"
        }
    ],
    "sg:phone":"+1 740 622 9245",
    "sg:postcode":"43812",
    "sg:province":"OH",
    "wof:name":"Rich A Pica",
    "wof:placetype":"venue"
},
  "geometry": {"coordinates":[-81.861082,40.27479],"type":"Point"}
}