{
  "type": "Feature",
  "properties": {
    "addr:full":"216 Pinedale Dr Dover OH 44622",
    "addr:housenumber":"216",
    "addr:postcode":"44622",
    "addr:street":"Pinedale Dr",
    "iso:country":"US",
    "sg:address":"216 Pinedale Dr",
    "sg:city":"Dover",
    "sg:classifiers":[
        {
            "category":"Shopping",
            "subcategory":"Hobbies, Toys, & Games",
            "type":"Retail Goods"
        }
    ],
    "sg:phone":"+1 330 364 2773",
    "sg:postcode":"44622",
    "sg:province":"OH",
    "wof:name":"Canal Dover Novelty Company",
    "wof:placetype":"venue"
},
  "geometry": {"coordinates":[-81.48248599999999,40.548389],"type":"Point"}
}