{
  "type": "Feature",
  "properties": {
    "addr:full": "120 E Highland Ave Ravenna OH 44266",
    "addr:housenumber": "120",
    "addr:postcode": "44266",
    "addr:street": "E Highland Ave",
    "iso:country": "US",
    "sg:address": "120 E Highland Ave",
    "sg:city": "Ravenna",
    "sg:classifiers": [
      {
        "category": "Professional",
        "subcategory": "Accounting \u0026 Tax Preparation",
        "type": "Services"
      }
    ],
    "sg:phone": "+1 330 678 5203",
    "sg:postcode": "44266",
    "sg:province": "OH",
    "sg:tags": [
      "accountant"
    ],
    "wof:name": "Hartley Accounting \u0026 Tax Svc",
    "wof:placetype": "venue"
  },
  "geometry": {"coordinates":[-81.241607,41.160096],"type":"Point"}
}
