{
  "type": "Feature",
  "properties": {
    "iso:country":"US",
    "sg:address":"120 E Highland Ave",
    "sg:city":"Ravenna",
    "sg:classifiers":[
        {
            "category":"Professional",
            "subcategory":"Accounting & Tax Preparation",
            "type":"Services"
        }
    ],
    "sg:phone":"+1 330 678 5203",
    "sg:postcode":"44266",
    "sg:province":"OH",
    "sg:tags":[
        "accountant"
    ],
    "wof:name":"Hartley Accounting & Tax Svc",
    "wof:placetype":"venue"
},
  "geometry": {"coordinates":[-81.241607,41.160096],"type":"Point"}
}