{
  "type": "Feature",
  "properties": {
    "addr:full": "28000 Chagrin Blvd Beachwood OH 44122",
    "addr:housenumber": "28000",
    "addr:postcode": "44122",
    "addr:street": "Chagrin Blvd",
    "iso:country": "US",
    "sg:address": "28000 Chagrin Blvd",
    "sg:city": "Beachwood",
    "sg:classifiers": [
      {
        "category": "Retail",
        "subcategory": "Auto Rental",
        "type": "Services"
      }
    ],
    "sg:phone": "+1 216 896 5510",
    "sg:postcode": "44122",
    "sg:province": "OH",
    "sg:tags": [
      "renting",
      "passenger",
      "car",
      "automobile"
    ],
    "sg:website": "www.enterprise.com",
    "wof:name": "Enterprise Rent-A-Car",
    "wof:placetype": "venue"
  },
  "geometry": {"coordinates":[-81.48062,41.462213],"type":"Point"}
}
