{
  "type": "Feature",
  "properties": {
    "addr:full": "310 E Main St Metamora OH 43540",
    "addr:housenumber": "310",
    "addr:postcode": "43540",
    "addr:street": "E Main St",
    "iso:country": "US",
    "sg:address": "310 E Main St",
    "sg:city": "Metamora",
    "sg:classifiers": [
      {
        "category": "Building \u0026 Trades",
        "subcategory": "Landscaping Services",
        "type": "Services"
      }
    ],
    "sg:phone": "+1 419 644 3002",
    "sg:postcode": "43540",
    "sg:province": "OH",
    "sg:tags": [
      "tree"
    ],
    "wof:name": "Alternative Tree Svc",
    "wof:placetype": "venue"
  },
  "geometry": {"coordinates":[-83.90797,41.711445],"type":"Point"}
}
