{
  "type": "Feature",
  "properties": {
    "addr:full": "3146 W 40th St Cleveland OH 44109",
    "addr:housenumber": "3146",
    "addr:postcode": "44109",
    "addr:street": "W 40Th St",
    "iso:country": "US",
    "sg:address": "3146 W 40th St",
    "sg:city": "Cleveland",
    "sg:classifiers": [
      {
        "category": "Wholesale",
        "subcategory": "Books, Periodicals, \u0026 Newspapers",
        "type": "Manufacturing \u0026 Wholesale Goods"
      }
    ],
    "sg:phone": "+1 216 355 2318",
    "sg:postcode": "44109",
    "sg:province": "OH",
    "sg:tags": [
      "dealer"
    ],
    "wof:name": "Simplicity Enterprise",
    "wof:placetype": "venue"
  },
  "geometry": {"coordinates":[-81.71224,41.468995],"type":"Point"}
}
