{
  "type": "Feature",
  "properties": {
    "iso:country":"US",
    "sg:address":"3146 W 40th St",
    "sg:city":"Cleveland",
    "sg:classifiers":[
        {
            "category":"Wholesale",
            "subcategory":"Books, Periodicals, & Newspapers",
            "type":"Manufacturing & Wholesale Goods"
        }
    ],
    "sg:phone":"+1 216 355 2318",
    "sg:postcode":"44109",
    "sg:province":"OH",
    "sg:tags":[
        "dealer"
    ],
    "wof:name":"Simplicity Enterprise",
    "wof:placetype":"venue"
},
  "geometry": {"coordinates":[-81.71223999999999,41.468995],"type":"Point"}
}