{
  "type": "Feature",
  "properties": {
    "iso:country":"US",
    "sg:address":"2355 W Market St",
    "sg:city":"Tiffin",
    "sg:classifiers":[
        {
            "category":"Health Services",
            "subcategory":"Doctor",
            "type":"Services"
        }
    ],
    "sg:phone":"+1 419 447 0253",
    "sg:postcode":"44883",
    "sg:province":"OH",
    "sg:tags":[
        "dentist"
    ],
    "wof:name":"Robert J Dornauer Inc",
    "wof:placetype":"venue"
},
  "geometry": {"coordinates":[-83.215774,41.109783],"type":"Point"}
}