{
  "type": "Feature",
  "properties": {
    "iso:country":"US",
    "sg:address":"8 E Broad St",
    "sg:city":"Newton Falls",
    "sg:classifiers":[
        {
            "category":"Retail",
            "subcategory":"Funeral Services",
            "type":"Services"
        }
    ],
    "sg:phone":"+1 330 872 5440",
    "sg:postcode":"44444",
    "sg:province":"OH",
    "sg:tags":[
        "home"
    ],
    "wof:name":"James Funeral Home Inc",
    "wof:placetype":"venue"
},
  "geometry": {"coordinates":[-80.97343100000001,41.186923],"type":"Point"}
}