{
  "type": "Feature",
  "properties": {
    "addr:full": "222 Piedmont Ave Ste 1700 Cincinnati OH 45219",
    "addr:housenumber": "222",
    "addr:postcode": "45219",
    "addr:street": "Piedmont Ave Ste 1700",
    "iso:country": "US",
    "sg:address": "222 Piedmont Ave Ste 1700",
    "sg:city": "Cincinnati",
    "sg:classifiers": [
      {
        "category": "Shopping",
        "subcategory": "Optical Goods",
        "type": "Retail Goods"
      }
    ],
    "sg:phone": "+1 513 475 7315",
    "sg:postcode": "45219",
    "sg:province": "OH",
    "sg:tags": [
      "eyeglass"
    ],
    "sg:website": "http://www.thomasutton.com",
    "wof:name": "Thoma \u0026 Sutton Eye-Care Professionals",
    "wof:placetype": "venue"
  },
  "geometry": {"coordinates":[-84.50386,39.136101],"type":"Point"}
}
