{
  "type": "Feature",
  "properties": {
    "iso:country":"US",
    "sg:address":"5386 Lake Rd",
    "sg:city":"Sheffield Lake",
    "sg:classifiers":[
        {
            "category":"Personal",
            "subcategory":"Beauty Salon",
            "type":"Services"
        }
    ],
    "sg:phone":"+1 440 949 7380",
    "sg:postcode":"44054",
    "sg:province":"OH",
    "wof:name":"D J's Hair Design",
    "wof:placetype":"venue"
},
  "geometry": {"coordinates":[-82.074403,41.498118],"type":"Point"}
}