{
  "type": "Feature",
  "properties": {
    "iso:country":"US",
    "sg:address":"128 E Main St",
    "sg:city":"Hopedale",
    "sg:classifiers":[
        {
            "category":"Retail",
            "subcategory":"Auto Repair",
            "type":"Services"
        }
    ],
    "sg:phone":"+1 740 937 2321",
    "sg:postcode":"43976",
    "sg:province":"OH",
    "sg:tags":[
        "body",
        "automobile",
        "painting",
        "supply"
    ],
    "wof:name":"Double Auto Body",
    "wof:placetype":"venue"
},
  "geometry": {"coordinates":[-80.898511,40.32597],"type":"Point"}
}