{
  "type": "Feature",
  "properties": {
    "addr:full": "27330 Donald Ave Cleveland OH 44140",
    "addr:housenumber": "27330",
    "addr:postcode": "44140",
    "addr:street": "Donald Ave",
    "iso:country": "US",
    "sg:address": "27330 Donald Ave",
    "sg:city": "Cleveland",
    "sg:classifiers": [
      {
        "category": "Wholesale",
        "subcategory": "Durable Goods \u0026 Equipment",
        "type": "Manufacturing \u0026 Wholesale Goods"
      }
    ],
    "sg:phone": "+1 440 871 2333",
    "sg:postcode": "44140",
    "sg:province": "OH",
    "sg:tags": [
      "representative",
      "manufacturer"
    ],
    "wof:name": "WIL Priver \u0026 Assoc",
    "wof:placetype": "venue"
  },
  "geometry": {"coordinates":[-81.92295,41.479955],"type":"Point"}
}
