{
  "type": "Feature",
  "properties": {
    "addr:full":"10228 Colerain Ave Cincinnati OH 45251",
    "addr:housenumber":"10228",
    "addr:postcode":"45251",
    "addr:street":"Colerain Ave",
    "iso:country":"US",
    "sg:address":"10228 Colerain Ave",
    "sg:city":"Cincinnati",
    "sg:classifiers":[
        {
            "category":"Shopping",
            "subcategory":"Computers & Home Electronics",
            "type":"Retail Goods"
        }
    ],
    "sg:phone":"+1 513 385 5331",
    "sg:postcode":"45251",
    "sg:province":"OH",
    "sg:website":"www.gamestop.com",
    "wof:name":"Gamestop",
    "wof:placetype":"venue"
},
  "geometry": {"coordinates":[-84.602458,39.259372],"type":"Point"}
}