{
  "type": "Feature",
  "properties": {
    "iso:country":"US",
    "sg:address":"106 S Main St",
    "sg:city":"London",
    "sg:classifiers":[
        {
            "category":"Utilities",
            "subcategory":"Mobile Phone",
            "type":"Services"
        }
    ],
    "sg:phone":"+1 740 852 3544",
    "sg:postcode":"43140",
    "sg:province":"OH",
    "sg:tags":[
        "telephone",
        "cellular"
    ],
    "wof:name":"DCW Wireless",
    "wof:placetype":"venue"
},
  "geometry": {"coordinates":[-83.446729,39.884824],"type":"Point"}
}