{
  "type": "Feature",
  "properties": {
    "addr:full":"1199 Mount Vernon Rd Newark OH 43055",
    "addr:housenumber":"1199",
    "addr:postcode":"43055",
    "addr:street":"Mount Vernon Rd",
    "iso:country":"US",
    "sg:address":"1199 Mount Vernon Rd",
    "sg:city":"Newark",
    "sg:classifiers":[
        {
            "category":"Home & Garden",
            "subcategory":"Hardware",
            "type":"Retail Goods"
        }
    ],
    "sg:phone":"+1 740 366 2630",
    "sg:postcode":"43055",
    "sg:province":"OH",
    "wof:name":"Plaza Hardware & Paint",
    "wof:placetype":"venue"
},
  "geometry": {"coordinates":[-82.419209,40.089506],"type":"Point"}
}