{
  "type": "Feature",
  "properties": {
    "iso:country":"US",
    "sg:address":"320 Springside Dr",
    "sg:city":"Akron",
    "sg:classifiers":[
        {
            "category":"Wholesale",
            "subcategory":"Chemicals & Plastics",
            "type":"Manufacturing & Wholesale Goods"
        }
    ],
    "sg:phone":"+1 330 849 5750",
    "sg:postcode":"44333",
    "sg:province":"OH",
    "wof:name":"Exxon Chemical Co",
    "wof:placetype":"venue"
},
  "geometry": {"coordinates":[-81.640712,41.142156],"type":"Point"}
}