{
  "type": "Feature",
  "properties": {
    "addr:full": "320 Springside Dr Akron OH 44333",
    "addr:housenumber": "320",
    "addr:postcode": "44333",
    "addr:street": "Springside Dr",
    "iso:country": "US",
    "sg:address": "320 Springside Dr",
    "sg:city": "Akron",
    "sg:classifiers": [
      {
        "category": "Wholesale",
        "subcategory": "Chemicals \u0026 Plastics",
        "type": "Manufacturing \u0026 Wholesale Goods"
      }
    ],
    "sg:phone": "+1 330 849 5750",
    "sg:postcode": "44333",
    "sg:province": "OH",
    "wof:name": "Exxon Chemical Co",
    "wof:placetype": "venue"
  },
  "geometry": {"coordinates":[-81.640712,41.142156],"type":"Point"}
}
