{
  "type": "Feature",
  "properties": {
    "addr:full": "7017 Vine St Cincinnati OH 45216",
    "addr:housenumber": "7017",
    "addr:postcode": "45216",
    "addr:street": "Vine St",
    "iso:country": "US",
    "sg:address": "7017 Vine St",
    "sg:city": "Cincinnati",
    "sg:classifiers": [
      {
        "category": "Health Services",
        "subcategory": "Doctor",
        "type": "Services"
      }
    ],
    "sg:phone": "+1 513 821 2201",
    "sg:postcode": "45216",
    "sg:province": "OH",
    "sg:tags": [
      "physician",
      "family",
      "practice",
      "surgeons",
      "medicine",
      "surgeon"
    ],
    "wof:name": "Faustop Vasquez Md",
    "wof:placetype": "venue"
  },
  "geometry": {"coordinates":[-84.480926,39.193599],"type":"Point"}
}
