{
  "type": "Feature",
  "properties": {
    "addr:full": "1395 Triplett Blvd Akron OH 44306",
    "addr:housenumber": "1395",
    "addr:postcode": "44306",
    "addr:street": "Triplett Blvd",
    "iso:country": "US",
    "sg:address": "1395 Triplett Blvd",
    "sg:city": "Akron",
    "sg:classifiers": [
      {
        "category": "Wholesale",
        "subcategory": "Auto Parts",
        "type": "Manufacturing \u0026 Wholesale Goods"
      }
    ],
    "sg:phone": "+1 330 794 1535",
    "sg:postcode": "44306",
    "sg:province": "OH",
    "sg:tags": [
      "engine",
      "repair",
      "diesel"
    ],
    "wof:name": "Williams Distribution",
    "wof:placetype": "venue"
  },
  "geometry": {"coordinates":[-81.475419,41.041532],"type":"Point"}
}
