{
  "type": "Feature",
  "properties": {
    "addr:full":"206 N 3rd St Fairborn OH 45324",
    "addr:housenumber":"206",
    "addr:postcode":"45324",
    "addr:street":"N 3Rd St",
    "iso:country":"US",
    "sg:address":"206 N 3rd St",
    "sg:city":"Fairborn",
    "sg:classifiers":[
        {
            "category":"Insurance",
            "subcategory":"Insurance Agent",
            "type":"Services"
        }
    ],
    "sg:phone":"+1 440 354 4664",
    "sg:postcode":"45324",
    "sg:province":"OH",
    "wof:name":"Farmers Insurance",
    "wof:placetype":"venue"
},
  "geometry": {"coordinates":[-84.02502,39.825276],"type":"Point"}
}