{
  "type": "Feature",
  "properties": {
    "addr:full": "1005 Bellefontaine Ave Lima OH 45804",
    "addr:housenumber": "1005",
    "addr:postcode": "45804",
    "addr:street": "Bellefontaine Ave",
    "iso:country": "US",
    "sg:address": "1005 Bellefontaine Ave",
    "sg:city": "Lima",
    "sg:classifiers": [
      {
        "category": "Health Services",
        "subcategory": "Doctor",
        "type": "Services"
      }
    ],
    "sg:phone": "+1 419 229 0415",
    "sg:postcode": "45804",
    "sg:province": "OH",
    "sg:tags": [
      "physician",
      "surgeon"
    ],
    "wof:name": "Neuro Psychiatry Consultants",
    "wof:placetype": "venue"
  },
  "geometry": {"coordinates":[-84.088647,40.736204],"type":"Point"}
}
