{
  "type": "Feature",
  "properties": {
    "iso:country":"US",
    "sg:address":"131 S Market St",
    "sg:city":"Lodi",
    "sg:classifiers":[
        {
            "category":"Building & Trades",
            "subcategory":"Electrical",
            "type":"Services"
        }
    ],
    "sg:phone":"+1 330 948 4140",
    "sg:postcode":"44254",
    "sg:province":"OH",
    "sg:tags":[
        "electric",
        "contractor"
    ],
    "wof:name":"All States Electric Co",
    "wof:placetype":"venue"
},
  "geometry": {"coordinates":[-82.010672,41.02994],"type":"Point"}
}