{
  "type": "Feature",
  "properties": {
    "addr:full": "1383 Rowe St Akron OH 44306",
    "addr:housenumber": "1383",
    "addr:postcode": "44306",
    "addr:street": "Rowe St",
    "iso:country": "US",
    "sg:address": "1383 Rowe St",
    "sg:city": "Akron",
    "sg:classifiers": [
      {
        "category": "Food \u0026 Beverages",
        "subcategory": "Groceries \u0026 Convenience Stores",
        "type": "Retail Goods"
      }
    ],
    "sg:phone": "+1 330 724 2480",
    "sg:postcode": "44306",
    "sg:province": "OH",
    "wof:name": "Coxs Meat \u0026 Food Market",
    "wof:placetype": "venue"
  },
  "geometry": {"coordinates":[-81.502065,41.040547],"type":"Point"}
}
