{
  "type": "Feature",
  "properties": {
    "addr:full":"14925 White Rd Middlefield OH 44062",
    "addr:housenumber":"14925",
    "addr:postcode":"44062",
    "addr:street":"White Rd",
    "iso:country":"US",
    "sg:address":"14925 White Rd",
    "sg:city":"Middlefield",
    "sg:classifiers":[
        {
            "category":"Wholesale",
            "subcategory":"Hardware",
            "type":"Manufacturing & Wholesale Goods"
        }
    ],
    "sg:phone":"+1 440 834 9771",
    "sg:postcode":"44062",
    "sg:province":"OH",
    "wof:name":"Turned In Stone",
    "wof:placetype":"venue"
},
  "geometry": {"coordinates":[-81.108631,41.462666],"type":"Point"}
}