{
  "type": "Feature",
  "properties": {
    "addr:full": "315 N Broad St Lancaster OH 43130",
    "addr:housenumber": "315",
    "addr:postcode": "43130",
    "addr:street": "N Broad St",
    "iso:country": "US",
    "sg:address": "315 N Broad St",
    "sg:city": "Lancaster",
    "sg:classifiers": [
      {
        "category": "Shopping",
        "subcategory": "Florist",
        "type": "Retail Goods"
      }
    ],
    "sg:phone": "+1 740 689 3688",
    "sg:postcode": "43130",
    "sg:province": "OH",
    "wof:name": "Floral Design Gallery",
    "wof:placetype": "venue"
  },
  "geometry": {"coordinates":[-82.601856,39.716618],"type":"Point"}
}
