{
  "type": "Feature",
  "properties": {
    "addr:full": "10701 East Blvd Cleveland OH 44106",
    "addr:housenumber": "10701",
    "addr:postcode": "44106",
    "addr:street": "East Blvd",
    "iso:country": "US",
    "sg:address": "10701 East Blvd",
    "sg:city": "Cleveland",
    "sg:classifiers": [
      {
        "category": "Building \u0026 Trades",
        "subcategory": "Construction",
        "type": "Services"
      }
    ],
    "sg:phone": "+1 216 932 0773",
    "sg:postcode": "44106",
    "sg:province": "OH",
    "sg:tags": [
      "general",
      "contractor"
    ],
    "sg:website": "www.ldvinc.com",
    "wof:name": "LDV Inc",
    "wof:placetype": "venue"
  },
  "geometry": {"coordinates":[-81.61335,41.51264],"type":"Point"}
}
