{
  "type": "Feature",
  "properties": {
    "iso:country":"US",
    "sg:address":"8837 Saint Clair Ave",
    "sg:city":"Cleveland",
    "sg:classifiers":[
        {
            "category":"Organizations",
            "subcategory":"Religious Organization",
            "type":"Services"
        }
    ],
    "sg:phone":"+1 216 451 7125",
    "sg:postcode":"44108",
    "sg:province":"OH",
    "sg:tags":[
        "church"
    ],
    "wof:name":"Church Church Of Christ",
    "wof:placetype":"venue"
},
  "geometry": {"coordinates":[-81.626943,41.533637],"type":"Point"}
}