{
  "type": "Feature",
  "properties": {
    "addr:full": "5301 State Rte 207 Clarksburg OH 43115",
    "addr:housenumber": "5301",
    "addr:postcode": "43115",
    "addr:street": "State Rte 207",
    "iso:country": "US",
    "sg:address": "5301 State Rte 207",
    "sg:city": "Clarksburg",
    "sg:classifiers": [
      {
        "category": "Farming",
        "subcategory": "Farm",
        "type": "Manufacturing \u0026 Wholesale Goods"
      }
    ],
    "sg:phone": "+1 740 775 9964",
    "sg:postcode": "43115",
    "sg:province": "OH",
    "sg:tags": [
      "crop",
      "general"
    ],
    "wof:name": "Charles D Brown",
    "wof:placetype": "venue"
  },
  "geometry": {"coordinates":[-83.067039,39.449215],"type":"Point"}
}
