{
  "type": "Feature",
  "properties": {
    "addr:full":"1395 W Longview Ave Mansfield OH 44906",
    "addr:housenumber":"1395",
    "addr:postcode":"44906",
    "addr:street":"W Longview Ave",
    "iso:country":"US",
    "sg:address":"1395 W Longview Ave",
    "sg:city":"Mansfield",
    "sg:classifiers":[
        {
            "category":"Home & Garden",
            "subcategory":"Building Materials",
            "type":"Retail Goods"
        }
    ],
    "sg:phone":"+1 419 747 4884",
    "sg:postcode":"44906",
    "sg:province":"OH",
    "wof:name":"84 Lumber Co",
    "wof:placetype":"venue"
},
  "geometry": {"coordinates":[-82.566402,40.776081],"type":"Point"}
}