{
  "type": "Feature",
  "properties": {
    "iso:country":"US",
    "sg:address":"904 S Roosevelt Ave",
    "sg:city":"Columbus",
    "sg:classifiers":[
        {
            "category":"Real Estate",
            "subcategory":"Real Estate Operator",
            "type":"Services"
        }
    ],
    "sg:phone":"+1 614 231 4235",
    "sg:postcode":"43209",
    "sg:province":"OH",
    "sg:tags":[
        "building",
        "apartment"
    ],
    "wof:name":"Rosemore Plaza Apartments",
    "wof:placetype":"venue"
},
  "geometry": {"coordinates":[-82.927904,39.950868],"type":"Point"}
}