{
  "type": "Feature",
  "properties": {
    "iso:country":"US",
    "sg:address":"179 W Locust St",
    "sg:city":"Wilmington",
    "sg:classifiers":[
        {
            "category":"Shopping",
            "subcategory":"Pharmacy",
            "type":"Retail Goods"
        }
    ],
    "sg:phone":"+1 937 382 0081",
    "sg:postcode":"45177",
    "sg:province":"OH",
    "wof:name":"Kratzer's Hometown Pharmacy",
    "wof:placetype":"venue"
},
  "geometry": {"coordinates":[-83.832685,39.446843],"type":"Point"}
}