{
  "type": "Feature",
  "properties": {
    "iso:country":"US",
    "sg:address":"6173 State Rte 327",
    "sg:city":"Jackson",
    "sg:classifiers":[
        {
            "category":"Recreation",
            "subcategory":"Amusement Park",
            "type":"Entertainment"
        }
    ],
    "sg:phone":"+1 740 384 5113",
    "sg:postcode":"45640",
    "sg:province":"OH",
    "sg:tags":[
        "equipment",
        "park",
        "trailer"
    ],
    "sg:website":"www.splashdownohio.com",
    "wof:name":"Splash Down Waterpark Inc",
    "wof:placetype":"venue"
},
  "geometry": {"coordinates":[-82.539007,39.070433],"type":"Point"}
}