{
  "type": "Feature",
  "properties": {
    "iso:country":"US",
    "sg:address":"316 Northview Dr",
    "sg:city":"London",
    "sg:classifiers":[
        {
            "category":"Organizations",
            "subcategory":"Religious Organization",
            "type":"Services"
        }
    ],
    "sg:phone":"+1 740 852 3168",
    "sg:postcode":"43140",
    "sg:province":"OH",
    "sg:tags":[
        "clergy"
    ],
    "wof:name":"First Church Of God",
    "wof:placetype":"venue"
},
  "geometry": {"coordinates":[-83.44704400000001,39.903056],"type":"Point"}
}