{
  "type": "Feature",
  "properties": {
    "iso:country":"US",
    "sg:address":"1950 W Market St",
    "sg:city":"Tiffin",
    "sg:classifiers":[
        {
            "category":"Restaurant",
            "type":"Food & Drink"
        }
    ],
    "sg:menulink":"http://www.allmenus.com/oh/tiffin/134263-subway/menu/",
    "sg:phone":"+1 419 448 0300",
    "sg:postcode":"44883",
    "sg:province":"OH",
    "sg:tags":[
        "american",
        "sandwich"
    ],
    "wof:name":"Subway",
    "wof:placetype":"venue"
},
  "geometry": {"coordinates":[-83.20804699999999,41.110935],"type":"Point"}
}