{
  "type": "Feature",
  "properties": {
    "addr:full": "1950 W Market St Tiffin OH 44883",
    "addr:housenumber": "1950",
    "addr:postcode": "44883",
    "addr:street": "W Market St",
    "iso:country": "US",
    "sg:address": "1950 W Market St",
    "sg:city": "Tiffin",
    "sg:classifiers": [
      {
        "category": "Restaurant",
        "type": "Food \u0026 Drink"
      }
    ],
    "sg:menulink": "http://www.allmenus.com/oh/tiffin/134263-subway/menu/",
    "sg:phone": "+1 419 448 0300",
    "sg:postcode": "44883",
    "sg:province": "OH",
    "sg:tags": [
      "american",
      "sandwich"
    ],
    "wof:name": "Subway",
    "wof:placetype": "venue"
  },
  "geometry": {"coordinates":[-83.208047,41.110935],"type":"Point"}
}
