{
  "type": "Feature",
  "properties": {
    "iso:country":"US",
    "sg:address":"650 Beaver Creek Cir",
    "sg:city":"Maumee",
    "sg:classifiers":[
        {
            "category":"Health Services",
            "subcategory":"Doctor",
            "type":"Services"
        }
    ],
    "sg:phone":"+1 419 891 6262",
    "sg:postcode":"43537",
    "sg:province":"OH",
    "sg:tags":[
        "physician",
        "surgeon"
    ],
    "wof:name":"Abaza & Abaza Pediatrics",
    "wof:placetype":"venue"
},
  "geometry": {"coordinates":[-83.688951,41.576207],"type":"Point"}
}