{
  "type": "Feature",
  "properties": {
    "addr:full": "650 Beaver Creek Cir Maumee OH 43537",
    "addr:housenumber": "650",
    "addr:postcode": "43537",
    "addr:street": "Beaver Creek Cir",
    "iso:country": "US",
    "sg:address": "650 Beaver Creek Cir",
    "sg:city": "Maumee",
    "sg:classifiers": [
      {
        "category": "Health Services",
        "subcategory": "Doctor",
        "type": "Services"
      }
    ],
    "sg:phone": "+1 419 891 6262",
    "sg:postcode": "43537",
    "sg:province": "OH",
    "sg:tags": [
      "physician",
      "surgeon"
    ],
    "wof:name": "Abaza \u0026 Abaza Pediatrics",
    "wof:placetype": "venue"
  },
  "geometry": {"coordinates":[-83.688951,41.576207],"type":"Point"}
}
