{
  "type": "Feature",
  "properties": {
    "addr:full": "2146 Ferguson Rd Cincinnati OH 45238",
    "addr:housenumber": "2146",
    "addr:postcode": "45238",
    "addr:street": "Ferguson Rd",
    "iso:country": "US",
    "sg:address": "2146 Ferguson Rd",
    "sg:city": "Cincinnati",
    "sg:classifiers": [
      {
        "category": "Education",
        "subcategory": "School",
        "type": "Public Place"
      }
    ],
    "sg:phone": "+1 513 244 3020",
    "sg:postcode": "45238",
    "sg:province": "OH",
    "wof:name": "Dater Junior High School",
    "wof:placetype": "venue"
  },
  "geometry": {"coordinates":[-84.601419,39.124066],"type":"Point"}
}
