{
  "type": "Feature",
  "properties": {
    "addr:full": "110 W Poe Rd Bowling Green OH 43402",
    "addr:housenumber": "110",
    "addr:postcode": "43402",
    "addr:street": "W Poe Rd",
    "iso:country": "US",
    "sg:address": "110 W Poe Rd",
    "sg:city": "Bowling Green",
    "sg:classifiers": [
      {
        "category": "Home \u0026 Garden",
        "subcategory": "Carpets \u0026 Floor Coverings",
        "type": "Retail Goods"
      }
    ],
    "sg:phone": "+1 419 352 2983",
    "sg:postcode": "43402",
    "sg:province": "OH",
    "sg:tags": [
      "tile",
      "including"
    ],
    "wof:name": "Kirians Home Shop Inc",
    "wof:placetype": "venue"
  },
  "geometry": {"coordinates":[-83.650543,41.385711],"type":"Point"}
}
