{
  "type": "Feature",
  "properties": {
    "iso:country":"US",
    "sg:address":"2645 State Rte 59",
    "sg:city":"Ravenna",
    "sg:classifiers":[
        {
            "category":"Home & Garden",
            "subcategory":"Furniture",
            "type":"Retail Goods"
        }
    ],
    "sg:phone":"+1 330 298 1553",
    "sg:postcode":"44266",
    "sg:province":"OH",
    "wof:name":"O'Neal's Sleep Shoppe",
    "wof:placetype":"venue"
},
  "geometry": {"coordinates":[-81.29715,41.158211],"type":"Point"}
}