{
  "type": "Feature",
  "properties": {
    "iso:country":"US",
    "sg:address":"950 S Sawburg Rd",
    "sg:city":"Alliance",
    "sg:classifiers":[
        {
            "category":"Professional",
            "subcategory":"Lawyer & Legal Services",
            "type":"Services"
        }
    ],
    "sg:phone":"+1 330 823 2226",
    "sg:postcode":"44601",
    "sg:province":"OH",
    "sg:tags":[
        "attorney"
    ],
    "wof:name":"Shetler & Spalding",
    "wof:placetype":"venue"
},
  "geometry": {"coordinates":[-81.134603,40.912182],"type":"Point"}
}