{
  "type": "Feature",
  "properties": {
    "addr:full": "3698 Jessup Rd Cincinnati OH 45247",
    "addr:housenumber": "3698",
    "addr:postcode": "45247",
    "addr:street": "Jessup Rd",
    "iso:country": "US",
    "sg:address": "3698 Jessup Rd",
    "sg:city": "Cincinnati",
    "sg:classifiers": [
      {
        "category": "Building \u0026 Trades",
        "subcategory": "Construction",
        "type": "Services"
      }
    ],
    "sg:phone": "+1 513 385 3698",
    "sg:postcode": "45247",
    "sg:province": "OH",
    "sg:tags": [
      "house",
      "builder",
      "home"
    ],
    "wof:name": "Haubner Homes Inc",
    "wof:placetype": "venue"
  },
  "geometry": {"coordinates":[-84.602857,39.198817],"type":"Point"}
}
