{
  "type": "Feature",
  "properties": {
    "iso:country":"US",
    "sg:address":"3698 Jessup Rd",
    "sg:city":"Cincinnati",
    "sg:classifiers":[
        {
            "category":"Building & Trades",
            "subcategory":"Construction",
            "type":"Services"
        }
    ],
    "sg:phone":"+1 513 385 3698",
    "sg:postcode":"45247",
    "sg:province":"OH",
    "sg:tags":[
        "house",
        "builder",
        "home"
    ],
    "wof:name":"Haubner Homes Inc",
    "wof:placetype":"venue"
},
  "geometry": {"coordinates":[-84.602857,39.198817],"type":"Point"}
}