{
  "type": "Feature",
  "properties": {
    "addr:full": "11200 W 130th St Cleveland OH 44136",
    "addr:housenumber": "11200",
    "addr:postcode": "44136",
    "addr:street": "W 130Th St",
    "iso:country": "US",
    "sg:address": "11200 W 130th St",
    "sg:city": "Cleveland",
    "sg:classifiers": [
      {
        "category": "Arts \u0026 Performance",
        "subcategory": "Theater",
        "type": "Entertainment"
      }
    ],
    "sg:phone": "+1 440 237 8386",
    "sg:postcode": "44136",
    "sg:province": "OH",
    "sg:tags": [
      "bureau"
    ],
    "wof:name": "A Area Artists Assoc",
    "wof:placetype": "venue"
  },
  "geometry": {"coordinates":[-81.785352,41.335632],"type":"Point"}
}
