{
  "type": "Feature",
  "properties": {
    "iso:country":"US",
    "sg:address":"322 Wyoming Ave",
    "sg:city":"Cincinnati",
    "sg:classifiers":[
        {
            "category":"Education",
            "subcategory":"Special Training",
            "type":"Public Place"
        }
    ],
    "sg:phone":"+1 513 948 1900",
    "sg:postcode":"45215",
    "sg:province":"OH",
    "sg:tags":[
        "instruction",
        "music"
    ],
    "sg:website":"www.wyomingfinearts.org",
    "wof:name":"Wyoming Fine Arts Ctr",
    "wof:placetype":"venue"
},
  "geometry": {"coordinates":[-84.46696900000001,39.227292],"type":"Point"}
}