{
  "type": "Feature",
  "properties": {
    "iso:country":"US",
    "sg:address":"250 Debartolo Pl",
    "sg:city":"Youngstown",
    "sg:classifiers":[
        {
            "category":"Health Services",
            "subcategory":"Doctor",
            "type":"Services"
        }
    ],
    "sg:phone":"+1 330 729 0695",
    "sg:postcode":"44512",
    "sg:province":"OH",
    "sg:tags":[
        "physician",
        "surgeon"
    ],
    "wof:name":"Paul W Weiss MD",
    "wof:placetype":"venue"
},
  "geometry": {"coordinates":[-80.655207,41.013419],"type":"Point"}
}