{
  "type": "Feature",
  "properties": {
    "addr:full":"1068 Jackson Pike Gallipolis OH 45631",
    "addr:housenumber":"1068",
    "addr:postcode":"45631",
    "addr:street":"Jackson Pike",
    "iso:country":"US",
    "sg:address":"1068 Jackson Pike",
    "sg:city":"Gallipolis",
    "sg:classifiers":[
        {
            "category":"Shopping",
            "subcategory":"Discount & Variety Stores",
            "type":"Retail Goods"
        }
    ],
    "sg:phone":"+1 740 446 8664",
    "sg:postcode":"45631",
    "sg:province":"OH",
    "wof:name":"Family Dollar Stores",
    "wof:placetype":"venue"
},
  "geometry": {"coordinates":[-82.254456,38.842764],"type":"Point"}
}