{
  "type": "Feature",
  "properties": {
    "addr:full": "3910 E Broad St Columbus OH 43213",
    "addr:housenumber": "3910",
    "addr:postcode": "43213",
    "addr:street": "E Broad St",
    "iso:country": "US",
    "sg:address": "3910 E Broad St",
    "sg:city": "Columbus",
    "sg:classifiers": [
      {
        "category": "Cinema",
        "subcategory": "Movie Rental",
        "type": "Entertainment"
      }
    ],
    "sg:phone": "+1 614 231 1298",
    "sg:postcode": "43213",
    "sg:province": "OH",
    "sg:tags": [
      "leasing",
      "video",
      "disc",
      "tape"
    ],
    "sg:website": "www.hollywoodvideo.com",
    "wof:name": "Hollywood Video",
    "wof:placetype": "venue"
  },
  "geometry": {"coordinates":[-82.900888,39.97321],"type":"Point"}
}
