{
  "type": "Feature",
  "properties": {
    "iso:country":"US",
    "sg:address":"3910 E Broad St",
    "sg:city":"Columbus",
    "sg:classifiers":[
        {
            "category":"Cinema",
            "subcategory":"Movie Rental",
            "type":"Entertainment"
        }
    ],
    "sg:phone":"+1 614 231 1298",
    "sg:postcode":"43213",
    "sg:province":"OH",
    "sg:tags":[
        "leasing",
        "video",
        "disc",
        "tape"
    ],
    "sg:website":"www.hollywoodvideo.com",
    "wof:name":"Hollywood Video",
    "wof:placetype":"venue"
},
  "geometry": {"coordinates":[-82.90088799999999,39.97321],"type":"Point"}
}