{
  "type": "Feature",
  "properties": {
    "addr:full":"50 N Center St Pickerington OH 43147",
    "addr:housenumber":"50",
    "addr:postcode":"43147",
    "addr:street":"N Center St",
    "iso:country":"US",
    "sg:address":"50 N Center St",
    "sg:city":"Pickerington",
    "sg:classifiers":[
        {
            "category":"Insurance",
            "subcategory":"Insurance Agent",
            "type":"Services"
        }
    ],
    "sg:phone":"+1 614 837 6700",
    "sg:postcode":"43147",
    "sg:province":"OH",
    "wof:name":"State Farm Insurance",
    "wof:placetype":"venue"
},
  "geometry": {"coordinates":[-82.753505,39.885264],"type":"Point"}
}