{
  "type": "Feature",
  "properties": {
    "addr:full":"399 E Main St Columbus OH 43215",
    "addr:housenumber":"399",
    "addr:postcode":"43215",
    "addr:street":"E Main St",
    "iso:country":"US",
    "sg:address":"399 E Main St",
    "sg:city":"Columbus",
    "sg:classifiers":[
        {
            "category":"Professional",
            "type":"Services"
        }
    ],
    "sg:phone":"+1 614 224 5214",
    "sg:postcode":"43215",
    "sg:province":"OH",
    "wof:name":"Neighborlinc",
    "wof:placetype":"venue"
},
  "geometry": {"coordinates":[-82.98863,39.957296],"type":"Point"}
}