{
  "type": "Feature",
  "properties": {
    "addr:full":"4721 E Royalton Rd Cleveland OH 44147",
    "addr:housenumber":"4721",
    "addr:postcode":"44147",
    "addr:street":"E Royalton Rd",
    "iso:country":"US",
    "sg:address":"4721 E Royalton Rd",
    "sg:city":"Cleveland",
    "sg:classifiers":[
        {
            "category":"Wholesale",
            "subcategory":"Electrical",
            "type":"Manufacturing & Wholesale Goods"
        }
    ],
    "sg:phone":"+1 440 526 2121",
    "sg:postcode":"44147",
    "sg:province":"OH",
    "sg:tags":[
        "alarm",
        "burglar",
        "system"
    ],
    "wof:name":"Securi-Com",
    "wof:placetype":"venue"
},
  "geometry": {"coordinates":[-81.65155799999999,41.315615],"type":"Point"}
}