{
  "type": "Feature",
  "properties": {
    "addr:full":"1249 Claremont Ave Ashland OH 44805",
    "addr:housenumber":"1249",
    "addr:postcode":"44805",
    "addr:street":"Claremont Ave",
    "iso:country":"US",
    "sg:address":"1249 Claremont Ave",
    "sg:city":"Ashland",
    "sg:classifiers":[
        {
            "category":"Retail",
            "subcategory":"Auto Repair",
            "type":"Services"
        }
    ],
    "sg:phone":"+1 419 289 1604",
    "sg:postcode":"44805",
    "sg:province":"OH",
    "sg:tags":[
        "repairing",
        "automotive",
        "provides",
        "automobile"
    ],
    "wof:name":"Monro Muffler Brake & Svc",
    "wof:placetype":"venue"
},
  "geometry": {"coordinates":[-82.330888,40.857114],"type":"Point"}
}