{
  "type": "Feature",
  "properties": {
    "addr:full":"611 Curtis Dr Miamisburg OH 45342",
    "addr:housenumber":"611",
    "addr:postcode":"45342",
    "addr:street":"Curtis Dr",
    "iso:country":"US",
    "sg:address":"611 Curtis Dr",
    "sg:city":"Miamisburg",
    "sg:classifiers":[
        {
            "category":"Retail",
            "subcategory":"Auto Repair",
            "type":"Services"
        }
    ],
    "sg:phone":"+1 937 866 0735",
    "sg:postcode":"45342",
    "sg:province":"OH",
    "sg:tags":[
        "wrecker"
    ],
    "wof:name":"South Acers Towing",
    "wof:placetype":"venue"
},
  "geometry": {"coordinates":[-84.303258,39.635118],"type":"Point"}
}