{
  "type": "Feature",
  "properties": {
    "iso:country":"US",
    "sg:address":"127 Scioto St",
    "sg:city":"Urbana",
    "sg:classifiers":[
        {
            "category":"Shopping",
            "subcategory":"Catalog Store",
            "type":"Retail Goods"
        }
    ],
    "sg:phone":"+1 937 652 2292",
    "sg:postcode":"43078",
    "sg:province":"OH",
    "sg:tags":[
        "mail",
        "order"
    ],
    "wof:name":"J C Penney Catalog",
    "wof:placetype":"venue"
},
  "geometry": {"coordinates":[-83.751938,40.107986],"type":"Point"}
}