{
  "type": "Feature",
  "properties": {
    "iso:country":"US",
    "sg:address":"241 Paddock Ct",
    "sg:city":"Delaware",
    "sg:classifiers":[
        {
            "category":"Health Services",
            "subcategory":"Health Practitioner",
            "type":"Services"
        }
    ],
    "sg:phone":"+1 740 369 8568",
    "sg:postcode":"43015",
    "sg:province":"OH",
    "wof:name":"Hartland Rehab Services",
    "wof:placetype":"venue"
},
  "geometry": {"coordinates":[-83.110937,40.309572],"type":"Point"}
}