{
  "type": "Feature",
  "properties": {
    "iso:country":"US",
    "sg:address":"7000 Town Centre Dr",
    "sg:city":"Cleveland",
    "sg:classifiers":[
        {
            "category":"Health Services",
            "subcategory":"Health Practitioner",
            "type":"Services"
        }
    ],
    "sg:phone":"+1 216 929 4334",
    "sg:postcode":"44147",
    "sg:province":"OH",
    "sg:tags":[
        "acupuncture"
    ],
    "wof:name":"Summit Acupuncture",
    "wof:placetype":"venue"
},
  "geometry": {"coordinates":[-81.68467699999999,41.311538],"type":"Point"}
}