{
  "type": "Feature",
  "properties": {
    "addr:full": "4309 Silsby Rd Cleveland OH 44118",
    "addr:housenumber": "4309",
    "addr:postcode": "44118",
    "addr:street": "Silsby Rd",
    "iso:country": "US",
    "sg:address": "4309 Silsby Rd",
    "sg:city": "Cleveland",
    "sg:classifiers": [
      {
        "category": "Food \u0026 Beverages",
        "subcategory": "Specialty",
        "type": "Retail Goods"
      }
    ],
    "sg:phone": "+1 216 381 8539",
    "sg:postcode": "44118",
    "sg:province": "OH",
    "sg:tags": [
      "vitamin"
    ],
    "wof:name": "Vivian Herbs Allen",
    "wof:placetype": "venue"
  },
  "geometry": {"coordinates":[-81.525309,41.497695],"type":"Point"}
}
