{
  "type": "Feature",
  "properties": {
    "addr:full": "4040 Medina Rd Akron OH 44333",
    "addr:housenumber": "4040",
    "addr:postcode": "44333",
    "addr:street": "Medina Rd",
    "iso:country": "US",
    "sg:address": "4040 Medina Rd",
    "sg:city": "Akron",
    "sg:classifiers": [
      {
        "category": "Retail",
        "subcategory": "Portrait Studio",
        "type": "Services"
      }
    ],
    "sg:phone": "+1 330 848 0432",
    "sg:postcode": "44333",
    "sg:province": "OH",
    "sg:tags": [
      "photographer"
    ],
    "wof:name": "Olan Mills Portrait Studio",
    "wof:placetype": "venue"
  },
  "geometry": {"coordinates":[-81.644593,41.135841],"type":"Point"}
}
