{
  "type": "Feature",
  "properties": {
    "iso:country":"US",
    "sg:address":"2301 Romig Rd",
    "sg:city":"Akron",
    "sg:classifiers":[
        {
            "category":"Shopping",
            "subcategory":"Gifts & Souvenirs",
            "type":"Retail Goods"
        }
    ],
    "sg:phone":"+1 330 745 5701",
    "sg:postcode":"44320",
    "sg:province":"OH",
    "sg:tags":[
        "shop"
    ],
    "wof:name":"Something Special Gifts",
    "wof:placetype":"venue"
},
  "geometry": {"coordinates":[-81.58105399999999,41.045731],"type":"Point"}
}