{
  "type": "Feature",
  "properties": {
    "addr:full": "2301 Romig Rd Akron OH 44320",
    "addr:housenumber": "2301",
    "addr:postcode": "44320",
    "addr:street": "Romig Rd",
    "iso:country": "US",
    "sg:address": "2301 Romig Rd",
    "sg:city": "Akron",
    "sg:classifiers": [
      {
        "category": "Shopping",
        "subcategory": "Gifts \u0026 Souvenirs",
        "type": "Retail Goods"
      }
    ],
    "sg:phone": "+1 330 745 5701",
    "sg:postcode": "44320",
    "sg:province": "OH",
    "sg:tags": [
      "shop"
    ],
    "wof:name": "Something Special Gifts",
    "wof:placetype": "venue"
  },
  "geometry": {"coordinates":[-81.581054,41.045731],"type":"Point"}
}
