{
  "type": "Feature",
  "properties": {
    "addr:full": "526 Fairwood Dr Tallmadge OH 44278",
    "addr:housenumber": "526",
    "addr:postcode": "44278",
    "addr:street": "Fairwood Dr",
    "iso:country": "US",
    "sg:address": "526 Fairwood Dr",
    "sg:city": "Tallmadge",
    "sg:classifiers": [
      {
        "category": "Real Estate",
        "subcategory": "Real Estate Agent",
        "type": "Services"
      }
    ],
    "sg:phone": "+1 330 630 2606",
    "sg:postcode": "44278",
    "sg:province": "OH",
    "wof:name": "Fortseras LLC",
    "wof:placetype": "venue"
  },
  "geometry": {"coordinates":[-81.424503,41.102951],"type":"Point"}
}
