{
  "type": "Feature",
  "properties": {
    "addr:full": "25101 Chagrin Blvd Cleveland OH 44122",
    "addr:housenumber": "25101",
    "addr:postcode": "44122",
    "addr:street": "Chagrin Blvd",
    "iso:country": "US",
    "sg:address": "25101 Chagrin Blvd",
    "sg:city": "Cleveland",
    "sg:classifiers": [
      {
        "category": "Real Estate",
        "subcategory": "Real Estate Operator",
        "type": "Services"
      }
    ],
    "sg:phone": "+1 440 944 2604",
    "sg:postcode": "44122",
    "sg:province": "OH",
    "sg:tags": [
      "building",
      "apartment"
    ],
    "wof:name": "Pine Ridge Apts",
    "wof:placetype": "venue"
  },
  "geometry": {"coordinates":[-81.502027,41.464541],"type":"Point"}
}
