{
  "type": "Feature",
  "properties": {
    "addr:full": "13206 Co Hwy 53 Upper Sandusky OH 43351",
    "addr:housenumber": "13206",
    "addr:postcode": "43351",
    "addr:street": "Co Hwy 53 Upper",
    "iso:country": "US",
    "sg:address": "13206 Co Hwy 53",
    "sg:city": "Upper Sandusky",
    "sg:classifiers": [
      {
        "category": "Real Estate",
        "subcategory": "Real Estate Operator",
        "type": "Services"
      }
    ],
    "sg:phone": "+1 419 294 3953",
    "sg:postcode": "43351",
    "sg:province": "OH",
    "sg:tags": [
      "property",
      "lessor"
    ],
    "wof:name": "Leroy Gohl",
    "wof:placetype": "venue"
  },
  "geometry": {"coordinates":[-83.365782,40.820068],"type":"Point"}
}
