{
  "type": "Feature",
  "properties": {
    "iso:country":"US",
    "sg:address":"170 N High St",
    "sg:city":"Columbus",
    "sg:classifiers":[
        {
            "category":"Government",
            "subcategory":"Office",
            "type":"Public Place"
        }
    ],
    "sg:phone":"+1 614 469 5705",
    "sg:postcode":"43215",
    "sg:province":"OH",
    "sg:tags":[
        "federal",
        "taxation"
    ],
    "wof:name":"Us Customs Svc",
    "wof:placetype":"venue"
},
  "geometry": {"coordinates":[-83.001321,39.966071],"type":"Point"}
}