{
  "type": "Feature",
  "properties": {
    "addr:full": "507 E Aurora Rd Macedonia OH 44056",
    "addr:housenumber": "507",
    "addr:postcode": "44056",
    "addr:street": "E Aurora Rd",
    "iso:country": "US",
    "sg:address": "507 E Aurora Rd",
    "sg:city": "Macedonia",
    "sg:classifiers": [
      {
        "category": "Health Services",
        "subcategory": "Chiropractor",
        "type": "Services"
      }
    ],
    "sg:phone": "+1 330 468 1199",
    "sg:postcode": "44056",
    "sg:province": "OH",
    "wof:name": "Nordonia Hills Chiropractic",
    "wof:placetype": "venue"
  },
  "geometry": {"coordinates":[-81.520188,41.314038],"type":"Point"}
}
