{
  "type": "Feature",
  "properties": {
    "addr:full":"1017 Helmsdale Rd Cleveland OH 44112",
    "addr:housenumber":"1017",
    "addr:postcode":"44112",
    "addr:street":"Helmsdale Rd",
    "iso:country":"US",
    "sg:address":"1017 Helmsdale Rd",
    "sg:city":"Cleveland",
    "sg:classifiers":[
        {
            "category":"Building & Trades",
            "subcategory":"Construction",
            "type":"Services"
        }
    ],
    "sg:phone":"+1 216 268 3573",
    "sg:postcode":"44112",
    "sg:province":"OH",
    "sg:tags":[
        "contractor"
    ],
    "wof:name":"D and A Seary Contractors",
    "wof:placetype":"venue"
},
  "geometry": {"coordinates":[-81.562173,41.532031],"type":"Point"}
}