{
  "type": "Feature",
  "properties": {
    "addr:full": "14590 Twp Rd 16 Glenmont OH 44628",
    "addr:housenumber": "16",
    "addr:postcode": "14590;44628",
    "addr:street": "Twp Rd",
    "iso:country": "US",
    "sg:address": "14590 Twp Rd 16",
    "sg:city": "Glenmont",
    "sg:phone": "+1 330 377 5683",
    "sg:postcode": "44628",
    "sg:province": "OH",
    "sg:tags": [
      "farm",
      "corn",
      "soybean"
    ],
    "wof:name": "Donald Banbury Farm",
    "wof:placetype": "venue"
  },
  "geometry": {"coordinates":[-82.15354,40.52158],"type":"Point"}
}
