{
  "type": "Feature",
  "properties": {
    "addr:full":"8374 Shadowpoint Ct Cincinnati OH 45242",
    "addr:housenumber":"8374",
    "addr:postcode":"45242",
    "addr:street":"Shadowpoint Ct",
    "iso:country":"US",
    "sg:address":"8374 Shadowpoint Ct",
    "sg:city":"Cincinnati",
    "sg:classifiers":[
        {
            "category":"Professional",
            "subcategory":"Management & Consulting",
            "type":"Services"
        }
    ],
    "sg:phone":"+1 513 489 3311",
    "sg:postcode":"45242",
    "sg:province":"OH",
    "sg:tags":[
        "home",
        "demonstration"
    ],
    "wof:name":"Tupperware",
    "wof:placetype":"venue"
},
  "geometry": {"coordinates":[-84.335773,39.258093],"type":"Point"}
}