{
  "type": "Feature",
  "properties": {
    "addr:full": "5550 Blazer Pkwy Dublin OH 43017",
    "addr:postcode": "5550;43017",
    "addr:street": "Blazer Pkwy",
    "iso:country": "US",
    "sg:address": "5550 Blazer Pkwy",
    "sg:city": "Dublin",
    "sg:classifiers": [
      {
        "category": "Professional",
        "type": "Services"
      }
    ],
    "sg:phone": "+1 614 336 7750",
    "sg:postcode": "43017",
    "sg:province": "OH",
    "wof:name": "Daqvid A Corna",
    "wof:placetype": "venue"
  },
  "geometry": {"coordinates":[-83.13109,40.078853],"type":"Point"}
}
