{
  "type": "Feature",
  "properties": {
    "addr:full": "7340 Cardinal Ln Chagrin Falls OH 44022",
    "addr:housenumber": "7340",
    "addr:postcode": "44022",
    "addr:street": "Cardinal Ln",
    "iso:country": "US",
    "sg:address": "7340 Cardinal Ln",
    "sg:city": "Chagrin Falls",
    "sg:classifiers": [
      {
        "category": "Building \u0026 Trades",
        "subcategory": "Construction",
        "type": "Services"
      }
    ],
    "sg:phone": "+1 440 247 6611",
    "sg:postcode": "44022",
    "sg:province": "OH",
    "sg:tags": [
      "contractor"
    ],
    "wof:name": "Cardinal Building \u0026 Design Co",
    "wof:placetype": "venue"
  },
  "geometry": {"coordinates":[-81.379791,41.45144],"type":"Point"}
}
