{
  "type": "Feature",
  "properties": {
    "addr:full":"3615 Union Ave SE Minerva OH 44657",
    "addr:housenumber":"3615",
    "addr:postcode":"44657",
    "addr:street":"Union Ave Se",
    "iso:country":"US",
    "sg:address":"3615 Union Ave SE",
    "sg:city":"Minerva",
    "sg:classifiers":[
        {
            "category":"Manufacturing",
            "subcategory":"Metals",
            "type":"Manufacturing & Wholesale Goods"
        }
    ],
    "sg:phone":"+1 330 868 6343",
    "sg:postcode":"44657",
    "sg:province":"OH",
    "sg:tags":[
        "stamping"
    ],
    "sg:website":"www.regalmetalproducts.com",
    "wof:name":"Regal Metal Products Co",
    "wof:placetype":"venue"
},
  "geometry": {"coordinates":[-81.09166399999999,40.750066],"type":"Point"}
}