{
  "type": "Feature",
  "properties": {
    "iso:country":"US",
    "sg:address":"7889 State Rte 534",
    "sg:city":"Windsor",
    "sg:classifiers":[
        {
            "category":"Retail",
            "subcategory":"Auto Repair",
            "type":"Services"
        }
    ],
    "sg:phone":"+1 440 272 5364",
    "sg:postcode":"44099",
    "sg:province":"OH",
    "sg:tags":[
        "body",
        "automobile",
        "painting"
    ],
    "wof:name":"Spirit Collision Ctr",
    "wof:placetype":"venue"
},
  "geometry": {"coordinates":[-80.934326,41.532906],"type":"Point"}
}