{
  "type": "Feature",
  "properties": {
    "addr:full": "12288 Mahoning Ave North Jackson OH 44451",
    "addr:housenumber": "12288",
    "addr:postcode": "44451",
    "addr:street": "Mahoning Ave North",
    "iso:country": "US",
    "sg:address": "12288 Mahoning Ave",
    "sg:city": "North Jackson",
    "sg:classifiers": [
      {
        "category": "Recreation",
        "type": "Entertainment"
      }
    ],
    "sg:phone": "+1 330 538 2737",
    "sg:postcode": "44451",
    "sg:province": "OH",
    "sg:tags": [
      "range",
      "pistol",
      "rifle"
    ],
    "wof:name": "American Indoor Shooting Range",
    "wof:placetype": "venue"
  },
  "geometry": {"coordinates":[-80.878386,41.099646],"type":"Point"}
}
