{
  "type": "Feature",
  "properties": {
    "addr:full": "500 Som Center Rd Cleveland OH 44143",
    "addr:housenumber": "500",
    "addr:postcode": "44143",
    "addr:street": "Som Center Rd",
    "iso:country": "US",
    "sg:address": "500 Som Center Rd",
    "sg:city": "Cleveland",
    "sg:classifiers": [
      {
        "category": "Real Estate",
        "subcategory": "Real Estate Operator",
        "type": "Services"
      }
    ],
    "sg:phone": "+1 440 442 1119",
    "sg:postcode": "44143",
    "sg:province": "OH",
    "sg:tags": [
      "mall",
      "shopping",
      "center"
    ],
    "wof:name": "Costanzo \u0026 Son",
    "wof:placetype": "venue"
  },
  "geometry": {"coordinates":[-81.439356,41.55578],"type":"Point"}
}
