{
  "type": "Feature",
  "properties": {
    "iso:country":"US",
    "sg:address":"1999 Westbelt Dr",
    "sg:city":"Columbus",
    "sg:classifiers":[
        {
            "category":"Wholesale",
            "subcategory":"Electrical",
            "type":"Manufacturing & Wholesale Goods"
        }
    ],
    "sg:phone":"+1 614 876 6799",
    "sg:postcode":"43228",
    "sg:province":"OH",
    "sg:tags":[
        "decoration",
        "light",
        "christmas"
    ],
    "wof:name":"Kurt S Adler Inc",
    "wof:placetype":"venue"
},
  "geometry": {"coordinates":[-83.12348,39.995612],"type":"Point"}
}