{
  "type": "Feature",
  "properties": {
    "addr:full": "13300 Van Camp Rd Bowling Green OH 43402",
    "addr:housenumber": "13300",
    "addr:postcode": "43402",
    "addr:street": "Van Camp Rd",
    "iso:country": "US",
    "sg:address": "13300 Van Camp Rd",
    "sg:city": "Bowling Green",
    "sg:classifiers": [
      {
        "category": "Professional",
        "type": "Services"
      }
    ],
    "sg:phone": "+1 419 354 2345",
    "sg:postcode": "43402",
    "sg:province": "OH",
    "sg:tags": [
      "establishment"
    ],
    "wof:name": "Kulka Terminal Blocks Marathon",
    "wof:placetype": "venue"
  },
  "geometry": {"coordinates":[-83.659827,41.397017],"type":"Point"}
}
