{
  "type": "Feature",
  "properties": {
    "addr:full": "555 Roslyn Ave Akron OH 44320",
    "addr:housenumber": "555",
    "addr:postcode": "44320",
    "addr:street": "Roslyn Ave",
    "iso:country": "US",
    "sg:address": "555 Roslyn Ave",
    "sg:city": "Akron",
    "sg:classifiers": [
      {
        "category": "Professional",
        "subcategory": "Art Services",
        "type": "Services"
      }
    ],
    "sg:phone": "+1 330 867 0997",
    "sg:postcode": "44320",
    "sg:province": "OH",
    "sg:tags": [
      "commercial",
      "design"
    ],
    "wof:name": "Wilson Graphics",
    "wof:placetype": "venue"
  },
  "geometry": {"coordinates":[-81.566974,41.09367],"type":"Point"}
}
