{
  "type": "Feature",
  "properties": {
    "addr:full": "5233 W 137th St Cleveland OH 44142",
    "addr:housenumber": "5233",
    "addr:postcode": "44142",
    "addr:street": "W 137Th St",
    "iso:country": "US",
    "sg:address": "5233 W 137th St",
    "sg:city": "Cleveland",
    "sg:classifiers": [
      {
        "category": "Wholesale",
        "subcategory": "Electrical",
        "type": "Manufacturing \u0026 Wholesale Goods"
      }
    ],
    "sg:phone": "+1 216 676 5211",
    "sg:postcode": "44142",
    "sg:province": "OH",
    "sg:tags": [
      "electric",
      "motor"
    ],
    "sg:website": "www.bdi-usa.com",
    "wof:name": "Bearing Distributors Inc",
    "wof:placetype": "venue"
  },
  "geometry": {"coordinates":[-81.786665,41.416124],"type":"Point"}
}
