{
  "type": "Feature",
  "properties": {
    "iso:country":"US",
    "sg:address":"2020 Tiffin Ave",
    "sg:city":"Findlay",
    "sg:classifiers":[
        {
            "category":"Autos & Motor Vehicles",
            "subcategory":"Automobile Sales",
            "type":"Retail Goods"
        }
    ],
    "sg:phone":"+1 419 423 7400",
    "sg:postcode":"45840",
    "sg:province":"OH",
    "sg:tags":[
        "car",
        "dealer"
    ],
    "wof:name":"Auto World",
    "wof:placetype":"venue"
},
  "geometry": {"coordinates":[-83.605618,41.054199],"type":"Point"}
}