{
  "type": "Feature",
  "properties": {
    "addr:full":"2535 Co Rd 90 Alger OH 45812",
    "addr:postcode":"2535;45812",
    "addr:street":"Co Rd 90",
    "iso:country":"US",
    "sg:address":"2535 Co Rd 90",
    "sg:city":"Alger",
    "sg:classifiers":[
        {
            "category":"Organizations",
            "subcategory":"Religious Organization",
            "type":"Services"
        }
    ],
    "sg:phone":"+1 419 757 5575",
    "sg:postcode":"45812",
    "sg:province":"OH",
    "sg:tags":[
        "clergy"
    ],
    "wof:name":"James Holbrook",
    "wof:placetype":"venue"
},
  "geometry": {"coordinates":[-83.832223,40.711415],"type":"Point"}
}