{
  "type": "Feature",
  "properties": {
    "iso:country":"US",
    "sg:address":"395 E High St",
    "sg:city":"Mc Arthur",
    "sg:classifiers":[
        {
            "category":"Organizations",
            "subcategory":"Religious Organization",
            "type":"Services"
        }
    ],
    "sg:phone":"+1 740 596 2394",
    "sg:postcode":"45651",
    "sg:province":"OH",
    "sg:tags":[
        "church"
    ],
    "wof:name":"CARE United Methodist Otrch",
    "wof:placetype":"venue"
},
  "geometry": {"coordinates":[-82.47526499999999,39.247689],"type":"Point"}
}