{
  "type": "Feature",
  "properties": {
    "addr:full":"4701 Walford Rd Cleveland OH 44128",
    "addr:housenumber":"4701",
    "addr:postcode":"44128",
    "addr:street":"Walford Rd",
    "iso:country":"US",
    "sg:address":"4701 Walford Rd",
    "sg:city":"Cleveland",
    "sg:classifiers":[
        {
            "category":"Professional",
            "type":"Services"
        }
    ],
    "sg:phone":"+1 216 593 0177",
    "sg:postcode":"44128",
    "sg:province":"OH",
    "sg:tags":[
        "establishment"
    ],
    "wof:name":"Taliup Record Inc",
    "wof:placetype":"venue"
},
  "geometry": {"coordinates":[-81.50954400000001,41.435018],"type":"Point"}
}