{
  "type": "Feature",
  "properties": {
    "addr:full": "36335 Reading Ave Willoughby OH 44094",
    "addr:housenumber": "36335",
    "addr:postcode": "44094",
    "addr:street": "Reading Ave",
    "iso:country": "US",
    "sg:address": "36335 Reading Ave",
    "sg:city": "Willoughby",
    "sg:classifiers": [
      {
        "category": "Professional",
        "type": "Services"
      }
    ],
    "sg:phone": "+1 440 942 7342",
    "sg:postcode": "44094",
    "sg:province": "OH",
    "wof:name": "Top Form",
    "wof:placetype": "venue"
  },
  "geometry": {"coordinates":[-81.426958,41.634769],"type":"Point"}
}
