{
  "type": "Feature",
  "properties": {
    "iso:country":"US",
    "sg:address":"25514 Royalton Rd",
    "sg:city":"Columbia Station",
    "sg:classifiers":[
        {
            "category":"Organizations",
            "subcategory":"Religious Organization",
            "type":"Services"
        }
    ],
    "sg:phone":"+1 440 236 8206",
    "sg:postcode":"44028",
    "sg:province":"OH",
    "sg:tags":[
        "church"
    ],
    "sg:website":"www.columbiabaptist.net",
    "wof:name":"Columbia Baptist Church",
    "wof:placetype":"venue"
},
  "geometry": {"coordinates":[-81.920646,41.312565],"type":"Point"}
}