{
  "type": "Feature",
  "properties": {
    "addr:full":"4697 W 130th St Cleveland OH 44135",
    "addr:housenumber":"4697",
    "addr:postcode":"44135",
    "addr:street":"W 130Th St",
    "iso:country":"US",
    "sg:address":"4697 W 130th St",
    "sg:city":"Cleveland",
    "sg:classifiers":[
        {
            "category":"Organizations",
            "subcategory":"Religious Organization",
            "type":"Services"
        }
    ],
    "sg:phone":"+1 216 671 2015",
    "sg:postcode":"44135",
    "sg:province":"OH",
    "sg:website":"www.annunciationparish.net",
    "wof:name":"Annunciation Church",
    "wof:placetype":"venue"
},
  "geometry": {"coordinates":[-81.780079,41.426671],"type":"Point"}
}