{
  "type": "Feature",
  "properties": {
    "iso:country":"US",
    "sg:address":"7453 Knauss Rd",
    "sg:city":"Bloomville",
    "sg:classifiers":[
        {
            "category":"Real Estate",
            "subcategory":"Real Estate Operator",
            "type":"Services"
        }
    ],
    "sg:phone":"+1 419 397 2283",
    "sg:postcode":"44818",
    "sg:province":"OH",
    "sg:tags":[
        "property",
        "lessor"
    ],
    "wof:name":"Fadley Therman",
    "wof:placetype":"venue"
},
  "geometry": {"coordinates":[-83.074198,40.976529],"type":"Point"}
}