{
  "type": "Feature",
  "properties": {
    "addr:full":"3987 Hamilton Middletown Rd Hamilton OH 45011",
    "addr:housenumber":"3987",
    "addr:postcode":"45011",
    "addr:street":"Hamilton Middletown Rd",
    "iso:country":"US",
    "sg:address":"3987 Hamilton Middletown Rd",
    "sg:city":"Hamilton",
    "sg:classifiers":[
        {
            "category":"Professional",
            "subcategory":"Accounting & Tax Preparation",
            "type":"Services"
        },
        {
            "category":"Manufacturing",
            "subcategory":"Tools & Machinery",
            "type":"Manufacturing & Wholesale Goods"
        }
    ],
    "sg:phone":"+1 513 737 2268",
    "sg:postcode":"45011",
    "sg:province":"OH",
    "sg:tags":[
        "battery",
        "bookkeeping",
        "general",
        "storage",
        "mfg"
    ],
    "wof:name":"Enersys Inc",
    "wof:placetype":"venue"
},
  "geometry": {"coordinates":[-84.483847,39.413355],"type":"Point"}
}