{
  "type": "Feature",
  "properties": {
    "addr:full":"9650 Monroe Rd Wapakoneta OH 45895",
    "addr:housenumber":"9650",
    "addr:postcode":"45895",
    "addr:street":"Monroe Rd",
    "iso:country":"US",
    "sg:address":"9650 Monroe Rd",
    "sg:city":"Wapakoneta",
    "sg:classifiers":[
        {
            "category":"Personal",
            "subcategory":"Beauty Salon",
            "type":"Services"
        }
    ],
    "sg:phone":"+1 419 657 2375",
    "sg:postcode":"45895",
    "sg:province":"OH",
    "wof:name":"Jeanne's Hair Style",
    "wof:placetype":"venue"
},
  "geometry": {"coordinates":[-84.26680399999999,40.641982],"type":"Point"}
}