{
  "type": "Feature",
  "properties": {
    "addr:full":"7 W Stimson Ave Athens OH 45701",
    "addr:housenumber":"7",
    "addr:postcode":"45701",
    "addr:street":"W Stimson Ave",
    "iso:country":"US",
    "sg:address":"7 W Stimson Ave",
    "sg:city":"Athens",
    "sg:classifiers":[
        {
            "category":"Banks & Credit Unions",
            "subcategory":"Financial Services",
            "type":"Services"
        }
    ],
    "sg:phone":"+1 740 592 4441",
    "sg:postcode":"45701",
    "sg:province":"OH",
    "sg:tags":[
        "company",
        "holding"
    ],
    "sg:website":"www.hvbonline.com",
    "wof:name":"Hocking Valley Bancshares Inc",
    "wof:placetype":"venue"
},
  "geometry": {"coordinates":[-82.09367399999999,39.332337],"type":"Point"}
}