{
  "type": "Feature",
  "properties": {
    "addr:full": "7967 Salem Rd Athens OH 45701",
    "addr:housenumber": "7967",
    "addr:postcode": "45701",
    "addr:street": "Salem Rd",
    "iso:country": "US",
    "sg:address": "7967 Salem Rd",
    "sg:city": "Athens",
    "sg:classifiers": [
      {
        "category": "Communications",
        "subcategory": "Radio Station",
        "type": "Services"
      }
    ],
    "sg:phone": "+1 740 594 6275",
    "sg:postcode": "45701",
    "sg:province": "OH",
    "sg:tags": [
      "broadcast"
    ],
    "wof:name": "Mark Dupler Rev",
    "wof:placetype": "venue"
  },
  "geometry": {"coordinates":[-82.167687,39.316704],"type":"Point"}
}
