{
  "type": "Feature",
  "properties": {
    "iso:country":"US",
    "sg:address":"6500 E Schaaf Rd",
    "sg:city":"Cleveland",
    "sg:classifiers":[
        {
            "category":"Building & Trades",
            "subcategory":"Equipment Rental",
            "type":"Services"
        }
    ],
    "sg:phone":"+1 216 573 7198",
    "sg:postcode":"44131",
    "sg:province":"OH",
    "sg:tags":[
        "contractor"
    ],
    "wof:name":"Indy Equipment/Independence",
    "wof:placetype":"venue"
},
  "geometry": {"coordinates":[-81.647519,41.413581],"type":"Point"}
}