{
  "type": "Feature",
  "properties": {
    "addr:full":"6171 Interstate Cir Cincinnati OH 45242",
    "addr:housenumber":"6171",
    "addr:postcode":"45242",
    "addr:street":"Interstate Cir",
    "iso:country":"US",
    "sg:address":"6171 Interstate Cir",
    "sg:city":"Cincinnati",
    "sg:classifiers":[
        {
            "category":"Wholesale",
            "subcategory":"Auto Parts",
            "type":"Manufacturing & Wholesale Goods"
        }
    ],
    "sg:phone":"+1 513 489 0500",
    "sg:postcode":"45242",
    "sg:province":"OH",
    "wof:name":"Baf Industries",
    "wof:placetype":"venue"
},
  "geometry": {"coordinates":[-84.365002,39.271882],"type":"Point"}
}