{
  "type": "Feature",
  "properties": {
    "addr:full": "4384 Green Cook Rd Westerville OH 43082",
    "addr:housenumber": "4384",
    "addr:postcode": "43082",
    "addr:street": "Green Cook Rd",
    "iso:country": "US",
    "sg:address": "4384 Green Cook Rd",
    "sg:city": "Westerville",
    "sg:classifiers": [
      {
        "category": "Building \u0026 Trades",
        "subcategory": "Construction",
        "type": "Services"
      }
    ],
    "sg:phone": "+1 740 965 9651",
    "sg:postcode": "43082",
    "sg:province": "OH",
    "sg:tags": [
      "floor",
      "covering"
    ],
    "wof:name": "Rice Jerry Floor Covering",
    "wof:placetype": "venue"
  },
  "geometry": {"coordinates":[-82.780158,40.141593],"type":"Point"}
}
