{
  "type": "Feature",
  "properties": {
    "iso:country":"US",
    "sg:address":"842 Center St",
    "sg:city":"Ashtabula",
    "sg:classifiers":[
        {
            "category":"Social Services",
            "subcategory":"Child Care",
            "type":"Services"
        }
    ],
    "sg:phone":"+1 440 997 5777",
    "sg:postcode":"44004",
    "sg:province":"OH",
    "sg:tags":[
        "day"
    ],
    "wof:name":"B & B Knowlson Inc",
    "wof:placetype":"venue"
},
  "geometry": {"coordinates":[-80.793316,41.864966],"type":"Point"}
}