{
  "type": "Feature",
  "properties": {
    "addr:full": "2076 S US Hwy 68 Wilmington OH 45177",
    "addr:housenumber": "2076",
    "addr:postcode": "45177",
    "addr:street": "S Us Hwy 68",
    "iso:country": "US",
    "sg:address": "2076 S US Hwy 68",
    "sg:city": "Wilmington",
    "sg:classifiers": [
      {
        "category": "Real Estate",
        "subcategory": "Real Estate Operator",
        "type": "Services"
      }
    ],
    "sg:phone": "+1 937 382 0765",
    "sg:postcode": "45177",
    "sg:province": "OH",
    "sg:tags": [
      "mobile",
      "home",
      "site"
    ],
    "wof:name": "Whites Mobile Home Park \u0026 Sls",
    "wof:placetype": "venue"
  },
  "geometry": {"coordinates":[-83.84068,39.418791],"type":"Point"}
}
