{
  "type": "Feature",
  "properties": {
    "iso:country":"US",
    "sg:address":"507 Adrian St",
    "sg:city":"Delta",
    "sg:classifiers":[
        {
            "category":"Building & Trades",
            "subcategory":"Construction",
            "type":"Services"
        }
    ],
    "sg:phone":"+1 419 246 0869",
    "sg:postcode":"43515",
    "sg:province":"OH",
    "sg:tags":[
        "house"
    ],
    "wof:name":"Sacred Spaces",
    "wof:placetype":"venue"
},
  "geometry": {"coordinates":[-84.012095,41.5789],"type":"Point"}
}