{
  "type": "Feature",
  "properties": {
    "addr:full": "1921 E 5th St Dayton OH 45403",
    "addr:housenumber": "1921",
    "addr:postcode": "45403",
    "addr:street": "E 5Th St",
    "iso:country": "US",
    "sg:address": "1921 E 5th St",
    "sg:city": "Dayton",
    "sg:classifiers": [
      {
        "category": "Building \u0026 Trades",
        "subcategory": "Construction",
        "type": "Services"
      }
    ],
    "sg:phone": "+1 937 236 5708",
    "sg:postcode": "45403",
    "sg:province": "OH",
    "sg:tags": [
      "auto",
      "contractor",
      "door",
      "glass",
      "replacement"
    ],
    "wof:name": "Miami Valley Door and Lock",
    "wof:placetype": "venue"
  },
  "geometry": {"coordinates":[-84.168485,39.759429],"type":"Point"}
}
