{
  "type": "Feature",
  "properties": {
    "addr:full":"5915 Landerbrook Dr Cleveland OH 44124",
    "addr:housenumber":"5915",
    "addr:postcode":"44124",
    "addr:street":"Landerbrook Dr",
    "iso:country":"US",
    "sg:address":"5915 Landerbrook Dr",
    "sg:city":"Cleveland",
    "sg:classifiers":[
        {
            "category":"Banks & Credit Unions",
            "subcategory":"Investment Brokerage",
            "type":"Services"
        }
    ],
    "sg:phone":"+1 440 684 4400",
    "sg:postcode":"44124",
    "sg:province":"OH",
    "sg:tags":[
        "brokerage",
        "security"
    ],
    "wof:name":"Prudential",
    "wof:placetype":"venue"
},
  "geometry": {"coordinates":[-81.464383,41.50522],"type":"Point"}
}