{
  "type": "Feature",
  "properties": {
    "addr:full": "225 Cackler Rd Streetsboro OH 44241",
    "addr:housenumber": "225",
    "addr:postcode": "44241",
    "addr:street": "Cackler Rd",
    "iso:country": "US",
    "sg:address": "225 Cackler Rd",
    "sg:city": "Streetsboro",
    "sg:classifiers": [
      {
        "category": "Building \u0026 Trades",
        "subcategory": "Landscaping Services",
        "type": "Services"
      }
    ],
    "sg:phone": "+1 330 677 4990",
    "sg:postcode": "44241",
    "sg:province": "OH",
    "wof:name": "D \u0026 S Landscaping",
    "wof:placetype": "venue"
  },
  "geometry": {"coordinates":[-81.384187,41.202903],"type":"Point"}
}
