{
  "type": "Feature",
  "properties": {
    "iso:country":"US",
    "sg:address":"225 Cackler Rd",
    "sg:city":"Streetsboro",
    "sg:classifiers":[
        {
            "category":"Building & Trades",
            "subcategory":"Landscaping Services",
            "type":"Services"
        }
    ],
    "sg:phone":"+1 330 677 4990",
    "sg:postcode":"44241",
    "sg:province":"OH",
    "wof:name":"D & S Landscaping",
    "wof:placetype":"venue"
},
  "geometry": {"coordinates":[-81.384187,41.202903],"type":"Point"}
}