{
  "type": "Feature",
  "properties": {
    "iso:country":"US",
    "sg:address":"8900 E Main St",
    "sg:city":"Reynoldsburg",
    "sg:classifiers":[
        {
            "category":"Building & Trades",
            "subcategory":"Landscaping Services",
            "type":"Services"
        }
    ],
    "sg:phone":"+1 614 864 5740",
    "sg:postcode":"43068",
    "sg:province":"OH",
    "sg:tags":[
        "contractor"
    ],
    "wof:name":"Yard Solutions",
    "wof:placetype":"venue"
},
  "geometry": {"coordinates":[-82.775807,39.956042],"type":"Point"}
}