{
  "type": "Feature",
  "properties": {
    "addr:full": "1076 Easton Dr Akron OH 44310",
    "addr:housenumber": "1076",
    "addr:postcode": "44310",
    "addr:street": "Easton Dr",
    "iso:country": "US",
    "sg:address": "1076 Easton Dr",
    "sg:city": "Akron",
    "sg:classifiers": [
      {
        "category": "Real Estate",
        "subcategory": "Surveying",
        "type": "Services"
      }
    ],
    "sg:phone": "+1 330 923 0861",
    "sg:postcode": "44310",
    "sg:province": "OH",
    "sg:tags": [
      "surveyor"
    ],
    "wof:name": "Edward F Lambacher",
    "wof:placetype": "venue"
  },
  "geometry": {"coordinates":[-81.496968,41.107922],"type":"Point"}
}
