{
  "type": "Feature",
  "properties": {
    "iso:country":"US",
    "sg:address":"5606 E Galbraith Rd",
    "sg:city":"Cincinnati",
    "sg:classifiers":[
        {
            "category":"Banks & Credit Unions",
            "subcategory":"Investment Brokerage",
            "type":"Services"
        }
    ],
    "sg:phone":"+1 513 791 4819",
    "sg:postcode":"45236",
    "sg:province":"OH",
    "sg:tags":[
        "security"
    ],
    "wof:name":"Beardancenet LLC",
    "wof:placetype":"venue"
},
  "geometry": {"coordinates":[-84.372056,39.205867],"type":"Point"}
}