{
  "type": "Feature",
  "properties": {
    "iso:country":"US",
    "sg:address":"617 S Main St",
    "sg:city":"Fostoria",
    "sg:classifiers":[
        {
            "category":"Building & Trades",
            "subcategory":"Construction",
            "type":"Services"
        }
    ],
    "sg:phone":"+1 419 436 0771",
    "sg:postcode":"44830",
    "sg:province":"OH",
    "sg:tags":[
        "residential"
    ],
    "wof:name":"Robert Essex",
    "wof:placetype":"venue"
},
  "geometry": {"coordinates":[-83.41416700000001,41.151404],"type":"Point"}
}