{
  "type": "Feature",
  "properties": {
    "addr:full": "617 S Main St Fostoria OH 44830",
    "addr:housenumber": "617",
    "addr:postcode": "44830",
    "addr:street": "S Main St",
    "iso:country": "US",
    "sg:address": "617 S Main St",
    "sg:city": "Fostoria",
    "sg:classifiers": [
      {
        "category": "Building \u0026 Trades",
        "subcategory": "Construction",
        "type": "Services"
      }
    ],
    "sg:phone": "+1 419 436 0771",
    "sg:postcode": "44830",
    "sg:province": "OH",
    "sg:tags": [
      "residential"
    ],
    "wof:name": "Robert Essex",
    "wof:placetype": "venue"
  },
  "geometry": {"coordinates":[-83.414167,41.151404],"type":"Point"}
}
