{
  "type": "Feature",
  "properties": {
    "addr:full":"7336 Kyles Station Rd Middletown OH 45044",
    "addr:postcode":"7336;45044",
    "addr:street":"Kyles Station Rd",
    "iso:country":"US",
    "sg:address":"7336 Kyles Station Rd",
    "sg:city":"Middletown",
    "sg:phone":"+1 513 779 2482",
    "sg:postcode":"45044",
    "sg:province":"OH",
    "sg:tags":[
        "farm",
        "corn",
        "soybean"
    ],
    "wof:name":"Price Farms Inc",
    "wof:placetype":"venue"
},
  "geometry": {"coordinates":[-84.379347,39.414599],"type":"Point"}
}