{
  "type": "Feature",
  "properties": {
    "iso:country":"US",
    "sg:address":"24112 Lime City Rd",
    "sg:city":"Perrysburg",
    "sg:classifiers":[
        {
            "category":"Building & Trades",
            "subcategory":"Landscaping Services",
            "type":"Services"
        }
    ],
    "sg:phone":"+1 419 874 6779",
    "sg:postcode":"43551",
    "sg:province":"OH",
    "wof:name":"Envirocare Lawn & Landscape",
    "wof:placetype":"venue"
},
  "geometry": {"coordinates":[-83.567853,41.50324],"type":"Point"}
}