{
  "type": "Feature",
  "properties": {
    "addr:full": "24112 Lime City Rd Perrysburg OH 43551",
    "addr:housenumber": "24112",
    "addr:postcode": "43551",
    "addr:street": "Lime City Rd",
    "iso:country": "US",
    "sg:address": "24112 Lime City Rd",
    "sg:city": "Perrysburg",
    "sg:classifiers": [
      {
        "category": "Building \u0026 Trades",
        "subcategory": "Landscaping Services",
        "type": "Services"
      }
    ],
    "sg:phone": "+1 419 874 6779",
    "sg:postcode": "43551",
    "sg:province": "OH",
    "wof:name": "Envirocare Lawn \u0026 Landscape",
    "wof:placetype": "venue"
  },
  "geometry": {"coordinates":[-83.567853,41.50324],"type":"Point"}
}
