{
  "type": "Feature",
  "properties": {
    "addr:full": "16501 Square Dr Marysville OH 43040",
    "addr:housenumber": "16501",
    "addr:postcode": "43040",
    "addr:street": "Square Dr",
    "iso:country": "US",
    "sg:address": "16501 Square Dr",
    "sg:city": "Marysville",
    "sg:classifiers": [
      {
        "category": "Health Services",
        "subcategory": "Chiropractor",
        "type": "Services"
      }
    ],
    "sg:phone": "+1 937 642 2333",
    "sg:postcode": "43040",
    "sg:province": "OH",
    "wof:name": "Cowgill Chiropractic Office",
    "wof:placetype": "venue"
  },
  "geometry": {"coordinates":[-83.347401,40.242548],"type":"Point"}
}
