{
  "type": "Feature",
  "properties": {
    "addr:full": "2601 Hill Ave Toledo OH 43607",
    "addr:housenumber": "2601",
    "addr:postcode": "43607",
    "addr:street": "Hill Ave",
    "iso:country": "US",
    "sg:address": "2601 Hill Ave",
    "sg:city": "Toledo",
    "sg:classifiers": [
      {
        "category": "Wholesale",
        "subcategory": "Machinery \u0026 Supplies",
        "type": "Manufacturing \u0026 Wholesale Goods"
      }
    ],
    "sg:phone": "+1 419 537 9333",
    "sg:postcode": "43607",
    "sg:province": "OH",
    "sg:tags": [
      "transmission",
      "bearing",
      "hose",
      "power"
    ],
    "wof:name": "Binkelman Corporation",
    "wof:placetype": "venue"
  },
  "geometry": {"coordinates":[-83.607812,41.638075],"type":"Point"}
}
