{
  "type": "Feature",
  "properties": {
    "addr:full": "3120 Columbus Ave Springfield OH 45503",
    "addr:housenumber": "3120",
    "addr:postcode": "45503",
    "addr:street": "Columbus Ave",
    "iso:country": "US",
    "sg:address": "3120 Columbus Ave",
    "sg:city": "Springfield",
    "sg:classifiers": [
      {
        "category": "Shopping",
        "subcategory": "Gifts \u0026 Souvenirs",
        "type": "Retail Goods"
      }
    ],
    "sg:phone": "+1 937 525 9454",
    "sg:postcode": "45503",
    "sg:province": "OH",
    "wof:name": "Coming Attrctns By Stacy",
    "wof:placetype": "venue"
  },
  "geometry": {"coordinates":[-83.752917,39.93897],"type":"Point"}
}
