{
  "type": "Feature",
  "properties": {
    "iso:country":"US",
    "sg:address":"548 Carmalt St",
    "sg:city":"Cincinnati",
    "sg:classifiers":[
        {
            "category":"Manufacturing",
            "subcategory":"Printing",
            "type":"Manufacturing & Wholesale Goods"
        }
    ],
    "sg:phone":"+1 513 281 1000",
    "sg:postcode":"45219",
    "sg:province":"OH",
    "sg:tags":[
        "printer"
    ],
    "wof:name":"Graphic Wire Inc",
    "wof:placetype":"venue"
},
  "geometry": {"coordinates":[-84.50469200000001,39.117036],"type":"Point"}
}