{
  "type": "Feature",
  "properties": {
    "addr:full":"1603 Amherst Rd NE Massillon OH 44646",
    "addr:housenumber":"1603",
    "addr:postcode":"44646",
    "addr:street":"Amherst Rd Ne",
    "iso:country":"US",
    "sg:address":"1603 Amherst Rd NE",
    "sg:city":"Massillon",
    "sg:classifiers":[
        {
            "category":"Personal",
            "subcategory":"Beauty Salon",
            "type":"Services"
        }
    ],
    "sg:phone":"+1 330 832 0710",
    "sg:postcode":"44646",
    "sg:province":"OH",
    "wof:name":"Amvale Beauty Salon",
    "wof:placetype":"venue"
},
  "geometry": {"coordinates":[-81.516003,40.816551],"type":"Point"}
}