{
  "type": "Feature",
  "properties": {
    "addr:full":"5871 Stearns Rd Bloomdale OH 44817",
    "addr:housenumber":"5871",
    "addr:postcode":"44817",
    "addr:street":"Stearns Rd",
    "iso:country":"US",
    "sg:address":"5871 Stearns Rd",
    "sg:city":"Bloomdale",
    "sg:phone":"+1 419 454 4935",
    "sg:postcode":"44817",
    "sg:province":"OH",
    "sg:tags":[
        "farm",
        "corn",
        "wheat",
        "soybean"
    ],
    "wof:name":"Herbert Hathaway",
    "wof:placetype":"venue"
},
  "geometry": {"coordinates":[-83.513851,41.180434],"type":"Point"}
}