{
  "type": "Feature",
  "properties": {
    "addr:full": "3009 Clifton Ave Cincinnati OH 45220",
    "addr:housenumber": "3009",
    "addr:postcode": "45220",
    "addr:street": "Clifton Ave",
    "iso:country": "US",
    "sg:address": "3009 Clifton Ave",
    "sg:city": "Cincinnati",
    "sg:classifiers": [
      {
        "category": "Health Services",
        "subcategory": "Doctor",
        "type": "Services"
      }
    ],
    "sg:phone": "+1 513 281 5070",
    "sg:postcode": "45220",
    "sg:province": "OH",
    "sg:tags": [
      "physician",
      "surgeon"
    ],
    "wof:name": "Midwest Urology",
    "wof:placetype": "venue"
  },
  "geometry": {"coordinates":[-84.51957,39.140429],"type":"Point"}
}
