{
  "type": "Feature",
  "properties": {
    "addr:full": "37496 Leading Creek Rd Middleport OH 45760",
    "addr:postcode": "37496;45760",
    "addr:street": "Leading Creek Rd",
    "iso:country": "US",
    "sg:address": "37496 Leading Creek Rd",
    "sg:city": "Middleport",
    "sg:classifiers": [
      {
        "category": "Retail",
        "subcategory": "Repair Shop",
        "type": "Services"
      }
    ],
    "sg:phone": "+1 740 742 2925",
    "sg:postcode": "45760",
    "sg:province": "OH",
    "sg:tags": [
      "engine"
    ],
    "wof:name": "Drehel's Small Engines",
    "wof:placetype": "venue"
  },
  "geometry": {"coordinates":[-82.110357,39.010954],"type":"Point"}
}
