{
  "type": "Feature",
  "properties": {
    "addr:full": "12 E Exchange St Akron OH 44308",
    "addr:housenumber": "12",
    "addr:postcode": "44308",
    "addr:street": "E Exchange St",
    "iso:country": "US",
    "sg:address": "12 E Exchange St",
    "sg:city": "Akron",
    "sg:classifiers": [
      {
        "category": "Professional",
        "subcategory": "Lawyer \u0026 Legal Services",
        "type": "Services"
      }
    ],
    "sg:phone": "+1 330 434 7733",
    "sg:postcode": "44308",
    "sg:province": "OH",
    "sg:tags": [
      "attorney"
    ],
    "wof:name": "Eoff \u0026 Elliott",
    "wof:placetype": "venue"
  },
  "geometry": {"coordinates":[-81.521855,41.076399],"type":"Point"}
}
