{
  "type": "Feature",
  "properties": {
    "addr:full": "25487 Detroit Rd Cleveland OH 44145",
    "addr:housenumber": "25487",
    "addr:postcode": "44145",
    "addr:street": "Detroit Rd",
    "iso:country": "US",
    "sg:address": "25487 Detroit Rd",
    "sg:city": "Cleveland",
    "sg:classifiers": [
      {
        "category": "Autos \u0026 Motor Vehicles",
        "subcategory": "Fuel \u0026 Gas Station",
        "type": "Retail Goods"
      }
    ],
    "sg:phone": "+1 440 871 2540",
    "sg:postcode": "44145",
    "sg:province": "OH",
    "sg:tags": [
      "oil"
    ],
    "wof:name": "Shell True North Energy",
    "wof:placetype": "venue"
  },
  "geometry": {"coordinates":[-81.905277,41.469643],"type":"Point"}
}
