{
  "type": "Feature",
  "properties": {
    "addr:full":"3673 Berkeley Rd Cleveland OH 44118",
    "addr:housenumber":"3673",
    "addr:postcode":"44118",
    "addr:street":"Berkeley Rd",
    "iso:country":"US",
    "sg:address":"3673 Berkeley Rd",
    "sg:city":"Cleveland",
    "sg:classifiers":[
        {
            "category":"Retail",
            "subcategory":"Auto Repair",
            "type":"Services"
        }
    ],
    "sg:phone":"+1 216 321 6000",
    "sg:postcode":"44118",
    "sg:province":"OH",
    "sg:tags":[
        "wrecker"
    ],
    "wof:name":"Tuffy's Towing & Vehicle",
    "wof:placetype":"venue"
},
  "geometry": {"coordinates":[-81.55147599999999,41.510068],"type":"Point"}
}