{
  "type": "Feature",
  "properties": {
    "iso:country":"US",
    "sg:address":"1840 Mackenzie Dr",
    "sg:city":"Columbus",
    "sg:classifiers":[
        {
            "category":"Insurance",
            "subcategory":"Hazard Insurance",
            "type":"Services"
        }
    ],
    "sg:phone":"+1 614 442 2500",
    "sg:postcode":"43220",
    "sg:province":"OH",
    "sg:tags":[
        "profit",
        "sharing",
        "pension",
        "plan"
    ],
    "wof:name":"Advisors Pension Svc Inc",
    "wof:placetype":"venue"
},
  "geometry": {"coordinates":[-83.069754,40.05173],"type":"Point"}
}