{
  "type": "Feature",
  "properties": {
    "addr:full":"1420 Presidential Dr Columbus OH 43212",
    "addr:housenumber":"1420",
    "addr:postcode":"43212",
    "addr:street":"Presidential Dr",
    "iso:country":"US",
    "sg:address":"1420 Presidential Dr",
    "sg:city":"Columbus",
    "sg:classifiers":[
        {
            "category":"Real Estate",
            "subcategory":"Real Estate Operator",
            "type":"Services"
        }
    ],
    "sg:phone":"+1 614 488 8644",
    "sg:postcode":"43212",
    "sg:province":"OH",
    "sg:tags":[
        "building",
        "nonresidential"
    ],
    "wof:name":"Tobar Properties LLC",
    "wof:placetype":"venue"
},
  "geometry": {"coordinates":[-83.046807,39.997213],"type":"Point"}
}