{
  "type": "Feature",
  "properties": {
    "iso:country":"US",
    "sg:address":"2756 S Arlington Rd",
    "sg:city":"Akron",
    "sg:classifiers":[
        {
            "category":"Government",
            "subcategory":"Office",
            "type":"Public Place"
        }
    ],
    "sg:phone":"+1 330 644 2265",
    "sg:postcode":"44312",
    "sg:province":"OH",
    "sg:tags":[
        "state"
    ],
    "wof:name":"Natural Resources Dept",
    "wof:placetype":"venue"
},
  "geometry": {"coordinates":[-81.492161,40.996271],"type":"Point"}
}