{
  "type": "Feature",
  "properties": {
    "addr:full":"1037 N Main St Bowling Green OH 43402",
    "addr:housenumber":"1037",
    "addr:postcode":"43402",
    "addr:street":"N Main St",
    "iso:country":"US",
    "sg:address":"1037 N Main St",
    "sg:city":"Bowling Green",
    "sg:classifiers":[
        {
            "category":"Real Estate",
            "subcategory":"Real Estate Agent",
            "type":"Services"
        }
    ],
    "sg:phone":"+1 419 352 3563",
    "sg:postcode":"43402",
    "sg:province":"OH",
    "sg:tags":[
        "broker",
        "auctioneer"
    ],
    "wof:name":"Bradley Real Estate & Auction",
    "wof:placetype":"venue"
},
  "geometry": {"coordinates":[-83.65054600000001,41.385925],"type":"Point"}
}