{
  "type": "Feature",
  "properties": {
    "iso:country":"US",
    "sg:address":"5486 Clarendon Dr",
    "sg:city":"Solon",
    "sg:classifiers":[
        {
            "category":"Professional",
            "type":"Services"
        }
    ],
    "sg:phone":"+1 440 248 3934",
    "sg:postcode":"44139",
    "sg:province":"OH",
    "wof:name":"Bob Kronenberg",
    "wof:placetype":"venue"
},
  "geometry": {"coordinates":[-81.447154,41.410591],"type":"Point"}
}