{
  "type": "Feature",
  "properties": {
    "iso:country":"US",
    "sg:address":"1553 Cordova Ave",
    "sg:city":"Cleveland",
    "sg:classifiers":[
        {
            "category":"Professional",
            "subcategory":"Management & Consulting",
            "type":"Services"
        }
    ],
    "sg:phone":"+1 216 227 8336",
    "sg:postcode":"44107",
    "sg:province":"OH",
    "sg:tags":[
        "consultant"
    ],
    "wof:name":"Kenneth J Uhler & Conslnt LLC",
    "wof:placetype":"venue"
},
  "geometry": {"coordinates":[-81.815748,41.479966],"type":"Point"}
}