{
  "type": "Feature",
  "properties": {
    "addr:full": "1553 Cordova Ave Cleveland OH 44107",
    "addr:housenumber": "1553",
    "addr:postcode": "44107",
    "addr:street": "Cordova Ave",
    "iso:country": "US",
    "sg:address": "1553 Cordova Ave",
    "sg:city": "Cleveland",
    "sg:classifiers": [
      {
        "category": "Professional",
        "subcategory": "Management \u0026 Consulting",
        "type": "Services"
      }
    ],
    "sg:phone": "+1 216 227 8336",
    "sg:postcode": "44107",
    "sg:province": "OH",
    "sg:tags": [
      "consultant"
    ],
    "wof:name": "Kenneth J Uhler \u0026 Conslnt LLC",
    "wof:placetype": "venue"
  },
  "geometry": {"coordinates":[-81.815748,41.479966],"type":"Point"}
}
