{
  "type": "Feature",
  "properties": {
    "iso:country":"US",
    "sg:address":"1205 Northmoreland Blvd",
    "sg:city":"Cuyahoga Falls",
    "sg:classifiers":[
        {
            "category":"Banks & Credit Unions",
            "subcategory":"Bank",
            "type":"Services"
        }
    ],
    "sg:phone":"+1 330 564 2374",
    "sg:postcode":"44221",
    "sg:province":"OH",
    "sg:tags":[
        "cashing",
        "check"
    ],
    "sg:website":"www.cashlandloans.com",
    "wof:name":"Cashland",
    "wof:placetype":"venue"
},
  "geometry": {"coordinates":[-81.46414799999999,41.132332],"type":"Point"}
}