{
  "type": "Feature",
  "properties": {
    "addr:full": "1719 Mansfield Rd Toledo OH 43613",
    "addr:housenumber": "1719",
    "addr:postcode": "43613",
    "addr:street": "Mansfield Rd",
    "iso:country": "US",
    "sg:address": "1719 Mansfield Rd",
    "sg:city": "Toledo",
    "sg:classifiers": [
      {
        "category": "Shopping",
        "subcategory": "Computers \u0026 Home Electronics",
        "type": "Retail Goods"
      }
    ],
    "sg:phone": "+1 419 531 9070",
    "sg:postcode": "43613",
    "sg:province": "OH",
    "wof:name": "Technology Enterprises",
    "wof:placetype": "venue"
  },
  "geometry": {"coordinates":[-83.586605,41.685388],"type":"Point"}
}
