{
  "type": "Feature",
  "properties": {
    "iso:country":"US",
    "sg:address":"1719 Mansfield Rd",
    "sg:city":"Toledo",
    "sg:classifiers":[
        {
            "category":"Shopping",
            "subcategory":"Computers & Home Electronics",
            "type":"Retail Goods"
        }
    ],
    "sg:phone":"+1 419 531 9070",
    "sg:postcode":"43613",
    "sg:province":"OH",
    "wof:name":"Technology Enterprises",
    "wof:placetype":"venue"
},
  "geometry": {"coordinates":[-83.586605,41.685388],"type":"Point"}
}