{
  "type": "Feature",
  "properties": {
    "addr:full": "6413 Anita Dr Cleveland OH 44130",
    "addr:housenumber": "6413",
    "addr:postcode": "44130",
    "addr:street": "Anita Dr",
    "iso:country": "US",
    "sg:address": "6413 Anita Dr",
    "sg:city": "Cleveland",
    "sg:classifiers": [
      {
        "category": "Wholesale",
        "subcategory": "Stationery",
        "type": "Manufacturing \u0026 Wholesale Goods"
      }
    ],
    "sg:phone": "+1 440 845 0228",
    "sg:postcode": "44130",
    "sg:province": "OH",
    "sg:tags": [
      "supply"
    ],
    "wof:name": "Wilco Business Forms Inc",
    "wof:placetype": "venue"
  },
  "geometry": {"coordinates":[-81.779455,41.385557],"type":"Point"}
}
