{
  "type": "Feature",
  "properties": {
    "addr:full": "1603 Gum Grove Rd Clarksville OH 45113",
    "addr:housenumber": "1603",
    "addr:postcode": "45113",
    "addr:street": "Gum Grove Rd",
    "iso:country": "US",
    "sg:address": "1603 Gum Grove Rd",
    "sg:city": "Clarksville",
    "sg:classifiers": [
      {
        "category": "Farming",
        "subcategory": "Nursery",
        "type": "Manufacturing \u0026 Wholesale Goods"
      }
    ],
    "sg:phone": "+1 937 289 3041",
    "sg:postcode": "45113",
    "sg:province": "OH",
    "sg:tags": [
      "ornamental"
    ],
    "wof:name": "Duncan Sod",
    "wof:placetype": "venue"
  },
  "geometry": {"coordinates":[-84.029697,39.398914],"type":"Point"}
}
