{
  "type": "Feature",
  "properties": {
    "addr:full": "9 S West Ave Willard OH 44890",
    "addr:housenumber": "9",
    "addr:postcode": "44890",
    "addr:street": "S West Ave",
    "iso:country": "US",
    "sg:address": "9 S West Ave",
    "sg:city": "Willard",
    "sg:classifiers": [
      {
        "category": "Retail",
        "subcategory": "Laundry \u0026 Dry Cleaning",
        "type": "Services"
      }
    ],
    "sg:phone": "+1 419 933 2296",
    "sg:postcode": "44890",
    "sg:province": "OH",
    "sg:tags": [
      "cleaners",
      "rug",
      "carpet"
    ],
    "wof:name": "Country Fresh Carpet Cleaning",
    "wof:placetype": "venue"
  },
  "geometry": {"coordinates":[-82.73761,41.058292],"type":"Point"}
}
