{
  "type": "Feature",
  "properties": {
    "iso:country":"US",
    "sg:address":"610 S Plum St",
    "sg:city":"Marysville",
    "sg:classifiers":[
        {
            "category":"Health Services",
            "subcategory":"Doctor",
            "type":"Services"
        }
    ],
    "sg:phone":"+1 937 644 1920",
    "sg:postcode":"43040",
    "sg:province":"OH",
    "sg:tags":[
        "physician",
        "surgeon"
    ],
    "wof:name":"Marysville Pediatrics",
    "wof:placetype":"venue"
},
  "geometry": {"coordinates":[-83.36619,40.230869],"type":"Point"}
}