{
  "type": "Feature",
  "properties": {
    "addr:full":"5270 Hudson Dr Hudson OH 44236",
    "addr:housenumber":"5270",
    "addr:postcode":"44236",
    "addr:street":"Hudson Dr",
    "iso:country":"US",
    "sg:address":"5270 Hudson Dr",
    "sg:city":"Hudson",
    "sg:classifiers":[
        {
            "category":"Manufacturing",
            "subcategory":"Wood Products",
            "type":"Manufacturing & Wholesale Goods"
        }
    ],
    "sg:phone":"+1 330 650 0582",
    "sg:postcode":"44236",
    "sg:province":"OH",
    "wof:name":"Claflin Co",
    "wof:placetype":"venue"
},
  "geometry": {"coordinates":[-81.451691,41.207143],"type":"Point"}
}