{
  "type": "Feature",
  "properties": {
    "addr:full":"101 N Main St Spencer OH 44275",
    "addr:housenumber":"101",
    "addr:postcode":"44275",
    "addr:street":"N Main St",
    "iso:country":"US",
    "sg:address":"101 N Main St",
    "sg:city":"Spencer",
    "sg:classifiers":[
        {
            "category":"Government",
            "subcategory":"Office",
            "type":"Public Place"
        }
    ],
    "sg:phone":"+1 330 648 2401",
    "sg:postcode":"44275",
    "sg:province":"OH",
    "sg:tags":[
        "utility"
    ],
    "wof:name":"Spencer Village Water Dept",
    "wof:placetype":"venue"
},
  "geometry": {"coordinates":[-82.1233,41.100894],"type":"Point"}
}