{
  "type": "Feature",
  "properties": {
    "iso:country":"US",
    "sg:address":"926 Waller St",
    "sg:city":"Portsmouth",
    "sg:classifiers":[
        {
            "category":"Freight",
            "type":"Transportation"
        }
    ],
    "sg:phone":"+1 740 354 4430",
    "sg:postcode":"45662",
    "sg:province":"OH",
    "sg:tags":[
        "operator",
        "local",
        "trucking"
    ],
    "wof:name":"S Walker Hauling",
    "wof:placetype":"venue"
},
  "geometry": {"coordinates":[-82.989069,38.737822],"type":"Point"}
}