{
  "type": "Feature",
  "properties": {
    "addr:full":"12045 Lebanon Rd Cincinnati OH 45241",
    "addr:housenumber":"12045",
    "addr:postcode":"45241",
    "addr:street":"Lebanon Rd",
    "iso:country":"US",
    "sg:address":"12045 Lebanon Rd",
    "sg:city":"Cincinnati",
    "sg:classifiers":[
        {
            "category":"Bakery",
            "type":"Food & Drink"
        },
        {
            "category":"Coffee & Tea",
            "type":"Food & Drink"
        },
        {
            "category":"Bagels",
            "type":"Food & Drink"
        },
        {
            "category":"Donuts",
            "type":"Food & Drink"
        }
    ],
    "sg:menulink":"http://www.allmenus.com/oh/sharonville/143937-dunkin-donuts/menu/",
    "sg:phone":"+1 513 563 6022",
    "sg:postcode":"45241",
    "sg:province":"OH",
    "sg:tags":[
        "american",
        "diner",
        "pastry"
    ],
    "wof:name":"Dunkin' Donuts",
    "wof:placetype":"venue"
},
  "geometry": {"coordinates":[-84.393394,39.293307],"type":"Point"}
}