{
  "type": "Feature",
  "properties": {
    "addr:full":"4526 Indianridge Rd Sylvania OH 43560",
    "addr:housenumber":"4526",
    "addr:postcode":"43560",
    "addr:street":"Indianridge Rd",
    "iso:country":"US",
    "sg:address":"4526 Indianridge Rd",
    "sg:city":"Sylvania",
    "sg:classifiers":[
        {
            "category":"Manufacturing",
            "subcategory":"Metals",
            "type":"Manufacturing & Wholesale Goods"
        }
    ],
    "sg:phone":"+1 419 474 1543",
    "sg:postcode":"43560",
    "sg:province":"OH",
    "sg:tags":[
        "metalwork",
        "architectural",
        "mfg"
    ],
    "wof:name":"Twining Co",
    "wof:placetype":"venue"
},
  "geometry": {"coordinates":[-83.65543,41.724973],"type":"Point"}
}