{
  "type": "Feature",
  "properties": {
    "iso:country":"US",
    "sg:address":"4555 Lake Forest Dr",
    "sg:city":"Cincinnati",
    "sg:classifiers":[
        {
            "category":"Shopping",
            "subcategory":"Computers & Home Electronics",
            "type":"Retail Goods"
        }
    ],
    "sg:phone":"+1 513 554 0123",
    "sg:postcode":"45242",
    "sg:province":"OH",
    "sg:tags":[
        "software"
    ],
    "sg:website":"www.compuware.com",
    "wof:name":"Compuware Corp",
    "wof:placetype":"venue"
},
  "geometry": {"coordinates":[-84.37745,39.253512],"type":"Point"}
}