{
  "type": "Feature",
  "properties": {
    "iso:country":"US",
    "sg:address":"11713 Spencerville-Delphos Rd",
    "sg:city":"Delphos",
    "sg:classifiers":[
        {
            "category":"Home & Garden",
            "subcategory":"Garden Supply",
            "type":"Retail Goods"
        }
    ],
    "sg:phone":"+1 419 695 1931",
    "sg:postcode":"45833",
    "sg:province":"OH",
    "sg:tags":[
        "supp",
        "chemical",
        "fe",
        "preparation",
        "mfg"
    ],
    "wof:name":"Royster-Clark Inc",
    "wof:placetype":"venue"
},
  "geometry": {"coordinates":[-84.359371,40.834716],"type":"Point"}
}