{
  "type": "Feature",
  "properties": {
    "iso:country":"US",
    "sg:address":"3051 Highpoint Trl",
    "sg:city":"Stow",
    "sg:classifiers":[
        {
            "category":"Shopping",
            "subcategory":"Gifts & Souvenirs",
            "type":"Retail Goods"
        }
    ],
    "sg:phone":"+1 330 677 4082",
    "sg:postcode":"44224",
    "sg:province":"OH",
    "sg:tags":[
        "shop",
        "novelty"
    ],
    "wof:name":"Decorative Expressions",
    "wof:placetype":"venue"
},
  "geometry": {"coordinates":[-81.398878,41.149309],"type":"Point"}
}