{
  "type": "Feature",
  "properties": {
    "addr:full": "6415 Madison Rd Cincinnati OH 45227",
    "addr:housenumber": "6415",
    "addr:postcode": "45227",
    "addr:street": "Madison Rd",
    "iso:country": "US",
    "sg:address": "6415 Madison Rd",
    "sg:city": "Cincinnati",
    "sg:classifiers": [
      {
        "category": "Autos \u0026 Motor Vehicles",
        "subcategory": "Fuel \u0026 Gas Station",
        "type": "Retail Goods"
      }
    ],
    "sg:phone": "+1 513 272 2534",
    "sg:postcode": "45227",
    "sg:province": "OH",
    "sg:tags": [
      "grocery",
      "station",
      "gasoline"
    ],
    "wof:name": "Speedway 1064",
    "wof:placetype": "venue"
  },
  "geometry": {"coordinates":[-84.385623,39.160084],"type":"Point"}
}
