{
  "type": "Feature",
  "properties": {
    "addr:full":"325 S Sandusky St Delaware OH 43015",
    "addr:housenumber":"325",
    "addr:postcode":"43015",
    "addr:street":"S Sandusky St",
    "iso:country":"US",
    "sg:address":"325 S Sandusky St",
    "sg:city":"Delaware",
    "sg:classifiers":[
        {
            "category":"Organizations",
            "subcategory":"Labor Organization",
            "type":"Services"
        }
    ],
    "sg:phone":"+1 740 369 9090",
    "sg:postcode":"43015",
    "sg:province":"OH",
    "sg:website":"www.uaw.org",
    "wof:name":"UAW",
    "wof:placetype":"venue"
},
  "geometry": {"coordinates":[-83.068594,40.287967],"type":"Point"}
}