{
  "type": "Feature",
  "properties": {
    "addr:full": "648 Clinton St Defiance OH 43512",
    "addr:housenumber": "648",
    "addr:postcode": "43512",
    "addr:street": "Clinton St",
    "iso:country": "US",
    "sg:address": "648 Clinton St",
    "sg:city": "Defiance",
    "sg:classifiers": [
      {
        "category": "Organizations",
        "subcategory": "Community Association",
        "type": "Services"
      }
    ],
    "sg:phone": "+1 419 782 4969",
    "sg:postcode": "43512",
    "sg:province": "OH",
    "wof:name": "American Legion Post 117",
    "wof:placetype": "venue"
  },
  "geometry": {"coordinates":[-84.364571,41.282878],"type":"Point"}
}
