{
  "type": "Feature",
  "properties": {
    "iso:country":"US",
    "sg:address":"648 Clinton St",
    "sg:city":"Defiance",
    "sg:classifiers":[
        {
            "category":"Organizations",
            "subcategory":"Community Association",
            "type":"Services"
        }
    ],
    "sg:phone":"+1 419 782 4969",
    "sg:postcode":"43512",
    "sg:province":"OH",
    "wof:name":"American Legion Post 117",
    "wof:placetype":"venue"
},
  "geometry": {"coordinates":[-84.364571,41.282878],"type":"Point"}
}