{
  "type": "Feature",
  "properties": {
    "addr:full": "7630 Hub Pkwy Cleveland OH 44125",
    "addr:housenumber": "7630",
    "addr:postcode": "44125",
    "addr:street": "Hub Pkwy",
    "iso:country": "US",
    "sg:address": "7630 Hub Pkwy",
    "sg:city": "Cleveland",
    "sg:classifiers": [
      {
        "category": "Professional",
        "subcategory": "Computer Services",
        "type": "Services"
      }
    ],
    "sg:phone": "+1 216 520 6230",
    "sg:postcode": "44125",
    "sg:province": "OH",
    "sg:tags": [
      "website",
      "design"
    ],
    "wof:name": "North Coast Virtual Marketing",
    "wof:placetype": "venue"
  },
  "geometry": {"coordinates":[-81.588519,41.364031],"type":"Point"}
}
