{
  "type": "Feature",
  "properties": {
    "addr:full":"836 W Main St Troy OH 45373",
    "addr:housenumber":"836",
    "addr:postcode":"45373",
    "addr:street":"W Main St",
    "iso:country":"US",
    "sg:address":"836 W Main St",
    "sg:city":"Troy",
    "sg:classifiers":[
        {
            "category":"Restaurant",
            "type":"Food & Drink"
        }
    ],
    "sg:phone":"+1 937 335 6800",
    "sg:postcode":"45373",
    "sg:province":"OH",
    "sg:tags":[
        "eating"
    ],
    "wof:name":"Gran Rio Mexican Restaurant",
    "wof:placetype":"venue"
},
  "geometry": {"coordinates":[-84.21177400000001,40.043274],"type":"Point"}
}