{
  "type": "Feature",
  "properties": {
    "addr:full": "120 S Main St Marysville OH 43040",
    "addr:housenumber": "120",
    "addr:postcode": "43040",
    "addr:street": "S Main St",
    "iso:country": "US",
    "sg:address": "120 S Main St",
    "sg:city": "Marysville",
    "sg:classifiers": [
      {
        "category": "Banks \u0026 Credit Unions",
        "subcategory": "Investment Brokerage",
        "type": "Services"
      }
    ],
    "sg:phone": "+1 937 642 0021",
    "sg:postcode": "43040",
    "sg:province": "OH",
    "sg:tags": [
      "security"
    ],
    "wof:name": "Advest Inc",
    "wof:placetype": "venue"
  },
  "geometry": {"coordinates":[-83.366869,40.236183],"type":"Point"}
}
