{
  "type": "Feature",
  "properties": {
    "addr:full":"2921 W State St Fremont OH 43420",
    "addr:housenumber":"2921",
    "addr:postcode":"43420",
    "addr:street":"W State St",
    "iso:country":"US",
    "sg:address":"2921 W State St",
    "sg:city":"Fremont",
    "sg:classifiers":[
        {
            "category":"Retail",
            "subcategory":"Auto Repair",
            "type":"Services"
        }
    ],
    "sg:phone":"+1 419 332 3360",
    "sg:postcode":"43420",
    "sg:province":"OH",
    "sg:tags":[
        "body",
        "automobile",
        "painting"
    ],
    "wof:name":"Trevino Body Shop",
    "wof:placetype":"venue"
},
  "geometry": {"coordinates":[-83.15573500000001,41.364813],"type":"Point"}
}