{
  "type": "Feature",
  "properties": {
    "addr:full": "522 S Metcalf St Lima OH 45801",
    "addr:housenumber": "522",
    "addr:postcode": "45801",
    "addr:street": "S Metcalf St",
    "iso:country": "US",
    "sg:address": "522 S Metcalf St",
    "sg:city": "Lima",
    "sg:classifiers": [
      {
        "category": "Autos \u0026 Motor Vehicles",
        "subcategory": "Auto Supplies",
        "type": "Retail Goods"
      }
    ],
    "sg:phone": "+1 419 228 6221",
    "sg:postcode": "45801",
    "sg:province": "OH",
    "sg:tags": [
      "automobile",
      "stereo",
      "radio"
    ],
    "wof:name": "Midget Radio Shop",
    "wof:placetype": "venue"
  },
  "geometry": {"coordinates":[-84.11344,40.734694],"type":"Point"}
}
