{
  "type": "Feature",
  "properties": {
    "iso:country":"US",
    "sg:address":"1617 State Rd",
    "sg:city":"Cuyahoga Falls",
    "sg:classifiers":[
        {
            "category":"Autos & Motor Vehicles",
            "subcategory":"Auto Supplies",
            "type":"Retail Goods"
        }
    ],
    "sg:phone":"+1 330 923 5754",
    "sg:postcode":"44223",
    "sg:province":"OH",
    "sg:tags":[
        "automobile",
        "parts"
    ],
    "wof:name":"Swanky Moto",
    "wof:placetype":"venue"
},
  "geometry": {"coordinates":[-81.508346,41.128639],"type":"Point"}
}