{
  "type": "Feature",
  "properties": {
    "iso:country":"US",
    "sg:address":"213 S Chillicothe St",
    "sg:city":"Plain City",
    "sg:classifiers":[
        {
            "category":"Government",
            "subcategory":"Office",
            "type":"Public Place"
        }
    ],
    "sg:phone":"+1 614 873 3165",
    "sg:postcode":"43064",
    "sg:province":"OH",
    "sg:tags":[
        "city",
        "taxation"
    ],
    "wof:name":"Village Clerk Treasurer",
    "wof:placetype":"venue"
},
  "geometry": {"coordinates":[-83.266277,40.10652],"type":"Point"}
}