{
  "type": "Feature",
  "properties": {
    "addr:full": "234 Autumn Rd SE Carrollton OH 44615",
    "addr:housenumber": "234",
    "addr:postcode": "44615",
    "addr:street": "Autumn Rd Se",
    "iso:country": "US",
    "sg:address": "234 Autumn Rd SE",
    "sg:city": "Carrollton",
    "sg:classifiers": [
      {
        "category": "Organizations",
        "subcategory": "Professional Association",
        "type": "Services"
      }
    ],
    "sg:phone": "+1 330 627 5910",
    "sg:postcode": "44615",
    "sg:province": "OH",
    "wof:name": "Carroll County Historical Scty",
    "wof:placetype": "venue"
  },
  "geometry": {"coordinates":[-81.089729,40.513582],"type":"Point"}
}
