{
  "type": "Feature",
  "properties": {
    "addr:full": "915 Perkins Jones Rd NE Warren OH 44483",
    "addr:housenumber": "915",
    "addr:postcode": "44483",
    "addr:street": "Perkins Jones Rd Ne",
    "iso:country": "US",
    "sg:address": "915 Perkins Jones Rd NE",
    "sg:city": "Warren",
    "sg:classifiers": [
      {
        "category": "Building \u0026 Trades",
        "subcategory": "Construction",
        "type": "Services"
      }
    ],
    "sg:phone": "+1 330 372 5317",
    "sg:postcode": "44483",
    "sg:province": "OH",
    "sg:tags": [
      "excavation",
      "excavating",
      "contractor"
    ],
    "wof:name": "Z-Tech Builders-Excavators",
    "wof:placetype": "venue"
  },
  "geometry": {"coordinates":[-80.789615,41.281636],"type":"Point"}
}
