{
  "type": "Feature",
  "properties": {
    "iso:country":"US",
    "sg:address":"27040 Cedar Rd",
    "sg:city":"Cleveland",
    "sg:classifiers":[
        {
            "category":"Real Estate",
            "subcategory":"Real Estate Agent",
            "type":"Services"
        }
    ],
    "sg:phone":"+1 216 468 1000",
    "sg:postcode":"44122",
    "sg:province":"OH",
    "sg:tags":[
        "consultant"
    ],
    "wof:name":"Kay Consulting",
    "wof:placetype":"venue"
},
  "geometry": {"coordinates":[-81.488731,41.501094],"type":"Point"}
}