{
  "type": "Feature",
  "properties": {
    "addr:full": "6150 Dutch Hollow Rd Lima OH 45807",
    "addr:housenumber": "6150",
    "addr:postcode": "45807",
    "addr:street": "Dutch Hollow Rd",
    "iso:country": "US",
    "sg:address": "6150 Dutch Hollow Rd",
    "sg:city": "Lima",
    "sg:classifiers": [
      {
        "category": "Farming",
        "subcategory": "Livestock Farm",
        "type": "Manufacturing \u0026 Wholesale Goods"
      }
    ],
    "sg:phone": "+1 419 642 3212",
    "sg:postcode": "45807",
    "sg:province": "OH",
    "sg:tags": [
      "chicken",
      "equine"
    ],
    "wof:name": "Robert Alger",
    "wof:placetype": "venue"
  },
  "geometry": {"coordinates":[-84.201421,40.830838],"type":"Point"}
}
