{
  "type": "Feature",
  "properties": {
    "addr:full":"3724 Harrison Ave Cincinnati OH 45211",
    "addr:housenumber":"3724",
    "addr:postcode":"45211",
    "addr:street":"Harrison Ave",
    "iso:country":"US",
    "sg:address":"3724 Harrison Ave",
    "sg:city":"Cincinnati",
    "sg:classifiers":[
        {
            "category":"Home & Garden",
            "subcategory":"Furniture",
            "type":"Retail Goods"
        }
    ],
    "sg:phone":"+1 513 661 6116",
    "sg:postcode":"45211",
    "sg:province":"OH",
    "sg:tags":[
        "cabinet"
    ],
    "wof:name":"J & B Cabinet Design",
    "wof:placetype":"venue"
},
  "geometry": {"coordinates":[-84.612208,39.156642],"type":"Point"}
}