{
  "type": "Feature",
  "properties": {
    "addr:full": "2343 Westbrooke Dr Columbus OH 43228",
    "addr:housenumber": "2343",
    "addr:postcode": "43228",
    "addr:street": "Westbrooke Dr",
    "iso:country": "US",
    "sg:address": "2343 Westbrooke Dr",
    "sg:city": "Columbus",
    "sg:classifiers": [
      {
        "category": "Manufacturing",
        "subcategory": "Printing",
        "type": "Manufacturing \u0026 Wholesale Goods"
      }
    ],
    "sg:phone": "+1 614 345 0000",
    "sg:postcode": "43228",
    "sg:province": "OH",
    "sg:tags": [
      "engraver"
    ],
    "wof:name": "Phototype Engraving Co Inc",
    "wof:placetype": "venue"
  },
  "geometry": {"coordinates":[-83.112272,40.00154],"type":"Point"}
}
