{
  "type": "Feature",
  "properties": {
    "iso:country":"US",
    "sg:address":"8158 Lake Dr NE",
    "sg:city":"Mineral City",
    "sg:classifiers":[
        {
            "category":"Organizations",
            "subcategory":"Religious Organization",
            "type":"Services"
        }
    ],
    "sg:phone":"+1 330 364 1353",
    "sg:postcode":"44656",
    "sg:province":"OH",
    "sg:tags":[
        "church"
    ],
    "wof:name":"Lake Drive Fellowship",
    "wof:placetype":"venue"
},
  "geometry": {"coordinates":[-81.298599,40.544432],"type":"Point"}
}