{
  "type": "Feature",
  "properties": {
    "addr:full": "5070 Shady Ridge Ln Cleveland OH 44131",
    "addr:housenumber": "5070",
    "addr:postcode": "44131",
    "addr:street": "Shady Ridge Ln",
    "iso:country": "US",
    "sg:address": "5070 Shady Ridge Ln",
    "sg:city": "Cleveland",
    "sg:classifiers": [
      {
        "category": "Real Estate",
        "subcategory": "Real Estate Agent",
        "type": "Services"
      }
    ],
    "sg:phone": "+1 216 398 0929",
    "sg:postcode": "44131",
    "sg:province": "OH",
    "wof:name": "Montclair Realty LLC",
    "wof:placetype": "venue"
  },
  "geometry": {"coordinates":[-81.672085,41.41703],"type":"Point"}
}
