{
  "type": "Feature",
  "properties": {
    "iso:country":"US",
    "sg:address":"330 N Main St",
    "sg:city":"Lima",
    "sg:classifiers":[
        {
            "category":"Banks & Credit Unions",
            "subcategory":"Investment Brokerage",
            "type":"Services"
        }
    ],
    "sg:phone":"+1 419 228 0400",
    "sg:postcode":"45801",
    "sg:province":"OH",
    "sg:tags":[
        "consultant",
        "planning",
        "financial"
    ],
    "wof:name":"Pomeroy Financial Planning LLC",
    "wof:placetype":"venue"
},
  "geometry": {"coordinates":[-84.10491,40.743637],"type":"Point"}
}