{
  "type": "Feature",
  "properties": {
    "iso:country":"US",
    "sg:address":"223 Perry Dr NW",
    "sg:city":"Canton",
    "sg:classifiers":[
        {
            "category":"Organizations",
            "subcategory":"Religious Organization",
            "type":"Services"
        }
    ],
    "sg:phone":"+1 330 477 7854",
    "sg:postcode":"44708",
    "sg:province":"OH",
    "sg:tags":[
        "clergy"
    ],
    "wof:name":"David D Burwell",
    "wof:placetype":"venue"
},
  "geometry": {"coordinates":[-81.445545,40.801023],"type":"Point"}
}