{
  "type": "Feature",
  "properties": {
    "addr:full":"219 Brainard Dr Youngstown OH 44512",
    "addr:housenumber":"219",
    "addr:postcode":"44512",
    "addr:street":"Brainard Dr",
    "iso:country":"US",
    "sg:address":"219 Brainard Dr",
    "sg:city":"Youngstown",
    "sg:classifiers":[
        {
            "category":"Professional",
            "subcategory":"Lawyer & Legal Services",
            "type":"Services"
        },
        {
            "category":"Professional",
            "type":"Services"
        }
    ],
    "sg:phone":"+1 330 965 1093",
    "sg:postcode":"44512",
    "sg:province":"OH",
    "sg:tags":[
        "attorney"
    ],
    "wof:name":"Bruce M Broyles Co L P A",
    "wof:placetype":"venue"
},
  "geometry": {"coordinates":[-80.66838799999999,41.041035],"type":"Point"}
}