{
  "type": "Feature",
  "properties": {
    "addr:full":"7014 Rock Springs Dr Hamilton OH 45011",
    "addr:housenumber":"7014",
    "addr:postcode":"45011",
    "addr:street":"Rock Springs Dr",
    "iso:country":"US",
    "sg:address":"7014 Rock Springs Dr",
    "sg:city":"Hamilton",
    "sg:classifiers":[
        {
            "category":"Professional",
            "subcategory":"Management & Consulting",
            "type":"Services"
        }
    ],
    "sg:phone":"+1 513 755 2559",
    "sg:postcode":"45011",
    "sg:province":"OH",
    "sg:tags":[
        "compressor",
        "mfr",
        "air"
    ],
    "wof:name":"Air Squared Inc",
    "wof:placetype":"venue"
},
  "geometry": {"coordinates":[-84.424452,39.377451],"type":"Point"}
}