{
  "type": "Feature",
  "properties": {
    "iso:country":"US",
    "sg:address":"2561 Linden Ave",
    "sg:city":"Zanesville",
    "sg:classifiers":[
        {
            "category":"Professional",
            "subcategory":"Business Services",
            "type":"Services"
        }
    ],
    "sg:phone":"+1 740 450 7950",
    "sg:postcode":"43701",
    "sg:province":"OH",
    "wof:name":"Mystic Creations Air Brush",
    "wof:placetype":"venue"
},
  "geometry": {"coordinates":[-81.994788,39.970275],"type":"Point"}
}