{
  "type": "Feature",
  "properties": {
    "addr:full": "3737 W Market St Akron OH 44333",
    "addr:housenumber": "3737",
    "addr:postcode": "44333",
    "addr:street": "W Market St",
    "iso:country": "US",
    "sg:address": "3737 W Market St",
    "sg:city": "Akron",
    "sg:classifiers": [
      {
        "category": "Coffee \u0026 Tea",
        "type": "Food \u0026 Drink"
      },
      {
        "category": "Bagels",
        "type": "Food \u0026 Drink"
      }
    ],
    "sg:menulink": "http://www.allmenus.com/oh/fairlawn/114752-brueggers/menu/",
    "sg:phone": "+1 330 665 1050",
    "sg:postcode": "44333",
    "sg:province": "OH",
    "sg:tags": [
      "wrap",
      "soup",
      "american",
      "sandwich",
      "salad"
    ],
    "wof:name": "Bruegger's",
    "wof:placetype": "venue"
  },
  "geometry": {"coordinates":[-81.634632,41.135999],"type":"Point"}
}
