{
  "type": "Feature",
  "properties": {
    "iso:country":"US",
    "sg:address":"1351 S High St",
    "sg:city":"Columbus",
    "sg:classifiers":[
        {
            "category":"Retail",
            "subcategory":"Funeral Services",
            "type":"Services"
        }
    ],
    "sg:phone":"+1 614 444 7854",
    "sg:postcode":"43207",
    "sg:province":"OH",
    "wof:name":"Graumlich & Son Funeral Home",
    "wof:placetype":"venue"
},
  "geometry": {"coordinates":[-82.996092,39.93508],"type":"Point"}
}