{
  "type": "Feature",
  "properties": {
    "iso:country":"US",
    "sg:address":"1335 Parkway Dr",
    "sg:city":"Lorain",
    "sg:classifiers":[
        {
            "category":"Professional",
            "type":"Services"
        }
    ],
    "sg:phone":"+1 440 282 1315",
    "sg:postcode":"44053",
    "sg:province":"OH",
    "wof:name":"Wayne Baird",
    "wof:placetype":"venue"
},
  "geometry": {"coordinates":[-82.187713,41.424172],"type":"Point"}
}