{
  "type": "Feature",
  "properties": {
    "iso:country":"US",
    "sg:address":"5482 Wadsworth Rd",
    "sg:city":"Dayton",
    "sg:classifiers":[
        {
            "category":"Autos & Motor Vehicles",
            "subcategory":"Automobile Sales",
            "type":"Retail Goods"
        }
    ],
    "sg:phone":"+1 937 277 0875",
    "sg:postcode":"45414",
    "sg:province":"OH",
    "sg:tags":[
        "used"
    ],
    "wof:name":"National Trends Truck Sales",
    "wof:placetype":"venue"
},
  "geometry": {"coordinates":[-84.187265,39.825587],"type":"Point"}
}