{
  "type": "Feature",
  "properties": {
    "iso:country":"US",
    "sg:address":"177 S 4th St",
    "sg:city":"Newark",
    "sg:classifiers":[
        {
            "category":"Banks & Credit Unions",
            "subcategory":"Financial Services",
            "type":"Services"
        }
    ],
    "sg:phone":"+1 614 783 1382",
    "sg:postcode":"43055",
    "sg:province":"OH",
    "sg:tags":[
        "investor"
    ],
    "wof:name":"Murphy Ventures Inc",
    "wof:placetype":"venue"
},
  "geometry": {"coordinates":[-82.401865,40.052243],"type":"Point"}
}