{
  "type": "Feature",
  "properties": {
    "addr:full": "177 S 4th St Newark OH 43055",
    "addr:housenumber": "177",
    "addr:postcode": "43055",
    "addr:street": "S 4Th St",
    "iso:country": "US",
    "sg:address": "177 S 4th St",
    "sg:city": "Newark",
    "sg:classifiers": [
      {
        "category": "Banks \u0026 Credit Unions",
        "subcategory": "Financial Services",
        "type": "Services"
      }
    ],
    "sg:phone": "+1 614 783 1382",
    "sg:postcode": "43055",
    "sg:province": "OH",
    "sg:tags": [
      "investor"
    ],
    "wof:name": "Murphy Ventures Inc",
    "wof:placetype": "venue"
  },
  "geometry": {"coordinates":[-82.401865,40.052243],"type":"Point"}
}
