{
  "type": "Feature",
  "properties": {
    "addr:full":"2403 Professor Ave Cleveland OH 44113",
    "addr:housenumber":"2403",
    "addr:postcode":"44113",
    "addr:street":"Professor Ave",
    "iso:country":"US",
    "sg:address":"2403 Professor Ave",
    "sg:city":"Cleveland",
    "sg:classifiers":[
        {
            "category":"Shopping",
            "type":"Retail Goods"
        }
    ],
    "sg:phone":"+1 216 357 4085",
    "sg:postcode":"44113",
    "sg:province":"OH",
    "sg:tags":[
        "art",
        "gallery",
        "dealer"
    ],
    "wof:name":"Gingko Limited",
    "wof:placetype":"venue"
},
  "geometry": {"coordinates":[-81.68511700000001,41.480337],"type":"Point"}
}