{
  "type": "Feature",
  "properties": {
    "addr:full": "3741 Charring Cross Dr Stow OH 44224",
    "addr:housenumber": "3741",
    "addr:postcode": "44224",
    "addr:street": "Charring Cross Dr",
    "iso:country": "US",
    "sg:address": "3741 Charring Cross Dr",
    "sg:city": "Stow",
    "sg:classifiers": [
      {
        "category": "Retail",
        "subcategory": "Auto Repair",
        "type": "Services"
      }
    ],
    "sg:phone": "+1 330 689 0654",
    "sg:postcode": "44224",
    "sg:province": "OH",
    "sg:tags": [
      "body",
      "automobile",
      "used"
    ],
    "wof:name": "Scooters Auto Sales",
    "wof:placetype": "venue"
  },
  "geometry": {"coordinates":[-81.427645,41.161308],"type":"Point"}
}
