{
  "type": "Feature",
  "properties": {
    "addr:full":"3590 Pleasant Ave Hamilton OH 45015",
    "addr:housenumber":"3590",
    "addr:postcode":"45015",
    "addr:street":"Pleasant Ave",
    "iso:country":"US",
    "sg:address":"3590 Pleasant Ave",
    "sg:city":"Hamilton",
    "sg:classifiers":[
        {
            "category":"Health Services",
            "subcategory":"Chiropractor",
            "type":"Services"
        }
    ],
    "sg:phone":"+1 513 895 8888",
    "sg:postcode":"45015",
    "sg:province":"OH",
    "wof:name":"Pleasant Avenue Chiro Inc",
    "wof:placetype":"venue"
},
  "geometry": {"coordinates":[-84.558098,39.360604],"type":"Point"}
}