{
  "type": "Feature",
  "properties": {
    "addr:full": "275 Taylor Station Rd Columbus OH 43213",
    "addr:housenumber": "275",
    "addr:postcode": "43213",
    "addr:street": "Taylor Station Rd",
    "iso:country": "US",
    "sg:address": "275 Taylor Station Rd",
    "sg:city": "Columbus",
    "sg:classifiers": [
      {
        "category": "Health Services",
        "subcategory": "Doctor",
        "type": "Services"
      }
    ],
    "sg:phone": "+1 614 751 4466",
    "sg:postcode": "43213",
    "sg:province": "OH",
    "sg:tags": [
      "physician",
      "medical",
      "surgeon"
    ],
    "wof:name": "Taylor Station Surgical Center",
    "wof:placetype": "venue"
  },
  "geometry": {"coordinates":[-82.843204,39.983984],"type":"Point"}
}
