{
  "type": "Feature",
  "properties": {
    "iso:country":"US",
    "sg:address":"9200 Broadview Rd",
    "sg:city":"Broadview Heights",
    "sg:classifiers":[
        {
            "category":"Banks & Credit Unions",
            "subcategory":"Bank",
            "type":"Services"
        }
    ],
    "sg:phone":"+1 440 746 1010",
    "sg:postcode":"44147",
    "sg:province":"OH",
    "sg:tags":[
        "broker",
        "mortgage"
    ],
    "wof:name":"Consumer Financial Counseling",
    "wof:placetype":"venue"
},
  "geometry": {"coordinates":[-81.684759,41.317732],"type":"Point"}
}