{
  "type": "Feature",
  "properties": {
    "iso:country":"US",
    "sg:address":"10470 Johnnycake Ridge Rd",
    "sg:city":"Painesville",
    "sg:classifiers":[
        {
            "category":"Professional",
            "subcategory":"Accounting & Tax Preparation",
            "type":"Services"
        }
    ],
    "sg:phone":"+1 440 354 3511",
    "sg:postcode":"44077",
    "sg:province":"OH",
    "sg:tags":[
        "accountant"
    ],
    "wof:name":"Ronald Call Accounting",
    "wof:placetype":"venue"
},
  "geometry": {"coordinates":[-81.263954,41.690427],"type":"Point"}
}