{
  "type": "Feature",
  "properties": {
    "iso:country":"US",
    "sg:address":"24620 Aurora Rd",
    "sg:city":"Cleveland",
    "sg:classifiers":[
        {
            "category":"Retail",
            "subcategory":"Auto Repair",
            "type":"Services"
        }
    ],
    "sg:phone":"+1 440 735 0154",
    "sg:postcode":"44146",
    "sg:province":"OH",
    "sg:tags":[
        "repairing",
        "automobile"
    ],
    "wof:name":"Nici's Auto Svc",
    "wof:placetype":"venue"
},
  "geometry": {"coordinates":[-81.504619,41.412108],"type":"Point"}
}