{
  "type": "Feature",
  "properties": {
    "addr:full":"3456 Mayfield Rd Cleveland OH 44118",
    "addr:housenumber":"3456",
    "addr:postcode":"44118",
    "addr:street":"Mayfield Rd",
    "iso:country":"US",
    "sg:address":"3456 Mayfield Rd",
    "sg:city":"Cleveland",
    "sg:classifiers":[
        {
            "category":"Restaurant",
            "type":"Food & Drink"
        }
    ],
    "sg:menulink":"http://www.allmenus.com/oh/cleveland-heights/170214-burger-king/menu/",
    "sg:phone":"+1 216 297 1830",
    "sg:postcode":"44118",
    "sg:province":"OH",
    "sg:tags":[
        "burger",
        "american"
    ],
    "wof:name":"Burger King",
    "wof:placetype":"venue"
},
  "geometry": {"coordinates":[-81.556431,41.520344],"type":"Point"}
}