{
  "type": "Feature",
  "properties": {
    "addr:full":"6924 Spring Valley Dr Holland OH 43528",
    "addr:housenumber":"6924",
    "addr:postcode":"43528",
    "addr:street":"Spring Valley Dr",
    "iso:country":"US",
    "sg:address":"6924 Spring Valley Dr",
    "sg:city":"Holland",
    "sg:classifiers":[
        {
            "category":"Banks & Credit Unions",
            "subcategory":"Bank",
            "type":"Services"
        }
    ],
    "sg:phone":"+1 419 866 5220",
    "sg:postcode":"43528",
    "sg:province":"OH",
    "sg:tags":[
        "loan",
        "real estate"
    ],
    "wof:name":"Premier Mortgage Funding Inc",
    "wof:placetype":"venue"
},
  "geometry": {"coordinates":[-83.705416,41.6129],"type":"Point"}
}