{
  "type": "Feature",
  "properties": {
    "iso:country":"US",
    "sg:address":"3127 Shirley Rd",
    "sg:city":"Youngstown",
    "sg:classifiers":[
        {
            "category":"Building & Trades",
            "subcategory":"Construction",
            "type":"Services"
        }
    ],
    "sg:phone":"+1 330 788 2161",
    "sg:postcode":"44502",
    "sg:province":"OH",
    "sg:tags":[
        "sewer",
        "contractor"
    ],
    "wof:name":"Malenic Sewer & Drain Co",
    "wof:placetype":"venue"
},
  "geometry": {"coordinates":[-80.62799200000001,41.067875],"type":"Point"}
}