{
  "type": "Feature",
  "properties": {
    "addr:full": "198 Millrose Dr Saint Clairsville OH 43950",
    "addr:housenumber": "198",
    "addr:postcode": "43950",
    "addr:street": "Millrose Dr Saint Clairsville",
    "iso:country": "US",
    "sg:address": "198 Millrose Dr",
    "sg:city": "Saint Clairsville",
    "sg:classifiers": [
      {
        "category": "Real Estate",
        "subcategory": "Real Estate Operator",
        "type": "Services"
      }
    ],
    "sg:phone": "+1 740 695 4303",
    "sg:postcode": "43950",
    "sg:province": "OH",
    "sg:tags": [
      "mobile",
      "home",
      "site"
    ],
    "wof:name": "Phillips Traylor Park",
    "wof:placetype": "venue"
  },
  "geometry": {"coordinates":[-80.890797,40.086829],"type":"Point"}
}
