{
  "type": "Feature",
  "properties": {
    "iso:country":"US",
    "sg:address":"4292 Broadview Rd",
    "sg:city":"Richfield",
    "sg:classifiers":[
        {
            "category":"Freight",
            "type":"Transportation"
        }
    ],
    "sg:phone":"+1 330 659 6492",
    "sg:postcode":"44286",
    "sg:province":"OH",
    "wof:name":"Transport Services Unlimited",
    "wof:placetype":"venue"
},
  "geometry": {"coordinates":[-81.65988299999999,41.246162],"type":"Point"}
}