{
  "type": "Feature",
  "properties": {
    "addr:full":"8675 W Pine Lake Rd Salem OH 44460",
    "addr:housenumber":"8675",
    "addr:postcode":"44460",
    "addr:street":"W Pine Lake Rd",
    "iso:country":"US",
    "sg:address":"8675 W Pine Lake Rd",
    "sg:city":"Salem",
    "sg:classifiers":[
        {
            "category":"Building & Trades",
            "subcategory":"Construction",
            "type":"Services"
        }
    ],
    "sg:phone":"+1 330 702 0147",
    "sg:postcode":"44460",
    "sg:province":"OH",
    "sg:tags":[
        "home",
        "builder"
    ],
    "wof:name":"Green Space Homes",
    "wof:placetype":"venue"
},
  "geometry": {"coordinates":[-80.81382600000001,40.929676],"type":"Point"}
}