{
  "type": "Feature",
  "properties": {
    "iso:country":"US",
    "sg:address":"6030 Steubenville Rd SE",
    "sg:city":"Amsterdam",
    "sg:classifiers":[
        {
            "category":"Farming",
            "subcategory":"Livestock Farm",
            "type":"Manufacturing & Wholesale Goods"
        }
    ],
    "sg:phone":"+1 740 543 3993",
    "sg:postcode":"43903",
    "sg:province":"OH",
    "sg:tags":[
        "animal",
        "general"
    ],
    "wof:name":"James Booth",
    "wof:placetype":"venue"
},
  "geometry": {"coordinates":[-80.93541999999999,40.482782],"type":"Point"}
}