{
  "type": "Feature",
  "properties": {
    "addr:full": "5341 Harroun Rd Sylvania OH 43560",
    "addr:housenumber": "5341",
    "addr:postcode": "43560",
    "addr:street": "Harroun Rd",
    "iso:country": "US",
    "sg:address": "5341 Harroun Rd",
    "sg:city": "Sylvania",
    "sg:classifiers": [
      {
        "category": "Professional",
        "subcategory": "Research",
        "type": "Services"
      }
    ],
    "sg:phone": "+1 419 885 7268",
    "sg:postcode": "43560",
    "sg:province": "OH",
    "sg:tags": [
      "market",
      "analysis"
    ],
    "wof:name": "AML Marketing Research",
    "wof:placetype": "venue"
  },
  "geometry": {"coordinates":[-83.69474,41.713045],"type":"Point"}
}
