{
  "type": "Feature",
  "properties": {
    "iso:country":"US",
    "sg:address":"2540 Shawnee Rd",
    "sg:city":"Lima",
    "sg:classifiers":[
        {
            "category":"Shopping",
            "subcategory":"Gifts & Souvenirs",
            "type":"Retail Goods"
        }
    ],
    "sg:phone":"+1 419 224 4448",
    "sg:postcode":"45806",
    "sg:province":"OH",
    "sg:tags":[
        "shop"
    ],
    "wof:name":"Cottage Treasures Gift Shop",
    "wof:placetype":"venue"
},
  "geometry": {"coordinates":[-84.151501,40.702873],"type":"Point"}
}