{
  "type": "Feature",
  "properties": {
    "iso:country":"US",
    "sg:address":"734 Fawcett Dr",
    "sg:city":"Dayton",
    "sg:classifiers":[
        {
            "category":"Professional",
            "subcategory":"Computer Services",
            "type":"Services"
        }
    ],
    "sg:phone":"+1 937 431 0576",
    "sg:postcode":"45434",
    "sg:province":"OH",
    "sg:tags":[
        "programing",
        "related",
        "custom"
    ],
    "wof:name":"Northrop Grumman Info Tech",
    "wof:placetype":"venue"
},
  "geometry": {"coordinates":[-84.04631000000001,39.712401],"type":"Point"}
}