{
  "type": "Feature",
  "properties": {
    "iso:country":"US",
    "sg:address":"549 Main St",
    "sg:city":"Coshocton",
    "sg:classifiers":[
        {
            "category":"Home & Garden",
            "subcategory":"Carpets & Floor Coverings",
            "type":"Retail Goods"
        }
    ],
    "sg:phone":"+1 740 622 0372",
    "sg:postcode":"43812",
    "sg:province":"OH",
    "sg:tags":[
        "dealer",
        "rug"
    ],
    "wof:name":"Fisher Decorating Ctr",
    "wof:placetype":"venue"
},
  "geometry": {"coordinates":[-81.86245700000001,40.273437],"type":"Point"}
}