{
  "type": "Feature",
  "properties": {
    "addr:full":"1545 W 2nd St Dayton OH 45402",
    "addr:housenumber":"1545",
    "addr:postcode":"45402",
    "addr:street":"W 2Nd St",
    "iso:country":"US",
    "sg:address":"1545 W 2nd St",
    "sg:city":"Dayton",
    "sg:classifiers":[
        {
            "category":"Shopping",
            "type":"Retail Goods"
        }
    ],
    "sg:phone":"+1 937 222 9110",
    "sg:postcode":"45402",
    "sg:province":"OH",
    "sg:tags":[
        "telephone",
        "cellular"
    ],
    "wof:name":"Express Communications",
    "wof:placetype":"venue"
},
  "geometry": {"coordinates":[-84.220034,39.756096],"type":"Point"}
}