{
  "type": "Feature",
  "properties": {
    "addr:full": "1445 Marion-Waldo Rd Marion OH 43302",
    "addr:housenumber": "1445",
    "addr:postcode": "43302",
    "addr:street": "Marion-Waldo Rd",
    "iso:country": "US",
    "sg:address": "1445 Marion-Waldo Rd",
    "sg:city": "Marion",
    "sg:classifiers": [
      {
        "category": "Shopping",
        "subcategory": "Books",
        "type": "Retail Goods"
      }
    ],
    "sg:phone": "+1 740 389 5557",
    "sg:postcode": "43302",
    "sg:province": "OH",
    "wof:name": "Waldenbooks",
    "wof:placetype": "venue"
  },
  "geometry": {"coordinates":[-83.119524,40.562787],"type":"Point"}
}
