{
  "type": "Feature",
  "properties": {
    "addr:full": "4226 Red River-West Grove Rd Arcanum OH 45304",
    "addr:housenumber": "4226",
    "addr:postcode": "45304",
    "addr:street": "Red River-West Grove Rd",
    "iso:country": "US",
    "sg:address": "4226 Red River-West Grove Rd",
    "sg:city": "Arcanum",
    "sg:phone": "+1 937 947 2023",
    "sg:postcode": "45304",
    "sg:province": "OH",
    "sg:tags": [
      "farm",
      "corn",
      "soybean"
    ],
    "wof:name": "David Ditmer Farm",
    "wof:placetype": "venue"
  },
  "geometry": {"coordinates":[-84.448268,40.041967],"type":"Point"}
}
