{
  "type": "Feature",
  "properties": {
    "addr:full":"21 W Elm St Butler OH 44822",
    "addr:housenumber":"21",
    "addr:postcode":"44822",
    "addr:street":"W Elm St",
    "iso:country":"US",
    "sg:address":"21 W Elm St",
    "sg:city":"Butler",
    "sg:classifiers":[
        {
            "category":"Education",
            "subcategory":"Library",
            "type":"Public Place"
        }
    ],
    "sg:phone":"+1 419 883 2220",
    "sg:postcode":"44822",
    "sg:province":"OH",
    "wof:name":"Butler Branch Library",
    "wof:placetype":"venue"
},
  "geometry": {"coordinates":[-82.426053,40.588437],"type":"Point"}
}