{
  "type": "Feature",
  "properties": {
    "addr:full": "7535 Cady Rd North Royalton OH 44133",
    "addr:housenumber": "7535",
    "addr:postcode": "44133",
    "addr:street": "Cady Rd",
    "iso:country": "US",
    "sg:address": "7535 Cady Rd",
    "sg:city": "North Royalton",
    "sg:classifiers": [
      {
        "category": "Professional",
        "subcategory": "Management \u0026 Consulting",
        "type": "Services"
      }
    ],
    "sg:phone": "+1 440 230 2924",
    "sg:postcode": "44133",
    "sg:province": "OH",
    "sg:tags": [
      "excavation",
      "business",
      "contractor"
    ],
    "wof:name": "AMF Construction Co",
    "wof:placetype": "venue"
  },
  "geometry": {"coordinates":[-81.728389,41.285596],"type":"Point"}
}
