{
  "type": "Feature",
  "properties": {
    "addr:full": "114 Upper Rd Piketon OH 45661",
    "addr:housenumber": "114",
    "addr:postcode": "45661",
    "addr:street": "Upper Rd",
    "iso:country": "US",
    "sg:address": "114 Upper Rd",
    "sg:city": "Piketon",
    "sg:classifiers": [
      {
        "category": "Organizations",
        "subcategory": "Religious Organization",
        "type": "Services"
      }
    ],
    "sg:phone": "+1 740 493 2060",
    "sg:postcode": "45661",
    "sg:province": "OH",
    "sg:tags": [
      "church"
    ],
    "sg:website": "www.cccuhq.org",
    "wof:name": "Bethel CCU",
    "wof:placetype": "venue"
  },
  "geometry": {"coordinates":[-83.124144,39.009382],"type":"Point"}
}
