{
  "type": "Feature",
  "properties": {
    "addr:full": "176 Woodman Dr Dayton OH 45431",
    "addr:housenumber": "176",
    "addr:postcode": "45431",
    "addr:street": "Woodman Dr",
    "iso:country": "US",
    "sg:address": "176 Woodman Dr",
    "sg:city": "Dayton",
    "sg:classifiers": [
      {
        "category": "Shopping",
        "subcategory": "Shoes",
        "type": "Retail Goods"
      }
    ],
    "sg:phone": "+1 937 443 6000",
    "sg:postcode": "45431",
    "sg:province": "OH",
    "wof:name": "Airway Shoe Service",
    "wof:placetype": "venue"
  },
  "geometry": {"coordinates":[-84.123304,39.767558],"type":"Point"}
}
