{
  "type": "Feature",
  "properties": {
    "addr:full":"6406 Fernhurst Ave Cleveland OH 44130",
    "addr:postcode":"6406;44130",
    "addr:street":"Fernhurst Ave",
    "iso:country":"US",
    "sg:address":"6406 Fernhurst Ave",
    "sg:city":"Cleveland",
    "sg:classifiers":[
        {
            "category":"Building & Trades",
            "subcategory":"Construction",
            "type":"Services"
        }
    ],
    "sg:phone":"+1 440 724 1697",
    "sg:postcode":"44130",
    "sg:province":"OH",
    "sg:tags":[
        "house"
    ],
    "wof:name":"Anthony Campomizzi Remodeling",
    "wof:placetype":"venue"
},
  "geometry": {"coordinates":[-81.781111,41.387406],"type":"Point"}
}