{
  "type": "Feature",
  "properties": {
    "addr:full":"224 N Gamble St Shelby OH 44875",
    "addr:housenumber":"224",
    "addr:postcode":"44875",
    "addr:street":"N Gamble St",
    "iso:country":"US",
    "sg:address":"224 N Gamble St",
    "sg:city":"Shelby",
    "sg:classifiers":[
        {
            "category":"Professional",
            "type":"Services"
        }
    ],
    "sg:phone":"+1 419 342 2952",
    "sg:postcode":"44875",
    "sg:province":"OH",
    "sg:tags":[
        "establishment"
    ],
    "wof:name":"Charlie's Body Shop",
    "wof:placetype":"venue"
},
  "geometry": {"coordinates":[-82.662419,40.889109],"type":"Point"}
}