{
  "type": "Feature",
  "properties": {
    "addr:full": "7830 Sugar Bush Ln Gates Mills OH 44040",
    "addr:housenumber": "7830",
    "addr:postcode": "44040",
    "addr:street": "Sugar Bush Ln",
    "iso:country": "US",
    "sg:address": "7830 Sugar Bush Ln",
    "sg:city": "Gates Mills",
    "sg:classifiers": [
      {
        "category": "Professional",
        "subcategory": "Engineering",
        "type": "Services"
      }
    ],
    "sg:phone": "+1 440 423 3520",
    "sg:postcode": "44040",
    "sg:province": "OH",
    "sg:tags": [
      "engineer"
    ],
    "wof:name": "Pdqs Inc",
    "wof:placetype": "venue"
  },
  "geometry": {"coordinates":[-81.396762,41.565866],"type":"Point"}
}
