{
  "type": "Feature",
  "properties": {
    "addr:full": "700 W Liberty St Hubbard OH 44425",
    "addr:housenumber": "700",
    "addr:postcode": "44425",
    "addr:street": "W Liberty St",
    "iso:country": "US",
    "sg:address": "700 W Liberty St",
    "sg:city": "Hubbard",
    "sg:classifiers": [
      {
        "category": "Health Services",
        "subcategory": "Clinic",
        "type": "Services"
      },
      {
        "category": "Health Services",
        "subcategory": "Health Practitioner",
        "type": "Services"
      }
    ],
    "sg:phone": "+1 330 534 3283",
    "sg:postcode": "44425",
    "sg:province": "OH",
    "sg:tags": [
      "therapist",
      "specialty",
      "outpatient",
      "physical"
    ],
    "wof:name": "Rehabilitation Network Inc",
    "wof:placetype": "venue"
  },
  "geometry": {"coordinates":[-80.581238,41.156372],"type":"Point"}
}
