{
  "type": "Feature",
  "properties": {
    "iso:country":"US",
    "sg:address":"3950 Davidson Run Ct",
    "sg:city":"Hilliard",
    "sg:classifiers":[
        {
            "category":"Farming",
            "subcategory":"Dairy Farm",
            "type":"Manufacturing & Wholesale Goods"
        }
    ],
    "sg:phone":"+1 614 921 9778",
    "sg:postcode":"43026",
    "sg:province":"OH",
    "wof:name":"Ron Buffington",
    "wof:placetype":"venue"
},
  "geometry": {"coordinates":[-83.12335400000001,40.053657],"type":"Point"}
}