{
  "type": "Feature",
  "properties": {
    "addr:full": "3950 Davidson Run Ct Hilliard OH 43026",
    "addr:housenumber": "3950",
    "addr:postcode": "43026",
    "addr:street": "Davidson Run Ct",
    "iso:country": "US",
    "sg:address": "3950 Davidson Run Ct",
    "sg:city": "Hilliard",
    "sg:classifiers": [
      {
        "category": "Farming",
        "subcategory": "Dairy Farm",
        "type": "Manufacturing \u0026 Wholesale Goods"
      }
    ],
    "sg:phone": "+1 614 921 9778",
    "sg:postcode": "43026",
    "sg:province": "OH",
    "wof:name": "Ron Buffington",
    "wof:placetype": "venue"
  },
  "geometry": {"coordinates":[-83.123354,40.053657],"type":"Point"}
}
