{
  "type": "Feature",
  "properties": {
    "addr:full":"1348 Maxfli Dr Akron OH 44312",
    "addr:housenumber":"1348",
    "addr:postcode":"44312",
    "addr:street":"Maxfli Dr",
    "iso:country":"US",
    "sg:address":"1348 Maxfli Dr",
    "sg:city":"Akron",
    "sg:classifiers":[
        {
            "category":"Banks & Credit Unions",
            "subcategory":"Financial Services",
            "type":"Services"
        }
    ],
    "sg:phone":"+1 330 644 7255",
    "sg:postcode":"44312",
    "sg:province":"OH",
    "sg:tags":[
        "company",
        "holding"
    ],
    "wof:name":"Hughes Holdings LLC",
    "wof:placetype":"venue"
},
  "geometry": {"coordinates":[-81.477158,40.991565],"type":"Point"}
}