{
  "type": "Feature",
  "properties": {
    "addr:full": "5204 Mahoning Ave Austintown OH 44515",
    "addr:housenumber": "5204",
    "addr:postcode": "44515",
    "addr:street": "Mahoning Ave",
    "iso:country": "US",
    "sg:address": "5204 Mahoning Ave",
    "sg:city": "Austintown",
    "sg:classifiers": [
      {
        "category": "Retail",
        "subcategory": "Repair Shop",
        "type": "Services"
      }
    ],
    "sg:phone": "+1 330 793 2422",
    "sg:postcode": "44515",
    "sg:province": "OH",
    "sg:tags": [
      "jewelry"
    ],
    "wof:name": "Jewelers Bench",
    "wof:placetype": "venue"
  },
  "geometry": {"coordinates":[-80.755552,41.099671],"type":"Point"}
}
