{
  "type": "Feature",
  "properties": {
    "addr:full": "8067 Maddock Rd North Ridgeville OH 44039",
    "addr:housenumber": "8067",
    "addr:postcode": "44039",
    "addr:street": "Maddock Rd",
    "iso:country": "US",
    "sg:address": "8067 Maddock Rd",
    "sg:city": "North Ridgeville",
    "sg:classifiers": [
      {
        "category": "Shopping",
        "subcategory": "Bicycles \u0026 Sporting Goods",
        "type": "Retail Goods"
      }
    ],
    "sg:phone": "+1 440 327 4817",
    "sg:postcode": "44039",
    "sg:province": "OH",
    "sg:tags": [
      "archery",
      "supply"
    ],
    "wof:name": "Pierces Archery Inc",
    "wof:placetype": "venue"
  },
  "geometry": {"coordinates":[-82.031813,41.378041],"type":"Point"}
}
