{
  "type": "Feature",
  "properties": {
    "addr:full":"300 N Fair Ave Hamilton OH 45011",
    "addr:housenumber":"300",
    "addr:postcode":"45011",
    "addr:street":"N Fair Ave",
    "iso:country":"US",
    "sg:address":"300 N Fair Ave",
    "sg:city":"Hamilton",
    "sg:classifiers":[
        {
            "category":"Government",
            "subcategory":"Office",
            "type":"Public Place"
        }
    ],
    "sg:phone":"+1 513 887 4000",
    "sg:postcode":"45011",
    "sg:province":"OH",
    "sg:tags":[
        "county",
        "resource"
    ],
    "wof:name":"Butler County Human Svc",
    "wof:placetype":"venue"
},
  "geometry": {"coordinates":[-84.54132799999999,39.397428],"type":"Point"}
}