{
  "type": "Feature",
  "properties": {
    "iso:country":"US",
    "sg:address":"2760 Som Center Rd",
    "sg:city":"Willoughby",
    "sg:classifiers":[
        {
            "category":"Insurance",
            "subcategory":"Hazard Insurance",
            "type":"Services"
        }
    ],
    "sg:phone":"+1 440 516 2600",
    "sg:postcode":"44094",
    "sg:province":"OH",
    "sg:tags":[
        "carrier"
    ],
    "wof:name":"United States Warranty Corp",
    "wof:placetype":"venue"
},
  "geometry": {"coordinates":[-81.43963100000001,41.589556],"type":"Point"}
}