{
  "type": "Feature",
  "properties": {
    "addr:full": "2760 Som Center Rd Willoughby OH 44094",
    "addr:postcode": "2760;44094",
    "addr:street": "Som Center Rd",
    "iso:country": "US",
    "sg:address": "2760 Som Center Rd",
    "sg:city": "Willoughby",
    "sg:classifiers": [
      {
        "category": "Insurance",
        "subcategory": "Hazard Insurance",
        "type": "Services"
      }
    ],
    "sg:phone": "+1 440 516 2600",
    "sg:postcode": "44094",
    "sg:province": "OH",
    "sg:tags": [
      "carrier"
    ],
    "wof:name": "United States Warranty Corp",
    "wof:placetype": "venue"
  },
  "geometry": {"coordinates":[-81.439631,41.589556],"type":"Point"}
}
