{
  "type": "Feature",
  "properties": {
    "addr:full": "3757 Fishcreek Rd Stow OH 44224",
    "addr:housenumber": "3757",
    "addr:postcode": "44224",
    "addr:street": "Fishcreek Rd",
    "iso:country": "US",
    "sg:address": "3757 Fishcreek Rd",
    "sg:city": "Stow",
    "sg:classifiers": [
      {
        "category": "Home \u0026 Garden",
        "subcategory": "Furniture",
        "type": "Retail Goods"
      }
    ],
    "sg:phone": "+1 330 686 6311",
    "sg:postcode": "44224",
    "sg:province": "OH",
    "wof:name": "Quality Marketing",
    "wof:placetype": "venue"
  },
  "geometry": {"coordinates":[-81.401399,41.161616],"type":"Point"}
}
