{
  "type": "Feature",
  "properties": {
    "addr:full": "1973 Edison Dr Piqua OH 45356",
    "addr:housenumber": "1973",
    "addr:postcode": "45356",
    "addr:street": "Edison Dr",
    "iso:country": "US",
    "sg:address": "1973 Edison Dr",
    "sg:city": "Piqua",
    "sg:classifiers": [
      {
        "category": "Education",
        "subcategory": "Junior College",
        "type": "Public Place"
      }
    ],
    "sg:phone": "+1 937 778 8600",
    "sg:postcode": "45356",
    "sg:province": "OH",
    "sg:website": "www.edisonohio.edu",
    "wof:name": "Edison State Community College",
    "wof:placetype": "venue"
  },
  "geometry": {"coordinates":[-84.211422,40.159119],"type":"Point"}
}
