{
  "type": "Feature",
  "properties": {
    "iso:country":"US",
    "sg:address":"333 W 1st St",
    "sg:city":"Dayton",
    "sg:classifiers":[
        {
            "category":"Organizations",
            "subcategory":"Non-profit Organization",
            "type":"Services"
        },
        {
            "category":"Professional",
            "subcategory":"Lawyer & Legal Services",
            "type":"Services"
        }
    ],
    "sg:phone":"+1 937 228 8088",
    "sg:postcode":"45402",
    "sg:province":"OH",
    "sg:tags":[
        "aid"
    ],
    "wof:name":"Legal Aid Society of Dayton",
    "wof:placetype":"venue"
},
  "geometry": {"coordinates":[-84.198663,39.761462],"type":"Point"}
}