{
  "type": "Feature",
  "properties": {
    "addr:full": "770 Daniel Rd Winchester OH 45697",
    "addr:housenumber": "770",
    "addr:postcode": "45697",
    "addr:street": "Daniel Rd",
    "iso:country": "US",
    "sg:address": "770 Daniel Rd",
    "sg:city": "Winchester",
    "sg:classifiers": [
      {
        "category": "Professional",
        "type": "Services"
      }
    ],
    "sg:phone": "+1 937 695 0604",
    "sg:postcode": "45697",
    "sg:province": "OH",
    "wof:name": "Richard R Roberts",
    "wof:placetype": "venue"
  },
  "geometry": {"coordinates":[-83.649787,39.007963],"type":"Point"}
}
