{
  "type": "Feature",
  "properties": {
    "addr:full": "109 W Logan St Celina OH 45822",
    "addr:housenumber": "109",
    "addr:postcode": "45822",
    "addr:street": "W Logan St",
    "iso:country": "US",
    "sg:address": "109 W Logan St",
    "sg:city": "Celina",
    "sg:classifiers": [
      {
        "category": "Restaurant",
        "type": "Food \u0026 Drink"
      }
    ],
    "sg:phone": "+1 419 586 3535",
    "sg:postcode": "45822",
    "sg:province": "OH",
    "wof:name": "Dairy Cone",
    "wof:placetype": "venue"
  },
  "geometry": {"coordinates":[-84.571511,40.545773],"type":"Point"}
}
