{
  "type": "Feature",
  "properties": {
    "iso:country":"US",
    "sg:address":"597 Park Ave E",
    "sg:city":"Mansfield",
    "sg:classifiers":[
        {
            "category":"Professional",
            "type":"Services"
        }
    ],
    "sg:phone":"+1 419 522 0576",
    "sg:postcode":"44905",
    "sg:province":"OH",
    "sg:tags":[
        "establishment"
    ],
    "wof:name":"Ohio Heartland Comm Action",
    "wof:placetype":"venue"
},
  "geometry": {"coordinates":[-82.49006,40.75819],"type":"Point"}
}