{
  "type": "Feature",
  "properties": {
    "iso:country":"US",
    "sg:address":"1820 W Fair Ave",
    "sg:city":"Lancaster",
    "sg:classifiers":[
        {
            "category":"Professional",
            "subcategory":"Employment Agencies",
            "type":"Services"
        }
    ],
    "sg:phone":"+1 740 654 3050",
    "sg:postcode":"43130",
    "sg:province":"OH",
    "sg:tags":[
        "help",
        "contractor"
    ],
    "wof:name":"Buckeye Staffing",
    "wof:placetype":"venue"
},
  "geometry": {"coordinates":[-82.629099,39.724998],"type":"Point"}
}