{
  "type": "Feature",
  "properties": {
    "addr:full": "15347 Lincoln Way W Dalton OH 44618",
    "addr:housenumber": "15347",
    "addr:postcode": "44618",
    "addr:street": "Lincoln Way W",
    "iso:country": "US",
    "sg:address": "15347 Lincoln Way W",
    "sg:city": "Dalton",
    "sg:classifiers": [
      {
        "category": "Farming",
        "subcategory": "Poultry Farm",
        "type": "Manufacturing \u0026 Wholesale Goods"
      }
    ],
    "sg:phone": "+1 330 833 5002",
    "sg:postcode": "44618",
    "sg:province": "OH",
    "sg:tags": [
      "hog",
      "chicken",
      "egg",
      "or",
      "feedlot"
    ],
    "wof:name": "Walter W Harrold",
    "wof:placetype": "venue"
  },
  "geometry": {"coordinates":[-81.64117,40.798874],"type":"Point"}
}
