{
  "type": "Feature",
  "properties": {
    "iso:country":"US",
    "sg:address":"15347 Lincoln Way W",
    "sg:city":"Dalton",
    "sg:classifiers":[
        {
            "category":"Farming",
            "subcategory":"Poultry Farm",
            "type":"Manufacturing & Wholesale Goods"
        }
    ],
    "sg:phone":"+1 330 833 5002",
    "sg:postcode":"44618",
    "sg:province":"OH",
    "sg:tags":[
        "hog",
        "chicken",
        "egg",
        "or",
        "feedlot"
    ],
    "wof:name":"Walter W Harrold",
    "wof:placetype":"venue"
},
  "geometry": {"coordinates":[-81.64117,40.798874],"type":"Point"}
}