{
  "type": "Feature",
  "properties": {
    "addr:full": "1040 Spindletop Hill Cincinnati OH 45245",
    "addr:housenumber": "1040",
    "addr:postcode": "45245",
    "addr:street": "Spindletop Hill",
    "iso:country": "US",
    "sg:address": "1040 Spindletop Hill",
    "sg:city": "Cincinnati",
    "sg:classifiers": [
      {
        "category": "Professional",
        "subcategory": "Management \u0026 Consulting",
        "type": "Services"
      }
    ],
    "sg:phone": "+1 513 752 6868",
    "sg:postcode": "45245",
    "sg:province": "OH",
    "sg:tags": [
      "consultant",
      "business"
    ],
    "wof:name": "Strategic Management",
    "wof:placetype": "venue"
  },
  "geometry": {"coordinates":[-84.265334,39.023817],"type":"Point"}
}
