{
  "type": "Feature",
  "properties": {
    "addr:full": "870 W Market St Tiffin OH 44883",
    "addr:housenumber": "870",
    "addr:postcode": "44883",
    "addr:street": "W Market St",
    "iso:country": "US",
    "sg:address": "870 W Market St",
    "sg:city": "Tiffin",
    "sg:classifiers": [
      {
        "category": "Shopping",
        "subcategory": "Shoes",
        "type": "Retail Goods"
      }
    ],
    "sg:phone": "+1 419 448 9864",
    "sg:postcode": "44883",
    "sg:province": "OH",
    "wof:name": "Shoebilee",
    "wof:placetype": "venue"
  },
  "geometry": {"coordinates":[-83.207576,41.111214],"type":"Point"}
}
