{
  "type": "Feature",
  "properties": {
    "addr:full": "417 S Broad St Lancaster OH 43130",
    "addr:housenumber": "417",
    "addr:postcode": "43130",
    "addr:street": "S Broad St",
    "iso:country": "US",
    "sg:address": "417 S Broad St",
    "sg:city": "Lancaster",
    "sg:classifiers": [
      {
        "category": "Retail",
        "subcategory": "Auto Repair",
        "type": "Services"
      }
    ],
    "sg:phone": "+1 740 687 5440",
    "sg:postcode": "43130",
    "sg:province": "OH",
    "sg:tags": [
      "repairing",
      "automobile"
    ],
    "wof:name": "Estep Auto \u0026 Truck Svc",
    "wof:placetype": "venue"
  },
  "geometry": {"coordinates":[-82.602178,39.710035],"type":"Point"}
}
