{
  "type": "Feature",
  "properties": {
    "addr:full": "3159 Penrod Rd NW Sugarcreek OH 44681",
    "addr:housenumber": "3159",
    "addr:postcode": "44681",
    "addr:street": "Penrod Rd Nw",
    "iso:country": "US",
    "sg:address": "3159 Penrod Rd NW",
    "sg:city": "Sugarcreek",
    "sg:classifiers": [
      {
        "category": "Freight",
        "type": "Transportation"
      }
    ],
    "sg:phone": "+1 330 852 2779",
    "sg:postcode": "44681",
    "sg:province": "OH",
    "sg:tags": [
      "general"
    ],
    "wof:name": "93 Stop N Store Mini Storage",
    "wof:placetype": "venue"
  },
  "geometry": {"coordinates":[-81.634849,40.530624],"type":"Point"}
}
