{
  "type": "Feature",
  "properties": {
    "addr:full":"5608 Zoar Rd Morrow OH 45152",
    "addr:housenumber":"5608",
    "addr:postcode":"45152",
    "addr:street":"Zoar Rd",
    "iso:country":"US",
    "sg:address":"5608 Zoar Rd",
    "sg:city":"Morrow",
    "sg:classifiers":[
        {
            "category":"Building & Trades",
            "subcategory":"Construction",
            "type":"Services"
        }
    ],
    "sg:phone":"+1 513 494 2815",
    "sg:postcode":"45152",
    "sg:province":"OH",
    "sg:tags":[
        "contractor"
    ],
    "wof:name":"Motz Roofing",
    "wof:placetype":"venue"
},
  "geometry": {"coordinates":[-84.19106499999999,39.351087],"type":"Point"}
}