{
  "type": "Feature",
  "properties": {
    "addr:full": "70 Lockwood Rd Milan OH 44846",
    "addr:housenumber": "70",
    "addr:postcode": "44846",
    "addr:street": "Lockwood Rd",
    "iso:country": "US",
    "sg:address": "70 Lockwood Rd",
    "sg:city": "Milan",
    "sg:classifiers": [
      {
        "category": "Farming",
        "subcategory": "Farm",
        "type": "Manufacturing \u0026 Wholesale Goods"
      }
    ],
    "sg:phone": "+1 419 499 2427",
    "sg:postcode": "44846",
    "sg:province": "OH",
    "wof:name": "Wikel Farms LTD",
    "wof:placetype": "venue"
  },
  "geometry": {"coordinates":[-82.604647,41.290199],"type":"Point"}
}
