{
  "type": "Feature",
  "properties": {
    "addr:full": "5916 Newtonsville Rd Goshen OH 45122",
    "addr:housenumber": "5916",
    "addr:postcode": "45122",
    "addr:street": "Newtonsville Rd",
    "iso:country": "US",
    "sg:address": "5916 Newtonsville Rd",
    "sg:city": "Goshen",
    "sg:classifiers": [
      {
        "category": "Building \u0026 Trades",
        "subcategory": "Cleaning \u0026 Sanitation",
        "type": "Services"
      }
    ],
    "sg:phone": "+1 513 625 7441",
    "sg:postcode": "45122",
    "sg:province": "OH",
    "sg:tags": [
      "window"
    ],
    "wof:name": "Buckeye Window Cleaning",
    "wof:placetype": "venue"
  },
  "geometry": {"coordinates":[-84.081346,39.188569],"type":"Point"}
}
