{
  "type": "Feature",
  "properties": {
    "iso:country":"US",
    "sg:address":"5916 Newtonsville Rd",
    "sg:city":"Goshen",
    "sg:classifiers":[
        {
            "category":"Building & Trades",
            "subcategory":"Cleaning & Sanitation",
            "type":"Services"
        }
    ],
    "sg:phone":"+1 513 625 7441",
    "sg:postcode":"45122",
    "sg:province":"OH",
    "sg:tags":[
        "window"
    ],
    "wof:name":"Buckeye Window Cleaning",
    "wof:placetype":"venue"
},
  "geometry": {"coordinates":[-84.081346,39.188569],"type":"Point"}
}