{
  "type": "Feature",
  "properties": {
    "addr:full":"4832 Plank Rd Norwalk OH 44857",
    "addr:housenumber":"4832",
    "addr:postcode":"44857",
    "addr:street":"Plank Rd",
    "iso:country":"US",
    "sg:address":"4832 Plank Rd",
    "sg:city":"Norwalk",
    "sg:classifiers":[
        {
            "category":"Wholesale",
            "subcategory":"Construction Materials",
            "type":"Manufacturing & Wholesale Goods"
        }
    ],
    "sg:phone":"+1 419 668 1610",
    "sg:postcode":"44857",
    "sg:province":"OH",
    "sg:tags":[
        "lumber"
    ],
    "wof:name":"Midwestern Wholesalers",
    "wof:placetype":"venue"
},
  "geometry": {"coordinates":[-82.614779,41.271942],"type":"Point"}
}