{
  "type": "Feature",
  "properties": {
    "addr:full": "164 E Alcott Rd Columbus OH 43207",
    "addr:housenumber": "164",
    "addr:postcode": "43207",
    "addr:street": "E Alcott Rd",
    "iso:country": "US",
    "sg:address": "164 E Alcott Rd",
    "sg:city": "Columbus",
    "sg:classifiers": [
      {
        "category": "Shopping",
        "type": "Retail Goods"
      }
    ],
    "sg:phone": "+1 614 491 2114",
    "sg:postcode": "43207",
    "sg:province": "OH",
    "sg:tags": [
      "trophy",
      "medal",
      "award"
    ],
    "wof:name": "R \u0026 J Trophies \u0026 Screen Ptg",
    "wof:placetype": "venue"
  },
  "geometry": {"coordinates":[-82.9874,39.90599],"type":"Point"}
}
