{
  "type": "Feature",
  "properties": {
    "iso:country":"US",
    "sg:address":"7414 Huntridge Ave",
    "sg:city":"Cincinnati",
    "sg:classifiers":[
        {
            "category":"Taxi",
            "type":"Transportation"
        }
    ],
    "sg:phone":"+1 513 729 3356",
    "sg:postcode":"45231",
    "sg:province":"OH",
    "sg:tags":[
        "taxicab"
    ],
    "wof:name":"Western Taxi",
    "wof:placetype":"venue"
},
  "geometry": {"coordinates":[-84.540761,39.229242],"type":"Point"}
}