{
  "type": "Feature",
  "properties": {
    "addr:full": "315 E Tiffin St Willard OH 44890",
    "addr:housenumber": "315",
    "addr:postcode": "44890",
    "addr:street": "E Tiffin St",
    "iso:country": "US",
    "sg:address": "315 E Tiffin St",
    "sg:city": "Willard",
    "sg:classifiers": [
      {
        "category": "Social Services",
        "type": "Services"
      }
    ],
    "sg:phone": "+1 419 933 4701",
    "sg:postcode": "44890",
    "sg:province": "OH",
    "sg:tags": [
      "senior",
      "executive",
      "citizen"
    ],
    "wof:name": "Services For Aging Inc",
    "wof:placetype": "venue"
  },
  "geometry": {"coordinates":[-82.721603,41.053158],"type":"Point"}
}
