{
  "type": "Feature",
  "properties": {
    "addr:full": "349 Elmdale Ave Akron OH 44320",
    "addr:housenumber": "349",
    "addr:postcode": "44320",
    "addr:street": "Elmdale Ave",
    "iso:country": "US",
    "sg:address": "349 Elmdale Ave",
    "sg:city": "Akron",
    "sg:classifiers": [
      {
        "category": "Building \u0026 Trades",
        "subcategory": "Construction",
        "type": "Services"
      }
    ],
    "sg:phone": "+1 330 865 0114",
    "sg:postcode": "44320",
    "sg:province": "OH",
    "sg:tags": [
      "gas",
      "line",
      "installation",
      "repair"
    ],
    "wof:name": "Green Mile Group",
    "wof:placetype": "venue"
  },
  "geometry": {"coordinates":[-81.567005,41.098402],"type":"Point"}
}
