{
  "type": "Feature",
  "properties": {
    "addr:full": "620 Arlington Rd Brookville OH 45309",
    "addr:housenumber": "620",
    "addr:postcode": "45309",
    "addr:street": "Arlington Rd",
    "iso:country": "US",
    "sg:address": "620 Arlington Rd",
    "sg:city": "Brookville",
    "sg:classifiers": [
      {
        "category": "Restaurant",
        "type": "Food \u0026 Drink"
      }
    ],
    "sg:menulink": "http://www.allmenus.com/oh/clay/233010-lees-famous-recipe-chicken/menu/",
    "sg:phone": "+1 937 833 6141",
    "sg:postcode": "45309",
    "sg:province": "OH",
    "sg:tags": [
      "american"
    ],
    "wof:name": "Lee's Famous Recipe Chicken",
    "wof:placetype": "venue"
  },
  "geometry": {"coordinates":[-84.424442,39.841791],"type":"Point"}
}
