{
  "type": "Feature",
  "properties": {
    "iso:country":"US",
    "sg:address":"620 Arlington Rd",
    "sg:city":"Brookville",
    "sg:classifiers":[
        {
            "category":"Restaurant",
            "type":"Food & Drink"
        }
    ],
    "sg:menulink":"http://www.allmenus.com/oh/clay/233010-lees-famous-recipe-chicken/menu/",
    "sg:phone":"+1 937 833 6141",
    "sg:postcode":"45309",
    "sg:province":"OH",
    "sg:tags":[
        "american"
    ],
    "wof:name":"Lee's Famous Recipe Chicken",
    "wof:placetype":"venue"
},
  "geometry": {"coordinates":[-84.424442,39.841791],"type":"Point"}
}