{
  "type": "Feature",
  "properties": {
    "iso:country":"US",
    "sg:address":"34208 Aurora Rd",
    "sg:city":"Cleveland",
    "sg:classifiers":[
        {
            "category":"Utilities",
            "subcategory":"Refuse",
            "type":"Services"
        },
        {
            "category":"Manufacturing",
            "subcategory":"Tools & Machinery",
            "type":"Manufacturing & Wholesale Goods"
        }
    ],
    "sg:phone":"+1 440 543 6464",
    "sg:postcode":"44139",
    "sg:province":"OH",
    "sg:tags":[
        "system",
        "compactors"
    ],
    "wof:name":"A Reddy Equipment",
    "wof:placetype":"venue"
},
  "geometry": {"coordinates":[-81.42860400000001,41.380626],"type":"Point"}
}