{
  "type": "Feature",
  "properties": {
    "addr:full":"1875 Liberty Ave Vermilion OH 44089",
    "addr:housenumber":"1875",
    "addr:postcode":"44089",
    "addr:street":"Liberty Ave",
    "iso:country":"US",
    "sg:address":"1875 Liberty Ave",
    "sg:city":"Vermilion",
    "sg:classifiers":[
        {
            "category":"Freight",
            "type":"Transportation"
        }
    ],
    "sg:phone":"+1 440 963 0277",
    "sg:postcode":"44089",
    "sg:province":"OH",
    "sg:tags":[
        "trucking"
    ],
    "wof:name":"Karnow Trucking Inc",
    "wof:placetype":"venue"
},
  "geometry": {"coordinates":[-82.288296,41.426893],"type":"Point"}
}