{
  "type": "Feature",
  "properties": {
    "iso:country":"US",
    "sg:address":"11590 Century Blvd",
    "sg:city":"Cincinnati",
    "sg:classifiers":[
        {
            "category":"Professional",
            "subcategory":"Employment Agencies",
            "type":"Services"
        }
    ],
    "sg:phone":"+1 513 671 5300",
    "sg:postcode":"45246",
    "sg:province":"OH",
    "sg:tags":[
        "help",
        "supply"
    ],
    "wof:name":"Tpsi",
    "wof:placetype":"venue"
},
  "geometry": {"coordinates":[-84.453407,39.28622],"type":"Point"}
}