{
  "type": "Feature",
  "properties": {
    "iso:country":"US",
    "sg:address":"273 S 3rd St",
    "sg:city":"Columbus",
    "sg:classifiers":[
        {
            "category":"Professional",
            "subcategory":"Employment Agencies",
            "type":"Services"
        }
    ],
    "sg:phone":"+1 614 228 7777",
    "sg:postcode":"43215",
    "sg:province":"OH",
    "sg:tags":[
        "help",
        "contractor"
    ],
    "wof:name":"Validex Employment Screening",
    "wof:placetype":"venue"
},
  "geometry": {"coordinates":[-82.99691900000001,39.956771],"type":"Point"}
}