{
  "type": "Feature",
  "properties": {
    "addr:full":"2214 Tedrow Rd Toledo OH 43614",
    "addr:housenumber":"2214",
    "addr:postcode":"43614",
    "addr:street":"Tedrow Rd",
    "iso:country":"US",
    "sg:address":"2214 Tedrow Rd",
    "sg:city":"Toledo",
    "sg:classifiers":[
        {
            "category":"Shopping",
            "subcategory":"Crafts & Fabrics",
            "type":"Retail Goods"
        }
    ],
    "sg:phone":"+1 419 385 7299",
    "sg:postcode":"43614",
    "sg:province":"OH",
    "sg:tags":[
        "material",
        "needlework"
    ],
    "wof:name":"Something Extra LLC",
    "wof:placetype":"venue"
},
  "geometry": {"coordinates":[-83.62031500000001,41.599021],"type":"Point"}
}