{
  "type": "Feature",
  "properties": {
    "iso:country":"US",
    "sg:address":"780 Eastland Ave",
    "sg:city":"Akron",
    "sg:classifiers":[
        {
            "category":"Food & Beverages",
            "subcategory":"Liquor & Beverages",
            "type":"Retail Goods"
        }
    ],
    "sg:phone":"+1 330 733 5432",
    "sg:postcode":"44305",
    "sg:province":"OH",
    "sg:tags":[
        "grocery",
        "alcoholic"
    ],
    "wof:name":"Six Corners Deli",
    "wof:placetype":"venue"
},
  "geometry": {"coordinates":[-81.46812300000001,41.083932],"type":"Point"}
}