{
  "type": "Feature",
  "properties": {
    "iso:country":"US",
    "sg:address":"1479 Daily Rd",
    "sg:city":"Eaton",
    "sg:classifiers":[
        {
            "category":"Banks & Credit Unions",
            "subcategory":"Financial Services",
            "type":"Services"
        }
    ],
    "sg:phone":"+1 937 456 2116",
    "sg:postcode":"45320",
    "sg:province":"OH",
    "sg:tags":[
        "trust",
        "management"
    ],
    "wof:name":"Paul R Plummer Trust & Al",
    "wof:placetype":"venue"
},
  "geometry": {"coordinates":[-84.741708,39.75567],"type":"Point"}
}