{
  "type": "Feature",
  "properties": {
    "addr:full": "1479 Daily Rd Eaton OH 45320",
    "addr:housenumber": "1479",
    "addr:postcode": "45320",
    "addr:street": "Daily Rd",
    "iso:country": "US",
    "sg:address": "1479 Daily Rd",
    "sg:city": "Eaton",
    "sg:classifiers": [
      {
        "category": "Banks \u0026 Credit Unions",
        "subcategory": "Financial Services",
        "type": "Services"
      }
    ],
    "sg:phone": "+1 937 456 2116",
    "sg:postcode": "45320",
    "sg:province": "OH",
    "sg:tags": [
      "trust",
      "management"
    ],
    "wof:name": "Paul R Plummer Trust \u0026 Al",
    "wof:placetype": "venue"
  },
  "geometry": {"coordinates":[-84.741708,39.75567],"type":"Point"}
}
