{
  "type": "Feature",
  "properties": {
    "addr:full": "1146 N 4th St Columbus OH 43201",
    "addr:housenumber": "1146",
    "addr:postcode": "43201",
    "addr:street": "N 4Th St",
    "iso:country": "US",
    "sg:address": "1146 N 4th St",
    "sg:city": "Columbus",
    "sg:classifiers": [
      {
        "category": "Professional",
        "subcategory": "Printing \u0026 Photocopies",
        "type": "Services"
      }
    ],
    "sg:phone": "+1 614 421 9900",
    "sg:postcode": "43201",
    "sg:province": "OH",
    "sg:tags": [
      "photocopying",
      "lithographic",
      "commercial"
    ],
    "wof:name": "Cyrus Printing",
    "wof:placetype": "venue"
  },
  "geometry": {"coordinates":[-82.999492,39.986793],"type":"Point"}
}
