{
  "type": "Feature",
  "properties": {
    "iso:country":"US",
    "sg:address":"417 3rd St",
    "sg:city":"Marietta",
    "sg:classifiers":[
        {
            "category":"Travel",
            "subcategory":"Travel Agent",
            "type":"Entertainment"
        }
    ],
    "sg:phone":"+1 740 373 3198",
    "sg:postcode":"45750",
    "sg:province":"OH",
    "sg:tags":[
        "operator",
        "tour"
    ],
    "wof:name":"McClure Tours & Travel Inc",
    "wof:placetype":"venue"
},
  "geometry": {"coordinates":[-81.45711300000001,39.419734],"type":"Point"}
}