{
  "type": "Feature",
  "properties": {
    "addr:full": "417 3rd St Marietta OH 45750",
    "addr:housenumber": "417",
    "addr:postcode": "45750",
    "addr:street": "3Rd St",
    "iso:country": "US",
    "sg:address": "417 3rd St",
    "sg:city": "Marietta",
    "sg:classifiers": [
      {
        "category": "Travel",
        "subcategory": "Travel Agent",
        "type": "Entertainment"
      }
    ],
    "sg:phone": "+1 740 373 3198",
    "sg:postcode": "45750",
    "sg:province": "OH",
    "sg:tags": [
      "operator",
      "tour"
    ],
    "wof:name": "McClure Tours \u0026 Travel Inc",
    "wof:placetype": "venue"
  },
  "geometry": {"coordinates":[-81.457113,39.419734],"type":"Point"}
}
