{
  "type": "Feature",
  "properties": {
    "addr:full": "26300 Cedar Rd Cleveland OH 44122",
    "addr:housenumber": "26300",
    "addr:postcode": "44122",
    "addr:street": "Cedar Rd",
    "iso:country": "US",
    "sg:address": "26300 Cedar Rd",
    "sg:city": "Cleveland",
    "sg:classifiers": [
      {
        "category": "Utilities",
        "subcategory": "Mobile Phone",
        "type": "Services"
      }
    ],
    "sg:phone": "+1 216 765 1480",
    "sg:postcode": "44122",
    "sg:province": "OH",
    "sg:tags": [
      "telephone",
      "cellular"
    ],
    "wof:name": "Cell Style",
    "wof:placetype": "venue"
  },
  "geometry": {"coordinates":[-81.493205,41.501129],"type":"Point"}
}
