{
  "type": "Feature",
  "properties": {
    "iso:country":"US",
    "sg:address":"2305 Mahoning Ave",
    "sg:city":"Youngstown",
    "sg:classifiers":[
        {
            "category":"Autos & Motor Vehicles",
            "subcategory":"Automobile Sales",
            "type":"Retail Goods"
        }
    ],
    "sg:phone":"+1 330 779 0391",
    "sg:postcode":"44509",
    "sg:province":"OH",
    "sg:tags":[
        "car",
        "dealer"
    ],
    "wof:name":"Bob K's Auto Sales",
    "wof:placetype":"venue"
},
  "geometry": {"coordinates":[-80.69525,41.102744],"type":"Point"}
}