{
  "type": "Feature",
  "properties": {
    "iso:country":"US",
    "sg:address":"873 Eastern Ave",
    "sg:city":"Woodsfield",
    "sg:classifiers":[
        {
            "category":"Autos & Motor Vehicles",
            "subcategory":"Automobile Sales",
            "type":"Retail Goods"
        }
    ],
    "sg:phone":"+1 740 472 1610",
    "sg:postcode":"43793",
    "sg:province":"OH",
    "sg:tags":[
        "car",
        "dealer"
    ],
    "wof:name":"Maria's Auto Sales",
    "wof:placetype":"venue"
},
  "geometry": {"coordinates":[-81.096448,39.759378],"type":"Point"}
}