{
  "type": "Feature",
  "properties": {
    "iso:country":"US",
    "sg:address":"6275 E Broad St",
    "sg:city":"Columbus",
    "sg:classifiers":[
        {
            "category":"Insurance",
            "subcategory":"Insurance Agent",
            "type":"Services"
        }
    ],
    "sg:phone":"+1 614 856 2600",
    "sg:postcode":"43213",
    "sg:province":"OH",
    "wof:name":"State Farm Insurance",
    "wof:placetype":"venue"
},
  "geometry": {"coordinates":[-82.832452,39.980573],"type":"Point"}
}