{
  "type": "Feature",
  "properties": {
    "addr:full": "3614 E 65th St Cleveland OH 44105",
    "addr:housenumber": "3614",
    "addr:postcode": "44105",
    "addr:street": "E 65Th St",
    "iso:country": "US",
    "sg:address": "3614 E 65th St",
    "sg:city": "Cleveland",
    "sg:classifiers": [
      {
        "category": "Bars \u0026 Pubs",
        "type": "Food \u0026 Drink"
      }
    ],
    "sg:phone": "+1 216 341 0595",
    "sg:postcode": "44105",
    "sg:province": "OH",
    "sg:tags": [
      "drinking",
      "eating"
    ],
    "wof:name": "Karb's Tavern",
    "wof:placetype": "venue"
  },
  "geometry": {"coordinates":[-81.64507,41.460294],"type":"Point"}
}
