{
  "type": "Feature",
  "properties": {
    "iso:country":"US",
    "sg:address":"3614 E 65th St",
    "sg:city":"Cleveland",
    "sg:classifiers":[
        {
            "category":"Bars & Pubs",
            "type":"Food & Drink"
        }
    ],
    "sg:phone":"+1 216 341 0595",
    "sg:postcode":"44105",
    "sg:province":"OH",
    "sg:tags":[
        "drinking",
        "eating"
    ],
    "wof:name":"Karb's Tavern",
    "wof:placetype":"venue"
},
  "geometry": {"coordinates":[-81.64507,41.460294],"type":"Point"}
}