{
  "type": "Feature",
  "properties": {
    "iso:country":"US",
    "sg:address":"10720 Hazelton-Etna Rd SW",
    "sg:city":"Pataskala",
    "sg:classifiers":[
        {
            "category":"Autos & Motor Vehicles",
            "subcategory":"Automobile Sales",
            "type":"Retail Goods"
        }
    ],
    "sg:phone":"+1 740 964 2025",
    "sg:postcode":"43062",
    "sg:province":"OH",
    "wof:name":"Amlin Ent Inc",
    "wof:placetype":"venue"
},
  "geometry": {"coordinates":[-82.681011,39.939942],"type":"Point"}
}