{
  "type": "Feature",
  "properties": {
    "addr:full":"108 W Washington St Jamestown OH 45335",
    "addr:housenumber":"108",
    "addr:postcode":"45335",
    "addr:street":"W Washington St",
    "iso:country":"US",
    "sg:address":"108 W Washington St",
    "sg:city":"Jamestown",
    "sg:classifiers":[
        {
            "category":"Shopping",
            "subcategory":"Discount & Variety Stores",
            "type":"Retail Goods"
        }
    ],
    "sg:phone":"+1 937 675 3475",
    "sg:postcode":"45335",
    "sg:province":"OH",
    "wof:name":"Dollar General",
    "wof:placetype":"venue"
},
  "geometry": {"coordinates":[-83.74084499999999,39.65847],"type":"Point"}
}