{
  "type": "Feature",
  "properties": {
    "iso:country":"US",
    "sg:address":"3570 W Smithville Western Rd",
    "sg:city":"Wooster",
    "sg:classifiers":[
        {
            "category":"Autos & Motor Vehicles",
            "subcategory":"Recreational Vehicle Sales",
            "type":"Retail Goods"
        }
    ],
    "sg:phone":"+1 330 345 7857",
    "sg:postcode":"44691",
    "sg:province":"OH",
    "wof:name":"D & T Enterprises LLC",
    "wof:placetype":"venue"
},
  "geometry": {"coordinates":[-82.003142,40.857804],"type":"Point"}
}