{
  "type": "Feature",
  "properties": {
    "addr:full": "3570 W Smithville Western Rd Wooster OH 44691",
    "addr:housenumber": "3570",
    "addr:postcode": "44691",
    "addr:street": "W Smithville Western Rd",
    "iso:country": "US",
    "sg:address": "3570 W Smithville Western Rd",
    "sg:city": "Wooster",
    "sg:classifiers": [
      {
        "category": "Autos \u0026 Motor Vehicles",
        "subcategory": "Recreational Vehicle Sales",
        "type": "Retail Goods"
      }
    ],
    "sg:phone": "+1 330 345 7857",
    "sg:postcode": "44691",
    "sg:province": "OH",
    "wof:name": "D \u0026 T Enterprises LLC",
    "wof:placetype": "venue"
  },
  "geometry": {"coordinates":[-82.003142,40.857804],"type":"Point"}
}
