{
  "type": "Feature",
  "properties": {
    "iso:country":"US",
    "sg:address":"4154 State Rte 726",
    "sg:city":"Eldorado",
    "sg:phone":"+1 937 456 6752",
    "sg:postcode":"45321",
    "sg:province":"OH",
    "sg:tags":[
        "farm",
        "corn",
        "soybean"
    ],
    "wof:name":"Lloyd Lee",
    "wof:placetype":"venue"
},
  "geometry": {"coordinates":[-84.676543,39.834572],"type":"Point"}
}