{
  "type": "Feature",
  "properties": {
    "addr:full": "137 W 2nd St Pomeroy OH 45769",
    "addr:housenumber": "137",
    "addr:postcode": "45769",
    "addr:street": "W 2Nd St",
    "iso:country": "US",
    "sg:address": "137 W 2nd St",
    "sg:city": "Pomeroy",
    "sg:classifiers": [
      {
        "category": "Shopping",
        "subcategory": "Discount \u0026 Variety Stores",
        "type": "Retail Goods"
      }
    ],
    "sg:phone": "+1 740 992 3481",
    "sg:postcode": "45769",
    "sg:province": "OH",
    "wof:name": "Johnsons Variety Store",
    "wof:placetype": "venue"
  },
  "geometry": {"coordinates":[-82.034073,39.027341],"type":"Point"}
}
