{
  "type": "Feature",
  "properties": {
    "iso:country":"US",
    "sg:address":"137 W 2nd St",
    "sg:city":"Pomeroy",
    "sg:classifiers":[
        {
            "category":"Shopping",
            "subcategory":"Discount & Variety Stores",
            "type":"Retail Goods"
        }
    ],
    "sg:phone":"+1 740 992 3481",
    "sg:postcode":"45769",
    "sg:province":"OH",
    "wof:name":"Johnsons Variety Store",
    "wof:placetype":"venue"
},
  "geometry": {"coordinates":[-82.03407300000001,39.027341],"type":"Point"}
}