{
  "type": "Feature",
  "properties": {
    "iso:country":"US",
    "sg:address":"3243 Milstead Dr",
    "sg:city":"Toledo",
    "sg:classifiers":[
        {
            "category":"Shopping",
            "subcategory":"Florist",
            "type":"Retail Goods"
        }
    ],
    "sg:phone":"+1 419 474 5884",
    "sg:postcode":"43606",
    "sg:province":"OH",
    "wof:name":"Blossom Ridge Floral & Accents",
    "wof:placetype":"venue"
},
  "geometry": {"coordinates":[-83.610439,41.680739],"type":"Point"}
}