{
  "type": "Feature",
  "properties": {
    "addr:full": "1700 W Main St Wilmington OH 45177",
    "addr:housenumber": "1700",
    "addr:postcode": "45177",
    "addr:street": "W Main St",
    "iso:country": "US",
    "sg:address": "1700 W Main St",
    "sg:city": "Wilmington",
    "sg:classifiers": [
      {
        "category": "Home \u0026 Garden",
        "subcategory": "Carpets \u0026 Floor Coverings",
        "type": "Retail Goods"
      }
    ],
    "sg:phone": "+1 937 382 1615",
    "sg:postcode": "45177",
    "sg:province": "OH",
    "wof:name": "Superior Carpet",
    "wof:placetype": "venue"
  },
  "geometry": {"coordinates":[-83.856072,39.445106],"type":"Point"}
}
