{
  "type": "Feature",
  "properties": {
    "iso:country":"US",
    "sg:address":"1700 W Main St",
    "sg:city":"Wilmington",
    "sg:classifiers":[
        {
            "category":"Home & Garden",
            "subcategory":"Carpets & Floor Coverings",
            "type":"Retail Goods"
        }
    ],
    "sg:phone":"+1 937 382 1615",
    "sg:postcode":"45177",
    "sg:province":"OH",
    "wof:name":"Superior Carpet",
    "wof:placetype":"venue"
},
  "geometry": {"coordinates":[-83.856072,39.445106],"type":"Point"}
}