{
  "type": "Feature",
  "properties": {
    "addr:full": "75 E Main St Newark OH 43055",
    "addr:housenumber": "75",
    "addr:postcode": "43055",
    "addr:street": "E Main St",
    "iso:country": "US",
    "sg:address": "75 E Main St",
    "sg:city": "Newark",
    "sg:classifiers": [
      {
        "category": "Government",
        "subcategory": "Office",
        "type": "Public Place"
      }
    ],
    "sg:phone": "+1 740 670 5400",
    "sg:postcode": "43055",
    "sg:province": "OH",
    "wof:name": "Honorable Russell Steiner",
    "wof:placetype": "venue"
  },
  "geometry": {"coordinates":[-82.399042,40.058654],"type":"Point"}
}
