{
  "type": "Feature",
  "properties": {
    "addr:full": "4904 W Broad St Columbus OH 43228",
    "addr:housenumber": "4904",
    "addr:postcode": "43228",
    "addr:street": "W Broad St",
    "iso:country": "US",
    "sg:address": "4904 W Broad St",
    "sg:city": "Columbus",
    "sg:classifiers": [
      {
        "category": "Cinema",
        "subcategory": "Movie Rental",
        "type": "Entertainment"
      }
    ],
    "sg:phone": "+1 614 853 0708",
    "sg:postcode": "43228",
    "sg:province": "OH",
    "sg:tags": [
      "leasing",
      "video",
      "disc",
      "tape"
    ],
    "sg:website": "www.hollywoodvideo.com",
    "wof:name": "Hollywood Video",
    "wof:placetype": "venue"
  },
  "geometry": {"coordinates":[-83.129796,39.952286],"type":"Point"}
}
