{
  "type": "Feature",
  "properties": {
    "addr:full":"2500 Shawnee Rd Lima OH 45806",
    "addr:housenumber":"2500",
    "addr:postcode":"45806",
    "addr:street":"Shawnee Rd",
    "iso:country":"US",
    "sg:address":"2500 Shawnee Rd",
    "sg:city":"Lima",
    "sg:classifiers":[
        {
            "category":"Professional",
            "subcategory":"Engineering",
            "type":"Services"
        }
    ],
    "sg:phone":"+1 419 999 4705",
    "sg:postcode":"45806",
    "sg:province":"OH",
    "sg:tags":[
        "engineer"
    ],
    "sg:website":"www.idcengr.com",
    "wof:name":"Idc Engineering Inc",
    "wof:placetype":"venue"
},
  "geometry": {"coordinates":[-84.151494,40.702111],"type":"Point"}
}