{
  "type": "Feature",
  "properties": {
    "addr:full": "822 Rhodes Ave Akron OH 44307",
    "addr:housenumber": "822",
    "addr:postcode": "44307",
    "addr:street": "Rhodes Ave",
    "iso:country": "US",
    "sg:address": "822 Rhodes Ave",
    "sg:city": "Akron",
    "sg:classifiers": [
      {
        "category": "Bars \u0026 Pubs",
        "type": "Food \u0026 Drink"
      }
    ],
    "sg:phone": "+1 330 535 3438",
    "sg:postcode": "44307",
    "sg:province": "OH",
    "wof:name": "New Kupata West",
    "wof:placetype": "venue"
  },
  "geometry": {"coordinates":[-81.538361,41.073187],"type":"Point"}
}
