{
  "type": "Feature",
  "properties": {
    "addr:full":"138 Hinderer Ave SW Massillon OH 44646",
    "addr:housenumber":"138",
    "addr:postcode":"44646",
    "addr:street":"Hinderer Ave Sw",
    "iso:country":"US",
    "sg:address":"138 Hinderer Ave SW",
    "sg:city":"Massillon",
    "sg:classifiers":[
        {
            "category":"Professional",
            "type":"Services"
        }
    ],
    "sg:phone":"+1 330 833 4360",
    "sg:postcode":"44646",
    "sg:province":"OH",
    "wof:name":"Peggy Marie McDonald",
    "wof:placetype":"venue"
},
  "geometry": {"coordinates":[-81.470315,40.791048],"type":"Point"}
}