{
  "type": "Feature",
  "properties": {
    "addr:full": "6333 Post Rd Dublin OH 43017",
    "addr:housenumber": "6333",
    "addr:postcode": "43017",
    "addr:street": "Post Rd",
    "iso:country": "US",
    "sg:address": "6333 Post Rd",
    "sg:city": "Dublin",
    "sg:classifiers": [
      {
        "category": "Building \u0026 Trades",
        "subcategory": "Construction",
        "type": "Services"
      }
    ],
    "sg:phone": "+1 614 766 4304",
    "sg:postcode": "43017",
    "sg:province": "OH",
    "sg:tags": [
      "house",
      "builder",
      "home"
    ],
    "wof:name": "Arlington Builders Inc",
    "wof:placetype": "venue"
  },
  "geometry": {"coordinates":[-83.158399,40.106841],"type":"Point"}
}
