{
  "type": "Feature",
  "properties": {
    "addr:full":"54 Alpha Park Cleveland OH 44143",
    "addr:housenumber":"54",
    "addr:postcode":"44143",
    "addr:street":"Alpha",
    "iso:country":"US",
    "sg:address":"54 Alpha Park",
    "sg:city":"Cleveland",
    "sg:classifiers":[
        {
            "category":"Building & Trades",
            "subcategory":"Plumbing",
            "type":"Services"
        }
    ],
    "sg:phone":"+1 440 473 1012",
    "sg:postcode":"44143",
    "sg:province":"OH",
    "sg:tags":[
        "air",
        "heating",
        "contractor",
        "system",
        "conditioning"
    ],
    "wof:name":"Alpha Drive Heating & AC CORP",
    "wof:placetype":"venue"
},
  "geometry": {"coordinates":[-81.45137699999999,41.553291],"type":"Point"}
}