{
  "type": "Feature",
  "properties": {
    "iso:country":"US",
    "sg:address":"2829 River Rd",
    "sg:city":"Willoughby",
    "sg:classifiers":[
        {
            "category":"Autos & Motor Vehicles",
            "subcategory":"Fuel & Gas Station",
            "type":"Retail Goods"
        }
    ],
    "sg:phone":"+1 440 946 5040",
    "sg:postcode":"44094",
    "sg:province":"OH",
    "sg:tags":[
        "station",
        "gasoline"
    ],
    "wof:name":"Shell",
    "wof:placetype":"venue"
},
  "geometry": {"coordinates":[-81.417027,41.58904],"type":"Point"}
}