{
  "type": "Feature",
  "properties": {
    "iso:country":"US",
    "sg:address":"55 Whittlesey Ave",
    "sg:city":"Norwalk",
    "sg:classifiers":[
        {
            "category":"Social Services",
            "type":"Services"
        }
    ],
    "sg:phone":"+1 419 668 4090",
    "sg:postcode":"44857",
    "sg:province":"OH",
    "sg:tags":[
        "organization",
        "welfare"
    ],
    "wof:name":"Salvation Army",
    "wof:placetype":"venue"
},
  "geometry": {"coordinates":[-82.61701600000001,41.243945],"type":"Point"}
}