{
  "type": "Feature",
  "properties": {
    "addr:full": "55 Whittlesey Ave Norwalk OH 44857",
    "addr:housenumber": "55",
    "addr:postcode": "44857",
    "addr:street": "Whittlesey Ave",
    "iso:country": "US",
    "sg:address": "55 Whittlesey Ave",
    "sg:city": "Norwalk",
    "sg:classifiers": [
      {
        "category": "Social Services",
        "type": "Services"
      }
    ],
    "sg:phone": "+1 419 668 4090",
    "sg:postcode": "44857",
    "sg:province": "OH",
    "sg:tags": [
      "organization",
      "welfare"
    ],
    "wof:name": "Salvation Army",
    "wof:placetype": "venue"
  },
  "geometry": {"coordinates":[-82.617016,41.243945],"type":"Point"}
}
