{
  "type": "Feature",
  "properties": {
    "addr:full": "2553 State Rte 222 New Richmond OH 45157",
    "addr:housenumber": "2553",
    "addr:postcode": "45157",
    "addr:street": "State Rte 222",
    "iso:country": "US",
    "sg:address": "2553 State Rte 222",
    "sg:city": "New Richmond",
    "sg:classifiers": [
      {
        "category": "Retail",
        "subcategory": "Repair Shop",
        "type": "Services"
      }
    ],
    "sg:phone": "+1 513 734 3274",
    "sg:postcode": "45157",
    "sg:province": "OH",
    "sg:tags": [
      "upholsterer"
    ],
    "wof:name": "Brashear Upholstery",
    "wof:placetype": "venue"
  },
  "geometry": {"coordinates":[-84.169773,38.956307],"type":"Point"}
}
