{
  "type": "Feature",
  "properties": {
    "iso:country":"US",
    "sg:address":"2553 State Rte 222",
    "sg:city":"New Richmond",
    "sg:classifiers":[
        {
            "category":"Retail",
            "subcategory":"Repair Shop",
            "type":"Services"
        }
    ],
    "sg:phone":"+1 513 734 3274",
    "sg:postcode":"45157",
    "sg:province":"OH",
    "sg:tags":[
        "upholsterer"
    ],
    "wof:name":"Brashear Upholstery",
    "wof:placetype":"venue"
},
  "geometry": {"coordinates":[-84.16977300000001,38.956307],"type":"Point"}
}