{
  "type": "Feature",
  "properties": {
    "addr:full":"21360 Center Ridge Rd Cleveland OH 44116",
    "addr:housenumber":"21360",
    "addr:postcode":"44116",
    "addr:street":"Center Ridge Rd",
    "iso:country":"US",
    "sg:address":"21360 Center Ridge Rd",
    "sg:city":"Cleveland",
    "sg:classifiers":[
        {
            "category":"Professional",
            "subcategory":"Lawyer & Legal Services",
            "type":"Services"
        }
    ],
    "sg:phone":"+1 440 895 9885",
    "sg:postcode":"44116",
    "sg:province":"OH",
    "sg:tags":[
        "attorney"
    ],
    "wof:name":"Patrick R Nixon",
    "wof:placetype":"venue"
},
  "geometry": {"coordinates":[-81.856421,41.460803],"type":"Point"}
}