{
  "type": "Feature",
  "properties": {
    "iso:country":"US",
    "sg:address":"275 Loveman Ave",
    "sg:city":"Worthington",
    "sg:classifiers":[
        {
            "category":"Wholesale",
            "subcategory":"Poultry",
            "type":"Manufacturing & Wholesale Goods"
        }
    ],
    "sg:phone":"+1 614 436 4122",
    "sg:postcode":"43085",
    "sg:province":"OH",
    "wof:name":"Mill Creek Pheasants",
    "wof:placetype":"venue"
},
  "geometry": {"coordinates":[-83.010525,40.079468],"type":"Point"}
}