{
  "type": "Feature",
  "properties": {
    "addr:full": "275 Loveman Ave Worthington OH 43085",
    "addr:housenumber": "275",
    "addr:postcode": "43085",
    "addr:street": "Loveman Ave",
    "iso:country": "US",
    "sg:address": "275 Loveman Ave",
    "sg:city": "Worthington",
    "sg:classifiers": [
      {
        "category": "Wholesale",
        "subcategory": "Poultry",
        "type": "Manufacturing \u0026 Wholesale Goods"
      }
    ],
    "sg:phone": "+1 614 436 4122",
    "sg:postcode": "43085",
    "sg:province": "OH",
    "wof:name": "Mill Creek Pheasants",
    "wof:placetype": "venue"
  },
  "geometry": {"coordinates":[-83.010525,40.079468],"type":"Point"}
}
