{
  "type": "Feature",
  "properties": {
    "addr:full":"4092 Bantas Creek Rd West Alexandria OH 45381",
    "addr:housenumber":"4092",
    "addr:postcode":"45381",
    "addr:street":"Bantas Creek Rd",
    "iso:country":"US",
    "sg:address":"4092 Bantas Creek Rd",
    "sg:city":"West Alexandria",
    "sg:classifiers":[
        {
            "category":"Professional",
            "type":"Services"
        }
    ],
    "sg:phone":"+1 937 839 4985",
    "sg:postcode":"45381",
    "sg:province":"OH",
    "wof:name":"Elden Grimme",
    "wof:placetype":"venue"
},
  "geometry": {"coordinates":[-84.552139,39.768507],"type":"Point"}
}