{
  "type": "Feature",
  "properties": {
    "iso:country":"US",
    "sg:address":"11272 Jug St",
    "sg:city":"Johnstown",
    "sg:classifiers":[
        {
            "category":"Personal",
            "subcategory":"Beauty Salon",
            "type":"Services"
        }
    ],
    "sg:phone":"+1 740 625 6440",
    "sg:postcode":"43031",
    "sg:province":"OH",
    "wof:name":"Connie's Beautyrama",
    "wof:placetype":"venue"
},
  "geometry": {"coordinates":[-82.69958200000001,40.097898],"type":"Point"}
}