{
  "type": "Feature",
  "properties": {
    "iso:country":"US",
    "sg:address":"9357 Twp Hwy 48",
    "sg:city":"Galion",
    "sg:classifiers":[
        {
            "category":"Manufacturing",
            "subcategory":"Retail Goods",
            "type":"Manufacturing & Wholesale Goods"
        }
    ],
    "sg:phone":"+1 419 468 8516",
    "sg:postcode":"44833",
    "sg:province":"OH",
    "sg:tags":[
        "manufacturer"
    ],
    "wof:name":"Dink Mar Inc",
    "wof:placetype":"venue"
},
  "geometry": {"coordinates":[-82.731909,40.694567],"type":"Point"}
}