{
  "type": "Feature",
  "properties": {
    "iso:country":"US",
    "sg:address":"768 Sandy Lake Rd",
    "sg:city":"Kent",
    "sg:classifiers":[
        {
            "category":"Retail",
            "subcategory":"Portrait Studio",
            "type":"Services"
        }
    ],
    "sg:phone":"+1 330 673 0774",
    "sg:postcode":"44240",
    "sg:province":"OH",
    "sg:tags":[
        "photographer"
    ],
    "sg:website":"www.pamfilie.com",
    "wof:name":"Pamfilie Photography",
    "wof:placetype":"venue"
},
  "geometry": {"coordinates":[-81.312834,41.092799],"type":"Point"}
}