{
  "type": "Feature",
  "properties": {
    "addr:full": "321 Crystal Ave Findlay OH 45840",
    "addr:housenumber": "321",
    "addr:postcode": "45840",
    "addr:street": "Crystal Ave",
    "iso:country": "US",
    "sg:address": "321 Crystal Ave",
    "sg:city": "Findlay",
    "sg:classifiers": [
      {
        "category": "Wholesale",
        "subcategory": "Durable Goods \u0026 Equipment",
        "type": "Manufacturing \u0026 Wholesale Goods"
      }
    ],
    "sg:phone": "+1 419 424 0647",
    "sg:postcode": "45840",
    "sg:province": "OH",
    "wof:name": "Kemco Tan Supply",
    "wof:placetype": "venue"
  },
  "geometry": {"coordinates":[-83.643333,41.051065],"type":"Point"}
}
