{
  "type": "Feature",
  "properties": {
    "iso:country":"US",
    "sg:address":"321 Crystal Ave",
    "sg:city":"Findlay",
    "sg:classifiers":[
        {
            "category":"Wholesale",
            "subcategory":"Durable Goods & Equipment",
            "type":"Manufacturing & Wholesale Goods"
        }
    ],
    "sg:phone":"+1 419 424 0647",
    "sg:postcode":"45840",
    "sg:province":"OH",
    "wof:name":"Kemco Tan Supply",
    "wof:placetype":"venue"
},
  "geometry": {"coordinates":[-83.643333,41.051065],"type":"Point"}
}