{
  "type": "Feature",
  "properties": {
    "iso:country":"US",
    "sg:address":"26675 Eckel Rd",
    "sg:city":"Perrysburg",
    "sg:classifiers":[
        {
            "category":"Freight",
            "type":"Transportation"
        }
    ],
    "sg:phone":"+1 419 874 5986",
    "sg:postcode":"43551",
    "sg:province":"OH",
    "sg:tags":[
        "delivery"
    ],
    "wof:name":"ZELLER Trucking",
    "wof:placetype":"venue"
},
  "geometry": {"coordinates":[-83.641093,41.539562],"type":"Point"}
}