{
  "type": "Feature",
  "properties": {
    "addr:full": "8406 Cox Rd Windsor OH 44099",
    "addr:housenumber": "8406",
    "addr:postcode": "44099",
    "addr:street": "Cox Rd",
    "iso:country": "US",
    "sg:address": "8406 Cox Rd",
    "sg:city": "Windsor",
    "sg:classifiers": [
      {
        "category": "Building \u0026 Trades",
        "subcategory": "Electrical",
        "type": "Services"
      }
    ],
    "sg:phone": "+1 440 272 5772",
    "sg:postcode": "44099",
    "sg:province": "OH",
    "sg:tags": [
      "electric",
      "contractor"
    ],
    "wof:name": "NAI Electric",
    "wof:placetype": "venue"
  },
  "geometry": {"coordinates":[-80.982357,41.520263],"type":"Point"}
}
