{
  "type": "Feature",
  "properties": {
    "iso:country":"US",
    "sg:address":"1658 E US Hwy 36",
    "sg:city":"Urbana",
    "sg:classifiers":[
        {
            "category":"Organizations",
            "subcategory":"Religious Organization",
            "type":"Services"
        }
    ],
    "sg:phone":"+1 937 652 1196",
    "sg:postcode":"43078",
    "sg:province":"OH",
    "sg:tags":[
        "church"
    ],
    "wof:name":"Free Will Baptist Church",
    "wof:placetype":"venue"
},
  "geometry": {"coordinates":[-83.71866300000001,40.106066],"type":"Point"}
}