{
  "type": "Feature",
  "properties": {
    "addr:full": "1658 E US Hwy 36 Urbana OH 43078",
    "addr:housenumber": "1658",
    "addr:postcode": "43078",
    "addr:street": "E Us Hwy 36",
    "iso:country": "US",
    "sg:address": "1658 E US Hwy 36",
    "sg:city": "Urbana",
    "sg:classifiers": [
      {
        "category": "Organizations",
        "subcategory": "Religious Organization",
        "type": "Services"
      }
    ],
    "sg:phone": "+1 937 652 1196",
    "sg:postcode": "43078",
    "sg:province": "OH",
    "sg:tags": [
      "church"
    ],
    "wof:name": "Free Will Baptist Church",
    "wof:placetype": "venue"
  },
  "geometry": {"coordinates":[-83.718663,40.106066],"type":"Point"}
}
