{
  "type": "Feature",
  "properties": {
    "iso:country":"US",
    "sg:address":"2387 Locust St S",
    "sg:city":"Canal Fulton",
    "sg:classifiers":[
        {
            "category":"Home & Garden",
            "subcategory":"Building Materials",
            "type":"Retail Goods"
        }
    ],
    "sg:phone":"+1 330 854 2517",
    "sg:postcode":"44614",
    "sg:province":"OH",
    "sg:tags":[
        "glass",
        "window",
        "plate"
    ],
    "wof:name":"Accent Mirror & Shower Door",
    "wof:placetype":"venue"
},
  "geometry": {"coordinates":[-81.569373,40.882188],"type":"Point"}
}