{
  "type": "Feature",
  "properties": {
    "addr:full": "2605 Deborah Dr Cleveland OH 44122",
    "addr:housenumber": "2605",
    "addr:postcode": "44122",
    "addr:street": "Deborah Dr",
    "iso:country": "US",
    "sg:address": "2605 Deborah Dr",
    "sg:city": "Cleveland",
    "sg:classifiers": [
      {
        "category": "Wholesale",
        "subcategory": "Machinery \u0026 Supplies",
        "type": "Manufacturing \u0026 Wholesale Goods"
      }
    ],
    "sg:phone": "+1 216 831 2515",
    "sg:postcode": "44122",
    "sg:province": "OH",
    "sg:tags": [
      "equipment",
      "industrial"
    ],
    "wof:name": "S B Reese Inc",
    "wof:placetype": "venue"
  },
  "geometry": {"coordinates":[-81.508011,41.487704],"type":"Point"}
}
