{
  "type": "Feature",
  "properties": {
    "addr:full":"1020 Hospital Dr Batavia OH 45103",
    "addr:housenumber":"1020",
    "addr:postcode":"45103",
    "addr:street":"Hospital Dr",
    "iso:country":"US",
    "sg:address":"1020 Hospital Dr",
    "sg:city":"Batavia",
    "sg:classifiers":[
        {
            "category":"Retail",
            "subcategory":"Car Wash",
            "type":"Services"
        }
    ],
    "sg:phone":"+1 513 732 1888",
    "sg:postcode":"45103",
    "sg:province":"OH",
    "sg:tags":[
        "polishing",
        "washing"
    ],
    "wof:name":"Batavia Carwash",
    "wof:placetype":"venue"
},
  "geometry": {"coordinates":[-84.14649300000001,39.080045],"type":"Point"}
}