{
  "type": "Feature",
  "properties": {
    "addr:full": "2025 Worth Ave Cincinnati OH 45212",
    "addr:housenumber": "2025",
    "addr:postcode": "45212",
    "addr:street": "Worth Ave",
    "iso:country": "US",
    "sg:address": "2025 Worth Ave",
    "sg:city": "Cincinnati",
    "sg:classifiers": [
      {
        "category": "Personal",
        "subcategory": "Beauty Salon",
        "type": "Services"
      }
    ],
    "sg:phone": "+1 513 631 1760",
    "sg:postcode": "45212",
    "sg:province": "OH",
    "wof:name": "Linda's Beauty Salon",
    "wof:placetype": "venue"
  },
  "geometry": {"coordinates":[-84.457793,39.173726],"type":"Point"}
}
