{
  "type": "Feature",
  "properties": {
    "iso:country":"US",
    "sg:address":"3349 Executive Pkwy",
    "sg:city":"Toledo",
    "sg:classifiers":[
        {
            "category":"Health Services",
            "subcategory":"Dentist",
            "type":"Services"
        }
    ],
    "sg:phone":"+1 419 537 9352",
    "sg:postcode":"43606",
    "sg:province":"OH",
    "sg:tags":[
        "dentists-cosmetic",
        "denture",
        "dentists-prosthodontists",
        "dentistry",
        "implant",
        "dentists-implantology"
    ],
    "sg:website":"http://www.westgatedentalarts.com",
    "wof:name":"Westgate Dental",
    "wof:placetype":"venue"
},
  "geometry": {"coordinates":[-83.628798,41.681865],"type":"Point"}
}