{
  "type": "Feature",
  "properties": {
    "iso:country":"US",
    "sg:address":"1026 S Union St",
    "sg:city":"Bryan",
    "sg:classifiers":[
        {
            "category":"Building & Trades",
            "subcategory":"Construction",
            "type":"Services"
        }
    ],
    "sg:phone":"+1 419 636 7981",
    "sg:postcode":"43506",
    "sg:province":"OH",
    "sg:tags":[
        "contractor"
    ],
    "wof:name":"Diversified Blasthole Drilling",
    "wof:placetype":"venue"
},
  "geometry": {"coordinates":[-84.536328,41.463239],"type":"Point"}
}