{
  "type": "Feature",
  "properties": {
    "iso:country":"US",
    "sg:address":"223 W Market St",
    "sg:city":"Washington Ct Hs",
    "sg:classifiers":[
        {
            "category":"Retail",
            "subcategory":"Funeral Services",
            "type":"Services"
        }
    ],
    "sg:phone":"+1 740 335 6078",
    "sg:postcode":"43160",
    "sg:province":"OH",
    "sg:tags":[
        "director"
    ],
    "wof:name":"Summers Funeral Home",
    "wof:placetype":"venue"
},
  "geometry": {"coordinates":[-83.442819,39.535284],"type":"Point"}
}