{
  "type": "Feature",
  "properties": {
    "addr:full": "223 W Market St Washington Ct Hs OH 43160",
    "addr:housenumber": "223",
    "addr:postcode": "43160",
    "addr:street": "W Market St",
    "iso:country": "US",
    "sg:address": "223 W Market St",
    "sg:city": "Washington Ct Hs",
    "sg:classifiers": [
      {
        "category": "Retail",
        "subcategory": "Funeral Services",
        "type": "Services"
      }
    ],
    "sg:phone": "+1 740 335 6078",
    "sg:postcode": "43160",
    "sg:province": "OH",
    "sg:tags": [
      "director"
    ],
    "wof:name": "Summers Funeral Home",
    "wof:placetype": "venue"
  },
  "geometry": {"coordinates":[-83.442819,39.535284],"type":"Point"}
}
