{
  "type": "Feature",
  "properties": {
    "addr:full":"3950 Shrine Rd Springfield OH 45502",
    "addr:postcode":"3950;45502",
    "addr:street":"Shrine Rd",
    "iso:country":"US",
    "sg:address":"3950 Shrine Rd",
    "sg:city":"Springfield",
    "sg:classifiers":[
        {
            "category":"Building & Trades",
            "subcategory":"Construction",
            "type":"Services"
        }
    ],
    "sg:phone":"+1 937 964 8948",
    "sg:postcode":"45502",
    "sg:province":"OH",
    "sg:tags":[
        "roofing",
        "contractor"
    ],
    "wof:name":"Fent's Roofing",
    "wof:placetype":"venue"
},
  "geometry": {"coordinates":[-83.910431,39.975656],"type":"Point"}
}