{
  "type": "Feature",
  "properties": {
    "iso:country":"US",
    "sg:address":"1833 Canton Ave NW",
    "sg:city":"North Canton",
    "sg:classifiers":[
        {
            "category":"Building & Trades",
            "subcategory":"Construction",
            "type":"Services"
        }
    ],
    "sg:phone":"+1 330 499 6888",
    "sg:postcode":"44708",
    "sg:province":"OH",
    "sg:tags":[
        "product",
        "asphalt"
    ],
    "wof:name":"Canton Asphalt Co",
    "wof:placetype":"venue"
},
  "geometry": {"coordinates":[-81.453931,40.819262],"type":"Point"}
}