{
  "type": "Feature",
  "properties": {
    "addr:full":"315 Gougler Ave Kent OH 44240",
    "addr:housenumber":"315",
    "addr:postcode":"44240",
    "addr:street":"Gougler Ave",
    "iso:country":"US",
    "sg:address":"315 Gougler Ave",
    "sg:city":"Kent",
    "sg:classifiers":[
        {
            "category":"Manufacturing",
            "subcategory":"Furniture",
            "type":"Manufacturing & Wholesale Goods"
        }
    ],
    "sg:phone":"+1 330 677 1123",
    "sg:postcode":"44240",
    "sg:province":"OH",
    "sg:tags":[
        "mechanics",
        "creeper",
        "mfg"
    ],
    "wof:name":"Pegasus Products Company Inc",
    "wof:placetype":"venue"
},
  "geometry": {"coordinates":[-81.359919,41.156736],"type":"Point"}
}