{
  "type": "Feature",
  "properties": {
    "addr:full": "8398 Reading Rd Cincinnati OH 45237",
    "addr:housenumber": "8398",
    "addr:postcode": "45237",
    "addr:street": "Reading Rd",
    "iso:country": "US",
    "sg:address": "8398 Reading Rd",
    "sg:city": "Cincinnati",
    "sg:classifiers": [
      {
        "category": "Restaurant",
        "type": "Food \u0026 Drink"
      }
    ],
    "sg:phone": "+1 513 821 5464",
    "sg:postcode": "45237",
    "sg:province": "OH",
    "sg:tags": [
      "eating"
    ],
    "wof:name": "Burger King",
    "wof:placetype": "venue"
  },
  "geometry": {"coordinates":[-84.44811,39.21081],"type":"Point"}
}
