{
  "type": "Feature",
  "properties": {
    "iso:country":"US",
    "sg:address":"8398 Reading Rd",
    "sg:city":"Cincinnati",
    "sg:classifiers":[
        {
            "category":"Restaurant",
            "type":"Food & Drink"
        }
    ],
    "sg:phone":"+1 513 821 5464",
    "sg:postcode":"45237",
    "sg:province":"OH",
    "sg:tags":[
        "eating"
    ],
    "wof:name":"Burger King",
    "wof:placetype":"venue"
},
  "geometry": {"coordinates":[-84.44811,39.21081],"type":"Point"}
}