{
  "type": "Feature",
  "properties": {
    "addr:full": "158 W Johnstown Rd Columbus OH 43230",
    "addr:housenumber": "158",
    "addr:postcode": "43230",
    "addr:street": "W Johnstown Rd",
    "iso:country": "US",
    "sg:address": "158 W Johnstown Rd",
    "sg:city": "Columbus",
    "sg:classifiers": [
      {
        "category": "Professional",
        "subcategory": "Art Services",
        "type": "Services"
      }
    ],
    "sg:phone": "+1 614 337 6295",
    "sg:postcode": "43230",
    "sg:province": "OH",
    "sg:tags": [
      "graphic",
      "designer"
    ],
    "wof:name": "New City Graphics",
    "wof:placetype": "venue"
  },
  "geometry": {"coordinates":[-82.882837,40.018245],"type":"Point"}
}
