{
  "type": "Feature",
  "properties": {
    "iso:country":"US",
    "sg:address":"310 Robin Rd",
    "sg:city":"Waverly",
    "sg:classifiers":[
        {
            "category":"Banks & Credit Unions",
            "subcategory":"Investment Brokerage",
            "type":"Services"
        }
    ],
    "sg:phone":"+1 440 338 1371",
    "sg:postcode":"45690",
    "sg:province":"OH",
    "sg:tags":[
        "advisory"
    ],
    "wof:name":"Golnik Enterprises",
    "wof:placetype":"venue"
},
  "geometry": {"coordinates":[-82.966965,39.132948],"type":"Point"}
}