{
  "type": "Feature",
  "properties": {
    "addr:full": "6767 Gracely Dr Cincinnati OH 45233",
    "addr:housenumber": "6767",
    "addr:postcode": "45233",
    "addr:street": "Gracely Dr",
    "iso:country": "US",
    "sg:address": "6767 Gracely Dr",
    "sg:city": "Cincinnati",
    "sg:classifiers": [
      {
        "category": "Bars \u0026 Pubs",
        "type": "Food \u0026 Drink"
      }
    ],
    "sg:phone": "+1 513 381 3114",
    "sg:postcode": "45233",
    "sg:province": "OH",
    "sg:tags": [
      "drinking",
      "eating"
    ],
    "wof:name": "Ogden Place",
    "wof:placetype": "venue"
  },
  "geometry": {"coordinates":[-84.695354,39.115767],"type":"Point"}
}
