{
  "type": "Feature",
  "properties": {
    "iso:country":"US",
    "sg:address":"5548 Poling Rd",
    "sg:city":"Lima",
    "sg:classifiers":[
        {
            "category":"Building & Trades",
            "subcategory":"Construction",
            "type":"Services"
        }
    ],
    "sg:phone":"+1 419 339 2354",
    "sg:postcode":"45807",
    "sg:province":"OH",
    "sg:tags":[
        "contractor"
    ],
    "wof:name":"Meyer Trim Rite",
    "wof:placetype":"venue"
},
  "geometry": {"coordinates":[-84.205399,40.757749],"type":"Point"}
}