{
  "type": "Feature",
  "properties": {
    "addr:full": "601 Sunbury Rd Delaware OH 43015",
    "addr:housenumber": "601",
    "addr:postcode": "43015",
    "addr:street": "Sunbury Rd",
    "iso:country": "US",
    "sg:address": "601 Sunbury Rd",
    "sg:city": "Delaware",
    "sg:classifiers": [
      {
        "category": "Insurance",
        "subcategory": "Insurance Agent",
        "type": "Services"
      }
    ],
    "sg:phone": "+1 740 362 5500",
    "sg:postcode": "43015",
    "sg:province": "OH",
    "wof:name": "Jessica Forman Agency",
    "wof:placetype": "venue"
  },
  "geometry": {"coordinates":[-83.04319,40.296826],"type":"Point"}
}
