{
  "type": "Feature",
  "properties": {
    "addr:full":"10049 Cherry Fork Rd Winchester OH 45697",
    "addr:housenumber":"10049",
    "addr:postcode":"45697",
    "addr:street":"Cherry Fork Rd",
    "iso:country":"US",
    "sg:address":"10049 Cherry Fork Rd",
    "sg:city":"Winchester",
    "sg:classifiers":[
        {
            "category":"Professional",
            "type":"Services"
        }
    ],
    "sg:phone":"+1 937 377 4420",
    "sg:postcode":"45697",
    "sg:province":"OH",
    "wof:name":"Jeffrey W Ratliff",
    "wof:placetype":"venue"
},
  "geometry": {"coordinates":[-83.70260500000001,38.88006],"type":"Point"}
}