{
  "type": "Feature",
  "properties": {
    "addr:full": "11114 Chardon Rd Chardon OH 44024",
    "addr:housenumber": "11114",
    "addr:postcode": "44024",
    "addr:street": "Chardon Rd",
    "iso:country": "US",
    "sg:address": "11114 Chardon Rd",
    "sg:city": "Chardon",
    "sg:classifiers": [
      {
        "category": "Wholesale",
        "subcategory": "Groceries",
        "type": "Manufacturing \u0026 Wholesale Goods"
      }
    ],
    "sg:phone": "+1 440 286 5121",
    "sg:postcode": "44024",
    "sg:province": "OH",
    "sg:tags": [
      "beverage"
    ],
    "wof:name": "Little Eagle Drive Thru Bvrg",
    "wof:placetype": "venue"
  },
  "geometry": {"coordinates":[-81.233694,41.580699],"type":"Point"}
}
