{
  "type": "Feature",
  "properties": {
    "addr:full": "2206 Eastern Ave Gallipolis OH 45631",
    "addr:housenumber": "2206",
    "addr:postcode": "45631",
    "addr:street": "Eastern Ave",
    "iso:country": "US",
    "sg:address": "2206 Eastern Ave",
    "sg:city": "Gallipolis",
    "sg:classifiers": [
      {
        "category": "Restaurant",
        "type": "Food \u0026 Drink"
      }
    ],
    "sg:menulink": "http://www.allmenus.com/oh/gallipolis/211479-kfc---kentucky-fried-chicken/menu/",
    "sg:phone": "+1 740 446 1483",
    "sg:postcode": "45631",
    "sg:province": "OH",
    "sg:tags": [
      "american",
      "chicken"
    ],
    "wof:name": "KFC - Kentucky Fried Chicken",
    "wof:placetype": "venue"
  },
  "geometry": {"coordinates":[-82.172341,38.823769],"type":"Point"}
}
