{
  "type": "Feature",
  "properties": {
    "addr:full": "321 W State St Fremont OH 43420",
    "addr:housenumber": "321",
    "addr:postcode": "43420",
    "addr:street": "W State St",
    "iso:country": "US",
    "sg:address": "321 W State St",
    "sg:city": "Fremont",
    "sg:classifiers": [
      {
        "category": "Banks \u0026 Credit Unions",
        "subcategory": "Bank",
        "type": "Services"
      }
    ],
    "sg:phone": "+1 419 334 7188",
    "sg:postcode": "43420",
    "sg:province": "OH",
    "sg:tags": [
      "savings",
      "state",
      "loan",
      "institution"
    ],
    "wof:name": "Home Savings \u0026 Loan Company",
    "wof:placetype": "venue"
  },
  "geometry": {"coordinates":[-83.114219,41.347451],"type":"Point"}
}
