{
  "type": "Feature",
  "properties": {
    "addr:full":"1163 N Court St Medina OH 44256",
    "addr:housenumber":"1163",
    "addr:postcode":"44256",
    "addr:street":"N Court St",
    "iso:country":"US",
    "sg:address":"1163 N Court St",
    "sg:city":"Medina",
    "sg:classifiers":[
        {
            "category":"Shopping",
            "subcategory":"Clothing, Apparel, & Fashions",
            "type":"Retail Goods"
        }
    ],
    "sg:phone":"+1 330 725 0224",
    "sg:postcode":"44256",
    "sg:province":"OH",
    "wof:name":"Dress Barn",
    "wof:placetype":"venue"
},
  "geometry": {"coordinates":[-81.863069,41.152477],"type":"Point"}
}