{
  "type": "Feature",
  "properties": {
    "iso:country":"US",
    "sg:address":"115 Newark Rd",
    "sg:city":"Mt Vernon",
    "sg:classifiers":[
        {
            "category":"Restaurant",
            "type":"Food & Drink"
        }
    ],
    "sg:phone":"+1 740 392 3477",
    "sg:postcode":"43050",
    "sg:province":"OH",
    "wof:name":"Ice Cream Station",
    "wof:placetype":"venue"
},
  "geometry": {"coordinates":[-82.485478,40.384598],"type":"Point"}
}