{
  "type": "Feature",
  "properties": {
    "addr:full": "1020 Holders Ln Zanesville OH 43701",
    "addr:housenumber": "1020",
    "addr:postcode": "43701",
    "addr:street": "Holders Ln",
    "iso:country": "US",
    "sg:address": "1020 Holders Ln",
    "sg:city": "Zanesville",
    "sg:classifiers": [
      {
        "category": "Building \u0026 Trades",
        "subcategory": "Construction",
        "type": "Services"
      }
    ],
    "sg:phone": "+1 740 872 3938",
    "sg:postcode": "43701",
    "sg:province": "OH",
    "sg:tags": [
      "masonry",
      "contractor"
    ],
    "wof:name": "Simply Stone Masonry",
    "wof:placetype": "venue"
  },
  "geometry": {"coordinates":[-81.967952,39.916935],"type":"Point"}
}
