{
  "type": "Feature",
  "properties": {
    "addr:full": "2115 Leiter Rd Miamisburg OH 45342",
    "addr:housenumber": "2115",
    "addr:postcode": "45342",
    "addr:street": "Leiter Rd",
    "iso:country": "US",
    "sg:address": "2115 Leiter Rd",
    "sg:city": "Miamisburg",
    "sg:classifiers": [
      {
        "category": "Health Services",
        "subcategory": "Doctor",
        "type": "Services"
      }
    ],
    "sg:phone": "+1 937 384 6850",
    "sg:postcode": "45342",
    "sg:province": "OH",
    "sg:tags": [
      "physician",
      "surgeon"
    ],
    "wof:name": "Randy Sansone MD",
    "wof:placetype": "venue"
  },
  "geometry": {"coordinates":[-84.245513,39.63772],"type":"Point"}
}
