{
  "type": "Feature",
  "properties": {
    "addr:full":"4752 Fishburg Rd Dayton OH 45424",
    "addr:housenumber":"4752",
    "addr:postcode":"45424",
    "addr:street":"Fishburg Rd",
    "iso:country":"US",
    "sg:address":"4752 Fishburg Rd",
    "sg:city":"Dayton",
    "sg:classifiers":[
        {
            "category":"Real Estate",
            "subcategory":"Real Estate Agent",
            "type":"Services"
        }
    ],
    "sg:phone":"+1 937 424 5461",
    "sg:postcode":"45424",
    "sg:province":"OH",
    "wof:name":"Ace Realty Of Ohio",
    "wof:placetype":"venue"
},
  "geometry": {"coordinates":[-84.13982799999999,39.840891],"type":"Point"}
}