{
  "type": "Feature",
  "properties": {
    "iso:country":"US",
    "sg:address":"2105 N Wooster Ave",
    "sg:city":"Dover",
    "sg:classifiers":[
        {
            "category":"Restaurant",
            "type":"Food & Drink"
        }
    ],
    "sg:menulink":"http://www.allmenus.com/oh/dover/67466-east-of-chicago-pizza/menu/",
    "sg:phone":"+1 330 602 3278",
    "sg:postcode":"44622",
    "sg:province":"OH",
    "sg:tags":[
        "sandwich",
        "salad",
        "soup",
        "american",
        "wrap",
        "pizza"
    ],
    "wof:name":"East of Chicago Pizza",
    "wof:placetype":"venue"
},
  "geometry": {"coordinates":[-81.489577,40.541259],"type":"Point"}
}