{
  "type": "Feature",
  "properties": {
    "iso:country":"US",
    "sg:address":"41 S High St",
    "sg:city":"Columbus",
    "sg:classifiers":[
        {
            "category":"Professional",
            "subcategory":"Lawyer & Legal Services",
            "type":"Services"
        }
    ],
    "sg:phone":"+1 614 365 2840",
    "sg:postcode":"43215",
    "sg:province":"OH",
    "sg:tags":[
        "attorney"
    ],
    "wof:name":"Philomena M Dane",
    "wof:placetype":"venue"
},
  "geometry": {"coordinates":[-83.00035699999999,39.9604],"type":"Point"}
}