{
  "type": "Feature",
  "properties": {
    "iso:country":"US",
    "sg:address":"2340 Gilbert Ave",
    "sg:city":"Cincinnati",
    "sg:phone":"+1 513 281 5545",
    "sg:postcode":"45206",
    "sg:province":"OH",
    "sg:tags":[
        "oil"
    ],
    "wof:name":"Clark Oil & Refining",
    "wof:placetype":"venue"
},
  "geometry": {"coordinates":[-84.49117,39.12442],"type":"Point"}
}