{
  "type": "Feature",
  "properties": {
    "addr:full":"332 College Ave Fostoria OH 44830",
    "addr:housenumber":"332",
    "addr:postcode":"44830",
    "addr:street":"College Ave",
    "iso:country":"US",
    "sg:address":"332 College Ave",
    "sg:city":"Fostoria",
    "sg:classifiers":[
        {
            "category":"Organizations",
            "subcategory":"Religious Organization",
            "type":"Services"
        }
    ],
    "sg:phone":"+1 419 436 2220",
    "sg:postcode":"44830",
    "sg:province":"OH",
    "sg:tags":[
        "clergy"
    ],
    "wof:name":"Robert Chew",
    "wof:placetype":"venue"
},
  "geometry": {"coordinates":[-83.419842,41.159483],"type":"Point"}
}