{
  "type": "Feature",
  "properties": {
    "addr:full":"1437 Childrens Home Rd Sidney OH 45365",
    "addr:housenumber":"1437",
    "addr:postcode":"45365",
    "addr:street":"Childrens Home Rd",
    "iso:country":"US",
    "sg:address":"1437 Childrens Home Rd",
    "sg:city":"Sidney",
    "sg:classifiers":[
        {
            "category":"Building & Trades",
            "subcategory":"Construction",
            "type":"Services"
        }
    ],
    "sg:phone":"+1 937 492 3860",
    "sg:postcode":"45365",
    "sg:province":"OH",
    "sg:tags":[
        "rental"
    ],
    "wof:name":"Mabes Rentals",
    "wof:placetype":"venue"
},
  "geometry": {"coordinates":[-84.14462,40.261833],"type":"Point"}
}