{
  "type": "Feature",
  "properties": {
    "iso:country":"US",
    "sg:address":"1828 W Henderson Rd",
    "sg:city":"Columbus",
    "sg:classifiers":[
        {
            "category":"Shopping",
            "subcategory":"Department Store",
            "type":"Retail Goods"
        }
    ],
    "sg:phone":"+1 614 457 7670",
    "sg:postcode":"43220",
    "sg:province":"OH",
    "wof:name":"Lazarus-Macys",
    "wof:placetype":"venue"
},
  "geometry": {"coordinates":[-83.07046,40.055287],"type":"Point"}
}