{
  "type": "Feature",
  "properties": {
    "addr:full":"7583 Harrison Ave Cincinnati OH 45247",
    "addr:housenumber":"7583",
    "addr:postcode":"45247",
    "addr:street":"Harrison Ave",
    "iso:country":"US",
    "sg:address":"7583 Harrison Ave",
    "sg:city":"Cincinnati",
    "sg:classifiers":[
        {
            "category":"Retail",
            "subcategory":"Repair Shop",
            "type":"Services"
        }
    ],
    "sg:phone":"+1 513 353 4785",
    "sg:postcode":"45247",
    "sg:province":"OH",
    "sg:tags":[
        "equipment",
        "commercial"
    ],
    "wof:name":"Strack Scale Service Inc",
    "wof:placetype":"venue"
},
  "geometry": {"coordinates":[-84.686663,39.217208],"type":"Point"}
}