{
  "type": "Feature",
  "properties": {
    "addr:full": "5300 Hamilton Ave Cincinnati OH 45224",
    "addr:housenumber": "5300",
    "addr:postcode": "45224",
    "addr:street": "Hamilton Ave",
    "iso:country": "US",
    "sg:address": "5300 Hamilton Ave",
    "sg:city": "Cincinnati",
    "sg:classifiers": [
      {
        "category": "Bars \u0026 Pubs",
        "subcategory": "Champagne Bar",
        "type": "Food \u0026 Drink"
      }
    ],
    "sg:phone": "+1 513 821 0323",
    "sg:postcode": "45224",
    "sg:province": "OH",
    "sg:tags": [
      "coal",
      "coke"
    ],
    "wof:name": "Live Coals Of Fire Ministry",
    "wof:placetype": "venue"
  },
  "geometry": {"coordinates":[-84.544838,39.185762],"type":"Point"}
}
