{
  "type": "Feature",
  "properties": {
    "addr:full":"2785 Som Center Rd Cleveland OH 44022",
    "addr:housenumber":"2785",
    "addr:postcode":"44022",
    "addr:street":"Som Center Rd",
    "iso:country":"US",
    "sg:address":"2785 Som Center Rd",
    "sg:city":"Cleveland",
    "sg:classifiers":[
        {
            "category":"Health Services",
            "subcategory":"Doctor",
            "type":"Services"
        }
    ],
    "sg:phone":"+1 440 944 8887",
    "sg:postcode":"44022",
    "sg:province":"OH",
    "sg:tags":[
        "laboratory",
        "medical"
    ],
    "wof:name":"Eastside Mri",
    "wof:placetype":"venue"
},
  "geometry": {"coordinates":[-81.43825099999999,41.491442],"type":"Point"}
}