{
  "type": "Feature",
  "properties": {
    "addr:full":"16740 Fredericktown Amity Rd Fredericktown OH 43019",
    "addr:postcode":"16740;43019",
    "addr:street":"Amity Rd",
    "iso:country":"US",
    "sg:address":"16740 Fredericktown Amity Rd",
    "sg:city":"Fredericktown",
    "sg:classifiers":[
        {
            "category":"Retail",
            "subcategory":"Animal Services",
            "type":"Services"
        }
    ],
    "sg:phone":"+1 740 694 1885",
    "sg:postcode":"43019",
    "sg:province":"OH",
    "sg:tags":[
        "pet",
        "grooming",
        "washing"
    ],
    "wof:name":"Doggy Day Spa",
    "wof:placetype":"venue"
},
  "geometry": {"coordinates":[-82.44759000000001,40.497802],"type":"Point"}
}