{
  "type": "Feature",
  "properties": {
    "iso:country":"US",
    "sg:address":"1995 Tiffin Ave",
    "sg:city":"Findlay",
    "sg:classifiers":[
        {
            "category":"Travel",
            "subcategory":"Travel Agent",
            "type":"Entertainment"
        }
    ],
    "sg:phone":"+1 419 424 8947",
    "sg:postcode":"45840",
    "sg:province":"OH",
    "sg:tags":[
        "agency",
        "bureau"
    ],
    "wof:name":"Central Travel & Ticket",
    "wof:placetype":"venue"
},
  "geometry": {"coordinates":[-83.605901,41.054029],"type":"Point"}
}