{
  "type": "Feature",
  "properties": {
    "addr:full": "1995 Tiffin Ave Findlay OH 45840",
    "addr:housenumber": "1995",
    "addr:postcode": "45840",
    "addr:street": "Tiffin Ave",
    "iso:country": "US",
    "sg:address": "1995 Tiffin Ave",
    "sg:city": "Findlay",
    "sg:classifiers": [
      {
        "category": "Travel",
        "subcategory": "Travel Agent",
        "type": "Entertainment"
      }
    ],
    "sg:phone": "+1 419 424 8947",
    "sg:postcode": "45840",
    "sg:province": "OH",
    "sg:tags": [
      "agency",
      "bureau"
    ],
    "wof:name": "Central Travel \u0026 Ticket",
    "wof:placetype": "venue"
  },
  "geometry": {"coordinates":[-83.605901,41.054029],"type":"Point"}
}
