{
  "type": "Feature",
  "properties": {
    "addr:full":"3136 Manchester Rd Akron OH 44319",
    "addr:housenumber":"3136",
    "addr:postcode":"44319",
    "addr:street":"Manchester Rd",
    "iso:country":"US",
    "sg:address":"3136 Manchester Rd",
    "sg:city":"Akron",
    "sg:classifiers":[
        {
            "category":"Shopping",
            "subcategory":"Computers & Home Electronics",
            "type":"Retail Goods"
        }
    ],
    "sg:phone":"+1 330 644 1111",
    "sg:postcode":"44319",
    "sg:province":"OH",
    "sg:tags":[
        "equipment",
        "dealer"
    ],
    "wof:name":"Desktop Solutions",
    "wof:placetype":"venue"
},
  "geometry": {"coordinates":[-81.552694,41.015508],"type":"Point"}
}