{
  "type": "Feature",
  "properties": {
    "iso:country":"US",
    "sg:address":"1604 State Rte 41 SW",
    "sg:city":"Washington Ct Hs",
    "sg:classifiers":[
        {
            "category":"Education",
            "subcategory":"School",
            "type":"Public Place"
        }
    ],
    "sg:phone":"+1 740 333 1844",
    "sg:postcode":"43160",
    "sg:province":"OH",
    "wof:name":"Miami Trace Local Schools",
    "wof:placetype":"venue"
},
  "geometry": {"coordinates":[-83.44175199999999,39.510468],"type":"Point"}
}