{
  "type": "Feature",
  "properties": {
    "iso:country":"US",
    "sg:address":"1694 N Countyline St",
    "sg:city":"Fostoria",
    "sg:classifiers":[
        {
            "category":"Banks & Credit Unions",
            "subcategory":"Bank",
            "type":"Services"
        }
    ],
    "sg:phone":"+1 419 436 1310",
    "sg:postcode":"44830",
    "sg:province":"OH",
    "sg:tags":[
        "commercial"
    ],
    "wof:name":"First Federal Bank of Midwest",
    "wof:placetype":"venue"
},
  "geometry": {"coordinates":[-83.420845,41.180876],"type":"Point"}
}