{
  "type": "Feature",
  "properties": {
    "addr:full": "28819 Tracy Rd Walbridge OH 43465",
    "addr:housenumber": "28819",
    "addr:postcode": "43465",
    "addr:street": "Tracy Rd",
    "iso:country": "US",
    "sg:address": "28819 Tracy Rd",
    "sg:city": "Walbridge",
    "sg:classifiers": [
      {
        "category": "Professional",
        "type": "Services"
      }
    ],
    "sg:phone": "+1 419 666 1312",
    "sg:postcode": "43465",
    "sg:province": "OH",
    "sg:tags": [
      "establishment"
    ],
    "wof:name": "Sound Jams",
    "wof:placetype": "venue"
  },
  "geometry": {"coordinates":[-83.527754,41.567052],"type":"Point"}
}
