{
  "type": "Feature",
  "properties": {
    "addr:full": "6105 Whipple Ave NW North Canton OH 44720",
    "addr:housenumber": "6105",
    "addr:postcode": "44720",
    "addr:street": "Whipple Ave Nw",
    "iso:country": "US",
    "sg:address": "6105 Whipple Ave NW",
    "sg:city": "North Canton",
    "sg:classifiers": [
      {
        "category": "Personal",
        "subcategory": "Beauty Salon",
        "type": "Services"
      }
    ],
    "sg:phone": "+1 330 966 6668",
    "sg:postcode": "44720",
    "sg:province": "OH",
    "wof:name": "Styles By Anita",
    "wof:placetype": "venue"
  },
  "geometry": {"coordinates":[-81.422439,40.867722],"type":"Point"}
}
