{
  "type": "Feature",
  "properties": {
    "addr:full":"2826 Weckerly Rd Monclova OH 43542",
    "addr:housenumber":"2826",
    "addr:postcode":"43542",
    "addr:street":"Weckerly Rd",
    "iso:country":"US",
    "sg:address":"2826 Weckerly Rd",
    "sg:city":"Monclova",
    "sg:classifiers":[
        {
            "category":"Building & Trades",
            "subcategory":"Cleaning & Sanitation",
            "type":"Services"
        }
    ],
    "sg:phone":"+1 419 865 0452",
    "sg:postcode":"43542",
    "sg:province":"OH",
    "sg:tags":[
        "fireplace",
        "chimney"
    ],
    "wof:name":"Masters Of London",
    "wof:placetype":"venue"
},
  "geometry": {"coordinates":[-83.77465599999999,41.586744],"type":"Point"}
}