{
  "type": "Feature",
  "properties": {
    "addr:full":"4696 N Ridge Rd Perry OH 44081",
    "addr:housenumber":"4696",
    "addr:postcode":"44081",
    "addr:street":"N Ridge Rd",
    "iso:country":"US",
    "sg:address":"4696 N Ridge Rd",
    "sg:city":"Perry",
    "sg:classifiers":[
        {
            "category":"Autos & Motor Vehicles",
            "subcategory":"Motorcycle Sales",
            "type":"Retail Goods"
        }
    ],
    "sg:phone":"+1 440 259 1822",
    "sg:postcode":"44081",
    "sg:province":"OH",
    "sg:tags":[
        "scooter"
    ],
    "wof:name":"Truimph Motorcycle Parts",
    "wof:placetype":"venue"
},
  "geometry": {"coordinates":[-81.129361,41.78605],"type":"Point"}
}