{
  "type": "Feature",
  "properties": {
    "iso:country":"US",
    "sg:address":"8160 Macedonia Commons Blvd",
    "sg:city":"Macedonia",
    "sg:classifiers":[
        {
            "category":"Utilities",
            "subcategory":"Mobile Phone",
            "type":"Services"
        },
        {
            "category":"Utilities",
            "subcategory":"Telephone",
            "type":"Services"
        }
    ],
    "sg:phone":"+1 330 908 1503",
    "sg:postcode":"44056",
    "sg:province":"OH",
    "sg:tags":[
        "communications",
        "cellular"
    ],
    "wof:name":"Alltel",
    "wof:placetype":"venue"
},
  "geometry": {"coordinates":[-81.51742400000001,41.305657],"type":"Point"}
}