{
  "type": "Feature",
  "properties": {
    "iso:country":"US",
    "sg:address":"1289 Claremont Ave",
    "sg:city":"Ashland",
    "sg:classifiers":[
        {
            "category":"Professional",
            "subcategory":"Accounting & Tax Preparation",
            "type":"Services"
        }
    ],
    "sg:phone":"+1 419 289 1342",
    "sg:postcode":"44805",
    "sg:province":"OH",
    "sg:tags":[
        "return",
        "filing"
    ],
    "wof:name":"H & R Block Tax Svc",
    "wof:placetype":"venue"
},
  "geometry": {"coordinates":[-82.33238799999999,40.856463],"type":"Point"}
}