{
  "type": "Feature",
  "properties": {
    "addr:full": "1158 N Court St Medina OH 44256",
    "addr:housenumber": "1158",
    "addr:postcode": "44256",
    "addr:street": "N Court St",
    "iso:country": "US",
    "sg:address": "1158 N Court St",
    "sg:city": "Medina",
    "sg:classifiers": [
      {
        "category": "Restaurant",
        "type": "Food \u0026 Drink"
      }
    ],
    "sg:phone": "+1 330 723 7917",
    "sg:postcode": "44256",
    "sg:province": "OH",
    "wof:name": "Don Tequila Mexican Restaurant",
    "wof:placetype": "venue"
  },
  "geometry": {"coordinates":[-81.862828,41.152995],"type":"Point"}
}
