{
  "type": "Feature",
  "properties": {
    "iso:country":"US",
    "sg:address":"2697 Dayton Germantown Pike",
    "sg:city":"Germantown",
    "sg:classifiers":[
        {
            "category":"Manufacturing",
            "subcategory":"Tools & Machinery",
            "type":"Manufacturing & Wholesale Goods"
        }
    ],
    "sg:phone":"+1 937 855 4681",
    "sg:postcode":"45327",
    "sg:province":"OH",
    "sg:tags":[
        "machine",
        "shop",
        "mill",
        "paper"
    ],
    "wof:name":"Foote Machine Shop",
    "wof:placetype":"venue"
},
  "geometry": {"coordinates":[-84.34436599999999,39.641423],"type":"Point"}
}