{
  "type": "Feature",
  "properties": {
    "addr:full":"112 W Main St Kent OH 44240",
    "addr:housenumber":"112",
    "addr:postcode":"44240",
    "addr:street":"W Main St",
    "iso:country":"US",
    "sg:address":"112 W Main St",
    "sg:city":"Kent",
    "sg:classifiers":[
        {
            "category":"Restaurant",
            "type":"Food & Drink"
        }
    ],
    "sg:phone":"+1 330 677 0223",
    "sg:postcode":"44240",
    "sg:province":"OH",
    "sg:tags":[
        "eating"
    ],
    "wof:name":"Taco Tonto's",
    "wof:placetype":"venue"
},
  "geometry": {"coordinates":[-81.358588,41.153697],"type":"Point"}
}