{
  "type": "Feature",
  "properties": {
    "iso:country":"US",
    "sg:address":"10506 Montgomery Rd",
    "sg:city":"Cincinnati",
    "sg:classifiers":[
        {
            "category":"Health Services",
            "subcategory":"Doctor",
            "type":"Services"
        }
    ],
    "sg:phone":"+1 513 791 1224",
    "sg:postcode":"45242",
    "sg:province":"OH",
    "sg:tags":[
        "medical"
    ],
    "wof:name":"Edmund W Jones MD",
    "wof:placetype":"venue"
},
  "geometry": {"coordinates":[-84.343608,39.253667],"type":"Point"}
}