{
  "type": "Feature",
  "properties": {
    "addr:full": "6505 Rockside Rd Cleveland OH 44131",
    "addr:housenumber": "6505",
    "addr:postcode": "44131",
    "addr:street": "Rockside Rd",
    "iso:country": "US",
    "sg:address": "6505 Rockside Rd",
    "sg:city": "Cleveland",
    "sg:classifiers": [
      {
        "category": "Health Services",
        "subcategory": "Health Practitioner",
        "type": "Services"
      }
    ],
    "sg:phone": "+1 216 524 1900",
    "sg:postcode": "44131",
    "sg:province": "OH",
    "sg:tags": [
      "psychologist"
    ],
    "wof:name": "Egan Chernin \u0026 Assoc",
    "wof:placetype": "venue"
  },
  "geometry": {"coordinates":[-81.649335,41.395905],"type":"Point"}
}
