{
  "type": "Feature",
  "properties": {
    "iso:country":"US",
    "sg:address":"9725 S Mason Montgomery Rd",
    "sg:city":"Mason",
    "sg:classifiers":[
        {
            "category":"Restaurant",
            "type":"Food & Drink"
        }
    ],
    "sg:phone":"+1 513 398 0949",
    "sg:postcode":"45040",
    "sg:province":"OH",
    "sg:website":"www.wafflehouse.com",
    "wof:name":"Waffle House",
    "wof:placetype":"venue"
},
  "geometry": {"coordinates":[-84.315476,39.295782],"type":"Point"}
}