{
  "type": "Feature",
  "properties": {
    "iso:country":"US",
    "sg:address":"937 Wooster Rd W",
    "sg:city":"Barberton",
    "sg:classifiers":[
        {
            "category":"Restaurant",
            "type":"Food & Drink"
        }
    ],
    "sg:phone":"+1 330 706 9242",
    "sg:postcode":"44203",
    "sg:province":"OH",
    "wof:name":"Dave's Diner",
    "wof:placetype":"venue"
},
  "geometry": {"coordinates":[-81.623841,41.010689],"type":"Point"}
}