{
  "type": "Feature",
  "properties": {
    "addr:full": "945 Lincoln Ave Steubenville OH 43952",
    "addr:housenumber": "945",
    "addr:postcode": "43952",
    "addr:street": "Lincoln Ave",
    "iso:country": "US",
    "sg:address": "945 Lincoln Ave",
    "sg:city": "Steubenville",
    "sg:classifiers": [
      {
        "category": "Autos \u0026 Motor Vehicles",
        "subcategory": "Fuel \u0026 Gas Station",
        "type": "Retail Goods"
      }
    ],
    "sg:phone": "+1 740 284 1607",
    "sg:postcode": "43952",
    "sg:province": "OH",
    "sg:tags": [
      "oil"
    ],
    "wof:name": "Lincoln Avenue Citgo",
    "wof:placetype": "venue"
  },
  "geometry": {"coordinates":[-80.627154,40.349685],"type":"Point"}
}
