{
  "type": "Feature",
  "properties": {
    "addr:full": "7260 Hart St Mentor OH 44060",
    "addr:housenumber": "7260",
    "addr:postcode": "44060",
    "addr:street": "Hart St",
    "iso:country": "US",
    "sg:address": "7260 Hart St",
    "sg:city": "Mentor",
    "sg:classifiers": [
      {
        "category": "Building \u0026 Trades",
        "subcategory": "Construction",
        "type": "Services"
      }
    ],
    "sg:phone": "+1 440 255 8108",
    "sg:postcode": "44060",
    "sg:province": "OH",
    "sg:tags": [
      "contractor"
    ],
    "wof:name": "Ruple Builders",
    "wof:placetype": "venue"
  },
  "geometry": {"coordinates":[-81.337702,41.674718],"type":"Point"}
}
