{
  "type": "Feature",
  "properties": {
    "iso:country":"US",
    "sg:address":"7260 Hart St",
    "sg:city":"Mentor",
    "sg:classifiers":[
        {
            "category":"Building & Trades",
            "subcategory":"Construction",
            "type":"Services"
        }
    ],
    "sg:phone":"+1 440 255 8108",
    "sg:postcode":"44060",
    "sg:province":"OH",
    "sg:tags":[
        "contractor"
    ],
    "wof:name":"Ruple Builders",
    "wof:placetype":"venue"
},
  "geometry": {"coordinates":[-81.33770199999999,41.674718],"type":"Point"}
}