{
  "type": "Feature",
  "properties": {
    "iso:country":"US",
    "sg:address":"315 E Columbia St",
    "sg:city":"Springfield",
    "sg:classifiers":[
        {
            "category":"Wholesale",
            "subcategory":"Electrical",
            "type":"Manufacturing & Wholesale Goods"
        }
    ],
    "sg:phone":"+1 937 325 5576",
    "sg:postcode":"45503",
    "sg:province":"OH",
    "sg:tags":[
        "electric",
        "motor"
    ],
    "sg:website":"www.maderelectric.com",
    "wof:name":"Mader Electric Motor Inc",
    "wof:placetype":"venue"
},
  "geometry": {"coordinates":[-83.80542800000001,39.9255],"type":"Point"}
}