{
  "type": "Feature",
  "properties": {
    "addr:full":"836 S Wheeling St Oregon OH 43616",
    "addr:housenumber":"836",
    "addr:postcode":"43616",
    "addr:street":"S Wheeling St",
    "iso:country":"US",
    "sg:address":"836 S Wheeling St",
    "sg:city":"Oregon",
    "sg:classifiers":[
        {
            "category":"Shopping",
            "subcategory":"Clothing, Apparel, & Fashions",
            "type":"Retail Goods"
        }
    ],
    "sg:phone":"+1 419 693 7377",
    "sg:postcode":"43616",
    "sg:province":"OH",
    "sg:tags":[
        "uniform"
    ],
    "wof:name":"Uniform Mart",
    "wof:placetype":"venue"
},
  "geometry": {"coordinates":[-83.486563,41.633525],"type":"Point"}
}