{
  "type": "Feature",
  "properties": {
    "addr:full":"390 W Bagley Rd Berea OH 44017",
    "addr:housenumber":"390",
    "addr:postcode":"44017",
    "addr:street":"W Bagley Rd",
    "iso:country":"US",
    "sg:address":"390 W Bagley Rd",
    "sg:city":"Berea",
    "sg:classifiers":[
        {
            "category":"Shopping",
            "subcategory":"Discount & Variety Stores",
            "type":"Retail Goods"
        }
    ],
    "sg:phone":"+1 440 239 9979",
    "sg:postcode":"44017",
    "sg:province":"OH",
    "wof:name":"Dollar General",
    "wof:placetype":"venue"
},
  "geometry": {"coordinates":[-81.865758,41.372337],"type":"Point"}
}