{
  "type": "Feature",
  "properties": {
    "iso:country":"US",
    "sg:address":"241 W 3rd St",
    "sg:city":"Dover",
    "sg:classifiers":[
        {
            "category":"Insurance",
            "subcategory":"Insurance Agent",
            "type":"Services"
        }
    ],
    "sg:phone":"+1 330 364 6464",
    "sg:postcode":"44622",
    "sg:province":"OH",
    "wof:name":"Jack McKean Agcy Inc",
    "wof:placetype":"venue"
},
  "geometry": {"coordinates":[-81.479089,40.520573],"type":"Point"}
}