{
  "type": "Feature",
  "properties": {
    "iso:country":"US",
    "sg:address":"4122 Tuscarawas St W",
    "sg:city":"Canton",
    "sg:classifiers":[
        {
            "category":"Shopping",
            "subcategory":"Clothing, Apparel, & Fashions",
            "type":"Retail Goods"
        }
    ],
    "sg:phone":"+1 330 479 2912",
    "sg:postcode":"44708",
    "sg:province":"OH",
    "wof:name":"Hot Spot",
    "wof:placetype":"venue"
},
  "geometry": {"coordinates":[-81.426085,40.796293],"type":"Point"}
}