{
  "type": "Feature",
  "properties": {
    "iso:country":"US",
    "sg:address":"7576 Purity Rd NE",
    "sg:city":"Saint Louisville",
    "sg:classifiers":[
        {
            "category":"Farming",
            "subcategory":"Livestock Farm",
            "type":"Manufacturing & Wholesale Goods"
        }
    ],
    "sg:phone":"+1 740 745 5615",
    "sg:postcode":"43071",
    "sg:province":"OH",
    "sg:tags":[
        "animal",
        "general"
    ],
    "wof:name":"Arthur Giles",
    "wof:placetype":"venue"
},
  "geometry": {"coordinates":[-82.342129,40.162251],"type":"Point"}
}