{
  "type": "Feature",
  "properties": {
    "addr:full": "145 S Front St Columbus OH 43215",
    "addr:housenumber": "145",
    "addr:postcode": "43215",
    "addr:street": "S Front St",
    "iso:country": "US",
    "sg:address": "145 S Front St",
    "sg:city": "Columbus",
    "sg:classifiers": [
      {
        "category": "Government",
        "subcategory": "Office",
        "type": "Public Place"
      }
    ],
    "sg:phone": "+1 614 466 2618",
    "sg:postcode": "43215",
    "sg:province": "OH",
    "sg:tags": [
      "program",
      "administrative"
    ],
    "wof:name": "Local Operations",
    "wof:placetype": "venue"
  },
  "geometry": {"coordinates":[-83.00198,39.959667],"type":"Point"}
}
