{
  "type": "Feature",
  "properties": {
    "addr:full": "1200 Main St Hamilton IN 45013",
    "addr:housenumber": "1200",
    "addr:postcode": "45013",
    "addr:street": "Main St",
    "iso:country": "US",
    "sg:address": "1200 Main St",
    "sg:city": "Hamilton",
    "sg:classifiers": [
      {
        "category": "Organizations",
        "subcategory": "Religious Organization",
        "type": "Services"
      }
    ],
    "sg:phone": "+1 513 844 1935",
    "sg:postcode": "45013",
    "sg:province": "IN",
    "sg:website": "www.graceumchamilton.org",
    "wof:name": "Grace United Methodist Church",
    "wof:placetype": "venue"
  },
  "geometry": {"coordinates":[-84.587408,39.418299],"type":"Point"}
}
