{
  "type": "Feature",
  "properties": {
    "iso:country":"US",
    "sg:address":"211 Jefferson St",
    "sg:city":"Findlay",
    "sg:classifiers":[
        {
            "category":"Manufacturing",
            "subcategory":"Rubber & Plastics",
            "type":"Manufacturing & Wholesale Goods"
        }
    ],
    "sg:phone":"+1 419 424 3113",
    "sg:postcode":"45840",
    "sg:province":"OH",
    "sg:tags":[
        "manufacture"
    ],
    "wof:name":"ECL Plastics Inc",
    "wof:placetype":"venue"
},
  "geometry": {"coordinates":[-83.645712,41.043678],"type":"Point"}
}