{
  "type": "Feature",
  "properties": {
    "addr:full": "211 Jefferson St Findlay OH 45840",
    "addr:housenumber": "211",
    "addr:postcode": "45840",
    "addr:street": "Jefferson St",
    "iso:country": "US",
    "sg:address": "211 Jefferson St",
    "sg:city": "Findlay",
    "sg:classifiers": [
      {
        "category": "Manufacturing",
        "subcategory": "Rubber \u0026 Plastics",
        "type": "Manufacturing \u0026 Wholesale Goods"
      }
    ],
    "sg:phone": "+1 419 424 3113",
    "sg:postcode": "45840",
    "sg:province": "OH",
    "sg:tags": [
      "manufacture"
    ],
    "wof:name": "ECL Plastics Inc",
    "wof:placetype": "venue"
  },
  "geometry": {"coordinates":[-83.645712,41.043678],"type":"Point"}
}
