{
  "type": "Feature",
  "properties": {
    "addr:full": "821 E Findlay St Carey OH 43316",
    "addr:housenumber": "821",
    "addr:postcode": "43316",
    "addr:street": "E Findlay St",
    "iso:country": "US",
    "sg:address": "821 E Findlay St",
    "sg:city": "Carey",
    "sg:classifiers": [
      {
        "category": "Health Services",
        "subcategory": "Nursing And Care Facility",
        "type": "Services"
      }
    ],
    "sg:phone": "+1 419 396 7287",
    "sg:postcode": "43316",
    "sg:province": "OH",
    "sg:tags": [
      "skilled"
    ],
    "wof:name": "Eaglewood Care Center",
    "wof:placetype": "venue"
  },
  "geometry": {"coordinates":[-83.367393,40.949811],"type":"Point"}
}
