{
  "type": "Feature",
  "properties": {
    "addr:full":"725 N Pennsylvania Ave Wellston OH 45692",
    "addr:housenumber":"725",
    "addr:postcode":"45692",
    "addr:street":"N Pennsylvania Ave",
    "iso:country":"US",
    "sg:address":"725 N Pennsylvania Ave",
    "sg:city":"Wellston",
    "sg:classifiers":[
        {
            "category":"Retail",
            "subcategory":"Auto Rental",
            "type":"Services"
        }
    ],
    "sg:phone":"+1 740 384 0862",
    "sg:postcode":"45692",
    "sg:province":"OH",
    "sg:tags":[
        "renting",
        "truck",
        "leasing"
    ],
    "wof:name":"U-Haul Co",
    "wof:placetype":"venue"
},
  "geometry": {"coordinates":[-82.532534,39.128176],"type":"Point"}
}