{
  "type": "Feature",
  "properties": {
    "addr:full": "3030 Graham Rd Stow OH 44224",
    "addr:housenumber": "3030",
    "addr:postcode": "44224",
    "addr:street": "Graham Rd",
    "iso:country": "US",
    "sg:address": "3030 Graham Rd",
    "sg:city": "Stow",
    "sg:classifiers": [
      {
        "category": "Shopping",
        "subcategory": "Hobbies, Toys, \u0026 Games",
        "type": "Retail Goods"
      }
    ],
    "sg:phone": "+1 330 688 2444",
    "sg:postcode": "44224",
    "sg:province": "OH",
    "sg:tags": [
      "product",
      "ceramic"
    ],
    "wof:name": "Imagine That Studio",
    "wof:placetype": "venue"
  },
  "geometry": {"coordinates":[-81.406502,41.16645],"type":"Point"}
}
