{
  "type": "Feature",
  "properties": {
    "addr:full": "18300 Royalton Rd Cleveland OH 44136",
    "addr:housenumber": "18300",
    "addr:postcode": "44136",
    "addr:street": "Royalton Rd",
    "iso:country": "US",
    "sg:address": "18300 Royalton Rd",
    "sg:city": "Cleveland",
    "sg:classifiers": [
      {
        "category": "Food \u0026 Beverages",
        "subcategory": "Groceries \u0026 Convenience Stores",
        "type": "Retail Goods"
      },
      {
        "category": "Shopping",
        "subcategory": "Pharmacy",
        "type": "Retail Goods"
      }
    ],
    "sg:phone": "+1 440 846 0009",
    "sg:postcode": "44136",
    "sg:province": "OH",
    "sg:tags": [
      "grocer"
    ],
    "wof:name": "Tops Friendly Market Pharmacy",
    "wof:placetype": "venue"
  },
  "geometry": {"coordinates":[-81.829333,41.313919],"type":"Point"}
}
