{
  "type": "Feature",
  "properties": {
    "iso:country":"US",
    "sg:address":"18300 Royalton Rd",
    "sg:city":"Cleveland",
    "sg:classifiers":[
        {
            "category":"Food & Beverages",
            "subcategory":"Groceries & Convenience Stores",
            "type":"Retail Goods"
        },
        {
            "category":"Shopping",
            "subcategory":"Pharmacy",
            "type":"Retail Goods"
        }
    ],
    "sg:phone":"+1 440 846 0009",
    "sg:postcode":"44136",
    "sg:province":"OH",
    "sg:tags":[
        "grocer"
    ],
    "wof:name":"Tops Friendly Market Pharmacy",
    "wof:placetype":"venue"
},
  "geometry": {"coordinates":[-81.82933300000001,41.313919],"type":"Point"}
}