{
  "type": "Feature",
  "properties": {
    "addr:full": "3284 N Bend Rd Cincinnati OH 45239",
    "addr:housenumber": "3284",
    "addr:postcode": "45239",
    "addr:street": "N Bend Rd",
    "iso:country": "US",
    "sg:address": "3284 N Bend Rd",
    "sg:city": "Cincinnati",
    "sg:classifiers": [
      {
        "category": "Professional",
        "subcategory": "Accounting \u0026 Tax Preparation",
        "type": "Services"
      }
    ],
    "sg:phone": "+1 513 661 6550",
    "sg:postcode": "45239",
    "sg:province": "OH",
    "sg:tags": [
      "accountant"
    ],
    "wof:name": "Aable One Day Tax Svc",
    "wof:placetype": "venue"
  },
  "geometry": {"coordinates":[-84.59286,39.190393],"type":"Point"}
}
