{
  "type": "Feature",
  "properties": {
    "iso:country":"US",
    "sg:address":"3510 Rangoon Dr",
    "sg:city":"Westerville",
    "sg:classifiers":[
        {
            "category":"Shopping",
            "subcategory":"Catalog Store",
            "type":"Retail Goods"
        }
    ],
    "sg:phone":"+1 614 882 3795",
    "sg:postcode":"43081",
    "sg:province":"OH",
    "sg:tags":[
        "mail",
        "house"
    ],
    "wof:name":"Loretta Mann",
    "wof:placetype":"venue"
},
  "geometry": {"coordinates":[-82.918571,40.089114],"type":"Point"}
}