{
  "type": "Feature",
  "properties": {
    "iso:country":"US",
    "sg:address":"3900 Sunforest Ct",
    "sg:city":"Toledo",
    "sg:classifiers":[
        {
            "category":"Health Services",
            "subcategory":"Doctor",
            "type":"Services"
        }
    ],
    "sg:phone":"+1 419 473 3446",
    "sg:postcode":"43623",
    "sg:province":"OH",
    "sg:tags":[
        "physician",
        "surgeon"
    ],
    "wof:name":"Urology Associates Of Nw Ohio",
    "wof:placetype":"venue"
},
  "geometry": {"coordinates":[-83.631635,41.691482],"type":"Point"}
}