{
  "type": "Feature",
  "properties": {
    "addr:full":"544 Jackson St Nelsonville OH 45764",
    "addr:housenumber":"544",
    "addr:postcode":"45764",
    "addr:street":"Jackson St",
    "iso:country":"US",
    "sg:address":"544 Jackson St",
    "sg:city":"Nelsonville",
    "sg:classifiers":[
        {
            "category":"Building & Trades",
            "subcategory":"Construction",
            "type":"Services"
        }
    ],
    "sg:phone":"+1 740 753 4190",
    "sg:postcode":"45764",
    "sg:province":"OH",
    "sg:tags":[
        "front",
        "store"
    ],
    "wof:name":"Classical Gifts",
    "wof:placetype":"venue"
},
  "geometry": {"coordinates":[-82.22649199999999,39.454787],"type":"Point"}
}