{
  "type": "Feature",
  "properties": {
    "addr:full":"434 Crescent Dr Berea OH 44017",
    "addr:housenumber":"434",
    "addr:postcode":"44017",
    "addr:street":"Crescent Dr",
    "iso:country":"US",
    "sg:address":"434 Crescent Dr",
    "sg:city":"Berea",
    "sg:classifiers":[
        {
            "category":"Wholesale",
            "subcategory":"Machinery & Supplies",
            "type":"Manufacturing & Wholesale Goods"
        }
    ],
    "sg:phone":"+1 440 243 0903",
    "sg:postcode":"44017",
    "sg:province":"OH",
    "sg:tags":[
        "repairing"
    ],
    "wof:name":"Blake Mill Wrighting",
    "wof:placetype":"venue"
},
  "geometry": {"coordinates":[-81.87228899999999,41.367549],"type":"Point"}
}