{
  "type": "Feature",
  "properties": {
    "iso:country":"US",
    "sg:address":"3898 Tyndall Rd",
    "sg:city":"Cleveland",
    "sg:classifiers":[
        {
            "category":"Shopping",
            "subcategory":"Clothing, Apparel, & Fashions",
            "type":"Retail Goods"
        }
    ],
    "sg:phone":"+1 216 321 6038",
    "sg:postcode":"44118",
    "sg:province":"OH",
    "sg:website":"www.autoracingalley.com",
    "wof:name":"Auto Racing Alley LTD",
    "wof:placetype":"venue"
},
  "geometry": {"coordinates":[-81.53964,41.487366],"type":"Point"}
}