{
  "type": "Feature",
  "properties": {
    "iso:country":"US",
    "sg:address":"2100 Reid Ave",
    "sg:city":"Lorain",
    "sg:classifiers":[
        {
            "category":"Professional",
            "subcategory":"Lawyer & Legal Services",
            "type":"Services"
        }
    ],
    "sg:phone":"+1 440 244 0826",
    "sg:postcode":"44052",
    "sg:province":"OH",
    "sg:tags":[
        "attorney"
    ],
    "wof:name":"Otero & Otero",
    "wof:placetype":"venue"
},
  "geometry": {"coordinates":[-82.16866899999999,41.450266],"type":"Point"}
}