{
  "type": "Feature",
  "properties": {
    "addr:full": "2100 Reid Ave Lorain OH 44052",
    "addr:housenumber": "2100",
    "addr:postcode": "44052",
    "addr:street": "Reid Ave",
    "iso:country": "US",
    "sg:address": "2100 Reid Ave",
    "sg:city": "Lorain",
    "sg:classifiers": [
      {
        "category": "Professional",
        "subcategory": "Lawyer \u0026 Legal Services",
        "type": "Services"
      }
    ],
    "sg:phone": "+1 440 244 0826",
    "sg:postcode": "44052",
    "sg:province": "OH",
    "sg:tags": [
      "attorney"
    ],
    "wof:name": "Otero \u0026 Otero",
    "wof:placetype": "venue"
  },
  "geometry": {"coordinates":[-82.168669,41.450266],"type":"Point"}
}
