{
  "type": "Feature",
  "properties": {
    "addr:full":"2825 W State Rte 73 Wilmington OH 45177",
    "addr:housenumber":"2825",
    "addr:postcode":"45177",
    "addr:street":"W State Rte 73",
    "iso:country":"US",
    "sg:address":"2825 W State Rte 73",
    "sg:city":"Wilmington",
    "sg:classifiers":[
        {
            "category":"Personal",
            "subcategory":"Beauty Salon",
            "type":"Services"
        }
    ],
    "sg:phone":"+1 937 383 2900",
    "sg:postcode":"45177",
    "sg:province":"OH",
    "wof:name":"Smart Style Family Hair Salon",
    "wof:placetype":"venue"
},
  "geometry": {"coordinates":[-83.873648,39.462768],"type":"Point"}
}