{
  "type": "Feature",
  "properties": {
    "iso:country":"US",
    "sg:address":"654 Perry St",
    "sg:city":"Defiance",
    "sg:classifiers":[
        {
            "category":"Personal",
            "subcategory":"Beauty Salon",
            "type":"Services"
        }
    ],
    "sg:phone":"+1 419 782 0217",
    "sg:postcode":"43512",
    "sg:province":"OH",
    "wof:name":"Custom Cuts",
    "wof:placetype":"venue"
},
  "geometry": {"coordinates":[-84.36678499999999,41.283322],"type":"Point"}
}