{
  "type": "Feature",
  "properties": {
    "iso:country":"US",
    "sg:address":"4221 Malsbary Rd",
    "sg:city":"Cincinnati",
    "sg:classifiers":[
        {
            "category":"Travel",
            "subcategory":"Hotels & Motels",
            "type":"Entertainment"
        }
    ],
    "sg:phone":"+1 513 984 8221",
    "sg:postcode":"45242",
    "sg:province":"OH",
    "wof:name":"Marriott",
    "wof:placetype":"venue"
},
  "geometry": {"coordinates":[-84.39152900000001,39.240892],"type":"Point"}
}