{
  "type": "Feature",
  "properties": {
    "addr:full": "4221 Malsbary Rd Cincinnati OH 45242",
    "addr:housenumber": "4221",
    "addr:postcode": "45242",
    "addr:street": "Malsbary Rd",
    "iso:country": "US",
    "sg:address": "4221 Malsbary Rd",
    "sg:city": "Cincinnati",
    "sg:classifiers": [
      {
        "category": "Travel",
        "subcategory": "Hotels \u0026 Motels",
        "type": "Entertainment"
      }
    ],
    "sg:phone": "+1 513 984 8221",
    "sg:postcode": "45242",
    "sg:province": "OH",
    "wof:name": "Marriott",
    "wof:placetype": "venue"
  },
  "geometry": {"coordinates":[-84.391529,39.240892],"type":"Point"}
}
