{
  "type": "Feature",
  "properties": {
    "addr:full":"1141 Northview Dr Hillsboro OH 45133",
    "addr:housenumber":"1141",
    "addr:postcode":"45133",
    "addr:street":"Northview Dr",
    "iso:country":"US",
    "sg:address":"1141 Northview Dr",
    "sg:city":"Hillsboro",
    "sg:classifiers":[
        {
            "category":"Health Services",
            "subcategory":"Nursing And Care Facility",
            "type":"Services"
        }
    ],
    "sg:phone":"+1 937 393 5766",
    "sg:postcode":"45133",
    "sg:province":"OH",
    "sg:tags":[
        "home",
        "convalescent"
    ],
    "wof:name":"Heartland Health Care Ctr",
    "wof:placetype":"venue"
},
  "geometry": {"coordinates":[-83.607686,39.219768],"type":"Point"}
}