{
  "type": "Feature",
  "properties": {
    "addr:full": "2220 Mc Guffey Rd Columbus OH 43211",
    "addr:housenumber": "2220",
    "addr:postcode": "43211",
    "addr:street": "Mc Guffey Rd",
    "iso:country": "US",
    "sg:address": "2220 Mc Guffey Rd",
    "sg:city": "Columbus",
    "sg:classifiers": [
      {
        "category": "Organizations",
        "subcategory": "Religious Organization",
        "type": "Services"
      }
    ],
    "sg:phone": "+1 614 267 3219",
    "sg:postcode": "43211",
    "sg:province": "OH",
    "sg:tags": [
      "church"
    ],
    "wof:name": "New Haven Church",
    "wof:placetype": "venue"
  },
  "geometry": {"coordinates":[-82.981492,40.011675],"type":"Point"}
}
