{
  "type": "Feature",
  "properties": {
    "iso:country":"US",
    "sg:address":"641 Lincoln Way W",
    "sg:city":"Massillon",
    "sg:classifiers":[
        {
            "category":"Wholesale",
            "subcategory":"Metals & Minerals",
            "type":"Manufacturing & Wholesale Goods"
        }
    ],
    "sg:phone":"+1 330 833 8214",
    "sg:postcode":"44647",
    "sg:province":"OH",
    "sg:tags":[
        "center"
    ],
    "wof:name":"Hartman Independent Company",
    "wof:placetype":"venue"
},
  "geometry": {"coordinates":[-81.532127,40.793827],"type":"Point"}
}