{
  "type": "Feature",
  "properties": {
    "addr:full":"7678 Mc Ewen Rd Dayton OH 45459",
    "addr:housenumber":"7678",
    "addr:postcode":"45459",
    "addr:street":"Mc Ewen Rd",
    "iso:country":"US",
    "sg:address":"7678 Mc Ewen Rd",
    "sg:city":"Dayton",
    "sg:classifiers":[
        {
            "category":"Wholesale",
            "subcategory":"Durable Goods & Equipment",
            "type":"Manufacturing & Wholesale Goods"
        }
    ],
    "sg:phone":"+1 937 438 9710",
    "sg:postcode":"45459",
    "sg:province":"OH",
    "sg:tags":[
        "product",
        "audio",
        "sales",
        "integration"
    ],
    "wof:name":"Vutex LLC",
    "wof:placetype":"venue"
},
  "geometry": {"coordinates":[-84.18781,39.632404],"type":"Point"}
}