{
  "type": "Feature",
  "properties": {
    "addr:full":"34 Triangle Park Dr Cincinnati OH 45246",
    "addr:housenumber":"34",
    "addr:postcode":"45246",
    "addr:street":"Triangle Park Dr",
    "iso:country":"US",
    "sg:address":"34 Triangle Park Dr",
    "sg:city":"Cincinnati",
    "sg:classifiers":[
        {
            "category":"Professional",
            "subcategory":"Business Services",
            "type":"Services"
        }
    ],
    "sg:phone":"+1 513 772 6200",
    "sg:postcode":"45246",
    "sg:province":"OH",
    "wof:name":"Lead Secure",
    "wof:placetype":"venue"
},
  "geometry": {"coordinates":[-84.44667099999999,39.28749],"type":"Point"}
}