{
  "type": "Feature",
  "properties": {
    "addr:full":"16511 Hilliard Rd Cleveland OH 44107",
    "addr:housenumber":"16511",
    "addr:postcode":"44107",
    "addr:street":"Hilliard Rd",
    "iso:country":"US",
    "sg:address":"16511 Hilliard Rd",
    "sg:city":"Cleveland",
    "sg:classifiers":[
        {
            "category":"Education",
            "subcategory":"School",
            "type":"Public Place"
        }
    ],
    "sg:phone":"+1 216 529 4228",
    "sg:postcode":"44107",
    "sg:province":"OH",
    "wof:name":"Hayes Elementary School",
    "wof:placetype":"venue"
},
  "geometry": {"coordinates":[-81.813132,41.475438],"type":"Point"}
}