{
  "type": "Feature",
  "properties": {
    "iso:country":"US",
    "sg:address":"26004 Euclid Ave",
    "sg:city":"Cleveland",
    "sg:classifiers":[
        {
            "category":"Restaurant",
            "type":"Food & Drink"
        }
    ],
    "sg:phone":"+1 216 797 0200",
    "sg:postcode":"44132",
    "sg:province":"OH",
    "wof:name":"Mr Ribs Bbq",
    "wof:placetype":"venue"
},
  "geometry": {"coordinates":[-81.501968,41.588016],"type":"Point"}
}