{
  "type": "Feature",
  "properties": {
    "iso:country":"US",
    "sg:address":"5690 Clyde Moore Dr",
    "sg:city":"Groveport",
    "sg:classifiers":[
        {
            "category":"Professional",
            "subcategory":"Computer Services",
            "type":"Services"
        }
    ],
    "sg:phone":"+1 614 497 1338",
    "sg:postcode":"43125",
    "sg:province":"OH",
    "sg:tags":[
        "programing",
        "custom"
    ],
    "wof:name":"Computer Sciences Corporation",
    "wof:placetype":"venue"
},
  "geometry": {"coordinates":[-82.903188,39.855967],"type":"Point"}
}