{
  "type": "Feature",
  "properties": {
    "addr:full": "4774 Outville Rd Granville OH 43023",
    "addr:housenumber": "4774",
    "addr:postcode": "43023",
    "addr:street": "Outville Rd",
    "iso:country": "US",
    "sg:address": "4774 Outville Rd",
    "sg:city": "Granville",
    "sg:classifiers": [
      {
        "category": "Farming",
        "subcategory": "Farm",
        "type": "Manufacturing \u0026 Wholesale Goods"
      }
    ],
    "sg:phone": "+1 740 927 5610",
    "sg:postcode": "43023",
    "sg:province": "OH",
    "wof:name": "Cardinal Lane Farms",
    "wof:placetype": "venue"
  },
  "geometry": {"coordinates":[-82.594978,40.020424],"type":"Point"}
}
