{
  "type": "Feature",
  "properties": {
    "addr:full":"365 Kenmore Ave SE Warren OH 44483",
    "addr:housenumber":"365",
    "addr:postcode":"44483",
    "addr:street":"Kenmore Ave Se",
    "iso:country":"US",
    "sg:address":"365 Kenmore Ave SE",
    "sg:city":"Warren",
    "sg:classifiers":[
        {
            "category":"Wholesale",
            "subcategory":"Medical Equipment & Supplies",
            "type":"Manufacturing & Wholesale Goods"
        }
    ],
    "sg:phone":"+1 330 399 5836",
    "sg:postcode":"44483",
    "sg:province":"OH",
    "wof:name":"Morick Inc",
    "wof:placetype":"venue"
},
  "geometry": {"coordinates":[-80.787988,41.23327],"type":"Point"}
}