{
  "type": "Feature",
  "properties": {
    "addr:full": "815 Greenler St Defiance OH 43512",
    "addr:housenumber": "815",
    "addr:postcode": "43512",
    "addr:street": "Greenler St",
    "iso:country": "US",
    "sg:address": "815 Greenler St",
    "sg:city": "Defiance",
    "sg:phone": "+1 419 784 3835",
    "sg:postcode": "43512",
    "sg:province": "OH",
    "sg:tags": [
      "fuel",
      "diesel"
    ],
    "wof:name": "American Ag Fuels",
    "wof:placetype": "venue"
  },
  "geometry": {"coordinates":[-84.350017,41.27748],"type":"Point"}
}
