{
  "type": "Feature",
  "properties": {
    "addr:full": "28599 S Woodland Rd Cleveland OH 44124",
    "addr:housenumber": "28599",
    "addr:postcode": "44124",
    "addr:street": "S Woodland Rd",
    "iso:country": "US",
    "sg:address": "28599 S Woodland Rd",
    "sg:city": "Cleveland",
    "sg:classifiers": [
      {
        "category": "Utilities",
        "subcategory": "Refuse",
        "type": "Services"
      }
    ],
    "sg:phone": "+1 216 595 9531",
    "sg:postcode": "44124",
    "sg:province": "OH",
    "sg:tags": [
      "system"
    ],
    "wof:name": "J \u0026 R Recycling Inc",
    "wof:placetype": "venue"
  },
  "geometry": {"coordinates":[-81.483094,41.473611],"type":"Point"}
}
