{
  "type": "Feature",
  "properties": {
    "addr:full": "1150 W 8th St Cincinnati OH 45203",
    "addr:housenumber": "1150",
    "addr:postcode": "45203",
    "addr:street": "W 8Th St",
    "iso:country": "US",
    "sg:address": "1150 W 8th St",
    "sg:city": "Cincinnati",
    "sg:classifiers": [
      {
        "category": "Professional",
        "subcategory": "Detective \u0026 Security Services",
        "type": "Services"
      }
    ],
    "sg:phone": "+1 513 621 6666",
    "sg:postcode": "45203",
    "sg:province": "OH",
    "sg:tags": [
      "guard",
      "patrol"
    ],
    "wof:name": "Burns International Security",
    "wof:placetype": "venue"
  },
  "geometry": {"coordinates":[-84.535653,39.104085],"type":"Point"}
}
