{
  "type": "Feature",
  "properties": {
    "iso:country":"US",
    "sg:address":"62 Morningside Dr",
    "sg:city":"Novelty",
    "sg:classifiers":[
        {
            "category":"Real Estate",
            "subcategory":"Architect",
            "type":"Services"
        }
    ],
    "sg:phone":"+1 440 338 4750",
    "sg:postcode":"44072",
    "sg:province":"OH",
    "wof:name":"Dunning Ann M A I A Inc",
    "wof:placetype":"venue"
},
  "geometry": {"coordinates":[-81.34030199999999,41.465199],"type":"Point"}
}