{
  "type": "Feature",
  "properties": {
    "addr:full":"6905 Meadowbrook Ave Cleveland OH 44144",
    "addr:housenumber":"6905",
    "addr:postcode":"44144",
    "addr:street":"Meadowbrook Ave",
    "iso:country":"US",
    "sg:address":"6905 Meadowbrook Ave",
    "sg:city":"Cleveland",
    "sg:classifiers":[
        {
            "category":"Building & Trades",
            "subcategory":"Landscaping Services",
            "type":"Services"
        }
    ],
    "sg:phone":"+1 216 661 4143",
    "sg:postcode":"44144",
    "sg:province":"OH",
    "sg:tags":[
        "landscape",
        "contractor"
    ],
    "wof:name":"Dees Tree Service & Ldscpg",
    "wof:placetype":"venue"
},
  "geometry": {"coordinates":[-81.732568,41.444994],"type":"Point"}
}