{
  "type": "Feature",
  "properties": {
    "addr:full":"193 Old State Rte 7 Steubenville OH 43952",
    "addr:housenumber":"193",
    "addr:postcode":"43952",
    "addr:street":"Old State Rte 7",
    "iso:country":"US",
    "sg:address":"193 Old State Rte 7",
    "sg:city":"Steubenville",
    "sg:classifiers":[
        {
            "category":"Freight",
            "type":"Transportation"
        }
    ],
    "sg:phone":"+1 740 282 7476",
    "sg:postcode":"43952",
    "sg:province":"OH",
    "sg:tags":[
        "trucking"
    ],
    "wof:name":"Spotti Trucking",
    "wof:placetype":"venue"
},
  "geometry": {"coordinates":[-80.624236,40.401849],"type":"Point"}
}