{
  "type": "Feature",
  "properties": {
    "addr:full": "95 Hill St Xenia OH 45385",
    "addr:housenumber": "95",
    "addr:postcode": "45385",
    "addr:street": "Hill St",
    "iso:country": "US",
    "sg:address": "95 Hill St",
    "sg:city": "Xenia",
    "sg:classifiers": [
      {
        "category": "Retail",
        "subcategory": "Auto Repair",
        "type": "Services"
      }
    ],
    "sg:phone": "+1 937 376 3185",
    "sg:postcode": "45385",
    "sg:province": "OH",
    "sg:tags": [
      "transmission"
    ],
    "wof:name": "Xenia Transmission Svc Co",
    "wof:placetype": "venue"
  },
  "geometry": {"coordinates":[-83.928493,39.680191],"type":"Point"}
}
