{
  "type": "Feature",
  "properties": {
    "addr:full":"1862 Noble Rd Cleveland OH 44112",
    "addr:housenumber":"1862",
    "addr:postcode":"44112",
    "addr:street":"Noble Rd",
    "iso:country":"US",
    "sg:address":"1862 Noble Rd",
    "sg:city":"Cleveland",
    "sg:classifiers":[
        {
            "category":"Social Services",
            "type":"Services"
        }
    ],
    "sg:phone":"+1 216 249 3000",
    "sg:postcode":"44112",
    "sg:province":"OH",
    "sg:tags":[
        "organization",
        "welfare"
    ],
    "wof:name":"David's Challenge",
    "wof:placetype":"venue"
},
  "geometry": {"coordinates":[-81.566909,41.542968],"type":"Point"}
}