{
  "type": "Feature",
  "properties": {
    "iso:country":"US",
    "sg:address":"3785 Green Rd",
    "sg:city":"Cleveland",
    "sg:classifiers":[
        {
            "category":"Real Estate",
            "subcategory":"Developer",
            "type":"Services"
        }
    ],
    "sg:phone":"+1 216 292 7616",
    "sg:postcode":"44122",
    "sg:province":"OH",
    "wof:name":"Thomas Holdings LLC",
    "wof:placetype":"venue"
},
  "geometry": {"coordinates":[-81.51694,41.458891],"type":"Point"}
}