{
  "type": "Feature",
  "properties": {
    "iso:country":"US",
    "sg:address":"5455 Wegman Dr",
    "sg:city":"Valley City",
    "sg:classifiers":[
        {
            "category":"Manufacturing",
            "subcategory":"Metals",
            "type":"Manufacturing & Wholesale Goods"
        }
    ],
    "sg:phone":"+1 330 220 7717",
    "sg:postcode":"44280",
    "sg:province":"OH",
    "sg:tags":[
        "steel",
        "processing"
    ],
    "sg:website":"www.northlakesteelcorp.com",
    "wof:name":"North Lake Steel",
    "wof:placetype":"venue"
},
  "geometry": {"coordinates":[-81.881992,41.252706],"type":"Point"}
}