{
  "type": "Feature",
  "properties": {
    "addr:full": "916 Patterson Ave Akron OH 44310",
    "addr:housenumber": "916",
    "addr:postcode": "44310",
    "addr:street": "Patterson Ave",
    "iso:country": "US",
    "sg:address": "916 Patterson Ave",
    "sg:city": "Akron",
    "sg:classifiers": [
      {
        "category": "Organizations",
        "subcategory": "Religious Organization",
        "type": "Services"
      }
    ],
    "sg:phone": "+1 330 923 5634",
    "sg:postcode": "44310",
    "sg:province": "OH",
    "wof:name": "Apostolic Holy Temple",
    "wof:placetype": "venue"
  },
  "geometry": {"coordinates":[-81.502168,41.109819],"type":"Point"}
}
