{
  "type": "Feature",
  "properties": {
    "iso:country":"US",
    "sg:address":"42005 Butternut Ridge Rd",
    "sg:city":"Elyria",
    "sg:classifiers":[
        {
            "category":"Manufacturing",
            "subcategory":"Metals",
            "type":"Manufacturing & Wholesale Goods"
        }
    ],
    "sg:phone":"+1 440 322 6017",
    "sg:postcode":"44035",
    "sg:province":"OH",
    "sg:tags":[
        "spring",
        "wire",
        "mfg"
    ],
    "wof:name":"James F Jalowiec",
    "wof:placetype":"venue"
},
  "geometry": {"coordinates":[-82.150447,41.313323],"type":"Point"}
}