{
  "type": "Feature",
  "properties": {
    "addr:full": "42005 Butternut Ridge Rd Elyria OH 44035",
    "addr:housenumber": "42005",
    "addr:postcode": "44035",
    "addr:street": "Butternut Ridge Rd",
    "iso:country": "US",
    "sg:address": "42005 Butternut Ridge Rd",
    "sg:city": "Elyria",
    "sg:classifiers": [
      {
        "category": "Manufacturing",
        "subcategory": "Metals",
        "type": "Manufacturing \u0026 Wholesale Goods"
      }
    ],
    "sg:phone": "+1 440 322 6017",
    "sg:postcode": "44035",
    "sg:province": "OH",
    "sg:tags": [
      "spring",
      "wire",
      "mfg"
    ],
    "wof:name": "James F Jalowiec",
    "wof:placetype": "venue"
  },
  "geometry": {"coordinates":[-82.150447,41.313323],"type":"Point"}
}
