{
  "type": "Feature",
  "properties": {
    "iso:country":"US",
    "sg:address":"310 Licking View Dr",
    "sg:city":"Heath",
    "sg:classifiers":[
        {
            "category":"Education",
            "subcategory":"School",
            "type":"Public Place"
        }
    ],
    "sg:phone":"+1 740 788 3200",
    "sg:postcode":"43056",
    "sg:province":"OH",
    "wof:name":"Heath Middle School",
    "wof:placetype":"venue"
},
  "geometry": {"coordinates":[-82.435506,40.025558],"type":"Point"}
}