{
  "type": "Feature",
  "properties": {
    "addr:full": "5660 Foxfire Dr Zanesville OH 43701",
    "addr:housenumber": "5660",
    "addr:postcode": "43701",
    "addr:street": "Foxfire Dr",
    "iso:country": "US",
    "sg:address": "5660 Foxfire Dr",
    "sg:city": "Zanesville",
    "sg:classifiers": [
      {
        "category": "Building \u0026 Trades",
        "subcategory": "Construction",
        "type": "Services"
      }
    ],
    "sg:phone": "+1 740 849 2666",
    "sg:postcode": "43701",
    "sg:province": "OH",
    "sg:tags": [
      "carpentry",
      "contractor"
    ],
    "wof:name": "Searls Custom Cabinets",
    "wof:placetype": "venue"
  },
  "geometry": {"coordinates":[-82.098618,39.882843],"type":"Point"}
}
