{
  "type": "Feature",
  "properties": {
    "iso:country":"US",
    "sg:address":"9396 Montgomery Rd",
    "sg:city":"Cincinnati",
    "sg:classifiers":[
        {
            "category":"Bars & Pubs",
            "type":"Food & Drink"
        }
    ],
    "sg:phone":"+1 513 793 8828",
    "sg:postcode":"45242",
    "sg:province":"OH",
    "sg:tags":[
        "drinking"
    ],
    "wof:name":"J Arthurs",
    "wof:placetype":"venue"
},
  "geometry": {"coordinates":[-84.354726,39.226612],"type":"Point"}
}