{
  "type": "Feature",
  "properties": {
    "addr:full": "9396 Montgomery Rd Cincinnati OH 45242",
    "addr:housenumber": "9396",
    "addr:postcode": "45242",
    "addr:street": "Montgomery Rd",
    "iso:country": "US",
    "sg:address": "9396 Montgomery Rd",
    "sg:city": "Cincinnati",
    "sg:classifiers": [
      {
        "category": "Bars \u0026 Pubs",
        "type": "Food \u0026 Drink"
      }
    ],
    "sg:phone": "+1 513 793 8828",
    "sg:postcode": "45242",
    "sg:province": "OH",
    "sg:tags": [
      "drinking"
    ],
    "wof:name": "J Arthurs",
    "wof:placetype": "venue"
  },
  "geometry": {"coordinates":[-84.354726,39.226612],"type":"Point"}
}
