{
  "type": "Feature",
  "properties": {
    "iso:country":"US",
    "sg:address":"94 Columbus Rd",
    "sg:city":"Athens",
    "sg:classifiers":[
        {
            "category":"Wholesale",
            "subcategory":"Groceries",
            "type":"Manufacturing & Wholesale Goods"
        }
    ],
    "sg:phone":"+1 740 589 6456",
    "sg:postcode":"45701",
    "sg:province":"OH",
    "sg:tags":[
        "food",
        "product"
    ],
    "wof:name":"Milo's Whole World Gourmet",
    "wof:placetype":"venue"
},
  "geometry": {"coordinates":[-82.102128,39.340882],"type":"Point"}
}