{
  "type": "Feature",
  "properties": {
    "addr:full": "7957 Euclid Ave Cleveland OH 44103",
    "addr:housenumber": "7957",
    "addr:postcode": "44103",
    "addr:street": "Euclid Ave",
    "iso:country": "US",
    "sg:address": "7957 Euclid Ave",
    "sg:city": "Cleveland",
    "sg:classifiers": [
      {
        "category": "Social Services",
        "subcategory": "Child Care",
        "type": "Services"
      }
    ],
    "sg:phone": "+1 216 229 7890",
    "sg:postcode": "44103",
    "sg:province": "OH",
    "wof:name": "All His Children",
    "wof:placetype": "venue"
  },
  "geometry": {"coordinates":[-81.632403,41.50383],"type":"Point"}
}
