{
  "type": "Feature",
  "properties": {
    "addr:full": "2779 Alkire Rd Grove City OH 43123",
    "addr:housenumber": "2779",
    "addr:postcode": "43123",
    "addr:street": "Alkire Rd",
    "iso:country": "US",
    "sg:address": "2779 Alkire Rd",
    "sg:city": "Grove City",
    "sg:classifiers": [
      {
        "category": "Organizations",
        "subcategory": "Religious Organization",
        "type": "Services"
      }
    ],
    "sg:phone": "+1 614 875 1028",
    "sg:postcode": "43123",
    "sg:province": "OH",
    "sg:tags": [
      "church"
    ],
    "sg:website": "www.alkirechurchofchrist.com",
    "wof:name": "Alkire Road Church Of Christ",
    "wof:placetype": "venue"
  },
  "geometry": {"coordinates":[-83.076642,39.916715],"type":"Point"}
}
