{
  "type": "Feature",
  "properties": {
    "iso:country":"US",
    "sg:address":"2779 Alkire Rd",
    "sg:city":"Grove City",
    "sg:classifiers":[
        {
            "category":"Organizations",
            "subcategory":"Religious Organization",
            "type":"Services"
        }
    ],
    "sg:phone":"+1 614 875 1028",
    "sg:postcode":"43123",
    "sg:province":"OH",
    "sg:tags":[
        "church"
    ],
    "sg:website":"www.alkirechurchofchrist.com",
    "wof:name":"Alkire Road Church Of Christ",
    "wof:placetype":"venue"
},
  "geometry": {"coordinates":[-83.07664200000001,39.916715],"type":"Point"}
}