{
  "type": "Feature",
  "properties": {
    "addr:full":"3822 Victory Ave NE Louisville OH 44641",
    "addr:housenumber":"3822",
    "addr:postcode":"44641",
    "addr:street":"Victory Ave Ne",
    "iso:country":"US",
    "sg:address":"3822 Victory Ave NE",
    "sg:city":"Louisville",
    "sg:classifiers":[
        {
            "category":"Manufacturing",
            "subcategory":"Tools & Machinery",
            "type":"Manufacturing & Wholesale Goods"
        }
    ],
    "sg:phone":"+1 330 456 8281",
    "sg:postcode":"44641",
    "sg:province":"OH",
    "sg:tags":[
        "machine",
        "shop",
        "job"
    ],
    "wof:name":"Salco Machine Inc",
    "wof:placetype":"venue"
},
  "geometry": {"coordinates":[-81.306714,40.833189],"type":"Point"}
}