{
  "type": "Feature",
  "properties": {
    "addr:full": "2429 Cherry Ave Alliance OH 44601",
    "addr:housenumber": "2429",
    "addr:postcode": "44601",
    "addr:street": "Cherry Ave",
    "iso:country": "US",
    "sg:address": "2429 Cherry Ave",
    "sg:city": "Alliance",
    "sg:classifiers": [
      {
        "category": "Shopping",
        "subcategory": "Luggage \u0026 Leather Goods",
        "type": "Retail Goods"
      }
    ],
    "sg:phone": "+1 330 823 2182",
    "sg:postcode": "44601",
    "sg:province": "OH",
    "wof:name": "Tanner's Leather",
    "wof:placetype": "venue"
  },
  "geometry": {"coordinates":[-81.104789,40.898443],"type":"Point"}
}
