{
  "type": "Feature",
  "properties": {
    "addr:full":"1546 N Main St Marion OH 43302",
    "addr:housenumber":"1546",
    "addr:postcode":"43302",
    "addr:street":"N Main St",
    "iso:country":"US",
    "sg:address":"1546 N Main St",
    "sg:city":"Marion",
    "sg:classifiers":[
        {
            "category":"Professional",
            "type":"Services"
        }
    ],
    "sg:phone":"+1 740 387 4102",
    "sg:postcode":"43302",
    "sg:province":"OH",
    "sg:tags":[
        "establishment"
    ],
    "wof:name":"K Tac Corp",
    "wof:placetype":"venue"
},
  "geometry": {"coordinates":[-83.13144,40.617007],"type":"Point"}
}