{
  "type": "Feature",
  "properties": {
    "addr:full": "3150 Fairfax Rd Cleveland OH 44118",
    "addr:housenumber": "3150",
    "addr:postcode": "44118",
    "addr:street": "Fairfax Rd",
    "iso:country": "US",
    "sg:address": "3150 Fairfax Rd",
    "sg:city": "Cleveland",
    "sg:classifiers": [
      {
        "category": "Social Services",
        "type": "Services"
      }
    ],
    "sg:phone": "+1 216 458 1158",
    "sg:postcode": "44118",
    "sg:province": "OH",
    "sg:tags": [
      "youth",
      "organization",
      "center"
    ],
    "wof:name": "Heights Youth Ctr",
    "wof:placetype": "venue"
  },
  "geometry": {"coordinates":[-81.566782,41.492513],"type":"Point"}
}
