{
  "type": "Feature",
  "properties": {
    "addr:full": "152 Main St Painesville OH 44077",
    "addr:housenumber": "152",
    "addr:postcode": "44077",
    "addr:street": "Main St",
    "iso:country": "US",
    "sg:address": "152 Main St",
    "sg:city": "Painesville",
    "sg:classifiers": [
      {
        "category": "Professional",
        "subcategory": "Lawyer \u0026 Legal Services",
        "type": "Services"
      }
    ],
    "sg:phone": "+1 440 352 3003",
    "sg:postcode": "44077",
    "sg:province": "OH",
    "sg:tags": [
      "attorney"
    ],
    "wof:name": "Ziegler Metzger \u0026 Miller",
    "wof:placetype": "venue"
  },
  "geometry": {"coordinates":[-81.241412,41.725865],"type":"Point"}
}
