{
  "type": "Feature",
  "properties": {
    "addr:full": "6635 Taylor Rd SW Reynoldsburg OH 43062",
    "addr:housenumber": "6635",
    "addr:postcode": "43062",
    "addr:street": "Taylor Rd Sw",
    "iso:country": "US",
    "sg:address": "6635 Taylor Rd SW",
    "sg:city": "Reynoldsburg",
    "sg:classifiers": [
      {
        "category": "Manufacturing",
        "subcategory": "Tools \u0026 Machinery",
        "type": "Manufacturing \u0026 Wholesale Goods"
      }
    ],
    "sg:phone": "+1 614 864 1116",
    "sg:postcode": "43062",
    "sg:province": "OH",
    "sg:tags": [
      "machine",
      "shop"
    ],
    "sg:website": "www.dana.com",
    "wof:name": "Dana Corporations",
    "wof:placetype": "venue"
  },
  "geometry": {"coordinates":[-82.767347,39.997148],"type":"Point"}
}
