{
  "type": "Feature",
  "properties": {
    "addr:full":"1258 Grandview Ave Columbus OH 43212",
    "addr:housenumber":"1258",
    "addr:postcode":"43212",
    "addr:street":"Grandview Ave",
    "iso:country":"US",
    "sg:address":"1258 Grandview Ave",
    "sg:city":"Columbus",
    "sg:classifiers":[
        {
            "category":"Insurance",
            "subcategory":"Insurance Agent",
            "type":"Services"
        }
    ],
    "sg:phone":"+1 614 486 3276",
    "sg:postcode":"43212",
    "sg:province":"OH",
    "sg:tags":[
        "agency"
    ],
    "wof:name":"State Farm Insurance",
    "wof:placetype":"venue"
},
  "geometry": {"coordinates":[-83.044842,39.982902],"type":"Point"}
}