{
  "type": "Feature",
  "properties": {
    "iso:country":"US",
    "sg:address":"8819 King Rd",
    "sg:city":"Lakeview",
    "sg:classifiers":[
        {
            "category":"Recreation",
            "subcategory":"Amusement Park",
            "type":"Entertainment"
        }
    ],
    "sg:phone":"+1 937 842 6460",
    "sg:postcode":"43331",
    "sg:province":"OH",
    "sg:tags":[
        "park"
    ],
    "wof:name":"Point Amusement Inc",
    "wof:placetype":"venue"
},
  "geometry": {"coordinates":[-83.85816699999999,40.522294],"type":"Point"}
}