{
  "type": "Feature",
  "properties": {
    "iso:country":"US",
    "sg:address":"1111 Parkman Rd NW",
    "sg:city":"Warren",
    "sg:classifiers":[
        {
            "category":"Building & Trades",
            "subcategory":"Equipment Rental",
            "type":"Services"
        }
    ],
    "sg:phone":"+1 330 393 8444",
    "sg:postcode":"44485",
    "sg:province":"OH",
    "sg:tags":[
        "yard"
    ],
    "sg:website":"www.rentway.com",
    "wof:name":"Rent Way",
    "wof:placetype":"venue"
},
  "geometry": {"coordinates":[-80.83729,41.241192],"type":"Point"}
}