{
  "type": "Feature",
  "properties": {
    "addr:full": "5511 State Rte 613 Mc Comb OH 45858",
    "addr:housenumber": "5511",
    "addr:postcode": "45858",
    "addr:street": "State Rte 613",
    "iso:country": "US",
    "sg:address": "5511 State Rte 613",
    "sg:city": "Mc Comb",
    "sg:classifiers": [
      {
        "category": "Manufacturing",
        "subcategory": "Glass \u0026 Minerals",
        "type": "Manufacturing \u0026 Wholesale Goods"
      }
    ],
    "sg:phone": "+1 419 293 2937",
    "sg:postcode": "45858",
    "sg:province": "OH",
    "sg:tags": [
      "ready",
      "concrete",
      "mfg"
    ],
    "wof:name": "K \u0026 L Ready Mix Inc",
    "wof:placetype": "venue"
  },
  "geometry": {"coordinates":[-83.772529,41.109801],"type":"Point"}
}
