{
  "type": "Feature",
  "properties": {
    "iso:country":"US",
    "sg:address":"5511 State Rte 613",
    "sg:city":"Mc Comb",
    "sg:classifiers":[
        {
            "category":"Manufacturing",
            "subcategory":"Glass & Minerals",
            "type":"Manufacturing & Wholesale Goods"
        }
    ],
    "sg:phone":"+1 419 293 2937",
    "sg:postcode":"45858",
    "sg:province":"OH",
    "sg:tags":[
        "ready",
        "concrete",
        "mfg"
    ],
    "wof:name":"K & L Ready Mix Inc",
    "wof:placetype":"venue"
},
  "geometry": {"coordinates":[-83.77252900000001,41.109801],"type":"Point"}
}