{
  "type": "Feature",
  "properties": {
    "addr:full": "7753 Hidden Valley Dr Willoughby OH 44094",
    "addr:housenumber": "7753",
    "addr:postcode": "44094",
    "addr:street": "Hidden Valley Dr",
    "iso:country": "US",
    "sg:address": "7753 Hidden Valley Dr",
    "sg:city": "Willoughby",
    "sg:classifiers": [
      {
        "category": "Professional",
        "type": "Services"
      }
    ],
    "sg:phone": "+1 440 256 4171",
    "sg:postcode": "44094",
    "sg:province": "OH",
    "wof:name": "Call For Care LLC",
    "wof:placetype": "venue"
  },
  "geometry": {"coordinates":[-81.366292,41.571202],"type":"Point"}
}
