{
  "type": "Feature",
  "properties": {
    "addr:full":"9567 Colerain Ave Cincinnati OH 45251",
    "addr:housenumber":"9567",
    "addr:postcode":"45251",
    "addr:street":"Colerain Ave",
    "iso:country":"US",
    "sg:address":"9567 Colerain Ave",
    "sg:city":"Cincinnati",
    "sg:classifiers":[
        {
            "category":"Shopping",
            "subcategory":"Jewelry",
            "type":"Retail Goods"
        }
    ],
    "sg:phone":"+1 513 385 7573",
    "sg:postcode":"45251",
    "sg:province":"OH",
    "sg:tags":[
        "jeweler"
    ],
    "wof:name":"Whitehall Co Jewellers",
    "wof:placetype":"venue"
},
  "geometry": {"coordinates":[-84.59651100000001,39.247591],"type":"Point"}
}