{
  "type": "Feature",
  "properties": {
    "addr:full": "6070 W Chester Rd West Chester OH 45069",
    "addr:housenumber": "6070",
    "addr:postcode": "45069",
    "addr:street": "W Chester Rd",
    "iso:country": "US",
    "sg:address": "6070 W Chester Rd",
    "sg:city": "West Chester",
    "sg:classifiers": [
      {
        "category": "Banks \u0026 Credit Unions",
        "subcategory": "Bank",
        "type": "Services"
      }
    ],
    "sg:phone": "+1 513 874 7311",
    "sg:postcode": "45069",
    "sg:province": "OH",
    "sg:tags": [
      "loan",
      "real estate"
    ],
    "wof:name": "Countrywide Home Loans",
    "wof:placetype": "venue"
  },
  "geometry": {"coordinates":[-84.434496,39.32957],"type":"Point"}
}
