{
  "type": "Feature",
  "properties": {
    "iso:country":"US",
    "sg:address":"860 Greenfield Dr",
    "sg:city":"Columbus",
    "sg:classifiers":[
        {
            "category":"Autos & Motor Vehicles",
            "subcategory":"Automobile Sales",
            "type":"Retail Goods"
        }
    ],
    "sg:phone":"+1 614 220 0883",
    "sg:postcode":"43223",
    "sg:province":"OH",
    "sg:tags":[
        "car",
        "dealer"
    ],
    "wof:name":"Francis & Sons Auto Shop",
    "wof:placetype":"venue"
},
  "geometry": {"coordinates":[-83.020556,39.940945],"type":"Point"}
}