{
  "type": "Feature",
  "properties": {
    "addr:full":"1463 Mentor Ave Painesville OH 44077",
    "addr:housenumber":"1463",
    "addr:postcode":"44077",
    "addr:street":"Mentor Ave",
    "iso:country":"US",
    "sg:address":"1463 Mentor Ave",
    "sg:city":"Painesville",
    "sg:classifiers":[
        {
            "category":"Bars & Pubs",
            "type":"Food & Drink"
        }
    ],
    "sg:phone":"+1 440 354 2758",
    "sg:postcode":"44077",
    "sg:province":"OH",
    "wof:name":"Mc Taggart's Lounge",
    "wof:placetype":"venue"
},
  "geometry": {"coordinates":[-81.274947,41.70136],"type":"Point"}
}