{
  "type": "Feature",
  "properties": {
    "iso:country":"US",
    "sg:address":"2639 Market St",
    "sg:city":"Youngstown",
    "sg:classifiers":[
        {
            "category":"Restaurant",
            "type":"Food & Drink"
        }
    ],
    "sg:phone":"+1 330 788 8299",
    "sg:postcode":"44507",
    "sg:province":"OH",
    "sg:tags":[
        "eating"
    ],
    "wof:name":"Home Cookin",
    "wof:placetype":"venue"
},
  "geometry": {"coordinates":[-80.657382,41.072953],"type":"Point"}
}