{
  "type": "Feature",
  "properties": {
    "addr:full":"1508 W River Rd N Elyria OH 44035",
    "addr:housenumber":"1508",
    "addr:postcode":"44035",
    "addr:street":"W River Rd N",
    "iso:country":"US",
    "sg:address":"1508 W River Rd N",
    "sg:city":"Elyria",
    "sg:classifiers":[
        {
            "category":"Restaurant",
            "type":"Food & Drink"
        }
    ],
    "sg:menulink":"http://www.allmenus.com/oh/elyria/170252-burger-king/menu/",
    "sg:phone":"+1 440 324 6050",
    "sg:postcode":"44035",
    "sg:province":"OH",
    "sg:tags":[
        "burger",
        "american"
    ],
    "wof:name":"Burger King",
    "wof:placetype":"venue"
},
  "geometry": {"coordinates":[-82.106307,41.393789],"type":"Point"}
}