{
  "type": "Feature",
  "properties": {
    "iso:country":"US",
    "sg:address":"2742 Twp Hwy 220",
    "sg:city":"Bloomingdale",
    "sg:classifiers":[
        {
            "category":"Retail",
            "subcategory":"Auto Repair",
            "type":"Services"
        }
    ],
    "sg:phone":"+1 740 765 5595",
    "sg:postcode":"43910",
    "sg:province":"OH",
    "sg:tags":[
        "muffler",
        "exhaust",
        "system"
    ],
    "wof:name":"B & D Small Engine & Exhaust",
    "wof:placetype":"venue"
},
  "geometry": {"coordinates":[-80.831977,40.441176],"type":"Point"}
}