{
  "type": "Feature",
  "properties": {
    "addr:full": "523 W Riverview Ave Napoleon OH 43545",
    "addr:housenumber": "523",
    "addr:postcode": "43545",
    "addr:street": "W Riverview Ave",
    "iso:country": "US",
    "sg:address": "523 W Riverview Ave",
    "sg:city": "Napoleon",
    "sg:classifiers": [
      {
        "category": "Real Estate",
        "subcategory": "Surveying",
        "type": "Services"
      }
    ],
    "sg:phone": "+1 419 592 0771",
    "sg:postcode": "43545",
    "sg:province": "OH",
    "sg:tags": [
      "surveyor"
    ],
    "wof:name": "Paul J Westhoven Surveyor",
    "wof:placetype": "venue"
  },
  "geometry": {"coordinates":[-84.131562,41.385],"type":"Point"}
}
