{
  "type": "Feature",
  "properties": {
    "addr:full": "9455 Creaser Rd North Bloomfield OH 44450",
    "addr:postcode": "9455;44450",
    "addr:street": "Creaser Rd",
    "iso:country": "US",
    "sg:address": "9455 Creaser Rd",
    "sg:city": "North Bloomfield",
    "sg:classifiers": [
      {
        "category": "Building \u0026 Trades",
        "subcategory": "Construction",
        "type": "Services"
      }
    ],
    "sg:phone": "+1 440 685 4786",
    "sg:postcode": "44450",
    "sg:province": "OH",
    "sg:tags": [
      "woodworker"
    ],
    "wof:name": "Kauffman Woodworking",
    "wof:placetype": "venue"
  },
  "geometry": {"coordinates":[-80.877944,41.480612],"type":"Point"}
}
