{
  "type": "Feature",
  "properties": {
    "addr:full":"7224 State Rte 734 Jamestown OH 45335",
    "addr:housenumber":"7224",
    "addr:postcode":"45335",
    "addr:street":"State Rte 734",
    "iso:country":"US",
    "sg:address":"7224 State Rte 734",
    "sg:city":"Jamestown",
    "sg:classifiers":[
        {
            "category":"Personal",
            "subcategory":"Beauty Salon",
            "type":"Services"
        }
    ],
    "sg:phone":"+1 937 376 3464",
    "sg:postcode":"45335",
    "sg:province":"OH",
    "wof:name":"Sophisticates Hair Salon",
    "wof:placetype":"venue"
},
  "geometry": {"coordinates":[-83.668004,39.654403],"type":"Point"}
}