{
  "type": "Feature",
  "properties": {
    "addr:full":"25570 Dixie Hwy Perrysburg OH 43551",
    "addr:housenumber":"25570",
    "addr:postcode":"43551",
    "addr:street":"Dixie Hwy",
    "iso:country":"US",
    "sg:address":"25570 Dixie Hwy",
    "sg:city":"Perrysburg",
    "sg:classifiers":[
        {
            "category":"Deli",
            "type":"Food & Drink"
        }
    ],
    "sg:menulink":"http://www.allmenus.com/oh/perrysburg/126514-blimpie-subs--sandwiches/menu/",
    "sg:phone":"+1 419 873 9484",
    "sg:postcode":"43551",
    "sg:province":"OH",
    "sg:tags":[
        "wrap",
        "american",
        "sandwich"
    ],
    "wof:name":"Blimpie Subs & Sandwiches",
    "wof:placetype":"venue"
},
  "geometry": {"coordinates":[-83.63746399999999,41.524547],"type":"Point"}
}