{
  "type": "Feature",
  "properties": {
    "addr:full":"14641 Twp Rd 89 Wapakoneta OH 45895",
    "addr:housenumber":"89",
    "addr:postcode":"14641;45895",
    "addr:street":"Twp Rd",
    "iso:country":"US",
    "sg:address":"14641 Twp Rd 89",
    "sg:city":"Wapakoneta",
    "sg:phone":"+1 419 568 2344",
    "sg:postcode":"45895",
    "sg:province":"OH",
    "sg:tags":[
        "farm",
        "grain",
        "wheat",
        "cash",
        "soybean"
    ],
    "wof:name":"Bernard Andrews",
    "wof:placetype":"venue"
},
  "geometry": {"coordinates":[-83.968943,40.527878],"type":"Point"}
}