{
  "type": "Feature",
  "properties": {
    "addr:full": "119 W Spring St St Marys OH 45885",
    "addr:housenumber": "119",
    "addr:postcode": "45885",
    "addr:street": "W Spring St",
    "iso:country": "US",
    "sg:address": "119 W Spring St",
    "sg:city": "St Marys",
    "sg:classifiers": [
      {
        "category": "Restaurant",
        "type": "Food \u0026 Drink"
      }
    ],
    "sg:phone": "+1 419 394 5944",
    "sg:postcode": "45885",
    "sg:province": "OH",
    "sg:tags": [
      "banquet",
      "rooms"
    ],
    "wof:name": "St Mary's Theatre",
    "wof:placetype": "venue"
  },
  "geometry": {"coordinates":[-84.388388,40.542906],"type":"Point"}
}
