{
  "type": "Feature",
  "properties": {
    "iso:country":"US",
    "sg:address":"119 W Spring St",
    "sg:city":"St Marys",
    "sg:classifiers":[
        {
            "category":"Restaurant",
            "type":"Food & Drink"
        }
    ],
    "sg:phone":"+1 419 394 5944",
    "sg:postcode":"45885",
    "sg:province":"OH",
    "sg:tags":[
        "banquet",
        "rooms"
    ],
    "wof:name":"St Mary's Theatre",
    "wof:placetype":"venue"
},
  "geometry": {"coordinates":[-84.38838800000001,40.542906],"type":"Point"}
}