{
  "type": "Feature",
  "properties": {
    "addr:full": "1535 Madison Ave Wooster OH 44691",
    "addr:housenumber": "1535",
    "addr:postcode": "44691",
    "addr:street": "Madison Ave",
    "iso:country": "US",
    "sg:address": "1535 Madison Ave",
    "sg:city": "Wooster",
    "sg:classifiers": [
      {
        "category": "Restaurant",
        "type": "Food \u0026 Drink"
      }
    ],
    "sg:phone": "+1 440 272 5552",
    "sg:postcode": "44691",
    "sg:province": "OH",
    "wof:name": "Sue-Min's Chinese Gourmet",
    "wof:placetype": "venue"
  },
  "geometry": {"coordinates":[-81.931734,40.781354],"type":"Point"}
}
