{
  "type": "Feature",
  "properties": {
    "addr:full": "28501 Bradner Rd Millbury OH 43447",
    "addr:postcode": "28501;43447",
    "addr:street": "Bradner Rd",
    "iso:country": "US",
    "sg:address": "28501 Bradner Rd",
    "sg:city": "Millbury",
    "sg:phone": "+1 419 836 1188",
    "sg:postcode": "43447",
    "sg:province": "OH",
    "sg:tags": [
      "farm",
      "corn",
      "soybean"
    ],
    "wof:name": "Theodore Wasserman",
    "wof:placetype": "venue"
  },
  "geometry": {"coordinates":[-83.434692,41.564858],"type":"Point"}
}
