{
  "type": "Feature",
  "properties": {
    "addr:full":"1632 Kasserine Ct Twinsburg OH 44087",
    "addr:housenumber":"1632",
    "addr:postcode":"44087",
    "addr:street":"Kasserine Ct",
    "iso:country":"US",
    "sg:address":"1632 Kasserine Ct",
    "sg:city":"Twinsburg",
    "sg:classifiers":[
        {
            "category":"Building & Trades",
            "subcategory":"Construction",
            "type":"Services"
        }
    ],
    "sg:phone":"+1 330 405 6545",
    "sg:postcode":"44087",
    "sg:province":"OH",
    "sg:tags":[
        "house"
    ],
    "wof:name":"Evergreen Home Improvement Co",
    "wof:placetype":"venue"
},
  "geometry": {"coordinates":[-81.469947,41.343936],"type":"Point"}
}