{
  "type": "Feature",
  "properties": {
    "iso:country":"US",
    "sg:address":"3612 E 116th St",
    "sg:city":"Cleveland",
    "sg:classifiers":[
        {
            "category":"Shopping",
            "subcategory":"Books",
            "type":"Retail Goods"
        }
    ],
    "sg:phone":"+1 216 752 4463",
    "sg:postcode":"44105",
    "sg:province":"OH",
    "sg:tags":[
        "dealer"
    ],
    "wof:name":"Agape Christian Books",
    "wof:placetype":"venue"
},
  "geometry": {"coordinates":[-81.602932,41.460906],"type":"Point"}
}