{
  "type": "Feature",
  "properties": {
    "iso:country":"US",
    "sg:address":"10794 Strausser St NW",
    "sg:city":"Canal Fulton",
    "sg:classifiers":[
        {
            "category":"Farming",
            "subcategory":"Dairy Farm",
            "type":"Manufacturing & Wholesale Goods"
        }
    ],
    "sg:phone":"+1 330 854 4004",
    "sg:postcode":"44614",
    "sg:province":"OH",
    "wof:name":"Dale Rohr",
    "wof:placetype":"venue"
},
  "geometry": {"coordinates":[-81.565659,40.896642],"type":"Point"}
}