{
  "type": "Feature",
  "properties": {
    "addr:full": "1328 Dublin Rd Columbus OH 43215",
    "addr:housenumber": "1328",
    "addr:postcode": "43215",
    "addr:street": "Dublin Rd",
    "iso:country": "US",
    "sg:address": "1328 Dublin Rd",
    "sg:city": "Columbus",
    "sg:classifiers": [
      {
        "category": "Insurance",
        "subcategory": "Insurance Agent",
        "type": "Services"
      }
    ],
    "sg:phone": "+1 614 486 9260",
    "sg:postcode": "43215",
    "sg:province": "OH",
    "wof:name": "Ward Connolly \u0026 Hodges",
    "wof:placetype": "venue"
  },
  "geometry": {"coordinates":[-83.052917,39.9748],"type":"Point"}
}
