{
  "type": "Feature",
  "properties": {
    "iso:country":"US",
    "sg:address":"419 W Market St",
    "sg:city":"Sandusky",
    "sg:classifiers":[
        {
            "category":"Social Services",
            "subcategory":"Job Training",
            "type":"Services"
        }
    ],
    "sg:phone":"+1 419 625 4744",
    "sg:postcode":"44870",
    "sg:province":"OH",
    "sg:tags":[
        "rehabilitation"
    ],
    "wof:name":"Goodwill Industries",
    "wof:placetype":"venue"
},
  "geometry": {"coordinates":[-82.714247,41.455318],"type":"Point"}
}