{
  "type": "Feature",
  "properties": {
    "addr:full": "6400 Dublin Park Dr Dublin OH 43016",
    "addr:housenumber": "6400",
    "addr:postcode": "43016",
    "addr:street": "Dublin Park Dr",
    "iso:country": "US",
    "sg:address": "6400 Dublin Park Dr",
    "sg:city": "Dublin",
    "sg:classifiers": [
      {
        "category": "Arena",
        "subcategory": "Sports Club",
        "type": "Entertainment"
      }
    ],
    "sg:phone": "+1 614 791 7849",
    "sg:postcode": "43016",
    "sg:province": "OH",
    "wof:name": "Sports Ohio",
    "wof:placetype": "venue"
  },
  "geometry": {"coordinates":[-83.185122,40.099682],"type":"Point"}
}
