{
  "type": "Feature",
  "properties": {
    "iso:country":"US",
    "sg:address":"2534 Milton St SE",
    "sg:city":"Warren",
    "sg:classifiers":[
        {
            "category":"Organizations",
            "subcategory":"Religious Organization",
            "type":"Services"
        }
    ],
    "sg:phone":"+1 330 369 5153",
    "sg:postcode":"44484",
    "sg:province":"OH",
    "sg:tags":[
        "church"
    ],
    "wof:name":"St James Catholic Church White",
    "wof:placetype":"venue"
},
  "geometry": {"coordinates":[-80.789418,41.220481],"type":"Point"}
}