{
  "type": "Feature",
  "properties": {
    "addr:full": "3151 Libra Ln Cincinnati OH 45251",
    "addr:housenumber": "3151",
    "addr:postcode": "45251",
    "addr:street": "Libra Ln",
    "iso:country": "US",
    "sg:address": "3151 Libra Ln",
    "sg:city": "Cincinnati",
    "sg:classifiers": [
      {
        "category": "Wholesale",
        "subcategory": "Electrical",
        "type": "Manufacturing \u0026 Wholesale Goods"
      }
    ],
    "sg:phone": "+1 513 521 0756",
    "sg:postcode": "45251",
    "sg:province": "OH",
    "sg:tags": [
      "electronic"
    ],
    "wof:name": "Route 35 Sales",
    "wof:placetype": "venue"
  },
  "geometry": {"coordinates":[-84.582256,39.241179],"type":"Point"}
}
