{
  "type": "Feature",
  "properties": {
    "addr:full": "1354 Park Ave W Mansfield OH 44906",
    "addr:housenumber": "1354",
    "addr:postcode": "44906",
    "addr:street": "Park Ave W",
    "iso:country": "US",
    "sg:address": "1354 Park Ave W",
    "sg:city": "Mansfield",
    "sg:classifiers": [
      {
        "category": "Restaurant",
        "type": "Food \u0026 Drink"
      }
    ],
    "sg:phone": "+1 419 529 5960",
    "sg:postcode": "44906",
    "sg:province": "OH",
    "sg:tags": [
      "eating"
    ],
    "wof:name": "Tee Jays Country Place",
    "wof:placetype": "venue"
  },
  "geometry": {"coordinates":[-82.564914,40.759526],"type":"Point"}
}
