{
  "type": "Feature",
  "properties": {
    "iso:country":"US",
    "sg:address":"12810 Shaw Ave",
    "sg:city":"Cleveland",
    "sg:classifiers":[
        {
            "category":"Restaurant",
            "type":"Food & Drink"
        }
    ],
    "sg:phone":"+1 216 541 4116",
    "sg:postcode":"44108",
    "sg:province":"OH",
    "sg:tags":[
        "out"
    ],
    "wof:name":"Shaw Dairy",
    "wof:placetype":"venue"
},
  "geometry": {"coordinates":[-81.593259,41.540695],"type":"Point"}
}