{
  "type": "Feature",
  "properties": {
    "addr:full": "12810 Shaw Ave Cleveland OH 44108",
    "addr:housenumber": "12810",
    "addr:postcode": "44108",
    "addr:street": "Shaw Ave",
    "iso:country": "US",
    "sg:address": "12810 Shaw Ave",
    "sg:city": "Cleveland",
    "sg:classifiers": [
      {
        "category": "Restaurant",
        "type": "Food \u0026 Drink"
      }
    ],
    "sg:phone": "+1 216 541 4116",
    "sg:postcode": "44108",
    "sg:province": "OH",
    "sg:tags": [
      "out"
    ],
    "wof:name": "Shaw Dairy",
    "wof:placetype": "venue"
  },
  "geometry": {"coordinates":[-81.593259,41.540695],"type":"Point"}
}
