{
  "type": "Feature",
  "properties": {
    "iso:country":"US",
    "sg:address":"2384 Blizzard Ln",
    "sg:city":"Albany",
    "sg:classifiers":[
        {
            "category":"Restaurant",
            "type":"Food & Drink"
        }
    ],
    "sg:phone":"+1 740 698 2384",
    "sg:postcode":"45710",
    "sg:province":"OH",
    "sg:tags":[
        "eating"
    ],
    "wof:name":"Dairy Queen",
    "wof:placetype":"venue"
},
  "geometry": {"coordinates":[-82.193735,39.235534],"type":"Point"}
}