{
  "type": "Feature",
  "properties": {
    "addr:full": "2384 Blizzard Ln Albany OH 45710",
    "addr:housenumber": "2384",
    "addr:postcode": "45710",
    "addr:street": "Blizzard Ln",
    "iso:country": "US",
    "sg:address": "2384 Blizzard Ln",
    "sg:city": "Albany",
    "sg:classifiers": [
      {
        "category": "Restaurant",
        "type": "Food \u0026 Drink"
      }
    ],
    "sg:phone": "+1 740 698 2384",
    "sg:postcode": "45710",
    "sg:province": "OH",
    "sg:tags": [
      "eating"
    ],
    "wof:name": "Dairy Queen",
    "wof:placetype": "venue"
  },
  "geometry": {"coordinates":[-82.193735,39.235534],"type":"Point"}
}
