{
  "type": "Feature",
  "properties": {
    "addr:full": "301 Country Club Rd Rayland OH 43907",
    "addr:housenumber": "301",
    "addr:postcode": "43907",
    "addr:street": "Country Club Rd",
    "iso:country": "US",
    "sg:address": "301 Country Club Rd",
    "sg:city": "Rayland",
    "sg:classifiers": [
      {
        "category": "Sports \u0026 Exercise",
        "subcategory": "Golf",
        "type": "Entertainment"
      }
    ],
    "sg:phone": "+1 740 859 5028",
    "sg:postcode": "43907",
    "sg:province": "OH",
    "sg:tags": [
      "course",
      "public"
    ],
    "wof:name": "Paradise Hills Golf Course",
    "wof:placetype": "venue"
  },
  "geometry": {"coordinates":[-80.994856,40.269502],"type":"Point"}
}
