{
  "type": "Feature",
  "properties": {
    "iso:country":"US",
    "sg:address":"301 Country Club Rd",
    "sg:city":"Rayland",
    "sg:classifiers":[
        {
            "category":"Sports & Exercise",
            "subcategory":"Golf",
            "type":"Entertainment"
        }
    ],
    "sg:phone":"+1 740 859 5028",
    "sg:postcode":"43907",
    "sg:province":"OH",
    "sg:tags":[
        "course",
        "public"
    ],
    "wof:name":"Paradise Hills Golf Course",
    "wof:placetype":"venue"
},
  "geometry": {"coordinates":[-80.994856,40.269502],"type":"Point"}
}