{
  "type": "Feature",
  "properties": {
    "addr:full":"27701 Detroit Rd Cleveland OH 44145",
    "addr:housenumber":"27701",
    "addr:postcode":"44145",
    "addr:street":"Detroit Rd",
    "iso:country":"US",
    "sg:address":"27701 Detroit Rd",
    "sg:city":"Cleveland",
    "sg:classifiers":[
        {
            "category":"Real Estate",
            "subcategory":"Real Estate Operator",
            "type":"Services"
        }
    ],
    "sg:phone":"+1 440 899 9982",
    "sg:postcode":"44145",
    "sg:province":"OH",
    "sg:tags":[
        "building",
        "apartment"
    ],
    "wof:name":"Remington Apartments",
    "wof:placetype":"venue"
},
  "geometry": {"coordinates":[-81.93037699999999,41.465888],"type":"Point"}
}