{
  "type": "Feature",
  "properties": {
    "addr:full": "140 Rogers St Xenia OH 45385",
    "addr:housenumber": "140",
    "addr:postcode": "45385",
    "addr:street": "Rogers St",
    "iso:country": "US",
    "sg:address": "140 Rogers St",
    "sg:city": "Xenia",
    "sg:classifiers": [
      {
        "category": "Health Services",
        "subcategory": "Doctor",
        "type": "Services"
      }
    ],
    "sg:phone": "+1 937 426 4511",
    "sg:postcode": "45385",
    "sg:province": "OH",
    "sg:tags": [
      "dentist"
    ],
    "wof:name": "Miami Valley Prosthodontics",
    "wof:placetype": "venue"
  },
  "geometry": {"coordinates":[-83.928082,39.675872],"type":"Point"}
}
