{
  "type": "Feature",
  "properties": {
    "addr:full": "1720 Wood Rd Cleveland OH 44121",
    "addr:housenumber": "1720",
    "addr:postcode": "44121",
    "addr:street": "Wood Rd",
    "iso:country": "US",
    "sg:address": "1720 Wood Rd",
    "sg:city": "Cleveland",
    "sg:classifiers": [
      {
        "category": "Professional",
        "type": "Services"
      }
    ],
    "sg:phone": "+1 216 381 1009",
    "sg:postcode": "44121",
    "sg:province": "OH",
    "wof:name": "Bettie L Ferrell",
    "wof:placetype": "venue"
  },
  "geometry": {"coordinates":[-81.543683,41.517724],"type":"Point"}
}
