{
  "type": "Feature",
  "properties": {
    "iso:country":"US",
    "sg:address":"142 Arlington Ave NW",
    "sg:city":"Canton",
    "sg:classifiers":[
        {
            "category":"Organizations",
            "subcategory":"Religious Organization",
            "type":"Services"
        }
    ],
    "sg:phone":"+1 330 455 4028",
    "sg:postcode":"44708",
    "sg:province":"OH",
    "sg:tags":[
        "church"
    ],
    "wof:name":"Pentecostal Assembly Church",
    "wof:placetype":"venue"
},
  "geometry": {"coordinates":[-81.40054600000001,40.800734],"type":"Point"}
}