{
  "type": "Feature",
  "properties": {
    "addr:full": "426 Acacia Dr Willowick OH 44095",
    "addr:housenumber": "426",
    "addr:postcode": "44095",
    "addr:street": "Acacia Dr",
    "iso:country": "US",
    "sg:address": "426 Acacia Dr",
    "sg:city": "Willowick",
    "sg:classifiers": [
      {
        "category": "Building \u0026 Trades",
        "subcategory": "Plumbing",
        "type": "Services"
      }
    ],
    "sg:phone": "+1 440 585 1042",
    "sg:postcode": "44095",
    "sg:province": "OH",
    "sg:tags": [
      "plumbing",
      "contractor"
    ],
    "wof:name": "Paul The Plumber",
    "wof:placetype": "venue"
  },
  "geometry": {"coordinates":[-81.480425,41.625315],"type":"Point"}
}
