{
  "type": "Feature",
  "properties": {
    "addr:full": "103 Great Southern Blvd Columbus OH 43207",
    "addr:housenumber": "103",
    "addr:postcode": "43207",
    "addr:street": "Great Southern Blvd",
    "iso:country": "US",
    "sg:address": "103 Great Southern Blvd",
    "sg:city": "Columbus",
    "sg:classifiers": [
      {
        "category": "Professional",
        "subcategory": "Employment Agencies",
        "type": "Services"
      }
    ],
    "sg:phone": "+1 614 497 9387",
    "sg:postcode": "43207",
    "sg:province": "OH",
    "sg:tags": [
      "opportunity"
    ],
    "wof:name": "Pro Staffing Inc",
    "wof:placetype": "venue"
  },
  "geometry": {"coordinates":[-83.001229,39.882729],"type":"Point"}
}
