{
  "type": "Feature",
  "properties": {
    "addr:full":"4421 W 140th St Cleveland OH 44135",
    "addr:housenumber":"4421",
    "addr:postcode":"44135",
    "addr:street":"W 140Th St",
    "iso:country":"US",
    "sg:address":"4421 W 140th St",
    "sg:city":"Cleveland",
    "sg:classifiers":[
        {
            "category":"Education",
            "subcategory":"Library",
            "type":"Public Place"
        }
    ],
    "sg:phone":"+1 216 623 7053",
    "sg:postcode":"44135",
    "sg:province":"OH",
    "wof:name":"Rockport Branch Library",
    "wof:placetype":"venue"
},
  "geometry": {"coordinates":[-81.790593,41.435004],"type":"Point"}
}