{
  "type": "Feature",
  "properties": {
    "iso:country":"US",
    "sg:address":"3996 S Hamilton Rd",
    "sg:city":"Groveport",
    "sg:classifiers":[
        {
            "category":"Restaurant",
            "type":"Food & Drink"
        }
    ],
    "sg:phone":"+1 614 836 7321",
    "sg:postcode":"43125",
    "sg:province":"OH",
    "sg:tags":[
        "eating"
    ],
    "wof:name":"Wendys",
    "wof:placetype":"venue"
},
  "geometry": {"coordinates":[-82.882006,39.90016],"type":"Point"}
}