{
  "type": "Feature",
  "properties": {
    "iso:country":"US",
    "sg:address":"4857 Winterset Dr",
    "sg:city":"Columbus",
    "sg:classifiers":[
        {
            "category":"Real Estate",
            "subcategory":"Real Estate Agent",
            "type":"Services"
        }
    ],
    "sg:phone":"+1 614 459 5941",
    "sg:postcode":"43220",
    "sg:province":"OH",
    "sg:tags":[
        "inspection"
    ],
    "wof:name":"Professional Property Inspctn",
    "wof:placetype":"venue"
},
  "geometry": {"coordinates":[-83.05771,40.056085],"type":"Point"}
}