{
  "type": "Feature",
  "properties": {
    "addr:full": "2975 Kingston Ave Grove City OH 43123",
    "addr:housenumber": "2975",
    "addr:postcode": "43123",
    "addr:street": "Kingston Ave",
    "iso:country": "US",
    "sg:address": "2975 Kingston Ave",
    "sg:city": "Grove City",
    "sg:classifiers": [
      {
        "category": "Education",
        "subcategory": "School",
        "type": "Public Place"
      }
    ],
    "sg:phone": "+1 614 801 8523",
    "sg:postcode": "43123",
    "sg:province": "OH",
    "wof:name": "Southwestern City Schools Head",
    "wof:placetype": "venue"
  },
  "geometry": {"coordinates":[-83.080857,39.876976],"type":"Point"}
}
