{
  "type": "Feature",
  "properties": {
    "iso:country":"US",
    "sg:address":"328 E 4th St",
    "sg:city":"Lima",
    "sg:classifiers":[
        {
            "category":"Organizations",
            "subcategory":"Religious Organization",
            "type":"Services"
        }
    ],
    "sg:phone":"+1 419 228 1893",
    "sg:postcode":"45804",
    "sg:province":"OH",
    "sg:tags":[
        "church"
    ],
    "wof:name":"New Hope Missionary Baptist",
    "wof:placetype":"venue"
},
  "geometry": {"coordinates":[-84.101183,40.716707],"type":"Point"}
}