{
  "type": "Feature",
  "properties": {
    "addr:full": "3659 Vincent Dr Cleveland OH 44131",
    "addr:housenumber": "3659",
    "addr:postcode": "44131",
    "addr:street": "Vincent Dr",
    "iso:country": "US",
    "sg:address": "3659 Vincent Dr",
    "sg:city": "Cleveland",
    "sg:classifiers": [
      {
        "category": "Building \u0026 Trades",
        "subcategory": "Construction",
        "type": "Services"
      }
    ],
    "sg:phone": "+1 216 642 0799",
    "sg:postcode": "44131",
    "sg:province": "OH",
    "sg:tags": [
      "carpentry",
      "contractor"
    ],
    "wof:name": "Spencer Home Improvement Inc",
    "wof:placetype": "venue"
  },
  "geometry": {"coordinates":[-81.663211,41.353828],"type":"Point"}
}
