{
  "type": "Feature",
  "properties": {
    "iso:country":"US",
    "sg:address":"5185 Wellfleet Dr",
    "sg:city":"Trotwood",
    "sg:classifiers":[
        {
            "category":"Real Estate",
            "subcategory":"Real Estate Operator",
            "type":"Services"
        }
    ],
    "sg:phone":"+1 937 854 3160",
    "sg:postcode":"45426",
    "sg:province":"OH",
    "sg:tags":[
        "apartment"
    ],
    "wof:name":"Salem Bend Condominiums",
    "wof:placetype":"venue"
},
  "geometry": {"coordinates":[-84.28935799999999,39.828467],"type":"Point"}
}