{
  "type": "Feature",
  "properties": {
    "addr:full": "4 Mount Vernon Ave Mt Vernon OH 43050",
    "addr:housenumber": "4",
    "addr:postcode": "43050",
    "addr:street": "Mount Vernon Ave",
    "iso:country": "US",
    "sg:address": "4 Mount Vernon Ave",
    "sg:city": "Mt Vernon",
    "sg:classifiers": [
      {
        "category": "Professional",
        "subcategory": "Management \u0026 Consulting",
        "type": "Services"
      }
    ],
    "sg:phone": "+1 740 392 3096",
    "sg:postcode": "43050",
    "sg:province": "OH",
    "sg:tags": [
      "party",
      "planning"
    ],
    "wof:name": "Parties Unlimited",
    "wof:placetype": "venue"
  },
  "geometry": {"coordinates":[-82.485332,40.384745],"type":"Point"}
}
