{
  "type": "Feature",
  "properties": {
    "addr:full": "2685 Derr Rd Springfield OH 45503",
    "addr:housenumber": "2685",
    "addr:postcode": "45503",
    "addr:street": "Derr Rd",
    "iso:country": "US",
    "sg:address": "2685 Derr Rd",
    "sg:city": "Springfield",
    "sg:classifiers": [
      {
        "category": "Health Services",
        "subcategory": "Chiropractor",
        "type": "Services"
      }
    ],
    "sg:phone": "+1 937 390 6138",
    "sg:postcode": "45503",
    "sg:province": "OH",
    "wof:name": "Springfield Chiropractic Ctr",
    "wof:placetype": "venue"
  },
  "geometry": {"coordinates":[-83.786183,39.957424],"type":"Point"}
}
