{
  "type": "Feature",
  "properties": {
    "addr:full": "4931 Longbenton Way Dublin OH 43017",
    "addr:housenumber": "4931",
    "addr:postcode": "43017",
    "addr:street": "Longbenton Way",
    "iso:country": "US",
    "sg:address": "4931 Longbenton Way",
    "sg:city": "Dublin",
    "sg:classifiers": [
      {
        "category": "Banks \u0026 Credit Unions",
        "subcategory": "Investment Brokerage",
        "type": "Services"
      }
    ],
    "sg:phone": "+1 614 766 0106",
    "sg:postcode": "43017",
    "sg:province": "OH",
    "sg:tags": [
      "loan",
      "security",
      "real estate"
    ],
    "wof:name": "Links Mortgage Corporation",
    "wof:placetype": "venue"
  },
  "geometry": {"coordinates":[-83.12333,40.126435],"type":"Point"}
}
