{
  "type": "Feature",
  "properties": {
    "addr:full":"2797 Medina Rd Medina OH 44256",
    "addr:housenumber":"2797",
    "addr:postcode":"44256",
    "addr:street":"Medina Rd",
    "iso:country":"US",
    "sg:address":"2797 Medina Rd",
    "sg:city":"Medina",
    "sg:classifiers":[
        {
            "category":"Shopping",
            "subcategory":"Used Merchandise",
            "type":"Retail Goods"
        }
    ],
    "sg:phone":"+1 330 722 0017",
    "sg:postcode":"44256",
    "sg:province":"OH",
    "sg:tags":[
        "antique"
    ],
    "sg:website":"www.antiquelandusa.com",
    "wof:name":"Medina Antique Mall Inc",
    "wof:placetype":"venue"
},
  "geometry": {"coordinates":[-81.788355,41.136249],"type":"Point"}
}