{
  "type": "Feature",
  "properties": {
    "iso:country":"US",
    "sg:address":"5000 Euclid Ave",
    "sg:city":"Cleveland",
    "sg:classifiers":[
        {
            "category":"Manufacturing",
            "subcategory":"Printing",
            "type":"Manufacturing & Wholesale Goods"
        }
    ],
    "sg:phone":"+1 216 431 3300",
    "sg:postcode":"44103",
    "sg:province":"OH",
    "sg:tags":[
        "printer"
    ],
    "wof:name":"E G Enterprises Svc",
    "wof:placetype":"venue"
},
  "geometry": {"coordinates":[-81.652973,41.504025],"type":"Point"}
}