{
  "type": "Feature",
  "properties": {
    "iso:country":"US",
    "sg:address":"5722 Chevrolet Blvd",
    "sg:city":"Cleveland",
    "sg:classifiers":[
        {
            "category":"Restaurant",
            "type":"Food & Drink"
        }
    ],
    "sg:phone":"+1 440 884 4500",
    "sg:postcode":"44130",
    "sg:province":"OH",
    "wof:name":"Antonio's Pizza Express",
    "wof:placetype":"venue"
},
  "geometry": {"coordinates":[-81.769002,41.40837],"type":"Point"}
}