{
  "type": "Feature",
  "properties": {
    "iso:country":"US",
    "sg:address":"11607 Pearl Rd",
    "sg:city":"Cleveland",
    "sg:classifiers":[
        {
            "category":"Social Services",
            "subcategory":"Adult Care",
            "type":"Services"
        }
    ],
    "sg:phone":"+1 440 238 9142",
    "sg:postcode":"44136",
    "sg:province":"OH",
    "sg:tags":[
        "retardation",
        "home",
        "dev",
        "disabled"
    ],
    "wof:name":"Albion Home",
    "wof:placetype":"venue"
},
  "geometry": {"coordinates":[-81.83698,41.328549],"type":"Point"}
}