{
  "type": "Feature",
  "properties": {
    "addr:full": "2484 W State St Alliance OH 44601",
    "addr:housenumber": "2484",
    "addr:postcode": "44601",
    "addr:street": "W State St",
    "iso:country": "US",
    "sg:address": "2484 W State St",
    "sg:city": "Alliance",
    "sg:classifiers": [
      {
        "category": "Sports \u0026 Exercise",
        "subcategory": "Gym",
        "type": "Entertainment"
      }
    ],
    "sg:phone": "+1 330 829 2339",
    "sg:postcode": "44601",
    "sg:province": "OH",
    "sg:tags": [
      "club",
      "health",
      "studio",
      "gymnasium"
    ],
    "wof:name": "Concorde Health \u0026 Wellness",
    "wof:placetype": "venue"
  },
  "geometry": {"coordinates":[-81.157646,40.90203],"type":"Point"}
}
