{
  "type": "Feature",
  "properties": {
    "iso:country":"US",
    "sg:address":"2484 W State St",
    "sg:city":"Alliance",
    "sg:classifiers":[
        {
            "category":"Sports & Exercise",
            "subcategory":"Gym",
            "type":"Entertainment"
        }
    ],
    "sg:phone":"+1 330 829 2339",
    "sg:postcode":"44601",
    "sg:province":"OH",
    "sg:tags":[
        "club",
        "health",
        "studio",
        "gymnasium"
    ],
    "wof:name":"Concorde Health & Wellness",
    "wof:placetype":"venue"
},
  "geometry": {"coordinates":[-81.157646,40.90203],"type":"Point"}
}