{
  "type": "Feature",
  "properties": {
    "addr:full": "37131 Colorado Ave Avon OH 44011",
    "addr:housenumber": "37131",
    "addr:postcode": "44011",
    "addr:street": "Colorado Ave",
    "iso:country": "US",
    "sg:address": "37131 Colorado Ave",
    "sg:city": "Avon",
    "sg:classifiers": [
      {
        "category": "Recreation",
        "type": "Entertainment"
      }
    ],
    "sg:phone": "+1 440 934 9314",
    "sg:postcode": "44011",
    "sg:province": "OH",
    "sg:tags": [
      "martial",
      "arts",
      "instruction"
    ],
    "wof:name": "Chu To Bu West Judo \u0026 Jujitsu",
    "wof:placetype": "venue"
  },
  "geometry": {"coordinates":[-82.036993,41.453337],"type":"Point"}
}
