{
  "type": "Feature",
  "properties": {
    "iso:country":"US",
    "sg:address":"37131 Colorado Ave",
    "sg:city":"Avon",
    "sg:classifiers":[
        {
            "category":"Recreation",
            "type":"Entertainment"
        }
    ],
    "sg:phone":"+1 440 934 9314",
    "sg:postcode":"44011",
    "sg:province":"OH",
    "sg:tags":[
        "martial",
        "arts",
        "instruction"
    ],
    "wof:name":"Chu To Bu West Judo & Jujitsu",
    "wof:placetype":"venue"
},
  "geometry": {"coordinates":[-82.036993,41.453337],"type":"Point"}
}