{
  "type": "Feature",
  "properties": {
    "addr:full": "109 Harris St Lodi OH 44254",
    "addr:housenumber": "109",
    "addr:postcode": "44254",
    "addr:street": "Harris St",
    "iso:country": "US",
    "sg:address": "109 Harris St",
    "sg:city": "Lodi",
    "sg:classifiers": [
      {
        "category": "Health Services",
        "subcategory": "Dentist",
        "type": "Services"
      }
    ],
    "sg:phone": "+1 330 948 1655",
    "sg:postcode": "44254",
    "sg:province": "OH",
    "sg:website": "www.familydentalcenter.org",
    "wof:name": "Lodi Family Dental Center",
    "wof:placetype": "venue"
  },
  "geometry": {"coordinates":[-82.010902,41.032902],"type":"Point"}
}
