{
  "type": "Feature",
  "properties": {
    "addr:full": "1633 Medford Ave Youngstown OH 44514",
    "addr:housenumber": "1633",
    "addr:postcode": "44514",
    "addr:street": "Medford Ave",
    "iso:country": "US",
    "sg:address": "1633 Medford Ave",
    "sg:city": "Youngstown",
    "sg:classifiers": [
      {
        "category": "Professional",
        "type": "Services"
      }
    ],
    "sg:phone": "+1 330 788 5554",
    "sg:postcode": "44514",
    "sg:province": "OH",
    "wof:name": "Poland Power Inc",
    "wof:placetype": "venue"
  },
  "geometry": {"coordinates":[-80.625679,41.057598],"type":"Point"}
}
