{
  "type": "Feature",
  "properties": {
    "iso:country":"US",
    "sg:address":"1195 George Washington Blvd",
    "sg:city":"Akron",
    "sg:classifiers":[
        {
            "category":"Home & Garden",
            "subcategory":"Building Materials",
            "type":"Retail Goods"
        }
    ],
    "sg:phone":"+1 330 761 3443",
    "sg:postcode":"44312",
    "sg:province":"OH",
    "sg:tags":[
        "door"
    ],
    "wof:name":"Percision",
    "wof:placetype":"venue"
},
  "geometry": {"coordinates":[-81.462107,41.027752],"type":"Point"}
}