{
  "type": "Feature",
  "properties": {
    "iso:country":"US",
    "sg:address":"2465 Schnebly Rd",
    "sg:city":"Spring Valley",
    "sg:classifiers":[
        {
            "category":"Retail",
            "subcategory":"Repair Shop",
            "type":"Services"
        }
    ],
    "sg:phone":"+1 937 862 4400",
    "sg:postcode":"45370",
    "sg:province":"OH",
    "sg:tags":[
        "good",
        "mfg"
    ],
    "wof:name":"Clean-A-Drain",
    "wof:placetype":"venue"
},
  "geometry": {"coordinates":[-84.007464,39.62146],"type":"Point"}
}