{
  "type": "Feature",
  "properties": {
    "addr:full": "1112 N Meridian Rd Youngstown OH 44509",
    "addr:housenumber": "1112",
    "addr:postcode": "44509",
    "addr:street": "N Meridian Rd",
    "iso:country": "US",
    "sg:address": "1112 N Meridian Rd",
    "sg:city": "Youngstown",
    "sg:classifiers": [
      {
        "category": "Shopping",
        "type": "Retail Goods"
      }
    ],
    "sg:phone": "+1 330 270 4400",
    "sg:postcode": "44509",
    "sg:province": "OH",
    "sg:tags": [
      "equipment",
      "telephone",
      "supply"
    ],
    "sg:website": "www.paralleltech.com",
    "wof:name": "Parallel Technologies Inc",
    "wof:placetype": "venue"
  },
  "geometry": {"coordinates":[-80.711224,41.127418],"type":"Point"}
}
