{
  "type": "Feature",
  "properties": {
    "addr:full": "791 Garfield St Akron OH 44310",
    "addr:housenumber": "791",
    "addr:postcode": "44310",
    "addr:street": "Garfield St",
    "iso:country": "US",
    "sg:address": "791 Garfield St",
    "sg:city": "Akron",
    "sg:classifiers": [
      {
        "category": "Professional",
        "type": "Services"
      }
    ],
    "sg:phone": "+1 330 384 9697",
    "sg:postcode": "44310",
    "sg:province": "OH",
    "wof:name": "Catherine Lochrie",
    "wof:placetype": "venue"
  },
  "geometry": {"coordinates":[-81.520347,41.105899],"type":"Point"}
}
