{
  "type": "Feature",
  "properties": {
    "addr:full":"55 W Bagley Rd Berea OH 44017",
    "addr:housenumber":"55",
    "addr:postcode":"44017",
    "addr:street":"W Bagley Rd",
    "iso:country":"US",
    "sg:address":"55 W Bagley Rd",
    "sg:city":"Berea",
    "sg:classifiers":[
        {
            "category":"Manufacturing",
            "subcategory":"Apparel",
            "type":"Manufacturing & Wholesale Goods"
        }
    ],
    "sg:phone":"+1 440 243 0070",
    "sg:postcode":"44017",
    "sg:province":"OH",
    "sg:tags":[
        "sewing",
        "contractor"
    ],
    "wof:name":"Just Sew",
    "wof:placetype":"venue"
},
  "geometry": {"coordinates":[-81.853562,41.372653],"type":"Point"}
}