{
  "type": "Feature",
  "properties": {
    "addr:full": "215 E Oak St Wauseon OH 43567",
    "addr:housenumber": "215",
    "addr:postcode": "43567",
    "addr:street": "E Oak St",
    "iso:country": "US",
    "sg:address": "215 E Oak St",
    "sg:city": "Wauseon",
    "sg:classifiers": [
      {
        "category": "Restaurant",
        "type": "Food \u0026 Drink"
      }
    ],
    "sg:phone": "+1 419 337 3800",
    "sg:postcode": "43567",
    "sg:province": "OH",
    "wof:name": "Tiny's Pizza \u0026 Subs",
    "wof:placetype": "venue"
  },
  "geometry": {"coordinates":[-84.140948,41.550844],"type":"Point"}
}
