{
  "type": "Feature",
  "properties": {
    "iso:country":"US",
    "sg:address":"215 E Oak St",
    "sg:city":"Wauseon",
    "sg:classifiers":[
        {
            "category":"Restaurant",
            "type":"Food & Drink"
        }
    ],
    "sg:phone":"+1 419 337 3800",
    "sg:postcode":"43567",
    "sg:province":"OH",
    "wof:name":"Tiny's Pizza & Subs",
    "wof:placetype":"venue"
},
  "geometry": {"coordinates":[-84.14094799999999,41.550844],"type":"Point"}
}