{
  "type": "Feature",
  "properties": {
    "addr:full": "2424 N Cool Rd Lima OH 45801",
    "addr:housenumber": "2424",
    "addr:postcode": "45801",
    "addr:street": "N Cool Rd",
    "iso:country": "US",
    "sg:address": "2424 N Cool Rd",
    "sg:city": "Lima",
    "sg:classifiers": [
      {
        "category": "Government",
        "subcategory": "Office",
        "type": "Public Place"
      }
    ],
    "sg:phone": "+1 419 649 2883",
    "sg:postcode": "45801",
    "sg:province": "OH",
    "sg:tags": [
      "executive"
    ],
    "wof:name": "Jackson Twnship Zning Inspctor",
    "wof:placetype": "venue"
  },
  "geometry": {"coordinates":[-83.994156,40.777716],"type":"Point"}
}
