{
  "type": "Feature",
  "properties": {
    "iso:country":"US",
    "sg:address":"195 Wadsworth Rd",
    "sg:city":"Wadsworth",
    "sg:classifiers":[
        {
            "category":"Health Services",
            "subcategory":"Doctor",
            "type":"Services"
        }
    ],
    "sg:phone":"+1 330 336 5046",
    "sg:postcode":"44281",
    "sg:province":"OH",
    "sg:tags":[
        "physician",
        "surgeon"
    ],
    "wof:name":"Lassalette Primary Personal",
    "wof:placetype":"venue"
},
  "geometry": {"coordinates":[-81.753962,41.026535],"type":"Point"}
}