{
  "type": "Feature",
  "properties": {
    "addr:full": "15892 Burton-Windsor Rd Middlefield OH 44062",
    "addr:postcode": "15892;44062",
    "addr:street": "Burton-Windsor Rd",
    "iso:country": "US",
    "sg:address": "15892 Burton-Windsor Rd",
    "sg:city": "Middlefield",
    "sg:classifiers": [
      {
        "category": "Home \u0026 Garden",
        "subcategory": "Furniture",
        "type": "Retail Goods"
      }
    ],
    "sg:phone": "+1 440 632 1551",
    "sg:postcode": "44062",
    "sg:province": "OH",
    "sg:tags": [
      "cabinet"
    ],
    "wof:name": "J M Custom Cabinets",
    "wof:placetype": "venue"
  },
  "geometry": {"coordinates":[-81.071812,41.500936],"type":"Point"}
}
