{
  "type": "Feature",
  "properties": {
    "addr:full": "1554 McKaig Rd Troy OH 45373",
    "addr:housenumber": "1554",
    "addr:postcode": "45373",
    "addr:street": "Mckaig Rd",
    "iso:country": "US",
    "sg:address": "1554 McKaig Rd",
    "sg:city": "Troy",
    "sg:classifiers": [
      {
        "category": "Shopping",
        "subcategory": "Computers \u0026 Home Electronics",
        "type": "Retail Goods"
      }
    ],
    "sg:phone": "+1 937 339 7227",
    "sg:postcode": "45373",
    "sg:province": "OH",
    "sg:tags": [
      "equipment",
      "satellite",
      "system"
    ],
    "wof:name": "All-Star Satellite Systems",
    "wof:placetype": "venue"
  },
  "geometry": {"coordinates":[-84.230174,40.039526],"type":"Point"}
}
