{
  "type": "Feature",
  "properties": {
    "addr:full": "845 Boardman Poland Rd Youngstown OH 44512",
    "addr:housenumber": "845",
    "addr:postcode": "44512",
    "addr:street": "Boardman Poland Rd",
    "iso:country": "US",
    "sg:address": "845 Boardman Poland Rd",
    "sg:city": "Youngstown",
    "sg:classifiers": [
      {
        "category": "Retail",
        "subcategory": "Laundry \u0026 Dry Cleaning",
        "type": "Services"
      }
    ],
    "sg:phone": "+1 330 758 2317",
    "sg:postcode": "44512",
    "sg:province": "OH",
    "sg:tags": [
      "cleaners"
    ],
    "wof:name": "Dutchess Dry Cleaners",
    "wof:placetype": "venue"
  },
  "geometry": {"coordinates":[-80.635227,41.02417],"type":"Point"}
}
