{
  "type": "Feature",
  "properties": {
    "iso:country":"US",
    "sg:address":"7797 W Chester Rd",
    "sg:city":"West Chester",
    "sg:classifiers":[
        {
            "category":"Banks & Credit Unions",
            "subcategory":"Bank",
            "type":"Services"
        }
    ],
    "sg:phone":"+1 513 755 4000",
    "sg:postcode":"45069",
    "sg:province":"OH",
    "sg:tags":[
        "national"
    ],
    "wof:name":"US Bancorp",
    "wof:placetype":"venue"
},
  "geometry": {"coordinates":[-84.370766,39.318341],"type":"Point"}
}