{
  "type": "Feature",
  "properties": {
    "addr:full": "1814 Coventry Rd Cleveland OH 44118",
    "addr:housenumber": "1814",
    "addr:postcode": "44118",
    "addr:street": "Coventry Rd",
    "iso:country": "US",
    "sg:address": "1814 Coventry Rd",
    "sg:city": "Cleveland",
    "sg:classifiers": [
      {
        "category": "Shopping",
        "subcategory": "Gifts \u0026 Souvenirs",
        "type": "Retail Goods"
      }
    ],
    "sg:phone": "+1 216 321 8500",
    "sg:postcode": "44118",
    "sg:province": "OH",
    "sg:tags": [
      "shop"
    ],
    "wof:name": "High Tide/Rock Bottom Inc",
    "wof:placetype": "venue"
  },
  "geometry": {"coordinates":[-81.58006,41.509925],"type":"Point"}
}
