{
  "type": "Feature",
  "properties": {
    "iso:country":"US",
    "sg:address":"43 2nd Ave",
    "sg:city":"Pataskala",
    "sg:classifiers":[
        {
            "category":"Building & Trades",
            "subcategory":"Construction",
            "type":"Services"
        }
    ],
    "sg:phone":"+1 740 964 2140",
    "sg:postcode":"43062",
    "sg:province":"OH",
    "sg:tags":[
        "hanging",
        "contractor"
    ],
    "wof:name":"Steve J Goslin",
    "wof:placetype":"venue"
},
  "geometry": {"coordinates":[-82.675625,40.000197],"type":"Point"}
}