{
  "type": "Feature",
  "properties": {
    "addr:full":"43 2nd Ave Pataskala OH 43062",
    "addr:housenumber":"43",
    "addr:postcode":"43062",
    "addr:street":"2Nd Ave",
    "iso:country":"US",
    "sg:address":"43 2nd Ave",
    "sg:city":"Pataskala",
    "sg:classifiers":[
        {
            "category":"Building & Trades",
            "subcategory":"Construction",
            "type":"Services"
        }
    ],
    "sg:phone":"+1 740 964 2140",
    "sg:postcode":"43062",
    "sg:province":"OH",
    "sg:tags":[
        "hanging",
        "contractor"
    ],
    "wof:name":"Steve J Goslin",
    "wof:placetype":"venue"
},
  "geometry": {"coordinates":[-82.675625,40.000197],"type":"Point"}
}