{
  "type": "Feature",
  "properties": {
    "addr:full":"114 N Broadway St Spencerville OH 45887",
    "addr:housenumber":"114",
    "addr:postcode":"45887",
    "addr:street":"N Broadway St",
    "iso:country":"US",
    "sg:address":"114 N Broadway St",
    "sg:city":"Spencerville",
    "sg:classifiers":[
        {
            "category":"Professional",
            "subcategory":"Lawyer & Legal Services",
            "type":"Services"
        }
    ],
    "sg:phone":"+1 419 647 4363",
    "sg:postcode":"45887",
    "sg:province":"OH",
    "sg:tags":[
        "attorney"
    ],
    "wof:name":"Ronald H Miller",
    "wof:placetype":"venue"
},
  "geometry": {"coordinates":[-84.35341200000001,40.708618],"type":"Point"}
}