{
  "type": "Feature",
  "properties": {
    "addr:full":"7040 Hudson Rd Kent OH 44240",
    "addr:housenumber":"7040",
    "addr:postcode":"44240",
    "addr:street":"Hudson Rd",
    "iso:country":"US",
    "sg:address":"7040 Hudson Rd",
    "sg:city":"Kent",
    "sg:classifiers":[
        {
            "category":"Real Estate",
            "subcategory":"Surveying",
            "type":"Services"
        }
    ],
    "sg:phone":"+1 330 673 7408",
    "sg:postcode":"44240",
    "sg:province":"OH",
    "sg:tags":[
        "surveyor"
    ],
    "wof:name":"Collier Surveying",
    "wof:placetype":"venue"
},
  "geometry": {"coordinates":[-81.365526,41.182383],"type":"Point"}
}