{
  "type": "Feature",
  "properties": {
    "iso:country":"US",
    "sg:address":"1630 Morse Rd",
    "sg:city":"Columbus",
    "sg:classifiers":[
        {
            "category":"Banks & Credit Unions",
            "subcategory":"Bank",
            "type":"Services"
        }
    ],
    "sg:phone":"+1 614 433 7429",
    "sg:postcode":"43229",
    "sg:province":"OH",
    "wof:name":"Charter One Bank",
    "wof:placetype":"venue"
},
  "geometry": {"coordinates":[-82.971326,40.060414],"type":"Point"}
}