{
  "type": "Feature",
  "properties": {
    "addr:full":"7759 Reading Rd Cincinnati OH 45237",
    "addr:housenumber":"7759",
    "addr:postcode":"45237",
    "addr:street":"Reading Rd",
    "iso:country":"US",
    "sg:address":"7759 Reading Rd",
    "sg:city":"Cincinnati",
    "sg:classifiers":[
        {
            "category":"Autos & Motor Vehicles",
            "subcategory":"Automobile Sales",
            "type":"Retail Goods"
        },
        {
            "category":"Retail",
            "subcategory":"Auto Rental",
            "type":"Services"
        }
    ],
    "sg:phone":"+1 513 679 6212",
    "sg:postcode":"45237",
    "sg:province":"OH",
    "sg:tags":[
        "truck",
        "leasing",
        "car"
    ],
    "sg:website":"http://www.enterprise.com/car_rental/deeplinkmap.do?gpbr=3809&bid=004&cnty=US&arc=YPTRL01&cm_mmc=Yellowpages.com-_-IYP-_-Tradelisting-_-branch",
    "wof:name":"Enterprise Rent-A-Car",
    "wof:placetype":"venue"
},
  "geometry": {"coordinates":[-84.455133,39.203215],"type":"Point"}
}