{
  "type": "Feature",
  "properties": {
    "addr:full":"1471 O Shaughnesy Dr Xenia OH 45385",
    "addr:housenumber":"1471",
    "addr:postcode":"45385",
    "addr:street":"O Shaughnesy Dr",
    "iso:country":"US",
    "sg:address":"1471 O Shaughnesy Dr",
    "sg:city":"Xenia",
    "sg:classifiers":[
        {
            "category":"Restaurant",
            "type":"Food & Drink"
        }
    ],
    "sg:phone":"+1 937 372 7428",
    "sg:postcode":"45385",
    "sg:province":"OH",
    "sg:tags":[
        "eating"
    ],
    "wof:name":"Brother Bears Coffee LLC",
    "wof:placetype":"venue"
},
  "geometry": {"coordinates":[-83.98521,39.705615],"type":"Point"}
}