{
  "type": "Feature",
  "properties": {
    "iso:country":"US",
    "sg:address":"673 Mohawk St",
    "sg:city":"Columbus",
    "sg:classifiers":[
        {
            "category":"Government",
            "subcategory":"Office",
            "type":"Public Place"
        }
    ],
    "sg:phone":"+1 614 542 0542",
    "sg:postcode":"43206",
    "sg:province":"OH",
    "sg:tags":[
        "city"
    ],
    "wof:name":"Capital City Brokerage",
    "wof:placetype":"venue"
},
  "geometry": {"coordinates":[-82.993645,39.948653],"type":"Point"}
}