{
  "type": "Feature",
  "properties": {
    "iso:country":"US",
    "sg:address":"4400 Crew Hood Rd",
    "sg:city":"Girard",
    "sg:classifiers":[
        {
            "category":"Retail",
            "subcategory":"Auto Repair",
            "type":"Services"
        }
    ],
    "sg:phone":"+1 330 539 2002",
    "sg:postcode":"44420",
    "sg:province":"OH",
    "sg:tags":[
        "repairing",
        "automobile"
    ],
    "wof:name":"Scandinavian Auto Repair",
    "wof:placetype":"venue"
},
  "geometry": {"coordinates":[-80.663765,41.203095],"type":"Point"}
}