{
  "type": "Feature",
  "properties": {
    "addr:full": "1600 Woodville Rd Millbury OH 43447",
    "addr:housenumber": "1600",
    "addr:postcode": "43447",
    "addr:street": "Woodville Rd",
    "iso:country": "US",
    "sg:address": "1600 Woodville Rd",
    "sg:city": "Millbury",
    "sg:classifiers": [
      {
        "category": "Manufacturing",
        "subcategory": "Printing",
        "type": "Manufacturing \u0026 Wholesale Goods"
      }
    ],
    "sg:phone": "+1 419 693 8055",
    "sg:postcode": "43447",
    "sg:province": "OH",
    "sg:tags": [
      "screen",
      "commercial"
    ],
    "sg:website": "www.adamsspe.com",
    "wof:name": "Adams Screen Printing \u0026 EMB",
    "wof:placetype": "venue"
  },
  "geometry": {"coordinates":[-83.427864,41.577278],"type":"Point"}
}
