{
  "type": "Feature",
  "properties": {
    "addr:full":"4232 Sherman Church Ave SW Canton OH 44706",
    "addr:housenumber":"4232",
    "addr:postcode":"44706",
    "addr:street":"Sherman Church Ave Sw",
    "iso:country":"US",
    "sg:address":"4232 Sherman Church Ave SW",
    "sg:city":"Canton",
    "sg:classifiers":[
        {
            "category":"Professional",
            "subcategory":"Business Services",
            "type":"Services"
        }
    ],
    "sg:phone":"+1 330 484 0507",
    "sg:postcode":"44706",
    "sg:province":"OH",
    "sg:tags":[
        "water",
        "treatment"
    ],
    "wof:name":"Pro Water Testing & Equipment",
    "wof:placetype":"venue"
},
  "geometry": {"coordinates":[-81.420461,40.744715],"type":"Point"}
}