{
  "type": "Feature",
  "properties": {
    "addr:full": "505 Apple Rd Amelia OH 45102",
    "addr:housenumber": "505",
    "addr:postcode": "45102",
    "addr:street": "Apple Rd",
    "iso:country": "US",
    "sg:address": "505 Apple Rd",
    "sg:city": "Amelia",
    "sg:classifiers": [
      {
        "category": "Building \u0026 Trades",
        "subcategory": "Construction",
        "type": "Services"
      }
    ],
    "sg:phone": "+1 513 732 2494",
    "sg:postcode": "45102",
    "sg:province": "OH",
    "sg:tags": [
      "contractor"
    ],
    "wof:name": "Howard Brown Pools",
    "wof:placetype": "venue"
  },
  "geometry": {"coordinates":[-84.20339,39.056408],"type":"Point"}
}
