{
  "type": "Feature",
  "properties": {
    "iso:country":"US",
    "sg:address":"505 Apple Rd",
    "sg:city":"Amelia",
    "sg:classifiers":[
        {
            "category":"Building & Trades",
            "subcategory":"Construction",
            "type":"Services"
        }
    ],
    "sg:phone":"+1 513 732 2494",
    "sg:postcode":"45102",
    "sg:province":"OH",
    "sg:tags":[
        "contractor"
    ],
    "wof:name":"Howard Brown Pools",
    "wof:placetype":"venue"
},
  "geometry": {"coordinates":[-84.20339,39.056408],"type":"Point"}
}