{
  "type": "Feature",
  "properties": {
    "iso:country":"US",
    "sg:address":"1223 E Main St",
    "sg:city":"Columbus",
    "sg:classifiers":[
        {
            "category":"Food & Beverages",
            "subcategory":"Groceries & Convenience Stores",
            "type":"Retail Goods"
        }
    ],
    "sg:phone":"+1 614 252 6158",
    "sg:postcode":"43205",
    "sg:province":"OH",
    "wof:name":"Ona Corporation",
    "wof:placetype":"venue"
},
  "geometry": {"coordinates":[-82.96538200000001,39.957684],"type":"Point"}
}