{
  "type": "Feature",
  "properties": {
    "addr:full": "1223 E Main St Columbus OH 43205",
    "addr:housenumber": "1223",
    "addr:postcode": "43205",
    "addr:street": "E Main St",
    "iso:country": "US",
    "sg:address": "1223 E Main St",
    "sg:city": "Columbus",
    "sg:classifiers": [
      {
        "category": "Food \u0026 Beverages",
        "subcategory": "Groceries \u0026 Convenience Stores",
        "type": "Retail Goods"
      }
    ],
    "sg:phone": "+1 614 252 6158",
    "sg:postcode": "43205",
    "sg:province": "OH",
    "wof:name": "Ona Corporation",
    "wof:placetype": "venue"
  },
  "geometry": {"coordinates":[-82.965382,39.957684],"type":"Point"}
}
