{
  "type": "Feature",
  "properties": {
    "iso:country":"US",
    "sg:address":"52 E 14th Ave",
    "sg:city":"Columbus",
    "sg:classifiers":[
        {
            "category":"Travel",
            "subcategory":"Bed & Breakfast",
            "type":"Entertainment"
        }
    ],
    "sg:phone":"+1 614 294 3144",
    "sg:postcode":"43201",
    "sg:province":"OH",
    "sg:tags":[
        "housing",
        "student"
    ],
    "wof:name":"Evans Scholars",
    "wof:placetype":"venue"
},
  "geometry": {"coordinates":[-83.004358,39.998824],"type":"Point"}
}