{
  "type": "Feature",
  "properties": {
    "addr:full": "52 E 14th Ave Columbus OH 43201",
    "addr:housenumber": "52",
    "addr:postcode": "43201",
    "addr:street": "E 14Th Ave",
    "iso:country": "US",
    "sg:address": "52 E 14th Ave",
    "sg:city": "Columbus",
    "sg:classifiers": [
      {
        "category": "Travel",
        "subcategory": "Bed \u0026 Breakfast",
        "type": "Entertainment"
      }
    ],
    "sg:phone": "+1 614 294 3144",
    "sg:postcode": "43201",
    "sg:province": "OH",
    "sg:tags": [
      "housing",
      "student"
    ],
    "wof:name": "Evans Scholars",
    "wof:placetype": "venue"
  },
  "geometry": {"coordinates":[-83.004358,39.998824],"type":"Point"}
}
