{
  "type": "Feature",
  "properties": {
    "addr:full": "655 W Market St Akron OH 44303",
    "addr:housenumber": "655",
    "addr:postcode": "44303",
    "addr:street": "W Market St",
    "iso:country": "US",
    "sg:address": "655 W Market St",
    "sg:city": "Akron",
    "sg:classifiers": [
      {
        "category": "Manufacturing",
        "subcategory": "Tools \u0026 Machinery",
        "type": "Manufacturing \u0026 Wholesale Goods"
      }
    ],
    "sg:phone": "+1 440 543 3440",
    "sg:postcode": "44303",
    "sg:province": "OH",
    "sg:tags": [
      "development",
      "lighting",
      "product",
      "fixture",
      "mfg"
    ],
    "wof:name": "Sterilux Limited",
    "wof:placetype": "venue"
  },
  "geometry": {"coordinates":[-81.538972,41.094706],"type":"Point"}
}
