{
  "type": "Feature",
  "properties": {
    "iso:country":"US",
    "sg:address":"655 W Market St",
    "sg:city":"Akron",
    "sg:classifiers":[
        {
            "category":"Manufacturing",
            "subcategory":"Tools & Machinery",
            "type":"Manufacturing & Wholesale Goods"
        }
    ],
    "sg:phone":"+1 440 543 3440",
    "sg:postcode":"44303",
    "sg:province":"OH",
    "sg:tags":[
        "development",
        "lighting",
        "product",
        "fixture",
        "mfg"
    ],
    "wof:name":"Sterilux Limited",
    "wof:placetype":"venue"
},
  "geometry": {"coordinates":[-81.538972,41.094706],"type":"Point"}
}