{
  "type": "Feature",
  "properties": {
    "addr:full": "2123 Washington Blvd Belpre OH 45714",
    "addr:housenumber": "2123",
    "addr:postcode": "45714",
    "addr:street": "Washington Blvd",
    "iso:country": "US",
    "sg:address": "2123 Washington Blvd",
    "sg:city": "Belpre",
    "sg:classifiers": [
      {
        "category": "Home \u0026 Garden",
        "subcategory": "Carpets \u0026 Floor Coverings",
        "type": "Retail Goods"
      },
      {
        "category": "Home \u0026 Garden",
        "subcategory": "Furniture",
        "type": "Retail Goods"
      }
    ],
    "sg:phone": "+1 740 423 5140",
    "sg:postcode": "45714",
    "sg:province": "OH",
    "wof:name": "Carpet \u0026 Furn Liquidators",
    "wof:placetype": "venue"
  },
  "geometry": {"coordinates":[-81.604304,39.27798],"type":"Point"}
}
