{
  "type": "Feature",
  "properties": {
    "iso:country":"US",
    "sg:address":"2123 Washington Blvd",
    "sg:city":"Belpre",
    "sg:classifiers":[
        {
            "category":"Home & Garden",
            "subcategory":"Carpets & Floor Coverings",
            "type":"Retail Goods"
        },
        {
            "category":"Home & Garden",
            "subcategory":"Furniture",
            "type":"Retail Goods"
        }
    ],
    "sg:phone":"+1 740 423 5140",
    "sg:postcode":"45714",
    "sg:province":"OH",
    "wof:name":"Carpet & Furn Liquidators",
    "wof:placetype":"venue"
},
  "geometry": {"coordinates":[-81.604304,39.27798],"type":"Point"}
}