{
  "type": "Feature",
  "properties": {
    "addr:full": "196 Chenango Rd S New London OH 44851",
    "addr:housenumber": "196",
    "addr:postcode": "44851",
    "addr:street": "Chenango Rd",
    "iso:country": "US",
    "sg:address": "196 Chenango Rd S",
    "sg:city": "New London",
    "sg:classifiers": [
      {
        "category": "Wholesale",
        "subcategory": "Farm Supplies",
        "type": "Manufacturing \u0026 Wholesale Goods"
      }
    ],
    "sg:phone": "+1 419 929 5677",
    "sg:postcode": "44851",
    "sg:province": "OH",
    "sg:tags": [
      "corn",
      "livestock",
      "soybean"
    ],
    "wof:name": "Gary A Burt",
    "wof:placetype": "venue"
  },
  "geometry": {"coordinates":[-82.378912,41.128796],"type":"Point"}
}
