{
  "type": "Feature",
  "properties": {
    "addr:full":"317 S Main St Celina OH 45822",
    "addr:housenumber":"317",
    "addr:postcode":"45822",
    "addr:street":"S Main St",
    "iso:country":"US",
    "sg:address":"317 S Main St",
    "sg:city":"Celina",
    "sg:classifiers":[
        {
            "category":"Food & Beverages",
            "subcategory":"Groceries & Convenience Stores",
            "type":"Retail Goods"
        }
    ],
    "sg:phone":"+1 419 586 8889",
    "sg:postcode":"45822",
    "sg:province":"OH",
    "wof:name":"Celina Party Mart",
    "wof:placetype":"venue"
},
  "geometry": {"coordinates":[-84.570866,40.54635],"type":"Point"}
}