{
  "type": "Feature",
  "properties": {
    "addr:full":"230 Northland Blvd Cincinnati OH 45246",
    "addr:housenumber":"230",
    "addr:postcode":"45246",
    "addr:street":"Northland Blvd",
    "iso:country":"US",
    "sg:address":"230 Northland Blvd",
    "sg:city":"Cincinnati",
    "sg:classifiers":[
        {
            "category":"Professional",
            "subcategory":"Lawyer & Legal Services",
            "type":"Services"
        }
    ],
    "sg:phone":"+1 513 771 7449",
    "sg:postcode":"45246",
    "sg:province":"OH",
    "sg:tags":[
        "attorney"
    ],
    "wof:name":"Nora C Hendrickson Law Offices",
    "wof:placetype":"venue"
},
  "geometry": {"coordinates":[-84.481279,39.282735],"type":"Point"}
}