{
  "type": "Feature",
  "properties": {
    "addr:full":"5300 N Summit St Toledo OH 43611",
    "addr:housenumber":"5300",
    "addr:postcode":"43611",
    "addr:street":"N Summit St",
    "iso:country":"US",
    "sg:address":"5300 N Summit St",
    "sg:city":"Toledo",
    "sg:classifiers":[
        {
            "category":"Retail",
            "subcategory":"Funeral Services",
            "type":"Services"
        }
    ],
    "sg:phone":"+1 419 726 1583",
    "sg:postcode":"43611",
    "sg:province":"OH",
    "sg:tags":[
        "home"
    ],
    "sg:website":"www.jasinfuneralhome.com",
    "wof:name":"David R Jasin Funeral Home",
    "wof:placetype":"venue"
},
  "geometry": {"coordinates":[-83.479235,41.717912],"type":"Point"}
}