{
  "type": "Feature",
  "properties": {
    "addr:full":"374 Homeworth Rd Alliance OH 44601",
    "addr:housenumber":"374",
    "addr:postcode":"44601",
    "addr:street":"Homeworth Rd",
    "iso:country":"US",
    "sg:address":"374 Homeworth Rd",
    "sg:city":"Alliance",
    "sg:classifiers":[
        {
            "category":"Sports & Exercise",
            "subcategory":"Golf",
            "type":"Entertainment"
        }
    ],
    "sg:phone":"+1 330 821 8865",
    "sg:postcode":"44601",
    "sg:province":"OH",
    "sg:tags":[
        "course"
    ],
    "wof:name":"Alliance Sleepy Hollow Country",
    "wof:placetype":"venue"
},
  "geometry": {"coordinates":[-81.07755,40.895883],"type":"Point"}
}