{
  "type": "Feature",
  "properties": {
    "iso:country":"US",
    "sg:address":"1121 5th St SW",
    "sg:city":"Canton",
    "sg:classifiers":[
        {
            "category":"Manufacturing",
            "subcategory":"Tools & Machinery",
            "type":"Manufacturing & Wholesale Goods"
        }
    ],
    "sg:phone":"+1 330 471 9610",
    "sg:postcode":"44707",
    "sg:province":"OH",
    "sg:tags":[
        "machine",
        "shop"
    ],
    "wof:name":"Iron Metal Machine & Fab",
    "wof:placetype":"venue"
},
  "geometry": {"coordinates":[-81.384843,40.797577],"type":"Point"}
}