{
  "type": "Feature",
  "properties": {
    "addr:full":"1000 N Union Ave Alliance OH 44601",
    "addr:housenumber":"1000",
    "addr:postcode":"44601",
    "addr:street":"N Union Ave",
    "iso:country":"US",
    "sg:address":"1000 N Union Ave",
    "sg:city":"Alliance",
    "sg:classifiers":[
        {
            "category":"Manufacturing",
            "subcategory":"Glass & Minerals",
            "type":"Manufacturing & Wholesale Goods"
        },
        {
            "category":"Manufacturing",
            "subcategory":"Furniture",
            "type":"Manufacturing & Wholesale Goods"
        }
    ],
    "sg:phone":"+1 330 821 4473",
    "sg:postcode":"44601",
    "sg:province":"OH",
    "sg:tags":[
        "fiberglass",
        "fabricator",
        "product",
        "fiber",
        "mfg"
    ],
    "sg:website":"www.alliance-equipment.com",
    "wof:name":"Alliance Equipment Company Inc",
    "wof:placetype":"venue"
},
  "geometry": {"coordinates":[-81.105875,40.931793],"type":"Point"}
}