{
  "type": "Feature",
  "properties": {
    "addr:full":"270 Graceland Blvd Columbus OH 43214",
    "addr:housenumber":"270",
    "addr:postcode":"43214",
    "addr:street":"Graceland Blvd",
    "iso:country":"US",
    "sg:address":"270 Graceland Blvd",
    "sg:city":"Columbus",
    "sg:classifiers":[
        {
            "category":"Shopping",
            "subcategory":"Shoes",
            "type":"Retail Goods"
        }
    ],
    "sg:phone":"+1 614 431 2296",
    "sg:postcode":"43214",
    "sg:province":"OH",
    "wof:name":"Nine West",
    "wof:placetype":"venue"
},
  "geometry": {"coordinates":[-83.02505600000001,40.066063],"type":"Point"}
}