{
  "type": "Feature",
  "properties": {
    "iso:country":"US",
    "sg:address":"540 E Portage Trl",
    "sg:city":"Cuyahoga Falls",
    "sg:classifiers":[
        {
            "category":"Shopping",
            "subcategory":"Florist",
            "type":"Retail Goods"
        }
    ],
    "sg:phone":"+1 330 929 2256",
    "sg:postcode":"44221",
    "sg:province":"OH",
    "wof:name":"Profusion of Petals",
    "wof:placetype":"venue"
},
  "geometry": {"coordinates":[-81.475102,41.136124],"type":"Point"}
}