{
  "type": "Feature",
  "properties": {
    "addr:full": "3936 Wheatlands Rd Sylvania OH 43560",
    "addr:housenumber": "3936",
    "addr:postcode": "43560",
    "addr:street": "Wheatlands Rd",
    "iso:country": "US",
    "sg:address": "3936 Wheatlands Rd",
    "sg:city": "Sylvania",
    "sg:classifiers": [
      {
        "category": "Building \u0026 Trades",
        "subcategory": "Construction",
        "type": "Services"
      }
    ],
    "sg:phone": "+1 419 843 2004",
    "sg:postcode": "43560",
    "sg:province": "OH",
    "sg:tags": [
      "contractor"
    ],
    "wof:name": "GKG Builders",
    "wof:placetype": "venue"
  },
  "geometry": {"coordinates":[-83.710217,41.688101],"type":"Point"}
}
