{
  "type": "Feature",
  "properties": {
    "addr:full": "331 W Main St Mt Sterling OH 43143",
    "addr:housenumber": "331",
    "addr:postcode": "43143",
    "addr:street": "W Main St",
    "iso:country": "US",
    "sg:address": "331 W Main St",
    "sg:city": "Mt Sterling",
    "sg:classifiers": [
      {
        "category": "Retail",
        "subcategory": "Funeral Services",
        "type": "Services"
      }
    ],
    "sg:phone": "+1 740 869 2777",
    "sg:postcode": "43143",
    "sg:province": "OH",
    "sg:tags": [
      "director"
    ],
    "wof:name": "Porter Funeral Home",
    "wof:placetype": "venue"
  },
  "geometry": {"coordinates":[-83.27112,39.714959],"type":"Point"}
}
