{
  "type": "Feature",
  "properties": {
    "iso:country":"US",
    "sg:address":"419 Main St",
    "sg:city":"Grafton",
    "sg:classifiers":[
        {
            "category":"Professional",
            "subcategory":"Computer Services",
            "type":"Services"
        }
    ],
    "sg:phone":"+1 440 926 1385",
    "sg:postcode":"44044",
    "sg:province":"OH",
    "sg:tags":[
        "consulting",
        "designer",
        "consultant",
        "programming",
        "related",
        "also"
    ],
    "wof:name":"Metro Computer Resources Inc",
    "wof:placetype":"venue"
},
  "geometry": {"coordinates":[-82.06448899999999,41.286553],"type":"Point"}
}