{
  "type": "Feature",
  "properties": {
    "addr:full":"1753 S Lincoln Ave Salem OH 44460",
    "addr:housenumber":"1753",
    "addr:postcode":"44460",
    "addr:street":"S Lincoln Ave",
    "iso:country":"US",
    "sg:address":"1753 S Lincoln Ave",
    "sg:city":"Salem",
    "sg:classifiers":[
        {
            "category":"Manufacturing",
            "subcategory":"Signs",
            "type":"Manufacturing & Wholesale Goods"
        }
    ],
    "sg:phone":"+1 330 337 6372",
    "sg:postcode":"44460",
    "sg:province":"OH",
    "sg:tags":[
        "specialty",
        "mfg"
    ],
    "wof:name":"Lodge Signs",
    "wof:placetype":"venue"
},
  "geometry": {"coordinates":[-80.844416,40.883918],"type":"Point"}
}