{
  "type": "Feature",
  "properties": {
    "addr:full": "1203 Youngstown Rd SE Warren OH 44484",
    "addr:housenumber": "1203",
    "addr:postcode": "44484",
    "addr:street": "Youngstown Rd Se",
    "iso:country": "US",
    "sg:address": "1203 Youngstown Rd SE",
    "sg:city": "Warren",
    "sg:classifiers": [
      {
        "category": "Home \u0026 Garden",
        "subcategory": "Building Materials",
        "type": "Retail Goods"
      }
    ],
    "sg:phone": "+1 330 394 5888",
    "sg:postcode": "44484",
    "sg:province": "OH",
    "sg:tags": [
      "paint"
    ],
    "wof:name": "Warren Glass \u0026 Paint Co LTD",
    "wof:placetype": "venue"
  },
  "geometry": {"coordinates":[-80.803896,41.230902],"type":"Point"}
}
