{
  "type": "Feature",
  "properties": {
    "addr:full":"120 W Boundary St Perrysburg OH 43551",
    "addr:housenumber":"120",
    "addr:postcode":"43551",
    "addr:street":"W Boundary St",
    "iso:country":"US",
    "sg:address":"120 W Boundary St",
    "sg:city":"Perrysburg",
    "sg:classifiers":[
        {
            "category":"Restaurant",
            "type":"Food & Drink"
        }
    ],
    "sg:phone":"+1 419 872 4890",
    "sg:postcode":"43551",
    "sg:province":"OH",
    "wof:name":"Village Pizza Factory",
    "wof:placetype":"venue"
},
  "geometry": {"coordinates":[-83.641226,41.555139],"type":"Point"}
}