{
  "type": "Feature",
  "properties": {
    "iso:country":"US",
    "sg:address":"147 Gregory Ln",
    "sg:city":"Hamilton",
    "sg:classifiers":[
        {
            "category":"Shopping",
            "subcategory":"Clothing, Apparel, & Fashions",
            "type":"Retail Goods"
        }
    ],
    "sg:phone":"+1 513 844 2338",
    "sg:postcode":"45013",
    "sg:province":"IN",
    "wof:name":"Incentive Builders",
    "wof:placetype":"venue"
},
  "geometry": {"coordinates":[-84.570968,39.421856],"type":"Point"}
}