{
  "type": "Feature",
  "properties": {
    "addr:full": "4561 Industrial Pkwy Cleveland OH 44135",
    "addr:housenumber": "4561",
    "addr:postcode": "44135",
    "addr:street": "Industrial Pkwy",
    "iso:country": "US",
    "sg:address": "4561 Industrial Pkwy",
    "sg:city": "Cleveland",
    "sg:classifiers": [
      {
        "category": "Wholesale",
        "subcategory": "Groceries",
        "type": "Manufacturing \u0026 Wholesale Goods"
      }
    ],
    "sg:phone": "+1 216 252 7377",
    "sg:postcode": "44135",
    "sg:province": "OH",
    "sg:tags": [
      "food"
    ],
    "wof:name": "Pepsi-Cola",
    "wof:placetype": "venue"
  },
  "geometry": {"coordinates":[-81.789946,41.429478],"type":"Point"}
}
