{
  "type": "Feature",
  "properties": {
    "iso:country":"US",
    "sg:address":"4561 Industrial Pkwy",
    "sg:city":"Cleveland",
    "sg:classifiers":[
        {
            "category":"Wholesale",
            "subcategory":"Groceries",
            "type":"Manufacturing & Wholesale Goods"
        }
    ],
    "sg:phone":"+1 216 252 7377",
    "sg:postcode":"44135",
    "sg:province":"OH",
    "sg:tags":[
        "food"
    ],
    "wof:name":"Pepsi-Cola",
    "wof:placetype":"venue"
},
  "geometry": {"coordinates":[-81.789946,41.429478],"type":"Point"}
}