{
  "type": "Feature",
  "properties": {
    "iso:country":"US",
    "sg:address":"3762 Pearl Rd",
    "sg:city":"Cleveland",
    "sg:classifiers":[
        {
            "category":"Shopping",
            "subcategory":"Discount & Variety Stores",
            "type":"Retail Goods"
        }
    ],
    "sg:phone":"+1 216 398 4960",
    "sg:postcode":"44109",
    "sg:province":"OH",
    "wof:name":"Dollar Paradise",
    "wof:placetype":"venue"
},
  "geometry": {"coordinates":[-81.70143400000001,41.453095],"type":"Point"}
}