{
  "type": "Feature",
  "properties": {
    "addr:full": "10646 Leuer Ave Cleveland OH 44108",
    "addr:housenumber": "10646",
    "addr:postcode": "44108",
    "addr:street": "Leuer Ave",
    "iso:country": "US",
    "sg:address": "10646 Leuer Ave",
    "sg:city": "Cleveland",
    "sg:classifiers": [
      {
        "category": "Home \u0026 Garden",
        "subcategory": "Furniture",
        "type": "Retail Goods"
      }
    ],
    "sg:phone": "+1 216 851 0888",
    "sg:postcode": "44108",
    "sg:province": "OH",
    "sg:tags": [
      "top",
      "counter"
    ],
    "wof:name": "Iaperial Counter Tops Inc",
    "wof:placetype": "venue"
  },
  "geometry": {"coordinates":[-81.611174,41.546188],"type":"Point"}
}
