{
  "type": "Feature",
  "properties": {
    "addr:full":"137 E Iron Ave Dover OH 44622",
    "addr:housenumber":"137",
    "addr:postcode":"44622",
    "addr:street":"E Iron Ave",
    "iso:country":"US",
    "sg:address":"137 E Iron Ave",
    "sg:city":"Dover",
    "sg:classifiers":[
        {
            "category":"Autos & Motor Vehicles",
            "subcategory":"Auto Supplies",
            "type":"Retail Goods"
        }
    ],
    "sg:phone":"+1 330 364 9191",
    "sg:postcode":"44622",
    "sg:province":"OH",
    "wof:name":"Performance Parts Express LTD",
    "wof:placetype":"venue"
},
  "geometry": {"coordinates":[-81.466022,40.515813],"type":"Point"}
}