{
  "type": "Feature",
  "properties": {
    "addr:full": "13968 Chillicothe Rd Novelty OH 44072",
    "addr:housenumber": "13968",
    "addr:postcode": "44072",
    "addr:street": "Chillicothe Rd",
    "iso:country": "US",
    "sg:address": "13968 Chillicothe Rd",
    "sg:city": "Novelty",
    "sg:classifiers": [
      {
        "category": "Organizations",
        "subcategory": "Religious Organization",
        "type": "Services"
      }
    ],
    "sg:phone": "+1 440 338 3191",
    "sg:postcode": "44072",
    "sg:province": "OH",
    "sg:tags": [
      "church"
    ],
    "sg:website": "www.riverviewchurch.net",
    "wof:name": "Riverview Church",
    "wof:placetype": "venue"
  },
  "geometry": {"coordinates":[-81.339897,41.489601],"type":"Point"}
}
