{
  "type": "Feature",
  "properties": {
    "iso:country":"US",
    "sg:address":"17820 Englewood Dr",
    "sg:city":"Cleveland",
    "sg:classifiers":[
        {
            "category":"Autos & Motor Vehicles",
            "subcategory":"Auto Supplies",
            "type":"Retail Goods"
        }
    ],
    "sg:phone":"+1 440 234 6210",
    "sg:postcode":"44130",
    "sg:province":"OH",
    "sg:tags":[
        "tire"
    ],
    "wof:name":"Goodyear Tire & Rubber Co",
    "wof:placetype":"venue"
},
  "geometry": {"coordinates":[-81.824716,41.38114],"type":"Point"}
}