{
  "type": "Feature",
  "properties": {
    "addr:full": "667 Eastland Ave SE Warren OH 44484",
    "addr:housenumber": "667",
    "addr:postcode": "44484",
    "addr:street": "Eastland Ave Se",
    "iso:country": "US",
    "sg:address": "667 Eastland Ave SE",
    "sg:city": "Warren",
    "sg:classifiers": [
      {
        "category": "Professional",
        "subcategory": "Management \u0026 Consulting",
        "type": "Services"
      }
    ],
    "sg:phone": "+1 330 369 2269",
    "sg:postcode": "44484",
    "sg:province": "OH",
    "sg:tags": [
      "construction"
    ],
    "wof:name": "Morse Diesel Intl",
    "wof:placetype": "venue"
  },
  "geometry": {"coordinates":[-80.778243,41.230169],"type":"Point"}
}
