{
  "type": "Feature",
  "properties": {
    "addr:full":"5846 W Fork Rd Cincinnati OH 45247",
    "addr:housenumber":"5846",
    "addr:postcode":"45247",
    "addr:street":"W Fork Rd",
    "iso:country":"US",
    "sg:address":"5846 W Fork Rd",
    "sg:city":"Cincinnati",
    "sg:classifiers":[
        {
            "category":"Building & Trades",
            "subcategory":"Plumbing",
            "type":"Services"
        }
    ],
    "sg:phone":"+1 513 598 5502",
    "sg:postcode":"45247",
    "sg:province":"OH",
    "sg:tags":[
        "boiler",
        "cleaning"
    ],
    "wof:name":"N K Svc",
    "wof:placetype":"venue"
},
  "geometry": {"coordinates":[-84.638482,39.198715],"type":"Point"}
}