{
  "type": "Feature",
  "properties": {
    "addr:full": "4095 Richmond Rd Beachwood OH 44122",
    "addr:housenumber": "4095",
    "addr:postcode": "44122",
    "addr:street": "Richmond Rd",
    "iso:country": "US",
    "sg:address": "4095 Richmond Rd",
    "sg:city": "Beachwood",
    "sg:phone": "+1 216 910 0422",
    "sg:postcode": "44122",
    "sg:province": "OH",
    "sg:website": "http://www.vcf.com",
    "wof:name": "Value City Furniture",
    "wof:placetype": "venue"
  },
  "geometry": {"coordinates":[-81.497704,41.4498],"type":"Point"}
}
