{
  "type": "Feature",
  "properties": {
    "addr:full":"5840 Youngstown Warren Rd Niles OH 44446",
    "addr:housenumber":"5840",
    "addr:postcode":"44446",
    "addr:street":"Youngstown Warren Rd",
    "iso:country":"US",
    "sg:address":"5840 Youngstown Warren Rd",
    "sg:city":"Niles",
    "sg:classifiers":[
        {
            "category":"Shopping",
            "subcategory":"Clothing, Apparel, & Fashions",
            "type":"Retail Goods"
        }
    ],
    "sg:phone":"+1 330 505 1103",
    "sg:postcode":"44446",
    "sg:province":"OH",
    "sg:tags":[
        "leather",
        "miscellaneous",
        "store",
        "accessory"
    ],
    "wof:name":"Cycle Leather Outlet Niles",
    "wof:placetype":"venue"
},
  "geometry": {"coordinates":[-80.74286499999999,41.207173],"type":"Point"}
}