{
  "type": "Feature",
  "properties": {
    "iso:country":"US",
    "sg:address":"1750 E Dublin Granville Rd",
    "sg:city":"Columbus",
    "sg:classifiers":[
        {
            "category":"Retail",
            "subcategory":"Auto Repair",
            "type":"Services"
        }
    ],
    "sg:phone":"+1 614 882 5077",
    "sg:postcode":"43229",
    "sg:province":"OH",
    "sg:tags":[
        "repairing",
        "automobile"
    ],
    "wof:name":"Fogle's Automotive Svc",
    "wof:placetype":"venue"
},
  "geometry": {"coordinates":[-82.97256299999999,40.087145],"type":"Point"}
}