{
  "type": "Feature",
  "properties": {
    "addr:full": "1750 E Dublin Granville Rd Columbus OH 43229",
    "addr:housenumber": "1750",
    "addr:postcode": "43229",
    "addr:street": "E Dublin Granville Rd",
    "iso:country": "US",
    "sg:address": "1750 E Dublin Granville Rd",
    "sg:city": "Columbus",
    "sg:classifiers": [
      {
        "category": "Retail",
        "subcategory": "Auto Repair",
        "type": "Services"
      }
    ],
    "sg:phone": "+1 614 882 5077",
    "sg:postcode": "43229",
    "sg:province": "OH",
    "sg:tags": [
      "repairing",
      "automobile"
    ],
    "wof:name": "Fogle's Automotive Svc",
    "wof:placetype": "venue"
  },
  "geometry": {"coordinates":[-82.972563,40.087145],"type":"Point"}
}
