{
  "type": "Feature",
  "properties": {
    "addr:full": "1177 Farnsworth Rd Waterville OH 43566",
    "addr:housenumber": "1177",
    "addr:postcode": "43566",
    "addr:street": "Farnsworth Rd",
    "iso:country": "US",
    "sg:address": "1177 Farnsworth Rd",
    "sg:city": "Waterville",
    "sg:classifiers": [
      {
        "category": "Manufacturing",
        "subcategory": "Metals",
        "type": "Manufacturing \u0026 Wholesale Goods"
      },
      {
        "category": "Wholesale",
        "subcategory": "Metals \u0026 Minerals",
        "type": "Manufacturing \u0026 Wholesale Goods"
      }
    ],
    "sg:phone": "+1 419 878 7591",
    "sg:postcode": "43566",
    "sg:province": "OH",
    "sg:tags": [
      "casting",
      "molding",
      "die",
      "mfg",
      "plastic",
      "zinc",
      "injection"
    ],
    "wof:name": "Reebar Die Casting Inc",
    "wof:placetype": "venue"
  },
  "geometry": {"coordinates":[-83.735229,41.498341],"type":"Point"}
}
