{
  "type": "Feature",
  "properties": {
    "iso:country":"US",
    "sg:address":"627 Fairfield Ave",
    "sg:city":"Fairborn",
    "sg:classifiers":[
        {
            "category":"Building & Trades",
            "subcategory":"Landscaping Services",
            "type":"Services"
        }
    ],
    "sg:phone":"+1 937 879 2925",
    "sg:postcode":"45324",
    "sg:province":"OH",
    "wof:name":"Atlantis Lawn Care Service",
    "wof:placetype":"venue"
},
  "geometry": {"coordinates":[-84.041792,39.79042],"type":"Point"}
}