{
  "type": "Feature",
  "properties": {
    "iso:country":"US",
    "sg:address":"28601 Chagrin Blvd",
    "sg:city":"Cleveland",
    "sg:classifiers":[
        {
            "category":"Real Estate",
            "subcategory":"Real Estate Agent",
            "type":"Services"
        }
    ],
    "sg:phone":"+1 216 831 2045",
    "sg:postcode":"44122",
    "sg:province":"OH",
    "wof:name":"Mutual Properties",
    "wof:placetype":"venue"
},
  "geometry": {"coordinates":[-81.47535999999999,41.462425],"type":"Point"}
}