{
  "type": "Feature",
  "properties": {
    "addr:full":"277 Moull St Newark OH 43055",
    "addr:housenumber":"277",
    "addr:postcode":"43055",
    "addr:street":"Moull St",
    "iso:country":"US",
    "sg:address":"277 Moull St",
    "sg:city":"Newark",
    "sg:classifiers":[
        {
            "category":"Real Estate",
            "subcategory":"Real Estate Agent",
            "type":"Services"
        }
    ],
    "sg:phone":"+1 740 344 0390",
    "sg:postcode":"43055",
    "sg:province":"OH",
    "sg:tags":[
        "appraiser"
    ],
    "wof:name":"Brent D Smith Appraisals",
    "wof:placetype":"venue"
},
  "geometry": {"coordinates":[-82.42138,40.070365],"type":"Point"}
}