{
  "type": "Feature",
  "properties": {
    "addr:full":"2195 Broehm Rd Columbus OH 43207",
    "addr:housenumber":"2195",
    "addr:postcode":"43207",
    "addr:street":"Broehm Rd",
    "iso:country":"US",
    "sg:address":"2195 Broehm Rd",
    "sg:city":"Columbus",
    "sg:classifiers":[
        {
            "category":"Freight",
            "type":"Transportation"
        }
    ],
    "sg:phone":"+1 614 491 0007",
    "sg:postcode":"43207",
    "sg:province":"OH",
    "sg:tags":[
        "warehouse",
        "self",
        "storage",
        "warehousing"
    ],
    "wof:name":"First Service Warehouse Inc",
    "wof:placetype":"venue"
},
  "geometry": {"coordinates":[-82.94923199999999,39.871104],"type":"Point"}
}