{
  "type": "Feature",
  "properties": {
    "addr:full": "1045 Eagon St Barberton OH 44203",
    "addr:housenumber": "1045",
    "addr:postcode": "44203",
    "addr:street": "Eagon St",
    "iso:country": "US",
    "sg:address": "1045 Eagon St",
    "sg:city": "Barberton",
    "sg:classifiers": [
      {
        "category": "Wholesale",
        "subcategory": "Electrical",
        "type": "Manufacturing \u0026 Wholesale Goods"
      }
    ],
    "sg:phone": "+1 330 785 5000",
    "sg:postcode": "44203",
    "sg:province": "OH",
    "sg:tags": [
      "equipment",
      "electronic",
      "supply"
    ],
    "wof:name": "Tritec Distribution Svc",
    "wof:placetype": "venue"
  },
  "geometry": {"coordinates":[-81.57926,41.031707],"type":"Point"}
}
