{
  "type": "Feature",
  "properties": {
    "iso:country":"US",
    "sg:address":"1045 Eagon St",
    "sg:city":"Barberton",
    "sg:classifiers":[
        {
            "category":"Wholesale",
            "subcategory":"Electrical",
            "type":"Manufacturing & Wholesale Goods"
        }
    ],
    "sg:phone":"+1 330 785 5000",
    "sg:postcode":"44203",
    "sg:province":"OH",
    "sg:tags":[
        "equipment",
        "electronic",
        "supply"
    ],
    "wof:name":"Tritec Distribution Svc",
    "wof:placetype":"venue"
},
  "geometry": {"coordinates":[-81.57926,41.031707],"type":"Point"}
}