{
  "type": "Feature",
  "properties": {
    "addr:full":"14 S Paint St Chillicothe OH 45601",
    "addr:housenumber":"14",
    "addr:postcode":"45601",
    "addr:street":"S Paint St",
    "iso:country":"US",
    "sg:address":"14 S Paint St",
    "sg:city":"Chillicothe",
    "sg:classifiers":[
        {
            "category":"Social Services",
            "subcategory":"Adult Care",
            "type":"Services"
        }
    ],
    "sg:phone":"+1 740 773 4630",
    "sg:postcode":"45601",
    "sg:province":"OH",
    "sg:tags":[
        "home",
        "residential"
    ],
    "wof:name":"Liberty Village Senior Comm",
    "wof:placetype":"venue"
},
  "geometry": {"coordinates":[-82.982094,39.33281],"type":"Point"}
}