{
  "type": "Feature",
  "properties": {
    "addr:full":"7777 Wall St Cleveland OH 44125",
    "addr:housenumber":"7777",
    "addr:postcode":"44125",
    "addr:street":"Wall St",
    "iso:country":"US",
    "sg:address":"7777 Wall St",
    "sg:city":"Cleveland",
    "sg:classifiers":[
        {
            "category":"Manufacturing",
            "subcategory":"Metals",
            "type":"Manufacturing & Wholesale Goods"
        }
    ],
    "sg:phone":"+1 216 524 1941",
    "sg:postcode":"44125",
    "sg:province":"OH",
    "wof:name":"Lgi Metal Finishing Company",
    "wof:placetype":"venue"
},
  "geometry": {"coordinates":[-81.629957,41.405984],"type":"Point"}
}