{
  "type": "Feature",
  "properties": {
    "addr:full": "4516 Church Rd Urbana OH 43078",
    "addr:housenumber": "4516",
    "addr:postcode": "43078",
    "addr:street": "Church Rd",
    "iso:country": "US",
    "sg:address": "4516 Church Rd",
    "sg:city": "Urbana",
    "sg:phone": "+1 937 652 3621",
    "sg:postcode": "43078",
    "sg:province": "OH",
    "sg:tags": [
      "farm",
      "grain",
      "cash"
    ],
    "wof:name": "Michael McGuire",
    "wof:placetype": "venue"
  },
  "geometry": {"coordinates":[-83.839636,40.185043],"type":"Point"}
}
