{
  "type": "Feature",
  "properties": {
    "iso:country":"US",
    "sg:address":"4516 Church Rd",
    "sg:city":"Urbana",
    "sg:phone":"+1 937 652 3621",
    "sg:postcode":"43078",
    "sg:province":"OH",
    "sg:tags":[
        "farm",
        "grain",
        "cash"
    ],
    "wof:name":"Michael McGuire",
    "wof:placetype":"venue"
},
  "geometry": {"coordinates":[-83.839636,40.185043],"type":"Point"}
}