{
  "type": "Feature",
  "properties": {
    "iso:country":"US",
    "sg:address":"496 W 1st Ave",
    "sg:city":"Columbus",
    "sg:classifiers":[
        {
            "category":"Organizations",
            "subcategory":"Religious Organization",
            "type":"Services"
        }
    ],
    "sg:phone":"+1 614 297 8063",
    "sg:postcode":"43201",
    "sg:province":"OH",
    "sg:tags":[
        "church"
    ],
    "wof:name":"St Pauls Baptist Church",
    "wof:placetype":"venue"
},
  "geometry": {"coordinates":[-83.018107,39.98068],"type":"Point"}
}