{
  "type": "Feature",
  "properties": {
    "addr:full":"21 W Washington St Athens OH 45701",
    "addr:housenumber":"21",
    "addr:postcode":"45701",
    "addr:street":"W Washington St",
    "iso:country":"US",
    "sg:address":"21 W Washington St",
    "sg:city":"Athens",
    "sg:classifiers":[
        {
            "category":"Professional",
            "subcategory":"Art Services",
            "type":"Services"
        }
    ],
    "sg:phone":"+1 740 594 5853",
    "sg:postcode":"45701",
    "sg:province":"OH",
    "sg:tags":[
        "photographer"
    ],
    "wof:name":"Luke Potter Photography",
    "wof:placetype":"venue"
},
  "geometry": {"coordinates":[-82.10169,39.329138],"type":"Point"}
}