{
  "type": "Feature",
  "properties": {
    "iso:country":"US",
    "sg:address":"3441 Warsaw Ave",
    "sg:city":"Cincinnati",
    "sg:classifiers":[
        {
            "category":"Shopping",
            "subcategory":"Clothing, Apparel, & Fashions",
            "type":"Retail Goods"
        }
    ],
    "sg:phone":"+1 513 471 3333",
    "sg:postcode":"45205",
    "sg:province":"OH",
    "wof:name":"Exclusive Wear",
    "wof:placetype":"venue"
},
  "geometry": {"coordinates":[-84.56818199999999,39.110257],"type":"Point"}
}