{
  "type": "Feature",
  "properties": {
    "addr:full": "590 N Hague Ave Columbus OH 43204",
    "addr:housenumber": "590",
    "addr:postcode": "43204",
    "addr:street": "N Hague Ave",
    "iso:country": "US",
    "sg:address": "590 N Hague Ave",
    "sg:city": "Columbus",
    "sg:classifiers": [
      {
        "category": "Food \u0026 Beverages",
        "subcategory": "Bakery",
        "type": "Retail Goods"
      },
      {
        "category": "Wholesale",
        "subcategory": "Groceries",
        "type": "Manufacturing \u0026 Wholesale Goods"
      }
    ],
    "sg:phone": "+1 614 276 5477",
    "sg:postcode": "43204",
    "sg:province": "OH",
    "sg:tags": [
      "baker"
    ],
    "sg:website": "www.nicklesbakery.com",
    "wof:name": "Nickles Bakery Inc",
    "wof:placetype": "venue"
  },
  "geometry": {"coordinates":[-83.078053,39.967345],"type":"Point"}
}
