{
  "type": "Feature",
  "properties": {
    "iso:country":"US",
    "sg:address":"590 N Hague Ave",
    "sg:city":"Columbus",
    "sg:classifiers":[
        {
            "category":"Food & Beverages",
            "subcategory":"Bakery",
            "type":"Retail Goods"
        },
        {
            "category":"Wholesale",
            "subcategory":"Groceries",
            "type":"Manufacturing & Wholesale Goods"
        }
    ],
    "sg:phone":"+1 614 276 5477",
    "sg:postcode":"43204",
    "sg:province":"OH",
    "sg:tags":[
        "baker"
    ],
    "sg:website":"www.nicklesbakery.com",
    "wof:name":"Nickles Bakery Inc",
    "wof:placetype":"venue"
},
  "geometry": {"coordinates":[-83.078053,39.967345],"type":"Point"}
}