{
  "type": "Feature",
  "properties": {
    "addr:full":"3839 Loveland Rd Youngstown OH 44502",
    "addr:housenumber":"3839",
    "addr:postcode":"44502",
    "addr:street":"Loveland Rd",
    "iso:country":"US",
    "sg:address":"3839 Loveland Rd",
    "sg:city":"Youngstown",
    "sg:classifiers":[
        {
            "category":"Professional",
            "subcategory":"Lawyer & Legal Services",
            "type":"Services"
        }
    ],
    "sg:phone":"+1 330 758 1781",
    "sg:postcode":"44502",
    "sg:province":"OH",
    "sg:tags":[
        "attorney"
    ],
    "wof:name":"Charles Draa",
    "wof:placetype":"venue"
},
  "geometry": {"coordinates":[-80.61582799999999,41.060892],"type":"Point"}
}