{
  "type": "Feature",
  "properties": {
    "addr:full": "30625 Solon Industrial Pkwy Cleveland OH 44139",
    "addr:postcode": "30625;44139",
    "addr:street": "Industrial Pkwy",
    "iso:country": "US",
    "sg:address": "30625 Solon Industrial Pkwy",
    "sg:city": "Cleveland",
    "sg:classifiers": [
      {
        "category": "Professional",
        "type": "Services"
      }
    ],
    "sg:phone": "+1 440 248 8645",
    "sg:postcode": "44139",
    "sg:province": "OH",
    "sg:tags": [
      "establishment"
    ],
    "wof:name": "BTI",
    "wof:placetype": "venue"
  },
  "geometry": {"coordinates":[-81.464885,41.373098],"type":"Point"}
}
