{
  "type": "Feature",
  "properties": {
    "iso:country":"US",
    "sg:address":"915 Michigan St",
    "sg:city":"Sidney",
    "sg:classifiers":[
        {
            "category":"Health Services",
            "subcategory":"Doctor",
            "type":"Services"
        }
    ],
    "sg:phone":"+1 937 492 6438",
    "sg:postcode":"45365",
    "sg:province":"OH",
    "sg:tags":[
        "physician",
        "surgeon"
    ],
    "wof:name":"C Gill Hoang MD",
    "wof:placetype":"venue"
},
  "geometry": {"coordinates":[-84.169059,40.287934],"type":"Point"}
}