{
  "type": "Feature",
  "properties": {
    "addr:full":"5220 Hauserman Rd Cleveland OH 44130",
    "addr:housenumber":"5220",
    "addr:postcode":"44130",
    "addr:street":"Hauserman Rd",
    "iso:country":"US",
    "sg:address":"5220 Hauserman Rd",
    "sg:city":"Cleveland",
    "sg:classifiers":[
        {
            "category":"Shopping",
            "type":"Retail Goods"
        }
    ],
    "sg:phone":"+1 440 842 5504",
    "sg:postcode":"44130",
    "sg:province":"OH",
    "sg:tags":[
        "religious"
    ],
    "sg:website":"www.henningers.com",
    "wof:name":"Henninger's",
    "wof:placetype":"venue"
},
  "geometry": {"coordinates":[-81.756728,41.415108],"type":"Point"}
}