{
  "type": "Feature",
  "properties": {
    "iso:country":"US",
    "sg:address":"7650 Rivers Edge Dr",
    "sg:city":"Columbus",
    "sg:classifiers":[
        {
            "category":"Professional",
            "subcategory":"Employment Agencies",
            "type":"Services"
        }
    ],
    "sg:phone":"+1 614 785 0111",
    "sg:postcode":"43235",
    "sg:province":"OH",
    "wof:name":"Sales Consultants",
    "wof:placetype":"venue"
},
  "geometry": {"coordinates":[-83.03412299999999,40.12182],"type":"Point"}
}