{
  "type": "Feature",
  "properties": {
    "iso:country":"US",
    "sg:address":"7865 Droesch Rd",
    "sg:city":"Maria Stein",
    "sg:classifiers":[
        {
            "category":"Real Estate",
            "subcategory":"Real Estate Operator",
            "type":"Services"
        }
    ],
    "sg:phone":"+1 419 925 4156",
    "sg:postcode":"45860",
    "sg:province":"OH",
    "sg:tags":[
        "property",
        "lessor"
    ],
    "wof:name":"D & B Poultry",
    "wof:placetype":"venue"
},
  "geometry": {"coordinates":[-84.496394,40.422355],"type":"Point"}
}