{
  "type": "Feature",
  "properties": {
    "addr:full": "7865 Droesch Rd Maria Stein OH 45860",
    "addr:housenumber": "7865",
    "addr:postcode": "45860",
    "addr:street": "Droesch Rd",
    "iso:country": "US",
    "sg:address": "7865 Droesch Rd",
    "sg:city": "Maria Stein",
    "sg:classifiers": [
      {
        "category": "Real Estate",
        "subcategory": "Real Estate Operator",
        "type": "Services"
      }
    ],
    "sg:phone": "+1 419 925 4156",
    "sg:postcode": "45860",
    "sg:province": "OH",
    "sg:tags": [
      "property",
      "lessor"
    ],
    "wof:name": "D \u0026 B Poultry",
    "wof:placetype": "venue"
  },
  "geometry": {"coordinates":[-84.496394,40.422355],"type":"Point"}
}
