{
  "type": "Feature",
  "properties": {
    "addr:full":"692 W Andover Rd Mansfield OH 44907",
    "addr:housenumber":"692",
    "addr:postcode":"44907",
    "addr:street":"W Andover Rd",
    "iso:country":"US",
    "sg:address":"692 W Andover Rd",
    "sg:city":"Mansfield",
    "sg:classifiers":[
        {
            "category":"Recreation",
            "type":"Entertainment"
        }
    ],
    "sg:phone":"+1 419 756 0261",
    "sg:postcode":"44907",
    "sg:province":"OH",
    "sg:tags":[
        "swim",
        "club"
    ],
    "wof:name":"Woodland Club Inc",
    "wof:placetype":"venue"
},
  "geometry": {"coordinates":[-82.541167,40.734745],"type":"Point"}
}