{
  "type": "Feature",
  "properties": {
    "addr:full":"7000 Center St Cincinnati OH 45243",
    "addr:housenumber":"7000",
    "addr:postcode":"45243",
    "addr:street":"Center St",
    "iso:country":"US",
    "sg:address":"7000 Center St",
    "sg:city":"Cincinnati",
    "sg:classifiers":[
        {
            "category":"Professional",
            "type":"Services"
        }
    ],
    "sg:phone":"+1 513 271 2079",
    "sg:postcode":"45243",
    "sg:province":"OH",
    "sg:tags":[
        "establishment"
    ],
    "wof:name":"Van Ness Prop",
    "wof:placetype":"venue"
},
  "geometry": {"coordinates":[-84.360991,39.189651],"type":"Point"}
}