{
  "type": "Feature",
  "properties": {
    "iso:country":"US",
    "sg:address":"99 Bean Rd",
    "sg:city":"The Plains",
    "sg:classifiers":[
        {
            "category":"Professional",
            "type":"Services"
        }
    ],
    "sg:phone":"+1 740 797 7361",
    "sg:postcode":"45780",
    "sg:province":"OH",
    "wof:name":"Phil Koska",
    "wof:placetype":"venue"
},
  "geometry": {"coordinates":[-82.141904,39.369969],"type":"Point"}
}