{
  "type": "Feature",
  "properties": {
    "addr:full":"4300 Hamann Pkwy Willoughby OH 44094",
    "addr:postcode":"4300;44094",
    "addr:street":"Hamann Pkwy",
    "iso:country":"US",
    "sg:address":"4300 Hamann Pkwy",
    "sg:city":"Willoughby",
    "sg:classifiers":[
        {
            "category":"Manufacturing",
            "subcategory":"Rubber & Plastics",
            "type":"Manufacturing & Wholesale Goods"
        }
    ],
    "sg:phone":"+1 440 269 2300",
    "sg:postcode":"44094",
    "sg:province":"OH",
    "sg:tags":[
        "product"
    ],
    "sg:website":"www.castnylon.com",
    "wof:name":"Cast Nylons LTD",
    "wof:placetype":"venue"
},
  "geometry": {"coordinates":[-81.421528,41.630642],"type":"Point"}
}