{
  "type": "Feature",
  "properties": {
    "addr:full": "1101 Giant Oaks Mill Rd Wheelersburg OH 45694",
    "addr:housenumber": "1101",
    "addr:postcode": "45694",
    "addr:street": "Giant Oaks Mill Rd",
    "iso:country": "US",
    "sg:address": "1101 Giant Oaks Mill Rd",
    "sg:city": "Wheelersburg",
    "sg:classifiers": [
      {
        "category": "Farming",
        "subcategory": "Livestock Farm",
        "type": "Manufacturing \u0026 Wholesale Goods"
      }
    ],
    "sg:phone": "+1 740 574 5643",
    "sg:postcode": "45694",
    "sg:province": "OH",
    "sg:tags": [
      "animal",
      "general"
    ],
    "wof:name": "Woodrow \u0026 Danny Dyer",
    "wof:placetype": "venue"
  },
  "geometry": {"coordinates":[-82.837346,38.694231],"type":"Point"}
}
