{
  "type": "Feature",
  "properties": {
    "iso:country":"US",
    "sg:address":"1101 Giant Oaks Mill Rd",
    "sg:city":"Wheelersburg",
    "sg:classifiers":[
        {
            "category":"Farming",
            "subcategory":"Livestock Farm",
            "type":"Manufacturing & Wholesale Goods"
        }
    ],
    "sg:phone":"+1 740 574 5643",
    "sg:postcode":"45694",
    "sg:province":"OH",
    "sg:tags":[
        "animal",
        "general"
    ],
    "wof:name":"Woodrow & Danny Dyer",
    "wof:placetype":"venue"
},
  "geometry": {"coordinates":[-82.837346,38.694231],"type":"Point"}
}