{
  "type": "Feature",
  "properties": {
    "iso:country":"US",
    "sg:address":"464 Parkview Dr",
    "sg:city":"Smithville",
    "sg:classifiers":[
        {
            "category":"Manufacturing",
            "subcategory":"Toys & Sporting Goods",
            "type":"Manufacturing & Wholesale Goods"
        }
    ],
    "sg:phone":"+1 330 669 3782",
    "sg:postcode":"44677",
    "sg:province":"OH",
    "sg:tags":[
        "mfg"
    ],
    "wof:name":"Beckis Wobble Yous",
    "wof:placetype":"venue"
},
  "geometry": {"coordinates":[-81.854418,40.859942],"type":"Point"}
}