{
  "type": "Feature",
  "properties": {
    "addr:full": "464 Parkview Dr Smithville OH 44677",
    "addr:housenumber": "464",
    "addr:postcode": "44677",
    "addr:street": "Parkview Dr",
    "iso:country": "US",
    "sg:address": "464 Parkview Dr",
    "sg:city": "Smithville",
    "sg:classifiers": [
      {
        "category": "Manufacturing",
        "subcategory": "Toys \u0026 Sporting Goods",
        "type": "Manufacturing \u0026 Wholesale Goods"
      }
    ],
    "sg:phone": "+1 330 669 3782",
    "sg:postcode": "44677",
    "sg:province": "OH",
    "sg:tags": [
      "mfg"
    ],
    "wof:name": "Beckis Wobble Yous",
    "wof:placetype": "venue"
  },
  "geometry": {"coordinates":[-81.854418,40.859942],"type":"Point"}
}
