{
  "type": "Feature",
  "properties": {
    "addr:full": "381 E Church St Marion OH 43302",
    "addr:housenumber": "381",
    "addr:postcode": "43302",
    "addr:street": "E Church St",
    "iso:country": "US",
    "sg:address": "381 E Church St",
    "sg:city": "Marion",
    "sg:classifiers": [
      {
        "category": "Health Services",
        "subcategory": "Health Practitioner",
        "type": "Services"
      }
    ],
    "sg:phone": "+1 740 223 7724",
    "sg:postcode": "43302",
    "sg:province": "OH",
    "sg:tags": [
      "merchandise"
    ],
    "wof:name": "Wrights Avada Audiology \u0026 Hea",
    "wof:placetype": "venue"
  },
  "geometry": {"coordinates":[-83.122014,40.587455],"type":"Point"}
}
