{
  "type": "Feature",
  "properties": {
    "iso:country":"US",
    "sg:address":"5598 Footville-Richmond Rd",
    "sg:city":"Rock Creek",
    "sg:classifiers":[
        {
            "category":"Autos & Motor Vehicles",
            "subcategory":"Auto Supplies",
            "type":"Retail Goods"
        }
    ],
    "sg:phone":"+1 440 474 9575",
    "sg:postcode":"44084",
    "sg:province":"OH",
    "sg:tags":[
        "tire"
    ],
    "wof:name":"Smolic Tire",
    "wof:placetype":"venue"
},
  "geometry": {"coordinates":[-80.934339,41.661593],"type":"Point"}
}