{
  "type": "Feature",
  "properties": {
    "iso:country":"US",
    "sg:address":"308 E Broad St",
    "sg:city":"Elyria",
    "sg:classifiers":[
        {
            "category":"Food & Beverages",
            "subcategory":"Liquor & Beverages",
            "type":"Retail Goods"
        }
    ],
    "sg:phone":"+1 440 322 4009",
    "sg:postcode":"44035",
    "sg:province":"OH",
    "sg:tags":[
        "alcoholic"
    ],
    "wof:name":"Beverage Warehouse",
    "wof:placetype":"venue"
},
  "geometry": {"coordinates":[-82.091843,41.367554],"type":"Point"}
}