{
  "type": "Feature",
  "properties": {
    "addr:full":"7425 York Rd Cleveland OH 44130",
    "addr:housenumber":"7425",
    "addr:postcode":"44130",
    "addr:street":"York Rd",
    "iso:country":"US",
    "sg:address":"7425 York Rd",
    "sg:city":"Cleveland",
    "sg:classifiers":[
        {
            "category":"Restaurant",
            "type":"Food & Drink"
        }
    ],
    "sg:phone":"+1 440 888 8400",
    "sg:postcode":"44130",
    "sg:province":"OH",
    "sg:tags":[
        "pizza"
    ],
    "sg:website":"http://www.marsellaspizza.net",
    "wof:name":"Marsella's Pizza",
    "wof:placetype":"venue"
},
  "geometry": {"coordinates":[-81.759743,41.363159],"type":"Point"}
}