{
  "type": "Feature",
  "properties": {
    "addr:full": "8732 Sequoia Ave SE Waynesburg OH 44688",
    "addr:housenumber": "8732",
    "addr:postcode": "44688",
    "addr:street": "Sequoia Ave Se",
    "iso:country": "US",
    "sg:address": "8732 Sequoia Ave SE",
    "sg:city": "Waynesburg",
    "sg:classifiers": [
      {
        "category": "Freight",
        "type": "Transportation"
      }
    ],
    "sg:phone": "+1 330 866 4202",
    "sg:postcode": "44688",
    "sg:province": "OH",
    "sg:tags": [
      "operator",
      "local",
      "trucking"
    ],
    "wof:name": "Thomas Trucking",
    "wof:placetype": "venue"
  },
  "geometry": {"coordinates":[-81.268788,40.675166],"type":"Point"}
}
