{
  "type": "Feature",
  "properties": {
    "addr:full": "1828 Woodville Pike Goshen OH 45122",
    "addr:housenumber": "1828",
    "addr:postcode": "45122",
    "addr:street": "Woodville Pike",
    "iso:country": "US",
    "sg:address": "1828 Woodville Pike",
    "sg:city": "Goshen",
    "sg:classifiers": [
      {
        "category": "Organizations",
        "subcategory": "Religious Organization",
        "type": "Services"
      }
    ],
    "sg:phone": "+1 513 625 5512",
    "sg:postcode": "45122",
    "sg:province": "OH",
    "sg:tags": [
      "church"
    ],
    "wof:name": "First Baptist Church Of Goshen",
    "wof:placetype": "venue"
  },
  "geometry": {"coordinates":[-84.169914,39.207809],"type":"Point"}
}
