{
  "type": "Feature",
  "properties": {
    "iso:country":"US",
    "sg:address":"1828 Woodville Pike",
    "sg:city":"Goshen",
    "sg:classifiers":[
        {
            "category":"Organizations",
            "subcategory":"Religious Organization",
            "type":"Services"
        }
    ],
    "sg:phone":"+1 513 625 5512",
    "sg:postcode":"45122",
    "sg:province":"OH",
    "sg:tags":[
        "church"
    ],
    "wof:name":"First Baptist Church Of Goshen",
    "wof:placetype":"venue"
},
  "geometry": {"coordinates":[-84.16991400000001,39.207809],"type":"Point"}
}