{
  "type": "Feature",
  "properties": {
    "iso:country":"US",
    "sg:address":"3415 Maple Ave",
    "sg:city":"Zanesville",
    "sg:classifiers":[
        {
            "category":"Autos & Motor Vehicles",
            "subcategory":"Fuel & Gas Station",
            "type":"Retail Goods"
        }
    ],
    "sg:phone":"+1 740 453 0802",
    "sg:postcode":"43701",
    "sg:province":"OH",
    "sg:tags":[
        "grocery",
        "station",
        "gasoline"
    ],
    "wof:name":"Maple Avenue Duchess",
    "wof:placetype":"venue"
},
  "geometry": {"coordinates":[-82.020079,39.9831],"type":"Point"}
}