{
  "type": "Feature",
  "properties": {
    "addr:full":"200 Ohio Ave Pandora OH 45877",
    "addr:housenumber":"200",
    "addr:postcode":"45877",
    "addr:street":"Ohio Ave",
    "iso:country":"US",
    "sg:address":"200 Ohio Ave",
    "sg:city":"Pandora",
    "sg:classifiers":[
        {
            "category":"Building & Trades",
            "subcategory":"Construction",
            "type":"Services"
        }
    ],
    "sg:phone":"+1 419 384 3577",
    "sg:postcode":"45877",
    "sg:province":"OH",
    "sg:tags":[
        "painter"
    ],
    "wof:name":"Allco Inc",
    "wof:placetype":"venue"
},
  "geometry": {"coordinates":[-83.960421,40.939058],"type":"Point"}
}