{
  "type": "Feature",
  "properties": {
    "addr:full": "2416 Shepler Church Ave SW Canton OH 44706",
    "addr:housenumber": "2416",
    "addr:postcode": "44706",
    "addr:street": "Shepler Church Ave Sw",
    "iso:country": "US",
    "sg:address": "2416 Shepler Church Ave SW",
    "sg:city": "Canton",
    "sg:classifiers": [
      {
        "category": "Manufacturing",
        "subcategory": "Signs",
        "type": "Manufacturing \u0026 Wholesale Goods"
      }
    ],
    "sg:phone": "+1 330 454 6632",
    "sg:postcode": "44706",
    "sg:province": "OH",
    "wof:name": "Downard's Pro Art",
    "wof:placetype": "venue"
  },
  "geometry": {"coordinates":[-81.40163,40.767227],"type":"Point"}
}
