{
  "type": "Feature",
  "properties": {
    "iso:country":"US",
    "sg:address":"2416 Shepler Church Ave SW",
    "sg:city":"Canton",
    "sg:classifiers":[
        {
            "category":"Manufacturing",
            "subcategory":"Signs",
            "type":"Manufacturing & Wholesale Goods"
        }
    ],
    "sg:phone":"+1 330 454 6632",
    "sg:postcode":"44706",
    "sg:province":"OH",
    "wof:name":"Downard's Pro Art",
    "wof:placetype":"venue"
},
  "geometry": {"coordinates":[-81.40163,40.767227],"type":"Point"}
}