{
  "type": "Feature",
  "properties": {
    "iso:country":"US",
    "sg:address":"3420 E 105th St",
    "sg:city":"Cleveland",
    "sg:classifiers":[
        {
            "category":"Professional",
            "type":"Services"
        }
    ],
    "sg:phone":"+1 216 206 2409",
    "sg:postcode":"44104",
    "sg:province":"OH",
    "wof:name":"Rch Development LLC",
    "wof:placetype":"venue"
},
  "geometry": {"coordinates":[-81.61164100000001,41.465383],"type":"Point"}
}