{
  "type": "Feature",
  "properties": {
    "addr:full": "3420 E 105th St Cleveland OH 44104",
    "addr:housenumber": "3420",
    "addr:postcode": "44104",
    "addr:street": "E 105Th St",
    "iso:country": "US",
    "sg:address": "3420 E 105th St",
    "sg:city": "Cleveland",
    "sg:classifiers": [
      {
        "category": "Professional",
        "type": "Services"
      }
    ],
    "sg:phone": "+1 216 206 2409",
    "sg:postcode": "44104",
    "sg:province": "OH",
    "wof:name": "Rch Development LLC",
    "wof:placetype": "venue"
  },
  "geometry": {"coordinates":[-81.611641,41.465383],"type":"Point"}
}
