{
  "type": "Feature",
  "properties": {
    "iso:country":"US",
    "sg:address":"3242 Lincoln Way E",
    "sg:city":"Massillon",
    "sg:classifiers":[
        {
            "category":"Restaurant",
            "type":"Food & Drink"
        },
        {
            "category":"Bars & Pubs",
            "type":"Food & Drink"
        }
    ],
    "sg:phone":"+1 330 833 3046",
    "sg:postcode":"44646",
    "sg:province":"OH",
    "sg:tags":[
        "drinking"
    ],
    "wof:name":"Ruben's Pub",
    "wof:placetype":"venue"
},
  "geometry": {"coordinates":[-81.473287,40.795173],"type":"Point"}
}