{
  "type": "Feature",
  "properties": {
    "addr:full": "3242 Lincoln Way E Massillon OH 44646",
    "addr:housenumber": "3242",
    "addr:postcode": "44646",
    "addr:street": "Lincoln Way E",
    "iso:country": "US",
    "sg:address": "3242 Lincoln Way E",
    "sg:city": "Massillon",
    "sg:classifiers": [
      {
        "category": "Restaurant",
        "type": "Food \u0026 Drink"
      },
      {
        "category": "Bars \u0026 Pubs",
        "type": "Food \u0026 Drink"
      }
    ],
    "sg:phone": "+1 330 833 3046",
    "sg:postcode": "44646",
    "sg:province": "OH",
    "sg:tags": [
      "drinking"
    ],
    "wof:name": "Ruben's Pub",
    "wof:placetype": "venue"
  },
  "geometry": {"coordinates":[-81.473287,40.795173],"type":"Point"}
}
