{
  "type": "Feature",
  "properties": {
    "iso:country":"US",
    "sg:address":"13437 Lorain Ave",
    "sg:city":"Cleveland",
    "sg:classifiers":[
        {
            "category":"Shopping",
            "subcategory":"Computers & Home Electronics",
            "type":"Retail Goods"
        }
    ],
    "sg:phone":"+1 216 252 2098",
    "sg:postcode":"44111",
    "sg:province":"OH",
    "wof:name":"Cleve Curtis Mathes",
    "wof:placetype":"venue"
},
  "geometry": {"coordinates":[-81.784375,41.456881],"type":"Point"}
}