{
  "type": "Feature",
  "properties": {
    "addr:full": "620 Deauville Dr Dayton OH 45429",
    "addr:housenumber": "620",
    "addr:postcode": "45429",
    "addr:street": "Deauville Dr",
    "iso:country": "US",
    "sg:address": "620 Deauville Dr",
    "sg:city": "Dayton",
    "sg:classifiers": [
      {
        "category": "Professional",
        "subcategory": "Art Services",
        "type": "Services"
      }
    ],
    "sg:phone": "+1 937 439 1536",
    "sg:postcode": "45429",
    "sg:province": "OH",
    "sg:tags": [
      "artist"
    ],
    "wof:name": "Indian Creek Co",
    "wof:placetype": "venue"
  },
  "geometry": {"coordinates":[-84.149527,39.664635],"type":"Point"}
}
