{
  "type": "Feature",
  "properties": {
    "iso:country":"US",
    "sg:address":"73 E Bel Meadow Ln",
    "sg:city":"Chagrin Falls",
    "sg:classifiers":[
        {
            "category":"Travel",
            "subcategory":"Travel Agent",
            "type":"Entertainment"
        }
    ],
    "sg:phone":"+1 440 338 1569",
    "sg:postcode":"44022",
    "sg:province":"OH",
    "sg:tags":[
        "agency"
    ],
    "wof:name":"Anchors LLC",
    "wof:placetype":"venue"
},
  "geometry": {"coordinates":[-81.331264,41.433346],"type":"Point"}
}