{
  "type": "Feature",
  "properties": {
    "iso:country":"US",
    "sg:address":"745 E Main St",
    "sg:city":"Newark",
    "sg:classifiers":[
        {
            "category":"Social Services",
            "type":"Services"
        }
    ],
    "sg:phone":"+1 740 345 0821",
    "sg:postcode":"43055",
    "sg:province":"OH",
    "sg:tags":[
        "senior",
        "citizen"
    ],
    "sg:website":"www.lcap.org",
    "wof:name":"Licking County Aging Program",
    "wof:placetype":"venue"
},
  "geometry": {"coordinates":[-82.372574,40.059971],"type":"Point"}
}