{
  "type": "Feature",
  "properties": {
    "iso:country":"US",
    "sg:address":"3611 Nantucket Dr",
    "sg:city":"Loveland",
    "sg:classifiers":[
        {
            "category":"Shopping",
            "subcategory":"Computers & Home Electronics",
            "type":"Retail Goods"
        }
    ],
    "sg:phone":"+1 513 583 1095",
    "sg:postcode":"45140",
    "sg:province":"OH",
    "sg:tags":[
        "software"
    ],
    "wof:name":"Pick Programmer's Shop",
    "wof:placetype":"venue"
},
  "geometry": {"coordinates":[-84.28486100000001,39.303097],"type":"Point"}
}