{
  "type": "Feature",
  "properties": {
    "iso:country":"US",
    "sg:address":"4740 Arbor Ave",
    "sg:city":"Sheffield Lake",
    "sg:classifiers":[
        {
            "category":"Building & Trades",
            "subcategory":"Construction",
            "type":"Services"
        }
    ],
    "sg:phone":"+1 440 277 8185",
    "sg:postcode":"44054",
    "sg:province":"OH",
    "sg:tags":[
        "house"
    ],
    "wof:name":"Henry A Nosse Remodeling",
    "wof:placetype":"venue"
},
  "geometry": {"coordinates":[-82.09316699999999,41.431193],"type":"Point"}
}