{
  "type": "Feature",
  "properties": {
    "addr:full": "4740 Arbor Ave Sheffield Lake OH 44054",
    "addr:housenumber": "4740",
    "addr:postcode": "44054",
    "addr:street": "Arbor Ave",
    "iso:country": "US",
    "sg:address": "4740 Arbor Ave",
    "sg:city": "Sheffield Lake",
    "sg:classifiers": [
      {
        "category": "Building \u0026 Trades",
        "subcategory": "Construction",
        "type": "Services"
      }
    ],
    "sg:phone": "+1 440 277 8185",
    "sg:postcode": "44054",
    "sg:province": "OH",
    "sg:tags": [
      "house"
    ],
    "wof:name": "Henry A Nosse Remodeling",
    "wof:placetype": "venue"
  },
  "geometry": {"coordinates":[-82.093167,41.431193],"type":"Point"}
}
