{
  "type": "Feature",
  "properties": {
    "addr:full": "1440 Lexington Ave Lorain OH 44052",
    "addr:housenumber": "1440",
    "addr:postcode": "44052",
    "addr:street": "Lexington Ave",
    "iso:country": "US",
    "sg:address": "1440 Lexington Ave",
    "sg:city": "Lorain",
    "sg:classifiers": [
      {
        "category": "Organizations",
        "subcategory": "Non-profit Organization",
        "type": "Services"
      }
    ],
    "sg:phone": "+1 440 246 5111",
    "sg:postcode": "44052",
    "sg:province": "OH",
    "sg:tags": [
      "information",
      "alcoholism",
      "treatment"
    ],
    "wof:name": "Compass House",
    "wof:placetype": "venue"
  },
  "geometry": {"coordinates":[-82.171981,41.456442],"type":"Point"}
}
