{
  "type": "Feature",
  "properties": {
    "addr:full": "5500 Church Hill Rd Zanesville OH 43701",
    "addr:housenumber": "5500",
    "addr:postcode": "43701",
    "addr:street": "Church Hill Rd",
    "iso:country": "US",
    "sg:address": "5500 Church Hill Rd",
    "sg:city": "Zanesville",
    "sg:classifiers": [
      {
        "category": "Organizations",
        "subcategory": "Religious Organization",
        "type": "Services"
      }
    ],
    "sg:phone": "+1 740 453 3421",
    "sg:postcode": "43701",
    "sg:province": "OH",
    "sg:tags": [
      "church"
    ],
    "wof:name": "Washington Twp Baptist Church",
    "wof:placetype": "venue"
  },
  "geometry": {"coordinates":[-81.951432,40.024679],"type":"Point"}
}
