{
  "type": "Feature",
  "properties": {
    "iso:country":"US",
    "sg:address":"8925 Mentor Ave",
    "sg:city":"Mentor",
    "sg:classifiers":[
        {
            "category":"Local Transit",
            "type":"Transportation"
        }
    ],
    "sg:phone":"+1 440 266 5466",
    "sg:postcode":"44060",
    "sg:province":"OH",
    "sg:tags":[
        "passenger"
    ],
    "wof:name":"Agem Limo Inc",
    "wof:placetype":"venue"
},
  "geometry": {"coordinates":[-81.319744,41.674872],"type":"Point"}
}