{
  "type": "Feature",
  "properties": {
    "addr:full": "495 S Lazelle St Columbus OH 43206",
    "addr:housenumber": "495",
    "addr:postcode": "43206",
    "addr:street": "S Lazelle St",
    "iso:country": "US",
    "sg:address": "495 S Lazelle St",
    "sg:city": "Columbus",
    "sg:classifiers": [
      {
        "category": "Food \u0026 Beverages",
        "subcategory": "Candy",
        "type": "Retail Goods"
      }
    ],
    "sg:phone": "+1 614 841 9521",
    "sg:postcode": "43206",
    "sg:province": "OH",
    "sg:tags": [
      "confectionery"
    ],
    "wof:name": "Anthony Thomas Candy Inc",
    "wof:placetype": "venue"
  },
  "geometry": {"coordinates":[-82.995234,39.952603],"type":"Point"}
}
