{
  "type": "Feature",
  "properties": {
    "iso:country":"US",
    "sg:address":"556 Davis Rd",
    "sg:city":"Cincinnati",
    "sg:classifiers":[
        {
            "category":"Building & Trades",
            "subcategory":"Construction",
            "type":"Services"
        }
    ],
    "sg:phone":"+1 513 752 1648",
    "sg:postcode":"45255",
    "sg:province":"OH",
    "sg:tags":[
        "hanging",
        "contractor"
    ],
    "wof:name":"Robert Woods Painting",
    "wof:placetype":"venue"
},
  "geometry": {"coordinates":[-84.30195500000001,39.056721],"type":"Point"}
}