{
  "type": "Feature",
  "properties": {
    "addr:full": "556 Davis Rd Cincinnati OH 45255",
    "addr:housenumber": "556",
    "addr:postcode": "45255",
    "addr:street": "Davis Rd",
    "iso:country": "US",
    "sg:address": "556 Davis Rd",
    "sg:city": "Cincinnati",
    "sg:classifiers": [
      {
        "category": "Building \u0026 Trades",
        "subcategory": "Construction",
        "type": "Services"
      }
    ],
    "sg:phone": "+1 513 752 1648",
    "sg:postcode": "45255",
    "sg:province": "OH",
    "sg:tags": [
      "hanging",
      "contractor"
    ],
    "wof:name": "Robert Woods Painting",
    "wof:placetype": "venue"
  },
  "geometry": {"coordinates":[-84.301955,39.056721],"type":"Point"}
}
