{
  "type": "Feature",
  "properties": {
    "addr:full":"3000 W Elm St Lima OH 45805",
    "addr:housenumber":"3000",
    "addr:postcode":"45805",
    "addr:street":"W Elm St",
    "iso:country":"US",
    "sg:address":"3000 W Elm St",
    "sg:city":"Lima",
    "sg:classifiers":[
        {
            "category":"Shopping",
            "subcategory":"Department Store",
            "type":"Retail Goods"
        }
    ],
    "sg:phone":"+1 419 999 5164",
    "sg:postcode":"45805",
    "sg:province":"OH",
    "wof:name":"Value City",
    "wof:placetype":"venue"
},
  "geometry": {"coordinates":[-84.16070499999999,40.737068],"type":"Point"}
}