{
  "type": "Feature",
  "properties": {
    "iso:country":"US",
    "sg:address":"11 E 4th St",
    "sg:city":"Dayton",
    "sg:classifiers":[
        {
            "category":"Government",
            "subcategory":"Office",
            "type":"Public Place"
        }
    ],
    "sg:phone":"+1 937 223 8839",
    "sg:postcode":"45402",
    "sg:province":"OH",
    "sg:tags":[
        "armed",
        "force",
        "recruiting"
    ],
    "wof:name":"US Air Force Recruiting",
    "wof:placetype":"venue"
},
  "geometry": {"coordinates":[-84.189791,39.758459],"type":"Point"}
}