{
  "type": "Feature",
  "properties": {
    "iso:country":"US",
    "sg:address":"385 Commercial St",
    "sg:city":"Marion",
    "sg:classifiers":[
        {
            "category":"Building & Trades",
            "subcategory":"Construction",
            "type":"Services"
        }
    ],
    "sg:phone":"+1 740 383 5174",
    "sg:postcode":"43302",
    "sg:province":"OH",
    "sg:tags":[
        "painter"
    ],
    "wof:name":"Helping Hand",
    "wof:placetype":"venue"
},
  "geometry": {"coordinates":[-83.134607,40.594181],"type":"Point"}
}