{
  "type": "Feature",
  "properties": {
    "addr:full":"14401 Co Rd 212 Findlay OH 45840",
    "addr:housenumber":"14401;212",
    "addr:postcode":"45840",
    "addr:street":"Co Rd",
    "iso:country":"US",
    "sg:address":"14401 Co Rd 212",
    "sg:city":"Findlay",
    "sg:classifiers":[
        {
            "category":"Shopping",
            "subcategory":"Computers & Home Electronics",
            "type":"Retail Goods"
        }
    ],
    "sg:phone":"+1 419 424 6300",
    "sg:postcode":"45840",
    "sg:province":"OH",
    "sg:tags":[
        "equipment",
        "electronic",
        "supply"
    ],
    "wof:name":"Best Buy",
    "wof:placetype":"venue"
},
  "geometry": {"coordinates":[-83.60418,41.080207],"type":"Point"}
}