{
  "type": "Feature",
  "properties": {
    "addr:full": "6361 Hickory Bark Dr Loveland OH 45140",
    "addr:housenumber": "6361",
    "addr:postcode": "45140",
    "addr:street": "Hickory Bark Dr",
    "iso:country": "US",
    "sg:address": "6361 Hickory Bark Dr",
    "sg:city": "Loveland",
    "sg:classifiers": [
      {
        "category": "Professional",
        "type": "Services"
      }
    ],
    "sg:phone": "+1 513 722 8244",
    "sg:postcode": "45140",
    "sg:province": "OH",
    "wof:name": "Paul Ventura",
    "wof:placetype": "venue"
  },
  "geometry": {"coordinates":[-84.218967,39.214651],"type":"Point"}
}
