{
  "type": "Feature",
  "properties": {
    "addr:full": "683 E Aurora Rd Macedonia OH 44056",
    "addr:housenumber": "683",
    "addr:postcode": "44056",
    "addr:street": "E Aurora Rd",
    "iso:country": "US",
    "sg:address": "683 E Aurora Rd",
    "sg:city": "Macedonia",
    "sg:classifiers": [
      {
        "category": "Restaurant",
        "type": "Food \u0026 Drink"
      }
    ],
    "sg:menulink": "http://www.allmenus.com/oh/macedonia/175541-arbys/menu/",
    "sg:phone": "+1 330 467 6022",
    "sg:postcode": "44056",
    "sg:province": "OH",
    "sg:tags": [
      "burger",
      "american"
    ],
    "wof:name": "Arby's",
    "wof:placetype": "venue"
  },
  "geometry": {"coordinates":[-81.51453,41.314131],"type":"Point"}
}
