{
  "type": "Feature",
  "properties": {
    "iso:country":"US",
    "sg:address":"683 E Aurora Rd",
    "sg:city":"Macedonia",
    "sg:classifiers":[
        {
            "category":"Restaurant",
            "type":"Food & Drink"
        }
    ],
    "sg:menulink":"http://www.allmenus.com/oh/macedonia/175541-arbys/menu/",
    "sg:phone":"+1 330 467 6022",
    "sg:postcode":"44056",
    "sg:province":"OH",
    "sg:tags":[
        "burger",
        "american"
    ],
    "wof:name":"Arby's",
    "wof:placetype":"venue"
},
  "geometry": {"coordinates":[-81.51452999999999,41.314131],"type":"Point"}
}