{
  "type": "Feature",
  "properties": {
    "iso:country":"US",
    "sg:address":"4395 Pennington Ln",
    "sg:city":"Athens",
    "sg:classifiers":[
        {
            "category":"Farming",
            "subcategory":"Livestock Farm",
            "type":"Manufacturing & Wholesale Goods"
        }
    ],
    "sg:phone":"+1 740 698 7060",
    "sg:postcode":"45701",
    "sg:province":"OH",
    "sg:tags":[
        "beef",
        "feedlot",
        "cattle"
    ],
    "wof:name":"Glen McDaniel",
    "wof:placetype":"venue"
},
  "geometry": {"coordinates":[-82.199421,39.269625],"type":"Point"}
}