{
  "type": "Feature",
  "properties": {
    "addr:full":"2104 Twp Hwy 221 Bloomingdale OH 43925",
    "addr:housenumber":"2104",
    "addr:postcode":"43925",
    "addr:street":"Twp Hwy 221",
    "iso:country":"US",
    "sg:address":"2104 Twp Hwy 221",
    "sg:city":"Bloomingdale",
    "sg:classifiers":[
        {
            "category":"Personal",
            "type":"Services"
        }
    ],
    "sg:phone":"+1 740 543 3999",
    "sg:postcode":"43925",
    "sg:province":"OH",
    "sg:tags":[
        "miscellaneous"
    ],
    "wof:name":"T 3 Personal Training",
    "wof:placetype":"venue"
},
  "geometry": {"coordinates":[-80.844127,40.424043],"type":"Point"}
}