{
  "type": "Feature",
  "properties": {
    "iso:country":"US",
    "sg:address":"7927 Meadowhaven Blvd",
    "sg:city":"Columbus",
    "sg:classifiers":[
        {
            "category":"Real Estate",
            "subcategory":"Real Estate Operator",
            "type":"Services"
        }
    ],
    "sg:phone":"+1 614 889 0578",
    "sg:postcode":"43235",
    "sg:province":"OH",
    "sg:tags":[
        "building",
        "apartment"
    ],
    "wof:name":"Remax Premiere Choice",
    "wof:placetype":"venue"
},
  "geometry": {"coordinates":[-83.088239,40.117811],"type":"Point"}
}