{
  "type": "Feature",
  "properties": {
    "iso:country":"US",
    "sg:address":"1974 E 61st St",
    "sg:city":"Cleveland",
    "sg:classifiers":[
        {
            "category":"Professional",
            "subcategory":"Business Services",
            "type":"Services"
        }
    ],
    "sg:phone":"+1 216 292 1070",
    "sg:postcode":"44103",
    "sg:province":"OH",
    "sg:tags":[
        "packaging"
    ],
    "wof:name":"Packaging Supply Corp",
    "wof:placetype":"venue"
},
  "geometry": {"coordinates":[-81.648208,41.505981],"type":"Point"}
}