{
  "type": "Feature",
  "properties": {
    "iso:country":"US",
    "sg:address":"5900 Maurice Ave",
    "sg:city":"Cleveland",
    "sg:classifiers":[
        {
            "category":"Manufacturing",
            "subcategory":"Apparel",
            "type":"Manufacturing & Wholesale Goods"
        }
    ],
    "sg:phone":"+1 216 271 8056",
    "sg:postcode":"44127",
    "sg:province":"OH",
    "sg:tags":[
        "product",
        "bed",
        "mfg"
    ],
    "sg:website":"www.firesidecomforts.com",
    "wof:name":"Fireside Comforts",
    "wof:placetype":"venue"
},
  "geometry": {"coordinates":[-81.648247,41.476884],"type":"Point"}
}