{
  "type": "Feature",
  "properties": {
    "addr:full":"3544 Wilson Ave Cincinnati OH 45229",
    "addr:housenumber":"3544",
    "addr:postcode":"45229",
    "addr:street":"Wilson Ave",
    "iso:country":"US",
    "sg:address":"3544 Wilson Ave",
    "sg:city":"Cincinnati",
    "sg:classifiers":[
        {
            "category":"Building & Trades",
            "subcategory":"Construction",
            "type":"Services"
        }
    ],
    "sg:phone":"+1 513 281 5937",
    "sg:postcode":"45229",
    "sg:province":"OH",
    "sg:tags":[
        "handyman"
    ],
    "wof:name":"Man-Around The House",
    "wof:placetype":"venue"
},
  "geometry": {"coordinates":[-84.50242,39.148597],"type":"Point"}
}