{
  "type": "Feature",
  "properties": {
    "iso:country":"US",
    "sg:address":"18534 Pearl Rd",
    "sg:city":"Cleveland",
    "sg:classifiers":[
        {
            "category":"Retail",
            "subcategory":"Car Wash",
            "type":"Services"
        }
    ],
    "sg:phone":"+1 440 238 0044",
    "sg:postcode":"44136",
    "sg:province":"OH",
    "sg:tags":[
        "polishing",
        "carwash",
        "washing"
    ],
    "wof:name":"New Image Auto & Van Wash",
    "wof:placetype":"venue"
},
  "geometry": {"coordinates":[-81.835917,41.275597],"type":"Point"}
}