{
  "type": "Feature",
  "properties": {
    "addr:full":"666 Jefferson Ave Defiance OH 43512",
    "addr:housenumber":"666",
    "addr:postcode":"43512",
    "addr:street":"Jefferson Ave",
    "iso:country":"US",
    "sg:address":"666 Jefferson Ave",
    "sg:city":"Defiance",
    "sg:classifiers":[
        {
            "category":"Wholesale",
            "subcategory":"Drugs",
            "type":"Manufacturing & Wholesale Goods"
        }
    ],
    "sg:phone":"+1 419 784 3518",
    "sg:postcode":"43512",
    "sg:province":"OH",
    "wof:name":"David Mc Master",
    "wof:placetype":"venue"
},
  "geometry": {"coordinates":[-84.362392,41.28153],"type":"Point"}
}