{
  "type": "Feature",
  "properties": {
    "iso:country":"US",
    "sg:address":"6007 Laverne Ave",
    "sg:city":"Cleveland",
    "sg:classifiers":[
        {
            "category":"Manufacturing",
            "subcategory":"Printing",
            "type":"Manufacturing & Wholesale Goods"
        }
    ],
    "sg:phone":"+1 216 661 5817",
    "sg:postcode":"44129",
    "sg:province":"OH",
    "sg:tags":[
        "lithographic",
        "commercial"
    ],
    "wof:name":"Rubicon Printed Products",
    "wof:placetype":"venue"
},
  "geometry": {"coordinates":[-81.730485,41.414968],"type":"Point"}
}