{
  "type": "Feature",
  "properties": {
    "addr:full": "320 Ludlow Ave Cincinnati OH 45220",
    "addr:housenumber": "320",
    "addr:postcode": "45220",
    "addr:street": "Ludlow Ave",
    "iso:country": "US",
    "sg:address": "320 Ludlow Ave",
    "sg:city": "Cincinnati",
    "sg:classifiers": [
      {
        "category": "Arts \u0026 Performance",
        "subcategory": "Theater",
        "type": "Entertainment"
      }
    ],
    "sg:phone": "+1 513 281 8750",
    "sg:postcode": "45220",
    "sg:province": "OH",
    "sg:website": "http://esquiretheatre.com",
    "wof:name": "Esquire Theatre",
    "wof:placetype": "venue"
  },
  "geometry": {"coordinates":[-84.520071,39.143625],"type":"Point"}
}
