{
  "type": "Feature",
  "properties": {
    "iso:country":"US",
    "sg:address":"320 Ludlow Ave",
    "sg:city":"Cincinnati",
    "sg:classifiers":[
        {
            "category":"Arts & Performance",
            "subcategory":"Theater",
            "type":"Entertainment"
        }
    ],
    "sg:phone":"+1 513 281 8750",
    "sg:postcode":"45220",
    "sg:province":"OH",
    "sg:website":"http://esquiretheatre.com",
    "wof:name":"Esquire Theatre",
    "wof:placetype":"venue"
},
  "geometry": {"coordinates":[-84.520071,39.143625],"type":"Point"}
}