{
  "type": "Feature",
  "properties": {
    "iso:country":"US",
    "sg:address":"143 Northwest Ave",
    "sg:city":"Tallmadge",
    "sg:classifiers":[
        {
            "category":"Utilities",
            "subcategory":"Telephone",
            "type":"Services"
        }
    ],
    "sg:phone":"+1 330 630 4487",
    "sg:postcode":"44278",
    "sg:province":"OH",
    "sg:tags":[
        "communications"
    ],
    "wof:name":"Silver Creek Ltd",
    "wof:placetype":"venue"
},
  "geometry": {"coordinates":[-81.446195,41.10547],"type":"Point"}
}