{
  "type": "Feature",
  "properties": {
    "addr:full":"2269 Westbrooke Dr Columbus OH 43228",
    "addr:housenumber":"2269",
    "addr:postcode":"43228",
    "addr:street":"Westbrooke Dr",
    "iso:country":"US",
    "sg:address":"2269 Westbrooke Dr",
    "sg:city":"Columbus",
    "sg:classifiers":[
        {
            "category":"Professional",
            "subcategory":"Art Services",
            "type":"Services"
        }
    ],
    "sg:phone":"+1 614 527 7991",
    "sg:postcode":"43228",
    "sg:province":"OH",
    "sg:tags":[
        "graphic",
        "designer"
    ],
    "wof:name":"Cannell Graphics LLC",
    "wof:placetype":"venue"
},
  "geometry": {"coordinates":[-83.110529,39.99994],"type":"Point"}
}