{
  "type": "Feature",
  "properties": {
    "addr:full": "2 Summit Park Dr Cleveland OH 44131",
    "addr:housenumber": "2",
    "addr:postcode": "44131",
    "addr:street": "Summit Park Dr",
    "iso:country": "US",
    "sg:address": "2 Summit Park Dr",
    "sg:city": "Cleveland",
    "sg:classifiers": [
      {
        "category": "Professional",
        "subcategory": "Employment Agencies",
        "type": "Services"
      }
    ],
    "sg:phone": "+1 216 328 1612",
    "sg:postcode": "44131",
    "sg:province": "OH",
    "sg:tags": [
      "opportunity"
    ],
    "wof:name": "Medical Office Svc",
    "wof:placetype": "venue"
  },
  "geometry": {"coordinates":[-81.655926,41.395674],"type":"Point"}
}
