{
  "type": "Feature",
  "properties": {
    "iso:country":"US",
    "sg:address":"3026 Strathmoor Ave",
    "sg:city":"Toledo",
    "sg:classifiers":[
        {
            "category":"Building & Trades",
            "subcategory":"Construction",
            "type":"Services"
        }
    ],
    "sg:phone":"+1 419 382 9574",
    "sg:postcode":"43614",
    "sg:province":"OH",
    "sg:tags":[
        "contractor"
    ],
    "wof:name":"Brumbaugh-Herrick Inc",
    "wof:placetype":"venue"
},
  "geometry": {"coordinates":[-83.615592,41.603729],"type":"Point"}
}