{
  "type": "Feature",
  "properties": {
    "iso:country":"US",
    "sg:address":"602 Chillicothe St",
    "sg:city":"Portsmouth",
    "sg:classifiers":[
        {
            "category":"Professional",
            "type":"Services"
        }
    ],
    "sg:phone":"+1 740 353 9474",
    "sg:postcode":"45662",
    "sg:province":"OH",
    "sg:tags":[
        "establishment"
    ],
    "wof:name":"A Special Wish Foundation",
    "wof:placetype":"venue"
},
  "geometry": {"coordinates":[-82.996409,38.735583],"type":"Point"}
}