{
  "type": "Feature",
  "properties": {
    "addr:full":"15 N East St Lebanon OH 45036",
    "addr:housenumber":"15",
    "addr:postcode":"45036",
    "addr:street":"N East St",
    "iso:country":"US",
    "sg:address":"15 N East St",
    "sg:city":"Lebanon",
    "sg:classifiers":[
        {
            "category":"Retail",
            "subcategory":"Laundry & Dry Cleaning",
            "type":"Services"
        }
    ],
    "sg:phone":"+1 513 932 6825",
    "sg:postcode":"45036",
    "sg:province":"OH",
    "sg:tags":[
        "cleaners",
        "rug",
        "carpet"
    ],
    "wof:name":"Reliable Carpet Cleaning Svc",
    "wof:placetype":"venue"
},
  "geometry": {"coordinates":[-84.203918,39.434291],"type":"Point"}
}