{
  "type": "Feature",
  "properties": {
    "iso:country":"US",
    "sg:address":"5782 Andrews Rd",
    "sg:city":"Mentor On Lake",
    "sg:classifiers":[
        {
            "category":"Banks & Credit Unions",
            "subcategory":"Investment Brokerage",
            "type":"Services"
        }
    ],
    "sg:phone":"+1 440 974 1241",
    "sg:postcode":"44060",
    "sg:province":"OH",
    "sg:tags":[
        "stock",
        "bond"
    ],
    "wof:name":"Edward Jones Investments",
    "wof:placetype":"venue"
},
  "geometry": {"coordinates":[-81.36136399999999,41.717507],"type":"Point"}
}