{
  "type": "Feature",
  "properties": {
    "addr:full": "3450 Orcutt Dr Copley OH 44321",
    "addr:housenumber": "3450",
    "addr:postcode": "44321",
    "addr:street": "Orcutt Dr",
    "iso:country": "US",
    "sg:address": "3450 Orcutt Dr",
    "sg:city": "Copley",
    "sg:classifiers": [
      {
        "category": "Manufacturing",
        "subcategory": "Furniture",
        "type": "Manufacturing \u0026 Wholesale Goods"
      }
    ],
    "sg:phone": "+1 330 670 6522",
    "sg:postcode": "44321",
    "sg:province": "OH",
    "sg:tags": [
      "wood"
    ],
    "wof:name": "Arden Riddle Gallery",
    "wof:placetype": "venue"
  },
  "geometry": {"coordinates":[-81.64242,41.090801],"type":"Point"}
}
