{
  "type": "Feature",
  "properties": {
    "addr:full": "3600 N 3 Bs and K Rd Sunbury OH 43074",
    "addr:housenumber": "3600;3",
    "addr:postcode": "43074",
    "addr:street": "N;And K Rd",
    "iso:country": "US",
    "sg:address": "3600 N 3 Bs and K Rd",
    "sg:city": "Sunbury",
    "sg:classifiers": [
      {
        "category": "Shopping",
        "subcategory": "Gifts \u0026 Souvenirs",
        "type": "Retail Goods"
      }
    ],
    "sg:phone": "+1 740 524 6672",
    "sg:postcode": "43074",
    "sg:province": "OH",
    "wof:name": "Bills Buckeye Stuff",
    "wof:placetype": "venue"
  },
  "geometry": {"coordinates":[-82.932652,40.318953],"type":"Point"}
}
