{
  "type": "Feature",
  "properties": {
    "iso:country":"US",
    "sg:address":"3600 N 3 Bs and K Rd",
    "sg:city":"Sunbury",
    "sg:classifiers":[
        {
            "category":"Shopping",
            "subcategory":"Gifts & Souvenirs",
            "type":"Retail Goods"
        }
    ],
    "sg:phone":"+1 740 524 6672",
    "sg:postcode":"43074",
    "sg:province":"OH",
    "wof:name":"Bills Buckeye Stuff",
    "wof:placetype":"venue"
},
  "geometry": {"coordinates":[-82.932652,40.318953],"type":"Point"}
}