{
  "type": "Feature",
  "properties": {
    "iso:country":"US",
    "sg:address":"2502 Abington Rd",
    "sg:city":"Akron",
    "sg:classifiers":[
        {
            "category":"Building & Trades",
            "subcategory":"Construction",
            "type":"Services"
        }
    ],
    "sg:phone":"+1 330 864 6533",
    "sg:postcode":"44333",
    "sg:province":"OH",
    "sg:tags":[
        "hanging",
        "contractor"
    ],
    "wof:name":"Ries Don Pntg & Wallpapering",
    "wof:placetype":"venue"
},
  "geometry": {"coordinates":[-81.602113,41.128993],"type":"Point"}
}