{
  "type": "Feature",
  "properties": {
    "addr:full": "4333 School Section Rd Cincinnati OH 45211",
    "addr:housenumber": "4333",
    "addr:postcode": "45211",
    "addr:street": "School Section Rd",
    "iso:country": "US",
    "sg:address": "4333 School Section Rd",
    "sg:city": "Cincinnati",
    "sg:classifiers": [
      {
        "category": "Building \u0026 Trades",
        "subcategory": "Construction",
        "type": "Services"
      }
    ],
    "sg:phone": "+1 513 574 7279",
    "sg:postcode": "45211",
    "sg:province": "OH",
    "sg:tags": [
      "nonresidential"
    ],
    "wof:name": "W C Ketterman Inc",
    "wof:placetype": "venue"
  },
  "geometry": {"coordinates":[-84.620112,39.170769],"type":"Point"}
}
