{
  "type": "Feature",
  "properties": {
    "iso:country":"US",
    "sg:address":"3849 E Broad St",
    "sg:city":"Columbus",
    "sg:classifiers":[
        {
            "category":"Restaurant",
            "type":"Food & Drink"
        }
    ],
    "sg:phone":"+1 614 231 3975",
    "sg:postcode":"43213",
    "sg:province":"OH",
    "wof:name":"Mark Pi's Express",
    "wof:placetype":"venue"
},
  "geometry": {"coordinates":[-82.90042,39.973426],"type":"Point"}
}