{
  "type": "Feature",
  "properties": {
    "iso:country":"US",
    "sg:address":"4149 N Holland Sylvania Ave",
    "sg:city":"Toledo",
    "sg:classifiers":[
        {
            "category":"Professional",
            "subcategory":"Lawyer & Legal Services",
            "type":"Services"
        }
    ],
    "sg:phone":"+1 419 882 4131",
    "sg:postcode":"43623",
    "sg:province":"OH",
    "sg:tags":[
        "attorney"
    ],
    "wof:name":"Smith & Smith Attorneys At Law",
    "wof:placetype":"venue"
},
  "geometry": {"coordinates":[-83.687665,41.69366],"type":"Point"}
}