{
  "type": "Feature",
  "properties": {
    "addr:full":"1240 N Court St Circleville OH 43113",
    "addr:housenumber":"1240",
    "addr:postcode":"43113",
    "addr:street":"N Court St",
    "iso:country":"US",
    "sg:address":"1240 N Court St",
    "sg:city":"Circleville",
    "sg:classifiers":[
        {
            "category":"Restaurant",
            "type":"Food & Drink"
        }
    ],
    "sg:menulink":"http://www.allmenus.com/oh/circleville/79154-pizza-hut/menu/",
    "sg:phone":"+1 740 477 6005",
    "sg:postcode":"43113",
    "sg:province":"OH",
    "sg:tags":[
        "american",
        "pizza"
    ],
    "wof:name":"Pizza Hut",
    "wof:placetype":"venue"
},
  "geometry": {"coordinates":[-82.940586,39.621372],"type":"Point"}
}