{
  "type": "Feature",
  "properties": {
    "addr:full":"6539 Brecksville Rd Cleveland OH 44131",
    "addr:housenumber":"6539",
    "addr:postcode":"44131",
    "addr:street":"Brecksville Rd",
    "iso:country":"US",
    "sg:address":"6539 Brecksville Rd",
    "sg:city":"Cleveland",
    "sg:classifiers":[
        {
            "category":"Banks & Credit Unions",
            "subcategory":"Investment Brokerage",
            "type":"Services"
        }
    ],
    "sg:phone":"+1 216 520 3163",
    "sg:postcode":"44131",
    "sg:province":"OH",
    "wof:name":"K J Investments",
    "wof:placetype":"venue"
},
  "geometry": {"coordinates":[-81.640961,41.38243],"type":"Point"}
}