{
  "type": "Feature",
  "properties": {
    "iso:country":"US",
    "sg:address":"1206 Romayne Dr",
    "sg:city":"Akron",
    "sg:classifiers":[
        {
            "category":"Organizations",
            "subcategory":"Religious Organization",
            "type":"Services"
        }
    ],
    "sg:phone":"+1 330 836 3992",
    "sg:postcode":"44313",
    "sg:province":"OH",
    "wof:name":"Dennis K Butts",
    "wof:placetype":"venue"
},
  "geometry": {"coordinates":[-81.553432,41.123118],"type":"Point"}
}