{
  "type": "Feature",
  "properties": {
    "iso:country":"US",
    "sg:address":"1745 27th St",
    "sg:city":"Portsmouth",
    "sg:classifiers":[
        {
            "category":"Health Services",
            "subcategory":"Doctor",
            "type":"Services"
        }
    ],
    "sg:phone":"+1 740 356 8169",
    "sg:postcode":"45662",
    "sg:province":"OH",
    "sg:tags":[
        "medical"
    ],
    "wof:name":"Tsuyoshi Inoshita MD",
    "wof:placetype":"venue"
},
  "geometry": {"coordinates":[-82.97921100000001,38.753416],"type":"Point"}
}