{
  "type": "Feature",
  "properties": {
    "addr:full": "1745 27th St Portsmouth OH 45662",
    "addr:housenumber": "1745",
    "addr:postcode": "45662",
    "addr:street": "27Th St",
    "iso:country": "US",
    "sg:address": "1745 27th St",
    "sg:city": "Portsmouth",
    "sg:classifiers": [
      {
        "category": "Health Services",
        "subcategory": "Doctor",
        "type": "Services"
      }
    ],
    "sg:phone": "+1 740 356 8169",
    "sg:postcode": "45662",
    "sg:province": "OH",
    "sg:tags": [
      "medical"
    ],
    "wof:name": "Tsuyoshi Inoshita MD",
    "wof:placetype": "venue"
  },
  "geometry": {"coordinates":[-82.979211,38.753416],"type":"Point"}
}
