{
  "type": "Feature",
  "properties": {
    "addr:full": "2257 Indianola Ave Columbus OH 43202",
    "addr:housenumber": "2257",
    "addr:postcode": "43202",
    "addr:street": "Indianola Ave",
    "iso:country": "US",
    "sg:address": "2257 Indianola Ave",
    "sg:city": "Columbus",
    "sg:classifiers": [
      {
        "category": "Organizations",
        "subcategory": "Religious Organization",
        "type": "Services"
      }
    ],
    "sg:phone": "+1 614 263 9590",
    "sg:postcode": "43202",
    "sg:province": "OH",
    "sg:tags": [
      "church"
    ],
    "wof:name": "Indianola Baptist Church",
    "wof:placetype": "venue"
  },
  "geometry": {"coordinates":[-83.00269,40.009434],"type":"Point"}
}
