{
  "type": "Feature",
  "properties": {
    "addr:full":"910 S Main St Englewood OH 45322",
    "addr:housenumber":"910",
    "addr:postcode":"45322",
    "addr:street":"S Main St",
    "iso:country":"US",
    "sg:address":"910 S Main St",
    "sg:city":"Englewood",
    "sg:classifiers":[
        {
            "category":"Restaurant",
            "type":"Food & Drink"
        }
    ],
    "sg:phone":"+1 937 836 6634",
    "sg:postcode":"45322",
    "sg:province":"OH",
    "sg:tags":[
        "eating"
    ],
    "wof:name":"Bolts Sports Cafe",
    "wof:placetype":"venue"
},
  "geometry": {"coordinates":[-84.28621099999999,39.863639],"type":"Point"}
}