{
  "type": "Feature",
  "properties": {
    "iso:country":"US",
    "sg:address":"2045 Kipling Dr",
    "sg:city":"Dayton",
    "sg:classifiers":[
        {
            "category":"Home & Garden",
            "subcategory":"Carpets & Floor Coverings",
            "type":"Retail Goods"
        }
    ],
    "sg:phone":"+1 937 276 5592",
    "sg:postcode":"45406",
    "sg:province":"OH",
    "sg:tags":[
        "vinyl"
    ],
    "wof:name":"David M Garner Floor & Wall",
    "wof:placetype":"venue"
},
  "geometry": {"coordinates":[-84.2428,39.784535],"type":"Point"}
}