{
  "type": "Feature",
  "properties": {
    "addr:full": "2045 Kipling Dr Dayton OH 45406",
    "addr:housenumber": "2045",
    "addr:postcode": "45406",
    "addr:street": "Kipling Dr",
    "iso:country": "US",
    "sg:address": "2045 Kipling Dr",
    "sg:city": "Dayton",
    "sg:classifiers": [
      {
        "category": "Home \u0026 Garden",
        "subcategory": "Carpets \u0026 Floor Coverings",
        "type": "Retail Goods"
      }
    ],
    "sg:phone": "+1 937 276 5592",
    "sg:postcode": "45406",
    "sg:province": "OH",
    "sg:tags": [
      "vinyl"
    ],
    "wof:name": "David M Garner Floor \u0026 Wall",
    "wof:placetype": "venue"
  },
  "geometry": {"coordinates":[-84.2428,39.784535],"type":"Point"}
}
