{
  "type": "Feature",
  "properties": {
    "iso:country":"US",
    "sg:address":"15 N Limestone St",
    "sg:city":"Jamestown",
    "sg:classifiers":[
        {
            "category":"Organizations",
            "subcategory":"Religious Organization",
            "type":"Services"
        }
    ],
    "sg:phone":"+1 937 675 2849",
    "sg:postcode":"45335",
    "sg:province":"OH",
    "sg:tags":[
        "church"
    ],
    "wof:name":"Church New Life Worship Ctr",
    "wof:placetype":"venue"
},
  "geometry": {"coordinates":[-83.734741,39.658993],"type":"Point"}
}