{
  "type": "Feature",
  "properties": {
    "addr:full": "1087 Wayne Rd Wilmington OH 45177",
    "addr:housenumber": "1087",
    "addr:postcode": "45177",
    "addr:street": "Wayne Rd",
    "iso:country": "US",
    "sg:address": "1087 Wayne Rd",
    "sg:city": "Wilmington",
    "sg:classifiers": [
      {
        "category": "Manufacturing",
        "subcategory": "Printing",
        "type": "Manufacturing \u0026 Wholesale Goods"
      }
    ],
    "sg:phone": "+1 937 382 2312",
    "sg:postcode": "45177",
    "sg:province": "OH",
    "sg:tags": [
      "screen"
    ],
    "wof:name": "Cox Printing Co",
    "wof:placetype": "venue"
  },
  "geometry": {"coordinates":[-83.847548,39.447239],"type":"Point"}
}
