{
  "type": "Feature",
  "properties": {
    "iso:country":"US",
    "sg:address":"6571 Brandt Pike",
    "sg:city":"Dayton",
    "sg:classifiers":[
        {
            "category":"Insurance",
            "subcategory":"Insurance Agent",
            "type":"Services"
        }
    ],
    "sg:phone":"+1 937 233 3728",
    "sg:postcode":"45424",
    "sg:province":"OH",
    "sg:website":"www.statefarm.com",
    "wof:name":"State Farm Insurance",
    "wof:placetype":"venue"
},
  "geometry": {"coordinates":[-84.112756,39.848939],"type":"Point"}
}