{
  "type": "Feature",
  "properties": {
    "addr:full":"1328 Linda St Cleveland OH 44116",
    "addr:housenumber":"1328",
    "addr:postcode":"44116",
    "addr:street":"Linda St",
    "iso:country":"US",
    "sg:address":"1328 Linda St",
    "sg:city":"Cleveland",
    "sg:classifiers":[
        {
            "category":"Wholesale",
            "subcategory":"Electrical",
            "type":"Manufacturing & Wholesale Goods"
        }
    ],
    "sg:phone":"+1 440 331 8181",
    "sg:postcode":"44116",
    "sg:province":"OH",
    "sg:tags":[
        "control",
        "security",
        "system"
    ],
    "wof:name":"American Electronic Security",
    "wof:placetype":"venue"
},
  "geometry": {"coordinates":[-81.840844,41.480826],"type":"Point"}
}