{
  "type": "Feature",
  "properties": {
    "iso:country":"US",
    "sg:address":"140 Mikes Dr",
    "sg:city":"Put In Bay",
    "sg:classifiers":[
        {
            "category":"Building & Trades",
            "subcategory":"Landscaping Services",
            "type":"Services"
        }
    ],
    "sg:phone":"+1 419 285 2147",
    "sg:postcode":"43456",
    "sg:province":"OH",
    "wof:name":"Yardworks",
    "wof:placetype":"venue"
},
  "geometry": {"coordinates":[-82.801363,41.661187],"type":"Point"}
}