{
  "type": "Feature",
  "properties": {
    "iso:country":"US",
    "sg:address":"1900 Carolina St",
    "sg:city":"Middletown",
    "sg:classifiers":[
        {
            "category":"Restaurant",
            "type":"Food & Drink"
        }
    ],
    "sg:phone":"+1 513 422 1921",
    "sg:postcode":"45044",
    "sg:province":"OH",
    "sg:tags":[
        "eating"
    ],
    "wof:name":"Lees Cafe",
    "wof:placetype":"venue"
},
  "geometry": {"coordinates":[-84.380405,39.492975],"type":"Point"}
}