{
  "type": "Feature",
  "properties": {
    "iso:country":"US",
    "sg:address":"850 Mc Daniel Ave E",
    "sg:city":"Minerva",
    "sg:classifiers":[
        {
            "category":"Professional",
            "subcategory":"Lawyer & Legal Services",
            "type":"Services"
        }
    ],
    "sg:phone":"+1 330 868 6161",
    "sg:postcode":"44657",
    "sg:province":"OH",
    "sg:tags":[
        "attorney"
    ],
    "wof:name":"Robert D Martin",
    "wof:placetype":"venue"
},
  "geometry": {"coordinates":[-81.088612,40.734561],"type":"Point"}
}