{
  "type": "Feature",
  "properties": {
    "addr:full":"29001 Cedar Rd Ste 450 Cleveland OH 44124",
    "addr:housenumber":"29001",
    "addr:postcode":"44124",
    "addr:street":"Cedar Rd Ste 450",
    "iso:country":"US",
    "sg:address":"29001 Cedar Rd Ste 450",
    "sg:city":"Cleveland",
    "sg:classifiers":[
        {
            "category":"Health Services",
            "subcategory":"Dentist",
            "type":"Services"
        }
    ],
    "sg:phone":"+1 440 461 3400",
    "sg:postcode":"44124",
    "sg:province":"OH",
    "sg:website":"www.clevelandperio.com",
    "wof:name":"Hess Roger DDS",
    "wof:placetype":"venue"
},
  "geometry": {"coordinates":[-81.47469,41.501327],"type":"Point"}
}