{
  "type": "Feature",
  "properties": {
    "addr:full": "3253 W 25th St Cleveland OH 44109",
    "addr:housenumber": "3253",
    "addr:postcode": "44109",
    "addr:street": "W 25Th St",
    "iso:country": "US",
    "sg:address": "3253 W 25th St",
    "sg:city": "Cleveland",
    "sg:classifiers": [
      {
        "category": "Personal",
        "subcategory": "Barber",
        "type": "Services"
      }
    ],
    "sg:phone": "+1 216 661 5008",
    "sg:postcode": "44109",
    "sg:province": "OH",
    "wof:name": "Belkies Hair Place",
    "wof:placetype": "venue"
  },
  "geometry": {"coordinates":[-81.700007,41.466627],"type":"Point"}
}
