{
  "type": "Feature",
  "properties": {
    "iso:country":"US",
    "sg:address":"576 Debbie Dr",
    "sg:city":"Gallipolis",
    "sg:classifiers":[
        {
            "category":"Organizations",
            "subcategory":"Religious Organization",
            "type":"Services"
        }
    ],
    "sg:phone":"+1 740 446 3800",
    "sg:postcode":"45631",
    "sg:province":"OH",
    "sg:tags":[
        "church"
    ],
    "wof:name":"Faith Temple Independent Chr",
    "wof:placetype":"venue"
},
  "geometry": {"coordinates":[-82.243272,38.801082],"type":"Point"}
}