{
  "type": "Feature",
  "properties": {
    "iso:country":"US",
    "sg:address":"1905 Morris Ave NE",
    "sg:city":"Canton",
    "sg:classifiers":[
        {
            "category":"Building & Trades",
            "subcategory":"Construction",
            "type":"Services"
        }
    ],
    "sg:phone":"+1 330 452 4276",
    "sg:postcode":"44705",
    "sg:province":"OH",
    "sg:tags":[
        "contractor"
    ],
    "wof:name":"Mike Cunningham",
    "wof:placetype":"venue"
},
  "geometry": {"coordinates":[-81.336167,40.820178],"type":"Point"}
}