{
  "type": "Feature",
  "properties": {
    "iso:country":"US",
    "sg:address":"625 Garfield Ave",
    "sg:city":"Lancaster",
    "sg:classifiers":[
        {
            "category":"Education",
            "subcategory":"School",
            "type":"Public Place"
        }
    ],
    "sg:phone":"+1 740 687 7332",
    "sg:postcode":"43130",
    "sg:province":"OH",
    "wof:name":"West Elementary School",
    "wof:placetype":"venue"
},
  "geometry": {"coordinates":[-82.617429,39.7214],"type":"Point"}
}