{
  "type": "Feature",
  "properties": {
    "iso:country":"US",
    "sg:address":"441 Boxhall Rd",
    "sg:city":"Toledo",
    "sg:classifiers":[
        {
            "category":"Retail",
            "subcategory":"Auto Repair",
            "type":"Services"
        }
    ],
    "sg:phone":"+1 419 476 0770",
    "sg:postcode":"43612",
    "sg:province":"OH",
    "sg:tags":[
        "recreational",
        "vehicle"
    ],
    "wof:name":"Obarski's Camper & Rv Awnings",
    "wof:placetype":"venue"
},
  "geometry": {"coordinates":[-83.555803,41.712663],"type":"Point"}
}