{
  "type": "Feature",
  "properties": {
    "iso:country":"US",
    "sg:address":"226 Oxford Rd",
    "sg:city":"Mansfield",
    "sg:classifiers":[
        {
            "category":"Insurance",
            "subcategory":"Insurance Agent",
            "type":"Services"
        }
    ],
    "sg:phone":"+1 419 884 3056",
    "sg:postcode":"44904",
    "sg:province":"OH",
    "wof:name":"Barber Thomas Jay Insurance AG",
    "wof:placetype":"venue"
},
  "geometry": {"coordinates":[-82.595691,40.687577],"type":"Point"}
}