{
  "type": "Feature",
  "properties": {
    "addr:full":"3725 Croton Ave Cleveland OH 44115",
    "addr:housenumber":"3725",
    "addr:postcode":"44115",
    "addr:street":"Croton Ave",
    "iso:country":"US",
    "sg:address":"3725 Croton Ave",
    "sg:city":"Cleveland",
    "sg:classifiers":[
        {
            "category":"Shopping",
            "subcategory":"Pharmacy",
            "type":"Retail Goods"
        }
    ],
    "sg:phone":"+1 216 881 4559",
    "sg:postcode":"44115",
    "sg:province":"OH",
    "wof:name":"Revco Drug Stores",
    "wof:placetype":"venue"
},
  "geometry": {"coordinates":[-81.664057,41.487749],"type":"Point"}
}