{
  "type": "Feature",
  "properties": {
    "iso:country":"US",
    "sg:address":"1329 Hillside Dr",
    "sg:city":"Greenville",
    "sg:classifiers":[
        {
            "category":"Building & Trades",
            "subcategory":"Plumbing",
            "type":"Services"
        }
    ],
    "sg:phone":"+1 937 548 1150",
    "sg:postcode":"45331",
    "sg:province":"OH",
    "sg:tags":[
        "conditioning",
        "air",
        "system",
        "contractor"
    ],
    "wof:name":"Scott's Heating & Air Cond Inc",
    "wof:placetype":"venue"
},
  "geometry": {"coordinates":[-84.625349,40.122084],"type":"Point"}
}