{
  "type": "Feature",
  "properties": {
    "addr:full": "2516 N Detroit Ave Toledo OH 43610",
    "addr:housenumber": "2516",
    "addr:postcode": "43610",
    "addr:street": "N Detroit Ave",
    "iso:country": "US",
    "sg:address": "2516 N Detroit Ave",
    "sg:city": "Toledo",
    "sg:classifiers": [
      {
        "category": "Food \u0026 Beverages",
        "subcategory": "Groceries \u0026 Convenience Stores",
        "type": "Retail Goods"
      }
    ],
    "sg:phone": "+1 419 246 0865",
    "sg:postcode": "43610",
    "sg:province": "OH",
    "wof:name": "Detroit Stop",
    "wof:placetype": "venue"
  },
  "geometry": {"coordinates":[-83.565679,41.671758],"type":"Point"}
}
