{
  "type": "Feature",
  "properties": {
    "addr:full": "34041 Stevens Blvd Willoughby OH 44095",
    "addr:housenumber": "34041",
    "addr:postcode": "44095",
    "addr:street": "Stevens Blvd",
    "iso:country": "US",
    "sg:address": "34041 Stevens Blvd",
    "sg:city": "Willoughby",
    "sg:classifiers": [
      {
        "category": "Education",
        "subcategory": "School",
        "type": "Public Place"
      }
    ],
    "sg:phone": "+1 440 975 3666",
    "sg:postcode": "44095",
    "sg:province": "OH",
    "sg:tags": [
      "high"
    ],
    "sg:website": "www.lgca.org",
    "wof:name": "North High School",
    "wof:placetype": "venue"
  },
  "geometry": {"coordinates":[-81.447968,41.650183],"type":"Point"}
}
