{
  "type": "Feature",
  "properties": {
    "iso:country":"US",
    "sg:address":"5410 Youngstown Warren Rd",
    "sg:city":"Niles",
    "sg:classifiers":[
        {
            "category":"Shopping",
            "subcategory":"Jewelry",
            "type":"Retail Goods"
        }
    ],
    "sg:phone":"+1 330 369 8800",
    "sg:postcode":"44446",
    "sg:province":"OH",
    "sg:tags":[
        "jeweler"
    ],
    "wof:name":"Mr T's Heart - Gold & Diamonds",
    "wof:placetype":"venue"
},
  "geometry": {"coordinates":[-80.752078,41.210899],"type":"Point"}
}