{
  "type": "Feature",
  "properties": {
    "addr:full": "9 W Mound St Columbus OH 43215",
    "addr:housenumber": "9",
    "addr:postcode": "43215",
    "addr:street": "W Mound St",
    "iso:country": "US",
    "sg:address": "9 W Mound St",
    "sg:city": "Columbus",
    "sg:classifiers": [
      {
        "category": "Insurance",
        "subcategory": "Insurance Agent",
        "type": "Services"
      }
    ],
    "sg:phone": "+1 937 462 7073",
    "sg:postcode": "43215",
    "sg:province": "OH",
    "wof:name": "Spinning Insurance",
    "wof:placetype": "venue"
  },
  "geometry": {"coordinates":[-82.999867,39.954659],"type":"Point"}
}
