{
  "type": "Feature",
  "properties": {
    "iso:country":"US",
    "sg:address":"1380 Deer Run Rd",
    "sg:city":"Newark",
    "sg:classifiers":[
        {
            "category":"Manufacturing",
            "subcategory":"Printing",
            "type":"Manufacturing & Wholesale Goods"
        }
    ],
    "sg:phone":"+1 740 364 1766",
    "sg:postcode":"43055",
    "sg:province":"OH",
    "sg:tags":[
        "printer"
    ],
    "wof:name":"Red Vette Printing Co",
    "wof:placetype":"venue"
},
  "geometry": {"coordinates":[-82.455277,40.076042],"type":"Point"}
}