{
  "type": "Feature",
  "properties": {
    "iso:country":"US",
    "sg:address":"1005 E 32nd St",
    "sg:city":"Lorain",
    "sg:classifiers":[
        {
            "category":"Manufacturing",
            "subcategory":"Metals",
            "type":"Manufacturing & Wholesale Goods"
        },
        {
            "category":"Building & Trades",
            "subcategory":"Construction",
            "type":"Services"
        }
    ],
    "sg:phone":"+1 440 835 2946",
    "sg:postcode":"44055",
    "sg:province":"OH",
    "sg:tags":[
        "mfg",
        "fabricated",
        "contractor",
        "machine",
        "r",
        "base",
        "structural",
        "fabrication",
        "welding"
    ],
    "wof:name":"A-1 Welding & Fabricating Inc",
    "wof:placetype":"venue"
},
  "geometry": {"coordinates":[-82.153992,41.441317],"type":"Point"}
}