{
  "type": "Feature",
  "properties": {
    "addr:full": "1214 W Ohio Pike Amelia OH 45102",
    "addr:housenumber": "1214",
    "addr:postcode": "45102",
    "addr:street": "W Ohio Pike",
    "iso:country": "US",
    "sg:address": "1214 W Ohio Pike",
    "sg:city": "Amelia",
    "sg:classifiers": [
      {
        "category": "Restaurant",
        "type": "Food \u0026 Drink"
      }
    ],
    "sg:phone": "+1 513 943 1496",
    "sg:postcode": "45102",
    "sg:province": "OH",
    "sg:website": "www.arbys.com",
    "wof:name": "Arby's",
    "wof:placetype": "venue"
  },
  "geometry": {"coordinates":[-84.231544,39.037841],"type":"Point"}
}
