{
  "type": "Feature",
  "properties": {
    "addr:full": "8695 Harper Point Dr Cincinnati OH 45249",
    "addr:housenumber": "8695",
    "addr:postcode": "45249",
    "addr:street": "Harper Point Dr",
    "iso:country": "US",
    "sg:address": "8695 Harper Point Dr",
    "sg:city": "Cincinnati",
    "sg:classifiers": [
      {
        "category": "Professional",
        "subcategory": "Computer Services",
        "type": "Services"
      }
    ],
    "sg:phone": "+1 513 469 2407",
    "sg:postcode": "45249",
    "sg:province": "OH",
    "sg:tags": [
      "internet"
    ],
    "wof:name": "Active Data Cabling",
    "wof:placetype": "venue"
  },
  "geometry": {"coordinates":[-84.326168,39.269034],"type":"Point"}
}
