{
  "type": "Feature",
  "properties": {
    "addr:full":"32607 Walker Rd Avon Lake OH 44012",
    "addr:housenumber":"32607",
    "addr:postcode":"44012",
    "addr:street":"Walker Rd",
    "iso:country":"US",
    "sg:address":"32607 Walker Rd",
    "sg:city":"Avon Lake",
    "sg:classifiers":[
        {
            "category":"Insurance",
            "subcategory":"Insurance Agent",
            "type":"Services"
        }
    ],
    "sg:phone":"+1 440 933 4400",
    "sg:postcode":"44012",
    "sg:province":"OH",
    "sg:tags":[
        "processing"
    ],
    "wof:name":"Compumed Claims Management Svc",
    "wof:placetype":"venue"
},
  "geometry": {"coordinates":[-82.009184,41.492981],"type":"Point"}
}