{
  "type": "Feature",
  "properties": {
    "iso:country":"US",
    "sg:address":"4146 Burbank Rd",
    "sg:city":"Wooster",
    "sg:classifiers":[
        {
            "category":"Personal",
            "subcategory":"Tanning Parlor",
            "type":"Services"
        }
    ],
    "sg:phone":"+1 330 264 3930",
    "sg:postcode":"44691",
    "sg:province":"OH",
    "sg:tags":[
        "salon"
    ],
    "wof:name":"Sunset Lane Tanning",
    "wof:placetype":"venue"
},
  "geometry": {"coordinates":[-81.946882,40.850306],"type":"Point"}
}