{
  "type": "Feature",
  "properties": {
    "addr:full": "198 Kendall Rd Minford OH 45653",
    "addr:housenumber": "198",
    "addr:postcode": "45653",
    "addr:street": "Kendall Rd",
    "iso:country": "US",
    "sg:address": "198 Kendall Rd",
    "sg:city": "Minford",
    "sg:classifiers": [
      {
        "category": "Farming",
        "subcategory": "Farm",
        "type": "Manufacturing \u0026 Wholesale Goods"
      }
    ],
    "sg:phone": "+1 740 820 2814",
    "sg:postcode": "45653",
    "sg:province": "OH",
    "sg:tags": [
      "crop",
      "general"
    ],
    "wof:name": "Glenn Rase",
    "wof:placetype": "venue"
  },
  "geometry": {"coordinates":[-82.832267,38.84962],"type":"Point"}
}
