{
  "type": "Feature",
  "properties": {
    "iso:country":"US",
    "sg:address":"5501 Cass Ave",
    "sg:city":"Cleveland",
    "sg:classifiers":[
        {
            "category":"Manufacturing",
            "subcategory":"Printing",
            "type":"Manufacturing & Wholesale Goods"
        }
    ],
    "sg:phone":"+1 216 651 9500",
    "sg:postcode":"44102",
    "sg:province":"OH",
    "sg:tags":[
        "commercial"
    ],
    "sg:website":"www.hkmdm.com",
    "wof:name":"HKM Direct Market Comms",
    "wof:placetype":"venue"
},
  "geometry": {"coordinates":[-81.725848,41.488945],"type":"Point"}
}