{
  "type": "Feature",
  "properties": {
    "iso:country":"US",
    "sg:address":"3802 Old Columbus Rd NW",
    "sg:city":"Carroll",
    "sg:classifiers":[
        {
            "category":"Personal",
            "subcategory":"Beauty Salon",
            "type":"Services"
        }
    ],
    "sg:phone":"+1 740 756 7555",
    "sg:postcode":"43112",
    "sg:province":"OH",
    "wof:name":"M J Artistics",
    "wof:placetype":"venue"
},
  "geometry": {"coordinates":[-82.682491,39.767747],"type":"Point"}
}