{
  "type": "Feature",
  "properties": {
    "addr:full": "7832 Morris Rd Hilliard OH 43026",
    "addr:housenumber": "7832",
    "addr:postcode": "43026",
    "addr:street": "Morris Rd",
    "iso:country": "US",
    "sg:address": "7832 Morris Rd",
    "sg:city": "Hilliard",
    "sg:classifiers": [
      {
        "category": "Professional",
        "type": "Services"
      }
    ],
    "sg:phone": "+1 614 527 1957",
    "sg:postcode": "43026",
    "sg:province": "OH",
    "sg:tags": [
      "establishment"
    ],
    "wof:name": "American Archives",
    "wof:placetype": "venue"
  },
  "geometry": {"coordinates":[-83.213487,40.004358],"type":"Point"}
}
