{
  "type": "Feature",
  "properties": {
    "addr:full":"27072 Carronade Dr Perrysburg OH 43551",
    "addr:housenumber":"27072",
    "addr:postcode":"43551",
    "addr:street":"Carronade Dr",
    "iso:country":"US",
    "sg:address":"27072 Carronade Dr",
    "sg:city":"Perrysburg",
    "sg:classifiers":[
        {
            "category":"Food & Beverages",
            "subcategory":"Specialty",
            "type":"Retail Goods"
        }
    ],
    "sg:phone":"+1 419 872 6155",
    "sg:postcode":"43551",
    "sg:province":"OH",
    "sg:tags":[
        "nutrition",
        "health",
        "ctr",
        "diet"
    ],
    "wof:name":"GNC",
    "wof:placetype":"venue"
},
  "geometry": {"coordinates":[-83.60052899999999,41.544751],"type":"Point"}
}