{
  "type": "Feature",
  "properties": {
    "iso:country":"US",
    "sg:address":"6401 River Styx Rd",
    "sg:city":"Medina",
    "sg:classifiers":[
        {
            "category":"Building & Trades",
            "subcategory":"Construction",
            "type":"Services"
        }
    ],
    "sg:phone":"+1 330 722 2977",
    "sg:postcode":"44256",
    "sg:province":"OH",
    "sg:tags":[
        "contractor",
        "nonresidential"
    ],
    "wof:name":"Angus Construction/Restoration",
    "wof:placetype":"venue"
},
  "geometry": {"coordinates":[-81.803772,41.099498],"type":"Point"}
}