{
  "type": "Feature",
  "properties": {
    "addr:full":"3425 Roundwood Rd Chagrin Falls OH 44022",
    "addr:housenumber":"3425",
    "addr:postcode":"44022",
    "addr:street":"Roundwood Rd",
    "iso:country":"US",
    "sg:address":"3425 Roundwood Rd",
    "sg:city":"Chagrin Falls",
    "sg:classifiers":[
        {
            "category":"Professional",
            "type":"Services"
        }
    ],
    "sg:phone":"+1 440 247 7631",
    "sg:postcode":"44022",
    "sg:province":"OH",
    "wof:name":"Edgar L Ostendorf Jr",
    "wof:placetype":"venue"
},
  "geometry": {"coordinates":[-81.433187,41.469106],"type":"Point"}
}