{
  "type": "Feature",
  "properties": {
    "addr:full":"4505 Orchard Park Dr Cleveland OH 44134",
    "addr:housenumber":"4505",
    "addr:postcode":"44134",
    "addr:street":"Orchard Park Dr",
    "iso:country":"US",
    "sg:address":"4505 Orchard Park Dr",
    "sg:city":"Cleveland",
    "sg:classifiers":[
        {
            "category":"Manufacturing",
            "subcategory":"Building Materials",
            "type":"Manufacturing & Wholesale Goods"
        }
    ],
    "sg:phone":"+1 440 888 8164",
    "sg:postcode":"44134",
    "sg:province":"OH",
    "sg:tags":[
        "mfg"
    ],
    "wof:name":"Old Orchard Woodworking",
    "wof:placetype":"venue"
},
  "geometry": {"coordinates":[-81.715925,41.383313],"type":"Point"}
}