{
  "type": "Feature",
  "properties": {
    "addr:full":"1575 E County Line Rd Springfield OH 45502",
    "addr:housenumber":"1575",
    "addr:postcode":"45502",
    "addr:street":"E County Line Rd",
    "iso:country":"US",
    "sg:address":"1575 E County Line Rd",
    "sg:city":"Springfield",
    "sg:phone":"+1 937 399 6523",
    "sg:postcode":"45502",
    "sg:province":"OH",
    "sg:tags":[
        "farm",
        "corn",
        "soybean"
    ],
    "wof:name":"Scott Haerr",
    "wof:placetype":"venue"
},
  "geometry": {"coordinates":[-83.76643900000001,40.024614],"type":"Point"}
}