{
  "type": "Feature",
  "properties": {
    "addr:full": "44 S 6th St Zanesville OH 43701",
    "addr:housenumber": "44",
    "addr:postcode": "43701",
    "addr:street": "S 6Th St",
    "iso:country": "US",
    "sg:address": "44 S 6th St",
    "sg:city": "Zanesville",
    "sg:classifiers": [
      {
        "category": "Professional",
        "subcategory": "Lawyer \u0026 Legal Services",
        "type": "Services"
      }
    ],
    "sg:phone": "+1 740 452 8431",
    "sg:postcode": "43701",
    "sg:province": "OH",
    "sg:tags": [
      "attorney"
    ],
    "wof:name": "Magaziner \u0026 Mc Glade",
    "wof:placetype": "venue"
  },
  "geometry": {"coordinates":[-82.005173,39.939296],"type":"Point"}
}
