{
  "type": "Feature",
  "properties": {
    "addr:full": "2 Reservoir Rd St Clairsville OH 43950",
    "addr:housenumber": "2",
    "addr:postcode": "43950",
    "addr:street": "Reservoir Rd",
    "iso:country": "US",
    "sg:address": "2 Reservoir Rd",
    "sg:city": "St Clairsville",
    "sg:classifiers": [
      {
        "category": "Government",
        "subcategory": "Post Office",
        "type": "Public Place"
      }
    ],
    "sg:phone": "+1 740 695 1030",
    "sg:postcode": "43950",
    "sg:province": "OH",
    "wof:name": "US Post Office",
    "wof:placetype": "venue"
  },
  "geometry": {"coordinates":[-80.91165,40.077731],"type":"Point"}
}
