{
  "type": "Feature",
  "properties": {
    "addr:full": "375 Glensprings Dr Cincinnati OH 45246",
    "addr:housenumber": "375",
    "addr:postcode": "45246",
    "addr:street": "Glensprings Dr",
    "iso:country": "US",
    "sg:address": "375 Glensprings Dr",
    "sg:city": "Cincinnati",
    "sg:classifiers": [
      {
        "category": "Personal",
        "type": "Services"
      }
    ],
    "sg:phone": "+1 513 674 5594",
    "sg:postcode": "45246",
    "sg:province": "OH",
    "wof:name": "Huff Rental Solutions",
    "wof:placetype": "venue"
  },
  "geometry": {"coordinates":[-84.488233,39.292851],"type":"Point"}
}
