{
  "type": "Feature",
  "properties": {
    "addr:full": "818 E Wayne St Celina OH 45822",
    "addr:housenumber": "818",
    "addr:postcode": "45822",
    "addr:street": "E Wayne St",
    "iso:country": "US",
    "sg:address": "818 E Wayne St",
    "sg:city": "Celina",
    "sg:classifiers": [
      {
        "category": "Banks \u0026 Credit Unions",
        "subcategory": "Bank",
        "type": "Services"
      }
    ],
    "sg:phone": "+1 419 586 9910",
    "sg:postcode": "45822",
    "sg:province": "OH",
    "sg:website": "www.pbcbank.com",
    "wof:name": "Peoples Bank Co",
    "wof:placetype": "venue"
  },
  "geometry": {"coordinates":[-84.554824,40.556565],"type":"Point"}
}
