{
  "type": "Feature",
  "properties": {
    "addr:full":"3153 Lantz Rd Dayton OH 45432",
    "addr:postcode":"3153;45432",
    "addr:street":"Lantz Rd",
    "iso:country":"US",
    "sg:address":"3153 Lantz Rd",
    "sg:city":"Dayton",
    "sg:classifiers":[
        {
            "category":"Professional",
            "type":"Services"
        }
    ],
    "sg:phone":"+1 937 427 0886",
    "sg:postcode":"45432",
    "sg:province":"OH",
    "sg:tags":[
        "establishment"
    ],
    "wof:name":"Shri Ram Chandra Mission",
    "wof:placetype":"venue"
},
  "geometry": {"coordinates":[-84.053517,39.733076],"type":"Point"}
}