{
  "type": "Feature",
  "properties": {
    "addr:full": "2213 Stringtown Rd Grove City OH 43123",
    "addr:housenumber": "2213",
    "addr:postcode": "43123",
    "addr:street": "Stringtown Rd",
    "iso:country": "US",
    "sg:address": "2213 Stringtown Rd",
    "sg:city": "Grove City",
    "sg:classifiers": [
      {
        "category": "Restaurant",
        "type": "Food \u0026 Drink"
      }
    ],
    "sg:phone": "+1 614 875 6988",
    "sg:postcode": "43123",
    "sg:province": "OH",
    "wof:name": "Magic Jeanie's Grill",
    "wof:placetype": "venue"
  },
  "geometry": {"coordinates":[-83.06061,39.878551],"type":"Point"}
}
