{
  "type": "Feature",
  "properties": {
    "iso:country":"US",
    "sg:address":"3664 Muddy Creek Rd",
    "sg:city":"Cincinnati",
    "sg:classifiers":[
        {
            "category":"Personal",
            "subcategory":"Beauty Salon",
            "type":"Services"
        }
    ],
    "sg:phone":"+1 513 451 2333",
    "sg:postcode":"45238",
    "sg:province":"OH",
    "sg:tags":[
        "shop"
    ],
    "wof:name":"Zahneis Hair & Nail Salon",
    "wof:placetype":"venue"
},
  "geometry": {"coordinates":[-84.620663,39.135824],"type":"Point"}
}