{
  "type": "Feature",
  "properties": {
    "addr:full": "1250 Bellefontaine St Wapakoneta OH 45895",
    "addr:housenumber": "1250",
    "addr:postcode": "45895",
    "addr:street": "Bellefontaine St",
    "iso:country": "US",
    "sg:address": "1250 Bellefontaine St",
    "sg:city": "Wapakoneta",
    "sg:classifiers": [
      {
        "category": "Autos \u0026 Motor Vehicles",
        "subcategory": "Auto Supplies",
        "type": "Retail Goods"
      }
    ],
    "sg:phone": "+1 419 739 7242",
    "sg:postcode": "45895",
    "sg:province": "OH",
    "sg:tags": [
      "automobile",
      "parts"
    ],
    "wof:name": "Advance Auto Parts Inc",
    "wof:placetype": "venue"
  },
  "geometry": {"coordinates":[-84.178088,40.56483],"type":"Point"}
}
