{
  "type": "Feature",
  "properties": {
    "addr:full":"2400 Michigan St Sidney OH 45365",
    "addr:housenumber":"2400",
    "addr:postcode":"45365",
    "addr:street":"Michigan St",
    "iso:country":"US",
    "sg:address":"2400 Michigan St",
    "sg:city":"Sidney",
    "sg:classifiers":[
        {
            "category":"Professional",
            "subcategory":"Accounting & Tax Preparation",
            "type":"Services"
        }
    ],
    "sg:phone":"+1 937 492 0508",
    "sg:postcode":"45365",
    "sg:province":"OH",
    "sg:tags":[
        "return",
        "filing"
    ],
    "wof:name":"H & R Block Tax Svc",
    "wof:placetype":"venue"
},
  "geometry": {"coordinates":[-84.19013699999999,40.287812],"type":"Point"}
}