{
  "type": "Feature",
  "properties": {
    "iso:country":"US",
    "sg:address":"5951 State Rte 303",
    "sg:city":"Wakeman",
    "sg:classifiers":[
        {
            "category":"Real Estate",
            "subcategory":"Real Estate Operator",
            "type":"Services"
        }
    ],
    "sg:phone":"+1 440 839 2734",
    "sg:postcode":"44889",
    "sg:province":"OH",
    "sg:tags":[
        "mobile",
        "home",
        "site"
    ],
    "wof:name":"John W & Rose M Ockenga",
    "wof:placetype":"venue"
},
  "geometry": {"coordinates":[-82.37395600000001,41.23915],"type":"Point"}
}