{
  "type": "Feature",
  "properties": {
    "addr:full": "8101 Forest Ct North Royalton OH 44133",
    "addr:housenumber": "8101",
    "addr:postcode": "44133",
    "addr:street": "Forest Ct",
    "iso:country": "US",
    "sg:address": "8101 Forest Ct",
    "sg:city": "North Royalton",
    "sg:classifiers": [
      {
        "category": "Home \u0026 Garden",
        "subcategory": "Carpets \u0026 Floor Coverings",
        "type": "Retail Goods"
      }
    ],
    "sg:phone": "+1 440 237 7231",
    "sg:postcode": "44133",
    "sg:province": "OH",
    "wof:name": "Broadview Carpet and Floors",
    "wof:placetype": "venue"
  },
  "geometry": {"coordinates":[-81.716193,41.348055],"type":"Point"}
}
