{
  "type": "Feature",
  "properties": {
    "iso:country":"US",
    "sg:address":"8101 Forest Ct",
    "sg:city":"North Royalton",
    "sg:classifiers":[
        {
            "category":"Home & Garden",
            "subcategory":"Carpets & Floor Coverings",
            "type":"Retail Goods"
        }
    ],
    "sg:phone":"+1 440 237 7231",
    "sg:postcode":"44133",
    "sg:province":"OH",
    "wof:name":"Broadview Carpet and Floors",
    "wof:placetype":"venue"
},
  "geometry": {"coordinates":[-81.716193,41.348055],"type":"Point"}
}