{
  "type": "Feature",
  "properties": {
    "addr:full":"1313 State Rte 131 Milford OH 45150",
    "addr:housenumber":"1313",
    "addr:postcode":"45150",
    "addr:street":"State Rte 131",
    "iso:country":"US",
    "sg:address":"1313 State Rte 131",
    "sg:city":"Milford",
    "sg:classifiers":[
        {
            "category":"Shopping",
            "type":"Retail Goods"
        }
    ],
    "sg:phone":"+1 513 576 6255",
    "sg:postcode":"45150",
    "sg:province":"OH",
    "sg:tags":[
        "craft",
        "gallery",
        "dealer"
    ],
    "wof:name":"Day Heights Fire Dept Orgnztn",
    "wof:placetype":"venue"
},
  "geometry": {"coordinates":[-84.221187,39.17641],"type":"Point"}
}