{
  "type": "Feature",
  "properties": {
    "addr:full":"204 S East Ave Montpelier OH 43543",
    "addr:housenumber":"204",
    "addr:postcode":"43543",
    "addr:street":"S East Ave",
    "iso:country":"US",
    "sg:address":"204 S East Ave",
    "sg:city":"Montpelier",
    "sg:classifiers":[
        {
            "category":"Wholesale",
            "subcategory":"Groceries",
            "type":"Manufacturing & Wholesale Goods"
        }
    ],
    "sg:phone":"+1 419 485 5461",
    "sg:postcode":"43543",
    "sg:province":"OH",
    "sg:tags":[
        "confectionery"
    ],
    "wof:name":"Stowits Snacks Sales",
    "wof:placetype":"venue"
},
  "geometry": {"coordinates":[-84.603482,41.58553],"type":"Point"}
}