{
  "type": "Feature",
  "properties": {
    "addr:full":"38401 Eagle Nest Dr Willoughby OH 44094",
    "addr:housenumber":"38401",
    "addr:postcode":"44094",
    "addr:street":"Eagle Nest Dr",
    "iso:country":"US",
    "sg:address":"38401 Eagle Nest Dr",
    "sg:city":"Willoughby",
    "sg:classifiers":[
        {
            "category":"Building & Trades",
            "subcategory":"Construction",
            "type":"Services"
        }
    ],
    "sg:phone":"+1 440 946 5364",
    "sg:postcode":"44094",
    "sg:province":"OH",
    "sg:tags":[
        "nonresidential"
    ],
    "wof:name":"Thomas A Rentschler Inc",
    "wof:placetype":"venue"
},
  "geometry": {"coordinates":[-81.394989,41.597185],"type":"Point"}
}