{
  "type": "Feature",
  "properties": {
    "iso:country":"US",
    "sg:address":"14675 Foltz Industrial Pkwy",
    "sg:city":"Strongsville",
    "sg:classifiers":[
        {
            "category":"Freight",
            "type":"Transportation"
        }
    ],
    "sg:phone":"+1 440 846 0722",
    "sg:postcode":"44149",
    "sg:province":"OH",
    "sg:tags":[
        "mover"
    ],
    "sg:website":"www.leadersmoving.com",
    "wof:name":"Leaders Moving & Storage",
    "wof:placetype":"venue"
},
  "geometry": {"coordinates":[-81.871112,41.306519],"type":"Point"}
}