{
  "type": "Feature",
  "properties": {
    "addr:full": "13911 Oak Brook Dr Cleveland OH 44133",
    "addr:housenumber": "13911",
    "addr:postcode": "44133",
    "addr:street": "Oak Brook Dr",
    "iso:country": "US",
    "sg:address": "13911 Oak Brook Dr",
    "sg:city": "Cleveland",
    "sg:classifiers": [
      {
        "category": "Real Estate",
        "subcategory": "Real Estate Operator",
        "type": "Services"
      }
    ],
    "sg:phone": "+1 440 237 3613",
    "sg:postcode": "44133",
    "sg:province": "OH",
    "sg:tags": [
      "apartment"
    ],
    "wof:name": "Oak Brook Garden Apartments",
    "wof:placetype": "venue"
  },
  "geometry": {"coordinates":[-81.749394,41.312788],"type":"Point"}
}
