{
  "type": "Feature",
  "properties": {
    "addr:full": "3840 Silverwood Dr Stow OH 44224",
    "addr:housenumber": "3840",
    "addr:postcode": "44224",
    "addr:street": "Silverwood Dr",
    "iso:country": "US",
    "sg:address": "3840 Silverwood Dr",
    "sg:city": "Stow",
    "sg:classifiers": [
      {
        "category": "Manufacturing",
        "subcategory": "Electronics",
        "type": "Manufacturing \u0026 Wholesale Goods"
      }
    ],
    "sg:phone": "+1 330 688 7779",
    "sg:postcode": "44224",
    "sg:province": "OH",
    "sg:tags": [
      "apparatus",
      "mfg"
    ],
    "wof:name": "Rorr Company Inc",
    "wof:placetype": "venue"
  },
  "geometry": {"coordinates":[-81.447721,41.172901],"type":"Point"}
}
