{
  "type": "Feature",
  "properties": {
    "addr:full": "1776 Lone Eagle St Columbus OH 43228",
    "addr:housenumber": "1776",
    "addr:postcode": "43228",
    "addr:street": "Lone Eagle St",
    "iso:country": "US",
    "sg:address": "1776 Lone Eagle St",
    "sg:city": "Columbus",
    "sg:classifiers": [
      {
        "category": "Manufacturing",
        "subcategory": "Signs",
        "type": "Manufacturing \u0026 Wholesale Goods"
      }
    ],
    "sg:phone": "+1 614 851 1100",
    "sg:postcode": "43228",
    "sg:province": "OH",
    "sg:tags": [
      "specialty",
      "mfg"
    ],
    "sg:website": "www.ledgible.com",
    "wof:name": "American Led-Gible Inc",
    "wof:placetype": "venue"
  },
  "geometry": {"coordinates":[-83.138554,39.911041],"type":"Point"}
}
