{
  "type": "Feature",
  "properties": {
    "addr:full":"4731 Shineystone Way Hilliard OH 43026",
    "addr:housenumber":"4731",
    "addr:postcode":"43026",
    "addr:street":"Shineystone Way",
    "iso:country":"US",
    "sg:address":"4731 Shineystone Way",
    "sg:city":"Hilliard",
    "sg:classifiers":[
        {
            "category":"Shopping",
            "subcategory":"Jewelry",
            "type":"Retail Goods"
        }
    ],
    "sg:phone":"+1 614 477 5263",
    "sg:postcode":"43026",
    "sg:province":"OH",
    "wof:name":"Mallory Square Studios",
    "wof:placetype":"venue"
},
  "geometry": {"coordinates":[-83.12176599999999,40.049046],"type":"Point"}
}