{
  "type": "Feature",
  "properties": {
    "addr:full": "2411 N Eastown Rd Lima OH 45807",
    "addr:housenumber": "2411",
    "addr:postcode": "45807",
    "addr:street": "N Eastown Rd",
    "iso:country": "US",
    "sg:address": "2411 N Eastown Rd",
    "sg:city": "Lima",
    "sg:classifiers": [
      {
        "category": "Professional",
        "type": "Services"
      }
    ],
    "sg:phone": "+1 419 222 3285",
    "sg:postcode": "45807",
    "sg:province": "OH",
    "wof:name": "Nasco Services",
    "wof:placetype": "venue"
  },
  "geometry": {"coordinates":[-84.165275,40.773275],"type":"Point"}
}
