{
  "type": "Feature",
  "properties": {
    "addr:full": "1415 E 286th St Wickliffe OH 44092",
    "addr:housenumber": "1415",
    "addr:postcode": "44092",
    "addr:street": "E 286Th St",
    "iso:country": "US",
    "sg:address": "1415 E 286th St",
    "sg:city": "Wickliffe",
    "sg:phone": "+1 440 943 0920",
    "sg:postcode": "44092",
    "sg:province": "OH",
    "sg:tags": [
      "product",
      "petroleum",
      "gasoline-wholesale"
    ],
    "wof:name": "Sky Oil Co Inc",
    "wof:placetype": "venue"
  },
  "geometry": {"coordinates":[-81.487535,41.599711],"type":"Point"}
}
