{
  "type": "Feature",
  "properties": {
    "addr:full":"11381 Montgomery Rd Cincinnati OH 45249",
    "addr:housenumber":"11381",
    "addr:postcode":"45249",
    "addr:street":"Montgomery Rd",
    "iso:country":"US",
    "sg:address":"11381 Montgomery Rd",
    "sg:city":"Cincinnati",
    "sg:classifiers":[
        {
            "category":"Restaurant",
            "type":"Food & Drink"
        }
    ],
    "sg:phone":"+1 513 469 9464",
    "sg:postcode":"45249",
    "sg:province":"OH",
    "sg:website":"www.buffalowildwings.com",
    "wof:name":"Buffalo Wild Wings Grill & Bar",
    "wof:placetype":"venue"
},
  "geometry": {"coordinates":[-84.328498,39.27059],"type":"Point"}
}