{
  "type": "Feature",
  "properties": {
    "iso:country":"US",
    "sg:address":"5128 Fishwick Dr",
    "sg:city":"Cincinnati",
    "sg:classifiers":[
        {
            "category":"Retail",
            "subcategory":"Auto Rental",
            "type":"Services"
        }
    ],
    "sg:phone":"+1 513 242 5270",
    "sg:postcode":"45216",
    "sg:province":"OH",
    "sg:tags":[
        "renting",
        "truck",
        "leasing"
    ],
    "wof:name":"Leaseway Transportation Lsng",
    "wof:placetype":"venue"
},
  "geometry": {"coordinates":[-84.481476,39.182917],"type":"Point"}
}