{
  "type": "Feature",
  "properties": {
    "iso:country":"US",
    "sg:address":"5 E Caston Rd",
    "sg:city":"Akron",
    "sg:classifiers":[
        {
            "category":"Restaurant",
            "type":"Food & Drink"
        }
    ],
    "sg:phone":"+1 330 644 7701",
    "sg:postcode":"44319",
    "sg:province":"OH",
    "sg:tags":[
        "parlor",
        "ice",
        "cream"
    ],
    "wof:name":"Tastee Freez",
    "wof:placetype":"venue"
},
  "geometry": {"coordinates":[-81.525357,40.955672],"type":"Point"}
}