{
  "type": "Feature",
  "properties": {
    "addr:full": "2181 E Aurora Rd Twinsburg OH 44087",
    "addr:housenumber": "2181",
    "addr:postcode": "44087",
    "addr:street": "E Aurora Rd",
    "iso:country": "US",
    "sg:address": "2181 E Aurora Rd",
    "sg:city": "Twinsburg",
    "sg:classifiers": [
      {
        "category": "Professional",
        "subcategory": "Business Services",
        "type": "Services"
      }
    ],
    "sg:phone": "+1 330 995 4710",
    "sg:postcode": "44087",
    "sg:province": "OH",
    "wof:name": "R X Options",
    "wof:placetype": "venue"
  },
  "geometry": {"coordinates":[-81.470746,41.311443],"type":"Point"}
}
