{
  "type": "Feature",
  "properties": {
    "iso:country":"US",
    "sg:address":"2181 E Aurora Rd",
    "sg:city":"Twinsburg",
    "sg:classifiers":[
        {
            "category":"Professional",
            "subcategory":"Business Services",
            "type":"Services"
        }
    ],
    "sg:phone":"+1 330 995 4710",
    "sg:postcode":"44087",
    "sg:province":"OH",
    "wof:name":"R X Options",
    "wof:placetype":"venue"
},
  "geometry": {"coordinates":[-81.47074600000001,41.311443],"type":"Point"}
}