{
  "type": "Feature",
  "properties": {
    "iso:country":"US",
    "sg:address":"2670 Maysville Pike",
    "sg:city":"Zanesville",
    "sg:classifiers":[
        {
            "category":"Shopping",
            "type":"Retail Goods"
        }
    ],
    "sg:phone":"+1 740 454 8992",
    "sg:postcode":"43701",
    "sg:province":"OH",
    "sg:tags":[
        "telephone",
        "cellular"
    ],
    "wof:name":"Custom Home Electronics",
    "wof:placetype":"venue"
},
  "geometry": {"coordinates":[-82.042606,39.894211],"type":"Point"}
}