{
  "type": "Feature",
  "properties": {
    "addr:full":"470 Kolb Dr Fairfield OH 45014",
    "addr:housenumber":"470",
    "addr:postcode":"45014",
    "addr:street":"Kolb Dr",
    "iso:country":"US",
    "sg:address":"470 Kolb Dr",
    "sg:city":"Fairfield",
    "sg:classifiers":[
        {
            "category":"Restaurant",
            "type":"Food & Drink"
        },
        {
            "category":"Bakery",
            "type":"Food & Drink"
        }
    ],
    "sg:menulink":"http://www.allmenus.com/oh/fairfield/100160-golden-corral/menu/",
    "sg:phone":"+1 513 682 6400",
    "sg:postcode":"45014",
    "sg:province":"OH",
    "sg:tags":[
        "american",
        "bakery",
        "pastry"
    ],
    "wof:name":"Golden Corral",
    "wof:placetype":"venue"
},
  "geometry": {"coordinates":[-84.521154,39.306167],"type":"Point"}
}