{
  "type": "Feature",
  "properties": {
    "addr:full":"3545 Fawn Run Dr Cincinnati OH 45241",
    "addr:housenumber":"3545",
    "addr:postcode":"45241",
    "addr:street":"Fawn Run Dr",
    "iso:country":"US",
    "sg:address":"3545 Fawn Run Dr",
    "sg:city":"Cincinnati",
    "sg:classifiers":[
        {
            "category":"Professional",
            "type":"Services"
        }
    ],
    "sg:phone":"+1 513 733 1006",
    "sg:postcode":"45241",
    "sg:province":"OH",
    "wof:name":"Amy R Pescovitz",
    "wof:placetype":"venue"
},
  "geometry": {"coordinates":[-84.40948400000001,39.243947],"type":"Point"}
}