{
  "type": "Feature",
  "properties": {
    "addr:full": "2452 Graves Rd Batavia OH 45103",
    "addr:housenumber": "2452",
    "addr:postcode": "45103",
    "addr:street": "Graves Rd",
    "iso:country": "US",
    "sg:address": "2452 Graves Rd",
    "sg:city": "Batavia",
    "sg:classifiers": [
      {
        "category": "Wholesale",
        "subcategory": "Electrical",
        "type": "Manufacturing \u0026 Wholesale Goods"
      }
    ],
    "sg:phone": "+1 513 732 0531",
    "sg:postcode": "45103",
    "sg:province": "OH",
    "sg:tags": [
      "appliance",
      "electric"
    ],
    "wof:name": "Healthcare Media Technologies",
    "wof:placetype": "venue"
  },
  "geometry": {"coordinates":[-84.129001,39.139773],"type":"Point"}
}
