{
  "type": "Feature",
  "properties": {
    "addr:full":"16170 Canaanville Hills Rd Athens OH 45701",
    "addr:housenumber":"16170",
    "addr:postcode":"45701",
    "addr:street":"Canaanville Hills Rd",
    "iso:country":"US",
    "sg:address":"16170 Canaanville Hills Rd",
    "sg:city":"Athens",
    "sg:classifiers":[
        {
            "category":"Banks & Credit Unions",
            "subcategory":"Investment Brokerage",
            "type":"Services"
        }
    ],
    "sg:phone":"+1 740 593 8888",
    "sg:postcode":"45701",
    "sg:province":"OH",
    "sg:tags":[
        "stock",
        "bond"
    ],
    "wof:name":"Ark Investments",
    "wof:placetype":"venue"
},
  "geometry": {"coordinates":[-81.98610600000001,39.316424],"type":"Point"}
}