{
  "type": "Feature",
  "properties": {
    "addr:full": "4046 Knapp Dr Grove City OH 43123",
    "addr:housenumber": "4046",
    "addr:postcode": "43123",
    "addr:street": "Knapp Dr",
    "iso:country": "US",
    "sg:address": "4046 Knapp Dr",
    "sg:city": "Grove City",
    "sg:classifiers": [
      {
        "category": "Shopping",
        "subcategory": "Hobbies, Toys, \u0026 Games",
        "type": "Retail Goods"
      }
    ],
    "sg:phone": "+1 614 871 3035",
    "sg:postcode": "43123",
    "sg:province": "OH",
    "sg:tags": [
      "equipment",
      "ceramic",
      "supply"
    ],
    "wof:name": "Coffee Break Ceramics \u0026 Crafts",
    "wof:placetype": "venue"
  },
  "geometry": {"coordinates":[-83.070998,39.880614],"type":"Point"}
}
