{
  "type": "Feature",
  "properties": {
    "iso:country":"US",
    "sg:address":"4046 Knapp Dr",
    "sg:city":"Grove City",
    "sg:classifiers":[
        {
            "category":"Shopping",
            "subcategory":"Hobbies, Toys, & Games",
            "type":"Retail Goods"
        }
    ],
    "sg:phone":"+1 614 871 3035",
    "sg:postcode":"43123",
    "sg:province":"OH",
    "sg:tags":[
        "equipment",
        "ceramic",
        "supply"
    ],
    "wof:name":"Coffee Break Ceramics & Crafts",
    "wof:placetype":"venue"
},
  "geometry": {"coordinates":[-83.070998,39.880614],"type":"Point"}
}