{
  "type": "Feature",
  "properties": {
    "addr:full":"1449 Crissinger Rd Marion OH 43302",
    "addr:housenumber":"1449",
    "addr:postcode":"43302",
    "addr:street":"Crissinger Rd",
    "iso:country":"US",
    "sg:address":"1449 Crissinger Rd",
    "sg:city":"Marion",
    "sg:classifiers":[
        {
            "category":"Organizations",
            "subcategory":"Religious Organization",
            "type":"Services"
        }
    ],
    "sg:phone":"+1 740 382 0462",
    "sg:postcode":"43302",
    "sg:province":"OH",
    "sg:tags":[
        "church"
    ],
    "wof:name":"First Free Will Baptist",
    "wof:placetype":"venue"
},
  "geometry": {"coordinates":[-83.15992300000001,40.561365],"type":"Point"}
}