{
  "type": "Feature",
  "properties": {
    "addr:full": "2745 Mapletree Ct Cincinnati OH 45236",
    "addr:housenumber": "2745",
    "addr:postcode": "45236",
    "addr:street": "Mapletree Ct",
    "iso:country": "US",
    "sg:address": "2745 Mapletree Ct",
    "sg:city": "Cincinnati",
    "sg:classifiers": [
      {
        "category": "Banks \u0026 Credit Unions",
        "subcategory": "Financial Services",
        "type": "Services"
      }
    ],
    "sg:phone": "+1 513 984 4021",
    "sg:postcode": "45236",
    "sg:province": "OH",
    "sg:tags": [
      "property",
      "management",
      "investment"
    ],
    "wof:name": "Stelllar Prprty Invstments LLC",
    "wof:placetype": "venue"
  },
  "geometry": {"coordinates":[-84.410215,39.22628],"type":"Point"}
}
