{
  "type": "Feature",
  "properties": {
    "addr:full":"3120 Parkman Rd NW Warren OH 44485",
    "addr:housenumber":"3120",
    "addr:postcode":"44485",
    "addr:street":"Parkman Rd Nw",
    "iso:country":"US",
    "sg:address":"3120 Parkman Rd NW",
    "sg:city":"Warren",
    "sg:classifiers":[
        {
            "category":"Food & Beverages",
            "subcategory":"Groceries & Convenience Stores",
            "type":"Retail Goods"
        }
    ],
    "sg:phone":"+1 330 898 2290",
    "sg:postcode":"44485",
    "sg:province":"OH",
    "sg:tags":[
        "ticket",
        "lottery",
        "beer",
        "wine"
    ],
    "wof:name":"Janine",
    "wof:placetype":"venue"
},
  "geometry": {"coordinates":[-80.863213,41.256623],"type":"Point"}
}