{
  "type": "Feature",
  "properties": {
    "addr:full":"7300 Nightingale Dr Holland OH 43528",
    "addr:housenumber":"7300",
    "addr:postcode":"43528",
    "addr:street":"Nightingale Dr",
    "iso:country":"US",
    "sg:address":"7300 Nightingale Dr",
    "sg:city":"Holland",
    "sg:classifiers":[
        {
            "category":"Real Estate",
            "subcategory":"Real Estate Operator",
            "type":"Services"
        }
    ],
    "sg:phone":"+1 419 865 3888",
    "sg:postcode":"43528",
    "sg:province":"OH",
    "sg:tags":[
        "building",
        "apartment"
    ],
    "wof:name":"Fox Chase Apartments",
    "wof:placetype":"venue"
},
  "geometry": {"coordinates":[-83.71553400000001,41.607033],"type":"Point"}
}