{
  "type": "Feature",
  "properties": {
    "iso:country":"US",
    "sg:address":"2290 Shawnee Rd",
    "sg:city":"Lima",
    "sg:classifiers":[
        {
            "category":"Restaurant",
            "type":"Food & Drink"
        }
    ],
    "sg:menulink":"http://www.allmenus.com/oh/shawnee/213865-taco-bell/menu/",
    "sg:phone":"+1 419 224 4575",
    "sg:postcode":"45805",
    "sg:province":"OH",
    "sg:tags":[
        "mexican"
    ],
    "wof:name":"Taco Bell",
    "wof:placetype":"venue"
},
  "geometry": {"coordinates":[-84.151409,40.707624],"type":"Point"}
}