{
  "type": "Feature",
  "properties": {
    "addr:full": "420 Pike St Cincinnati OH 45215",
    "addr:housenumber": "420",
    "addr:postcode": "45215",
    "addr:street": "Pike St",
    "iso:country": "US",
    "sg:address": "420 Pike St",
    "sg:city": "Cincinnati",
    "sg:classifiers": [
      {
        "category": "Professional",
        "subcategory": "Business Services",
        "type": "Services"
      }
    ],
    "sg:phone": "+1 513 821 4745",
    "sg:postcode": "45215",
    "sg:province": "OH",
    "sg:tags": [
      "interior",
      "consultant",
      "design",
      "decorator"
    ],
    "wof:name": "Interior Solutions Group LLC",
    "wof:placetype": "venue"
  },
  "geometry": {"coordinates":[-84.447239,39.224757],"type":"Point"}
}
