{
  "type": "Feature",
  "properties": {
    "addr:full":"214 Warner St Marietta OH 45750",
    "addr:housenumber":"214",
    "addr:postcode":"45750",
    "addr:street":"Warner St",
    "iso:country":"US",
    "sg:address":"214 Warner St",
    "sg:city":"Marietta",
    "sg:classifiers":[
        {
            "category":"Building & Trades",
            "subcategory":"Construction",
            "type":"Services"
        }
    ],
    "sg:phone":"+1 740 568 0118",
    "sg:postcode":"45750",
    "sg:province":"OH",
    "sg:tags":[
        "home",
        "improvement"
    ],
    "sg:website":"www.fgsmov.com",
    "wof:name":"First General Svc-Mid Ohio Vly",
    "wof:placetype":"venue"
},
  "geometry": {"coordinates":[-81.430728,39.418583],"type":"Point"}
}