{
  "type": "Feature",
  "properties": {
    "iso:country":"US",
    "sg:address":"718 29th St NE",
    "sg:city":"Canton",
    "sg:classifiers":[
        {
            "category":"Restaurant",
            "type":"Food & Drink"
        }
    ],
    "sg:phone":"+1 330 452 6937",
    "sg:postcode":"44714",
    "sg:province":"OH",
    "sg:tags":[
        "eating"
    ],
    "wof:name":"Grace Shahan",
    "wof:placetype":"venue"
},
  "geometry": {"coordinates":[-81.365233,40.828144],"type":"Point"}
}