{
  "type": "Feature",
  "properties": {
    "addr:full": "718 29th St NE Canton OH 44714",
    "addr:housenumber": "718",
    "addr:postcode": "44714",
    "addr:street": "29Th St Ne",
    "iso:country": "US",
    "sg:address": "718 29th St NE",
    "sg:city": "Canton",
    "sg:classifiers": [
      {
        "category": "Restaurant",
        "type": "Food \u0026 Drink"
      }
    ],
    "sg:phone": "+1 330 452 6937",
    "sg:postcode": "44714",
    "sg:province": "OH",
    "sg:tags": [
      "eating"
    ],
    "wof:name": "Grace Shahan",
    "wof:placetype": "venue"
  },
  "geometry": {"coordinates":[-81.365233,40.828144],"type":"Point"}
}
