{
  "type": "Feature",
  "properties": {
    "addr:full": "232 W Main St Logan OH 43138",
    "addr:housenumber": "232",
    "addr:postcode": "43138",
    "addr:street": "W Main St",
    "iso:country": "US",
    "sg:address": "232 W Main St",
    "sg:city": "Logan",
    "sg:classifiers": [
      {
        "category": "Building \u0026 Trades",
        "subcategory": "Pest Control",
        "type": "Services"
      }
    ],
    "sg:phone": "+1 740 385 7125",
    "sg:postcode": "43138",
    "sg:province": "OH",
    "wof:name": "Arab Termite \u0026 Pest Control Co",
    "wof:placetype": "venue"
  },
  "geometry": {"coordinates":[-82.412742,39.540458],"type":"Point"}
}
