{
  "type": "Feature",
  "properties": {
    "addr:full":"10427 Detroit Ave Cleveland OH 44102",
    "addr:housenumber":"10427",
    "addr:postcode":"44102",
    "addr:street":"Detroit Ave",
    "iso:country":"US",
    "sg:address":"10427 Detroit Ave",
    "sg:city":"Cleveland",
    "sg:classifiers":[
        {
            "category":"Education",
            "subcategory":"School",
            "type":"Public Place"
        }
    ],
    "sg:phone":"+1 216 521 6511",
    "sg:postcode":"44102",
    "sg:province":"OH",
    "sg:tags":[
        "k-",
        "private"
    ],
    "wof:name":"Cleveland Municipal School District",
    "wof:placetype":"venue"
},
  "geometry": {"coordinates":[-81.75622199999999,41.480405],"type":"Point"}
}