{
  "type": "Feature",
  "properties": {
    "addr:full":"1638 Newton Ave Dayton OH 45406",
    "addr:housenumber":"1638",
    "addr:postcode":"45406",
    "addr:street":"Newton Ave",
    "iso:country":"US",
    "sg:address":"1638 Newton Ave",
    "sg:city":"Dayton",
    "sg:classifiers":[
        {
            "category":"Professional",
            "type":"Services"
        }
    ],
    "sg:phone":"+1 937 276 3453",
    "sg:postcode":"45406",
    "sg:province":"OH",
    "wof:name":"Young Electronics Unlimited",
    "wof:placetype":"venue"
},
  "geometry": {"coordinates":[-84.237104,39.778576],"type":"Point"}
}