{
  "type": "Feature",
  "properties": {
    "addr:full": "23660 Miles Rd Cleveland OH 44128",
    "addr:housenumber": "23660",
    "addr:postcode": "44128",
    "addr:street": "Miles Rd",
    "iso:country": "US",
    "sg:address": "23660 Miles Rd",
    "sg:city": "Cleveland",
    "sg:classifiers": [
      {
        "category": "Professional",
        "subcategory": "Management \u0026 Consulting",
        "type": "Services"
      }
    ],
    "sg:phone": "+1 216 332 9377",
    "sg:postcode": "44128",
    "sg:province": "OH",
    "sg:tags": [
      "consultant"
    ],
    "wof:name": "Claiborne Consulting Co",
    "wof:placetype": "venue"
  },
  "geometry": {"coordinates":[-81.510598,41.424306],"type":"Point"}
}
