{
  "type": "Feature",
  "properties": {
    "addr:full":"5715 Telegraph Rd Toledo OH 43612",
    "addr:housenumber":"5715",
    "addr:postcode":"43612",
    "addr:street":"Telegraph Rd",
    "iso:country":"US",
    "sg:address":"5715 Telegraph Rd",
    "sg:city":"Toledo",
    "sg:classifiers":[
        {
            "category":"Retail",
            "subcategory":"Repair Shop",
            "type":"Services"
        }
    ],
    "sg:phone":"+1 419 269 1560",
    "sg:postcode":"43612",
    "sg:province":"OH",
    "sg:tags":[
        "welding"
    ],
    "wof:name":"American Manufacturing Op",
    "wof:placetype":"venue"
},
  "geometry": {"coordinates":[-83.54745200000001,41.72024],"type":"Point"}
}