{
  "type": "Feature",
  "properties": {
    "addr:full": "3048 Graham Rd Stow OH 44224",
    "addr:housenumber": "3048",
    "addr:postcode": "44224",
    "addr:street": "Graham Rd",
    "iso:country": "US",
    "sg:address": "3048 Graham Rd",
    "sg:city": "Stow",
    "sg:classifiers": [
      {
        "category": "Restaurant",
        "type": "Food \u0026 Drink"
      }
    ],
    "sg:phone": "+1 330 677 9901",
    "sg:postcode": "44224",
    "sg:province": "OH",
    "sg:tags": [
      "parlor",
      "ice",
      "cream"
    ],
    "sg:website": "www.handelsicecream.com",
    "wof:name": "Handel's Homemade Ice Cream",
    "wof:placetype": "venue"
  },
  "geometry": {"coordinates":[-81.400574,41.16631],"type":"Point"}
}
