{
  "type": "Feature",
  "properties": {
    "addr:full":"955 Wheeling Ave Cambridge OH 43725",
    "addr:housenumber":"955",
    "addr:postcode":"43725",
    "addr:street":"Wheeling Ave",
    "iso:country":"US",
    "sg:address":"955 Wheeling Ave",
    "sg:city":"Cambridge",
    "sg:classifiers":[
        {
            "category":"Shopping",
            "subcategory":"Jewelry",
            "type":"Retail Goods"
        }
    ],
    "sg:phone":"+1 740 432 2253",
    "sg:postcode":"43725",
    "sg:province":"OH",
    "sg:tags":[
        "jeweler"
    ],
    "wof:name":"Mj's",
    "wof:placetype":"venue"
},
  "geometry": {"coordinates":[-81.587104,40.024738],"type":"Point"}
}