{
  "type": "Feature",
  "properties": {
    "addr:full":"3292 Andrews Rd Bucyrus OH 44820",
    "addr:housenumber":"3292",
    "addr:postcode":"44820",
    "addr:street":"Andrews Rd",
    "iso:country":"US",
    "sg:address":"3292 Andrews Rd",
    "sg:city":"Bucyrus",
    "sg:classifiers":[
        {
            "category":"Building & Trades",
            "subcategory":"Construction",
            "type":"Services"
        }
    ],
    "sg:phone":"+1 419 562 0712",
    "sg:postcode":"44820",
    "sg:province":"OH",
    "sg:tags":[
        "residential",
        "commercial"
    ],
    "wof:name":"Lutz Construction",
    "wof:placetype":"venue"
},
  "geometry": {"coordinates":[-82.955292,40.83778],"type":"Point"}
}