{
  "type": "Feature",
  "properties": {
    "addr:full": "1623 Golden Gate Plz Cleveland OH 44124",
    "addr:housenumber": "1623",
    "addr:postcode": "44124",
    "addr:street": "Golden Gate Plz",
    "iso:country": "US",
    "sg:address": "1623 Golden Gate Plz",
    "sg:city": "Cleveland",
    "sg:classifiers": [
      {
        "category": "Government",
        "subcategory": "Office",
        "type": "Public Place"
      }
    ],
    "sg:phone": "+1 440 442 0030",
    "sg:postcode": "44124",
    "sg:province": "OH",
    "sg:tags": [
      "parish",
      "government-county"
    ],
    "wof:name": "Cuyahoga County Auto \u0026 Boat",
    "wof:placetype": "venue"
  },
  "geometry": {"coordinates":[-81.449837,41.51632],"type":"Point"}
}
