{
  "type": "Feature",
  "properties": {
    "addr:full": "310 Hillside Ave Lancaster OH 43130",
    "addr:housenumber": "310",
    "addr:postcode": "43130",
    "addr:street": "Hillside Ave",
    "iso:country": "US",
    "sg:address": "310 Hillside Ave",
    "sg:city": "Lancaster",
    "sg:classifiers": [
      {
        "category": "Manufacturing",
        "subcategory": "Toys \u0026 Sporting Goods",
        "type": "Manufacturing \u0026 Wholesale Goods"
      }
    ],
    "sg:phone": "+1 740 654 0220",
    "sg:postcode": "43130",
    "sg:province": "OH",
    "sg:tags": [
      "personal",
      "mfg"
    ],
    "wof:name": "Ye Dragon \u0026 Unicorn",
    "wof:placetype": "venue"
  },
  "geometry": {"coordinates":[-82.60648,39.727743],"type":"Point"}
}
