{
  "type": "Feature",
  "properties": {
    "addr:full":"919 Yesterday Ln Medina OH 44256",
    "addr:housenumber":"919",
    "addr:postcode":"44256",
    "addr:street":"Yesterday Ln",
    "iso:country":"US",
    "sg:address":"919 Yesterday Ln",
    "sg:city":"Medina",
    "sg:classifiers":[
        {
            "category":"Professional",
            "subcategory":"Credit Reporting & Collection",
            "type":"Services"
        }
    ],
    "sg:phone":"+1 330 722 9694",
    "sg:postcode":"44256",
    "sg:province":"OH",
    "sg:tags":[
        "agency"
    ],
    "wof:name":"Credit Plus Solutions Group",
    "wof:placetype":"venue"
},
  "geometry": {"coordinates":[-81.88746,41.123916],"type":"Point"}
}