{
  "type": "Feature",
  "properties": {
    "addr:full":"12 E Warren St Lebanon OH 45036",
    "addr:housenumber":"12",
    "addr:postcode":"45036",
    "addr:street":"E Warren St",
    "iso:country":"US",
    "sg:address":"12 E Warren St",
    "sg:city":"Lebanon",
    "sg:classifiers":[
        {
            "category":"Professional",
            "subcategory":"Lawyer & Legal Services",
            "type":"Services"
        }
    ],
    "sg:phone":"+1 513 932 2115",
    "sg:postcode":"45036",
    "sg:province":"OH",
    "sg:tags":[
        "attorney"
    ],
    "sg:website":"http://www.ypad.com/business-profile.cfm/state/OH/city/Lebanon/ppid/14966",
    "wof:name":"Rittgers & Rittgers",
    "wof:placetype":"venue"
},
  "geometry": {"coordinates":[-84.207846,39.4366],"type":"Point"}
}