{
  "type": "Feature",
  "properties": {
    "iso:country":"US",
    "sg:address":"852 Wales Rd NE",
    "sg:city":"Massillon",
    "sg:classifiers":[
        {
            "category":"Building & Trades",
            "subcategory":"Landscaping Services",
            "type":"Services"
        }
    ],
    "sg:phone":"+1 330 833 6364",
    "sg:postcode":"44646",
    "sg:province":"OH",
    "sg:tags":[
        "lawn",
        "maintenance",
        "grounds"
    ],
    "wof:name":"Leonard's Lawn Maintenance",
    "wof:placetype":"venue"
},
  "geometry": {"coordinates":[-81.509376,40.808364],"type":"Point"}
}