{
  "type": "Feature",
  "properties": {
    "addr:full": "852 Wales Rd NE Massillon OH 44646",
    "addr:housenumber": "852",
    "addr:postcode": "44646",
    "addr:street": "Wales Rd Ne",
    "iso:country": "US",
    "sg:address": "852 Wales Rd NE",
    "sg:city": "Massillon",
    "sg:classifiers": [
      {
        "category": "Building \u0026 Trades",
        "subcategory": "Landscaping Services",
        "type": "Services"
      }
    ],
    "sg:phone": "+1 330 833 6364",
    "sg:postcode": "44646",
    "sg:province": "OH",
    "sg:tags": [
      "lawn",
      "maintenance",
      "grounds"
    ],
    "wof:name": "Leonard's Lawn Maintenance",
    "wof:placetype": "venue"
  },
  "geometry": {"coordinates":[-81.509376,40.808364],"type":"Point"}
}
