{
  "type": "Feature",
  "properties": {
    "addr:full": "151 N Salem Warren Rd North Jackson OH 44451",
    "addr:housenumber": "151",
    "addr:postcode": "44451",
    "addr:street": "N Salem Warren Rd",
    "iso:country": "US",
    "sg:address": "151 N Salem Warren Rd",
    "sg:city": "North Jackson",
    "sg:classifiers": [
      {
        "category": "Home \u0026 Garden",
        "subcategory": "Household Appliances",
        "type": "Retail Goods"
      }
    ],
    "sg:phone": "+1 330 538 3967",
    "sg:postcode": "44451",
    "sg:province": "OH",
    "wof:name": "Anderson Appliance Ctr",
    "wof:placetype": "venue"
  },
  "geometry": {"coordinates":[-80.8571,41.101217],"type":"Point"}
}
