{
  "type": "Feature",
  "properties": {
    "iso:country":"US",
    "sg:address":"151 N Salem Warren Rd",
    "sg:city":"North Jackson",
    "sg:classifiers":[
        {
            "category":"Home & Garden",
            "subcategory":"Household Appliances",
            "type":"Retail Goods"
        }
    ],
    "sg:phone":"+1 330 538 3967",
    "sg:postcode":"44451",
    "sg:province":"OH",
    "wof:name":"Anderson Appliance Ctr",
    "wof:placetype":"venue"
},
  "geometry": {"coordinates":[-80.8571,41.101217],"type":"Point"}
}