{
  "type": "Feature",
  "properties": {
    "iso:country":"US",
    "sg:address":"2037 Parkview Dr",
    "sg:city":"Twinsburg",
    "sg:classifiers":[
        {
            "category":"Building & Trades",
            "subcategory":"Construction",
            "type":"Services"
        }
    ],
    "sg:phone":"+1 330 963 6670",
    "sg:postcode":"44087",
    "sg:province":"OH",
    "sg:tags":[
        "contractor",
        "carpentry"
    ],
    "wof:name":"Ability Home Improvements Inc",
    "wof:placetype":"venue"
},
  "geometry": {"coordinates":[-81.452581,41.343765],"type":"Point"}
}