{
  "type": "Feature",
  "properties": {
    "addr:full":"28 Harding Ave Jackson OH 45640",
    "addr:housenumber":"28",
    "addr:postcode":"45640",
    "addr:street":"Harding Ave",
    "iso:country":"US",
    "sg:address":"28 Harding Ave",
    "sg:city":"Jackson",
    "sg:classifiers":[
        {
            "category":"Retail",
            "subcategory":"Funeral Services",
            "type":"Services"
        }
    ],
    "sg:phone":"+1 740 286 2010",
    "sg:postcode":"45640",
    "sg:province":"OH",
    "sg:tags":[
        "director"
    ],
    "wof:name":"Eisnaugle-Lewis Funeral Home",
    "wof:placetype":"venue"
},
  "geometry": {"coordinates":[-82.63413300000001,39.048959],"type":"Point"}
}