{
  "type": "Feature",
  "properties": {
    "addr:full": "1003 Concord Ave Columbus OH 43212",
    "addr:housenumber": "1003",
    "addr:postcode": "43212",
    "addr:street": "Concord Ave",
    "iso:country": "US",
    "sg:address": "1003 Concord Ave",
    "sg:city": "Columbus",
    "sg:classifiers": [
      {
        "category": "Professional",
        "subcategory": "Computer Services",
        "type": "Services"
      }
    ],
    "sg:phone": "+1 614 299 0184",
    "sg:postcode": "43212",
    "sg:province": "OH",
    "sg:tags": [
      "wiring"
    ],
    "sg:website": "www.statcabling.com",
    "wof:name": "Stat Communications",
    "wof:placetype": "venue"
  },
  "geometry": {"coordinates":[-83.033763,39.992153],"type":"Point"}
}
