{
  "type": "Feature",
  "properties": {
    "addr:full":"4319 Lincoln Way E Massillon OH 44646",
    "addr:housenumber":"4319",
    "addr:postcode":"44646",
    "addr:street":"Lincoln Way E",
    "iso:country":"US",
    "sg:address":"4319 Lincoln Way E",
    "sg:city":"Massillon",
    "sg:classifiers":[
        {
            "category":"Autos & Motor Vehicles",
            "subcategory":"Automobile Sales",
            "type":"Retail Goods"
        }
    ],
    "sg:phone":"+1 330 477 3795",
    "sg:postcode":"44646",
    "sg:province":"OH",
    "sg:tags":[
        "car",
        "dealer"
    ],
    "wof:name":"Waikem Auto Group",
    "wof:placetype":"venue"
},
  "geometry": {"coordinates":[-81.453129,40.792531],"type":"Point"}
}