{
  "type": "Feature",
  "properties": {
    "iso:country":"US",
    "sg:address":"7615 Reading Rd",
    "sg:city":"Cincinnati",
    "sg:classifiers":[
        {
            "category":"Banks & Credit Unions",
            "subcategory":"Bank",
            "type":"Services"
        }
    ],
    "sg:phone":"+1 513 761 1101",
    "sg:postcode":"45237",
    "sg:province":"OH",
    "sg:tags":[
        "savings"
    ],
    "sg:website":"www.franklinsavings.com",
    "wof:name":"Franklin Savings & Loan Co",
    "wof:placetype":"venue"
},
  "geometry": {"coordinates":[-84.45667,39.200789],"type":"Point"}
}