{
  "type": "Feature",
  "properties": {
    "addr:full": "1842 Enterprise Pkwy Twinsburg OH 44087",
    "addr:housenumber": "1842",
    "addr:postcode": "44087",
    "addr:street": "Enterprise Pkwy",
    "iso:country": "US",
    "sg:address": "1842 Enterprise Pkwy",
    "sg:city": "Twinsburg",
    "sg:classifiers": [
      {
        "category": "Real Estate",
        "subcategory": "Real Estate Agent",
        "type": "Services"
      }
    ],
    "sg:phone": "+1 330 963 4453",
    "sg:postcode": "44087",
    "sg:province": "OH",
    "wof:name": "First Industrial Realty",
    "wof:placetype": "venue"
  },
  "geometry": {"coordinates":[-81.453539,41.291547],"type":"Point"}
}
