{
  "type": "Feature",
  "properties": {
    "addr:full":"1205 Park Ave W Mansfield OH 44906",
    "addr:housenumber":"1205",
    "addr:postcode":"44906",
    "addr:street":"Park Ave W",
    "iso:country":"US",
    "sg:address":"1205 Park Ave W",
    "sg:city":"Mansfield",
    "sg:classifiers":[
        {
            "category":"Shopping",
            "subcategory":"Beauty & Cosmetics",
            "type":"Retail Goods"
        }
    ],
    "sg:phone":"+1 419 529 3377",
    "sg:postcode":"44906",
    "sg:province":"OH",
    "sg:tags":[
        "hair",
        "salon"
    ],
    "wof:name":"Merle Norman Cosmetics",
    "wof:placetype":"venue"
},
  "geometry": {"coordinates":[-82.560029,40.759263],"type":"Point"}
}