{
  "type": "Feature",
  "properties": {
    "addr:full": "18620 Washington St Tontogany OH 43565",
    "addr:housenumber": "18620",
    "addr:postcode": "43565",
    "addr:street": "Washington St",
    "iso:country": "US",
    "sg:address": "18620 Washington St",
    "sg:city": "Tontogany",
    "sg:classifiers": [
      {
        "category": "Retail",
        "subcategory": "Funeral Services",
        "type": "Services"
      }
    ],
    "sg:phone": "+1 419 823 4471",
    "sg:postcode": "43565",
    "sg:province": "OH",
    "sg:tags": [
      "director"
    ],
    "wof:name": "Peinert Funeral Home",
    "wof:placetype": "venue"
  },
  "geometry": {"coordinates":[-83.740022,41.420463],"type":"Point"}
}
