{
  "type": "Feature",
  "properties": {
    "addr:full":"12657 Chillicothe Rd Chesterland OH 44026",
    "addr:housenumber":"12657",
    "addr:postcode":"44026",
    "addr:street":"Chillicothe Rd",
    "iso:country":"US",
    "sg:address":"12657 Chillicothe Rd",
    "sg:city":"Chesterland",
    "sg:classifiers":[
        {
            "category":"Autos & Motor Vehicles",
            "subcategory":"Auto Supplies",
            "type":"Retail Goods"
        }
    ],
    "sg:phone":"+1 440 729 9030",
    "sg:postcode":"44026",
    "sg:province":"OH",
    "sg:tags":[
        "automobile",
        "parts"
    ],
    "wof:name":"Auto Parts Ctr",
    "wof:placetype":"venue"
},
  "geometry": {"coordinates":[-81.33786499999999,41.524094],"type":"Point"}
}