{
  "type": "Feature",
  "properties": {
    "addr:full": "3081 Gilchrist Rd Akron OH 44260",
    "addr:housenumber": "3081",
    "addr:postcode": "44260",
    "addr:street": "Gilchrist Rd",
    "iso:country": "US",
    "sg:address": "3081 Gilchrist Rd",
    "sg:city": "Akron",
    "sg:classifiers": [
      {
        "category": "Wholesale",
        "subcategory": "Non-durable Goods",
        "type": "Manufacturing \u0026 Wholesale Goods"
      }
    ],
    "sg:phone": "+1 330 733 4485",
    "sg:postcode": "44260",
    "sg:province": "OH",
    "wof:name": "Carved Crystal Gifts",
    "wof:placetype": "venue"
  },
  "geometry": {"coordinates":[-81.421715,41.059408],"type":"Point"}
}
