{
  "type": "Feature",
  "properties": {
    "addr:full": "1063 E 68th St Cleveland OH 44103",
    "addr:housenumber": "1063",
    "addr:postcode": "44103",
    "addr:street": "E 68Th St",
    "iso:country": "US",
    "sg:address": "1063 E 68th St",
    "sg:city": "Cleveland",
    "sg:classifiers": [
      {
        "category": "Social Services",
        "subcategory": "Child Care",
        "type": "Services"
      }
    ],
    "sg:phone": "+1 216 426 0475",
    "sg:postcode": "44103",
    "sg:province": "OH",
    "wof:name": "Avis Daycare Ctr",
    "wof:placetype": "venue"
  },
  "geometry": {"coordinates":[-81.640328,41.524466],"type":"Point"}
}
