{
  "type": "Feature",
  "properties": {
    "addr:full": "600 Howard St Bridgeport OH 43912",
    "addr:housenumber": "600",
    "addr:postcode": "43912",
    "addr:street": "Howard St",
    "iso:country": "US",
    "sg:address": "600 Howard St",
    "sg:city": "Bridgeport",
    "sg:classifiers": [
      {
        "category": "Social Services",
        "type": "Services"
      }
    ],
    "sg:phone": "+1 740 635 2070",
    "sg:postcode": "43912",
    "sg:province": "OH",
    "sg:tags": [
      "organization",
      "welfare"
    ],
    "wof:name": "Belmont County Society",
    "wof:placetype": "venue"
  },
  "geometry": {"coordinates":[-80.749083,40.070158],"type":"Point"}
}
