{
  "type": "Feature",
  "properties": {
    "iso:country":"US",
    "sg:address":"106 Groves Ave",
    "sg:city":"Marietta",
    "sg:classifiers":[
        {
            "category":"Retail",
            "subcategory":"Auto Repair",
            "type":"Services"
        }
    ],
    "sg:phone":"+1 740 373 2218",
    "sg:postcode":"45750",
    "sg:province":"OH",
    "sg:tags":[
        "body",
        "automobile",
        "painting"
    ],
    "wof:name":"Huck's Autobody & Collision",
    "wof:placetype":"venue"
},
  "geometry": {"coordinates":[-81.482375,39.427476],"type":"Point"}
}