{
  "type": "Feature",
  "properties": {
    "addr:full":"1662 Co Rd 10 Bellefontaine OH 43311",
    "addr:housenumber":"1662;10",
    "addr:postcode":"43311",
    "addr:street":"Co Rd",
    "iso:country":"US",
    "sg:address":"1662 Co Rd 10",
    "sg:city":"Bellefontaine",
    "sg:classifiers":[
        {
            "category":"Building & Trades",
            "subcategory":"Construction",
            "type":"Services"
        }
    ],
    "sg:phone":"+1 937 599 1702",
    "sg:postcode":"43311",
    "sg:province":"OH",
    "sg:tags":[
        "general",
        "contractor"
    ],
    "wof:name":"Westerman General Construction",
    "wof:placetype":"venue"
},
  "geometry": {"coordinates":[-83.734432,40.352089],"type":"Point"}
}