{
  "type": "Feature",
  "properties": {
    "iso:country":"US",
    "sg:address":"303 Broadway St",
    "sg:city":"Cincinnati",
    "sg:classifiers":[
        {
            "category":"Banks & Credit Unions",
            "subcategory":"Investment Brokerage",
            "type":"Services"
        }
    ],
    "sg:phone":"+1 513 362 8000",
    "sg:postcode":"45202",
    "sg:province":"OH",
    "sg:tags":[
        "consultant",
        "planning",
        "financial"
    ],
    "sg:website":"www.integratedfundservices.com",
    "wof:name":"IFS Financial Svc Inc",
    "wof:placetype":"venue"
},
  "geometry": {"coordinates":[-84.506017,39.100154],"type":"Point"}
}