{
  "type": "Feature",
  "properties": {
    "addr:full": "7354 State Rte 14 Ravenna OH 44266",
    "addr:housenumber": "7354",
    "addr:postcode": "44266",
    "addr:street": "State Rte 14",
    "iso:country": "US",
    "sg:address": "7354 State Rte 14",
    "sg:city": "Ravenna",
    "sg:classifiers": [
      {
        "category": "Retail",
        "subcategory": "Auto Repair",
        "type": "Services"
      }
    ],
    "sg:phone": "+1 330 297 1800",
    "sg:postcode": "44266",
    "sg:province": "OH",
    "sg:tags": [
      "body",
      "automobile",
      "painting"
    ],
    "wof:name": "Lintz Collision \u0026 Refinish",
    "wof:placetype": "venue"
  },
  "geometry": {"coordinates":[-81.281793,41.188157],"type":"Point"}
}
