{
  "type": "Feature",
  "properties": {
    "iso:country":"US",
    "sg:address":"50 S Miami St",
    "sg:city":"West Milton",
    "sg:classifiers":[
        {
            "category":"Manufacturing",
            "subcategory":"Printing",
            "type":"Manufacturing & Wholesale Goods"
        }
    ],
    "sg:phone":"+1 937 698 8137",
    "sg:postcode":"45383",
    "sg:province":"OH",
    "sg:tags":[
        "equipment",
        "industrial",
        "commercial",
        "business"
    ],
    "wof:name":"Bar Tech Imaging Inc",
    "wof:placetype":"venue"
},
  "geometry": {"coordinates":[-84.3276,39.962037],"type":"Point"}
}