{
  "type": "Feature",
  "properties": {
    "addr:full":"3317 E Broad St Columbus OH 43213",
    "addr:housenumber":"3317",
    "addr:postcode":"43213",
    "addr:street":"E Broad St",
    "iso:country":"US",
    "sg:address":"3317 E Broad St",
    "sg:city":"Columbus",
    "sg:classifiers":[
        {
            "category":"Personal",
            "subcategory":"Beauty Salon",
            "type":"Services"
        }
    ],
    "sg:phone":"+1 614 236 8777",
    "sg:postcode":"43213",
    "sg:province":"OH",
    "wof:name":"Voltar",
    "wof:placetype":"venue"
},
  "geometry": {"coordinates":[-82.912577,39.972008],"type":"Point"}
}