{
  "type": "Feature",
  "properties": {
    "iso:country":"US",
    "sg:address":"1301 E 6th St",
    "sg:city":"Cleveland",
    "sg:classifiers":[
        {
            "category":"Parking",
            "type":"Transportation"
        }
    ],
    "sg:phone":"+1 216 623 0268",
    "sg:postcode":"44114",
    "sg:province":"OH",
    "sg:tags":[
        "garage"
    ],
    "wof:name":"Bond Court Office Garage",
    "wof:placetype":"venue"
},
  "geometry": {"coordinates":[-81.692465,41.504104],"type":"Point"}
}