{
  "type": "Feature",
  "properties": {
    "iso:country":"US",
    "sg:address":"6117 State Rte 18",
    "sg:city":"Republic",
    "sg:classifiers":[
        {
            "category":"Organizations",
            "subcategory":"Religious Organization",
            "type":"Services"
        }
    ],
    "sg:phone":"+1 419 585 0481",
    "sg:postcode":"44867",
    "sg:province":"OH",
    "sg:tags":[
        "clergy"
    ],
    "wof:name":"Richard Barrell",
    "wof:placetype":"venue"
},
  "geometry": {"coordinates":[-83.048939,41.124308],"type":"Point"}
}