{
  "type": "Feature",
  "properties": {
    "addr:full": "4354 S Range Rd New Middletown OH 44442",
    "addr:housenumber": "4354",
    "addr:postcode": "44442",
    "addr:street": "S Range Rd",
    "iso:country": "US",
    "sg:address": "4354 S Range Rd",
    "sg:city": "New Middletown",
    "sg:classifiers": [
      {
        "category": "Building \u0026 Trades",
        "subcategory": "Construction",
        "type": "Services"
      }
    ],
    "sg:phone": "+1 330 542 2585",
    "sg:postcode": "44442",
    "sg:province": "OH",
    "sg:tags": [
      "bridge"
    ],
    "wof:name": "Jet Excavating Co",
    "wof:placetype": "venue"
  },
  "geometry": {"coordinates":[-80.573385,40.943826],"type":"Point"}
}
