{
  "type": "Feature",
  "properties": {
    "addr:full": "626 N 4th St Steubenville OH 43952",
    "addr:housenumber": "626",
    "addr:postcode": "43952",
    "addr:street": "N 4Th St",
    "iso:country": "US",
    "sg:address": "626 N 4th St",
    "sg:city": "Steubenville",
    "sg:classifiers": [
      {
        "category": "Health Services",
        "subcategory": "Clinic",
        "type": "Services"
      }
    ],
    "sg:phone": "+1 740 282 4623",
    "sg:postcode": "43952",
    "sg:province": "OH",
    "sg:tags": [
      "home"
    ],
    "wof:name": "Primary Nursing Care",
    "wof:placetype": "venue"
  },
  "geometry": {"coordinates":[-80.611141,40.367536],"type":"Point"}
}
