{
  "type": "Feature",
  "properties": {
    "addr:full": "358 S Main St Akron OH 44311",
    "addr:housenumber": "358",
    "addr:postcode": "44311",
    "addr:street": "S Main St",
    "iso:country": "US",
    "sg:address": "358 S Main St",
    "sg:city": "Akron",
    "sg:classifiers": [
      {
        "category": "Bars \u0026 Pubs",
        "type": "Food \u0026 Drink"
      }
    ],
    "sg:phone": "+1 330 535 6776",
    "sg:postcode": "44311",
    "sg:province": "OH",
    "sg:tags": [
      "drinking"
    ],
    "wof:name": "Club Amsterdam",
    "wof:placetype": "venue"
  },
  "geometry": {"coordinates":[-81.522769,41.075793],"type":"Point"}
}
