{
  "type": "Feature",
  "properties": {
    "iso:country":"US",
    "sg:address":"381 Heil Dr",
    "sg:city":"Columbus",
    "sg:classifiers":[
        {
            "category":"Building & Trades",
            "subcategory":"Construction",
            "type":"Services"
        }
    ],
    "sg:phone":"+1 614 471 4172",
    "sg:postcode":"43230",
    "sg:province":"OH",
    "sg:tags":[
        "housing"
    ],
    "wof:name":"Backulich Remodeling",
    "wof:placetype":"venue"
},
  "geometry": {"coordinates":[-82.869782,40.024059],"type":"Point"}
}