{
  "type": "Feature",
  "properties": {
    "addr:full":"100 E Main St Martinsville OH 45146",
    "addr:housenumber":"100",
    "addr:postcode":"45146",
    "addr:street":"E Main St",
    "iso:country":"US",
    "sg:address":"100 E Main St",
    "sg:city":"Martinsville",
    "sg:classifiers":[
        {
            "category":"Retail",
            "subcategory":"Auto Repair",
            "type":"Services"
        }
    ],
    "sg:phone":"+1 937 685 4043",
    "sg:postcode":"45146",
    "sg:province":"OH",
    "sg:tags":[
        "repairing",
        "automobile"
    ],
    "wof:name":"Brown's Distributors & Garage",
    "wof:placetype":"venue"
},
  "geometry": {"coordinates":[-83.81148399999999,39.323768],"type":"Point"}
}