{
  "type": "Feature",
  "properties": {
    "addr:full":"236 Green St Dayton OH 45402",
    "addr:housenumber":"236",
    "addr:postcode":"45402",
    "addr:street":"Green St",
    "iso:country":"US",
    "sg:address":"236 Green St",
    "sg:city":"Dayton",
    "sg:classifiers":[
        {
            "category":"Restaurant",
            "type":"Food & Drink"
        }
    ],
    "sg:phone":"+1 937 237 1672",
    "sg:postcode":"45402",
    "sg:province":"OH",
    "sg:tags":[
        "shop",
        "coffee"
    ],
    "wof:name":"Common Ground Unlimited Inc",
    "wof:placetype":"venue"
},
  "geometry": {"coordinates":[-84.183756,39.754753],"type":"Point"}
}