{
  "type": "Feature",
  "properties": {
    "addr:full":"1925 W Dorothy Ln Dayton OH 45439",
    "addr:housenumber":"1925",
    "addr:postcode":"45439",
    "addr:street":"W Dorothy Ln",
    "iso:country":"US",
    "sg:address":"1925 W Dorothy Ln",
    "sg:city":"Dayton",
    "sg:classifiers":[
        {
            "category":"Ice Cream",
            "type":"Food & Drink"
        }
    ],
    "sg:menulink":"http://www.allmenus.com/oh/moraine/92717-steak-n-shake/menu/",
    "sg:phone":"+1 937 299 9140",
    "sg:postcode":"45439",
    "sg:province":"OH",
    "sg:tags":[
        "american"
    ],
    "wof:name":"Steak 'n Shake",
    "wof:placetype":"venue"
},
  "geometry": {"coordinates":[-84.205378,39.709463],"type":"Point"}
}