{
  "type": "Feature",
  "properties": {
    "iso:country":"US",
    "sg:address":"5509 Milan Rd",
    "sg:city":"Sandusky",
    "sg:classifiers":[
        {
            "category":"Professional",
            "subcategory":"Advertising",
            "type":"Services"
        }
    ],
    "sg:phone":"+1 419 621 2100",
    "sg:postcode":"44870",
    "sg:province":"OH",
    "wof:name":"Ameritech Advertising",
    "wof:placetype":"venue"
},
  "geometry": {"coordinates":[-82.652815,41.396869],"type":"Point"}
}