{
  "type": "Feature",
  "properties": {
    "addr:full": "20891 Liberty Hi Rd Bowling Green OH 43402",
    "addr:housenumber": "20891",
    "addr:postcode": "43402",
    "addr:street": "Liberty Hi",
    "iso:country": "US",
    "sg:address": "20891 Liberty Hi Rd",
    "sg:city": "Bowling Green",
    "sg:classifiers": [
      {
        "category": "Building \u0026 Trades",
        "subcategory": "Landscaping Services",
        "type": "Services"
      }
    ],
    "sg:phone": "+1 419 810 3394",
    "sg:postcode": "43402",
    "sg:province": "OH",
    "sg:tags": [
      "lawn",
      "maintenance",
      "grounds"
    ],
    "wof:name": "Kazmaier Lawn Svc \u0026 Lndscpng",
    "wof:placetype": "venue"
  },
  "geometry": {"coordinates":[-83.708817,41.452345],"type":"Point"}
}
