{
  "type": "Feature",
  "properties": {
    "addr:full":"594 N Detroit St Xenia OH 45385",
    "addr:housenumber":"594",
    "addr:postcode":"45385",
    "addr:street":"N Detroit St",
    "iso:country":"US",
    "sg:address":"594 N Detroit St",
    "sg:city":"Xenia",
    "sg:classifiers":[
        {
            "category":"Shopping",
            "subcategory":"Bicycles & Sporting Goods",
            "type":"Retail Goods"
        }
    ],
    "sg:phone":"+1 937 372 2555",
    "sg:postcode":"45385",
    "sg:province":"OH",
    "wof:name":"K & G Bike Ctr",
    "wof:placetype":"venue"
},
  "geometry": {"coordinates":[-83.931253,39.693518],"type":"Point"}
}