{
  "type": "Feature",
  "properties": {
    "addr:full": "2030 Britains Ln Columbus OH 43224",
    "addr:housenumber": "2030",
    "addr:postcode": "43224",
    "addr:street": "Britains Ln",
    "iso:country": "US",
    "sg:address": "2030 Britains Ln",
    "sg:city": "Columbus",
    "sg:classifiers": [
      {
        "category": "Manufacturing",
        "subcategory": "Building Materials",
        "type": "Manufacturing \u0026 Wholesale Goods"
      }
    ],
    "sg:phone": "+1 614 262 6340",
    "sg:postcode": "43224",
    "sg:province": "OH",
    "wof:name": "Historic Turnings \u0026 Millwork",
    "wof:placetype": "venue"
  },
  "geometry": {"coordinates":[-82.961992,40.034526],"type":"Point"}
}
