{
  "type": "Feature",
  "properties": {
    "iso:country":"US",
    "sg:address":"2030 Britains Ln",
    "sg:city":"Columbus",
    "sg:classifiers":[
        {
            "category":"Manufacturing",
            "subcategory":"Building Materials",
            "type":"Manufacturing & Wholesale Goods"
        }
    ],
    "sg:phone":"+1 614 262 6340",
    "sg:postcode":"43224",
    "sg:province":"OH",
    "wof:name":"Historic Turnings & Millwork",
    "wof:placetype":"venue"
},
  "geometry": {"coordinates":[-82.961992,40.034526],"type":"Point"}
}