{
  "type": "Feature",
  "properties": {
    "addr:full":"1212 S Main St Englewood OH 45322",
    "addr:housenumber":"1212",
    "addr:postcode":"45322",
    "addr:street":"S Main St",
    "iso:country":"US",
    "sg:address":"1212 S Main St",
    "sg:city":"Englewood",
    "sg:classifiers":[
        {
            "category":"Travel",
            "subcategory":"Hotels & Motels",
            "type":"Entertainment"
        }
    ],
    "sg:phone":"+1 937 832 3770",
    "sg:postcode":"45322",
    "sg:province":"OH",
    "sg:tags":[
        "operation"
    ],
    "wof:name":"Motel 6",
    "wof:placetype":"venue"
},
  "geometry": {"coordinates":[-84.28374700000001,39.861518],"type":"Point"}
}