{
  "type": "Feature",
  "properties": {
    "addr:full": "115 E Main St Adena OH 43901",
    "addr:housenumber": "115",
    "addr:postcode": "43901",
    "addr:street": "E Main St",
    "iso:country": "US",
    "sg:address": "115 E Main St",
    "sg:city": "Adena",
    "sg:classifiers": [
      {
        "category": "Government",
        "subcategory": "Police Station",
        "type": "Public Place"
      }
    ],
    "sg:phone": "+1 740 546 3211",
    "sg:postcode": "43901",
    "sg:province": "OH",
    "sg:tags": [
      "protection"
    ],
    "wof:name": "Adena Vlg Police Dept",
    "wof:placetype": "venue"
  },
  "geometry": {"coordinates":[-80.87128,40.217886],"type":"Point"}
}
