{
  "type": "Feature",
  "properties": {
    "addr:full":"2518 Needmore Rd Dayton OH 45414",
    "addr:housenumber":"2518",
    "addr:postcode":"45414",
    "addr:street":"Needmore Rd",
    "iso:country":"US",
    "sg:address":"2518 Needmore Rd",
    "sg:city":"Dayton",
    "sg:classifiers":[
        {
            "category":"Restaurant",
            "type":"Food & Drink"
        }
    ],
    "sg:phone":"+1 937 276 2122",
    "sg:postcode":"45414",
    "sg:province":"OH",
    "sg:tags":[
        "family"
    ],
    "wof:name":"Big Boy Restaurant",
    "wof:placetype":"venue"
},
  "geometry": {"coordinates":[-84.184591,39.819773],"type":"Point"}
}