{
  "type": "Feature",
  "properties": {
    "iso:country":"US",
    "sg:address":"13995 Superior Rd",
    "sg:city":"Cleveland",
    "sg:classifiers":[
        {
            "category":"Building & Trades",
            "subcategory":"Construction",
            "type":"Services"
        }
    ],
    "sg:phone":"+1 216 320 1344",
    "sg:postcode":"44118",
    "sg:province":"OH",
    "sg:tags":[
        "general",
        "contractor"
    ],
    "wof:name":"D & G Construction",
    "wof:placetype":"venue"
},
  "geometry": {"coordinates":[-81.580761,41.519061],"type":"Point"}
}