{
  "type": "Feature",
  "properties": {
    "iso:country":"US",
    "sg:address":"1807 E 28th St",
    "sg:city":"Lorain",
    "sg:classifiers":[
        {
            "category":"Railroad",
            "type":"Transportation"
        }
    ],
    "sg:phone":"+1 440 277 7222",
    "sg:postcode":"44055",
    "sg:province":"OH",
    "sg:tags":[
        "rail"
    ],
    "wof:name":"Lake Terminal Railroad Company",
    "wof:placetype":"venue"
},
  "geometry": {"coordinates":[-82.13228100000001,41.445633],"type":"Point"}
}