{
  "type": "Feature",
  "properties": {
    "addr:full": "1758 Lincoln Ave Cincinnati OH 45212",
    "addr:housenumber": "1758",
    "addr:postcode": "45212",
    "addr:street": "Lincoln Ave",
    "iso:country": "US",
    "sg:address": "1758 Lincoln Ave",
    "sg:city": "Cincinnati",
    "sg:classifiers": [
      {
        "category": "Shopping",
        "subcategory": "Clothing, Apparel, \u0026 Fashions",
        "type": "Retail Goods"
      }
    ],
    "sg:phone": "+1 330 539 6085",
    "sg:postcode": "45212",
    "sg:province": "OH",
    "sg:tags": [
      "alteration"
    ],
    "wof:name": "Gloria's Alterations",
    "wof:placetype": "venue"
  },
  "geometry": {"coordinates":[-84.467221,39.159181],"type":"Point"}
}
