{
  "type": "Feature",
  "properties": {
    "iso:country":"US",
    "sg:address":"3303 Beekman St",
    "sg:city":"Cincinnati",
    "sg:classifiers":[
        {
            "category":"Government",
            "subcategory":"Office",
            "type":"Public Place"
        }
    ],
    "sg:phone":"+1 513 681 7223",
    "sg:postcode":"45225",
    "sg:province":"OH",
    "sg:tags":[
        "conservation"
    ],
    "wof:name":"Recreation Commission",
    "wof:placetype":"venue"
},
  "geometry": {"coordinates":[-84.551379,39.148261],"type":"Point"}
}