{
  "type": "Feature",
  "properties": {
    "iso:country":"US",
    "sg:address":"1429 E Kemper Rd",
    "sg:city":"Cincinnati",
    "sg:classifiers":[
        {
            "category":"Restaurant",
            "type":"Food & Drink"
        }
    ],
    "sg:menulink":"http://www.allmenus.com/oh/sharonville/64430-chuck-e-cheeses/menu/",
    "sg:phone":"+1 513 772 2720",
    "sg:postcode":"45246",
    "sg:province":"OH",
    "sg:tags":[
        "american",
        "pizza"
    ],
    "wof:name":"Chuck E. Cheese's",
    "wof:placetype":"venue"
},
  "geometry": {"coordinates":[-84.448076,39.285212],"type":"Point"}
}