{
  "type": "Feature",
  "properties": {
    "addr:full": "97 S Liberty St Powell OH 43065",
    "addr:housenumber": "97",
    "addr:postcode": "43065",
    "addr:street": "S Liberty St",
    "iso:country": "US",
    "sg:address": "97 S Liberty St",
    "sg:city": "Powell",
    "sg:classifiers": [
      {
        "category": "Social Services",
        "type": "Services"
      }
    ],
    "sg:phone": "+1 614 781 1340",
    "sg:postcode": "43065",
    "sg:province": "OH",
    "sg:tags": [
      "counselor",
      "marriage",
      "family"
    ],
    "wof:name": "Susan M Carson",
    "wof:placetype": "venue"
  },
  "geometry": {"coordinates":[-83.074542,40.153643],"type":"Point"}
}
