{
  "type": "Feature",
  "properties": {
    "iso:country":"US",
    "sg:address":"3322 Morse Rd",
    "sg:city":"Columbus",
    "sg:classifiers":[
        {
            "category":"Freight",
            "type":"Transportation"
        },
        {
            "category":"Real Estate",
            "subcategory":"Real Estate Operator",
            "type":"Services"
        }
    ],
    "sg:phone":"+1 614 471 5777",
    "sg:postcode":"43231",
    "sg:province":"OH",
    "sg:tags":[
        "building",
        "storage",
        "general",
        "commercial",
        "nonresidential"
    ],
    "wof:name":"S & M Rent-A-Space",
    "wof:placetype":"venue"
},
  "geometry": {"coordinates":[-82.929885,40.058451],"type":"Point"}
}