{
  "type": "Feature",
  "properties": {
    "addr:full": "54 E Schaaf Rd Cleveland OH 44131",
    "addr:housenumber": "54",
    "addr:postcode": "44131",
    "addr:street": "E Schaaf Rd",
    "iso:country": "US",
    "sg:address": "54 E Schaaf Rd",
    "sg:city": "Cleveland",
    "sg:classifiers": [
      {
        "category": "Utilities",
        "subcategory": "Refuse",
        "type": "Services"
      },
      {
        "category": "Wholesale",
        "subcategory": "Scrap",
        "type": "Manufacturing \u0026 Wholesale Goods"
      }
    ],
    "sg:phone": "+1 216 661 6102",
    "sg:postcode": "44131",
    "sg:province": "OH",
    "sg:tags": [
      "recycling",
      "center",
      "system"
    ],
    "wof:name": "Rosby Resource Recovery Inc",
    "wof:placetype": "venue"
  },
  "geometry": {"coordinates":[-81.675875,41.420592],"type":"Point"}
}
