{
  "type": "Feature",
  "properties": {
    "addr:full":"3319 Erie Ave Cincinnati OH 45208",
    "addr:housenumber":"3319",
    "addr:postcode":"45208",
    "addr:street":"Erie Ave",
    "iso:country":"US",
    "sg:address":"3319 Erie Ave",
    "sg:city":"Cincinnati",
    "sg:classifiers":[
        {
            "category":"Personal",
            "subcategory":"Beauty Salon",
            "type":"Services"
        }
    ],
    "sg:phone":"+1 513 533 0316",
    "sg:postcode":"45208",
    "sg:province":"OH",
    "wof:name":"Second Floor Salon",
    "wof:placetype":"venue"
},
  "geometry": {"coordinates":[-84.42392599999999,39.141346],"type":"Point"}
}