{
  "type": "Feature",
  "properties": {
    "addr:full": "6603 State Rte 45 Lisbon OH 44432",
    "addr:housenumber": "6603",
    "addr:postcode": "44432",
    "addr:street": "State Rte 45",
    "iso:country": "US",
    "sg:address": "6603 State Rte 45",
    "sg:city": "Lisbon",
    "sg:classifiers": [
      {
        "category": "Shopping",
        "subcategory": "Clothing, Apparel, \u0026 Fashions",
        "type": "Retail Goods"
      }
    ],
    "sg:phone": "+1 330 420 9463",
    "sg:postcode": "44432",
    "sg:province": "OH",
    "sg:tags": [
      "alteration"
    ],
    "wof:name": "Alterations By Clothing Srgns",
    "wof:placetype": "venue"
  },
  "geometry": {"coordinates":[-80.787687,40.804479],"type":"Point"}
}
