{
  "type": "Feature",
  "properties": {
    "iso:country":"US",
    "sg:address":"6603 State Rte 45",
    "sg:city":"Lisbon",
    "sg:classifiers":[
        {
            "category":"Shopping",
            "subcategory":"Clothing, Apparel, & Fashions",
            "type":"Retail Goods"
        }
    ],
    "sg:phone":"+1 330 420 9463",
    "sg:postcode":"44432",
    "sg:province":"OH",
    "sg:tags":[
        "alteration"
    ],
    "wof:name":"Alterations By Clothing Srgns",
    "wof:placetype":"venue"
},
  "geometry": {"coordinates":[-80.78768700000001,40.804479],"type":"Point"}
}