{
  "type": "Feature",
  "properties": {
    "iso:country":"US",
    "sg:address":"5001 Monroe St",
    "sg:city":"Toledo",
    "sg:classifiers":[
        {
            "category":"Shopping",
            "subcategory":"Jewelry",
            "type":"Retail Goods"
        }
    ],
    "sg:phone":"+1 419 471 1803",
    "sg:postcode":"43606",
    "sg:province":"OH",
    "sg:tags":[
        "jeweler"
    ],
    "wof:name":"Gold & Silver Express",
    "wof:placetype":"venue"
},
  "geometry": {"coordinates":[-83.642016,41.697742],"type":"Point"}
}