{
  "type": "Feature",
  "properties": {
    "addr:full":"1147 E Turkeyfoot Lake Rd Akron OH 44312",
    "addr:housenumber":"1147",
    "addr:postcode":"44312",
    "addr:street":"E Turkeyfoot Lake Rd",
    "iso:country":"US",
    "sg:address":"1147 E Turkeyfoot Lake Rd",
    "sg:city":"Akron",
    "sg:classifiers":[
        {
            "category":"Banks & Credit Unions",
            "subcategory":"Investment Brokerage",
            "type":"Services"
        }
    ],
    "sg:phone":"+1 330 896 4343",
    "sg:postcode":"44312",
    "sg:province":"OH",
    "sg:tags":[
        "consultant",
        "planning",
        "financial"
    ],
    "wof:name":"Anderson Anderson Assoc",
    "wof:placetype":"venue"
},
  "geometry": {"coordinates":[-81.48244,40.974468],"type":"Point"}
}