{
  "type": "Feature",
  "properties": {
    "addr:full":"11802 Lorain Ave Cleveland OH 44111",
    "addr:housenumber":"11802",
    "addr:postcode":"44111",
    "addr:street":"Lorain Ave",
    "iso:country":"US",
    "sg:address":"11802 Lorain Ave",
    "sg:city":"Cleveland",
    "sg:classifiers":[
        {
            "category":"Professional",
            "subcategory":"Employment Agencies",
            "type":"Services"
        }
    ],
    "sg:phone":"+1 216 252 9460",
    "sg:postcode":"44111",
    "sg:province":"OH",
    "sg:tags":[
        "opportunity"
    ],
    "wof:name":"Urban Link",
    "wof:placetype":"venue"
},
  "geometry": {"coordinates":[-81.769936,41.461608],"type":"Point"}
}