{
  "type": "Feature",
  "properties": {
    "addr:full": "1829 Frail Rd Lima OH 45806",
    "addr:housenumber": "1829",
    "addr:postcode": "45806",
    "addr:street": "Frail Rd",
    "iso:country": "US",
    "sg:address": "1829 Frail Rd",
    "sg:city": "Lima",
    "sg:classifiers": [
      {
        "category": "Building \u0026 Trades",
        "subcategory": "Construction",
        "type": "Services"
      }
    ],
    "sg:phone": "+1 419 225 3425",
    "sg:postcode": "45806",
    "sg:province": "OH",
    "sg:tags": [
      "house"
    ],
    "wof:name": "Elite Builders",
    "wof:placetype": "venue"
  },
  "geometry": {"coordinates":[-84.139582,40.681008],"type":"Point"}
}
