{
  "type": "Feature",
  "properties": {
    "addr:full": "61 N Cleveland Massillon Rd Akron OH 44333",
    "addr:housenumber": "61",
    "addr:postcode": "44333",
    "addr:street": "N Cleveland Massillon Rd",
    "iso:country": "US",
    "sg:address": "61 N Cleveland Massillon Rd",
    "sg:city": "Akron",
    "sg:phone": "+1 330 666 6758",
    "sg:postcode": "44333",
    "sg:province": "OH",
    "sg:tags": [
      "food",
      "repair",
      "commercial",
      "ma",
      "mfg"
    ],
    "wof:name": "Hobart Sales \u0026 Service",
    "wof:placetype": "venue"
  },
  "geometry": {"coordinates":[-81.637264,41.136766],"type":"Point"}
}
