{
  "type": "Feature",
  "properties": {
    "addr:full": "349 Jefferson St Greenfield OH 45123",
    "addr:housenumber": "349",
    "addr:postcode": "45123",
    "addr:street": "Jefferson St",
    "iso:country": "US",
    "sg:address": "349 Jefferson St",
    "sg:city": "Greenfield",
    "sg:classifiers": [
      {
        "category": "Health Services",
        "subcategory": "Optometrist",
        "type": "Services"
      }
    ],
    "sg:phone": "+1 937 981 3801",
    "sg:postcode": "45123",
    "sg:province": "OH",
    "wof:name": "Michael E Chester Inc",
    "wof:placetype": "venue"
  },
  "geometry": {"coordinates":[-83.384043,39.351429],"type":"Point"}
}
