{
  "type": "Feature",
  "properties": {
    "addr:full": "3748 State Rte 7 Chesapeake OH 45619",
    "addr:housenumber": "3748",
    "addr:postcode": "45619",
    "addr:street": "State Rte 7",
    "iso:country": "US",
    "sg:address": "3748 State Rte 7",
    "sg:city": "Chesapeake",
    "sg:classifiers": [
      {
        "category": "Organizations",
        "subcategory": "Non-profit Organization",
        "type": "Services"
      }
    ],
    "sg:phone": "+1 740 867 4532",
    "sg:postcode": "45619",
    "sg:province": "OH",
    "wof:name": "Chesapeake Community Ctr",
    "wof:placetype": "venue"
  },
  "geometry": {"coordinates":[-82.424758,38.434763],"type":"Point"}
}
