{
  "type": "Feature",
  "properties": {
    "addr:full":"27900 Chagrin Blvd Cleveland OH 44122",
    "addr:housenumber":"27900",
    "addr:postcode":"44122",
    "addr:street":"Chagrin Blvd",
    "iso:country":"US",
    "sg:address":"27900 Chagrin Blvd",
    "sg:city":"Cleveland",
    "sg:classifiers":[
        {
            "category":"Wholesale",
            "subcategory":"Groceries",
            "type":"Manufacturing & Wholesale Goods"
        }
    ],
    "sg:phone":"+1 440 893 9767",
    "sg:postcode":"44122",
    "sg:province":"OH",
    "wof:name":"Riverwood Naturals",
    "wof:placetype":"venue"
},
  "geometry": {"coordinates":[-81.481072,41.462264],"type":"Point"}
}