{
  "type": "Feature",
  "properties": {
    "addr:full": "2727 N Fairfield Rd Dayton OH 45431",
    "addr:housenumber": "2727",
    "addr:postcode": "45431",
    "addr:street": "N Fairfield Rd",
    "iso:country": "US",
    "sg:address": "2727 N Fairfield Rd",
    "sg:city": "Dayton",
    "sg:classifiers": [
      {
        "category": "Shopping",
        "subcategory": "Clothing, Apparel, \u0026 Fashions",
        "type": "Retail Goods"
      }
    ],
    "sg:phone": "+1 937 320 1982",
    "sg:postcode": "45431",
    "sg:province": "OH",
    "wof:name": "Christopher \u0026 Banks",
    "wof:placetype": "venue"
  },
  "geometry": {"coordinates":[-84.052219,39.768912],"type":"Point"}
}
