{
  "type": "Feature",
  "properties": {
    "iso:country":"US",
    "sg:address":"11885 US Hwy 50",
    "sg:city":"Hillsboro",
    "sg:classifiers":[
        {
            "category":"Building & Trades",
            "subcategory":"Electrical",
            "type":"Services"
        }
    ],
    "sg:phone":"+1 937 365 1200",
    "sg:postcode":"45133",
    "sg:province":"OH",
    "sg:tags":[
        "electric",
        "contractor"
    ],
    "wof:name":"D & P Electric Svc",
    "wof:placetype":"venue"
},
  "geometry": {"coordinates":[-83.456782,39.216161],"type":"Point"}
}