{
  "type": "Feature",
  "properties": {
    "iso:country":"US",
    "sg:address":"211 S Court St",
    "sg:city":"Medina",
    "sg:classifiers":[
        {
            "category":"Professional",
            "subcategory":"Lawyer & Legal Services",
            "type":"Services"
        }
    ],
    "sg:phone":"+1 330 725 6082",
    "sg:postcode":"44256",
    "sg:province":"OH",
    "sg:tags":[
        "attorney"
    ],
    "wof:name":"Bruce D Parish",
    "wof:placetype":"venue"
},
  "geometry": {"coordinates":[-81.864068,41.137805],"type":"Point"}
}