{
  "type": "Feature",
  "properties": {
    "iso:country":"US",
    "sg:address":"190 Northfield Rd",
    "sg:city":"Cleveland",
    "sg:classifiers":[
        {
            "category":"Building & Trades",
            "subcategory":"Construction",
            "type":"Services"
        }
    ],
    "sg:phone":"+1 440 786 9100",
    "sg:postcode":"44146",
    "sg:province":"OH",
    "sg:tags":[
        "concrete",
        "restoration",
        "cleaning",
        "repair"
    ],
    "sg:website":"www.naturestonefloors.com",
    "wof:name":"Nature Stone",
    "wof:placetype":"venue"
},
  "geometry": {"coordinates":[-81.52694,41.377045],"type":"Point"}
}