{
  "type": "Feature",
  "properties": {
    "addr:full": "190 Northfield Rd Cleveland OH 44146",
    "addr:housenumber": "190",
    "addr:postcode": "44146",
    "addr:street": "Northfield Rd",
    "iso:country": "US",
    "sg:address": "190 Northfield Rd",
    "sg:city": "Cleveland",
    "sg:classifiers": [
      {
        "category": "Building \u0026 Trades",
        "subcategory": "Construction",
        "type": "Services"
      }
    ],
    "sg:phone": "+1 440 786 9100",
    "sg:postcode": "44146",
    "sg:province": "OH",
    "sg:tags": [
      "concrete",
      "restoration",
      "cleaning",
      "repair"
    ],
    "sg:website": "www.naturestonefloors.com",
    "wof:name": "Nature Stone",
    "wof:placetype": "venue"
  },
  "geometry": {"coordinates":[-81.52694,41.377045],"type":"Point"}
}
