{
  "type": "Feature",
  "properties": {
    "addr:full":"6464 Winton Rd Cincinnati OH 45224",
    "addr:housenumber":"6464",
    "addr:postcode":"45224",
    "addr:street":"Winton Rd",
    "iso:country":"US",
    "sg:address":"6464 Winton Rd",
    "sg:city":"Cincinnati",
    "sg:classifiers":[
        {
            "category":"Autos & Motor Vehicles",
            "subcategory":"Fuel & Gas Station",
            "type":"Retail Goods"
        }
    ],
    "sg:phone":"+1 513 641 1155",
    "sg:postcode":"45224",
    "sg:province":"OH",
    "sg:tags":[
        "oil"
    ],
    "wof:name":"Bp Oil",
    "wof:placetype":"venue"
},
  "geometry": {"coordinates":[-84.52085599999999,39.201429],"type":"Point"}
}