{
  "type": "Feature",
  "properties": {
    "addr:full":"6823 Harrison Ave Cincinnati OH 45247",
    "addr:housenumber":"6823",
    "addr:postcode":"45247",
    "addr:street":"Harrison Ave",
    "iso:country":"US",
    "sg:address":"6823 Harrison Ave",
    "sg:city":"Cincinnati",
    "sg:classifiers":[
        {
            "category":"Building & Trades",
            "subcategory":"Construction",
            "type":"Services"
        }
    ],
    "sg:phone":"+1 513 598 2800",
    "sg:postcode":"45247",
    "sg:province":"OH",
    "sg:tags":[
        "foundation",
        "repair",
        "waterproofing",
        "basement"
    ],
    "sg:website":"www.jbsd-inc.com",
    "wof:name":"Jack Boiman Sons & Daughters",
    "wof:placetype":"venue"
},
  "geometry": {"coordinates":[-84.67153399999999,39.198453],"type":"Point"}
}