{
  "type": "Feature",
  "properties": {
    "iso:country":"US",
    "sg:address":"2630 Alexander Ct",
    "sg:city":"Troy",
    "sg:classifiers":[
        {
            "category":"Organizations",
            "subcategory":"Religious Organization",
            "type":"Services"
        }
    ],
    "sg:phone":"+1 937 339 7285",
    "sg:postcode":"45373",
    "sg:province":"OH",
    "sg:tags":[
        "clergy"
    ],
    "wof:name":"Dorland Loomis",
    "wof:placetype":"venue"
},
  "geometry": {"coordinates":[-84.25197900000001,40.041853],"type":"Point"}
}