{
  "type": "Feature",
  "properties": {
    "addr:full": "1667 S Breiel Blvd Middletown OH 45044",
    "addr:housenumber": "1667",
    "addr:postcode": "45044",
    "addr:street": "S Breiel Blvd",
    "iso:country": "US",
    "sg:address": "1667 S Breiel Blvd",
    "sg:city": "Middletown",
    "sg:classifiers": [
      {
        "category": "Autos \u0026 Motor Vehicles",
        "subcategory": "Fuel \u0026 Gas Station",
        "type": "Retail Goods"
      }
    ],
    "sg:phone": "+1 513 423 8244",
    "sg:postcode": "45044",
    "sg:province": "OH",
    "sg:tags": [
      "convenience",
      "gasoline",
      "store"
    ],
    "wof:name": "Speedway Superamerica LLC",
    "wof:placetype": "venue"
  },
  "geometry": {"coordinates":[-84.355588,39.498938],"type":"Point"}
}
