{
  "type": "Feature",
  "properties": {
    "iso:country":"US",
    "sg:address":"390 S 2nd Ave",
    "sg:city":"Middleport",
    "sg:classifiers":[
        {
            "category":"Shopping",
            "subcategory":"Used Merchandise",
            "type":"Retail Goods"
        }
    ],
    "sg:phone":"+1 740 992 5262",
    "sg:postcode":"45760",
    "sg:province":"OH",
    "wof:name":"Redcoat Antiques",
    "wof:placetype":"venue"
},
  "geometry": {"coordinates":[-82.049977,38.999068],"type":"Point"}
}