{
  "type": "Feature",
  "properties": {
    "iso:country":"US",
    "sg:address":"667 Huston St E",
    "sg:city":"Barberton",
    "sg:classifiers":[
        {
            "category":"Freight",
            "type":"Transportation"
        }
    ],
    "sg:phone":"+1 330 753 1461",
    "sg:postcode":"44203",
    "sg:province":"OH",
    "sg:tags":[
        "operator",
        "local",
        "trucking"
    ],
    "wof:name":"Harris Movers",
    "wof:placetype":"venue"
},
  "geometry": {"coordinates":[-81.579972,41.01808],"type":"Point"}
}