{
  "type": "Feature",
  "properties": {
    "addr:full":"2510 E Sharon Rd Cincinnati OH 45241",
    "addr:housenumber":"2510",
    "addr:postcode":"45241",
    "addr:street":"E Sharon Rd",
    "iso:country":"US",
    "sg:address":"2510 E Sharon Rd",
    "sg:city":"Cincinnati",
    "sg:classifiers":[
        {
            "category":"Manufacturing",
            "subcategory":"Rubber & Plastics",
            "type":"Manufacturing & Wholesale Goods"
        },
        {
            "category":"Utilities",
            "subcategory":"Natural Gas",
            "type":"Services"
        },
        {
            "category":"Communications",
            "subcategory":"Television Station",
            "type":"Services"
        }
    ],
    "sg:phone":"+1 513 771 2590",
    "sg:postcode":"45241",
    "sg:province":"OH",
    "sg:tags":[
        "hose",
        "coupling",
        "tubing-rubber",
        "hydraulic",
        "fitting",
        "cylinders-air"
    ],
    "sg:website":"http://www.ypad.com/business-profile.cfm/state/OH/city/Cincinnati/ppid/14821",
    "wof:name":"Ohio Hydraulics Inc",
    "wof:placetype":"venue"
},
  "geometry": {"coordinates":[-84.43351,39.269581],"type":"Point"}
}