{
  "type": "Feature",
  "properties": {
    "addr:full":"36575 Reading Ave Willoughby OH 44094",
    "addr:postcode":"36575;44094",
    "addr:street":"Reading Ave",
    "iso:country":"US",
    "sg:address":"36575 Reading Ave",
    "sg:city":"Willoughby",
    "sg:classifiers":[
        {
            "category":"Manufacturing",
            "subcategory":"Tools & Machinery",
            "type":"Manufacturing & Wholesale Goods"
        }
    ],
    "sg:phone":"+1 440 951 5934",
    "sg:postcode":"44094",
    "sg:province":"OH",
    "sg:tags":[
        "industrial",
        "mold",
        "mfg"
    ],
    "wof:name":"Faith Tool & Manufacturing",
    "wof:placetype":"venue"
},
  "geometry": {"coordinates":[-81.429509,41.634518],"type":"Point"}
}