{
  "type": "Feature",
  "properties": {
    "addr:full": "5 Willipie St Wapakoneta OH 45895",
    "addr:housenumber": "5",
    "addr:postcode": "45895",
    "addr:street": "Willipie St",
    "iso:country": "US",
    "sg:address": "5 Willipie St",
    "sg:city": "Wapakoneta",
    "sg:classifiers": [
      {
        "category": "Professional",
        "subcategory": "Lawyer \u0026 Legal Services",
        "type": "Services"
      }
    ],
    "sg:phone": "+1 419 738 8171",
    "sg:postcode": "45895",
    "sg:province": "OH",
    "sg:tags": [
      "attorney"
    ],
    "wof:name": "Miller \u0026 Hearn",
    "wof:placetype": "venue"
  },
  "geometry": {"coordinates":[-84.194057,40.570521],"type":"Point"}
}
