{
  "type": "Feature",
  "properties": {
    "iso:country":"US",
    "sg:address":"5 Willipie St",
    "sg:city":"Wapakoneta",
    "sg:classifiers":[
        {
            "category":"Professional",
            "subcategory":"Lawyer & Legal Services",
            "type":"Services"
        }
    ],
    "sg:phone":"+1 419 738 8171",
    "sg:postcode":"45895",
    "sg:province":"OH",
    "sg:tags":[
        "attorney"
    ],
    "wof:name":"Miller & Hearn",
    "wof:placetype":"venue"
},
  "geometry": {"coordinates":[-84.194057,40.570521],"type":"Point"}
}