{
  "type": "Feature",
  "properties": {
    "addr:full": "7397 Main St Cincinnati OH 45244",
    "addr:housenumber": "7397",
    "addr:postcode": "45244",
    "addr:street": "Main St",
    "iso:country": "US",
    "sg:address": "7397 Main St",
    "sg:city": "Cincinnati",
    "sg:classifiers": [
      {
        "category": "Banks \u0026 Credit Unions",
        "subcategory": "Bank",
        "type": "Services"
      }
    ],
    "sg:phone": "+1 513 272 4400",
    "sg:postcode": "45244",
    "sg:province": "OH",
    "sg:tags": [
      "state"
    ],
    "wof:name": "US Bancorp",
    "wof:placetype": "venue"
  },
  "geometry": {"coordinates":[-84.34396,39.124452],"type":"Point"}
}
