{
  "type": "Feature",
  "properties": {
    "addr:full":"4898 Co Rd 223 Clyde OH 43410",
    "addr:housenumber":"4898",
    "addr:postcode":"43410",
    "addr:street":"Co Rd 223",
    "iso:country":"US",
    "sg:address":"4898 Co Rd 223",
    "sg:city":"Clyde",
    "sg:classifiers":[
        {
            "category":"Farming",
            "subcategory":"Farm",
            "type":"Manufacturing & Wholesale Goods"
        }
    ],
    "sg:phone":"+1 419 547 7013",
    "sg:postcode":"43410",
    "sg:province":"OH",
    "sg:tags":[
        "crop",
        "general"
    ],
    "wof:name":"Mark Payne",
    "wof:placetype":"venue"
},
  "geometry": {"coordinates":[-82.943338,41.328566],"type":"Point"}
}