{
  "type": "Feature",
  "properties": {
    "addr:full":"218 Cordero Trl Loveland OH 45140",
    "addr:housenumber":"218",
    "addr:postcode":"45140",
    "addr:street":"Cordero Trl",
    "iso:country":"US",
    "sg:address":"218 Cordero Trl",
    "sg:city":"Loveland",
    "sg:classifiers":[
        {
            "category":"Professional",
            "type":"Services"
        }
    ],
    "sg:phone":"+1 513 677 3897",
    "sg:postcode":"45140",
    "sg:province":"OH",
    "wof:name":"Dominic Servizzi",
    "wof:placetype":"venue"
},
  "geometry": {"coordinates":[-84.28116900000001,39.266043],"type":"Point"}
}