{
  "type": "Feature",
  "properties": {
    "addr:full": "75 E Clinton St Millersburg OH 44654",
    "addr:housenumber": "75",
    "addr:postcode": "44654",
    "addr:street": "E Clinton St",
    "iso:country": "US",
    "sg:address": "75 E Clinton St",
    "sg:city": "Millersburg",
    "sg:classifiers": [
      {
        "category": "Government",
        "subcategory": "Office",
        "type": "Public Place"
      }
    ],
    "sg:phone": "+1 330 674 1896",
    "sg:postcode": "44654",
    "sg:province": "OH",
    "wof:name": "Auditors Office",
    "wof:placetype": "venue"
  },
  "geometry": {"coordinates":[-81.916576,40.555375],"type":"Point"}
}
