{
  "type": "Feature",
  "properties": {
    "addr:full":"8493 Forestview Ave Mentor OH 44060",
    "addr:housenumber":"8493",
    "addr:postcode":"44060",
    "addr:street":"Forestview Ave",
    "iso:country":"US",
    "sg:address":"8493 Forestview Ave",
    "sg:city":"Mentor",
    "sg:classifiers":[
        {
            "category":"Building & Trades",
            "subcategory":"Landscaping Services",
            "type":"Services"
        }
    ],
    "sg:phone":"+1 440 974 0333",
    "sg:postcode":"44060",
    "sg:province":"OH",
    "sg:tags":[
        "tree"
    ],
    "wof:name":"Lake County Tree Svc",
    "wof:placetype":"venue"
},
  "geometry": {"coordinates":[-81.336476,41.663332],"type":"Point"}
}