{
  "type": "Feature",
  "properties": {
    "addr:full":"7777 Montgomery Rd Cincinnati OH 45236",
    "addr:housenumber":"7777",
    "addr:postcode":"45236",
    "addr:street":"Montgomery Rd",
    "iso:country":"US",
    "sg:address":"7777 Montgomery Rd",
    "sg:city":"Cincinnati",
    "sg:classifiers":[
        {
            "category":"Health Services",
            "subcategory":"Chiropractor",
            "type":"Services"
        }
    ],
    "sg:phone":"+1 513 791 2251",
    "sg:postcode":"45236",
    "sg:province":"OH",
    "wof:name":"Family Healing Ctr",
    "wof:placetype":"venue"
},
  "geometry": {"coordinates":[-84.38448200000001,39.197328],"type":"Point"}
}