{
  "type": "Feature",
  "properties": {
    "iso:country":"US",
    "sg:address":"1709 S Raccoon Rd",
    "sg:city":"Youngstown",
    "sg:classifiers":[
        {
            "category":"Restaurant",
            "type":"Food & Drink"
        }
    ],
    "sg:phone":"+1 330 792 0527",
    "sg:postcode":"44515",
    "sg:province":"OH",
    "wof:name":"Mc Donald's",
    "wof:placetype":"venue"
},
  "geometry": {"coordinates":[-80.732263,41.080585],"type":"Point"}
}