{
  "type": "Feature",
  "properties": {
    "addr:full":"1601 Madison Rd Cincinnati OH 45206",
    "addr:housenumber":"1601",
    "addr:postcode":"45206",
    "addr:street":"Madison Rd",
    "iso:country":"US",
    "sg:address":"1601 Madison Rd",
    "sg:city":"Cincinnati",
    "sg:classifiers":[
        {
            "category":"Professional",
            "type":"Services"
        }
    ],
    "sg:phone":"+1 513 861 0021",
    "sg:postcode":"45206",
    "sg:province":"OH",
    "sg:tags":[
        "establishment"
    ],
    "wof:name":"CMRAAB",
    "wof:placetype":"venue"
},
  "geometry": {"coordinates":[-84.47595099999999,39.129615],"type":"Point"}
}