{
  "type": "Feature",
  "properties": {
    "addr:full":"15350 Arcadia St NW Canal Fulton OH 44614",
    "addr:housenumber":"15350",
    "addr:postcode":"44614",
    "addr:street":"Arcadia St Nw",
    "iso:country":"US",
    "sg:address":"15350 Arcadia St NW",
    "sg:city":"Canal Fulton",
    "sg:phone":"+1 330 854 3828",
    "sg:postcode":"44614",
    "sg:province":"OH",
    "sg:tags":[
        "farm",
        "corn"
    ],
    "wof:name":"Thomas Rohr",
    "wof:placetype":"venue"
},
  "geometry": {"coordinates":[-81.636549,40.879287],"type":"Point"}
}