{
  "type": "Feature",
  "properties": {
    "addr:full":"2138 Eagle Ct Cincinnati OH 45237",
    "addr:housenumber":"2138",
    "addr:postcode":"45237",
    "addr:street":"Eagle Ct",
    "iso:country":"US",
    "sg:address":"2138 Eagle Ct",
    "sg:city":"Cincinnati",
    "sg:classifiers":[
        {
            "category":"Manufacturing",
            "subcategory":"Furniture",
            "type":"Manufacturing & Wholesale Goods"
        }
    ],
    "sg:phone":"+1 513 631 1717",
    "sg:postcode":"45237",
    "sg:province":"OH",
    "sg:tags":[
        "household",
        "wood",
        "mfg"
    ],
    "wof:name":"Architectural Effects Inc",
    "wof:placetype":"venue"
},
  "geometry": {"coordinates":[-84.45592000000001,39.183216],"type":"Point"}
}