{
  "type": "Feature",
  "properties": {
    "addr:full":"895 Central Ave Cincinnati OH 45202",
    "addr:housenumber":"895",
    "addr:postcode":"45202",
    "addr:street":"Central Ave",
    "iso:country":"US",
    "sg:address":"895 Central Ave",
    "sg:city":"Cincinnati",
    "sg:classifiers":[
        {
            "category":"Professional",
            "subcategory":"Art Services",
            "type":"Services"
        }
    ],
    "sg:phone":"+1 513 351 3333",
    "sg:postcode":"45202",
    "sg:province":"OH",
    "sg:tags":[
        "graphic",
        "designer"
    ],
    "sg:website":"www.wilkerdesign.com",
    "wof:name":"Wilker Design",
    "wof:placetype":"venue"
},
  "geometry": {"coordinates":[-84.52038400000001,39.103773],"type":"Point"}
}