{
  "type": "Feature",
  "properties": {
    "addr:full":"9291 N Girdle Rd Middlefield OH 44062",
    "addr:housenumber":"9291",
    "addr:postcode":"44062",
    "addr:street":"N Girdle Rd",
    "iso:country":"US",
    "sg:address":"9291 N Girdle Rd",
    "sg:city":"Middlefield",
    "sg:classifiers":[
        {
            "category":"Manufacturing",
            "subcategory":"Wood Products",
            "type":"Manufacturing & Wholesale Goods"
        }
    ],
    "sg:phone":"+1 440 693 4603",
    "sg:postcode":"44062",
    "sg:province":"OH",
    "sg:tags":[
        "pallet",
        "skid",
        "mfg"
    ],
    "wof:name":"Custom Pallet Mfg",
    "wof:placetype":"venue"
},
  "geometry": {"coordinates":[-80.974762,41.463292],"type":"Point"}
}