{
  "type": "Feature",
  "properties": {
    "iso:country":"US",
    "sg:address":"11001 US Hwy 250",
    "sg:city":"Milan",
    "sg:classifiers":[
        {
            "category":"Restaurant",
            "type":"Food & Drink"
        }
    ],
    "sg:phone":"+1 419 499 4360",
    "sg:postcode":"44846",
    "sg:province":"OH",
    "sg:tags":[
        "caterer"
    ],
    "wof:name":"Colonnade Catering",
    "wof:placetype":"venue"
},
  "geometry": {"coordinates":[-82.619838,41.326882],"type":"Point"}
}