{
  "type": "Feature",
  "properties": {
    "addr:full":"20950 Lakeland Blvd Cleveland OH 44119",
    "addr:housenumber":"20950",
    "addr:postcode":"44119",
    "addr:street":"Lakeland Blvd",
    "iso:country":"US",
    "sg:address":"20950 Lakeland Blvd",
    "sg:city":"Cleveland",
    "sg:classifiers":[
        {
            "category":"Autos & Motor Vehicles",
            "subcategory":"Automobile Sales",
            "type":"Retail Goods"
        },
        {
            "category":"Retail",
            "subcategory":"Auto Rental",
            "type":"Services"
        }
    ],
    "sg:phone":"+1 216 531 8810",
    "sg:postcode":"44119",
    "sg:province":"OH",
    "sg:tags":[
        "truck",
        "leasing",
        "car"
    ],
    "sg:website":"http://www.enterprise.com/car_rental/deeplinkmap.do?gpbr=3923&bid=004&cnty=US&arc=YPTRL01&cm_mmc=Yellowpages.com-_-IYP-_-Tradelisting-_-branch",
    "wof:name":"Enterprise Rent-A-Car",
    "wof:placetype":"venue"
},
  "geometry": {"coordinates":[-81.532049,41.584222],"type":"Point"}
}