{
  "type": "Feature",
  "properties": {
    "iso:country":"US",
    "sg:address":"724 Seville Rd",
    "sg:city":"Wadsworth",
    "sg:classifiers":[
        {
            "category":"Manufacturing",
            "subcategory":"Chemicals & Compounds",
            "type":"Manufacturing & Wholesale Goods"
        }
    ],
    "sg:phone":"+1 330 336 7667",
    "sg:postcode":"44281",
    "sg:province":"OH",
    "sg:tags":[
        "lithographing",
        "ink"
    ],
    "wof:name":"Rainbow Inks Inc",
    "wof:placetype":"venue"
},
  "geometry": {"coordinates":[-81.752731,41.010306],"type":"Point"}
}