{
  "type": "Feature",
  "properties": {
    "addr:full":"527 S Main St Englewood OH 45322",
    "addr:housenumber":"527",
    "addr:postcode":"45322",
    "addr:street":"S Main St",
    "iso:country":"US",
    "sg:address":"527 S Main St",
    "sg:city":"Englewood",
    "sg:classifiers":[
        {
            "category":"Restaurant",
            "type":"Food & Drink"
        }
    ],
    "sg:menulink":"http://www.allmenus.com/oh/englewood/233020-lees-famous-recipe-chicken/menu/",
    "sg:phone":"+1 937 836 7905",
    "sg:postcode":"45322",
    "sg:province":"OH",
    "sg:tags":[
        "american"
    ],
    "wof:name":"Lee's Famous Recipe Chicken",
    "wof:placetype":"venue"
},
  "geometry": {"coordinates":[-84.29643,39.870891],"type":"Point"}
}