{
  "type": "Feature",
  "properties": {
    "addr:full":"4245 Mc Cann Rd Salem OH 44460",
    "addr:housenumber":"4245",
    "addr:postcode":"44460",
    "addr:street":"Mc Cann Rd",
    "iso:country":"US",
    "sg:address":"4245 Mc Cann Rd",
    "sg:city":"Salem",
    "sg:classifiers":[
        {
            "category":"Farming",
            "subcategory":"Farm",
            "type":"Manufacturing & Wholesale Goods"
        }
    ],
    "sg:phone":"+1 330 525 7420",
    "sg:postcode":"44460",
    "sg:province":"OH",
    "sg:tags":[
        "crop",
        "general"
    ],
    "wof:name":"Rusty Kiko",
    "wof:placetype":"venue"
},
  "geometry": {"coordinates":[-80.953339,40.83887],"type":"Point"}
}