{
  "type": "Feature",
  "properties": {
    "iso:country":"US",
    "sg:address":"1495 Morse Rd",
    "sg:city":"Columbus",
    "sg:classifiers":[
        {
            "category":"Health Services",
            "subcategory":"Doctor",
            "type":"Services"
        }
    ],
    "sg:phone":"+1 614 268 2122",
    "sg:postcode":"43229",
    "sg:province":"OH",
    "sg:tags":[
        "dentist"
    ],
    "wof:name":"Jack T Foliano Inc",
    "wof:placetype":"venue"
},
  "geometry": {"coordinates":[-82.982511,40.060806],"type":"Point"}
}