{
  "type": "Feature",
  "properties": {
    "addr:full":"7530 Lucerne Dr Cleveland OH 44130",
    "addr:housenumber":"7530",
    "addr:postcode":"44130",
    "addr:street":"Lucerne Dr",
    "iso:country":"US",
    "sg:address":"7530 Lucerne Dr",
    "sg:city":"Cleveland",
    "sg:classifiers":[
        {
            "category":"Professional",
            "subcategory":"Management & Consulting",
            "type":"Services"
        }
    ],
    "sg:phone":"+1 440 243 4729",
    "sg:postcode":"44130",
    "sg:province":"OH",
    "sg:tags":[
        "marketing",
        "consultant"
    ],
    "wof:name":"Superior Marketing Solutions",
    "wof:placetype":"venue"
},
  "geometry": {"coordinates":[-81.816554,41.357313],"type":"Point"}
}