{
  "type": "Feature",
  "properties": {
    "addr:full": "37406 New Lima Rd Rutland OH 45775",
    "addr:housenumber": "37406",
    "addr:postcode": "45775",
    "addr:street": "New Lima Rd",
    "iso:country": "US",
    "sg:address": "37406 New Lima Rd",
    "sg:city": "Rutland",
    "sg:classifiers": [
      {
        "category": "Autos \u0026 Motor Vehicles",
        "subcategory": "Automobile Sales",
        "type": "Retail Goods"
      }
    ],
    "sg:phone": "+1 740 742 2072",
    "sg:postcode": "45775",
    "sg:province": "OH",
    "sg:tags": [
      "car",
      "dealer"
    ],
    "wof:name": "Vance's Auto Sales",
    "wof:placetype": "venue"
  },
  "geometry": {"coordinates":[-82.13462,39.122309],"type":"Point"}
}
