{
  "type": "Feature",
  "properties": {
    "addr:full": "10258 Lorain Ave Cleveland OH 44111",
    "addr:housenumber": "10258",
    "addr:postcode": "44111",
    "addr:street": "Lorain Ave",
    "iso:country": "US",
    "sg:address": "10258 Lorain Ave",
    "sg:city": "Cleveland",
    "sg:classifiers": [
      {
        "category": "Personal",
        "subcategory": "Adult",
        "type": "Services"
      }
    ],
    "sg:phone": "+1 216 252 1313",
    "sg:postcode": "44111",
    "sg:province": "OH",
    "sg:tags": [
      "escort"
    ],
    "wof:name": "Wild Things",
    "wof:placetype": "venue"
  },
  "geometry": {"coordinates":[-81.756071,41.466219],"type":"Point"}
}
