{
  "type": "Feature",
  "properties": {
    "addr:full":"901 Walnut St Hamilton OH 45013",
    "addr:housenumber":"901",
    "addr:postcode":"45013",
    "addr:street":"Walnut St",
    "iso:country":"US",
    "sg:address":"901 Walnut St",
    "sg:city":"Hamilton",
    "sg:classifiers":[
        {
            "category":"Freight",
            "type":"Transportation"
        },
        {
            "category":"Building & Trades",
            "subcategory":"Construction",
            "type":"Services"
        }
    ],
    "sg:phone":"+1 513 896 9222",
    "sg:postcode":"45013",
    "sg:province":"OH",
    "sg:tags":[
        "contractor",
        "dry wall",
        "general"
    ],
    "wof:name":"L & G Contracting",
    "wof:placetype":"venue"
},
  "geometry": {"coordinates":[-84.65473,39.388908],"type":"Point"}
}