{
  "type": "Feature",
  "properties": {
    "iso:country":"US",
    "sg:address":"17621 Detroit Ave",
    "sg:city":"Cleveland",
    "sg:classifiers":[
        {
            "category":"Bars & Pubs",
            "type":"Food & Drink"
        }
    ],
    "sg:phone":"+1 216 228 8874",
    "sg:postcode":"44107",
    "sg:province":"OH",
    "wof:name":"RKC Holdings LLC",
    "wof:placetype":"venue"
},
  "geometry": {"coordinates":[-81.819339,41.484813],"type":"Point"}
}