{
  "type": "Feature",
  "properties": {
    "addr:full": "17621 Detroit Ave Cleveland OH 44107",
    "addr:housenumber": "17621",
    "addr:postcode": "44107",
    "addr:street": "Detroit Ave",
    "iso:country": "US",
    "sg:address": "17621 Detroit Ave",
    "sg:city": "Cleveland",
    "sg:classifiers": [
      {
        "category": "Bars \u0026 Pubs",
        "type": "Food \u0026 Drink"
      }
    ],
    "sg:phone": "+1 216 228 8874",
    "sg:postcode": "44107",
    "sg:province": "OH",
    "wof:name": "RKC Holdings LLC",
    "wof:placetype": "venue"
  },
  "geometry": {"coordinates":[-81.819339,41.484813],"type":"Point"}
}
