{
  "type": "Feature",
  "properties": {
    "iso:country":"US",
    "sg:address":"3406 Ormond Ave",
    "sg:city":"Cincinnati",
    "sg:classifiers":[
        {
            "category":"Restaurant",
            "type":"Food & Drink"
        }
    ],
    "sg:phone":"+1 513 281 8988",
    "sg:postcode":"45220",
    "sg:province":"OH",
    "wof:name":"Uno Chicago Grill",
    "wof:placetype":"venue"
},
  "geometry": {"coordinates":[-84.521376,39.143725],"type":"Point"}
}