{
  "type": "Feature",
  "properties": {
    "iso:country":"US",
    "sg:address":"151 W Staunton Rd",
    "sg:city":"Troy",
    "sg:classifiers":[
        {
            "category":"Communications",
            "subcategory":"Radio Station",
            "type":"Services"
        }
    ],
    "sg:phone":"+1 937 339 8376",
    "sg:postcode":"45373",
    "sg:province":"OH",
    "sg:tags":[
        "broadcast"
    ],
    "wof:name":"W K K I Radio",
    "wof:placetype":"venue"
},
  "geometry": {"coordinates":[-84.200468,40.044249],"type":"Point"}
}