{
  "type": "Feature",
  "properties": {
    "addr:full":"1105 Blois Dr Marion OH 43302",
    "addr:housenumber":"1105",
    "addr:postcode":"43302",
    "addr:street":"Blois Dr",
    "iso:country":"US",
    "sg:address":"1105 Blois Dr",
    "sg:city":"Marion",
    "sg:classifiers":[
        {
            "category":"Building & Trades",
            "subcategory":"Construction",
            "type":"Services"
        }
    ],
    "sg:phone":"+1 740 389 2781",
    "sg:postcode":"43302",
    "sg:province":"OH",
    "sg:tags":[
        "house",
        "general",
        "contractor"
    ],
    "wof:name":"Feustel Contracting & Hm Rmdlg",
    "wof:placetype":"venue"
},
  "geometry": {"coordinates":[-83.096768,40.567401],"type":"Point"}
}