{
  "type": "Feature",
  "properties": {
    "addr:full":"8180 Corporate Park Dr Cincinnati OH 45242",
    "addr:housenumber":"8180",
    "addr:postcode":"45242",
    "addr:street":"Corporate Park Dr",
    "iso:country":"US",
    "sg:address":"8180 Corporate Park Dr",
    "sg:city":"Cincinnati",
    "sg:classifiers":[
        {
            "category":"Professional",
            "subcategory":"Lawyer & Legal Services",
            "type":"Services"
        }
    ],
    "sg:phone":"+1 513 489 7200",
    "sg:postcode":"45242",
    "sg:province":"OH",
    "sg:tags":[
        "attorney",
        "law",
        "personal",
        "real estate",
        "injury"
    ],
    "sg:website":"http://www.glazerlaw.net",
    "wof:name":"Richard H Glazer Co LPA",
    "wof:placetype":"venue"
},
  "geometry": {"coordinates":[-84.340492,39.261504],"type":"Point"}
}