{
  "type": "Feature",
  "properties": {
    "iso:country":"US",
    "sg:address":"1044 Sunwood Ct",
    "sg:city":"Cincinnati",
    "sg:classifiers":[
        {
            "category":"Health Services",
            "subcategory":"Medical Lab",
            "type":"Services"
        }
    ],
    "sg:phone":"+1 513 521 8378",
    "sg:postcode":"45231",
    "sg:province":"OH",
    "sg:tags":[
        "laboratory"
    ],
    "wof:name":"Norman Clinical Lab",
    "wof:placetype":"venue"
},
  "geometry": {"coordinates":[-84.52181,39.244156],"type":"Point"}
}