{
  "type": "Feature",
  "properties": {
    "addr:full": "3858 Montgomery Rd Cincinnati OH 45212",
    "addr:housenumber": "3858",
    "addr:postcode": "45212",
    "addr:street": "Montgomery Rd",
    "iso:country": "US",
    "sg:address": "3858 Montgomery Rd",
    "sg:city": "Cincinnati",
    "sg:classifiers": [
      {
        "category": "Autos \u0026 Motor Vehicles",
        "subcategory": "Auto Supplies",
        "type": "Retail Goods"
      }
    ],
    "sg:phone": "+1 513 631 4703",
    "sg:postcode": "45212",
    "sg:province": "OH",
    "sg:tags": [
      "automobile",
      "part",
      "accessory"
    ],
    "sg:website": "http://www.autozone.com",
    "wof:name": "AutoZone",
    "wof:placetype": "venue"
  },
  "geometry": {"coordinates":[-84.464638,39.149813],"type":"Point"}
}
