{
  "type": "Feature",
  "properties": {
    "addr:full":"2086 Romig Rd Akron OH 44320",
    "addr:housenumber":"2086",
    "addr:postcode":"44320",
    "addr:street":"Romig Rd",
    "iso:country":"US",
    "sg:address":"2086 Romig Rd",
    "sg:city":"Akron",
    "sg:classifiers":[
        {
            "category":"Banks & Credit Unions",
            "subcategory":"Bank",
            "type":"Services"
        }
    ],
    "sg:phone":"+1 330 848 1704",
    "sg:postcode":"44320",
    "sg:province":"OH",
    "sg:tags":[
        "cashing",
        "personal",
        "check",
        "institution"
    ],
    "sg:website":"www.tenaska.com",
    "wof:name":"Advance America",
    "wof:placetype":"venue"
},
  "geometry": {"coordinates":[-81.580755,41.054251],"type":"Point"}
}