{
  "type": "Feature",
  "properties": {
    "addr:full":"739 Slocum St Lancaster OH 43130",
    "addr:housenumber":"739",
    "addr:postcode":"43130",
    "addr:street":"Slocum St",
    "iso:country":"US",
    "sg:address":"739 Slocum St",
    "sg:city":"Lancaster",
    "sg:classifiers":[
        {
            "category":"Shopping",
            "subcategory":"Pharmacy",
            "type":"Retail Goods"
        }
    ],
    "sg:phone":"+1 740 653 2678",
    "sg:postcode":"43130",
    "sg:province":"OH",
    "wof:name":"Columbus Prescription",
    "wof:placetype":"venue"
},
  "geometry": {"coordinates":[-82.612757,39.722371],"type":"Point"}
}