{
  "type": "Feature",
  "properties": {
    "addr:full":"620 Alum Creek Dr Columbus OH 43205",
    "addr:housenumber":"620",
    "addr:postcode":"43205",
    "addr:street":"Alum Creek Dr",
    "iso:country":"US",
    "sg:address":"620 Alum Creek Dr",
    "sg:city":"Columbus",
    "sg:classifiers":[
        {
            "category":"Insurance",
            "subcategory":"Insurance Agent",
            "type":"Services"
        }
    ],
    "sg:phone":"+1 614 884 1800",
    "sg:postcode":"43205",
    "sg:province":"OH",
    "wof:name":"Burns & Assoc",
    "wof:placetype":"venue"
},
  "geometry": {"coordinates":[-82.94445399999999,39.955249],"type":"Point"}
}