{
  "type": "Feature",
  "properties": {
    "addr:full":"1531 Triplett Blvd Akron OH 44306",
    "addr:housenumber":"1531",
    "addr:postcode":"44306",
    "addr:street":"Triplett Blvd",
    "iso:country":"US",
    "sg:address":"1531 Triplett Blvd",
    "sg:city":"Akron",
    "sg:classifiers":[
        {
            "category":"Wholesale",
            "subcategory":"Non-durable Goods",
            "type":"Manufacturing & Wholesale Goods"
        }
    ],
    "sg:phone":"+1 330 733 1680",
    "sg:postcode":"44306",
    "sg:province":"OH",
    "sg:tags":[
        "packaging",
        "print",
        "product",
        "publishes",
        "periodical"
    ],
    "wof:name":"Victor Printing & Publishing",
    "wof:placetype":"venue"
},
  "geometry": {"coordinates":[-81.47073399999999,41.043155],"type":"Point"}
}