{
  "type": "Feature",
  "properties": {
    "addr:full":"486 Graham Rd Cuyahoga Falls OH 44221",
    "addr:housenumber":"486",
    "addr:postcode":"44221",
    "addr:street":"Graham Rd",
    "iso:country":"US",
    "sg:address":"486 Graham Rd",
    "sg:city":"Cuyahoga Falls",
    "sg:classifiers":[
        {
            "category":"Shopping",
            "type":"Retail Goods"
        }
    ],
    "sg:phone":"+1 330 922 4642",
    "sg:postcode":"44221",
    "sg:province":"OH",
    "sg:tags":[
        "cards",
        "sport",
        "baseball",
        "memorabilia"
    ],
    "wof:name":"Stan's Sportscards",
    "wof:placetype":"venue"
},
  "geometry": {"coordinates":[-81.493137,41.158102],"type":"Point"}
}