{
  "type": "Feature",
  "properties": {
    "iso:country":"US",
    "sg:address":"117 S Water St",
    "sg:city":"Kent",
    "sg:classifiers":[
        {
            "category":"Banks & Credit Unions",
            "subcategory":"Investment Brokerage",
            "type":"Services"
        }
    ],
    "sg:phone":"+1 330 677 1914",
    "sg:postcode":"44240",
    "sg:province":"OH",
    "wof:name":"Barrett Financial Group",
    "wof:placetype":"venue"
},
  "geometry": {"coordinates":[-81.358104,41.152881],"type":"Point"}
}