{
  "type": "Feature",
  "properties": {
    "iso:country":"US",
    "sg:address":"8256 W Central Ave",
    "sg:city":"Toledo",
    "sg:classifiers":[
        {
            "category":"Restaurant",
            "type":"Food & Drink"
        }
    ],
    "sg:phone":"+1 419 841 5038",
    "sg:postcode":"43617",
    "sg:province":"OH",
    "sg:tags":[
        "out"
    ],
    "wof:name":"West Central Carryout",
    "wof:placetype":"venue"
},
  "geometry": {"coordinates":[-83.73915100000001,41.673733],"type":"Point"}
}