{
  "type": "Feature",
  "properties": {
    "addr:full": "8256 W Central Ave Toledo OH 43617",
    "addr:housenumber": "8256",
    "addr:postcode": "43617",
    "addr:street": "W Central Ave",
    "iso:country": "US",
    "sg:address": "8256 W Central Ave",
    "sg:city": "Toledo",
    "sg:classifiers": [
      {
        "category": "Restaurant",
        "type": "Food \u0026 Drink"
      }
    ],
    "sg:phone": "+1 419 841 5038",
    "sg:postcode": "43617",
    "sg:province": "OH",
    "sg:tags": [
      "out"
    ],
    "wof:name": "West Central Carryout",
    "wof:placetype": "venue"
  },
  "geometry": {"coordinates":[-83.739151,41.673733],"type":"Point"}
}
