{
  "type": "Feature",
  "properties": {
    "addr:full":"28202 Chardon Rd Wickliffe OH 44092",
    "addr:housenumber":"28202",
    "addr:postcode":"44092",
    "addr:street":"Chardon Rd",
    "iso:country":"US",
    "sg:address":"28202 Chardon Rd",
    "sg:city":"Wickliffe",
    "sg:classifiers":[
        {
            "category":"Food & Beverages",
            "subcategory":"Specialty",
            "type":"Retail Goods"
        }
    ],
    "sg:phone":"+1 440 585 8575",
    "sg:postcode":"44092",
    "sg:province":"OH",
    "sg:tags":[
        "health",
        "vitamin",
        "diet"
    ],
    "wof:name":"Vitality Health Food Shops",
    "wof:placetype":"venue"
},
  "geometry": {"coordinates":[-81.48035900000001,41.583474],"type":"Point"}
}