{
  "type": "Feature",
  "properties": {
    "addr:full":"2853 Southridge Dr Columbus OH 43224",
    "addr:housenumber":"2853",
    "addr:postcode":"43224",
    "addr:street":"Southridge Dr",
    "iso:country":"US",
    "sg:address":"2853 Southridge Dr",
    "sg:city":"Columbus",
    "sg:classifiers":[
        {
            "category":"Organizations",
            "subcategory":"Religious Organization",
            "type":"Services"
        }
    ],
    "sg:phone":"+1 614 475 8543",
    "sg:postcode":"43224",
    "sg:province":"OH",
    "sg:tags":[
        "church"
    ],
    "wof:name":"New Tabernacle Chr-Christ",
    "wof:placetype":"venue"
},
  "geometry": {"coordinates":[-82.940147,40.040497],"type":"Point"}
}