{
  "type": "Feature",
  "properties": {
    "iso:country":"US",
    "sg:address":"635 Barrington Dr",
    "sg:city":"Dayton",
    "sg:classifiers":[
        {
            "category":"Professional",
            "type":"Services"
        }
    ],
    "sg:phone":"+1 937 890 8295",
    "sg:postcode":"45415",
    "sg:province":"OH",
    "wof:name":"April D Mescher",
    "wof:placetype":"venue"
},
  "geometry": {"coordinates":[-84.263628,39.838406],"type":"Point"}
}