{
  "type": "Feature",
  "properties": {
    "iso:country":"US",
    "sg:address":"1811 Hightower Dr",
    "sg:city":"Columbus",
    "sg:classifiers":[
        {
            "category":"Real Estate",
            "subcategory":"Real Estate Agent",
            "type":"Services"
        }
    ],
    "sg:phone":"+1 614 799 9417",
    "sg:postcode":"43235",
    "sg:province":"OH",
    "wof:name":"Siegfried Properties",
    "wof:placetype":"venue"
},
  "geometry": {"coordinates":[-83.06526100000001,40.11302],"type":"Point"}
}