{
  "type": "Feature",
  "properties": {
    "addr:full": "29429 Bowman Rd Coolville OH 45723",
    "addr:housenumber": "29429",
    "addr:postcode": "45723",
    "addr:street": "Bowman Rd",
    "iso:country": "US",
    "sg:address": "29429 Bowman Rd",
    "sg:city": "Coolville",
    "sg:classifiers": [
      {
        "category": "Farming",
        "subcategory": "Livestock Farm",
        "type": "Manufacturing \u0026 Wholesale Goods"
      }
    ],
    "sg:phone": "+1 740 667 3664",
    "sg:postcode": "45723",
    "sg:province": "OH",
    "sg:tags": [
      "beef",
      "feedlot",
      "cattle"
    ],
    "wof:name": "Jeff L Nutter",
    "wof:placetype": "venue"
  },
  "geometry": {"coordinates":[-81.739428,39.216306],"type":"Point"}
}
