{
  "type": "Feature",
  "properties": {
    "addr:full":"107 N Main St Baltimore OH 43105",
    "addr:housenumber":"107",
    "addr:postcode":"43105",
    "addr:street":"N Main St",
    "iso:country":"US",
    "sg:address":"107 N Main St",
    "sg:city":"Baltimore",
    "sg:classifiers":[
        {
            "category":"Building & Trades",
            "subcategory":"Plumbing",
            "type":"Services"
        }
    ],
    "sg:phone":"+1 740 862 2101",
    "sg:postcode":"43105",
    "sg:province":"OH",
    "sg:tags":[
        "mechanical",
        "contractor"
    ],
    "wof:name":"H & A Mechanical Inc",
    "wof:placetype":"venue"
},
  "geometry": {"coordinates":[-82.601418,39.846211],"type":"Point"}
}