{
  "type": "Feature",
  "properties": {
    "addr:full": "1811 White Oaks Rd Marion OH 43302",
    "addr:housenumber": "1811",
    "addr:postcode": "43302",
    "addr:street": "White Oaks Rd",
    "iso:country": "US",
    "sg:address": "1811 White Oaks Rd",
    "sg:city": "Marion",
    "sg:classifiers": [
      {
        "category": "Retail",
        "subcategory": "Auto Repair",
        "type": "Services"
      }
    ],
    "sg:phone": "+1 740 223 7575",
    "sg:postcode": "43302",
    "sg:province": "OH",
    "sg:tags": [
      "repairing",
      "automobile"
    ],
    "wof:name": "Phoenix Motor Svc",
    "wof:placetype": "venue"
  },
  "geometry": {"coordinates":[-83.149091,40.551225],"type":"Point"}
}
