{
  "type": "Feature",
  "properties": {
    "addr:full": "7966 Hills and Dales Rd Massillon OH 44646",
    "addr:housenumber": "7966",
    "addr:postcode": "44646",
    "addr:street": "Hills And Dales Rd",
    "iso:country": "US",
    "sg:address": "7966 Hills and Dales Rd",
    "sg:city": "Massillon",
    "sg:classifiers": [
      {
        "category": "Autos \u0026 Motor Vehicles",
        "subcategory": "Automobile Sales",
        "type": "Retail Goods"
      }
    ],
    "sg:phone": "+1 800 370 6259",
    "sg:postcode": "44646",
    "sg:province": "OH",
    "sg:tags": [
      "car"
    ],
    "sg:website": "progressivejeep.com/",
    "wof:name": "Progressive Chrysler Jeep Dodge",
    "wof:placetype": "venue"
  },
  "geometry": {"coordinates":[-81.494728,40.82359],"type":"Point"}
}
