{
  "type": "Feature",
  "properties": {
    "iso:country":"US",
    "sg:address":"7966 Hills and Dales Rd",
    "sg:city":"Massillon",
    "sg:classifiers":[
        {
            "category":"Autos & Motor Vehicles",
            "subcategory":"Automobile Sales",
            "type":"Retail Goods"
        }
    ],
    "sg:phone":"+1 800 370 6259",
    "sg:postcode":"44646",
    "sg:province":"OH",
    "sg:tags":[
        "car"
    ],
    "sg:website":"progressivejeep.com/",
    "wof:name":"Progressive Chrysler Jeep Dodge",
    "wof:placetype":"venue"
},
  "geometry": {"coordinates":[-81.49472799999999,40.82359],"type":"Point"}
}