{
  "type": "Feature",
  "properties": {
    "addr:full": "186 Mill St Athens OH 45701",
    "addr:housenumber": "186",
    "addr:postcode": "45701",
    "addr:street": "Mill St",
    "iso:country": "US",
    "sg:address": "186 Mill St",
    "sg:city": "Athens",
    "sg:classifiers": [
      {
        "category": "Home \u0026 Garden",
        "subcategory": "Hardware",
        "type": "Retail Goods"
      }
    ],
    "sg:phone": "+1 740 594 0524",
    "sg:postcode": "45701",
    "sg:province": "OH",
    "wof:name": "True Blue Clothing",
    "wof:placetype": "venue"
  },
  "geometry": {"coordinates":[-82.092311,39.329503],"type":"Point"}
}
