{
  "type": "Feature",
  "properties": {
    "addr:full":"1884 W Main St Troy OH 45373",
    "addr:housenumber":"1884",
    "addr:postcode":"45373",
    "addr:street":"W Main St",
    "iso:country":"US",
    "sg:address":"1884 W Main St",
    "sg:city":"Troy",
    "sg:classifiers":[
        {
            "category":"Home & Garden",
            "subcategory":"Building Materials",
            "type":"Retail Goods"
        }
    ],
    "sg:phone":"+1 937 335 2173",
    "sg:postcode":"45373",
    "sg:province":"OH",
    "sg:tags":[
        "paint",
        "floor",
        "covering"
    ],
    "wof:name":"Sherwin-Williams Paints",
    "wof:placetype":"venue"
},
  "geometry": {"coordinates":[-84.240072,40.055549],"type":"Point"}
}