{
  "type": "Feature",
  "properties": {
    "addr:full": "60 High St Mechanicsburg OH 43044",
    "addr:housenumber": "60",
    "addr:postcode": "43044",
    "addr:street": "High St",
    "iso:country": "US",
    "sg:address": "60 High St",
    "sg:city": "Mechanicsburg",
    "sg:classifiers": [
      {
        "category": "Education",
        "subcategory": "School",
        "type": "Public Place"
      }
    ],
    "sg:phone": "+1 937 834 2497",
    "sg:postcode": "43044",
    "sg:province": "OH",
    "wof:name": "Mechanicsburg High School",
    "wof:placetype": "venue"
  },
  "geometry": {"coordinates":[-83.554535,40.078062],"type":"Point"}
}
