{
  "type": "Feature",
  "properties": {
    "iso:country":"US",
    "sg:address":"10 Chelsea Ct",
    "sg:city":"Cleveland",
    "sg:classifiers":[
        {
            "category":"Banks & Credit Unions",
            "subcategory":"Financial Services",
            "type":"Services"
        }
    ],
    "sg:phone":"+1 216 292 6464",
    "sg:postcode":"44122",
    "sg:province":"OH",
    "sg:tags":[
        "trust",
        "management"
    ],
    "wof:name":"Mandell Family Partnership",
    "wof:placetype":"venue"
},
  "geometry": {"coordinates":[-81.49685100000001,41.494691],"type":"Point"}
}