{
  "type": "Feature",
  "properties": {
    "iso:country":"US",
    "sg:address":"16707 Detroit Ave",
    "sg:city":"Lakewood",
    "sg:classifiers":[
        {
            "category":"Shopping",
            "subcategory":"Computers & Home Electronics",
            "type":"Retail Goods"
        }
    ],
    "sg:phone":"+1 216 221 9234",
    "sg:postcode":"44107",
    "sg:province":"OH",
    "wof:name":"Game Crazy",
    "wof:placetype":"venue"
},
  "geometry": {"coordinates":[-81.81373000000001,41.485249],"type":"Point"}
}