{
  "type": "Feature",
  "properties": {
    "addr:full":"12551 Kinsman Rd Burton OH 44021",
    "addr:housenumber":"12551",
    "addr:postcode":"44021",
    "addr:street":"Kinsman Rd",
    "iso:country":"US",
    "sg:address":"12551 Kinsman Rd",
    "sg:city":"Burton",
    "sg:classifiers":[
        {
            "category":"Building & Trades",
            "subcategory":"Construction",
            "type":"Services"
        }
    ],
    "sg:phone":"+1 440 834 4629",
    "sg:postcode":"44021",
    "sg:province":"OH",
    "sg:tags":[
        "painter"
    ],
    "wof:name":"J P Painting & Son",
    "wof:placetype":"venue"
},
  "geometry": {"coordinates":[-81.188444,41.470701],"type":"Point"}
}