{
  "type": "Feature",
  "properties": {
    "addr:full": "1545 Alum Creek Dr Columbus OH 43209",
    "addr:housenumber": "1545",
    "addr:postcode": "43209",
    "addr:street": "Alum Creek Dr",
    "iso:country": "US",
    "sg:address": "1545 Alum Creek Dr",
    "sg:city": "Columbus",
    "sg:classifiers": [
      {
        "category": "Organizations",
        "subcategory": "Labor Organization",
        "type": "Services"
      }
    ],
    "sg:phone": "+1 614 252 2898",
    "sg:postcode": "43209",
    "sg:province": "OH",
    "wof:name": "AFSCME",
    "wof:placetype": "venue"
  },
  "geometry": {"coordinates":[-82.94367,39.940973],"type":"Point"}
}
