{
  "type": "Feature",
  "properties": {
    "addr:full": "480 E Columbus St Pickerington OH 43147",
    "addr:housenumber": "480",
    "addr:postcode": "43147",
    "addr:street": "E Columbus St",
    "iso:country": "US",
    "sg:address": "480 E Columbus St",
    "sg:city": "Pickerington",
    "sg:classifiers": [
      {
        "category": "Building \u0026 Trades",
        "subcategory": "Construction",
        "type": "Services"
      }
    ],
    "sg:phone": "+1 614 833 3935",
    "sg:postcode": "43147",
    "sg:province": "OH",
    "sg:tags": [
      "house"
    ],
    "wof:name": "Joe Brake Builders",
    "wof:placetype": "venue"
  },
  "geometry": {"coordinates":[-82.740549,39.883412],"type":"Point"}
}
