{
  "type": "Feature",
  "properties": {
    "addr:full":"12613 Bellaire Rd Cleveland OH 44135",
    "addr:housenumber":"12613",
    "addr:postcode":"44135",
    "addr:street":"Bellaire Rd",
    "iso:country":"US",
    "sg:address":"12613 Bellaire Rd",
    "sg:city":"Cleveland",
    "sg:classifiers":[
        {
            "category":"Organizations",
            "subcategory":"Religious Organization",
            "type":"Services"
        }
    ],
    "sg:phone":"+1 216 671 0433",
    "sg:postcode":"44135",
    "sg:province":"OH",
    "sg:tags":[
        "church"
    ],
    "wof:name":"City Of Truth Church",
    "wof:placetype":"venue"
},
  "geometry": {"coordinates":[-81.776662,41.439699],"type":"Point"}
}