{
  "type": "Feature",
  "properties": {
    "addr:full": "1991 Crocker Rd Cleveland OH 44145",
    "addr:housenumber": "1991",
    "addr:postcode": "44145",
    "addr:street": "Crocker Rd",
    "iso:country": "US",
    "sg:address": "1991 Crocker Rd",
    "sg:city": "Cleveland",
    "sg:classifiers": [
      {
        "category": "Professional",
        "subcategory": "Lawyer \u0026 Legal Services",
        "type": "Services"
      }
    ],
    "sg:phone": "+1 440 835 0600",
    "sg:postcode": "44145",
    "sg:province": "OH",
    "sg:tags": [
      "attorney"
    ],
    "sg:website": "www.healthlaw.com",
    "wof:name": "Waldheger Coyne Co",
    "wof:placetype": "venue"
  },
  "geometry": {"coordinates":[-81.950408,41.460615],"type":"Point"}
}
