{
  "type": "Feature",
  "properties": {
    "iso:country":"US",
    "sg:address":"125 Lincoln Way W",
    "sg:city":"Massillon",
    "sg:classifiers":[
        {
            "category":"Shopping",
            "subcategory":"Clothing, Apparel, & Fashions",
            "type":"Retail Goods"
        }
    ],
    "sg:phone":"+1 330 833 4303",
    "sg:postcode":"44647",
    "sg:province":"OH",
    "sg:tags":[
        "ready",
        "furnishing"
    ],
    "wof:name":"Howard's Tiger Rags Apparel",
    "wof:placetype":"venue"
},
  "geometry": {"coordinates":[-81.524722,40.79594],"type":"Point"}
}