{
  "type": "Feature",
  "properties": {
    "iso:country":"US",
    "sg:address":"4824 S Prospect St",
    "sg:city":"Ravenna",
    "sg:classifiers":[
        {
            "category":"Retail",
            "subcategory":"Auto Repair",
            "type":"Services"
        }
    ],
    "sg:phone":"+1 330 325 1770",
    "sg:postcode":"44266",
    "sg:province":"OH",
    "sg:tags":[
        "automobile",
        "lubrication"
    ],
    "wof:name":"Repairthatglassrapid Oil&Lube",
    "wof:placetype":"venue"
},
  "geometry": {"coordinates":[-81.242069,41.119932],"type":"Point"}
}