{
  "type": "Feature",
  "properties": {
    "iso:country":"US",
    "sg:address":"3347 Glencairn Rd",
    "sg:city":"Cleveland",
    "sg:classifiers":[
        {
            "category":"Shopping",
            "type":"Retail Goods"
        }
    ],
    "sg:phone":"+1 216 751 8873",
    "sg:postcode":"44122",
    "sg:province":"OH",
    "sg:tags":[
        "merchandise"
    ],
    "wof:name":"Kristie Leu",
    "wof:placetype":"venue"
},
  "geometry": {"coordinates":[-81.55556199999999,41.470853],"type":"Point"}
}