{
  "type": "Feature",
  "properties": {
    "addr:full": "18759 Indian Hollow Rd Grafton OH 44044",
    "addr:housenumber": "18759",
    "addr:postcode": "44044",
    "addr:street": "Indian Hollow Rd",
    "iso:country": "US",
    "sg:address": "18759 Indian Hollow Rd",
    "sg:city": "Grafton",
    "sg:phone": "+1 440 355 6682",
    "sg:postcode": "44044",
    "sg:province": "OH",
    "sg:tags": [
      "hog",
      "wheat",
      "farm",
      "corn",
      "soybean",
      "or",
      "feedlot"
    ],
    "wof:name": "Brian Duplaga",
    "wof:placetype": "venue"
  },
  "geometry": {"coordinates":[-82.094919,41.210579],"type":"Point"}
}
