{
  "type": "Feature",
  "properties": {
    "addr:full": "3325 Cricket Dr Youngstown OH 44511",
    "addr:housenumber": "3325",
    "addr:postcode": "44511",
    "addr:street": "Cricket Dr",
    "iso:country": "US",
    "sg:address": "3325 Cricket Dr",
    "sg:city": "Youngstown",
    "sg:classifiers": [
      {
        "category": "Organizations",
        "subcategory": "Community Association",
        "type": "Services"
      }
    ],
    "sg:phone": "+1 330 799 4567",
    "sg:postcode": "44511",
    "sg:province": "OH",
    "wof:name": "First Catholc Slovak Union U S",
    "wof:placetype": "venue"
  },
  "geometry": {"coordinates":[-80.68872,41.068095],"type":"Point"}
}
