{
  "type": "Feature",
  "properties": {
    "addr:full":"3840 Gordon Dr Cincinnati OH 45245",
    "addr:housenumber":"3840",
    "addr:postcode":"45245",
    "addr:street":"Gordon Dr",
    "iso:country":"US",
    "sg:address":"3840 Gordon Dr",
    "sg:city":"Cincinnati",
    "sg:classifiers":[
        {
            "category":"Retail",
            "subcategory":"Repair Shop",
            "type":"Services"
        }
    ],
    "sg:phone":"+1 513 752 6129",
    "sg:postcode":"45245",
    "sg:province":"OH",
    "sg:tags":[
        "reupholstery",
        "furniture"
    ],
    "wof:name":"Taylor Upholstering Inc",
    "wof:placetype":"venue"
},
  "geometry": {"coordinates":[-84.275597,39.075001],"type":"Point"}
}