{
  "type": "Feature",
  "properties": {
    "addr:full":"14945 Sandusky Dr SW Dundee OH 44624",
    "addr:housenumber":"14945",
    "addr:postcode":"44624",
    "addr:street":"Sandusky Dr Sw",
    "iso:country":"US",
    "sg:address":"14945 Sandusky Dr SW",
    "sg:city":"Dundee",
    "sg:classifiers":[
        {
            "category":"Retail",
            "subcategory":"Auto Repair",
            "type":"Services"
        }
    ],
    "sg:phone":"+1 330 359 5960",
    "sg:postcode":"44624",
    "sg:province":"OH",
    "sg:tags":[
        "body",
        "automobile",
        "painting"
    ],
    "wof:name":"B & M Body Shop Inc",
    "wof:placetype":"venue"
},
  "geometry": {"coordinates":[-81.640152,40.659904],"type":"Point"}
}