{
  "type": "Feature",
  "properties": {
    "iso:country":"US",
    "sg:address":"1533 Rockwell Dr",
    "sg:city":"Xenia",
    "sg:classifiers":[
        {
            "category":"Building & Trades",
            "subcategory":"Construction",
            "type":"Services"
        }
    ],
    "sg:phone":"+1 937 376 4881",
    "sg:postcode":"45385",
    "sg:province":"OH",
    "sg:tags":[
        "contractor"
    ],
    "wof:name":"Xenia Roofing & Siding",
    "wof:placetype":"venue"
},
  "geometry": {"coordinates":[-83.956619,39.686016],"type":"Point"}
}