{
  "type": "Feature",
  "properties": {
    "iso:country":"US",
    "sg:address":"485 Rocky Fork Blvd",
    "sg:city":"Columbus",
    "sg:classifiers":[
        {
            "category":"Social Services",
            "subcategory":"Child Care",
            "type":"Services"
        }
    ],
    "sg:phone":"+1 614 471 9272",
    "sg:postcode":"43230",
    "sg:province":"OH",
    "sg:tags":[
        "day"
    ],
    "wof:name":"La Petite Academy 508",
    "wof:placetype":"venue"
},
  "geometry": {"coordinates":[-82.866632,40.01342],"type":"Point"}
}