{
  "type": "Feature",
  "properties": {
    "addr:full": "3655 Wales Ave NW Massillon OH 44646",
    "addr:housenumber": "3655",
    "addr:postcode": "44646",
    "addr:street": "Wales Ave Nw",
    "iso:country": "US",
    "sg:address": "3655 Wales Ave NW",
    "sg:city": "Massillon",
    "sg:classifiers": [
      {
        "category": "Retail",
        "subcategory": "Funeral Services",
        "type": "Services"
      }
    ],
    "sg:phone": "+1 330 832 1349",
    "sg:postcode": "44646",
    "sg:province": "OH",
    "sg:tags": [
      "cemetery"
    ],
    "wof:name": "Rose Hill Memorial Gardens \u0026 Mausoleum",
    "wof:placetype": "venue"
  },
  "geometry": {"coordinates":[-81.502403,40.834599],"type":"Point"}
}
