{
  "type": "Feature",
  "properties": {
    "addr:full": "115 E Main St Coldwater OH 45828",
    "addr:housenumber": "115",
    "addr:postcode": "45828",
    "addr:street": "E Main St",
    "iso:country": "US",
    "sg:address": "115 E Main St",
    "sg:city": "Coldwater",
    "sg:classifiers": [
      {
        "category": "Building \u0026 Trades",
        "subcategory": "Plumbing",
        "type": "Services"
      }
    ],
    "sg:phone": "+1 419 678 2812",
    "sg:postcode": "45828",
    "sg:province": "OH",
    "sg:tags": [
      "plumbing",
      "contractor"
    ],
    "wof:name": "Rish Plumbing Inc",
    "wof:placetype": "venue"
  },
  "geometry": {"coordinates":[-84.628602,40.479692],"type":"Point"}
}
