{
  "type": "Feature",
  "properties": {
    "addr:full":"3997 Penry Rd Radnor OH 43066",
    "addr:housenumber":"3997",
    "addr:postcode":"43066",
    "addr:street":"Penry Rd",
    "iso:country":"US",
    "sg:address":"3997 Penry Rd",
    "sg:city":"Radnor",
    "sg:phone":"+1 740 595 3451",
    "sg:postcode":"43066",
    "sg:province":"OH",
    "sg:tags":[
        "farm",
        "corn",
        "soybean"
    ],
    "wof:name":"Charles Lehner",
    "wof:placetype":"venue"
},
  "geometry": {"coordinates":[-83.12585900000001,40.366764],"type":"Point"}
}