{
  "type": "Feature",
  "properties": {
    "iso:country":"US",
    "sg:address":"26210 Emery Rd",
    "sg:city":"Cleveland",
    "sg:classifiers":[
        {
            "category":"Autos & Motor Vehicles",
            "subcategory":"Automobile Sales",
            "type":"Retail Goods"
        }
    ],
    "sg:phone":"+1 216 464 3223",
    "sg:postcode":"44128",
    "sg:province":"OH",
    "sg:tags":[
        "car",
        "dealer"
    ],
    "wof:name":"Euro Lease",
    "wof:placetype":"venue"
},
  "geometry": {"coordinates":[-81.49257799999999,41.435003],"type":"Point"}
}