{
  "type": "Feature",
  "properties": {
    "addr:full": "920 Burr Ave Columbus OH 43212",
    "addr:housenumber": "920",
    "addr:postcode": "43212",
    "addr:street": "Burr Ave",
    "iso:country": "US",
    "sg:address": "920 Burr Ave",
    "sg:city": "Columbus",
    "sg:classifiers": [
      {
        "category": "Retail",
        "subcategory": "Laundry \u0026 Dry Cleaning",
        "type": "Services"
      }
    ],
    "sg:phone": "+1 614 338 8098",
    "sg:postcode": "43212",
    "sg:province": "OH",
    "sg:tags": [
      "linen",
      "supply"
    ],
    "wof:name": "Ameri Pride Svc",
    "wof:placetype": "venue"
  },
  "geometry": {"coordinates":[-83.027147,39.976697],"type":"Point"}
}
