{
  "type": "Feature",
  "properties": {
    "addr:full": "61 Railroad St Canfield OH 44406",
    "addr:housenumber": "61",
    "addr:postcode": "44406",
    "addr:street": "Railroad St",
    "iso:country": "US",
    "sg:address": "61 Railroad St",
    "sg:city": "Canfield",
    "sg:classifiers": [
      {
        "category": "Freight",
        "type": "Transportation"
      }
    ],
    "sg:phone": "+1 330 533 9841",
    "sg:postcode": "44406",
    "sg:province": "OH",
    "sg:tags": [
      "truck",
      "broker"
    ],
    "wof:name": "Dart Services Inc",
    "wof:placetype": "venue"
  },
  "geometry": {"coordinates":[-80.77175,41.021793],"type":"Point"}
}
