{
  "type": "Feature",
  "properties": {
    "addr:full":"7742 Erastus Durbin Rd Celina OH 45822",
    "addr:postcode":"7742;45822",
    "addr:street":"Durbin Rd",
    "iso:country":"US",
    "sg:address":"7742 Erastus Durbin Rd",
    "sg:city":"Celina",
    "sg:classifiers":[
        {
            "category":"Farming",
            "subcategory":"Farm",
            "type":"Manufacturing & Wholesale Goods"
        }
    ],
    "sg:phone":"+1 419 586 7267",
    "sg:postcode":"45822",
    "sg:province":"OH",
    "sg:tags":[
        "crop",
        "general"
    ],
    "wof:name":"Stoner Brothers",
    "wof:placetype":"venue"
},
  "geometry": {"coordinates":[-84.70817700000001,40.574584],"type":"Point"}
}