{
  "type": "Feature",
  "properties": {
    "addr:full":"4788 Flatrock Trl Payne OH 45880",
    "addr:housenumber":"4788",
    "addr:postcode":"45880",
    "addr:street":"Flatrock Trl",
    "iso:country":"US",
    "sg:address":"4788 Flatrock Trl",
    "sg:city":"Payne",
    "sg:phone":"+1 419 263 2264",
    "sg:postcode":"45880",
    "sg:province":"OH",
    "sg:tags":[
        "farm",
        "soybean"
    ],
    "wof:name":"Allen Harp",
    "wof:placetype":"venue"
},
  "geometry": {"coordinates":[-84.730521,41.067164],"type":"Point"}
}