{
  "type": "Feature",
  "properties": {
    "addr:full":"3714 Columbus Ave Sandusky OH 44870",
    "addr:housenumber":"3714",
    "addr:postcode":"44870",
    "addr:street":"Columbus Ave",
    "iso:country":"US",
    "sg:address":"3714 Columbus Ave",
    "sg:city":"Sandusky",
    "sg:classifiers":[
        {
            "category":"Restaurant",
            "type":"Food & Drink"
        }
    ],
    "sg:phone":"+1 419 626 6608",
    "sg:postcode":"44870",
    "sg:province":"OH",
    "sg:tags":[
        "eating"
    ],
    "wof:name":"Pizza House",
    "wof:placetype":"venue"
},
  "geometry": {"coordinates":[-82.686781,41.414228],"type":"Point"}
}