{
  "type": "Feature",
  "properties": {
    "iso:country":"US",
    "sg:address":"131 N Columbus St",
    "sg:city":"Lancaster",
    "sg:classifiers":[
        {
            "category":"Retail",
            "subcategory":"Portrait Studio",
            "type":"Services"
        }
    ],
    "sg:phone":"+1 740 689 1052",
    "sg:postcode":"43130",
    "sg:province":"OH",
    "sg:tags":[
        "photographer"
    ],
    "wof:name":"Scrapbookers Haven",
    "wof:placetype":"venue"
},
  "geometry": {"coordinates":[-82.604642,39.71407],"type":"Point"}
}