{
  "type": "Feature",
  "properties": {
    "addr:full": "1171 W 3rd Ave Columbus OH 43212",
    "addr:housenumber": "1171",
    "addr:postcode": "43212",
    "addr:street": "W 3Rd Ave",
    "iso:country": "US",
    "sg:address": "1171 W 3rd Ave",
    "sg:city": "Columbus",
    "sg:classifiers": [
      {
        "category": "Arts \u0026 Performance",
        "subcategory": "Theater",
        "type": "Entertainment"
      }
    ],
    "sg:phone": "+1 614 299 3800",
    "sg:postcode": "43212",
    "sg:province": "OH",
    "sg:tags": [
      "entertainer"
    ],
    "wof:name": "Danella Inc",
    "wof:placetype": "venue"
  },
  "geometry": {"coordinates":[-83.037101,39.984778],"type":"Point"}
}
