{
  "type": "Feature",
  "properties": {
    "iso:country":"US",
    "sg:address":"1171 W 3rd Ave",
    "sg:city":"Columbus",
    "sg:classifiers":[
        {
            "category":"Arts & Performance",
            "subcategory":"Theater",
            "type":"Entertainment"
        }
    ],
    "sg:phone":"+1 614 299 3800",
    "sg:postcode":"43212",
    "sg:province":"OH",
    "sg:tags":[
        "entertainer"
    ],
    "wof:name":"Danella Inc",
    "wof:placetype":"venue"
},
  "geometry": {"coordinates":[-83.03710100000001,39.984778],"type":"Point"}
}