{
  "type": "Feature",
  "properties": {
    "iso:country":"US",
    "sg:address":"5261 Dolloff Rd",
    "sg:city":"Cleveland",
    "sg:classifiers":[
        {
            "category":"Building & Trades",
            "subcategory":"Construction",
            "type":"Services"
        }
    ],
    "sg:phone":"+1 216 631 8385",
    "sg:postcode":"44127",
    "sg:province":"OH",
    "sg:tags":[
        "painter"
    ],
    "wof:name":"S & S Painting",
    "wof:placetype":"venue"
},
  "geometry": {"coordinates":[-81.65445800000001,41.468771],"type":"Point"}
}