{
  "type": "Feature",
  "properties": {
    "addr:full": "5261 Dolloff Rd Cleveland OH 44127",
    "addr:postcode": "5261;44127",
    "addr:street": "Dolloff Rd",
    "iso:country": "US",
    "sg:address": "5261 Dolloff Rd",
    "sg:city": "Cleveland",
    "sg:classifiers": [
      {
        "category": "Building \u0026 Trades",
        "subcategory": "Construction",
        "type": "Services"
      }
    ],
    "sg:phone": "+1 216 631 8385",
    "sg:postcode": "44127",
    "sg:province": "OH",
    "sg:tags": [
      "painter"
    ],
    "wof:name": "S \u0026 S Painting",
    "wof:placetype": "venue"
  },
  "geometry": {"coordinates":[-81.654458,41.468771],"type":"Point"}
}
