{
  "type": "Feature",
  "properties": {
    "addr:full":"7507 Exchange Rd Cleveland OH 44125",
    "addr:housenumber":"7507",
    "addr:postcode":"44125",
    "addr:street":"Exchange Rd",
    "iso:country":"US",
    "sg:address":"7507 Exchange Rd",
    "sg:city":"Cleveland",
    "sg:classifiers":[
        {
            "category":"Manufacturing",
            "subcategory":"Tools & Machinery",
            "type":"Manufacturing & Wholesale Goods"
        }
    ],
    "sg:phone":"+1 216 524 1797",
    "sg:postcode":"44125",
    "sg:province":"OH",
    "sg:tags":[
        "die",
        "manufacturer"
    ],
    "wof:name":"Machine Tooling Inc",
    "wof:placetype":"venue"
},
  "geometry": {"coordinates":[-81.62939299999999,41.407935],"type":"Point"}
}