{
  "type": "Feature",
  "properties": {
    "iso:country":"US",
    "sg:address":"4863 Hills and Dales Rd NW",
    "sg:city":"Canton",
    "sg:classifiers":[
        {
            "category":"Education",
            "subcategory":"Dance Studio",
            "type":"Public Place"
        }
    ],
    "sg:phone":"+1 330 477 9046",
    "sg:postcode":"44708",
    "sg:province":"OH",
    "sg:tags":[
        "instruction",
        "dancing"
    ],
    "wof:name":"Colleen's School Of Dance",
    "wof:placetype":"venue"
},
  "geometry": {"coordinates":[-81.436373,40.833398],"type":"Point"}
}