{
  "type": "Feature",
  "properties": {
    "iso:country":"US",
    "sg:address":"39700 Twp Rd 83",
    "sg:city":"Warsaw",
    "sg:classifiers":[
        {
            "category":"Building & Trades",
            "subcategory":"Construction",
            "type":"Services"
        }
    ],
    "sg:phone":"+1 740 824 3810",
    "sg:postcode":"43844",
    "sg:province":"OH",
    "sg:tags":[
        "carpentry",
        "contractor"
    ],
    "wof:name":"Grashel The",
    "wof:placetype":"venue"
},
  "geometry": {"coordinates":[-82.016787,40.312327],"type":"Point"}
}