{
  "type": "Feature",
  "properties": {
    "iso:country":"US",
    "sg:address":"4488 Glengarry Dr",
    "sg:city":"Dayton",
    "sg:classifiers":[
        {
            "category":"Restaurant",
            "type":"Food & Drink"
        }
    ],
    "sg:menulink":"http://www.allmenus.com/oh/beavercreek/105536-bds-mongolian-bbq/menu/",
    "sg:phone":"+1 937 427 1900",
    "sg:postcode":"45440",
    "sg:province":"OH",
    "sg:tags":[
        "mongolian",
        "asian"
    ],
    "wof:name":"Bd's Mongolian BBQ",
    "wof:placetype":"venue"
},
  "geometry": {"coordinates":[-84.10154799999999,39.69393],"type":"Point"}
}