{
  "type": "Feature",
  "properties": {
    "iso:country":"US",
    "sg:address":"2760 Poplar Ridge Rd",
    "sg:city":"West Union",
    "sg:classifiers":[
        {
            "category":"Farming",
            "subcategory":"Farm",
            "type":"Manufacturing & Wholesale Goods"
        }
    ],
    "sg:phone":"+1 937 544 4194",
    "sg:postcode":"45693",
    "sg:province":"OH",
    "sg:tags":[
        "mushroom"
    ],
    "wof:name":"Madison's Ridgeview Farm Inc",
    "wof:placetype":"venue"
},
  "geometry": {"coordinates":[-83.489094,38.779208],"type":"Point"}
}