{
  "type": "Feature",
  "properties": {
    "addr:full": "736 US Hwy 250 E Ashland OH 44805",
    "addr:housenumber": "736",
    "addr:postcode": "44805",
    "addr:street": "Us Hwy 250 E",
    "iso:country": "US",
    "sg:address": "736 US Hwy 250 E",
    "sg:city": "Ashland",
    "sg:classifiers": [
      {
        "category": "Travel",
        "subcategory": "Hotels \u0026 Motels",
        "type": "Entertainment"
      }
    ],
    "sg:phone": "+1 419 281 0567",
    "sg:postcode": "44805",
    "sg:province": "OH",
    "sg:tags": [
      "operation"
    ],
    "wof:name": "Super 8 Motel",
    "wof:placetype": "venue"
  },
  "geometry": {"coordinates":[-82.267699,40.858371],"type":"Point"}
}
