{
  "type": "Feature",
  "properties": {
    "addr:full": "5253 Twp Rd 59 Mount Gilead OH 43338",
    "addr:housenumber": "59",
    "addr:postcode": "5253;43338",
    "addr:street": "Twp Rd;Mount",
    "iso:country": "US",
    "sg:address": "5253 Twp Rd 59",
    "sg:city": "Mount Gilead",
    "sg:classifiers": [
      {
        "category": "Building \u0026 Trades",
        "subcategory": "Construction",
        "type": "Services"
      }
    ],
    "sg:phone": "+1 419 946 8597",
    "sg:postcode": "43338",
    "sg:province": "OH",
    "sg:tags": [
      "house"
    ],
    "wof:name": "Staten Builder",
    "wof:placetype": "venue"
  },
  "geometry": {"coordinates":[-82.758991,40.624537],"type":"Point"}
}
