{
  "type": "Feature",
  "properties": {
    "iso:country":"US",
    "sg:address":"3652 Harbor Bay Dr",
    "sg:city":"Loveland",
    "sg:classifiers":[
        {
            "category":"Banks & Credit Unions",
            "subcategory":"Investment Brokerage",
            "type":"Services"
        }
    ],
    "sg:phone":"+1 513 697 8406",
    "sg:postcode":"45140",
    "sg:province":"OH",
    "sg:tags":[
        "advisory"
    ],
    "wof:name":"United Financial",
    "wof:placetype":"venue"
},
  "geometry": {"coordinates":[-84.28853,39.302338],"type":"Point"}
}