{
  "type": "Feature",
  "properties": {
    "addr:full": "300 Prestige Place Dr Miamisburg OH 45342",
    "addr:housenumber": "300",
    "addr:postcode": "45342",
    "addr:street": "Prestige Place Dr",
    "iso:country": "US",
    "sg:address": "300 Prestige Place Dr",
    "sg:city": "Miamisburg",
    "sg:classifiers": [
      {
        "category": "Travel",
        "subcategory": "Hotels \u0026 Motels",
        "type": "Entertainment"
      }
    ],
    "sg:phone": "+1 937 436 0080",
    "sg:postcode": "45342",
    "sg:province": "OH",
    "wof:name": "Doubletree Guest Suites",
    "wof:placetype": "venue"
  },
  "geometry": {"coordinates":[-84.227974,39.633021],"type":"Point"}
}
