{
  "type": "Feature",
  "properties": {
    "iso:country":"US",
    "sg:address":"1242 W Mehring Way",
    "sg:city":"Cincinnati",
    "sg:classifiers":[
        {
            "category":"Manufacturing",
            "subcategory":"Tools & Machinery",
            "type":"Manufacturing & Wholesale Goods"
        }
    ],
    "sg:phone":"+1 513 721 6334",
    "sg:postcode":"45203",
    "sg:province":"OH",
    "sg:tags":[
        "marking",
        "mfg",
        "metal",
        "devices",
        "trade",
        "printing",
        "mach"
    ],
    "sg:website":"www.ecshaw.com",
    "wof:name":"E C Shaw Co",
    "wof:placetype":"venue"
},
  "geometry": {"coordinates":[-84.539407,39.100167],"type":"Point"}
}