{
  "type": "Feature",
  "properties": {
    "addr:full": "1242 W Mehring Way Cincinnati OH 45203",
    "addr:housenumber": "1242",
    "addr:postcode": "45203",
    "addr:street": "W Mehring Way",
    "iso:country": "US",
    "sg:address": "1242 W Mehring Way",
    "sg:city": "Cincinnati",
    "sg:classifiers": [
      {
        "category": "Manufacturing",
        "subcategory": "Tools \u0026 Machinery",
        "type": "Manufacturing \u0026 Wholesale Goods"
      }
    ],
    "sg:phone": "+1 513 721 6334",
    "sg:postcode": "45203",
    "sg:province": "OH",
    "sg:tags": [
      "marking",
      "mfg",
      "metal",
      "devices",
      "trade",
      "printing",
      "mach"
    ],
    "sg:website": "www.ecshaw.com",
    "wof:name": "E C Shaw Co",
    "wof:placetype": "venue"
  },
  "geometry": {"coordinates":[-84.539407,39.100167],"type":"Point"}
}
