{
  "type": "Feature",
  "properties": {
    "addr:full": "36582 Cline Ln Graysville OH 45734",
    "addr:postcode": "36582;45734",
    "addr:street": "Cline Ln",
    "iso:country": "US",
    "sg:address": "36582 Cline Ln",
    "sg:city": "Graysville",
    "sg:classifiers": [
      {
        "category": "Mining \u0026 Drilling",
        "type": "Manufacturing \u0026 Wholesale Goods"
      }
    ],
    "sg:phone": "+1 740 934 2553",
    "sg:postcode": "45734",
    "sg:province": "OH",
    "sg:tags": [
      "well"
    ],
    "wof:name": "R\u0026F Oil Co",
    "wof:placetype": "venue"
  },
  "geometry": {"coordinates":[-81.16139,39.668689],"type":"Point"}
}
