{
  "type": "Feature",
  "properties": {
    "iso:country":"US",
    "sg:address":"36582 Cline Ln",
    "sg:city":"Graysville",
    "sg:classifiers":[
        {
            "category":"Mining & Drilling",
            "type":"Manufacturing & Wholesale Goods"
        }
    ],
    "sg:phone":"+1 740 934 2553",
    "sg:postcode":"45734",
    "sg:province":"OH",
    "sg:tags":[
        "well"
    ],
    "wof:name":"R&F Oil Co",
    "wof:placetype":"venue"
},
  "geometry": {"coordinates":[-81.16139,39.668689],"type":"Point"}
}