{
  "type": "Feature",
  "properties": {
    "addr:full":"1720 Spruce St Defiance OH 43512",
    "addr:housenumber":"1720",
    "addr:postcode":"43512",
    "addr:street":"Spruce St",
    "iso:country":"US",
    "sg:address":"1720 Spruce St",
    "sg:city":"Defiance",
    "sg:classifiers":[
        {
            "category":"Home & Garden",
            "subcategory":"Hardware",
            "type":"Retail Goods"
        }
    ],
    "sg:phone":"+1 419 784 5822",
    "sg:postcode":"43512",
    "sg:province":"OH",
    "sg:tags":[
        "saw"
    ],
    "wof:name":"KMH Supply Co",
    "wof:placetype":"venue"
},
  "geometry": {"coordinates":[-84.335831,41.280298],"type":"Point"}
}