{
  "type": "Feature",
  "properties": {
    "addr:full": "30050 Chagrin Blvd Ste 150 Cleveland OH 44124",
    "addr:housenumber": "30050",
    "addr:postcode": "44124",
    "addr:street": "Chagrin Blvd Ste 150",
    "iso:country": "US",
    "sg:address": "30050 Chagrin Blvd Ste 150",
    "sg:city": "Cleveland",
    "sg:classifiers": [
      {
        "category": "Banks \u0026 Credit Unions",
        "subcategory": "Bank",
        "type": "Services"
      }
    ],
    "sg:phone": "+1 216 378 2810",
    "sg:postcode": "44124",
    "sg:province": "OH",
    "wof:name": "Sky Trust",
    "wof:placetype": "venue"
  },
  "geometry": {"coordinates":[-81.466301,41.462299],"type":"Point"}
}
