{
  "type": "Feature",
  "properties": {
    "iso:country":"US",
    "sg:address":"3120 Madison Rd",
    "sg:city":"Cincinnati",
    "sg:classifiers":[
        {
            "category":"Restaurant",
            "type":"Food & Drink"
        }
    ],
    "sg:phone":"+1 513 321 1600",
    "sg:postcode":"45209",
    "sg:province":"OH",
    "wof:name":"Baba India",
    "wof:placetype":"venue"
},
  "geometry": {"coordinates":[-84.429416,39.153587],"type":"Point"}
}