{
  "type": "Feature",
  "properties": {
    "addr:full":"13530 Strong Rd Maplewood OH 45340",
    "addr:housenumber":"13530",
    "addr:postcode":"45340",
    "addr:street":"Strong Rd",
    "iso:country":"US",
    "sg:address":"13530 Strong Rd",
    "sg:city":"Maplewood",
    "sg:classifiers":[
        {
            "category":"Farming",
            "subcategory":"Livestock Farm",
            "type":"Manufacturing & Wholesale Goods"
        }
    ],
    "sg:phone":"+1 937 596 6301",
    "sg:postcode":"45340",
    "sg:province":"OH",
    "sg:tags":[
        "hog",
        "or",
        "feedlot"
    ],
    "wof:name":"Terry Clineshens",
    "wof:placetype":"venue"
},
  "geometry": {"coordinates":[-84.008273,40.395495],"type":"Point"}
}