{
  "type": "Feature",
  "properties": {
    "addr:full":"11504 Strecker Rd Bellevue OH 44811",
    "addr:postcode":"11504;44811",
    "addr:street":"Strecker Rd",
    "iso:country":"US",
    "sg:address":"11504 Strecker Rd",
    "sg:city":"Bellevue",
    "sg:classifiers":[
        {
            "category":"Recreation",
            "type":"Entertainment"
        }
    ],
    "sg:phone":"+1 419 483 4225",
    "sg:postcode":"44811",
    "sg:province":"OH",
    "sg:tags":[
        "stable"
    ],
    "wof:name":"Bridle-Vue Stables",
    "wof:placetype":"venue"
},
  "geometry": {"coordinates":[-82.82156500000001,41.325932],"type":"Point"}
}