{
  "type": "Feature",
  "properties": {
    "iso:country":"US",
    "sg:address":"11504 Strecker Rd",
    "sg:city":"Bellevue",
    "sg:classifiers":[
        {
            "category":"Recreation",
            "type":"Entertainment"
        }
    ],
    "sg:phone":"+1 419 483 4225",
    "sg:postcode":"44811",
    "sg:province":"OH",
    "sg:tags":[
        "stable"
    ],
    "wof:name":"Bridle-Vue Stables",
    "wof:placetype":"venue"
},
  "geometry": {"coordinates":[-82.821565,41.325932],"type":"Point"}
}