{
  "type": "Feature",
  "properties": {
    "iso:country":"US",
    "sg:address":"353 Fox Dr",
    "sg:city":"Piqua",
    "sg:classifiers":[
        {
            "category":"Building & Trades",
            "subcategory":"Construction",
            "type":"Services"
        }
    ],
    "sg:phone":"+1 937 615 9030",
    "sg:postcode":"45356",
    "sg:province":"OH",
    "sg:tags":[
        "stone",
        "setting",
        "contractor"
    ],
    "wof:name":"Masonry Systems Inc",
    "wof:placetype":"venue"
},
  "geometry": {"coordinates":[-84.241838,40.121307],"type":"Point"}
}