{
  "type": "Feature",
  "properties": {
    "addr:full": "7278 Lawyer Rd Cincinnati OH 45244",
    "addr:housenumber": "7278",
    "addr:postcode": "45244",
    "addr:street": "Lawyer Rd",
    "iso:country": "US",
    "sg:address": "7278 Lawyer Rd",
    "sg:city": "Cincinnati",
    "sg:classifiers": [
      {
        "category": "Wholesale",
        "subcategory": "Apparel",
        "type": "Manufacturing \u0026 Wholesale Goods"
      }
    ],
    "sg:phone": "+1 513 232 0497",
    "sg:postcode": "45244",
    "sg:province": "OH",
    "sg:tags": [
      "consulting",
      "management",
      "industry"
    ],
    "wof:name": "John Bowman \u0026 Associates Inc",
    "wof:placetype": "venue"
  },
  "geometry": {"coordinates":[-84.352029,39.105081],"type":"Point"}
}
