{
  "type": "Feature",
  "properties": {
    "addr:full": "8140 Broadview Rd Cleveland OH 44147",
    "addr:housenumber": "8140",
    "addr:postcode": "44147",
    "addr:street": "Broadview Rd",
    "iso:country": "US",
    "sg:address": "8140 Broadview Rd",
    "sg:city": "Cleveland",
    "sg:classifiers": [
      {
        "category": "Food \u0026 Beverages",
        "subcategory": "Bakery",
        "type": "Retail Goods"
      }
    ],
    "sg:phone": "+1 440 526 5177",
    "sg:postcode": "44147",
    "sg:province": "OH",
    "sg:tags": [
      "doughnut"
    ],
    "wof:name": "Jo Ann's Donuts \u0026 Ice Cream",
    "wof:placetype": "venue"
  },
  "geometry": {"coordinates":[-81.684679,41.344721],"type":"Point"}
}
