{
  "type": "Feature",
  "properties": {
    "iso:country":"US",
    "sg:address":"619 Oak St",
    "sg:city":"Cincinnati",
    "sg:classifiers":[
        {
            "category":"Health Services",
            "subcategory":"Doctor",
            "type":"Services"
        }
    ],
    "sg:phone":"+1 513 569 6161",
    "sg:postcode":"45206",
    "sg:province":"OH",
    "sg:tags":[
        "clinic"
    ],
    "wof:name":"Bethesda Ob-Gyn Ctr",
    "wof:placetype":"venue"
},
  "geometry": {"coordinates":[-84.495807,39.129661],"type":"Point"}
}