{
  "type": "Feature",
  "properties": {
    "iso:country":"US",
    "sg:address":"7535 W Chester Rd",
    "sg:city":"West Chester",
    "sg:classifiers":[
        {
            "category":"Shopping",
            "subcategory":"Hobbies, Toys, & Games",
            "type":"Retail Goods"
        }
    ],
    "sg:phone":"+1 513 777 9969",
    "sg:postcode":"45069",
    "sg:province":"OH",
    "wof:name":"Wanda Keefe Crafts",
    "wof:placetype":"venue"
},
  "geometry": {"coordinates":[-84.377299,39.31948],"type":"Point"}
}