{
  "type": "Feature",
  "properties": {
    "addr:full":"7535 W Chester Rd West Chester OH 45069",
    "addr:housenumber":"7535",
    "addr:postcode":"45069",
    "addr:street":"W Chester Rd",
    "iso:country":"US",
    "sg:address":"7535 W Chester Rd",
    "sg:city":"West Chester",
    "sg:classifiers":[
        {
            "category":"Shopping",
            "subcategory":"Hobbies, Toys, & Games",
            "type":"Retail Goods"
        }
    ],
    "sg:phone":"+1 513 777 9969",
    "sg:postcode":"45069",
    "sg:province":"OH",
    "wof:name":"Wanda Keefe Crafts",
    "wof:placetype":"venue"
},
  "geometry": {"coordinates":[-84.37729899999999,39.31948],"type":"Point"}
}