{
  "type": "Feature",
  "properties": {
    "addr:full": "1346 W 112th St Cleveland OH 44102",
    "addr:housenumber": "1346",
    "addr:postcode": "44102",
    "addr:street": "W 112Th St",
    "iso:country": "US",
    "sg:address": "1346 W 112th St",
    "sg:city": "Cleveland",
    "sg:classifiers": [
      {
        "category": "Shopping",
        "subcategory": "Gifts \u0026 Souvenirs",
        "type": "Retail Goods"
      }
    ],
    "sg:phone": "+1 216 228 9983",
    "sg:postcode": "44102",
    "sg:province": "OH",
    "wof:name": "Kitsch City",
    "wof:placetype": "venue"
  },
  "geometry": {"coordinates":[-81.763878,41.486089],"type":"Point"}
}
