{
  "type": "Feature",
  "properties": {
    "addr:full": "604 Main St Zanesville OH 43701",
    "addr:housenumber": "604",
    "addr:postcode": "43701",
    "addr:street": "Main St",
    "iso:country": "US",
    "sg:address": "604 Main St",
    "sg:city": "Zanesville",
    "sg:classifiers": [
      {
        "category": "Insurance",
        "subcategory": "Insurance Agent",
        "type": "Services"
      }
    ],
    "sg:phone": "+1 740 588 9321",
    "sg:postcode": "43701",
    "sg:province": "OH",
    "wof:name": "SEO Financial Group",
    "wof:placetype": "venue"
  },
  "geometry": {"coordinates":[-82.005164,39.939964],"type":"Point"}
}
