{
  "type": "Feature",
  "properties": {
    "addr:full": "3777 Upper Bellbrook Rd Bellbrook OH 45305",
    "addr:housenumber": "3777",
    "addr:postcode": "45305",
    "addr:street": "Upper Bellbrook Rd",
    "iso:country": "US",
    "sg:address": "3777 Upper Bellbrook Rd",
    "sg:city": "Bellbrook",
    "sg:classifiers": [
      {
        "category": "Education",
        "subcategory": "School",
        "type": "Public Place"
      }
    ],
    "sg:phone": "+1 937 848 3777",
    "sg:postcode": "45305",
    "sg:province": "OH",
    "sg:tags": [
      "high",
      "junior"
    ],
    "sg:website": "www.bellbrook.com",
    "wof:name": "Bellbrook Junior High School",
    "wof:placetype": "venue"
  },
  "geometry": {"coordinates":[-84.069469,39.652401],"type":"Point"}
}
