{
  "type": "Feature",
  "properties": {
    "addr:full":"2757 Observatory Ave Cincinnati OH 45208",
    "addr:housenumber":"2757",
    "addr:postcode":"45208",
    "addr:street":"Observatory Ave",
    "iso:country":"US",
    "sg:address":"2757 Observatory Ave",
    "sg:city":"Cincinnati",
    "sg:classifiers":[
        {
            "category":"Shopping",
            "subcategory":"Clothing, Apparel, & Fashions",
            "type":"Retail Goods"
        }
    ],
    "sg:phone":"+1 513 321 6930",
    "sg:postcode":"45208",
    "sg:province":"OH",
    "wof:name":"Soho Women's Apparel",
    "wof:placetype":"venue"
},
  "geometry": {"coordinates":[-84.441444,39.137381],"type":"Point"}
}