{
  "type": "Feature",
  "properties": {
    "iso:country":"US",
    "sg:address":"10498 White Horse Trl",
    "sg:city":"Piqua",
    "sg:classifiers":[
        {
            "category":"Building & Trades",
            "subcategory":"Construction",
            "type":"Services"
        }
    ],
    "sg:phone":"+1 937 773 3920",
    "sg:postcode":"45356",
    "sg:province":"OH",
    "sg:tags":[
        "house",
        "construct",
        "contractor"
    ],
    "wof:name":"L & B Seamless Gutter",
    "wof:placetype":"venue"
},
  "geometry": {"coordinates":[-84.234779,40.206165],"type":"Point"}
}