{
  "type": "Feature",
  "properties": {
    "addr:full": "7537 Panther Ave NE Canton OH 44721",
    "addr:housenumber": "7537",
    "addr:postcode": "44721",
    "addr:street": "Panther Ave Ne",
    "iso:country": "US",
    "sg:address": "7537 Panther Ave NE",
    "sg:city": "Canton",
    "sg:classifiers": [
      {
        "category": "Retail",
        "subcategory": "Photofinishing",
        "type": "Services"
      }
    ],
    "sg:phone": "+1 330 494 8671",
    "sg:postcode": "44721",
    "sg:province": "OH",
    "sg:tags": [
      "communications",
      "telegraph",
      "laboratory"
    ],
    "wof:name": "J F Photo",
    "wof:placetype": "venue"
  },
  "geometry": {"coordinates":[-81.333509,40.889648],"type":"Point"}
}
