{
  "type": "Feature",
  "properties": {
    "iso:country":"US",
    "sg:address":"801 Brittain Rd",
    "sg:city":"Akron",
    "sg:classifiers":[
        {
            "category":"Personal",
            "subcategory":"Barber",
            "type":"Services"
        }
    ],
    "sg:phone":"+1 330 798 0165",
    "sg:postcode":"44305",
    "sg:province":"OH",
    "wof:name":"Brittain Road Barbers",
    "wof:placetype":"venue"
},
  "geometry": {"coordinates":[-81.46697,41.083413],"type":"Point"}
}