{
  "type": "Feature",
  "properties": {
    "iso:country":"US",
    "sg:address":"2 N Paint St",
    "sg:city":"Chillicothe",
    "sg:classifiers":[
        {
            "category":"Government",
            "subcategory":"Office",
            "type":"Public Place"
        }
    ],
    "sg:phone":"+1 740 702 3085",
    "sg:postcode":"45601",
    "sg:province":"OH",
    "wof:name":"Ross County Commissioners Ofc",
    "wof:placetype":"venue"
},
  "geometry": {"coordinates":[-82.982436,39.334517],"type":"Point"}
}