{
  "type": "Feature",
  "properties": {
    "addr:full":"1100 Evans Ave Akron OH 44305",
    "addr:housenumber":"1100",
    "addr:postcode":"44305",
    "addr:street":"Evans Ave",
    "iso:country":"US",
    "sg:address":"1100 Evans Ave",
    "sg:city":"Akron",
    "sg:classifiers":[
        {
            "category":"Manufacturing",
            "subcategory":"Tools & Machinery",
            "type":"Manufacturing & Wholesale Goods"
        }
    ],
    "sg:phone":"+1 330 633 1337",
    "sg:postcode":"44305",
    "sg:province":"OH",
    "sg:tags":[
        "mold"
    ],
    "wof:name":"Diversified Engraving Stamp",
    "wof:placetype":"venue"
},
  "geometry": {"coordinates":[-81.483796,41.095072],"type":"Point"}
}