{
  "type": "Feature",
  "properties": {
    "iso:country":"US",
    "sg:address":"6106 London Groveport Rd",
    "sg:city":"Grove City",
    "sg:classifiers":[
        {
            "category":"Building & Trades",
            "subcategory":"Construction",
            "type":"Services"
        }
    ],
    "sg:phone":"+1 614 877 0190",
    "sg:postcode":"43123",
    "sg:province":"OH",
    "sg:tags":[
        "dry wall",
        "contractor"
    ],
    "wof:name":"Steve's Drywall Inc",
    "wof:placetype":"venue"
},
  "geometry": {"coordinates":[-83.159486,39.849255],"type":"Point"}
}