{
  "type": "Feature",
  "properties": {
    "addr:full": "6106 London Groveport Rd Grove City OH 43123",
    "addr:housenumber": "6106",
    "addr:postcode": "43123",
    "addr:street": "London Groveport Rd",
    "iso:country": "US",
    "sg:address": "6106 London Groveport Rd",
    "sg:city": "Grove City",
    "sg:classifiers": [
      {
        "category": "Building \u0026 Trades",
        "subcategory": "Construction",
        "type": "Services"
      }
    ],
    "sg:phone": "+1 614 877 0190",
    "sg:postcode": "43123",
    "sg:province": "OH",
    "sg:tags": [
      "dry wall",
      "contractor"
    ],
    "wof:name": "Steve's Drywall Inc",
    "wof:placetype": "venue"
  },
  "geometry": {"coordinates":[-83.159486,39.849255],"type":"Point"}
}
