{
  "type": "Feature",
  "properties": {
    "iso:country":"US",
    "sg:address":"7710 Reading Rd",
    "sg:city":"Cincinnati",
    "sg:classifiers":[
        {
            "category":"Government",
            "subcategory":"Office",
            "type":"Public Place"
        }
    ],
    "sg:phone":"+1 513 821 6695",
    "sg:postcode":"45237",
    "sg:province":"OH",
    "sg:tags":[
        "educational",
        "program",
        "administrative"
    ],
    "wof:name":"Hamilton Life Skills County",
    "wof:placetype":"venue"
},
  "geometry": {"coordinates":[-84.455906,39.201732],"type":"Point"}
}