{
  "type": "Feature",
  "properties": {
    "iso:country":"US",
    "sg:address":"448 Greenwell Ave",
    "sg:city":"Cincinnati",
    "sg:classifiers":[
        {
            "category":"Insurance",
            "subcategory":"Insurance Agent",
            "type":"Services"
        }
    ],
    "sg:phone":"+1 513 471 0737",
    "sg:postcode":"45238",
    "sg:province":"OH",
    "wof:name":"Young Insurance Svc",
    "wof:placetype":"venue"
},
  "geometry": {"coordinates":[-84.60517400000001,39.099965],"type":"Point"}
}