{
  "type": "Feature",
  "properties": {
    "addr:full": "448 Greenwell Ave Cincinnati OH 45238",
    "addr:housenumber": "448",
    "addr:postcode": "45238",
    "addr:street": "Greenwell Ave",
    "iso:country": "US",
    "sg:address": "448 Greenwell Ave",
    "sg:city": "Cincinnati",
    "sg:classifiers": [
      {
        "category": "Insurance",
        "subcategory": "Insurance Agent",
        "type": "Services"
      }
    ],
    "sg:phone": "+1 513 471 0737",
    "sg:postcode": "45238",
    "sg:province": "OH",
    "wof:name": "Young Insurance Svc",
    "wof:placetype": "venue"
  },
  "geometry": {"coordinates":[-84.605174,39.099965],"type":"Point"}
}
