{
  "type": "Feature",
  "properties": {
    "iso:country":"US",
    "sg:address":"9550 Heimberger Rd NW",
    "sg:city":"Baltimore",
    "sg:classifiers":[
        {
            "category":"Building & Trades",
            "subcategory":"Landscaping Services",
            "type":"Services"
        }
    ],
    "sg:phone":"+1 740 862 2147",
    "sg:postcode":"43105",
    "sg:province":"OH",
    "sg:tags":[
        "fertilizing",
        "seeding",
        "contractor"
    ],
    "wof:name":"Hydromaster Seeding Co",
    "wof:placetype":"venue"
},
  "geometry": {"coordinates":[-82.662123,39.863076],"type":"Point"}
}