{
  "type": "Feature",
  "properties": {
    "addr:full": "8765 Heller Rd Whitehouse OH 43571",
    "addr:housenumber": "8765",
    "addr:postcode": "43571",
    "addr:street": "Heller Rd",
    "iso:country": "US",
    "sg:address": "8765 Heller Rd",
    "sg:city": "Whitehouse",
    "sg:classifiers": [
      {
        "category": "Banks \u0026 Credit Unions",
        "subcategory": "Financial Services",
        "type": "Services"
      }
    ],
    "sg:phone": "+1 419 877 0273",
    "sg:postcode": "43571",
    "sg:province": "OH",
    "sg:tags": [
      "investor"
    ],
    "wof:name": "Bramar Investments LTD",
    "wof:placetype": "venue"
  },
  "geometry": {"coordinates":[-83.807229,41.48844],"type":"Point"}
}
