{
  "type": "Feature",
  "properties": {
    "iso:country":"US",
    "sg:address":"8765 Heller Rd",
    "sg:city":"Whitehouse",
    "sg:classifiers":[
        {
            "category":"Banks & Credit Unions",
            "subcategory":"Financial Services",
            "type":"Services"
        }
    ],
    "sg:phone":"+1 419 877 0273",
    "sg:postcode":"43571",
    "sg:province":"OH",
    "sg:tags":[
        "investor"
    ],
    "wof:name":"Bramar Investments LTD",
    "wof:placetype":"venue"
},
  "geometry": {"coordinates":[-83.80722900000001,41.48844],"type":"Point"}
}