{
  "type": "Feature",
  "properties": {
    "iso:country":"US",
    "sg:address":"6204 Wilmington Pike",
    "sg:city":"Dayton",
    "sg:classifiers":[
        {
            "category":"Shopping",
            "subcategory":"Books",
            "type":"Retail Goods"
        }
    ],
    "sg:phone":"+1 937 848 6802",
    "sg:postcode":"45459",
    "sg:province":"OH",
    "sg:tags":[
        "dealer"
    ],
    "sg:website":"www.christianlightbookstore.com",
    "wof:name":"Christian Light Bookstores",
    "wof:placetype":"venue"
},
  "geometry": {"coordinates":[-84.110237,39.635009],"type":"Point"}
}