{
  "type": "Feature",
  "properties": {
    "addr:full":"39697 Churchill Rd Lisbon OH 44432",
    "addr:housenumber":"39697",
    "addr:postcode":"44432",
    "addr:street":"Churchill Rd",
    "iso:country":"US",
    "sg:address":"39697 Churchill Rd",
    "sg:city":"Lisbon",
    "sg:classifiers":[
        {
            "category":"Retail",
            "subcategory":"Auto Repair",
            "type":"Services"
        }
    ],
    "sg:phone":"+1 330 424 5062",
    "sg:postcode":"44432",
    "sg:province":"OH",
    "sg:tags":[
        "body",
        "automobile",
        "painting",
        "repairing"
    ],
    "wof:name":"Evans Bob Auto Body",
    "wof:placetype":"venue"
},
  "geometry": {"coordinates":[-80.746461,40.784886],"type":"Point"}
}