{
  "type": "Feature",
  "properties": {
    "iso:country":"US",
    "sg:address":"790 Carnegie Ave",
    "sg:city":"Akron",
    "sg:classifiers":[
        {
            "category":"Organizations",
            "subcategory":"Religious Organization",
            "type":"Services"
        }
    ],
    "sg:phone":"+1 330 753 9241",
    "sg:postcode":"44314",
    "sg:province":"OH",
    "sg:tags":[
        "church"
    ],
    "wof:name":"Sherwood Park Baptist Church",
    "wof:placetype":"venue"
},
  "geometry": {"coordinates":[-81.55324299999999,41.024412],"type":"Point"}
}