{
  "type": "Feature",
  "properties": {
    "addr:full": "790 Carnegie Ave Akron OH 44314",
    "addr:housenumber": "790",
    "addr:postcode": "44314",
    "addr:street": "Carnegie Ave",
    "iso:country": "US",
    "sg:address": "790 Carnegie Ave",
    "sg:city": "Akron",
    "sg:classifiers": [
      {
        "category": "Organizations",
        "subcategory": "Religious Organization",
        "type": "Services"
      }
    ],
    "sg:phone": "+1 330 753 9241",
    "sg:postcode": "44314",
    "sg:province": "OH",
    "sg:tags": [
      "church"
    ],
    "wof:name": "Sherwood Park Baptist Church",
    "wof:placetype": "venue"
  },
  "geometry": {"coordinates":[-81.553243,41.024412],"type":"Point"}
}
