{
  "type": "Feature",
  "properties": {
    "iso:country":"US",
    "sg:address":"432 Elm St",
    "sg:city":"Sidney",
    "sg:classifiers":[
        {
            "category":"Retail",
            "subcategory":"Animal Services",
            "type":"Services"
        }
    ],
    "sg:phone":"+1 937 492 4226",
    "sg:postcode":"45365",
    "sg:province":"OH",
    "wof:name":"Professional Dog Grooming",
    "wof:placetype":"venue"
},
  "geometry": {"coordinates":[-84.151205,40.291193],"type":"Point"}
}