{
  "type": "Feature",
  "properties": {
    "addr:full":"118 N Washington St Greenfield OH 45123",
    "addr:housenumber":"118",
    "addr:postcode":"45123",
    "addr:street":"N Washington St",
    "iso:country":"US",
    "sg:address":"118 N Washington St",
    "sg:city":"Greenfield",
    "sg:classifiers":[
        {
            "category":"Insurance",
            "subcategory":"Insurance Agent",
            "type":"Services"
        }
    ],
    "sg:phone":"+1 937 981 2121",
    "sg:postcode":"45123",
    "sg:province":"OH",
    "wof:name":"Security Insurance",
    "wof:placetype":"venue"
},
  "geometry": {"coordinates":[-83.38318599999999,39.351938],"type":"Point"}
}