{
  "type": "Feature",
  "properties": {
    "addr:full": "9917 Springfield Pike Cincinnati OH 45215",
    "addr:housenumber": "9917",
    "addr:postcode": "45215",
    "addr:street": "Springfield Pike",
    "iso:country": "US",
    "sg:address": "9917 Springfield Pike",
    "sg:city": "Cincinnati",
    "sg:classifiers": [
      {
        "category": "Shopping",
        "subcategory": "Used Merchandise",
        "type": "Retail Goods"
      }
    ],
    "sg:phone": "+1 513 771 5211",
    "sg:postcode": "45215",
    "sg:province": "OH",
    "wof:name": "Butterflies Shoppe",
    "wof:placetype": "venue"
  },
  "geometry": {"coordinates":[-84.470994,39.24515],"type":"Point"}
}
