{
  "type": "Feature",
  "properties": {
    "addr:full": "116 W 3rd St Cincinnati OH 45202",
    "addr:housenumber": "116",
    "addr:postcode": "45202",
    "addr:street": "W 3Rd St",
    "iso:country": "US",
    "sg:address": "116 W 3rd St",
    "sg:city": "Cincinnati",
    "sg:classifiers": [
      {
        "category": "Professional",
        "subcategory": "Printing \u0026 Photocopies",
        "type": "Services"
      }
    ],
    "sg:phone": "+1 513 621 4148",
    "sg:postcode": "45202",
    "sg:province": "OH",
    "sg:tags": [
      "duplicating",
      "copying"
    ],
    "wof:name": "Hess Reproductions \u0026 Supplies",
    "wof:placetype": "venue"
  },
  "geometry": {"coordinates":[-84.51538,39.098319],"type":"Point"}
}
