{
  "type": "Feature",
  "properties": {
    "iso:country":"US",
    "sg:address":"116 W 3rd St",
    "sg:city":"Cincinnati",
    "sg:classifiers":[
        {
            "category":"Professional",
            "subcategory":"Printing & Photocopies",
            "type":"Services"
        }
    ],
    "sg:phone":"+1 513 621 4148",
    "sg:postcode":"45202",
    "sg:province":"OH",
    "sg:tags":[
        "duplicating",
        "copying"
    ],
    "wof:name":"Hess Reproductions & Supplies",
    "wof:placetype":"venue"
},
  "geometry": {"coordinates":[-84.51537999999999,39.098319],"type":"Point"}
}