{
  "type": "Feature",
  "properties": {
    "addr:full":"478 Fleming Rd Cincinnati OH 45231",
    "addr:housenumber":"478",
    "addr:postcode":"45231",
    "addr:street":"Fleming Rd",
    "iso:country":"US",
    "sg:address":"478 Fleming Rd",
    "sg:city":"Cincinnati",
    "sg:classifiers":[
        {
            "category":"Wholesale",
            "subcategory":"Hardware",
            "type":"Manufacturing & Wholesale Goods"
        }
    ],
    "sg:phone":"+1 513 621 2828",
    "sg:postcode":"45231",
    "sg:province":"OH",
    "sg:tags":[
        "refrigerating"
    ],
    "wof:name":"Valley Refrigeration & AC SVC",
    "wof:placetype":"venue"
},
  "geometry": {"coordinates":[-84.496889,39.235968],"type":"Point"}
}