{
  "type": "Feature",
  "properties": {
    "addr:full": "408 N Broadway St New Philadelphia OH 44663",
    "addr:housenumber": "408",
    "addr:postcode": "44663",
    "addr:street": "N Broadway St",
    "iso:country": "US",
    "sg:address": "408 N Broadway St",
    "sg:city": "New Philadelphia",
    "sg:classifiers": [
      {
        "category": "Building \u0026 Trades",
        "subcategory": "Construction",
        "type": "Services"
      }
    ],
    "sg:phone": "+1 330 364 7168",
    "sg:postcode": "44663",
    "sg:province": "OH",
    "sg:tags": [
      "contractor"
    ],
    "wof:name": "Wbw Contractors",
    "wof:placetype": "venue"
  },
  "geometry": {"coordinates":[-81.444122,40.495055],"type":"Point"}
}
