{
  "type": "Feature",
  "properties": {
    "iso:country":"US",
    "sg:address":"408 N Broadway St",
    "sg:city":"New Philadelphia",
    "sg:classifiers":[
        {
            "category":"Building & Trades",
            "subcategory":"Construction",
            "type":"Services"
        }
    ],
    "sg:phone":"+1 330 364 7168",
    "sg:postcode":"44663",
    "sg:province":"OH",
    "sg:tags":[
        "contractor"
    ],
    "wof:name":"Wbw Contractors",
    "wof:placetype":"venue"
},
  "geometry": {"coordinates":[-81.444122,40.495055],"type":"Point"}
}