{
  "type": "Feature",
  "properties": {
    "iso:country":"US",
    "sg:address":"957 Tallmadge Rd",
    "sg:city":"Kent",
    "sg:classifiers":[
        {
            "category":"Manufacturing",
            "subcategory":"Paper Products",
            "type":"Manufacturing & Wholesale Goods"
        }
    ],
    "sg:phone":"+1 330 677 4750",
    "sg:postcode":"44240",
    "sg:province":"OH",
    "sg:tags":[
        "builder",
        "rotational",
        "mold"
    ],
    "wof:name":"Johndel Inc",
    "wof:placetype":"venue"
},
  "geometry": {"coordinates":[-81.358969,41.100123],"type":"Point"}
}