{
  "type": "Feature",
  "properties": {
    "addr:full":"510 Front St Greenville OH 45331",
    "addr:housenumber":"510",
    "addr:postcode":"45331",
    "addr:street":"Front St",
    "iso:country":"US",
    "sg:address":"510 Front St",
    "sg:city":"Greenville",
    "sg:classifiers":[
        {
            "category":"Organizations",
            "subcategory":"Religious Organization",
            "type":"Services"
        }
    ],
    "sg:phone":"+1 937 547 1239",
    "sg:postcode":"45331",
    "sg:province":"OH",
    "sg:tags":[
        "church"
    ],
    "wof:name":"Bible Baptist Church",
    "wof:placetype":"venue"
},
  "geometry": {"coordinates":[-84.62821700000001,40.095639],"type":"Point"}
}