{
  "type": "Feature",
  "properties": {
    "iso:country":"US",
    "sg:address":"1123 Maureen Ln",
    "sg:city":"Cincinnati",
    "sg:classifiers":[
        {
            "category":"Professional",
            "type":"Services"
        }
    ],
    "sg:phone":"+1 513 941 9505",
    "sg:postcode":"45238",
    "sg:province":"OH",
    "wof:name":"Donald B Wells",
    "wof:placetype":"venue"
},
  "geometry": {"coordinates":[-84.609498,39.117383],"type":"Point"}
}