{
  "type": "Feature",
  "properties": {
    "addr:full":"26104 Great Northern Shop Ctr North Olmsted OH 44070",
    "addr:housenumber":"26104",
    "addr:postcode":"44070",
    "addr:street":"Great",
    "iso:country":"US",
    "sg:address":"26104 Great Northern Shop Ctr",
    "sg:city":"North Olmsted",
    "sg:classifiers":[
        {
            "category":"Restaurant",
            "type":"Food & Drink"
        }
    ],
    "sg:menulink":"http://www.allmenus.com/oh/north-olmsted/64428-chuck-e-cheeses/menu/",
    "sg:phone":"+1 440 734 9929",
    "sg:postcode":"44070",
    "sg:province":"OH",
    "sg:tags":[
        "american",
        "pizza"
    ],
    "wof:name":"Chuck E. Cheese's",
    "wof:placetype":"venue"
},
  "geometry": {"coordinates":[-81.914158,41.417902],"type":"Point"}
}