{
  "type": "Feature",
  "properties": {
    "addr:full":"734 Preston Dr Waynesville OH 45068",
    "addr:housenumber":"734",
    "addr:postcode":"45068",
    "addr:street":"Preston Dr",
    "iso:country":"US",
    "sg:address":"734 Preston Dr",
    "sg:city":"Waynesville",
    "sg:classifiers":[
        {
            "category":"Building & Trades",
            "subcategory":"Construction",
            "type":"Services"
        }
    ],
    "sg:phone":"+1 513 897 1220",
    "sg:postcode":"45068",
    "sg:province":"OH",
    "wof:name":"Mueller Energy Service Inc",
    "wof:placetype":"venue"
},
  "geometry": {"coordinates":[-84.08646,39.540796],"type":"Point"}
}