{
  "type": "Feature",
  "properties": {
    "addr:full":"203 Park Ave London OH 43140",
    "addr:housenumber":"203",
    "addr:postcode":"43140",
    "addr:street":"Park Ave",
    "iso:country":"US",
    "sg:address":"203 Park Ave",
    "sg:city":"London",
    "sg:classifiers":[
        {
            "category":"Recreation",
            "type":"Entertainment"
        }
    ],
    "sg:phone":"+1 740 852 9051",
    "sg:postcode":"43140",
    "sg:province":"OH",
    "sg:tags":[
        "pool",
        "swimming"
    ],
    "wof:name":"London Municipal Swimming Pool",
    "wof:placetype":"venue"
},
  "geometry": {"coordinates":[-83.447025,39.893347],"type":"Point"}
}