{
  "type": "Feature",
  "properties": {
    "addr:full": "405 W Center St Marion OH 43302",
    "addr:housenumber": "405",
    "addr:postcode": "43302",
    "addr:street": "W Center St",
    "iso:country": "US",
    "sg:address": "405 W Center St",
    "sg:city": "Marion",
    "sg:classifiers": [
      {
        "category": "Professional",
        "subcategory": "Management \u0026 Consulting",
        "type": "Services"
      }
    ],
    "sg:phone": "+1 740 383 8373",
    "sg:postcode": "43302",
    "sg:province": "OH",
    "sg:tags": [
      "marketing",
      "program"
    ],
    "wof:name": "Real Imagination Marketing LLC",
    "wof:placetype": "venue"
  },
  "geometry": {"coordinates":[-83.13714,40.58836],"type":"Point"}
}
