{
  "type": "Feature",
  "properties": {
    "addr:full": "3953 Lori Lynn Dr Batavia OH 45103",
    "addr:housenumber": "3953",
    "addr:postcode": "45103",
    "addr:street": "Lori Lynn Dr",
    "iso:country": "US",
    "sg:address": "3953 Lori Lynn Dr",
    "sg:city": "Batavia",
    "sg:classifiers": [
      {
        "category": "Organizations",
        "subcategory": "Religious Organization",
        "type": "Services"
      }
    ],
    "sg:phone": "+1 513 724 6655",
    "sg:postcode": "45103",
    "sg:province": "OH",
    "sg:tags": [
      "church"
    ],
    "wof:name": "Spirit \u0026 Truth Fellowship",
    "wof:placetype": "venue"
  },
  "geometry": {"coordinates":[-84.074089,39.048642],"type":"Point"}
}
