{
  "type": "Feature",
  "properties": {
    "iso:country":"US",
    "sg:address":"1395 Gardner Blvd",
    "sg:city":"Barberton",
    "sg:classifiers":[
        {
            "category":"Shopping",
            "subcategory":"Computers & Home Electronics",
            "type":"Retail Goods"
        },
        {
            "category":"Professional",
            "subcategory":"Computer Services",
            "type":"Services"
        }
    ],
    "sg:phone":"+1 330 825 8727",
    "sg:postcode":"44203",
    "sg:province":"OH",
    "sg:tags":[
        "equipment",
        "design",
        "system",
        "dealer"
    ],
    "wof:name":"Reliable Micro",
    "wof:placetype":"venue"
},
  "geometry": {"coordinates":[-81.636502,41.024071],"type":"Point"}
}