{
  "type": "Feature",
  "properties": {
    "iso:country":"US",
    "sg:address":"30999 E Landerwood Dr",
    "sg:city":"Cleveland",
    "sg:classifiers":[
        {
            "category":"Professional",
            "type":"Services"
        }
    ],
    "sg:phone":"+1 216 831 8388",
    "sg:postcode":"44124",
    "sg:province":"OH",
    "wof:name":"Bruce Kendrick",
    "wof:placetype":"venue"
},
  "geometry": {"coordinates":[-81.458191,41.468487],"type":"Point"}
}