{
  "type": "Feature",
  "properties": {
    "addr:full": "5532 Douglas Rd Toledo OH 43613",
    "addr:housenumber": "5532",
    "addr:postcode": "43613",
    "addr:street": "Douglas Rd",
    "iso:country": "US",
    "sg:address": "5532 Douglas Rd",
    "sg:city": "Toledo",
    "sg:classifiers": [
      {
        "category": "Professional",
        "type": "Services"
      }
    ],
    "sg:phone": "+1 419 754 1262",
    "sg:postcode": "43613",
    "sg:province": "OH",
    "sg:tags": [
      "establishment"
    ],
    "wof:name": "AFLAC Topolaski District",
    "wof:placetype": "venue"
  },
  "geometry": {"coordinates":[-83.604801,41.716989],"type":"Point"}
}
