{
  "type": "Feature",
  "properties": {
    "addr:full": "4590 US Hwy 127 Greenville OH 45331",
    "addr:housenumber": "4590",
    "addr:postcode": "45331",
    "addr:street": "Us Hwy 127",
    "iso:country": "US",
    "sg:address": "4590 US Hwy 127",
    "sg:city": "Greenville",
    "sg:classifiers": [
      {
        "category": "Building \u0026 Trades",
        "subcategory": "Plumbing",
        "type": "Services"
      }
    ],
    "sg:phone": "+1 937 548 9802",
    "sg:postcode": "45331",
    "sg:province": "OH",
    "sg:tags": [
      "conditioning",
      "air",
      "system",
      "contractor"
    ],
    "wof:name": "Fourman's Heating \u0026 Cooling",
    "wof:placetype": "venue"
  },
  "geometry": {"coordinates":[-84.630511,40.050393],"type":"Point"}
}
