{
  "type": "Feature",
  "properties": {
    "addr:full":"11339 Melissa Ct Cincinnati OH 45251",
    "addr:housenumber":"11339",
    "addr:postcode":"45251",
    "addr:street":"Melissa Ct",
    "iso:country":"US",
    "sg:address":"11339 Melissa Ct",
    "sg:city":"Cincinnati",
    "sg:classifiers":[
        {
            "category":"Manufacturing",
            "subcategory":"Petroleum Products",
            "type":"Manufacturing & Wholesale Goods"
        }
    ],
    "sg:phone":"+1 513 851 3853",
    "sg:postcode":"45251",
    "sg:province":"OH",
    "sg:tags":[
        "candles-wholesale",
        "manufacturer"
    ],
    "wof:name":"Candle Ahd Sand Art",
    "wof:placetype":"venue"
},
  "geometry": {"coordinates":[-84.57763799999999,39.28481],"type":"Point"}
}