{
  "type": "Feature",
  "properties": {
    "addr:full":"5433 Perkins Rd Bedford OH 44146",
    "addr:housenumber":"5433",
    "addr:postcode":"44146",
    "addr:street":"Perkins Rd",
    "iso:country":"US",
    "sg:address":"5433 Perkins Rd",
    "sg:city":"Bedford",
    "sg:classifiers":[
        {
            "category":"Wholesale",
            "subcategory":"Construction Materials",
            "type":"Manufacturing & Wholesale Goods"
        },
        {
            "category":"Manufacturing",
            "subcategory":"Building Materials",
            "type":"Manufacturing & Wholesale Goods"
        }
    ],
    "sg:phone":"+1 440 232 6767",
    "sg:postcode":"44146",
    "sg:province":"OH",
    "sg:tags":[
        "mfg"
    ],
    "wof:name":"Appalachian Hardwood Lumber Co",
    "wof:placetype":"venue"
},
  "geometry": {"coordinates":[-81.498514,41.411803],"type":"Point"}
}