{
  "type": "Feature",
  "properties": {
    "addr:full":"17910 Resting Meadows Strongsville OH 44136",
    "addr:housenumber":"17910",
    "addr:postcode":"44136",
    "addr:street":"Resting Meadows",
    "iso:country":"US",
    "sg:address":"17910 Resting Meadows",
    "sg:city":"Strongsville",
    "sg:classifiers":[
        {
            "category":"Shopping",
            "subcategory":"Bicycles & Sporting Goods",
            "type":"Retail Goods"
        }
    ],
    "sg:phone":"+1 440 846 9798",
    "sg:postcode":"44136",
    "sg:province":"OH",
    "wof:name":"Royalton Arms",
    "wof:placetype":"venue"
},
  "geometry": {"coordinates":[-81.82592200000001,41.309254],"type":"Point"}
}