{
  "type": "Feature",
  "properties": {
    "addr:full": "5632 Mahoning Ave Austintown OH 44515",
    "addr:housenumber": "5632",
    "addr:postcode": "44515",
    "addr:street": "Mahoning Ave",
    "iso:country": "US",
    "sg:address": "5632 Mahoning Ave",
    "sg:city": "Austintown",
    "sg:classifiers": [
      {
        "category": "Banks \u0026 Credit Unions",
        "subcategory": "Bank",
        "type": "Services"
      }
    ],
    "sg:phone": "+1 330 792 2392",
    "sg:postcode": "44515",
    "sg:province": "OH",
    "wof:name": "First National Bank",
    "wof:placetype": "venue"
  },
  "geometry": {"coordinates":[-80.771533,41.099678],"type":"Point"}
}
