{
  "type": "Feature",
  "properties": {
    "iso:country":"US",
    "sg:address":"5632 Mahoning Ave",
    "sg:city":"Austintown",
    "sg:classifiers":[
        {
            "category":"Banks & Credit Unions",
            "subcategory":"Bank",
            "type":"Services"
        }
    ],
    "sg:phone":"+1 330 792 2392",
    "sg:postcode":"44515",
    "sg:province":"OH",
    "wof:name":"First National Bank",
    "wof:placetype":"venue"
},
  "geometry": {"coordinates":[-80.77153300000001,41.099678],"type":"Point"}
}