{
  "type": "Feature",
  "properties": {
    "addr:full":"2407 Grovewood Ave Cleveland OH 44134",
    "addr:housenumber":"2407",
    "addr:postcode":"44134",
    "addr:street":"Grovewood Ave",
    "iso:country":"US",
    "sg:address":"2407 Grovewood Ave",
    "sg:city":"Cleveland",
    "sg:classifiers":[
        {
            "category":"Communications",
            "subcategory":"Film & Video Production",
            "type":"Services"
        }
    ],
    "sg:phone":"+1 216 749 7370",
    "sg:postcode":"44134",
    "sg:province":"OH",
    "sg:tags":[
        "duplication",
        "tape"
    ],
    "wof:name":"Ungar Video & Film",
    "wof:placetype":"venue"
},
  "geometry": {"coordinates":[-81.706603,41.413066],"type":"Point"}
}