{
  "type": "Feature",
  "properties": {
    "addr:full": "3980 Laylin Rd Norwalk OH 44857",
    "addr:housenumber": "3980",
    "addr:postcode": "44857",
    "addr:street": "Laylin Rd",
    "iso:country": "US",
    "sg:address": "3980 Laylin Rd",
    "sg:city": "Norwalk",
    "sg:classifiers": [
      {
        "category": "Building \u0026 Trades",
        "subcategory": "Construction",
        "type": "Services"
      }
    ],
    "sg:phone": "+1 419 663 7246",
    "sg:postcode": "44857",
    "sg:province": "OH",
    "sg:tags": [
      "downspouts",
      "gutter"
    ],
    "wof:name": "Gutter Solutions",
    "wof:placetype": "venue"
  },
  "geometry": {"coordinates":[-82.566588,41.248977],"type":"Point"}
}
