{
  "type": "Feature",
  "properties": {
    "iso:country":"US",
    "sg:address":"152 Allen Ave",
    "sg:city":"New Holland",
    "sg:classifiers":[
        {
            "category":"Personal",
            "type":"Services"
        }
    ],
    "sg:phone":"+1 740 495 9850",
    "sg:postcode":"43145",
    "sg:province":"OH",
    "sg:tags":[
        "therapist",
        "massage"
    ],
    "wof:name":"Robert Connell",
    "wof:placetype":"venue"
},
  "geometry": {"coordinates":[-83.263744,39.558738],"type":"Point"}
}