{
  "type": "Feature",
  "properties": {
    "iso:country":"US",
    "sg:address":"3233 Refugee Rd",
    "sg:city":"Columbus",
    "sg:classifiers":[
        {
            "category":"Autos & Motor Vehicles",
            "subcategory":"Fuel & Gas Station",
            "type":"Retail Goods"
        }
    ],
    "sg:phone":"+1 614 236 1712",
    "sg:postcode":"43232",
    "sg:province":"OH",
    "sg:tags":[
        "grocery",
        "station",
        "gasoline"
    ],
    "wof:name":"Speedway 9165",
    "wof:placetype":"venue"
},
  "geometry": {"coordinates":[-82.911434,39.91717],"type":"Point"}
}