{
  "type": "Feature",
  "properties": {
    "addr:full": "3233 Refugee Rd Columbus OH 43232",
    "addr:housenumber": "3233",
    "addr:postcode": "43232",
    "addr:street": "Refugee Rd",
    "iso:country": "US",
    "sg:address": "3233 Refugee Rd",
    "sg:city": "Columbus",
    "sg:classifiers": [
      {
        "category": "Autos \u0026 Motor Vehicles",
        "subcategory": "Fuel \u0026 Gas Station",
        "type": "Retail Goods"
      }
    ],
    "sg:phone": "+1 614 236 1712",
    "sg:postcode": "43232",
    "sg:province": "OH",
    "sg:tags": [
      "grocery",
      "station",
      "gasoline"
    ],
    "wof:name": "Speedway 9165",
    "wof:placetype": "venue"
  },
  "geometry": {"coordinates":[-82.911434,39.91717],"type":"Point"}
}
