{
  "type": "Feature",
  "properties": {
    "iso:country":"US",
    "sg:address":"8270 Dowling Rd",
    "sg:city":"Perrysburg",
    "sg:phone":"+1 419 833 6433",
    "sg:postcode":"43551",
    "sg:province":"OH",
    "sg:tags":[
        "farm",
        "corn",
        "soybean"
    ],
    "wof:name":"Dennis Farms",
    "wof:placetype":"venue"
},
  "geometry": {"coordinates":[-83.552451,41.477944],"type":"Point"}
}