{
  "type": "Feature",
  "properties": {
    "addr:full": "26300 Cedar Rd Beachwood OH 44122",
    "addr:housenumber": "26300",
    "addr:postcode": "44122",
    "addr:street": "Cedar Rd",
    "iso:country": "US",
    "sg:address": "26300 Cedar Rd",
    "sg:city": "Beachwood",
    "sg:classifiers": [
      {
        "category": "Shopping",
        "subcategory": "Clothing, Apparel, \u0026 Fashions",
        "type": "Retail Goods"
      }
    ],
    "sg:phone": "+1 216 514 4828",
    "sg:postcode": "44122",
    "sg:province": "OH",
    "sg:tags": [
      "men's",
      "women's",
      "sportswear",
      "apparel",
      "girls'",
      "accessory",
      "clothing",
      "boys'",
      "store"
    ],
    "sg:website": "http://www.americaneagleoutfitters.com",
    "wof:name": "American Eagle Outfitters",
    "wof:placetype": "venue"
  },
  "geometry": {"coordinates":[-81.496668,41.501282],"type":"Point"}
}
