{
  "type": "Feature",
  "properties": {
    "addr:full": "2388 Newark Granville Rd Granville OH 43023",
    "addr:housenumber": "2388",
    "addr:postcode": "43023",
    "addr:street": "Newark Granville Rd",
    "iso:country": "US",
    "sg:address": "2388 Newark Granville Rd",
    "sg:city": "Granville",
    "sg:classifiers": [
      {
        "category": "Building \u0026 Trades",
        "subcategory": "Construction",
        "type": "Services"
      }
    ],
    "sg:phone": "+1 614 338 0125",
    "sg:postcode": "43023",
    "sg:province": "OH",
    "sg:tags": [
      "asbestos",
      "removal"
    ],
    "wof:name": "Keen \u0026 Cross Inc",
    "wof:placetype": "venue"
  },
  "geometry": {"coordinates":[-82.478346,40.059158],"type":"Point"}
}
