{
  "type": "Feature",
  "properties": {
    "addr:full":"1788 Eastbrook Dr S Columbus OH 43223",
    "addr:housenumber":"1788",
    "addr:postcode":"43223",
    "addr:street":"Eastbrook Dr S",
    "iso:country":"US",
    "sg:address":"1788 Eastbrook Dr S",
    "sg:city":"Columbus",
    "sg:classifiers":[
        {
            "category":"Freight",
            "type":"Transportation"
        }
    ],
    "sg:phone":"+1 614 871 6037",
    "sg:postcode":"43223",
    "sg:province":"OH",
    "sg:tags":[
        "trucking"
    ],
    "wof:name":"GDR Hauling Svc",
    "wof:placetype":"venue"
},
  "geometry": {"coordinates":[-83.048597,39.91955],"type":"Point"}
}