{
  "type": "Feature",
  "properties": {
    "addr:full":"3157 N Dayton Xenia Rd Dayton OH 45434",
    "addr:housenumber":"3157",
    "addr:postcode":"45434",
    "addr:street":"N Dayton Xenia Rd",
    "iso:country":"US",
    "sg:address":"3157 N Dayton Xenia Rd",
    "sg:city":"Dayton",
    "sg:classifiers":[
        {
            "category":"Restaurant",
            "type":"Food & Drink"
        }
    ],
    "sg:phone":"+1 937 426 9502",
    "sg:postcode":"45434",
    "sg:province":"OH",
    "sg:website":"www.mcdonalds.com",
    "wof:name":"Mc Donald's",
    "wof:placetype":"venue"
},
  "geometry": {"coordinates":[-84.053135,39.72643],"type":"Point"}
}