{
  "type": "Feature",
  "properties": {
    "addr:full":"18006 Lotus Dr Cleveland OH 44128",
    "addr:housenumber":"18006",
    "addr:postcode":"44128",
    "addr:street":"Lotus Dr",
    "iso:country":"US",
    "sg:address":"18006 Lotus Dr",
    "sg:city":"Cleveland",
    "sg:classifiers":[
        {
            "category":"Professional",
            "type":"Services"
        }
    ],
    "sg:phone":"+1 216 283 8657",
    "sg:postcode":"44128",
    "sg:province":"OH",
    "wof:name":"A Healthier You",
    "wof:placetype":"venue"
},
  "geometry": {"coordinates":[-81.55301799999999,41.445734],"type":"Point"}
}