{
  "type": "Feature",
  "properties": {
    "addr:full": "11000 Euclid Ave Cleveland OH 44106",
    "addr:housenumber": "11000",
    "addr:postcode": "44106",
    "addr:street": "Euclid Ave",
    "iso:country": "US",
    "sg:address": "11000 Euclid Ave",
    "sg:city": "Cleveland",
    "sg:classifiers": [
      {
        "category": "Education",
        "subcategory": "Library",
        "type": "Public Place"
      }
    ],
    "sg:phone": "+1 216 368 3745",
    "sg:postcode": "44106",
    "sg:province": "OH",
    "wof:name": "Cleveland Medical Library Association Inc",
    "wof:placetype": "venue"
  },
  "geometry": {"coordinates":[-81.608466,41.506433],"type":"Point"}
}
