{
  "type": "Feature",
  "properties": {
    "iso:country":"US",
    "sg:address":"11000 Euclid Ave",
    "sg:city":"Cleveland",
    "sg:classifiers":[
        {
            "category":"Education",
            "subcategory":"Library",
            "type":"Public Place"
        }
    ],
    "sg:phone":"+1 216 368 3745",
    "sg:postcode":"44106",
    "sg:province":"OH",
    "wof:name":"Cleveland Medical Library Association Inc",
    "wof:placetype":"venue"
},
  "geometry": {"coordinates":[-81.60846600000001,41.506433],"type":"Point"}
}