{
  "type": "Feature",
  "properties": {
    "iso:country":"US",
    "sg:address":"23 W Washington St",
    "sg:city":"Athens",
    "sg:classifiers":[
        {
            "category":"Personal",
            "subcategory":"Barber",
            "type":"Services"
        }
    ],
    "sg:phone":"+1 740 594 7557",
    "sg:postcode":"45701",
    "sg:province":"OH",
    "wof:name":"Smart Barber Shop",
    "wof:placetype":"venue"
},
  "geometry": {"coordinates":[-82.101614,39.329132],"type":"Point"}
}