{
  "type": "Feature",
  "properties": {
    "iso:country":"US",
    "sg:address":"454 Ohio Pike",
    "sg:city":"Cincinnati",
    "sg:classifiers":[
        {
            "category":"Banks & Credit Unions",
            "subcategory":"Bank",
            "type":"Services"
        }
    ],
    "sg:phone":"+1 513 576 9100",
    "sg:postcode":"45255",
    "sg:province":"OH",
    "sg:tags":[
        "cashing",
        "check"
    ],
    "wof:name":"One Source Cash Advance",
    "wof:placetype":"venue"
},
  "geometry": {"coordinates":[-84.310329,39.071734],"type":"Point"}
}