{
  "type": "Feature",
  "properties": {
    "addr:full": "259 Jefferson St Greenfield OH 45123",
    "addr:housenumber": "259",
    "addr:postcode": "45123",
    "addr:street": "Jefferson St",
    "iso:country": "US",
    "sg:address": "259 Jefferson St",
    "sg:city": "Greenfield",
    "sg:classifiers": [
      {
        "category": "Shopping",
        "subcategory": "Pharmacy",
        "type": "Retail Goods"
      }
    ],
    "sg:phone": "+1 937 981 2454",
    "sg:postcode": "45123",
    "sg:province": "OH",
    "sg:tags": [
      "equipment"
    ],
    "wof:name": "Corner Pharmacy",
    "wof:placetype": "venue"
  },
  "geometry": {"coordinates":[-83.381885,39.351905],"type":"Point"}
}
