{
  "type": "Feature",
  "properties": {
    "iso:country":"US",
    "sg:address":"5901 Airport Hwy",
    "sg:city":"Toledo",
    "sg:classifiers":[
        {
            "category":"Education",
            "subcategory":"School",
            "type":"Public Place"
        }
    ],
    "sg:phone":"+1 419 865 5743",
    "sg:postcode":"43615",
    "sg:province":"OH",
    "wof:name":"St John's High School",
    "wof:placetype":"venue"
},
  "geometry": {"coordinates":[-83.68196399999999,41.614224],"type":"Point"}
}