{
  "type": "Feature",
  "properties": {
    "addr:full":"2920 W Central Ave Toledo OH 43606",
    "addr:housenumber":"2920",
    "addr:postcode":"43606",
    "addr:street":"W Central Ave",
    "iso:country":"US",
    "sg:address":"2920 W Central Ave",
    "sg:city":"Toledo",
    "sg:classifiers":[
        {
            "category":"Professional",
            "subcategory":"Lawyer & Legal Services",
            "type":"Services"
        }
    ],
    "sg:phone":"+1 419 537 6700",
    "sg:postcode":"43606",
    "sg:province":"OH",
    "sg:tags":[
        "attorney"
    ],
    "wof:name":"Virginia M Wall Law Offices",
    "wof:placetype":"venue"
},
  "geometry": {"coordinates":[-83.61607600000001,41.677451],"type":"Point"}
}