{
  "type": "Feature",
  "properties": {
    "addr:full":"15028 E US Hwy 224 Findlay OH 45840",
    "addr:housenumber":"15028",
    "addr:postcode":"45840",
    "addr:street":"E Us Hwy 224",
    "iso:country":"US",
    "sg:address":"15028 E US Hwy 224",
    "sg:city":"Findlay",
    "sg:classifiers":[
        {
            "category":"Utilities",
            "subcategory":"Mobile Phone",
            "type":"Services"
        }
    ],
    "sg:phone":"+1 419 424 2351",
    "sg:postcode":"45840",
    "sg:province":"OH",
    "sg:tags":[
        "telephone",
        "cellular"
    ],
    "sg:website":"www.verizonwireless.com",
    "wof:name":"Verizon Wireless",
    "wof:placetype":"venue"
},
  "geometry": {"coordinates":[-83.591977,41.055793],"type":"Point"}
}