{
  "type": "Feature",
  "properties": {
    "addr:full": "420 Chillicothe St Portsmouth OH 45662",
    "addr:housenumber": "420",
    "addr:postcode": "45662",
    "addr:street": "Chillicothe St",
    "iso:country": "US",
    "sg:address": "420 Chillicothe St",
    "sg:city": "Portsmouth",
    "sg:classifiers": [
      {
        "category": "Wholesale",
        "subcategory": "Durable Goods \u0026 Equipment",
        "type": "Manufacturing \u0026 Wholesale Goods"
      }
    ],
    "sg:phone": "+1 740 353 4266",
    "sg:postcode": "45662",
    "sg:province": "OH",
    "sg:tags": [
      "compact",
      "toy",
      "appliance",
      "disc",
      "tape",
      "electrical"
    ],
    "wof:name": "L \u0026 T Distributors",
    "wof:placetype": "venue"
  },
  "geometry": {"coordinates":[-82.996495,38.733807],"type":"Point"}
}
