{
  "type": "Feature",
  "properties": {
    "addr:full":"899 Mardec St West Union OH 45693",
    "addr:housenumber":"899",
    "addr:postcode":"45693",
    "addr:street":"Mardec St",
    "iso:country":"US",
    "sg:address":"899 Mardec St",
    "sg:city":"West Union",
    "sg:classifiers":[
        {
            "category":"Professional",
            "subcategory":"Lawyer & Legal Services",
            "type":"Services"
        }
    ],
    "sg:phone":"+1 937 544 5747",
    "sg:postcode":"45693",
    "sg:province":"OH",
    "sg:tags":[
        "attorney"
    ],
    "wof:name":"Armstrong Kenneth L Jr Atty Rs",
    "wof:placetype":"venue"
},
  "geometry": {"coordinates":[-83.53516999999999,38.790897],"type":"Point"}
}