{
  "type": "Feature",
  "properties": {
    "iso:country":"US",
    "sg:address":"3426 Corban Commons Dr",
    "sg:city":"Columbus",
    "sg:classifiers":[
        {
            "category":"Real Estate",
            "subcategory":"Real Estate Operator",
            "type":"Services"
        }
    ],
    "sg:phone":"+1 614 337 1577",
    "sg:postcode":"43219",
    "sg:province":"OH",
    "sg:tags":[
        "building",
        "apartment"
    ],
    "wof:name":"Corban Commons Apartments",
    "wof:placetype":"venue"
},
  "geometry": {"coordinates":[-82.92140999999999,40.020759],"type":"Point"}
}