{
  "type": "Feature",
  "properties": {
    "addr:full":"643 Washington Ave Elyria OH 44035",
    "addr:housenumber":"643",
    "addr:postcode":"44035",
    "addr:street":"Washington Ave",
    "iso:country":"US",
    "sg:address":"643 Washington Ave",
    "sg:city":"Elyria",
    "sg:classifiers":[
        {
            "category":"Banks & Credit Unions",
            "subcategory":"Financial Services",
            "type":"Services"
        }
    ],
    "sg:phone":"+1 440 322 0562",
    "sg:postcode":"44035",
    "sg:province":"OH",
    "sg:tags":[
        "trust",
        "management"
    ],
    "wof:name":"L William Gast Living Trust",
    "wof:placetype":"venue"
},
  "geometry": {"coordinates":[-82.10159299999999,41.377818],"type":"Point"}
}