{
  "type": "Feature",
  "properties": {
    "iso:country":"US",
    "sg:address":"4006 Dover Rd",
    "sg:city":"Youngstown",
    "sg:classifiers":[
        {
            "category":"Professional",
            "subcategory":"Computer Services",
            "type":"Services"
        }
    ],
    "sg:phone":"+1 330 788 8942",
    "sg:postcode":"44511",
    "sg:province":"OH",
    "wof:name":"J B PC Upgrades",
    "wof:placetype":"venue"
},
  "geometry": {"coordinates":[-80.682827,41.058952],"type":"Point"}
}