{
  "type": "Feature",
  "properties": {
    "iso:country":"US",
    "sg:address":"2037 Morning Glory",
    "sg:city":"Lima",
    "sg:classifiers":[
        {
            "category":"Building & Trades",
            "subcategory":"Construction",
            "type":"Services"
        }
    ],
    "sg:phone":"+1 419 223 8356",
    "sg:postcode":"45807",
    "sg:province":"OH",
    "sg:tags":[
        "painter"
    ],
    "wof:name":"J & J Quality Painting",
    "wof:placetype":"venue"
},
  "geometry": {"coordinates":[-84.193455,40.777463],"type":"Point"}
}