{
  "type": "Feature",
  "properties": {
    "addr:full": "2037 Morning Glory Lima OH 45807",
    "addr:housenumber": "2037",
    "addr:postcode": "45807",
    "addr:street": "Morning Glory",
    "iso:country": "US",
    "sg:address": "2037 Morning Glory",
    "sg:city": "Lima",
    "sg:classifiers": [
      {
        "category": "Building \u0026 Trades",
        "subcategory": "Construction",
        "type": "Services"
      }
    ],
    "sg:phone": "+1 419 223 8356",
    "sg:postcode": "45807",
    "sg:province": "OH",
    "sg:tags": [
      "painter"
    ],
    "wof:name": "J \u0026 J Quality Painting",
    "wof:placetype": "venue"
  },
  "geometry": {"coordinates":[-84.193455,40.777463],"type":"Point"}
}
