{
  "type": "Feature",
  "properties": {
    "addr:full": "5114 Darrow Rd Hudson OH 44236",
    "addr:housenumber": "5114",
    "addr:postcode": "44236",
    "addr:street": "Darrow Rd",
    "iso:country": "US",
    "sg:address": "5114 Darrow Rd",
    "sg:city": "Hudson",
    "sg:classifiers": [
      {
        "category": "Professional",
        "type": "Services"
      }
    ],
    "sg:phone": "+1 330 342 0331",
    "sg:postcode": "44236",
    "sg:province": "OH",
    "sg:tags": [
      "establishment"
    ],
    "wof:name": "Exper Count Inc",
    "wof:placetype": "venue"
  },
  "geometry": {"coordinates":[-81.44049,41.205651],"type":"Point"}
}
