{
  "type": "Feature",
  "properties": {
    "addr:full":"10433 Clifton Blvd Cleveland OH 44102",
    "addr:housenumber":"10433",
    "addr:postcode":"44102",
    "addr:street":"Clifton Blvd",
    "iso:country":"US",
    "sg:address":"10433 Clifton Blvd",
    "sg:city":"Cleveland",
    "sg:classifiers":[
        {
            "category":"Freight",
            "type":"Transportation"
        }
    ],
    "sg:phone":"+1 216 631 1314",
    "sg:postcode":"44102",
    "sg:province":"OH",
    "sg:tags":[
        "warehouse",
        "self",
        "storage"
    ],
    "wof:name":"Warehouse Gallery",
    "wof:placetype":"venue"
},
  "geometry": {"coordinates":[-81.75722399999999,41.485306],"type":"Point"}
}