{
  "type": "Feature",
  "properties": {
    "addr:full": "11230 Deerfield Rd Cincinnati OH 45242",
    "addr:housenumber": "11230",
    "addr:postcode": "45242",
    "addr:street": "Deerfield Rd",
    "iso:country": "US",
    "sg:address": "11230 Deerfield Rd",
    "sg:city": "Cincinnati",
    "sg:classifiers": [
      {
        "category": "Real Estate",
        "subcategory": "Real Estate Operator",
        "type": "Services"
      }
    ],
    "sg:phone": "+1 513 489 9801",
    "sg:postcode": "45242",
    "sg:province": "OH",
    "sg:tags": [
      "building",
      "residential"
    ],
    "wof:name": "Creek Road Partnership",
    "wof:placetype": "venue"
  },
  "geometry": {"coordinates":[-84.359847,39.270052],"type":"Point"}
}
