{
  "type": "Feature",
  "properties": {
    "iso:country":"US",
    "sg:address":"1125 Glendale Milford Rd",
    "sg:city":"Cincinnati",
    "sg:classifiers":[
        {
            "category":"Freight",
            "type":"Transportation"
        }
    ],
    "sg:phone":"+1 513 771 4848",
    "sg:postcode":"45215",
    "sg:province":"OH",
    "sg:tags":[
        "trucking"
    ],
    "sg:website":"www.atslogistics.com",
    "wof:name":"Advance Transportation Systems",
    "wof:placetype":"venue"
},
  "geometry": {"coordinates":[-84.450897,39.25627],"type":"Point"}
}