{
  "type": "Feature",
  "properties": {
    "addr:full": "421 W Broad St Pataskala OH 43062",
    "addr:housenumber": "421",
    "addr:postcode": "43062",
    "addr:street": "W Broad St",
    "iso:country": "US",
    "sg:address": "421 W Broad St",
    "sg:city": "Pataskala",
    "sg:classifiers": [
      {
        "category": "Retail",
        "subcategory": "Auto Rental",
        "type": "Services"
      }
    ],
    "sg:phone": "+1 740 927 9668",
    "sg:postcode": "43062",
    "sg:province": "OH",
    "sg:tags": [
      "renting",
      "truck",
      "leasing"
    ],
    "wof:name": "U-Haul Co",
    "wof:placetype": "venue"
  },
  "geometry": {"coordinates":[-82.685227,40.001341],"type":"Point"}
}
