{
  "type": "Feature",
  "properties": {
    "addr:full": "12110 Antioch Rd Logan OH 43138",
    "addr:housenumber": "12110",
    "addr:postcode": "43138",
    "addr:street": "Antioch Rd",
    "iso:country": "US",
    "sg:address": "12110 Antioch Rd",
    "sg:city": "Logan",
    "sg:classifiers": [
      {
        "category": "Building \u0026 Trades",
        "subcategory": "Construction",
        "type": "Services"
      }
    ],
    "sg:phone": "+1 740 385 7718",
    "sg:postcode": "43138",
    "sg:province": "OH",
    "sg:tags": [
      "excavating",
      "contractor"
    ],
    "wof:name": "James H Nihiser Excavating",
    "wof:placetype": "venue"
  },
  "geometry": {"coordinates":[-82.480419,39.554563],"type":"Point"}
}
