{
  "type": "Feature",
  "properties": {
    "addr:full": "232 25th St NW Canton OH 44709",
    "addr:housenumber": "232",
    "addr:postcode": "44709",
    "addr:street": "25Th St Nw",
    "iso:country": "US",
    "sg:address": "232 25th St NW",
    "sg:city": "Canton",
    "sg:classifiers": [
      {
        "category": "Real Estate",
        "subcategory": "Real Estate Operator",
        "type": "Services"
      }
    ],
    "sg:phone": "+1 330 452 5220",
    "sg:postcode": "44709",
    "sg:province": "OH",
    "sg:tags": [
      "building",
      "nonresidential"
    ],
    "wof:name": "IMG Properties Inc",
    "wof:placetype": "venue"
  },
  "geometry": {"coordinates":[-81.371781,40.823759],"type":"Point"}
}
