{
  "type": "Feature",
  "properties": {
    "addr:full":"960 W Main St Tipp City OH 45371",
    "addr:housenumber":"960",
    "addr:postcode":"45371",
    "addr:street":"W Main St",
    "iso:country":"US",
    "sg:address":"960 W Main St",
    "sg:city":"Tipp City",
    "sg:classifiers":[
        {
            "category":"Food & Beverages",
            "subcategory":"Groceries & Convenience Stores",
            "type":"Retail Goods"
        }
    ],
    "sg:phone":"+1 937 667 4494",
    "sg:postcode":"45371",
    "sg:province":"OH",
    "wof:name":"Tipp City Foodtown",
    "wof:placetype":"venue"
},
  "geometry": {"coordinates":[-84.184645,39.960805],"type":"Point"}
}