{
  "type": "Feature",
  "properties": {
    "iso:country":"US",
    "sg:address":"7342 Nettlecreek Rd",
    "sg:city":"Saint Paris",
    "sg:classifiers":[
        {
            "category":"Retail",
            "subcategory":"Animal Services",
            "type":"Services"
        }
    ],
    "sg:phone":"+1 937 653 4967",
    "sg:postcode":"43072",
    "sg:province":"OH",
    "sg:tags":[
        "association"
    ],
    "wof:name":"Mad River Valley Kennel Center",
    "wof:placetype":"venue"
},
  "geometry": {"coordinates":[-83.904075,40.099221],"type":"Point"}
}