{
  "type": "Feature",
  "properties": {
    "addr:full": "7342 Nettlecreek Rd Saint Paris OH 43072",
    "addr:housenumber": "7342",
    "addr:postcode": "43072",
    "addr:street": "Nettlecreek Rd",
    "iso:country": "US",
    "sg:address": "7342 Nettlecreek Rd",
    "sg:city": "Saint Paris",
    "sg:classifiers": [
      {
        "category": "Retail",
        "subcategory": "Animal Services",
        "type": "Services"
      }
    ],
    "sg:phone": "+1 937 653 4967",
    "sg:postcode": "43072",
    "sg:province": "OH",
    "sg:tags": [
      "association"
    ],
    "wof:name": "Mad River Valley Kennel Center",
    "wof:placetype": "venue"
  },
  "geometry": {"coordinates":[-83.904075,40.099221],"type":"Point"}
}
