{
  "type": "Feature",
  "properties": {
    "addr:full":"300 N Main St Georgetown OH 45121",
    "addr:housenumber":"300",
    "addr:postcode":"45121",
    "addr:street":"N Main St",
    "iso:country":"US",
    "sg:address":"300 N Main St",
    "sg:city":"Georgetown",
    "sg:classifiers":[
        {
            "category":"Restaurant",
            "type":"Food & Drink"
        }
    ],
    "sg:phone":"+1 937 378 9081",
    "sg:postcode":"45121",
    "sg:province":"OH",
    "sg:tags":[
        "parlor",
        "ice",
        "cream"
    ],
    "wof:name":"Main Street Dairy Bar",
    "wof:placetype":"venue"
},
  "geometry": {"coordinates":[-83.904123,38.868079],"type":"Point"}
}