{
  "type": "Feature",
  "properties": {
    "addr:full": "4841 Pin Oak Rd Akron OH 44333",
    "addr:housenumber": "4841",
    "addr:postcode": "44333",
    "addr:street": "Pin Oak Rd",
    "iso:country": "US",
    "sg:address": "4841 Pin Oak Rd",
    "sg:city": "Akron",
    "sg:classifiers": [
      {
        "category": "Real Estate",
        "subcategory": "Real Estate Operator",
        "type": "Services"
      }
    ],
    "sg:phone": "+1 330 665 5600",
    "sg:postcode": "44333",
    "sg:province": "OH",
    "sg:tags": [
      "building",
      "nonresidential"
    ],
    "wof:name": "Stouffer Properties LLC",
    "wof:placetype": "venue"
  },
  "geometry": {"coordinates":[-81.681014,41.163678],"type":"Point"}
}
