{
  "type": "Feature",
  "properties": {
    "addr:full": "325 Birchbark Trl Aurora OH 44202",
    "addr:housenumber": "325",
    "addr:postcode": "44202",
    "addr:street": "Birchbark Trl",
    "iso:country": "US",
    "sg:address": "325 Birchbark Trl",
    "sg:city": "Aurora",
    "sg:classifiers": [
      {
        "category": "Wholesale",
        "subcategory": "Durable Goods \u0026 Equipment",
        "type": "Manufacturing \u0026 Wholesale Goods"
      }
    ],
    "sg:phone": "+1 330 562 2998",
    "sg:postcode": "44202",
    "sg:province": "OH",
    "sg:tags": [
      "importer"
    ],
    "wof:name": "Tech-SERV USA Inc",
    "wof:placetype": "venue"
  },
  "geometry": {"coordinates":[-81.35834,41.310353],"type":"Point"}
}
