{
  "type": "Feature",
  "properties": {
    "iso:country":"US",
    "sg:address":"325 Birchbark Trl",
    "sg:city":"Aurora",
    "sg:classifiers":[
        {
            "category":"Wholesale",
            "subcategory":"Durable Goods & Equipment",
            "type":"Manufacturing & Wholesale Goods"
        }
    ],
    "sg:phone":"+1 330 562 2998",
    "sg:postcode":"44202",
    "sg:province":"OH",
    "sg:tags":[
        "importer"
    ],
    "wof:name":"Tech-SERV USA Inc",
    "wof:placetype":"venue"
},
  "geometry": {"coordinates":[-81.35834,41.310353],"type":"Point"}
}