{
  "type": "Feature",
  "properties": {
    "addr:full": "951 Nathaniel Rd Cleveland OH 44110",
    "addr:housenumber": "951",
    "addr:postcode": "44110",
    "addr:street": "Nathaniel Rd",
    "iso:country": "US",
    "sg:address": "951 Nathaniel Rd",
    "sg:city": "Cleveland",
    "sg:classifiers": [
      {
        "category": "Personal",
        "subcategory": "Beauty Salon",
        "type": "Services"
      }
    ],
    "sg:phone": "+1 216 486 6245",
    "sg:postcode": "44110",
    "sg:province": "OH",
    "sg:tags": [
      "manicuring"
    ],
    "wof:name": "Hands From Heaven Nail Care",
    "wof:placetype": "venue"
  },
  "geometry": {"coordinates":[-81.570823,41.553864],"type":"Point"}
}
