{
  "type": "Feature",
  "properties": {
    "iso:country":"US",
    "sg:address":"6002 N US Hwy 68",
    "sg:city":"Wilmington",
    "sg:classifiers":[
        {
            "category":"Autos & Motor Vehicles",
            "subcategory":"Motorcycle Sales",
            "type":"Retail Goods"
        }
    ],
    "sg:phone":"+1 937 283 2220",
    "sg:postcode":"45177",
    "sg:province":"OH",
    "sg:tags":[
        "parts"
    ],
    "wof:name":"Clinton County Motor Sports",
    "wof:placetype":"venue"
},
  "geometry": {"coordinates":[-83.847274,39.527528],"type":"Point"}
}