{
  "type": "Feature",
  "properties": {
    "addr:full": "6002 N US Hwy 68 Wilmington OH 45177",
    "addr:housenumber": "6002",
    "addr:postcode": "45177",
    "addr:street": "N Us Hwy 68",
    "iso:country": "US",
    "sg:address": "6002 N US Hwy 68",
    "sg:city": "Wilmington",
    "sg:classifiers": [
      {
        "category": "Autos \u0026 Motor Vehicles",
        "subcategory": "Motorcycle Sales",
        "type": "Retail Goods"
      }
    ],
    "sg:phone": "+1 937 283 2220",
    "sg:postcode": "45177",
    "sg:province": "OH",
    "sg:tags": [
      "parts"
    ],
    "wof:name": "Clinton County Motor Sports",
    "wof:placetype": "venue"
  },
  "geometry": {"coordinates":[-83.847274,39.527528],"type":"Point"}
}
