{
  "type": "Feature",
  "properties": {
    "addr:full": "4216 Milan Rd Sandusky OH 44870",
    "addr:housenumber": "4216",
    "addr:postcode": "44870",
    "addr:street": "Milan Rd",
    "iso:country": "US",
    "sg:address": "4216 Milan Rd",
    "sg:city": "Sandusky",
    "sg:classifiers": [
      {
        "category": "Professional",
        "type": "Services"
      }
    ],
    "sg:phone": "+1 419 609 1042",
    "sg:postcode": "44870",
    "sg:province": "OH",
    "sg:tags": [
      "establishment"
    ],
    "wof:name": "Ideal Co",
    "wof:placetype": "venue"
  },
  "geometry": {"coordinates":[-82.672768,41.416907],"type":"Point"}
}
