{
  "type": "Feature",
  "properties": {
    "iso:country":"US",
    "sg:address":"4880 Dexter Falls Rd",
    "sg:city":"Columbus",
    "sg:classifiers":[
        {
            "category":"Shopping",
            "subcategory":"Computers & Home Electronics",
            "type":"Retail Goods"
        }
    ],
    "sg:phone":"+1 614 876 1999",
    "sg:postcode":"43221",
    "sg:province":"OH",
    "wof:name":"Systems Integrators Inc",
    "wof:placetype":"venue"
},
  "geometry": {"coordinates":[-83.115026,40.053934],"type":"Point"}
}