{
  "type": "Feature",
  "properties": {
    "addr:full": "6050 Hi Tek Ct Mason OH 45040",
    "addr:housenumber": "6050",
    "addr:postcode": "45040",
    "addr:street": "Hi Tek Ct",
    "iso:country": "US",
    "sg:address": "6050 Hi Tek Ct",
    "sg:city": "Mason",
    "sg:classifiers": [
      {
        "category": "Manufacturing",
        "subcategory": "Tools \u0026 Machinery",
        "type": "Manufacturing \u0026 Wholesale Goods"
      }
    ],
    "sg:phone": "+1 513 459 1094",
    "sg:postcode": "45040",
    "sg:province": "OH",
    "sg:tags": [
      "repair",
      "industrial",
      "mfg",
      "aircraft",
      "en",
      "welding"
    ],
    "sg:website": "www.hitekmfg.com",
    "wof:name": "Hi-Tek Manufacturing Inc",
    "wof:placetype": "venue"
  },
  "geometry": {"coordinates":[-84.330612,39.339831],"type":"Point"}
}
