{
  "type": "Feature",
  "properties": {
    "addr:full": "2550 Cherry St Toledo OH 43608",
    "addr:housenumber": "2550",
    "addr:postcode": "43608",
    "addr:street": "Cherry St",
    "iso:country": "US",
    "sg:address": "2550 Cherry St",
    "sg:city": "Toledo",
    "sg:classifiers": [
      {
        "category": "Education",
        "subcategory": "School",
        "type": "Public Place"
      }
    ],
    "sg:phone": "+1 419 255 2280",
    "sg:postcode": "43608",
    "sg:province": "OH",
    "sg:website": "www.centralcatholic.org",
    "wof:name": "Central Catholic High School",
    "wof:placetype": "venue"
  },
  "geometry": {"coordinates":[-83.54501,41.672493],"type":"Point"}
}
