{
  "type": "Feature",
  "properties": {
    "addr:full":"250 E 5th St Cincinnati OH 45202",
    "addr:housenumber":"250",
    "addr:postcode":"45202",
    "addr:street":"E 5Th St",
    "iso:country":"US",
    "sg:address":"250 E 5th St",
    "sg:city":"Cincinnati",
    "sg:classifiers":[
        {
            "category":"Banks & Credit Unions",
            "subcategory":"Investment Brokerage",
            "type":"Services"
        },
        {
            "category":"Banks & Credit Unions",
            "subcategory":"Financial Services",
            "type":"Services"
        }
    ],
    "sg:phone":"+1 513 723 2300",
    "sg:postcode":"45202",
    "sg:province":"OH",
    "sg:tags":[
        "investor"
    ],
    "sg:website":"www.bcvc.com",
    "wof:name":"Blue Chip Venture Company",
    "wof:placetype":"venue"
},
  "geometry": {"coordinates":[-84.508324,39.101923],"type":"Point"}
}