{
  "type": "Feature",
  "properties": {
    "addr:full": "7878 Olentangy River Rd Columbus OH 43235",
    "addr:housenumber": "7878",
    "addr:postcode": "43235",
    "addr:street": "Olentangy River Rd",
    "iso:country": "US",
    "sg:address": "7878 Olentangy River Rd",
    "sg:city": "Columbus",
    "sg:classifiers": [
      {
        "category": "Building \u0026 Trades",
        "subcategory": "Construction",
        "type": "Services"
      }
    ],
    "sg:phone": "+1 614 888 6382",
    "sg:postcode": "43235",
    "sg:province": "OH",
    "wof:name": "American Water Works Company",
    "wof:placetype": "venue"
  },
  "geometry": {"coordinates":[-83.036696,40.12507],"type":"Point"}
}
