{
  "type": "Feature",
  "properties": {
    "iso:country":"US",
    "sg:address":"7878 Olentangy River Rd",
    "sg:city":"Columbus",
    "sg:classifiers":[
        {
            "category":"Building & Trades",
            "subcategory":"Construction",
            "type":"Services"
        }
    ],
    "sg:phone":"+1 614 888 6382",
    "sg:postcode":"43235",
    "sg:province":"OH",
    "wof:name":"American Water Works Company",
    "wof:placetype":"venue"
},
  "geometry": {"coordinates":[-83.03669600000001,40.12507],"type":"Point"}
}