{
  "type": "Feature",
  "properties": {
    "addr:full": "1756 Moore Rd Avon OH 44011",
    "addr:housenumber": "1756",
    "addr:postcode": "44011",
    "addr:street": "Moore Rd",
    "iso:country": "US",
    "sg:address": "1756 Moore Rd",
    "sg:city": "Avon",
    "sg:classifiers": [
      {
        "category": "Building \u0026 Trades",
        "subcategory": "Construction",
        "type": "Services"
      }
    ],
    "sg:phone": "+1 440 934 2385",
    "sg:postcode": "44011",
    "sg:province": "OH",
    "sg:tags": [
      "planning",
      "remodeling",
      "kitchen"
    ],
    "wof:name": "Caruso's Kitchen Design Ctr",
    "wof:placetype": "venue"
  },
  "geometry": {"coordinates":[-82.047975,41.463307],"type":"Point"}
}
