{
  "type": "Feature",
  "properties": {
    "iso:country":"US",
    "sg:address":"1756 Moore Rd",
    "sg:city":"Avon",
    "sg:classifiers":[
        {
            "category":"Building & Trades",
            "subcategory":"Construction",
            "type":"Services"
        }
    ],
    "sg:phone":"+1 440 934 2385",
    "sg:postcode":"44011",
    "sg:province":"OH",
    "sg:tags":[
        "planning",
        "remodeling",
        "kitchen"
    ],
    "wof:name":"Caruso's Kitchen Design Ctr",
    "wof:placetype":"venue"
},
  "geometry": {"coordinates":[-82.04797499999999,41.463307],"type":"Point"}
}