{
  "type": "Feature",
  "properties": {
    "addr:full": "400 Lexington Ave Mansfield OH 44907",
    "addr:housenumber": "400",
    "addr:postcode": "44907",
    "addr:street": "Lexington Ave",
    "iso:country": "US",
    "sg:address": "400 Lexington Ave",
    "sg:city": "Mansfield",
    "sg:classifiers": [
      {
        "category": "Professional",
        "subcategory": "Accounting \u0026 Tax Preparation",
        "type": "Services"
      }
    ],
    "sg:phone": "+1 419 529 8934",
    "sg:postcode": "44907",
    "sg:province": "OH",
    "sg:tags": [
      "accountant"
    ],
    "wof:name": "Wayne R Winnett CPA",
    "wof:placetype": "venue"
  },
  "geometry": {"coordinates":[-82.524775,40.74383],"type":"Point"}
}
