{
  "type": "Feature",
  "properties": {
    "iso:country":"US",
    "sg:address":"400 Lexington Ave",
    "sg:city":"Mansfield",
    "sg:classifiers":[
        {
            "category":"Professional",
            "subcategory":"Accounting & Tax Preparation",
            "type":"Services"
        }
    ],
    "sg:phone":"+1 419 529 8934",
    "sg:postcode":"44907",
    "sg:province":"OH",
    "sg:tags":[
        "accountant"
    ],
    "wof:name":"Wayne R Winnett CPA",
    "wof:placetype":"venue"
},
  "geometry": {"coordinates":[-82.52477500000001,40.74383],"type":"Point"}
}