{
  "type": "Feature",
  "properties": {
    "iso:country":"US",
    "sg:address":"2687 E 5th Ave",
    "sg:city":"Columbus",
    "sg:classifiers":[
        {
            "category":"Building & Trades",
            "subcategory":"Plumbing",
            "type":"Services"
        }
    ],
    "sg:phone":"+1 614 252 4955",
    "sg:postcode":"43219",
    "sg:province":"OH",
    "sg:tags":[
        "air",
        "heating",
        "conditioning",
        "contractor"
    ],
    "wof:name":"Charlie Krumm Heating & Coolg",
    "wof:placetype":"venue"
},
  "geometry": {"coordinates":[-82.93232,39.985081],"type":"Point"}
}