{
  "type": "Feature",
  "properties": {
    "addr:full": "895 Parsons Ave Columbus OH 43206",
    "addr:housenumber": "895",
    "addr:postcode": "43206",
    "addr:street": "Parsons Ave",
    "iso:country": "US",
    "sg:address": "895 Parsons Ave",
    "sg:city": "Columbus",
    "sg:classifiers": [
      {
        "category": "Retail",
        "subcategory": "Self-service Laundry",
        "type": "Services"
      }
    ],
    "sg:phone": "+1 614 443 2901",
    "sg:postcode": "43206",
    "sg:province": "OH",
    "wof:name": "Clean Machine",
    "wof:placetype": "venue"
  },
  "geometry": {"coordinates":[-82.982959,39.945268],"type":"Point"}
}
