{
  "type": "Feature",
  "properties": {
    "addr:full": "3429 E Brainard Rd Beachwood OH 44122",
    "addr:housenumber": "3429",
    "addr:postcode": "44122",
    "addr:street": "E Brainard Rd",
    "iso:country": "US",
    "sg:address": "3429 E Brainard Rd",
    "sg:city": "Beachwood",
    "sg:classifiers": [
      {
        "category": "Banks \u0026 Credit Unions",
        "subcategory": "Financial Services",
        "type": "Services"
      }
    ],
    "sg:phone": "+1 216 292 6344",
    "sg:postcode": "44122",
    "sg:province": "OH",
    "sg:tags": [
      "broker",
      "mortgage"
    ],
    "wof:name": "Allfund Mortgage Inc",
    "wof:placetype": "venue"
  },
  "geometry": {"coordinates":[-81.480771,41.462747],"type":"Point"}
}
