{
  "type": "Feature",
  "properties": {
    "iso:country":"US",
    "sg:address":"1979 E 55th St",
    "sg:city":"Cleveland",
    "sg:classifiers":[
        {
            "category":"Professional",
            "subcategory":"Computer Services",
            "type":"Services"
        }
    ],
    "sg:phone":"+1 216 881 8156",
    "sg:postcode":"44103",
    "sg:province":"OH",
    "sg:tags":[
        "internet"
    ],
    "wof:name":"Inner City On Line",
    "wof:placetype":"venue"
},
  "geometry": {"coordinates":[-81.651749,41.504388],"type":"Point"}
}