{
  "type": "Feature",
  "properties": {
    "addr:full": "1651 E 71st St Cleveland OH 44103",
    "addr:housenumber": "1651",
    "addr:postcode": "44103",
    "addr:street": "E 71St St",
    "iso:country": "US",
    "sg:address": "1651 E 71st St",
    "sg:city": "Cleveland",
    "sg:classifiers": [
      {
        "category": "Education",
        "subcategory": "School",
        "type": "Public Place"
      }
    ],
    "sg:phone": "+1 216 431 6858",
    "sg:postcode": "44103",
    "sg:province": "OH",
    "sg:tags": [
      "middle"
    ],
    "sg:website": "http://www.cmsdnet.net",
    "wof:name": "Martin Luther King Middle School",
    "wof:placetype": "venue"
  },
  "geometry": {"coordinates":[-81.639572,41.509746],"type":"Point"}
}
