{
  "type": "Feature",
  "properties": {
    "addr:full": "1011 Dover Ave Dover OH 44622",
    "addr:housenumber": "1011",
    "addr:postcode": "44622",
    "addr:street": "Dover Ave",
    "iso:country": "US",
    "sg:address": "1011 Dover Ave",
    "sg:city": "Dover",
    "sg:classifiers": [
      {
        "category": "Health Services",
        "subcategory": "Chiropractor",
        "type": "Services"
      }
    ],
    "sg:phone": "+1 330 602 7105",
    "sg:postcode": "44622",
    "sg:province": "OH",
    "wof:name": "Dover Chiropractic",
    "wof:placetype": "venue"
  },
  "geometry": {"coordinates":[-81.4841,40.52936],"type":"Point"}
}
