{
  "type": "Feature",
  "properties": {
    "addr:full":"1201 Taylor St Elyria OH 44035",
    "addr:housenumber":"1201",
    "addr:postcode":"44035",
    "addr:street":"Taylor St",
    "iso:country":"US",
    "sg:address":"1201 Taylor St",
    "sg:city":"Elyria",
    "sg:classifiers":[
        {
            "category":"Banks & Credit Unions",
            "subcategory":"Financial Services",
            "type":"Services"
        }
    ],
    "sg:phone":"+1 440 366 5592",
    "sg:postcode":"44035",
    "sg:province":"OH",
    "sg:tags":[
        "investor"
    ],
    "wof:name":"Jfc Capital Inc",
    "wof:placetype":"venue"
},
  "geometry": {"coordinates":[-82.07311799999999,41.371573],"type":"Point"}
}