{
  "type": "Feature",
  "properties": {
    "iso:country":"US",
    "sg:address":"51 N High St",
    "sg:city":"Columbus",
    "sg:classifiers":[
        {
            "category":"Professional",
            "subcategory":"Lawyer & Legal Services",
            "type":"Services"
        }
    ],
    "sg:phone":"+1 614 846 7160",
    "sg:postcode":"43215",
    "sg:province":"OH",
    "sg:tags":[
        "attorney"
    ],
    "wof:name":"Steve C Carr",
    "wof:placetype":"venue"
},
  "geometry": {"coordinates":[-83.000908,39.963082],"type":"Point"}
}