{
  "type": "Feature",
  "properties": {
    "addr:full": "3747 Dover Rd Wooster OH 44691",
    "addr:housenumber": "3747",
    "addr:postcode": "44691",
    "addr:street": "Dover Rd",
    "iso:country": "US",
    "sg:address": "3747 Dover Rd",
    "sg:city": "Wooster",
    "sg:classifiers": [
      {
        "category": "Freight",
        "type": "Transportation"
      }
    ],
    "sg:phone": "+1 330 264 1219",
    "sg:postcode": "44691",
    "sg:province": "OH",
    "sg:tags": [
      "farm",
      "crop",
      "trucking",
      "operator",
      "general",
      "local"
    ],
    "wof:name": "Myers Farming",
    "wof:placetype": "venue"
  },
  "geometry": {"coordinates":[-81.894171,40.762745],"type":"Point"}
}
