{
  "type": "Feature",
  "properties": {
    "addr:full":"22380 Hammansburg Rd Deshler OH 43516",
    "addr:housenumber":"22380",
    "addr:postcode":"43516",
    "addr:street":"Hammansburg Rd",
    "iso:country":"US",
    "sg:address":"22380 Hammansburg Rd",
    "sg:city":"Deshler",
    "sg:phone":"+1 419 278 6835",
    "sg:postcode":"43516",
    "sg:province":"OH",
    "sg:tags":[
        "farm",
        "grain",
        "cash"
    ],
    "wof:name":"David L Baer Farm",
    "wof:placetype":"venue"
},
  "geometry": {"coordinates":[-83.830868,41.2264],"type":"Point"}
}