{
  "type": "Feature",
  "properties": {
    "addr:full":"1623 Co Rd 19 Mingo Junction OH 43938",
    "addr:housenumber":"1623;19",
    "addr:postcode":"43938",
    "addr:street":"Co Rd",
    "iso:country":"US",
    "sg:address":"1623 Co Rd 19",
    "sg:city":"Mingo Junction",
    "sg:classifiers":[
        {
            "category":"Building & Trades",
            "subcategory":"Construction",
            "type":"Services"
        }
    ],
    "sg:phone":"+1 740 598 3033",
    "sg:postcode":"43938",
    "sg:province":"OH",
    "sg:tags":[
        "downspouts",
        "gutter",
        "contractor"
    ],
    "wof:name":"Seamless Gutters & Accessories",
    "wof:placetype":"venue"
},
  "geometry": {"coordinates":[-80.65424,40.289724],"type":"Point"}
}