{
  "type": "Feature",
  "properties": {
    "addr:full": "478 Crabtree Rd Jackson OH 45640",
    "addr:housenumber": "478",
    "addr:postcode": "45640",
    "addr:street": "Crabtree Rd",
    "iso:country": "US",
    "sg:address": "478 Crabtree Rd",
    "sg:city": "Jackson",
    "sg:classifiers": [
      {
        "category": "Building \u0026 Trades",
        "subcategory": "Construction",
        "type": "Services"
      }
    ],
    "sg:phone": "+1 740 820 3461",
    "sg:postcode": "45640",
    "sg:province": "OH",
    "sg:tags": [
      "heavy"
    ],
    "wof:name": "Dale Phipps",
    "wof:placetype": "venue"
  },
  "geometry": {"coordinates":[-82.781969,38.954352],"type":"Point"}
}
