{
  "type": "Feature",
  "properties": {
    "addr:full":"165 W Galbraith Rd Cincinnati OH 45216",
    "addr:housenumber":"165",
    "addr:postcode":"45216",
    "addr:street":"W Galbraith Rd",
    "iso:country":"US",
    "sg:address":"165 W Galbraith Rd",
    "sg:city":"Cincinnati",
    "sg:classifiers":[
        {
            "category":"Social Services",
            "subcategory":"Adult Care",
            "type":"Services"
        }
    ],
    "sg:phone":"+1 513 948 4370",
    "sg:postcode":"45216",
    "sg:province":"OH",
    "sg:tags":[
        "residential"
    ],
    "sg:website":"www.bridgewaypointe.org",
    "wof:name":"Bridgeway Pointe",
    "wof:placetype":"venue"
},
  "geometry": {"coordinates":[-84.48275099999999,39.213792],"type":"Point"}
}