{
  "type": "Feature",
  "properties": {
    "addr:full":"2969 Manchester Rd Cleveland OH 44122",
    "addr:housenumber":"2969",
    "addr:postcode":"44122",
    "addr:street":"Manchester Rd",
    "iso:country":"US",
    "sg:address":"2969 Manchester Rd",
    "sg:city":"Cleveland",
    "sg:classifiers":[
        {
            "category":"Organizations",
            "subcategory":"Religious Organization",
            "type":"Services"
        }
    ],
    "sg:phone":"+1 216 283 5335",
    "sg:postcode":"44122",
    "sg:province":"OH",
    "sg:tags":[
        "clergy"
    ],
    "wof:name":"Sarah Sager",
    "wof:placetype":"venue"
},
  "geometry": {"coordinates":[-81.545918,41.47584],"type":"Point"}
}