{
  "type": "Feature",
  "properties": {
    "addr:full": "3587 E Livingston Ave Columbus OH 43227",
    "addr:housenumber": "3587",
    "addr:postcode": "43227",
    "addr:street": "E Livingston Ave",
    "iso:country": "US",
    "sg:address": "3587 E Livingston Ave",
    "sg:city": "Columbus",
    "sg:classifiers": [
      {
        "category": "Recreation",
        "type": "Entertainment"
      }
    ],
    "sg:phone": "+1 614 231 0533",
    "sg:postcode": "43227",
    "sg:province": "OH",
    "sg:tags": [
      "bingo",
      "game"
    ],
    "wof:name": "Livingston Court Bingo",
    "wof:placetype": "venue"
  },
  "geometry": {"coordinates":[-82.899677,39.945938],"type":"Point"}
}
