{
  "type": "Feature",
  "properties": {
    "addr:full": "144 Merchant St Cincinnati OH 45246",
    "addr:housenumber": "144",
    "addr:postcode": "45246",
    "addr:street": "Merchant St",
    "iso:country": "US",
    "sg:address": "144 Merchant St",
    "sg:city": "Cincinnati",
    "sg:classifiers": [
      {
        "category": "Organizations",
        "subcategory": "Professional Association",
        "type": "Services"
      }
    ],
    "sg:phone": "+1 513 674 0555",
    "sg:postcode": "45246",
    "sg:province": "OH",
    "wof:name": "Association Of Luxury Suite",
    "wof:placetype": "venue"
  },
  "geometry": {"coordinates":[-84.473613,39.280502],"type":"Point"}
}
