{
  "type": "Feature",
  "properties": {
    "addr:full":"15833 US Rte 33 Wapakoneta OH 45895",
    "addr:housenumber":"15833",
    "addr:postcode":"45895",
    "addr:street":"Us Rte 33",
    "iso:country":"US",
    "sg:address":"15833 US Rte 33",
    "sg:city":"Wapakoneta",
    "sg:classifiers":[
        {
            "category":"Wholesale",
            "subcategory":"Groceries",
            "type":"Manufacturing & Wholesale Goods"
        }
    ],
    "sg:phone":"+1 419 738 4391",
    "sg:postcode":"45895",
    "sg:province":"OH",
    "sg:tags":[
        "food",
        "product",
        "health"
    ],
    "wof:name":"Herron's Herb Shoppe",
    "wof:placetype":"venue"
},
  "geometry": {"coordinates":[-84.14592,40.555758],"type":"Point"}
}