{
  "type": "Feature",
  "properties": {
    "addr:full": "547 W 2nd St Xenia OH 45385",
    "addr:housenumber": "547",
    "addr:postcode": "45385",
    "addr:street": "W 2Nd St",
    "iso:country": "US",
    "sg:address": "547 W 2nd St",
    "sg:city": "Xenia",
    "sg:classifiers": [
      {
        "category": "Home \u0026 Garden",
        "subcategory": "Garden Supply",
        "type": "Retail Goods"
      }
    ],
    "sg:phone": "+1 937 372 5552",
    "sg:postcode": "45385",
    "sg:province": "OH",
    "sg:tags": [
      "operator",
      "building",
      "commercial",
      "center"
    ],
    "wof:name": "Kennedys Garden Center",
    "wof:placetype": "venue"
  },
  "geometry": {"coordinates":[-83.938409,39.682925],"type":"Point"}
}
