{
  "type": "Feature",
  "properties": {
    "addr:full":"12900 Tinkers Creek Rd Cleveland OH 44125",
    "addr:postcode":"12900;44125",
    "addr:street":"Tinkers Creek Rd",
    "iso:country":"US",
    "sg:address":"12900 Tinkers Creek Rd",
    "sg:city":"Cleveland",
    "sg:classifiers":[
        {
            "category":"Restaurant",
            "type":"Food & Drink"
        }
    ],
    "sg:phone":"+1 216 524 7086",
    "sg:postcode":"44125",
    "sg:province":"OH",
    "sg:tags":[
        "banquet",
        "rooms"
    ],
    "wof:name":"Sherwood Forest Party Ctr",
    "wof:placetype":"venue"
},
  "geometry": {"coordinates":[-81.600516,41.367834],"type":"Point"}
}