{
  "type": "Feature",
  "properties": {
    "iso:country":"US",
    "sg:address":"7730 Jefferson Rd",
    "sg:city":"Ashtabula",
    "sg:classifiers":[
        {
            "category":"Professional",
            "type":"Services"
        }
    ],
    "sg:phone":"+1 440 997 9448",
    "sg:postcode":"44004",
    "sg:province":"OH",
    "wof:name":"Mokri Motorsports",
    "wof:placetype":"venue"
},
  "geometry": {"coordinates":[-80.78531700000001,41.834179],"type":"Point"}
}