{
  "type": "Feature",
  "properties": {
    "iso:country":"US",
    "sg:address":"6865 Amherst Dr",
    "sg:city":"Northfield",
    "sg:classifiers":[
        {
            "category":"Education",
            "subcategory":"Special Training",
            "type":"Public Place"
        }
    ],
    "sg:phone":"+1 330 467 2629",
    "sg:postcode":"44067",
    "sg:province":"OH",
    "sg:tags":[
        "continuing",
        "nursing"
    ],
    "wof:name":"Ed 4 Nurses Inc",
    "wof:placetype":"venue"
},
  "geometry": {"coordinates":[-81.569615,41.3129],"type":"Point"}
}