{
  "type": "Feature",
  "properties": {
    "addr:full": "3002 S 11th St Ironton OH 45638",
    "addr:housenumber": "3002",
    "addr:postcode": "45638",
    "addr:street": "S 11Th St",
    "iso:country": "US",
    "sg:address": "3002 S 11th St",
    "sg:city": "Ironton",
    "sg:classifiers": [
      {
        "category": "Personal",
        "subcategory": "Beauty Salon",
        "type": "Services"
      }
    ],
    "sg:phone": "+1 740 532 2565",
    "sg:postcode": "45638",
    "sg:province": "OH",
    "wof:name": "Brenda's Styling \u0026 Tanning",
    "wof:placetype": "venue"
  },
  "geometry": {"coordinates":[-82.655234,38.512426],"type":"Point"}
}
