{
  "type": "Feature",
  "properties": {
    "addr:full":"1120 W High St Bryan OH 43506",
    "addr:housenumber":"1120",
    "addr:postcode":"43506",
    "addr:street":"W High St",
    "iso:country":"US",
    "sg:address":"1120 W High St",
    "sg:city":"Bryan",
    "sg:classifiers":[
        {
            "category":"Government",
            "subcategory":"Office",
            "type":"Public Place"
        }
    ],
    "sg:phone":"+1 419 636 9395",
    "sg:postcode":"43506",
    "sg:province":"OH",
    "wof:name":"Williams County Soil & Water",
    "wof:placetype":"venue"
},
  "geometry": {"coordinates":[-84.567674,41.47462],"type":"Point"}
}