{
  "type": "Feature",
  "properties": {
    "addr:full": "12437 Indian Hollow Rd Grafton OH 44044",
    "addr:housenumber": "12437",
    "addr:postcode": "44044",
    "addr:street": "Indian Hollow Rd",
    "iso:country": "US",
    "sg:address": "12437 Indian Hollow Rd",
    "sg:city": "Grafton",
    "sg:classifiers": [
      {
        "category": "Banks \u0026 Credit Unions",
        "subcategory": "Financial Services",
        "type": "Services"
      }
    ],
    "sg:phone": "+1 440 458 4406",
    "sg:postcode": "44044",
    "sg:province": "OH",
    "sg:tags": [
      "trust",
      "management"
    ],
    "wof:name": "Hovatter Family Trust",
    "wof:placetype": "venue"
  },
  "geometry": {"coordinates":[-82.087164,41.303606],"type":"Point"}
}
