{
  "type": "Feature",
  "properties": {
    "iso:country":"US",
    "sg:address":"228 Byers Rd",
    "sg:city":"Miamisburg",
    "sg:classifiers":[
        {
            "category":"Manufacturing",
            "subcategory":"Tools & Machinery",
            "type":"Manufacturing & Wholesale Goods"
        }
    ],
    "sg:phone":"+1 937 865 5217",
    "sg:postcode":"45342",
    "sg:province":"OH",
    "sg:tags":[
        "equipment",
        "system",
        "automation"
    ],
    "wof:name":"Corporate Automation",
    "wof:placetype":"venue"
},
  "geometry": {"coordinates":[-84.234411,39.638734],"type":"Point"}
}