{
  "type": "Feature",
  "properties": {
    "addr:full": "228 Byers Rd Miamisburg OH 45342",
    "addr:housenumber": "228",
    "addr:postcode": "45342",
    "addr:street": "Byers Rd",
    "iso:country": "US",
    "sg:address": "228 Byers Rd",
    "sg:city": "Miamisburg",
    "sg:classifiers": [
      {
        "category": "Manufacturing",
        "subcategory": "Tools \u0026 Machinery",
        "type": "Manufacturing \u0026 Wholesale Goods"
      }
    ],
    "sg:phone": "+1 937 865 5217",
    "sg:postcode": "45342",
    "sg:province": "OH",
    "sg:tags": [
      "equipment",
      "system",
      "automation"
    ],
    "wof:name": "Corporate Automation",
    "wof:placetype": "venue"
  },
  "geometry": {"coordinates":[-84.234411,39.638734],"type":"Point"}
}
