{
  "type": "Feature",
  "properties": {
    "iso:country":"US",
    "sg:address":"995 High St",
    "sg:city":"Wadsworth",
    "sg:classifiers":[
        {
            "category":"Banks & Credit Unions",
            "subcategory":"Bank",
            "type":"Services"
        }
    ],
    "sg:phone":"+1 330 334 3060",
    "sg:postcode":"44281",
    "sg:province":"OH",
    "sg:tags":[
        "cashing",
        "check"
    ],
    "wof:name":"Check 'n Go",
    "wof:placetype":"venue"
},
  "geometry": {"coordinates":[-81.72881599999999,41.050267],"type":"Point"}
}