{
  "type": "Feature",
  "properties": {
    "addr:full": "995 High St Wadsworth OH 44281",
    "addr:housenumber": "995",
    "addr:postcode": "44281",
    "addr:street": "High St",
    "iso:country": "US",
    "sg:address": "995 High St",
    "sg:city": "Wadsworth",
    "sg:classifiers": [
      {
        "category": "Banks \u0026 Credit Unions",
        "subcategory": "Bank",
        "type": "Services"
      }
    ],
    "sg:phone": "+1 330 334 3060",
    "sg:postcode": "44281",
    "sg:province": "OH",
    "sg:tags": [
      "cashing",
      "check"
    ],
    "wof:name": "Check 'n Go",
    "wof:placetype": "venue"
  },
  "geometry": {"coordinates":[-81.728816,41.050267],"type":"Point"}
}
