{
  "type": "Feature",
  "properties": {
    "addr:full": "3181 Linwood Ave Cincinnati OH 45208",
    "addr:housenumber": "3181",
    "addr:postcode": "45208",
    "addr:street": "Linwood Ave",
    "iso:country": "US",
    "sg:address": "3181 Linwood Ave",
    "sg:city": "Cincinnati",
    "sg:classifiers": [
      {
        "category": "Health Services",
        "subcategory": "Nursing And Care Facility",
        "type": "Services"
      }
    ],
    "sg:phone": "+1 513 533 0880",
    "sg:postcode": "45208",
    "sg:province": "OH",
    "sg:tags": [
      "skilled"
    ],
    "wof:name": "Absolute Nursing",
    "wof:placetype": "venue"
  },
  "geometry": {"coordinates":[-84.430402,39.128539],"type":"Point"}
}
