{
  "type": "Feature",
  "properties": {
    "iso:country":"US",
    "sg:address":"10323 Fremont Pike",
    "sg:city":"Perrysburg",
    "sg:classifiers":[
        {
            "category":"Shopping",
            "subcategory":"Department Store",
            "type":"Retail Goods"
        }
    ],
    "sg:phone":"+1 419 874 4407",
    "sg:postcode":"43551",
    "sg:province":"OH",
    "sg:website":"www.kohls.com",
    "wof:name":"Kohl's",
    "wof:placetype":"venue"
},
  "geometry": {"coordinates":[-83.595338,41.546864],"type":"Point"}
}