{
  "type": "Feature",
  "properties": {
    "addr:full": "94 Northwoods Blvd Columbus OH 43235",
    "addr:housenumber": "94",
    "addr:postcode": "43235",
    "addr:street": "Northwoods Blvd",
    "iso:country": "US",
    "sg:address": "94 Northwoods Blvd",
    "sg:city": "Columbus",
    "sg:classifiers": [
      {
        "category": "Professional",
        "type": "Services"
      }
    ],
    "sg:phone": "+1 614 847 8208",
    "sg:postcode": "43235",
    "sg:province": "OH",
    "sg:tags": [
      "establishment"
    ],
    "wof:name": "Rexam Metallizing",
    "wof:placetype": "venue"
  },
  "geometry": {"coordinates":[-83.019106,40.128823],"type":"Point"}
}
