{
  "type": "Feature",
  "properties": {
    "addr:full": "623 S 2nd St Ripley OH 45167",
    "addr:housenumber": "623",
    "addr:postcode": "45167",
    "addr:street": "S 2Nd St",
    "iso:country": "US",
    "sg:address": "623 S 2nd St",
    "sg:city": "Ripley",
    "sg:classifiers": [
      {
        "category": "Freight",
        "type": "Transportation"
      }
    ],
    "sg:phone": "+1 937 392 4365",
    "sg:postcode": "45167",
    "sg:province": "OH",
    "sg:tags": [
      "warehouse",
      "tobacco"
    ],
    "wof:name": "New Farmers Union Warehouse",
    "wof:placetype": "venue"
  },
  "geometry": {"coordinates":[-83.83967,38.736087],"type":"Point"}
}
