{
  "type": "Feature",
  "properties": {
    "addr:full": "2000 Highland Rd Twinsburg OH 44087",
    "addr:housenumber": "2000",
    "addr:postcode": "44087",
    "addr:street": "Highland Rd",
    "iso:country": "US",
    "sg:address": "2000 Highland Rd",
    "sg:city": "Twinsburg",
    "sg:classifiers": [
      {
        "category": "Utilities",
        "subcategory": "Telephone",
        "type": "Services"
      }
    ],
    "sg:phone": "+1 330 963 1300",
    "sg:postcode": "44087",
    "sg:province": "OH",
    "sg:tags": [
      "communications",
      "computer",
      "programing",
      "custom"
    ],
    "wof:name": "Alltel",
    "wof:placetype": "venue"
  },
  "geometry": {"coordinates":[-81.450403,41.297676],"type":"Point"}
}
