{
  "type": "Feature",
  "properties": {
    "addr:full": "570 White Pond Dr Akron OH 44320",
    "addr:housenumber": "570",
    "addr:postcode": "44320",
    "addr:street": "White Pond Dr",
    "iso:country": "US",
    "sg:address": "570 White Pond Dr",
    "sg:city": "Akron",
    "sg:classifiers": [
      {
        "category": "Health Services",
        "subcategory": "Doctor",
        "type": "Services"
      }
    ],
    "sg:phone": "+1 330 869 0954",
    "sg:postcode": "44320",
    "sg:province": "OH",
    "sg:tags": [
      "physician",
      "surgeon"
    ],
    "wof:name": "Gastroenterology Group Inc",
    "wof:placetype": "venue"
  },
  "geometry": {"coordinates":[-81.586353,41.101824],"type":"Point"}
}
