{
  "type": "Feature",
  "properties": {
    "addr:full": "6135 Kruse Dr Solon OH 44139",
    "addr:housenumber": "6135",
    "addr:postcode": "44139",
    "addr:street": "Kruse Dr",
    "iso:country": "US",
    "sg:address": "6135 Kruse Dr",
    "sg:city": "Solon",
    "sg:classifiers": [
      {
        "category": "Autos \u0026 Motor Vehicles",
        "subcategory": "Automobile Sales",
        "type": "Retail Goods"
      },
      {
        "category": "Retail",
        "subcategory": "Auto Repair",
        "type": "Services"
      }
    ],
    "sg:phone": "+1 440 542 0602",
    "sg:postcode": "44139",
    "sg:province": "OH",
    "sg:tags": [
      "car"
    ],
    "sg:website": "www.landroversolon.com",
    "wof:name": "Land Rover Solon",
    "wof:placetype": "venue"
  },
  "geometry": {"coordinates":[-81.440903,41.392101],"type":"Point"}
}
