{
  "type": "Feature",
  "properties": {
    "iso:country":"US",
    "sg:address":"6135 Kruse Dr",
    "sg:city":"Solon",
    "sg:classifiers":[
        {
            "category":"Autos & Motor Vehicles",
            "subcategory":"Automobile Sales",
            "type":"Retail Goods"
        },
        {
            "category":"Retail",
            "subcategory":"Auto Repair",
            "type":"Services"
        }
    ],
    "sg:phone":"+1 440 542 0602",
    "sg:postcode":"44139",
    "sg:province":"OH",
    "sg:tags":[
        "car"
    ],
    "sg:website":"www.landroversolon.com",
    "wof:name":"Land Rover Solon",
    "wof:placetype":"venue"
},
  "geometry": {"coordinates":[-81.44090300000001,41.392101],"type":"Point"}
}