{
  "type": "Feature",
  "properties": {
    "addr:full": "226 Flint Dr Chillicothe OH 45601",
    "addr:housenumber": "226",
    "addr:postcode": "45601",
    "addr:street": "Flint Dr",
    "iso:country": "US",
    "sg:address": "226 Flint Dr",
    "sg:city": "Chillicothe",
    "sg:classifiers": [
      {
        "category": "Building \u0026 Trades",
        "subcategory": "Construction",
        "type": "Services"
      }
    ],
    "sg:phone": "+1 740 772 4979",
    "sg:postcode": "45601",
    "sg:province": "OH",
    "sg:tags": [
      "house"
    ],
    "wof:name": "Clearview Home Improvements",
    "wof:placetype": "venue"
  },
  "geometry": {"coordinates":[-83.077066,39.362866],"type":"Point"}
}
