{
  "type": "Feature",
  "properties": {
    "iso:country":"US",
    "sg:address":"509 W McPherson Hwy",
    "sg:city":"Clyde",
    "sg:classifiers":[
        {
            "category":"Health Services",
            "subcategory":"Health Practitioner",
            "type":"Services"
        }
    ],
    "sg:phone":"+1 419 547 0524",
    "sg:postcode":"43410",
    "sg:province":"OH",
    "sg:tags":[
        "therapist",
        "physical"
    ],
    "wof:name":"Memorial Hospital Physical",
    "wof:placetype":"venue"
},
  "geometry": {"coordinates":[-82.984674,41.31258],"type":"Point"}
}