{
  "type": "Feature",
  "properties": {
    "iso:country":"US",
    "sg:address":"64 E Broad St",
    "sg:city":"Columbus",
    "sg:classifiers":[
        {
            "category":"Home & Garden",
            "subcategory":"Building Materials",
            "type":"Retail Goods"
        }
    ],
    "sg:phone":"+1 614 280 0772",
    "sg:postcode":"43215",
    "sg:province":"OH",
    "wof:name":"Owens Corning",
    "wof:placetype":"venue"
},
  "geometry": {"coordinates":[-82.998665,39.962491],"type":"Point"}
}