{
  "type": "Feature",
  "properties": {
    "addr:full":"9687 Colerain Ave Cincinnati OH 45251",
    "addr:housenumber":"9687",
    "addr:postcode":"45251",
    "addr:street":"Colerain Ave",
    "iso:country":"US",
    "sg:address":"9687 Colerain Ave",
    "sg:city":"Cincinnati",
    "sg:classifiers":[
        {
            "category":"Organizations",
            "subcategory":"Membership Organization",
            "type":"Services"
        }
    ],
    "sg:phone":"+1 513 385 0909",
    "sg:postcode":"45251",
    "sg:province":"OH",
    "sg:tags":[
        "travel",
        "agency"
    ],
    "wof:name":"AAA World Wide Travel Agency",
    "wof:placetype":"venue"
},
  "geometry": {"coordinates":[-84.595799,39.245412],"type":"Point"}
}