{
  "type": "Feature",
  "properties": {
    "addr:full": "3064 Kent Rd Stow OH 44224",
    "addr:housenumber": "3064",
    "addr:postcode": "44224",
    "addr:street": "Kent Rd",
    "iso:country": "US",
    "sg:address": "3064 Kent Rd",
    "sg:city": "Stow",
    "sg:classifiers": [
      {
        "category": "Food \u0026 Beverages",
        "subcategory": "Specialty",
        "type": "Retail Goods"
      }
    ],
    "sg:phone": "+1 330 688 2515",
    "sg:postcode": "44224",
    "sg:province": "OH",
    "wof:name": "L S Paserba Enterprises",
    "wof:placetype": "venue"
  },
  "geometry": {"coordinates":[-81.449948,41.155437],"type":"Point"}
}
