{
  "type": "Feature",
  "properties": {
    "addr:full":"8075 Co Hwy 58 Upper Sandusky OH 43351",
    "addr:housenumber":"8075",
    "addr:postcode":"43351",
    "addr:street":"Co Hwy 58",
    "iso:country":"US",
    "sg:address":"8075 Co Hwy 58",
    "sg:city":"Upper Sandusky",
    "sg:classifiers":[
        {
            "category":"Building & Trades",
            "subcategory":"Construction",
            "type":"Services"
        }
    ],
    "sg:phone":"+1 419 294 3955",
    "sg:postcode":"43351",
    "sg:province":"OH",
    "sg:tags":[
        "general",
        "contractor"
    ],
    "wof:name":"Shields Contractors",
    "wof:placetype":"venue"
},
  "geometry": {"coordinates":[-83.26428,40.788932],"type":"Point"}
}