{
  "type": "Feature",
  "properties": {
    "addr:full": "1388 Lakewood Ave Cleveland OH 44107",
    "addr:housenumber": "1388",
    "addr:postcode": "44107",
    "addr:street": "Lakewood Ave",
    "iso:country": "US",
    "sg:address": "1388 Lakewood Ave",
    "sg:city": "Cleveland",
    "sg:classifiers": [
      {
        "category": "Building \u0026 Trades",
        "subcategory": "Construction",
        "type": "Services"
      }
    ],
    "sg:phone": "+1 216 221 6083",
    "sg:postcode": "44107",
    "sg:province": "OH",
    "sg:tags": [
      "hanging",
      "painter",
      "contractor"
    ],
    "wof:name": "Fresh Coat Painting",
    "wof:placetype": "venue"
  },
  "geometry": {"coordinates":[-81.776422,41.486215],"type":"Point"}
}
