{
  "type": "Feature",
  "properties": {
    "addr:full": "770 N Sharpsville Ave Sharon OH 16146",
    "addr:housenumber": "770",
    "addr:postcode": "16146",
    "addr:street": "N Sharpsville Ave",
    "iso:country": "US",
    "sg:address": "770 N Sharpsville Ave",
    "sg:city": "Sharon",
    "sg:classifiers": [
      {
        "category": "Retail",
        "subcategory": "Auto Repair",
        "type": "Services"
      }
    ],
    "sg:phone": "+1 724 342 7769",
    "sg:postcode": "16146",
    "sg:province": "OH",
    "sg:tags": [
      "automotive"
    ],
    "wof:name": "Arrow Automotive Inc",
    "wof:placetype": "venue"
  },
  "geometry": {"coordinates":[-80.503213,41.243138],"type":"Point"}
}
