{
  "type": "Feature",
  "properties": {
    "addr:full": "5661 Rapid Run Rd Cincinnati OH 45238",
    "addr:housenumber": "5661",
    "addr:postcode": "45238",
    "addr:street": "Rapid Run Rd",
    "iso:country": "US",
    "sg:address": "5661 Rapid Run Rd",
    "sg:city": "Cincinnati",
    "sg:classifiers": [
      {
        "category": "Shopping",
        "subcategory": "Pets \u0026 Pet Supplies",
        "type": "Retail Goods"
      },
      {
        "category": "Retail",
        "subcategory": "Animal Services",
        "type": "Services"
      }
    ],
    "sg:phone": "+1 513 451 8787",
    "sg:postcode": "45238",
    "sg:province": "OH",
    "sg:tags": [
      "grooming",
      "dog",
      "cat"
    ],
    "wof:name": "Jenny's Grooming",
    "wof:placetype": "venue"
  },
  "geometry": {"coordinates":[-84.633632,39.111866],"type":"Point"}
}
