{
  "type": "Feature",
  "properties": {
    "iso:country":"US",
    "sg:address":"5889 Burnett East Rd",
    "sg:city":"Kinsman",
    "sg:classifiers":[
        {
            "category":"Wholesale",
            "subcategory":"Scrap",
            "type":"Manufacturing & Wholesale Goods"
        }
    ],
    "sg:phone":"+1 330 876 9944",
    "sg:postcode":"44428",
    "sg:province":"OH",
    "sg:tags":[
        "material",
        "metal",
        "iron"
    ],
    "sg:website":"www.gulfcoastdismantling.com",
    "wof:name":"Gulf Coast Dismantling & Salv",
    "wof:placetype":"venue"
},
  "geometry": {"coordinates":[-80.603543,41.437604],"type":"Point"}
}