{
  "type": "Feature",
  "properties": {
    "iso:country":"US",
    "sg:address":"101 N Summit St",
    "sg:city":"Toledo",
    "sg:classifiers":[
        {
            "category":"Professional",
            "type":"Services"
        }
    ],
    "sg:phone":"+1 419 244 9653",
    "sg:postcode":"43604",
    "sg:province":"OH",
    "sg:tags":[
        "establishment"
    ],
    "wof:name":"On Command",
    "wof:placetype":"venue"
},
  "geometry": {"coordinates":[-83.534891,41.649589],"type":"Point"}
}