{
  "type": "Feature",
  "properties": {
    "addr:full": "3040 E Main St Columbus OH 43209",
    "addr:housenumber": "3040",
    "addr:postcode": "43209",
    "addr:street": "E Main St",
    "iso:country": "US",
    "sg:address": "3040 E Main St",
    "sg:city": "Columbus",
    "sg:classifiers": [
      {
        "category": "Insurance",
        "subcategory": "Insurance Agent",
        "type": "Services"
      }
    ],
    "sg:phone": "+1 614 231 4663",
    "sg:postcode": "43209",
    "sg:province": "OH",
    "wof:name": "Goldmeier Insurance",
    "wof:placetype": "venue"
  },
  "geometry": {"coordinates":[-82.916398,39.956699],"type":"Point"}
}
