{
  "type": "Feature",
  "properties": {
    "iso:country":"US",
    "sg:address":"8535 Harrison Pike",
    "sg:city":"Cleves",
    "sg:classifiers":[
        {
            "category":"Building & Trades",
            "subcategory":"Electrical",
            "type":"Services"
        }
    ],
    "sg:phone":"+1 513 353 4800",
    "sg:postcode":"45002",
    "sg:province":"OH",
    "sg:tags":[
        "electric",
        "contractor"
    ],
    "wof:name":"Southern Electric Inc",
    "wof:placetype":"venue"
},
  "geometry": {"coordinates":[-84.731674,39.226216],"type":"Point"}
}