{
  "type": "Feature",
  "properties": {
    "addr:full":"1421 Union Ave Columbus OH 43223",
    "addr:housenumber":"1421",
    "addr:postcode":"43223",
    "addr:street":"Union Ave",
    "iso:country":"US",
    "sg:address":"1421 Union Ave",
    "sg:city":"Columbus",
    "sg:classifiers":[
        {
            "category":"Manufacturing",
            "subcategory":"Printing",
            "type":"Manufacturing & Wholesale Goods"
        }
    ],
    "sg:phone":"+1 614 272 2372",
    "sg:postcode":"43223",
    "sg:province":"OH",
    "sg:tags":[
        "printer"
    ],
    "wof:name":"Southwest Graphics",
    "wof:placetype":"venue"
},
  "geometry": {"coordinates":[-83.036812,39.949014],"type":"Point"}
}