{
  "type": "Feature",
  "properties": {
    "iso:country":"US",
    "sg:address":"412 Ohio Ave",
    "sg:city":"Troy",
    "sg:classifiers":[
        {
            "category":"Shopping",
            "subcategory":"Bicycles & Sporting Goods",
            "type":"Retail Goods"
        }
    ],
    "sg:phone":"+1 937 339 0154",
    "sg:postcode":"45373",
    "sg:province":"OH",
    "wof:name":"Base Paintball",
    "wof:placetype":"venue"
},
  "geometry": {"coordinates":[-84.19326599999999,40.043295],"type":"Point"}
}