{
  "type": "Feature",
  "properties": {
    "addr:full": "412 Ohio Ave Troy OH 45373",
    "addr:housenumber": "412",
    "addr:postcode": "45373",
    "addr:street": "Ohio Ave",
    "iso:country": "US",
    "sg:address": "412 Ohio Ave",
    "sg:city": "Troy",
    "sg:classifiers": [
      {
        "category": "Shopping",
        "subcategory": "Bicycles \u0026 Sporting Goods",
        "type": "Retail Goods"
      }
    ],
    "sg:phone": "+1 937 339 0154",
    "sg:postcode": "45373",
    "sg:province": "OH",
    "wof:name": "Base Paintball",
    "wof:placetype": "venue"
  },
  "geometry": {"coordinates":[-84.193266,40.043295],"type":"Point"}
}
