{
  "type": "Feature",
  "properties": {
    "addr:full":"376 Paxton Rd Gallipolis OH 45631",
    "addr:housenumber":"376",
    "addr:postcode":"45631",
    "addr:street":"Paxton Rd",
    "iso:country":"US",
    "sg:address":"376 Paxton Rd",
    "sg:city":"Gallipolis",
    "sg:classifiers":[
        {
            "category":"Retail",
            "subcategory":"Auto Repair",
            "type":"Services"
        }
    ],
    "sg:phone":"+1 740 446 8708",
    "sg:postcode":"45631",
    "sg:province":"OH",
    "sg:tags":[
        "wrecker"
    ],
    "wof:name":"Curry's Towing Svc",
    "wof:placetype":"venue"
},
  "geometry": {"coordinates":[-82.25265,38.766216],"type":"Point"}
}