{
  "type": "Feature",
  "properties": {
    "addr:full": "1299 W Ohio Pike Amelia OH 45102",
    "addr:housenumber": "1299",
    "addr:postcode": "45102",
    "addr:street": "W Ohio Pike",
    "iso:country": "US",
    "sg:address": "1299 W Ohio Pike",
    "sg:city": "Amelia",
    "sg:classifiers": [
      {
        "category": "Professional",
        "subcategory": "Business Services",
        "type": "Services"
      }
    ],
    "sg:phone": "+1 513 752 7993",
    "sg:postcode": "45102",
    "sg:province": "OH",
    "sg:tags": [
      "embroidery"
    ],
    "wof:name": "Est Printing \u0026 Label",
    "wof:placetype": "venue"
  },
  "geometry": {"coordinates":[-84.231505,39.038003],"type":"Point"}
}
