{
  "type": "Feature",
  "properties": {
    "iso:country":"US",
    "sg:address":"4216 W Broad St",
    "sg:city":"Columbus",
    "sg:classifiers":[
        {
            "category":"Manufacturing",
            "subcategory":"Printing",
            "type":"Manufacturing & Wholesale Goods"
        }
    ],
    "sg:phone":"+1 614 274 1439",
    "sg:postcode":"43228",
    "sg:province":"OH",
    "sg:tags":[
        "lithographic",
        "commercial"
    ],
    "wof:name":"Minuteman Press",
    "wof:placetype":"venue"
},
  "geometry": {"coordinates":[-83.114874,39.952909],"type":"Point"}
}