{
  "type": "Feature",
  "properties": {
    "addr:full": "401 South St Chardon OH 44024",
    "addr:housenumber": "401",
    "addr:postcode": "44024",
    "addr:street": "South St",
    "iso:country": "US",
    "sg:address": "401 South St",
    "sg:city": "Chardon",
    "sg:classifiers": [
      {
        "category": "Real Estate",
        "subcategory": "Real Estate Services",
        "type": "Services"
      }
    ],
    "sg:phone": "+1 440 286 7158",
    "sg:postcode": "44024",
    "sg:province": "OH",
    "sg:tags": [
      "company",
      "title"
    ],
    "wof:name": "Geauga Title Insurance Agency",
    "wof:placetype": "venue"
  },
  "geometry": {"coordinates":[-81.203335,41.575637],"type":"Point"}
}
