{
  "type": "Feature",
  "properties": {
    "addr:full": "2559 S Reynolds Rd Toledo OH 43614",
    "addr:housenumber": "2559",
    "addr:postcode": "43614",
    "addr:street": "S Reynolds Rd",
    "iso:country": "US",
    "sg:address": "2559 S Reynolds Rd",
    "sg:city": "Toledo",
    "sg:classifiers": [
      {
        "category": "Shopping",
        "subcategory": "Crafts \u0026 Fabrics",
        "type": "Retail Goods"
      }
    ],
    "sg:phone": "+1 419 381 0175",
    "sg:postcode": "43614",
    "sg:province": "OH",
    "sg:tags": [
      "sewing"
    ],
    "wof:name": "Jo-Ann Fabrics \u0026 Crafts",
    "wof:placetype": "venue"
  },
  "geometry": {"coordinates":[-83.664611,41.593398],"type":"Point"}
}
