{
  "type": "Feature",
  "properties": {
    "iso:country":"US",
    "sg:address":"2559 S Reynolds Rd",
    "sg:city":"Toledo",
    "sg:classifiers":[
        {
            "category":"Shopping",
            "subcategory":"Crafts & Fabrics",
            "type":"Retail Goods"
        }
    ],
    "sg:phone":"+1 419 381 0175",
    "sg:postcode":"43614",
    "sg:province":"OH",
    "sg:tags":[
        "sewing"
    ],
    "wof:name":"Jo-Ann Fabrics & Crafts",
    "wof:placetype":"venue"
},
  "geometry": {"coordinates":[-83.66461099999999,41.593398],"type":"Point"}
}