{
  "type": "Feature",
  "properties": {
    "addr:full": "3093 W Broad St Columbus OH 43204",
    "addr:housenumber": "3093",
    "addr:postcode": "43204",
    "addr:street": "W Broad St",
    "iso:country": "US",
    "sg:address": "3093 W Broad St",
    "sg:city": "Columbus",
    "sg:classifiers": [
      {
        "category": "Personal",
        "subcategory": "Beauty Salon",
        "type": "Services"
      }
    ],
    "sg:phone": "+1 614 274 5670",
    "sg:postcode": "43204",
    "sg:province": "OH",
    "wof:name": "Westmoor Beauty Salon",
    "wof:placetype": "venue"
  },
  "geometry": {"coordinates":[-83.083019,39.954444],"type":"Point"}
}
