{
  "type": "Feature",
  "properties": {
    "iso:country":"US",
    "sg:address":"1507 Dana Ave",
    "sg:city":"Cincinnati",
    "sg:classifiers":[
        {
            "category":"Professional",
            "subcategory":"Computer Services",
            "type":"Services"
        }
    ],
    "sg:phone":"+1 937 746 1182",
    "sg:postcode":"45207",
    "sg:province":"OH",
    "sg:tags":[
        "datum",
        "related",
        "w"
    ],
    "wof:name":"A C T",
    "wof:placetype":"venue"
},
  "geometry": {"coordinates":[-84.475002,39.146656],"type":"Point"}
}