{
  "type": "Feature",
  "properties": {
    "addr:full": "4901 Richmond Cir Sandusky OH 44870",
    "addr:housenumber": "4901",
    "addr:postcode": "44870",
    "addr:street": "Richmond Cir",
    "iso:country": "US",
    "sg:address": "4901 Richmond Cir",
    "sg:city": "Sandusky",
    "sg:classifiers": [
      {
        "category": "Retail",
        "subcategory": "Laundry \u0026 Dry Cleaning",
        "type": "Services"
      }
    ],
    "sg:phone": "+1 419 624 1772",
    "sg:postcode": "44870",
    "sg:province": "OH",
    "sg:tags": [
      "cleaners",
      "rug",
      "carpet"
    ],
    "wof:name": "Carpet Guys",
    "wof:placetype": "venue"
  },
  "geometry": {"coordinates":[-82.676279,41.401255],"type":"Point"}
}
