{
  "type": "Feature",
  "properties": {
    "iso:country":"US",
    "sg:address":"4901 Richmond Cir",
    "sg:city":"Sandusky",
    "sg:classifiers":[
        {
            "category":"Retail",
            "subcategory":"Laundry & Dry Cleaning",
            "type":"Services"
        }
    ],
    "sg:phone":"+1 419 624 1772",
    "sg:postcode":"44870",
    "sg:province":"OH",
    "sg:tags":[
        "cleaners",
        "rug",
        "carpet"
    ],
    "wof:name":"Carpet Guys",
    "wof:placetype":"venue"
},
  "geometry": {"coordinates":[-82.67627899999999,41.401255],"type":"Point"}
}