{
  "type": "Feature",
  "properties": {
    "iso:country":"US",
    "sg:address":"489 Sherman Ave",
    "sg:city":"Sharon",
    "sg:classifiers":[
        {
            "category":"Building & Trades",
            "subcategory":"Plumbing",
            "type":"Services"
        }
    ],
    "sg:phone":"+1 724 866 0413",
    "sg:postcode":"16146",
    "sg:province":"OH",
    "sg:tags":[
        "conditioning",
        "air",
        "system",
        "contractor"
    ],
    "wof:name":"J L Mendillo Construction",
    "wof:placetype":"venue"
},
  "geometry": {"coordinates":[-80.49457200000001,41.225451],"type":"Point"}
}