{
  "type": "Feature",
  "properties": {
    "addr:full": "2947 E 14th Ave Columbus OH 43219",
    "addr:housenumber": "2947",
    "addr:postcode": "43219",
    "addr:street": "E 14Th Ave",
    "iso:country": "US",
    "sg:address": "2947 E 14th Ave",
    "sg:city": "Columbus",
    "sg:classifiers": [
      {
        "category": "Wholesale",
        "subcategory": "Construction Materials",
        "type": "Manufacturing \u0026 Wholesale Goods"
      }
    ],
    "sg:phone": "+1 614 253 6496",
    "sg:postcode": "43219",
    "sg:province": "OH",
    "sg:tags": [
      "fencing"
    ],
    "wof:name": "Master-Halco Inc",
    "wof:placetype": "venue"
  },
  "geometry": {"coordinates":[-82.925128,39.993739],"type":"Point"}
}
