{
  "type": "Feature",
  "properties": {
    "addr:full": "106 Oak St Buckland OH 45819",
    "addr:housenumber": "106",
    "addr:postcode": "45819",
    "addr:street": "Oak St",
    "iso:country": "US",
    "sg:address": "106 Oak St",
    "sg:city": "Buckland",
    "sg:classifiers": [
      {
        "category": "Education",
        "subcategory": "Special Training",
        "type": "Public Place"
      }
    ],
    "sg:phone": "+1 419 657 6922",
    "sg:postcode": "45819",
    "sg:province": "OH",
    "sg:tags": [
      "instruction",
      "driving"
    ],
    "wof:name": "Maximum Driver's Training",
    "wof:placetype": "venue"
  },
  "geometry": {"coordinates":[-84.259045,40.62641],"type":"Point"}
}
