{
  "type": "Feature",
  "properties": {
    "addr:full": "30270 Woodall Dr Solon OH 44139",
    "addr:postcode": "30270;44139",
    "addr:street": "Woodall Dr",
    "iso:country": "US",
    "sg:address": "30270 Woodall Dr",
    "sg:city": "Solon",
    "sg:classifiers": [
      {
        "category": "Building \u0026 Trades",
        "subcategory": "Construction",
        "type": "Services"
      }
    ],
    "sg:phone": "+1 440 498 0203",
    "sg:postcode": "44139",
    "sg:province": "OH",
    "sg:tags": [
      "residential"
    ],
    "wof:name": "John N Wittrup Construction",
    "wof:placetype": "venue"
  },
  "geometry": {"coordinates":[-81.463787,41.421274],"type":"Point"}
}
