{
  "type": "Feature",
  "properties": {
    "addr:full": "14848 Twp Rd 25 Arlington OH 45814",
    "addr:housenumber": "14848;25",
    "addr:postcode": "45814",
    "addr:street": "Twp Rd",
    "iso:country": "US",
    "sg:address": "14848 Twp Rd 25",
    "sg:city": "Arlington",
    "sg:phone": "+1 419 694 6261",
    "sg:postcode": "45814",
    "sg:province": "OH",
    "sg:tags": [
      "farm",
      "grain",
      "cash"
    ],
    "wof:name": "Gary Stacy",
    "wof:placetype": "venue"
  },
  "geometry": {"coordinates":[-83.596417,40.920974],"type":"Point"}
}
