{
  "type": "Feature",
  "properties": {
    "addr:full": "42857 N Ridge Rd Elyria OH 44035",
    "addr:housenumber": "42857",
    "addr:postcode": "44035",
    "addr:street": "N Ridge Rd",
    "iso:country": "US",
    "sg:address": "42857 N Ridge Rd",
    "sg:city": "Elyria",
    "sg:classifiers": [
      {
        "category": "Shopping",
        "subcategory": "Clothing, Apparel, \u0026 Fashions",
        "type": "Retail Goods"
      }
    ],
    "sg:phone": "+1 440 324 9630",
    "sg:postcode": "44035",
    "sg:province": "OH",
    "wof:name": "Romantics Lngrie Extic Dncwear",
    "wof:placetype": "venue"
  },
  "geometry": {"coordinates":[-82.141107,41.418081],"type":"Point"}
}
