{
  "type": "Feature",
  "properties": {
    "iso:country":"US",
    "sg:address":"42857 N Ridge Rd",
    "sg:city":"Elyria",
    "sg:classifiers":[
        {
            "category":"Shopping",
            "subcategory":"Clothing, Apparel, & Fashions",
            "type":"Retail Goods"
        }
    ],
    "sg:phone":"+1 440 324 9630",
    "sg:postcode":"44035",
    "sg:province":"OH",
    "wof:name":"Romantics Lngrie Extic Dncwear",
    "wof:placetype":"venue"
},
  "geometry": {"coordinates":[-82.14110700000001,41.418081],"type":"Point"}
}