{
  "type": "Feature",
  "properties": {
    "iso:country":"US",
    "sg:address":"3822 Silsby Rd",
    "sg:city":"Cleveland",
    "sg:classifiers":[
        {
            "category":"Shopping",
            "subcategory":"Hobbies, Toys, & Games",
            "type":"Retail Goods"
        }
    ],
    "sg:phone":"+1 216 932 6585",
    "sg:postcode":"44118",
    "sg:province":"OH",
    "wof:name":"Pieces of A Dream",
    "wof:placetype":"venue"
},
  "geometry": {"coordinates":[-81.541472,41.497649],"type":"Point"}
}