{
  "type": "Feature",
  "properties": {
    "addr:full":"15955 Thomas St Newbury OH 44065",
    "addr:housenumber":"15955",
    "addr:postcode":"44065",
    "addr:street":"Thomas St",
    "iso:country":"US",
    "sg:address":"15955 Thomas St",
    "sg:city":"Newbury",
    "sg:classifiers":[
        {
            "category":"Building & Trades",
            "subcategory":"Construction",
            "type":"Services"
        }
    ],
    "sg:phone":"+1 440 564 7273",
    "sg:postcode":"44065",
    "sg:province":"OH",
    "sg:tags":[
        "contractor"
    ],
    "wof:name":"Dan Williamson",
    "wof:placetype":"venue"
},
  "geometry": {"coordinates":[-81.280952,41.439005],"type":"Point"}
}