{
  "type": "Feature",
  "properties": {
    "iso:country":"US",
    "sg:address":"1076 Leedale Ave",
    "sg:city":"Cleveland",
    "sg:classifiers":[
        {
            "category":"Organizations",
            "subcategory":"Membership Organization",
            "type":"Services"
        }
    ],
    "sg:phone":"+1 216 228 4779",
    "sg:postcode":"44107",
    "sg:province":"OH",
    "wof:name":"Women In History",
    "wof:placetype":"venue"
},
  "geometry": {"coordinates":[-81.802885,41.49358],"type":"Point"}
}