{
  "type": "Feature",
  "properties": {
    "addr:full": "253 W Aurora Rd Northfield OH 44067",
    "addr:housenumber": "253",
    "addr:postcode": "44067",
    "addr:street": "W Aurora Rd",
    "iso:country": "US",
    "sg:address": "253 W Aurora Rd",
    "sg:city": "Northfield",
    "sg:classifiers": [
      {
        "category": "Building \u0026 Trades",
        "subcategory": "Cleaning \u0026 Sanitation",
        "type": "Services"
      }
    ],
    "sg:phone": "+1 330 467 7706",
    "sg:postcode": "44067",
    "sg:province": "OH",
    "sg:tags": [
      "janitor"
    ],
    "wof:name": "World Clean",
    "wof:placetype": "venue"
  },
  "geometry": {"coordinates":[-81.545797,41.314348],"type":"Point"}
}
