{
  "type": "Feature",
  "properties": {
    "iso:country":"US",
    "sg:address":"253 W Aurora Rd",
    "sg:city":"Northfield",
    "sg:classifiers":[
        {
            "category":"Building & Trades",
            "subcategory":"Cleaning & Sanitation",
            "type":"Services"
        }
    ],
    "sg:phone":"+1 330 467 7706",
    "sg:postcode":"44067",
    "sg:province":"OH",
    "sg:tags":[
        "janitor"
    ],
    "wof:name":"World Clean",
    "wof:placetype":"venue"
},
  "geometry": {"coordinates":[-81.54579699999999,41.314348],"type":"Point"}
}