{
  "type": "Feature",
  "properties": {
    "addr:full": "702 Chicago St Toledo OH 43611",
    "addr:housenumber": "702",
    "addr:postcode": "43611",
    "addr:street": "Chicago St",
    "iso:country": "US",
    "sg:address": "702 Chicago St",
    "sg:city": "Toledo",
    "sg:classifiers": [
      {
        "category": "Building \u0026 Trades",
        "subcategory": "Construction",
        "type": "Services"
      }
    ],
    "sg:phone": "+1 419 726 1156",
    "sg:postcode": "43611",
    "sg:province": "OH",
    "sg:tags": [
      "house"
    ],
    "wof:name": "Jj Construction",
    "wof:placetype": "venue"
  },
  "geometry": {"coordinates":[-83.510095,41.674782],"type":"Point"}
}
