{
  "type": "Feature",
  "properties": {
    "addr:full": "20 North St Dublin OH 43017",
    "addr:housenumber": "20",
    "addr:postcode": "43017",
    "addr:street": "North St",
    "iso:country": "US",
    "sg:address": "20 North St",
    "sg:city": "Dublin",
    "sg:classifiers": [
      {
        "category": "Professional",
        "subcategory": "Management \u0026 Consulting",
        "type": "Services"
      }
    ],
    "sg:phone": "+1 614 793 0575",
    "sg:postcode": "43017",
    "sg:province": "OH",
    "wof:name": "Brinker Capital Holdings Inc",
    "wof:placetype": "venue"
  },
  "geometry": {"coordinates":[-83.113207,40.100997],"type":"Point"}
}
