{
  "type": "Feature",
  "properties": {
    "iso:country":"US",
    "sg:address":"2368 Boehler Rd",
    "sg:city":"Monroeville",
    "sg:classifiers":[
        {
            "category":"Farming",
            "subcategory":"Farm",
            "type":"Manufacturing & Wholesale Goods"
        }
    ],
    "sg:phone":"+1 419 465 2985",
    "sg:postcode":"44847",
    "sg:province":"OH",
    "sg:tags":[
        "crop",
        "general"
    ],
    "wof:name":"Gilbert Ruffing",
    "wof:placetype":"venue"
},
  "geometry": {"coordinates":[-82.730824,41.201073],"type":"Point"}
}