{
  "type": "Feature",
  "properties": {
    "iso:country":"US",
    "sg:address":"89 Park Ave W",
    "sg:city":"Mansfield",
    "sg:classifiers":[
        {
            "category":"Travel",
            "subcategory":"Travel Agent",
            "type":"Entertainment"
        }
    ],
    "sg:phone":"+1 419 522 2929",
    "sg:postcode":"44902",
    "sg:province":"OH",
    "sg:tags":[
        "agency"
    ],
    "wof:name":"Richland Travel",
    "wof:placetype":"venue"
},
  "geometry": {"coordinates":[-82.520243,40.758685],"type":"Point"}
}