{
  "type": "Feature",
  "properties": {
    "addr:full": "254 S Summit St Smithville OH 44677",
    "addr:housenumber": "254",
    "addr:postcode": "44677",
    "addr:street": "S Summit St",
    "iso:country": "US",
    "sg:address": "254 S Summit St",
    "sg:city": "Smithville",
    "sg:classifiers": [
      {
        "category": "Building \u0026 Trades",
        "subcategory": "Construction",
        "type": "Services"
      }
    ],
    "sg:phone": "+1 330 669 2764",
    "sg:postcode": "44677",
    "sg:province": "OH",
    "sg:tags": [
      "hanging",
      "contractor"
    ],
    "wof:name": "Thompson Painting and Dctg Co",
    "wof:placetype": "venue"
  },
  "geometry": {"coordinates":[-81.861625,40.859983],"type":"Point"}
}
