{
  "type": "Feature",
  "properties": {
    "addr:full":"7792 McCreary Rd Cleveland OH 44131",
    "addr:housenumber":"7792",
    "addr:postcode":"44131",
    "addr:street":"Mccreary Rd",
    "iso:country":"US",
    "sg:address":"7792 McCreary Rd",
    "sg:city":"Cleveland",
    "sg:classifiers":[
        {
            "category":"Communications",
            "type":"Services"
        }
    ],
    "sg:phone":"+1 216 524 1140",
    "sg:postcode":"44131",
    "sg:province":"OH",
    "wof:name":"CMP Communications",
    "wof:placetype":"venue"
},
  "geometry": {"coordinates":[-81.67257499999999,41.355033],"type":"Point"}
}