{
  "type": "Feature",
  "properties": {
    "iso:country":"US",
    "sg:address":"29001 Cedar Rd",
    "sg:city":"Cleveland",
    "sg:classifiers":[
        {
            "category":"Health Services",
            "subcategory":"Health Practitioner",
            "type":"Services"
        }
    ],
    "sg:phone":"+1 440 461 6600",
    "sg:postcode":"44124",
    "sg:province":"OH",
    "sg:tags":[
        "therapist",
        "physical"
    ],
    "wof:name":"Bloch Physical Therapy Inc",
    "wof:placetype":"venue"
},
  "geometry": {"coordinates":[-81.472281,41.501235],"type":"Point"}
}