{
  "type": "Feature",
  "properties": {
    "addr:full":"6823 Williams Rd Painesville OH 44077",
    "addr:housenumber":"6823",
    "addr:postcode":"44077",
    "addr:street":"Williams Rd",
    "iso:country":"US",
    "sg:address":"6823 Williams Rd",
    "sg:city":"Painesville",
    "sg:classifiers":[
        {
            "category":"Building & Trades",
            "subcategory":"Construction",
            "type":"Services"
        }
    ],
    "sg:phone":"+1 440 352 1023",
    "sg:postcode":"44077",
    "sg:province":"OH",
    "sg:tags":[
        "carpentry",
        "contractor"
    ],
    "wof:name":"Wayne Horton Construction",
    "wof:placetype":"venue"
},
  "geometry": {"coordinates":[-81.198176,41.681533],"type":"Point"}
}