{
  "type": "Feature",
  "properties": {
    "iso:country":"US",
    "sg:address":"7658 Fishel Dr N",
    "sg:city":"Dublin",
    "sg:classifiers":[
        {
            "category":"Wholesale",
            "subcategory":"Sporting Goods",
            "type":"Manufacturing & Wholesale Goods"
        }
    ],
    "sg:phone":"+1 614 761 2935",
    "sg:postcode":"43016",
    "sg:province":"OH",
    "sg:tags":[
        "swimming",
        "equipment",
        "supply",
        "pool",
        "spa"
    ],
    "sg:website":"www.qualitypool.com",
    "wof:name":"Quality Pool Supply Co",
    "wof:placetype":"venue"
},
  "geometry": {"coordinates":[-83.192849,40.104825],"type":"Point"}
}