{
  "type": "Feature",
  "properties": {
    "iso:country":"US",
    "sg:address":"5475 Engle Rd",
    "sg:city":"Cleveland",
    "sg:classifiers":[
        {
            "category":"Shopping",
            "subcategory":"Bicycles & Sporting Goods",
            "type":"Retail Goods"
        }
    ],
    "sg:phone":"+1 216 433 9011",
    "sg:postcode":"44142",
    "sg:province":"OH",
    "sg:tags":[
        "ski",
        "jet"
    ],
    "wof:name":"Power Sports Of Cleveland Inc",
    "wof:placetype":"venue"
},
  "geometry": {"coordinates":[-81.819459,41.41527],"type":"Point"}
}