{
  "type": "Feature",
  "properties": {
    "addr:full": "6420 E Main St Reynoldsburg OH 43068",
    "addr:housenumber": "6420",
    "addr:postcode": "43068",
    "addr:street": "E Main St",
    "iso:country": "US",
    "sg:address": "6420 E Main St",
    "sg:city": "Reynoldsburg",
    "sg:classifiers": [
      {
        "category": "Wholesale",
        "subcategory": "Machinery \u0026 Supplies",
        "type": "Manufacturing \u0026 Wholesale Goods"
      }
    ],
    "sg:phone": "+1 614 864 4214",
    "sg:postcode": "43068",
    "sg:province": "OH",
    "sg:tags": [
      "field",
      "oil"
    ],
    "wof:name": "Mc Junkin Appalachian Oil Fld",
    "wof:placetype": "venue"
  },
  "geometry": {"coordinates":[-82.821729,39.954991],"type":"Point"}
}
