{
  "type": "Feature",
  "properties": {
    "addr:full":"14500 Rider Rd Burton OH 44021",
    "addr:housenumber":"14500",
    "addr:postcode":"44021",
    "addr:street":"Rider Rd",
    "iso:country":"US",
    "sg:address":"14500 Rider Rd",
    "sg:city":"Burton",
    "sg:classifiers":[
        {
            "category":"Real Estate",
            "subcategory":"Real Estate Agent",
            "type":"Services"
        }
    ],
    "sg:phone":"+1 440 834 8301",
    "sg:postcode":"44021",
    "sg:province":"OH",
    "sg:tags":[
        "appraiser"
    ],
    "wof:name":"Herb Farrow & Assoc Inc",
    "wof:placetype":"venue"
},
  "geometry": {"coordinates":[-81.18067600000001,41.471444],"type":"Point"}
}