{
  "type": "Feature",
  "properties": {
    "iso:country":"US",
    "sg:address":"11290 Sebring Dr",
    "sg:city":"Cincinnati",
    "sg:classifiers":[
        {
            "category":"Building & Trades",
            "subcategory":"Plumbing",
            "type":"Services"
        }
    ],
    "sg:phone":"+1 513 674 9110",
    "sg:postcode":"45240",
    "sg:province":"OH",
    "sg:tags":[
        "specializing",
        "heating",
        "contractor",
        "conditioning",
        "mechanical",
        "air"
    ],
    "wof:name":"Driekast Piping Corp",
    "wof:placetype":"venue"
},
  "geometry": {"coordinates":[-84.556872,39.28536],"type":"Point"}
}