{
  "type": "Feature",
  "properties": {
    "addr:full":"9717 Kenwood Rd Cincinnati OH 45242",
    "addr:housenumber":"9717",
    "addr:postcode":"45242",
    "addr:street":"Kenwood Rd",
    "iso:country":"US",
    "sg:address":"9717 Kenwood Rd",
    "sg:city":"Cincinnati",
    "sg:classifiers":[
        {
            "category":"Restaurant",
            "type":"Food & Drink"
        }
    ],
    "sg:menulink":"http://www.allmenus.com/oh/blue-ash/90153-penn-station/menu/",
    "sg:phone":"+1 513 791 7366",
    "sg:postcode":"45242",
    "sg:province":"OH",
    "sg:tags":[
        "wrap",
        "american",
        "sandwich"
    ],
    "wof:name":"Penn Station",
    "wof:placetype":"venue"
},
  "geometry": {"coordinates":[-84.376638,39.234953],"type":"Point"}
}