{
  "type": "Feature",
  "properties": {
    "iso:country":"US",
    "sg:address":"6 S Main St",
    "sg:city":"New London",
    "sg:classifiers":[
        {
            "category":"Real Estate",
            "subcategory":"Real Estate Agent",
            "type":"Services"
        }
    ],
    "sg:phone":"+1 419 929 3051",
    "sg:postcode":"44851",
    "sg:province":"OH",
    "wof:name":"Foster Realty",
    "wof:placetype":"venue"
},
  "geometry": {"coordinates":[-82.399321,41.085124],"type":"Point"}
}