{
  "type": "Feature",
  "properties": {
    "addr:full": "2842 E Main St Springfield OH 45503",
    "addr:housenumber": "2842",
    "addr:postcode": "45503",
    "addr:street": "E Main St",
    "iso:country": "US",
    "sg:address": "2842 E Main St",
    "sg:city": "Springfield",
    "sg:classifiers": [
      {
        "category": "Professional",
        "subcategory": "Business Services",
        "type": "Services"
      }
    ],
    "sg:phone": "+1 937 328 0098",
    "sg:postcode": "45503",
    "sg:province": "OH",
    "sg:tags": [
      "embroidery"
    ],
    "wof:name": "Embroidered Basket \u0026 More",
    "wof:placetype": "venue"
  },
  "geometry": {"coordinates":[-83.762693,39.923417],"type":"Point"}
}
