{
  "type": "Feature",
  "properties": {
    "addr:full":"9930 Johnnycake Ridge Rd Mentor OH 44060",
    "addr:housenumber":"9930",
    "addr:postcode":"44060",
    "addr:street":"Johnnycake Ridge Rd",
    "iso:country":"US",
    "sg:address":"9930 Johnnycake Ridge Rd",
    "sg:city":"Mentor",
    "sg:classifiers":[
        {
            "category":"Insurance",
            "subcategory":"Insurance Agent",
            "type":"Services"
        }
    ],
    "sg:phone":"+1 440 392 0795",
    "sg:postcode":"44060",
    "sg:province":"OH",
    "wof:name":"David Sillanpaa Insurance",
    "wof:placetype":"venue"
},
  "geometry": {"coordinates":[-81.285534,41.671027],"type":"Point"}
}