{
  "type": "Feature",
  "properties": {
    "addr:full":"415 E Main St Canfield OH 44406",
    "addr:housenumber":"415",
    "addr:postcode":"44406",
    "addr:street":"E Main St",
    "iso:country":"US",
    "sg:address":"415 E Main St",
    "sg:city":"Canfield",
    "sg:classifiers":[
        {
            "category":"Professional",
            "subcategory":"Computer Services",
            "type":"Services"
        }
    ],
    "sg:phone":"+1 330 702 8088",
    "sg:postcode":"44406",
    "sg:province":"OH",
    "sg:tags":[
        "internet"
    ],
    "wof:name":"WSI",
    "wof:placetype":"venue"
},
  "geometry": {"coordinates":[-80.745901,41.02466],"type":"Point"}
}