{
  "type": "Feature",
  "properties": {
    "addr:full": "9325 Hunters Creek Dr Cincinnati OH 45242",
    "addr:housenumber": "9325",
    "addr:postcode": "45242",
    "addr:street": "Hunters Creek Dr",
    "iso:country": "US",
    "sg:address": "9325 Hunters Creek Dr",
    "sg:city": "Cincinnati",
    "sg:classifiers": [
      {
        "category": "Professional",
        "subcategory": "Management \u0026 Consulting",
        "type": "Services"
      }
    ],
    "sg:phone": "+1 513 985 0908",
    "sg:postcode": "45242",
    "sg:province": "OH",
    "sg:tags": [
      "consultant"
    ],
    "wof:name": "Capitalized Assets LTD",
    "wof:placetype": "venue"
  },
  "geometry": {"coordinates":[-84.389556,39.227258],"type":"Point"}
}
