{
  "type": "Feature",
  "properties": {
    "addr:full":"691 Richmond Rd Cleveland OH 44143",
    "addr:housenumber":"691",
    "addr:postcode":"44143",
    "addr:street":"Richmond Rd",
    "iso:country":"US",
    "sg:address":"691 Richmond Rd",
    "sg:city":"Cleveland",
    "sg:classifiers":[
        {
            "category":"Shopping",
            "subcategory":"Jewelry",
            "type":"Retail Goods"
        }
    ],
    "sg:phone":"+1 440 684 0088",
    "sg:postcode":"44143",
    "sg:province":"OH",
    "sg:tags":[
        "jeweler"
    ],
    "wof:name":"Jewels & More",
    "wof:placetype":"venue"
},
  "geometry": {"coordinates":[-81.49709900000001,41.54074],"type":"Point"}
}