{
  "type": "Feature",
  "properties": {
    "addr:full": "13406 E Shelby Rd Minster OH 45865",
    "addr:housenumber": "13406",
    "addr:postcode": "45865",
    "addr:street": "E Shelby Rd",
    "iso:country": "US",
    "sg:address": "13406 E Shelby Rd",
    "sg:city": "Minster",
    "sg:classifiers": [
      {
        "category": "Freight",
        "type": "Transportation"
      }
    ],
    "sg:phone": "+1 419 628 2289",
    "sg:postcode": "45865",
    "sg:province": "OH",
    "sg:tags": [
      "operator",
      "local",
      "trucking"
    ],
    "wof:name": "Larger Larry Bulk Milk Trnspt",
    "wof:placetype": "venue"
  },
  "geometry": {"coordinates":[-84.33869,40.388089],"type":"Point"}
}
