{
  "type": "Feature",
  "properties": {
    "addr:full":"6330 Cincinnati Dayton Rd Liberty Twp OH 45044",
    "addr:housenumber":"6330",
    "addr:postcode":"45044",
    "addr:street":"Cincinnati Dayton Rd",
    "iso:country":"US",
    "sg:address":"6330 Cincinnati Dayton Rd",
    "sg:city":"Liberty Twp",
    "sg:classifiers":[
        {
            "category":"Building & Trades",
            "subcategory":"Plumbing",
            "type":"Services"
        }
    ],
    "sg:phone":"+1 513 779 4512",
    "sg:postcode":"45044",
    "sg:province":"OH",
    "sg:tags":[
        "plumbing",
        "contractor"
    ],
    "wof:name":"Master Plumber Inc",
    "wof:placetype":"venue"
},
  "geometry": {"coordinates":[-84.37288599999999,39.385666],"type":"Point"}
}