{
  "type": "Feature",
  "properties": {
    "addr:full": "34115 Mills Rd North Ridgeville OH 44039",
    "addr:housenumber": "34115",
    "addr:postcode": "44039",
    "addr:street": "Mills Rd",
    "iso:country": "US",
    "sg:address": "34115 Mills Rd",
    "sg:city": "North Ridgeville",
    "sg:classifiers": [
      {
        "category": "Building \u0026 Trades",
        "subcategory": "Construction",
        "type": "Services"
      }
    ],
    "sg:phone": "+1 440 353 3602",
    "sg:postcode": "44039",
    "sg:province": "OH",
    "sg:tags": [
      "hanging",
      "contractor"
    ],
    "wof:name": "Discount Wall Coverings Inc",
    "wof:placetype": "venue"
  },
  "geometry": {"coordinates":[-81.995218,41.418764],"type":"Point"}
}
