{
  "type": "Feature",
  "properties": {
    "addr:full": "4936 Park Ave W Seville OH 44273",
    "addr:housenumber": "4936",
    "addr:postcode": "44273",
    "addr:street": "Park Ave W",
    "iso:country": "US",
    "sg:address": "4936 Park Ave W",
    "sg:city": "Seville",
    "sg:classifiers": [
      {
        "category": "Personal",
        "subcategory": "Beauty Salon",
        "type": "Services"
      }
    ],
    "sg:phone": "+1 330 769 7697",
    "sg:postcode": "44273",
    "sg:province": "OH",
    "wof:name": "Park Avenue Style",
    "wof:placetype": "venue"
  },
  "geometry": {"coordinates":[-81.865498,41.034553],"type":"Point"}
}
