{
  "type": "Feature",
  "properties": {
    "addr:full": "5789 Kensington Ridge Dr Cincinnati OH 45230",
    "addr:housenumber": "5789",
    "addr:postcode": "45230",
    "addr:street": "Kensington Ridge Dr",
    "iso:country": "US",
    "sg:address": "5789 Kensington Ridge Dr",
    "sg:city": "Cincinnati",
    "sg:classifiers": [
      {
        "category": "Restaurant",
        "type": "Food \u0026 Drink"
      }
    ],
    "sg:phone": "+1 513 231 9064",
    "sg:postcode": "45230",
    "sg:province": "OH",
    "sg:tags": [
      "eating"
    ],
    "wof:name": "Smartexecutivecom Inc",
    "wof:placetype": "venue"
  },
  "geometry": {"coordinates":[-84.399004,39.076505],"type":"Point"}
}
