{
  "type": "Feature",
  "properties": {
    "iso:country":"US",
    "sg:address":"5789 Kensington Ridge Dr",
    "sg:city":"Cincinnati",
    "sg:classifiers":[
        {
            "category":"Restaurant",
            "type":"Food & Drink"
        }
    ],
    "sg:phone":"+1 513 231 9064",
    "sg:postcode":"45230",
    "sg:province":"OH",
    "sg:tags":[
        "eating"
    ],
    "wof:name":"Smartexecutivecom Inc",
    "wof:placetype":"venue"
},
  "geometry": {"coordinates":[-84.39900400000001,39.076505],"type":"Point"}
}