{
  "type": "Feature",
  "properties": {
    "iso:country":"US",
    "sg:address":"12901 Shaw Ave",
    "sg:city":"Cleveland",
    "sg:classifiers":[
        {
            "category":"Restaurant",
            "type":"Food & Drink"
        }
    ],
    "sg:phone":"+1 216 268 4983",
    "sg:postcode":"44108",
    "sg:province":"OH",
    "sg:tags":[
        "house",
        "steak"
    ],
    "sg:website":"http://www.manusa.com",
    "wof:name":"Shaw Savmor Bylight Sprmkt",
    "wof:placetype":"venue"
},
  "geometry": {"coordinates":[-81.59386499999999,41.540879],"type":"Point"}
}