{
  "type": "Feature",
  "properties": {
    "addr:full": "3950 Prospect Ave E Cleveland OH 44115",
    "addr:housenumber": "3950",
    "addr:postcode": "44115",
    "addr:street": "Prospect Ave E",
    "iso:country": "US",
    "sg:address": "3950 Prospect Ave E",
    "sg:city": "Cleveland",
    "sg:classifiers": [
      {
        "category": "Wholesale",
        "subcategory": "Painting Supplies",
        "type": "Manufacturing \u0026 Wholesale Goods"
      }
    ],
    "sg:phone": "+1 216 431 3562",
    "sg:postcode": "44115",
    "sg:province": "OH",
    "sg:tags": [
      "covering",
      "wall",
      "mfg",
      "design",
      "housewares-wholesale",
      "manufacturer"
    ],
    "sg:website": "http://www.blonderwall.com",
    "wof:name": "Blonder Home Accents",
    "wof:placetype": "venue"
  },
  "geometry": {"coordinates":[-81.660245,41.501971],"type":"Point"}
}
