{
  "type": "Feature",
  "properties": {
    "addr:full": "1655 Hess Rd Toledo OH 43615",
    "addr:housenumber": "1655",
    "addr:postcode": "43615",
    "addr:street": "Hess Rd",
    "iso:country": "US",
    "sg:address": "1655 Hess Rd",
    "sg:city": "Toledo",
    "sg:classifiers": [
      {
        "category": "Shopping",
        "subcategory": "Clothing, Apparel, \u0026 Fashions",
        "type": "Retail Goods"
      }
    ],
    "sg:phone": "+1 419 531 7888",
    "sg:postcode": "43615",
    "sg:province": "OH",
    "sg:tags": [
      "t"
    ],
    "wof:name": "Millennium Grafix",
    "wof:placetype": "venue"
  },
  "geometry": {"coordinates":[-83.666889,41.654279],"type":"Point"}
}
