{
  "type": "Feature",
  "properties": {
    "addr:full":"7826 Saint Clair Ave Cleveland OH 44103",
    "addr:housenumber":"7826",
    "addr:postcode":"44103",
    "addr:street":"Saint Clair Ave",
    "iso:country":"US",
    "sg:address":"7826 Saint Clair Ave",
    "sg:city":"Cleveland",
    "sg:classifiers":[
        {
            "category":"Restaurant",
            "type":"Food & Drink"
        }
    ],
    "sg:phone":"+1 216 431 4519",
    "sg:postcode":"44103",
    "sg:province":"OH",
    "sg:tags":[
        "eating"
    ],
    "wof:name":"Victory Lunch Inc",
    "wof:placetype":"venue"
},
  "geometry": {"coordinates":[-81.63377699999999,41.530364],"type":"Point"}
}