{
  "type": "Feature",
  "properties": {
    "addr:full": "4513 Spokane Ave Cleveland OH 44109",
    "addr:housenumber": "4513",
    "addr:postcode": "44109",
    "addr:street": "Spokane Ave",
    "iso:country": "US",
    "sg:address": "4513 Spokane Ave",
    "sg:city": "Cleveland",
    "sg:classifiers": [
      {
        "category": "Building \u0026 Trades",
        "subcategory": "Plumbing",
        "type": "Services"
      }
    ],
    "sg:phone": "+1 216 398 6699",
    "sg:postcode": "44109",
    "sg:province": "OH",
    "sg:tags": [
      "conditioning",
      "air",
      "system",
      "contractor"
    ],
    "wof:name": "Weathertemp",
    "wof:placetype": "venue"
  },
  "geometry": {"coordinates":[-81.717876,41.4382],"type":"Point"}
}
