{
  "type": "Feature",
  "properties": {
    "iso:country":"US",
    "sg:address":"7034 Vine St",
    "sg:city":"Cincinnati",
    "sg:classifiers":[
        {
            "category":"Personal",
            "subcategory":"Beauty Salon",
            "type":"Services"
        }
    ],
    "sg:phone":"+1 513 761 6444",
    "sg:postcode":"45216",
    "sg:province":"OH",
    "wof:name":"Carthage Creative Cuts",
    "wof:placetype":"venue"
},
  "geometry": {"coordinates":[-84.48029699999999,39.194063],"type":"Point"}
}