{
  "type": "Feature",
  "properties": {
    "addr:full":"1446 Thornwood Dr SW Heath OH 43056",
    "addr:housenumber":"1446",
    "addr:postcode":"43056",
    "addr:street":"Thornwood Dr Sw",
    "iso:country":"US",
    "sg:address":"1446 Thornwood Dr SW",
    "sg:city":"Heath",
    "sg:classifiers":[
        {
            "category":"Recreation",
            "type":"Entertainment"
        }
    ],
    "sg:phone":"+1 740 403 6116",
    "sg:postcode":"43056",
    "sg:province":"OH",
    "sg:tags":[
        "stable"
    ],
    "wof:name":"Dusty Bottom Stables",
    "wof:placetype":"venue"
},
  "geometry": {"coordinates":[-82.481736,40.003476],"type":"Point"}
}