{
  "type": "Feature",
  "properties": {
    "iso:country":"US",
    "sg:address":"7765 Refugee Rd",
    "sg:city":"Pickerington",
    "sg:classifiers":[
        {
            "category":"Wholesale",
            "subcategory":"Farm Supplies",
            "type":"Manufacturing & Wholesale Goods"
        }
    ],
    "sg:phone":"+1 614 833 6160",
    "sg:postcode":"43147",
    "sg:province":"OH",
    "wof:name":"Ohio Mulch",
    "wof:placetype":"venue"
},
  "geometry": {"coordinates":[-82.733572,39.907403],"type":"Point"}
}