{
  "type": "Feature",
  "properties": {
    "iso:country":"US",
    "sg:address":"601 Jacqueline Ct",
    "sg:city":"Holland",
    "sg:classifiers":[
        {
            "category":"Professional",
            "type":"Services"
        }
    ],
    "sg:phone":"+1 419 255 2073",
    "sg:postcode":"43528",
    "sg:province":"OH",
    "wof:name":"Ebony Bazaar",
    "wof:placetype":"venue"
},
  "geometry": {"coordinates":[-83.739497,41.630944],"type":"Point"}
}