{
  "type": "Feature",
  "properties": {
    "iso:country":"US",
    "sg:address":"900 Goodale Blvd",
    "sg:city":"Columbus",
    "sg:classifiers":[
        {
            "category":"Restaurant",
            "type":"Food & Drink"
        }
    ],
    "sg:menulink":"http://www.allmenus.com/oh/columbus/19269-the-buckeye-hall-of-fame-cafe/menu/",
    "sg:phone":"+1 614 291 2233",
    "sg:postcode":"43212",
    "sg:province":"OH",
    "sg:tags":[
        "american",
        "sandwich"
    ],
    "wof:name":"Buckeye Grill",
    "wof:placetype":"venue"
},
  "geometry": {"coordinates":[-83.02745,39.974311],"type":"Point"}
}