{
  "type": "Feature",
  "properties": {
    "addr:full": "2760 Parkman Rd NW Warren OH 44485",
    "addr:housenumber": "2760",
    "addr:postcode": "44485",
    "addr:street": "Parkman Rd Nw",
    "iso:country": "US",
    "sg:address": "2760 Parkman Rd NW",
    "sg:city": "Warren",
    "sg:classifiers": [
      {
        "category": "Health Services",
        "subcategory": "Podiatrist",
        "type": "Services"
      }
    ],
    "sg:phone": "+1 330 898 1800",
    "sg:postcode": "44485",
    "sg:province": "OH",
    "wof:name": "Associates Family Foot Care",
    "wof:placetype": "venue"
  },
  "geometry": {"coordinates":[-80.860377,41.2547],"type":"Point"}
}
