{
  "type": "Feature",
  "properties": {
    "addr:full": "6405 Berry Pond Way Canal Winchester OH 43110",
    "addr:housenumber": "6405",
    "addr:postcode": "43110",
    "addr:street": "Berry Pond Way",
    "iso:country": "US",
    "sg:address": "6405 Berry Pond Way",
    "sg:city": "Canal Winchester",
    "sg:classifiers": [
      {
        "category": "Wholesale",
        "subcategory": "Metals \u0026 Minerals",
        "type": "Manufacturing \u0026 Wholesale Goods"
      }
    ],
    "sg:phone": "+1 614 837 9524",
    "sg:postcode": "43110",
    "sg:province": "OH",
    "sg:tags": [
      "center"
    ],
    "wof:name": "Distinctive Metal Art",
    "wof:placetype": "venue"
  },
  "geometry": {"coordinates":[-82.827824,39.910415],"type":"Point"}
}
