{
  "type": "Feature",
  "properties": {
    "iso:country":"US",
    "sg:address":"6405 Berry Pond Way",
    "sg:city":"Canal Winchester",
    "sg:classifiers":[
        {
            "category":"Wholesale",
            "subcategory":"Metals & Minerals",
            "type":"Manufacturing & Wholesale Goods"
        }
    ],
    "sg:phone":"+1 614 837 9524",
    "sg:postcode":"43110",
    "sg:province":"OH",
    "sg:tags":[
        "center"
    ],
    "wof:name":"Distinctive Metal Art",
    "wof:placetype":"venue"
},
  "geometry": {"coordinates":[-82.82782400000001,39.910415],"type":"Point"}
}