{
  "type": "Feature",
  "properties": {
    "addr:full": "3033 Tod Ave NW Warren OH 44485",
    "addr:housenumber": "3033",
    "addr:postcode": "44485",
    "addr:street": "Tod Ave Nw",
    "iso:country": "US",
    "sg:address": "3033 Tod Ave NW",
    "sg:city": "Warren",
    "sg:classifiers": [
      {
        "category": "Social Services",
        "subcategory": "Adult Care",
        "type": "Services"
      }
    ],
    "sg:phone": "+1 330 898 4053",
    "sg:postcode": "44485",
    "sg:province": "OH",
    "sg:tags": [
      "home",
      "residential"
    ],
    "wof:name": "Silver Lining",
    "wof:placetype": "venue"
  },
  "geometry": {"coordinates":[-80.839271,41.259962],"type":"Point"}
}
