{
  "type": "Feature",
  "properties": {
    "iso:country":"US",
    "sg:address":"7970 Bricker Rd NW",
    "sg:city":"Massillon",
    "sg:classifiers":[
        {
            "category":"Shopping",
            "subcategory":"Used Merchandise",
            "type":"Retail Goods"
        }
    ],
    "sg:phone":"+1 330 854 5282",
    "sg:postcode":"44646",
    "sg:province":"OH",
    "wof:name":"J & J Collectiques",
    "wof:placetype":"venue"
},
  "geometry": {"coordinates":[-81.524457,40.893963],"type":"Point"}
}