{
  "type": "Feature",
  "properties": {
    "addr:full": "7970 Bricker Rd NW Massillon OH 44646",
    "addr:housenumber": "7970",
    "addr:postcode": "44646",
    "addr:street": "Bricker Rd Nw",
    "iso:country": "US",
    "sg:address": "7970 Bricker Rd NW",
    "sg:city": "Massillon",
    "sg:classifiers": [
      {
        "category": "Shopping",
        "subcategory": "Used Merchandise",
        "type": "Retail Goods"
      }
    ],
    "sg:phone": "+1 330 854 5282",
    "sg:postcode": "44646",
    "sg:province": "OH",
    "wof:name": "J \u0026 J Collectiques",
    "wof:placetype": "venue"
  },
  "geometry": {"coordinates":[-81.524457,40.893963],"type":"Point"}
}
