{
  "type": "Feature",
  "properties": {
    "addr:full":"11414 Airport Hwy Swanton OH 43558",
    "addr:housenumber":"11414",
    "addr:postcode":"43558",
    "addr:street":"Airport Hwy",
    "iso:country":"US",
    "sg:address":"11414 Airport Hwy",
    "sg:city":"Swanton",
    "sg:classifiers":[
        {
            "category":"Autos & Motor Vehicles",
            "subcategory":"Auto Supplies",
            "type":"Retail Goods"
        }
    ],
    "sg:phone":"+1 419 826 1922",
    "sg:postcode":"43558",
    "sg:province":"OH",
    "wof:name":"Pike Machinery & Wrecking",
    "wof:placetype":"venue"
},
  "geometry": {"coordinates":[-83.814752,41.592129],"type":"Point"}
}