{
  "type": "Feature",
  "properties": {
    "addr:full":"1139 Fehl Ln Cincinnati OH 45230",
    "addr:housenumber":"1139",
    "addr:postcode":"45230",
    "addr:street":"Fehl Ln",
    "iso:country":"US",
    "sg:address":"1139 Fehl Ln",
    "sg:city":"Cincinnati",
    "sg:classifiers":[
        {
            "category":"Professional",
            "subcategory":"Business Services",
            "type":"Services"
        }
    ],
    "sg:phone":"+1 513 624 9988",
    "sg:postcode":"45230",
    "sg:province":"OH",
    "sg:tags":[
        "convention",
        "meeting",
        "facility"
    ],
    "wof:name":"Goyer Management Intl",
    "wof:placetype":"venue"
},
  "geometry": {"coordinates":[-84.352442,39.070972],"type":"Point"}
}