{
  "type": "Feature",
  "properties": {
    "addr:full": "1235 Triplett Blvd Akron OH 44306",
    "addr:housenumber": "1235",
    "addr:postcode": "44306",
    "addr:street": "Triplett Blvd",
    "iso:country": "US",
    "sg:address": "1235 Triplett Blvd",
    "sg:city": "Akron",
    "sg:classifiers": [
      {
        "category": "Autos \u0026 Motor Vehicles",
        "subcategory": "Fuel \u0026 Gas Station",
        "type": "Retail Goods"
      }
    ],
    "sg:phone": "+1 330 724 9849",
    "sg:postcode": "44306",
    "sg:province": "OH",
    "sg:tags": [
      "station",
      "gasoline",
      "oil"
    ],
    "wof:name": "Holland Oil Company",
    "wof:placetype": "venue"
  },
  "geometry": {"coordinates":[-81.482841,41.041586],"type":"Point"}
}
