{
  "type": "Feature",
  "properties": {
    "iso:country":"US",
    "sg:address":"1235 Triplett Blvd",
    "sg:city":"Akron",
    "sg:classifiers":[
        {
            "category":"Autos & Motor Vehicles",
            "subcategory":"Fuel & Gas Station",
            "type":"Retail Goods"
        }
    ],
    "sg:phone":"+1 330 724 9849",
    "sg:postcode":"44306",
    "sg:province":"OH",
    "sg:tags":[
        "station",
        "gasoline",
        "oil"
    ],
    "wof:name":"Holland Oil Company",
    "wof:placetype":"venue"
},
  "geometry": {"coordinates":[-81.48284099999999,41.041586],"type":"Point"}
}