{
  "type": "Feature",
  "properties": {
    "addr:full": "13826 Hannan Trace Rd Crown City OH 45623",
    "addr:postcode": "13826;45623",
    "addr:street": "Hannan Trace Rd",
    "iso:country": "US",
    "sg:address": "13826 Hannan Trace Rd",
    "sg:city": "Crown City",
    "sg:classifiers": [
      {
        "category": "Home \u0026 Garden",
        "subcategory": "Carpets \u0026 Floor Coverings",
        "type": "Retail Goods"
      }
    ],
    "sg:phone": "+1 740 256 1267",
    "sg:postcode": "45623",
    "sg:province": "OH",
    "wof:name": "Carpet Designs",
    "wof:placetype": "venue"
  },
  "geometry": {"coordinates":[-82.26217,38.63301],"type":"Point"}
}
