{
  "type": "Feature",
  "properties": {
    "addr:full":"944 E River St Elyria OH 44035",
    "addr:housenumber":"944",
    "addr:postcode":"44035",
    "addr:street":"E River St",
    "iso:country":"US",
    "sg:address":"944 E River St",
    "sg:city":"Elyria",
    "sg:classifiers":[
        {
            "category":"Building & Trades",
            "subcategory":"Construction",
            "type":"Services"
        }
    ],
    "sg:phone":"+1 440 323 7711",
    "sg:postcode":"44035",
    "sg:province":"OH",
    "sg:tags":[
        "house"
    ],
    "wof:name":"Ocheltree Kitchen & Bath",
    "wof:placetype":"venue"
},
  "geometry": {"coordinates":[-82.10096299999999,41.36188],"type":"Point"}
}