{
  "type": "Feature",
  "properties": {
    "iso:country":"US",
    "sg:address":"859 Dixie Hwy",
    "sg:city":"Rossford",
    "sg:classifiers":[
        {
            "category":"Cinema",
            "subcategory":"Movie Rental",
            "type":"Entertainment"
        }
    ],
    "sg:phone":"+1 419 661 1319",
    "sg:postcode":"43460",
    "sg:province":"OH",
    "sg:tags":[
        "leasing",
        "video",
        "disc",
        "tape"
    ],
    "sg:website":"www.moviegallery.com",
    "wof:name":"Movie Gallery",
    "wof:placetype":"venue"
},
  "geometry": {"coordinates":[-83.561885,41.606881],"type":"Point"}
}