{
  "type": "Feature",
  "properties": {
    "iso:country":"US",
    "sg:address":"76 E Dennick Ave",
    "sg:city":"Youngstown",
    "sg:classifiers":[
        {
            "category":"Manufacturing",
            "subcategory":"Tools & Machinery",
            "type":"Manufacturing & Wholesale Goods"
        }
    ],
    "sg:phone":"+1 330 746 4488",
    "sg:postcode":"44505",
    "sg:province":"OH",
    "sg:tags":[
        "process",
        "industrial",
        "furnace",
        "mfg"
    ],
    "wof:name":"Advanced Furnace Dynamics Inc",
    "wof:placetype":"venue"
},
  "geometry": {"coordinates":[-80.63855700000001,41.129878],"type":"Point"}
}