{
  "type": "Feature",
  "properties": {
    "iso:country":"US",
    "sg:address":"441 Lohr Rd",
    "sg:city":"Mansfield",
    "sg:classifiers":[
        {
            "category":"Shopping",
            "subcategory":"Shoes",
            "type":"Retail Goods"
        }
    ],
    "sg:phone":"+1 419 529 4389",
    "sg:postcode":"44903",
    "sg:province":"OH",
    "wof:name":"Kathy S Dust Buster Clean",
    "wof:placetype":"venue"
},
  "geometry": {"coordinates":[-82.688641,40.74881],"type":"Point"}
}