{
  "type": "Feature",
  "properties": {
    "addr:full": "775 Fountain St Marion OH 43302",
    "addr:housenumber": "775",
    "addr:postcode": "43302",
    "addr:street": "Fountain St",
    "iso:country": "US",
    "sg:address": "775 Fountain St",
    "sg:city": "Marion",
    "sg:classifiers": [
      {
        "category": "Organizations",
        "subcategory": "Religious Organization",
        "type": "Services"
      }
    ],
    "sg:phone": "+1 740 382 6548",
    "sg:postcode": "43302",
    "sg:province": "OH",
    "wof:name": "Pentecostal Church of Christ",
    "wof:placetype": "venue"
  },
  "geometry": {"coordinates":[-83.154878,40.604798],"type":"Point"}
}
