{
  "type": "Feature",
  "properties": {
    "addr:full":"602 South St Chardon OH 44024",
    "addr:housenumber":"602",
    "addr:postcode":"44024",
    "addr:street":"South St",
    "iso:country":"US",
    "sg:address":"602 South St",
    "sg:city":"Chardon",
    "sg:classifiers":[
        {
            "category":"Banks & Credit Unions",
            "subcategory":"Bank",
            "type":"Services"
        }
    ],
    "sg:phone":"+1 440 279 0145",
    "sg:postcode":"44024",
    "sg:province":"OH",
    "wof:name":"Commerce Bank Leasing",
    "wof:placetype":"venue"
},
  "geometry": {"coordinates":[-81.20018899999999,41.562309],"type":"Point"}
}