{
  "type": "Feature",
  "properties": {
    "addr:full":"45 Orchard Rd Wilmington OH 45177",
    "addr:housenumber":"45",
    "addr:postcode":"45177",
    "addr:street":"Orchard Rd",
    "iso:country":"US",
    "sg:address":"45 Orchard Rd",
    "sg:city":"Wilmington",
    "sg:classifiers":[
        {
            "category":"Retail",
            "subcategory":"Veterinary Services",
            "type":"Services"
        }
    ],
    "sg:phone":"+1 937 383 0008",
    "sg:postcode":"45177",
    "sg:province":"OH",
    "sg:tags":[
        "veterinarian"
    ],
    "wof:name":"Orchard Animal Care",
    "wof:placetype":"venue"
},
  "geometry": {"coordinates":[-83.837816,39.475249],"type":"Point"}
}