{
  "type": "Feature",
  "properties": {
    "addr:full": "1466 Reserve Dr Akron OH 44333",
    "addr:housenumber": "1466",
    "addr:postcode": "44333",
    "addr:street": "Reserve Dr",
    "iso:country": "US",
    "sg:address": "1466 Reserve Dr",
    "sg:city": "Akron",
    "sg:classifiers": [
      {
        "category": "Real Estate",
        "subcategory": "Real Estate Agent",
        "type": "Services"
      }
    ],
    "sg:phone": "+1 330 668 4744",
    "sg:postcode": "44333",
    "sg:province": "OH",
    "sg:tags": [
      "consultant"
    ],
    "wof:name": "Banke' Consultants",
    "wof:placetype": "venue"
  },
  "geometry": {"coordinates":[-81.674072,41.174428],"type":"Point"}
}
