{
  "type": "Feature",
  "properties": {
    "addr:full": "2118 Maplewood Dr Columbus OH 43229",
    "addr:housenumber": "2118",
    "addr:postcode": "43229",
    "addr:street": "Maplewood Dr",
    "iso:country": "US",
    "sg:address": "2118 Maplewood Dr",
    "sg:city": "Columbus",
    "sg:classifiers": [
      {
        "category": "Restaurant",
        "type": "Food \u0026 Drink"
      }
    ],
    "sg:phone": "+1 614 898 9956",
    "sg:postcode": "43229",
    "sg:province": "OH",
    "sg:tags": [
      "eating"
    ],
    "wof:name": "Will's Salad Bar",
    "wof:placetype": "venue"
  },
  "geometry": {"coordinates":[-82.960243,40.074133],"type":"Point"}
}
