{
  "type": "Feature",
  "properties": {
    "addr:full": "3255 Laurel Rd Brunswick OH 44212",
    "addr:housenumber": "3255",
    "addr:postcode": "44212",
    "addr:street": "Laurel Rd",
    "iso:country": "US",
    "sg:address": "3255 Laurel Rd",
    "sg:city": "Brunswick",
    "sg:classifiers": [
      {
        "category": "Building \u0026 Trades",
        "subcategory": "Plumbing",
        "type": "Services"
      }
    ],
    "sg:phone": "+1 440 842 5959",
    "sg:postcode": "44212",
    "sg:province": "OH",
    "sg:tags": [
      "plumbing",
      "contractor"
    ],
    "wof:name": "Modern Plumbing \u0026 Heating Co",
    "wof:placetype": "venue"
  },
  "geometry": {"coordinates":[-81.802565,41.226906],"type":"Point"}
}
