{
  "type": "Feature",
  "properties": {
    "addr:full":"3407 Cleveland Ave Columbus OH 43224",
    "addr:housenumber":"3407",
    "addr:postcode":"43224",
    "addr:street":"Cleveland Ave",
    "iso:country":"US",
    "sg:address":"3407 Cleveland Ave",
    "sg:city":"Columbus",
    "sg:classifiers":[
        {
            "category":"Banks & Credit Unions",
            "subcategory":"Bank",
            "type":"Services"
        }
    ],
    "sg:phone":"+1 614 262 4888",
    "sg:postcode":"43224",
    "sg:province":"OH",
    "sg:tags":[
        "state"
    ],
    "sg:website":"www.53.com",
    "wof:name":"Fifth Third Bank",
    "wof:placetype":"venue"
},
  "geometry": {"coordinates":[-82.963106,40.036157],"type":"Point"}
}