{
  "type": "Feature",
  "properties": {
    "iso:country":"US",
    "sg:address":"301 E Main St",
    "sg:city":"Junction City",
    "sg:classifiers":[
        {
            "category":"Autos & Motor Vehicles",
            "subcategory":"Automobile Sales",
            "type":"Retail Goods"
        }
    ],
    "sg:phone":"+1 740 987 2886",
    "sg:postcode":"43748",
    "sg:province":"OH",
    "sg:tags":[
        "car",
        "dealer"
    ],
    "wof:name":"Reliable Auto Sales",
    "wof:placetype":"venue"
},
  "geometry": {"coordinates":[-82.296538,39.721291],"type":"Point"}
}