{
  "type": "Feature",
  "properties": {
    "iso:country":"US",
    "sg:address":"719 Fox Rd",
    "sg:city":"Van Wert",
    "sg:classifiers":[
        {
            "category":"Food & Beverages",
            "subcategory":"Groceries & Convenience Stores",
            "type":"Retail Goods"
        }
    ],
    "sg:phone":"+1 419 238 5304",
    "sg:postcode":"45891",
    "sg:province":"OH",
    "sg:tags":[
        "grocer"
    ],
    "sg:website":"www.nashfinch.com",
    "wof:name":"Pick'n Save",
    "wof:placetype":"venue"
},
  "geometry": {"coordinates":[-84.596751,40.851684],"type":"Point"}
}