{
  "type": "Feature",
  "properties": {
    "addr:full": "7120 Sponagle Rd SE Sugar Grove OH 43155",
    "addr:housenumber": "7120",
    "addr:postcode": "43155",
    "addr:street": "Sponagle Rd Se",
    "iso:country": "US",
    "sg:address": "7120 Sponagle Rd SE",
    "sg:city": "Sugar Grove",
    "sg:classifiers": [
      {
        "category": "Organizations",
        "subcategory": "Religious Organization",
        "type": "Services"
      }
    ],
    "sg:phone": "+1 740 746 8316",
    "sg:postcode": "43155",
    "sg:province": "OH",
    "sg:tags": [
      "church"
    ],
    "wof:name": "Trinity Lutheran Church",
    "wof:placetype": "venue"
  },
  "geometry": {"coordinates":[-82.494534,39.631178],"type":"Point"}
}
