{
  "type": "Feature",
  "properties": {
    "addr:full": "3919 E Market St Warren OH 44484",
    "addr:housenumber": "3919",
    "addr:postcode": "44484",
    "addr:street": "E Market St",
    "iso:country": "US",
    "sg:address": "3919 E Market St",
    "sg:city": "Warren",
    "sg:classifiers": [
      {
        "category": "Health Services",
        "subcategory": "Doctor",
        "type": "Services"
      }
    ],
    "sg:phone": "+1 330 856 1433",
    "sg:postcode": "44484",
    "sg:province": "OH",
    "sg:tags": [
      "dentist"
    ],
    "wof:name": "Snelson \u0026 Snelson",
    "wof:placetype": "venue"
  },
  "geometry": {"coordinates":[-80.766611,41.237188],"type":"Point"}
}
