{
  "type": "Feature",
  "properties": {
    "addr:full":"422 Front St Marietta OH 45750",
    "addr:housenumber":"422",
    "addr:postcode":"45750",
    "addr:street":"Front St",
    "iso:country":"US",
    "sg:address":"422 Front St",
    "sg:city":"Marietta",
    "sg:classifiers":[
        {
            "category":"Mining & Drilling",
            "type":"Manufacturing & Wholesale Goods"
        }
    ],
    "sg:phone":"+1 740 374 5383",
    "sg:postcode":"45750",
    "sg:province":"OH",
    "sg:tags":[
        "field",
        "oil"
    ],
    "wof:name":"Concord Well Svc",
    "wof:placetype":"venue"
},
  "geometry": {"coordinates":[-81.45801899999999,39.416514],"type":"Point"}
}