{
  "type": "Feature",
  "properties": {
    "iso:country":"US",
    "sg:address":"5452 Co Rd 201",
    "sg:city":"Millersburg",
    "sg:classifiers":[
        {
            "category":"Manufacturing",
            "subcategory":"Rubber & Plastics",
            "type":"Manufacturing & Wholesale Goods"
        }
    ],
    "sg:phone":"+1 330 893 3060",
    "sg:postcode":"44654",
    "sg:province":"OH",
    "sg:tags":[
        "product",
        "fabricated",
        "mfg"
    ],
    "wof:name":"Unique Plastics",
    "wof:placetype":"venue"
},
  "geometry": {"coordinates":[-81.82081599999999,40.558953],"type":"Point"}
}