{
  "type": "Feature",
  "properties": {
    "addr:full": "5452 Co Rd 201 Millersburg OH 44654",
    "addr:housenumber": "5452",
    "addr:postcode": "201;44654",
    "addr:street": "Co Rd",
    "iso:country": "US",
    "sg:address": "5452 Co Rd 201",
    "sg:city": "Millersburg",
    "sg:classifiers": [
      {
        "category": "Manufacturing",
        "subcategory": "Rubber \u0026 Plastics",
        "type": "Manufacturing \u0026 Wholesale Goods"
      }
    ],
    "sg:phone": "+1 330 893 3060",
    "sg:postcode": "44654",
    "sg:province": "OH",
    "sg:tags": [
      "product",
      "fabricated",
      "mfg"
    ],
    "wof:name": "Unique Plastics",
    "wof:placetype": "venue"
  },
  "geometry": {"coordinates":[-81.820816,40.558953],"type":"Point"}
}
