{
  "type": "Feature",
  "properties": {
    "iso:country":"US",
    "sg:address":"10233 Munson Rd",
    "sg:city":"Shreve",
    "sg:classifiers":[
        {
            "category":"Farming",
            "subcategory":"Livestock Farm",
            "type":"Manufacturing & Wholesale Goods"
        }
    ],
    "sg:phone":"+1 330 695 5002",
    "sg:postcode":"44676",
    "sg:province":"OH",
    "wof:name":"James Anderson",
    "wof:placetype":"venue"
},
  "geometry": {"coordinates":[-81.93357,40.677831],"type":"Point"}
}