{
  "type": "Feature",
  "properties": {
    "addr:full":"831 Mc Clain Rd Columbus OH 43212",
    "addr:housenumber":"831",
    "addr:postcode":"43212",
    "addr:street":"Mc Clain Rd",
    "iso:country":"US",
    "sg:address":"831 Mc Clain Rd",
    "sg:city":"Columbus",
    "sg:classifiers":[
        {
            "category":"Shopping",
            "type":"Retail Goods"
        }
    ],
    "sg:phone":"+1 614 270 0638",
    "sg:postcode":"43212",
    "sg:province":"OH",
    "sg:tags":[
        "rental",
        "audio",
        "installation",
        "sales"
    ],
    "wof:name":"Macroline Sound Technology",
    "wof:placetype":"venue"
},
  "geometry": {"coordinates":[-83.036113,39.975807],"type":"Point"}
}