{
  "type": "Feature",
  "properties": {
    "addr:full": "1454 S Smyser Rd Wooster OH 44691",
    "addr:housenumber": "1454",
    "addr:postcode": "44691",
    "addr:street": "S Smyser Rd",
    "iso:country": "US",
    "sg:address": "1454 S Smyser Rd",
    "sg:city": "Wooster",
    "sg:classifiers": [
      {
        "category": "Building \u0026 Trades",
        "subcategory": "Construction",
        "type": "Services"
      }
    ],
    "sg:phone": "+1 330 262 1907",
    "sg:postcode": "44691",
    "sg:province": "OH",
    "sg:tags": [
      "excavating",
      "contractor"
    ],
    "wof:name": "Griffith Excavating",
    "wof:placetype": "venue"
  },
  "geometry": {"coordinates":[-81.994275,40.781932],"type":"Point"}
}
