{
  "type": "Feature",
  "properties": {
    "addr:full": "11576 Twp Rd K Napoleon OH 43545",
    "addr:housenumber": "11576",
    "addr:postcode": "43545",
    "addr:street": "Twp Rd",
    "iso:country": "US",
    "sg:address": "11576 Twp Rd K",
    "sg:city": "Napoleon",
    "sg:phone": "+1 419 592 0129",
    "sg:postcode": "43545",
    "sg:province": "OH",
    "sg:tags": [
      "farm",
      "corn",
      "grain",
      "cash"
    ],
    "wof:name": "Ronnie Rohrs",
    "wof:placetype": "venue"
  },
  "geometry": {"coordinates":[-84.086778,41.31204],"type":"Point"}
}
