{
  "type": "Feature",
  "properties": {
    "iso:country":"US",
    "sg:address":"323 W Water St",
    "sg:city":"Oak Harbor",
    "sg:classifiers":[
        {
            "category":"Autos & Motor Vehicles",
            "subcategory":"Fuel & Gas Station",
            "type":"Retail Goods"
        }
    ],
    "sg:phone":"+1 419 898 3344",
    "sg:postcode":"43449",
    "sg:province":"OH",
    "sg:tags":[
        "oil"
    ],
    "wof:name":"Sunoco Friendship",
    "wof:placetype":"venue"
},
  "geometry": {"coordinates":[-83.151385,41.507989],"type":"Point"}
}