{
  "type": "Feature",
  "properties": {
    "addr:full": "1475 Sand Run Rd Akron OH 44313",
    "addr:housenumber": "1475",
    "addr:postcode": "44313",
    "addr:street": "Sand Run Rd",
    "iso:country": "US",
    "sg:address": "1475 Sand Run Rd",
    "sg:city": "Akron",
    "sg:classifiers": [
      {
        "category": "Shopping",
        "subcategory": "Bicycles \u0026 Sporting Goods",
        "type": "Retail Goods"
      }
    ],
    "sg:phone": "+1 330 865 8060",
    "sg:postcode": "44313",
    "sg:province": "OH",
    "sg:tags": [
      "place",
      "arcade",
      "amusement"
    ],
    "wof:name": "Bike \u0026 Trail",
    "wof:placetype": "venue"
  },
  "geometry": {"coordinates":[-81.587268,41.156147],"type":"Point"}
}
