{
  "type": "Feature",
  "properties": {
    "iso:country":"US",
    "sg:address":"1475 Sand Run Rd",
    "sg:city":"Akron",
    "sg:classifiers":[
        {
            "category":"Shopping",
            "subcategory":"Bicycles & Sporting Goods",
            "type":"Retail Goods"
        }
    ],
    "sg:phone":"+1 330 865 8060",
    "sg:postcode":"44313",
    "sg:province":"OH",
    "sg:tags":[
        "place",
        "arcade",
        "amusement"
    ],
    "wof:name":"Bike & Trail",
    "wof:placetype":"venue"
},
  "geometry": {"coordinates":[-81.58726799999999,41.156147],"type":"Point"}
}