{
  "type": "Feature",
  "properties": {
    "addr:full":"1823 W 65th St Cleveland OH 44102",
    "addr:housenumber":"1823",
    "addr:postcode":"44102",
    "addr:street":"W 65Th St",
    "iso:country":"US",
    "sg:address":"1823 W 65th St",
    "sg:city":"Cleveland",
    "sg:classifiers":[
        {
            "category":"Restaurant",
            "type":"Food & Drink"
        }
    ],
    "sg:menulink":"http://www.allmenus.com/oh/cleveland/78296-dominos-pizza/menu/",
    "sg:phone":"+1 216 961 0030",
    "sg:postcode":"44102",
    "sg:province":"OH",
    "sg:tags":[
        "american",
        "wing",
        "pizza"
    ],
    "wof:name":"Domino's Pizza",
    "wof:placetype":"venue"
},
  "geometry": {"coordinates":[-81.729972,41.48155],"type":"Point"}
}