{
  "type": "Feature",
  "properties": {
    "addr:full":"1859 Section Rd Cincinnati OH 45237",
    "addr:housenumber":"1859",
    "addr:postcode":"45237",
    "addr:street":"Section Rd",
    "iso:country":"US",
    "sg:address":"1859 Section Rd",
    "sg:city":"Cincinnati",
    "sg:classifiers":[
        {
            "category":"Professional",
            "subcategory":"Engineering",
            "type":"Services"
        }
    ],
    "sg:phone":"+1 513 458 3060",
    "sg:postcode":"45237",
    "sg:province":"OH",
    "sg:tags":[
        "consultant",
        "automation",
        "engineer"
    ],
    "wof:name":"Q Point Robotic Solutions",
    "wof:placetype":"venue"
},
  "geometry": {"coordinates":[-84.454724,39.197218],"type":"Point"}
}