{
  "type": "Feature",
  "properties": {
    "iso:country":"US",
    "sg:address":"230 N High St",
    "sg:city":"Hillsboro",
    "sg:classifiers":[
        {
            "category":"Organizations",
            "subcategory":"Political Organization",
            "type":"Services"
        }
    ],
    "sg:phone":"+1 937 393 1067",
    "sg:postcode":"45133",
    "sg:province":"OH",
    "wof:name":"Republican Headquarter",
    "wof:placetype":"venue"
},
  "geometry": {"coordinates":[-83.61106,39.203771],"type":"Point"}
}