{
  "type": "Feature",
  "properties": {
    "iso:country":"US",
    "sg:address":"3131 Chelsea Dr",
    "sg:city":"Cleveland",
    "sg:classifiers":[
        {
            "category":"Restaurant",
            "type":"Food & Drink"
        }
    ],
    "sg:phone":"+1 216 371 3498",
    "sg:postcode":"44118",
    "sg:province":"OH",
    "sg:tags":[
        "banquet",
        "rooms"
    ],
    "wof:name":"Civic",
    "wof:placetype":"venue"
},
  "geometry": {"coordinates":[-81.564703,41.521626],"type":"Point"}
}