{
  "type": "Feature",
  "properties": {
    "addr:full": "12560 Island Rd Grafton OH 44044",
    "addr:housenumber": "12560",
    "addr:postcode": "44044",
    "addr:street": "Island Rd",
    "iso:country": "US",
    "sg:address": "12560 Island Rd",
    "sg:city": "Grafton",
    "sg:classifiers": [
      {
        "category": "Building \u0026 Trades",
        "subcategory": "Construction",
        "type": "Services"
      }
    ],
    "sg:phone": "+1 440 277 8909",
    "sg:postcode": "44044",
    "sg:province": "OH",
    "wof:name": "Island Road Free Will Baptist",
    "wof:placetype": "venue"
  },
  "geometry": {"coordinates":[-82.001539,41.303554],"type":"Point"}
}
