{
  "type": "Feature",
  "properties": {
    "addr:full": "72 Amelia-Olive Branch Rd Amelia OH 45102",
    "addr:housenumber": "72",
    "addr:postcode": "45102",
    "addr:street": "Amelia-Olive Branch Rd",
    "iso:country": "US",
    "sg:address": "72 Amelia-Olive Branch Rd",
    "sg:city": "Amelia",
    "sg:classifiers": [
      {
        "category": "Real Estate",
        "subcategory": "Real Estate Operator",
        "type": "Services"
      }
    ],
    "sg:phone": "+1 513 753 6022",
    "sg:postcode": "45102",
    "sg:province": "OH",
    "sg:tags": [
      "apartment"
    ],
    "wof:name": "Crown Station Apartments",
    "wof:placetype": "venue"
  },
  "geometry": {"coordinates":[-84.226833,39.041362],"type":"Point"}
}
