{
  "type": "Feature",
  "properties": {
    "addr:full": "1775 State Rte 39 Lucas OH 44843",
    "addr:housenumber": "1775",
    "addr:postcode": "44843",
    "addr:street": "State Rte 39",
    "iso:country": "US",
    "sg:address": "1775 State Rte 39",
    "sg:city": "Lucas",
    "sg:classifiers": [
      {
        "category": "Building \u0026 Trades",
        "subcategory": "Pest Control",
        "type": "Services"
      }
    ],
    "sg:phone": "+1 419 892 2166",
    "sg:postcode": "44843",
    "sg:province": "OH",
    "wof:name": "Absolute Pest Svc",
    "wof:placetype": "venue"
  },
  "geometry": {"coordinates":[-82.438819,40.710351],"type":"Point"}
}
