{
  "type": "Feature",
  "properties": {
    "addr:full":"2175 N West St Lima OH 45801",
    "addr:housenumber":"2175",
    "addr:postcode":"45801",
    "addr:street":"N West St",
    "iso:country":"US",
    "sg:address":"2175 N West St",
    "sg:city":"Lima",
    "sg:classifiers":[
        {
            "category":"Retail",
            "subcategory":"Veterinary Services",
            "type":"Services"
        }
    ],
    "sg:phone":"+1 419 227 6863",
    "sg:postcode":"45801",
    "sg:province":"OH",
    "wof:name":"Northwest Animal Clinic",
    "wof:placetype":"venue"
},
  "geometry": {"coordinates":[-84.108791,40.771399],"type":"Point"}
}