{
  "type": "Feature",
  "properties": {
    "addr:full": "2327 E Sand Rd Port Clinton OH 43452",
    "addr:housenumber": "2327",
    "addr:postcode": "43452",
    "addr:street": "E Sand Rd",
    "iso:country": "US",
    "sg:address": "2327 E Sand Rd",
    "sg:city": "Port Clinton",
    "sg:classifiers": [
      {
        "category": "Travel",
        "subcategory": "Hotels \u0026 Motels",
        "type": "Entertainment"
      }
    ],
    "sg:phone": "+1 419 734 3356",
    "sg:postcode": "43452",
    "sg:province": "OH",
    "sg:tags": [
      "cottage",
      "cabin"
    ],
    "wof:name": "Char-Nel Shores Resorts",
    "wof:placetype": "venue"
  },
  "geometry": {"coordinates":[-82.891857,41.519921],"type":"Point"}
}
