{
  "type": "Feature",
  "properties": {
    "iso:country":"US",
    "sg:address":"2327 E Sand Rd",
    "sg:city":"Port Clinton",
    "sg:classifiers":[
        {
            "category":"Travel",
            "subcategory":"Hotels & Motels",
            "type":"Entertainment"
        }
    ],
    "sg:phone":"+1 419 734 3356",
    "sg:postcode":"43452",
    "sg:province":"OH",
    "sg:tags":[
        "cottage",
        "cabin"
    ],
    "wof:name":"Char-Nel Shores Resorts",
    "wof:placetype":"venue"
},
  "geometry": {"coordinates":[-82.891857,41.519921],"type":"Point"}
}