{
  "type": "Feature",
  "properties": {
    "addr:full":"2700 Hidden Lakes Dr NE Warren OH 44410",
    "addr:housenumber":"2700",
    "addr:postcode":"44410",
    "addr:street":"Hidden Lakes Dr Ne",
    "iso:country":"US",
    "sg:address":"2700 Hidden Lakes Dr NE",
    "sg:city":"Warren",
    "sg:classifiers":[
        {
            "category":"Health Services",
            "subcategory":"Doctor",
            "type":"Services"
        }
    ],
    "sg:phone":"+1 330 609 6499",
    "sg:postcode":"44410",
    "sg:province":"OH",
    "sg:tags":[
        "dentist"
    ],
    "wof:name":"G C Charnas DDS",
    "wof:placetype":"venue"
},
  "geometry": {"coordinates":[-80.72648599999999,41.266605],"type":"Point"}
}