{
  "type": "Feature",
  "properties": {
    "iso:country":"US",
    "sg:address":"1760 Hilliard Rome Rd",
    "sg:city":"Hilliard",
    "sg:classifiers":[
        {
            "category":"Real Estate",
            "subcategory":"Real Estate Agent",
            "type":"Services"
        }
    ],
    "sg:phone":"+1 614 850 0460",
    "sg:postcode":"43026",
    "sg:province":"OH",
    "wof:name":"Continental Real Estate",
    "wof:placetype":"venue"
},
  "geometry": {"coordinates":[-83.151757,39.990614],"type":"Point"}
}