{
  "type": "Feature",
  "properties": {
    "iso:country":"US",
    "sg:address":"1420 Main St",
    "sg:city":"Cuyahoga Falls",
    "sg:classifiers":[
        {
            "category":"Travel",
            "subcategory":"Hotels & Motels",
            "type":"Entertainment"
        }
    ],
    "sg:phone":"+1 330 926 1233",
    "sg:postcode":"44221",
    "sg:province":"OH",
    "sg:website":"www.countryinns.com",
    "wof:name":"Country Inn & Suites",
    "wof:placetype":"venue"
},
  "geometry": {"coordinates":[-81.484371,41.120507],"type":"Point"}
}