{
  "type": "Feature",
  "properties": {
    "addr:full": "1420 Main St Cuyahoga Falls OH 44221",
    "addr:housenumber": "1420",
    "addr:postcode": "44221",
    "addr:street": "Main St",
    "iso:country": "US",
    "sg:address": "1420 Main St",
    "sg:city": "Cuyahoga Falls",
    "sg:classifiers": [
      {
        "category": "Travel",
        "subcategory": "Hotels \u0026 Motels",
        "type": "Entertainment"
      }
    ],
    "sg:phone": "+1 330 926 1233",
    "sg:postcode": "44221",
    "sg:province": "OH",
    "sg:website": "www.countryinns.com",
    "wof:name": "Country Inn \u0026 Suites",
    "wof:placetype": "venue"
  },
  "geometry": {"coordinates":[-81.484371,41.120507],"type":"Point"}
}
