{
  "type": "Feature",
  "properties": {
    "addr:full": "11974 Lebanon Rd Cincinnati OH 45241",
    "addr:housenumber": "11974",
    "addr:postcode": "45241",
    "addr:street": "Lebanon Rd",
    "iso:country": "US",
    "sg:address": "11974 Lebanon Rd",
    "sg:city": "Cincinnati",
    "sg:classifiers": [
      {
        "category": "Bars \u0026 Pubs",
        "type": "Food \u0026 Drink"
      }
    ],
    "sg:phone": "+1 513 563 0844",
    "sg:postcode": "45241",
    "sg:province": "OH",
    "sg:tags": [
      "drinking"
    ],
    "wof:name": "Autos Cadillac Ranch Inc",
    "wof:placetype": "venue"
  },
  "geometry": {"coordinates":[-84.394279,39.290847],"type":"Point"}
}
