{
  "type": "Feature",
  "properties": {
    "addr:full":"5819 Woodville Rd Northwood OH 43619",
    "addr:housenumber":"5819",
    "addr:postcode":"43619",
    "addr:street":"Woodville Rd",
    "iso:country":"US",
    "sg:address":"5819 Woodville Rd",
    "sg:city":"Northwood",
    "sg:classifiers":[
        {
            "category":"Building & Trades",
            "subcategory":"Landscaping Services",
            "type":"Services"
        }
    ],
    "sg:phone":"+1 419 836 7828",
    "sg:postcode":"43619",
    "sg:province":"OH",
    "sg:tags":[
        "heavy",
        "supply"
    ],
    "wof:name":"Woodville Road Nursery",
    "wof:placetype":"venue"
},
  "geometry": {"coordinates":[-83.435874,41.582944],"type":"Point"}
}