{
  "type": "Feature",
  "properties": {
    "addr:full": "1200 E 200th St Cleveland OH 44117",
    "addr:housenumber": "1200",
    "addr:postcode": "44117",
    "addr:street": "E 200Th St",
    "iso:country": "US",
    "sg:address": "1200 E 200th St",
    "sg:city": "Cleveland",
    "sg:classifiers": [
      {
        "category": "Education",
        "subcategory": "School",
        "type": "Public Place"
      }
    ],
    "sg:phone": "+1 216 383 5111",
    "sg:postcode": "44117",
    "sg:province": "OH",
    "wof:name": "Hannah Gibbons Elementary Schl",
    "wof:placetype": "venue"
  },
  "geometry": {"coordinates":[-81.539431,41.577849],"type":"Point"}
}
