{
  "type": "Feature",
  "properties": {
    "iso:country":"US",
    "sg:address":"108 W Washington St",
    "sg:city":"New Carlisle",
    "sg:classifiers":[
        {
            "category":"Retail",
            "subcategory":"Repair Shop",
            "type":"Services"
        }
    ],
    "sg:phone":"+1 937 846 1775",
    "sg:postcode":"45344",
    "sg:province":"OH",
    "sg:tags":[
        "welding"
    ],
    "wof:name":"Vernon Campbell",
    "wof:placetype":"venue"
},
  "geometry": {"coordinates":[-84.02507799999999,39.937024],"type":"Point"}
}