{
  "type": "Feature",
  "properties": {
    "addr:full": "987 E Ash St Piqua OH 45356",
    "addr:housenumber": "987",
    "addr:postcode": "45356",
    "addr:street": "E Ash St",
    "iso:country": "US",
    "sg:address": "987 E Ash St",
    "sg:city": "Piqua",
    "sg:classifiers": [
      {
        "category": "Personal",
        "subcategory": "Beauty Salon",
        "type": "Services"
      }
    ],
    "sg:phone": "+1 937 773 4343",
    "sg:postcode": "45356",
    "sg:province": "OH",
    "wof:name": "Master Cuts",
    "wof:placetype": "venue"
  },
  "geometry": {"coordinates":[-84.218711,40.150976],"type":"Point"}
}
