{
  "type": "Feature",
  "properties": {
    "addr:full": "34753 Rocksprings Rd Pomeroy OH 45769",
    "addr:housenumber": "34753",
    "addr:postcode": "45769",
    "addr:street": "Rocksprings Rd",
    "iso:country": "US",
    "sg:address": "34753 Rocksprings Rd",
    "sg:city": "Pomeroy",
    "sg:classifiers": [
      {
        "category": "Retail",
        "subcategory": "Laundry \u0026 Dry Cleaning",
        "type": "Services"
      }
    ],
    "sg:phone": "+1 740 992 6788",
    "sg:postcode": "45769",
    "sg:province": "OH",
    "sg:tags": [
      "cleaners",
      "rug",
      "carpet"
    ],
    "wof:name": "Stanley Steemer Carpet Cleaner",
    "wof:placetype": "venue"
  },
  "geometry": {"coordinates":[-82.016657,39.069531],"type":"Point"}
}
