{
  "type": "Feature",
  "properties": {
    "iso:country":"US",
    "sg:address":"34753 Rocksprings Rd",
    "sg:city":"Pomeroy",
    "sg:classifiers":[
        {
            "category":"Retail",
            "subcategory":"Laundry & Dry Cleaning",
            "type":"Services"
        }
    ],
    "sg:phone":"+1 740 992 6788",
    "sg:postcode":"45769",
    "sg:province":"OH",
    "sg:tags":[
        "cleaners",
        "rug",
        "carpet"
    ],
    "wof:name":"Stanley Steemer Carpet Cleaner",
    "wof:placetype":"venue"
},
  "geometry": {"coordinates":[-82.016657,39.069531],"type":"Point"}
}