{
  "type": "Feature",
  "properties": {
    "addr:full": "840 Parkview St Wauseon OH 43567",
    "addr:housenumber": "840",
    "addr:postcode": "43567",
    "addr:street": "Parkview St",
    "iso:country": "US",
    "sg:address": "840 Parkview St",
    "sg:city": "Wauseon",
    "sg:classifiers": [
      {
        "category": "Education",
        "subcategory": "School",
        "type": "Public Place"
      }
    ],
    "sg:phone": "+1 419 335 5756",
    "sg:postcode": "43567",
    "sg:province": "OH",
    "sg:website": "www.wauseon.k12.oh.us",
    "wof:name": "Wauseon High School",
    "wof:placetype": "venue"
  },
  "geometry": {"coordinates":[-84.130259,41.553689],"type":"Point"}
}
