{
  "type": "Feature",
  "properties": {
    "iso:country":"US",
    "sg:address":"3906 Linden Ave",
    "sg:city":"Dayton",
    "sg:classifiers":[
        {
            "category":"Shopping",
            "subcategory":"Used Merchandise",
            "type":"Retail Goods"
        }
    ],
    "sg:phone":"+1 937 253 7700",
    "sg:postcode":"45432",
    "sg:province":"OH",
    "sg:tags":[
        "carpet",
        "dealer",
        "rug"
    ],
    "wof:name":"Big Bob's Used Carpet Shop",
    "wof:placetype":"venue"
},
  "geometry": {"coordinates":[-84.123621,39.745916],"type":"Point"}
}