{
  "type": "Feature",
  "properties": {
    "addr:full": "3817 Center Rd Brunswick OH 44212",
    "addr:housenumber": "3817",
    "addr:postcode": "44212",
    "addr:street": "Center Rd",
    "iso:country": "US",
    "sg:address": "3817 Center Rd",
    "sg:city": "Brunswick",
    "sg:classifiers": [
      {
        "category": "Restaurant",
        "type": "Food \u0026 Drink"
      }
    ],
    "sg:phone": "+1 330 225 1666",
    "sg:postcode": "44212",
    "sg:province": "OH",
    "sg:tags": [
      "pizza"
    ],
    "wof:name": "Master Pizza Restaurant",
    "wof:placetype": "venue"
  },
  "geometry": {"coordinates":[-81.822904,41.238377],"type":"Point"}
}
