{
  "type": "Feature",
  "properties": {
    "addr:full":"4374 Tuller Rd Dublin OH 43017",
    "addr:housenumber":"4374",
    "addr:postcode":"43017",
    "addr:street":"Tuller Rd",
    "iso:country":"US",
    "sg:address":"4374 Tuller Rd",
    "sg:city":"Dublin",
    "sg:classifiers":[
        {
            "category":"Building & Trades",
            "subcategory":"Electrical",
            "type":"Services"
        }
    ],
    "sg:phone":"+1 614 766 0780",
    "sg:postcode":"43017",
    "sg:province":"OH",
    "sg:tags":[
        "electrical",
        "contractor"
    ],
    "wof:name":"National Energy MGT Svcs LLC",
    "wof:placetype":"venue"
},
  "geometry": {"coordinates":[-83.099085,40.107347],"type":"Point"}
}