{
  "type": "Feature",
  "properties": {
    "iso:country":"US",
    "sg:address":"2423 N Reynolds Rd",
    "sg:city":"Toledo",
    "sg:classifiers":[
        {
            "category":"Retail",
            "subcategory":"Animal Services",
            "type":"Services"
        }
    ],
    "sg:phone":"+1 419 578 7301",
    "sg:postcode":"43615",
    "sg:province":"OH",
    "sg:tags":[
        "pet",
        "grooming",
        "washing"
    ],
    "wof:name":"Let The Fur Fly Pet Salon",
    "wof:placetype":"venue"
},
  "geometry": {"coordinates":[-83.668031,41.667072],"type":"Point"}
}