{
  "type": "Feature",
  "properties": {
    "iso:country":"US",
    "sg:address":"2368 E State St",
    "sg:city":"Salem",
    "sg:classifiers":[
        {
            "category":"Professional",
            "subcategory":"Management & Consulting",
            "type":"Services"
        }
    ],
    "sg:phone":"+1 330 332 1020",
    "sg:postcode":"44460",
    "sg:province":"OH",
    "sg:tags":[
        "business"
    ],
    "wof:name":"Mr Zips/Top Driver",
    "wof:placetype":"venue"
},
  "geometry": {"coordinates":[-80.826407,40.901001],"type":"Point"}
}