{
  "type": "Feature",
  "properties": {
    "iso:country":"US",
    "sg:address":"6300 Biddulph Rd",
    "sg:city":"Cleveland",
    "sg:classifiers":[
        {
            "category":"Banks & Credit Unions",
            "subcategory":"Bank",
            "type":"Services"
        }
    ],
    "sg:phone":"+1 216 741 5900",
    "sg:postcode":"44144",
    "sg:province":"OH",
    "wof:name":"US Bank",
    "wof:placetype":"venue"
},
  "geometry": {"coordinates":[-81.730394,41.430419],"type":"Point"}
}