{
  "type": "Feature",
  "properties": {
    "addr:full":"205 Greenbriar Dr Aurora OH 44202",
    "addr:housenumber":"205",
    "addr:postcode":"44202",
    "addr:street":"Greenbriar Dr",
    "iso:country":"US",
    "sg:address":"205 Greenbriar Dr",
    "sg:city":"Aurora",
    "sg:classifiers":[
        {
            "category":"Organizations",
            "subcategory":"Professional Association",
            "type":"Services"
        }
    ],
    "sg:phone":"+1 330 995 3250",
    "sg:postcode":"44202",
    "sg:province":"OH",
    "wof:name":"Four Season Comm Assoc",
    "wof:placetype":"venue"
},
  "geometry": {"coordinates":[-81.353426,41.296508],"type":"Point"}
}