{
  "type": "Feature",
  "properties": {
    "iso:country":"US",
    "sg:address":"1753 E Livingston Ave",
    "sg:city":"Columbus",
    "sg:classifiers":[
        {
            "category":"Real Estate",
            "subcategory":"Real Estate Agent",
            "type":"Services"
        }
    ],
    "sg:phone":"+1 614 258 9537",
    "sg:postcode":"43205",
    "sg:province":"OH",
    "wof:name":"Harris Realty Co",
    "wof:placetype":"venue"
},
  "geometry": {"coordinates":[-82.950091,39.948634],"type":"Point"}
}