{
  "type": "Feature",
  "properties": {
    "iso:country":"US",
    "sg:address":"17547 State Rte 45",
    "sg:city":"Wellsville",
    "sg:classifiers":[
        {
            "category":"Professional",
            "type":"Services"
        }
    ],
    "sg:phone":"+1 330 532 4299",
    "sg:postcode":"43968",
    "sg:province":"OH",
    "wof:name":"Landmark Structures",
    "wof:placetype":"venue"
},
  "geometry": {"coordinates":[-80.675149,40.646472],"type":"Point"}
}