{
  "type": "Feature",
  "properties": {
    "iso:country":"US",
    "sg:address":"36 W Sugartree St",
    "sg:city":"Wilmington",
    "sg:classifiers":[
        {
            "category":"Bars & Pubs",
            "type":"Food & Drink"
        }
    ],
    "sg:phone":"+1 937 383 2494",
    "sg:postcode":"45177",
    "sg:province":"OH",
    "sg:tags":[
        "drinking"
    ],
    "wof:name":"Wagon Wheel Cafe",
    "wof:placetype":"venue"
},
  "geometry": {"coordinates":[-83.830028,39.44419],"type":"Point"}
}