{
  "type": "Feature",
  "properties": {
    "addr:full": "1000 Miamisburg Centerville Rd Washington Twp OH 45459",
    "addr:housenumber": "1000",
    "addr:postcode": "45459",
    "addr:street": "Miamisburg Centerville Rd",
    "iso:country": "US",
    "sg:address": "1000 Miamisburg Centerville Rd",
    "sg:city": "Washington Twp",
    "sg:classifiers": [
      {
        "category": "Food \u0026 Beverages",
        "subcategory": "Liquor \u0026 Beverages",
        "type": "Retail Goods"
      }
    ],
    "sg:phone": "+1 937 439 5250",
    "sg:postcode": "45459",
    "sg:province": "OH",
    "sg:tags": [
      "beer",
      "ale"
    ],
    "wof:name": "Caesar's Drive Thru",
    "wof:placetype": "venue"
  },
  "geometry": {"coordinates":[-84.192982,39.62936],"type":"Point"}
}
