{
  "type": "Feature",
  "properties": {
    "addr:full":"5109 Warrensville Center Rd Cleveland OH 44137",
    "addr:housenumber":"5109",
    "addr:postcode":"44137",
    "addr:street":"Warrensville Center Rd",
    "iso:country":"US",
    "sg:address":"5109 Warrensville Center Rd",
    "sg:city":"Cleveland",
    "sg:classifiers":[
        {
            "category":"Personal",
            "subcategory":"Beauty Salon",
            "type":"Services"
        }
    ],
    "sg:phone":"+1 216 587 2626",
    "sg:postcode":"44137",
    "sg:province":"OH",
    "wof:name":"Ro Mae Total Beauty Salon",
    "wof:placetype":"venue"
},
  "geometry": {"coordinates":[-81.537284,41.421324],"type":"Point"}
}