{
  "type": "Feature",
  "properties": {
    "addr:full":"235 Lincoln Way W Massillon OH 44647",
    "addr:housenumber":"235",
    "addr:postcode":"44647",
    "addr:street":"Lincoln Way W",
    "iso:country":"US",
    "sg:address":"235 Lincoln Way W",
    "sg:city":"Massillon",
    "sg:classifiers":[
        {
            "category":"Restaurant",
            "type":"Food & Drink"
        }
    ],
    "sg:phone":"+1 330 837 2999",
    "sg:postcode":"44647",
    "sg:province":"OH",
    "sg:website":"www.buffalowildwings.com",
    "wof:name":"Buffalo Wild Wings Grill & Bar",
    "wof:placetype":"venue"
},
  "geometry": {"coordinates":[-81.526781,40.795427],"type":"Point"}
}