{
  "type": "Feature",
  "properties": {
    "iso:country":"US",
    "sg:address":"4395 Rex Lake Dr",
    "sg:city":"Akron",
    "sg:classifiers":[
        {
            "category":"Organizations",
            "subcategory":"Community Association",
            "type":"Services"
        }
    ],
    "sg:phone":"+1 330 644 9711",
    "sg:postcode":"44319",
    "sg:province":"OH",
    "sg:tags":[
        "fraternal"
    ],
    "wof:name":"Masonic Temples Portage Lakes",
    "wof:placetype":"venue"
},
  "geometry": {"coordinates":[-81.550443,40.978206],"type":"Point"}
}