{
  "type": "Feature",
  "properties": {
    "iso:country":"US",
    "sg:address":"13708 Lorain Ave",
    "sg:city":"Cleveland",
    "sg:classifiers":[
        {
            "category":"Retail",
            "subcategory":"Auto Rental",
            "type":"Services"
        }
    ],
    "sg:phone":"+1 216 252 9999",
    "sg:postcode":"44111",
    "sg:province":"OH",
    "sg:tags":[
        "renting",
        "automobile"
    ],
    "wof:name":"Rent A Ctr",
    "wof:placetype":"venue"
},
  "geometry": {"coordinates":[-81.790256,41.45511],"type":"Point"}
}