{
  "type": "Feature",
  "properties": {
    "addr:full":"46 Erie St N Massillon OH 44646",
    "addr:housenumber":"46",
    "addr:postcode":"44646",
    "addr:street":"Erie St N",
    "iso:country":"US",
    "sg:address":"46 Erie St N",
    "sg:city":"Massillon",
    "sg:classifiers":[
        {
            "category":"Banks & Credit Unions",
            "subcategory":"Bank",
            "type":"Services"
        }
    ],
    "sg:phone":"+1 330 830 3270",
    "sg:postcode":"44646",
    "sg:province":"OH",
    "sg:tags":[
        "correspondent",
        "mortgage",
        "loan",
        "banker",
        "real estate"
    ],
    "wof:name":"Castle Mortgage Corporation",
    "wof:placetype":"venue"
},
  "geometry": {"coordinates":[-81.52340700000001,40.79691],"type":"Point"}
}