{
  "type": "Feature",
  "properties": {
    "addr:full": "533 W Main St Conneaut OH 44030",
    "addr:housenumber": "533",
    "addr:postcode": "44030",
    "addr:street": "W Main St",
    "iso:country": "US",
    "sg:address": "533 W Main St",
    "sg:city": "Conneaut",
    "sg:classifiers": [
      {
        "category": "Professional",
        "type": "Services"
      }
    ],
    "sg:phone": "+1 440 599 2340",
    "sg:postcode": "44030",
    "sg:province": "OH",
    "sg:tags": [
      "establishment"
    ],
    "wof:name": "AFLAC-Jeanna Burr",
    "wof:placetype": "venue"
  },
  "geometry": {"coordinates":[-80.615974,41.926984],"type":"Point"}
}
