{
  "type": "Feature",
  "properties": {
    "addr:full":"1084 S Opfer-Lentz Rd Elmore OH 43416",
    "addr:housenumber":"1084",
    "addr:postcode":"43416",
    "addr:street":"S Opfer-Lentz Rd",
    "iso:country":"US",
    "sg:address":"1084 S Opfer-Lentz Rd",
    "sg:city":"Elmore",
    "sg:phone":"+1 419 862 2519",
    "sg:postcode":"43416",
    "sg:province":"OH",
    "sg:tags":[
        "farm",
        "crop",
        "general"
    ],
    "wof:name":"Rothert Farm Inc",
    "wof:placetype":"venue"
},
  "geometry": {"coordinates":[-83.31961699999999,41.500192],"type":"Point"}
}