{
  "type": "Feature",
  "properties": {
    "addr:full":"2601 W Market St Warren OH 44485",
    "addr:housenumber":"2601",
    "addr:postcode":"44485",
    "addr:street":"W Market St",
    "iso:country":"US",
    "sg:address":"2601 W Market St",
    "sg:city":"Warren",
    "sg:classifiers":[
        {
            "category":"Personal",
            "subcategory":"Beauty Salon",
            "type":"Services"
        }
    ],
    "sg:phone":"+1 330 898 2244",
    "sg:postcode":"44485",
    "sg:province":"OH",
    "wof:name":"Unity Hair Care",
    "wof:placetype":"venue"
},
  "geometry": {"coordinates":[-80.855143,41.237074],"type":"Point"}
}