{
  "type": "Feature",
  "properties": {
    "addr:full": "6077 Lane Rd Centerburg OH 43011",
    "addr:housenumber": "6077",
    "addr:postcode": "43011",
    "addr:street": "Lane Rd",
    "iso:country": "US",
    "sg:address": "6077 Lane Rd",
    "sg:city": "Centerburg",
    "sg:classifiers": [
      {
        "category": "Retail",
        "subcategory": "Repair Shop",
        "type": "Services"
      }
    ],
    "sg:phone": "+1 614 882 7971",
    "sg:postcode": "43011",
    "sg:province": "OH",
    "sg:tags": [
      "appliance"
    ],
    "wof:name": "Westerville Refrigeration",
    "wof:placetype": "venue"
  },
  "geometry": {"coordinates":[-82.773728,40.289502],"type":"Point"}
}
