{
  "type": "Feature",
  "properties": {
    "addr:full": "2340 Shepler Church Ave SW Canton OH 44706",
    "addr:housenumber": "2340",
    "addr:postcode": "44706",
    "addr:street": "Shepler Church Ave Sw",
    "iso:country": "US",
    "sg:address": "2340 Shepler Church Ave SW",
    "sg:city": "Canton",
    "sg:classifiers": [
      {
        "category": "Building \u0026 Trades",
        "subcategory": "Construction",
        "type": "Services"
      }
    ],
    "sg:phone": "+1 330 453 2566",
    "sg:postcode": "44706",
    "sg:province": "OH",
    "sg:tags": [
      "remodeling",
      "retail",
      "contractor",
      "commercial",
      "general"
    ],
    "sg:website": "www.eckinger.com",
    "wof:name": "Eckinger Construction Co",
    "wof:placetype": "venue"
  },
  "geometry": {"coordinates":[-81.400675,40.767713],"type":"Point"}
}
