{
  "type": "Feature",
  "properties": {
    "iso:country":"US",
    "sg:address":"1369 Millville Ave",
    "sg:city":"Hamilton",
    "sg:classifiers":[
        {
            "category":"Organizations",
            "subcategory":"Religious Organization",
            "type":"Services"
        }
    ],
    "sg:phone":"+1 513 863 6900",
    "sg:postcode":"45013",
    "sg:province":"IN",
    "sg:tags":[
        "church"
    ],
    "wof:name":"Millville Avenue Church Of God",
    "wof:placetype":"venue"
},
  "geometry": {"coordinates":[-84.605316,39.406093],"type":"Point"}
}