{
  "type": "Feature",
  "properties": {
    "iso:country":"US",
    "sg:address":"5286 State Rte 5",
    "sg:city":"Cortland",
    "sg:classifiers":[
        {
            "category":"Home & Garden",
            "subcategory":"Garden Supply",
            "type":"Retail Goods"
        }
    ],
    "sg:phone":"+1 330 637 6840",
    "sg:postcode":"44410",
    "sg:province":"OH",
    "sg:tags":[
        "landscaping",
        "equipment"
    ],
    "wof:name":"Buckeye Bulk Inc",
    "wof:placetype":"venue"
},
  "geometry": {"coordinates":[-80.70742199999999,41.357867],"type":"Point"}
}