{
  "type": "Feature",
  "properties": {
    "addr:full": "5286 State Rte 5 Cortland OH 44410",
    "addr:housenumber": "5286",
    "addr:postcode": "44410",
    "addr:street": "State Rte 5",
    "iso:country": "US",
    "sg:address": "5286 State Rte 5",
    "sg:city": "Cortland",
    "sg:classifiers": [
      {
        "category": "Home \u0026 Garden",
        "subcategory": "Garden Supply",
        "type": "Retail Goods"
      }
    ],
    "sg:phone": "+1 330 637 6840",
    "sg:postcode": "44410",
    "sg:province": "OH",
    "sg:tags": [
      "landscaping",
      "equipment"
    ],
    "wof:name": "Buckeye Bulk Inc",
    "wof:placetype": "venue"
  },
  "geometry": {"coordinates":[-80.707422,41.357867],"type":"Point"}
}
