{
  "type": "Feature",
  "properties": {
    "addr:full":"10 Lincoln Ter Pomeroy OH 45769",
    "addr:housenumber":"10",
    "addr:postcode":"45769",
    "addr:street":"Lincoln Ter",
    "iso:country":"US",
    "sg:address":"10 Lincoln Ter",
    "sg:city":"Pomeroy",
    "sg:classifiers":[
        {
            "category":"Restaurant",
            "type":"Food & Drink"
        }
    ],
    "sg:phone":"+1 740 992 1044",
    "sg:postcode":"45769",
    "sg:province":"OH",
    "sg:tags":[
        "eating"
    ],
    "wof:name":"Dairy Valley",
    "wof:placetype":"venue"
},
  "geometry": {"coordinates":[-82.036799,39.026821],"type":"Point"}
}