{
  "type": "Feature",
  "properties": {
    "iso:country":"US",
    "sg:address":"39458 Bradbury Rd",
    "sg:city":"Middleport",
    "sg:classifiers":[
        {
            "category":"Building & Trades",
            "subcategory":"Plumbing",
            "type":"Services"
        }
    ],
    "sg:phone":"+1 740 992 6252",
    "sg:postcode":"45760",
    "sg:province":"OH",
    "sg:tags":[
        "heating",
        "contractor"
    ],
    "wof:name":"Heatingchuck's Heating Cooling",
    "wof:placetype":"venue"
},
  "geometry": {"coordinates":[-82.064342,39.01015],"type":"Point"}
}