{
  "type": "Feature",
  "properties": {
    "addr:full": "7356 Misty Woods Ct Morrow OH 45152",
    "addr:housenumber": "7356",
    "addr:postcode": "45152",
    "addr:street": "Misty Woods Ct",
    "iso:country": "US",
    "sg:address": "7356 Misty Woods Ct",
    "sg:city": "Morrow",
    "sg:classifiers": [
      {
        "category": "Building \u0026 Trades",
        "subcategory": "Construction",
        "type": "Services"
      }
    ],
    "sg:phone": "+1 513 899 3984",
    "sg:postcode": "45152",
    "sg:province": "OH",
    "sg:tags": [
      "specializing",
      "family",
      "general",
      "new",
      "home",
      "contractor"
    ],
    "wof:name": "Boggs Quality Construction",
    "wof:placetype": "venue"
  },
  "geometry": {"coordinates":[-84.12883,39.320874],"type":"Point"}
}
