{
  "type": "Feature",
  "properties": {
    "iso:country":"US",
    "sg:address":"4137 Boardman Canfield Rd",
    "sg:city":"Canfield",
    "sg:classifiers":[
        {
            "category":"Banks & Credit Unions",
            "subcategory":"Investment Brokerage",
            "type":"Services"
        }
    ],
    "sg:phone":"+1 330 702 7300",
    "sg:postcode":"44406",
    "sg:province":"OH",
    "sg:tags":[
        "consultant",
        "planning",
        "financial"
    ],
    "wof:name":"Merrill Lynch Pierce Fenner",
    "wof:placetype":"venue"
},
  "geometry": {"coordinates":[-80.72925600000001,41.024739],"type":"Point"}
}