{
  "type": "Feature",
  "properties": {
    "addr:full": "3818 Columbus-Lancaster Rd NW Carroll OH 43112",
    "addr:housenumber": "3818",
    "addr:postcode": "43112",
    "addr:street": "Columbus-Lancaster Rd Nw",
    "iso:country": "US",
    "sg:address": "3818 Columbus-Lancaster Rd NW",
    "sg:city": "Carroll",
    "sg:classifiers": [
      {
        "category": "Home \u0026 Garden",
        "subcategory": "Building Materials",
        "type": "Retail Goods"
      }
    ],
    "sg:phone": "+1 740 756 7225",
    "sg:postcode": "43112",
    "sg:province": "OH",
    "sg:tags": [
      "wallpaper"
    ],
    "wof:name": "Wallpaper Outlet",
    "wof:placetype": "venue"
  },
  "geometry": {"coordinates":[-82.673476,39.764004],"type":"Point"}
}
