{
  "type": "Feature",
  "properties": {
    "addr:full": "318 Louisiana Ave Perrysburg OH 43551",
    "addr:housenumber": "318",
    "addr:postcode": "43551",
    "addr:street": "Louisiana Ave",
    "iso:country": "US",
    "sg:address": "318 Louisiana Ave",
    "sg:city": "Perrysburg",
    "sg:classifiers": [
      {
        "category": "Professional",
        "subcategory": "Management \u0026 Consulting",
        "type": "Services"
      }
    ],
    "sg:phone": "+1 419 874 4946",
    "sg:postcode": "43551",
    "sg:province": "OH",
    "wof:name": "James Raymond \u0026 Associates",
    "wof:placetype": "venue"
  },
  "geometry": {"coordinates":[-83.627967,41.557212],"type":"Point"}
}
