{
  "type": "Feature",
  "properties": {
    "iso:country":"US",
    "sg:address":"318 Louisiana Ave",
    "sg:city":"Perrysburg",
    "sg:classifiers":[
        {
            "category":"Professional",
            "subcategory":"Management & Consulting",
            "type":"Services"
        }
    ],
    "sg:phone":"+1 419 874 4946",
    "sg:postcode":"43551",
    "sg:province":"OH",
    "wof:name":"James Raymond & Associates",
    "wof:placetype":"venue"
},
  "geometry": {"coordinates":[-83.627967,41.557212],"type":"Point"}
}