{
  "type": "Feature",
  "properties": {
    "iso:country":"US",
    "sg:address":"4753 Cornell Rd",
    "sg:city":"Cincinnati",
    "sg:classifiers":[
        {
            "category":"Insurance",
            "subcategory":"Insurance Agent",
            "type":"Services"
        }
    ],
    "sg:phone":"+1 513 530 5775",
    "sg:postcode":"45241",
    "sg:province":"OH",
    "wof:name":"Bill Neal",
    "wof:placetype":"venue"
},
  "geometry": {"coordinates":[-84.378118,39.270508],"type":"Point"}
}