{
  "type": "Feature",
  "properties": {
    "addr:full": "4753 Cornell Rd Cincinnati OH 45241",
    "addr:housenumber": "4753",
    "addr:postcode": "45241",
    "addr:street": "Cornell Rd",
    "iso:country": "US",
    "sg:address": "4753 Cornell Rd",
    "sg:city": "Cincinnati",
    "sg:classifiers": [
      {
        "category": "Insurance",
        "subcategory": "Insurance Agent",
        "type": "Services"
      }
    ],
    "sg:phone": "+1 513 530 5775",
    "sg:postcode": "45241",
    "sg:province": "OH",
    "wof:name": "Bill Neal",
    "wof:placetype": "venue"
  },
  "geometry": {"coordinates":[-84.378118,39.270508],"type":"Point"}
}
