{
  "type": "Feature",
  "properties": {
    "addr:full":"2400 Elida Rd Lima OH 45805",
    "addr:postcode":"2400;45805",
    "addr:street":"Elida Rd",
    "iso:country":"US",
    "sg:address":"2400 Elida Rd",
    "sg:city":"Lima",
    "sg:classifiers":[
        {
            "category":"Shopping",
            "type":"Retail Goods"
        }
    ],
    "sg:phone":"+1 419 331 2889",
    "sg:postcode":"45805",
    "sg:province":"OH",
    "sg:tags":[
        "wedding",
        "supply"
    ],
    "wof:name":"American Commodore Tuxedo",
    "wof:placetype":"venue"
},
  "geometry": {"coordinates":[-84.148983,40.762762],"type":"Point"}
}