{
  "type": "Feature",
  "properties": {
    "addr:full": "415 S Vandemark Rd Sidney OH 45365",
    "addr:housenumber": "415",
    "addr:postcode": "45365",
    "addr:street": "S Vandemark Rd",
    "iso:country": "US",
    "sg:address": "415 S Vandemark Rd",
    "sg:city": "Sidney",
    "sg:classifiers": [
      {
        "category": "Government",
        "subcategory": "Office",
        "type": "Public Place"
      }
    ],
    "sg:phone": "+1 937 498 8117",
    "sg:postcode": "45365",
    "sg:province": "OH",
    "sg:tags": [
      "village"
    ],
    "wof:name": "Streets Department",
    "wof:placetype": "venue"
  },
  "geometry": {"coordinates":[-84.188,40.28201],"type":"Point"}
}
