{
  "type": "Feature",
  "properties": {
    "iso:country":"US",
    "sg:address":"111 E 6th St",
    "sg:city":"Marysville",
    "sg:classifiers":[
        {
            "category":"Real Estate",
            "subcategory":"Real Estate Services",
            "type":"Services"
        }
    ],
    "sg:phone":"+1 937 644 3172",
    "sg:postcode":"43040",
    "sg:province":"OH",
    "sg:tags":[
        "abstract",
        "title"
    ],
    "wof:name":"ACS Lionheart Title",
    "wof:placetype":"venue"
},
  "geometry": {"coordinates":[-83.36695400000001,40.235237],"type":"Point"}
}