{
  "type": "Feature",
  "properties": {
    "addr:full": "354 Hearne Ave Cincinnati OH 45229",
    "addr:housenumber": "354",
    "addr:postcode": "45229",
    "addr:street": "Hearne Ave",
    "iso:country": "US",
    "sg:address": "354 Hearne Ave",
    "sg:city": "Cincinnati",
    "sg:classifiers": [
      {
        "category": "Manufacturing",
        "subcategory": "Printing",
        "type": "Manufacturing \u0026 Wholesale Goods"
      }
    ],
    "sg:phone": "+1 513 961 3331",
    "sg:postcode": "45229",
    "sg:province": "OH",
    "sg:tags": [
      "dealers-wholesale",
      "news",
      "newspaper",
      "magazine",
      "publishing"
    ],
    "wof:name": "N J E M A Magazine",
    "wof:placetype": "venue"
  },
  "geometry": {"coordinates":[-84.501432,39.142942],"type":"Point"}
}
