{
  "type": "Feature",
  "properties": {
    "addr:full":"53055 High Ridge Rd Bridgeport OH 43912",
    "addr:housenumber":"53055",
    "addr:postcode":"43912",
    "addr:street":"High Ridge Rd",
    "iso:country":"US",
    "sg:address":"53055 High Ridge Rd",
    "sg:city":"Bridgeport",
    "sg:classifiers":[
        {
            "category":"Utilities",
            "subcategory":"Telephone",
            "type":"Services"
        }
    ],
    "sg:phone":"+1 740 695 6148",
    "sg:postcode":"43912",
    "sg:province":"OH",
    "sg:tags":[
        "communications"
    ],
    "wof:name":"Ohio Bell Telephone Basem",
    "wof:placetype":"venue"
},
  "geometry": {"coordinates":[-80.83093599999999,40.063353],"type":"Point"}
}