{
  "type": "Feature",
  "properties": {
    "addr:full":"393 E Town St Columbus OH 43215",
    "addr:housenumber":"393",
    "addr:postcode":"43215",
    "addr:street":"E Town St",
    "iso:country":"US",
    "sg:address":"393 E Town St",
    "sg:city":"Columbus",
    "sg:classifiers":[
        {
            "category":"Manufacturing",
            "subcategory":"Tools & Machinery",
            "type":"Manufacturing & Wholesale Goods"
        }
    ],
    "sg:phone":"+1 614 221 8410",
    "sg:postcode":"43215",
    "sg:province":"OH",
    "sg:tags":[
        "surgical",
        "mfg"
    ],
    "wof:name":"Alum Creek Wheelchair Company",
    "wof:placetype":"venue"
},
  "geometry": {"coordinates":[-82.98920200000001,39.959971],"type":"Point"}
}