{
  "type": "Feature",
  "properties": {
    "addr:full": "192 Ponderosa Dr Oregon OH 43616",
    "addr:housenumber": "192",
    "addr:postcode": "43616",
    "addr:street": "Ponderosa Dr",
    "iso:country": "US",
    "sg:address": "192 Ponderosa Dr",
    "sg:city": "Oregon",
    "sg:classifiers": [
      {
        "category": "Manufacturing",
        "subcategory": "Lumber",
        "type": "Manufacturing \u0026 Wholesale Goods"
      }
    ],
    "sg:phone": "+1 419 691 2371",
    "sg:postcode": "43616",
    "sg:province": "OH",
    "sg:tags": [
      "forestry"
    ],
    "wof:name": "James Maher",
    "wof:placetype": "venue"
  },
  "geometry": {"coordinates":[-83.479931,41.649522],"type":"Point"}
}
