{
  "type": "Feature",
  "properties": {
    "iso:country":"US",
    "sg:address":"192 Ponderosa Dr",
    "sg:city":"Oregon",
    "sg:classifiers":[
        {
            "category":"Manufacturing",
            "subcategory":"Lumber",
            "type":"Manufacturing & Wholesale Goods"
        }
    ],
    "sg:phone":"+1 419 691 2371",
    "sg:postcode":"43616",
    "sg:province":"OH",
    "sg:tags":[
        "forestry"
    ],
    "wof:name":"James Maher",
    "wof:placetype":"venue"
},
  "geometry": {"coordinates":[-83.47993099999999,41.649522],"type":"Point"}
}