{
  "type": "Feature",
  "properties": {
    "addr:full": "524 N Lexington-Springmill Rd Mansfield OH 44906",
    "addr:housenumber": "524",
    "addr:postcode": "44906",
    "addr:street": "N Lexington-Springmill Rd",
    "iso:country": "US",
    "sg:address": "524 N Lexington-Springmill Rd",
    "sg:city": "Mansfield",
    "sg:classifiers": [
      {
        "category": "Shopping",
        "subcategory": "Department Store",
        "type": "Retail Goods"
      }
    ],
    "sg:phone": "+1 419 529 8877",
    "sg:postcode": "44906",
    "sg:province": "OH",
    "wof:name": "Kohl's Department Store",
    "wof:placetype": "venue"
  },
  "geometry": {"coordinates":[-82.59032,40.766846],"type":"Point"}
}
