{
  "type": "Feature",
  "properties": {
    "iso:country":"US",
    "sg:address":"713 N State St",
    "sg:city":"Girard",
    "sg:classifiers":[
        {
            "category":"Shopping",
            "subcategory":"Pharmacy",
            "type":"Retail Goods"
        }
    ],
    "sg:phone":"+1 330 545 8414",
    "sg:postcode":"44420",
    "sg:province":"OH",
    "sg:tags":[
        "aid",
        "first",
        "supply"
    ],
    "sg:website":"http://www.riteaid.com",
    "wof:name":"Rite Aid",
    "wof:placetype":"venue"
},
  "geometry": {"coordinates":[-80.703453,41.161499],"type":"Point"}
}