{
  "type": "Feature",
  "properties": {
    "addr:full": "3996 Fulton Dr NW Canton OH 44718",
    "addr:housenumber": "3996",
    "addr:postcode": "44718",
    "addr:street": "Fulton Dr Nw",
    "iso:country": "US",
    "sg:address": "3996 Fulton Dr NW",
    "sg:city": "Canton",
    "sg:classifiers": [
      {
        "category": "Insurance",
        "subcategory": "Insurance Agent",
        "type": "Services"
      }
    ],
    "sg:phone": "+1 330 966 0384",
    "sg:postcode": "44718",
    "sg:province": "OH",
    "wof:name": "Jones Insurance \u0026 Assoc",
    "wof:placetype": "venue"
  },
  "geometry": {"coordinates":[-81.42138,40.835445],"type":"Point"}
}
