{
  "type": "Feature",
  "properties": {
    "addr:full":"2148 Refugee Rd Columbus OH 43207",
    "addr:housenumber":"2148",
    "addr:postcode":"43207",
    "addr:street":"Refugee Rd",
    "iso:country":"US",
    "sg:address":"2148 Refugee Rd",
    "sg:city":"Columbus",
    "sg:classifiers":[
        {
            "category":"Retail",
            "subcategory":"Auto Repair",
            "type":"Services"
        }
    ],
    "sg:phone":"+1 614 445 6718",
    "sg:postcode":"43207",
    "sg:province":"OH",
    "sg:tags":[
        "repairing",
        "automobile"
    ],
    "wof:name":"Nu Cor Automotive",
    "wof:placetype":"venue"
},
  "geometry": {"coordinates":[-82.945932,39.919054],"type":"Point"}
}