{
  "type": "Feature",
  "properties": {
    "addr:full": "1175 Westwood Dr Van Wert OH 45891",
    "addr:housenumber": "1175",
    "addr:postcode": "45891",
    "addr:street": "Westwood Dr",
    "iso:country": "US",
    "sg:address": "1175 Westwood Dr",
    "sg:city": "Van Wert",
    "sg:classifiers": [
      {
        "category": "Health Services",
        "subcategory": "Podiatrist",
        "type": "Services"
      }
    ],
    "sg:phone": "+1 419 238 3570",
    "sg:postcode": "45891",
    "sg:province": "OH",
    "wof:name": "West Ohio Family Foot Care",
    "wof:placetype": "venue"
  },
  "geometry": {"coordinates":[-84.594832,40.853146],"type":"Point"}
}
