{
  "type": "Feature",
  "properties": {
    "iso:country":"US",
    "sg:address":"15957 E Liverpool Rd",
    "sg:city":"East Liverpool",
    "sg:classifiers":[
        {
            "category":"Restaurant",
            "type":"Food & Drink"
        }
    ],
    "sg:phone":"+1 330 385 5441",
    "sg:postcode":"43920",
    "sg:province":"OH",
    "sg:tags":[
        "eating"
    ],
    "wof:name":"Wendys",
    "wof:placetype":"venue"
},
  "geometry": {"coordinates":[-80.601795,40.670197],"type":"Point"}
}