{
  "type": "Feature",
  "properties": {
    "addr:full": "200 W Benson Ave Cincinnati OH 45215",
    "addr:housenumber": "200",
    "addr:postcode": "45215",
    "addr:street": "W Benson Ave",
    "iso:country": "US",
    "sg:address": "200 W Benson Ave",
    "sg:city": "Cincinnati",
    "sg:classifiers": [
      {
        "category": "Restaurant",
        "type": "Food \u0026 Drink"
      }
    ],
    "sg:phone": "+1 513 821 3466",
    "sg:postcode": "45215",
    "sg:province": "OH",
    "sg:tags": [
      "eating",
      "pub"
    ],
    "wof:name": "Foley's Irish Pub",
    "wof:placetype": "venue"
  },
  "geometry": {"coordinates":[-84.443817,39.223363],"type":"Point"}
}
