{
  "type": "Feature",
  "properties": {
    "addr:full":"5275 Gender Rd Canal Winchester OH 43110",
    "addr:housenumber":"5275",
    "addr:postcode":"43110",
    "addr:street":"Gender Rd",
    "iso:country":"US",
    "sg:address":"5275 Gender Rd",
    "sg:city":"Canal Winchester",
    "sg:classifiers":[
        {
            "category":"Banks & Credit Unions",
            "subcategory":"Investment Brokerage",
            "type":"Services"
        }
    ],
    "sg:phone":"+1 614 834 5555",
    "sg:postcode":"43110",
    "sg:province":"OH",
    "wof:name":"Johnson Investment",
    "wof:placetype":"venue"
},
  "geometry": {"coordinates":[-82.826508,39.874254],"type":"Point"}
}