{
  "type": "Feature",
  "properties": {
    "iso:country":"US",
    "sg:address":"8 Oakfield Dr",
    "sg:city":"Milan",
    "sg:classifiers":[
        {
            "category":"Professional",
            "subcategory":"Business Services",
            "type":"Services"
        }
    ],
    "sg:phone":"+1 419 499 1600",
    "sg:postcode":"44846",
    "sg:province":"OH",
    "sg:tags":[
        "arbitration"
    ],
    "wof:name":"John Py",
    "wof:placetype":"venue"
},
  "geometry": {"coordinates":[-82.58134,41.295413],"type":"Point"}
}