{
  "type": "Feature",
  "properties": {
    "addr:full":"7471 State Rte 97 Mansfield OH 44903",
    "addr:housenumber":"7471",
    "addr:postcode":"44903",
    "addr:street":"State Rte 97",
    "iso:country":"US",
    "sg:address":"7471 State Rte 97",
    "sg:city":"Mansfield",
    "sg:classifiers":[
        {
            "category":"Recreation",
            "subcategory":"Marina",
            "type":"Entertainment"
        }
    ],
    "sg:phone":"+1 419 884 6277",
    "sg:postcode":"44903",
    "sg:province":"OH",
    "wof:name":"Dan's Marine",
    "wof:placetype":"venue"
},
  "geometry": {"coordinates":[-82.645931,40.707085],"type":"Point"}
}