{
  "type": "Feature",
  "properties": {
    "iso:country":"US",
    "sg:address":"104 E Washington St",
    "sg:city":"Napoleon",
    "sg:classifiers":[
        {
            "category":"Government",
            "subcategory":"Office",
            "type":"Public Place"
        }
    ],
    "sg:phone":"+1 419 599 7370",
    "sg:postcode":"43545",
    "sg:province":"OH",
    "wof:name":"Henry County Planning Comm",
    "wof:placetype":"venue"
},
  "geometry": {"coordinates":[-84.124306,41.391337],"type":"Point"}
}