{
  "type": "Feature",
  "properties": {
    "addr:full": "4427 Talmadge Rd Toledo OH 43623",
    "addr:housenumber": "4427",
    "addr:postcode": "43623",
    "addr:street": "Talmadge Rd",
    "iso:country": "US",
    "sg:address": "4427 Talmadge Rd",
    "sg:city": "Toledo",
    "sg:classifiers": [
      {
        "category": "Professional",
        "type": "Services"
      }
    ],
    "sg:phone": "+1 419 475 2885",
    "sg:postcode": "43623",
    "sg:province": "OH",
    "wof:name": "Uritox LLC",
    "wof:placetype": "venue"
  },
  "geometry": {"coordinates":[-83.644874,41.695377],"type":"Point"}
}
