{
  "type": "Feature",
  "properties": {
    "iso:country":"US",
    "sg:address":"5475 Avion Park Dr",
    "sg:city":"Cleveland",
    "sg:classifiers":[
        {
            "category":"Manufacturing",
            "subcategory":"Metals",
            "type":"Manufacturing & Wholesale Goods"
        }
    ],
    "sg:phone":"+1 440 473 2020",
    "sg:postcode":"44143",
    "sg:province":"OH",
    "sg:tags":[
        "treating",
        "heat"
    ],
    "sg:website":"www.bodycote.com",
    "wof:name":"Bodycote Shore Inc",
    "wof:placetype":"venue"
},
  "geometry": {"coordinates":[-81.47839999999999,41.559413],"type":"Point"}
}