{
  "type": "Feature",
  "properties": {
    "addr:full":"1753 E 26th Ave Columbus OH 43219",
    "addr:housenumber":"1753",
    "addr:postcode":"43219",
    "addr:street":"E 26Th Ave",
    "iso:country":"US",
    "sg:address":"1753 E 26th Ave",
    "sg:city":"Columbus",
    "sg:classifiers":[
        {
            "category":"Professional",
            "type":"Services"
        }
    ],
    "sg:phone":"+1 614 261 3639",
    "sg:postcode":"43219",
    "sg:province":"OH",
    "wof:name":"Carl N Lee",
    "wof:placetype":"venue"
},
  "geometry": {"coordinates":[-82.960616,40.007586],"type":"Point"}
}