{
  "type": "Feature",
  "properties": {
    "addr:full":"3026 Georgetown Rd NE Canton OH 44704",
    "addr:housenumber":"3026",
    "addr:postcode":"44704",
    "addr:street":"Georgetown Rd Ne",
    "iso:country":"US",
    "sg:address":"3026 Georgetown Rd NE",
    "sg:city":"Canton",
    "sg:classifiers":[
        {
            "category":"Retail",
            "subcategory":"Auto Repair",
            "type":"Services"
        }
    ],
    "sg:phone":"+1 330 452 4809",
    "sg:postcode":"44704",
    "sg:province":"OH",
    "sg:tags":[
        "repairing",
        "automobile"
    ],
    "wof:name":"Ohio Body Shop",
    "wof:placetype":"venue"
},
  "geometry": {"coordinates":[-81.34282399999999,40.797838],"type":"Point"}
}