{
  "type": "Feature",
  "properties": {
    "iso:country":"US",
    "sg:address":"3934 W Oak Harbor Southeast Rd",
    "sg:city":"Port Clinton",
    "sg:classifiers":[
        {
            "category":"Wholesale",
            "subcategory":"Vending Machines",
            "type":"Manufacturing & Wholesale Goods"
        }
    ],
    "sg:phone":"+1 419 732 8369",
    "sg:postcode":"43452",
    "sg:province":"OH",
    "sg:tags":[
        "operator"
    ],
    "wof:name":"Hoffman Vending",
    "wof:placetype":"venue"
},
  "geometry": {"coordinates":[-83.008769,41.486523],"type":"Point"}
}