{
  "type": "Feature",
  "properties": {
    "addr:full": "3934 W Oak Harbor Southeast Rd Port Clinton OH 43452",
    "addr:housenumber": "3934",
    "addr:postcode": "43452",
    "addr:street": "W Oak;Southeast Rd",
    "iso:country": "US",
    "sg:address": "3934 W Oak Harbor Southeast Rd",
    "sg:city": "Port Clinton",
    "sg:classifiers": [
      {
        "category": "Wholesale",
        "subcategory": "Vending Machines",
        "type": "Manufacturing \u0026 Wholesale Goods"
      }
    ],
    "sg:phone": "+1 419 732 8369",
    "sg:postcode": "43452",
    "sg:province": "OH",
    "sg:tags": [
      "operator"
    ],
    "wof:name": "Hoffman Vending",
    "wof:placetype": "venue"
  },
  "geometry": {"coordinates":[-83.008769,41.486523],"type":"Point"}
}
