{
  "type": "Feature",
  "properties": {
    "addr:full": "45 N Central Ave Columbus OH 43222",
    "addr:housenumber": "45",
    "addr:postcode": "43222",
    "addr:street": "N Central Ave",
    "iso:country": "US",
    "sg:address": "45 N Central Ave",
    "sg:city": "Columbus",
    "sg:classifiers": [
      {
        "category": "Building \u0026 Trades",
        "subcategory": "Construction",
        "type": "Services"
      }
    ],
    "sg:phone": "+1 614 279 9085",
    "sg:postcode": "43222",
    "sg:province": "OH",
    "sg:tags": [
      "downspouts",
      "gutter"
    ],
    "wof:name": "A Complete Gutter Svc",
    "wof:placetype": "venue"
  },
  "geometry": {"coordinates":[-83.0385,39.958908],"type":"Point"}
}
