{
  "type": "Feature",
  "properties": {
    "iso:country":"US",
    "sg:address":"1813 E Perkins Ave",
    "sg:city":"Sandusky",
    "sg:classifiers":[
        {
            "category":"Autos & Motor Vehicles",
            "subcategory":"Auto Supplies",
            "type":"Retail Goods"
        }
    ],
    "sg:phone":"+1 419 626 9901",
    "sg:postcode":"44870",
    "sg:province":"OH",
    "sg:tags":[
        "tire"
    ],
    "wof:name":"Tire Team",
    "wof:placetype":"venue"
},
  "geometry": {"coordinates":[-82.66868599999999,41.42897],"type":"Point"}
}