{
  "type": "Feature",
  "properties": {
    "addr:full": "2735 Bull Creek Rd Laurelville OH 43135",
    "addr:housenumber": "2735",
    "addr:postcode": "43135",
    "addr:street": "Bull Creek Rd",
    "iso:country": "US",
    "sg:address": "2735 Bull Creek Rd",
    "sg:city": "Laurelville",
    "sg:classifiers": [
      {
        "category": "Building \u0026 Trades",
        "subcategory": "Construction",
        "type": "Services"
      }
    ],
    "sg:phone": "+1 740 655 2370",
    "sg:postcode": "43135",
    "sg:province": "OH",
    "sg:tags": [
      "carpentry",
      "contractor"
    ],
    "wof:name": "Roger M Francis",
    "wof:placetype": "venue"
  },
  "geometry": {"coordinates":[-82.771453,39.436757],"type":"Point"}
}
