{
  "type": "Feature",
  "properties": {
    "addr:full": "103 Western Ave Akron OH 44313",
    "addr:housenumber": "103",
    "addr:postcode": "44313",
    "addr:street": "Western Ave",
    "iso:country": "US",
    "sg:address": "103 Western Ave",
    "sg:city": "Akron",
    "sg:classifiers": [
      {
        "category": "Manufacturing",
        "subcategory": "Tools \u0026 Machinery",
        "type": "Manufacturing \u0026 Wholesale Goods"
      }
    ],
    "sg:phone": "+1 330 864 0800",
    "sg:postcode": "44313",
    "sg:province": "OH",
    "sg:tags": [
      "industry",
      "special"
    ],
    "wof:name": "Hf Rubber Machinery",
    "wof:placetype": "venue"
  },
  "geometry": {"coordinates":[-81.576375,41.116473],"type":"Point"}
}
