{
  "type": "Feature",
  "properties": {
    "addr:full": "504 W Jefferson St Sandusky OH 44870",
    "addr:housenumber": "504",
    "addr:postcode": "44870",
    "addr:street": "W Jefferson St",
    "iso:country": "US",
    "sg:address": "504 W Jefferson St",
    "sg:city": "Sandusky",
    "sg:classifiers": [
      {
        "category": "Retail",
        "subcategory": "Veterinary Services",
        "type": "Services"
      }
    ],
    "sg:phone": "+1 419 621 9080",
    "sg:postcode": "44870",
    "sg:province": "OH",
    "sg:tags": [
      "veterinarian"
    ],
    "wof:name": "Brent Gary S DVM",
    "wof:placetype": "venue"
  },
  "geometry": {"coordinates":[-82.712898,41.4515],"type":"Point"}
}
