{
  "type": "Feature",
  "properties": {
    "addr:full":"935 W State St Alliance OH 44601",
    "addr:housenumber":"935",
    "addr:postcode":"44601",
    "addr:street":"W State St",
    "iso:country":"US",
    "sg:address":"935 W State St",
    "sg:city":"Alliance",
    "sg:classifiers":[
        {
            "category":"Restaurant",
            "type":"Food & Drink"
        }
    ],
    "sg:phone":"+1 330 823 5111",
    "sg:postcode":"44601",
    "sg:province":"OH",
    "wof:name":"Domino's Pizza",
    "wof:placetype":"venue"
},
  "geometry": {"coordinates":[-81.11911600000001,40.90187],"type":"Point"}
}