{
  "type": "Feature",
  "properties": {
    "addr:full": "108 Palmetto Pl S Byesville OH 43723",
    "addr:housenumber": "108",
    "addr:postcode": "43723",
    "addr:street": "Palmetto Pl S",
    "iso:country": "US",
    "sg:address": "108 Palmetto Pl S",
    "sg:city": "Byesville",
    "sg:classifiers": [
      {
        "category": "Health Services",
        "subcategory": "Clinic",
        "type": "Services"
      }
    ],
    "sg:phone": "+1 740 685 1610",
    "sg:postcode": "43723",
    "sg:province": "OH",
    "sg:tags": [
      "home"
    ],
    "wof:name": "Community Home Healthcare",
    "wof:placetype": "venue"
  },
  "geometry": {"coordinates":[-81.545975,39.96458],"type":"Point"}
}
