{
  "type": "Feature",
  "properties": {
    "iso:country":"US",
    "sg:address":"12678 State Rte 73",
    "sg:city":"New Vienna",
    "sg:classifiers":[
        {
            "category":"Building & Trades",
            "subcategory":"Construction",
            "type":"Services"
        }
    ],
    "sg:phone":"+1 937 987 9760",
    "sg:postcode":"45159",
    "sg:province":"OH",
    "sg:tags":[
        "concrete",
        "contractor"
    ],
    "wof:name":"Conley Bros Concrete",
    "wof:placetype":"venue"
},
  "geometry": {"coordinates":[-83.702584,39.334093],"type":"Point"}
}