{
  "type": "Feature",
  "properties": {
    "addr:full":"3288 Cherryview Ct North Bend OH 45052",
    "addr:housenumber":"3288",
    "addr:postcode":"45052",
    "addr:street":"Cherryview Ct",
    "iso:country":"US",
    "sg:address":"3288 Cherryview Ct",
    "sg:city":"North Bend",
    "sg:classifiers":[
        {
            "category":"Education",
            "subcategory":"Special Training",
            "type":"Public Place"
        }
    ],
    "sg:phone":"+1 513 941 8802",
    "sg:postcode":"45052",
    "sg:province":"OH",
    "sg:tags":[
        "self",
        "motivational",
        "improvement"
    ],
    "wof:name":"Attitudes For Success",
    "wof:placetype":"venue"
},
  "geometry": {"coordinates":[-84.70031,39.149598],"type":"Point"}
}