{
  "type": "Feature",
  "properties": {
    "iso:country":"US",
    "sg:address":"27300 Euclid Ave",
    "sg:city":"Cleveland",
    "sg:classifiers":[
        {
            "category":"Building & Trades",
            "subcategory":"Construction",
            "type":"Services"
        }
    ],
    "sg:phone":"+1 216 472 0800",
    "sg:postcode":"44132",
    "sg:province":"OH",
    "sg:tags":[
        "general",
        "contractor"
    ],
    "wof:name":"Leach Construction",
    "wof:placetype":"venue"
},
  "geometry": {"coordinates":[-81.492667,41.593237],"type":"Point"}
}