{
  "type": "Feature",
  "properties": {
    "iso:country":"US",
    "sg:address":"10720 Memphis Ave",
    "sg:city":"Cleveland",
    "sg:classifiers":[
        {
            "category":"Autos & Motor Vehicles",
            "subcategory":"Automobile Sales",
            "type":"Retail Goods"
        }
    ],
    "sg:phone":"+1 216 671 5039",
    "sg:postcode":"44144",
    "sg:province":"OH",
    "sg:tags":[
        "truck"
    ],
    "wof:name":"Valley Ford Truck Sales",
    "wof:placetype":"venue"
},
  "geometry": {"coordinates":[-81.762175,41.442501],"type":"Point"}
}