{
  "type": "Feature",
  "properties": {
    "addr:full": "11700 Princeton Pike Cincinnati OH 45246",
    "addr:housenumber": "11700",
    "addr:postcode": "45246",
    "addr:street": "Princeton Pike",
    "iso:country": "US",
    "sg:address": "11700 Princeton Pike",
    "sg:city": "Cincinnati",
    "sg:classifiers": [
      {
        "category": "Shopping",
        "subcategory": "Gifts \u0026 Souvenirs",
        "type": "Retail Goods"
      }
    ],
    "sg:phone": "+1 513 671 9555",
    "sg:postcode": "45246",
    "sg:province": "OH",
    "sg:tags": [
      "shop"
    ],
    "wof:name": "Angels Gifts",
    "wof:placetype": "venue"
  },
  "geometry": {"coordinates":[-84.466252,39.294854],"type":"Point"}
}
