{
  "type": "Feature",
  "properties": {
    "iso:country":"US",
    "sg:address":"9909 Avon Lake Rd",
    "sg:city":"Burbank",
    "sg:classifiers":[
        {
            "category":"Shopping",
            "type":"Retail Goods"
        }
    ],
    "sg:phone":"+1 330 948 6498",
    "sg:postcode":"44214",
    "sg:province":"OH",
    "sg:tags":[
        "merchandise"
    ],
    "wof:name":"Prime Buckeye Factory Shops",
    "wof:placetype":"venue"
},
  "geometry": {"coordinates":[-81.996174,41.003022],"type":"Point"}
}