{
  "type": "Feature",
  "properties": {
    "addr:full": "11053 Prospect Rd Strongsville OH 44149",
    "addr:housenumber": "11053",
    "addr:postcode": "44149",
    "addr:street": "Prospect Rd",
    "iso:country": "US",
    "sg:address": "11053 Prospect Rd",
    "sg:city": "Strongsville",
    "sg:classifiers": [
      {
        "category": "Shopping",
        "subcategory": "Clothing, Apparel, \u0026 Fashions",
        "type": "Retail Goods"
      }
    ],
    "sg:phone": "+1 440 572 7759",
    "sg:postcode": "44149",
    "sg:province": "OH",
    "sg:tags": [
      "tailor"
    ],
    "wof:name": "Victor's Tailoring",
    "wof:placetype": "venue"
  },
  "geometry": {"coordinates":[-81.857561,41.336018],"type":"Point"}
}
