{
  "type": "Feature",
  "properties": {
    "addr:full":"3150 W Sylvania Ave Toledo OH 43613",
    "addr:housenumber":"3150",
    "addr:postcode":"43613",
    "addr:street":"W Sylvania Ave",
    "iso:country":"US",
    "sg:address":"3150 W Sylvania Ave",
    "sg:city":"Toledo",
    "sg:classifiers":[
        {
            "category":"Real Estate",
            "subcategory":"Real Estate Operator",
            "type":"Services"
        },
        {
            "category":"Health Services",
            "subcategory":"Medical Lab",
            "type":"Services"
        }
    ],
    "sg:phone":"+1 419 475 3500",
    "sg:postcode":"43613",
    "sg:province":"OH",
    "sg:tags":[
        "laboratory",
        "dental",
        "work"
    ],
    "wof:name":"Wayton Dental Lab Inc",
    "wof:placetype":"venue"
},
  "geometry": {"coordinates":[-83.62053899999999,41.691928],"type":"Point"}
}