{
  "type": "Feature",
  "properties": {
    "addr:full": "10515 Reading Rd Cincinnati OH 45241",
    "addr:housenumber": "10515",
    "addr:postcode": "45241",
    "addr:street": "Reading Rd",
    "iso:country": "US",
    "sg:address": "10515 Reading Rd",
    "sg:city": "Cincinnati",
    "sg:classifiers": [
      {
        "category": "Wholesale",
        "subcategory": "Auto Parts",
        "type": "Manufacturing \u0026 Wholesale Goods"
      }
    ],
    "sg:phone": "+1 513 733 8200",
    "sg:postcode": "45241",
    "sg:province": "OH",
    "wof:name": "Berlin Tire Centers",
    "wof:placetype": "venue"
  },
  "geometry": {"coordinates":[-84.422086,39.254968],"type":"Point"}
}
