{
  "type": "Feature",
  "properties": {
    "iso:country":"US",
    "sg:address":"10515 Reading Rd",
    "sg:city":"Cincinnati",
    "sg:classifiers":[
        {
            "category":"Wholesale",
            "subcategory":"Auto Parts",
            "type":"Manufacturing & Wholesale Goods"
        }
    ],
    "sg:phone":"+1 513 733 8200",
    "sg:postcode":"45241",
    "sg:province":"OH",
    "wof:name":"Berlin Tire Centers",
    "wof:placetype":"venue"
},
  "geometry": {"coordinates":[-84.422086,39.254968],"type":"Point"}
}