{
  "type": "Feature",
  "properties": {
    "addr:full":"327 S Market St Wooster OH 44691",
    "addr:housenumber":"327",
    "addr:postcode":"44691",
    "addr:street":"S Market St",
    "iso:country":"US",
    "sg:address":"327 S Market St",
    "sg:city":"Wooster",
    "sg:classifiers":[
        {
            "category":"Shopping",
            "type":"Retail Goods"
        }
    ],
    "sg:phone":"+1 330 264 8703",
    "sg:postcode":"44691",
    "sg:province":"OH",
    "sg:tags":[
        "merchandise"
    ],
    "wof:name":"Chapman Memorials",
    "wof:placetype":"venue"
},
  "geometry": {"coordinates":[-81.939289,40.795499],"type":"Point"}
}