{
  "type": "Feature",
  "properties": {
    "addr:full":"3631 Homestead Rd Ravenna OH 44266",
    "addr:housenumber":"3631",
    "addr:postcode":"44266",
    "addr:street":"Homestead Rd",
    "iso:country":"US",
    "sg:address":"3631 Homestead Rd",
    "sg:city":"Ravenna",
    "sg:classifiers":[
        {
            "category":"Real Estate",
            "subcategory":"Real Estate Agent",
            "type":"Services"
        }
    ],
    "sg:phone":"+1 330 325 1545",
    "sg:postcode":"44266",
    "sg:province":"OH",
    "sg:tags":[
        "manager"
    ],
    "wof:name":"Reedy Rentals LLC",
    "wof:placetype":"venue"
},
  "geometry": {"coordinates":[-81.299513,41.089702],"type":"Point"}
}