{
  "type": "Feature",
  "properties": {
    "addr:full": "4100 Leetonia Rd Leetonia OH 44431",
    "addr:housenumber": "4100",
    "addr:postcode": "44431",
    "addr:street": "Leetonia Rd",
    "iso:country": "US",
    "sg:address": "4100 Leetonia Rd",
    "sg:city": "Leetonia",
    "sg:phone": "+1 330 427 2344",
    "sg:postcode": "44431",
    "sg:province": "OH",
    "sg:tags": [
      "farm",
      "corn",
      "wheat",
      "soybean"
    ],
    "wof:name": "Brad Smith",
    "wof:placetype": "venue"
  },
  "geometry": {"coordinates":[-80.755612,40.841985],"type":"Point"}
}
