{
  "type": "Feature",
  "properties": {
    "addr:full": "13400 Brookpark Rd Cleveland OH 44135",
    "addr:housenumber": "13400",
    "addr:postcode": "44135",
    "addr:street": "Brookpark Rd",
    "iso:country": "US",
    "sg:address": "13400 Brookpark Rd",
    "sg:city": "Cleveland",
    "sg:classifiers": [
      {
        "category": "Food \u0026 Beverages",
        "subcategory": "Candy",
        "type": "Retail Goods"
      },
      {
        "category": "Manufacturing",
        "subcategory": "Food",
        "type": "Manufacturing \u0026 Wholesale Goods"
      }
    ],
    "sg:phone": "+1 216 362 8700",
    "sg:postcode": "44135",
    "sg:province": "OH",
    "sg:tags": [
      "product",
      "confectionery",
      "dairy",
      "mfg"
    ],
    "wof:name": "Malley's Chocolates",
    "wof:placetype": "venue"
  },
  "geometry": {"coordinates":[-81.78184,41.418522],"type":"Point"}
}
