{
  "type": "Feature",
  "properties": {
    "addr:full":"4964 Britton Farms Ct Hilliard OH 43026",
    "addr:housenumber":"4964",
    "addr:postcode":"43026",
    "addr:street":"Britton Farms Ct",
    "iso:country":"US",
    "sg:address":"4964 Britton Farms Ct",
    "sg:city":"Hilliard",
    "sg:classifiers":[
        {
            "category":"Insurance",
            "subcategory":"Insurance Agent",
            "type":"Services"
        }
    ],
    "sg:phone":"+1 614 529 1607",
    "sg:postcode":"43026",
    "sg:province":"OH",
    "sg:tags":[
        "adjuster"
    ],
    "wof:name":"Solid Rock Medical Claims Serv",
    "wof:placetype":"venue"
},
  "geometry": {"coordinates":[-83.136168,40.05464],"type":"Point"}
}