{
  "type": "Feature",
  "properties": {
    "iso:country":"US",
    "sg:address":"15237 Euclid Ave",
    "sg:city":"Cleveland",
    "sg:classifiers":[
        {
            "category":"Banks & Credit Unions",
            "subcategory":"Bank",
            "type":"Services"
        }
    ],
    "sg:phone":"+1 216 451 0371",
    "sg:postcode":"44112",
    "sg:province":"OH",
    "sg:tags":[
        "short",
        "institution",
        "business"
    ],
    "wof:name":"Msh Inc",
    "wof:placetype":"venue"
},
  "geometry": {"coordinates":[-81.57537600000001,41.536455],"type":"Point"}
}