{
  "type": "Feature",
  "properties": {
    "addr:full": "1498 Luby Ln Zanesville OH 43701",
    "addr:housenumber": "1498",
    "addr:postcode": "43701",
    "addr:street": "Luby Ln",
    "iso:country": "US",
    "sg:address": "1498 Luby Ln",
    "sg:city": "Zanesville",
    "sg:classifiers": [
      {
        "category": "Farming",
        "subcategory": "Dairy Farm",
        "type": "Manufacturing \u0026 Wholesale Goods"
      }
    ],
    "sg:phone": "+1 740 452 2290",
    "sg:postcode": "43701",
    "sg:province": "OH",
    "wof:name": "Joseph T \u0026 Carol A Luby",
    "wof:placetype": "venue"
  },
  "geometry": {"coordinates":[-82.052362,39.904955],"type":"Point"}
}
