{
  "type": "Feature",
  "properties": {
    "iso:country":"US",
    "sg:address":"1498 Luby Ln",
    "sg:city":"Zanesville",
    "sg:classifiers":[
        {
            "category":"Farming",
            "subcategory":"Dairy Farm",
            "type":"Manufacturing & Wholesale Goods"
        }
    ],
    "sg:phone":"+1 740 452 2290",
    "sg:postcode":"43701",
    "sg:province":"OH",
    "wof:name":"Joseph T & Carol A Luby",
    "wof:placetype":"venue"
},
  "geometry": {"coordinates":[-82.052362,39.904955],"type":"Point"}
}