{
  "type": "Feature",
  "properties": {
    "addr:full": "41 S High St Columbus OH 43215",
    "addr:housenumber": "41",
    "addr:postcode": "43215",
    "addr:street": "S High St",
    "iso:country": "US",
    "sg:address": "41 S High St",
    "sg:city": "Columbus",
    "sg:classifiers": [
      {
        "category": "Banks \u0026 Credit Unions",
        "subcategory": "Investment Brokerage",
        "type": "Services"
      }
    ],
    "sg:phone": "+1 614 629 5100",
    "sg:postcode": "43215",
    "sg:province": "OH",
    "sg:tags": [
      "advisory"
    ],
    "wof:name": "Weber Flton Felman Inv Council",
    "wof:placetype": "venue"
  },
  "geometry": {"coordinates":[-83.000357,39.9604],"type":"Point"}
}
