{
  "type": "Feature",
  "properties": {
    "addr:full": "7261 Engle Rd Cleveland OH 44130",
    "addr:housenumber": "7261",
    "addr:postcode": "44130",
    "addr:street": "Engle Rd",
    "iso:country": "US",
    "sg:address": "7261 Engle Rd",
    "sg:city": "Cleveland",
    "sg:classifiers": [
      {
        "category": "Wholesale",
        "subcategory": "Non-durable Goods",
        "type": "Manufacturing \u0026 Wholesale Goods"
      }
    ],
    "sg:phone": "+1 440 243 1229",
    "sg:postcode": "44130",
    "sg:province": "OH",
    "sg:tags": [
      "publisher",
      "calendar",
      "co",
      "custom"
    ],
    "wof:name": "Town Planner The",
    "wof:placetype": "venue"
  },
  "geometry": {"coordinates":[-81.825052,41.365563],"type":"Point"}
}
