{
  "type": "Feature",
  "properties": {
    "iso:country":"US",
    "sg:address":"1721 Lake Center St NW",
    "sg:city":"Uniontown",
    "sg:classifiers":[
        {
            "category":"Building & Trades",
            "subcategory":"Construction",
            "type":"Services"
        }
    ],
    "sg:phone":"+1 330 877 6299",
    "sg:postcode":"44685",
    "sg:province":"OH",
    "sg:tags":[
        "heavy"
    ],
    "wof:name":"Ebys Construction",
    "wof:placetype":"venue"
},
  "geometry": {"coordinates":[-81.37708000000001,40.957037],"type":"Point"}
}