{
  "type": "Feature",
  "properties": {
    "addr:full":"1355 Mc Kinley Ave Columbus OH 43222",
    "addr:housenumber":"1355",
    "addr:postcode":"43222",
    "addr:street":"Mc Kinley Ave",
    "iso:country":"US",
    "sg:address":"1355 Mc Kinley Ave",
    "sg:city":"Columbus",
    "sg:classifiers":[
        {
            "category":"Manufacturing",
            "subcategory":"Glass & Minerals",
            "type":"Manufacturing & Wholesale Goods"
        }
    ],
    "sg:phone":"+1 614 276 2631",
    "sg:postcode":"43222",
    "sg:province":"OH",
    "sg:tags":[
        "concrete",
        "block",
        "mfg"
    ],
    "wof:name":"Harry Wellnitz Co",
    "wof:placetype":"venue"
},
  "geometry": {"coordinates":[-83.033168,39.963272],"type":"Point"}
}