{
  "type": "Feature",
  "properties": {
    "iso:country":"US",
    "sg:address":"3215 Crown Point St NW",
    "sg:city":"Massillon",
    "sg:classifiers":[
        {
            "category":"Building & Trades",
            "subcategory":"Cleaning & Sanitation",
            "type":"Services"
        }
    ],
    "sg:phone":"+1 330 832 6598",
    "sg:postcode":"44646",
    "sg:province":"OH",
    "sg:tags":[
        "maintenance"
    ],
    "wof:name":"Hall of Fame Window Cleaning",
    "wof:placetype":"venue"
},
  "geometry": {"coordinates":[-81.472488,40.804059],"type":"Point"}
}