{
  "type": "Feature",
  "properties": {
    "addr:full": "1975 Radcliff Dr Cincinnati OH 45204",
    "addr:housenumber": "1975",
    "addr:postcode": "45204",
    "addr:street": "Radcliff Dr",
    "iso:country": "US",
    "sg:address": "1975 Radcliff Dr",
    "sg:city": "Cincinnati",
    "sg:classifiers": [
      {
        "category": "Communications",
        "subcategory": "Television Station",
        "type": "Services"
      }
    ],
    "sg:phone": "+1 513 471 3913",
    "sg:postcode": "45204",
    "sg:province": "OH",
    "sg:tags": [
      "broadcasting",
      "co"
    ],
    "wof:name": "Greater Dayton Public TV Inc",
    "wof:placetype": "venue"
  },
  "geometry": {"coordinates":[-84.546848,39.122063],"type":"Point"}
}
