{
  "type": "Feature",
  "properties": {
    "addr:full":"4833 E Main St Berlin OH 44654",
    "addr:housenumber":"4833",
    "addr:postcode":"44654",
    "addr:street":"E Main St",
    "iso:country":"US",
    "sg:address":"4833 E Main St",
    "sg:city":"Berlin",
    "sg:classifiers":[
        {
            "category":"Food & Beverages",
            "subcategory":"Groceries & Convenience Stores",
            "type":"Retail Goods"
        }
    ],
    "sg:phone":"+1 330 893 3118",
    "sg:postcode":"44654",
    "sg:province":"OH",
    "sg:tags":[
        "product"
    ],
    "wof:name":"Hartman's Home Fresh Foods",
    "wof:placetype":"venue"
},
  "geometry": {"coordinates":[-81.79618000000001,40.561667],"type":"Point"}
}