{
  "type": "Feature",
  "properties": {
    "iso:country":"US",
    "sg:address":"443 Patterson Rd",
    "sg:city":"Dayton",
    "sg:classifiers":[
        {
            "category":"Bars & Pubs",
            "type":"Food & Drink"
        }
    ],
    "sg:phone":"+1 937 293 4542",
    "sg:postcode":"45419",
    "sg:province":"OH",
    "sg:tags":[
        "drinking"
    ],
    "wof:name":"Partners Tavern",
    "wof:placetype":"venue"
},
  "geometry": {"coordinates":[-84.161045,39.724767],"type":"Point"}
}