{
  "type": "Feature",
  "properties": {
    "addr:full": "443 Patterson Rd Dayton OH 45419",
    "addr:housenumber": "443",
    "addr:postcode": "45419",
    "addr:street": "Patterson Rd",
    "iso:country": "US",
    "sg:address": "443 Patterson Rd",
    "sg:city": "Dayton",
    "sg:classifiers": [
      {
        "category": "Bars \u0026 Pubs",
        "type": "Food \u0026 Drink"
      }
    ],
    "sg:phone": "+1 937 293 4542",
    "sg:postcode": "45419",
    "sg:province": "OH",
    "sg:tags": [
      "drinking"
    ],
    "wof:name": "Partners Tavern",
    "wof:placetype": "venue"
  },
  "geometry": {"coordinates":[-84.161045,39.724767],"type":"Point"}
}
