{
  "type": "Feature",
  "properties": {
    "addr:full":"1127 12th St NE Canton OH 44703",
    "addr:housenumber":"1127",
    "addr:postcode":"44703",
    "addr:street":"12Th St Ne",
    "iso:country":"US",
    "sg:address":"1127 12th St NE",
    "sg:city":"Canton",
    "sg:classifiers":[
        {
            "category":"Retail",
            "subcategory":"Self-service Laundry",
            "type":"Services"
        }
    ],
    "sg:phone":"+1 330 456 9949",
    "sg:postcode":"44703",
    "sg:province":"OH",
    "wof:name":"Bubbles & Bleach",
    "wof:placetype":"venue"
},
  "geometry": {"coordinates":[-81.382965,40.809484],"type":"Point"}
}