{
  "type": "Feature",
  "properties": {
    "iso:country":"US",
    "sg:address":"55 Granville St",
    "sg:city":"Columbus",
    "sg:classifiers":[
        {
            "category":"Health Services",
            "subcategory":"Doctor",
            "type":"Services"
        }
    ],
    "sg:phone":"+1 614 471 3020",
    "sg:postcode":"43230",
    "sg:province":"OH",
    "wof:name":"Male JAS R",
    "wof:placetype":"venue"
},
  "geometry": {"coordinates":[-82.879171,40.018774],"type":"Point"}
}