{
  "type": "Feature",
  "properties": {
    "iso:country":"US",
    "sg:address":"693 Jolson Ave",
    "sg:city":"Akron",
    "sg:classifiers":[
        {
            "category":"Wholesale",
            "subcategory":"Machinery & Supplies",
            "type":"Manufacturing & Wholesale Goods"
        }
    ],
    "sg:phone":"+1 330 645 9100",
    "sg:postcode":"44319",
    "sg:province":"OH",
    "sg:tags":[
        "equipment",
        "consulting",
        "industrial",
        "management"
    ],
    "wof:name":"North Amer Met Eqp Sls Group",
    "wof:placetype":"venue"
},
  "geometry": {"coordinates":[-81.547834,40.992962],"type":"Point"}
}