{
  "type": "Feature",
  "properties": {
    "addr:full": "374 Eckard Rd Dalton OH 44618",
    "addr:housenumber": "374",
    "addr:postcode": "44618",
    "addr:street": "Eckard Rd",
    "iso:country": "US",
    "sg:address": "374 Eckard Rd",
    "sg:city": "Dalton",
    "sg:classifiers": [
      {
        "category": "Manufacturing",
        "subcategory": "Tools \u0026 Machinery",
        "type": "Manufacturing \u0026 Wholesale Goods"
      }
    ],
    "sg:phone": "+1 330 828 8357",
    "sg:postcode": "44618",
    "sg:province": "OH",
    "sg:tags": [
      "machine",
      "shop"
    ],
    "wof:name": "C \u0026 D Mfg Inc",
    "wof:placetype": "venue"
  },
  "geometry": {"coordinates":[-81.678096,40.79287],"type":"Point"}
}
