{
  "type": "Feature",
  "properties": {
    "iso:country":"US",
    "sg:address":"374 Eckard Rd",
    "sg:city":"Dalton",
    "sg:classifiers":[
        {
            "category":"Manufacturing",
            "subcategory":"Tools & Machinery",
            "type":"Manufacturing & Wholesale Goods"
        }
    ],
    "sg:phone":"+1 330 828 8357",
    "sg:postcode":"44618",
    "sg:province":"OH",
    "sg:tags":[
        "machine",
        "shop"
    ],
    "wof:name":"C & D Mfg Inc",
    "wof:placetype":"venue"
},
  "geometry": {"coordinates":[-81.678096,40.79287],"type":"Point"}
}