{
  "type": "Feature",
  "properties": {
    "iso:country":"US",
    "sg:address":"6388 Kolthoff Dr",
    "sg:city":"Cleveland",
    "sg:classifiers":[
        {
            "category":"Government",
            "subcategory":"Office",
            "type":"Public Place"
        }
    ],
    "sg:phone":"+1 216 433 1300",
    "sg:postcode":"44142",
    "sg:province":"OH",
    "sg:tags":[
        "city"
    ],
    "wof:name":"Brook Park Civil Svc Dept",
    "wof:placetype":"venue"
},
  "geometry": {"coordinates":[-81.851704,41.39123],"type":"Point"}
}