{
  "type": "Feature",
  "properties": {
    "iso:country":"US",
    "sg:address":"10119 Love-Day Rd",
    "sg:city":"Hamersville",
    "sg:phone":"+1 937 379 1643",
    "sg:postcode":"45130",
    "sg:province":"OH",
    "sg:tags":[
        "farm",
        "soybean",
        "tobacco"
    ],
    "wof:name":"Omar Figgins",
    "wof:placetype":"venue"
},
  "geometry": {"coordinates":[-84.018299,38.919256],"type":"Point"}
}