{
  "type": "Feature",
  "properties": {
    "addr:full": "624 Uplands Camp Rd Dayton OH 45419",
    "addr:housenumber": "624",
    "addr:postcode": "45419",
    "addr:street": "Uplands Camp Rd",
    "iso:country": "US",
    "sg:address": "624 Uplands Camp Rd",
    "sg:city": "Dayton",
    "sg:classifiers": [
      {
        "category": "Autos \u0026 Motor Vehicles",
        "subcategory": "Automobile Sales",
        "type": "Retail Goods"
      },
      {
        "category": "Shopping",
        "subcategory": "Clothing, Apparel, \u0026 Fashions",
        "type": "Retail Goods"
      }
    ],
    "sg:phone": "+1 937 299 1318",
    "sg:postcode": "45419",
    "sg:province": "OH",
    "sg:tags": [
      "equipment",
      "aircraft",
      "parts",
      "transportation",
      "supply"
    ],
    "sg:website": "www.discountpilotsupplies.com",
    "wof:name": "Spinners Discount Pilot Shop",
    "wof:placetype": "venue"
  },
  "geometry": {"coordinates":[-84.183325,39.6931],"type":"Point"}
}
