{
  "type": "Feature",
  "properties": {
    "addr:full":"4636 Karl Rd Columbus OH 43229",
    "addr:housenumber":"4636",
    "addr:postcode":"43229",
    "addr:street":"Karl Rd",
    "iso:country":"US",
    "sg:address":"4636 Karl Rd",
    "sg:city":"Columbus",
    "sg:classifiers":[
        {
            "category":"Autos & Motor Vehicles",
            "subcategory":"Fuel & Gas Station",
            "type":"Retail Goods"
        }
    ],
    "sg:phone":"+1 614 436 7025",
    "sg:postcode":"43229",
    "sg:province":"OH",
    "sg:tags":[
        "oil"
    ],
    "sg:website":"www.procareauto.com",
    "wof:name":"Procare Automotive Svc Ctr",
    "wof:placetype":"venue"
},
  "geometry": {"coordinates":[-82.97716699999999,40.063157],"type":"Point"}
}