{
  "type": "Feature",
  "properties": {
    "addr:full": "15740 Broadway Ave Cleveland OH 44137",
    "addr:housenumber": "15740",
    "addr:postcode": "44137",
    "addr:street": "Broadway Ave",
    "iso:country": "US",
    "sg:address": "15740 Broadway Ave",
    "sg:city": "Cleveland",
    "sg:classifiers": [
      {
        "category": "Personal",
        "subcategory": "Beauty Salon",
        "type": "Services"
      }
    ],
    "sg:phone": "+1 216 475 2887",
    "sg:postcode": "44137",
    "sg:province": "OH",
    "wof:name": "Visual Effects",
    "wof:placetype": "venue"
  },
  "geometry": {"coordinates":[-81.570403,41.415708],"type":"Point"}
}
