{
  "type": "Feature",
  "properties": {
    "iso:country":"US",
    "sg:address":"1002 W Market St",
    "sg:city":"Warren",
    "sg:classifiers":[
        {
            "category":"Building & Trades",
            "subcategory":"Construction",
            "type":"Services"
        }
    ],
    "sg:phone":"+1 330 399 6875",
    "sg:postcode":"44481",
    "sg:province":"OH",
    "sg:tags":[
        "home",
        "remodeling",
        "family",
        "contractor"
    ],
    "sg:website":"www.mhkb.com",
    "wof:name":"Modern Home Kitchen & Bath Ctr",
    "wof:placetype":"venue"
},
  "geometry": {"coordinates":[-80.832624,41.234147],"type":"Point"}
}