{
  "type": "Feature",
  "properties": {
    "addr:full":"620 N Main St Canton OH 44720",
    "addr:housenumber":"620",
    "addr:postcode":"44720",
    "addr:street":"N Main St",
    "iso:country":"US",
    "sg:address":"620 N Main St",
    "sg:city":"Canton",
    "sg:classifiers":[
        {
            "category":"Retail",
            "subcategory":"Repair Shop",
            "type":"Services"
        },
        {
            "category":"Shopping",
            "subcategory":"Musical Instruments",
            "type":"Retail Goods"
        }
    ],
    "sg:phone":"+1 330 499 3378",
    "sg:postcode":"44720",
    "sg:province":"OH",
    "wof:name":"Margolis Music",
    "wof:placetype":"venue"
},
  "geometry": {"coordinates":[-81.403245,40.883045],"type":"Point"}
}