{
  "type": "Feature",
  "properties": {
    "iso:country":"US",
    "sg:address":"57797 Mount Victory Rd",
    "sg:city":"Jacobsburg",
    "sg:classifiers":[
        {
            "category":"Farming",
            "subcategory":"Livestock Farm",
            "type":"Manufacturing & Wholesale Goods"
        }
    ],
    "sg:phone":"+1 740 795 5511",
    "sg:postcode":"43933",
    "sg:province":"OH",
    "sg:tags":[
        "beef",
        "feedlot",
        "cattle"
    ],
    "wof:name":"West Family Farm",
    "wof:placetype":"venue"
},
  "geometry": {"coordinates":[-80.863713,39.918824],"type":"Point"}
}