{
  "type": "Feature",
  "properties": {
    "iso:country":"US",
    "sg:address":"4781 N Ridge Rd W",
    "sg:city":"Geneva",
    "sg:classifiers":[
        {
            "category":"Shopping",
            "type":"Retail Goods"
        }
    ],
    "sg:phone":"+1 440 466 9466",
    "sg:postcode":"44041",
    "sg:province":"OH",
    "sg:tags":[
        "trophy",
        "medal",
        "award"
    ],
    "wof:name":"Winner's Circle Trophy Shop",
    "wof:placetype":"venue"
},
  "geometry": {"coordinates":[-80.925376,41.81176],"type":"Point"}
}