{
  "type": "Feature",
  "properties": {
    "iso:country":"US",
    "sg:address":"120 Harding Way E",
    "sg:city":"Galion",
    "sg:classifiers":[
        {
            "category":"Insurance",
            "subcategory":"Insurance Agent",
            "type":"Services"
        }
    ],
    "sg:phone":"+1 419 468 6686",
    "sg:postcode":"44833",
    "sg:province":"OH",
    "wof:name":"Harry L Hall Agency",
    "wof:placetype":"venue"
},
  "geometry": {"coordinates":[-82.78921699999999,40.733946],"type":"Point"}
}