{
  "type": "Feature",
  "properties": {
    "iso:country":"US",
    "sg:address":"150 W Rayen Ave",
    "sg:city":"Youngstown",
    "sg:classifiers":[
        {
            "category":"Wholesale",
            "subcategory":"Plants",
            "type":"Manufacturing & Wholesale Goods"
        }
    ],
    "sg:phone":"+1 330 746 4611",
    "sg:postcode":"44502",
    "sg:province":"OH",
    "sg:tags":[
        "supply"
    ],
    "wof:name":"Youngstown Plant & Flower Inc",
    "wof:placetype":"venue"
},
  "geometry": {"coordinates":[-80.64954,41.103989],"type":"Point"}
}