{
  "type": "Feature",
  "properties": {
    "addr:full":"518 Kathron Ave Cuyahoga Falls OH 44221",
    "addr:housenumber":"518",
    "addr:postcode":"44221",
    "addr:street":"Kathron Ave",
    "iso:country":"US",
    "sg:address":"518 Kathron Ave",
    "sg:city":"Cuyahoga Falls",
    "sg:classifiers":[
        {
            "category":"Shopping",
            "subcategory":"Computers & Home Electronics",
            "type":"Retail Goods"
        }
    ],
    "sg:phone":"+1 330 929 2748",
    "sg:postcode":"44221",
    "sg:province":"OH",
    "sg:tags":[
        "software"
    ],
    "wof:name":"Alexor Software Group LTD",
    "wof:placetype":"venue"
},
  "geometry": {"coordinates":[-81.476327,41.153328],"type":"Point"}
}