{
  "type": "Feature",
  "properties": {
    "iso:country":"US",
    "sg:address":"9858 Fox Knoll Dr",
    "sg:city":"Orrville",
    "sg:classifiers":[
        {
            "category":"Building & Trades",
            "subcategory":"Landscaping Services",
            "type":"Services"
        }
    ],
    "sg:phone":"+1 330 682 6978",
    "sg:postcode":"44667",
    "sg:province":"OH",
    "sg:tags":[
        "landscape"
    ],
    "wof:name":"Keener Landscaping Inc",
    "wof:placetype":"venue"
},
  "geometry": {"coordinates":[-81.80057600000001,40.887818],"type":"Point"}
}