{
  "type": "Feature",
  "properties": {
    "addr:full": "9858 Fox Knoll Dr Orrville OH 44667",
    "addr:housenumber": "9858",
    "addr:postcode": "44667",
    "addr:street": "Fox Knoll Dr",
    "iso:country": "US",
    "sg:address": "9858 Fox Knoll Dr",
    "sg:city": "Orrville",
    "sg:classifiers": [
      {
        "category": "Building \u0026 Trades",
        "subcategory": "Landscaping Services",
        "type": "Services"
      }
    ],
    "sg:phone": "+1 330 682 6978",
    "sg:postcode": "44667",
    "sg:province": "OH",
    "sg:tags": [
      "landscape"
    ],
    "wof:name": "Keener Landscaping Inc",
    "wof:placetype": "venue"
  },
  "geometry": {"coordinates":[-81.800576,40.887818],"type":"Point"}
}
