{
  "type": "Feature",
  "properties": {
    "addr:full":"5123 Norwich St Hilliard OH 43026",
    "addr:housenumber":"5123",
    "addr:postcode":"43026",
    "addr:street":"Norwich St",
    "iso:country":"US",
    "sg:address":"5123 Norwich St",
    "sg:city":"Hilliard",
    "sg:classifiers":[
        {
            "category":"Health Services",
            "subcategory":"Doctor",
            "type":"Services"
        }
    ],
    "sg:phone":"+1 614 850 9990",
    "sg:postcode":"43026",
    "sg:province":"OH",
    "sg:tags":[
        "physician",
        "surgeon",
        "medical"
    ],
    "wof:name":"Dove Family Care Inc",
    "wof:placetype":"venue"
},
  "geometry": {"coordinates":[-83.153211,40.030492],"type":"Point"}
}