{
  "type": "Feature",
  "properties": {
    "iso:country":"US",
    "sg:address":"10495 State Rte 550",
    "sg:city":"Athens",
    "sg:classifiers":[
        {
            "category":"Building & Trades",
            "subcategory":"Construction",
            "type":"Services"
        }
    ],
    "sg:phone":"+1 740 594 2199",
    "sg:postcode":"45701",
    "sg:province":"OH",
    "sg:tags":[
        "excavating"
    ],
    "wof:name":"J C Trivett Excavating",
    "wof:placetype":"venue"
},
  "geometry": {"coordinates":[-82.092716,39.375077],"type":"Point"}
}