{
  "type": "Feature",
  "properties": {
    "iso:country":"US",
    "sg:address":"771 N Main St",
    "sg:city":"Akron",
    "sg:classifiers":[
        {
            "category":"Professional",
            "subcategory":"Business Services",
            "type":"Services"
        }
    ],
    "sg:phone":"+1 330 434 8187",
    "sg:postcode":"44310",
    "sg:province":"OH",
    "sg:tags":[
        "interior",
        "consultant",
        "design",
        "decorator"
    ],
    "wof:name":"Ken Rowe Interiors",
    "wof:placetype":"venue"
},
  "geometry": {"coordinates":[-81.510769,41.105804],"type":"Point"}
}