{
  "type": "Feature",
  "properties": {
    "iso:country":"US",
    "sg:address":"93 Mosser Pl",
    "sg:city":"Akron",
    "sg:classifiers":[
        {
            "category":"Organizations",
            "subcategory":"Religious Organization",
            "type":"Services"
        }
    ],
    "sg:phone":"+1 330 376 1735",
    "sg:postcode":"44310",
    "sg:province":"OH",
    "sg:tags":[
        "church"
    ],
    "wof:name":"St Anthony's Convent",
    "wof:placetype":"venue"
},
  "geometry": {"coordinates":[-81.513598,41.098814],"type":"Point"}
}