{
  "type": "Feature",
  "properties": {
    "addr:full":"3832 Watterson Rd Cincinnati OH 45227",
    "addr:housenumber":"3832",
    "addr:postcode":"45227",
    "addr:street":"Watterson Rd",
    "iso:country":"US",
    "sg:address":"3832 Watterson Rd",
    "sg:city":"Cincinnati",
    "sg:classifiers":[
        {
            "category":"Retail",
            "subcategory":"Repair Shop",
            "type":"Services"
        }
    ],
    "sg:phone":"+1 513 271 5575",
    "sg:postcode":"45227",
    "sg:province":"OH",
    "sg:tags":[
        "lock",
        "locksmith"
    ],
    "wof:name":"Fairfax Lock & Key Svc",
    "wof:placetype":"venue"
},
  "geometry": {"coordinates":[-84.390941,39.145459],"type":"Point"}
}