{
  "type": "Feature",
  "properties": {
    "iso:country":"US",
    "sg:address":"1949 Fox Trace Trl",
    "sg:city":"Cuyahoga Falls",
    "sg:classifiers":[
        {
            "category":"Building & Trades",
            "subcategory":"Construction",
            "type":"Services"
        }
    ],
    "sg:phone":"+1 330 753 2027",
    "sg:postcode":"44223",
    "sg:province":"OH",
    "wof:name":"Hunters Point/Lexington Homes",
    "wof:placetype":"venue"
},
  "geometry": {"coordinates":[-81.51917899999999,41.156963],"type":"Point"}
}