{
  "type": "Feature",
  "properties": {
    "addr:full": "6138 Pyrmont Rd Lewisburg OH 45338",
    "addr:housenumber": "6138",
    "addr:postcode": "45338",
    "addr:street": "Pyrmont Rd",
    "iso:country": "US",
    "sg:address": "6138 Pyrmont Rd",
    "sg:city": "Lewisburg",
    "sg:classifiers": [
      {
        "category": "Farming",
        "subcategory": "Farm",
        "type": "Manufacturing \u0026 Wholesale Goods"
      }
    ],
    "sg:phone": "+1 937 962 2364",
    "sg:postcode": "45338",
    "sg:province": "OH",
    "sg:tags": [
      "crop",
      "general"
    ],
    "wof:name": "Falldorf Detrick",
    "wof:placetype": "venue"
  },
  "geometry": {"coordinates":[-84.527717,39.802566],"type":"Point"}
}
