{
  "type": "Feature",
  "properties": {
    "addr:full": "823 E Long St Columbus OH 43203",
    "addr:housenumber": "823",
    "addr:postcode": "43203",
    "addr:street": "E Long St",
    "iso:country": "US",
    "sg:address": "823 E Long St",
    "sg:city": "Columbus",
    "sg:classifiers": [
      {
        "category": "Retail",
        "subcategory": "Funeral Services",
        "type": "Services"
      }
    ],
    "sg:phone": "+1 614 372 1927",
    "sg:postcode": "43203",
    "sg:province": "OH",
    "sg:tags": [
      "director"
    ],
    "wof:name": "Mcnabb Funeral Home",
    "wof:placetype": "venue"
  },
  "geometry": {"coordinates":[-82.978547,39.967462],"type":"Point"}
}
