{
  "type": "Feature",
  "properties": {
    "addr:full": "811 Elm St Cincinnati OH 45202",
    "addr:housenumber": "811",
    "addr:postcode": "45202",
    "addr:street": "Elm St",
    "iso:country": "US",
    "sg:address": "811 Elm St",
    "sg:city": "Cincinnati",
    "sg:classifiers": [
      {
        "category": "Shopping",
        "subcategory": "Clothing, Apparel, \u0026 Fashions",
        "type": "Retail Goods"
      }
    ],
    "sg:phone": "+1 513 579 8700",
    "sg:postcode": "45202",
    "sg:province": "OH",
    "sg:tags": [
      "family"
    ],
    "wof:name": "Keepin It Real Urban Wear",
    "wof:placetype": "venue"
  },
  "geometry": {"coordinates":[-84.517234,39.104448],"type":"Point"}
}
