{
  "type": "Feature",
  "properties": {
    "iso:country":"US",
    "sg:address":"811 Elm St",
    "sg:city":"Cincinnati",
    "sg:classifiers":[
        {
            "category":"Shopping",
            "subcategory":"Clothing, Apparel, & Fashions",
            "type":"Retail Goods"
        }
    ],
    "sg:phone":"+1 513 579 8700",
    "sg:postcode":"45202",
    "sg:province":"OH",
    "sg:tags":[
        "family"
    ],
    "wof:name":"Keepin It Real Urban Wear",
    "wof:placetype":"venue"
},
  "geometry": {"coordinates":[-84.517234,39.104448],"type":"Point"}
}