{
  "type": "Feature",
  "properties": {
    "iso:country":"US",
    "sg:address":"3330 Prospect Ave E",
    "sg:city":"Cleveland",
    "sg:classifiers":[
        {
            "category":"Health Services",
            "subcategory":"Clinic",
            "type":"Services"
        }
    ],
    "sg:phone":"+1 216 426 9996",
    "sg:postcode":"44115",
    "sg:province":"OH",
    "sg:tags":[
        "home"
    ],
    "wof:name":"Xcel Healthcare Providers Inc",
    "wof:placetype":"venue"
},
  "geometry": {"coordinates":[-81.663363,41.501503],"type":"Point"}
}