{
  "type": "Feature",
  "properties": {
    "addr:full": "1335 Bluejack Ln Newark OH 43056",
    "addr:housenumber": "1335",
    "addr:postcode": "43056",
    "addr:street": "Bluejack Ln",
    "iso:country": "US",
    "sg:address": "1335 Bluejack Ln",
    "sg:city": "Newark",
    "sg:classifiers": [
      {
        "category": "Building \u0026 Trades",
        "subcategory": "Construction",
        "type": "Services"
      }
    ],
    "sg:phone": "+1 740 323 1335",
    "sg:postcode": "43056",
    "sg:province": "OH",
    "sg:tags": [
      "house"
    ],
    "wof:name": "Rosato \u0026 Associates",
    "wof:placetype": "venue"
  },
  "geometry": {"coordinates":[-82.433865,40.017738],"type":"Point"}
}
