{
  "type": "Feature",
  "properties": {
    "addr:full":"3319 State Rte 141 Gallipolis OH 45631",
    "addr:housenumber":"3319",
    "addr:postcode":"45631",
    "addr:street":"State Rte 141",
    "iso:country":"US",
    "sg:address":"3319 State Rte 141",
    "sg:city":"Gallipolis",
    "sg:classifiers":[
        {
            "category":"Wholesale",
            "subcategory":"Auto Parts",
            "type":"Manufacturing & Wholesale Goods"
        }
    ],
    "sg:phone":"+1 740 446 0800",
    "sg:postcode":"45631",
    "sg:province":"OH",
    "sg:tags":[
        "truck",
        "accessory"
    ],
    "wof:name":"Scufy's Rv & Supply Inc",
    "wof:placetype":"venue"
},
  "geometry": {"coordinates":[-82.273235,38.796851],"type":"Point"}
}