{
  "type": "Feature",
  "properties": {
    "iso:country":"US",
    "sg:address":"1320 Belmont Ave",
    "sg:city":"Youngstown",
    "sg:classifiers":[
        {
            "category":"Health Services",
            "subcategory":"Doctor",
            "type":"Services"
        }
    ],
    "sg:phone":"+1 330 746 0607",
    "sg:postcode":"44504",
    "sg:province":"OH",
    "sg:tags":[
        "physician",
        "family",
        "practice",
        "surgeons",
        "medicine",
        "surgeon"
    ],
    "wof:name":"D MHD Family Practice",
    "wof:placetype":"venue"
},
  "geometry": {"coordinates":[-80.656811,41.117005],"type":"Point"}
}