{
  "type": "Feature",
  "properties": {
    "addr:full": "272 Milton Dr Tallmadge OH 44278",
    "addr:housenumber": "272",
    "addr:postcode": "44278",
    "addr:street": "Milton Dr",
    "iso:country": "US",
    "sg:address": "272 Milton Dr",
    "sg:city": "Tallmadge",
    "sg:classifiers": [
      {
        "category": "Organizations",
        "subcategory": "Religious Organization",
        "type": "Services"
      }
    ],
    "sg:phone": "+1 330 630 9638",
    "sg:postcode": "44278",
    "sg:province": "OH",
    "sg:tags": [
      "clergy"
    ],
    "wof:name": "David S Kiewit",
    "wof:placetype": "venue"
  },
  "geometry": {"coordinates":[-81.405917,41.107592],"type":"Point"}
}
