{
  "type": "Feature",
  "properties": {
    "iso:country":"US",
    "sg:address":"350 S Locust St",
    "sg:city":"Oxford",
    "sg:classifiers":[
        {
            "category":"Banks & Credit Unions",
            "subcategory":"Bank",
            "type":"Services"
        }
    ],
    "sg:phone":"+1 513 523 5102",
    "sg:postcode":"45056",
    "sg:province":"OH",
    "sg:tags":[
        "depository",
        "banking",
        "check",
        "cashing"
    ],
    "wof:name":"First American Cash Advance",
    "wof:placetype":"venue"
},
  "geometry": {"coordinates":[-84.749472,39.506344],"type":"Point"}
}