{
  "type": "Feature",
  "properties": {
    "addr:full": "350 S Locust St Oxford OH 45056",
    "addr:housenumber": "350",
    "addr:postcode": "45056",
    "addr:street": "S Locust St",
    "iso:country": "US",
    "sg:address": "350 S Locust St",
    "sg:city": "Oxford",
    "sg:classifiers": [
      {
        "category": "Banks \u0026 Credit Unions",
        "subcategory": "Bank",
        "type": "Services"
      }
    ],
    "sg:phone": "+1 513 523 5102",
    "sg:postcode": "45056",
    "sg:province": "OH",
    "sg:tags": [
      "depository",
      "banking",
      "check",
      "cashing"
    ],
    "wof:name": "First American Cash Advance",
    "wof:placetype": "venue"
  },
  "geometry": {"coordinates":[-84.749472,39.506344],"type":"Point"}
}
