{
  "type": "Feature",
  "properties": {
    "iso:country":"US",
    "sg:address":"2400 Romig Rd",
    "sg:city":"Akron",
    "sg:classifiers":[
        {
            "category":"Shopping",
            "subcategory":"Jewelry",
            "type":"Retail Goods"
        }
    ],
    "sg:phone":"+1 330 753 4500",
    "sg:postcode":"44320",
    "sg:province":"OH",
    "wof:name":"Zales Jewelry",
    "wof:placetype":"venue"
},
  "geometry": {"coordinates":[-81.580813,41.048739],"type":"Point"}
}