{
  "type": "Feature",
  "properties": {
    "iso:country":"US",
    "sg:address":"4220 State Route 43",
    "sg:city":"Kent",
    "sg:classifiers":[
        {
            "category":"Restaurant",
            "type":"Food & Drink"
        }
    ],
    "sg:menulink":"http://www.allmenus.com/oh/brimfield/61459-gemini-pizza/menu/",
    "sg:phone":"+1 330 676 1966",
    "sg:postcode":"44240",
    "sg:province":"OH",
    "sg:tags":[
        "american",
        "pizza"
    ],
    "wof:name":"Gemini Pizza",
    "wof:placetype":"venue"
},
  "geometry": {"coordinates":[-81.353089,41.170977],"type":"Point"}
}