{
  "type": "Feature",
  "properties": {
    "addr:full":"185 Cohen Dr Zanesville OH 43701",
    "addr:housenumber":"185",
    "addr:postcode":"43701",
    "addr:street":"Cohen Dr",
    "iso:country":"US",
    "sg:address":"185 Cohen Dr",
    "sg:city":"Zanesville",
    "sg:classifiers":[
        {
            "category":"Building & Trades",
            "subcategory":"Construction",
            "type":"Services"
        }
    ],
    "sg:phone":"+1 740 704 3872",
    "sg:postcode":"43701",
    "sg:province":"OH",
    "sg:tags":[
        "heavy"
    ],
    "wof:name":"Envirotect",
    "wof:placetype":"venue"
},
  "geometry": {"coordinates":[-81.889847,39.964485],"type":"Point"}
}