{
  "type": "Feature",
  "properties": {
    "addr:full": "3837 Starr Centre Dr Canfield OH 44406",
    "addr:housenumber": "3837",
    "addr:postcode": "44406",
    "addr:street": "Starr Centre Dr",
    "iso:country": "US",
    "sg:address": "3837 Starr Centre Dr",
    "sg:city": "Canfield",
    "sg:classifiers": [
      {
        "category": "Social Services",
        "type": "Services"
      }
    ],
    "sg:phone": "+1 330 702 0208",
    "sg:postcode": "44406",
    "sg:province": "OH",
    "sg:tags": [
      "counselor",
      "marriage",
      "family"
    ],
    "wof:name": "Antoinette Beard",
    "wof:placetype": "venue"
  },
  "geometry": {"coordinates":[-80.716653,41.025354],"type":"Point"}
}
