{
  "type": "Feature",
  "properties": {
    "iso:country":"US",
    "sg:address":"17 N Chalfant Ave",
    "sg:city":"Newark",
    "sg:classifiers":[
        {
            "category":"Social Services",
            "subcategory":"Child Care",
            "type":"Services"
        }
    ],
    "sg:phone":"+1 740 522 3338",
    "sg:postcode":"43055",
    "sg:province":"OH",
    "sg:tags":[
        "center",
        "preschool"
    ],
    "wof:name":"Pride -N- Joy Preschool Inc",
    "wof:placetype":"venue"
},
  "geometry": {"coordinates":[-82.469079,40.043291],"type":"Point"}
}