{
  "type": "Feature",
  "properties": {
    "iso:country":"US",
    "sg:address":"150 E Wilson Bridge Rd",
    "sg:city":"Worthington",
    "sg:classifiers":[
        {
            "category":"Professional",
            "subcategory":"Management & Consulting",
            "type":"Services"
        }
    ],
    "sg:phone":"+1 614 781 0787",
    "sg:postcode":"43085",
    "sg:province":"OH",
    "sg:tags":[
        "consultant",
        "training"
    ],
    "sg:website":"www.coresi.com",
    "wof:name":"Core Solutions Inc",
    "wof:placetype":"venue"
},
  "geometry": {"coordinates":[-83.007259,40.109505],"type":"Point"}
}