{
  "type": "Feature",
  "properties": {
    "addr:full":"2113 Central Ave Middletown OH 45044",
    "addr:housenumber":"2113",
    "addr:postcode":"45044",
    "addr:street":"Central Ave",
    "iso:country":"US",
    "sg:address":"2113 Central Ave",
    "sg:city":"Middletown",
    "sg:classifiers":[
        {
            "category":"Real Estate",
            "subcategory":"Real Estate Agent",
            "type":"Services"
        }
    ],
    "sg:phone":"+1 513 422 4040",
    "sg:postcode":"45044",
    "sg:province":"OH",
    "wof:name":"Don M Realtors Johnson",
    "wof:placetype":"venue"
},
  "geometry": {"coordinates":[-84.386578,39.512576],"type":"Point"}
}