{
  "type": "Feature",
  "properties": {
    "iso:country":"US",
    "sg:address":"2522 E 38th St",
    "sg:city":"Lorain",
    "sg:classifiers":[
        {
            "category":"Professional",
            "type":"Services"
        }
    ],
    "sg:phone":"+1 440 277 6642",
    "sg:postcode":"44055",
    "sg:province":"OH",
    "wof:name":"Kuprianov Michail",
    "wof:placetype":"venue"
},
  "geometry": {"coordinates":[-82.110057,41.436195],"type":"Point"}
}