{
  "type": "Feature",
  "properties": {
    "addr:full": "12420 Kinsman Rd Burton OH 44021",
    "addr:housenumber": "12420",
    "addr:postcode": "44021",
    "addr:street": "Kinsman Rd",
    "iso:country": "US",
    "sg:address": "12420 Kinsman Rd",
    "sg:city": "Burton",
    "sg:classifiers": [
      {
        "category": "Home \u0026 Garden",
        "subcategory": "Furniture",
        "type": "Retail Goods"
      }
    ],
    "sg:phone": "+1 440 834 8200",
    "sg:postcode": "44021",
    "sg:province": "OH",
    "wof:name": "Millers Furniture",
    "wof:placetype": "venue"
  },
  "geometry": {"coordinates":[-81.19118,41.470921],"type":"Point"}
}
