{
  "type": "Feature",
  "properties": {
    "iso:country":"US",
    "sg:address":"362 Heritage Ridge Rd",
    "sg:city":"Blanchester",
    "sg:classifiers":[
        {
            "category":"Real Estate",
            "subcategory":"Real Estate Agent",
            "type":"Services"
        }
    ],
    "sg:phone":"+1 513 625 4193",
    "sg:postcode":"45107",
    "sg:province":"OH",
    "sg:tags":[
        "inspection"
    ],
    "wof:name":"Ameri Spec Home Inspection Svc",
    "wof:placetype":"venue"
},
  "geometry": {"coordinates":[-84.002026,39.261258],"type":"Point"}
}