{
  "type": "Feature",
  "properties": {
    "iso:country":"US",
    "sg:address":"1910 Indian Wood Cir",
    "sg:city":"Maumee",
    "sg:classifiers":[
        {
            "category":"Insurance",
            "subcategory":"Insurance Agent",
            "type":"Services"
        }
    ],
    "sg:phone":"+1 419 887 1225",
    "sg:postcode":"43537",
    "sg:province":"OH",
    "wof:name":"Security Benefits",
    "wof:placetype":"venue"
},
  "geometry": {"coordinates":[-83.678316,41.584362],"type":"Point"}
}