{
  "type": "Feature",
  "properties": {
    "iso:country":"US",
    "sg:address":"7900 W Sugar Grove Rd",
    "sg:city":"Covington",
    "sg:classifiers":[
        {
            "category":"Organizations",
            "subcategory":"Religious Organization",
            "type":"Services"
        }
    ],
    "sg:phone":"+1 937 473 5270",
    "sg:postcode":"45318",
    "sg:province":"OH",
    "sg:tags":[
        "church"
    ],
    "wof:name":"Stillwater Community Church",
    "wof:placetype":"venue"
},
  "geometry": {"coordinates":[-84.352457,40.080317],"type":"Point"}
}