{
  "type": "Feature",
  "properties": {
    "addr:full":"9 W Main St West Jefferson OH 43162",
    "addr:housenumber":"9",
    "addr:postcode":"43162",
    "addr:street":"W Main St",
    "iso:country":"US",
    "sg:address":"9 W Main St",
    "sg:city":"West Jefferson",
    "sg:classifiers":[
        {
            "category":"Insurance",
            "subcategory":"Insurance Agent",
            "type":"Services"
        }
    ],
    "sg:phone":"+1 614 879 8717",
    "sg:postcode":"43162",
    "sg:province":"OH",
    "wof:name":"Graves Insurance",
    "wof:placetype":"venue"
},
  "geometry": {"coordinates":[-83.26831900000001,39.944764],"type":"Point"}
}