{
  "type": "Feature",
  "properties": {
    "addr:full":"8894 State Rte 14 Streetsboro OH 44241",
    "addr:housenumber":"8894",
    "addr:postcode":"44241",
    "addr:street":"State Rte 14",
    "iso:country":"US",
    "sg:address":"8894 State Rte 14",
    "sg:city":"Streetsboro",
    "sg:classifiers":[
        {
            "category":"Organizations",
            "subcategory":"Religious Organization",
            "type":"Services"
        }
    ],
    "sg:phone":"+1 330 626 3424",
    "sg:postcode":"44241",
    "sg:province":"OH",
    "sg:tags":[
        "church"
    ],
    "wof:name":"St Joan Of Arc Streetsboro",
    "wof:placetype":"venue"
},
  "geometry": {"coordinates":[-81.334292,41.236149],"type":"Point"}
}