{
  "type": "Feature",
  "properties": {
    "addr:full": "2208 W Alexis Rd Toledo OH 43613",
    "addr:housenumber": "2208",
    "addr:postcode": "43613",
    "addr:street": "W Alexis Rd",
    "iso:country": "US",
    "sg:address": "2208 W Alexis Rd",
    "sg:city": "Toledo",
    "sg:classifiers": [
      {
        "category": "Cinema",
        "subcategory": "Movie Rental",
        "type": "Entertainment"
      }
    ],
    "sg:phone": "+1 419 475 5671",
    "sg:postcode": "43613",
    "sg:province": "OH",
    "sg:tags": [
      "leasing",
      "video",
      "disc",
      "tape"
    ],
    "wof:name": "Galaxy Video",
    "wof:placetype": "venue"
  },
  "geometry": {"coordinates":[-83.600128,41.721277],"type":"Point"}
}
