{
  "type": "Feature",
  "properties": {
    "iso:country":"US",
    "sg:address":"4213 Hanover Dr",
    "sg:city":"Mason",
    "sg:classifiers":[
        {
            "category":"Wholesale",
            "subcategory":"Non-durable Goods",
            "type":"Manufacturing & Wholesale Goods"
        }
    ],
    "sg:phone":"+1 513 398 1177",
    "sg:postcode":"45040",
    "sg:province":"OH",
    "sg:tags":[
        "specialty",
        "mfg"
    ],
    "wof:name":"Jtc Assoc",
    "wof:placetype":"venue"
},
  "geometry": {"coordinates":[-84.292985,39.362189],"type":"Point"}
}