{
  "type": "Feature",
  "properties": {
    "iso:country":"US",
    "sg:address":"6220 E Dublin Granville Rd",
    "sg:city":"New Albany",
    "sg:classifiers":[
        {
            "category":"Organizations",
            "subcategory":"Religious Organization",
            "type":"Services"
        }
    ],
    "sg:phone":"+1 614 939 0765",
    "sg:postcode":"43054",
    "sg:province":"OH",
    "sg:tags":[
        "synagogue"
    ],
    "wof:name":"Chabad Center For A Jewish",
    "wof:placetype":"venue"
},
  "geometry": {"coordinates":[-82.822384,40.081844],"type":"Point"}
}