{
  "type": "Feature",
  "properties": {
    "addr:full": "6220 E Dublin Granville Rd New Albany OH 43054",
    "addr:housenumber": "6220",
    "addr:postcode": "43054",
    "addr:street": "E Dublin Granville Rd",
    "iso:country": "US",
    "sg:address": "6220 E Dublin Granville Rd",
    "sg:city": "New Albany",
    "sg:classifiers": [
      {
        "category": "Organizations",
        "subcategory": "Religious Organization",
        "type": "Services"
      }
    ],
    "sg:phone": "+1 614 939 0765",
    "sg:postcode": "43054",
    "sg:province": "OH",
    "sg:tags": [
      "synagogue"
    ],
    "wof:name": "Chabad Center For A Jewish",
    "wof:placetype": "venue"
  },
  "geometry": {"coordinates":[-82.822384,40.081844],"type":"Point"}
}
