{
  "type": "Feature",
  "properties": {
    "iso:country":"US",
    "sg:address":"7356 Hiner Rd",
    "sg:city":"Wooster",
    "sg:classifiers":[
        {
            "category":"Banks & Credit Unions",
            "subcategory":"Financial Services",
            "type":"Services"
        }
    ],
    "sg:phone":"+1 330 264 2084",
    "sg:postcode":"44691",
    "sg:province":"OH",
    "sg:tags":[
        "trust",
        "management"
    ],
    "wof:name":"Howman Family Revocable Trust",
    "wof:placetype":"venue"
},
  "geometry": {"coordinates":[-82.056917,40.839511],"type":"Point"}
}