{
  "type": "Feature",
  "properties": {
    "addr:full": "7356 Hiner Rd Wooster OH 44691",
    "addr:housenumber": "7356",
    "addr:postcode": "44691",
    "addr:street": "Hiner Rd",
    "iso:country": "US",
    "sg:address": "7356 Hiner Rd",
    "sg:city": "Wooster",
    "sg:classifiers": [
      {
        "category": "Banks \u0026 Credit Unions",
        "subcategory": "Financial Services",
        "type": "Services"
      }
    ],
    "sg:phone": "+1 330 264 2084",
    "sg:postcode": "44691",
    "sg:province": "OH",
    "sg:tags": [
      "trust",
      "management"
    ],
    "wof:name": "Howman Family Revocable Trust",
    "wof:placetype": "venue"
  },
  "geometry": {"coordinates":[-82.056917,40.839511],"type":"Point"}
}
