{
  "type": "Feature",
  "properties": {
    "addr:full": "39105 Bradbury Rd Middleport OH 45760",
    "addr:postcode": "39105;45760",
    "addr:street": "Bradbury Rd",
    "iso:country": "US",
    "sg:address": "39105 Bradbury Rd",
    "sg:city": "Middleport",
    "sg:classifiers": [
      {
        "category": "Education",
        "subcategory": "School",
        "type": "Public Place"
      }
    ],
    "sg:phone": "+1 740 992 2349",
    "sg:postcode": "45760",
    "sg:province": "OH",
    "wof:name": "Bradbury Elementary School",
    "wof:placetype": "venue"
  },
  "geometry": {"coordinates":[-82.071962,39.011687],"type":"Point"}
}
