{
  "type": "Feature",
  "properties": {
    "iso:country":"US",
    "sg:address":"1200 S High St",
    "sg:city":"Columbus",
    "sg:classifiers":[
        {
            "category":"Retail",
            "subcategory":"Veterinary Services",
            "type":"Services"
        }
    ],
    "sg:phone":"+1 614 444 9696",
    "sg:postcode":"43206",
    "sg:province":"OH",
    "sg:tags":[
        "small",
        "hospital",
        "animal"
    ],
    "wof:name":"German Village Veterinary Hosp",
    "wof:placetype":"venue"
},
  "geometry": {"coordinates":[-82.99609100000001,39.937366],"type":"Point"}
}