{
  "type": "Feature",
  "properties": {
    "iso:country":"US",
    "sg:address":"429 W Liberty St",
    "sg:city":"Wooster",
    "sg:classifiers":[
        {
            "category":"Building & Trades",
            "subcategory":"Electrical",
            "type":"Services"
        }
    ],
    "sg:phone":"+1 330 262 3916",
    "sg:postcode":"44691",
    "sg:province":"OH",
    "sg:tags":[
        "electrical",
        "contractor"
    ],
    "wof:name":"Wayne Electric Inc",
    "wof:placetype":"venue"
},
  "geometry": {"coordinates":[-81.948347,40.798355],"type":"Point"}
}