{
  "type": "Feature",
  "properties": {
    "iso:country":"US",
    "sg:address":"304 S Breiel Blvd",
    "sg:city":"Middletown",
    "sg:classifiers":[
        {
            "category":"Professional",
            "subcategory":"Accounting & Tax Preparation",
            "type":"Services"
        }
    ],
    "sg:phone":"+1 513 422 4838",
    "sg:postcode":"45044",
    "sg:province":"OH",
    "wof:name":"Hendricks James E CPA",
    "wof:placetype":"venue"
},
  "geometry": {"coordinates":[-84.354793,39.509609],"type":"Point"}
}