{
  "type": "Feature",
  "properties": {
    "addr:full":"6570 Mayfield Rd Cleveland OH 44124",
    "addr:housenumber":"6570",
    "addr:postcode":"44124",
    "addr:street":"Mayfield Rd",
    "iso:country":"US",
    "sg:address":"6570 Mayfield Rd",
    "sg:city":"Cleveland",
    "sg:classifiers":[
        {
            "category":"Freight",
            "type":"Transportation"
        }
    ],
    "sg:phone":"+1 440 446 0049",
    "sg:postcode":"44124",
    "sg:province":"OH",
    "sg:tags":[
        "warehouse",
        "self",
        "storage"
    ],
    "wof:name":"Cleveland Design Warehouse",
    "wof:placetype":"venue"
},
  "geometry": {"coordinates":[-81.442205,41.520009],"type":"Point"}
}