{
  "type": "Feature",
  "properties": {
    "addr:full":"3920 Burnham Ave Toledo OH 43612",
    "addr:housenumber":"3920",
    "addr:postcode":"43612",
    "addr:street":"Burnham Ave",
    "iso:country":"US",
    "sg:address":"3920 Burnham Ave",
    "sg:city":"Toledo",
    "sg:classifiers":[
        {
            "category":"Local Transit",
            "type":"Transportation"
        }
    ],
    "sg:phone":"+1 419 269 0332",
    "sg:postcode":"43612",
    "sg:province":"OH",
    "sg:tags":[
        "ambulance"
    ],
    "wof:name":"Brookeside Ambulette",
    "wof:placetype":"venue"
},
  "geometry": {"coordinates":[-83.559156,41.692383],"type":"Point"}
}