{
  "type": "Feature",
  "properties": {
    "addr:full": "43 Main St Glouster OH 45732",
    "addr:housenumber": "43",
    "addr:postcode": "45732",
    "addr:street": "Main St",
    "iso:country": "US",
    "sg:address": "43 Main St",
    "sg:city": "Glouster",
    "sg:classifiers": [
      {
        "category": "Wholesale",
        "subcategory": "Groceries",
        "type": "Manufacturing \u0026 Wholesale Goods"
      }
    ],
    "sg:phone": "+1 740 767 4946",
    "sg:postcode": "45732",
    "sg:province": "OH",
    "sg:tags": [
      "food",
      "broker"
    ],
    "wof:name": "Zio Products",
    "wof:placetype": "venue"
  },
  "geometry": {"coordinates":[-82.080666,39.503433],"type":"Point"}
}
