{
  "type": "Feature",
  "properties": {
    "addr:full": "769 Lakengren Dr Eaton OH 45320",
    "addr:housenumber": "769",
    "addr:postcode": "45320",
    "addr:street": "Lakengren Dr",
    "iso:country": "US",
    "sg:address": "769 Lakengren Dr",
    "sg:city": "Eaton",
    "sg:classifiers": [
      {
        "category": "Professional",
        "subcategory": "Management \u0026 Consulting",
        "type": "Services"
      }
    ],
    "sg:phone": "+1 937 456 5567",
    "sg:postcode": "45320",
    "sg:province": "OH",
    "wof:name": "Ron Mickelson \u0026 Co",
    "wof:placetype": "venue"
  },
  "geometry": {"coordinates":[-84.682242,39.6883],"type":"Point"}
}
