{
  "type": "Feature",
  "properties": {
    "addr:full": "3480 N Main St Findlay OH 45840",
    "addr:housenumber": "3480",
    "addr:postcode": "45840",
    "addr:street": "N Main St",
    "iso:country": "US",
    "sg:address": "3480 N Main St",
    "sg:city": "Findlay",
    "sg:classifiers": [
      {
        "category": "Building \u0026 Trades",
        "subcategory": "Construction",
        "type": "Services"
      }
    ],
    "sg:phone": "+1 419 422 6672",
    "sg:postcode": "45840",
    "sg:province": "OH",
    "sg:tags": [
      "house"
    ],
    "wof:name": "Dazec Inc",
    "wof:placetype": "venue"
  },
  "geometry": {"coordinates":[-83.649964,41.082158],"type":"Point"}
}
