{
  "type": "Feature",
  "properties": {
    "iso:country":"US",
    "sg:address":"3480 N Main St",
    "sg:city":"Findlay",
    "sg:classifiers":[
        {
            "category":"Building & Trades",
            "subcategory":"Construction",
            "type":"Services"
        }
    ],
    "sg:phone":"+1 419 422 6672",
    "sg:postcode":"45840",
    "sg:province":"OH",
    "sg:tags":[
        "house"
    ],
    "wof:name":"Dazec Inc",
    "wof:placetype":"venue"
},
  "geometry": {"coordinates":[-83.649964,41.082158],"type":"Point"}
}