{
  "type": "Feature",
  "properties": {
    "iso:country":"US",
    "sg:address":"2123 Merrill Rd",
    "sg:city":"Kent",
    "sg:classifiers":[
        {
            "category":"Government",
            "subcategory":"Office",
            "type":"Public Place"
        }
    ],
    "sg:phone":"+1 330 673 5332",
    "sg:postcode":"44240",
    "sg:province":"OH",
    "sg:tags":[
        "village"
    ],
    "wof:name":"Brake Lake Village Office",
    "wof:placetype":"venue"
},
  "geometry": {"coordinates":[-81.32083799999999,41.160349],"type":"Point"}
}