{
  "type": "Feature",
  "properties": {
    "addr:full": "145 W 2nd St Salem OH 44460",
    "addr:housenumber": "145",
    "addr:postcode": "44460",
    "addr:street": "W 2Nd St",
    "iso:country": "US",
    "sg:address": "145 W 2nd St",
    "sg:city": "Salem",
    "sg:classifiers": [
      {
        "category": "Retail",
        "subcategory": "Laundry \u0026 Dry Cleaning",
        "type": "Services"
      }
    ],
    "sg:phone": "+1 330 337 7943",
    "sg:postcode": "44460",
    "sg:province": "OH",
    "sg:tags": [
      "cleaners",
      "rug",
      "carpet"
    ],
    "wof:name": "Franklin Cleaning Svc",
    "wof:placetype": "venue"
  },
  "geometry": {"coordinates":[-80.857648,40.90205],"type":"Point"}
}
