{
  "type": "Feature",
  "properties": {
    "addr:full": "1310 Parkway Blvd Alliance OH 44601",
    "addr:housenumber": "1310",
    "addr:postcode": "44601",
    "addr:street": "Parkway Blvd",
    "iso:country": "US",
    "sg:address": "1310 Parkway Blvd",
    "sg:city": "Alliance",
    "sg:classifiers": [
      {
        "category": "Professional",
        "subcategory": "Engineering",
        "type": "Services"
      }
    ],
    "sg:phone": "+1 330 821 4460",
    "sg:postcode": "44601",
    "sg:province": "OH",
    "sg:tags": [
      "engineer"
    ],
    "wof:name": "Robert Herrmann PE",
    "wof:placetype": "venue"
  },
  "geometry": {"coordinates":[-81.117322,40.908693],"type":"Point"}
}
