{
  "type": "Feature",
  "properties": {
    "addr:full": "1245 N High St Columbus OH 43201",
    "addr:housenumber": "1245",
    "addr:postcode": "43201",
    "addr:street": "N High St",
    "iso:country": "US",
    "sg:address": "1245 N High St",
    "sg:city": "Columbus",
    "sg:classifiers": [
      {
        "category": "Shopping",
        "subcategory": "Used Merchandise",
        "type": "Retail Goods"
      }
    ],
    "sg:phone": "+1 614 294 2130",
    "sg:postcode": "43201",
    "sg:province": "OH",
    "sg:tags": [
      "pawnbroker"
    ],
    "wof:name": "Luigi's Pawn Shop",
    "wof:placetype": "venue"
  },
  "geometry": {"coordinates":[-83.005654,39.987416],"type":"Point"}
}
