{
  "type": "Feature",
  "properties": {
    "iso:country":"US",
    "sg:address":"7908 Kellogg Creek Dr",
    "sg:city":"Mentor",
    "sg:classifiers":[
        {
            "category":"Banks & Credit Unions",
            "subcategory":"Bank",
            "type":"Services"
        }
    ],
    "sg:phone":"+1 440 205 0902",
    "sg:postcode":"44060",
    "sg:province":"OH",
    "sg:tags":[
        "loan",
        "real estate"
    ],
    "wof:name":"Falls Closing Inc",
    "wof:placetype":"venue"
},
  "geometry": {"coordinates":[-81.301773,41.657211],"type":"Point"}
}