{
  "type": "Feature",
  "properties": {
    "addr:full": "7908 Kellogg Creek Dr Mentor OH 44060",
    "addr:housenumber": "7908",
    "addr:postcode": "44060",
    "addr:street": "Kellogg Creek Dr",
    "iso:country": "US",
    "sg:address": "7908 Kellogg Creek Dr",
    "sg:city": "Mentor",
    "sg:classifiers": [
      {
        "category": "Banks \u0026 Credit Unions",
        "subcategory": "Bank",
        "type": "Services"
      }
    ],
    "sg:phone": "+1 440 205 0902",
    "sg:postcode": "44060",
    "sg:province": "OH",
    "sg:tags": [
      "loan",
      "real estate"
    ],
    "wof:name": "Falls Closing Inc",
    "wof:placetype": "venue"
  },
  "geometry": {"coordinates":[-81.301773,41.657211],"type":"Point"}
}
