{
  "type": "Feature",
  "properties": {
    "iso:country":"US",
    "sg:address":"1948 S Washington Ave",
    "sg:city":"Columbus",
    "sg:classifiers":[
        {
            "category":"Building & Trades",
            "subcategory":"Construction",
            "type":"Services"
        }
    ],
    "sg:phone":"+1 614 449 9685",
    "sg:postcode":"43207",
    "sg:province":"OH",
    "sg:tags":[
        "housing"
    ],
    "wof:name":"Robert J and Linda C Kirk Jr",
    "wof:placetype":"venue"
},
  "geometry": {"coordinates":[-82.985824,39.923848],"type":"Point"}
}