{
  "type": "Feature",
  "properties": {
    "addr:full": "463 Garden Valley Ct Youngstown OH 44512",
    "addr:housenumber": "463",
    "addr:postcode": "44512",
    "addr:street": "Garden Valley Ct",
    "iso:country": "US",
    "sg:address": "463 Garden Valley Ct",
    "sg:city": "Youngstown",
    "sg:classifiers": [
      {
        "category": "Personal",
        "subcategory": "Beauty Salon",
        "type": "Services"
      }
    ],
    "sg:phone": "+1 330 758 3175",
    "sg:postcode": "44512",
    "sg:province": "OH",
    "wof:name": "Patty Beauty Salon",
    "wof:placetype": "venue"
  },
  "geometry": {"coordinates":[-80.675222,40.99632],"type":"Point"}
}
