{
  "type": "Feature",
  "properties": {
    "iso:country":"US",
    "sg:address":"463 Garden Valley Ct",
    "sg:city":"Youngstown",
    "sg:classifiers":[
        {
            "category":"Personal",
            "subcategory":"Beauty Salon",
            "type":"Services"
        }
    ],
    "sg:phone":"+1 330 758 3175",
    "sg:postcode":"44512",
    "sg:province":"OH",
    "wof:name":"Patty Beauty Salon",
    "wof:placetype":"venue"
},
  "geometry": {"coordinates":[-80.67522200000001,40.99632],"type":"Point"}
}