{
  "type": "Feature",
  "properties": {
    "addr:full": "2171 Arms Dr Girard OH 44420",
    "addr:housenumber": "2171",
    "addr:postcode": "44420",
    "addr:street": "Arms Dr",
    "iso:country": "US",
    "sg:address": "2171 Arms Dr",
    "sg:city": "Girard",
    "sg:classifiers": [
      {
        "category": "Food \u0026 Beverages",
        "subcategory": "Groceries \u0026 Convenience Stores",
        "type": "Retail Goods"
      }
    ],
    "sg:phone": "+1 330 759 3288",
    "sg:postcode": "44420",
    "sg:province": "OH",
    "wof:name": "Shaklee Food Suplements",
    "wof:placetype": "venue"
  },
  "geometry": {"coordinates":[-80.640746,41.176304],"type":"Point"}
}
