{
  "type": "Feature",
  "properties": {
    "addr:full":"215 S Chestnut St Jefferson OH 44047",
    "addr:housenumber":"215",
    "addr:postcode":"44047",
    "addr:street":"S Chestnut St",
    "iso:country":"US",
    "sg:address":"215 S Chestnut St",
    "sg:city":"Jefferson",
    "sg:classifiers":[
        {
            "category":"Real Estate",
            "subcategory":"Architect",
            "type":"Services"
        }
    ],
    "sg:phone":"+1 440 576 4588",
    "sg:postcode":"44047",
    "sg:province":"OH",
    "wof:name":"Beverly J Cowles",
    "wof:placetype":"venue"
},
  "geometry": {"coordinates":[-80.76952799999999,41.73395],"type":"Point"}
}