{
  "type": "Feature",
  "properties": {
    "addr:full": "16903 Fischer Rd Lakewood OH 44107",
    "addr:housenumber": "16903",
    "addr:postcode": "44107",
    "addr:street": "Fischer Rd",
    "iso:country": "US",
    "sg:address": "16903 Fischer Rd",
    "sg:city": "Lakewood",
    "sg:classifiers": [
      {
        "category": "Wholesale",
        "subcategory": "Drugs",
        "type": "Manufacturing \u0026 Wholesale Goods"
      }
    ],
    "sg:phone": "+1 216 226 5024",
    "sg:postcode": "44107",
    "sg:province": "OH",
    "sg:tags": [
      "personal",
      "product",
      "soap",
      "related",
      "care"
    ],
    "wof:name": "Simply Splashing",
    "wof:placetype": "venue"
  },
  "geometry": {"coordinates":[-81.814731,41.467963],"type":"Point"}
}
