{
  "type": "Feature",
  "properties": {
    "iso:country":"US",
    "sg:address":"2476 N Turkeyfoot Rd",
    "sg:city":"Akron",
    "sg:classifiers":[
        {
            "category":"Home & Garden",
            "subcategory":"Household Appliances",
            "type":"Retail Goods"
        },
        {
            "category":"Building & Trades",
            "subcategory":"Construction",
            "type":"Services"
        },
        {
            "category":"Utilities",
            "type":"Services"
        }
    ],
    "sg:phone":"+1 330 644 7811",
    "sg:postcode":"44319",
    "sg:province":"OH",
    "sg:tags":[
        "system",
        "specialty",
        "pump",
        "heating",
        "geothermal",
        "contractor",
        "cooling",
        "heat",
        "air conditioning"
    ],
    "sg:website":"http://www.LakesHtg.com",
    "wof:name":"Lakes Heating & Air Conditioning",
    "wof:placetype":"venue"
},
  "geometry": {"coordinates":[-81.527086,41.020942],"type":"Point"}
}