{
  "type": "Feature",
  "properties": {
    "addr:full":"5346 Twp Rd 55 Bellefontaine OH 43311",
    "addr:housenumber":"5346;55",
    "addr:postcode":"43311",
    "addr:street":"Twp Rd",
    "iso:country":"US",
    "sg:address":"5346 Twp Rd 55",
    "sg:city":"Bellefontaine",
    "sg:classifiers":[
        {
            "category":"Professional",
            "subcategory":"Lawyer & Legal Services",
            "type":"Services"
        }
    ],
    "sg:phone":"+1 937 592 2827",
    "sg:postcode":"43311",
    "sg:province":"OH",
    "sg:tags":[
        "attorney"
    ],
    "wof:name":"Jeffery C Snapp",
    "wof:placetype":"venue"
},
  "geometry": {"coordinates":[-83.71589299999999,40.31255],"type":"Point"}
}