{
  "type": "Feature",
  "properties": {
    "addr:full": "4925 State Rte 93 New Lexington OH 43764",
    "addr:housenumber": "4925",
    "addr:postcode": "43764",
    "addr:street": "State Rte 93",
    "iso:country": "US",
    "sg:address": "4925 State Rte 93",
    "sg:city": "New Lexington",
    "sg:classifiers": [
      {
        "category": "Manufacturing",
        "subcategory": "Metals",
        "type": "Manufacturing \u0026 Wholesale Goods"
      }
    ],
    "sg:phone": "+1 740 342 3036",
    "sg:postcode": "43764",
    "sg:province": "OH",
    "sg:tags": [
      "tool",
      "mfg"
    ],
    "wof:name": "Stephen D \u0026 Karen L Detri",
    "wof:placetype": "venue"
  },
  "geometry": {"coordinates":[-82.228137,39.645945],"type":"Point"}
}
