{
  "type": "Feature",
  "properties": {
    "addr:full": "508 W 6th Ave Lancaster OH 43130",
    "addr:housenumber": "508",
    "addr:postcode": "43130",
    "addr:street": "W 6Th Ave",
    "iso:country": "US",
    "sg:address": "508 W 6th Ave",
    "sg:city": "Lancaster",
    "sg:classifiers": [
      {
        "category": "Wholesale",
        "subcategory": "Office Equipment",
        "type": "Manufacturing \u0026 Wholesale Goods"
      }
    ],
    "sg:phone": "+1 740 654 6699",
    "sg:postcode": "43130",
    "sg:province": "OH",
    "sg:tags": [
      "calculator",
      "paper",
      "cash",
      "product",
      "register"
    ],
    "wof:name": "Fairfield Cash Register",
    "wof:placetype": "venue"
  },
  "geometry": {"coordinates":[-82.610294,39.720132],"type":"Point"}
}
