{
  "type": "Feature",
  "properties": {
    "addr:full": "4500 Baker St SE Canton OH 44730",
    "addr:housenumber": "4500",
    "addr:postcode": "44730",
    "addr:street": "Baker St Se",
    "iso:country": "US",
    "sg:address": "4500 Baker St SE",
    "sg:city": "Canton",
    "sg:classifiers": [
      {
        "category": "Insurance",
        "subcategory": "Insurance Agent",
        "type": "Services"
      }
    ],
    "sg:phone": "+1 330 488 6259",
    "sg:postcode": "44730",
    "sg:province": "OH",
    "wof:name": "Don Motz Insurance",
    "wof:placetype": "venue"
  },
  "geometry": {"coordinates":[-81.312557,40.767287],"type":"Point"}
}
