{
  "type": "Feature",
  "properties": {
    "addr:full":"9840 Royalton Rd North Royalton OH 44133",
    "addr:postcode":"9840;44133",
    "addr:street":"Royalton Rd",
    "iso:country":"US",
    "sg:address":"9840 Royalton Rd",
    "sg:city":"North Royalton",
    "sg:classifiers":[
        {
            "category":"Manufacturing",
            "subcategory":"Metals",
            "type":"Manufacturing & Wholesale Goods"
        }
    ],
    "sg:phone":"+1 440 582 8515",
    "sg:postcode":"44133",
    "sg:province":"OH",
    "sg:tags":[
        "product",
        "fabricated",
        "mfg"
    ],
    "wof:name":"Ziegler Engineering Inc",
    "wof:placetype":"venue"
},
  "geometry": {"coordinates":[-81.756299,41.31288],"type":"Point"}
}