{
  "type": "Feature",
  "properties": {
    "iso:country":"US",
    "sg:address":"3102 Tuscarawas St W",
    "sg:city":"Canton",
    "sg:classifiers":[
        {
            "category":"Restaurant",
            "type":"Food & Drink"
        }
    ],
    "sg:phone":"+1 330 454 8200",
    "sg:postcode":"44708",
    "sg:province":"OH",
    "sg:tags":[
        "pizzeria"
    ],
    "wof:name":"Italos Pizza Inc",
    "wof:placetype":"venue"
},
  "geometry": {"coordinates":[-81.41066499999999,40.798139],"type":"Point"}
}