{
  "type": "Feature",
  "properties": {
    "addr:full": "3102 Tuscarawas St W Canton OH 44708",
    "addr:housenumber": "3102",
    "addr:postcode": "44708",
    "addr:street": "Tuscarawas St W",
    "iso:country": "US",
    "sg:address": "3102 Tuscarawas St W",
    "sg:city": "Canton",
    "sg:classifiers": [
      {
        "category": "Restaurant",
        "type": "Food \u0026 Drink"
      }
    ],
    "sg:phone": "+1 330 454 8200",
    "sg:postcode": "44708",
    "sg:province": "OH",
    "sg:tags": [
      "pizzeria"
    ],
    "wof:name": "Italos Pizza Inc",
    "wof:placetype": "venue"
  },
  "geometry": {"coordinates":[-81.410665,40.798139],"type":"Point"}
}
