{
  "type": "Feature",
  "properties": {
    "addr:full": "1459 Greensburg Rd Uniontown OH 44685",
    "addr:housenumber": "1459",
    "addr:postcode": "44685",
    "addr:street": "Greensburg Rd",
    "iso:country": "US",
    "sg:address": "1459 Greensburg Rd",
    "sg:city": "Uniontown",
    "sg:classifiers": [
      {
        "category": "Professional",
        "type": "Services"
      }
    ],
    "sg:phone": "+1 330 896 9043",
    "sg:postcode": "44685",
    "sg:province": "OH",
    "wof:name": "Sean Jones",
    "wof:placetype": "venue"
  },
  "geometry": {"coordinates":[-81.486776,40.942904],"type":"Point"}
}
