{
  "type": "Feature",
  "properties": {
    "addr:full":"200 W Main St Cridersville OH 45806",
    "addr:housenumber":"200",
    "addr:postcode":"45806",
    "addr:street":"W Main St",
    "iso:country":"US",
    "sg:address":"200 W Main St",
    "sg:city":"Cridersville",
    "sg:classifiers":[
        {
            "category":"Shopping",
            "subcategory":"Pharmacy",
            "type":"Retail Goods"
        }
    ],
    "sg:phone":"+1 419 645 4009",
    "sg:postcode":"45806",
    "sg:province":"OH",
    "wof:name":"Village Pharmacy",
    "wof:placetype":"venue"
},
  "geometry": {"coordinates":[-84.145174,40.654205],"type":"Point"}
}