{
  "type": "Feature",
  "properties": {
    "addr:full": "1220 S 7th St Ironton OH 45638",
    "addr:housenumber": "1220",
    "addr:postcode": "45638",
    "addr:street": "S 7Th St",
    "iso:country": "US",
    "sg:address": "1220 S 7th St",
    "sg:city": "Ironton",
    "sg:classifiers": [
      {
        "category": "Personal",
        "subcategory": "Beauty Salon",
        "type": "Services"
      }
    ],
    "sg:phone": "+1 740 532 3775",
    "sg:postcode": "45638",
    "sg:province": "OH",
    "wof:name": "Today's Image",
    "wof:placetype": "venue"
  },
  "geometry": {"coordinates":[-82.673687,38.528054],"type":"Point"}
}
