{
  "type": "Feature",
  "properties": {
    "iso:country":"US",
    "sg:address":"25 S Front St",
    "sg:city":"Columbus",
    "sg:classifiers":[
        {
            "category":"Education",
            "subcategory":"Junior College",
            "type":"Public Place"
        },
        {
            "category":"Government",
            "subcategory":"Office",
            "type":"Public Place"
        }
    ],
    "sg:phone":"+1 614 466 2095",
    "sg:postcode":"43215",
    "sg:province":"OH",
    "sg:tags":[
        "technical",
        "institute",
        "department"
    ],
    "sg:website":"www.ode.state.oh.us",
    "wof:name":"Vocational & Career Education",
    "wof:placetype":"venue"
},
  "geometry": {"coordinates":[-83.00240599999999,39.962022],"type":"Point"}
}