{
  "type": "Feature",
  "properties": {
    "addr:full": "252 S Belmont Ave Springfield OH 45505",
    "addr:housenumber": "252",
    "addr:postcode": "45505",
    "addr:street": "S Belmont Ave",
    "iso:country": "US",
    "sg:address": "252 S Belmont Ave",
    "sg:city": "Springfield",
    "sg:classifiers": [
      {
        "category": "Freight",
        "type": "Transportation"
      }
    ],
    "sg:phone": "+1 937 324 8294",
    "sg:postcode": "45505",
    "sg:province": "OH",
    "sg:tags": [
      "operator",
      "local",
      "trucking"
    ],
    "wof:name": "Ferrell Trucking",
    "wof:placetype": "venue"
  },
  "geometry": {"coordinates":[-83.779944,39.919716],"type":"Point"}
}
