{
  "type": "Feature",
  "properties": {
    "addr:full":"2521 Starr Ave Oregon OH 43616",
    "addr:housenumber":"2521",
    "addr:postcode":"43616",
    "addr:street":"Starr Ave",
    "iso:country":"US",
    "sg:address":"2521 Starr Ave",
    "sg:city":"Oregon",
    "sg:classifiers":[
        {
            "category":"Food & Beverages",
            "subcategory":"Meat & Fish",
            "type":"Retail Goods"
        }
    ],
    "sg:phone":"+1 419 698 2731",
    "sg:postcode":"43616",
    "sg:province":"OH",
    "wof:name":"House Of Meats",
    "wof:placetype":"venue"
},
  "geometry": {"coordinates":[-83.487461,41.644023],"type":"Point"}
}