{
  "type": "Feature",
  "properties": {
    "addr:full": "1005 W Main St Kent OH 44240",
    "addr:housenumber": "1005",
    "addr:postcode": "44240",
    "addr:street": "W Main St",
    "iso:country": "US",
    "sg:address": "1005 W Main St",
    "sg:city": "Kent",
    "sg:classifiers": [
      {
        "category": "Retail",
        "subcategory": "Auto Repair",
        "type": "Services"
      }
    ],
    "sg:phone": "+1 330 678 9095",
    "sg:postcode": "44240",
    "sg:province": "OH",
    "sg:tags": [
      "repairing",
      "automobile"
    ],
    "wof:name": "AWTI Transmissions",
    "wof:placetype": "venue"
  },
  "geometry": {"coordinates":[-81.380447,41.151571],"type":"Point"}
}
