{
  "type": "Feature",
  "properties": {
    "addr:full": "804 Steel Dr Valley City OH 44280",
    "addr:housenumber": "804",
    "addr:postcode": "44280",
    "addr:street": "Steel Dr",
    "iso:country": "US",
    "sg:address": "804 Steel Dr",
    "sg:city": "Valley City",
    "sg:classifiers": [
      {
        "category": "Professional",
        "subcategory": "Business Services",
        "type": "Services"
      }
    ],
    "sg:phone": "+1 330 225 3388",
    "sg:postcode": "44280",
    "sg:province": "OH",
    "sg:tags": [
      "company",
      "holding"
    ],
    "wof:name": "Pj Steel L L C",
    "wof:placetype": "venue"
  },
  "geometry": {"coordinates":[-81.888028,41.252999],"type":"Point"}
}
