{
  "type": "Feature",
  "properties": {
    "iso:country":"US",
    "sg:address":"334 N Chestnut St",
    "sg:city":"Ravenna",
    "sg:classifiers":[
        {
            "category":"Building & Trades",
            "subcategory":"Construction",
            "type":"Services"
        }
    ],
    "sg:phone":"+1 330 296 7236",
    "sg:postcode":"44266",
    "sg:province":"OH",
    "sg:tags":[
        "contractor"
    ],
    "wof:name":"Pantalone Roofing",
    "wof:placetype":"venue"
},
  "geometry": {"coordinates":[-81.24283200000001,41.161117],"type":"Point"}
}