{
  "type": "Feature",
  "properties": {
    "addr:full": "334 N Chestnut St Ravenna OH 44266",
    "addr:housenumber": "334",
    "addr:postcode": "44266",
    "addr:street": "N Chestnut St",
    "iso:country": "US",
    "sg:address": "334 N Chestnut St",
    "sg:city": "Ravenna",
    "sg:classifiers": [
      {
        "category": "Building \u0026 Trades",
        "subcategory": "Construction",
        "type": "Services"
      }
    ],
    "sg:phone": "+1 330 296 7236",
    "sg:postcode": "44266",
    "sg:province": "OH",
    "sg:tags": [
      "contractor"
    ],
    "wof:name": "Pantalone Roofing",
    "wof:placetype": "venue"
  },
  "geometry": {"coordinates":[-81.242832,41.161117],"type":"Point"}
}
