{
  "type": "Feature",
  "properties": {
    "iso:country":"US",
    "sg:address":"11896 Coal Bank Rd",
    "sg:city":"Doylestown",
    "sg:classifiers":[
        {
            "category":"Real Estate",
            "subcategory":"Real Estate Operator",
            "type":"Services"
        }
    ],
    "sg:phone":"+1 330 658 6464",
    "sg:postcode":"44230",
    "sg:province":"OH",
    "sg:tags":[
        "building",
        "nonresidential"
    ],
    "wof:name":"Galehouse Family Ltd",
    "wof:placetype":"venue"
},
  "geometry": {"coordinates":[-81.70005399999999,40.946076],"type":"Point"}
}