{
  "type": "Feature",
  "properties": {
    "iso:country":"US",
    "sg:address":"620 N Howard St",
    "sg:city":"Akron",
    "sg:classifiers":[
        {
            "category":"Wholesale",
            "subcategory":"Groceries",
            "type":"Manufacturing & Wholesale Goods"
        }
    ],
    "sg:phone":"+1 330 384 1954",
    "sg:postcode":"44310",
    "sg:province":"OH",
    "sg:tags":[
        "grocer"
    ],
    "wof:name":"MNJ Carry Out",
    "wof:placetype":"venue"
},
  "geometry": {"coordinates":[-81.515078,41.104123],"type":"Point"}
}