{
  "type": "Feature",
  "properties": {
    "addr:full": "4858 Meeker Upper Sandusky Rd Morral OH 43337",
    "addr:housenumber": "4858",
    "addr:postcode": "43337",
    "addr:street": "Meeker Upper Sandusky Rd",
    "iso:country": "US",
    "sg:address": "4858 Meeker Upper Sandusky Rd",
    "sg:city": "Morral",
    "sg:classifiers": [
      {
        "category": "Farming",
        "subcategory": "Livestock Farm",
        "type": "Manufacturing \u0026 Wholesale Goods"
      }
    ],
    "sg:phone": "+1 740 465 6136",
    "sg:postcode": "43337",
    "sg:province": "OH",
    "sg:tags": [
      "equine"
    ],
    "wof:name": "Salt Rock Farm",
    "wof:placetype": "venue"
  },
  "geometry": {"coordinates":[-83.297079,40.676513],"type":"Point"}
}
