{
  "type": "Feature",
  "properties": {
    "addr:full": "224 7th St SW New Philadelphia OH 44663",
    "addr:housenumber": "224",
    "addr:postcode": "44663",
    "addr:street": "7Th St Sw",
    "iso:country": "US",
    "sg:address": "224 7th St SW",
    "sg:city": "New Philadelphia",
    "sg:classifiers": [
      {
        "category": "Building \u0026 Trades",
        "subcategory": "Cleaning \u0026 Sanitation",
        "type": "Services"
      }
    ],
    "sg:phone": "+1 330 339 1611",
    "sg:postcode": "44663",
    "sg:province": "OH",
    "sg:tags": [
      "janitor"
    ],
    "wof:name": "E \u0026 J Window \u0026 Floor Cleaning",
    "wof:placetype": "venue"
  },
  "geometry": {"coordinates":[-81.459288,40.48988],"type":"Point"}
}
