{
  "type": "Feature",
  "properties": {
    "iso:country":"US",
    "sg:address":"224 7th St SW",
    "sg:city":"New Philadelphia",
    "sg:classifiers":[
        {
            "category":"Building & Trades",
            "subcategory":"Cleaning & Sanitation",
            "type":"Services"
        }
    ],
    "sg:phone":"+1 330 339 1611",
    "sg:postcode":"44663",
    "sg:province":"OH",
    "sg:tags":[
        "janitor"
    ],
    "wof:name":"E & J Window & Floor Cleaning",
    "wof:placetype":"venue"
},
  "geometry": {"coordinates":[-81.459288,40.48988],"type":"Point"}
}