{
  "type": "Feature",
  "properties": {
    "addr:full":"7203 Newark Rd Mt Vernon OH 43050",
    "addr:housenumber":"7203",
    "addr:postcode":"43050",
    "addr:street":"Newark Rd",
    "iso:country":"US",
    "sg:address":"7203 Newark Rd",
    "sg:city":"Mt Vernon",
    "sg:classifiers":[
        {
            "category":"Freight",
            "type":"Transportation"
        }
    ],
    "sg:phone":"+1 740 392 2445",
    "sg:postcode":"43050",
    "sg:province":"OH",
    "sg:tags":[
        "trucking"
    ],
    "wof:name":"Richard Wolfe Trucking Inc",
    "wof:placetype":"venue"
},
  "geometry": {"coordinates":[-82.46566,40.339974],"type":"Point"}
}