{
  "type": "Feature",
  "properties": {
    "addr:full": "7185 Schradin Rd Okeana IN 45053",
    "addr:housenumber": "7185",
    "addr:postcode": "45053",
    "addr:street": "Schradin Rd",
    "iso:country": "US",
    "sg:address": "7185 Schradin Rd",
    "sg:city": "Okeana",
    "sg:classifiers": [
      {
        "category": "Building \u0026 Trades",
        "subcategory": "Construction",
        "type": "Services"
      }
    ],
    "sg:phone": "+1 513 738 1829",
    "sg:postcode": "45053",
    "sg:province": "IN",
    "sg:tags": [
      "excavating",
      "contractor"
    ],
    "wof:name": "Howard Mallory \u0026 Son Excavtg",
    "wof:placetype": "venue"
  },
  "geometry": {"coordinates":[-84.789481,39.330072],"type":"Point"}
}
