{
  "type": "Feature",
  "properties": {
    "iso:country":"US",
    "sg:address":"7185 Schradin Rd",
    "sg:city":"Okeana",
    "sg:classifiers":[
        {
            "category":"Building & Trades",
            "subcategory":"Construction",
            "type":"Services"
        }
    ],
    "sg:phone":"+1 513 738 1829",
    "sg:postcode":"45053",
    "sg:province":"IN",
    "sg:tags":[
        "excavating",
        "contractor"
    ],
    "wof:name":"Howard Mallory & Son Excavtg",
    "wof:placetype":"venue"
},
  "geometry": {"coordinates":[-84.789481,39.330072],"type":"Point"}
}