{
  "type": "Feature",
  "properties": {
    "iso:country":"US",
    "sg:address":"525 N Vandemark Rd",
    "sg:city":"Sidney",
    "sg:classifiers":[
        {
            "category":"Utilities",
            "subcategory":"Mobile Phone",
            "type":"Services"
        }
    ],
    "sg:phone":"+1 937 498 4030",
    "sg:postcode":"45365",
    "sg:province":"OH",
    "sg:tags":[
        "telephone",
        "cellular"
    ],
    "sg:website":"www.atplusllc.com",
    "wof:name":"A T Plus LLC",
    "wof:placetype":"venue"
},
  "geometry": {"coordinates":[-84.18797000000001,40.290355],"type":"Point"}
}