{
  "type": "Feature",
  "properties": {
    "iso:country":"US",
    "sg:address":"14625 Woodworth Rd",
    "sg:city":"Cleveland",
    "sg:classifiers":[
        {
            "category":"Food & Beverages",
            "subcategory":"Groceries & Convenience Stores",
            "type":"Retail Goods"
        }
    ],
    "sg:phone":"+1 216 851 5684",
    "sg:postcode":"44112",
    "sg:province":"OH",
    "sg:tags":[
        "grocer"
    ],
    "wof:name":"Woodworth Food Market",
    "wof:placetype":"venue"
},
  "geometry": {"coordinates":[-81.57970899999999,41.545259],"type":"Point"}
}