{
  "type": "Feature",
  "properties": {
    "addr:full":"7819 Broadview Rd Cleveland OH 44131",
    "addr:housenumber":"7819",
    "addr:postcode":"44131",
    "addr:street":"Broadview Rd",
    "iso:country":"US",
    "sg:address":"7819 Broadview Rd",
    "sg:city":"Cleveland",
    "sg:classifiers":[
        {
            "category":"Health Services",
            "subcategory":"Hospital",
            "type":"Services"
        },
        {
            "category":"Social Services",
            "type":"Services"
        }
    ],
    "sg:phone":"+1 216 901 9900",
    "sg:postcode":"44131",
    "sg:province":"OH",
    "sg:tags":[
        "professional",
        "counselor",
        "mental"
    ],
    "wof:name":"Haven Counseling Svc Inc",
    "wof:placetype":"venue"
},
  "geometry": {"coordinates":[-81.68450799999999,41.351721],"type":"Point"}
}