{
  "type": "Feature",
  "properties": {
    "addr:full": "45 W Main St Westerville OH 43081",
    "addr:housenumber": "45",
    "addr:postcode": "43081",
    "addr:street": "W Main St",
    "iso:country": "US",
    "sg:address": "45 W Main St",
    "sg:city": "Westerville",
    "sg:classifiers": [
      {
        "category": "Arts \u0026 Performance",
        "subcategory": "Theater",
        "type": "Entertainment"
      }
    ],
    "sg:phone": "+1 614 890 5523",
    "sg:postcode": "43081",
    "sg:province": "OH",
    "sg:tags": [
      "group"
    ],
    "sg:website": "www.westervillesymphony.org",
    "wof:name": "Westerville Symphony",
    "wof:placetype": "venue"
  },
  "geometry": {"coordinates":[-82.934316,40.126295],"type":"Point"}
}
