{
  "type": "Feature",
  "properties": {
    "addr:full":"6353 Som Center Rd Solon OH 44139",
    "addr:housenumber":"6353",
    "addr:postcode":"44139",
    "addr:street":"Som Center Rd",
    "iso:country":"US",
    "sg:address":"6353 Som Center Rd",
    "sg:city":"Solon",
    "sg:classifiers":[
        {
            "category":"Bagels",
            "type":"Food & Drink"
        },
        {
            "category":"Coffee & Tea",
            "type":"Food & Drink"
        },
        {
            "category":"Food & Beverages",
            "subcategory":"Bakery",
            "type":"Retail Goods"
        },
        {
            "category":"Bakery",
            "type":"Food & Drink"
        },
        {
            "category":"Donuts",
            "type":"Food & Drink"
        }
    ],
    "sg:menulink":"http://www.allmenus.com/oh/solon/143971-dunkin-donuts/menu/",
    "sg:phone":"+1 440 349 3638",
    "sg:postcode":"44139",
    "sg:province":"OH",
    "sg:tags":[
        "coffee",
        "diner",
        "tea",
        "bakery",
        "bagel",
        "american",
        "pastry"
    ],
    "wof:name":"Dunkin' Donuts",
    "wof:placetype":"venue"
},
  "geometry": {"coordinates":[-81.43730499999999,41.386305],"type":"Point"}
}