{
  "type": "Feature",
  "properties": {
    "addr:full": "7864 Hamilton Ave Cincinnati OH 45231",
    "addr:housenumber": "7864",
    "addr:postcode": "45231",
    "addr:street": "Hamilton Ave",
    "iso:country": "US",
    "sg:address": "7864 Hamilton Ave",
    "sg:city": "Cincinnati",
    "sg:classifiers": [
      {
        "category": "Wholesale",
        "subcategory": "Medical Equipment \u0026 Supplies",
        "type": "Manufacturing \u0026 Wholesale Goods"
      },
      {
        "category": "Shopping",
        "subcategory": "Beauty \u0026 Cosmetics",
        "type": "Retail Goods"
      },
      {
        "category": "Food \u0026 Beverages",
        "subcategory": "Specialty",
        "type": "Retail Goods"
      },
      {
        "category": "Shopping",
        "subcategory": "Computers \u0026 Home Electronics",
        "type": "Retail Goods"
      },
      {
        "category": "Shopping",
        "subcategory": "Optical Goods",
        "type": "Retail Goods"
      },
      {
        "category": "Personal",
        "subcategory": "Skin Care",
        "type": "Services"
      },
      {
        "category": "Manufacturing",
        "subcategory": "Chemicals \u0026 Compounds",
        "type": "Manufacturing \u0026 Wholesale Goods"
      },
      {
        "category": "Retail",
        "subcategory": "Photofinishing",
        "type": "Services"
      },
      {
        "category": "Shopping",
        "subcategory": "Pharmacy",
        "type": "Retail Goods"
      },
      {
        "category": "Health Services",
        "subcategory": "Optometrist",
        "type": "Services"
      },
      {
        "category": "Food \u0026 Beverages",
        "subcategory": "Groceries \u0026 Convenience Stores",
        "type": "Retail Goods"
      }
    ],
    "sg:phone": "+1 513 931 4707",
    "sg:postcode": "45231",
    "sg:province": "OH",
    "sg:tags": [
      "pharmaceutical",
      "product",
      "photo",
      "wheelchair",
      "vitamin",
      "perfume",
      "lens",
      "supplement",
      "contact",
      "wellness",
      "finishing",
      "consumer"
    ],
    "sg:website": "http://www.walgreens.com/default.jsp?ec=iyp_yellowpages_trademark",
    "wof:name": "Walgreens Pharmacies",
    "wof:placetype": "venue"
  },
  "geometry": {"coordinates":[-84.547879,39.236382],"type":"Point"}
}
