{
  "type": "Feature",
  "properties": {
    "addr:full": "4610 Woodville Rd Northwood OH 43619",
    "addr:housenumber": "4610",
    "addr:postcode": "43619",
    "addr:street": "Woodville Rd",
    "iso:country": "US",
    "sg:address": "4610 Woodville Rd",
    "sg:city": "Northwood",
    "sg:classifiers": [
      {
        "category": "Insurance",
        "subcategory": "Insurance Agent",
        "type": "Services"
      }
    ],
    "sg:phone": "+1 419 697 7250",
    "sg:postcode": "43619",
    "sg:province": "OH",
    "wof:name": "Ron Plichta Insurance",
    "wof:placetype": "venue"
  },
  "geometry": {"coordinates":[-83.463293,41.601189],"type":"Point"}
}
