{
  "type": "Feature",
  "properties": {
    "iso:country":"US",
    "sg:address":"2306 Park Ave",
    "sg:city":"Cincinnati",
    "sg:classifiers":[
        {
            "category":"Professional",
            "subcategory":"Lawyer & Legal Services",
            "type":"Services"
        }
    ],
    "sg:phone":"+1 513 533 4567",
    "sg:postcode":"45206",
    "sg:province":"OH",
    "sg:tags":[
        "attorney"
    ],
    "wof:name":"Namanworth & Smith",
    "wof:placetype":"venue"
},
  "geometry": {"coordinates":[-84.48626400000001,39.12452],"type":"Point"}
}