{
  "type": "Feature",
  "properties": {
    "addr:full":"440 E 5th St Dayton OH 45402",
    "addr:housenumber":"440",
    "addr:postcode":"45402",
    "addr:street":"E 5Th St",
    "iso:country":"US",
    "sg:address":"440 E 5th St",
    "sg:city":"Dayton",
    "sg:classifiers":[
        {
            "category":"Shopping",
            "subcategory":"Used Merchandise",
            "type":"Retail Goods"
        }
    ],
    "sg:phone":"+1 937 228 2940",
    "sg:postcode":"45402",
    "sg:province":"OH",
    "wof:name":"Feathers Vintage Clothing",
    "wof:placetype":"venue"
},
  "geometry": {"coordinates":[-84.185546,39.757148],"type":"Point"}
}