{
  "type": "Feature",
  "properties": {
    "iso:country":"US",
    "sg:address":"23 Lisbon St",
    "sg:city":"Canfield",
    "sg:classifiers":[
        {
            "category":"Professional",
            "subcategory":"Business Services",
            "type":"Services"
        }
    ],
    "sg:phone":"+1 330 533 2955",
    "sg:postcode":"44406",
    "sg:province":"OH",
    "sg:tags":[
        "drafting"
    ],
    "wof:name":"Bender Engineering Co",
    "wof:placetype":"venue"
},
  "geometry": {"coordinates":[-80.761742,41.023154],"type":"Point"}
}