{
  "type": "Feature",
  "properties": {
    "iso:country":"US",
    "sg:address":"2569 Laurel Lindale Rd",
    "sg:city":"New Richmond",
    "sg:classifiers":[
        {
            "category":"Building & Trades",
            "subcategory":"Construction",
            "type":"Services"
        }
    ],
    "sg:phone":"+1 513 474 9147",
    "sg:postcode":"45157",
    "sg:province":"OH",
    "sg:tags":[
        "painter"
    ],
    "wof:name":"Maddux Paintg",
    "wof:placetype":"venue"
},
  "geometry": {"coordinates":[-84.255501,38.9547],"type":"Point"}
}