{
  "type": "Feature",
  "properties": {
    "addr:full": "5592 Broadview Rd Cleveland OH 44134",
    "addr:housenumber": "5592",
    "addr:postcode": "44134",
    "addr:street": "Broadview Rd",
    "iso:country": "US",
    "sg:address": "5592 Broadview Rd",
    "sg:city": "Cleveland",
    "sg:classifiers": [
      {
        "category": "Shopping",
        "subcategory": "Jewelry",
        "type": "Retail Goods"
      }
    ],
    "sg:phone": "+1 216 739 2290",
    "sg:postcode": "44134",
    "sg:province": "OH",
    "wof:name": "Van Scoy Hair Clinic Inc",
    "wof:placetype": "venue"
  },
  "geometry": {"coordinates":[-81.692556,41.409827],"type":"Point"}
}
