{
  "type": "Feature",
  "properties": {
    "iso:country":"US",
    "sg:address":"8231 E Carlton Rd",
    "sg:city":"West Alexandria",
    "sg:classifiers":[
        {
            "category":"Professional",
            "type":"Services"
        }
    ],
    "sg:phone":"+1 937 787 4445",
    "sg:postcode":"45381",
    "sg:province":"OH",
    "wof:name":"Gary Lewis",
    "wof:placetype":"venue"
},
  "geometry": {"coordinates":[-84.483064,39.678997],"type":"Point"}
}