{
  "type": "Feature",
  "properties": {
    "iso:country":"US",
    "sg:address":"2790 S Range Line Rd",
    "sg:city":"Ludlow Falls",
    "sg:classifiers":[
        {
            "category":"Building & Trades",
            "subcategory":"Construction",
            "type":"Services"
        }
    ],
    "sg:phone":"+1 937 698 6798",
    "sg:postcode":"45339",
    "sg:province":"OH",
    "sg:tags":[
        "residential"
    ],
    "wof:name":"S W Residential Reconstruction",
    "wof:placetype":"venue"
},
  "geometry": {"coordinates":[-84.371188,39.999387],"type":"Point"}
}