{
  "type": "Feature",
  "properties": {
    "iso:country":"US",
    "sg:address":"48 Westview Ave",
    "sg:city":"Columbus",
    "sg:classifiers":[
        {
            "category":"Shopping",
            "type":"Retail Goods"
        }
    ],
    "sg:phone":"+1 614 909 9678",
    "sg:postcode":"43214",
    "sg:province":"OH",
    "sg:tags":[
        "cosmetic",
        "perfume"
    ],
    "wof:name":"Barnum Beauty Supply",
    "wof:placetype":"venue"
},
  "geometry": {"coordinates":[-83.02100900000001,40.069729],"type":"Point"}
}