{
  "type": "Feature",
  "properties": {
    "addr:full":"4010 Blacksnake Hill Rd NE Dover OH 44622",
    "addr:housenumber":"4010",
    "addr:postcode":"44622",
    "addr:street":"Blacksnake Hill Rd Ne",
    "iso:country":"US",
    "sg:address":"4010 Blacksnake Hill Rd NE",
    "sg:city":"Dover",
    "sg:classifiers":[
        {
            "category":"Real Estate",
            "subcategory":"Real Estate Agent",
            "type":"Services"
        }
    ],
    "sg:phone":"+1 330 364 5588",
    "sg:postcode":"44622",
    "sg:province":"OH",
    "wof:name":"Miller Kahl Appraisels",
    "wof:placetype":"venue"
},
  "geometry": {"coordinates":[-81.454099,40.548299],"type":"Point"}
}