{
  "type": "Feature",
  "properties": {
    "addr:full":"12512 Detroit Ave Cleveland OH 44107",
    "addr:housenumber":"12512",
    "addr:postcode":"44107",
    "addr:street":"Detroit Ave",
    "iso:country":"US",
    "sg:address":"12512 Detroit Ave",
    "sg:city":"Cleveland",
    "sg:classifiers":[
        {
            "category":"Recreation",
            "type":"Entertainment"
        }
    ],
    "sg:phone":"+1 216 227 3835",
    "sg:postcode":"44107",
    "sg:province":"OH",
    "sg:tags":[
        "amusement"
    ],
    "wof:name":"Cyrano's Place",
    "wof:placetype":"venue"
},
  "geometry": {"coordinates":[-81.776246,41.484355],"type":"Point"}
}