{
  "type": "Feature",
  "properties": {
    "addr:full":"6761 Kellogg Rd Cincinnati OH 45230",
    "addr:housenumber":"6761",
    "addr:postcode":"45230",
    "addr:street":"Kellogg Rd",
    "iso:country":"US",
    "sg:address":"6761 Kellogg Rd",
    "sg:city":"Cincinnati",
    "sg:classifiers":[
        {
            "category":"Wholesale",
            "subcategory":"Farm Supplies",
            "type":"Manufacturing & Wholesale Goods"
        }
    ],
    "sg:phone":"+1 513 232 8981",
    "sg:postcode":"45230",
    "sg:province":"OH",
    "sg:tags":[
        "grain"
    ],
    "sg:website":"www.cargill.com",
    "wof:name":"Cargill Inc",
    "wof:placetype":"venue"
},
  "geometry": {"coordinates":[-84.393984,39.049674],"type":"Point"}
}