{
  "type": "Feature",
  "properties": {
    "addr:full":"504 E Dorothy Ln Dayton OH 45419",
    "addr:housenumber":"504",
    "addr:postcode":"45419",
    "addr:street":"E Dorothy Ln",
    "iso:country":"US",
    "sg:address":"504 E Dorothy Ln",
    "sg:city":"Dayton",
    "sg:classifiers":[
        {
            "category":"Professional",
            "subcategory":"Business Services",
            "type":"Services"
        }
    ],
    "sg:phone":"+1 937 293 2183",
    "sg:postcode":"45419",
    "sg:province":"OH",
    "sg:tags":[
        "interior",
        "consultant",
        "design",
        "decorator"
    ],
    "wof:name":"Perkins Perk",
    "wof:placetype":"venue"
},
  "geometry": {"coordinates":[-84.16108800000001,39.703973],"type":"Point"}
}