{
  "type": "Feature",
  "properties": {
    "addr:full": "1315 Old Springfield Rd Vandalia OH 45377",
    "addr:housenumber": "1315",
    "addr:postcode": "45377",
    "addr:street": "Old Springfield Rd",
    "iso:country": "US",
    "sg:address": "1315 Old Springfield Rd",
    "sg:city": "Vandalia",
    "sg:classifiers": [
      {
        "category": "Utilities",
        "subcategory": "Telephone",
        "type": "Services"
      }
    ],
    "sg:phone": "+1 937 898 5101",
    "sg:postcode": "45377",
    "sg:province": "OH",
    "sg:tags": [
      "communications"
    ],
    "wof:name": "Goad Enterprises",
    "wof:placetype": "venue"
  },
  "geometry": {"coordinates":[-84.264153,39.913407],"type":"Point"}
}
