{
  "type": "Feature",
  "properties": {
    "addr:full": "10678 Main St New Middletown OH 44490",
    "addr:housenumber": "10678",
    "addr:postcode": "44490",
    "addr:street": "Main St",
    "iso:country": "US",
    "sg:address": "10678 Main St",
    "sg:city": "New Middletown",
    "sg:classifiers": [
      {
        "category": "Building \u0026 Trades",
        "subcategory": "Construction",
        "type": "Services"
      }
    ],
    "sg:phone": "+1 330 542 3223",
    "sg:postcode": "44490",
    "sg:province": "OH",
    "sg:tags": [
      "excavating",
      "contractor"
    ],
    "wof:name": "Combs Excavating",
    "wof:placetype": "venue"
  },
  "geometry": {"coordinates":[-80.775088,40.900631],"type":"Point"}
}
