{
  "type": "Feature",
  "properties": {
    "addr:full": "144 Sherwood Ct Seville OH 44273",
    "addr:housenumber": "144",
    "addr:postcode": "44273",
    "addr:street": "Sherwood Ct",
    "iso:country": "US",
    "sg:address": "144 Sherwood Ct",
    "sg:city": "Seville",
    "sg:classifiers": [
      {
        "category": "Insurance",
        "subcategory": "Insurance Agent",
        "type": "Services"
      }
    ],
    "sg:phone": "+1 330 769 4548",
    "sg:postcode": "44273",
    "sg:province": "OH",
    "wof:name": "Primerica Financial Svc",
    "wof:placetype": "venue"
  },
  "geometry": {"coordinates":[-81.858688,41.0172],"type":"Point"}
}
