{
  "type": "Feature",
  "properties": {
    "addr:full": "6233 W Liberty St Hubbard OH 44425",
    "addr:housenumber": "6233",
    "addr:postcode": "44425",
    "addr:street": "W Liberty St",
    "iso:country": "US",
    "sg:address": "6233 W Liberty St",
    "sg:city": "Hubbard",
    "sg:classifiers": [
      {
        "category": "Recreation",
        "type": "Entertainment"
      }
    ],
    "sg:phone": "+1 330 534 9026",
    "sg:postcode": "44425",
    "sg:province": "OH",
    "sg:tags": [
      "club",
      "course",
      "golf"
    ],
    "wof:name": "Pine Lakes Golf Club Limited",
    "wof:placetype": "venue"
  },
  "geometry": {"coordinates":[-80.593837,41.156403],"type":"Point"}
}
