{
  "type": "Feature",
  "properties": {
    "iso:country":"US",
    "sg:address":"6233 W Liberty St",
    "sg:city":"Hubbard",
    "sg:classifiers":[
        {
            "category":"Recreation",
            "type":"Entertainment"
        }
    ],
    "sg:phone":"+1 330 534 9026",
    "sg:postcode":"44425",
    "sg:province":"OH",
    "sg:tags":[
        "club",
        "course",
        "golf"
    ],
    "wof:name":"Pine Lakes Golf Club Limited",
    "wof:placetype":"venue"
},
  "geometry": {"coordinates":[-80.59383699999999,41.156403],"type":"Point"}
}