{
  "type": "Feature",
  "properties": {
    "iso:country":"US",
    "sg:address":"3261 E 137th St",
    "sg:city":"Cleveland",
    "sg:classifiers":[
        {
            "category":"Personal",
            "subcategory":"Beauty Salon",
            "type":"Services"
        }
    ],
    "sg:phone":"+1 216 752 5668",
    "sg:postcode":"44120",
    "sg:province":"OH",
    "sg:tags":[
        "manicuring"
    ],
    "wof:name":"Lee's Nails Studio",
    "wof:placetype":"venue"
},
  "geometry": {"coordinates":[-81.587458,41.469105],"type":"Point"}
}