{
  "type": "Feature",
  "properties": {
    "iso:country":"US",
    "sg:address":"1603 Chase Ave",
    "sg:city":"Cincinnati",
    "sg:classifiers":[
        {
            "category":"Social Services",
            "type":"Services"
        }
    ],
    "sg:phone":"+1 513 541 7914",
    "sg:postcode":"45223",
    "sg:province":"OH",
    "sg:tags":[
        "youth",
        "organization",
        "center"
    ],
    "wof:name":"Citizens Committee On Youth",
    "wof:placetype":"venue"
},
  "geometry": {"coordinates":[-84.54051699999999,39.163271],"type":"Point"}
}