{
  "type": "Feature",
  "properties": {
    "addr:full": "3925 N Ridge Rd E Ashtabula OH 44004",
    "addr:housenumber": "3925",
    "addr:postcode": "44004",
    "addr:street": "N Ridge Rd E",
    "iso:country": "US",
    "sg:address": "3925 N Ridge Rd E",
    "sg:city": "Ashtabula",
    "sg:classifiers": [
      {
        "category": "Home \u0026 Garden",
        "subcategory": "Mobile Homes",
        "type": "Retail Goods"
      }
    ],
    "sg:phone": "+1 440 992 9524",
    "sg:postcode": "44004",
    "sg:province": "OH",
    "wof:name": "Mobile Acres Park \u0026 Sales",
    "wof:placetype": "venue"
  },
  "geometry": {"coordinates":[-80.741708,41.884174],"type":"Point"}
}
