{
  "type": "Feature",
  "properties": {
    "addr:full":"13177 Vega St SW Massillon OH 44647",
    "addr:housenumber":"13177",
    "addr:postcode":"44647",
    "addr:street":"Vega St Sw",
    "iso:country":"US",
    "sg:address":"13177 Vega St SW",
    "sg:city":"Massillon",
    "sg:classifiers":[
        {
            "category":"Freight",
            "type":"Transportation"
        }
    ],
    "sg:phone":"+1 330 830 8383",
    "sg:postcode":"44647",
    "sg:province":"OH",
    "sg:tags":[
        "special"
    ],
    "wof:name":"B & E Storage",
    "wof:placetype":"venue"
},
  "geometry": {"coordinates":[-81.60256,40.776049],"type":"Point"}
}