{
  "type": "Feature",
  "properties": {
    "addr:full":"12 N Crandon Ave Niles OH 44446",
    "addr:housenumber":"12",
    "addr:postcode":"44446",
    "addr:street":"N Crandon Ave",
    "iso:country":"US",
    "sg:address":"12 N Crandon Ave",
    "sg:city":"Niles",
    "sg:classifiers":[
        {
            "category":"Restaurant",
            "type":"Food & Drink"
        }
    ],
    "sg:phone":"+1 330 652 1522",
    "sg:postcode":"44446",
    "sg:province":"OH",
    "sg:tags":[
        "eating"
    ],
    "wof:name":"NYSL",
    "wof:placetype":"venue"
},
  "geometry": {"coordinates":[-80.74303,41.183568],"type":"Point"}
}