{
  "type": "Feature",
  "properties": {
    "addr:full":"1405 E 9th St Cleveland OH 44114",
    "addr:housenumber":"1405",
    "addr:postcode":"44114",
    "addr:street":"E 9Th St",
    "iso:country":"US",
    "sg:address":"1405 E 9th St",
    "sg:city":"Cleveland",
    "sg:classifiers":[
        {
            "category":"Restaurant",
            "type":"Food & Drink"
        }
    ],
    "sg:menulink":"http://www.allmenus.com/oh/cleveland/221038-captain-tonys-pizza/menu/",
    "sg:phone":"+1 216 781 8669",
    "sg:postcode":"44114",
    "sg:province":"OH",
    "sg:tags":[
        "american",
        "italian",
        "pizza"
    ],
    "wof:name":"Captain Tony's Pizza",
    "wof:placetype":"venue"
},
  "geometry": {"coordinates":[-81.68955800000001,41.503436],"type":"Point"}
}