{
  "type": "Feature",
  "properties": {
    "addr:full": "3973 S Schenley Ave Youngstown OH 44511",
    "addr:housenumber": "3973",
    "addr:postcode": "44511",
    "addr:street": "S Schenley Ave",
    "iso:country": "US",
    "sg:address": "3973 S Schenley Ave",
    "sg:city": "Youngstown",
    "sg:classifiers": [
      {
        "category": "Wholesale",
        "subcategory": "Meat",
        "type": "Manufacturing \u0026 Wholesale Goods"
      }
    ],
    "sg:phone": "+1 330 792 1033",
    "sg:postcode": "44511",
    "sg:province": "OH",
    "wof:name": "Sherwood Foods Distributors",
    "wof:placetype": "venue"
  },
  "geometry": {"coordinates":[-80.692912,41.05818],"type":"Point"}
}
