{
  "type": "Feature",
  "properties": {
    "iso:country":"US",
    "sg:address":"3973 S Schenley Ave",
    "sg:city":"Youngstown",
    "sg:classifiers":[
        {
            "category":"Wholesale",
            "subcategory":"Meat",
            "type":"Manufacturing & Wholesale Goods"
        }
    ],
    "sg:phone":"+1 330 792 1033",
    "sg:postcode":"44511",
    "sg:province":"OH",
    "wof:name":"Sherwood Foods Distributors",
    "wof:placetype":"venue"
},
  "geometry": {"coordinates":[-80.69291200000001,41.05818],"type":"Point"}
}