{
  "type": "Feature",
  "properties": {
    "iso:country":"US",
    "sg:address":"101 E Main St",
    "sg:city":"Eaton",
    "sg:classifiers":[
        {
            "category":"Government",
            "subcategory":"Office",
            "type":"Public Place"
        }
    ],
    "sg:phone":"+1 937 456 8140",
    "sg:postcode":"45320",
    "sg:province":"OH",
    "sg:tags":[
        "county",
        "taxation"
    ],
    "wof:name":"Preble County Treasurer",
    "wof:placetype":"venue"
},
  "geometry": {"coordinates":[-84.63475699999999,39.743956],"type":"Point"}
}