{
  "type": "Feature",
  "properties": {
    "addr:full": "101 E Main St Eaton OH 45320",
    "addr:housenumber": "101",
    "addr:postcode": "45320",
    "addr:street": "E Main St",
    "iso:country": "US",
    "sg:address": "101 E Main St",
    "sg:city": "Eaton",
    "sg:classifiers": [
      {
        "category": "Government",
        "subcategory": "Office",
        "type": "Public Place"
      }
    ],
    "sg:phone": "+1 937 456 8140",
    "sg:postcode": "45320",
    "sg:province": "OH",
    "sg:tags": [
      "county",
      "taxation"
    ],
    "wof:name": "Preble County Treasurer",
    "wof:placetype": "venue"
  },
  "geometry": {"coordinates":[-84.634757,39.743956],"type":"Point"}
}
