{
  "type": "Feature",
  "properties": {
    "iso:country":"US",
    "sg:address":"88 Center Rd",
    "sg:city":"Cleveland",
    "sg:classifiers":[
        {
            "category":"Health Services",
            "subcategory":"Doctor",
            "type":"Services"
        }
    ],
    "sg:phone":"+1 440 439 2230",
    "sg:postcode":"44146",
    "sg:province":"OH",
    "sg:tags":[
        "dentist"
    ],
    "wof:name":"Bedford Family Dentistry",
    "wof:placetype":"venue"
},
  "geometry": {"coordinates":[-81.536939,41.394711],"type":"Point"}
}