{
  "type": "Feature",
  "properties": {
    "addr:full": "18850 Bagley Rd Cleveland OH 44130",
    "addr:housenumber": "18850",
    "addr:postcode": "44130",
    "addr:street": "Bagley Rd",
    "iso:country": "US",
    "sg:address": "18850 Bagley Rd",
    "sg:city": "Cleveland",
    "sg:classifiers": [
      {
        "category": "Insurance",
        "subcategory": "Insurance Agent",
        "type": "Services"
      }
    ],
    "sg:phone": "+1 440 234 7116",
    "sg:postcode": "44130",
    "sg:province": "OH",
    "wof:name": "Staadecker \u0026 Associates",
    "wof:placetype": "venue"
  },
  "geometry": {"coordinates":[-81.832797,41.372154],"type":"Point"}
}
