{
  "type": "Feature",
  "properties": {
    "addr:full":"6414 Thoreau Cleveland OH 44129",
    "addr:housenumber":"6414",
    "addr:postcode":"44129",
    "addr:street":"Thoreau Cleveland",
    "iso:country":"US",
    "sg:address":"6414 Thoreau",
    "sg:city":"Cleveland",
    "sg:classifiers":[
        {
            "category":"Building & Trades",
            "subcategory":"Plumbing",
            "type":"Services"
        }
    ],
    "sg:phone":"+1 440 885 0800",
    "sg:postcode":"44129",
    "sg:province":"OH",
    "sg:tags":[
        "plumbing",
        "contractor"
    ],
    "wof:name":"Ridge Plumbing Inc",
    "wof:placetype":"venue"
},
  "geometry": {"coordinates":[-81.73139999999999,41.370472],"type":"Point"}
}