{
  "type": "Feature",
  "properties": {
    "addr:full":"549 Tohatchi Dr Cincinnati OH 45215",
    "addr:housenumber":"549",
    "addr:postcode":"45215",
    "addr:street":"Tohatchi Dr",
    "iso:country":"US",
    "sg:address":"549 Tohatchi Dr",
    "sg:city":"Cincinnati",
    "sg:classifiers":[
        {
            "category":"Health Services",
            "subcategory":"Health Practitioner",
            "type":"Services"
        }
    ],
    "sg:phone":"+1 513 522 1403",
    "sg:postcode":"45215",
    "sg:province":"OH",
    "sg:tags":[
        "nutritionist"
    ],
    "wof:name":"Shirley Eckvall",
    "wof:placetype":"venue"
},
  "geometry": {"coordinates":[-84.49673300000001,39.228944],"type":"Point"}
}