{
  "type": "Feature",
  "properties": {
    "addr:full":"27500 Cedar Rd Cleveland OH 44122",
    "addr:housenumber":"27500",
    "addr:postcode":"44122",
    "addr:street":"Cedar Rd",
    "iso:country":"US",
    "sg:address":"27500 Cedar Rd",
    "sg:city":"Cleveland",
    "sg:classifiers":[
        {
            "category":"Professional",
            "type":"Services"
        }
    ],
    "sg:phone":"+1 216 464 8832",
    "sg:postcode":"44122",
    "sg:province":"OH",
    "wof:name":"Marvin & Sandra Drucker",
    "wof:placetype":"venue"
},
  "geometry": {"coordinates":[-81.485992,41.501109],"type":"Point"}
}