{
  "type": "Feature",
  "properties": {
    "addr:full": "2812 State Rte 529 Cardington OH 43315",
    "addr:housenumber": "2812",
    "addr:postcode": "43315",
    "addr:street": "State Rte 529",
    "iso:country": "US",
    "sg:address": "2812 State Rte 529",
    "sg:city": "Cardington",
    "sg:classifiers": [
      {
        "category": "Recreation",
        "type": "Entertainment"
      }
    ],
    "sg:phone": "+1 419 864 3816",
    "sg:postcode": "43315",
    "sg:province": "OH",
    "sg:tags": [
      "pool",
      "swimming"
    ],
    "wof:name": "Cardington Swimming Pool",
    "wof:placetype": "venue"
  },
  "geometry": {"coordinates":[-82.880403,40.49515],"type":"Point"}
}
