{
  "type": "Feature",
  "properties": {
    "addr:full": "4416 Plymouth Rock Ct Columbus OH 43230",
    "addr:housenumber": "4416",
    "addr:postcode": "43230",
    "addr:street": "Plymouth Rock Ct",
    "iso:country": "US",
    "sg:address": "4416 Plymouth Rock Ct",
    "sg:city": "Columbus",
    "sg:classifiers": [
      {
        "category": "Real Estate",
        "subcategory": "Real Estate Services",
        "type": "Services"
      }
    ],
    "sg:phone": "+1 614 498 1280",
    "sg:postcode": "43230",
    "sg:province": "OH",
    "sg:tags": [
      "company",
      "title"
    ],
    "wof:name": "Fidelity Title Svc",
    "wof:placetype": "venue"
  },
  "geometry": {"coordinates":[-82.884581,40.064546],"type":"Point"}
}
