{
  "type": "Feature",
  "properties": {
    "addr:full": "2330 8th St SW Akron OH 44314",
    "addr:housenumber": "2330",
    "addr:postcode": "44314",
    "addr:street": "8Th St Sw",
    "iso:country": "US",
    "sg:address": "2330 8th St SW",
    "sg:city": "Akron",
    "sg:classifiers": [
      {
        "category": "Shopping",
        "type": "Retail Goods"
      }
    ],
    "sg:phone": "+1 330 922 4590",
    "sg:postcode": "44314",
    "sg:province": "OH",
    "sg:tags": [
      "candle"
    ],
    "wof:name": "Sisters Scented Candles",
    "wof:placetype": "venue"
  },
  "geometry": {"coordinates":[-81.552435,41.041711],"type":"Point"}
}
