{
  "type": "Feature",
  "properties": {
    "iso:country":"US",
    "sg:address":"921 Robinwood Ave",
    "sg:city":"Columbus",
    "sg:classifiers":[
        {
            "category":"Building & Trades",
            "subcategory":"Cleaning & Sanitation",
            "type":"Services"
        }
    ],
    "sg:phone":"+1 614 231 8974",
    "sg:postcode":"43213",
    "sg:province":"OH",
    "sg:tags":[
        "janitor"
    ],
    "wof:name":"All City Cleaning Svc",
    "wof:placetype":"venue"
},
  "geometry": {"coordinates":[-82.897104,39.953989],"type":"Point"}
}