{
  "type": "Feature",
  "properties": {
    "iso:country":"US",
    "sg:address":"2257 Atlee Ct",
    "sg:city":"Columbus",
    "sg:classifiers":[
        {
            "category":"Professional",
            "subcategory":"Lawyer & Legal Services",
            "type":"Services"
        }
    ],
    "sg:phone":"+1 614 459 4840",
    "sg:postcode":"43220",
    "sg:province":"OH",
    "sg:tags":[
        "attorney"
    ],
    "wof:name":"Michael & Michael",
    "wof:placetype":"venue"
},
  "geometry": {"coordinates":[-83.08071700000001,40.05457],"type":"Point"}
}