{
  "type": "Feature",
  "properties": {
    "addr:full": "2257 Atlee Ct Columbus OH 43220",
    "addr:housenumber": "2257",
    "addr:postcode": "43220",
    "addr:street": "Atlee Ct",
    "iso:country": "US",
    "sg:address": "2257 Atlee Ct",
    "sg:city": "Columbus",
    "sg:classifiers": [
      {
        "category": "Professional",
        "subcategory": "Lawyer \u0026 Legal Services",
        "type": "Services"
      }
    ],
    "sg:phone": "+1 614 459 4840",
    "sg:postcode": "43220",
    "sg:province": "OH",
    "sg:tags": [
      "attorney"
    ],
    "wof:name": "Michael \u0026 Michael",
    "wof:placetype": "venue"
  },
  "geometry": {"coordinates":[-83.080717,40.05457],"type":"Point"}
}
