{
  "type": "Feature",
  "properties": {
    "addr:full":"6767 Edison St NE Hartville OH 44632",
    "addr:housenumber":"6767",
    "addr:postcode":"44632",
    "addr:street":"Edison St Ne",
    "iso:country":"US",
    "sg:address":"6767 Edison St NE",
    "sg:city":"Hartville",
    "sg:classifiers":[
        {
            "category":"Farming",
            "subcategory":"Farm",
            "type":"Manufacturing & Wholesale Goods"
        }
    ],
    "sg:phone":"+1 330 877 6520",
    "sg:postcode":"44632",
    "sg:province":"OH",
    "wof:name":"Moore's Farm",
    "wof:placetype":"venue"
},
  "geometry": {"coordinates":[-81.251397,40.952104],"type":"Point"}
}