{
  "type": "Feature",
  "properties": {
    "iso:country":"US",
    "sg:address":"171 N Bridge St",
    "sg:city":"Chillicothe",
    "sg:classifiers":[
        {
            "category":"Building & Trades",
            "subcategory":"Equipment Rental",
            "type":"Services"
        }
    ],
    "sg:phone":"+1 740 773 6429",
    "sg:postcode":"45601",
    "sg:province":"OH",
    "sg:tags":[
        "yard"
    ],
    "wof:name":"Phillips Rent All",
    "wof:placetype":"venue"
},
  "geometry": {"coordinates":[-82.975325,39.338836],"type":"Point"}
}