{
  "type": "Feature",
  "properties": {
    "iso:country":"US",
    "sg:address":"18074 Royalton Rd",
    "sg:city":"Cleveland",
    "sg:classifiers":[
        {
            "category":"Shopping",
            "subcategory":"Shoes",
            "type":"Retail Goods"
        }
    ],
    "sg:phone":"+1 440 268 0470",
    "sg:postcode":"44136",
    "sg:province":"OH",
    "wof:name":"Famous Footwear",
    "wof:placetype":"venue"
},
  "geometry": {"coordinates":[-81.83082400000001,41.314277],"type":"Point"}
}