{
  "type": "Feature",
  "properties": {
    "iso:country":"US",
    "sg:address":"1278 W 9th St",
    "sg:city":"Cleveland",
    "sg:classifiers":[
        {
            "category":"Real Estate",
            "subcategory":"Real Estate Operator",
            "type":"Services"
        }
    ],
    "sg:phone":"+1 216 579 4000",
    "sg:postcode":"44113",
    "sg:province":"OH",
    "sg:tags":[
        "apartment"
    ],
    "wof:name":"Bingham Burnside LLC",
    "wof:placetype":"venue"
},
  "geometry": {"coordinates":[-81.701505,41.500074],"type":"Point"}
}