{
  "type": "Feature",
  "properties": {
    "addr:full": "206 E Tulane Rd Columbus OH 43202",
    "addr:housenumber": "206",
    "addr:postcode": "43202",
    "addr:street": "E Tulane Rd",
    "iso:country": "US",
    "sg:address": "206 E Tulane Rd",
    "sg:city": "Columbus",
    "sg:classifiers": [
      {
        "category": "Food \u0026 Beverages",
        "subcategory": "Specialty",
        "type": "Retail Goods"
      }
    ],
    "sg:phone": "+1 614 263 8702",
    "sg:postcode": "43202",
    "sg:province": "OH",
    "sg:tags": [
      "vitamin"
    ],
    "wof:name": "Superior Line Co",
    "wof:placetype": "venue"
  },
  "geometry": {"coordinates":[-83.009525,40.023137],"type":"Point"}
}
