{
  "type": "Feature",
  "properties": {
    "addr:full":"9650 Lancaster-Newark Rd NE Baltimore OH 43105",
    "addr:housenumber":"9650",
    "addr:postcode":"43105",
    "addr:street":"Lancaster-Newark Rd Ne",
    "iso:country":"US",
    "sg:address":"9650 Lancaster-Newark Rd NE",
    "sg:city":"Baltimore",
    "sg:classifiers":[
        {
            "category":"Building & Trades",
            "subcategory":"Construction",
            "type":"Services"
        }
    ],
    "sg:phone":"+1 740 862 8512",
    "sg:postcode":"43105",
    "sg:province":"OH",
    "sg:tags":[
        "contractor"
    ],
    "wof:name":"Mercurio Builders",
    "wof:placetype":"venue"
},
  "geometry": {"coordinates":[-82.56679800000001,39.860397],"type":"Point"}
}