{
  "type": "Feature",
  "properties": {
    "addr:full":"54 Country Ln Columbus OH 43213",
    "addr:housenumber":"54",
    "addr:postcode":"43213",
    "addr:street":"Country Ln",
    "iso:country":"US",
    "sg:address":"54 Country Ln",
    "sg:city":"Columbus",
    "sg:classifiers":[
        {
            "category":"Government",
            "subcategory":"Office",
            "type":"Public Place"
        }
    ],
    "sg:phone":"+1 614 995 5353",
    "sg:postcode":"43213",
    "sg:province":"OH",
    "sg:tags":[
        "state",
        "program"
    ],
    "wof:name":"Drivers License Exam",
    "wof:placetype":"venue"
},
  "geometry": {"coordinates":[-82.89913300000001,39.974321],"type":"Point"}
}