{
  "type": "Feature",
  "properties": {
    "addr:full":"5231 Ash Dr West Liberty OH 43357",
    "addr:housenumber":"5231",
    "addr:postcode":"43357",
    "addr:street":"Ash Dr West",
    "iso:country":"US",
    "sg:address":"5231 Ash Dr",
    "sg:city":"West Liberty",
    "sg:classifiers":[
        {
            "category":"Building & Trades",
            "subcategory":"Construction",
            "type":"Services"
        }
    ],
    "sg:phone":"+1 937 465 0058",
    "sg:postcode":"43357",
    "sg:province":"OH",
    "sg:tags":[
        "carpentry",
        "contractor"
    ],
    "wof:name":"Commercial Installers",
    "wof:placetype":"venue"
},
  "geometry": {"coordinates":[-83.75531599999999,40.28606],"type":"Point"}
}