{
  "type": "Feature",
  "properties": {
    "addr:full":"8735 Factory Shops Blvd Jeffersonville OH 43128",
    "addr:housenumber":"8735",
    "addr:postcode":"43128",
    "addr:street":"Factory Shops Blvd",
    "iso:country":"US",
    "sg:address":"8735 Factory Shops Blvd",
    "sg:city":"Jeffersonville",
    "sg:classifiers":[
        {
            "category":"Shopping",
            "subcategory":"Shoes",
            "type":"Retail Goods"
        }
    ],
    "sg:phone":"+1 740 948 9701",
    "sg:postcode":"43128",
    "sg:province":"OH",
    "wof:name":"Saucony Factory Outlet Store",
    "wof:placetype":"venue"
},
  "geometry": {"coordinates":[-83.602011,39.617109],"type":"Point"}
}