{
  "type": "Feature",
  "properties": {
    "addr:full": "1548 Cederwood Dr Westlake OH 44145",
    "addr:housenumber": "1548",
    "addr:postcode": "44145",
    "addr:street": "Cederwood Dr",
    "iso:country": "US",
    "sg:address": "1548 Cederwood Dr",
    "sg:city": "Westlake",
    "sg:classifiers": [
      {
        "category": "Wholesale",
        "subcategory": "Non-durable Goods",
        "type": "Manufacturing \u0026 Wholesale Goods"
      }
    ],
    "sg:phone": "+1 440 871 8224",
    "sg:postcode": "44145",
    "sg:province": "OH",
    "wof:name": "Doubledown Distribution",
    "wof:placetype": "venue"
  },
  "geometry": {"coordinates":[-81.957354,41.467367],"type":"Point"}
}
