{
  "type": "Feature",
  "properties": {
    "iso:country":"US",
    "sg:address":"8358 Twp Hwy 94",
    "sg:city":"Thornville",
    "sg:classifiers":[
        {
            "category":"Shopping",
            "subcategory":"Clothing, Apparel, & Fashions",
            "type":"Retail Goods"
        }
    ],
    "sg:phone":"+1 740 246 4907",
    "sg:postcode":"43076",
    "sg:province":"OH",
    "wof:name":"Roadrunner Enterprises",
    "wof:placetype":"venue"
},
  "geometry": {"coordinates":[-82.398172,39.877592],"type":"Point"}
}