{
  "type": "Feature",
  "properties": {
    "iso:country":"US",
    "sg:address":"101 N Westminster St",
    "sg:city":"Waynesfield",
    "sg:classifiers":[
        {
            "category":"Restaurant",
            "type":"Food & Drink"
        }
    ],
    "sg:phone":"+1 419 568 7801",
    "sg:postcode":"45896",
    "sg:province":"OH",
    "sg:tags":[
        "pizza"
    ],
    "wof:name":"Tussing's Pizza",
    "wof:placetype":"venue"
},
  "geometry": {"coordinates":[-83.975387,40.601067],"type":"Point"}
}