{
  "type": "Feature",
  "properties": {
    "addr:full": "101 N Westminster St Waynesfield OH 45896",
    "addr:housenumber": "101",
    "addr:postcode": "45896",
    "addr:street": "N Westminster St",
    "iso:country": "US",
    "sg:address": "101 N Westminster St",
    "sg:city": "Waynesfield",
    "sg:classifiers": [
      {
        "category": "Restaurant",
        "type": "Food \u0026 Drink"
      }
    ],
    "sg:phone": "+1 419 568 7801",
    "sg:postcode": "45896",
    "sg:province": "OH",
    "sg:tags": [
      "pizza"
    ],
    "wof:name": "Tussing's Pizza",
    "wof:placetype": "venue"
  },
  "geometry": {"coordinates":[-83.975387,40.601067],"type":"Point"}
}
