{
  "type": "Feature",
  "properties": {
    "iso:country":"US",
    "sg:address":"18901 Euclid Ave",
    "sg:city":"Cleveland",
    "sg:classifiers":[
        {
            "category":"Wholesale",
            "subcategory":"Durable Goods & Equipment",
            "type":"Manufacturing & Wholesale Goods"
        }
    ],
    "sg:phone":"+1 216 486 2888",
    "sg:postcode":"44117",
    "sg:province":"OH",
    "sg:tags":[
        "importer"
    ],
    "sg:website":"www.leadcolighting.com",
    "wof:name":"Leadco Products Inc",
    "wof:placetype":"venue"
},
  "geometry": {"coordinates":[-81.546908,41.559225],"type":"Point"}
}