{
  "type": "Feature",
  "properties": {
    "addr:full":"7250 Brookpark Rd Cleveland OH 44129",
    "addr:housenumber":"7250",
    "addr:postcode":"44129",
    "addr:street":"Brookpark Rd",
    "iso:country":"US",
    "sg:address":"7250 Brookpark Rd",
    "sg:city":"Cleveland",
    "sg:classifiers":[
        {
            "category":"Autos & Motor Vehicles",
            "subcategory":"Fuel & Gas Station",
            "type":"Retail Goods"
        }
    ],
    "sg:phone":"+1 216 398 4445",
    "sg:postcode":"44129",
    "sg:province":"OH",
    "sg:tags":[
        "oil"
    ],
    "wof:name":"Super America",
    "wof:placetype":"venue"
},
  "geometry": {"coordinates":[-81.73032600000001,41.418769],"type":"Point"}
}