{
  "type": "Feature",
  "properties": {
    "iso:country":"US",
    "sg:address":"7250 Brookpark Rd",
    "sg:city":"Cleveland",
    "sg:classifiers":[
        {
            "category":"Autos & Motor Vehicles",
            "subcategory":"Fuel & Gas Station",
            "type":"Retail Goods"
        }
    ],
    "sg:phone":"+1 216 398 4445",
    "sg:postcode":"44129",
    "sg:province":"OH",
    "sg:tags":[
        "oil"
    ],
    "wof:name":"Super America",
    "wof:placetype":"venue"
},
  "geometry": {"coordinates":[-81.730326,41.418769],"type":"Point"}
}