{
  "type": "Feature",
  "properties": {
    "addr:full":"1091 Moneta Ave Aurora OH 44202",
    "addr:housenumber":"1091",
    "addr:postcode":"44202",
    "addr:street":"Moneta Ave",
    "iso:country":"US",
    "sg:address":"1091 Moneta Ave",
    "sg:city":"Aurora",
    "sg:classifiers":[
        {
            "category":"Building & Trades",
            "subcategory":"Construction",
            "type":"Services"
        }
    ],
    "sg:phone":"+1 330 562 9384",
    "sg:postcode":"44202",
    "sg:province":"OH",
    "sg:tags":[
        "home",
        "contractor",
        "remodeling",
        "family",
        "improvement"
    ],
    "wof:name":"Tripp Home Complete Inc",
    "wof:placetype":"venue"
},
  "geometry": {"coordinates":[-81.3844,41.346668],"type":"Point"}
}