{
  "type": "Feature",
  "properties": {
    "iso:country":"US",
    "sg:address":"6280 Garber Rd",
    "sg:city":"Dayton",
    "sg:classifiers":[
        {
            "category":"Freight",
            "type":"Transportation"
        }
    ],
    "sg:phone":"+1 937 890 3167",
    "sg:postcode":"45415",
    "sg:province":"OH",
    "sg:tags":[
        "operator",
        "local",
        "trucking"
    ],
    "wof:name":"Lloyds Inc",
    "wof:placetype":"venue"
},
  "geometry": {"coordinates":[-84.273128,39.833623],"type":"Point"}
}