{
  "type": "Feature",
  "properties": {
    "addr:full":"3937 Broadway Grove City OH 43123",
    "addr:housenumber":"3937",
    "addr:postcode":"43123",
    "addr:street":"Broadway",
    "iso:country":"US",
    "sg:address":"3937 Broadway",
    "sg:city":"Grove City",
    "sg:classifiers":[
        {
            "category":"Personal",
            "subcategory":"Beauty Salon",
            "type":"Services"
        }
    ],
    "sg:phone":"+1 614 875 9320",
    "sg:postcode":"43123",
    "sg:province":"OH",
    "wof:name":"Hair Gallery & Day Spa",
    "wof:placetype":"venue"
},
  "geometry": {"coordinates":[-83.092298,39.88389],"type":"Point"}
}