{
  "type": "Feature",
  "properties": {
    "addr:full": "12235 York Rd Cleveland OH 44133",
    "addr:housenumber": "12235",
    "addr:postcode": "44133",
    "addr:street": "York Rd",
    "iso:country": "US",
    "sg:address": "12235 York Rd",
    "sg:city": "Cleveland",
    "sg:classifiers": [
      {
        "category": "Professional",
        "subcategory": "Management \u0026 Consulting",
        "type": "Services"
      }
    ],
    "sg:phone": "+1 440 237 4450",
    "sg:postcode": "44133",
    "sg:province": "OH",
    "sg:tags": [
      "party",
      "planning"
    ],
    "wof:name": "Parties 4 Kidz",
    "wof:placetype": "venue"
  },
  "geometry": {"coordinates":[-81.756516,41.323285],"type":"Point"}
}
