{
  "type": "Feature",
  "properties": {
    "iso:country":"US",
    "sg:address":"12235 York Rd",
    "sg:city":"Cleveland",
    "sg:classifiers":[
        {
            "category":"Professional",
            "subcategory":"Management & Consulting",
            "type":"Services"
        }
    ],
    "sg:phone":"+1 440 237 4450",
    "sg:postcode":"44133",
    "sg:province":"OH",
    "sg:tags":[
        "party",
        "planning"
    ],
    "wof:name":"Parties 4 Kidz",
    "wof:placetype":"venue"
},
  "geometry": {"coordinates":[-81.756516,41.323285],"type":"Point"}
}