{
  "type": "Feature",
  "properties": {
    "addr:full": "600 Union St Ashland OH 44805",
    "addr:housenumber": "600",
    "addr:postcode": "44805",
    "addr:street": "Union St",
    "iso:country": "US",
    "sg:address": "600 Union St",
    "sg:city": "Ashland",
    "sg:classifiers": [
      {
        "category": "Manufacturing",
        "subcategory": "Paper Products",
        "type": "Manufacturing \u0026 Wholesale Goods"
      }
    ],
    "sg:phone": "+1 419 289 2666",
    "sg:postcode": "44805",
    "sg:province": "OH",
    "sg:tags": [
      "box",
      "folding",
      "mfg",
      "paperboard",
      "commercial",
      "printing",
      "co"
    ],
    "sg:website": "www.caraustar.com",
    "wof:name": "Caraustar Custom Packaging",
    "wof:placetype": "venue"
  },
  "geometry": {"coordinates":[-82.312885,40.873129],"type":"Point"}
}
