{
  "type": "Feature",
  "properties": {
    "iso:country":"US",
    "sg:address":"600 Union St",
    "sg:city":"Ashland",
    "sg:classifiers":[
        {
            "category":"Manufacturing",
            "subcategory":"Paper Products",
            "type":"Manufacturing & Wholesale Goods"
        }
    ],
    "sg:phone":"+1 419 289 2666",
    "sg:postcode":"44805",
    "sg:province":"OH",
    "sg:tags":[
        "box",
        "folding",
        "mfg",
        "paperboard",
        "commercial",
        "printing",
        "co"
    ],
    "sg:website":"www.caraustar.com",
    "wof:name":"Caraustar Custom Packaging",
    "wof:placetype":"venue"
},
  "geometry": {"coordinates":[-82.312885,40.873129],"type":"Point"}
}