{
  "type": "Feature",
  "properties": {
    "iso:country":"US",
    "sg:address":"9403 Olde Eight Rd",
    "sg:city":"Northfield",
    "sg:classifiers":[
        {
            "category":"Professional",
            "subcategory":"Business Services",
            "type":"Services"
        }
    ],
    "sg:phone":"+1 330 467 1600",
    "sg:postcode":"44067",
    "sg:province":"OH",
    "sg:tags":[
        "recording",
        "studio"
    ],
    "wof:name":"Melodik Records",
    "wof:placetype":"venue"
},
  "geometry": {"coordinates":[-81.53892500000001,41.318524],"type":"Point"}
}