{
  "type": "Feature",
  "properties": {
    "addr:full": "5229 Bayside Dr Dayton OH 45431",
    "addr:housenumber": "5229",
    "addr:postcode": "45431",
    "addr:street": "Bayside Dr",
    "iso:country": "US",
    "sg:address": "5229 Bayside Dr",
    "sg:city": "Dayton",
    "sg:classifiers": [
      {
        "category": "Professional",
        "type": "Services"
      }
    ],
    "sg:phone": "+1 937 253 7016",
    "sg:postcode": "45431",
    "sg:province": "OH",
    "wof:name": "Edna M Back",
    "wof:placetype": "venue"
  },
  "geometry": {"coordinates":[-84.114652,39.762464],"type":"Point"}
}
