{
  "type": "Feature",
  "properties": {
    "iso:country":"US",
    "sg:address":"5229 Bayside Dr",
    "sg:city":"Dayton",
    "sg:classifiers":[
        {
            "category":"Professional",
            "type":"Services"
        }
    ],
    "sg:phone":"+1 937 253 7016",
    "sg:postcode":"45431",
    "sg:province":"OH",
    "wof:name":"Edna M Back",
    "wof:placetype":"venue"
},
  "geometry": {"coordinates":[-84.114652,39.762464],"type":"Point"}
}