{
  "type": "Feature",
  "properties": {
    "iso:country":"US",
    "sg:address":"3336 Lincoln Way E",
    "sg:city":"Massillon",
    "sg:classifiers":[
        {
            "category":"Personal",
            "subcategory":"Beauty Salon",
            "type":"Services"
        }
    ],
    "sg:phone":"+1 330 833 2291",
    "sg:postcode":"44646",
    "sg:province":"OH",
    "wof:name":"Crowning Glory Hair Styles",
    "wof:placetype":"venue"
},
  "geometry": {"coordinates":[-81.470574,40.79501],"type":"Point"}
}