{
  "type": "Feature",
  "properties": {
    "iso:country":"US",
    "sg:address":"6010 Franklin Lebanon Rd",
    "sg:city":"Franklin",
    "sg:classifiers":[
        {
            "category":"Organizations",
            "subcategory":"Religious Organization",
            "type":"Services"
        }
    ],
    "sg:phone":"+1 513 422 6204",
    "sg:postcode":"45005",
    "sg:province":"OH",
    "sg:tags":[
        "church"
    ],
    "wof:name":"Thompson Mem Prim Baptist Chr",
    "wof:placetype":"venue"
},
  "geometry": {"coordinates":[-84.28311100000001,39.531031],"type":"Point"}
}