{
  "type": "Feature",
  "properties": {
    "iso:country":"US",
    "sg:address":"221 N Portage St",
    "sg:city":"Doylestown",
    "sg:classifiers":[
        {
            "category":"Food & Beverages",
            "subcategory":"Dairy",
            "type":"Retail Goods"
        }
    ],
    "sg:phone":"+1 330 658 6583",
    "sg:postcode":"44230",
    "sg:province":"OH",
    "sg:tags":[
        "convenience",
        "store"
    ],
    "wof:name":"Stop N Go 94",
    "wof:placetype":"venue"
},
  "geometry": {"coordinates":[-81.694963,40.971246],"type":"Point"}
}