{
  "type": "Feature",
  "properties": {
    "iso:country":"US",
    "sg:address":"1617 Elmore Ct",
    "sg:city":"Cincinnati",
    "sg:classifiers":[
        {
            "category":"Organizations",
            "subcategory":"Non-profit Organization",
            "type":"Services"
        }
    ],
    "sg:phone":"+1 513 731 8400",
    "sg:postcode":"45223",
    "sg:province":"OH",
    "wof:name":"Millcreek Restoration Proj",
    "wof:placetype":"venue"
},
  "geometry": {"coordinates":[-84.541571,39.155346],"type":"Point"}
}