{
  "type": "Feature",
  "properties": {
    "addr:full": "1050 W Co Rd 592 Tiffin OH 44883",
    "addr:housenumber": "1050;592",
    "addr:postcode": "44883",
    "addr:street": "W Co Rd",
    "iso:country": "US",
    "sg:address": "1050 W Co Rd 592",
    "sg:city": "Tiffin",
    "sg:classifiers": [
      {
        "category": "Marine",
        "type": "Transportation"
      }
    ],
    "sg:phone": "+1 419 447 9532",
    "sg:postcode": "44883",
    "sg:province": "OH",
    "sg:tags": [
      "water",
      "transport"
    ],
    "wof:name": "Charter Boat Fishing",
    "wof:placetype": "venue"
  },
  "geometry": {"coordinates":[-83.188713,41.182109],"type":"Point"}
}
