{
  "type": "Feature",
  "properties": {
    "addr:full": "545 Clough Pike Cincinnati OH 45244",
    "addr:housenumber": "545",
    "addr:postcode": "45244",
    "addr:street": "Clough Pike",
    "iso:country": "US",
    "sg:address": "545 Clough Pike",
    "sg:city": "Cincinnati",
    "sg:classifiers": [
      {
        "category": "Personal",
        "subcategory": "Beauty Salon",
        "type": "Services"
      }
    ],
    "sg:phone": "+1 513 688 1075",
    "sg:postcode": "45244",
    "sg:province": "OH",
    "sg:tags": [
      "manicuring"
    ],
    "wof:name": "Image Nails",
    "wof:placetype": "venue"
  },
  "geometry": {"coordinates":[-84.300151,39.085673],"type":"Point"}
}
