{
  "type": "Feature",
  "properties": {
    "addr:full":"1801 Tuley Rd Indian Springs OH 45015",
    "addr:housenumber":"1801",
    "addr:postcode":"45015",
    "addr:street":"Tuley Rd",
    "iso:country":"US",
    "sg:address":"1801 Tuley Rd",
    "sg:city":"Indian Springs",
    "sg:classifiers":[
        {
            "category":"Food & Beverages",
            "subcategory":"Specialty",
            "type":"Retail Goods"
        }
    ],
    "sg:phone":"+1 513 868 1007",
    "sg:postcode":"45015",
    "sg:province":"OH",
    "sg:tags":[
        "herb"
    ],
    "wof:name":"Adrianne's Herbal Magik",
    "wof:placetype":"venue"
},
  "geometry": {"coordinates":[-84.53636400000001,39.376205],"type":"Point"}
}