{
  "type": "Feature",
  "properties": {
    "addr:full":"8496 Swaney Rd Bluffton OH 45817",
    "addr:housenumber":"8496",
    "addr:postcode":"45817",
    "addr:street":"Swaney Rd",
    "iso:country":"US",
    "sg:address":"8496 Swaney Rd",
    "sg:city":"Bluffton",
    "sg:classifiers":[
        {
            "category":"Travel",
            "subcategory":"Travel Agent",
            "type":"Entertainment"
        }
    ],
    "sg:phone":"+1 419 358 0010",
    "sg:postcode":"45817",
    "sg:province":"OH",
    "sg:tags":[
        "agency"
    ],
    "wof:name":"Bluffton Travel Agency",
    "wof:placetype":"venue"
},
  "geometry": {"coordinates":[-83.956897,40.862252],"type":"Point"}
}