{
  "type": "Feature",
  "properties": {
    "addr:full":"4224 State Rte 87 Farmdale OH 44417",
    "addr:housenumber":"4224",
    "addr:postcode":"44417",
    "addr:street":"State Rte 87",
    "iso:country":"US",
    "sg:address":"4224 State Rte 87",
    "sg:city":"Farmdale",
    "sg:classifiers":[
        {
            "category":"Education",
            "subcategory":"School",
            "type":"Public Place"
        }
    ],
    "sg:phone":"+1 330 876 3610",
    "sg:postcode":"44417",
    "sg:province":"OH",
    "wof:name":"Gustavus Elementary School Inc",
    "wof:placetype":"venue"
},
  "geometry": {"coordinates":[-80.66654699999999,41.46219],"type":"Point"}
}