{
  "type": "Feature",
  "properties": {
    "iso:country":"US",
    "sg:address":"3808 Mogadore Rd",
    "sg:city":"Mogadore",
    "sg:classifiers":[
        {
            "category":"Professional",
            "subcategory":"Advertising",
            "type":"Services"
        }
    ],
    "sg:phone":"+1 330 628 5595",
    "sg:postcode":"44260",
    "sg:province":"OH",
    "sg:tags":[
        "agency"
    ],
    "wof:name":"Siebert Advrtsng",
    "wof:placetype":"venue"
},
  "geometry": {"coordinates":[-81.39605899999999,41.051008],"type":"Point"}
}