{
  "type": "Feature",
  "properties": {
    "addr:full":"2940 Monroe St Toledo OH 43606",
    "addr:housenumber":"2940",
    "addr:postcode":"43606",
    "addr:street":"Monroe St",
    "iso:country":"US",
    "sg:address":"2940 Monroe St",
    "sg:city":"Toledo",
    "sg:classifiers":[
        {
            "category":"Banks & Credit Unions",
            "subcategory":"Bank",
            "type":"Services"
        }
    ],
    "sg:phone":"+1 419 241 9100",
    "sg:postcode":"43606",
    "sg:province":"OH",
    "sg:tags":[
        "depository",
        "banking"
    ],
    "wof:name":"Central Clearing Co",
    "wof:placetype":"venue"
},
  "geometry": {"coordinates":[-83.569711,41.664299],"type":"Point"}
}