{
  "type": "Feature",
  "properties": {
    "iso:country":"US",
    "sg:address":"4 Limited Pkwy",
    "sg:city":"Reynoldsburg",
    "sg:classifiers":[
        {
            "category":"Professional",
            "subcategory":"Employment Agencies",
            "type":"Services"
        }
    ],
    "sg:phone":"+1 614 577 7073",
    "sg:postcode":"43068",
    "sg:province":"OH",
    "sg:tags":[
        "opportunity"
    ],
    "wof:name":"Adeco",
    "wof:placetype":"venue"
},
  "geometry": {"coordinates":[-82.896807,40.056865],"type":"Point"}
}