{
  "type": "Feature",
  "properties": {
    "iso:country":"US",
    "sg:address":"755 Mount Orab Pike",
    "sg:city":"Georgetown",
    "sg:classifiers":[
        {
            "category":"Social Services",
            "type":"Services"
        }
    ],
    "sg:phone":"+1 937 378 4155",
    "sg:postcode":"45121",
    "sg:province":"OH",
    "wof:name":"Brown County Communications",
    "wof:placetype":"venue"
},
  "geometry": {"coordinates":[-83.901869,38.874628],"type":"Point"}
}