{
  "type": "Feature",
  "properties": {
    "addr:full":"11614 Glenpark Rd NE Bolivar OH 44612",
    "addr:housenumber":"11614",
    "addr:postcode":"44612",
    "addr:street":"Glenpark Rd Ne Bolivar",
    "iso:country":"US",
    "sg:address":"11614 Glenpark Rd NE",
    "sg:city":"Bolivar",
    "sg:classifiers":[
        {
            "category":"Professional",
            "subcategory":"Engineering",
            "type":"Services"
        }
    ],
    "sg:phone":"+1 330 874 2121",
    "sg:postcode":"44612",
    "sg:province":"OH",
    "sg:tags":[
        "security",
        "national"
    ],
    "wof:name":"Bolivar Dam",
    "wof:placetype":"venue"
},
  "geometry": {"coordinates":[-81.437764,40.64985],"type":"Point"}
}