{
  "type": "Feature",
  "properties": {
    "addr:full":"275 Federal Plz W Youngstown OH 44503",
    "addr:housenumber":"275",
    "addr:postcode":"44503",
    "addr:street":"Federal Plz W",
    "iso:country":"US",
    "sg:address":"275 Federal Plz W",
    "sg:city":"Youngstown",
    "sg:classifiers":[
        {
            "category":"Building & Trades",
            "subcategory":"Construction",
            "type":"Services"
        }
    ],
    "sg:phone":"+1 330 742 7855",
    "sg:postcode":"44503",
    "sg:province":"OH",
    "sg:tags":[
        "hanging",
        "contractor"
    ],
    "wof:name":"Johns Painting",
    "wof:placetype":"venue"
},
  "geometry": {"coordinates":[-80.653745,41.101884],"type":"Point"}
}