{
  "type": "Feature",
  "properties": {
    "iso:country":"US",
    "sg:address":"530 Wessel Dr",
    "sg:city":"Fairfield",
    "sg:classifiers":[
        {
            "category":"Utilities",
            "subcategory":"Mobile Phone",
            "type":"Services"
        }
    ],
    "sg:phone":"+1 513 829 6789",
    "sg:postcode":"45014",
    "sg:province":"OH",
    "sg:tags":[
        "communication",
        "radiotelephone"
    ],
    "wof:name":"Radioshack Cellular Sale & Eqp",
    "wof:placetype":"venue"
},
  "geometry": {"coordinates":[-84.562976,39.33457],"type":"Point"}
}