{
  "type": "Feature",
  "properties": {
    "iso:country":"US",
    "sg:address":"22284 State Rte 751",
    "sg:city":"West Lafayette",
    "sg:classifiers":[
        {
            "category":"Building & Trades",
            "subcategory":"Plumbing",
            "type":"Services"
        }
    ],
    "sg:phone":"+1 740 545 9400",
    "sg:postcode":"43845",
    "sg:province":"OH",
    "sg:tags":[
        "heating",
        "contractor"
    ],
    "wof:name":"Best Heating & Air Cond",
    "wof:placetype":"venue"
},
  "geometry": {"coordinates":[-81.706367,40.270193],"type":"Point"}
}