{
  "type": "Feature",
  "properties": {
    "addr:full": "22284 State Rte 751 West Lafayette OH 43845",
    "addr:housenumber": "22284",
    "addr:postcode": "43845",
    "addr:street": "State Rte 751",
    "iso:country": "US",
    "sg:address": "22284 State Rte 751",
    "sg:city": "West Lafayette",
    "sg:classifiers": [
      {
        "category": "Building \u0026 Trades",
        "subcategory": "Plumbing",
        "type": "Services"
      }
    ],
    "sg:phone": "+1 740 545 9400",
    "sg:postcode": "43845",
    "sg:province": "OH",
    "sg:tags": [
      "heating",
      "contractor"
    ],
    "wof:name": "Best Heating \u0026 Air Cond",
    "wof:placetype": "venue"
  },
  "geometry": {"coordinates":[-81.706367,40.270193],"type":"Point"}
}
