{
  "type": "Feature",
  "properties": {
    "iso:country":"US",
    "sg:address":"6421 Monclova Rd",
    "sg:city":"Maumee",
    "sg:classifiers":[
        {
            "category":"Manufacturing",
            "subcategory":"Chemicals & Compounds",
            "type":"Manufacturing & Wholesale Goods"
        }
    ],
    "sg:phone":"+1 419 893 7226",
    "sg:postcode":"43537",
    "sg:province":"OH",
    "sg:tags":[
        "gas"
    ],
    "sg:website":"www.linde-gas.com",
    "wof:name":"Linde Gas",
    "wof:placetype":"venue"
},
  "geometry": {"coordinates":[-83.695038,41.558708],"type":"Point"}
}