{
  "type": "Feature",
  "properties": {
    "addr:full": "6421 Monclova Rd Maumee OH 43537",
    "addr:postcode": "6421;43537",
    "addr:street": "Monclova Rd",
    "iso:country": "US",
    "sg:address": "6421 Monclova Rd",
    "sg:city": "Maumee",
    "sg:classifiers": [
      {
        "category": "Manufacturing",
        "subcategory": "Chemicals \u0026 Compounds",
        "type": "Manufacturing \u0026 Wholesale Goods"
      }
    ],
    "sg:phone": "+1 419 893 7226",
    "sg:postcode": "43537",
    "sg:province": "OH",
    "sg:tags": [
      "gas"
    ],
    "sg:website": "www.linde-gas.com",
    "wof:name": "Linde Gas",
    "wof:placetype": "venue"
  },
  "geometry": {"coordinates":[-83.695038,41.558708],"type":"Point"}
}
