{
  "type": "Feature",
  "properties": {
    "addr:full": "1430 W High St Orrville OH 44667",
    "addr:housenumber": "1430",
    "addr:postcode": "44667",
    "addr:street": "W High St",
    "iso:country": "US",
    "sg:address": "1430 W High St",
    "sg:city": "Orrville",
    "sg:classifiers": [
      {
        "category": "Professional",
        "subcategory": "Business Services",
        "type": "Services"
      }
    ],
    "sg:phone": "+1 330 682 7225",
    "sg:postcode": "44667",
    "sg:province": "OH",
    "sg:tags": [
      "packing",
      "shipping"
    ],
    "wof:name": "Packship USA LLC",
    "wof:placetype": "venue"
  },
  "geometry": {"coordinates":[-81.779851,40.844147],"type":"Point"}
}
