{
  "type": "Feature",
  "properties": {
    "iso:country":"US",
    "sg:address":"4480 Alum Creek Dr",
    "sg:city":"Columbus",
    "sg:classifiers":[
        {
            "category":"Restaurant",
            "type":"Food & Drink"
        }
    ],
    "sg:menulink":"http://www.allmenus.com/oh/hamilton/200669-long-john-silvers/menu/",
    "sg:phone":"+1 614 492 9021",
    "sg:postcode":"43207",
    "sg:province":"OH",
    "sg:tags":[
        "seafood",
        "american"
    ],
    "wof:name":"Long John Silver's",
    "wof:placetype":"venue"
},
  "geometry": {"coordinates":[-82.93135599999999,39.876829],"type":"Point"}
}