{
  "type": "Feature",
  "properties": {
    "addr:full": "4480 Alum Creek Dr Columbus OH 43207",
    "addr:postcode": "4480;43207",
    "addr:street": "Alum Creek Dr",
    "iso:country": "US",
    "sg:address": "4480 Alum Creek Dr",
    "sg:city": "Columbus",
    "sg:classifiers": [
      {
        "category": "Restaurant",
        "type": "Food \u0026 Drink"
      }
    ],
    "sg:menulink": "http://www.allmenus.com/oh/hamilton/200669-long-john-silvers/menu/",
    "sg:phone": "+1 614 492 9021",
    "sg:postcode": "43207",
    "sg:province": "OH",
    "sg:tags": [
      "seafood",
      "american"
    ],
    "wof:name": "Long John Silver's",
    "wof:placetype": "venue"
  },
  "geometry": {"coordinates":[-82.931356,39.876829],"type":"Point"}
}
