{
  "type": "Feature",
  "properties": {
    "addr:full": "5868 Marin Dr Toledo OH 43613",
    "addr:housenumber": "5868",
    "addr:postcode": "43613",
    "addr:street": "Marin Dr",
    "iso:country": "US",
    "sg:address": "5868 Marin Dr",
    "sg:city": "Toledo",
    "sg:classifiers": [
      {
        "category": "Freight",
        "type": "Transportation"
      }
    ],
    "sg:phone": "+1 419 472 7513",
    "sg:postcode": "43613",
    "sg:province": "OH",
    "sg:tags": [
      "trucking"
    ],
    "wof:name": "Glover Trucking LTD",
    "wof:placetype": "venue"
  },
  "geometry": {"coordinates":[-83.592405,41.722786],"type":"Point"}
}
