{
  "type": "Feature",
  "properties": {
    "iso:country":"US",
    "sg:address":"3030 Superior Ave E",
    "sg:city":"Cleveland",
    "sg:classifiers":[
        {
            "category":"Personal",
            "subcategory":"Beauty Salon",
            "type":"Services"
        }
    ],
    "sg:phone":"+1 216 574 2288",
    "sg:postcode":"44114",
    "sg:province":"OH",
    "wof:name":"LA Beaute Skin Care & Csmtcs",
    "wof:placetype":"venue"
},
  "geometry": {"coordinates":[-81.67011100000001,41.510548],"type":"Point"}
}