{
  "type": "Feature",
  "properties": {
    "addr:full": "100 Valley View Rd Doylestown OH 44230",
    "addr:housenumber": "100",
    "addr:postcode": "44230",
    "addr:street": "Valley View Rd",
    "iso:country": "US",
    "sg:address": "100 Valley View Rd",
    "sg:city": "Doylestown",
    "sg:classifiers": [
      {
        "category": "Education",
        "subcategory": "School",
        "type": "Public Place"
      }
    ],
    "sg:phone": "+1 330 658 2011",
    "sg:postcode": "44230",
    "sg:province": "OH",
    "sg:website": "www.chippewa.k12.oh.us",
    "wof:name": "Chippewa High School",
    "wof:placetype": "venue"
  },
  "geometry": {"coordinates":[-81.69628,40.96025],"type":"Point"}
}
