{
  "type": "Feature",
  "properties": {
    "iso:country":"US",
    "sg:address":"229 Lehigh Ave",
    "sg:city":"Cuyahoga Falls",
    "sg:classifiers":[
        {
            "category":"Retail",
            "subcategory":"Repair Shop",
            "type":"Services"
        }
    ],
    "sg:phone":"+1 330 920 1266",
    "sg:postcode":"44221",
    "sg:province":"OH",
    "sg:tags":[
        "plumbing",
        "drain",
        "cleaning",
        "sewer",
        "contractor"
    ],
    "wof:name":"Falls Sewer & Drain Cleaning",
    "wof:placetype":"venue"
},
  "geometry": {"coordinates":[-81.478301,41.155841],"type":"Point"}
}