{
  "type": "Feature",
  "properties": {
    "addr:full":"3250 W Henderson Rd Columbus OH 43220",
    "addr:housenumber":"3250",
    "addr:postcode":"43220",
    "addr:street":"W Henderson Rd",
    "iso:country":"US",
    "sg:address":"3250 W Henderson Rd",
    "sg:city":"Columbus",
    "sg:classifiers":[
        {
            "category":"Personal",
            "type":"Services"
        }
    ],
    "sg:phone":"+1 614 457 9292",
    "sg:postcode":"43220",
    "sg:province":"OH",
    "sg:tags":[
        "therapist",
        "massage"
    ],
    "wof:name":"Healthtouch",
    "wof:placetype":"venue"
},
  "geometry": {"coordinates":[-83.08139799999999,40.059612],"type":"Point"}
}