{
  "type": "Feature",
  "properties": {
    "addr:full":"7597 W Chester Rd West Chester OH 45069",
    "addr:housenumber":"7597",
    "addr:postcode":"45069",
    "addr:street":"W Chester Rd",
    "iso:country":"US",
    "sg:address":"7597 W Chester Rd",
    "sg:city":"West Chester",
    "sg:classifiers":[
        {
            "category":"Shopping",
            "subcategory":"Books",
            "type":"Retail Goods"
        }
    ],
    "sg:phone":"+1 513 755 6332",
    "sg:postcode":"45069",
    "sg:province":"OH",
    "wof:name":"Norm Johnson Bookseller",
    "wof:placetype":"venue"
},
  "geometry": {"coordinates":[-84.371966,39.318525],"type":"Point"}
}