{
  "type": "Feature",
  "properties": {
    "addr:full": "502 S Main St Orrville OH 44667",
    "addr:housenumber": "502",
    "addr:postcode": "44667",
    "addr:street": "S Main St",
    "iso:country": "US",
    "sg:address": "502 S Main St",
    "sg:city": "Orrville",
    "sg:classifiers": [
      {
        "category": "Organizations",
        "subcategory": "Religious Organization",
        "type": "Services"
      }
    ],
    "sg:phone": "+1 330 682 0581",
    "sg:postcode": "44667",
    "sg:province": "OH",
    "sg:tags": [
      "clergy"
    ],
    "wof:name": "Church Of The Nazarene",
    "wof:placetype": "venue"
  },
  "geometry": {"coordinates":[-81.764343,40.836752],"type":"Point"}
}
