{
  "type": "Feature",
  "properties": {
    "addr:full":"512 Peters Ave Troy OH 45373",
    "addr:housenumber":"512",
    "addr:postcode":"45373",
    "addr:street":"Peters Ave",
    "iso:country":"US",
    "sg:address":"512 Peters Ave",
    "sg:city":"Troy",
    "sg:classifiers":[
        {
            "category":"Farming",
            "subcategory":"Farm",
            "type":"Manufacturing & Wholesale Goods"
        }
    ],
    "sg:phone":"+1 937 339 6019",
    "sg:postcode":"45373",
    "sg:province":"OH",
    "sg:tags":[
        "crop",
        "general"
    ],
    "wof:name":"Red Oak Farm LLC",
    "wof:placetype":"venue"
},
  "geometry": {"coordinates":[-84.21734499999999,40.027545],"type":"Point"}
}