{
  "type": "Feature",
  "properties": {
    "addr:full": "44781 Pomeroy Pike Racine OH 45771",
    "addr:housenumber": "44781",
    "addr:postcode": "45771",
    "addr:street": "Pomeroy Pike",
    "iso:country": "US",
    "sg:address": "44781 Pomeroy Pike",
    "sg:city": "Racine",
    "sg:classifiers": [
      {
        "category": "Retail",
        "subcategory": "Repair Shop",
        "type": "Services"
      },
      {
        "category": "Shopping",
        "subcategory": "Bicycles \u0026 Sporting Goods",
        "type": "Retail Goods"
      }
    ],
    "sg:phone": "+1 740 985 3364",
    "sg:postcode": "45771",
    "sg:province": "OH",
    "sg:tags": [
      "taxidermist"
    ],
    "wof:name": "Brown's Taxidermy",
    "wof:placetype": "venue"
  },
  "geometry": {"coordinates":[-81.951978,39.072011],"type":"Point"}
}
