{
  "type": "Feature",
  "properties": {
    "addr:full": "3424 Timber Oak Dr Columbus OH 43204",
    "addr:housenumber": "3424",
    "addr:postcode": "43204",
    "addr:street": "Timber Oak Dr",
    "iso:country": "US",
    "sg:address": "3424 Timber Oak Dr",
    "sg:city": "Columbus",
    "sg:classifiers": [
      {
        "category": "Building \u0026 Trades",
        "subcategory": "Landscaping Services",
        "type": "Services"
      }
    ],
    "sg:phone": "+1 614 276 8763",
    "sg:postcode": "43204",
    "sg:province": "OH",
    "wof:name": "McFarland Emporium",
    "wof:placetype": "venue"
  },
  "geometry": {"coordinates":[-83.093496,39.971611],"type":"Point"}
}
