{
  "type": "Feature",
  "properties": {
    "addr:full": "3470 Salem Ave Dayton OH 45406",
    "addr:housenumber": "3470",
    "addr:postcode": "45406",
    "addr:street": "Salem Ave",
    "iso:country": "US",
    "sg:address": "3470 Salem Ave",
    "sg:city": "Dayton",
    "sg:classifiers": [
      {
        "category": "Food \u0026 Beverages",
        "subcategory": "Liquor \u0026 Beverages",
        "type": "Retail Goods"
      }
    ],
    "sg:phone": "+1 937 275 3190",
    "sg:postcode": "45406",
    "sg:province": "OH",
    "wof:name": "Gina's Liquor",
    "wof:placetype": "venue"
  },
  "geometry": {"coordinates":[-84.243821,39.792112],"type":"Point"}
}
