{
  "type": "Feature",
  "properties": {
    "addr:full": "1029 Ledro St Cincinnati OH 45246",
    "addr:housenumber": "1029",
    "addr:postcode": "45246",
    "addr:street": "Ledro St",
    "iso:country": "US",
    "sg:address": "1029 Ledro St",
    "sg:city": "Cincinnati",
    "sg:classifiers": [
      {
        "category": "Shopping",
        "subcategory": "Clothing, Apparel, \u0026 Fashions",
        "type": "Retail Goods"
      }
    ],
    "sg:phone": "+1 513 825 4710",
    "sg:postcode": "45246",
    "sg:province": "OH",
    "sg:tags": [
      "garment"
    ],
    "wof:name": "GJS Sash \u0026 Apparel",
    "wof:placetype": "venue"
  },
  "geometry": {"coordinates":[-84.452722,39.300586],"type":"Point"}
}
