{
  "type": "Feature",
  "properties": {
    "addr:full": "1026 Goodale Blvd Columbus OH 43212",
    "addr:housenumber": "1026",
    "addr:postcode": "43212",
    "addr:street": "Goodale Blvd",
    "iso:country": "US",
    "sg:address": "1026 Goodale Blvd",
    "sg:city": "Columbus",
    "sg:classifiers": [
      {
        "category": "Wholesale",
        "subcategory": "Hardware",
        "type": "Manufacturing \u0026 Wholesale Goods"
      }
    ],
    "sg:phone": "+1 614 294 6851",
    "sg:postcode": "43212",
    "sg:province": "OH",
    "sg:tags": [
      "plumbing",
      "e",
      "representative",
      "heating"
    ],
    "wof:name": "Peterson Thermal Equipment",
    "wof:placetype": "venue"
  },
  "geometry": {"coordinates":[-83.029892,39.97447],"type":"Point"}
}
