{
  "type": "Feature",
  "properties": {
    "addr:full":"8360 State Rte 124 Latham OH 45646",
    "addr:housenumber":"8360",
    "addr:postcode":"45646",
    "addr:street":"State Rte 124",
    "iso:country":"US",
    "sg:address":"8360 State Rte 124",
    "sg:city":"Latham",
    "sg:classifiers":[
        {
            "category":"Food & Beverages",
            "subcategory":"Liquor & Beverages",
            "type":"Retail Goods"
        }
    ],
    "sg:phone":"+1 740 493 2477",
    "sg:postcode":"45646",
    "sg:province":"OH",
    "sg:tags":[
        "beer",
        "ale"
    ],
    "wof:name":"Valley Carry Out",
    "wof:placetype":"venue"
},
  "geometry": {"coordinates":[-83.246272,39.099256],"type":"Point"}
}