{
  "type": "Feature",
  "properties": {
    "addr:full": "319 Mark Dr Tallmadge OH 44278",
    "addr:housenumber": "319",
    "addr:postcode": "44278",
    "addr:street": "Mark Dr",
    "iso:country": "US",
    "sg:address": "319 Mark Dr",
    "sg:city": "Tallmadge",
    "sg:classifiers": [
      {
        "category": "Professional",
        "subcategory": "Business Services",
        "type": "Services"
      }
    ],
    "sg:phone": "+1 330 633 3418",
    "sg:postcode": "44278",
    "sg:province": "OH",
    "sg:tags": [
      "recording",
      "studio"
    ],
    "wof:name": "Listen Again Recording",
    "wof:placetype": "venue"
  },
  "geometry": {"coordinates":[-81.453555,41.109205],"type":"Point"}
}
