{
  "type": "Feature",
  "properties": {
    "addr:full": "8220 Arbor Square Dr Mason OH 45040",
    "addr:housenumber": "8220",
    "addr:postcode": "45040",
    "addr:street": "Arbor Square Dr",
    "iso:country": "US",
    "sg:address": "8220 Arbor Square Dr",
    "sg:city": "Mason",
    "sg:classifiers": [
      {
        "category": "Food Court",
        "type": "Food \u0026 Drink"
      },
      {
        "category": "Restaurant",
        "type": "Food \u0026 Drink"
      },
      {
        "category": "Bagels",
        "subcategory": "None",
        "type": "Food \u0026 Drink"
      },
      {
        "category": "Coffee \u0026 Tea",
        "type": "Food \u0026 Drink"
      },
      {
        "category": "Bakery",
        "type": "Food \u0026 Drink"
      },
      {
        "category": "Food \u0026 Beverages",
        "subcategory": "Groceries \u0026 Convenience Stores",
        "type": "Retail Goods"
      }
    ],
    "sg:phone": "+1 513 770 0451",
    "sg:postcode": "45040",
    "sg:province": "OH",
    "sg:tags": [
      "shop",
      "box",
      "sandwich",
      "espresso",
      "lunch",
      "brunch",
      "breakfast"
    ],
    "sg:website": "http://www.brueggers.com",
    "wof:name": "Bruegger's",
    "wof:placetype": "venue"
  },
  "geometry": {"coordinates":[-84.314133,39.319041],"type":"Point"}
}
