{
  "type": "Feature",
  "properties": {
    "addr:full":"8220 Arbor Square Dr Mason OH 45040",
    "addr:housenumber":"8220",
    "addr:postcode":"45040",
    "addr:street":"Arbor Square Dr",
    "iso:country":"US",
    "sg:address":"8220 Arbor Square Dr",
    "sg:city":"Mason",
    "sg:classifiers":[
        {
            "category":"Food Court",
            "type":"Food & Drink"
        },
        {
            "category":"Restaurant",
            "type":"Food & Drink"
        },
        {
            "category":"Bagels",
            "subcategory":"None",
            "type":"Food & Drink"
        },
        {
            "category":"Coffee & Tea",
            "type":"Food & Drink"
        },
        {
            "category":"Bakery",
            "type":"Food & Drink"
        },
        {
            "category":"Food & Beverages",
            "subcategory":"Groceries & Convenience Stores",
            "type":"Retail Goods"
        }
    ],
    "sg:phone":"+1 513 770 0451",
    "sg:postcode":"45040",
    "sg:province":"OH",
    "sg:tags":[
        "shop",
        "box",
        "sandwich",
        "espresso",
        "lunch",
        "brunch",
        "breakfast"
    ],
    "sg:website":"http://www.brueggers.com",
    "wof:name":"Bruegger's",
    "wof:placetype":"venue"
},
  "geometry": {"coordinates":[-84.314133,39.319041],"type":"Point"}
}