{
  "type": "Feature",
  "properties": {
    "iso:country":"US",
    "sg:address":"3020 Madison Rd",
    "sg:city":"Cincinnati",
    "sg:classifiers":[
        {
            "category":"Retail",
            "subcategory":"Veterinary Services",
            "type":"Services"
        }
    ],
    "sg:phone":"+1 513 531 0600",
    "sg:postcode":"45209",
    "sg:province":"OH",
    "wof:name":"Oakley Square Family Dentistry",
    "wof:placetype":"venue"
},
  "geometry": {"coordinates":[-84.43274700000001,39.15159],"type":"Point"}
}