{
  "type": "Feature",
  "properties": {
    "addr:full": "3020 Madison Rd Cincinnati OH 45209",
    "addr:housenumber": "3020",
    "addr:postcode": "45209",
    "addr:street": "Madison Rd",
    "iso:country": "US",
    "sg:address": "3020 Madison Rd",
    "sg:city": "Cincinnati",
    "sg:classifiers": [
      {
        "category": "Retail",
        "subcategory": "Veterinary Services",
        "type": "Services"
      }
    ],
    "sg:phone": "+1 513 531 0600",
    "sg:postcode": "45209",
    "sg:province": "OH",
    "wof:name": "Oakley Square Family Dentistry",
    "wof:placetype": "venue"
  },
  "geometry": {"coordinates":[-84.432747,39.15159],"type":"Point"}
}
