{
  "type": "Feature",
  "properties": {
    "addr:full": "5878 Quail Run Dr Grove City OH 43123",
    "addr:housenumber": "5878",
    "addr:postcode": "43123",
    "addr:street": "Quail Run Dr",
    "iso:country": "US",
    "sg:address": "5878 Quail Run Dr",
    "sg:city": "Grove City",
    "sg:classifiers": [
      {
        "category": "Building \u0026 Trades",
        "subcategory": "Construction",
        "type": "Services"
      }
    ],
    "sg:phone": "+1 614 539 9548",
    "sg:postcode": "43123",
    "sg:province": "OH",
    "sg:tags": [
      "house"
    ],
    "wof:name": "Blair Builders",
    "wof:placetype": "venue"
  },
  "geometry": {"coordinates":[-83.067913,39.844764],"type":"Point"}
}
