{
  "type": "Feature",
  "properties": {
    "iso:country":"US",
    "sg:address":"4200 Stelzer Rd",
    "sg:city":"Columbus",
    "sg:classifiers":[
        {
            "category":"Travel",
            "subcategory":"Hotels & Motels",
            "type":"Entertainment"
        }
    ],
    "sg:phone":"+1 614 428 6022",
    "sg:postcode":"43230",
    "sg:province":"OH",
    "sg:tags":[
        "corporate",
        "lodging"
    ],
    "sg:website":"http://redirect.searchignite.com/si/cm/tracking/DGTrackingRedirect.aspx?siclientid=2918&siredirect=http%3A%2F%2Fwww%2Eextendedstayamerica%2Ecom%2FCEA&sisearchengine=155&siproduct=ESA+Columbus+%2D+Easton&clearppc=1",
    "wof:name":"Extended Stay America Columbus - Easton",
    "wof:placetype":"venue"
},
  "geometry": {"coordinates":[-82.910309,40.05946],"type":"Point"}
}