{
  "type": "Feature",
  "properties": {
    "addr:full": "4200 Stelzer Rd Columbus OH 43230",
    "addr:postcode": "4200;43230",
    "addr:street": "Stelzer Rd",
    "iso:country": "US",
    "sg:address": "4200 Stelzer Rd",
    "sg:city": "Columbus",
    "sg:classifiers": [
      {
        "category": "Travel",
        "subcategory": "Hotels \u0026 Motels",
        "type": "Entertainment"
      }
    ],
    "sg:phone": "+1 614 428 6022",
    "sg:postcode": "43230",
    "sg:province": "OH",
    "sg:tags": [
      "corporate",
      "lodging"
    ],
    "sg:website": "http://redirect.searchignite.com/si/cm/tracking/DGTrackingRedirect.aspx?siclientid=2918\u0026siredirect=http%3A%2F%2Fwww%2Eextendedstayamerica%2Ecom%2FCEA\u0026sisearchengine=155\u0026siproduct=ESA+Columbus+%2D+Easton\u0026clearppc=1",
    "wof:name": "Extended Stay America Columbus - Easton",
    "wof:placetype": "venue"
  },
  "geometry": {"coordinates":[-82.910309,40.05946],"type":"Point"}
}
