{
  "type": "Feature",
  "properties": {
    "addr:full": "1645 Coventry Rd Cleveland OH 44118",
    "addr:housenumber": "1645",
    "addr:postcode": "44118",
    "addr:street": "Coventry Rd",
    "iso:country": "US",
    "sg:address": "1645 Coventry Rd",
    "sg:city": "Cleveland",
    "sg:classifiers": [
      {
        "category": "Building \u0026 Trades",
        "subcategory": "Landscaping Services",
        "type": "Services"
      }
    ],
    "sg:phone": "+1 216 371 4786",
    "sg:postcode": "44118",
    "sg:province": "OH",
    "sg:tags": [
      "landscape",
      "contractor"
    ],
    "wof:name": "Tree \u0026 Lawn Landscaping",
    "wof:placetype": "venue"
  },
  "geometry": {"coordinates":[-81.58013,41.512126],"type":"Point"}
}
