{
  "type": "Feature",
  "properties": {
    "addr:full":"671 Canton Rd Akron OH 44312",
    "addr:housenumber":"671",
    "addr:postcode":"44312",
    "addr:street":"Canton Rd",
    "iso:country":"US",
    "sg:address":"671 Canton Rd",
    "sg:city":"Akron",
    "sg:classifiers":[
        {
            "category":"Social Services",
            "subcategory":"Child Care",
            "type":"Services"
        }
    ],
    "sg:phone":"+1 330 784 3181",
    "sg:postcode":"44312",
    "sg:province":"OH",
    "sg:tags":[
        "day"
    ],
    "wof:name":"Eastgate Pre-School",
    "wof:placetype":"venue"
},
  "geometry": {"coordinates":[-81.436256,41.042648],"type":"Point"}
}