{
  "type": "Feature",
  "properties": {
    "addr:full": "205 Corporate Ct Fairfield OH 45014",
    "addr:housenumber": "205",
    "addr:postcode": "45014",
    "addr:street": "Corporate Ct",
    "iso:country": "US",
    "sg:address": "205 Corporate Ct",
    "sg:city": "Fairfield",
    "sg:classifiers": [
      {
        "category": "Wholesale",
        "subcategory": "Machinery \u0026 Supplies",
        "type": "Manufacturing \u0026 Wholesale Goods"
      }
    ],
    "sg:phone": "+1 513 860 9428",
    "sg:postcode": "45014",
    "sg:province": "OH",
    "wof:name": "Saeilo Machinery",
    "wof:placetype": "venue"
  },
  "geometry": {"coordinates":[-84.483422,39.317547],"type":"Point"}
}
