{
  "type": "Feature",
  "properties": {
    "iso:country":"US",
    "sg:address":"500 W Wayne St",
    "sg:city":"Celina",
    "sg:classifiers":[
        {
            "category":"Manufacturing",
            "subcategory":"Retail Goods",
            "type":"Manufacturing & Wholesale Goods"
        }
    ],
    "sg:phone":"+1 419 586 2351",
    "sg:postcode":"45822",
    "sg:province":"OH",
    "sg:tags":[
        "product",
        "mfg"
    ],
    "wof:name":"Decatur Industries",
    "wof:placetype":"venue"
},
  "geometry": {"coordinates":[-84.57692299999999,40.553052],"type":"Point"}
}