{
  "type": "Feature",
  "properties": {
    "addr:full": "500 W Wayne St Celina OH 45822",
    "addr:housenumber": "500",
    "addr:postcode": "45822",
    "addr:street": "W Wayne St",
    "iso:country": "US",
    "sg:address": "500 W Wayne St",
    "sg:city": "Celina",
    "sg:classifiers": [
      {
        "category": "Manufacturing",
        "subcategory": "Retail Goods",
        "type": "Manufacturing \u0026 Wholesale Goods"
      }
    ],
    "sg:phone": "+1 419 586 2351",
    "sg:postcode": "45822",
    "sg:province": "OH",
    "sg:tags": [
      "product",
      "mfg"
    ],
    "wof:name": "Decatur Industries",
    "wof:placetype": "venue"
  },
  "geometry": {"coordinates":[-84.576923,40.553052],"type":"Point"}
}
