{
  "type": "Feature",
  "properties": {
    "iso:country":"US",
    "sg:address":"4584 N Fairgreen Dr",
    "sg:city":"Dayton",
    "sg:classifiers":[
        {
            "category":"Shopping",
            "subcategory":"Music",
            "type":"Retail Goods"
        }
    ],
    "sg:phone":"+1 937 832 0878",
    "sg:postcode":"45416",
    "sg:province":"OH",
    "wof:name":"Disc World",
    "wof:placetype":"venue"
},
  "geometry": {"coordinates":[-84.262023,39.809297],"type":"Point"}
}