{
  "type": "Feature",
  "properties": {
    "addr:full": "51685 Portman Rd Amherst OH 44001",
    "addr:housenumber": "51685",
    "addr:postcode": "44001",
    "addr:street": "Portman Rd",
    "iso:country": "US",
    "sg:address": "51685 Portman Rd",
    "sg:city": "Amherst",
    "sg:classifiers": [
      {
        "category": "Building \u0026 Trades",
        "subcategory": "Construction",
        "type": "Services"
      },
      {
        "category": "Building \u0026 Trades",
        "subcategory": "Plumbing",
        "type": "Services"
      }
    ],
    "sg:phone": "+1 440 965 7070",
    "sg:postcode": "44001",
    "sg:province": "OH",
    "sg:tags": [
      "excavating",
      "contractor"
    ],
    "wof:name": "Kathy's Excavating",
    "wof:placetype": "venue"
  },
  "geometry": {"coordinates":[-82.318593,41.353148],"type":"Point"}
}
