{
  "type": "Feature",
  "properties": {
    "addr:full":"479 Hill Rd N Pickerington OH 43147",
    "addr:housenumber":"479",
    "addr:postcode":"43147",
    "addr:street":"Hill Rd N",
    "iso:country":"US",
    "sg:address":"479 Hill Rd N",
    "sg:city":"Pickerington",
    "sg:classifiers":[
        {
            "category":"Shopping",
            "subcategory":"Books",
            "type":"Retail Goods"
        }
    ],
    "sg:phone":"+1 614 833 1331",
    "sg:postcode":"43147",
    "sg:province":"OH",
    "sg:tags":[
        "comic"
    ],
    "wof:name":"Armoury Games",
    "wof:placetype":"venue"
},
  "geometry": {"coordinates":[-82.764337,39.896984],"type":"Point"}
}