{
  "type": "Feature",
  "properties": {
    "addr:full":"1265 Waterville Monclova Rd Waterville OH 43566",
    "addr:housenumber":"1265",
    "addr:postcode":"43566",
    "addr:street":"Waterville Monclova Rd",
    "iso:country":"US",
    "sg:address":"1265 Waterville Monclova Rd",
    "sg:city":"Waterville",
    "sg:classifiers":[
        {
            "category":"Manufacturing",
            "subcategory":"Tools & Machinery",
            "type":"Manufacturing & Wholesale Goods"
        }
    ],
    "sg:phone":"+1 419 878 9779",
    "sg:postcode":"43566",
    "sg:province":"OH",
    "sg:tags":[
        "cutting"
    ],
    "wof:name":"Crum Manufacturing",
    "wof:placetype":"venue"
},
  "geometry": {"coordinates":[-83.735861,41.487192],"type":"Point"}
}