{
  "type": "Feature",
  "properties": {
    "addr:full":"4674 Parkman Rd NW Warren OH 44481",
    "addr:housenumber":"4674",
    "addr:postcode":"44481",
    "addr:street":"Parkman Rd Nw",
    "iso:country":"US",
    "sg:address":"4674 Parkman Rd NW",
    "sg:city":"Warren",
    "sg:classifiers":[
        {
            "category":"Retail",
            "subcategory":"Auto Rental",
            "type":"Services"
        }
    ],
    "sg:phone":"+1 330 898 7904",
    "sg:postcode":"44481",
    "sg:province":"OH",
    "sg:tags":[
        "renting",
        "truck",
        "leasing"
    ],
    "wof:name":"U-Haul Co",
    "wof:placetype":"venue"
},
  "geometry": {"coordinates":[-80.87829499999999,41.264241],"type":"Point"}
}