{
  "type": "Feature",
  "properties": {
    "addr:full": "3695 Center Rd Brunswick OH 44212",
    "addr:housenumber": "3695",
    "addr:postcode": "44212",
    "addr:street": "Center Rd",
    "iso:country": "US",
    "sg:address": "3695 Center Rd",
    "sg:city": "Brunswick",
    "sg:classifiers": [
      {
        "category": "Professional",
        "subcategory": "Lawyer \u0026 Legal Services",
        "type": "Services"
      }
    ],
    "sg:phone": "+1 330 225 7220",
    "sg:postcode": "44212",
    "sg:province": "OH",
    "sg:tags": [
      "attorney"
    ],
    "wof:name": "Robert T Tinl \u0026 Assoc",
    "wof:placetype": "venue"
  },
  "geometry": {"coordinates":[-81.818388,41.238397],"type":"Point"}
}
