{
  "type": "Feature",
  "properties": {
    "addr:full": "1234 Delta Rd Springfield OH 45505",
    "addr:housenumber": "1234",
    "addr:postcode": "45505",
    "addr:street": "Delta Rd",
    "iso:country": "US",
    "sg:address": "1234 Delta Rd",
    "sg:city": "Springfield",
    "sg:classifiers": [
      {
        "category": "Real Estate",
        "subcategory": "Real Estate Operator",
        "type": "Services"
      }
    ],
    "sg:phone": "+1 937 323 2566",
    "sg:postcode": "45505",
    "sg:province": "OH",
    "sg:tags": [
      "apartment"
    ],
    "wof:name": "Sunset Hills Apartment",
    "wof:placetype": "venue"
  },
  "geometry": {"coordinates":[-83.793051,39.905572],"type":"Point"}
}
