{
  "type": "Feature",
  "properties": {
    "iso:country":"US",
    "sg:address":"1646 N Keowee St",
    "sg:city":"Dayton",
    "sg:classifiers":[
        {
            "category":"Autos & Motor Vehicles",
            "subcategory":"Automobile Sales",
            "type":"Retail Goods"
        }
    ],
    "sg:phone":"+1 937 222 8655",
    "sg:postcode":"45404",
    "sg:province":"OH",
    "sg:tags":[
        "used"
    ],
    "wof:name":"S & W Motor Company Inc",
    "wof:placetype":"venue"
},
  "geometry": {"coordinates":[-84.189091,39.787389],"type":"Point"}
}