{
  "type": "Feature",
  "properties": {
    "iso:country":"US",
    "sg:address":"450 State Rte 551",
    "sg:city":"Waverly",
    "sg:classifiers":[
        {
            "category":"Travel",
            "subcategory":"Campground",
            "type":"Entertainment"
        }
    ],
    "sg:phone":"+1 740 947 2859",
    "sg:postcode":"45690",
    "sg:province":"OH",
    "sg:tags":[
        "trailer"
    ],
    "wof:name":"Pirates Cove",
    "wof:placetype":"venue"
},
  "geometry": {"coordinates":[-83.04056,39.105477],"type":"Point"}
}