{
  "type": "Feature",
  "properties": {
    "addr:full":"113 W Main St Van Wert OH 45891",
    "addr:housenumber":"113",
    "addr:postcode":"45891",
    "addr:street":"W Main St",
    "iso:country":"US",
    "sg:address":"113 W Main St",
    "sg:city":"Van Wert",
    "sg:classifiers":[
        {
            "category":"Personal",
            "subcategory":"Tanning Parlor",
            "type":"Services"
        }
    ],
    "sg:phone":"+1 419 238 0717",
    "sg:postcode":"45891",
    "sg:province":"OH",
    "sg:tags":[
        "salon"
    ],
    "wof:name":"Four Seasons Trop Tanning",
    "wof:placetype":"venue"
},
  "geometry": {"coordinates":[-84.58413,40.869695],"type":"Point"}
}