{
  "type": "Feature",
  "properties": {
    "iso:country":"US",
    "sg:address":"3757 Inpark Cir",
    "sg:city":"Dayton",
    "sg:classifiers":[
        {
            "category":"Manufacturing",
            "subcategory":"Printing",
            "type":"Manufacturing & Wholesale Goods"
        }
    ],
    "sg:phone":"+1 937 235 3111",
    "sg:postcode":"45414",
    "sg:province":"OH",
    "sg:tags":[
        "bookbinder",
        "bindery"
    ],
    "wof:name":"Dayton Bindery Service Inc",
    "wof:placetype":"venue"
},
  "geometry": {"coordinates":[-84.173709,39.80218],"type":"Point"}
}