{
  "type": "Feature",
  "properties": {
    "addr:full": "5086 Utica Rd Waynesville OH 45068",
    "addr:housenumber": "5086",
    "addr:postcode": "45068",
    "addr:street": "Utica Rd",
    "iso:country": "US",
    "sg:address": "5086 Utica Rd",
    "sg:city": "Waynesville",
    "sg:classifiers": [
      {
        "category": "Building \u0026 Trades",
        "subcategory": "Landscaping Services",
        "type": "Services"
      }
    ],
    "sg:phone": "+1 513 934 0200",
    "sg:postcode": "45068",
    "sg:province": "OH",
    "sg:tags": [
      "tree"
    ],
    "wof:name": "Shape It Up Tree Svc",
    "wof:placetype": "venue"
  },
  "geometry": {"coordinates":[-84.15964,39.509605],"type":"Point"}
}
