{
  "type": "Feature",
  "properties": {
    "addr:full":"11291 Island Rd Grafton OH 44044",
    "addr:housenumber":"11291",
    "addr:postcode":"44044",
    "addr:street":"Island Rd",
    "iso:country":"US",
    "sg:address":"11291 Island Rd",
    "sg:city":"Grafton",
    "sg:classifiers":[
        {
            "category":"Shopping",
            "subcategory":"Gifts & Souvenirs",
            "type":"Retail Goods"
        }
    ],
    "sg:phone":"+1 440 748 1032",
    "sg:postcode":"44044",
    "sg:province":"OH",
    "sg:tags":[
        "basket",
        "parcel"
    ],
    "wof:name":"Basket & Gift Shop",
    "wof:placetype":"venue"
},
  "geometry": {"coordinates":[-82.001203,41.324318],"type":"Point"}
}