{
  "type": "Feature",
  "properties": {
    "addr:full":"34738 Vine St Willowick OH 44095",
    "addr:housenumber":"34738",
    "addr:postcode":"44095",
    "addr:street":"Vine St",
    "iso:country":"US",
    "sg:address":"34738 Vine St",
    "sg:city":"Willowick",
    "sg:classifiers":[
        {
            "category":"Banks & Credit Unions",
            "subcategory":"Bank",
            "type":"Services"
        }
    ],
    "sg:phone":"+1 440 918 9585",
    "sg:postcode":"44095",
    "sg:province":"OH",
    "sg:tags":[
        "cashing",
        "personal",
        "check",
        "institution"
    ],
    "wof:name":"Advance America",
    "wof:placetype":"venue"
},
  "geometry": {"coordinates":[-81.441277,41.642465],"type":"Point"}
}