{
  "type": "Feature",
  "properties": {
    "addr:full": "2329 W Broad St Columbus OH 43204",
    "addr:housenumber": "2329",
    "addr:postcode": "43204",
    "addr:street": "W Broad St",
    "iso:country": "US",
    "sg:address": "2329 W Broad St",
    "sg:city": "Columbus",
    "sg:classifiers": [
      {
        "category": "Bars \u0026 Pubs",
        "type": "Food \u0026 Drink"
      }
    ],
    "sg:phone": "+1 614 272 9228",
    "sg:postcode": "43204",
    "sg:province": "OH",
    "wof:name": "Eddie's",
    "wof:placetype": "venue"
  },
  "geometry": {"coordinates":[-83.062435,39.955428],"type":"Point"}
}
