{
  "type": "Feature",
  "properties": {
    "addr:full": "30347 Clinton St Hanoverton OH 44423",
    "addr:housenumber": "30347",
    "addr:postcode": "44423",
    "addr:street": "Clinton St",
    "iso:country": "US",
    "sg:address": "30347 Clinton St",
    "sg:city": "Hanoverton",
    "sg:classifiers": [
      {
        "category": "Wholesale",
        "subcategory": "Scrap",
        "type": "Manufacturing \u0026 Wholesale Goods"
      }
    ],
    "sg:phone": "+1 330 223 2291",
    "sg:postcode": "44423",
    "sg:province": "OH",
    "sg:tags": [
      "specializing",
      "brokerage",
      "company",
      "metal"
    ],
    "wof:name": "BBC Company",
    "wof:placetype": "venue"
  },
  "geometry": {"coordinates":[-80.930977,40.75588],"type":"Point"}
}
