{
  "type": "Feature",
  "properties": {
    "addr:full":"2601 Harrison Ave Cincinnati OH 45211",
    "addr:housenumber":"2601",
    "addr:postcode":"45211",
    "addr:street":"Harrison Ave",
    "iso:country":"US",
    "sg:address":"2601 Harrison Ave",
    "sg:city":"Cincinnati",
    "sg:classifiers":[
        {
            "category":"Social Services",
            "subcategory":"Child Care",
            "type":"Services"
        }
    ],
    "sg:phone":"+1 513 662 8101",
    "sg:postcode":"45211",
    "sg:province":"OH",
    "wof:name":"Cinti Pre-School",
    "wof:placetype":"venue"
},
  "geometry": {"coordinates":[-84.589062,39.14134],"type":"Point"}
}