{
  "type": "Feature",
  "properties": {
    "iso:country":"US",
    "sg:address":"4533 Floyd Dr",
    "sg:city":"Columbus",
    "sg:classifiers":[
        {
            "category":"Building & Trades",
            "subcategory":"Construction",
            "type":"Services"
        }
    ],
    "sg:phone":"+1 614 837 1817",
    "sg:postcode":"43232",
    "sg:province":"OH",
    "sg:tags":[
        "contractor"
    ],
    "wof:name":"Horn Masonry",
    "wof:placetype":"venue"
},
  "geometry": {"coordinates":[-82.881716,39.908893],"type":"Point"}
}