{
  "type": "Feature",
  "properties": {
    "iso:country":"US",
    "sg:address":"4960 Springboro Pike",
    "sg:city":"Dayton",
    "sg:classifiers":[
        {
            "category":"Shopping",
            "subcategory":"Jewelry",
            "type":"Retail Goods"
        }
    ],
    "sg:phone":"+1 937 297 9111",
    "sg:postcode":"45439",
    "sg:province":"OH",
    "sg:tags":[
        "jeweler"
    ],
    "wof:name":"Jewelry & Gem Exchange",
    "wof:placetype":"venue"
},
  "geometry": {"coordinates":[-84.220455,39.688716],"type":"Point"}
}