{
  "type": "Feature",
  "properties": {
    "addr:full":"2614 Lagrange St Toledo OH 43608",
    "addr:housenumber":"2614",
    "addr:postcode":"43608",
    "addr:street":"Lagrange St",
    "iso:country":"US",
    "sg:address":"2614 Lagrange St",
    "sg:city":"Toledo",
    "sg:classifiers":[
        {
            "category":"Real Estate",
            "subcategory":"Real Estate Agent",
            "type":"Services"
        }
    ],
    "sg:phone":"+1 419 242 3819",
    "sg:postcode":"43608",
    "sg:province":"OH",
    "sg:tags":[
        "agency",
        "rental"
    ],
    "wof:name":"South Broadway Rentals LTD",
    "wof:placetype":"venue"
},
  "geometry": {"coordinates":[-83.537862,41.672721],"type":"Point"}
}