{
  "type": "Feature",
  "properties": {
    "addr:full": "5636 W Central Ave Toledo OH 43615",
    "addr:housenumber": "5636",
    "addr:postcode": "43615",
    "addr:street": "W Central Ave",
    "iso:country": "US",
    "sg:address": "5636 W Central Ave",
    "sg:city": "Toledo",
    "sg:classifiers": [
      {
        "category": "Retail",
        "subcategory": "Animal Services",
        "type": "Services"
      }
    ],
    "sg:phone": "+1 419 531 7387",
    "sg:postcode": "43615",
    "sg:province": "OH",
    "wof:name": "Grr \u0026 Purr Grooming Shop",
    "wof:placetype": "venue"
  },
  "geometry": {"coordinates":[-83.676262,41.676592],"type":"Point"}
}
