{
  "type": "Feature",
  "properties": {
    "iso:country":"US",
    "sg:address":"5636 W Central Ave",
    "sg:city":"Toledo",
    "sg:classifiers":[
        {
            "category":"Retail",
            "subcategory":"Animal Services",
            "type":"Services"
        }
    ],
    "sg:phone":"+1 419 531 7387",
    "sg:postcode":"43615",
    "sg:province":"OH",
    "wof:name":"Grr & Purr Grooming Shop",
    "wof:placetype":"venue"
},
  "geometry": {"coordinates":[-83.676262,41.676592],"type":"Point"}
}