{
  "type": "Feature",
  "properties": {
    "addr:full": "1703 Yellow Rose Ct Fairborn OH 45324",
    "addr:housenumber": "1703",
    "addr:postcode": "45324",
    "addr:street": "Yellow Rose Ct",
    "iso:country": "US",
    "sg:address": "1703 Yellow Rose Ct",
    "sg:city": "Fairborn",
    "sg:classifiers": [
      {
        "category": "Professional",
        "type": "Services"
      }
    ],
    "sg:phone": "+1 937 879 7600",
    "sg:postcode": "45324",
    "sg:province": "OH",
    "sg:tags": [
      "establishment"
    ],
    "wof:name": "Deagle-Anderson",
    "wof:placetype": "venue"
  },
  "geometry": {"coordinates":[-83.989714,39.791377],"type":"Point"}
}
