{
  "type": "Feature",
  "properties": {
    "addr:full": "103 S Diamond St Mansfield OH 44902",
    "addr:housenumber": "103",
    "addr:postcode": "44902",
    "addr:street": "S Diamond St",
    "iso:country": "US",
    "sg:address": "103 S Diamond St",
    "sg:city": "Mansfield",
    "sg:classifiers": [
      {
        "category": "Professional",
        "subcategory": "Accounting \u0026 Tax Preparation",
        "type": "Services"
      }
    ],
    "sg:phone": "+1 419 525 1515",
    "sg:postcode": "44902",
    "sg:province": "OH",
    "sg:tags": [
      "accountant"
    ],
    "wof:name": "Interstate Plaza Consultants",
    "wof:placetype": "venue"
  },
  "geometry": {"coordinates":[-82.51421,40.755924],"type":"Point"}
}
