{
  "type": "Feature",
  "properties": {
    "addr:full": "13422 Back Massillon Rd Orrville OH 44667",
    "addr:housenumber": "13422",
    "addr:postcode": "44667",
    "addr:street": "Back Massillon Rd",
    "iso:country": "US",
    "sg:address": "13422 Back Massillon Rd",
    "sg:city": "Orrville",
    "sg:classifiers": [
      {
        "category": "Utilities",
        "type": "Services"
      }
    ],
    "sg:phone": "+1 330 683 5296",
    "sg:postcode": "44667",
    "sg:province": "OH",
    "sg:tags": [
      "sanitary"
    ],
    "wof:name": "Brent R Kornhaus",
    "wof:placetype": "venue"
  },
  "geometry": {"coordinates":[-81.742503,40.873831],"type":"Point"}
}
