{
  "type": "Feature",
  "properties": {
    "iso:country":"US",
    "sg:address":"7800 Plaza Blvd",
    "sg:city":"Mentor",
    "sg:classifiers":[
        {
            "category":"Restaurant",
            "type":"Food & Drink"
        }
    ],
    "sg:menulink":"http://www.allmenus.com/oh/mentor/109419-village-inn/menu/",
    "sg:phone":"+1 440 255 6960",
    "sg:postcode":"44060",
    "sg:province":"OH",
    "sg:tags":[
        "new",
        "american"
    ],
    "wof:name":"Village Inn",
    "wof:placetype":"venue"
},
  "geometry": {"coordinates":[-81.364929,41.65821],"type":"Point"}
}