{
  "type": "Feature",
  "properties": {
    "addr:full": "3415 Paxton Ave Cincinnati OH 45208",
    "addr:housenumber": "3415",
    "addr:postcode": "45208",
    "addr:street": "Paxton Ave",
    "iso:country": "US",
    "sg:address": "3415 Paxton Ave",
    "sg:city": "Cincinnati",
    "sg:classifiers": [
      {
        "category": "Shopping",
        "subcategory": "Computers \u0026 Home Electronics",
        "type": "Retail Goods"
      }
    ],
    "sg:phone": "+1 513 871 7922",
    "sg:postcode": "45208",
    "sg:province": "OH",
    "wof:name": "Cranel Inc",
    "wof:placetype": "venue"
  },
  "geometry": {"coordinates":[-84.434056,39.138469],"type":"Point"}
}
