{
  "type": "Feature",
  "properties": {
    "addr:full": "14 E Liberty St Cincinnati OH 45202",
    "addr:housenumber": "14",
    "addr:postcode": "45202",
    "addr:street": "E Liberty St",
    "iso:country": "US",
    "sg:address": "14 E Liberty St",
    "sg:city": "Cincinnati",
    "sg:classifiers": [
      {
        "category": "Organizations",
        "subcategory": "Religious Organization",
        "type": "Services"
      }
    ],
    "sg:phone": "+1 513 421 2547",
    "sg:postcode": "45202",
    "sg:province": "OH",
    "sg:tags": [
      "church"
    ],
    "wof:name": "St Francis Soup Kitchen",
    "wof:placetype": "venue"
  },
  "geometry": {"coordinates":[-84.515062,39.112798],"type":"Point"}
}
