{
  "type": "Feature",
  "properties": {
    "iso:country":"US",
    "sg:address":"615 Elsinore Pl",
    "sg:city":"Cincinnati",
    "sg:classifiers":[
        {
            "category":"Professional",
            "type":"Services"
        }
    ],
    "sg:phone":"+1 513 651 0534",
    "sg:postcode":"45202",
    "sg:province":"OH",
    "sg:tags":[
        "establishment"
    ],
    "wof:name":"Jancoa Inc",
    "wof:placetype":"venue"
},
  "geometry": {"coordinates":[-84.50219300000001,39.113101],"type":"Point"}
}