{
  "type": "Feature",
  "properties": {
    "addr:full": "431 Ohio Pike Cincinnati OH 45255",
    "addr:housenumber": "431",
    "addr:postcode": "45255",
    "addr:street": "Ohio Pike",
    "iso:country": "US",
    "sg:address": "431 Ohio Pike",
    "sg:city": "Cincinnati",
    "sg:classifiers": [
      {
        "category": "Banks \u0026 Credit Unions",
        "subcategory": "Investment Brokerage",
        "type": "Services"
      }
    ],
    "sg:phone": "+1 513 688 7444",
    "sg:postcode": "45255",
    "sg:province": "OH",
    "sg:tags": [
      "advisory",
      "insurance"
    ],
    "wof:name": "Southport Advisors Inc",
    "wof:placetype": "venue"
  },
  "geometry": {"coordinates":[-84.312439,39.071722],"type":"Point"}
}
