{
  "type": "Feature",
  "properties": {
    "iso:country":"US",
    "sg:address":"2999 Dublin Arbor Ln",
    "sg:city":"Dublin",
    "sg:classifiers":[
        {
            "category":"Wholesale",
            "subcategory":"Durable Goods & Equipment",
            "type":"Manufacturing & Wholesale Goods"
        }
    ],
    "sg:phone":"+1 614 799 6177",
    "sg:postcode":"43017",
    "sg:province":"OH",
    "sg:tags":[
        "representative",
        "manufacturer"
    ],
    "wof:name":"Stephen D Esses",
    "wof:placetype":"venue"
},
  "geometry": {"coordinates":[-83.097143,40.091105],"type":"Point"}
}