{
  "type": "Feature",
  "properties": {
    "addr:full": "2999 Dublin Arbor Ln Dublin OH 43017",
    "addr:housenumber": "2999",
    "addr:postcode": "43017",
    "addr:street": "Dublin Arbor Ln",
    "iso:country": "US",
    "sg:address": "2999 Dublin Arbor Ln",
    "sg:city": "Dublin",
    "sg:classifiers": [
      {
        "category": "Wholesale",
        "subcategory": "Durable Goods \u0026 Equipment",
        "type": "Manufacturing \u0026 Wholesale Goods"
      }
    ],
    "sg:phone": "+1 614 799 6177",
    "sg:postcode": "43017",
    "sg:province": "OH",
    "sg:tags": [
      "representative",
      "manufacturer"
    ],
    "wof:name": "Stephen D Esses",
    "wof:placetype": "venue"
  },
  "geometry": {"coordinates":[-83.097143,40.091105],"type":"Point"}
}
