{
  "type": "Feature",
  "properties": {
    "iso:country":"US",
    "sg:address":"172 Woodrow Ave",
    "sg:city":"Cleveland",
    "sg:classifiers":[
        {
            "category":"Wholesale",
            "subcategory":"Durable Goods & Equipment",
            "type":"Manufacturing & Wholesale Goods"
        }
    ],
    "sg:phone":"+1 440 439 7263",
    "sg:postcode":"44146",
    "sg:province":"OH",
    "sg:tags":[
        "representative",
        "manufacturer"
    ],
    "wof:name":"Culver Sales Co",
    "wof:placetype":"venue"
},
  "geometry": {"coordinates":[-81.529645,41.393979],"type":"Point"}
}