{
  "type": "Feature",
  "properties": {
    "iso:country":"US",
    "sg:address":"62 S Main St",
    "sg:city":"Poland",
    "sg:classifiers":[
        {
            "category":"Professional",
            "subcategory":"Lawyer & Legal Services",
            "type":"Services"
        }
    ],
    "sg:phone":"+1 330 707 0377",
    "sg:postcode":"44514",
    "sg:province":"OH",
    "sg:tags":[
        "attorney"
    ],
    "wof:name":"Amy L Higgins",
    "wof:placetype":"venue"
},
  "geometry": {"coordinates":[-80.614546,41.024141],"type":"Point"}
}