{
  "type": "Feature",
  "properties": {
    "iso:country":"US",
    "sg:address":"11620 Lebanon Rd",
    "sg:city":"Cincinnati",
    "sg:classifiers":[
        {
            "category":"Restaurant",
            "type":"Food & Drink"
        }
    ],
    "sg:menulink":"http://www.allmenus.com/oh/sharonville/162912-rallys/menu/",
    "sg:phone":"+1 513 563 4656",
    "sg:postcode":"45241",
    "sg:province":"OH",
    "sg:tags":[
        "sandwich",
        "dog",
        "burger",
        "hot",
        "wrap",
        "american"
    ],
    "wof:name":"Rally's",
    "wof:placetype":"venue"
},
  "geometry": {"coordinates":[-84.400567,39.283505],"type":"Point"}
}