{
  "type": "Feature",
  "properties": {
    "iso:country":"US",
    "sg:address":"6504 Ridgewood Lakes Dr",
    "sg:city":"Cleveland",
    "sg:classifiers":[
        {
            "category":"Organizations",
            "subcategory":"Religious Organization",
            "type":"Services"
        }
    ],
    "sg:phone":"+1 440 888 2229",
    "sg:postcode":"44129",
    "sg:province":"OH",
    "sg:tags":[
        "clergy"
    ],
    "wof:name":"Erhard Knull",
    "wof:placetype":"venue"
},
  "geometry": {"coordinates":[-81.73584200000001,41.387302],"type":"Point"}
}