{
  "type": "Feature",
  "properties": {
    "addr:full":"4161 Bridgewater Pkwy Stow OH 44224",
    "addr:housenumber":"4161",
    "addr:postcode":"44224",
    "addr:street":"Bridgewater Pkwy",
    "iso:country":"US",
    "sg:address":"4161 Bridgewater Pkwy",
    "sg:city":"Stow",
    "sg:classifiers":[
        {
            "category":"Manufacturing",
            "subcategory":"Tools & Machinery",
            "type":"Manufacturing & Wholesale Goods"
        }
    ],
    "sg:phone":"+1 330 920 3770",
    "sg:postcode":"44224",
    "sg:province":"OH",
    "sg:tags":[
        "laboratory",
        "medical",
        "devices",
        "mfg"
    ],
    "wof:name":"Imaging Center",
    "wof:placetype":"venue"
},
  "geometry": {"coordinates":[-81.480777,41.179354],"type":"Point"}
}