{
  "type": "Feature",
  "properties": {
    "iso:country":"US",
    "sg:address":"2065 Newark Rd",
    "sg:city":"Zanesville",
    "sg:classifiers":[
        {
            "category":"Professional",
            "type":"Services"
        }
    ],
    "sg:phone":"+1 740 452 0844",
    "sg:postcode":"43701",
    "sg:province":"OH",
    "wof:name":"Nicholas A Berelsman",
    "wof:placetype":"venue"
},
  "geometry": {"coordinates":[-82.045117,39.964214],"type":"Point"}
}