{
  "type": "Feature",
  "properties": {
    "addr:full": "12423 Saint Clair Ave Cleveland OH 44108",
    "addr:housenumber": "12423",
    "addr:postcode": "44108",
    "addr:street": "Saint Clair Ave",
    "iso:country": "US",
    "sg:address": "12423 Saint Clair Ave",
    "sg:city": "Cleveland",
    "sg:classifiers": [
      {
        "category": "Personal",
        "subcategory": "Beauty Salon",
        "type": "Services"
      }
    ],
    "sg:phone": "+1 216 761 0920",
    "sg:postcode": "44108",
    "sg:province": "OH",
    "wof:name": "Projections Beauty Salon",
    "wof:placetype": "venue"
  },
  "geometry": {"coordinates":[-81.597664,41.541402],"type":"Point"}
}
