{
  "type": "Feature",
  "properties": {
    "addr:full": "1452 Courter St Dayton OH 45427",
    "addr:housenumber": "1452",
    "addr:postcode": "45427",
    "addr:street": "Courter St",
    "iso:country": "US",
    "sg:address": "1452 Courter St",
    "sg:city": "Dayton",
    "sg:classifiers": [
      {
        "category": "Insurance",
        "subcategory": "Insurance Agent",
        "type": "Services"
      }
    ],
    "sg:phone": "+1 937 274 9214",
    "sg:postcode": "45427",
    "sg:province": "OH",
    "wof:name": "American Family Insurance",
    "wof:placetype": "venue"
  },
  "geometry": {"coordinates":[-84.271657,39.770036],"type":"Point"}
}
