{
  "type": "Feature",
  "properties": {
    "iso:country":"US",
    "sg:address":"1452 Courter St",
    "sg:city":"Dayton",
    "sg:classifiers":[
        {
            "category":"Insurance",
            "subcategory":"Insurance Agent",
            "type":"Services"
        }
    ],
    "sg:phone":"+1 937 274 9214",
    "sg:postcode":"45427",
    "sg:province":"OH",
    "wof:name":"American Family Insurance",
    "wof:placetype":"venue"
},
  "geometry": {"coordinates":[-84.271657,39.770036],"type":"Point"}
}