{
  "type": "Feature",
  "properties": {
    "addr:full": "13967 Cedar Rd Cleveland OH 44118",
    "addr:housenumber": "13967",
    "addr:postcode": "44118",
    "addr:street": "Cedar Rd",
    "iso:country": "US",
    "sg:address": "13967 Cedar Rd",
    "sg:city": "Cleveland",
    "sg:classifiers": [
      {
        "category": "Organizations",
        "subcategory": "Religious Organization",
        "type": "Services"
      }
    ],
    "sg:phone": "+1 216 932 0206",
    "sg:postcode": "44118",
    "sg:province": "OH",
    "sg:tags": [
      "synagogue"
    ],
    "wof:name": "Sinai Synagogue",
    "wof:placetype": "venue"
  },
  "geometry": {"coordinates":[-81.53738,41.501356],"type":"Point"}
}
