{
  "type": "Feature",
  "properties": {
    "addr:full":"8001 Rockside Rd Cleveland OH 44125",
    "addr:housenumber":"8001",
    "addr:postcode":"44125",
    "addr:street":"Rockside Rd",
    "iso:country":"US",
    "sg:address":"8001 Rockside Rd",
    "sg:city":"Cleveland",
    "sg:phone":"+1 216 524 9404",
    "sg:postcode":"44125",
    "sg:province":"OH",
    "wof:name":"Lockkeepers",
    "wof:placetype":"venue"
},
  "geometry": {"coordinates":[-81.626633,41.393581],"type":"Point"}
}