{
  "type": "Feature",
  "properties": {
    "addr:full":"33 W Kemper Rd Cincinnati OH 45246",
    "addr:housenumber":"33",
    "addr:postcode":"45246",
    "addr:street":"W Kemper Rd",
    "iso:country":"US",
    "sg:address":"33 W Kemper Rd",
    "sg:city":"Cincinnati",
    "sg:classifiers":[
        {
            "category":"Autos & Motor Vehicles",
            "subcategory":"Automobile Sales",
            "type":"Retail Goods"
        }
    ],
    "sg:phone":"+1 513 782 2829",
    "sg:postcode":"45246",
    "sg:province":"OH",
    "sg:tags":[
        "new",
        "used",
        "car"
    ],
    "sg:website":"http://jakesweeney.com",
    "wof:name":"Jake Sweeney Chevrolet Mazda BMW Parts",
    "wof:placetype":"venue"
},
  "geometry": {"coordinates":[-84.468267,39.287933],"type":"Point"}
}