{
  "type": "Feature",
  "properties": {
    "iso:country":"US",
    "sg:address":"4627 Brookstone Ct",
    "sg:city":"Brunswick",
    "sg:classifiers":[
        {
            "category":"Building & Trades",
            "subcategory":"Construction",
            "type":"Services"
        }
    ],
    "sg:phone":"+1 330 273 3843",
    "sg:postcode":"44212",
    "sg:province":"OH",
    "sg:tags":[
        "house"
    ],
    "wof:name":"Lee Kar Services",
    "wof:placetype":"venue"
},
  "geometry": {"coordinates":[-81.853296,41.264158],"type":"Point"}
}