{
  "type": "Feature",
  "properties": {
    "addr:full": "6476 Shenandoah Ave NW Canton OH 44718",
    "addr:housenumber": "6476",
    "addr:postcode": "44718",
    "addr:street": "Shenandoah Ave Nw",
    "iso:country": "US",
    "sg:address": "6476 Shenandoah Ave NW",
    "sg:city": "Canton",
    "sg:classifiers": [
      {
        "category": "Manufacturing",
        "subcategory": "Metals",
        "type": "Manufacturing \u0026 Wholesale Goods"
      }
    ],
    "sg:phone": "+1 330 244 2905",
    "sg:postcode": "44718",
    "sg:province": "OH",
    "sg:tags": [
      "steel"
    ],
    "wof:name": "Wheeling Corrugating Co",
    "wof:placetype": "venue"
  },
  "geometry": {"coordinates":[-81.476205,40.874603],"type":"Point"}
}
