{
  "type": "Feature",
  "properties": {
    "addr:full": "17232 Sand Ridge Rd Weston OH 43569",
    "addr:housenumber": "17232",
    "addr:postcode": "43569",
    "addr:street": "Sand Ridge Rd",
    "iso:country": "US",
    "sg:address": "17232 Sand Ridge Rd",
    "sg:city": "Weston",
    "sg:phone": "+1 419 669 2598",
    "sg:postcode": "43569",
    "sg:province": "OH",
    "sg:tags": [
      "farm",
      "corn",
      "wheat",
      "soybean"
    ],
    "wof:name": "Dale Limes",
    "wof:placetype": "venue"
  },
  "geometry": {"coordinates":[-83.731393,41.3474],"type":"Point"}
}
