{
  "type": "Feature",
  "properties": {
    "iso:country":"US",
    "sg:address":"17232 Sand Ridge Rd",
    "sg:city":"Weston",
    "sg:phone":"+1 419 669 2598",
    "sg:postcode":"43569",
    "sg:province":"OH",
    "sg:tags":[
        "farm",
        "corn",
        "wheat",
        "soybean"
    ],
    "wof:name":"Dale Limes",
    "wof:placetype":"venue"
},
  "geometry": {"coordinates":[-83.731393,41.3474],"type":"Point"}
}