{
  "type": "Feature",
  "properties": {
    "iso:country":"US",
    "sg:address":"17106 Park Dr",
    "sg:city":"Chagrin Falls",
    "sg:classifiers":[
        {
            "category":"Shopping",
            "subcategory":"Computers & Home Electronics",
            "type":"Retail Goods"
        }
    ],
    "sg:phone":"+1 440 543 1325",
    "sg:postcode":"44023",
    "sg:province":"OH",
    "sg:tags":[
        "sales"
    ],
    "wof:name":"Computer Experience",
    "wof:placetype":"venue"
},
  "geometry": {"coordinates":[-81.345398,41.403279],"type":"Point"}
}