{
  "type": "Feature",
  "properties": {
    "addr:full": "1606 McDonough St Sandusky OH 44870",
    "addr:housenumber": "1606",
    "addr:postcode": "44870",
    "addr:street": "Mcdonough St",
    "iso:country": "US",
    "sg:address": "1606 McDonough St",
    "sg:city": "Sandusky",
    "sg:classifiers": [
      {
        "category": "Shopping",
        "type": "Retail Goods"
      }
    ],
    "sg:phone": "+1 419 626 6745",
    "sg:postcode": "44870",
    "sg:province": "OH",
    "sg:tags": [
      "merchandise"
    ],
    "wof:name": "Alarmtec Security Systems",
    "wof:placetype": "venue"
  },
  "geometry": {"coordinates":[-82.715569,41.441469],"type":"Point"}
}
