{
  "type": "Feature",
  "properties": {
    "iso:country":"US",
    "sg:address":"6262 Seeds Rd",
    "sg:city":"Grove City",
    "sg:classifiers":[
        {
            "category":"Wholesale",
            "subcategory":"Electrical",
            "type":"Manufacturing & Wholesale Goods"
        }
    ],
    "sg:phone":"+1 614 539 5035",
    "sg:postcode":"43123",
    "sg:province":"OH",
    "sg:tags":[
        "battery",
        "repairing",
        "rebuilding"
    ],
    "wof:name":"Battery Power Systems Inc",
    "wof:placetype":"venue"
},
  "geometry": {"coordinates":[-83.091747,39.837277],"type":"Point"}
}