{
  "type": "Feature",
  "properties": {
    "addr:full": "6249 Dunlap Rd Hillsboro OH 45133",
    "addr:housenumber": "6249",
    "addr:postcode": "45133",
    "addr:street": "Dunlap Rd",
    "iso:country": "US",
    "sg:address": "6249 Dunlap Rd",
    "sg:city": "Hillsboro",
    "sg:classifiers": [
      {
        "category": "Building \u0026 Trades",
        "subcategory": "Construction",
        "type": "Services"
      }
    ],
    "sg:phone": "+1 937 393 0700",
    "sg:postcode": "45133",
    "sg:province": "OH",
    "sg:tags": [
      "excavating",
      "contractor"
    ],
    "wof:name": "Wright Excavating",
    "wof:placetype": "venue"
  },
  "geometry": {"coordinates":[-83.62102,39.183778],"type":"Point"}
}
