{
  "type": "Feature",
  "properties": {
    "iso:country":"US",
    "sg:address":"6249 Dunlap Rd",
    "sg:city":"Hillsboro",
    "sg:classifiers":[
        {
            "category":"Building & Trades",
            "subcategory":"Construction",
            "type":"Services"
        }
    ],
    "sg:phone":"+1 937 393 0700",
    "sg:postcode":"45133",
    "sg:province":"OH",
    "sg:tags":[
        "excavating",
        "contractor"
    ],
    "wof:name":"Wright Excavating",
    "wof:placetype":"venue"
},
  "geometry": {"coordinates":[-83.62102,39.183778],"type":"Point"}
}