{
  "type": "Feature",
  "properties": {
    "iso:country":"US",
    "sg:address":"4650 Coolbrook Dr",
    "sg:city":"Hilliard",
    "sg:classifiers":[
        {
            "category":"Banks & Credit Unions",
            "subcategory":"Financial Services",
            "type":"Services"
        }
    ],
    "sg:phone":"+1 614 771 1751",
    "sg:postcode":"43026",
    "sg:province":"OH",
    "sg:tags":[
        "investor"
    ],
    "wof:name":"Cowtown Investment Club",
    "wof:placetype":"venue"
},
  "geometry": {"coordinates":[-83.112349,40.049728],"type":"Point"}
}