{
  "type": "Feature",
  "properties": {
    "addr:full": "6444 Monroe St Sylvania OH 43560",
    "addr:housenumber": "6444",
    "addr:postcode": "43560",
    "addr:street": "Monroe St",
    "iso:country": "US",
    "sg:address": "6444 Monroe St",
    "sg:city": "Sylvania",
    "sg:classifiers": [
      {
        "category": "Health Services",
        "subcategory": "Doctor",
        "type": "Services"
      }
    ],
    "sg:phone": "+1 419 885 2553",
    "sg:postcode": "43560",
    "sg:province": "OH",
    "sg:tags": [
      "physician",
      "surgeon",
      "medical"
    ],
    "wof:name": "Northwest Ohio Orthopedics",
    "wof:placetype": "venue"
  },
  "geometry": {"coordinates":[-83.701315,41.715623],"type":"Point"}
}
