{
  "type": "Feature",
  "properties": {
    "addr:full":"134 2nd St NW New Philadelphia OH 44663",
    "addr:housenumber":"134",
    "addr:postcode":"44663",
    "addr:street":"2Nd St Nw New Philadelphia",
    "iso:country":"US",
    "sg:address":"134 2nd St NW",
    "sg:city":"New Philadelphia",
    "sg:classifiers":[
        {
            "category":"Building & Trades",
            "subcategory":"Construction",
            "type":"Services"
        }
    ],
    "sg:phone":"+1 330 364 1112",
    "sg:postcode":"44663",
    "sg:province":"OH",
    "sg:tags":[
        "excavation",
        "contractor"
    ],
    "wof:name":"Wagner Excavating LLC",
    "wof:placetype":"venue"
},
  "geometry": {"coordinates":[-81.447388,40.491594],"type":"Point"}
}