{
  "type": "Feature",
  "properties": {
    "addr:full":"843 N 21st St Newark OH 43055",
    "addr:housenumber":"843",
    "addr:postcode":"43055",
    "addr:street":"N 21St St",
    "iso:country":"US",
    "sg:address":"843 N 21st St",
    "sg:city":"Newark",
    "sg:classifiers":[
        {
            "category":"Banks & Credit Unions",
            "subcategory":"Investment Brokerage",
            "type":"Services"
        }
    ],
    "sg:phone":"+1 740 349 9191",
    "sg:postcode":"43055",
    "sg:province":"OH",
    "sg:tags":[
        "security"
    ],
    "wof:name":"Edward Jones 14460",
    "wof:placetype":"venue"
},
  "geometry": {"coordinates":[-82.428854,40.071432],"type":"Point"}
}