{
  "type": "Feature",
  "properties": {
    "addr:full": "31099 Miles Rd Chagrin Falls OH 44022",
    "addr:housenumber": "31099",
    "addr:postcode": "44022",
    "addr:street": "Miles Rd",
    "iso:country": "US",
    "sg:address": "31099 Miles Rd",
    "sg:city": "Chagrin Falls",
    "sg:classifiers": [
      {
        "category": "Building \u0026 Trades",
        "subcategory": "Construction",
        "type": "Services"
      }
    ],
    "sg:phone": "+1 216 789 2252",
    "sg:postcode": "44022",
    "sg:province": "OH",
    "sg:tags": [
      "concrete",
      "contractor"
    ],
    "wof:name": "Three V Cement",
    "wof:placetype": "venue"
  },
  "geometry": {"coordinates":[-81.460481,41.424525],"type":"Point"}
}
