{
  "type": "Feature",
  "properties": {
    "iso:country":"US",
    "sg:address":"5965 E Broad St",
    "sg:city":"Columbus",
    "sg:classifiers":[
        {
            "category":"Health Services",
            "subcategory":"Doctor",
            "type":"Services"
        }
    ],
    "sg:phone":"+1 614 234 2900",
    "sg:postcode":"43213",
    "sg:province":"OH",
    "wof:name":"Mt Carmel Women's Health Ctr",
    "wof:placetype":"venue"
},
  "geometry": {"coordinates":[-82.845479,39.978888],"type":"Point"}
}