{
  "type": "Feature",
  "properties": {
    "addr:full": "37400 N Industrial Pkwy Willoughby OH 44094",
    "addr:housenumber": "37400",
    "addr:postcode": "44094",
    "addr:street": "N Industrial Pkwy",
    "iso:country": "US",
    "sg:address": "37400 N Industrial Pkwy",
    "sg:city": "Willoughby",
    "sg:classifiers": [
      {
        "category": "Utilities",
        "subcategory": "Sewage",
        "type": "Services"
      }
    ],
    "sg:phone": "+1 440 953 4111",
    "sg:postcode": "44094",
    "sg:province": "OH",
    "sg:tags": [
      "system",
      "sewerage"
    ],
    "wof:name": "Sewer Department",
    "wof:placetype": "venue"
  },
  "geometry": {"coordinates":[-81.413418,41.642168],"type":"Point"}
}
