{
  "type": "Feature",
  "properties": {
    "addr:full":"2022 Worth Ave Cincinnati OH 45212",
    "addr:housenumber":"2022",
    "addr:postcode":"45212",
    "addr:street":"Worth Ave",
    "iso:country":"US",
    "sg:address":"2022 Worth Ave",
    "sg:city":"Cincinnati",
    "sg:classifiers":[
        {
            "category":"Food & Beverages",
            "subcategory":"Groceries & Convenience Stores",
            "type":"Retail Goods"
        }
    ],
    "sg:phone":"+1 513 631 7536",
    "sg:postcode":"45212",
    "sg:province":"OH",
    "wof:name":"Thrifty Food Market",
    "wof:placetype":"venue"
},
  "geometry": {"coordinates":[-84.457752,39.173873],"type":"Point"}
}