{
  "type": "Feature",
  "properties": {
    "addr:full": "77 Mercerville Rd Crown City OH 45623",
    "addr:housenumber": "77",
    "addr:postcode": "45623",
    "addr:street": "Mercerville Rd",
    "iso:country": "US",
    "sg:address": "77 Mercerville Rd",
    "sg:city": "Crown City",
    "sg:classifiers": [
      {
        "category": "Shopping",
        "subcategory": "Computers \u0026 Home Electronics",
        "type": "Retail Goods"
      }
    ],
    "sg:phone": "+1 740 256 6156",
    "sg:postcode": "45623",
    "sg:province": "OH",
    "sg:tags": [
      "equipment",
      "satellite",
      "system"
    ],
    "wof:name": "Tri State Installers",
    "wof:placetype": "venue"
  },
  "geometry": {"coordinates":[-82.272837,38.661375],"type":"Point"}
}
