{
  "type": "Feature",
  "properties": {
    "addr:full": "3236 Cherry St Toledo OH 43608",
    "addr:housenumber": "3236",
    "addr:postcode": "43608",
    "addr:street": "Cherry St",
    "iso:country": "US",
    "sg:address": "3236 Cherry St",
    "sg:city": "Toledo",
    "sg:classifiers": [
      {
        "category": "Shopping",
        "type": "Retail Goods"
      }
    ],
    "sg:phone": "+1 419 255 7327",
    "sg:postcode": "43608",
    "sg:province": "OH",
    "sg:tags": [
      "repair",
      "merchandise"
    ],
    "wof:name": "Kc CB Sales",
    "wof:placetype": "venue"
  },
  "geometry": {"coordinates":[-83.55297,41.681756],"type":"Point"}
}
