{
  "type": "Feature",
  "properties": {
    "addr:full": "125 Meadowpark Dr Cambridge OH 43725",
    "addr:housenumber": "125",
    "addr:postcode": "43725",
    "addr:street": "Meadowpark Dr",
    "iso:country": "US",
    "sg:address": "125 Meadowpark Dr",
    "sg:city": "Cambridge",
    "sg:classifiers": [
      {
        "category": "Organizations",
        "subcategory": "Religious Organization",
        "type": "Services"
      }
    ],
    "sg:phone": "+1 740 432 7680",
    "sg:postcode": "43725",
    "sg:province": "OH",
    "sg:tags": [
      "church"
    ],
    "wof:name": "Cambridge Bible Church",
    "wof:placetype": "venue"
  },
  "geometry": {"coordinates":[-81.618952,40.017219],"type":"Point"}
}
