{
  "type": "Feature",
  "properties": {
    "addr:full": "23 S B St Hamilton IN 45013",
    "addr:housenumber": "23",
    "addr:postcode": "45013",
    "addr:street": "S B",
    "iso:country": "US",
    "sg:address": "23 S B St",
    "sg:city": "Hamilton",
    "sg:classifiers": [
      {
        "category": "Organizations",
        "subcategory": "Religious Organization",
        "type": "Services"
      }
    ],
    "sg:phone": "+1 513 868 0230",
    "sg:postcode": "45013",
    "sg:province": "IN",
    "sg:tags": [
      "church"
    ],
    "wof:name": "Four Square Pentecostal Church",
    "wof:placetype": "venue"
  },
  "geometry": {"coordinates":[-84.567761,39.401862],"type":"Point"}
}
