{
  "type": "Feature",
  "properties": {
    "addr:full": "7750 Jamaica Rd Miamisburg OH 45342",
    "addr:housenumber": "7750",
    "addr:postcode": "45342",
    "addr:street": "Jamaica Rd",
    "iso:country": "US",
    "sg:address": "7750 Jamaica Rd",
    "sg:city": "Miamisburg",
    "sg:classifiers": [
      {
        "category": "Government",
        "subcategory": "Office",
        "type": "Public Place"
      }
    ],
    "sg:phone": "+1 937 384 0299",
    "sg:postcode": "45342",
    "sg:province": "OH",
    "sg:tags": [
      "management"
    ],
    "wof:name": "James Water Proofing",
    "wof:placetype": "venue"
  },
  "geometry": {"coordinates":[-84.32789,39.643113],"type":"Point"}
}
