{
  "type": "Feature",
  "properties": {
    "addr:full":"230 W Huron Rd Cleveland OH 44113",
    "addr:housenumber":"230",
    "addr:postcode":"44113",
    "addr:street":"W Huron Rd",
    "iso:country":"US",
    "sg:address":"230 W Huron Rd",
    "sg:city":"Cleveland",
    "sg:classifiers":[
        {
            "category":"Shopping",
            "subcategory":"Beauty & Cosmetics",
            "type":"Retail Goods"
        }
    ],
    "sg:phone":"+1 216 241 3666",
    "sg:postcode":"44113",
    "sg:province":"OH",
    "sg:tags":[
        "hair",
        "product",
        "skin",
        "care"
    ],
    "wof:name":"Buth-Na-Bodhaige Inc",
    "wof:placetype":"venue"
},
  "geometry": {"coordinates":[-81.694536,41.496868],"type":"Point"}
}