{
  "type": "Feature",
  "properties": {
    "addr:full": "350 Northland Blvd Cincinnati OH 45246",
    "addr:housenumber": "350",
    "addr:postcode": "45246",
    "addr:street": "Northland Blvd",
    "iso:country": "US",
    "sg:address": "350 Northland Blvd",
    "sg:city": "Cincinnati",
    "sg:classifiers": [
      {
        "category": "Food \u0026 Beverages",
        "subcategory": "Liquor \u0026 Beverages",
        "type": "Retail Goods"
      }
    ],
    "sg:phone": "+1 513 771 3419",
    "sg:postcode": "45246",
    "sg:province": "OH",
    "sg:tags": [
      "alcoholic"
    ],
    "wof:name": "T C B",
    "wof:placetype": "venue"
  },
  "geometry": {"coordinates":[-84.495108,39.2817],"type":"Point"}
}
