{
  "type": "Feature",
  "properties": {
    "addr:full":"2831 State Rte 97 Lexington OH 44904",
    "addr:housenumber":"2831",
    "addr:postcode":"44904",
    "addr:street":"State Rte 97",
    "iso:country":"US",
    "sg:address":"2831 State Rte 97",
    "sg:city":"Lexington",
    "sg:classifiers":[
        {
            "category":"Building & Trades",
            "subcategory":"Construction",
            "type":"Services"
        }
    ],
    "sg:phone":"+1 419 884 3828",
    "sg:postcode":"44904",
    "sg:province":"OH",
    "sg:tags":[
        "home",
        "improvement"
    ],
    "wof:name":"Louie Gaul Builders Inc",
    "wof:placetype":"venue"
},
  "geometry": {"coordinates":[-82.613102,40.696078],"type":"Point"}
}