{
  "type": "Feature",
  "properties": {
    "addr:full": "620 Main St Wintersville OH 43953",
    "addr:housenumber": "620",
    "addr:postcode": "43953",
    "addr:street": "Main St",
    "iso:country": "US",
    "sg:address": "620 Main St",
    "sg:city": "Wintersville",
    "sg:classifiers": [
      {
        "category": "Food \u0026 Beverages",
        "subcategory": "Groceries \u0026 Convenience Stores",
        "type": "Retail Goods"
      }
    ],
    "sg:phone": "+1 740 266 2243",
    "sg:postcode": "43953",
    "sg:province": "OH",
    "wof:name": "KWIK King Food Store",
    "wof:placetype": "venue"
  },
  "geometry": {"coordinates":[-80.698192,40.374318],"type":"Point"}
}
