{
  "type": "Feature",
  "properties": {
    "addr:full": "316 Center St Wheelersburg OH 45694",
    "addr:housenumber": "316",
    "addr:postcode": "45694",
    "addr:street": "Center St",
    "iso:country": "US",
    "sg:address": "316 Center St",
    "sg:city": "Wheelersburg",
    "sg:classifiers": [
      {
        "category": "Restaurant",
        "type": "Food \u0026 Drink"
      }
    ],
    "sg:phone": "+1 740 574 8188",
    "sg:postcode": "45694",
    "sg:province": "OH",
    "wof:name": "Wendys",
    "wof:placetype": "venue"
  },
  "geometry": {"coordinates":[-82.861058,38.728947],"type":"Point"}
}
