{
  "type": "Feature",
  "properties": {
    "iso:country":"US",
    "sg:address":"375 S High St",
    "sg:city":"Columbus",
    "sg:classifiers":[
        {
            "category":"Government",
            "subcategory":"Office",
            "type":"Public Place"
        }
    ],
    "sg:phone":"+1 614 645 8204",
    "sg:postcode":"43215",
    "sg:province":"OH",
    "wof:name":"Honorable Steven B Hayes",
    "wof:placetype":"venue"
},
  "geometry": {"coordinates":[-82.999086,39.953877],"type":"Point"}
}