{
  "type": "Feature",
  "properties": {
    "iso:country":"US",
    "sg:address":"14125 Detroit Ave",
    "sg:city":"Cleveland",
    "sg:classifiers":[
        {
            "category":"Shopping",
            "subcategory":"Gifts & Souvenirs",
            "type":"Retail Goods"
        }
    ],
    "sg:phone":"+1 216 521 9277",
    "sg:postcode":"44107",
    "sg:province":"OH",
    "sg:tags":[
        "shop"
    ],
    "wof:name":"Hixson's School-Floral Design",
    "wof:placetype":"venue"
},
  "geometry": {"coordinates":[-81.789866,41.485457],"type":"Point"}
}