{
  "type": "Feature",
  "properties": {
    "addr:full": "14125 Detroit Ave Cleveland OH 44107",
    "addr:housenumber": "14125",
    "addr:postcode": "44107",
    "addr:street": "Detroit Ave",
    "iso:country": "US",
    "sg:address": "14125 Detroit Ave",
    "sg:city": "Cleveland",
    "sg:classifiers": [
      {
        "category": "Shopping",
        "subcategory": "Gifts \u0026 Souvenirs",
        "type": "Retail Goods"
      }
    ],
    "sg:phone": "+1 216 521 9277",
    "sg:postcode": "44107",
    "sg:province": "OH",
    "sg:tags": [
      "shop"
    ],
    "wof:name": "Hixson's School-Floral Design",
    "wof:placetype": "venue"
  },
  "geometry": {"coordinates":[-81.789866,41.485457],"type":"Point"}
}
