{
  "type": "Feature",
  "properties": {
    "addr:full":"2230 Picton Pkwy Akron OH 44312",
    "addr:housenumber":"2230",
    "addr:postcode":"44312",
    "addr:street":"Picton Pkwy",
    "iso:country":"US",
    "sg:address":"2230 Picton Pkwy",
    "sg:city":"Akron",
    "sg:classifiers":[
        {
            "category":"Wholesale",
            "subcategory":"Electrical",
            "type":"Manufacturing & Wholesale Goods"
        }
    ],
    "sg:phone":"+1 330 245 2630",
    "sg:postcode":"44312",
    "sg:province":"OH",
    "sg:tags":[
        "electronic",
        "mfr",
        "parts",
        "assembly"
    ],
    "wof:name":"Aesco Manufacturing Services",
    "wof:placetype":"venue"
},
  "geometry": {"coordinates":[-81.467567,41.006084],"type":"Point"}
}