{
  "type": "Feature",
  "properties": {
    "addr:full":"2880 Mogadore Rd Akron OH 44312",
    "addr:housenumber":"2880",
    "addr:postcode":"44312",
    "addr:street":"Mogadore Rd",
    "iso:country":"US",
    "sg:address":"2880 Mogadore Rd",
    "sg:city":"Akron",
    "sg:classifiers":[
        {
            "category":"Real Estate",
            "subcategory":"Real Estate Operator",
            "type":"Services"
        }
    ],
    "sg:phone":"+1 330 794 8237",
    "sg:postcode":"44312",
    "sg:province":"OH",
    "sg:tags":[
        "building",
        "apartment"
    ],
    "wof:name":"Mogadore Square",
    "wof:placetype":"venue"
},
  "geometry": {"coordinates":[-81.42800200000001,41.057297],"type":"Point"}
}