{
  "type": "Feature",
  "properties": {
    "addr:full": "76 Troy Town Dr Troy OH 45373",
    "addr:housenumber": "76",
    "addr:postcode": "45373",
    "addr:street": "Troy Town Dr",
    "iso:country": "US",
    "sg:address": "76 Troy Town Dr",
    "sg:city": "Troy",
    "sg:classifiers": [
      {
        "category": "Health Services",
        "subcategory": "Doctor",
        "type": "Services"
      }
    ],
    "sg:phone": "+1 937 335 1302",
    "sg:postcode": "45373",
    "sg:province": "OH",
    "sg:tags": [
      "medical"
    ],
    "wof:name": "Delcamp Don D MD",
    "wof:placetype": "venue"
  },
  "geometry": {"coordinates":[-84.237533,40.05349],"type":"Point"}
}
