{
  "type": "Feature",
  "properties": {
    "iso:country":"US",
    "sg:address":"4618 Dressler Rd NW",
    "sg:city":"Canton",
    "sg:classifiers":[
        {
            "category":"Real Estate",
            "subcategory":"Real Estate Agent",
            "type":"Services"
        }
    ],
    "sg:phone":"+1 330 493 9323",
    "sg:postcode":"44718",
    "sg:province":"OH",
    "sg:tags":[
        "manager"
    ],
    "sg:website":"www.cutlergmac.com",
    "wof:name":"CUTLER/Gmac Real Estate",
    "wof:placetype":"venue"
},
  "geometry": {"coordinates":[-81.434309,40.848348],"type":"Point"}
}