{
  "type": "Feature",
  "properties": {
    "addr:full": "2626 Revere Dr Akron OH 44333",
    "addr:housenumber": "2626",
    "addr:postcode": "44333",
    "addr:street": "Revere Dr",
    "iso:country": "US",
    "sg:address": "2626 Revere Dr",
    "sg:city": "Akron",
    "sg:classifiers": [
      {
        "category": "Building \u0026 Trades",
        "subcategory": "Construction",
        "type": "Services"
      }
    ],
    "sg:phone": "+1 330 864 0666",
    "sg:postcode": "44333",
    "sg:province": "OH",
    "sg:tags": [
      "roofing",
      "contractor"
    ],
    "wof:name": "Larry Coffee Roofing Co",
    "wof:placetype": "venue"
  },
  "geometry": {"coordinates":[-81.597411,41.154245],"type":"Point"}
}
