{
  "type": "Feature",
  "properties": {
    "addr:full": "2850 Salt Springs Rd Girard OH 44420",
    "addr:housenumber": "2850",
    "addr:postcode": "44420",
    "addr:street": "Salt Springs Rd",
    "iso:country": "US",
    "sg:address": "2850 Salt Springs Rd",
    "sg:city": "Girard",
    "sg:classifiers": [
      {
        "category": "Retail",
        "subcategory": "Repair Shop",
        "type": "Services"
      }
    ],
    "sg:phone": "+1 330 530 2720",
    "sg:postcode": "44420",
    "sg:province": "OH",
    "sg:tags": [
      "equipment",
      "electronic",
      "supply"
    ],
    "wof:name": "Radio Repair Shop",
    "wof:placetype": "venue"
  },
  "geometry": {"coordinates":[-80.72466,41.145129],"type":"Point"}
}
