{
  "type": "Feature",
  "properties": {
    "iso:country":"US",
    "sg:address":"7072 Versailles Rd",
    "sg:city":"Covington",
    "sg:phone":"+1 937 473 2689",
    "sg:postcode":"45318",
    "sg:province":"OH",
    "sg:tags":[
        "farm",
        "corn"
    ],
    "wof:name":"Charles Clouse Farm",
    "wof:placetype":"venue"
},
  "geometry": {"coordinates":[-84.339389,40.181344],"type":"Point"}
}