{
  "type": "Feature",
  "properties": {
    "addr:full":"308 N Main St Mt Vernon OH 43050",
    "addr:housenumber":"308",
    "addr:postcode":"43050",
    "addr:street":"N Main St",
    "iso:country":"US",
    "sg:address":"308 N Main St",
    "sg:city":"Mt Vernon",
    "sg:classifiers":[
        {
            "category":"Organizations",
            "subcategory":"Religious Organization",
            "type":"Services"
        }
    ],
    "sg:phone":"+1 740 397 0526",
    "sg:postcode":"43050",
    "sg:province":"OH",
    "sg:tags":[
        "clergy"
    ],
    "wof:name":"G Richard Vogeley",
    "wof:placetype":"venue"
},
  "geometry": {"coordinates":[-82.485028,40.397455],"type":"Point"}
}