{
  "type": "Feature",
  "properties": {
    "addr:full": "156 Lake St Lancaster OH 43130",
    "addr:housenumber": "156",
    "addr:postcode": "43130",
    "addr:street": "Lake St",
    "iso:country": "US",
    "sg:address": "156 Lake St",
    "sg:city": "Lancaster",
    "sg:classifiers": [
      {
        "category": "Professional",
        "type": "Services"
      }
    ],
    "sg:phone": "+1 740 689 8490",
    "sg:postcode": "43130",
    "sg:province": "OH",
    "sg:tags": [
      "establishment"
    ],
    "wof:name": "Careworks",
    "wof:placetype": "venue"
  },
  "geometry": {"coordinates":[-82.599265,39.722625],"type":"Point"}
}
