{
  "type": "Feature",
  "properties": {
    "addr:full": "2169 Golden Leaf Ln Columbus OH 43223",
    "addr:housenumber": "2169",
    "addr:postcode": "43223",
    "addr:street": "Golden Leaf Ln",
    "iso:country": "US",
    "sg:address": "2169 Golden Leaf Ln",
    "sg:city": "Columbus",
    "sg:classifiers": [
      {
        "category": "Real Estate",
        "subcategory": "Real Estate Agent",
        "type": "Services"
      }
    ],
    "sg:phone": "+1 614 279 1462",
    "sg:postcode": "43223",
    "sg:province": "OH",
    "sg:tags": [
      "property",
      "management"
    ],
    "wof:name": "Manna Crest Homes",
    "wof:placetype": "venue"
  },
  "geometry": {"coordinates":[-83.056606,39.922909],"type":"Point"}
}
