{
  "type": "Feature",
  "properties": {
    "addr:full": "152 Lincoln St Wellington OH 44090",
    "addr:housenumber": "152",
    "addr:postcode": "44090",
    "addr:street": "Lincoln St",
    "iso:country": "US",
    "sg:address": "152 Lincoln St",
    "sg:city": "Wellington",
    "sg:classifiers": [
      {
        "category": "Building \u0026 Trades",
        "subcategory": "Construction",
        "type": "Services"
      }
    ],
    "sg:phone": "+1 440 647 5052",
    "sg:postcode": "44090",
    "sg:province": "OH",
    "sg:tags": [
      "product",
      "asphalt"
    ],
    "wof:name": "Sealco Asphalt Sealing",
    "wof:placetype": "venue"
  },
  "geometry": {"coordinates":[-82.214744,41.175434],"type":"Point"}
}
