{
  "type": "Feature",
  "properties": {
    "iso:country":"US",
    "sg:address":"8346 Tyler Blvd",
    "sg:city":"Mentor",
    "sg:classifiers":[
        {
            "category":"Professional",
            "subcategory":"Credit Reporting & Collection",
            "type":"Services"
        }
    ],
    "sg:phone":"+1 440 255 1300",
    "sg:postcode":"44060",
    "sg:province":"OH",
    "sg:tags":[
        "agency"
    ],
    "wof:name":"Grace Recovery Svc",
    "wof:placetype":"venue"
},
  "geometry": {"coordinates":[-81.340992,41.682789],"type":"Point"}
}