{
  "type": "Feature",
  "properties": {
    "addr:full": "5384 Bahama Ter Cincinnati OH 45223",
    "addr:housenumber": "5384",
    "addr:postcode": "45223",
    "addr:street": "Bahama Ter",
    "iso:country": "US",
    "sg:address": "5384 Bahama Ter",
    "sg:city": "Cincinnati",
    "sg:classifiers": [
      {
        "category": "Real Estate",
        "subcategory": "Real Estate Operator",
        "type": "Services"
      }
    ],
    "sg:phone": "+1 513 681 5333",
    "sg:postcode": "45223",
    "sg:province": "OH",
    "sg:tags": [
      "apartment"
    ],
    "wof:name": "Colerain Tower Apartments",
    "wof:placetype": "venue"
  },
  "geometry": {"coordinates":[-84.567287,39.189484],"type":"Point"}
}
