{
  "type": "Feature",
  "properties": {
    "iso:country":"US",
    "sg:address":"1 E Vine St",
    "sg:city":"Mt Vernon",
    "sg:classifiers":[
        {
            "category":"Professional",
            "subcategory":"Lawyer & Legal Services",
            "type":"Services"
        }
    ],
    "sg:phone":"+1 740 392 2900",
    "sg:postcode":"43050",
    "sg:province":"OH",
    "sg:tags":[
        "attorney"
    ],
    "wof:name":"William J Kepko",
    "wof:placetype":"venue"
},
  "geometry": {"coordinates":[-82.485519,40.392657],"type":"Point"}
}