{
  "type": "Feature",
  "properties": {
    "addr:full": "19101 Brewster Rd Aurora OH 44202",
    "addr:housenumber": "19101",
    "addr:postcode": "44202",
    "addr:street": "Brewster Rd",
    "iso:country": "US",
    "sg:address": "19101 Brewster Rd",
    "sg:city": "Aurora",
    "sg:classifiers": [
      {
        "category": "Real Estate",
        "subcategory": "Real Estate Agent",
        "type": "Services"
      }
    ],
    "sg:phone": "+1 440 543 7995",
    "sg:postcode": "44202",
    "sg:province": "OH",
    "sg:tags": [
      "inspection"
    ],
    "sg:website": "www.homeprideinspection.com",
    "wof:name": "Home Pride House Inspections",
    "wof:placetype": "venue"
  },
  "geometry": {"coordinates":[-81.365074,41.349236],"type":"Point"}
}
