{
  "type": "Feature",
  "properties": {
    "iso:country":"US",
    "sg:address":"14617 Saranac Rd",
    "sg:city":"Cleveland",
    "sg:classifiers":[
        {
            "category":"Railroad",
            "type":"Transportation"
        }
    ],
    "sg:phone":"+1 216 761 2083",
    "sg:postcode":"44110",
    "sg:province":"OH",
    "sg:tags":[
        "operator",
        "line"
    ],
    "wof:name":"C Sxt",
    "wof:placetype":"venue"
},
  "geometry": {"coordinates":[-81.57922000000001,41.559217],"type":"Point"}
}