{
  "type": "Feature",
  "properties": {
    "iso:country":"US",
    "sg:address":"2155 Bassett Rd",
    "sg:city":"Cleveland",
    "sg:classifiers":[
        {
            "category":"Education",
            "subcategory":"School",
            "type":"Public Place"
        }
    ],
    "sg:phone":"+1 440 835 6330",
    "sg:postcode":"44145",
    "sg:province":"OH",
    "wof:name":"Bassett Elementary School",
    "wof:placetype":"venue"
},
  "geometry": {"coordinates":[-81.944281,41.456541],"type":"Point"}
}