{
  "type": "Feature",
  "properties": {
    "addr:full": "11999 Baker Rd Maplewood OH 45340",
    "addr:housenumber": "11999",
    "addr:postcode": "45340",
    "addr:street": "Baker Rd",
    "iso:country": "US",
    "sg:address": "11999 Baker Rd",
    "sg:city": "Maplewood",
    "sg:classifiers": [
      {
        "category": "Freight",
        "type": "Transportation"
      }
    ],
    "sg:phone": "+1 937 596 5128",
    "sg:postcode": "45340",
    "sg:province": "OH",
    "sg:tags": [
      "local",
      "storage",
      "trucking"
    ],
    "wof:name": "Rv Transport Specialties",
    "wof:placetype": "venue"
  },
  "geometry": {"coordinates":[-84.035536,40.365047],"type":"Point"}
}
