{
  "type": "Feature",
  "properties": {
    "iso:country":"US",
    "sg:address":"15611 School Ave",
    "sg:city":"Cleveland",
    "sg:classifiers":[
        {
            "category":"Professional",
            "subcategory":"Detective & Security Services",
            "type":"Services"
        }
    ],
    "sg:phone":"+1 216 451 1808",
    "sg:postcode":"44110",
    "sg:province":"OH",
    "sg:tags":[
        "investigator"
    ],
    "wof:name":"Christine's Investigation",
    "wof:placetype":"venue"
},
  "geometry": {"coordinates":[-81.571718,41.559737],"type":"Point"}
}