{
  "type": "Feature",
  "properties": {
    "addr:full": "15611 School Ave Cleveland OH 44110",
    "addr:housenumber": "15611",
    "addr:postcode": "44110",
    "addr:street": "School Ave",
    "iso:country": "US",
    "sg:address": "15611 School Ave",
    "sg:city": "Cleveland",
    "sg:classifiers": [
      {
        "category": "Professional",
        "subcategory": "Detective \u0026 Security Services",
        "type": "Services"
      }
    ],
    "sg:phone": "+1 216 451 1808",
    "sg:postcode": "44110",
    "sg:province": "OH",
    "sg:tags": [
      "investigator"
    ],
    "wof:name": "Christine's Investigation",
    "wof:placetype": "venue"
  },
  "geometry": {"coordinates":[-81.571718,41.559737],"type":"Point"}
}
