{
  "type": "Feature",
  "properties": {
    "iso:country":"US",
    "sg:address":"4415 Huston Rd",
    "sg:city":"Hamilton",
    "sg:classifiers":[
        {
            "category":"Building & Trades",
            "subcategory":"Construction",
            "type":"Services"
        }
    ],
    "sg:phone":"+1 513 523 2262",
    "sg:postcode":"45013",
    "sg:province":"IN",
    "sg:tags":[
        "excavating",
        "contractor"
    ],
    "wof:name":"M & C Excavating & Septic",
    "wof:placetype":"venue"
},
  "geometry": {"coordinates":[-84.609436,39.49885],"type":"Point"}
}