{
  "type": "Feature",
  "properties": {
    "addr:full": "4415 Huston Rd Hamilton IN 45013",
    "addr:housenumber": "4415",
    "addr:postcode": "45013",
    "addr:street": "Huston Rd",
    "iso:country": "US",
    "sg:address": "4415 Huston Rd",
    "sg:city": "Hamilton",
    "sg:classifiers": [
      {
        "category": "Building \u0026 Trades",
        "subcategory": "Construction",
        "type": "Services"
      }
    ],
    "sg:phone": "+1 513 523 2262",
    "sg:postcode": "45013",
    "sg:province": "IN",
    "sg:tags": [
      "excavating",
      "contractor"
    ],
    "wof:name": "M \u0026 C Excavating \u0026 Septic",
    "wof:placetype": "venue"
  },
  "geometry": {"coordinates":[-84.609436,39.49885],"type":"Point"}
}
