{
  "type": "Feature",
  "properties": {
    "addr:full":"14555 Madison Ave Lakewood OH 44107",
    "addr:housenumber":"14555",
    "addr:postcode":"44107",
    "addr:street":"Madison Ave",
    "iso:country":"US",
    "sg:address":"14555 Madison Ave",
    "sg:city":"Lakewood",
    "sg:classifiers":[
        {
            "category":"Building & Trades",
            "subcategory":"Construction",
            "type":"Services"
        }
    ],
    "sg:phone":"+1 216 221 9250",
    "sg:postcode":"44107",
    "sg:province":"OH",
    "sg:tags":[
        "contractor"
    ],
    "wof:name":"McLean Construction & Remodeli",
    "wof:placetype":"venue"
},
  "geometry": {"coordinates":[-81.79780100000001,41.477126],"type":"Point"}
}