{
  "type": "Feature",
  "properties": {
    "iso:country":"US",
    "sg:address":"5495 Glenway Ave",
    "sg:city":"Cincinnati",
    "sg:classifiers":[
        {
            "category":"Autos & Motor Vehicles",
            "subcategory":"Auto Supplies",
            "type":"Retail Goods"
        }
    ],
    "sg:phone":"+1 513 347 0400",
    "sg:postcode":"45238",
    "sg:province":"OH",
    "sg:tags":[
        "automobile",
        "parts"
    ],
    "sg:website":"www.pepboys.com",
    "wof:name":"Pep Boys Supercenter",
    "wof:placetype":"venue"
},
  "geometry": {"coordinates":[-84.60906900000001,39.130995],"type":"Point"}
}