{
  "type": "Feature",
  "properties": {
    "addr:full": "5495 Glenway Ave Cincinnati OH 45238",
    "addr:housenumber": "5495",
    "addr:postcode": "45238",
    "addr:street": "Glenway Ave",
    "iso:country": "US",
    "sg:address": "5495 Glenway Ave",
    "sg:city": "Cincinnati",
    "sg:classifiers": [
      {
        "category": "Autos \u0026 Motor Vehicles",
        "subcategory": "Auto Supplies",
        "type": "Retail Goods"
      }
    ],
    "sg:phone": "+1 513 347 0400",
    "sg:postcode": "45238",
    "sg:province": "OH",
    "sg:tags": [
      "automobile",
      "parts"
    ],
    "sg:website": "www.pepboys.com",
    "wof:name": "Pep Boys Supercenter",
    "wof:placetype": "venue"
  },
  "geometry": {"coordinates":[-84.609069,39.130995],"type":"Point"}
}
