{
  "type": "Feature",
  "properties": {
    "addr:full": "3326 Ebenezer Rd Cincinnati OH 45248",
    "addr:housenumber": "3326",
    "addr:postcode": "45248",
    "addr:street": "Ebenezer Rd",
    "iso:country": "US",
    "sg:address": "3326 Ebenezer Rd",
    "sg:city": "Cincinnati",
    "sg:classifiers": [
      {
        "category": "Shopping",
        "type": "Retail Goods"
      }
    ],
    "sg:phone": "+1 513 574 6827",
    "sg:postcode": "45248",
    "sg:province": "OH",
    "sg:tags": [
      "merchandise"
    ],
    "wof:name": "Aquarium Creators",
    "wof:placetype": "venue"
  },
  "geometry": {"coordinates":[-84.650044,39.150582],"type":"Point"}
}
