{
  "type": "Feature",
  "properties": {
    "iso:country":"US",
    "sg:address":"3326 Ebenezer Rd",
    "sg:city":"Cincinnati",
    "sg:classifiers":[
        {
            "category":"Shopping",
            "type":"Retail Goods"
        }
    ],
    "sg:phone":"+1 513 574 6827",
    "sg:postcode":"45248",
    "sg:province":"OH",
    "sg:tags":[
        "merchandise"
    ],
    "wof:name":"Aquarium Creators",
    "wof:placetype":"venue"
},
  "geometry": {"coordinates":[-84.65004399999999,39.150582],"type":"Point"}
}