{
  "type": "Feature",
  "properties": {
    "addr:full": "1800 E 21st St Ashtabula OH 44004",
    "addr:housenumber": "1800",
    "addr:postcode": "44004",
    "addr:street": "E 21St St",
    "iso:country": "US",
    "sg:address": "1800 E 21st St",
    "sg:city": "Ashtabula",
    "sg:classifiers": [
      {
        "category": "Professional",
        "subcategory": "Advertising",
        "type": "Services"
      }
    ],
    "sg:phone": "+1 440 998 4998",
    "sg:postcode": "44004",
    "sg:province": "OH",
    "sg:tags": [
      "distribution"
    ],
    "wof:name": "R \u0026 J Distributors",
    "wof:placetype": "venue"
  },
  "geometry": {"coordinates":[-80.776254,41.889162],"type":"Point"}
}
