{
  "type": "Feature",
  "properties": {
    "iso:country":"US",
    "sg:address":"1800 E 21st St",
    "sg:city":"Ashtabula",
    "sg:classifiers":[
        {
            "category":"Professional",
            "subcategory":"Advertising",
            "type":"Services"
        }
    ],
    "sg:phone":"+1 440 998 4998",
    "sg:postcode":"44004",
    "sg:province":"OH",
    "sg:tags":[
        "distribution"
    ],
    "wof:name":"R & J Distributors",
    "wof:placetype":"venue"
},
  "geometry": {"coordinates":[-80.77625399999999,41.889162],"type":"Point"}
}