{
  "type": "Feature",
  "properties": {
    "addr:full":"13109 Chardon-Windsor Rd Chardon OH 44024",
    "addr:housenumber":"13109",
    "addr:postcode":"44024",
    "addr:street":"Chardon-Windsor Rd",
    "iso:country":"US",
    "sg:address":"13109 Chardon-Windsor Rd",
    "sg:city":"Chardon",
    "sg:classifiers":[
        {
            "category":"Real Estate",
            "subcategory":"Real Estate Operator",
            "type":"Services"
        }
    ],
    "sg:phone":"+1 440 286 5426",
    "sg:postcode":"44024",
    "sg:province":"OH",
    "sg:tags":[
        "mobile",
        "home",
        "community"
    ],
    "wof:name":"Leaders Mobile Home Community",
    "wof:placetype":"venue"
},
  "geometry": {"coordinates":[-81.175782,41.578356],"type":"Point"}
}