{
  "type": "Feature",
  "properties": {
    "iso:country":"US",
    "sg:address":"3 Public Sq",
    "sg:city":"Cleveland",
    "sg:classifiers":[
        {
            "category":"Government",
            "subcategory":"Office",
            "type":"Public Place"
        }
    ],
    "sg:phone":"+1 216 274 2256",
    "sg:postcode":"44114",
    "sg:province":"OH",
    "sg:tags":[
        "commission",
        "state"
    ],
    "wof:name":"Cuyahoga County Soldiers and S",
    "wof:placetype":"venue"
},
  "geometry": {"coordinates":[-81.695026,41.499758],"type":"Point"}
}