{
  "type": "Feature",
  "properties": {
    "addr:full": "460 S Washington St New Bremen OH 45869",
    "addr:housenumber": "460",
    "addr:postcode": "45869",
    "addr:street": "S Washington St",
    "iso:country": "US",
    "sg:address": "460 S Washington St",
    "sg:city": "New Bremen",
    "sg:classifiers": [
      {
        "category": "Restaurant",
        "type": "Food \u0026 Drink"
      }
    ],
    "sg:phone": "+1 419 629 0403",
    "sg:postcode": "45869",
    "sg:province": "OH",
    "sg:tags": [
      "eating"
    ],
    "wof:name": "China 88",
    "wof:placetype": "venue"
  },
  "geometry": {"coordinates":[-84.378892,40.42752],"type":"Point"}
}
