{
  "type": "Feature",
  "properties": {
    "iso:country":"US",
    "sg:address":"11400 Rust Dr",
    "sg:city":"Chesterland",
    "sg:classifiers":[
        {
            "category":"Manufacturing",
            "subcategory":"Tools & Machinery",
            "type":"Manufacturing & Wholesale Goods"
        }
    ],
    "sg:phone":"+1 440 729 2932",
    "sg:postcode":"44026",
    "sg:province":"OH",
    "sg:tags":[
        "machine",
        "mfg",
        "accessory"
    ],
    "wof:name":"G & E Tooling Co",
    "wof:placetype":"venue"
},
  "geometry": {"coordinates":[-81.333226,41.555862],"type":"Point"}
}