{
  "type": "Feature",
  "properties": {
    "addr:full": "11400 Rust Dr Chesterland OH 44026",
    "addr:postcode": "11400;44026",
    "addr:street": "Rust Dr",
    "iso:country": "US",
    "sg:address": "11400 Rust Dr",
    "sg:city": "Chesterland",
    "sg:classifiers": [
      {
        "category": "Manufacturing",
        "subcategory": "Tools \u0026 Machinery",
        "type": "Manufacturing \u0026 Wholesale Goods"
      }
    ],
    "sg:phone": "+1 440 729 2932",
    "sg:postcode": "44026",
    "sg:province": "OH",
    "sg:tags": [
      "machine",
      "mfg",
      "accessory"
    ],
    "wof:name": "G \u0026 E Tooling Co",
    "wof:placetype": "venue"
  },
  "geometry": {"coordinates":[-81.333226,41.555862],"type":"Point"}
}
