{
  "type": "Feature",
  "properties": {
    "addr:full": "1300 W 6th St Cleveland OH 44113",
    "addr:housenumber": "1300",
    "addr:postcode": "44113",
    "addr:street": "W 6Th St",
    "iso:country": "US",
    "sg:address": "1300 W 6th St",
    "sg:city": "Cleveland",
    "sg:classifiers": [
      {
        "category": "Shopping",
        "subcategory": "Clothing, Apparel, \u0026 Fashions",
        "type": "Retail Goods"
      }
    ],
    "sg:phone": "+1 216 861 4556",
    "sg:postcode": "44113",
    "sg:province": "OH",
    "sg:tags": [
      "tuxedo"
    ],
    "wof:name": "Executive Tuxedo",
    "wof:placetype": "venue"
  },
  "geometry": {"coordinates":[-81.697734,41.498762],"type":"Point"}
}
