{
  "type": "Feature",
  "properties": {
    "addr:full":"4064 State Rte 718 Troy OH 45373",
    "addr:housenumber":"4064",
    "addr:postcode":"45373",
    "addr:street":"State Rte 718",
    "iso:country":"US",
    "sg:address":"4064 State Rte 718",
    "sg:city":"Troy",
    "sg:classifiers":[
        {
            "category":"Freight",
            "type":"Transportation"
        }
    ],
    "sg:phone":"+1 937 335 2171",
    "sg:postcode":"45373",
    "sg:province":"OH",
    "sg:tags":[
        "operator",
        "local",
        "trucking"
    ],
    "wof:name":"Binkley Trucking",
    "wof:placetype":"venue"
},
  "geometry": {"coordinates":[-84.28026699999999,40.041253],"type":"Point"}
}