{
  "type": "Feature",
  "properties": {
    "addr:full":"5 W Main St Seville OH 44273",
    "addr:housenumber":"5",
    "addr:postcode":"44273",
    "addr:street":"W Main St",
    "iso:country":"US",
    "sg:address":"5 W Main St",
    "sg:city":"Seville",
    "sg:classifiers":[
        {
            "category":"Restaurant",
            "type":"Food & Drink"
        }
    ],
    "sg:phone":"+1 330 769 2519",
    "sg:postcode":"44273",
    "sg:province":"OH",
    "sg:tags":[
        "pizza"
    ],
    "wof:name":"Remington Pizza Express",
    "wof:placetype":"venue"
},
  "geometry": {"coordinates":[-81.863546,41.010031],"type":"Point"}
}