{
  "type": "Feature",
  "properties": {
    "iso:country":"US",
    "sg:address":"25201 Rockside Rd",
    "sg:city":"Bedford",
    "sg:classifiers":[
        {
            "category":"Restaurant",
            "type":"Food & Drink"
        }
    ],
    "sg:menulink":"http://www.allmenus.com/oh/bedford-heights/170145-burger-king/menu/",
    "sg:phone":"+1 440 232 3314",
    "sg:postcode":"44146",
    "sg:province":"OH",
    "sg:tags":[
        "burger",
        "american"
    ],
    "wof:name":"Burger King",
    "wof:placetype":"venue"
},
  "geometry": {"coordinates":[-81.503122,41.409519],"type":"Point"}
}