{
  "type": "Feature",
  "properties": {
    "addr:full":"4601 Eastgate Blvd Cincinnati OH 45245",
    "addr:housenumber":"4601",
    "addr:postcode":"45245",
    "addr:street":"Eastgate Blvd",
    "iso:country":"US",
    "sg:address":"4601 Eastgate Blvd",
    "sg:city":"Cincinnati",
    "sg:classifiers":[
        {
            "category":"Shopping",
            "subcategory":"Shoes",
            "type":"Retail Goods"
        }
    ],
    "sg:phone":"+1 513 752 0770",
    "sg:postcode":"45245",
    "sg:province":"OH",
    "sg:tags":[
        "family"
    ],
    "sg:website":"www.rackroomshoes.com",
    "wof:name":"Rack Room Shoes Inc",
    "wof:placetype":"venue"
},
  "geometry": {"coordinates":[-84.27309099999999,39.10214],"type":"Point"}
}