{
  "type": "Feature",
  "properties": {
    "addr:full": "10735 Montgomery Rd Cincinnati OH 45242",
    "addr:housenumber": "10735",
    "addr:postcode": "45242",
    "addr:street": "Montgomery Rd",
    "iso:country": "US",
    "sg:address": "10735 Montgomery Rd",
    "sg:city": "Cincinnati",
    "sg:classifiers": [
      {
        "category": "Personal",
        "subcategory": "Beauty Salon",
        "type": "Services"
      }
    ],
    "sg:phone": "+1 513 421 2378",
    "sg:postcode": "45242",
    "sg:province": "OH",
    "sg:tags": [
      "shop"
    ],
    "wof:name": "Look Your Best LTD",
    "wof:placetype": "venue"
  },
  "geometry": {"coordinates":[-84.341928,39.257848],"type":"Point"}
}
