{
  "type": "Feature",
  "properties": {
    "addr:full": "2730 Kingston Ave Grove City OH 43123",
    "addr:housenumber": "2730",
    "addr:postcode": "43123",
    "addr:street": "Kingston Ave",
    "iso:country": "US",
    "sg:address": "2730 Kingston Ave",
    "sg:city": "Grove City",
    "sg:classifiers": [
      {
        "category": "Organizations",
        "subcategory": "Religious Organization",
        "type": "Services"
      }
    ],
    "sg:phone": "+1 614 875 6939",
    "sg:postcode": "43123",
    "sg:province": "OH",
    "sg:tags": [
      "church"
    ],
    "sg:website": "www.firstbaptistgc.org",
    "wof:name": "First Baptist Of Grove City",
    "wof:placetype": "venue"
  },
  "geometry": {"coordinates":[-83.072711,39.877136],"type":"Point"}
}
