{
  "type": "Feature",
  "properties": {
    "addr:full": "14 N Lowry Ave Springfield OH 45504",
    "addr:housenumber": "14",
    "addr:postcode": "45504",
    "addr:street": "N Lowry Ave",
    "iso:country": "US",
    "sg:address": "14 N Lowry Ave",
    "sg:city": "Springfield",
    "sg:classifiers": [
      {
        "category": "Professional",
        "subcategory": "Detective \u0026 Security Services",
        "type": "Services"
      }
    ],
    "sg:phone": "+1 937 322 0122",
    "sg:postcode": "45504",
    "sg:province": "OH",
    "sg:tags": [
      "car"
    ],
    "wof:name": "Montgomery SEC \u0026 Investigation",
    "wof:placetype": "venue"
  },
  "geometry": {"coordinates":[-83.815787,39.926046],"type":"Point"}
}
