{
  "type": "Feature",
  "properties": {
    "iso:country":"US",
    "sg:address":"4141 W Broad St",
    "sg:city":"Columbus",
    "sg:classifiers":[
        {
            "category":"Shopping",
            "subcategory":"Department Store",
            "type":"Retail Goods"
        }
    ],
    "sg:phone":"+1 614 278 4800",
    "sg:postcode":"43228",
    "sg:province":"OH",
    "sg:website":"www.fds.com",
    "wof:name":"Macy's",
    "wof:placetype":"venue"
},
  "geometry": {"coordinates":[-83.114693,39.952844],"type":"Point"}
}