{
  "type": "Feature",
  "properties": {
    "iso:country":"US",
    "sg:address":"10 Delaware Dr",
    "sg:city":"Chillicothe",
    "sg:classifiers":[
        {
            "category":"Organizations",
            "subcategory":"Religious Organization",
            "type":"Services"
        }
    ],
    "sg:phone":"+1 740 774 6659",
    "sg:postcode":"45601",
    "sg:province":"OH",
    "sg:tags":[
        "church"
    ],
    "wof:name":"Community Of Christ",
    "wof:placetype":"venue"
},
  "geometry": {"coordinates":[-82.98258,39.363912],"type":"Point"}
}