{
  "type": "Feature",
  "properties": {
    "addr:full":"1410 2nd St SW Canton OH 44702",
    "addr:housenumber":"1410",
    "addr:postcode":"44702",
    "addr:street":"2Nd St Sw",
    "iso:country":"US",
    "sg:address":"1410 2nd St SW",
    "sg:city":"Canton",
    "sg:classifiers":[
        {
            "category":"Building & Trades",
            "subcategory":"Electrical",
            "type":"Services"
        }
    ],
    "sg:phone":"+1 330 456 0053",
    "sg:postcode":"44702",
    "sg:province":"OH",
    "sg:tags":[
        "electrical",
        "contractor"
    ],
    "wof:name":"Bart Lee Electric Inc",
    "wof:placetype":"venue"
},
  "geometry": {"coordinates":[-81.38732400000001,40.799904],"type":"Point"}
}