{
  "type": "Feature",
  "properties": {
    "addr:full":"15 Gates St Dayton OH 45402",
    "addr:housenumber":"15",
    "addr:postcode":"45402",
    "addr:street":"Gates St",
    "iso:country":"US",
    "sg:address":"15 Gates St",
    "sg:city":"Dayton",
    "sg:classifiers":[
        {
            "category":"Organizations",
            "subcategory":"Labor Organization",
            "type":"Services"
        }
    ],
    "sg:phone":"+1 937 461 9983",
    "sg:postcode":"45402",
    "sg:province":"OH",
    "wof:name":"AFSCME Ohio Council 8",
    "wof:placetype":"venue"
},
  "geometry": {"coordinates":[-84.18391699999999,39.758008],"type":"Point"}
}