{
  "type": "Feature",
  "properties": {
    "iso:country":"US",
    "sg:address":"7543 Liberty Ln",
    "sg:city":"Liberty Twp",
    "sg:classifiers":[
        {
            "category":"Food & Beverages",
            "subcategory":"Specialty",
            "type":"Retail Goods"
        }
    ],
    "sg:phone":"+1 513 777 2669",
    "sg:postcode":"45044",
    "sg:province":"OH",
    "sg:tags":[
        "water",
        "bulk",
        "company"
    ],
    "wof:name":"N & N Water Hauling",
    "wof:placetype":"venue"
},
  "geometry": {"coordinates":[-84.36956600000001,39.381767],"type":"Point"}
}