{
  "type": "Feature",
  "properties": {
    "iso:country":"US",
    "sg:address":"3676 E 133rd St",
    "sg:city":"Cleveland",
    "sg:classifiers":[
        {
            "category":"Freight",
            "type":"Transportation"
        }
    ],
    "sg:phone":"+1 216 561 4328",
    "sg:postcode":"44120",
    "sg:province":"OH",
    "sg:tags":[
        "operator",
        "local",
        "trucking"
    ],
    "wof:name":"A R Jones Trucking Co",
    "wof:placetype":"venue"
},
  "geometry": {"coordinates":[-81.59015100000001,41.460296],"type":"Point"}
}