{
  "type": "Feature",
  "properties": {
    "addr:full": "162 N Diamond St Mansfield OH 44902",
    "addr:housenumber": "162",
    "addr:postcode": "44902",
    "addr:street": "N Diamond St",
    "iso:country": "US",
    "sg:address": "162 N Diamond St",
    "sg:city": "Mansfield",
    "sg:classifiers": [
      {
        "category": "Wholesale",
        "subcategory": "Painting Supplies",
        "type": "Manufacturing \u0026 Wholesale Goods"
      }
    ],
    "sg:phone": "+1 419 524 7446",
    "sg:postcode": "44902",
    "sg:province": "OH",
    "wof:name": "Signlife",
    "wof:placetype": "venue"
  },
  "geometry": {"coordinates":[-82.51375,40.762093],"type":"Point"}
}
