{
  "type": "Feature",
  "properties": {
    "iso:country":"US",
    "sg:address":"11925 Pearl Rd",
    "sg:city":"Strongsville",
    "sg:classifiers":[
        {
            "category":"Banks & Credit Unions",
            "subcategory":"Bank",
            "type":"Services"
        }
    ],
    "sg:phone":"+1 440 238 2500",
    "sg:postcode":"44136",
    "sg:province":"OH",
    "sg:tags":[
        "personal",
        "institution"
    ],
    "wof:name":"Orix Commercial Alliance Corp",
    "wof:placetype":"venue"
},
  "geometry": {"coordinates":[-81.836904,41.329873],"type":"Point"}
}