{
  "type": "Feature",
  "properties": {
    "addr:full": "2545 E 79th St Cleveland OH 44104",
    "addr:housenumber": "2545",
    "addr:postcode": "44104",
    "addr:street": "E 79Th St",
    "iso:country": "US",
    "sg:address": "2545 E 79th St",
    "sg:city": "Cleveland",
    "sg:classifiers": [
      {
        "category": "Manufacturing",
        "subcategory": "Paper Products",
        "type": "Manufacturing \u0026 Wholesale Goods"
      }
    ],
    "sg:phone": "+1 216 791 1308",
    "sg:postcode": "44104",
    "sg:province": "OH",
    "sg:tags": [
      "box",
      "paperboard",
      "mfg"
    ],
    "wof:name": "Model Box Company",
    "wof:placetype": "venue"
  },
  "geometry": {"coordinates":[-81.63332,41.488535],"type":"Point"}
}
