{
  "type": "Feature",
  "properties": {
    "iso:country":"US",
    "sg:address":"6685 Middle Ridge Rd",
    "sg:city":"Madison",
    "sg:classifiers":[
        {
            "category":"Organizations",
            "subcategory":"Religious Organization",
            "type":"Services"
        }
    ],
    "sg:phone":"+1 440 428 1435",
    "sg:postcode":"44057",
    "sg:province":"OH",
    "sg:website":"www.madisoncrossroads.org",
    "wof:name":"Crossroads Community Church",
    "wof:placetype":"venue"
},
  "geometry": {"coordinates":[-81.05345,41.789202],"type":"Point"}
}