{
  "type": "Feature",
  "properties": {
    "addr:full": "2612 Gilbert Ave Cincinnati OH 45206",
    "addr:housenumber": "2612",
    "addr:postcode": "45206",
    "addr:street": "Gilbert Ave",
    "iso:country": "US",
    "sg:address": "2612 Gilbert Ave",
    "sg:city": "Cincinnati",
    "sg:classifiers": [
      {
        "category": "Education",
        "subcategory": "School",
        "type": "Public Place"
      }
    ],
    "sg:phone": "+1 513 475 0222",
    "sg:postcode": "45206",
    "sg:province": "OH",
    "sg:website": "www.lifeskillscenters.com",
    "wof:name": "Life Skills Ctr-Cincinnati",
    "wof:placetype": "venue"
  },
  "geometry": {"coordinates":[-84.488714,39.128829],"type":"Point"}
}
