{
  "type": "Feature",
  "properties": {
    "iso:country":"US",
    "sg:address":"1600 Princeton Dr",
    "sg:city":"Dayton",
    "sg:classifiers":[
        {
            "category":"Recreation",
            "type":"Entertainment"
        }
    ],
    "sg:phone":"+1 937 333 3322",
    "sg:postcode":"45406",
    "sg:province":"OH",
    "sg:tags":[
        "center"
    ],
    "wof:name":"Northwest Recreation Ctr",
    "wof:placetype":"venue"
},
  "geometry": {"coordinates":[-84.229157,39.773023],"type":"Point"}
}