{
  "type": "Feature",
  "properties": {
    "addr:full": "7529 W Bier Rd Oak Harbor OH 43449",
    "addr:housenumber": "7529",
    "addr:postcode": "43449",
    "addr:street": "W Bier Rd",
    "iso:country": "US",
    "sg:address": "7529 W Bier Rd",
    "sg:city": "Oak Harbor",
    "sg:classifiers": [
      {
        "category": "Building \u0026 Trades",
        "subcategory": "Construction",
        "type": "Services"
      }
    ],
    "sg:phone": "+1 419 898 5216",
    "sg:postcode": "43449",
    "sg:province": "OH",
    "sg:tags": [
      "general",
      "contractor"
    ],
    "wof:name": "Curt Rieff Builders",
    "wof:placetype": "venue"
  },
  "geometry": {"coordinates":[-83.086573,41.537869],"type":"Point"}
}
