{
  "type": "Feature",
  "properties": {
    "addr:full": "6219 Knox-School Rd Minerva OH 44657",
    "addr:housenumber": "6219",
    "addr:postcode": "44657",
    "addr:street": "Knox-School Rd",
    "iso:country": "US",
    "sg:address": "6219 Knox-School Rd",
    "sg:city": "Minerva",
    "sg:classifiers": [
      {
        "category": "Farming",
        "subcategory": "Farm",
        "type": "Manufacturing \u0026 Wholesale Goods"
      }
    ],
    "sg:phone": "+1 330 525 7069",
    "sg:postcode": "44657",
    "sg:province": "OH",
    "sg:tags": [
      "crop",
      "general"
    ],
    "wof:name": "Lowell Smith",
    "wof:placetype": "venue"
  },
  "geometry": {"coordinates":[-81.031223,40.813695],"type":"Point"}
}
