{
  "type": "Feature",
  "properties": {
    "iso:country":"US",
    "sg:address":"6219 Knox-School Rd",
    "sg:city":"Minerva",
    "sg:classifiers":[
        {
            "category":"Farming",
            "subcategory":"Farm",
            "type":"Manufacturing & Wholesale Goods"
        }
    ],
    "sg:phone":"+1 330 525 7069",
    "sg:postcode":"44657",
    "sg:province":"OH",
    "sg:tags":[
        "crop",
        "general"
    ],
    "wof:name":"Lowell Smith",
    "wof:placetype":"venue"
},
  "geometry": {"coordinates":[-81.031223,40.813695],"type":"Point"}
}