{
  "type": "Feature",
  "properties": {
    "addr:full":"114 Worthington Mall Worthington OH 43085",
    "addr:housenumber":"114",
    "addr:postcode":"43085",
    "addr:street":"Worthington Mall",
    "iso:country":"US",
    "sg:address":"114 Worthington Mall",
    "sg:city":"Worthington",
    "sg:classifiers":[
        {
            "category":"Food & Beverages",
            "subcategory":"Bakery",
            "type":"Retail Goods"
        }
    ],
    "sg:phone":"+1 614 431 1676",
    "sg:postcode":"43085",
    "sg:province":"OH",
    "sg:tags":[
        "cookie",
        "cracker"
    ],
    "wof:name":"Cheryl & Co",
    "wof:placetype":"venue"
},
  "geometry": {"coordinates":[-83.01721999999999,40.107895],"type":"Point"}
}