{
  "type": "Feature",
  "properties": {
    "iso:country":"US",
    "sg:address":"5757 Cooper Rd",
    "sg:city":"Cincinnati",
    "sg:classifiers":[
        {
            "category":"Education",
            "subcategory":"School",
            "type":"Public Place"
        }
    ],
    "sg:phone":"+1 513 791 8013",
    "sg:postcode":"45242",
    "sg:province":"OH",
    "sg:website":"www.sycamoreschools.org",
    "wof:name":"Sycamore Junior High School",
    "wof:placetype":"venue"
},
  "geometry": {"coordinates":[-84.368652,39.229018],"type":"Point"}
}