{
  "type": "Feature",
  "properties": {
    "iso:country":"US",
    "sg:address":"233 S Main St",
    "sg:city":"Bryan",
    "sg:classifiers":[
        {
            "category":"Restaurant",
            "type":"Food & Drink"
        }
    ],
    "sg:phone":"+1 419 636 1818",
    "sg:postcode":"43506",
    "sg:province":"OH",
    "sg:tags":[
        "eating"
    ],
    "sg:website":"www.lestersonline.com",
    "wof:name":"Lesters Diners Inc",
    "wof:placetype":"venue"
},
  "geometry": {"coordinates":[-84.550966,41.47288],"type":"Point"}
}