{
  "type": "Feature",
  "properties": {
    "addr:full": "3145 Hamilton Mason Rd Hamilton OH 45011",
    "addr:housenumber": "3145",
    "addr:postcode": "45011",
    "addr:street": "Hamilton Mason Rd",
    "iso:country": "US",
    "sg:address": "3145 Hamilton Mason Rd",
    "sg:city": "Hamilton",
    "sg:classifiers": [
      {
        "category": "Health Services",
        "subcategory": "Chiropractor",
        "type": "Services"
      }
    ],
    "sg:phone": "+1 513 895 2305",
    "sg:postcode": "45011",
    "sg:province": "OH",
    "wof:name": "Cinti Centers For Pain Relief",
    "wof:placetype": "venue"
  },
  "geometry": {"coordinates":[-84.51413,39.379123],"type":"Point"}
}
