{
  "type": "Feature",
  "properties": {
    "addr:full":"755 Boardman Canfield Rd Youngstown OH 44512",
    "addr:housenumber":"755",
    "addr:postcode":"44512",
    "addr:street":"Boardman Canfield Rd",
    "iso:country":"US",
    "sg:address":"755 Boardman Canfield Rd",
    "sg:city":"Youngstown",
    "sg:classifiers":[
        {
            "category":"Building & Trades",
            "subcategory":"Construction",
            "type":"Services"
        }
    ],
    "sg:phone":"+1 330 542 0950",
    "sg:postcode":"44512",
    "sg:province":"OH",
    "sg:tags":[
        "builder",
        "masonry",
        "repairer",
        "chimney",
        "contractor"
    ],
    "wof:name":"New Life Masonry Inc",
    "wof:placetype":"venue"
},
  "geometry": {"coordinates":[-80.68386,41.024436],"type":"Point"}
}