{
  "type": "Feature",
  "properties": {
    "iso:country":"US",
    "sg:address":"523 Primrose St",
    "sg:city":"Galion",
    "sg:classifiers":[
        {
            "category":"Building & Trades",
            "subcategory":"Electrical",
            "type":"Services"
        }
    ],
    "sg:phone":"+1 419 468 8802",
    "sg:postcode":"44833",
    "sg:province":"OH",
    "sg:tags":[
        "telecommunication",
        "contractor"
    ],
    "wof:name":"Laek & Assoc",
    "wof:placetype":"venue"
},
  "geometry": {"coordinates":[-82.78080300000001,40.73598],"type":"Point"}
}