{
  "type": "Feature",
  "properties": {
    "addr:full": "523 Primrose St Galion OH 44833",
    "addr:housenumber": "523",
    "addr:postcode": "44833",
    "addr:street": "Primrose St",
    "iso:country": "US",
    "sg:address": "523 Primrose St",
    "sg:city": "Galion",
    "sg:classifiers": [
      {
        "category": "Building \u0026 Trades",
        "subcategory": "Electrical",
        "type": "Services"
      }
    ],
    "sg:phone": "+1 419 468 8802",
    "sg:postcode": "44833",
    "sg:province": "OH",
    "sg:tags": [
      "telecommunication",
      "contractor"
    ],
    "wof:name": "Laek \u0026 Assoc",
    "wof:placetype": "venue"
  },
  "geometry": {"coordinates":[-82.780803,40.73598],"type":"Point"}
}
