{
  "type": "Feature",
  "properties": {
    "addr:full": "3575 Maple Ave Zanesville OH 43701",
    "addr:housenumber": "3575",
    "addr:postcode": "43701",
    "addr:street": "Maple Ave",
    "iso:country": "US",
    "sg:address": "3575 Maple Ave",
    "sg:city": "Zanesville",
    "sg:classifiers": [
      {
        "category": "Government",
        "subcategory": "Post Office",
        "type": "Public Place"
      }
    ],
    "sg:phone": "+1 740 454 3998",
    "sg:postcode": "43701",
    "sg:province": "OH",
    "wof:name": "US Post Office",
    "wof:placetype": "venue"
  },
  "geometry": {"coordinates":[-82.022252,39.986451],"type":"Point"}
}
