{
  "type": "Feature",
  "properties": {
    "addr:full":"3101 Springboro Rd Dayton OH 45439",
    "addr:housenumber":"3101",
    "addr:postcode":"45439",
    "addr:street":"Springboro Rd",
    "iso:country":"US",
    "sg:address":"3101 Springboro Rd",
    "sg:city":"Dayton",
    "sg:classifiers":[
        {
            "category":"Railroad",
            "type":"Transportation"
        }
    ],
    "sg:phone":"+1 937 297 5401",
    "sg:postcode":"45439",
    "sg:province":"OH",
    "sg:website":"www.nscorp.com",
    "wof:name":"Norfolk Southern Railway Co",
    "wof:placetype":"venue"
},
  "geometry": {"coordinates":[-84.21755,39.708185],"type":"Point"}
}