{
  "type": "Feature",
  "properties": {
    "addr:full":"3801 State Rte 167 Jefferson OH 44047",
    "addr:housenumber":"3801",
    "addr:postcode":"44047",
    "addr:street":"State Rte 167",
    "iso:country":"US",
    "sg:address":"3801 State Rte 167",
    "sg:city":"Jefferson",
    "sg:classifiers":[
        {
            "category":"Retail",
            "subcategory":"Repair Shop",
            "type":"Services"
        }
    ],
    "sg:phone":"+1 440 858 2622",
    "sg:postcode":"44047",
    "sg:province":"OH",
    "sg:tags":[
        "engine"
    ],
    "wof:name":"Williams & Sons Repair",
    "wof:placetype":"venue"
},
  "geometry": {"coordinates":[-80.648928,41.751941],"type":"Point"}
}