{
  "type": "Feature",
  "properties": {
    "addr:full": "7461 South Ave Youngstown OH 44512",
    "addr:housenumber": "7461",
    "addr:postcode": "44512",
    "addr:street": "South Ave",
    "iso:country": "US",
    "sg:address": "7461 South Ave",
    "sg:city": "Youngstown",
    "sg:classifiers": [
      {
        "category": "Communications",
        "subcategory": "Radio Station",
        "type": "Services"
      }
    ],
    "sg:phone": "+1 330 965 0057",
    "sg:postcode": "44512",
    "sg:province": "OH",
    "sg:tags": [
      "company",
      "broadcasting"
    ],
    "sg:website": "www.clearchannel.com",
    "wof:name": "WBBG",
    "wof:placetype": "venue"
  },
  "geometry": {"coordinates":[-80.634266,41.020493],"type":"Point"}
}
