{
  "type": "Feature",
  "properties": {
    "addr:full": "21611 Center Ridge Rd Rocky River OH 44116",
    "addr:housenumber": "21611",
    "addr:postcode": "44116",
    "addr:street": "Center Ridge Rd",
    "iso:country": "US",
    "sg:address": "21611 Center Ridge Rd",
    "sg:city": "Rocky River",
    "sg:classifiers": [
      {
        "category": "Shopping",
        "subcategory": "Hobbies, Toys, \u0026 Games",
        "type": "Retail Goods"
      }
    ],
    "sg:phone": "+1 440 356 5062",
    "sg:postcode": "44116",
    "sg:province": "OH",
    "wof:name": "Zb Company Inc",
    "wof:placetype": "venue"
  },
  "geometry": {"coordinates":[-81.86087,41.459367],"type":"Point"}
}
