{
  "type": "Feature",
  "properties": {
    "addr:full": "1020 Marcie Ln Milford OH 45150",
    "addr:housenumber": "1020",
    "addr:postcode": "45150",
    "addr:street": "Marcie Ln",
    "iso:country": "US",
    "sg:address": "1020 Marcie Ln",
    "sg:city": "Milford",
    "sg:classifiers": [
      {
        "category": "Building \u0026 Trades",
        "subcategory": "Construction",
        "type": "Services"
      }
    ],
    "sg:phone": "+1 513 831 6580",
    "sg:postcode": "45150",
    "sg:province": "OH",
    "sg:tags": [
      "foundation",
      "contractor"
    ],
    "wof:name": "Buckeye Structure",
    "wof:placetype": "venue"
  },
  "geometry": {"coordinates":[-84.245741,39.182161],"type":"Point"}
}
