{
  "type": "Feature",
  "properties": {
    "addr:full": "15657 Brookpark Rd Cleveland OH 44142",
    "addr:housenumber": "15657",
    "addr:postcode": "44142",
    "addr:street": "Brookpark Rd",
    "iso:country": "US",
    "sg:address": "15657 Brookpark Rd",
    "sg:city": "Cleveland",
    "sg:classifiers": [
      {
        "category": "Wholesale",
        "subcategory": "Construction Materials",
        "type": "Manufacturing \u0026 Wholesale Goods"
      }
    ],
    "sg:phone": "+1 216 635 1682",
    "sg:postcode": "44142",
    "sg:province": "OH",
    "sg:tags": [
      "lumber"
    ],
    "wof:name": "Allegheny Plywood Co Inc",
    "wof:placetype": "venue"
  },
  "geometry": {"coordinates":[-81.806565,41.418481],"type":"Point"}
}
