{
  "type": "Feature",
  "properties": {
    "addr:full": "10520 Pippin Rd Cincinnati OH 45231",
    "addr:housenumber": "10520",
    "addr:postcode": "45231",
    "addr:street": "Pippin Rd",
    "iso:country": "US",
    "sg:address": "10520 Pippin Rd",
    "sg:city": "Cincinnati",
    "sg:classifiers": [
      {
        "category": "Wholesale",
        "subcategory": "Plants",
        "type": "Manufacturing \u0026 Wholesale Goods"
      }
    ],
    "sg:phone": "+1 513 825 1885",
    "sg:postcode": "45231",
    "sg:province": "OH",
    "sg:tags": [
      "supply"
    ],
    "sg:website": "www.tristatefoliage.com",
    "wof:name": "Tri State Foliage Inc",
    "wof:placetype": "venue"
  },
  "geometry": {"coordinates":[-84.574153,39.267133],"type":"Point"}
}
