{
  "type": "Feature",
  "properties": {
    "iso:country":"US",
    "sg:address":"10845 Cable St",
    "sg:city":"Whitehouse",
    "sg:classifiers":[
        {
            "category":"Real Estate",
            "subcategory":"Real Estate Operator",
            "type":"Services"
        }
    ],
    "sg:phone":"+1 419 877 0056",
    "sg:postcode":"43571",
    "sg:province":"OH",
    "sg:tags":[
        "building",
        "apartment"
    ],
    "wof:name":"High Pt Commons Retirement Vlg",
    "wof:placetype":"venue"
},
  "geometry": {"coordinates":[-83.80152200000001,41.523781],"type":"Point"}
}