{
  "type": "Feature",
  "properties": {
    "addr:full": "645 Helke Rd Vandalia OH 45377",
    "addr:housenumber": "645",
    "addr:postcode": "45377",
    "addr:street": "Helke Rd",
    "iso:country": "US",
    "sg:address": "645 Helke Rd",
    "sg:city": "Vandalia",
    "sg:classifiers": [
      {
        "category": "Organizations",
        "subcategory": "Religious Organization",
        "type": "Services"
      }
    ],
    "sg:phone": "+1 937 898 2864",
    "sg:postcode": "45377",
    "sg:province": "OH",
    "sg:tags": [
      "church"
    ],
    "sg:website": "www.openbibleeast.org",
    "wof:name": "Open Bible Churches-Eastern",
    "wof:placetype": "venue"
  },
  "geometry": {"coordinates":[-84.208655,39.884634],"type":"Point"}
}
