{
  "type": "Feature",
  "properties": {
    "iso:country":"US",
    "sg:address":"100 Millersburg St",
    "sg:city":"Nashville",
    "sg:classifiers":[
        {
            "category":"Personal",
            "type":"Services"
        }
    ],
    "sg:phone":"+1 330 378 2314",
    "sg:postcode":"44661",
    "sg:province":"OH",
    "sg:tags":[
        "genealogist"
    ],
    "wof:name":"Holmes County Genealogy Soc",
    "wof:placetype":"venue"
},
  "geometry": {"coordinates":[-82.11249,40.596322],"type":"Point"}
}