{
  "type": "Feature",
  "properties": {
    "addr:full": "229 E 15th Ave Columbus OH 43201",
    "addr:housenumber": "229",
    "addr:postcode": "43201",
    "addr:street": "E 15Th Ave",
    "iso:country": "US",
    "sg:address": "229 E 15th Ave",
    "sg:city": "Columbus",
    "sg:classifiers": [
      {
        "category": "Organizations",
        "subcategory": "Community Association",
        "type": "Services"
      }
    ],
    "sg:phone": "+1 614 294 3561",
    "sg:postcode": "43201",
    "sg:province": "OH",
    "sg:tags": [
      "sorority",
      "fraternity"
    ],
    "wof:name": "Delta Delta Delta Sorority",
    "wof:placetype": "venue"
  },
  "geometry": {"coordinates":[-83.003005,39.999736],"type":"Point"}
}
