{
  "type": "Feature",
  "properties": {
    "iso:country":"US",
    "sg:address":"4467 Industrial Pkwy",
    "sg:city":"Cleveland",
    "sg:classifiers":[
        {
            "category":"Manufacturing",
            "subcategory":"Tools & Machinery",
            "type":"Manufacturing & Wholesale Goods"
        }
    ],
    "sg:phone":"+1 216 252 3900",
    "sg:postcode":"44135",
    "sg:province":"OH",
    "sg:tags":[
        "equipment",
        "hospital",
        "supply"
    ],
    "wof:name":"Health Aid Of Ohio Inc",
    "wof:placetype":"venue"
},
  "geometry": {"coordinates":[-81.79272400000001,41.426906],"type":"Point"}
}