{
  "type": "Feature",
  "properties": {
    "iso:country":"US",
    "sg:address":"1335 Dublin Rd",
    "sg:city":"Columbus",
    "sg:classifiers":[
        {
            "category":"Manufacturing",
            "subcategory":"Printing",
            "type":"Manufacturing & Wholesale Goods"
        }
    ],
    "sg:phone":"+1 614 486 3444",
    "sg:postcode":"43215",
    "sg:province":"OH",
    "sg:tags":[
        "print",
        "shop",
        "copying"
    ],
    "wof:name":"Colortech Graphics & Printing",
    "wof:placetype":"venue"
},
  "geometry": {"coordinates":[-83.06251399999999,39.97976],"type":"Point"}
}