{
  "type": "Feature",
  "properties": {
    "addr:full": "562 Woodbay Dr Columbus OH 43230",
    "addr:housenumber": "562",
    "addr:postcode": "43230",
    "addr:street": "Woodbay Dr",
    "iso:country": "US",
    "sg:address": "562 Woodbay Dr",
    "sg:city": "Columbus",
    "sg:classifiers": [
      {
        "category": "Building \u0026 Trades",
        "subcategory": "Construction",
        "type": "Services"
      }
    ],
    "sg:phone": "+1 614 475 7830",
    "sg:postcode": "43230",
    "sg:province": "OH",
    "wof:name": "Slaughters Painting",
    "wof:placetype": "venue"
  },
  "geometry": {"coordinates":[-82.891922,40.033677],"type":"Point"}
}
