{
  "type": "Feature",
  "properties": {
    "iso:country":"US",
    "sg:address":"562 Woodbay Dr",
    "sg:city":"Columbus",
    "sg:classifiers":[
        {
            "category":"Building & Trades",
            "subcategory":"Construction",
            "type":"Services"
        }
    ],
    "sg:phone":"+1 614 475 7830",
    "sg:postcode":"43230",
    "sg:province":"OH",
    "wof:name":"Slaughters Painting",
    "wof:placetype":"venue"
},
  "geometry": {"coordinates":[-82.891922,40.033677],"type":"Point"}
}