{
  "type": "Feature",
  "properties": {
    "iso:country":"US",
    "sg:address":"4152 Rozelle Creek Rd",
    "sg:city":"Chillicothe",
    "sg:classifiers":[
        {
            "category":"Food & Beverages",
            "subcategory":"Groceries & Convenience Stores",
            "type":"Retail Goods"
        }
    ],
    "sg:phone":"+1 740 663 5661",
    "sg:postcode":"45601",
    "sg:province":"OH",
    "wof:name":"A & R Market",
    "wof:placetype":"venue"
},
  "geometry": {"coordinates":[-82.98474,39.247332],"type":"Point"}
}