{
  "type": "Feature",
  "properties": {
    "addr:full": "4152 Rozelle Creek Rd Chillicothe OH 45601",
    "addr:postcode": "4152;45601",
    "addr:street": "Rozelle Creek Rd",
    "iso:country": "US",
    "sg:address": "4152 Rozelle Creek Rd",
    "sg:city": "Chillicothe",
    "sg:classifiers": [
      {
        "category": "Food \u0026 Beverages",
        "subcategory": "Groceries \u0026 Convenience Stores",
        "type": "Retail Goods"
      }
    ],
    "sg:phone": "+1 740 663 5661",
    "sg:postcode": "45601",
    "sg:province": "OH",
    "wof:name": "A \u0026 R Market",
    "wof:placetype": "venue"
  },
  "geometry": {"coordinates":[-82.98474,39.247332],"type":"Point"}
}
