{
  "type": "Feature",
  "properties": {
    "addr:full":"287 Fair Ave Quaker City OH 43773",
    "addr:housenumber":"287",
    "addr:postcode":"43773",
    "addr:street":"Fair Ave",
    "iso:country":"US",
    "sg:address":"287 Fair Ave",
    "sg:city":"Quaker City",
    "sg:classifiers":[
        {
            "category":"Organizations",
            "subcategory":"Religious Organization",
            "type":"Services"
        }
    ],
    "sg:phone":"+1 740 679 2871",
    "sg:postcode":"43773",
    "sg:province":"OH",
    "sg:tags":[
        "church"
    ],
    "wof:name":"Living Water Fellowship",
    "wof:placetype":"venue"
},
  "geometry": {"coordinates":[-81.236823,40.05773],"type":"Point"}
}