{
  "type": "Feature",
  "properties": {
    "iso:country":"US",
    "sg:address":"6985 Truck World Blvd",
    "sg:city":"Hubbard",
    "sg:classifiers":[
        {
            "category":"Freight",
            "type":"Transportation"
        }
    ],
    "sg:phone":"+1 330 534 4787",
    "sg:postcode":"44425",
    "sg:province":"OH",
    "sg:tags":[
        "trucking"
    ],
    "wof:name":"TRL Inc",
    "wof:placetype":"venue"
},
  "geometry": {"coordinates":[-80.565218,41.177785],"type":"Point"}
}