{
  "type": "Feature",
  "properties": {
    "iso:country":"US",
    "sg:address":"5425 W 140th St",
    "sg:city":"Cleveland",
    "sg:classifiers":[
        {
            "category":"Organizations",
            "subcategory":"Professional Association",
            "type":"Services"
        }
    ],
    "sg:phone":"+1 216 267 6060",
    "sg:postcode":"44142",
    "sg:province":"OH",
    "sg:tags":[
        "sales"
    ],
    "wof:name":"Northbridge",
    "wof:placetype":"venue"
},
  "geometry": {"coordinates":[-81.791554,41.414649],"type":"Point"}
}