{
  "type": "Feature",
  "properties": {
    "addr:full": "26340 Curtiss Wright Pkwy Cleveland OH 44143",
    "addr:postcode": "26340;44143",
    "addr:street": "Wright Pkwy",
    "iso:country": "US",
    "sg:address": "26340 Curtiss Wright Pkwy",
    "sg:city": "Cleveland",
    "sg:classifiers": [
      {
        "category": "Airport",
        "type": "Transportation"
      }
    ],
    "sg:phone": "+1 216 523 4805",
    "sg:postcode": "44143",
    "sg:province": "OH",
    "sg:tags": [
      "airplane",
      "hangar"
    ],
    "wof:name": "Flight Operations",
    "wof:placetype": "venue"
  },
  "geometry": {"coordinates":[-81.494274,41.565008],"type":"Point"}
}
