{
  "type": "Feature",
  "properties": {
    "addr:full":"3130 N Co Rd 25A Troy OH 45373",
    "addr:housenumber":"3130;25a",
    "addr:postcode":"45373",
    "addr:street":"N Co Rd",
    "iso:country":"US",
    "sg:address":"3130 N Co Rd 25A",
    "sg:city":"Troy",
    "sg:classifiers":[
        {
            "category":"Health Services",
            "subcategory":"Doctor",
            "type":"Services"
        }
    ],
    "sg:phone":"+1 937 335 9633",
    "sg:postcode":"45373",
    "sg:province":"OH",
    "sg:tags":[
        "physician",
        "surgeon"
    ],
    "wof:name":"Upper Valley Kidney Clinic",
    "wof:placetype":"venue"
},
  "geometry": {"coordinates":[-84.22411099999999,40.089297],"type":"Point"}
}