{
  "type": "Feature",
  "properties": {
    "iso:country":"US",
    "sg:address":"1459 Iris Glen Dr",
    "sg:city":"Twinsburg",
    "sg:classifiers":[
        {
            "category":"Wholesale",
            "subcategory":"Vending Machines",
            "type":"Manufacturing & Wholesale Goods"
        }
    ],
    "sg:phone":"+1 330 963 0041",
    "sg:postcode":"44087",
    "sg:province":"OH",
    "sg:tags":[
        "operator"
    ],
    "wof:name":"Sas Vending",
    "wof:placetype":"venue"
},
  "geometry": {"coordinates":[-81.473347,41.334523],"type":"Point"}
}