{
  "type": "Feature",
  "properties": {
    "addr:full": "9661 Waterford Pl Loveland OH 45140",
    "addr:housenumber": "9661",
    "addr:postcode": "45140",
    "addr:street": "Waterford Pl",
    "iso:country": "US",
    "sg:address": "9661 Waterford Pl",
    "sg:city": "Loveland",
    "sg:classifiers": [
      {
        "category": "Real Estate",
        "subcategory": "Real Estate Agent",
        "type": "Services"
      }
    ],
    "sg:phone": "+1 513 899 9582",
    "sg:postcode": "45140",
    "sg:province": "OH",
    "sg:tags": [
      "appraiser"
    ],
    "wof:name": "Fiehler \u0026 Assoc Inc",
    "wof:placetype": "venue"
  },
  "geometry": {"coordinates":[-84.291662,39.289298],"type":"Point"}
}
