{
  "type": "Feature",
  "properties": {
    "iso:country":"US",
    "sg:address":"9661 Waterford Pl",
    "sg:city":"Loveland",
    "sg:classifiers":[
        {
            "category":"Real Estate",
            "subcategory":"Real Estate Agent",
            "type":"Services"
        }
    ],
    "sg:phone":"+1 513 899 9582",
    "sg:postcode":"45140",
    "sg:province":"OH",
    "sg:tags":[
        "appraiser"
    ],
    "wof:name":"Fiehler & Assoc Inc",
    "wof:placetype":"venue"
},
  "geometry": {"coordinates":[-84.291662,39.289298],"type":"Point"}
}