{
  "type": "Feature",
  "properties": {
    "iso:country":"US",
    "sg:address":"5518 Mad River Rd",
    "sg:city":"Dayton",
    "sg:classifiers":[
        {
            "category":"Building & Trades",
            "subcategory":"Construction",
            "type":"Services"
        }
    ],
    "sg:phone":"+1 937 428 7754",
    "sg:postcode":"45459",
    "sg:province":"OH",
    "sg:tags":[
        "hanging",
        "contractor"
    ],
    "wof:name":"Spreadmaster Painting Inc",
    "wof:placetype":"venue"
},
  "geometry": {"coordinates":[-84.178229,39.666056],"type":"Point"}
}