{
  "type": "Feature",
  "properties": {
    "addr:full":"125 Furnace Run Dr Akron OH 44307",
    "addr:housenumber":"125",
    "addr:postcode":"44307",
    "addr:street":"Furnace Run Dr",
    "iso:country":"US",
    "sg:address":"125 Furnace Run Dr",
    "sg:city":"Akron",
    "sg:classifiers":[
        {
            "category":"Organizations",
            "subcategory":"Religious Organization",
            "type":"Services"
        }
    ],
    "sg:phone":"+1 330 773 7449",
    "sg:postcode":"44307",
    "sg:province":"OH",
    "sg:tags":[
        "clergy"
    ],
    "wof:name":"Rickey G Brown",
    "wof:placetype":"venue"
},
  "geometry": {"coordinates":[-81.529785,41.069219],"type":"Point"}
}