{
  "type": "Feature",
  "properties": {
    "iso:country":"US",
    "sg:address":"1221 E Patterson St",
    "sg:city":"Alliance",
    "sg:classifiers":[
        {
            "category":"Organizations",
            "subcategory":"Religious Organization",
            "type":"Services"
        }
    ],
    "sg:phone":"+1 330 821 0435",
    "sg:postcode":"44601",
    "sg:province":"OH",
    "sg:tags":[
        "church"
    ],
    "wof:name":"Church Of God In Christ",
    "wof:placetype":"venue"
},
  "geometry": {"coordinates":[-81.089243,40.923161],"type":"Point"}
}