{
  "type": "Feature",
  "properties": {
    "addr:full": "303 N Fulton St Wauseon OH 43567",
    "addr:housenumber": "303",
    "addr:postcode": "43567",
    "addr:street": "N Fulton St",
    "iso:country": "US",
    "sg:address": "303 N Fulton St",
    "sg:city": "Wauseon",
    "sg:classifiers": [
      {
        "category": "Government",
        "subcategory": "Office",
        "type": "Public Place"
      }
    ],
    "sg:phone": "+1 419 335 0328",
    "sg:postcode": "43567",
    "sg:province": "OH",
    "sg:tags": [
      "county"
    ],
    "wof:name": "Fulton County Republican Cmmtt",
    "wof:placetype": "venue"
  },
  "geometry": {"coordinates":[-84.142217,41.551407],"type":"Point"}
}
