{
  "type": "Feature",
  "properties": {
    "addr:full": "2210 E Dublin Granville Rd Columbus OH 43229",
    "addr:housenumber": "2210",
    "addr:postcode": "43229",
    "addr:street": "E Dublin Granville Rd",
    "iso:country": "US",
    "sg:address": "2210 E Dublin Granville Rd",
    "sg:city": "Columbus",
    "sg:classifiers": [
      {
        "category": "Professional",
        "type": "Services"
      }
    ],
    "sg:phone": "+1 614 523 1919",
    "sg:postcode": "43229",
    "sg:province": "OH",
    "sg:tags": [
      "establishment"
    ],
    "wof:name": "W D's",
    "wof:placetype": "venue"
  },
  "geometry": {"coordinates":[-82.956854,40.086233],"type":"Point"}
}
