{
  "type": "Feature",
  "properties": {
    "addr:full": "8099 Mayfield Rd Chesterland OH 44026",
    "addr:housenumber": "8099",
    "addr:postcode": "44026",
    "addr:street": "Mayfield Rd",
    "iso:country": "US",
    "sg:address": "8099 Mayfield Rd",
    "sg:city": "Chesterland",
    "sg:classifiers": [
      {
        "category": "Home \u0026 Garden",
        "subcategory": "Carpets \u0026 Floor Coverings",
        "type": "Retail Goods"
      }
    ],
    "sg:phone": "+1 440 729 2434",
    "sg:postcode": "44026",
    "sg:province": "OH",
    "sg:tags": [
      "dealer",
      "rug"
    ],
    "wof:name": "Sarafian Oriental Rug Co",
    "wof:placetype": "venue"
  },
  "geometry": {"coordinates":[-81.34862,41.522265],"type":"Point"}
}
