{
  "type": "Feature",
  "properties": {
    "iso:country":"US",
    "sg:address":"917 Main St",
    "sg:city":"Cincinnati",
    "sg:classifiers":[
        {
            "category":"Real Estate",
            "subcategory":"Real Estate Operator",
            "type":"Services"
        }
    ],
    "sg:phone":"+1 513 977 4220",
    "sg:postcode":"45202",
    "sg:province":"OH",
    "sg:tags":[
        "property",
        "lessor"
    ],
    "wof:name":"917 Prtners An Ohio Gen Partnr",
    "wof:placetype":"venue"
},
  "geometry": {"coordinates":[-84.511032,39.106745],"type":"Point"}
}