{
  "type": "Feature",
  "properties": {
    "iso:country":"US",
    "sg:address":"6756 Pence Shewman Rd",
    "sg:city":"Eldorado",
    "sg:classifiers":[
        {
            "category":"Wholesale",
            "subcategory":"Meat",
            "type":"Manufacturing & Wholesale Goods"
        }
    ],
    "sg:phone":"+1 937 273 2911",
    "sg:postcode":"45321",
    "sg:province":"OH",
    "sg:tags":[
        "product"
    ],
    "wof:name":"Tyson Fresh Meats",
    "wof:placetype":"venue"
},
  "geometry": {"coordinates":[-84.69679600000001,39.841886],"type":"Point"}
}