{
  "type": "Feature",
  "properties": {
    "addr:full":"11606 Buckeye Rd Cleveland OH 44120",
    "addr:housenumber":"11606",
    "addr:postcode":"44120",
    "addr:street":"Buckeye Rd",
    "iso:country":"US",
    "sg:address":"11606 Buckeye Rd",
    "sg:city":"Cleveland",
    "sg:classifiers":[
        {
            "category":"Restaurant",
            "type":"Food & Drink"
        }
    ],
    "sg:phone":"+1 216 721 3877",
    "sg:postcode":"44120",
    "sg:province":"OH",
    "sg:tags":[
        "caterer"
    ],
    "wof:name":"Sunshine Cuisine",
    "wof:placetype":"venue"
},
  "geometry": {"coordinates":[-81.602244,41.480851],"type":"Point"}
}