{
  "type": "Feature",
  "properties": {
    "iso:country":"US",
    "sg:address":"5301 Mayfield Rd",
    "sg:city":"Cleveland",
    "sg:classifiers":[
        {
            "category":"Personal",
            "type":"Services"
        }
    ],
    "sg:phone":"+1 440 473 5108",
    "sg:postcode":"44124",
    "sg:province":"OH",
    "sg:tags":[
        "executive"
    ],
    "wof:name":"Building Department",
    "wof:placetype":"venue"
},
  "geometry": {"coordinates":[-81.487998,41.520018],"type":"Point"}
}