{
  "type": "Feature",
  "properties": {
    "addr:full":"870 N 20th St Columbus OH 43219",
    "addr:housenumber":"870",
    "addr:postcode":"43219",
    "addr:street":"N 20Th St",
    "iso:country":"US",
    "sg:address":"870 N 20th St",
    "sg:city":"Columbus",
    "sg:classifiers":[
        {
            "category":"Building & Trades",
            "subcategory":"Construction",
            "type":"Services"
        }
    ],
    "sg:phone":"+1 614 252 1050",
    "sg:postcode":"43219",
    "sg:province":"OH",
    "sg:tags":[
        "product",
        "asphalt"
    ],
    "sg:website":"www.ableindustries.net",
    "wof:name":"Able Industries Inc",
    "wof:placetype":"venue"
},
  "geometry": {"coordinates":[-82.97234,39.984171],"type":"Point"}
}