{
  "type": "Feature",
  "properties": {
    "iso:country":"US",
    "sg:address":"2806 Fisher Rd",
    "sg:city":"Columbus",
    "sg:classifiers":[
        {
            "category":"Retail",
            "subcategory":"Repair Shop",
            "type":"Services"
        }
    ],
    "sg:phone":"+1 614 308 9028",
    "sg:postcode":"43204",
    "sg:province":"OH",
    "sg:tags":[
        "electrical",
        "major",
        "appliance",
        "household"
    ],
    "wof:name":"Capital City Appliance Service",
    "wof:placetype":"venue"
},
  "geometry": {"coordinates":[-83.079552,39.972277],"type":"Point"}
}