{
  "type": "Feature",
  "properties": {
    "addr:full": "2800 E Midlothian Blvd Struthers OH 44471",
    "addr:housenumber": "2800",
    "addr:postcode": "44471",
    "addr:street": "E Midlothian Blvd",
    "iso:country": "US",
    "sg:address": "2800 E Midlothian Blvd",
    "sg:city": "Struthers",
    "sg:classifiers": [
      {
        "category": "Real Estate",
        "subcategory": "Surveying",
        "type": "Services"
      }
    ],
    "sg:phone": "+1 330 755 5734",
    "sg:postcode": "44471",
    "sg:province": "OH",
    "sg:tags": [
      "surveyor"
    ],
    "wof:name": "GMS Surveyors \u0026 Engineers",
    "wof:placetype": "venue"
  },
  "geometry": {"coordinates":[-80.603634,41.06068],"type":"Point"}
}
