{
  "type": "Feature",
  "properties": {
    "addr:full":"2968 Dialton Rd St Paris OH 43072",
    "addr:housenumber":"2968",
    "addr:postcode":"43072",
    "addr:street":"Dialton Rd St",
    "iso:country":"US",
    "sg:address":"2968 Dialton Rd",
    "sg:city":"St Paris",
    "sg:classifiers":[
        {
            "category":"Organizations",
            "subcategory":"Religious Organization",
            "type":"Services"
        }
    ],
    "sg:phone":"+1 937 663 5862",
    "sg:postcode":"43072",
    "sg:province":"OH",
    "sg:tags":[
        "church"
    ],
    "wof:name":"Grafton Christiansburg Churc",
    "wof:placetype":"venue"
},
  "geometry": {"coordinates":[-83.935631,40.07675],"type":"Point"}
}