{
  "type": "Feature",
  "properties": {
    "addr:full":"8261 Diagonal Rd Streetsboro OH 44241",
    "addr:housenumber":"8261",
    "addr:postcode":"44241",
    "addr:street":"Diagonal Rd",
    "iso:country":"US",
    "sg:address":"8261 Diagonal Rd",
    "sg:city":"Streetsboro",
    "sg:classifiers":[
        {
            "category":"Retail",
            "subcategory":"Animal Services",
            "type":"Services"
        }
    ],
    "sg:phone":"+1 330 626 2040",
    "sg:postcode":"44241",
    "sg:province":"OH",
    "sg:tags":[
        "breeder",
        "horse"
    ],
    "wof:name":"Sahbra Farms",
    "wof:placetype":"venue"
},
  "geometry": {"coordinates":[-81.316946,41.214752],"type":"Point"}
}