{
  "type": "Feature",
  "properties": {
    "iso:country":"US",
    "sg:address":"7544 State Rte 56",
    "sg:city":"Mechanicsburg",
    "sg:classifiers":[
        {
            "category":"Wholesale",
            "subcategory":"Non-durable Goods",
            "type":"Manufacturing & Wholesale Goods"
        }
    ],
    "sg:phone":"+1 937 834 2276",
    "sg:postcode":"43044",
    "sg:province":"OH",
    "wof:name":"King Distributing West Cent",
    "wof:placetype":"venue"
},
  "geometry": {"coordinates":[-83.587166,40.020705],"type":"Point"}
}