{
  "type": "Feature",
  "properties": {
    "iso:country":"US",
    "sg:address":"5781 S Park Blvd",
    "sg:city":"Cleveland",
    "sg:classifiers":[
        {
            "category":"Retail",
            "subcategory":"Portrait Studio",
            "type":"Services"
        }
    ],
    "sg:phone":"+1 440 842 4010",
    "sg:postcode":"44134",
    "sg:province":"OH",
    "sg:tags":[
        "photographer"
    ],
    "wof:name":"Foremost Fotography",
    "wof:placetype":"venue"
},
  "geometry": {"coordinates":[-81.699996,41.405548],"type":"Point"}
}