{
  "type": "Feature",
  "properties": {
    "iso:country":"US",
    "sg:address":"5249 Bromwick Dr",
    "sg:city":"Dayton",
    "sg:classifiers":[
        {
            "category":"Food & Beverages",
            "subcategory":"Specialty",
            "type":"Retail Goods"
        }
    ],
    "sg:phone":"+1 937 837 0363",
    "sg:postcode":"45426",
    "sg:province":"OH",
    "wof:name":"Woodbridge Distribution",
    "wof:placetype":"venue"
},
  "geometry": {"coordinates":[-84.270729,39.822695],"type":"Point"}
}