{
  "type": "Feature",
  "properties": {
    "addr:full": "1401 Central Pkwy Cincinnati OH 45214",
    "addr:housenumber": "1401",
    "addr:postcode": "45214",
    "addr:street": "Central Pkwy",
    "iso:country": "US",
    "sg:address": "1401 Central Pkwy",
    "sg:city": "Cincinnati",
    "sg:classifiers": [
      {
        "category": "Professional",
        "type": "Services"
      }
    ],
    "sg:phone": "+1 513 721 8900",
    "sg:postcode": "45214",
    "sg:province": "OH",
    "wof:name": "Mogulmedia",
    "wof:placetype": "venue"
  },
  "geometry": {"coordinates":[-84.520322,39.110507],"type":"Point"}
}
