{
  "type": "Feature",
  "properties": {
    "addr:full": "1468 Main St Hamilton IN 45013",
    "addr:housenumber": "1468",
    "addr:postcode": "45013",
    "addr:street": "Main St",
    "iso:country": "US",
    "sg:address": "1468 Main St",
    "sg:city": "Hamilton",
    "sg:classifiers": [
      {
        "category": "Personal",
        "subcategory": "Beauty Salon",
        "type": "Services"
      }
    ],
    "sg:phone": "+1 513 863 4468",
    "sg:postcode": "45013",
    "sg:province": "IN",
    "sg:tags": [
      "shop"
    ],
    "wof:name": "Borics Hair Care For Everyone",
    "wof:placetype": "venue"
  },
  "geometry": {"coordinates":[-84.59455,39.424282],"type":"Point"}
}
