{
  "type": "Feature",
  "properties": {
    "iso:country":"US",
    "sg:address":"1000 Ghent Rd",
    "sg:city":"Fairlawn",
    "sg:classifiers":[
        {
            "category":"Wholesale",
            "subcategory":"Machinery & Supplies",
            "type":"Manufacturing & Wholesale Goods"
        }
    ],
    "sg:phone":"+1 330 668 9811",
    "sg:postcode":"44333",
    "sg:province":"OH",
    "sg:tags":[
        "salon",
        "beauty"
    ],
    "wof:name":"E W Intl Beauty Supply",
    "wof:placetype":"venue"
},
  "geometry": {"coordinates":[-81.631418,41.150967],"type":"Point"}
}