{
  "type": "Feature",
  "properties": {
    "iso:country":"US",
    "sg:address":"1500 Canton Rd",
    "sg:city":"Akron",
    "sg:classifiers":[
        {
            "category":"Health Services",
            "subcategory":"Doctor",
            "type":"Services"
        }
    ],
    "sg:phone":"+1 330 733 7911",
    "sg:postcode":"44312",
    "sg:province":"OH",
    "wof:name":"Family Dental Team Inc",
    "wof:placetype":"venue"
},
  "geometry": {"coordinates":[-81.422898,41.026504],"type":"Point"}
}