{
  "type": "Feature",
  "properties": {
    "addr:full": "697 Sundance Dr Cincinnati OH 45233",
    "addr:housenumber": "697",
    "addr:postcode": "45233",
    "addr:street": "Sundance Dr",
    "iso:country": "US",
    "sg:address": "697 Sundance Dr",
    "sg:city": "Cincinnati",
    "sg:classifiers": [
      {
        "category": "Professional",
        "subcategory": "Management \u0026 Consulting",
        "type": "Services"
      }
    ],
    "sg:phone": "+1 513 467 0170",
    "sg:postcode": "45233",
    "sg:province": "OH",
    "sg:tags": [
      "marketing",
      "consultant"
    ],
    "wof:name": "Mary Andres \u0026 Assoc",
    "wof:placetype": "venue"
  },
  "geometry": {"coordinates":[-84.668118,39.109127],"type":"Point"}
}
