{
  "type": "Feature",
  "properties": {
    "addr:full": "108 E Main St Norwalk OH 44857",
    "addr:housenumber": "108",
    "addr:postcode": "44857",
    "addr:street": "E Main St",
    "iso:country": "US",
    "sg:address": "108 E Main St",
    "sg:city": "Norwalk",
    "sg:classifiers": [
      {
        "category": "Building \u0026 Trades",
        "subcategory": "Plumbing",
        "type": "Services"
      }
    ],
    "sg:phone": "+1 419 668 8493",
    "sg:postcode": "44857",
    "sg:province": "OH",
    "sg:tags": [
      "contractor"
    ],
    "wof:name": "Bauer Heating \u0026 AC",
    "wof:placetype": "venue"
  },
  "geometry": {"coordinates":[-82.609322,41.245225],"type":"Point"}
}
