{
  "type": "Feature",
  "properties": {
    "iso:country":"US",
    "sg:address":"108 E Main St",
    "sg:city":"Norwalk",
    "sg:classifiers":[
        {
            "category":"Building & Trades",
            "subcategory":"Plumbing",
            "type":"Services"
        }
    ],
    "sg:phone":"+1 419 668 8493",
    "sg:postcode":"44857",
    "sg:province":"OH",
    "sg:tags":[
        "contractor"
    ],
    "wof:name":"Bauer Heating & AC",
    "wof:placetype":"venue"
},
  "geometry": {"coordinates":[-82.60932200000001,41.245225],"type":"Point"}
}