{
  "type": "Feature",
  "properties": {
    "iso:country":"US",
    "sg:address":"1221 Gibson St",
    "sg:city":"Youngstown",
    "sg:classifiers":[
        {
            "category":"Home & Garden",
            "subcategory":"Building Materials",
            "type":"Retail Goods"
        },
        {
            "category":"Building & Trades",
            "subcategory":"Construction",
            "type":"Services"
        }
    ],
    "sg:phone":"+1 330 747 3135",
    "sg:postcode":"44502",
    "sg:province":"OH",
    "sg:tags":[
        "carpentry",
        "door",
        "contractor"
    ],
    "wof:name":"Youngstown Automatic Door Co",
    "wof:placetype":"venue"
},
  "geometry": {"coordinates":[-80.642872,41.085651],"type":"Point"}
}