{
  "type": "Feature",
  "properties": {
    "addr:full": "1221 Gibson St Youngstown OH 44502",
    "addr:housenumber": "1221",
    "addr:postcode": "44502",
    "addr:street": "Gibson St",
    "iso:country": "US",
    "sg:address": "1221 Gibson St",
    "sg:city": "Youngstown",
    "sg:classifiers": [
      {
        "category": "Home \u0026 Garden",
        "subcategory": "Building Materials",
        "type": "Retail Goods"
      },
      {
        "category": "Building \u0026 Trades",
        "subcategory": "Construction",
        "type": "Services"
      }
    ],
    "sg:phone": "+1 330 747 3135",
    "sg:postcode": "44502",
    "sg:province": "OH",
    "sg:tags": [
      "carpentry",
      "door",
      "contractor"
    ],
    "wof:name": "Youngstown Automatic Door Co",
    "wof:placetype": "venue"
  },
  "geometry": {"coordinates":[-80.642872,41.085651],"type":"Point"}
}
