{
  "type": "Feature",
  "properties": {
    "addr:full": "2940 S Arlington Rd Akron OH 44312",
    "addr:housenumber": "2940",
    "addr:postcode": "44312",
    "addr:street": "S Arlington Rd",
    "iso:country": "US",
    "sg:address": "2940 S Arlington Rd",
    "sg:city": "Akron",
    "sg:classifiers": [
      {
        "category": "Home \u0026 Garden",
        "subcategory": "Building Materials",
        "type": "Retail Goods"
      }
    ],
    "sg:phone": "+1 330 644 1235",
    "sg:postcode": "44312",
    "sg:province": "OH",
    "sg:tags": [
      "paint"
    ],
    "wof:name": "Sherwin-Williams Paints",
    "wof:placetype": "venue"
  },
  "geometry": {"coordinates":[-81.492419,40.990977],"type":"Point"}
}
