{
  "type": "Feature",
  "properties": {
    "iso:country":"US",
    "sg:address":"1116 Straight St",
    "sg:city":"Cincinnati",
    "sg:classifiers":[
        {
            "category":"Manufacturing",
            "subcategory":"Printing",
            "type":"Manufacturing & Wholesale Goods"
        }
    ],
    "sg:phone":"+1 513 542 4400",
    "sg:postcode":"45214",
    "sg:province":"OH",
    "sg:tags":[
        "bookbinder"
    ],
    "wof:name":"Cinti Tab & Print",
    "wof:placetype":"venue"
},
  "geometry": {"coordinates":[-84.535453,39.130616],"type":"Point"}
}