{
  "type": "Feature",
  "properties": {
    "addr:full": "1116 Straight St Cincinnati OH 45214",
    "addr:housenumber": "1116",
    "addr:postcode": "45214",
    "addr:street": "Straight St",
    "iso:country": "US",
    "sg:address": "1116 Straight St",
    "sg:city": "Cincinnati",
    "sg:classifiers": [
      {
        "category": "Manufacturing",
        "subcategory": "Printing",
        "type": "Manufacturing \u0026 Wholesale Goods"
      }
    ],
    "sg:phone": "+1 513 542 4400",
    "sg:postcode": "45214",
    "sg:province": "OH",
    "sg:tags": [
      "bookbinder"
    ],
    "wof:name": "Cinti Tab \u0026 Print",
    "wof:placetype": "venue"
  },
  "geometry": {"coordinates":[-84.535453,39.130616],"type":"Point"}
}
