{
  "type": "Feature",
  "properties": {
    "iso:country":"US",
    "sg:address":"9401 Towne Square Ave",
    "sg:city":"Cincinnati",
    "sg:classifiers":[
        {
            "category":"Retail",
            "subcategory":"Veterinary Services",
            "type":"Services"
        }
    ],
    "sg:phone":"+1 513 793 1875",
    "sg:postcode":"45242",
    "sg:province":"OH",
    "sg:website":"www.townesquareanimalclinic.com",
    "wof:name":"Towne Square Animal Clinic",
    "wof:placetype":"venue"
},
  "geometry": {"coordinates":[-84.376375,39.228132],"type":"Point"}
}