{
  "type": "Feature",
  "properties": {
    "iso:country":"US",
    "sg:address":"24400 Highland Rd",
    "sg:city":"Cleveland",
    "sg:classifiers":[
        {
            "category":"Manufacturing",
            "subcategory":"Glass & Minerals",
            "type":"Manufacturing & Wholesale Goods"
        }
    ],
    "sg:phone":"+1 216 266 9738",
    "sg:postcode":"44143",
    "sg:province":"OH",
    "sg:tags":[
        "laboratory",
        "p",
        "testing",
        "commercial",
        "mfg"
    ],
    "wof:name":"GE",
    "wof:placetype":"venue"
},
  "geometry": {"coordinates":[-81.523447,41.553875],"type":"Point"}
}