{
  "type": "Feature",
  "properties": {
    "addr:full": "447 Oberlin Elyria Rd Elyria OH 44035",
    "addr:housenumber": "447",
    "addr:postcode": "44035",
    "addr:street": "Oberlin Elyria Rd",
    "iso:country": "US",
    "sg:address": "447 Oberlin Elyria Rd",
    "sg:city": "Elyria",
    "sg:classifiers": [
      {
        "category": "Wholesale",
        "subcategory": "Scrap",
        "type": "Manufacturing \u0026 Wholesale Goods"
      }
    ],
    "sg:phone": "+1 440 284 2656",
    "sg:postcode": "44035",
    "sg:province": "OH",
    "sg:tags": [
      "recycling",
      "center"
    ],
    "wof:name": "Black River Industries",
    "wof:placetype": "venue"
  },
  "geometry": {"coordinates":[-82.116226,41.343797],"type":"Point"}
}
