{
  "type": "Feature",
  "properties": {
    "iso:country":"US",
    "sg:address":"447 Oberlin Elyria Rd",
    "sg:city":"Elyria",
    "sg:classifiers":[
        {
            "category":"Wholesale",
            "subcategory":"Scrap",
            "type":"Manufacturing & Wholesale Goods"
        }
    ],
    "sg:phone":"+1 440 284 2656",
    "sg:postcode":"44035",
    "sg:province":"OH",
    "sg:tags":[
        "recycling",
        "center"
    ],
    "wof:name":"Black River Industries",
    "wof:placetype":"venue"
},
  "geometry": {"coordinates":[-82.116226,41.343797],"type":"Point"}
}