{
  "type": "Feature",
  "properties": {
    "addr:full": "2806 W Monroe St Sandusky OH 44870",
    "addr:housenumber": "2806",
    "addr:postcode": "44870",
    "addr:street": "W Monroe St",
    "iso:country": "US",
    "sg:address": "2806 W Monroe St",
    "sg:city": "Sandusky",
    "sg:classifiers": [
      {
        "category": "Manufacturing",
        "subcategory": "Metals",
        "type": "Manufacturing \u0026 Wholesale Goods"
      }
    ],
    "sg:phone": "+1 419 625 5125",
    "sg:postcode": "44870",
    "sg:province": "OH",
    "sg:tags": [
      "foundry",
      "iron"
    ],
    "wof:name": "G \u0026 C Foundry Co",
    "wof:placetype": "venue"
  },
  "geometry": {"coordinates":[-82.737884,41.446105],"type":"Point"}
}
