{
  "type": "Feature",
  "properties": {
    "iso:country":"US",
    "sg:address":"39119 Barnesville Bethesda Rd",
    "sg:city":"Bethesda",
    "sg:classifiers":[
        {
            "category":"Recreation",
            "type":"Entertainment"
        }
    ],
    "sg:phone":"+1 740 484 4792",
    "sg:postcode":"43719",
    "sg:province":"OH",
    "sg:tags":[
        "stable"
    ],
    "wof:name":"Road's End Farm",
    "wof:placetype":"venue"
},
  "geometry": {"coordinates":[-81.10347,40.002537],"type":"Point"}
}