{
  "type": "Feature",
  "properties": {
    "addr:full": "2443 Royalview Ct Cincinnati OH 45244",
    "addr:postcode": "2443;45244",
    "addr:street": "Royalview Ct",
    "iso:country": "US",
    "sg:address": "2443 Royalview Ct",
    "sg:city": "Cincinnati",
    "sg:classifiers": [
      {
        "category": "Professional",
        "subcategory": "Management \u0026 Consulting",
        "type": "Services"
      }
    ],
    "sg:phone": "+1 513 607 1742",
    "sg:postcode": "45244",
    "sg:province": "OH",
    "wof:name": "Don AHearn \u0026 Associates",
    "wof:placetype": "venue"
  },
  "geometry": {"coordinates":[-84.365303,39.100551],"type":"Point"}
}
