{
  "type": "Feature",
  "properties": {
    "iso:country":"US",
    "sg:address":"2443 Royalview Ct",
    "sg:city":"Cincinnati",
    "sg:classifiers":[
        {
            "category":"Professional",
            "subcategory":"Management & Consulting",
            "type":"Services"
        }
    ],
    "sg:phone":"+1 513 607 1742",
    "sg:postcode":"45244",
    "sg:province":"OH",
    "wof:name":"Don AHearn & Associates",
    "wof:placetype":"venue"
},
  "geometry": {"coordinates":[-84.365303,39.100551],"type":"Point"}
}