{
  "type": "Feature",
  "properties": {
    "iso:country":"US",
    "sg:address":"1251 E Main St",
    "sg:city":"Ashland",
    "sg:classifiers":[
        {
            "category":"Health Services",
            "subcategory":"Nursing And Care Facility",
            "type":"Services"
        }
    ],
    "sg:phone":"+1 419 281 9595",
    "sg:postcode":"44805",
    "sg:province":"OH",
    "sg:tags":[
        "home",
        "convalescent"
    ],
    "wof:name":"Cyrstal Care Ctr",
    "wof:placetype":"venue"
},
  "geometry": {"coordinates":[-82.29056199999999,40.863947],"type":"Point"}
}