{
  "type": "Feature",
  "properties": {
    "addr:full":"3375 N Dayton Xenia Rd Dayton OH 45432",
    "addr:housenumber":"3375",
    "addr:postcode":"45432",
    "addr:street":"N Dayton Xenia Rd",
    "iso:country":"US",
    "sg:address":"3375 N Dayton Xenia Rd",
    "sg:city":"Dayton",
    "sg:classifiers":[
        {
            "category":"Recreation",
            "type":"Entertainment"
        }
    ],
    "sg:phone":"+1 937 431 1980",
    "sg:postcode":"45432",
    "sg:province":"OH",
    "sg:tags":[
        "martial",
        "arts",
        "instruction"
    ],
    "wof:name":"Beavercreek Martial Arts",
    "wof:placetype":"venue"
},
  "geometry": {"coordinates":[-84.062456,39.730872],"type":"Point"}
}