{
  "type": "Feature",
  "properties": {
    "addr:full": "765 McCartney Rd Youngstown OH 44505",
    "addr:housenumber": "765",
    "addr:postcode": "44505",
    "addr:street": "Mccartney Rd",
    "iso:country": "US",
    "sg:address": "765 McCartney Rd",
    "sg:city": "Youngstown",
    "sg:classifiers": [
      {
        "category": "Home \u0026 Garden",
        "subcategory": "Hardware",
        "type": "Retail Goods"
      }
    ],
    "sg:phone": "+1 330 743 7431",
    "sg:postcode": "44505",
    "sg:province": "OH",
    "wof:name": "Campbell Hardware",
    "wof:placetype": "venue"
  },
  "geometry": {"coordinates":[-80.586289,41.090274],"type":"Point"}
}
