{
  "type": "Feature",
  "properties": {
    "iso:country":"US",
    "sg:address":"765 McCartney Rd",
    "sg:city":"Youngstown",
    "sg:classifiers":[
        {
            "category":"Home & Garden",
            "subcategory":"Hardware",
            "type":"Retail Goods"
        }
    ],
    "sg:phone":"+1 330 743 7431",
    "sg:postcode":"44505",
    "sg:province":"OH",
    "wof:name":"Campbell Hardware",
    "wof:placetype":"venue"
},
  "geometry": {"coordinates":[-80.58628899999999,41.090274],"type":"Point"}
}