{
  "type": "Feature",
  "properties": {
    "iso:country":"US",
    "sg:address":"3575 Reserve Commons Dr",
    "sg:city":"Medina",
    "sg:classifiers":[
        {
            "category":"Health Services",
            "subcategory":"Doctor",
            "type":"Services"
        }
    ],
    "sg:phone":"+1 330 764 4994",
    "sg:postcode":"44256",
    "sg:province":"OH",
    "sg:tags":[
        "physician",
        "surgeon"
    ],
    "wof:name":"Cardiovascular Medicine Assoc",
    "wof:placetype":"venue"
},
  "geometry": {"coordinates":[-81.81619999999999,41.137645],"type":"Point"}
}