{
  "type": "Feature",
  "properties": {
    "addr:full":"3715 Twp Rd 142 Findlay OH 45840",
    "addr:housenumber":"3715",
    "addr:postcode":"45840",
    "addr:street":"Twp Rd 142",
    "iso:country":"US",
    "sg:address":"3715 Twp Rd 142",
    "sg:city":"Findlay",
    "sg:classifiers":[
        {
            "category":"Building & Trades",
            "subcategory":"Construction",
            "type":"Services"
        }
    ],
    "sg:phone":"+1 419 299 3795",
    "sg:postcode":"45840",
    "sg:province":"OH",
    "sg:tags":[
        "contractor"
    ],
    "wof:name":"Robert J Siefer",
    "wof:placetype":"venue"
},
  "geometry": {"coordinates":[-83.66895100000001,41.1133],"type":"Point"}
}