{
  "type": "Feature",
  "properties": {
    "addr:full":"5412 Monroe St Toledo OH 43623",
    "addr:housenumber":"5412",
    "addr:postcode":"43623",
    "addr:street":"Monroe St",
    "iso:country":"US",
    "sg:address":"5412 Monroe St",
    "sg:city":"Toledo",
    "sg:classifiers":[
        {
            "category":"Retail",
            "subcategory":"Portrait Studio",
            "type":"Services"
        }
    ],
    "sg:phone":"+1 419 842 1510",
    "sg:postcode":"43623",
    "sg:province":"OH",
    "sg:tags":[
        "photographer"
    ],
    "wof:name":"Moto Photo",
    "wof:placetype":"venue"
},
  "geometry": {"coordinates":[-83.665182,41.706298],"type":"Point"}
}