{
  "type": "Feature",
  "properties": {
    "addr:full": "5796 Sarah Ave NW Warren OH 44483",
    "addr:housenumber": "5796",
    "addr:postcode": "44483",
    "addr:street": "Sarah Ave Nw",
    "iso:country": "US",
    "sg:address": "5796 Sarah Ave NW",
    "sg:city": "Warren",
    "sg:classifiers": [
      {
        "category": "Wholesale",
        "subcategory": "Electrical",
        "type": "Manufacturing \u0026 Wholesale Goods"
      }
    ],
    "sg:phone": "+1 330 550 4319",
    "sg:postcode": "44483",
    "sg:province": "OH",
    "sg:tags": [
      "center",
      "arcade",
      "entertainment"
    ],
    "wof:name": "Surfs Up Fun Center",
    "wof:placetype": "venue"
  },
  "geometry": {"coordinates":[-80.855454,41.310916],"type":"Point"}
}
