{
  "type": "Feature",
  "properties": {
    "addr:full":"848 Kenwick Rd Columbus OH 43209",
    "addr:housenumber":"848",
    "addr:postcode":"43209",
    "addr:street":"Kenwick Rd",
    "iso:country":"US",
    "sg:address":"848 Kenwick Rd",
    "sg:city":"Columbus",
    "sg:classifiers":[
        {
            "category":"Professional",
            "subcategory":"Computer Services",
            "type":"Services"
        }
    ],
    "sg:phone":"+1 614 975 5539",
    "sg:postcode":"43209",
    "sg:province":"OH",
    "sg:tags":[
        "related"
    ],
    "wof:name":"Project Consulting & Resour",
    "wof:placetype":"venue"
},
  "geometry": {"coordinates":[-82.924071,39.954079],"type":"Point"}
}