{
  "type": "Feature",
  "properties": {
    "iso:country":"US",
    "sg:address":"641 Griswold St NE",
    "sg:city":"Warren",
    "sg:classifiers":[
        {
            "category":"Wholesale",
            "subcategory":"Scrap",
            "type":"Manufacturing & Wholesale Goods"
        }
    ],
    "sg:phone":"+1 330 373 1391",
    "sg:postcode":"44483",
    "sg:province":"OH",
    "sg:tags":[
        "metal",
        "iron"
    ],
    "wof:name":"Warren Scrap Co",
    "wof:placetype":"venue"
},
  "geometry": {"coordinates":[-80.810974,41.251995],"type":"Point"}
}