{
  "type": "Feature",
  "properties": {
    "addr:full": "1189 Lyons Rd Dayton OH 45458",
    "addr:housenumber": "1189",
    "addr:postcode": "45458",
    "addr:street": "Lyons Rd",
    "iso:country": "US",
    "sg:address": "1189 Lyons Rd",
    "sg:city": "Dayton",
    "sg:classifiers": [
      {
        "category": "Wholesale",
        "subcategory": "Electrical",
        "type": "Manufacturing \u0026 Wholesale Goods"
      }
    ],
    "sg:phone": "+1 937 291 9200",
    "sg:postcode": "45458",
    "sg:province": "OH",
    "sg:tags": [
      "equipment"
    ],
    "wof:name": "Asco Valve Inc",
    "wof:placetype": "venue"
  },
  "geometry": {"coordinates":[-84.193955,39.627737],"type":"Point"}
}
