{
  "type": "Feature",
  "properties": {
    "iso:country":"US",
    "sg:address":"9083 Leavitt Rd",
    "sg:city":"Elyria",
    "sg:classifiers":[
        {
            "category":"Building & Trades",
            "subcategory":"Landscaping Services",
            "type":"Services"
        }
    ],
    "sg:phone":"+1 440 986 2477",
    "sg:postcode":"44035",
    "sg:province":"OH",
    "sg:tags":[
        "landscape"
    ],
    "wof:name":"Landscape Sales",
    "wof:placetype":"venue"
},
  "geometry": {"coordinates":[-82.21035999999999,41.366707],"type":"Point"}
}