{
  "type": "Feature",
  "properties": {
    "iso:country":"US",
    "sg:address":"102 E Woodside Dr",
    "sg:city":"Gambier",
    "sg:classifiers":[
        {
            "category":"Social Services",
            "subcategory":"Child Care",
            "type":"Services"
        }
    ],
    "sg:phone":"+1 740 427 5819",
    "sg:postcode":"43022",
    "sg:province":"OH",
    "sg:tags":[
        "kindergarten",
        "academic",
        "school"
    ],
    "wof:name":"Gazebo School Park",
    "wof:placetype":"venue"
},
  "geometry": {"coordinates":[-82.39635199999999,40.382673],"type":"Point"}
}