{
  "type": "Feature",
  "properties": {
    "addr:full":"5585 Brandt Pike Dayton OH 45424",
    "addr:housenumber":"5585",
    "addr:postcode":"45424",
    "addr:street":"Brandt Pike",
    "iso:country":"US",
    "sg:address":"5585 Brandt Pike",
    "sg:city":"Dayton",
    "sg:classifiers":[
        {
            "category":"Professional",
            "subcategory":"Management & Consulting",
            "type":"Services"
        }
    ],
    "sg:phone":"+1 937 237 0112",
    "sg:postcode":"45424",
    "sg:province":"OH",
    "sg:tags":[
        "consultant",
        "training"
    ],
    "wof:name":"WBI",
    "wof:placetype":"venue"
},
  "geometry": {"coordinates":[-84.121977,39.830694],"type":"Point"}
}