{
  "type": "Feature",
  "properties": {
    "addr:full":"1703 Brookpark Rd Cleveland OH 44109",
    "addr:housenumber":"1703",
    "addr:postcode":"44109",
    "addr:street":"Brookpark Rd",
    "iso:country":"US",
    "sg:address":"1703 Brookpark Rd",
    "sg:city":"Cleveland",
    "sg:classifiers":[
        {
            "category":"Real Estate",
            "subcategory":"Real Estate Agent",
            "type":"Services"
        }
    ],
    "sg:phone":"+1 216 749 6300",
    "sg:postcode":"44109",
    "sg:province":"OH",
    "sg:tags":[
        "property",
        "management"
    ],
    "sg:website":"www.wrpmapartments.com",
    "wof:name":"Western Reserve Property Mgmt",
    "wof:placetype":"venue"
},
  "geometry": {"coordinates":[-81.694249,41.419136],"type":"Point"}
}