{
  "type": "Feature",
  "properties": {
    "addr:full": "10708 Elk Ave Cleveland OH 44108",
    "addr:housenumber": "10708",
    "addr:postcode": "44108",
    "addr:street": "Elk Ave",
    "iso:country": "US",
    "sg:address": "10708 Elk Ave",
    "sg:city": "Cleveland",
    "sg:classifiers": [
      {
        "category": "Personal",
        "subcategory": "Beauty Salon",
        "type": "Services"
      }
    ],
    "sg:phone": "+1 216 761 7725",
    "sg:postcode": "44108",
    "sg:province": "OH",
    "wof:name": "Carlito's Cuts",
    "wof:placetype": "venue"
  },
  "geometry": {"coordinates":[-81.611011,41.543353],"type":"Point"}
}
