{
  "type": "Feature",
  "properties": {
    "addr:full":"223 W Steels Corners Rd Cuyahoga Falls OH 44223",
    "addr:housenumber":"223",
    "addr:postcode":"44223",
    "addr:street":"W Steels Corners Rd",
    "iso:country":"US",
    "sg:address":"223 W Steels Corners Rd",
    "sg:city":"Cuyahoga Falls",
    "sg:classifiers":[
        {
            "category":"Building & Trades",
            "subcategory":"Construction",
            "type":"Services"
        }
    ],
    "sg:phone":"+1 330 926 1044",
    "sg:postcode":"44223",
    "sg:province":"OH",
    "sg:tags":[
        "house",
        "improvement",
        "home"
    ],
    "wof:name":"Ramsey's Remodeling",
    "wof:placetype":"venue"
},
  "geometry": {"coordinates":[-81.515168,41.181022],"type":"Point"}
}