{
  "type": "Feature",
  "properties": {
    "iso:country":"US",
    "sg:address":"3867 April Ln",
    "sg:city":"Columbus",
    "sg:classifiers":[
        {
            "category":"Utilities",
            "subcategory":"Refuse",
            "type":"Services"
        }
    ],
    "sg:phone":"+1 614 235 0104",
    "sg:postcode":"43227",
    "sg:province":"OH",
    "sg:tags":[
        "pet",
        "waste",
        "removal"
    ],
    "sg:website":"www.petbutler.net",
    "wof:name":"Pet Butler Dog Waste Removal",
    "wof:placetype":"venue"
},
  "geometry": {"coordinates":[-82.89670099999999,39.942252],"type":"Point"}
}