{
  "type": "Feature",
  "properties": {
    "addr:full": "14195 New Buffalo Rd Columbiana OH 44408",
    "addr:housenumber": "14195",
    "addr:postcode": "44408",
    "addr:street": "New Buffalo Rd",
    "iso:country": "US",
    "sg:address": "14195 New Buffalo Rd",
    "sg:city": "Columbiana",
    "sg:classifiers": [
      {
        "category": "Building \u0026 Trades",
        "subcategory": "Landscaping Services",
        "type": "Services"
      }
    ],
    "sg:phone": "+1 330 482 9345",
    "sg:postcode": "44408",
    "sg:province": "OH",
    "sg:tags": [
      "landscape",
      "contractor"
    ],
    "wof:name": "X Treme Landscape",
    "wof:placetype": "venue"
  },
  "geometry": {"coordinates":[-80.702032,40.917974],"type":"Point"}
}
