{
  "type": "Feature",
  "properties": {
    "iso:country":"US",
    "sg:address":"14195 New Buffalo Rd",
    "sg:city":"Columbiana",
    "sg:classifiers":[
        {
            "category":"Building & Trades",
            "subcategory":"Landscaping Services",
            "type":"Services"
        }
    ],
    "sg:phone":"+1 330 482 9345",
    "sg:postcode":"44408",
    "sg:province":"OH",
    "sg:tags":[
        "landscape",
        "contractor"
    ],
    "wof:name":"X Treme Landscape",
    "wof:placetype":"venue"
},
  "geometry": {"coordinates":[-80.702032,40.917974],"type":"Point"}
}