{
  "type": "Feature",
  "properties": {
    "addr:full": "6831 Chapel Rd Madison OH 44057",
    "addr:housenumber": "6831",
    "addr:postcode": "44057",
    "addr:street": "Chapel Rd",
    "iso:country": "US",
    "sg:address": "6831 Chapel Rd",
    "sg:city": "Madison",
    "sg:classifiers": [
      {
        "category": "Health Services",
        "subcategory": "Nursing And Care Facility",
        "type": "Services"
      }
    ],
    "sg:phone": "+1 440 428 5103",
    "sg:postcode": "44057",
    "sg:province": "OH",
    "sg:tags": [
      "home",
      "convalescent"
    ],
    "wof:name": "Cardinal Woods Skilling Nurse",
    "wof:placetype": "venue"
  },
  "geometry": {"coordinates":[-81.048362,41.819834],"type":"Point"}
}
