{
  "type": "Feature",
  "properties": {
    "addr:full": "4080 Roselea Pl Columbus OH 43214",
    "addr:housenumber": "4080",
    "addr:postcode": "43214",
    "addr:street": "Roselea Pl",
    "iso:country": "US",
    "sg:address": "4080 Roselea Pl",
    "sg:city": "Columbus",
    "sg:classifiers": [
      {
        "category": "Organizations",
        "subcategory": "Membership Organization",
        "type": "Services"
      }
    ],
    "sg:phone": "+1 614 267 2502",
    "sg:postcode": "43214",
    "sg:province": "OH",
    "sg:tags": [
      "profit",
      "athletic",
      "association"
    ],
    "sg:website": "www.ohsaa.org",
    "wof:name": "Ohio High School Athletic Assn",
    "wof:placetype": "venue"
  },
  "geometry": {"coordinates":[-83.021452,40.045575],"type":"Point"}
}
