{
  "type": "Feature",
  "properties": {
    "addr:full":"1350 Oxley Rd Columbus OH 43212",
    "addr:housenumber":"1350",
    "addr:postcode":"43212",
    "addr:street":"Oxley Rd",
    "iso:country":"US",
    "sg:address":"1350 Oxley Rd",
    "sg:city":"Columbus",
    "sg:classifiers":[
        {
            "category":"Recreation",
            "subcategory":"Arcade",
            "type":"Entertainment"
        }
    ],
    "sg:phone":"+1 614 299 4141",
    "sg:postcode":"43212",
    "sg:province":"OH",
    "sg:tags":[
        "amusement",
        "devices"
    ],
    "sg:website":"www.shafferservices.com",
    "wof:name":"Shaffer Services Inc",
    "wof:placetype":"venue"
},
  "geometry": {"coordinates":[-83.03504599999999,39.986369],"type":"Point"}
}