{
  "type": "Feature",
  "properties": {
    "addr:full":"813 Elmore Ave Akron OH 44302",
    "addr:housenumber":"813",
    "addr:postcode":"44302",
    "addr:street":"Elmore Ave",
    "iso:country":"US",
    "sg:address":"813 Elmore Ave",
    "sg:city":"Akron",
    "sg:classifiers":[
        {
            "category":"Wholesale",
            "subcategory":"Metals & Minerals",
            "type":"Manufacturing & Wholesale Goods"
        }
    ],
    "sg:phone":"+1 330 869 8172",
    "sg:postcode":"44302",
    "sg:province":"OH",
    "sg:tags":[
        "center"
    ],
    "wof:name":"Eximport Trading Co Inc",
    "wof:placetype":"venue"
},
  "geometry": {"coordinates":[-81.54635,41.095059],"type":"Point"}
}