{
  "type": "Feature",
  "properties": {
    "iso:country":"US",
    "sg:address":"15458 Co Rd 72",
    "sg:city":"Findlay",
    "sg:classifiers":[
        {
            "category":"Building & Trades",
            "subcategory":"Construction",
            "type":"Services"
        }
    ],
    "sg:phone":"+1 419 365 9900",
    "sg:postcode":"45840",
    "sg:province":"OH",
    "sg:tags":[
        "roofing",
        "contractor"
    ],
    "wof:name":"Seal-Ect Svc",
    "wof:placetype":"venue"
},
  "geometry": {"coordinates":[-83.669997,40.94385],"type":"Point"}
}