{
  "type": "Feature",
  "properties": {
    "iso:country":"US",
    "sg:address":"139 N Main St",
    "sg:city":"Cadiz",
    "sg:classifiers":[
        {
            "category":"Organizations",
            "subcategory":"Religious Organization",
            "type":"Services"
        }
    ],
    "sg:phone":"+1 740 942 2235",
    "sg:postcode":"43907",
    "sg:province":"OH",
    "sg:tags":[
        "church"
    ],
    "wof:name":"First Church Of Christ",
    "wof:placetype":"venue"
},
  "geometry": {"coordinates":[-80.996899,40.272986],"type":"Point"}
}