{
  "type": "Feature",
  "properties": {
    "addr:full":"4453 Center Rd Youngstown OH 44514",
    "addr:housenumber":"4453",
    "addr:postcode":"44514",
    "addr:street":"Center Rd",
    "iso:country":"US",
    "sg:address":"4453 Center Rd",
    "sg:city":"Youngstown",
    "sg:classifiers":[
        {
            "category":"Shopping",
            "subcategory":"Stationery & Office Supplies",
            "type":"Retail Goods"
        },
        {
            "category":"Shopping",
            "subcategory":"Hobbies, Toys, & Games",
            "type":"Retail Goods"
        },
        {
            "category":"Education",
            "subcategory":"Special Training",
            "type":"Public Place"
        },
        {
            "category":"Recreation",
            "subcategory":"Gun Range",
            "type":"Entertainment"
        },
        {
            "category":"Arena",
            "subcategory":"Sports Club",
            "type":"Entertainment"
        }
    ],
    "sg:phone":"+1 330 540 5425",
    "sg:postcode":"44514",
    "sg:province":"OH",
    "sg:tags":[
        "instruction",
        "marksmanship",
        "gunsmith",
        "equipment",
        "self defense",
        "safety",
        "martial art"
    ],
    "sg:website":"http://www.martialartstrainingcenter.net",
    "wof:name":"Martial Arts Training Center",
    "wof:placetype":"venue"
},
  "geometry": {"coordinates":[-80.569559,41.023791],"type":"Point"}
}