{
  "type": "Feature",
  "properties": {
    "addr:full":"95 Rosewood Dr Avon Lake OH 44012",
    "addr:housenumber":"95",
    "addr:postcode":"44012",
    "addr:street":"Rosewood Dr",
    "iso:country":"US",
    "sg:address":"95 Rosewood Dr",
    "sg:city":"Avon Lake",
    "sg:classifiers":[
        {
            "category":"Manufacturing",
            "subcategory":"Tools & Machinery",
            "type":"Manufacturing & Wholesale Goods"
        }
    ],
    "sg:phone":"+1 440 933 2880",
    "sg:postcode":"44012",
    "sg:province":"OH",
    "sg:tags":[
        "surgical",
        "mfg"
    ],
    "wof:name":"Out On A Limb Tree Service",
    "wof:placetype":"venue"
},
  "geometry": {"coordinates":[-82.03984699999999,41.508756],"type":"Point"}
}