{
  "type": "Feature",
  "properties": {
    "addr:full": "95 Rosewood Dr Avon Lake OH 44012",
    "addr:housenumber": "95",
    "addr:postcode": "44012",
    "addr:street": "Rosewood Dr",
    "iso:country": "US",
    "sg:address": "95 Rosewood Dr",
    "sg:city": "Avon Lake",
    "sg:classifiers": [
      {
        "category": "Manufacturing",
        "subcategory": "Tools \u0026 Machinery",
        "type": "Manufacturing \u0026 Wholesale Goods"
      }
    ],
    "sg:phone": "+1 440 933 2880",
    "sg:postcode": "44012",
    "sg:province": "OH",
    "sg:tags": [
      "surgical",
      "mfg"
    ],
    "wof:name": "Out On A Limb Tree Service",
    "wof:placetype": "venue"
  },
  "geometry": {"coordinates":[-82.039847,41.508756],"type":"Point"}
}
