{
  "type": "Feature",
  "properties": {
    "addr:full": "875 Moe Dr Akron OH 44310",
    "addr:housenumber": "875",
    "addr:postcode": "44310",
    "addr:street": "Moe Dr",
    "iso:country": "US",
    "sg:address": "875 Moe Dr",
    "sg:city": "Akron",
    "sg:classifiers": [
      {
        "category": "Manufacturing",
        "subcategory": "Tools \u0026 Machinery",
        "type": "Manufacturing \u0026 Wholesale Goods"
      }
    ],
    "sg:phone": "+1 330 633 0765",
    "sg:postcode": "44310",
    "sg:province": "OH",
    "sg:tags": [
      "metalworking"
    ],
    "wof:name": "R-Eight Tool Corp",
    "wof:placetype": "venue"
  },
  "geometry": {"coordinates":[-81.483865,41.107659],"type":"Point"}
}
