{
  "type": "Feature",
  "properties": {
    "iso:country":"US",
    "sg:address":"7331 E Bayshore Rd",
    "sg:city":"Lakeside Marblehead",
    "sg:phone":"+1 419 732 2786",
    "sg:postcode":"43440",
    "sg:province":"OH",
    "sg:tags":[
        "farm",
        "corn",
        "soybean"
    ],
    "wof:name":"Arthur Kihlken",
    "wof:placetype":"venue"
},
  "geometry": {"coordinates":[-82.792531,41.508111],"type":"Point"}
}