{
  "type": "Feature",
  "properties": {
    "addr:full": "19691 Euclid Ave Euclid OH 44117",
    "addr:housenumber": "19691",
    "addr:postcode": "44117",
    "addr:street": "Euclid Ave",
    "iso:country": "US",
    "sg:address": "19691 Euclid Ave",
    "sg:city": "Euclid",
    "sg:classifiers": [
      {
        "category": "Building \u0026 Trades",
        "subcategory": "Landscaping Services",
        "type": "Services"
      }
    ],
    "sg:phone": "+1 216 486 1886",
    "sg:postcode": "44117",
    "sg:province": "OH",
    "sg:tags": [
      "designer",
      "consultant",
      "snow",
      "contractor",
      "removal",
      "landscape"
    ],
    "wof:name": "Unique Concepts Landscaping Co",
    "wof:placetype": "venue"
  },
  "geometry": {"coordinates":[-81.542969,41.56226],"type":"Point"}
}
