{
  "type": "Feature",
  "properties": {
    "addr:full":"1225 Lake Center St NW Uniontown OH 44685",
    "addr:housenumber":"1225",
    "addr:postcode":"44685",
    "addr:street":"Lake Center St Nw",
    "iso:country":"US",
    "sg:address":"1225 Lake Center St NW",
    "sg:city":"Uniontown",
    "sg:classifiers":[
        {
            "category":"Restaurant",
            "type":"Food & Drink"
        }
    ],
    "sg:phone":"+1 330 877 6542",
    "sg:postcode":"44685",
    "sg:province":"OH",
    "sg:tags":[
        "eating"
    ],
    "wof:name":"Canton Sub Co",
    "wof:placetype":"venue"
},
  "geometry": {"coordinates":[-81.36343100000001,40.958643],"type":"Point"}
}