{
  "type": "Feature",
  "properties": {
    "iso:country":"US",
    "sg:address":"1600 E Long St",
    "sg:city":"Columbus",
    "sg:classifiers":[
        {
            "category":"Education",
            "subcategory":"Library",
            "type":"Public Place"
        }
    ],
    "sg:phone":"+1 614 645 2275",
    "sg:postcode":"43203",
    "sg:province":"OH",
    "wof:name":"Columbus Metropolitan Library",
    "wof:placetype":"venue"
},
  "geometry": {"coordinates":[-82.958479,39.968651],"type":"Point"}
}