{
  "type": "Feature",
  "properties": {
    "addr:full": "1 Petro Pl Girard OH 44420",
    "addr:housenumber": "1",
    "addr:postcode": "44420",
    "addr:street": "Petro Pl",
    "iso:country": "US",
    "sg:address": "1 Petro Pl",
    "sg:city": "Girard",
    "sg:classifiers": [
      {
        "category": "Communications",
        "type": "Services"
      }
    ],
    "sg:phone": "+1 330 544 6494",
    "sg:postcode": "44420",
    "sg:province": "OH",
    "wof:name": "Paliden Communications",
    "wof:placetype": "venue"
  },
  "geometry": {"coordinates":[-80.716718,41.141335],"type":"Point"}
}
