{
  "type": "Feature",
  "properties": {
    "iso:country":"US",
    "sg:address":"2339 Fulton Rd",
    "sg:city":"Wooster",
    "sg:classifiers":[
        {
            "category":"Retail",
            "subcategory":"Repair Shop",
            "type":"Services"
        }
    ],
    "sg:phone":"+1 330 435 6127",
    "sg:postcode":"44691",
    "sg:province":"OH",
    "sg:tags":[
        "scooter",
        "motorcycle",
        "motor"
    ],
    "wof:name":"Dirt Road Cycles",
    "wof:placetype":"venue"
},
  "geometry": {"coordinates":[-81.919,40.903518],"type":"Point"}
}