{
  "type": "Feature",
  "properties": {
    "iso:country":"US",
    "sg:address":"6300 Commerce Center Dr",
    "sg:city":"Groveport",
    "sg:classifiers":[
        {
            "category":"Professional",
            "subcategory":"Business Services",
            "type":"Services"
        }
    ],
    "sg:phone":"+1 614 837 0099",
    "sg:postcode":"43125",
    "sg:province":"OH",
    "sg:tags":[
        "plant",
        "design",
        "maintenance"
    ],
    "sg:website":"www.initialplants.com",
    "wof:name":"Initial Tropical Plants",
    "wof:placetype":"venue"
},
  "geometry": {"coordinates":[-82.91242699999999,39.846603],"type":"Point"}
}