{
  "type": "Feature",
  "properties": {
    "addr:full":"764 Decatur Ct Cincinnati OH 45240",
    "addr:housenumber":"764",
    "addr:postcode":"45240",
    "addr:street":"Decatur Ct",
    "iso:country":"US",
    "sg:address":"764 Decatur Ct",
    "sg:city":"Cincinnati",
    "sg:classifiers":[
        {
            "category":"Professional",
            "type":"Services"
        }
    ],
    "sg:phone":"+1 513 825 9000",
    "sg:postcode":"45240",
    "sg:province":"OH",
    "sg:tags":[
        "establishment"
    ],
    "wof:name":"Accuaire International Inc",
    "wof:placetype":"venue"
},
  "geometry": {"coordinates":[-84.50314899999999,39.278277],"type":"Point"}
}