{
  "type": "Feature",
  "properties": {
    "addr:full": "1550 N Wilson Rd Columbus OH 43204",
    "addr:housenumber": "1550",
    "addr:postcode": "43204",
    "addr:street": "N Wilson Rd",
    "iso:country": "US",
    "sg:address": "1550 N Wilson Rd",
    "sg:city": "Columbus",
    "sg:classifiers": [
      {
        "category": "Manufacturing",
        "subcategory": "Printing",
        "type": "Manufacturing \u0026 Wholesale Goods"
      }
    ],
    "sg:phone": "+1 614 276 7866",
    "sg:postcode": "43204",
    "sg:province": "OH",
    "sg:tags": [
      "commercial"
    ],
    "wof:name": "Clark Graphics Inc",
    "wof:placetype": "venue"
  },
  "geometry": {"coordinates":[-83.105958,39.985139],"type":"Point"}
}
