{
  "type": "Feature",
  "properties": {
    "addr:full":"2110 Beechmont Ave Cincinnati OH 45230",
    "addr:housenumber":"2110",
    "addr:postcode":"45230",
    "addr:street":"Beechmont Ave",
    "iso:country":"US",
    "sg:address":"2110 Beechmont Ave",
    "sg:city":"Cincinnati",
    "sg:classifiers":[
        {
            "category":"Banks & Credit Unions",
            "subcategory":"Bank",
            "type":"Services"
        }
    ],
    "sg:phone":"+1 513 231 7871",
    "sg:postcode":"45230",
    "sg:province":"OH",
    "sg:tags":[
        "federal",
        "savings",
        "loan",
        "association",
        "institution"
    ],
    "wof:name":"Mt Washington Savings & Ln Co",
    "wof:placetype":"venue"
},
  "geometry": {"coordinates":[-84.386926,39.092922],"type":"Point"}
}