{
  "type": "Feature",
  "properties": {
    "addr:full": "1022 W Woodruff Ave Toledo OH 43606",
    "addr:housenumber": "1022",
    "addr:postcode": "43606",
    "addr:street": "W Woodruff Ave",
    "iso:country": "US",
    "sg:address": "1022 W Woodruff Ave",
    "sg:city": "Toledo",
    "sg:classifiers": [
      {
        "category": "Building \u0026 Trades",
        "subcategory": "Construction",
        "type": "Services"
      }
    ],
    "sg:phone": "+1 419 244 4520",
    "sg:postcode": "43606",
    "sg:province": "OH",
    "sg:tags": [
      "hanging",
      "contractor"
    ],
    "wof:name": "Samples Painting",
    "wof:placetype": "venue"
  },
  "geometry": {"coordinates":[-83.566931,41.660257],"type":"Point"}
}
