{
  "type": "Feature",
  "properties": {
    "addr:full":"440 Downtowner Plz Coshocton OH 43812",
    "addr:housenumber":"440",
    "addr:postcode":"43812",
    "addr:street":"Downtowner Plz",
    "iso:country":"US",
    "sg:address":"440 Downtowner Plz",
    "sg:city":"Coshocton",
    "sg:classifiers":[
        {
            "category":"Home & Garden",
            "subcategory":"Household Appliances",
            "type":"Retail Goods"
        }
    ],
    "sg:phone":"+1 740 622 5956",
    "sg:postcode":"43812",
    "sg:province":"OH",
    "sg:tags":[
        "sales",
        "vacuum"
    ],
    "wof:name":"Vacshak",
    "wof:placetype":"venue"
},
  "geometry": {"coordinates":[-81.869192,40.269781],"type":"Point"}
}