{
  "type": "Feature",
  "properties": {
    "iso:country":"US",
    "sg:address":"540 W Center St",
    "sg:city":"West Mansfield",
    "sg:classifiers":[
        {
            "category":"Real Estate",
            "subcategory":"Real Estate Operator",
            "type":"Services"
        }
    ],
    "sg:phone":"+1 937 355 5291",
    "sg:postcode":"43358",
    "sg:province":"OH",
    "sg:tags":[
        "property",
        "lessor"
    ],
    "wof:name":"Dally John",
    "wof:placetype":"venue"
},
  "geometry": {"coordinates":[-83.55305300000001,40.399868],"type":"Point"}
}