{
  "type": "Feature",
  "properties": {
    "iso:country":"US",
    "sg:address":"1326 Marquette St",
    "sg:city":"Cleveland",
    "sg:classifiers":[
        {
            "category":"Retail",
            "subcategory":"Auto Repair",
            "type":"Services"
        }
    ],
    "sg:phone":"+1 216 431 0001",
    "sg:postcode":"44114",
    "sg:province":"OH",
    "sg:tags":[
        "repairing",
        "automobile"
    ],
    "wof:name":"J P Automotive",
    "wof:placetype":"venue"
},
  "geometry": {"coordinates":[-81.652861,41.52201],"type":"Point"}
}