{
  "type": "Feature",
  "properties": {
    "iso:country":"US",
    "sg:address":"4543 Everhard Rd NW",
    "sg:city":"Canton",
    "sg:classifiers":[
        {
            "category":"Insurance",
            "subcategory":"Insurance Agent",
            "type":"Services"
        }
    ],
    "sg:phone":"+1 330 493 1010",
    "sg:postcode":"44718",
    "sg:province":"OH",
    "wof:name":"Dwight E Crawford",
    "wof:placetype":"venue"
},
  "geometry": {"coordinates":[-81.43564000000001,40.857031],"type":"Point"}
}