{
  "type": "Feature",
  "properties": {
    "addr:full": "4543 Everhard Rd NW Canton OH 44718",
    "addr:housenumber": "4543",
    "addr:postcode": "44718",
    "addr:street": "Everhard Rd Nw",
    "iso:country": "US",
    "sg:address": "4543 Everhard Rd NW",
    "sg:city": "Canton",
    "sg:classifiers": [
      {
        "category": "Insurance",
        "subcategory": "Insurance Agent",
        "type": "Services"
      }
    ],
    "sg:phone": "+1 330 493 1010",
    "sg:postcode": "44718",
    "sg:province": "OH",
    "wof:name": "Dwight E Crawford",
    "wof:placetype": "venue"
  },
  "geometry": {"coordinates":[-81.43564,40.857031],"type":"Point"}
}
