{
  "type": "Feature",
  "properties": {
    "iso:country":"US",
    "sg:address":"2550 Millville Ave",
    "sg:city":"Hamilton",
    "sg:classifiers":[
        {
            "category":"Education",
            "subcategory":"School",
            "type":"Public Place"
        }
    ],
    "sg:phone":"+1 513 863 8705",
    "sg:postcode":"45013",
    "sg:province":"OH",
    "sg:website":"www.queenofpeace.swoca.net",
    "wof:name":"Queen Of Peace School",
    "wof:placetype":"venue"
},
  "geometry": {"coordinates":[-84.643164,39.393794],"type":"Point"}
}