{
  "type": "Feature",
  "properties": {
    "addr:full":"2715 Mahoning Ave Youngstown OH 44509",
    "addr:housenumber":"2715",
    "addr:postcode":"44509",
    "addr:street":"Mahoning Ave",
    "iso:country":"US",
    "sg:address":"2715 Mahoning Ave",
    "sg:city":"Youngstown",
    "sg:classifiers":[
        {
            "category":"Restaurant",
            "type":"Food & Drink"
        }
    ],
    "sg:phone":"+1 330 799 7809",
    "sg:postcode":"44509",
    "sg:province":"OH",
    "sg:tags":[
        "pizza"
    ],
    "wof:name":"Inner Circle Pizza",
    "wof:placetype":"venue"
},
  "geometry": {"coordinates":[-80.699838,41.102965],"type":"Point"}
}