{
  "type": "Feature",
  "properties": {
    "iso:country":"US",
    "sg:address":"222 S Bridge St",
    "sg:city":"Newcomerstown",
    "sg:classifiers":[
        {
            "category":"Social Services",
            "type":"Services"
        }
    ],
    "sg:phone":"+1 740 498 6151",
    "sg:postcode":"43832",
    "sg:province":"OH",
    "sg:tags":[
        "senior",
        "citizen"
    ],
    "wof:name":"Harcatus Senior Nutrition",
    "wof:placetype":"venue"
},
  "geometry": {"coordinates":[-81.606157,40.272912],"type":"Point"}
}