{
  "type": "Feature",
  "properties": {
    "iso:country":"US",
    "sg:address":"6180 Sparta Rd",
    "sg:city":"Fredericktown",
    "sg:classifiers":[
        {
            "category":"Farming",
            "subcategory":"Livestock Farm",
            "type":"Manufacturing & Wholesale Goods"
        }
    ],
    "sg:phone":"+1 740 694 6078",
    "sg:postcode":"43019",
    "sg:province":"OH",
    "sg:tags":[
        "beef",
        "feedlot",
        "cattle"
    ],
    "wof:name":"Sky High Farms",
    "wof:placetype":"venue"
},
  "geometry": {"coordinates":[-82.637327,40.431432],"type":"Point"}
}