{
  "type": "Feature",
  "properties": {
    "addr:full": "10027 Infirmary Rd Mantua OH 44255",
    "addr:postcode": "10027;44255",
    "addr:street": "Infirmary Rd",
    "iso:country": "US",
    "sg:address": "10027 Infirmary Rd",
    "sg:city": "Mantua",
    "sg:classifiers": [
      {
        "category": "Manufacturing",
        "subcategory": "Jewelry",
        "type": "Manufacturing \u0026 Wholesale Goods"
      }
    ],
    "sg:phone": "+1 330 274 0750",
    "sg:postcode": "44255",
    "sg:province": "OH",
    "sg:tags": [
      "costume",
      "mfg"
    ],
    "wof:name": "Crooked River Beadworks",
    "wof:placetype": "venue"
  },
  "geometry": {"coordinates":[-81.246599,41.26608],"type":"Point"}
}
