{
  "type": "Feature",
  "properties": {
    "iso:country":"US",
    "sg:address":"4005 Townsfair Way",
    "sg:city":"Columbus",
    "sg:classifiers":[
        {
            "category":"Shopping",
            "subcategory":"Books",
            "type":"Retail Goods"
        }
    ],
    "sg:phone":"+1 614 476 8480",
    "sg:postcode":"43219",
    "sg:province":"OH",
    "sg:tags":[
        "dealer"
    ],
    "wof:name":"Barnes & Noble Booksellers",
    "wof:placetype":"venue"
},
  "geometry": {"coordinates":[-82.914485,40.048942],"type":"Point"}
}