{
  "type": "Feature",
  "properties": {
    "addr:full": "15200 Madison Rd Middlefield OH 44062",
    "addr:housenumber": "15200",
    "addr:postcode": "44062",
    "addr:street": "Madison Rd",
    "iso:country": "US",
    "sg:address": "15200 Madison Rd",
    "sg:city": "Middlefield",
    "sg:classifiers": [
      {
        "category": "Utilities",
        "subcategory": "Refuse",
        "type": "Services"
      }
    ],
    "sg:phone": "+1 440 684 2700",
    "sg:postcode": "44062",
    "sg:province": "OH",
    "sg:tags": [
      "garbage",
      "collection"
    ],
    "wof:name": "DSI Disposal Svc Inc",
    "wof:placetype": "venue"
  },
  "geometry": {"coordinates":[-81.051279,41.45337],"type":"Point"}
}
