{
  "type": "Feature",
  "properties": {
    "iso:country":"US",
    "sg:address":"833 E Meadowlawn Blvd",
    "sg:city":"Cleveland",
    "sg:classifiers":[
        {
            "category":"Recreation",
            "type":"Entertainment"
        }
    ],
    "sg:phone":"+1 216 524 1978",
    "sg:postcode":"44131",
    "sg:province":"OH",
    "sg:tags":[
        "parks"
    ],
    "wof:name":"Country Fur N'Feather Wildlife",
    "wof:placetype":"venue"
},
  "geometry": {"coordinates":[-81.674593,41.400334],"type":"Point"}
}