{
  "type": "Feature",
  "properties": {
    "addr:full": "833 E Meadowlawn Blvd Cleveland OH 44131",
    "addr:housenumber": "833",
    "addr:postcode": "44131",
    "addr:street": "E Meadowlawn Blvd",
    "iso:country": "US",
    "sg:address": "833 E Meadowlawn Blvd",
    "sg:city": "Cleveland",
    "sg:classifiers": [
      {
        "category": "Recreation",
        "type": "Entertainment"
      }
    ],
    "sg:phone": "+1 216 524 1978",
    "sg:postcode": "44131",
    "sg:province": "OH",
    "sg:tags": [
      "parks"
    ],
    "wof:name": "Country Fur N'Feather Wildlife",
    "wof:placetype": "venue"
  },
  "geometry": {"coordinates":[-81.674593,41.400334],"type":"Point"}
}
