{
  "type": "Feature",
  "properties": {
    "addr:full": "9633 Waterford Pl Loveland OH 45140",
    "addr:housenumber": "9633",
    "addr:postcode": "45140",
    "addr:street": "Waterford Pl",
    "iso:country": "US",
    "sg:address": "9633 Waterford Pl",
    "sg:city": "Loveland",
    "sg:classifiers": [
      {
        "category": "Professional",
        "type": "Services"
      }
    ],
    "sg:phone": "+1 513 792 2964",
    "sg:postcode": "45140",
    "sg:province": "OH",
    "sg:tags": [
      "establishment"
    ],
    "wof:name": "Horizon Companies Inc",
    "wof:placetype": "venue"
  },
  "geometry": {"coordinates":[-84.29283,39.289566],"type":"Point"}
}
