{
  "type": "Feature",
  "properties": {
    "addr:full": "72116 Kinsman Rd St Clairsville OH 43950",
    "addr:postcode": "72116;43950",
    "addr:street": "Kinsman Rd",
    "iso:country": "US",
    "sg:address": "72116 Kinsman Rd",
    "sg:city": "St Clairsville",
    "sg:classifiers": [
      {
        "category": "Building \u0026 Trades",
        "subcategory": "Construction",
        "type": "Services"
      }
    ],
    "sg:phone": "+1 740 526 1155",
    "sg:postcode": "43950",
    "sg:province": "OH",
    "sg:tags": [
      "painter"
    ],
    "wof:name": "Kimmel Painting",
    "wof:placetype": "venue"
  },
  "geometry": {"coordinates":[-80.90401,40.132227],"type":"Point"}
}
