{
  "type": "Feature",
  "properties": {
    "iso:country":"US",
    "sg:address":"9321 Ravenna Rd",
    "sg:city":"Twinsburg",
    "sg:classifiers":[
        {
            "category":"Professional",
            "subcategory":"Computer Services",
            "type":"Services"
        },
        {
            "category":"Shopping",
            "subcategory":"Computers & Home Electronics",
            "type":"Retail Goods"
        }
    ],
    "sg:phone":"+1 330 405 2990",
    "sg:postcode":"44087",
    "sg:province":"OH",
    "sg:tags":[
        "software",
        "design",
        "system",
        "integrated"
    ],
    "wof:name":"Automation Software & Engrg",
    "wof:placetype":"venue"
},
  "geometry": {"coordinates":[-81.42130299999999,41.303997],"type":"Point"}
}