{
  "type": "Feature",
  "properties": {
    "addr:full": "9321 Ravenna Rd Twinsburg OH 44087",
    "addr:housenumber": "9321",
    "addr:postcode": "44087",
    "addr:street": "Ravenna Rd",
    "iso:country": "US",
    "sg:address": "9321 Ravenna Rd",
    "sg:city": "Twinsburg",
    "sg:classifiers": [
      {
        "category": "Professional",
        "subcategory": "Computer Services",
        "type": "Services"
      },
      {
        "category": "Shopping",
        "subcategory": "Computers \u0026 Home Electronics",
        "type": "Retail Goods"
      }
    ],
    "sg:phone": "+1 330 405 2990",
    "sg:postcode": "44087",
    "sg:province": "OH",
    "sg:tags": [
      "software",
      "design",
      "system",
      "integrated"
    ],
    "wof:name": "Automation Software \u0026 Engrg",
    "wof:placetype": "venue"
  },
  "geometry": {"coordinates":[-81.421303,41.303997],"type":"Point"}
}
