{
  "type": "Feature",
  "properties": {
    "addr:full": "1045 Trump Rd NW Carrollton OH 44615",
    "addr:housenumber": "1045",
    "addr:postcode": "44615",
    "addr:street": "Trump Rd Nw",
    "iso:country": "US",
    "sg:address": "1045 Trump Rd NW",
    "sg:city": "Carrollton",
    "sg:classifiers": [
      {
        "category": "Banks \u0026 Credit Unions",
        "subcategory": "Bank",
        "type": "Services"
      }
    ],
    "sg:phone": "+1 330 627 7635",
    "sg:postcode": "44615",
    "sg:province": "OH",
    "sg:website": "www.skyfi.com",
    "wof:name": "Sky Bank",
    "wof:placetype": "venue"
  },
  "geometry": {"coordinates":[-81.096367,40.59292],"type":"Point"}
}
