{
  "type": "Feature",
  "properties": {
    "addr:full":"5150 Angola Rd Toledo OH 43615",
    "addr:housenumber":"5150",
    "addr:postcode":"43615",
    "addr:street":"Angola Rd",
    "iso:country":"US",
    "sg:address":"5150 Angola Rd",
    "sg:city":"Toledo",
    "sg:classifiers":[
        {
            "category":"Building & Trades",
            "subcategory":"Landscaping Services",
            "type":"Services"
        }
    ],
    "sg:phone":"+1 419 382 3386",
    "sg:postcode":"43615",
    "sg:province":"OH",
    "sg:tags":[
        "irrigation",
        "snowplowing",
        "landscape"
    ],
    "wof:name":"Hurst Landscaping & Irrigation",
    "wof:placetype":"venue"
},
  "geometry": {"coordinates":[-83.664051,41.622783],"type":"Point"}
}