{
  "type": "Feature",
  "properties": {
    "iso:country":"US",
    "sg:address":"12609 Burton Heights Blvd",
    "sg:city":"Burton",
    "sg:classifiers":[
        {
            "category":"Building & Trades",
            "subcategory":"Landscaping Services",
            "type":"Services"
        }
    ],
    "sg:phone":"+1 440 834 0314",
    "sg:postcode":"44021",
    "sg:province":"OH",
    "sg:tags":[
        "landscape"
    ],
    "wof:name":"Napps Landscaping",
    "wof:placetype":"venue"
},
  "geometry": {"coordinates":[-81.186392,41.456522],"type":"Point"}
}