{
  "type": "Feature",
  "properties": {
    "addr:full": "50525 Beautiful Ridge Rd Clarington OH 43915",
    "addr:postcode": "50525;43915",
    "addr:street": "Beautiful Ridge Rd",
    "iso:country": "US",
    "sg:address": "50525 Beautiful Ridge Rd",
    "sg:city": "Clarington",
    "sg:phone": "+1 740 458 1644",
    "sg:postcode": "43915",
    "sg:province": "OH",
    "sg:tags": [
      "farm",
      "corn",
      "grain",
      "cash"
    ],
    "wof:name": "Miller John",
    "wof:placetype": "venue"
  },
  "geometry": {"coordinates":[-80.90373,39.72645],"type":"Point"}
}
