{
  "type": "Feature",
  "properties": {
    "addr:full": "11749 Mills Rd Garrettsville OH 44231",
    "addr:housenumber": "11749",
    "addr:postcode": "44231",
    "addr:street": "Mills Rd",
    "iso:country": "US",
    "sg:address": "11749 Mills Rd",
    "sg:city": "Garrettsville",
    "sg:classifiers": [
      {
        "category": "Banks \u0026 Credit Unions",
        "subcategory": "Bank",
        "type": "Services"
      }
    ],
    "sg:phone": "+1 330 527 5709",
    "sg:postcode": "44231",
    "sg:province": "OH",
    "sg:tags": [
      "personal",
      "institution"
    ],
    "wof:name": "Sherco Financial",
    "wof:placetype": "venue"
  },
  "geometry": {"coordinates":[-81.094836,41.311841],"type":"Point"}
}
