{
  "type": "Feature",
  "properties": {
    "iso:country":"US",
    "sg:address":"3051 Lamb Ave",
    "sg:city":"Columbus",
    "sg:classifiers":[
        {
            "category":"Retail",
            "subcategory":"Auto Repair",
            "type":"Services"
        }
    ],
    "sg:phone":"+1 614 471 1666",
    "sg:postcode":"43219",
    "sg:province":"OH",
    "sg:tags":[
        "body",
        "repairing",
        "painting",
        "shop",
        "automobile"
    ],
    "sg:website":"http://www.elitebodyworkscolumbus.com",
    "wof:name":"Elite Body Works",
    "wof:placetype":"venue"
},
  "geometry": {"coordinates":[-82.923981,39.996693],"type":"Point"}
}