{
  "type": "Feature",
  "properties": {
    "addr:full": "700 W Pete Rose Way Cincinnati OH 45203",
    "addr:housenumber": "700",
    "addr:postcode": "45203",
    "addr:street": "W Pete Rose Way",
    "iso:country": "US",
    "sg:address": "700 W Pete Rose Way",
    "sg:city": "Cincinnati",
    "sg:classifiers": [
      {
        "category": "Professional",
        "subcategory": "Business Services",
        "type": "Services"
      }
    ],
    "sg:phone": "+1 513 272 2272",
    "sg:postcode": "45203",
    "sg:province": "OH",
    "sg:tags": [
      "interior",
      "consultant",
      "decorating",
      "design",
      "decorator"
    ],
    "wof:name": "Fentress-Hughes Interiors",
    "wof:placetype": "venue"
  },
  "geometry": {"coordinates":[-84.52336,39.095608],"type":"Point"}
}
