{
  "type": "Feature",
  "properties": {
    "iso:country":"US",
    "sg:address":"32 Annandale Dr",
    "sg:city":"Chagrin Falls",
    "sg:classifiers":[
        {
            "category":"Wholesale",
            "subcategory":"Plants",
            "type":"Manufacturing & Wholesale Goods"
        }
    ],
    "sg:phone":"+1 440 338 1820",
    "sg:postcode":"44022",
    "sg:province":"OH",
    "sg:tags":[
        "supply"
    ],
    "wof:name":"Western Reserves Pines",
    "wof:placetype":"venue"
},
  "geometry": {"coordinates":[-81.33413,41.429111],"type":"Point"}
}