{
  "type": "Feature",
  "properties": {
    "iso:country":"US",
    "sg:address":"6525 Market Ave N",
    "sg:city":"Canton",
    "sg:classifiers":[
        {
            "category":"Health Services",
            "subcategory":"Chiropractor",
            "type":"Services"
        }
    ],
    "sg:phone":"+1 330 433 9000",
    "sg:postcode":"44721",
    "sg:province":"OH",
    "wof:name":"Theis Chiropractic Clinic Inc",
    "wof:placetype":"venue"
},
  "geometry": {"coordinates":[-81.363941,40.874107],"type":"Point"}
}