{
  "type": "Feature",
  "properties": {
    "iso:country":"US",
    "sg:address":"133 Aldrich Rd",
    "sg:city":"Columbus",
    "sg:phone":"+1 614 268 6093",
    "sg:postcode":"43214",
    "sg:province":"OH",
    "sg:tags":[
        "farm",
        "corn",
        "soybean"
    ],
    "wof:name":"Vern Cahill",
    "wof:placetype":"venue"
},
  "geometry": {"coordinates":[-83.023698,40.050439],"type":"Point"}
}