{
  "type": "Feature",
  "properties": {
    "iso:country":"US",
    "sg:address":"602 Parmelee Ave",
    "sg:city":"Youngstown",
    "sg:classifiers":[
        {
            "category":"Wholesale",
            "subcategory":"Medical Equipment & Supplies",
            "type":"Manufacturing & Wholesale Goods"
        }
    ],
    "sg:phone":"+1 330 742 7823",
    "sg:postcode":"44510",
    "sg:province":"OH",
    "wof:name":"Memo Supply Co Inc",
    "wof:placetype":"venue"
},
  "geometry": {"coordinates":[-80.66031,41.115053],"type":"Point"}
}