{
  "type": "Feature",
  "properties": {
    "iso:country":"US",
    "sg:address":"26225 Broadway Ave",
    "sg:city":"Bedford",
    "sg:classifiers":[
        {
            "category":"Professional",
            "subcategory":"Testing Lab",
            "type":"Services"
        }
    ],
    "sg:phone":"+1 440 232 1775",
    "sg:postcode":"44146",
    "sg:province":"OH",
    "sg:tags":[
        "development",
        "consulting",
        "research",
        "reinforced",
        "plastic"
    ],
    "wof:name":"Pultrusion Dynamics Inc",
    "wof:placetype":"venue"
},
  "geometry": {"coordinates":[-81.49138000000001,41.351661],"type":"Point"}
}