{
  "type": "Feature",
  "properties": {
    "addr:full":"417 Mount Vernon Rd Newark OH 43055",
    "addr:housenumber":"417",
    "addr:postcode":"43055",
    "addr:street":"Mount Vernon Rd",
    "iso:country":"US",
    "sg:address":"417 Mount Vernon Rd",
    "sg:city":"Newark",
    "sg:classifiers":[
        {
            "category":"Restaurant",
            "type":"Food & Drink"
        }
    ],
    "sg:phone":"+1 740 322 6448",
    "sg:postcode":"43055",
    "sg:province":"OH",
    "sg:tags":[
        "pizza"
    ],
    "sg:website":"www.stonebrospizza.com",
    "wof:name":"Stone Brothers Pizza",
    "wof:placetype":"venue"
},
  "geometry": {"coordinates":[-82.41038500000001,40.069417],"type":"Point"}
}