{
  "type": "Feature",
  "properties": {
    "addr:full":"5087 Cobblestone Dr Columbus OH 43220",
    "addr:housenumber":"5087",
    "addr:postcode":"43220",
    "addr:street":"Cobblestone Dr",
    "iso:country":"US",
    "sg:address":"5087 Cobblestone Dr",
    "sg:city":"Columbus",
    "sg:classifiers":[
        {
            "category":"Manufacturing",
            "subcategory":"Toys & Sporting Goods",
            "type":"Manufacturing & Wholesale Goods"
        }
    ],
    "sg:phone":"+1 614 451 1735",
    "sg:postcode":"43220",
    "sg:province":"OH",
    "sg:tags":[
        "mfg"
    ],
    "wof:name":"J & J Jerseys LLC",
    "wof:placetype":"venue"
},
  "geometry": {"coordinates":[-83.07836399999999,40.058825],"type":"Point"}
}