{
  "type": "Feature",
  "properties": {
    "addr:full":"300 Hilliard Rome Rd Columbus OH 43228",
    "addr:housenumber":"300",
    "addr:postcode":"43228",
    "addr:street":"Hilliard Rome Rd",
    "iso:country":"US",
    "sg:address":"300 Hilliard Rome Rd",
    "sg:city":"Columbus",
    "sg:classifiers":[
        {
            "category":"Autos & Motor Vehicles",
            "subcategory":"Fuel & Gas Station",
            "type":"Retail Goods"
        }
    ],
    "sg:phone":"+1 614 870 8066",
    "sg:postcode":"43228",
    "sg:province":"OH",
    "sg:tags":[
        "station",
        "gasoline"
    ],
    "wof:name":"Swifty Serv STA",
    "wof:placetype":"venue"
},
  "geometry": {"coordinates":[-83.145983,39.959075],"type":"Point"}
}