{
  "type": "Feature",
  "properties": {
    "addr:full":"136 Jessica Dr Dover OH 44622",
    "addr:housenumber":"136",
    "addr:postcode":"44622",
    "addr:street":"Jessica Dr",
    "iso:country":"US",
    "sg:address":"136 Jessica Dr",
    "sg:city":"Dover",
    "sg:classifiers":[
        {
            "category":"Real Estate",
            "subcategory":"Real Estate Agent",
            "type":"Services"
        }
    ],
    "sg:phone":"+1 330 343 4150",
    "sg:postcode":"44622",
    "sg:province":"OH",
    "wof:name":"Wolfe & Associates",
    "wof:placetype":"venue"
},
  "geometry": {"coordinates":[-81.494911,40.556018],"type":"Point"}
}