{
  "type": "Feature",
  "properties": {
    "iso:country":"US",
    "sg:address":"6394 Trenton Franklin Rd",
    "sg:city":"Middletown",
    "sg:classifiers":[
        {
            "category":"Freight",
            "type":"Transportation"
        }
    ],
    "sg:phone":"+1 513 420 1770",
    "sg:postcode":"45042",
    "sg:province":"OH",
    "sg:tags":[
        "cartage",
        "trucking"
    ],
    "wof:name":"Exel Transportation Svc",
    "wof:placetype":"venue"
},
  "geometry": {"coordinates":[-84.38458199999999,39.546925],"type":"Point"}
}