{
  "type": "Feature",
  "properties": {
    "addr:full":"2981 State Rte 756 Felicity OH 45120",
    "addr:housenumber":"2981",
    "addr:postcode":"45120",
    "addr:street":"State Rte 756",
    "iso:country":"US",
    "sg:address":"2981 State Rte 756",
    "sg:city":"Felicity",
    "sg:classifiers":[
        {
            "category":"Farming",
            "subcategory":"Farm",
            "type":"Manufacturing & Wholesale Goods"
        }
    ],
    "sg:phone":"+1 513 734 6520",
    "sg:postcode":"45120",
    "sg:province":"OH",
    "sg:tags":[
        "crop",
        "general"
    ],
    "wof:name":"Kenneth T Shinkle",
    "wof:placetype":"venue"
},
  "geometry": {"coordinates":[-84.128281,38.851874],"type":"Point"}
}