{
  "type": "Feature",
  "properties": {
    "addr:full": "7296 Mentor Ave Mentor OH 44060",
    "addr:housenumber": "7296",
    "addr:postcode": "44060",
    "addr:street": "Mentor Ave",
    "iso:country": "US",
    "sg:address": "7296 Mentor Ave",
    "sg:city": "Mentor",
    "sg:classifiers": [
      {
        "category": "Professional",
        "type": "Services"
      }
    ],
    "sg:phone": "+1 440 269 8004",
    "sg:postcode": "44060",
    "sg:province": "OH",
    "wof:name": "Webs Image Inc",
    "wof:placetype": "venue"
  },
  "geometry": {"coordinates":[-81.382836,41.649653],"type":"Point"}
}
