{
  "type": "Feature",
  "properties": {
    "iso:country":"US",
    "sg:address":"5805 Valley Belt Rd",
    "sg:city":"Cleveland",
    "sg:classifiers":[
        {
            "category":"Shopping",
            "type":"Retail Goods"
        },
        {
            "category":"Retail",
            "subcategory":"Repair Shop",
            "type":"Services"
        }
    ],
    "sg:phone":"+1 216 459 8700",
    "sg:postcode":"44131",
    "sg:province":"OH",
    "sg:tags":[
        "equipment",
        "electrical",
        "refrigeration",
        "supply"
    ],
    "sg:website":"www.electapplrep.com",
    "wof:name":"Electrical Appliance Repr Svc",
    "wof:placetype":"venue"
},
  "geometry": {"coordinates":[-81.651656,41.417471],"type":"Point"}
}