{
  "type": "Feature",
  "properties": {
    "addr:full": "4182 Westland Mall Columbus OH 43228",
    "addr:housenumber": "4182",
    "addr:postcode": "43228",
    "addr:street": "Westland Mall",
    "iso:country": "US",
    "sg:address": "4182 Westland Mall",
    "sg:city": "Columbus",
    "sg:classifiers": [
      {
        "category": "Shopping",
        "subcategory": "Clothing, Apparel, \u0026 Fashions",
        "type": "Retail Goods"
      }
    ],
    "sg:phone": "+1 614 272 9333",
    "sg:postcode": "43228",
    "sg:province": "OH",
    "sg:tags": [
      "shop",
      "bridal"
    ],
    "wof:name": "Wedding World",
    "wof:placetype": "venue"
  },
  "geometry": {"coordinates":[-83.115304,39.952891],"type":"Point"}
}
