{
  "type": "Feature",
  "properties": {
    "iso:country":"US",
    "sg:address":"13410 Telpahak St SE",
    "sg:city":"Minerva",
    "sg:classifiers":[
        {
            "category":"Wholesale",
            "subcategory":"Non-durable Goods",
            "type":"Manufacturing & Wholesale Goods"
        }
    ],
    "sg:phone":"+1 330 868 4766",
    "sg:postcode":"44657",
    "sg:province":"OH",
    "wof:name":"Jeff Haines Distributing Inc",
    "wof:placetype":"venue"
},
  "geometry": {"coordinates":[-81.151295,40.742585],"type":"Point"}
}