{
  "type": "Feature",
  "properties": {
    "addr:full": "13410 Telpahak St SE Minerva OH 44657",
    "addr:housenumber": "13410",
    "addr:postcode": "44657",
    "addr:street": "Telpahak St Se",
    "iso:country": "US",
    "sg:address": "13410 Telpahak St SE",
    "sg:city": "Minerva",
    "sg:classifiers": [
      {
        "category": "Wholesale",
        "subcategory": "Non-durable Goods",
        "type": "Manufacturing \u0026 Wholesale Goods"
      }
    ],
    "sg:phone": "+1 330 868 4766",
    "sg:postcode": "44657",
    "sg:province": "OH",
    "wof:name": "Jeff Haines Distributing Inc",
    "wof:placetype": "venue"
  },
  "geometry": {"coordinates":[-81.151295,40.742585],"type":"Point"}
}
