{
  "type": "Feature",
  "properties": {
    "addr:full": "119 S Main St New Carlisle OH 45344",
    "addr:housenumber": "119",
    "addr:postcode": "45344",
    "addr:street": "S Main St",
    "iso:country": "US",
    "sg:address": "119 S Main St",
    "sg:city": "New Carlisle",
    "sg:classifiers": [
      {
        "category": "Food \u0026 Beverages",
        "subcategory": "Groceries \u0026 Convenience Stores",
        "type": "Retail Goods"
      }
    ],
    "sg:phone": "+1 937 845 8852",
    "sg:postcode": "45344",
    "sg:province": "OH",
    "sg:tags": [
      "grocer"
    ],
    "wof:name": "Los Compadres",
    "wof:placetype": "venue"
  },
  "geometry": {"coordinates":[-84.025156,39.936218],"type":"Point"}
}
