{
  "type": "Feature",
  "properties": {
    "addr:full":"6645 Mount Vernon Rd Newark OH 43055",
    "addr:housenumber":"6645",
    "addr:postcode":"43055",
    "addr:street":"Mount Vernon Rd",
    "iso:country":"US",
    "sg:address":"6645 Mount Vernon Rd",
    "sg:city":"Newark",
    "sg:classifiers":[
        {
            "category":"Education",
            "subcategory":"School",
            "type":"Public Place"
        }
    ],
    "sg:phone":"+1 740 745 5982",
    "sg:postcode":"43055",
    "sg:province":"OH",
    "wof:name":"Newton Elementary School",
    "wof:placetype":"venue"
},
  "geometry": {"coordinates":[-82.42550799999999,40.153613],"type":"Point"}
}