{
  "type": "Feature",
  "properties": {
    "addr:full":"30749 Pinetree Rd Cleveland OH 44124",
    "addr:housenumber":"30749",
    "addr:postcode":"44124",
    "addr:street":"Pinetree Rd",
    "iso:country":"US",
    "sg:address":"30749 Pinetree Rd",
    "sg:city":"Cleveland",
    "sg:classifiers":[
        {
            "category":"Health Services",
            "subcategory":"Optometrist",
            "type":"Services"
        }
    ],
    "sg:phone":"+1 216 360 9955",
    "sg:postcode":"44124",
    "sg:province":"OH",
    "wof:name":"Western Reserve Optical",
    "wof:placetype":"venue"
},
  "geometry": {"coordinates":[-81.46039500000001,41.46247],"type":"Point"}
}