{
  "type": "Feature",
  "properties": {
    "iso:country":"US",
    "sg:address":"3430 W Pleasant Valley Rd",
    "sg:city":"Cleveland",
    "sg:classifiers":[
        {
            "category":"Retail",
            "subcategory":"Repair Shop",
            "type":"Services"
        }
    ],
    "sg:phone":"+1 440 885 0048",
    "sg:postcode":"44134",
    "sg:province":"OH",
    "sg:tags":[
        "equipment",
        "printing"
    ],
    "wof:name":"Print Tech",
    "wof:placetype":"venue"
},
  "geometry": {"coordinates":[-81.704522,41.36177],"type":"Point"}
}