{
  "type": "Feature",
  "properties": {
    "addr:full":"129 Bidwell Ave Fremont OH 43420",
    "addr:housenumber":"129",
    "addr:postcode":"43420",
    "addr:street":"Bidwell Ave",
    "iso:country":"US",
    "sg:address":"129 Bidwell Ave",
    "sg:city":"Fremont",
    "sg:classifiers":[
        {
            "category":"Retail",
            "subcategory":"Laundry & Dry Cleaning",
            "type":"Services"
        }
    ],
    "sg:phone":"+1 419 332 0707",
    "sg:postcode":"43420",
    "sg:province":"OH",
    "sg:tags":[
        "linen",
        "supply"
    ],
    "wof:name":"Metrotex Textile Rental Svc",
    "wof:placetype":"venue"
},
  "geometry": {"coordinates":[-83.11243399999999,41.346206],"type":"Point"}
}