{
  "type": "Feature",
  "properties": {
    "addr:full": "1215 Harlan Rd Lucas OH 44843",
    "addr:housenumber": "1215",
    "addr:postcode": "44843",
    "addr:street": "Harlan Rd",
    "iso:country": "US",
    "sg:address": "1215 Harlan Rd",
    "sg:city": "Lucas",
    "sg:classifiers": [
      {
        "category": "Building \u0026 Trades",
        "subcategory": "Construction",
        "type": "Services"
      }
    ],
    "sg:phone": "+1 419 892 3352",
    "sg:postcode": "44843",
    "sg:province": "OH",
    "sg:tags": [
      "house"
    ],
    "wof:name": "Geisel Construction Co LLC",
    "wof:placetype": "venue"
  },
  "geometry": {"coordinates":[-82.379045,40.732872],"type":"Point"}
}
