{
  "type": "Feature",
  "properties": {
    "iso:country":"US",
    "sg:address":"4322 S Ridge Rd W",
    "sg:city":"Geneva",
    "sg:classifiers":[
        {
            "category":"Restaurant",
            "type":"Food & Drink"
        }
    ],
    "sg:phone":"+1 440 259 5144",
    "sg:postcode":"44041",
    "sg:province":"OH",
    "sg:tags":[
        "drive"
    ],
    "wof:name":"Checkers Drive-In Restaurant",
    "wof:placetype":"venue"
},
  "geometry": {"coordinates":[-80.90944500000001,41.805941],"type":"Point"}
}