{
  "type": "Feature",
  "properties": {
    "addr:full": "4322 S Ridge Rd W Geneva OH 44041",
    "addr:housenumber": "4322",
    "addr:postcode": "44041",
    "addr:street": "S Ridge Rd W",
    "iso:country": "US",
    "sg:address": "4322 S Ridge Rd W",
    "sg:city": "Geneva",
    "sg:classifiers": [
      {
        "category": "Restaurant",
        "type": "Food \u0026 Drink"
      }
    ],
    "sg:phone": "+1 440 259 5144",
    "sg:postcode": "44041",
    "sg:province": "OH",
    "sg:tags": [
      "drive"
    ],
    "wof:name": "Checkers Drive-In Restaurant",
    "wof:placetype": "venue"
  },
  "geometry": {"coordinates":[-80.909445,41.805941],"type":"Point"}
}
