{
  "type": "Feature",
  "properties": {
    "iso:country":"US",
    "sg:address":"8790 Guilford Rd",
    "sg:city":"Seville",
    "sg:classifiers":[
        {
            "category":"Retail",
            "subcategory":"Animal Services",
            "type":"Services"
        }
    ],
    "sg:phone":"+1 330 336 4787",
    "sg:postcode":"44273",
    "sg:province":"OH",
    "wof:name":"A Second Home",
    "wof:placetype":"venue"
},
  "geometry": {"coordinates":[-81.832484,41.035895],"type":"Point"}
}