{
  "type": "Feature",
  "properties": {
    "iso:country":"US",
    "sg:address":"19245 Detroit Rd",
    "sg:city":"Rocky River",
    "sg:classifiers":[
        {
            "category":"Food & Beverages",
            "subcategory":"Liquor & Beverages",
            "type":"Retail Goods"
        }
    ],
    "sg:phone":"+1 440 333 4686",
    "sg:postcode":"44116",
    "sg:province":"OH",
    "sg:tags":[
        "a",
        "bistro",
        "gourmet",
        "operates",
        "as",
        "wine"
    ],
    "wof:name":"Avas Beachcliff Tavern Inc",
    "wof:placetype":"venue"
},
  "geometry": {"coordinates":[-81.835556,41.482076],"type":"Point"}
}