{
  "type": "Feature",
  "properties": {
    "addr:full": "19245 Detroit Rd Rocky River OH 44116",
    "addr:housenumber": "19245",
    "addr:postcode": "44116",
    "addr:street": "Detroit Rd",
    "iso:country": "US",
    "sg:address": "19245 Detroit Rd",
    "sg:city": "Rocky River",
    "sg:classifiers": [
      {
        "category": "Food \u0026 Beverages",
        "subcategory": "Liquor \u0026 Beverages",
        "type": "Retail Goods"
      }
    ],
    "sg:phone": "+1 440 333 4686",
    "sg:postcode": "44116",
    "sg:province": "OH",
    "sg:tags": [
      "a",
      "bistro",
      "gourmet",
      "operates",
      "as",
      "wine"
    ],
    "wof:name": "Avas Beachcliff Tavern Inc",
    "wof:placetype": "venue"
  },
  "geometry": {"coordinates":[-81.835556,41.482076],"type":"Point"}
}
