{
  "type": "Feature",
  "properties": {
    "iso:country":"US",
    "sg:address":"6800 Cintas Blvd",
    "sg:city":"Mason",
    "sg:classifiers":[
        {
            "category":"Retail",
            "subcategory":"Laundry & Dry Cleaning",
            "type":"Services"
        }
    ],
    "sg:phone":"+1 513 459 1200",
    "sg:postcode":"45040",
    "sg:province":"OH",
    "sg:tags":[
        "uniform",
        "supply"
    ],
    "sg:website":"www.cintas-corp.com",
    "wof:name":"Cintas Corp",
    "wof:placetype":"venue"
},
  "geometry": {"coordinates":[-84.284576,39.338678],"type":"Point"}
}