{
  "type": "Feature",
  "properties": {
    "iso:country":"US",
    "sg:address":"1526 Demorest Rd",
    "sg:city":"Columbus",
    "sg:classifiers":[
        {
            "category":"Professional",
            "type":"Services"
        }
    ],
    "sg:phone":"+1 614 539 1949",
    "sg:postcode":"43228",
    "sg:province":"OH",
    "wof:name":"Rocks Unlimited",
    "wof:placetype":"venue"
},
  "geometry": {"coordinates":[-83.093819,39.921192],"type":"Point"}
}