{
  "type": "Feature",
  "properties": {
    "addr:full": "979 Bechtle Ave Springfield OH 45504",
    "addr:housenumber": "979",
    "addr:postcode": "45504",
    "addr:street": "Bechtle Ave",
    "iso:country": "US",
    "sg:address": "979 Bechtle Ave",
    "sg:city": "Springfield",
    "sg:classifiers": [
      {
        "category": "Shopping",
        "subcategory": "Department Store",
        "type": "Retail Goods"
      }
    ],
    "sg:phone": "+1 937 327 9497",
    "sg:postcode": "45504",
    "sg:province": "OH",
    "sg:tags": [
      "shop"
    ],
    "wof:name": "Big Lots Furniture",
    "wof:placetype": "venue"
  },
  "geometry": {"coordinates":[-83.835076,39.937269],"type":"Point"}
}
