{
  "type": "Feature",
  "properties": {
    "iso:country":"US",
    "sg:address":"979 Bechtle Ave",
    "sg:city":"Springfield",
    "sg:classifiers":[
        {
            "category":"Shopping",
            "subcategory":"Department Store",
            "type":"Retail Goods"
        }
    ],
    "sg:phone":"+1 937 327 9497",
    "sg:postcode":"45504",
    "sg:province":"OH",
    "sg:tags":[
        "shop"
    ],
    "wof:name":"Big Lots Furniture",
    "wof:placetype":"venue"
},
  "geometry": {"coordinates":[-83.835076,39.937269],"type":"Point"}
}