{
  "type": "Feature",
  "properties": {
    "iso:country":"US",
    "sg:address":"860 W Emmitt Ave",
    "sg:city":"Waverly",
    "sg:classifiers":[
        {
            "category":"Wholesale",
            "subcategory":"Sporting Goods",
            "type":"Manufacturing & Wholesale Goods"
        }
    ],
    "sg:phone":"+1 740 941 3242",
    "sg:postcode":"45690",
    "sg:province":"OH",
    "sg:tags":[
        "paint",
        "game",
        "ball"
    ],
    "wof:name":"J D R's Paintball & Gifts",
    "wof:placetype":"venue"
},
  "geometry": {"coordinates":[-82.990346,39.123769],"type":"Point"}
}