{
  "type": "Feature",
  "properties": {
    "iso:country":"US",
    "sg:address":"300 Dayton Ave",
    "sg:city":"Springfield",
    "sg:classifiers":[
        {
            "category":"Personal",
            "subcategory":"Barber",
            "type":"Services"
        }
    ],
    "sg:phone":"+1 937 323 9021",
    "sg:postcode":"45506",
    "sg:province":"OH",
    "wof:name":"Don's Dayton Ave Barber Shop",
    "wof:placetype":"venue"
},
  "geometry": {"coordinates":[-83.836861,39.922622],"type":"Point"}
}