{
  "type": "Feature",
  "properties": {
    "addr:full": "4881 Trabue Rd Columbus OH 43228",
    "addr:housenumber": "4881",
    "addr:postcode": "43228",
    "addr:street": "Trabue Rd",
    "iso:country": "US",
    "sg:address": "4881 Trabue Rd",
    "sg:city": "Columbus",
    "sg:classifiers": [
      {
        "category": "Manufacturing",
        "subcategory": "Motor Vehicles \u0026 Parts",
        "type": "Manufacturing \u0026 Wholesale Goods"
      }
    ],
    "sg:phone": "+1 614 771 2102",
    "sg:postcode": "43228",
    "sg:province": "OH",
    "sg:tags": [
      "equipment",
      "railroad",
      "mfg"
    ],
    "wof:name": "North Fork Southern",
    "wof:placetype": "venue"
  },
  "geometry": {"coordinates":[-83.129719,39.983441],"type":"Point"}
}
