{
  "type": "Feature",
  "properties": {
    "iso:country":"US",
    "sg:address":"4881 Trabue Rd",
    "sg:city":"Columbus",
    "sg:classifiers":[
        {
            "category":"Manufacturing",
            "subcategory":"Motor Vehicles & Parts",
            "type":"Manufacturing & Wholesale Goods"
        }
    ],
    "sg:phone":"+1 614 771 2102",
    "sg:postcode":"43228",
    "sg:province":"OH",
    "sg:tags":[
        "equipment",
        "railroad",
        "mfg"
    ],
    "wof:name":"North Fork Southern",
    "wof:placetype":"venue"
},
  "geometry": {"coordinates":[-83.12971899999999,39.983441],"type":"Point"}
}