{
  "type": "Feature",
  "properties": {
    "addr:full": "711 E River St Elyria OH 44035",
    "addr:housenumber": "711",
    "addr:postcode": "44035",
    "addr:street": "E River St",
    "iso:country": "US",
    "sg:address": "711 E River St",
    "sg:city": "Elyria",
    "sg:classifiers": [
      {
        "category": "Personal",
        "subcategory": "Barber",
        "type": "Services"
      }
    ],
    "sg:phone": "+1 440 322 5266",
    "sg:postcode": "44035",
    "sg:province": "OH",
    "wof:name": "Looper's Barber Shop",
    "wof:placetype": "venue"
  },
  "geometry": {"coordinates":[-82.099483,41.36485],"type":"Point"}
}
