{
  "type": "Feature",
  "properties": {
    "iso:country":"US",
    "sg:address":"711 E River St",
    "sg:city":"Elyria",
    "sg:classifiers":[
        {
            "category":"Personal",
            "subcategory":"Barber",
            "type":"Services"
        }
    ],
    "sg:phone":"+1 440 322 5266",
    "sg:postcode":"44035",
    "sg:province":"OH",
    "wof:name":"Looper's Barber Shop",
    "wof:placetype":"venue"
},
  "geometry": {"coordinates":[-82.09948300000001,41.36485],"type":"Point"}
}