{
  "type": "Feature",
  "properties": {
    "iso:country":"US",
    "sg:address":"226 S 7th St",
    "sg:city":"Greenfield",
    "sg:classifiers":[
        {
            "category":"Retail",
            "subcategory":"Self-service Laundry",
            "type":"Services"
        }
    ],
    "sg:phone":"+1 937 981 9918",
    "sg:postcode":"45123",
    "sg:province":"OH",
    "wof:name":"Greenfield Econowash",
    "wof:placetype":"venue"
},
  "geometry": {"coordinates":[-83.390394,39.348469],"type":"Point"}
}