{
  "type": "Feature",
  "properties": {
    "addr:full": "226 S 7th St Greenfield OH 45123",
    "addr:housenumber": "226",
    "addr:postcode": "45123",
    "addr:street": "S 7Th St",
    "iso:country": "US",
    "sg:address": "226 S 7th St",
    "sg:city": "Greenfield",
    "sg:classifiers": [
      {
        "category": "Retail",
        "subcategory": "Self-service Laundry",
        "type": "Services"
      }
    ],
    "sg:phone": "+1 937 981 9918",
    "sg:postcode": "45123",
    "sg:province": "OH",
    "wof:name": "Greenfield Econowash",
    "wof:placetype": "venue"
  },
  "geometry": {"coordinates":[-83.390394,39.348469],"type":"Point"}
}
