{
  "type": "Feature",
  "properties": {
    "addr:full": "5515 Telegraph Rd Toledo OH 43612",
    "addr:housenumber": "5515",
    "addr:postcode": "43612",
    "addr:street": "Telegraph Rd",
    "iso:country": "US",
    "sg:address": "5515 Telegraph Rd",
    "sg:city": "Toledo",
    "sg:classifiers": [
      {
        "category": "Wholesale",
        "subcategory": "Hardware",
        "type": "Manufacturing \u0026 Wholesale Goods"
      },
      {
        "category": "Building \u0026 Trades",
        "subcategory": "Plumbing",
        "type": "Services"
      }
    ],
    "sg:phone": "+1 419 324 0378",
    "sg:postcode": "43612",
    "sg:province": "OH",
    "sg:tags": [
      "sheet",
      "work",
      "metal",
      "heating",
      "air",
      "contractor"
    ],
    "wof:name": "Air Concepts",
    "wof:placetype": "venue"
  },
  "geometry": {"coordinates":[-83.547385,41.718157],"type":"Point"}
}
