{
  "type": "Feature",
  "properties": {
    "iso:country":"US",
    "sg:address":"3269 Elsmere Rd",
    "sg:city":"Cleveland",
    "sg:classifiers":[
        {
            "category":"Shopping",
            "subcategory":"Department Store",
            "type":"Retail Goods"
        }
    ],
    "sg:phone":"+1 216 295 0555",
    "sg:postcode":"44120",
    "sg:province":"OH",
    "wof:name":"Co Shaker LLC",
    "wof:placetype":"venue"
},
  "geometry": {"coordinates":[-81.56017799999999,41.468202],"type":"Point"}
}