{
  "type": "Feature",
  "properties": {
    "addr:full":"4040 Stoney Ridge Rd Avon OH 44011",
    "addr:housenumber":"4040",
    "addr:postcode":"44011",
    "addr:street":"Stoney Ridge Rd",
    "iso:country":"US",
    "sg:address":"4040 Stoney Ridge Rd",
    "sg:city":"Avon",
    "sg:classifiers":[
        {
            "category":"Building & Trades",
            "subcategory":"Construction",
            "type":"Services"
        }
    ],
    "sg:phone":"+1 440 934 5716",
    "sg:postcode":"44011",
    "sg:province":"OH",
    "sg:tags":[
        "excavation",
        "work"
    ],
    "wof:name":"Universal Excavating Inc",
    "wof:placetype":"venue"
},
  "geometry": {"coordinates":[-82.04205,41.41935],"type":"Point"}
}