{
  "type": "Feature",
  "properties": {
    "addr:full": "2118 E Main St Springfield OH 45503",
    "addr:housenumber": "2118",
    "addr:postcode": "45503",
    "addr:street": "E Main St",
    "iso:country": "US",
    "sg:address": "2118 E Main St",
    "sg:city": "Springfield",
    "sg:classifiers": [
      {
        "category": "Autos \u0026 Motor Vehicles",
        "subcategory": "Fuel \u0026 Gas Station",
        "type": "Retail Goods"
      }
    ],
    "sg:phone": "+1 937 322 4950",
    "sg:postcode": "45503",
    "sg:province": "OH",
    "sg:tags": [
      "oil"
    ],
    "wof:name": "Citgo Gas Station",
    "wof:placetype": "venue"
  },
  "geometry": {"coordinates":[-83.777761,39.923412],"type":"Point"}
}
