{
  "type": "Feature",
  "properties": {
    "addr:full":"1710 Maysville Ave Zanesville OH 43701",
    "addr:housenumber":"1710",
    "addr:postcode":"43701",
    "addr:street":"Maysville Ave",
    "iso:country":"US",
    "sg:address":"1710 Maysville Ave",
    "sg:city":"Zanesville",
    "sg:classifiers":[
        {
            "category":"Wholesale",
            "subcategory":"Auto Parts",
            "type":"Manufacturing & Wholesale Goods"
        }
    ],
    "sg:phone":"+1 740 454 3220",
    "sg:postcode":"43701",
    "sg:province":"OH",
    "sg:tags":[
        "radiator"
    ],
    "wof:name":"Wolfe Radiator Works",
    "wof:placetype":"venue"
},
  "geometry": {"coordinates":[-82.013778,39.914834],"type":"Point"}
}