{
  "type": "Feature",
  "properties": {
    "addr:full": "511 Walnut St Green Camp OH 43322",
    "addr:housenumber": "511",
    "addr:postcode": "43322",
    "addr:street": "Walnut St",
    "iso:country": "US",
    "sg:address": "511 Walnut St",
    "sg:city": "Green Camp",
    "sg:classifiers": [
      {
        "category": "Professional",
        "subcategory": "Computer Services",
        "type": "Services"
      }
    ],
    "sg:phone": "+1 740 528 2161",
    "sg:postcode": "43322",
    "sg:province": "OH",
    "sg:tags": [
      "repair"
    ],
    "wof:name": "P C Pals",
    "wof:placetype": "venue"
  },
  "geometry": {"coordinates":[-83.20753,40.533664],"type":"Point"}
}
