{
  "type": "Feature",
  "properties": {
    "iso:country":"US",
    "sg:address":"511 Walnut St",
    "sg:city":"Green Camp",
    "sg:classifiers":[
        {
            "category":"Professional",
            "subcategory":"Computer Services",
            "type":"Services"
        }
    ],
    "sg:phone":"+1 740 528 2161",
    "sg:postcode":"43322",
    "sg:province":"OH",
    "sg:tags":[
        "repair"
    ],
    "wof:name":"P C Pals",
    "wof:placetype":"venue"
},
  "geometry": {"coordinates":[-83.20753000000001,40.533664],"type":"Point"}
}