{
  "type": "Feature",
  "properties": {
    "addr:full": "120 W McPherson Hwy Clyde OH 43410",
    "addr:housenumber": "120",
    "addr:postcode": "43410",
    "addr:street": "W Mcpherson Hwy",
    "iso:country": "US",
    "sg:address": "120 W McPherson Hwy",
    "sg:city": "Clyde",
    "sg:classifiers": [
      {
        "category": "Restaurant",
        "type": "Food \u0026 Drink"
      }
    ],
    "sg:phone": "+1 419 547 8375",
    "sg:postcode": "43410",
    "sg:province": "OH",
    "sg:tags": [
      "eating"
    ],
    "wof:name": "Pizza House",
    "wof:placetype": "venue"
  },
  "geometry": {"coordinates":[-82.976417,41.310195],"type":"Point"}
}
