{
  "type": "Feature",
  "properties": {
    "addr:full": "11191 W State Rte 571 Laura OH 45337",
    "addr:housenumber": "11191",
    "addr:postcode": "45337",
    "addr:street": "W State Rte 571",
    "iso:country": "US",
    "sg:address": "11191 W State Rte 571",
    "sg:city": "Laura",
    "sg:classifiers": [
      {
        "category": "Organizations",
        "subcategory": "Religious Organization",
        "type": "Services"
      }
    ],
    "sg:phone": "+1 937 947 1960",
    "sg:postcode": "45337",
    "sg:province": "OH",
    "sg:tags": [
      "church"
    ],
    "wof:name": "Main Street Baptist Church",
    "wof:placetype": "venue"
  },
  "geometry": {"coordinates":[-84.41094,40.000764],"type":"Point"}
}
