{
  "type": "Feature",
  "properties": {
    "iso:country":"US",
    "sg:address":"5231 High Hill Rd",
    "sg:city":"Cambridge",
    "sg:classifiers":[
        {
            "category":"Building & Trades",
            "subcategory":"Construction",
            "type":"Services"
        }
    ],
    "sg:phone":"+1 740 439 3750",
    "sg:postcode":"43725",
    "sg:province":"OH",
    "sg:tags":[
        "contractor"
    ],
    "wof:name":"Morgan Heartscapes",
    "wof:placetype":"venue"
},
  "geometry": {"coordinates":[-81.64792,39.972552],"type":"Point"}
}