{
  "type": "Feature",
  "properties": {
    "addr:full": "5231 High Hill Rd Cambridge OH 43725",
    "addr:housenumber": "5231",
    "addr:postcode": "43725",
    "addr:street": "High Hill Rd",
    "iso:country": "US",
    "sg:address": "5231 High Hill Rd",
    "sg:city": "Cambridge",
    "sg:classifiers": [
      {
        "category": "Building \u0026 Trades",
        "subcategory": "Construction",
        "type": "Services"
      }
    ],
    "sg:phone": "+1 740 439 3750",
    "sg:postcode": "43725",
    "sg:province": "OH",
    "sg:tags": [
      "contractor"
    ],
    "wof:name": "Morgan Heartscapes",
    "wof:placetype": "venue"
  },
  "geometry": {"coordinates":[-81.64792,39.972552],"type":"Point"}
}
