{
  "type": "Feature",
  "properties": {
    "iso:country":"US",
    "sg:address":"6822 Lincoln Way",
    "sg:city":"Wooster",
    "sg:classifiers":[
        {
            "category":"Wholesale",
            "subcategory":"Machinery & Supplies",
            "type":"Manufacturing & Wholesale Goods"
        }
    ],
    "sg:phone":"+1 330 264 3868",
    "sg:postcode":"44691",
    "sg:province":"OH",
    "sg:tags":[
        "field",
        "oil",
        "equipment"
    ],
    "wof:name":"Phoenix Specialty Inc",
    "wof:placetype":"venue"
},
  "geometry": {"coordinates":[-81.844811,40.79761],"type":"Point"}
}