{
  "type": "Feature",
  "properties": {
    "iso:country":"US",
    "sg:address":"5300 W Loveland Rd",
    "sg:city":"Madison",
    "sg:classifiers":[
        {
            "category":"Building & Trades",
            "subcategory":"Landscaping Services",
            "type":"Services"
        }
    ],
    "sg:phone":"+1 440 298 3349",
    "sg:postcode":"44057",
    "sg:province":"OH",
    "sg:tags":[
        "landscape"
    ],
    "wof:name":"Rabe & Company",
    "wof:placetype":"venue"
},
  "geometry": {"coordinates":[-81.077187,41.73315],"type":"Point"}
}