{
  "type": "Feature",
  "properties": {
    "addr:full": "136 News Plz Washington Ct Hs OH 43160",
    "addr:postcode": "43160",
    "addr:street": "Plz Washington Ct",
    "iso:country": "US",
    "sg:address": "136 News Plz",
    "sg:city": "Washington Ct Hs",
    "sg:classifiers": [
      {
        "category": "Personal",
        "type": "Services"
      }
    ],
    "sg:phone": "+1 740 333 4244",
    "sg:postcode": "43160",
    "sg:province": "OH",
    "sg:tags": [
      "therapist",
      "massage"
    ],
    "wof:name": "Health Kneads-Massage",
    "wof:placetype": "venue"
  },
  "geometry": {"coordinates":[-83.437815,39.536614],"type":"Point"}
}
