{
  "type": "Feature",
  "properties": {
    "addr:full":"9394 Sterling Dr Cincinnati OH 45241",
    "addr:housenumber":"9394",
    "addr:postcode":"45241",
    "addr:street":"Sterling Dr",
    "iso:country":"US",
    "sg:address":"9394 Sterling Dr",
    "sg:city":"Cincinnati",
    "sg:classifiers":[
        {
            "category":"Education",
            "subcategory":"School",
            "type":"Public Place"
        }
    ],
    "sg:phone":"+1 513 779 3014",
    "sg:postcode":"45241",
    "sg:province":"OH",
    "sg:website":"www.lakotaonline.com",
    "wof:name":"Shawnee Elementary School",
    "wof:placetype":"venue"
},
  "geometry": {"coordinates":[-84.37194100000001,39.312885],"type":"Point"}
}