{
  "type": "Feature",
  "properties": {
    "iso:country":"US",
    "sg:address":"600 E 4th St",
    "sg:city":"East Liverpool",
    "sg:classifiers":[
        {
            "category":"Social Services",
            "subcategory":"Adult Care",
            "type":"Services"
        }
    ],
    "sg:phone":"+1 330 385 4732",
    "sg:postcode":"43920",
    "sg:province":"OH",
    "sg:tags":[
        "organization",
        "senior",
        "citizen"
    ],
    "wof:name":"Senior Citizens Ctr",
    "wof:placetype":"venue"
},
  "geometry": {"coordinates":[-80.574985,40.617585],"type":"Point"}
}