{
  "type": "Feature",
  "properties": {
    "addr:full": "2502 Ashcraft Rd Dayton OH 45414",
    "addr:housenumber": "2502",
    "addr:postcode": "45414",
    "addr:street": "Ashcraft Rd",
    "iso:country": "US",
    "sg:address": "2502 Ashcraft Rd",
    "sg:city": "Dayton",
    "sg:classifiers": [
      {
        "category": "Autos \u0026 Motor Vehicles",
        "subcategory": "Automobile Sales",
        "type": "Retail Goods"
      }
    ],
    "sg:phone": "+1 937 274 9530",
    "sg:postcode": "45414",
    "sg:province": "OH",
    "sg:tags": [
      "classic"
    ],
    "wof:name": "Century Corp",
    "wof:placetype": "venue"
  },
  "geometry": {"coordinates":[-84.183203,39.82558],"type":"Point"}
}
