{
  "type": "Feature",
  "properties": {
    "iso:country":"US",
    "sg:address":"2502 Ashcraft Rd",
    "sg:city":"Dayton",
    "sg:classifiers":[
        {
            "category":"Autos & Motor Vehicles",
            "subcategory":"Automobile Sales",
            "type":"Retail Goods"
        }
    ],
    "sg:phone":"+1 937 274 9530",
    "sg:postcode":"45414",
    "sg:province":"OH",
    "sg:tags":[
        "classic"
    ],
    "wof:name":"Century Corp",
    "wof:placetype":"venue"
},
  "geometry": {"coordinates":[-84.18320300000001,39.82558],"type":"Point"}
}