{
  "type": "Feature",
  "properties": {
    "addr:full":"1928 Horseshoe Blvd Cleveland OH 44145",
    "addr:housenumber":"1928",
    "addr:postcode":"44145",
    "addr:street":"Horseshoe Blvd",
    "iso:country":"US",
    "sg:address":"1928 Horseshoe Blvd",
    "sg:city":"Cleveland",
    "sg:classifiers":[
        {
            "category":"Wholesale",
            "subcategory":"Electrical",
            "type":"Manufacturing & Wholesale Goods"
        }
    ],
    "sg:phone":"+1 440 333 2771",
    "sg:postcode":"44145",
    "sg:province":"OH",
    "sg:tags":[
        "communication",
        "radio",
        "system"
    ],
    "wof:name":"Denny's Electronics",
    "wof:placetype":"venue"
},
  "geometry": {"coordinates":[-81.879254,41.457817],"type":"Point"}
}