{
  "type": "Feature",
  "properties": {
    "iso:country":"US",
    "sg:address":"67701 W Alamar Ln",
    "sg:city":"Saint Clairsville",
    "sg:classifiers":[
        {
            "category":"Professional",
            "type":"Services"
        }
    ],
    "sg:phone":"+1 740 695 2966",
    "sg:postcode":"43950",
    "sg:province":"OH",
    "wof:name":"Paper Shack",
    "wof:placetype":"venue"
},
  "geometry": {"coordinates":[-80.954429,40.063264],"type":"Point"}
}