{
  "type": "Feature",
  "properties": {
    "addr:full":"137 Commerce Dr Loveland OH 45140",
    "addr:housenumber":"137",
    "addr:postcode":"45140",
    "addr:street":"Commerce Dr",
    "iso:country":"US",
    "sg:address":"137 Commerce Dr",
    "sg:city":"Loveland",
    "sg:classifiers":[
        {
            "category":"Wholesale",
            "subcategory":"Medical Equipment & Supplies",
            "type":"Manufacturing & Wholesale Goods"
        }
    ],
    "sg:phone":"+1 513 683 3390",
    "sg:postcode":"45140",
    "sg:province":"OH",
    "sg:tags":[
        "hospital"
    ],
    "wof:name":"Excel Home Health & Medical",
    "wof:placetype":"venue"
},
  "geometry": {"coordinates":[-84.304259,39.281868],"type":"Point"}
}