{
  "type": "Feature",
  "properties": {
    "iso:country":"US",
    "sg:address":"341 Stelton Rd",
    "sg:city":"Xenia",
    "sg:classifiers":[
        {
            "category":"Real Estate",
            "subcategory":"Real Estate Agent",
            "type":"Services"
        }
    ],
    "sg:phone":"+1 937 376 2152",
    "sg:postcode":"45385",
    "sg:province":"OH",
    "sg:tags":[
        "finding",
        "apartment",
        "rental"
    ],
    "wof:name":"Zahra Investments Meadows-Xn",
    "wof:placetype":"venue"
},
  "geometry": {"coordinates":[-83.936989,39.673665],"type":"Point"}
}