{
  "type": "Feature",
  "properties": {
    "iso:country":"US",
    "sg:address":"7270 E State Route 37",
    "sg:city":"Sunbury",
    "sg:classifiers":[
        {
            "category":"Ice Cream",
            "type":"Food & Drink"
        }
    ],
    "sg:menulink":"http://www.allmenus.com/oh/berkshire/165289-dairy-queen/menu/",
    "sg:phone":"+1 740 369 0317",
    "sg:postcode":"43074",
    "sg:province":"OH",
    "sg:tags":[
        "burger",
        "american"
    ],
    "wof:name":"Dairy Queen",
    "wof:placetype":"venue"
},
  "geometry": {"coordinates":[-82.932136,40.267336],"type":"Point"}
}