{
  "type": "Feature",
  "properties": {
    "addr:full": "19601 Van Aken Blvd Cleveland OH 44122",
    "addr:housenumber": "19601",
    "addr:postcode": "44122",
    "addr:street": "Van Aken Blvd",
    "iso:country": "US",
    "sg:address": "19601 Van Aken Blvd",
    "sg:city": "Cleveland",
    "sg:classifiers": [
      {
        "category": "Real Estate",
        "subcategory": "Real Estate Operator",
        "type": "Services"
      }
    ],
    "sg:phone": "+1 216 991 2373",
    "sg:postcode": "44122",
    "sg:province": "OH",
    "sg:tags": [
      "building",
      "apartment"
    ],
    "wof:name": "Blair House Apartments",
    "wof:placetype": "venue"
  },
  "geometry": {"coordinates":[-81.542978,41.466828],"type":"Point"}
}
