{
  "type": "Feature",
  "properties": {
    "iso:country":"US",
    "sg:address":"19601 Van Aken Blvd",
    "sg:city":"Cleveland",
    "sg:classifiers":[
        {
            "category":"Real Estate",
            "subcategory":"Real Estate Operator",
            "type":"Services"
        }
    ],
    "sg:phone":"+1 216 991 2373",
    "sg:postcode":"44122",
    "sg:province":"OH",
    "sg:tags":[
        "building",
        "apartment"
    ],
    "wof:name":"Blair House Apartments",
    "wof:placetype":"venue"
},
  "geometry": {"coordinates":[-81.54297800000001,41.466828],"type":"Point"}
}