{
  "type": "Feature",
  "properties": {
    "addr:full": "8442 Mayfield Rd Chesterland OH 44026",
    "addr:housenumber": "8442",
    "addr:postcode": "44026",
    "addr:street": "Mayfield Rd",
    "iso:country": "US",
    "sg:address": "8442 Mayfield Rd",
    "sg:city": "Chesterland",
    "sg:classifiers": [
      {
        "category": "Professional",
        "subcategory": "Lawyer \u0026 Legal Services",
        "type": "Services"
      }
    ],
    "sg:phone": "+1 440 729 3770",
    "sg:postcode": "44026",
    "sg:province": "OH",
    "sg:tags": [
      "attorney"
    ],
    "wof:name": "Scott A Larrick",
    "wof:placetype": "venue"
  },
  "geometry": {"coordinates":[-81.339129,41.522233],"type":"Point"}
}
