{
  "type": "Feature",
  "properties": {
    "addr:full":"1 S Main St Pleasant Hill OH 45359",
    "addr:housenumber":"1",
    "addr:postcode":"45359",
    "addr:street":"S Main St",
    "iso:country":"US",
    "sg:address":"1 S Main St",
    "sg:city":"Pleasant Hill",
    "sg:classifiers":[
        {
            "category":"Retail",
            "subcategory":"Funeral Services",
            "type":"Services"
        }
    ],
    "sg:phone":"+1 937 676 2201",
    "sg:postcode":"45359",
    "sg:province":"OH",
    "sg:tags":[
        "director"
    ],
    "wof:name":"Jackson Funeral Home",
    "wof:placetype":"venue"
},
  "geometry": {"coordinates":[-84.34417500000001,40.050771],"type":"Point"}
}