{
  "type": "Feature",
  "properties": {
    "iso:country":"US",
    "sg:address":"7782 Astra Cir",
    "sg:city":"Reynoldsburg",
    "sg:classifiers":[
        {
            "category":"Real Estate",
            "subcategory":"Real Estate Services",
            "type":"Services"
        }
    ],
    "sg:phone":"+1 614 501 0861",
    "sg:postcode":"43068",
    "sg:province":"OH",
    "sg:tags":[
        "company",
        "title"
    ],
    "wof:name":"Four Corners Search Svc",
    "wof:placetype":"venue"
},
  "geometry": {"coordinates":[-82.797667,39.977886],"type":"Point"}
}