{
  "type": "Feature",
  "properties": {
    "addr:full": "990 State Rte 28 Milford OH 45150",
    "addr:housenumber": "990",
    "addr:postcode": "45150",
    "addr:street": "State Rte 28",
    "iso:country": "US",
    "sg:address": "990 State Rte 28",
    "sg:city": "Milford",
    "sg:classifiers": [
      {
        "category": "Health Services",
        "subcategory": "Medical Lab",
        "type": "Services"
      }
    ],
    "sg:phone": "+1 513 831 4299",
    "sg:postcode": "45150",
    "sg:province": "OH",
    "sg:tags": [
      "laboratory"
    ],
    "wof:name": "Little Miami Crown \u0026 Bridge",
    "wof:placetype": "venue"
  },
  "geometry": {"coordinates":[-84.248352,39.192311],"type":"Point"}
}
