{
  "type": "Feature",
  "properties": {
    "iso:country":"US",
    "sg:address":"31500 Carlton Dr",
    "sg:city":"Bay Village",
    "sg:classifiers":[
        {
            "category":"Shopping",
            "subcategory":"Hobbies, Toys, & Games",
            "type":"Retail Goods"
        },
        {
            "category":"Shopping",
            "subcategory":"Gifts & Souvenirs",
            "type":"Retail Goods"
        }
    ],
    "sg:phone":"+1 440 871 6073",
    "sg:postcode":"44140",
    "sg:province":"OH",
    "sg:tags":[
        "shop",
        "craft",
        "novelty"
    ],
    "wof:name":"Painted Picket",
    "wof:placetype":"venue"
},
  "geometry": {"coordinates":[-81.966052,41.490123],"type":"Point"}
}