{
  "type": "Feature",
  "properties": {
    "addr:full": "31500 Carlton Dr Bay Village OH 44140",
    "addr:housenumber": "31500",
    "addr:postcode": "44140",
    "addr:street": "Carlton Dr",
    "iso:country": "US",
    "sg:address": "31500 Carlton Dr",
    "sg:city": "Bay Village",
    "sg:classifiers": [
      {
        "category": "Shopping",
        "subcategory": "Hobbies, Toys, \u0026 Games",
        "type": "Retail Goods"
      },
      {
        "category": "Shopping",
        "subcategory": "Gifts \u0026 Souvenirs",
        "type": "Retail Goods"
      }
    ],
    "sg:phone": "+1 440 871 6073",
    "sg:postcode": "44140",
    "sg:province": "OH",
    "sg:tags": [
      "shop",
      "craft",
      "novelty"
    ],
    "wof:name": "Painted Picket",
    "wof:placetype": "venue"
  },
  "geometry": {"coordinates":[-81.966052,41.490123],"type":"Point"}
}
