{
  "type": "Feature",
  "properties": {
    "addr:full":"220 Driving Park Rd Wellston OH 45692",
    "addr:housenumber":"220",
    "addr:postcode":"45692",
    "addr:street":"Driving Park Rd",
    "iso:country":"US",
    "sg:address":"220 Driving Park Rd",
    "sg:city":"Wellston",
    "sg:classifiers":[
        {
            "category":"Freight",
            "type":"Transportation"
        }
    ],
    "sg:phone":"+1 740 384 2125",
    "sg:postcode":"45692",
    "sg:province":"OH",
    "sg:tags":[
        "general"
    ],
    "wof:name":"Shur Lok Storage",
    "wof:placetype":"venue"
},
  "geometry": {"coordinates":[-82.542486,39.111027],"type":"Point"}
}