{
  "type": "Feature",
  "properties": {
    "iso:country":"US",
    "sg:address":"804 W Main St",
    "sg:city":"Barnesville",
    "sg:classifiers":[
        {
            "category":"Banks & Credit Unions",
            "subcategory":"Bank",
            "type":"Services"
        }
    ],
    "sg:phone":"+1 740 425 2200",
    "sg:postcode":"43713",
    "sg:province":"OH",
    "sg:tags":[
        "cashing",
        "check"
    ],
    "wof:name":"Valley Payroll Advance",
    "wof:placetype":"venue"
},
  "geometry": {"coordinates":[-81.191351,39.993761],"type":"Point"}
}