{
  "type": "Feature",
  "properties": {
    "addr:full":"820 Cincinnati St Dayton OH 45408",
    "addr:housenumber":"820",
    "addr:postcode":"45408",
    "addr:street":"Cincinnati St",
    "iso:country":"US",
    "sg:address":"820 Cincinnati St",
    "sg:city":"Dayton",
    "sg:classifiers":[
        {
            "category":"Organizations",
            "subcategory":"Religious Organization",
            "type":"Services"
        }
    ],
    "sg:phone":"+1 937 223 4635",
    "sg:postcode":"45408",
    "sg:province":"OH",
    "sg:tags":[
        "church"
    ],
    "wof:name":"Gods Temple Of Peace For All",
    "wof:placetype":"venue"
},
  "geometry": {"coordinates":[-84.202685,39.741042],"type":"Point"}
}