{
  "type": "Feature",
  "properties": {
    "addr:full":"430 Broadway Lorain OH 44052",
    "addr:housenumber":"430",
    "addr:postcode":"44052",
    "addr:street":"Broadway",
    "iso:country":"US",
    "sg:address":"430 Broadway",
    "sg:city":"Lorain",
    "sg:classifiers":[
        {
            "category":"Building & Trades",
            "subcategory":"Construction",
            "type":"Services"
        }
    ],
    "sg:phone":"+1 440 244 6969",
    "sg:postcode":"44052",
    "sg:province":"OH",
    "sg:tags":[
        "contractor"
    ],
    "wof:name":"Professional Roofers",
    "wof:placetype":"venue"
},
  "geometry": {"coordinates":[-82.176412,41.466837],"type":"Point"}
}