{
  "type": "Feature",
  "properties": {
    "addr:full": "1444 Newark Granville Rd Granville OH 43023",
    "addr:housenumber": "1444",
    "addr:postcode": "43023",
    "addr:street": "Newark Granville Rd",
    "iso:country": "US",
    "sg:address": "1444 Newark Granville Rd",
    "sg:city": "Granville",
    "sg:classifiers": [
      {
        "category": "Shopping",
        "subcategory": "Used Merchandise",
        "type": "Retail Goods"
      }
    ],
    "sg:phone": "+1 740 587 4814",
    "sg:postcode": "43023",
    "sg:province": "OH",
    "wof:name": "Cream Station Antiques",
    "wof:placetype": "venue"
  },
  "geometry": {"coordinates":[-82.494717,40.063837],"type":"Point"}
}
