{
  "type": "Feature",
  "properties": {
    "iso:country":"US",
    "sg:address":"783 S Wall St",
    "sg:city":"Columbus",
    "sg:classifiers":[
        {
            "category":"Manufacturing",
            "subcategory":"Toys & Sporting Goods",
            "type":"Manufacturing & Wholesale Goods"
        }
    ],
    "sg:phone":"+1 614 537 4154",
    "sg:postcode":"43206",
    "sg:province":"OH",
    "sg:website":"www.boygirldesign.com",
    "wof:name":"Boy Girl Design",
    "wof:placetype":"venue"
},
  "geometry": {"coordinates":[-82.998347,39.945347],"type":"Point"}
}