{
  "type": "Feature",
  "properties": {
    "addr:full": "12990 Snow Rd Cleveland OH 44130",
    "addr:housenumber": "12990",
    "addr:postcode": "44130",
    "addr:street": "Snow Rd",
    "iso:country": "US",
    "sg:address": "12990 Snow Rd",
    "sg:city": "Cleveland",
    "sg:classifiers": [
      {
        "category": "Manufacturing",
        "subcategory": "Metals",
        "type": "Manufacturing \u0026 Wholesale Goods"
      }
    ],
    "sg:phone": "+1 216 676 6174",
    "sg:postcode": "44130",
    "sg:province": "OH",
    "sg:tags": [
      "hardware",
      "production",
      "stampings",
      "stamping",
      "mfg"
    ],
    "sg:website": "www.triadmetal.com",
    "wof:name": "Triad Metal Products Company",
    "wof:placetype": "venue"
  },
  "geometry": {"coordinates":[-81.769631,41.40511],"type":"Point"}
}
