{
  "type": "Feature",
  "properties": {
    "iso:country":"US",
    "sg:address":"685 Mccartney Rd",
    "sg:city":"Youngstown",
    "sg:classifiers":[
        {
            "category":"Fast Food",
            "type":"Food & Drink"
        },
        {
            "category":"Restaurant",
            "type":"Food & Drink"
        }
    ],
    "sg:phone":"+1 330 743 4304",
    "sg:postcode":"44505",
    "sg:province":"OH",
    "sg:tags":[
        "american",
        "hot",
        "hamburger",
        "dog"
    ],
    "sg:website":"http://www.bk.com",
    "wof:name":"Burger King",
    "wof:placetype":"venue"
},
  "geometry": {"coordinates":[-80.592439,41.090323],"type":"Point"}
}