{
  "type": "Feature",
  "properties": {
    "addr:full":"31 N Court St Athens OH 45701",
    "addr:housenumber":"31",
    "addr:postcode":"45701",
    "addr:street":"N Court St",
    "iso:country":"US",
    "sg:address":"31 N Court St",
    "sg:city":"Athens",
    "sg:classifiers":[
        {
            "category":"Bagels",
            "type":"Food & Drink"
        },
        {
            "category":"Restaurant",
            "type":"Food & Drink"
        },
        {
            "category":"Bakery",
            "type":"Food & Drink"
        }
    ],
    "sg:menulink":"http://www.allmenus.com/oh/athens/17945-worlds-best-bagels/menu/",
    "sg:phone":"+1 740 594 5506",
    "sg:postcode":"45701",
    "sg:province":"OH",
    "sg:tags":[
        "bagel",
        "american",
        "sandwich",
        "bakery",
        "pastry"
    ],
    "wof:name":"World's Best Bagels",
    "wof:placetype":"venue"
},
  "geometry": {"coordinates":[-82.101012,39.330032],"type":"Point"}
}