{
  "type": "Feature",
  "properties": {
    "addr:full":"213 E Mansfield St New Washington OH 44854",
    "addr:housenumber":"213",
    "addr:postcode":"44854",
    "addr:street":"E Mansfield St",
    "iso:country":"US",
    "sg:address":"213 E Mansfield St",
    "sg:city":"New Washington",
    "sg:classifiers":[
        {
            "category":"Organizations",
            "subcategory":"Religious Organization",
            "type":"Services"
        }
    ],
    "sg:phone":"+1 419 492 7006",
    "sg:postcode":"44854",
    "sg:province":"OH",
    "sg:tags":[
        "clergy"
    ],
    "wof:name":"Joseph H Bartczak",
    "wof:placetype":"venue"
},
  "geometry": {"coordinates":[-82.85038400000001,40.962286],"type":"Point"}
}