{
  "type": "Feature",
  "properties": {
    "addr:full": "750 Piedmont Rd Columbus OH 43224",
    "addr:housenumber": "750",
    "addr:postcode": "43224",
    "addr:street": "Piedmont Rd",
    "iso:country": "US",
    "sg:address": "750 Piedmont Rd",
    "sg:city": "Columbus",
    "sg:classifiers": [
      {
        "category": "Government",
        "subcategory": "Office",
        "type": "Public Place"
      }
    ],
    "sg:phone": "+1 614 352 5224",
    "sg:postcode": "43224",
    "sg:province": "OH",
    "sg:tags": [
      "job"
    ],
    "wof:name": "Human Resource Dept",
    "wof:placetype": "venue"
  },
  "geometry": {"coordinates":[-82.992294,40.034622],"type":"Point"}
}
