{
  "type": "Feature",
  "properties": {
    "addr:full":"1612 Prosser Ave Kettering OH 45409",
    "addr:housenumber":"1612",
    "addr:postcode":"45409",
    "addr:street":"Prosser Ave",
    "iso:country":"US",
    "sg:address":"1612 Prosser Ave",
    "sg:city":"Kettering",
    "sg:classifiers":[
        {
            "category":"Shopping",
            "subcategory":"Computers & Home Electronics",
            "type":"Retail Goods"
        }
    ],
    "sg:phone":"+1 937 298 1875",
    "sg:postcode":"45409",
    "sg:province":"OH",
    "sg:tags":[
        "software"
    ],
    "wof:name":"Research Computer Svc",
    "wof:placetype":"venue"
},
  "geometry": {"coordinates":[-84.198325,39.723964],"type":"Point"}
}