{
  "type": "Feature",
  "properties": {
    "addr:full":"3463 S High St Columbus OH 43207",
    "addr:housenumber":"3463",
    "addr:postcode":"43207",
    "addr:street":"S High St",
    "iso:country":"US",
    "sg:address":"3463 S High St",
    "sg:city":"Columbus",
    "sg:classifiers":[
        {
            "category":"Shopping",
            "subcategory":"Department Store",
            "type":"Retail Goods"
        }
    ],
    "sg:phone":"+1 614 491 7312",
    "sg:postcode":"43207",
    "sg:province":"OH",
    "sg:tags":[
        "eating"
    ],
    "wof:name":"Kmart",
    "wof:placetype":"venue"
},
  "geometry": {"coordinates":[-82.997276,39.890205],"type":"Point"}
}