{
  "type": "Feature",
  "properties": {
    "addr:full": "1150 W 5th Ave Columbus OH 43212",
    "addr:housenumber": "1150",
    "addr:postcode": "43212",
    "addr:street": "W 5Th Ave",
    "iso:country": "US",
    "sg:address": "1150 W 5th Ave",
    "sg:city": "Columbus",
    "sg:classifiers": [
      {
        "category": "Organizations",
        "subcategory": "Religious Organization",
        "type": "Services"
      }
    ],
    "sg:phone": "+1 614 488 9695",
    "sg:postcode": "43212",
    "sg:province": "OH",
    "sg:tags": [
      "church"
    ],
    "sg:website": "www.gbgm-umc.org",
    "wof:name": "St Luke's United Methodist Chr",
    "wof:placetype": "venue"
  },
  "geometry": {"coordinates":[-83.037855,39.988459],"type":"Point"}
}
