{
  "type": "Feature",
  "properties": {
    "addr:full": "3397 N Dayton Xenia Rd Dayton OH 45432",
    "addr:housenumber": "3397",
    "addr:postcode": "45432",
    "addr:street": "N Dayton Xenia Rd",
    "iso:country": "US",
    "sg:address": "3397 N Dayton Xenia Rd",
    "sg:city": "Dayton",
    "sg:classifiers": [
      {
        "category": "Home \u0026 Garden",
        "subcategory": "Carpets \u0026 Floor Coverings",
        "type": "Retail Goods"
      }
    ],
    "sg:phone": "+1 937 426 9311",
    "sg:postcode": "45432",
    "sg:province": "OH",
    "sg:tags": [
      "dealer",
      "rug"
    ],
    "wof:name": "Central Carpet \u0026 Interiors",
    "wof:placetype": "venue"
  },
  "geometry": {"coordinates":[-84.061877,39.730347],"type":"Point"}
}
