{
  "type": "Feature",
  "properties": {
    "iso:country":"US",
    "sg:address":"3397 N Dayton Xenia Rd",
    "sg:city":"Dayton",
    "sg:classifiers":[
        {
            "category":"Home & Garden",
            "subcategory":"Carpets & Floor Coverings",
            "type":"Retail Goods"
        }
    ],
    "sg:phone":"+1 937 426 9311",
    "sg:postcode":"45432",
    "sg:province":"OH",
    "sg:tags":[
        "dealer",
        "rug"
    ],
    "wof:name":"Central Carpet & Interiors",
    "wof:placetype":"venue"
},
  "geometry": {"coordinates":[-84.061877,39.730347],"type":"Point"}
}