{
  "type": "Feature",
  "properties": {
    "addr:full":"3640 Ferry Rd Bellbrook OH 45305",
    "addr:housenumber":"3640",
    "addr:postcode":"45305",
    "addr:street":"Ferry Rd",
    "iso:country":"US",
    "sg:address":"3640 Ferry Rd",
    "sg:city":"Bellbrook",
    "sg:classifiers":[
        {
            "category":"Professional",
            "type":"Services"
        }
    ],
    "sg:phone":"+1 937 885 2132",
    "sg:postcode":"45305",
    "sg:province":"OH",
    "sg:tags":[
        "establishment"
    ],
    "wof:name":"Victorian Bellbrook",
    "wof:placetype":"venue"
},
  "geometry": {"coordinates":[-84.094424,39.593095],"type":"Point"}
}