{
  "type": "Feature",
  "properties": {
    "iso:country":"US",
    "sg:address":"4337 Oxford Gettysburg Rd",
    "sg:city":"Eaton",
    "sg:classifiers":[
        {
            "category":"Building & Trades",
            "subcategory":"Electrical",
            "type":"Services"
        }
    ],
    "sg:phone":"+1 937 456 2348",
    "sg:postcode":"45320",
    "sg:province":"OH",
    "sg:tags":[
        "electrical",
        "contractor"
    ],
    "wof:name":"Tobias Electric Inc",
    "wof:placetype":"venue"
},
  "geometry": {"coordinates":[-84.723022,39.80664],"type":"Point"}
}