{
  "type": "Feature",
  "properties": {
    "addr:full": "7590 Jenther Dr Mentor OH 44060",
    "addr:housenumber": "dr",
    "addr:postcode": "7590;44060",
    "addr:street": "Jenther",
    "iso:country": "US",
    "sg:address": "7590 Jenther Dr",
    "sg:city": "Mentor",
    "sg:classifiers": [
      {
        "category": "Manufacturing",
        "subcategory": "Tools \u0026 Machinery",
        "type": "Manufacturing \u0026 Wholesale Goods"
      }
    ],
    "sg:phone": "+1 440 946 6846",
    "sg:postcode": "44060",
    "sg:province": "OH",
    "sg:tags": [
      "machine",
      "shop"
    ],
    "wof:name": "Omega Machine \u0026 Tool Inc",
    "wof:placetype": "venue"
  },
  "geometry": {"coordinates":[-81.36936,41.667094],"type":"Point"}
}
