{
  "type": "Feature",
  "properties": {
    "iso:country":"US",
    "sg:address":"7590 Jenther Dr",
    "sg:city":"Mentor",
    "sg:classifiers":[
        {
            "category":"Manufacturing",
            "subcategory":"Tools & Machinery",
            "type":"Manufacturing & Wholesale Goods"
        }
    ],
    "sg:phone":"+1 440 946 6846",
    "sg:postcode":"44060",
    "sg:province":"OH",
    "sg:tags":[
        "machine",
        "shop"
    ],
    "wof:name":"Omega Machine & Tool Inc",
    "wof:placetype":"venue"
},
  "geometry": {"coordinates":[-81.36936,41.667094],"type":"Point"}
}