{
  "type": "Feature",
  "properties": {
    "iso:country":"US",
    "sg:address":"2500 W State St",
    "sg:city":"Alliance",
    "sg:classifiers":[
        {
            "category":"Freight",
            "type":"Transportation"
        }
    ],
    "sg:phone":"+1 330 823 4063",
    "sg:postcode":"44601",
    "sg:province":"OH",
    "sg:tags":[
        "operator",
        "local",
        "trucking"
    ],
    "wof:name":"Penney Catalog Pickup Info",
    "wof:placetype":"venue"
},
  "geometry": {"coordinates":[-81.157723,40.901955],"type":"Point"}
}