{
  "type": "Feature",
  "properties": {
    "addr:full": "132 S 4th St Marietta OH 45750",
    "addr:housenumber": "132",
    "addr:postcode": "45750",
    "addr:street": "S 4Th St",
    "iso:country": "US",
    "sg:address": "132 S 4th St",
    "sg:city": "Marietta",
    "sg:classifiers": [
      {
        "category": "Professional",
        "subcategory": "Accounting \u0026 Tax Preparation",
        "type": "Services"
      }
    ],
    "sg:phone": "+1 740 373 7423",
    "sg:postcode": "45750",
    "sg:province": "OH",
    "sg:tags": [
      "accountant"
    ],
    "sg:website": "www.reacpa.com",
    "wof:name": "Rea \u0026 Assoc Inc",
    "wof:placetype": "venue"
  },
  "geometry": {"coordinates":[-81.447664,39.412839],"type":"Point"}
}
