{
  "type": "Feature",
  "properties": {
    "addr:full":"3812 W 150th St Cleveland OH 44111",
    "addr:housenumber":"3812",
    "addr:postcode":"44111",
    "addr:street":"W 150Th St",
    "iso:country":"US",
    "sg:address":"3812 W 150th St",
    "sg:city":"Cleveland",
    "sg:classifiers":[
        {
            "category":"Manufacturing",
            "subcategory":"Metals",
            "type":"Manufacturing & Wholesale Goods"
        },
        {
            "category":"Manufacturing",
            "subcategory":"Tools & Machinery",
            "type":"Manufacturing & Wholesale Goods"
        }
    ],
    "sg:phone":"+1 216 941 0198",
    "sg:postcode":"44111",
    "sg:province":"OH",
    "sg:tags":[
        "die",
        "mfg",
        "fixture",
        "jig"
    ],
    "wof:name":"B & T Tool & Die Co Inc",
    "wof:placetype":"venue"
},
  "geometry": {"coordinates":[-81.80150500000001,41.4511],"type":"Point"}
}