{
  "type": "Feature",
  "properties": {
    "addr:full": "3812 W 150th St Cleveland OH 44111",
    "addr:housenumber": "3812",
    "addr:postcode": "44111",
    "addr:street": "W 150Th St",
    "iso:country": "US",
    "sg:address": "3812 W 150th St",
    "sg:city": "Cleveland",
    "sg:classifiers": [
      {
        "category": "Manufacturing",
        "subcategory": "Metals",
        "type": "Manufacturing \u0026 Wholesale Goods"
      },
      {
        "category": "Manufacturing",
        "subcategory": "Tools \u0026 Machinery",
        "type": "Manufacturing \u0026 Wholesale Goods"
      }
    ],
    "sg:phone": "+1 216 941 0198",
    "sg:postcode": "44111",
    "sg:province": "OH",
    "sg:tags": [
      "die",
      "mfg",
      "fixture",
      "jig"
    ],
    "wof:name": "B \u0026 T Tool \u0026 Die Co Inc",
    "wof:placetype": "venue"
  },
  "geometry": {"coordinates":[-81.801505,41.4511],"type":"Point"}
}
