{
  "type": "Feature",
  "properties": {
    "iso:country":"US",
    "sg:address":"6524 Wentworth Ave",
    "sg:city":"Cleveland",
    "sg:classifiers":[
        {
            "category":"Building & Trades",
            "subcategory":"Construction",
            "type":"Services"
        }
    ],
    "sg:phone":"+1 440 243 6524",
    "sg:postcode":"44142",
    "sg:province":"OH",
    "sg:tags":[
        "house"
    ],
    "wof:name":"Baldini Remodeling Home R",
    "wof:placetype":"venue"
},
  "geometry": {"coordinates":[-81.865759,41.392948],"type":"Point"}
}