{
  "type": "Feature",
  "properties": {
    "addr:full": "70 Commercial Way Springboro OH 45066",
    "addr:housenumber": "70",
    "addr:postcode": "45066",
    "addr:street": "Commercial Way",
    "iso:country": "US",
    "sg:address": "70 Commercial Way",
    "sg:city": "Springboro",
    "sg:classifiers": [
      {
        "category": "Professional",
        "subcategory": "Research",
        "type": "Services"
      },
      {
        "category": "Utilities",
        "type": "Services"
      }
    ],
    "sg:phone": "+1 937 743 0002",
    "sg:postcode": "45066",
    "sg:province": "OH",
    "sg:tags": [
      "refuse",
      "business",
      "consulting",
      "environmental",
      "ecological",
      "sanitary"
    ],
    "sg:website": "www.astenvironmental.com",
    "wof:name": "AST Environmental Inc",
    "wof:placetype": "venue"
  },
  "geometry": {"coordinates":[-84.268,39.558356],"type":"Point"}
}
