{
  "type": "Feature",
  "properties": {
    "iso:country":"US",
    "sg:address":"4181 Manchester Ave NW",
    "sg:city":"North Lawrence",
    "sg:classifiers":[
        {
            "category":"Building & Trades",
            "subcategory":"Construction",
            "type":"Services"
        }
    ],
    "sg:phone":"+1 330 832 6446",
    "sg:postcode":"44666",
    "sg:province":"OH",
    "sg:tags":[
        "home",
        "builder"
    ],
    "wof:name":"Nathan Glick Construction LTD",
    "wof:placetype":"venue"
},
  "geometry": {"coordinates":[-81.601322,40.839879],"type":"Point"}
}