{
  "type": "Feature",
  "properties": {
    "iso:country":"US",
    "sg:address":"401 Market St",
    "sg:city":"Steubenville",
    "sg:classifiers":[
        {
            "category":"Health Services",
            "subcategory":"Doctor",
            "type":"Services"
        }
    ],
    "sg:phone":"+1 740 266 6157",
    "sg:postcode":"43952",
    "sg:province":"OH",
    "sg:tags":[
        "physician",
        "surgeon"
    ],
    "wof:name":"Riverside Medical Of Ohio",
    "wof:placetype":"venue"
},
  "geometry": {"coordinates":[-80.615938,40.360238],"type":"Point"}
}