{
  "type": "Feature",
  "properties": {
    "addr:full": "850 Harmon Ave Columbus OH 43223",
    "addr:housenumber": "850",
    "addr:postcode": "43223",
    "addr:street": "Harmon Ave",
    "iso:country": "US",
    "sg:address": "850 Harmon Ave",
    "sg:city": "Columbus",
    "sg:classifiers": [
      {
        "category": "Building \u0026 Trades",
        "subcategory": "Equipment Rental",
        "type": "Services"
      }
    ],
    "sg:phone": "+1 614 221 2344",
    "sg:postcode": "43223",
    "sg:province": "OH",
    "sg:tags": [
      "yard"
    ],
    "wof:name": "Volvo Rents",
    "wof:placetype": "venue"
  },
  "geometry": {"coordinates":[-83.018589,39.949817],"type":"Point"}
}
