{
  "type": "Feature",
  "properties": {
    "iso:country":"US",
    "sg:address":"850 Harmon Ave",
    "sg:city":"Columbus",
    "sg:classifiers":[
        {
            "category":"Building & Trades",
            "subcategory":"Equipment Rental",
            "type":"Services"
        }
    ],
    "sg:phone":"+1 614 221 2344",
    "sg:postcode":"43223",
    "sg:province":"OH",
    "sg:tags":[
        "yard"
    ],
    "wof:name":"Volvo Rents",
    "wof:placetype":"venue"
},
  "geometry": {"coordinates":[-83.01858900000001,39.949817],"type":"Point"}
}