{
  "type": "Feature",
  "properties": {
    "addr:full": "126 S Sycamore St Lebanon OH 45036",
    "addr:housenumber": "126",
    "addr:postcode": "45036",
    "addr:street": "S Sycamore St",
    "iso:country": "US",
    "sg:address": "126 S Sycamore St",
    "sg:city": "Lebanon",
    "sg:classifiers": [
      {
        "category": "Real Estate",
        "subcategory": "Real Estate Agent",
        "type": "Services"
      }
    ],
    "sg:phone": "+1 513 932 9722",
    "sg:postcode": "45036",
    "sg:province": "OH",
    "sg:tags": [
      "management"
    ],
    "wof:name": "Griffin Gate Collections Inc",
    "wof:placetype": "venue"
  },
  "geometry": {"coordinates":[-84.20985,39.433162],"type":"Point"}
}
