{
  "type": "Feature",
  "properties": {
    "addr:full": "12415 Manning Rd Germantown OH 45327",
    "addr:housenumber": "12415",
    "addr:postcode": "45327",
    "addr:street": "Manning Rd",
    "iso:country": "US",
    "sg:address": "12415 Manning Rd",
    "sg:city": "Germantown",
    "sg:classifiers": [
      {
        "category": "Building \u0026 Trades",
        "subcategory": "Construction",
        "type": "Services"
      }
    ],
    "sg:phone": "+1 937 696 2070",
    "sg:postcode": "45327",
    "sg:province": "OH",
    "sg:tags": [
      "paving",
      "contractor"
    ],
    "wof:name": "Wallace Enterprises LLC",
    "wof:placetype": "venue"
  },
  "geometry": {"coordinates":[-84.408451,39.657711],"type":"Point"}
}
