{
  "type": "Feature",
  "properties": {
    "iso:country":"US",
    "sg:address":"99 S Main St",
    "sg:city":"Congress",
    "sg:classifiers":[
        {
            "category":"Government",
            "subcategory":"Office",
            "type":"Public Place"
        }
    ],
    "sg:phone":"+1 419 846 3311",
    "sg:postcode":"44287",
    "sg:province":"OH",
    "sg:tags":[
        "village"
    ],
    "wof:name":"Congress Twp Office",
    "wof:placetype":"venue"
},
  "geometry": {"coordinates":[-82.109571,40.969823],"type":"Point"}
}