{
  "type": "Feature",
  "properties": {
    "addr:full": "10295 Phillipp Pkwy Streetsboro OH 44241",
    "addr:housenumber": "10295",
    "addr:postcode": "44241",
    "addr:street": "Phillipp Pkwy",
    "iso:country": "US",
    "sg:address": "10295 Phillipp Pkwy",
    "sg:city": "Streetsboro",
    "sg:classifiers": [
      {
        "category": "Manufacturing",
        "subcategory": "Building Materials",
        "type": "Manufacturing \u0026 Wholesale Goods"
      }
    ],
    "sg:phone": "+1 330 220 8881",
    "sg:postcode": "44241",
    "sg:province": "OH",
    "sg:website": "www.recproducts.com",
    "wof:name": "Recreational Products Inc",
    "wof:placetype": "venue"
  },
  "geometry": {"coordinates":[-81.371692,41.269004],"type":"Point"}
}
