{
  "type": "Feature",
  "properties": {
    "addr:full": "1020 E Taggart St East Palestine OH 44413",
    "addr:housenumber": "1020",
    "addr:postcode": "44413",
    "addr:street": "E Taggart St",
    "iso:country": "US",
    "sg:address": "1020 E Taggart St",
    "sg:city": "East Palestine",
    "sg:phone": "+1 330 426 2657",
    "sg:postcode": "44413",
    "sg:province": "OH",
    "sg:tags": [
      "oil"
    ],
    "wof:name": "Leake Oil Co Inc",
    "wof:placetype": "venue"
  },
  "geometry": {"coordinates":[-80.524909,40.83473],"type":"Point"}
}
