{
  "type": "Feature",
  "properties": {
    "addr:full": "1168 Alliance Rd NW Minerva OH 44657",
    "addr:housenumber": "1168",
    "addr:postcode": "minerva;44657",
    "addr:street": "Alliance Rd Nw",
    "iso:country": "US",
    "sg:address": "1168 Alliance Rd NW",
    "sg:city": "Minerva",
    "sg:classifiers": [
      {
        "category": "Health Services",
        "subcategory": "Doctor",
        "type": "Services"
      }
    ],
    "sg:phone": "+1 330 868 3711",
    "sg:postcode": "44657",
    "sg:province": "OH",
    "sg:tags": [
      "physician",
      "surgeon"
    ],
    "wof:name": "Alliance Medical Specialists",
    "wof:placetype": "venue"
  },
  "geometry": {"coordinates":[-81.119464,40.71785],"type":"Point"}
}
