{
  "type": "Feature",
  "properties": {
    "iso:country":"US",
    "sg:address":"1168 Alliance Rd NW",
    "sg:city":"Minerva",
    "sg:classifiers":[
        {
            "category":"Health Services",
            "subcategory":"Doctor",
            "type":"Services"
        }
    ],
    "sg:phone":"+1 330 868 3711",
    "sg:postcode":"44657",
    "sg:province":"OH",
    "sg:tags":[
        "physician",
        "surgeon"
    ],
    "wof:name":"Alliance Medical Specialists",
    "wof:placetype":"venue"
},
  "geometry": {"coordinates":[-81.11946399999999,40.71785],"type":"Point"}
}