{
  "type": "Feature",
  "properties": {
    "iso:country":"US",
    "sg:address":"1505 Whipple Ave NW",
    "sg:city":"Canton",
    "sg:classifiers":[
        {
            "category":"Professional",
            "subcategory":"Accounting & Tax Preparation",
            "type":"Services"
        }
    ],
    "sg:phone":"+1 330 478 2801",
    "sg:postcode":"44708",
    "sg:province":"OH",
    "sg:tags":[
        "accountant"
    ],
    "wof:name":"Cindric Burge & Co Inc",
    "wof:placetype":"venue"
},
  "geometry": {"coordinates":[-81.425284,40.815607],"type":"Point"}
}