{
  "type": "Feature",
  "properties": {
    "addr:full": "1505 Whipple Ave NW Canton OH 44708",
    "addr:housenumber": "1505",
    "addr:postcode": "44708",
    "addr:street": "Whipple Ave Nw",
    "iso:country": "US",
    "sg:address": "1505 Whipple Ave NW",
    "sg:city": "Canton",
    "sg:classifiers": [
      {
        "category": "Professional",
        "subcategory": "Accounting \u0026 Tax Preparation",
        "type": "Services"
      }
    ],
    "sg:phone": "+1 330 478 2801",
    "sg:postcode": "44708",
    "sg:province": "OH",
    "sg:tags": [
      "accountant"
    ],
    "wof:name": "Cindric Burge \u0026 Co Inc",
    "wof:placetype": "venue"
  },
  "geometry": {"coordinates":[-81.425284,40.815607],"type":"Point"}
}
