{
  "type": "Feature",
  "properties": {
    "addr:full": "335 S Wayne Ave Cincinnati OH 45215",
    "addr:housenumber": "335",
    "addr:postcode": "45215",
    "addr:street": "S Wayne Ave",
    "iso:country": "US",
    "sg:address": "335 S Wayne Ave",
    "sg:city": "Cincinnati",
    "sg:classifiers": [
      {
        "category": "Building \u0026 Trades",
        "subcategory": "Construction",
        "type": "Services"
      },
      {
        "category": "Building \u0026 Trades",
        "subcategory": "Plumbing",
        "type": "Services"
      }
    ],
    "sg:phone": "+1 513 761 1747",
    "sg:postcode": "45215",
    "sg:province": "OH",
    "sg:tags": [
      "house",
      "conditioning",
      "air",
      "system",
      "contractor"
    ],
    "wof:name": "AK Lynros Construction LLC",
    "wof:placetype": "venue"
  },
  "geometry": {"coordinates":[-84.462033,39.217926],"type":"Point"}
}
