{
  "type": "Feature",
  "properties": {
    "addr:full":"4373 Belden Village St NW Canton OH 44718",
    "addr:housenumber":"4373",
    "addr:postcode":"44718",
    "addr:street":"Belden Village St Nw",
    "iso:country":"US",
    "sg:address":"4373 Belden Village St NW",
    "sg:city":"Canton",
    "sg:classifiers":[
        {
            "category":"Shopping",
            "subcategory":"Clothing, Apparel, & Fashions",
            "type":"Retail Goods"
        }
    ],
    "sg:phone":"+1 330 966 7199",
    "sg:postcode":"44718",
    "sg:province":"OH",
    "sg:tags":[
        "infant",
        "wear"
    ],
    "sg:website":"www.limitedtoo.com",
    "wof:name":"Limited Too",
    "wof:placetype":"venue"
},
  "geometry": {"coordinates":[-81.430018,40.855833],"type":"Point"}
}