{
  "type": "Feature",
  "properties": {
    "addr:full": "6081 US Hwy 23 Fostoria OH 44830",
    "addr:housenumber": "6081",
    "addr:postcode": "44830",
    "addr:street": "Us Hwy 23",
    "iso:country": "US",
    "sg:address": "6081 US Hwy 23",
    "sg:city": "Fostoria",
    "sg:classifiers": [
      {
        "category": "Professional",
        "subcategory": "Accounting \u0026 Tax Preparation",
        "type": "Services"
      }
    ],
    "sg:phone": "+1 419 436 0725",
    "sg:postcode": "44830",
    "sg:province": "OH",
    "sg:tags": [
      "return",
      "filing"
    ],
    "wof:name": "Ehats Tax Return Prep",
    "wof:placetype": "venue"
  },
  "geometry": {"coordinates":[-83.420401,41.21369],"type":"Point"}
}
