{
  "type": "Feature",
  "properties": {
    "addr:full": "39235 Camelot Way Avon OH 44011",
    "addr:housenumber": "39235",
    "addr:postcode": "44011",
    "addr:street": "Camelot Way",
    "iso:country": "US",
    "sg:address": "39235 Camelot Way",
    "sg:city": "Avon",
    "sg:classifiers": [
      {
        "category": "Professional",
        "subcategory": "Accounting \u0026 Tax Preparation",
        "type": "Services"
      }
    ],
    "sg:phone": "+1 440 934 8332",
    "sg:postcode": "44011",
    "sg:province": "OH",
    "sg:tags": [
      "bookkeeping",
      "general"
    ],
    "wof:name": "Briteside Accounting",
    "wof:placetype": "venue"
  },
  "geometry": {"coordinates":[-82.057341,41.419274],"type":"Point"}
}
