{
  "type": "Feature",
  "properties": {
    "addr:full": "49 N 6th St Waterville OH 43566",
    "addr:housenumber": "49",
    "addr:postcode": "43566",
    "addr:street": "N 6Th St",
    "iso:country": "US",
    "sg:address": "49 N 6th St",
    "sg:city": "Waterville",
    "sg:classifiers": [
      {
        "category": "Railroad",
        "type": "Transportation"
      }
    ],
    "sg:phone": "+1 419 878 2177",
    "sg:postcode": "43566",
    "sg:province": "OH",
    "wof:name": "Toledo Lake Erie \u0026 Western Inc",
    "wof:placetype": "venue"
  },
  "geometry": {"coordinates":[-83.723819,41.500457],"type":"Point"}
}
