{
  "type": "Feature",
  "properties": {
    "iso:country":"US",
    "sg:address":"49 N 6th St",
    "sg:city":"Waterville",
    "sg:classifiers":[
        {
            "category":"Railroad",
            "type":"Transportation"
        }
    ],
    "sg:phone":"+1 419 878 2177",
    "sg:postcode":"43566",
    "sg:province":"OH",
    "wof:name":"Toledo Lake Erie & Western Inc",
    "wof:placetype":"venue"
},
  "geometry": {"coordinates":[-83.72381900000001,41.500457],"type":"Point"}
}