{
  "type": "Feature",
  "properties": {
    "iso:country":"US",
    "sg:address":"2263 W US Hwy 22 and 3",
    "sg:city":"Maineville",
    "sg:classifiers":[
        {
            "category":"Organizations",
            "subcategory":"Non-profit Organization",
            "type":"Services"
        }
    ],
    "sg:phone":"+1 513 583 1311",
    "sg:postcode":"45039",
    "sg:province":"OH",
    "sg:tags":[
        "medical",
        "management"
    ],
    "wof:name":"Medco Review Inc",
    "wof:placetype":"venue"
},
  "geometry": {"coordinates":[-84.260953,39.314343],"type":"Point"}
}