{
  "type": "Feature",
  "properties": {
    "addr:full":"180 Chapel Ln Canfield OH 44406",
    "addr:housenumber":"180",
    "addr:postcode":"44406",
    "addr:street":"Chapel Ln",
    "iso:country":"US",
    "sg:address":"180 Chapel Ln",
    "sg:city":"Canfield",
    "sg:classifiers":[
        {
            "category":"Manufacturing",
            "subcategory":"Soap",
            "type":"Manufacturing & Wholesale Goods"
        }
    ],
    "sg:phone":"+1 330 533 7172",
    "sg:postcode":"44406",
    "sg:province":"OH",
    "sg:tags":[
        "detergent",
        "mfg"
    ],
    "wof:name":"Handmaiden Seciality Soap",
    "wof:placetype":"venue"
},
  "geometry": {"coordinates":[-80.75240599999999,41.032858],"type":"Point"}
}