{
  "type": "Feature",
  "properties": {
    "iso:country":"US",
    "sg:address":"6059 Lundy-Whitacre Rd",
    "sg:city":"Morrow",
    "sg:phone":"+1 513 899 4685",
    "sg:postcode":"45152",
    "sg:province":"OH",
    "sg:tags":[
        "farm",
        "soybean"
    ],
    "wof:name":"Stopkotte Farms",
    "wof:placetype":"venue"
},
  "geometry": {"coordinates":[-84.066633,39.335743],"type":"Point"}
}