{
  "type": "Feature",
  "properties": {
    "iso:country":"US",
    "sg:address":"2153 W 100th St",
    "sg:city":"Cleveland",
    "sg:classifiers":[
        {
            "category":"Shopping",
            "type":"Retail Goods"
        }
    ],
    "sg:phone":"+1 216 334 1730",
    "sg:postcode":"44102",
    "sg:province":"OH",
    "sg:tags":[
        "art",
        "gallery",
        "dealer"
    ],
    "wof:name":"Cleveland Performing Art",
    "wof:placetype":"venue"
},
  "geometry": {"coordinates":[-81.752987,41.472368],"type":"Point"}
}