{
  "type": "Feature",
  "properties": {
    "addr:full": "8521 East Ave Mentor OH 44060",
    "addr:housenumber": "8521",
    "addr:postcode": "44060",
    "addr:street": "East Ave",
    "iso:country": "US",
    "sg:address": "8521 East Ave",
    "sg:city": "Mentor",
    "sg:classifiers": [
      {
        "category": "Retail",
        "subcategory": "Repair Shop",
        "type": "Services"
      }
    ],
    "sg:phone": "+1 440 255 1506",
    "sg:postcode": "44060",
    "sg:province": "OH",
    "sg:tags": [
      "scooter",
      "motorcycle",
      "motor"
    ],
    "wof:name": "Pappa G's Motorcycle Repair",
    "wof:placetype": "venue"
  },
  "geometry": {"coordinates":[-81.335103,41.680024],"type":"Point"}
}
