{
  "type": "Feature",
  "properties": {
    "addr:full": "441 N Main St Mansfield OH 44902",
    "addr:housenumber": "441",
    "addr:postcode": "44902",
    "addr:street": "N Main St",
    "iso:country": "US",
    "sg:address": "441 N Main St",
    "sg:city": "Mansfield",
    "sg:classifiers": [
      {
        "category": "Home \u0026 Garden",
        "subcategory": "Furniture",
        "type": "Retail Goods"
      }
    ],
    "sg:phone": "+1 419 295 0177",
    "sg:postcode": "44902",
    "sg:province": "OH",
    "sg:tags": [
      "mattress"
    ],
    "wof:name": "Mid Ohio Mfg Direct",
    "wof:placetype": "venue"
  },
  "geometry": {"coordinates":[-82.514662,40.771062],"type":"Point"}
}
