{
  "type": "Feature",
  "properties": {
    "addr:full":"549 S Chillicothe Rd Aurora OH 44202",
    "addr:housenumber":"549",
    "addr:postcode":"44202",
    "addr:street":"S Chillicothe Rd",
    "iso:country":"US",
    "sg:address":"549 S Chillicothe Rd",
    "sg:city":"Aurora",
    "sg:classifiers":[
        {
            "category":"Restaurant",
            "type":"Food & Drink"
        }
    ],
    "sg:menulink":"http://www.allmenus.com/oh/aurora/134672-subway/menu/",
    "sg:phone":"+1 330 995 3093",
    "sg:postcode":"44202",
    "sg:province":"OH",
    "sg:tags":[
        "american",
        "sandwich"
    ],
    "wof:name":"Subway",
    "wof:placetype":"venue"
},
  "geometry": {"coordinates":[-81.340208,41.301962],"type":"Point"}
}