{
  "type": "Feature",
  "properties": {
    "addr:full":"98 Wildwood Dr Marietta OH 45750",
    "addr:housenumber":"98",
    "addr:postcode":"45750",
    "addr:street":"Wildwood Dr",
    "iso:country":"US",
    "sg:address":"98 Wildwood Dr",
    "sg:city":"Marietta",
    "sg:classifiers":[
        {
            "category":"Professional",
            "type":"Services"
        }
    ],
    "sg:phone":"+1 740 373 9671",
    "sg:postcode":"45750",
    "sg:province":"OH",
    "wof:name":"4 More Storage Inc",
    "wof:placetype":"venue"
},
  "geometry": {"coordinates":[-81.439998,39.438186],"type":"Point"}
}