{
  "type": "Feature",
  "properties": {
    "iso:country":"US",
    "sg:address":"1044 Belmont Ave",
    "sg:city":"Youngstown",
    "sg:classifiers":[
        {
            "category":"Health Services",
            "subcategory":"Clinic",
            "type":"Services"
        }
    ],
    "sg:phone":"+1 330 480 2595",
    "sg:postcode":"44504",
    "sg:province":"OH",
    "sg:tags":[
        "banks",
        "blood",
        "center"
    ],
    "wof:name":"St Elizabeth Blood Donor Svc",
    "wof:placetype":"venue"
},
  "geometry": {"coordinates":[-80.655653,41.113258],"type":"Point"}
}