{
  "type": "Feature",
  "properties": {
    "addr:full": "750 W Streetsboro St Hudson OH 44236",
    "addr:housenumber": "750",
    "addr:postcode": "44236",
    "addr:street": "W Streetsboro St",
    "iso:country": "US",
    "sg:address": "750 W Streetsboro St",
    "sg:city": "Hudson",
    "sg:classifiers": [
      {
        "category": "Organizations",
        "subcategory": "Religious Organization",
        "type": "Services"
      }
    ],
    "sg:phone": "+1 330 650 9533",
    "sg:postcode": "44236",
    "sg:province": "OH",
    "sg:tags": [
      "church"
    ],
    "sg:website": "www.hudsonchapel.org",
    "wof:name": "Hudson Community Chapel",
    "wof:placetype": "venue"
  },
  "geometry": {"coordinates":[-81.482717,41.232897],"type":"Point"}
}
