{
  "type": "Feature",
  "properties": {
    "iso:country":"US",
    "sg:address":"9224 Darrow Rd",
    "sg:city":"Twinsburg",
    "sg:classifiers":[
        {
            "category":"Restaurant",
            "type":"Food & Drink"
        }
    ],
    "sg:phone":"+1 330 425 3435",
    "sg:postcode":"44087",
    "sg:province":"OH",
    "sg:tags":[
        "eating"
    ],
    "wof:name":"Tinkers Creek Tap & Grill",
    "wof:placetype":"venue"
},
  "geometry": {"coordinates":[-81.440305,41.316973],"type":"Point"}
}