{
  "type": "Feature",
  "properties": {
    "iso:country":"US",
    "sg:address":"4061 Clough Woods Dr",
    "sg:city":"Batavia",
    "sg:classifiers":[
        {
            "category":"Manufacturing",
            "subcategory":"Chemicals & Compounds",
            "type":"Manufacturing & Wholesale Goods"
        }
    ],
    "sg:phone":"+1 513 943 4225",
    "sg:postcode":"45103",
    "sg:province":"OH",
    "sg:tags":[
        "preparation",
        "mfg"
    ],
    "wof:name":"Key Resin Company",
    "wof:placetype":"venue"
},
  "geometry": {"coordinates":[-84.235895,39.064201],"type":"Point"}
}