{
  "type": "Feature",
  "properties": {
    "addr:full": "4061 Clough Woods Dr Batavia OH 45103",
    "addr:housenumber": "4061",
    "addr:postcode": "45103",
    "addr:street": "Clough Woods Dr",
    "iso:country": "US",
    "sg:address": "4061 Clough Woods Dr",
    "sg:city": "Batavia",
    "sg:classifiers": [
      {
        "category": "Manufacturing",
        "subcategory": "Chemicals \u0026 Compounds",
        "type": "Manufacturing \u0026 Wholesale Goods"
      }
    ],
    "sg:phone": "+1 513 943 4225",
    "sg:postcode": "45103",
    "sg:province": "OH",
    "sg:tags": [
      "preparation",
      "mfg"
    ],
    "wof:name": "Key Resin Company",
    "wof:placetype": "venue"
  },
  "geometry": {"coordinates":[-84.235895,39.064201],"type":"Point"}
}
