{
  "type": "Feature",
  "properties": {
    "addr:full": "7661 Freedom Ave NW North Canton OH 44720",
    "addr:housenumber": "7661",
    "addr:postcode": "44720",
    "addr:street": "Freedom Ave Nw",
    "iso:country": "US",
    "sg:address": "7661 Freedom Ave NW",
    "sg:city": "North Canton",
    "sg:classifiers": [
      {
        "category": "Manufacturing",
        "subcategory": "Tools \u0026 Machinery",
        "type": "Manufacturing \u0026 Wholesale Goods"
      }
    ],
    "sg:phone": "+1 330 499 8450",
    "sg:postcode": "44720",
    "sg:province": "OH",
    "sg:tags": [
      "mold"
    ],
    "sg:website": "www.xcelmold.com",
    "wof:name": "Xcel Mold \u0026 Machine Inc",
    "wof:placetype": "venue"
  },
  "geometry": {"coordinates":[-81.429928,40.891568],"type":"Point"}
}
