{
  "type": "Feature",
  "properties": {
    "iso:country":"US",
    "sg:address":"7661 Freedom Ave NW",
    "sg:city":"North Canton",
    "sg:classifiers":[
        {
            "category":"Manufacturing",
            "subcategory":"Tools & Machinery",
            "type":"Manufacturing & Wholesale Goods"
        }
    ],
    "sg:phone":"+1 330 499 8450",
    "sg:postcode":"44720",
    "sg:province":"OH",
    "sg:tags":[
        "mold"
    ],
    "sg:website":"www.xcelmold.com",
    "wof:name":"Xcel Mold & Machine Inc",
    "wof:placetype":"venue"
},
  "geometry": {"coordinates":[-81.429928,40.891568],"type":"Point"}
}