{
  "type": "Feature",
  "properties": {
    "iso:country":"US",
    "sg:address":"3645 N High St",
    "sg:city":"Columbus",
    "sg:classifiers":[
        {
            "category":"Coffee & Tea",
            "type":"Food & Drink"
        },
        {
            "category":"Restaurant",
            "type":"Food & Drink"
        }
    ],
    "sg:menulink":"http://www.allmenus.com/oh/columbus/221265-caribou-coffee/menu/",
    "sg:phone":"+1 614 262 8770",
    "sg:postcode":"43214",
    "sg:province":"OH",
    "sg:tags":[
        "tea",
        "coffee",
        "american",
        "diner"
    ],
    "wof:name":"Caribou Coffee",
    "wof:placetype":"venue"
},
  "geometry": {"coordinates":[-83.017135,40.036361],"type":"Point"}
}