{
  "type": "Feature",
  "properties": {
    "addr:full":"33 W Dixon Ave Dayton OH 45419",
    "addr:housenumber":"33",
    "addr:postcode":"45419",
    "addr:street":"W Dixon Ave",
    "iso:country":"US",
    "sg:address":"33 W Dixon Ave",
    "sg:city":"Dayton",
    "sg:classifiers":[
        {
            "category":"Organizations",
            "subcategory":"Religious Organization",
            "type":"Services"
        }
    ],
    "sg:phone":"+1 937 293 1154",
    "sg:postcode":"45419",
    "sg:province":"OH",
    "sg:tags":[
        "church"
    ],
    "sg:website":"www.stpauls-dayton.org",
    "wof:name":"St Paul's Episcopal Church",
    "wof:placetype":"venue"
},
  "geometry": {"coordinates":[-84.173638,39.724623],"type":"Point"}
}