{
  "type": "Feature",
  "properties": {
    "addr:full":"158 W Johnstown Rd Columbus OH 43230",
    "addr:housenumber":"158",
    "addr:postcode":"43230",
    "addr:street":"W Johnstown Rd",
    "iso:country":"US",
    "sg:address":"158 W Johnstown Rd",
    "sg:city":"Columbus",
    "sg:classifiers":[
        {
            "category":"Professional",
            "subcategory":"Lawyer & Legal Services",
            "type":"Services"
        }
    ],
    "sg:phone":"+1 614 476 5540",
    "sg:postcode":"43230",
    "sg:province":"OH",
    "sg:tags":[
        "attorney"
    ],
    "wof:name":"Amspirit Business Connections",
    "wof:placetype":"venue"
},
  "geometry": {"coordinates":[-82.88283699999999,40.018245],"type":"Point"}
}