{
  "type": "Feature",
  "properties": {
    "addr:full": "11595 Huntington Way NW Pickerington OH 43147",
    "addr:housenumber": "11595",
    "addr:postcode": "43147",
    "addr:street": "Huntington Way Nw",
    "iso:country": "US",
    "sg:address": "11595 Huntington Way NW",
    "sg:city": "Pickerington",
    "sg:classifiers": [
      {
        "category": "Travel",
        "subcategory": "Travel Agent",
        "type": "Entertainment"
      }
    ],
    "sg:phone": "+1 614 837 5172",
    "sg:postcode": "43147",
    "sg:province": "OH",
    "sg:tags": [
      "agency"
    ],
    "wof:name": "Jams Associates",
    "wof:placetype": "venue"
  },
  "geometry": {"coordinates":[-82.717234,39.900942],"type":"Point"}
}
