{
  "type": "Feature",
  "properties": {
    "addr:full":"18 N Nelson Rd Columbus OH 43219",
    "addr:housenumber":"18",
    "addr:postcode":"43219",
    "addr:street":"N Nelson Rd",
    "iso:country":"US",
    "sg:address":"18 N Nelson Rd",
    "sg:city":"Columbus",
    "sg:classifiers":[
        {
            "category":"Restaurant",
            "type":"Food & Drink"
        }
    ],
    "sg:phone":"+1 614 252 4949",
    "sg:postcode":"43219",
    "sg:province":"OH",
    "wof:name":"Old Bag Of Nails Pub",
    "wof:placetype":"venue"
},
  "geometry": {"coordinates":[-82.95026799999999,39.96875],"type":"Point"}
}