{
  "type": "Feature",
  "properties": {
    "addr:full":"25224 Co Rd 24 Coshocton OH 43812",
    "addr:housenumber":"25224;24",
    "addr:postcode":"43812",
    "addr:street":"Co Rd",
    "iso:country":"US",
    "sg:address":"25224 Co Rd 24",
    "sg:city":"Coshocton",
    "sg:classifiers":[
        {
            "category":"Shopping",
            "subcategory":"Books",
            "type":"Retail Goods"
        }
    ],
    "sg:phone":"+1 740 622 5349",
    "sg:postcode":"43812",
    "sg:province":"OH",
    "sg:tags":[
        "religious"
    ],
    "wof:name":"Fountain of Blessings",
    "wof:placetype":"venue"
},
  "geometry": {"coordinates":[-81.893226,40.319584],"type":"Point"}
}