{
  "type": "Feature",
  "properties": {
    "addr:full": "2804 Clark Ave Cleveland OH 44109",
    "addr:housenumber": "2804",
    "addr:postcode": "44109",
    "addr:street": "Clark Ave",
    "iso:country": "US",
    "sg:address": "2804 Clark Ave",
    "sg:city": "Cleveland",
    "sg:classifiers": [
      {
        "category": "Professional",
        "subcategory": "Lawyer \u0026 Legal Services",
        "type": "Services"
      }
    ],
    "sg:phone": "+1 216 621 9658",
    "sg:postcode": "44109",
    "sg:province": "OH",
    "sg:tags": [
      "attorney"
    ],
    "wof:name": "Kraig \u0026 Kraig",
    "wof:placetype": "venue"
  },
  "geometry": {"coordinates":[-81.701717,41.469969],"type":"Point"}
}
