{
  "type": "Feature",
  "properties": {
    "iso:country":"US",
    "sg:address":"2804 Clark Ave",
    "sg:city":"Cleveland",
    "sg:classifiers":[
        {
            "category":"Professional",
            "subcategory":"Lawyer & Legal Services",
            "type":"Services"
        }
    ],
    "sg:phone":"+1 216 621 9658",
    "sg:postcode":"44109",
    "sg:province":"OH",
    "sg:tags":[
        "attorney"
    ],
    "wof:name":"Kraig & Kraig",
    "wof:placetype":"venue"
},
  "geometry": {"coordinates":[-81.701717,41.469969],"type":"Point"}
}