{
  "type": "Feature",
  "properties": {
    "addr:full":"1096 Overton Dr Akron OH 44319",
    "addr:housenumber":"1096",
    "addr:postcode":"44319",
    "addr:street":"Overton Dr",
    "iso:country":"US",
    "sg:address":"1096 Overton Dr",
    "sg:city":"Akron",
    "sg:classifiers":[
        {
            "category":"Shopping",
            "subcategory":"Hobbies, Toys, & Games",
            "type":"Retail Goods"
        }
    ],
    "sg:phone":"+1 330 644 0068",
    "sg:postcode":"44319",
    "sg:province":"OH",
    "sg:tags":[
        "craft"
    ],
    "wof:name":"Crafts By BJ",
    "wof:placetype":"venue"
},
  "geometry": {"coordinates":[-81.564258,40.984925],"type":"Point"}
}