{
  "type": "Feature",
  "properties": {
    "addr:full": "14610 Judas Rd New Holland OH 43145",
    "addr:postcode": "14610;43145",
    "addr:street": "Judas Rd",
    "iso:country": "US",
    "sg:address": "14610 Judas Rd",
    "sg:city": "New Holland",
    "sg:classifiers": [
      {
        "category": "Farming",
        "subcategory": "Farm",
        "type": "Manufacturing \u0026 Wholesale Goods"
      }
    ],
    "sg:phone": "+1 740 495 5700",
    "sg:postcode": "43145",
    "sg:province": "OH",
    "sg:tags": [
      "crop",
      "general"
    ],
    "wof:name": "Bruce Mc Fadden",
    "wof:placetype": "venue"
  },
  "geometry": {"coordinates":[-83.235549,39.522517],"type":"Point"}
}
