{
  "type": "Feature",
  "properties": {
    "iso:country":"US",
    "sg:address":"595 E Broad St",
    "sg:city":"Columbus",
    "sg:classifiers":[
        {
            "category":"Real Estate",
            "subcategory":"Real Estate Agent",
            "type":"Services"
        }
    ],
    "sg:phone":"+1 614 221 2266",
    "sg:postcode":"43215",
    "sg:province":"OH",
    "sg:website":"www.allc.biz",
    "wof:name":"All-C Appraisals",
    "wof:placetype":"venue"
},
  "geometry": {"coordinates":[-82.984886,39.96393],"type":"Point"}
}