{
  "type": "Feature",
  "properties": {
    "addr:full":"7939 W Central Ave Toledo OH 43617",
    "addr:housenumber":"7939",
    "addr:postcode":"43617",
    "addr:street":"W Central Ave",
    "iso:country":"US",
    "sg:address":"7939 W Central Ave",
    "sg:city":"Toledo",
    "sg:classifiers":[
        {
            "category":"Retail",
            "subcategory":"Auto Repair",
            "type":"Services"
        }
    ],
    "sg:phone":"+1 419 841 2525",
    "sg:postcode":"43617",
    "sg:province":"OH",
    "sg:tags":[
        "body"
    ],
    "sg:website":"www.central-collision.com",
    "wof:name":"Central Collision",
    "wof:placetype":"venue"
},
  "geometry": {"coordinates":[-83.73314000000001,41.673615],"type":"Point"}
}