{
  "type": "Feature",
  "properties": {
    "iso:country":"US",
    "sg:address":"1585 Bethel Rd",
    "sg:city":"Columbus",
    "sg:classifiers":[
        {
            "category":"Banks & Credit Unions",
            "subcategory":"Investment Brokerage",
            "type":"Services"
        }
    ],
    "sg:phone":"+1 614 451 5030",
    "sg:postcode":"43220",
    "sg:province":"OH",
    "sg:tags":[
        "security",
        "management",
        "insurance",
        "ag"
    ],
    "wof:name":"Manex Financial Management",
    "wof:placetype":"venue"
},
  "geometry": {"coordinates":[-83.06211,40.063815],"type":"Point"}
}