{
  "type": "Feature",
  "properties": {
    "addr:full":"5530 Tuttle Crossing Blvd Dublin OH 43016",
    "addr:housenumber":"5530",
    "addr:postcode":"43016",
    "addr:street":"Tuttle Crossing Blvd",
    "iso:country":"US",
    "sg:address":"5530 Tuttle Crossing Blvd",
    "sg:city":"Dublin",
    "sg:classifiers":[
        {
            "category":"Travel",
            "subcategory":"Hotels & Motels",
            "type":"Entertainment"
        }
    ],
    "sg:phone":"+1 614 760 0245",
    "sg:postcode":"43016",
    "sg:province":"OH",
    "sg:tags":[
        "operation"
    ],
    "wof:name":"Wellesley Inn & Suites",
    "wof:placetype":"venue"
},
  "geometry": {"coordinates":[-83.140855,40.075076],"type":"Point"}
}