{
  "type": "Feature",
  "properties": {
    "addr:full":"124 W Washington St Medina OH 44256",
    "addr:housenumber":"124",
    "addr:postcode":"44256",
    "addr:street":"W Washington St",
    "iso:country":"US",
    "sg:address":"124 W Washington St",
    "sg:city":"Medina",
    "sg:classifiers":[
        {
            "category":"Education",
            "subcategory":"School",
            "type":"Public Place"
        }
    ],
    "sg:phone":"+1 330 723 6393",
    "sg:postcode":"44256",
    "sg:province":"OH",
    "sg:website":"www.medina-esc.k12.oh.us",
    "wof:name":"Medina County Board-Education",
    "wof:placetype":"venue"
},
  "geometry": {"coordinates":[-81.864948,41.137959],"type":"Point"}
}