{
  "type": "Feature",
  "properties": {
    "addr:full": "220 S Chillicothe Rd Aurora OH 44202",
    "addr:housenumber": "220",
    "addr:postcode": "44202",
    "addr:street": "S Chillicothe Rd",
    "iso:country": "US",
    "sg:address": "220 S Chillicothe Rd",
    "sg:city": "Aurora",
    "sg:classifiers": [
      {
        "category": "Personal",
        "subcategory": "Barber",
        "type": "Services"
      }
    ],
    "sg:phone": "+1 330 562 6313",
    "sg:postcode": "44202",
    "sg:province": "OH",
    "wof:name": "Aurora Carriage House Hair",
    "wof:placetype": "venue"
  },
  "geometry": {"coordinates":[-81.345595,41.312751],"type":"Point"}
}
