{
  "type": "Feature",
  "properties": {
    "iso:country":"US",
    "sg:address":"326 N Walnut St",
    "sg:city":"Dover",
    "sg:classifiers":[
        {
            "category":"Shopping",
            "subcategory":"Used Merchandise",
            "type":"Retail Goods"
        }
    ],
    "sg:phone":"+1 330 364 1311",
    "sg:postcode":"44622",
    "sg:province":"OH",
    "wof:name":"Second Time Around",
    "wof:placetype":"venue"
},
  "geometry": {"coordinates":[-81.47841,40.52195],"type":"Point"}
}