{
  "type": "Feature",
  "properties": {
    "iso:country":"US",
    "sg:address":"27500 Royalton Rd",
    "sg:city":"Columbia Station",
    "sg:classifiers":[
        {
            "category":"Retail",
            "subcategory":"Auto Repair",
            "type":"Services"
        }
    ],
    "sg:phone":"+1 440 236 3501",
    "sg:postcode":"44028",
    "sg:province":"OH",
    "sg:tags":[
        "motorcycle"
    ],
    "wof:name":"Mike's Customs",
    "wof:placetype":"venue"
},
  "geometry": {"coordinates":[-81.936976,41.31296],"type":"Point"}
}