{
  "type": "Feature",
  "properties": {
    "addr:full": "105 S Main St Bryan OH 43506",
    "addr:housenumber": "105",
    "addr:postcode": "43506",
    "addr:street": "S Main St",
    "iso:country": "US",
    "sg:address": "105 S Main St",
    "sg:city": "Bryan",
    "sg:classifiers": [
      {
        "category": "Shopping",
        "subcategory": "Clothing, Apparel, \u0026 Fashions",
        "type": "Retail Goods"
      }
    ],
    "sg:phone": "+1 419 636 1240",
    "sg:postcode": "43506",
    "sg:province": "OH",
    "sg:tags": [
      "wear"
    ],
    "wof:name": "Hawks Clothing Store",
    "wof:placetype": "venue"
  },
  "geometry": {"coordinates":[-84.550989,41.47454],"type":"Point"}
}
