{
  "type": "Feature",
  "properties": {
    "iso:country":"US",
    "sg:address":"2626 Vine St",
    "sg:city":"Cincinnati",
    "sg:classifiers":[
        {
            "category":"Professional",
            "subcategory":"Business Services",
            "type":"Services"
        }
    ],
    "sg:phone":"+1 513 961 8463",
    "sg:postcode":"45219",
    "sg:province":"OH",
    "wof:name":"Short Vine Grind",
    "wof:placetype":"venue"
},
  "geometry": {"coordinates":[-84.509444,39.130026],"type":"Point"}
}