{
  "type": "Feature",
  "properties": {
    "addr:full": "426 E 115th St Cleveland OH 44108",
    "addr:housenumber": "426",
    "addr:postcode": "44108",
    "addr:street": "E 115Th St",
    "iso:country": "US",
    "sg:address": "426 E 115th St",
    "sg:city": "Cleveland",
    "sg:classifiers": [
      {
        "category": "Social Services",
        "subcategory": "Child Care",
        "type": "Services"
      }
    ],
    "sg:phone": "+1 216 990 0944",
    "sg:postcode": "44108",
    "sg:province": "OH",
    "wof:name": "Anna's Daycare",
    "wof:placetype": "venue"
  },
  "geometry": {"coordinates":[-81.604988,41.545558],"type":"Point"}
}
