{
  "type": "Feature",
  "properties": {
    "iso:country":"US",
    "sg:address":"1820 E Main St",
    "sg:city":"Springfield",
    "sg:classifiers":[
        {
            "category":"Retail",
            "subcategory":"Auto Repair",
            "type":"Services"
        }
    ],
    "sg:phone":"+1 937 323 5002",
    "sg:postcode":"45503",
    "sg:province":"OH",
    "sg:tags":[
        "repairing",
        "automobile"
    ],
    "wof:name":"Eagle Automotive Car Care Ctr",
    "wof:placetype":"venue"
},
  "geometry": {"coordinates":[-83.781413,39.923397],"type":"Point"}
}