{
  "type": "Feature",
  "properties": {
    "iso:country":"US",
    "sg:address":"9108 Cox Rd",
    "sg:city":"West Chester",
    "sg:classifiers":[
        {
            "category":"Shopping",
            "subcategory":"Discount & Variety Stores",
            "type":"Retail Goods"
        }
    ],
    "sg:phone":"+1 513 777 4107",
    "sg:postcode":"45069",
    "sg:province":"OH",
    "wof:name":"Dollar General Store",
    "wof:placetype":"venue"
},
  "geometry": {"coordinates":[-84.367925,39.320996],"type":"Point"}
}