{
  "type": "Feature",
  "properties": {
    "addr:full": "324 Main St Hamilton IN 45013",
    "addr:housenumber": "324",
    "addr:postcode": "45013",
    "addr:street": "Main St",
    "iso:country": "US",
    "sg:address": "324 Main St",
    "sg:city": "Hamilton",
    "sg:classifiers": [
      {
        "category": "Professional",
        "subcategory": "Accounting \u0026 Tax Preparation",
        "type": "Services"
      }
    ],
    "sg:phone": "+1 513 868 8090",
    "sg:postcode": "45013",
    "sg:province": "IN",
    "sg:tags": [
      "return",
      "filing"
    ],
    "wof:name": "B \u0026 B Income Tax \u0026 Bookkeeping",
    "wof:placetype": "venue"
  },
  "geometry": {"coordinates":[-84.570082,39.404624],"type":"Point"}
}
