{
  "type": "Feature",
  "properties": {
    "addr:full": "956 Cleveland Ave Cincinnati OH 45229",
    "addr:housenumber": "956",
    "addr:postcode": "45229",
    "addr:street": "Cleveland Ave",
    "iso:country": "US",
    "sg:address": "956 Cleveland Ave",
    "sg:city": "Cincinnati",
    "sg:classifiers": [
      {
        "category": "Shopping",
        "subcategory": "Clothing, Apparel, \u0026 Fashions",
        "type": "Retail Goods"
      }
    ],
    "sg:phone": "+1 513 861 2905",
    "sg:postcode": "45229",
    "sg:province": "OH",
    "wof:name": "Carmen Lynn Crews Lingerie",
    "wof:placetype": "venue"
  },
  "geometry": {"coordinates":[-84.48651,39.142092],"type":"Point"}
}
