{
  "type": "Feature",
  "properties": {
    "addr:full":"2932 Noe Bixby Rd Columbus OH 43232",
    "addr:housenumber":"2932",
    "addr:postcode":"43232",
    "addr:street":"Noe Bixby Rd",
    "iso:country":"US",
    "sg:address":"2932 Noe Bixby Rd",
    "sg:city":"Columbus",
    "sg:classifiers":[
        {
            "category":"Bars & Pubs",
            "type":"Food & Drink"
        }
    ],
    "sg:phone":"+1 614 759 0800",
    "sg:postcode":"43232",
    "sg:province":"OH",
    "sg:tags":[
        "drinking"
    ],
    "wof:name":"Krazy Charlie's",
    "wof:placetype":"venue"
},
  "geometry": {"coordinates":[-82.86350400000001,39.915341],"type":"Point"}
}