{
  "type": "Feature",
  "properties": {
    "iso:country":"US",
    "sg:address":"1838 N State St",
    "sg:city":"Girard",
    "sg:classifiers":[
        {
            "category":"Retail",
            "subcategory":"Repair Shop",
            "type":"Services"
        }
    ],
    "sg:phone":"+1 330 545 8702",
    "sg:postcode":"44420",
    "sg:province":"OH",
    "sg:tags":[
        "lock",
        "locksmith"
    ],
    "wof:name":"Ace Lock & Key",
    "wof:placetype":"venue"
},
  "geometry": {"coordinates":[-80.71033300000001,41.175191],"type":"Point"}
}