{
  "type": "Feature",
  "properties": {
    "iso:country":"US",
    "sg:address":"240 N 7th St",
    "sg:city":"Steubenville",
    "sg:classifiers":[
        {
            "category":"Shopping",
            "subcategory":"Discount & Variety Stores",
            "type":"Retail Goods"
        },
        {
            "category":"Shopping",
            "subcategory":"Department Store",
            "type":"Retail Goods"
        }
    ],
    "sg:phone":"+1 740 282 5358",
    "sg:postcode":"43952",
    "sg:province":"OH",
    "wof:name":"Family Dollar Stores",
    "wof:placetype":"venue"
},
  "geometry": {"coordinates":[-80.617778,40.364719],"type":"Point"}
}