{
  "type": "Feature",
  "properties": {
    "addr:full":"105 Atwood Pl Huron OH 44839",
    "addr:housenumber":"105",
    "addr:postcode":"44839",
    "addr:street":"Atwood Pl",
    "iso:country":"US",
    "sg:address":"105 Atwood Pl",
    "sg:city":"Huron",
    "sg:classifiers":[
        {
            "category":"Taxi",
            "type":"Transportation"
        }
    ],
    "sg:phone":"+1 419 656 3647",
    "sg:postcode":"44839",
    "sg:province":"OH",
    "sg:tags":[
        "taxicab"
    ],
    "wof:name":"Best Bet Shuttle",
    "wof:placetype":"venue"
},
  "geometry": {"coordinates":[-82.590231,41.412179],"type":"Point"}
}