{
  "type": "Feature",
  "properties": {
    "addr:full": "639 Talowood Dr Beavercreek OH 45430",
    "addr:housenumber": "639",
    "addr:postcode": "45430",
    "addr:street": "Talowood Dr",
    "iso:country": "US",
    "sg:address": "639 Talowood Dr",
    "sg:city": "Beavercreek",
    "sg:classifiers": [
      {
        "category": "Building \u0026 Trades",
        "subcategory": "Plumbing",
        "type": "Services"
      }
    ],
    "sg:phone": "+1 937 426 4659",
    "sg:postcode": "45430",
    "sg:province": "OH",
    "sg:tags": [
      "plumbing",
      "contractor"
    ],
    "wof:name": "Drain Works Quality Svc",
    "wof:placetype": "venue"
  },
  "geometry": {"coordinates":[-84.074678,39.709617],"type":"Point"}
}
