{
  "type": "Feature",
  "properties": {
    "iso:country":"US",
    "sg:address":"1600 N Limestone St",
    "sg:city":"Springfield",
    "sg:classifiers":[
        {
            "category":"Education",
            "subcategory":"School",
            "type":"Public Place"
        }
    ],
    "sg:phone":"+1 937 342 4162",
    "sg:postcode":"45503",
    "sg:province":"OH",
    "wof:name":"Springfield City Schools",
    "wof:placetype":"venue"
},
  "geometry": {"coordinates":[-83.80489,39.943871],"type":"Point"}
}