{
  "type": "Feature",
  "properties": {
    "addr:full": "10151 Jug St Pataskala OH 43062",
    "addr:housenumber": "10151",
    "addr:postcode": "43062",
    "addr:street": "Jug St",
    "iso:country": "US",
    "sg:address": "10151 Jug St",
    "sg:city": "Pataskala",
    "sg:classifiers": [
      {
        "category": "Insurance",
        "subcategory": "Insurance Agent",
        "type": "Services"
      }
    ],
    "sg:phone": "+1 740 924 9066",
    "sg:postcode": "43062",
    "sg:province": "OH",
    "wof:name": "American Family Insurance",
    "wof:placetype": "venue"
  },
  "geometry": {"coordinates":[-82.679879,40.096885],"type":"Point"}
}
