{
  "type": "Feature",
  "properties": {
    "addr:full": "10912 Rd 93 Paulding OH 45879",
    "addr:housenumber": "10912",
    "addr:postcode": "45879",
    "addr:street": "Rd 93",
    "iso:country": "US",
    "sg:address": "10912 Rd 93",
    "sg:city": "Paulding",
    "sg:classifiers": [
      {
        "category": "Wholesale",
        "subcategory": "Machinery \u0026 Supplies",
        "type": "Manufacturing \u0026 Wholesale Goods"
      },
      {
        "category": "Retail",
        "subcategory": "Repair Shop",
        "type": "Services"
      }
    ],
    "sg:phone": "+1 419 399 5899",
    "sg:postcode": "45879",
    "sg:province": "OH",
    "sg:tags": [
      "equipment",
      "establishment",
      "commercial",
      "welding"
    ],
    "wof:name": "Mac Donald Portable Welding",
    "wof:placetype": "venue"
  },
  "geometry": {"coordinates":[-84.6217,41.128722],"type":"Point"}
}
