{
  "type": "Feature",
  "properties": {
    "addr:full": "94 Fox Trace Ln Hudson OH 44236",
    "addr:housenumber": "94",
    "addr:postcode": "44236",
    "addr:street": "Fox Trace Ln",
    "iso:country": "US",
    "sg:address": "94 Fox Trace Ln",
    "sg:city": "Hudson",
    "sg:classifiers": [
      {
        "category": "Professional",
        "subcategory": "Management \u0026 Consulting",
        "type": "Services"
      }
    ],
    "sg:phone": "+1 330 463 5353",
    "sg:postcode": "44236",
    "sg:province": "OH",
    "sg:tags": [
      "consultant",
      "business"
    ],
    "wof:name": "Tabs Group",
    "wof:placetype": "venue"
  },
  "geometry": {"coordinates":[-81.431502,41.239784],"type":"Point"}
}
