{
  "type": "Feature",
  "properties": {
    "iso:country":"US",
    "sg:address":"1011 Winnebago Ave",
    "sg:city":"Sandusky",
    "sg:classifiers":[
        {
            "category":"Autos & Motor Vehicles",
            "subcategory":"Automobile Sales",
            "type":"Retail Goods"
        }
    ],
    "sg:phone":"+1 419 627 9874",
    "sg:postcode":"44870",
    "sg:province":"OH",
    "sg:tags":[
        "car",
        "dealer"
    ],
    "wof:name":"North Coast Motorcars",
    "wof:placetype":"venue"
},
  "geometry": {"coordinates":[-82.74651,41.445873],"type":"Point"}
}