{
  "type": "Feature",
  "properties": {
    "iso:country":"US",
    "sg:address":"701 Broad Ave NW",
    "sg:city":"Canton",
    "sg:classifiers":[
        {
            "category":"Organizations",
            "subcategory":"Religious Organization",
            "type":"Services"
        }
    ],
    "sg:phone":"+1 330 454 3978",
    "sg:postcode":"44708",
    "sg:province":"OH",
    "sg:website":"www.bethel-lutheranchurch.org",
    "wof:name":"Bethel Lutheran Church",
    "wof:placetype":"venue"
},
  "geometry": {"coordinates":[-81.40500900000001,40.806182],"type":"Point"}
}