{
  "type": "Feature",
  "properties": {
    "iso:country":"US",
    "sg:address":"17647 Foltz Industrial Pkwy",
    "sg:city":"Strongsville",
    "sg:classifiers":[
        {
            "category":"Insurance",
            "subcategory":"Insurance Agent",
            "type":"Services"
        }
    ],
    "sg:phone":"+1 440 572 2880",
    "sg:postcode":"44149",
    "sg:province":"OH",
    "wof:name":"Catan Lamrite Inc",
    "wof:placetype":"venue"
},
  "geometry": {"coordinates":[-81.869393,41.294451],"type":"Point"}
}