{
  "type": "Feature",
  "properties": {
    "iso:country":"US",
    "sg:address":"433 W Bagley Rd",
    "sg:city":"Berea",
    "sg:classifiers":[
        {
            "category":"Travel",
            "subcategory":"Travel Agent",
            "type":"Entertainment"
        }
    ],
    "sg:phone":"+1 440 816 1760",
    "sg:postcode":"44017",
    "sg:province":"OH",
    "sg:tags":[
        "agency",
        "bureau"
    ],
    "sg:website":"www.kandktravel.com",
    "wof:name":"K & K Travel",
    "wof:placetype":"venue"
},
  "geometry": {"coordinates":[-81.866215,41.372117],"type":"Point"}
}