{
  "type": "Feature",
  "properties": {
    "addr:full": "2384 Lester Rd Valley City OH 44280",
    "addr:housenumber": "2384",
    "addr:postcode": "44280",
    "addr:street": "Lester Rd",
    "iso:country": "US",
    "sg:address": "2384 Lester Rd",
    "sg:city": "Valley City",
    "sg:classifiers": [
      {
        "category": "Professional",
        "subcategory": "Art Services",
        "type": "Services"
      }
    ],
    "sg:phone": "+1 330 483 3160",
    "sg:postcode": "44280",
    "sg:province": "OH",
    "sg:tags": [
      "photographer"
    ],
    "wof:name": "Valley Audio Visual",
    "wof:placetype": "venue"
  },
  "geometry": {"coordinates":[-81.935803,41.209739],"type":"Point"}
}
