{
  "type": "Feature",
  "properties": {
    "addr:full":"516 W North St West Unity OH 43570",
    "addr:housenumber":"516",
    "addr:postcode":"43570",
    "addr:street":"W North St",
    "iso:country":"US",
    "sg:address":"516 W North St",
    "sg:city":"West Unity",
    "sg:classifiers":[
        {
            "category":"Manufacturing",
            "subcategory":"Metals",
            "type":"Manufacturing & Wholesale Goods"
        }
    ],
    "sg:phone":"+1 419 924 2386",
    "sg:postcode":"43570",
    "sg:province":"OH",
    "sg:tags":[
        "fabricated",
        "structural"
    ],
    "wof:name":"BDJ Industries Inc",
    "wof:placetype":"venue"
},
  "geometry": {"coordinates":[-84.438137,41.587485],"type":"Point"}
}