{
  "type": "Feature",
  "properties": {
    "addr:full": "3333 E 55th St Cleveland OH 44127",
    "addr:housenumber": "3333",
    "addr:postcode": "44127",
    "addr:street": "E 55Th St",
    "iso:country": "US",
    "sg:address": "3333 E 55th St",
    "sg:city": "Cleveland",
    "sg:classifiers": [
      {
        "category": "Building \u0026 Trades",
        "subcategory": "Construction",
        "type": "Services"
      }
    ],
    "sg:phone": "+1 216 441 9585",
    "sg:postcode": "44127",
    "sg:province": "OH",
    "sg:tags": [
      "home",
      "improvement"
    ],
    "wof:name": "Vinyl Systems Inc",
    "wof:placetype": "venue"
  },
  "geometry": {"coordinates":[-81.651211,41.46767],"type":"Point"}
}
