{
  "type": "Feature",
  "properties": {
    "addr:full": "17 N Sandusky St Delaware OH 43015",
    "addr:housenumber": "17",
    "addr:postcode": "43015",
    "addr:street": "N Sandusky St",
    "iso:country": "US",
    "sg:address": "17 N Sandusky St",
    "sg:city": "Delaware",
    "sg:classifiers": [
      {
        "category": "Shopping",
        "subcategory": "Used Merchandise",
        "type": "Retail Goods"
      }
    ],
    "sg:phone": "+1 740 362 1140",
    "sg:postcode": "43015",
    "sg:province": "OH",
    "sg:tags": [
      "antique"
    ],
    "wof:name": "DPS Antiques \u0026 Collectibles",
    "wof:placetype": "venue"
  },
  "geometry": {"coordinates":[-83.067765,40.299599],"type":"Point"}
}
