{
  "type": "Feature",
  "properties": {
    "addr:full": "711 Lilac Ln Marion OH 43302",
    "addr:housenumber": "711",
    "addr:postcode": "43302",
    "addr:street": "Lilac Ln",
    "iso:country": "US",
    "sg:address": "711 Lilac Ln",
    "sg:city": "Marion",
    "sg:classifiers": [
      {
        "category": "Bars \u0026 Pubs",
        "type": "Food \u0026 Drink"
      }
    ],
    "sg:phone": "+1 740 382 8585",
    "sg:postcode": "43302",
    "sg:province": "OH",
    "sg:tags": [
      "drinking"
    ],
    "wof:name": "Ot Tavern Inc",
    "wof:placetype": "venue"
  },
  "geometry": {"coordinates":[-83.137097,40.576212],"type":"Point"}
}
