{
  "type": "Feature",
  "properties": {
    "addr:full": "4257 E Main St Columbus OH 43213",
    "addr:housenumber": "4257",
    "addr:postcode": "43213",
    "addr:street": "E Main St",
    "iso:country": "US",
    "sg:address": "4257 E Main St",
    "sg:city": "Columbus",
    "sg:classifiers": [
      {
        "category": "Autos \u0026 Motor Vehicles",
        "subcategory": "Auto Supplies",
        "type": "Retail Goods"
      },
      {
        "category": "Wholesale",
        "subcategory": "Auto Parts",
        "type": "Manufacturing \u0026 Wholesale Goods"
      }
    ],
    "sg:phone": "+1 614 236 2035",
    "sg:postcode": "43213",
    "sg:province": "OH",
    "sg:tags": [
      "retreading",
      "tire"
    ],
    "wof:name": "CMC Tires",
    "wof:placetype": "venue"
  },
  "geometry": {"coordinates":[-82.884818,39.955641],"type":"Point"}
}
