{
  "type": "Feature",
  "properties": {
    "addr:full":"1080 Industrial Pkwy Medina OH 44256",
    "addr:housenumber":"1080",
    "addr:postcode":"44256",
    "addr:street":"Industrial Pkwy",
    "iso:country":"US",
    "sg:address":"1080 Industrial Pkwy",
    "sg:city":"Medina",
    "sg:classifiers":[
        {
            "category":"Manufacturing",
            "subcategory":"Tools & Machinery",
            "type":"Manufacturing & Wholesale Goods"
        }
    ],
    "sg:phone":"+1 330 723 4431",
    "sg:postcode":"44256",
    "sg:province":"OH",
    "sg:tags":[
        "equipment",
        "lighting",
        "electrical",
        "mfg"
    ],
    "wof:name":"Main Street Orna Lamp Posts",
    "wof:placetype":"venue"
},
  "geometry": {"coordinates":[-81.897279,41.116033],"type":"Point"}
}