{
  "type": "Feature",
  "properties": {
    "iso:country":"US",
    "sg:address":"310 Judith Dr",
    "sg:city":"Dayton",
    "sg:classifiers":[
        {
            "category":"Professional",
            "type":"Services"
        }
    ],
    "sg:phone":"+1 937 433 5537",
    "sg:postcode":"45429",
    "sg:province":"OH",
    "wof:name":"Alfonso Velez",
    "wof:placetype":"venue"
},
  "geometry": {"coordinates":[-84.16160499999999,39.675278],"type":"Point"}
}