{
  "type": "Feature",
  "properties": {
    "addr:full": "310 Judith Dr Dayton OH 45429",
    "addr:housenumber": "310",
    "addr:postcode": "45429",
    "addr:street": "Judith Dr",
    "iso:country": "US",
    "sg:address": "310 Judith Dr",
    "sg:city": "Dayton",
    "sg:classifiers": [
      {
        "category": "Professional",
        "type": "Services"
      }
    ],
    "sg:phone": "+1 937 433 5537",
    "sg:postcode": "45429",
    "sg:province": "OH",
    "wof:name": "Alfonso Velez",
    "wof:placetype": "venue"
  },
  "geometry": {"coordinates":[-84.161605,39.675278],"type":"Point"}
}
