{
  "type": "Feature",
  "properties": {
    "iso:country":"US",
    "sg:address":"723 Loda Dr",
    "sg:city":"Cincinnati",
    "sg:classifiers":[
        {
            "category":"Organizations",
            "subcategory":"Non-profit Organization",
            "type":"Services"
        }
    ],
    "sg:phone":"+1 513 753 8222",
    "sg:postcode":"45245",
    "sg:province":"OH",
    "wof:name":"Families Of Sma Oki Chapter",
    "wof:placetype":"venue"
},
  "geometry": {"coordinates":[-84.288938,39.071205],"type":"Point"}
}