{
  "type": "Feature",
  "properties": {
    "addr:full": "264 Westbear Ct Galloway OH 43119",
    "addr:housenumber": "264",
    "addr:postcode": "43119",
    "addr:street": "Westbear Ct",
    "iso:country": "US",
    "sg:address": "264 Westbear Ct",
    "sg:city": "Galloway",
    "sg:classifiers": [
      {
        "category": "Professional",
        "type": "Services"
      }
    ],
    "sg:phone": "+1 614 870 9404",
    "sg:postcode": "43119",
    "sg:province": "OH",
    "wof:name": "Tom Lethat",
    "wof:placetype": "venue"
  },
  "geometry": {"coordinates":[-83.159542,39.955875],"type":"Point"}
}
