{
  "type": "Feature",
  "properties": {
    "addr:full": "3975 Dayton Park Dr Dayton OH 45414",
    "addr:housenumber": "3975",
    "addr:postcode": "45414",
    "addr:street": "Dayton Park Dr",
    "iso:country": "US",
    "sg:address": "3975 Dayton Park Dr",
    "sg:city": "Dayton",
    "sg:classifiers": [
      {
        "category": "Wholesale",
        "subcategory": "Groceries",
        "type": "Manufacturing \u0026 Wholesale Goods"
      }
    ],
    "sg:phone": "+1 937 233 1177",
    "sg:postcode": "45414",
    "sg:province": "OH",
    "sg:tags": [
      "juice",
      "commercial",
      "equipment"
    ],
    "wof:name": "Midwest Juice \u0026 Syrup Co Inc",
    "wof:placetype": "venue"
  },
  "geometry": {"coordinates":[-84.172166,39.802228],"type":"Point"}
}
