{
  "type": "Feature",
  "properties": {
    "addr:full": "2000 Jefferson St Springfield OH 45506",
    "addr:housenumber": "2000",
    "addr:postcode": "45506",
    "addr:street": "Jefferson St",
    "iso:country": "US",
    "sg:address": "2000 Jefferson St",
    "sg:city": "Springfield",
    "sg:classifiers": [
      {
        "category": "Autos \u0026 Motor Vehicles",
        "subcategory": "Fuel \u0026 Gas Station",
        "type": "Retail Goods"
      }
    ],
    "sg:phone": "+1 937 322 1873",
    "sg:postcode": "45506",
    "sg:province": "OH",
    "sg:tags": [
      "grocery",
      "station",
      "gasoline"
    ],
    "wof:name": "Speedway Superamerica LLC",
    "wof:placetype": "venue"
  },
  "geometry": {"coordinates":[-83.844051,39.923014],"type":"Point"}
}
