{
  "type": "Feature",
  "properties": {
    "iso:country":"US",
    "sg:address":"2000 Jefferson St",
    "sg:city":"Springfield",
    "sg:classifiers":[
        {
            "category":"Autos & Motor Vehicles",
            "subcategory":"Fuel & Gas Station",
            "type":"Retail Goods"
        }
    ],
    "sg:phone":"+1 937 322 1873",
    "sg:postcode":"45506",
    "sg:province":"OH",
    "sg:tags":[
        "grocery",
        "station",
        "gasoline"
    ],
    "wof:name":"Speedway Superamerica LLC",
    "wof:placetype":"venue"
},
  "geometry": {"coordinates":[-83.84405099999999,39.923014],"type":"Point"}
}