{
  "type": "Feature",
  "properties": {
    "addr:full": "7279 Ballycastle Dr Columbus OH 43235",
    "addr:housenumber": "7279",
    "addr:postcode": "43235",
    "addr:street": "Ballycastle Dr",
    "iso:country": "US",
    "sg:address": "7279 Ballycastle Dr",
    "sg:city": "Columbus",
    "sg:classifiers": [
      {
        "category": "Home \u0026 Garden",
        "subcategory": "Building Materials",
        "type": "Retail Goods"
      }
    ],
    "sg:phone": "+1 614 210 0103",
    "sg:postcode": "43235",
    "sg:province": "OH",
    "sg:tags": [
      "glass",
      "window",
      "plate"
    ],
    "wof:name": "Safelite Auto Glass",
    "wof:placetype": "venue"
  },
  "geometry": {"coordinates":[-83.078143,40.110589],"type":"Point"}
}
