{
  "type": "Feature",
  "properties": {
    "addr:full":"103 N Brookwood Ave Hamilton IN 45013",
    "addr:housenumber":"103",
    "addr:postcode":"45013",
    "addr:street":"N Brookwood Ave",
    "iso:country":"US",
    "sg:address":"103 N Brookwood Ave",
    "sg:city":"Hamilton",
    "sg:classifiers":[
        {
            "category":"Insurance",
            "subcategory":"Insurance Agent",
            "type":"Services"
        }
    ],
    "sg:phone":"+1 513 863 8797",
    "sg:postcode":"45013",
    "sg:province":"IN",
    "wof:name":"Allstate",
    "wof:placetype":"venue"
},
  "geometry": {"coordinates":[-84.587068,39.422121],"type":"Point"}
}