{
  "type": "Feature",
  "properties": {
    "iso:country":"US",
    "sg:address":"206 Washington Blvd",
    "sg:city":"Belpre",
    "sg:classifiers":[
        {
            "category":"Autos & Motor Vehicles",
            "subcategory":"Fuel & Gas Station",
            "type":"Retail Goods"
        }
    ],
    "sg:phone":"+1 740 423 5378",
    "sg:postcode":"45714",
    "sg:province":"OH",
    "sg:tags":[
        "station",
        "oil"
    ],
    "wof:name":"B P Oil Co",
    "wof:placetype":"venue"
},
  "geometry": {"coordinates":[-81.57099100000001,39.272332],"type":"Point"}
}