{
  "type": "Feature",
  "properties": {
    "addr:full":"100 Glenn Ave Washington Ct Hs OH 43160",
    "addr:housenumber":"100",
    "addr:postcode":"43160",
    "addr:street":"Glenn Ave Washington Ct",
    "iso:country":"US",
    "sg:address":"100 Glenn Ave",
    "sg:city":"Washington Ct Hs",
    "sg:classifiers":[
        {
            "category":"Professional",
            "subcategory":"Employment Agencies",
            "type":"Services"
        }
    ],
    "sg:phone":"+1 740 335 6852",
    "sg:postcode":"43160",
    "sg:province":"OH",
    "sg:tags":[
        "opportunity"
    ],
    "wof:name":"Remedy Intelligent Staffing",
    "wof:placetype":"venue"
},
  "geometry": {"coordinates":[-83.42665599999999,39.553543],"type":"Point"}
}