{
  "type": "Feature",
  "properties": {
    "addr:full":"11105 Chillicothe Rd Chesterland OH 44026",
    "addr:housenumber":"11105",
    "addr:postcode":"44026",
    "addr:street":"Chillicothe Rd",
    "iso:country":"US",
    "sg:address":"11105 Chillicothe Rd",
    "sg:city":"Chesterland",
    "sg:classifiers":[
        {
            "category":"Building & Trades",
            "subcategory":"Construction",
            "type":"Services"
        }
    ],
    "sg:phone":"+1 440 729 7057",
    "sg:postcode":"44026",
    "sg:province":"OH",
    "sg:tags":[
        "excavation",
        "contractor"
    ],
    "wof:name":"Gary Cloonan Excavating Inc",
    "wof:placetype":"venue"
},
  "geometry": {"coordinates":[-81.348332,41.569485],"type":"Point"}
}