{
  "type": "Feature",
  "properties": {
    "addr:full": "74 8th St NW Barberton OH 44203",
    "addr:housenumber": "74",
    "addr:postcode": "44203",
    "addr:street": "8Th St Nw",
    "iso:country": "US",
    "sg:address": "74 8th St NW",
    "sg:city": "Barberton",
    "sg:classifiers": [
      {
        "category": "Autos \u0026 Motor Vehicles",
        "subcategory": "Motorcycle Sales",
        "type": "Retail Goods"
      }
    ],
    "sg:phone": "+1 330 753 7780",
    "sg:postcode": "44203",
    "sg:province": "OH",
    "sg:tags": [
      "scooter"
    ],
    "wof:name": "American Thunder Of Barberton",
    "wof:placetype": "venue"
  },
  "geometry": {"coordinates":[-81.614927,41.01242],"type":"Point"}
}
