{
  "type": "Feature",
  "properties": {
    "addr:full":"1639 Tall Meadows Dr Columbus OH 43223",
    "addr:housenumber":"1639",
    "addr:postcode":"43223",
    "addr:street":"Tall Meadows Dr",
    "iso:country":"US",
    "sg:address":"1639 Tall Meadows Dr",
    "sg:city":"Columbus",
    "sg:classifiers":[
        {
            "category":"Building & Trades",
            "subcategory":"Plumbing",
            "type":"Services"
        }
    ],
    "sg:phone":"+1 614 459 0770",
    "sg:postcode":"43223",
    "sg:province":"OH",
    "sg:tags":[
        "contractor"
    ],
    "wof:name":"Central Ohio Mechanical",
    "wof:placetype":"venue"
},
  "geometry": {"coordinates":[-83.081756,39.923368],"type":"Point"}
}