{
  "type": "Feature",
  "properties": {
    "addr:full": "1716 Remelle Rd Monroeville OH 44847",
    "addr:housenumber": "1716",
    "addr:postcode": "44847",
    "addr:street": "Remelle Rd",
    "iso:country": "US",
    "sg:address": "1716 Remelle Rd",
    "sg:city": "Monroeville",
    "sg:classifiers": [
      {
        "category": "Building \u0026 Trades",
        "subcategory": "Construction",
        "type": "Services"
      }
    ],
    "sg:phone": "+1 419 663 3113",
    "sg:postcode": "44847",
    "sg:province": "OH",
    "sg:tags": [
      "excavating",
      "contractor"
    ],
    "wof:name": "Buckeye Excavating \u0026 Constr",
    "wof:placetype": "venue"
  },
  "geometry": {"coordinates":[-82.662634,41.177002],"type":"Point"}
}
