{
  "type": "Feature",
  "properties": {
    "addr:full":"1658 Morrison Farms Dr Blacklick OH 43004",
    "addr:housenumber":"1658",
    "addr:postcode":"43004",
    "addr:street":"Morrison Farms Dr",
    "iso:country":"US",
    "sg:address":"1658 Morrison Farms Dr",
    "sg:city":"Blacklick",
    "sg:classifiers":[
        {
            "category":"Building & Trades",
            "subcategory":"Landscaping Services",
            "type":"Services"
        }
    ],
    "sg:phone":"+1 614 868 1887",
    "sg:postcode":"43004",
    "sg:province":"OH",
    "sg:tags":[
        "sanitary"
    ],
    "wof:name":"Natures Gifts Inc",
    "wof:placetype":"venue"
},
  "geometry": {"coordinates":[-82.78654400000001,40.016871],"type":"Point"}
}