{
  "type": "Feature",
  "properties": {
    "addr:full": "15611 Detroit Ave Cleveland OH 44107",
    "addr:housenumber": "15611",
    "addr:postcode": "44107",
    "addr:street": "Detroit Ave",
    "iso:country": "US",
    "sg:address": "15611 Detroit Ave",
    "sg:city": "Cleveland",
    "sg:classifiers": [
      {
        "category": "Personal",
        "subcategory": "Beauty Salon",
        "type": "Services"
      }
    ],
    "sg:phone": "+1 216 521 3220",
    "sg:postcode": "44107",
    "sg:province": "OH",
    "wof:name": "Changes-Hair Salon",
    "wof:placetype": "venue"
  },
  "geometry": {"coordinates":[-81.807009,41.485063],"type":"Point"}
}
