{
  "type": "Feature",
  "properties": {
    "iso:country":"US",
    "sg:address":"15611 Detroit Ave",
    "sg:city":"Cleveland",
    "sg:classifiers":[
        {
            "category":"Personal",
            "subcategory":"Beauty Salon",
            "type":"Services"
        }
    ],
    "sg:phone":"+1 216 521 3220",
    "sg:postcode":"44107",
    "sg:province":"OH",
    "wof:name":"Changes-Hair Salon",
    "wof:placetype":"venue"
},
  "geometry": {"coordinates":[-81.80700899999999,41.485063],"type":"Point"}
}