{
  "type": "Feature",
  "properties": {
    "iso:country":"US",
    "sg:address":"486 Olivet Dr",
    "sg:city":"Elyria",
    "sg:classifiers":[
        {
            "category":"Manufacturing",
            "subcategory":"Jewelry",
            "type":"Manufacturing & Wholesale Goods"
        }
    ],
    "sg:phone":"+1 440 329 7907",
    "sg:postcode":"44035",
    "sg:province":"OH",
    "sg:tags":[
        "precious",
        "metal",
        "mfg"
    ],
    "wof:name":"White Hawk Jewelry",
    "wof:placetype":"venue"
},
  "geometry": {"coordinates":[-82.086442,41.389406],"type":"Point"}
}