{
  "type": "Feature",
  "properties": {
    "iso:country":"US",
    "sg:address":"653 Miner Rd",
    "sg:city":"Cleveland",
    "sg:classifiers":[
        {
            "category":"Manufacturing",
            "subcategory":"Tools & Machinery",
            "type":"Manufacturing & Wholesale Goods"
        }
    ],
    "sg:phone":"+1 440 684 3000",
    "sg:postcode":"44143",
    "sg:province":"OH",
    "sg:tags":[
        "pip",
        "repair",
        "industrial",
        "welding",
        "mfg"
    ],
    "wof:name":"Alloy Bellows & Precision Wldg",
    "wof:placetype":"venue"
},
  "geometry": {"coordinates":[-81.458192,41.539201],"type":"Point"}
}