{
  "type": "Feature",
  "properties": {
    "addr:full": "4256 Hawkins Rd New Waterford OH 44445",
    "addr:housenumber": "4256",
    "addr:postcode": "44445",
    "addr:street": "Hawkins Rd",
    "iso:country": "US",
    "sg:address": "4256 Hawkins Rd",
    "sg:city": "New Waterford",
    "sg:classifiers": [
      {
        "category": "Building \u0026 Trades",
        "subcategory": "Construction",
        "type": "Services"
      }
    ],
    "sg:phone": "+1 330 457 2869",
    "sg:postcode": "44445",
    "sg:province": "OH",
    "sg:tags": [
      "house"
    ],
    "wof:name": "Stacy Builders Inc",
    "wof:placetype": "venue"
  },
  "geometry": {"coordinates":[-80.613896,40.836707],"type":"Point"}
}
