{
  "type": "Feature",
  "properties": {
    "iso:country":"US",
    "sg:address":"34939 N Turtle Trl",
    "sg:city":"Willoughby",
    "sg:classifiers":[
        {
            "category":"Professional",
            "type":"Services"
        }
    ],
    "sg:phone":"+1 440 918 0677",
    "sg:postcode":"44094",
    "sg:province":"OH",
    "wof:name":"A Petal Apart From Rest",
    "wof:placetype":"venue"
},
  "geometry": {"coordinates":[-81.438436,41.62152],"type":"Point"}
}