{
  "type": "Feature",
  "properties": {
    "addr:full":"1211 S Defiance St Archbold OH 43502",
    "addr:housenumber":"1211",
    "addr:postcode":"43502",
    "addr:street":"S Defiance St",
    "iso:country":"US",
    "sg:address":"1211 S Defiance St",
    "sg:city":"Archbold",
    "sg:classifiers":[
        {
            "category":"Social Services",
            "type":"Services"
        }
    ],
    "sg:phone":"+1 419 445 0800",
    "sg:postcode":"43502",
    "sg:province":"OH",
    "sg:tags":[
        "youth",
        "organization",
        "center"
    ],
    "wof:name":"Outback Youth Center",
    "wof:placetype":"venue"
},
  "geometry": {"coordinates":[-84.306589,41.509517],"type":"Point"}
}