{
  "type": "Feature",
  "properties": {
    "iso:country":"US",
    "sg:address":"327 Main St",
    "sg:city":"Coshocton",
    "sg:classifiers":[
        {
            "category":"Autos & Motor Vehicles",
            "subcategory":"Automobile Sales",
            "type":"Retail Goods"
        }
    ],
    "sg:phone":"+1 740 622 3792",
    "sg:postcode":"43812",
    "sg:province":"OH",
    "wof:name":"McFarland John",
    "wof:placetype":"venue"
},
  "geometry": {"coordinates":[-81.866297,40.273574],"type":"Point"}
}