{
  "type": "Feature",
  "properties": {
    "addr:full":"20725 Belvidere Ave Cleveland OH 44126",
    "addr:housenumber":"20725",
    "addr:postcode":"44126",
    "addr:street":"Belvidere Ave",
    "iso:country":"US",
    "sg:address":"20725 Belvidere Ave",
    "sg:city":"Cleveland",
    "sg:classifiers":[
        {
            "category":"Building & Trades",
            "subcategory":"Plumbing",
            "type":"Services"
        }
    ],
    "sg:phone":"+1 440 356 1997",
    "sg:postcode":"44126",
    "sg:province":"OH",
    "sg:tags":[
        "contractor"
    ],
    "wof:name":"Wallace Heating & AC",
    "wof:placetype":"venue"
},
  "geometry": {"coordinates":[-81.85278599999999,41.453592],"type":"Point"}
}