{
  "type": "Feature",
  "properties": {
    "addr:full":"115 N Pleasant St Georgetown OH 45121",
    "addr:housenumber":"115",
    "addr:postcode":"45121",
    "addr:street":"N Pleasant St",
    "iso:country":"US",
    "sg:address":"115 N Pleasant St",
    "sg:city":"Georgetown",
    "sg:classifiers":[
        {
            "category":"Manufacturing",
            "subcategory":"Printing",
            "type":"Manufacturing & Wholesale Goods"
        }
    ],
    "sg:phone":"+1 937 378 9040",
    "sg:postcode":"45121",
    "sg:province":"OH",
    "sg:tags":[
        "lithographic",
        "commercial"
    ],
    "wof:name":"Perfect Print",
    "wof:placetype":"venue"
},
  "geometry": {"coordinates":[-83.905052,38.867641],"type":"Point"}
}