{
  "type": "Feature",
  "properties": {
    "addr:full":"222 Meigs St Sandusky OH 44870",
    "addr:housenumber":"222",
    "addr:postcode":"44870",
    "addr:street":"Meigs St",
    "iso:country":"US",
    "sg:address":"222 Meigs St",
    "sg:city":"Sandusky",
    "sg:classifiers":[
        {
            "category":"Government",
            "subcategory":"Office",
            "type":"Public Place"
        }
    ],
    "sg:phone":"+1 419 627 5879",
    "sg:postcode":"44870",
    "sg:province":"OH",
    "sg:tags":[
        "village"
    ],
    "wof:name":"Sandusky City Public Svc Dept",
    "wof:placetype":"venue"
},
  "geometry": {"coordinates":[-82.702032,41.45904],"type":"Point"}
}