{
  "type": "Feature",
  "properties": {
    "iso:country":"US",
    "sg:address":"1029 Halesworth Dr",
    "sg:city":"Cincinnati",
    "sg:classifiers":[
        {
            "category":"Wholesale",
            "subcategory":"Machinery & Supplies",
            "type":"Manufacturing & Wholesale Goods"
        }
    ],
    "sg:phone":"+1 513 742 0254",
    "sg:postcode":"45240",
    "sg:province":"OH",
    "sg:tags":[
        "salon",
        "beauty"
    ],
    "wof:name":"Mother Goins",
    "wof:placetype":"venue"
},
  "geometry": {"coordinates":[-84.516998,39.2915],"type":"Point"}
}