{
  "type": "Feature",
  "properties": {
    "addr:full":"1509 Lake Ave Elyria OH 44035",
    "addr:housenumber":"1509",
    "addr:postcode":"44035",
    "addr:street":"Lake Ave",
    "iso:country":"US",
    "sg:address":"1509 Lake Ave",
    "sg:city":"Elyria",
    "sg:classifiers":[
        {
            "category":"Shopping",
            "subcategory":"Clothing, Apparel, & Fashions",
            "type":"Retail Goods"
        }
    ],
    "sg:phone":"+1 440 324 3431",
    "sg:postcode":"44035",
    "sg:province":"OH",
    "wof:name":"Petra Lingerie Fashions",
    "wof:placetype":"venue"
},
  "geometry": {"coordinates":[-82.129273,41.387338],"type":"Point"}
}