{
  "type": "Feature",
  "properties": {
    "iso:country":"US",
    "sg:address":"9075 Bank St",
    "sg:city":"Cleveland",
    "sg:classifiers":[
        {
            "category":"Wholesale",
            "subcategory":"Medical Equipment & Supplies",
            "type":"Manufacturing & Wholesale Goods"
        }
    ],
    "sg:phone":"+1 216 328 9801",
    "sg:postcode":"44125",
    "sg:province":"OH",
    "sg:tags":[
        "hospital"
    ],
    "wof:name":"Lifegas",
    "wof:placetype":"venue"
},
  "geometry": {"coordinates":[-81.624265,41.405881],"type":"Point"}
}