{
  "type": "Feature",
  "properties": {
    "addr:full": "9318 Sheehan Rd Dayton OH 45458",
    "addr:housenumber": "9318",
    "addr:postcode": "45458",
    "addr:street": "Sheehan Rd",
    "iso:country": "US",
    "sg:address": "9318 Sheehan Rd",
    "sg:city": "Dayton",
    "sg:classifiers": [
      {
        "category": "Building \u0026 Trades",
        "subcategory": "Landscaping Services",
        "type": "Services"
      }
    ],
    "sg:phone": "+1 937 435 5118",
    "sg:postcode": "45458",
    "sg:province": "OH",
    "sg:tags": [
      "landscape",
      "contractor"
    ],
    "wof:name": "Worth Landscape Svc",
    "wof:placetype": "venue"
  },
  "geometry": {"coordinates":[-84.164498,39.605879],"type":"Point"}
}
