{
  "type": "Feature",
  "properties": {
    "addr:full":"1131 Race St Cincinnati OH 45202",
    "addr:housenumber":"1131",
    "addr:postcode":"45202",
    "addr:street":"Race St",
    "iso:country":"US",
    "sg:address":"1131 Race St",
    "sg:city":"Cincinnati",
    "sg:classifiers":[
        {
            "category":"Utilities",
            "subcategory":"Mobile Phone",
            "type":"Services"
        }
    ],
    "sg:phone":"+1 513 241 7550",
    "sg:postcode":"45202",
    "sg:province":"OH",
    "sg:tags":[
        "telephone",
        "cellular"
    ],
    "wof:name":"Store",
    "wof:placetype":"venue"
},
  "geometry": {"coordinates":[-84.516392,39.107688],"type":"Point"}
}