{
  "type": "Feature",
  "properties": {
    "addr:full":"2576 Berk St Cuyahoga Falls OH 44221",
    "addr:housenumber":"2576",
    "addr:postcode":"44221",
    "addr:street":"Berk St",
    "iso:country":"US",
    "sg:address":"2576 Berk St",
    "sg:city":"Cuyahoga Falls",
    "sg:classifiers":[
        {
            "category":"Shopping",
            "subcategory":"Gifts & Souvenirs",
            "type":"Retail Goods"
        }
    ],
    "sg:phone":"+1 330 928 2873",
    "sg:postcode":"44221",
    "sg:province":"OH",
    "sg:tags":[
        "balloon",
        "artist"
    ],
    "sg:website":"www.mrballoon.net",
    "wof:name":"Mr Balloon",
    "wof:placetype":"venue"
},
  "geometry": {"coordinates":[-81.484652,41.143534],"type":"Point"}
}