{
  "type": "Feature",
  "properties": {
    "addr:full": "370 State Rte 568 Carey OH 43316",
    "addr:housenumber": "370",
    "addr:postcode": "43316",
    "addr:street": "State Rte 568",
    "iso:country": "US",
    "sg:address": "370 State Rte 568",
    "sg:city": "Carey",
    "sg:classifiers": [
      {
        "category": "Organizations",
        "subcategory": "Religious Organization",
        "type": "Services"
      }
    ],
    "sg:phone": "+1 419 387 7227",
    "sg:postcode": "43316",
    "sg:province": "OH",
    "sg:tags": [
      "church"
    ],
    "wof:name": "Ridge Chapel Church-Nazarene",
    "wof:placetype": "venue"
  },
  "geometry": {"coordinates":[-83.387037,40.953356],"type":"Point"}
}
