{
  "type": "Feature",
  "properties": {
    "addr:full":"4081 State Rte 43 Kent OH 44240",
    "addr:housenumber":"4081",
    "addr:postcode":"44240",
    "addr:street":"State Rte 43",
    "iso:country":"US",
    "sg:address":"4081 State Rte 43",
    "sg:city":"Kent",
    "sg:classifiers":[
        {
            "category":"Restaurant",
            "type":"Food & Drink"
        }
    ],
    "sg:phone":"+1 330 678 5005",
    "sg:postcode":"44240",
    "sg:province":"OH",
    "sg:tags":[
        "pizzeria",
        "pizza"
    ],
    "sg:website":"www.gioninos.com",
    "wof:name":"Gionninos Pizzeria",
    "wof:placetype":"venue"
},
  "geometry": {"coordinates":[-81.346321,41.097599],"type":"Point"}
}