{
  "type": "Feature",
  "properties": {
    "addr:full":"58 Forest Ave Cincinnati OH 45215",
    "addr:housenumber":"58",
    "addr:postcode":"45215",
    "addr:street":"Forest Ave",
    "iso:country":"US",
    "sg:address":"58 Forest Ave",
    "sg:city":"Cincinnati",
    "sg:classifiers":[
        {
            "category":"Wholesale",
            "subcategory":"Auto Parts",
            "type":"Manufacturing & Wholesale Goods"
        }
    ],
    "sg:phone":"+1 513 761 3577",
    "sg:postcode":"45215",
    "sg:province":"OH",
    "sg:tags":[
        "automotive",
        "supply"
    ],
    "wof:name":"Auto RAD Supply Co Inc",
    "wof:placetype":"venue"
},
  "geometry": {"coordinates":[-84.473569,39.236249],"type":"Point"}
}