{
  "type": "Feature",
  "properties": {
    "addr:full": "4443 Westview Dr Copley OH 44321",
    "addr:housenumber": "4443",
    "addr:postcode": "44321",
    "addr:street": "Westview Dr",
    "iso:country": "US",
    "sg:address": "4443 Westview Dr",
    "sg:city": "Copley",
    "sg:classifiers": [
      {
        "category": "Insurance",
        "subcategory": "Insurance Agent",
        "type": "Services"
      }
    ],
    "sg:phone": "+1 330 666 5551",
    "sg:postcode": "44321",
    "sg:province": "OH",
    "wof:name": "A J Gurbis \u0026 Assoc Inc",
    "wof:placetype": "venue"
  },
  "geometry": {"coordinates":[-81.66975,41.124329],"type":"Point"}
}
