{
  "type": "Feature",
  "properties": {
    "addr:full": "318 Dorney Plz Findlay OH 45840",
    "addr:housenumber": "318",
    "addr:postcode": "45840",
    "addr:street": "Dorney Plz",
    "iso:country": "US",
    "sg:address": "318 Dorney Plz",
    "sg:city": "Findlay",
    "sg:classifiers": [
      {
        "category": "Government",
        "subcategory": "Office",
        "type": "Public Place"
      }
    ],
    "sg:phone": "+1 419 424 7101",
    "sg:postcode": "45840",
    "sg:province": "OH",
    "sg:tags": [
      "city",
      "taxation"
    ],
    "wof:name": "Findlay Auditors Office",
    "wof:placetype": "venue"
  },
  "geometry": {"coordinates":[-83.651244,41.039082],"type":"Point"}
}
