{
  "type": "Feature",
  "properties": {
    "addr:full":"58 W 3rd St Mansfield OH 44902",
    "addr:housenumber":"58",
    "addr:postcode":"44902",
    "addr:street":"W 3Rd St",
    "iso:country":"US",
    "sg:address":"58 W 3rd St",
    "sg:city":"Mansfield",
    "sg:classifiers":[
        {
            "category":"Real Estate",
            "subcategory":"Real Estate Services",
            "type":"Services"
        }
    ],
    "sg:phone":"+1 419 525 4600",
    "sg:postcode":"44902",
    "sg:province":"OH",
    "sg:tags":[
        "company",
        "title"
    ],
    "sg:website":"www.southerntitle.com",
    "wof:name":"Southern Title",
    "wof:placetype":"venue"
},
  "geometry": {"coordinates":[-82.517038,40.75993],"type":"Point"}
}