{
  "type": "Feature",
  "properties": {
    "addr:full": "2106 Troy Pike Dayton OH 45404",
    "addr:housenumber": "2106",
    "addr:postcode": "45404",
    "addr:street": "Troy Pike",
    "iso:country": "US",
    "sg:address": "2106 Troy Pike",
    "sg:city": "Dayton",
    "sg:classifiers": [
      {
        "category": "Home \u0026 Garden",
        "subcategory": "Furniture",
        "type": "Retail Goods"
      }
    ],
    "sg:phone": "+1 937 237 5015",
    "sg:postcode": "45404",
    "sg:province": "OH",
    "sg:tags": [
      "business",
      "merchandise"
    ],
    "wof:name": "Turpin Auction",
    "wof:placetype": "venue"
  },
  "geometry": {"coordinates":[-84.163823,39.793291],"type":"Point"}
}
