{
  "type": "Feature",
  "properties": {
    "addr:full": "7449 State Rte 219 New Knoxville OH 45871",
    "addr:housenumber": "7449",
    "addr:postcode": "45871",
    "addr:street": "State Rte 219",
    "iso:country": "US",
    "sg:address": "7449 State Rte 219",
    "sg:city": "New Knoxville",
    "sg:classifiers": [
      {
        "category": "Building \u0026 Trades",
        "subcategory": "Landscaping Services",
        "type": "Services"
      }
    ],
    "sg:phone": "+1 419 753 3256",
    "sg:postcode": "45871",
    "sg:province": "OH",
    "sg:tags": [
      "landscape",
      "contractor"
    ],
    "wof:name": "Penn Landscaping \u0026 Design",
    "wof:placetype": "venue"
  },
  "geometry": {"coordinates":[-84.307225,40.496067],"type":"Point"}
}
