{
  "type": "Feature",
  "properties": {
    "iso:country":"US",
    "sg:address":"131 Whieldon Ln",
    "sg:city":"Worthington",
    "sg:classifiers":[
        {
            "category":"Personal",
            "type":"Services"
        }
    ],
    "sg:phone":"+1 614 846 3449",
    "sg:postcode":"43085",
    "sg:province":"OH",
    "sg:tags":[
        "miscellaneous"
    ],
    "wof:name":"Premier Concierge",
    "wof:placetype":"venue"
},
  "geometry": {"coordinates":[-83.040872,40.094815],"type":"Point"}
}