{
  "type": "Feature",
  "properties": {
    "iso:country":"US",
    "sg:address":"4934 Everhard Rd NW",
    "sg:city":"Canton",
    "sg:classifiers":[
        {
            "category":"Professional",
            "subcategory":"Business Services",
            "type":"Services"
        }
    ],
    "sg:phone":"+1 330 498 0653",
    "sg:postcode":"44718",
    "sg:province":"OH",
    "sg:tags":[
        "packaging"
    ],
    "wof:name":"Shipping Connection",
    "wof:placetype":"venue"
},
  "geometry": {"coordinates":[-81.440437,40.851665],"type":"Point"}
}