{
  "type": "Feature",
  "properties": {
    "addr:full":"5635 Deerfield Cir Mason OH 45040",
    "addr:housenumber":"5635",
    "addr:postcode":"45040",
    "addr:street":"Deerfield Cir",
    "iso:country":"US",
    "sg:address":"5635 Deerfield Cir",
    "sg:city":"Mason",
    "sg:classifiers":[
        {
            "category":"Shopping",
            "subcategory":"Hobbies, Toys, & Games",
            "type":"Retail Goods"
        }
    ],
    "sg:phone":"+1 513 754 1930",
    "sg:postcode":"45040",
    "sg:province":"OH",
    "sg:tags":[
        "equipment",
        "video",
        "rental"
    ],
    "wof:name":"E:b Games",
    "wof:placetype":"venue"
},
  "geometry": {"coordinates":[-84.318895,39.350477],"type":"Point"}
}