{
  "type": "Feature",
  "properties": {
    "iso:country":"US",
    "sg:address":"4394 Eastgate Square Dr",
    "sg:city":"Cincinnati",
    "sg:classifiers":[
        {
            "category":"Shopping",
            "subcategory":"Beauty & Cosmetics",
            "type":"Retail Goods"
        },
        {
            "category":"Shopping",
            "subcategory":"Clothing, Apparel, & Fashions",
            "type":"Retail Goods"
        }
    ],
    "sg:phone":"+1 513 943 7422",
    "sg:postcode":"45245",
    "sg:province":"OH",
    "sg:tags":[
        "hair",
        "equipment",
        "supply"
    ],
    "wof:name":"Sally Beauty Supply",
    "wof:placetype":"venue"
},
  "geometry": {"coordinates":[-84.268761,39.095251],"type":"Point"}
}