{
  "type": "Feature",
  "properties": {
    "addr:full":"11335 Yawberg Rd Grand Rapids OH 43522",
    "addr:housenumber":"11335",
    "addr:postcode":"43522",
    "addr:street":"Yawberg Rd",
    "iso:country":"US",
    "sg:address":"11335 Yawberg Rd",
    "sg:city":"Grand Rapids",
    "sg:phone":"+1 419 832 3884",
    "sg:postcode":"43522",
    "sg:province":"OH",
    "sg:tags":[
        "farm",
        "corn",
        "soybean"
    ],
    "wof:name":"Lowell Fitch",
    "wof:placetype":"venue"
},
  "geometry": {"coordinates":[-83.844399,41.43433],"type":"Point"}
}