{
  "type": "Feature",
  "properties": {
    "iso:country":"US",
    "sg:address":"860 Ansonia St",
    "sg:city":"Oregon",
    "sg:classifiers":[
        {
            "category":"Professional",
            "subcategory":"Accounting & Tax Preparation",
            "type":"Services"
        }
    ],
    "sg:phone":"+1 419 693 2693",
    "sg:postcode":"43616",
    "sg:province":"OH",
    "sg:tags":[
        "accountant"
    ],
    "sg:website":"www.tskbi.com",
    "wof:name":"Tucker Stein Kissling Bueltel",
    "wof:placetype":"venue"
},
  "geometry": {"coordinates":[-83.48783299999999,41.634372],"type":"Point"}
}