{
  "type": "Feature",
  "properties": {
    "addr:full": "38520 Crimm Rd Scio OH 43988",
    "addr:postcode": "38520;43988",
    "addr:street": "Crimm Rd",
    "iso:country": "US",
    "sg:address": "38520 Crimm Rd",
    "sg:city": "Scio",
    "sg:classifiers": [
      {
        "category": "Manufacturing",
        "subcategory": "Pottery",
        "type": "Manufacturing \u0026 Wholesale Goods"
      }
    ],
    "sg:phone": "+1 740 945 3111",
    "sg:postcode": "43988",
    "sg:province": "OH",
    "sg:tags": [
      "product"
    ],
    "wof:name": "Scio Pottery Assoc",
    "wof:placetype": "venue"
  },
  "geometry": {"coordinates":[-81.095896,40.396772],"type":"Point"}
}
