{
  "type": "Feature",
  "properties": {
    "iso:country":"US",
    "sg:address":"13673 Beaver Springfield Rd",
    "sg:city":"New Springfield",
    "sg:classifiers":[
        {
            "category":"Travel",
            "subcategory":"Travel Agent",
            "type":"Entertainment"
        }
    ],
    "sg:phone":"+1 330 549 9281",
    "sg:postcode":"44443",
    "sg:province":"OH",
    "sg:tags":[
        "agency",
        "bureau"
    ],
    "wof:name":"Cruise Planners",
    "wof:placetype":"venue"
},
  "geometry": {"coordinates":[-80.63175,40.919134],"type":"Point"}
}