{
  "type": "Feature",
  "properties": {
    "iso:country":"US",
    "sg:address":"5010 Hudson Dr",
    "sg:city":"Stow",
    "sg:classifiers":[
        {
            "category":"Manufacturing",
            "subcategory":"Metals",
            "type":"Manufacturing & Wholesale Goods"
        }
    ],
    "sg:phone":"+1 330 688 5617",
    "sg:postcode":"44224",
    "sg:province":"OH",
    "sg:tags":[
        "steel",
        "industrial",
        "fabrication"
    ],
    "sg:website":"www.wrayco.com",
    "wof:name":"Wrayco Industries Inc",
    "wof:placetype":"venue"
},
  "geometry": {"coordinates":[-81.455877,41.20034],"type":"Point"}
}