{
  "type": "Feature",
  "properties": {
    "iso:country":"US",
    "sg:address":"36170 Sugar Ridge Rd",
    "sg:city":"North Ridgeville",
    "sg:classifiers":[
        {
            "category":"Building & Trades",
            "subcategory":"Construction",
            "type":"Services"
        }
    ],
    "sg:phone":"+1 440 353 9702",
    "sg:postcode":"44039",
    "sg:province":"OH",
    "sg:tags":[
        "house"
    ],
    "wof:name":"Knight Builders",
    "wof:placetype":"venue"
},
  "geometry": {"coordinates":[-82.03134,41.374331],"type":"Point"}
}