{
  "type": "Feature",
  "properties": {
    "addr:full": "3555 Chantilly St Columbus OH 43207",
    "addr:housenumber": "3555",
    "addr:postcode": "43207",
    "addr:street": "Chantilly St",
    "iso:country": "US",
    "sg:address": "3555 Chantilly St",
    "sg:city": "Columbus",
    "sg:classifiers": [
      {
        "category": "Building \u0026 Trades",
        "subcategory": "Construction",
        "type": "Services"
      }
    ],
    "sg:phone": "+1 614 491 1905",
    "sg:postcode": "43207",
    "sg:province": "OH",
    "sg:tags": [
      "house",
      "remodeling",
      "family",
      "contractor"
    ],
    "wof:name": "Mid-Ohio Construction",
    "wof:placetype": "venue"
  },
  "geometry": {"coordinates":[-82.925049,39.897461],"type":"Point"}
}
