{
  "type": "Feature",
  "properties": {
    "iso:country":"US",
    "sg:address":"11700 Princeton Pike",
    "sg:city":"Cincinnati",
    "sg:classifiers":[
        {
            "category":"Shopping",
            "subcategory":"Gifts & Souvenirs",
            "type":"Retail Goods"
        }
    ],
    "sg:phone":"+1 513 671 2970",
    "sg:postcode":"45246",
    "sg:province":"OH",
    "sg:tags":[
        "shop"
    ],
    "wof:name":"Home Sweet Home",
    "wof:placetype":"venue"
},
  "geometry": {"coordinates":[-84.466252,39.294854],"type":"Point"}
}