{
  "type": "Feature",
  "properties": {
    "addr:full": "1788 Vizedom Rd Hamilton OH 45013",
    "addr:housenumber": "1788",
    "addr:postcode": "45013",
    "addr:street": "Vizedom Rd",
    "iso:country": "US",
    "sg:address": "1788 Vizedom Rd",
    "sg:city": "Hamilton",
    "sg:classifiers": [
      {
        "category": "Building \u0026 Trades",
        "subcategory": "Construction",
        "type": "Services"
      }
    ],
    "sg:phone": "+1 513 867 8857",
    "sg:postcode": "45013",
    "sg:province": "OH",
    "sg:tags": [
      "masonry",
      "contractor"
    ],
    "wof:name": "Reliable Masonry",
    "wof:placetype": "venue"
  },
  "geometry": {"coordinates":[-84.61854,39.435348],"type":"Point"}
}
