{
  "type": "Feature",
  "properties": {
    "addr:full":"5144 US Rte 35 W Eaton OH 45320",
    "addr:housenumber":"5144",
    "addr:postcode":"45320",
    "addr:street":"Us Rte 35 W",
    "iso:country":"US",
    "sg:address":"5144 US Rte 35 W",
    "sg:city":"Eaton",
    "sg:classifiers":[
        {
            "category":"Personal",
            "subcategory":"Beauty Salon",
            "type":"Services"
        },
        {
            "category":"Shopping",
            "subcategory":"Clothing, Apparel, & Fashions",
            "type":"Retail Goods"
        }
    ],
    "sg:phone":"+1 937 456 9900",
    "sg:postcode":"45320",
    "sg:province":"OH",
    "sg:tags":[
        "shop"
    ],
    "wof:name":"West Winds Beauty & Barber Sal",
    "wof:placetype":"venue"
},
  "geometry": {"coordinates":[-84.709689,39.789877],"type":"Point"}
}