{
  "type": "Feature",
  "properties": {
    "addr:full":"4798 Ridge Rd Cleveland OH 44144",
    "addr:housenumber":"4798",
    "addr:postcode":"44144",
    "addr:street":"Ridge Rd",
    "iso:country":"US",
    "sg:address":"4798 Ridge Rd",
    "sg:city":"Cleveland",
    "sg:classifiers":[
        {
            "category":"Food & Beverages",
            "subcategory":"Groceries & Convenience Stores",
            "type":"Retail Goods"
        }
    ],
    "sg:phone":"+1 216 398 7222",
    "sg:postcode":"44144",
    "sg:province":"OH",
    "sg:tags":[
        "grocer"
    ],
    "wof:name":"Tops Friendly Market",
    "wof:placetype":"venue"
},
  "geometry": {"coordinates":[-81.73442799999999,41.421221],"type":"Point"}
}