{
  "type": "Feature",
  "properties": {
    "iso:country":"US",
    "sg:address":"8851 Portage St NW",
    "sg:city":"Massillon",
    "sg:classifiers":[
        {
            "category":"Building & Trades",
            "subcategory":"Construction",
            "type":"Services"
        }
    ],
    "sg:phone":"+1 330 323 3667",
    "sg:postcode":"44646",
    "sg:province":"OH",
    "sg:tags":[
        "excavation",
        "contractor"
    ],
    "wof:name":"Groundsource Excavating Inc",
    "wof:placetype":"venue"
},
  "geometry": {"coordinates":[-81.51785599999999,40.880146],"type":"Point"}
}