{
  "type": "Feature",
  "properties": {
    "addr:full": "8851 Portage St NW Massillon OH 44646",
    "addr:housenumber": "8851",
    "addr:postcode": "44646",
    "addr:street": "Portage St Nw",
    "iso:country": "US",
    "sg:address": "8851 Portage St NW",
    "sg:city": "Massillon",
    "sg:classifiers": [
      {
        "category": "Building \u0026 Trades",
        "subcategory": "Construction",
        "type": "Services"
      }
    ],
    "sg:phone": "+1 330 323 3667",
    "sg:postcode": "44646",
    "sg:province": "OH",
    "sg:tags": [
      "excavation",
      "contractor"
    ],
    "wof:name": "Groundsource Excavating Inc",
    "wof:placetype": "venue"
  },
  "geometry": {"coordinates":[-81.517856,40.880146],"type":"Point"}
}
