{
  "type": "Feature",
  "properties": {
    "iso:country":"US",
    "sg:address":"3015 Saddlebrook",
    "sg:city":"Findlay",
    "sg:classifiers":[
        {
            "category":"Manufacturing",
            "subcategory":"Rubber & Plastics",
            "type":"Manufacturing & Wholesale Goods"
        }
    ],
    "sg:phone":"+1 419 427 1941",
    "sg:postcode":"45840",
    "sg:province":"OH",
    "sg:tags":[
        "product",
        "mfg"
    ],
    "wof:name":"Emerald Marketing",
    "wof:placetype":"venue"
},
  "geometry": {"coordinates":[-83.674604,41.075287],"type":"Point"}
}