{
  "type": "Feature",
  "properties": {
    "addr:full": "3015 Saddlebrook Findlay OH 45840",
    "addr:housenumber": "3015",
    "addr:postcode": "45840",
    "addr:street": "Saddlebrook",
    "iso:country": "US",
    "sg:address": "3015 Saddlebrook",
    "sg:city": "Findlay",
    "sg:classifiers": [
      {
        "category": "Manufacturing",
        "subcategory": "Rubber \u0026 Plastics",
        "type": "Manufacturing \u0026 Wholesale Goods"
      }
    ],
    "sg:phone": "+1 419 427 1941",
    "sg:postcode": "45840",
    "sg:province": "OH",
    "sg:tags": [
      "product",
      "mfg"
    ],
    "wof:name": "Emerald Marketing",
    "wof:placetype": "venue"
  },
  "geometry": {"coordinates":[-83.674604,41.075287],"type":"Point"}
}
