{
  "type": "Feature",
  "properties": {
    "addr:full": "608 Main St Cincinnati OH 45202",
    "addr:housenumber": "608",
    "addr:postcode": "45202",
    "addr:street": "Main St",
    "iso:country": "US",
    "sg:address": "608 Main St",
    "sg:city": "Cincinnati",
    "sg:classifiers": [
      {
        "category": "Shopping",
        "subcategory": "Luggage \u0026 Leather Goods",
        "type": "Retail Goods"
      }
    ],
    "sg:phone": "+1 513 723 0887",
    "sg:postcode": "45202",
    "sg:province": "OH",
    "wof:name": "Rans Shoe Repair",
    "wof:placetype": "venue"
  },
  "geometry": {"coordinates":[-84.510163,39.103472],"type":"Point"}
}
