{
  "type": "Feature",
  "properties": {
    "addr:full":"4323 Main Ave Ashtabula OH 44004",
    "addr:housenumber":"4323",
    "addr:postcode":"44004",
    "addr:street":"Main Ave",
    "iso:country":"US",
    "sg:address":"4323 Main Ave",
    "sg:city":"Ashtabula",
    "sg:classifiers":[
        {
            "category":"Autos & Motor Vehicles",
            "subcategory":"Auto Supplies",
            "type":"Retail Goods"
        }
    ],
    "sg:phone":"+1 440 993 8566",
    "sg:postcode":"44004",
    "sg:province":"OH",
    "sg:tags":[
        "tire"
    ],
    "wof:name":"Firestone Tire & Auto Ctr",
    "wof:placetype":"venue"
},
  "geometry": {"coordinates":[-80.781267,41.868255],"type":"Point"}
}