{
  "type": "Feature",
  "properties": {
    "iso:country":"US",
    "sg:address":"41 N Main St",
    "sg:city":"Germantown",
    "sg:classifiers":[
        {
            "category":"Real Estate",
            "subcategory":"Real Estate Agent",
            "type":"Services"
        }
    ],
    "sg:phone":"+1 937 855 3471",
    "sg:postcode":"45327",
    "sg:province":"OH",
    "wof:name":"Solutions Plus",
    "wof:placetype":"venue"
},
  "geometry": {"coordinates":[-84.37056800000001,39.625575],"type":"Point"}
}