{
  "type": "Feature",
  "properties": {
    "addr:full": "41 N Main St Germantown OH 45327",
    "addr:housenumber": "41",
    "addr:postcode": "45327",
    "addr:street": "N Main St",
    "iso:country": "US",
    "sg:address": "41 N Main St",
    "sg:city": "Germantown",
    "sg:classifiers": [
      {
        "category": "Real Estate",
        "subcategory": "Real Estate Agent",
        "type": "Services"
      }
    ],
    "sg:phone": "+1 937 855 3471",
    "sg:postcode": "45327",
    "sg:province": "OH",
    "wof:name": "Solutions Plus",
    "wof:placetype": "venue"
  },
  "geometry": {"coordinates":[-84.370568,39.625575],"type":"Point"}
}
