{
  "type": "Feature",
  "properties": {
    "iso:country":"US",
    "sg:address":"2215 E Waterloo Rd",
    "sg:city":"Akron",
    "sg:classifiers":[
        {
            "category":"Home & Garden",
            "subcategory":"Carpets & Floor Coverings",
            "type":"Retail Goods"
        }
    ],
    "sg:phone":"+1 330 784 6409",
    "sg:postcode":"44312",
    "sg:province":"OH",
    "sg:tags":[
        "dealer",
        "rug"
    ],
    "wof:name":"Carpet Gallery Of Akron",
    "wof:placetype":"venue"
},
  "geometry": {"coordinates":[-81.447364,41.034621],"type":"Point"}
}