{
  "type": "Feature",
  "properties": {
    "addr:full": "14993 Pearl Rd Cleveland OH 44136",
    "addr:housenumber": "14993",
    "addr:postcode": "44136",
    "addr:street": "Pearl Rd",
    "iso:country": "US",
    "sg:address": "14993 Pearl Rd",
    "sg:city": "Cleveland",
    "sg:classifiers": [
      {
        "category": "Restaurant",
        "type": "Food \u0026 Drink"
      }
    ],
    "sg:phone": "+1 440 846 0588",
    "sg:postcode": "44136",
    "sg:province": "OH",
    "sg:tags": [
      "shop",
      "coffee",
      "eating"
    ],
    "wof:name": "Cupachino \u0026 Cones Cafe",
    "wof:placetype": "venue"
  },
  "geometry": {"coordinates":[-81.835146,41.307591],"type":"Point"}
}
