{
  "type": "Feature",
  "properties": {
    "addr:full": "562 Congress Park Dr Dayton OH 45459",
    "addr:housenumber": "562",
    "addr:postcode": "45459",
    "addr:street": "Congress Park Dr",
    "iso:country": "US",
    "sg:address": "562 Congress Park Dr",
    "sg:city": "Dayton",
    "sg:classifiers": [
      {
        "category": "Manufacturing",
        "subcategory": "Printing",
        "type": "Manufacturing \u0026 Wholesale Goods"
      }
    ],
    "sg:phone": "+1 937 435 1113",
    "sg:postcode": "45459",
    "sg:province": "OH",
    "sg:tags": [
      "publisher"
    ],
    "wof:name": "Ohio Head Start Assn Inc",
    "wof:placetype": "venue"
  },
  "geometry": {"coordinates":[-84.176335,39.630661],"type":"Point"}
}
