{
  "type": "Feature",
  "properties": {
    "addr:full":"7850 Mentor Ave Mentor OH 44060",
    "addr:housenumber":"7850",
    "addr:postcode":"44060",
    "addr:street":"Mentor Ave",
    "iso:country":"US",
    "sg:address":"7850 Mentor Ave",
    "sg:city":"Mentor",
    "sg:classifiers":[
        {
            "category":"Shopping",
            "subcategory":"Jewelry",
            "type":"Retail Goods"
        }
    ],
    "sg:phone":"+1 440 951 3820",
    "sg:postcode":"44060",
    "sg:province":"OH",
    "sg:tags":[
        "jeweler"
    ],
    "wof:name":"Marlo's Jewelers",
    "wof:placetype":"venue"
},
  "geometry": {"coordinates":[-81.362095,41.660627],"type":"Point"}
}