{
  "type": "Feature",
  "properties": {
    "addr:full":"11830 Brookpark Rd Cleveland OH 44130",
    "addr:housenumber":"11830",
    "addr:postcode":"44130",
    "addr:street":"Brookpark Rd",
    "iso:country":"US",
    "sg:address":"11830 Brookpark Rd",
    "sg:city":"Cleveland",
    "sg:classifiers":[
        {
            "category":"Manufacturing",
            "subcategory":"Tools & Machinery",
            "type":"Manufacturing & Wholesale Goods"
        }
    ],
    "sg:phone":"+1 216 267 9861",
    "sg:postcode":"44130",
    "sg:province":"OH",
    "sg:tags":[
        "die",
        "maker"
    ],
    "sg:website":"www.anchor-mfg.com",
    "wof:name":"Anchor Tool & Die Co",
    "wof:placetype":"venue"
},
  "geometry": {"coordinates":[-81.769137,41.418331],"type":"Point"}
}