{
  "type": "Feature",
  "properties": {
    "addr:full":"5045 Kemary Ave SW Navarre OH 44662",
    "addr:housenumber":"5045",
    "addr:postcode":"44662",
    "addr:street":"Kemary Ave Sw",
    "iso:country":"US",
    "sg:address":"5045 Kemary Ave SW",
    "sg:city":"Navarre",
    "sg:phone":"+1 330 832 4069",
    "sg:postcode":"44662",
    "sg:province":"OH",
    "sg:tags":[
        "farm",
        "field",
        "corn",
        "crop"
    ],
    "wof:name":"Donald Snyder",
    "wof:placetype":"venue"
},
  "geometry": {"coordinates":[-81.478848,40.731193],"type":"Point"}
}