{
  "type": "Feature",
  "properties": {
    "iso:country":"US",
    "sg:address":"7030 Reading Rd",
    "sg:city":"Cincinnati",
    "sg:classifiers":[
        {
            "category":"Shopping",
            "subcategory":"Clothing, Apparel, & Fashions",
            "type":"Retail Goods"
        }
    ],
    "sg:phone":"+1 513 731 0244",
    "sg:postcode":"45237",
    "sg:province":"OH",
    "sg:tags":[
        "furnishing"
    ],
    "wof:name":"Deveroes",
    "wof:placetype":"venue"
},
  "geometry": {"coordinates":[-84.46402,39.188198],"type":"Point"}
}