{
  "type": "Feature",
  "properties": {
    "addr:full": "5913 Hoover Rd Grove City OH 43123",
    "addr:housenumber": "5913",
    "addr:postcode": "43123",
    "addr:street": "Hoover Rd",
    "iso:country": "US",
    "sg:address": "5913 Hoover Rd",
    "sg:city": "Grove City",
    "sg:classifiers": [
      {
        "category": "Restaurant",
        "type": "Food \u0026 Drink"
      }
    ],
    "sg:phone": "+1 614 875 8525",
    "sg:postcode": "43123",
    "sg:province": "OH",
    "sg:tags": [
      "eating",
      "pizza"
    ],
    "wof:name": "Tammy's Pizza",
    "wof:placetype": "venue"
  },
  "geometry": {"coordinates":[-83.072878,39.841712],"type":"Point"}
}
