{
  "type": "Feature",
  "properties": {
    "iso:country":"US",
    "sg:address":"3507 Granview Rd",
    "sg:city":"Granville",
    "sg:classifiers":[
        {
            "category":"Recreation",
            "type":"Entertainment"
        }
    ],
    "sg:phone":"+1 740 587 2356",
    "sg:postcode":"43023",
    "sg:province":"OH",
    "sg:tags":[
        "stable"
    ],
    "wof:name":"Grenoble Stables",
    "wof:placetype":"venue"
},
  "geometry": {"coordinates":[-82.543401,40.037704],"type":"Point"}
}