{
  "type": "Feature",
  "properties": {
    "addr:full": "2054 Miamisburg Centerville Rd Dayton OH 45459",
    "addr:housenumber": "2054",
    "addr:postcode": "45459",
    "addr:street": "Miamisburg Centerville Rd",
    "iso:country": "US",
    "sg:address": "2054 Miamisburg Centerville Rd",
    "sg:city": "Dayton",
    "sg:classifiers": [
      {
        "category": "Shopping",
        "subcategory": "Computers \u0026 Home Electronics",
        "type": "Retail Goods"
      }
    ],
    "sg:phone": "+1 937 434 7900",
    "sg:postcode": "45459",
    "sg:province": "OH",
    "sg:tags": [
      "equipment",
      "dealer"
    ],
    "wof:name": "Computer Zoo",
    "wof:placetype": "venue"
  },
  "geometry": {"coordinates":[-84.206701,39.633734],"type":"Point"}
}
