{
  "type": "Feature",
  "properties": {
    "addr:full": "711 Winkler Dr Wooster OH 44691",
    "addr:housenumber": "711",
    "addr:postcode": "44691",
    "addr:street": "Winkler Dr",
    "iso:country": "US",
    "sg:address": "711 Winkler Dr",
    "sg:city": "Wooster",
    "sg:classifiers": [
      {
        "category": "Mining \u0026 Drilling",
        "type": "Manufacturing \u0026 Wholesale Goods"
      }
    ],
    "sg:phone": "+1 330 345 3172",
    "sg:postcode": "44691",
    "sg:province": "OH",
    "sg:tags": [
      "oil",
      "gas",
      "producer"
    ],
    "wof:name": "Oil \u0026 Gas Solutions LTD",
    "wof:placetype": "venue"
  },
  "geometry": {"coordinates":[-81.931813,40.835948],"type":"Point"}
}
