{
  "type": "Feature",
  "properties": {
    "iso:country":"US",
    "sg:address":"711 Winkler Dr",
    "sg:city":"Wooster",
    "sg:classifiers":[
        {
            "category":"Mining & Drilling",
            "type":"Manufacturing & Wholesale Goods"
        }
    ],
    "sg:phone":"+1 330 345 3172",
    "sg:postcode":"44691",
    "sg:province":"OH",
    "sg:tags":[
        "oil",
        "gas",
        "producer"
    ],
    "wof:name":"Oil & Gas Solutions LTD",
    "wof:placetype":"venue"
},
  "geometry": {"coordinates":[-81.931813,40.835948],"type":"Point"}
}