{
  "type": "Feature",
  "properties": {
    "addr:full": "724 S High St Columbus OH 43206",
    "addr:housenumber": "724",
    "addr:postcode": "43206",
    "addr:street": "S High St",
    "iso:country": "US",
    "sg:address": "724 S High St",
    "sg:city": "Columbus",
    "sg:classifiers": [
      {
        "category": "Shopping",
        "subcategory": "Clothing, Apparel, \u0026 Fashions",
        "type": "Retail Goods"
      }
    ],
    "sg:phone": "+1 614 445 6563",
    "sg:postcode": "43206",
    "sg:province": "OH",
    "sg:tags": [
      "tailor"
    ],
    "wof:name": "Alterations By Nina",
    "wof:placetype": "venue"
  },
  "geometry": {"coordinates":[-82.997709,39.947602],"type":"Point"}
}
