{
  "type": "Feature",
  "properties": {
    "addr:full":"4208 Newark Ave Cleveland OH 44109",
    "addr:housenumber":"4208",
    "addr:postcode":"44109",
    "addr:street":"Newark Ave",
    "iso:country":"US",
    "sg:address":"4208 Newark Ave",
    "sg:city":"Cleveland",
    "sg:classifiers":[
        {
            "category":"Health Services",
            "subcategory":"Nursing And Care Facility",
            "type":"Services"
        }
    ],
    "sg:phone":"+1 216 939 9186",
    "sg:postcode":"44109",
    "sg:province":"OH",
    "sg:tags":[
        "home",
        "convalescent"
    ],
    "wof:name":"Old Brooklyn Adult Care II",
    "wof:placetype":"venue"
},
  "geometry": {"coordinates":[-81.714482,41.467002],"type":"Point"}
}