{
  "type": "Feature",
  "properties": {
    "iso:country":"US",
    "sg:address":"6515 Saint Clair Ave",
    "sg:city":"Cleveland",
    "sg:classifiers":[
        {
            "category":"Manufacturing",
            "subcategory":"Tools & Machinery",
            "type":"Manufacturing & Wholesale Goods"
        }
    ],
    "sg:phone":"+1 216 431 5596",
    "sg:postcode":"44103",
    "sg:province":"OH",
    "sg:tags":[
        "die",
        "maker",
        "mfg"
    ],
    "wof:name":"Immba Tool & Die Corp",
    "wof:placetype":"venue"
},
  "geometry": {"coordinates":[-81.644639,41.525648],"type":"Point"}
}