{
  "type": "Feature",
  "properties": {
    "addr:full": "2208 Tedrow Rd Toledo OH 43614",
    "addr:housenumber": "2208",
    "addr:postcode": "43614",
    "addr:street": "Tedrow Rd",
    "iso:country": "US",
    "sg:address": "2208 Tedrow Rd",
    "sg:city": "Toledo",
    "sg:classifiers": [
      {
        "category": "Wholesale",
        "subcategory": "Non-durable Goods",
        "type": "Manufacturing \u0026 Wholesale Goods"
      }
    ],
    "sg:phone": "+1 419 380 0999",
    "sg:postcode": "43614",
    "sg:province": "OH",
    "sg:tags": [
      "packaging",
      "industrial",
      "material"
    ],
    "wof:name": "MDH Sales",
    "wof:placetype": "venue"
  },
  "geometry": {"coordinates":[-83.620405,41.598935],"type":"Point"}
}
