{
  "type": "Feature",
  "properties": {
    "addr:full": "1735 S University Blvd Middletown OH 45044",
    "addr:housenumber": "1735",
    "addr:postcode": "45044",
    "addr:street": "S University Blvd",
    "iso:country": "US",
    "sg:address": "1735 S University Blvd",
    "sg:city": "Middletown",
    "sg:classifiers": [
      {
        "category": "Organizations",
        "subcategory": "Religious Organization",
        "type": "Services"
      }
    ],
    "sg:phone": "+1 513 705 6472",
    "sg:postcode": "45044",
    "sg:province": "OH",
    "wof:name": "CCR Ministries",
    "wof:placetype": "venue"
  },
  "geometry": {"coordinates":[-84.396115,39.49541],"type":"Point"}
}
