{
  "type": "Feature",
  "properties": {
    "iso:country":"US",
    "sg:address":"1735 S University Blvd",
    "sg:city":"Middletown",
    "sg:classifiers":[
        {
            "category":"Organizations",
            "subcategory":"Religious Organization",
            "type":"Services"
        }
    ],
    "sg:phone":"+1 513 705 6472",
    "sg:postcode":"45044",
    "sg:province":"OH",
    "wof:name":"CCR Ministries",
    "wof:placetype":"venue"
},
  "geometry": {"coordinates":[-84.396115,39.49541],"type":"Point"}
}