{
  "type": "Feature",
  "properties": {
    "addr:full": "4752 Fields Ertel Rd Cincinnati OH 45249",
    "addr:housenumber": "4752",
    "addr:postcode": "45249",
    "addr:street": "Fields Ertel Rd",
    "iso:country": "US",
    "sg:address": "4752 Fields Ertel Rd",
    "sg:city": "Cincinnati",
    "sg:classifiers": [
      {
        "category": "Restaurant",
        "type": "Food \u0026 Drink"
      }
    ],
    "sg:phone": "+1 513 774 9666",
    "sg:postcode": "45249",
    "sg:province": "OH",
    "sg:tags": [
      "eating"
    ],
    "wof:name": "Hi Bombay",
    "wof:placetype": "venue"
  },
  "geometry": {"coordinates":[-84.309262,39.292478],"type":"Point"}
}
