{
  "type": "Feature",
  "properties": {
    "addr:full": "7370 Badenoch Dr Dublin OH 43017",
    "addr:postcode": "7370;43017",
    "addr:street": "Badenoch Dr",
    "iso:country": "US",
    "sg:address": "7370 Badenoch Dr",
    "sg:city": "Dublin",
    "sg:classifiers": [
      {
        "category": "Professional",
        "type": "Services"
      }
    ],
    "sg:phone": "+1 614 766 9426",
    "sg:postcode": "43017",
    "sg:province": "OH",
    "wof:name": "David W Holzer",
    "wof:placetype": "venue"
  },
  "geometry": {"coordinates":[-83.156303,40.16017],"type":"Point"}
}
