{
  "type": "Feature",
  "properties": {
    "iso:country":"US",
    "sg:address":"558 Wildindigo Run",
    "sg:city":"Westerville",
    "sg:classifiers":[
        {
            "category":"Banks & Credit Unions",
            "subcategory":"Financial Services",
            "type":"Services"
        }
    ],
    "sg:phone":"+1 614 784 5555",
    "sg:postcode":"43081",
    "sg:province":"OH",
    "sg:tags":[
        "investor"
    ],
    "wof:name":"Marathon Investments",
    "wof:placetype":"venue"
},
  "geometry": {"coordinates":[-83.002707,40.129966],"type":"Point"}
}