{
  "type": "Feature",
  "properties": {
    "addr:full": "558 Wildindigo Run Westerville OH 43081",
    "addr:housenumber": "558",
    "addr:postcode": "43081",
    "addr:street": "Wildindigo Run",
    "iso:country": "US",
    "sg:address": "558 Wildindigo Run",
    "sg:city": "Westerville",
    "sg:classifiers": [
      {
        "category": "Banks \u0026 Credit Unions",
        "subcategory": "Financial Services",
        "type": "Services"
      }
    ],
    "sg:phone": "+1 614 784 5555",
    "sg:postcode": "43081",
    "sg:province": "OH",
    "sg:tags": [
      "investor"
    ],
    "wof:name": "Marathon Investments",
    "wof:placetype": "venue"
  },
  "geometry": {"coordinates":[-83.002707,40.129966],"type":"Point"}
}
