{
  "type": "Feature",
  "properties": {
    "addr:full":"320 Caldwell St Piqua OH 45356",
    "addr:housenumber":"320",
    "addr:postcode":"45356",
    "addr:street":"Caldwell St",
    "iso:country":"US",
    "sg:address":"320 Caldwell St",
    "sg:city":"Piqua",
    "sg:classifiers":[
        {
            "category":"Organizations",
            "subcategory":"Religious Organization",
            "type":"Services"
        }
    ],
    "sg:phone":"+1 937 773 6351",
    "sg:postcode":"45356",
    "sg:province":"OH",
    "sg:tags":[
        "synagogue"
    ],
    "wof:name":"Anshe Emethodist Temple",
    "wof:placetype":"venue"
},
  "geometry": {"coordinates":[-84.243934,40.149438],"type":"Point"}
}