{
  "type": "Feature",
  "properties": {
    "addr:full": "201 N Buckeye St Wooster OH 44691",
    "addr:housenumber": "201",
    "addr:postcode": "44691",
    "addr:street": "N Buckeye St",
    "iso:country": "US",
    "sg:address": "201 N Buckeye St",
    "sg:city": "Wooster",
    "sg:classifiers": [
      {
        "category": "Manufacturing",
        "subcategory": "Printing",
        "type": "Manufacturing \u0026 Wholesale Goods"
      }
    ],
    "sg:phone": "+1 330 264 2223",
    "sg:postcode": "44691",
    "sg:province": "OH",
    "sg:tags": [
      "commercial"
    ],
    "sg:website": "www.murrprinting.com",
    "wof:name": "Murr's Printing",
    "wof:placetype": "venue"
  },
  "geometry": {"coordinates":[-81.938754,40.800249],"type":"Point"}
}
