{
  "type": "Feature",
  "properties": {
    "addr:full": "301 S Main St Munroe Falls OH 44262",
    "addr:housenumber": "301",
    "addr:postcode": "44262",
    "addr:street": "S Main St",
    "iso:country": "US",
    "sg:address": "301 S Main St",
    "sg:city": "Munroe Falls",
    "sg:classifiers": [
      {
        "category": "Wholesale",
        "subcategory": "Fruits \u0026 Vegetables",
        "type": "Manufacturing \u0026 Wholesale Goods"
      }
    ],
    "sg:phone": "+1 330 630 9801",
    "sg:postcode": "44262",
    "sg:province": "OH",
    "sg:tags": [
      "produce"
    ],
    "wof:name": "Roetzel S J \u0026 Son Produce",
    "wof:placetype": "venue"
  },
  "geometry": {"coordinates":[-81.440041,41.12782],"type":"Point"}
}
