{
  "type": "Feature",
  "properties": {
    "iso:country":"US",
    "sg:address":"301 S Main St",
    "sg:city":"Munroe Falls",
    "sg:classifiers":[
        {
            "category":"Wholesale",
            "subcategory":"Fruits & Vegetables",
            "type":"Manufacturing & Wholesale Goods"
        }
    ],
    "sg:phone":"+1 330 630 9801",
    "sg:postcode":"44262",
    "sg:province":"OH",
    "sg:tags":[
        "produce"
    ],
    "wof:name":"Roetzel S J & Son Produce",
    "wof:placetype":"venue"
},
  "geometry": {"coordinates":[-81.44004099999999,41.12782],"type":"Point"}
}