{
  "type": "Feature",
  "properties": {
    "addr:full":"26608 Royalton Rd Columbia Station OH 44028",
    "addr:housenumber":"26608",
    "addr:postcode":"44028",
    "addr:street":"Royalton Rd",
    "iso:country":"US",
    "sg:address":"26608 Royalton Rd",
    "sg:city":"Columbia Station",
    "sg:classifiers":[
        {
            "category":"Wholesale",
            "subcategory":"Non-durable Goods",
            "type":"Manufacturing & Wholesale Goods"
        }
    ],
    "sg:phone":"+1 440 236 6443",
    "sg:postcode":"44028",
    "sg:province":"OH",
    "wof:name":"Confectionetly Yours",
    "wof:placetype":"venue"
},
  "geometry": {"coordinates":[-81.92928999999999,41.312852],"type":"Point"}
}