{
  "type": "Feature",
  "properties": {
    "addr:full":"1828 Harrisburg Pike Grove City OH 43123",
    "addr:housenumber":"1828",
    "addr:postcode":"43123",
    "addr:street":"Harrisburg Pike",
    "iso:country":"US",
    "sg:address":"1828 Harrisburg Pike",
    "sg:city":"Grove City",
    "sg:classifiers":[
        {
            "category":"Autos & Motor Vehicles",
            "subcategory":"Automobile Sales",
            "type":"Retail Goods"
        }
    ],
    "sg:phone":"+1 614 274 2622",
    "sg:postcode":"43123",
    "sg:province":"OH",
    "sg:tags":[
        "car",
        "used",
        "dealer"
    ],
    "wof:name":"Estridge Westside Used Cars",
    "wof:placetype":"venue"
},
  "geometry": {"coordinates":[-83.06269500000001,39.919347],"type":"Point"}
}