{
  "type": "Feature",
  "properties": {
    "addr:full":"300 Dietz Rd NE Warren OH 44483",
    "addr:housenumber":"300",
    "addr:postcode":"44483",
    "addr:street":"Dietz Rd Ne",
    "iso:country":"US",
    "sg:address":"300 Dietz Rd NE",
    "sg:city":"Warren",
    "sg:classifiers":[
        {
            "category":"Wholesale",
            "subcategory":"Hardware",
            "type":"Manufacturing & Wholesale Goods"
        }
    ],
    "sg:phone":"+1 330 392 1551",
    "sg:postcode":"44483",
    "sg:province":"OH",
    "sg:tags":[
        "plumbing",
        "fixture",
        "supply"
    ],
    "wof:name":"Trumbull Industries",
    "wof:placetype":"venue"
},
  "geometry": {"coordinates":[-80.809072,41.257619],"type":"Point"}
}