{
  "type": "Feature",
  "properties": {
    "iso:country":"US",
    "sg:address":"10042 Simms Station Rd",
    "sg:city":"Dayton",
    "sg:classifiers":[
        {
            "category":"Shopping",
            "subcategory":"Hobbies, Toys, & Games",
            "type":"Retail Goods"
        }
    ],
    "sg:phone":"+1 937 885 6788",
    "sg:postcode":"45458",
    "sg:province":"OH",
    "sg:tags":[
        "craft"
    ],
    "wof:name":"Kathy Franks Arts & Crafts",
    "wof:placetype":"venue"
},
  "geometry": {"coordinates":[-84.144627,39.596329],"type":"Point"}
}