{
  "type": "Feature",
  "properties": {
    "addr:full": "10042 Simms Station Rd Dayton OH 45458",
    "addr:housenumber": "10042",
    "addr:postcode": "45458",
    "addr:street": "Simms Station Rd",
    "iso:country": "US",
    "sg:address": "10042 Simms Station Rd",
    "sg:city": "Dayton",
    "sg:classifiers": [
      {
        "category": "Shopping",
        "subcategory": "Hobbies, Toys, \u0026 Games",
        "type": "Retail Goods"
      }
    ],
    "sg:phone": "+1 937 885 6788",
    "sg:postcode": "45458",
    "sg:province": "OH",
    "sg:tags": [
      "craft"
    ],
    "wof:name": "Kathy Franks Arts \u0026 Crafts",
    "wof:placetype": "venue"
  },
  "geometry": {"coordinates":[-84.144627,39.596329],"type":"Point"}
}
