{
  "type": "Feature",
  "properties": {
    "iso:country":"US",
    "sg:address":"3077 Southwest Blvd",
    "sg:city":"Grove City",
    "sg:classifiers":[
        {
            "category":"Organizations",
            "subcategory":"Religious Organization",
            "type":"Services"
        }
    ],
    "sg:phone":"+1 614 871 3670",
    "sg:postcode":"43123",
    "sg:province":"OH",
    "wof:name":"L Ds Missionaries",
    "wof:placetype":"venue"
},
  "geometry": {"coordinates":[-83.085097,39.890545],"type":"Point"}
}