{
  "type": "Feature",
  "properties": {
    "iso:country":"US",
    "sg:address":"11 Glen Este Pl",
    "sg:city":"Cincinnati",
    "sg:classifiers":[
        {
            "category":"Organizations",
            "subcategory":"Religious Organization",
            "type":"Services"
        }
    ],
    "sg:phone":"+1 513 281 6025",
    "sg:postcode":"45217",
    "sg:province":"OH",
    "sg:tags":[
        "clergy"
    ],
    "wof:name":"Eugene Walker",
    "wof:placetype":"venue"
},
  "geometry": {"coordinates":[-84.505889,39.154814],"type":"Point"}
}