{
  "type": "Feature",
  "properties": {
    "iso:country":"US",
    "sg:address":"201 Eastbury Ave NE",
    "sg:city":"Canton",
    "sg:classifiers":[
        {
            "category":"Wholesale",
            "subcategory":"Poultry",
            "type":"Manufacturing & Wholesale Goods"
        }
    ],
    "sg:phone":"+1 330 494 3876",
    "sg:postcode":"44720",
    "sg:province":"OH",
    "wof:name":"Abcare Co",
    "wof:placetype":"venue"
},
  "geometry": {"coordinates":[-81.385357,40.876801],"type":"Point"}
}