{
  "type": "Feature",
  "properties": {
    "iso:country":"US",
    "sg:address":"6402 E Main St",
    "sg:city":"Reynoldsburg",
    "sg:classifiers":[
        {
            "category":"Professional",
            "subcategory":"Testing Lab",
            "type":"Services"
        }
    ],
    "sg:phone":"+1 614 501 6607",
    "sg:postcode":"43068",
    "sg:province":"OH",
    "sg:tags":[
        "laboratory"
    ],
    "wof:name":"Business Technology Cente",
    "wof:placetype":"venue"
},
  "geometry": {"coordinates":[-82.821063,39.955006],"type":"Point"}
}