{
  "type": "Feature",
  "properties": {
    "iso:country":"US",
    "sg:address":"415 Wellman Ave",
    "sg:city":"Girard",
    "sg:classifiers":[
        {
            "category":"Banks & Credit Unions",
            "subcategory":"Investment Brokerage",
            "type":"Services"
        }
    ],
    "sg:phone":"+1 330 719 2828",
    "sg:postcode":"44420",
    "sg:province":"OH",
    "sg:tags":[
        "advisory"
    ],
    "wof:name":"Smith Barney Investments",
    "wof:placetype":"venue"
},
  "geometry": {"coordinates":[-80.686408,41.158114],"type":"Point"}
}