{
  "type": "Feature",
  "properties": {
    "iso:country":"US",
    "sg:address":"1303 Huntly Dr",
    "sg:city":"Columbus",
    "sg:classifiers":[
        {
            "category":"Retail",
            "subcategory":"Portrait Studio",
            "type":"Services"
        }
    ],
    "sg:phone":"+1 614 868 6965",
    "sg:postcode":"43227",
    "sg:province":"OH",
    "sg:tags":[
        "photographer"
    ],
    "wof:name":"Reilly's Wedding Photography",
    "wof:placetype":"venue"
},
  "geometry": {"coordinates":[-82.87622,39.950629],"type":"Point"}
}