{
  "type": "Feature",
  "properties": {
    "iso:country":"US",
    "sg:address":"2835 Fowler Dr",
    "sg:city":"Willoughby",
    "sg:classifiers":[
        {
            "category":"Real Estate",
            "subcategory":"Real Estate Operator",
            "type":"Services"
        }
    ],
    "sg:phone":"+1 440 943 3264",
    "sg:postcode":"44094",
    "sg:province":"OH",
    "sg:tags":[
        "building",
        "nonresidential"
    ],
    "wof:name":"S & D Industrial Plaza",
    "wof:placetype":"venue"
},
  "geometry": {"coordinates":[-81.445472,41.584056],"type":"Point"}
}