{
  "type": "Feature",
  "properties": {
    "addr:full": "3272 Hermosa Dr Youngstown OH 44511",
    "addr:housenumber": "3272",
    "addr:postcode": "44511",
    "addr:street": "Hermosa Dr",
    "iso:country": "US",
    "sg:address": "3272 Hermosa Dr",
    "sg:city": "Youngstown",
    "sg:classifiers": [
      {
        "category": "Restaurant",
        "type": "Food \u0026 Drink"
      }
    ],
    "sg:phone": "+1 330 792 6056",
    "sg:postcode": "44511",
    "sg:province": "OH",
    "sg:tags": [
      "eating"
    ],
    "wof:name": "Valley Grille LLC",
    "wof:placetype": "venue"
  },
  "geometry": {"coordinates":[-80.692016,41.068445],"type":"Point"}
}
