{
  "type": "Feature",
  "properties": {
    "iso:country":"US",
    "sg:address":"315 Madison St",
    "sg:city":"Port Clinton",
    "sg:classifiers":[
        {
            "category":"Government",
            "subcategory":"Office",
            "type":"Public Place"
        }
    ],
    "sg:phone":"+1 419 734 6897",
    "sg:postcode":"43452",
    "sg:province":"OH",
    "wof:name":"Ottawa County Bldg & Grounds",
    "wof:placetype":"venue"
},
  "geometry": {"coordinates":[-82.941014,41.509302],"type":"Point"}
}