{
  "type": "Feature",
  "properties": {
    "addr:full": "826 W Main St Springfield OH 45504",
    "addr:housenumber": "826",
    "addr:postcode": "45504",
    "addr:street": "W Main St",
    "iso:country": "US",
    "sg:address": "826 W Main St",
    "sg:city": "Springfield",
    "sg:classifiers": [
      {
        "category": "Food \u0026 Beverages",
        "subcategory": "Liquor \u0026 Beverages",
        "type": "Retail Goods"
      }
    ],
    "sg:phone": "+1 937 324 8690",
    "sg:postcode": "45504",
    "sg:province": "OH",
    "sg:tags": [
      "beer",
      "ale",
      "alcoholic"
    ],
    "wof:name": "John's Drive Thru",
    "wof:placetype": "venue"
  },
  "geometry": {"coordinates":[-83.825054,39.925559],"type":"Point"}
}
