{
  "type": "Feature",
  "properties": {
    "iso:country":"US",
    "sg:address":"826 W Main St",
    "sg:city":"Springfield",
    "sg:classifiers":[
        {
            "category":"Food & Beverages",
            "subcategory":"Liquor & Beverages",
            "type":"Retail Goods"
        }
    ],
    "sg:phone":"+1 937 324 8690",
    "sg:postcode":"45504",
    "sg:province":"OH",
    "sg:tags":[
        "beer",
        "ale",
        "alcoholic"
    ],
    "wof:name":"John's Drive Thru",
    "wof:placetype":"venue"
},
  "geometry": {"coordinates":[-83.82505399999999,39.925559],"type":"Point"}
}