{
  "type": "Feature",
  "properties": {
    "addr:full": "909 Milton Blvd Newton Falls OH 44444",
    "addr:housenumber": "909",
    "addr:postcode": "44444",
    "addr:street": "Milton Blvd",
    "iso:country": "US",
    "sg:address": "909 Milton Blvd",
    "sg:city": "Newton Falls",
    "sg:classifiers": [
      {
        "category": "Education",
        "subcategory": "School",
        "type": "Public Place"
      }
    ],
    "sg:phone": "+1 330 872 0695",
    "sg:postcode": "44444",
    "sg:province": "OH",
    "wof:name": "Newton Falls Middle School",
    "wof:placetype": "venue"
  },
  "geometry": {"coordinates":[-80.966309,41.177986],"type":"Point"}
}
