{
  "type": "Feature",
  "properties": {
    "addr:full": "2332 Fenner Rd Troy OH 45373",
    "addr:housenumber": "2332",
    "addr:postcode": "45373",
    "addr:street": "Fenner Rd",
    "iso:country": "US",
    "sg:address": "2332 Fenner Rd",
    "sg:city": "Troy",
    "sg:classifiers": [
      {
        "category": "Building \u0026 Trades",
        "subcategory": "Cleaning \u0026 Sanitation",
        "type": "Services"
      }
    ],
    "sg:phone": "+1 937 440 9080",
    "sg:postcode": "45373",
    "sg:province": "OH",
    "sg:tags": [
      "janitor"
    ],
    "wof:name": "Ultra Shine Pro Cleaning Svc",
    "wof:placetype": "venue"
  },
  "geometry": {"coordinates":[-84.244933,40.024254],"type":"Point"}
}
