{
  "type": "Feature",
  "properties": {
    "addr:full": "26401 Miles Rd Cleveland OH 44128",
    "addr:housenumber": "26401",
    "addr:postcode": "44128",
    "addr:street": "Miles Rd",
    "iso:country": "US",
    "sg:address": "26401 Miles Rd",
    "sg:city": "Cleveland",
    "sg:classifiers": [
      {
        "category": "Freight",
        "type": "Transportation"
      }
    ],
    "sg:phone": "+1 216 896 6300",
    "sg:postcode": "44128",
    "sg:province": "OH",
    "sg:tags": [
      "commercial",
      "storage"
    ],
    "sg:website": "www.twomenandatruck.com",
    "wof:name": "Two Men \u0026 A Truck",
    "wof:placetype": "venue"
  },
  "geometry": {"coordinates":[-81.49526,41.424325],"type":"Point"}
}
