{
  "type": "Feature",
  "properties": {
    "iso:country":"US",
    "sg:address":"1177 W Ohio Pike",
    "sg:city":"Amelia",
    "sg:classifiers":[
        {
            "category":"Organizations",
            "subcategory":"Religious Organization",
            "type":"Services"
        }
    ],
    "sg:phone":"+1 513 752 2525",
    "sg:postcode":"45102",
    "sg:province":"OH",
    "sg:tags":[
        "church"
    ],
    "wof:name":"Calvin Presbyterian Church",
    "wof:placetype":"venue"
},
  "geometry": {"coordinates":[-84.231424,39.037936],"type":"Point"}
}