{
  "type": "Feature",
  "properties": {
    "addr:full": "1177 W Ohio Pike Amelia OH 45102",
    "addr:housenumber": "1177",
    "addr:postcode": "45102",
    "addr:street": "W Ohio Pike",
    "iso:country": "US",
    "sg:address": "1177 W Ohio Pike",
    "sg:city": "Amelia",
    "sg:classifiers": [
      {
        "category": "Organizations",
        "subcategory": "Religious Organization",
        "type": "Services"
      }
    ],
    "sg:phone": "+1 513 752 2525",
    "sg:postcode": "45102",
    "sg:province": "OH",
    "sg:tags": [
      "church"
    ],
    "wof:name": "Calvin Presbyterian Church",
    "wof:placetype": "venue"
  },
  "geometry": {"coordinates":[-84.231424,39.037936],"type":"Point"}
}
