{
  "type": "Feature",
  "properties": {
    "addr:full":"356 Poland Ave Struthers OH 44471",
    "addr:housenumber":"356",
    "addr:postcode":"44471",
    "addr:street":"Poland Ave",
    "iso:country":"US",
    "sg:address":"356 Poland Ave",
    "sg:city":"Struthers",
    "sg:phone":"+1 330 755 9605",
    "sg:postcode":"44471",
    "sg:province":"OH",
    "sg:tags":[
        "farm",
        "corn",
        "soybean"
    ],
    "wof:name":"Edward Sakely",
    "wof:placetype":"venue"
},
  "geometry": {"coordinates":[-80.59158499999999,41.0472],"type":"Point"}
}