{
  "type": "Feature",
  "properties": {
    "addr:full":"6966 McNerney Dr Northwood OH 43619",
    "addr:housenumber":"6966",
    "addr:postcode":"43619",
    "addr:street":"Mcnerney Dr",
    "iso:country":"US",
    "sg:address":"6966 McNerney Dr",
    "sg:city":"Northwood",
    "sg:classifiers":[
        {
            "category":"Wholesale",
            "subcategory":"Machinery & Supplies",
            "type":"Manufacturing & Wholesale Goods"
        }
    ],
    "sg:phone":"+1 419 661 5500",
    "sg:postcode":"43619",
    "sg:province":"OH",
    "sg:tags":[
        "equipment",
        "industrial"
    ],
    "wof:name":"Mc Cormick Equipment Co Inc",
    "wof:placetype":"venue"
},
  "geometry": {"coordinates":[-83.52708800000001,41.602415],"type":"Point"}
}