{
  "type": "Feature",
  "properties": {
    "addr:full": "147 Freedom Ct Elyria OH 44035",
    "addr:housenumber": "147",
    "addr:postcode": "44035",
    "addr:street": "Freedom Ct",
    "iso:country": "US",
    "sg:address": "147 Freedom Ct",
    "sg:city": "Elyria",
    "sg:classifiers": [
      {
        "category": "Manufacturing",
        "subcategory": "Tools \u0026 Machinery",
        "type": "Manufacturing \u0026 Wholesale Goods"
      }
    ],
    "sg:phone": "+1 440 324 2825",
    "sg:postcode": "44035",
    "sg:province": "OH",
    "sg:tags": [
      "machine",
      "shop",
      "job"
    ],
    "wof:name": "Midway Manufacturing Inc",
    "wof:placetype": "venue"
  },
  "geometry": {"coordinates":[-82.127583,41.408302],"type":"Point"}
}
