{
  "type": "Feature",
  "properties": {
    "addr:full": "14849 State Rte 152 Toronto OH 43964",
    "addr:housenumber": "14849",
    "addr:postcode": "43964",
    "addr:street": "State Rte 152",
    "iso:country": "US",
    "sg:address": "14849 State Rte 152",
    "sg:city": "Toronto",
    "sg:classifiers": [
      {
        "category": "Freight",
        "type": "Transportation"
      }
    ],
    "sg:phone": "+1 740 544 5199",
    "sg:postcode": "43964",
    "sg:province": "OH",
    "sg:tags": [
      "hauling",
      "trucking"
    ],
    "wof:name": "J D Rawson \u0026 Sons Trucking",
    "wof:placetype": "venue"
  },
  "geometry": {"coordinates":[-80.69515,40.495497],"type":"Point"}
}
