{
  "type": "Feature",
  "properties": {
    "iso:country":"US",
    "sg:address":"3165 Foxmoor St NE",
    "sg:city":"Hartville",
    "sg:classifiers":[
        {
            "category":"Building & Trades",
            "subcategory":"Landscaping Services",
            "type":"Services"
        }
    ],
    "sg:phone":"+1 330 877 4304",
    "sg:postcode":"44632",
    "sg:province":"OH",
    "wof:name":"Ikes Lawn Mowing",
    "wof:placetype":"venue"
},
  "geometry": {"coordinates":[-81.318262,40.930591],"type":"Point"}
}