{
  "type": "Feature",
  "properties": {
    "addr:full":"320 N Main St Marion OH 43302",
    "addr:housenumber":"320",
    "addr:postcode":"43302",
    "addr:street":"N Main St",
    "iso:country":"US",
    "sg:address":"320 N Main St",
    "sg:city":"Marion",
    "sg:classifiers":[
        {
            "category":"Retail",
            "subcategory":"Auto Repair",
            "type":"Services"
        }
    ],
    "sg:phone":"+1 740 383 1898",
    "sg:postcode":"43302",
    "sg:province":"OH",
    "sg:tags":[
        "body",
        "automobile",
        "painting"
    ],
    "wof:name":"Smith Brothers",
    "wof:placetype":"venue"
},
  "geometry": {"coordinates":[-83.129051,40.592916],"type":"Point"}
}