{
  "type": "Feature",
  "properties": {
    "iso:country":"US",
    "sg:address":"9755 Plank Rd",
    "sg:city":"Montville",
    "sg:classifiers":[
        {
            "category":"Manufacturing",
            "subcategory":"Rubber & Plastics",
            "type":"Manufacturing & Wholesale Goods"
        }
    ],
    "sg:phone":"+1 440 968 9800",
    "sg:postcode":"44064",
    "sg:province":"OH",
    "wof:name":"Service Packaging",
    "wof:placetype":"venue"
},
  "geometry": {"coordinates":[-81.057877,41.60544],"type":"Point"}
}