{
  "type": "Feature",
  "properties": {
    "addr:full":"17 E William St Delaware OH 43015",
    "addr:housenumber":"17",
    "addr:postcode":"43015",
    "addr:street":"E William St",
    "iso:country":"US",
    "sg:address":"17 E William St",
    "sg:city":"Delaware",
    "sg:classifiers":[
        {
            "category":"Autos & Motor Vehicles",
            "subcategory":"Fuel & Gas Station",
            "type":"Retail Goods"
        }
    ],
    "sg:phone":"+1 740 369 4171",
    "sg:postcode":"43015",
    "sg:province":"OH",
    "sg:tags":[
        "oil"
    ],
    "wof:name":"BP Oil Co",
    "wof:placetype":"venue"
},
  "geometry": {"coordinates":[-83.067165,40.298839],"type":"Point"}
}