{
  "type": "Feature",
  "properties": {
    "addr:full":"9302 Miles Ave Cleveland OH 44105",
    "addr:housenumber":"9302",
    "addr:postcode":"44105",
    "addr:street":"Miles Ave",
    "iso:country":"US",
    "sg:address":"9302 Miles Ave",
    "sg:city":"Cleveland",
    "sg:classifiers":[
        {
            "category":"Shopping",
            "subcategory":"Discount & Variety Stores",
            "type":"Retail Goods"
        }
    ],
    "sg:phone":"+1 216 641 6713",
    "sg:postcode":"44105",
    "sg:province":"OH",
    "wof:name":"Family Dollar Store",
    "wof:placetype":"venue"
},
  "geometry": {"coordinates":[-81.61956000000001,41.445063],"type":"Point"}
}