{
  "type": "Feature",
  "properties": {
    "addr:full": "228 Park Ave W Mansfield OH 44902",
    "addr:housenumber": "228",
    "addr:postcode": "44902",
    "addr:street": "Park Ave W",
    "iso:country": "US",
    "sg:address": "228 Park Ave W",
    "sg:city": "Mansfield",
    "sg:classifiers": [
      {
        "category": "Health Services",
        "subcategory": "Clinic",
        "type": "Services"
      }
    ],
    "sg:phone": "+1 419 774 5970",
    "sg:postcode": "44902",
    "sg:province": "OH",
    "sg:tags": [
      "social"
    ],
    "wof:name": "Forensic Center",
    "wof:placetype": "venue"
  },
  "geometry": {"coordinates":[-82.526029,40.758874],"type":"Point"}
}
