{
  "type": "Feature",
  "properties": {
    "iso:country":"US",
    "sg:address":"228 Park Ave W",
    "sg:city":"Mansfield",
    "sg:classifiers":[
        {
            "category":"Health Services",
            "subcategory":"Clinic",
            "type":"Services"
        }
    ],
    "sg:phone":"+1 419 774 5970",
    "sg:postcode":"44902",
    "sg:province":"OH",
    "sg:tags":[
        "social"
    ],
    "wof:name":"Forensic Center",
    "wof:placetype":"venue"
},
  "geometry": {"coordinates":[-82.52602899999999,40.758874],"type":"Point"}
}