{
  "type": "Feature",
  "properties": {
    "addr:full":"6950 Americana Pkwy Reynoldsburg OH 43068",
    "addr:housenumber":"6950",
    "addr:postcode":"43068",
    "addr:street":"Americana Pkwy",
    "iso:country":"US",
    "sg:address":"6950 Americana Pkwy",
    "sg:city":"Reynoldsburg",
    "sg:classifiers":[
        {
            "category":"Home & Garden",
            "subcategory":"Building Materials",
            "type":"Retail Goods"
        }
    ],
    "sg:phone":"+1 614 575 1340",
    "sg:postcode":"43068",
    "sg:province":"OH",
    "sg:tags":[
        "windows"
    ],
    "wof:name":"Baywatch Windows",
    "wof:placetype":"venue"
},
  "geometry": {"coordinates":[-82.815578,39.930015],"type":"Point"}
}