{
  "type": "Feature",
  "properties": {
    "addr:full": "2231 Smeltzer Rd Marion OH 43302",
    "addr:housenumber": "2231",
    "addr:postcode": "43302",
    "addr:street": "Smeltzer Rd",
    "iso:country": "US",
    "sg:address": "2231 Smeltzer Rd",
    "sg:city": "Marion",
    "sg:classifiers": [
      {
        "category": "Organizations",
        "subcategory": "Religious Organization",
        "type": "Services"
      }
    ],
    "sg:phone": "+1 740 499 4347",
    "sg:postcode": "43302",
    "sg:province": "OH",
    "sg:tags": [
      "church"
    ],
    "wof:name": "Faith Fellowship Ministries",
    "wof:placetype": "venue"
  },
  "geometry": {"coordinates":[-83.136929,40.545788],"type":"Point"}
}
