{
  "type": "Feature",
  "properties": {
    "addr:full":"360 Solon Rd Bedford OH 44146",
    "addr:housenumber":"360",
    "addr:postcode":"44146",
    "addr:street":"Solon Rd",
    "iso:country":"US",
    "sg:address":"360 Solon Rd",
    "sg:city":"Bedford",
    "sg:classifiers":[
        {
            "category":"Real Estate",
            "subcategory":"Real Estate Operator",
            "type":"Services"
        }
    ],
    "sg:phone":"+1 440 786 0963",
    "sg:postcode":"44146",
    "sg:province":"OH",
    "sg:tags":[
        "building",
        "nonresidential"
    ],
    "wof:name":"Kmm Properties of Cleveland",
    "wof:placetype":"venue"
},
  "geometry": {"coordinates":[-81.516839,41.386539],"type":"Point"}
}