{
  "type": "Feature",
  "properties": {
    "addr:full": "638 Watervliet Ave Dayton OH 45420",
    "addr:housenumber": "638",
    "addr:postcode": "45420",
    "addr:street": "Watervliet Ave",
    "iso:country": "US",
    "sg:address": "638 Watervliet Ave",
    "sg:city": "Dayton",
    "sg:classifiers": [
      {
        "category": "Real Estate",
        "subcategory": "Real Estate Agent",
        "type": "Services"
      }
    ],
    "sg:phone": "+1 937 252 3984",
    "sg:postcode": "45420",
    "sg:province": "OH",
    "sg:tags": [
      "management"
    ],
    "wof:name": "Raelyn Property Management",
    "wof:placetype": "venue"
  },
  "geometry": {"coordinates":[-84.143045,39.732157],"type":"Point"}
}
