{
  "type": "Feature",
  "properties": {
    "addr:full": "2375 Dorr St Toledo OH 43607",
    "addr:housenumber": "2375",
    "addr:postcode": "43607",
    "addr:street": "Dorr St",
    "iso:country": "US",
    "sg:address": "2375 Dorr St",
    "sg:city": "Toledo",
    "sg:classifiers": [
      {
        "category": "Building \u0026 Trades",
        "subcategory": "Construction",
        "type": "Services"
      }
    ],
    "sg:phone": "+1 419 531 2441",
    "sg:postcode": "43607",
    "sg:province": "OH",
    "sg:tags": [
      "excavation",
      "contractor"
    ],
    "wof:name": "Ropper Construction",
    "wof:placetype": "venue"
  },
  "geometry": {"coordinates":[-83.60234,41.652863],"type":"Point"}
}
