{
  "type": "Feature",
  "properties": {
    "addr:full": "3253 Jefferson Ave Cincinnati OH 45220",
    "addr:housenumber": "3253",
    "addr:postcode": "45220",
    "addr:street": "Jefferson Ave",
    "iso:country": "US",
    "sg:address": "3253 Jefferson Ave",
    "sg:city": "Cincinnati",
    "sg:classifiers": [
      {
        "category": "Restaurant",
        "type": "Food \u0026 Drink"
      }
    ],
    "sg:phone": "+1 513 961 0013",
    "sg:postcode": "45220",
    "sg:province": "OH",
    "wof:name": "Corinthian Restaurant \u0026 Lounge",
    "wof:placetype": "venue"
  },
  "geometry": {"coordinates":[-84.513385,39.140607],"type":"Point"}
}
