{
  "type": "Feature",
  "properties": {
    "iso:country":"US",
    "sg:address":"8180 Corporate Park Dr",
    "sg:city":"Cincinnati",
    "sg:classifiers":[
        {
            "category":"Social Services",
            "subcategory":"Job Training",
            "type":"Services"
        }
    ],
    "sg:phone":"+1 513 469 2771",
    "sg:postcode":"45242",
    "sg:province":"OH",
    "sg:tags":[
        "rehabilitation"
    ],
    "sg:website":"www.smarthealthcare.net",
    "wof:name":"Smart Healthcare Svc Corp",
    "wof:placetype":"venue"
},
  "geometry": {"coordinates":[-84.339083,39.25997],"type":"Point"}
}