{
  "type": "Feature",
  "properties": {
    "iso:country":"US",
    "sg:address":"16808 Co Rd M",
    "sg:city":"Napoleon",
    "sg:classifiers":[
        {
            "category":"Manufacturing",
            "subcategory":"Buildings",
            "type":"Manufacturing & Wholesale Goods"
        }
    ],
    "sg:phone":"+1 419 758 3308",
    "sg:postcode":"43545",
    "sg:province":"OH",
    "sg:tags":[
        "prefabricated",
        "wood",
        "mfg"
    ],
    "wof:name":"Barden Homes of NW Ohio",
    "wof:placetype":"venue"
},
  "geometry": {"coordinates":[-84.185357,41.340921],"type":"Point"}
}