{
  "type": "Feature",
  "properties": {
    "addr:full":"37444 Holley Rd Pomeroy OH 45769",
    "addr:postcode":"37444;45769",
    "addr:street":"Holley Rd",
    "iso:country":"US",
    "sg:address":"37444 Holley Rd",
    "sg:city":"Pomeroy",
    "sg:classifiers":[
        {
            "category":"Professional",
            "subcategory":"Management & Consulting",
            "type":"Services"
        }
    ],
    "sg:phone":"+1 740 992 7992",
    "sg:postcode":"45769",
    "sg:province":"OH",
    "sg:tags":[
        "cad"
    ],
    "wof:name":"Warren Taylor Services Inc",
    "wof:placetype":"venue"
},
  "geometry": {"coordinates":[-82.09595299999999,39.158142],"type":"Point"}
}