{
  "type": "Feature",
  "properties": {
    "iso:country":"US",
    "sg:address":"2115 Warrensville Center Rd",
    "sg:city":"Cleveland",
    "sg:classifiers":[
        {
            "category":"Ice Cream",
            "type":"Food & Drink"
        }
    ],
    "sg:menulink":"http://www.allmenus.com/oh/south-euclid/175699-dairy-queen/menu/",
    "sg:phone":"+1 216 371 1605",
    "sg:postcode":"44121",
    "sg:province":"OH",
    "sg:tags":[
        "burger",
        "american"
    ],
    "wof:name":"Dairy Queen",
    "wof:placetype":"venue"
},
  "geometry": {"coordinates":[-81.535721,41.502237],"type":"Point"}
}