{
  "type": "Feature",
  "properties": {
    "addr:full":"225 Maple Ave Woodsfield OH 43793",
    "addr:housenumber":"225",
    "addr:postcode":"43793",
    "addr:street":"Maple Ave",
    "iso:country":"US",
    "sg:address":"225 Maple Ave",
    "sg:city":"Woodsfield",
    "sg:classifiers":[
        {
            "category":"Organizations",
            "subcategory":"Religious Organization",
            "type":"Services"
        }
    ],
    "sg:phone":"+1 740 472 5139",
    "sg:postcode":"43793",
    "sg:province":"OH",
    "sg:tags":[
        "church"
    ],
    "wof:name":"Woodsfield Church Of Nazarene",
    "wof:placetype":"venue"
},
  "geometry": {"coordinates":[-81.104947,39.766805],"type":"Point"}
}