{
  "type": "Feature",
  "properties": {
    "iso:country":"US",
    "sg:address":"15200 Madison Rd",
    "sg:city":"Middlefield",
    "sg:classifiers":[
        {
            "category":"Freight",
            "type":"Transportation"
        }
    ],
    "sg:phone":"+1 440 632 6367",
    "sg:postcode":"44062",
    "sg:province":"OH",
    "sg:tags":[
        "commercial",
        "storage"
    ],
    "wof:name":"Middlefield Home & Bus Stge",
    "wof:placetype":"venue"
},
  "geometry": {"coordinates":[-81.05127899999999,41.45337],"type":"Point"}
}