{
  "type": "Feature",
  "properties": {
    "addr:full": "15200 Madison Rd Middlefield OH 44062",
    "addr:housenumber": "15200",
    "addr:postcode": "44062",
    "addr:street": "Madison Rd",
    "iso:country": "US",
    "sg:address": "15200 Madison Rd",
    "sg:city": "Middlefield",
    "sg:classifiers": [
      {
        "category": "Freight",
        "type": "Transportation"
      }
    ],
    "sg:phone": "+1 440 632 6367",
    "sg:postcode": "44062",
    "sg:province": "OH",
    "sg:tags": [
      "commercial",
      "storage"
    ],
    "wof:name": "Middlefield Home \u0026 Bus Stge",
    "wof:placetype": "venue"
  },
  "geometry": {"coordinates":[-81.051279,41.45337],"type":"Point"}
}
