{
  "type": "Feature",
  "properties": {
    "addr:full":"9515 Detroit Ave Cleveland OH 44102",
    "addr:housenumber":"9515",
    "addr:postcode":"44102",
    "addr:street":"Detroit Ave",
    "iso:country":"US",
    "sg:address":"9515 Detroit Ave",
    "sg:city":"Cleveland",
    "sg:classifiers":[
        {
            "category":"Retail",
            "subcategory":"Auto Repair",
            "type":"Services"
        }
    ],
    "sg:phone":"+1 216 281 0303",
    "sg:postcode":"44102",
    "sg:province":"OH",
    "sg:tags":[
        "transmission",
        "shop"
    ],
    "wof:name":"Enhanced Transmissions Inc",
    "wof:placetype":"venue"
},
  "geometry": {"coordinates":[-81.749488,41.479971],"type":"Point"}
}