{
  "type": "Feature",
  "properties": {
    "iso:country":"US",
    "sg:address":"5315 Stickney Ave",
    "sg:city":"Toledo",
    "sg:classifiers":[
        {
            "category":"Home & Garden",
            "subcategory":"Garden Supply",
            "type":"Retail Goods"
        }
    ],
    "sg:phone":"+1 419 727 7856",
    "sg:postcode":"43612",
    "sg:province":"OH",
    "sg:tags":[
        "mulch"
    ],
    "wof:name":"Kurtz Brothers Compost Facilit",
    "wof:placetype":"venue"
},
  "geometry": {"coordinates":[-83.527829,41.710465],"type":"Point"}
}