{
  "type": "Feature",
  "properties": {
    "addr:full":"41 Kellie Ter Georgetown OH 45121",
    "addr:housenumber":"41",
    "addr:postcode":"45121",
    "addr:street":"Kellie Ter",
    "iso:country":"US",
    "sg:address":"41 Kellie Ter",
    "sg:city":"Georgetown",
    "sg:classifiers":[
        {
            "category":"Manufacturing",
            "subcategory":"Tools & Machinery",
            "type":"Manufacturing & Wholesale Goods"
        }
    ],
    "sg:phone":"+1 937 378 2211",
    "sg:postcode":"45121",
    "sg:province":"OH",
    "sg:tags":[
        "farm",
        "mfg"
    ],
    "wof:name":"Gary L Layman",
    "wof:placetype":"venue"
},
  "geometry": {"coordinates":[-83.90222,38.848654],"type":"Point"}
}