{
  "type": "Feature",
  "properties": {
    "iso:country":"US",
    "sg:address":"28935 Euclid Ave",
    "sg:city":"Wickliffe",
    "sg:classifiers":[
        {
            "category":"Personal",
            "subcategory":"Tattoo Parlor",
            "type":"Services"
        }
    ],
    "sg:phone":"+1 440 943 4008",
    "sg:postcode":"44092",
    "sg:province":"OH",
    "sg:tags":[
        "tattooing"
    ],
    "sg:website":"www.finestlines.com",
    "wof:name":"Finest Lines Tattoo Studio Inc",
    "wof:placetype":"venue"
},
  "geometry": {"coordinates":[-81.479134,41.602536],"type":"Point"}
}