{
  "type": "Feature",
  "properties": {
    "addr:full":"605 Meadowcrest Rd Cincinnati OH 45231",
    "addr:housenumber":"605",
    "addr:postcode":"45231",
    "addr:street":"Meadowcrest Rd",
    "iso:country":"US",
    "sg:address":"605 Meadowcrest Rd",
    "sg:city":"Cincinnati",
    "sg:classifiers":[
        {
            "category":"Organizations",
            "subcategory":"Religious Organization",
            "type":"Services"
        }
    ],
    "sg:phone":"+1 513 772 2889",
    "sg:postcode":"45231",
    "sg:province":"OH",
    "sg:tags":[
        "church"
    ],
    "sg:website":"www.gracefreechurch.com",
    "wof:name":"Grace Evangelical Free Church",
    "wof:placetype":"venue"
},
  "geometry": {"coordinates":[-84.500068,39.240441],"type":"Point"}
}