{
  "type": "Feature",
  "properties": {
    "iso:country":"US",
    "sg:address":"3325 W State St",
    "sg:city":"Fremont",
    "sg:classifiers":[
        {
            "category":"Building & Trades",
            "subcategory":"Construction",
            "type":"Services"
        }
    ],
    "sg:phone":"+1 419 332 5149",
    "sg:postcode":"43420",
    "sg:province":"OH",
    "sg:tags":[
        "paint",
        "painting",
        "contractor"
    ],
    "wof:name":"Damman Paint Inc",
    "wof:placetype":"venue"
},
  "geometry": {"coordinates":[-83.170996,41.371078],"type":"Point"}
}