{
  "type": "Feature",
  "properties": {
    "iso:country":"US",
    "sg:address":"252 Southpark Center",
    "sg:city":"Cleveland",
    "sg:classifiers":[
        {
            "category":"Shopping",
            "subcategory":"Shoes",
            "type":"Retail Goods"
        }
    ],
    "sg:phone":"+1 440 846 1132",
    "sg:postcode":"44136",
    "sg:province":"OH",
    "sg:tags":[
        "shoe",
        "store"
    ],
    "wof:name":"Lady Foot Locker",
    "wof:placetype":"venue"
},
  "geometry": {"coordinates":[-81.820449,41.310925],"type":"Point"}
}