{
  "type": "Feature",
  "properties": {
    "iso:country":"US",
    "sg:address":"1331 E 260th St",
    "sg:city":"Euclid",
    "sg:classifiers":[
        {
            "category":"Sports & Exercise",
            "subcategory":"Bowling",
            "type":"Entertainment"
        }
    ],
    "sg:phone":"+1 216 261 1715",
    "sg:postcode":"44132",
    "sg:province":"OH",
    "sg:tags":[
        "eating",
        "center"
    ],
    "wof:name":"Palisades Palace",
    "wof:placetype":"venue"
},
  "geometry": {"coordinates":[-81.50276100000001,41.593152],"type":"Point"}
}