{
  "type": "Feature",
  "properties": {
    "addr:full": "277 8th Ave Mansfield OH 44905",
    "addr:housenumber": "277",
    "addr:postcode": "44905",
    "addr:street": "8Th Ave",
    "iso:country": "US",
    "sg:address": "277 8th Ave",
    "sg:city": "Mansfield",
    "sg:classifiers": [
      {
        "category": "Retail",
        "subcategory": "Auto Repair",
        "type": "Services"
      }
    ],
    "sg:phone": "+1 419 589 4181",
    "sg:postcode": "44905",
    "sg:province": "OH",
    "sg:tags": [
      "truck"
    ],
    "wof:name": "Yard Tractors Of America",
    "wof:placetype": "venue"
  },
  "geometry": {"coordinates":[-82.493808,40.76743],"type":"Point"}
}
