{
  "type": "Feature",
  "properties": {
    "addr:full":"5051 Calhoon Dr Hilliard OH 43026",
    "addr:housenumber":"5051",
    "addr:postcode":"43026",
    "addr:street":"Calhoon Dr",
    "iso:country":"US",
    "sg:address":"5051 Calhoon Dr",
    "sg:city":"Hilliard",
    "sg:classifiers":[
        {
            "category":"Personal",
            "subcategory":"Beauty Salon",
            "type":"Services"
        }
    ],
    "sg:phone":"+1 614 777 0582",
    "sg:postcode":"43026",
    "sg:province":"OH",
    "sg:tags":[
        "manicuring"
    ],
    "wof:name":"Creative Nail Design",
    "wof:placetype":"venue"
},
  "geometry": {"coordinates":[-83.144825,40.008251],"type":"Point"}
}