{
  "type": "Feature",
  "properties": {
    "iso:country":"US",
    "sg:address":"8536 Eccles Pl",
    "sg:city":"Dayton",
    "sg:classifiers":[
        {
            "category":"Building & Trades",
            "subcategory":"Electrical",
            "type":"Services"
        }
    ],
    "sg:phone":"+1 937 433 5194",
    "sg:postcode":"45458",
    "sg:province":"OH",
    "sg:tags":[
        "electrical",
        "contractor"
    ],
    "wof:name":"Harning Electric",
    "wof:placetype":"venue"
},
  "geometry": {"coordinates":[-84.146818,39.620538],"type":"Point"}
}