{
  "type": "Feature",
  "properties": {
    "addr:full":"4255 Lincoln Way Wooster OH 44691",
    "addr:housenumber":"4255",
    "addr:postcode":"44691",
    "addr:street":"Lincoln Way",
    "iso:country":"US",
    "sg:address":"4255 Lincoln Way",
    "sg:city":"Wooster",
    "sg:classifiers":[
        {
            "category":"Manufacturing",
            "subcategory":"Tools & Machinery",
            "type":"Manufacturing & Wholesale Goods"
        }
    ],
    "sg:phone":"+1 330 264 8699",
    "sg:postcode":"44691",
    "sg:province":"OH",
    "sg:tags":[
        "equipment",
        "tree",
        "supply"
    ],
    "sg:website":"www.raycomfg.com",
    "wof:name":"Rayco Manufacturing Inc",
    "wof:placetype":"venue"
},
  "geometry": {"coordinates":[-81.88485900000001,40.796144],"type":"Point"}
}