{
  "type": "Feature",
  "properties": {
    "addr:full":"111 Hickory St Dayton OH 45410",
    "addr:housenumber":"111",
    "addr:postcode":"45410",
    "addr:street":"Hickory St",
    "iso:country":"US",
    "sg:address":"111 Hickory St",
    "sg:city":"Dayton",
    "sg:classifiers":[
        {
            "category":"Food & Beverages",
            "subcategory":"Groceries & Convenience Stores",
            "type":"Retail Goods"
        }
    ],
    "sg:phone":"+1 937 228 5061",
    "sg:postcode":"45410",
    "sg:province":"OH",
    "sg:tags":[
        "product"
    ],
    "wof:name":"Food Stamps",
    "wof:placetype":"venue"
},
  "geometry": {"coordinates":[-84.18310700000001,39.748718],"type":"Point"}
}