{
  "type": "Feature",
  "properties": {
    "addr:full": "116 Louisiana Ave Perrysburg OH 43551",
    "addr:housenumber": "116",
    "addr:postcode": "43551",
    "addr:street": "Louisiana Ave",
    "iso:country": "US",
    "sg:address": "116 Louisiana Ave",
    "sg:city": "Perrysburg",
    "sg:classifiers": [
      {
        "category": "Shopping",
        "subcategory": "Crafts \u0026 Fabrics",
        "type": "Retail Goods"
      }
    ],
    "sg:phone": "+1 419 872 9819",
    "sg:postcode": "43551",
    "sg:province": "OH",
    "sg:tags": [
      "material",
      "needlework",
      "sewing"
    ],
    "sg:website": "www.accomplishments-shop.com",
    "wof:name": "Accomplishments Inc",
    "wof:placetype": "venue"
  },
  "geometry": {"coordinates":[-83.629474,41.559482],"type":"Point"}
}
