{
  "type": "Feature",
  "properties": {
    "iso:country":"US",
    "sg:address":"116 Louisiana Ave",
    "sg:city":"Perrysburg",
    "sg:classifiers":[
        {
            "category":"Shopping",
            "subcategory":"Crafts & Fabrics",
            "type":"Retail Goods"
        }
    ],
    "sg:phone":"+1 419 872 9819",
    "sg:postcode":"43551",
    "sg:province":"OH",
    "sg:tags":[
        "material",
        "needlework",
        "sewing"
    ],
    "sg:website":"www.accomplishments-shop.com",
    "wof:name":"Accomplishments Inc",
    "wof:placetype":"venue"
},
  "geometry": {"coordinates":[-83.629474,41.559482],"type":"Point"}
}