{
  "type": "Feature",
  "properties": {
    "addr:full": "6805 Lansing Ave Cleveland OH 44105",
    "addr:housenumber": "6805",
    "addr:postcode": "44105",
    "addr:street": "Lansing Ave",
    "iso:country": "US",
    "sg:address": "6805 Lansing Ave",
    "sg:city": "Cleveland",
    "sg:classifiers": [
      {
        "category": "Manufacturing",
        "subcategory": "Printing",
        "type": "Manufacturing \u0026 Wholesale Goods"
      }
    ],
    "sg:phone": "+1 216 341 1177",
    "sg:postcode": "44105",
    "sg:province": "OH",
    "sg:tags": [
      "commercial"
    ],
    "wof:name": "Colorline Screen Graphics",
    "wof:placetype": "venue"
  },
  "geometry": {"coordinates":[-81.640556,41.452743],"type":"Point"}
}
