{
  "type": "Feature",
  "properties": {
    "addr:full":"1420 Frank Rd Columbus OH 43223",
    "addr:housenumber":"1420",
    "addr:postcode":"43223",
    "addr:street":"Frank Rd",
    "iso:country":"US",
    "sg:address":"1420 Frank Rd",
    "sg:city":"Columbus",
    "sg:classifiers":[
        {
            "category":"Autos & Motor Vehicles",
            "subcategory":"Automobile Sales",
            "type":"Retail Goods"
        }
    ],
    "sg:phone":"+1 614 308 1121",
    "sg:postcode":"43223",
    "sg:province":"OH",
    "sg:tags":[
        "car",
        "dealer"
    ],
    "wof:name":"D & G Family Auto Sales",
    "wof:placetype":"venue"
},
  "geometry": {"coordinates":[-83.040193,39.917338],"type":"Point"}
}