{
  "type": "Feature",
  "properties": {
    "addr:full": "7848 Tippecanoe Rd Canfield OH 44406",
    "addr:housenumber": "7848",
    "addr:postcode": "44406",
    "addr:street": "Tippecanoe Rd",
    "iso:country": "US",
    "sg:address": "7848 Tippecanoe Rd",
    "sg:city": "Canfield",
    "sg:classifiers": [
      {
        "category": "Wholesale",
        "subcategory": "Farm Supplies",
        "type": "Manufacturing \u0026 Wholesale Goods"
      }
    ],
    "sg:phone": "+1 330 507 2444",
    "sg:postcode": "44406",
    "sg:province": "OH",
    "wof:name": "Keich Enterprises Inc",
    "wof:placetype": "venue"
  },
  "geometry": {"coordinates":[-80.711475,40.997864],"type":"Point"}
}
