{
  "type": "Feature",
  "properties": {
    "iso:country":"US",
    "sg:address":"137 S Main St",
    "sg:city":"De Graff",
    "sg:classifiers":[
        {
            "category":"Home & Garden",
            "subcategory":"Building Materials",
            "type":"Retail Goods"
        }
    ],
    "sg:phone":"+1 937 585 5043",
    "sg:postcode":"43318",
    "sg:province":"OH",
    "wof:name":"De Graff Building Supply",
    "wof:placetype":"venue"
},
  "geometry": {"coordinates":[-83.914654,40.309205],"type":"Point"}
}