{
  "type": "Feature",
  "properties": {
    "addr:full":"9035 Willey Rd Harrison OH 45030",
    "addr:housenumber":"9035",
    "addr:postcode":"45030",
    "addr:street":"Willey Rd",
    "iso:country":"US",
    "sg:address":"9035 Willey Rd",
    "sg:city":"Harrison",
    "sg:classifiers":[
        {
            "category":"Shopping",
            "subcategory":"Hobbies, Toys, & Games",
            "type":"Retail Goods"
        }
    ],
    "sg:phone":"+1 513 738 1974",
    "sg:postcode":"45030",
    "sg:province":"OH",
    "sg:tags":[
        "equipment",
        "ceramic",
        "supply"
    ],
    "wof:name":"Country Work Shop",
    "wof:placetype":"venue"
},
  "geometry": {"coordinates":[-84.73746800000001,39.276265],"type":"Point"}
}