{
  "type": "Feature",
  "properties": {
    "iso:country":"US",
    "sg:address":"5101 Younger Rd",
    "sg:city":"Celina",
    "sg:classifiers":[
        {
            "category":"Farming",
            "subcategory":"Livestock Farm",
            "type":"Manufacturing & Wholesale Goods"
        }
    ],
    "sg:phone":"+1 419 678 8016",
    "sg:postcode":"45822",
    "sg:province":"OH",
    "sg:tags":[
        "feedlot",
        "hog",
        "or",
        "beef",
        "cattle"
    ],
    "wof:name":"Hubert Homan",
    "wof:placetype":"venue"
},
  "geometry": {"coordinates":[-84.60607400000001,40.494513],"type":"Point"}
}