{
  "type": "Feature",
  "properties": {
    "addr:full":"110 Glendale Milford Rd Loveland OH 45140",
    "addr:housenumber":"110",
    "addr:postcode":"45140",
    "addr:street":"Glendale Milford Rd",
    "iso:country":"US",
    "sg:address":"110 Glendale Milford Rd",
    "sg:city":"Loveland",
    "sg:classifiers":[
        {
            "category":"Home & Garden",
            "subcategory":"Garden Supply",
            "type":"Retail Goods"
        }
    ],
    "sg:phone":"+1 513 831 0060",
    "sg:postcode":"45140",
    "sg:province":"OH",
    "sg:tags":[
        "landscaping",
        "equipment"
    ],
    "sg:website":"www.irvinewoodrecovery.com",
    "wof:name":"Irvine Wood Recovery Inc",
    "wof:placetype":"venue"
},
  "geometry": {"coordinates":[-84.311966,39.21178],"type":"Point"}
}