{
  "type": "Feature",
  "properties": {
    "addr:full": "8636 Yawberg Rd Whitehouse OH 43571",
    "addr:housenumber": "8636",
    "addr:postcode": "43571",
    "addr:street": "Yawberg Rd",
    "iso:country": "US",
    "sg:address": "8636 Yawberg Rd",
    "sg:city": "Whitehouse",
    "sg:classifiers": [
      {
        "category": "Building \u0026 Trades",
        "subcategory": "Construction",
        "type": "Services"
      }
    ],
    "sg:phone": "+1 419 875 6695",
    "sg:postcode": "43571",
    "sg:province": "OH",
    "sg:tags": [
      "nonresidential"
    ],
    "wof:name": "North Cross Development Co LLC",
    "wof:placetype": "venue"
  },
  "geometry": {"coordinates":[-83.8456,41.484955],"type":"Point"}
}
