{
  "type": "Feature",
  "properties": {
    "addr:full": "8204 State Rte 353 Ripley OH 45167",
    "addr:housenumber": "8204",
    "addr:postcode": "45167",
    "addr:street": "State Rte 353",
    "iso:country": "US",
    "sg:address": "8204 State Rte 353",
    "sg:city": "Ripley",
    "sg:classifiers": [
      {
        "category": "Farming",
        "subcategory": "Farm",
        "type": "Manufacturing \u0026 Wholesale Goods"
      }
    ],
    "sg:phone": "+1 937 373 3651",
    "sg:postcode": "45167",
    "sg:province": "OH",
    "sg:tags": [
      "crop",
      "general"
    ],
    "wof:name": "Joseph Fauth",
    "wof:placetype": "venue"
  },
  "geometry": {"coordinates":[-83.770276,38.81041],"type":"Point"}
}
