{
  "type": "Feature",
  "properties": {
    "addr:full": "940 Rocky Ridge Dr Akron OH 44313",
    "addr:housenumber": "940",
    "addr:postcode": "44313",
    "addr:street": "Rocky Ridge Dr",
    "iso:country": "US",
    "sg:address": "940 Rocky Ridge Dr",
    "sg:city": "Akron",
    "sg:classifiers": [
      {
        "category": "Home \u0026 Garden",
        "subcategory": "Home Furnishings",
        "type": "Retail Goods"
      }
    ],
    "sg:phone": "+1 330 867 3660",
    "sg:postcode": "44313",
    "sg:province": "OH",
    "sg:tags": [
      "kitchen",
      "accessory"
    ],
    "wof:name": "Ballarini",
    "wof:placetype": "venue"
  },
  "geometry": {"coordinates":[-81.53346,41.117697],"type":"Point"}
}
