{
  "type": "Feature",
  "properties": {
    "addr:full": "1608 E Perry St Port Clinton OH 43452",
    "addr:housenumber": "1608",
    "addr:postcode": "43452",
    "addr:street": "E Perry St",
    "iso:country": "US",
    "sg:address": "1608 E Perry St",
    "sg:city": "Port Clinton",
    "sg:classifiers": [
      {
        "category": "Home \u0026 Garden",
        "subcategory": "Hardware",
        "type": "Retail Goods"
      }
    ],
    "sg:phone": "+1 419 734 9243",
    "sg:postcode": "43452",
    "sg:province": "OH",
    "wof:name": "Ace Hardware",
    "wof:placetype": "venue"
  },
  "geometry": {"coordinates":[-82.920522,41.514363],"type":"Point"}
}
