{
  "type": "Feature",
  "properties": {
    "iso:country":"US",
    "sg:address":"1608 E Perry St",
    "sg:city":"Port Clinton",
    "sg:classifiers":[
        {
            "category":"Home & Garden",
            "subcategory":"Hardware",
            "type":"Retail Goods"
        }
    ],
    "sg:phone":"+1 419 734 9243",
    "sg:postcode":"43452",
    "sg:province":"OH",
    "wof:name":"Ace Hardware",
    "wof:placetype":"venue"
},
  "geometry": {"coordinates":[-82.92052200000001,41.514363],"type":"Point"}
}