{
  "type": "Feature",
  "properties": {
    "iso:country":"US",
    "sg:address":"2746 Dry Lane Rd N",
    "sg:city":"La Rue",
    "sg:classifiers":[
        {
            "category":"Real Estate",
            "subcategory":"Real Estate Operator",
            "type":"Services"
        }
    ],
    "sg:phone":"+1 740 499 2113",
    "sg:postcode":"43332",
    "sg:province":"OH",
    "sg:tags":[
        "property",
        "lessor"
    ],
    "wof:name":"Richard E Fiedler",
    "wof:placetype":"venue"
},
  "geometry": {"coordinates":[-83.361695,40.636629],"type":"Point"}
}