{
  "type": "Feature",
  "properties": {
    "addr:full": "442 N Limestone St Springfield OH 45503",
    "addr:housenumber": "442",
    "addr:postcode": "45503",
    "addr:street": "N Limestone St",
    "iso:country": "US",
    "sg:address": "442 N Limestone St",
    "sg:city": "Springfield",
    "sg:classifiers": [
      {
        "category": "Autos \u0026 Motor Vehicles",
        "subcategory": "Auto Supplies",
        "type": "Retail Goods"
      }
    ],
    "sg:phone": "+1 937 323 7080",
    "sg:postcode": "45503",
    "sg:province": "OH",
    "sg:tags": [
      "tire"
    ],
    "wof:name": "Clark County Tire Jido",
    "wof:placetype": "venue"
  },
  "geometry": {"coordinates":[-83.806861,39.930013],"type":"Point"}
}
