{
  "type": "Feature",
  "properties": {
    "addr:full":"341 21st St NW Canton OH 44709",
    "addr:housenumber":"341",
    "addr:postcode":"44709",
    "addr:street":"21St St Nw",
    "iso:country":"US",
    "sg:address":"341 21st St NW",
    "sg:city":"Canton",
    "sg:classifiers":[
        {
            "category":"Farming",
            "subcategory":"Farm",
            "type":"Manufacturing & Wholesale Goods"
        }
    ],
    "sg:phone":"+1 330 456 5115",
    "sg:postcode":"44709",
    "sg:province":"OH",
    "sg:tags":[
        "crop",
        "general"
    ],
    "wof:name":"White Star Farms",
    "wof:placetype":"venue"
},
  "geometry": {"coordinates":[-81.374149,40.820983],"type":"Point"}
}