{
  "type": "Feature",
  "properties": {
    "iso:country":"US",
    "sg:address":"3962 Linden Ave",
    "sg:city":"Dayton",
    "sg:classifiers":[
        {
            "category":"Wholesale",
            "subcategory":"Toys & Hobbies",
            "type":"Manufacturing & Wholesale Goods"
        }
    ],
    "sg:phone":"+1 937 254 8551",
    "sg:postcode":"45432",
    "sg:province":"OH",
    "sg:tags":[
        "sport"
    ],
    "wof:name":"TCI Sports Fan",
    "wof:placetype":"venue"
},
  "geometry": {"coordinates":[-84.124689,39.746287],"type":"Point"}
}