{
  "type": "Feature",
  "properties": {
    "addr:full": "3962 Linden Ave Dayton OH 45432",
    "addr:housenumber": "3962",
    "addr:postcode": "45432",
    "addr:street": "Linden Ave",
    "iso:country": "US",
    "sg:address": "3962 Linden Ave",
    "sg:city": "Dayton",
    "sg:classifiers": [
      {
        "category": "Wholesale",
        "subcategory": "Toys \u0026 Hobbies",
        "type": "Manufacturing \u0026 Wholesale Goods"
      }
    ],
    "sg:phone": "+1 937 254 8551",
    "sg:postcode": "45432",
    "sg:province": "OH",
    "sg:tags": [
      "sport"
    ],
    "wof:name": "TCI Sports Fan",
    "wof:placetype": "venue"
  },
  "geometry": {"coordinates":[-84.124689,39.746287],"type":"Point"}
}
