{
  "type": "Feature",
  "properties": {
    "iso:country":"US",
    "sg:address":"750 Sunnymeade Pl",
    "sg:city":"Troy",
    "sg:classifiers":[
        {
            "category":"Shopping",
            "subcategory":"Gifts & Souvenirs",
            "type":"Retail Goods"
        }
    ],
    "sg:phone":"+1 937 339 1225",
    "sg:postcode":"45373",
    "sg:province":"OH",
    "wof:name":"Armored Card",
    "wof:placetype":"venue"
},
  "geometry": {"coordinates":[-84.214456,40.013733],"type":"Point"}
}