{
  "type": "Feature",
  "properties": {
    "addr:full": "750 Sunnymeade Pl Troy OH 45373",
    "addr:housenumber": "750",
    "addr:postcode": "45373",
    "addr:street": "Sunnymeade Pl",
    "iso:country": "US",
    "sg:address": "750 Sunnymeade Pl",
    "sg:city": "Troy",
    "sg:classifiers": [
      {
        "category": "Shopping",
        "subcategory": "Gifts \u0026 Souvenirs",
        "type": "Retail Goods"
      }
    ],
    "sg:phone": "+1 937 339 1225",
    "sg:postcode": "45373",
    "sg:province": "OH",
    "wof:name": "Armored Card",
    "wof:placetype": "venue"
  },
  "geometry": {"coordinates":[-84.214456,40.013733],"type":"Point"}
}
