{
  "type": "Feature",
  "properties": {
    "addr:full": "716 Lima St Kenton OH 43326",
    "addr:housenumber": "716",
    "addr:postcode": "43326",
    "addr:street": "Lima St",
    "iso:country": "US",
    "sg:address": "716 Lima St",
    "sg:city": "Kenton",
    "sg:classifiers": [
      {
        "category": "Shopping",
        "subcategory": "Clothing, Apparel, \u0026 Fashions",
        "type": "Retail Goods"
      }
    ],
    "sg:phone": "+1 419 673 0997",
    "sg:postcode": "43326",
    "sg:province": "OH",
    "wof:name": "Horse Country",
    "wof:placetype": "venue"
  },
  "geometry": {"coordinates":[-83.619633,40.649751],"type":"Point"}
}
