{
  "type": "Feature",
  "properties": {
    "addr:full": "16106 State Rte 15 Continental OH 45831",
    "addr:housenumber": "16106",
    "addr:postcode": "45831",
    "addr:street": "State Rte 15",
    "iso:country": "US",
    "sg:address": "16106 State Rte 15",
    "sg:city": "Continental",
    "sg:phone": "+1 419 596 3839",
    "sg:postcode": "45831",
    "sg:province": "OH",
    "sg:tags": [
      "farm",
      "soybean"
    ],
    "wof:name": "Norman Liebrecht",
    "wof:placetype": "venue"
  },
  "geometry": {"coordinates":[-84.17083,41.066108],"type":"Point"}
}
