{
  "type": "Feature",
  "properties": {
    "iso:country":"US",
    "sg:address":"5820 N Dixie Dr",
    "sg:city":"Dayton",
    "sg:classifiers":[
        {
            "category":"Banks & Credit Unions",
            "subcategory":"Bank",
            "type":"Services"
        }
    ],
    "sg:phone":"+1 937 277 4166",
    "sg:postcode":"45414",
    "sg:province":"OH",
    "sg:tags":[
        "national",
        "commercial"
    ],
    "sg:website":"www.nationalcity.com",
    "wof:name":"National City Bank",
    "wof:placetype":"venue"
},
  "geometry": {"coordinates":[-84.198211,39.821178],"type":"Point"}
}