{
  "type": "Feature",
  "properties": {
    "addr:full":"445 E Main Cross St Findlay OH 45840",
    "addr:housenumber":"445",
    "addr:postcode":"45840",
    "addr:street":"E Main Cross St",
    "iso:country":"US",
    "sg:address":"445 E Main Cross St",
    "sg:city":"Findlay",
    "sg:classifiers":[
        {
            "category":"Wholesale",
            "subcategory":"Construction Materials",
            "type":"Manufacturing & Wholesale Goods"
        }
    ],
    "sg:phone":"+1 419 422 3400",
    "sg:postcode":"45840",
    "sg:province":"OH",
    "sg:tags":[
        "glass"
    ],
    "wof:name":"Riverside Glass Co",
    "wof:placetype":"venue"
},
  "geometry": {"coordinates":[-83.641507,41.039541],"type":"Point"}
}