{
  "type": "Feature",
  "properties": {
    "iso:country":"US",
    "sg:address":"309 N Greenlawn Ave",
    "sg:city":"Elida",
    "sg:classifiers":[
        {
            "category":"Retail",
            "subcategory":"Auto Repair",
            "type":"Services"
        }
    ],
    "sg:phone":"+1 419 339 1673",
    "sg:postcode":"45807",
    "sg:province":"OH",
    "sg:tags":[
        "body",
        "automobile",
        "painting",
        "roof",
        "sun"
    ],
    "wof:name":"Swickrath's Inc",
    "wof:placetype":"venue"
},
  "geometry": {"coordinates":[-84.203733,40.790521],"type":"Point"}
}