{
  "type": "Feature",
  "properties": {
    "addr:full":"11499 Chester Rd Ste 511 Cincinnati OH 45246",
    "addr:housenumber":"11499",
    "addr:postcode":"45246",
    "addr:street":"Chester Rd Ste 511",
    "iso:country":"US",
    "sg:address":"11499 Chester Rd Ste 511",
    "sg:city":"Cincinnati",
    "sg:classifiers":[
        {
            "category":"Professional",
            "subcategory":"Engineering",
            "type":"Services"
        },
        {
            "category":"Building & Trades",
            "subcategory":"Electrical",
            "type":"Services"
        },
        {
            "category":"Professional",
            "subcategory":"Management & Consulting",
            "type":"Services"
        }
    ],
    "sg:phone":"+1 513 782 0012",
    "sg:postcode":"45246",
    "sg:province":"OH",
    "sg:tags":[
        "control",
        "consultant",
        "system",
        "controls",
        "regulator",
        "environmental",
        "ecological",
        "engineer"
    ],
    "wof:name":"Gza Geoenvironmental Inc",
    "wof:placetype":"venue"
},
  "geometry": {"coordinates":[-84.443192,39.282857],"type":"Point"}
}