{
  "type": "Feature",
  "properties": {
    "addr:full": "748 US Hwy 30 Nevada OH 44849",
    "addr:housenumber": "748",
    "addr:postcode": "44849",
    "addr:street": "Us Hwy 30",
    "iso:country": "US",
    "sg:address": "748 US Hwy 30",
    "sg:city": "Nevada",
    "sg:phone": "+1 740 482 2102",
    "sg:postcode": "44849",
    "sg:province": "OH",
    "sg:tags": [
      "farm",
      "corn"
    ],
    "wof:name": "M \u0026 S Farms",
    "wof:placetype": "venue"
  },
  "geometry": {"coordinates":[-83.077775,40.839763],"type":"Point"}
}
