{
  "type": "Feature",
  "properties": {
    "addr:full":"647 Harrisburg Pike Columbus OH 43223",
    "addr:housenumber":"647",
    "addr:postcode":"43223",
    "addr:street":"Harrisburg Pike",
    "iso:country":"US",
    "sg:address":"647 Harrisburg Pike",
    "sg:city":"Columbus",
    "sg:classifiers":[
        {
            "category":"Shopping",
            "subcategory":"Used Merchandise",
            "type":"Retail Goods"
        }
    ],
    "sg:phone":"+1 614 272 6281",
    "sg:postcode":"43223",
    "sg:province":"OH",
    "wof:name":"Thrift Stores",
    "wof:placetype":"venue"
},
  "geometry": {"coordinates":[-83.036675,39.944894],"type":"Point"}
}