{
  "type": "Feature",
  "properties": {
    "addr:full":"2724 NW Lebanon Rd Dalton OH 44618",
    "addr:housenumber":"2724",
    "addr:postcode":"44618",
    "addr:street":"Nw Lebanon Rd",
    "iso:country":"US",
    "sg:address":"2724 NW Lebanon Rd",
    "sg:city":"Dalton",
    "sg:classifiers":[
        {
            "category":"Freight",
            "type":"Transportation"
        }
    ],
    "sg:phone":"+1 330 828 2244",
    "sg:postcode":"44618",
    "sg:province":"OH",
    "sg:tags":[
        "hauling",
        "trucking"
    ],
    "wof:name":"K & B Transport",
    "wof:placetype":"venue"
},
  "geometry": {"coordinates":[-81.667202,40.832831],"type":"Point"}
}