{
  "type": "Feature",
  "properties": {
    "addr:full":"65 Dayton Ave Dayton OH 45402",
    "addr:housenumber":"65",
    "addr:postcode":"45402",
    "addr:street":"Dayton Ave",
    "iso:country":"US",
    "sg:address":"65 Dayton Ave",
    "sg:city":"Dayton",
    "sg:classifiers":[
        {
            "category":"Insurance",
            "subcategory":"Insurance Agent",
            "type":"Services"
        }
    ],
    "sg:phone":"+1 937 426 2338",
    "sg:postcode":"45402",
    "sg:province":"OH",
    "wof:name":"American Family Insurance",
    "wof:placetype":"venue"
},
  "geometry": {"coordinates":[-84.208456,39.761601],"type":"Point"}
}