{
  "type": "Feature",
  "properties": {
    "addr:full": "4733 E Main St Columbus OH 43213",
    "addr:housenumber": "4733",
    "addr:postcode": "43213",
    "addr:street": "E Main St",
    "iso:country": "US",
    "sg:address": "4733 E Main St",
    "sg:city": "Columbus",
    "sg:classifiers": [
      {
        "category": "Personal",
        "subcategory": "Beauty Salon",
        "type": "Services"
      }
    ],
    "sg:phone": "+1 614 864 6245",
    "sg:postcode": "43213",
    "sg:province": "OH",
    "sg:tags": [
      "manicuring"
    ],
    "wof:name": "T's Nails",
    "wof:placetype": "venue"
  },
  "geometry": {"coordinates":[-82.872548,39.955288],"type":"Point"}
}
