{
  "type": "Feature",
  "properties": {
    "addr:full": "3223 Elida Rd Lima OH 45805",
    "addr:housenumber": "3223",
    "addr:postcode": "45805",
    "addr:street": "Elida Rd",
    "iso:country": "US",
    "sg:address": "3223 Elida Rd",
    "sg:city": "Lima",
    "sg:classifiers": [
      {
        "category": "Home \u0026 Garden",
        "subcategory": "Furniture",
        "type": "Retail Goods"
      }
    ],
    "sg:phone": "+1 419 331 3131",
    "sg:postcode": "45805",
    "sg:province": "OH",
    "wof:name": "Ashley Furniture Home Store",
    "wof:placetype": "venue"
  },
  "geometry": {"coordinates":[-84.163287,40.769285],"type":"Point"}
}
