{
  "type": "Feature",
  "properties": {
    "addr:full": "3002 Hayes Ave Sandusky OH 44870",
    "addr:housenumber": "3002",
    "addr:postcode": "44870",
    "addr:street": "Hayes Ave",
    "iso:country": "US",
    "sg:address": "3002 Hayes Ave",
    "sg:city": "Sandusky",
    "sg:classifiers": [
      {
        "category": "Personal",
        "type": "Services"
      },
      {
        "category": "Retail",
        "subcategory": "Auto Repair",
        "type": "Services"
      }
    ],
    "sg:phone": "+1 419 625 7867",
    "sg:postcode": "44870",
    "sg:province": "OH",
    "sg:tags": [
      "towing"
    ],
    "wof:name": "Sidoti Automotive Inc",
    "wof:placetype": "venue"
  },
  "geometry": {"coordinates":[-82.719803,41.4226],"type":"Point"}
}
