{
  "type": "Feature",
  "properties": {
    "addr:full":"10000 Brecksville Rd Cleveland OH 44141",
    "addr:postcode":"10000;44141",
    "addr:street":"Brecksville Rd",
    "iso:country":"US",
    "sg:address":"10000 Brecksville Rd",
    "sg:city":"Cleveland",
    "sg:classifiers":[
        {
            "category":"Banks & Credit Unions",
            "subcategory":"Bank",
            "type":"Services"
        }
    ],
    "sg:phone":"+1 216 535 3270",
    "sg:postcode":"44141",
    "sg:province":"OH",
    "wof:name":"Century Federal Credit Union",
    "wof:placetype":"venue"
},
  "geometry": {"coordinates":[-81.62716899999999,41.291195],"type":"Point"}
}