{
  "type": "Feature",
  "properties": {
    "addr:full": "3479 Foskett Rd Medina OH 44256",
    "addr:housenumber": "3479",
    "addr:postcode": "44256",
    "addr:street": "Foskett Rd",
    "iso:country": "US",
    "sg:address": "3479 Foskett Rd",
    "sg:city": "Medina",
    "sg:classifiers": [
      {
        "category": "Building \u0026 Trades",
        "subcategory": "Construction",
        "type": "Services"
      }
    ],
    "sg:phone": "+1 330 725 3268",
    "sg:postcode": "44256",
    "sg:province": "OH",
    "sg:tags": [
      "excavation",
      "sanitary",
      "contractor"
    ],
    "wof:name": "Herrmann Brothers Excavating",
    "wof:placetype": "venue"
  },
  "geometry": {"coordinates":[-81.816369,41.196097],"type":"Point"}
}
