{
  "type": "Feature",
  "properties": {
    "addr:full":"734 Main St Steubenville OH 43953",
    "addr:housenumber":"734",
    "addr:postcode":"43953",
    "addr:street":"Main St",
    "iso:country":"US",
    "sg:address":"734 Main St",
    "sg:city":"Steubenville",
    "sg:classifiers":[
        {
            "category":"Real Estate",
            "subcategory":"Real Estate Agent",
            "type":"Services"
        }
    ],
    "sg:phone":"+1 740 264 7701",
    "sg:postcode":"43953",
    "sg:province":"OH",
    "wof:name":"Becker & Cole Inc",
    "wof:placetype":"venue"
},
  "geometry": {"coordinates":[-80.698638,40.374322],"type":"Point"}
}