{
  "type": "Feature",
  "properties": {
    "addr:full":"1010 Cereal Ave Hamilton IN 45013",
    "addr:housenumber":"1010",
    "addr:postcode":"45013",
    "addr:street":"Cereal Ave",
    "iso:country":"US",
    "sg:address":"1010 Cereal Ave",
    "sg:city":"Hamilton",
    "sg:classifiers":[
        {
            "category":"Professional",
            "type":"Services"
        }
    ],
    "sg:phone":"+1 513 895 0000",
    "sg:postcode":"45013",
    "sg:province":"IN",
    "sg:tags":[
        "establishment"
    ],
    "wof:name":"Dr Nassef Inc",
    "wof:placetype":"venue"
},
  "geometry": {"coordinates":[-84.573534,39.41463],"type":"Point"}
}