{
  "type": "Feature",
  "properties": {
    "addr:full":"550 Oxford State Rd Middletown OH 45044",
    "addr:housenumber":"550",
    "addr:postcode":"45044",
    "addr:street":"State Rd",
    "iso:country":"US",
    "sg:address":"550 Oxford State Rd",
    "sg:city":"Middletown",
    "sg:classifiers":[
        {
            "category":"Autos & Motor Vehicles",
            "subcategory":"Fuel & Gas Station",
            "type":"Retail Goods"
        }
    ],
    "sg:phone":"+1 513 422 3820",
    "sg:postcode":"45044",
    "sg:province":"OH",
    "sg:tags":[
        "oil"
    ],
    "wof:name":"Trenton Sunoco",
    "wof:placetype":"venue"
},
  "geometry": {"coordinates":[-84.418801,39.480948],"type":"Point"}
}