{
  "type": "Feature",
  "properties": {
    "iso:country":"US",
    "sg:address":"2221 W Park Dr",
    "sg:city":"Lorain",
    "sg:classifiers":[
        {
            "category":"Building & Trades",
            "subcategory":"Plumbing",
            "type":"Services"
        }
    ],
    "sg:phone":"+1 440 282 6816",
    "sg:postcode":"44053",
    "sg:province":"OH",
    "sg:tags":[
        "mechanical",
        "contractor"
    ],
    "wof:name":"Bay Mechanical & Electrical",
    "wof:placetype":"venue"
},
  "geometry": {"coordinates":[-82.212442,41.445726],"type":"Point"}
}