{
  "type": "Feature",
  "properties": {
    "addr:full": "2221 W Park Dr Lorain OH 44053",
    "addr:housenumber": "2221",
    "addr:postcode": "44053",
    "addr:street": "W Park Dr",
    "iso:country": "US",
    "sg:address": "2221 W Park Dr",
    "sg:city": "Lorain",
    "sg:classifiers": [
      {
        "category": "Building \u0026 Trades",
        "subcategory": "Plumbing",
        "type": "Services"
      }
    ],
    "sg:phone": "+1 440 282 6816",
    "sg:postcode": "44053",
    "sg:province": "OH",
    "sg:tags": [
      "mechanical",
      "contractor"
    ],
    "wof:name": "Bay Mechanical \u0026 Electrical",
    "wof:placetype": "venue"
  },
  "geometry": {"coordinates":[-82.212442,41.445726],"type":"Point"}
}
