{
  "type": "Feature",
  "properties": {
    "iso:country":"US",
    "sg:address":"1425 Globe St",
    "sg:city":"East Liverpool",
    "sg:classifiers":[
        {
            "category":"Shopping",
            "subcategory":"Hobbies, Toys, & Games",
            "type":"Retail Goods"
        }
    ],
    "sg:phone":"+1 330 385 2059",
    "sg:postcode":"43920",
    "sg:province":"OH",
    "sg:tags":[
        "product",
        "ceramic"
    ],
    "wof:name":"East Liverpool China",
    "wof:placetype":"venue"
},
  "geometry": {"coordinates":[-80.545045,40.635675],"type":"Point"}
}