{
  "type": "Feature",
  "properties": {
    "addr:full": "1425 Globe St East Liverpool OH 43920",
    "addr:housenumber": "1425",
    "addr:postcode": "43920",
    "addr:street": "Globe St",
    "iso:country": "US",
    "sg:address": "1425 Globe St",
    "sg:city": "East Liverpool",
    "sg:classifiers": [
      {
        "category": "Shopping",
        "subcategory": "Hobbies, Toys, \u0026 Games",
        "type": "Retail Goods"
      }
    ],
    "sg:phone": "+1 330 385 2059",
    "sg:postcode": "43920",
    "sg:province": "OH",
    "sg:tags": [
      "product",
      "ceramic"
    ],
    "wof:name": "East Liverpool China",
    "wof:placetype": "venue"
  },
  "geometry": {"coordinates":[-80.545045,40.635675],"type":"Point"}
}
