{
  "type": "Feature",
  "properties": {
    "addr:full": "636 Northland Blvd Cincinnati OH 45240",
    "addr:housenumber": "636",
    "addr:postcode": "45240",
    "addr:street": "Northland Blvd",
    "iso:country": "US",
    "sg:address": "636 Northland Blvd",
    "sg:city": "Cincinnati",
    "sg:classifiers": [
      {
        "category": "Manufacturing",
        "subcategory": "Tools \u0026 Machinery",
        "type": "Manufacturing \u0026 Wholesale Goods"
      },
      {
        "category": "Utilities",
        "subcategory": "Water",
        "type": "Services"
      },
      {
        "category": "Personal",
        "type": "Services"
      },
      {
        "category": "Building \u0026 Trades",
        "subcategory": "Cleaning \u0026 Sanitation",
        "type": "Services"
      },
      {
        "category": "Home \u0026 Garden",
        "subcategory": "Carpets \u0026 Floor Coverings",
        "type": "Retail Goods"
      }
    ],
    "sg:phone": "+1 513 825 2047",
    "sg:postcode": "45240",
    "sg:province": "OH",
    "sg:tags": [
      "control",
      "equipment",
      "counteracting",
      "emergency",
      "extraction",
      "duct",
      "cleaners-water",
      "odor",
      "damage",
      "rug",
      "polishing",
      "flood",
      "waxing",
      "restoration",
      "fire",
      "ventilation",
      "smoke",
      "remediation",
      "air",
      "mold"
    ],
    "sg:website": "https://smclean.custhelp.com/cgi-bin/smclean.cfg/php/enduser/doc_serve.php?2=DR_YP",
    "wof:name": "ServiceMaster Clean",
    "wof:placetype": "venue"
  },
  "geometry": {"coordinates":[-84.497744,39.281392],"type":"Point"}
}
