{
  "type": "Feature",
  "properties": {
    "addr:full": "864 W North St Lima OH 45801",
    "addr:housenumber": "864",
    "addr:postcode": "45801",
    "addr:street": "W North St",
    "iso:country": "US",
    "sg:address": "864 W North St",
    "sg:city": "Lima",
    "sg:classifiers": [
      {
        "category": "Manufacturing",
        "subcategory": "Food",
        "type": "Manufacturing \u0026 Wholesale Goods"
      }
    ],
    "sg:phone": "+1 419 225 5272",
    "sg:postcode": "45801",
    "sg:province": "OH",
    "sg:tags": [
      "drink",
      "soft",
      "mfg"
    ],
    "wof:name": "Vinnies Drive Thru",
    "wof:placetype": "venue"
  },
  "geometry": {"coordinates":[-84.118826,40.742757],"type":"Point"}
}
