{
  "type": "Feature",
  "properties": {
    "iso:country":"US",
    "sg:address":"7 Deerfield Ln",
    "sg:city":"Cleveland",
    "sg:classifiers":[
        {
            "category":"Real Estate",
            "subcategory":"Real Estate Operator",
            "type":"Services"
        }
    ],
    "sg:phone":"+1 216 464 8082",
    "sg:postcode":"44122",
    "sg:province":"OH",
    "sg:tags":[
        "building",
        "nonresidential"
    ],
    "wof:name":"Shegwin Falls Shopping Center",
    "wof:placetype":"venue"
},
  "geometry": {"coordinates":[-81.496163,41.489574],"type":"Point"}
}