{
  "type": "Feature",
  "properties": {
    "addr:full":"255 Mistletoe Ct Sunbury OH 43074",
    "addr:housenumber":"255",
    "addr:postcode":"43074",
    "addr:street":"Mistletoe Ct",
    "iso:country":"US",
    "sg:address":"255 Mistletoe Ct",
    "sg:city":"Sunbury",
    "sg:classifiers":[
        {
            "category":"Shopping",
            "subcategory":"Used Merchandise",
            "type":"Retail Goods"
        }
    ],
    "sg:phone":"+1 740 965 8800",
    "sg:postcode":"43074",
    "sg:province":"OH",
    "wof:name":"Sunshine Antiques",
    "wof:placetype":"venue"
},
  "geometry": {"coordinates":[-82.852615,40.239618],"type":"Point"}
}