{
  "type": "Feature",
  "properties": {
    "addr:full": "2165 Slade Rd Batavia OH 45103",
    "addr:housenumber": "2165",
    "addr:postcode": "45103",
    "addr:street": "Slade Rd",
    "iso:country": "US",
    "sg:address": "2165 Slade Rd",
    "sg:city": "Batavia",
    "sg:classifiers": [
      {
        "category": "Recreation",
        "subcategory": "Marina",
        "type": "Entertainment"
      }
    ],
    "sg:phone": "+1 513 797 7100",
    "sg:postcode": "45103",
    "sg:province": "OH",
    "sg:tags": [
      "repairing",
      "boat"
    ],
    "wof:name": "East Fork Marine LLC",
    "wof:placetype": "venue"
  },
  "geometry": {"coordinates":[-84.16912,39.02045],"type":"Point"}
}
