{
  "type": "Feature",
  "properties": {
    "addr:full": "1 Park Centre Dr Wadsworth OH 44281",
    "addr:housenumber": "1",
    "addr:postcode": "44281",
    "addr:street": "Park Centre Dr",
    "iso:country": "US",
    "sg:address": "1 Park Centre Dr",
    "sg:city": "Wadsworth",
    "sg:classifiers": [
      {
        "category": "Health Services",
        "subcategory": "Doctor",
        "type": "Services"
      }
    ],
    "sg:phone": "+1 330 336 7688",
    "sg:postcode": "44281",
    "sg:province": "OH",
    "sg:tags": [
      "physician",
      "surgeon"
    ],
    "wof:name": "Eye Care Of Medina",
    "wof:placetype": "venue"
  },
  "geometry": {"coordinates":[-81.72827,41.048304],"type":"Point"}
}
