{
  "type": "Feature",
  "properties": {
    "iso:country":"US",
    "sg:address":"2547 S 9th St",
    "sg:city":"Ironton",
    "sg:classifiers":[
        {
            "category":"Building & Trades",
            "subcategory":"Electrical",
            "type":"Services"
        }
    ],
    "sg:phone":"+1 740 532 0874",
    "sg:postcode":"45638",
    "sg:province":"OH",
    "sg:tags":[
        "electrical",
        "contractor"
    ],
    "wof:name":"Robert E Dalton",
    "wof:placetype":"venue"
},
  "geometry": {"coordinates":[-82.661664,38.517202],"type":"Point"}
}