{
  "type": "Feature",
  "properties": {
    "iso:country":"US",
    "sg:address":"1216 Starr Ave",
    "sg:city":"Toledo",
    "sg:classifiers":[
        {
            "category":"Professional",
            "subcategory":"Business Services",
            "type":"Services"
        }
    ],
    "sg:phone":"+1 419 691 5007",
    "sg:postcode":"43605",
    "sg:province":"OH",
    "sg:tags":[
        "telemarketing"
    ],
    "wof:name":"Nikki's Prepaid Legal",
    "wof:placetype":"venue"
},
  "geometry": {"coordinates":[-83.512439,41.64347],"type":"Point"}
}