{
  "type": "Feature",
  "properties": {
    "addr:full": "15549 E Liverpool Rd East Liverpool OH 43920",
    "addr:housenumber": "15549",
    "addr:postcode": "43920",
    "addr:street": "E Liverpool Rd",
    "iso:country": "US",
    "sg:address": "15549 E Liverpool Rd",
    "sg:city": "East Liverpool",
    "sg:classifiers": [
      {
        "category": "Restaurant",
        "type": "Food \u0026 Drink"
      }
    ],
    "sg:phone": "+1 330 385 8900",
    "sg:postcode": "43920",
    "sg:province": "OH",
    "sg:tags": [
      "eating"
    ],
    "wof:name": "Green Marble Coffee Shoppe",
    "wof:placetype": "venue"
  },
  "geometry": {"coordinates":[-80.606249,40.676445],"type":"Point"}
}
