{
  "type": "Feature",
  "properties": {
    "addr:full": "61 Trux St Plymouth OH 44865",
    "addr:housenumber": "61",
    "addr:postcode": "44865",
    "addr:street": "Trux St",
    "iso:country": "US",
    "sg:address": "61 Trux St",
    "sg:city": "Plymouth",
    "sg:classifiers": [
      {
        "category": "Shopping",
        "subcategory": "Used Merchandise",
        "type": "Retail Goods"
      }
    ],
    "sg:phone": "+1 419 687 2061",
    "sg:postcode": "44865",
    "sg:province": "OH",
    "wof:name": "Stitches In Time",
    "wof:placetype": "venue"
  },
  "geometry": {"coordinates":[-82.663239,40.994341],"type":"Point"}
}
