{
  "type": "Feature",
  "properties": {
    "iso:country":"US",
    "sg:address":"760 Rose Hill Rd",
    "sg:city":"Reynoldsburg",
    "sg:classifiers":[
        {
            "category":"Education",
            "subcategory":"School",
            "type":"Public Place"
        }
    ],
    "sg:phone":"+1 614 866 5148",
    "sg:postcode":"43068",
    "sg:province":"OH",
    "wof:name":"Rose Hill Elementary School",
    "wof:placetype":"venue"
},
  "geometry": {"coordinates":[-82.819506,39.968737],"type":"Point"}
}