{
  "type": "Feature",
  "properties": {
    "addr:full": "33505 Bainbridge Rd Solon OH 44139",
    "addr:housenumber": "33505",
    "addr:postcode": "44139",
    "addr:street": "Bainbridge Rd",
    "iso:country": "US",
    "sg:address": "33505 Bainbridge Rd",
    "sg:city": "Solon",
    "sg:classifiers": [
      {
        "category": "Wholesale",
        "subcategory": "Auto Parts",
        "type": "Manufacturing \u0026 Wholesale Goods"
      }
    ],
    "sg:phone": "+1 440 248 2965",
    "sg:postcode": "44139",
    "sg:province": "OH",
    "sg:tags": [
      "supply"
    ],
    "wof:name": "Carquest Solon",
    "wof:placetype": "venue"
  },
  "geometry": {"coordinates":[-81.437747,41.388395],"type":"Point"}
}
