{
  "type": "Feature",
  "properties": {
    "iso:country":"US",
    "sg:address":"33505 Bainbridge Rd",
    "sg:city":"Solon",
    "sg:classifiers":[
        {
            "category":"Wholesale",
            "subcategory":"Auto Parts",
            "type":"Manufacturing & Wholesale Goods"
        }
    ],
    "sg:phone":"+1 440 248 2965",
    "sg:postcode":"44139",
    "sg:province":"OH",
    "sg:tags":[
        "supply"
    ],
    "wof:name":"Carquest Solon",
    "wof:placetype":"venue"
},
  "geometry": {"coordinates":[-81.437747,41.388395],"type":"Point"}
}