{
  "type": "Feature",
  "properties": {
    "addr:full":"29 S Ludlow St Dayton OH 45402",
    "addr:housenumber":"29",
    "addr:postcode":"45402",
    "addr:street":"S Ludlow St",
    "iso:country":"US",
    "sg:address":"29 S Ludlow St",
    "sg:city":"Dayton",
    "sg:classifiers":[
        {
            "category":"Real Estate",
            "subcategory":"Real Estate Agent",
            "type":"Services"
        }
    ],
    "sg:phone":"+1 937 228 5638",
    "sg:postcode":"45402",
    "sg:province":"OH",
    "wof:name":"Rain & Associates",
    "wof:placetype":"venue"
},
  "geometry": {"coordinates":[-84.19338999999999,39.758221],"type":"Point"}
}