{
  "type": "Feature",
  "properties": {
    "addr:full":"155 Tri County Pkwy Cincinnati OH 45246",
    "addr:housenumber":"155",
    "addr:postcode":"45246",
    "addr:street":"Tri County Pkwy",
    "iso:country":"US",
    "sg:address":"155 Tri County Pkwy",
    "sg:city":"Cincinnati",
    "sg:classifiers":[
        {
            "category":"Professional",
            "subcategory":"Engineering",
            "type":"Services"
        }
    ],
    "sg:phone":"+1 513 771 3617",
    "sg:postcode":"45246",
    "sg:province":"OH",
    "sg:tags":[
        "engineer"
    ],
    "wof:name":"S I Group",
    "wof:placetype":"venue"
},
  "geometry": {"coordinates":[-84.475078,39.282331],"type":"Point"}
}