{
  "type": "Feature",
  "properties": {
    "addr:full":"2162 Main St Peninsula OH 44264",
    "addr:housenumber":"2162",
    "addr:postcode":"44264",
    "addr:street":"Main St",
    "iso:country":"US",
    "sg:address":"2162 Main St",
    "sg:city":"Peninsula",
    "sg:classifiers":[
        {
            "category":"Personal",
            "subcategory":"Beauty Salon",
            "type":"Services"
        }
    ],
    "sg:phone":"+1 330 359 6262",
    "sg:postcode":"44264",
    "sg:province":"OH",
    "wof:name":"Mindy's Hair Studio",
    "wof:placetype":"venue"
},
  "geometry": {"coordinates":[-81.56522099999999,41.242448],"type":"Point"}
}