{
  "type": "Feature",
  "properties": {
    "addr:full":"28100 Chagrin Blvd Beachwood OH 44122",
    "addr:housenumber":"28100",
    "addr:postcode":"44122",
    "addr:street":"Chagrin Blvd",
    "iso:country":"US",
    "sg:address":"28100 Chagrin Blvd",
    "sg:city":"Beachwood",
    "sg:classifiers":[
        {
            "category":"Arena",
            "subcategory":"Sports Club",
            "type":"Entertainment"
        }
    ],
    "sg:phone":"+1 216 595 9900",
    "sg:postcode":"44122",
    "sg:province":"OH",
    "sg:tags":[
        "martial art"
    ],
    "wof:name":"Karate For Kids",
    "wof:placetype":"venue"
},
  "geometry": {"coordinates":[-81.480003,41.4622],"type":"Point"}
}