{
  "type": "Feature",
  "properties": {
    "iso:country":"US",
    "sg:address":"55 E Long St",
    "sg:city":"Columbus",
    "sg:classifiers":[
        {
            "category":"Parking",
            "type":"Transportation"
        }
    ],
    "sg:phone":"+1 614 222 0443",
    "sg:postcode":"43215",
    "sg:province":"OH",
    "sg:tags":[
        "garage"
    ],
    "wof:name":"Allright Parking",
    "wof:placetype":"venue"
},
  "geometry": {"coordinates":[-82.999048,39.96509],"type":"Point"}
}