{
  "type": "Feature",
  "properties": {
    "iso:country":"US",
    "sg:address":"34 S Main St",
    "sg:city":"Chagrin Falls",
    "sg:classifiers":[
        {
            "category":"Banks & Credit Unions",
            "subcategory":"Bank",
            "type":"Services"
        }
    ],
    "sg:phone":"+1 440 247 5656",
    "sg:postcode":"44022",
    "sg:province":"OH",
    "sg:tags":[
        "mortgage",
        "loan",
        "broker",
        "real estate"
    ],
    "wof:name":"Federated Funding Group Llc",
    "wof:placetype":"venue"
},
  "geometry": {"coordinates":[-81.390503,41.428799],"type":"Point"}
}