{
  "type": "Feature",
  "properties": {
    "addr:full": "6430 Eastland Rd Cleveland OH 44142",
    "addr:housenumber": "6430",
    "addr:postcode": "44142",
    "addr:street": "Eastland Rd",
    "iso:country": "US",
    "sg:address": "6430 Eastland Rd",
    "sg:city": "Cleveland",
    "sg:classifiers": [
      {
        "category": "Wholesale",
        "subcategory": "Medical Equipment \u0026 Supplies",
        "type": "Manufacturing \u0026 Wholesale Goods"
      }
    ],
    "sg:phone": "+1 440 243 9905",
    "sg:postcode": "44142",
    "sg:province": "OH",
    "wof:name": "Lincare Inc",
    "wof:placetype": "venue"
  },
  "geometry": {"coordinates":[-81.842676,41.393931],"type":"Point"}
}
