{
  "type": "Feature",
  "properties": {
    "iso:country":"US",
    "sg:address":"6430 Eastland Rd",
    "sg:city":"Cleveland",
    "sg:classifiers":[
        {
            "category":"Wholesale",
            "subcategory":"Medical Equipment & Supplies",
            "type":"Manufacturing & Wholesale Goods"
        }
    ],
    "sg:phone":"+1 440 243 9905",
    "sg:postcode":"44142",
    "sg:province":"OH",
    "wof:name":"Lincare Inc",
    "wof:placetype":"venue"
},
  "geometry": {"coordinates":[-81.842676,41.393931],"type":"Point"}
}