{
  "type": "Feature",
  "properties": {
    "addr:full":"3586 Co Rd 716A Celina OH 45822",
    "addr:housenumber":"3586;716a",
    "addr:postcode":"45822",
    "addr:street":"Co Rd",
    "iso:country":"US",
    "sg:address":"3586 Co Rd 716A",
    "sg:city":"Celina",
    "sg:classifiers":[
        {
            "category":"Building & Trades",
            "subcategory":"Equipment Rental",
            "type":"Services"
        }
    ],
    "sg:phone":"+1 419 925 4100",
    "sg:postcode":"45822",
    "sg:province":"OH",
    "sg:tags":[
        "yard"
    ],
    "wof:name":"Reliable Rental Inc",
    "wof:placetype":"venue"
},
  "geometry": {"coordinates":[-84.517124,40.457826],"type":"Point"}
}