{
  "type": "Feature",
  "properties": {
    "addr:full":"2 Limited Pkwy Columbus OH 43230",
    "addr:postcode":"43230",
    "addr:street":"Pkwy",
    "iso:country":"US",
    "sg:address":"2 Limited Pkwy",
    "sg:city":"Columbus",
    "sg:classifiers":[
        {
            "category":"Shopping",
            "subcategory":"Clothing, Apparel, & Fashions",
            "type":"Retail Goods"
        }
    ],
    "sg:phone":"+1 614 415 5100",
    "sg:postcode":"43230",
    "sg:province":"OH",
    "wof:name":"Structure",
    "wof:placetype":"venue"
},
  "geometry": {"coordinates":[-82.89688099999999,40.056897],"type":"Point"}
}