{
  "type": "Feature",
  "properties": {
    "addr:full":"8462 State Rte 179 Lakeville OH 44638",
    "addr:housenumber":"8462",
    "addr:postcode":"44638",
    "addr:street":"State Rte 179",
    "iso:country":"US",
    "sg:address":"8462 State Rte 179",
    "sg:city":"Lakeville",
    "sg:classifiers":[
        {
            "category":"Utilities",
            "subcategory":"Natural Gas",
            "type":"Services"
        }
    ],
    "sg:phone":"+1 419 827 2239",
    "sg:postcode":"44638",
    "sg:province":"OH",
    "sg:tags":[
        "transmission"
    ],
    "wof:name":"Columbia Gas Transmission Corp",
    "wof:placetype":"venue"
},
  "geometry": {"coordinates":[-82.135347,40.649164],"type":"Point"}
}