{
  "type": "Feature",
  "properties": {
    "iso:country":"US",
    "sg:address":"112 E 8th St",
    "sg:city":"Lorain",
    "sg:classifiers":[
        {
            "category":"Personal",
            "subcategory":"Barber",
            "type":"Services"
        }
    ],
    "sg:phone":"+1 440 244 6428",
    "sg:postcode":"44052",
    "sg:province":"OH",
    "wof:name":"Baker's Barber Shop",
    "wof:placetype":"venue"
},
  "geometry": {"coordinates":[-82.17322900000001,41.464266],"type":"Point"}
}