{
  "type": "Feature",
  "properties": {
    "iso:country":"US",
    "sg:address":"4581 Wing Rd",
    "sg:city":"Mechanicsburg",
    "sg:classifiers":[
        {
            "category":"Organizations",
            "subcategory":"Membership Organization",
            "type":"Services"
        }
    ],
    "sg:phone":"+1 937 322 2995",
    "sg:postcode":"43044",
    "sg:province":"OH",
    "wof:name":"US Prussia Collectors of Ohio",
    "wof:placetype":"venue"
},
  "geometry": {"coordinates":[-83.543437,40.076486],"type":"Point"}
}