{
  "type": "Feature",
  "properties": {
    "addr:full": "4581 Wing Rd Mechanicsburg OH 43044",
    "addr:housenumber": "4581",
    "addr:postcode": "43044",
    "addr:street": "Wing Rd",
    "iso:country": "US",
    "sg:address": "4581 Wing Rd",
    "sg:city": "Mechanicsburg",
    "sg:classifiers": [
      {
        "category": "Organizations",
        "subcategory": "Membership Organization",
        "type": "Services"
      }
    ],
    "sg:phone": "+1 937 322 2995",
    "sg:postcode": "43044",
    "sg:province": "OH",
    "wof:name": "US Prussia Collectors of Ohio",
    "wof:placetype": "venue"
  },
  "geometry": {"coordinates":[-83.543437,40.076486],"type":"Point"}
}
