{
  "type": "Feature",
  "properties": {
    "iso:country":"US",
    "sg:address":"215 N Walnut St",
    "sg:city":"Bucyrus",
    "sg:classifiers":[
        {
            "category":"Retail",
            "subcategory":"Funeral Services",
            "type":"Services"
        }
    ],
    "sg:phone":"+1 419 562 6776",
    "sg:postcode":"44820",
    "sg:province":"OH",
    "sg:tags":[
        "director"
    ],
    "wof:name":"Munz-Pirnstill Funeral Home",
    "wof:placetype":"venue"
},
  "geometry": {"coordinates":[-82.974228,40.810808],"type":"Point"}
}