{
  "type": "Feature",
  "properties": {
    "addr:full":"250 S Civic Center Dr Columbus OH 43215",
    "addr:housenumber":"250",
    "addr:postcode":"43215",
    "addr:street":"S Civic Center Dr",
    "iso:country":"US",
    "sg:address":"250 S Civic Center Dr",
    "sg:city":"Columbus",
    "sg:classifiers":[
        {
            "category":"Government",
            "subcategory":"Office",
            "type":"Public Place"
        },
        {
            "category":"Government",
            "subcategory":"Court House",
            "type":"Public Place"
        }
    ],
    "sg:phone":"+1 614 461 0256",
    "sg:postcode":"43215",
    "sg:province":"OH",
    "sg:tags":[
        "legal"
    ],
    "sg:website":"www.sconet.state.oh.us",
    "wof:name":"Office Disciplinary Counsel",
    "wof:placetype":"venue"
},
  "geometry": {"coordinates":[-83.003238,39.956886],"type":"Point"}
}