{
  "type": "Feature",
  "properties": {
    "addr:full": "1660 Ebenezer Rd Cincinnati OH 45233",
    "addr:housenumber": "1660",
    "addr:postcode": "45233",
    "addr:street": "Ebenezer Rd",
    "iso:country": "US",
    "sg:address": "1660 Ebenezer Rd",
    "sg:city": "Cincinnati",
    "sg:classifiers": [
      {
        "category": "Retail",
        "subcategory": "Auto Repair",
        "type": "Services"
      }
    ],
    "sg:phone": "+1 513 941 1880",
    "sg:postcode": "45233",
    "sg:province": "OH",
    "sg:tags": [
      "general"
    ],
    "wof:name": "Garage The",
    "wof:placetype": "venue"
  },
  "geometry": {"coordinates":[-84.651919,39.123929],"type":"Point"}
}
