{
  "type": "Feature",
  "properties": {
    "iso:country":"US",
    "sg:address":"582 Winslow Ave",
    "sg:city":"Akron",
    "sg:classifiers":[
        {
            "category":"Building & Trades",
            "subcategory":"Construction",
            "type":"Services"
        }
    ],
    "sg:phone":"+1 330 929 4714",
    "sg:postcode":"44313",
    "sg:province":"OH",
    "sg:tags":[
        "industrial",
        "nonresidential"
    ],
    "wof:name":"Brown Development & Cnstr",
    "wof:placetype":"venue"
},
  "geometry": {"coordinates":[-81.583308,41.129574],"type":"Point"}
}