{
  "type": "Feature",
  "properties": {
    "addr:full": "254 S Grubb St Columbus OH 43215",
    "addr:housenumber": "254",
    "addr:postcode": "43215",
    "addr:street": "S Grubb St",
    "iso:country": "US",
    "sg:address": "254 S Grubb St",
    "sg:city": "Columbus",
    "sg:classifiers": [
      {
        "category": "Manufacturing",
        "subcategory": "Signs",
        "type": "Manufacturing \u0026 Wholesale Goods"
      }
    ],
    "sg:phone": "+1 614 228 6105",
    "sg:postcode": "43215",
    "sg:province": "OH",
    "wof:name": "Marathon Media",
    "wof:placetype": "venue"
  },
  "geometry": {"coordinates":[-83.016497,39.954745],"type":"Point"}
}
