{
  "type": "Feature",
  "properties": {
    "addr:full":"4754 Co Rd 36 Chesapeake OH 45619",
    "addr:housenumber":"4754;36",
    "addr:postcode":"45619",
    "addr:street":"Co Rd",
    "iso:country":"US",
    "sg:address":"4754 Co Rd 36",
    "sg:city":"Chesapeake",
    "sg:phone":"+1 740 867 5660",
    "sg:postcode":"45619",
    "sg:province":"OH",
    "sg:tags":[
        "beef",
        "farm",
        "crop",
        "field",
        "cattle",
        "feedlot"
    ],
    "wof:name":"Jim Mayberry",
    "wof:placetype":"venue"
},
  "geometry": {"coordinates":[-82.431248,38.545296],"type":"Point"}
}