{
  "type": "Feature",
  "properties": {
    "addr:full":"19200 Young Rd Guysville OH 45735",
    "addr:housenumber":"19200",
    "addr:postcode":"45735",
    "addr:street":"Young Rd",
    "iso:country":"US",
    "sg:address":"19200 Young Rd",
    "sg:city":"Guysville",
    "sg:classifiers":[
        {
            "category":"Freight",
            "type":"Transportation"
        }
    ],
    "sg:phone":"+1 740 662 3213",
    "sg:postcode":"45735",
    "sg:province":"OH",
    "sg:tags":[
        "mobile",
        "home"
    ],
    "wof:name":"Don's Excavating & Sanitation",
    "wof:placetype":"venue"
},
  "geometry": {"coordinates":[-81.927538,39.237643],"type":"Point"}
}