{
  "type": "Feature",
  "properties": {
    "addr:full": "128 Perry St Sandusky OH 44870",
    "addr:housenumber": "128",
    "addr:postcode": "44870",
    "addr:street": "Perry St",
    "iso:country": "US",
    "sg:address": "128 Perry St",
    "sg:city": "Sandusky",
    "sg:classifiers": [
      {
        "category": "Professional",
        "type": "Services"
      }
    ],
    "sg:phone": "+1 419 625 9927",
    "sg:postcode": "44870",
    "sg:province": "OH",
    "wof:name": "Barbara A Hemphill",
    "wof:placetype": "venue"
  },
  "geometry": {"coordinates":[-82.704546,41.460147],"type":"Point"}
}
