{
  "type": "Feature",
  "properties": {
    "iso:country":"US",
    "sg:address":"2211 Marengo St",
    "sg:city":"Toledo",
    "sg:classifiers":[
        {
            "category":"Wholesale",
            "subcategory":"Vending Machines",
            "type":"Manufacturing & Wholesale Goods"
        }
    ],
    "sg:phone":"+1 419 382 5770",
    "sg:postcode":"43614",
    "sg:province":"OH",
    "sg:tags":[
        "operator"
    ],
    "wof:name":"Weight Machines Vinsko Inc",
    "wof:placetype":"venue"
},
  "geometry": {"coordinates":[-83.598641,41.606338],"type":"Point"}
}