{
  "type": "Feature",
  "properties": {
    "addr:full": "19701 S Miles Rd Cleveland OH 44128",
    "addr:housenumber": "19701",
    "addr:postcode": "44128",
    "addr:street": "S Miles Rd",
    "iso:country": "US",
    "sg:address": "19701 S Miles Rd",
    "sg:city": "Cleveland",
    "sg:classifiers": [
      {
        "category": "Shopping",
        "subcategory": "Computers \u0026 Home Electronics",
        "type": "Retail Goods"
      }
    ],
    "sg:phone": "+1 216 663 7141",
    "sg:postcode": "44128",
    "sg:province": "OH",
    "sg:tags": [
      "equipment",
      "dealer"
    ],
    "wof:name": "Reclaimed Assets Warehouse",
    "wof:placetype": "venue"
  },
  "geometry": {"coordinates":[-81.551865,41.433612],"type":"Point"}
}
