{
  "type": "Feature",
  "properties": {
    "addr:full": "56260 Davis Rd Bellaire OH 43906",
    "addr:housenumber": "56260",
    "addr:postcode": "43906",
    "addr:street": "Davis Rd",
    "iso:country": "US",
    "sg:address": "56260 Davis Rd",
    "sg:city": "Bellaire",
    "sg:classifiers": [
      {
        "category": "Real Estate",
        "subcategory": "Real Estate Operator",
        "type": "Services"
      }
    ],
    "sg:phone": "+1 740 676 6393",
    "sg:postcode": "43906",
    "sg:province": "OH",
    "sg:tags": [
      "property",
      "lessor"
    ],
    "wof:name": "Thomas Arthur",
    "wof:placetype": "venue"
  },
  "geometry": {"coordinates":[-80.766168,39.996527],"type":"Point"}
}
