{
  "type": "Feature",
  "properties": {
    "addr:full": "2616 South St SE Warren OH 44483",
    "addr:housenumber": "2616",
    "addr:postcode": "44483",
    "addr:street": "South St Se",
    "iso:country": "US",
    "sg:address": "2616 South St SE",
    "sg:city": "Warren",
    "sg:classifiers": [
      {
        "category": "Personal",
        "subcategory": "Beauty Salon",
        "type": "Services"
      }
    ],
    "sg:phone": "+1 330 394 7772",
    "sg:postcode": "44483",
    "sg:province": "OH",
    "sg:tags": [
      "shop"
    ],
    "wof:name": "Hair Inspirations",
    "wof:placetype": "venue"
  },
  "geometry": {"coordinates":[-80.785137,41.23441],"type":"Point"}
}
