{
  "type": "Feature",
  "properties": {
    "iso:country":"US",
    "sg:address":"2616 South St SE",
    "sg:city":"Warren",
    "sg:classifiers":[
        {
            "category":"Personal",
            "subcategory":"Beauty Salon",
            "type":"Services"
        }
    ],
    "sg:phone":"+1 330 394 7772",
    "sg:postcode":"44483",
    "sg:province":"OH",
    "sg:tags":[
        "shop"
    ],
    "wof:name":"Hair Inspirations",
    "wof:placetype":"venue"
},
  "geometry": {"coordinates":[-80.785137,41.23441],"type":"Point"}
}