{
  "type": "Feature",
  "properties": {
    "addr:full": "2586 Billingsley Rd Columbus OH 43235",
    "addr:housenumber": "2586",
    "addr:postcode": "43235",
    "addr:street": "Billingsley Rd",
    "iso:country": "US",
    "sg:address": "2586 Billingsley Rd",
    "sg:city": "Columbus",
    "sg:classifiers": [
      {
        "category": "Professional",
        "type": "Services"
      }
    ],
    "sg:phone": "+1 614 798 5165",
    "sg:postcode": "43235",
    "sg:province": "OH",
    "sg:tags": [
      "establishment"
    ],
    "wof:name": "J B Squared",
    "wof:placetype": "venue"
  },
  "geometry": {"coordinates":[-83.083971,40.112465],"type":"Point"}
}
