{
  "type": "Feature",
  "properties": {
    "iso:country":"US",
    "sg:address":"216 Jefferson St",
    "sg:city":"Greenfield",
    "sg:classifiers":[
        {
            "category":"Restaurant",
            "type":"Food & Drink"
        }
    ],
    "sg:phone":"+1 937 981 5300",
    "sg:postcode":"45123",
    "sg:province":"OH",
    "sg:tags":[
        "eating"
    ],
    "wof:name":"Fortune Wok",
    "wof:placetype":"venue"
},
  "geometry": {"coordinates":[-83.38133500000001,39.351858],"type":"Point"}
}