{
  "type": "Feature",
  "properties": {
    "addr:full": "216 Jefferson St Greenfield OH 45123",
    "addr:housenumber": "216",
    "addr:postcode": "45123",
    "addr:street": "Jefferson St",
    "iso:country": "US",
    "sg:address": "216 Jefferson St",
    "sg:city": "Greenfield",
    "sg:classifiers": [
      {
        "category": "Restaurant",
        "type": "Food \u0026 Drink"
      }
    ],
    "sg:phone": "+1 937 981 5300",
    "sg:postcode": "45123",
    "sg:province": "OH",
    "sg:tags": [
      "eating"
    ],
    "wof:name": "Fortune Wok",
    "wof:placetype": "venue"
  },
  "geometry": {"coordinates":[-83.381335,39.351858],"type":"Point"}
}
