{
  "type": "Feature",
  "properties": {
    "addr:full":"6293 Co Hwy 30 Upper Sandusky OH 43338",
    "addr:housenumber":"6293",
    "addr:postcode":"43338",
    "addr:street":"Co Hwy 30 Upper",
    "iso:country":"US",
    "sg:address":"6293 Co Hwy 30",
    "sg:city":"Upper Sandusky",
    "sg:classifiers":[
        {
            "category":"Freight",
            "type":"Transportation"
        }
    ],
    "sg:phone":"+1 419 294 5728",
    "sg:postcode":"43338",
    "sg:province":"OH",
    "sg:tags":[
        "trucking"
    ],
    "wof:name":"Con-Way Central Express",
    "wof:placetype":"venue"
},
  "geometry": {"coordinates":[-82.842975,40.584234],"type":"Point"}
}