{
  "type": "Feature",
  "properties": {
    "addr:full": "23499 Co Rd 7 Alvada OH 44802",
    "addr:housenumber": "23499",
    "addr:postcode": "44802",
    "addr:street": "Co Rd 7",
    "iso:country": "US",
    "sg:address": "23499 Co Rd 7",
    "sg:city": "Alvada",
    "sg:phone": "+1 419 387 7418",
    "sg:postcode": "44802",
    "sg:province": "OH",
    "sg:tags": [
      "farm",
      "corn",
      "wheat",
      "soybean"
    ],
    "wof:name": "Laura Breece Farm",
    "wof:placetype": "venue"
  },
  "geometry": {"coordinates":[-83.431461,41.029963],"type":"Point"}
}
