{
  "type": "Feature",
  "properties": {
    "iso:country":"US",
    "sg:address":"10900 Euclid Ave",
    "sg:city":"Cleveland",
    "sg:classifiers":[
        {
            "category":"Education",
            "subcategory":"College",
            "type":"Public Place"
        }
    ],
    "sg:phone":"+1 216 368 2460",
    "sg:postcode":"44106",
    "sg:province":"OH",
    "wof:name":"Case Western School Dentistry",
    "wof:placetype":"venue"
},
  "geometry": {"coordinates":[-81.609027,41.505931],"type":"Point"}
}