{
  "type": "Feature",
  "properties": {
    "addr:full": "798 S State St Westerville OH 43081",
    "addr:housenumber": "798",
    "addr:postcode": "43081",
    "addr:street": "S State St",
    "iso:country": "US",
    "sg:address": "798 S State St",
    "sg:city": "Westerville",
    "sg:classifiers": [
      {
        "category": "Retail",
        "subcategory": "Auto Repair",
        "type": "Services"
      }
    ],
    "sg:phone": "+1 614 882 9121",
    "sg:postcode": "43081",
    "sg:province": "OH",
    "sg:tags": [
      "automotive"
    ],
    "wof:name": "Procare Auto Svc Solutions LLC",
    "wof:placetype": "venue"
  },
  "geometry": {"coordinates":[-82.924844,40.106015],"type":"Point"}
}
