{
  "type": "Feature",
  "properties": {
    "addr:full":"117 E Main St Chillicothe OH 45601",
    "addr:housenumber":"117",
    "addr:postcode":"45601",
    "addr:street":"E Main St",
    "iso:country":"US",
    "sg:address":"117 E Main St",
    "sg:city":"Chillicothe",
    "sg:classifiers":[
        {
            "category":"Food & Beverages",
            "subcategory":"Bakery",
            "type":"Retail Goods"
        }
    ],
    "sg:phone":"+1 740 634 2700",
    "sg:postcode":"45601",
    "sg:province":"OH",
    "sg:tags":[
        "baker"
    ],
    "wof:name":"Benner Block Bakery",
    "wof:placetype":"venue"
},
  "geometry": {"coordinates":[-82.97638999999999,39.334118],"type":"Point"}
}