{
  "type": "Feature",
  "properties": {
    "addr:full":"200 E 2nd St Salem OH 44460",
    "addr:housenumber":"200",
    "addr:postcode":"44460",
    "addr:street":"E 2Nd St",
    "iso:country":"US",
    "sg:address":"200 E 2nd St",
    "sg:city":"Salem",
    "sg:classifiers":[
        {
            "category":"Professional",
            "subcategory":"Employment Agencies",
            "type":"Services"
        }
    ],
    "sg:phone":"+1 330 337 1200",
    "sg:postcode":"44460",
    "sg:province":"OH",
    "sg:tags":[
        "opportunity",
        "help",
        "contractor"
    ],
    "wof:name":"Employ Temps Staffing Agency",
    "wof:placetype":"venue"
},
  "geometry": {"coordinates":[-80.855357,40.902103],"type":"Point"}
}