{
  "type": "Feature",
  "properties": {
    "iso:country":"US",
    "sg:address":"839 E 5th St",
    "sg:city":"Marysville",
    "sg:classifiers":[
        {
            "category":"Home & Garden",
            "subcategory":"Household Appliances",
            "type":"Retail Goods"
        }
    ],
    "sg:phone":"+1 937 644 1112",
    "sg:postcode":"43040",
    "sg:province":"OH",
    "wof:name":"B & R TV & Appliance",
    "wof:placetype":"venue"
},
  "geometry": {"coordinates":[-83.355802,40.235606],"type":"Point"}
}