{
  "type": "Feature",
  "properties": {
    "iso:country":"US",
    "sg:address":"14911 Snow Rd",
    "sg:city":"Cleveland",
    "sg:classifiers":[
        {
            "category":"Professional",
            "type":"Services"
        }
    ],
    "sg:phone":"+1 216 267 6332",
    "sg:postcode":"44142",
    "sg:province":"OH",
    "sg:tags":[
        "establishment"
    ],
    "wof:name":"Snapps Inc",
    "wof:placetype":"venue"
},
  "geometry": {"coordinates":[-81.804028,41.403751],"type":"Point"}
}