{
  "type": "Feature",
  "properties": {
    "addr:full":"9383 W Sprague Rd Cleveland OH 44133",
    "addr:housenumber":"9383",
    "addr:postcode":"44133",
    "addr:street":"W Sprague Rd",
    "iso:country":"US",
    "sg:address":"9383 W Sprague Rd",
    "sg:city":"Cleveland",
    "sg:classifiers":[
        {
            "category":"Shopping",
            "type":"Retail Goods"
        }
    ],
    "sg:phone":"+1 440 842 3395",
    "sg:postcode":"44133",
    "sg:province":"OH",
    "sg:tags":[
        "pet",
        "shop"
    ],
    "wof:name":"Feathers & Friends Pet Shop",
    "wof:placetype":"venue"
},
  "geometry": {"coordinates":[-81.754537,41.350661],"type":"Point"}
}