{
  "type": "Feature",
  "properties": {
    "addr:full": "3820 Colerain Ave Cincinnati OH 45223",
    "addr:housenumber": "3820",
    "addr:postcode": "45223",
    "addr:street": "Colerain Ave",
    "iso:country": "US",
    "sg:address": "3820 Colerain Ave",
    "sg:city": "Cincinnati",
    "sg:classifiers": [
      {
        "category": "Manufacturing",
        "subcategory": "Tools \u0026 Machinery",
        "type": "Manufacturing \u0026 Wholesale Goods"
      }
    ],
    "sg:phone": "+1 513 681 2420",
    "sg:postcode": "45223",
    "sg:province": "OH",
    "sg:tags": [
      "transformer",
      "power"
    ],
    "sg:website": "www.foster-transformer.com",
    "wof:name": "Foster Transformer Co",
    "wof:placetype": "venue"
  },
  "geometry": {"coordinates":[-84.543057,39.15588],"type":"Point"}
}
