{
  "type": "Feature",
  "properties": {
    "iso:country":"US",
    "sg:address":"9311 Scott Rd",
    "sg:city":"Edgerton",
    "sg:classifiers":[
        {
            "category":"Manufacturing",
            "subcategory":"Tools & Machinery",
            "type":"Manufacturing & Wholesale Goods"
        }
    ],
    "sg:phone":"+1 419 658 2695",
    "sg:postcode":"43517",
    "sg:province":"OH",
    "sg:tags":[
        "machine",
        "shop"
    ],
    "wof:name":"Gates Medical Inc",
    "wof:placetype":"venue"
},
  "geometry": {"coordinates":[-84.64547899999999,41.412386],"type":"Point"}
}