{
  "type": "Feature",
  "properties": {
    "addr:full": "9311 Scott Rd Edgerton OH 43517",
    "addr:housenumber": "9311",
    "addr:postcode": "43517",
    "addr:street": "Scott Rd",
    "iso:country": "US",
    "sg:address": "9311 Scott Rd",
    "sg:city": "Edgerton",
    "sg:classifiers": [
      {
        "category": "Manufacturing",
        "subcategory": "Tools \u0026 Machinery",
        "type": "Manufacturing \u0026 Wholesale Goods"
      }
    ],
    "sg:phone": "+1 419 658 2695",
    "sg:postcode": "43517",
    "sg:province": "OH",
    "sg:tags": [
      "machine",
      "shop"
    ],
    "wof:name": "Gates Medical Inc",
    "wof:placetype": "venue"
  },
  "geometry": {"coordinates":[-84.645479,41.412386],"type":"Point"}
}
