{
  "type": "Feature",
  "properties": {
    "addr:full": "5555 Youngstown Warren Rd Niles OH 44446",
    "addr:housenumber": "5555",
    "addr:postcode": "44446",
    "addr:street": "Youngstown Warren Rd",
    "iso:country": "US",
    "sg:address": "5555 Youngstown Warren Rd",
    "sg:city": "Niles",
    "sg:classifiers": [
      {
        "category": "Shopping",
        "subcategory": "Jewelry",
        "type": "Retail Goods"
      }
    ],
    "sg:phone": "+1 330 544 8791",
    "sg:postcode": "44446",
    "sg:province": "OH",
    "sg:tags": [
      "jeweler"
    ],
    "wof:name": "Alvin's Jewelers",
    "wof:placetype": "venue"
  },
  "geometry": {"coordinates":[-80.750489,41.210417],"type":"Point"}
}
