{
  "type": "Feature",
  "properties": {
    "addr:full": "1260 S County Line Rd Johnstown OH 43074",
    "addr:housenumber": "1260",
    "addr:postcode": "43074",
    "addr:street": "S County Line Rd",
    "iso:country": "US",
    "sg:address": "1260 S County Line Rd",
    "sg:city": "Johnstown",
    "sg:classifiers": [
      {
        "category": "Professional",
        "type": "Services"
      }
    ],
    "sg:phone": "+1 740 966 5954",
    "sg:postcode": "43074",
    "sg:province": "OH",
    "wof:name": "Larry McClary",
    "wof:placetype": "venue"
  },
  "geometry": {"coordinates":[-82.757627,40.181438],"type":"Point"}
}
