{
  "type": "Feature",
  "properties": {
    "addr:full": "466 Dehan Rd Wilmington OH 45177",
    "addr:housenumber": "466",
    "addr:postcode": "45177",
    "addr:street": "Dehan Rd",
    "iso:country": "US",
    "sg:address": "466 Dehan Rd",
    "sg:city": "Wilmington",
    "sg:classifiers": [
      {
        "category": "Building \u0026 Trades",
        "subcategory": "Construction",
        "type": "Services"
      }
    ],
    "sg:phone": "+1 937 382 1994",
    "sg:postcode": "45177",
    "sg:province": "OH",
    "sg:tags": [
      "excavating",
      "contractor"
    ],
    "wof:name": "Lamb's Excavating \u0026 Equipment",
    "wof:placetype": "venue"
  },
  "geometry": {"coordinates":[-83.738551,39.412067],"type":"Point"}
}
