{
  "type": "Feature",
  "properties": {
    "addr:full":"6728 Hyland Croy Rd Dublin OH 43016",
    "addr:housenumber":"6728",
    "addr:postcode":"43016",
    "addr:street":"Hyland Croy Rd",
    "iso:country":"US",
    "sg:address":"6728 Hyland Croy Rd",
    "sg:city":"Dublin",
    "sg:classifiers":[
        {
            "category":"Professional",
            "type":"Services"
        }
    ],
    "sg:phone":"+1 614 766 1900",
    "sg:postcode":"43016",
    "sg:province":"OH",
    "wof:name":"Custom Misc Metals",
    "wof:placetype":"venue"
},
  "geometry": {"coordinates":[-83.176058,40.106257],"type":"Point"}
}