{
  "type": "Feature",
  "properties": {
    "addr:full":"1730 Columbus Ave Niles OH 44446",
    "addr:housenumber":"1730",
    "addr:postcode":"44446",
    "addr:street":"Columbus Ave",
    "iso:country":"US",
    "sg:address":"1730 Columbus Ave",
    "sg:city":"Niles",
    "sg:classifiers":[
        {
            "category":"Building & Trades",
            "subcategory":"Landscaping Services",
            "type":"Services"
        },
        {
            "category":"Building & Trades",
            "subcategory":"Construction",
            "type":"Services"
        }
    ],
    "sg:phone":"+1 330 652 1299",
    "sg:postcode":"44446",
    "sg:province":"OH",
    "sg:tags":[
        "marking",
        "lot",
        "excavation",
        "snow",
        "contractor",
        "paving",
        "maintenance",
        "parking",
        "removal",
        "driveway"
    ],
    "sg:website":"http://www.carlspaving.com",
    "wof:name":"Carl's Paving",
    "wof:placetype":"venue"
},
  "geometry": {"coordinates":[-80.770279,41.19643],"type":"Point"}
}