{
  "type": "Feature",
  "properties": {
    "iso:country":"US",
    "sg:address":"1687 Timber Ct",
    "sg:city":"Niles",
    "sg:classifiers":[
        {
            "category":"Personal",
            "subcategory":"Beauty Salon",
            "type":"Services"
        }
    ],
    "sg:phone":"+1 330 544 6461",
    "sg:postcode":"44446",
    "sg:province":"OH",
    "wof:name":"Fran-Tastic Hair",
    "wof:placetype":"venue"
},
  "geometry": {"coordinates":[-80.732966,41.17958],"type":"Point"}
}