{
  "type": "Feature",
  "properties": {
    "addr:full": "129 N Fulton St Wauseon OH 43567",
    "addr:housenumber": "129",
    "addr:postcode": "43567",
    "addr:street": "N Fulton St",
    "iso:country": "US",
    "sg:address": "129 N Fulton St",
    "sg:city": "Wauseon",
    "sg:classifiers": [
      {
        "category": "Home \u0026 Garden",
        "subcategory": "Household Appliances",
        "type": "Retail Goods"
      }
    ],
    "sg:phone": "+1 419 335 5971",
    "sg:postcode": "43567",
    "sg:province": "OH",
    "sg:tags": [
      "television",
      "stereo"
    ],
    "wof:name": "Ohio Radiant Floor",
    "wof:placetype": "venue"
  },
  "geometry": {"coordinates":[-84.141537,41.548879],"type":"Point"}
}
