{
  "type": "Feature",
  "properties": {
    "addr:full": "214 W Franklin St Kenton OH 43326",
    "addr:housenumber": "214",
    "addr:postcode": "43326",
    "addr:street": "W Franklin St",
    "iso:country": "US",
    "sg:address": "214 W Franklin St",
    "sg:city": "Kenton",
    "sg:classifiers": [
      {
        "category": "Restaurant",
        "type": "Food \u0026 Drink"
      }
    ],
    "sg:phone": "+1 419 673 1174",
    "sg:postcode": "43326",
    "sg:province": "OH",
    "sg:tags": [
      "drinking",
      "eating"
    ],
    "wof:name": "Varsity Restaurant \u0026 Bar",
    "wof:placetype": "venue"
  },
  "geometry": {"coordinates":[-83.610407,40.647313],"type":"Point"}
}
