{
  "type": "Feature",
  "properties": {
    "iso:country":"US",
    "sg:address":"214 W Franklin St",
    "sg:city":"Kenton",
    "sg:classifiers":[
        {
            "category":"Restaurant",
            "type":"Food & Drink"
        }
    ],
    "sg:phone":"+1 419 673 1174",
    "sg:postcode":"43326",
    "sg:province":"OH",
    "sg:tags":[
        "drinking",
        "eating"
    ],
    "wof:name":"Varsity Restaurant & Bar",
    "wof:placetype":"venue"
},
  "geometry": {"coordinates":[-83.610407,40.647313],"type":"Point"}
}