{
  "type": "Feature",
  "properties": {
    "addr:full": "2154 2nd St SE Canton OH 44707",
    "addr:housenumber": "2154",
    "addr:postcode": "44707",
    "addr:street": "2Nd St Se",
    "iso:country": "US",
    "sg:address": "2154 2nd St SE",
    "sg:city": "Canton",
    "sg:classifiers": [
      {
        "category": "Shopping",
        "subcategory": "Discount \u0026 Variety Stores",
        "type": "Retail Goods"
      }
    ],
    "sg:phone": "+1 330 456 0078",
    "sg:postcode": "44707",
    "sg:province": "OH",
    "sg:tags": [
      "merchandise",
      "general"
    ],
    "wof:name": "Pride Enterprise",
    "wof:placetype": "venue"
  },
  "geometry": {"coordinates":[-81.347181,40.79215],"type":"Point"}
}
