{
  "type": "Feature",
  "properties": {
    "iso:country":"US",
    "sg:address":"2154 2nd St SE",
    "sg:city":"Canton",
    "sg:classifiers":[
        {
            "category":"Shopping",
            "subcategory":"Discount & Variety Stores",
            "type":"Retail Goods"
        }
    ],
    "sg:phone":"+1 330 456 0078",
    "sg:postcode":"44707",
    "sg:province":"OH",
    "sg:tags":[
        "merchandise",
        "general"
    ],
    "wof:name":"Pride Enterprise",
    "wof:placetype":"venue"
},
  "geometry": {"coordinates":[-81.34718100000001,40.79215],"type":"Point"}
}