{
  "type": "Feature",
  "properties": {
    "addr:full": "300 Walnut Ave NE Canton OH 44702",
    "addr:housenumber": "300",
    "addr:postcode": "44702",
    "addr:street": "Walnut Ave Ne",
    "iso:country": "US",
    "sg:address": "300 Walnut Ave NE",
    "sg:city": "Canton",
    "sg:classifiers": [
      {
        "category": "Organizations",
        "subcategory": "Religious Organization",
        "type": "Services"
      }
    ],
    "sg:phone": "+1 330 456 3213",
    "sg:postcode": "44702",
    "sg:province": "OH",
    "sg:tags": [
      "church"
    ],
    "wof:name": "Open Door Chapel",
    "wof:placetype": "venue"
  },
  "geometry": {"coordinates":[-81.372176,40.800177],"type":"Point"}
}
