{
  "type": "Feature",
  "properties": {
    "iso:country":"US",
    "sg:address":"4460 Lake Forest Dr",
    "sg:city":"Cincinnati",
    "sg:classifiers":[
        {
            "category":"Shopping",
            "subcategory":"Computers & Home Electronics",
            "type":"Retail Goods"
        }
    ],
    "sg:phone":"+1 513 612 6080",
    "sg:postcode":"45242",
    "sg:province":"OH",
    "sg:tags":[
        "software"
    ],
    "wof:name":"Engyro Corp",
    "wof:placetype":"venue"
},
  "geometry": {"coordinates":[-84.38133,39.254556],"type":"Point"}
}