{
  "type": "Feature",
  "properties": {
    "addr:full": "4222 Airport Hwy Toledo OH 43615",
    "addr:housenumber": "4222",
    "addr:postcode": "43615",
    "addr:street": "Airport Hwy",
    "iso:country": "US",
    "sg:address": "4222 Airport Hwy",
    "sg:city": "Toledo",
    "sg:classifiers": [
      {
        "category": "Professional",
        "subcategory": "Accounting \u0026 Tax Preparation",
        "type": "Services"
      }
    ],
    "sg:phone": "+1 419 382 5393",
    "sg:postcode": "43615",
    "sg:province": "OH",
    "sg:tags": [
      "return",
      "filing"
    ],
    "wof:name": "Amtex Corp",
    "wof:placetype": "venue"
  },
  "geometry": {"coordinates":[-83.642461,41.620209],"type":"Point"}
}
