{
  "type": "Feature",
  "properties": {
    "iso:country":"US",
    "sg:address":"175 Montrose West Ave",
    "sg:city":"Copley",
    "sg:classifiers":[
        {
            "category":"Freight",
            "type":"Transportation"
        }
    ],
    "sg:phone":"+1 330 665 4411",
    "sg:postcode":"44321",
    "sg:province":"OH",
    "sg:tags":[
        "broker",
        "trucking"
    ],
    "sg:website":"www.transamtrans.com",
    "wof:name":"Transamerica Transportation",
    "wof:placetype":"venue"
},
  "geometry": {"coordinates":[-81.653403,41.131387],"type":"Point"}
}