{
  "type": "Feature",
  "properties": {
    "addr:full": "2211 S James Rd Columbus OH 43232",
    "addr:housenumber": "2211",
    "addr:postcode": "43232",
    "addr:street": "S James Rd",
    "iso:country": "US",
    "sg:address": "2211 S James Rd",
    "sg:city": "Columbus",
    "sg:classifiers": [
      {
        "category": "Professional",
        "subcategory": "Advertising",
        "type": "Services"
      }
    ],
    "sg:phone": "+1 614 257 7408",
    "sg:postcode": "43232",
    "sg:province": "OH",
    "sg:tags": [
      "installation",
      "display"
    ],
    "wof:name": "Quality Installation Svc",
    "wof:placetype": "venue"
  },
  "geometry": {"coordinates":[-82.920609,39.925169],"type":"Point"}
}
