{
  "type": "Feature",
  "properties": {
    "addr:full": "1640 Stubbs Mills Rd Lebanon OH 45036",
    "addr:housenumber": "1640",
    "addr:postcode": "45036",
    "addr:street": "Stubbs Mills Rd",
    "iso:country": "US",
    "sg:address": "1640 Stubbs Mills Rd",
    "sg:city": "Lebanon",
    "sg:classifiers": [
      {
        "category": "Farming",
        "subcategory": "Orchard",
        "type": "Manufacturing \u0026 Wholesale Goods"
      }
    ],
    "sg:phone": "+1 513 932 2853",
    "sg:postcode": "45036",
    "sg:province": "OH",
    "sg:tags": [
      "fruit",
      "tree"
    ],
    "sg:website": "www.ironsfruitfarm.com",
    "wof:name": "Irons Fruit Farm",
    "wof:placetype": "venue"
  },
  "geometry": {"coordinates":[-84.180022,39.408049],"type":"Point"}
}
