{
  "type": "Feature",
  "properties": {
    "addr:full": "5505 Keim Cir Columbus OH 43228",
    "addr:housenumber": "5505",
    "addr:postcode": "43228",
    "addr:street": "Keim Cir",
    "iso:country": "US",
    "sg:address": "5505 Keim Cir",
    "sg:city": "Columbus",
    "sg:classifiers": [
      {
        "category": "Travel",
        "subcategory": "Hotels \u0026 Motels",
        "type": "Entertainment"
      }
    ],
    "sg:phone": "+1 614 853 6283",
    "sg:postcode": "43228",
    "sg:province": "OH",
    "wof:name": "Kdm \u0026 Assoc LLC",
    "wof:placetype": "venue"
  },
  "geometry": {"coordinates":[-83.152524,39.981199],"type":"Point"}
}
