{
  "type": "Feature",
  "properties": {
    "addr:full":"13162 Mahan Rd Saint Paris OH 43072",
    "addr:housenumber":"13162",
    "addr:postcode":"43072",
    "addr:street":"Mahan Rd",
    "iso:country":"US",
    "sg:address":"13162 Mahan Rd",
    "sg:city":"Saint Paris",
    "sg:phone":"+1 937 663 4817",
    "sg:postcode":"43072",
    "sg:province":"OH",
    "sg:tags":[
        "farm",
        "corn",
        "soybean"
    ],
    "wof:name":"Marcella Mahan",
    "wof:placetype":"venue"
},
  "geometry": {"coordinates":[-83.99299999999999,40.165826],"type":"Point"}
}