{
  "type": "Feature",
  "properties": {
    "addr:full":"3433 Great Western Blvd Columbus OH 43204",
    "addr:housenumber":"3433",
    "addr:postcode":"43204",
    "addr:street":"Great Western Blvd",
    "iso:country":"US",
    "sg:address":"3433 Great Western Blvd",
    "sg:city":"Columbus",
    "sg:classifiers":[
        {
            "category":"Professional",
            "subcategory":"Employment Agencies",
            "type":"Services"
        }
    ],
    "sg:phone":"+1 614 224 7041",
    "sg:postcode":"43204",
    "sg:province":"OH",
    "sg:tags":[
        "help",
        "contractor"
    ],
    "wof:name":"Minute Man",
    "wof:placetype":"venue"
},
  "geometry": {"coordinates":[-83.091132,39.95808],"type":"Point"}
}