{
  "type": "Feature",
  "properties": {
    "addr:full":"3799 Gateway Lakes Dr Grove City OH 43123",
    "addr:housenumber":"3799",
    "addr:postcode":"43123",
    "addr:street":"Gateway Lakes Dr",
    "iso:country":"US",
    "sg:address":"3799 Gateway Lakes Dr",
    "sg:city":"Grove City",
    "sg:classifiers":[
        {
            "category":"Real Estate",
            "subcategory":"Real Estate Operator",
            "type":"Services"
        }
    ],
    "sg:phone":"+1 614 801 0020",
    "sg:postcode":"43123",
    "sg:province":"OH",
    "sg:tags":[
        "building",
        "apartment"
    ],
    "wof:name":"Gateway Lakes",
    "wof:placetype":"venue"
},
  "geometry": {"coordinates":[-83.04592700000001,39.882183],"type":"Point"}
}