{
  "type": "Feature",
  "properties": {
    "iso:country":"US",
    "sg:address":"5545 3rd St",
    "sg:city":"Portsmouth",
    "sg:classifiers":[
        {
            "category":"Banks & Credit Unions",
            "subcategory":"Investment Brokerage",
            "type":"Services"
        }
    ],
    "sg:phone":"+1 740 455 7324",
    "sg:postcode":"45662",
    "sg:province":"OH",
    "sg:tags":[
        "advisory",
        "financial"
    ],
    "wof:name":"Raymond James Financial Svc",
    "wof:placetype":"venue"
},
  "geometry": {"coordinates":[-82.891091,38.759258],"type":"Point"}
}