{
  "type": "Feature",
  "properties": {
    "addr:full": "1028 Broad St Conneaut OH 44030",
    "addr:housenumber": "1028",
    "addr:postcode": "44030",
    "addr:street": "Broad St",
    "iso:country": "US",
    "sg:address": "1028 Broad St",
    "sg:city": "Conneaut",
    "sg:classifiers": [
      {
        "category": "Personal",
        "subcategory": "Barber",
        "type": "Services"
      }
    ],
    "sg:phone": "+1 440 593 3188",
    "sg:postcode": "44030",
    "sg:province": "OH",
    "wof:name": "Rob Todaro Hair Studio",
    "wof:placetype": "venue"
  },
  "geometry": {"coordinates":[-80.553123,41.964371],"type":"Point"}
}
