{
  "type": "Feature",
  "properties": {
    "iso:country":"US",
    "sg:address":"29847 Oregon Rd",
    "sg:city":"Perrysburg",
    "sg:classifiers":[
        {
            "category":"Real Estate",
            "subcategory":"Real Estate Agent",
            "type":"Services"
        }
    ],
    "sg:phone":"+1 419 661 9570",
    "sg:postcode":"43551",
    "sg:province":"OH",
    "wof:name":"Evergreen Apartments LLC",
    "wof:placetype":"venue"
},
  "geometry": {"coordinates":[-83.537769,41.580125],"type":"Point"}
}