{
  "type": "Feature",
  "properties": {
    "addr:full": "1001 Pike St Marietta OH 45750",
    "addr:housenumber": "1001",
    "addr:postcode": "45750",
    "addr:street": "Pike St",
    "iso:country": "US",
    "sg:address": "1001 Pike St",
    "sg:city": "Marietta",
    "sg:classifiers": [
      {
        "category": "Health Services",
        "subcategory": "Doctor",
        "type": "Services"
      }
    ],
    "sg:phone": "+1 740 376 0060",
    "sg:postcode": "45750",
    "sg:province": "OH",
    "sg:tags": [
      "physician",
      "surgeon"
    ],
    "wof:name": "Frontier Health Care",
    "wof:placetype": "venue"
  },
  "geometry": {"coordinates":[-81.412585,39.404233],"type":"Point"}
}
