{
  "type": "Feature",
  "properties": {
    "iso:country":"US",
    "sg:address":"1001 Pike St",
    "sg:city":"Marietta",
    "sg:classifiers":[
        {
            "category":"Health Services",
            "subcategory":"Doctor",
            "type":"Services"
        }
    ],
    "sg:phone":"+1 740 376 0060",
    "sg:postcode":"45750",
    "sg:province":"OH",
    "sg:tags":[
        "physician",
        "surgeon"
    ],
    "wof:name":"Frontier Health Care",
    "wof:placetype":"venue"
},
  "geometry": {"coordinates":[-81.41258500000001,39.404233],"type":"Point"}
}