{
  "type": "Feature",
  "properties": {
    "addr:full":"715 Hebron Rd Heath OH 43056",
    "addr:housenumber":"715",
    "addr:postcode":"43056",
    "addr:street":"Hebron Rd",
    "iso:country":"US",
    "sg:address":"715 Hebron Rd",
    "sg:city":"Heath",
    "sg:classifiers":[
        {
            "category":"Personal",
            "subcategory":"Beauty Salon",
            "type":"Services"
        }
    ],
    "sg:phone":"+1 740 522 3003",
    "sg:postcode":"43056",
    "sg:province":"OH",
    "sg:website":"www.greatclips.com",
    "wof:name":"Great Clips",
    "wof:placetype":"venue"
},
  "geometry": {"coordinates":[-82.436127,40.032722],"type":"Point"}
}