{
  "type": "Feature",
  "properties": {
    "addr:full": "312 Walnut St Cincinnati OH 45202",
    "addr:housenumber": "312",
    "addr:postcode": "45202",
    "addr:street": "Walnut St",
    "iso:country": "US",
    "sg:address": "312 Walnut St",
    "sg:city": "Cincinnati",
    "sg:classifiers": [
      {
        "category": "Food \u0026 Beverages",
        "subcategory": "Meat \u0026 Fish",
        "type": "Retail Goods"
      }
    ],
    "sg:phone": "+1 513 762 7607",
    "sg:postcode": "45202",
    "sg:province": "OH",
    "sg:tags": [
      "sales"
    ],
    "wof:name": "Brand MGT Solutions LLC",
    "wof:placetype": "venue"
  },
  "geometry": {"coordinates":[-84.510814,39.099463],"type":"Point"}
}
