{
  "type": "Feature",
  "properties": {
    "iso:country":"US",
    "sg:address":"1028 Circle on the Green",
    "sg:city":"Columbus",
    "sg:classifiers":[
        {
            "category":"Home & Garden",
            "subcategory":"Home Furnishings",
            "type":"Retail Goods"
        }
    ],
    "sg:phone":"+1 614 846 2700",
    "sg:postcode":"43235",
    "sg:province":"OH",
    "sg:tags":[
        "household"
    ],
    "wof:name":"Pecoa",
    "wof:placetype":"venue"
},
  "geometry": {"coordinates":[-83.04748,40.128188],"type":"Point"}
}