{
  "type": "Feature",
  "properties": {
    "addr:full":"14015 Turney Rd Maple Heights OH 44137",
    "addr:housenumber":"14015",
    "addr:postcode":"44137",
    "addr:street":"Turney Rd",
    "iso:country":"US",
    "sg:address":"14015 Turney Rd",
    "sg:city":"Maple Heights",
    "sg:classifiers":[
        {
            "category":"Building & Trades",
            "subcategory":"Electrical",
            "type":"Services"
        }
    ],
    "sg:phone":"+1 216 663 4822",
    "sg:postcode":"44137",
    "sg:province":"OH",
    "sg:tags":[
        "electrical",
        "contractor"
    ],
    "wof:name":"North Electric",
    "wof:placetype":"venue"
},
  "geometry": {"coordinates":[-81.58352499999999,41.394569],"type":"Point"}
}