{
  "type": "Feature",
  "properties": {
    "iso:country":"US",
    "sg:address":"3001 W 121st St",
    "sg:city":"Cleveland",
    "sg:classifiers":[
        {
            "category":"Building & Trades",
            "subcategory":"Landscaping Services",
            "type":"Services"
        }
    ],
    "sg:phone":"+1 216 251 0054",
    "sg:postcode":"44111",
    "sg:province":"OH",
    "sg:tags":[
        "landscape",
        "contractor"
    ],
    "wof:name":"Jack Cactus Landscaping",
    "wof:placetype":"venue"
},
  "geometry": {"coordinates":[-81.772699,41.468917],"type":"Point"}
}