{
  "type": "Feature",
  "properties": {
    "iso:country":"US",
    "sg:address":"35 N Liberty St",
    "sg:city":"Camden",
    "sg:classifiers":[
        {
            "category":"Organizations",
            "subcategory":"Religious Organization",
            "type":"Services"
        }
    ],
    "sg:phone":"+1 937 452 7291",
    "sg:postcode":"45311",
    "sg:province":"OH",
    "sg:tags":[
        "church"
    ],
    "wof:name":"First Southern Baptist Church",
    "wof:placetype":"venue"
},
  "geometry": {"coordinates":[-84.651377,39.62922],"type":"Point"}
}