{
  "type": "Feature",
  "properties": {
    "addr:full": "3218 W Sylvania Ave Toledo OH 43613",
    "addr:housenumber": "3218",
    "addr:postcode": "43613",
    "addr:street": "W Sylvania Ave",
    "iso:country": "US",
    "sg:address": "3218 W Sylvania Ave",
    "sg:city": "Toledo",
    "sg:classifiers": [
      {
        "category": "Professional",
        "type": "Services"
      }
    ],
    "sg:phone": "+1 419 474 2881",
    "sg:postcode": "43613",
    "sg:province": "OH",
    "sg:tags": [
      "establishment"
    ],
    "wof:name": "Shelly Co",
    "wof:placetype": "venue"
  },
  "geometry": {"coordinates":[-83.621508,41.691913],"type":"Point"}
}
