{
  "type": "Feature",
  "properties": {
    "addr:full":"33549 Solon Rd Solon OH 44139",
    "addr:postcode":"33549;44139",
    "addr:street":"Solon Rd",
    "iso:country":"US",
    "sg:address":"33549 Solon Rd",
    "sg:city":"Solon",
    "sg:classifiers":[
        {
            "category":"Wholesale",
            "subcategory":"Groceries",
            "type":"Manufacturing & Wholesale Goods"
        }
    ],
    "sg:phone":"+1 440 248 4550",
    "sg:postcode":"44139",
    "sg:province":"OH",
    "sg:tags":[
        "food",
        "distributor"
    ],
    "wof:name":"American Specialty Foods Inc",
    "wof:placetype":"venue"
},
  "geometry": {"coordinates":[-81.440298,41.390315],"type":"Point"}
}