{
  "type": "Feature",
  "properties": {
    "iso:country":"US",
    "sg:address":"1340 E 289th St",
    "sg:city":"Wickliffe",
    "sg:classifiers":[
        {
            "category":"Manufacturing",
            "subcategory":"Tools & Machinery",
            "type":"Manufacturing & Wholesale Goods"
        }
    ],
    "sg:phone":"+1 440 585 3300",
    "sg:postcode":"44092",
    "sg:province":"OH",
    "sg:tags":[
        "cleaner",
        "assembly",
        "vacuum"
    ],
    "wof:name":"Royal Appliance Mfg Co",
    "wof:placetype":"venue"
},
  "geometry": {"coordinates":[-81.483991,41.605521],"type":"Point"}
}