{
  "type": "Feature",
  "properties": {
    "addr:full": "665 Kenilworth Ave Sheffield Lake OH 44054",
    "addr:housenumber": "665",
    "addr:postcode": "44054",
    "addr:street": "Kenilworth Ave",
    "iso:country": "US",
    "sg:address": "665 Kenilworth Ave",
    "sg:city": "Sheffield Lake",
    "sg:classifiers": [
      {
        "category": "Professional",
        "type": "Services"
      }
    ],
    "sg:phone": "+1 440 949 8104",
    "sg:postcode": "44054",
    "sg:province": "OH",
    "wof:name": "Mia Stodolak",
    "wof:placetype": "venue"
  },
  "geometry": {"coordinates":[-82.102968,41.48935],"type":"Point"}
}
