{
  "type": "Feature",
  "properties": {
    "addr:full": "91 E Washington St Jamestown OH 45335",
    "addr:housenumber": "91",
    "addr:postcode": "45335",
    "addr:street": "E Washington St",
    "iso:country": "US",
    "sg:address": "91 E Washington St",
    "sg:city": "Jamestown",
    "sg:classifiers": [
      {
        "category": "Autos \u0026 Motor Vehicles",
        "subcategory": "Auto Supplies",
        "type": "Retail Goods"
      }
    ],
    "sg:phone": "+1 937 675 6668",
    "sg:postcode": "45335",
    "sg:province": "OH",
    "sg:tags": [
      "tire"
    ],
    "wof:name": "Hometown Tire Sales \u0026 Svc",
    "wof:placetype": "venue"
  },
  "geometry": {"coordinates":[-83.726482,39.657851],"type":"Point"}
}
