{
  "type": "Feature",
  "properties": {
    "iso:country":"US",
    "sg:address":"91 E Washington St",
    "sg:city":"Jamestown",
    "sg:classifiers":[
        {
            "category":"Autos & Motor Vehicles",
            "subcategory":"Auto Supplies",
            "type":"Retail Goods"
        }
    ],
    "sg:phone":"+1 937 675 6668",
    "sg:postcode":"45335",
    "sg:province":"OH",
    "sg:tags":[
        "tire"
    ],
    "wof:name":"Hometown Tire Sales & Svc",
    "wof:placetype":"venue"
},
  "geometry": {"coordinates":[-83.726482,39.657851],"type":"Point"}
}