{
  "type": "Feature",
  "properties": {
    "addr:full": "414 W Main St Lakeside Marblhd OH 43440",
    "addr:housenumber": "414",
    "addr:postcode": "43440",
    "addr:street": "W Main St",
    "iso:country": "US",
    "sg:address": "414 W Main St",
    "sg:city": "Lakeside Marblhd",
    "sg:classifiers": [
      {
        "category": "Shopping",
        "subcategory": "Gifts \u0026 Souvenirs",
        "type": "Retail Goods"
      }
    ],
    "sg:phone": "+1 419 798 5034",
    "sg:postcode": "43440",
    "sg:province": "OH",
    "sg:tags": [
      "shop"
    ],
    "wof:name": "Mary Pat's Crafts",
    "wof:placetype": "venue"
  },
  "geometry": {"coordinates":[-82.73074,41.540304],"type":"Point"}
}
