{
  "type": "Feature",
  "properties": {
    "addr:full":"7913 Chardon Rd Kirtland OH 44094",
    "addr:housenumber":"7913",
    "addr:postcode":"44094",
    "addr:street":"Chardon Rd",
    "iso:country":"US",
    "sg:address":"7913 Chardon Rd",
    "sg:city":"Kirtland",
    "sg:classifiers":[
        {
            "category":"Shopping",
            "type":"Retail Goods"
        },
        {
            "category":"Sports & Exercise",
            "subcategory":"Gym",
            "type":"Entertainment"
        }
    ],
    "sg:phone":"+1 440 256 4358",
    "sg:postcode":"44094",
    "sg:province":"OH",
    "sg:tags":[
        "supply",
        "bath",
        "equipment",
        "health",
        "spa",
        "whirlpool"
    ],
    "wof:name":"Spa Giene LLC",
    "wof:placetype":"venue"
},
  "geometry": {"coordinates":[-81.362647,41.583987],"type":"Point"}
}