{
  "type": "Feature",
  "properties": {
    "iso:country":"US",
    "sg:address":"314 Pioneer St",
    "sg:city":"Akron",
    "sg:classifiers":[
        {
            "category":"Restaurant",
            "type":"Food & Drink"
        }
    ],
    "sg:phone":"+1 330 798 0043",
    "sg:postcode":"44305",
    "sg:province":"OH",
    "sg:tags":[
        "eating"
    ],
    "wof:name":"Julians",
    "wof:placetype":"venue"
},
  "geometry": {"coordinates":[-81.472031,41.072943],"type":"Point"}
}