{
  "type": "Feature",
  "properties": {
    "addr:full":"137 S Main St Dayton OH 45402",
    "addr:housenumber":"137",
    "addr:postcode":"45402",
    "addr:street":"S Main St",
    "iso:country":"US",
    "sg:address":"137 S Main St",
    "sg:city":"Dayton",
    "sg:classifiers":[
        {
            "category":"Real Estate",
            "subcategory":"Real Estate Operator",
            "type":"Services"
        }
    ],
    "sg:phone":"+1 937 224 0904",
    "sg:postcode":"45402",
    "sg:province":"OH",
    "sg:tags":[
        "building",
        "nonresidential"
    ],
    "wof:name":"Remax Central Properties",
    "wof:placetype":"venue"
},
  "geometry": {"coordinates":[-84.191213,39.757401],"type":"Point"}
}