{
  "type": "Feature",
  "properties": {
    "addr:full": "5995 Bremen Rd SE Lancaster OH 43130",
    "addr:housenumber": "5995",
    "addr:postcode": "43130",
    "addr:street": "Bremen Rd Se",
    "iso:country": "US",
    "sg:address": "5995 Bremen Rd SE",
    "sg:city": "Lancaster",
    "sg:classifiers": [
      {
        "category": "Building \u0026 Trades",
        "subcategory": "Electrical",
        "type": "Services"
      }
    ],
    "sg:phone": "+1 740 569 7659",
    "sg:postcode": "43130",
    "sg:province": "OH",
    "sg:tags": [
      "electrical",
      "contractor"
    ],
    "wof:name": "Carter Bob Electrical Contg",
    "wof:placetype": "venue"
  },
  "geometry": {"coordinates":[-82.486751,39.703419],"type":"Point"}
}
