{
  "type": "Feature",
  "properties": {
    "addr:full":"18125 Sloane Ave Cleveland OH 44107",
    "addr:housenumber":"18125",
    "addr:postcode":"44107",
    "addr:street":"Sloane Ave",
    "iso:country":"US",
    "sg:address":"18125 Sloane Ave",
    "sg:city":"Cleveland",
    "sg:classifiers":[
        {
            "category":"Health Services",
            "subcategory":"Doctor",
            "type":"Services"
        }
    ],
    "sg:phone":"+1 216 221 3550",
    "sg:postcode":"44107",
    "sg:province":"OH",
    "sg:tags":[
        "dentist"
    ],
    "wof:name":"Constantine Bitounis DDS",
    "wof:placetype":"venue"
},
  "geometry": {"coordinates":[-81.82330399999999,41.486166],"type":"Point"}
}