{
  "type": "Feature",
  "properties": {
    "iso:country":"US",
    "sg:address":"4803 Whetsel Ave",
    "sg:city":"Cincinnati",
    "sg:classifiers":[
        {
            "category":"Professional",
            "type":"Services"
        }
    ],
    "sg:phone":"+1 513 272 0360",
    "sg:postcode":"45227",
    "sg:province":"OH",
    "sg:tags":[
        "establishment"
    ],
    "wof:name":"Varities",
    "wof:placetype":"venue"
},
  "geometry": {"coordinates":[-84.393285,39.159639],"type":"Point"}
}