{
  "type": "Feature",
  "properties": {
    "addr:full": "984 Severn Dr Coshocton OH 43812",
    "addr:housenumber": "984",
    "addr:postcode": "43812",
    "addr:street": "Severn Dr",
    "iso:country": "US",
    "sg:address": "984 Severn Dr",
    "sg:city": "Coshocton",
    "sg:classifiers": [
      {
        "category": "Professional",
        "type": "Services"
      }
    ],
    "sg:phone": "+1 740 622 7688",
    "sg:postcode": "43812",
    "sg:province": "OH",
    "wof:name": "Spaulding Inc",
    "wof:placetype": "venue"
  },
  "geometry": {"coordinates":[-81.839036,40.261485],"type":"Point"}
}
