{
  "type": "Feature",
  "properties": {
    "addr:full": "1900 Resor Rd Fairfield OH 45014",
    "addr:postcode": "1900;45014",
    "addr:street": "Resor Rd",
    "iso:country": "US",
    "sg:address": "1900 Resor Rd",
    "sg:city": "Fairfield",
    "sg:classifiers": [
      {
        "category": "Manufacturing",
        "subcategory": "Signs",
        "type": "Manufacturing \u0026 Wholesale Goods"
      }
    ],
    "sg:phone": "+1 513 829 3291",
    "sg:postcode": "45014",
    "sg:province": "OH",
    "sg:tags": [
      "specialty",
      "mfg"
    ],
    "wof:name": "Classic Strokes",
    "wof:placetype": "venue"
  },
  "geometry": {"coordinates":[-84.559773,39.322777],"type":"Point"}
}
