{
  "type": "Feature",
  "properties": {
    "iso:country":"US",
    "sg:address":"5714 Archmere Ave",
    "sg:city":"Cleveland",
    "sg:classifiers":[
        {
            "category":"Freight",
            "type":"Transportation"
        }
    ],
    "sg:phone":"+1 440 237 5377",
    "sg:postcode":"44144",
    "sg:province":"OH",
    "sg:tags":[
        "operator",
        "local",
        "trucking"
    ],
    "wof:name":"Friedel Trucking Co Inc",
    "wof:placetype":"venue"
},
  "geometry": {"coordinates":[-81.724692,41.426239],"type":"Point"}
}