{
  "type": "Feature",
  "properties": {
    "addr:full": "14502 Detroit Ave Lakewood OH 44107",
    "addr:housenumber": "14502",
    "addr:postcode": "44107",
    "addr:street": "Detroit Ave",
    "iso:country": "US",
    "sg:address": "14502 Detroit Ave",
    "sg:city": "Lakewood",
    "sg:classifiers": [
      {
        "category": "Organizations",
        "subcategory": "Religious Organization",
        "type": "Services"
      }
    ],
    "sg:phone": "+1 216 221 1514",
    "sg:postcode": "44107",
    "sg:province": "OH",
    "sg:tags": [
      "school",
      "nursery"
    ],
    "wof:name": "Lakewood Presbt Nurs Schl",
    "wof:placetype": "venue"
  },
  "geometry": {"coordinates":[-81.796947,41.485344],"type":"Point"}
}
