{
  "type": "Feature",
  "properties": {
    "addr:full":"4721 Cornell Rd Cincinnati OH 45241",
    "addr:housenumber":"4721",
    "addr:postcode":"45241",
    "addr:street":"Cornell Rd",
    "iso:country":"US",
    "sg:address":"4721 Cornell Rd",
    "sg:city":"Cincinnati",
    "sg:classifiers":[
        {
            "category":"Shopping",
            "subcategory":"Computers & Home Electronics",
            "type":"Retail Goods"
        }
    ],
    "sg:phone":"+1 513 489 4888",
    "sg:postcode":"45241",
    "sg:province":"OH",
    "sg:tags":[
        "software"
    ],
    "wof:name":"Tech King",
    "wof:placetype":"venue"
},
  "geometry": {"coordinates":[-84.377903,39.270471],"type":"Point"}
}