{
  "type": "Feature",
  "properties": {
    "addr:full":"3717 Pamdon Dr Barberton OH 44203",
    "addr:housenumber":"3717",
    "addr:postcode":"44203",
    "addr:street":"Pamdon Dr",
    "iso:country":"US",
    "sg:address":"3717 Pamdon Dr",
    "sg:city":"Barberton",
    "sg:classifiers":[
        {
            "category":"Building & Trades",
            "subcategory":"Landscaping Services",
            "type":"Services"
        }
    ],
    "sg:phone":"+1 330 825 6474",
    "sg:postcode":"44203",
    "sg:province":"OH",
    "wof:name":"Leonhards Lawnworks Inc",
    "wof:placetype":"venue"
},
  "geometry": {"coordinates":[-81.665491,41.033816],"type":"Point"}
}