{
  "type": "Feature",
  "properties": {
    "addr:full": "1001 Lakeside Ave E Cleveland OH 44114",
    "addr:housenumber": "1001",
    "addr:postcode": "44114",
    "addr:street": "Lakeside Ave E",
    "iso:country": "US",
    "sg:address": "1001 Lakeside Ave E",
    "sg:city": "Cleveland",
    "sg:classifiers": [
      {
        "category": "Restaurant",
        "type": "Food \u0026 Drink"
      }
    ],
    "sg:phone": "+1 216 696 8840",
    "sg:postcode": "44114",
    "sg:province": "OH",
    "wof:name": "North Point Grill",
    "wof:placetype": "venue"
  },
  "geometry": {"coordinates":[-81.691285,41.50566],"type":"Point"}
}
