{
  "type": "Feature",
  "properties": {
    "iso:country":"US",
    "sg:address":"6158 Inverurie Dr E",
    "sg:city":"Dublin",
    "sg:classifiers":[
        {
            "category":"Real Estate",
            "subcategory":"Developer",
            "type":"Services"
        }
    ],
    "sg:phone":"+1 614 336 2825",
    "sg:postcode":"43017",
    "sg:province":"OH",
    "wof:name":"Fieldstone Villages LLC",
    "wof:placetype":"venue"
},
  "geometry": {"coordinates":[-83.156526,40.14992],"type":"Point"}
}