{
  "type": "Feature",
  "properties": {
    "iso:country":"US",
    "sg:address":"3951 Hamilton Scipio Rd",
    "sg:city":"Hamilton",
    "sg:classifiers":[
        {
            "category":"Farming",
            "subcategory":"Farm",
            "type":"Manufacturing & Wholesale Goods"
        }
    ],
    "sg:phone":"+1 513 892 9903",
    "sg:postcode":"45013",
    "sg:province":"IN",
    "sg:tags":[
        "crop",
        "general"
    ],
    "wof:name":"Niederman Farms",
    "wof:placetype":"venue"
},
  "geometry": {"coordinates":[-84.689566,39.391079],"type":"Point"}
}