{
  "type": "Feature",
  "properties": {
    "iso:country":"US",
    "sg:address":"207 N Main St",
    "sg:city":"Lima",
    "sg:classifiers":[
        {
            "category":"Professional",
            "subcategory":"Accounting & Tax Preparation",
            "type":"Services"
        }
    ],
    "sg:phone":"+1 419 227 9040",
    "sg:postcode":"45801",
    "sg:province":"OH",
    "sg:tags":[
        "payroll"
    ],
    "wof:name":"Payroll Services Inc",
    "wof:placetype":"venue"
},
  "geometry": {"coordinates":[-84.105054,40.742054],"type":"Point"}
}