{
  "type": "Feature",
  "properties": {
    "addr:full": "11650 Peters Rd Tipp City OH 45371",
    "addr:housenumber": "11650",
    "addr:postcode": "45371",
    "addr:street": "Peters Rd",
    "iso:country": "US",
    "sg:address": "11650 Peters Rd",
    "sg:city": "Tipp City",
    "sg:classifiers": [
      {
        "category": "Freight",
        "type": "Transportation"
      }
    ],
    "sg:phone": "+1 937 667 2800",
    "sg:postcode": "45371",
    "sg:province": "OH",
    "sg:tags": [
      "commercial",
      "storage"
    ],
    "wof:name": "Storage Unlimited",
    "wof:placetype": "venue"
  },
  "geometry": {"coordinates":[-84.227324,39.923965],"type":"Point"}
}
