{
  "type": "Feature",
  "properties": {
    "addr:full": "27215 Wolf Rd Bay Village OH 44140",
    "addr:housenumber": "27215",
    "addr:postcode": "44140",
    "addr:street": "Wolf Rd",
    "iso:country": "US",
    "sg:address": "27215 Wolf Rd",
    "sg:city": "Bay Village",
    "sg:classifiers": [
      {
        "category": "Cinema",
        "subcategory": "Movie Rental",
        "type": "Entertainment"
      }
    ],
    "sg:phone": "+1 440 967 1212",
    "sg:postcode": "44140",
    "sg:province": "OH",
    "sg:tags": [
      "video",
      "store"
    ],
    "wof:name": "M G A Inc",
    "wof:placetype": "venue"
  },
  "geometry": {"coordinates":[-81.923083,41.484933],"type":"Point"}
}
