{
  "type": "Feature",
  "properties": {
    "addr:full":"500 S Washington St New Paris OH 45347",
    "addr:housenumber":"500",
    "addr:postcode":"45347",
    "addr:street":"S Washington St",
    "iso:country":"US",
    "sg:address":"500 S Washington St",
    "sg:city":"New Paris",
    "sg:classifiers":[
        {
            "category":"Travel",
            "subcategory":"Campground",
            "type":"Entertainment"
        }
    ],
    "sg:phone":"+1 937 437 5771",
    "sg:postcode":"45347",
    "sg:province":"OH",
    "sg:website":"www.naturalspringsresort.com",
    "wof:name":"Natural Springs Resort",
    "wof:placetype":"venue"
},
  "geometry": {"coordinates":[-84.792678,39.852561],"type":"Point"}
}