{
  "type": "Feature",
  "properties": {
    "addr:full": "71 Justin Pl Hamilton OH 45013",
    "addr:housenumber": "71",
    "addr:postcode": "45013",
    "addr:street": "Justin Pl",
    "iso:country": "US",
    "sg:address": "71 Justin Pl",
    "sg:city": "Hamilton",
    "sg:classifiers": [
      {
        "category": "Food \u0026 Beverages",
        "subcategory": "Liquor \u0026 Beverages",
        "type": "Retail Goods"
      }
    ],
    "sg:phone": "+1 513 867 8707",
    "sg:postcode": "45013",
    "sg:province": "OH",
    "sg:tags": [
      "alcoholic"
    ],
    "wof:name": "Franklin Party Supply",
    "wof:placetype": "venue"
  },
  "geometry": {"coordinates":[-84.576471,39.432481],"type":"Point"}
}
