{
  "type": "Feature",
  "properties": {
    "iso:country":"US",
    "sg:address":"7710 Euclid Ave",
    "sg:city":"Cleveland",
    "sg:classifiers":[
        {
            "category":"Organizations",
            "subcategory":"Professional Association",
            "type":"Services"
        }
    ],
    "sg:phone":"+1 216 391 2167",
    "sg:postcode":"44103",
    "sg:province":"OH",
    "sg:tags":[
        "community"
    ],
    "wof:name":"Community of Fathers & Family",
    "wof:placetype":"venue"
},
  "geometry": {"coordinates":[-81.63358599999999,41.503735],"type":"Point"}
}