{
  "type": "Feature",
  "properties": {
    "addr:full": "7710 Euclid Ave Cleveland OH 44103",
    "addr:housenumber": "7710",
    "addr:postcode": "44103",
    "addr:street": "Euclid Ave",
    "iso:country": "US",
    "sg:address": "7710 Euclid Ave",
    "sg:city": "Cleveland",
    "sg:classifiers": [
      {
        "category": "Organizations",
        "subcategory": "Professional Association",
        "type": "Services"
      }
    ],
    "sg:phone": "+1 216 391 2167",
    "sg:postcode": "44103",
    "sg:province": "OH",
    "sg:tags": [
      "community"
    ],
    "wof:name": "Community of Fathers \u0026 Family",
    "wof:placetype": "venue"
  },
  "geometry": {"coordinates":[-81.633586,41.503735],"type":"Point"}
}
