{
  "type": "Feature",
  "properties": {
    "addr:full":"4018 E 148th St Cleveland OH 44128",
    "addr:housenumber":"4018",
    "addr:postcode":"44128",
    "addr:street":"E 148Th St",
    "iso:country":"US",
    "sg:address":"4018 E 148th St",
    "sg:city":"Cleveland",
    "sg:classifiers":[
        {
            "category":"Real Estate",
            "subcategory":"Real Estate Agent",
            "type":"Services"
        }
    ],
    "sg:phone":"+1 216 295 7378",
    "sg:postcode":"44128",
    "sg:province":"OH",
    "wof:name":"DAC Property & Management",
    "wof:placetype":"venue"
},
  "geometry": {"coordinates":[-81.577572,41.450132],"type":"Point"}
}