{
  "type": "Feature",
  "properties": {
    "iso:country":"US",
    "sg:address":"64508 Slade Rd",
    "sg:city":"Cambridge",
    "sg:classifiers":[
        {
            "category":"Manufacturing",
            "subcategory":"Aerospace",
            "type":"Manufacturing & Wholesale Goods"
        }
    ],
    "sg:phone":"+1 740 432 5548",
    "sg:postcode":"43725",
    "sg:province":"OH",
    "sg:tags":[
        "aircraft",
        "mfg"
    ],
    "wof:name":"Wayne Sicard",
    "wof:placetype":"venue"
},
  "geometry": {"coordinates":[-81.466497,40.035419],"type":"Point"}
}