{
  "type": "Feature",
  "properties": {
    "addr:full": "1842 Coventry Rd Cleveland OH 44118",
    "addr:housenumber": "1842",
    "addr:postcode": "44118",
    "addr:street": "Coventry Rd",
    "iso:country": "US",
    "sg:address": "1842 Coventry Rd",
    "sg:city": "Cleveland",
    "sg:classifiers": [
      {
        "category": "Restaurant",
        "type": "Food \u0026 Drink"
      }
    ],
    "sg:menulink": "http://www.allmenus.com/oh/cleveland-heights/38116-daves-comic-subs/menu/",
    "sg:phone": "+1 216 320 0330",
    "sg:postcode": "44118",
    "sg:province": "OH",
    "sg:tags": [
      "american"
    ],
    "wof:name": "Dave's Comic Subs",
    "wof:placetype": "venue"
  },
  "geometry": {"coordinates":[-81.579976,41.509159],"type":"Point"}
}
