{
  "type": "Feature",
  "properties": {
    "addr:full": "5001 Manchester Rd Middletown OH 45042",
    "addr:housenumber": "5001",
    "addr:postcode": "45042",
    "addr:street": "Manchester Rd",
    "iso:country": "US",
    "sg:address": "5001 Manchester Rd",
    "sg:city": "Middletown",
    "sg:classifiers": [
      {
        "category": "Professional",
        "subcategory": "Management \u0026 Consulting",
        "type": "Services"
      }
    ],
    "sg:phone": "+1 513 424 7655",
    "sg:postcode": "45042",
    "sg:province": "OH",
    "sg:tags": [
      "consultant",
      "business"
    ],
    "wof:name": "Multi-National Business",
    "wof:placetype": "venue"
  },
  "geometry": {"coordinates":[-84.337182,39.524999],"type":"Point"}
}
