{
  "type": "Feature",
  "properties": {
    "iso:country":"US",
    "sg:address":"5521 Fair Ln",
    "sg:city":"Cincinnati",
    "sg:classifiers":[
        {
            "category":"Retail",
            "subcategory":"Auto Repair",
            "type":"Services"
        }
    ],
    "sg:phone":"+1 513 561 1520",
    "sg:postcode":"45227",
    "sg:province":"OH",
    "sg:tags":[
        "automotive",
        "engineering"
    ],
    "wof:name":"Surface Enhancement Tech LLC",
    "wof:placetype":"venue"
},
  "geometry": {"coordinates":[-84.403446,39.144056],"type":"Point"}
}