{
  "type": "Feature",
  "properties": {
    "addr:full":"13983 Ridge Rd North Royalton OH 44133",
    "addr:housenumber":"13983",
    "addr:postcode":"44133",
    "addr:street":"Ridge Rd",
    "iso:country":"US",
    "sg:address":"13983 Ridge Rd",
    "sg:city":"North Royalton",
    "sg:classifiers":[
        {
            "category":"Restaurant",
            "type":"Food & Drink"
        }
    ],
    "sg:menulink":"http://www.allmenus.com/oh/north-royalton/85875-zeppes-pizzeria/menu/",
    "sg:phone":"+1 440 582 5400",
    "sg:postcode":"44133",
    "sg:province":"OH",
    "sg:tags":[
        "american",
        "pizza"
    ],
    "wof:name":"Zeppe's Pizzeria",
    "wof:placetype":"venue"
},
  "geometry": {"coordinates":[-81.734167,41.313974],"type":"Point"}
}