{
  "type": "Feature",
  "properties": {
    "iso:country":"US",
    "sg:address":"1620 Poe Ave",
    "sg:city":"Akron",
    "sg:classifiers":[
        {
            "category":"Retail",
            "subcategory":"Auto Repair",
            "type":"Services"
        },
        {
            "category":"Wholesale",
            "subcategory":"Chemicals & Plastics",
            "type":"Manufacturing & Wholesale Goods"
        }
    ],
    "sg:phone":"+1 330 733 4229",
    "sg:postcode":"44306",
    "sg:province":"OH",
    "sg:tags":[
        "automobile",
        "rustproofing",
        "undercoating",
        "automotive"
    ],
    "wof:name":"Mc Clain Oil Spray",
    "wof:placetype":"venue"
},
  "geometry": {"coordinates":[-81.47152699999999,41.057429],"type":"Point"}
}