{
  "type": "Feature",
  "properties": {
    "iso:country":"US",
    "sg:address":"5138 Blazer Pkwy",
    "sg:city":"Dublin",
    "sg:classifiers":[
        {
            "category":"Health Services",
            "subcategory":"Chiropractor",
            "type":"Services"
        }
    ],
    "sg:phone":"+1 614 889 7499",
    "sg:postcode":"43017",
    "sg:province":"OH",
    "wof:name":"Dublin Chiropractic Ctr",
    "wof:placetype":"venue"
},
  "geometry": {"coordinates":[-83.128095,40.075843],"type":"Point"}
}