{
  "type": "Feature",
  "properties": {
    "addr:full": "4424 Carver Woods Dr Cincinnati OH 45242",
    "addr:housenumber": "4424",
    "addr:postcode": "45242",
    "addr:street": "Carver Woods Dr",
    "iso:country": "US",
    "sg:address": "4424 Carver Woods Dr",
    "sg:city": "Cincinnati",
    "sg:classifiers": [
      {
        "category": "Wholesale",
        "subcategory": "Stationery",
        "type": "Manufacturing \u0026 Wholesale Goods"
      }
    ],
    "sg:phone": "+1 513 936 6300",
    "sg:postcode": "45242",
    "sg:province": "OH",
    "sg:tags": [
      "packaging",
      "material"
    ],
    "wof:name": "Fort James Corp Packgng Div",
    "wof:placetype": "venue"
  },
  "geometry": {"coordinates":[-84.38666,39.245282],"type":"Point"}
}
