{
  "type": "Feature",
  "properties": {
    "addr:full":"4445 20th St NW Canton OH 44708",
    "addr:housenumber":"4445",
    "addr:postcode":"44708",
    "addr:street":"20Th St Nw",
    "iso:country":"US",
    "sg:address":"4445 20th St NW",
    "sg:city":"Canton",
    "sg:classifiers":[
        {
            "category":"Personal",
            "type":"Services"
        }
    ],
    "sg:phone":"+1 330 478 8140",
    "sg:postcode":"44708",
    "sg:province":"OH",
    "sg:tags":[
        "electrolysis"
    ],
    "wof:name":"Linda's Advanced Electrology",
    "wof:placetype":"venue"
},
  "geometry": {"coordinates":[-81.433713,40.821691],"type":"Point"}
}