{
  "type": "Feature",
  "properties": {
    "iso:country":"US",
    "sg:address":"2596 Sun Valley Rd",
    "sg:city":"Port Clinton",
    "sg:classifiers":[
        {
            "category":"Shopping",
            "subcategory":"Clothing, Apparel, & Fashions",
            "type":"Retail Goods"
        }
    ],
    "sg:phone":"+1 419 732 2911",
    "sg:postcode":"43452",
    "sg:province":"OH",
    "sg:tags":[
        "t"
    ],
    "wof:name":"Lake Erie Sports",
    "wof:placetype":"venue"
},
  "geometry": {"coordinates":[-82.872883,41.526246],"type":"Point"}
}