{
  "type": "Feature",
  "properties": {
    "addr:full": "2596 Sun Valley Rd Port Clinton OH 43452",
    "addr:housenumber": "2596",
    "addr:postcode": "43452",
    "addr:street": "Sun Valley Rd",
    "iso:country": "US",
    "sg:address": "2596 Sun Valley Rd",
    "sg:city": "Port Clinton",
    "sg:classifiers": [
      {
        "category": "Shopping",
        "subcategory": "Clothing, Apparel, \u0026 Fashions",
        "type": "Retail Goods"
      }
    ],
    "sg:phone": "+1 419 732 2911",
    "sg:postcode": "43452",
    "sg:province": "OH",
    "sg:tags": [
      "t"
    ],
    "wof:name": "Lake Erie Sports",
    "wof:placetype": "venue"
  },
  "geometry": {"coordinates":[-82.872883,41.526246],"type":"Point"}
}
