{
  "type": "Feature",
  "properties": {
    "iso:country":"US",
    "sg:address":"51 S Stanfield Rd",
    "sg:city":"Troy",
    "sg:classifiers":[
        {
            "category":"Health Services",
            "subcategory":"Chiropractor",
            "type":"Services"
        }
    ],
    "sg:phone":"+1 937 335 2722",
    "sg:postcode":"45373",
    "sg:province":"OH",
    "wof:name":"Troy Chiropractic Wellness Ctr",
    "wof:placetype":"venue"
},
  "geometry": {"coordinates":[-84.240576,40.054983],"type":"Point"}
}