{
  "type": "Feature",
  "properties": {
    "addr:full": "622 S Market St Troy OH 45373",
    "addr:housenumber": "622",
    "addr:postcode": "45373",
    "addr:street": "S Market St",
    "iso:country": "US",
    "sg:address": "622 S Market St",
    "sg:city": "Troy",
    "sg:classifiers": [
      {
        "category": "Organizations",
        "subcategory": "Community Association",
        "type": "Services"
      }
    ],
    "sg:phone": "+1 937 339 3502",
    "sg:postcode": "45373",
    "sg:province": "OH",
    "sg:tags": [
      "military"
    ],
    "wof:name": "American Legion",
    "wof:placetype": "venue"
  },
  "geometry": {"coordinates":[-84.2078,40.033822],"type":"Point"}
}
