{
  "type": "Feature",
  "properties": {
    "addr:full":"4935 State Rte 601 E Norwalk OH 44857",
    "addr:housenumber":"4935",
    "addr:postcode":"44857",
    "addr:street":"State Rte 601 E",
    "iso:country":"US",
    "sg:address":"4935 State Rte 601 E",
    "sg:city":"Norwalk",
    "sg:classifiers":[
        {
            "category":"Organizations",
            "subcategory":"Religious Organization",
            "type":"Services"
        }
    ],
    "sg:phone":"+1 419 668 7964",
    "sg:postcode":"44857",
    "sg:province":"OH",
    "wof:name":"Freedom Ministry",
    "wof:placetype":"venue"
},
  "geometry": {"coordinates":[-82.575998,41.274741],"type":"Point"}
}