{
  "type": "Feature",
  "properties": {
    "iso:country":"US",
    "sg:address":"4859 Tuscarawas St W",
    "sg:city":"Canton",
    "sg:classifiers":[
        {
            "category":"Restaurant",
            "type":"Food & Drink"
        }
    ],
    "sg:phone":"+1 330 478 1996",
    "sg:postcode":"44708",
    "sg:province":"OH",
    "wof:name":"Hanini Subs & Corn Beef",
    "wof:placetype":"venue"
},
  "geometry": {"coordinates":[-81.439555,40.79407],"type":"Point"}
}