{
  "type": "Feature",
  "properties": {
    "addr:full":"310 N Howard St Akron OH 44304",
    "addr:housenumber":"310",
    "addr:postcode":"44304",
    "addr:street":"N Howard St",
    "iso:country":"US",
    "sg:address":"310 N Howard St",
    "sg:city":"Akron",
    "sg:classifiers":[
        {
            "category":"Autos & Motor Vehicles",
            "subcategory":"Auto Supplies",
            "type":"Retail Goods"
        }
    ],
    "sg:phone":"+1 330 996 4043",
    "sg:postcode":"44304",
    "sg:province":"OH",
    "sg:tags":[
        "wheel",
        "cover"
    ],
    "wof:name":"Central Alloy Wheels",
    "wof:placetype":"venue"
},
  "geometry": {"coordinates":[-81.516029,41.093204],"type":"Point"}
}