{
  "type": "Feature",
  "properties": {
    "iso:country":"US",
    "sg:address":"21700 Miles Rd",
    "sg:city":"Cleveland",
    "sg:classifiers":[
        {
            "category":"Shopping",
            "type":"Retail Goods"
        }
    ],
    "sg:phone":"+1 216 475 3020",
    "sg:postcode":"44128",
    "sg:province":"OH",
    "sg:tags":[
        "telephone",
        "cellular"
    ],
    "wof:name":"Instant Mobile",
    "wof:placetype":"venue"
},
  "geometry": {"coordinates":[-81.530015,41.428216],"type":"Point"}
}