{
  "type": "Feature",
  "properties": {
    "addr:full": "128 Asbury Rd Cincinnati OH 45255",
    "addr:housenumber": "128",
    "addr:postcode": "45255",
    "addr:street": "Asbury Rd",
    "iso:country": "US",
    "sg:address": "128 Asbury Rd",
    "sg:city": "Cincinnati",
    "sg:classifiers": [
      {
        "category": "Professional",
        "subcategory": "Engineering",
        "type": "Services"
      }
    ],
    "sg:phone": "+1 513 624 8365",
    "sg:postcode": "45255",
    "sg:province": "OH",
    "sg:tags": [
      "engineer"
    ],
    "wof:name": "VOS Consulting",
    "wof:placetype": "venue"
  },
  "geometry": {"coordinates":[-84.35392,39.041869],"type":"Point"}
}
