{
  "type": "Feature",
  "properties": {
    "addr:full": "113 S Scioto St Circleville OH 43113",
    "addr:housenumber": "113",
    "addr:postcode": "43113",
    "addr:street": "S Scioto St",
    "iso:country": "US",
    "sg:address": "113 S Scioto St",
    "sg:city": "Circleville",
    "sg:classifiers": [
      {
        "category": "Education",
        "subcategory": "Special Training",
        "type": "Public Place"
      }
    ],
    "sg:phone": "+1 740 420 2531",
    "sg:postcode": "43113",
    "sg:province": "OH",
    "sg:tags": [
      "instruction",
      "driving"
    ],
    "wof:name": "Top Hat Driving School LTD",
    "wof:placetype": "venue"
  },
  "geometry": {"coordinates":[-82.947885,39.602602],"type":"Point"}
}
