{
  "type": "Feature",
  "properties": {
    "iso:country":"US",
    "sg:address":"6695 Promway Ave NW",
    "sg:city":"North Canton",
    "sg:classifiers":[
        {
            "category":"Retail",
            "subcategory":"Auto Repair",
            "type":"Services"
        }
    ],
    "sg:phone":"+1 330 499 7400",
    "sg:postcode":"44720",
    "sg:province":"OH",
    "sg:tags":[
        "repairing",
        "automobile"
    ],
    "wof:name":"Auto Master Automotive Svc",
    "wof:placetype":"venue"
},
  "geometry": {"coordinates":[-81.427948,40.877624],"type":"Point"}
}