{
  "type": "Feature",
  "properties": {
    "addr:full": "4200 E University Blvd Middletown OH 45042",
    "addr:housenumber": "4200",
    "addr:postcode": "45042",
    "addr:street": "E University Blvd",
    "iso:country": "US",
    "sg:address": "4200 E University Blvd",
    "sg:city": "Middletown",
    "sg:classifiers": [
      {
        "category": "Building \u0026 Trades",
        "subcategory": "Construction",
        "type": "Services"
      }
    ],
    "sg:phone": "+1 513 425 6884",
    "sg:postcode": "45042",
    "sg:province": "OH",
    "sg:tags": [
      "general",
      "contractor"
    ],
    "wof:name": "Impier Builder LLC",
    "wof:placetype": "venue"
  },
  "geometry": {"coordinates":[-84.356479,39.52728],"type":"Point"}
}
