{
  "type": "Feature",
  "properties": {
    "addr:full": "1340 Auburn Ave Barberton OH 44203",
    "addr:housenumber": "1340",
    "addr:postcode": "44203",
    "addr:street": "Auburn Ave",
    "iso:country": "US",
    "sg:address": "1340 Auburn Ave",
    "sg:city": "Barberton",
    "sg:classifiers": [
      {
        "category": "Education",
        "subcategory": "School",
        "type": "Public Place"
      }
    ],
    "sg:phone": "+1 330 848 4246",
    "sg:postcode": "44203",
    "sg:province": "OH",
    "wof:name": "Johnson Elementary School",
    "wof:placetype": "venue"
  },
  "geometry": {"coordinates":[-81.638285,41.004588],"type":"Point"}
}
