{
  "type": "Feature",
  "properties": {
    "addr:full": "650 Youngstown Warren Rd Niles OH 44446",
    "addr:housenumber": "650",
    "addr:postcode": "44446",
    "addr:street": "Youngstown Warren Rd",
    "iso:country": "US",
    "sg:address": "650 Youngstown Warren Rd",
    "sg:city": "Niles",
    "sg:classifiers": [
      {
        "category": "Health Services",
        "subcategory": "Health Practitioner",
        "type": "Services"
      }
    ],
    "sg:phone": "+1 330 505 1362",
    "sg:postcode": "44446",
    "sg:province": "OH",
    "sg:tags": [
      "therapist",
      "physical"
    ],
    "wof:name": "Healthsouth Rehabilitation Ctr",
    "wof:placetype": "venue"
  },
  "geometry": {"coordinates":[-80.72679,41.193863],"type":"Point"}
}
