{
  "type": "Feature",
  "properties": {
    "addr:full": "6016 Northcliff Ave Cleveland OH 44144",
    "addr:housenumber": "6016",
    "addr:postcode": "44144",
    "addr:street": "Northcliff Ave",
    "iso:country": "US",
    "sg:address": "6016 Northcliff Ave",
    "sg:city": "Cleveland",
    "sg:classifiers": [
      {
        "category": "Real Estate",
        "subcategory": "Real Estate Agent",
        "type": "Services"
      }
    ],
    "sg:phone": "+1 216 398 9187",
    "sg:postcode": "44144",
    "sg:province": "OH",
    "wof:name": "Veb Enterprise LLC",
    "wof:placetype": "venue"
  },
  "geometry": {"coordinates":[-81.730555,41.42501],"type":"Point"}
}
