{
  "type": "Feature",
  "properties": {
    "iso:country":"US",
    "sg:address":"491 Georgesville Rd",
    "sg:city":"Columbus",
    "sg:classifiers":[
        {
            "category":"Banks & Credit Unions",
            "subcategory":"Investment Brokerage",
            "type":"Services"
        }
    ],
    "sg:phone":"+1 614 272 8349",
    "sg:postcode":"43228",
    "sg:province":"OH",
    "wof:name":"Capital Commercial Investments",
    "wof:placetype":"venue"
},
  "geometry": {"coordinates":[-83.11175299999999,39.943253],"type":"Point"}
}