{
  "type": "Feature",
  "properties": {
    "addr:full": "491 Georgesville Rd Columbus OH 43228",
    "addr:housenumber": "491",
    "addr:postcode": "43228",
    "addr:street": "Georgesville Rd",
    "iso:country": "US",
    "sg:address": "491 Georgesville Rd",
    "sg:city": "Columbus",
    "sg:classifiers": [
      {
        "category": "Banks \u0026 Credit Unions",
        "subcategory": "Investment Brokerage",
        "type": "Services"
      }
    ],
    "sg:phone": "+1 614 272 8349",
    "sg:postcode": "43228",
    "sg:province": "OH",
    "wof:name": "Capital Commercial Investments",
    "wof:placetype": "venue"
  },
  "geometry": {"coordinates":[-83.111753,39.943253],"type":"Point"}
}
