{
  "type": "Feature",
  "properties": {
    "addr:full": "6111 Kyles Station Rd Hamilton OH 45011",
    "addr:postcode": "6111;45011",
    "addr:street": "Kyles Station Rd",
    "iso:country": "US",
    "sg:address": "6111 Kyles Station Rd",
    "sg:city": "Hamilton",
    "sg:classifiers": [
      {
        "category": "Retail",
        "subcategory": "Animal Services",
        "type": "Services"
      }
    ],
    "sg:phone": "+1 513 777 8848",
    "sg:postcode": "45011",
    "sg:province": "OH",
    "wof:name": "Hedgehurst Landscaping",
    "wof:placetype": "venue"
  },
  "geometry": {"coordinates":[-84.414168,39.416282],"type":"Point"}
}
