{
  "type": "Feature",
  "properties": {
    "addr:full": "1162 S Riverside Dr NW Mc Connelsville OH 43756",
    "addr:housenumber": "1162",
    "addr:postcode": "43756",
    "addr:street": "S Riverside Dr Nw Mc",
    "iso:country": "US",
    "sg:address": "1162 S Riverside Dr NW",
    "sg:city": "Mc Connelsville",
    "sg:classifiers": [
      {
        "category": "Professional",
        "type": "Services"
      }
    ],
    "sg:phone": "+1 740 962 3467",
    "sg:postcode": "43756",
    "sg:province": "OH",
    "wof:name": "Louis E Huck",
    "wof:placetype": "venue"
  },
  "geometry": {"coordinates":[-81.834656,39.624774],"type":"Point"}
}
