{
  "type": "Feature",
  "properties": {
    "iso:country":"US",
    "sg:address":"243 W 3rd St",
    "sg:city":"Dover",
    "sg:classifiers":[
        {
            "category":"Coffee & Tea",
            "type":"Food & Drink"
        },
        {
            "category":"Restaurant",
            "type":"Food & Drink"
        }
    ],
    "sg:menulink":"http://www.allmenus.com/oh/dover/245006-uncommon-grounds/menu/",
    "sg:phone":"+1 330 343 3178",
    "sg:postcode":"44622",
    "sg:province":"OH",
    "sg:tags":[
        "tea",
        "coffee",
        "american"
    ],
    "wof:name":"Uncommon Grounds",
    "wof:placetype":"venue"
},
  "geometry": {"coordinates":[-81.47903700000001,40.520531],"type":"Point"}
}