{
  "type": "Feature",
  "properties": {
    "addr:full": "243 W 3rd St Dover OH 44622",
    "addr:housenumber": "243",
    "addr:postcode": "44622",
    "addr:street": "W 3Rd St",
    "iso:country": "US",
    "sg:address": "243 W 3rd St",
    "sg:city": "Dover",
    "sg:classifiers": [
      {
        "category": "Coffee \u0026 Tea",
        "type": "Food \u0026 Drink"
      },
      {
        "category": "Restaurant",
        "type": "Food \u0026 Drink"
      }
    ],
    "sg:menulink": "http://www.allmenus.com/oh/dover/245006-uncommon-grounds/menu/",
    "sg:phone": "+1 330 343 3178",
    "sg:postcode": "44622",
    "sg:province": "OH",
    "sg:tags": [
      "tea",
      "coffee",
      "american"
    ],
    "wof:name": "Uncommon Grounds",
    "wof:placetype": "venue"
  },
  "geometry": {"coordinates":[-81.479037,40.520531],"type":"Point"}
}
