{
  "type": "Feature",
  "properties": {
    "addr:full": "6365 Pearl Rd Cleveland OH 44130",
    "addr:housenumber": "6365",
    "addr:postcode": "44130",
    "addr:street": "Pearl Rd",
    "iso:country": "US",
    "sg:address": "6365 Pearl Rd",
    "sg:city": "Cleveland",
    "sg:classifiers": [
      {
        "category": "Building \u0026 Trades",
        "subcategory": "Construction",
        "type": "Services"
      },
      {
        "category": "Restaurant",
        "type": "Food \u0026 Drink"
      }
    ],
    "sg:phone": "+1 440 884 2582",
    "sg:postcode": "44130",
    "sg:province": "OH",
    "sg:tags": [
      "dry wall",
      "includes",
      "paper",
      "vinyl",
      "hanging",
      "operation"
    ],
    "wof:name": "Clubhouse The",
    "wof:placetype": "venue"
  },
  "geometry": {"coordinates":[-81.767922,41.38664],"type":"Point"}
}
