{
  "type": "Feature",
  "properties": {
    "iso:country":"US",
    "sg:address":"4070 E Galbraith Rd",
    "sg:city":"Cincinnati",
    "sg:classifiers":[
        {
            "category":"Food & Beverages",
            "subcategory":"Groceries & Convenience Stores",
            "type":"Retail Goods"
        }
    ],
    "sg:phone":"+1 513 793 3390",
    "sg:postcode":"45236",
    "sg:province":"OH",
    "sg:tags":[
        "grocer"
    ],
    "wof:name":"Irvs Kosher Market & Deli",
    "wof:placetype":"venue"
},
  "geometry": {"coordinates":[-84.401133,39.208693],"type":"Point"}
}