{
  "type": "Feature",
  "properties": {
    "addr:full": "4070 E Galbraith Rd Cincinnati OH 45236",
    "addr:housenumber": "4070",
    "addr:postcode": "45236",
    "addr:street": "E Galbraith Rd",
    "iso:country": "US",
    "sg:address": "4070 E Galbraith Rd",
    "sg:city": "Cincinnati",
    "sg:classifiers": [
      {
        "category": "Food \u0026 Beverages",
        "subcategory": "Groceries \u0026 Convenience Stores",
        "type": "Retail Goods"
      }
    ],
    "sg:phone": "+1 513 793 3390",
    "sg:postcode": "45236",
    "sg:province": "OH",
    "sg:tags": [
      "grocer"
    ],
    "wof:name": "Irvs Kosher Market \u0026 Deli",
    "wof:placetype": "venue"
  },
  "geometry": {"coordinates":[-84.401133,39.208693],"type":"Point"}
}
