{
  "type": "Feature",
  "properties": {
    "addr:full": "538 N Market St Wooster OH 44691",
    "addr:housenumber": "538",
    "addr:postcode": "44691",
    "addr:street": "N Market St",
    "iso:country": "US",
    "sg:address": "538 N Market St",
    "sg:city": "Wooster",
    "sg:classifiers": [
      {
        "category": "Professional",
        "subcategory": "Engineering",
        "type": "Services"
      }
    ],
    "sg:phone": "+1 330 263 5200",
    "sg:postcode": "44691",
    "sg:province": "OH",
    "wof:name": "Engineering Department",
    "wof:placetype": "venue"
  },
  "geometry": {"coordinates":[-81.941422,40.80348],"type":"Point"}
}
