{
  "type": "Feature",
  "properties": {
    "addr:full":"1212 Dalton Ave Cincinnati OH 45203",
    "addr:housenumber":"1212",
    "addr:postcode":"45203",
    "addr:street":"Dalton Ave",
    "iso:country":"US",
    "sg:address":"1212 Dalton Ave",
    "sg:city":"Cincinnati",
    "sg:classifiers":[
        {
            "category":"Building & Trades",
            "subcategory":"Plumbing",
            "type":"Services"
        }
    ],
    "sg:phone":"+1 513 721 3616",
    "sg:postcode":"45203",
    "sg:province":"OH",
    "sg:tags":[
        "conditioning",
        "air",
        "system",
        "contractor"
    ],
    "wof:name":"Controls Center Inc",
    "wof:placetype":"venue"
},
  "geometry": {"coordinates":[-84.536395,39.1075],"type":"Point"}
}