{
  "type": "Feature",
  "properties": {
    "iso:country":"US",
    "sg:address":"130 Lafayette Rd",
    "sg:city":"Medina",
    "sg:classifiers":[
        {
            "category":"Building & Trades",
            "subcategory":"Construction",
            "type":"Services"
        }
    ],
    "sg:phone":"+1 330 659 2370",
    "sg:postcode":"44256",
    "sg:province":"OH",
    "sg:tags":[
        "designer"
    ],
    "wof:name":"Design Group",
    "wof:placetype":"venue"
},
  "geometry": {"coordinates":[-81.864465,41.134184],"type":"Point"}
}