{
  "type": "Feature",
  "properties": {
    "addr:full": "130 Lafayette Rd Medina OH 44256",
    "addr:housenumber": "130",
    "addr:postcode": "44256",
    "addr:street": "Rd",
    "iso:country": "US",
    "sg:address": "130 Lafayette Rd",
    "sg:city": "Medina",
    "sg:classifiers": [
      {
        "category": "Building \u0026 Trades",
        "subcategory": "Construction",
        "type": "Services"
      }
    ],
    "sg:phone": "+1 330 659 2370",
    "sg:postcode": "44256",
    "sg:province": "OH",
    "sg:tags": [
      "designer"
    ],
    "wof:name": "Design Group",
    "wof:placetype": "venue"
  },
  "geometry": {"coordinates":[-81.864465,41.134184],"type":"Point"}
}
