{
  "type": "Feature",
  "properties": {
    "addr:full": "9711 Lamont Ave Cleveland OH 44106",
    "addr:housenumber": "9711",
    "addr:postcode": "44106",
    "addr:street": "Lamont Ave",
    "iso:country": "US",
    "sg:address": "9711 Lamont Ave",
    "sg:city": "Cleveland",
    "sg:classifiers": [
      {
        "category": "Education",
        "subcategory": "School",
        "type": "Public Place"
      }
    ],
    "sg:phone": "+1 216 791 6120",
    "sg:postcode": "44106",
    "sg:province": "OH",
    "wof:name": "Charles Orr Academy",
    "wof:placetype": "venue"
  },
  "geometry": {"coordinates":[-81.617409,41.508788],"type":"Point"}
}
