{
  "type": "Feature",
  "properties": {
    "addr:full":"351 W Central Ave Delaware OH 43015",
    "addr:housenumber":"351",
    "addr:postcode":"43015",
    "addr:street":"W Central Ave",
    "iso:country":"US",
    "sg:address":"351 W Central Ave",
    "sg:city":"Delaware",
    "sg:classifiers":[
        {
            "category":"Banks & Credit Unions",
            "subcategory":"Bank",
            "type":"Services"
        }
    ],
    "sg:phone":"+1 740 362 2296",
    "sg:postcode":"43015",
    "sg:province":"OH",
    "sg:tags":[
        "state",
        "commercial"
    ],
    "wof:name":"Peoples Bank National Assn",
    "wof:placetype":"venue"
},
  "geometry": {"coordinates":[-83.08253499999999,40.303798],"type":"Point"}
}