{
  "type": "Feature",
  "properties": {
    "addr:full": "19490 Anderson Rd Luckey OH 43402",
    "addr:housenumber": "19490",
    "addr:postcode": "43402",
    "addr:street": "Anderson Rd",
    "iso:country": "US",
    "sg:address": "19490 Anderson Rd",
    "sg:city": "Luckey",
    "sg:classifiers": [
      {
        "category": "Building \u0026 Trades",
        "subcategory": "Construction",
        "type": "Services"
      }
    ],
    "sg:phone": "+1 419 833 4283",
    "sg:postcode": "43402",
    "sg:province": "OH",
    "sg:tags": [
      "home",
      "builder"
    ],
    "wof:name": "Duane Seifert Builders",
    "wof:placetype": "venue"
  },
  "geometry": {"coordinates":[-83.571135,41.437809],"type":"Point"}
}
