{
  "type": "Feature",
  "properties": {
    "addr:full": "231 Zeta St Ravenna OH 44266",
    "addr:housenumber": "231",
    "addr:postcode": "44266",
    "addr:street": "Zeta St",
    "iso:country": "US",
    "sg:address": "231 Zeta St",
    "sg:city": "Ravenna",
    "sg:classifiers": [
      {
        "category": "Building \u0026 Trades",
        "subcategory": "Electrical",
        "type": "Services"
      }
    ],
    "sg:phone": "+1 330 296 8859",
    "sg:postcode": "44266",
    "sg:province": "OH",
    "sg:tags": [
      "electrical",
      "contractor"
    ],
    "wof:name": "Woodruff Electric",
    "wof:placetype": "venue"
  },
  "geometry": {"coordinates":[-81.261734,41.155902],"type":"Point"}
}
