{
  "type": "Feature",
  "properties": {
    "iso:country":"US",
    "sg:address":"231 Zeta St",
    "sg:city":"Ravenna",
    "sg:classifiers":[
        {
            "category":"Building & Trades",
            "subcategory":"Electrical",
            "type":"Services"
        }
    ],
    "sg:phone":"+1 330 296 8859",
    "sg:postcode":"44266",
    "sg:province":"OH",
    "sg:tags":[
        "electrical",
        "contractor"
    ],
    "wof:name":"Woodruff Electric",
    "wof:placetype":"venue"
},
  "geometry": {"coordinates":[-81.261734,41.155902],"type":"Point"}
}