{
  "type": "Feature",
  "properties": {
    "addr:full": "490 Forest Dr Springfield OH 45505",
    "addr:housenumber": "490",
    "addr:postcode": "45505",
    "addr:street": "Forest Dr",
    "iso:country": "US",
    "sg:address": "490 Forest Dr",
    "sg:city": "Springfield",
    "sg:classifiers": [
      {
        "category": "Manufacturing",
        "subcategory": "Musical Instruments",
        "type": "Manufacturing \u0026 Wholesale Goods"
      }
    ],
    "sg:phone": "+1 937 322 5041",
    "sg:postcode": "45505",
    "sg:province": "OH",
    "sg:tags": [
      "mfg"
    ],
    "wof:name": "Morgan Woodwind Products",
    "wof:placetype": "venue"
  },
  "geometry": {"coordinates":[-83.753633,39.916693],"type":"Point"}
}
