{
  "type": "Feature",
  "properties": {
    "iso:country":"US",
    "sg:address":"3910 E 93rd St",
    "sg:city":"Cleveland",
    "sg:classifiers":[
        {
            "category":"Manufacturing",
            "subcategory":"Tools & Machinery",
            "type":"Manufacturing & Wholesale Goods"
        }
    ],
    "sg:phone":"+1 216 883 6390",
    "sg:postcode":"44105",
    "sg:province":"OH",
    "sg:tags":[
        "industrial",
        "mfg"
    ],
    "wof:name":"Monroe Die & Stamping Co",
    "wof:placetype":"venue"
},
  "geometry": {"coordinates":[-81.62137800000001,41.451792],"type":"Point"}
}