{
  "type": "Feature",
  "properties": {
    "addr:full": "525 Main St Groveport OH 43125",
    "addr:housenumber": "525",
    "addr:postcode": "43125",
    "addr:street": "Main St",
    "iso:country": "US",
    "sg:address": "525 Main St",
    "sg:city": "Groveport",
    "sg:classifiers": [
      {
        "category": "Health Services",
        "subcategory": "Clinic",
        "type": "Services"
      }
    ],
    "sg:phone": "+1 614 836 4949",
    "sg:postcode": "43125",
    "sg:province": "OH",
    "sg:tags": [
      "home"
    ],
    "wof:name": "Triad Home Health Svc LLC",
    "wof:placetype": "venue"
  },
  "geometry": {"coordinates":[-82.885582,39.851695],"type":"Point"}
}
