{
  "type": "Feature",
  "properties": {
    "iso:country":"US",
    "sg:address":"3689 Clague Rd",
    "sg:city":"North Olmsted",
    "sg:classifiers":[
        {
            "category":"Personal",
            "subcategory":"Beauty Salon",
            "type":"Services"
        }
    ],
    "sg:phone":"+1 440 801 1199",
    "sg:postcode":"44070",
    "sg:province":"OH",
    "wof:name":"Loxx The Hair Lounge",
    "wof:placetype":"venue"
},
  "geometry": {"coordinates":[-81.88097500000001,41.435505],"type":"Point"}
}