{
  "type": "Feature",
  "properties": {
    "addr:full": "7765 State Rte 656 Sunbury OH 43074",
    "addr:housenumber": "7765",
    "addr:postcode": "43074",
    "addr:street": "State Rte 656",
    "iso:country": "US",
    "sg:address": "7765 State Rte 656",
    "sg:city": "Sunbury",
    "sg:classifiers": [
      {
        "category": "Wholesale",
        "subcategory": "Medical Equipment \u0026 Supplies",
        "type": "Manufacturing \u0026 Wholesale Goods"
      }
    ],
    "sg:phone": "+1 740 524 5232",
    "sg:postcode": "43074",
    "sg:province": "OH",
    "sg:tags": [
      "distributor"
    ],
    "wof:name": "Medi Source",
    "wof:placetype": "venue"
  },
  "geometry": {"coordinates":[-82.814055,40.328242],"type":"Point"}
}
