{
  "type": "Feature",
  "properties": {
    "iso:country":"US",
    "sg:address":"7765 State Rte 656",
    "sg:city":"Sunbury",
    "sg:classifiers":[
        {
            "category":"Wholesale",
            "subcategory":"Medical Equipment & Supplies",
            "type":"Manufacturing & Wholesale Goods"
        }
    ],
    "sg:phone":"+1 740 524 5232",
    "sg:postcode":"43074",
    "sg:province":"OH",
    "sg:tags":[
        "distributor"
    ],
    "wof:name":"Medi Source",
    "wof:placetype":"venue"
},
  "geometry": {"coordinates":[-82.814055,40.328242],"type":"Point"}
}