{
  "type": "Feature",
  "properties": {
    "addr:full":"1240 E Central Ave Miamisburg OH 45342",
    "addr:housenumber":"1240",
    "addr:postcode":"45342",
    "addr:street":"E Central Ave",
    "iso:country":"US",
    "sg:address":"1240 E Central Ave",
    "sg:city":"Miamisburg",
    "sg:classifiers":[
        {
            "category":"Home & Garden",
            "subcategory":"Hardware",
            "type":"Retail Goods"
        }
    ],
    "sg:phone":"+1 937 865 0320",
    "sg:postcode":"45342",
    "sg:province":"OH",
    "wof:name":"Handyman Ace Hardware",
    "wof:placetype":"venue"
},
  "geometry": {"coordinates":[-84.266182,39.640477],"type":"Point"}
}