{
  "type": "Feature",
  "properties": {
    "addr:full":"2330 Northmoor Dr Springfield OH 45503",
    "addr:housenumber":"2330",
    "addr:postcode":"45503",
    "addr:street":"Northmoor Dr",
    "iso:country":"US",
    "sg:address":"2330 Northmoor Dr",
    "sg:city":"Springfield",
    "sg:classifiers":[
        {
            "category":"Personal",
            "subcategory":"Beauty Salon",
            "type":"Services"
        }
    ],
    "sg:phone":"+1 937 399 0221",
    "sg:postcode":"45503",
    "sg:province":"OH",
    "sg:tags":[
        "shop",
        "toilet",
        "preparation",
        "mfg"
    ],
    "wof:name":"Hair & Nail Impressions",
    "wof:placetype":"venue"
},
  "geometry": {"coordinates":[-83.79069699999999,39.95353],"type":"Point"}
}