{
  "type": "Feature",
  "properties": {
    "iso:country":"US",
    "sg:address":"4972 Coventry Ct S",
    "sg:city":"Columbus",
    "sg:classifiers":[
        {
            "category":"Manufacturing",
            "subcategory":"Tools & Machinery",
            "type":"Manufacturing & Wholesale Goods"
        }
    ],
    "sg:phone":"+1 614 577 9439",
    "sg:postcode":"43232",
    "sg:province":"OH",
    "sg:tags":[
        "mfg"
    ],
    "wof:name":"Creative Suggestions",
    "wof:placetype":"venue"
},
  "geometry": {"coordinates":[-82.861445,39.938342],"type":"Point"}
}