{
  "type": "Feature",
  "properties": {
    "iso:country":"US",
    "sg:address":"4404 Twp Rd 142",
    "sg:city":"Findlay",
    "sg:classifiers":[
        {
            "category":"Wholesale",
            "subcategory":"Auto Parts",
            "type":"Manufacturing & Wholesale Goods"
        }
    ],
    "sg:phone":"+1 419 422 7434",
    "sg:postcode":"45840",
    "sg:province":"OH",
    "sg:tags":[
        "automobile",
        "rebuilt",
        "used"
    ],
    "sg:website":"www.dicksautosalvage.com",
    "wof:name":"Dick S Auto Salvage",
    "wof:placetype":"venue"
},
  "geometry": {"coordinates":[-83.66911500000001,41.104524],"type":"Point"}
}