{
  "type": "Feature",
  "properties": {
    "addr:full": "7699 Harrison Ave Cleves OH 45002",
    "addr:housenumber": "7699",
    "addr:postcode": "45002",
    "addr:street": "Harrison Ave",
    "iso:country": "US",
    "sg:address": "7699 Harrison Ave",
    "sg:city": "Cleves",
    "sg:classifiers": [
      {
        "category": "Retail",
        "subcategory": "Auto Repair",
        "type": "Services"
      }
    ],
    "sg:phone": "+1 513 353 2829",
    "sg:postcode": "45002",
    "sg:province": "OH",
    "sg:tags": [
      "repairing",
      "automobile"
    ],
    "wof:name": "Mitchs Auto Care",
    "wof:placetype": "venue"
  },
  "geometry": {"coordinates":[-84.692182,39.217042],"type":"Point"}
}
