{
  "type": "Feature",
  "properties": {
    "iso:country":"US",
    "sg:address":"36400 Maplegrove Rd",
    "sg:city":"Willoughby",
    "sg:classifiers":[
        {
            "category":"Organizations",
            "subcategory":"Religious Organization",
            "type":"Services"
        }
    ],
    "sg:phone":"+1 440 942 2052",
    "sg:postcode":"44094",
    "sg:province":"OH",
    "sg:tags":[
        "church"
    ],
    "sg:website":"www.maplegrovecma.org",
    "wof:name":"Maplegrove Alliance Church",
    "wof:placetype":"venue"
},
  "geometry": {"coordinates":[-81.41835,41.605705],"type":"Point"}
}