{
  "type": "Feature",
  "properties": {
    "addr:full": "36400 Maplegrove Rd Willoughby OH 44094",
    "addr:housenumber": "36400",
    "addr:postcode": "44094",
    "addr:street": "Maplegrove Rd",
    "iso:country": "US",
    "sg:address": "36400 Maplegrove Rd",
    "sg:city": "Willoughby",
    "sg:classifiers": [
      {
        "category": "Organizations",
        "subcategory": "Religious Organization",
        "type": "Services"
      }
    ],
    "sg:phone": "+1 440 942 2052",
    "sg:postcode": "44094",
    "sg:province": "OH",
    "sg:tags": [
      "church"
    ],
    "sg:website": "www.maplegrovecma.org",
    "wof:name": "Maplegrove Alliance Church",
    "wof:placetype": "venue"
  },
  "geometry": {"coordinates":[-81.41835,41.605705],"type":"Point"}
}
