{
  "type": "Feature",
  "properties": {
    "addr:full":"41 30th St NW Barberton OH 44203",
    "addr:housenumber":"41",
    "addr:postcode":"44203",
    "addr:street":"30Th St Nw",
    "iso:country":"US",
    "sg:address":"41 30th St NW",
    "sg:city":"Barberton",
    "sg:classifiers":[
        {
            "category":"Real Estate",
            "subcategory":"Real Estate Operator",
            "type":"Services"
        }
    ],
    "sg:phone":"+1 330 825 9464",
    "sg:postcode":"44203",
    "sg:province":"OH",
    "sg:tags":[
        "apartment"
    ],
    "wof:name":"Heritage Place Senior Apts",
    "wof:placetype":"venue"
},
  "geometry": {"coordinates":[-81.637207,41.006299],"type":"Point"}
}