{
  "type": "Feature",
  "properties": {
    "addr:full":"1030 Fawcett Rd Peebles OH 45660",
    "addr:housenumber":"1030",
    "addr:postcode":"45660",
    "addr:street":"Fawcett Rd",
    "iso:country":"US",
    "sg:address":"1030 Fawcett Rd",
    "sg:city":"Peebles",
    "sg:classifiers":[
        {
            "category":"Wholesale",
            "subcategory":"Fruits & Vegetables",
            "type":"Manufacturing & Wholesale Goods"
        }
    ],
    "sg:phone":"+1 937 587 2079",
    "sg:postcode":"45660",
    "sg:province":"OH",
    "sg:tags":[
        "produce"
    ],
    "wof:name":"Seasons Harvest Inc",
    "wof:placetype":"venue"
},
  "geometry": {"coordinates":[-83.448256,38.865849],"type":"Point"}
}