{
  "type": "Feature",
  "properties": {
    "iso:country":"US",
    "sg:address":"3315 Centennial Rd",
    "sg:city":"Sylvania",
    "sg:classifiers":[
        {
            "category":"Manufacturing",
            "subcategory":"Tools & Machinery",
            "type":"Manufacturing & Wholesale Goods"
        }
    ],
    "sg:phone":"+1 419 843 2131",
    "sg:postcode":"43560",
    "sg:province":"OH",
    "sg:tags":[
        "industrial",
        "mfg"
    ],
    "wof:name":"Accurate Machining",
    "wof:placetype":"venue"
},
  "geometry": {"coordinates":[-83.742239,41.677412],"type":"Point"}
}