{
  "type": "Feature",
  "properties": {
    "addr:full": "2700 Medina Rd Medina OH 44256",
    "addr:housenumber": "2700",
    "addr:postcode": "44256",
    "addr:street": "Medina Rd",
    "iso:country": "US",
    "sg:address": "2700 Medina Rd",
    "sg:city": "Medina",
    "sg:classifiers": [
      {
        "category": "Autos \u0026 Motor Vehicles",
        "subcategory": "Automobile Sales",
        "type": "Retail Goods"
      }
    ],
    "sg:phone": "+1 330 441 4300",
    "sg:postcode": "44256",
    "sg:province": "OH",
    "sg:tags": [
      "car",
      "dealer"
    ],
    "wof:name": "Serpentini Used Car Express",
    "wof:placetype": "venue"
  },
  "geometry": {"coordinates":[-81.785187,41.136157],"type":"Point"}
}
