{
  "type": "Feature",
  "properties": {
    "addr:full": "12900 Lake Ave Cleveland OH 44107",
    "addr:housenumber": "12900",
    "addr:postcode": "44107",
    "addr:street": "Lake Ave",
    "iso:country": "US",
    "sg:address": "12900 Lake Ave",
    "sg:city": "Cleveland",
    "sg:classifiers": [
      {
        "category": "Building \u0026 Trades",
        "subcategory": "Construction",
        "type": "Services"
      }
    ],
    "sg:phone": "+1 216 221 8712",
    "sg:postcode": "44107",
    "sg:province": "OH",
    "sg:tags": [
      "designer"
    ],
    "wof:name": "Product Plus Design Inc",
    "wof:placetype": "venue"
  },
  "geometry": {"coordinates":[-81.782733,41.492156],"type":"Point"}
}
