{
  "type": "Feature",
  "properties": {
    "iso:country":"US",
    "sg:address":"12900 Lake Ave",
    "sg:city":"Cleveland",
    "sg:classifiers":[
        {
            "category":"Building & Trades",
            "subcategory":"Construction",
            "type":"Services"
        }
    ],
    "sg:phone":"+1 216 221 8712",
    "sg:postcode":"44107",
    "sg:province":"OH",
    "sg:tags":[
        "designer"
    ],
    "wof:name":"Product Plus Design Inc",
    "wof:placetype":"venue"
},
  "geometry": {"coordinates":[-81.78273299999999,41.492156],"type":"Point"}
}