{
  "type": "Feature",
  "properties": {
    "iso:country":"US",
    "sg:address":"700 12th St NE",
    "sg:city":"Canton",
    "sg:classifiers":[
        {
            "category":"Building & Trades",
            "subcategory":"Pest Control",
            "type":"Services"
        }
    ],
    "sg:phone":"+1 330 456 0956",
    "sg:postcode":"44703",
    "sg:province":"OH",
    "wof:name":"T & L Pest Control Inc",
    "wof:placetype":"venue"
},
  "geometry": {"coordinates":[-81.378289,40.809352],"type":"Point"}
}