{
  "type": "Feature",
  "properties": {
    "iso:country":"US",
    "sg:address":"451 Miller St",
    "sg:city":"Youngstown",
    "sg:classifiers":[
        {
            "category":"Organizations",
            "subcategory":"Community Association",
            "type":"Services"
        }
    ],
    "sg:phone":"+1 330 783 1318",
    "sg:postcode":"44502",
    "sg:province":"OH",
    "sg:tags":[
        "fraternal"
    ],
    "sg:website":"www.foe.com",
    "wof:name":"Fraternal Order Of Eagles",
    "wof:placetype":"venue"
},
  "geometry": {"coordinates":[-80.64712400000001,41.073522],"type":"Point"}
}