{
  "type": "Feature",
  "properties": {
    "iso:country":"US",
    "sg:address":"2460 Fairmount Blvd",
    "sg:city":"Cleveland",
    "sg:classifiers":[
        {
            "category":"Health Services",
            "subcategory":"Doctor",
            "type":"Services"
        }
    ],
    "sg:phone":"+1 216 791 5191",
    "sg:postcode":"44106",
    "sg:province":"OH",
    "wof:name":"Berke Dental Center Inc",
    "wof:placetype":"venue"
},
  "geometry": {"coordinates":[-81.59151,41.499417],"type":"Point"}
}