{
  "type": "Feature",
  "properties": {
    "iso:country":"US",
    "sg:address":"217 W Market St",
    "sg:city":"Celina",
    "sg:classifiers":[
        {
            "category":"Banks & Credit Unions",
            "subcategory":"Investment Brokerage",
            "type":"Services"
        }
    ],
    "sg:phone":"+1 419 586 9009",
    "sg:postcode":"45822",
    "sg:province":"OH",
    "sg:tags":[
        "consultant",
        "planning",
        "financial"
    ],
    "wof:name":"Money Concepts Financial Ctr",
    "wof:placetype":"venue"
},
  "geometry": {"coordinates":[-84.572903,40.549091],"type":"Point"}
}