{
  "type": "Feature",
  "properties": {
    "addr:full":"2150 N Eastown Rd Lima OH 45807",
    "addr:housenumber":"2150",
    "addr:postcode":"45807",
    "addr:street":"N Eastown Rd",
    "iso:country":"US",
    "sg:address":"2150 N Eastown Rd",
    "sg:city":"Lima",
    "sg:classifiers":[
        {
            "category":"Real Estate",
            "subcategory":"Real Estate Agent",
            "type":"Services"
        }
    ],
    "sg:phone":"+1 419 331 7653",
    "sg:postcode":"45807",
    "sg:province":"OH",
    "wof:name":"Prudential",
    "wof:placetype":"venue"
},
  "geometry": {"coordinates":[-84.165149,40.767262],"type":"Point"}
}