{
  "type": "Feature",
  "properties": {
    "iso:country":"US",
    "sg:address":"5726 Southwyck Blvd",
    "sg:city":"Toledo",
    "sg:classifiers":[
        {
            "category":"Banks & Credit Unions",
            "subcategory":"Bank",
            "type":"Services"
        }
    ],
    "sg:phone":"+1 419 865 2637",
    "sg:postcode":"43614",
    "sg:province":"OH",
    "wof:name":"Emprise Technologies LLC",
    "wof:placetype":"venue"
},
  "geometry": {"coordinates":[-83.670147,41.600215],"type":"Point"}
}