{
  "type": "Feature",
  "properties": {
    "addr:full": "5726 Southwyck Blvd Toledo OH 43614",
    "addr:housenumber": "5726",
    "addr:postcode": "43614",
    "addr:street": "Southwyck Blvd",
    "iso:country": "US",
    "sg:address": "5726 Southwyck Blvd",
    "sg:city": "Toledo",
    "sg:classifiers": [
      {
        "category": "Banks \u0026 Credit Unions",
        "subcategory": "Bank",
        "type": "Services"
      }
    ],
    "sg:phone": "+1 419 865 2637",
    "sg:postcode": "43614",
    "sg:province": "OH",
    "wof:name": "Emprise Technologies LLC",
    "wof:placetype": "venue"
  },
  "geometry": {"coordinates":[-83.670147,41.600215],"type":"Point"}
}
