{
  "type": "Feature",
  "properties": {
    "addr:full":"141 S Main St Bryan OH 43506",
    "addr:housenumber":"141",
    "addr:postcode":"43506",
    "addr:street":"S Main St",
    "iso:country":"US",
    "sg:address":"141 S Main St",
    "sg:city":"Bryan",
    "sg:classifiers":[
        {
            "category":"Personal",
            "subcategory":"Hair Removal",
            "type":"Services"
        }
    ],
    "sg:phone":"+1 419 636 0588",
    "sg:postcode":"43506",
    "sg:province":"OH",
    "sg:tags":[
        "removing"
    ],
    "wof:name":"Wyse Choice Electrolysis",
    "wof:placetype":"venue"
},
  "geometry": {"coordinates":[-84.550984,41.474066],"type":"Point"}
}