{
  "type": "Feature",
  "properties": {
    "addr:full": "410 E Huron St Jackson OH 45640",
    "addr:housenumber": "410",
    "addr:postcode": "45640",
    "addr:street": "E Huron St",
    "iso:country": "US",
    "sg:address": "410 E Huron St",
    "sg:city": "Jackson",
    "sg:classifiers": [
      {
        "category": "Personal",
        "subcategory": "Beauty Salon",
        "type": "Services"
      }
    ],
    "sg:phone": "+1 740 286 6855",
    "sg:postcode": "45640",
    "sg:province": "OH",
    "sg:tags": [
      "shop"
    ],
    "wof:name": "Cutting Edge Dsigns By Katrina",
    "wof:placetype": "venue"
  },
  "geometry": {"coordinates":[-82.629933,39.044483],"type":"Point"}
}
