{
  "type": "Feature",
  "properties": {
    "addr:full": "1267 Westphal Ave Columbus OH 43227",
    "addr:housenumber": "1267",
    "addr:postcode": "43227",
    "addr:street": "Westphal Ave",
    "iso:country": "US",
    "sg:address": "1267 Westphal Ave",
    "sg:city": "Columbus",
    "sg:classifiers": [
      {
        "category": "Building \u0026 Trades",
        "subcategory": "Electrical",
        "type": "Services"
      }
    ],
    "sg:phone": "+1 614 237 3524",
    "sg:postcode": "43227",
    "sg:province": "OH",
    "sg:tags": [
      "electrical",
      "contractor"
    ],
    "wof:name": "Hahns Electric",
    "wof:placetype": "venue"
  },
  "geometry": {"coordinates":[-82.883078,39.947928],"type":"Point"}
}
