{
  "type": "Feature",
  "properties": {
    "addr:full": "1765 Harrisburg Pike Columbus OH 43223",
    "addr:housenumber": "1765",
    "addr:postcode": "43223",
    "addr:street": "Harrisburg Pike",
    "iso:country": "US",
    "sg:address": "1765 Harrisburg Pike",
    "sg:city": "Columbus",
    "sg:classifiers": [
      {
        "category": "Manufacturing",
        "subcategory": "Signs",
        "type": "Manufacturing \u0026 Wholesale Goods"
      }
    ],
    "sg:phone": "+1 614 272 9802",
    "sg:postcode": "43223",
    "sg:province": "OH",
    "sg:tags": [
      "specialty",
      "mfg"
    ],
    "wof:name": "Superior Signs \u0026 Decals",
    "wof:placetype": "venue"
  },
  "geometry": {"coordinates":[-83.060047,39.922848],"type":"Point"}
}
