{
  "type": "Feature",
  "properties": {
    "iso:country":"US",
    "sg:address":"1765 Harrisburg Pike",
    "sg:city":"Columbus",
    "sg:classifiers":[
        {
            "category":"Manufacturing",
            "subcategory":"Signs",
            "type":"Manufacturing & Wholesale Goods"
        }
    ],
    "sg:phone":"+1 614 272 9802",
    "sg:postcode":"43223",
    "sg:province":"OH",
    "sg:tags":[
        "specialty",
        "mfg"
    ],
    "wof:name":"Superior Signs & Decals",
    "wof:placetype":"venue"
},
  "geometry": {"coordinates":[-83.060047,39.922848],"type":"Point"}
}