{
  "type": "Feature",
  "properties": {
    "iso:country":"US",
    "sg:address":"2030 Stringtown Rd",
    "sg:city":"Grove City",
    "sg:classifiers":[
        {
            "category":"Health Services",
            "subcategory":"Doctor",
            "type":"Services"
        }
    ],
    "sg:phone":"+1 614 883 0160",
    "sg:postcode":"43123",
    "sg:province":"OH",
    "sg:tags":[
        "physician",
        "surgeon"
    ],
    "wof:name":"America's Urgent Care",
    "wof:placetype":"venue"
},
  "geometry": {"coordinates":[-83.058605,39.878568],"type":"Point"}
}