{
  "type": "Feature",
  "properties": {
    "addr:full": "744 E Court St Urbana OH 43078",
    "addr:housenumber": "744",
    "addr:postcode": "43078",
    "addr:street": "E Court St",
    "iso:country": "US",
    "sg:address": "744 E Court St",
    "sg:city": "Urbana",
    "sg:classifiers": [
      {
        "category": "Wholesale",
        "subcategory": "Metals \u0026 Minerals",
        "type": "Manufacturing \u0026 Wholesale Goods"
      }
    ],
    "sg:phone": "+1 937 653 7059",
    "sg:postcode": "43078",
    "sg:province": "OH",
    "sg:tags": [
      "center"
    ],
    "wof:name": "Samuel Bevel",
    "wof:placetype": "venue"
  },
  "geometry": {"coordinates":[-83.736965,40.108299],"type":"Point"}
}
