{
  "type": "Feature",
  "properties": {
    "iso:country":"US",
    "sg:address":"744 E Court St",
    "sg:city":"Urbana",
    "sg:classifiers":[
        {
            "category":"Wholesale",
            "subcategory":"Metals & Minerals",
            "type":"Manufacturing & Wholesale Goods"
        }
    ],
    "sg:phone":"+1 937 653 7059",
    "sg:postcode":"43078",
    "sg:province":"OH",
    "sg:tags":[
        "center"
    ],
    "wof:name":"Samuel Bevel",
    "wof:placetype":"venue"
},
  "geometry": {"coordinates":[-83.736965,40.108299],"type":"Point"}
}