{
  "type": "Feature",
  "properties": {
    "addr:full":"34425 Lorain Rd North Ridgeville OH 44039",
    "addr:housenumber":"34425",
    "addr:postcode":"44039",
    "addr:street":"Lorain Rd",
    "iso:country":"US",
    "sg:address":"34425 Lorain Rd",
    "sg:city":"North Ridgeville",
    "sg:classifiers":[
        {
            "category":"Wholesale",
            "subcategory":"Stationery",
            "type":"Manufacturing & Wholesale Goods"
        }
    ],
    "sg:phone":"+1 440 582 3296",
    "sg:postcode":"44039",
    "sg:province":"OH",
    "sg:tags":[
        "including",
        "envelope",
        "business",
        "for",
        "supply"
    ],
    "wof:name":"The Stone Group",
    "wof:placetype":"venue"
},
  "geometry": {"coordinates":[-81.993718,41.372319],"type":"Point"}
}