{
  "type": "Feature",
  "properties": {
    "addr:full": "35005 Chardon Rd Willoughby OH 44094",
    "addr:housenumber": "35005",
    "addr:postcode": "44094",
    "addr:street": "Chardon Rd",
    "iso:country": "US",
    "sg:address": "35005 Chardon Rd",
    "sg:city": "Willoughby",
    "sg:classifiers": [
      {
        "category": "Health Services",
        "subcategory": "Doctor",
        "type": "Services"
      }
    ],
    "sg:phone": "+1 440 942 8934",
    "sg:postcode": "44094",
    "sg:province": "OH",
    "sg:tags": [
      "dentist"
    ],
    "wof:name": "Western Reserve Orthodontics",
    "wof:placetype": "venue"
  },
  "geometry": {"coordinates":[-81.432445,41.588606],"type":"Point"}
}
