{
  "type": "Feature",
  "properties": {
    "addr:full":"8532 Hawley Mills Rd New Paris OH 45347",
    "addr:housenumber":"8532",
    "addr:postcode":"45347",
    "addr:street":"Hawley Mills Rd",
    "iso:country":"US",
    "sg:address":"8532 Hawley Mills Rd",
    "sg:city":"New Paris",
    "sg:classifiers":[
        {
            "category":"Building & Trades",
            "subcategory":"Construction",
            "type":"Services"
        }
    ],
    "sg:phone":"+1 937 437 0604",
    "sg:postcode":"45347",
    "sg:province":"OH",
    "sg:tags":[
        "house"
    ],
    "wof:name":"Spahr Construction",
    "wof:placetype":"venue"
},
  "geometry": {"coordinates":[-84.786326,39.859608],"type":"Point"}
}