{
  "type": "Feature",
  "properties": {
    "iso:country":"US",
    "sg:address":"150 Ballard Dr",
    "sg:city":"Springboro",
    "sg:classifiers":[
        {
            "category":"Restaurant",
            "type":"Food & Drink"
        }
    ],
    "sg:phone":"+1 937 885 1538",
    "sg:postcode":"45066",
    "sg:province":"OH",
    "sg:tags":[
        "eating"
    ],
    "wof:name":"Baldwin & Trick Entps LLC",
    "wof:placetype":"venue"
},
  "geometry": {"coordinates":[-84.214288,39.579938],"type":"Point"}
}