{
  "type": "Feature",
  "properties": {
    "addr:full": "150 Ballard Dr Springboro OH 45066",
    "addr:housenumber": "150",
    "addr:postcode": "45066",
    "addr:street": "Ballard Dr",
    "iso:country": "US",
    "sg:address": "150 Ballard Dr",
    "sg:city": "Springboro",
    "sg:classifiers": [
      {
        "category": "Restaurant",
        "type": "Food \u0026 Drink"
      }
    ],
    "sg:phone": "+1 937 885 1538",
    "sg:postcode": "45066",
    "sg:province": "OH",
    "sg:tags": [
      "eating"
    ],
    "wof:name": "Baldwin \u0026 Trick Entps LLC",
    "wof:placetype": "venue"
  },
  "geometry": {"coordinates":[-84.214288,39.579938],"type":"Point"}
}
