{
  "type": "Feature",
  "properties": {
    "addr:full": "1620 Albert St Youngstown OH 44505",
    "addr:housenumber": "1620",
    "addr:postcode": "44505",
    "addr:street": "Albert St",
    "iso:country": "US",
    "sg:address": "1620 Albert St",
    "sg:city": "Youngstown",
    "sg:classifiers": [
      {
        "category": "Retail",
        "subcategory": "Auto Repair",
        "type": "Services"
      }
    ],
    "sg:phone": "+1 330 746 9775",
    "sg:postcode": "44505",
    "sg:province": "OH",
    "sg:tags": [
      "repairing",
      "automobile"
    ],
    "wof:name": "Rutherford's Garage",
    "wof:placetype": "venue"
  },
  "geometry": {"coordinates":[-80.631568,41.121638],"type":"Point"}
}
