{
  "type": "Feature",
  "properties": {
    "addr:full": "840 N Knoop-Johnston Rd Sidney OH 45365",
    "addr:housenumber": "840",
    "addr:postcode": "45365",
    "addr:street": "N Knoop-Johnston Rd",
    "iso:country": "US",
    "sg:address": "840 N Knoop-Johnston Rd",
    "sg:city": "Sidney",
    "sg:classifiers": [
      {
        "category": "Insurance",
        "subcategory": "Insurance Agent",
        "type": "Services"
      }
    ],
    "sg:phone": "+1 937 498 1313",
    "sg:postcode": "45365",
    "sg:province": "OH",
    "wof:name": "Michael R Becker Insurance",
    "wof:placetype": "venue"
  },
  "geometry": {"coordinates":[-84.117073,40.295541],"type":"Point"}
}
