{
  "type": "Feature",
  "properties": {
    "addr:full": "6050 Ridge Rd Cleveland OH 44129",
    "addr:housenumber": "6050",
    "addr:postcode": "44129",
    "addr:street": "Ridge Rd",
    "iso:country": "US",
    "sg:address": "6050 Ridge Rd",
    "sg:city": "Cleveland",
    "sg:classifiers": [
      {
        "category": "Social Services",
        "subcategory": "Child Care",
        "type": "Services"
      }
    ],
    "sg:phone": "+1 440 845 3725",
    "sg:postcode": "44129",
    "sg:province": "OH",
    "sg:tags": [
      "kindergarten",
      "academic",
      "school"
    ],
    "wof:name": "Parma Co-Op Pre-School",
    "wof:placetype": "venue"
  },
  "geometry": {"coordinates":[-81.734579,41.397817],"type":"Point"}
}
