{
  "type": "Feature",
  "properties": {
    "addr:full":"26100 Benton Ave Cleveland OH 44132",
    "addr:housenumber":"26100",
    "addr:postcode":"44132",
    "addr:street":"Benton Ave",
    "iso:country":"US",
    "sg:address":"26100 Benton Ave",
    "sg:city":"Cleveland",
    "sg:classifiers":[
        {
            "category":"Building & Trades",
            "subcategory":"Construction",
            "type":"Services"
        }
    ],
    "sg:phone":"+1 216 322 5314",
    "sg:postcode":"44132",
    "sg:province":"OH",
    "sg:tags":[
        "home",
        "improvement"
    ],
    "wof:name":"Renovations Plus",
    "wof:placetype":"venue"
},
  "geometry": {"coordinates":[-81.499314,41.604627],"type":"Point"}
}