{
  "type": "Feature",
  "properties": {
    "addr:full": "6820 Commerce Court Dr Blacklick OH 43004",
    "addr:housenumber": "6820",
    "addr:postcode": "43004",
    "addr:street": "Commerce Court Dr",
    "iso:country": "US",
    "sg:address": "6820 Commerce Court Dr",
    "sg:city": "Blacklick",
    "sg:classifiers": [
      {
        "category": "Manufacturing",
        "subcategory": "Tools \u0026 Machinery",
        "type": "Manufacturing \u0026 Wholesale Goods"
      }
    ],
    "sg:phone": "+1 614 501 6740",
    "sg:postcode": "43004",
    "sg:province": "OH",
    "sg:tags": [
      "equipment",
      "lighting",
      "mfg"
    ],
    "sg:website": "www.sunergoline.com",
    "wof:name": "Sun Ergoline Inc",
    "wof:placetype": "venue"
  },
  "geometry": {"coordinates":[-82.817648,39.989205],"type":"Point"}
}
