{
  "type": "Feature",
  "properties": {
    "iso:country":"US",
    "sg:address":"6820 Commerce Court Dr",
    "sg:city":"Blacklick",
    "sg:classifiers":[
        {
            "category":"Manufacturing",
            "subcategory":"Tools & Machinery",
            "type":"Manufacturing & Wholesale Goods"
        }
    ],
    "sg:phone":"+1 614 501 6740",
    "sg:postcode":"43004",
    "sg:province":"OH",
    "sg:tags":[
        "equipment",
        "lighting",
        "mfg"
    ],
    "sg:website":"www.sunergoline.com",
    "wof:name":"Sun Ergoline Inc",
    "wof:placetype":"venue"
},
  "geometry": {"coordinates":[-82.81764800000001,39.989205],"type":"Point"}
}