{
  "type": "Feature",
  "properties": {
    "iso:country":"US",
    "sg:address":"416 S East St",
    "sg:city":"Lebanon",
    "sg:classifiers":[
        {
            "category":"Government",
            "subcategory":"Office",
            "type":"Public Place"
        }
    ],
    "sg:phone":"+1 513 695 1420",
    "sg:postcode":"45036",
    "sg:province":"OH",
    "sg:tags":[
        "county",
        "resource"
    ],
    "wof:name":"Warren County Human Svc Info",
    "wof:placetype":"venue"
},
  "geometry": {"coordinates":[-84.20490599999999,39.425531],"type":"Point"}
}