{
  "type": "Feature",
  "properties": {
    "iso:country":"US",
    "sg:address":"203 2nd St NW",
    "sg:city":"Barberton",
    "sg:classifiers":[
        {
            "category":"Manufacturing",
            "subcategory":"Metals",
            "type":"Manufacturing & Wholesale Goods"
        }
    ],
    "sg:phone":"+1 330 745 3425",
    "sg:postcode":"44203",
    "sg:province":"OH",
    "sg:tags":[
        "fabricator",
        "sheet"
    ],
    "wof:name":"Helfin Welding & Sheet Metal",
    "wof:placetype":"venue"
},
  "geometry": {"coordinates":[-81.60737899999999,41.015384],"type":"Point"}
}