{
  "type": "Feature",
  "properties": {
    "addr:full": "203 2nd St NW Barberton OH 44203",
    "addr:housenumber": "203",
    "addr:postcode": "44203",
    "addr:street": "2Nd St Nw",
    "iso:country": "US",
    "sg:address": "203 2nd St NW",
    "sg:city": "Barberton",
    "sg:classifiers": [
      {
        "category": "Manufacturing",
        "subcategory": "Metals",
        "type": "Manufacturing \u0026 Wholesale Goods"
      }
    ],
    "sg:phone": "+1 330 745 3425",
    "sg:postcode": "44203",
    "sg:province": "OH",
    "sg:tags": [
      "fabricator",
      "sheet"
    ],
    "wof:name": "Helfin Welding \u0026 Sheet Metal",
    "wof:placetype": "venue"
  },
  "geometry": {"coordinates":[-81.607379,41.015384],"type":"Point"}
}
