{
  "type": "Feature",
  "properties": {
    "addr:full": "3689 Twp Rd 124 Millersburg OH 44654",
    "addr:housenumber": "3689",
    "addr:postcode": "44654",
    "addr:street": "Twp Rd 124",
    "iso:country": "US",
    "sg:address": "3689 Twp Rd 124",
    "sg:city": "Millersburg",
    "sg:classifiers": [
      {
        "category": "Building \u0026 Trades",
        "subcategory": "Construction",
        "type": "Services"
      }
    ],
    "sg:phone": "+1 330 893 1600",
    "sg:postcode": "44654",
    "sg:province": "OH",
    "sg:tags": [
      "downspouts",
      "gutter"
    ],
    "wof:name": "Superior Seamless Spouting",
    "wof:placetype": "venue"
  },
  "geometry": {"coordinates":[-81.81467,40.508232],"type":"Point"}
}
