{
  "type": "Feature",
  "properties": {
    "addr:full":"32901 Station St Solon OH 44139",
    "addr:housenumber":"32901",
    "addr:postcode":"44139",
    "addr:street":"Station St",
    "iso:country":"US",
    "sg:address":"32901 Station St",
    "sg:city":"Solon",
    "sg:classifiers":[
        {
            "category":"Restaurant",
            "type":"Food & Drink"
        }
    ],
    "sg:phone":"+1 440 349 9800",
    "sg:postcode":"44139",
    "sg:province":"OH",
    "sg:tags":[
        "eating"
    ],
    "wof:name":"Sirens Restaurant Llc",
    "wof:placetype":"venue"
},
  "geometry": {"coordinates":[-81.438047,41.38629],"type":"Point"}
}