{
  "type": "Feature",
  "properties": {
    "addr:full":"2500 E Rahn Rd Dayton OH 45440",
    "addr:housenumber":"2500",
    "addr:postcode":"45440",
    "addr:street":"E Rahn Rd",
    "iso:country":"US",
    "sg:address":"2500 E Rahn Rd",
    "sg:city":"Dayton",
    "sg:classifiers":[
        {
            "category":"Professional",
            "type":"Services"
        }
    ],
    "sg:phone":"+1 937 436 3988",
    "sg:postcode":"45440",
    "sg:province":"OH",
    "wof:name":"Gayle A Rzepecki",
    "wof:placetype":"venue"
},
  "geometry": {"coordinates":[-84.116321,39.669926],"type":"Point"}
}