{
  "type": "Feature",
  "properties": {
    "addr:full": "13220 Shaker Sq Cleveland OH 44120",
    "addr:housenumber": "13220",
    "addr:postcode": "44120",
    "addr:street": "Shaker Sq",
    "iso:country": "US",
    "sg:address": "13220 Shaker Sq",
    "sg:city": "Cleveland",
    "sg:classifiers": [
      {
        "category": "Restaurant",
        "type": "Food \u0026 Drink"
      }
    ],
    "sg:menulink": "http://www.allmenus.com/oh/cleveland/44478-fire/menu/",
    "sg:phone": "+1 216 921 3473",
    "sg:postcode": "44120",
    "sg:province": "OH",
    "sg:tags": [
      "american"
    ],
    "wof:name": "Fire",
    "wof:placetype": "venue"
  },
  "geometry": {"coordinates":[-81.590162,41.483315],"type":"Point"}
}
