{
  "type": "Feature",
  "properties": {
    "iso:country":"US",
    "sg:address":"13220 Shaker Sq",
    "sg:city":"Cleveland",
    "sg:classifiers":[
        {
            "category":"Restaurant",
            "type":"Food & Drink"
        }
    ],
    "sg:menulink":"http://www.allmenus.com/oh/cleveland/44478-fire/menu/",
    "sg:phone":"+1 216 921 3473",
    "sg:postcode":"44120",
    "sg:province":"OH",
    "sg:tags":[
        "american"
    ],
    "wof:name":"Fire",
    "wof:placetype":"venue"
},
  "geometry": {"coordinates":[-81.59016200000001,41.483315],"type":"Point"}
}