{
  "type": "Feature",
  "properties": {
    "iso:country":"US",
    "sg:address":"1290 Poland Ave",
    "sg:city":"Youngstown",
    "sg:classifiers":[
        {
            "category":"Railroad",
            "type":"Transportation"
        }
    ],
    "sg:phone":"+1 330 742 5861",
    "sg:postcode":"44502",
    "sg:province":"OH",
    "wof:name":"Mahoning Valley Railway Co",
    "wof:placetype":"venue"
},
  "geometry": {"coordinates":[-80.62991100000001,41.080646],"type":"Point"}
}