{
  "type": "Feature",
  "properties": {
    "iso:country":"US",
    "sg:address":"300 Walnut St",
    "sg:city":"Perrysburg",
    "sg:classifiers":[
        {
            "category":"Government",
            "subcategory":"Court House",
            "type":"Public Place"
        }
    ],
    "sg:phone":"+1 419 872 7900",
    "sg:postcode":"43551",
    "sg:province":"OH",
    "sg:tags":[
        "city"
    ],
    "sg:website":"www.perrysburgcourt.com",
    "wof:name":"Perrysburg Criminal Court",
    "wof:placetype":"venue"
},
  "geometry": {"coordinates":[-83.630685,41.557325],"type":"Point"}
}