{
  "type": "Feature",
  "properties": {
    "addr:full": "1145 Briarcliff Rd Reynoldsburg OH 43068",
    "addr:housenumber": "1145",
    "addr:postcode": "43068",
    "addr:street": "Briarcliff Rd",
    "iso:country": "US",
    "sg:address": "1145 Briarcliff Rd",
    "sg:city": "Reynoldsburg",
    "sg:classifiers": [
      {
        "category": "Building \u0026 Trades",
        "subcategory": "Electrical",
        "type": "Services"
      }
    ],
    "sg:phone": "+1 614 863 0588",
    "sg:postcode": "43068",
    "sg:province": "OH",
    "sg:tags": [
      "electric",
      "contractor"
    ],
    "wof:name": "Excel Electrical Svc",
    "wof:placetype": "venue"
  },
  "geometry": {"coordinates":[-82.811354,39.959185],"type":"Point"}
}
