{
  "type": "Feature",
  "properties": {
    "addr:full": "5672 Childs Ave Cincinnati OH 45248",
    "addr:housenumber": "5672",
    "addr:postcode": "45248",
    "addr:street": "Childs Ave",
    "iso:country": "US",
    "sg:address": "5672 Childs Ave",
    "sg:city": "Cincinnati",
    "sg:classifiers": [
      {
        "category": "Retail",
        "subcategory": "Laundry \u0026 Dry Cleaning",
        "type": "Services"
      }
    ],
    "sg:phone": "+1 513 598 6604",
    "sg:postcode": "45248",
    "sg:province": "OH",
    "sg:tags": [
      "cleaners",
      "rug",
      "carpet"
    ],
    "wof:name": "Chem Dry Of Cincinnati",
    "wof:placetype": "venue"
  },
  "geometry": {"coordinates":[-84.63374,39.151648],"type":"Point"}
}
