{
  "type": "Feature",
  "properties": {
    "addr:full": "4785 Wendler Blvd Columbus OH 43230",
    "addr:housenumber": "4785",
    "addr:postcode": "43230",
    "addr:street": "Wendler Blvd",
    "iso:country": "US",
    "sg:address": "4785 Wendler Blvd",
    "sg:city": "Columbus",
    "sg:classifiers": [
      {
        "category": "Freight",
        "type": "Transportation"
      }
    ],
    "sg:phone": "+1 614 475 1389",
    "sg:postcode": "43230",
    "sg:province": "OH",
    "sg:tags": [
      "operator",
      "local",
      "mover",
      "storage",
      "trucking"
    ],
    "wof:name": "American Italian Moving",
    "wof:placetype": "venue"
  },
  "geometry": {"coordinates":[-82.891183,40.046765],"type":"Point"}
}
