{
  "type": "Feature",
  "properties": {
    "iso:country":"US",
    "sg:address":"11215 Marlette Dr",
    "sg:city":"Cincinnati",
    "sg:classifiers":[
        {
            "category":"Professional",
            "type":"Services"
        }
    ],
    "sg:phone":"+1 513 469 0609",
    "sg:postcode":"45249",
    "sg:province":"OH",
    "wof:name":"Daniel L Brenning",
    "wof:placetype":"venue"
},
  "geometry": {"coordinates":[-84.342863,39.268736],"type":"Point"}
}