{
  "type": "Feature",
  "properties": {
    "addr:full": "11487 Appleton Rd Croton OH 43013",
    "addr:housenumber": "11487",
    "addr:postcode": "43013",
    "addr:street": "Appleton Rd",
    "iso:country": "US",
    "sg:address": "11487 Appleton Rd",
    "sg:city": "Croton",
    "sg:classifiers": [
      {
        "category": "Farming",
        "subcategory": "Farm \u0026 Veterinary Services",
        "type": "Manufacturing \u0026 Wholesale Goods"
      }
    ],
    "sg:phone": "+1 740 893 3437",
    "sg:postcode": "43013",
    "sg:province": "OH",
    "sg:tags": [
      "crop"
    ],
    "wof:name": "Looker Hobert",
    "wof:placetype": "venue"
  },
  "geometry": {"coordinates":[-82.625054,40.217998],"type":"Point"}
}
