{
  "type": "Feature",
  "properties": {
    "iso:country":"US",
    "sg:address":"11487 Appleton Rd",
    "sg:city":"Croton",
    "sg:classifiers":[
        {
            "category":"Farming",
            "subcategory":"Farm & Veterinary Services",
            "type":"Manufacturing & Wholesale Goods"
        }
    ],
    "sg:phone":"+1 740 893 3437",
    "sg:postcode":"43013",
    "sg:province":"OH",
    "sg:tags":[
        "crop"
    ],
    "wof:name":"Looker Hobert",
    "wof:placetype":"venue"
},
  "geometry": {"coordinates":[-82.62505400000001,40.217998],"type":"Point"}
}