{
  "type": "Feature",
  "properties": {
    "iso:country":"US",
    "sg:address":"19348 Lucerne Rd",
    "sg:city":"Fredericktown",
    "sg:phone":"+1 740 694 2183",
    "sg:postcode":"43019",
    "sg:province":"OH",
    "sg:tags":[
        "farm",
        "corn"
    ],
    "wof:name":"Marvin Shinaberry",
    "wof:placetype":"venue"
},
  "geometry": {"coordinates":[-82.628547,40.519928],"type":"Point"}
}