{
  "type": "Feature",
  "properties": {
    "addr:full":"507 7th Ave East Liverpool OH 43920",
    "addr:housenumber":"507",
    "addr:postcode":"43920",
    "addr:street":"7Th Ave",
    "iso:country":"US",
    "sg:address":"507 7th Ave",
    "sg:city":"East Liverpool",
    "sg:classifiers":[
        {
            "category":"Organizations",
            "subcategory":"Religious Organization",
            "type":"Services"
        }
    ],
    "sg:phone":"+1 330 385 0668",
    "sg:postcode":"43920",
    "sg:province":"OH",
    "sg:tags":[
        "church"
    ],
    "wof:name":"LA Croft Church-The Nazarene",
    "wof:placetype":"venue"
},
  "geometry": {"coordinates":[-80.59865600000001,40.645583],"type":"Point"}
}