{
  "type": "Feature",
  "properties": {
    "addr:full":"5458 Fulton Dr NW Canton OH 44718",
    "addr:housenumber":"5458",
    "addr:postcode":"44718",
    "addr:street":"Fulton Dr Nw",
    "iso:country":"US",
    "sg:address":"5458 Fulton Dr NW",
    "sg:city":"Canton",
    "sg:classifiers":[
        {
            "category":"Professional",
            "subcategory":"Advertising",
            "type":"Services"
        }
    ],
    "sg:phone":"+1 330 244 1133",
    "sg:postcode":"44718",
    "sg:province":"OH",
    "sg:tags":[
        "mail"
    ],
    "wof:name":"A D Tapes",
    "wof:placetype":"venue"
},
  "geometry": {"coordinates":[-81.449381,40.85262],"type":"Point"}
}