{
  "type": "Feature",
  "properties": {
    "addr:full": "3054 17th St SW Canton OH 44706",
    "addr:housenumber": "3054",
    "addr:postcode": "44706",
    "addr:street": "17Th St Sw",
    "iso:country": "US",
    "sg:address": "3054 17th St SW",
    "sg:city": "Canton",
    "sg:classifiers": [
      {
        "category": "Organizations",
        "subcategory": "Religious Organization",
        "type": "Services"
      }
    ],
    "sg:phone": "+1 330 455 3445",
    "sg:postcode": "44706",
    "sg:province": "OH",
    "sg:tags": [
      "church"
    ],
    "wof:name": "All Nations Tabernacle",
    "wof:placetype": "venue"
  },
  "geometry": {"coordinates":[-81.411091,40.780717],"type":"Point"}
}
