{
  "type": "Feature",
  "properties": {
    "iso:country":"US",
    "sg:address":"14320 Delaware Ave",
    "sg:city":"Lakewood",
    "sg:classifiers":[
        {
            "category":"Building & Trades",
            "subcategory":"Construction",
            "type":"Services"
        }
    ],
    "sg:phone":"+1 216 221 6987",
    "sg:postcode":"44107",
    "sg:province":"OH",
    "sg:tags":[
        "deck"
    ],
    "wof:name":"Decknicians Inc",
    "wof:placetype":"venue"
},
  "geometry": {"coordinates":[-81.79332700000001,41.471199],"type":"Point"}
}