{
  "type": "Feature",
  "properties": {
    "addr:full": "14320 Delaware Ave Lakewood OH 44107",
    "addr:housenumber": "14320",
    "addr:postcode": "44107",
    "addr:street": "Delaware Ave",
    "iso:country": "US",
    "sg:address": "14320 Delaware Ave",
    "sg:city": "Lakewood",
    "sg:classifiers": [
      {
        "category": "Building \u0026 Trades",
        "subcategory": "Construction",
        "type": "Services"
      }
    ],
    "sg:phone": "+1 216 221 6987",
    "sg:postcode": "44107",
    "sg:province": "OH",
    "sg:tags": [
      "deck"
    ],
    "wof:name": "Decknicians Inc",
    "wof:placetype": "venue"
  },
  "geometry": {"coordinates":[-81.793327,41.471199],"type":"Point"}
}
