{
  "type": "Feature",
  "properties": {
    "addr:full": "887 State Rte 302 Ashland OH 44805",
    "addr:housenumber": "887",
    "addr:postcode": "44805",
    "addr:street": "State Rte 302",
    "iso:country": "US",
    "sg:address": "887 State Rte 302",
    "sg:city": "Ashland",
    "sg:classifiers": [
      {
        "category": "Farming",
        "subcategory": "Farm \u0026 Veterinary Services",
        "type": "Manufacturing \u0026 Wholesale Goods"
      }
    ],
    "sg:phone": "+1 419 207 0793",
    "sg:postcode": "44805",
    "sg:province": "OH",
    "sg:tags": [
      "crop"
    ],
    "wof:name": "Spraying Devices Inc",
    "wof:placetype": "venue"
  },
  "geometry": {"coordinates":[-82.296733,40.92824],"type":"Point"}
}
