{
  "type": "Feature",
  "properties": {
    "iso:country":"US",
    "sg:address":"19880 Detroit Rd",
    "sg:city":"Cleveland",
    "sg:classifiers":[
        {
            "category":"Banks & Credit Unions",
            "subcategory":"Bank",
            "type":"Services"
        }
    ],
    "sg:phone":"+1 440 356 8032",
    "sg:postcode":"44116",
    "sg:province":"OH",
    "wof:name":"Sky Bank",
    "wof:placetype":"venue"
},
  "geometry": {"coordinates":[-81.842326,41.479347],"type":"Point"}
}