{
  "type": "Feature",
  "properties": {
    "addr:full": "865 Glenmore Way Westerville OH 43082",
    "addr:housenumber": "865",
    "addr:postcode": "westerville oh 43082",
    "addr:street": "Glenmore Way",
    "iso:country": "US",
    "sg:address": "865 Glenmore Way",
    "sg:city": "Westerville",
    "sg:classifiers": [
      {
        "category": "Real Estate",
        "subcategory": "Real Estate Operator",
        "type": "Services"
      }
    ],
    "sg:phone": "+1 614 895 0894",
    "sg:postcode": "43082",
    "sg:province": "OH",
    "sg:tags": [
      "apartment"
    ],
    "wof:name": "Woods At Polaris Parkway",
    "wof:placetype": "venue"
  },
  "geometry": {"coordinates":[-82.929356,40.148838],"type":"Point"}
}
