{
  "type": "Feature",
  "properties": {
    "addr:full":"590 N Carroll-Erie Rd Port Clinton OH 43452",
    "addr:housenumber":"590",
    "addr:postcode":"43452",
    "addr:street":"N Carroll-Erie Rd",
    "iso:country":"US",
    "sg:address":"590 N Carroll-Erie Rd",
    "sg:city":"Port Clinton",
    "sg:phone":"+1 419 898 1799",
    "sg:postcode":"43452",
    "sg:province":"OH",
    "sg:tags":[
        "farm",
        "corn"
    ],
    "wof:name":"Don Jess",
    "wof:placetype":"venue"
},
  "geometry": {"coordinates":[-83.06795,41.522897],"type":"Point"}
}