{
  "type": "Feature",
  "properties": {
    "iso:country":"US",
    "sg:address":"485 West St",
    "sg:city":"Berea",
    "sg:classifiers":[
        {
            "category":"Organizations",
            "subcategory":"Religious Organization",
            "type":"Services"
        }
    ],
    "sg:phone":"+1 440 826 1641",
    "sg:postcode":"44017",
    "sg:province":"OH",
    "sg:tags":[
        "church"
    ],
    "wof:name":"Heritage Congregational Church",
    "wof:placetype":"venue"
},
  "geometry": {"coordinates":[-81.876,41.364538],"type":"Point"}
}