{
  "type": "Feature",
  "properties": {
    "iso:country":"US",
    "sg:address":"1061 Mc Kinley Ave",
    "sg:city":"Columbus",
    "sg:classifiers":[
        {
            "category":"Autos & Motor Vehicles",
            "subcategory":"Automobile Sales",
            "type":"Retail Goods"
        }
    ],
    "sg:phone":"+1 614 486 5488",
    "sg:postcode":"43222",
    "sg:province":"OH",
    "sg:tags":[
        "used"
    ],
    "wof:name":"Pars Automotive",
    "wof:placetype":"venue"
},
  "geometry": {"coordinates":[-83.032024,39.963228],"type":"Point"}
}