{
  "type": "Feature",
  "properties": {
    "addr:full": "1061 Mc Kinley Ave Columbus OH 43222",
    "addr:housenumber": "1061",
    "addr:postcode": "43222",
    "addr:street": "Mc Kinley Ave",
    "iso:country": "US",
    "sg:address": "1061 Mc Kinley Ave",
    "sg:city": "Columbus",
    "sg:classifiers": [
      {
        "category": "Autos \u0026 Motor Vehicles",
        "subcategory": "Automobile Sales",
        "type": "Retail Goods"
      }
    ],
    "sg:phone": "+1 614 486 5488",
    "sg:postcode": "43222",
    "sg:province": "OH",
    "sg:tags": [
      "used"
    ],
    "wof:name": "Pars Automotive",
    "wof:placetype": "venue"
  },
  "geometry": {"coordinates":[-83.032024,39.963228],"type":"Point"}
}
