{
  "type": "Feature",
  "properties": {
    "addr:full": "234 W 6th Ave Lancaster OH 43130",
    "addr:housenumber": "234",
    "addr:postcode": "43130",
    "addr:street": "W 6Th Ave",
    "iso:country": "US",
    "sg:address": "234 W 6th Ave",
    "sg:city": "Lancaster",
    "sg:classifiers": [
      {
        "category": "Education",
        "subcategory": "Special Training",
        "type": "Public Place"
      }
    ],
    "sg:phone": "+1 740 654 3748",
    "sg:postcode": "43130",
    "sg:province": "OH",
    "sg:tags": [
      "instruction",
      "driving"
    ],
    "wof:name": "Carroll Lyn Driving School",
    "wof:placetype": "venue"
  },
  "geometry": {"coordinates":[-82.604565,39.719902],"type":"Point"}
}
