{
  "type": "Feature",
  "properties": {
    "iso:country":"US",
    "sg:address":"1451 S Main St",
    "sg:city":"Bellefontaine",
    "sg:classifiers":[
        {
            "category":"Professional",
            "subcategory":"Management & Consulting",
            "type":"Services"
        }
    ],
    "sg:phone":"+1 937 599 1156",
    "sg:postcode":"43311",
    "sg:province":"OH",
    "sg:tags":[
        "personnel",
        "consultant"
    ],
    "wof:name":"CBS Personnel",
    "wof:placetype":"venue"
},
  "geometry": {"coordinates":[-83.76181,40.341344],"type":"Point"}
}