{
  "type": "Feature",
  "properties": {
    "addr:full": "12 N Lincoln St Wilmington OH 45177",
    "addr:housenumber": "12",
    "addr:postcode": "45177",
    "addr:street": "N Lincoln St",
    "iso:country": "US",
    "sg:address": "12 N Lincoln St",
    "sg:city": "Wilmington",
    "sg:classifiers": [
      {
        "category": "Real Estate",
        "subcategory": "Real Estate Agent",
        "type": "Services"
      }
    ],
    "sg:phone": "+1 937 382 2112",
    "sg:postcode": "45177",
    "sg:province": "OH",
    "sg:website": "www.century21complete.com",
    "wof:name": "Century 21 Complete Realty",
    "wof:placetype": "venue"
  },
  "geometry": {"coordinates":[-83.825431,39.446271],"type":"Point"}
}
