{
  "type": "Feature",
  "properties": {
    "iso:country":"US",
    "sg:address":"204 Country Club Dr",
    "sg:city":"Oxford",
    "sg:classifiers":[
        {
            "category":"Professional",
            "subcategory":"Business Services",
            "type":"Services"
        }
    ],
    "sg:phone":"+1 513 524 1735",
    "sg:postcode":"45056",
    "sg:province":"OH",
    "sg:tags":[
        "interior",
        "consultant",
        "design",
        "decorator"
    ],
    "wof:name":"M H Interiors",
    "wof:placetype":"venue"
},
  "geometry": {"coordinates":[-84.76548099999999,39.518108],"type":"Point"}
}