{
  "type": "Feature",
  "properties": {
    "addr:full": "204 Country Club Dr Oxford OH 45056",
    "addr:housenumber": "204",
    "addr:postcode": "45056",
    "addr:street": "Country Club Dr",
    "iso:country": "US",
    "sg:address": "204 Country Club Dr",
    "sg:city": "Oxford",
    "sg:classifiers": [
      {
        "category": "Professional",
        "subcategory": "Business Services",
        "type": "Services"
      }
    ],
    "sg:phone": "+1 513 524 1735",
    "sg:postcode": "45056",
    "sg:province": "OH",
    "sg:tags": [
      "interior",
      "consultant",
      "design",
      "decorator"
    ],
    "wof:name": "M H Interiors",
    "wof:placetype": "venue"
  },
  "geometry": {"coordinates":[-84.765481,39.518108],"type":"Point"}
}
