{
  "type": "Feature",
  "properties": {
    "addr:full":"10 Erie Rd Willoughby OH 44095",
    "addr:housenumber":"10",
    "addr:postcode":"44095",
    "addr:street":"Erie Rd",
    "iso:country":"US",
    "sg:address":"10 Erie Rd",
    "sg:city":"Willoughby",
    "sg:classifiers":[
        {
            "category":"Wholesale",
            "subcategory":"Construction Materials",
            "type":"Manufacturing & Wholesale Goods"
        }
    ],
    "sg:phone":"+1 440 951 1031",
    "sg:postcode":"44095",
    "sg:province":"OH",
    "sg:tags":[
        "coal",
        "product",
        "combustion"
    ],
    "wof:name":"Headwarters",
    "wof:placetype":"venue"
},
  "geometry": {"coordinates":[-81.43953399999999,41.674461],"type":"Point"}
}