{
  "type": "Feature",
  "properties": {
    "addr:full": "2525 Home Orchard Dr Springfield OH 45503",
    "addr:housenumber": "2525",
    "addr:postcode": "45503",
    "addr:street": "Home Orchard Dr",
    "iso:country": "US",
    "sg:address": "2525 Home Orchard Dr",
    "sg:city": "Springfield",
    "sg:classifiers": [
      {
        "category": "Building \u0026 Trades",
        "subcategory": "Landscaping Services",
        "type": "Services"
      }
    ],
    "sg:phone": "+1 937 399 3418",
    "sg:postcode": "45503",
    "sg:province": "OH",
    "sg:tags": [
      "landscape",
      "contractor"
    ],
    "wof:name": "Brennan's Lawn Maintenance",
    "wof:placetype": "venue"
  },
  "geometry": {"coordinates":[-83.791535,39.957715],"type":"Point"}
}
