{
  "type": "Feature",
  "properties": {
    "addr:full": "3231 Central Park W Toledo OH 43617",
    "addr:housenumber": "3231",
    "addr:postcode": "43617",
    "addr:street": "Central Park W",
    "iso:country": "US",
    "sg:address": "3231 Central Park W",
    "sg:city": "Toledo",
    "sg:classifiers": [
      {
        "category": "Banks \u0026 Credit Unions",
        "subcategory": "Investment Brokerage",
        "type": "Services"
      }
    ],
    "sg:phone": "+1 419 841 0060",
    "sg:postcode": "43617",
    "sg:province": "OH",
    "sg:tags": [
      "consultant",
      "planning",
      "financial"
    ],
    "wof:name": "Ron Gould \u0026 Assoc LLC",
    "wof:placetype": "venue"
  },
  "geometry": {"coordinates":[-83.700556,41.676135],"type":"Point"}
}
