{
  "type": "Feature",
  "properties": {
    "iso:country":"US",
    "sg:address":"26979 Arbor Ln",
    "sg:city":"Olmsted Falls",
    "sg:classifiers":[
        {
            "category":"Building & Trades",
            "subcategory":"Landscaping Services",
            "type":"Services"
        }
    ],
    "sg:phone":"+1 440 427 1578",
    "sg:postcode":"44138",
    "sg:province":"OH",
    "sg:tags":[
        "landscape"
    ],
    "wof:name":"Jones Landscapes Inc",
    "wof:placetype":"venue"
},
  "geometry": {"coordinates":[-81.934046,41.379568],"type":"Point"}
}