{
  "type": "Feature",
  "properties": {
    "addr:full": "26979 Arbor Ln Olmsted Falls OH 44138",
    "addr:housenumber": "26979",
    "addr:postcode": "44138",
    "addr:street": "Arbor Ln",
    "iso:country": "US",
    "sg:address": "26979 Arbor Ln",
    "sg:city": "Olmsted Falls",
    "sg:classifiers": [
      {
        "category": "Building \u0026 Trades",
        "subcategory": "Landscaping Services",
        "type": "Services"
      }
    ],
    "sg:phone": "+1 440 427 1578",
    "sg:postcode": "44138",
    "sg:province": "OH",
    "sg:tags": [
      "landscape"
    ],
    "wof:name": "Jones Landscapes Inc",
    "wof:placetype": "venue"
  },
  "geometry": {"coordinates":[-81.934046,41.379568],"type":"Point"}
}
