{
  "type": "Feature",
  "properties": {
    "addr:full": "24247 Lorain Ave North Olmsted OH 44070",
    "addr:housenumber": "24247",
    "addr:postcode": "44070",
    "addr:street": "Lorain Ave",
    "iso:country": "US",
    "sg:address": "24247 Lorain Ave",
    "sg:city": "North Olmsted",
    "sg:classifiers": [
      {
        "category": "Restaurant",
        "type": "Food \u0026 Drink"
      }
    ],
    "sg:phone": "+1 440 779 9150",
    "sg:postcode": "44070",
    "sg:province": "OH",
    "sg:tags": [
      "eating"
    ],
    "wof:name": "Taco Bell",
    "wof:placetype": "venue"
  },
  "geometry": {"coordinates":[-81.878307,41.441766],"type":"Point"}
}
