{
  "type": "Feature",
  "properties": {
    "addr:full":"2949 Millville Shandon Rd Hamilton IN 45013",
    "addr:housenumber":"2949",
    "addr:postcode":"45013",
    "addr:street":"Shandon Rd",
    "iso:country":"US",
    "sg:address":"2949 Millville Shandon Rd",
    "sg:city":"Hamilton",
    "sg:classifiers":[
        {
            "category":"Freight",
            "type":"Transportation"
        }
    ],
    "sg:phone":"+1 513 738 4339",
    "sg:postcode":"45013",
    "sg:province":"IN",
    "sg:tags":[
        "operator",
        "local",
        "trucking"
    ],
    "wof:name":"Boos Trucking",
    "wof:placetype":"venue"
},
  "geometry": {"coordinates":[-84.718219,39.343193],"type":"Point"}
}