{
  "type": "Feature",
  "properties": {
    "addr:full": "142 Austin St Fremont OH 43420",
    "addr:housenumber": "142",
    "addr:postcode": "43420",
    "addr:street": "Austin St",
    "iso:country": "US",
    "sg:address": "142 Austin St",
    "sg:city": "Fremont",
    "sg:classifiers": [
      {
        "category": "Retail",
        "subcategory": "Laundry \u0026 Dry Cleaning",
        "type": "Services"
      }
    ],
    "sg:phone": "+1 419 332 5951",
    "sg:postcode": "43420",
    "sg:province": "OH",
    "sg:tags": [
      "cleaners"
    ],
    "wof:name": "Quality Cleaners Inc",
    "wof:placetype": "venue"
  },
  "geometry": {"coordinates":[-83.130866,41.346617],"type":"Point"}
}
