{
  "type": "Feature",
  "properties": {
    "addr:full": "6956 Tradewinds Ct Hamilton OH 45011",
    "addr:housenumber": "6956",
    "addr:postcode": "45011",
    "addr:street": "Tradewinds Ct",
    "iso:country": "US",
    "sg:address": "6956 Tradewinds Ct",
    "sg:city": "Hamilton",
    "sg:classifiers": [
      {
        "category": "Professional",
        "type": "Services"
      }
    ],
    "sg:phone": "+1 513 887 6100",
    "sg:postcode": "45011",
    "sg:province": "OH",
    "sg:tags": [
      "establishment"
    ],
    "wof:name": "Direct Marketing Solutions",
    "wof:placetype": "venue"
  },
  "geometry": {"coordinates":[-84.446228,39.37895],"type":"Point"}
}
