{
  "type": "Feature",
  "properties": {
    "addr:full": "8761 Shepard Rd Macedonia OH 44056",
    "addr:housenumber": "8761",
    "addr:postcode": "44056",
    "addr:street": "Shepard Rd",
    "iso:country": "US",
    "sg:address": "8761 Shepard Rd",
    "sg:city": "Macedonia",
    "sg:classifiers": [
      {
        "category": "Social Services",
        "type": "Services"
      }
    ],
    "sg:phone": "+1 330 467 8366",
    "sg:postcode": "44056",
    "sg:province": "OH",
    "sg:tags": [
      "membership"
    ],
    "wof:name": "Young Mens Christian Assn",
    "wof:placetype": "venue"
  },
  "geometry": {"coordinates":[-81.489142,41.311848],"type":"Point"}
}
