{
  "type": "Feature",
  "properties": {
    "addr:full": "1057 Wellfleet Dr Grafton OH 44044",
    "addr:housenumber": "1057",
    "addr:postcode": "44044",
    "addr:street": "Wellfleet Dr",
    "iso:country": "US",
    "sg:address": "1057 Wellfleet Dr",
    "sg:city": "Grafton",
    "sg:classifiers": [
      {
        "category": "Shopping",
        "type": "Retail Goods"
      }
    ],
    "sg:phone": "+1 440 926 9016",
    "sg:postcode": "44044",
    "sg:province": "OH",
    "sg:tags": [
      "computer",
      "merchandise"
    ],
    "wof:name": "Celda Enterprises",
    "wof:placetype": "venue"
  },
  "geometry": {"coordinates":[-82.060771,41.284675],"type":"Point"}
}
