{
  "type": "Feature",
  "properties": {
    "addr:full": "3730 Hallock Young Rd Newton Falls OH 44444",
    "addr:postcode": "3730;44444",
    "addr:street": "Young Rd",
    "iso:country": "US",
    "sg:address": "3730 Hallock Young Rd",
    "sg:city": "Newton Falls",
    "sg:classifiers": [
      {
        "category": "Farming",
        "subcategory": "Farm",
        "type": "Manufacturing \u0026 Wholesale Goods"
      }
    ],
    "sg:phone": "+1 330 872 5213",
    "sg:postcode": "44444",
    "sg:province": "OH",
    "sg:tags": [
      "crop",
      "general"
    ],
    "wof:name": "Sleepy Hollow Farms",
    "wof:placetype": "venue"
  },
  "geometry": {"coordinates":[-80.924439,41.144145],"type":"Point"}
}
