{
  "type": "Feature",
  "properties": {
    "addr:full": "2200 Donald Rd Bethel OH 45106",
    "addr:housenumber": "2200",
    "addr:postcode": "45106",
    "addr:street": "Donald Rd",
    "iso:country": "US",
    "sg:address": "2200 Donald Rd",
    "sg:city": "Bethel",
    "sg:classifiers": [
      {
        "category": "Food \u0026 Beverages",
        "subcategory": "Meat \u0026 Fish",
        "type": "Retail Goods"
      }
    ],
    "sg:phone": "+1 513 734 4002",
    "sg:postcode": "45106",
    "sg:province": "OH",
    "wof:name": "Moore S Prime Meats Inc",
    "wof:placetype": "venue"
  },
  "geometry": {"coordinates":[-84.075759,38.924566],"type":"Point"}
}
