{
  "type": "Feature",
  "properties": {
    "addr:full": "355 N Whitewoman St Coshocton OH 43812",
    "addr:housenumber": "355",
    "addr:postcode": "43812",
    "addr:street": "N Whitewoman St",
    "iso:country": "US",
    "sg:address": "355 N Whitewoman St",
    "sg:city": "Coshocton",
    "sg:classifiers": [
      {
        "category": "Shopping",
        "subcategory": "Clothing, Apparel, \u0026 Fashions",
        "type": "Retail Goods"
      }
    ],
    "sg:phone": "+1 740 295 0284",
    "sg:postcode": "43812",
    "sg:province": "OH",
    "sg:tags": [
      "leather"
    ],
    "wof:name": "River Ridge Leather",
    "wof:placetype": "venue"
  },
  "geometry": {"coordinates":[-81.877409,40.276307],"type":"Point"}
}
