{
  "type": "Feature",
  "properties": {
    "addr:full": "458 Lake Rd NE Lancaster OH 43130",
    "addr:housenumber": "458",
    "addr:postcode": "43130",
    "addr:street": "Lake Rd Ne",
    "iso:country": "US",
    "sg:address": "458 Lake Rd NE",
    "sg:city": "Lancaster",
    "sg:classifiers": [
      {
        "category": "Insurance",
        "subcategory": "Insurance Agent",
        "type": "Services"
      }
    ],
    "sg:phone": "+1 740 536 7755",
    "sg:postcode": "43130",
    "sg:province": "OH",
    "wof:name": "Multi State Insurance",
    "wof:placetype": "venue"
  },
  "geometry": {"coordinates":[-82.497799,39.720206],"type":"Point"}
}
