{
  "type": "Feature",
  "properties": {
    "addr:full":"502 S Main St Niles OH 44446",
    "addr:housenumber":"502",
    "addr:postcode":"44446",
    "addr:street":"S Main St",
    "iso:country":"US",
    "sg:address":"502 S Main St",
    "sg:city":"Niles",
    "sg:classifiers":[
        {
            "category":"Professional",
            "type":"Services"
        }
    ],
    "sg:phone":"+1 330 505 3392",
    "sg:postcode":"44446",
    "sg:province":"OH",
    "wof:name":"Isle",
    "wof:placetype":"venue"
},
  "geometry": {"coordinates":[-80.767678,41.173067],"type":"Point"}
}