{
  "type": "Feature",
  "properties": {
    "iso:country":"US",
    "sg:address":"814 Carini Ln",
    "sg:city":"Cincinnati",
    "sg:classifiers":[
        {
            "category":"Wholesale",
            "subcategory":"Durable Goods & Equipment",
            "type":"Manufacturing & Wholesale Goods"
        }
    ],
    "sg:phone":"+1 513 825 2617",
    "sg:postcode":"45218",
    "sg:province":"OH",
    "sg:tags":[
        "representative",
        "manufacturer"
    ],
    "wof:name":"William G Baker & Assoc Inc",
    "wof:placetype":"venue"
},
  "geometry": {"coordinates":[-84.508872,39.262843],"type":"Point"}
}