{
  "type": "Feature",
  "properties": {
    "addr:full": "814 Carini Ln Cincinnati OH 45218",
    "addr:housenumber": "814",
    "addr:postcode": "45218",
    "addr:street": "Carini Ln",
    "iso:country": "US",
    "sg:address": "814 Carini Ln",
    "sg:city": "Cincinnati",
    "sg:classifiers": [
      {
        "category": "Wholesale",
        "subcategory": "Durable Goods \u0026 Equipment",
        "type": "Manufacturing \u0026 Wholesale Goods"
      }
    ],
    "sg:phone": "+1 513 825 2617",
    "sg:postcode": "45218",
    "sg:province": "OH",
    "sg:tags": [
      "representative",
      "manufacturer"
    ],
    "wof:name": "William G Baker \u0026 Assoc Inc",
    "wof:placetype": "venue"
  },
  "geometry": {"coordinates":[-84.508872,39.262843],"type":"Point"}
}
