{
  "type": "Feature",
  "properties": {
    "addr:full": "4140 N Crogan St Port Clinton OH 43452",
    "addr:housenumber": "4140",
    "addr:postcode": "43452",
    "addr:street": "N Crogan St",
    "iso:country": "US",
    "sg:address": "4140 N Crogan St",
    "sg:city": "Port Clinton",
    "sg:classifiers": [
      {
        "category": "Restaurant",
        "type": "Food \u0026 Drink"
      }
    ],
    "sg:phone": "+1 419 797 4454",
    "sg:postcode": "43452",
    "sg:province": "OH",
    "wof:name": "Point Bar \u0026 Grille",
    "wof:placetype": "venue"
  },
  "geometry": {"coordinates":[-82.836535,41.583799],"type":"Point"}
}
