{
  "type": "Feature",
  "properties": {
    "iso:country":"US",
    "sg:address":"4140 N Crogan St",
    "sg:city":"Port Clinton",
    "sg:classifiers":[
        {
            "category":"Restaurant",
            "type":"Food & Drink"
        }
    ],
    "sg:phone":"+1 419 797 4454",
    "sg:postcode":"43452",
    "sg:province":"OH",
    "wof:name":"Point Bar & Grille",
    "wof:placetype":"venue"
},
  "geometry": {"coordinates":[-82.836535,41.583799],"type":"Point"}
}