{
  "type": "Feature",
  "properties": {
    "iso:country":"US",
    "sg:address":"2535 Fixler Rd",
    "sg:city":"Wadsworth",
    "sg:classifiers":[
        {
            "category":"Building & Trades",
            "subcategory":"Construction",
            "type":"Services"
        }
    ],
    "sg:phone":"+1 330 334 4468",
    "sg:postcode":"44281",
    "sg:province":"OH",
    "sg:tags":[
        "repair",
        "masonry",
        "stone",
        "exterior",
        "pointing"
    ],
    "wof:name":"A-1 Restoration Inc",
    "wof:placetype":"venue"
},
  "geometry": {"coordinates":[-81.779022,41.081262],"type":"Point"}
}