{
  "type": "Feature",
  "properties": {
    "addr:full": "9 N Lake St Madison OH 44057",
    "addr:housenumber": "9",
    "addr:postcode": "44057",
    "addr:street": "N Lake St",
    "iso:country": "US",
    "sg:address": "9 N Lake St",
    "sg:city": "Madison",
    "sg:classifiers": [
      {
        "category": "Professional",
        "type": "Services"
      }
    ],
    "sg:phone": "+1 440 428 3227",
    "sg:postcode": "44057",
    "sg:province": "OH",
    "sg:tags": [
      "establishment"
    ],
    "wof:name": "Perfection Employees",
    "wof:placetype": "venue"
  },
  "geometry": {"coordinates":[-81.047218,41.772081],"type":"Point"}
}
