{
  "type": "Feature",
  "properties": {
    "addr:full": "20793 US Hwy 24 Defiance OH 43512",
    "addr:housenumber": "20793",
    "addr:postcode": "43512",
    "addr:street": "Us Hwy 24",
    "iso:country": "US",
    "sg:address": "20793 US Hwy 24",
    "sg:city": "Defiance",
    "sg:classifiers": [
      {
        "category": "Autos \u0026 Motor Vehicles",
        "subcategory": "Automobile Sales",
        "type": "Retail Goods"
      }
    ],
    "sg:phone": "+1 419 784 5444",
    "sg:postcode": "43512",
    "sg:province": "OH",
    "sg:tags": [
      "car",
      "dealer"
    ],
    "sg:website": "www.markmoatsford.com",
    "wof:name": "Mark Moats Ford-Mercury",
    "wof:placetype": "venue"
  },
  "geometry": {"coordinates":[-84.354904,41.308349],"type":"Point"}
}
