{
  "type": "Feature",
  "properties": {
    "addr:full": "1241 Twp Rd 593 Ashland OH 44805",
    "addr:housenumber": "1241;593",
    "addr:postcode": "44805",
    "addr:street": "Twp Rd",
    "iso:country": "US",
    "sg:address": "1241 Twp Rd 593",
    "sg:city": "Ashland",
    "sg:classifiers": [
      {
        "category": "Farming",
        "subcategory": "Farm",
        "type": "Manufacturing \u0026 Wholesale Goods"
      }
    ],
    "sg:phone": "+1 419 281 0919",
    "sg:postcode": "44805",
    "sg:province": "OH",
    "sg:tags": [
      "crop",
      "general"
    ],
    "wof:name": "Mark Crist",
    "wof:placetype": "venue"
  },
  "geometry": {"coordinates":[-82.240047,40.881106],"type":"Point"}
}
