{
  "type": "Feature",
  "properties": {
    "addr:full": "1737 Steese Rd Uniontown OH 44685",
    "addr:housenumber": "1737",
    "addr:postcode": "44685",
    "addr:street": "Steese Rd",
    "iso:country": "US",
    "sg:address": "1737 Steese Rd",
    "sg:city": "Uniontown",
    "sg:classifiers": [
      {
        "category": "Education",
        "subcategory": "School",
        "type": "Public Place"
      }
    ],
    "sg:phone": "+1 330 896 7700",
    "sg:postcode": "44685",
    "sg:province": "OH",
    "sg:website": "www.greenschools.org",
    "wof:name": "Green Intermediate School",
    "wof:placetype": "venue"
  },
  "geometry": {"coordinates":[-81.475802,40.947802],"type":"Point"}
}
