{
  "type": "Feature",
  "properties": {
    "iso:country":"US",
    "sg:address":"1006 Solida Rd",
    "sg:city":"South Point",
    "sg:classifiers":[
        {
            "category":"Utilities",
            "subcategory":"Natural Gas",
            "type":"Services"
        }
    ],
    "sg:phone":"+1 740 894 5704",
    "sg:postcode":"45680",
    "sg:province":"OH",
    "sg:tags":[
        "transmission"
    ],
    "wof:name":"Columbia Gas Transmission Corp",
    "wof:placetype":"venue"
},
  "geometry": {"coordinates":[-82.56554199999999,38.425559],"type":"Point"}
}