{
  "type": "Feature",
  "properties": {
    "addr:full": "1006 Solida Rd South Point OH 45680",
    "addr:housenumber": "1006",
    "addr:postcode": "45680",
    "addr:street": "Solida Rd",
    "iso:country": "US",
    "sg:address": "1006 Solida Rd",
    "sg:city": "South Point",
    "sg:classifiers": [
      {
        "category": "Utilities",
        "subcategory": "Natural Gas",
        "type": "Services"
      }
    ],
    "sg:phone": "+1 740 894 5704",
    "sg:postcode": "45680",
    "sg:province": "OH",
    "sg:tags": [
      "transmission"
    ],
    "wof:name": "Columbia Gas Transmission Corp",
    "wof:placetype": "venue"
  },
  "geometry": {"coordinates":[-82.565542,38.425559],"type":"Point"}
}
