{
  "type": "Feature",
  "properties": {
    "addr:full": "3505 Armstrong Rd Wooster OH 44691",
    "addr:housenumber": "3505",
    "addr:postcode": "44691",
    "addr:street": "Armstrong Rd",
    "iso:country": "US",
    "sg:address": "3505 Armstrong Rd",
    "sg:city": "Wooster",
    "sg:classifiers": [
      {
        "category": "Building \u0026 Trades",
        "subcategory": "Construction",
        "type": "Services"
      }
    ],
    "sg:phone": "+1 330 345 7116",
    "sg:postcode": "44691",
    "sg:province": "OH",
    "sg:tags": [
      "masonry",
      "contractor"
    ],
    "wof:name": "Morse Construction",
    "wof:placetype": "venue"
  },
  "geometry": {"coordinates":[-82.004209,40.901186],"type":"Point"}
}
