{
  "type": "Feature",
  "properties": {
    "iso:country":"US",
    "sg:address":"3505 Armstrong Rd",
    "sg:city":"Wooster",
    "sg:classifiers":[
        {
            "category":"Building & Trades",
            "subcategory":"Construction",
            "type":"Services"
        }
    ],
    "sg:phone":"+1 330 345 7116",
    "sg:postcode":"44691",
    "sg:province":"OH",
    "sg:tags":[
        "masonry",
        "contractor"
    ],
    "wof:name":"Morse Construction",
    "wof:placetype":"venue"
},
  "geometry": {"coordinates":[-82.004209,40.901186],"type":"Point"}
}