{
  "type": "Feature",
  "properties": {
    "iso:country":"US",
    "sg:address":"1587 W River Rd N",
    "sg:city":"Elyria",
    "sg:classifiers":[
        {
            "category":"Banks & Credit Unions",
            "subcategory":"Bank",
            "type":"Services"
        }
    ],
    "sg:phone":"+1 440 324 6033",
    "sg:postcode":"44035",
    "sg:province":"OH",
    "sg:tags":[
        "loan",
        "financing",
        "real estate"
    ],
    "wof:name":"Household Finance",
    "wof:placetype":"venue"
},
  "geometry": {"coordinates":[-82.106324,41.394143],"type":"Point"}
}