{
  "type": "Feature",
  "properties": {
    "addr:full": "1587 W River Rd N Elyria OH 44035",
    "addr:housenumber": "1587",
    "addr:postcode": "44035",
    "addr:street": "W River Rd N",
    "iso:country": "US",
    "sg:address": "1587 W River Rd N",
    "sg:city": "Elyria",
    "sg:classifiers": [
      {
        "category": "Banks \u0026 Credit Unions",
        "subcategory": "Bank",
        "type": "Services"
      }
    ],
    "sg:phone": "+1 440 324 6033",
    "sg:postcode": "44035",
    "sg:province": "OH",
    "sg:tags": [
      "loan",
      "financing",
      "real estate"
    ],
    "wof:name": "Household Finance",
    "wof:placetype": "venue"
  },
  "geometry": {"coordinates":[-82.106324,41.394143],"type":"Point"}
}
