{
  "type": "Feature",
  "properties": {
    "iso:country":"US",
    "sg:address":"404 Cumberland St",
    "sg:city":"Caldwell",
    "sg:classifiers":[
        {
            "category":"Personal",
            "subcategory":"Beauty Salon",
            "type":"Services"
        }
    ],
    "sg:phone":"+1 740 732 1523",
    "sg:postcode":"43724",
    "sg:province":"OH",
    "wof:name":"Hair On The Square",
    "wof:placetype":"venue"
},
  "geometry": {"coordinates":[-81.51554299999999,39.747247],"type":"Point"}
}