{
  "type": "Feature",
  "properties": {
    "iso:country":"US",
    "sg:address":"4239 Loubell Ln",
    "sg:city":"Cincinnati",
    "sg:classifiers":[
        {
            "category":"Building & Trades",
            "subcategory":"Construction",
            "type":"Services"
        }
    ],
    "sg:phone":"+1 513 471 3130",
    "sg:postcode":"45205",
    "sg:province":"OH",
    "sg:tags":[
        "concrete",
        "contractor"
    ],
    "wof:name":"Concrete Specialties",
    "wof:placetype":"venue"
},
  "geometry": {"coordinates":[-84.592017,39.1066],"type":"Point"}
}