{
  "type": "Feature",
  "properties": {
    "addr:full": "2865 State Rd Cuyahoga Falls OH 44223",
    "addr:housenumber": "2865",
    "addr:postcode": "44223",
    "addr:street": "State Rd",
    "iso:country": "US",
    "sg:address": "2865 State Rd",
    "sg:city": "Cuyahoga Falls",
    "sg:classifiers": [
      {
        "category": "Shopping",
        "subcategory": "Gifts \u0026 Souvenirs",
        "type": "Retail Goods"
      }
    ],
    "sg:phone": "+1 330 929 7324",
    "sg:postcode": "44223",
    "sg:province": "OH",
    "sg:tags": [
      "shop"
    ],
    "wof:name": "Loren's Hallmark",
    "wof:placetype": "venue"
  },
  "geometry": {"coordinates":[-81.508445,41.149962],"type":"Point"}
}
