{
  "type": "Feature",
  "properties": {
    "iso:country":"US",
    "sg:address":"100 N 4th St",
    "sg:city":"Steubenville",
    "sg:classifiers":[
        {
            "category":"Banks & Credit Unions",
            "subcategory":"Bank",
            "type":"Services"
        }
    ],
    "sg:phone":"+1 740 284 1039",
    "sg:postcode":"43952",
    "sg:province":"OH",
    "sg:tags":[
        "loan",
        "broker",
        "real estate"
    ],
    "wof:name":"Mountain State Lending",
    "wof:placetype":"venue"
},
  "geometry": {"coordinates":[-80.614932,40.360497],"type":"Point"}
}