{
  "type": "Feature",
  "properties": {
    "addr:full": "100 N 4th St Steubenville OH 43952",
    "addr:housenumber": "100",
    "addr:postcode": "43952",
    "addr:street": "N 4Th St",
    "iso:country": "US",
    "sg:address": "100 N 4th St",
    "sg:city": "Steubenville",
    "sg:classifiers": [
      {
        "category": "Banks \u0026 Credit Unions",
        "subcategory": "Bank",
        "type": "Services"
      }
    ],
    "sg:phone": "+1 740 284 1039",
    "sg:postcode": "43952",
    "sg:province": "OH",
    "sg:tags": [
      "loan",
      "broker",
      "real estate"
    ],
    "wof:name": "Mountain State Lending",
    "wof:placetype": "venue"
  },
  "geometry": {"coordinates":[-80.614932,40.360497],"type":"Point"}
}
