{
  "type": "Feature",
  "properties": {
    "addr:full": "6784 Loop Rd Dayton OH 45459",
    "addr:housenumber": "6784",
    "addr:postcode": "45459",
    "addr:street": "Loop Rd",
    "iso:country": "US",
    "sg:address": "6784 Loop Rd",
    "sg:city": "Dayton",
    "sg:classifiers": [
      {
        "category": "Banks \u0026 Credit Unions",
        "subcategory": "Bank",
        "type": "Services"
      }
    ],
    "sg:phone": "+1 937 435 6020",
    "sg:postcode": "45459",
    "sg:province": "OH",
    "sg:tags": [
      "broker",
      "mortgage"
    ],
    "wof:name": "Select Mortgage",
    "wof:placetype": "venue"
  },
  "geometry": {"coordinates":[-84.148207,39.643775],"type":"Point"}
}
