{
  "type": "Feature",
  "properties": {
    "iso:country":"US",
    "sg:address":"6784 Loop Rd",
    "sg:city":"Dayton",
    "sg:classifiers":[
        {
            "category":"Banks & Credit Unions",
            "subcategory":"Bank",
            "type":"Services"
        }
    ],
    "sg:phone":"+1 937 435 6020",
    "sg:postcode":"45459",
    "sg:province":"OH",
    "sg:tags":[
        "broker",
        "mortgage"
    ],
    "wof:name":"Select Mortgage",
    "wof:placetype":"venue"
},
  "geometry": {"coordinates":[-84.148207,39.643775],"type":"Point"}
}