{
  "type": "Feature",
  "properties": {
    "addr:full": "1400 Seidel Pkwy Piqua OH 45356",
    "addr:housenumber": "1400",
    "addr:postcode": "45356",
    "addr:street": "Seidel Pkwy",
    "iso:country": "US",
    "sg:address": "1400 Seidel Pkwy",
    "sg:city": "Piqua",
    "sg:classifiers": [
      {
        "category": "Organizations",
        "subcategory": "Religious Organization",
        "type": "Services"
      }
    ],
    "sg:phone": "+1 937 773 6877",
    "sg:postcode": "45356",
    "sg:province": "OH",
    "sg:tags": [
      "church"
    ],
    "wof:name": "Upper Valley Community Church",
    "wof:placetype": "venue"
  },
  "geometry": {"coordinates":[-84.21873,40.165264],"type":"Point"}
}
