{
  "type": "Feature",
  "properties": {
    "addr:full": "6421 E Main St Reynoldsburg OH 43068",
    "addr:housenumber": "6421",
    "addr:postcode": "43068",
    "addr:street": "E Main St",
    "iso:country": "US",
    "sg:address": "6421 E Main St",
    "sg:city": "Reynoldsburg",
    "sg:classifiers": [
      {
        "category": "Education",
        "subcategory": "Special Training",
        "type": "Public Place"
      }
    ],
    "sg:phone": "+1 614 866 1882",
    "sg:postcode": "43068",
    "sg:province": "OH",
    "sg:tags": [
      "instruction",
      "driving"
    ],
    "sg:website": "www.columbusdrivingacademy.com",
    "wof:name": "Columbus Driving Academy Inc",
    "wof:placetype": "venue"
  },
  "geometry": {"coordinates":[-82.821725,39.954841],"type":"Point"}
}
