{
  "type": "Feature",
  "properties": {
    "addr:full": "3001 Elm Rd NE Warren OH 44483",
    "addr:housenumber": "3001",
    "addr:postcode": "44483",
    "addr:street": "Elm Rd Ne",
    "iso:country": "US",
    "sg:address": "3001 Elm Rd NE",
    "sg:city": "Warren",
    "sg:classifiers": [
      {
        "category": "Restaurant",
        "type": "Food \u0026 Drink"
      }
    ],
    "sg:menulink": "http://www.allmenus.com/oh/warren/134418-subway/menu/",
    "sg:phone": "+1 330 372 5600",
    "sg:postcode": "44483",
    "sg:province": "OH",
    "sg:tags": [
      "american",
      "sandwich"
    ],
    "wof:name": "Subway",
    "wof:placetype": "venue"
  },
  "geometry": {"coordinates":[-80.783532,41.262557],"type":"Point"}
}
