{
  "type": "Feature",
  "properties": {
    "iso:country":"US",
    "sg:address":"3001 Elm Rd NE",
    "sg:city":"Warren",
    "sg:classifiers":[
        {
            "category":"Restaurant",
            "type":"Food & Drink"
        }
    ],
    "sg:menulink":"http://www.allmenus.com/oh/warren/134418-subway/menu/",
    "sg:phone":"+1 330 372 5600",
    "sg:postcode":"44483",
    "sg:province":"OH",
    "sg:tags":[
        "american",
        "sandwich"
    ],
    "wof:name":"Subway",
    "wof:placetype":"venue"
},
  "geometry": {"coordinates":[-80.78353199999999,41.262557],"type":"Point"}
}