{
  "type": "Feature",
  "properties": {
    "addr:full": "4750 E National Rd Springfield OH 45505",
    "addr:housenumber": "4750",
    "addr:postcode": "45505",
    "addr:street": "E National Rd",
    "iso:country": "US",
    "sg:address": "4750 E National Rd",
    "sg:city": "Springfield",
    "sg:classifiers": [
      {
        "category": "Wholesale",
        "subcategory": "Durable Goods \u0026 Equipment",
        "type": "Manufacturing \u0026 Wholesale Goods"
      }
    ],
    "sg:phone": "+1 937 325 1412",
    "sg:postcode": "45505",
    "sg:province": "OH",
    "sg:tags": [
      "antique"
    ],
    "wof:name": "Knights Antiques",
    "wof:placetype": "venue"
  },
  "geometry": {"coordinates":[-83.712381,39.923365],"type":"Point"}
}
