{
  "type": "Feature",
  "properties": {
    "addr:full": "25335 Letchworth Rd Cleveland OH 44122",
    "addr:postcode": "25335;44122",
    "addr:street": "Letchworth Rd",
    "iso:country": "US",
    "sg:address": "25335 Letchworth Rd",
    "sg:city": "Cleveland",
    "sg:classifiers": [
      {
        "category": "Insurance",
        "subcategory": "Insurance Agent",
        "type": "Services"
      }
    ],
    "sg:phone": "+1 216 696 1333",
    "sg:postcode": "44122",
    "sg:province": "OH",
    "wof:name": "Simmerson \u0026 Walter Insurance",
    "wof:placetype": "venue"
  },
  "geometry": {"coordinates":[-81.499767,41.472139],"type":"Point"}
}
