{
  "type": "Feature",
  "properties": {
    "addr:full":"15937 E Liverpool Rd East Liverpool OH 43920",
    "addr:housenumber":"15937",
    "addr:postcode":"43920",
    "addr:street":"E Liverpool Rd",
    "iso:country":"US",
    "sg:address":"15937 E Liverpool Rd",
    "sg:city":"East Liverpool",
    "sg:classifiers":[
        {
            "category":"Home & Garden",
            "subcategory":"Household Appliances",
            "type":"Retail Goods"
        }
    ],
    "sg:phone":"+1 330 386 9550",
    "sg:postcode":"43920",
    "sg:province":"OH",
    "wof:name":"Sears Roebuck & Co",
    "wof:placetype":"venue"
},
  "geometry": {"coordinates":[-80.601766,40.67013],"type":"Point"}
}