{
  "type": "Feature",
  "properties": {
    "iso:country":"US",
    "sg:address":"221 E 4th St",
    "sg:city":"Cincinnati",
    "sg:classifiers":[
        {
            "category":"Manufacturing",
            "subcategory":"Food",
            "type":"Manufacturing & Wholesale Goods"
        }
    ],
    "sg:phone":"+1 513 723 4487",
    "sg:postcode":"45202",
    "sg:province":"OH",
    "sg:tags":[
        "desert",
        "ice",
        "mfg"
    ],
    "wof:name":"Welsh Farms LLC",
    "wof:placetype":"venue"
},
  "geometry": {"coordinates":[-84.509175,39.100366],"type":"Point"}
}