{
  "type": "Feature",
  "properties": {
    "addr:full": "221 E 4th St Cincinnati OH 45202",
    "addr:housenumber": "221",
    "addr:postcode": "45202",
    "addr:street": "E 4Th St",
    "iso:country": "US",
    "sg:address": "221 E 4th St",
    "sg:city": "Cincinnati",
    "sg:classifiers": [
      {
        "category": "Manufacturing",
        "subcategory": "Food",
        "type": "Manufacturing \u0026 Wholesale Goods"
      }
    ],
    "sg:phone": "+1 513 723 4487",
    "sg:postcode": "45202",
    "sg:province": "OH",
    "sg:tags": [
      "desert",
      "ice",
      "mfg"
    ],
    "wof:name": "Welsh Farms LLC",
    "wof:placetype": "venue"
  },
  "geometry": {"coordinates":[-84.509175,39.100366],"type":"Point"}
}
