{
  "type": "Feature",
  "properties": {
    "addr:full": "3100 Old Providence Ln Westerville OH 43081",
    "addr:housenumber": "3100",
    "addr:postcode": "43081",
    "addr:street": "Old Providence Ln",
    "iso:country": "US",
    "sg:address": "3100 Old Providence Ln",
    "sg:city": "Westerville",
    "sg:classifiers": [
      {
        "category": "Real Estate",
        "subcategory": "Developer",
        "type": "Services"
      }
    ],
    "sg:phone": "+1 614 481 8269",
    "sg:postcode": "43081",
    "sg:province": "OH",
    "wof:name": "Austin Lawrence Co",
    "wof:placetype": "venue"
  },
  "geometry": {"coordinates":[-82.934572,40.09081],"type":"Point"}
}
