{
  "type": "Feature",
  "properties": {
    "iso:country":"US",
    "sg:address":"2925 Lagrange St",
    "sg:city":"Toledo",
    "sg:classifiers":[
        {
            "category":"Shopping",
            "subcategory":"Bicycles & Sporting Goods",
            "type":"Retail Goods"
        }
    ],
    "sg:phone":"+1 419 244 2802",
    "sg:postcode":"43608",
    "sg:province":"OH",
    "sg:tags":[
        "apparel",
        "bowling",
        "accessory"
    ],
    "wof:name":"Shot Makers",
    "wof:placetype":"venue"
},
  "geometry": {"coordinates":[-83.540155,41.677738],"type":"Point"}
}