{
  "type": "Feature",
  "properties": {
    "addr:full": "25 Edwards St Madison OH 44057",
    "addr:housenumber": "25",
    "addr:postcode": "44057",
    "addr:street": "Edwards St",
    "iso:country": "US",
    "sg:address": "25 Edwards St",
    "sg:city": "Madison",
    "sg:classifiers": [
      {
        "category": "Retail",
        "subcategory": "Auto Repair",
        "type": "Services"
      }
    ],
    "sg:phone": "+1 440 428 1221",
    "sg:postcode": "44057",
    "sg:province": "OH",
    "sg:tags": [
      "truck"
    ],
    "sg:website": "www.comtruckonline.com",
    "wof:name": "Commercial Truck \u0026 Fleet Svc",
    "wof:placetype": "venue"
  },
  "geometry": {"coordinates":[-81.051639,41.775741],"type":"Point"}
}
