{
  "type": "Feature",
  "properties": {
    "addr:full":"6401 Fairdale Dr Cambridge OH 43725",
    "addr:housenumber":"6401",
    "addr:postcode":"43725",
    "addr:street":"Fairdale Dr",
    "iso:country":"US",
    "sg:address":"6401 Fairdale Dr",
    "sg:city":"Cambridge",
    "sg:classifiers":[
        {
            "category":"Professional",
            "subcategory":"Business Services",
            "type":"Services"
        }
    ],
    "sg:phone":"+1 740 432 2111",
    "sg:postcode":"43725",
    "sg:province":"OH",
    "wof:name":"Wharton Business Svc",
    "wof:placetype":"venue"
},
  "geometry": {"coordinates":[-81.62192899999999,40.01435],"type":"Point"}
}