{
  "type": "Feature",
  "properties": {
    "addr:full":"4526 Bayshore Rd Oregon OH 43616",
    "addr:housenumber":"4526",
    "addr:postcode":"43616",
    "addr:street":"Bayshore Rd",
    "iso:country":"US",
    "sg:address":"4526 Bayshore Rd",
    "sg:city":"Oregon",
    "sg:classifiers":[
        {
            "category":"Retail",
            "subcategory":"Repair Shop",
            "type":"Services"
        }
    ],
    "sg:phone":"+1 419 693 5840",
    "sg:postcode":"43616",
    "sg:province":"OH",
    "sg:tags":[
        "tank",
        "cleaning"
    ],
    "wof:name":"RBM Environmental & Constr",
    "wof:placetype":"venue"
},
  "geometry": {"coordinates":[-83.441126,41.690805],"type":"Point"}
}