{
  "type": "Feature",
  "properties": {
    "iso:country":"US",
    "sg:address":"8654 Johnstown-Alexandria Rd",
    "sg:city":"Johnstown",
    "sg:classifiers":[
        {
            "category":"Sports & Exercise",
            "subcategory":"Golf",
            "type":"Entertainment"
        }
    ],
    "sg:phone":"+1 740 966 5648",
    "sg:postcode":"43031",
    "sg:province":"OH",
    "sg:tags":[
        "course",
        "public"
    ],
    "wof:name":"Clovervalley Golf Club",
    "wof:placetype":"venue"
},
  "geometry": {"coordinates":[-82.741148,40.180424],"type":"Point"}
}