{
  "type": "Feature",
  "properties": {
    "addr:full": "8654 Johnstown-Alexandria Rd Johnstown OH 43031",
    "addr:housenumber": "8654",
    "addr:postcode": "43031",
    "addr:street": "Johnstown-Alexandria Rd",
    "iso:country": "US",
    "sg:address": "8654 Johnstown-Alexandria Rd",
    "sg:city": "Johnstown",
    "sg:classifiers": [
      {
        "category": "Sports \u0026 Exercise",
        "subcategory": "Golf",
        "type": "Entertainment"
      }
    ],
    "sg:phone": "+1 740 966 5648",
    "sg:postcode": "43031",
    "sg:province": "OH",
    "sg:tags": [
      "course",
      "public"
    ],
    "wof:name": "Clovervalley Golf Club",
    "wof:placetype": "venue"
  },
  "geometry": {"coordinates":[-82.741148,40.180424],"type":"Point"}
}
