{
  "type": "Feature",
  "properties": {
    "addr:full":"114 W Tully St Convoy OH 45832",
    "addr:housenumber":"114",
    "addr:postcode":"45832",
    "addr:street":"W Tully St",
    "iso:country":"US",
    "sg:address":"114 W Tully St",
    "sg:city":"Convoy",
    "sg:classifiers":[
        {
            "category":"Personal",
            "subcategory":"Beauty Salon",
            "type":"Services"
        }
    ],
    "sg:phone":"+1 419 749 4007",
    "sg:postcode":"45832",
    "sg:province":"OH",
    "wof:name":"Sophisti-Cut",
    "wof:placetype":"venue"
},
  "geometry": {"coordinates":[-84.709245,40.916973],"type":"Point"}
}