{
  "type": "Feature",
  "properties": {
    "addr:full": "4555 London Groveport Rd Orient OH 43146",
    "addr:housenumber": "4555",
    "addr:postcode": "43146",
    "addr:street": "London Groveport Rd",
    "iso:country": "US",
    "sg:address": "4555 London Groveport Rd",
    "sg:city": "Orient",
    "sg:classifiers": [
      {
        "category": "Retail",
        "subcategory": "Auto Repair",
        "type": "Services"
      }
    ],
    "sg:phone": "+1 614 871 2620",
    "sg:postcode": "43146",
    "sg:province": "OH",
    "sg:tags": [
      "heavy",
      "equipment",
      "truck",
      "engine",
      "rebuilding"
    ],
    "wof:name": "Mid State Diesel Service \u0026 Sup",
    "wof:placetype": "venue"
  },
  "geometry": {"coordinates":[-83.127612,39.843649],"type":"Point"}
}
