{
  "type": "Feature",
  "properties": {
    "addr:full":"36055 Shaker Blvd Chagrin Falls OH 44022",
    "addr:housenumber":"36055",
    "addr:postcode":"44022",
    "addr:street":"Shaker Blvd",
    "iso:country":"US",
    "sg:address":"36055 Shaker Blvd",
    "sg:city":"Chagrin Falls",
    "sg:classifiers":[
        {
            "category":"Building & Trades",
            "subcategory":"Landscaping Services",
            "type":"Services"
        }
    ],
    "sg:phone":"+1 440 247 5696",
    "sg:postcode":"44022",
    "sg:province":"OH",
    "sg:tags":[
        "landscape"
    ],
    "wof:name":"Frederick L & Jill S Wenh",
    "wof:placetype":"venue"
},
  "geometry": {"coordinates":[-81.423613,41.478332],"type":"Point"}
}