{
  "type": "Feature",
  "properties": {
    "addr:full": "5550 Co Rd 16 Woodville OH 43469",
    "addr:housenumber": "5550;16",
    "addr:postcode": "43469",
    "addr:street": "Co Rd",
    "iso:country": "US",
    "sg:address": "5550 Co Rd 16",
    "sg:city": "Woodville",
    "sg:classifiers": [
      {
        "category": "Real Estate",
        "subcategory": "Real Estate Operator",
        "type": "Services"
      }
    ],
    "sg:phone": "+1 419 849 2107",
    "sg:postcode": "43469",
    "sg:province": "OH",
    "sg:tags": [
      "property",
      "lessor"
    ],
    "wof:name": "Bernard Schultze",
    "wof:placetype": "venue"
  },
  "geometry": {"coordinates":[-83.397247,41.49427],"type":"Point"}
}
