{
  "type": "Feature",
  "properties": {
    "iso:country":"US",
    "sg:address":"4747 Suder Ave",
    "sg:city":"Toledo",
    "sg:classifiers":[
        {
            "category":"Restaurant",
            "type":"Food & Drink"
        }
    ],
    "sg:menulink":"http://www.allmenus.com/oh/toledo/255024-china-king/menu/",
    "sg:phone":"+1 419 729 8788",
    "sg:postcode":"43611",
    "sg:province":"OH",
    "wof:name":"China King",
    "wof:placetype":"venue"
},
  "geometry": {"coordinates":[-83.498924,41.706751],"type":"Point"}
}