{
  "type": "Feature",
  "properties": {
    "iso:country":"US",
    "sg:address":"1302 Vanderbilt Rd",
    "sg:city":"Mansfield",
    "sg:classifiers":[
        {
            "category":"Building & Trades",
            "subcategory":"Plumbing",
            "type":"Services"
        }
    ],
    "sg:phone":"+1 419 886 2500",
    "sg:postcode":"44904",
    "sg:province":"OH",
    "sg:tags":[
        "heating",
        "contractor"
    ],
    "wof:name":"Clearfork Rural Heating",
    "wof:placetype":"venue"
},
  "geometry": {"coordinates":[-82.555974,40.666863],"type":"Point"}
}