{
  "type": "Feature",
  "properties": {
    "addr:full": "1709 Dubois Dr Piqua OH 45356",
    "addr:housenumber": "1709",
    "addr:postcode": "45356",
    "addr:street": "Dubois Dr",
    "iso:country": "US",
    "sg:address": "1709 Dubois Dr",
    "sg:city": "Piqua",
    "sg:classifiers": [
      {
        "category": "Shopping",
        "subcategory": "Used Merchandise",
        "type": "Retail Goods"
      }
    ],
    "sg:phone": "+1 937 773 8662",
    "sg:postcode": "45356",
    "sg:province": "OH",
    "wof:name": "Piqua Antique Mall",
    "wof:placetype": "venue"
  },
  "geometry": {"coordinates":[-84.271107,40.14944],"type":"Point"}
}
