{
  "type": "Feature",
  "properties": {
    "addr:full": "1555 Basil Dr Columbus OH 43227",
    "addr:housenumber": "1555",
    "addr:postcode": "43227",
    "addr:street": "Basil Dr",
    "iso:country": "US",
    "sg:address": "1555 Basil Dr",
    "sg:city": "Columbus",
    "sg:classifiers": [
      {
        "category": "Building \u0026 Trades",
        "subcategory": "Plumbing",
        "type": "Services"
      }
    ],
    "sg:phone": "+1 614 575 8324",
    "sg:postcode": "43227",
    "sg:province": "OH",
    "sg:tags": [
      "conditioning",
      "air",
      "system",
      "contractor"
    ],
    "wof:name": "Climatech Heating \u0026 Air Condg",
    "wof:placetype": "venue"
  },
  "geometry": {"coordinates":[-82.895682,39.940153],"type":"Point"}
}
