{
  "type": "Feature",
  "properties": {
    "iso:country":"US",
    "sg:address":"1555 Basil Dr",
    "sg:city":"Columbus",
    "sg:classifiers":[
        {
            "category":"Building & Trades",
            "subcategory":"Plumbing",
            "type":"Services"
        }
    ],
    "sg:phone":"+1 614 575 8324",
    "sg:postcode":"43227",
    "sg:province":"OH",
    "sg:tags":[
        "conditioning",
        "air",
        "system",
        "contractor"
    ],
    "wof:name":"Climatech Heating & Air Condg",
    "wof:placetype":"venue"
},
  "geometry": {"coordinates":[-82.89568199999999,39.940153],"type":"Point"}
}