{
  "type": "Feature",
  "properties": {
    "addr:full": "1229 W 6th St Cleveland OH 44113",
    "addr:housenumber": "1229",
    "addr:postcode": "44113",
    "addr:street": "W 6Th St",
    "iso:country": "US",
    "sg:address": "1229 W 6th St",
    "sg:city": "Cleveland",
    "sg:classifiers": [
      {
        "category": "Bars \u0026 Pubs",
        "type": "Food \u0026 Drink"
      }
    ],
    "sg:phone": "+1 216 696 5355",
    "sg:postcode": "44113",
    "sg:province": "OH",
    "sg:tags": [
      "nightclub"
    ],
    "wof:name": "That Groovy Little Night Club",
    "wof:placetype": "venue"
  },
  "geometry": {"coordinates":[-81.699688,41.501161],"type":"Point"}
}
