{
  "type": "Feature",
  "properties": {
    "addr:full": "14610 Pearl Rd Strongsville OH 44136",
    "addr:housenumber": "14610",
    "addr:postcode": "44136",
    "addr:street": "Pearl Rd",
    "iso:country": "US",
    "sg:address": "14610 Pearl Rd",
    "sg:city": "Strongsville",
    "sg:classifiers": [
      {
        "category": "Restaurant",
        "type": "Food \u0026 Drink"
      }
    ],
    "sg:menulink": "http://www.allmenus.com/oh/strongsville/274008-sweet-mango-thai-cuisine/menu/",
    "sg:phone": "+1 440 238 9921",
    "sg:postcode": "44136",
    "sg:province": "OH",
    "sg:tags": [
      "thai",
      "asian"
    ],
    "wof:name": "Sweet Mango Thai Cuisine",
    "wof:placetype": "venue"
  },
  "geometry": {"coordinates":[-81.835463,41.308934],"type":"Point"}
}
