{
  "type": "Feature",
  "properties": {
    "addr:full":"38151 Willoughby Pkwy Willoughby OH 44094",
    "addr:housenumber":"38151",
    "addr:postcode":"44094",
    "addr:street":"Willoughby Pkwy",
    "iso:country":"US",
    "sg:address":"38151 Willoughby Pkwy",
    "sg:city":"Willoughby",
    "sg:classifiers":[
        {
            "category":"Retail",
            "subcategory":"Auto Repair",
            "type":"Services"
        }
    ],
    "sg:phone":"+1 440 918 7700",
    "sg:postcode":"44094",
    "sg:province":"OH",
    "sg:tags":[
        "repairing",
        "automobile"
    ],
    "wof:name":"First Choice Auto & Truck Rpr",
    "wof:placetype":"venue"
},
  "geometry": {"coordinates":[-81.401133,41.677972],"type":"Point"}
}