{
  "type": "Feature",
  "properties": {
    "iso:country":"US",
    "sg:address":"2357 Sullivant Ave",
    "sg:city":"Columbus",
    "sg:classifiers":[
        {
            "category":"Retail",
            "subcategory":"Auto Repair",
            "type":"Services"
        }
    ],
    "sg:phone":"+1 614 272 0587",
    "sg:postcode":"43204",
    "sg:province":"OH",
    "sg:tags":[
        "body",
        "automobile",
        "painting"
    ],
    "wof:name":"Ricardos Body Shop",
    "wof:placetype":"venue"
},
  "geometry": {"coordinates":[-83.062343,39.945606],"type":"Point"}
}