{
  "type": "Feature",
  "properties": {
    "iso:country":"US",
    "sg:address":"6340 Scioto Darby Rd",
    "sg:city":"Hilliard",
    "sg:classifiers":[
        {
            "category":"Restaurant",
            "type":"Food & Drink"
        }
    ],
    "sg:menulink":"http://www.allmenus.com/oh/norwich/99390-beef-obradys/menu/",
    "sg:phone":"+1 614 529 9464",
    "sg:postcode":"43026",
    "sg:province":"OH",
    "sg:tags":[
        "food",
        "burger",
        "american",
        "wing",
        "pub"
    ],
    "wof:name":"Beef O'Brady's",
    "wof:placetype":"venue"
},
  "geometry": {"coordinates":[-83.179896,40.033022],"type":"Point"}
}