{
  "type": "Feature",
  "properties": {
    "addr:full":"9484 Dublin Rd Powell OH 43065",
    "addr:housenumber":"9484",
    "addr:postcode":"43065",
    "addr:street":"Dublin Rd",
    "iso:country":"US",
    "sg:address":"9484 Dublin Rd",
    "sg:city":"Powell",
    "sg:classifiers":[
        {
            "category":"Real Estate",
            "subcategory":"Real Estate Agent",
            "type":"Services"
        }
    ],
    "sg:phone":"+1 614 766 2424",
    "sg:postcode":"43065",
    "sg:province":"OH",
    "wof:name":"24 Karat Real Estate Inc",
    "wof:placetype":"venue"
},
  "geometry": {"coordinates":[-83.136917,40.166805],"type":"Point"}
}