{
  "type": "Feature",
  "properties": {
    "addr:full": "11700 Station Rd Columbia Station OH 44028",
    "addr:housenumber": "11700",
    "addr:postcode": "44028",
    "addr:street": "Station Rd",
    "iso:country": "US",
    "sg:address": "11700 Station Rd",
    "sg:city": "Columbia Station",
    "sg:classifiers": [
      {
        "category": "Retail",
        "subcategory": "Repair Shop",
        "type": "Services"
      }
    ],
    "sg:phone": "+1 440 236 3737",
    "sg:postcode": "44028",
    "sg:province": "OH",
    "sg:tags": [
      "door"
    ],
    "wof:name": "Action Automatics",
    "wof:placetype": "venue"
  },
  "geometry": {"coordinates":[-81.943291,41.334284],"type":"Point"}
}
