{
  "type": "Feature",
  "properties": {
    "iso:country":"US",
    "sg:address":"10519 Madison Ave",
    "sg:city":"Cleveland",
    "sg:classifiers":[
        {
            "category":"Retail",
            "subcategory":"Auto Repair",
            "type":"Services"
        }
    ],
    "sg:phone":"+1 216 961 1024",
    "sg:postcode":"44102",
    "sg:province":"OH",
    "sg:tags":[
        "repairing",
        "automobile"
    ],
    "wof:name":"Zak & Jacob Inc",
    "wof:placetype":"venue"
},
  "geometry": {"coordinates":[-81.759685,41.476971],"type":"Point"}
}