{
  "type": "Feature",
  "properties": {
    "iso:country":"US",
    "sg:address":"117 Main St",
    "sg:city":"Corning",
    "sg:classifiers":[
        {
            "category":"Shopping",
            "subcategory":"Bicycles & Sporting Goods",
            "type":"Retail Goods"
        }
    ],
    "sg:phone":"+1 740 347 4830",
    "sg:postcode":"43730",
    "sg:province":"OH",
    "sg:tags":[
        "tackle",
        "fishing"
    ],
    "wof:name":"O J's Bait Shop",
    "wof:placetype":"venue"
},
  "geometry": {"coordinates":[-82.089277,39.602746],"type":"Point"}
}