{
  "type": "Feature",
  "properties": {
    "addr:full":"7616 Birchmont Dr Chagrin Falls OH 44022",
    "addr:housenumber":"7616",
    "addr:postcode":"44022",
    "addr:street":"Birchmont Dr",
    "iso:country":"US",
    "sg:address":"7616 Birchmont Dr",
    "sg:city":"Chagrin Falls",
    "sg:classifiers":[
        {
            "category":"Manufacturing",
            "subcategory":"Tools & Machinery",
            "type":"Manufacturing & Wholesale Goods"
        }
    ],
    "sg:phone":"+1 440 247 4547",
    "sg:postcode":"44022",
    "sg:province":"OH",
    "sg:tags":[
        "jig",
        "fixture",
        "mfg"
    ],
    "wof:name":"Sutliff Tool Co",
    "wof:placetype":"venue"
},
  "geometry": {"coordinates":[-81.36864300000001,41.436184],"type":"Point"}
}