{
  "type": "Feature",
  "properties": {
    "addr:full": "20107 Harvard Ave Cleveland OH 44122",
    "addr:housenumber": "20107",
    "addr:postcode": "44122",
    "addr:street": "Harvard Ave",
    "iso:country": "US",
    "sg:address": "20107 Harvard Ave",
    "sg:city": "Cleveland",
    "sg:classifiers": [
      {
        "category": "Personal",
        "subcategory": "Beauty Salon",
        "type": "Services"
      }
    ],
    "sg:phone": "+1 216 991 5888",
    "sg:postcode": "44122",
    "sg:province": "OH",
    "wof:name": "Foxy Jan's Salon",
    "wof:placetype": "venue"
  },
  "geometry": {"coordinates":[-81.537485,41.449935],"type":"Point"}
}
