{
  "type": "Feature",
  "properties": {
    "addr:full": "12100 Reed Hartman Hwy Cincinnati OH 45241",
    "addr:housenumber": "12100",
    "addr:postcode": "45241",
    "addr:street": "Reed Hartman Hwy",
    "iso:country": "US",
    "sg:address": "12100 Reed Hartman Hwy",
    "sg:city": "Cincinnati",
    "sg:classifiers": [
      {
        "category": "Health Services",
        "subcategory": "Nursing And Care Facility",
        "type": "Services"
      },
      {
        "category": "Real Estate",
        "subcategory": "Real Estate Operator",
        "type": "Services"
      }
    ],
    "sg:phone": "+1 513 530 9555",
    "sg:postcode": "45241",
    "sg:province": "OH",
    "sg:tags": [
      "building",
      "retirement",
      "nonresidential",
      "community",
      "intermediate",
      "home"
    ],
    "wof:name": "Brookwood Retirement Community",
    "wof:placetype": "venue"
  },
  "geometry": {"coordinates":[-84.370592,39.290955],"type":"Point"}
}
