{
  "type": "Feature",
  "properties": {
    "iso:country":"US",
    "sg:address":"2546 Commerce Blvd",
    "sg:city":"Cincinnati",
    "sg:classifiers":[
        {
            "category":"Retail",
            "subcategory":"Repair Shop",
            "type":"Services"
        }
    ],
    "sg:phone":"+1 513 772 6666",
    "sg:postcode":"45241",
    "sg:province":"OH",
    "sg:tags":[
        "heavy",
        "road"
    ],
    "wof:name":"Precision Power",
    "wof:placetype":"venue"
},
  "geometry": {"coordinates":[-84.42414599999999,39.290057],"type":"Point"}
}