{
  "type": "Feature",
  "properties": {
    "addr:full": "11029 State Rte 128 Harrison IN 45030",
    "addr:housenumber": "11029",
    "addr:postcode": "45030",
    "addr:street": "State Rte 128",
    "iso:country": "US",
    "sg:address": "11029 State Rte 128",
    "sg:city": "Harrison",
    "sg:classifiers": [
      {
        "category": "Retail",
        "subcategory": "Auto Repair",
        "type": "Services"
      }
    ],
    "sg:phone": "+1 513 738 0978",
    "sg:postcode": "45030",
    "sg:province": "IN",
    "sg:tags": [
      "repairing",
      "automobile"
    ],
    "wof:name": "D \u0026 D Automotive",
    "wof:placetype": "venue"
  },
  "geometry": {"coordinates":[-84.682001,39.27781],"type":"Point"}
}
