{
  "type": "Feature",
  "properties": {
    "addr:full":"18663 State Rte 34 Bryan OH 43506",
    "addr:housenumber":"18663",
    "addr:postcode":"43506",
    "addr:street":"State Rte 34",
    "iso:country":"US",
    "sg:address":"18663 State Rte 34",
    "sg:city":"Bryan",
    "sg:classifiers":[
        {
            "category":"Building & Trades",
            "subcategory":"Construction",
            "type":"Services"
        }
    ],
    "sg:phone":"+1 419 636 8312",
    "sg:postcode":"43506",
    "sg:province":"OH",
    "sg:tags":[
        "downspouts",
        "downspout",
        "gutter",
        "contractor"
    ],
    "wof:name":"G & D Guttermakers",
    "wof:placetype":"venue"
},
  "geometry": {"coordinates":[-84.466072,41.478127],"type":"Point"}
}