{
  "type": "Feature",
  "properties": {
    "addr:full":"17877 Saint Clair Ave Cleveland OH 44110",
    "addr:housenumber":"17877",
    "addr:postcode":"44110",
    "addr:street":"Saint Clair Ave",
    "iso:country":"US",
    "sg:address":"17877 Saint Clair Ave",
    "sg:city":"Cleveland",
    "sg:classifiers":[
        {
            "category":"Retail",
            "subcategory":"Auto Repair",
            "type":"Services"
        }
    ],
    "sg:phone":"+1 216 486 7100",
    "sg:postcode":"44110",
    "sg:province":"OH",
    "sg:tags":[
        "trailer"
    ],
    "wof:name":"Cleveland Semitrailer LLC",
    "wof:placetype":"venue"
},
  "geometry": {"coordinates":[-81.555993,41.567612],"type":"Point"}
}