{
  "type": "Feature",
  "properties": {
    "addr:full": "71 West Ave Tallmadge OH 44278",
    "addr:housenumber": "71",
    "addr:postcode": "44278",
    "addr:street": "West Ave",
    "iso:country": "US",
    "sg:address": "71 West Ave",
    "sg:city": "Tallmadge",
    "sg:classifiers": [
      {
        "category": "Real Estate",
        "subcategory": "Real Estate Agent",
        "type": "Services"
      }
    ],
    "sg:phone": "+1 330 633 5536",
    "sg:postcode": "44278",
    "sg:province": "OH",
    "wof:name": "Mosholder Realty Inc",
    "wof:placetype": "venue"
  },
  "geometry": {"coordinates":[-81.44596,41.101428],"type":"Point"}
}
