{
  "type": "Feature",
  "properties": {
    "addr:full": "1716 Victoria Ln Lima OH 45805",
    "addr:housenumber": "1716",
    "addr:postcode": "45805",
    "addr:street": "Victoria Ln",
    "iso:country": "US",
    "sg:address": "1716 Victoria Ln",
    "sg:city": "Lima",
    "sg:classifiers": [
      {
        "category": "Real Estate",
        "subcategory": "Real Estate Agent",
        "type": "Services"
      }
    ],
    "sg:phone": "+1 419 331 1199",
    "sg:postcode": "45805",
    "sg:province": "OH",
    "wof:name": "Mullenhour Rentals",
    "wof:placetype": "venue"
  },
  "geometry": {"coordinates":[-84.155415,40.75886],"type":"Point"}
}
