{
  "type": "Feature",
  "properties": {
    "addr:full": "1004 Columbus Ave Marysville OH 43040",
    "addr:housenumber": "1004",
    "addr:postcode": "43040",
    "addr:street": "Columbus Ave",
    "iso:country": "US",
    "sg:address": "1004 Columbus Ave",
    "sg:city": "Marysville",
    "sg:classifiers": [
      {
        "category": "Sports \u0026 Exercise",
        "subcategory": "Gym",
        "type": "Entertainment"
      }
    ],
    "sg:phone": "+1 937 644 2500",
    "sg:postcode": "43040",
    "sg:province": "OH",
    "sg:tags": [
      "club",
      "health",
      "studio",
      "gymnasium"
    ],
    "wof:name": "Power Fitness Ctr",
    "wof:placetype": "venue"
  },
  "geometry": {"coordinates":[-83.352442,40.232385],"type":"Point"}
}
