{
  "type": "Feature",
  "properties": {
    "addr:full":"1958 Twp Rd 115 Dillonvale OH 43917",
    "addr:housenumber":"1958",
    "addr:postcode":"43917",
    "addr:street":"Twp Rd 115",
    "iso:country":"US",
    "sg:address":"1958 Twp Rd 115",
    "sg:city":"Dillonvale",
    "sg:classifiers":[
        {
            "category":"Real Estate",
            "subcategory":"Real Estate Operator",
            "type":"Services"
        }
    ],
    "sg:phone":"+1 740 769 7210",
    "sg:postcode":"43917",
    "sg:province":"OH",
    "sg:tags":[
        "property",
        "lessor"
    ],
    "wof:name":"Lollini and Sons Inc",
    "wof:placetype":"venue"
},
  "geometry": {"coordinates":[-80.749489,40.225438],"type":"Point"}
}