{
  "type": "Feature",
  "properties": {
    "addr:full": "585 Parsons Ave Chillicothe OH 45601",
    "addr:housenumber": "585",
    "addr:postcode": "45601",
    "addr:street": "Parsons Ave",
    "iso:country": "US",
    "sg:address": "585 Parsons Ave",
    "sg:city": "Chillicothe",
    "sg:classifiers": [
      {
        "category": "Manufacturing",
        "subcategory": "Printing",
        "type": "Manufacturing \u0026 Wholesale Goods"
      }
    ],
    "sg:phone": "+1 740 773 1445",
    "sg:postcode": "45601",
    "sg:province": "OH",
    "wof:name": "Kem Printing",
    "wof:placetype": "venue"
  },
  "geometry": {"coordinates":[-83.002438,39.32358],"type":"Point"}
}
