{
  "type": "Feature",
  "properties": {
    "addr:full":"2801 Market St Youngstown OH 44507",
    "addr:housenumber":"2801",
    "addr:postcode":"44507",
    "addr:street":"Market St",
    "iso:country":"US",
    "sg:address":"2801 Market St",
    "sg:city":"Youngstown",
    "sg:classifiers":[
        {
            "category":"Government",
            "subcategory":"Court House",
            "type":"Public Place"
        }
    ],
    "sg:phone":"+1 330 740 2109",
    "sg:postcode":"44507",
    "sg:province":"OH",
    "sg:tags":[
        "county"
    ],
    "wof:name":"Mahoning County Court-Bkpg",
    "wof:placetype":"venue"
},
  "geometry": {"coordinates":[-80.65786,41.070884],"type":"Point"}
}