{
  "type": "Feature",
  "properties": {
    "iso:country":"US",
    "sg:address":"917 Eastern Ave",
    "sg:city":"Bellefontaine",
    "sg:classifiers":[
        {
            "category":"Real Estate",
            "subcategory":"Real Estate Operator",
            "type":"Services"
        }
    ],
    "sg:phone":"+1 937 593 7428",
    "sg:postcode":"43311",
    "sg:province":"OH",
    "sg:tags":[
        "property",
        "lessor"
    ],
    "wof:name":"Gary Allen",
    "wof:placetype":"venue"
},
  "geometry": {"coordinates":[-83.74117,40.356004],"type":"Point"}
}