{
  "type": "Feature",
  "properties": {
    "addr:full": "55 Public Sq Cleveland OH 44113",
    "addr:housenumber": "55",
    "addr:postcode": "44113",
    "addr:street": "Public Sq",
    "iso:country": "US",
    "sg:address": "55 Public Sq",
    "sg:city": "Cleveland",
    "sg:classifiers": [
      {
        "category": "Insurance",
        "subcategory": "Insurance Agent",
        "type": "Services"
      }
    ],
    "sg:phone": "+1 216 621 3003",
    "sg:postcode": "44113",
    "sg:province": "OH",
    "wof:name": "Grange Insurance",
    "wof:placetype": "venue"
  },
  "geometry": {"coordinates":[-81.694334,41.500371],"type":"Point"}
}
