{
  "type": "Feature",
  "properties": {
    "addr:full":"1718 E Cooke Rd Columbus OH 43224",
    "addr:housenumber":"1718",
    "addr:postcode":"43224",
    "addr:street":"E Cooke Rd",
    "iso:country":"US",
    "sg:address":"1718 E Cooke Rd",
    "sg:city":"Columbus",
    "sg:classifiers":[
        {
            "category":"Social Services",
            "subcategory":"Child Care",
            "type":"Services"
        }
    ],
    "sg:phone":"+1 614 262 8190",
    "sg:postcode":"43224",
    "sg:province":"OH",
    "sg:tags":[
        "day"
    ],
    "wof:name":"C D C S C N Linden",
    "wof:placetype":"venue"
},
  "geometry": {"coordinates":[-82.97341400000001,40.045575],"type":"Point"}
}