{
  "type": "Feature",
  "properties": {
    "iso:country":"US",
    "sg:address":"16600 W Sprague Rd",
    "sg:city":"Cleveland",
    "sg:classifiers":[
        {
            "category":"Professional",
            "subcategory":"Business Services",
            "type":"Services"
        }
    ],
    "sg:phone":"+1 440 234 2440",
    "sg:postcode":"44130",
    "sg:province":"OH",
    "sg:tags":[
        "inventory"
    ],
    "wof:name":"R G I S Inventory Specialists",
    "wof:placetype":"venue"
},
  "geometry": {"coordinates":[-81.81778199999999,41.350794],"type":"Point"}
}