{
  "type": "Feature",
  "properties": {
    "addr:full":"1330 Fulton St Port Clinton OH 43452",
    "addr:housenumber":"1330",
    "addr:postcode":"43452",
    "addr:street":"Fulton St",
    "iso:country":"US",
    "sg:address":"1330 Fulton St",
    "sg:city":"Port Clinton",
    "sg:classifiers":[
        {
            "category":"Health Services",
            "subcategory":"Nursing And Care Facility",
            "type":"Services"
        }
    ],
    "sg:phone":"+1 419 734 5506",
    "sg:postcode":"43452",
    "sg:province":"OH",
    "sg:tags":[
        "home"
    ],
    "sg:website":"www.edgewoodmanornursingcenter.com",
    "wof:name":"Edgewood Manor Nursing Ctr",
    "wof:placetype":"venue"
},
  "geometry": {"coordinates":[-82.93385600000001,41.49628],"type":"Point"}
}