{
  "type": "Feature",
  "properties": {
    "addr:full":"3822 Springfield Xenia Rd Springfield OH 45506",
    "addr:housenumber":"3822",
    "addr:postcode":"45506",
    "addr:street":"Springfield Xenia Rd",
    "iso:country":"US",
    "sg:address":"3822 Springfield Xenia Rd",
    "sg:city":"Springfield",
    "sg:classifiers":[
        {
            "category":"Building & Trades",
            "subcategory":"Construction",
            "type":"Services"
        }
    ],
    "sg:phone":"+1 937 323 2008",
    "sg:postcode":"45506",
    "sg:province":"OH",
    "sg:tags":[
        "carpentry",
        "contractor"
    ],
    "wof:name":"Mallard Cabinetry Inc",
    "wof:placetype":"venue"
},
  "geometry": {"coordinates":[-83.845705,39.870082],"type":"Point"}
}