{
  "type": "Feature",
  "properties": {
    "addr:full":"6126 Harvest Ln Toledo OH 43623",
    "addr:housenumber":"6126",
    "addr:postcode":"43623",
    "addr:street":"Harvest Ln",
    "iso:country":"US",
    "sg:address":"6126 Harvest Ln",
    "sg:city":"Toledo",
    "sg:classifiers":[
        {
            "category":"Professional",
            "subcategory":"Computer Services",
            "type":"Services"
        }
    ],
    "sg:phone":"+1 419 475 5793",
    "sg:postcode":"43623",
    "sg:province":"OH",
    "sg:tags":[
        "internet"
    ],
    "wof:name":"Advanced Digital Svc",
    "wof:placetype":"venue"
},
  "geometry": {"coordinates":[-83.634811,41.726655],"type":"Point"}
}