{
  "type": "Feature",
  "properties": {
    "addr:full": "6732 Clough Pike Cincinnati OH 45244",
    "addr:housenumber": "6732",
    "addr:postcode": "45244",
    "addr:street": "Clough Pike",
    "iso:country": "US",
    "sg:address": "6732 Clough Pike",
    "sg:city": "Cincinnati",
    "sg:classifiers": [
      {
        "category": "Food \u0026 Beverages",
        "subcategory": "Groceries \u0026 Convenience Stores",
        "type": "Retail Goods"
      }
    ],
    "sg:phone": "+1 513 232 3786",
    "sg:postcode": "45244",
    "sg:province": "OH",
    "wof:name": "Ameristop Food Marts",
    "wof:placetype": "venue"
  },
  "geometry": {"coordinates":[-84.369047,39.098708],"type":"Point"}
}
