{
  "type": "Feature",
  "properties": {
    "iso:country":"US",
    "sg:address":"6732 Clough Pike",
    "sg:city":"Cincinnati",
    "sg:classifiers":[
        {
            "category":"Food & Beverages",
            "subcategory":"Groceries & Convenience Stores",
            "type":"Retail Goods"
        }
    ],
    "sg:phone":"+1 513 232 3786",
    "sg:postcode":"45244",
    "sg:province":"OH",
    "wof:name":"Ameristop Food Marts",
    "wof:placetype":"venue"
},
  "geometry": {"coordinates":[-84.36904699999999,39.098708],"type":"Point"}
}