{
  "type": "Feature",
  "properties": {
    "iso:country":"US",
    "sg:address":"597 Main St",
    "sg:city":"Grafton",
    "sg:classifiers":[
        {
            "category":"Restaurant",
            "type":"Food & Drink"
        }
    ],
    "sg:phone":"+1 440 926 3099",
    "sg:postcode":"44044",
    "sg:province":"OH",
    "sg:tags":[
        "eating"
    ],
    "wof:name":"Harvest Cafe",
    "wof:placetype":"venue"
},
  "geometry": {"coordinates":[-82.063288,41.279818],"type":"Point"}
}