{
  "type": "Feature",
  "properties": {
    "addr:full": "597 Main St Grafton OH 44044",
    "addr:housenumber": "597",
    "addr:postcode": "44044",
    "addr:street": "Main St",
    "iso:country": "US",
    "sg:address": "597 Main St",
    "sg:city": "Grafton",
    "sg:classifiers": [
      {
        "category": "Restaurant",
        "type": "Food \u0026 Drink"
      }
    ],
    "sg:phone": "+1 440 926 3099",
    "sg:postcode": "44044",
    "sg:province": "OH",
    "sg:tags": [
      "eating"
    ],
    "wof:name": "Harvest Cafe",
    "wof:placetype": "venue"
  },
  "geometry": {"coordinates":[-82.063288,41.279818],"type":"Point"}
}
