{
  "type": "Feature",
  "properties": {
    "addr:full":"4740 Storms Creek Rd Urbana OH 43078",
    "addr:housenumber":"4740",
    "addr:postcode":"43078",
    "addr:street":"Storms Creek Rd",
    "iso:country":"US",
    "sg:address":"4740 Storms Creek Rd",
    "sg:city":"Urbana",
    "sg:classifiers":[
        {
            "category":"Building & Trades",
            "subcategory":"Construction",
            "type":"Services"
        }
    ],
    "sg:phone":"+1 937 788 2575",
    "sg:postcode":"43078",
    "sg:province":"OH",
    "sg:tags":[
        "residential",
        "commercial",
        "exterior",
        "interior",
        "painting",
        "painter"
    ],
    "wof:name":"A 1 Pro Painting",
    "wof:placetype":"venue"
},
  "geometry": {"coordinates":[-83.85915900000001,40.041135],"type":"Point"}
}