{
  "type": "Feature",
  "properties": {
    "iso:country":"US",
    "sg:address":"3322 Bishop St",
    "sg:city":"Cincinnati",
    "sg:classifiers":[
        {
            "category":"Banks & Credit Unions",
            "subcategory":"Financial Services",
            "type":"Services"
        }
    ],
    "sg:phone":"+1 513 381 6866",
    "sg:postcode":"45220",
    "sg:province":"OH",
    "sg:tags":[
        "trust",
        "investment",
        "real estate"
    ],
    "wof:name":"Restoration Plus",
    "wof:placetype":"venue"
},
  "geometry": {"coordinates":[-84.513116,39.14069],"type":"Point"}
}