{
  "type": "Feature",
  "properties": {
    "iso:country":"US",
    "sg:address":"408 Center Rd",
    "sg:city":"Akron",
    "sg:classifiers":[
        {
            "category":"Building & Trades",
            "subcategory":"Plumbing",
            "type":"Services"
        }
    ],
    "sg:phone":"+1 330 882 6094",
    "sg:postcode":"44319",
    "sg:province":"OH",
    "wof:name":"Dye Plumbing",
    "wof:placetype":"venue"
},
  "geometry": {"coordinates":[-81.549021,40.950293],"type":"Point"}
}