{
  "type": "Feature",
  "properties": {
    "addr:full": "1823 Coventry Rd Cleveland OH 44118",
    "addr:housenumber": "1823",
    "addr:postcode": "44118",
    "addr:street": "Coventry Rd",
    "iso:country": "US",
    "sg:address": "1823 Coventry Rd",
    "sg:city": "Cleveland",
    "sg:classifiers": [
      {
        "category": "Real Estate",
        "subcategory": "Architect",
        "type": "Services"
      }
    ],
    "sg:phone": "+1 216 283 6073",
    "sg:postcode": "44118",
    "sg:province": "OH",
    "wof:name": "Bocca Grille",
    "wof:placetype": "venue"
  },
  "geometry": {"coordinates":[-81.57991,41.509825],"type":"Point"}
}
