{
  "type": "Feature",
  "properties": {
    "addr:full": "1024 Mahoning Ave Youngstown OH 44502",
    "addr:housenumber": "1024",
    "addr:postcode": "44502",
    "addr:street": "Mahoning Ave",
    "iso:country": "US",
    "sg:address": "1024 Mahoning Ave",
    "sg:city": "Youngstown",
    "sg:classifiers": [
      {
        "category": "Retail",
        "subcategory": "Repair Shop",
        "type": "Services"
      }
    ],
    "sg:phone": "+1 330 747 8043",
    "sg:postcode": "44502",
    "sg:province": "OH",
    "sg:tags": [
      "refinishing",
      "furniture"
    ],
    "wof:name": "Arkwright \u0026 Anderson Furniture",
    "wof:placetype": "venue"
  },
  "geometry": {"coordinates":[-80.670003,41.101833],"type":"Point"}
}
