{
  "type": "Feature",
  "properties": {
    "addr:full": "905 Lorain Blvd Elyria OH 44035",
    "addr:housenumber": "905",
    "addr:postcode": "44035",
    "addr:street": "Lorain Blvd",
    "iso:country": "US",
    "sg:address": "905 Lorain Blvd",
    "sg:city": "Elyria",
    "sg:classifiers": [
      {
        "category": "Building \u0026 Trades",
        "subcategory": "Plumbing",
        "type": "Services"
      }
    ],
    "sg:phone": "+1 440 284 0560",
    "sg:postcode": "44035",
    "sg:province": "OH",
    "sg:tags": [
      "product",
      "management",
      "energy",
      "system"
    ],
    "wof:name": "True North Energy",
    "wof:placetype": "venue"
  },
  "geometry": {"coordinates":[-82.116591,41.389455],"type":"Point"}
}
