{
  "type": "Feature",
  "properties": {
    "addr:full": "871 Michigan Ave Columbus OH 43215",
    "addr:housenumber": "871",
    "addr:postcode": "43215",
    "addr:street": "Michigan Ave",
    "iso:country": "US",
    "sg:address": "871 Michigan Ave",
    "sg:city": "Columbus",
    "sg:classifiers": [
      {
        "category": "Wholesale",
        "subcategory": "Beer",
        "type": "Manufacturing \u0026 Wholesale Goods"
      }
    ],
    "sg:phone": "+1 614 294 3555",
    "sg:postcode": "43215",
    "sg:province": "OH",
    "sg:tags": [
      "ale"
    ],
    "sg:website": "www.bevgroup.com",
    "wof:name": "Central Beverage Group Ltd",
    "wof:placetype": "venue"
  },
  "geometry": {"coordinates":[-83.017243,39.978315],"type":"Point"}
}
