{
  "type": "Feature",
  "properties": {
    "iso:country":"US",
    "sg:address":"725 S Cable Rd",
    "sg:city":"Lima",
    "sg:classifiers":[
        {
            "category":"Professional",
            "type":"Services"
        }
    ],
    "sg:phone":"+1 419 227 1241",
    "sg:postcode":"45805",
    "sg:province":"OH",
    "sg:tags":[
        "establishment"
    ],
    "wof:name":"Ohio Cleveland Mission",
    "wof:placetype":"venue"
},
  "geometry": {"coordinates":[-84.146691,40.73076],"type":"Point"}
}