{
  "type": "Feature",
  "properties": {
    "addr:full": "725 S Cable Rd Lima OH 45805",
    "addr:housenumber": "725",
    "addr:postcode": "45805",
    "addr:street": "S Cable Rd",
    "iso:country": "US",
    "sg:address": "725 S Cable Rd",
    "sg:city": "Lima",
    "sg:classifiers": [
      {
        "category": "Professional",
        "type": "Services"
      }
    ],
    "sg:phone": "+1 419 227 1241",
    "sg:postcode": "45805",
    "sg:province": "OH",
    "sg:tags": [
      "establishment"
    ],
    "wof:name": "Ohio Cleveland Mission",
    "wof:placetype": "venue"
  },
  "geometry": {"coordinates":[-84.146691,40.73076],"type":"Point"}
}
