{
  "type": "Feature",
  "properties": {
    "addr:full":"2652 Elm Rd Cortland OH 44410",
    "addr:housenumber":"2652",
    "addr:postcode":"44410",
    "addr:street":"Elm Rd",
    "iso:country":"US",
    "sg:address":"2652 Elm Rd",
    "sg:city":"Cortland",
    "sg:classifiers":[
        {
            "category":"Health Services",
            "subcategory":"Doctor",
            "type":"Services"
        }
    ],
    "sg:phone":"+1 330 372 0372",
    "sg:postcode":"44410",
    "sg:province":"OH",
    "sg:tags":[
        "physician",
        "surgeon"
    ],
    "wof:name":"Shipman Eucker & Fealko",
    "wof:placetype":"venue"
},
  "geometry": {"coordinates":[-80.755865,41.296178],"type":"Point"}
}