{
  "type": "Feature",
  "properties": {
    "addr:full": "1147 Bechtle Ave Springfield OH 45504",
    "addr:housenumber": "1147",
    "addr:postcode": "45504",
    "addr:street": "Bechtle Ave",
    "iso:country": "US",
    "sg:address": "1147 Bechtle Ave",
    "sg:city": "Springfield",
    "sg:classifiers": [
      {
        "category": "Personal",
        "subcategory": "Beauty Salon",
        "type": "Services"
      }
    ],
    "sg:phone": "+1 937 322 8323",
    "sg:postcode": "45504",
    "sg:province": "OH",
    "wof:name": "Indentity Hair Salon",
    "wof:placetype": "venue"
  },
  "geometry": {"coordinates":[-83.835631,39.939012],"type":"Point"}
}
