{
  "type": "Feature",
  "properties": {
    "addr:full": "114 W 1st St Dayton OH 45402",
    "addr:housenumber": "114",
    "addr:postcode": "45402",
    "addr:street": "W 1St St",
    "iso:country": "US",
    "sg:address": "114 W 1st St",
    "sg:city": "Dayton",
    "sg:classifiers": [
      {
        "category": "Organizations",
        "subcategory": "Community Association",
        "type": "Services"
      }
    ],
    "sg:phone": "+1 937 640 3544",
    "sg:postcode": "45402",
    "sg:province": "OH",
    "sg:tags": [
      "club"
    ],
    "wof:name": "Prestige Dining Club",
    "wof:placetype": "venue"
  },
  "geometry": {"coordinates":[-84.195854,39.761763],"type":"Point"}
}
