{
  "type": "Feature",
  "properties": {
    "iso:country":"US",
    "sg:address":"4601 Eastgate Blvd",
    "sg:city":"Cincinnati",
    "sg:classifiers":[
        {
            "category":"Personal",
            "type":"Services"
        }
    ],
    "sg:phone":"+1 513 753 8847",
    "sg:postcode":"45245",
    "sg:province":"OH",
    "sg:tags":[
        "formal",
        "retail",
        "wear",
        "accessory",
        "rent"
    ],
    "wof:name":"Skeffingtons Formalwear Inc",
    "wof:placetype":"venue"
},
  "geometry": {"coordinates":[-84.27309099999999,39.10214],"type":"Point"}
}