{
  "type": "Feature",
  "properties": {
    "addr:full": "241 N Washington St Delaware OH 43015",
    "addr:housenumber": "241",
    "addr:postcode": "43015",
    "addr:street": "N Washington St",
    "iso:country": "US",
    "sg:address": "241 N Washington St",
    "sg:city": "Delaware",
    "sg:classifiers": [
      {
        "category": "Professional",
        "subcategory": "Accounting \u0026 Tax Preparation",
        "type": "Services"
      }
    ],
    "sg:phone": "+1 740 369 7002",
    "sg:postcode": "43015",
    "sg:province": "OH",
    "sg:tags": [
      "bookkeeping",
      "general"
    ],
    "wof:name": "Beeghley Bookkeeping Svc",
    "wof:placetype": "venue"
  },
  "geometry": {"coordinates":[-83.070704,40.306562],"type":"Point"}
}
