{
  "type": "Feature",
  "properties": {
    "iso:country":"US",
    "sg:address":"241 N Washington St",
    "sg:city":"Delaware",
    "sg:classifiers":[
        {
            "category":"Professional",
            "subcategory":"Accounting & Tax Preparation",
            "type":"Services"
        }
    ],
    "sg:phone":"+1 740 369 7002",
    "sg:postcode":"43015",
    "sg:province":"OH",
    "sg:tags":[
        "bookkeeping",
        "general"
    ],
    "wof:name":"Beeghley Bookkeeping Svc",
    "wof:placetype":"venue"
},
  "geometry": {"coordinates":[-83.07070400000001,40.306562],"type":"Point"}
}