{
  "type": "Feature",
  "properties": {
    "iso:country":"US",
    "sg:address":"5918 Lakeside Ave",
    "sg:city":"Toledo",
    "sg:classifiers":[
        {
            "category":"Wholesale",
            "subcategory":"Construction Materials",
            "type":"Manufacturing & Wholesale Goods"
        }
    ],
    "sg:phone":"+1 419 729 0670",
    "sg:postcode":"43611",
    "sg:province":"OH",
    "sg:tags":[
        "insulation"
    ],
    "wof:name":"Gerald Mc Clintick",
    "wof:placetype":"venue"
},
  "geometry": {"coordinates":[-83.463239,41.725647],"type":"Point"}
}