{
  "type": "Feature",
  "properties": {
    "addr:full": "5918 Lakeside Ave Toledo OH 43611",
    "addr:housenumber": "5918",
    "addr:postcode": "43611",
    "addr:street": "Lakeside Ave",
    "iso:country": "US",
    "sg:address": "5918 Lakeside Ave",
    "sg:city": "Toledo",
    "sg:classifiers": [
      {
        "category": "Wholesale",
        "subcategory": "Construction Materials",
        "type": "Manufacturing \u0026 Wholesale Goods"
      }
    ],
    "sg:phone": "+1 419 729 0670",
    "sg:postcode": "43611",
    "sg:province": "OH",
    "sg:tags": [
      "insulation"
    ],
    "wof:name": "Gerald Mc Clintick",
    "wof:placetype": "venue"
  },
  "geometry": {"coordinates":[-83.463239,41.725647],"type":"Point"}
}
