{
  "type": "Feature",
  "properties": {
    "addr:full": "107 S Main St Clyde OH 43410",
    "addr:housenumber": "107",
    "addr:postcode": "43410",
    "addr:street": "S Main St",
    "iso:country": "US",
    "sg:address": "107 S Main St",
    "sg:city": "Clyde",
    "sg:classifiers": [
      {
        "category": "Real Estate",
        "subcategory": "Real Estate Agent",
        "type": "Services"
      }
    ],
    "sg:phone": "+1 419 547 3800",
    "sg:postcode": "43410",
    "sg:province": "OH",
    "wof:name": "Bolte Real Estate",
    "wof:placetype": "venue"
  },
  "geometry": {"coordinates":[-82.97493,41.305139],"type":"Point"}
}
