{
  "type": "Feature",
  "properties": {
    "addr:full": "452 Zanesville Rd Roseville OH 43777",
    "addr:housenumber": "452",
    "addr:postcode": "43777",
    "addr:street": "Zanesville Rd",
    "iso:country": "US",
    "sg:address": "452 Zanesville Rd",
    "sg:city": "Roseville",
    "sg:classifiers": [
      {
        "category": "Restaurant",
        "type": "Food \u0026 Drink"
      }
    ],
    "sg:phone": "+1 740 697 9070",
    "sg:postcode": "43777",
    "sg:province": "OH",
    "sg:tags": [
      "caterer"
    ],
    "wof:name": "Nancy's Catering",
    "wof:placetype": "venue"
  },
  "geometry": {"coordinates":[-82.076691,39.814703],"type":"Point"}
}
