{
  "type": "Feature",
  "properties": {
    "iso:country":"US",
    "sg:address":"28 Station St",
    "sg:city":"Athens",
    "sg:classifiers":[
        {
            "category":"Utilities",
            "subcategory":"Cable",
            "type":"Services"
        }
    ],
    "sg:phone":"+1 740 592 4831",
    "sg:postcode":"45701",
    "sg:province":"OH",
    "sg:tags":[
        "television"
    ],
    "sg:website":"www.timewarnercable.com",
    "wof:name":"Time Warner Cable",
    "wof:placetype":"venue"
},
  "geometry": {"coordinates":[-82.108102,39.328425],"type":"Point"}
}