{
  "type": "Feature",
  "properties": {
    "iso:country":"US",
    "sg:address":"495 Andrews Ave",
    "sg:city":"Youngstown",
    "sg:classifiers":[
        {
            "category":"Wholesale",
            "subcategory":"Medical Equipment & Supplies",
            "type":"Manufacturing & Wholesale Goods"
        }
    ],
    "sg:phone":"+1 330 740 0133",
    "sg:postcode":"44505",
    "sg:province":"OH",
    "sg:tags":[
        "physician",
        "surgeon"
    ],
    "wof:name":"Tri State Med Source",
    "wof:placetype":"venue"
},
  "geometry": {"coordinates":[-80.63893899999999,41.102613],"type":"Point"}
}