{
  "type": "Feature",
  "properties": {
    "addr:full": "495 Andrews Ave Youngstown OH 44505",
    "addr:housenumber": "495",
    "addr:postcode": "44505",
    "addr:street": "Andrews Ave",
    "iso:country": "US",
    "sg:address": "495 Andrews Ave",
    "sg:city": "Youngstown",
    "sg:classifiers": [
      {
        "category": "Wholesale",
        "subcategory": "Medical Equipment \u0026 Supplies",
        "type": "Manufacturing \u0026 Wholesale Goods"
      }
    ],
    "sg:phone": "+1 330 740 0133",
    "sg:postcode": "44505",
    "sg:province": "OH",
    "sg:tags": [
      "physician",
      "surgeon"
    ],
    "wof:name": "Tri State Med Source",
    "wof:placetype": "venue"
  },
  "geometry": {"coordinates":[-80.638939,41.102613],"type":"Point"}
}
