{
  "type": "Feature",
  "properties": {
    "iso:country":"US",
    "sg:address":"3740 W Sylvania Ave",
    "sg:city":"Toledo",
    "sg:classifiers":[
        {
            "category":"Health Services",
            "subcategory":"Doctor",
            "type":"Services"
        }
    ],
    "sg:phone":"+1 419 473 6601",
    "sg:postcode":"43623",
    "sg:province":"OH",
    "sg:tags":[
        "physician",
        "surgeon"
    ],
    "wof:name":"Family Practice Of Toledo",
    "wof:placetype":"venue"
},
  "geometry": {"coordinates":[-83.635279,41.691437],"type":"Point"}
}