{
  "type": "Feature",
  "properties": {
    "addr:full": "3881 N Ridge Rd Perry OH 44081",
    "addr:housenumber": "3881",
    "addr:postcode": "44081",
    "addr:street": "N Ridge Rd",
    "iso:country": "US",
    "sg:address": "3881 N Ridge Rd",
    "sg:city": "Perry",
    "sg:classifiers": [
      {
        "category": "Autos \u0026 Motor Vehicles",
        "subcategory": "Automobile Sales",
        "type": "Retail Goods"
      }
    ],
    "sg:phone": "+1 440 259 1900",
    "sg:postcode": "44081",
    "sg:province": "OH",
    "sg:tags": [
      "car",
      "dealer"
    ],
    "wof:name": "G \u0026 M Motors",
    "wof:placetype": "venue"
  },
  "geometry": {"coordinates":[-81.150152,41.779126],"type":"Point"}
}
