{
  "type": "Feature",
  "properties": {
    "iso:country":"US",
    "sg:address":"3881 N Ridge Rd",
    "sg:city":"Perry",
    "sg:classifiers":[
        {
            "category":"Autos & Motor Vehicles",
            "subcategory":"Automobile Sales",
            "type":"Retail Goods"
        }
    ],
    "sg:phone":"+1 440 259 1900",
    "sg:postcode":"44081",
    "sg:province":"OH",
    "sg:tags":[
        "car",
        "dealer"
    ],
    "wof:name":"G & M Motors",
    "wof:placetype":"venue"
},
  "geometry": {"coordinates":[-81.15015200000001,41.779126],"type":"Point"}
}