{
  "type": "Feature",
  "properties": {
    "iso:country":"US",
    "sg:address":"5350 Cincinnati Dayton Rd",
    "sg:city":"Middletown",
    "sg:classifiers":[
        {
            "category":"Building & Trades",
            "subcategory":"Landscaping Services",
            "type":"Services"
        }
    ],
    "sg:phone":"+1 513 777 2542",
    "sg:postcode":"45044",
    "sg:province":"OH",
    "sg:tags":[
        "landscape"
    ],
    "wof:name":"City Wide Turf Inc",
    "wof:placetype":"venue"
},
  "geometry": {"coordinates":[-84.366739,39.420311],"type":"Point"}
}