{
  "type": "Feature",
  "properties": {
    "iso:country":"US",
    "sg:address":"323 Kenridge Rd",
    "sg:city":"Akron",
    "sg:classifiers":[
        {
            "category":"Professional",
            "type":"Services"
        }
    ],
    "sg:phone":"+1 330 867 0201",
    "sg:postcode":"44333",
    "sg:province":"OH",
    "wof:name":"Dague Designs",
    "wof:placetype":"venue"
},
  "geometry": {"coordinates":[-81.61157,41.125226],"type":"Point"}
}