{
  "type": "Feature",
  "properties": {
    "addr:full": "4380 Tonawanda Trl Dayton OH 45430",
    "addr:housenumber": "4380",
    "addr:postcode": "45430",
    "addr:street": "Tonawanda Trl",
    "iso:country": "US",
    "sg:address": "4380 Tonawanda Trl",
    "sg:city": "Dayton",
    "sg:classifiers": [
      {
        "category": "Professional",
        "subcategory": "Accounting \u0026 Tax Preparation",
        "type": "Services"
      }
    ],
    "sg:phone": "+1 937 427 1000",
    "sg:postcode": "45430",
    "sg:province": "OH",
    "sg:tags": [
      "accountant"
    ],
    "wof:name": "Burris \u0026 Co",
    "wof:placetype": "venue"
  },
  "geometry": {"coordinates":[-84.099533,39.69783],"type":"Point"}
}
