{
  "type": "Feature",
  "properties": {
    "iso:country":"US",
    "sg:address":"4380 Tonawanda Trl",
    "sg:city":"Dayton",
    "sg:classifiers":[
        {
            "category":"Professional",
            "subcategory":"Accounting & Tax Preparation",
            "type":"Services"
        }
    ],
    "sg:phone":"+1 937 427 1000",
    "sg:postcode":"45430",
    "sg:province":"OH",
    "sg:tags":[
        "accountant"
    ],
    "wof:name":"Burris & Co",
    "wof:placetype":"venue"
},
  "geometry": {"coordinates":[-84.09953299999999,39.69783],"type":"Point"}
}