{
  "type": "Feature",
  "properties": {
    "iso:country":"US",
    "sg:address":"91 State Rte 56 NW",
    "sg:city":"London",
    "sg:classifiers":[
        {
            "category":"Education",
            "subcategory":"School",
            "type":"Public Place"
        }
    ],
    "sg:phone":"+1 740 852 7350",
    "sg:postcode":"43140",
    "sg:province":"OH",
    "sg:tags":[
        "elementary"
    ],
    "wof:name":"Somerford Elementary School",
    "wof:placetype":"venue"
},
  "geometry": {"coordinates":[-83.49485199999999,39.937734],"type":"Point"}
}