{
  "type": "Feature",
  "properties": {
    "addr:full": "467 N Spring St Wilmington OH 45177",
    "addr:housenumber": "467",
    "addr:postcode": "45177",
    "addr:street": "N Spring St",
    "iso:country": "US",
    "sg:address": "467 N Spring St",
    "sg:city": "Wilmington",
    "sg:classifiers": [
      {
        "category": "Building \u0026 Trades",
        "subcategory": "Landscaping Services",
        "type": "Services"
      }
    ],
    "sg:phone": "+1 937 382 7514",
    "sg:postcode": "45177",
    "sg:province": "OH",
    "sg:tags": [
      "landscape"
    ],
    "wof:name": "J\u0026G",
    "wof:placetype": "venue"
  },
  "geometry": {"coordinates":[-83.831183,39.451377],"type":"Point"}
}
