{
  "type": "Feature",
  "properties": {
    "addr:full": "284 West Ave Tallmadge OH 44278",
    "addr:housenumber": "284",
    "addr:postcode": "44278",
    "addr:street": "West Ave",
    "iso:country": "US",
    "sg:address": "284 West Ave",
    "sg:city": "Tallmadge",
    "sg:classifiers": [
      {
        "category": "Restaurant",
        "type": "Food \u0026 Drink"
      }
    ],
    "sg:phone": "+1 330 633 3985",
    "sg:postcode": "44278",
    "sg:province": "OH",
    "sg:tags": [
      "shop",
      "coffee"
    ],
    "wof:name": "J's Java Hut",
    "wof:placetype": "venue"
  },
  "geometry": {"coordinates":[-81.455042,41.101746],"type":"Point"}
}
