{
  "type": "Feature",
  "properties": {
    "addr:full":"10537 Harrison Ave Harrison OH 45030",
    "addr:housenumber":"10537",
    "addr:postcode":"45030",
    "addr:street":"Harrison Ave",
    "iso:country":"US",
    "sg:address":"10537 Harrison Ave",
    "sg:city":"Harrison",
    "sg:classifiers":[
        {
            "category":"Shopping",
            "subcategory":"Hobbies, Toys, & Games",
            "type":"Retail Goods"
        }
    ],
    "sg:phone":"+1 513 202 1229",
    "sg:postcode":"45030",
    "sg:province":"OH",
    "wof:name":"Makin Memories",
    "wof:placetype":"venue"
},
  "geometry": {"coordinates":[-84.795188,39.252988],"type":"Point"}
}