{
  "type": "Feature",
  "properties": {
    "addr:full": "10620 Cedar Ave Cleveland OH 44106",
    "addr:housenumber": "10620",
    "addr:postcode": "44106",
    "addr:street": "Cedar Ave",
    "iso:country": "US",
    "sg:address": "10620 Cedar Ave",
    "sg:city": "Cleveland",
    "sg:classifiers": [
      {
        "category": "Wholesale",
        "subcategory": "Durable Goods \u0026 Equipment",
        "type": "Manufacturing \u0026 Wholesale Goods"
      }
    ],
    "sg:phone": "+1 216 231 2103",
    "sg:postcode": "44106",
    "sg:province": "OH",
    "sg:tags": [
      "laboratory",
      "supply"
    ],
    "wof:name": "Fisher Scientific",
    "wof:placetype": "venue"
  },
  "geometry": {"coordinates":[-81.612327,41.499093],"type":"Point"}
}
