{
  "type": "Feature",
  "properties": {
    "iso:country":"US",
    "sg:address":"124 N Main St",
    "sg:city":"Hubbard",
    "sg:classifiers":[
        {
            "category":"Personal",
            "subcategory":"Beauty Salon",
            "type":"Services"
        }
    ],
    "sg:phone":"+1 330 534 0911",
    "sg:postcode":"44425",
    "sg:province":"OH",
    "wof:name":"Creative Visions",
    "wof:placetype":"venue"
},
  "geometry": {"coordinates":[-80.568977,41.15781],"type":"Point"}
}