{
  "type": "Feature",
  "properties": {
    "addr:full": "499 Glenrose Ln Cincinnati OH 45244",
    "addr:housenumber": "499",
    "addr:postcode": "45244",
    "addr:street": "Glenrose Ln",
    "iso:country": "US",
    "sg:address": "499 Glenrose Ln",
    "sg:city": "Cincinnati",
    "sg:classifiers": [
      {
        "category": "Building \u0026 Trades",
        "subcategory": "Construction",
        "type": "Services"
      }
    ],
    "sg:phone": "+1 513 312 6998",
    "sg:postcode": "45244",
    "sg:province": "OH",
    "sg:tags": [
      "siding",
      "contractor"
    ],
    "wof:name": "J D Norris Siding \u0026 Windows",
    "wof:placetype": "venue"
  },
  "geometry": {"coordinates":[-84.304513,39.098744],"type":"Point"}
}
