{
  "type": "Feature",
  "properties": {
    "addr:full":"2820 S River Rd Zanesville OH 43701",
    "addr:housenumber":"2820",
    "addr:postcode":"43701",
    "addr:street":"S River Rd",
    "iso:country":"US",
    "sg:address":"2820 S River Rd",
    "sg:city":"Zanesville",
    "sg:classifiers":[
        {
            "category":"Building & Trades",
            "subcategory":"Construction",
            "type":"Services"
        }
    ],
    "sg:phone":"+1 740 453 5868",
    "sg:postcode":"43701",
    "sg:province":"OH",
    "sg:tags":[
        "welding",
        "contractor"
    ],
    "wof:name":"Bakers Welding",
    "wof:placetype":"venue"
},
  "geometry": {"coordinates":[-81.993804,39.89127],"type":"Point"}
}