{
  "type": "Feature",
  "properties": {
    "addr:full": "515 Union Ave NW New Philadelphia OH 44663",
    "addr:housenumber": "515",
    "addr:postcode": "44663",
    "addr:street": "Union Ave Nw New Philadelphia",
    "iso:country": "US",
    "sg:address": "515 Union Ave NW",
    "sg:city": "New Philadelphia",
    "sg:classifiers": [
      {
        "category": "Shopping",
        "subcategory": "Pharmacy",
        "type": "Retail Goods"
      }
    ],
    "sg:phone": "+1 330 602 4687",
    "sg:postcode": "44663",
    "sg:province": "OH",
    "wof:name": "CVS",
    "wof:placetype": "venue"
  },
  "geometry": {"coordinates":[-81.459669,40.498964],"type":"Point"}
}
