{
  "type": "Feature",
  "properties": {
    "iso:country":"US",
    "sg:address":"515 Union Ave NW",
    "sg:city":"New Philadelphia",
    "sg:classifiers":[
        {
            "category":"Shopping",
            "subcategory":"Pharmacy",
            "type":"Retail Goods"
        }
    ],
    "sg:phone":"+1 330 602 4687",
    "sg:postcode":"44663",
    "sg:province":"OH",
    "wof:name":"CVS",
    "wof:placetype":"venue"
},
  "geometry": {"coordinates":[-81.45966900000001,40.498964],"type":"Point"}
}