{
  "type": "Feature",
  "properties": {
    "addr:full": "630 S Cottage St Ashland OH 44805",
    "addr:housenumber": "630",
    "addr:postcode": "44805",
    "addr:street": "S Cottage St",
    "iso:country": "US",
    "sg:address": "630 S Cottage St",
    "sg:city": "Ashland",
    "sg:classifiers": [
      {
        "category": "Autos \u0026 Motor Vehicles",
        "subcategory": "Fuel \u0026 Gas Station",
        "type": "Retail Goods"
      }
    ],
    "sg:phone": "+1 419 281 1492",
    "sg:postcode": "44805",
    "sg:province": "OH",
    "sg:tags": [
      "grocery",
      "station",
      "gasoline"
    ],
    "wof:name": "Speedway 1408",
    "wof:placetype": "venue"
  },
  "geometry": {"coordinates":[-82.318569,40.872921],"type":"Point"}
}
