{
  "type": "Feature",
  "properties": {
    "iso:country":"US",
    "sg:address":"4315 Wales Ave NW",
    "sg:city":"Massillon",
    "sg:classifiers":[
        {
            "category":"Building & Trades",
            "subcategory":"Landscaping Services",
            "type":"Services"
        }
    ],
    "sg:phone":"+1 330 837 4315",
    "sg:postcode":"44646",
    "sg:province":"OH",
    "sg:tags":[
        "landscape"
    ],
    "wof:name":"Santora Landscaping",
    "wof:placetype":"venue"
},
  "geometry": {"coordinates":[-81.49320899999999,40.847505],"type":"Point"}
}