{
  "type": "Feature",
  "properties": {
    "iso:country":"US",
    "sg:address":"592 Presidential Dr",
    "sg:city":"Youngstown",
    "sg:classifiers":[
        {
            "category":"Wholesale",
            "subcategory":"Electrical",
            "type":"Manufacturing & Wholesale Goods"
        }
    ],
    "sg:phone":"+1 330 629 9116",
    "sg:postcode":"44512",
    "sg:province":"OH",
    "sg:tags":[
        "video",
        "disc",
        "tape"
    ],
    "sg:website":"www.ingramentertainment.com",
    "wof:name":"Ingram Entertainment",
    "wof:placetype":"venue"
},
  "geometry": {"coordinates":[-80.64215299999999,41.016561],"type":"Point"}
}