{
  "type": "Feature",
  "properties": {
    "addr:full": "592 Presidential Dr Youngstown OH 44512",
    "addr:housenumber": "592",
    "addr:postcode": "44512",
    "addr:street": "Presidential Dr",
    "iso:country": "US",
    "sg:address": "592 Presidential Dr",
    "sg:city": "Youngstown",
    "sg:classifiers": [
      {
        "category": "Wholesale",
        "subcategory": "Electrical",
        "type": "Manufacturing \u0026 Wholesale Goods"
      }
    ],
    "sg:phone": "+1 330 629 9116",
    "sg:postcode": "44512",
    "sg:province": "OH",
    "sg:tags": [
      "video",
      "disc",
      "tape"
    ],
    "sg:website": "www.ingramentertainment.com",
    "wof:name": "Ingram Entertainment",
    "wof:placetype": "venue"
  },
  "geometry": {"coordinates":[-80.642153,41.016561],"type":"Point"}
}
