{
  "type": "Feature",
  "properties": {
    "iso:country":"US",
    "sg:address":"5254 Lake Rd E",
    "sg:city":"Geneva",
    "sg:classifiers":[
        {
            "category":"Social Services",
            "subcategory":"Adult Care",
            "type":"Services"
        }
    ],
    "sg:phone":"+1 440 466 0988",
    "sg:postcode":"44041",
    "sg:province":"OH",
    "sg:tags":[
        "home",
        "residential"
    ],
    "wof:name":"Beach Club Residential",
    "wof:placetype":"venue"
},
  "geometry": {"coordinates":[-80.944993,41.86113],"type":"Point"}
}