{
  "type": "Feature",
  "properties": {
    "iso:country":"US",
    "sg:address":"4280 Oviatt Rd",
    "sg:city":"Richfield",
    "sg:classifiers":[
        {
            "category":"Restaurant",
            "type":"Food & Drink"
        }
    ],
    "sg:phone":"+1 330 659 3670",
    "sg:postcode":"44286",
    "sg:province":"OH",
    "sg:tags":[
        "eating"
    ],
    "wof:name":"El Chanro Restaurant",
    "wof:placetype":"venue"
},
  "geometry": {"coordinates":[-81.68226,41.251758],"type":"Point"}
}