{
  "type": "Feature",
  "properties": {
    "addr:full": "4280 Oviatt Rd Richfield OH 44286",
    "addr:postcode": "4280;44286",
    "addr:street": "Oviatt Rd",
    "iso:country": "US",
    "sg:address": "4280 Oviatt Rd",
    "sg:city": "Richfield",
    "sg:classifiers": [
      {
        "category": "Restaurant",
        "type": "Food \u0026 Drink"
      }
    ],
    "sg:phone": "+1 330 659 3670",
    "sg:postcode": "44286",
    "sg:province": "OH",
    "sg:tags": [
      "eating"
    ],
    "wof:name": "El Chanro Restaurant",
    "wof:placetype": "venue"
  },
  "geometry": {"coordinates":[-81.68226,41.251758],"type":"Point"}
}
