{
  "type": "Feature",
  "properties": {
    "addr:full": "425 Walnut St Cincinnati OH 45202",
    "addr:housenumber": "425",
    "addr:postcode": "45202",
    "addr:street": "Walnut St",
    "iso:country": "US",
    "sg:address": "425 Walnut St",
    "sg:city": "Cincinnati",
    "sg:classifiers": [
      {
        "category": "Banks \u0026 Credit Unions",
        "subcategory": "Investment Brokerage",
        "type": "Services"
      }
    ],
    "sg:phone": "+1 513 241 8600",
    "sg:postcode": "45202",
    "sg:province": "OH",
    "sg:tags": [
      "security",
      "stock",
      "bond"
    ],
    "sg:website": "www.lakemason.com",
    "wof:name": "Legg Mason Wood Walker Inc",
    "wof:placetype": "venue"
  },
  "geometry": {"coordinates":[-84.511373,39.100998],"type":"Point"}
}
