{
  "type": "Feature",
  "properties": {
    "iso:country":"US",
    "sg:address":"425 Walnut St",
    "sg:city":"Cincinnati",
    "sg:classifiers":[
        {
            "category":"Banks & Credit Unions",
            "subcategory":"Investment Brokerage",
            "type":"Services"
        }
    ],
    "sg:phone":"+1 513 241 8600",
    "sg:postcode":"45202",
    "sg:province":"OH",
    "sg:tags":[
        "security",
        "stock",
        "bond"
    ],
    "sg:website":"www.lakemason.com",
    "wof:name":"Legg Mason Wood Walker Inc",
    "wof:placetype":"venue"
},
  "geometry": {"coordinates":[-84.51137300000001,39.100998],"type":"Point"}
}