{
  "type": "Feature",
  "properties": {
    "addr:full":"4036 W Enon Rd Fairborn OH 45324",
    "addr:housenumber":"4036",
    "addr:postcode":"45324",
    "addr:street":"W Enon Rd",
    "iso:country":"US",
    "sg:address":"4036 W Enon Rd",
    "sg:city":"Fairborn",
    "sg:classifiers":[
        {
            "category":"Manufacturing",
            "subcategory":"Metals",
            "type":"Manufacturing & Wholesale Goods"
        }
    ],
    "sg:phone":"+1 937 767 7809",
    "sg:postcode":"45324",
    "sg:province":"OH",
    "sg:tags":[
        "steel",
        "foundry",
        "investment"
    ],
    "wof:name":"Aerospace/Energy Consultant",
    "wof:placetype":"venue"
},
  "geometry": {"coordinates":[-83.947743,39.799892],"type":"Point"}
}