{
  "type": "Feature",
  "properties": {
    "iso:country":"US",
    "sg:address":"8134 S State Rte 48",
    "sg:city":"Maineville",
    "sg:classifiers":[
        {
            "category":"Shopping",
            "subcategory":"Computers & Home Electronics",
            "type":"Retail Goods"
        }
    ],
    "sg:phone":"+1 513 697 8100",
    "sg:postcode":"45039",
    "sg:province":"OH",
    "sg:tags":[
        "equipment",
        "satellite",
        "system"
    ],
    "wof:name":"Audio Video Concepts",
    "wof:placetype":"venue"
},
  "geometry": {"coordinates":[-84.22082,39.316537],"type":"Point"}
}