{
  "type": "Feature",
  "properties": {
    "addr:full": "8134 S State Rte 48 Maineville OH 45039",
    "addr:housenumber": "8134",
    "addr:postcode": "45039",
    "addr:street": "S State Rte 48",
    "iso:country": "US",
    "sg:address": "8134 S State Rte 48",
    "sg:city": "Maineville",
    "sg:classifiers": [
      {
        "category": "Shopping",
        "subcategory": "Computers \u0026 Home Electronics",
        "type": "Retail Goods"
      }
    ],
    "sg:phone": "+1 513 697 8100",
    "sg:postcode": "45039",
    "sg:province": "OH",
    "sg:tags": [
      "equipment",
      "satellite",
      "system"
    ],
    "wof:name": "Audio Video Concepts",
    "wof:placetype": "venue"
  },
  "geometry": {"coordinates":[-84.22082,39.316537],"type":"Point"}
}
