{
  "type": "Feature",
  "properties": {
    "addr:full":"2400 Reading Rd Cincinnati OH 45206",
    "addr:housenumber":"2400",
    "addr:postcode":"45206",
    "addr:street":"Reading Rd",
    "iso:country":"US",
    "sg:address":"2400 Reading Rd",
    "sg:city":"Cincinnati",
    "sg:classifiers":[
        {
            "category":"Organizations",
            "subcategory":"Non-profit Organization",
            "type":"Services"
        }
    ],
    "sg:phone":"+1 513 721 2910",
    "sg:postcode":"45206",
    "sg:province":"OH",
    "wof:name":"Mental Health Assn",
    "wof:placetype":"venue"
},
  "geometry": {"coordinates":[-84.50183199999999,39.126684],"type":"Point"}
}