{
  "type": "Feature",
  "properties": {
    "iso:country":"US",
    "sg:address":"11145 Mount Sterling-Waterloo Rd",
    "sg:city":"Mt Sterling",
    "sg:classifiers":[
        {
            "category":"Manufacturing",
            "subcategory":"Signs",
            "type":"Manufacturing & Wholesale Goods"
        }
    ],
    "sg:phone":"+1 740 869 2194",
    "sg:postcode":"43143",
    "sg:province":"OH",
    "wof:name":"Leey Signs Graphics Inc",
    "wof:placetype":"venue"
},
  "geometry": {"coordinates":[-83.269023,39.711925],"type":"Point"}
}