{
  "type": "Feature",
  "properties": {
    "iso:country":"US",
    "sg:address":"4004 Huffman Rd",
    "sg:city":"Medina",
    "sg:classifiers":[
        {
            "category":"Professional",
            "subcategory":"Management & Consulting",
            "type":"Services"
        }
    ],
    "sg:phone":"+1 330 242 2958",
    "sg:postcode":"44256",
    "sg:province":"OH",
    "sg:tags":[
        "investor"
    ],
    "wof:name":"Ohio Land & Investment Co LLC",
    "wof:placetype":"venue"
},
  "geometry": {"coordinates":[-81.829087,41.170429],"type":"Point"}
}