{
  "type": "Feature",
  "properties": {
    "addr:full": "4004 Huffman Rd Medina OH 44256",
    "addr:housenumber": "4004",
    "addr:postcode": "44256",
    "addr:street": "Huffman Rd",
    "iso:country": "US",
    "sg:address": "4004 Huffman Rd",
    "sg:city": "Medina",
    "sg:classifiers": [
      {
        "category": "Professional",
        "subcategory": "Management \u0026 Consulting",
        "type": "Services"
      }
    ],
    "sg:phone": "+1 330 242 2958",
    "sg:postcode": "44256",
    "sg:province": "OH",
    "sg:tags": [
      "investor"
    ],
    "wof:name": "Ohio Land \u0026 Investment Co LLC",
    "wof:placetype": "venue"
  },
  "geometry": {"coordinates":[-81.829087,41.170429],"type":"Point"}
}
