{
  "type": "Feature",
  "properties": {
    "iso:country":"US",
    "sg:address":"19859 Idlewood Trl",
    "sg:city":"Strongsville",
    "sg:classifiers":[
        {
            "category":"Home & Garden",
            "subcategory":"Carpets & Floor Coverings",
            "type":"Retail Goods"
        }
    ],
    "sg:phone":"+1 440 878 9600",
    "sg:postcode":"44149",
    "sg:province":"OH",
    "sg:tags":[
        "laying",
        "contractor"
    ],
    "wof:name":"Predota Flooring",
    "wof:placetype":"venue"
},
  "geometry": {"coordinates":[-81.84366,41.328332],"type":"Point"}
}