{
  "type": "Feature",
  "properties": {
    "addr:full": "19859 Idlewood Trl Strongsville OH 44149",
    "addr:housenumber": "19859",
    "addr:postcode": "44149",
    "addr:street": "Idlewood Trl",
    "iso:country": "US",
    "sg:address": "19859 Idlewood Trl",
    "sg:city": "Strongsville",
    "sg:classifiers": [
      {
        "category": "Home \u0026 Garden",
        "subcategory": "Carpets \u0026 Floor Coverings",
        "type": "Retail Goods"
      }
    ],
    "sg:phone": "+1 440 878 9600",
    "sg:postcode": "44149",
    "sg:province": "OH",
    "sg:tags": [
      "laying",
      "contractor"
    ],
    "wof:name": "Predota Flooring",
    "wof:placetype": "venue"
  },
  "geometry": {"coordinates":[-81.84366,41.328332],"type":"Point"}
}
