{
  "type": "Feature",
  "properties": {
    "addr:full":"212 Lancaster Pike Circleville OH 43113",
    "addr:housenumber":"212",
    "addr:postcode":"43113",
    "addr:street":"Lancaster Pike",
    "iso:country":"US",
    "sg:address":"212 Lancaster Pike",
    "sg:city":"Circleville",
    "sg:classifiers":[
        {
            "category":"Shopping",
            "subcategory":"Pharmacy",
            "type":"Retail Goods"
        }
    ],
    "sg:phone":"+1 740 474 1971",
    "sg:postcode":"43113",
    "sg:province":"OH",
    "sg:tags":[
        "drug",
        "store"
    ],
    "wof:name":"Medicine Shoppe The",
    "wof:placetype":"venue"
},
  "geometry": {"coordinates":[-82.93162599999999,39.599293],"type":"Point"}
}