{
  "type": "Feature",
  "properties": {
    "addr:full": "2700 Hamilton Mason Rd Hamilton OH 45011",
    "addr:housenumber": "2700",
    "addr:postcode": "45011",
    "addr:street": "Hamilton Mason Rd",
    "iso:country": "US",
    "sg:address": "2700 Hamilton Mason Rd",
    "sg:city": "Hamilton",
    "sg:classifiers": [
      {
        "category": "Building \u0026 Trades",
        "subcategory": "Plumbing",
        "type": "Services"
      }
    ],
    "sg:phone": "+1 513 868 2702",
    "sg:postcode": "45011",
    "sg:province": "OH",
    "sg:tags": [
      "contractor"
    ],
    "wof:name": "Curry Plumbing Inc",
    "wof:placetype": "venue"
  },
  "geometry": {"coordinates":[-84.527215,39.380389],"type":"Point"}
}
