{
  "type": "Feature",
  "properties": {
    "iso:country":"US",
    "sg:address":"335 Hess Rd",
    "sg:city":"Washington Ct Hs",
    "sg:classifiers":[
        {
            "category":"Personal",
            "type":"Services"
        }
    ],
    "sg:phone":"+1 740 333 3314",
    "sg:postcode":"43160",
    "sg:province":"OH",
    "sg:tags":[
        "therapist",
        "massage"
    ],
    "wof:name":"Pamela Runyons Relaxation",
    "wof:placetype":"venue"
},
  "geometry": {"coordinates":[-83.334858,39.552046],"type":"Point"}
}