{
  "type": "Feature",
  "properties": {
    "iso:country":"US",
    "sg:address":"728 Keystone Furnace Rd",
    "sg:city":"Jackson",
    "sg:classifiers":[
        {
            "category":"Freight",
            "type":"Transportation"
        }
    ],
    "sg:phone":"+1 740 286 8913",
    "sg:postcode":"45640",
    "sg:province":"OH",
    "sg:tags":[
        "operator",
        "trucking"
    ],
    "wof:name":"Newsom Trucking",
    "wof:placetype":"venue"
},
  "geometry": {"coordinates":[-82.594811,39.036892],"type":"Point"}
}