{
  "type": "Feature",
  "properties": {
    "addr:full":"1842 Pulver Rd Mansfield OH 44903",
    "addr:housenumber":"1842",
    "addr:postcode":"44903",
    "addr:street":"Pulver Rd",
    "iso:country":"US",
    "sg:address":"1842 Pulver Rd",
    "sg:city":"Mansfield",
    "sg:classifiers":[
        {
            "category":"Food & Beverages",
            "subcategory":"Specialty",
            "type":"Retail Goods"
        }
    ],
    "sg:phone":"+1 419 524 0565",
    "sg:postcode":"44903",
    "sg:province":"OH",
    "wof:name":"Spiess French Fries",
    "wof:placetype":"venue"
},
  "geometry": {"coordinates":[-82.455084,40.70881],"type":"Point"}
}