{
  "type": "Feature",
  "properties": {
    "addr:full": "7899 Columbia Rd SW Pataskala OH 43062",
    "addr:housenumber": "7899",
    "addr:postcode": "43062",
    "addr:street": "Columbia Rd Sw",
    "iso:country": "US",
    "sg:address": "7899 Columbia Rd SW",
    "sg:city": "Pataskala",
    "sg:classifiers": [
      {
        "category": "Real Estate",
        "subcategory": "Developer",
        "type": "Services"
      }
    ],
    "sg:phone": "+1 740 524 7400",
    "sg:postcode": "43062",
    "sg:province": "OH",
    "wof:name": "KASS Corp",
    "wof:placetype": "venue"
  },
  "geometry": {"coordinates":[-82.695525,39.977759],"type":"Point"}
}
