{
  "type": "Feature",
  "properties": {
    "iso:country":"US",
    "sg:address":"7070 Spinach Dr",
    "sg:city":"Mentor",
    "sg:classifiers":[
        {
            "category":"Manufacturing",
            "subcategory":"Chemicals & Compounds",
            "type":"Manufacturing & Wholesale Goods"
        }
    ],
    "sg:phone":"+1 440 205 8739",
    "sg:postcode":"44060",
    "sg:province":"OH",
    "sg:tags":[
        "adhesive",
        "sealant"
    ],
    "wof:name":"Avery Dennison Corp",
    "wof:placetype":"venue"
},
  "geometry": {"coordinates":[-81.34434,41.680354],"type":"Point"}
}