{
  "type": "Feature",
  "properties": {
    "addr:full": "7070 Spinach Dr Mentor OH 44060",
    "addr:housenumber": "7070",
    "addr:postcode": "44060",
    "addr:street": "Spinach",
    "iso:country": "US",
    "sg:address": "7070 Spinach Dr",
    "sg:city": "Mentor",
    "sg:classifiers": [
      {
        "category": "Manufacturing",
        "subcategory": "Chemicals \u0026 Compounds",
        "type": "Manufacturing \u0026 Wholesale Goods"
      }
    ],
    "sg:phone": "+1 440 205 8739",
    "sg:postcode": "44060",
    "sg:province": "OH",
    "sg:tags": [
      "adhesive",
      "sealant"
    ],
    "wof:name": "Avery Dennison Corp",
    "wof:placetype": "venue"
  },
  "geometry": {"coordinates":[-81.34434,41.680354],"type":"Point"}
}
