{
  "type": "Feature",
  "properties": {
    "iso:country":"US",
    "sg:address":"1338 Westphal Ave",
    "sg:city":"Columbus",
    "sg:classifiers":[
        {
            "category":"Wholesale",
            "subcategory":"Groceries",
            "type":"Manufacturing & Wholesale Goods"
        }
    ],
    "sg:phone":"+1 614 239 7802",
    "sg:postcode":"43227",
    "sg:province":"OH",
    "sg:tags":[
        "water",
        "bottled"
    ],
    "wof:name":"Ice Springs Bottled Water Inc",
    "wof:placetype":"venue"
},
  "geometry": {"coordinates":[-82.882838,39.949377],"type":"Point"}
}