{
  "type": "Feature",
  "properties": {
    "addr:full": "1338 Westphal Ave Columbus OH 43227",
    "addr:housenumber": "1338",
    "addr:postcode": "43227",
    "addr:street": "Westphal Ave",
    "iso:country": "US",
    "sg:address": "1338 Westphal Ave",
    "sg:city": "Columbus",
    "sg:classifiers": [
      {
        "category": "Wholesale",
        "subcategory": "Groceries",
        "type": "Manufacturing \u0026 Wholesale Goods"
      }
    ],
    "sg:phone": "+1 614 239 7802",
    "sg:postcode": "43227",
    "sg:province": "OH",
    "sg:tags": [
      "water",
      "bottled"
    ],
    "wof:name": "Ice Springs Bottled Water Inc",
    "wof:placetype": "venue"
  },
  "geometry": {"coordinates":[-82.882838,39.949377],"type":"Point"}
}
