{
  "type": "Feature",
  "properties": {
    "addr:full":"771 N Garland Ave Youngstown OH 44506",
    "addr:housenumber":"771",
    "addr:postcode":"44506",
    "addr:street":"N Garland Ave",
    "iso:country":"US",
    "sg:address":"771 N Garland Ave",
    "sg:city":"Youngstown",
    "sg:classifiers":[
        {
            "category":"Building & Trades",
            "subcategory":"Construction",
            "type":"Services"
        }
    ],
    "sg:phone":"+1 330 743 3966",
    "sg:postcode":"44506",
    "sg:province":"OH",
    "sg:tags":[
        "maintenance",
        "contractor"
    ],
    "wof:name":"OTM Maintenance",
    "wof:placetype":"venue"
},
  "geometry": {"coordinates":[-80.628362,41.109274],"type":"Point"}
}