{
  "type": "Feature",
  "properties": {
    "iso:country":"US",
    "sg:address":"2328 Florence Ave",
    "sg:city":"Cincinnati",
    "sg:classifiers":[
        {
            "category":"Retail",
            "subcategory":"Auto Repair",
            "type":"Services"
        }
    ],
    "sg:phone":"+1 513 961 6000",
    "sg:postcode":"45206",
    "sg:province":"OH",
    "sg:tags":[
        "repairing",
        "automobile"
    ],
    "wof:name":"Berry's Auto",
    "wof:placetype":"venue"
},
  "geometry": {"coordinates":[-84.493582,39.122459],"type":"Point"}
}