{
  "type": "Feature",
  "properties": {
    "addr:full": "515 Natalie Ln Lebanon OH 45036",
    "addr:housenumber": "515",
    "addr:postcode": "45036",
    "addr:street": "Natalie Ln",
    "iso:country": "US",
    "sg:address": "515 Natalie Ln",
    "sg:city": "Lebanon",
    "sg:classifiers": [
      {
        "category": "Building \u0026 Trades",
        "subcategory": "Construction",
        "type": "Services"
      }
    ],
    "sg:phone": "+1 513 933 9149",
    "sg:postcode": "45036",
    "sg:province": "OH",
    "sg:tags": [
      "house"
    ],
    "wof:name": "Pete Wagner Construction",
    "wof:placetype": "venue"
  },
  "geometry": {"coordinates":[-84.22391,39.408522],"type":"Point"}
}
