{
  "type": "Feature",
  "properties": {
    "iso:country":"US",
    "sg:address":"3611 Socialville Foster Rd",
    "sg:city":"Mason",
    "sg:classifiers":[
        {
            "category":"Banks & Credit Unions",
            "subcategory":"Bank",
            "type":"Services"
        }
    ],
    "sg:phone":"+1 513 398 1044",
    "sg:postcode":"45040",
    "sg:province":"OH",
    "sg:tags":[
        "loan",
        "real estate"
    ],
    "wof:name":"Queen City Funding LLC",
    "wof:placetype":"venue"
},
  "geometry": {"coordinates":[-84.28622,39.321315],"type":"Point"}
}