{
  "type": "Feature",
  "properties": {
    "addr:full": "4901 Reading Rd Cincinnati OH 45237",
    "addr:housenumber": "4901",
    "addr:postcode": "45237",
    "addr:street": "Reading Rd",
    "iso:country": "US",
    "sg:address": "4901 Reading Rd",
    "sg:city": "Cincinnati",
    "sg:classifiers": [
      {
        "category": "Wholesale",
        "subcategory": "Electrical",
        "type": "Manufacturing \u0026 Wholesale Goods"
      }
    ],
    "sg:phone": "+1 513 242 4777",
    "sg:postcode": "45237",
    "sg:province": "OH",
    "sg:tags": [
      "mobile",
      "telephone"
    ],
    "wof:name": "Wireless Connection",
    "wof:placetype": "venue"
  },
  "geometry": {"coordinates":[-84.466753,39.176169],"type":"Point"}
}
