{
  "type": "Feature",
  "properties": {
    "iso:country":"US",
    "sg:address":"973 Harrisburg Pike",
    "sg:city":"Columbus",
    "sg:classifiers":[
        {
            "category":"Shopping",
            "subcategory":"Books",
            "type":"Retail Goods"
        }
    ],
    "sg:phone":"+1 614 272 1373",
    "sg:postcode":"43223",
    "sg:province":"OH",
    "sg:tags":[
        "dealer"
    ],
    "wof:name":"Lions Den",
    "wof:placetype":"venue"
},
  "geometry": {"coordinates":[-83.042633,39.936816],"type":"Point"}
}