{
  "type": "Feature",
  "properties": {
    "iso:country":"US",
    "sg:address":"734 Sand Ridge Rd",
    "sg:city":"Bowling Green",
    "sg:classifiers":[
        {
            "category":"Shopping",
            "subcategory":"Books",
            "type":"Retail Goods"
        }
    ],
    "sg:phone":"+1 419 352 8207",
    "sg:postcode":"43402",
    "sg:province":"OH",
    "sg:website":"www.gideons.org",
    "wof:name":"Gideons International",
    "wof:placetype":"venue"
},
  "geometry": {"coordinates":[-83.660489,41.363528],"type":"Point"}
}