{
  "type": "Feature",
  "properties": {
    "iso:country":"US",
    "sg:address":"3315 Centennial Rd",
    "sg:city":"Sylvania",
    "sg:classifiers":[
        {
            "category":"Wholesale",
            "subcategory":"Non-durable Goods",
            "type":"Manufacturing & Wholesale Goods"
        },
        {
            "category":"Manufacturing",
            "subcategory":"Printing",
            "type":"Manufacturing & Wholesale Goods"
        }
    ],
    "sg:phone":"+1 419 841 5395",
    "sg:postcode":"43560",
    "sg:province":"OH",
    "sg:tags":[
        "advertising",
        "merchandise",
        "promotional"
    ],
    "sg:website":"www.ad-sensations.com",
    "wof:name":"Ad-Sensations Inc",
    "wof:placetype":"venue"
},
  "geometry": {"coordinates":[-83.742239,41.677412],"type":"Point"}
}