{
  "type": "Feature",
  "properties": {
    "iso:country":"US",
    "sg:address":"1225 W Hunter St",
    "sg:city":"Logan",
    "sg:classifiers":[
        {
            "category":"Government",
            "subcategory":"Office",
            "type":"Public Place"
        }
    ],
    "sg:phone":"+1 740 385 5607",
    "sg:postcode":"43138",
    "sg:province":"OH",
    "sg:tags":[
        "state",
        "resource"
    ],
    "sg:website":"www.ohiobwc.com",
    "wof:name":"Workman's Compensation Bureau",
    "wof:placetype":"venue"
},
  "geometry": {"coordinates":[-82.426245,39.543135],"type":"Point"}
}