{
  "type": "Feature",
  "properties": {
    "addr:full": "111 S Broad St Canfield OH 44406",
    "addr:housenumber": "111",
    "addr:postcode": "44406",
    "addr:street": "S Broad St",
    "iso:country": "US",
    "sg:address": "111 S Broad St",
    "sg:city": "Canfield",
    "sg:classifiers": [
      {
        "category": "Personal",
        "subcategory": "Barber",
        "type": "Services"
      }
    ],
    "sg:phone": "+1 330 533 3672",
    "sg:postcode": "44406",
    "sg:province": "OH",
    "wof:name": "Broad St Barber Shop",
    "wof:placetype": "venue"
  },
  "geometry": {"coordinates":[-80.760295,41.023219],"type":"Point"}
}
