{
  "type": "Feature",
  "properties": {
    "addr:full": "5749 Bastille Pl Columbus OH 43213",
    "addr:housenumber": "5749",
    "addr:postcode": "43213",
    "addr:street": "Bastille Pl",
    "iso:country": "US",
    "sg:address": "5749 Bastille Pl",
    "sg:city": "Columbus",
    "sg:classifiers": [
      {
        "category": "Real Estate",
        "subcategory": "Real Estate Operator",
        "type": "Services"
      }
    ],
    "sg:phone": "+1 614 863 4095",
    "sg:postcode": "43213",
    "sg:province": "OH",
    "sg:tags": [
      "building",
      "nonresidential"
    ],
    "wof:name": "Recchie Joseph J \u0026 Martha",
    "wof:placetype": "venue"
  },
  "geometry": {"coordinates":[-82.850217,39.973675],"type":"Point"}
}
