{
  "type": "Feature",
  "properties": {
    "addr:full": "4105 E 71st St Cleveland OH 44105",
    "addr:housenumber": "4105",
    "addr:postcode": "44105",
    "addr:street": "E 71St St",
    "iso:country": "US",
    "sg:address": "4105 E 71st St",
    "sg:city": "Cleveland",
    "sg:classifiers": [
      {
        "category": "Retail",
        "subcategory": "Funeral Services",
        "type": "Services"
      }
    ],
    "sg:phone": "+1 216 341 1772",
    "sg:postcode": "44105",
    "sg:province": "OH",
    "sg:tags": [
      "director"
    ],
    "wof:name": "Domagalski Komorowski Funeral",
    "wof:placetype": "venue"
  },
  "geometry": {"coordinates":[-81.638796,41.446453],"type":"Point"}
}
