{
  "type": "Feature",
  "properties": {
    "addr:full":"307 W Benson Ave Cincinnati OH 45215",
    "addr:housenumber":"307",
    "addr:postcode":"45215",
    "addr:street":"W Benson Ave",
    "iso:country":"US",
    "sg:address":"307 W Benson Ave",
    "sg:city":"Cincinnati",
    "sg:classifiers":[
        {
            "category":"Professional",
            "type":"Services"
        }
    ],
    "sg:phone":"+1 513 821 2929",
    "sg:postcode":"45215",
    "sg:province":"OH",
    "sg:tags":[
        "establishment"
    ],
    "wof:name":"Private Collection-Gutierrez",
    "wof:placetype":"venue"
},
  "geometry": {"coordinates":[-84.446091,39.223684],"type":"Point"}
}