{
  "type": "Feature",
  "properties": {
    "iso:country":"US",
    "sg:address":"6485 Pearl Rd",
    "sg:city":"Cleveland",
    "sg:classifiers":[
        {
            "category":"Retail",
            "subcategory":"Repair Shop",
            "type":"Services"
        }
    ],
    "sg:phone":"+1 440 842 9100",
    "sg:postcode":"44130",
    "sg:province":"OH",
    "sg:tags":[
        "hardware"
    ],
    "wof:name":"Black & Decker (US) Inc",
    "wof:placetype":"venue"
},
  "geometry": {"coordinates":[-81.771495,41.384929],"type":"Point"}
}