{
  "type": "Feature",
  "properties": {
    "addr:full": "17480 Chamberlain Rd Grafton OH 44044",
    "addr:housenumber": "17480",
    "addr:postcode": "44044",
    "addr:street": "Chamberlain Rd",
    "iso:country": "US",
    "sg:address": "17480 Chamberlain Rd",
    "sg:city": "Grafton",
    "sg:classifiers": [
      {
        "category": "Manufacturing",
        "subcategory": "Tools \u0026 Machinery",
        "type": "Manufacturing \u0026 Wholesale Goods"
      }
    ],
    "sg:phone": "+1 440 926 2400",
    "sg:postcode": "44044",
    "sg:province": "OH",
    "sg:tags": [
      "machine",
      "shop"
    ],
    "wof:name": "Term Machine \u0026 Fabricating",
    "wof:placetype": "venue"
  },
  "geometry": {"coordinates":[-82.062365,41.232571],"type":"Point"}
}
