{
  "type": "Feature",
  "properties": {
    "addr:full":"1210 Bay Ln Dayton OH 45430",
    "addr:housenumber":"1210",
    "addr:postcode":"45430",
    "addr:street":"Bay Ln",
    "iso:country":"US",
    "sg:address":"1210 Bay Ln",
    "sg:city":"Dayton",
    "sg:classifiers":[
        {
            "category":"Building & Trades",
            "subcategory":"Construction",
            "type":"Services"
        }
    ],
    "sg:phone":"+1 937 426 5316",
    "sg:postcode":"45430",
    "sg:province":"OH",
    "sg:tags":[
        "contractor"
    ],
    "wof:name":"Mike Nye",
    "wof:placetype":"venue"
},
  "geometry": {"coordinates":[-84.09565600000001,39.725344],"type":"Point"}
}