{
  "type": "Feature",
  "properties": {
    "addr:full":"528 Wickham Way Columbus OH 43230",
    "addr:housenumber":"528",
    "addr:postcode":"43230",
    "addr:street":"Wickham Way",
    "iso:country":"US",
    "sg:address":"528 Wickham Way",
    "sg:city":"Columbus",
    "sg:classifiers":[
        {
            "category":"Restaurant",
            "type":"Food & Drink"
        }
    ],
    "sg:phone":"+1 614 475 5988",
    "sg:postcode":"43230",
    "sg:province":"OH",
    "sg:tags":[
        "eating"
    ],
    "wof:name":"Legend Diner",
    "wof:placetype":"venue"
},
  "geometry": {"coordinates":[-82.862763,40.02793],"type":"Point"}
}