{
  "type": "Feature",
  "properties": {
    "iso:country":"US",
    "sg:address":"8135 Beechmont Ave",
    "sg:city":"Cincinnati",
    "sg:classifiers":[
        {
            "category":"Health Services",
            "subcategory":"Nursing And Care Facility",
            "type":"Services"
        }
    ],
    "sg:phone":"+1 513 474 5513",
    "sg:postcode":"45255",
    "sg:province":"OH",
    "sg:tags":[
        "skilled"
    ],
    "wof:name":"Vista Care",
    "wof:placetype":"venue"
},
  "geometry": {"coordinates":[-84.327403,39.072738],"type":"Point"}
}