{
  "type": "Feature",
  "properties": {
    "addr:full": "4420 Sherwin Rd Willoughby OH 44094",
    "addr:housenumber": "4420",
    "addr:postcode": "44094",
    "addr:street": "Sherwin Rd",
    "iso:country": "US",
    "sg:address": "4420 Sherwin Rd",
    "sg:city": "Willoughby",
    "sg:classifiers": [
      {
        "category": "Banks \u0026 Credit Unions",
        "subcategory": "Bank",
        "type": "Services"
      }
    ],
    "sg:phone": "+1 440 269 5900",
    "sg:postcode": "44094",
    "sg:province": "OH",
    "sg:tags": [
      "equipment",
      "financing",
      "leasing",
      "vehicle"
    ],
    "wof:name": "Mercedes-Benz Credit Corp",
    "wof:placetype": "venue"
  },
  "geometry": {"coordinates":[-81.384097,41.62989],"type":"Point"}
}
