{
  "type": "Feature",
  "properties": {
    "addr:full": "2220 Superior Via Cleveland OH 44113",
    "addr:housenumber": "2220",
    "addr:postcode": "44113",
    "addr:street": "Superior Via Cleveland",
    "iso:country": "US",
    "sg:address": "2220 Superior Via",
    "sg:city": "Cleveland",
    "sg:classifiers": [
      {
        "category": "Professional",
        "subcategory": "Employment Agencies",
        "type": "Services"
      }
    ],
    "sg:phone": "+1 216 579 1920",
    "sg:postcode": "44113",
    "sg:province": "OH",
    "sg:tags": [
      "modeling"
    ],
    "wof:name": "1920 Model \u0026 Talent Svc",
    "wof:placetype": "venue"
  },
  "geometry": {"coordinates":[-81.706085,41.493029],"type":"Point"}
}
