{
  "type": "Feature",
  "properties": {
    "iso:country":"US",
    "sg:address":"4451 Broadview Rd",
    "sg:city":"Cleveland",
    "sg:classifiers":[
        {
            "category":"Personal",
            "subcategory":"Beauty Salon",
            "type":"Services"
        }
    ],
    "sg:phone":"+1 216 741 1155",
    "sg:postcode":"44109",
    "sg:province":"OH",
    "wof:name":"Shear Combinations Hair Design",
    "wof:placetype":"venue"
},
  "geometry": {"coordinates":[-81.697046,41.434199],"type":"Point"}
}