{
  "type": "Feature",
  "properties": {
    "iso:country":"US",
    "sg:address":"6499 E Broad St",
    "sg:city":"Columbus",
    "sg:classifiers":[
        {
            "category":"Health Services",
            "subcategory":"Doctor",
            "type":"Services"
        }
    ],
    "sg:phone":"+1 614 868 9804",
    "sg:postcode":"43213",
    "sg:province":"OH",
    "sg:tags":[
        "dentist"
    ],
    "wof:name":"David Silverglade DDS Inc",
    "wof:placetype":"venue"
},
  "geometry": {"coordinates":[-82.830674,39.980755],"type":"Point"}
}