{
  "type": "Feature",
  "properties": {
    "addr:full":"334 Wells Jones Rd Waverly OH 45690",
    "addr:housenumber":"334",
    "addr:postcode":"45690",
    "addr:street":"Wells Jones Rd",
    "iso:country":"US",
    "sg:address":"334 Wells Jones Rd",
    "sg:city":"Waverly",
    "sg:classifiers":[
        {
            "category":"Professional",
            "type":"Services"
        }
    ],
    "sg:phone":"+1 740 947 5509",
    "sg:postcode":"45690",
    "sg:province":"OH",
    "sg:tags":[
        "establishment"
    ],
    "wof:name":"Botkin R Cottage",
    "wof:placetype":"venue"
},
  "geometry": {"coordinates":[-83.027272,39.104682],"type":"Point"}
}