{
  "type": "Feature",
  "properties": {
    "addr:full": "48040 Adams Rd Racine OH 45771",
    "addr:housenumber": "48040",
    "addr:postcode": "45771",
    "addr:street": "Adams Rd",
    "iso:country": "US",
    "sg:address": "48040 Adams Rd",
    "sg:city": "Racine",
    "sg:classifiers": [
      {
        "category": "Farming",
        "subcategory": "Farm",
        "type": "Manufacturing \u0026 Wholesale Goods"
      }
    ],
    "sg:phone": "+1 740 247 2113",
    "sg:postcode": "45771",
    "sg:province": "OH",
    "sg:tags": [
      "produce"
    ],
    "wof:name": "OBrien James Farms",
    "wof:placetype": "venue"
  },
  "geometry": {"coordinates":[-81.906755,38.907542],"type":"Point"}
}
