{
  "type": "Feature",
  "properties": {
    "addr:full": "2089 Columbia Rd Valley City OH 44280",
    "addr:housenumber": "2089",
    "addr:postcode": "44280",
    "addr:street": "Columbia Rd",
    "iso:country": "US",
    "sg:address": "2089 Columbia Rd",
    "sg:city": "Valley City",
    "sg:classifiers": [
      {
        "category": "Retail",
        "subcategory": "Funeral Services",
        "type": "Services"
      }
    ],
    "sg:phone": "+1 330 483 3300",
    "sg:postcode": "44280",
    "sg:province": "OH",
    "sg:tags": [
      "director"
    ],
    "wof:name": "Bauer Funeral Home",
    "wof:placetype": "venue"
  },
  "geometry": {"coordinates":[-81.922191,41.222504],"type":"Point"}
}
