{
  "type": "Feature",
  "properties": {
    "addr:full": "3105 OH-103 E Willard OH 44890",
    "addr:housenumber": "3105",
    "addr:postcode": "44890",
    "addr:street": "Oh-103 E",
    "iso:country": "US",
    "sg:address": "3105 OH-103 E",
    "sg:city": "Willard",
    "sg:classifiers": [
      {
        "category": "Restaurant",
        "type": "Food \u0026 Drink"
      }
    ],
    "sg:menulink": "http://www.allmenus.com/oh/new-haven/193765-noble-romans/menu/",
    "sg:phone": "+1 419 933 7221",
    "sg:postcode": "44890",
    "sg:province": "OH",
    "sg:tags": [
      "wrap",
      "italian",
      "american",
      "sandwich",
      "pizza"
    ],
    "wof:name": "Noble Roman's",
    "wof:placetype": "venue"
  },
  "geometry": {"coordinates":[-82.685761,41.052661],"type":"Point"}
}
