{
  "type": "Feature",
  "properties": {
    "addr:full": "5826 Lee Rd S Cleveland OH 44137",
    "addr:housenumber": "5826",
    "addr:postcode": "44137",
    "addr:street": "Lee Rd S",
    "iso:country": "US",
    "sg:address": "5826 Lee Rd S",
    "sg:city": "Cleveland",
    "sg:classifiers": [
      {
        "category": "Personal",
        "subcategory": "Barber",
        "type": "Services"
      }
    ],
    "sg:phone": "+1 216 662 2268",
    "sg:postcode": "44137",
    "sg:province": "OH",
    "wof:name": "Loren's Barber Shop",
    "wof:placetype": "venue"
  },
  "geometry": {"coordinates":[-81.565739,41.400222],"type":"Point"}
}
