{
  "type": "Feature",
  "properties": {
    "addr:full":"38348 Airport Pkwy Willoughby OH 44094",
    "addr:housenumber":"38348",
    "addr:postcode":"44094",
    "addr:street":"Airport Pkwy",
    "iso:country":"US",
    "sg:address":"38348 Airport Pkwy",
    "sg:city":"Willoughby",
    "sg:classifiers":[
        {
            "category":"Manufacturing",
            "subcategory":"Building Materials",
            "type":"Manufacturing & Wholesale Goods"
        },
        {
            "category":"Building & Trades",
            "subcategory":"Construction",
            "type":"Services"
        }
    ],
    "sg:phone":"+1 440 951 3876",
    "sg:postcode":"44094",
    "sg:province":"OH",
    "sg:tags":[
        "mfg",
        "laminated",
        "cabinet",
        "wood",
        "maker",
        "kitchen"
    ],
    "wof:name":"Euromark Cabinets",
    "wof:placetype":"venue"
},
  "geometry": {"coordinates":[-81.401617,41.675441],"type":"Point"}
}