{
  "type": "Feature",
  "properties": {
    "iso:country":"US",
    "sg:address":"695 Lafayette Rd",
    "sg:city":"Medina",
    "sg:classifiers":[
        {
            "category":"Retail",
            "subcategory":"Laundry & Dry Cleaning",
            "type":"Services"
        }
    ],
    "sg:phone":"+1 330 725 4440",
    "sg:postcode":"44256",
    "sg:province":"OH",
    "sg:tags":[
        "cleaners"
    ],
    "wof:name":"Tecco's Dry Cleaners",
    "wof:placetype":"venue"
},
  "geometry": {"coordinates":[-81.878517,41.129407],"type":"Point"}
}