{
  "type": "Feature",
  "properties": {
    "addr:full": "134 N Main St Hudson OH 44236",
    "addr:housenumber": "134",
    "addr:postcode": "44236",
    "addr:street": "N Main St",
    "iso:country": "US",
    "sg:address": "134 N Main St",
    "sg:city": "Hudson",
    "sg:classifiers": [
      {
        "category": "Shopping",
        "subcategory": "Clothing, Apparel, \u0026 Fashions",
        "type": "Retail Goods"
      }
    ],
    "sg:phone": "+1 330 650 4032",
    "sg:postcode": "44236",
    "sg:province": "OH",
    "sg:tags": [
      "family",
      "furnishing",
      "store"
    ],
    "wof:name": "Country Blues Inc",
    "wof:placetype": "venue"
  },
  "geometry": {"coordinates":[-81.44051,41.241322],"type":"Point"}
}
