{
  "type": "Feature",
  "properties": {
    "iso:country":"US",
    "sg:address":"5647 Old Blue Rock Rd",
    "sg:city":"Cincinnati",
    "sg:classifiers":[
        {
            "category":"Insurance",
            "subcategory":"Insurance Agent",
            "type":"Services"
        }
    ],
    "sg:phone":"+1 513 741 0462",
    "sg:postcode":"45247",
    "sg:province":"OH",
    "wof:name":"Ronda Mettey Insurance Agency",
    "wof:placetype":"venue"
},
  "geometry": {"coordinates":[-84.623745,39.229849],"type":"Point"}
}