{
  "type": "Feature",
  "properties": {
    "addr:full": "5647 Old Blue Rock Rd Cincinnati OH 45247",
    "addr:housenumber": "5647",
    "addr:postcode": "45247",
    "addr:street": "Old Blue Rock Rd",
    "iso:country": "US",
    "sg:address": "5647 Old Blue Rock Rd",
    "sg:city": "Cincinnati",
    "sg:classifiers": [
      {
        "category": "Insurance",
        "subcategory": "Insurance Agent",
        "type": "Services"
      }
    ],
    "sg:phone": "+1 513 741 0462",
    "sg:postcode": "45247",
    "sg:province": "OH",
    "wof:name": "Ronda Mettey Insurance Agency",
    "wof:placetype": "venue"
  },
  "geometry": {"coordinates":[-84.623745,39.229849],"type":"Point"}
}
