{
  "type": "Feature",
  "properties": {
    "iso:country":"US",
    "sg:address":"471 Morrison Rd",
    "sg:city":"Gahanna",
    "sg:classifiers":[
        {
            "category":"Retail",
            "subcategory":"Laundry & Dry Cleaning",
            "type":"Services"
        }
    ],
    "sg:phone":"+1 614 478 7440",
    "sg:postcode":"43230",
    "sg:province":"OH",
    "sg:tags":[
        "cleaners"
    ],
    "wof:name":"Hanna's Drycleaner",
    "wof:placetype":"venue"
},
  "geometry": {"coordinates":[-82.865054,40.008886],"type":"Point"}
}