{
  "type": "Feature",
  "properties": {
    "addr:full":"23875 Commerce Park Cleveland OH 44122",
    "addr:housenumber":"23875",
    "addr:postcode":"44122",
    "addr:street":"Commerce Park",
    "iso:country":"US",
    "sg:address":"23875 Commerce Park",
    "sg:city":"Cleveland",
    "sg:classifiers":[
        {
            "category":"Health Services",
            "subcategory":"Health Practitioner",
            "type":"Services"
        }
    ],
    "sg:phone":"+1 216 292 7370",
    "sg:postcode":"44122",
    "sg:province":"OH",
    "sg:tags":[
        "pathologist",
        "speech"
    ],
    "wof:name":"Western Reserve Speech",
    "wof:placetype":"venue"
},
  "geometry": {"coordinates":[-81.51405200000001,41.461085],"type":"Point"}
}