{
  "type": "Feature",
  "properties": {
    "iso:country":"US",
    "sg:address":"5664 E Harbor Rd",
    "sg:city":"Lakeside Marblehead",
    "sg:classifiers":[
        {
            "category":"Home & Garden",
            "subcategory":"Mobile Homes",
            "type":"Retail Goods"
        }
    ],
    "sg:phone":"+1 419 734 7234",
    "sg:postcode":"43440",
    "sg:province":"OH",
    "wof:name":"M H C Corporation",
    "wof:placetype":"venue"
},
  "geometry": {"coordinates":[-82.825204,41.531301],"type":"Point"}
}