{
  "type": "Feature",
  "properties": {
    "addr:full": "8510 Industry Park Dr Piqua OH 45356",
    "addr:housenumber": "8510",
    "addr:postcode": "45356",
    "addr:street": "Industry Park Dr",
    "iso:country": "US",
    "sg:address": "8510 Industry Park Dr",
    "sg:city": "Piqua",
    "sg:classifiers": [
      {
        "category": "Home \u0026 Garden",
        "subcategory": "Building Materials",
        "type": "Retail Goods"
      }
    ],
    "sg:phone": "+1 937 773 9840",
    "sg:postcode": "45356",
    "sg:province": "OH",
    "sg:tags": [
      "roofing"
    ],
    "sg:website": "www.classicroof.com",
    "wof:name": "Classic Products Inc",
    "wof:placetype": "venue"
  },
  "geometry": {"coordinates":[-84.232249,40.159977],"type":"Point"}
}
