{
  "type": "Feature",
  "properties": {
    "addr:full": "2740 Wagar Rd Cleveland OH 44116",
    "addr:postcode": "2740;44116",
    "addr:street": "Wagar Rd",
    "iso:country": "US",
    "sg:address": "2740 Wagar Rd",
    "sg:city": "Cleveland",
    "sg:classifiers": [
      {
        "category": "Retail",
        "subcategory": "Repair Shop",
        "type": "Services"
      }
    ],
    "sg:phone": "+1 440 333 2686",
    "sg:postcode": "44116",
    "sg:province": "OH",
    "sg:tags": [
      "equipment",
      "telephone",
      "system"
    ],
    "wof:name": "Professional Phone Consultant",
    "wof:placetype": "venue"
  },
  "geometry": {"coordinates":[-81.852701,41.465841],"type":"Point"}
}
