{
  "type": "Feature",
  "properties": {
    "addr:full": "3390 W 67th St Cleveland OH 44102",
    "addr:housenumber": "3390",
    "addr:postcode": "44102",
    "addr:street": "W 67Th St",
    "iso:country": "US",
    "sg:address": "3390 W 67th St",
    "sg:city": "Cleveland",
    "sg:classifiers": [
      {
        "category": "Restaurant",
        "type": "Food \u0026 Drink"
      }
    ],
    "sg:phone": "+1 216 631 7273",
    "sg:postcode": "44102",
    "sg:province": "OH",
    "sg:tags": [
      "parlor",
      "ice",
      "cream"
    ],
    "wof:name": "Summertime Sweet Treats Inc",
    "wof:placetype": "venue"
  },
  "geometry": {"coordinates":[-81.733626,41.461445],"type":"Point"}
}
