{
  "type": "Feature",
  "properties": {
    "iso:country":"US",
    "sg:address":"3390 W 67th St",
    "sg:city":"Cleveland",
    "sg:classifiers":[
        {
            "category":"Restaurant",
            "type":"Food & Drink"
        }
    ],
    "sg:phone":"+1 216 631 7273",
    "sg:postcode":"44102",
    "sg:province":"OH",
    "sg:tags":[
        "parlor",
        "ice",
        "cream"
    ],
    "wof:name":"Summertime Sweet Treats Inc",
    "wof:placetype":"venue"
},
  "geometry": {"coordinates":[-81.733626,41.461445],"type":"Point"}
}