{
  "type": "Feature",
  "properties": {
    "iso:country":"US",
    "sg:address":"203 Hedrick Rd",
    "sg:city":"Peebles",
    "sg:classifiers":[
        {
            "category":"Real Estate",
            "subcategory":"Real Estate Agent",
            "type":"Services"
        }
    ],
    "sg:phone":"+1 937 587 3489",
    "sg:postcode":"45660",
    "sg:province":"OH",
    "sg:tags":[
        "appraiser"
    ],
    "wof:name":"Hedrick Appraisal Svc",
    "wof:placetype":"venue"
},
  "geometry": {"coordinates":[-83.449845,39.011705],"type":"Point"}
}