{
  "type": "Feature",
  "properties": {
    "iso:country":"US",
    "sg:address":"760 Farmersville Germantn Pike",
    "sg:city":"Germantown",
    "sg:classifiers":[
        {
            "category":"Organizations",
            "subcategory":"Religious Organization",
            "type":"Services"
        }
    ],
    "sg:phone":"+1 937 855 6907",
    "sg:postcode":"45327",
    "sg:province":"OH",
    "sg:tags":[
        "church"
    ],
    "wof:name":"First Church Of God",
    "wof:placetype":"venue"
},
  "geometry": {"coordinates":[-84.382541,39.637813],"type":"Point"}
}