{
  "type": "Feature",
  "properties": {
    "addr:full": "2225 Settlers Trl Vandalia OH 45377",
    "addr:housenumber": "2225",
    "addr:postcode": "45377",
    "addr:street": "Settlers Trl",
    "iso:country": "US",
    "sg:address": "2225 Settlers Trl",
    "sg:city": "Vandalia",
    "sg:classifiers": [
      {
        "category": "Building \u0026 Trades",
        "subcategory": "Construction",
        "type": "Services"
      }
    ],
    "sg:phone": "+1 937 898 9004",
    "sg:postcode": "45377",
    "sg:province": "OH",
    "sg:tags": [
      "house"
    ],
    "wof:name": "Xpert LLC",
    "wof:placetype": "venue"
  },
  "geometry": {"coordinates":[-84.168175,39.893131],"type":"Point"}
}
