{
  "type": "Feature",
  "properties": {
    "iso:country":"US",
    "sg:address":"565 N Broad St",
    "sg:city":"Canfield",
    "sg:classifiers":[
        {
            "category":"Professional",
            "subcategory":"Accounting & Tax Preparation",
            "type":"Services"
        }
    ],
    "sg:phone":"+1 330 758 0854",
    "sg:postcode":"44406",
    "sg:province":"OH",
    "sg:tags":[
        "accountant"
    ],
    "sg:website":"www.bobcpas.com",
    "wof:name":"Burns O Hare & Bella Inc",
    "wof:placetype":"venue"
},
  "geometry": {"coordinates":[-80.760571,41.041153],"type":"Point"}
}