{
  "type": "Feature",
  "properties": {
    "iso:country":"US",
    "sg:address":"3401 Enterprise Pkwy",
    "sg:city":"Cleveland",
    "sg:classifiers":[
        {
            "category":"Shopping",
            "subcategory":"Computers & Home Electronics",
            "type":"Retail Goods"
        }
    ],
    "sg:phone":"+1 216 766 5774",
    "sg:postcode":"44122",
    "sg:province":"OH",
    "sg:tags":[
        "software"
    ],
    "wof:name":"Futurion",
    "wof:placetype":"venue"
},
  "geometry": {"coordinates":[-81.494602,41.466431],"type":"Point"}
}