{
  "type": "Feature",
  "properties": {
    "iso:country":"US",
    "sg:address":"36 W Broad St",
    "sg:city":"Newton Falls",
    "sg:classifiers":[
        {
            "category":"Insurance",
            "subcategory":"Insurance Agent",
            "type":"Services"
        }
    ],
    "sg:phone":"+1 330 872 1023",
    "sg:postcode":"44444",
    "sg:province":"OH",
    "wof:name":"John R Davis Insurance",
    "wof:placetype":"venue"
},
  "geometry": {"coordinates":[-80.976574,41.187916],"type":"Point"}
}