{
  "type": "Feature",
  "properties": {
    "addr:full":"630 Mc Adams Dr New Carlisle OH 45344",
    "addr:housenumber":"630",
    "addr:postcode":"45344",
    "addr:street":"Mc Adams Dr",
    "iso:country":"US",
    "sg:address":"630 Mc Adams Dr",
    "sg:city":"New Carlisle",
    "sg:classifiers":[
        {
            "category":"Bars & Pubs",
            "type":"Food & Drink"
        }
    ],
    "sg:phone":"+1 937 884 8449",
    "sg:postcode":"45344",
    "sg:province":"OH",
    "sg:tags":[
        "drinking"
    ],
    "wof:name":"Chasers",
    "wof:placetype":"venue"
},
  "geometry": {"coordinates":[-84.04711399999999,39.889334],"type":"Point"}
}