{
  "type": "Feature",
  "properties": {
    "addr:full": "250 Marion Rd Cincinnati OH 45215",
    "addr:housenumber": "250",
    "addr:postcode": "45215",
    "addr:street": "Marion Rd",
    "iso:country": "US",
    "sg:address": "250 Marion Rd",
    "sg:city": "Cincinnati",
    "sg:classifiers": [
      {
        "category": "Wholesale",
        "subcategory": "Construction Materials",
        "type": "Manufacturing \u0026 Wholesale Goods"
      },
      {
        "category": "Home \u0026 Garden",
        "subcategory": "Building Materials",
        "type": "Retail Goods"
      }
    ],
    "sg:phone": "+1 513 771 9121",
    "sg:postcode": "45215",
    "sg:province": "OH",
    "sg:website": "www.bushelman.com",
    "wof:name": "Bushelman Supply Co Inc",
    "wof:placetype": "venue"
  },
  "geometry": {"coordinates":[-84.467337,39.251885],"type":"Point"}
}
