{
  "type": "Feature",
  "properties": {
    "iso:country":"US",
    "sg:address":"2362 Hamilton Cleves Rd",
    "sg:city":"Hamilton",
    "sg:classifiers":[
        {
            "category":"Sports & Exercise",
            "subcategory":"Race Track",
            "type":"Entertainment"
        }
    ],
    "sg:phone":"+1 513 863 0562",
    "sg:postcode":"45013",
    "sg:province":"OH",
    "sg:website":"http://www.tristatedragway.com",
    "wof:name":"Tri-State Dragway",
    "wof:placetype":"venue"
},
  "geometry": {"coordinates":[-84.594005,39.354837],"type":"Point"}
}