{
  "type": "Feature",
  "properties": {
    "iso:country":"US",
    "sg:address":"5741 Greendale Dr",
    "sg:city":"Galloway",
    "sg:classifiers":[
        {
            "category":"Shopping",
            "subcategory":"Computers & Home Electronics",
            "type":"Retail Goods"
        }
    ],
    "sg:phone":"+1 614 878 6666",
    "sg:postcode":"43119",
    "sg:province":"OH",
    "wof:name":"Ron Fowler Computers",
    "wof:placetype":"venue"
},
  "geometry": {"coordinates":[-83.151826,39.943464],"type":"Point"}
}