{
  "type": "Feature",
  "properties": {
    "addr:full": "9556 Beerbower Rd Edgerton OH 43517",
    "addr:housenumber": "9556",
    "addr:postcode": "43517",
    "addr:street": "Beerbower Rd",
    "iso:country": "US",
    "sg:address": "9556 Beerbower Rd",
    "sg:city": "Edgerton",
    "sg:classifiers": [
      {
        "category": "Farming",
        "subcategory": "Farm \u0026 Veterinary Services",
        "type": "Manufacturing \u0026 Wholesale Goods"
      }
    ],
    "sg:phone": "+1 419 658 2487",
    "sg:postcode": "43517",
    "sg:province": "OH",
    "sg:tags": [
      "management"
    ],
    "wof:name": "Mildred Ann Chatterton",
    "wof:placetype": "venue"
  },
  "geometry": {"coordinates":[-84.635507,41.397833],"type":"Point"}
}
