{
  "type": "Feature",
  "properties": {
    "iso:country":"US",
    "sg:address":"15285 S State Ave",
    "sg:city":"Middlefield",
    "sg:classifiers":[
        {
            "category":"Shopping",
            "type":"Retail Goods"
        }
    ],
    "sg:phone":"+1 440 632 9695",
    "sg:postcode":"44062",
    "sg:province":"OH",
    "sg:tags":[
        "product",
        "wood"
    ],
    "wof:name":"Woodcraft Industries",
    "wof:placetype":"venue"
},
  "geometry": {"coordinates":[-81.073115,41.452469],"type":"Point"}
}