{
  "type": "Feature",
  "properties": {
    "addr:full":"11449 Valley View Rd Northfield OH 44067",
    "addr:housenumber":"11449",
    "addr:postcode":"44067",
    "addr:street":"Valley View Rd",
    "iso:country":"US",
    "sg:address":"11449 Valley View Rd",
    "sg:city":"Northfield",
    "sg:classifiers":[
        {
            "category":"Professional",
            "type":"Services"
        }
    ],
    "sg:phone":"+1 330 467 6874",
    "sg:postcode":"44067",
    "sg:province":"OH",
    "wof:name":"Bet Trk Inc",
    "wof:placetype":"venue"
},
  "geometry": {"coordinates":[-81.56003699999999,41.334927],"type":"Point"}
}