{
  "type": "Feature",
  "properties": {
    "addr:full":"135 N High St Hillsboro OH 45133",
    "addr:housenumber":"135",
    "addr:postcode":"45133",
    "addr:street":"N High St",
    "iso:country":"US",
    "sg:address":"135 N High St",
    "sg:city":"Hillsboro",
    "sg:classifiers":[
        {
            "category":"Professional",
            "subcategory":"Management & Consulting",
            "type":"Services"
        }
    ],
    "sg:phone":"+1 937 393 0339",
    "sg:postcode":"45133",
    "sg:province":"OH",
    "sg:tags":[
        "development",
        "economic",
        "agency"
    ],
    "wof:name":"Southern Ohio Economic Dev",
    "wof:placetype":"venue"
},
  "geometry": {"coordinates":[-83.61133599999999,39.203313],"type":"Point"}
}