{
  "type": "Feature",
  "properties": {
    "iso:country":"US",
    "sg:address":"4966 Norquest Blvd",
    "sg:city":"Youngstown",
    "sg:classifiers":[
        {
            "category":"Manufacturing",
            "subcategory":"Buildings",
            "type":"Manufacturing & Wholesale Goods"
        },
        {
            "category":"Home & Garden",
            "subcategory":"Building Materials",
            "type":"Retail Goods"
        },
        {
            "category":"Building & Trades",
            "subcategory":"Construction",
            "type":"Services"
        }
    ],
    "sg:phone":"+1 330 207 1741",
    "sg:postcode":"44515",
    "sg:province":"OH",
    "sg:tags":[
        "heating",
        "bathroom",
        "industrial",
        "specialty",
        "deck",
        "altering",
        "builder",
        "system",
        "kitchen",
        "contractor",
        "drywall",
        "planning",
        "contractors-commercial",
        "improvement",
        "remodeling",
        "air conditioning"
    ],
    "wof:name":"Trinity Home Improvement & Construction",
    "wof:placetype":"venue"
},
  "geometry": {"coordinates":[-80.749138,41.105798],"type":"Point"}
}