{
  "type": "Feature",
  "properties": {
    "addr:full": "5750 Branding Iron Ct Galloway OH 43119",
    "addr:housenumber": "5750",
    "addr:postcode": "43119",
    "addr:street": "Branding Iron Ct",
    "iso:country": "US",
    "sg:address": "5750 Branding Iron Ct",
    "sg:city": "Galloway",
    "sg:classifiers": [
      {
        "category": "Building \u0026 Trades",
        "subcategory": "Construction",
        "type": "Services"
      }
    ],
    "sg:phone": "+1 614 878 3431",
    "sg:postcode": "43119",
    "sg:province": "OH",
    "sg:tags": [
      "house"
    ],
    "wof:name": "John Burns Construction",
    "wof:placetype": "venue"
  },
  "geometry": {"coordinates":[-83.149689,39.942017],"type":"Point"}
}
