{
  "type": "Feature",
  "properties": {
    "addr:full": "1105 Ludlow St Hamilton OH 45011",
    "addr:housenumber": "1105",
    "addr:postcode": "45011",
    "addr:street": "Ludlow St",
    "iso:country": "US",
    "sg:address": "1105 Ludlow St",
    "sg:city": "Hamilton",
    "sg:classifiers": [
      {
        "category": "Building \u0026 Trades",
        "subcategory": "Plumbing",
        "type": "Services"
      }
    ],
    "sg:phone": "+1 513 863 6790",
    "sg:postcode": "45011",
    "sg:province": "OH",
    "sg:tags": [
      "plumbing",
      "contractor"
    ],
    "wof:name": "Carter Feltner Plumbing Co",
    "wof:placetype": "venue"
  },
  "geometry": {"coordinates":[-84.550827,39.393687],"type":"Point"}
}
