{
  "type": "Feature",
  "properties": {
    "addr:full": "437 Huber Village Blvd Westerville OH 43081",
    "addr:housenumber": "437",
    "addr:postcode": "43081",
    "addr:street": "Huber Village Blvd",
    "iso:country": "US",
    "sg:address": "437 Huber Village Blvd",
    "sg:city": "Westerville",
    "sg:classifiers": [
      {
        "category": "Building \u0026 Trades",
        "subcategory": "Electrical",
        "type": "Services"
      }
    ],
    "sg:phone": "+1 614 891 3996",
    "sg:postcode": "43081",
    "sg:province": "OH",
    "sg:tags": [
      "electrical",
      "electric",
      "contractor"
    ],
    "wof:name": "Competent Electrical Services",
    "wof:placetype": "venue"
  },
  "geometry": {"coordinates":[-82.907543,40.103071],"type":"Point"}
}
