{
  "type": "Feature",
  "properties": {
    "addr:full":"14519 Madison Ave Lakewood OH 44107",
    "addr:housenumber":"14519",
    "addr:postcode":"44107",
    "addr:street":"Madison Ave",
    "iso:country":"US",
    "sg:address":"14519 Madison Ave",
    "sg:city":"Lakewood",
    "sg:classifiers":[
        {
            "category":"Shopping",
            "subcategory":"Florist",
            "type":"Retail Goods"
        }
    ],
    "sg:phone":"+1 216 521 0170",
    "sg:postcode":"44107",
    "sg:province":"OH",
    "wof:name":"Ottage Flower",
    "wof:placetype":"venue"
},
  "geometry": {"coordinates":[-81.796644,41.47711],"type":"Point"}
}