{
  "type": "Feature",
  "properties": {
    "addr:full": "22706 State Rte 613 Oakwood OH 45873",
    "addr:housenumber": "22706",
    "addr:postcode": "45873",
    "addr:street": "State Rte 613",
    "iso:country": "US",
    "sg:address": "22706 State Rte 613",
    "sg:city": "Oakwood",
    "sg:classifiers": [
      {
        "category": "Building \u0026 Trades",
        "subcategory": "Construction",
        "type": "Services"
      }
    ],
    "sg:phone": "+1 419 594 3210",
    "sg:postcode": "45873",
    "sg:province": "OH",
    "sg:tags": [
      "control",
      "erosion"
    ],
    "wof:name": "Enviroscape ECM LTD",
    "wof:placetype": "venue"
  },
  "geometry": {"coordinates":[-84.387043,41.092291],"type":"Point"}
}
