{
  "type": "Feature",
  "properties": {
    "iso:country":"US",
    "sg:address":"11290 Wellington Dr",
    "sg:city":"Chardon",
    "sg:classifiers":[
        {
            "category":"Real Estate",
            "subcategory":"Surveying",
            "type":"Services"
        }
    ],
    "sg:phone":"+1 440 286 8417",
    "sg:postcode":"44024",
    "sg:province":"OH",
    "sg:tags":[
        "surveyor"
    ],
    "wof:name":"O'Hara Land Surveying",
    "wof:placetype":"venue"
},
  "geometry": {"coordinates":[-81.236437,41.606213],"type":"Point"}
}