{
  "type": "Feature",
  "properties": {
    "addr:full": "32640 State Rte 172 Hanoverton OH 44423",
    "addr:housenumber": "32640",
    "addr:postcode": "44423",
    "addr:street": "State Rte 172",
    "iso:country": "US",
    "sg:address": "32640 State Rte 172",
    "sg:city": "Hanoverton",
    "sg:classifiers": [
      {
        "category": "Personal",
        "subcategory": "Beauty Salon",
        "type": "Services"
      }
    ],
    "sg:phone": "+1 330 222 2105",
    "sg:postcode": "44423",
    "sg:province": "OH",
    "wof:name": "Happy Clipper II",
    "wof:placetype": "venue"
  },
  "geometry": {"coordinates":[-80.885024,40.79483],"type":"Point"}
}
