{
  "type": "Feature",
  "properties": {
    "iso:country":"US",
    "sg:address":"34800 Vine St",
    "sg:city":"Willowick",
    "sg:classifiers":[
        {
            "category":"Real Estate",
            "subcategory":"Real Estate Operator",
            "type":"Services"
        }
    ],
    "sg:phone":"+1 440 946 4644",
    "sg:postcode":"44095",
    "sg:province":"OH",
    "sg:tags":[
        "building",
        "apartment"
    ],
    "wof:name":"Manor Park Apartments",
    "wof:placetype":"venue"
},
  "geometry": {"coordinates":[-81.439571,41.642547],"type":"Point"}
}