{
  "type": "Feature",
  "properties": {
    "addr:full":"5030 High Saddle Ave NW Massillon OH 44646",
    "addr:housenumber":"5030",
    "addr:postcode":"44646",
    "addr:street":"High Saddle Ave Nw",
    "iso:country":"US",
    "sg:address":"5030 High Saddle Ave NW",
    "sg:city":"Massillon",
    "sg:classifiers":[
        {
            "category":"Professional",
            "type":"Services"
        }
    ],
    "sg:phone":"+1 330 832 3681",
    "sg:postcode":"44646",
    "sg:province":"OH",
    "sg:tags":[
        "establishment"
    ],
    "wof:name":"Amerada Hess Corp",
    "wof:placetype":"venue"
},
  "geometry": {"coordinates":[-81.506545,40.853553],"type":"Point"}
}