{
  "type": "Feature",
  "properties": {
    "addr:full":"7230 Cincinnati Brookville Rd Okeana IN 45053",
    "addr:housenumber":"7230",
    "addr:postcode":"45053",
    "addr:street":"Cincinnati Brookville Rd",
    "iso:country":"US",
    "sg:address":"7230 Cincinnati Brookville Rd",
    "sg:city":"Okeana",
    "sg:classifiers":[
        {
            "category":"Building & Trades",
            "subcategory":"Construction",
            "type":"Services"
        }
    ],
    "sg:phone":"+1 513 542 4745",
    "sg:postcode":"45053",
    "sg:province":"IN",
    "sg:tags":[
        "bricklaying",
        "contractor"
    ],
    "wof:name":"J Construction Co Inc",
    "wof:placetype":"venue"
},
  "geometry": {"coordinates":[-84.78845200000001,39.372131],"type":"Point"}
}