{
  "type": "Feature",
  "properties": {
    "addr:full":"5473 N Bend Rd Cincinnati OH 45247",
    "addr:housenumber":"5473",
    "addr:postcode":"45247",
    "addr:street":"N Bend Rd",
    "iso:country":"US",
    "sg:address":"5473 N Bend Rd",
    "sg:city":"Cincinnati",
    "sg:classifiers":[
        {
            "category":"Professional",
            "type":"Services"
        },
        {
            "category":"Personal",
            "type":"Services"
        },
        {
            "category":"Restaurant",
            "type":"Food & Drink"
        },
        {
            "category":"Fast Food",
            "type":"Food & Drink"
        }
    ],
    "sg:phone":"+1 513 389 7878",
    "sg:postcode":"45247",
    "sg:province":"OH",
    "sg:tags":[
        "delivery",
        "take",
        "pizza"
    ],
    "sg:website":"http://www.papajohns.com",
    "wof:name":"Papa John's Pizza",
    "wof:placetype":"venue"
},
  "geometry": {"coordinates":[-84.60013499999999,39.189748],"type":"Point"}
}