{
  "type": "Feature",
  "properties": {
    "addr:full":"4800 Crayton Ave Cleveland OH 44104",
    "addr:housenumber":"4800",
    "addr:postcode":"44104",
    "addr:street":"Crayton Ave",
    "iso:country":"US",
    "sg:address":"4800 Crayton Ave",
    "sg:city":"Cleveland",
    "sg:classifiers":[
        {
            "category":"Wholesale",
            "subcategory":"Fruits & Vegetables",
            "type":"Manufacturing & Wholesale Goods"
        }
    ],
    "sg:phone":"+1 216 431 2771",
    "sg:postcode":"44104",
    "sg:province":"OH",
    "sg:tags":[
        "produce"
    ],
    "wof:name":"Z & R Foods Inc",
    "wof:placetype":"venue"
},
  "geometry": {"coordinates":[-81.657625,41.483921],"type":"Point"}
}