{
  "type": "Feature",
  "properties": {
    "iso:country":"US",
    "sg:address":"681 N Main St",
    "sg:city":"Akron",
    "sg:classifiers":[
        {
            "category":"Organizations",
            "subcategory":"Non-profit Organization",
            "type":"Services"
        }
    ],
    "sg:phone":"+1 330 434 2181",
    "sg:postcode":"44310",
    "sg:province":"OH",
    "wof:name":"Akron Education Assn",
    "wof:placetype":"venue"
},
  "geometry": {"coordinates":[-81.510802,41.103048],"type":"Point"}
}