{
  "type": "Feature",
  "properties": {
    "addr:full": "2277 Parkville Ct Columbus OH 43229",
    "addr:housenumber": "2277",
    "addr:postcode": "43229",
    "addr:street": "Parkville Ct",
    "iso:country": "US",
    "sg:address": "2277 Parkville Ct",
    "sg:city": "Columbus",
    "sg:classifiers": [
      {
        "category": "Food \u0026 Beverages",
        "subcategory": "Bakery",
        "type": "Retail Goods"
      }
    ],
    "sg:phone": "+1 614 794 7297",
    "sg:postcode": "43229",
    "sg:province": "OH",
    "wof:name": "Duke \u0026 Shadows K 9 Bakery",
    "wof:placetype": "venue"
  },
  "geometry": {"coordinates":[-82.957151,40.084414],"type":"Point"}
}
