{
  "type": "Feature",
  "properties": {
    "iso:country":"US",
    "sg:address":"2277 Parkville Ct",
    "sg:city":"Columbus",
    "sg:classifiers":[
        {
            "category":"Food & Beverages",
            "subcategory":"Bakery",
            "type":"Retail Goods"
        }
    ],
    "sg:phone":"+1 614 794 7297",
    "sg:postcode":"43229",
    "sg:province":"OH",
    "wof:name":"Duke & Shadows K 9 Bakery",
    "wof:placetype":"venue"
},
  "geometry": {"coordinates":[-82.957151,40.084414],"type":"Point"}
}