{
  "type": "Feature",
  "properties": {
    "addr:full": "232 N Gamble St Shelby OH 44875",
    "addr:housenumber": "232",
    "addr:postcode": "44875",
    "addr:street": "N Gamble St",
    "iso:country": "US",
    "sg:address": "232 N Gamble St",
    "sg:city": "Shelby",
    "sg:classifiers": [
      {
        "category": "Organizations",
        "subcategory": "Professional Association",
        "type": "Services"
      }
    ],
    "sg:phone": "+1 419 347 9559",
    "sg:postcode": "44875",
    "sg:province": "OH",
    "wof:name": "Veterans Of Foreign Wars",
    "wof:placetype": "venue"
  },
  "geometry": {"coordinates":[-82.662515,40.890054],"type":"Point"}
}
