{
  "type": "Feature",
  "properties": {
    "addr:full":"116 W Franklin St Troy OH 45373",
    "addr:housenumber":"116",
    "addr:postcode":"45373",
    "addr:street":"W Franklin St",
    "iso:country":"US",
    "sg:address":"116 W Franklin St",
    "sg:city":"Troy",
    "sg:classifiers":[
        {
            "category":"Social Services",
            "type":"Services"
        }
    ],
    "sg:phone":"+1 937 335 0448",
    "sg:postcode":"45373",
    "sg:province":"OH",
    "sg:tags":[
        "organization",
        "welfare"
    ],
    "wof:name":"Partners In Hope",
    "wof:placetype":"venue"
},
  "geometry": {"coordinates":[-84.20518800000001,40.039038],"type":"Point"}
}