{
  "type": "Feature",
  "properties": {
    "addr:full": "1208 Race St Cincinnati OH 45202",
    "addr:housenumber": "1208",
    "addr:postcode": "45202",
    "addr:street": "Race St",
    "iso:country": "US",
    "sg:address": "1208 Race St",
    "sg:city": "Cincinnati",
    "sg:classifiers": [
      {
        "category": "Organizations",
        "subcategory": "Religious Organization",
        "type": "Services"
      }
    ],
    "sg:phone": "+1 513 421 0065",
    "sg:postcode": "45202",
    "sg:province": "OH",
    "sg:tags": [
      "church"
    ],
    "wof:name": "First Lutheran Church",
    "wof:placetype": "venue"
  },
  "geometry": {"coordinates":[-84.516582,39.109124],"type":"Point"}
}
