{
  "type": "Feature",
  "properties": {
    "addr:full": "623 E Market St Akron OH 44304",
    "addr:housenumber": "623",
    "addr:postcode": "44304",
    "addr:street": "E Market St",
    "iso:country": "US",
    "sg:address": "623 E Market St",
    "sg:city": "Akron",
    "sg:classifiers": [
      {
        "category": "Restaurant",
        "type": "Food \u0026 Drink"
      }
    ],
    "sg:menulink": "http://www.allmenus.com/oh/akron/164578-wendys/menu/",
    "sg:phone": "+1 330 762 8753",
    "sg:postcode": "44304",
    "sg:province": "OH",
    "sg:tags": [
      "burger",
      "american",
      "soup"
    ],
    "wof:name": "Wendy's",
    "wof:placetype": "venue"
  },
  "geometry": {"coordinates":[-81.497809,41.077559],"type":"Point"}
}
