{
  "type": "Feature",
  "properties": {
    "iso:country":"US",
    "sg:address":"1703 Co Rd 130",
    "sg:city":"Bellefontaine",
    "sg:classifiers":[
        {
            "category":"Building & Trades",
            "subcategory":"Construction",
            "type":"Services"
        }
    ],
    "sg:phone":"+1 937 592 8799",
    "sg:postcode":"43311",
    "sg:province":"OH",
    "sg:tags":[
        "contractor"
    ],
    "wof:name":"McCullough Drywall",
    "wof:placetype":"venue"
},
  "geometry": {"coordinates":[-83.78116300000001,40.378806],"type":"Point"}
}