{
  "type": "Feature",
  "properties": {
    "addr:full": "1060 W Bagley Rd Berea OH 44017",
    "addr:housenumber": "1060",
    "addr:postcode": "44017",
    "addr:street": "W Bagley Rd",
    "iso:country": "US",
    "sg:address": "1060 W Bagley Rd",
    "sg:city": "Berea",
    "sg:classifiers": [
      {
        "category": "Professional",
        "type": "Services"
      }
    ],
    "sg:phone": "+1 440 234 4425",
    "sg:postcode": "44017",
    "sg:province": "OH",
    "wof:name": "Partysolver",
    "wof:placetype": "venue"
  },
  "geometry": {"coordinates":[-81.89248,41.372572],"type":"Point"}
}
