{
  "type": "Feature",
  "properties": {
    "iso:country":"US",
    "sg:address":"4630 Elida Rd",
    "sg:city":"Lima",
    "sg:classifiers":[
        {
            "category":"Autos & Motor Vehicles",
            "subcategory":"Fuel & Gas Station",
            "type":"Retail Goods"
        }
    ],
    "sg:phone":"+1 419 331 4285",
    "sg:postcode":"45807",
    "sg:province":"OH",
    "sg:tags":[
        "grocery",
        "station",
        "gasoline"
    ],
    "wof:name":"Speedway 3617",
    "wof:placetype":"venue"
},
  "geometry": {"coordinates":[-84.186733,40.780805],"type":"Point"}
}