{
  "type": "Feature",
  "properties": {
    "addr:full":"4433 Bowen Rd Toledo OH 43613",
    "addr:housenumber":"4433",
    "addr:postcode":"43613",
    "addr:street":"Bowen Rd",
    "iso:country":"US",
    "sg:address":"4433 Bowen Rd",
    "sg:city":"Toledo",
    "sg:classifiers":[
        {
            "category":"Building & Trades",
            "subcategory":"Landscaping Services",
            "type":"Services"
        }
    ],
    "sg:phone":"+1 419 473 0368",
    "sg:postcode":"43613",
    "sg:province":"OH",
    "sg:tags":[
        "lawn",
        "maintenance",
        "grounds"
    ],
    "wof:name":"Hugheservices Lawn & Landscape",
    "wof:placetype":"venue"
},
  "geometry": {"coordinates":[-83.61077400000001,41.699719],"type":"Point"}
}