{
  "type": "Feature",
  "properties": {
    "addr:full": "5245 Oberlin Ave Lorain OH 44053",
    "addr:housenumber": "5245",
    "addr:postcode": "44053",
    "addr:street": "Oberlin Ave",
    "iso:country": "US",
    "sg:address": "5245 Oberlin Ave",
    "sg:city": "Lorain",
    "sg:classifiers": [
      {
        "category": "Shopping",
        "subcategory": "Tobacco",
        "type": "Retail Goods"
      }
    ],
    "sg:phone": "+1 440 960 1154",
    "sg:postcode": "44053",
    "sg:province": "OH",
    "sg:tags": [
      "cigarette",
      "cigar",
      "dealer"
    ],
    "wof:name": "Lorain's Cigarette LTD",
    "wof:placetype": "venue"
  },
  "geometry": {"coordinates":[-82.185586,41.423093],"type":"Point"}
}
