{
  "type": "Feature",
  "properties": {
    "iso:country":"US",
    "sg:address":"80 W Washington St",
    "sg:city":"Jamestown",
    "sg:classifiers":[
        {
            "category":"Retail",
            "subcategory":"Veterinary Services",
            "type":"Services"
        }
    ],
    "sg:phone":"+1 937 675 7411",
    "sg:postcode":"45335",
    "sg:province":"OH",
    "sg:tags":[
        "veterinarian"
    ],
    "wof:name":"Veterinary Associates",
    "wof:placetype":"venue"
},
  "geometry": {"coordinates":[-83.740575,39.65845],"type":"Point"}
}