{
  "type": "Feature",
  "properties": {
    "iso:country":"US",
    "sg:address":"432 Springs Dr",
    "sg:city":"Columbus",
    "sg:classifiers":[
        {
            "category":"Communications",
            "subcategory":"Film & Video Production",
            "type":"Services"
        }
    ],
    "sg:phone":"+1 614 267 2000",
    "sg:postcode":"43214",
    "sg:province":"OH",
    "sg:tags":[
        "taping"
    ],
    "wof:name":"Hurley Learning Systems Inc",
    "wof:placetype":"venue"
},
  "geometry": {"coordinates":[-83.00733,40.051679],"type":"Point"}
}