{
  "type": "Feature",
  "properties": {
    "addr:full": "432 Springs Dr Columbus OH 43214",
    "addr:housenumber": "432",
    "addr:postcode": "43214",
    "addr:street": "Springs Dr",
    "iso:country": "US",
    "sg:address": "432 Springs Dr",
    "sg:city": "Columbus",
    "sg:classifiers": [
      {
        "category": "Communications",
        "subcategory": "Film \u0026 Video Production",
        "type": "Services"
      }
    ],
    "sg:phone": "+1 614 267 2000",
    "sg:postcode": "43214",
    "sg:province": "OH",
    "sg:tags": [
      "taping"
    ],
    "wof:name": "Hurley Learning Systems Inc",
    "wof:placetype": "venue"
  },
  "geometry": {"coordinates":[-83.00733,40.051679],"type":"Point"}
}
