{
  "type": "Feature",
  "properties": {
    "addr:full":"561 W Schrock Rd Columbus OH 43229",
    "addr:housenumber":"561",
    "addr:postcode":"43229",
    "addr:street":"W Schrock Rd",
    "iso:country":"US",
    "sg:address":"561 W Schrock Rd",
    "sg:city":"Columbus",
    "sg:classifiers":[
        {
            "category":"Building & Trades",
            "subcategory":"Electrical",
            "type":"Services"
        }
    ],
    "sg:phone":"+1 614 885 4222",
    "sg:postcode":"43229",
    "sg:province":"OH",
    "sg:tags":[
        "rod",
        "installation",
        "lightning"
    ],
    "wof:name":"Sunshine Installations",
    "wof:placetype":"venue"
},
  "geometry": {"coordinates":[-83.001172,40.101281],"type":"Point"}
}