{
  "type": "Feature",
  "properties": {
    "addr:full": "7927 New Cumberland Rd NE Mineral City OH 44656",
    "addr:housenumber": "7927",
    "addr:postcode": "44656",
    "addr:street": "New Cumberland Rd Ne",
    "iso:country": "US",
    "sg:address": "7927 New Cumberland Rd NE",
    "sg:city": "Mineral City",
    "sg:classifiers": [
      {
        "category": "Social Services",
        "type": "Services"
      }
    ],
    "sg:phone": "+1 330 859 2324",
    "sg:postcode": "44656",
    "sg:province": "OH",
    "sg:tags": [
      "organization",
      "welfare"
    ],
    "wof:name": "Windy City Group Inc",
    "wof:placetype": "venue"
  },
  "geometry": {"coordinates":[-81.350324,40.593006],"type":"Point"}
}
