{
  "type": "Feature",
  "properties": {
    "addr:full": "1345 Lorine Pl Columbus OH 43235",
    "addr:housenumber": "1345",
    "addr:postcode": "43235",
    "addr:street": "Lorine Pl",
    "iso:country": "US",
    "sg:address": "1345 Lorine Pl",
    "sg:city": "Columbus",
    "sg:classifiers": [
      {
        "category": "Mining \u0026 Drilling",
        "type": "Manufacturing \u0026 Wholesale Goods"
      }
    ],
    "sg:phone": "+1 614 635 5781",
    "sg:postcode": "43235",
    "sg:province": "OH",
    "sg:tags": [
      "production",
      "gas",
      "oil"
    ],
    "wof:name": "Mason Producing Inc",
    "wof:placetype": "venue"
  },
  "geometry": {"coordinates":[-83.053212,40.105063],"type":"Point"}
}
