{
  "type": "Feature",
  "properties": {
    "iso:country":"US",
    "sg:address":"1345 Lorine Pl",
    "sg:city":"Columbus",
    "sg:classifiers":[
        {
            "category":"Mining & Drilling",
            "type":"Manufacturing & Wholesale Goods"
        }
    ],
    "sg:phone":"+1 614 635 5781",
    "sg:postcode":"43235",
    "sg:province":"OH",
    "sg:tags":[
        "production",
        "gas",
        "oil"
    ],
    "wof:name":"Mason Producing Inc",
    "wof:placetype":"venue"
},
  "geometry": {"coordinates":[-83.053212,40.105063],"type":"Point"}
}