{
  "type": "Feature",
  "properties": {
    "iso:country":"US",
    "sg:address":"4619 Main Ave",
    "sg:city":"Ashtabula",
    "sg:classifiers":[
        {
            "category":"Coffee & Tea",
            "type":"Food & Drink"
        },
        {
            "category":"Cafe",
            "type":"Food & Drink"
        }
    ],
    "sg:menulink":"http://www.allmenus.com/oh/ashtabula/57246-e-comm-cafe/menu/",
    "sg:phone":"+1 440 997 0099",
    "sg:postcode":"44004",
    "sg:province":"OH",
    "sg:tags":[
        "american"
    ],
    "wof:name":"E-comm Cafe",
    "wof:placetype":"venue"
},
  "geometry": {"coordinates":[-80.782251,41.865263],"type":"Point"}
}