{
  "type": "Feature",
  "properties": {
    "addr:full":"17005 Lorain Ave Cleveland OH 44111",
    "addr:housenumber":"17005",
    "addr:postcode":"44111",
    "addr:street":"Lorain Ave",
    "iso:country":"US",
    "sg:address":"17005 Lorain Ave",
    "sg:city":"Cleveland",
    "sg:classifiers":[
        {
            "category":"Shopping",
            "subcategory":"Jewelry",
            "type":"Retail Goods"
        }
    ],
    "sg:phone":"+1 216 251 5141",
    "sg:postcode":"44111",
    "sg:province":"OH",
    "sg:tags":[
        "repair"
    ],
    "wof:name":"Buchwald Jewelers",
    "wof:placetype":"venue"
},
  "geometry": {"coordinates":[-81.81586900000001,41.450283],"type":"Point"}
}