{
  "type": "Feature",
  "properties": {
    "addr:full": "1058 Old Logan Rd Lancaster OH 43130",
    "addr:housenumber": "1058",
    "addr:postcode": "43130",
    "addr:street": "Old Logan Rd",
    "iso:country": "US",
    "sg:address": "1058 Old Logan Rd",
    "sg:city": "Lancaster",
    "sg:classifiers": [
      {
        "category": "Retail",
        "subcategory": "Auto Repair",
        "type": "Services"
      }
    ],
    "sg:phone": "+1 740 654 4956",
    "sg:postcode": "43130",
    "sg:province": "OH",
    "sg:tags": [
      "body",
      "automobile",
      "painting"
    ],
    "wof:name": "Boyer Bros Paint \u0026 Body",
    "wof:placetype": "venue"
  },
  "geometry": {"coordinates":[-82.593079,39.70036],"type":"Point"}
}
