{
  "type": "Feature",
  "properties": {
    "iso:country":"US",
    "sg:address":"1058 Old Logan Rd",
    "sg:city":"Lancaster",
    "sg:classifiers":[
        {
            "category":"Retail",
            "subcategory":"Auto Repair",
            "type":"Services"
        }
    ],
    "sg:phone":"+1 740 654 4956",
    "sg:postcode":"43130",
    "sg:province":"OH",
    "sg:tags":[
        "body",
        "automobile",
        "painting"
    ],
    "wof:name":"Boyer Bros Paint & Body",
    "wof:placetype":"venue"
},
  "geometry": {"coordinates":[-82.593079,39.70036],"type":"Point"}
}