{
  "type": "Feature",
  "properties": {
    "addr:full": "29 4th St Shelby OH 44875",
    "addr:housenumber": "29",
    "addr:postcode": "44875",
    "addr:street": "4Th St",
    "iso:country": "US",
    "sg:address": "29 4th St",
    "sg:city": "Shelby",
    "sg:classifiers": [
      {
        "category": "Building \u0026 Trades",
        "subcategory": "Construction",
        "type": "Services"
      }
    ],
    "sg:phone": "+1 419 342 5342",
    "sg:postcode": "44875",
    "sg:province": "OH",
    "sg:tags": [
      "house"
    ],
    "wof:name": "August Maver Construction",
    "wof:placetype": "venue"
  },
  "geometry": {"coordinates":[-82.651383,40.884342],"type":"Point"}
}
