{
  "type": "Feature",
  "properties": {
    "iso:country":"US",
    "sg:address":"11226 State Rte 15",
    "sg:city":"Ottawa",
    "sg:classifiers":[
        {
            "category":"Farming",
            "subcategory":"Livestock Farm",
            "type":"Manufacturing & Wholesale Goods"
        }
    ],
    "sg:phone":"+1 419 523 4124",
    "sg:postcode":"45875",
    "sg:province":"OH",
    "sg:tags":[
        "hog",
        "or",
        "feedlot"
    ],
    "wof:name":"Steven Leopold",
    "wof:placetype":"venue"
},
  "geometry": {"coordinates":[-84.075929,41.047198],"type":"Point"}
}