{
  "type": "Feature",
  "properties": {
    "addr:full": "17325 Throckley Ave Cleveland OH 44128",
    "addr:housenumber": "17325",
    "addr:postcode": "44128",
    "addr:street": "Throckley Ave",
    "iso:country": "US",
    "sg:address": "17325 Throckley Ave",
    "sg:city": "Cleveland",
    "sg:classifiers": [
      {
        "category": "Shopping",
        "subcategory": "Florist",
        "type": "Retail Goods"
      }
    ],
    "sg:phone": "+1 216 752 4068",
    "sg:postcode": "44128",
    "sg:province": "OH",
    "wof:name": "JOY-Josephine Is Orgnl",
    "wof:placetype": "venue"
  },
  "geometry": {"coordinates":[-81.555668,41.455948],"type":"Point"}
}
