{
  "type": "Feature",
  "properties": {
    "addr:full": "37 Elva Ct Vandalia OH 45377",
    "addr:housenumber": "37",
    "addr:postcode": "45377",
    "addr:street": "Elva Ct",
    "iso:country": "US",
    "sg:address": "37 Elva Ct",
    "sg:city": "Vandalia",
    "sg:classifiers": [
      {
        "category": "Manufacturing",
        "subcategory": "Printing",
        "type": "Manufacturing \u0026 Wholesale Goods"
      }
    ],
    "sg:phone": "+1 937 898 7690",
    "sg:postcode": "45377",
    "sg:province": "OH",
    "sg:tags": [
      "commercial"
    ],
    "wof:name": "Digital Techniques",
    "wof:placetype": "venue"
  },
  "geometry": {"coordinates":[-84.199928,39.885443],"type":"Point"}
}
