{
  "type": "Feature",
  "properties": {
    "addr:full":"7 Endicott St Cincinnati OH 45218",
    "addr:housenumber":"7",
    "addr:postcode":"45218",
    "addr:street":"Endicott St",
    "iso:country":"US",
    "sg:address":"7 Endicott St",
    "sg:city":"Cincinnati",
    "sg:classifiers":[
        {
            "category":"Education",
            "subcategory":"Library",
            "type":"Public Place"
        }
    ],
    "sg:phone":"+1 513 369 4441",
    "sg:postcode":"45218",
    "sg:province":"OH",
    "sg:website":"http://www.mhrecovery.com",
    "wof:name":"Public Library",
    "wof:placetype":"venue"
},
  "geometry": {"coordinates":[-84.52139099999999,39.268036],"type":"Point"}
}