{
  "type": "Feature",
  "properties": {
    "iso:country":"US",
    "sg:address":"5050 Nebraska Ave",
    "sg:city":"Dayton",
    "sg:classifiers":[
        {
            "category":"Personal",
            "subcategory":"Beauty Salon",
            "type":"Services"
        }
    ],
    "sg:phone":"+1 937 237 9450",
    "sg:postcode":"45424",
    "sg:province":"OH",
    "wof:name":"Shea's Beauty Salon",
    "wof:placetype":"venue"
},
  "geometry": {"coordinates":[-84.119868,39.830527],"type":"Point"}
}