{
  "type": "Feature",
  "properties": {
    "addr:full":"2820 Maple Ave Zanesville OH 43701",
    "addr:housenumber":"2820",
    "addr:postcode":"43701",
    "addr:street":"Maple Ave",
    "iso:country":"US",
    "sg:address":"2820 Maple Ave",
    "sg:city":"Zanesville",
    "sg:classifiers":[
        {
            "category":"Restaurant",
            "type":"Food & Drink"
        }
    ],
    "sg:menulink":"http://www.allmenus.com/oh/zanesville/100880-captain-ds-seafood/menu/",
    "sg:phone":"+1 740 452 1585",
    "sg:postcode":"43701",
    "sg:province":"OH",
    "sg:tags":[
        "seafood",
        "american"
    ],
    "wof:name":"Captain D's Seafood",
    "wof:placetype":"venue"
},
  "geometry": {"coordinates":[-82.011838,39.973845],"type":"Point"}
}