{
  "type": "Feature",
  "properties": {
    "addr:full": "4455 Hills and Dales Rd NW Canton OH 44708",
    "addr:housenumber": "4455",
    "addr:postcode": "44708",
    "addr:street": "Hills And Dales Rd Nw",
    "iso:country": "US",
    "sg:address": "4455 Hills and Dales Rd NW",
    "sg:city": "Canton",
    "sg:classifiers": [
      {
        "category": "Banks \u0026 Credit Unions",
        "subcategory": "Bank",
        "type": "Services"
      }
    ],
    "sg:phone": "+1 330 478 3400",
    "sg:postcode": "44708",
    "sg:province": "OH",
    "sg:tags": [
      "mortgage",
      "loan",
      "banker",
      "real estate"
    ],
    "wof:name": "First Merit Mortgage Corp",
    "wof:placetype": "venue"
  },
  "geometry": {"coordinates":[-81.426601,40.833068],"type":"Point"}
}
