{
  "type": "Feature",
  "properties": {
    "addr:full": "420 Center St Wheelersburg OH 45694",
    "addr:housenumber": "420",
    "addr:postcode": "45694",
    "addr:street": "Center St",
    "iso:country": "US",
    "sg:address": "420 Center St",
    "sg:city": "Wheelersburg",
    "sg:classifiers": [
      {
        "category": "Health Services",
        "subcategory": "Chiropractor",
        "type": "Services"
      }
    ],
    "sg:phone": "+1 740 574 0074",
    "sg:postcode": "45694",
    "sg:province": "OH",
    "wof:name": "Lawson Family Chiropractic",
    "wof:placetype": "venue"
  },
  "geometry": {"coordinates":[-82.859747,38.728919],"type":"Point"}
}
