{
  "type": "Feature",
  "properties": {
    "iso:country":"US",
    "sg:address":"322 Reading Rd",
    "sg:city":"Mason",
    "sg:classifiers":[
        {
            "category":"Restaurant",
            "type":"Food & Drink"
        }
    ],
    "sg:phone":"+1 513 398 0718",
    "sg:postcode":"45040",
    "sg:province":"OH",
    "sg:tags":[
        "shop",
        "coffee"
    ],
    "sg:website":"www.kiddcoffee.com",
    "wof:name":"Kidd Coffee",
    "wof:placetype":"venue"
},
  "geometry": {"coordinates":[-84.314598,39.358204],"type":"Point"}
}