{
  "type": "Feature",
  "properties": {
    "addr:full":"14 Heid Dr Dayton OH 45404",
    "addr:housenumber":"14",
    "addr:postcode":"45404",
    "addr:street":"Heid Dr",
    "iso:country":"US",
    "sg:address":"14 Heid Dr",
    "sg:city":"Dayton",
    "sg:classifiers":[
        {
            "category":"Manufacturing",
            "subcategory":"Metals",
            "type":"Manufacturing & Wholesale Goods"
        }
    ],
    "sg:phone":"+1 937 233 9191",
    "sg:postcode":"45404",
    "sg:province":"OH",
    "sg:tags":[
        "automotive",
        "stamping",
        "parts"
    ],
    "wof:name":"Select Industries Corp",
    "wof:placetype":"venue"
},
  "geometry": {"coordinates":[-84.163599,39.795396],"type":"Point"}
}