{
  "type": "Feature",
  "properties": {
    "addr:full": "37174 State Rte 93 Hamden OH 45634",
    "addr:housenumber": "37174",
    "addr:postcode": "45634",
    "addr:street": "State Rte 93",
    "iso:country": "US",
    "sg:address": "37174 State Rte 93",
    "sg:city": "Hamden",
    "sg:classifiers": [
      {
        "category": "Personal",
        "subcategory": "Beauty Salon",
        "type": "Services"
      }
    ],
    "sg:phone": "+1 740 384 6418",
    "sg:postcode": "45634",
    "sg:province": "OH",
    "wof:name": "His N Her's Styling \u0026 Tanning",
    "wof:placetype": "venue"
  },
  "geometry": {"coordinates":[-82.509619,39.184399],"type":"Point"}
}
