{
  "type": "Feature",
  "properties": {
    "addr:full": "2735 Hudson Dr Cuyahoga Falls OH 44221",
    "addr:housenumber": "2735",
    "addr:postcode": "44221",
    "addr:street": "Hudson Dr",
    "iso:country": "US",
    "sg:address": "2735 Hudson Dr",
    "sg:city": "Cuyahoga Falls",
    "sg:classifiers": [
      {
        "category": "Home \u0026 Garden",
        "subcategory": "Hardware",
        "type": "Retail Goods"
      }
    ],
    "sg:phone": "+1 330 928 5316",
    "sg:postcode": "44221",
    "sg:province": "OH",
    "wof:name": "Hudson Drive Hardware",
    "wof:placetype": "venue"
  },
  "geometry": {"coordinates":[-81.472324,41.146892],"type":"Point"}
}
