{
  "type": "Feature",
  "properties": {
    "addr:full": "5160 Wallings Rd Cleveland OH 44133",
    "addr:housenumber": "5160",
    "addr:postcode": "44133",
    "addr:street": "Wallings Rd",
    "iso:country": "US",
    "sg:address": "5160 Wallings Rd",
    "sg:city": "Cleveland",
    "sg:classifiers": [
      {
        "category": "Sports \u0026 Exercise",
        "subcategory": "Gym",
        "type": "Entertainment"
      }
    ],
    "sg:phone": "+1 440 237 6668",
    "sg:postcode": "44133",
    "sg:province": "OH",
    "sg:tags": [
      "club",
      "health",
      "studio",
      "gymnasium"
    ],
    "wof:name": "Curves",
    "wof:placetype": "venue"
  },
  "geometry": {"coordinates":[-81.718329,41.332905],"type":"Point"}
}
