{
  "type": "Feature",
  "properties": {
    "addr:full": "418 Colegate Dr Marietta OH 45750",
    "addr:housenumber": "418",
    "addr:postcode": "45750",
    "addr:street": "Colegate Dr",
    "iso:country": "US",
    "sg:address": "418 Colegate Dr",
    "sg:city": "Marietta",
    "sg:classifiers": [
      {
        "category": "Government",
        "subcategory": "Office",
        "type": "Public Place"
      }
    ],
    "sg:phone": "+1 740 373 7113",
    "sg:postcode": "45750",
    "sg:province": "OH",
    "sg:tags": [
      "federal",
      "planning",
      "dev"
    ],
    "wof:name": "USDA Rural Development",
    "wof:placetype": "venue"
  },
  "geometry": {"coordinates":[-81.436197,39.424948],"type":"Point"}
}
