{
  "type": "Feature",
  "properties": {
    "addr:full": "8008 Main St Miamitown OH 45041",
    "addr:housenumber": "8008",
    "addr:postcode": "45041",
    "addr:street": "Main St",
    "iso:country": "US",
    "sg:address": "8008 Main St",
    "sg:city": "Miamitown",
    "sg:classifiers": [
      {
        "category": "Shopping",
        "subcategory": "Used Merchandise",
        "type": "Retail Goods"
      }
    ],
    "sg:phone": "+1 513 353 2689",
    "sg:postcode": "45041",
    "sg:province": "OH",
    "sg:tags": [
      "antique"
    ],
    "wof:name": "Chamber House Antique Mall",
    "wof:placetype": "venue"
  },
  "geometry": {"coordinates":[-84.70476,39.213878],"type":"Point"}
}
