{
  "type": "Feature",
  "properties": {
    "addr:full":"5555 Canal Rd Cleveland OH 44125",
    "addr:housenumber":"5555",
    "addr:postcode":"44125",
    "addr:street":"Canal Rd",
    "iso:country":"US",
    "sg:address":"5555 Canal Rd",
    "sg:city":"Cleveland",
    "sg:classifiers":[
        {
            "category":"Professional",
            "subcategory":"Engineering",
            "type":"Services"
        }
    ],
    "sg:phone":"+1 216 447 1335",
    "sg:postcode":"44125",
    "sg:province":"OH",
    "wof:name":"PSI Environmental",
    "wof:placetype":"venue"
},
  "geometry": {"coordinates":[-81.629395,41.411354],"type":"Point"}
}