{
  "type": "Feature",
  "properties": {
    "iso:country":"US",
    "sg:address":"23220 Chagrin Blvd",
    "sg:city":"Cleveland",
    "sg:classifiers":[
        {
            "category":"Professional",
            "type":"Services"
        }
    ],
    "sg:phone":"+1 216 378 9670",
    "sg:postcode":"44122",
    "sg:province":"OH",
    "sg:tags":[
        "establishment"
    ],
    "wof:name":"John W Gold LLC",
    "wof:placetype":"venue"
},
  "geometry": {"coordinates":[-81.505443,41.464401],"type":"Point"}
}