{
  "type": "Feature",
  "properties": {
    "addr:full": "17530 Schumm Rd Willshire OH 45898",
    "addr:postcode": "17530;45898",
    "addr:street": "Schumm Rd",
    "iso:country": "US",
    "sg:address": "17530 Schumm Rd",
    "sg:city": "Willshire",
    "sg:classifiers": [
      {
        "category": "Real Estate",
        "subcategory": "Real Estate Operator",
        "type": "Services"
      }
    ],
    "sg:phone": "+1 419 495 2025",
    "sg:postcode": "45898",
    "sg:province": "OH",
    "sg:tags": [
      "property",
      "lessor"
    ],
    "wof:name": "Luginbill Farm",
    "wof:placetype": "venue"
  },
  "geometry": {"coordinates":[-84.727414,40.749331],"type":"Point"}
}
