{
  "type": "Feature",
  "properties": {
    "addr:full":"351 W Main St Portage OH 43451",
    "addr:housenumber":"351",
    "addr:postcode":"43451",
    "addr:street":"W Main St",
    "iso:country":"US",
    "sg:address":"351 W Main St",
    "sg:city":"Portage",
    "sg:classifiers":[
        {
            "category":"Social Services",
            "subcategory":"Adult Care",
            "type":"Services"
        },
        {
            "category":"Real Estate",
            "subcategory":"Real Estate Agent",
            "type":"Services"
        }
    ],
    "sg:phone":"+1 419 686 6951",
    "sg:postcode":"43451",
    "sg:province":"OH",
    "sg:tags":[
        "home",
        "manager"
    ],
    "wof:name":"Warner Home",
    "wof:placetype":"venue"
},
  "geometry": {"coordinates":[-83.65899400000001,41.32671],"type":"Point"}
}