{
  "type": "Feature",
  "properties": {
    "addr:full": "1800 Tiffin Ave Findlay OH 45840",
    "addr:housenumber": "1800",
    "addr:postcode": "45840",
    "addr:street": "Tiffin Ave",
    "iso:country": "US",
    "sg:address": "1800 Tiffin Ave",
    "sg:city": "Findlay",
    "sg:classifiers": [
      {
        "category": "Shopping",
        "subcategory": "Jewelry",
        "type": "Retail Goods"
      }
    ],
    "sg:phone": "+1 419 420 0015",
    "sg:postcode": "45840",
    "sg:province": "OH",
    "sg:tags": [
      "jeweler"
    ],
    "wof:name": "Cory's Jewel Box",
    "wof:placetype": "venue"
  },
  "geometry": {"coordinates":[-83.61281,41.053246],"type":"Point"}
}
