{
  "type": "Feature",
  "properties": {
    "addr:full":"2675 Edmondson Rd Cincinnati OH 45209",
    "addr:housenumber":"2675",
    "addr:postcode":"45209",
    "addr:street":"Edmondson Rd",
    "iso:country":"US",
    "sg:address":"2675 Edmondson Rd",
    "sg:city":"Cincinnati",
    "sg:classifiers":[
        {
            "category":"Shopping",
            "subcategory":"Clothing, Apparel, & Fashions",
            "type":"Retail Goods"
        }
    ],
    "sg:phone":"+1 513 841 2111",
    "sg:postcode":"45209",
    "sg:province":"OH",
    "sg:website":"www.nyandcompany.com",
    "wof:name":"New York & Co",
    "wof:placetype":"venue"
},
  "geometry": {"coordinates":[-84.44460599999999,39.148979],"type":"Point"}
}