{
  "type": "Feature",
  "properties": {
    "addr:full":"9536 Co Rd 313 Findlay OH 45840",
    "addr:housenumber":"9536",
    "addr:postcode":"45840",
    "addr:street":"Co Rd 313",
    "iso:country":"US",
    "sg:address":"9536 Co Rd 313",
    "sg:city":"Findlay",
    "sg:classifiers":[
        {
            "category":"Retail",
            "subcategory":"Veterinary Services",
            "type":"Services"
        }
    ],
    "sg:phone":"+1 419 424 1463",
    "sg:postcode":"45840",
    "sg:province":"OH",
    "wof:name":"G D Reissig DVM",
    "wof:placetype":"venue"
},
  "geometry": {"coordinates":[-83.686932,41.010752],"type":"Point"}
}