{
  "type": "Feature",
  "properties": {
    "addr:full": "6538 Glenmont Dr Hamilton OH 45011",
    "addr:housenumber": "6538",
    "addr:postcode": "45011",
    "addr:street": "Glenmont Dr",
    "iso:country": "US",
    "sg:address": "6538 Glenmont Dr",
    "sg:city": "Hamilton",
    "sg:classifiers": [
      {
        "category": "Building \u0026 Trades",
        "subcategory": "Construction",
        "type": "Services"
      }
    ],
    "sg:phone": "+1 513 896 9272",
    "sg:postcode": "45011",
    "sg:province": "OH",
    "sg:tags": [
      "hanging",
      "contractor"
    ],
    "wof:name": "Connie Cargould Wallpapering",
    "wof:placetype": "venue"
  },
  "geometry": {"coordinates":[-84.521939,39.393932],"type":"Point"}
}
