{
  "type": "Feature",
  "properties": {
    "iso:country":"US",
    "sg:address":"62 State Rte 97",
    "sg:city":"Lexington",
    "sg:classifiers":[
        {
            "category":"Wholesale",
            "subcategory":"Construction Materials",
            "type":"Manufacturing & Wholesale Goods"
        }
    ],
    "sg:phone":"+1 419 884 2910",
    "sg:postcode":"44904",
    "sg:province":"OH",
    "sg:tags":[
        "fence"
    ],
    "wof:name":"Jay's Fencing",
    "wof:placetype":"venue"
},
  "geometry": {"coordinates":[-82.587976,40.678864],"type":"Point"}
}