{
  "type": "Feature",
  "properties": {
    "addr:full":"425 Crescent Ave Cincinnati OH 45215",
    "addr:housenumber":"425",
    "addr:postcode":"45215",
    "addr:street":"Crescent Ave",
    "iso:country":"US",
    "sg:address":"425 Crescent Ave",
    "sg:city":"Cincinnati",
    "sg:classifiers":[
        {
            "category":"Education",
            "subcategory":"School",
            "type":"Public Place"
        }
    ],
    "sg:phone":"+1 513 761 0223",
    "sg:postcode":"45215",
    "sg:province":"OH",
    "wof:name":"Terry's Montessori School",
    "wof:placetype":"venue"
},
  "geometry": {"coordinates":[-84.46549400000001,39.225895],"type":"Point"}
}