{
  "type": "Feature",
  "properties": {
    "addr:full":"5484 Dutch Hollow Rd Elida OH 45807",
    "addr:housenumber":"5484",
    "addr:postcode":"45807",
    "addr:street":"Dutch Hollow Rd",
    "iso:country":"US",
    "sg:address":"5484 Dutch Hollow Rd",
    "sg:city":"Elida",
    "sg:classifiers":[
        {
            "category":"Retail",
            "subcategory":"Auto Repair",
            "type":"Services"
        }
    ],
    "sg:phone":"+1 419 339 9590",
    "sg:postcode":"45807",
    "sg:province":"OH",
    "sg:tags":[
        "repairing",
        "automobile",
        "general"
    ],
    "wof:name":"Strayer Auto Repair",
    "wof:placetype":"venue"
},
  "geometry": {"coordinates":[-84.203954,40.811347],"type":"Point"}
}