{
  "type": "Feature",
  "properties": {
    "addr:full": "4905 Robinhood Dr Willoughby OH 44094",
    "addr:housenumber": "4905",
    "addr:postcode": "44094",
    "addr:street": "Robinhood Dr",
    "iso:country": "US",
    "sg:address": "4905 Robinhood Dr",
    "sg:city": "Willoughby",
    "sg:classifiers": [
      {
        "category": "Restaurant",
        "type": "Food \u0026 Drink"
      }
    ],
    "sg:phone": "+1 440 942 1633",
    "sg:postcode": "44094",
    "sg:province": "OH",
    "sg:tags": [
      "eating"
    ],
    "wof:name": "Hong To Chinese Restaurant",
    "wof:placetype": "venue"
  },
  "geometry": {"coordinates":[-81.426969,41.625089],"type":"Point"}
}
