{
  "type": "Feature",
  "properties": {
    "iso:country":"US",
    "sg:address":"3239 Medina Rd",
    "sg:city":"Medina",
    "sg:classifiers":[
        {
            "category":"Autos & Motor Vehicles",
            "subcategory":"Fuel & Gas Station",
            "type":"Retail Goods"
        }
    ],
    "sg:phone":"+1 330 723 2291",
    "sg:postcode":"44256",
    "sg:province":"OH",
    "sg:tags":[
        "grocery",
        "station",
        "gasoline"
    ],
    "wof:name":"Speedway 9294",
    "wof:placetype":"venue"
},
  "geometry": {"coordinates":[-81.804427,41.136297],"type":"Point"}
}