{
  "type": "Feature",
  "properties": {
    "addr:full":"7730 1st Pl Cleveland OH 44146",
    "addr:housenumber":"7730",
    "addr:postcode":"44146",
    "addr:street":"1St Pl",
    "iso:country":"US",
    "sg:address":"7730 1st Pl",
    "sg:city":"Cleveland",
    "sg:classifiers":[
        {
            "category":"Professional",
            "subcategory":"Testing Lab",
            "type":"Services"
        }
    ],
    "sg:phone":"+1 440 786 9762",
    "sg:postcode":"44146",
    "sg:province":"OH",
    "sg:tags":[
        "laboratory"
    ],
    "wof:name":"Ameri Path",
    "wof:placetype":"venue"
},
  "geometry": {"coordinates":[-81.511321,41.374794],"type":"Point"}
}