{
  "type": "Feature",
  "properties": {
    "iso:country":"US",
    "sg:address":"9153 N Dixie Dr",
    "sg:city":"Dayton",
    "sg:classifiers":[
        {
            "category":"Retail",
            "subcategory":"Repair Shop",
            "type":"Services"
        },
        {
            "category":"Home & Garden",
            "subcategory":"Furniture",
            "type":"Retail Goods"
        }
    ],
    "sg:phone":"+1 937 454 1801",
    "sg:postcode":"45414",
    "sg:province":"OH",
    "sg:tags":[
        "refinishing"
    ],
    "wof:name":"Petes Furniture Repair Inc",
    "wof:placetype":"venue"
},
  "geometry": {"coordinates":[-84.199167,39.864978],"type":"Point"}
}