{
  "type": "Feature",
  "properties": {
    "addr:full": "7637 Oregon Ridge Rd Millfield OH 45761",
    "addr:housenumber": "7637",
    "addr:postcode": "45761",
    "addr:street": "Oregon Ridge Rd",
    "iso:country": "US",
    "sg:address": "7637 Oregon Ridge Rd",
    "sg:city": "Millfield",
    "sg:classifiers": [
      {
        "category": "Shopping",
        "subcategory": "Musical Instruments",
        "type": "Retail Goods"
      }
    ],
    "sg:phone": "+1 740 767 9808",
    "sg:postcode": "45761",
    "sg:province": "OH",
    "wof:name": "Volcano Guitar Works",
    "wof:placetype": "venue"
  },
  "geometry": {"coordinates":[-82.135253,39.461807],"type":"Point"}
}
