{
  "type": "Feature",
  "properties": {
    "addr:full":"5525 Parkside Dr Mason OH 45040",
    "addr:housenumber":"5525",
    "addr:postcode":"45040",
    "addr:street":"Parkside Dr",
    "iso:country":"US",
    "sg:address":"5525 Parkside Dr",
    "sg:city":"Mason",
    "sg:classifiers":[
        {
            "category":"Food & Beverages",
            "subcategory":"Groceries & Convenience Stores",
            "type":"Retail Goods"
        }
    ],
    "sg:phone":"+1 513 398 3705",
    "sg:postcode":"45040",
    "sg:province":"OH",
    "sg:tags":[
        "station",
        "gasoline"
    ],
    "wof:name":"Circle K Store",
    "wof:placetype":"venue"
},
  "geometry": {"coordinates":[-84.280593,39.35851],"type":"Point"}
}