{
  "type": "Feature",
  "properties": {
    "iso:country":"US",
    "sg:address":"3021 Bethel Rd",
    "sg:city":"Columbus",
    "sg:classifiers":[
        {
            "category":"Travel",
            "subcategory":"Travel Agent",
            "type":"Entertainment"
        }
    ],
    "sg:phone":"+1 614 442 1505",
    "sg:postcode":"43220",
    "sg:province":"OH",
    "sg:tags":[
        "passenger",
        "transportation",
        "agency",
        "tour",
        "ar",
        "operator"
    ],
    "wof:name":"Traveltyme Inc",
    "wof:placetype":"venue"
},
  "geometry": {"coordinates":[-83.097518,40.065021],"type":"Point"}
}