{
  "type": "Feature",
  "properties": {
    "iso:country":"US",
    "sg:address":"1107 E Bogart Rd",
    "sg:city":"Sandusky",
    "sg:classifiers":[
        {
            "category":"Home & Garden",
            "subcategory":"Furniture",
            "type":"Retail Goods"
        }
    ],
    "sg:phone":"+1 419 621 5610",
    "sg:postcode":"44870",
    "sg:province":"OH",
    "wof:name":"Mallard Bay Patio & Fireplace",
    "wof:placetype":"venue"
},
  "geometry": {"coordinates":[-82.655636,41.395862],"type":"Point"}
}