{
  "type": "Feature",
  "properties": {
    "addr:full": "1107 E Bogart Rd Sandusky OH 44870",
    "addr:housenumber": "1107",
    "addr:postcode": "44870",
    "addr:street": "E Bogart Rd",
    "iso:country": "US",
    "sg:address": "1107 E Bogart Rd",
    "sg:city": "Sandusky",
    "sg:classifiers": [
      {
        "category": "Home \u0026 Garden",
        "subcategory": "Furniture",
        "type": "Retail Goods"
      }
    ],
    "sg:phone": "+1 419 621 5610",
    "sg:postcode": "44870",
    "sg:province": "OH",
    "wof:name": "Mallard Bay Patio \u0026 Fireplace",
    "wof:placetype": "venue"
  },
  "geometry": {"coordinates":[-82.655636,41.395862],"type":"Point"}
}
