{
  "type": "Feature",
  "properties": {
    "addr:full":"3937 Spring Grove Ave Cincinnati OH 45223",
    "addr:housenumber":"3937",
    "addr:postcode":"45223",
    "addr:street":"Spring Grove Ave",
    "iso:country":"US",
    "sg:address":"3937 Spring Grove Ave",
    "sg:city":"Cincinnati",
    "sg:classifiers":[
        {
            "category":"Retail",
            "subcategory":"Repair Shop",
            "type":"Services"
        }
    ],
    "sg:phone":"+1 513 681 1977",
    "sg:postcode":"45223",
    "sg:province":"OH",
    "sg:tags":[
        "refinishing",
        "furniture"
    ],
    "wof:name":"Final Finish",
    "wof:placetype":"venue"
},
  "geometry": {"coordinates":[-84.537958,39.159406],"type":"Point"}
}