{
  "type": "Feature",
  "properties": {
    "addr:full":"1109 Howe Ave Cuyahoga Falls OH 44221",
    "addr:housenumber":"1109",
    "addr:postcode":"44221",
    "addr:street":"Howe Ave",
    "iso:country":"US",
    "sg:address":"1109 Howe Ave",
    "sg:city":"Cuyahoga Falls",
    "sg:classifiers":[
        {
            "category":"Retail",
            "subcategory":"Repair Shop",
            "type":"Services"
        },
        {
            "category":"Home & Garden",
            "subcategory":"Household Appliances",
            "type":"Retail Goods"
        }
    ],
    "sg:phone":"+1 330 633 3333",
    "sg:postcode":"44221",
    "sg:province":"OH",
    "sg:tags":[
        "machine",
        "used",
        "merchandise",
        "se",
        "sewing"
    ],
    "wof:name":"Akron Sewing Machine Center",
    "wof:placetype":"venue"
},
  "geometry": {"coordinates":[-81.466381,41.118977],"type":"Point"}
}