{
  "type": "Feature",
  "properties": {
    "addr:full":"7552 Pearl Rd Cleveland OH 44130",
    "addr:housenumber":"7552",
    "addr:postcode":"44130",
    "addr:street":"Pearl Rd",
    "iso:country":"US",
    "sg:address":"7552 Pearl Rd",
    "sg:city":"Cleveland",
    "sg:classifiers":[
        {
            "category":"Building & Trades",
            "subcategory":"Construction",
            "type":"Services"
        }
    ],
    "sg:phone":"+1 440 816 9397",
    "sg:postcode":"44130",
    "sg:province":"OH",
    "sg:tags":[
        "house"
    ],
    "wof:name":"Diversfd Constr of OH LLC",
    "wof:placetype":"venue"
},
  "geometry": {"coordinates":[-81.815583,41.359122],"type":"Point"}
}