{
  "type": "Feature",
  "properties": {
    "iso:country":"US",
    "sg:address":"111 Exchange St",
    "sg:city":"Bellevue",
    "sg:classifiers":[
        {
            "category":"Local Transit",
            "type":"Transportation"
        }
    ],
    "sg:phone":"+1 419 483 3322",
    "sg:postcode":"44811",
    "sg:province":"OH",
    "sg:tags":[
        "ambulance"
    ],
    "wof:name":"North Central EMS",
    "wof:placetype":"venue"
},
  "geometry": {"coordinates":[-82.840834,41.274663],"type":"Point"}
}