{
  "type": "Feature",
  "properties": {
    "iso:country":"US",
    "sg:address":"56 N Portage St",
    "sg:city":"Doylestown",
    "sg:classifiers":[
        {
            "category":"Education",
            "subcategory":"School",
            "type":"Public Place"
        }
    ],
    "sg:phone":"+1 330 658 6368",
    "sg:postcode":"44230",
    "sg:province":"OH",
    "sg:tags":[
        "board"
    ],
    "wof:name":"Chippewa School District",
    "wof:placetype":"venue"
},
  "geometry": {"coordinates":[-81.696892,40.969577],"type":"Point"}
}