{
  "type": "Feature",
  "properties": {
    "addr:full": "56 N Portage St Doylestown OH 44230",
    "addr:housenumber": "56",
    "addr:postcode": "44230",
    "addr:street": "N Portage St",
    "iso:country": "US",
    "sg:address": "56 N Portage St",
    "sg:city": "Doylestown",
    "sg:classifiers": [
      {
        "category": "Education",
        "subcategory": "School",
        "type": "Public Place"
      }
    ],
    "sg:phone": "+1 330 658 6368",
    "sg:postcode": "44230",
    "sg:province": "OH",
    "sg:tags": [
      "board"
    ],
    "wof:name": "Chippewa School District",
    "wof:placetype": "venue"
  },
  "geometry": {"coordinates":[-81.696892,40.969577],"type":"Point"}
}
