{
  "type": "Feature",
  "properties": {
    "addr:full": "9650 Yale Rd Deerfield OH 44411",
    "addr:housenumber": "9650",
    "addr:postcode": "44411",
    "addr:street": "Yale Rd",
    "iso:country": "US",
    "sg:address": "9650 Yale Rd",
    "sg:city": "Deerfield",
    "sg:classifiers": [
      {
        "category": "Freight",
        "type": "Transportation"
      }
    ],
    "sg:phone": "+1 330 654 4677",
    "sg:postcode": "44411",
    "sg:province": "OH",
    "sg:tags": [
      "operator",
      "local",
      "trucking"
    ],
    "wof:name": "Drd Trucking Inc An Ohio",
    "wof:placetype": "venue"
  },
  "geometry": {"coordinates":[-81.043136,41.062107],"type":"Point"}
}
