{
  "type": "Feature",
  "properties": {
    "addr:full":"128 S Michigan Ave Edgerton OH 43517",
    "addr:housenumber":"128",
    "addr:postcode":"43517",
    "addr:street":"S Michigan Ave",
    "iso:country":"US",
    "sg:address":"128 S Michigan Ave",
    "sg:city":"Edgerton",
    "sg:classifiers":[
        {
            "category":"Professional",
            "type":"Services"
        }
    ],
    "sg:phone":"+1 419 298 2180",
    "sg:postcode":"43517",
    "sg:province":"OH",
    "wof:name":"Fat Frog LLC",
    "wof:placetype":"venue"
},
  "geometry": {"coordinates":[-84.748141,41.448529],"type":"Point"}
}