{
  "type": "Feature",
  "properties": {
    "iso:country":"US",
    "sg:address":"4001 Ackerman Blvd",
    "sg:city":"Dayton",
    "sg:classifiers":[
        {
            "category":"Education",
            "subcategory":"School",
            "type":"Public Place"
        }
    ],
    "sg:phone":"+1 937 499 1870",
    "sg:postcode":"45429",
    "sg:province":"OH",
    "wof:name":"Oakview Elementary School",
    "wof:placetype":"venue"
},
  "geometry": {"coordinates":[-84.15453,39.688266],"type":"Point"}
}