{
  "type": "Feature",
  "properties": {
    "addr:full": "4871 Prosperity Pl Cincinnati OH 45238",
    "addr:housenumber": "4871",
    "addr:postcode": "45238",
    "addr:street": "Prosperity Pl",
    "iso:country": "US",
    "sg:address": "4871 Prosperity Pl",
    "sg:city": "Cincinnati",
    "sg:classifiers": [
      {
        "category": "Health Services",
        "subcategory": "Doctor",
        "type": "Services"
      }
    ],
    "sg:phone": "+1 513 251 9900",
    "sg:postcode": "45238",
    "sg:province": "OH",
    "sg:tags": [
      "physician",
      "surgeon"
    ],
    "wof:name": "Midwest Physicians \u0026 Surgeons",
    "wof:placetype": "venue"
  },
  "geometry": {"coordinates":[-84.596576,39.12296],"type":"Point"}
}
