{
  "type": "Feature",
  "properties": {
    "addr:full": "323 Wooster Rd Mount Vernon OH 43050",
    "addr:housenumber": "323",
    "addr:postcode": "43050",
    "addr:street": "Wooster Rd",
    "iso:country": "US",
    "sg:address": "323 Wooster Rd",
    "sg:city": "Mount Vernon",
    "sg:classifiers": [
      {
        "category": "Building \u0026 Trades",
        "subcategory": "Construction",
        "type": "Services"
      }
    ],
    "sg:phone": "+1 614 989 9439",
    "sg:postcode": "43050",
    "sg:province": "OH",
    "sg:tags": [
      "concrete"
    ],
    "wof:name": "A \u0026 D Concrete Concepts Inc",
    "wof:placetype": "venue"
  },
  "geometry": {"coordinates":[-82.477456,40.406161],"type":"Point"}
}
