{
  "type": "Feature",
  "properties": {
    "iso:country":"US",
    "sg:address":"323 Wooster Rd",
    "sg:city":"Mount Vernon",
    "sg:classifiers":[
        {
            "category":"Building & Trades",
            "subcategory":"Construction",
            "type":"Services"
        }
    ],
    "sg:phone":"+1 614 989 9439",
    "sg:postcode":"43050",
    "sg:province":"OH",
    "sg:tags":[
        "concrete"
    ],
    "wof:name":"A & D Concrete Concepts Inc",
    "wof:placetype":"venue"
},
  "geometry": {"coordinates":[-82.477456,40.406161],"type":"Point"}
}