{
  "type": "Feature",
  "properties": {
    "addr:full":"71 N Canal St Akron OH 44308",
    "addr:housenumber":"71",
    "addr:postcode":"44308",
    "addr:street":"N Canal St",
    "iso:country":"US",
    "sg:address":"71 N Canal St",
    "sg:city":"Akron",
    "sg:classifiers":[
        {
            "category":"Building & Trades",
            "subcategory":"Electrical",
            "type":"Services"
        }
    ],
    "sg:phone":"+1 330 376 7545",
    "sg:postcode":"44308",
    "sg:province":"OH",
    "sg:tags":[
        "electrical",
        "contractor"
    ],
    "wof:name":"Modern Lighting & Elc Corp",
    "wof:placetype":"venue"
},
  "geometry": {"coordinates":[-81.517315,41.087707],"type":"Point"}
}