{
  "type": "Feature",
  "properties": {
    "addr:full": "2536 Columbus St Grove City OH 43123",
    "addr:housenumber": "2536",
    "addr:postcode": "43123",
    "addr:street": "Columbus St",
    "iso:country": "US",
    "sg:address": "2536 Columbus St",
    "sg:city": "Grove City",
    "sg:classifiers": [
      {
        "category": "Restaurant",
        "type": "Food \u0026 Drink"
      }
    ],
    "sg:menulink": "http://www.allmenus.com/oh/jackson/79135-pizza-hut/menu/",
    "sg:phone": "+1 614 895 1111",
    "sg:postcode": "43123",
    "sg:province": "OH",
    "sg:tags": [
      "american",
      "pizza"
    ],
    "wof:name": "Pizza Hut",
    "wof:placetype": "venue"
  },
  "geometry": {"coordinates":[-83.070241,39.881427],"type":"Point"}
}
