{
  "type": "Feature",
  "properties": {
    "iso:country":"US",
    "sg:address":"1440 Yankee Park Pl",
    "sg:city":"Dayton",
    "sg:classifiers":[
        {
            "category":"Wholesale",
            "subcategory":"Computers",
            "type":"Manufacturing & Wholesale Goods"
        }
    ],
    "sg:phone":"+1 937 432 6085",
    "sg:postcode":"45458",
    "sg:province":"OH",
    "wof:name":"Compsee",
    "wof:placetype":"venue"
},
  "geometry": {"coordinates":[-84.199148,39.624955],"type":"Point"}
}