{
  "type": "Feature",
  "properties": {
    "addr:full": "2385 State Rte 364 Minster OH 45865",
    "addr:housenumber": "2385",
    "addr:postcode": "45865",
    "addr:street": "State Rte 364",
    "iso:country": "US",
    "sg:address": "2385 State Rte 364",
    "sg:city": "Minster",
    "sg:classifiers": [
      {
        "category": "Farming",
        "subcategory": "Farm",
        "type": "Manufacturing \u0026 Wholesale Goods"
      }
    ],
    "sg:phone": "+1 419 628 2036",
    "sg:postcode": "45865",
    "sg:province": "OH",
    "sg:tags": [
      "far",
      "corn",
      "crop",
      "general",
      "field",
      "soybean"
    ],
    "wof:name": "Heitbrink Farm Drainage",
    "wof:placetype": "venue"
  },
  "geometry": {"coordinates":[-84.434073,40.383913],"type":"Point"}
}
