{
  "type": "Feature",
  "properties": {
    "iso:country":"US",
    "sg:address":"2385 State Rte 364",
    "sg:city":"Minster",
    "sg:classifiers":[
        {
            "category":"Farming",
            "subcategory":"Farm",
            "type":"Manufacturing & Wholesale Goods"
        }
    ],
    "sg:phone":"+1 419 628 2036",
    "sg:postcode":"45865",
    "sg:province":"OH",
    "sg:tags":[
        "far",
        "corn",
        "crop",
        "general",
        "field",
        "soybean"
    ],
    "wof:name":"Heitbrink Farm Drainage",
    "wof:placetype":"venue"
},
  "geometry": {"coordinates":[-84.434073,40.383913],"type":"Point"}
}