{
  "type": "Feature",
  "properties": {
    "iso:country":"US",
    "sg:address":"105 Springhill Rd",
    "sg:city":"Granville",
    "sg:classifiers":[
        {
            "category":"Building & Trades",
            "subcategory":"Construction",
            "type":"Services"
        }
    ],
    "sg:phone":"+1 740 587 2265",
    "sg:postcode":"43023",
    "sg:province":"OH",
    "sg:tags":[
        "contractor"
    ],
    "wof:name":"Dick Wills Construction Inc",
    "wof:placetype":"venue"
},
  "geometry": {"coordinates":[-82.508546,40.055069],"type":"Point"}
}