{
  "type": "Feature",
  "properties": {
    "iso:country":"US",
    "sg:address":"7794 5 Mile Rd",
    "sg:city":"Cincinnati",
    "sg:classifiers":[
        {
            "category":"Health Services",
            "subcategory":"Doctor",
            "type":"Services"
        }
    ],
    "sg:phone":"+1 513 232 0500",
    "sg:postcode":"45230",
    "sg:province":"OH",
    "wof:name":"Wilson David G MD",
    "wof:placetype":"venue"
},
  "geometry": {"coordinates":[-84.35169399999999,39.077309],"type":"Point"}
}