{
  "type": "Feature",
  "properties": {
    "addr:full": "7794 5 Mile Rd Cincinnati OH 45230",
    "addr:housenumber": "7794",
    "addr:postcode": "45230",
    "addr:street": "5 Mile Rd",
    "iso:country": "US",
    "sg:address": "7794 5 Mile Rd",
    "sg:city": "Cincinnati",
    "sg:classifiers": [
      {
        "category": "Health Services",
        "subcategory": "Doctor",
        "type": "Services"
      }
    ],
    "sg:phone": "+1 513 232 0500",
    "sg:postcode": "45230",
    "sg:province": "OH",
    "wof:name": "Wilson David G MD",
    "wof:placetype": "venue"
  },
  "geometry": {"coordinates":[-84.351694,39.077309],"type":"Point"}
}
