{
  "type": "Feature",
  "properties": {
    "addr:full": "787 White Pond Dr Akron OH 44320",
    "addr:housenumber": "787",
    "addr:postcode": "44320",
    "addr:street": "White Pond Dr",
    "iso:country": "US",
    "sg:address": "787 White Pond Dr",
    "sg:city": "Akron",
    "sg:classifiers": [
      {
        "category": "Insurance",
        "subcategory": "Insurance Agent",
        "type": "Services"
      }
    ],
    "sg:phone": "+1 330 869 6452",
    "sg:postcode": "44320",
    "sg:province": "OH",
    "wof:name": "Auto-Owners Insurance Co",
    "wof:placetype": "venue"
  },
  "geometry": {"coordinates":[-81.589114,41.095683],"type":"Point"}
}
