{
  "type": "Feature",
  "properties": {
    "iso:country":"US",
    "sg:address":"2923 Atoll Dr",
    "sg:city":"Lewis Center",
    "sg:classifiers":[
        {
            "category":"Real Estate",
            "subcategory":"Real Estate Operator",
            "type":"Services"
        }
    ],
    "sg:phone":"+1 740 548 7396",
    "sg:postcode":"43035",
    "sg:province":"OH",
    "sg:tags":[
        "building",
        "nonresidential"
    ],
    "wof:name":"Bricole Properties Ltd",
    "wof:placetype":"venue"
},
  "geometry": {"coordinates":[-82.98350000000001,40.189386],"type":"Point"}
}