{
  "type": "Feature",
  "properties": {
    "addr:full": "2923 Atoll Dr Lewis Center OH 43035",
    "addr:housenumber": "2923",
    "addr:postcode": "43035",
    "addr:street": "Atoll Dr",
    "iso:country": "US",
    "sg:address": "2923 Atoll Dr",
    "sg:city": "Lewis Center",
    "sg:classifiers": [
      {
        "category": "Real Estate",
        "subcategory": "Real Estate Operator",
        "type": "Services"
      }
    ],
    "sg:phone": "+1 740 548 7396",
    "sg:postcode": "43035",
    "sg:province": "OH",
    "sg:tags": [
      "building",
      "nonresidential"
    ],
    "wof:name": "Bricole Properties Ltd",
    "wof:placetype": "venue"
  },
  "geometry": {"coordinates":[-82.9835,40.189386],"type":"Point"}
}
