{
  "type": "Feature",
  "properties": {
    "addr:full": "209 W Poe Rd Bowling Green OH 43402",
    "addr:housenumber": "209",
    "addr:postcode": "43402",
    "addr:street": "W Poe Rd",
    "iso:country": "US",
    "sg:address": "209 W Poe Rd",
    "sg:city": "Bowling Green",
    "sg:classifiers": [
      {
        "category": "Insurance",
        "subcategory": "Insurance Agent",
        "type": "Services"
      }
    ],
    "sg:phone": "+1 419 353 8611",
    "sg:postcode": "43402",
    "sg:province": "OH",
    "wof:name": "Auto Owners Insurance",
    "wof:placetype": "venue"
  },
  "geometry": {"coordinates":[-83.651204,41.385739],"type":"Point"}
}
