{
  "type": "Feature",
  "properties": {
    "iso:country":"US",
    "sg:address":"5126 N Summit St",
    "sg:city":"Toledo",
    "sg:classifiers":[
        {
            "category":"Retail",
            "subcategory":"Repair Shop",
            "type":"Services"
        },
        {
            "category":"Autos & Motor Vehicles",
            "subcategory":"Recreational Vehicle Sales",
            "type":"Retail Goods"
        }
    ],
    "sg:phone":"+1 419 726 9999",
    "sg:postcode":"43611",
    "sg:province":"OH",
    "sg:tags":[
        "scooter",
        "motorcycle"
    ],
    "wof:name":"Excel Jet Sports LLC",
    "wof:placetype":"venue"
},
  "geometry": {"coordinates":[-83.47905,41.715091],"type":"Point"}
}