{
  "type": "Feature",
  "properties": {
    "addr:full": "821 Hope St Lima OH 45804",
    "addr:housenumber": "821",
    "addr:postcode": "45804",
    "addr:street": "Hope St",
    "iso:country": "US",
    "sg:address": "821 Hope St",
    "sg:city": "Lima",
    "sg:classifiers": [
      {
        "category": "Personal",
        "subcategory": "Beauty Salon",
        "type": "Services"
      }
    ],
    "sg:phone": "+1 419 229 8394",
    "sg:postcode": "45804",
    "sg:province": "OH",
    "wof:name": "Emma's Beauty Shop",
    "wof:placetype": "venue"
  },
  "geometry": {"coordinates":[-84.092786,40.717873],"type":"Point"}
}
