{
  "type": "Feature",
  "properties": {
    "addr:full": "100 E Campus View Blvd Columbus OH 43235",
    "addr:housenumber": "100",
    "addr:postcode": "43235",
    "addr:street": "E Campus View Blvd",
    "iso:country": "US",
    "sg:address": "100 E Campus View Blvd",
    "sg:city": "Columbus",
    "sg:classifiers": [
      {
        "category": "Shopping",
        "subcategory": "Computers \u0026 Home Electronics",
        "type": "Retail Goods"
      }
    ],
    "sg:phone": "+1 614 841 9877",
    "sg:postcode": "43235",
    "sg:province": "OH",
    "sg:tags": [
      "software"
    ],
    "sg:website": "www.hublink.com",
    "wof:name": "Hublink",
    "wof:placetype": "venue"
  },
  "geometry": {"coordinates":[-83.013464,40.118349],"type":"Point"}
}
