{
  "type": "Feature",
  "properties": {
    "addr:full":"5781 Corduroy Rd Oregon OH 43616",
    "addr:housenumber":"5781",
    "addr:postcode":"43616",
    "addr:street":"Corduroy Rd",
    "iso:country":"US",
    "sg:address":"5781 Corduroy Rd",
    "sg:city":"Oregon",
    "sg:classifiers":[
        {
            "category":"Restaurant",
            "type":"Food & Drink"
        }
    ],
    "sg:phone":"+1 419 693 0451",
    "sg:postcode":"43616",
    "sg:province":"OH",
    "sg:tags":[
        "eating"
    ],
    "wof:name":"Millers Carry Out",
    "wof:placetype":"venue"
},
  "geometry": {"coordinates":[-83.42758000000001,41.65969],"type":"Point"}
}