{
  "type": "Feature",
  "properties": {
    "iso:country":"US",
    "sg:address":"4280 Co Rd 15",
    "sg:city":"Alger",
    "sg:phone":"+1 419 648 8125",
    "sg:postcode":"45812",
    "sg:province":"OH",
    "sg:tags":[
        "farm",
        "corn",
        "soybean"
    ],
    "wof:name":"Brad Richardson",
    "wof:placetype":"venue"
},
  "geometry": {"coordinates":[-83.880124,40.681148],"type":"Point"}
}