{
  "type": "Feature",
  "properties": {
    "addr:full": "4280 Co Rd 15 Alger OH 45812",
    "addr:housenumber": "4280",
    "addr:postcode": "45812",
    "addr:street": "Co Rd 15",
    "iso:country": "US",
    "sg:address": "4280 Co Rd 15",
    "sg:city": "Alger",
    "sg:phone": "+1 419 648 8125",
    "sg:postcode": "45812",
    "sg:province": "OH",
    "sg:tags": [
      "farm",
      "corn",
      "soybean"
    ],
    "wof:name": "Brad Richardson",
    "wof:placetype": "venue"
  },
  "geometry": {"coordinates":[-83.880124,40.681148],"type":"Point"}
}
