{
  "type": "Feature",
  "properties": {
    "addr:full": "139 W 8th St Cambridge OH 43725",
    "addr:housenumber": "139",
    "addr:postcode": "43725",
    "addr:street": "W 8Th St",
    "iso:country": "US",
    "sg:address": "139 W 8th St",
    "sg:city": "Cambridge",
    "sg:classifiers": [
      {
        "category": "Professional",
        "subcategory": "Lawyer \u0026 Legal Services",
        "type": "Services"
      }
    ],
    "sg:phone": "+1 740 432 6322",
    "sg:postcode": "43725",
    "sg:province": "OH",
    "sg:tags": [
      "attorney"
    ],
    "wof:name": "Tribbie Scott Plummer \u0026 Padden",
    "wof:placetype": "venue"
  },
  "geometry": {"coordinates":[-81.590361,40.024851],"type":"Point"}
}
