{
  "type": "Feature",
  "properties": {
    "addr:full": "16406 Co Rd R Napoleon OH 43545",
    "addr:housenumber": "16406",
    "addr:postcode": "43545",
    "addr:street": "Co Rd R Napoleon",
    "iso:country": "US",
    "sg:address": "16406 Co Rd R",
    "sg:city": "Napoleon",
    "sg:classifiers": [
      {
        "category": "Building \u0026 Trades",
        "subcategory": "Construction",
        "type": "Services"
      }
    ],
    "sg:phone": "+1 419 758 3561",
    "sg:postcode": "43545",
    "sg:province": "OH",
    "sg:tags": [
      "excavation",
      "contractor"
    ],
    "wof:name": "Burdette H Rathge \u0026 Sons Inc",
    "wof:placetype": "venue"
  },
  "geometry": {"coordinates":[-84.177267,41.413745],"type":"Point"}
}
