{
  "type": "Feature",
  "properties": {
    "addr:full":"1616 Ridge Rd Hinckley OH 44233",
    "addr:housenumber":"1616",
    "addr:postcode":"44233",
    "addr:street":"Ridge Rd",
    "iso:country":"US",
    "sg:address":"1616 Ridge Rd",
    "sg:city":"Hinckley",
    "sg:classifiers":[
        {
            "category":"Government",
            "subcategory":"Office",
            "type":"Public Place"
        }
    ],
    "sg:phone":"+1 330 225 2276",
    "sg:postcode":"44233",
    "sg:province":"OH",
    "sg:tags":[
        "village"
    ],
    "wof:name":"Hinckley Twp Svc Garage",
    "wof:placetype":"venue"
},
  "geometry": {"coordinates":[-81.745087,41.232216],"type":"Point"}
}