{
  "type": "Feature",
  "properties": {
    "iso:country":"US",
    "sg:address":"49350 W Main St",
    "sg:city":"Harrisville",
    "sg:classifiers":[
        {
            "category":"Government",
            "subcategory":"Office",
            "type":"Public Place"
        }
    ],
    "sg:phone":"+1 740 546 4100",
    "sg:postcode":"43907",
    "sg:province":"OH",
    "sg:tags":[
        "village"
    ],
    "wof:name":"Harrisville Village Council",
    "wof:placetype":"venue"
},
  "geometry": {"coordinates":[-80.889655,40.181649],"type":"Point"}
}