{
  "type": "Feature",
  "properties": {
    "addr:full":"374 Boardman Poland Rd Youngstown OH 44514",
    "addr:housenumber":"374",
    "addr:postcode":"44514",
    "addr:street":"Boardman Poland Rd",
    "iso:country":"US",
    "sg:address":"374 Boardman Poland Rd",
    "sg:city":"Youngstown",
    "sg:classifiers":[
        {
            "category":"Insurance",
            "subcategory":"Insurance Agent",
            "type":"Services"
        }
    ],
    "sg:phone":"+1 330 758 7133",
    "sg:postcode":"44514",
    "sg:province":"OH",
    "wof:name":"John A Reese Agency",
    "wof:placetype":"venue"
},
  "geometry": {"coordinates":[-80.64442099999999,41.024376],"type":"Point"}
}