{
  "type": "Feature",
  "properties": {
    "iso:country":"US",
    "sg:address":"405 E Main St",
    "sg:city":"Canfield",
    "sg:classifiers":[
        {
            "category":"Shopping",
            "subcategory":"Discount & Variety Stores",
            "type":"Retail Goods"
        }
    ],
    "sg:phone":"+1 330 533 3054",
    "sg:postcode":"44406",
    "sg:province":"OH",
    "wof:name":"Dollar Tree",
    "wof:placetype":"venue"
},
  "geometry": {"coordinates":[-80.745721,41.024659],"type":"Point"}
}