{
  "type": "Feature",
  "properties": {
    "addr:full": "8999 Bay Dr NE Mineral City OH 44656",
    "addr:housenumber": "8999",
    "addr:postcode": "44656",
    "addr:street": "Bay Dr Ne",
    "iso:country": "US",
    "sg:address": "8999 Bay Dr NE",
    "sg:city": "Mineral City",
    "sg:classifiers": [
      {
        "category": "Real Estate",
        "subcategory": "Real Estate Operator",
        "type": "Services"
      }
    ],
    "sg:phone": "+1 330 343 8910",
    "sg:postcode": "44656",
    "sg:province": "OH",
    "sg:tags": [
      "building",
      "equipment",
      "rental",
      "nonresidential"
    ],
    "wof:name": "M \u0026 L Leasing Co",
    "wof:placetype": "venue"
  },
  "geometry": {"coordinates":[-81.279389,40.533829],"type":"Point"}
}
