{
  "type": "Feature",
  "properties": {
    "iso:country":"US",
    "sg:address":"8999 Bay Dr NE",
    "sg:city":"Mineral City",
    "sg:classifiers":[
        {
            "category":"Real Estate",
            "subcategory":"Real Estate Operator",
            "type":"Services"
        }
    ],
    "sg:phone":"+1 330 343 8910",
    "sg:postcode":"44656",
    "sg:province":"OH",
    "sg:tags":[
        "building",
        "equipment",
        "rental",
        "nonresidential"
    ],
    "wof:name":"M & L Leasing Co",
    "wof:placetype":"venue"
},
  "geometry": {"coordinates":[-81.27938899999999,40.533829],"type":"Point"}
}