{
  "type": "Feature",
  "properties": {
    "addr:full": "1620 Owen Rd Northwood OH 43619",
    "addr:housenumber": "1620",
    "addr:postcode": "43619",
    "addr:street": "Owen Rd",
    "iso:country": "US",
    "sg:address": "1620 Owen Rd",
    "sg:city": "Northwood",
    "sg:classifiers": [
      {
        "category": "Building \u0026 Trades",
        "subcategory": "Construction",
        "type": "Services"
      }
    ],
    "sg:phone": "+1 419 697 6185",
    "sg:postcode": "43619",
    "sg:province": "OH",
    "sg:tags": [
      "nonresidential"
    ],
    "wof:name": "K and J Enterprise",
    "wof:placetype": "venue"
  },
  "geometry": {"coordinates":[-83.459374,41.59075],"type":"Point"}
}
