{
  "type": "Feature",
  "properties": {
    "addr:full":"21755 Twp Rd 164 Coshocton OH 43812",
    "addr:postcode":"21755;43812",
    "addr:street":"Twp Rd 164",
    "iso:country":"US",
    "sg:address":"21755 Twp Rd 164",
    "sg:city":"Coshocton",
    "sg:classifiers":[
        {
            "category":"Government",
            "subcategory":"Office",
            "type":"Public Place"
        }
    ],
    "sg:phone":"+1 740 622 9741",
    "sg:postcode":"43812",
    "sg:province":"OH",
    "wof:name":"Coshocton Cnty Animal Shelter",
    "wof:placetype":"venue"
},
  "geometry": {"coordinates":[-81.81539100000001,40.250284],"type":"Point"}
}