{
  "type": "Feature",
  "properties": {
    "addr:full":"21371 Naumann Ave Euclid OH 44123",
    "addr:postcode":"21371;44123",
    "addr:street":"Naumann Ave",
    "iso:country":"US",
    "sg:address":"21371 Naumann Ave",
    "sg:city":"Euclid",
    "sg:classifiers":[
        {
            "category":"Building & Trades",
            "subcategory":"Landscaping Services",
            "type":"Services"
        }
    ],
    "sg:phone":"+1 216 383 8359",
    "sg:postcode":"44123",
    "sg:province":"OH",
    "sg:tags":[
        "landscape"
    ],
    "wof:name":"Jozef Udovic Inc",
    "wof:placetype":"venue"
},
  "geometry": {"coordinates":[-81.53073000000001,41.592764],"type":"Point"}
}