{
  "type": "Feature",
  "properties": {
    "addr:full": "147 Farragut Rd Cincinnati OH 45218",
    "addr:housenumber": "147",
    "addr:postcode": "45218",
    "addr:street": "Farragut Rd",
    "iso:country": "US",
    "sg:address": "147 Farragut Rd",
    "sg:city": "Cincinnati",
    "sg:classifiers": [
      {
        "category": "Education",
        "subcategory": "School",
        "type": "Public Place"
      }
    ],
    "sg:phone": "+1 513 825 7140",
    "sg:postcode": "45218",
    "sg:province": "OH",
    "wof:name": "Winton Woods Middle School",
    "wof:placetype": "venue"
  },
  "geometry": {"coordinates":[-84.518948,39.266183],"type":"Point"}
}
