{
  "type": "Feature",
  "properties": {
    "addr:full": "8749 Co Rd 46 Galion OH 44833",
    "addr:housenumber": "8749;46",
    "addr:postcode": "44833",
    "addr:street": "Co Rd",
    "iso:country": "US",
    "sg:address": "8749 Co Rd 46",
    "sg:city": "Galion",
    "sg:classifiers": [
      {
        "category": "Retail",
        "subcategory": "Car Wash",
        "type": "Services"
      }
    ],
    "sg:phone": "+1 419 462 1519",
    "sg:postcode": "44833",
    "sg:province": "OH",
    "sg:tags": [
      "automobile",
      "detail",
      "clean"
    ],
    "wof:name": "Keenan Total Touch-Up",
    "wof:placetype": "venue"
  },
  "geometry": {"coordinates":[-82.746574,40.668182],"type":"Point"}
}
