{
  "type": "Feature",
  "properties": {
    "addr:full":"1796 S Winfield Dr Tiffin OH 44883",
    "addr:housenumber":"1796",
    "addr:postcode":"44883",
    "addr:street":"S Winfield Dr",
    "iso:country":"US",
    "sg:address":"1796 S Winfield Dr",
    "sg:city":"Tiffin",
    "sg:classifiers":[
        {
            "category":"Banks & Credit Unions",
            "subcategory":"Financial Services",
            "type":"Services"
        }
    ],
    "sg:phone":"+1 419 447 7835",
    "sg:postcode":"44883",
    "sg:province":"OH",
    "sg:tags":[
        "trust",
        "management"
    ],
    "wof:name":"Stoneham Family Trust",
    "wof:placetype":"venue"
},
  "geometry": {"coordinates":[-83.159694,41.097966],"type":"Point"}
}