{
  "type": "Feature",
  "properties": {
    "iso:country":"US",
    "sg:address":"149 Oakview Ave",
    "sg:city":"Struthers",
    "sg:classifiers":[
        {
            "category":"Building & Trades",
            "subcategory":"Landscaping Services",
            "type":"Services"
        }
    ],
    "sg:phone":"+1 330 750 6193",
    "sg:postcode":"44471",
    "sg:province":"OH",
    "sg:tags":[
        "lawn",
        "snow",
        "removal",
        "maintenance",
        "contractor",
        "landscape"
    ],
    "wof:name":"Wolfe's Landscaping",
    "wof:placetype":"venue"
},
  "geometry": {"coordinates":[-80.57487,41.060646],"type":"Point"}
}