{
  "type": "Feature",
  "properties": {
    "iso:country":"US",
    "sg:address":"120 Cricket Ln",
    "sg:city":"Cortland",
    "sg:classifiers":[
        {
            "category":"Arts & Performance",
            "subcategory":"Theater",
            "type":"Entertainment"
        }
    ],
    "sg:phone":"+1 330 847 9113",
    "sg:postcode":"44410",
    "sg:province":"OH",
    "sg:tags":[
        "talent",
        "agency",
        "casting"
    ],
    "wof:name":"S&K Talent Agents Inc",
    "wof:placetype":"venue"
},
  "geometry": {"coordinates":[-80.715917,41.325279],"type":"Point"}
}