{
  "type": "Feature",
  "properties": {
    "addr:full":"445 W Milltown Rd Wooster OH 44691",
    "addr:housenumber":"445",
    "addr:postcode":"44691",
    "addr:street":"W Milltown Rd",
    "iso:country":"US",
    "sg:address":"445 W Milltown Rd",
    "sg:city":"Wooster",
    "sg:classifiers":[
        {
            "category":"Banks & Credit Unions",
            "subcategory":"Bank",
            "type":"Services"
        }
    ],
    "sg:phone":"+1 330 263 9170",
    "sg:postcode":"44691",
    "sg:province":"OH",
    "sg:tags":[
        "state"
    ],
    "sg:website":"www.skyfi.com",
    "wof:name":"Sky Bank",
    "wof:placetype":"venue"
},
  "geometry": {"coordinates":[-81.94508399999999,40.843366],"type":"Point"}
}