{
  "type": "Feature",
  "properties": {
    "addr:full": "122 Karl Brown Way Loveland OH 45140",
    "addr:housenumber": "122",
    "addr:postcode": "45140",
    "addr:street": "Karl Brown Way",
    "iso:country": "US",
    "sg:address": "122 Karl Brown Way",
    "sg:city": "Loveland",
    "sg:classifiers": [
      {
        "category": "Building \u0026 Trades",
        "subcategory": "Plumbing",
        "type": "Services"
      }
    ],
    "sg:phone": "+1 513 683 3714",
    "sg:postcode": "45140",
    "sg:province": "OH",
    "sg:tags": [
      "conditioning",
      "air",
      "system",
      "contractor"
    ],
    "wof:name": "Rick Ogden Heating \u0026 Cooling",
    "wof:placetype": "venue"
  },
  "geometry": {"coordinates":[-84.259434,39.267862],"type":"Point"}
}
