{
  "type": "Feature",
  "properties": {
    "addr:full": "350 Shadywood Dr Dayton OH 45415",
    "addr:housenumber": "350",
    "addr:postcode": "45415",
    "addr:street": "Shadywood Dr",
    "iso:country": "US",
    "sg:address": "350 Shadywood Dr",
    "sg:city": "Dayton",
    "sg:classifiers": [
      {
        "category": "Manufacturing",
        "subcategory": "Food",
        "type": "Manufacturing \u0026 Wholesale Goods"
      }
    ],
    "sg:phone": "+1 937 832 0460",
    "sg:postcode": "45415",
    "sg:province": "OH",
    "sg:tags": [
      "product",
      "mfg"
    ],
    "wof:name": "Sweet Affaires Chocolates",
    "wof:placetype": "venue"
  },
  "geometry": {"coordinates":[-84.282815,39.851157],"type":"Point"}
}
