{
  "type": "Feature",
  "properties": {
    "iso:country":"US",
    "sg:address":"1211 Cardinal Dr",
    "sg:city":"Bryan",
    "sg:classifiers":[
        {
            "category":"Social Services",
            "subcategory":"Adult Care",
            "type":"Services"
        }
    ],
    "sg:phone":"+1 419 636 2369",
    "sg:postcode":"43506",
    "sg:province":"OH",
    "sg:tags":[
        "residential",
        "facility"
    ],
    "wof:name":"Filling Memorial Home of Mercy",
    "wof:placetype":"venue"
},
  "geometry": {"coordinates":[-84.56649899999999,41.460336],"type":"Point"}
}