{
  "type": "Feature",
  "properties": {
    "addr:full":"3359 W 58th St Cleveland OH 44102",
    "addr:housenumber":"3359",
    "addr:postcode":"44102",
    "addr:street":"W 58Th St",
    "iso:country":"US",
    "sg:address":"3359 W 58th St",
    "sg:city":"Cleveland",
    "sg:classifiers":[
        {
            "category":"Personal",
            "type":"Services"
        }
    ],
    "sg:phone":"+1 216 651 4673",
    "sg:postcode":"44102",
    "sg:province":"OH",
    "sg:tags":[
        "church",
        "chapel",
        "place",
        "worship",
        "wedding"
    ],
    "sg:website":"http://www.churchofreason.org",
    "wof:name":"Church Of Reason",
    "wof:placetype":"venue"
},
  "geometry": {"coordinates":[-81.725937,41.462848],"type":"Point"}
}