{
  "type": "Feature",
  "properties": {
    "addr:full": "4374 Karl Rd Columbus OH 43224",
    "addr:housenumber": "4374",
    "addr:postcode": "43224",
    "addr:street": "Karl Rd",
    "iso:country": "US",
    "sg:address": "4374 Karl Rd",
    "sg:city": "Columbus",
    "sg:classifiers": [
      {
        "category": "Shopping",
        "subcategory": "Beauty \u0026 Cosmetics",
        "type": "Retail Goods"
      }
    ],
    "sg:phone": "+1 614 261 8040",
    "sg:postcode": "43224",
    "sg:province": "OH",
    "sg:tags": [
      "merchandise"
    ],
    "wof:name": "Jyekye",
    "wof:placetype": "venue"
  },
  "geometry": {"coordinates":[-82.976239,40.05552],"type":"Point"}
}
