{
  "type": "Feature",
  "properties": {
    "addr:full":"1610 S Water St Kent OH 44240",
    "addr:housenumber":"1610",
    "addr:postcode":"44240",
    "addr:street":"S Water St",
    "iso:country":"US",
    "sg:address":"1610 S Water St",
    "sg:city":"Kent",
    "sg:classifiers":[
        {
            "category":"Retail",
            "subcategory":"Auto Repair",
            "type":"Services"
        }
    ],
    "sg:phone":"+1 330 677 9455",
    "sg:postcode":"44240",
    "sg:province":"OH",
    "sg:tags":[
        "automotive"
    ],
    "wof:name":"Meineke Discount Mufflers",
    "wof:placetype":"venue"
},
  "geometry": {"coordinates":[-81.354214,41.134628],"type":"Point"}
}