{
  "type": "Feature",
  "properties": {
    "addr:full": "6652 Providence St Whitehouse OH 43571",
    "addr:housenumber": "6652",
    "addr:postcode": "43571",
    "addr:street": "Providence St",
    "iso:country": "US",
    "sg:address": "6652 Providence St",
    "sg:city": "Whitehouse",
    "sg:classifiers": [
      {
        "category": "Restaurant",
        "type": "Food \u0026 Drink"
      }
    ],
    "sg:phone": "+1 419 877 0646",
    "sg:postcode": "43571",
    "sg:province": "OH",
    "sg:tags": [
      "pizza"
    ],
    "wof:name": "Whitehouse Party Store",
    "wof:placetype": "venue"
  },
  "geometry": {"coordinates":[-83.804277,41.519998],"type":"Point"}
}
