{
  "type": "Feature",
  "properties": {
    "addr:full":"2188 Murray Hill Rd Cleveland OH 44106",
    "addr:housenumber":"2188",
    "addr:postcode":"44106",
    "addr:street":"Murray Hill Rd",
    "iso:country":"US",
    "sg:address":"2188 Murray Hill Rd",
    "sg:city":"Cleveland",
    "sg:classifiers":[
        {
            "category":"Shopping",
            "type":"Retail Goods"
        }
    ],
    "sg:phone":"+1 216 231 2012",
    "sg:postcode":"44106",
    "sg:province":"OH",
    "sg:tags":[
        "art",
        "gallery",
        "merchandise",
        "dealer"
    ],
    "wof:name":"Murray Hill Arts & Crafts",
    "wof:placetype":"venue"
},
  "geometry": {"coordinates":[-81.60195899999999,41.502766],"type":"Point"}
}