{
  "type": "Feature",
  "properties": {
    "iso:country":"US",
    "sg:address":"2247 Waycross Rd",
    "sg:city":"Cincinnati",
    "sg:classifiers":[
        {
            "category":"Social Services",
            "subcategory":"Child Care",
            "type":"Services"
        }
    ],
    "sg:phone":"+1 513 742 0735",
    "sg:postcode":"45240",
    "sg:province":"OH",
    "wof:name":"Kids Kingdom",
    "wof:placetype":"venue"
},
  "geometry": {"coordinates":[-84.56232,39.280054],"type":"Point"}
}