{
  "type": "Feature",
  "properties": {
    "addr:full":"642 E State St Alliance OH 44601",
    "addr:housenumber":"642",
    "addr:postcode":"44601",
    "addr:street":"E State St",
    "iso:country":"US",
    "sg:address":"642 E State St",
    "sg:city":"Alliance",
    "sg:classifiers":[
        {
            "category":"Autos & Motor Vehicles",
            "subcategory":"Fuel & Gas Station",
            "type":"Retail Goods"
        }
    ],
    "sg:phone":"+1 330 821 4212",
    "sg:postcode":"44601",
    "sg:province":"OH",
    "sg:tags":[
        "oil"
    ],
    "wof:name":"Super America",
    "wof:placetype":"venue"
},
  "geometry": {"coordinates":[-81.096582,40.901734],"type":"Point"}
}