{
  "type": "Feature",
  "properties": {
    "iso:country":"US",
    "sg:address":"499 Kimber Rd",
    "sg:city":"Wooster",
    "sg:classifiers":[
        {
            "category":"Personal",
            "type":"Services"
        }
    ],
    "sg:phone":"+1 330 264 7757",
    "sg:postcode":"44691",
    "sg:province":"OH",
    "sg:tags":[
        "therapist",
        "massage"
    ],
    "wof:name":"Janet Plymire Massotherapist",
    "wof:placetype":"venue"
},
  "geometry": {"coordinates":[-81.952112,40.719138],"type":"Point"}
}