{
  "type": "Feature",
  "properties": {
    "iso:country":"US",
    "sg:address":"416 Erie St N",
    "sg:city":"Massillon",
    "sg:classifiers":[
        {
            "category":"Food & Beverages",
            "subcategory":"Specialty",
            "type":"Retail Goods"
        }
    ],
    "sg:phone":"+1 330 833 0706",
    "sg:postcode":"44646",
    "sg:province":"OH",
    "sg:tags":[
        "water",
        "bulk",
        "company"
    ],
    "wof:name":"Nick Williams Water Store",
    "wof:placetype":"venue"
},
  "geometry": {"coordinates":[-81.524879,40.80065],"type":"Point"}
}