{
  "type": "Feature",
  "properties": {
    "iso:country":"US",
    "sg:address":"1003 E Kibby St",
    "sg:city":"Lima",
    "sg:classifiers":[
        {
            "category":"Organizations",
            "subcategory":"Religious Organization",
            "type":"Services"
        }
    ],
    "sg:phone":"+1 419 222 7001",
    "sg:postcode":"45804",
    "sg:province":"OH",
    "wof:name":"Livingword Fellowship",
    "wof:placetype":"venue"
},
  "geometry": {"coordinates":[-84.089929,40.73057],"type":"Point"}
}