{
  "type": "Feature",
  "properties": {
    "iso:country":"US",
    "sg:address":"15 S Main St",
    "sg:city":"Mechanicsburg",
    "sg:classifiers":[
        {
            "category":"Insurance",
            "subcategory":"Insurance Agent",
            "type":"Services"
        }
    ],
    "sg:phone":"+1 937 834 3402",
    "sg:postcode":"43044",
    "sg:province":"OH",
    "wof:name":"KYTE Insurance Inc",
    "wof:placetype":"venue"
},
  "geometry": {"coordinates":[-83.555269,40.07134],"type":"Point"}
}