{
  "type": "Feature",
  "properties": {
    "addr:full": "2606 Sonnington Dr Dublin OH 43016",
    "addr:housenumber": "2606",
    "addr:postcode": "43016",
    "addr:street": "Sonnington Dr",
    "iso:country": "US",
    "sg:address": "2606 Sonnington Dr",
    "sg:city": "Dublin",
    "sg:classifiers": [
      {
        "category": "Recreation",
        "type": "Entertainment"
      }
    ],
    "sg:phone": "+1 614 292 1489",
    "sg:postcode": "43016",
    "sg:province": "OH",
    "sg:tags": [
      "amusement"
    ],
    "wof:name": "Columbus Fencing Ctr",
    "wof:placetype": "venue"
  },
  "geometry": {"coordinates":[-83.085503,40.129537],"type":"Point"}
}
