{
  "type": "Feature",
  "properties": {
    "addr:full": "23215 Commerce Park Rd Cleveland OH 44122",
    "addr:housenumber": "23215",
    "addr:postcode": "44122",
    "addr:street": "Commerce Park Rd",
    "iso:country": "US",
    "sg:address": "23215 Commerce Park Rd",
    "sg:city": "Cleveland",
    "sg:classifiers": [
      {
        "category": "Building \u0026 Trades",
        "subcategory": "Construction",
        "type": "Services"
      }
    ],
    "sg:phone": "+1 216 595 1550",
    "sg:postcode": "44122",
    "sg:province": "OH",
    "wof:name": "Rigging International Rimco",
    "wof:placetype": "venue"
  },
  "geometry": {"coordinates":[-81.505198,41.46211],"type":"Point"}
}
