{
  "type": "Feature",
  "properties": {
    "addr:full": "1882 Highland Rd Twinsburg OH 44087",
    "addr:housenumber": "1882",
    "addr:postcode": "44087",
    "addr:street": "Highland Rd",
    "iso:country": "US",
    "sg:address": "1882 Highland Rd",
    "sg:city": "Twinsburg",
    "sg:classifiers": [
      {
        "category": "Building \u0026 Trades",
        "subcategory": "Electrical",
        "type": "Services"
      }
    ],
    "sg:phone": "+1 330 425 8125",
    "sg:postcode": "44087",
    "sg:province": "OH",
    "sg:tags": [
      "electrical",
      "electric",
      "contractor"
    ],
    "wof:name": "E F Lea Electric",
    "wof:placetype": "venue"
  },
  "geometry": {"coordinates":[-81.447247,41.297672],"type":"Point"}
}
