{
  "type": "Feature",
  "properties": {
    "addr:full": "877 E Franklin St Centerville OH 45459",
    "addr:housenumber": "877",
    "addr:postcode": "45459",
    "addr:street": "E Franklin St",
    "iso:country": "US",
    "sg:address": "877 E Franklin St",
    "sg:city": "Centerville",
    "sg:classifiers": [
      {
        "category": "Restaurant",
        "type": "Food \u0026 Drink"
      }
    ],
    "sg:phone": "+1 937 438 3093",
    "sg:postcode": "45459",
    "sg:province": "OH",
    "wof:name": "Soft Rock Cafe",
    "wof:placetype": "venue"
  },
  "geometry": {"coordinates":[-84.142167,39.62861],"type":"Point"}
}
