{
  "type": "Feature",
  "properties": {
    "iso:country":"US",
    "sg:address":"877 E Franklin St",
    "sg:city":"Centerville",
    "sg:classifiers":[
        {
            "category":"Restaurant",
            "type":"Food & Drink"
        }
    ],
    "sg:phone":"+1 937 438 3093",
    "sg:postcode":"45459",
    "sg:province":"OH",
    "wof:name":"Soft Rock Cafe",
    "wof:placetype":"venue"
},
  "geometry": {"coordinates":[-84.142167,39.62861],"type":"Point"}
}