{
  "type": "Feature",
  "properties": {
    "addr:full":"413 W Main St Lakeside Marblhd OH 43440",
    "addr:housenumber":"413",
    "addr:postcode":"43440",
    "addr:street":"W Main St",
    "iso:country":"US",
    "sg:address":"413 W Main St",
    "sg:city":"Lakeside Marblhd",
    "sg:classifiers":[
        {
            "category":"Shopping",
            "subcategory":"Jewelry",
            "type":"Retail Goods"
        }
    ],
    "sg:phone":"+1 419 798 9283",
    "sg:postcode":"43440",
    "sg:province":"OH",
    "sg:tags":[
        "jeweler"
    ],
    "wof:name":"Golden I Jeweler",
    "wof:placetype":"venue"
},
  "geometry": {"coordinates":[-82.73074200000001,41.540455],"type":"Point"}
}