{
  "type": "Feature",
  "properties": {
    "iso:country":"US",
    "sg:address":"237 State Rte 61 S",
    "sg:city":"Monroeville",
    "sg:classifiers":[
        {
            "category":"Freight",
            "type":"Transportation"
        }
    ],
    "sg:phone":"+1 419 744 2889",
    "sg:postcode":"44847",
    "sg:province":"OH",
    "sg:tags":[
        "trucking"
    ],
    "wof:name":"Zidar Farms",
    "wof:placetype":"venue"
},
  "geometry": {"coordinates":[-82.657718,41.134949],"type":"Point"}
}