{
  "type": "Feature",
  "properties": {
    "iso:country":"US",
    "sg:address":"5058 S Prospect St",
    "sg:city":"Ravenna",
    "sg:classifiers":[
        {
            "category":"Building & Trades",
            "subcategory":"Construction",
            "type":"Services"
        }
    ],
    "sg:phone":"+1 330 296 7877",
    "sg:postcode":"44266",
    "sg:province":"OH",
    "sg:tags":[
        "roofing",
        "contractor"
    ],
    "sg:website":"www.portageroofing.com",
    "wof:name":"Portage Roofing Inc",
    "wof:placetype":"venue"
},
  "geometry": {"coordinates":[-81.24195,41.126404],"type":"Point"}
}