{
  "type": "Feature",
  "properties": {
    "addr:full":"25651 Fort Meigs Rd Perrysburg OH 43551",
    "addr:housenumber":"25651",
    "addr:postcode":"43551",
    "addr:street":"Fort Meigs Rd",
    "iso:country":"US",
    "sg:address":"25651 Fort Meigs Rd",
    "sg:city":"Perrysburg",
    "sg:classifiers":[
        {
            "category":"Shopping",
            "subcategory":"Jewelry",
            "type":"Retail Goods"
        }
    ],
    "sg:phone":"+1 419 874 7242",
    "sg:postcode":"43551",
    "sg:province":"OH",
    "wof:name":"Natural Time Products",
    "wof:placetype":"venue"
},
  "geometry": {"coordinates":[-83.655592,41.523475],"type":"Point"}
}