{
  "type": "Feature",
  "properties": {
    "iso:country":"US",
    "sg:address":"2516 S Main St",
    "sg:city":"Findlay",
    "sg:classifiers":[
        {
            "category":"Building & Trades",
            "subcategory":"Plumbing",
            "type":"Services"
        }
    ],
    "sg:phone":"+1 419 422 8822",
    "sg:postcode":"45840",
    "sg:province":"OH",
    "sg:tags":[
        "heating",
        "contractor"
    ],
    "wof:name":"Wilbur & Son Standard Water",
    "wof:placetype":"venue"
},
  "geometry": {"coordinates":[-83.650472,41.007687],"type":"Point"}
}