{
  "type": "Feature",
  "properties": {
    "addr:full": "2516 S Main St Findlay OH 45840",
    "addr:housenumber": "2516",
    "addr:postcode": "45840",
    "addr:street": "S Main St",
    "iso:country": "US",
    "sg:address": "2516 S Main St",
    "sg:city": "Findlay",
    "sg:classifiers": [
      {
        "category": "Building \u0026 Trades",
        "subcategory": "Plumbing",
        "type": "Services"
      }
    ],
    "sg:phone": "+1 419 422 8822",
    "sg:postcode": "45840",
    "sg:province": "OH",
    "sg:tags": [
      "heating",
      "contractor"
    ],
    "wof:name": "Wilbur \u0026 Son Standard Water",
    "wof:placetype": "venue"
  },
  "geometry": {"coordinates":[-83.650472,41.007687],"type":"Point"}
}
