{
  "type": "Feature",
  "properties": {
    "addr:full":"1565 S Hawkins Ave Akron OH 44320",
    "addr:housenumber":"1565",
    "addr:postcode":"44320",
    "addr:street":"S Hawkins Ave",
    "iso:country":"US",
    "sg:address":"1565 S Hawkins Ave",
    "sg:city":"Akron",
    "sg:classifiers":[
        {
            "category":"Shopping",
            "subcategory":"Discount & Variety Stores",
            "type":"Retail Goods"
        }
    ],
    "sg:phone":"+1 330 864 9100",
    "sg:postcode":"44320",
    "sg:province":"OH",
    "wof:name":"Strictly Dollar",
    "wof:placetype":"venue"
},
  "geometry": {"coordinates":[-81.569619,41.066408],"type":"Point"}
}