{
  "type": "Feature",
  "properties": {
    "addr:full": "2007 Central Ave Middletown OH 45044",
    "addr:housenumber": "2007",
    "addr:postcode": "45044",
    "addr:street": "Central Ave",
    "iso:country": "US",
    "sg:address": "2007 Central Ave",
    "sg:city": "Middletown",
    "sg:classifiers": [
      {
        "category": "Insurance",
        "subcategory": "Insurance Agent",
        "type": "Services"
      }
    ],
    "sg:phone": "+1 513 423 6553",
    "sg:postcode": "45044",
    "sg:province": "OH",
    "sg:tags": [
      "agency"
    ],
    "wof:name": "Dick Monroe Insurance Agency",
    "wof:placetype": "venue"
  },
  "geometry": {"coordinates":[-84.387892,39.512655],"type":"Point"}
}
