{
  "type": "Feature",
  "properties": {
    "addr:full": "509 Clinton St Findlay OH 45840",
    "addr:housenumber": "509",
    "addr:postcode": "45840",
    "addr:street": "Clinton St",
    "iso:country": "US",
    "sg:address": "509 Clinton St",
    "sg:city": "Findlay",
    "sg:classifiers": [
      {
        "category": "Building \u0026 Trades",
        "subcategory": "Construction",
        "type": "Services"
      }
    ],
    "sg:phone": "+1 419 425 4731",
    "sg:postcode": "45840",
    "sg:province": "OH",
    "sg:tags": [
      "house"
    ],
    "wof:name": "Walker Construction",
    "wof:placetype": "venue"
  },
  "geometry": {"coordinates":[-83.648227,41.047232],"type":"Point"}
}
