{
  "type": "Feature",
  "properties": {
    "iso:country":"US",
    "sg:address":"5290 N Co Rd 43",
    "sg:city":"Tiffin",
    "sg:classifiers":[
        {
            "category":"Insurance",
            "subcategory":"Insurance Agent",
            "type":"Services"
        }
    ],
    "sg:phone":"+1 419 639 2085",
    "sg:postcode":"44883",
    "sg:province":"OH",
    "wof:name":"Clouse Insurance",
    "wof:placetype":"venue"
},
  "geometry": {"coordinates":[-83.053606,41.191452],"type":"Point"}
}