{
  "type": "Feature",
  "properties": {
    "addr:full": "404 S Wayne St Van Wert OH 45891",
    "addr:housenumber": "404",
    "addr:postcode": "45891",
    "addr:street": "S Wayne St",
    "iso:country": "US",
    "sg:address": "404 S Wayne St",
    "sg:city": "Van Wert",
    "sg:classifiers": [
      {
        "category": "Shopping",
        "type": "Retail Goods"
      }
    ],
    "sg:phone": "+1 419 238 3438",
    "sg:postcode": "45891",
    "sg:province": "OH",
    "sg:tags": [
      "wedding",
      "supply"
    ],
    "wof:name": "Adventurous Affairs II",
    "wof:placetype": "venue"
  },
  "geometry": {"coordinates":[-84.56937,40.866344],"type":"Point"}
}
