{
  "type": "Feature",
  "properties": {
    "addr:full": "2551 Franksway St Columbus OH 43232",
    "addr:housenumber": "2551",
    "addr:postcode": "43232",
    "addr:street": "Franksway St",
    "iso:country": "US",
    "sg:address": "2551 Franksway St",
    "sg:city": "Columbus",
    "sg:classifiers": [
      {
        "category": "Personal",
        "subcategory": "Beauty Salon",
        "type": "Services"
      }
    ],
    "sg:phone": "+1 614 864 3000",
    "sg:postcode": "43232",
    "sg:province": "OH",
    "wof:name": "Expressions Hair \u0026 Nail Salon",
    "wof:placetype": "venue"
  },
  "geometry": {"coordinates":[-82.881482,39.92236],"type":"Point"}
}
