{
  "type": "Feature",
  "properties": {
    "iso:country":"US",
    "sg:address":"2551 Franksway St",
    "sg:city":"Columbus",
    "sg:classifiers":[
        {
            "category":"Personal",
            "subcategory":"Beauty Salon",
            "type":"Services"
        }
    ],
    "sg:phone":"+1 614 864 3000",
    "sg:postcode":"43232",
    "sg:province":"OH",
    "wof:name":"Expressions Hair & Nail Salon",
    "wof:placetype":"venue"
},
  "geometry": {"coordinates":[-82.88148200000001,39.92236],"type":"Point"}
}