{
  "type": "Feature",
  "properties": {
    "iso:country":"US",
    "sg:address":"2886 Stafford Dr",
    "sg:city":"Mansfield",
    "sg:classifiers":[
        {
            "category":"Organizations",
            "subcategory":"Membership Organization",
            "type":"Services"
        }
    ],
    "sg:phone":"+1 419 756 5850",
    "sg:postcode":"44904",
    "sg:province":"OH",
    "sg:tags":[
        "animal"
    ],
    "wof:name":"RES-Q-1 Inc",
    "wof:placetype":"venue"
},
  "geometry": {"coordinates":[-82.52094,40.678606],"type":"Point"}
}