{
  "type": "Feature",
  "properties": {
    "addr:full": "1300 E 2nd St Defiance OH 43512",
    "addr:housenumber": "1300",
    "addr:postcode": "43512",
    "addr:street": "E 2Nd St",
    "iso:country": "US",
    "sg:address": "1300 E 2nd St",
    "sg:city": "Defiance",
    "sg:classifiers": [
      {
        "category": "Social Services",
        "subcategory": "Job Training",
        "type": "Services"
      }
    ],
    "sg:phone": "+1 419 784 3777",
    "sg:postcode": "43512",
    "sg:province": "OH",
    "sg:tags": [
      "employment"
    ],
    "wof:name": "Northwest Oh Workforce Devmnt",
    "wof:placetype": "venue"
  },
  "geometry": {"coordinates":[-84.341751,41.282768],"type":"Point"}
}
