{
  "type": "Feature",
  "properties": {
    "addr:full":"1125 Sharlene Dr Youngstown OH 44511",
    "addr:housenumber":"1125",
    "addr:postcode":"44511",
    "addr:street":"Sharlene Dr",
    "iso:country":"US",
    "sg:address":"1125 Sharlene Dr",
    "sg:city":"Youngstown",
    "sg:classifiers":[
        {
            "category":"Real Estate",
            "subcategory":"Real Estate Agent",
            "type":"Services"
        }
    ],
    "sg:phone":"+1 330 779 3000",
    "sg:postcode":"44511",
    "sg:province":"OH",
    "sg:tags":[
        "agency",
        "rental"
    ],
    "wof:name":"Rental Guide",
    "wof:placetype":"venue"
},
  "geometry": {"coordinates":[-80.70844700000001,41.086746],"type":"Point"}
}