{
  "type": "Feature",
  "properties": {
    "iso:country":"US",
    "sg:address":"2804 Clark Ave",
    "sg:city":"Cleveland",
    "sg:classifiers":[
        {
            "category":"Personal",
            "subcategory":"Barber",
            "type":"Services"
        }
    ],
    "sg:phone":"+1 216 771 5080",
    "sg:postcode":"44109",
    "sg:province":"OH",
    "wof:name":"Martin's Hair Styling",
    "wof:placetype":"venue"
},
  "geometry": {"coordinates":[-81.701717,41.469969],"type":"Point"}
}