{
  "type": "Feature",
  "properties": {
    "addr:full": "380 Jefferson St Greenfield OH 45123",
    "addr:housenumber": "380",
    "addr:postcode": "45123",
    "addr:street": "Jefferson St",
    "iso:country": "US",
    "sg:address": "380 Jefferson St",
    "sg:city": "Greenfield",
    "sg:classifiers": [
      {
        "category": "Retail",
        "subcategory": "Funeral Services",
        "type": "Services"
      }
    ],
    "sg:phone": "+1 937 981 4081",
    "sg:postcode": "45123",
    "sg:province": "OH",
    "sg:tags": [
      "director",
      "home"
    ],
    "wof:name": "Murray-Fettro Funeral Home",
    "wof:placetype": "venue"
  },
  "geometry": {"coordinates":[-83.384257,39.351212],"type":"Point"}
}
