{
  "type": "Feature",
  "properties": {
    "addr:full": "121 S Main St North Baltimore OH 45872",
    "addr:housenumber": "121",
    "addr:postcode": "45872",
    "addr:street": "S Main St",
    "iso:country": "US",
    "sg:address": "121 S Main St",
    "sg:city": "North Baltimore",
    "sg:classifiers": [
      {
        "category": "Sports \u0026 Exercise",
        "subcategory": "Bowling",
        "type": "Entertainment"
      }
    ],
    "sg:phone": "+1 419 257 2071",
    "sg:postcode": "45872",
    "sg:province": "OH",
    "sg:tags": [
      "center"
    ],
    "wof:name": "Ten Pin Lanes \u0026 Lounge",
    "wof:placetype": "venue"
  },
  "geometry": {"coordinates":[-83.678268,41.180696],"type":"Point"}
}
