{
  "type": "Feature",
  "properties": {
    "iso:country":"US",
    "sg:address":"121 S Main St",
    "sg:city":"North Baltimore",
    "sg:classifiers":[
        {
            "category":"Sports & Exercise",
            "subcategory":"Bowling",
            "type":"Entertainment"
        }
    ],
    "sg:phone":"+1 419 257 2071",
    "sg:postcode":"45872",
    "sg:province":"OH",
    "sg:tags":[
        "center"
    ],
    "wof:name":"Ten Pin Lanes & Lounge",
    "wof:placetype":"venue"
},
  "geometry": {"coordinates":[-83.678268,41.180696],"type":"Point"}
}