{
  "type": "Feature",
  "properties": {
    "iso:country":"US",
    "sg:address":"801 W 5th St",
    "sg:city":"Cincinnati",
    "sg:classifiers":[
        {
            "category":"Shopping",
            "subcategory":"Clothing, Apparel, & Fashions",
            "type":"Retail Goods"
        }
    ],
    "sg:phone":"+1 513 723 9494",
    "sg:postcode":"45203",
    "sg:province":"OH",
    "sg:tags":[
        "salvage",
        "surplus",
        "merchandise"
    ],
    "wof:name":"Mark Golden Inc",
    "wof:placetype":"venue"
},
  "geometry": {"coordinates":[-84.528346,39.098879],"type":"Point"}
}