{
  "type": "Feature",
  "properties": {
    "addr:full":"415 Northfield Rd Cleveland OH 44146",
    "addr:housenumber":"415",
    "addr:postcode":"44146",
    "addr:street":"Northfield Rd",
    "iso:country":"US",
    "sg:address":"415 Northfield Rd",
    "sg:city":"Cleveland",
    "sg:classifiers":[
        {
            "category":"Social Services",
            "subcategory":"Child Care",
            "type":"Services"
        }
    ],
    "sg:phone":"+1 440 232 4712",
    "sg:postcode":"44146",
    "sg:province":"OH",
    "sg:tags":[
        "kindergarten",
        "academic",
        "school"
    ],
    "wof:name":"Bedford Co-Op Nursery School",
    "wof:placetype":"venue"
},
  "geometry": {"coordinates":[-81.527237,41.409267],"type":"Point"}
}