{
  "type": "Feature",
  "properties": {
    "addr:full":"8570 Bayberry Dr NE Warren OH 44484",
    "addr:housenumber":"8570",
    "addr:postcode":"44484",
    "addr:street":"Bayberry Dr Ne",
    "iso:country":"US",
    "sg:address":"8570 Bayberry Dr NE",
    "sg:city":"Warren",
    "sg:classifiers":[
        {
            "category":"Building & Trades",
            "subcategory":"Construction",
            "type":"Services"
        }
    ],
    "sg:phone":"+1 330 392 7015",
    "sg:postcode":"44484",
    "sg:province":"OH",
    "sg:tags":[
        "painter"
    ],
    "wof:name":"Brush Up Painting",
    "wof:placetype":"venue"
},
  "geometry": {"coordinates":[-80.735291,41.252966],"type":"Point"}
}