{
  "type": "Feature",
  "properties": {
    "iso:country":"US",
    "sg:address":"2126 Martin Ave",
    "sg:city":"Dayton",
    "sg:classifiers":[
        {
            "category":"Building & Trades",
            "subcategory":"Construction",
            "type":"Services"
        }
    ],
    "sg:phone":"+1 937 890 3445",
    "sg:postcode":"45414",
    "sg:province":"OH",
    "sg:tags":[
        "house",
        "carpentry",
        "contractor"
    ],
    "wof:name":"Interior Perfections",
    "wof:placetype":"venue"
},
  "geometry": {"coordinates":[-84.196697,39.827438],"type":"Point"}
}