{
  "type": "Feature",
  "properties": {
    "addr:full":"1811 Columbia Ave Middletown OH 45042",
    "addr:housenumber":"1811",
    "addr:postcode":"45042",
    "addr:street":"Columbia Ave",
    "iso:country":"US",
    "sg:address":"1811 Columbia Ave",
    "sg:city":"Middletown",
    "sg:classifiers":[
        {
            "category":"Building & Trades",
            "subcategory":"Construction",
            "type":"Services"
        }
    ],
    "sg:phone":"+1 513 423 7735",
    "sg:postcode":"45042",
    "sg:province":"OH",
    "sg:tags":[
        "residential"
    ],
    "wof:name":"Christopher D King",
    "wof:placetype":"venue"
},
  "geometry": {"coordinates":[-84.391184,39.516944],"type":"Point"}
}