{
  "type": "Feature",
  "properties": {
    "addr:full": "2705 Wadsworth Rd Cleveland OH 44122",
    "addr:housenumber": "2705",
    "addr:postcode": "44122",
    "addr:street": "Wadsworth Rd",
    "iso:country": "US",
    "sg:address": "2705 Wadsworth Rd",
    "sg:city": "Cleveland",
    "sg:classifiers": [
      {
        "category": "Health Services",
        "subcategory": "Health Practitioner",
        "type": "Services"
      }
    ],
    "sg:phone": "+1 216 464 1170",
    "sg:postcode": "44122",
    "sg:province": "OH",
    "sg:tags": [
      "psychologist"
    ],
    "wof:name": "Lawrence S Waldman",
    "wof:placetype": "venue"
  },
  "geometry": {"coordinates":[-81.519758,41.482457],"type":"Point"}
}
