{
  "type": "Feature",
  "properties": {
    "addr:full":"6375 Strip Ave NW Canton OH 44720",
    "addr:postcode":"6375;44720",
    "addr:street":"Strip Ave Nw",
    "iso:country":"US",
    "sg:address":"6375 Strip Ave NW",
    "sg:city":"Canton",
    "sg:classifiers":[
        {
            "category":"Home & Garden",
            "subcategory":"Building Materials",
            "type":"Retail Goods"
        }
    ],
    "sg:phone":"+1 330 497 2720",
    "sg:postcode":"44720",
    "sg:province":"OH",
    "wof:name":"Lowes",
    "wof:placetype":"venue"
},
  "geometry": {"coordinates":[-81.431279,40.870419],"type":"Point"}
}