{
  "type": "Feature",
  "properties": {
    "addr:full": "615 Davis St Crestline OH 44827",
    "addr:housenumber": "615",
    "addr:postcode": "44827",
    "addr:street": "Davis St",
    "iso:country": "US",
    "sg:address": "615 Davis St",
    "sg:city": "Crestline",
    "sg:classifiers": [
      {
        "category": "Professional",
        "type": "Services"
      }
    ],
    "sg:phone": "+1 419 683 3555",
    "sg:postcode": "44827",
    "sg:province": "OH",
    "wof:name": "Royal Arch Masons of Ohio",
    "wof:placetype": "venue"
  },
  "geometry": {"coordinates":[-82.744821,40.788527],"type":"Point"}
}
