{
  "type": "Feature",
  "properties": {
    "iso:country":"US",
    "sg:address":"4060 Dueber Ave SW",
    "sg:city":"Canton",
    "sg:classifiers":[
        {
            "category":"Building & Trades",
            "subcategory":"Plumbing",
            "type":"Services"
        }
    ],
    "sg:phone":"+1 330 484 5554",
    "sg:postcode":"44706",
    "sg:province":"OH",
    "sg:tags":[
        "septic"
    ],
    "wof:name":"Griffith Septic Svc",
    "wof:placetype":"venue"
},
  "geometry": {"coordinates":[-81.39784899999999,40.75753],"type":"Point"}
}