{
  "type": "Feature",
  "properties": {
    "addr:full": "4060 Dueber Ave SW Canton OH 44706",
    "addr:housenumber": "4060",
    "addr:postcode": "44706",
    "addr:street": "Dueber Ave Sw",
    "iso:country": "US",
    "sg:address": "4060 Dueber Ave SW",
    "sg:city": "Canton",
    "sg:classifiers": [
      {
        "category": "Building \u0026 Trades",
        "subcategory": "Plumbing",
        "type": "Services"
      }
    ],
    "sg:phone": "+1 330 484 5554",
    "sg:postcode": "44706",
    "sg:province": "OH",
    "sg:tags": [
      "septic"
    ],
    "wof:name": "Griffith Septic Svc",
    "wof:placetype": "venue"
  },
  "geometry": {"coordinates":[-81.397849,40.75753],"type":"Point"}
}
