{
  "type": "Feature",
  "properties": {
    "iso:country":"US",
    "sg:address":"10925 Reed Hartman Hwy",
    "sg:city":"Cincinnati",
    "sg:classifiers":[
        {
            "category":"Real Estate",
            "subcategory":"Real Estate Operator",
            "type":"Services"
        }
    ],
    "sg:phone":"+1 513 984 3030",
    "sg:postcode":"45242",
    "sg:province":"OH",
    "sg:tags":[
        "apartment"
    ],
    "sg:website":"www.cincyapt.com",
    "wof:name":"Community Management Co",
    "wof:placetype":"venue"
},
  "geometry": {"coordinates":[-84.376149,39.269584],"type":"Point"}
}