{
  "type": "Feature",
  "properties": {
    "iso:country":"US",
    "sg:address":"3334 Bruening Ave SW",
    "sg:city":"Canton",
    "sg:classifiers":[
        {
            "category":"Retail",
            "subcategory":"Auto Rental",
            "type":"Services"
        }
    ],
    "sg:phone":"+1 330 456 1848",
    "sg:postcode":"44706",
    "sg:province":"OH",
    "sg:tags":[
        "renting",
        "truck",
        "leasing"
    ],
    "wof:name":"Pac Lease",
    "wof:placetype":"venue"
},
  "geometry": {"coordinates":[-81.40436200000001,40.762956],"type":"Point"}
}