{
  "type": "Feature",
  "properties": {
    "iso:country":"US",
    "sg:address":"68 N High St",
    "sg:city":"New Albany",
    "sg:classifiers":[
        {
            "category":"Health Services",
            "subcategory":"Optometrist",
            "type":"Services"
        }
    ],
    "sg:phone":"+1 614 933 0575",
    "sg:postcode":"43054",
    "sg:province":"OH",
    "wof:name":"Sorensen & Sorensen",
    "wof:placetype":"venue"
},
  "geometry": {"coordinates":[-82.808661,40.082812],"type":"Point"}
}