{
  "type": "Feature",
  "properties": {
    "addr:full": "1463 Warrensville Center Rd Cleveland OH 44121",
    "addr:housenumber": "1463",
    "addr:postcode": "44121",
    "addr:street": "Warrensville Center Rd",
    "iso:country": "US",
    "sg:address": "1463 Warrensville Center Rd",
    "sg:city": "Cleveland",
    "sg:classifiers": [
      {
        "category": "Building \u0026 Trades",
        "subcategory": "Cleaning \u0026 Sanitation",
        "type": "Services"
      }
    ],
    "sg:phone": "+1 216 382 5432",
    "sg:postcode": "44121",
    "sg:province": "OH",
    "sg:tags": [
      "janitor"
    ],
    "wof:name": "Eufaula Commercial Cleaning",
    "wof:placetype": "venue"
  },
  "geometry": {"coordinates":[-81.536379,41.518199],"type":"Point"}
}
