{
  "type": "Feature",
  "properties": {
    "addr:full": "3908 Marvin Ave Cleveland OH 44109",
    "addr:housenumber": "3908",
    "addr:postcode": "44109",
    "addr:street": "Marvin Ave",
    "iso:country": "US",
    "sg:address": "3908 Marvin Ave",
    "sg:city": "Cleveland",
    "sg:classifiers": [
      {
        "category": "Autos \u0026 Motor Vehicles",
        "subcategory": "Automobile Sales",
        "type": "Retail Goods"
      }
    ],
    "sg:phone": "+1 216 661 4827",
    "sg:postcode": "44109",
    "sg:province": "OH",
    "wof:name": "Ninos Autoworld Corp",
    "wof:placetype": "venue"
  },
  "geometry": {"coordinates":[-81.709069,41.460009],"type":"Point"}
}
