{
  "type": "Feature",
  "properties": {
    "iso:country":"US",
    "sg:address":"2007 South Ave",
    "sg:city":"Youngstown",
    "sg:classifiers":[
        {
            "category":"Manufacturing",
            "subcategory":"Tools & Machinery",
            "type":"Manufacturing & Wholesale Goods"
        }
    ],
    "sg:phone":"+1 330 747 4637",
    "sg:postcode":"44502",
    "sg:province":"OH",
    "sg:tags":[
        "redesign",
        "machining",
        "precision",
        "contract"
    ],
    "wof:name":"Imds Power Transmissions",
    "wof:placetype":"venue"
},
  "geometry": {"coordinates":[-80.646176,41.079087],"type":"Point"}
}