{
  "type": "Feature",
  "properties": {
    "addr:full":"5950 Boymel Dr Fairfield OH 45014",
    "addr:housenumber":"5950",
    "addr:postcode":"45014",
    "addr:street":"Boymel Dr",
    "iso:country":"US",
    "sg:address":"5950 Boymel Dr",
    "sg:city":"Fairfield",
    "sg:classifiers":[
        {
            "category":"Social Services",
            "subcategory":"Child Care",
            "type":"Services"
        }
    ],
    "sg:phone":"+1 513 874 5545",
    "sg:postcode":"45014",
    "sg:province":"OH",
    "sg:tags":[
        "day"
    ],
    "wof:name":"Youthland Academy Fairfield",
    "wof:placetype":"venue"
},
  "geometry": {"coordinates":[-84.49865,39.318966],"type":"Point"}
}