{
  "type": "Feature",
  "properties": {
    "addr:full":"1860 Lockbourne Rd Columbus OH 43207",
    "addr:housenumber":"1860",
    "addr:postcode":"43207",
    "addr:street":"Lockbourne Rd",
    "iso:country":"US",
    "sg:address":"1860 Lockbourne Rd",
    "sg:city":"Columbus",
    "sg:classifiers":[
        {
            "category":"Shopping",
            "type":"Retail Goods"
        }
    ],
    "sg:phone":"+1 614 443 6000",
    "sg:postcode":"43207",
    "sg:province":"OH",
    "sg:tags":[
        "telephone",
        "cellular"
    ],
    "wof:name":"Comstation",
    "wof:placetype":"venue"
},
  "geometry": {"coordinates":[-82.96498800000001,39.926806],"type":"Point"}
}