{
  "type": "Feature",
  "properties": {
    "iso:country":"US",
    "sg:address":"6714 Gates Mills Blvd",
    "sg:city":"Gates Mills",
    "sg:classifiers":[
        {
            "category":"Home & Garden",
            "subcategory":"Mobile Homes",
            "type":"Retail Goods"
        }
    ],
    "sg:phone":"+1 440 449 4721",
    "sg:postcode":"44040",
    "sg:province":"OH",
    "wof:name":"Sahara Mobile Homes Sales Inc",
    "wof:placetype":"venue"
},
  "geometry": {"coordinates":[-81.42942,41.514168],"type":"Point"}
}