{
  "type": "Feature",
  "properties": {
    "addr:full": "6714 Gates Mills Blvd Gates Mills OH 44040",
    "addr:housenumber": "6714",
    "addr:postcode": "44040",
    "addr:street": "Gates Mills Blvd",
    "iso:country": "US",
    "sg:address": "6714 Gates Mills Blvd",
    "sg:city": "Gates Mills",
    "sg:classifiers": [
      {
        "category": "Home \u0026 Garden",
        "subcategory": "Mobile Homes",
        "type": "Retail Goods"
      }
    ],
    "sg:phone": "+1 440 449 4721",
    "sg:postcode": "44040",
    "sg:province": "OH",
    "wof:name": "Sahara Mobile Homes Sales Inc",
    "wof:placetype": "venue"
  },
  "geometry": {"coordinates":[-81.42942,41.514168],"type":"Point"}
}
