{
  "type": "Feature",
  "properties": {
    "addr:full": "400 Niles Cortland Rd SE Warren OH 44484",
    "addr:housenumber": "400",
    "addr:postcode": "44484",
    "addr:street": "Niles Cortland Rd Se",
    "iso:country": "US",
    "sg:address": "400 Niles Cortland Rd SE",
    "sg:city": "Warren",
    "sg:classifiers": [
      {
        "category": "Health Services",
        "subcategory": "Doctor",
        "type": "Services"
      }
    ],
    "sg:phone": "+1 330 856 1311",
    "sg:postcode": "44484",
    "sg:province": "OH",
    "sg:tags": [
      "physician",
      "surgeon"
    ],
    "wof:name": "Rowland \u0026 Assoc Ob/Gyn",
    "wof:placetype": "venue"
  },
  "geometry": {"coordinates":[-80.740578,41.234758],"type":"Point"}
}
