{
  "type": "Feature",
  "properties": {
    "iso:country":"US",
    "sg:address":"400 Niles Cortland Rd SE",
    "sg:city":"Warren",
    "sg:classifiers":[
        {
            "category":"Health Services",
            "subcategory":"Doctor",
            "type":"Services"
        }
    ],
    "sg:phone":"+1 330 856 1311",
    "sg:postcode":"44484",
    "sg:province":"OH",
    "sg:tags":[
        "physician",
        "surgeon"
    ],
    "wof:name":"Rowland & Assoc Ob/Gyn",
    "wof:placetype":"venue"
},
  "geometry": {"coordinates":[-80.740578,41.234758],"type":"Point"}
}