{
  "type": "Feature",
  "properties": {
    "iso:country":"US",
    "sg:address":"8216 W Chester Rd",
    "sg:city":"West Chester",
    "sg:classifiers":[
        {
            "category":"Building & Trades",
            "subcategory":"Construction",
            "type":"Services"
        }
    ],
    "sg:phone":"+1 513 642 0039",
    "sg:postcode":"45069",
    "sg:province":"OH",
    "sg:tags":[
        "floor",
        "contractor"
    ],
    "wof:name":"Axis Interior Systems Inc",
    "wof:placetype":"venue"
},
  "geometry": {"coordinates":[-84.356033,39.317762],"type":"Point"}
}