{
  "type": "Feature",
  "properties": {
    "addr:full": "8216 W Chester Rd West Chester OH 45069",
    "addr:housenumber": "8216",
    "addr:postcode": "45069",
    "addr:street": "W Chester Rd",
    "iso:country": "US",
    "sg:address": "8216 W Chester Rd",
    "sg:city": "West Chester",
    "sg:classifiers": [
      {
        "category": "Building \u0026 Trades",
        "subcategory": "Construction",
        "type": "Services"
      }
    ],
    "sg:phone": "+1 513 642 0039",
    "sg:postcode": "45069",
    "sg:province": "OH",
    "sg:tags": [
      "floor",
      "contractor"
    ],
    "wof:name": "Axis Interior Systems Inc",
    "wof:placetype": "venue"
  },
  "geometry": {"coordinates":[-84.356033,39.317762],"type":"Point"}
}
