{
  "type": "Feature",
  "properties": {
    "iso:country":"US",
    "sg:address":"323 S 15th St",
    "sg:city":"Sebring",
    "sg:classifiers":[
        {
            "category":"Organizations",
            "subcategory":"Religious Organization",
            "type":"Services"
        }
    ],
    "sg:phone":"+1 330 938 2033",
    "sg:postcode":"44672",
    "sg:province":"OH",
    "sg:tags":[
        "church"
    ],
    "wof:name":"St Ann's Church",
    "wof:placetype":"venue"
},
  "geometry": {"coordinates":[-81.018891,40.916599],"type":"Point"}
}