{
  "type": "Feature",
  "properties": {
    "addr:full":"5150 Sandy Ln Fairfield OH 45014",
    "addr:housenumber":"5150",
    "addr:postcode":"45014",
    "addr:street":"Sandy Ln",
    "iso:country":"US",
    "sg:address":"5150 Sandy Ln",
    "sg:city":"Fairfield",
    "sg:classifiers":[
        {
            "category":"Health Services",
            "subcategory":"Doctor",
            "type":"Services"
        }
    ],
    "sg:phone":"+1 513 870 7000",
    "sg:postcode":"45014",
    "sg:province":"OH",
    "sg:tags":[
        "physician",
        "surgeon"
    ],
    "wof:name":"John P Weintz MD",
    "wof:placetype":"venue"
},
  "geometry": {"coordinates":[-84.55756100000001,39.340229],"type":"Point"}
}