{
  "type": "Feature",
  "properties": {
    "addr:full":"3739 Broadway Grove City OH 43123",
    "addr:housenumber":"3739",
    "addr:postcode":"43123",
    "addr:street":"Broadway",
    "iso:country":"US",
    "sg:address":"3739 Broadway",
    "sg:city":"Grove City",
    "sg:classifiers":[
        {
            "category":"Building & Trades",
            "subcategory":"Plumbing",
            "type":"Services"
        }
    ],
    "sg:phone":"+1 614 870 3358",
    "sg:postcode":"43123",
    "sg:province":"OH",
    "sg:tags":[
        "conditioning",
        "air",
        "system",
        "contractor"
    ],
    "wof:name":"Fast Response",
    "wof:placetype":"venue"
},
  "geometry": {"coordinates":[-83.09048300000001,39.885808],"type":"Point"}
}