{
  "type": "Feature",
  "properties": {
    "addr:full": "1077 Morgan Ross Rd Hamilton IN 45013",
    "addr:housenumber": "1077",
    "addr:postcode": "45013",
    "addr:street": "Morgan Ross Rd",
    "iso:country": "US",
    "sg:address": "1077 Morgan Ross Rd",
    "sg:city": "Hamilton",
    "sg:classifiers": [
      {
        "category": "Organizations",
        "subcategory": "Religious Organization",
        "type": "Services"
      }
    ],
    "sg:phone": "+1 513 756 0160",
    "sg:postcode": "45013",
    "sg:province": "IN",
    "sg:tags": [
      "church"
    ],
    "wof:name": "Auburn Old Time Holiness Chr",
    "wof:placetype": "venue"
  },
  "geometry": {"coordinates":[-84.703348,39.383147],"type":"Point"}
}
