{
  "type": "Feature",
  "properties": {
    "addr:full": "15691 State Rte 93 Pedro OH 45659",
    "addr:housenumber": "15691",
    "addr:postcode": "45659",
    "addr:street": "State Rte 93 Pedro",
    "iso:country": "US",
    "sg:address": "15691 State Rte 93",
    "sg:city": "Pedro",
    "sg:classifiers": [
      {
        "category": "Farming",
        "subcategory": "Farm",
        "type": "Manufacturing \u0026 Wholesale Goods"
      }
    ],
    "sg:phone": "+1 740 643 2500",
    "sg:postcode": "45659",
    "sg:province": "OH",
    "sg:tags": [
      "crop",
      "general"
    ],
    "wof:name": "Freddie L Evans",
    "wof:placetype": "venue"
  },
  "geometry": {"coordinates":[-82.640824,38.709545],"type":"Point"}
}
