{
  "type": "Feature",
  "properties": {
    "addr:full": "108 4th St Elyria OH 44035",
    "addr:housenumber": "108",
    "addr:postcode": "44035",
    "addr:street": "4Th St",
    "iso:country": "US",
    "sg:address": "108 4th St",
    "sg:city": "Elyria",
    "sg:classifiers": [
      {
        "category": "Shopping",
        "subcategory": "Bicycles \u0026 Sporting Goods",
        "type": "Retail Goods"
      }
    ],
    "sg:phone": "+1 440 323 0420",
    "sg:postcode": "44035",
    "sg:province": "OH",
    "sg:tags": [
      "equipment",
      "skateboard"
    ],
    "wof:name": "Grounded Skateboards",
    "wof:placetype": "venue"
  },
  "geometry": {"coordinates":[-82.102013,41.363477],"type":"Point"}
}
