{
  "type": "Feature",
  "properties": {
    "addr:full":"25467 Detroit Rd Westlake OH 44145",
    "addr:housenumber":"25467",
    "addr:postcode":"44145",
    "addr:street":"Detroit Rd",
    "iso:country":"US",
    "sg:address":"25467 Detroit Rd",
    "sg:city":"Westlake",
    "sg:classifiers":[
        {
            "category":"Restaurant",
            "type":"Food & Drink"
        }
    ],
    "sg:menulink":"http://www.allmenus.com/oh/westlake/211495-kfc---kentucky-fried-chicken/menu/",
    "sg:phone":"+1 440 835 2515",
    "sg:postcode":"44145",
    "sg:province":"OH",
    "sg:tags":[
        "american",
        "chicken"
    ],
    "wof:name":"KFC - Kentucky Fried Chicken",
    "wof:placetype":"venue"
},
  "geometry": {"coordinates":[-81.901084,41.469665],"type":"Point"}
}