{
  "type": "Feature",
  "properties": {
    "addr:full": "330 Cargo Rd Crown City OH 45623",
    "addr:postcode": "45623",
    "addr:street": "Cargo Rd",
    "iso:country": "US",
    "sg:address": "330 Cargo Rd",
    "sg:city": "Crown City",
    "sg:classifiers": [
      {
        "category": "Farming",
        "subcategory": "Nursery",
        "type": "Manufacturing \u0026 Wholesale Goods"
      }
    ],
    "sg:phone": "+1 740 256 1760",
    "sg:postcode": "45623",
    "sg:province": "OH",
    "sg:tags": [
      "ornamental"
    ],
    "wof:name": "Preston Farm \u0026 Greenhouse",
    "wof:placetype": "venue"
  },
  "geometry": {"coordinates":[-82.221705,38.680717],"type":"Point"}
}
