{
  "type": "Feature",
  "properties": {
    "addr:full": "3445 Clifton Ave Cincinnati OH 45220",
    "addr:housenumber": "3445",
    "addr:postcode": "45220",
    "addr:street": "Clifton Ave",
    "iso:country": "US",
    "sg:address": "3445 Clifton Ave",
    "sg:city": "Cincinnati",
    "sg:classifiers": [
      {
        "category": "Social Services",
        "subcategory": "Child Care",
        "type": "Services"
      }
    ],
    "sg:phone": "+1 513 861 2692",
    "sg:postcode": "45220",
    "sg:province": "OH",
    "sg:tags": [
      "day"
    ],
    "wof:name": "Immaneul Child Development Ctr",
    "wof:placetype": "venue"
  },
  "geometry": {"coordinates":[-84.519176,39.144266],"type":"Point"}
}
