{
  "type": "Feature",
  "properties": {
    "addr:full": "10556 Clearlake Dr Painesville OH 44077",
    "addr:housenumber": "10556",
    "addr:postcode": "44077",
    "addr:street": "Clearlake Dr",
    "iso:country": "US",
    "sg:address": "10556 Clearlake Dr",
    "sg:city": "Painesville",
    "sg:classifiers": [
      {
        "category": "Real Estate",
        "subcategory": "Real Estate Agent",
        "type": "Services"
      }
    ],
    "sg:phone": "+1 440 639 4339",
    "sg:postcode": "44077",
    "sg:province": "OH",
    "wof:name": "Zames Realty",
    "wof:placetype": "venue"
  },
  "geometry": {"coordinates":[-81.258368,41.689016],"type":"Point"}
}
