{
  "type": "Feature",
  "properties": {
    "addr:full": "23 N Center St Springfield OH 45502",
    "addr:housenumber": "23",
    "addr:postcode": "45502",
    "addr:street": "N Center St",
    "iso:country": "US",
    "sg:address": "23 N Center St",
    "sg:city": "Springfield",
    "sg:classifiers": [
      {
        "category": "Real Estate",
        "subcategory": "Architect",
        "type": "Services"
      }
    ],
    "sg:phone": "+1 937 325 9991",
    "sg:postcode": "45502",
    "sg:province": "OH",
    "sg:tags": [
      "construction",
      "management",
      "architectural"
    ],
    "wof:name": "Wrdc Group",
    "wof:placetype": "venue"
  },
  "geometry": {"coordinates":[-83.812269,39.925049],"type":"Point"}
}
