{
  "type": "Feature",
  "properties": {
    "iso:country":"US",
    "sg:address":"701 W North St",
    "sg:city":"Lima",
    "sg:classifiers":[
        {
            "category":"Autos & Motor Vehicles",
            "subcategory":"Fuel & Gas Station",
            "type":"Retail Goods"
        }
    ],
    "sg:phone":"+1 419 224 1942",
    "sg:postcode":"45801",
    "sg:province":"OH",
    "sg:tags":[
        "oil"
    ],
    "wof:name":"Amia Inc",
    "wof:placetype":"venue"
},
  "geometry": {"coordinates":[-84.113344,40.742673],"type":"Point"}
}