{
  "type": "Feature",
  "properties": {
    "addr:full": "701 W North St Lima OH 45801",
    "addr:housenumber": "701",
    "addr:postcode": "45801",
    "addr:street": "W North St",
    "iso:country": "US",
    "sg:address": "701 W North St",
    "sg:city": "Lima",
    "sg:classifiers": [
      {
        "category": "Autos \u0026 Motor Vehicles",
        "subcategory": "Fuel \u0026 Gas Station",
        "type": "Retail Goods"
      }
    ],
    "sg:phone": "+1 419 224 1942",
    "sg:postcode": "45801",
    "sg:province": "OH",
    "sg:tags": [
      "oil"
    ],
    "wof:name": "Amia Inc",
    "wof:placetype": "venue"
  },
  "geometry": {"coordinates":[-84.113344,40.742673],"type":"Point"}
}
