{
  "type": "Feature",
  "properties": {
    "addr:full": "270 Northland Blvd Cincinnati OH 45246",
    "addr:housenumber": "270",
    "addr:postcode": "45246",
    "addr:street": "Northland Blvd",
    "iso:country": "US",
    "sg:address": "270 Northland Blvd",
    "sg:city": "Cincinnati",
    "sg:classifiers": [
      {
        "category": "Professional",
        "subcategory": "Employment Agencies",
        "type": "Services"
      }
    ],
    "sg:phone": "+1 513 772 3666",
    "sg:postcode": "45246",
    "sg:province": "OH",
    "sg:tags": [
      "temporary",
      "help"
    ],
    "wof:name": "C M Temporary Services Inc",
    "wof:placetype": "venue"
  },
  "geometry": {"coordinates":[-84.482004,39.282706],"type":"Point"}
}
