{
  "type": "Feature",
  "properties": {
    "addr:full":"805 Main St Delta OH 43515",
    "addr:housenumber":"805",
    "addr:postcode":"43515",
    "addr:street":"Main St",
    "iso:country":"US",
    "sg:address":"805 Main St",
    "sg:city":"Delta",
    "sg:classifiers":[
        {
            "category":"Wholesale",
            "subcategory":"Apparel",
            "type":"Manufacturing & Wholesale Goods"
        }
    ],
    "sg:phone":"+1 419 822 4916",
    "sg:postcode":"43515",
    "sg:province":"OH",
    "sg:tags":[
        "clothing"
    ],
    "wof:name":"Robby M Inc",
    "wof:placetype":"venue"
},
  "geometry": {"coordinates":[-83.998009,41.574037],"type":"Point"}
}