{
  "type": "Feature",
  "properties": {
    "addr:full": "2420 Brook Haven Ln Hinckley OH 44233",
    "addr:housenumber": "2420",
    "addr:postcode": "44233",
    "addr:street": "Brook Haven Ln",
    "iso:country": "US",
    "sg:address": "2420 Brook Haven Ln",
    "sg:city": "Hinckley",
    "sg:classifiers": [
      {
        "category": "Building \u0026 Trades",
        "subcategory": "Construction",
        "type": "Services"
      }
    ],
    "sg:phone": "+1 440 888 9180",
    "sg:postcode": "44233",
    "sg:province": "OH",
    "sg:tags": [
      "stonework",
      "masonry",
      "other"
    ],
    "wof:name": "Diliberto Waterproofing Inc",
    "wof:placetype": "venue"
  },
  "geometry": {"coordinates":[-81.773431,41.269419],"type":"Point"}
}
