{
  "type": "Feature",
  "properties": {
    "addr:full":"9245 Norwalk Rd Litchfield OH 44253",
    "addr:housenumber":"9245",
    "addr:postcode":"44253",
    "addr:street":"Norwalk Rd",
    "iso:country":"US",
    "sg:address":"9245 Norwalk Rd",
    "sg:city":"Litchfield",
    "sg:classifiers":[
        {
            "category":"Professional",
            "subcategory":"Business Services",
            "type":"Services"
        },
        {
            "category":"Government",
            "subcategory":"Post Office",
            "type":"Public Place"
        }
    ],
    "sg:phone":"+1 330 723 7117",
    "sg:postcode":"44253",
    "sg:province":"OH",
    "sg:tags":[
        "mail",
        "shipping"
    ],
    "sg:website":"http://www.usps.com",
    "wof:name":"Us Post Office",
    "wof:placetype":"venue"
},
  "geometry": {"coordinates":[-82.022087,41.167992],"type":"Point"}
}