{
  "type": "Feature",
  "properties": {
    "addr:full":"2100 Springboro Rd Dayton OH 45439",
    "addr:housenumber":"2100",
    "addr:postcode":"45439",
    "addr:street":"Springboro Rd",
    "iso:country":"US",
    "sg:address":"2100 Springboro Rd",
    "sg:city":"Dayton",
    "sg:classifiers":[
        {
            "category":"Retail",
            "subcategory":"Auto Repair",
            "type":"Services"
        }
    ],
    "sg:phone":"+1 937 294 6820",
    "sg:postcode":"45439",
    "sg:province":"OH",
    "sg:tags":[
        "wrecker"
    ],
    "wof:name":"Eddie's Towing & Recovery",
    "wof:placetype":"venue"
},
  "geometry": {"coordinates":[-84.21385100000001,39.721756],"type":"Point"}
}