{
  "type": "Feature",
  "properties": {
    "addr:full":"4600 Montgomery Rd Cincinnati OH 45212",
    "addr:housenumber":"4600",
    "addr:postcode":"45212",
    "addr:street":"Montgomery Rd",
    "iso:country":"US",
    "sg:address":"4600 Montgomery Rd",
    "sg:city":"Cincinnati",
    "sg:classifiers":[
        {
            "category":"Real Estate",
            "subcategory":"Real Estate Agent",
            "type":"Services"
        }
    ],
    "sg:phone":"+1 513 241 7373",
    "sg:postcode":"45212",
    "sg:province":"OH",
    "sg:website":"www.cresapartners.com",
    "wof:name":"A M Piker Inc",
    "wof:placetype":"venue"
},
  "geometry": {"coordinates":[-84.45622299999999,39.160543],"type":"Point"}
}