{
  "type": "Feature",
  "properties": {
    "addr:full": "14 S Main St Akron OH 44308",
    "addr:housenumber": "14",
    "addr:postcode": "44308",
    "addr:street": "S Main St",
    "iso:country": "US",
    "sg:address": "14 S Main St",
    "sg:city": "Akron",
    "sg:classifiers": [
      {
        "category": "Personal",
        "subcategory": "Beauty Salon",
        "type": "Services"
      }
    ],
    "sg:phone": "+1 330 688 2694",
    "sg:postcode": "44308",
    "sg:province": "OH",
    "wof:name": "Utopia",
    "wof:placetype": "venue"
  },
  "geometry": {"coordinates":[-81.517822,41.082976],"type":"Point"}
}
