{
  "type": "Feature",
  "properties": {
    "iso:country":"US",
    "sg:address":"902 E Main St",
    "sg:city":"Coldwater",
    "sg:classifiers":[
        {
            "category":"Retail",
            "subcategory":"Auto Repair",
            "type":"Services"
        }
    ],
    "sg:phone":"+1 419 678 3535",
    "sg:postcode":"45828",
    "sg:province":"OH",
    "sg:tags":[
        "repairing",
        "automobile"
    ],
    "wof:name":"Mall Service Ctr",
    "wof:placetype":"venue"
},
  "geometry": {"coordinates":[-84.618236,40.479889],"type":"Point"}
}