{
  "type": "Feature",
  "properties": {
    "addr:full": "7141 E Broad St Columbus OH 43213",
    "addr:housenumber": "7141",
    "addr:postcode": "43213",
    "addr:street": "E Broad St",
    "iso:country": "US",
    "sg:address": "7141 E Broad St",
    "sg:city": "Columbus",
    "sg:classifiers": [
      {
        "category": "Home \u0026 Garden",
        "subcategory": "Garden Supply",
        "type": "Retail Goods"
      }
    ],
    "sg:phone": "+1 614 861 6767",
    "sg:postcode": "43213",
    "sg:province": "OH",
    "sg:tags": [
      "nurseryman"
    ],
    "sg:website": "www.franks.com",
    "wof:name": "Franks Nursery \u0026 Crafts 26",
    "wof:placetype": "venue"
  },
  "geometry": {"coordinates":[-82.813721,39.982829],"type":"Point"}
}
