{
  "type": "Feature",
  "properties": {
    "addr:full": "7676 Reynolds Rd Mentor OH 44060",
    "addr:housenumber": "7676",
    "addr:postcode": "44060",
    "addr:street": "Reynolds Rd",
    "iso:country": "US",
    "sg:address": "7676 Reynolds Rd",
    "sg:city": "Mentor",
    "sg:classifiers": [
      {
        "category": "Real Estate",
        "subcategory": "Real Estate Agent",
        "type": "Services"
      }
    ],
    "sg:phone": "+1 440 602 8200",
    "sg:postcode": "44060",
    "sg:province": "OH",
    "wof:name": "Gatto Adams Group LLC",
    "wof:placetype": "venue"
  },
  "geometry": {"coordinates":[-81.378331,41.661474],"type":"Point"}
}
