{
  "type": "Feature",
  "properties": {
    "addr:full":"6995 E Kemper Rd Cincinnati OH 45249",
    "addr:housenumber":"6995",
    "addr:postcode":"45249",
    "addr:street":"E Kemper Rd",
    "iso:country":"US",
    "sg:address":"6995 E Kemper Rd",
    "sg:city":"Cincinnati",
    "sg:classifiers":[
        {
            "category":"Retail",
            "subcategory":"Veterinary Services",
            "type":"Services"
        }
    ],
    "sg:phone":"+1 513 530 0911",
    "sg:postcode":"45249",
    "sg:province":"OH",
    "sg:tags":[
        "veterinarian"
    ],
    "sg:website":"www.carecentervets.com",
    "wof:name":"Care Center",
    "wof:placetype":"venue"
},
  "geometry": {"coordinates":[-84.362278,39.281477],"type":"Point"}
}