{
  "type": "Feature",
  "properties": {
    "addr:full":"4783 Summerside Rd Cincinnati OH 45244",
    "addr:housenumber":"4783",
    "addr:postcode":"45244",
    "addr:street":"Summerside Rd",
    "iso:country":"US",
    "sg:address":"4783 Summerside Rd",
    "sg:city":"Cincinnati",
    "sg:classifiers":[
        {
            "category":"Building & Trades",
            "subcategory":"Construction",
            "type":"Services"
        }
    ],
    "sg:phone":"+1 513 231 8835",
    "sg:postcode":"45244",
    "sg:province":"OH",
    "sg:tags":[
        "hanging",
        "contractor"
    ],
    "wof:name":"Brite-Cote Painting Co",
    "wof:placetype":"venue"
},
  "geometry": {"coordinates":[-84.28887,39.12093],"type":"Point"}
}