{
  "type": "Feature",
  "properties": {
    "iso:country":"US",
    "sg:address":"650 W Smith Rd",
    "sg:city":"Medina",
    "sg:classifiers":[
        {
            "category":"Building & Trades",
            "subcategory":"Pest Control",
            "type":"Services"
        }
    ],
    "sg:phone":"+1 330 723 8900",
    "sg:postcode":"44256",
    "sg:province":"OH",
    "sg:tags":[
        "deodorizing",
        "disinfecting"
    ],
    "wof:name":"King George Svc Corp",
    "wof:placetype":"venue"
},
  "geometry": {"coordinates":[-81.87595,41.136135],"type":"Point"}
}