{
  "type": "Feature",
  "properties": {
    "iso:country":"US",
    "sg:address":"201 N Main St",
    "sg:city":"Mt Vernon",
    "sg:classifiers":[
        {
            "category":"Health Services",
            "subcategory":"Nursing And Care Facility",
            "type":"Services"
        }
    ],
    "sg:phone":"+1 740 397 3897",
    "sg:postcode":"43050",
    "sg:province":"OH",
    "sg:tags":[
        "home",
        "retirement",
        "community"
    ],
    "wof:name":"Living Center Inc",
    "wof:placetype":"venue"
},
  "geometry": {"coordinates":[-82.48521599999999,40.396207],"type":"Point"}
}