{
  "type": "Feature",
  "properties": {
    "addr:full": "15423 Neo Pkwy Cleveland OH 44128",
    "addr:postcode": "15423;44128",
    "addr:street": "Neo Pkwy",
    "iso:country": "US",
    "sg:address": "15423 Neo Pkwy",
    "sg:city": "Cleveland",
    "sg:classifiers": [
      {
        "category": "Retail",
        "subcategory": "Animal Services",
        "type": "Services"
      }
    ],
    "sg:phone": "+1 216 581 7200",
    "sg:postcode": "44128",
    "sg:province": "OH",
    "sg:tags": [
      "pet"
    ],
    "sg:website": "www.petsdx.com",
    "wof:name": "Petsdx Veterinary Imaging",
    "wof:placetype": "venue"
  },
  "geometry": {"coordinates":[-81.5733,41.427934],"type":"Point"}
}
