{
  "type": "Feature",
  "properties": {
    "addr:full":"2882 E Main St Columbus OH 43209",
    "addr:housenumber":"2882",
    "addr:postcode":"43209",
    "addr:street":"E Main St",
    "iso:country":"US",
    "sg:address":"2882 E Main St",
    "sg:city":"Columbus",
    "sg:classifiers":[
        {
            "category":"Restaurant",
            "type":"Food & Drink"
        }
    ],
    "sg:phone":"+1 614 231 8370",
    "sg:postcode":"43209",
    "sg:province":"OH",
    "wof:name":"Boston Soul",
    "wof:placetype":"venue"
},
  "geometry": {"coordinates":[-82.92196,39.956852],"type":"Point"}
}