{
  "type": "Feature",
  "properties": {
    "addr:full":"241 W Main St Van Wert OH 45891",
    "addr:housenumber":"241",
    "addr:postcode":"45891",
    "addr:street":"W Main St",
    "iso:country":"US",
    "sg:address":"241 W Main St",
    "sg:city":"Van Wert",
    "sg:classifiers":[
        {
            "category":"Recreation",
            "type":"Entertainment"
        }
    ],
    "sg:phone":"+1 419 238 0443",
    "sg:postcode":"45891",
    "sg:province":"OH",
    "sg:tags":[
        "y",
        "a",
        "c",
        "m"
    ],
    "sg:website":"www.vwymca.com",
    "wof:name":"YMCA",
    "wof:placetype":"venue"
},
  "geometry": {"coordinates":[-84.584784,40.869709],"type":"Point"}
}