{
  "type": "Feature",
  "properties": {
    "iso:country":"US",
    "sg:address":"11833 Prospect Rd",
    "sg:city":"Strongsville",
    "sg:classifiers":[
        {
            "category":"Manufacturing",
            "subcategory":"Tools & Machinery",
            "type":"Manufacturing & Wholesale Goods"
        }
    ],
    "sg:phone":"+1 440 572 0080",
    "sg:postcode":"44149",
    "sg:province":"OH",
    "sg:tags":[
        "machine",
        "shop",
        "job"
    ],
    "wof:name":"Continental Tool & Machine Inc",
    "wof:placetype":"venue"
},
  "geometry": {"coordinates":[-81.857696,41.320104],"type":"Point"}
}