{
  "type": "Feature",
  "properties": {
    "addr:full": "11833 Prospect Rd Strongsville OH 44149",
    "addr:housenumber": "11833",
    "addr:postcode": "44149",
    "addr:street": "Prospect Rd",
    "iso:country": "US",
    "sg:address": "11833 Prospect Rd",
    "sg:city": "Strongsville",
    "sg:classifiers": [
      {
        "category": "Manufacturing",
        "subcategory": "Tools \u0026 Machinery",
        "type": "Manufacturing \u0026 Wholesale Goods"
      }
    ],
    "sg:phone": "+1 440 572 0080",
    "sg:postcode": "44149",
    "sg:province": "OH",
    "sg:tags": [
      "machine",
      "shop",
      "job"
    ],
    "wof:name": "Continental Tool \u0026 Machine Inc",
    "wof:placetype": "venue"
  },
  "geometry": {"coordinates":[-81.857696,41.320104],"type":"Point"}
}
