{
  "type": "Feature",
  "properties": {
    "addr:full":"1799 May Rd Mogadore OH 44260",
    "addr:housenumber":"1799",
    "addr:postcode":"44260",
    "addr:street":"May Rd",
    "iso:country":"US",
    "sg:address":"1799 May Rd",
    "sg:city":"Mogadore",
    "sg:classifiers":[
        {
            "category":"Building & Trades",
            "subcategory":"Electrical",
            "type":"Services"
        }
    ],
    "sg:phone":"+1 330 628 1591",
    "sg:postcode":"44260",
    "sg:province":"OH",
    "sg:tags":[
        "electrical",
        "contractor"
    ],
    "wof:name":"Montecalvo Electric Inc",
    "wof:placetype":"venue"
},
  "geometry": {"coordinates":[-81.32021,41.037274],"type":"Point"}
}