{
  "type": "Feature",
  "properties": {
    "iso:country":"US",
    "sg:address":"377 E William St",
    "sg:city":"Delaware",
    "sg:classifiers":[
        {
            "category":"Health Services",
            "subcategory":"Doctor",
            "type":"Services"
        }
    ],
    "sg:phone":"+1 740 363 1304",
    "sg:postcode":"43015",
    "sg:province":"OH",
    "sg:tags":[
        "physician",
        "surgeon"
    ],
    "wof:name":"Delaware Family Practice",
    "wof:placetype":"venue"
},
  "geometry": {"coordinates":[-83.05083,40.297992],"type":"Point"}
}