{
  "type": "Feature",
  "properties": {
    "addr:full":"1636 Baum Hill Rd Chillicothe OH 45601",
    "addr:housenumber":"1636",
    "addr:postcode":"45601",
    "addr:street":"Baum Hill Rd",
    "iso:country":"US",
    "sg:address":"1636 Baum Hill Rd",
    "sg:city":"Chillicothe",
    "sg:classifiers":[
        {
            "category":"Manufacturing",
            "subcategory":"Lumber",
            "type":"Manufacturing & Wholesale Goods"
        }
    ],
    "sg:phone":"+1 740 626 7188",
    "sg:postcode":"45601",
    "sg:province":"OH",
    "sg:tags":[
        "company",
        "logging"
    ],
    "wof:name":"Robert Bray Logging",
    "wof:placetype":"venue"
},
  "geometry": {"coordinates":[-83.131676,39.254875],"type":"Point"}
}