{
  "type": "Feature",
  "properties": {
    "iso:country":"US",
    "sg:address":"10992 Ashburn Rd",
    "sg:city":"Wapakoneta",
    "sg:classifiers":[
        {
            "category":"Professional",
            "subcategory":"Advertising",
            "type":"Services"
        }
    ],
    "sg:phone":"+1 419 738 9727",
    "sg:postcode":"45895",
    "sg:province":"OH",
    "wof:name":"American Publishing Classified",
    "wof:placetype":"venue"
},
  "geometry": {"coordinates":[-84.088055,40.512124],"type":"Point"}
}