{
  "type": "Feature",
  "properties": {
    "addr:full": "19618 Paver-Barnes Rd Marysville OH 43040",
    "addr:housenumber": "19618",
    "addr:postcode": "43040",
    "addr:street": "Paver-Barnes Rd",
    "iso:country": "US",
    "sg:address": "19618 Paver-Barnes Rd",
    "sg:city": "Marysville",
    "sg:classifiers": [
      {
        "category": "Building \u0026 Trades",
        "subcategory": "Construction",
        "type": "Services"
      },
      {
        "category": "Wholesale",
        "subcategory": "Furniture",
        "type": "Manufacturing \u0026 Wholesale Goods"
      }
    ],
    "sg:phone": "+1 937 644 8548",
    "sg:postcode": "43040",
    "sg:province": "OH",
    "sg:tags": [
      "seating",
      "installation",
      "refurbishing",
      "company",
      "seat",
      "auditorium"
    ],
    "wof:name": "C \u0026 J Seating Inc",
    "wof:placetype": "venue"
  },
  "geometry": {"coordinates":[-83.442965,40.285821],"type":"Point"}
}
