{
  "type": "Feature",
  "properties": {
    "iso:country":"US",
    "sg:address":"6598 N Ridge Rd",
    "sg:city":"Madison",
    "sg:classifiers":[
        {
            "category":"Restaurant",
            "type":"Food & Drink"
        }
    ],
    "sg:phone":"+1 440 428 9102",
    "sg:postcode":"44057",
    "sg:province":"OH",
    "wof:name":"Wendy's",
    "wof:placetype":"venue"
},
  "geometry": {"coordinates":[-81.051609,41.802495],"type":"Point"}
}