{
  "type": "Feature",
  "properties": {
    "addr:full": "6598 N Ridge Rd Madison OH 44057",
    "addr:housenumber": "6598",
    "addr:postcode": "44057",
    "addr:street": "N Ridge Rd",
    "iso:country": "US",
    "sg:address": "6598 N Ridge Rd",
    "sg:city": "Madison",
    "sg:classifiers": [
      {
        "category": "Restaurant",
        "type": "Food \u0026 Drink"
      }
    ],
    "sg:phone": "+1 440 428 9102",
    "sg:postcode": "44057",
    "sg:province": "OH",
    "wof:name": "Wendy's",
    "wof:placetype": "venue"
  },
  "geometry": {"coordinates":[-81.051609,41.802495],"type":"Point"}
}
