{
  "type": "Feature",
  "properties": {
    "addr:full":"3435 Airborne Rd Wilmington OH 45177",
    "addr:housenumber":"3435",
    "addr:postcode":"45177",
    "addr:street":"Airborne Rd",
    "iso:country":"US",
    "sg:address":"3435 Airborne Rd",
    "sg:city":"Wilmington",
    "sg:classifiers":[
        {
            "category":"Shopping",
            "subcategory":"Clothing, Apparel, & Fashions",
            "type":"Retail Goods"
        }
    ],
    "sg:phone":"+1 937 383 2271",
    "sg:postcode":"45177",
    "sg:province":"OH",
    "sg:tags":[
        "family"
    ],
    "wof:name":"Cyberian Outpost Inc",
    "wof:placetype":"venue"
},
  "geometry": {"coordinates":[-83.772637,39.439246],"type":"Point"}
}