{
  "type": "Feature",
  "properties": {
    "addr:full": "14709 Ridge Rd Cleveland OH 44133",
    "addr:housenumber": "14709",
    "addr:postcode": "44133",
    "addr:street": "Ridge Rd",
    "iso:country": "US",
    "sg:address": "14709 Ridge Rd",
    "sg:city": "Cleveland",
    "sg:classifiers": [
      {
        "category": "Education",
        "subcategory": "School",
        "type": "Public Place"
      }
    ],
    "sg:phone": "+1 440 582 9120",
    "sg:postcode": "44133",
    "sg:province": "OH",
    "wof:name": "North Royalton Middle School",
    "wof:placetype": "venue"
  },
  "geometry": {"coordinates":[-81.734531,41.312967],"type":"Point"}
}
