{
  "type": "Feature",
  "properties": {
    "iso:country":"US",
    "sg:address":"201 Milan Ave",
    "sg:city":"Norwalk",
    "sg:classifiers":[
        {
            "category":"Restaurant",
            "type":"Food & Drink"
        }
    ],
    "sg:phone":"+1 419 668 8503",
    "sg:postcode":"44857",
    "sg:province":"OH",
    "sg:tags":[
        "eating"
    ],
    "wof:name":"Great Wall Chinese Kitchen",
    "wof:placetype":"venue"
},
  "geometry": {"coordinates":[-82.611965,41.257025],"type":"Point"}
}