{
  "type": "Feature",
  "properties": {
    "addr:full": "5381 Darrow Rd Hudson OH 44236",
    "addr:housenumber": "5381",
    "addr:postcode": "44236",
    "addr:street": "Darrow Rd",
    "iso:country": "US",
    "sg:address": "5381 Darrow Rd",
    "sg:city": "Hudson",
    "sg:classifiers": [
      {
        "category": "Home \u0026 Garden",
        "subcategory": "Household Appliances",
        "type": "Retail Goods"
      }
    ],
    "sg:phone": "+1 330 342 1139",
    "sg:postcode": "44236",
    "sg:province": "OH",
    "wof:name": "Viking \u0026 White Sewing Center",
    "wof:placetype": "venue"
  },
  "geometry": {"coordinates":[-81.440268,41.21023],"type":"Point"}
}
