{
  "type": "Feature",
  "properties": {
    "iso:country":"US",
    "sg:address":"5381 Darrow Rd",
    "sg:city":"Hudson",
    "sg:classifiers":[
        {
            "category":"Home & Garden",
            "subcategory":"Household Appliances",
            "type":"Retail Goods"
        }
    ],
    "sg:phone":"+1 330 342 1139",
    "sg:postcode":"44236",
    "sg:province":"OH",
    "wof:name":"Viking & White Sewing Center",
    "wof:placetype":"venue"
},
  "geometry": {"coordinates":[-81.440268,41.21023],"type":"Point"}
}