{
  "type": "Feature",
  "properties": {
    "iso:country":"US",
    "sg:address":"6180 Linworth Rd",
    "sg:city":"Columbus",
    "sg:classifiers":[
        {
            "category":"Health Services",
            "subcategory":"Chiropractor",
            "type":"Services"
        }
    ],
    "sg:phone":"+1 614 848 5211",
    "sg:postcode":"43085",
    "sg:province":"OH",
    "wof:name":"Worthington Chiropractic Ctr",
    "wof:placetype":"venue"
},
  "geometry": {"coordinates":[-83.049609,40.09268],"type":"Point"}
}