{
  "type": "Feature",
  "properties": {
    "iso:country":"US",
    "sg:address":"520 S Main St",
    "sg:city":"Akron",
    "sg:classifiers":[
        {
            "category":"Professional",
            "subcategory":"Computer Services",
            "type":"Services"
        }
    ],
    "sg:phone":"+1 330 535 1199",
    "sg:postcode":"44311",
    "sg:province":"OH",
    "sg:tags":[
        "internet"
    ],
    "sg:website":"www.textdata.com",
    "wof:name":"Lek Internet Svc",
    "wof:placetype":"venue"
},
  "geometry": {"coordinates":[-81.52443100000001,41.073244],"type":"Point"}
}