{
  "type": "Feature",
  "properties": {
    "addr:full":"3595 W Park Rd Cleveland OH 44111",
    "addr:housenumber":"3595",
    "addr:postcode":"44111",
    "addr:street":"W Park Rd",
    "iso:country":"US",
    "sg:address":"3595 W Park Rd",
    "sg:city":"Cleveland",
    "sg:classifiers":[
        {
            "category":"Organizations",
            "subcategory":"Religious Organization",
            "type":"Services"
        }
    ],
    "sg:phone":"+1 216 941 5707",
    "sg:postcode":"44111",
    "sg:province":"OH",
    "sg:tags":[
        "church"
    ],
    "wof:name":"Holy Resurrection Orthodox Chr",
    "wof:placetype":"venue"
},
  "geometry": {"coordinates":[-81.809445,41.455309],"type":"Point"}
}