{
  "type": "Feature",
  "properties": {
    "addr:full": "35411 State Rte 93 Hamden OH 45634",
    "addr:housenumber": "35411",
    "addr:postcode": "45634",
    "addr:street": "State Rte 93",
    "iso:country": "US",
    "sg:address": "35411 State Rte 93",
    "sg:city": "Hamden",
    "sg:classifiers": [
      {
        "category": "Home \u0026 Garden",
        "subcategory": "Carpets \u0026 Floor Coverings",
        "type": "Retail Goods"
      },
      {
        "category": "Manufacturing",
        "subcategory": "Lumber",
        "type": "Manufacturing \u0026 Wholesale Goods"
      }
    ],
    "sg:phone": "+1 740 596 4558",
    "sg:postcode": "45634",
    "sg:province": "OH",
    "sg:tags": [
      "hardwood",
      "mill",
      "material"
    ],
    "wof:name": "Twin Oak Forest Products Ltd",
    "wof:placetype": "venue"
  },
  "geometry": {"coordinates":[-82.482106,39.207607],"type":"Point"}
}
