{
  "type": "Feature",
  "properties": {
    "iso:country":"US",
    "sg:address":"35411 State Rte 93",
    "sg:city":"Hamden",
    "sg:classifiers":[
        {
            "category":"Home & Garden",
            "subcategory":"Carpets & Floor Coverings",
            "type":"Retail Goods"
        },
        {
            "category":"Manufacturing",
            "subcategory":"Lumber",
            "type":"Manufacturing & Wholesale Goods"
        }
    ],
    "sg:phone":"+1 740 596 4558",
    "sg:postcode":"45634",
    "sg:province":"OH",
    "sg:tags":[
        "hardwood",
        "mill",
        "material"
    ],
    "wof:name":"Twin Oak Forest Products Ltd",
    "wof:placetype":"venue"
},
  "geometry": {"coordinates":[-82.482106,39.207607],"type":"Point"}
}