{
  "type": "Feature",
  "properties": {
    "iso:country":"US",
    "sg:address":"26433 Kingston Pike",
    "sg:city":"Circleville",
    "sg:classifiers":[
        {
            "category":"Freight",
            "type":"Transportation"
        }
    ],
    "sg:phone":"+1 740 477 1093",
    "sg:postcode":"43113",
    "sg:province":"OH",
    "sg:tags":[
        "operator",
        "local",
        "trucking"
    ],
    "wof:name":"Reeves Ronald Jr & Karen",
    "wof:placetype":"venue"
},
  "geometry": {"coordinates":[-82.931842,39.548557],"type":"Point"}
}