{
  "type": "Feature",
  "properties": {
    "addr:full": "7376 Sylvan Dr Kent OH 44240",
    "addr:housenumber": "7376",
    "addr:postcode": "44240",
    "addr:street": "Sylvan Dr",
    "iso:country": "US",
    "sg:address": "7376 Sylvan Dr",
    "sg:city": "Kent",
    "sg:classifiers": [
      {
        "category": "Building \u0026 Trades",
        "subcategory": "Landscaping Services",
        "type": "Services"
      }
    ],
    "sg:phone": "+1 330 677 0615",
    "sg:postcode": "44240",
    "sg:province": "OH",
    "sg:tags": [
      "lawn",
      "snowplowing",
      "care"
    ],
    "wof:name": "Bower Lawn Care",
    "wof:placetype": "venue"
  },
  "geometry": {"coordinates":[-81.34714,41.190952],"type":"Point"}
}
