{
  "type": "Feature",
  "properties": {
    "addr:full": "1480 Enterprise Pkwy Twinsburg OH 44087",
    "addr:housenumber": "1480",
    "addr:postcode": "44087",
    "addr:street": "Enterprise Pkwy",
    "iso:country": "US",
    "sg:address": "1480 Enterprise Pkwy",
    "sg:city": "Twinsburg",
    "sg:classifiers": [
      {
        "category": "Home \u0026 Garden",
        "subcategory": "Garden Supply",
        "type": "Retail Goods"
      }
    ],
    "sg:phone": "+1 330 425 2887",
    "sg:postcode": "44087",
    "sg:province": "OH",
    "sg:tags": [
      "sprinkler"
    ],
    "wof:name": "Reserve Irrigation",
    "wof:placetype": "venue"
  },
  "geometry": {"coordinates":[-81.465621,41.291539],"type":"Point"}
}
