{
  "type": "Feature",
  "properties": {
    "iso:country":"US",
    "sg:address":"1480 Enterprise Pkwy",
    "sg:city":"Twinsburg",
    "sg:classifiers":[
        {
            "category":"Home & Garden",
            "subcategory":"Garden Supply",
            "type":"Retail Goods"
        }
    ],
    "sg:phone":"+1 330 425 2887",
    "sg:postcode":"44087",
    "sg:province":"OH",
    "sg:tags":[
        "sprinkler"
    ],
    "wof:name":"Reserve Irrigation",
    "wof:placetype":"venue"
},
  "geometry": {"coordinates":[-81.465621,41.291539],"type":"Point"}
}