{
  "type": "Feature",
  "properties": {
    "iso:country":"US",
    "sg:address":"1715 John St",
    "sg:city":"Cincinnati",
    "sg:classifiers":[
        {
            "category":"Food & Beverages",
            "subcategory":"Groceries & Convenience Stores",
            "type":"Retail Goods"
        }
    ],
    "sg:phone":"+1 513 241 0761",
    "sg:postcode":"45214",
    "sg:province":"OH",
    "sg:tags":[
        "grocer"
    ],
    "wof:name":"Save Way Super Market Inc",
    "wof:placetype":"venue"
},
  "geometry": {"coordinates":[-84.524637,39.114689],"type":"Point"}
}