{
  "type": "Feature",
  "properties": {
    "iso:country":"US",
    "sg:address":"220 State St",
    "sg:city":"Conneaut",
    "sg:classifiers":[
        {
            "category":"Autos & Motor Vehicles",
            "subcategory":"Fuel & Gas Station",
            "type":"Retail Goods"
        }
    ],
    "sg:phone":"+1 440 599 6315",
    "sg:postcode":"44030",
    "sg:province":"OH",
    "sg:tags":[
        "oil"
    ],
    "wof:name":"Conneaut Clark Gas Station",
    "wof:placetype":"venue"
},
  "geometry": {"coordinates":[-80.55450500000001,41.944226],"type":"Point"}
}