{
  "type": "Feature",
  "properties": {
    "addr:full":"700 2nd St SW Warren OH 44483",
    "addr:housenumber":"700",
    "addr:postcode":"44483",
    "addr:street":"2Nd St Sw",
    "iso:country":"US",
    "sg:address":"700 2nd St SW",
    "sg:city":"Warren",
    "sg:classifiers":[
        {
            "category":"Banks & Credit Unions",
            "subcategory":"Investment Brokerage",
            "type":"Services"
        }
    ],
    "sg:phone":"+1 330 393 1567",
    "sg:postcode":"44483",
    "sg:province":"OH",
    "sg:tags":[
        "stock",
        "bond"
    ],
    "sg:website":"www.butlerwick.com",
    "wof:name":"Butler Wick & Co",
    "wof:placetype":"venue"
},
  "geometry": {"coordinates":[-80.827907,41.224373],"type":"Point"}
}