{
  "type": "Feature",
  "properties": {
    "addr:full":"405 Moxahala Ave Zanesville OH 43701",
    "addr:housenumber":"405",
    "addr:postcode":"43701",
    "addr:street":"Moxahala Ave",
    "iso:country":"US",
    "sg:address":"405 Moxahala Ave",
    "sg:city":"Zanesville",
    "sg:classifiers":[
        {
            "category":"Building & Trades",
            "subcategory":"Construction",
            "type":"Services"
        }
    ],
    "sg:phone":"+1 740 455 9121",
    "sg:postcode":"43701",
    "sg:province":"OH",
    "sg:tags":[
        "specializing",
        "new",
        "commercial",
        "contractor"
    ],
    "wof:name":"C Mitzel Co",
    "wof:placetype":"venue"
},
  "geometry": {"coordinates":[-82.005775,39.932903],"type":"Point"}
}