{
  "type": "Feature",
  "properties": {
    "addr:full":"6811 Dublin Center Dr Dublin OH 43017",
    "addr:housenumber":"6811",
    "addr:postcode":"43017",
    "addr:street":"Dublin Center Dr",
    "iso:country":"US",
    "sg:address":"6811 Dublin Center Dr",
    "sg:city":"Dublin",
    "sg:classifiers":[
        {
            "category":"Wholesale",
            "subcategory":"Sporting Goods",
            "type":"Manufacturing & Wholesale Goods"
        }
    ],
    "sg:phone":"+1 614 336 1332",
    "sg:postcode":"43017",
    "sg:province":"OH",
    "wof:name":"Laxworld Ohio",
    "wof:placetype":"venue"
},
  "geometry": {"coordinates":[-83.093915,40.105147],"type":"Point"}
}