{
  "type": "Feature",
  "properties": {
    "addr:full": "6145 Columbus Pike Lewis Center OH 43035",
    "addr:housenumber": "6145",
    "addr:postcode": "43035",
    "addr:street": "Columbus Pike",
    "iso:country": "US",
    "sg:address": "6145 Columbus Pike",
    "sg:city": "Lewis Center",
    "sg:classifiers": [
      {
        "category": "Manufacturing",
        "subcategory": "Printing",
        "type": "Manufacturing \u0026 Wholesale Goods"
      }
    ],
    "sg:phone": "+1 740 548 6130",
    "sg:postcode": "43035",
    "sg:province": "OH",
    "sg:tags": [
      "directory",
      "publishing"
    ],
    "wof:name": "Dickman Directories Inc",
    "wof:placetype": "venue"
  },
  "geometry": {"coordinates":[-83.030297,40.205511],"type":"Point"}
}
