{
  "type": "Feature",
  "properties": {
    "addr:full": "12607 Monroe Rd Leesburg OH 45135",
    "addr:housenumber": "12607",
    "addr:postcode": "45135",
    "addr:street": "Monroe Rd",
    "iso:country": "US",
    "sg:address": "12607 Monroe Rd",
    "sg:city": "Leesburg",
    "sg:classifiers": [
      {
        "category": "Shopping",
        "subcategory": "Discount \u0026 Variety Stores",
        "type": "Retail Goods"
      }
    ],
    "sg:phone": "+1 937 780 2613",
    "sg:postcode": "45135",
    "sg:province": "OH",
    "sg:tags": [
      "merchandise",
      "general"
    ],
    "wof:name": "Leesburg Modern Sales",
    "wof:placetype": "venue"
  },
  "geometry": {"coordinates":[-83.501999,39.351475],"type":"Point"}
}
