{
  "type": "Feature",
  "properties": {
    "addr:full": "29 N Portage St Doylestown OH 44230",
    "addr:housenumber": "29",
    "addr:postcode": "44230",
    "addr:street": "N Portage St",
    "iso:country": "US",
    "sg:address": "29 N Portage St",
    "sg:city": "Doylestown",
    "sg:classifiers": [
      {
        "category": "Professional",
        "subcategory": "Lawyer \u0026 Legal Services",
        "type": "Services"
      }
    ],
    "sg:phone": "+1 330 658 3755",
    "sg:postcode": "44230",
    "sg:province": "OH",
    "sg:tags": [
      "attorney"
    ],
    "wof:name": "Lynn A Beaumont",
    "wof:placetype": "venue"
  },
  "geometry": {"coordinates":[-81.697143,40.9692],"type":"Point"}
}
