{
  "type": "Feature",
  "properties": {
    "addr:full":"9446 Co Rd G Bryan OH 43506",
    "addr:housenumber":"9446",
    "addr:postcode":"43506",
    "addr:street":"Co Rd",
    "iso:country":"US",
    "sg:address":"9446 Co Rd G",
    "sg:city":"Bryan",
    "sg:phone":"+1 419 636 5308",
    "sg:postcode":"43506",
    "sg:province":"OH",
    "sg:tags":[
        "farm",
        "soybean"
    ],
    "wof:name":"Geiselman Farms",
    "wof:placetype":"venue"
},
  "geometry": {"coordinates":[-84.650687,41.513613],"type":"Point"}
}