{
  "type": "Feature",
  "properties": {
    "addr:full": "101 Peters Ave Troy OH 45373",
    "addr:housenumber": "101",
    "addr:postcode": "45373",
    "addr:street": "Peters Ave",
    "iso:country": "US",
    "sg:address": "101 Peters Ave",
    "sg:city": "Troy",
    "sg:classifiers": [
      {
        "category": "Government",
        "subcategory": "Office",
        "type": "Public Place"
      }
    ],
    "sg:phone": "+1 937 335 8009",
    "sg:postcode": "45373",
    "sg:province": "OH",
    "sg:tags": [
      "national",
      "security"
    ],
    "wof:name": "US Defense Supply Agency",
    "wof:placetype": "venue"
  },
  "geometry": {"coordinates":[-84.209463,40.031792],"type":"Point"}
}
