{
  "type": "Feature",
  "properties": {
    "addr:full": "124 High St Fredericktown OH 43019",
    "addr:housenumber": "124",
    "addr:postcode": "43019",
    "addr:street": "High St",
    "iso:country": "US",
    "sg:address": "124 High St",
    "sg:city": "Fredericktown",
    "sg:classifiers": [
      {
        "category": "Retail",
        "subcategory": "Auto Repair",
        "type": "Services"
      },
      {
        "category": "Manufacturing",
        "subcategory": "Rubber \u0026 Plastics",
        "type": "Manufacturing \u0026 Wholesale Goods"
      }
    ],
    "sg:phone": "+1 740 694 1019",
    "sg:postcode": "43019",
    "sg:province": "OH",
    "sg:tags": [
      "automobile",
      "product",
      "mfg",
      "restoration",
      "classic"
    ],
    "wof:name": "Bumpers International Inc",
    "wof:placetype": "venue"
  },
  "geometry": {"coordinates":[-82.546923,40.484496],"type":"Point"}
}
