{
  "type": "Feature",
  "properties": {
    "iso:country":"US",
    "sg:address":"328 Jamestown Rd",
    "sg:city":"South Charleston",
    "sg:classifiers":[
        {
            "category":"Organizations",
            "subcategory":"Religious Organization",
            "type":"Services"
        }
    ],
    "sg:phone":"+1 937 462 8654",
    "sg:postcode":"45368",
    "sg:province":"OH",
    "sg:tags":[
        "church"
    ],
    "wof:name":"International Pentecostal Chr",
    "wof:placetype":"venue"
},
  "geometry": {"coordinates":[-83.641134,39.820449],"type":"Point"}
}