{
  "type": "Feature",
  "properties": {
    "iso:country":"US",
    "sg:address":"201 Riverside Dr",
    "sg:city":"Dayton",
    "sg:classifiers":[
        {
            "category":"Real Estate",
            "subcategory":"Real Estate Agent",
            "type":"Services"
        }
    ],
    "sg:phone":"+1 937 223 4543",
    "sg:postcode":"45405",
    "sg:province":"OH",
    "wof:name":"Midwest Brokers & Assoc Rltrs",
    "wof:placetype":"venue"
},
  "geometry": {"coordinates":[-84.19114399999999,39.769807],"type":"Point"}
}