{
  "type": "Feature",
  "properties": {
    "addr:full": "26 W Torrence Rd Columbus OH 43214",
    "addr:housenumber": "26",
    "addr:postcode": "43214",
    "addr:street": "W Torrence Rd",
    "iso:country": "US",
    "sg:address": "26 W Torrence Rd",
    "sg:city": "Columbus",
    "sg:classifiers": [
      {
        "category": "Professional",
        "subcategory": "Management \u0026 Consulting",
        "type": "Services"
      }
    ],
    "sg:phone": "+1 614 263 7624",
    "sg:postcode": "43214",
    "sg:province": "OH",
    "sg:tags": [
      "marketing",
      "program"
    ],
    "wof:name": "P B Tech",
    "wof:placetype": "venue"
  },
  "geometry": {"coordinates":[-83.017278,40.035209],"type":"Point"}
}
