{
  "type": "Feature",
  "properties": {
    "iso:country":"US",
    "sg:address":"321 Outerbelt St",
    "sg:city":"Columbus",
    "sg:classifiers":[
        {
            "category":"Professional",
            "subcategory":"Art Services",
            "type":"Services"
        }
    ],
    "sg:phone":"+1 614 860 0088",
    "sg:postcode":"43213",
    "sg:province":"OH",
    "sg:tags":[
        "photographer"
    ],
    "wof:name":"Paul Poplis Photography",
    "wof:placetype":"venue"
},
  "geometry": {"coordinates":[-82.830578,39.987907],"type":"Point"}
}