{
  "type": "Feature",
  "properties": {
    "addr:full": "1425 Sycamore Line Sandusky OH 44870",
    "addr:housenumber": "1425",
    "addr:postcode": "44870",
    "addr:street": "Sycamore Line",
    "iso:country": "US",
    "sg:address": "1425 Sycamore Line",
    "sg:city": "Sandusky",
    "sg:classifiers": [
      {
        "category": "Autos \u0026 Motor Vehicles",
        "subcategory": "Fuel \u0026 Gas Station",
        "type": "Retail Goods"
      }
    ],
    "sg:phone": "+1 419 627 0567",
    "sg:postcode": "44870",
    "sg:province": "OH",
    "sg:tags": [
      "oil"
    ],
    "wof:name": "Gastown",
    "wof:placetype": "venue"
  },
  "geometry": {"coordinates":[-82.697546,41.445883],"type":"Point"}
}
