{
  "type": "Feature",
  "properties": {
    "iso:country":"US",
    "sg:address":"1425 Sycamore Line",
    "sg:city":"Sandusky",
    "sg:classifiers":[
        {
            "category":"Autos & Motor Vehicles",
            "subcategory":"Fuel & Gas Station",
            "type":"Retail Goods"
        }
    ],
    "sg:phone":"+1 419 627 0567",
    "sg:postcode":"44870",
    "sg:province":"OH",
    "sg:tags":[
        "oil"
    ],
    "wof:name":"Gastown",
    "wof:placetype":"venue"
},
  "geometry": {"coordinates":[-82.697546,41.445883],"type":"Point"}
}