{
  "type": "Feature",
  "properties": {
    "addr:full":"5811 Canal Rd Cleveland OH 44125",
    "addr:housenumber":"5811",
    "addr:postcode":"44125",
    "addr:street":"Canal Rd",
    "iso:country":"US",
    "sg:address":"5811 Canal Rd",
    "sg:city":"Cleveland",
    "sg:classifiers":[
        {
            "category":"Banks & Credit Unions",
            "subcategory":"Bank",
            "type":"Services"
        }
    ],
    "sg:phone":"+1 216 750 2331",
    "sg:postcode":"44125",
    "sg:province":"OH",
    "sg:tags":[
        "loan",
        "broker"
    ],
    "wof:name":"Multi-Fund Inc",
    "wof:placetype":"venue"
},
  "geometry": {"coordinates":[-81.626918,41.405043],"type":"Point"}
}