{
  "type": "Feature",
  "properties": {
    "iso:country":"US",
    "sg:address":"1290 W Market St",
    "sg:city":"Akron",
    "sg:classifiers":[
        {
            "category":"Education",
            "subcategory":"School",
            "type":"Public Place"
        }
    ],
    "sg:phone":"+1 330 864 7210",
    "sg:postcode":"44313",
    "sg:province":"OH",
    "sg:tags":[
        "religious"
    ],
    "wof:name":"Our Lady Of The Elms Elem Schl",
    "wof:placetype":"venue"
},
  "geometry": {"coordinates":[-81.556287,41.103385],"type":"Point"}
}