{
  "type": "Feature",
  "properties": {
    "addr:full": "12090 Pheasant Ct Chardon OH 44024",
    "addr:housenumber": "12090",
    "addr:postcode": "44024",
    "addr:street": "Pheasant Ct",
    "iso:country": "US",
    "sg:address": "12090 Pheasant Ct",
    "sg:city": "Chardon",
    "sg:classifiers": [
      {
        "category": "Building \u0026 Trades",
        "subcategory": "Construction",
        "type": "Services"
      }
    ],
    "sg:phone": "+1 216 346 8783",
    "sg:postcode": "44024",
    "sg:province": "OH",
    "sg:tags": [
      "home",
      "builder"
    ],
    "wof:name": "Dream Home Construction",
    "wof:placetype": "venue"
  },
  "geometry": {"coordinates":[-81.220604,41.541073],"type":"Point"}
}
