{
  "type": "Feature",
  "properties": {
    "addr:full":"4660 Twp Rd 115 Mc Comb OH 45858",
    "addr:postcode":"4660;45858",
    "addr:street":"Twp Rd 115",
    "iso:country":"US",
    "sg:address":"4660 Twp Rd 115",
    "sg:city":"Mc Comb",
    "sg:phone":"+1 419 293 3393",
    "sg:postcode":"45858",
    "sg:province":"OH",
    "sg:tags":[
        "farm",
        "corn",
        "wheat",
        "soybean"
    ],
    "wof:name":"Kenneth Scheele",
    "wof:placetype":"venue"
},
  "geometry": {"coordinates":[-83.87499099999999,41.10067],"type":"Point"}
}