{
  "type": "Feature",
  "properties": {
    "iso:country":"US",
    "sg:address":"4164 W 8th St",
    "sg:city":"Cincinnati",
    "sg:classifiers":[
        {
            "category":"Retail",
            "subcategory":"Funeral Services",
            "type":"Services"
        }
    ],
    "sg:phone":"+1 513 251 9700",
    "sg:postcode":"45205",
    "sg:province":"OH",
    "sg:tags":[
        "director"
    ],
    "wof:name":"Meyer Ralph & Deters Funeral",
    "wof:placetype":"venue"
},
  "geometry": {"coordinates":[-84.58929500000001,39.107552],"type":"Point"}
}