{
  "type": "Feature",
  "properties": {
    "addr:full": "7125 Beechmont Ave Cincinnati OH 45230",
    "addr:housenumber": "7125",
    "addr:postcode": "45230",
    "addr:street": "Beechmont Ave",
    "iso:country": "US",
    "sg:address": "7125 Beechmont Ave",
    "sg:city": "Cincinnati",
    "sg:classifiers": [
      {
        "category": "Freight",
        "type": "Transportation"
      }
    ],
    "sg:phone": "+1 513 232 1540",
    "sg:postcode": "45230",
    "sg:province": "OH",
    "sg:tags": [
      "operator",
      "local",
      "trucking"
    ],
    "wof:name": "Longrun Inc",
    "wof:placetype": "venue"
  },
  "geometry": {"coordinates":[-84.36219,39.073663],"type":"Point"}
}
