{
  "type": "Feature",
  "properties": {
    "addr:full": "17386 State Rte 2 Wauseon OH 43567",
    "addr:housenumber": "17386",
    "addr:postcode": "43567",
    "addr:street": "State Rte 2",
    "iso:country": "US",
    "sg:address": "17386 State Rte 2",
    "sg:city": "Wauseon",
    "sg:classifiers": [
      {
        "category": "Autos \u0026 Motor Vehicles",
        "subcategory": "Auto Supplies",
        "type": "Retail Goods"
      },
      {
        "category": "Wholesale",
        "subcategory": "Auto Parts",
        "type": "Manufacturing \u0026 Wholesale Goods"
      }
    ],
    "sg:phone": "+1 419 335 7010",
    "sg:postcode": "43567",
    "sg:province": "OH",
    "sg:tags": [
      "tire"
    ],
    "sg:website": "www.millertire.com",
    "wof:name": "M E Miller Tire Co",
    "wof:placetype": "venue"
  },
  "geometry": {"coordinates":[-84.19941,41.543799],"type":"Point"}
}
