{
  "type": "Feature",
  "properties": {
    "iso:country":"US",
    "sg:address":"17386 State Rte 2",
    "sg:city":"Wauseon",
    "sg:classifiers":[
        {
            "category":"Autos & Motor Vehicles",
            "subcategory":"Auto Supplies",
            "type":"Retail Goods"
        },
        {
            "category":"Wholesale",
            "subcategory":"Auto Parts",
            "type":"Manufacturing & Wholesale Goods"
        }
    ],
    "sg:phone":"+1 419 335 7010",
    "sg:postcode":"43567",
    "sg:province":"OH",
    "sg:tags":[
        "tire"
    ],
    "sg:website":"www.millertire.com",
    "wof:name":"M E Miller Tire Co",
    "wof:placetype":"venue"
},
  "geometry": {"coordinates":[-84.19941,41.543799],"type":"Point"}
}