{
  "type": "Feature",
  "properties": {
    "addr:full": "5262 Cleveland Ave Columbus OH 43231",
    "addr:housenumber": "5262",
    "addr:postcode": "43231",
    "addr:street": "Cleveland Ave",
    "iso:country": "US",
    "sg:address": "5262 Cleveland Ave",
    "sg:city": "Columbus",
    "sg:classifiers": [
      {
        "category": "Shopping",
        "subcategory": "Department Store",
        "type": "Retail Goods"
      }
    ],
    "sg:phone": "+1 614 899 1290",
    "sg:postcode": "43231",
    "sg:province": "OH",
    "wof:name": "Kiddy Fashions \u0026 Avon",
    "wof:placetype": "venue"
  },
  "geometry": {"coordinates":[-82.95167,40.078211],"type":"Point"}
}
