{
  "type": "Feature",
  "properties": {
    "addr:full": "1029 Hickory Rd Heath OH 43056",
    "addr:housenumber": "1029",
    "addr:postcode": "43056",
    "addr:street": "Hickory Rd",
    "iso:country": "US",
    "sg:address": "1029 Hickory Rd",
    "sg:city": "Heath",
    "sg:classifiers": [
      {
        "category": "Arts \u0026 Performance",
        "subcategory": "Theater",
        "type": "Entertainment"
      }
    ],
    "sg:phone": "+1 740 788 9546",
    "sg:postcode": "43056",
    "sg:province": "OH",
    "sg:tags": [
      "live",
      "music"
    ],
    "wof:name": "D J Jay Productions",
    "wof:placetype": "venue"
  },
  "geometry": {"coordinates":[-82.380577,40.021668],"type":"Point"}
}
