{
  "type": "Feature",
  "properties": {
    "addr:full": "4140 Tuller Rd Dublin OH 43017",
    "addr:housenumber": "4140",
    "addr:postcode": "43017",
    "addr:street": "Tuller Rd",
    "iso:country": "US",
    "sg:address": "4140 Tuller Rd",
    "sg:city": "Dublin",
    "sg:classifiers": [
      {
        "category": "Wholesale",
        "subcategory": "Medical Equipment \u0026 Supplies",
        "type": "Manufacturing \u0026 Wholesale Goods"
      },
      {
        "category": "Manufacturing",
        "subcategory": "Tools \u0026 Machinery",
        "type": "Manufacturing \u0026 Wholesale Goods"
      }
    ],
    "sg:phone": "+1 614 791 9141",
    "sg:postcode": "43017",
    "sg:province": "OH",
    "sg:tags": [
      "dental"
    ],
    "wof:name": "Patterson Dental",
    "wof:placetype": "venue"
  },
  "geometry": {"coordinates":[-83.09257,40.106909],"type":"Point"}
}
