{
  "type": "Feature",
  "properties": {
    "addr:full":"1436 Krebs Dr Newark OH 43055",
    "addr:housenumber":"1436",
    "addr:postcode":"43055",
    "addr:street":"Krebs Dr",
    "iso:country":"US",
    "sg:address":"1436 Krebs Dr",
    "sg:city":"Newark",
    "sg:classifiers":[
        {
            "category":"Building & Trades",
            "subcategory":"Construction",
            "type":"Services"
        }
    ],
    "sg:phone":"+1 740 366 4094",
    "sg:postcode":"43055",
    "sg:province":"OH",
    "sg:tags":[
        "residential",
        "contractor"
    ],
    "wof:name":"Jay Crouch Construction",
    "wof:placetype":"venue"
},
  "geometry": {"coordinates":[-82.45339,40.070331],"type":"Point"}
}