{
  "type": "Feature",
  "properties": {
    "addr:full": "14009 Puritas Ave Cleveland OH 44135",
    "addr:postcode": "14009;44135",
    "addr:street": "Puritas Ave",
    "iso:country": "US",
    "sg:address": "14009 Puritas Ave",
    "sg:city": "Cleveland",
    "sg:classifiers": [
      {
        "category": "Personal",
        "subcategory": "Barber",
        "type": "Services"
      }
    ],
    "sg:phone": "+1 216 889 1780",
    "sg:postcode": "44135",
    "sg:province": "OH",
    "wof:name": "Shear Styles Barber Shop",
    "wof:placetype": "venue"
  },
  "geometry": {"coordinates":[-81.792036,41.433468],"type":"Point"}
}
