{
  "type": "Feature",
  "properties": {
    "addr:full":"9615 Summers Rd Adamsville OH 43802",
    "addr:housenumber":"9615",
    "addr:postcode":"43802",
    "addr:street":"Summers Rd",
    "iso:country":"US",
    "sg:address":"9615 Summers Rd",
    "sg:city":"Adamsville",
    "sg:classifiers":[
        {
            "category":"Farming",
            "subcategory":"Livestock Farm",
            "type":"Manufacturing & Wholesale Goods"
        }
    ],
    "sg:phone":"+1 740 796 3647",
    "sg:postcode":"43802",
    "sg:province":"OH",
    "sg:tags":[
        "field",
        "cattle",
        "beef",
        "feedlot",
        "cr"
    ],
    "wof:name":"Willard Hatfield",
    "wof:placetype":"venue"
},
  "geometry": {"coordinates":[-81.893179,40.094441],"type":"Point"}
}