{
  "type": "Feature",
  "properties": {
    "addr:full": "17400 Lorain Ave Cleveland OH 44111",
    "addr:housenumber": "17400",
    "addr:postcode": "44111",
    "addr:street": "Lorain Ave",
    "iso:country": "US",
    "sg:address": "17400 Lorain Ave",
    "sg:city": "Cleveland",
    "sg:classifiers": [
      {
        "category": "Shopping",
        "subcategory": "Pharmacy",
        "type": "Retail Goods"
      }
    ],
    "sg:phone": "+1 216 671 3100",
    "sg:postcode": "44111",
    "sg:province": "OH",
    "wof:name": "Medic Drug",
    "wof:placetype": "venue"
  },
  "geometry": {"coordinates":[-81.818909,41.450105],"type":"Point"}
}
