{
  "type": "Feature",
  "properties": {
    "addr:full": "3747 Watkins Rd Medina OH 44256",
    "addr:housenumber": "3747",
    "addr:postcode": "44256",
    "addr:street": "Watkins Rd",
    "iso:country": "US",
    "sg:address": "3747 Watkins Rd",
    "sg:city": "Medina",
    "sg:classifiers": [
      {
        "category": "Professional",
        "type": "Services"
      }
    ],
    "sg:phone": "+1 330 725 4268",
    "sg:postcode": "44256",
    "sg:province": "OH",
    "wof:name": "3b G Company LLC",
    "wof:placetype": "venue"
  },
  "geometry": {"coordinates":[-81.868109,41.179501],"type":"Point"}
}
