{
  "type": "Feature",
  "properties": {
    "addr:full":"212 E 8th St Cincinnati OH 45202",
    "addr:housenumber":"212",
    "addr:postcode":"45202",
    "addr:street":"E 8Th St",
    "iso:country":"US",
    "sg:address":"212 E 8th St",
    "sg:city":"Cincinnati",
    "sg:classifiers":[
        {
            "category":"Professional",
            "type":"Services"
        }
    ],
    "sg:phone":"+1 513 621 2086",
    "sg:postcode":"45202",
    "sg:province":"OH",
    "wof:name":"Archdiosese Of Cincinnati",
    "wof:placetype":"venue"
},
  "geometry": {"coordinates":[-84.509038,39.105219],"type":"Point"}
}