{
  "type": "Feature",
  "properties": {
    "iso:country":"US",
    "sg:address":"4440 Kennard Ct",
    "sg:city":"Cleveland",
    "sg:classifiers":[
        {
            "category":"Health Services",
            "subcategory":"Doctor",
            "type":"Services"
        }
    ],
    "sg:phone":"+1 216 881 2504",
    "sg:postcode":"44104",
    "sg:province":"OH",
    "sg:tags":[
        "clinic",
        "medical",
        "outpatient",
        "specialty"
    ],
    "wof:name":"Miracle Vlg Ctr For Cmnty Hlth",
    "wof:placetype":"venue"
},
  "geometry": {"coordinates":[-81.65584699999999,41.491953],"type":"Point"}
}