{
  "type": "Feature",
  "properties": {
    "addr:full": "40 Greenwood Ln Springboro OH 45066",
    "addr:housenumber": "40",
    "addr:postcode": "45066",
    "addr:street": "Greenwood Ln",
    "iso:country": "US",
    "sg:address": "40 Greenwood Ln",
    "sg:city": "Springboro",
    "sg:classifiers": [
      {
        "category": "Autos \u0026 Motor Vehicles",
        "subcategory": "Automobile Sales",
        "type": "Retail Goods"
      }
    ],
    "sg:phone": "+1 937 743 4433",
    "sg:postcode": "45066",
    "sg:province": "OH",
    "sg:tags": [
      "cart"
    ],
    "wof:name": "Precision Karting Products",
    "wof:placetype": "venue"
  },
  "geometry": {"coordinates":[-84.264626,39.564507],"type":"Point"}
}
