{
  "type": "Feature",
  "properties": {
    "iso:country":"US",
    "sg:address":"40 Greenwood Ln",
    "sg:city":"Springboro",
    "sg:classifiers":[
        {
            "category":"Autos & Motor Vehicles",
            "subcategory":"Automobile Sales",
            "type":"Retail Goods"
        }
    ],
    "sg:phone":"+1 937 743 4433",
    "sg:postcode":"45066",
    "sg:province":"OH",
    "sg:tags":[
        "cart"
    ],
    "wof:name":"Precision Karting Products",
    "wof:placetype":"venue"
},
  "geometry": {"coordinates":[-84.26462600000001,39.564507],"type":"Point"}
}