{
  "type": "Feature",
  "properties": {
    "iso:country":"US",
    "sg:address":"840 Champlain St",
    "sg:city":"Toledo",
    "sg:classifiers":[
        {
            "category":"Manufacturing",
            "subcategory":"Metals",
            "type":"Manufacturing & Wholesale Goods"
        }
    ],
    "sg:phone":"+1 419 243 2196",
    "sg:postcode":"43604",
    "sg:province":"OH",
    "sg:tags":[
        "sheet",
        "fabrication",
        "custom"
    ],
    "wof:name":"Kuhlman Engineering Co",
    "wof:placetype":"venue"
},
  "geometry": {"coordinates":[-83.532301,41.661421],"type":"Point"}
}