{
  "type": "Feature",
  "properties": {
    "iso:country":"US",
    "sg:address":"26940 Pumpkin Ridge Rd",
    "sg:city":"Mc Arthur",
    "sg:classifiers":[
        {
            "category":"Manufacturing",
            "subcategory":"Lumber",
            "type":"Manufacturing & Wholesale Goods"
        }
    ],
    "sg:phone":"+1 740 596 4273",
    "sg:postcode":"45654",
    "sg:province":"OH",
    "sg:tags":[
        "planing",
        "mills",
        "sawmill"
    ],
    "wof:name":"J & J Wood",
    "wof:placetype":"venue"
},
  "geometry": {"coordinates":[-82.439762,39.33547],"type":"Point"}
}