{
  "type": "Feature",
  "properties": {
    "iso:country":"US",
    "sg:address":"5109 Chipman Dr",
    "sg:city":"Columbus",
    "sg:classifiers":[
        {
            "category":"Building & Trades",
            "subcategory":"Plumbing",
            "type":"Services"
        }
    ],
    "sg:phone":"+1 614 834 1680",
    "sg:postcode":"43232",
    "sg:province":"OH",
    "sg:tags":[
        "conditioning",
        "air",
        "system",
        "contractor"
    ],
    "wof:name":"RHC Robinette Heating & Clng",
    "wof:placetype":"venue"
},
  "geometry": {"coordinates":[-82.87002699999999,39.898698],"type":"Point"}
}