{
  "type": "Feature",
  "properties": {
    "addr:full": "7735 State Rte 37 Sunbury OH 43074",
    "addr:housenumber": "7735",
    "addr:postcode": "43074",
    "addr:street": "State Rte 37",
    "iso:country": "US",
    "sg:address": "7735 State Rte 37",
    "sg:city": "Sunbury",
    "sg:classifiers": [
      {
        "category": "Communications",
        "type": "Services"
      }
    ],
    "sg:phone": "+1 740 965 5915",
    "sg:postcode": "43074",
    "sg:province": "OH",
    "sg:tags": [
      "carrier"
    ],
    "wof:name": "Flying J Communications",
    "wof:placetype": "venue"
  },
  "geometry": {"coordinates":[-82.909946,40.265598],"type":"Point"}
}
