{
  "type": "Feature",
  "properties": {
    "addr:full":"4914 State Rte 276 Batavia OH 45103",
    "addr:housenumber":"4914",
    "addr:postcode":"45103",
    "addr:street":"State Rte 276",
    "iso:country":"US",
    "sg:address":"4914 State Rte 276",
    "sg:city":"Batavia",
    "sg:classifiers":[
        {
            "category":"Building & Trades",
            "subcategory":"Construction",
            "type":"Services"
        }
    ],
    "sg:phone":"+1 513 732 0160",
    "sg:postcode":"45103",
    "sg:province":"OH",
    "sg:tags":[
        "excavation",
        "contractor"
    ],
    "wof:name":"Gilkinson & Sons Excvtg LLC",
    "wof:placetype":"venue"
},
  "geometry": {"coordinates":[-84.13248299999999,39.106103],"type":"Point"}
}