{
  "type": "Feature",
  "properties": {
    "iso:country":"US",
    "sg:address":"17826 Twp Rd 56",
    "sg:city":"Bluffton",
    "sg:phone":"+1 419 477 5131",
    "sg:postcode":"45817",
    "sg:province":"OH",
    "sg:tags":[
        "farm",
        "field",
        "crop"
    ],
    "wof:name":"Kenneth Hamilton",
    "wof:placetype":"venue"
},
  "geometry": {"coordinates":[-83.804177,40.90997],"type":"Point"}
}