{
  "type": "Feature",
  "properties": {
    "iso:country":"US",
    "sg:address":"3619 Park East Dr",
    "sg:city":"Cleveland",
    "sg:classifiers":[
        {
            "category":"Health Services",
            "subcategory":"Health Practitioner",
            "type":"Services"
        }
    ],
    "sg:phone":"+1 216 595 8900",
    "sg:postcode":"44122",
    "sg:province":"OH",
    "sg:tags":[
        "psychologist"
    ],
    "wof:name":"Neuropsychology & Psychothrpy",
    "wof:placetype":"venue"
},
  "geometry": {"coordinates":[-81.494373,41.46384],"type":"Point"}
}