{
  "type": "Feature",
  "properties": {
    "addr:full": "2746 Cleveland Ave NW Canton OH 44709",
    "addr:housenumber": "2746",
    "addr:postcode": "44709",
    "addr:street": "Cleveland Ave Nw",
    "iso:country": "US",
    "sg:address": "2746 Cleveland Ave NW",
    "sg:city": "Canton",
    "sg:classifiers": [
      {
        "category": "Restaurant",
        "type": "Food \u0026 Drink"
      }
    ],
    "sg:menulink": "http://www.allmenus.com/oh/canton/67455-east-of-chicago-pizza/menu/",
    "sg:phone": "+1 330 455 3399",
    "sg:postcode": "44709",
    "sg:province": "OH",
    "sg:tags": [
      "sandwich",
      "salad",
      "soup",
      "american",
      "wrap",
      "pizza"
    ],
    "wof:name": "East of Chicago Pizza",
    "wof:placetype": "venue"
  },
  "geometry": {"coordinates":[-81.386445,40.829524],"type":"Point"}
}
