{
  "type": "Feature",
  "properties": {
    "iso:country":"US",
    "sg:address":"2746 Cleveland Ave NW",
    "sg:city":"Canton",
    "sg:classifiers":[
        {
            "category":"Restaurant",
            "type":"Food & Drink"
        }
    ],
    "sg:menulink":"http://www.allmenus.com/oh/canton/67455-east-of-chicago-pizza/menu/",
    "sg:phone":"+1 330 455 3399",
    "sg:postcode":"44709",
    "sg:province":"OH",
    "sg:tags":[
        "sandwich",
        "salad",
        "soup",
        "american",
        "wrap",
        "pizza"
    ],
    "wof:name":"East of Chicago Pizza",
    "wof:placetype":"venue"
},
  "geometry": {"coordinates":[-81.38644499999999,40.829524],"type":"Point"}
}