{
  "type": "Feature",
  "properties": {
    "addr:full":"4730 W Bancroft St Toledo OH 43615",
    "addr:housenumber":"4730",
    "addr:postcode":"43615",
    "addr:street":"W Bancroft St",
    "iso:country":"US",
    "sg:address":"4730 W Bancroft St",
    "sg:city":"Toledo",
    "sg:classifiers":[
        {
            "category":"Personal",
            "type":"Services"
        }
    ],
    "sg:phone":"+1 419 754 1150",
    "sg:postcode":"43615",
    "sg:province":"OH",
    "wof:name":"Handy Hubby",
    "wof:placetype":"venue"
},
  "geometry": {"coordinates":[-83.65055,41.662496],"type":"Point"}
}