{
  "type": "Feature",
  "properties": {
    "addr:full": "55 N Sandusky St Delaware OH 43015",
    "addr:housenumber": "55",
    "addr:postcode": "43015",
    "addr:street": "N Sandusky St",
    "iso:country": "US",
    "sg:address": "55 N Sandusky St",
    "sg:city": "Delaware",
    "sg:classifiers": [
      {
        "category": "Real Estate",
        "subcategory": "Real Estate Agent",
        "type": "Services"
      }
    ],
    "sg:phone": "+1 740 369 1555",
    "sg:postcode": "43015",
    "sg:province": "OH",
    "sg:tags": [
      "appraiser"
    ],
    "wof:name": "Mc Mullen Realty Svc",
    "wof:placetype": "venue"
  },
  "geometry": {"coordinates":[-83.067648,40.301009],"type":"Point"}
}
