{
  "type": "Feature",
  "properties": {
    "iso:country":"US",
    "sg:address":"55 N Sandusky St",
    "sg:city":"Delaware",
    "sg:classifiers":[
        {
            "category":"Real Estate",
            "subcategory":"Real Estate Agent",
            "type":"Services"
        }
    ],
    "sg:phone":"+1 740 369 1555",
    "sg:postcode":"43015",
    "sg:province":"OH",
    "sg:tags":[
        "appraiser"
    ],
    "wof:name":"Mc Mullen Realty Svc",
    "wof:placetype":"venue"
},
  "geometry": {"coordinates":[-83.06764800000001,40.301009],"type":"Point"}
}