{
  "type": "Feature",
  "properties": {
    "addr:full": "7235 State Rte 45 Lisbon OH 44432",
    "addr:housenumber": "7235",
    "addr:postcode": "44432",
    "addr:street": "State Rte 45",
    "iso:country": "US",
    "sg:address": "7235 State Rte 45",
    "sg:city": "Lisbon",
    "sg:classifiers": [
      {
        "category": "Wholesale",
        "subcategory": "Machinery \u0026 Supplies",
        "type": "Manufacturing \u0026 Wholesale Goods"
      },
      {
        "category": "Manufacturing",
        "subcategory": "Metals",
        "type": "Manufacturing \u0026 Wholesale Goods"
      }
    ],
    "sg:phone": "+1 330 424 9585",
    "sg:postcode": "44432",
    "sg:province": "OH",
    "sg:tags": [
      "hose",
      "coupling",
      "used",
      "equipment",
      "fitting",
      "construction",
      "new"
    ],
    "wof:name": "Ray Lewis \u0026 Company",
    "wof:placetype": "venue"
  },
  "geometry": {"coordinates":[-80.78006,40.794175],"type":"Point"}
}
