{
  "type": "Feature",
  "properties": {
    "iso:country":"US",
    "sg:address":"7235 State Rte 45",
    "sg:city":"Lisbon",
    "sg:classifiers":[
        {
            "category":"Wholesale",
            "subcategory":"Machinery & Supplies",
            "type":"Manufacturing & Wholesale Goods"
        },
        {
            "category":"Manufacturing",
            "subcategory":"Metals",
            "type":"Manufacturing & Wholesale Goods"
        }
    ],
    "sg:phone":"+1 330 424 9585",
    "sg:postcode":"44432",
    "sg:province":"OH",
    "sg:tags":[
        "hose",
        "coupling",
        "used",
        "equipment",
        "fitting",
        "construction",
        "new"
    ],
    "wof:name":"Ray Lewis & Company",
    "wof:placetype":"venue"
},
  "geometry": {"coordinates":[-80.78006000000001,40.794175],"type":"Point"}
}