{
  "type": "Feature",
  "properties": {
    "iso:country":"US",
    "sg:address":"2216 Losantiville Ave",
    "sg:city":"Cincinnati",
    "sg:classifiers":[
        {
            "category":"Travel",
            "subcategory":"Travel Agent",
            "type":"Entertainment"
        }
    ],
    "sg:phone":"+1 513 531 5600",
    "sg:postcode":"45237",
    "sg:province":"OH",
    "sg:tags":[
        "agency",
        "bureau"
    ],
    "wof:name":"Travel Bug Travel Agency",
    "wof:placetype":"venue"
},
  "geometry": {"coordinates":[-84.45126999999999,39.191137],"type":"Point"}
}