{
  "type": "Feature",
  "properties": {
    "addr:full": "1120 E Broad St Elyria OH 44035",
    "addr:housenumber": "1120",
    "addr:postcode": "44035",
    "addr:street": "E Broad St",
    "iso:country": "US",
    "sg:address": "1120 E Broad St",
    "sg:city": "Elyria",
    "sg:classifiers": [
      {
        "category": "Health Services",
        "subcategory": "Doctor",
        "type": "Services"
      }
    ],
    "sg:phone": "+1 440 365 2600",
    "sg:postcode": "44035",
    "sg:province": "OH",
    "sg:tags": [
      "phys"
    ],
    "wof:name": "Ksenich Nicholas J MD",
    "wof:placetype": "venue"
  },
  "geometry": {"coordinates":[-82.074412,41.363718],"type":"Point"}
}
