{
  "type": "Feature",
  "properties": {
    "addr:full":"306 Looney Rd Piqua OH 45356",
    "addr:housenumber":"306",
    "addr:postcode":"45356",
    "addr:street":"Looney Rd",
    "iso:country":"US",
    "sg:address":"306 Looney Rd",
    "sg:city":"Piqua",
    "sg:classifiers":[
        {
            "category":"Shopping",
            "subcategory":"Computers & Home Electronics",
            "type":"Retail Goods"
        }
    ],
    "sg:phone":"+1 937 778 1400",
    "sg:postcode":"45356",
    "sg:province":"OH",
    "sg:tags":[
        "equipment",
        "dealer"
    ],
    "wof:name":"Micro Direct",
    "wof:placetype":"venue"
},
  "geometry": {"coordinates":[-84.216815,40.15014],"type":"Point"}
}