{
  "type": "Feature",
  "properties": {
    "iso:country":"US",
    "sg:address":"1536 Maysville Ave",
    "sg:city":"Zanesville",
    "sg:classifiers":[
        {
            "category":"Restaurant",
            "type":"Food & Drink"
        }
    ],
    "sg:phone":"+1 740 452 9444",
    "sg:postcode":"43701",
    "sg:province":"OH",
    "sg:tags":[
        "eating",
        "pizza"
    ],
    "wof:name":"Four Star Pizza Inc",
    "wof:placetype":"venue"
},
  "geometry": {"coordinates":[-82.012736,39.916265],"type":"Point"}
}