{
  "type": "Feature",
  "properties": {
    "addr:full":"1324 N Superior St Toledo OH 43604",
    "addr:housenumber":"1324",
    "addr:postcode":"43604",
    "addr:street":"N Superior St",
    "iso:country":"US",
    "sg:address":"1324 N Superior St",
    "sg:city":"Toledo",
    "sg:classifiers":[
        {
            "category":"Social Services",
            "type":"Services"
        }
    ],
    "sg:phone":"+1 419 243 1289",
    "sg:postcode":"43604",
    "sg:province":"OH",
    "sg:tags":[
        "center",
        "community"
    ],
    "sg:website":"www.friendly-center.org",
    "wof:name":"Friendly Center Inc",
    "wof:placetype":"venue"
},
  "geometry": {"coordinates":[-83.520878,41.66065],"type":"Point"}
}