{
  "type": "Feature",
  "properties": {
    "addr:full": "2030 Wellington Rd Middletown OH 45044",
    "addr:housenumber": "2030",
    "addr:postcode": "45044",
    "addr:street": "Wellington Rd",
    "iso:country": "US",
    "sg:address": "2030 Wellington Rd",
    "sg:city": "Middletown",
    "sg:classifiers": [
      {
        "category": "Shopping",
        "subcategory": "Used Merchandise",
        "type": "Retail Goods"
      }
    ],
    "sg:phone": "+1 513 422 8737",
    "sg:postcode": "45044",
    "sg:province": "OH",
    "wof:name": "Manchester Station Consignment",
    "wof:placetype": "venue"
  },
  "geometry": {"coordinates":[-84.341177,39.495718],"type":"Point"}
}
