{
  "type": "Feature",
  "properties": {
    "iso:country":"US",
    "sg:address":"5320 Foxhill Cir NE",
    "sg:city":"Canton",
    "sg:classifiers":[
        {
            "category":"Manufacturing",
            "subcategory":"Apparel",
            "type":"Manufacturing & Wholesale Goods"
        }
    ],
    "sg:phone":"+1 330 492 4294",
    "sg:postcode":"44705",
    "sg:province":"OH",
    "sg:tags":[
        "sequin",
        "t",
        "applique",
        "shirt",
        "retail"
    ],
    "wof:name":"All That Jazz",
    "wof:placetype":"venue"
},
  "geometry": {"coordinates":[-81.343332,40.858086],"type":"Point"}
}