{
  "type": "Feature",
  "properties": {
    "iso:country":"US",
    "sg:address":"20 S Marion St",
    "sg:city":"Bloomville",
    "sg:classifiers":[
        {
            "category":"Education",
            "subcategory":"Library",
            "type":"Public Place"
        }
    ],
    "sg:phone":"+1 419 983 4675",
    "sg:postcode":"44818",
    "sg:province":"OH",
    "wof:name":"Bliss Memorial Library",
    "wof:placetype":"venue"
},
  "geometry": {"coordinates":[-83.015427,41.051566],"type":"Point"}
}