{
  "type": "Feature",
  "properties": {
    "addr:full":"886 E Midlothian Blvd Youngstown OH 44502",
    "addr:housenumber":"886",
    "addr:postcode":"44502",
    "addr:street":"E Midlothian Blvd",
    "iso:country":"US",
    "sg:address":"886 E Midlothian Blvd",
    "sg:city":"Youngstown",
    "sg:classifiers":[
        {
            "category":"Shopping",
            "subcategory":"Discount & Variety Stores",
            "type":"Retail Goods"
        }
    ],
    "sg:phone":"+1 330 788 7065",
    "sg:postcode":"44502",
    "sg:province":"OH",
    "wof:name":"Big Lots",
    "wof:placetype":"venue"
},
  "geometry": {"coordinates":[-80.63763,41.060838],"type":"Point"}
}