{
  "type": "Feature",
  "properties": {
    "iso:country":"US",
    "sg:address":"6501 Madison Rd",
    "sg:city":"Cincinnati",
    "sg:classifiers":[
        {
            "category":"Autos & Motor Vehicles",
            "subcategory":"Auto Supplies",
            "type":"Retail Goods"
        }
    ],
    "sg:phone":"+1 513 272 2441",
    "sg:postcode":"45227",
    "sg:province":"OH",
    "sg:tags":[
        "body",
        "shop",
        "part",
        "equipment",
        "automobile"
    ],
    "wof:name":"Colortime Inc",
    "wof:placetype":"venue"
},
  "geometry": {"coordinates":[-84.384216,39.159969],"type":"Point"}
}