{
  "type": "Feature",
  "properties": {
    "addr:full": "1434 S Hamilton Rd Columbus OH 43227",
    "addr:housenumber": "1434",
    "addr:postcode": "43227",
    "addr:street": "S Hamilton Rd",
    "iso:country": "US",
    "sg:address": "1434 S Hamilton Rd",
    "sg:city": "Columbus",
    "sg:classifiers": [
      {
        "category": "Personal",
        "subcategory": "Barber",
        "type": "Services"
      }
    ],
    "sg:phone": "+1 614 864 9064",
    "sg:postcode": "43227",
    "sg:province": "OH",
    "wof:name": "KRS Barber \u0026 Salon",
    "wof:placetype": "venue"
  },
  "geometry": {"coordinates":[-82.877622,39.946457],"type":"Point"}
}
