{
  "type": "Feature",
  "properties": {
    "iso:country":"US",
    "sg:address":"1100 Burkholder Rd",
    "sg:city":"Clyde",
    "sg:classifiers":[
        {
            "category":"Wholesale",
            "subcategory":"Farm Supplies",
            "type":"Manufacturing & Wholesale Goods"
        }
    ],
    "sg:phone":"+1 419 547 9588",
    "sg:postcode":"43410",
    "sg:province":"OH",
    "wof:name":"Country Spring Farmers Co-Op",
    "wof:placetype":"venue"
},
  "geometry": {"coordinates":[-82.96325899999999,41.315211],"type":"Point"}
}