{
  "type": "Feature",
  "properties": {
    "addr:full": "1100 Burkholder Rd Clyde OH 43410",
    "addr:housenumber": "1100",
    "addr:postcode": "43410",
    "addr:street": "Burkholder Rd",
    "iso:country": "US",
    "sg:address": "1100 Burkholder Rd",
    "sg:city": "Clyde",
    "sg:classifiers": [
      {
        "category": "Wholesale",
        "subcategory": "Farm Supplies",
        "type": "Manufacturing \u0026 Wholesale Goods"
      }
    ],
    "sg:phone": "+1 419 547 9588",
    "sg:postcode": "43410",
    "sg:province": "OH",
    "wof:name": "Country Spring Farmers Co-Op",
    "wof:placetype": "venue"
  },
  "geometry": {"coordinates":[-82.963259,41.315211],"type":"Point"}
}
