{
  "type": "Feature",
  "properties": {
    "iso:country":"US",
    "sg:address":"3021 Sferra Ave NW",
    "sg:city":"Warren",
    "sg:classifiers":[
        {
            "category":"Manufacturing",
            "subcategory":"Metals",
            "type":"Manufacturing & Wholesale Goods"
        }
    ],
    "sg:phone":"+1 330 395 3490",
    "sg:postcode":"44483",
    "sg:province":"OH",
    "sg:tags":[
        "steel",
        "pr",
        "light",
        "equipment",
        "stainless",
        "chimney"
    ],
    "wof:name":"Charles Mfg Co",
    "wof:placetype":"venue"
},
  "geometry": {"coordinates":[-80.824258,41.263051],"type":"Point"}
}