{
  "type": "Feature",
  "properties": {
    "addr:full": "123 S Walnut St Ottawa OH 45875",
    "addr:housenumber": "123",
    "addr:postcode": "45875",
    "addr:street": "S Walnut St",
    "iso:country": "US",
    "sg:address": "123 S Walnut St",
    "sg:city": "Ottawa",
    "sg:classifiers": [
      {
        "category": "Professional",
        "subcategory": "Management \u0026 Consulting",
        "type": "Services"
      }
    ],
    "sg:phone": "+1 419 523 3500",
    "sg:postcode": "45875",
    "sg:province": "OH",
    "wof:name": "American Express",
    "wof:placetype": "venue"
  },
  "geometry": {"coordinates":[-84.048988,41.018906],"type":"Point"}
}
