{
  "type": "Feature",
  "properties": {
    "iso:country":"US",
    "sg:address":"123 S Walnut St",
    "sg:city":"Ottawa",
    "sg:classifiers":[
        {
            "category":"Professional",
            "subcategory":"Management & Consulting",
            "type":"Services"
        }
    ],
    "sg:phone":"+1 419 523 3500",
    "sg:postcode":"45875",
    "sg:province":"OH",
    "wof:name":"American Express",
    "wof:placetype":"venue"
},
  "geometry": {"coordinates":[-84.04898799999999,41.018906],"type":"Point"}
}