{
  "type": "Feature",
  "properties": {
    "addr:full": "410 2nd St Marietta OH 45750",
    "addr:housenumber": "410",
    "addr:postcode": "45750",
    "addr:street": "2Nd St",
    "iso:country": "US",
    "sg:address": "410 2nd St",
    "sg:city": "Marietta",
    "sg:classifiers": [
      {
        "category": "Health Services",
        "subcategory": "Doctor",
        "type": "Services"
      }
    ],
    "sg:phone": "+1 740 374 3622",
    "sg:postcode": "45750",
    "sg:province": "OH",
    "sg:tags": [
      "physician",
      "surgeon",
      "gynecologist"
    ],
    "wof:name": "Gynecologic Associates Inc",
    "wof:placetype": "venue"
  },
  "geometry": {"coordinates":[-81.458457,39.419102],"type":"Point"}
}
