{
  "type": "Feature",
  "properties": {
    "addr:full":"2439 N Reynolds Rd Toledo OH 43615",
    "addr:housenumber":"2439",
    "addr:postcode":"43615",
    "addr:street":"N Reynolds Rd",
    "iso:country":"US",
    "sg:address":"2439 N Reynolds Rd",
    "sg:city":"Toledo",
    "sg:classifiers":[
        {
            "category":"Health Services",
            "subcategory":"Chiropractor",
            "type":"Services"
        }
    ],
    "sg:phone":"+1 419 535 7818",
    "sg:postcode":"43615",
    "sg:province":"OH",
    "wof:name":"ABA Family Chiropractic Ctr",
    "wof:placetype":"venue"
},
  "geometry": {"coordinates":[-83.668111,41.669203],"type":"Point"}
}