{
  "type": "Feature",
  "properties": {
    "iso:country":"US",
    "sg:address":"116 Dearborn St SE",
    "sg:city":"Girard",
    "sg:classifiers":[
        {
            "category":"Professional",
            "type":"Services"
        }
    ],
    "sg:phone":"+1 330 545 2607",
    "sg:postcode":"44420",
    "sg:province":"OH",
    "wof:name":"Edward Desantis",
    "wof:placetype":"venue"
},
  "geometry": {"coordinates":[-80.682983,41.137872],"type":"Point"}
}