{
  "type": "Feature",
  "properties": {
    "addr:full": "116 Dearborn St SE Girard OH 44420",
    "addr:housenumber": "116",
    "addr:postcode": "44420",
    "addr:street": "Dearborn St Se",
    "iso:country": "US",
    "sg:address": "116 Dearborn St SE",
    "sg:city": "Girard",
    "sg:classifiers": [
      {
        "category": "Professional",
        "type": "Services"
      }
    ],
    "sg:phone": "+1 330 545 2607",
    "sg:postcode": "44420",
    "sg:province": "OH",
    "wof:name": "Edward Desantis",
    "wof:placetype": "venue"
  },
  "geometry": {"coordinates":[-80.682983,41.137872],"type":"Point"}
}
