{
  "type": "Feature",
  "properties": {
    "addr:full": "118 N Main St Mendon OH 45862",
    "addr:housenumber": "118",
    "addr:postcode": "45862",
    "addr:street": "N Main St",
    "iso:country": "US",
    "sg:address": "118 N Main St",
    "sg:city": "Mendon",
    "sg:classifiers": [
      {
        "category": "Government",
        "subcategory": "Fire Station",
        "type": "Public Place"
      }
    ],
    "sg:phone": "+1 419 586 6455",
    "sg:postcode": "45862",
    "sg:province": "OH",
    "sg:tags": [
      "department"
    ],
    "wof:name": "Mendon Village Fire Dept",
    "wof:placetype": "venue"
  },
  "geometry": {"coordinates":[-84.518641,40.674408],"type":"Point"}
}
