{
  "type": "Feature",
  "properties": {
    "addr:full": "123 Hayes Ave Port Clinton OH 43452",
    "addr:housenumber": "123",
    "addr:postcode": "43452",
    "addr:street": "Hayes Ave",
    "iso:country": "US",
    "sg:address": "123 Hayes Ave",
    "sg:city": "Port Clinton",
    "sg:classifiers": [
      {
        "category": "Building \u0026 Trades",
        "subcategory": "Construction",
        "type": "Services"
      }
    ],
    "sg:phone": "+1 419 732 2388",
    "sg:postcode": "43452",
    "sg:province": "OH",
    "sg:tags": [
      "hanging",
      "contractor"
    ],
    "wof:name": "Randy Smith Painting \u0026 Buildin",
    "wof:placetype": "venue"
  },
  "geometry": {"coordinates":[-82.92842,41.51245],"type":"Point"}
}
