{
  "type": "Feature",
  "properties": {
    "iso:country":"US",
    "sg:address":"123 Hayes Ave",
    "sg:city":"Port Clinton",
    "sg:classifiers":[
        {
            "category":"Building & Trades",
            "subcategory":"Construction",
            "type":"Services"
        }
    ],
    "sg:phone":"+1 419 732 2388",
    "sg:postcode":"43452",
    "sg:province":"OH",
    "sg:tags":[
        "hanging",
        "contractor"
    ],
    "wof:name":"Randy Smith Painting & Buildin",
    "wof:placetype":"venue"
},
  "geometry": {"coordinates":[-82.92842,41.51245],"type":"Point"}
}