{
  "type": "Feature",
  "properties": {
    "iso:country":"US",
    "sg:address":"91 Marion Ave",
    "sg:city":"Mansfield",
    "sg:classifiers":[
        {
            "category":"Organizations",
            "subcategory":"Religious Organization",
            "type":"Services"
        }
    ],
    "sg:phone":"+1 419 522 5926",
    "sg:postcode":"44903",
    "sg:province":"OH",
    "sg:tags":[
        "church"
    ],
    "wof:name":"New Beginning Full Gospel Bapt",
    "wof:placetype":"venue"
},
  "geometry": {"coordinates":[-82.52748,40.757477],"type":"Point"}
}