{
  "type": "Feature",
  "properties": {
    "iso:country":"US",
    "sg:address":"125 Stablewatch Ct",
    "sg:city":"Monroe",
    "sg:classifiers":[
        {
            "category":"Building & Trades",
            "subcategory":"Construction",
            "type":"Services"
        }
    ],
    "sg:phone":"+1 513 539 4474",
    "sg:postcode":"45050",
    "sg:province":"OH",
    "sg:tags":[
        "resurfacing",
        "floor",
        "laying",
        "refinishing",
        "contractor"
    ],
    "wof:name":"All About Hardwood Floors Co",
    "wof:placetype":"venue"
},
  "geometry": {"coordinates":[-84.35171800000001,39.433763],"type":"Point"}
}