{
  "type": "Feature",
  "properties": {
    "iso:country":"US",
    "sg:address":"1766 Parsons Ave",
    "sg:city":"Columbus",
    "sg:classifiers":[
        {
            "category":"Bars & Pubs",
            "type":"Food & Drink"
        }
    ],
    "sg:phone":"+1 614 444 2187",
    "sg:postcode":"43207",
    "sg:province":"OH",
    "sg:tags":[
        "drinking"
    ],
    "wof:name":"Friendly Tavern Inc",
    "wof:placetype":"venue"
},
  "geometry": {"coordinates":[-82.984165,39.927377],"type":"Point"}
}