{
  "type": "Feature",
  "properties": {
    "addr:full": "12494 Friendsville Rd Burbank OH 44214",
    "addr:postcode": "12494;44214",
    "addr:street": "Friendsville Rd",
    "iso:country": "US",
    "sg:address": "12494 Friendsville Rd",
    "sg:city": "Burbank",
    "sg:classifiers": [
      {
        "category": "Farming",
        "subcategory": "Dairy Farm",
        "type": "Manufacturing \u0026 Wholesale Goods"
      }
    ],
    "sg:phone": "+1 330 435 4059",
    "sg:postcode": "44214",
    "sg:province": "OH",
    "wof:name": "Cliff Brook Farm",
    "wof:placetype": "venue"
  },
  "geometry": {"coordinates":[-81.956999,40.951372],"type":"Point"}
}
