{
  "type": "Feature",
  "properties": {
    "iso:country":"US",
    "sg:address":"20 Front St",
    "sg:city":"Tiffin",
    "sg:classifiers":[
        {
            "category":"Retail",
            "subcategory":"Repair Shop",
            "type":"Services"
        }
    ],
    "sg:phone":"+1 419 447 0141",
    "sg:postcode":"44883",
    "sg:province":"OH",
    "sg:tags":[
        "upholsterer"
    ],
    "wof:name":"Yvonne's Upholstery",
    "wof:placetype":"venue"
},
  "geometry": {"coordinates":[-83.178888,41.112839],"type":"Point"}
}