{
  "type": "Feature",
  "properties": {
    "addr:full":"4608 Woodville Rd Northwood OH 43619",
    "addr:housenumber":"4608",
    "addr:postcode":"43619",
    "addr:street":"Woodville Rd",
    "iso:country":"US",
    "sg:address":"4608 Woodville Rd",
    "sg:city":"Northwood",
    "sg:classifiers":[
        {
            "category":"Shopping",
            "subcategory":"Musical Instruments",
            "type":"Retail Goods"
        }
    ],
    "sg:phone":"+1 419 693 3500",
    "sg:postcode":"43619",
    "sg:province":"OH",
    "wof:name":"Payless Music",
    "wof:placetype":"venue"
},
  "geometry": {"coordinates":[-83.463283,41.60118],"type":"Point"}
}