{
  "type": "Feature",
  "properties": {
    "addr:full": "874 Twp Hwy 68 Nevada OH 44849",
    "addr:housenumber": "874",
    "addr:postcode": "44849",
    "addr:street": "Twp Hwy 68",
    "iso:country": "US",
    "sg:address": "874 Twp Hwy 68",
    "sg:city": "Nevada",
    "sg:classifiers": [
      {
        "category": "Wholesale",
        "subcategory": "Machinery \u0026 Supplies",
        "type": "Manufacturing \u0026 Wholesale Goods"
      }
    ],
    "sg:phone": "+1 740 465 6119",
    "sg:postcode": "44849",
    "sg:province": "OH",
    "sg:tags": [
      "crane",
      "derrick"
    ],
    "wof:name": "Russel Killen",
    "wof:placetype": "venue"
  },
  "geometry": {"coordinates":[-83.140265,40.702561],"type":"Point"}
}
