{
  "type": "Feature",
  "properties": {
    "iso:country":"US",
    "sg:address":"3875 Ferry Rd",
    "sg:city":"Bellbrook",
    "sg:classifiers":[
        {
            "category":"Building & Trades",
            "subcategory":"Construction",
            "type":"Services"
        }
    ],
    "sg:phone":"+1 937 885 5890",
    "sg:postcode":"45305",
    "sg:province":"OH",
    "sg:tags":[
        "hanging",
        "contractor"
    ],
    "wof:name":"Audia Louis E Painting Contr",
    "wof:placetype":"venue"
},
  "geometry": {"coordinates":[-84.10236,39.594223],"type":"Point"}
}