{
  "type": "Feature",
  "properties": {
    "addr:full": "108 S Sandusky Ave Bucyrus OH 44820",
    "addr:housenumber": "108",
    "addr:postcode": "44820",
    "addr:street": "S Sandusky Ave",
    "iso:country": "US",
    "sg:address": "108 S Sandusky Ave",
    "sg:city": "Bucyrus",
    "sg:classifiers": [
      {
        "category": "Restaurant",
        "type": "Food \u0026 Drink"
      }
    ],
    "sg:menulink": "http://www.allmenus.com/oh/bucyrus/63937-pelican-house/menu/",
    "sg:phone": "+1 419 562 9727",
    "sg:postcode": "44820",
    "sg:province": "OH",
    "sg:tags": [
      "american",
      "diner"
    ],
    "wof:name": "Pelican House",
    "wof:placetype": "venue"
  },
  "geometry": {"coordinates":[-82.97557,40.807669],"type":"Point"}
}
