{
  "type": "Feature",
  "properties": {
    "iso:country":"US",
    "sg:address":"1929 Kenny Rd",
    "sg:city":"Columbus",
    "sg:classifiers":[
        {
            "category":"Organizations",
            "subcategory":"Non-profit Organization",
            "type":"Services"
        },
        {
            "category":"Education",
            "subcategory":"School",
            "type":"Public Place"
        },
        {
            "category":"Education",
            "subcategory":"Special Training",
            "type":"Public Place"
        }
    ],
    "sg:phone":"+1 614 292 8707",
    "sg:postcode":"43210",
    "sg:province":"OH",
    "sg:website":"www.edcouncil.org",
    "wof:name":"Educational Council",
    "wof:placetype":"venue"
},
  "geometry": {"coordinates":[-83.034787,39.998791],"type":"Point"}
}