{
  "type": "Feature",
  "properties": {
    "addr:full":"880 Baldwin Aly Cincinnati OH 45202",
    "addr:housenumber":"880",
    "addr:postcode":"45202",
    "addr:street":"Baldwin Aly",
    "iso:country":"US",
    "sg:address":"880 Baldwin Aly",
    "sg:city":"Cincinnati",
    "sg:classifiers":[
        {
            "category":"Education",
            "subcategory":"Library",
            "type":"Public Place"
        }
    ],
    "sg:phone":"+1 513 556 1550",
    "sg:postcode":"45202",
    "sg:province":"OH",
    "wof:name":"Engineering Library",
    "wof:placetype":"venue"
},
  "geometry": {"coordinates":[-84.514368,39.105067],"type":"Point"}
}