{
  "type": "Feature",
  "properties": {
    "addr:full": "774 W Locust St Newark OH 43055",
    "addr:housenumber": "774",
    "addr:postcode": "43055",
    "addr:street": "W Locust St",
    "iso:country": "US",
    "sg:address": "774 W Locust St",
    "sg:city": "Newark",
    "sg:classifiers": [
      {
        "category": "Freight",
        "type": "Transportation"
      }
    ],
    "sg:phone": "+1 740 344 7566",
    "sg:postcode": "43055",
    "sg:province": "OH",
    "sg:tags": [
      "mobile",
      "home",
      "accessory"
    ],
    "wof:name": "Watson Mobiel HM Transporting",
    "wof:placetype": "venue"
  },
  "geometry": {"coordinates":[-82.4311,40.059164],"type":"Point"}
}
