{
  "type": "Feature",
  "properties": {
    "addr:full":"245 N Main St Springboro OH 45066",
    "addr:housenumber":"245",
    "addr:postcode":"45066",
    "addr:street":"N Main St",
    "iso:country":"US",
    "sg:address":"245 N Main St",
    "sg:city":"Springboro",
    "sg:classifiers":[
        {
            "category":"Health Services",
            "subcategory":"Doctor",
            "type":"Services"
        }
    ],
    "sg:phone":"+1 937 748 2855",
    "sg:postcode":"45066",
    "sg:province":"OH",
    "sg:tags":[
        "dentist"
    ],
    "wof:name":"Adel Hanna DDS",
    "wof:placetype":"venue"
},
  "geometry": {"coordinates":[-84.232613,39.560993],"type":"Point"}
}