{
  "type": "Feature",
  "properties": {
    "addr:full":"118 W Water St Piqua OH 45356",
    "addr:housenumber":"118",
    "addr:postcode":"45356",
    "addr:street":"W Water St",
    "iso:country":"US",
    "sg:address":"118 W Water St",
    "sg:city":"Piqua",
    "sg:classifiers":[
        {
            "category":"Personal",
            "subcategory":"Tattoo Parlor",
            "type":"Services"
        }
    ],
    "sg:phone":"+1 937 778 1055",
    "sg:postcode":"45356",
    "sg:province":"OH",
    "sg:tags":[
        "tattooing"
    ],
    "wof:name":"Extreme Tattoo",
    "wof:placetype":"venue"
},
  "geometry": {"coordinates":[-84.239777,40.147665],"type":"Point"}
}