{
  "type": "Feature",
  "properties": {
    "addr:full":"271 Schrop Ave Akron OH 44312",
    "addr:housenumber":"271",
    "addr:postcode":"44312",
    "addr:street":"Schrop Ave",
    "iso:country":"US",
    "sg:address":"271 Schrop Ave",
    "sg:city":"Akron",
    "sg:classifiers":[
        {
            "category":"Freight",
            "type":"Transportation"
        }
    ],
    "sg:phone":"+1 330 784 2400",
    "sg:postcode":"44312",
    "sg:province":"OH",
    "sg:tags":[
        "delivery"
    ],
    "wof:name":"Home Checkout",
    "wof:placetype":"venue"
},
  "geometry": {"coordinates":[-81.446941,41.056503],"type":"Point"}
}