{
  "type": "Feature",
  "properties": {
    "addr:full": "2690 W 7th St Cleveland OH 44113",
    "addr:housenumber": "2690",
    "addr:postcode": "44113",
    "addr:street": "W 7Th St",
    "iso:country": "US",
    "sg:address": "2690 W 7th St",
    "sg:city": "Cleveland",
    "sg:classifiers": [
      {
        "category": "Government",
        "subcategory": "Office",
        "type": "Public Place"
      }
    ],
    "sg:phone": "+1 216 664 3069",
    "sg:postcode": "44113",
    "sg:province": "OH",
    "sg:tags": [
      "general"
    ],
    "wof:name": "Public Safety",
    "wof:placetype": "venue"
  },
  "geometry": {"coordinates":[-81.678877,41.474125],"type":"Point"}
}
