{
  "type": "Feature",
  "properties": {
    "addr:full":"8 N Union Ave Alliance OH 44601",
    "addr:housenumber":"8",
    "addr:postcode":"44601",
    "addr:street":"N Union Ave",
    "iso:country":"US",
    "sg:address":"8 N Union Ave",
    "sg:city":"Alliance",
    "sg:classifiers":[
        {
            "category":"Autos & Motor Vehicles",
            "subcategory":"Fuel & Gas Station",
            "type":"Retail Goods"
        }
    ],
    "sg:phone":"+1 330 823 0162",
    "sg:postcode":"44601",
    "sg:province":"OH",
    "sg:tags":[
        "repair",
        "oil",
        "automotive",
        "gasoline",
        "general",
        "station"
    ],
    "wof:name":"Main Street Marathon Service",
    "wof:placetype":"venue"
},
  "geometry": {"coordinates":[-81.10591599999999,40.922629],"type":"Point"}
}