{
  "type": "Feature",
  "properties": {
    "addr:full": "11066 Wilson Mills Rd Chardon OH 44024",
    "addr:housenumber": "11066",
    "addr:postcode": "44024",
    "addr:street": "Wilson Mills Rd",
    "iso:country": "US",
    "sg:address": "11066 Wilson Mills Rd",
    "sg:city": "Chardon",
    "sg:classifiers": [
      {
        "category": "Professional",
        "subcategory": "Management \u0026 Consulting",
        "type": "Services"
      }
    ],
    "sg:phone": "+1 440 285 0900",
    "sg:postcode": "44024",
    "sg:province": "OH",
    "sg:tags": [
      "consultant",
      "business"
    ],
    "wof:name": "Dennis D Laughlin Assoc Inc",
    "wof:placetype": "venue"
  },
  "geometry": {"coordinates":[-81.245261,41.554137],"type":"Point"}
}
