{
  "type": "Feature",
  "properties": {
    "addr:full": "2515 Lake Ave Ashtabula OH 44004",
    "addr:housenumber": "2515",
    "addr:postcode": "44004",
    "addr:street": "Lake Ave",
    "iso:country": "US",
    "sg:address": "2515 Lake Ave",
    "sg:city": "Ashtabula",
    "sg:classifiers": [
      {
        "category": "Health Services",
        "subcategory": "Health Practitioner",
        "type": "Services"
      }
    ],
    "sg:phone": "+1 440 997 6680",
    "sg:postcode": "44004",
    "sg:province": "OH",
    "sg:tags": [
      "therapist",
      "physical"
    ],
    "wof:name": "Ashtabula County Medical Ctr",
    "wof:placetype": "venue"
  },
  "geometry": {"coordinates":[-80.79602,41.880244],"type":"Point"}
}
