{
  "type": "Feature",
  "properties": {
    "addr:full": "5824 Newton Falls Rd Ravenna OH 44266",
    "addr:housenumber": "5824",
    "addr:postcode": "44266",
    "addr:street": "Newton Falls Rd",
    "iso:country": "US",
    "sg:address": "5824 Newton Falls Rd",
    "sg:city": "Ravenna",
    "sg:classifiers": [
      {
        "category": "Autos \u0026 Motor Vehicles",
        "subcategory": "Automobile Sales",
        "type": "Retail Goods"
      }
    ],
    "sg:phone": "+1 330 297 9498",
    "sg:postcode": "44266",
    "sg:province": "OH",
    "sg:tags": [
      "automotive",
      "used"
    ],
    "wof:name": "Midway Auto Sales \u0026 Wrecking",
    "wof:placetype": "venue"
  },
  "geometry": {"coordinates":[-81.183004,41.16313],"type":"Point"}
}
