{
  "type": "Feature",
  "properties": {
    "addr:full": "6681 Hetzler Rd Middletown OH 45042",
    "addr:housenumber": "6681",
    "addr:postcode": "45042",
    "addr:street": "Hetzler Rd",
    "iso:country": "US",
    "sg:address": "6681 Hetzler Rd",
    "sg:city": "Middletown",
    "sg:classifiers": [
      {
        "category": "Building \u0026 Trades",
        "subcategory": "Construction",
        "type": "Services"
      }
    ],
    "sg:phone": "+1 513 424 7887",
    "sg:postcode": "45042",
    "sg:province": "OH",
    "sg:tags": [
      "roofing",
      "contractor"
    ],
    "wof:name": "Garcia Roof Systems",
    "wof:placetype": "venue"
  },
  "geometry": {"coordinates":[-84.440537,39.542823],"type":"Point"}
}
