{
  "type": "Feature",
  "properties": {
    "iso:country":"US",
    "sg:address":"6681 Hetzler Rd",
    "sg:city":"Middletown",
    "sg:classifiers":[
        {
            "category":"Building & Trades",
            "subcategory":"Construction",
            "type":"Services"
        }
    ],
    "sg:phone":"+1 513 424 7887",
    "sg:postcode":"45042",
    "sg:province":"OH",
    "sg:tags":[
        "roofing",
        "contractor"
    ],
    "wof:name":"Garcia Roof Systems",
    "wof:placetype":"venue"
},
  "geometry": {"coordinates":[-84.440537,39.542823],"type":"Point"}
}