{
  "type": "Feature",
  "properties": {
    "iso:country":"US",
    "sg:address":"64 E Main St",
    "sg:city":"Amelia",
    "sg:classifiers":[
        {
            "category":"Retail",
            "subcategory":"Driving School",
            "type":"Services"
        },
        {
            "category":"Autos & Motor Vehicles",
            "subcategory":"Motorcycle Sales",
            "type":"Retail Goods"
        }
    ],
    "sg:phone":"+1 513 753 0888",
    "sg:postcode":"45102",
    "sg:province":"OH",
    "sg:tags":[
        "instruction"
    ],
    "wof:name":"H H Motor Sports",
    "wof:placetype":"venue"
},
  "geometry": {"coordinates":[-84.214212,39.02556],"type":"Point"}
}