{
  "type": "Feature",
  "properties": {
    "addr:full":"3853 Center Rd Brunswick OH 44212",
    "addr:housenumber":"3853",
    "addr:postcode":"44212",
    "addr:street":"Center Rd",
    "iso:country":"US",
    "sg:address":"3853 Center Rd",
    "sg:city":"Brunswick",
    "sg:classifiers":[
        {
            "category":"Manufacturing",
            "subcategory":"Printing",
            "type":"Manufacturing & Wholesale Goods"
        }
    ],
    "sg:phone":"+1 330 273 3488",
    "sg:postcode":"44212",
    "sg:province":"OH",
    "sg:tags":[
        "printer"
    ],
    "wof:name":"Printing Partners",
    "wof:placetype":"venue"
},
  "geometry": {"coordinates":[-81.82186799999999,41.238306],"type":"Point"}
}