{
  "type": "Feature",
  "properties": {
    "iso:country":"US",
    "sg:address":"1546 Rockaway St",
    "sg:city":"Akron",
    "sg:classifiers":[
        {
            "category":"Home & Garden",
            "subcategory":"Furniture",
            "type":"Retail Goods"
        }
    ],
    "sg:phone":"+1 330 745 9117",
    "sg:postcode":"44314",
    "sg:province":"OH",
    "sg:tags":[
        "equipment",
        "kitchen",
        "cabinet"
    ],
    "wof:name":"Creative Remodeling By Turchin",
    "wof:placetype":"venue"
},
  "geometry": {"coordinates":[-81.552322,41.056702],"type":"Point"}
}