{
  "type": "Feature",
  "properties": {
    "iso:country":"US",
    "sg:address":"827 Southwestern Run",
    "sg:city":"Youngstown",
    "sg:classifiers":[
        {
            "category":"Professional",
            "subcategory":"Computer Services",
            "type":"Services"
        }
    ],
    "sg:phone":"+1 330 726 2442",
    "sg:postcode":"44514",
    "sg:province":"OH",
    "sg:tags":[
        "programming",
        "custom"
    ],
    "sg:website":"www.magicalcomputing.com",
    "wof:name":"Magical Computing Solutions",
    "wof:placetype":"venue"
},
  "geometry": {"coordinates":[-80.63842,40.988726],"type":"Point"}
}