{
  "type": "Feature",
  "properties": {
    "iso:country":"US",
    "sg:address":"732 Pleasant Valley Dr",
    "sg:city":"Springboro",
    "sg:classifiers":[
        {
            "category":"Professional",
            "subcategory":"Art Services",
            "type":"Services"
        }
    ],
    "sg:phone":"+1 937 743 3088",
    "sg:postcode":"45066",
    "sg:province":"OH",
    "sg:tags":[
        "photographer"
    ],
    "wof:name":"Werlegig Imaging Inc",
    "wof:placetype":"venue"
},
  "geometry": {"coordinates":[-84.258853,39.559574],"type":"Point"}
}