{
  "type": "Feature",
  "properties": {
    "addr:full":"301 W Market St Baltimore OH 43105",
    "addr:housenumber":"301",
    "addr:postcode":"43105",
    "addr:street":"W Market St",
    "iso:country":"US",
    "sg:address":"301 W Market St",
    "sg:city":"Baltimore",
    "sg:classifiers":[
        {
            "category":"Organizations",
            "subcategory":"Religious Organization",
            "type":"Services"
        }
    ],
    "sg:phone":"+1 740 862 8060",
    "sg:postcode":"43105",
    "sg:province":"OH",
    "sg:tags":[
        "clergy"
    ],
    "wof:name":"Bruce Gischel",
    "wof:placetype":"venue"
},
  "geometry": {"coordinates":[-82.60527399999999,39.845552],"type":"Point"}
}