{
  "type": "Feature",
  "properties": {
    "addr:full": "324 W Ash St Piqua OH 45356",
    "addr:housenumber": "324",
    "addr:postcode": "45356",
    "addr:street": "W Ash St",
    "iso:country": "US",
    "sg:address": "324 W Ash St",
    "sg:city": "Piqua",
    "sg:classifiers": [
      {
        "category": "Travel",
        "subcategory": "Hotels \u0026 Motels",
        "type": "Entertainment"
      }
    ],
    "sg:phone": "+1 937 615 9810",
    "sg:postcode": "45356",
    "sg:province": "OH",
    "sg:tags": [
      "breakfast",
      "accommodation",
      "bed"
    ],
    "wof:name": "Ash Street B \u0026 B Camberley",
    "wof:placetype": "venue"
  },
  "geometry": {"coordinates":[-84.243592,40.14973],"type":"Point"}
}
