{
  "type": "Feature",
  "properties": {
    "iso:country":"US",
    "sg:address":"4874 Newton Falls Rd",
    "sg:city":"Ravenna",
    "sg:classifiers":[
        {
            "category":"Manufacturing",
            "subcategory":"Food",
            "type":"Manufacturing & Wholesale Goods"
        }
    ],
    "sg:phone":"+1 330 296 6186",
    "sg:postcode":"44266",
    "sg:province":"OH",
    "sg:tags":[
        "drink",
        "soft",
        "mfg"
    ],
    "wof:name":"Joes Commando",
    "wof:placetype":"venue"
},
  "geometry": {"coordinates":[-81.216762,41.157678],"type":"Point"}
}