{
  "type": "Feature",
  "properties": {
    "addr:full": "4874 Newton Falls Rd Ravenna OH 44266",
    "addr:housenumber": "4874",
    "addr:postcode": "44266",
    "addr:street": "Newton Falls Rd",
    "iso:country": "US",
    "sg:address": "4874 Newton Falls Rd",
    "sg:city": "Ravenna",
    "sg:classifiers": [
      {
        "category": "Manufacturing",
        "subcategory": "Food",
        "type": "Manufacturing \u0026 Wholesale Goods"
      }
    ],
    "sg:phone": "+1 330 296 6186",
    "sg:postcode": "44266",
    "sg:province": "OH",
    "sg:tags": [
      "drink",
      "soft",
      "mfg"
    ],
    "wof:name": "Joes Commando",
    "wof:placetype": "venue"
  },
  "geometry": {"coordinates":[-81.216762,41.157678],"type":"Point"}
}
