{
  "type": "Feature",
  "properties": {
    "addr:full":"1784 Bethel New Richmond Rd New Richmond OH 45157",
    "addr:housenumber":"1784",
    "addr:postcode":"45157",
    "addr:street":"Bethel New Richmond Rd",
    "iso:country":"US",
    "sg:address":"1784 Bethel New Richmond Rd",
    "sg:city":"New Richmond",
    "sg:classifiers":[
        {
            "category":"Health Services",
            "subcategory":"Dentist",
            "type":"Services"
        }
    ],
    "sg:phone":"+1 513 553 2949",
    "sg:postcode":"45157",
    "sg:province":"OH",
    "wof:name":"Theiss Jas D DMD",
    "wof:placetype":"venue"
},
  "geometry": {"coordinates":[-84.210796,38.953343],"type":"Point"}
}