{
  "type": "Feature",
  "properties": {
    "addr:full":"24262 Broadway Ave Bedford OH 44146",
    "addr:housenumber":"24262",
    "addr:postcode":"44146",
    "addr:street":"Broadway Ave",
    "iso:country":"US",
    "sg:address":"24262 Broadway Ave",
    "sg:city":"Bedford",
    "sg:classifiers":[
        {
            "category":"Real Estate",
            "subcategory":"Real Estate Agent",
            "type":"Services"
        }
    ],
    "sg:phone":"+1 440 232 0069",
    "sg:postcode":"44146",
    "sg:province":"OH",
    "wof:name":"Insite Realty Inc",
    "wof:placetype":"venue"
},
  "geometry": {"coordinates":[-81.50435,41.362374],"type":"Point"}
}