{
  "type": "Feature",
  "properties": {
    "addr:full": "250 S Chestnut St Ravenna OH 44266",
    "addr:housenumber": "250",
    "addr:postcode": "44266",
    "addr:street": "S Chestnut St",
    "iso:country": "US",
    "sg:address": "250 S Chestnut St",
    "sg:city": "Ravenna",
    "sg:classifiers": [
      {
        "category": "Professional",
        "subcategory": "Lawyer \u0026 Legal Services",
        "type": "Services"
      }
    ],
    "sg:phone": "+1 330 297 5788",
    "sg:postcode": "44266",
    "sg:province": "OH",
    "sg:tags": [
      "attorney"
    ],
    "wof:name": "Ravenna Law Director",
    "wof:placetype": "venue"
  },
  "geometry": {"coordinates":[-81.243288,41.155637],"type":"Point"}
}
