{
  "type": "Feature",
  "properties": {
    "addr:full": "5557 State Rte 66 Defiance OH 43512",
    "addr:housenumber": "5557",
    "addr:postcode": "43512",
    "addr:street": "State Rte 66",
    "iso:country": "US",
    "sg:address": "5557 State Rte 66",
    "sg:city": "Defiance",
    "sg:classifiers": [
      {
        "category": "Freight",
        "type": "Transportation"
      },
      {
        "category": "Home \u0026 Garden",
        "subcategory": "Garden Supply",
        "type": "Retail Goods"
      }
    ],
    "sg:phone": "+1 419 782 0807",
    "sg:postcode": "43512",
    "sg:province": "OH",
    "sg:tags": [
      "lawn",
      "center",
      "snowplowing",
      "trucking",
      "mfr",
      "topsoil"
    ],
    "wof:name": "Garden Ridge Nursery",
    "wof:placetype": "venue"
  },
  "geometry": {"coordinates":[-84.360716,41.363691],"type":"Point"}
}
