{
  "type": "Feature",
  "properties": {
    "iso:country":"US",
    "sg:address":"5557 State Rte 66",
    "sg:city":"Defiance",
    "sg:classifiers":[
        {
            "category":"Freight",
            "type":"Transportation"
        },
        {
            "category":"Home & Garden",
            "subcategory":"Garden Supply",
            "type":"Retail Goods"
        }
    ],
    "sg:phone":"+1 419 782 0807",
    "sg:postcode":"43512",
    "sg:province":"OH",
    "sg:tags":[
        "lawn",
        "center",
        "snowplowing",
        "trucking",
        "mfr",
        "topsoil"
    ],
    "wof:name":"Garden Ridge Nursery",
    "wof:placetype":"venue"
},
  "geometry": {"coordinates":[-84.360716,41.363691],"type":"Point"}
}