{
  "type": "Feature",
  "properties": {
    "addr:full": "5005 Rockside Rd Cleveland OH 44131",
    "addr:housenumber": "5005",
    "addr:postcode": "44131",
    "addr:street": "Rockside Rd",
    "iso:country": "US",
    "sg:address": "5005 Rockside Rd",
    "sg:city": "Cleveland",
    "sg:classifiers": [
      {
        "category": "Professional",
        "subcategory": "Lawyer \u0026 Legal Services",
        "type": "Services"
      }
    ],
    "sg:phone": "+1 216 566 0223",
    "sg:postcode": "44131",
    "sg:province": "OH",
    "sg:tags": [
      "attorney"
    ],
    "wof:name": "Gerald D Piszczek Co",
    "wof:placetype": "venue"
  },
  "geometry": {"coordinates":[-81.65351,41.396943],"type":"Point"}
}
