{
  "type": "Feature",
  "properties": {
    "iso:country":"US",
    "sg:address":"11 W Main St",
    "sg:city":"Ashville",
    "sg:classifiers":[
        {
            "category":"Real Estate",
            "subcategory":"Real Estate Agent",
            "type":"Services"
        }
    ],
    "sg:phone":"+1 740 983 2232",
    "sg:postcode":"43103",
    "sg:province":"OH",
    "wof:name":"Ashville Realty",
    "wof:placetype":"venue"
},
  "geometry": {"coordinates":[-82.954166,39.713022],"type":"Point"}
}