{
  "type": "Feature",
  "properties": {
    "addr:full": "2608 Old Mill Rd Hudson OH 44236",
    "addr:housenumber": "2608",
    "addr:postcode": "44236",
    "addr:street": "Old Mill Rd",
    "iso:country": "US",
    "sg:address": "2608 Old Mill Rd",
    "sg:city": "Hudson",
    "sg:classifiers": [
      {
        "category": "Food \u0026 Beverages",
        "subcategory": "Dairy",
        "type": "Retail Goods"
      }
    ],
    "sg:phone": "+1 330 487 0554",
    "sg:postcode": "44236",
    "sg:province": "OH",
    "sg:tags": [
      "product"
    ],
    "wof:name": "Hawkins Hill Farm LLC",
    "wof:placetype": "venue"
  },
  "geometry": {"coordinates":[-81.420792,41.28459],"type":"Point"}
}
