{
  "type": "Feature",
  "properties": {
    "addr:full": "1370 Ontario St Cleveland OH 44113",
    "addr:housenumber": "1370",
    "addr:postcode": "44113",
    "addr:street": "Ontario St",
    "iso:country": "US",
    "sg:address": "1370 Ontario St",
    "sg:city": "Cleveland",
    "sg:classifiers": [
      {
        "category": "Real Estate",
        "subcategory": "Real Estate Agent",
        "type": "Services"
      }
    ],
    "sg:phone": "+1 216 363 6009",
    "sg:postcode": "44113",
    "sg:province": "OH",
    "sg:tags": [
      "company",
      "management"
    ],
    "wof:name": "L O M Inc",
    "wof:placetype": "venue"
  },
  "geometry": {"coordinates":[-81.695101,41.501244],"type":"Point"}
}
