{
  "type": "Feature",
  "properties": {
    "addr:full":"110 Bellaire Dr Painesville OH 44077",
    "addr:housenumber":"110",
    "addr:postcode":"44077",
    "addr:street":"Bellaire Dr",
    "iso:country":"US",
    "sg:address":"110 Bellaire Dr",
    "sg:city":"Painesville",
    "sg:classifiers":[
        {
            "category":"Organizations",
            "subcategory":"Religious Organization",
            "type":"Services"
        }
    ],
    "sg:phone":"+1 440 352 3244",
    "sg:postcode":"44077",
    "sg:province":"OH",
    "sg:tags":[
        "clergy"
    ],
    "wof:name":"Dennis Michelson",
    "wof:placetype":"venue"
},
  "geometry": {"coordinates":[-81.220929,41.711506],"type":"Point"}
}