{
  "type": "Feature",
  "properties": {
    "addr:full": "4322 Westland Mall Columbus OH 43228",
    "addr:housenumber": "4322",
    "addr:postcode": "43228",
    "addr:street": "Westland Mall",
    "iso:country": "US",
    "sg:address": "4322 Westland Mall",
    "sg:city": "Columbus",
    "sg:classifiers": [
      {
        "category": "Shopping",
        "subcategory": "Shoes",
        "type": "Retail Goods"
      }
    ],
    "sg:phone": "+1 614 274 2228",
    "sg:postcode": "43228",
    "sg:province": "OH",
    "wof:name": "Foot Locker",
    "wof:placetype": "venue"
  },
  "geometry": {"coordinates":[-83.115324,39.952733],"type":"Point"}
}
