{
  "type": "Feature",
  "properties": {
    "addr:full": "2 Emerald Way Franklin OH 45005",
    "addr:housenumber": "2",
    "addr:postcode": "45005",
    "addr:street": "Emerald Way",
    "iso:country": "US",
    "sg:address": "2 Emerald Way",
    "sg:city": "Franklin",
    "sg:classifiers": [
      {
        "category": "Real Estate",
        "subcategory": "Real Estate Operator",
        "type": "Services"
      }
    ],
    "sg:phone": "+1 937 743 1403",
    "sg:postcode": "45005",
    "sg:province": "OH",
    "sg:tags": [
      "building",
      "apartment"
    ],
    "wof:name": "Emerald Edge Apartments",
    "wof:placetype": "venue"
  },
  "geometry": {"coordinates":[-84.290939,39.561903],"type":"Point"}
}
