{
  "type": "Feature",
  "properties": {
    "addr:full": "161 N State St Painesville OH 44077",
    "addr:housenumber": "161",
    "addr:postcode": "44077",
    "addr:street": "N State St",
    "iso:country": "US",
    "sg:address": "161 N State St",
    "sg:city": "Painesville",
    "sg:classifiers": [
      {
        "category": "Health Services",
        "subcategory": "Health Practitioner",
        "type": "Services"
      }
    ],
    "sg:phone": "+1 440 354 6030",
    "sg:postcode": "44077",
    "sg:province": "OH",
    "sg:tags": [
      "psychologist"
    ],
    "wof:name": "James R Eisenberg",
    "wof:placetype": "venue"
  },
  "geometry": {"coordinates":[-81.243316,41.728942],"type":"Point"}
}
