{
  "type": "Feature",
  "properties": {
    "addr:full": "2242 S Main St Mansfield OH 44907",
    "addr:housenumber": "2242",
    "addr:postcode": "44907",
    "addr:street": "S Main St",
    "iso:country": "US",
    "sg:address": "2242 S Main St",
    "sg:city": "Mansfield",
    "sg:classifiers": [
      {
        "category": "Restaurant",
        "type": "Food \u0026 Drink"
      }
    ],
    "sg:menulink": "http://www.allmenus.com/oh/mansfield/170317-burger-king/menu/",
    "sg:phone": "+1 419 756 6999",
    "sg:postcode": "44907",
    "sg:province": "OH",
    "sg:tags": [
      "burger",
      "american"
    ],
    "wof:name": "Burger King",
    "wof:placetype": "venue"
  },
  "geometry": {"coordinates":[-82.511538,40.700297],"type":"Point"}
}
