{
  "type": "Feature",
  "properties": {
    "iso:country":"US",
    "sg:address":"10848 Chillicothe Rd",
    "sg:city":"Kirtland",
    "sg:classifiers":[
        {
            "category":"Organizations",
            "subcategory":"Religious Organization",
            "type":"Services"
        }
    ],
    "sg:phone":"+1 440 256 3400",
    "sg:postcode":"44094",
    "sg:province":"OH",
    "sg:tags":[
        "church"
    ],
    "sg:website":"www.eastshore.org",
    "wof:name":"East Shore Unitarian Universal",
    "wof:placetype":"venue"
},
  "geometry": {"coordinates":[-81.349142,41.572955],"type":"Point"}
}