{
  "type": "Feature",
  "properties": {
    "iso:country":"US",
    "sg:address":"470 White Pond Dr",
    "sg:city":"Akron",
    "sg:classifiers":[
        {
            "category":"Health Services",
            "subcategory":"Clinic",
            "type":"Services"
        }
    ],
    "sg:phone":"+1 330 864 9480",
    "sg:postcode":"44320",
    "sg:province":"OH",
    "sg:tags":[
        "pr",
        "medical",
        "examination",
        "insurance"
    ],
    "sg:website":"www.portamedic.com",
    "wof:name":"Portamedic 4",
    "wof:placetype":"venue"
},
  "geometry": {"coordinates":[-81.586725,41.100423],"type":"Point"}
}