{
  "type": "Feature",
  "properties": {
    "iso:country":"US",
    "sg:address":"1790 Town Park Blvd",
    "sg:city":"Uniontown",
    "sg:classifiers":[
        {
            "category":"Health Services",
            "subcategory":"Doctor",
            "type":"Services"
        }
    ],
    "sg:phone":"+1 330 899 0300",
    "sg:postcode":"44685",
    "sg:province":"OH",
    "sg:tags":[
        "physician",
        "surgeon"
    ],
    "wof:name":"Northeast Ohio Pediatric",
    "wof:placetype":"venue"
},
  "geometry": {"coordinates":[-81.46771,40.950563],"type":"Point"}
}