{
  "type": "Feature",
  "properties": {
    "addr:full": "5100 Springfield St Dayton OH 45431",
    "addr:housenumber": "5100",
    "addr:postcode": "45431",
    "addr:street": "Springfield St",
    "iso:country": "US",
    "sg:address": "5100 Springfield St",
    "sg:city": "Dayton",
    "sg:classifiers": [
      {
        "category": "Professional",
        "subcategory": "Computer Services",
        "type": "Services"
      }
    ],
    "sg:phone": "+1 937 910 6400",
    "sg:postcode": "45431",
    "sg:province": "OH",
    "sg:tags": [
      "prepackaged",
      "engineering",
      "software"
    ],
    "wof:name": "Adroit Systems",
    "wof:placetype": "venue"
  },
  "geometry": {"coordinates":[-84.118025,39.783149],"type":"Point"}
}
