{
  "type": "Feature",
  "properties": {
    "addr:full": "131 Central Ave Greenville OH 45331",
    "addr:housenumber": "131",
    "addr:postcode": "45331",
    "addr:street": "Central Ave",
    "iso:country": "US",
    "sg:address": "131 Central Ave",
    "sg:city": "Greenville",
    "sg:classifiers": [
      {
        "category": "Education",
        "subcategory": "School",
        "type": "Public Place"
      }
    ],
    "sg:phone": "+1 937 548 3202",
    "sg:postcode": "45331",
    "sg:province": "OH",
    "wof:name": "Greenville Junior High School",
    "wof:placetype": "venue"
  },
  "geometry": {"coordinates":[-84.633849,40.098955],"type":"Point"}
}
