{
  "type": "Feature",
  "properties": {
    "iso:country":"US",
    "sg:address":"197 Baranof E",
    "sg:city":"Westerville",
    "sg:classifiers":[
        {
            "category":"Shopping",
            "subcategory":"Hobbies, Toys, & Games",
            "type":"Retail Goods"
        }
    ],
    "sg:phone":"+1 614 882 3232",
    "sg:postcode":"43081",
    "sg:province":"OH",
    "wof:name":"Knots & Crafts",
    "wof:placetype":"venue"
},
  "geometry": {"coordinates":[-82.956936,40.129189],"type":"Point"}
}