{
  "type": "Feature",
  "properties": {
    "addr:full": "197 Baranof E Westerville OH 43081",
    "addr:housenumber": "197",
    "addr:postcode": "westerville oh 43081",
    "addr:street": "Baranof E",
    "iso:country": "US",
    "sg:address": "197 Baranof E",
    "sg:city": "Westerville",
    "sg:classifiers": [
      {
        "category": "Shopping",
        "subcategory": "Hobbies, Toys, \u0026 Games",
        "type": "Retail Goods"
      }
    ],
    "sg:phone": "+1 614 882 3232",
    "sg:postcode": "43081",
    "sg:province": "OH",
    "wof:name": "Knots \u0026 Crafts",
    "wof:placetype": "venue"
  },
  "geometry": {"coordinates":[-82.956936,40.129189],"type":"Point"}
}
