{
  "type": "Feature",
  "properties": {
    "iso:country":"US",
    "sg:address":"3701 Main St",
    "sg:city":"Hilliard",
    "sg:classifiers":[
        {
            "category":"Professional",
            "subcategory":"Computer Services",
            "type":"Services"
        }
    ],
    "sg:phone":"+1 614 777 1319",
    "sg:postcode":"43026",
    "sg:province":"OH",
    "sg:tags":[
        "repair"
    ],
    "wof:name":"Precision Laser Svc",
    "wof:placetype":"venue"
},
  "geometry": {"coordinates":[-83.161045,40.027538],"type":"Point"}
}