{
  "type": "Feature",
  "properties": {
    "addr:full": "3701 Main St Hilliard OH 43026",
    "addr:housenumber": "3701",
    "addr:postcode": "43026",
    "addr:street": "Main St",
    "iso:country": "US",
    "sg:address": "3701 Main St",
    "sg:city": "Hilliard",
    "sg:classifiers": [
      {
        "category": "Professional",
        "subcategory": "Computer Services",
        "type": "Services"
      }
    ],
    "sg:phone": "+1 614 777 1319",
    "sg:postcode": "43026",
    "sg:province": "OH",
    "sg:tags": [
      "repair"
    ],
    "wof:name": "Precision Laser Svc",
    "wof:placetype": "venue"
  },
  "geometry": {"coordinates":[-83.161045,40.027538],"type":"Point"}
}
