{
  "type": "Feature",
  "properties": {
    "addr:full":"26025 1st St Cleveland OH 44145",
    "addr:housenumber":"26025",
    "addr:postcode":"44145",
    "addr:street":"1St St",
    "iso:country":"US",
    "sg:address":"26025 1st St",
    "sg:city":"Cleveland",
    "sg:classifiers":[
        {
            "category":"Retail",
            "subcategory":"Auto Rental",
            "type":"Services"
        }
    ],
    "sg:phone":"+1 440 899 9520",
    "sg:postcode":"44145",
    "sg:province":"OH",
    "sg:tags":[
        "renting",
        "truck",
        "leasing"
    ],
    "sg:website":"www.penske.com",
    "wof:name":"Penske Truck Leasing",
    "wof:placetype":"venue"
},
  "geometry": {"coordinates":[-81.90952900000001,41.476228],"type":"Point"}
}