{
  "type": "Feature",
  "properties": {
    "addr:full": "693 Arbor Way Aurora OH 44202",
    "addr:housenumber": "693",
    "addr:postcode": "44202",
    "addr:street": "Arbor Way",
    "iso:country": "US",
    "sg:address": "693 Arbor Way",
    "sg:city": "Aurora",
    "sg:classifiers": [
      {
        "category": "Shopping",
        "subcategory": "Hobbies, Toys, \u0026 Games",
        "type": "Retail Goods"
      }
    ],
    "sg:phone": "+1 330 562 3594",
    "sg:postcode": "44202",
    "sg:province": "OH",
    "wof:name": "Aristocrafts Inc",
    "wof:placetype": "venue"
  },
  "geometry": {"coordinates":[-81.37014,41.29983],"type":"Point"}
}
