{
  "type": "Feature",
  "properties": {
    "iso:country":"US",
    "sg:address":"11470 Hawke Rd",
    "sg:city":"Columbia Station",
    "sg:classifiers":[
        {
            "category":"Wholesale",
            "subcategory":"Construction Materials",
            "type":"Manufacturing & Wholesale Goods"
        }
    ],
    "sg:phone":"+1 440 748 1044",
    "sg:postcode":"44028",
    "sg:province":"OH",
    "sg:tags":[
        "fence"
    ],
    "wof:name":"Dynasty Fence",
    "wof:placetype":"venue"
},
  "geometry": {"coordinates":[-81.971535,41.32709],"type":"Point"}
}