{
  "type": "Feature",
  "properties": {
    "addr:full":"509 Valewood Ct Englewood OH 45322",
    "addr:housenumber":"509",
    "addr:postcode":"45322",
    "addr:street":"Valewood Ct",
    "iso:country":"US",
    "sg:address":"509 Valewood Ct",
    "sg:city":"Englewood",
    "sg:classifiers":[
        {
            "category":"Organizations",
            "subcategory":"Non-profit Organization",
            "type":"Services"
        }
    ],
    "sg:phone":"+1 937 836 1897",
    "sg:postcode":"45322",
    "sg:province":"OH",
    "sg:tags":[
        "human"
    ],
    "wof:name":"Montgomery Dev Ctr Support Grp",
    "wof:placetype":"venue"
},
  "geometry": {"coordinates":[-84.30290599999999,39.858401],"type":"Point"}
}