{
  "type": "Feature",
  "properties": {
    "addr:full":"8 Main St Centerburg OH 43011",
    "addr:housenumber":"8",
    "addr:postcode":"43011",
    "addr:street":"Main St",
    "iso:country":"US",
    "sg:address":"8 Main St",
    "sg:city":"Centerburg",
    "sg:classifiers":[
        {
            "category":"Restaurant",
            "type":"Food & Drink"
        }
    ],
    "sg:phone":"+1 740 625 6800",
    "sg:postcode":"43011",
    "sg:province":"OH",
    "sg:tags":[
        "pizza"
    ],
    "wof:name":"D J's Pizza & Subs",
    "wof:placetype":"venue"
},
  "geometry": {"coordinates":[-82.695549,40.305002],"type":"Point"}
}