{
  "type": "Feature",
  "properties": {
    "iso:country":"US",
    "sg:address":"211 Orton St",
    "sg:city":"Marion",
    "sg:classifiers":[
        {
            "category":"Building & Trades",
            "subcategory":"Plumbing",
            "type":"Services"
        }
    ],
    "sg:phone":"+1 740 396 0326",
    "sg:postcode":"43302",
    "sg:province":"OH",
    "sg:tags":[
        "conditioning",
        "air",
        "system",
        "contractor"
    ],
    "wof:name":"Classic Heating & Air Cond",
    "wof:placetype":"venue"
},
  "geometry": {"coordinates":[-83.135155,40.619596],"type":"Point"}
}