{
  "type": "Feature",
  "properties": {
    "addr:full": "157 Sunny Ln NE Newark OH 43055",
    "addr:housenumber": "157",
    "addr:postcode": "43055",
    "addr:street": "Sunny Ln Ne",
    "iso:country": "US",
    "sg:address": "157 Sunny Ln NE",
    "sg:city": "Newark",
    "sg:classifiers": [
      {
        "category": "Retail",
        "subcategory": "Auto Repair",
        "type": "Services"
      }
    ],
    "sg:phone": "+1 740 345 3956",
    "sg:postcode": "43055",
    "sg:province": "OH",
    "sg:tags": [
      "repairing",
      "automobile"
    ],
    "wof:name": "Bud's Automotive",
    "wof:placetype": "venue"
  },
  "geometry": {"coordinates":[-82.264492,40.092472],"type":"Point"}
}
