{
  "type": "Feature",
  "properties": {
    "addr:full": "34659 Vine St Willoughby OH 44095",
    "addr:housenumber": "34659",
    "addr:postcode": "44095",
    "addr:street": "Vine St",
    "iso:country": "US",
    "sg:address": "34659 Vine St",
    "sg:city": "Willoughby",
    "sg:classifiers": [
      {
        "category": "Restaurant",
        "type": "Food \u0026 Drink"
      }
    ],
    "sg:phone": "+1 440 951 9773",
    "sg:postcode": "44095",
    "sg:province": "OH",
    "sg:tags": [
      "eating"
    ],
    "wof:name": "Mama Primozz Pizza and Catrg",
    "wof:placetype": "venue"
  },
  "geometry": {"coordinates":[-81.440953,41.642617],"type":"Point"}
}
