{
  "type": "Feature",
  "properties": {
    "addr:full":"1317 Euclid Ave Cleveland OH 44115",
    "addr:housenumber":"1317",
    "addr:postcode":"44115",
    "addr:street":"Euclid Ave",
    "iso:country":"US",
    "sg:address":"1317 Euclid Ave",
    "sg:city":"Cleveland",
    "sg:classifiers":[
        {
            "category":"Home & Garden",
            "subcategory":"Carpets & Floor Coverings",
            "type":"Retail Goods"
        }
    ],
    "sg:phone":"+1 216 241 5959",
    "sg:postcode":"44115",
    "sg:province":"OH",
    "sg:tags":[
        "dealer",
        "rug"
    ],
    "wof:name":"Haig Avedisian LTD Inc",
    "wof:placetype":"venue"
},
  "geometry": {"coordinates":[-81.68250500000001,41.500867],"type":"Point"}
}