{
  "type": "Feature",
  "properties": {
    "addr:full":"762 S Pearl St Columbus OH 43206",
    "addr:housenumber":"762",
    "addr:postcode":"43206",
    "addr:street":"S Pearl St",
    "iso:country":"US",
    "sg:address":"762 S Pearl St",
    "sg:city":"Columbus",
    "sg:classifiers":[
        {
            "category":"Professional",
            "subcategory":"Management & Consulting",
            "type":"Services"
        }
    ],
    "sg:phone":"+1 614 445 6962",
    "sg:postcode":"43206",
    "sg:province":"OH",
    "sg:tags":[
        "consultant",
        "business"
    ],
    "wof:name":"Altair Learning Management LLC",
    "wof:placetype":"venue"
},
  "geometry": {"coordinates":[-82.996658,39.94686],"type":"Point"}
}