{
  "type": "Feature",
  "properties": {
    "addr:full":"12025 Shore Rd Loveland OH 45140",
    "addr:housenumber":"12025",
    "addr:postcode":"45140",
    "addr:street":"Shore Rd",
    "iso:country":"US",
    "sg:address":"12025 Shore Rd",
    "sg:city":"Loveland",
    "sg:phone":"+1 513 683 4686",
    "sg:postcode":"45140",
    "sg:province":"OH",
    "wof:name":"Loveland Castle Museum",
    "wof:placetype":"venue"
},
  "geometry": {"coordinates":[-84.265137,39.285309],"type":"Point"}
}