{
  "type": "Feature",
  "properties": {
    "iso:country":"US",
    "sg:address":"58 E Waterloo St",
    "sg:city":"Canal Winchester",
    "sg:classifiers":[
        {
            "category":"Insurance",
            "subcategory":"Insurance Agent",
            "type":"Services"
        }
    ],
    "sg:phone":"+1 614 837 3099",
    "sg:postcode":"43110",
    "sg:province":"OH",
    "wof:name":"Timothy Leu",
    "wof:placetype":"venue"
},
  "geometry": {"coordinates":[-82.804641,39.842542],"type":"Point"}
}