{
  "type": "Feature",
  "properties": {
    "addr:full":"5126 Columbus Rd NE Louisville OH 44641",
    "addr:housenumber":"5126",
    "addr:postcode":"44641",
    "addr:street":"Columbus Rd Ne",
    "iso:country":"US",
    "sg:address":"5126 Columbus Rd NE",
    "sg:city":"Louisville",
    "sg:classifiers":[
        {
            "category":"Wholesale",
            "subcategory":"Computers",
            "type":"Manufacturing & Wholesale Goods"
        }
    ],
    "sg:phone":"+1 330 456 2267",
    "sg:postcode":"44641",
    "sg:province":"OH",
    "wof:name":"Stamp Gazetteer",
    "wof:placetype":"venue"
},
  "geometry": {"coordinates":[-81.306432,40.855381],"type":"Point"}
}