{
  "type": "Feature",
  "properties": {
    "iso:country":"US",
    "sg:address":"9398 Avemore Ct",
    "sg:city":"Dublin",
    "sg:classifiers":[
        {
            "category":"Restaurant",
            "type":"Food & Drink"
        }
    ],
    "sg:phone":"+1 614 764 9611",
    "sg:postcode":"43017",
    "sg:province":"OH",
    "sg:tags":[
        "eating"
    ],
    "wof:name":"Hays Hucek Inc",
    "wof:placetype":"venue"
},
  "geometry": {"coordinates":[-83.145622,40.155185],"type":"Point"}
}