{
  "type": "Feature",
  "properties": {
    "addr:full": "4929 Glenridge Cir NE Canton OH 44714",
    "addr:housenumber": "4929",
    "addr:postcode": "44714",
    "addr:street": "Glenridge Cir Ne",
    "iso:country": "US",
    "sg:address": "4929 Glenridge Cir NE",
    "sg:city": "Canton",
    "sg:classifiers": [
      {
        "category": "Professional",
        "subcategory": "Management \u0026 Consulting",
        "type": "Services"
      }
    ],
    "sg:phone": "+1 330 966 1676",
    "sg:postcode": "44714",
    "sg:province": "OH",
    "sg:tags": [
      "selling",
      "establishment",
      "direct"
    ],
    "wof:name": "Webwyse Corp",
    "wof:placetype": "venue"
  },
  "geometry": {"coordinates":[-81.357937,40.851699],"type":"Point"}
}
