{
  "type": "Feature",
  "properties": {
    "iso:country":"US",
    "sg:address":"231 E Broadway St",
    "sg:city":"Covington",
    "sg:classifiers":[
        {
            "category":"Real Estate",
            "subcategory":"Real Estate Operator",
            "type":"Services"
        }
    ],
    "sg:phone":"+1 937 473 3101",
    "sg:postcode":"45318",
    "sg:province":"OH",
    "sg:tags":[
        "property",
        "lessor"
    ],
    "wof:name":"Robert Gearhardt Farm",
    "wof:placetype":"venue"
},
  "geometry": {"coordinates":[-84.35172300000001,40.120989],"type":"Point"}
}