{
  "type": "Feature",
  "properties": {
    "addr:full": "1115 E Main St Jackson OH 45640",
    "addr:housenumber": "1115",
    "addr:postcode": "45640",
    "addr:street": "E Main St",
    "iso:country": "US",
    "sg:address": "1115 E Main St",
    "sg:city": "Jackson",
    "sg:classifiers": [
      {
        "category": "Shopping",
        "subcategory": "Clothing, Apparel, \u0026 Fashions",
        "type": "Retail Goods"
      }
    ],
    "sg:phone": "+1 740 288 4506",
    "sg:postcode": "45640",
    "sg:province": "OH",
    "sg:website": "www.catofashions.com",
    "wof:name": "Cato",
    "wof:placetype": "venue"
  },
  "geometry": {"coordinates":[-82.627081,39.036275],"type":"Point"}
}
