{
  "type": "Feature",
  "properties": {
    "iso:country":"US",
    "sg:address":"1115 E Main St",
    "sg:city":"Jackson",
    "sg:classifiers":[
        {
            "category":"Shopping",
            "subcategory":"Clothing, Apparel, & Fashions",
            "type":"Retail Goods"
        }
    ],
    "sg:phone":"+1 740 288 4506",
    "sg:postcode":"45640",
    "sg:province":"OH",
    "sg:website":"www.catofashions.com",
    "wof:name":"Cato",
    "wof:placetype":"venue"
},
  "geometry": {"coordinates":[-82.627081,39.036275],"type":"Point"}
}