{
  "type": "Feature",
  "properties": {
    "iso:country":"US",
    "sg:address":"3560 W Siebenthaler Ave",
    "sg:city":"Dayton",
    "sg:classifiers":[
        {
            "category":"Travel",
            "subcategory":"Campground",
            "type":"Entertainment"
        }
    ],
    "sg:phone":"+1 937 275 0433",
    "sg:postcode":"45406",
    "sg:province":"OH",
    "sg:tags":[
        "camp"
    ],
    "wof:name":"Camp KFC",
    "wof:placetype":"venue"
},
  "geometry": {"coordinates":[-84.246314,39.798022],"type":"Point"}
}