{
  "type": "Feature",
  "properties": {
    "addr:full":"1246 Ashland Ave Zanesville OH 43701",
    "addr:housenumber":"1246",
    "addr:postcode":"43701",
    "addr:street":"Ashland Ave",
    "iso:country":"US",
    "sg:address":"1246 Ashland Ave",
    "sg:city":"Zanesville",
    "sg:classifiers":[
        {
            "category":"Health Services",
            "subcategory":"Doctor",
            "type":"Services"
        }
    ],
    "sg:phone":"+1 740 450 4271",
    "sg:postcode":"43701",
    "sg:province":"OH",
    "sg:tags":[
        "physician",
        "surgeon"
    ],
    "wof:name":"Maria Jamiolkowski DO",
    "wof:placetype":"venue"
},
  "geometry": {"coordinates":[-82.012062,39.955011],"type":"Point"}
}