{
  "type": "Feature",
  "properties": {
    "addr:full":"2036 Woodville Rd Oregon OH 43616",
    "addr:housenumber":"2036",
    "addr:postcode":"43616",
    "addr:street":"Woodville Rd",
    "iso:country":"US",
    "sg:address":"2036 Woodville Rd",
    "sg:city":"Oregon",
    "sg:classifiers":[
        {
            "category":"Restaurant",
            "type":"Food & Drink"
        }
    ],
    "sg:menulink":"http://www.allmenus.com/oh/oregon/68792-marcos-pizza/menu/",
    "sg:phone":"+1 419 697 1131",
    "sg:postcode":"43616",
    "sg:province":"OH",
    "sg:tags":[
        "american",
        "pizza"
    ],
    "wof:name":"Marco's Pizza",
    "wof:placetype":"venue"
},
  "geometry": {"coordinates":[-83.50103900000001,41.625972],"type":"Point"}
}