{
  "type": "Feature",
  "properties": {
    "addr:full": "1728 Hilliard Rome Rd Hilliard OH 43026",
    "addr:housenumber": "1728",
    "addr:postcode": "43026",
    "addr:street": "Hilliard Rome Rd",
    "iso:country": "US",
    "sg:address": "1728 Hilliard Rome Rd",
    "sg:city": "Hilliard",
    "sg:classifiers": [
      {
        "category": "Professional",
        "subcategory": "Accounting \u0026 Tax Preparation",
        "type": "Services"
      }
    ],
    "sg:phone": "+1 614 777 9260",
    "sg:postcode": "43026",
    "sg:province": "OH",
    "sg:tags": [
      "return",
      "filing"
    ],
    "sg:website": "www.libertytax.com",
    "wof:name": "Liberty Tax Svc",
    "wof:placetype": "venue"
  },
  "geometry": {"coordinates":[-83.151819,39.991122],"type":"Point"}
}
