{
  "type": "Feature",
  "properties": {
    "addr:full": "3180 Pine Valley Rd Columbus OH 43219",
    "addr:housenumber": "3180",
    "addr:postcode": "43219",
    "addr:street": "Pine Valley Rd",
    "iso:country": "US",
    "sg:address": "3180 Pine Valley Rd",
    "sg:city": "Columbus",
    "sg:classifiers": [
      {
        "category": "Retail",
        "subcategory": "Repair Shop",
        "type": "Services"
      }
    ],
    "sg:phone": "+1 614 337 2700",
    "sg:postcode": "43219",
    "sg:province": "OH",
    "sg:tags": [
      "photography",
      "camera",
      "supply"
    ],
    "wof:name": "Whites Camera Shop \u0026 Repair",
    "wof:placetype": "venue"
  },
  "geometry": {"coordinates":[-82.921805,40.012401],"type":"Point"}
}
