{
  "type": "Feature",
  "properties": {
    "iso:country":"US",
    "sg:address":"3180 Pine Valley Rd",
    "sg:city":"Columbus",
    "sg:classifiers":[
        {
            "category":"Retail",
            "subcategory":"Repair Shop",
            "type":"Services"
        }
    ],
    "sg:phone":"+1 614 337 2700",
    "sg:postcode":"43219",
    "sg:province":"OH",
    "sg:tags":[
        "photography",
        "camera",
        "supply"
    ],
    "wof:name":"Whites Camera Shop & Repair",
    "wof:placetype":"venue"
},
  "geometry": {"coordinates":[-82.92180500000001,40.012401],"type":"Point"}
}