{
  "type": "Feature",
  "properties": {
    "addr:full": "3533 Southern Blvd Kettering OH 45429",
    "addr:housenumber": "3533",
    "addr:postcode": "45429",
    "addr:street": "Southern Blvd",
    "iso:country": "US",
    "sg:address": "3533 Southern Blvd",
    "sg:city": "Kettering",
    "sg:classifiers": [
      {
        "category": "Health Services",
        "subcategory": "Doctor",
        "type": "Services"
      }
    ],
    "sg:phone": "+1 937 643 9939",
    "sg:postcode": "45429",
    "sg:province": "OH",
    "sg:tags": [
      "physician",
      "surgeon"
    ],
    "wof:name": "Schuster Cardiology Assoc",
    "wof:placetype": "venue"
  },
  "geometry": {"coordinates":[-84.190862,39.697036],"type":"Point"}
}
