{
  "type": "Feature",
  "properties": {
    "iso:country":"US",
    "sg:address":"4311 W 145th St",
    "sg:city":"Cleveland",
    "sg:classifiers":[
        {
            "category":"Real Estate",
            "subcategory":"Real Estate Agent",
            "type":"Services"
        }
    ],
    "sg:phone":"+1 216 252 7029",
    "sg:postcode":"44135",
    "sg:province":"OH",
    "wof:name":"Core Investment Properties LLC",
    "wof:placetype":"venue"
},
  "geometry": {"coordinates":[-81.795966,41.437164],"type":"Point"}
}