{
  "type": "Feature",
  "properties": {
    "addr:full":"626 Brookfield Rd Brookfield OH 44403",
    "addr:housenumber":"626",
    "addr:postcode":"44403",
    "addr:street":"Brookfield Rd",
    "iso:country":"US",
    "sg:address":"626 Brookfield Rd",
    "sg:city":"Brookfield",
    "sg:classifiers":[
        {
            "category":"Building & Trades",
            "subcategory":"Construction",
            "type":"Services"
        }
    ],
    "sg:phone":"+1 330 448 1327",
    "sg:postcode":"44403",
    "sg:province":"OH",
    "sg:tags":[
        "general",
        "contractor"
    ],
    "wof:name":"Orenchak Builders",
    "wof:placetype":"venue"
},
  "geometry": {"coordinates":[-80.568078,41.228401],"type":"Point"}
}