{
  "type": "Feature",
  "properties": {
    "iso:country":"US",
    "sg:address":"6517 Glenway Ave",
    "sg:city":"Cincinnati",
    "sg:classifiers":[
        {
            "category":"Home & Garden",
            "subcategory":"Building Materials",
            "type":"Retail Goods"
        }
    ],
    "sg:phone":"+1 513 574 6117",
    "sg:postcode":"45211",
    "sg:province":"OH",
    "sg:tags":[
        "glass",
        "company"
    ],
    "wof:name":"Tri-State Glass America",
    "wof:placetype":"venue"
},
  "geometry": {"coordinates":[-84.628916,39.155264],"type":"Point"}
}