{
  "type": "Feature",
  "properties": {
    "iso:country":"US",
    "sg:address":"28310 Oregon Rd",
    "sg:city":"Perrysburg",
    "sg:classifiers":[
        {
            "category":"Banks & Credit Unions",
            "subcategory":"Bank",
            "type":"Services"
        }
    ],
    "sg:phone":"+1 419 666 1800",
    "sg:postcode":"43551",
    "sg:province":"OH",
    "sg:website":"www.mpfcu.org",
    "wof:name":"Cornerstone Community",
    "wof:placetype":"venue"
},
  "geometry": {"coordinates":[-83.537848,41.563689],"type":"Point"}
}