{
  "type": "Feature",
  "properties": {
    "iso:country":"US",
    "sg:address":"1120 Chester Ave",
    "sg:city":"Cleveland",
    "sg:classifiers":[
        {
            "category":"Real Estate",
            "subcategory":"Real Estate Services",
            "type":"Services"
        }
    ],
    "sg:phone":"+1 216 621 4057",
    "sg:postcode":"44114",
    "sg:province":"OH",
    "sg:tags":[
        "company",
        "title"
    ],
    "wof:name":"Guardian Title",
    "wof:placetype":"venue"
},
  "geometry": {"coordinates":[-81.685203,41.502036],"type":"Point"}
}