{
  "type": "Feature",
  "properties": {
    "iso:country":"US",
    "sg:address":"10286 Tarlton Rd",
    "sg:city":"Circleville",
    "sg:classifiers":[
        {
            "category":"Professional",
            "type":"Services"
        }
    ],
    "sg:phone":"+1 740 477 3010",
    "sg:postcode":"43113",
    "sg:province":"OH",
    "wof:name":"Mickey Stump",
    "wof:placetype":"venue"
},
  "geometry": {"coordinates":[-82.83779699999999,39.561099],"type":"Point"}
}