{
  "type": "Feature",
  "properties": {
    "iso:country":"US",
    "sg:address":"400 N 4th St",
    "sg:city":"Tipp City",
    "sg:classifiers":[
        {
            "category":"Building & Trades",
            "subcategory":"Construction",
            "type":"Services"
        }
    ],
    "sg:phone":"+1 937 667 5105",
    "sg:postcode":"45371",
    "sg:province":"OH",
    "sg:tags":[
        "contractor"
    ],
    "wof:name":"Stum Masonry Inc",
    "wof:placetype":"venue"
},
  "geometry": {"coordinates":[-84.172826,39.967423],"type":"Point"}
}