{
  "type": "Feature",
  "properties": {
    "iso:country":"US",
    "sg:address":"11609 Claridon Troy Rd",
    "sg:city":"Chardon",
    "sg:classifiers":[
        {
            "category":"Manufacturing",
            "subcategory":"Toys & Sporting Goods",
            "type":"Manufacturing & Wholesale Goods"
        }
    ],
    "sg:phone":"+1 440 635 0282",
    "sg:postcode":"44024",
    "sg:province":"OH",
    "sg:tags":[
        "mfg"
    ],
    "wof:name":"Field Specialties",
    "wof:placetype":"venue"
},
  "geometry": {"coordinates":[-81.144002,41.560836],"type":"Point"}
}