{
  "type": "Feature",
  "properties": {
    "addr:full": "842 Knox-School Rd Alliance OH 44601",
    "addr:housenumber": "842",
    "addr:postcode": "44601",
    "addr:street": "Knox-School Rd",
    "iso:country": "US",
    "sg:address": "842 Knox-School Rd",
    "sg:city": "Alliance",
    "sg:classifiers": [
      {
        "category": "Farming",
        "subcategory": "Farm",
        "type": "Manufacturing \u0026 Wholesale Goods"
      }
    ],
    "sg:phone": "+1 330 823 1040",
    "sg:postcode": "44601",
    "sg:province": "OH",
    "sg:tags": [
      "crop",
      "general"
    ],
    "wof:name": "Pork Chop Acres",
    "wof:placetype": "venue"
  },
  "geometry": {"coordinates":[-81.030983,40.891421],"type":"Point"}
}
