{
  "type": "Feature",
  "properties": {
    "addr:full":"113 William St Yorkville OH 43971",
    "addr:housenumber":"113",
    "addr:postcode":"43971",
    "addr:street":"William St",
    "iso:country":"US",
    "sg:address":"113 William St",
    "sg:city":"Yorkville",
    "sg:classifiers":[
        {
            "category":"Personal",
            "subcategory":"Barber",
            "type":"Services"
        }
    ],
    "sg:phone":"+1 740 859 2751",
    "sg:postcode":"43971",
    "sg:province":"OH",
    "wof:name":"Fior Barber Shop",
    "wof:placetype":"venue"
},
  "geometry": {"coordinates":[-80.70625800000001,40.1596],"type":"Point"}
}