{
  "type": "Feature",
  "properties": {
    "addr:full": "8871 Charington Ct Pickerington OH 43147",
    "addr:housenumber": "8871",
    "addr:postcode": "43147",
    "addr:street": "Charington Ct",
    "iso:country": "US",
    "sg:address": "8871 Charington Ct",
    "sg:city": "Pickerington",
    "sg:classifiers": [
      {
        "category": "Building \u0026 Trades",
        "subcategory": "Cleaning \u0026 Sanitation",
        "type": "Services"
      }
    ],
    "sg:phone": "+1 614 864 9400",
    "sg:postcode": "43147",
    "sg:province": "OH",
    "sg:tags": [
      "janitor"
    ],
    "wof:name": "Sterling Maids",
    "wof:placetype": "venue"
  },
  "geometry": {"coordinates":[-82.753888,39.92539],"type":"Point"}
}
