{
  "type": "Feature",
  "properties": {
    "iso:country":"US",
    "sg:address":"8871 Charington Ct",
    "sg:city":"Pickerington",
    "sg:classifiers":[
        {
            "category":"Building & Trades",
            "subcategory":"Cleaning & Sanitation",
            "type":"Services"
        }
    ],
    "sg:phone":"+1 614 864 9400",
    "sg:postcode":"43147",
    "sg:province":"OH",
    "sg:tags":[
        "janitor"
    ],
    "wof:name":"Sterling Maids",
    "wof:placetype":"venue"
},
  "geometry": {"coordinates":[-82.753888,39.92539],"type":"Point"}
}