{
  "type": "Feature",
  "properties": {
    "addr:full": "6801 Pearl Rd Cleveland OH 44130",
    "addr:housenumber": "6801",
    "addr:postcode": "44130",
    "addr:street": "Pearl Rd",
    "iso:country": "US",
    "sg:address": "6801 Pearl Rd",
    "sg:city": "Cleveland",
    "sg:classifiers": [
      {
        "category": "Health Services",
        "subcategory": "Optometrist",
        "type": "Services"
      }
    ],
    "sg:phone": "+1 440 845 3006",
    "sg:postcode": "44130",
    "sg:province": "OH",
    "wof:name": "Dr Richard E Holt \u0026 Associates",
    "wof:placetype": "venue"
  },
  "geometry": {"coordinates":[-81.785848,41.380199],"type":"Point"}
}
