{
  "type": "Feature",
  "properties": {
    "iso:country":"US",
    "sg:address":"6801 Pearl Rd",
    "sg:city":"Cleveland",
    "sg:classifiers":[
        {
            "category":"Health Services",
            "subcategory":"Optometrist",
            "type":"Services"
        }
    ],
    "sg:phone":"+1 440 845 3006",
    "sg:postcode":"44130",
    "sg:province":"OH",
    "wof:name":"Dr Richard E Holt & Associates",
    "wof:placetype":"venue"
},
  "geometry": {"coordinates":[-81.785848,41.380199],"type":"Point"}
}