{
  "type": "Feature",
  "properties": {
    "addr:full":"1870 Dayton Germantown Pike Germantown OH 45327",
    "addr:housenumber":"1870",
    "addr:postcode":"45327",
    "addr:street":"Dayton Germantown Pike",
    "iso:country":"US",
    "sg:address":"1870 Dayton Germantown Pike",
    "sg:city":"Germantown",
    "sg:classifiers":[
        {
            "category":"Health Services",
            "subcategory":"Doctor",
            "type":"Services"
        }
    ],
    "sg:phone":"+1 937 855 6006",
    "sg:postcode":"45327",
    "sg:province":"OH",
    "sg:tags":[
        "physician",
        "surgeon"
    ],
    "wof:name":"Providence Medical Grp",
    "wof:placetype":"venue"
},
  "geometry": {"coordinates":[-84.354247,39.633834],"type":"Point"}
}