{
  "type": "Feature",
  "properties": {
    "addr:full":"389 Niles Cortland Rd NE Warren OH 44484",
    "addr:housenumber":"389",
    "addr:postcode":"44484",
    "addr:street":"Niles Cortland Rd Ne",
    "iso:country":"US",
    "sg:address":"389 Niles Cortland Rd NE",
    "sg:city":"Warren",
    "sg:classifiers":[
        {
            "category":"Food & Beverages",
            "subcategory":"Specialty",
            "type":"Retail Goods"
        }
    ],
    "sg:phone":"+1 330 394 4448",
    "sg:postcode":"44484",
    "sg:province":"OH",
    "sg:tags":[
        "gourmet",
        "shop"
    ],
    "wof:name":"Go Gourmet",
    "wof:placetype":"venue"
},
  "geometry": {"coordinates":[-80.74063200000001,41.240496],"type":"Point"}
}