{
  "type": "Feature",
  "properties": {
    "iso:country":"US",
    "sg:address":"536 Canton Rd",
    "sg:city":"Akron",
    "sg:classifiers":[
        {
            "category":"Shopping",
            "subcategory":"Computers & Home Electronics",
            "type":"Retail Goods"
        }
    ],
    "sg:phone":"+1 330 784 8843",
    "sg:postcode":"44312",
    "sg:province":"OH",
    "wof:name":"Radio Shack",
    "wof:placetype":"venue"
},
  "geometry": {"coordinates":[-81.437549,41.04931],"type":"Point"}
}