{
  "type": "Feature",
  "properties": {
    "addr:full": "5865 Broadview Rd Cleveland OH 44134",
    "addr:housenumber": "5865",
    "addr:postcode": "44134",
    "addr:street": "Broadview Rd",
    "iso:country": "US",
    "sg:address": "5865 Broadview Rd",
    "sg:city": "Cleveland",
    "sg:classifiers": [
      {
        "category": "Real Estate",
        "subcategory": "Real Estate Agent",
        "type": "Services"
      }
    ],
    "sg:phone": "+1 216 741 7161",
    "sg:postcode": "44134",
    "sg:province": "OH",
    "wof:name": "Elm Realty",
    "wof:placetype": "venue"
  },
  "geometry": {"coordinates":[-81.690138,41.40368],"type":"Point"}
}
