{
  "type": "Feature",
  "properties": {
    "addr:full":"310 North St Caldwell OH 43724",
    "addr:housenumber":"310",
    "addr:postcode":"43724",
    "addr:street":"North St",
    "iso:country":"US",
    "sg:address":"310 North St",
    "sg:city":"Caldwell",
    "sg:classifiers":[
        {
            "category":"Professional",
            "type":"Services"
        }
    ],
    "sg:phone":"+1 740 732 1388",
    "sg:postcode":"43724",
    "sg:province":"OH",
    "wof:name":"K & K Svc",
    "wof:placetype":"venue"
},
  "geometry": {"coordinates":[-81.514948,39.747782],"type":"Point"}
}