{
  "type": "Feature",
  "properties": {
    "addr:full":"1690 Woodlands Dr Maumee OH 43537",
    "addr:housenumber":"1690",
    "addr:postcode":"43537",
    "addr:street":"Woodlands Dr",
    "iso:country":"US",
    "sg:address":"1690 Woodlands Dr",
    "sg:city":"Maumee",
    "sg:classifiers":[
        {
            "category":"Banks & Credit Unions",
            "subcategory":"Bank",
            "type":"Services"
        }
    ],
    "sg:phone":"+1 419 897 7958",
    "sg:postcode":"43537",
    "sg:province":"OH",
    "sg:tags":[
        "federal",
        "savings",
        "institution"
    ],
    "wof:name":"Ohio Savings Bank",
    "wof:placetype":"venue"
},
  "geometry": {"coordinates":[-83.685193,41.587086],"type":"Point"}
}