{
  "type": "Feature",
  "properties": {
    "iso:country":"US",
    "sg:address":"7716 Center St",
    "sg:city":"Mentor",
    "sg:classifiers":[
        {
            "category":"Building & Trades",
            "subcategory":"Construction",
            "type":"Services"
        }
    ],
    "sg:phone":"+1 440 255 0346",
    "sg:postcode":"44060",
    "sg:province":"OH",
    "sg:tags":[
        "concrete",
        "work"
    ],
    "wof:name":"LPT Inc",
    "wof:placetype":"venue"
},
  "geometry": {"coordinates":[-81.34018399999999,41.660523],"type":"Point"}
}