{
  "type": "Feature",
  "properties": {
    "addr:full":"2200 N Limestone St Springfield OH 45503",
    "addr:housenumber":"2200",
    "addr:postcode":"45503",
    "addr:street":"N Limestone St",
    "iso:country":"US",
    "sg:address":"2200 N Limestone St",
    "sg:city":"Springfield",
    "sg:classifiers":[
        {
            "category":"Health Services",
            "subcategory":"Doctor",
            "type":"Services"
        }
    ],
    "sg:phone":"+1 937 342 1018",
    "sg:postcode":"45503",
    "sg:province":"OH",
    "sg:tags":[
        "physician",
        "surgeon"
    ],
    "wof:name":"Arthur Neil Cole Inc",
    "wof:placetype":"venue"
},
  "geometry": {"coordinates":[-83.80388499999999,39.953286],"type":"Point"}
}