{
  "type": "Feature",
  "properties": {
    "addr:full": "3467 E Livingston Ave Columbus OH 43227",
    "addr:housenumber": "3467",
    "addr:postcode": "43227",
    "addr:street": "E Livingston Ave",
    "iso:country": "US",
    "sg:address": "3467 E Livingston Ave",
    "sg:city": "Columbus",
    "sg:classifiers": [
      {
        "category": "Banks \u0026 Credit Unions",
        "subcategory": "Bank",
        "type": "Services"
      }
    ],
    "sg:phone": "+1 614 231 3405",
    "sg:postcode": "43227",
    "sg:province": "OH",
    "sg:tags": [
      "loan",
      "real estate"
    ],
    "wof:name": "Quality Financial Svc",
    "wof:placetype": "venue"
  },
  "geometry": {"coordinates":[-82.902749,39.946119],"type":"Point"}
}
