{
  "type": "Feature",
  "properties": {
    "addr:full":"3189 State Rte 305 Warren OH 44410",
    "addr:housenumber":"3189",
    "addr:postcode":"44410",
    "addr:street":"State Rte 305",
    "iso:country":"US",
    "sg:address":"3189 State Rte 305",
    "sg:city":"Warren",
    "sg:classifiers":[
        {
            "category":"Manufacturing",
            "subcategory":"Lumber",
            "type":"Manufacturing & Wholesale Goods"
        }
    ],
    "sg:phone":"+1 330 847 8334",
    "sg:postcode":"44410",
    "sg:province":"OH",
    "sg:tags":[
        "company",
        "logging"
    ],
    "wof:name":"3 B's Logging",
    "wof:placetype":"venue"
},
  "geometry": {"coordinates":[-80.69355899999999,41.311262],"type":"Point"}
}