{
  "type": "Feature",
  "properties": {
    "iso:country":"US",
    "sg:address":"3790 Harding Hwy",
    "sg:city":"Lima",
    "sg:classifiers":[
        {
            "category":"Home & Garden",
            "subcategory":"Furniture",
            "type":"Retail Goods"
        }
    ],
    "sg:phone":"+1 419 225 9712",
    "sg:postcode":"45804",
    "sg:province":"OH",
    "sg:tags":[
        "store"
    ],
    "wof:name":"Buckeye Furniture",
    "wof:placetype":"venue"
},
  "geometry": {"coordinates":[-84.035803,40.731047],"type":"Point"}
}