{
  "type": "Feature",
  "properties": {
    "addr:full": "3790 Harding Hwy Lima OH 45804",
    "addr:housenumber": "3790",
    "addr:postcode": "45804",
    "addr:street": "Harding Hwy",
    "iso:country": "US",
    "sg:address": "3790 Harding Hwy",
    "sg:city": "Lima",
    "sg:classifiers": [
      {
        "category": "Home \u0026 Garden",
        "subcategory": "Furniture",
        "type": "Retail Goods"
      }
    ],
    "sg:phone": "+1 419 225 9712",
    "sg:postcode": "45804",
    "sg:province": "OH",
    "sg:tags": [
      "store"
    ],
    "wof:name": "Buckeye Furniture",
    "wof:placetype": "venue"
  },
  "geometry": {"coordinates":[-84.035803,40.731047],"type":"Point"}
}
