{
  "type": "Feature",
  "properties": {
    "addr:full":"1799 E 4th St Lima OH 45804",
    "addr:housenumber":"1799",
    "addr:postcode":"45804",
    "addr:street":"E 4Th St",
    "iso:country":"US",
    "sg:address":"1799 E 4th St",
    "sg:city":"Lima",
    "sg:classifiers":[
        {
            "category":"Manufacturing",
            "subcategory":"Metals",
            "type":"Manufacturing & Wholesale Goods"
        }
    ],
    "sg:phone":"+1 419 224 8324",
    "sg:postcode":"45804",
    "sg:province":"OH",
    "sg:tags":[
        "treating",
        "heat"
    ],
    "wof:name":"Heat Treating Technologies Inc",
    "wof:placetype":"venue"
},
  "geometry": {"coordinates":[-84.080968,40.716929],"type":"Point"}
}