{
  "type": "Feature",
  "properties": {
    "addr:full": "4210 Cedar Hill Rd NW Canal Winchester OH 43110",
    "addr:housenumber": "4210",
    "addr:postcode": "43110",
    "addr:street": "Cedar Hill Rd Nw",
    "iso:country": "US",
    "sg:address": "4210 Cedar Hill Rd NW",
    "sg:city": "Canal Winchester",
    "sg:classifiers": [
      {
        "category": "Organizations",
        "subcategory": "Religious Organization",
        "type": "Services"
      }
    ],
    "sg:phone": "+1 614 837 7122",
    "sg:postcode": "43110",
    "sg:province": "OH",
    "sg:tags": [
      "church"
    ],
    "wof:name": "Bloom Baptist Church",
    "wof:placetype": "venue"
  },
  "geometry": {"coordinates":[-82.804808,39.796283],"type":"Point"}
}
