{
  "type": "Feature",
  "properties": {
    "iso:country":"US",
    "sg:address":"6560 Royalton Rd",
    "sg:city":"Cleveland",
    "sg:classifiers":[
        {
            "category":"Building & Trades",
            "subcategory":"Plumbing",
            "type":"Services"
        }
    ],
    "sg:phone":"+1 440 230 9631",
    "sg:postcode":"44133",
    "sg:province":"OH",
    "sg:tags":[
        "conditioning",
        "air",
        "system",
        "contractor"
    ],
    "wof:name":"Air America Hvac Svc Inc",
    "wof:placetype":"venue"
},
  "geometry": {"coordinates":[-81.725117,41.31398],"type":"Point"}
}