{
  "type": "Feature",
  "properties": {
    "addr:full": "6560 Royalton Rd Cleveland OH 44133",
    "addr:housenumber": "6560",
    "addr:postcode": "44133",
    "addr:street": "Royalton Rd",
    "iso:country": "US",
    "sg:address": "6560 Royalton Rd",
    "sg:city": "Cleveland",
    "sg:classifiers": [
      {
        "category": "Building \u0026 Trades",
        "subcategory": "Plumbing",
        "type": "Services"
      }
    ],
    "sg:phone": "+1 440 230 9631",
    "sg:postcode": "44133",
    "sg:province": "OH",
    "sg:tags": [
      "conditioning",
      "air",
      "system",
      "contractor"
    ],
    "wof:name": "Air America Hvac Svc Inc",
    "wof:placetype": "venue"
  },
  "geometry": {"coordinates":[-81.725117,41.31398],"type":"Point"}
}
