{
  "type": "Feature",
  "properties": {
    "addr:full":"5040 E Walnut St Westerville OH 43081",
    "addr:housenumber":"5040",
    "addr:postcode":"43081",
    "addr:street":"E Walnut St",
    "iso:country":"US",
    "sg:address":"5040 E Walnut St",
    "sg:city":"Westerville",
    "sg:classifiers":[
        {
            "category":"Shopping",
            "subcategory":"Used Merchandise",
            "type":"Retail Goods"
        }
    ],
    "sg:phone":"+1 614 882 2112",
    "sg:postcode":"43081",
    "sg:province":"OH",
    "wof:name":"Oakbridge Antiques",
    "wof:placetype":"venue"
},
  "geometry": {"coordinates":[-82.854257,40.11494],"type":"Point"}
}