{
  "type": "Feature",
  "properties": {
    "iso:country":"US",
    "sg:address":"118 E Gambier St",
    "sg:city":"Mount Vernon",
    "sg:classifiers":[
        {
            "category":"Utilities",
            "subcategory":"Telephone",
            "type":"Services"
        }
    ],
    "sg:phone":"+1 740 397 3228",
    "sg:postcode":"43050",
    "sg:province":"OH",
    "sg:tags":[
        "communications"
    ],
    "wof:name":"Arete Neolith Inc",
    "wof:placetype":"venue"
},
  "geometry": {"coordinates":[-82.482662,40.391512],"type":"Point"}
}