{
  "type": "Feature",
  "properties": {
    "addr:full":"103 Coventry Dr Painesville OH 44077",
    "addr:housenumber":"103",
    "addr:postcode":"44077",
    "addr:street":"Coventry Dr",
    "iso:country":"US",
    "sg:address":"103 Coventry Dr",
    "sg:city":"Painesville",
    "sg:classifiers":[
        {
            "category":"Banks & Credit Unions",
            "subcategory":"Investment Brokerage",
            "type":"Services"
        }
    ],
    "sg:phone":"+1 440 352 4008",
    "sg:postcode":"44077",
    "sg:province":"OH",
    "sg:tags":[
        "retirement",
        "planning"
    ],
    "wof:name":"Otter Retirement & Cnsltng",
    "wof:placetype":"venue"
},
  "geometry": {"coordinates":[-81.271945,41.693135],"type":"Point"}
}