{
  "type": "Feature",
  "properties": {
    "addr:full": "16114 Chagrin Blvd Cleveland OH 44120",
    "addr:housenumber": "16114",
    "addr:postcode": "44120",
    "addr:street": "Chagrin Blvd",
    "iso:country": "US",
    "sg:address": "16114 Chagrin Blvd",
    "sg:city": "Cleveland",
    "sg:classifiers": [
      {
        "category": "Personal",
        "subcategory": "Beauty Salon",
        "type": "Services"
      }
    ],
    "sg:phone": "+1 216 283 0100",
    "sg:postcode": "44120",
    "sg:province": "OH",
    "wof:name": "P J's II Beauty Salon",
    "wof:placetype": "venue"
  },
  "geometry": {"coordinates":[-81.567592,41.464369],"type":"Point"}
}
