{
  "type": "Feature",
  "properties": {
    "iso:country":"US",
    "sg:address":"1551 Vienna Rd",
    "sg:city":"Vienna",
    "sg:classifiers":[
        {
            "category":"Wholesale",
            "subcategory":"Metals & Minerals",
            "type":"Manufacturing & Wholesale Goods"
        }
    ],
    "sg:phone":"+1 330 609 5137",
    "sg:postcode":"44446",
    "sg:province":"OH",
    "sg:tags":[
        "steel",
        "warehouse",
        "distributor"
    ],
    "wof:name":"Timken Latrobe Steel Dist",
    "wof:placetype":"venue"
},
  "geometry": {"coordinates":[-80.738222,41.194399],"type":"Point"}
}