{
  "type": "Feature",
  "properties": {
    "addr:full": "1551 Vienna Rd Vienna OH 44446",
    "addr:housenumber": "1551",
    "addr:postcode": "44446",
    "addr:street": "Vienna Rd",
    "iso:country": "US",
    "sg:address": "1551 Vienna Rd",
    "sg:city": "Vienna",
    "sg:classifiers": [
      {
        "category": "Wholesale",
        "subcategory": "Metals \u0026 Minerals",
        "type": "Manufacturing \u0026 Wholesale Goods"
      }
    ],
    "sg:phone": "+1 330 609 5137",
    "sg:postcode": "44446",
    "sg:province": "OH",
    "sg:tags": [
      "steel",
      "warehouse",
      "distributor"
    ],
    "wof:name": "Timken Latrobe Steel Dist",
    "wof:placetype": "venue"
  },
  "geometry": {"coordinates":[-80.738222,41.194399],"type":"Point"}
}
