{
  "type": "Feature",
  "properties": {
    "addr:full": "5324 Fleet Ave Cleveland OH 44105",
    "addr:housenumber": "5324",
    "addr:postcode": "44105",
    "addr:street": "Fleet Ave",
    "iso:country": "US",
    "sg:address": "5324 Fleet Ave",
    "sg:city": "Cleveland",
    "sg:classifiers": [
      {
        "category": "Food \u0026 Beverages",
        "subcategory": "Meat \u0026 Fish",
        "type": "Retail Goods"
      }
    ],
    "sg:phone": "+1 216 271 4575",
    "sg:postcode": "44105",
    "sg:province": "OH",
    "wof:name": "Jaworski Meat Market \u0026 Deli",
    "wof:placetype": "venue"
  },
  "geometry": {"coordinates":[-81.652308,41.455833],"type":"Point"}
}
