{
  "type": "Feature",
  "properties": {
    "iso:country":"US",
    "sg:address":"5324 Fleet Ave",
    "sg:city":"Cleveland",
    "sg:classifiers":[
        {
            "category":"Food & Beverages",
            "subcategory":"Meat & Fish",
            "type":"Retail Goods"
        }
    ],
    "sg:phone":"+1 216 271 4575",
    "sg:postcode":"44105",
    "sg:province":"OH",
    "wof:name":"Jaworski Meat Market & Deli",
    "wof:placetype":"venue"
},
  "geometry": {"coordinates":[-81.652308,41.455833],"type":"Point"}
}