{
  "type": "Feature",
  "properties": {
    "addr:full": "145 E Main St St Clairsville OH 43950",
    "addr:housenumber": "145",
    "addr:postcode": "43950",
    "addr:street": "E Main St",
    "iso:country": "US",
    "sg:address": "145 E Main St",
    "sg:city": "St Clairsville",
    "sg:classifiers": [
      {
        "category": "Professional",
        "subcategory": "Business Services",
        "type": "Services"
      }
    ],
    "sg:phone": "+1 740 695 4500",
    "sg:postcode": "43950",
    "sg:province": "OH",
    "sg:tags": [
      "painter",
      "sign"
    ],
    "wof:name": "Raymond Sign Technology",
    "wof:placetype": "venue"
  },
  "geometry": {"coordinates":[-80.899323,40.080821],"type":"Point"}
}
