{
  "type": "Feature",
  "properties": {
    "addr:full": "8600 Cedar Ave Cleveland OH 44106",
    "addr:housenumber": "8600",
    "addr:postcode": "44106",
    "addr:street": "Cedar Ave",
    "iso:country": "US",
    "sg:address": "8600 Cedar Ave",
    "sg:city": "Cleveland",
    "sg:classifiers": [
      {
        "category": "Building \u0026 Trades",
        "subcategory": "Construction",
        "type": "Services"
      }
    ],
    "sg:phone": "+1 216 791 6711",
    "sg:postcode": "44106",
    "sg:province": "OH",
    "sg:tags": [
      "home",
      "improvement"
    ],
    "wof:name": "Pearlrock Companies",
    "wof:placetype": "venue"
  },
  "geometry": {"coordinates":[-81.625924,41.499762],"type":"Point"}
}
