{
  "type": "Feature",
  "properties": {
    "addr:full":"786 Farview Ave Lebanon OH 45036",
    "addr:housenumber":"786",
    "addr:postcode":"45036",
    "addr:street":"Farview Ave",
    "iso:country":"US",
    "sg:address":"786 Farview Ave",
    "sg:city":"Lebanon",
    "sg:classifiers":[
        {
            "category":"Real Estate",
            "subcategory":"Real Estate Agent",
            "type":"Services"
        }
    ],
    "sg:phone":"+1 513 932 2857",
    "sg:postcode":"45036",
    "sg:province":"OH",
    "wof:name":"Cincinnati Management Co",
    "wof:placetype":"venue"
},
  "geometry": {"coordinates":[-84.21569700000001,39.448464],"type":"Point"}
}