{
  "type": "Feature",
  "properties": {
    "iso:country":"US",
    "sg:address":"6986 Old Tarlton Pike",
    "sg:city":"Circleville",
    "sg:classifiers":[
        {
            "category":"Insurance",
            "subcategory":"Hazard Insurance",
            "type":"Services"
        }
    ],
    "sg:phone":"+1 740 420 0000",
    "sg:postcode":"43113",
    "sg:province":"OH",
    "sg:tags":[
        "bond"
    ],
    "wof:name":"A-1 Bail Bonds Inc",
    "wof:placetype":"venue"
},
  "geometry": {"coordinates":[-82.906446,39.586838],"type":"Point"}
}