{
  "type": "Feature",
  "properties": {
    "addr:full": "28132 E Broadway St Walbridge OH 43465",
    "addr:housenumber": "28132",
    "addr:postcode": "43465",
    "addr:street": "E Broadway St",
    "iso:country": "US",
    "sg:address": "28132 E Broadway St",
    "sg:city": "Walbridge",
    "sg:classifiers": [
      {
        "category": "Personal",
        "subcategory": "Beauty Salon",
        "type": "Services"
      }
    ],
    "sg:phone": "+1 419 838 6285",
    "sg:postcode": "43465",
    "sg:province": "OH",
    "wof:name": "Snip Snap \u0026 Smiles",
    "wof:placetype": "venue"
  },
  "geometry": {"coordinates":[-83.511688,41.561326],"type":"Point"}
}
