{
  "type": "Feature",
  "properties": {
    "iso:country":"US",
    "sg:address":"29299 Clemens Rd",
    "sg:city":"Cleveland",
    "sg:classifiers":[
        {
            "category":"Communications",
            "subcategory":"Film & Video Production",
            "type":"Services"
        }
    ],
    "sg:phone":"+1 440 617 0220",
    "sg:postcode":"44145",
    "sg:province":"OH",
    "sg:tags":[
        "taping"
    ],
    "wof:name":"Vital Video",
    "wof:placetype":"venue"
},
  "geometry": {"coordinates":[-81.94377299999999,41.470454],"type":"Point"}
}