{
  "type": "Feature",
  "properties": {
    "addr:full": "29299 Clemens Rd Cleveland OH 44145",
    "addr:housenumber": "29299",
    "addr:postcode": "44145",
    "addr:street": "Clemens Rd",
    "iso:country": "US",
    "sg:address": "29299 Clemens Rd",
    "sg:city": "Cleveland",
    "sg:classifiers": [
      {
        "category": "Communications",
        "subcategory": "Film \u0026 Video Production",
        "type": "Services"
      }
    ],
    "sg:phone": "+1 440 617 0220",
    "sg:postcode": "44145",
    "sg:province": "OH",
    "sg:tags": [
      "taping"
    ],
    "wof:name": "Vital Video",
    "wof:placetype": "venue"
  },
  "geometry": {"coordinates":[-81.943773,41.470454],"type":"Point"}
}
