{
  "type": "Feature",
  "properties": {
    "addr:full":"4037 State Rd Cuyahoga Falls OH 44223",
    "addr:housenumber":"4037",
    "addr:postcode":"44223",
    "addr:street":"State Rd",
    "iso:country":"US",
    "sg:address":"4037 State Rd",
    "sg:city":"Cuyahoga Falls",
    "sg:classifiers":[
        {
            "category":"Restaurant",
            "type":"Food & Drink"
        }
    ],
    "sg:phone":"+1 330 929 2940",
    "sg:postcode":"44223",
    "sg:province":"OH",
    "wof:name":"Athena's",
    "wof:placetype":"venue"
},
  "geometry": {"coordinates":[-81.508503,41.182756],"type":"Point"}
}