{
  "type": "Feature",
  "properties": {
    "iso:country":"US",
    "sg:address":"410 Dayton St",
    "sg:city":"Cincinnati",
    "sg:classifiers":[
        {
            "category":"Arts & Performance",
            "subcategory":"Theater",
            "type":"Entertainment"
        }
    ],
    "sg:phone":"+1 513 651 0888",
    "sg:postcode":"45214",
    "sg:province":"OH",
    "sg:tags":[
        "entertainer"
    ],
    "wof:name":"On Impact Entertainment",
    "wof:placetype":"venue"
},
  "geometry": {"coordinates":[-84.525761,39.118289],"type":"Point"}
}