{
  "type": "Feature",
  "properties": {
    "addr:full":"25700 Science Park Dr Cleveland OH 44122",
    "addr:housenumber":"25700",
    "addr:postcode":"44122",
    "addr:street":"Science Park Dr",
    "iso:country":"US",
    "sg:address":"25700 Science Park Dr",
    "sg:city":"Cleveland",
    "sg:classifiers":[
        {
            "category":"Professional",
            "type":"Services"
        }
    ],
    "sg:phone":"+1 216 378 0688",
    "sg:postcode":"44122",
    "sg:province":"OH",
    "wof:name":"Dennis Barba",
    "wof:placetype":"venue"
},
  "geometry": {"coordinates":[-81.49778499999999,41.470304],"type":"Point"}
}