{
  "type": "Feature",
  "properties": {
    "addr:full":"640 S Main St Monroe OH 45050",
    "addr:housenumber":"640",
    "addr:postcode":"45050",
    "addr:street":"S Main St",
    "iso:country":"US",
    "sg:address":"640 S Main St",
    "sg:city":"Monroe",
    "sg:classifiers":[
        {
            "category":"Personal",
            "subcategory":"Beauty Salon",
            "type":"Services"
        }
    ],
    "sg:phone":"+1 513 539 7816",
    "sg:postcode":"45050",
    "sg:province":"OH",
    "sg:tags":[
        "manicuring"
    ],
    "wof:name":"Monroe Nails",
    "wof:placetype":"venue"
},
  "geometry": {"coordinates":[-84.365403,39.433767],"type":"Point"}
}