{
  "type": "Feature",
  "properties": {
    "addr:full":"436 W Columbia St Springfield OH 45504",
    "addr:housenumber":"436",
    "addr:postcode":"45504",
    "addr:street":"W Columbia St",
    "iso:country":"US",
    "sg:address":"436 W Columbia St",
    "sg:city":"Springfield",
    "sg:classifiers":[
        {
            "category":"Social Services",
            "subcategory":"Job Training",
            "type":"Services"
        }
    ],
    "sg:phone":"+1 937 323 4077",
    "sg:postcode":"45504",
    "sg:province":"OH",
    "sg:tags":[
        "retardation",
        "disabled",
        "mental",
        "dev"
    ],
    "wof:name":"Consumer Support Svc",
    "wof:placetype":"venue"
},
  "geometry": {"coordinates":[-83.81791,39.926398],"type":"Point"}
}