{
  "type": "Feature",
  "properties": {
    "addr:full":"299 Deo Dr Newark OH 43055",
    "addr:housenumber":"299",
    "addr:postcode":"43055",
    "addr:street":"Deo Dr",
    "iso:country":"US",
    "sg:address":"299 Deo Dr",
    "sg:city":"Newark",
    "sg:classifiers":[
        {
            "category":"Freight",
            "type":"Transportation"
        },
        {
            "category":"Professional",
            "subcategory":"Business Services",
            "type":"Services"
        }
    ],
    "sg:phone":"+1 740 366 1325",
    "sg:postcode":"43055",
    "sg:province":"OH",
    "sg:tags":[
        "packaging",
        "printing",
        "shipping"
    ],
    "wof:name":"Express Pack N Ship",
    "wof:placetype":"venue"
},
  "geometry": {"coordinates":[-82.420461,40.08605],"type":"Point"}
}