{
  "type": "Feature",
  "properties": {
    "addr:full": "8598 Main St Kinsman OH 44428",
    "addr:housenumber": "8598",
    "addr:postcode": "44428",
    "addr:street": "Main St",
    "iso:country": "US",
    "sg:address": "8598 Main St",
    "sg:city": "Kinsman",
    "sg:classifiers": [
      {
        "category": "Home \u0026 Garden",
        "subcategory": "Hardware",
        "type": "Retail Goods"
      }
    ],
    "sg:phone": "+1 330 876 4405",
    "sg:postcode": "44428",
    "sg:province": "OH",
    "wof:name": "Kinsman Supply \u0026 Rental Inc",
    "wof:placetype": "venue"
  },
  "geometry": {"coordinates":[-80.579445,41.455464],"type":"Point"}
}
