{
  "type": "Feature",
  "properties": {
    "iso:country":"US",
    "sg:address":"8598 Main St",
    "sg:city":"Kinsman",
    "sg:classifiers":[
        {
            "category":"Home & Garden",
            "subcategory":"Hardware",
            "type":"Retail Goods"
        }
    ],
    "sg:phone":"+1 330 876 4405",
    "sg:postcode":"44428",
    "sg:province":"OH",
    "wof:name":"Kinsman Supply & Rental Inc",
    "wof:placetype":"venue"
},
  "geometry": {"coordinates":[-80.57944500000001,41.455464],"type":"Point"}
}