{
  "type": "Feature",
  "properties": {
    "addr:full": "2302 8th St Portsmouth OH 45662",
    "addr:housenumber": "2302",
    "addr:postcode": "45662",
    "addr:street": "8Th St",
    "iso:country": "US",
    "sg:address": "2302 8th St",
    "sg:city": "Portsmouth",
    "sg:classifiers": [
      {
        "category": "Building \u0026 Trades",
        "subcategory": "Plumbing",
        "type": "Services"
      }
    ],
    "sg:phone": "+1 740 353 5668",
    "sg:postcode": "45662",
    "sg:province": "OH",
    "sg:tags": [
      "plumbing",
      "contractor",
      "heating",
      "conditioning",
      "air"
    ],
    "wof:name": "Mechanical Construction Co",
    "wof:placetype": "venue"
  },
  "geometry": {"coordinates":[-82.971462,38.735815],"type":"Point"}
}
