{
  "type": "Feature",
  "properties": {
    "iso:country":"US",
    "sg:address":"9175 Allen Rd",
    "sg:city":"West Chester",
    "sg:classifiers":[
        {
            "category":"Wholesale",
            "subcategory":"Groceries",
            "type":"Manufacturing & Wholesale Goods"
        }
    ],
    "sg:phone":"+1 513 860 2146",
    "sg:postcode":"45069",
    "sg:province":"OH",
    "sg:tags":[
        "tea",
        "coffee"
    ],
    "wof:name":"Millstone Coffee Inc",
    "wof:placetype":"venue"
},
  "geometry": {"coordinates":[-84.435354,39.323982],"type":"Point"}
}