{
  "type": "Feature",
  "properties": {
    "iso:country":"US",
    "sg:address":"7887 Washington Park Dr",
    "sg:city":"Dayton",
    "sg:classifiers":[
        {
            "category":"Banks & Credit Unions",
            "subcategory":"Bank",
            "type":"Services"
        }
    ],
    "sg:phone":"+1 937 432 0821",
    "sg:postcode":"45459",
    "sg:province":"OH",
    "sg:tags":[
        "mortgage"
    ],
    "wof:name":"First Place Bank",
    "wof:placetype":"venue"
},
  "geometry": {"coordinates":[-84.210404,39.635546],"type":"Point"}
}