{
  "type": "Feature",
  "properties": {
    "addr:full": "737 Industrial Blvd Wooster OH 44691",
    "addr:housenumber": "737",
    "addr:postcode": "44691",
    "addr:street": "Industrial Blvd",
    "iso:country": "US",
    "sg:address": "737 Industrial Blvd",
    "sg:city": "Wooster",
    "sg:classifiers": [
      {
        "category": "Retail",
        "subcategory": "Auto Repair",
        "type": "Services"
      }
    ],
    "sg:phone": "+1 330 264 9237",
    "sg:postcode": "44691",
    "sg:province": "OH",
    "sg:tags": [
      "truck",
      "retread",
      "tire"
    ],
    "wof:name": "K-S Bandag Inc",
    "wof:placetype": "venue"
  },
  "geometry": {"coordinates":[-81.917747,40.800692],"type":"Point"}
}
