{
  "type": "Feature",
  "properties": {
    "addr:full": "8081 State Rte 366 Russells Point OH 43348",
    "addr:housenumber": "8081",
    "addr:postcode": "43348",
    "addr:street": "State Rte 366",
    "iso:country": "US",
    "sg:address": "8081 State Rte 366",
    "sg:city": "Russells Point",
    "sg:classifiers": [
      {
        "category": "Manufacturing",
        "subcategory": "Building Materials",
        "type": "Manufacturing \u0026 Wholesale Goods"
      }
    ],
    "sg:phone": "+1 937 843 6076",
    "sg:postcode": "43348",
    "sg:province": "OH",
    "sg:tags": [
      "cabinet"
    ],
    "wof:name": "Castle Cabinets \u0026 Counter Tops",
    "wof:placetype": "venue"
  },
  "geometry": {"coordinates":[-83.869896,40.468486],"type":"Point"}
}
