{
  "type": "Feature",
  "properties": {
    "iso:country":"US",
    "sg:address":"8081 State Rte 366",
    "sg:city":"Russells Point",
    "sg:classifiers":[
        {
            "category":"Manufacturing",
            "subcategory":"Building Materials",
            "type":"Manufacturing & Wholesale Goods"
        }
    ],
    "sg:phone":"+1 937 843 6076",
    "sg:postcode":"43348",
    "sg:province":"OH",
    "sg:tags":[
        "cabinet"
    ],
    "wof:name":"Castle Cabinets & Counter Tops",
    "wof:placetype":"venue"
},
  "geometry": {"coordinates":[-83.869896,40.468486],"type":"Point"}
}