{
  "type": "Feature",
  "properties": {
    "addr:full":"4360 Fulton Dr NW Canton OH 44718",
    "addr:housenumber":"4360",
    "addr:postcode":"44718",
    "addr:street":"Fulton Dr Nw",
    "iso:country":"US",
    "sg:address":"4360 Fulton Dr NW",
    "sg:city":"Canton",
    "sg:classifiers":[
        {
            "category":"Health Services",
            "subcategory":"Doctor",
            "type":"Services"
        }
    ],
    "sg:phone":"+1 330 489 1445",
    "sg:postcode":"44718",
    "sg:province":"OH",
    "sg:tags":[
        "medical"
    ],
    "wof:name":"James F King MD",
    "wof:placetype":"venue"
},
  "geometry": {"coordinates":[-81.430575,40.84089],"type":"Point"}
}