{
  "type": "Feature",
  "properties": {
    "iso:country":"US",
    "sg:address":"1072 Fire Ln",
    "sg:city":"Harrisburg",
    "sg:classifiers":[
        {
            "category":"Building & Trades",
            "subcategory":"Construction",
            "type":"Services"
        }
    ],
    "sg:phone":"+1 614 877 3638",
    "sg:postcode":"43126",
    "sg:province":"OH",
    "sg:tags":[
        "marking",
        "maintenance",
        "parking"
    ],
    "wof:name":"Harrisburg Vlg Street Dept",
    "wof:placetype":"venue"
},
  "geometry": {"coordinates":[-83.170503,39.810417],"type":"Point"}
}