{
  "type": "Feature",
  "properties": {
    "addr:full": "2520 Port Clinton Rd Fremont OH 43420",
    "addr:housenumber": "2520",
    "addr:postcode": "43420",
    "addr:street": "Port Clinton Rd",
    "iso:country": "US",
    "sg:address": "2520 Port Clinton Rd",
    "sg:city": "Fremont",
    "sg:classifiers": [
      {
        "category": "Organizations",
        "subcategory": "Membership Organization",
        "type": "Services"
      }
    ],
    "sg:phone": "+1 419 334 4517",
    "sg:postcode": "43420",
    "sg:province": "OH",
    "sg:tags": [
      "society",
      "humane"
    ],
    "wof:name": "Humane Society Of Sandusky Inc",
    "wof:placetype": "venue"
  },
  "geometry": {"coordinates":[-83.10611,41.381639],"type":"Point"}
}
