{
  "type": "Feature",
  "properties": {
    "addr:full": "63 W Main St Newark OH 43055",
    "addr:housenumber": "63",
    "addr:postcode": "43055",
    "addr:street": "W Main St",
    "iso:country": "US",
    "sg:address": "63 W Main St",
    "sg:city": "Newark",
    "sg:classifiers": [
      {
        "category": "Insurance",
        "subcategory": "Insurance Agent",
        "type": "Services"
      }
    ],
    "sg:phone": "+1 740 345 9574",
    "sg:postcode": "43055",
    "sg:province": "OH",
    "wof:name": "Weiland Paul Ins",
    "wof:placetype": "venue"
  },
  "geometry": {"coordinates":[-82.405836,40.056711],"type":"Point"}
}
