{
  "type": "Feature",
  "properties": {
    "iso:country":"US",
    "sg:address":"4609 Wing View Ln",
    "sg:city":"Dayton",
    "sg:classifiers":[
        {
            "category":"Wholesale",
            "subcategory":"Machinery & Supplies",
            "type":"Manufacturing & Wholesale Goods"
        },
        {
            "category":"Wholesale",
            "subcategory":"Electrical",
            "type":"Manufacturing & Wholesale Goods"
        }
    ],
    "sg:phone":"+1 937 434 8240",
    "sg:postcode":"45429",
    "sg:province":"OH",
    "sg:tags":[
        "fire",
        "equipment",
        "alarm",
        "establishment",
        "system"
    ],
    "wof:name":"Fyr-Fyter Sales & Service Inc",
    "wof:placetype":"venue"
},
  "geometry": {"coordinates":[-84.15647800000001,39.679601],"type":"Point"}
}