{
  "type": "Feature",
  "properties": {
    "addr:full": "4609 Wing View Ln Dayton OH 45429",
    "addr:housenumber": "4609",
    "addr:postcode": "45429",
    "addr:street": "Wing View Ln",
    "iso:country": "US",
    "sg:address": "4609 Wing View Ln",
    "sg:city": "Dayton",
    "sg:classifiers": [
      {
        "category": "Wholesale",
        "subcategory": "Machinery \u0026 Supplies",
        "type": "Manufacturing \u0026 Wholesale Goods"
      },
      {
        "category": "Wholesale",
        "subcategory": "Electrical",
        "type": "Manufacturing \u0026 Wholesale Goods"
      }
    ],
    "sg:phone": "+1 937 434 8240",
    "sg:postcode": "45429",
    "sg:province": "OH",
    "sg:tags": [
      "fire",
      "equipment",
      "alarm",
      "establishment",
      "system"
    ],
    "wof:name": "Fyr-Fyter Sales \u0026 Service Inc",
    "wof:placetype": "venue"
  },
  "geometry": {"coordinates":[-84.156478,39.679601],"type":"Point"}
}
