{
  "type": "Feature",
  "properties": {
    "iso:country":"US",
    "sg:address":"3547 Kehr Rd",
    "sg:city":"Oxford",
    "sg:classifiers":[
        {
            "category":"Shopping",
            "type":"Retail Goods"
        }
    ],
    "sg:phone":"+1 513 523 9225",
    "sg:postcode":"45056",
    "sg:province":"IN",
    "sg:tags":[
        "miscellaneous",
        "store"
    ],
    "wof:name":"Sunrise Essentials",
    "wof:placetype":"venue"
},
  "geometry": {"coordinates":[-84.750811,39.478153],"type":"Point"}
}