{
  "type": "Feature",
  "properties": {
    "addr:full": "512 Linden Ave Franklin OH 45005",
    "addr:housenumber": "512",
    "addr:postcode": "45005",
    "addr:street": "Linden Ave",
    "iso:country": "US",
    "sg:address": "512 Linden Ave",
    "sg:city": "Franklin",
    "sg:classifiers": [
      {
        "category": "Manufacturing",
        "subcategory": "Tools \u0026 Machinery",
        "type": "Manufacturing \u0026 Wholesale Goods"
      }
    ],
    "sg:phone": "+1 937 704 9650",
    "sg:postcode": "45005",
    "sg:province": "OH",
    "sg:tags": [
      "machine",
      "shop"
    ],
    "wof:name": "3 D Industries",
    "wof:placetype": "venue"
  },
  "geometry": {"coordinates":[-84.320048,39.580901],"type":"Point"}
}
