{
  "type": "Feature",
  "properties": {
    "addr:full": "4741 Ceramic Rd Crooksville OH 43731",
    "addr:postcode": "4741;43731",
    "addr:street": "Ceramic Rd",
    "iso:country": "US",
    "sg:address": "4741 Ceramic Rd",
    "sg:city": "Crooksville",
    "sg:classifiers": [
      {
        "category": "Shopping",
        "subcategory": "Bicycles \u0026 Sporting Goods",
        "type": "Retail Goods"
      }
    ],
    "sg:phone": "+1 740 982 0526",
    "sg:postcode": "43731",
    "sg:province": "OH",
    "wof:name": "Totally Conscientious Golf",
    "wof:placetype": "venue"
  },
  "geometry": {"coordinates":[-82.087705,39.753533],"type":"Point"}
}
