{
  "type": "Feature",
  "properties": {
    "addr:full": "1368 Research Park Dr Dayton OH 45432",
    "addr:housenumber": "1368",
    "addr:postcode": "45432",
    "addr:street": "Research Park Dr",
    "iso:country": "US",
    "sg:address": "1368 Research Park Dr",
    "sg:city": "Dayton",
    "sg:classifiers": [
      {
        "category": "Government",
        "subcategory": "Office",
        "type": "Public Place"
      }
    ],
    "sg:phone": "+1 937 427 5510",
    "sg:postcode": "45432",
    "sg:province": "OH",
    "sg:tags": [
      "city"
    ],
    "wof:name": "Beavercreek City Manager",
    "wof:placetype": "venue"
  },
  "geometry": {"coordinates":[-84.067789,39.73145],"type":"Point"}
}
