{
  "type": "Feature",
  "properties": {
    "addr:full":"6040 Wooster Pike Medina OH 44256",
    "addr:housenumber":"6040",
    "addr:postcode":"44256",
    "addr:street":"Wooster Pike",
    "iso:country":"US",
    "sg:address":"6040 Wooster Pike",
    "sg:city":"Medina",
    "sg:classifiers":[
        {
            "category":"Farming",
            "subcategory":"Livestock Farm",
            "type":"Manufacturing & Wholesale Goods"
        }
    ],
    "sg:phone":"+1 330 722 2497",
    "sg:postcode":"44256",
    "sg:province":"OH",
    "sg:tags":[
        "horse",
        "other",
        "equine"
    ],
    "wof:name":"Lehr King Stables Inc",
    "wof:placetype":"venue"
},
  "geometry": {"coordinates":[-81.86419100000001,41.107602],"type":"Point"}
}