{
  "type": "Feature",
  "properties": {
    "addr:full": "10935 W 130th St North Royalton OH 44133",
    "addr:housenumber": "10935",
    "addr:postcode": "44133",
    "addr:street": "W 130Th St",
    "iso:country": "US",
    "sg:address": "10935 W 130th St",
    "sg:city": "North Royalton",
    "sg:classifiers": [
      {
        "category": "Manufacturing",
        "subcategory": "Tools \u0026 Machinery",
        "type": "Manufacturing \u0026 Wholesale Goods"
      }
    ],
    "sg:phone": "+1 440 230 5420",
    "sg:postcode": "44133",
    "sg:province": "OH",
    "sg:tags": [
      "measuring",
      "instrument",
      "electrical",
      "mfg"
    ],
    "wof:name": "Advalan LLC",
    "wof:placetype": "venue"
  },
  "geometry": {"coordinates":[-81.785205,41.33404],"type":"Point"}
}
