{
  "type": "Feature",
  "properties": {
    "iso:country":"US",
    "sg:address":"10935 W 130th St",
    "sg:city":"North Royalton",
    "sg:classifiers":[
        {
            "category":"Manufacturing",
            "subcategory":"Tools & Machinery",
            "type":"Manufacturing & Wholesale Goods"
        }
    ],
    "sg:phone":"+1 440 230 5420",
    "sg:postcode":"44133",
    "sg:province":"OH",
    "sg:tags":[
        "measuring",
        "instrument",
        "electrical",
        "mfg"
    ],
    "wof:name":"Advalan LLC",
    "wof:placetype":"venue"
},
  "geometry": {"coordinates":[-81.785205,41.33404],"type":"Point"}
}