{
  "type": "Feature",
  "properties": {
    "iso:country":"US",
    "sg:address":"144 Groves Ave",
    "sg:city":"Marietta",
    "sg:classifiers":[
        {
            "category":"Wholesale",
            "subcategory":"Meat",
            "type":"Manufacturing & Wholesale Goods"
        }
    ],
    "sg:phone":"+1 740 373 5699",
    "sg:postcode":"45750",
    "sg:province":"OH",
    "sg:tags":[
        "packer"
    ],
    "wof:name":"R & L Processing",
    "wof:placetype":"venue"
},
  "geometry": {"coordinates":[-81.479749,39.427353],"type":"Point"}
}