{
  "type": "Feature",
  "properties": {
    "addr:full": "144 Groves Ave Marietta OH 45750",
    "addr:housenumber": "144",
    "addr:postcode": "45750",
    "addr:street": "Groves Ave",
    "iso:country": "US",
    "sg:address": "144 Groves Ave",
    "sg:city": "Marietta",
    "sg:classifiers": [
      {
        "category": "Wholesale",
        "subcategory": "Meat",
        "type": "Manufacturing \u0026 Wholesale Goods"
      }
    ],
    "sg:phone": "+1 740 373 5699",
    "sg:postcode": "45750",
    "sg:province": "OH",
    "sg:tags": [
      "packer"
    ],
    "wof:name": "R \u0026 L Processing",
    "wof:placetype": "venue"
  },
  "geometry": {"coordinates":[-81.479749,39.427353],"type":"Point"}
}
