{
  "type": "Feature",
  "properties": {
    "addr:full":"828 Market St Zanesville OH 43701",
    "addr:housenumber":"828",
    "addr:postcode":"43701",
    "addr:street":"Market St",
    "iso:country":"US",
    "sg:address":"828 Market St",
    "sg:city":"Zanesville",
    "sg:classifiers":[
        {
            "category":"Shopping",
            "subcategory":"Musical Instruments",
            "type":"Retail Goods"
        }
    ],
    "sg:phone":"+1 740 454 2357",
    "sg:postcode":"43701",
    "sg:province":"OH",
    "wof:name":"C A House Music",
    "wof:placetype":"venue"
},
  "geometry": {"coordinates":[-82.002214,39.941532],"type":"Point"}
}