{
  "type": "Feature",
  "properties": {
    "iso:country":"US",
    "sg:address":"101 E Benson Ave",
    "sg:city":"Cincinnati",
    "sg:classifiers":[
        {
            "category":"Wholesale",
            "subcategory":"Machinery & Supplies",
            "type":"Manufacturing & Wholesale Goods"
        },
        {
            "category":"Building & Trades",
            "subcategory":"Construction",
            "type":"Services"
        }
    ],
    "sg:phone":"+1 513 761 6777",
    "sg:postcode":"45215",
    "sg:province":"OH",
    "sg:tags":[
        "woodworking",
        "woodworker"
    ],
    "sg:website":"www.mullerco.com",
    "wof:name":"Edward B Mueller Co Inc",
    "wof:placetype":"venue"
},
  "geometry": {"coordinates":[-84.439668,39.222048],"type":"Point"}
}