{
  "type": "Feature",
  "properties": {
    "addr:full": "101 E Benson Ave Cincinnati OH 45215",
    "addr:housenumber": "101",
    "addr:postcode": "45215",
    "addr:street": "E Benson Ave",
    "iso:country": "US",
    "sg:address": "101 E Benson Ave",
    "sg:city": "Cincinnati",
    "sg:classifiers": [
      {
        "category": "Wholesale",
        "subcategory": "Machinery \u0026 Supplies",
        "type": "Manufacturing \u0026 Wholesale Goods"
      },
      {
        "category": "Building \u0026 Trades",
        "subcategory": "Construction",
        "type": "Services"
      }
    ],
    "sg:phone": "+1 513 761 6777",
    "sg:postcode": "45215",
    "sg:province": "OH",
    "sg:tags": [
      "woodworking",
      "woodworker"
    ],
    "sg:website": "www.mullerco.com",
    "wof:name": "Edward B Mueller Co Inc",
    "wof:placetype": "venue"
  },
  "geometry": {"coordinates":[-84.439668,39.222048],"type":"Point"}
}
