{
  "type": "Feature",
  "properties": {
    "iso:country":"US",
    "sg:address":"2841 Riviera Dr",
    "sg:city":"Fairlawn",
    "sg:classifiers":[
        {
            "category":"Building & Trades",
            "subcategory":"Construction",
            "type":"Services"
        }
    ],
    "sg:phone":"+1 330 867 4505",
    "sg:postcode":"44333",
    "sg:province":"OH",
    "sg:tags":[
        "steel"
    ],
    "wof:name":"RMM Global",
    "wof:placetype":"venue"
},
  "geometry": {"coordinates":[-81.611751,41.127364],"type":"Point"}
}