{
  "type": "Feature",
  "properties": {
    "addr:full": "959 Bellefontaine Ave Lima OH 45804",
    "addr:housenumber": "959",
    "addr:postcode": "45804",
    "addr:street": "Bellefontaine Ave",
    "iso:country": "US",
    "sg:address": "959 Bellefontaine Ave",
    "sg:city": "Lima",
    "sg:classifiers": [
      {
        "category": "Restaurant",
        "type": "Food \u0026 Drink"
      }
    ],
    "sg:menulink": "http://www.allmenus.com/oh/lima/233027-lees-famous-recipe-chicken/menu/",
    "sg:phone": "+1 419 228 9562",
    "sg:postcode": "45804",
    "sg:province": "OH",
    "sg:tags": [
      "american"
    ],
    "wof:name": "Lee's Famous Recipe Chicken",
    "wof:placetype": "venue"
  },
  "geometry": {"coordinates":[-84.089195,40.736568],"type":"Point"}
}
