{
  "type": "Feature",
  "properties": {
    "addr:full": "3380 W State Rte 73 Wilmington OH 45177",
    "addr:housenumber": "3380",
    "addr:postcode": "45177",
    "addr:street": "W State Rte 73",
    "iso:country": "US",
    "sg:address": "3380 W State Rte 73",
    "sg:city": "Wilmington",
    "sg:classifiers": [
      {
        "category": "Manufacturing",
        "subcategory": "Metals",
        "type": "Manufacturing \u0026 Wholesale Goods"
      }
    ],
    "sg:phone": "+1 937 382 7388",
    "sg:postcode": "45177",
    "sg:province": "OH",
    "sg:tags": [
      "center"
    ],
    "wof:name": "Vincent Metal Goods",
    "wof:placetype": "venue"
  },
  "geometry": {"coordinates":[-83.878822,39.466215],"type":"Point"}
}
