{
  "type": "Feature",
  "properties": {
    "iso:country":"US",
    "sg:address":"276 W Beal Ave",
    "sg:city":"Bucyrus",
    "sg:classifiers":[
        {
            "category":"Professional",
            "subcategory":"Computer Services",
            "type":"Services"
        }
    ],
    "sg:phone":"+1 419 562 2271",
    "sg:postcode":"44820",
    "sg:province":"OH",
    "sg:tags":[
        "repair"
    ],
    "wof:name":"Atwood Computer Svc",
    "wof:placetype":"venue"
},
  "geometry": {"coordinates":[-82.98033100000001,40.790196],"type":"Point"}
}