{
  "type": "Feature",
  "properties": {
    "addr:full": "276 W Beal Ave Bucyrus OH 44820",
    "addr:housenumber": "276",
    "addr:postcode": "44820",
    "addr:street": "W Beal Ave",
    "iso:country": "US",
    "sg:address": "276 W Beal Ave",
    "sg:city": "Bucyrus",
    "sg:classifiers": [
      {
        "category": "Professional",
        "subcategory": "Computer Services",
        "type": "Services"
      }
    ],
    "sg:phone": "+1 419 562 2271",
    "sg:postcode": "44820",
    "sg:province": "OH",
    "sg:tags": [
      "repair"
    ],
    "wof:name": "Atwood Computer Svc",
    "wof:placetype": "venue"
  },
  "geometry": {"coordinates":[-82.980331,40.790196],"type":"Point"}
}
