{
  "type": "Feature",
  "properties": {
    "addr:full": "4016 Woodbine Ave Cleveland OH 44113",
    "addr:housenumber": "4016",
    "addr:postcode": "44113",
    "addr:street": "Woodbine Ave",
    "iso:country": "US",
    "sg:address": "4016 Woodbine Ave",
    "sg:city": "Cleveland",
    "sg:classifiers": [
      {
        "category": "Education",
        "subcategory": "School",
        "type": "Public Place"
      }
    ],
    "sg:phone": "+1 216 281 6188",
    "sg:postcode": "44113",
    "sg:province": "OH",
    "sg:tags": [
      "middle"
    ],
    "sg:website": "http://www.cmsdnet.net",
    "wof:name": "Garrett Morgan Schl Of Science Middle School",
    "wof:placetype": "venue"
  },
  "geometry": {"coordinates":[-81.714464,41.484207],"type":"Point"}
}
