{
  "type": "Feature",
  "properties": {
    "addr:full": "5396 Co Hwy 47 Upper Sandusky OH 43351",
    "addr:housenumber": "5396",
    "addr:postcode": "43351",
    "addr:street": "Co Hwy 47",
    "iso:country": "US",
    "sg:address": "5396 Co Hwy 47",
    "sg:city": "Upper Sandusky",
    "sg:classifiers": [
      {
        "category": "Real Estate",
        "subcategory": "Real Estate Operator",
        "type": "Services"
      }
    ],
    "sg:phone": "+1 419 294 1789",
    "sg:postcode": "43351",
    "sg:province": "OH",
    "sg:tags": [
      "property",
      "lessor"
    ],
    "wof:name": "Helen Pool",
    "wof:placetype": "venue"
  },
  "geometry": {"coordinates":[-83.217573,40.862139],"type":"Point"}
}
