{
  "type": "Feature",
  "properties": {
    "addr:full": "26477 Southpoint Rd Perrysburg OH 43551",
    "addr:housenumber": "26477",
    "addr:postcode": "43551",
    "addr:street": "Southpoint Rd",
    "iso:country": "US",
    "sg:address": "26477 Southpoint Rd",
    "sg:city": "Perrysburg",
    "sg:classifiers": [
      {
        "category": "Manufacturing",
        "subcategory": "Printing",
        "type": "Manufacturing \u0026 Wholesale Goods"
      }
    ],
    "sg:phone": "+1 419 385 3375",
    "sg:postcode": "43551",
    "sg:province": "OH",
    "sg:tags": [
      "offset"
    ],
    "wof:name": "Northwest Print Inc",
    "wof:placetype": "venue"
  },
  "geometry": {"coordinates":[-83.641614,41.536114],"type":"Point"}
}
