{
  "type": "Feature",
  "properties": {
    "iso:country":"US",
    "sg:address":"49866 S Park Cir",
    "sg:city":"East Liverpool",
    "sg:classifiers":[
        {
            "category":"Professional",
            "subcategory":"Engineering",
            "type":"Services"
        }
    ],
    "sg:phone":"+1 330 386 9281",
    "sg:postcode":"43920",
    "sg:province":"OH",
    "sg:tags":[
        "engineer"
    ],
    "wof:name":"B3S Inc",
    "wof:placetype":"venue"
},
  "geometry": {"coordinates":[-80.560261,40.703881],"type":"Point"}
}