{
  "type": "Feature",
  "properties": {
    "iso:country":"US",
    "sg:address":"37903 Euclid Ave",
    "sg:city":"Willoughby",
    "sg:classifiers":[
        {
            "category":"Banks & Credit Unions",
            "subcategory":"Investment Brokerage",
            "type":"Services"
        }
    ],
    "sg:phone":"+1 440 942 8877",
    "sg:postcode":"44094",
    "sg:province":"OH",
    "sg:tags":[
        "advisory",
        "financial"
    ],
    "wof:name":"Citadel Investment Advisory",
    "wof:placetype":"venue"
},
  "geometry": {"coordinates":[-81.410337,41.634718],"type":"Point"}
}