{
  "type": "Feature",
  "properties": {
    "addr:full":"7378 Twp Rd 93 Carey OH 43316",
    "addr:housenumber":"7378;93",
    "addr:postcode":"43316",
    "addr:street":"Twp Rd",
    "iso:country":"US",
    "sg:address":"7378 Twp Rd 93",
    "sg:city":"Carey",
    "sg:classifiers":[
        {
            "category":"Farming",
            "subcategory":"Farm",
            "type":"Manufacturing & Wholesale Goods"
        }
    ],
    "sg:phone":"+1 419 595 2427",
    "sg:postcode":"43316",
    "sg:province":"OH",
    "sg:tags":[
        "corn",
        "wheat",
        "soybean",
        "crop",
        "general"
    ],
    "wof:name":"Donald Kuhlman",
    "wof:placetype":"venue"
},
  "geometry": {"coordinates":[-83.32444,41.014692],"type":"Point"}
}