{
  "type": "Feature",
  "properties": {
    "iso:country":"US",
    "sg:address":"7845 Greenland Pl",
    "sg:city":"Cincinnati",
    "sg:classifiers":[
        {
            "category":"Shopping",
            "subcategory":"Gifts & Souvenirs",
            "type":"Retail Goods"
        }
    ],
    "sg:phone":"+1 513 948 0699",
    "sg:postcode":"45237",
    "sg:province":"OH",
    "wof:name":"Rm Productions",
    "wof:placetype":"venue"
},
  "geometry": {"coordinates":[-84.45992099999999,39.20673],"type":"Point"}
}