{
  "type": "Feature",
  "properties": {
    "addr:full": "7845 Greenland Pl Cincinnati OH 45237",
    "addr:housenumber": "7845",
    "addr:postcode": "45237",
    "addr:street": "Greenland Pl",
    "iso:country": "US",
    "sg:address": "7845 Greenland Pl",
    "sg:city": "Cincinnati",
    "sg:classifiers": [
      {
        "category": "Shopping",
        "subcategory": "Gifts \u0026 Souvenirs",
        "type": "Retail Goods"
      }
    ],
    "sg:phone": "+1 513 948 0699",
    "sg:postcode": "45237",
    "sg:province": "OH",
    "wof:name": "Rm Productions",
    "wof:placetype": "venue"
  },
  "geometry": {"coordinates":[-84.459921,39.20673],"type":"Point"}
}
