{
  "type": "Feature",
  "properties": {
    "addr:full": "1286 Koebel Rd Columbus OH 43207",
    "addr:housenumber": "1286",
    "addr:postcode": "43207",
    "addr:street": "Koebel Rd",
    "iso:country": "US",
    "sg:address": "1286 Koebel Rd",
    "sg:city": "Columbus",
    "sg:classifiers": [
      {
        "category": "Banks \u0026 Credit Unions",
        "subcategory": "Investment Brokerage",
        "type": "Services"
      }
    ],
    "sg:phone": "+1 614 497 8009",
    "sg:postcode": "43207",
    "sg:province": "OH",
    "sg:tags": [
      "advisory"
    ],
    "wof:name": "Hill Investments",
    "wof:placetype": "venue"
  },
  "geometry": {"coordinates":[-82.961314,39.912504],"type":"Point"}
}
