{
  "type": "Feature",
  "properties": {
    "addr:full": "2509 Professor Ave Cleveland OH 44113",
    "addr:housenumber": "2509",
    "addr:postcode": "44113",
    "addr:street": "Professor Ave",
    "iso:country": "US",
    "sg:address": "2509 Professor Ave",
    "sg:city": "Cleveland",
    "sg:classifiers": [
      {
        "category": "Building \u0026 Trades",
        "subcategory": "Construction",
        "type": "Services"
      }
    ],
    "sg:phone": "+1 216 621 7899",
    "sg:postcode": "44113",
    "sg:province": "OH",
    "sg:tags": [
      "contractor"
    ],
    "wof:name": "Sutton Builders",
    "wof:placetype": "venue"
  },
  "geometry": {"coordinates":[-81.683173,41.478474],"type":"Point"}
}
