{
  "type": "Feature",
  "properties": {
    "addr:full": "9405 Sutton Pl Hamilton OH 45011",
    "addr:housenumber": "9405",
    "addr:postcode": "45011",
    "addr:street": "Sutton Pl",
    "iso:country": "US",
    "sg:address": "9405 Sutton Pl",
    "sg:city": "Hamilton",
    "sg:classifiers": [
      {
        "category": "Wholesale",
        "subcategory": "Metals \u0026 Minerals",
        "type": "Manufacturing \u0026 Wholesale Goods"
      }
    ],
    "sg:phone": "+1 513 860 5900",
    "sg:postcode": "45011",
    "sg:province": "OH",
    "sg:tags": [
      "pipe"
    ],
    "wof:name": "Pipe Products Inc",
    "wof:placetype": "venue"
  },
  "geometry": {"coordinates":[-84.469997,39.324195],"type":"Point"}
}
