{
  "type": "Feature",
  "properties": {
    "iso:country":"US",
    "sg:address":"9405 Sutton Pl",
    "sg:city":"Hamilton",
    "sg:classifiers":[
        {
            "category":"Wholesale",
            "subcategory":"Metals & Minerals",
            "type":"Manufacturing & Wholesale Goods"
        }
    ],
    "sg:phone":"+1 513 860 5900",
    "sg:postcode":"45011",
    "sg:province":"OH",
    "sg:tags":[
        "pipe"
    ],
    "wof:name":"Pipe Products Inc",
    "wof:placetype":"venue"
},
  "geometry": {"coordinates":[-84.469997,39.324195],"type":"Point"}
}