{
  "type": "Feature",
  "properties": {
    "addr:full":"1525 Marion-Waldo Rd Marion OH 43302",
    "addr:housenumber":"1525",
    "addr:postcode":"43302",
    "addr:street":"Marion-Waldo Rd",
    "iso:country":"US",
    "sg:address":"1525 Marion-Waldo Rd",
    "sg:city":"Marion",
    "sg:classifiers":[
        {
            "category":"Shopping",
            "subcategory":"Department Store",
            "type":"Retail Goods"
        }
    ],
    "sg:phone":"+1 740 389 5441",
    "sg:postcode":"43302",
    "sg:province":"OH",
    "wof:name":"JC Penney",
    "wof:placetype":"venue"
},
  "geometry": {"coordinates":[-83.119119,40.561417],"type":"Point"}
}