{
  "type": "Feature",
  "properties": {
    "addr:full": "7345 Jeffers Rd Whitehouse OH 43571",
    "addr:housenumber": "7345",
    "addr:postcode": "43571",
    "addr:street": "Jeffers Rd",
    "iso:country": "US",
    "sg:address": "7345 Jeffers Rd",
    "sg:city": "Whitehouse",
    "sg:classifiers": [
      {
        "category": "Building \u0026 Trades",
        "subcategory": "Electrical",
        "type": "Services"
      }
    ],
    "sg:phone": "+1 419 875 5157",
    "sg:postcode": "43571",
    "sg:province": "OH",
    "sg:tags": [
      "electrical",
      "contractor"
    ],
    "wof:name": "Dynamic Currents Corp",
    "wof:placetype": "venue"
  },
  "geometry": {"coordinates":[-83.85572,41.50574],"type":"Point"}
}
