{
  "type": "Feature",
  "properties": {
    "iso:country":"US",
    "sg:address":"7345 Jeffers Rd",
    "sg:city":"Whitehouse",
    "sg:classifiers":[
        {
            "category":"Building & Trades",
            "subcategory":"Electrical",
            "type":"Services"
        }
    ],
    "sg:phone":"+1 419 875 5157",
    "sg:postcode":"43571",
    "sg:province":"OH",
    "sg:tags":[
        "electrical",
        "contractor"
    ],
    "wof:name":"Dynamic Currents Corp",
    "wof:placetype":"venue"
},
  "geometry": {"coordinates":[-83.85572000000001,41.50574],"type":"Point"}
}