{
  "type": "Feature",
  "properties": {
    "addr:full":"36 S Franklin St Chagrin Falls OH 44022",
    "addr:housenumber":"36",
    "addr:postcode":"44022",
    "addr:street":"S Franklin St",
    "iso:country":"US",
    "sg:address":"36 S Franklin St",
    "sg:city":"Chagrin Falls",
    "sg:classifiers":[
        {
            "category":"Professional",
            "type":"Services"
        }
    ],
    "sg:phone":"+1 440 247 3391",
    "sg:postcode":"44022",
    "sg:province":"OH",
    "sg:tags":[
        "establishment"
    ],
    "wof:name":"Justin S Rerkot & Assoc",
    "wof:placetype":"venue"
},
  "geometry": {"coordinates":[-81.390717,41.424187],"type":"Point"}
}