{
  "type": "Feature",
  "properties": {
    "addr:full":"516 Washington St Chagrin Falls OH 44022",
    "addr:housenumber":"516",
    "addr:postcode":"44022",
    "addr:street":"Washington St",
    "iso:country":"US",
    "sg:address":"516 Washington St",
    "sg:city":"Chagrin Falls",
    "sg:classifiers":[
        {
            "category":"Professional",
            "type":"Services"
        }
    ],
    "sg:phone":"+1 440 893 0900",
    "sg:postcode":"44022",
    "sg:province":"OH",
    "sg:website":"www.digitaldesignvideo.com",
    "wof:name":"Digital Design Video Inc",
    "wof:placetype":"venue"
},
  "geometry": {"coordinates":[-81.373324,41.426497],"type":"Point"}
}