{
  "type": "Feature",
  "properties": {
    "addr:full":"1107 Bechtle Ave Springfield OH 45504",
    "addr:housenumber":"1107",
    "addr:postcode":"45504",
    "addr:street":"Bechtle Ave",
    "iso:country":"US",
    "sg:address":"1107 Bechtle Ave",
    "sg:city":"Springfield",
    "sg:classifiers":[
        {
            "category":"Insurance",
            "subcategory":"Insurance Agent",
            "type":"Services"
        }
    ],
    "sg:phone":"+1 937 323 7997",
    "sg:postcode":"45504",
    "sg:province":"OH",
    "wof:name":"Acceptance Insurance Agency",
    "wof:placetype":"venue"
},
  "geometry": {"coordinates":[-83.835762,39.939569],"type":"Point"}
}