{
  "type": "Feature",
  "properties": {
    "iso:country":"US",
    "sg:address":"66440 Belmont Morristown Rd",
    "sg:city":"Belmont",
    "sg:classifiers":[
        {
            "category":"Food & Beverages",
            "subcategory":"Groceries & Convenience Stores",
            "type":"Retail Goods"
        },
        {
            "category":"Autos & Motor Vehicles",
            "subcategory":"Fuel & Gas Station",
            "type":"Retail Goods"
        }
    ],
    "sg:phone":"+1 740 782 1239",
    "sg:postcode":"43718",
    "sg:province":"OH",
    "sg:tags":[
        "station",
        "gasoline"
    ],
    "wof:name":"Bel-Morr Shur Fast",
    "wof:placetype":"venue"
},
  "geometry": {"coordinates":[-81.053168,40.060612],"type":"Point"}
}