{
  "type": "Feature",
  "properties": {
    "addr:full": "66440 Belmont Morristown Rd Belmont OH 43718",
    "addr:housenumber": "66440",
    "addr:postcode": "43718",
    "addr:street": "Belmont Morristown Rd",
    "iso:country": "US",
    "sg:address": "66440 Belmont Morristown Rd",
    "sg:city": "Belmont",
    "sg:classifiers": [
      {
        "category": "Food \u0026 Beverages",
        "subcategory": "Groceries \u0026 Convenience Stores",
        "type": "Retail Goods"
      },
      {
        "category": "Autos \u0026 Motor Vehicles",
        "subcategory": "Fuel \u0026 Gas Station",
        "type": "Retail Goods"
      }
    ],
    "sg:phone": "+1 740 782 1239",
    "sg:postcode": "43718",
    "sg:province": "OH",
    "sg:tags": [
      "station",
      "gasoline"
    ],
    "wof:name": "Bel-Morr Shur Fast",
    "wof:placetype": "venue"
  },
  "geometry": {"coordinates":[-81.053168,40.060612],"type":"Point"}
}
