{
  "type": "Feature",
  "properties": {
    "addr:full": "2246 4th St Cuyahoga Falls OH 44221",
    "addr:housenumber": "2246",
    "addr:postcode": "44221",
    "addr:street": "4Th St",
    "iso:country": "US",
    "sg:address": "2246 4th St",
    "sg:city": "Cuyahoga Falls",
    "sg:classifiers": [
      {
        "category": "Retail",
        "subcategory": "Repair Shop",
        "type": "Services"
      }
    ],
    "sg:phone": "+1 330 923 9874",
    "sg:postcode": "44221",
    "sg:province": "OH",
    "sg:tags": [
      "upholsterer"
    ],
    "wof:name": "KUTA Upholstery",
    "wof:placetype": "venue"
  },
  "geometry": {"coordinates":[-81.487104,41.136958],"type":"Point"}
}
