{
  "type": "Feature",
  "properties": {
    "iso:country":"US",
    "sg:address":"1585 Georgesville Sq",
    "sg:city":"Columbus",
    "sg:classifiers":[
        {
            "category":"Utilities",
            "subcategory":"Mobile Phone",
            "type":"Services"
        }
    ],
    "sg:phone":"+1 614 878 6106",
    "sg:postcode":"43228",
    "sg:province":"OH",
    "sg:tags":[
        "telephone",
        "cellular"
    ],
    "wof:name":"T Mobile",
    "wof:placetype":"venue"
},
  "geometry": {"coordinates":[-83.12047200000001,39.921256],"type":"Point"}
}