{
  "type": "Feature",
  "properties": {
    "addr:full": "1585 Georgesville Sq Columbus OH 43228",
    "addr:housenumber": "1585",
    "addr:postcode": "43228",
    "addr:street": "Georgesville Sq",
    "iso:country": "US",
    "sg:address": "1585 Georgesville Sq",
    "sg:city": "Columbus",
    "sg:classifiers": [
      {
        "category": "Utilities",
        "subcategory": "Mobile Phone",
        "type": "Services"
      }
    ],
    "sg:phone": "+1 614 878 6106",
    "sg:postcode": "43228",
    "sg:province": "OH",
    "sg:tags": [
      "telephone",
      "cellular"
    ],
    "wof:name": "T Mobile",
    "wof:placetype": "venue"
  },
  "geometry": {"coordinates":[-83.120472,39.921256],"type":"Point"}
}
