{
  "type": "Feature",
  "properties": {
    "iso:country":"US",
    "sg:address":"1612 Leonard St",
    "sg:city":"Cleveland",
    "sg:classifiers":[
        {
            "category":"Retail",
            "subcategory":"Funeral Services",
            "type":"Services"
        }
    ],
    "sg:phone":"+1 216 861 2334",
    "sg:postcode":"44113",
    "sg:province":"OH",
    "sg:tags":[
        "passenger",
        "crematory",
        "local"
    ],
    "wof:name":"Cremation Service Inc",
    "wof:placetype":"venue"
},
  "geometry": {"coordinates":[-81.700419,41.491823],"type":"Point"}
}