{
  "type": "Feature",
  "properties": {
    "iso:country":"US",
    "sg:address":"5640 W 224th St",
    "sg:city":"Cleveland",
    "sg:classifiers":[
        {
            "category":"Building & Trades",
            "subcategory":"Landscaping Services",
            "type":"Services"
        }
    ],
    "sg:phone":"+1 440 777 2619",
    "sg:postcode":"44126",
    "sg:province":"OH",
    "sg:tags":[
        "landscape"
    ],
    "wof:name":"Petes Landscaping",
    "wof:placetype":"venue"
},
  "geometry": {"coordinates":[-81.868493,41.425782],"type":"Point"}
}