{
  "type": "Feature",
  "properties": {
    "addr:full":"8447 Tod Ave SW Warren OH 44481",
    "addr:housenumber":"8447",
    "addr:postcode":"44481",
    "addr:street":"Tod Ave Sw",
    "iso:country":"US",
    "sg:address":"8447 Tod Ave SW",
    "sg:city":"Warren",
    "sg:classifiers":[
        {
            "category":"Autos & Motor Vehicles",
            "subcategory":"Recreational Vehicle Sales",
            "type":"Retail Goods"
        }
    ],
    "sg:phone":"+1 330 824 3304",
    "sg:postcode":"44481",
    "sg:province":"OH",
    "sg:tags":[
        "canopy",
        "shell",
        "truck",
        "cap"
    ],
    "wof:name":"Glass Masters Truck Access",
    "wof:placetype":"venue"
},
  "geometry": {"coordinates":[-80.857051,41.140492],"type":"Point"}
}