{
  "type": "Feature",
  "properties": {
    "addr:full":"550 Forest Fair Dr Cincinnati OH 45240",
    "addr:housenumber":"550",
    "addr:postcode":"45240",
    "addr:street":"Forest Fair Dr",
    "iso:country":"US",
    "sg:address":"550 Forest Fair Dr",
    "sg:city":"Cincinnati",
    "sg:classifiers":[
        {
            "category":"Restaurant",
            "type":"Food & Drink"
        }
    ],
    "sg:phone":"+1 513 671 4300",
    "sg:postcode":"45240",
    "sg:province":"OH",
    "sg:tags":[
        "eating"
    ],
    "wof:name":"Coffee Basket",
    "wof:placetype":"venue"
},
  "geometry": {"coordinates":[-84.519856,39.301039],"type":"Point"}
}