{
  "type": "Feature",
  "properties": {
    "addr:full": "7844 Navarre Rd SW Massillon OH 44646",
    "addr:housenumber": "7844",
    "addr:postcode": "44646",
    "addr:street": "Navarre Rd Sw",
    "iso:country": "US",
    "sg:address": "7844 Navarre Rd SW",
    "sg:city": "Massillon",
    "sg:classifiers": [
      {
        "category": "Professional",
        "type": "Services"
      }
    ],
    "sg:phone": "+1 330 832 5288",
    "sg:postcode": "44646",
    "sg:province": "OH",
    "sg:tags": [
      "establishment"
    ],
    "wof:name": "Flex-Team",
    "wof:placetype": "venue"
  },
  "geometry": {"coordinates":[-81.503091,40.746744],"type":"Point"}
}
