{
  "type": "Feature",
  "properties": {
    "addr:full":"124 S Main St Clyde OH 43410",
    "addr:housenumber":"124",
    "addr:postcode":"43410",
    "addr:street":"S Main St",
    "iso:country":"US",
    "sg:address":"124 S Main St",
    "sg:city":"Clyde",
    "sg:classifiers":[
        {
            "category":"Health Services",
            "subcategory":"Chiropractor",
            "type":"Services"
        }
    ],
    "sg:phone":"+1 419 547 3404",
    "sg:postcode":"43410",
    "sg:province":"OH",
    "wof:name":"Reed Chiropractic",
    "wof:placetype":"venue"
},
  "geometry": {"coordinates":[-82.974785,41.304618],"type":"Point"}
}