{
  "type": "Feature",
  "properties": {
    "addr:full": "1201 N Main St Orrville OH 44667",
    "addr:housenumber": "1201",
    "addr:postcode": "44667",
    "addr:street": "N Main St",
    "iso:country": "US",
    "sg:address": "1201 N Main St",
    "sg:city": "Orrville",
    "sg:classifiers": [
      {
        "category": "Professional",
        "type": "Services"
      }
    ],
    "sg:phone": "+1 330 682 9010",
    "sg:postcode": "44667",
    "sg:province": "OH",
    "sg:tags": [
      "establishment"
    ],
    "wof:name": "Magnepak Ultrasonics",
    "wof:placetype": "venue"
  },
  "geometry": {"coordinates":[-81.763843,40.852702],"type":"Point"}
}
