{
  "type": "Feature",
  "properties": {
    "addr:full": "8239 S Bedford Rd Macedonia OH 44056",
    "addr:housenumber": "8239",
    "addr:postcode": "44056",
    "addr:street": "S Bedford Rd",
    "iso:country": "US",
    "sg:address": "8239 S Bedford Rd",
    "sg:city": "Macedonia",
    "sg:classifiers": [
      {
        "category": "Restaurant",
        "type": "Food \u0026 Drink"
      }
    ],
    "sg:phone": "+1 330 467 4969",
    "sg:postcode": "44056",
    "sg:province": "OH",
    "sg:tags": [
      "eating"
    ],
    "wof:name": "Sereni Tea Garden",
    "wof:placetype": "venue"
  },
  "geometry": {"coordinates":[-81.50897,41.311155],"type":"Point"}
}
