{
  "type": "Feature",
  "properties": {
    "addr:full": "425 Herrick St Uhrichsville OH 44683",
    "addr:housenumber": "425",
    "addr:postcode": "44683",
    "addr:street": "Herrick St",
    "iso:country": "US",
    "sg:address": "425 Herrick St",
    "sg:city": "Uhrichsville",
    "sg:phone": "+1 740 922 9730",
    "sg:postcode": "44683",
    "sg:province": "OH",
    "sg:tags": [
      "material",
      "fixture",
      "display"
    ],
    "wof:name": "Platinum Visual Systems",
    "wof:placetype": "venue"
  },
  "geometry": {"coordinates":[-81.353269,40.38731],"type":"Point"}
}
