{
  "type": "Feature",
  "properties": {
    "addr:full": "263 Marker Rd Versailles OH 45380",
    "addr:housenumber": "263",
    "addr:postcode": "45380",
    "addr:street": "Marker Rd",
    "iso:country": "US",
    "sg:address": "263 Marker Rd",
    "sg:city": "Versailles",
    "sg:classifiers": [
      {
        "category": "Restaurant",
        "type": "Food \u0026 Drink"
      }
    ],
    "sg:phone": "+1 937 526 4848",
    "sg:postcode": "45380",
    "sg:province": "OH",
    "wof:name": "Tiger's Den",
    "wof:placetype": "venue"
  },
  "geometry": {"coordinates":[-84.487411,40.216609],"type":"Point"}
}
