{
  "type": "Feature",
  "properties": {
    "addr:full": "1266 State Rte 303 Streetsboro OH 44241",
    "addr:housenumber": "1266",
    "addr:postcode": "44241",
    "addr:street": "State Rte 303",
    "iso:country": "US",
    "sg:address": "1266 State Rte 303",
    "sg:city": "Streetsboro",
    "sg:classifiers": [
      {
        "category": "Retail",
        "subcategory": "Laundry \u0026 Dry Cleaning",
        "type": "Services"
      }
    ],
    "sg:phone": "+1 330 626 4015",
    "sg:postcode": "44241",
    "sg:province": "OH",
    "sg:tags": [
      "drycleaning",
      "plant"
    ],
    "wof:name": "Dryclean USA",
    "wof:placetype": "venue"
  },
  "geometry": {"coordinates":[-81.349865,41.239371],"type":"Point"}
}
