{
  "type": "Feature",
  "properties": {
    "iso:country":"US",
    "sg:address":"1266 State Rte 303",
    "sg:city":"Streetsboro",
    "sg:classifiers":[
        {
            "category":"Retail",
            "subcategory":"Laundry & Dry Cleaning",
            "type":"Services"
        }
    ],
    "sg:phone":"+1 330 626 4015",
    "sg:postcode":"44241",
    "sg:province":"OH",
    "sg:tags":[
        "drycleaning",
        "plant"
    ],
    "wof:name":"Dryclean USA",
    "wof:placetype":"venue"
},
  "geometry": {"coordinates":[-81.349865,41.239371],"type":"Point"}
}