{
  "type": "Feature",
  "properties": {
    "addr:full": "2246 Wadsworth Rd Norton OH 44203",
    "addr:housenumber": "2246",
    "addr:postcode": "44203",
    "addr:street": "Wadsworth Rd",
    "iso:country": "US",
    "sg:address": "2246 Wadsworth Rd",
    "sg:city": "Norton",
    "sg:classifiers": [
      {
        "category": "Autos \u0026 Motor Vehicles",
        "subcategory": "Automobile Sales",
        "type": "Retail Goods"
      }
    ],
    "sg:phone": "+1 330 848 1960",
    "sg:postcode": "44203",
    "sg:province": "OH",
    "sg:tags": [
      "car",
      "dealer"
    ],
    "wof:name": "RPM Auto Group",
    "wof:placetype": "venue"
  },
  "geometry": {"coordinates":[-81.611016,41.054549],"type":"Point"}
}
