{
  "type": "Feature",
  "properties": {
    "iso:country":"US",
    "sg:address":"331 E 13th St",
    "sg:city":"Cincinnati",
    "sg:classifiers":[
        {
            "category":"Retail",
            "subcategory":"Repair Shop",
            "type":"Services"
        }
    ],
    "sg:phone":"+1 513 381 5557",
    "sg:postcode":"45202",
    "sg:province":"OH",
    "sg:tags":[
        "related"
    ],
    "wof:name":"Keystone National Repair Svc",
    "wof:placetype":"venue"
},
  "geometry": {"coordinates":[-84.508948,39.110174],"type":"Point"}
}