{
  "type": "Feature",
  "properties": {
    "addr:full": "2860 Sullivant Ave Columbus OH 43204",
    "addr:postcode": "2860;43204",
    "addr:street": "Sullivant Ave",
    "iso:country": "US",
    "sg:address": "2860 Sullivant Ave",
    "sg:city": "Columbus",
    "sg:classifiers": [
      {
        "category": "Food \u0026 Beverages",
        "subcategory": "Dairy",
        "type": "Retail Goods"
      }
    ],
    "sg:phone": "+1 614 279 8466",
    "sg:postcode": "43204",
    "sg:province": "OH",
    "sg:tags": [
      "product"
    ],
    "wof:name": "Hilltop Dairy Twist",
    "wof:placetype": "venue"
  },
  "geometry": {"coordinates":[-83.075464,39.943668],"type":"Point"}
}
