{
  "type": "Feature",
  "properties": {
    "iso:country":"US",
    "sg:address":"2860 Sullivant Ave",
    "sg:city":"Columbus",
    "sg:classifiers":[
        {
            "category":"Food & Beverages",
            "subcategory":"Dairy",
            "type":"Retail Goods"
        }
    ],
    "sg:phone":"+1 614 279 8466",
    "sg:postcode":"43204",
    "sg:province":"OH",
    "sg:tags":[
        "product"
    ],
    "wof:name":"Hilltop Dairy Twist",
    "wof:placetype":"venue"
},
  "geometry": {"coordinates":[-83.075464,39.943668],"type":"Point"}
}