{
  "type": "Feature",
  "properties": {
    "addr:full": "499 E Aurora Rd Macedonia OH 44056",
    "addr:housenumber": "499",
    "addr:postcode": "44056",
    "addr:street": "E Aurora Rd",
    "iso:country": "US",
    "sg:address": "499 E Aurora Rd",
    "sg:city": "Macedonia",
    "sg:classifiers": [
      {
        "category": "Personal",
        "subcategory": "Beauty Salon",
        "type": "Services"
      }
    ],
    "sg:phone": "+1 330 468 3444",
    "sg:postcode": "44056",
    "sg:province": "OH",
    "wof:name": "Best Cuts",
    "wof:placetype": "venue"
  },
  "geometry": {"coordinates":[-81.519966,41.314032],"type":"Point"}
}
