{
  "type": "Feature",
  "properties": {
    "iso:country":"US",
    "sg:address":"340 E Waterloo Rd",
    "sg:city":"Akron",
    "sg:classifiers":[
        {
            "category":"Restaurant",
            "type":"Food & Drink"
        }
    ],
    "sg:menulink":"http://www.allmenus.com/oh/akron/83212-papa-johns-pizza/menu/",
    "sg:phone":"+1 330 724 7272",
    "sg:postcode":"44319",
    "sg:province":"OH",
    "sg:tags":[
        "american",
        "pizza"
    ],
    "wof:name":"Papa John's Pizza",
    "wof:placetype":"venue"
},
  "geometry": {"coordinates":[-81.515068,41.028832],"type":"Point"}
}