{
  "type": "Feature",
  "properties": {
    "iso:country":"US",
    "sg:address":"5621 Farms Dr",
    "sg:city":"Columbus",
    "sg:classifiers":[
        {
            "category":"Professional",
            "subcategory":"Accounting & Tax Preparation",
            "type":"Services"
        }
    ],
    "sg:phone":"+1 614 863 5730",
    "sg:postcode":"43213",
    "sg:province":"OH",
    "sg:tags":[
        "accountant"
    ],
    "wof:name":"Bonnie E Morris Inc",
    "wof:placetype":"venue"
},
  "geometry": {"coordinates":[-82.84884,39.96399],"type":"Point"}
}