{
  "type": "Feature",
  "properties": {
    "addr:full": "1562 E 105th St Cleveland OH 44106",
    "addr:housenumber": "1562",
    "addr:postcode": "44106",
    "addr:street": "E 105Th St",
    "iso:country": "US",
    "sg:address": "1562 E 105th St",
    "sg:city": "Cleveland",
    "sg:classifiers": [
      {
        "category": "Restaurant",
        "type": "Food \u0026 Drink"
      }
    ],
    "sg:phone": "+1 216 421 1313",
    "sg:postcode": "44106",
    "sg:province": "OH",
    "sg:tags": [
      "delicatessen"
    ],
    "wof:name": "Big Daddy's Deli",
    "wof:placetype": "venue"
  },
  "geometry": {"coordinates":[-81.61548,41.513228],"type":"Point"}
}
