{
  "type": "Feature",
  "properties": {
    "addr:full": "9326 Gettysburg Dr Twinsburg OH 44087",
    "addr:housenumber": "9326",
    "addr:postcode": "44087",
    "addr:street": "Gettysburg Dr",
    "iso:country": "US",
    "sg:address": "9326 Gettysburg Dr",
    "sg:city": "Twinsburg",
    "sg:classifiers": [
      {
        "category": "Restaurant",
        "type": "Food \u0026 Drink"
      }
    ],
    "sg:phone": "+1 330 487 0269",
    "sg:postcode": "44087",
    "sg:province": "OH",
    "sg:tags": [
      "eating"
    ],
    "wof:name": "Beal St Cafe",
    "wof:placetype": "venue"
  },
  "geometry": {"coordinates":[-81.465094,41.324571],"type":"Point"}
}
