{
  "type": "Feature",
  "properties": {
    "iso:country":"US",
    "sg:address":"9326 Gettysburg Dr",
    "sg:city":"Twinsburg",
    "sg:classifiers":[
        {
            "category":"Restaurant",
            "type":"Food & Drink"
        }
    ],
    "sg:phone":"+1 330 487 0269",
    "sg:postcode":"44087",
    "sg:province":"OH",
    "sg:tags":[
        "eating"
    ],
    "wof:name":"Beal St Cafe",
    "wof:placetype":"venue"
},
  "geometry": {"coordinates":[-81.46509399999999,41.324571],"type":"Point"}
}