{
  "type": "Feature",
  "properties": {
    "addr:full":"309 S State St Westerville OH 43081",
    "addr:housenumber":"309",
    "addr:postcode":"43081",
    "addr:street":"S State St",
    "iso:country":"US",
    "sg:address":"309 S State St",
    "sg:city":"Westerville",
    "sg:classifiers":[
        {
            "category":"Insurance",
            "subcategory":"Insurance Agent",
            "type":"Services"
        }
    ],
    "sg:phone":"+1 614 890 2555",
    "sg:postcode":"43081",
    "sg:province":"OH",
    "wof:name":"State Farm Insurance",
    "wof:placetype":"venue"
},
  "geometry": {"coordinates":[-82.928246,40.116632],"type":"Point"}
}