{
  "type": "Feature",
  "properties": {
    "addr:full":"4238 Floral Ave Cincinnati OH 45212",
    "addr:housenumber":"4238",
    "addr:postcode":"45212",
    "addr:street":"Floral Ave",
    "iso:country":"US",
    "sg:address":"4238 Floral Ave",
    "sg:city":"Cincinnati",
    "sg:classifiers":[
        {
            "category":"Professional",
            "subcategory":"Management & Consulting",
            "type":"Services"
        }
    ],
    "sg:phone":"+1 513 841 2449",
    "sg:postcode":"45212",
    "sg:province":"OH",
    "sg:tags":[
        "counselor",
        "public",
        "relations"
    ],
    "wof:name":"3 C Media Inc",
    "wof:placetype":"venue"
},
  "geometry": {"coordinates":[-84.45277,39.155196],"type":"Point"}
}