{
  "type": "Feature",
  "properties": {
    "addr:full":"150 S Four Mile Run Rd Youngstown OH 44515",
    "addr:housenumber":"150",
    "addr:postcode":"44515",
    "addr:street":"S Four Mile Run Rd",
    "iso:country":"US",
    "sg:address":"150 S Four Mile Run Rd",
    "sg:city":"Youngstown",
    "sg:classifiers":[
        {
            "category":"Organizations",
            "subcategory":"Labor Organization",
            "type":"Services"
        }
    ],
    "sg:phone":"+1 330 792 4500",
    "sg:postcode":"44515",
    "sg:province":"OH",
    "wof:name":"Afscme Ohio Council Afl-Cio",
    "wof:placetype":"venue"
},
  "geometry": {"coordinates":[-80.715431,41.099712],"type":"Point"}
}