{
  "type": "Feature",
  "properties": {
    "addr:full": "32 N Wilkinson St Dayton OH 45402",
    "addr:housenumber": "32",
    "addr:postcode": "45402",
    "addr:street": "N Wilkinson St",
    "iso:country": "US",
    "sg:address": "32 N Wilkinson St",
    "sg:city": "Dayton",
    "sg:classifiers": [
      {
        "category": "Insurance",
        "subcategory": "Hazard Insurance",
        "type": "Services"
      }
    ],
    "sg:phone": "+1 937 224 3744",
    "sg:postcode": "45402",
    "sg:province": "OH",
    "sg:tags": [
      "bond"
    ],
    "wof:name": "Brenda's Bail Bonds",
    "wof:placetype": "venue"
  },
  "geometry": {"coordinates":[-84.195505,39.759968],"type":"Point"}
}
