{
  "type": "Feature",
  "properties": {
    "iso:country":"US",
    "sg:address":"1401 Raff Rd SW",
    "sg:city":"Canton",
    "sg:classifiers":[
        {
            "category":"Building & Trades",
            "subcategory":"Cleaning & Sanitation",
            "type":"Services"
        }
    ],
    "sg:phone":"+1 330 478 5151",
    "sg:postcode":"44710",
    "sg:province":"OH",
    "sg:tags":[
        "property",
        "maintenance"
    ],
    "sg:website":"www.preferred-interiors.com",
    "wof:name":"Preferred Interiors Ents",
    "wof:placetype":"venue"
},
  "geometry": {"coordinates":[-81.419892,40.783842],"type":"Point"}
}