{
  "type": "Feature",
  "properties": {
    "addr:full":"14839 Hofmeister Rd Petersburg OH 44454",
    "addr:postcode":"14839;44454",
    "addr:street":"Hofmeister Rd",
    "iso:country":"US",
    "sg:address":"14839 Hofmeister Rd",
    "sg:city":"Petersburg",
    "sg:classifiers":[
        {
            "category":"Freight",
            "type":"Transportation"
        }
    ],
    "sg:phone":"+1 330 542 2172",
    "sg:postcode":"44454",
    "sg:province":"OH",
    "sg:tags":[
        "operator",
        "local",
        "trucking"
    ],
    "wof:name":"Leonard Thomas Trucking Servic",
    "wof:placetype":"venue"
},
  "geometry": {"coordinates":[-80.557068,40.902547],"type":"Point"}
}