{
  "type": "Feature",
  "properties": {
    "addr:full":"118 Harding Way W Galion OH 44833",
    "addr:housenumber":"118",
    "addr:postcode":"44833",
    "addr:street":"Harding Way W",
    "iso:country":"US",
    "sg:address":"118 Harding Way W",
    "sg:city":"Galion",
    "sg:classifiers":[
        {
            "category":"Professional",
            "subcategory":"Lawyer & Legal Services",
            "type":"Services"
        }
    ],
    "sg:phone":"+1 419 468 1131",
    "sg:postcode":"44833",
    "sg:province":"OH",
    "sg:tags":[
        "attorney"
    ],
    "wof:name":"Wagner Law Firm",
    "wof:placetype":"venue"
},
  "geometry": {"coordinates":[-82.79096199999999,40.733998],"type":"Point"}
}