{
  "type": "Feature",
  "properties": {
    "addr:full": "12981 Grafton Rd Grafton OH 44044",
    "addr:housenumber": "12981",
    "addr:postcode": "44044",
    "addr:street": "Grafton Rd",
    "iso:country": "US",
    "sg:address": "12981 Grafton Rd",
    "sg:city": "Grafton",
    "sg:classifiers": [
      {
        "category": "Organizations",
        "subcategory": "Religious Organization",
        "type": "Services"
      }
    ],
    "sg:phone": "+1 440 458 5450",
    "sg:postcode": "44044",
    "sg:province": "OH",
    "sg:tags": [
      "church"
    ],
    "wof:name": "Grafton Baptist Church",
    "wof:placetype": "venue"
  },
  "geometry": {"coordinates":[-82.070232,41.300005],"type":"Point"}
}
