{
  "type": "Feature",
  "properties": {
    "iso:country":"US",
    "sg:address":"821 McCartney Rd",
    "sg:city":"Youngstown",
    "sg:classifiers":[
        {
            "category":"Health Services",
            "subcategory":"Doctor",
            "type":"Services"
        }
    ],
    "sg:phone":"+1 330 743 4440",
    "sg:postcode":"44505",
    "sg:province":"OH",
    "sg:tags":[
        "medical"
    ],
    "wof:name":"Frangopoulos Michael MD",
    "wof:placetype":"venue"
},
  "geometry": {"coordinates":[-80.582886,41.090296],"type":"Point"}
}