{
  "type": "Feature",
  "properties": {
    "iso:country":"US",
    "sg:address":"8250 Kenwood Rd",
    "sg:city":"Cincinnati",
    "sg:classifiers":[
        {
            "category":"Health Services",
            "subcategory":"Hospital",
            "type":"Services"
        }
    ],
    "sg:phone":"+1 513 793 6011",
    "sg:postcode":"45236",
    "sg:province":"OH",
    "sg:tags":[
        "surgical",
        "center",
        "general"
    ],
    "wof:name":"Kenwood Surgery Center",
    "wof:placetype":"venue"
},
  "geometry": {"coordinates":[-84.37944400000001,39.207522],"type":"Point"}
}