{
  "type": "Feature",
  "properties": {
    "addr:full": "900 Tiffin Ave Findlay OH 45840",
    "addr:housenumber": "900",
    "addr:postcode": "45840",
    "addr:street": "Tiffin Ave",
    "iso:country": "US",
    "sg:address": "900 Tiffin Ave",
    "sg:city": "Findlay",
    "sg:classifiers": [
      {
        "category": "Retail",
        "subcategory": "Auto Repair",
        "type": "Services"
      }
    ],
    "sg:phone": "+1 419 424 3157",
    "sg:postcode": "45840",
    "sg:province": "OH",
    "sg:tags": [
      "repairing",
      "automobile"
    ],
    "wof:name": "Midas Auto Svc Experts",
    "wof:placetype": "venue"
  },
  "geometry": {"coordinates":[-83.632626,41.048266],"type":"Point"}
}
