{
  "type": "Feature",
  "properties": {
    "addr:full": "103 S Case Ave Akron OH 44305",
    "addr:housenumber": "103",
    "addr:postcode": "44305",
    "addr:street": "S Case Ave",
    "iso:country": "US",
    "sg:address": "103 S Case Ave",
    "sg:city": "Akron",
    "sg:classifiers": [
      {
        "category": "Retail",
        "subcategory": "Auto Repair",
        "type": "Services"
      }
    ],
    "sg:phone": "+1 330 376 8511",
    "sg:postcode": "44305",
    "sg:province": "OH",
    "sg:tags": [
      "repairing",
      "automobile",
      "radiator"
    ],
    "wof:name": "International Welding",
    "wof:placetype": "venue"
  },
  "geometry": {"coordinates":[-81.489806,41.068382],"type":"Point"}
}
