{
  "type": "Feature",
  "properties": {
    "iso:country":"US",
    "sg:address":"103 S Case Ave",
    "sg:city":"Akron",
    "sg:classifiers":[
        {
            "category":"Retail",
            "subcategory":"Auto Repair",
            "type":"Services"
        }
    ],
    "sg:phone":"+1 330 376 8511",
    "sg:postcode":"44305",
    "sg:province":"OH",
    "sg:tags":[
        "repairing",
        "automobile",
        "radiator"
    ],
    "wof:name":"International Welding",
    "wof:placetype":"venue"
},
  "geometry": {"coordinates":[-81.489806,41.068382],"type":"Point"}
}