{
  "type": "Feature",
  "properties": {
    "iso:country":"US",
    "sg:address":"719 W Market St",
    "sg:city":"Baltimore",
    "sg:classifiers":[
        {
            "category":"Real Estate",
            "subcategory":"Real Estate Services",
            "type":"Services"
        }
    ],
    "sg:phone":"+1 740 862 4192",
    "sg:postcode":"43105",
    "sg:province":"OH",
    "sg:tags":[
        "abstract",
        "title"
    ],
    "wof:name":"Baltimore Title Agency",
    "wof:placetype":"venue"
},
  "geometry": {"coordinates":[-82.61110600000001,39.845564],"type":"Point"}
}