{
  "type": "Feature",
  "properties": {
    "addr:full": "4089 Leap Rd Hilliard OH 43026",
    "addr:housenumber": "4089",
    "addr:postcode": "43026",
    "addr:street": "Leap Rd",
    "iso:country": "US",
    "sg:address": "4089 Leap Rd",
    "sg:city": "Hilliard",
    "sg:classifiers": [
      {
        "category": "Professional",
        "subcategory": "Computer Services",
        "type": "Services"
      }
    ],
    "sg:phone": "+1 614 850 3366",
    "sg:postcode": "43026",
    "sg:province": "OH",
    "sg:tags": [
      "management",
      "related",
      "facility"
    ],
    "wof:name": "Redemtech Inc",
    "wof:placetype": "venue"
  },
  "geometry": {"coordinates":[-83.140136,40.038427],"type":"Point"}
}
