{
  "type": "Feature",
  "properties": {
    "iso:country":"US",
    "sg:address":"1717 Rockhurst Dr",
    "sg:city":"Dayton",
    "sg:classifiers":[
        {
            "category":"Professional",
            "subcategory":"Computer Services",
            "type":"Services"
        }
    ],
    "sg:phone":"+1 937 252 7635",
    "sg:postcode":"45420",
    "sg:province":"OH",
    "sg:tags":[
        "graphics"
    ],
    "wof:name":"Cannon IV",
    "wof:placetype":"venue"
},
  "geometry": {"coordinates":[-84.13577600000001,39.713451],"type":"Point"}
}