{
  "type": "Feature",
  "properties": {
    "addr:full": "927 S Market St Troy OH 45373",
    "addr:housenumber": "927",
    "addr:postcode": "45373",
    "addr:street": "S Market St",
    "iso:country": "US",
    "sg:address": "927 S Market St",
    "sg:city": "Troy",
    "sg:classifiers": [
      {
        "category": "Manufacturing",
        "subcategory": "Electronics",
        "type": "Manufacturing \u0026 Wholesale Goods"
      }
    ],
    "sg:phone": "+1 937 339 8293",
    "sg:postcode": "45373",
    "sg:province": "OH",
    "sg:tags": [
      "equipment",
      "mfg",
      "home"
    ],
    "wof:name": "Traffic Jams of Troy",
    "wof:placetype": "venue"
  },
  "geometry": {"coordinates":[-84.208423,40.030023],"type":"Point"}
}
