{
  "type": "Feature",
  "properties": {
    "iso:country":"US",
    "sg:address":"5763 Talmadge Rd",
    "sg:city":"Toledo",
    "sg:classifiers":[
        {
            "category":"Retail",
            "subcategory":"Repair Shop",
            "type":"Services"
        },
        {
            "category":"Shopping",
            "subcategory":"Jewelry",
            "type":"Retail Goods"
        }
    ],
    "sg:phone":"+1 419 472 9943",
    "sg:postcode":"43623",
    "sg:province":"OH",
    "sg:tags":[
        "watch"
    ],
    "wof:name":"Stan's Watch Repair",
    "wof:placetype":"venue"
},
  "geometry": {"coordinates":[-83.64570500000001,41.718392],"type":"Point"}
}