{
  "type": "Feature",
  "properties": {
    "addr:full": "5763 Talmadge Rd Toledo OH 43623",
    "addr:housenumber": "5763",
    "addr:postcode": "43623",
    "addr:street": "Talmadge Rd",
    "iso:country": "US",
    "sg:address": "5763 Talmadge Rd",
    "sg:city": "Toledo",
    "sg:classifiers": [
      {
        "category": "Retail",
        "subcategory": "Repair Shop",
        "type": "Services"
      },
      {
        "category": "Shopping",
        "subcategory": "Jewelry",
        "type": "Retail Goods"
      }
    ],
    "sg:phone": "+1 419 472 9943",
    "sg:postcode": "43623",
    "sg:province": "OH",
    "sg:tags": [
      "watch"
    ],
    "wof:name": "Stan's Watch Repair",
    "wof:placetype": "venue"
  },
  "geometry": {"coordinates":[-83.645705,41.718392],"type":"Point"}
}
