{
  "type": "Feature",
  "properties": {
    "iso:country":"US",
    "sg:address":"215 N Fayette St",
    "sg:city":"Washington Ct Hs",
    "sg:classifiers":[
        {
            "category":"Personal",
            "subcategory":"Beauty Salon",
            "type":"Services"
        }
    ],
    "sg:phone":"+1 740 335 3130",
    "sg:postcode":"43160",
    "sg:province":"OH",
    "wof:name":"D3 Styling Salon",
    "wof:placetype":"venue"
},
  "geometry": {"coordinates":[-83.44069399999999,39.53818],"type":"Point"}
}