{
  "type": "Feature",
  "properties": {
    "addr:full": "7976 Broadview Rd Cleveland OH 44147",
    "addr:housenumber": "7976",
    "addr:postcode": "44147",
    "addr:street": "Broadview Rd",
    "iso:country": "US",
    "sg:address": "7976 Broadview Rd",
    "sg:city": "Cleveland",
    "sg:classifiers": [
      {
        "category": "Arena",
        "subcategory": "Sports Club",
        "type": "Entertainment"
      }
    ],
    "sg:phone": "+1 440 746 1717",
    "sg:postcode": "44147",
    "sg:province": "OH",
    "sg:tags": [
      "manager",
      "recruiter",
      "promoter"
    ],
    "wof:name": "Vegas Experts",
    "wof:placetype": "venue"
  },
  "geometry": {"coordinates":[-81.684674,41.347449],"type":"Point"}
}
