{
  "type": "Feature",
  "properties": {
    "iso:country":"US",
    "sg:address":"450 Oak Ridge Blvd",
    "sg:city":"Miamisburg",
    "sg:classifiers":[
        {
            "category":"Health Services",
            "subcategory":"Nursing And Care Facility",
            "type":"Services"
        }
    ],
    "sg:phone":"+1 937 866 8885",
    "sg:postcode":"45342",
    "sg:province":"OH",
    "sg:tags":[
        "home",
        "convalescent"
    ],
    "wof:name":"Oak Ridge Retirement Village",
    "wof:placetype":"venue"
},
  "geometry": {"coordinates":[-84.24896099999999,39.631562],"type":"Point"}
}