{
  "type": "Feature",
  "properties": {
    "addr:full": "450 Oak Ridge Blvd Miamisburg OH 45342",
    "addr:housenumber": "450",
    "addr:postcode": "45342",
    "addr:street": "Oak Ridge Blvd",
    "iso:country": "US",
    "sg:address": "450 Oak Ridge Blvd",
    "sg:city": "Miamisburg",
    "sg:classifiers": [
      {
        "category": "Health Services",
        "subcategory": "Nursing And Care Facility",
        "type": "Services"
      }
    ],
    "sg:phone": "+1 937 866 8885",
    "sg:postcode": "45342",
    "sg:province": "OH",
    "sg:tags": [
      "home",
      "convalescent"
    ],
    "wof:name": "Oak Ridge Retirement Village",
    "wof:placetype": "venue"
  },
  "geometry": {"coordinates":[-84.248961,39.631562],"type":"Point"}
}
