{
  "type": "Feature",
  "properties": {
    "iso:country":"US",
    "sg:address":"4190 State Rd",
    "sg:city":"Cuyahoga Falls",
    "sg:classifiers":[
        {
            "category":"Sports & Exercise",
            "subcategory":"Bowling",
            "type":"Entertainment"
        }
    ],
    "sg:phone":"+1 330 928 3794",
    "sg:postcode":"44223",
    "sg:province":"OH",
    "sg:tags":[
        "operated",
        "snack",
        "bar",
        "alley",
        "coin"
    ],
    "wof:name":"North Lanes",
    "wof:placetype":"venue"
},
  "geometry": {"coordinates":[-81.50865899999999,41.183944],"type":"Point"}
}