{
  "type": "Feature",
  "properties": {
    "addr:full": "4190 State Rd Cuyahoga Falls OH 44223",
    "addr:housenumber": "4190",
    "addr:postcode": "44223",
    "addr:street": "State Rd",
    "iso:country": "US",
    "sg:address": "4190 State Rd",
    "sg:city": "Cuyahoga Falls",
    "sg:classifiers": [
      {
        "category": "Sports \u0026 Exercise",
        "subcategory": "Bowling",
        "type": "Entertainment"
      }
    ],
    "sg:phone": "+1 330 928 3794",
    "sg:postcode": "44223",
    "sg:province": "OH",
    "sg:tags": [
      "operated",
      "snack",
      "bar",
      "alley",
      "coin"
    ],
    "wof:name": "North Lanes",
    "wof:placetype": "venue"
  },
  "geometry": {"coordinates":[-81.508659,41.183944],"type":"Point"}
}
