{
  "type": "Feature",
  "properties": {
    "addr:full": "39 Baermar Dr Shelby OH 44875",
    "addr:housenumber": "39",
    "addr:postcode": "44875",
    "addr:street": "Baermar Dr",
    "iso:country": "US",
    "sg:address": "39 Baermar Dr",
    "sg:city": "Shelby",
    "sg:classifiers": [
      {
        "category": "Building \u0026 Trades",
        "subcategory": "Plumbing",
        "type": "Services"
      }
    ],
    "sg:phone": "+1 419 342 3697",
    "sg:postcode": "44875",
    "sg:province": "OH",
    "sg:tags": [
      "contractor"
    ],
    "wof:name": "Gary Blevins",
    "wof:placetype": "venue"
  },
  "geometry": {"coordinates":[-82.666684,40.86652],"type":"Point"}
}
