{
  "type": "Feature",
  "properties": {
    "addr:full": "728 Graham Dr Fremont OH 43420",
    "addr:housenumber": "728",
    "addr:postcode": "43420",
    "addr:street": "Graham Dr",
    "iso:country": "US",
    "sg:address": "728 Graham Dr",
    "sg:city": "Fremont",
    "sg:classifiers": [
      {
        "category": "Manufacturing",
        "subcategory": "Metals",
        "type": "Manufacturing \u0026 Wholesale Goods"
      }
    ],
    "sg:phone": "+1 419 355 9111",
    "sg:postcode": "43420",
    "sg:province": "OH",
    "sg:tags": [
      "pneumatic",
      "valve",
      "hydraulic",
      "mfg"
    ],
    "wof:name": "Seawin Inc",
    "wof:placetype": "venue"
  },
  "geometry": {"coordinates":[-83.076714,41.35183],"type":"Point"}
}
