{
  "type": "Feature",
  "properties": {
    "iso:country":"US",
    "sg:address":"2542 S Linden Ave",
    "sg:city":"Alliance",
    "sg:classifiers":[
        {
            "category":"Food & Beverages",
            "subcategory":"Specialty",
            "type":"Retail Goods"
        }
    ],
    "sg:phone":"+1 330 823 6222",
    "sg:postcode":"44601",
    "sg:province":"OH",
    "sg:tags":[
        "herb"
    ],
    "wof:name":"Hart's Desire Herb Alliance",
    "wof:placetype":"venue"
},
  "geometry": {"coordinates":[-81.099935,40.898552],"type":"Point"}
}