{
  "type": "Feature",
  "properties": {
    "addr:full":"7359 International Dr Holland OH 43528",
    "addr:housenumber":"7359",
    "addr:postcode":"43528",
    "addr:street":"International Dr",
    "iso:country":"US",
    "sg:address":"7359 International Dr",
    "sg:city":"Holland",
    "sg:classifiers":[
        {
            "category":"Banks & Credit Unions",
            "subcategory":"Investment Brokerage",
            "type":"Services"
        }
    ],
    "sg:phone":"+1 419 536 9108",
    "sg:postcode":"43528",
    "sg:province":"OH",
    "sg:tags":[
        "funds",
        "mutual"
    ],
    "wof:name":"Sammons Securities Co LLC",
    "wof:placetype":"venue"
},
  "geometry": {"coordinates":[-83.716572,41.609156],"type":"Point"}
}