{
  "type": "Feature",
  "properties": {
    "iso:country":"US",
    "sg:address":"172 S 30th St",
    "sg:city":"Newark",
    "sg:classifiers":[
        {
            "category":"Personal",
            "subcategory":"Beauty Salon",
            "type":"Services"
        }
    ],
    "sg:phone":"+1 740 344 9724",
    "sg:postcode":"43055",
    "sg:province":"OH",
    "wof:name":"Kristoffer's Salon",
    "wof:placetype":"venue"
},
  "geometry": {"coordinates":[-82.44198,40.044425],"type":"Point"}
}