{
  "type": "Feature",
  "properties": {
    "addr:full":"302 S Chestnut St Barnesville OH 43713",
    "addr:housenumber":"302",
    "addr:postcode":"43713",
    "addr:street":"S Chestnut St",
    "iso:country":"US",
    "sg:address":"302 S Chestnut St",
    "sg:city":"Barnesville",
    "sg:phone":"+1 740 425 1241",
    "sg:postcode":"43713",
    "sg:province":"OH",
    "sg:tags":[
        "bulk",
        "distributor",
        "kerosene",
        "oil",
        "heating"
    ],
    "wof:name":"Starr Oil",
    "wof:placetype":"venue"
},
  "geometry": {"coordinates":[-81.17802500000001,39.98631],"type":"Point"}
}