{
  "type": "Feature",
  "properties": {
    "iso:country":"US",
    "sg:address":"3142 W 14th St",
    "sg:city":"Cleveland",
    "sg:classifiers":[
        {
            "category":"Restaurant",
            "type":"Food & Drink"
        }
    ],
    "sg:phone":"+1 216 861 6555",
    "sg:postcode":"44109",
    "sg:province":"OH",
    "sg:tags":[
        "eating"
    ],
    "wof:name":"Vanessas Pizzeria",
    "wof:placetype":"venue"
},
  "geometry": {"coordinates":[-81.69125699999999,41.468029],"type":"Point"}
}