{
  "type": "Feature",
  "properties": {
    "iso:country":"US",
    "sg:address":"2118 Tremainsville Rd",
    "sg:city":"Toledo",
    "sg:classifiers":[
        {
            "category":"Shopping",
            "subcategory":"Clothing, Apparel, & Fashions",
            "type":"Retail Goods"
        }
    ],
    "sg:phone":"+1 419 472 5504",
    "sg:postcode":"43613",
    "sg:province":"OH",
    "sg:tags":[
        "leather",
        "garment"
    ],
    "wof:name":"Briarpatch",
    "wof:placetype":"venue"
},
  "geometry": {"coordinates":[-83.59567699999999,41.699578],"type":"Point"}
}