{
  "type": "Feature",
  "properties": {
    "iso:country":"US",
    "sg:address":"305 W 3rd St",
    "sg:city":"Mc Donald",
    "sg:classifiers":[
        {
            "category":"Home & Garden",
            "subcategory":"Carpets & Floor Coverings",
            "type":"Retail Goods"
        }
    ],
    "sg:phone":"+1 330 530 4878",
    "sg:postcode":"44437",
    "sg:province":"OH",
    "sg:tags":[
        "rug"
    ],
    "wof:name":"Endi Enterprises",
    "wof:placetype":"venue"
},
  "geometry": {"coordinates":[-80.72700500000001,41.166913],"type":"Point"}
}