{
  "type": "Feature",
  "properties": {
    "iso:country":"US",
    "sg:address":"800 Lila Ave",
    "sg:city":"Milford",
    "sg:classifiers":[
        {
            "category":"Wholesale",
            "subcategory":"Non-durable Goods",
            "type":"Manufacturing & Wholesale Goods"
        }
    ],
    "sg:phone":"+1 513 831 2834",
    "sg:postcode":"45150",
    "sg:province":"OH",
    "wof:name":"Young Robt L & Assoc",
    "wof:placetype":"venue"
},
  "geometry": {"coordinates":[-84.283615,39.17595],"type":"Point"}
}