{
  "type": "Feature",
  "properties": {
    "iso:country":"US",
    "sg:address":"2020 Cincinnati Dayton Rd",
    "sg:city":"Middletown",
    "sg:classifiers":[
        {
            "category":"Autos & Motor Vehicles",
            "subcategory":"Automobile Sales",
            "type":"Retail Goods"
        }
    ],
    "sg:phone":"+1 513 423 7500",
    "sg:postcode":"45044",
    "sg:province":"OH",
    "sg:tags":[
        "car",
        "dealer"
    ],
    "wof:name":"D & D Auto Finance",
    "wof:placetype":"venue"
},
  "geometry": {"coordinates":[-84.337116,39.493177],"type":"Point"}
}