{
  "type": "Feature",
  "properties": {
    "addr:full":"50585 Richardson Ave Negley OH 44441",
    "addr:housenumber":"50585",
    "addr:postcode":"44441",
    "addr:street":"Richardson Ave",
    "iso:country":"US",
    "sg:address":"50585 Richardson Ave",
    "sg:city":"Negley",
    "sg:classifiers":[
        {
            "category":"Autos & Motor Vehicles",
            "subcategory":"Automobile Sales",
            "type":"Retail Goods"
        }
    ],
    "sg:phone":"+1 330 426 6556",
    "sg:postcode":"44441",
    "sg:province":"OH",
    "sg:tags":[
        "car",
        "dealer"
    ],
    "wof:name":"R & P Auto Sales",
    "wof:placetype":"venue"
},
  "geometry": {"coordinates":[-80.544,40.789732],"type":"Point"}
}