{
  "type": "Feature",
  "properties": {
    "addr:full":"435 S Main St Franklin OH 45005",
    "addr:housenumber":"435",
    "addr:postcode":"45005",
    "addr:street":"S Main St",
    "iso:country":"US",
    "sg:address":"435 S Main St",
    "sg:city":"Franklin",
    "sg:classifiers":[
        {
            "category":"Personal",
            "subcategory":"Beauty Salon",
            "type":"Services"
        }
    ],
    "sg:phone":"+1 937 746 2717",
    "sg:postcode":"45005",
    "sg:province":"OH",
    "wof:name":"Innovations Hair Design",
    "wof:placetype":"venue"
},
  "geometry": {"coordinates":[-84.30442499999999,39.559902],"type":"Point"}
}