{
  "type": "Feature",
  "properties": {
    "iso:country":"US",
    "sg:address":"7817 Cooper Rd",
    "sg:city":"Cincinnati",
    "sg:classifiers":[
        {
            "category":"Health Services",
            "subcategory":"Doctor",
            "type":"Services"
        }
    ],
    "sg:phone":"+1 513 891 8089",
    "sg:postcode":"45242",
    "sg:province":"OH",
    "sg:tags":[
        "physician",
        "surgeon"
    ],
    "wof:name":"Henry C Waite MD",
    "wof:placetype":"venue"
},
  "geometry": {"coordinates":[-84.355277,39.226508],"type":"Point"}
}