{
  "type": "Feature",
  "properties": {
    "iso:country":"US",
    "sg:address":"2495 Election House Rd NW",
    "sg:city":"Lancaster",
    "sg:classifiers":[
        {
            "category":"Building & Trades",
            "subcategory":"Construction",
            "type":"Services"
        }
    ],
    "sg:phone":"+1 740 654 2855",
    "sg:postcode":"43130",
    "sg:province":"OH",
    "wof:name":"Eversole Builders",
    "wof:placetype":"venue"
},
  "geometry": {"coordinates":[-82.64622199999999,39.769983],"type":"Point"}
}