{
  "type": "Feature",
  "properties": {
    "addr:full": "1580 Holloway Rd Holland OH 43528",
    "addr:housenumber": "1580",
    "addr:postcode": "43528",
    "addr:street": "Holloway Rd",
    "iso:country": "US",
    "sg:address": "1580 Holloway Rd",
    "sg:city": "Holland",
    "sg:classifiers": [
      {
        "category": "Wholesale",
        "subcategory": "Construction Materials",
        "type": "Manufacturing \u0026 Wholesale Goods"
      }
    ],
    "sg:phone": "+1 419 866 4400",
    "sg:postcode": "43528",
    "sg:province": "OH",
    "sg:tags": [
      "insulation"
    ],
    "wof:name": "Insulation Fabricators Inc",
    "wof:placetype": "venue"
  },
  "geometry": {"coordinates":[-83.713303,41.614797],"type":"Point"}
}
