{
  "type": "Feature",
  "properties": {
    "addr:full":"1003 E Main St Newark OH 43055",
    "addr:housenumber":"1003",
    "addr:postcode":"43055",
    "addr:street":"E Main St",
    "iso:country":"US",
    "sg:address":"1003 E Main St",
    "sg:city":"Newark",
    "sg:classifiers":[
        {
            "category":"Government",
            "subcategory":"Office",
            "type":"Public Place"
        }
    ],
    "sg:phone":"+1 740 349 6769",
    "sg:postcode":"43055",
    "sg:province":"OH",
    "sg:tags":[
        "management"
    ],
    "wof:name":"Waste Water Plant",
    "wof:placetype":"venue"
},
  "geometry": {"coordinates":[-82.362362,40.061082],"type":"Point"}
}