{
  "type": "Feature",
  "properties": {
    "iso:country":"US",
    "sg:address":"23230 Chagrin Blvd",
    "sg:city":"Cleveland",
    "sg:classifiers":[
        {
            "category":"Real Estate",
            "subcategory":"Real Estate Operator",
            "type":"Services"
        }
    ],
    "sg:phone":"+1 216 595 1800",
    "sg:postcode":"44122",
    "sg:province":"OH",
    "sg:tags":[
        "owner",
        "building",
        "apartment"
    ],
    "wof:name":"Carriage Hill Apartments",
    "wof:placetype":"venue"
},
  "geometry": {"coordinates":[-81.5055,41.464401],"type":"Point"}
}