{
  "type": "Feature",
  "properties": {
    "addr:full": "1031 S Main St Centerville OH 45458",
    "addr:housenumber": "1031",
    "addr:postcode": "45458",
    "addr:street": "S Main St",
    "iso:country": "US",
    "sg:address": "1031 S Main St",
    "sg:city": "Centerville",
    "sg:classifiers": [
      {
        "category": "Insurance",
        "subcategory": "Insurance Agent",
        "type": "Services"
      }
    ],
    "sg:phone": "+1 937 424 5438",
    "sg:postcode": "45458",
    "sg:province": "OH",
    "wof:name": "Eric Lowman Insurance",
    "wof:placetype": "venue"
  },
  "geometry": {"coordinates":[-84.160375,39.611868],"type":"Point"}
}
