{
  "type": "Feature",
  "properties": {
    "iso:country":"US",
    "sg:address":"25 Hillside Ct",
    "sg:city":"Howard",
    "sg:classifiers":[
        {
            "category":"Real Estate",
            "subcategory":"Real Estate Agent",
            "type":"Services"
        }
    ],
    "sg:phone":"+1 740 392 8762",
    "sg:postcode":"43028",
    "sg:province":"OH",
    "wof:name":"Richard Perrin Assoc Inc",
    "wof:placetype":"venue"
},
  "geometry": {"coordinates":[-82.34174299999999,40.41585],"type":"Point"}
}