{
  "type": "Feature",
  "properties": {
    "addr:full": "896 National Rd Bridgeport OH 43912",
    "addr:housenumber": "896",
    "addr:postcode": "43912",
    "addr:street": "National Rd",
    "iso:country": "US",
    "sg:address": "896 National Rd",
    "sg:city": "Bridgeport",
    "sg:classifiers": [
      {
        "category": "Professional",
        "subcategory": "Business Services",
        "type": "Services"
      }
    ],
    "sg:phone": "+1 740 968 3378",
    "sg:postcode": "43912",
    "sg:province": "OH",
    "sg:tags": [
      "drafting"
    ],
    "wof:name": "Ad-Vance Structural Drafting",
    "wof:placetype": "venue"
  },
  "geometry": {"coordinates":[-80.76157,40.070617],"type":"Point"}
}
