{
  "type": "Feature",
  "properties": {
    "iso:country":"US",
    "sg:address":"771 S 30th St",
    "sg:city":"Heath",
    "sg:classifiers":[
        {
            "category":"Wholesale",
            "subcategory":"Groceries",
            "type":"Manufacturing & Wholesale Goods"
        }
    ],
    "sg:phone":"+1 740 522 0669",
    "sg:postcode":"43056",
    "sg:province":"OH",
    "sg:tags":[
        "pretzel"
    ],
    "wof:name":"Auntie Anne's Hand Rolled Soft",
    "wof:placetype":"venue"
},
  "geometry": {"coordinates":[-82.443395,40.030931],"type":"Point"}
}