{
  "type": "Feature",
  "properties": {
    "addr:full": "3460 Harding Hwy E Marion OH 43302",
    "addr:housenumber": "3460",
    "addr:postcode": "43302",
    "addr:street": "Harding Hwy E",
    "iso:country": "US",
    "sg:address": "3460 Harding Hwy E",
    "sg:city": "Marion",
    "sg:classifiers": [
      {
        "category": "Wholesale",
        "subcategory": "Hardware",
        "type": "Manufacturing \u0026 Wholesale Goods"
      }
    ],
    "sg:phone": "+1 740 375 0141",
    "sg:postcode": "43302",
    "sg:province": "OH",
    "sg:tags": [
      "robot"
    ],
    "wof:name": "Motion Controls Plus",
    "wof:placetype": "venue"
  },
  "geometry": {"coordinates":[-83.040558,40.611648],"type":"Point"}
}
