{
  "type": "Feature",
  "properties": {
    "iso:country":"US",
    "sg:address":"8430 Mayfield Rd",
    "sg:city":"Chesterland",
    "sg:classifiers":[
        {
            "category":"Shopping",
            "type":"Retail Goods"
        }
    ],
    "sg:phone":"+1 440 729 3284",
    "sg:postcode":"44026",
    "sg:province":"OH",
    "sg:tags":[
        "merchandise"
    ],
    "wof:name":"Discount Directory Inc",
    "wof:placetype":"venue"
},
  "geometry": {"coordinates":[-81.338796,41.522227],"type":"Point"}
}