{
  "type": "Feature",
  "properties": {
    "addr:full": "213 E Main St Jackson OH 45640",
    "addr:housenumber": "213",
    "addr:postcode": "45640",
    "addr:street": "E Main St",
    "iso:country": "US",
    "sg:address": "213 E Main St",
    "sg:city": "Jackson",
    "sg:classifiers": [
      {
        "category": "Insurance",
        "subcategory": "Insurance Agent",
        "type": "Services"
      }
    ],
    "sg:phone": "+1 740 286 5031",
    "sg:postcode": "45640",
    "sg:province": "OH",
    "sg:tags": [
      "accident"
    ],
    "wof:name": "Carlisle Insurance",
    "wof:placetype": "venue"
  },
  "geometry": {"coordinates":[-82.631816,39.047493],"type":"Point"}
}
