{
  "type": "Feature",
  "properties": {
    "iso:country":"US",
    "sg:address":"10023 Windzag Ln",
    "sg:city":"Cincinnati",
    "sg:classifiers":[
        {
            "category":"Shopping",
            "subcategory":"Jewelry",
            "type":"Retail Goods"
        }
    ],
    "sg:phone":"+1 513 793 8710",
    "sg:postcode":"45242",
    "sg:province":"OH",
    "sg:tags":[
        "jeweler"
    ],
    "wof:name":"Marquerite Shurte Jewelry",
    "wof:placetype":"venue"
},
  "geometry": {"coordinates":[-84.364763,39.244721],"type":"Point"}
}