{
  "type": "Feature",
  "properties": {
    "iso:country":"US",
    "sg:address":"11010 Southland Rd",
    "sg:city":"Cincinnati",
    "sg:classifiers":[
        {
            "category":"Food & Beverages",
            "subcategory":"Groceries & Convenience Stores",
            "type":"Retail Goods"
        }
    ],
    "sg:phone":"+1 513 742 8281",
    "sg:postcode":"45240",
    "sg:province":"OH",
    "wof:name":"Forest Park Sunoco",
    "wof:placetype":"venue"
},
  "geometry": {"coordinates":[-84.49518399999999,39.277344],"type":"Point"}
}