{
  "type": "Feature",
  "properties": {
    "iso:country":"US",
    "sg:address":"6003 Squirrel Woods Ct",
    "sg:city":"Cincinnati",
    "sg:classifiers":[
        {
            "category":"Recreation",
            "type":"Entertainment"
        }
    ],
    "sg:phone":"+1 513 741 1080",
    "sg:postcode":"45247",
    "sg:province":"OH",
    "wof:name":"Kissel Bros Shows Inc",
    "wof:placetype":"venue"
},
  "geometry": {"coordinates":[-84.62231,39.204283],"type":"Point"}
}