{
  "type": "Feature",
  "properties": {
    "iso:country":"US",
    "sg:address":"59535 Claysville Rd",
    "sg:city":"Cambridge",
    "sg:classifiers":[
        {
            "category":"Organizations",
            "subcategory":"Religious Organization",
            "type":"Services"
        }
    ],
    "sg:phone":"+1 740 432 4341",
    "sg:postcode":"43725",
    "sg:province":"OH",
    "sg:tags":[
        "church"
    ],
    "wof:name":"East Union Presbyterian Church",
    "wof:placetype":"venue"
},
  "geometry": {"coordinates":[-81.66425099999999,39.963205],"type":"Point"}
}