{
  "type": "Feature",
  "properties": {
    "iso:country":"US",
    "sg:address":"1414 Whipple Ave NW",
    "sg:city":"Canton",
    "sg:classifiers":[
        {
            "category":"Insurance",
            "subcategory":"Life Insurance",
            "type":"Services"
        }
    ],
    "sg:phone":"+1 330 479 9052",
    "sg:postcode":"44708",
    "sg:province":"OH",
    "sg:tags":[
        "carrier"
    ],
    "wof:name":"Neff & Associates",
    "wof:placetype":"venue"
},
  "geometry": {"coordinates":[-81.425204,40.814266],"type":"Point"}
}