{
  "type": "Feature",
  "properties": {
    "addr:full": "1414 Whipple Ave NW Canton OH 44708",
    "addr:housenumber": "1414",
    "addr:postcode": "44708",
    "addr:street": "Whipple Ave Nw",
    "iso:country": "US",
    "sg:address": "1414 Whipple Ave NW",
    "sg:city": "Canton",
    "sg:classifiers": [
      {
        "category": "Insurance",
        "subcategory": "Life Insurance",
        "type": "Services"
      }
    ],
    "sg:phone": "+1 330 479 9052",
    "sg:postcode": "44708",
    "sg:province": "OH",
    "sg:tags": [
      "carrier"
    ],
    "wof:name": "Neff \u0026 Associates",
    "wof:placetype": "venue"
  },
  "geometry": {"coordinates":[-81.425204,40.814266],"type":"Point"}
}
