{
  "type": "Feature",
  "properties": {
    "iso:country":"US",
    "sg:address":"975 Old Henderson Rd",
    "sg:city":"Columbus",
    "sg:classifiers":[
        {
            "category":"Manufacturing",
            "subcategory":"Signs",
            "type":"Manufacturing & Wholesale Goods"
        }
    ],
    "sg:phone":"+1 614 459 7006",
    "sg:postcode":"43220",
    "sg:province":"OH",
    "sg:tags":[
        "specialty",
        "mfg"
    ],
    "wof:name":"Hightech Signs",
    "wof:placetype":"venue"
},
  "geometry": {"coordinates":[-83.04463,40.052237],"type":"Point"}
}