{
  "type": "Feature",
  "properties": {
    "addr:full": "3646 Edwards Rd Cincinnati OH 45208",
    "addr:housenumber": "3646",
    "addr:postcode": "45208",
    "addr:street": "Edwards Rd",
    "iso:country": "US",
    "sg:address": "3646 Edwards Rd",
    "sg:city": "Cincinnati",
    "sg:classifiers": [
      {
        "category": "Restaurant",
        "type": "Food \u0026 Drink"
      }
    ],
    "sg:phone": "+1 513 321 2028",
    "sg:postcode": "45208",
    "sg:province": "OH",
    "sg:tags": [
      "eating"
    ],
    "wof:name": "Sizzling Wok Hyde Park",
    "wof:placetype": "venue"
  },
  "geometry": {"coordinates":[-84.442849,39.143712],"type":"Point"}
}
