{
  "type": "Feature",
  "properties": {
    "iso:country":"US",
    "sg:address":"2340 Larson Rd SE",
    "sg:city":"Gnadenhutten",
    "sg:classifiers":[
        {
            "category":"Professional",
            "subcategory":"Management & Consulting",
            "type":"Services"
        }
    ],
    "sg:phone":"+1 740 254 9860",
    "sg:postcode":"44629",
    "sg:province":"OH",
    "sg:tags":[
        "consultant"
    ],
    "wof:name":"Norris Consulting",
    "wof:placetype":"venue"
},
  "geometry": {"coordinates":[-81.417103,40.366488],"type":"Point"}
}