{
  "type": "Feature",
  "properties": {
    "iso:country":"US",
    "sg:address":"257 W Union St",
    "sg:city":"Athens",
    "sg:classifiers":[
        {
            "category":"Manufacturing",
            "subcategory":"Electronics",
            "type":"Manufacturing & Wholesale Goods"
        }
    ],
    "sg:phone":"+1 740 593 3150",
    "sg:postcode":"45701",
    "sg:province":"OH",
    "sg:tags":[
        "apparatus",
        "mfg",
        "component",
        "telephone",
        "telegraph",
        "home",
        "electronic"
    ],
    "sg:website":"www.gorman-redlich.com",
    "wof:name":"Gorman-Redlich Mfg Co",
    "wof:placetype":"venue"
},
  "geometry": {"coordinates":[-82.115073,39.329764],"type":"Point"}
}