{
  "type": "Feature",
  "properties": {
    "iso:country":"US",
    "sg:address":"23440 Lakeland Blvd",
    "sg:city":"Cleveland",
    "sg:classifiers":[
        {
            "category":"Building & Trades",
            "subcategory":"Electrical",
            "type":"Services"
        }
    ],
    "sg:phone":"+1 216 731 0202",
    "sg:postcode":"44132",
    "sg:province":"OH",
    "sg:tags":[
        "electrical",
        "electric",
        "contractor"
    ],
    "wof:name":"Euclid Electric Company",
    "wof:placetype":"venue"
},
  "geometry": {"coordinates":[-81.520338,41.59002],"type":"Point"}
}