{
  "type": "Feature",
  "properties": {
    "addr:full": "5816 Hunting Haven Dr Hilliard OH 43026",
    "addr:housenumber": "5816",
    "addr:postcode": "43026",
    "addr:street": "Hunting Haven Dr",
    "iso:country": "US",
    "sg:address": "5816 Hunting Haven Dr",
    "sg:city": "Hilliard",
    "sg:classifiers": [
      {
        "category": "Professional",
        "subcategory": "Management \u0026 Consulting",
        "type": "Services"
      }
    ],
    "sg:phone": "+1 614 777 8957",
    "sg:postcode": "43026",
    "sg:province": "OH",
    "sg:tags": [
      "retail",
      "direct",
      "sales"
    ],
    "wof:name": "Cmb Production",
    "wof:placetype": "venue"
  },
  "geometry": {"coordinates":[-83.17075,40.013475],"type":"Point"}
}
