{
  "type": "Feature",
  "properties": {
    "addr:full":"9265 Deerfield Dr Westfield Center OH 44251",
    "addr:housenumber":"9265",
    "addr:postcode":"44251",
    "addr:street":"Deerfield Dr",
    "iso:country":"US",
    "sg:address":"9265 Deerfield Dr",
    "sg:city":"Westfield Center",
    "sg:classifiers":[
        {
            "category":"Health Services",
            "subcategory":"Dentist",
            "type":"Services"
        }
    ],
    "sg:phone":"+1 330 948 9041",
    "sg:postcode":"44251",
    "sg:province":"OH",
    "wof:name":"Thomas Darren K DDS",
    "wof:placetype":"venue"
},
  "geometry": {"coordinates":[-81.9328,41.0266],"type":"Point"}
}