{
  "type": "Feature",
  "properties": {
    "addr:full": "1283 E 17th St Cleveland OH 44114",
    "addr:housenumber": "1283",
    "addr:postcode": "44114",
    "addr:street": "E 17Th St",
    "iso:country": "US",
    "sg:address": "1283 E 17th St",
    "sg:city": "Cleveland",
    "sg:classifiers": [
      {
        "category": "Food \u0026 Beverages",
        "subcategory": "Groceries \u0026 Convenience Stores",
        "type": "Retail Goods"
      }
    ],
    "sg:phone": "+1 216 771 4905",
    "sg:postcode": "44114",
    "sg:province": "OH",
    "wof:name": "Grossman's In \u0026 Out Foods",
    "wof:placetype": "venue"
  },
  "geometry": {"coordinates":[-81.683584,41.508276],"type":"Point"}
}
