{
  "type": "Feature",
  "properties": {
    "addr:full": "8580 Gallia Pike Franklin Furnace OH 45629",
    "addr:postcode": "8580;45629",
    "addr:street": "Gallia Pike",
    "iso:country": "US",
    "sg:address": "8580 Gallia Pike",
    "sg:city": "Franklin Furnace",
    "sg:classifiers": [
      {
        "category": "Real Estate",
        "subcategory": "Developer",
        "type": "Services"
      }
    ],
    "sg:phone": "+1 740 574 2076",
    "sg:postcode": "45629",
    "sg:province": "OH",
    "sg:tags": [
      "cemetery"
    ],
    "wof:name": "Sunset Memorial Gardens",
    "wof:placetype": "venue"
  },
  "geometry": {"coordinates":[-82.856175,38.676695],"type":"Point"}
}
