{
  "type": "Feature",
  "properties": {
    "addr:full": "1548 Sheridan Dr Lancaster OH 43130",
    "addr:housenumber": "1548",
    "addr:postcode": "43130",
    "addr:street": "Sheridan Dr",
    "iso:country": "US",
    "sg:address": "1548 Sheridan Dr",
    "sg:city": "Lancaster",
    "sg:classifiers": [
      {
        "category": "Health Services",
        "subcategory": "Medical Lab",
        "type": "Services"
      }
    ],
    "sg:phone": "+1 740 654 2365",
    "sg:postcode": "43130",
    "sg:province": "OH",
    "sg:tags": [
      "laboratory"
    ],
    "wof:name": "Quest Diagnostics",
    "wof:placetype": "venue"
  },
  "geometry": {"coordinates":[-82.569587,39.738646],"type":"Point"}
}
