{
  "type": "Feature",
  "properties": {
    "iso:country":"US",
    "sg:address":"962 Pinewood Ave",
    "sg:city":"Toledo",
    "sg:classifiers":[
        {
            "category":"Food & Beverages",
            "subcategory":"Groceries & Convenience Stores",
            "type":"Retail Goods"
        }
    ],
    "sg:phone":"+1 419 244 6230",
    "sg:postcode":"43607",
    "sg:province":"OH",
    "wof:name":"Hamer's Carry Out",
    "wof:placetype":"venue"
},
  "geometry": {"coordinates":[-83.566154,41.651215],"type":"Point"}
}