{
  "type": "Feature",
  "properties": {
    "addr:full": "962 Pinewood Ave Toledo OH 43607",
    "addr:housenumber": "962",
    "addr:postcode": "43607",
    "addr:street": "Pinewood Ave",
    "iso:country": "US",
    "sg:address": "962 Pinewood Ave",
    "sg:city": "Toledo",
    "sg:classifiers": [
      {
        "category": "Food \u0026 Beverages",
        "subcategory": "Groceries \u0026 Convenience Stores",
        "type": "Retail Goods"
      }
    ],
    "sg:phone": "+1 419 244 6230",
    "sg:postcode": "43607",
    "sg:province": "OH",
    "wof:name": "Hamer's Carry Out",
    "wof:placetype": "venue"
  },
  "geometry": {"coordinates":[-83.566154,41.651215],"type":"Point"}
}
