{
  "type": "Feature",
  "properties": {
    "iso:country":"US",
    "sg:address":"216 Wooster St",
    "sg:city":"Lodi",
    "sg:classifiers":[
        {
            "category":"Insurance",
            "subcategory":"Insurance Agent",
            "type":"Services"
        }
    ],
    "sg:phone":"+1 330 948 1160",
    "sg:postcode":"44254",
    "sg:province":"OH",
    "wof:name":"Woodmen Accident & Life Ins Co",
    "wof:placetype":"venue"
},
  "geometry": {"coordinates":[-82.011021,41.032748],"type":"Point"}
}