{
  "type": "Feature",
  "properties": {
    "addr:full": "216 Wooster St Lodi OH 44254",
    "addr:housenumber": "216",
    "addr:postcode": "44254",
    "addr:street": "Wooster St",
    "iso:country": "US",
    "sg:address": "216 Wooster St",
    "sg:city": "Lodi",
    "sg:classifiers": [
      {
        "category": "Insurance",
        "subcategory": "Insurance Agent",
        "type": "Services"
      }
    ],
    "sg:phone": "+1 330 948 1160",
    "sg:postcode": "44254",
    "sg:province": "OH",
    "wof:name": "Woodmen Accident \u0026 Life Ins Co",
    "wof:placetype": "venue"
  },
  "geometry": {"coordinates":[-82.011021,41.032748],"type":"Point"}
}
