{
  "type": "Feature",
  "properties": {
    "addr:full": "686 Hadcock Rd Brunswick OH 44212",
    "addr:housenumber": "686",
    "addr:postcode": "44212",
    "addr:street": "Hadcock Rd",
    "iso:country": "US",
    "sg:address": "686 Hadcock Rd",
    "sg:city": "Brunswick",
    "sg:classifiers": [
      {
        "category": "Building \u0026 Trades",
        "subcategory": "Construction",
        "type": "Services"
      }
    ],
    "sg:phone": "+1 330 220 6161",
    "sg:postcode": "44212",
    "sg:province": "OH",
    "sg:tags": [
      "concrete",
      "contractor"
    ],
    "wof:name": "D \u0026 D Cement Contractor",
    "wof:placetype": "venue"
  },
  "geometry": {"coordinates":[-81.82393,41.257046],"type":"Point"}
}
