{
  "type": "Feature",
  "properties": {
    "addr:full":"6969 Tyler Ct Mason OH 45040",
    "addr:housenumber":"6969",
    "addr:postcode":"45040",
    "addr:street":"Tyler Ct",
    "iso:country":"US",
    "sg:address":"6969 Tyler Ct",
    "sg:city":"Mason",
    "sg:classifiers":[
        {
            "category":"Retail",
            "subcategory":"Laundry & Dry Cleaning",
            "type":"Services"
        }
    ],
    "sg:phone":"+1 513 733 8686",
    "sg:postcode":"45040",
    "sg:province":"OH",
    "sg:tags":[
        "cleaners"
    ],
    "sg:website":"www.pressed4time.com",
    "wof:name":"Pressed 4 Time",
    "wof:placetype":"venue"
},
  "geometry": {"coordinates":[-84.346936,39.355318],"type":"Point"}
}