{
  "type": "Feature",
  "properties": {
    "addr:full":"107 Brelsford Ave Trenton OH 45067",
    "addr:housenumber":"107",
    "addr:postcode":"45067",
    "addr:street":"Brelsford Ave",
    "iso:country":"US",
    "sg:address":"107 Brelsford Ave",
    "sg:city":"Trenton",
    "sg:classifiers":[
        {
            "category":"Wholesale",
            "subcategory":"Vending Machines",
            "type":"Manufacturing & Wholesale Goods"
        }
    ],
    "sg:phone":"+1 513 988 9351",
    "sg:postcode":"45067",
    "sg:province":"OH",
    "sg:tags":[
        "operator"
    ],
    "wof:name":"Teresas Vending",
    "wof:placetype":"venue"
},
  "geometry": {"coordinates":[-84.465564,39.482174],"type":"Point"}
}