{
  "type": "Feature",
  "properties": {
    "addr:full":"20 E Alexis Rd Toledo OH 43612",
    "addr:housenumber":"20",
    "addr:postcode":"43612",
    "addr:street":"E Alexis Rd",
    "iso:country":"US",
    "sg:address":"20 E Alexis Rd",
    "sg:city":"Toledo",
    "sg:classifiers":[
        {
            "category":"Personal",
            "subcategory":"Beauty Salon",
            "type":"Services"
        }
    ],
    "sg:phone":"+1 419 269 1788",
    "sg:postcode":"43612",
    "sg:province":"OH",
    "wof:name":"Queen Nails",
    "wof:placetype":"venue"
},
  "geometry": {"coordinates":[-83.542025,41.72222],"type":"Point"}
}