{
  "type": "Feature",
  "properties": {
    "iso:country":"US",
    "sg:address":"4207 Harvard Ave",
    "sg:city":"Cleveland",
    "sg:classifiers":[
        {
            "category":"Organizations",
            "subcategory":"Labor Organization",
            "type":"Services"
        }
    ],
    "sg:phone":"+1 216 883 7382",
    "sg:postcode":"44105",
    "sg:province":"OH",
    "wof:name":"United Auto Workers Of America",
    "wof:placetype":"venue"
},
  "geometry": {"coordinates":[-81.661546,41.447145],"type":"Point"}
}