{
  "type": "Feature",
  "properties": {
    "addr:full": "3640 Herbert Ave Cincinnati OH 45211",
    "addr:housenumber": "3640",
    "addr:postcode": "45211",
    "addr:street": "Herbert Ave",
    "iso:country": "US",
    "sg:address": "3640 Herbert Ave",
    "sg:city": "Cincinnati",
    "sg:classifiers": [
      {
        "category": "Building \u0026 Trades",
        "subcategory": "Electrical",
        "type": "Services"
      }
    ],
    "sg:phone": "+1 513 481 0091",
    "sg:postcode": "45211",
    "sg:province": "OH",
    "sg:tags": [
      "electric",
      "contractor"
    ],
    "wof:name": "KOTZ Electrical \u0026 Mechanical",
    "wof:placetype": "venue"
  },
  "geometry": {"coordinates":[-84.609635,39.151271],"type":"Point"}
}
