{
  "type": "Feature",
  "properties": {
    "iso:country":"US",
    "sg:address":"154 Chester St",
    "sg:city":"Painesville",
    "sg:classifiers":[
        {
            "category":"Professional",
            "type":"Services"
        }
    ],
    "sg:phone":"+1 440 639 8651",
    "sg:postcode":"44077",
    "sg:province":"OH",
    "wof:name":"J Natividad Soto Rodriguez",
    "wof:placetype":"venue"
},
  "geometry": {"coordinates":[-81.25323,41.729676],"type":"Point"}
}