{
  "type": "Feature",
  "properties": {
    "addr:full": "3615 Fulton Dr NW Canton OH 44718",
    "addr:housenumber": "3615",
    "addr:postcode": "44718",
    "addr:street": "Fulton Dr Nw",
    "iso:country": "US",
    "sg:address": "3615 Fulton Dr NW",
    "sg:city": "Canton",
    "sg:classifiers": [
      {
        "category": "Professional",
        "subcategory": "Business Services",
        "type": "Services"
      }
    ],
    "sg:phone": "+1 330 493 9066",
    "sg:postcode": "44718",
    "sg:province": "OH",
    "sg:tags": [
      "embroidery"
    ],
    "wof:name": "Country Sisters Custom Embrdry",
    "wof:placetype": "venue"
  },
  "geometry": {"coordinates":[-81.412637,40.830583],"type":"Point"}
}
