{
  "type": "Feature",
  "properties": {
    "addr:full": "370 Co Rd 5 Mc Clure OH 43534",
    "addr:housenumber": "370",
    "addr:postcode": "43534",
    "addr:street": "Co Rd 5 Mc Clure",
    "iso:country": "US",
    "sg:address": "370 Co Rd 5",
    "sg:city": "Mc Clure",
    "sg:phone": "+1 419 278 1880",
    "sg:postcode": "43534",
    "sg:province": "OH",
    "sg:tags": [
      "farm",
      "corn",
      "wheat",
      "soybean"
    ],
    "wof:name": "Rettig Farms",
    "wof:placetype": "venue"
  },
  "geometry": {"coordinates":[-83.960712,41.364667],"type":"Point"}
}
