{
  "type": "Feature",
  "properties": {
    "addr:full": "5198 River Rd Cincinnati OH 45233",
    "addr:housenumber": "5198",
    "addr:postcode": "45233",
    "addr:street": "River Rd",
    "iso:country": "US",
    "sg:address": "5198 River Rd",
    "sg:city": "Cincinnati",
    "sg:classifiers": [
      {
        "category": "Shopping",
        "subcategory": "Gifts \u0026 Souvenirs",
        "type": "Retail Goods"
      },
      {
        "category": "Wholesale",
        "subcategory": "Drugs",
        "type": "Manufacturing \u0026 Wholesale Goods"
      },
      {
        "category": "Professional",
        "subcategory": "Printing \u0026 Photocopies",
        "type": "Services"
      }
    ],
    "sg:phone": "+1 513 941 7673",
    "sg:postcode": "45233",
    "sg:province": "OH",
    "sg:tags": [
      "shop",
      "decal"
    ],
    "wof:name": "Prographics Systems",
    "wof:placetype": "venue"
  },
  "geometry": {"coordinates":[-84.646088,39.091061],"type":"Point"}
}
