{
  "type": "Feature",
  "properties": {
    "addr:full":"2033 Randy Scott Dr Dayton OH 45449",
    "addr:housenumber":"2033",
    "addr:postcode":"45449",
    "addr:street":"Randy Scott Dr",
    "iso:country":"US",
    "sg:address":"2033 Randy Scott Dr",
    "sg:city":"Dayton",
    "sg:classifiers":[
        {
            "category":"Real Estate",
            "subcategory":"Real Estate Operator",
            "type":"Services"
        }
    ],
    "sg:phone":"+1 937 859 1866",
    "sg:postcode":"45449",
    "sg:province":"OH",
    "sg:tags":[
        "apartment"
    ],
    "wof:name":"Centerzille Park Apartments",
    "wof:placetype":"venue"
},
  "geometry": {"coordinates":[-84.235167,39.645137],"type":"Point"}
}