{
  "type": "Feature",
  "properties": {
    "addr:full":"7521 State Rd Cincinnati OH 45255",
    "addr:housenumber":"7521",
    "addr:postcode":"45255",
    "addr:street":"State Rd",
    "iso:country":"US",
    "sg:address":"7521 State Rd",
    "sg:city":"Cincinnati",
    "sg:classifiers":[
        {
            "category":"Health Services",
            "subcategory":"Doctor",
            "type":"Services"
        }
    ],
    "sg:phone":"+1 513 232 6560",
    "sg:postcode":"45255",
    "sg:province":"OH",
    "sg:tags":[
        "dentist"
    ],
    "wof:name":"Peter Schwenkmeyer Inc",
    "wof:placetype":"venue"
},
  "geometry": {"coordinates":[-84.347888,39.084212],"type":"Point"}
}