{
  "type": "Feature",
  "properties": {
    "addr:full": "2024 State Rte 39 NW Dover OH 44622",
    "addr:housenumber": "2024",
    "addr:postcode": "44622",
    "addr:street": "State Rte 39 Nw",
    "iso:country": "US",
    "sg:address": "2024 State Rte 39 NW",
    "sg:city": "Dover",
    "sg:classifiers": [
      {
        "category": "Travel",
        "subcategory": "Hotels \u0026 Motels",
        "type": "Entertainment"
      }
    ],
    "sg:phone": "+1 330 364 8881",
    "sg:postcode": "44622",
    "sg:province": "OH",
    "sg:tags": [
      "station",
      "gas",
      "stand",
      "ice",
      "cream"
    ],
    "sg:website": "www.choicehotels.com",
    "wof:name": "Comfort Inn",
    "wof:placetype": "venue"
  },
  "geometry": {"coordinates":[-81.495005,40.52775],"type":"Point"}
}
