{
  "type": "Feature",
  "properties": {
    "addr:full":"10439 Springwater Dr Mount Vernon OH 43050",
    "addr:housenumber":"10439",
    "addr:postcode":"43050",
    "addr:street":"Springwater Dr",
    "iso:country":"US",
    "sg:address":"10439 Springwater Dr",
    "sg:city":"Mount Vernon",
    "sg:classifiers":[
        {
            "category":"Professional",
            "type":"Services"
        }
    ],
    "sg:phone":"+1 740 392 3160",
    "sg:postcode":"43050",
    "sg:province":"OH",
    "wof:name":"Gail F Reninger Famil",
    "wof:placetype":"venue"
},
  "geometry": {"coordinates":[-82.54266699999999,40.389704],"type":"Point"}
}