{
  "type": "Feature",
  "properties": {
    "iso:country":"US",
    "sg:address":"9191 Postal Dr",
    "sg:city":"Cleveland",
    "sg:classifiers":[
        {
            "category":"Building & Trades",
            "subcategory":"Construction",
            "type":"Services"
        }
    ],
    "sg:phone":"+1 440 740 0145",
    "sg:postcode":"44147",
    "sg:province":"OH",
    "sg:tags":[
        "general",
        "contractor"
    ],
    "wof:name":"Norton Construction Co",
    "wof:placetype":"venue"
},
  "geometry": {"coordinates":[-81.670742,41.31401],"type":"Point"}
}