{
  "type": "Feature",
  "properties": {
    "addr:full": "9191 Postal Dr Cleveland OH 44147",
    "addr:housenumber": "9191",
    "addr:postcode": "44147",
    "addr:street": "Postal Dr",
    "iso:country": "US",
    "sg:address": "9191 Postal Dr",
    "sg:city": "Cleveland",
    "sg:classifiers": [
      {
        "category": "Building \u0026 Trades",
        "subcategory": "Construction",
        "type": "Services"
      }
    ],
    "sg:phone": "+1 440 740 0145",
    "sg:postcode": "44147",
    "sg:province": "OH",
    "sg:tags": [
      "general",
      "contractor"
    ],
    "wof:name": "Norton Construction Co",
    "wof:placetype": "venue"
  },
  "geometry": {"coordinates":[-81.670742,41.31401],"type":"Point"}
}
