{
  "type": "Feature",
  "properties": {
    "iso:country":"US",
    "sg:address":"101 E 6th St",
    "sg:city":"East Liverpool",
    "sg:classifiers":[
        {
            "category":"Shopping",
            "subcategory":"Tobacco",
            "type":"Retail Goods"
        }
    ],
    "sg:phone":"+1 330 385 6330",
    "sg:postcode":"43920",
    "sg:province":"OH",
    "sg:tags":[
        "cigarette",
        "product",
        "cigar",
        "dealer"
    ],
    "wof:name":"Curtis Cigar",
    "wof:placetype":"venue"
},
  "geometry": {"coordinates":[-80.577909,40.619573],"type":"Point"}
}