{
  "type": "Feature",
  "properties": {
    "addr:full":"1739 Niles Rd SE Warren OH 44484",
    "addr:housenumber":"1739",
    "addr:postcode":"44484",
    "addr:street":"Niles Rd Se",
    "iso:country":"US",
    "sg:address":"1739 Niles Rd SE",
    "sg:city":"Warren",
    "sg:classifiers":[
        {
            "category":"Autos & Motor Vehicles",
            "subcategory":"Automobile Sales",
            "type":"Retail Goods"
        }
    ],
    "sg:phone":"+1 330 369 8184",
    "sg:postcode":"44484",
    "sg:province":"OH",
    "sg:tags":[
        "car",
        "dealer"
    ],
    "wof:name":"D & J Auto",
    "wof:placetype":"venue"
},
  "geometry": {"coordinates":[-80.798175,41.223208],"type":"Point"}
}