{
  "type": "Feature",
  "properties": {
    "iso:country":"US",
    "sg:address":"6735 W Meadows Ln",
    "sg:city":"Maumee",
    "sg:classifiers":[
        {
            "category":"Professional",
            "type":"Services"
        }
    ],
    "sg:phone":"+1 419 866 0270",
    "sg:postcode":"43537",
    "sg:province":"OH",
    "wof:name":"Toledo Feadrations Teachers",
    "wof:placetype":"venue"
},
  "geometry": {"coordinates":[-83.70236,41.57878],"type":"Point"}
}