{
  "type": "Feature",
  "properties": {
    "iso:country":"US",
    "sg:address":"3 W Main St",
    "sg:city":"Alexandria",
    "sg:classifiers":[
        {
            "category":"Restaurant",
            "type":"Food & Drink"
        }
    ],
    "sg:phone":"+1 740 924 2222",
    "sg:postcode":"43001",
    "sg:province":"OH",
    "sg:tags":[
        "pizza"
    ],
    "wof:name":"Main Street Pizza",
    "wof:placetype":"venue"
},
  "geometry": {"coordinates":[-82.613123,40.08927],"type":"Point"}
}