{
  "type": "Feature",
  "properties": {
    "addr:full":"840 Ohio St Delphos OH 45833",
    "addr:housenumber":"840",
    "addr:postcode":"45833",
    "addr:street":"Ohio St",
    "iso:country":"US",
    "sg:address":"840 Ohio St",
    "sg:city":"Delphos",
    "sg:classifiers":[
        {
            "category":"Retail",
            "subcategory":"Veterinary Services",
            "type":"Services"
        }
    ],
    "sg:phone":"+1 419 692 5946",
    "sg:postcode":"45833",
    "sg:province":"OH",
    "sg:tags":[
        "veterinarian"
    ],
    "wof:name":"Kessen Veterinary Clinic",
    "wof:placetype":"venue"
},
  "geometry": {"coordinates":[-84.350611,40.841657],"type":"Point"}
}