{
  "type": "Feature",
  "properties": {
    "iso:country":"US",
    "sg:address":"2305 Manchester Rd",
    "sg:city":"Akron",
    "sg:classifiers":[
        {
            "category":"Insurance",
            "subcategory":"Insurance Agent",
            "type":"Services"
        }
    ],
    "sg:phone":"+1 330 753 1006",
    "sg:postcode":"44314",
    "sg:province":"OH",
    "sg:tags":[
        "plan"
    ],
    "wof:name":"Nine Insurance Agency Inc",
    "wof:placetype":"venue"
},
  "geometry": {"coordinates":[-81.54558299999999,41.036517],"type":"Point"}
}