{
  "type": "Feature",
  "properties": {
    "iso:country":"US",
    "sg:address":"10221 Colerain Ave",
    "sg:city":"Cincinnati",
    "sg:classifiers":[
        {
            "category":"Retail",
            "subcategory":"Repair Shop",
            "type":"Services"
        },
        {
            "category":"Building & Trades",
            "subcategory":"Equipment Rental",
            "type":"Services"
        }
    ],
    "sg:phone":"+1 800 508 4761",
    "sg:postcode":"45251",
    "sg:province":"OH",
    "sg:tags":[
        "yard",
        "supply",
        "contractor",
        "tools-renting",
        "store",
        "contractors'"
    ],
    "sg:website":"http://www-sunbeltrentals-com.netsolads.com/?utm_source=yp.com&utm_medium=tilead&utm_term=localsearch&utm_campaign=&_nsag=39093",
    "wof:name":"Sunbelt Rentals At Lowe's",
    "wof:placetype":"venue"
},
  "geometry": {"coordinates":[-84.60255100000001,39.259712],"type":"Point"}
}