{
  "type": "Feature",
  "properties": {
    "addr:full": "10221 Colerain Ave Cincinnati OH 45251",
    "addr:housenumber": "10221",
    "addr:postcode": "45251",
    "addr:street": "Colerain Ave",
    "iso:country": "US",
    "sg:address": "10221 Colerain Ave",
    "sg:city": "Cincinnati",
    "sg:classifiers": [
      {
        "category": "Retail",
        "subcategory": "Repair Shop",
        "type": "Services"
      },
      {
        "category": "Building \u0026 Trades",
        "subcategory": "Equipment Rental",
        "type": "Services"
      }
    ],
    "sg:phone": "+1 800 508 4761",
    "sg:postcode": "45251",
    "sg:province": "OH",
    "sg:tags": [
      "yard",
      "supply",
      "contractor",
      "tools-renting",
      "store",
      "contractors'"
    ],
    "sg:website": "http://www-sunbeltrentals-com.netsolads.com/?utm_source=yp.com\u0026utm_medium=tilead\u0026utm_term=localsearch\u0026utm_campaign=\u0026_nsag=39093",
    "wof:name": "Sunbelt Rentals At Lowe's",
    "wof:placetype": "venue"
  },
  "geometry": {"coordinates":[-84.602551,39.259712],"type":"Point"}
}
