{
  "type": "Feature",
  "properties": {
    "addr:full":"4501 W Mitchell Ave Cincinnati OH 45232",
    "addr:housenumber":"4501",
    "addr:postcode":"45232",
    "addr:street":"W Mitchell Ave",
    "iso:country":"US",
    "sg:address":"4501 W Mitchell Ave",
    "sg:city":"Cincinnati",
    "sg:classifiers":[
        {
            "category":"Manufacturing",
            "subcategory":"Food",
            "type":"Manufacturing & Wholesale Goods"
        }
    ],
    "sg:phone":"+1 513 681 8555",
    "sg:postcode":"45232",
    "sg:province":"OH",
    "sg:tags":[
        "extract",
        "syrup",
        "flavoring"
    ],
    "wof:name":"Slush Puppie Distribution",
    "wof:placetype":"venue"
},
  "geometry": {"coordinates":[-84.51439999999999,39.170808],"type":"Point"}
}