{
  "type": "Feature",
  "properties": {
    "addr:full":"216 E Monteray Ave Dayton OH 45419",
    "addr:housenumber":"216",
    "addr:postcode":"45419",
    "addr:street":"E Monteray Ave",
    "iso:country":"US",
    "sg:address":"216 E Monteray Ave",
    "sg:city":"Dayton",
    "sg:classifiers":[
        {
            "category":"Real Estate",
            "subcategory":"Architect",
            "type":"Services"
        }
    ],
    "sg:phone":"+1 937 299 6588",
    "sg:postcode":"45419",
    "sg:province":"OH",
    "wof:name":"Mitolo Studio Inc",
    "wof:placetype":"venue"
},
  "geometry": {"coordinates":[-84.166887,39.711213],"type":"Point"}
}