{
  "type": "Feature",
  "properties": {
    "iso:country":"US",
    "sg:address":"889 S Miami St",
    "sg:city":"West Milton",
    "sg:classifiers":[
        {
            "category":"Government",
            "subcategory":"Office",
            "type":"Public Place"
        }
    ],
    "sg:phone":"+1 937 698 4884",
    "sg:postcode":"45383",
    "sg:province":"OH",
    "sg:tags":[
        "village"
    ],
    "wof:name":"West Milton Waste Water Plant",
    "wof:placetype":"venue"
},
  "geometry": {"coordinates":[-84.323471,39.950591],"type":"Point"}
}