{
  "type": "Feature",
  "properties": {
    "addr:full": "2715 Copley Rd Akron OH 44321",
    "addr:housenumber": "2715",
    "addr:postcode": "44321",
    "addr:street": "Copley Rd",
    "iso:country": "US",
    "sg:address": "2715 Copley Rd",
    "sg:city": "Akron",
    "sg:classifiers": [
      {
        "category": "Sports \u0026 Exercise",
        "subcategory": "Golf",
        "type": "Entertainment"
      }
    ],
    "sg:phone": "+1 330 665 4111",
    "sg:postcode": "44321",
    "sg:province": "OH",
    "sg:tags": [
      "course",
      "public"
    ],
    "wof:name": "Oshux Golf Inc",
    "wof:placetype": "venue"
  },
  "geometry": {"coordinates":[-81.617132,41.092279],"type":"Point"}
}
