{
  "type": "Feature",
  "properties": {
    "addr:full": "17 Creston Ave Dayton OH 45404",
    "addr:housenumber": "17",
    "addr:postcode": "45404",
    "addr:street": "Creston Ave",
    "iso:country": "US",
    "sg:address": "17 Creston Ave",
    "sg:city": "Dayton",
    "sg:classifiers": [
      {
        "category": "Building \u0026 Trades",
        "subcategory": "Plumbing",
        "type": "Services"
      }
    ],
    "sg:phone": "+1 937 228 6492",
    "sg:postcode": "45404",
    "sg:province": "OH",
    "sg:tags": [
      "conditioning",
      "air",
      "system",
      "contractor"
    ],
    "sg:website": "www.envengsys.com",
    "wof:name": "Environmental Engineering",
    "wof:placetype": "venue"
  },
  "geometry": {"coordinates":[-84.176378,39.771016],"type":"Point"}
}
