{
  "type": "Feature",
  "properties": {
    "addr:full":"2600 Deweese Pkwy Dayton OH 45414",
    "addr:postcode":"2600;45414",
    "addr:street":"Deweese Pkwy",
    "iso:country":"US",
    "sg:address":"2600 Deweese Pkwy",
    "sg:city":"Dayton",
    "sg:classifiers":[
        {
            "category":"Museum",
            "type":"Entertainment"
        }
    ],
    "sg:phone":"+1 937 275 9156",
    "sg:postcode":"45414",
    "sg:province":"OH",
    "sg:tags":[
        "gallery"
    ],
    "wof:name":"Dayton Society Natural History",
    "wof:placetype":"venue"
},
  "geometry": {"coordinates":[-84.20272300000001,39.785898],"type":"Point"}
}