{
  "type": "Feature",
  "properties": {
    "iso:country":"US",
    "sg:address":"926 E Tallmadge Ave",
    "sg:city":"Akron",
    "sg:classifiers":[
        {
            "category":"Wholesale",
            "subcategory":"Office Equipment",
            "type":"Manufacturing & Wholesale Goods"
        }
    ],
    "sg:phone":"+1 330 633 1663",
    "sg:postcode":"44310",
    "sg:province":"OH",
    "sg:tags":[
        "machine",
        "duplicating",
        "copying"
    ],
    "wof:name":"Rhs Office Systems",
    "wof:placetype":"venue"
},
  "geometry": {"coordinates":[-81.481582,41.102079],"type":"Point"}
}