{
  "type": "Feature",
  "properties": {
    "addr:full":"3719 Edgewater Dr Vermilion OH 44089",
    "addr:housenumber":"3719",
    "addr:postcode":"44089",
    "addr:street":"Edgewater Dr",
    "iso:country":"US",
    "sg:address":"3719 Edgewater Dr",
    "sg:city":"Vermilion",
    "sg:classifiers":[
        {
            "category":"Professional",
            "type":"Services"
        }
    ],
    "sg:phone":"+1 440 949 6325",
    "sg:postcode":"44089",
    "sg:province":"OH",
    "wof:name":"Ernest Philippi",
    "wof:placetype":"venue"
},
  "geometry": {"coordinates":[-82.33822600000001,41.429286],"type":"Point"}
}