{
  "type": "Feature",
  "properties": {
    "iso:country":"US",
    "sg:address":"3719 Edgewater Dr",
    "sg:city":"Vermilion",
    "sg:classifiers":[
        {
            "category":"Professional",
            "type":"Services"
        }
    ],
    "sg:phone":"+1 440 949 6325",
    "sg:postcode":"44089",
    "sg:province":"OH",
    "wof:name":"Ernest Philippi",
    "wof:placetype":"venue"
},
  "geometry": {"coordinates":[-82.338226,41.429286],"type":"Point"}
}