{
  "type": "Feature",
  "properties": {
    "addr:full":"105 E Taylor St Mt Victory OH 43340",
    "addr:housenumber":"105",
    "addr:postcode":"43340",
    "addr:street":"E Taylor St",
    "iso:country":"US",
    "sg:address":"105 E Taylor St",
    "sg:city":"Mt Victory",
    "sg:classifiers":[
        {
            "category":"Shopping",
            "subcategory":"Used Merchandise",
            "type":"Retail Goods"
        }
    ],
    "sg:phone":"+1 937 354 9048",
    "sg:postcode":"43340",
    "sg:province":"OH",
    "sg:tags":[
        "antique"
    ],
    "wof:name":"Vintage Sandy's Antq",
    "wof:placetype":"venue"
},
  "geometry": {"coordinates":[-83.51989500000001,40.534737],"type":"Point"}
}