{
  "type": "Feature",
  "properties": {
    "addr:full": "1713 Byron Dr Cleveland OH 44124",
    "addr:housenumber": "1713",
    "addr:postcode": "44124",
    "addr:street": "Byron Dr",
    "iso:country": "US",
    "sg:address": "1713 Byron Dr",
    "sg:city": "Cleveland",
    "sg:classifiers": [
      {
        "category": "Shopping",
        "subcategory": "Florist",
        "type": "Retail Goods"
      }
    ],
    "sg:phone": "+1 440 461 3535",
    "sg:postcode": "44124",
    "sg:province": "OH",
    "wof:name": "Flowers By Bucci",
    "wof:placetype": "venue"
  },
  "geometry": {"coordinates":[-81.467497,41.51394],"type":"Point"}
}
