{
  "type": "Feature",
  "properties": {
    "addr:full":"23361 Aurora Rd Bedford OH 44146",
    "addr:housenumber":"23361",
    "addr:postcode":"44146",
    "addr:street":"Aurora Rd",
    "iso:country":"US",
    "sg:address":"23361 Aurora Rd",
    "sg:city":"Bedford",
    "sg:classifiers":[
        {
            "category":"Retail",
            "subcategory":"Driving School",
            "type":"Services"
        },
        {
            "category":"Autos & Motor Vehicles",
            "subcategory":"Motorcycle Sales",
            "type":"Retail Goods"
        }
    ],
    "sg:phone":"+1 440 786 2230",
    "sg:postcode":"44146",
    "sg:province":"OH",
    "sg:tags":[
        "instruction"
    ],
    "sg:website":"http://www.southeastgolfcar.com",
    "wof:name":"South East Polaris",
    "wof:placetype":"venue"
},
  "geometry": {"coordinates":[-81.514381,41.416969],"type":"Point"}
}