{
  "type": "Feature",
  "properties": {
    "addr:full":"34305 Solon Rd Cleveland OH 44139",
    "addr:postcode":"34305;44139",
    "addr:street":"Solon Rd",
    "iso:country":"US",
    "sg:address":"34305 Solon Rd",
    "sg:city":"Cleveland",
    "sg:classifiers":[
        {
            "category":"Health Services",
            "subcategory":"Health Practitioner",
            "type":"Services"
        }
    ],
    "sg:phone":"+1 440 349 3038",
    "sg:postcode":"44139",
    "sg:province":"OH",
    "sg:tags":[
        "psychologist"
    ],
    "wof:name":"Linda K Mc Graw & Assoc",
    "wof:placetype":"venue"
},
  "geometry": {"coordinates":[-81.436367,41.392469],"type":"Point"}
}