{
  "type": "Feature",
  "properties": {
    "addr:full": "5505 Pine Bluff Rd Columbus OH 43229",
    "addr:housenumber": "5505",
    "addr:postcode": "43229",
    "addr:street": "Pine Bluff Rd",
    "iso:country": "US",
    "sg:address": "5505 Pine Bluff Rd",
    "sg:city": "Columbus",
    "sg:classifiers": [
      {
        "category": "Building \u0026 Trades",
        "subcategory": "Landscaping Services",
        "type": "Services"
      }
    ],
    "sg:phone": "+1 614 846 9350",
    "sg:postcode": "43229",
    "sg:province": "OH",
    "sg:tags": [
      "design",
      "landscape",
      "maintenance"
    ],
    "wof:name": "Lodder Landscape",
    "wof:placetype": "venue"
  },
  "geometry": {"coordinates":[-82.972335,40.077715],"type":"Point"}
}
