{
  "type": "Feature",
  "properties": {
    "addr:full": "366 Crestway Oval Brunswick OH 44212",
    "addr:housenumber": "366",
    "addr:postcode": "44212",
    "addr:street": "Crestway Oval",
    "iso:country": "US",
    "sg:address": "366 Crestway Oval",
    "sg:city": "Brunswick",
    "sg:classifiers": [
      {
        "category": "Food \u0026 Beverages",
        "subcategory": "Groceries \u0026 Convenience Stores",
        "type": "Retail Goods"
      }
    ],
    "sg:phone": "+1 216 926 7370",
    "sg:postcode": "44212",
    "sg:province": "OH",
    "sg:tags": [
      "product"
    ],
    "wof:name": "Brunswick Food Svc LTD",
    "wof:placetype": "venue"
  },
  "geometry": {"coordinates":[-81.823741,41.267462],"type":"Point"}
}
