{
  "type": "Feature",
  "properties": {
    "iso:country":"US",
    "sg:address":"366 Crestway Oval",
    "sg:city":"Brunswick",
    "sg:classifiers":[
        {
            "category":"Food & Beverages",
            "subcategory":"Groceries & Convenience Stores",
            "type":"Retail Goods"
        }
    ],
    "sg:phone":"+1 216 926 7370",
    "sg:postcode":"44212",
    "sg:province":"OH",
    "sg:tags":[
        "product"
    ],
    "wof:name":"Brunswick Food Svc LTD",
    "wof:placetype":"venue"
},
  "geometry": {"coordinates":[-81.823741,41.267462],"type":"Point"}
}