{
  "type": "Feature",
  "properties": {
    "addr:full": "4141 N High St Columbus OH 43214",
    "addr:housenumber": "4141",
    "addr:postcode": "43214",
    "addr:street": "N High St",
    "iso:country": "US",
    "sg:address": "4141 N High St",
    "sg:city": "Columbus",
    "sg:classifiers": [
      {
        "category": "Personal",
        "subcategory": "Beauty Salon",
        "type": "Services"
      }
    ],
    "sg:phone": "+1 614 263 2916",
    "sg:postcode": "43214",
    "sg:province": "OH",
    "wof:name": "Clintonville Beauty Salon",
    "wof:placetype": "venue"
  },
  "geometry": {"coordinates":[-83.019984,40.046598],"type":"Point"}
}
