{
  "type": "Feature",
  "properties": {
    "iso:country":"US",
    "sg:address":"4141 N High St",
    "sg:city":"Columbus",
    "sg:classifiers":[
        {
            "category":"Personal",
            "subcategory":"Beauty Salon",
            "type":"Services"
        }
    ],
    "sg:phone":"+1 614 263 2916",
    "sg:postcode":"43214",
    "sg:province":"OH",
    "wof:name":"Clintonville Beauty Salon",
    "wof:placetype":"venue"
},
  "geometry": {"coordinates":[-83.01998399999999,40.046598],"type":"Point"}
}