{
  "type": "Feature",
  "properties": {
    "addr:full": "4540 Selma Pike Springfield OH 45502",
    "addr:housenumber": "4540",
    "addr:postcode": "45502",
    "addr:street": "Selma Pike",
    "iso:country": "US",
    "sg:address": "4540 Selma Pike",
    "sg:city": "Springfield",
    "sg:classifiers": [
      {
        "category": "Home \u0026 Garden",
        "subcategory": "Building Materials",
        "type": "Retail Goods"
      }
    ],
    "sg:phone": "+1 937 265 5527",
    "sg:postcode": "45502",
    "sg:province": "OH",
    "sg:website": "www.stainedglassbarn.com",
    "wof:name": "Stained Glass Barn",
    "wof:placetype": "venue"
  },
  "geometry": {"coordinates":[-83.770137,39.852235],"type":"Point"}
}
