{
  "type": "Feature",
  "properties": {
    "iso:country":"US",
    "sg:address":"4540 Selma Pike",
    "sg:city":"Springfield",
    "sg:classifiers":[
        {
            "category":"Home & Garden",
            "subcategory":"Building Materials",
            "type":"Retail Goods"
        }
    ],
    "sg:phone":"+1 937 265 5527",
    "sg:postcode":"45502",
    "sg:province":"OH",
    "sg:website":"www.stainedglassbarn.com",
    "wof:name":"Stained Glass Barn",
    "wof:placetype":"venue"
},
  "geometry": {"coordinates":[-83.77013700000001,39.852235],"type":"Point"}
}