{
  "type": "Feature",
  "properties": {
    "addr:full": "601 N Greenwood St Marion OH 43302",
    "addr:housenumber": "601",
    "addr:postcode": "43302",
    "addr:street": "N Greenwood St",
    "iso:country": "US",
    "sg:address": "601 N Greenwood St",
    "sg:city": "Marion",
    "sg:classifiers": [
      {
        "category": "Building \u0026 Trades",
        "subcategory": "Construction",
        "type": "Services"
      }
    ],
    "sg:phone": "+1 740 382 3012",
    "sg:postcode": "43302",
    "sg:province": "OH",
    "sg:tags": [
      "excavation",
      "grading",
      "driveway",
      "contractor"
    ],
    "wof:name": "Riemar \u0026 Klingel",
    "wof:placetype": "venue"
  },
  "geometry": {"coordinates":[-83.121018,40.599684],"type":"Point"}
}
