{
  "type": "Feature",
  "properties": {
    "iso:country":"US",
    "sg:address":"601 N Greenwood St",
    "sg:city":"Marion",
    "sg:classifiers":[
        {
            "category":"Building & Trades",
            "subcategory":"Construction",
            "type":"Services"
        }
    ],
    "sg:phone":"+1 740 382 3012",
    "sg:postcode":"43302",
    "sg:province":"OH",
    "sg:tags":[
        "excavation",
        "grading",
        "driveway",
        "contractor"
    ],
    "wof:name":"Riemar & Klingel",
    "wof:placetype":"venue"
},
  "geometry": {"coordinates":[-83.12101800000001,40.599684],"type":"Point"}
}