{
  "type": "Feature",
  "properties": {
    "addr:full": "8454 Blue Ash Rd Cincinnati OH 45236",
    "addr:housenumber": "8454",
    "addr:postcode": "45236",
    "addr:street": "Blue Ash Rd",
    "iso:country": "US",
    "sg:address": "8454 Blue Ash Rd",
    "sg:city": "Cincinnati",
    "sg:classifiers": [
      {
        "category": "Building \u0026 Trades",
        "subcategory": "Construction",
        "type": "Services"
      }
    ],
    "sg:phone": "+1 513 794 1501",
    "sg:postcode": "45236",
    "sg:province": "OH",
    "sg:tags": [
      "residential",
      "contractor"
    ],
    "sg:website": "www.universalconceptsonline.com",
    "wof:name": "Universal Concepts \u0026 Design",
    "wof:placetype": "venue"
  },
  "geometry": {"coordinates":[-84.387997,39.213557],"type":"Point"}
}
