{
  "type": "Feature",
  "properties": {
    "addr:full": "407 E Main St New Lebanon OH 45345",
    "addr:housenumber": "407",
    "addr:postcode": "45345",
    "addr:street": "E Main St",
    "iso:country": "US",
    "sg:address": "407 E Main St",
    "sg:city": "New Lebanon",
    "sg:classifiers": [
      {
        "category": "Personal",
        "subcategory": "Beauty Salon",
        "type": "Services"
      }
    ],
    "sg:phone": "+1 937 687 4262",
    "sg:postcode": "45345",
    "sg:province": "OH",
    "sg:tags": [
      "manicuring"
    ],
    "wof:name": "Queen Nails",
    "wof:placetype": "venue"
  },
  "geometry": {"coordinates":[-84.377153,39.74578],"type":"Point"}
}
