{
  "type": "Feature",
  "properties": {
    "iso:country":"US",
    "sg:address":"68 S 4th St",
    "sg:city":"Columbus",
    "sg:classifiers":[
        {
            "category":"Real Estate",
            "subcategory":"Real Estate Agent",
            "type":"Services"
        }
    ],
    "sg:phone":"+1 614 221 6048",
    "sg:postcode":"43215",
    "sg:province":"OH",
    "sg:tags":[
        "operator",
        "management",
        "apartment"
    ],
    "wof:name":"Oxford Realty",
    "wof:placetype":"venue"
},
  "geometry": {"coordinates":[-82.995806,39.960868],"type":"Point"}
}