{
  "type": "Feature",
  "properties": {
    "iso:country":"US",
    "sg:address":"1593 Woodcrest Dr",
    "sg:city":"Wooster",
    "sg:classifiers":[
        {
            "category":"Manufacturing",
            "subcategory":"Tools & Machinery",
            "type":"Manufacturing & Wholesale Goods"
        }
    ],
    "sg:phone":"+1 330 264 9662",
    "sg:postcode":"44691",
    "sg:province":"OH",
    "sg:tags":[
        "machine",
        "vending",
        "mfg"
    ],
    "wof:name":"Jlmn Co",
    "wof:placetype":"venue"
},
  "geometry": {"coordinates":[-81.91821,40.818746],"type":"Point"}
}