{
  "type": "Feature",
  "properties": {
    "addr:full": "105 W Spring St St Marys OH 45885",
    "addr:housenumber": "105",
    "addr:postcode": "45885",
    "addr:street": "W Spring St",
    "iso:country": "US",
    "sg:address": "105 W Spring St",
    "sg:city": "St Marys",
    "sg:classifiers": [
      {
        "category": "Shopping",
        "type": "Retail Goods"
      }
    ],
    "sg:phone": "+1 419 394 6691",
    "sg:postcode": "45885",
    "sg:province": "OH",
    "sg:tags": [
      "picture",
      "frame",
      "merchandise"
    ],
    "wof:name": "Castle Gallery",
    "wof:placetype": "venue"
  },
  "geometry": {"coordinates":[-84.388237,40.543018],"type":"Point"}
}
