{
  "type": "Feature",
  "properties": {
    "addr:full": "178 Wayne St Mansfield OH 44902",
    "addr:housenumber": "178",
    "addr:postcode": "44902",
    "addr:street": "Wayne St",
    "iso:country": "US",
    "sg:address": "178 Wayne St",
    "sg:city": "Mansfield",
    "sg:classifiers": [
      {
        "category": "Bars \u0026 Pubs",
        "type": "Food \u0026 Drink"
      }
    ],
    "sg:phone": "+1 419 522 6707",
    "sg:postcode": "44902",
    "sg:province": "OH",
    "sg:tags": [
      "drinking"
    ],
    "wof:name": "Rocking Horse",
    "wof:placetype": "venue"
  },
  "geometry": {"coordinates":[-82.506262,40.763537],"type":"Point"}
}
