{
  "type": "Feature",
  "properties": {
    "addr:full": "11911 Pippin Rd Cincinnati OH 45231",
    "addr:housenumber": "11911",
    "addr:postcode": "45231",
    "addr:street": "Pippin Rd",
    "iso:country": "US",
    "sg:address": "11911 Pippin Rd",
    "sg:city": "Cincinnati",
    "sg:classifiers": [
      {
        "category": "Building \u0026 Trades",
        "subcategory": "Construction",
        "type": "Services"
      }
    ],
    "sg:phone": "+1 513 763 0768",
    "sg:postcode": "45231",
    "sg:province": "OH",
    "sg:tags": [
      "excavation",
      "contractor"
    ],
    "wof:name": "Kens Water Hauling and Excav",
    "wof:placetype": "venue"
  },
  "geometry": {"coordinates":[-84.571874,39.302136],"type":"Point"}
}
