{
  "type": "Feature",
  "properties": {
    "addr:full": "693 N Hague Ave Columbus OH 43204",
    "addr:housenumber": "693",
    "addr:postcode": "43204",
    "addr:street": "N Hague Ave",
    "iso:country": "US",
    "sg:address": "693 N Hague Ave",
    "sg:city": "Columbus",
    "sg:classifiers": [
      {
        "category": "Building \u0026 Trades",
        "subcategory": "Construction",
        "type": "Services"
      }
    ],
    "sg:phone": "+1 614 278 9729",
    "sg:postcode": "43204",
    "sg:province": "OH",
    "sg:tags": [
      "painter"
    ],
    "wof:name": "A K Painting",
    "wof:placetype": "venue"
  },
  "geometry": {"coordinates":[-83.077775,39.966579],"type":"Point"}
}
