{
  "type": "Feature",
  "properties": {
    "addr:full":"4785 Leetonia Rd Leetonia OH 44431",
    "addr:housenumber":"4785",
    "addr:postcode":"44431",
    "addr:street":"Leetonia Rd",
    "iso:country":"US",
    "sg:address":"4785 Leetonia Rd",
    "sg:city":"Leetonia",
    "sg:classifiers":[
        {
            "category":"Farming",
            "subcategory":"Farm & Veterinary Services",
            "type":"Manufacturing & Wholesale Goods"
        }
    ],
    "sg:phone":"+1 330 427 6527",
    "sg:postcode":"44431",
    "sg:province":"OH",
    "sg:tags":[
        "preparation",
        "soil",
        "supply"
    ],
    "wof:name":"Grubbs Bros Inc",
    "wof:placetype":"venue"
},
  "geometry": {"coordinates":[-80.75590800000001,40.831162],"type":"Point"}
}