{
  "type": "Feature",
  "properties": {
    "addr:full": "4785 Leetonia Rd Leetonia OH 44431",
    "addr:housenumber": "4785",
    "addr:postcode": "44431",
    "addr:street": "Leetonia Rd",
    "iso:country": "US",
    "sg:address": "4785 Leetonia Rd",
    "sg:city": "Leetonia",
    "sg:classifiers": [
      {
        "category": "Farming",
        "subcategory": "Farm \u0026 Veterinary Services",
        "type": "Manufacturing \u0026 Wholesale Goods"
      }
    ],
    "sg:phone": "+1 330 427 6527",
    "sg:postcode": "44431",
    "sg:province": "OH",
    "sg:tags": [
      "preparation",
      "soil",
      "supply"
    ],
    "wof:name": "Grubbs Bros Inc",
    "wof:placetype": "venue"
  },
  "geometry": {"coordinates":[-80.755908,40.831162],"type":"Point"}
}
