{
  "type": "Feature",
  "properties": {
    "iso:country":"US",
    "sg:address":"1975 Royal Oak Dr",
    "sg:city":"Lewis Center",
    "sg:classifiers":[
        {
            "category":"Building & Trades",
            "subcategory":"Construction",
            "type":"Services"
        }
    ],
    "sg:phone":"+1 740 548 8526",
    "sg:postcode":"43035",
    "sg:province":"OH",
    "sg:tags":[
        "house"
    ],
    "wof:name":"Homewood Corporation",
    "wof:placetype":"venue"
},
  "geometry": {"coordinates":[-82.99306300000001,40.165727],"type":"Point"}
}