{
  "type": "Feature",
  "properties": {
    "addr:full": "1975 Royal Oak Dr Lewis Center OH 43035",
    "addr:housenumber": "1975",
    "addr:postcode": "43035",
    "addr:street": "Royal Oak Dr",
    "iso:country": "US",
    "sg:address": "1975 Royal Oak Dr",
    "sg:city": "Lewis Center",
    "sg:classifiers": [
      {
        "category": "Building \u0026 Trades",
        "subcategory": "Construction",
        "type": "Services"
      }
    ],
    "sg:phone": "+1 740 548 8526",
    "sg:postcode": "43035",
    "sg:province": "OH",
    "sg:tags": [
      "house"
    ],
    "wof:name": "Homewood Corporation",
    "wof:placetype": "venue"
  },
  "geometry": {"coordinates":[-82.993063,40.165727],"type":"Point"}
}
