{
  "type": "Feature",
  "properties": {
    "addr:full":"3401 Drew Rd Arcanum OH 45304",
    "addr:housenumber":"3401",
    "addr:postcode":"45304",
    "addr:street":"Drew Rd",
    "iso:country":"US",
    "sg:address":"3401 Drew Rd",
    "sg:city":"Arcanum",
    "sg:classifiers":[
        {
            "category":"Manufacturing",
            "subcategory":"Tools & Machinery",
            "type":"Manufacturing & Wholesale Goods"
        }
    ],
    "sg:phone":"+1 937 692 5038",
    "sg:postcode":"45304",
    "sg:province":"OH",
    "sg:tags":[
        "industrial",
        "mfg"
    ],
    "wof:name":"Baker Machining Service",
    "wof:placetype":"venue"
},
  "geometry": {"coordinates":[-84.57419299999999,40.017269],"type":"Point"}
}