{
  "type": "Feature",
  "properties": {
    "addr:full": "9974 International Blvd Cincinnati OH 45246",
    "addr:housenumber": "9974",
    "addr:postcode": "45246",
    "addr:street": "International Blvd",
    "iso:country": "US",
    "sg:address": "9974 International Blvd",
    "sg:city": "Cincinnati",
    "sg:classifiers": [
      {
        "category": "Manufacturing",
        "subcategory": "Printing",
        "type": "Manufacturing \u0026 Wholesale Goods"
      }
    ],
    "sg:phone": "+1 513 860 5550",
    "sg:postcode": "45246",
    "sg:province": "OH",
    "sg:tags": [
      "business",
      "form",
      "mfg"
    ],
    "wof:name": "Relizon Company",
    "wof:placetype": "venue"
  },
  "geometry": {"coordinates":[-84.442743,39.305034],"type":"Point"}
}
