{
  "type": "Feature",
  "properties": {
    "addr:full": "913 Lincoln Ave Cincinnati OH 45206",
    "addr:housenumber": "913",
    "addr:postcode": "45206",
    "addr:street": "Lincoln Ave",
    "iso:country": "US",
    "sg:address": "913 Lincoln Ave",
    "sg:city": "Cincinnati",
    "sg:classifiers": [
      {
        "category": "Shopping",
        "subcategory": "Clothing, Apparel, \u0026 Fashions",
        "type": "Retail Goods"
      }
    ],
    "sg:phone": "+1 513 221 0902",
    "sg:postcode": "45206",
    "sg:province": "OH",
    "wof:name": "African International",
    "wof:placetype": "venue"
  },
  "geometry": {"coordinates":[-84.487519,39.132086],"type":"Point"}
}
