{
  "type": "Feature",
  "properties": {
    "iso:country":"US",
    "sg:address":"913 Lincoln Ave",
    "sg:city":"Cincinnati",
    "sg:classifiers":[
        {
            "category":"Shopping",
            "subcategory":"Clothing, Apparel, & Fashions",
            "type":"Retail Goods"
        }
    ],
    "sg:phone":"+1 513 221 0902",
    "sg:postcode":"45206",
    "sg:province":"OH",
    "wof:name":"African International",
    "wof:placetype":"venue"
},
  "geometry": {"coordinates":[-84.48751900000001,39.132086],"type":"Point"}
}