{
  "type": "Feature",
  "properties": {
    "addr:full": "7155 Briarcliff Rd Reynoldsburg OH 43068",
    "addr:housenumber": "7155",
    "addr:postcode": "43068",
    "addr:street": "Briarcliff Rd",
    "iso:country": "US",
    "sg:address": "7155 Briarcliff Rd",
    "sg:city": "Reynoldsburg",
    "sg:classifiers": [
      {
        "category": "Recreation",
        "type": "Entertainment"
      }
    ],
    "sg:phone": "+1 614 501 0027",
    "sg:postcode": "43068",
    "sg:province": "OH",
    "sg:tags": [
      "aquarium"
    ],
    "wof:name": "A Fine Aquarium Svc",
    "wof:placetype": "venue"
  },
  "geometry": {"coordinates":[-82.807625,39.962799],"type":"Point"}
}
