{
  "type": "Feature",
  "properties": {
    "iso:country":"US",
    "sg:address":"2160 Tall Timbers Ct",
    "sg:city":"Columbus",
    "sg:classifiers":[
        {
            "category":"Manufacturing",
            "subcategory":"Chemicals & Compounds",
            "type":"Manufacturing & Wholesale Goods"
        },
        {
            "category":"Personal",
            "subcategory":"Hair Removal",
            "type":"Services"
        }
    ],
    "sg:phone":"+1 614 274 9832",
    "sg:postcode":"43228",
    "sg:province":"OH",
    "sg:tags":[
        "electrolysis"
    ],
    "wof:name":"Chandler Phyllis",
    "wof:placetype":"venue"
},
  "geometry": {"coordinates":[-83.105884,39.997928],"type":"Point"}
}