{
  "type": "Feature",
  "properties": {
    "addr:full": "3630 E 116th St Cleveland OH 44105",
    "addr:housenumber": "3630",
    "addr:postcode": "44105",
    "addr:street": "E 116Th St",
    "iso:country": "US",
    "sg:address": "3630 E 116th St",
    "sg:city": "Cleveland",
    "sg:classifiers": [
      {
        "category": "Organizations",
        "subcategory": "Religious Organization",
        "type": "Services"
      }
    ],
    "sg:phone": "+1 216 752 9658",
    "sg:postcode": "44105",
    "sg:province": "OH",
    "wof:name": "Greater Love Missionary Bapt",
    "wof:placetype": "venue"
  },
  "geometry": {"coordinates":[-81.602857,41.461587],"type":"Point"}
}
