{
  "type": "Feature",
  "properties": {
    "iso:country":"US",
    "sg:address":"3630 E 116th St",
    "sg:city":"Cleveland",
    "sg:classifiers":[
        {
            "category":"Organizations",
            "subcategory":"Religious Organization",
            "type":"Services"
        }
    ],
    "sg:phone":"+1 216 752 9658",
    "sg:postcode":"44105",
    "sg:province":"OH",
    "wof:name":"Greater Love Missionary Bapt",
    "wof:placetype":"venue"
},
  "geometry": {"coordinates":[-81.602857,41.461587],"type":"Point"}
}