{
  "type": "Feature",
  "properties": {
    "addr:full":"6063 Lick Run Lyra Rd Wheelersburg OH 45694",
    "addr:postcode":"6063;45694",
    "addr:street":"Lick Run Lyra Rd",
    "iso:country":"US",
    "sg:address":"6063 Lick Run Lyra Rd",
    "sg:city":"Wheelersburg",
    "sg:classifiers":[
        {
            "category":"Utilities",
            "subcategory":"Refuse",
            "type":"Services"
        }
    ],
    "sg:phone":"+1 740 574 1264",
    "sg:postcode":"45694",
    "sg:province":"OH",
    "sg:tags":[
        "system"
    ],
    "wof:name":"American Tire Recycling",
    "wof:placetype":"venue"
},
  "geometry": {"coordinates":[-82.76134999999999,38.715177],"type":"Point"}
}