{
  "type": "Feature",
  "properties": {
    "iso:country":"US",
    "sg:address":"305 N High St",
    "sg:city":"Columbus Grove",
    "sg:classifiers":[
        {
            "category":"Organizations",
            "subcategory":"Religious Organization",
            "type":"Services"
        }
    ],
    "sg:phone":"+1 419 659 5980",
    "sg:postcode":"45830",
    "sg:province":"OH",
    "sg:tags":[
        "church"
    ],
    "wof:name":"Seventh-Day Adventist Church",
    "wof:placetype":"venue"
},
  "geometry": {"coordinates":[-84.05122,40.922781],"type":"Point"}
}