{
  "type": "Feature",
  "properties": {
    "addr:full":"5682 Mayfield Rd Cleveland OH 44124",
    "addr:housenumber":"5682",
    "addr:postcode":"44124",
    "addr:street":"Mayfield Rd",
    "iso:country":"US",
    "sg:address":"5682 Mayfield Rd",
    "sg:city":"Cleveland",
    "sg:classifiers":[
        {
            "category":"Health Services",
            "subcategory":"Doctor",
            "type":"Services"
        }
    ],
    "sg:phone":"+1 440 449 9111",
    "sg:postcode":"44124",
    "sg:province":"OH",
    "sg:tags":[
        "dentist"
    ],
    "wof:name":"Craig R Shimizu DDS",
    "wof:placetype":"venue"
},
  "geometry": {"coordinates":[-81.47416,41.519945],"type":"Point"}
}