{
  "type": "Feature",
  "properties": {
    "iso:country":"US",
    "sg:address":"6670 Belmont Ave",
    "sg:city":"Girard",
    "sg:classifiers":[
        {
            "category":"Food & Beverages",
            "subcategory":"Groceries & Convenience Stores",
            "type":"Retail Goods"
        },
        {
            "category":"Restaurant",
            "type":"Food & Drink"
        }
    ],
    "sg:phone":"+1 330 539 4419",
    "sg:postcode":"44420",
    "sg:province":"OH",
    "sg:tags":[
        "eating"
    ],
    "wof:name":"Punky's Pit Stop",
    "wof:placetype":"venue"
},
  "geometry": {"coordinates":[-80.663995,41.199054],"type":"Point"}
}