{
  "type": "Feature",
  "properties": {
    "addr:full": "6670 Belmont Ave Girard OH 44420",
    "addr:housenumber": "6670",
    "addr:postcode": "44420",
    "addr:street": "Belmont Ave",
    "iso:country": "US",
    "sg:address": "6670 Belmont Ave",
    "sg:city": "Girard",
    "sg:classifiers": [
      {
        "category": "Food \u0026 Beverages",
        "subcategory": "Groceries \u0026 Convenience Stores",
        "type": "Retail Goods"
      },
      {
        "category": "Restaurant",
        "type": "Food \u0026 Drink"
      }
    ],
    "sg:phone": "+1 330 539 4419",
    "sg:postcode": "44420",
    "sg:province": "OH",
    "sg:tags": [
      "eating"
    ],
    "wof:name": "Punky's Pit Stop",
    "wof:placetype": "venue"
  },
  "geometry": {"coordinates":[-80.663995,41.199054],"type":"Point"}
}
