{
  "type": "Feature",
  "properties": {
    "addr:full":"5310 Packard Dr Dayton OH 45424",
    "addr:housenumber":"5310",
    "addr:postcode":"45424",
    "addr:street":"Packard Dr",
    "iso:country":"US",
    "sg:address":"5310 Packard Dr",
    "sg:city":"Dayton",
    "sg:classifiers":[
        {
            "category":"Organizations",
            "subcategory":"Religious Organization",
            "type":"Services"
        }
    ],
    "sg:phone":"+1 937 233 3444",
    "sg:postcode":"45424",
    "sg:province":"OH",
    "wof:name":"Huber Hts First Bapt-S B C",
    "wof:placetype":"venue"
},
  "geometry": {"coordinates":[-84.125606,39.830254],"type":"Point"}
}