{
  "type": "Feature",
  "properties": {
    "addr:full":"122 Admiral Dr Willoughby OH 44095",
    "addr:housenumber":"122",
    "addr:postcode":"44095",
    "addr:street":"Admiral Dr",
    "iso:country":"US",
    "sg:address":"122 Admiral Dr",
    "sg:city":"Willoughby",
    "sg:classifiers":[
        {
            "category":"Building & Trades",
            "subcategory":"Construction",
            "type":"Services"
        }
    ],
    "sg:phone":"+1 440 951 1235",
    "sg:postcode":"44095",
    "sg:province":"OH",
    "sg:tags":[
        "concrete",
        "contractor"
    ],
    "wof:name":"Dowhan Concrete Construction",
    "wof:placetype":"venue"
},
  "geometry": {"coordinates":[-81.43641599999999,41.672819],"type":"Point"}
}