{
  "type": "Feature",
  "properties": {
    "iso:country":"US",
    "sg:address":"964 Maple Ave",
    "sg:city":"Zanesville",
    "sg:classifiers":[
        {
            "category":"Health Services",
            "subcategory":"Doctor",
            "type":"Services"
        }
    ],
    "sg:phone":"+1 740 453 7444",
    "sg:postcode":"43701",
    "sg:province":"OH",
    "sg:tags":[
        "dentist"
    ],
    "wof:name":"Melvin L Miskovich DDS",
    "wof:placetype":"venue"
},
  "geometry": {"coordinates":[-82.01075400000001,39.950854],"type":"Point"}
}