{
  "type": "Feature",
  "properties": {
    "addr:full":"5353 Inn Cir NW North Canton OH 44720",
    "addr:housenumber":"5353",
    "addr:postcode":"44720",
    "addr:street":"Inn Cir Nw",
    "iso:country":"US",
    "sg:address":"5353 Inn Cir NW",
    "sg:city":"North Canton",
    "sg:classifiers":[
        {
            "category":"Travel",
            "subcategory":"Hotels & Motels",
            "type":"Entertainment"
        }
    ],
    "sg:phone":"+1 330 499 1970",
    "sg:postcode":"44720",
    "sg:province":"OH",
    "wof:name":"Red Roof Inn Canton",
    "wof:placetype":"venue"
},
  "geometry": {"coordinates":[-81.433432,40.858352],"type":"Point"}
}