{
  "type": "Feature",
  "properties": {
    "iso:country":"US",
    "sg:address":"280 Emmaus Rd",
    "sg:city":"Marysville",
    "sg:classifiers":[
        {
            "category":"Building & Trades",
            "subcategory":"Construction",
            "type":"Services"
        }
    ],
    "sg:phone":"+1 937 644 1388",
    "sg:postcode":"43040",
    "sg:province":"OH",
    "sg:tags":[
        "house",
        "nonresidential"
    ],
    "wof:name":"Wing James",
    "wof:placetype":"venue"
},
  "geometry": {"coordinates":[-83.386584,40.235337],"type":"Point"}
}