{
  "type": "Feature",
  "properties": {
    "addr:full": "3651 Towne Blvd Franklin OH 45005",
    "addr:housenumber": "3651",
    "addr:postcode": "45005",
    "addr:street": "Towne Blvd",
    "iso:country": "US",
    "sg:address": "3651 Towne Blvd",
    "sg:city": "Franklin",
    "sg:classifiers": [
      {
        "category": "Food \u0026 Beverages",
        "subcategory": "Groceries \u0026 Convenience Stores",
        "type": "Retail Goods"
      }
    ],
    "sg:phone": "+1 513 420 3901",
    "sg:postcode": "45005",
    "sg:province": "OH",
    "sg:tags": [
      "grocer"
    ],
    "sg:website": "www.meijer.com",
    "wof:name": "Meijer",
    "wof:placetype": "venue"
  },
  "geometry": {"coordinates":[-84.332088,39.500807],"type":"Point"}
}
