{
  "type": "Feature",
  "properties": {
    "iso:country":"US",
    "sg:address":"9501 Colerain Ave",
    "sg:city":"Cincinnati",
    "sg:classifiers":[
        {
            "category":"Shopping",
            "subcategory":"Clothing, Apparel, & Fashions",
            "type":"Retail Goods"
        }
    ],
    "sg:phone":"+1 513 245 9437",
    "sg:postcode":"45251",
    "sg:province":"OH",
    "sg:tags":[
        "infant",
        "wear"
    ],
    "sg:website":"www.childrensplace.com",
    "wof:name":"Children's Place",
    "wof:placetype":"venue"
},
  "geometry": {"coordinates":[-84.59504699999999,39.243543],"type":"Point"}
}