{
  "type": "Feature",
  "properties": {
    "addr:full": "13 E 1st St Arcanum OH 45304",
    "addr:housenumber": "13",
    "addr:postcode": "45304",
    "addr:street": "E 1St St",
    "iso:country": "US",
    "sg:address": "13 E 1st St",
    "sg:city": "Arcanum",
    "sg:classifiers": [
      {
        "category": "Building \u0026 Trades",
        "subcategory": "Plumbing",
        "type": "Services"
      }
    ],
    "sg:phone": "+1 937 692 5817",
    "sg:postcode": "45304",
    "sg:province": "OH",
    "sg:tags": [
      "contractor"
    ],
    "wof:name": "Bechtol Plumbing \u0026 Heating",
    "wof:placetype": "venue"
  },
  "geometry": {"coordinates":[-84.553097,39.989506],"type":"Point"}
}
