{
  "type": "Feature",
  "properties": {
    "iso:country":"US",
    "sg:address":"13 E 1st St",
    "sg:city":"Arcanum",
    "sg:classifiers":[
        {
            "category":"Building & Trades",
            "subcategory":"Plumbing",
            "type":"Services"
        }
    ],
    "sg:phone":"+1 937 692 5817",
    "sg:postcode":"45304",
    "sg:province":"OH",
    "sg:tags":[
        "contractor"
    ],
    "wof:name":"Bechtol Plumbing & Heating",
    "wof:placetype":"venue"
},
  "geometry": {"coordinates":[-84.55309699999999,39.989506],"type":"Point"}
}