{
  "type": "Feature",
  "properties": {
    "addr:full": "740 Euclid Ave Cleveland OH 44115",
    "addr:housenumber": "740",
    "addr:postcode": "44115",
    "addr:street": "Euclid Ave",
    "iso:country": "US",
    "sg:address": "740 Euclid Ave",
    "sg:city": "Cleveland",
    "sg:classifiers": [
      {
        "category": "Parking",
        "type": "Transportation"
      }
    ],
    "sg:phone": "+1 216 861 3021",
    "sg:postcode": "44115",
    "sg:province": "OH",
    "sg:tags": [
      "garage"
    ],
    "wof:name": "AMPCO System Parking",
    "wof:placetype": "venue"
  },
  "geometry": {"coordinates":[-81.689253,41.499911],"type":"Point"}
}
