{
  "type": "Feature",
  "properties": {
    "iso:country":"US",
    "sg:address":"740 Euclid Ave",
    "sg:city":"Cleveland",
    "sg:classifiers":[
        {
            "category":"Parking",
            "type":"Transportation"
        }
    ],
    "sg:phone":"+1 216 861 3021",
    "sg:postcode":"44115",
    "sg:province":"OH",
    "sg:tags":[
        "garage"
    ],
    "wof:name":"AMPCO System Parking",
    "wof:placetype":"venue"
},
  "geometry": {"coordinates":[-81.68925299999999,41.499911],"type":"Point"}
}