{
  "type": "Feature",
  "properties": {
    "iso:country":"US",
    "sg:address":"506 E Sycamore St",
    "sg:city":"Columbus",
    "sg:classifiers":[
        {
            "category":"Insurance",
            "subcategory":"Insurance Agent",
            "type":"Services"
        }
    ],
    "sg:phone":"+1 614 443 1976",
    "sg:postcode":"43206",
    "sg:province":"OH",
    "wof:name":"Health Insurance Resources",
    "wof:placetype":"venue"
},
  "geometry": {"coordinates":[-82.98576799999999,39.948795],"type":"Point"}
}