{
  "type": "Feature",
  "properties": {
    "addr:full": "1900 Train Ave Cleveland OH 44113",
    "addr:postcode": "1900;44113",
    "addr:street": "Train Ave",
    "iso:country": "US",
    "sg:address": "1900 Train Ave",
    "sg:city": "Cleveland",
    "sg:classifiers": [
      {
        "category": "Professional",
        "type": "Services"
      }
    ],
    "sg:phone": "+1 216 685 1934",
    "sg:postcode": "44113",
    "sg:province": "OH",
    "sg:tags": [
      "establishment"
    ],
    "wof:name": "VMG Inc",
    "wof:placetype": "venue"
  },
  "geometry": {"coordinates":[-81.698256,41.480273],"type":"Point"}
}
