{
  "type": "Feature",
  "properties": {
    "iso:country":"US",
    "sg:address":"178 S Washington St",
    "sg:city":"Tiffin",
    "sg:classifiers":[
        {
            "category":"Organizations",
            "subcategory":"Non-profit Organization",
            "type":"Services"
        }
    ],
    "sg:phone":"+1 419 447 7901",
    "sg:postcode":"44883",
    "sg:province":"OH",
    "wof:name":"Renaissance House Inc",
    "wof:placetype":"venue"
},
  "geometry": {"coordinates":[-83.17634700000001,41.112522],"type":"Point"}
}