{
  "type": "Feature",
  "properties": {
    "addr:full": "178 S Washington St Tiffin OH 44883",
    "addr:housenumber": "178",
    "addr:postcode": "44883",
    "addr:street": "S Washington St",
    "iso:country": "US",
    "sg:address": "178 S Washington St",
    "sg:city": "Tiffin",
    "sg:classifiers": [
      {
        "category": "Organizations",
        "subcategory": "Non-profit Organization",
        "type": "Services"
      }
    ],
    "sg:phone": "+1 419 447 7901",
    "sg:postcode": "44883",
    "sg:province": "OH",
    "wof:name": "Renaissance House Inc",
    "wof:placetype": "venue"
  },
  "geometry": {"coordinates":[-83.176347,41.112522],"type":"Point"}
}
