{
  "type": "Feature",
  "properties": {
    "addr:full":"225 Commercial Ave SE New Philadelphia OH 44663",
    "addr:housenumber":"225",
    "addr:postcode":"44663",
    "addr:street":"Commercial Ave Se",
    "iso:country":"US",
    "sg:address":"225 Commercial Ave SE",
    "sg:city":"New Philadelphia",
    "sg:classifiers":[
        {
            "category":"Restaurant",
            "type":"Food & Drink"
        }
    ],
    "sg:phone":"+1 330 339 3000",
    "sg:postcode":"44663",
    "sg:province":"OH",
    "sg:tags":[
        "pizza"
    ],
    "wof:name":"South Philly Pizza",
    "wof:placetype":"venue"
},
  "geometry": {"coordinates":[-81.446274,40.477923],"type":"Point"}
}