{
  "type": "Feature",
  "properties": {
    "addr:full":"506 W Sharon Rd Cincinnati OH 45240",
    "addr:housenumber":"506",
    "addr:postcode":"45240",
    "addr:street":"W Sharon Rd",
    "iso:country":"US",
    "sg:address":"506 W Sharon Rd",
    "sg:city":"Cincinnati",
    "sg:classifiers":[
        {
            "category":"Building & Trades",
            "subcategory":"Construction",
            "type":"Services"
        }
    ],
    "sg:phone":"+1 513 851 3835",
    "sg:postcode":"45240",
    "sg:province":"OH",
    "sg:tags":[
        "installation",
        "door"
    ],
    "wof:name":"Door Tech",
    "wof:placetype":"venue"
},
  "geometry": {"coordinates":[-84.49466700000001,39.274564],"type":"Point"}
}