{
  "type": "Feature",
  "properties": {
    "iso:country":"US",
    "sg:address":"7860 Nebraska Ave",
    "sg:city":"Toledo",
    "sg:classifiers":[
        {
            "category":"Retail",
            "subcategory":"Animal Services",
            "type":"Services"
        }
    ],
    "sg:phone":"+1 419 868 8433",
    "sg:postcode":"43617",
    "sg:province":"OH",
    "sg:tags":[
        "training"
    ],
    "wof:name":"Toledo Horse Sports",
    "wof:placetype":"venue"
},
  "geometry": {"coordinates":[-83.72628899999999,41.646598],"type":"Point"}
}