{
  "type": "Feature",
  "properties": {
    "addr:full": "21457 Rd 15-U Columbus Grove OH 45830",
    "addr:housenumber": "21457;15-u",
    "addr:postcode": "45830",
    "addr:street": "Rd;Columbus Grove",
    "iso:country": "US",
    "sg:address": "21457 Rd 15-U",
    "sg:city": "Columbus Grove",
    "sg:classifiers": [
      {
        "category": "Building \u0026 Trades",
        "subcategory": "Construction",
        "type": "Services"
      }
    ],
    "sg:phone": "+1 419 646 3716",
    "sg:postcode": "45830",
    "sg:province": "OH",
    "sg:tags": [
      "system",
      "met",
      "exterior",
      "insulation",
      "finishing",
      "drywall"
    ],
    "wof:name": "Halker Drywall \u0026 Plastering",
    "wof:placetype": "venue"
  },
  "geometry": {"coordinates":[-84.152173,40.869322],"type":"Point"}
}
