{
  "type": "Feature",
  "properties": {
    "iso:country":"US",
    "sg:address":"9996 Serene Ct",
    "sg:city":"Twinsburg",
    "sg:classifiers":[
        {
            "category":"Building & Trades",
            "subcategory":"Construction",
            "type":"Services"
        }
    ],
    "sg:phone":"+1 330 405 2719",
    "sg:postcode":"44087",
    "sg:province":"OH",
    "sg:tags":[
        "contractor"
    ],
    "wof:name":"Little India",
    "wof:placetype":"venue"
},
  "geometry": {"coordinates":[-81.466364,41.341579],"type":"Point"}
}