{
  "type": "Feature",
  "properties": {
    "iso:country":"US",
    "sg:address":"20 S Foster St",
    "sg:city":"Springfield",
    "sg:classifiers":[
        {
            "category":"Shopping",
            "subcategory":"Used Merchandise",
            "type":"Retail Goods"
        }
    ],
    "sg:phone":"+1 937 325 3247",
    "sg:postcode":"45505",
    "sg:province":"OH",
    "sg:tags":[
        "antique"
    ],
    "wof:name":"Edward G Dietz",
    "wof:placetype":"venue"
},
  "geometry": {"coordinates":[-83.804425,39.923023],"type":"Point"}
}