{
  "type": "Feature",
  "properties": {
    "iso:country":"US",
    "sg:address":"7135 Broadway Ave",
    "sg:city":"Cleveland",
    "sg:classifiers":[
        {
            "category":"Organizations",
            "subcategory":"Religious Organization",
            "type":"Services"
        }
    ],
    "sg:phone":"+1 216 441 4004",
    "sg:postcode":"44105",
    "sg:province":"OH",
    "sg:tags":[
        "synagogue"
    ],
    "wof:name":"Harvest Temple",
    "wof:placetype":"venue"
},
  "geometry": {"coordinates":[-81.637314,41.457096],"type":"Point"}
}