{
  "type": "Feature",
  "properties": {
    "addr:full": "4880 Hudson Dr Cuyahoga Falls OH 44224",
    "addr:housenumber": "4880",
    "addr:postcode": "44224",
    "addr:street": "Hudson Dr",
    "iso:country": "US",
    "sg:address": "4880 Hudson Dr",
    "sg:city": "Cuyahoga Falls",
    "sg:classifiers": [
      {
        "category": "Retail",
        "subcategory": "Auto Repair",
        "type": "Services"
      }
    ],
    "sg:phone": "+1 330 688 0788",
    "sg:postcode": "44224",
    "sg:province": "OH",
    "sg:tags": [
      "repairing",
      "automobile"
    ],
    "wof:name": "Monegan's",
    "wof:placetype": "venue"
  },
  "geometry": {"coordinates":[-81.457731,41.196865],"type":"Point"}
}
