{
  "type": "Feature",
  "properties": {
    "iso:country":"US",
    "sg:address":"8300 W Chester Rd",
    "sg:city":"West Chester",
    "sg:classifiers":[
        {
            "category":"Shopping",
            "subcategory":"Clothing, Apparel, & Fashions",
            "type":"Retail Goods"
        }
    ],
    "sg:phone":"+1 513 942 8271",
    "sg:postcode":"45069",
    "sg:province":"OH",
    "wof:name":"Uniform and Apparel Speci",
    "wof:placetype":"venue"
},
  "geometry": {"coordinates":[-84.353639,39.317721],"type":"Point"}
}