{
  "type": "Feature",
  "properties": {
    "addr:full": "5601 State Rte 39 Millersburg OH 44654",
    "addr:housenumber": "5601",
    "addr:postcode": "44654",
    "addr:street": "State Rte 39",
    "iso:country": "US",
    "sg:address": "5601 State Rte 39",
    "sg:city": "Millersburg",
    "sg:classifiers": [
      {
        "category": "Building \u0026 Trades",
        "subcategory": "Equipment Rental",
        "type": "Services"
      },
      {
        "category": "Wholesale",
        "subcategory": "Chemicals \u0026 Plastics",
        "type": "Manufacturing \u0026 Wholesale Goods"
      }
    ],
    "sg:phone": "+1 330 674 2114",
    "sg:postcode": "44654",
    "sg:province": "OH",
    "sg:tags": [
      "oxygen"
    ],
    "wof:name": "Miller Art Home Oxygen",
    "wof:placetype": "venue"
  },
  "geometry": {"coordinates":[-81.820961,40.55542],"type":"Point"}
}
