{
  "type": "Feature",
  "properties": {
    "iso:country":"US",
    "sg:address":"1720 Depot Rd",
    "sg:city":"Salem",
    "sg:classifiers":[
        {
            "category":"Home & Garden",
            "subcategory":"Garden Supply",
            "type":"Retail Goods"
        }
    ],
    "sg:phone":"+1 330 332 2117",
    "sg:postcode":"44460",
    "sg:province":"OH",
    "sg:tags":[
        "nurseryman"
    ],
    "wof:name":"Carriage Hill Ground Covers",
    "wof:placetype":"venue"
},
  "geometry": {"coordinates":[-80.856954,40.887173],"type":"Point"}
}