{
  "type": "Feature",
  "properties": {
    "iso:country":"US",
    "sg:address":"1010 Heritage Trl",
    "sg:city":"Ottawa",
    "sg:classifiers":[
        {
            "category":"Building & Trades",
            "subcategory":"Construction",
            "type":"Services"
        }
    ],
    "sg:phone":"+1 419 523 5556",
    "sg:postcode":"45875",
    "sg:province":"OH",
    "sg:tags":[
        "wood",
        "installation",
        "refinishing",
        "floor"
    ],
    "wof:name":"Heritage Floors",
    "wof:placetype":"venue"
},
  "geometry": {"coordinates":[-84.04249299999999,41.005114],"type":"Point"}
}