{
  "type": "Feature",
  "properties": {
    "addr:full":"635 Albin Ave Washington Ct Hs OH 43160",
    "addr:housenumber":"635",
    "addr:postcode":"43160",
    "addr:street":"Albin Ave Washington Ct",
    "iso:country":"US",
    "sg:address":"635 Albin Ave",
    "sg:city":"Washington Ct Hs",
    "sg:classifiers":[
        {
            "category":"Organizations",
            "subcategory":"Community Association",
            "type":"Services"
        }
    ],
    "sg:phone":"+1 740 335 3101",
    "sg:postcode":"43160",
    "sg:province":"OH",
    "wof:name":"American Red Cross",
    "wof:placetype":"venue"
},
  "geometry": {"coordinates":[-83.439808,39.524192],"type":"Point"}
}