{
  "type": "Feature",
  "properties": {
    "addr:full": "6501 Wilson Mills Rd Cleveland OH 44143",
    "addr:housenumber": "6501",
    "addr:postcode": "44143",
    "addr:street": "Wilson Mills Rd",
    "iso:country": "US",
    "sg:address": "6501 Wilson Mills Rd",
    "sg:city": "Cleveland",
    "sg:classifiers": [
      {
        "category": "Social Services",
        "subcategory": "Job Training",
        "type": "Services"
      }
    ],
    "sg:phone": "+1 440 646 9701",
    "sg:postcode": "44143",
    "sg:province": "OH",
    "sg:tags": [
      "rehabilitation"
    ],
    "wof:name": "Parman \u0026 Assoc",
    "wof:placetype": "venue"
  },
  "geometry": {"coordinates":[-81.438794,41.538902],"type":"Point"}
}
