{
  "type": "Feature",
  "properties": {
    "addr:full":"2250 Venus Dr Hilliard OH 43026",
    "addr:housenumber":"2250",
    "addr:postcode":"43026",
    "addr:street":"Venus Dr",
    "iso:country":"US",
    "sg:address":"2250 Venus Dr",
    "sg:city":"Hilliard",
    "sg:classifiers":[
        {
            "category":"Building & Trades",
            "subcategory":"Construction",
            "type":"Services"
        }
    ],
    "sg:phone":"+1 614 850 9831",
    "sg:postcode":"43026",
    "sg:province":"OH",
    "sg:tags":[
        "contractor"
    ],
    "wof:name":"Nu-TEC Roofing Contractors LLC",
    "wof:placetype":"venue"
},
  "geometry": {"coordinates":[-83.148202,39.99462],"type":"Point"}
}