{
  "type": "Feature",
  "properties": {
    "addr:full":"143 S Thomas Rd Tallmadge OH 44278",
    "addr:housenumber":"143",
    "addr:postcode":"44278",
    "addr:street":"S Thomas Rd",
    "iso:country":"US",
    "sg:address":"143 S Thomas Rd",
    "sg:city":"Tallmadge",
    "sg:classifiers":[
        {
            "category":"Manufacturing",
            "subcategory":"Tools & Machinery",
            "type":"Manufacturing & Wholesale Goods"
        }
    ],
    "sg:phone":"+1 330 634 0640",
    "sg:postcode":"44278",
    "sg:province":"OH",
    "sg:tags":[
        "metalworking",
        "industrial",
        "mfg"
    ],
    "wof:name":"Resource Inc",
    "wof:placetype":"venue"
},
  "geometry": {"coordinates":[-81.462113,41.099601],"type":"Point"}
}