{
  "type": "Feature",
  "properties": {
    "addr:full":"505 State Rte 741 Lebanon OH 45036",
    "addr:housenumber":"505",
    "addr:postcode":"45036",
    "addr:street":"State Rte 741",
    "iso:country":"US",
    "sg:address":"505 State Rte 741",
    "sg:city":"Lebanon",
    "sg:classifiers":[
        {
            "category":"Government",
            "subcategory":"Office",
            "type":"Public Place"
        }
    ],
    "sg:phone":"+1 513 932 3030",
    "sg:postcode":"45036",
    "sg:province":"OH",
    "sg:tags":[
        "state",
        "program"
    ],
    "sg:website":"www.dot.state.oh.us",
    "wof:name":"Transportation Dept",
    "wof:placetype":"venue"
},
  "geometry": {"coordinates":[-84.279573,39.437934],"type":"Point"}
}