{
  "type": "Feature",
  "properties": {
    "addr:full":"3146 Mill Run Dr Hilliard OH 43026",
    "addr:housenumber":"3146",
    "addr:postcode":"43026",
    "addr:street":"Mill Run Dr",
    "iso:country":"US",
    "sg:address":"3146 Mill Run Dr",
    "sg:city":"Hilliard",
    "sg:classifiers":[
        {
            "category":"Building & Trades",
            "subcategory":"Landscaping Services",
            "type":"Services"
        }
    ],
    "sg:phone":"+1 614 771 1571",
    "sg:postcode":"43026",
    "sg:province":"OH",
    "sg:tags":[
        "landscape",
        "contractor"
    ],
    "wof:name":"Site Maintenance",
    "wof:placetype":"venue"
},
  "geometry": {"coordinates":[-83.11298499999999,40.024119],"type":"Point"}
}