{
  "type": "Feature",
  "properties": {
    "addr:full":"740 Dresden Ave East Liverpool OH 43920",
    "addr:housenumber":"740",
    "addr:postcode":"43920",
    "addr:street":"Dresden Ave",
    "iso:country":"US",
    "sg:address":"740 Dresden Ave",
    "sg:city":"East Liverpool",
    "sg:classifiers":[
        {
            "category":"Restaurant",
            "type":"Food & Drink"
        }
    ],
    "sg:phone":"+1 330 385 6700",
    "sg:postcode":"43920",
    "sg:province":"OH",
    "sg:tags":[
        "eating"
    ],
    "wof:name":"Italos Pizza Shop",
    "wof:placetype":"venue"
},
  "geometry": {"coordinates":[-80.580185,40.623098],"type":"Point"}
}