{
  "type": "Feature",
  "properties": {
    "iso:country":"US",
    "sg:address":"1935 W 96th St",
    "sg:city":"Cleveland",
    "sg:classifiers":[
        {
            "category":"Building & Trades",
            "subcategory":"Construction",
            "type":"Services"
        }
    ],
    "sg:phone":"+1 216 226 0800",
    "sg:postcode":"44102",
    "sg:province":"OH",
    "sg:tags":[
        "contractor"
    ],
    "wof:name":"Broadview Roofing & Remodeling",
    "wof:placetype":"venue"
},
  "geometry": {"coordinates":[-81.749477,41.478458],"type":"Point"}
}