{
  "type": "Feature",
  "properties": {
    "iso:country":"US",
    "sg:address":"6009 Landerhaven Dr",
    "sg:city":"Cleveland",
    "sg:classifiers":[
        {
            "category":"Education",
            "subcategory":"School",
            "type":"Public Place"
        }
    ],
    "sg:phone":"+1 440 442 2922",
    "sg:postcode":"44124",
    "sg:province":"OH",
    "wof:name":"Ohio Education Associations",
    "wof:placetype":"venue"
},
  "geometry": {"coordinates":[-81.462863,41.50335],"type":"Point"}
}