{
  "type": "Feature",
  "properties": {
    "iso:country":"US",
    "sg:address":"7829 Gatewood Oval",
    "sg:city":"Gates Mills",
    "sg:classifiers":[
        {
            "category":"Building & Trades",
            "subcategory":"Construction",
            "type":"Services"
        }
    ],
    "sg:phone":"+1 440 449 8887",
    "sg:postcode":"44040",
    "sg:province":"OH",
    "sg:tags":[
        "door",
        "window",
        "installation"
    ],
    "wof:name":"Kronick Home Improvements",
    "wof:placetype":"venue"
},
  "geometry": {"coordinates":[-81.39631799999999,41.56831],"type":"Point"}
}