{
  "type": "Feature",
  "properties": {
    "addr:full": "5308 Blanche Ave Cleveland OH 44127",
    "addr:housenumber": "5308",
    "addr:postcode": "44127",
    "addr:street": "Blanche Ave",
    "iso:country": "US",
    "sg:address": "5308 Blanche Ave",
    "sg:city": "Cleveland",
    "sg:classifiers": [
      {
        "category": "Retail",
        "subcategory": "Auto Repair",
        "type": "Services"
      }
    ],
    "sg:phone": "+1 216 441 0646",
    "sg:postcode": "44127",
    "sg:province": "OH",
    "sg:tags": [
      "transmission",
      "automobile",
      "parts"
    ],
    "wof:name": "Cleveland Transmission Supply",
    "wof:placetype": "venue"
  },
  "geometry": {"coordinates":[-81.653477,41.463426],"type":"Point"}
}
