{
  "type": "Feature",
  "properties": {
    "addr:full": "205 Martin St Greenville OH 45331",
    "addr:housenumber": "205",
    "addr:postcode": "45331",
    "addr:street": "Martin St",
    "iso:country": "US",
    "sg:address": "205 Martin St",
    "sg:city": "Greenville",
    "sg:classifiers": [
      {
        "category": "Shopping",
        "subcategory": "Used Merchandise",
        "type": "Retail Goods"
      }
    ],
    "sg:phone": "+1 937 547 1196",
    "sg:postcode": "45331",
    "sg:province": "OH",
    "sg:tags": [
      "new",
      "clothing",
      "furniture"
    ],
    "wof:name": "Family Bazaar",
    "wof:placetype": "venue"
  },
  "geometry": {"coordinates":[-84.628538,40.099373],"type":"Point"}
}
