{
  "type": "Feature",
  "properties": {
    "iso:country":"US",
    "sg:address":"220 Fernwood Rd",
    "sg:city":"Steubenville",
    "sg:classifiers":[
        {
            "category":"Health Services",
            "subcategory":"Doctor",
            "type":"Services"
        }
    ],
    "sg:phone":"+1 740 266 2626",
    "sg:postcode":"43953",
    "sg:province":"OH",
    "sg:tags":[
        "dentist"
    ],
    "wof:name":"Thomas Matanzo DDS Inc",
    "wof:placetype":"venue"
},
  "geometry": {"coordinates":[-80.69854599999999,40.371482],"type":"Point"}
}