{
  "type": "Feature",
  "properties": {
    "addr:full": "220 Fernwood Rd Steubenville OH 43953",
    "addr:housenumber": "220",
    "addr:postcode": "43953",
    "addr:street": "Fernwood Rd",
    "iso:country": "US",
    "sg:address": "220 Fernwood Rd",
    "sg:city": "Steubenville",
    "sg:classifiers": [
      {
        "category": "Health Services",
        "subcategory": "Doctor",
        "type": "Services"
      }
    ],
    "sg:phone": "+1 740 266 2626",
    "sg:postcode": "43953",
    "sg:province": "OH",
    "sg:tags": [
      "dentist"
    ],
    "wof:name": "Thomas Matanzo DDS Inc",
    "wof:placetype": "venue"
  },
  "geometry": {"coordinates":[-80.698546,40.371482],"type":"Point"}
}
