{
  "type": "Feature",
  "properties": {
    "addr:full": "1109 State Rte 133 Bethel OH 45106",
    "addr:housenumber": "1109",
    "addr:postcode": "45106",
    "addr:street": "State Rte 133",
    "iso:country": "US",
    "sg:address": "1109 State Rte 133",
    "sg:city": "Bethel",
    "sg:classifiers": [
      {
        "category": "Professional",
        "subcategory": "Engineering",
        "type": "Services"
      }
    ],
    "sg:phone": "+1 513 876 4332",
    "sg:postcode": "45106",
    "sg:province": "OH",
    "sg:tags": [
      "engineer"
    ],
    "wof:name": "Maverick Engineering \u0026 Consult",
    "wof:placetype": "venue"
  },
  "geometry": {"coordinates":[-84.095146,38.842161],"type":"Point"}
}
