{
  "type": "Feature",
  "properties": {
    "iso:country":"US",
    "sg:address":"22200 Lingrell Rd",
    "sg:city":"West Mansfield",
    "sg:classifiers":[
        {
            "category":"Farming",
            "subcategory":"Livestock Farm",
            "type":"Manufacturing & Wholesale Goods"
        }
    ],
    "sg:phone":"+1 937 982 3346",
    "sg:postcode":"43358",
    "sg:province":"OH",
    "sg:tags":[
        "market",
        "raise",
        "sow"
    ],
    "wof:name":"Pig Paradise",
    "wof:placetype":"venue"
},
  "geometry": {"coordinates":[-83.490597,40.460585],"type":"Point"}
}