{
  "type": "Feature",
  "properties": {
    "addr:full":"14801 Co Rd 34 Bellevue OH 44811",
    "addr:housenumber":"14801;34",
    "addr:postcode":"44811",
    "addr:street":"Co Rd",
    "iso:country":"US",
    "sg:address":"14801 Co Rd 34",
    "sg:city":"Bellevue",
    "sg:classifiers":[
        {
            "category":"Real Estate",
            "subcategory":"Real Estate Operator",
            "type":"Services"
        }
    ],
    "sg:phone":"+1 419 483 6887",
    "sg:postcode":"44811",
    "sg:province":"OH",
    "sg:tags":[
        "property",
        "lessor"
    ],
    "wof:name":"Harold Kistler",
    "wof:placetype":"venue"
},
  "geometry": {"coordinates":[-82.882749,41.240975],"type":"Point"}
}