{
  "type": "Feature",
  "properties": {
    "iso:country":"US",
    "sg:address":"1653 Merriman Rd",
    "sg:city":"Akron",
    "sg:classifiers":[
        {
            "category":"Professional",
            "subcategory":"Advertising",
            "type":"Services"
        }
    ],
    "sg:phone":"+1 330 836 3030",
    "sg:postcode":"44313",
    "sg:province":"OH",
    "wof:name":"Info Channel Inc",
    "wof:placetype":"venue"
},
  "geometry": {"coordinates":[-81.552183,41.134615],"type":"Point"}
}