{
  "type": "Feature",
  "properties": {
    "addr:full": "3817 Tamara Dr Grove City OH 43123",
    "addr:housenumber": "3817",
    "addr:postcode": "43123",
    "addr:street": "Tamara Dr",
    "iso:country": "US",
    "sg:address": "3817 Tamara Dr",
    "sg:city": "Grove City",
    "sg:classifiers": [
      {
        "category": "Banks \u0026 Credit Unions",
        "subcategory": "Bank",
        "type": "Services"
      }
    ],
    "sg:phone": "+1 614 875 8666",
    "sg:postcode": "43123",
    "sg:province": "OH",
    "sg:tags": [
      "institution",
      "business"
    ],
    "wof:name": "Navastone Inc",
    "wof:placetype": "venue"
  },
  "geometry": {"coordinates":[-83.074055,39.885447],"type":"Point"}
}
