{
  "type": "Feature",
  "properties": {
    "addr:full":"607 Central Center Chillicothe OH 45601",
    "addr:housenumber":"607",
    "addr:postcode":"45601",
    "addr:street":"Central Center",
    "iso:country":"US",
    "sg:address":"607 Central Center",
    "sg:city":"Chillicothe",
    "sg:classifiers":[
        {
            "category":"Restaurant",
            "type":"Food & Drink"
        }
    ],
    "sg:phone":"+1 740 773 5577",
    "sg:postcode":"45601",
    "sg:province":"OH",
    "sg:tags":[
        "eating"
    ],
    "wof:name":"Panda Pantry",
    "wof:placetype":"venue"
},
  "geometry": {"coordinates":[-83.00181499999999,39.337239],"type":"Point"}
}