{
  "type": "Feature",
  "properties": {
    "iso:country":"US",
    "sg:address":"1194 Applegrove St NE",
    "sg:city":"Canton",
    "sg:classifiers":[
        {
            "category":"Building & Trades",
            "subcategory":"Construction",
            "type":"Services"
        }
    ],
    "sg:phone":"+1 330 498 0982",
    "sg:postcode":"44721",
    "sg:province":"OH",
    "sg:tags":[
        "concrete",
        "contractor"
    ],
    "wof:name":"Dickerson Construction Co",
    "wof:placetype":"venue"
},
  "geometry": {"coordinates":[-81.359537,40.889214],"type":"Point"}
}