{
  "type": "Feature",
  "properties": {
    "iso:country":"US",
    "sg:address":"35228 N Turtle Trl",
    "sg:city":"Willoughby",
    "sg:classifiers":[
        {
            "category":"Shopping",
            "subcategory":"Florist",
            "type":"Retail Goods"
        }
    ],
    "sg:phone":"+1 440 942 8799",
    "sg:postcode":"44094",
    "sg:province":"OH",
    "wof:name":"Design Focus",
    "wof:placetype":"venue"
},
  "geometry": {"coordinates":[-81.43678199999999,41.621688],"type":"Point"}
}