{
  "type": "Feature",
  "properties": {
    "addr:full": "1525 Almedia Ct Miamisburg OH 45342",
    "addr:housenumber": "1525",
    "addr:postcode": "45342",
    "addr:street": "Almedia Ct",
    "iso:country": "US",
    "sg:address": "1525 Almedia Ct",
    "sg:city": "Miamisburg",
    "sg:classifiers": [
      {
        "category": "Real Estate",
        "subcategory": "Real Estate Operator",
        "type": "Services"
      }
    ],
    "sg:phone": "+1 937 866 1030",
    "sg:postcode": "45342",
    "sg:province": "OH",
    "sg:tags": [
      "apartment"
    ],
    "wof:name": "Maple Oaks Apartments",
    "wof:placetype": "venue"
  },
  "geometry": {"coordinates":[-84.26158,39.64272],"type":"Point"}
}
