{
  "type": "Feature",
  "properties": {
    "addr:full": "130 N Fulton St Wauseon OH 43567",
    "addr:housenumber": "130",
    "addr:postcode": "43567",
    "addr:street": "N Fulton St",
    "iso:country": "US",
    "sg:address": "130 N Fulton St",
    "sg:city": "Wauseon",
    "sg:classifiers": [
      {
        "category": "Retail",
        "subcategory": "Repair Shop",
        "type": "Services"
      }
    ],
    "sg:phone": "+1 419 337 8803",
    "sg:postcode": "43567",
    "sg:province": "OH",
    "sg:tags": [
      "lock",
      "locksmith"
    ],
    "wof:name": "Pflager Lock \u0026 Key",
    "wof:placetype": "venue"
  },
  "geometry": {"coordinates":[-84.141385,41.548885],"type":"Point"}
}
