{
  "type": "Feature",
  "properties": {
    "iso:country":"US",
    "sg:address":"130 N Fulton St",
    "sg:city":"Wauseon",
    "sg:classifiers":[
        {
            "category":"Retail",
            "subcategory":"Repair Shop",
            "type":"Services"
        }
    ],
    "sg:phone":"+1 419 337 8803",
    "sg:postcode":"43567",
    "sg:province":"OH",
    "sg:tags":[
        "lock",
        "locksmith"
    ],
    "wof:name":"Pflager Lock & Key",
    "wof:placetype":"venue"
},
  "geometry": {"coordinates":[-84.141385,41.548885],"type":"Point"}
}