{
  "type": "Feature",
  "properties": {
    "addr:full":"65227 Porterfield Rd St Clairsville OH 43950",
    "addr:housenumber":"65227",
    "addr:postcode":"43950",
    "addr:street":"Porterfield Rd",
    "iso:country":"US",
    "sg:address":"65227 Porterfield Rd",
    "sg:city":"St Clairsville",
    "sg:classifiers":[
        {
            "category":"Utilities",
            "subcategory":"Refuse",
            "type":"Services"
        }
    ],
    "sg:phone":"+1 740 695 5462",
    "sg:postcode":"43950",
    "sg:province":"OH",
    "sg:tags":[
        "garbage",
        "collection"
    ],
    "wof:name":"J & W Roll-Off Svc",
    "wof:placetype":"venue"
},
  "geometry": {"coordinates":[-80.92978599999999,40.032806],"type":"Point"}
}