{
  "type": "Feature",
  "properties": {
    "iso:country":"US",
    "sg:address":"217 Market St",
    "sg:city":"Portsmouth",
    "sg:classifiers":[
        {
            "category":"Home & Garden",
            "subcategory":"Hardware",
            "type":"Retail Goods"
        }
    ],
    "sg:phone":"+1 740 353 8959",
    "sg:postcode":"45662",
    "sg:province":"OH",
    "wof:name":"True Value",
    "wof:placetype":"venue"
},
  "geometry": {"coordinates":[-83.003034,38.732384],"type":"Point"}
}