{
  "type": "Feature",
  "properties": {
    "addr:full":"1993 State Rte 59 Kent OH 44240",
    "addr:housenumber":"1993",
    "addr:postcode":"44240",
    "addr:street":"State Rte 59",
    "iso:country":"US",
    "sg:address":"1993 State Rte 59",
    "sg:city":"Kent",
    "sg:classifiers":[
        {
            "category":"Health Services",
            "subcategory":"Hospital",
            "type":"Services"
        }
    ],
    "sg:phone":"+1 330 678 4380",
    "sg:postcode":"44240",
    "sg:province":"OH",
    "sg:tags":[
        "general"
    ],
    "wof:name":"Med Center One",
    "wof:placetype":"venue"
},
  "geometry": {"coordinates":[-81.318912,41.155939],"type":"Point"}
}