{
  "type": "Feature",
  "properties": {
    "addr:full":"492 Armstrong St Columbus OH 43215",
    "addr:housenumber":"492",
    "addr:postcode":"43215",
    "addr:street":"Armstrong St",
    "iso:country":"US",
    "sg:address":"492 Armstrong St",
    "sg:city":"Columbus",
    "sg:classifiers":[
        {
            "category":"Communications",
            "subcategory":"Film & Video Production",
            "type":"Services"
        }
    ],
    "sg:phone":"+1 614 228 4808",
    "sg:postcode":"43215",
    "sg:province":"OH",
    "sg:tags":[
        "audio",
        "taping"
    ],
    "sg:website":"www.ozonestudios.com",
    "wof:name":"Ozone Studios LLC",
    "wof:placetype":"venue"
},
  "geometry": {"coordinates":[-83.00597500000001,39.971644],"type":"Point"}
}