{
  "type": "Feature",
  "properties": {
    "iso:country":"US",
    "sg:address":"7689 Indian Pond Ct",
    "sg:city":"Cincinnati",
    "sg:classifiers":[
        {
            "category":"Professional",
            "type":"Services"
        }
    ],
    "sg:phone":"+1 513 755 1412",
    "sg:postcode":"45241",
    "sg:province":"OH",
    "wof:name":"Larry Dunbar",
    "wof:placetype":"venue"
},
  "geometry": {"coordinates":[-84.37265499999999,39.303293],"type":"Point"}
}