{
  "type": "Feature",
  "properties": {
    "addr:full": "511 N Park St Columbus OH 43215",
    "addr:housenumber": "511",
    "addr:postcode": "43215",
    "addr:street": "N Park St",
    "iso:country": "US",
    "sg:address": "511 N Park St",
    "sg:city": "Columbus",
    "sg:classifiers": [
      {
        "category": "Travel",
        "subcategory": "Hotels \u0026 Motels",
        "type": "Entertainment"
      }
    ],
    "sg:phone": "+1 614 224 5151",
    "sg:postcode": "43215",
    "sg:province": "OH",
    "wof:name": "Economy Inn",
    "wof:placetype": "venue"
  },
  "geometry": {"coordinates":[-83.004568,39.972857],"type":"Point"}
}
