{
  "type": "Feature",
  "properties": {
    "addr:full":"3244 Candy Woods Dr Youngstown OH 44514",
    "addr:housenumber":"3244",
    "addr:postcode":"44514",
    "addr:street":"Candy Woods Dr",
    "iso:country":"US",
    "sg:address":"3244 Candy Woods Dr",
    "sg:city":"Youngstown",
    "sg:classifiers":[
        {
            "category":"Professional",
            "subcategory":"Computer Services",
            "type":"Services"
        }
    ],
    "sg:phone":"+1 330 518 3853",
    "sg:postcode":"44514",
    "sg:province":"OH",
    "sg:tags":[
        "web",
        "design",
        "hosting",
        "site"
    ],
    "wof:name":"Turbo Web Solutions, Inc",
    "wof:placetype":"venue"
},
  "geometry": {"coordinates":[-80.59029200000001,41.029708],"type":"Point"}
}