{
  "type": "Feature",
  "properties": {
    "iso:country":"US",
    "sg:address":"108 Collins Ave",
    "sg:city":"South Point",
    "sg:classifiers":[
        {
            "category":"Government",
            "subcategory":"Post Office",
            "type":"Public Place"
        }
    ],
    "sg:phone":"+1 740 377 4002",
    "sg:postcode":"45680",
    "sg:province":"OH",
    "sg:website":"www.usps.com",
    "wof:name":"US Post Office",
    "wof:placetype":"venue"
},
  "geometry": {"coordinates":[-82.57517,38.423821],"type":"Point"}
}