{
  "type": "Feature",
  "properties": {
    "iso:country":"US",
    "sg:address":"13170 Ravenna Rd",
    "sg:city":"Chardon",
    "sg:classifiers":[
        {
            "category":"Health Services",
            "subcategory":"Doctor",
            "type":"Services"
        }
    ],
    "sg:phone":"+1 440 286 5464",
    "sg:postcode":"44024",
    "sg:province":"OH",
    "sg:tags":[
        "physician",
        "surgeon"
    ],
    "wof:name":"Prem S Jawa MD",
    "wof:placetype":"venue"
},
  "geometry": {"coordinates":[-81.193692,41.509898],"type":"Point"}
}