{
  "type": "Feature",
  "properties": {
    "iso:country":"US",
    "sg:address":"1001 E Centerville Station Rd",
    "sg:city":"Dayton",
    "sg:classifiers":[
        {
            "category":"Banks & Credit Unions",
            "subcategory":"Bank",
            "type":"Services"
        }
    ],
    "sg:phone":"+1 937 433 3773",
    "sg:postcode":"45459",
    "sg:province":"OH",
    "sg:tags":[
        "national",
        "commercial"
    ],
    "wof:name":"National City Bank",
    "wof:placetype":"venue"
},
  "geometry": {"coordinates":[-84.13739099999999,39.628395],"type":"Point"}
}