{
  "type": "Feature",
  "properties": {
    "addr:full": "1001 E Centerville Station Rd Dayton OH 45459",
    "addr:housenumber": "1001",
    "addr:postcode": "45459",
    "addr:street": "E Centerville Station Rd",
    "iso:country": "US",
    "sg:address": "1001 E Centerville Station Rd",
    "sg:city": "Dayton",
    "sg:classifiers": [
      {
        "category": "Banks \u0026 Credit Unions",
        "subcategory": "Bank",
        "type": "Services"
      }
    ],
    "sg:phone": "+1 937 433 3773",
    "sg:postcode": "45459",
    "sg:province": "OH",
    "sg:tags": [
      "national",
      "commercial"
    ],
    "wof:name": "National City Bank",
    "wof:placetype": "venue"
  },
  "geometry": {"coordinates":[-84.137391,39.628395],"type":"Point"}
}
