{
  "type": "Feature",
  "properties": {
    "iso:country":"US",
    "sg:address":"470 Center St",
    "sg:city":"Chardon",
    "sg:classifiers":[
        {
            "category":"Government",
            "subcategory":"Office",
            "type":"Public Place"
        }
    ],
    "sg:phone":"+1 440 285 2222",
    "sg:postcode":"44024",
    "sg:province":"OH",
    "sg:tags":[
        "executive"
    ],
    "wof:name":"County of Geauga",
    "wof:placetype":"venue"
},
  "geometry": {"coordinates":[-81.222741,41.589558],"type":"Point"}
}