{
  "type": "Feature",
  "properties": {
    "addr:full": "4100 Simpson Ave Cincinnati OH 45227",
    "addr:housenumber": "4100",
    "addr:postcode": "45227",
    "addr:street": "Simpson Ave",
    "iso:country": "US",
    "sg:address": "4100 Simpson Ave",
    "sg:city": "Cincinnati",
    "sg:classifiers": [
      {
        "category": "Education",
        "subcategory": "School",
        "type": "Public Place"
      }
    ],
    "sg:phone": "+1 513 271 8288",
    "sg:postcode": "45227",
    "sg:province": "OH",
    "sg:tags": [
      "religious"
    ],
    "sg:website": "www.princeofpeacecincinnati.org",
    "wof:name": "Prince Of Peace Catholic Schl",
    "wof:placetype": "venue"
  },
  "geometry": {"coordinates":[-84.390542,39.150573],"type":"Point"}
}
