{
  "type": "Feature",
  "properties": {
    "addr:full": "34560 Twp Rd 366 Pomeroy OH 45769",
    "addr:housenumber": "366",
    "addr:postcode": "34560;45769",
    "addr:street": "Twp Rd",
    "iso:country": "US",
    "sg:address": "34560 Twp Rd 366",
    "sg:city": "Pomeroy",
    "sg:classifiers": [
      {
        "category": "Professional",
        "subcategory": "Advertising",
        "type": "Services"
      }
    ],
    "sg:phone": "+1 740 992 1815",
    "sg:postcode": "45769",
    "sg:province": "OH",
    "sg:tags": [
      "counselor"
    ],
    "wof:name": "Felcon Design \u0026 Marketing",
    "wof:placetype": "venue"
  },
  "geometry": {"coordinates":[-82.095801,39.070272],"type":"Point"}
}
