{
  "type": "Feature",
  "properties": {
    "iso:country":"US",
    "sg:address":"34560 Twp Rd 366",
    "sg:city":"Pomeroy",
    "sg:classifiers":[
        {
            "category":"Professional",
            "subcategory":"Advertising",
            "type":"Services"
        }
    ],
    "sg:phone":"+1 740 992 1815",
    "sg:postcode":"45769",
    "sg:province":"OH",
    "sg:tags":[
        "counselor"
    ],
    "wof:name":"Felcon Design & Marketing",
    "wof:placetype":"venue"
},
  "geometry": {"coordinates":[-82.09580099999999,39.070272],"type":"Point"}
}