{
  "type": "Feature",
  "properties": {
    "iso:country":"US",
    "sg:address":"2131 Park Ave W",
    "sg:city":"Mansfield",
    "sg:classifiers":[
        {
            "category":"Home & Garden",
            "subcategory":"Furniture",
            "type":"Retail Goods"
        }
    ],
    "sg:phone":"+1 419 529 9887",
    "sg:postcode":"44906",
    "sg:province":"OH",
    "wof:name":"Erich's Lawn Furniture LTD",
    "wof:placetype":"venue"
},
  "geometry": {"coordinates":[-82.59119,40.759663],"type":"Point"}
}