{
  "type": "Feature",
  "properties": {
    "addr:full": "2131 Park Ave W Mansfield OH 44906",
    "addr:housenumber": "2131",
    "addr:postcode": "44906",
    "addr:street": "Park Ave W",
    "iso:country": "US",
    "sg:address": "2131 Park Ave W",
    "sg:city": "Mansfield",
    "sg:classifiers": [
      {
        "category": "Home \u0026 Garden",
        "subcategory": "Furniture",
        "type": "Retail Goods"
      }
    ],
    "sg:phone": "+1 419 529 9887",
    "sg:postcode": "44906",
    "sg:province": "OH",
    "wof:name": "Erich's Lawn Furniture LTD",
    "wof:placetype": "venue"
  },
  "geometry": {"coordinates":[-82.59119,40.759663],"type":"Point"}
}
