{
  "type": "Feature",
  "properties": {
    "addr:full": "8800 Governors Hill Dr Cincinnati OH 45249",
    "addr:housenumber": "8800",
    "addr:postcode": "45249",
    "addr:street": "Governors Hill Dr",
    "iso:country": "US",
    "sg:address": "8800 Governors Hill Dr",
    "sg:city": "Cincinnati",
    "sg:classifiers": [
      {
        "category": "Education",
        "subcategory": "Special Training",
        "type": "Public Place"
      },
      {
        "category": "Education",
        "subcategory": "Vocational School",
        "type": "Public Place"
      },
      {
        "category": "Education",
        "subcategory": "University",
        "type": "Public Place"
      },
      {
        "category": "Education",
        "subcategory": "School",
        "type": "Public Place"
      }
    ],
    "sg:phone": "+1 877 268 3879",
    "sg:postcode": "45249",
    "sg:province": "OH",
    "sg:tags": [
      "college",
      "adult",
      "business"
    ],
    "sg:website": "http://www.kelleradvantage.com/landing36/index.html?vc=167328",
    "wof:name": "Keller Graduate School of Management",
    "wof:placetype": "venue"
  },
  "geometry": {"coordinates":[-84.319816,39.287974],"type":"Point"}
}
