{
  "type": "Feature",
  "properties": {
    "addr:full":"3215 Elida Rd Lima OH 45805",
    "addr:housenumber":"3215",
    "addr:postcode":"45805",
    "addr:street":"Elida Rd",
    "iso:country":"US",
    "sg:address":"3215 Elida Rd",
    "sg:city":"Lima",
    "sg:classifiers":[
        {
            "category":"Shopping",
            "type":"Retail Goods"
        }
    ],
    "sg:phone":"+1 419 331 9596",
    "sg:postcode":"45805",
    "sg:province":"OH",
    "sg:tags":[
        "merchandise"
    ],
    "wof:name":"Sprint Spectrum LP",
    "wof:placetype":"venue"
},
  "geometry": {"coordinates":[-84.16340700000001,40.769365],"type":"Point"}
}