{
  "type": "Feature",
  "properties": {
    "addr:full": "30441 Euclid Ave Wickliffe OH 44092",
    "addr:housenumber": "30441",
    "addr:postcode": "44092",
    "addr:street": "Euclid Ave",
    "iso:country": "US",
    "sg:address": "30441 Euclid Ave",
    "sg:city": "Wickliffe",
    "sg:classifiers": [
      {
        "category": "Restaurant",
        "type": "Food \u0026 Drink"
      }
    ],
    "sg:menulink": "http://www.allmenus.com/oh/wickliffe/17142-guiseppes-pizza--subs/menu/",
    "sg:phone": "+1 440 944 9300",
    "sg:postcode": "44092",
    "sg:province": "OH",
    "sg:tags": [
      "american",
      "pizza"
    ],
    "wof:name": "Guiseppe's Pizza \u0026 Subs",
    "wof:placetype": "venue"
  },
  "geometry": {"coordinates":[-81.457962,41.618272],"type":"Point"}
}
