{
  "type": "Feature",
  "properties": {
    "addr:full": "3025 N Summit St Toledo OH 43611",
    "addr:housenumber": "3025",
    "addr:postcode": "43611",
    "addr:street": "N Summit St",
    "iso:country": "US",
    "sg:address": "3025 N Summit St",
    "sg:city": "Toledo",
    "sg:classifiers": [
      {
        "category": "Restaurant",
        "type": "Food \u0026 Drink"
      }
    ],
    "sg:phone": "+1 419 729 9775",
    "sg:postcode": "43611",
    "sg:province": "OH",
    "sg:tags": [
      "drinking",
      "eating"
    ],
    "wof:name": "Fritz \u0026 Alfredo's",
    "wof:placetype": "venue"
  },
  "geometry": {"coordinates":[-83.49541,41.679593],"type":"Point"}
}
