{
  "type": "Feature",
  "properties": {
    "iso:country":"US",
    "sg:address":"6076 Branch Hill-Guinea Pike",
    "sg:city":"Milford",
    "sg:classifiers":[
        {
            "category":"Retail",
            "subcategory":"Laundry & Dry Cleaning",
            "type":"Services"
        }
    ],
    "sg:phone":"+1 513 575 5510",
    "sg:postcode":"45150",
    "sg:province":"OH",
    "wof:name":"Pro Master Carpet Care",
    "wof:placetype":"venue"
},
  "geometry": {"coordinates":[-84.224498,39.205341],"type":"Point"}
}