{
  "type": "Feature",
  "properties": {
    "iso:country":"US",
    "sg:address":"3951 W Sylvania Ave",
    "sg:city":"Toledo",
    "sg:classifiers":[
        {
            "category":"Health Services",
            "subcategory":"Doctor",
            "type":"Services"
        }
    ],
    "sg:phone":"+1 419 475 6673",
    "sg:postcode":"43623",
    "sg:province":"OH",
    "sg:tags":[
        "dentist"
    ],
    "wof:name":"Frogameni Deborah L",
    "wof:placetype":"venue"
},
  "geometry": {"coordinates":[-83.644214,41.691117],"type":"Point"}
}