{
  "type": "Feature",
  "properties": {
    "addr:full":"587 State Rte 60 Greenwich OH 44837",
    "addr:housenumber":"587",
    "addr:postcode":"44837",
    "addr:street":"State Rte 60",
    "iso:country":"US",
    "sg:address":"587 State Rte 60",
    "sg:city":"Greenwich",
    "sg:classifiers":[
        {
            "category":"Building & Trades",
            "subcategory":"Landscaping Services",
            "type":"Services"
        }
    ],
    "sg:phone":"+1 419 207 0611",
    "sg:postcode":"44837",
    "sg:province":"OH",
    "sg:tags":[
        "landscape",
        "contractor"
    ],
    "wof:name":"C C Ward Landscaping",
    "wof:placetype":"venue"
},
  "geometry": {"coordinates":[-82.36743199999999,40.977455],"type":"Point"}
}