{
  "type": "Feature",
  "properties": {
    "iso:country":"US",
    "sg:address":"50 E Mulberry St",
    "sg:city":"Lebanon",
    "sg:classifiers":[
        {
            "category":"Shopping",
            "subcategory":"Computers & Home Electronics",
            "type":"Retail Goods"
        }
    ],
    "sg:phone":"+1 513 933 9393",
    "sg:postcode":"45036",
    "sg:province":"OH",
    "sg:tags":[
        "audio"
    ],
    "wof:name":"Extreme Audio & Video",
    "wof:placetype":"venue"
},
  "geometry": {"coordinates":[-84.207332,39.434453],"type":"Point"}
}