{
  "type": "Feature",
  "properties": {
    "addr:full": "11774 W US Rte 36 Bradford OH 45308",
    "addr:housenumber": "11774",
    "addr:postcode": "45308",
    "addr:street": "W Us Rte 36",
    "iso:country": "US",
    "sg:address": "11774 W US Rte 36",
    "sg:city": "Bradford",
    "sg:classifiers": [
      {
        "category": "Autos \u0026 Motor Vehicles",
        "subcategory": "Automobile Sales",
        "type": "Retail Goods"
      }
    ],
    "sg:phone": "+1 937 448 2974",
    "sg:postcode": "45308",
    "sg:province": "OH",
    "sg:tags": [
      "car",
      "use",
      "sale"
    ],
    "wof:name": "Recks Used Cars",
    "wof:placetype": "venue"
  },
  "geometry": {"coordinates":[-84.425901,40.115898],"type":"Point"}
}
