{
  "type": "Feature",
  "properties": {
    "addr:full": "3653 Darrow Rd Stow OH 44224",
    "addr:housenumber": "3653",
    "addr:postcode": "44224",
    "addr:street": "Darrow Rd",
    "iso:country": "US",
    "sg:address": "3653 Darrow Rd",
    "sg:city": "Stow",
    "sg:classifiers": [
      {
        "category": "Personal",
        "type": "Services"
      }
    ],
    "sg:phone": "+1 330 686 0127",
    "sg:postcode": "44224",
    "sg:province": "OH",
    "sg:tags": [
      "therapist",
      "massage"
    ],
    "wof:name": "Sullivan Massotherapy",
    "wof:placetype": "venue"
  },
  "geometry": {"coordinates":[-81.440313,41.161796],"type":"Point"}
}
