{
  "type": "Feature",
  "properties": {
    "addr:full":"7500 Buffham Rd Seville OH 44273",
    "addr:housenumber":"7500",
    "addr:postcode":"44273",
    "addr:street":"Buffham Rd",
    "iso:country":"US",
    "sg:address":"7500 Buffham Rd",
    "sg:city":"Seville",
    "sg:classifiers":[
        {
            "category":"Education",
            "subcategory":"School",
            "type":"Public Place"
        }
    ],
    "sg:phone":"+1 330 948 2500",
    "sg:postcode":"44273",
    "sg:province":"OH",
    "wof:name":"Cloverleaf Middle School",
    "wof:placetype":"venue"
},
  "geometry": {"coordinates":[-81.95913299999999,41.041477],"type":"Point"}
}