{
  "type": "Feature",
  "properties": {
    "iso:country":"US",
    "sg:address":"26420 Lakeland Blvd",
    "sg:city":"Cleveland",
    "sg:classifiers":[
        {
            "category":"Local Transit",
            "type":"Transportation"
        }
    ],
    "sg:phone":"+1 216 797 4000",
    "sg:postcode":"44132",
    "sg:province":"OH",
    "sg:tags":[
        "ambulance"
    ],
    "wof:name":"Hillcrest Ambulance Svc Inc",
    "wof:placetype":"venue"
},
  "geometry": {"coordinates":[-81.494742,41.603567],"type":"Point"}
}