{
  "type": "Feature",
  "properties": {
    "addr:full":"4439 Midway Mall Elyria OH 44035",
    "addr:housenumber":"4439",
    "addr:postcode":"44035",
    "addr:street":"Midway Mall",
    "iso:country":"US",
    "sg:address":"4439 Midway Mall",
    "sg:city":"Elyria",
    "sg:classifiers":[
        {
            "category":"Shopping",
            "subcategory":"Shoes",
            "type":"Retail Goods"
        },
        {
            "category":"Shopping",
            "subcategory":"Clothing, Apparel, & Fashions",
            "type":"Retail Goods"
        }
    ],
    "sg:phone":"+1 440 324 2692",
    "sg:postcode":"44035",
    "sg:province":"OH",
    "sg:tags":[
        "athletic",
        "leisure",
        "accessory",
        "footwear",
        "active",
        "sportswear",
        "wear"
    ],
    "wof:name":"Finish Line",
    "wof:placetype":"venue"
},
  "geometry": {"coordinates":[-82.113527,41.398613],"type":"Point"}
}