{
  "type": "Feature",
  "properties": {
    "iso:country":"US",
    "sg:address":"211 S Main St",
    "sg:city":"Dayton",
    "sg:classifiers":[
        {
            "category":"Real Estate",
            "subcategory":"Real Estate Agent",
            "type":"Services"
        }
    ],
    "sg:phone":"+1 937 228 3961",
    "sg:postcode":"45402",
    "sg:province":"OH",
    "wof:name":"Hutchins Commercial Realty LTD",
    "wof:placetype":"venue"
},
  "geometry": {"coordinates":[-84.190798,39.755542],"type":"Point"}
}