{
  "type": "Feature",
  "properties": {
    "addr:full": "35 E Park St Fort Loramie OH 45845",
    "addr:housenumber": "35",
    "addr:postcode": "45845",
    "addr:street": "E Park St",
    "iso:country": "US",
    "sg:address": "35 E Park St",
    "sg:city": "Fort Loramie",
    "sg:classifiers": [
      {
        "category": "Real Estate",
        "subcategory": "Real Estate Operator",
        "type": "Services"
      }
    ],
    "sg:phone": "+1 937 295 3319",
    "sg:postcode": "45845",
    "sg:province": "OH",
    "sg:tags": [
      "property",
      "lessor"
    ],
    "wof:name": "Louis Hilgefort",
    "wof:placetype": "venue"
  },
  "geometry": {"coordinates":[-84.373578,40.349832],"type":"Point"}
}
