{
  "type": "Feature",
  "properties": {
    "addr:full":"3200 Madison Rd Cincinnati OH 45209",
    "addr:housenumber":"3200",
    "addr:postcode":"45209",
    "addr:street":"Madison Rd",
    "iso:country":"US",
    "sg:address":"3200 Madison Rd",
    "sg:city":"Cincinnati",
    "sg:classifiers":[
        {
            "category":"Restaurant",
            "type":"Food & Drink"
        }
    ],
    "sg:menulink":"http://www.allmenus.com/oh/cincinnati/269100-boca-cincinnati/menu/",
    "sg:phone":"+1 513 542 2022",
    "sg:postcode":"45209",
    "sg:province":"OH",
    "sg:tags":[
        "italian"
    ],
    "wof:name":"Boca Cincinnati",
    "wof:placetype":"venue"
},
  "geometry": {"coordinates":[-84.42743,39.155068],"type":"Point"}
}