{
  "type": "Feature",
  "properties": {
    "iso:country":"US",
    "sg:address":"7498 Broadview Rd",
    "sg:city":"Cleveland",
    "sg:classifiers":[
        {
            "category":"Autos & Motor Vehicles",
            "subcategory":"Fuel & Gas Station",
            "type":"Retail Goods"
        }
    ],
    "sg:phone":"+1 216 642 1175",
    "sg:postcode":"44134",
    "sg:province":"OH",
    "sg:tags":[
        "station",
        "gasoline",
        "oil"
    ],
    "sg:website":"www.hollandoil.com",
    "wof:name":"Holland Oil Company",
    "wof:placetype":"venue"
},
  "geometry": {"coordinates":[-81.68467,41.363075],"type":"Point"}
}