{
  "type": "Feature",
  "properties": {
    "iso:country":"US",
    "sg:address":"199 S Village Dr",
    "sg:city":"Dayton",
    "sg:classifiers":[
        {
            "category":"Home & Garden",
            "subcategory":"Home Furnishings",
            "type":"Retail Goods"
        }
    ],
    "sg:phone":"+1 937 291 2037",
    "sg:postcode":"45459",
    "sg:province":"OH",
    "wof:name":"Joan E Trent",
    "wof:placetype":"venue"
},
  "geometry": {"coordinates":[-84.15360099999999,39.65401],"type":"Point"}
}