{
  "type": "Feature",
  "properties": {
    "addr:full":"6914 Plainfield Rd Cincinnati OH 45236",
    "addr:housenumber":"6914",
    "addr:postcode":"45236",
    "addr:street":"Plainfield Rd",
    "iso:country":"US",
    "sg:address":"6914 Plainfield Rd",
    "sg:city":"Cincinnati",
    "sg:classifiers":[
        {
            "category":"Home & Garden",
            "subcategory":"Building Materials",
            "type":"Retail Goods"
        }
    ],
    "sg:phone":"+1 513 794 0007",
    "sg:postcode":"45236",
    "sg:province":"OH",
    "sg:tags":[
        "plasterboard",
        "wallboard"
    ],
    "wof:name":"Archcraft Products Inc",
    "wof:placetype":"venue"
},
  "geometry": {"coordinates":[-84.400294,39.195575],"type":"Point"}
}