{
  "type": "Feature",
  "properties": {
    "iso:country":"US",
    "sg:address":"2 River Pl",
    "sg:city":"Dayton",
    "sg:classifiers":[
        {
            "category":"Professional",
            "subcategory":"Engineering",
            "type":"Services"
        }
    ],
    "sg:phone":"+1 937 228 4141",
    "sg:postcode":"45405",
    "sg:province":"OH",
    "sg:tags":[
        "water",
        "treatment",
        "engineer"
    ],
    "sg:website":"www.danisbuilding.com",
    "wof:name":"Danis Environmental Industries",
    "wof:placetype":"venue"
},
  "geometry": {"coordinates":[-84.191384,39.766726],"type":"Point"}
}