{
  "type": "Feature",
  "properties": {
    "iso:country":"US",
    "sg:address":"2401 Gilbert Ave",
    "sg:city":"Cincinnati",
    "sg:classifiers":[
        {
            "category":"Restaurant",
            "type":"Food & Drink"
        }
    ],
    "sg:phone":"+1 513 559 0926",
    "sg:postcode":"45206",
    "sg:province":"OH",
    "sg:tags":[
        "eating"
    ],
    "wof:name":"Z ZS Pizza Company",
    "wof:placetype":"venue"
},
  "geometry": {"coordinates":[-84.490918,39.124899],"type":"Point"}
}