{
  "type": "Feature",
  "properties": {
    "addr:full": "11258 Lebanon Rd Cincinnati OH 45241",
    "addr:housenumber": "11258",
    "addr:postcode": "45241",
    "addr:street": "Lebanon Rd",
    "iso:country": "US",
    "sg:address": "11258 Lebanon Rd",
    "sg:city": "Cincinnati",
    "sg:classifiers": [
      {
        "category": "Health Services",
        "subcategory": "Doctor",
        "type": "Services"
      }
    ],
    "sg:phone": "+1 513 563 0044",
    "sg:postcode": "45241",
    "sg:province": "OH",
    "sg:tags": [
      "physician",
      "surgeon",
      "medical"
    ],
    "wof:name": "Liberty Sharonville Pediatrics",
    "wof:placetype": "venue"
  },
  "geometry": {"coordinates":[-84.409281,39.277261],"type":"Point"}
}
