{
  "type": "Feature",
  "properties": {
    "iso:country":"US",
    "sg:address":"102 Rogers Pkwy",
    "sg:city":"Chillicothe",
    "sg:classifiers":[
        {
            "category":"Organizations",
            "subcategory":"Religious Organization",
            "type":"Services"
        }
    ],
    "sg:phone":"+1 740 774 3635",
    "sg:postcode":"45601",
    "sg:province":"OH",
    "sg:tags":[
        "clergy"
    ],
    "wof:name":"Harlan W Alspach",
    "wof:placetype":"venue"
},
  "geometry": {"coordinates":[-82.980875,39.355105],"type":"Point"}
}