{
  "type": "Feature",
  "properties": {
    "addr:full":"2525 State Rte 18 Tiffin OH 44883",
    "addr:housenumber":"2525",
    "addr:postcode":"44883",
    "addr:street":"State Rte 18",
    "iso:country":"US",
    "sg:address":"2525 State Rte 18",
    "sg:city":"Tiffin",
    "sg:classifiers":[
        {
            "category":"Wholesale",
            "subcategory":"Durable Goods & Equipment",
            "type":"Manufacturing & Wholesale Goods"
        }
    ],
    "sg:phone":"+1 419 447 2141",
    "sg:postcode":"44883",
    "sg:province":"OH",
    "sg:tags":[
        "representative",
        "manufacturer"
    ],
    "wof:name":"Ernst & Corp",
    "wof:placetype":"venue"
},
  "geometry": {"coordinates":[-83.21913499999999,41.109226],"type":"Point"}
}