{
  "type": "Feature",
  "properties": {
    "addr:full": "417 Boardman Poland Rd Youngstown OH 44512",
    "addr:housenumber": "417",
    "addr:postcode": "44512",
    "addr:street": "Boardman Poland Rd",
    "iso:country": "US",
    "sg:address": "417 Boardman Poland Rd",
    "sg:city": "Youngstown",
    "sg:classifiers": [
      {
        "category": "Shopping",
        "subcategory": "Department Store",
        "type": "Retail Goods"
      }
    ],
    "sg:phone": "+1 330 758 5930",
    "sg:postcode": "44512",
    "sg:province": "OH",
    "wof:name": "Target",
    "wof:placetype": "venue"
  },
  "geometry": {"coordinates":[-80.645544,41.024227],"type":"Point"}
}
