{
  "type": "Feature",
  "properties": {
    "iso:country":"US",
    "sg:address":"2074 Abington Rd",
    "sg:city":"Cleveland",
    "sg:classifiers":[
        {
            "category":"Health Services",
            "subcategory":"Doctor",
            "type":"Services"
        }
    ],
    "sg:phone":"+1 216 844 7438",
    "sg:postcode":"44106",
    "sg:province":"OH",
    "sg:tags":[
        "physician",
        "surgeon"
    ],
    "wof:name":"Myung Lee MD",
    "wof:placetype":"venue"
},
  "geometry": {"coordinates":[-81.605114,41.505762],"type":"Point"}
}