{
  "type": "Feature",
  "properties": {
    "iso:country":"US",
    "sg:address":"19035 Detroit Rd",
    "sg:city":"Cleveland",
    "sg:classifiers":[
        {
            "category":"Professional",
            "subcategory":"Management & Consulting",
            "type":"Services"
        }
    ],
    "sg:phone":"+1 440 331 6600",
    "sg:postcode":"44116",
    "sg:province":"OH",
    "sg:tags":[
        "communications",
        "consultant"
    ],
    "wof:name":"Old River Publications LLC",
    "wof:placetype":"venue"
},
  "geometry": {"coordinates":[-81.834486,41.482629],"type":"Point"}
}