{
  "type": "Feature",
  "properties": {
    "addr:full": "19035 Detroit Rd Cleveland OH 44116",
    "addr:housenumber": "19035",
    "addr:postcode": "44116",
    "addr:street": "Detroit Rd",
    "iso:country": "US",
    "sg:address": "19035 Detroit Rd",
    "sg:city": "Cleveland",
    "sg:classifiers": [
      {
        "category": "Professional",
        "subcategory": "Management \u0026 Consulting",
        "type": "Services"
      }
    ],
    "sg:phone": "+1 440 331 6600",
    "sg:postcode": "44116",
    "sg:province": "OH",
    "sg:tags": [
      "communications",
      "consultant"
    ],
    "wof:name": "Old River Publications LLC",
    "wof:placetype": "venue"
  },
  "geometry": {"coordinates":[-81.834486,41.482629],"type":"Point"}
}
