{
  "type": "Feature",
  "properties": {
    "addr:full": "2512 Long St Hamilton OH 45014",
    "addr:housenumber": "2512",
    "addr:postcode": "45014",
    "addr:street": "Long St",
    "iso:country": "US",
    "sg:address": "2512 Long St",
    "sg:city": "Hamilton",
    "sg:classifiers": [
      {
        "category": "Utilities",
        "type": "Services"
      }
    ],
    "sg:phone": "+1 513 738 4161",
    "sg:postcode": "45014",
    "sg:province": "OH",
    "sg:tags": [
      "sweeping"
    ],
    "wof:name": "P K Pressure Kleen",
    "wof:placetype": "venue"
  },
  "geometry": {"coordinates":[-84.649114,39.31201],"type":"Point"}
}
