{
  "type": "Feature",
  "properties": {
    "addr:full":"7374 E Main St Reynoldsburg OH 43068",
    "addr:housenumber":"7374",
    "addr:postcode":"43068",
    "addr:street":"E Main St",
    "iso:country":"US",
    "sg:address":"7374 E Main St",
    "sg:city":"Reynoldsburg",
    "sg:classifiers":[
        {
            "category":"Insurance",
            "subcategory":"Insurance Agent",
            "type":"Services"
        }
    ],
    "sg:phone":"+1 614 863 9566",
    "sg:postcode":"43068",
    "sg:province":"OH",
    "wof:name":"Farmers Insurance Group",
    "wof:placetype":"venue"
},
  "geometry": {"coordinates":[-82.802162,39.955342],"type":"Point"}
}