{
  "type": "Feature",
  "properties": {
    "iso:country":"US",
    "sg:address":"3107 Dorr St",
    "sg:city":"Toledo",
    "sg:classifiers":[
        {
            "category":"Autos & Motor Vehicles",
            "subcategory":"Automobile Sales",
            "type":"Retail Goods"
        }
    ],
    "sg:phone":"+1 419 537 0100",
    "sg:postcode":"43607",
    "sg:province":"OH",
    "sg:tags":[
        "car",
        "dealer"
    ],
    "wof:name":"Mac's Motors",
    "wof:placetype":"venue"
},
  "geometry": {"coordinates":[-83.617084,41.65279],"type":"Point"}
}