{
  "type": "Feature",
  "properties": {
    "addr:full": "3107 Dorr St Toledo OH 43607",
    "addr:postcode": "3107;43607",
    "addr:street": "Dorr St",
    "iso:country": "US",
    "sg:address": "3107 Dorr St",
    "sg:city": "Toledo",
    "sg:classifiers": [
      {
        "category": "Autos \u0026 Motor Vehicles",
        "subcategory": "Automobile Sales",
        "type": "Retail Goods"
      }
    ],
    "sg:phone": "+1 419 537 0100",
    "sg:postcode": "43607",
    "sg:province": "OH",
    "sg:tags": [
      "car",
      "dealer"
    ],
    "wof:name": "Mac's Motors",
    "wof:placetype": "venue"
  },
  "geometry": {"coordinates":[-83.617084,41.65279],"type":"Point"}
}
