{
  "type": "Feature",
  "properties": {
    "addr:full": "1688 State Rte 749 Amelia OH 45102",
    "addr:housenumber": "1688",
    "addr:postcode": "45102",
    "addr:street": "State Rte 749",
    "iso:country": "US",
    "sg:address": "1688 State Rte 749",
    "sg:city": "Amelia",
    "sg:classifiers": [
      {
        "category": "Manufacturing",
        "subcategory": "Rubber \u0026 Plastics",
        "type": "Manufacturing \u0026 Wholesale Goods"
      }
    ],
    "sg:phone": "+1 513 797 5570",
    "sg:postcode": "45102",
    "sg:province": "OH",
    "sg:tags": [
      "supply"
    ],
    "wof:name": "G \u0026 G Products Co",
    "wof:placetype": "venue"
  },
  "geometry": {"coordinates":[-84.222712,38.993214],"type":"Point"}
}
