{
  "type": "Feature",
  "properties": {
    "iso:country":"US",
    "sg:address":"1811 Hayden Ave",
    "sg:city":"Cleveland",
    "sg:classifiers":[
        {
            "category":"Food & Beverages",
            "subcategory":"Groceries & Convenience Stores",
            "type":"Retail Goods"
        }
    ],
    "sg:phone":"+1 216 249 2832",
    "sg:postcode":"44112",
    "sg:province":"OH",
    "sg:tags":[
        "grocer"
    ],
    "wof:name":"Brothers & Sisters",
    "wof:placetype":"venue"
},
  "geometry": {"coordinates":[-81.58865900000001,41.530063],"type":"Point"}
}