{
  "type": "Feature",
  "properties": {
    "addr:full": "1811 Hayden Ave Cleveland OH 44112",
    "addr:housenumber": "1811",
    "addr:postcode": "44112",
    "addr:street": "Hayden Ave",
    "iso:country": "US",
    "sg:address": "1811 Hayden Ave",
    "sg:city": "Cleveland",
    "sg:classifiers": [
      {
        "category": "Food \u0026 Beverages",
        "subcategory": "Groceries \u0026 Convenience Stores",
        "type": "Retail Goods"
      }
    ],
    "sg:phone": "+1 216 249 2832",
    "sg:postcode": "44112",
    "sg:province": "OH",
    "sg:tags": [
      "grocer"
    ],
    "wof:name": "Brothers \u0026 Sisters",
    "wof:placetype": "venue"
  },
  "geometry": {"coordinates":[-81.588659,41.530063],"type":"Point"}
}
