{
  "type": "Feature",
  "properties": {
    "iso:country":"US",
    "sg:address":"3000 E Livingston Ave",
    "sg:city":"Columbus",
    "sg:classifiers":[
        {
            "category":"Autos & Motor Vehicles",
            "subcategory":"Automobile Sales",
            "type":"Retail Goods"
        }
    ],
    "sg:phone":"+1 614 235 0077",
    "sg:postcode":"43209",
    "sg:province":"OH",
    "sg:tags":[
        "used"
    ],
    "wof:name":"J & L Used Cars",
    "wof:placetype":"venue"
},
  "geometry": {"coordinates":[-82.916155,39.94698],"type":"Point"}
}