{
  "type": "Feature",
  "properties": {
    "addr:full": "608 Morgan Ave Mansfield OH 44905",
    "addr:housenumber": "608",
    "addr:postcode": "44905",
    "addr:street": "Morgan Ave",
    "iso:country": "US",
    "sg:address": "608 Morgan Ave",
    "sg:city": "Mansfield",
    "sg:classifiers": [
      {
        "category": "Retail",
        "subcategory": "Repair Shop",
        "type": "Services"
      }
    ],
    "sg:phone": "+1 419 525 0059",
    "sg:postcode": "44905",
    "sg:province": "OH",
    "sg:tags": [
      "plumbing",
      "drain",
      "cleaning",
      "sewer"
    ],
    "wof:name": "Jim's Sewer \u0026 Drain Cleaning",
    "wof:placetype": "venue"
  },
  "geometry": {"coordinates":[-82.492679,40.788502],"type":"Point"}
}
