{
  "type": "Feature",
  "properties": {
    "iso:country":"US",
    "sg:address":"4968 Darrow Rd",
    "sg:city":"Stow",
    "sg:classifiers":[
        {
            "category":"Restaurant",
            "type":"Food & Drink"
        }
    ],
    "sg:menulink":"http://www.allmenus.com/oh/stow/134616-subway/menu/",
    "sg:phone":"+1 330 655 2400",
    "sg:postcode":"44224",
    "sg:province":"OH",
    "sg:tags":[
        "american",
        "sandwich"
    ],
    "wof:name":"Subway",
    "wof:placetype":"venue"
},
  "geometry": {"coordinates":[-81.44040699999999,41.200873],"type":"Point"}
}