{
  "type": "Feature",
  "properties": {
    "addr:full": "4968 Darrow Rd Stow OH 44224",
    "addr:housenumber": "4968",
    "addr:postcode": "44224",
    "addr:street": "Darrow Rd",
    "iso:country": "US",
    "sg:address": "4968 Darrow Rd",
    "sg:city": "Stow",
    "sg:classifiers": [
      {
        "category": "Restaurant",
        "type": "Food \u0026 Drink"
      }
    ],
    "sg:menulink": "http://www.allmenus.com/oh/stow/134616-subway/menu/",
    "sg:phone": "+1 330 655 2400",
    "sg:postcode": "44224",
    "sg:province": "OH",
    "sg:tags": [
      "american",
      "sandwich"
    ],
    "wof:name": "Subway",
    "wof:placetype": "venue"
  },
  "geometry": {"coordinates":[-81.440407,41.200873],"type":"Point"}
}
