{
  "type": "Feature",
  "properties": {
    "iso:country":"US",
    "sg:address":"1348 N Detroit St",
    "sg:city":"Xenia",
    "sg:classifiers":[
        {
            "category":"Wholesale",
            "subcategory":"Groceries",
            "type":"Manufacturing & Wholesale Goods"
        }
    ],
    "sg:phone":"+1 937 372 3205",
    "sg:postcode":"45385",
    "sg:province":"OH",
    "wof:name":"G M Candy Supplies",
    "wof:placetype":"venue"
},
  "geometry": {"coordinates":[-83.93333699999999,39.703603],"type":"Point"}
}