{
  "type": "Feature",
  "properties": {
    "addr:full":"6674 Strip Ave NW North Canton OH 44720",
    "addr:housenumber":"6674",
    "addr:postcode":"44720",
    "addr:street":"Strip Ave Nw",
    "iso:country":"US",
    "sg:address":"6674 Strip Ave NW",
    "sg:city":"North Canton",
    "sg:classifiers":[
        {
            "category":"Shopping",
            "subcategory":"Clothing, Apparel, & Fashions",
            "type":"Retail Goods"
        }
    ],
    "sg:phone":"+1 330 494 8130",
    "sg:postcode":"44720",
    "sg:province":"OH",
    "sg:tags":[
        "furnishing"
    ],
    "wof:name":"Men's Wearhouse",
    "wof:placetype":"venue"
},
  "geometry": {"coordinates":[-81.431904,40.875266],"type":"Point"}
}