{
  "type": "Feature",
  "properties": {
    "addr:full": "574 N Main St Springboro OH 45066",
    "addr:housenumber": "574",
    "addr:postcode": "45066",
    "addr:street": "N Main St",
    "iso:country": "US",
    "sg:address": "574 N Main St",
    "sg:city": "Springboro",
    "sg:classifiers": [
      {
        "category": "Shopping",
        "subcategory": "Computers \u0026 Home Electronics",
        "type": "Retail Goods"
      }
    ],
    "sg:phone": "+1 937 748 8808",
    "sg:postcode": "45066",
    "sg:province": "OH",
    "sg:tags": [
      "software"
    ],
    "sg:website": "www.rent-right.com",
    "wof:name": "Rentright",
    "wof:placetype": "venue"
  },
  "geometry": {"coordinates":[-84.231593,39.56915],"type":"Point"}
}
