{
  "type": "Feature",
  "properties": {
    "addr:full":"63 Douglas St Xenia OH 45385",
    "addr:housenumber":"63",
    "addr:postcode":"45385",
    "addr:street":"Douglas St",
    "iso:country":"US",
    "sg:address":"63 Douglas St",
    "sg:city":"Xenia",
    "sg:classifiers":[
        {
            "category":"Building & Trades",
            "subcategory":"Landscaping Services",
            "type":"Services"
        }
    ],
    "sg:phone":"+1 937 374 7425",
    "sg:postcode":"45385",
    "sg:province":"OH",
    "sg:tags":[
        "tree"
    ],
    "wof:name":"Bill's Tree Svc",
    "wof:placetype":"venue"
},
  "geometry": {"coordinates":[-83.905886,39.68813],"type":"Point"}
}