{
  "type": "Feature",
  "properties": {
    "addr:full":"30963 Pebble Beach Oval Westlake OH 44145",
    "addr:housenumber":"30963",
    "addr:postcode":"44145",
    "addr:street":"Pebble Beach Oval",
    "iso:country":"US",
    "sg:address":"30963 Pebble Beach Oval",
    "sg:city":"Westlake",
    "sg:classifiers":[
        {
            "category":"Insurance",
            "subcategory":"Insurance Agent",
            "type":"Services"
        }
    ],
    "sg:phone":"+1 440 892 9213",
    "sg:postcode":"44145",
    "sg:province":"OH",
    "wof:name":"Donna Stricker",
    "wof:placetype":"venue"
},
  "geometry": {"coordinates":[-81.962974,41.450636],"type":"Point"}
}