{
  "type": "Feature",
  "properties": {
    "addr:full":"5605 Carry Ave Cleveland OH 44103",
    "addr:housenumber":"5605",
    "addr:postcode":"44103",
    "addr:street":"Carry Ave",
    "iso:country":"US",
    "sg:address":"5605 Carry Ave",
    "sg:city":"Cleveland",
    "sg:classifiers":[
        {
            "category":"Building & Trades",
            "subcategory":"Cleaning & Sanitation",
            "type":"Services"
        }
    ],
    "sg:phone":"+1 216 431 4478",
    "sg:postcode":"44103",
    "sg:province":"OH",
    "sg:tags":[
        "janitor"
    ],
    "wof:name":"All Seasons Cleaners Inc",
    "wof:placetype":"venue"
},
  "geometry": {"coordinates":[-81.65016799999999,41.524368],"type":"Point"}
}