{
  "type": "Feature",
  "properties": {
    "addr:full":"17160 W Walbridge East Rd Graytown OH 43432",
    "addr:housenumber":"17160",
    "addr:postcode":"43432",
    "addr:street":"W Walbridge East Rd",
    "iso:country":"US",
    "sg:address":"17160 W Walbridge East Rd",
    "sg:city":"Graytown",
    "sg:classifiers":[
        {
            "category":"Building & Trades",
            "subcategory":"Construction",
            "type":"Services"
        }
    ],
    "sg:phone":"+1 419 862 2498",
    "sg:postcode":"43432",
    "sg:province":"OH",
    "sg:tags":[
        "insulation",
        "heat",
        "contractor"
    ],
    "wof:name":"Efficiency Insulation",
    "wof:placetype":"venue"
},
  "geometry": {"coordinates":[-83.274548,41.589451],"type":"Point"}
}