{
  "type": "Feature",
  "properties": {
    "addr:full": "33902 Lake Shore Blvd Willoughby OH 44095",
    "addr:housenumber": "33902",
    "addr:postcode": "44095",
    "addr:street": "Lake Shore Blvd",
    "iso:country": "US",
    "sg:address": "33902 Lake Shore Blvd",
    "sg:city": "Willoughby",
    "sg:classifiers": [
      {
        "category": "Building \u0026 Trades",
        "subcategory": "Construction",
        "type": "Services"
      }
    ],
    "sg:phone": "+1 440 975 9123",
    "sg:postcode": "44095",
    "sg:province": "OH",
    "sg:tags": [
      "house"
    ],
    "wof:name": "PM Home Improvement",
    "wof:placetype": "venue"
  },
  "geometry": {"coordinates":[-81.454308,41.659121],"type":"Point"}
}
