{
  "type": "Feature",
  "properties": {
    "iso:country":"US",
    "sg:address":"33902 Lake Shore Blvd",
    "sg:city":"Willoughby",
    "sg:classifiers":[
        {
            "category":"Building & Trades",
            "subcategory":"Construction",
            "type":"Services"
        }
    ],
    "sg:phone":"+1 440 975 9123",
    "sg:postcode":"44095",
    "sg:province":"OH",
    "sg:tags":[
        "house"
    ],
    "wof:name":"PM Home Improvement",
    "wof:placetype":"venue"
},
  "geometry": {"coordinates":[-81.454308,41.659121],"type":"Point"}
}