{
  "type": "Feature",
  "properties": {
    "addr:full":"10 Stower Ln Norwalk OH 44857",
    "addr:housenumber":"10",
    "addr:postcode":"44857",
    "addr:street":"Stower Ln",
    "iso:country":"US",
    "sg:address":"10 Stower Ln",
    "sg:city":"Norwalk",
    "sg:classifiers":[
        {
            "category":"Professional",
            "subcategory":"Business Services",
            "type":"Services"
        }
    ],
    "sg:phone":"+1 419 663 4257",
    "sg:postcode":"44857",
    "sg:province":"OH",
    "sg:tags":[
        "broker",
        "merchandise"
    ],
    "wof:name":"Broker One",
    "wof:placetype":"venue"
},
  "geometry": {"coordinates":[-82.608757,41.267121],"type":"Point"}
}