{
  "type": "Feature",
  "properties": {
    "iso:country":"US",
    "sg:address":"499 State Rte 603 W",
    "sg:city":"Shiloh",
    "sg:classifiers":[
        {
            "category":"Organizations",
            "subcategory":"Religious Organization",
            "type":"Services"
        }
    ],
    "sg:phone":"+1 419 896 2309",
    "sg:postcode":"44878",
    "sg:province":"OH",
    "sg:tags":[
        "church"
    ],
    "wof:name":"Rome Community Church",
    "wof:placetype":"venue"
},
  "geometry": {"coordinates":[-82.533753,40.928215],"type":"Point"}
}