{
  "type": "Feature",
  "properties": {
    "addr:full": "4401 Lefferson Rd Middletown OH 45044",
    "addr:housenumber": "4401",
    "addr:postcode": "45044",
    "addr:street": "Lefferson Rd",
    "iso:country": "US",
    "sg:address": "4401 Lefferson Rd",
    "sg:city": "Middletown",
    "sg:classifiers": [
      {
        "category": "Wholesale",
        "subcategory": "Hardware",
        "type": "Manufacturing \u0026 Wholesale Goods"
      }
    ],
    "sg:phone": "+1 513 727 1963",
    "sg:postcode": "45044",
    "sg:province": "OH",
    "sg:tags": [
      "fastener"
    ],
    "wof:name": "Ziegler's Bolt \u0026 Nut House",
    "wof:placetype": "venue"
  },
  "geometry": {"coordinates":[-84.355002,39.489421],"type":"Point"}
}
