{
  "type": "Feature",
  "properties": {
    "iso:country":"US",
    "sg:address":"4401 Lefferson Rd",
    "sg:city":"Middletown",
    "sg:classifiers":[
        {
            "category":"Wholesale",
            "subcategory":"Hardware",
            "type":"Manufacturing & Wholesale Goods"
        }
    ],
    "sg:phone":"+1 513 727 1963",
    "sg:postcode":"45044",
    "sg:province":"OH",
    "sg:tags":[
        "fastener"
    ],
    "wof:name":"Ziegler's Bolt & Nut House",
    "wof:placetype":"venue"
},
  "geometry": {"coordinates":[-84.355002,39.489421],"type":"Point"}
}