{
  "type": "Feature",
  "properties": {
    "addr:full":"809 Sunset View Blvd Tallmadge OH 44278",
    "addr:housenumber":"809",
    "addr:postcode":"44278",
    "addr:street":"Sunset View Blvd",
    "iso:country":"US",
    "sg:address":"809 Sunset View Blvd",
    "sg:city":"Tallmadge",
    "sg:classifiers":[
        {
            "category":"Building & Trades",
            "subcategory":"Plumbing",
            "type":"Services"
        }
    ],
    "sg:phone":"+1 330 633 4015",
    "sg:postcode":"44278",
    "sg:province":"OH",
    "sg:tags":[
        "contractor"
    ],
    "wof:name":"Wasson & Co",
    "wof:placetype":"venue"
},
  "geometry": {"coordinates":[-81.426408,41.079268],"type":"Point"}
}