{
  "type": "Feature",
  "properties": {
    "addr:full":"1048 Wheeling Ave Cambridge OH 43725",
    "addr:housenumber":"1048",
    "addr:postcode":"43725",
    "addr:street":"Wheeling Ave",
    "iso:country":"US",
    "sg:address":"1048 Wheeling Ave",
    "sg:city":"Cambridge",
    "sg:classifiers":[
        {
            "category":"Organizations",
            "subcategory":"Community Association",
            "type":"Services"
        }
    ],
    "sg:phone":"+1 740 432 2100",
    "sg:postcode":"43725",
    "sg:province":"OH",
    "sg:tags":[
        "fraternal"
    ],
    "wof:name":"Elks Lodge",
    "wof:placetype":"venue"
},
  "geometry": {"coordinates":[-81.5857,40.02466],"type":"Point"}
}