{
  "type": "Feature",
  "properties": {
    "addr:full":"1290 N Warpole St Upper Sandusky OH 43351",
    "addr:housenumber":"1290",
    "addr:postcode":"43351",
    "addr:street":"N Warpole St",
    "iso:country":"US",
    "sg:address":"1290 N Warpole St",
    "sg:city":"Upper Sandusky",
    "sg:classifiers":[
        {
            "category":"Ice Cream",
            "type":"Food & Drink"
        }
    ],
    "sg:menulink":"http://www.allmenus.com/oh/crane/175659-dairy-queen/menu/",
    "sg:phone":"+1 419 294 3022",
    "sg:postcode":"43351",
    "sg:province":"OH",
    "sg:tags":[
        "burger",
        "american"
    ],
    "wof:name":"Dairy Queen",
    "wof:placetype":"venue"
},
  "geometry": {"coordinates":[-83.29009499999999,40.832187],"type":"Point"}
}