{
  "type": "Feature",
  "properties": {
    "addr:full":"8388 Snoddy Rd Shreve OH 44676",
    "addr:housenumber":"8388",
    "addr:postcode":"44676",
    "addr:street":"Snoddy Rd",
    "iso:country":"US",
    "sg:address":"8388 Snoddy Rd",
    "sg:city":"Shreve",
    "sg:classifiers":[
        {
            "category":"Farming",
            "subcategory":"Dairy Farm",
            "type":"Manufacturing & Wholesale Goods"
        }
    ],
    "sg:phone":"+1 330 496 2331",
    "sg:postcode":"44676",
    "sg:province":"OH",
    "wof:name":"Wasuka Farms",
    "wof:placetype":"venue"
},
  "geometry": {"coordinates":[-82.114654,40.69769],"type":"Point"}
}