{
  "type": "Feature",
  "properties": {
    "addr:full":"960 W Wooster St Bowling Green OH 43402",
    "addr:housenumber":"960",
    "addr:postcode":"43402",
    "addr:street":"W Wooster St",
    "iso:country":"US",
    "sg:address":"960 W Wooster St",
    "sg:city":"Bowling Green",
    "sg:classifiers":[
        {
            "category":"Health Services",
            "subcategory":"Doctor",
            "type":"Services"
        }
    ],
    "sg:phone":"+1 419 352 3527",
    "sg:postcode":"43402",
    "sg:province":"OH",
    "wof:name":"J A Whittaker DDS Inc",
    "wof:placetype":"venue"
},
  "geometry": {"coordinates":[-83.665301,41.374042],"type":"Point"}
}