{
  "type": "Feature",
  "properties": {
    "iso:country":"US",
    "sg:address":"500 Lincoln Park Blvd",
    "sg:city":"Dayton",
    "sg:classifiers":[
        {
            "category":"Real Estate",
            "subcategory":"Real Estate Agent",
            "type":"Services"
        }
    ],
    "sg:phone":"+1 937 298 1123",
    "sg:postcode":"45429",
    "sg:province":"OH",
    "wof:name":"Jack Heinz Realtors",
    "wof:placetype":"venue"
},
  "geometry": {"coordinates":[-84.161112,39.696897],"type":"Point"}
}