{
  "type": "Feature",
  "properties": {
    "iso:country":"US",
    "sg:address":"13401 Lake Shore Blvd",
    "sg:city":"Cleveland",
    "sg:classifiers":[
        {
            "category":"Professional",
            "subcategory":"Computer Services",
            "type":"Services"
        }
    ],
    "sg:phone":"+1 216 451 5415",
    "sg:postcode":"44110",
    "sg:province":"OH",
    "sg:tags":[
        "hardware",
        "provider",
        "internet",
        "software"
    ],
    "wof:name":"Poe",
    "wof:placetype":"venue"
},
  "geometry": {"coordinates":[-81.587812,41.567259],"type":"Point"}
}