{
  "type": "Feature",
  "properties": {
    "addr:full": "2331 US Hwy 22 SW Washington Ct Hs OH 43160",
    "addr:housenumber": "2331",
    "addr:postcode": "43160",
    "addr:street": "Us Hwy 22 Sw",
    "iso:country": "US",
    "sg:address": "2331 US Hwy 22 SW",
    "sg:city": "Washington Ct Hs",
    "sg:classifiers": [
      {
        "category": "Building \u0026 Trades",
        "subcategory": "Construction",
        "type": "Services"
      }
    ],
    "sg:phone": "+1 740 335 1800",
    "sg:postcode": "43160",
    "sg:province": "OH",
    "sg:tags": [
      "road",
      "contractor"
    ],
    "wof:name": "Highway Dept",
    "wof:placetype": "venue"
  },
  "geometry": {"coordinates":[-83.475709,39.526321],"type":"Point"}
}
