{
  "type": "Feature",
  "properties": {
    "addr:full": "2925 Interstate Pkwy Brunswick OH 44212",
    "addr:housenumber": "2925",
    "addr:postcode": "44212",
    "addr:street": "Interstate Pkwy",
    "iso:country": "US",
    "sg:address": "2925 Interstate Pkwy",
    "sg:city": "Brunswick",
    "sg:classifiers": [
      {
        "category": "Manufacturing",
        "subcategory": "Chemicals \u0026 Compounds",
        "type": "Manufacturing \u0026 Wholesale Goods"
      }
    ],
    "sg:phone": "+1 330 220 8691",
    "sg:postcode": "44212",
    "sg:province": "OH",
    "sg:tags": [
      "fertilizer"
    ],
    "wof:name": "Lesco Service Ctr",
    "wof:placetype": "venue"
  },
  "geometry": {"coordinates":[-81.792051,41.247186],"type":"Point"}
}
