{
  "type": "Feature",
  "properties": {
    "iso:country":"US",
    "sg:address":"38721 Mentor Ave",
    "sg:city":"Willoughby",
    "sg:classifiers":[
        {
            "category":"Wholesale",
            "subcategory":"Computers",
            "type":"Manufacturing & Wholesale Goods"
        }
    ],
    "sg:phone":"+1 440 951 1616",
    "sg:postcode":"44094",
    "sg:province":"OH",
    "sg:tags":[
        "installation",
        "sales",
        "telephone",
        "system",
        "mail",
        "voice"
    ],
    "wof:name":"Network Plus",
    "wof:placetype":"venue"
},
  "geometry": {"coordinates":[-81.39255,41.645076],"type":"Point"}
}