{
  "type": "Feature",
  "properties": {
    "iso:country":"US",
    "sg:address":"25701 N Lakeland Blvd",
    "sg:city":"Cleveland",
    "sg:classifiers":[
        {
            "category":"Insurance",
            "subcategory":"Insurance Agent",
            "type":"Services"
        }
    ],
    "sg:phone":"+1 216 732 8600",
    "sg:postcode":"44132",
    "sg:province":"OH",
    "wof:name":"Pride Healthcare Benefits",
    "wof:placetype":"venue"
},
  "geometry": {"coordinates":[-81.50604,41.600199],"type":"Point"}
}