{
  "type": "Feature",
  "properties": {
    "iso:country":"US",
    "sg:address":"538 E Center St",
    "sg:city":"Marion",
    "sg:classifiers":[
        {
            "category":"Restaurant",
            "type":"Food & Drink"
        }
    ],
    "sg:phone":"+1 740 383 3030",
    "sg:postcode":"43302",
    "sg:province":"OH",
    "sg:tags":[
        "eating",
        "pizza"
    ],
    "wof:name":"Domino's Pizza",
    "wof:placetype":"venue"
},
  "geometry": {"coordinates":[-83.115574,40.589221],"type":"Point"}
}