{
  "type": "Feature",
  "properties": {
    "addr:full": "538 E Center St Marion OH 43302",
    "addr:housenumber": "538",
    "addr:postcode": "43302",
    "addr:street": "E Center St",
    "iso:country": "US",
    "sg:address": "538 E Center St",
    "sg:city": "Marion",
    "sg:classifiers": [
      {
        "category": "Restaurant",
        "type": "Food \u0026 Drink"
      }
    ],
    "sg:phone": "+1 740 383 3030",
    "sg:postcode": "43302",
    "sg:province": "OH",
    "sg:tags": [
      "eating",
      "pizza"
    ],
    "wof:name": "Domino's Pizza",
    "wof:placetype": "venue"
  },
  "geometry": {"coordinates":[-83.115574,40.589221],"type":"Point"}
}
