{
  "type": "Feature",
  "properties": {
    "iso:country":"US",
    "sg:address":"3131 Queen City Ave",
    "sg:city":"Cincinnati",
    "sg:classifiers":[
        {
            "category":"Sports & Exercise",
            "subcategory":"Gym",
            "type":"Entertainment"
        }
    ],
    "sg:phone":"+1 513 389 5600",
    "sg:postcode":"45238",
    "sg:province":"OH",
    "sg:tags":[
        "club",
        "health",
        "studio",
        "gymnasium"
    ],
    "wof:name":"Mercy Healthplex Western Hills",
    "wof:placetype":"venue"
},
  "geometry": {"coordinates":[-84.606568,39.136455],"type":"Point"}
}