{
  "type": "Feature",
  "properties": {
    "iso:country":"US",
    "sg:address":"1209 Blue Ave",
    "sg:city":"Zanesville",
    "sg:classifiers":[
        {
            "category":"Food & Beverages",
            "subcategory":"Groceries & Convenience Stores",
            "type":"Retail Goods"
        }
    ],
    "sg:phone":"+1 740 454 3990",
    "sg:postcode":"43701",
    "sg:province":"OH",
    "wof:name":"Duke & Duchess Shoppe",
    "wof:placetype":"venue"
},
  "geometry": {"coordinates":[-82.017276,39.953798],"type":"Point"}
}