{
  "type": "Feature",
  "properties": {
    "addr:full": "1209 Blue Ave Zanesville OH 43701",
    "addr:housenumber": "1209",
    "addr:postcode": "43701",
    "addr:street": "Blue Ave",
    "iso:country": "US",
    "sg:address": "1209 Blue Ave",
    "sg:city": "Zanesville",
    "sg:classifiers": [
      {
        "category": "Food \u0026 Beverages",
        "subcategory": "Groceries \u0026 Convenience Stores",
        "type": "Retail Goods"
      }
    ],
    "sg:phone": "+1 740 454 3990",
    "sg:postcode": "43701",
    "sg:province": "OH",
    "wof:name": "Duke \u0026 Duchess Shoppe",
    "wof:placetype": "venue"
  },
  "geometry": {"coordinates":[-82.017276,39.953798],"type":"Point"}
}
