{
  "type": "Feature",
  "properties": {
    "addr:full":"109 Dove Ct Enon OH 45323",
    "addr:housenumber":"109",
    "addr:postcode":"45323",
    "addr:street":"Dove Ct",
    "iso:country":"US",
    "sg:address":"109 Dove Ct",
    "sg:city":"Enon",
    "sg:classifiers":[
        {
            "category":"Insurance",
            "subcategory":"Hazard Insurance",
            "type":"Services"
        },
        {
            "category":"Insurance",
            "subcategory":"Insurance Agent",
            "type":"Services"
        }
    ],
    "sg:phone":"+1 937 864 1907",
    "sg:postcode":"45323",
    "sg:province":"OH",
    "sg:tags":[
        "carrier"
    ],
    "wof:name":"Sentry Insurance A Mutual Co",
    "wof:placetype":"venue"
},
  "geometry": {"coordinates":[-83.929677,39.849289],"type":"Point"}
}