{
  "type": "Feature",
  "properties": {
    "addr:full":"5130 Salem Ave Dayton OH 45426",
    "addr:housenumber":"5130",
    "addr:postcode":"45426",
    "addr:street":"Salem Ave",
    "iso:country":"US",
    "sg:address":"5130 Salem Ave",
    "sg:city":"Dayton",
    "sg:classifiers":[
        {
            "category":"Banks & Credit Unions",
            "subcategory":"Bank",
            "type":"Services"
        }
    ],
    "sg:phone":"+1 937 837 4105",
    "sg:postcode":"45426",
    "sg:province":"OH",
    "sg:tags":[
        "savings",
        "loan",
        "association"
    ],
    "wof:name":"Mid-America Federal Savings",
    "wof:placetype":"venue"
},
  "geometry": {"coordinates":[-84.275392,39.816379],"type":"Point"}
}