{
  "type": "Feature",
  "properties": {
    "iso:country":"US",
    "sg:address":"143 Hemlock Dr",
    "sg:city":"Elyria",
    "sg:classifiers":[
        {
            "category":"Airline",
            "type":"Transportation"
        }
    ],
    "sg:phone":"+1 440 366 5508",
    "sg:postcode":"44035",
    "sg:province":"OH",
    "sg:tags":[
        "nonscheduled",
        "air"
    ],
    "wof:name":"Foxy Lady Charter Service",
    "wof:placetype":"venue"
},
  "geometry": {"coordinates":[-82.087345,41.417151],"type":"Point"}
}