{
  "type": "Feature",
  "properties": {
    "addr:full": "5725 Silverside Dr Toledo OH 43612",
    "addr:housenumber": "5725",
    "addr:postcode": "43612",
    "addr:street": "Silverside Dr",
    "iso:country": "US",
    "sg:address": "5725 Silverside Dr",
    "sg:city": "Toledo",
    "sg:classifiers": [
      {
        "category": "Real Estate",
        "subcategory": "Real Estate Operator",
        "type": "Services"
      }
    ],
    "sg:phone": "+1 419 476 8269",
    "sg:postcode": "43612",
    "sg:province": "OH",
    "sg:tags": [
      "apartment"
    ],
    "wof:name": "North Towne Village Apartments",
    "wof:placetype": "venue"
  },
  "geometry": {"coordinates":[-83.553763,41.72112],"type":"Point"}
}
