{
  "type": "Feature",
  "properties": {
    "addr:full":"331 N Main St Marion OH 43302",
    "addr:housenumber":"331",
    "addr:postcode":"43302",
    "addr:street":"N Main St",
    "iso:country":"US",
    "sg:address":"331 N Main St",
    "sg:city":"Marion",
    "sg:classifiers":[
        {
            "category":"Food & Beverages",
            "subcategory":"Groceries & Convenience Stores",
            "type":"Retail Goods"
        }
    ],
    "sg:phone":"+1 740 382 0204",
    "sg:postcode":"43302",
    "sg:province":"OH",
    "wof:name":"Pop Wylies Service",
    "wof:placetype":"venue"
},
  "geometry": {"coordinates":[-83.129098,40.592591],"type":"Point"}
}