{
  "type": "Feature",
  "properties": {
    "addr:full":"29635 Lakeland Blvd Wickliffe OH 44092",
    "addr:housenumber":"29635",
    "addr:postcode":"44092",
    "addr:street":"Lakeland Blvd",
    "iso:country":"US",
    "sg:address":"29635 Lakeland Blvd",
    "sg:city":"Wickliffe",
    "sg:classifiers":[
        {
            "category":"Banks & Credit Unions",
            "subcategory":"Bank",
            "type":"Services"
        }
    ],
    "sg:phone":"+1 440 943 5702",
    "sg:postcode":"44092",
    "sg:province":"OH",
    "sg:tags":[
        "broker",
        "mortgage"
    ],
    "wof:name":"Lake Financial",
    "wof:placetype":"venue"
},
  "geometry": {"coordinates":[-81.48168699999999,41.611884],"type":"Point"}
}