{
  "type": "Feature",
  "properties": {
    "addr:full": "530 Barwell St Akron OH 44303",
    "addr:housenumber": "530",
    "addr:postcode": "44303",
    "addr:street": "Barwell St",
    "iso:country": "US",
    "sg:address": "530 Barwell St",
    "sg:city": "Akron",
    "sg:classifiers": [
      {
        "category": "Organizations",
        "subcategory": "Non-profit Organization",
        "type": "Services"
      }
    ],
    "sg:phone": "+1 330 864 5174",
    "sg:postcode": "44303",
    "sg:province": "OH",
    "sg:tags": [
      "fund",
      "counselor",
      "raising"
    ],
    "wof:name": "RBC Enterprises",
    "wof:placetype": "venue"
  },
  "geometry": {"coordinates":[-81.538803,41.104617],"type":"Point"}
}
