{
  "type": "Feature",
  "properties": {
    "addr:full": "35405 Chardon Rd Willoughby OH 44094",
    "addr:housenumber": "35405",
    "addr:postcode": "44094",
    "addr:street": "Chardon Rd",
    "iso:country": "US",
    "sg:address": "35405 Chardon Rd",
    "sg:city": "Willoughby",
    "sg:classifiers": [
      {
        "category": "Government",
        "subcategory": "Office",
        "type": "Public Place"
      },
      {
        "category": "Government",
        "subcategory": "Fire Station",
        "type": "Public Place"
      }
    ],
    "sg:phone": "+1 440 942 7207",
    "sg:postcode": "44094",
    "sg:province": "OH",
    "sg:tags": [
      "department",
      "enforcement",
      "law"
    ],
    "wof:name": "Willoughby Hills Police Dept",
    "wof:placetype": "venue"
  },
  "geometry": {"coordinates":[-81.436371,41.588101],"type":"Point"}
}
