{
  "type": "Feature",
  "properties": {
    "addr:full": "7212 State Rte 72 Leesburg OH 45135",
    "addr:housenumber": "7212",
    "addr:postcode": "45135",
    "addr:street": "State Rte 72",
    "iso:country": "US",
    "sg:address": "7212 State Rte 72",
    "sg:city": "Leesburg",
    "sg:classifiers": [
      {
        "category": "Professional",
        "type": "Services"
      }
    ],
    "sg:phone": "+1 937 584 4542",
    "sg:postcode": "45135",
    "sg:province": "OH",
    "wof:name": "Jeff Finley",
    "wof:placetype": "venue"
  },
  "geometry": {"coordinates":[-83.589969,39.297261],"type":"Point"}
}
