{
  "type": "Feature",
  "properties": {
    "addr:full": "411 E Main St Jewett OH 43986",
    "addr:housenumber": "411",
    "addr:postcode": "43986",
    "addr:street": "E Main St",
    "iso:country": "US",
    "sg:address": "411 E Main St",
    "sg:city": "Jewett",
    "sg:classifiers": [
      {
        "category": "Government",
        "subcategory": "Office",
        "type": "Public Place"
      }
    ],
    "sg:phone": "+1 740 946 1471",
    "sg:postcode": "43986",
    "sg:province": "OH",
    "sg:tags": [
      "executive"
    ],
    "wof:name": "Village Administration",
    "wof:placetype": "venue"
  },
  "geometry": {"coordinates":[-80.996155,40.367188],"type":"Point"}
}
