{
  "type": "Feature",
  "properties": {
    "addr:full": "53455 State Rte 147 Senecaville OH 43780",
    "addr:housenumber": "53455",
    "addr:postcode": "43780",
    "addr:street": "State Rte 147",
    "iso:country": "US",
    "sg:address": "53455 State Rte 147",
    "sg:city": "Senecaville",
    "sg:classifiers": [
      {
        "category": "Manufacturing",
        "subcategory": "Tools \u0026 Machinery",
        "type": "Manufacturing \u0026 Wholesale Goods"
      }
    ],
    "sg:phone": "+1 740 838 1818",
    "sg:postcode": "43780",
    "sg:province": "OH",
    "sg:tags": [
      "machine",
      "shop"
    ],
    "wof:name": "Seneca Machine \u0026 Engineering",
    "wof:placetype": "venue"
  },
  "geometry": {"coordinates":[-81.394133,39.875845],"type":"Point"}
}
