{
  "type": "Feature",
  "properties": {
    "iso:country":"US",
    "sg:address":"53455 State Rte 147",
    "sg:city":"Senecaville",
    "sg:classifiers":[
        {
            "category":"Manufacturing",
            "subcategory":"Tools & Machinery",
            "type":"Manufacturing & Wholesale Goods"
        }
    ],
    "sg:phone":"+1 740 838 1818",
    "sg:postcode":"43780",
    "sg:province":"OH",
    "sg:tags":[
        "machine",
        "shop"
    ],
    "wof:name":"Seneca Machine & Engineering",
    "wof:placetype":"venue"
},
  "geometry": {"coordinates":[-81.394133,39.875845],"type":"Point"}
}