{
  "type": "Feature",
  "properties": {
    "addr:full": "820 N Mantua St Kent OH 44240",
    "addr:housenumber": "820",
    "addr:postcode": "44240",
    "addr:street": "N Mantua St",
    "iso:country": "US",
    "sg:address": "820 N Mantua St",
    "sg:city": "Kent",
    "sg:classifiers": [
      {
        "category": "Personal",
        "subcategory": "Beauty Salon",
        "type": "Services"
      }
    ],
    "sg:phone": "+1 330 673 9222",
    "sg:postcode": "44240",
    "sg:province": "OH",
    "sg:tags": [
      "shop"
    ],
    "wof:name": "A Cut Above",
    "wof:placetype": "venue"
  },
  "geometry": {"coordinates":[-81.35875,41.160844],"type":"Point"}
}
