{
  "type": "Feature",
  "properties": {
    "addr:full": "735 Ogden Ave Toledo OH 43609",
    "addr:housenumber": "735",
    "addr:postcode": "43609",
    "addr:street": "Ogden Ave",
    "iso:country": "US",
    "sg:address": "735 Ogden Ave",
    "sg:city": "Toledo",
    "sg:classifiers": [
      {
        "category": "Wholesale",
        "subcategory": "Groceries",
        "type": "Manufacturing \u0026 Wholesale Goods"
      }
    ],
    "sg:phone": "+1 419 380 8286",
    "sg:postcode": "43609",
    "sg:province": "OH",
    "sg:tags": [
      "food",
      "product"
    ],
    "wof:name": "Maguire Foods Inc",
    "wof:placetype": "venue"
  },
  "geometry": {"coordinates":[-83.583645,41.626431],"type":"Point"}
}
