{
  "type": "Feature",
  "properties": {
    "addr:full":"3964 Brown Park Dr Hilliard OH 43026",
    "addr:housenumber":"3964",
    "addr:postcode":"43026",
    "addr:street":"Brown Park Dr",
    "iso:country":"US",
    "sg:address":"3964 Brown Park Dr",
    "sg:city":"Hilliard",
    "sg:classifiers":[
        {
            "category":"Professional",
            "subcategory":"Accounting & Tax Preparation",
            "type":"Services"
        }
    ],
    "sg:phone":"+1 614 850 9440",
    "sg:postcode":"43026",
    "sg:province":"OH",
    "sg:tags":[
        "accountant"
    ],
    "wof:name":"ABC Solutions",
    "wof:placetype":"venue"
},
  "geometry": {"coordinates":[-83.136385,40.033142],"type":"Point"}
}