{
  "type": "Feature",
  "properties": {
    "addr:full":"4273 Pymatuning Lake Rd Andover OH 44003",
    "addr:housenumber":"4273",
    "addr:postcode":"44003",
    "addr:street":"Pymatuning Lake Rd",
    "iso:country":"US",
    "sg:address":"4273 Pymatuning Lake Rd",
    "sg:city":"Andover",
    "sg:classifiers":[
        {
            "category":"Travel",
            "subcategory":"Campground",
            "type":"Entertainment"
        }
    ],
    "sg:phone":"+1 440 293 7116",
    "sg:postcode":"44003",
    "sg:province":"OH",
    "sg:website":"www.holidaycamplands.com",
    "wof:name":"Holiday Camplands Assn",
    "wof:placetype":"venue"
},
  "geometry": {"coordinates":[-80.54197499999999,41.63315],"type":"Point"}
}