{
  "type": "Feature",
  "properties": {
    "addr:full":"8220 Devonshire Pl Maineville OH 45039",
    "addr:housenumber":"8220",
    "addr:postcode":"45039",
    "addr:street":"Devonshire Pl",
    "iso:country":"US",
    "sg:address":"8220 Devonshire Pl",
    "sg:city":"Maineville",
    "sg:classifiers":[
        {
            "category":"Wholesale",
            "subcategory":"Vending Machines",
            "type":"Manufacturing & Wholesale Goods"
        }
    ],
    "sg:phone":"+1 513 683 6714",
    "sg:postcode":"45039",
    "sg:province":"OH",
    "sg:tags":[
        "operator"
    ],
    "wof:name":"Oconnor Vending",
    "wof:placetype":"venue"
},
  "geometry": {"coordinates":[-84.2445,39.316168],"type":"Point"}
}