{
  "type": "Feature",
  "properties": {
    "addr:full": "465 W Oregon Ave Sebring OH 44672",
    "addr:housenumber": "465",
    "addr:postcode": "44672",
    "addr:street": "W Oregon Ave",
    "iso:country": "US",
    "sg:address": "465 W Oregon Ave",
    "sg:city": "Sebring",
    "sg:classifiers": [
      {
        "category": "Shopping",
        "subcategory": "Gifts \u0026 Souvenirs",
        "type": "Retail Goods"
      }
    ],
    "sg:phone": "+1 330 938 9047",
    "sg:postcode": "44672",
    "sg:province": "OH",
    "wof:name": "Mary Kay Beauty Consultant",
    "wof:placetype": "venue"
  },
  "geometry": {"coordinates":[-81.026173,40.922104],"type":"Point"}
}
