{
  "type": "Feature",
  "properties": {
    "iso:country":"US",
    "sg:address":"465 W Oregon Ave",
    "sg:city":"Sebring",
    "sg:classifiers":[
        {
            "category":"Shopping",
            "subcategory":"Gifts & Souvenirs",
            "type":"Retail Goods"
        }
    ],
    "sg:phone":"+1 330 938 9047",
    "sg:postcode":"44672",
    "sg:province":"OH",
    "wof:name":"Mary Kay Beauty Consultant",
    "wof:placetype":"venue"
},
  "geometry": {"coordinates":[-81.026173,40.922104],"type":"Point"}
}