{
  "type": "Feature",
  "properties": {
    "addr:full": "60711 Dynamite Rd Salesville OH 43778",
    "addr:housenumber": "60711",
    "addr:postcode": "43778",
    "addr:street": "Dynamite Rd",
    "iso:country": "US",
    "sg:address": "60711 Dynamite Rd",
    "sg:city": "Salesville",
    "sg:classifiers": [
      {
        "category": "Wholesale",
        "subcategory": "Chemicals \u0026 Plastics",
        "type": "Manufacturing \u0026 Wholesale Goods"
      }
    ],
    "sg:phone": "+1 740 685 2585",
    "sg:postcode": "43778",
    "sg:province": "OH",
    "wof:name": "Gibson Station Location",
    "wof:placetype": "venue"
  },
  "geometry": {"coordinates":[-81.417272,39.977218],"type":"Point"}
}
