{
  "type": "Feature",
  "properties": {
    "iso:country":"US",
    "sg:address":"60711 Dynamite Rd",
    "sg:city":"Salesville",
    "sg:classifiers":[
        {
            "category":"Wholesale",
            "subcategory":"Chemicals & Plastics",
            "type":"Manufacturing & Wholesale Goods"
        }
    ],
    "sg:phone":"+1 740 685 2585",
    "sg:postcode":"43778",
    "sg:province":"OH",
    "wof:name":"Gibson Station Location",
    "wof:placetype":"venue"
},
  "geometry": {"coordinates":[-81.417272,39.977218],"type":"Point"}
}