{
  "type": "Feature",
  "properties": {
    "iso:country":"US",
    "sg:address":"3700 Jaeger Rd",
    "sg:city":"Lorain",
    "sg:classifiers":[
        {
            "category":"Building & Trades",
            "subcategory":"Construction",
            "type":"Services"
        }
    ],
    "sg:phone":"+1 440 282 5528",
    "sg:postcode":"44053",
    "sg:province":"OH",
    "sg:tags":[
        "house"
    ],
    "wof:name":"Powell Builders",
    "wof:placetype":"venue"
},
  "geometry": {"coordinates":[-82.217515,41.427437],"type":"Point"}
}