{
  "type": "Feature",
  "properties": {
    "addr:full":"609 Birchard Ave Fremont OH 43420",
    "addr:housenumber":"609",
    "addr:postcode":"43420",
    "addr:street":"Birchard Ave",
    "iso:country":"US",
    "sg:address":"609 Birchard Ave",
    "sg:city":"Fremont",
    "sg:classifiers":[
        {
            "category":"Banks & Credit Unions",
            "subcategory":"Financial Services",
            "type":"Services"
        }
    ],
    "sg:phone":"+1 419 332 2386",
    "sg:postcode":"43420",
    "sg:province":"OH",
    "sg:tags":[
        "trader",
        "royalty",
        "oil"
    ],
    "wof:name":"Energy Investment Rentals",
    "wof:placetype":"venue"
},
  "geometry": {"coordinates":[-83.117412,41.344267],"type":"Point"}
}