{
  "type": "Feature",
  "properties": {
    "addr:full":"975 S Main St Lindsey OH 43442",
    "addr:housenumber":"975",
    "addr:postcode":"43442",
    "addr:street":"S Main St",
    "iso:country":"US",
    "sg:address":"975 S Main St",
    "sg:city":"Lindsey",
    "sg:phone":"+1 419 665 2211",
    "sg:postcode":"43442",
    "sg:province":"OH",
    "sg:tags":[
        "farm",
        "corn",
        "soybean"
    ],
    "wof:name":"Scott Smith",
    "wof:placetype":"venue"
},
  "geometry": {"coordinates":[-83.220962,41.414164],"type":"Point"}
}