{
  "type": "Feature",
  "properties": {
    "iso:country":"US",
    "sg:address":"137 E State St",
    "sg:city":"Columbus",
    "sg:classifiers":[
        {
            "category":"Professional",
            "subcategory":"Management & Consulting",
            "type":"Services"
        }
    ],
    "sg:phone":"+1 614 225 1600",
    "sg:postcode":"43215",
    "sg:province":"OH",
    "sg:tags":[
        "consultant"
    ],
    "wof:name":"Bse Partners LLC",
    "wof:placetype":"venue"
},
  "geometry": {"coordinates":[-82.996059,39.960546],"type":"Point"}
}