{
  "type": "Feature",
  "properties": {
    "addr:full": "6700 N Dixie Dr Dayton OH 45414",
    "addr:housenumber": "6700",
    "addr:postcode": "45414",
    "addr:street": "N Dixie Dr",
    "iso:country": "US",
    "sg:address": "6700 N Dixie Dr",
    "sg:city": "Dayton",
    "sg:classifiers": [
      {
        "category": "Bars \u0026 Pubs",
        "type": "Food \u0026 Drink"
      }
    ],
    "sg:phone": "+1 937 898 8908",
    "sg:postcode": "45414",
    "sg:province": "OH",
    "wof:name": "Gemini Lounge",
    "wof:placetype": "venue"
  },
  "geometry": {"coordinates":[-84.198472,39.830656],"type":"Point"}
}
