{
  "type": "Feature",
  "properties": {
    "iso:country":"US",
    "sg:address":"6700 N Dixie Dr",
    "sg:city":"Dayton",
    "sg:classifiers":[
        {
            "category":"Bars & Pubs",
            "type":"Food & Drink"
        }
    ],
    "sg:phone":"+1 937 898 8908",
    "sg:postcode":"45414",
    "sg:province":"OH",
    "wof:name":"Gemini Lounge",
    "wof:placetype":"venue"
},
  "geometry": {"coordinates":[-84.198472,39.830656],"type":"Point"}
}