{
  "type": "Feature",
  "properties": {
    "addr:full":"17608 Hicks Rd Bedford OH 44146",
    "addr:housenumber":"17608",
    "addr:postcode":"44146",
    "addr:street":"Hicks Rd",
    "iso:country":"US",
    "sg:address":"17608 Hicks Rd",
    "sg:city":"Bedford",
    "sg:classifiers":[
        {
            "category":"Building & Trades",
            "subcategory":"Construction",
            "type":"Services"
        }
    ],
    "sg:phone":"+1 440 439 1967",
    "sg:postcode":"44146",
    "sg:province":"OH",
    "sg:tags":[
        "family"
    ],
    "wof:name":"Advance Home Improvements Inc",
    "wof:placetype":"venue"
},
  "geometry": {"coordinates":[-81.546959,41.363362],"type":"Point"}
}