{
  "type": "Feature",
  "properties": {
    "addr:full": "1003 Wilmington Pike Dayton OH 45420",
    "addr:housenumber": "1003",
    "addr:postcode": "45420",
    "addr:street": "Wilmington Pike",
    "iso:country": "US",
    "sg:address": "1003 Wilmington Pike",
    "sg:city": "Dayton",
    "sg:classifiers": [
      {
        "category": "Real Estate",
        "subcategory": "Real Estate Operator",
        "type": "Services"
      }
    ],
    "sg:phone": "+1 937 294 3853",
    "sg:postcode": "45420",
    "sg:province": "OH",
    "sg:tags": [
      "apartment"
    ],
    "wof:name": "Roscommon Place Apartments",
    "wof:placetype": "venue"
  },
  "geometry": {"coordinates":[-84.15469,39.727101],"type":"Point"}
}
