{
  "type": "Feature",
  "properties": {
    "addr:full": "1510 State Rte 377 Stockport OH 43787",
    "addr:housenumber": "1510",
    "addr:postcode": "43787",
    "addr:street": "State Rte 377",
    "iso:country": "US",
    "sg:address": "1510 State Rte 377",
    "sg:city": "Stockport",
    "sg:classifiers": [
      {
        "category": "Organizations",
        "subcategory": "Religious Organization",
        "type": "Services"
      }
    ],
    "sg:phone": "+1 740 557 3588",
    "sg:postcode": "43787",
    "sg:province": "OH",
    "sg:tags": [
      "church"
    ],
    "wof:name": "Antioch Church Of Christ",
    "wof:placetype": "venue"
  },
  "geometry": {"coordinates":[-81.852952,39.574719],"type":"Point"}
}
