{
  "type": "Feature",
  "properties": {
    "addr:full": "2450 Sandridge Dr Dayton OH 45439",
    "addr:housenumber": "2450",
    "addr:postcode": "45439",
    "addr:street": "Sandridge Dr",
    "iso:country": "US",
    "sg:address": "2450 Sandridge Dr",
    "sg:city": "Dayton",
    "sg:classifiers": [
      {
        "category": "Utilities",
        "subcategory": "Refuse",
        "type": "Services"
      }
    ],
    "sg:phone": "+1 937 496 7134",
    "sg:postcode": "45439",
    "sg:province": "OH",
    "sg:tags": [
      "waste",
      "management"
    ],
    "wof:name": "Montgmery Pub Wrks Solid Waste",
    "wof:placetype": "venue"
  },
  "geometry": {"coordinates":[-84.214774,39.716936],"type":"Point"}
}
