{
  "type": "Feature",
  "properties": {
    "addr:full":"573 S Alpha Bellbrook Rd Bellbrook OH 45305",
    "addr:housenumber":"573",
    "addr:postcode":"45305",
    "addr:street":"S Alpha Bellbrook Rd",
    "iso:country":"US",
    "sg:address":"573 S Alpha Bellbrook Rd",
    "sg:city":"Bellbrook",
    "sg:phone":"+1 937 426 1146",
    "sg:postcode":"45305",
    "sg:province":"OH",
    "sg:tags":[
        "farm",
        "corn"
    ],
    "wof:name":"Ronald Wenning",
    "wof:placetype":"venue"
},
  "geometry": {"coordinates":[-84.060643,39.675355],"type":"Point"}
}