{
  "type": "Feature",
  "properties": {
    "addr:full":"3618 Elyria Ave Lorain OH 44055",
    "addr:housenumber":"3618",
    "addr:postcode":"44055",
    "addr:street":"Elyria Ave",
    "iso:country":"US",
    "sg:address":"3618 Elyria Ave",
    "sg:city":"Lorain",
    "sg:classifiers":[
        {
            "category":"Restaurant",
            "type":"Food & Drink"
        }
    ],
    "sg:phone":"+1 440 933 3332",
    "sg:postcode":"44055",
    "sg:province":"OH",
    "sg:tags":[
        "eating"
    ],
    "wof:name":"Michael A Burger",
    "wof:placetype":"venue"
},
  "geometry": {"coordinates":[-82.161227,41.435277],"type":"Point"}
}