{
  "type": "Feature",
  "properties": {
    "addr:full": "2390 Baty Rd Lima OH 45807",
    "addr:postcode": "2390;45807",
    "addr:street": "Baty Rd",
    "iso:country": "US",
    "sg:address": "2390 Baty Rd",
    "sg:city": "Lima",
    "sg:classifiers": [
      {
        "category": "Shopping",
        "subcategory": "Bicycles \u0026 Sporting Goods",
        "type": "Retail Goods"
      }
    ],
    "sg:phone": "+1 419 339 7888",
    "sg:postcode": "45807",
    "sg:province": "OH",
    "sg:tags": [
      "equipment",
      "golf",
      "supply"
    ],
    "wof:name": "Lima Golf Shop",
    "wof:placetype": "venue"
  },
  "geometry": {"coordinates":[-84.184339,40.770294],"type":"Point"}
}
