{
  "type": "Feature",
  "properties": {
    "iso:country":"US",
    "sg:address":"211 N Court St",
    "sg:city":"Marysville",
    "sg:classifiers":[
        {
            "category":"Freight",
            "type":"Transportation"
        }
    ],
    "sg:phone":"+1 937 642 7199",
    "sg:postcode":"43040",
    "sg:province":"OH",
    "wof:name":"TMJ Travel",
    "wof:placetype":"venue"
},
  "geometry": {"coordinates":[-83.368034,40.238558],"type":"Point"}
}