{
  "type": "Feature",
  "properties": {
    "addr:full": "2339 Cleveland Ave Columbus OH 43211",
    "addr:housenumber": "2339",
    "addr:postcode": "43211",
    "addr:street": "Cleveland Ave",
    "iso:country": "US",
    "sg:address": "2339 Cleveland Ave",
    "sg:city": "Columbus",
    "sg:classifiers": [
      {
        "category": "Health Services",
        "subcategory": "Doctor",
        "type": "Services"
      }
    ],
    "sg:phone": "+1 614 268 8221",
    "sg:postcode": "43211",
    "sg:province": "OH",
    "sg:tags": [
      "physician",
      "family",
      "medical",
      "practice",
      "surgeons",
      "medicine"
    ],
    "wof:name": "Linden Medical Center",
    "wof:placetype": "venue"
  },
  "geometry": {"coordinates":[-82.966721,40.014778],"type":"Point"}
}
