{
  "type": "Feature",
  "properties": {
    "iso:country":"US",
    "sg:address":"3915 E Market St",
    "sg:city":"Warren",
    "sg:classifiers":[
        {
            "category":"Health Services",
            "subcategory":"Doctor",
            "type":"Services"
        }
    ],
    "sg:phone":"+1 330 856 6377",
    "sg:postcode":"44484",
    "sg:province":"OH",
    "sg:tags":[
        "physician",
        "surgeon"
    ],
    "wof:name":"James C Haun Inc",
    "wof:placetype":"venue"
},
  "geometry": {"coordinates":[-80.766418,41.237196],"type":"Point"}
}