{
  "type": "Feature",
  "properties": {
    "iso:country":"US",
    "sg:address":"9091 New Haven Rd",
    "sg:city":"Harrison",
    "sg:classifiers":[
        {
            "category":"Organizations",
            "subcategory":"Religious Organization",
            "type":"Services"
        }
    ],
    "sg:phone":"+1 513 738 5673",
    "sg:postcode":"45030",
    "sg:province":"OH",
    "sg:tags":[
        "church"
    ],
    "wof:name":"Cornerstone Christian Church",
    "wof:placetype":"venue"
},
  "geometry": {"coordinates":[-84.74056,39.275353],"type":"Point"}
}