{
  "type": "Feature",
  "properties": {
    "iso:country":"US",
    "sg:address":"13500 Detroit Ave",
    "sg:city":"Cleveland",
    "sg:classifiers":[
        {
            "category":"Education",
            "subcategory":"School",
            "type":"Public Place"
        }
    ],
    "sg:phone":"+1 216 221 3776",
    "sg:postcode":"44107",
    "sg:province":"OH",
    "sg:tags":[
        "religious"
    ],
    "sg:website":"www.sehs.net",
    "wof:name":"St Edward High School",
    "wof:placetype":"venue"
},
  "geometry": {"coordinates":[-81.78317800000001,41.485015],"type":"Point"}
}