{
  "type": "Feature",
  "properties": {
    "iso:country":"US",
    "sg:address":"926 Gay St",
    "sg:city":"Portsmouth",
    "sg:classifiers":[
        {
            "category":"Real Estate",
            "subcategory":"Real Estate Operator",
            "type":"Services"
        }
    ],
    "sg:phone":"+1 740 353 2147",
    "sg:postcode":"45662",
    "sg:province":"OH",
    "sg:tags":[
        "building",
        "apartment"
    ],
    "wof:name":"A-D & S Rentals",
    "wof:placetype":"venue"
},
  "geometry": {"coordinates":[-82.994263,38.737967],"type":"Point"}
}