{
  "type": "Feature",
  "properties": {
    "addr:full": "401 Scarlet Oak Dr Findlay OH 45840",
    "addr:housenumber": "401",
    "addr:postcode": "45840",
    "addr:street": "Scarlet Oak Dr",
    "iso:country": "US",
    "sg:address": "401 Scarlet Oak Dr",
    "sg:city": "Findlay",
    "sg:classifiers": [
      {
        "category": "Recreation",
        "type": "Entertainment"
      }
    ],
    "sg:phone": "+1 419 424 5961",
    "sg:postcode": "45840",
    "sg:province": "OH",
    "sg:tags": [
      "club",
      "membership"
    ],
    "wof:name": "Lakeview Pool \u0026 Tennis Club In",
    "wof:placetype": "venue"
  },
  "geometry": {"coordinates":[-83.603237,41.040293],"type":"Point"}
}
