{
  "type": "Feature",
  "properties": {
    "iso:country":"US",
    "sg:address":"401 Scarlet Oak Dr",
    "sg:city":"Findlay",
    "sg:classifiers":[
        {
            "category":"Recreation",
            "type":"Entertainment"
        }
    ],
    "sg:phone":"+1 419 424 5961",
    "sg:postcode":"45840",
    "sg:province":"OH",
    "sg:tags":[
        "club",
        "membership"
    ],
    "wof:name":"Lakeview Pool & Tennis Club In",
    "wof:placetype":"venue"
},
  "geometry": {"coordinates":[-83.603237,41.040293],"type":"Point"}
}