{
  "type": "Feature",
  "properties": {
    "addr:full":"4916 Whipple Ave NW Canton OH 44718",
    "addr:housenumber":"4916",
    "addr:postcode":"44718",
    "addr:street":"Whipple Ave Nw",
    "iso:country":"US",
    "sg:address":"4916 Whipple Ave NW",
    "sg:city":"Canton",
    "sg:classifiers":[
        {
            "category":"Manufacturing",
            "subcategory":"Tools & Machinery",
            "type":"Manufacturing & Wholesale Goods"
        }
    ],
    "sg:phone":"+1 330 491 1750",
    "sg:postcode":"44718",
    "sg:province":"OH",
    "sg:tags":[
        "equipment",
        "computer"
    ],
    "wof:name":"Legend Micro Retail",
    "wof:placetype":"venue"
},
  "geometry": {"coordinates":[-81.423214,40.850994],"type":"Point"}
}