{
  "type": "Feature",
  "properties": {
    "iso:country":"US",
    "sg:address":"7767 Montgomery Rd",
    "sg:city":"Cincinnati",
    "sg:classifiers":[
        {
            "category":"Health Services",
            "subcategory":"Health Practitioner",
            "type":"Services"
        },
        {
            "category":"Professional",
            "subcategory":"Employment Agencies",
            "type":"Services"
        }
    ],
    "sg:phone":"+1 513 272 3999",
    "sg:postcode":"45236",
    "sg:province":"OH",
    "sg:tags":[
        "nurse",
        "registry",
        "staffing"
    ],
    "sg:website":"www.trustaff.com",
    "wof:name":"Trustaff",
    "wof:placetype":"venue"
},
  "geometry": {"coordinates":[-84.383763,39.197659],"type":"Point"}
}