{
  "type": "Feature",
  "properties": {
    "iso:country":"US",
    "sg:address":"10501 Blacklick Eastern Rd",
    "sg:city":"Pickerington",
    "sg:classifiers":[
        {
            "category":"Restaurant",
            "type":"Food & Drink"
        }
    ],
    "sg:menulink":"http://www.allmenus.com/oh/violet/136750-smoothie-king/menu/",
    "sg:phone":"+1 614 759 9183",
    "sg:postcode":"43147",
    "sg:province":"OH",
    "sg:tags":[
        "smoothy",
        "juice",
        "american"
    ],
    "wof:name":"Smoothie King",
    "wof:placetype":"venue"
},
  "geometry": {"coordinates":[-82.78260299999999,39.929196],"type":"Point"}
}