{
  "type": "Feature",
  "properties": {
    "addr:full": "10501 Blacklick Eastern Rd Pickerington OH 43147",
    "addr:housenumber": "10501",
    "addr:postcode": "43147",
    "addr:street": "Blacklick Eastern Rd",
    "iso:country": "US",
    "sg:address": "10501 Blacklick Eastern Rd",
    "sg:city": "Pickerington",
    "sg:classifiers": [
      {
        "category": "Restaurant",
        "type": "Food \u0026 Drink"
      }
    ],
    "sg:menulink": "http://www.allmenus.com/oh/violet/136750-smoothie-king/menu/",
    "sg:phone": "+1 614 759 9183",
    "sg:postcode": "43147",
    "sg:province": "OH",
    "sg:tags": [
      "smoothy",
      "juice",
      "american"
    ],
    "wof:name": "Smoothie King",
    "wof:placetype": "venue"
  },
  "geometry": {"coordinates":[-82.782603,39.929196],"type":"Point"}
}
