{
  "type": "Feature",
  "properties": {
    "addr:full":"2150 Leiter Rd Miamisburg OH 45342",
    "addr:postcode":"2150;45342",
    "addr:street":"Leiter Rd",
    "iso:country":"US",
    "sg:address":"2150 Leiter Rd",
    "sg:city":"Miamisburg",
    "sg:classifiers":[
        {
            "category":"Shopping",
            "subcategory":"Pharmacy",
            "type":"Retail Goods"
        }
    ],
    "sg:phone":"+1 937 384 8771",
    "sg:postcode":"45342",
    "sg:province":"OH",
    "wof:name":"Midwest Home Infusion Svcs",
    "wof:placetype":"venue"
},
  "geometry": {"coordinates":[-84.250631,39.638637],"type":"Point"}
}