{
  "type": "Feature",
  "properties": {
    "addr:full":"4208 Lincoln Way E Massillon OH 44646",
    "addr:housenumber":"4208",
    "addr:postcode":"44646",
    "addr:street":"Lincoln Way E",
    "iso:country":"US",
    "sg:address":"4208 Lincoln Way E",
    "sg:city":"Massillon",
    "sg:classifiers":[
        {
            "category":"Wholesale",
            "subcategory":"Sporting Goods",
            "type":"Manufacturing & Wholesale Goods"
        },
        {
            "category":"Manufacturing",
            "subcategory":"Printing",
            "type":"Manufacturing & Wholesale Goods"
        }
    ],
    "sg:phone":"+1 330 477 3479",
    "sg:postcode":"44646",
    "sg:province":"OH",
    "sg:tags":[
        "equipment",
        "screen",
        "bowling"
    ],
    "wof:name":"Stahlheber's Inc",
    "wof:placetype":"venue"
},
  "geometry": {"coordinates":[-81.454926,40.793005],"type":"Point"}
}