{
  "type": "Feature",
  "properties": {
    "addr:full":"104 Louden Ct Elyria OH 44035",
    "addr:housenumber":"104",
    "addr:postcode":"44035",
    "addr:street":"Louden Ct",
    "iso:country":"US",
    "sg:address":"104 Louden Ct",
    "sg:city":"Elyria",
    "sg:classifiers":[
        {
            "category":"Government",
            "subcategory":"Office",
            "type":"Public Place"
        }
    ],
    "sg:phone":"+1 440 322 4197",
    "sg:postcode":"44035",
    "sg:province":"OH",
    "sg:tags":[
        "building",
        "operator",
        "apartment"
    ],
    "wof:name":"Lorain Metropolitan Hsing Auth",
    "wof:placetype":"venue"
},
  "geometry": {"coordinates":[-82.100545,41.344603],"type":"Point"}
}