{
  "type": "Feature",
  "properties": {
    "iso:country":"US",
    "sg:address":"3607 Park Ave W",
    "sg:city":"Mansfield",
    "sg:classifiers":[
        {
            "category":"Building & Trades",
            "subcategory":"Construction",
            "type":"Services"
        }
    ],
    "sg:phone":"+1 419 529 2839",
    "sg:postcode":"44906",
    "sg:province":"OH",
    "sg:tags":[
        "floor",
        "laying",
        "contractor"
    ],
    "wof:name":"James F Shaum",
    "wof:placetype":"venue"
},
  "geometry": {"coordinates":[-82.644417,40.760321],"type":"Point"}
}