{
  "type": "Feature",
  "properties": {
    "addr:full": "14259 Claridon Troy Rd Burton OH 44021",
    "addr:housenumber": "14259",
    "addr:postcode": "44021",
    "addr:street": "Claridon Troy Rd",
    "iso:country": "US",
    "sg:address": "14259 Claridon Troy Rd",
    "sg:city": "Burton",
    "sg:classifiers": [
      {
        "category": "Education",
        "subcategory": "School",
        "type": "Public Place"
      }
    ],
    "sg:phone": "+1 440 834 4123",
    "sg:postcode": "44021",
    "sg:province": "OH",
    "wof:name": "Berkshire Local School Dist",
    "wof:placetype": "venue"
  },
  "geometry": {"coordinates":[-81.145063,41.48166],"type":"Point"}
}
