{
  "type": "Feature",
  "properties": {
    "addr:full":"1 Simmons Ave Peebles OH 45660",
    "addr:housenumber":"1",
    "addr:postcode":"45660",
    "addr:street":"Simmons Ave",
    "iso:country":"US",
    "sg:address":"1 Simmons Ave",
    "sg:city":"Peebles",
    "sg:classifiers":[
        {
            "category":"Education",
            "subcategory":"School",
            "type":"Public Place"
        }
    ],
    "sg:phone":"+1 937 587 2611",
    "sg:postcode":"45660",
    "sg:province":"OH",
    "sg:tags":[
        "elementary"
    ],
    "wof:name":"Peebles Elementary School",
    "wof:placetype":"venue"
},
  "geometry": {"coordinates":[-83.40974300000001,38.950764],"type":"Point"}
}