{
  "type": "Feature",
  "properties": {
    "addr:full": "15560 Mayfield Rd Huntsburg OH 44046",
    "addr:housenumber": "15560",
    "addr:postcode": "44046",
    "addr:street": "Mayfield Rd",
    "iso:country": "US",
    "sg:address": "15560 Mayfield Rd",
    "sg:city": "Huntsburg",
    "sg:classifiers": [
      {
        "category": "Travel",
        "subcategory": "Campground",
        "type": "Entertainment"
      }
    ],
    "sg:phone": "+1 440 635 5050",
    "sg:postcode": "44046",
    "sg:province": "OH",
    "wof:name": "Windrush Hollow Camp Inc",
    "wof:placetype": "venue"
  },
  "geometry": {"coordinates":[-81.089555,41.534655],"type":"Point"}
}
