{
  "type": "Feature",
  "properties": {
    "addr:full":"3619 Liberty Ave Vermilion OH 44089",
    "addr:housenumber":"3619",
    "addr:postcode":"44089",
    "addr:street":"Liberty Ave",
    "iso:country":"US",
    "sg:address":"3619 Liberty Ave",
    "sg:city":"Vermilion",
    "sg:classifiers":[
        {
            "category":"Home & Garden",
            "subcategory":"Garden Supply",
            "type":"Retail Goods"
        }
    ],
    "sg:phone":"+1 440 967 9601",
    "sg:postcode":"44089",
    "sg:province":"OH",
    "sg:tags":[
        "farm"
    ],
    "wof:name":"U-Haul",
    "wof:placetype":"venue"
},
  "geometry": {"coordinates":[-82.31877,41.424761],"type":"Point"}
}