{
  "type": "Feature",
  "properties": {
    "iso:country":"US",
    "sg:address":"140 West Ave",
    "sg:city":"Tallmadge",
    "sg:classifiers":[
        {
            "category":"Autos & Motor Vehicles",
            "subcategory":"Automobile Sales",
            "type":"Retail Goods"
        }
    ],
    "sg:phone":"+1 330 630 2000",
    "sg:postcode":"44278",
    "sg:province":"OH",
    "sg:tags":[
        "car",
        "dealer"
    ],
    "sg:website":"www.serpentinichevy.com",
    "wof:name":"Bob Serpentini's Chevy Connctn",
    "wof:placetype":"venue"
},
  "geometry": {"coordinates":[-81.447436,41.101607],"type":"Point"}
}