{
  "type": "Feature",
  "properties": {
    "iso:country":"US",
    "sg:address":"3406 S Hametown Rd",
    "sg:city":"Norton",
    "sg:classifiers":[
        {
            "category":"Organizations",
            "subcategory":"Religious Organization",
            "type":"Services"
        }
    ],
    "sg:phone":"+1 330 825 7217",
    "sg:postcode":"44203",
    "sg:province":"OH",
    "sg:tags":[
        "church"
    ],
    "wof:name":"Living Hope United Methodist",
    "wof:placetype":"venue"
},
  "geometry": {"coordinates":[-81.66707100000001,41.040091],"type":"Point"}
}