{
  "type": "Feature",
  "properties": {
    "addr:full":"20014 Co Rd Hj Archbold OH 43502",
    "addr:postcode":"20014;43502",
    "addr:street":"Co Rd",
    "iso:country":"US",
    "sg:address":"20014 Co Rd Hj",
    "sg:city":"Archbold",
    "sg:classifiers":[
        {
            "category":"Retail",
            "subcategory":"Veterinary Services",
            "type":"Services"
        }
    ],
    "sg:phone":"+1 419 445 0505",
    "sg:postcode":"43502",
    "sg:province":"OH",
    "wof:name":"Gene Goering Dvm",
    "wof:placetype":"venue"
},
  "geometry": {"coordinates":[-84.249348,41.594376],"type":"Point"}
}