{
  "type": "Feature",
  "properties": {
    "addr:full": "2259 Rickle Dr Akron OH 44333",
    "addr:housenumber": "2259",
    "addr:postcode": "44333",
    "addr:street": "Rickle Dr",
    "iso:country": "US",
    "sg:address": "2259 Rickle Dr",
    "sg:city": "Akron",
    "sg:classifiers": [
      {
        "category": "Banks \u0026 Credit Unions",
        "subcategory": "Investment Brokerage",
        "type": "Services"
      }
    ],
    "sg:phone": "+1 330 869 8290",
    "sg:postcode": "44333",
    "sg:province": "OH",
    "sg:tags": [
      "advisory"
    ],
    "wof:name": "Five Star Financial Services I",
    "wof:placetype": "venue"
  },
  "geometry": {"coordinates":[-81.590079,41.14226],"type":"Point"}
}
