{
  "type": "Feature",
  "properties": {
    "iso:country":"US",
    "sg:address":"803 Ridgeway Ave",
    "sg:city":"Cincinnati",
    "sg:classifiers":[
        {
            "category":"Social Services",
            "subcategory":"Child Care",
            "type":"Services"
        }
    ],
    "sg:phone":"+1 513 221 5329",
    "sg:postcode":"45229",
    "sg:province":"OH",
    "wof:name":"Sister Sister Childcare",
    "wof:placetype":"venue"
},
  "geometry": {"coordinates":[-84.490877,39.139616],"type":"Point"}
}