{
  "type": "Feature",
  "properties": {
    "addr:full": "1061 Piper Rd Mansfield OH 44905",
    "addr:housenumber": "1061",
    "addr:postcode": "44905",
    "addr:street": "Piper Rd",
    "iso:country": "US",
    "sg:address": "1061 Piper Rd",
    "sg:city": "Mansfield",
    "sg:classifiers": [
      {
        "category": "Food \u0026 Beverages",
        "subcategory": "Specialty",
        "type": "Retail Goods"
      }
    ],
    "sg:phone": "+1 419 589 9141",
    "sg:postcode": "44905",
    "sg:province": "OH",
    "wof:name": "Sherrys Health Shoppe Inc",
    "wof:placetype": "venue"
  },
  "geometry": {"coordinates":[-82.475861,40.799648],"type":"Point"}
}
