{
  "type": "Feature",
  "properties": {
    "addr:full": "3622 Chapel Rd Hamilton OH 45013",
    "addr:housenumber": "3622",
    "addr:postcode": "45013",
    "addr:street": "Chapel Rd",
    "iso:country": "US",
    "sg:address": "3622 Chapel Rd",
    "sg:city": "Hamilton",
    "sg:classifiers": [
      {
        "category": "Building \u0026 Trades",
        "subcategory": "Electrical",
        "type": "Services"
      }
    ],
    "sg:phone": "+1 513 738 5115",
    "sg:postcode": "45013",
    "sg:province": "OH",
    "sg:tags": [
      "installs",
      "communication",
      "equipment"
    ],
    "wof:name": "Advanced McRwave Installations",
    "wof:placetype": "venue"
  },
  "geometry": {"coordinates":[-84.740214,39.337368],"type":"Point"}
}
