{
  "type": "Feature",
  "properties": {
    "iso:country":"US",
    "sg:address":"3622 Chapel Rd",
    "sg:city":"Hamilton",
    "sg:classifiers":[
        {
            "category":"Building & Trades",
            "subcategory":"Electrical",
            "type":"Services"
        }
    ],
    "sg:phone":"+1 513 738 5115",
    "sg:postcode":"45013",
    "sg:province":"OH",
    "sg:tags":[
        "installs",
        "communication",
        "equipment"
    ],
    "wof:name":"Advanced McRwave Installations",
    "wof:placetype":"venue"
},
  "geometry": {"coordinates":[-84.74021399999999,39.337368],"type":"Point"}
}