{
  "type": "Feature",
  "properties": {
    "addr:full": "1793 E Ohio Pike Amelia OH 45102",
    "addr:housenumber": "1793",
    "addr:postcode": "45102",
    "addr:street": "E Ohio Pike",
    "iso:country": "US",
    "sg:address": "1793 E Ohio Pike",
    "sg:city": "Amelia",
    "sg:classifiers": [
      {
        "category": "Retail",
        "subcategory": "Auto Repair",
        "type": "Services"
      }
    ],
    "sg:phone": "+1 513 797 4888",
    "sg:postcode": "45102",
    "sg:province": "OH",
    "sg:tags": [
      "general"
    ],
    "wof:name": "Ray \u0026 Rons Auto Service Inc",
    "wof:placetype": "venue"
  },
  "geometry": {"coordinates":[-84.20311,39.019265],"type":"Point"}
}
