{
  "type": "Feature",
  "properties": {
    "addr:full": "10111 US Hwy 250 Milan OH 44846",
    "addr:housenumber": "10111",
    "addr:postcode": "44846",
    "addr:street": "Us Hwy 250",
    "iso:country": "US",
    "sg:address": "10111 US Hwy 250",
    "sg:city": "Milan",
    "sg:classifiers": [
      {
        "category": "Home \u0026 Garden",
        "subcategory": "Carpets \u0026 Floor Coverings",
        "type": "Retail Goods"
      }
    ],
    "sg:phone": "+1 419 625 0500",
    "sg:postcode": "44846",
    "sg:province": "OH",
    "sg:tags": [
      "dealer",
      "rug"
    ],
    "wof:name": "Warnike Carpet and Tile Co",
    "wof:placetype": "venue"
  },
  "geometry": {"coordinates":[-82.625697,41.335013],"type":"Point"}
}
