{
  "type": "Feature",
  "properties": {
    "iso:country":"US",
    "sg:address":"10111 US Hwy 250",
    "sg:city":"Milan",
    "sg:classifiers":[
        {
            "category":"Home & Garden",
            "subcategory":"Carpets & Floor Coverings",
            "type":"Retail Goods"
        }
    ],
    "sg:phone":"+1 419 625 0500",
    "sg:postcode":"44846",
    "sg:province":"OH",
    "sg:tags":[
        "dealer",
        "rug"
    ],
    "wof:name":"Warnike Carpet and Tile Co",
    "wof:placetype":"venue"
},
  "geometry": {"coordinates":[-82.625697,41.335013],"type":"Point"}
}