{
  "type": "Feature",
  "properties": {
    "iso:country":"US",
    "sg:address":"4745 Riverwood Dr",
    "sg:city":"Madison",
    "sg:classifiers":[
        {
            "category":"Restaurant",
            "type":"Food & Drink"
        }
    ],
    "sg:phone":"+1 440 259 2011",
    "sg:postcode":"44057",
    "sg:province":"OH",
    "sg:tags":[
        "eating"
    ],
    "wof:name":"Coffee Creek Nursery",
    "wof:placetype":"venue"
},
  "geometry": {"coordinates":[-81.116697,41.744318],"type":"Point"}
}