{
  "type": "Feature",
  "properties": {
    "addr:full": "5860 S Co Rd 25A Tipp City OH 45371",
    "addr:housenumber": "5860;25a",
    "addr:postcode": "45371",
    "addr:street": "S Co Rd",
    "iso:country": "US",
    "sg:address": "5860 S Co Rd 25A",
    "sg:city": "Tipp City",
    "sg:classifiers": [
      {
        "category": "Real Estate",
        "subcategory": "Developer",
        "type": "Services"
      }
    ],
    "sg:phone": "+1 937 667 1700",
    "sg:postcode": "45371",
    "sg:province": "OH",
    "sg:website": "www.borchersrentals.com",
    "wof:name": "Borchers Construction Co",
    "wof:placetype": "venue"
  },
  "geometry": {"coordinates":[-84.199122,39.952896],"type":"Point"}
}
