{
  "type": "Feature",
  "properties": {
    "addr:full": "8228 Mayfield Rd Chesterland OH 44026",
    "addr:housenumber": "8228",
    "addr:postcode": "44026",
    "addr:street": "Mayfield Rd",
    "iso:country": "US",
    "sg:address": "8228 Mayfield Rd",
    "sg:city": "Chesterland",
    "sg:classifiers": [
      {
        "category": "Real Estate",
        "subcategory": "Real Estate Agent",
        "type": "Services"
      }
    ],
    "sg:phone": "+1 440 729 9494",
    "sg:postcode": "44026",
    "sg:province": "OH",
    "wof:name": "Remax Revolution",
    "wof:placetype": "venue"
  },
  "geometry": {"coordinates":[-81.347249,41.522329],"type":"Point"}
}
