{
  "type": "Feature",
  "properties": {
    "addr:full": "40 College Dr Doylestown OH 44230",
    "addr:housenumber": "40",
    "addr:postcode": "44230",
    "addr:street": "College Dr",
    "iso:country": "US",
    "sg:address": "40 College Dr",
    "sg:city": "Doylestown",
    "sg:classifiers": [
      {
        "category": "Professional",
        "subcategory": "Accounting \u0026 Tax Preparation",
        "type": "Services"
      }
    ],
    "sg:phone": "+1 330 658 2051",
    "sg:postcode": "44230",
    "sg:province": "OH",
    "wof:name": "Crandall Tax Service Co Inc",
    "wof:placetype": "venue"
  },
  "geometry": {"coordinates":[-81.694514,40.971184],"type":"Point"}
}
