{
  "type": "Feature",
  "properties": {
    "iso:country":"US",
    "sg:address":"40 College Dr",
    "sg:city":"Doylestown",
    "sg:classifiers":[
        {
            "category":"Professional",
            "subcategory":"Accounting & Tax Preparation",
            "type":"Services"
        }
    ],
    "sg:phone":"+1 330 658 2051",
    "sg:postcode":"44230",
    "sg:province":"OH",
    "wof:name":"Crandall Tax Service Co Inc",
    "wof:placetype":"venue"
},
  "geometry": {"coordinates":[-81.694514,40.971184],"type":"Point"}
}