{
  "type": "Feature",
  "properties": {
    "addr:full": "7306 Harrison Ave Cincinnati OH 45247",
    "addr:housenumber": "7306",
    "addr:postcode": "45247",
    "addr:street": "Harrison Ave",
    "iso:country": "US",
    "sg:address": "7306 Harrison Ave",
    "sg:city": "Cincinnati",
    "sg:classifiers": [
      {
        "category": "Bars \u0026 Pubs",
        "type": "Food \u0026 Drink"
      }
    ],
    "sg:phone": "+1 513 353 5777",
    "sg:postcode": "45247",
    "sg:province": "OH",
    "wof:name": "Iveys Pub",
    "wof:placetype": "venue"
  },
  "geometry": {"coordinates":[-84.682818,39.217558],"type":"Point"}
}
