{
  "type": "Feature",
  "properties": {
    "addr:full":"2727 Miami Shelby Rd Russia OH 45363",
    "addr:housenumber":"2727",
    "addr:postcode":"45363",
    "addr:street":"Miami Shelby Rd",
    "iso:country":"US",
    "sg:address":"2727 Miami Shelby Rd",
    "sg:city":"Russia",
    "sg:classifiers":[
        {
            "category":"Farming",
            "subcategory":"Livestock Farm",
            "type":"Manufacturing & Wholesale Goods"
        }
    ],
    "sg:phone":"+1 937 526 3643",
    "sg:postcode":"45363",
    "sg:province":"OH",
    "sg:tags":[
        "beef",
        "feedlot",
        "cattle"
    ],
    "wof:name":"Roger Meyer",
    "wof:placetype":"venue"
},
  "geometry": {"coordinates":[-84.38141,40.197334],"type":"Point"}
}