{
  "type": "Feature",
  "properties": {
    "iso:country":"US",
    "sg:address":"5870 Abbey Church Rd",
    "sg:city":"Dublin",
    "sg:classifiers":[
        {
            "category":"Wholesale",
            "subcategory":"Electrical",
            "type":"Manufacturing & Wholesale Goods"
        }
    ],
    "sg:phone":"+1 614 764 2771",
    "sg:postcode":"43017",
    "sg:province":"OH",
    "sg:tags":[
        "instrument",
        "electronic"
    ],
    "wof:name":"R D Cloon Assoc",
    "wof:placetype":"venue"
},
  "geometry": {"coordinates":[-83.094741,40.074053],"type":"Point"}
}