{
  "type": "Feature",
  "properties": {
    "addr:full": "5870 Abbey Church Rd Dublin OH 43017",
    "addr:housenumber": "5870",
    "addr:postcode": "43017",
    "addr:street": "Abbey Church Rd",
    "iso:country": "US",
    "sg:address": "5870 Abbey Church Rd",
    "sg:city": "Dublin",
    "sg:classifiers": [
      {
        "category": "Wholesale",
        "subcategory": "Electrical",
        "type": "Manufacturing \u0026 Wholesale Goods"
      }
    ],
    "sg:phone": "+1 614 764 2771",
    "sg:postcode": "43017",
    "sg:province": "OH",
    "sg:tags": [
      "instrument",
      "electronic"
    ],
    "wof:name": "R D Cloon Assoc",
    "wof:placetype": "venue"
  },
  "geometry": {"coordinates":[-83.094741,40.074053],"type":"Point"}
}
