{
  "type": "Feature",
  "properties": {
    "addr:full": "405 N Findlay St Haskins OH 43525",
    "addr:housenumber": "405",
    "addr:postcode": "43525",
    "addr:street": "N Findlay St",
    "iso:country": "US",
    "sg:address": "405 N Findlay St",
    "sg:city": "Haskins",
    "sg:classifiers": [
      {
        "category": "Education",
        "subcategory": "School",
        "type": "Public Place"
      }
    ],
    "sg:phone": "+1 419 823 1591",
    "sg:postcode": "43525",
    "sg:province": "OH",
    "wof:name": "Haskins Elementary School",
    "wof:placetype": "venue"
  },
  "geometry": {"coordinates":[-83.706831,41.469623],"type":"Point"}
}
