{
  "type": "Feature",
  "properties": {
    "addr:full":"6279 Tri Ridge Blvd Loveland OH 45140",
    "addr:housenumber":"6279",
    "addr:postcode":"45140",
    "addr:street":"Tri Ridge Blvd",
    "iso:country":"US",
    "sg:address":"6279 Tri Ridge Blvd",
    "sg:city":"Loveland",
    "sg:classifiers":[
        {
            "category":"Insurance",
            "subcategory":"Hazard Insurance",
            "type":"Services"
        }
    ],
    "sg:phone":"+1 513 576 6221",
    "sg:postcode":"45140",
    "sg:province":"OH",
    "sg:tags":[
        "employee",
        "benefit",
        "compensation",
        "plan"
    ],
    "wof:name":"North Amer Benefits Network",
    "wof:placetype":"venue"
},
  "geometry": {"coordinates":[-84.28318400000001,39.225262],"type":"Point"}
}