{
  "type": "Feature",
  "properties": {
    "addr:full":"1949 Forman Rd Jefferson OH 44047",
    "addr:housenumber":"1949",
    "addr:postcode":"44047",
    "addr:street":"Forman Rd",
    "iso:country":"US",
    "sg:address":"1949 Forman Rd",
    "sg:city":"Jefferson",
    "sg:classifiers":[
        {
            "category":"Building & Trades",
            "subcategory":"Construction",
            "type":"Services"
        }
    ],
    "sg:phone":"+1 440 992 1300",
    "sg:postcode":"44047",
    "sg:province":"OH",
    "sg:tags":[
        "asbestos",
        "removal"
    ],
    "wof:name":"Monit Air Group",
    "wof:placetype":"venue"
},
  "geometry": {"coordinates":[-80.83592400000001,41.698793],"type":"Point"}
}