{
  "type": "Feature",
  "properties": {
    "iso:country":"US",
    "sg:address":"100 S Main St",
    "sg:city":"Waynesville",
    "sg:classifiers":[
        {
            "category":"Shopping",
            "subcategory":"Used Merchandise",
            "type":"Retail Goods"
        }
    ],
    "sg:phone":"+1 513 897 9686",
    "sg:postcode":"45068",
    "sg:province":"OH",
    "sg:tags":[
        "antique"
    ],
    "wof:name":"Brass Lantern Antiques",
    "wof:placetype":"venue"
},
  "geometry": {"coordinates":[-84.086747,39.529703],"type":"Point"}
}