{
  "type": "Feature",
  "properties": {
    "iso:country":"US",
    "sg:address":"2755 Bazetta Rd NE",
    "sg:city":"Warren",
    "sg:classifiers":[
        {
            "category":"Education",
            "subcategory":"School",
            "type":"Public Place"
        }
    ],
    "sg:phone":"+1 330 372 2145",
    "sg:postcode":"44410",
    "sg:province":"OH",
    "sg:website":"www.bazetta.com",
    "wof:name":"Bazetta Elementary School",
    "wof:placetype":"venue"
},
  "geometry": {"coordinates":[-80.77904100000001,41.289105],"type":"Point"}
}