{
  "type": "Feature",
  "properties": {
    "addr:full":"799 Holiday Ave Uhrichsville OH 44683",
    "addr:housenumber":"799",
    "addr:postcode":"44683",
    "addr:street":"Holiday Ave",
    "iso:country":"US",
    "sg:address":"799 Holiday Ave",
    "sg:city":"Uhrichsville",
    "sg:classifiers":[
        {
            "category":"Wholesale",
            "subcategory":"Electrical",
            "type":"Manufacturing & Wholesale Goods"
        }
    ],
    "sg:phone":"+1 740 922 9660",
    "sg:postcode":"44683",
    "sg:province":"OH",
    "wof:name":"Charlie Robinson",
    "wof:placetype":"venue"
},
  "geometry": {"coordinates":[-81.35420999999999,40.3853],"type":"Point"}
}