{
  "type": "Feature",
  "properties": {
    "iso:country":"US",
    "sg:address":"20700 Wakefield Cir",
    "sg:city":"Strongsville",
    "sg:classifiers":[
        {
            "category":"Wholesale",
            "subcategory":"Machinery & Supplies",
            "type":"Manufacturing & Wholesale Goods"
        }
    ],
    "sg:phone":"+1 440 572 0276",
    "sg:postcode":"44149",
    "sg:province":"OH",
    "sg:tags":[
        "equipment",
        "industrial"
    ],
    "wof:name":"North Coast Material Handling",
    "wof:placetype":"venue"
},
  "geometry": {"coordinates":[-81.854851,41.287572],"type":"Point"}
}