{
  "type": "Feature",
  "properties": {
    "iso:country":"US",
    "sg:address":"2218 Berrywood Dr",
    "sg:city":"Cincinnati",
    "sg:classifiers":[
        {
            "category":"Building & Trades",
            "subcategory":"Cleaning & Sanitation",
            "type":"Services"
        }
    ],
    "sg:phone":"+1 513 232 8453",
    "sg:postcode":"45244",
    "sg:province":"OH",
    "sg:tags":[
        "ceiling",
        "maintenance"
    ],
    "wof:name":"Cincinnati Ceilings",
    "wof:placetype":"venue"
},
  "geometry": {"coordinates":[-84.346493,39.095493],"type":"Point"}
}