{
  "type": "Feature",
  "properties": {
    "iso:country":"US",
    "sg:address":"1709 Brintnall Dr",
    "sg:city":"Brunswick",
    "sg:classifiers":[
        {
            "category":"Real Estate",
            "subcategory":"Real Estate Operator",
            "type":"Services"
        }
    ],
    "sg:phone":"+1 330 273 5064",
    "sg:postcode":"44212",
    "sg:province":"OH",
    "sg:tags":[
        "building",
        "nonresidential"
    ],
    "wof:name":"Steven Carroll Properties Inc",
    "wof:placetype":"venue"
},
  "geometry": {"coordinates":[-81.831917,41.228744],"type":"Point"}
}