{
  "type": "Feature",
  "properties": {
    "addr:full":"2700 Washington Ave Cleveland OH 44113",
    "addr:housenumber":"2700",
    "addr:postcode":"44113",
    "addr:street":"Washington Ave",
    "iso:country":"US",
    "sg:address":"2700 Washington Ave",
    "sg:city":"Cleveland",
    "sg:classifiers":[
        {
            "category":"Professional",
            "type":"Services"
        }
    ],
    "sg:phone":"+1 216 781 6138",
    "sg:postcode":"44113",
    "sg:province":"OH",
    "sg:tags":[
        "establishment"
    ],
    "wof:name":"Golden Age Ctr - Greater",
    "wof:placetype":"venue"
},
  "geometry": {"coordinates":[-81.709181,41.492582],"type":"Point"}
}