{
  "type": "Feature",
  "properties": {
    "addr:full": "5021 W 161st St Cleveland OH 44142",
    "addr:housenumber": "5021",
    "addr:postcode": "44142",
    "addr:street": "W 161St St",
    "iso:country": "US",
    "sg:address": "5021 W 161st St",
    "sg:city": "Cleveland",
    "sg:classifiers": [
      {
        "category": "Wholesale",
        "subcategory": "Machinery \u0026 Supplies",
        "type": "Manufacturing \u0026 Wholesale Goods"
      }
    ],
    "sg:phone": "+1 216 362 1277",
    "sg:postcode": "44142",
    "sg:province": "OH",
    "sg:tags": [
      "ladder"
    ],
    "wof:name": "Buckeye Ladder Co",
    "wof:placetype": "venue"
  },
  "geometry": {"coordinates":[-81.811147,41.413752],"type":"Point"}
}
