{
  "type": "Feature",
  "properties": {
    "iso:country":"US",
    "sg:address":"5021 W 161st St",
    "sg:city":"Cleveland",
    "sg:classifiers":[
        {
            "category":"Wholesale",
            "subcategory":"Machinery & Supplies",
            "type":"Manufacturing & Wholesale Goods"
        }
    ],
    "sg:phone":"+1 216 362 1277",
    "sg:postcode":"44142",
    "sg:province":"OH",
    "sg:tags":[
        "ladder"
    ],
    "wof:name":"Buckeye Ladder Co",
    "wof:placetype":"venue"
},
  "geometry": {"coordinates":[-81.81114700000001,41.413752],"type":"Point"}
}