{
  "type": "Feature",
  "properties": {
    "iso:country":"US",
    "sg:address":"2034 S Alex Rd",
    "sg:city":"Dayton",
    "sg:classifiers":[
        {
            "category":"Local Transit",
            "type":"Transportation"
        }
    ],
    "sg:phone":"+1 937 865 5804",
    "sg:postcode":"45449",
    "sg:province":"OH",
    "sg:tags":[
        "ambulance"
    ],
    "wof:name":"Emt",
    "wof:placetype":"venue"
},
  "geometry": {"coordinates":[-84.243129,39.645725],"type":"Point"}
}