{
  "type": "Feature",
  "properties": {
    "addr:full":"595 1/2 S. 3rd St. Columbus OH 43215",
    "addr:housenumber":"595 1 / 2",
    "addr:postcode":"43215",
    "addr:street":"S. 3Rd St.",
    "iso:country":"US",
    "sg:address":"595 1/2 S. 3rd St.",
    "sg:city":"Columbus",
    "sg:classifiers":[
        {
            "category":"Professional",
            "subcategory":"Computer Services",
            "type":"Services"
        }
    ],
    "sg:phone":"+1 810 373 2377",
    "sg:postcode":"43215",
    "sg:province":"OH",
    "sg:tags":[
        "sms",
        "text-message",
        "platform",
        "api",
        "mobile",
        "wireless",
        "development",
        "product",
        "lean",
        "startup",
        "short-message-service",
        "ohdontforget",
        "antitow",
        "ref",
        "vampireads"
    ],
    "sg:website":"http://www.recessmobile.com",
    "wof:name":"Recess Mobile",
    "wof:placetype":"venue"
},
  "geometry": {"coordinates":[-82.997843,39.961815],"type":"Point"}
}