{
  "type": "Feature",
  "properties": {
    "addr:full": "4560 Rybolt Rd Cincinnati OH 45248",
    "addr:housenumber": "4560",
    "addr:postcode": "45248",
    "addr:street": "Rybolt Rd",
    "iso:country": "US",
    "sg:address": "4560 Rybolt Rd",
    "sg:city": "Cincinnati",
    "sg:classifiers": [
      {
        "category": "Manufacturing",
        "subcategory": "Printing",
        "type": "Manufacturing \u0026 Wholesale Goods"
      }
    ],
    "sg:phone": "+1 513 574 3636",
    "sg:postcode": "45248",
    "sg:province": "OH",
    "wof:name": "S \u0026 J Design",
    "wof:placetype": "venue"
  },
  "geometry": {"coordinates":[-84.666504,39.177703],"type":"Point"}
}
