{
  "type": "Feature",
  "properties": {
    "iso:country":"US",
    "sg:address":"4526 Tuscarawas St W",
    "sg:city":"Canton",
    "sg:classifiers":[
        {
            "category":"Restaurant",
            "type":"Food & Drink"
        }
    ],
    "sg:menulink":"http://www.allmenus.com/oh/perry-heights/79184-pizza-hut/menu/",
    "sg:phone":"+1 330 478 1800",
    "sg:postcode":"44708",
    "sg:province":"OH",
    "sg:tags":[
        "american",
        "pizza"
    ],
    "wof:name":"Pizza Hut",
    "wof:placetype":"venue"
},
  "geometry": {"coordinates":[-81.42931299999999,40.795829],"type":"Point"}
}