{
  "type": "Feature",
  "properties": {
    "iso:country":"US",
    "sg:address":"3889 S Main St",
    "sg:city":"Mineral Ridge",
    "sg:classifiers":[
        {
            "category":"Organizations",
            "subcategory":"Community Association",
            "type":"Services"
        }
    ],
    "sg:phone":"+1 330 652 8768",
    "sg:postcode":"44440",
    "sg:province":"OH",
    "sg:tags":[
        "military"
    ],
    "sg:website":"www.vfw.org",
    "wof:name":"Veterans Of Foreign Wars",
    "wof:placetype":"venue"
},
  "geometry": {"coordinates":[-80.768788,41.139245],"type":"Point"}
}