{
  "type": "Feature",
  "properties": {
    "iso:country":"US",
    "sg:address":"3090 Angel Dr",
    "sg:city":"Bethel",
    "sg:classifiers":[
        {
            "category":"Health Services",
            "subcategory":"Clinic",
            "type":"Services"
        }
    ],
    "sg:phone":"+1 800 854 6555",
    "sg:postcode":"45106",
    "sg:province":"OH",
    "sg:tags":[
        "specialty",
        "outpatient"
    ],
    "sg:website":"www.emrinfo.com",
    "wof:name":"Sipple Clinic",
    "wof:placetype":"venue"
},
  "geometry": {"coordinates":[-84.09087100000001,38.963402],"type":"Point"}
}