{
  "type": "Feature",
  "properties": {
    "iso:country":"US",
    "sg:address":"5059 Newmans-Cardington Rd E",
    "sg:city":"Cardington",
    "sg:phone":"+1 419 864 7103",
    "sg:postcode":"43315",
    "sg:province":"OH",
    "sg:tags":[
        "farm",
        "corn",
        "wheat",
        "soybean"
    ],
    "wof:name":"E & H Farms",
    "wof:placetype":"venue"
},
  "geometry": {"coordinates":[-82.985018,40.499067],"type":"Point"}
}