{
  "type": "Feature",
  "properties": {
    "addr:full": "5059 Newmans-Cardington Rd E Cardington OH 43315",
    "addr:housenumber": "5059",
    "addr:postcode": "43315",
    "addr:street": "Newmans-Cardington Rd E",
    "iso:country": "US",
    "sg:address": "5059 Newmans-Cardington Rd E",
    "sg:city": "Cardington",
    "sg:phone": "+1 419 864 7103",
    "sg:postcode": "43315",
    "sg:province": "OH",
    "sg:tags": [
      "farm",
      "corn",
      "wheat",
      "soybean"
    ],
    "wof:name": "E \u0026 H Farms",
    "wof:placetype": "venue"
  },
  "geometry": {"coordinates":[-82.985018,40.499067],"type":"Point"}
}
