{
  "type": "Feature",
  "properties": {
    "addr:full": "1990 Graham Rd Cuyahoga Falls OH 44224",
    "addr:housenumber": "1990",
    "addr:postcode": "44224",
    "addr:street": "Graham Rd",
    "iso:country": "US",
    "sg:address": "1990 Graham Rd",
    "sg:city": "Cuyahoga Falls",
    "sg:classifiers": [
      {
        "category": "Real Estate",
        "subcategory": "Real Estate Agent",
        "type": "Services"
      }
    ],
    "sg:phone": "+1 330 689 0700",
    "sg:postcode": "44224",
    "sg:province": "OH",
    "wof:name": "Penney Real Estate Co",
    "wof:placetype": "venue"
  },
  "geometry": {"coordinates":[-81.443947,41.166717],"type":"Point"}
}
