{
  "type": "Feature",
  "properties": {
    "addr:full": "900 W Vine St Mt Vernon OH 43050",
    "addr:housenumber": "900",
    "addr:postcode": "43050",
    "addr:street": "W Vine St",
    "iso:country": "US",
    "sg:address": "900 W Vine St",
    "sg:city": "Mt Vernon",
    "sg:classifiers": [
      {
        "category": "Education",
        "subcategory": "School",
        "type": "Public Place"
      }
    ],
    "sg:phone": "+1 740 393 6769",
    "sg:postcode": "43050",
    "sg:province": "OH",
    "wof:name": "KNOX County Alternative Ctr",
    "wof:placetype": "venue"
  },
  "geometry": {"coordinates":[-82.497807,40.393243],"type":"Point"}
}
