{
  "type": "Feature",
  "properties": {
    "iso:country":"US",
    "sg:address":"900 W Vine St",
    "sg:city":"Mt Vernon",
    "sg:classifiers":[
        {
            "category":"Education",
            "subcategory":"School",
            "type":"Public Place"
        }
    ],
    "sg:phone":"+1 740 393 6769",
    "sg:postcode":"43050",
    "sg:province":"OH",
    "wof:name":"KNOX County Alternative Ctr",
    "wof:placetype":"venue"
},
  "geometry": {"coordinates":[-82.49780699999999,40.393243],"type":"Point"}
}