{
  "type": "Feature",
  "properties": {
    "addr:full": "400 E Auburn Ave Bellefontaine OH 43311",
    "addr:housenumber": "400",
    "addr:postcode": "43311",
    "addr:street": "E Auburn Ave",
    "iso:country": "US",
    "sg:address": "400 E Auburn Ave",
    "sg:city": "Bellefontaine",
    "sg:classifiers": [
      {
        "category": "Real Estate",
        "subcategory": "Real Estate Operator",
        "type": "Services"
      }
    ],
    "sg:phone": "+1 937 599 2334",
    "sg:postcode": "43311",
    "sg:province": "OH",
    "sg:tags": [
      "building",
      "nonresidential"
    ],
    "wof:name": "Patrician Properties LTD",
    "wof:placetype": "venue"
  },
  "geometry": {"coordinates":[-83.754426,40.357954],"type":"Point"}
}
