{
  "type": "Feature",
  "properties": {
    "iso:country":"US",
    "sg:address":"400 E Auburn Ave",
    "sg:city":"Bellefontaine",
    "sg:classifiers":[
        {
            "category":"Real Estate",
            "subcategory":"Real Estate Operator",
            "type":"Services"
        }
    ],
    "sg:phone":"+1 937 599 2334",
    "sg:postcode":"43311",
    "sg:province":"OH",
    "sg:tags":[
        "building",
        "nonresidential"
    ],
    "wof:name":"Patrician Properties LTD",
    "wof:placetype":"venue"
},
  "geometry": {"coordinates":[-83.754426,40.357954],"type":"Point"}
}