{
  "type": "Feature",
  "properties": {
    "addr:full":"29 E Ashtabula St Jefferson OH 44047",
    "addr:housenumber":"29",
    "addr:postcode":"44047",
    "addr:street":"E Ashtabula St",
    "iso:country":"US",
    "sg:address":"29 E Ashtabula St",
    "sg:city":"Jefferson",
    "sg:classifiers":[
        {
            "category":"Real Estate",
            "subcategory":"Developer",
            "type":"Services"
        }
    ],
    "sg:phone":"+1 440 576 5551",
    "sg:postcode":"44047",
    "sg:province":"OH",
    "sg:tags":[
        "land",
        "surveying"
    ],
    "wof:name":"Westfall Land Surveying",
    "wof:placetype":"venue"
},
  "geometry": {"coordinates":[-80.764268,41.742393],"type":"Point"}
}