{
  "type": "Feature",
  "properties": {
    "addr:full": "5610 Alan Moss Ct Dublin OH 43017",
    "addr:housenumber": "5610",
    "addr:postcode": "43017",
    "addr:street": "Alan Moss Ct",
    "iso:country": "US",
    "sg:address": "5610 Alan Moss Ct",
    "sg:city": "Dublin",
    "sg:classifiers": [
      {
        "category": "Retail",
        "subcategory": "Veterinary Services",
        "type": "Services"
      }
    ],
    "sg:phone": "+1 614 424 5259",
    "sg:postcode": "43017",
    "sg:province": "OH",
    "sg:tags": [
      "specialty"
    ],
    "wof:name": "John Johnson Dvm",
    "wof:placetype": "venue"
  },
  "geometry": {"coordinates":[-83.143069,40.11489],"type":"Point"}
}
