{
  "type": "Feature",
  "properties": {
    "addr:full": "7200 Corduroy Rd Oregon OH 43618",
    "addr:housenumber": "7200",
    "addr:postcode": "43618",
    "addr:street": "Corduroy Rd",
    "iso:country": "US",
    "sg:address": "7200 Corduroy Rd",
    "sg:city": "Oregon",
    "sg:classifiers": [
      {
        "category": "Restaurant",
        "type": "Food \u0026 Drink"
      }
    ],
    "sg:phone": "+1 419 836 8500",
    "sg:postcode": "43618",
    "sg:province": "OH",
    "sg:tags": [
      "eating"
    ],
    "wof:name": "Rons Concessions",
    "wof:placetype": "venue"
  },
  "geometry": {"coordinates":[-83.374091,41.660122],"type":"Point"}
}
