{
  "type": "Feature",
  "properties": {
    "addr:full": "7601 Broadview Rd Cleveland OH 44131",
    "addr:housenumber": "7601",
    "addr:postcode": "44131",
    "addr:street": "Broadview Rd",
    "iso:country": "US",
    "sg:address": "7601 Broadview Rd",
    "sg:city": "Cleveland",
    "sg:classifiers": [
      {
        "category": "Personal",
        "subcategory": "Beauty Salon",
        "type": "Services"
      }
    ],
    "sg:phone": "+1 216 447 4040",
    "sg:postcode": "44131",
    "sg:province": "OH",
    "sg:tags": [
      "shop"
    ],
    "wof:name": "Michael's Hair Design",
    "wof:placetype": "venue"
  },
  "geometry": {"coordinates":[-81.684506,41.359258],"type":"Point"}
}
