{
  "type": "Feature",
  "properties": {
    "addr:full": "20303 Albion Rd Strongsville OH 44149",
    "addr:housenumber": "20303",
    "addr:postcode": "44149",
    "addr:street": "Albion Rd",
    "iso:country": "US",
    "sg:address": "20303 Albion Rd",
    "sg:city": "Strongsville",
    "sg:classifiers": [
      {
        "category": "Building \u0026 Trades",
        "subcategory": "Electrical",
        "type": "Services"
      }
    ],
    "sg:phone": "+1 440 238 3955",
    "sg:postcode": "44149",
    "sg:province": "OH",
    "sg:tags": [
      "electrical",
      "contractor"
    ],
    "wof:name": "Emerald Electric \u0026 Constructio",
    "wof:placetype": "venue"
  },
  "geometry": {"coordinates":[-81.849401,41.331609],"type":"Point"}
}
