{
  "type": "Feature",
  "properties": {
    "addr:full":"3631 Marine Rd Toledo OH 43609",
    "addr:housenumber":"3631",
    "addr:postcode":"43609",
    "addr:street":"Marine Rd",
    "iso:country":"US",
    "sg:address":"3631 Marine Rd",
    "sg:city":"Toledo",
    "sg:classifiers":[
        {
            "category":"Wholesale",
            "subcategory":"Machinery & Supplies",
            "type":"Manufacturing & Wholesale Goods"
        }
    ],
    "sg:phone":"+1 419 841 3104",
    "sg:postcode":"43609",
    "sg:province":"OH",
    "sg:tags":[
        "machine",
        "sewing"
    ],
    "wof:name":"Toledo Industrial Sewing Mchns",
    "wof:placetype":"venue"
},
  "geometry": {"coordinates":[-83.630128,41.629504],"type":"Point"}
}