{
  "type": "Feature",
  "properties": {
    "addr:full":"27106 E Oviatt Rd Cleveland OH 44140",
    "addr:housenumber":"27106",
    "addr:postcode":"44140",
    "addr:street":"E Oviatt Rd",
    "iso:country":"US",
    "sg:address":"27106 E Oviatt Rd",
    "sg:city":"Cleveland",
    "sg:classifiers":[
        {
            "category":"Government",
            "subcategory":"Post Office",
            "type":"Public Place"
        }
    ],
    "sg:phone":"+1 440 835 6517",
    "sg:postcode":"44140",
    "sg:province":"OH",
    "wof:name":"US Post Office",
    "wof:placetype":"venue"
},
  "geometry": {"coordinates":[-81.91856300000001,41.479544],"type":"Point"}
}