{
  "type": "Feature",
  "properties": {
    "addr:full": "25621 Shoemaker Rd Circleville OH 43113",
    "addr:postcode": "25621;43113",
    "addr:street": "Shoemaker Rd",
    "iso:country": "US",
    "sg:address": "25621 Shoemaker Rd",
    "sg:city": "Circleville",
    "sg:classifiers": [
      {
        "category": "Building \u0026 Trades",
        "subcategory": "Plumbing",
        "type": "Services"
      }
    ],
    "sg:phone": "+1 740 773 3733",
    "sg:postcode": "43113",
    "sg:province": "OH",
    "sg:tags": [
      "conditioning",
      "air",
      "system",
      "contractor"
    ],
    "wof:name": "Liberty Heating \u0026 Cooling",
    "wof:placetype": "venue"
  },
  "geometry": {"coordinates":[-82.825101,39.550242],"type":"Point"}
}
