{
  "type": "Feature",
  "properties": {
    "iso:country":"US",
    "sg:address":"25621 Shoemaker Rd",
    "sg:city":"Circleville",
    "sg:classifiers":[
        {
            "category":"Building & Trades",
            "subcategory":"Plumbing",
            "type":"Services"
        }
    ],
    "sg:phone":"+1 740 773 3733",
    "sg:postcode":"43113",
    "sg:province":"OH",
    "sg:tags":[
        "conditioning",
        "air",
        "system",
        "contractor"
    ],
    "wof:name":"Liberty Heating & Cooling",
    "wof:placetype":"venue"
},
  "geometry": {"coordinates":[-82.825101,39.550242],"type":"Point"}
}