{
  "type": "Feature",
  "properties": {
    "iso:country":"US",
    "sg:address":"3900 Sullivant Ave",
    "sg:city":"Columbus",
    "sg:classifiers":[
        {
            "category":"Manufacturing",
            "subcategory":"Metals",
            "type":"Manufacturing & Wholesale Goods"
        }
    ],
    "sg:phone":"+1 614 276 9900",
    "sg:postcode":"43228",
    "sg:province":"OH",
    "sg:tags":[
        "fabricator",
        "sheet"
    ],
    "sg:website":"www.accfab.com",
    "wof:name":"Accurate Fabrication Inc",
    "wof:placetype":"venue"
},
  "geometry": {"coordinates":[-83.10235900000001,39.942336],"type":"Point"}
}