{
  "type": "Feature",
  "properties": {
    "iso:country":"US",
    "sg:address":"3440 Granite Cir",
    "sg:city":"Toledo",
    "sg:classifiers":[
        {
            "category":"Shopping",
            "subcategory":"Computers & Home Electronics",
            "type":"Retail Goods"
        }
    ],
    "sg:phone":"+1 614 210 0545",
    "sg:postcode":"43617",
    "sg:province":"OH",
    "sg:tags":[
        "software"
    ],
    "sg:website":"www.pro-activesolutions.com",
    "wof:name":"Pro-Active Solutions",
    "wof:placetype":"venue"
},
  "geometry": {"coordinates":[-83.714491,41.68017],"type":"Point"}
}