{
  "type": "Feature",
  "properties": {
    "addr:full": "197 E Center St Marion OH 43302",
    "addr:housenumber": "197",
    "addr:postcode": "43302",
    "addr:street": "E Center St",
    "iso:country": "US",
    "sg:address": "197 E Center St",
    "sg:city": "Marion",
    "sg:classifiers": [
      {
        "category": "Organizations",
        "subcategory": "Religious Organization",
        "type": "Services"
      }
    ],
    "sg:phone": "+1 740 387 6220",
    "sg:postcode": "43302",
    "sg:province": "OH",
    "sg:tags": [
      "church"
    ],
    "wof:name": "St Paul's Episcopal Church",
    "wof:placetype": "venue"
  },
  "geometry": {"coordinates":[-83.126924,40.588647],"type":"Point"}
}
