{
  "type": "Feature",
  "properties": {
    "iso:country":"US",
    "sg:address":"644 Killian Rd",
    "sg:city":"Akron",
    "sg:classifiers":[
        {
            "category":"Manufacturing",
            "subcategory":"Tools & Machinery",
            "type":"Manufacturing & Wholesale Goods"
        }
    ],
    "sg:phone":"+1 330 644 7118",
    "sg:postcode":"44319",
    "sg:province":"OH",
    "sg:tags":[
        "machine",
        "shop",
        "job"
    ],
    "wof:name":"Ken-Dal Corporation",
    "wof:placetype":"venue"
},
  "geometry": {"coordinates":[-81.498043,40.997463],"type":"Point"}
}