{
  "type": "Feature",
  "properties": {
    "addr:full": "315 Broad St Ashland OH 44805",
    "addr:housenumber": "315",
    "addr:postcode": "44805",
    "addr:street": "Broad St",
    "iso:country": "US",
    "sg:address": "315 Broad St",
    "sg:city": "Ashland",
    "sg:classifiers": [
      {
        "category": "Wholesale",
        "subcategory": "Non-durable Goods",
        "type": "Manufacturing \u0026 Wholesale Goods"
      }
    ],
    "sg:phone": "+1 419 289 6909",
    "sg:postcode": "44805",
    "sg:province": "OH",
    "sg:tags": [
      "advertising"
    ],
    "wof:name": "H \u0026 S Promotional Products",
    "wof:placetype": "venue"
  },
  "geometry": {"coordinates":[-82.320339,40.867436],"type":"Point"}
}
