{
  "type": "Feature",
  "properties": {
    "addr:full":"4822 Mahoning Ave Youngstown OH 44515",
    "addr:housenumber":"4822",
    "addr:postcode":"44515",
    "addr:street":"Mahoning Ave",
    "iso:country":"US",
    "sg:address":"4822 Mahoning Ave",
    "sg:city":"Youngstown",
    "sg:classifiers":[
        {
            "category":"Retail",
            "subcategory":"Auto Repair",
            "type":"Services"
        }
    ],
    "sg:phone":"+1 330 792 8462",
    "sg:postcode":"44515",
    "sg:province":"OH",
    "sg:tags":[
        "general"
    ],
    "wof:name":"Valvoline Instant Oil Change",
    "wof:placetype":"venue"
},
  "geometry": {"coordinates":[-80.748507,41.100182],"type":"Point"}
}