{
  "type": "Feature",
  "properties": {
    "iso:country":"US",
    "sg:address":"513 Sunset Blvd",
    "sg:city":"Wadsworth",
    "sg:classifiers":[
        {
            "category":"Utilities",
            "subcategory":"Mobile Phone",
            "type":"Services"
        }
    ],
    "sg:phone":"+1 330 336 4407",
    "sg:postcode":"44281",
    "sg:province":"OH",
    "sg:tags":[
        "communication",
        "radiotelephone"
    ],
    "wof:name":"R&R Communications",
    "wof:placetype":"venue"
},
  "geometry": {"coordinates":[-81.74575400000001,41.025608],"type":"Point"}
}