{
  "type": "Feature",
  "properties": {
    "addr:full": "513 Sunset Blvd Wadsworth OH 44281",
    "addr:housenumber": "513",
    "addr:postcode": "44281",
    "addr:street": "Sunset Blvd",
    "iso:country": "US",
    "sg:address": "513 Sunset Blvd",
    "sg:city": "Wadsworth",
    "sg:classifiers": [
      {
        "category": "Utilities",
        "subcategory": "Mobile Phone",
        "type": "Services"
      }
    ],
    "sg:phone": "+1 330 336 4407",
    "sg:postcode": "44281",
    "sg:province": "OH",
    "sg:tags": [
      "communication",
      "radiotelephone"
    ],
    "wof:name": "R\u0026R Communications",
    "wof:placetype": "venue"
  },
  "geometry": {"coordinates":[-81.745754,41.025608],"type":"Point"}
}
