{
  "type": "Feature",
  "properties": {
    "addr:full":"6219 W 130th St Cleveland OH 44130",
    "addr:housenumber":"6219",
    "addr:postcode":"44130",
    "addr:street":"W 130Th St",
    "iso:country":"US",
    "sg:address":"6219 W 130th St",
    "sg:city":"Cleveland",
    "sg:classifiers":[
        {
            "category":"Food & Beverages",
            "subcategory":"Groceries & Convenience Stores",
            "type":"Retail Goods"
        }
    ],
    "sg:phone":"+1 216 676 9253",
    "sg:postcode":"44130",
    "sg:province":"OH",
    "sg:tags":[
        "grocer"
    ],
    "wof:name":"Dairy Deli",
    "wof:placetype":"venue"
},
  "geometry": {"coordinates":[-81.784398,41.396642],"type":"Point"}
}