{
  "type": "Feature",
  "properties": {
    "iso:country":"US",
    "sg:address":"106 Harding Way E",
    "sg:city":"Galion",
    "sg:classifiers":[
        {
            "category":"Government",
            "subcategory":"Office",
            "type":"Public Place"
        }
    ],
    "sg:phone":"+1 419 468 6801",
    "sg:postcode":"44833",
    "sg:province":"OH",
    "sg:tags":[
        "executive"
    ],
    "wof:name":"Galion Industrial Development",
    "wof:placetype":"venue"
},
  "geometry": {"coordinates":[-82.78940799999999,40.73395],"type":"Point"}
}