{
  "type": "Feature",
  "properties": {
    "iso:country":"US",
    "sg:address":"699 Harrisburg Pike",
    "sg:city":"Columbus",
    "sg:classifiers":[
        {
            "category":"Personal",
            "subcategory":"Beauty Salon",
            "type":"Services"
        }
    ],
    "sg:phone":"+1 614 272 9123",
    "sg:postcode":"43223",
    "sg:province":"OH",
    "sg:tags":[
        "manicuring"
    ],
    "wof:name":"Beautiful Nails",
    "wof:placetype":"venue"
},
  "geometry": {"coordinates":[-83.037311,39.943721],"type":"Point"}
}