{
  "type": "Feature",
  "properties": {
    "addr:full":"90 Hospital Dr Athens OH 45701",
    "addr:housenumber":"90",
    "addr:postcode":"45701",
    "addr:street":"Hospital Dr",
    "iso:country":"US",
    "sg:address":"90 Hospital Dr",
    "sg:city":"Athens",
    "sg:classifiers":[
        {
            "category":"Health Services",
            "subcategory":"Hospital",
            "type":"Services"
        }
    ],
    "sg:phone":"+1 740 592 3091",
    "sg:postcode":"45701",
    "sg:province":"OH",
    "sg:tags":[
        "mental"
    ],
    "wof:name":"Tri County Mental Health Svc",
    "wof:placetype":"venue"
},
  "geometry": {"coordinates":[-82.115651,39.328897],"type":"Point"}
}