{
  "type": "Feature",
  "properties": {
    "addr:full": "10245 Milton-Potsdam Rd West Milton OH 45383",
    "addr:housenumber": "10245",
    "addr:postcode": "45383",
    "addr:street": "Milton-Potsdam Rd West",
    "iso:country": "US",
    "sg:address": "10245 Milton-Potsdam Rd",
    "sg:city": "West Milton",
    "sg:classifiers": [
      {
        "category": "Organizations",
        "subcategory": "Religious Organization",
        "type": "Services"
      }
    ],
    "sg:phone": "+1 937 698 5350",
    "sg:postcode": "45383",
    "sg:province": "OH",
    "sg:tags": [
      "clergy"
    ],
    "wof:name": "Eugene M Baker",
    "wof:placetype": "venue"
  },
  "geometry": {"coordinates":[-84.39354,39.963564],"type":"Point"}
}
