{
  "type": "Feature",
  "properties": {
    "iso:country":"US",
    "sg:address":"6505 Angola Rd",
    "sg:city":"Holland",
    "sg:classifiers":[
        {
            "category":"Professional",
            "type":"Services"
        }
    ],
    "sg:phone":"+1 419 867 3944",
    "sg:postcode":"43528",
    "sg:province":"OH",
    "wof:name":"Slot World Inc",
    "wof:placetype":"venue"
},
  "geometry": {"coordinates":[-83.69591,41.624356],"type":"Point"}
}