{
  "type": "Feature",
  "properties": {
    "addr:full": "5644 Monroe St Sylvania OH 43560",
    "addr:housenumber": "5644",
    "addr:postcode": "43560",
    "addr:street": "Monroe St",
    "iso:country": "US",
    "sg:address": "5644 Monroe St",
    "sg:city": "Sylvania",
    "sg:classifiers": [
      {
        "category": "Shopping",
        "subcategory": "Hobbies, Toys, \u0026 Games",
        "type": "Retail Goods"
      }
    ],
    "sg:phone": "+1 419 824 6252",
    "sg:postcode": "43560",
    "sg:province": "OH",
    "sg:tags": [
      "supply"
    ],
    "wof:name": "Gags \u0026 Games Holloween USA",
    "wof:placetype": "venue"
  },
  "geometry": {"coordinates":[-83.674183,41.709042],"type":"Point"}
}
