{
  "type": "Feature",
  "properties": {
    "addr:full":"4393 Ridge Rd Cleveland OH 44144",
    "addr:housenumber":"4393",
    "addr:postcode":"44144",
    "addr:street":"Ridge Rd",
    "iso:country":"US",
    "sg:address":"4393 Ridge Rd",
    "sg:city":"Cleveland",
    "sg:classifiers":[
        {
            "category":"Autos & Motor Vehicles",
            "subcategory":"Fuel & Gas Station",
            "type":"Retail Goods"
        }
    ],
    "sg:phone":"+1 216 398 9945",
    "sg:postcode":"44144",
    "sg:province":"OH",
    "sg:tags":[
        "station",
        "gasoline"
    ],
    "wof:name":"Zeeway Gas-N-Go",
    "wof:placetype":"venue"
},
  "geometry": {"coordinates":[-81.735247,41.436668],"type":"Point"}
}