{
  "type": "Feature",
  "properties": {
    "addr:full":"2911 Erie Ave Cincinnati OH 45208",
    "addr:housenumber":"2911",
    "addr:postcode":"45208",
    "addr:street":"Erie Ave",
    "iso:country":"US",
    "sg:address":"2911 Erie Ave",
    "sg:city":"Cincinnati",
    "sg:classifiers":[
        {
            "category":"Professional",
            "type":"Services"
        }
    ],
    "sg:phone":"+1 513 556 0954",
    "sg:postcode":"45208",
    "sg:province":"OH",
    "wof:name":"Gerald Matthews",
    "wof:placetype":"venue"
},
  "geometry": {"coordinates":[-84.434364,39.138687],"type":"Point"}
}