{
  "type": "Feature",
  "properties": {
    "addr:full": "21 Ludlow St Hamilton OH 45011",
    "addr:housenumber": "21",
    "addr:postcode": "45011",
    "addr:street": "Ludlow St",
    "iso:country": "US",
    "sg:address": "21 Ludlow St",
    "sg:city": "Hamilton",
    "sg:classifiers": [
      {
        "category": "Professional",
        "type": "Services"
      }
    ],
    "sg:phone": "+1 513 893 0784",
    "sg:postcode": "45011",
    "sg:province": "OH",
    "wof:name": "Ronald G Gardner",
    "wof:placetype": "venue"
  },
  "geometry": {"coordinates":[-84.564487,39.39821],"type":"Point"}
}
