{
  "type": "Feature",
  "properties": {
    "iso:country":"US",
    "sg:address":"395 Reed St",
    "sg:city":"Mansfield",
    "sg:classifiers":[
        {
            "category":"Home & Garden",
            "subcategory":"Building Materials",
            "type":"Retail Goods"
        }
    ],
    "sg:phone":"+1 419 525 2222",
    "sg:postcode":"44903",
    "sg:province":"OH",
    "sg:tags":[
        "windows"
    ],
    "sg:website":"www.bayworldmfg.com",
    "wof:name":"Bay World Intl Inc",
    "wof:placetype":"venue"
},
  "geometry": {"coordinates":[-82.52843,40.769348],"type":"Point"}
}