{
  "type": "Feature",
  "properties": {
    "addr:full": "12431 Co Rd 32 Bellevue OH 44811",
    "addr:housenumber": "12431;32",
    "addr:postcode": "44811",
    "addr:street": "Co Rd",
    "iso:country": "US",
    "sg:address": "12431 Co Rd 32",
    "sg:city": "Bellevue",
    "sg:phone": "+1 419 483 7802",
    "sg:postcode": "44811",
    "sg:province": "OH",
    "sg:tags": [
      "farm",
      "wheat",
      "soybean"
    ],
    "wof:name": "William Covert",
    "wof:placetype": "venue"
  },
  "geometry": {"coordinates":[-82.834884,41.34184],"type":"Point"}
}
