{
  "type": "Feature",
  "properties": {
    "addr:full":"111 S Cleveland Ave Mogadore OH 44260",
    "addr:housenumber":"111",
    "addr:postcode":"44260",
    "addr:street":"S Cleveland Ave",
    "iso:country":"US",
    "sg:address":"111 S Cleveland Ave",
    "sg:city":"Mogadore",
    "sg:classifiers":[
        {
            "category":"Government",
            "subcategory":"Police Station",
            "type":"Public Place"
        }
    ],
    "sg:phone":"+1 330 633 4404",
    "sg:postcode":"44260",
    "sg:province":"OH",
    "sg:tags":[
        "department"
    ],
    "wof:name":"Mogadore Police Dept",
    "wof:placetype":"venue"
},
  "geometry": {"coordinates":[-81.393073,41.047324],"type":"Point"}
}