{
  "type": "Feature",
  "properties": {
    "iso:country":"US",
    "sg:address":"1201 N Lathrop Rd",
    "sg:city":"Swanton",
    "sg:classifiers":[
        {
            "category":"Professional",
            "type":"Services"
        }
    ],
    "sg:phone":"+1 419 829 3308",
    "sg:postcode":"43558",
    "sg:province":"OH",
    "sg:tags":[
        "establishment"
    ],
    "wof:name":"Myers John S",
    "wof:placetype":"venue"
},
  "geometry": {"coordinates":[-83.856461,41.647689],"type":"Point"}
}