{
  "type": "Feature",
  "properties": {
    "addr:full":"7437 Oakmeadows Dr Worthington OH 43085",
    "addr:housenumber":"7437",
    "addr:postcode":"43085",
    "addr:street":"Oakmeadows Dr",
    "iso:country":"US",
    "sg:address":"7437 Oakmeadows Dr",
    "sg:city":"Worthington",
    "sg:classifiers":[
        {
            "category":"Manufacturing",
            "subcategory":"Printing",
            "type":"Manufacturing & Wholesale Goods"
        }
    ],
    "sg:phone":"+1 614 888 5233",
    "sg:postcode":"43085",
    "sg:province":"OH",
    "sg:tags":[
        "printer"
    ],
    "wof:name":"Signature Graphics",
    "wof:placetype":"venue"
},
  "geometry": {"coordinates":[-82.979375,40.117643],"type":"Point"}
}