{
  "type": "Feature",
  "properties": {
    "addr:full":"3414 Dorr St Toledo OH 43607",
    "addr:postcode":"3414;43607",
    "addr:street":"Dorr St",
    "iso:country":"US",
    "sg:address":"3414 Dorr St",
    "sg:city":"Toledo",
    "sg:classifiers":[
        {
            "category":"Real Estate",
            "subcategory":"Real Estate Operator",
            "type":"Services"
        }
    ],
    "sg:phone":"+1 419 536 1858",
    "sg:postcode":"43607",
    "sg:province":"OH",
    "sg:tags":[
        "building",
        "apartment"
    ],
    "wof:name":"University Circle Apartments",
    "wof:placetype":"venue"
},
  "geometry": {"coordinates":[-83.623451,41.652918],"type":"Point"}
}