{
  "type": "Feature",
  "properties": {
    "iso:country":"US",
    "sg:address":"533 E Market St",
    "sg:city":"Warren",
    "sg:classifiers":[
        {
            "category":"Health Services",
            "subcategory":"Health Practitioner",
            "type":"Services"
        }
    ],
    "sg:phone":"+1 330 395 0007",
    "sg:postcode":"44481",
    "sg:province":"OH",
    "sg:tags":[
        "nurse",
        "registry"
    ],
    "wof:name":"Precise Nursing",
    "wof:placetype":"venue"
},
  "geometry": {"coordinates":[-80.810935,41.236303],"type":"Point"}
}