{
  "type": "Feature",
  "properties": {
    "addr:full": "4001 N Stygler Rd Columbus OH 43230",
    "addr:housenumber": "4001",
    "addr:postcode": "43230",
    "addr:street": "N Stygler Rd",
    "iso:country": "US",
    "sg:address": "4001 N Stygler Rd",
    "sg:city": "Columbus",
    "sg:classifiers": [
      {
        "category": "Organizations",
        "subcategory": "Religious Organization",
        "type": "Services"
      }
    ],
    "sg:phone": "+1 614 471 2261",
    "sg:postcode": "43230",
    "sg:province": "OH",
    "wof:name": "Covenant Evangelical Church",
    "wof:placetype": "venue"
  },
  "geometry": {"coordinates":[-82.88887,40.038945],"type":"Point"}
}
