{
  "type": "Feature",
  "properties": {
    "addr:full": "2339 N 3 Bs and K Rd Sunbury OH 43074",
    "addr:housenumber": "2339;3",
    "addr:postcode": "43074",
    "addr:street": "N;And K Rd",
    "iso:country": "US",
    "sg:address": "2339 N 3 Bs and K Rd",
    "sg:city": "Sunbury",
    "sg:classifiers": [
      {
        "category": "Professional",
        "type": "Services"
      }
    ],
    "sg:phone": "+1 740 524 1522",
    "sg:postcode": "43074",
    "sg:province": "OH",
    "wof:name": "Leslie B McDonald",
    "wof:placetype": "venue"
  },
  "geometry": {"coordinates":[-82.934339,40.300867],"type":"Point"}
}
