{
  "type": "Feature",
  "properties": {
    "addr:full": "530 S Taft Ave Fremont OH 43420",
    "addr:housenumber": "530",
    "addr:postcode": "43420",
    "addr:street": "S Taft Ave",
    "iso:country": "US",
    "sg:address": "530 S Taft Ave",
    "sg:city": "Fremont",
    "sg:classifiers": [
      {
        "category": "Manufacturing",
        "subcategory": "Retail Goods",
        "type": "Manufacturing \u0026 Wholesale Goods"
      }
    ],
    "sg:phone": "+1 419 559 9689",
    "sg:postcode": "43420",
    "sg:province": "OH",
    "sg:tags": [
      "product",
      "mfg"
    ],
    "wof:name": "Bomb Mfg LLC",
    "wof:placetype": "venue"
  },
  "geometry": {"coordinates":[-83.1353,41.341722],"type":"Point"}
}
