{
  "type": "Feature",
  "properties": {
    "addr:full":"108 S Market St Mc Arthur OH 45651",
    "addr:housenumber":"108",
    "addr:postcode":"45651",
    "addr:street":"S Market St",
    "iso:country":"US",
    "sg:address":"108 S Market St",
    "sg:city":"Mc Arthur",
    "sg:classifiers":[
        {
            "category":"Professional",
            "subcategory":"Management & Consulting",
            "type":"Services"
        }
    ],
    "sg:phone":"+1 740 594 2276",
    "sg:postcode":"45651",
    "sg:province":"OH",
    "sg:tags":[
        "support",
        "facility"
    ],
    "wof:name":"TASC",
    "wof:placetype":"venue"
},
  "geometry": {"coordinates":[-82.478904,39.24654],"type":"Point"}
}