{
  "type": "Feature",
  "properties": {
    "iso:country":"US",
    "sg:address":"1431 6th St SW",
    "sg:city":"Canton",
    "sg:classifiers":[
        {
            "category":"Retail",
            "subcategory":"Auto Repair",
            "type":"Services"
        }
    ],
    "sg:phone":"+1 330 453 3003",
    "sg:postcode":"44707",
    "sg:province":"OH",
    "sg:tags":[
        "body",
        "automobile",
        "painting"
    ],
    "wof:name":"Classic Collision Ctr Inc",
    "wof:placetype":"venue"
},
  "geometry": {"coordinates":[-81.388326,40.797188],"type":"Point"}
}