{
  "type": "Feature",
  "properties": {
    "iso:country":"US",
    "sg:address":"959 Hebron Rd",
    "sg:city":"Heath",
    "sg:classifiers":[
        {
            "category":"Shopping",
            "subcategory":"Clothing, Apparel, & Fashions",
            "type":"Retail Goods"
        }
    ],
    "sg:phone":"+1 740 522 2733",
    "sg:postcode":"43056",
    "sg:province":"OH",
    "sg:website":"www.catofashions.com",
    "wof:name":"Cato",
    "wof:placetype":"venue"
},
  "geometry": {"coordinates":[-82.446675,40.026317],"type":"Point"}
}