{
  "type": "Feature",
  "properties": {
    "iso:country":"US",
    "sg:address":"6 E Broadway St",
    "sg:city":"Covington",
    "sg:classifiers":[
        {
            "category":"Autos & Motor Vehicles",
            "subcategory":"Fuel & Gas Station",
            "type":"Retail Goods"
        }
    ],
    "sg:phone":"+1 937 473 8164",
    "sg:postcode":"45318",
    "sg:province":"OH",
    "sg:tags":[
        "convenience",
        "station",
        "store"
    ],
    "wof:name":"Als BP Service",
    "wof:placetype":"venue"
},
  "geometry": {"coordinates":[-84.35471099999999,40.12133],"type":"Point"}
}