{
  "type": "Feature",
  "properties": {
    "addr:full": "6 E Broadway St Covington OH 45318",
    "addr:housenumber": "6",
    "addr:postcode": "45318",
    "addr:street": "E Broadway St",
    "iso:country": "US",
    "sg:address": "6 E Broadway St",
    "sg:city": "Covington",
    "sg:classifiers": [
      {
        "category": "Autos \u0026 Motor Vehicles",
        "subcategory": "Fuel \u0026 Gas Station",
        "type": "Retail Goods"
      }
    ],
    "sg:phone": "+1 937 473 8164",
    "sg:postcode": "45318",
    "sg:province": "OH",
    "sg:tags": [
      "convenience",
      "station",
      "store"
    ],
    "wof:name": "Als BP Service",
    "wof:placetype": "venue"
  },
  "geometry": {"coordinates":[-84.354711,40.12133],"type":"Point"}
}
