{
  "type": "Feature",
  "properties": {
    "addr:full":"3888 Crestfield Dr Groveport OH 43125",
    "addr:housenumber":"3888",
    "addr:postcode":"43125",
    "addr:street":"Crestfield Dr",
    "iso:country":"US",
    "sg:address":"3888 Crestfield Dr",
    "sg:city":"Groveport",
    "sg:classifiers":[
        {
            "category":"Professional",
            "subcategory":"Management & Consulting",
            "type":"Services"
        }
    ],
    "sg:phone":"+1 614 834 0464",
    "sg:postcode":"43125",
    "sg:province":"OH",
    "sg:tags":[
        "retail",
        "direct",
        "sales"
    ],
    "wof:name":"Allen L Betts",
    "wof:placetype":"venue"
},
  "geometry": {"coordinates":[-82.876949,39.89644],"type":"Point"}
}