{
  "type": "Feature",
  "properties": {
    "addr:full": "294 Avondale Ave Avon Lake OH 44012",
    "addr:housenumber": "294",
    "addr:postcode": "44012",
    "addr:street": "Avondale Ave",
    "iso:country": "US",
    "sg:address": "294 Avondale Ave",
    "sg:city": "Avon Lake",
    "sg:classifiers": [
      {
        "category": "Autos \u0026 Motor Vehicles",
        "subcategory": "Auto Supplies",
        "type": "Retail Goods"
      },
      {
        "category": "Wholesale",
        "subcategory": "Auto Parts",
        "type": "Manufacturing \u0026 Wholesale Goods"
      }
    ],
    "sg:phone": "+1 440 933 3204",
    "sg:postcode": "44012",
    "sg:province": "OH",
    "sg:tags": [
      "automobile"
    ],
    "wof:name": "Napa Avon Lake Auto Parts",
    "wof:placetype": "venue"
  },
  "geometry": {"coordinates":[-82.053386,41.502064],"type":"Point"}
}
