{
  "type": "Feature",
  "properties": {
    "iso:country":"US",
    "sg:address":"294 Avondale Ave",
    "sg:city":"Avon Lake",
    "sg:classifiers":[
        {
            "category":"Autos & Motor Vehicles",
            "subcategory":"Auto Supplies",
            "type":"Retail Goods"
        },
        {
            "category":"Wholesale",
            "subcategory":"Auto Parts",
            "type":"Manufacturing & Wholesale Goods"
        }
    ],
    "sg:phone":"+1 440 933 3204",
    "sg:postcode":"44012",
    "sg:province":"OH",
    "sg:tags":[
        "automobile"
    ],
    "wof:name":"Napa Avon Lake Auto Parts",
    "wof:placetype":"venue"
},
  "geometry": {"coordinates":[-82.053386,41.502064],"type":"Point"}
}