{
  "type": "Feature",
  "properties": {
    "addr:full": "39 E William St Delaware OH 43015",
    "addr:housenumber": "39",
    "addr:postcode": "43015",
    "addr:street": "E William St",
    "iso:country": "US",
    "sg:address": "39 E William St",
    "sg:city": "Delaware",
    "sg:classifiers": [
      {
        "category": "Building \u0026 Trades",
        "subcategory": "Plumbing",
        "type": "Services"
      }
    ],
    "sg:phone": "+1 740 369 2419",
    "sg:postcode": "43015",
    "sg:province": "OH",
    "sg:tags": [
      "plumbing"
    ],
    "wof:name": "Trimen",
    "wof:placetype": "venue"
  },
  "geometry": {"coordinates":[-83.066353,40.298793],"type":"Point"}
}
