{
  "type": "Feature",
  "properties": {
    "addr:full": "5349 Sunset Ridge Dr Mason OH 45040",
    "addr:housenumber": "5349",
    "addr:postcode": "45040",
    "addr:street": "Sunset Ridge Dr",
    "iso:country": "US",
    "sg:address": "5349 Sunset Ridge Dr",
    "sg:city": "Mason",
    "sg:classifiers": [
      {
        "category": "Shopping",
        "subcategory": "Computers \u0026 Home Electronics",
        "type": "Retail Goods"
      }
    ],
    "sg:phone": "+1 513 459 1223",
    "sg:postcode": "45040",
    "sg:province": "OH",
    "wof:name": "Kathy Heming Computer Art",
    "wof:placetype": "venue"
  },
  "geometry": {"coordinates":[-84.332856,39.363004],"type":"Point"}
}
