{
  "type": "Feature",
  "properties": {
    "addr:full": "308 Main St Toledo OH 43605",
    "addr:housenumber": "308",
    "addr:postcode": "43605",
    "addr:street": "Main St",
    "iso:country": "US",
    "sg:address": "308 Main St",
    "sg:city": "Toledo",
    "sg:classifiers": [
      {
        "category": "Restaurant",
        "type": "Food \u0026 Drink"
      }
    ],
    "sg:phone": "+1 419 691 7464",
    "sg:postcode": "43605",
    "sg:province": "OH",
    "sg:tags": [
      "eating"
    ],
    "wof:name": "Frankies Restaurant \u0026 Lounge",
    "wof:placetype": "venue"
  },
  "geometry": {"coordinates":[-83.521395,41.646683],"type":"Point"}
}
