{
  "type": "Feature",
  "properties": {
    "iso:country":"US",
    "sg:address":"308 Main St",
    "sg:city":"Toledo",
    "sg:classifiers":[
        {
            "category":"Restaurant",
            "type":"Food & Drink"
        }
    ],
    "sg:phone":"+1 419 691 7464",
    "sg:postcode":"43605",
    "sg:province":"OH",
    "sg:tags":[
        "eating"
    ],
    "wof:name":"Frankies Restaurant & Lounge",
    "wof:placetype":"venue"
},
  "geometry": {"coordinates":[-83.521395,41.646683],"type":"Point"}
}