{
  "type": "Feature",
  "properties": {
    "addr:full": "13520 S Main St Beloit OH 44609",
    "addr:housenumber": "13520",
    "addr:postcode": "44609",
    "addr:street": "S Main St",
    "iso:country": "US",
    "sg:address": "13520 S Main St",
    "sg:city": "Beloit",
    "sg:classifiers": [
      {
        "category": "Autos \u0026 Motor Vehicles",
        "subcategory": "Automobile Sales",
        "type": "Retail Goods"
      }
    ],
    "sg:phone": "+1 330 938 9270",
    "sg:postcode": "44609",
    "sg:province": "OH",
    "sg:tags": [
      "car",
      "dealer"
    ],
    "wof:name": "Beloit Auto Sales",
    "wof:placetype": "venue"
  },
  "geometry": {"coordinates":[-80.993718,40.92283],"type":"Point"}
}
