{
  "type": "Feature",
  "properties": {
    "addr:full": "102 W South St Mc Arthur OH 45651",
    "addr:housenumber": "102",
    "addr:postcode": "45651",
    "addr:street": "W South St",
    "iso:country": "US",
    "sg:address": "102 W South St",
    "sg:city": "Mc Arthur",
    "sg:classifiers": [
      {
        "category": "Food \u0026 Beverages",
        "subcategory": "Groceries \u0026 Convenience Stores",
        "type": "Retail Goods"
      },
      {
        "category": "Autos \u0026 Motor Vehicles",
        "subcategory": "Fuel \u0026 Gas Station",
        "type": "Retail Goods"
      }
    ],
    "sg:phone": "+1 740 596 5940",
    "sg:postcode": "45651",
    "sg:province": "OH",
    "sg:tags": [
      "oil"
    ],
    "wof:name": "Clarks Pump N Shop",
    "wof:placetype": "venue"
  },
  "geometry": {"coordinates":[-82.479815,39.244302],"type":"Point"}
}
