{
  "type": "Feature",
  "properties": {
    "iso:country":"US",
    "sg:address":"102 W South St",
    "sg:city":"Mc Arthur",
    "sg:classifiers":[
        {
            "category":"Food & Beverages",
            "subcategory":"Groceries & Convenience Stores",
            "type":"Retail Goods"
        },
        {
            "category":"Autos & Motor Vehicles",
            "subcategory":"Fuel & Gas Station",
            "type":"Retail Goods"
        }
    ],
    "sg:phone":"+1 740 596 5940",
    "sg:postcode":"45651",
    "sg:province":"OH",
    "sg:tags":[
        "oil"
    ],
    "wof:name":"Clarks Pump N Shop",
    "wof:placetype":"venue"
},
  "geometry": {"coordinates":[-82.479815,39.244302],"type":"Point"}
}