{
  "type": "Feature",
  "properties": {
    "addr:full": "5562 Shannon Heights Blvd Dublin OH 43016",
    "addr:housenumber": "5562",
    "addr:postcode": "43016",
    "addr:street": "Shannon Heights Blvd",
    "iso:country": "US",
    "sg:address": "5562 Shannon Heights Blvd",
    "sg:city": "Dublin",
    "sg:classifiers": [
      {
        "category": "Restaurant",
        "type": "Food \u0026 Drink"
      }
    ],
    "sg:phone": "+1 614 361 9778",
    "sg:postcode": "43016",
    "sg:province": "OH",
    "sg:tags": [
      "eating"
    ],
    "wof:name": "Papa Delta Limited",
    "wof:placetype": "venue"
  },
  "geometry": {"coordinates":[-83.123637,40.067219],"type":"Point"}
}
