{
  "type": "Feature",
  "properties": {
    "addr:full":"330 Triumph Way Columbus OH 43230",
    "addr:housenumber":"330",
    "addr:postcode":"43230",
    "addr:street":"Triumph Way",
    "iso:country":"US",
    "sg:address":"330 Triumph Way",
    "sg:city":"Columbus",
    "sg:classifiers":[
        {
            "category":"Professional",
            "subcategory":"Computer Services",
            "type":"Services"
        }
    ],
    "sg:phone":"+1 614 478 9603",
    "sg:postcode":"43230",
    "sg:province":"OH",
    "sg:tags":[
        "consultant",
        "designer"
    ],
    "wof:name":"Viper Systems Inc",
    "wof:placetype":"venue"
},
  "geometry": {"coordinates":[-82.899501,40.026768],"type":"Point"}
}