{
  "type": "Feature",
  "properties": {
    "iso:country":"US",
    "sg:address":"6738 Hilmar Dr",
    "sg:city":"Westerville",
    "sg:classifiers":[
        {
            "category":"Retail",
            "subcategory":"Repair Shop",
            "type":"Services"
        }
    ],
    "sg:phone":"+1 614 901 9335",
    "sg:postcode":"43082",
    "sg:province":"OH",
    "sg:tags":[
        "upholsterer"
    ],
    "wof:name":"Varney's Upholstery",
    "wof:placetype":"venue"
},
  "geometry": {"coordinates":[-82.908463,40.153781],"type":"Point"}
}