{
  "type": "Feature",
  "properties": {
    "iso:country":"US",
    "sg:address":"35 Timbermill Ct",
    "sg:city":"Springboro",
    "sg:classifiers":[
        {
            "category":"Professional",
            "type":"Services"
        }
    ],
    "sg:phone":"+1 937 885 8885",
    "sg:postcode":"45066",
    "sg:province":"OH",
    "wof:name":"Fansam One LLC",
    "wof:placetype":"venue"
},
  "geometry": {"coordinates":[-84.19713299999999,39.570916],"type":"Point"}
}