{
  "type": "Feature",
  "properties": {
    "iso:country":"US",
    "sg:address":"8639 Beechmont Ave",
    "sg:city":"Cincinnati",
    "sg:classifiers":[
        {
            "category":"Autos & Motor Vehicles",
            "subcategory":"Automobile Sales",
            "type":"Retail Goods"
        },
        {
            "category":"Retail",
            "subcategory":"Auto Repair",
            "type":"Services"
        }
    ],
    "sg:phone":"+1 513 388 3700",
    "sg:postcode":"45255",
    "sg:province":"OH",
    "sg:tags":[
        "car"
    ],
    "wof:name":"Beechmont Porsche Inc",
    "wof:placetype":"venue"
},
  "geometry": {"coordinates":[-84.314903,39.071999],"type":"Point"}
}