{
  "type": "Feature",
  "properties": {
    "addr:full": "7969 Eastbrooke Trl Youngstown OH 44514",
    "addr:housenumber": "7969",
    "addr:postcode": "44514",
    "addr:street": "Eastbrooke Trl",
    "iso:country": "US",
    "sg:address": "7969 Eastbrooke Trl",
    "sg:city": "Youngstown",
    "sg:classifiers": [
      {
        "category": "Restaurant",
        "type": "Food \u0026 Drink"
      }
    ],
    "sg:phone": "+1 330 707 1789",
    "sg:postcode": "44514",
    "sg:province": "OH",
    "sg:tags": [
      "eating"
    ],
    "wof:name": "Subway",
    "wof:placetype": "venue"
  },
  "geometry": {"coordinates":[-80.582097,41.005473],"type":"Point"}
}
