{
  "type": "Feature",
  "properties": {
    "addr:full":"26 West St Cincinnati OH 45220",
    "addr:housenumber":"26",
    "addr:postcode":"45220",
    "addr:street":"West St",
    "iso:country":"US",
    "sg:address":"26 West St",
    "sg:city":"Cincinnati",
    "sg:classifiers":[
        {
            "category":"Professional",
            "subcategory":"Testing Lab",
            "type":"Services"
        }
    ],
    "sg:phone":"+1 513 569 7904",
    "sg:postcode":"45220",
    "sg:province":"OH",
    "sg:tags":[
        "laboratory"
    ],
    "wof:name":"Homeland Security Research Ctr",
    "wof:placetype":"venue"
},
  "geometry": {"coordinates":[-84.51248099999999,39.147757],"type":"Point"}
}