{
  "type": "Feature",
  "properties": {
    "addr:full": "301 W Main Cross St Findlay OH 45840",
    "addr:housenumber": "301",
    "addr:postcode": "45840",
    "addr:street": "W Main Cross St",
    "iso:country": "US",
    "sg:address": "301 W Main Cross St",
    "sg:city": "Findlay",
    "sg:classifiers": [
      {
        "category": "Food \u0026 Beverages",
        "subcategory": "Groceries \u0026 Convenience Stores",
        "type": "Retail Goods"
      }
    ],
    "sg:phone": "+1 419 423 3505",
    "sg:postcode": "45840",
    "sg:province": "OH",
    "sg:tags": [
      "grocer"
    ],
    "wof:name": "Great Scot Supermarkets",
    "wof:placetype": "venue"
  },
  "geometry": {"coordinates":[-83.655085,41.039324],"type":"Point"}
}
