{
  "type": "Feature",
  "properties": {
    "iso:country":"US",
    "sg:address":"301 W Main Cross St",
    "sg:city":"Findlay",
    "sg:classifiers":[
        {
            "category":"Food & Beverages",
            "subcategory":"Groceries & Convenience Stores",
            "type":"Retail Goods"
        }
    ],
    "sg:phone":"+1 419 423 3505",
    "sg:postcode":"45840",
    "sg:province":"OH",
    "sg:tags":[
        "grocer"
    ],
    "wof:name":"Great Scot Supermarkets",
    "wof:placetype":"venue"
},
  "geometry": {"coordinates":[-83.655085,41.039324],"type":"Point"}
}