{
  "type": "Feature",
  "properties": {
    "addr:full":"209 S High St Columbus OH 43215",
    "addr:housenumber":"209",
    "addr:postcode":"43215",
    "addr:street":"S High St",
    "iso:country":"US",
    "sg:address":"209 S High St",
    "sg:city":"Columbus",
    "sg:classifiers":[
        {
            "category":"Shopping",
            "subcategory":"Shoes",
            "type":"Retail Goods"
        }
    ],
    "sg:phone":"+1 614 463 1080",
    "sg:postcode":"43215",
    "sg:province":"OH",
    "sg:tags":[
        "shoe",
        "store"
    ],
    "sg:website":"www.royalimpression.com",
    "wof:name":"Royal Impression",
    "wof:placetype":"venue"
},
  "geometry": {"coordinates":[-82.999841,39.95776],"type":"Point"}
}