{
  "type": "Feature",
  "properties": {
    "addr:full": "26901 Eckel Rd Perrysburg OH 43551",
    "addr:postcode": "26901;43551",
    "addr:street": "Eckel Rd",
    "iso:country": "US",
    "sg:address": "26901 Eckel Rd",
    "sg:city": "Perrysburg",
    "sg:classifiers": [
      {
        "category": "Building \u0026 Trades",
        "subcategory": "Construction",
        "type": "Services"
      }
    ],
    "sg:phone": "+1 419 874 9420",
    "sg:postcode": "43551",
    "sg:province": "OH",
    "sg:tags": [
      "fire",
      "repairing",
      "damage"
    ],
    "wof:name": "Harris Fire Wtr Clg Spcialists",
    "wof:placetype": "venue"
  },
  "geometry": {"coordinates":[-83.641919,41.546213],"type":"Point"}
}
