{
  "type": "Feature",
  "properties": {
    "iso:country":"US",
    "sg:address":"4600 W 160th St",
    "sg:city":"Cleveland",
    "sg:classifiers":[
        {
            "category":"Manufacturing",
            "subcategory":"Tools & Machinery",
            "type":"Manufacturing & Wholesale Goods"
        }
    ],
    "sg:phone":"+1 440 876 8960",
    "sg:postcode":"44135",
    "sg:province":"OH",
    "sg:tags":[
        "industry",
        "mfg"
    ],
    "wof:name":"Van Dorn Demag Corporation",
    "wof:placetype":"venue"
},
  "geometry": {"coordinates":[-81.80989,41.433709],"type":"Point"}
}