{
  "type": "Feature",
  "properties": {
    "addr:full": "11418 Deerfield Rd Cincinnati OH 45242",
    "addr:housenumber": "11418",
    "addr:postcode": "45242",
    "addr:street": "Deerfield Rd",
    "iso:country": "US",
    "sg:address": "11418 Deerfield Rd",
    "sg:city": "Cincinnati",
    "sg:classifiers": [
      {
        "category": "Wholesale",
        "subcategory": "Medical Equipment \u0026 Supplies",
        "type": "Manufacturing \u0026 Wholesale Goods"
      }
    ],
    "sg:phone": "+1 513 489 4205",
    "sg:postcode": "45242",
    "sg:province": "OH",
    "sg:tags": [
      "dental"
    ],
    "wof:name": "Island Dental Supply",
    "wof:placetype": "venue"
  },
  "geometry": {"coordinates":[-84.357735,39.27358],"type":"Point"}
}
