{
  "type": "Feature",
  "properties": {
    "iso:country":"US",
    "sg:address":"11418 Deerfield Rd",
    "sg:city":"Cincinnati",
    "sg:classifiers":[
        {
            "category":"Wholesale",
            "subcategory":"Medical Equipment & Supplies",
            "type":"Manufacturing & Wholesale Goods"
        }
    ],
    "sg:phone":"+1 513 489 4205",
    "sg:postcode":"45242",
    "sg:province":"OH",
    "sg:tags":[
        "dental"
    ],
    "wof:name":"Island Dental Supply",
    "wof:placetype":"venue"
},
  "geometry": {"coordinates":[-84.35773500000001,39.27358],"type":"Point"}
}