{
  "type": "Feature",
  "properties": {
    "addr:full": "1394 Sigma Cir Cincinnati OH 45255",
    "addr:housenumber": "1394",
    "addr:postcode": "45255",
    "addr:street": "Sigma Cir",
    "iso:country": "US",
    "sg:address": "1394 Sigma Cir",
    "sg:city": "Cincinnati",
    "sg:classifiers": [
      {
        "category": "Building \u0026 Trades",
        "subcategory": "Electrical",
        "type": "Services"
      }
    ],
    "sg:phone": "+1 513 474 0994",
    "sg:postcode": "45255",
    "sg:province": "OH",
    "sg:tags": [
      "electrical",
      "contractor"
    ],
    "wof:name": "Van Treeck Werner",
    "wof:placetype": "venue"
  },
  "geometry": {"coordinates":[-84.326829,39.076187],"type":"Point"}
}
