{
  "type": "Feature",
  "properties": {
    "addr:full": "627 Eastland Ave SE Warren OH 44484",
    "addr:housenumber": "627",
    "addr:postcode": "44484",
    "addr:street": "Eastland Ave Se",
    "iso:country": "US",
    "sg:address": "627 Eastland Ave SE",
    "sg:city": "Warren",
    "sg:classifiers": [
      {
        "category": "Health Services",
        "subcategory": "Doctor",
        "type": "Services"
      }
    ],
    "sg:phone": "+1 330 392 4334",
    "sg:postcode": "44484",
    "sg:province": "OH",
    "sg:tags": [
      "physician",
      "surgeon"
    ],
    "wof:name": "Charles H Curtiss Inc",
    "wof:placetype": "venue"
  },
  "geometry": {"coordinates":[-80.778393,41.230173],"type":"Point"}
}
