{
  "type": "Feature",
  "properties": {
    "addr:full": "2892 E 14th Ave Columbus OH 43219",
    "addr:housenumber": "2892",
    "addr:postcode": "43219",
    "addr:street": "E 14Th Ave",
    "iso:country": "US",
    "sg:address": "2892 E 14th Ave",
    "sg:city": "Columbus",
    "sg:classifiers": [
      {
        "category": "Retail",
        "subcategory": "Auto Repair",
        "type": "Services"
      }
    ],
    "sg:phone": "+1 614 258 4200",
    "sg:postcode": "43219",
    "sg:province": "OH",
    "sg:tags": [
      "repairing",
      "automobile"
    ],
    "wof:name": "Automotive \u0026 Truck Svc",
    "wof:placetype": "venue"
  },
  "geometry": {"coordinates":[-82.923844,39.993806],"type":"Point"}
}
