{
  "type": "Feature",
  "properties": {
    "addr:full":"1370 Ontario St Cleveland OH 44113",
    "addr:housenumber":"1370",
    "addr:postcode":"44113",
    "addr:street":"Ontario St",
    "iso:country":"US",
    "sg:address":"1370 Ontario St",
    "sg:city":"Cleveland",
    "sg:classifiers":[
        {
            "category":"Insurance",
            "subcategory":"Hazard Insurance",
            "type":"Services"
        }
    ],
    "sg:phone":"+1 216 696 6966",
    "sg:postcode":"44113",
    "sg:province":"OH",
    "sg:tags":[
        "bond"
    ],
    "wof:name":"Turoczy Bonding Co",
    "wof:placetype":"venue"
},
  "geometry": {"coordinates":[-81.69510099999999,41.501244],"type":"Point"}
}