{
  "type": "Feature",
  "properties": {
    "iso:country":"US",
    "sg:address":"401 E Robb Ave",
    "sg:city":"Lima",
    "sg:classifiers":[
        {
            "category":"Railroad",
            "type":"Transportation"
        }
    ],
    "sg:phone":"+1 419 225 4121",
    "sg:postcode":"45801",
    "sg:province":"OH",
    "sg:website":"www.csx.com",
    "wof:name":"CSX Transportation",
    "wof:placetype":"venue"
},
  "geometry": {"coordinates":[-84.10005099999999,40.759346],"type":"Point"}
}