{
  "type": "Feature",
  "properties": {
    "addr:full": "401 E Robb Ave Lima OH 45801",
    "addr:housenumber": "401",
    "addr:postcode": "45801",
    "addr:street": "E Robb Ave",
    "iso:country": "US",
    "sg:address": "401 E Robb Ave",
    "sg:city": "Lima",
    "sg:classifiers": [
      {
        "category": "Railroad",
        "type": "Transportation"
      }
    ],
    "sg:phone": "+1 419 225 4121",
    "sg:postcode": "45801",
    "sg:province": "OH",
    "sg:website": "www.csx.com",
    "wof:name": "CSX Transportation",
    "wof:placetype": "venue"
  },
  "geometry": {"coordinates":[-84.100051,40.759346],"type":"Point"}
}
