{
  "type": "Feature",
  "properties": {
    "addr:full": "5573 Bethel Rd Sycamore OH 44882",
    "addr:housenumber": "5573",
    "addr:postcode": "44882",
    "addr:street": "Bethel Rd",
    "iso:country": "US",
    "sg:address": "5573 Bethel Rd",
    "sg:city": "Sycamore",
    "sg:classifiers": [
      {
        "category": "Farming",
        "subcategory": "Farm \u0026 Veterinary Services",
        "type": "Manufacturing \u0026 Wholesale Goods"
      }
    ],
    "sg:phone": "+1 419 562 8171",
    "sg:postcode": "44882",
    "sg:province": "OH",
    "sg:tags": [
      "grain",
      "cash"
    ],
    "wof:name": "Paul Dornbirer",
    "wof:placetype": "venue"
  },
  "geometry": {"coordinates":[-83.055155,40.903057],"type":"Point"}
}
