{
  "type": "Feature",
  "properties": {
    "iso:country":"US",
    "sg:address":"875 Moe Dr",
    "sg:city":"Akron",
    "sg:classifiers":[
        {
            "category":"Manufacturing",
            "subcategory":"Tools & Machinery",
            "type":"Manufacturing & Wholesale Goods"
        }
    ],
    "sg:phone":"+1 330 633 3113",
    "sg:postcode":"44310",
    "sg:province":"OH",
    "sg:tags":[
        "machine",
        "shop"
    ],
    "wof:name":"Specialized Finish & Machine",
    "wof:placetype":"venue"
},
  "geometry": {"coordinates":[-81.48386499999999,41.107659],"type":"Point"}
}