{
  "type": "Feature",
  "properties": {
    "iso:country":"US",
    "sg:address":"6819 W Central Ave",
    "sg:city":"Toledo",
    "sg:classifiers":[
        {
            "category":"Restaurant",
            "type":"Food & Drink"
        }
    ],
    "sg:phone":"+1 419 842 1900",
    "sg:postcode":"43617",
    "sg:province":"OH",
    "wof:name":"Cafe Marie Restaurant",
    "wof:placetype":"venue"
},
  "geometry": {"coordinates":[-83.70535599999999,41.674946],"type":"Point"}
}