{
  "type": "Feature",
  "properties": {
    "iso:country":"US",
    "sg:address":"1160 Conaway Rd",
    "sg:city":"Peebles",
    "sg:classifiers":[
        {
            "category":"Shopping",
            "subcategory":"Computers & Home Electronics",
            "type":"Retail Goods"
        }
    ],
    "sg:phone":"+1 937 587 2019",
    "sg:postcode":"45660",
    "sg:province":"OH",
    "sg:tags":[
        "equipment",
        "electronic",
        "supply"
    ],
    "sg:website":"www.schmitz-tech.com",
    "wof:name":"Schmitz Electronics Inc",
    "wof:placetype":"venue"
},
  "geometry": {"coordinates":[-83.357139,39.018231],"type":"Point"}
}