{
  "type": "Feature",
  "properties": {
    "addr:full":"122 E Charles St Bucyrus OH 44820",
    "addr:housenumber":"122",
    "addr:postcode":"44820",
    "addr:street":"E Charles St",
    "iso:country":"US",
    "sg:address":"122 E Charles St",
    "sg:city":"Bucyrus",
    "sg:classifiers":[
        {
            "category":"Personal",
            "subcategory":"Beauty Salon",
            "type":"Services"
        }
    ],
    "sg:phone":"+1 419 562 7303",
    "sg:postcode":"44820",
    "sg:province":"OH",
    "sg:tags":[
        "shop"
    ],
    "wof:name":"Creative Options Hair Design",
    "wof:placetype":"venue"
},
  "geometry": {"coordinates":[-82.975297,40.805482],"type":"Point"}
}