{
  "type": "Feature",
  "properties": {
    "iso:country":"US",
    "sg:address":"9551 Gibson Rd",
    "sg:city":"North Jackson",
    "sg:classifiers":[
        {
            "category":"Utilities",
            "subcategory":"Refuse",
            "type":"Services"
        }
    ],
    "sg:phone":"+1 330 538 0768",
    "sg:postcode":"44451",
    "sg:province":"OH",
    "sg:tags":[
        "garbage",
        "collection"
    ],
    "wof:name":"Allison Brothers Inc",
    "wof:placetype":"venue"
},
  "geometry": {"coordinates":[-80.831803,41.061845],"type":"Point"}
}