{
  "type": "Feature",
  "properties": {
    "iso:country":"US",
    "sg:address":"2832 Commodore Ln",
    "sg:city":"Cincinnati",
    "sg:classifiers":[
        {
            "category":"Social Services",
            "subcategory":"Child Care",
            "type":"Services"
        }
    ],
    "sg:phone":"+1 513 741 3748",
    "sg:postcode":"45251",
    "sg:province":"OH",
    "sg:tags":[
        "sitting"
    ],
    "wof:name":"Sitters For Your Stars",
    "wof:placetype":"venue"
},
  "geometry": {"coordinates":[-84.582252,39.226516],"type":"Point"}
}