{
  "type": "Feature",
  "properties": {
    "addr:full": "4267 Moreland Cir E Grove City OH 43123",
    "addr:housenumber": "4267",
    "addr:postcode": "43123",
    "addr:street": "Moreland Cir E",
    "iso:country": "US",
    "sg:address": "4267 Moreland Cir E",
    "sg:city": "Grove City",
    "sg:classifiers": [
      {
        "category": "Shopping",
        "subcategory": "Hobbies, Toys, \u0026 Games",
        "type": "Retail Goods"
      }
    ],
    "sg:phone": "+1 614 539 0456",
    "sg:postcode": "43123",
    "sg:province": "OH",
    "sg:tags": [
      "craft",
      "supply"
    ],
    "wof:name": "Thomas Poe Gifts",
    "wof:placetype": "venue"
  },
  "geometry": {"coordinates":[-83.052976,39.875507],"type":"Point"}
}
