{
  "type": "Feature",
  "properties": {
    "addr:full":"4595 W Broad St Columbus OH 43228",
    "addr:housenumber":"4595",
    "addr:postcode":"43228",
    "addr:street":"W Broad St",
    "iso:country":"US",
    "sg:address":"4595 W Broad St",
    "sg:city":"Columbus",
    "sg:classifiers":[
        {
            "category":"Restaurant",
            "type":"Food & Drink"
        }
    ],
    "sg:menulink":"http://www.allmenus.com/oh/prairie/141802-waffle-house/menu/",
    "sg:phone":"+1 614 851 9227",
    "sg:postcode":"43228",
    "sg:province":"OH",
    "sg:tags":[
        "american"
    ],
    "wof:name":"Waffle House",
    "wof:placetype":"venue"
},
  "geometry": {"coordinates":[-83.123086,39.952225],"type":"Point"}
}