{
  "type": "Feature",
  "properties": {
    "addr:full":"10552 Success Ln Dayton OH 45458",
    "addr:housenumber":"10552",
    "addr:postcode":"45458",
    "addr:street":"Success Ln",
    "iso:country":"US",
    "sg:address":"10552 Success Ln",
    "sg:city":"Dayton",
    "sg:classifiers":[
        {
            "category":"Wholesale",
            "subcategory":"Electrical",
            "type":"Manufacturing & Wholesale Goods"
        }
    ],
    "sg:phone":"+1 937 886 9601",
    "sg:postcode":"45458",
    "sg:province":"OH",
    "sg:tags":[
        "equipment",
        "electronic",
        "supply"
    ],
    "sg:website":"www.nuhorizons.com",
    "wof:name":"NU Horizons Electronics Corp",
    "wof:placetype":"venue"
},
  "geometry": {"coordinates":[-84.205603,39.595024],"type":"Point"}
}