{
  "type": "Feature",
  "properties": {
    "iso:country":"US",
    "sg:address":"95 W McKinley Way",
    "sg:city":"Youngstown",
    "sg:classifiers":[
        {
            "category":"Shopping",
            "subcategory":"Shoes",
            "type":"Retail Goods"
        }
    ],
    "sg:phone":"+1 330 757 8930",
    "sg:postcode":"44514",
    "sg:province":"OH",
    "wof:name":"Diorio Shoes Inc",
    "wof:placetype":"venue"
},
  "geometry": {"coordinates":[-80.616179,41.024173],"type":"Point"}
}