{
  "type": "Feature",
  "properties": {
    "addr:full":"8241 Troy Pike Dayton OH 45424",
    "addr:housenumber":"8241",
    "addr:postcode":"45424",
    "addr:street":"Troy Pike",
    "iso:country":"US",
    "sg:address":"8241 Troy Pike",
    "sg:city":"Dayton",
    "sg:classifiers":[
        {
            "category":"Shopping",
            "subcategory":"Department Store",
            "type":"Retail Goods"
        }
    ],
    "sg:phone":"+1 937 237 8072",
    "sg:postcode":"45424",
    "sg:province":"OH",
    "wof:name":"Marshalls",
    "wof:placetype":"venue"
},
  "geometry": {"coordinates":[-84.137449,39.87198],"type":"Point"}
}