{
  "type": "Feature",
  "properties": {
    "addr:full":"72 Town Sq Lima OH 45801",
    "addr:housenumber":"72",
    "addr:postcode":"45801",
    "addr:street":"Town Sq",
    "iso:country":"US",
    "sg:address":"72 Town Sq",
    "sg:city":"Lima",
    "sg:classifiers":[
        {
            "category":"Real Estate",
            "subcategory":"Real Estate Agent",
            "type":"Services"
        },
        {
            "category":"Real Estate",
            "subcategory":"Real Estate Operator",
            "type":"Services"
        }
    ],
    "sg:phone":"+1 419 227 5732",
    "sg:postcode":"45801",
    "sg:province":"OH",
    "sg:tags":[
        "apartment"
    ],
    "wof:name":"Town Square Apartments",
    "wof:placetype":"venue"
},
  "geometry": {"coordinates":[-84.104812,40.740677],"type":"Point"}
}