{
  "type": "Feature",
  "properties": {
    "addr:full": "1266 N Broad St Fairborn OH 45324",
    "addr:housenumber": "1266",
    "addr:postcode": "45324",
    "addr:street": "N Broad St",
    "iso:country": "US",
    "sg:address": "1266 N Broad St",
    "sg:city": "Fairborn",
    "sg:classifiers": [
      {
        "category": "Health Services",
        "subcategory": "Doctor",
        "type": "Services"
      }
    ],
    "sg:phone": "+1 937 879 0433",
    "sg:postcode": "45324",
    "sg:province": "OH",
    "sg:tags": [
      "physician",
      "surgeon"
    ],
    "wof:name": "Community Physicians Dialysis",
    "wof:placetype": "venue"
  },
  "geometry": {"coordinates":[-84.011462,39.835407],"type":"Point"}
}
