{
  "type": "Feature",
  "properties": {
    "addr:full":"3400 S Dixie Dr Dayton OH 45439",
    "addr:housenumber":"3400",
    "addr:postcode":"45439",
    "addr:street":"S Dixie Dr",
    "iso:country":"US",
    "sg:address":"3400 S Dixie Dr",
    "sg:city":"Dayton",
    "sg:classifiers":[
        {
            "category":"Professional",
            "subcategory":"Accounting & Tax Preparation",
            "type":"Services"
        }
    ],
    "sg:phone":"+1 937 299 3400",
    "sg:postcode":"45439",
    "sg:province":"OH",
    "sg:tags":[
        "accountant",
        "public",
        "certified"
    ],
    "wof:name":"Flagel Huber Flagel & Co",
    "wof:placetype":"venue"
},
  "geometry": {"coordinates":[-84.20199100000001,39.70356],"type":"Point"}
}