{
  "type": "Feature",
  "properties": {
    "iso:country":"US",
    "sg:address":"601 N Fountain Ave",
    "sg:city":"Springfield",
    "sg:classifiers":[
        {
            "category":"Social Services",
            "subcategory":"Adult Care",
            "type":"Services"
        }
    ],
    "sg:phone":"+1 937 390 7973",
    "sg:postcode":"45504",
    "sg:province":"OH",
    "sg:tags":[
        "residential"
    ],
    "wof:name":"Resource Center",
    "wof:placetype":"venue"
},
  "geometry": {"coordinates":[-83.80960399999999,39.932713],"type":"Point"}
}