{
  "type": "Feature",
  "properties": {
    "addr:full": "601 N Fountain Ave Springfield OH 45504",
    "addr:housenumber": "601",
    "addr:postcode": "45504",
    "addr:street": "N Fountain Ave",
    "iso:country": "US",
    "sg:address": "601 N Fountain Ave",
    "sg:city": "Springfield",
    "sg:classifiers": [
      {
        "category": "Social Services",
        "subcategory": "Adult Care",
        "type": "Services"
      }
    ],
    "sg:phone": "+1 937 390 7973",
    "sg:postcode": "45504",
    "sg:province": "OH",
    "sg:tags": [
      "residential"
    ],
    "wof:name": "Resource Center",
    "wof:placetype": "venue"
  },
  "geometry": {"coordinates":[-83.809604,39.932713],"type":"Point"}
}
