{
  "type": "Feature",
  "properties": {
    "addr:full":"919 Manchester St Kent OH 44240",
    "addr:housenumber":"919",
    "addr:postcode":"44240",
    "addr:street":"Manchester St",
    "iso:country":"US",
    "sg:address":"919 Manchester St",
    "sg:city":"Kent",
    "sg:classifiers":[
        {
            "category":"Wholesale",
            "subcategory":"Machinery & Supplies",
            "type":"Manufacturing & Wholesale Goods"
        }
    ],
    "sg:phone":"+1 330 673 7074",
    "sg:postcode":"44240",
    "sg:province":"OH",
    "sg:tags":[
        "equipment",
        "industrial"
    ],
    "wof:name":"A-Alert Inert Gas Welding",
    "wof:placetype":"venue"
},
  "geometry": {"coordinates":[-81.37278000000001,41.146431],"type":"Point"}
}