{
  "type": "Feature",
  "properties": {
    "iso:country":"US",
    "sg:address":"9065 US Hwy 50 W",
    "sg:city":"Bainbridge",
    "sg:phone":"+1 740 626 7152",
    "sg:postcode":"45612",
    "sg:province":"OH",
    "sg:tags":[
        "farm",
        "corn",
        "soybean"
    ],
    "wof:name":"Gene Purdum",
    "wof:placetype":"venue"
},
  "geometry": {"coordinates":[-83.185537,39.257715],"type":"Point"}
}