{
  "type": "Feature",
  "properties": {
    "addr:full": "4280 Hudson Dr Stow OH 44224",
    "addr:housenumber": "4280",
    "addr:postcode": "44224",
    "addr:street": "Hudson Dr",
    "iso:country": "US",
    "sg:address": "4280 Hudson Dr",
    "sg:city": "Stow",
    "sg:classifiers": [
      {
        "category": "Real Estate",
        "subcategory": "Real Estate Operator",
        "type": "Services"
      }
    ],
    "sg:phone": "+1 330 920 4410",
    "sg:postcode": "44224",
    "sg:province": "OH",
    "sg:tags": [
      "building",
      "parks"
    ],
    "wof:name": "Scott Bader Inc",
    "wof:placetype": "venue"
  },
  "geometry": {"coordinates":[-81.471759,41.18272],"type":"Point"}
}
