{
  "type": "Feature",
  "properties": {
    "addr:full": "3215 Murray Rd Lima OH 45801",
    "addr:housenumber": "3215",
    "addr:postcode": "45801",
    "addr:street": "Murray Rd",
    "iso:country": "US",
    "sg:address": "3215 Murray Rd",
    "sg:city": "Lima",
    "sg:classifiers": [
      {
        "category": "Real Estate",
        "subcategory": "Real Estate Agent",
        "type": "Services"
      }
    ],
    "sg:phone": "+1 419 649 1581",
    "sg:postcode": "45801",
    "sg:province": "OH",
    "wof:name": "T\u0026J Real Estate Enterprises Lt",
    "wof:placetype": "venue"
  },
  "geometry": {"coordinates":[-83.982542,40.785708],"type":"Point"}
}
