{
  "type": "Feature",
  "properties": {
    "iso:country":"US",
    "sg:address":"7135 Angola Rd",
    "sg:city":"Holland",
    "sg:classifiers":[
        {
            "category":"Farming",
            "subcategory":"Nursery",
            "type":"Manufacturing & Wholesale Goods"
        },
        {
            "category":"Building & Trades",
            "subcategory":"Landscaping Services",
            "type":"Services"
        }
    ],
    "sg:phone":"+1 419 868 9766",
    "sg:postcode":"43528",
    "sg:province":"OH",
    "sg:tags":[
        "installs",
        "planning",
        "sprinkler",
        "landscape",
        "contractor"
    ],
    "wof:name":"Simmons Landscape & Irrigation",
    "wof:placetype":"venue"
},
  "geometry": {"coordinates":[-83.711258,41.624879],"type":"Point"}
}