{
  "type": "Feature",
  "properties": {
    "addr:full": "7135 Angola Rd Holland OH 43528",
    "addr:housenumber": "7135",
    "addr:postcode": "43528",
    "addr:street": "Angola Rd",
    "iso:country": "US",
    "sg:address": "7135 Angola Rd",
    "sg:city": "Holland",
    "sg:classifiers": [
      {
        "category": "Farming",
        "subcategory": "Nursery",
        "type": "Manufacturing \u0026 Wholesale Goods"
      },
      {
        "category": "Building \u0026 Trades",
        "subcategory": "Landscaping Services",
        "type": "Services"
      }
    ],
    "sg:phone": "+1 419 868 9766",
    "sg:postcode": "43528",
    "sg:province": "OH",
    "sg:tags": [
      "installs",
      "planning",
      "sprinkler",
      "landscape",
      "contractor"
    ],
    "wof:name": "Simmons Landscape \u0026 Irrigation",
    "wof:placetype": "venue"
  },
  "geometry": {"coordinates":[-83.711258,41.624879],"type":"Point"}
}
