{
  "type": "Feature",
  "properties": {
    "addr:full": "6300 W Chester Rd West Chester OH 45069",
    "addr:housenumber": "6300",
    "addr:postcode": "45069",
    "addr:street": "W Chester Rd",
    "iso:country": "US",
    "sg:address": "6300 W Chester Rd",
    "sg:city": "West Chester",
    "sg:classifiers": [
      {
        "category": "Organizations",
        "subcategory": "Religious Organization",
        "type": "Services"
      }
    ],
    "sg:phone": "+1 513 777 4571",
    "sg:postcode": "45069",
    "sg:province": "OH",
    "sg:tags": [
      "church"
    ],
    "sg:website": "www.lakotahillsbaptist.com",
    "wof:name": "Lakota Hills Baptist Church",
    "wof:placetype": "venue"
  },
  "geometry": {"coordinates":[-84.415846,39.326029],"type":"Point"}
}
