{
  "type": "Feature",
  "properties": {
    "iso:country":"US",
    "sg:address":"33495 Station St",
    "sg:city":"Cleveland",
    "sg:classifiers":[
        {
            "category":"Personal",
            "subcategory":"Beauty Salon",
            "type":"Services"
        }
    ],
    "sg:phone":"+1 440 248 7720",
    "sg:postcode":"44139",
    "sg:province":"OH",
    "wof:name":"Station Street Salon",
    "wof:placetype":"venue"
},
  "geometry": {"coordinates":[-81.440046,41.386984],"type":"Point"}
}