{
  "type": "Feature",
  "properties": {
    "iso:country":"US",
    "sg:address":"501 Mohican Dr",
    "sg:city":"Loveland",
    "sg:classifiers":[
        {
            "category":"Building & Trades",
            "subcategory":"Plumbing",
            "type":"Services"
        }
    ],
    "sg:phone":"+1 513 677 0597",
    "sg:postcode":"45140",
    "sg:province":"OH",
    "sg:tags":[
        "heating",
        "contractor"
    ],
    "wof:name":"Miller Heating & Cooling",
    "wof:placetype":"venue"
},
  "geometry": {"coordinates":[-84.27866400000001,39.264475],"type":"Point"}
}