{
  "type": "Feature",
  "properties": {
    "addr:full": "501 Mohican Dr Loveland OH 45140",
    "addr:housenumber": "501",
    "addr:postcode": "45140",
    "addr:street": "Mohican Dr",
    "iso:country": "US",
    "sg:address": "501 Mohican Dr",
    "sg:city": "Loveland",
    "sg:classifiers": [
      {
        "category": "Building \u0026 Trades",
        "subcategory": "Plumbing",
        "type": "Services"
      }
    ],
    "sg:phone": "+1 513 677 0597",
    "sg:postcode": "45140",
    "sg:province": "OH",
    "sg:tags": [
      "heating",
      "contractor"
    ],
    "wof:name": "Miller Heating \u0026 Cooling",
    "wof:placetype": "venue"
  },
  "geometry": {"coordinates":[-84.278664,39.264475],"type":"Point"}
}
