{
  "type": "Feature",
  "properties": {
    "iso:country":"US",
    "sg:address":"1432 E 21st St",
    "sg:city":"Ashtabula",
    "sg:classifiers":[
        {
            "category":"Wholesale",
            "subcategory":"Electrical",
            "type":"Manufacturing & Wholesale Goods"
        }
    ],
    "sg:phone":"+1 440 992 3688",
    "sg:postcode":"44004",
    "sg:province":"OH",
    "sg:tags":[
        "disposal",
        "garbage"
    ],
    "wof:name":"Refuse Equipment & Truck Svc",
    "wof:placetype":"venue"
},
  "geometry": {"coordinates":[-80.780439,41.888786],"type":"Point"}
}