{
  "type": "Feature",
  "properties": {
    "addr:full":"720 Portage Trl Cuyahoga Falls OH 44221",
    "addr:housenumber":"720",
    "addr:postcode":"44221",
    "addr:street":"Portage Trl",
    "iso:country":"US",
    "sg:address":"720 Portage Trl",
    "sg:city":"Cuyahoga Falls",
    "sg:classifiers":[
        {
            "category":"Retail",
            "subcategory":"Repair Shop",
            "type":"Services"
        }
    ],
    "sg:phone":"+1 330 375 0300",
    "sg:postcode":"44221",
    "sg:province":"OH",
    "sg:tags":[
        "repairing",
        "piano",
        "refinishing"
    ],
    "wof:name":"San's Piano Tuning",
    "wof:placetype":"venue"
},
  "geometry": {"coordinates":[-81.492976,41.140147],"type":"Point"}
}