{
  "type": "Feature",
  "properties": {
    "addr:full": "37 S Detroit St Xenia OH 45385",
    "addr:housenumber": "37",
    "addr:postcode": "45385",
    "addr:street": "S Detroit St",
    "iso:country": "US",
    "sg:address": "37 S Detroit St",
    "sg:city": "Xenia",
    "sg:classifiers": [
      {
        "category": "Wholesale",
        "subcategory": "Toys \u0026 Hobbies",
        "type": "Manufacturing \u0026 Wholesale Goods"
      }
    ],
    "sg:phone": "+1 937 372 9570",
    "sg:postcode": "45385",
    "sg:province": "OH",
    "sg:tags": [
      "wholesaler"
    ],
    "wof:name": "Reptiles By Mack",
    "wof:placetype": "venue"
  },
  "geometry": {"coordinates":[-83.929254,39.684581],"type":"Point"}
}
