{
  "type": "Feature",
  "properties": {
    "iso:country":"US",
    "sg:address":"37 S Detroit St",
    "sg:city":"Xenia",
    "sg:classifiers":[
        {
            "category":"Wholesale",
            "subcategory":"Toys & Hobbies",
            "type":"Manufacturing & Wholesale Goods"
        }
    ],
    "sg:phone":"+1 937 372 9570",
    "sg:postcode":"45385",
    "sg:province":"OH",
    "sg:tags":[
        "wholesaler"
    ],
    "wof:name":"Reptiles By Mack",
    "wof:placetype":"venue"
},
  "geometry": {"coordinates":[-83.929254,39.684581],"type":"Point"}
}