{
  "type": "Feature",
  "properties": {
    "addr:full": "3963 Broadway Grove City OH 43123",
    "addr:housenumber": "3963",
    "addr:postcode": "43123",
    "addr:street": "Broadway",
    "iso:country": "US",
    "sg:address": "3963 Broadway",
    "sg:city": "Grove City",
    "sg:classifiers": [
      {
        "category": "Professional",
        "subcategory": "Business Services",
        "type": "Services"
      }
    ],
    "sg:phone": "+1 614 801 1340",
    "sg:postcode": "43123",
    "sg:province": "OH",
    "sg:tags": [
      "telemarketing"
    ],
    "wof:name": "Central Scheduling",
    "wof:placetype": "venue"
  },
  "geometry": {"coordinates":[-83.092809,39.883258],"type":"Point"}
}
