{
  "type": "Feature",
  "properties": {
    "iso:country":"US",
    "sg:address":"111 W Water St",
    "sg:city":"Troy",
    "sg:classifiers":[
        {
            "category":"Bars & Pubs",
            "type":"Food & Drink"
        }
    ],
    "sg:phone":"+1 937 339 8595",
    "sg:postcode":"45373",
    "sg:province":"OH",
    "sg:website":"www.dabrewery.com",
    "wof:name":"Brewery",
    "wof:placetype":"venue"
},
  "geometry": {"coordinates":[-84.203596,40.041155],"type":"Point"}
}