{
  "type": "Feature",
  "properties": {
    "iso:country":"US",
    "sg:address":"171 E Livingston Ave",
    "sg:city":"Columbus",
    "sg:classifiers":[
        {
            "category":"Professional",
            "subcategory":"Lawyer & Legal Services",
            "type":"Services"
        }
    ],
    "sg:phone":"+1 614 221 2750",
    "sg:postcode":"43215",
    "sg:province":"OH",
    "sg:tags":[
        "attorney"
    ],
    "wof:name":"James B Curtin",
    "wof:placetype":"venue"
},
  "geometry": {"coordinates":[-82.99373799999999,39.952593],"type":"Point"}
}