{
  "type": "Feature",
  "properties": {
    "addr:full": "500 N Main St Lima OH 45801",
    "addr:housenumber": "500",
    "addr:postcode": "45801",
    "addr:street": "N Main St",
    "iso:country": "US",
    "sg:address": "500 N Main St",
    "sg:city": "Lima",
    "sg:classifiers": [
      {
        "category": "Autos \u0026 Motor Vehicles",
        "subcategory": "Automobile Sales",
        "type": "Retail Goods"
      }
    ],
    "sg:phone": "+1 419 991 2886",
    "sg:postcode": "45801",
    "sg:province": "OH",
    "sg:tags": [
      "car",
      "dealer"
    ],
    "wof:name": "E Z Auto",
    "wof:placetype": "venue"
  },
  "geometry": {"coordinates":[-84.104979,40.746482],"type":"Point"}
}
