{
  "type": "Feature",
  "properties": {
    "addr:full": "33 Triangle Park Dr Cincinnati OH 45246",
    "addr:housenumber": "33",
    "addr:postcode": "45246",
    "addr:street": "Triangle Park Dr",
    "iso:country": "US",
    "sg:address": "33 Triangle Park Dr",
    "sg:city": "Cincinnati",
    "sg:classifiers": [
      {
        "category": "Banks \u0026 Credit Unions",
        "subcategory": "Bank",
        "type": "Services"
      }
    ],
    "sg:phone": "+1 513 772 7009",
    "sg:postcode": "45246",
    "sg:province": "OH",
    "sg:tags": [
      "loan",
      "mortgage",
      "real estate"
    ],
    "wof:name": "Progressive Mortgage",
    "wof:placetype": "venue"
  },
  "geometry": {"coordinates":[-84.446671,39.28749],"type":"Point"}
}
