{
  "type": "Feature",
  "properties": {
    "iso:country":"US",
    "sg:address":"33 Triangle Park Dr",
    "sg:city":"Cincinnati",
    "sg:classifiers":[
        {
            "category":"Banks & Credit Unions",
            "subcategory":"Bank",
            "type":"Services"
        }
    ],
    "sg:phone":"+1 513 772 7009",
    "sg:postcode":"45246",
    "sg:province":"OH",
    "sg:tags":[
        "loan",
        "mortgage",
        "real estate"
    ],
    "wof:name":"Progressive Mortgage",
    "wof:placetype":"venue"
},
  "geometry": {"coordinates":[-84.44667099999999,39.28749],"type":"Point"}
}