{
  "type": "Feature",
  "properties": {
    "addr:full": "5754 Cedarwood Dr Lewisburg OH 45338",
    "addr:housenumber": "5754",
    "addr:postcode": "45338",
    "addr:street": "Cedarwood Dr",
    "iso:country": "US",
    "sg:address": "5754 Cedarwood Dr",
    "sg:city": "Lewisburg",
    "sg:classifiers": [
      {
        "category": "Restaurant",
        "type": "Food \u0026 Drink"
      }
    ],
    "sg:phone": "+1 937 962 2510",
    "sg:postcode": "45338",
    "sg:province": "OH",
    "sg:tags": [
      "eating"
    ],
    "wof:name": "KS Restaurant",
    "wof:placetype": "venue"
  },
  "geometry": {"coordinates":[-84.485209,39.828787],"type":"Point"}
}
