{
  "type": "Feature",
  "properties": {
    "addr:full":"444 N Main St Akron OH 44310",
    "addr:housenumber":"444",
    "addr:postcode":"44310",
    "addr:street":"N Main St",
    "iso:country":"US",
    "sg:address":"444 N Main St",
    "sg:city":"Akron",
    "sg:classifiers":[
        {
            "category":"Health Services",
            "subcategory":"Health Practitioner",
            "type":"Services"
        }
    ],
    "sg:phone":"+1 330 379 8123",
    "sg:postcode":"44310",
    "sg:province":"OH",
    "sg:tags":[
        "psychologist"
    ],
    "wof:name":"Ivonne H Hobfoll Psycholgst",
    "wof:placetype":"venue"
},
  "geometry": {"coordinates":[-81.511849,41.09764],"type":"Point"}
}