{
  "type": "Feature",
  "properties": {
    "addr:full": "3759 Hamilton Cleves Rd Hamilton IN 45013",
    "addr:housenumber": "3759",
    "addr:postcode": "45013",
    "addr:street": "Cleves Rd",
    "iso:country": "US",
    "sg:address": "3759 Hamilton Cleves Rd",
    "sg:city": "Hamilton",
    "sg:classifiers": [
      {
        "category": "Professional",
        "subcategory": "Accounting \u0026 Tax Preparation",
        "type": "Services"
      }
    ],
    "sg:phone": "+1 513 738 1080",
    "sg:postcode": "45013",
    "sg:province": "IN",
    "sg:tags": [
      "accountant"
    ],
    "wof:name": "Barnthouse \u0026 Cornett",
    "wof:placetype": "venue"
  },
  "geometry": {"coordinates":[-84.63438,39.326873],"type":"Point"}
}
