{
  "type": "Feature",
  "properties": {
    "addr:full": "235 Cherry St Chillicothe OH 45601",
    "addr:housenumber": "235",
    "addr:postcode": "45601",
    "addr:street": "Cherry St",
    "iso:country": "US",
    "sg:address": "235 Cherry St",
    "sg:city": "Chillicothe",
    "sg:classifiers": [
      {
        "category": "Education",
        "subcategory": "School",
        "type": "Public Place"
      }
    ],
    "sg:phone": "+1 740 775 2936",
    "sg:postcode": "45601",
    "sg:province": "OH",
    "wof:name": "Schools Chillicothe City Schls",
    "wof:placetype": "venue"
  },
  "geometry": {"coordinates":[-82.994696,39.337194],"type":"Point"}
}
