{
  "type": "Feature",
  "properties": {
    "addr:full": "2020 Lincoln Way E Massillon OH 44646",
    "addr:housenumber": "2020",
    "addr:postcode": "44646",
    "addr:street": "Lincoln Way E",
    "iso:country": "US",
    "sg:address": "2020 Lincoln Way E",
    "sg:city": "Massillon",
    "sg:classifiers": [
      {
        "category": "Banks \u0026 Credit Unions",
        "subcategory": "Financial Services",
        "type": "Services"
      }
    ],
    "sg:phone": "+1 330 833 4276",
    "sg:postcode": "44646",
    "sg:province": "OH",
    "sg:tags": [
      "investor"
    ],
    "wof:name": "LRC Meadows Investors",
    "wof:placetype": "venue"
  },
  "geometry": {"coordinates":[-81.494774,40.798673],"type":"Point"}
}
