{
  "type": "Feature",
  "properties": {
    "iso:country":"US",
    "sg:address":"1878 Maryland Ave",
    "sg:city":"Columbus",
    "sg:classifiers":[
        {
            "category":"Professional",
            "type":"Services"
        }
    ],
    "sg:phone":"+1 614 252 6312",
    "sg:postcode":"43219",
    "sg:province":"OH",
    "wof:name":"Hord Jameika",
    "wof:placetype":"venue"
},
  "geometry": {"coordinates":[-82.951809,39.977655],"type":"Point"}
}