{
  "type": "Feature",
  "properties": {
    "iso:country":"US",
    "sg:address":"118 W High St",
    "sg:city":"Ashley",
    "sg:classifiers":[
        {
            "category":"Shopping",
            "type":"Retail Goods"
        }
    ],
    "sg:phone":"+1 740 747 2121",
    "sg:postcode":"43003",
    "sg:province":"OH",
    "sg:tags":[
        "trophy",
        "medal",
        "award"
    ],
    "wof:name":"R B Powers Co",
    "wof:placetype":"venue"
},
  "geometry": {"coordinates":[-82.963668,40.409546],"type":"Point"}
}