{
  "type": "Feature",
  "properties": {
    "iso:country":"US",
    "sg:address":"527 W Pike St",
    "sg:city":"Morrow",
    "sg:classifiers":[
        {
            "category":"Social Services",
            "subcategory":"Child Care",
            "type":"Services"
        }
    ],
    "sg:phone":"+1 513 899 9888",
    "sg:postcode":"45152",
    "sg:province":"OH",
    "sg:tags":[
        "kindergarten",
        "academic",
        "school"
    ],
    "wof:name":"Morrow Early Childhood Dev Ctr",
    "wof:placetype":"venue"
},
  "geometry": {"coordinates":[-84.141586,39.355901],"type":"Point"}
}