{
  "type": "Feature",
  "properties": {
    "iso:country":"US",
    "sg:address":"891 Highview Dr",
    "sg:city":"Columbus",
    "sg:classifiers":[
        {
            "category":"Wholesale",
            "subcategory":"Computers",
            "type":"Manufacturing & Wholesale Goods"
        }
    ],
    "sg:phone":"+1 614 885 3343",
    "sg:postcode":"43235",
    "sg:province":"OH",
    "wof:name":"Software Spectrum Inc",
    "wof:placetype":"venue"
},
  "geometry": {"coordinates":[-83.04140200000001,40.128611],"type":"Point"}
}