{
  "type": "Feature",
  "properties": {
    "addr:full": "891 Highview Dr Columbus OH 43235",
    "addr:housenumber": "891",
    "addr:postcode": "43235",
    "addr:street": "Highview Dr",
    "iso:country": "US",
    "sg:address": "891 Highview Dr",
    "sg:city": "Columbus",
    "sg:classifiers": [
      {
        "category": "Wholesale",
        "subcategory": "Computers",
        "type": "Manufacturing \u0026 Wholesale Goods"
      }
    ],
    "sg:phone": "+1 614 885 3343",
    "sg:postcode": "43235",
    "sg:province": "OH",
    "wof:name": "Software Spectrum Inc",
    "wof:placetype": "venue"
  },
  "geometry": {"coordinates":[-83.041402,40.128611],"type":"Point"}
}
