{
  "type": "Feature",
  "properties": {
    "iso:country":"US",
    "sg:address":"8531 Market St",
    "sg:city":"Youngstown",
    "sg:classifiers":[
        {
            "category":"Professional",
            "subcategory":"Computer Services",
            "type":"Services"
        }
    ],
    "sg:phone":"+1 330 726 5811",
    "sg:postcode":"44512",
    "sg:province":"OH",
    "sg:tags":[
        "training",
        "added",
        "reseller",
        "sal",
        "consulting",
        "value"
    ],
    "sg:website":"www.dimail.com",
    "wof:name":"Datakinetics Inc",
    "wof:placetype":"venue"
},
  "geometry": {"coordinates":[-80.662656,40.993249],"type":"Point"}
}