{
  "type": "Feature",
  "properties": {
    "iso:country":"US",
    "sg:address":"20426 Williamsburg Ct",
    "sg:city":"Cleveland",
    "sg:classifiers":[
        {
            "category":"Real Estate",
            "subcategory":"Real Estate Agent",
            "type":"Services"
        }
    ],
    "sg:phone":"+1 440 243 2206",
    "sg:postcode":"44130",
    "sg:province":"OH",
    "wof:name":"Yes 1 Realty Inc",
    "wof:placetype":"venue"
},
  "geometry": {"coordinates":[-81.847211,41.379853],"type":"Point"}
}