{
  "type": "Feature",
  "properties": {
    "iso:country":"US",
    "sg:address":"1405 Amherst Rd NE",
    "sg:city":"Massillon",
    "sg:classifiers":[
        {
            "category":"Retail",
            "subcategory":"Auto Repair",
            "type":"Services"
        }
    ],
    "sg:phone":"+1 330 834 9790",
    "sg:postcode":"44646",
    "sg:province":"OH",
    "sg:tags":[
        "repairing",
        "automobile",
        "gas"
    ],
    "sg:website":"michelinman.com|terrystiretown.com",
    "wof:name":"Terry's Tire Town",
    "wof:placetype":"venue"
},
  "geometry": {"coordinates":[-81.516899,40.812901],"type":"Point"}
}