{
  "type": "Feature",
  "properties": {
    "addr:full":"1295 S Johnson Rd Sebring OH 44672",
    "addr:housenumber":"1295",
    "addr:postcode":"44672",
    "addr:street":"S Johnson Rd",
    "iso:country":"US",
    "sg:address":"1295 S Johnson Rd",
    "sg:city":"Sebring",
    "sg:phone":"+1 330 938 6317",
    "sg:postcode":"44672",
    "sg:province":"OH",
    "sg:tags":[
        "farm"
    ],
    "wof:name":"Edwin A Stevens",
    "wof:placetype":"venue"
},
  "geometry": {"coordinates":[-81.03185999999999,40.911615],"type":"Point"}
}