{
  "type": "Feature",
  "properties": {
    "iso:country":"US",
    "sg:address":"3600 Terminal Rd",
    "sg:city":"Vandalia",
    "sg:classifiers":[
        {
            "category":"Organizations",
            "subcategory":"Community Association",
            "type":"Services"
        }
    ],
    "sg:phone":"+1 937 454 1221",
    "sg:postcode":"45377",
    "sg:province":"OH",
    "wof:name":"U S O",
    "wof:placetype":"venue"
},
  "geometry": {"coordinates":[-84.223614,39.899355],"type":"Point"}
}