{
  "type": "Feature",
  "properties": {
    "iso:country":"US",
    "sg:address":"137 Patti Dr",
    "sg:city":"Westerville",
    "sg:classifiers":[
        {
            "category":"Building & Trades",
            "subcategory":"Plumbing",
            "type":"Services"
        }
    ],
    "sg:phone":"+1 614 901 8020",
    "sg:postcode":"43081",
    "sg:province":"OH",
    "sg:tags":[
        "contractor"
    ],
    "wof:name":"Holt Mechanical",
    "wof:placetype":"venue"
},
  "geometry": {"coordinates":[-82.908501,40.121123],"type":"Point"}
}