{
  "type": "Feature",
  "properties": {
    "iso:country":"US",
    "sg:address":"1355 Cornish Dr",
    "sg:city":"Vandalia",
    "sg:classifiers":[
        {
            "category":"Freight",
            "type":"Transportation"
        }
    ],
    "sg:phone":"+1 937 898 7655",
    "sg:postcode":"45377",
    "sg:province":"OH",
    "sg:tags":[
        "delivery"
    ],
    "wof:name":"Economy Delivery Svc",
    "wof:placetype":"venue"
},
  "geometry": {"coordinates":[-84.217463,39.873254],"type":"Point"}
}