{
  "type": "Feature",
  "properties": {
    "addr:full": "11267 Reeder Ave NE Alliance OH 44601",
    "addr:housenumber": "11267",
    "addr:postcode": "44601",
    "addr:street": "Reeder Ave Ne",
    "iso:country": "US",
    "sg:address": "11267 Reeder Ave NE",
    "sg:city": "Alliance",
    "sg:classifiers": [
      {
        "category": "Building \u0026 Trades",
        "subcategory": "Construction",
        "type": "Services"
      }
    ],
    "sg:phone": "+1 330 935 0347",
    "sg:postcode": "44601",
    "sg:province": "OH",
    "sg:tags": [
      "house"
    ],
    "wof:name": "Frank Blosser Const",
    "wof:placetype": "venue"
  },
  "geometry": {"coordinates":[-81.197921,40.934439],"type":"Point"}
}
