{
  "type": "Feature",
  "properties": {
    "addr:full":"2820 Margate Rd Columbus OH 43221",
    "addr:housenumber":"2820",
    "addr:postcode":"43221",
    "addr:street":"Margate Rd",
    "iso:country":"US",
    "sg:address":"2820 Margate Rd",
    "sg:city":"Columbus",
    "sg:classifiers":[
        {
            "category":"Professional",
            "type":"Services"
        },
        {
            "category":"Restaurant",
            "type":"Food & Drink"
        }
    ],
    "sg:phone":"+1 614 485 3633",
    "sg:postcode":"43221",
    "sg:province":"OH",
    "sg:tags":[
        "establishment",
        "eating"
    ],
    "wof:name":"Gambrinus Franchise Co LLC",
    "wof:placetype":"venue"
},
  "geometry": {"coordinates":[-83.08516,40.012662],"type":"Point"}
}