{
  "type": "Feature",
  "properties": {
    "addr:full": "16508 Westdale Ave Cleveland OH 44135",
    "addr:housenumber": "16508",
    "addr:postcode": "44135",
    "addr:street": "Westdale Ave",
    "iso:country": "US",
    "sg:address": "16508 Westdale Ave",
    "sg:city": "Cleveland",
    "sg:classifiers": [
      {
        "category": "Professional",
        "subcategory": "Management \u0026 Consulting",
        "type": "Services"
      }
    ],
    "sg:phone": "+1 216 941 5622",
    "sg:postcode": "44135",
    "sg:province": "OH",
    "sg:tags": [
      "fuel"
    ],
    "wof:name": "Spirko Management Corp",
    "wof:placetype": "venue"
  },
  "geometry": {"coordinates":[-81.813491,41.439126],"type":"Point"}
}
