{
  "type": "Feature",
  "properties": {
    "addr:full":"970 Enright Ave Cincinnati OH 45205",
    "addr:housenumber":"970",
    "addr:postcode":"45205",
    "addr:street":"Enright Ave",
    "iso:country":"US",
    "sg:address":"970 Enright Ave",
    "sg:city":"Cincinnati",
    "sg:classifiers":[
        {
            "category":"Shopping",
            "subcategory":"Discount & Variety Stores",
            "type":"Retail Goods"
        }
    ],
    "sg:phone":"+1 513 921 0851",
    "sg:postcode":"45205",
    "sg:province":"OH",
    "wof:name":"Big Lots",
    "wof:placetype":"venue"
},
  "geometry": {"coordinates":[-84.572405,39.109818],"type":"Point"}
}