{
  "type": "Feature",
  "properties": {
    "addr:full": "1161 Riddlebarger Rd Portsmouth OH 45662",
    "addr:housenumber": "1161",
    "addr:postcode": "45662",
    "addr:street": "Riddlebarger Rd",
    "iso:country": "US",
    "sg:address": "1161 Riddlebarger Rd",
    "sg:city": "Portsmouth",
    "sg:classifiers": [
      {
        "category": "Farming",
        "subcategory": "Farm",
        "type": "Manufacturing \u0026 Wholesale Goods"
      }
    ],
    "sg:phone": "+1 740 820 2583",
    "sg:postcode": "45662",
    "sg:province": "OH",
    "sg:tags": [
      "crop",
      "general"
    ],
    "wof:name": "Roger Riddlebarger",
    "wof:placetype": "venue"
  },
  "geometry": {"coordinates":[-82.901309,38.836321],"type":"Point"}
}
