{
  "type": "Feature",
  "properties": {
    "iso:country":"US",
    "sg:address":"2310 Superior Ave E",
    "sg:city":"Cleveland",
    "sg:classifiers":[
        {
            "category":"Restaurant",
            "type":"Food & Drink"
        }
    ],
    "sg:phone":"+1 216 566 7282",
    "sg:postcode":"44114",
    "sg:province":"OH",
    "sg:tags":[
        "eating"
    ],
    "wof:name":"Culinarchy",
    "wof:placetype":"venue"
},
  "geometry": {"coordinates":[-81.67512,41.508629],"type":"Point"}
}