{
  "type": "Feature",
  "properties": {
    "addr:full":"3203 Cranston Dr Dublin OH 43017",
    "addr:housenumber":"3203",
    "addr:postcode":"43017",
    "addr:street":"Cranston Dr",
    "iso:country":"US",
    "sg:address":"3203 Cranston Dr",
    "sg:city":"Dublin",
    "sg:classifiers":[
        {
            "category":"Professional",
            "subcategory":"Computer Services",
            "type":"Services"
        }
    ],
    "sg:phone":"+1 614 336 9820",
    "sg:postcode":"43017",
    "sg:province":"OH",
    "sg:tags":[
        "internet"
    ],
    "wof:name":"Groupware Online",
    "wof:placetype":"venue"
},
  "geometry": {"coordinates":[-83.10358100000001,40.085437],"type":"Point"}
}