{
  "type": "Feature",
  "properties": {
    "addr:full":"117 E Washington St Lisbon OH 44432",
    "addr:housenumber":"117",
    "addr:postcode":"44432",
    "addr:street":"E Washington St",
    "iso:country":"US",
    "sg:address":"117 E Washington St",
    "sg:city":"Lisbon",
    "sg:classifiers":[
        {
            "category":"Banks & Credit Unions",
            "subcategory":"Bank",
            "type":"Services"
        }
    ],
    "sg:phone":"+1 330 424 0667",
    "sg:postcode":"44432",
    "sg:province":"OH",
    "sg:tags":[
        "loan",
        "broker"
    ],
    "wof:name":"Allied Home Mrtg Capitl Corp",
    "wof:placetype":"venue"
},
  "geometry": {"coordinates":[-80.767213,40.771004],"type":"Point"}
}