{
  "type": "Feature",
  "properties": {
    "iso:country":"US",
    "sg:address":"4167 State Rte 43",
    "sg:city":"Kent",
    "sg:classifiers":[
        {
            "category":"Organizations",
            "subcategory":"Religious Organization",
            "type":"Services"
        }
    ],
    "sg:phone":"+1 330 673 6079",
    "sg:postcode":"44240",
    "sg:province":"OH",
    "sg:tags":[
        "church"
    ],
    "wof:name":"Victory Baptist Temple",
    "wof:placetype":"venue"
},
  "geometry": {"coordinates":[-81.346731,41.102956],"type":"Point"}
}