{
  "type": "Feature",
  "properties": {
    "addr:full": "8125 Uehling Ln Dayton OH 45424",
    "addr:housenumber": "8125",
    "addr:postcode": "45424",
    "addr:street": "Uehling Ln",
    "iso:country": "US",
    "sg:address": "8125 Uehling Ln",
    "sg:city": "Dayton",
    "sg:classifiers": [
      {
        "category": "Building \u0026 Trades",
        "subcategory": "Cleaning \u0026 Sanitation",
        "type": "Services"
      }
    ],
    "sg:phone": "+1 937 434 3828",
    "sg:postcode": "45424",
    "sg:province": "OH",
    "sg:tags": [
      "ventilating",
      "system"
    ],
    "wof:name": "Duct Doctor",
    "wof:placetype": "venue"
  },
  "geometry": {"coordinates":[-84.129753,39.870667],"type":"Point"}
}
