{
  "type": "Feature",
  "properties": {
    "iso:country":"US",
    "sg:address":"120 Harrison Ave",
    "sg:city":"Harrison",
    "sg:classifiers":[
        {
            "category":"Professional",
            "subcategory":"Art Services",
            "type":"Services"
        }
    ],
    "sg:phone":"+1 513 367 0260",
    "sg:postcode":"45030",
    "sg:province":"OH",
    "sg:tags":[
        "graphic",
        "designer"
    ],
    "sg:website":"www.pfeifferdesign.com",
    "wof:name":"Pfeiffer Design Group",
    "wof:placetype":"venue"
},
  "geometry": {"coordinates":[-84.818735,39.261953],"type":"Point"}
}