{
  "type": "Feature",
  "properties": {
    "addr:full": "9507 Debold Koebel Rd Pleasant Plain OH 45162",
    "addr:housenumber": "9507",
    "addr:postcode": "45162",
    "addr:street": "Debold Koebel Rd",
    "iso:country": "US",
    "sg:address": "9507 Debold Koebel Rd",
    "sg:city": "Pleasant Plain",
    "sg:classifiers": [
      {
        "category": "Building \u0026 Trades",
        "subcategory": "Construction",
        "type": "Services"
      }
    ],
    "sg:phone": "+1 513 877 2421",
    "sg:postcode": "45162",
    "sg:province": "OH",
    "sg:tags": [
      "carpentry",
      "general",
      "contractor"
    ],
    "wof:name": "Jim's Carpentry Inc",
    "wof:placetype": "venue"
  },
  "geometry": {"coordinates":[-84.113174,39.287278],"type":"Point"}
}
