{
  "type": "Feature",
  "properties": {
    "addr:full":"5311 W Broad St Columbus OH 43228",
    "addr:housenumber":"5311",
    "addr:postcode":"43228",
    "addr:street":"W Broad St",
    "iso:country":"US",
    "sg:address":"5311 W Broad St",
    "sg:city":"Columbus",
    "sg:classifiers":[
        {
            "category":"Real Estate",
            "subcategory":"Real Estate Agent",
            "type":"Services"
        }
    ],
    "sg:phone":"+1 614 878 6431",
    "sg:postcode":"43228",
    "sg:province":"OH",
    "wof:name":"Saxton Realty",
    "wof:placetype":"venue"
},
  "geometry": {"coordinates":[-83.14182599999999,39.951631],"type":"Point"}
}