{
  "type": "Feature",
  "properties": {
    "iso:country":"US",
    "sg:address":"2145 W Dublin Granville Rd",
    "sg:city":"Columbus",
    "sg:classifiers":[
        {
            "category":"Restaurant",
            "type":"Food & Drink"
        }
    ],
    "sg:phone":"+1 614 438 0052",
    "sg:postcode":"43085",
    "sg:province":"OH",
    "sg:tags":[
        "eating",
        "caterer"
    ],
    "wof:name":"Two Caterers",
    "wof:placetype":"venue"
},
  "geometry": {"coordinates":[-83.049167,40.090129],"type":"Point"}
}