{
  "type": "Feature",
  "properties": {
    "addr:full": "510 E 5th St Dayton OH 45402",
    "addr:housenumber": "510",
    "addr:postcode": "45402",
    "addr:street": "E 5Th St",
    "iso:country": "US",
    "sg:address": "510 E 5th St",
    "sg:city": "Dayton",
    "sg:classifiers": [
      {
        "category": "Professional",
        "subcategory": "Business Services",
        "type": "Services"
      }
    ],
    "sg:phone": "+1 937 222 3011",
    "sg:postcode": "45402",
    "sg:province": "OH",
    "sg:tags": [
      "interior",
      "consultant",
      "design",
      "decorator"
    ],
    "wof:name": "Comfy Corners Hm Decor \u0026 Acces",
    "wof:placetype": "venue"
  },
  "geometry": {"coordinates":[-84.182603,39.757025],"type":"Point"}
}
