{
  "type": "Feature",
  "properties": {
    "addr:full": "2853 Alexander Rd Atwater OH 44201",
    "addr:housenumber": "2853",
    "addr:postcode": "44201",
    "addr:street": "Alexander Rd",
    "iso:country": "US",
    "sg:address": "2853 Alexander Rd",
    "sg:city": "Atwater",
    "sg:classifiers": [
      {
        "category": "Professional",
        "type": "Services"
      }
    ],
    "sg:phone": "+1 330 325 2766",
    "sg:postcode": "44201",
    "sg:province": "OH",
    "wof:name": "Melissa Semonin Memorial",
    "wof:placetype": "venue"
  },
  "geometry": {"coordinates":[-81.287039,41.026727],"type":"Point"}
}
