{
  "type": "Feature",
  "properties": {
    "addr:full": "3200 Woodburn Ave Cincinnati OH 45207",
    "addr:housenumber": "3200",
    "addr:postcode": "45207",
    "addr:street": "Woodburn Ave",
    "iso:country": "US",
    "sg:address": "3200 Woodburn Ave",
    "sg:city": "Cincinnati",
    "sg:classifiers": [
      {
        "category": "Restaurant",
        "type": "Food \u0026 Drink"
      }
    ],
    "sg:phone": "+1 513 281 6832",
    "sg:postcode": "45207",
    "sg:province": "OH",
    "sg:tags": [
      "eating"
    ],
    "wof:name": "Ikes Barbecue \u0026 Zodiac Lounge",
    "wof:placetype": "venue"
  },
  "geometry": {"coordinates":[-84.475789,39.137637],"type":"Point"}
}
