{
  "type": "Feature",
  "properties": {
    "addr:full": "1302 N Barron St Eaton OH 45320",
    "addr:housenumber": "1302",
    "addr:postcode": "45320",
    "addr:street": "N Barron St",
    "iso:country": "US",
    "sg:address": "1302 N Barron St",
    "sg:city": "Eaton",
    "sg:classifiers": [
      {
        "category": "Banks \u0026 Credit Unions",
        "subcategory": "Bank",
        "type": "Services"
      }
    ],
    "sg:phone": "+1 937 456 9607",
    "sg:postcode": "45320",
    "sg:province": "OH",
    "sg:tags": [
      "national",
      "commercial"
    ],
    "wof:name": "Firstar Bank",
    "wof:placetype": "venue"
  },
  "geometry": {"coordinates":[-84.636413,39.758552],"type":"Point"}
}
