{
  "type": "Feature",
  "properties": {
    "iso:country":"US",
    "sg:address":"1302 N Barron St",
    "sg:city":"Eaton",
    "sg:classifiers":[
        {
            "category":"Banks & Credit Unions",
            "subcategory":"Bank",
            "type":"Services"
        }
    ],
    "sg:phone":"+1 937 456 9607",
    "sg:postcode":"45320",
    "sg:province":"OH",
    "sg:tags":[
        "national",
        "commercial"
    ],
    "wof:name":"Firstar Bank",
    "wof:placetype":"venue"
},
  "geometry": {"coordinates":[-84.636413,39.758552],"type":"Point"}
}