{
  "type": "Feature",
  "properties": {
    "iso:country":"US",
    "sg:address":"2899 Hubbard Rd",
    "sg:city":"Madison",
    "sg:classifiers":[
        {
            "category":"Manufacturing",
            "subcategory":"Printing",
            "type":"Manufacturing & Wholesale Goods"
        }
    ],
    "sg:phone":"+1 440 428 0790",
    "sg:postcode":"44057",
    "sg:province":"OH",
    "sg:tags":[
        "newspaper"
    ],
    "wof:name":"Tribune",
    "wof:placetype":"venue"
},
  "geometry": {"coordinates":[-81.048444,41.798541],"type":"Point"}
}