{
  "type": "Feature",
  "properties": {
    "iso:country":"US",
    "sg:address":"11969 Lagrange Rd",
    "sg:city":"Elyria",
    "sg:classifiers":[
        {
            "category":"Building & Trades",
            "subcategory":"Construction",
            "type":"Services"
        }
    ],
    "sg:phone":"+1 440 458 6688",
    "sg:postcode":"44035",
    "sg:province":"OH",
    "sg:tags":[
        "marking",
        "maintenance",
        "parking"
    ],
    "wof:name":"Carlisle Township Road Dept",
    "wof:placetype":"venue"
},
  "geometry": {"coordinates":[-82.117501,41.323648],"type":"Point"}
}