{
  "type": "Feature",
  "properties": {
    "addr:full": "11969 Lagrange Rd Elyria OH 44035",
    "addr:housenumber": "11969",
    "addr:postcode": "44035",
    "addr:street": "Lagrange Rd",
    "iso:country": "US",
    "sg:address": "11969 Lagrange Rd",
    "sg:city": "Elyria",
    "sg:classifiers": [
      {
        "category": "Building \u0026 Trades",
        "subcategory": "Construction",
        "type": "Services"
      }
    ],
    "sg:phone": "+1 440 458 6688",
    "sg:postcode": "44035",
    "sg:province": "OH",
    "sg:tags": [
      "marking",
      "maintenance",
      "parking"
    ],
    "wof:name": "Carlisle Township Road Dept",
    "wof:placetype": "venue"
  },
  "geometry": {"coordinates":[-82.117501,41.323648],"type":"Point"}
}
