{
  "type": "Feature",
  "properties": {
    "addr:full":"22820 Tracy Ave Cleveland OH 44123",
    "addr:housenumber":"22820",
    "addr:postcode":"44123",
    "addr:street":"Tracy Ave",
    "iso:country":"US",
    "sg:address":"22820 Tracy Ave",
    "sg:city":"Cleveland",
    "sg:classifiers":[
        {
            "category":"Building & Trades",
            "subcategory":"Electrical",
            "type":"Services"
        }
    ],
    "sg:phone":"+1 216 261 5101",
    "sg:postcode":"44123",
    "sg:province":"OH",
    "sg:tags":[
        "electric",
        "contractor"
    ],
    "wof:name":"E C Electric",
    "wof:placetype":"venue"
},
  "geometry": {"coordinates":[-81.52032800000001,41.594248],"type":"Point"}
}