{
  "type": "Feature",
  "properties": {
    "addr:full":"7106 Ravenna Ave SE Waynesburg OH 44688",
    "addr:housenumber":"7106",
    "addr:postcode":"44688",
    "addr:street":"Ravenna Ave Se",
    "iso:country":"US",
    "sg:address":"7106 Ravenna Ave SE",
    "sg:city":"Waynesburg",
    "sg:classifiers":[
        {
            "category":"Wholesale",
            "subcategory":"Auto Parts",
            "type":"Manufacturing & Wholesale Goods"
        }
    ],
    "sg:phone":"+1 330 866 9965",
    "sg:postcode":"44688",
    "sg:province":"OH",
    "sg:tags":[
        "automobile",
        "rebuilt",
        "used"
    ],
    "wof:name":"We Got It Auto Recycling LLC",
    "wof:placetype":"venue"
},
  "geometry": {"coordinates":[-81.257653,40.697265],"type":"Point"}
}