{
  "type": "Feature",
  "properties": {
    "iso:country":"US",
    "sg:address":"2886 Niles Cortland Rd NE",
    "sg:city":"Cortland",
    "sg:classifiers":[
        {
            "category":"Insurance",
            "subcategory":"Insurance Agent",
            "type":"Services"
        }
    ],
    "sg:phone":"+1 330 638 6779",
    "sg:postcode":"44410",
    "sg:province":"OH",
    "wof:name":"Springer Rj Ins Agcy",
    "wof:placetype":"venue"
},
  "geometry": {"coordinates":[-80.733437,41.29537],"type":"Point"}
}