{
  "type": "Feature",
  "properties": {
    "addr:full":"726 Westwood Dr Newark OH 43055",
    "addr:housenumber":"726",
    "addr:postcode":"43055",
    "addr:street":"Westwood Dr",
    "iso:country":"US",
    "sg:address":"726 Westwood Dr",
    "sg:city":"Newark",
    "sg:classifiers":[
        {
            "category":"Shopping",
            "type":"Retail Goods"
        }
    ],
    "sg:phone":"+1 740 344 4552",
    "sg:postcode":"43055",
    "sg:province":"OH",
    "sg:tags":[
        "product",
        "wood"
    ],
    "wof:name":"Wood Cheryl",
    "wof:placetype":"venue"
},
  "geometry": {"coordinates":[-82.467521,40.062978],"type":"Point"}
}