{
  "type": "Feature",
  "properties": {
    "addr:full":"4116 Rockside Rd Cleveland OH 44131",
    "addr:housenumber":"4116",
    "addr:postcode":"44131",
    "addr:street":"Rockside Rd",
    "iso:country":"US",
    "sg:address":"4116 Rockside Rd",
    "sg:city":"Cleveland",
    "sg:classifiers":[
        {
            "category":"Organizations",
            "subcategory":"Community Association",
            "type":"Services"
        }
    ],
    "sg:phone":"+1 216 524 7918",
    "sg:postcode":"44131",
    "sg:province":"OH",
    "sg:tags":[
        "military"
    ],
    "sg:website":"www.vfw.org",
    "wof:name":"Veterans Of Foreign Wars",
    "wof:placetype":"venue"
},
  "geometry": {"coordinates":[-81.663301,41.399886],"type":"Point"}
}