{
  "type": "Feature",
  "properties": {
    "addr:full": "8790 Governors Hill Dr Cincinnati OH 45249",
    "addr:housenumber": "8790",
    "addr:postcode": "45249",
    "addr:street": "Governors Hill Dr",
    "iso:country": "US",
    "sg:address": "8790 Governors Hill Dr",
    "sg:city": "Cincinnati",
    "sg:classifiers": [
      {
        "category": "Professional",
        "subcategory": "Computer Services",
        "type": "Services"
      }
    ],
    "sg:phone": "+1 513 683 9449",
    "sg:postcode": "45249",
    "sg:province": "OH",
    "sg:tags": [
      "consultant",
      "designer"
    ],
    "wof:name": "Prima",
    "wof:placetype": "venue"
  },
  "geometry": {"coordinates":[-84.319061,39.289244],"type":"Point"}
}
