{
  "type": "Feature",
  "properties": {
    "iso:country":"US",
    "sg:address":"2117 Drumlin Dr",
    "sg:city":"Grove City",
    "sg:classifiers":[
        {
            "category":"Freight",
            "type":"Transportation"
        }
    ],
    "sg:phone":"+1 614 875 0582",
    "sg:postcode":"43123",
    "sg:province":"OH",
    "sg:tags":[
        "truck",
        "hauling",
        "dump"
    ],
    "wof:name":"K D Bear Enterprises Inc",
    "wof:placetype":"venue"
},
  "geometry": {"coordinates":[-83.065352,39.909979],"type":"Point"}
}