{
  "type": "Feature",
  "properties": {
    "addr:full":"2225 E Dublin Granville Rd Columbus OH 43229",
    "addr:housenumber":"2225",
    "addr:postcode":"43229",
    "addr:street":"E Dublin Granville Rd",
    "iso:country":"US",
    "sg:address":"2225 E Dublin Granville Rd",
    "sg:city":"Columbus",
    "sg:classifiers":[
        {
            "category":"Restaurant",
            "type":"Food & Drink"
        }
    ],
    "sg:menulink":"http://www.allmenus.com/oh/columbus/213136-taco-bell/menu/",
    "sg:phone":"+1 614 895 7667",
    "sg:postcode":"43229",
    "sg:province":"OH",
    "sg:tags":[
        "mexican"
    ],
    "wof:name":"Taco Bell",
    "wof:placetype":"venue"
},
  "geometry": {"coordinates":[-82.95775399999999,40.085776],"type":"Point"}
}