{
  "type": "Feature",
  "properties": {
    "addr:full":"7792 Olentangy River Rd Columbus OH 43235",
    "addr:housenumber":"7792",
    "addr:postcode":"43235",
    "addr:street":"Olentangy River Rd",
    "iso:country":"US",
    "sg:address":"7792 Olentangy River Rd",
    "sg:city":"Columbus",
    "sg:classifiers":[
        {
            "category":"Insurance",
            "subcategory":"Insurance Agent",
            "type":"Services"
        }
    ],
    "sg:phone":"+1 614 766 2775",
    "sg:postcode":"43235",
    "sg:province":"OH",
    "wof:name":"Steve Brown Agency Inc",
    "wof:placetype":"venue"
},
  "geometry": {"coordinates":[-83.03574399999999,40.122111],"type":"Point"}
}