{
  "type": "Feature",
  "properties": {
    "iso:country":"US",
    "sg:address":"103 E Indianola Ave",
    "sg:city":"Youngstown",
    "sg:classifiers":[
        {
            "category":"Home & Garden",
            "subcategory":"Building Materials",
            "type":"Retail Goods"
        }
    ],
    "sg:phone":"+1 330 782 1171",
    "sg:postcode":"44507",
    "sg:province":"OH",
    "sg:tags":[
        "roofing"
    ],
    "wof:name":"Banner Supply Co",
    "wof:placetype":"venue"
},
  "geometry": {"coordinates":[-80.652821,41.072568],"type":"Point"}
}