{
  "type": "Feature",
  "properties": {
    "addr:full": "21413 Halworth Rd Cleveland OH 44122",
    "addr:postcode": "21413;44122",
    "addr:street": "Halworth Rd",
    "iso:country": "US",
    "sg:address": "21413 Halworth Rd",
    "sg:city": "Cleveland",
    "sg:classifiers": [
      {
        "category": "Manufacturing",
        "subcategory": "Signs",
        "type": "Manufacturing \u0026 Wholesale Goods"
      }
    ],
    "sg:phone": "+1 216 752 9220",
    "sg:postcode": "44122",
    "sg:province": "OH",
    "wof:name": "Tek Solutions LLC",
    "wof:placetype": "venue"
  },
  "geometry": {"coordinates":[-81.524238,41.465703],"type":"Point"}
}
