{
  "type": "Feature",
  "properties": {
    "iso:country":"US",
    "sg:address":"5060 Girdle Rd",
    "sg:city":"Bristolville",
    "sg:classifiers":[
        {
            "category":"Freight",
            "type":"Transportation"
        }
    ],
    "sg:phone":"+1 330 889 3300",
    "sg:postcode":"44491",
    "sg:province":"OH",
    "sg:tags":[
        "trucking"
    ],
    "wof:name":"Grand River Transportation Inc",
    "wof:placetype":"venue"
},
  "geometry": {"coordinates":[-80.973668,41.396523],"type":"Point"}
}