{
  "type": "Feature",
  "properties": {
    "iso:country":"US",
    "sg:address":"17295 Chamberlain Rd",
    "sg:city":"Grafton",
    "sg:classifiers":[
        {
            "category":"Building & Trades",
            "subcategory":"Construction",
            "type":"Services"
        }
    ],
    "sg:phone":"+1 440 926 2288",
    "sg:postcode":"44044",
    "sg:province":"OH",
    "sg:tags":[
        "designer",
        "dealer",
        "pool",
        "swimming"
    ],
    "wof:name":"Pools Ponds & Courts",
    "wof:placetype":"venue"
},
  "geometry": {"coordinates":[-82.06219,41.233992],"type":"Point"}
}