{
  "type": "Feature",
  "properties": {
    "addr:full":"7405 Hitchcock Rd Youngstown OH 44512",
    "addr:housenumber":"7405",
    "addr:postcode":"44512",
    "addr:street":"Hitchcock Rd",
    "iso:country":"US",
    "sg:address":"7405 Hitchcock Rd",
    "sg:city":"Youngstown",
    "sg:classifiers":[
        {
            "category":"Building & Trades",
            "subcategory":"Construction",
            "type":"Services"
        }
    ],
    "sg:phone":"+1 330 758 9187",
    "sg:postcode":"44512",
    "sg:province":"OH",
    "sg:tags":[
        "hanging",
        "contractor"
    ],
    "wof:name":"Deniro Contracting",
    "wof:placetype":"venue"
},
  "geometry": {"coordinates":[-80.67692099999999,41.02263],"type":"Point"}
}