{
  "type": "Feature",
  "properties": {
    "addr:full":"210 E 305th St Willowick OH 44095",
    "addr:housenumber":"210",
    "addr:postcode":"44095",
    "addr:street":"E 305Th St",
    "iso:country":"US",
    "sg:address":"210 E 305th St",
    "sg:city":"Willowick",
    "sg:classifiers":[
        {
            "category":"Banks & Credit Unions",
            "subcategory":"Bank",
            "type":"Services"
        }
    ],
    "sg:phone":"+1 440 943 5600",
    "sg:postcode":"44095",
    "sg:province":"OH",
    "sg:tags":[
        "national"
    ],
    "wof:name":"National City Bank",
    "wof:placetype":"venue"
},
  "geometry": {"coordinates":[-81.47413,41.639021],"type":"Point"}
}