{
  "type": "Feature",
  "properties": {
    "addr:full": "7487 Indian Trl Youngstown OH 44514",
    "addr:housenumber": "7487",
    "addr:postcode": "44514",
    "addr:street": "Indian Trl",
    "iso:country": "US",
    "sg:address": "7487 Indian Trl",
    "sg:city": "Youngstown",
    "sg:classifiers": [
      {
        "category": "Professional",
        "subcategory": "Business Services",
        "type": "Services"
      }
    ],
    "sg:phone": "+1 330 757 8500",
    "sg:postcode": "44514",
    "sg:province": "OH",
    "sg:tags": [
      "appraiser"
    ],
    "wof:name": "A \u0026 A Appraisals",
    "wof:placetype": "venue"
  },
  "geometry": {"coordinates":[-80.617399,41.010483],"type":"Point"}
}
