{
  "type": "Feature",
  "properties": {
    "iso:country":"US",
    "sg:address":"7487 Indian Trl",
    "sg:city":"Youngstown",
    "sg:classifiers":[
        {
            "category":"Professional",
            "subcategory":"Business Services",
            "type":"Services"
        }
    ],
    "sg:phone":"+1 330 757 8500",
    "sg:postcode":"44514",
    "sg:province":"OH",
    "sg:tags":[
        "appraiser"
    ],
    "wof:name":"A & A Appraisals",
    "wof:placetype":"venue"
},
  "geometry": {"coordinates":[-80.61739900000001,41.010483],"type":"Point"}
}