{
  "type": "Feature",
  "properties": {
    "iso:country":"US",
    "sg:address":"7462 Jager Ct",
    "sg:city":"Cincinnati",
    "sg:classifiers":[
        {
            "category":"Health Services",
            "subcategory":"Dentist",
            "type":"Services"
        }
    ],
    "sg:phone":"+1 513 232 4600",
    "sg:postcode":"45230",
    "sg:province":"OH",
    "wof:name":"Schiller & Emami Drs",
    "wof:placetype":"venue"
},
  "geometry": {"coordinates":[-84.35133399999999,39.066778],"type":"Point"}
}