{
  "type": "Feature",
  "properties": {
    "addr:full":"535 Park Ave Newton Falls OH 44444",
    "addr:housenumber":"535",
    "addr:postcode":"44444",
    "addr:street":"Park Ave",
    "iso:country":"US",
    "sg:address":"535 Park Ave",
    "sg:city":"Newton Falls",
    "sg:classifiers":[
        {
            "category":"Shopping",
            "subcategory":"Jewelry",
            "type":"Retail Goods"
        }
    ],
    "sg:phone":"+1 330 872 8312",
    "sg:postcode":"44444",
    "sg:province":"OH",
    "wof:name":"Stephens Jewelry Inc",
    "wof:placetype":"venue"
},
  "geometry": {"coordinates":[-80.976389,41.195296],"type":"Point"}
}