{
  "type": "Feature",
  "properties": {
    "iso:country":"US",
    "sg:address":"4136 Logan Way",
    "sg:city":"Youngstown",
    "sg:classifiers":[
        {
            "category":"Manufacturing",
            "subcategory":"Furniture",
            "type":"Manufacturing & Wholesale Goods"
        }
    ],
    "sg:phone":"+1 330 759 2234",
    "sg:postcode":"44505",
    "sg:province":"OH",
    "sg:tags":[
        "building",
        "mfg",
        "wood",
        "public",
        "furn"
    ],
    "wof:name":"Gasser Chair Company Inc",
    "wof:placetype":"venue"
},
  "geometry": {"coordinates":[-80.634021,41.155582],"type":"Point"}
}