{
  "type": "Feature",
  "properties": {
    "addr:full": "4136 Logan Way Youngstown OH 44505",
    "addr:housenumber": "4136",
    "addr:postcode": "44505",
    "addr:street": "Logan Way",
    "iso:country": "US",
    "sg:address": "4136 Logan Way",
    "sg:city": "Youngstown",
    "sg:classifiers": [
      {
        "category": "Manufacturing",
        "subcategory": "Furniture",
        "type": "Manufacturing \u0026 Wholesale Goods"
      }
    ],
    "sg:phone": "+1 330 759 2234",
    "sg:postcode": "44505",
    "sg:province": "OH",
    "sg:tags": [
      "building",
      "mfg",
      "wood",
      "public",
      "furn"
    ],
    "wof:name": "Gasser Chair Company Inc",
    "wof:placetype": "venue"
  },
  "geometry": {"coordinates":[-80.634021,41.155582],"type":"Point"}
}
