{
  "type": "Feature",
  "properties": {
    "iso:country":"US",
    "sg:address":"3220 Spring Grove Ave",
    "sg:city":"Cincinnati",
    "sg:classifiers":[
        {
            "category":"Shopping",
            "type":"Retail Goods"
        }
    ],
    "sg:phone":"+1 513 681 5111",
    "sg:postcode":"45225",
    "sg:province":"OH",
    "sg:tags":[
        "plumbing",
        "electrical",
        "supply"
    ],
    "wof:name":"Leons Supply",
    "wof:placetype":"venue"
},
  "geometry": {"coordinates":[-84.54161499999999,39.141488],"type":"Point"}
}