{
  "type": "Feature",
  "properties": {
    "addr:full": "3220 Spring Grove Ave Cincinnati OH 45225",
    "addr:housenumber": "3220",
    "addr:postcode": "45225",
    "addr:street": "Spring Grove Ave",
    "iso:country": "US",
    "sg:address": "3220 Spring Grove Ave",
    "sg:city": "Cincinnati",
    "sg:classifiers": [
      {
        "category": "Shopping",
        "type": "Retail Goods"
      }
    ],
    "sg:phone": "+1 513 681 5111",
    "sg:postcode": "45225",
    "sg:province": "OH",
    "sg:tags": [
      "plumbing",
      "electrical",
      "supply"
    ],
    "wof:name": "Leons Supply",
    "wof:placetype": "venue"
  },
  "geometry": {"coordinates":[-84.541615,39.141488],"type":"Point"}
}
