{
  "type": "Feature",
  "properties": {
    "addr:full":"2111 Kindel Ave Cincinnati OH 45214",
    "addr:housenumber":"2111",
    "addr:postcode":"45214",
    "addr:street":"Kindel Ave",
    "iso:country":"US",
    "sg:address":"2111 Kindel Ave",
    "sg:city":"Cincinnati",
    "sg:classifiers":[
        {
            "category":"Wholesale",
            "subcategory":"Meat",
            "type":"Manufacturing & Wholesale Goods"
        }
    ],
    "sg:phone":"+1 513 621 4160",
    "sg:postcode":"45214",
    "sg:province":"OH",
    "sg:tags":[
        "sausage",
        "mfg"
    ],
    "wof:name":"Blr Meats LLC",
    "wof:placetype":"venue"
},
  "geometry": {"coordinates":[-84.53184899999999,39.121101],"type":"Point"}
}