{
  "type": "Feature",
  "properties": {
    "addr:full": "8478 Waynesburg Dr SE Waynesburg OH 44688",
    "addr:housenumber": "8478",
    "addr:postcode": "44688",
    "addr:street": "Waynesburg Dr Se",
    "iso:country": "US",
    "sg:address": "8478 Waynesburg Dr SE",
    "sg:city": "Waynesburg",
    "sg:classifiers": [
      {
        "category": "Retail",
        "subcategory": "Auto Repair",
        "type": "Services"
      }
    ],
    "sg:phone": "+1 330 866 2742",
    "sg:postcode": "44688",
    "sg:province": "OH",
    "sg:tags": [
      "body"
    ],
    "wof:name": "Almasy Body Shop",
    "wof:placetype": "venue"
  },
  "geometry": {"coordinates":[-81.261021,40.679587],"type":"Point"}
}
