{
  "type": "Feature",
  "properties": {
    "addr:full": "4502 N Leavitt Rd NW Warren OH 44485",
    "addr:housenumber": "4502",
    "addr:postcode": "44485",
    "addr:street": "N Leavitt Rd Nw",
    "iso:country": "US",
    "sg:address": "4502 N Leavitt Rd NW",
    "sg:city": "Warren",
    "sg:classifiers": [
      {
        "category": "Home \u0026 Garden",
        "subcategory": "Building Materials",
        "type": "Retail Goods"
      }
    ],
    "sg:phone": "+1 330 847 3612",
    "sg:postcode": "44485",
    "sg:province": "OH",
    "sg:tags": [
      "door"
    ],
    "wof:name": "T N A Garage Doors",
    "wof:placetype": "venue"
  },
  "geometry": {"coordinates":[-80.864533,41.29042],"type":"Point"}
}
