{
  "type": "Feature",
  "properties": {
    "iso:country":"US",
    "sg:address":"4502 N Leavitt Rd NW",
    "sg:city":"Warren",
    "sg:classifiers":[
        {
            "category":"Home & Garden",
            "subcategory":"Building Materials",
            "type":"Retail Goods"
        }
    ],
    "sg:phone":"+1 330 847 3612",
    "sg:postcode":"44485",
    "sg:province":"OH",
    "sg:tags":[
        "door"
    ],
    "wof:name":"T N A Garage Doors",
    "wof:placetype":"venue"
},
  "geometry": {"coordinates":[-80.86453299999999,41.29042],"type":"Point"}
}