{
  "type": "Feature",
  "properties": {
    "addr:full": "3166 Linwood Ave Cincinnati OH 45208",
    "addr:housenumber": "3166",
    "addr:postcode": "45208",
    "addr:street": "Linwood Ave",
    "iso:country": "US",
    "sg:address": "3166 Linwood Ave",
    "sg:city": "Cincinnati",
    "sg:classifiers": [
      {
        "category": "Restaurant",
        "type": "Food \u0026 Drink"
      }
    ],
    "sg:phone": "+1 513 321 0978",
    "sg:postcode": "45208",
    "sg:province": "OH",
    "wof:name": "Ramundo's Pizzeria",
    "wof:placetype": "venue"
  },
  "geometry": {"coordinates":[-84.430402,39.128539],"type":"Point"}
}
