{
  "type": "Feature",
  "properties": {
    "iso:country":"US",
    "sg:address":"3166 Linwood Ave",
    "sg:city":"Cincinnati",
    "sg:classifiers":[
        {
            "category":"Restaurant",
            "type":"Food & Drink"
        }
    ],
    "sg:phone":"+1 513 321 0978",
    "sg:postcode":"45208",
    "sg:province":"OH",
    "wof:name":"Ramundo's Pizzeria",
    "wof:placetype":"venue"
},
  "geometry": {"coordinates":[-84.430402,39.128539],"type":"Point"}
}