{
  "type": "Feature",
  "properties": {
    "addr:full": "2009 Springdale Rd Cincinnati OH 45231",
    "addr:housenumber": "2009",
    "addr:postcode": "45231",
    "addr:street": "Springdale Rd",
    "iso:country": "US",
    "sg:address": "2009 Springdale Rd",
    "sg:city": "Cincinnati",
    "sg:classifiers": [
      {
        "category": "Restaurant",
        "type": "Food \u0026 Drink"
      }
    ],
    "sg:phone": "+1 513 742 8771",
    "sg:postcode": "45231",
    "sg:province": "OH",
    "sg:tags": [
      "eating"
    ],
    "wof:name": "Goody Shop",
    "wof:placetype": "venue"
  },
  "geometry": {"coordinates":[-84.557627,39.259395],"type":"Point"}
}
