{
  "type": "Feature",
  "properties": {
    "iso:country":"US",
    "sg:address":"934 Keswick Pl",
    "sg:city":"Cincinnati",
    "sg:classifiers":[
        {
            "category":"Wholesale",
            "subcategory":"Machinery & Supplies",
            "type":"Manufacturing & Wholesale Goods"
        }
    ],
    "sg:phone":"+1 513 232 4862",
    "sg:postcode":"45230",
    "sg:province":"OH",
    "sg:tags":[
        "re",
        "product",
        "fiber",
        "organic",
        "used"
    ],
    "wof:name":"Symco Products Inc",
    "wof:placetype":"venue"
},
  "geometry": {"coordinates":[-84.371996,39.066145],"type":"Point"}
}