{
  "type": "Feature",
  "properties": {
    "iso:country":"US",
    "sg:address":"10121 Princeton Glendale Rd",
    "sg:city":"Cincinnati",
    "sg:classifiers":[
        {
            "category":"Wholesale",
            "subcategory":"Construction Materials",
            "type":"Manufacturing & Wholesale Goods"
        }
    ],
    "sg:phone":"+1 513 874 8863",
    "sg:postcode":"45246",
    "sg:province":"OH",
    "wof:name":"Holham/Dundee Cement Co",
    "wof:placetype":"venue"
},
  "geometry": {"coordinates":[-84.465406,39.304567],"type":"Point"}
}