{
  "type": "Feature",
  "properties": {
    "addr:full": "4512 Fohl St SW Canton OH 44706",
    "addr:postcode": "4512;44706",
    "addr:street": "Fohl St Sw",
    "iso:country": "US",
    "sg:address": "4512 Fohl St SW",
    "sg:city": "Canton",
    "sg:classifiers": [
      {
        "category": "Shopping",
        "subcategory": "Bicycles \u0026 Sporting Goods",
        "type": "Retail Goods"
      }
    ],
    "sg:phone": "+1 330 484 1350",
    "sg:postcode": "44706",
    "sg:province": "OH",
    "wof:name": "E\u0026G Fishing Supplies",
    "wof:placetype": "venue"
  },
  "geometry": {"coordinates":[-81.435967,40.729653],"type":"Point"}
}
