{
  "type": "Feature",
  "properties": {
    "iso:country":"US",
    "sg:address":"4512 Fohl St SW",
    "sg:city":"Canton",
    "sg:classifiers":[
        {
            "category":"Shopping",
            "subcategory":"Bicycles & Sporting Goods",
            "type":"Retail Goods"
        }
    ],
    "sg:phone":"+1 330 484 1350",
    "sg:postcode":"44706",
    "sg:province":"OH",
    "wof:name":"E&G Fishing Supplies",
    "wof:placetype":"venue"
},
  "geometry": {"coordinates":[-81.43596700000001,40.729653],"type":"Point"}
}