{
  "type": "Feature",
  "properties": {
    "iso:country":"US",
    "sg:address":"1335 W Main St",
    "sg:city":"Kent",
    "sg:classifiers":[
        {
            "category":"Wholesale",
            "subcategory":"Medical Equipment & Supplies",
            "type":"Manufacturing & Wholesale Goods"
        }
    ],
    "sg:phone":"+1 330 673 9809",
    "sg:postcode":"44240",
    "sg:province":"OH",
    "sg:tags":[
        "hospital"
    ],
    "wof:name":"Integrated Medical Inc",
    "wof:placetype":"venue"
},
  "geometry": {"coordinates":[-81.391975,41.153235],"type":"Point"}
}