{
  "type": "Feature",
  "properties": {
    "addr:full": "1335 W Main St Kent OH 44240",
    "addr:housenumber": "1335",
    "addr:postcode": "44240",
    "addr:street": "W Main St",
    "iso:country": "US",
    "sg:address": "1335 W Main St",
    "sg:city": "Kent",
    "sg:classifiers": [
      {
        "category": "Wholesale",
        "subcategory": "Medical Equipment \u0026 Supplies",
        "type": "Manufacturing \u0026 Wholesale Goods"
      }
    ],
    "sg:phone": "+1 330 673 9809",
    "sg:postcode": "44240",
    "sg:province": "OH",
    "sg:tags": [
      "hospital"
    ],
    "wof:name": "Integrated Medical Inc",
    "wof:placetype": "venue"
  },
  "geometry": {"coordinates":[-81.391975,41.153235],"type":"Point"}
}
