{
  "type": "Feature",
  "properties": {
    "iso:country":"US",
    "sg:address":"1800 E State Rd",
    "sg:city":"Lima",
    "sg:classifiers":[
        {
            "category":"Retail",
            "subcategory":"Repair Shop",
            "type":"Services"
        }
    ],
    "sg:phone":"+1 419 229 7226",
    "sg:postcode":"45801",
    "sg:province":"OH",
    "sg:tags":[
        "appliance"
    ],
    "wof:name":"A-1 Appliance Repair Svc",
    "wof:placetype":"venue"
},
  "geometry": {"coordinates":[-84.074224,40.817442],"type":"Point"}
}