{
  "type": "Feature",
  "properties": {
    "addr:full":"1585 Lexington Ave Mansfield OH 44907",
    "addr:housenumber":"1585",
    "addr:postcode":"44907",
    "addr:street":"Lexington Ave",
    "iso:country":"US",
    "sg:address":"1585 Lexington Ave",
    "sg:city":"Mansfield",
    "sg:classifiers":[
        {
            "category":"Freight",
            "type":"Transportation"
        }
    ],
    "sg:phone":"+1 419 756 5577",
    "sg:postcode":"44907",
    "sg:province":"OH",
    "sg:tags":[
        "commercial",
        "storage"
    ],
    "wof:name":"Storage Inns Of America",
    "wof:placetype":"venue"
},
  "geometry": {"coordinates":[-82.547377,40.7171],"type":"Point"}
}