{
  "type": "Feature",
  "properties": {
    "iso:country":"US",
    "sg:address":"18510 Euclid Ave",
    "sg:city":"Cleveland",
    "sg:classifiers":[
        {
            "category":"Travel",
            "subcategory":"Hotels & Motels",
            "type":"Entertainment"
        }
    ],
    "sg:phone":"+1 216 531 5602",
    "sg:postcode":"44112",
    "sg:province":"OH",
    "wof:name":"American Motel",
    "wof:placetype":"venue"
},
  "geometry": {"coordinates":[-81.548659,41.558022],"type":"Point"}
}