{
  "type": "Feature",
  "properties": {
    "iso:country":"US",
    "sg:address":"26 Hitching Post Rd",
    "sg:city":"Englewood",
    "sg:classifiers":[
        {
            "category":"Wholesale",
            "subcategory":"Computers",
            "type":"Manufacturing & Wholesale Goods"
        }
    ],
    "sg:phone":"+1 937 836 6867",
    "sg:postcode":"45322",
    "sg:province":"OH",
    "sg:tags":[
        "consulting",
        "related"
    ],
    "wof:name":"P C Broker",
    "wof:placetype":"venue"
},
  "geometry": {"coordinates":[-84.31035799999999,39.893376],"type":"Point"}
}