{
  "type": "Feature",
  "properties": {
    "addr:full": "26 Hitching Post Rd Englewood OH 45322",
    "addr:housenumber": "26",
    "addr:postcode": "45322",
    "addr:street": "Hitching Post Rd",
    "iso:country": "US",
    "sg:address": "26 Hitching Post Rd",
    "sg:city": "Englewood",
    "sg:classifiers": [
      {
        "category": "Wholesale",
        "subcategory": "Computers",
        "type": "Manufacturing \u0026 Wholesale Goods"
      }
    ],
    "sg:phone": "+1 937 836 6867",
    "sg:postcode": "45322",
    "sg:province": "OH",
    "sg:tags": [
      "consulting",
      "related"
    ],
    "wof:name": "P C Broker",
    "wof:placetype": "venue"
  },
  "geometry": {"coordinates":[-84.310358,39.893376],"type":"Point"}
}
