{
  "type": "Feature",
  "properties": {
    "addr:full": "3227 Belmont Ave Youngstown OH 44505",
    "addr:housenumber": "3227",
    "addr:postcode": "44505",
    "addr:street": "Belmont Ave",
    "iso:country": "US",
    "sg:address": "3227 Belmont Ave",
    "sg:city": "Youngstown",
    "sg:classifiers": [
      {
        "category": "Building \u0026 Trades",
        "subcategory": "Plumbing",
        "type": "Services"
      }
    ],
    "sg:phone": "+1 330 534 7840",
    "sg:postcode": "44505",
    "sg:province": "OH",
    "sg:tags": [
      "heating",
      "contractor"
    ],
    "wof:name": "Quality Heating \u0026 AC",
    "wof:placetype": "venue"
  },
  "geometry": {"coordinates":[-80.665429,41.141502],"type":"Point"}
}
