{
  "type": "Feature",
  "properties": {
    "iso:country":"US",
    "sg:address":"1004 N McCord Rd",
    "sg:city":"Toledo",
    "sg:classifiers":[
        {
            "category":"Professional",
            "type":"Services"
        }
    ],
    "sg:phone":"+1 419 868 9142",
    "sg:postcode":"43615",
    "sg:province":"OH",
    "wof:name":"Prince Protection Specialists",
    "wof:placetype":"venue"
},
  "geometry": {"coordinates":[-83.703566,41.649091],"type":"Point"}
}