{
  "type": "Feature",
  "properties": {
    "addr:full": "9640 Kramer Rd Bowling Green OH 43402",
    "addr:housenumber": "9640",
    "addr:postcode": "43402",
    "addr:street": "Kramer Rd",
    "iso:country": "US",
    "sg:address": "9640 Kramer Rd",
    "sg:city": "Bowling Green",
    "sg:phone": "+1 419 352 8849",
    "sg:postcode": "43402",
    "sg:province": "OH",
    "sg:tags": [
      "farm",
      "corn",
      "soybean"
    ],
    "wof:name": "Franklin Swartz",
    "wof:placetype": "venue"
  },
  "geometry": {"coordinates":[-83.591685,41.341525],"type":"Point"}
}
