{
  "type": "Feature",
  "properties": {
    "iso:country":"US",
    "sg:address":"2902 Monroe St",
    "sg:city":"Toledo",
    "sg:classifiers":[
        {
            "category":"Restaurant",
            "type":"Food & Drink"
        }
    ],
    "sg:menulink":"http://www.allmenus.com/oh/toledo/211503-kfc---kentucky-fried-chicken/menu/",
    "sg:phone":"+1 419 242 6200",
    "sg:postcode":"43606",
    "sg:province":"OH",
    "sg:tags":[
        "american",
        "chicken"
    ],
    "wof:name":"KFC - Kentucky Fried Chicken",
    "wof:placetype":"venue"
},
  "geometry": {"coordinates":[-83.568512,41.663744],"type":"Point"}
}