{
  "type": "Feature",
  "properties": {
    "addr:full": "3021 Bethel Rd Columbus OH 43220",
    "addr:housenumber": "3021",
    "addr:postcode": "43220",
    "addr:street": "Bethel Rd",
    "iso:country": "US",
    "sg:address": "3021 Bethel Rd",
    "sg:city": "Columbus",
    "sg:classifiers": [
      {
        "category": "Professional",
        "subcategory": "Computer Services",
        "type": "Services"
      }
    ],
    "sg:phone": "+1 614 884 3714",
    "sg:postcode": "43220",
    "sg:province": "OH",
    "sg:tags": [
      "development",
      "software"
    ],
    "wof:name": "Desktop Solutions",
    "wof:placetype": "venue"
  },
  "geometry": {"coordinates":[-83.097518,40.065021],"type":"Point"}
}
