{
  "type": "Feature",
  "properties": {
    "addr:full":"34560 Parkinson Rd Middleport OH 45760",
    "addr:postcode":"34560;45760",
    "addr:street":"Parkinson Rd",
    "iso:country":"US",
    "sg:address":"34560 Parkinson Rd",
    "sg:city":"Middleport",
    "sg:phone":"+1 740 742 2083",
    "sg:postcode":"45760",
    "sg:province":"OH",
    "sg:tags":[
        "farm",
        "field",
        "corn",
        "livestock",
        "crop"
    ],
    "wof:name":"Kopec Farms",
    "wof:placetype":"venue"
},
  "geometry": {"coordinates":[-82.193275,39.031733],"type":"Point"}
}