{
  "type": "Feature",
  "properties": {
    "iso:country":"US",
    "sg:address":"3150 Darlington Rd",
    "sg:city":"Toledo",
    "sg:classifiers":[
        {
            "category":"Shopping",
            "subcategory":"Florist",
            "type":"Retail Goods"
        }
    ],
    "sg:phone":"+1 419 536 0605",
    "sg:postcode":"43606",
    "sg:province":"OH",
    "wof:name":"Floralcrest Designs LLC",
    "wof:placetype":"venue"
},
  "geometry": {"coordinates":[-83.620925,41.668735],"type":"Point"}
}