{
  "type": "Feature",
  "properties": {
    "addr:full": "380 N Main St Mansfield OH 44902",
    "addr:housenumber": "380",
    "addr:postcode": "44902",
    "addr:street": "N Main St",
    "iso:country": "US",
    "sg:address": "380 N Main St",
    "sg:city": "Mansfield",
    "sg:classifiers": [
      {
        "category": "Professional",
        "type": "Services"
      }
    ],
    "sg:phone": "+1 419 522 1102",
    "sg:postcode": "44902",
    "sg:province": "OH",
    "sg:tags": [
      "establishment"
    ],
    "wof:name": "PSPI",
    "wof:placetype": "venue"
  },
  "geometry": {"coordinates":[-82.514761,40.768855],"type":"Point"}
}
