{
  "type": "Feature",
  "properties": {
    "addr:full":"24615 Chagrin Blvd Cleveland OH 44122",
    "addr:housenumber":"24615",
    "addr:postcode":"44122",
    "addr:street":"Chagrin Blvd",
    "iso:country":"US",
    "sg:address":"24615 Chagrin Blvd",
    "sg:city":"Cleveland",
    "sg:classifiers":[
        {
            "category":"Banks & Credit Unions",
            "subcategory":"Bank",
            "type":"Services"
        }
    ],
    "sg:phone":"+1 216 515 0053",
    "sg:postcode":"44122",
    "sg:province":"OH",
    "sg:tags":[
        "national",
        "commercial"
    ],
    "wof:name":"Huntington National Bank",
    "wof:placetype":"venue"
},
  "geometry": {"coordinates":[-81.500809,41.464529],"type":"Point"}
}