{
  "type": "Feature",
  "properties": {
    "addr:full":"10905 Hebron Rd Hebron OH 43025",
    "addr:housenumber":"10905",
    "addr:postcode":"43025",
    "addr:street":"Hebron Rd",
    "iso:country":"US",
    "sg:address":"10905 Hebron Rd",
    "sg:city":"Hebron",
    "sg:classifiers":[
        {
            "category":"Retail",
            "subcategory":"Auto Rental",
            "type":"Services"
        }
    ],
    "sg:phone":"+1 740 928 6335",
    "sg:postcode":"43025",
    "sg:province":"OH",
    "sg:tags":[
        "truck"
    ],
    "wof:name":"U-Haul",
    "wof:placetype":"venue"
},
  "geometry": {"coordinates":[-82.47967300000001,39.937639],"type":"Point"}
}