{
  "type": "Feature",
  "properties": {
    "addr:full":"6551 Wales Rd Northwood OH 43619",
    "addr:housenumber":"6551",
    "addr:postcode":"43619",
    "addr:street":"Wales Rd",
    "iso:country":"US",
    "sg:address":"6551 Wales Rd",
    "sg:city":"Northwood",
    "sg:classifiers":[
        {
            "category":"Retail",
            "subcategory":"Repair Shop",
            "type":"Services"
        }
    ],
    "sg:phone":"+1 419 693 0404",
    "sg:postcode":"43619",
    "sg:province":"OH",
    "sg:tags":[
        "industrial",
        "tank",
        "machinery",
        "clean"
    ],
    "wof:name":"Buckeye Tank & Trailer Inc",
    "wof:placetype":"venue"
},
  "geometry": {"coordinates":[-83.50618900000001,41.608516],"type":"Point"}
}