{
  "type": "Feature",
  "properties": {
    "iso:country":"US",
    "sg:address":"115 US Hwy 6",
    "sg:city":"Mc Clure",
    "sg:classifiers":[
        {
            "category":"Professional",
            "type":"Services"
        }
    ],
    "sg:phone":"+1 419 748 9734",
    "sg:postcode":"43534",
    "sg:province":"OH",
    "sg:tags":[
        "establishment"
    ],
    "wof:name":"Richard's Marathon",
    "wof:placetype":"venue"
},
  "geometry": {"coordinates":[-83.941204,41.371304],"type":"Point"}
}