{
  "type": "Feature",
  "properties": {
    "addr:full": "1 Andrews Cir Cleveland OH 44141",
    "addr:housenumber": "1",
    "addr:postcode": "44141",
    "addr:street": "Andrews Cir",
    "iso:country": "US",
    "sg:address": "1 Andrews Cir",
    "sg:city": "Cleveland",
    "sg:classifiers": [
      {
        "category": "Professional",
        "subcategory": "Business Services",
        "type": "Services"
      }
    ],
    "sg:phone": "+1 440 717 0291",
    "sg:postcode": "44141",
    "sg:province": "OH",
    "sg:tags": [
      "organizing"
    ],
    "wof:name": "Home Organizing Angels",
    "wof:placetype": "venue"
  },
  "geometry": {"coordinates":[-81.643711,41.280319],"type":"Point"}
}
