{
  "type": "Feature",
  "properties": {
    "addr:full":"50 Coors Blvd Pataskala OH 43062",
    "addr:housenumber":"50",
    "addr:postcode":"43062",
    "addr:street":"Coors Blvd",
    "iso:country":"US",
    "sg:address":"50 Coors Blvd",
    "sg:city":"Pataskala",
    "sg:classifiers":[
        {
            "category":"Real Estate",
            "subcategory":"Real Estate Operator",
            "type":"Services"
        }
    ],
    "sg:phone":"+1 740 927 1126",
    "sg:postcode":"43062",
    "sg:province":"OH",
    "sg:tags":[
        "apartment"
    ],
    "wof:name":"Pataskala Greens Vlg Square",
    "wof:placetype":"venue"
},
  "geometry": {"coordinates":[-82.671925,39.998846],"type":"Point"}
}