{
  "type": "Feature",
  "properties": {
    "addr:full": "301 Bank St Lodi OH 44254",
    "addr:housenumber": "301",
    "addr:postcode": "44254",
    "addr:street": "Bank St",
    "iso:country": "US",
    "sg:address": "301 Bank St",
    "sg:city": "Lodi",
    "sg:classifiers": [
      {
        "category": "Government",
        "subcategory": "Office",
        "type": "Public Place"
      }
    ],
    "sg:phone": "+1 330 948 1099",
    "sg:postcode": "44254",
    "sg:province": "OH",
    "sg:tags": [
      "govt",
      "city"
    ],
    "wof:name": "Lodi Utility Office",
    "wof:placetype": "venue"
  },
  "geometry": {"coordinates":[-82.015098,41.032947],"type":"Point"}
}
