{
  "type": "Feature",
  "properties": {
    "addr:full":"7009 Taylorsville Rd Dayton OH 45424",
    "addr:housenumber":"7009",
    "addr:postcode":"45424",
    "addr:street":"Taylorsville Rd",
    "iso:country":"US",
    "sg:address":"7009 Taylorsville Rd",
    "sg:city":"Dayton",
    "sg:classifiers":[
        {
            "category":"Sports & Exercise",
            "subcategory":"Gym",
            "type":"Entertainment"
        }
    ],
    "sg:phone":"+1 937 236 6050",
    "sg:postcode":"45424",
    "sg:province":"OH",
    "sg:tags":[
        "spa",
        "health"
    ],
    "wof:name":"Bella's Day Spa Inc",
    "wof:placetype":"venue"
},
  "geometry": {"coordinates":[-84.11065600000001,39.861138],"type":"Point"}
}