{
  "type": "Feature",
  "properties": {
    "addr:full": "4780 W 139th St Cleveland OH 44135",
    "addr:housenumber": "4780",
    "addr:postcode": "44135",
    "addr:street": "W 139Th St",
    "iso:country": "US",
    "sg:address": "4780 W 139th St",
    "sg:city": "Cleveland",
    "sg:classifiers": [
      {
        "category": "Manufacturing",
        "subcategory": "Metals",
        "type": "Manufacturing \u0026 Wholesale Goods"
      }
    ],
    "sg:phone": "+1 216 267 3554",
    "sg:postcode": "44135",
    "sg:province": "OH",
    "sg:tags": [
      "stamping"
    ],
    "wof:name": "Niagara Stamping Co",
    "wof:placetype": "venue"
  },
  "geometry": {"coordinates":[-81.789745,41.424804],"type":"Point"}
}
