{
  "type": "Feature",
  "properties": {
    "addr:full":"6664 Miller-Paul Rd Westerville OH 43082",
    "addr:housenumber":"6664",
    "addr:postcode":"43082",
    "addr:street":"Miller-Paul Rd",
    "iso:country":"US",
    "sg:address":"6664 Miller-Paul Rd",
    "sg:city":"Westerville",
    "sg:classifiers":[
        {
            "category":"Professional",
            "subcategory":"Management & Consulting",
            "type":"Services"
        }
    ],
    "sg:phone":"+1 614 855 7744",
    "sg:postcode":"43082",
    "sg:province":"OH",
    "wof:name":"Kenworthy Management Inc",
    "wof:placetype":"venue"
},
  "geometry": {"coordinates":[-82.821344,40.131341],"type":"Point"}
}