{
  "type": "Feature",
  "properties": {
    "addr:full":"7084 S Raccoon Rd Canfield OH 44406",
    "addr:housenumber":"7084",
    "addr:postcode":"44406",
    "addr:street":"S Raccoon Rd",
    "iso:country":"US",
    "sg:address":"7084 S Raccoon Rd",
    "sg:city":"Canfield",
    "sg:classifiers":[
        {
            "category":"Professional",
            "type":"Services"
        }
    ],
    "sg:phone":"+1 330 497 9289",
    "sg:postcode":"44406",
    "sg:province":"OH",
    "wof:name":"Tru Comfort Inc",
    "wof:placetype":"venue"
},
  "geometry": {"coordinates":[-80.73699000000001,41.013577],"type":"Point"}
}