{
  "type": "Feature",
  "properties": {
    "addr:full": "7323 Alkire Rd Galloway OH 43119",
    "addr:housenumber": "7323",
    "addr:postcode": "43119",
    "addr:street": "Alkire Rd",
    "iso:country": "US",
    "sg:address": "7323 Alkire Rd",
    "sg:city": "Galloway",
    "sg:classifiers": [
      {
        "category": "Professional",
        "type": "Services"
      }
    ],
    "sg:phone": "+1 614 878 4711",
    "sg:postcode": "43119",
    "sg:province": "OH",
    "wof:name": "Larry E Schilling",
    "wof:placetype": "venue"
  },
  "geometry": {"coordinates":[-83.187025,39.899725],"type":"Point"}
}
