{
  "type": "Feature",
  "properties": {
    "addr:full": "6520 Batavia Pike Cincinnati OH 45244",
    "addr:housenumber": "6520",
    "addr:postcode": "45244",
    "addr:street": "Batavia Pike",
    "iso:country": "US",
    "sg:address": "6520 Batavia Pike",
    "sg:city": "Cincinnati",
    "sg:classifiers": [
      {
        "category": "Recreation",
        "type": "Entertainment"
      }
    ],
    "sg:phone": "+1 513 271 4653",
    "sg:postcode": "45244",
    "sg:province": "OH",
    "sg:tags": [
      "range",
      "practice",
      "golf"
    ],
    "wof:name": "Anderson Twp Practice Range",
    "wof:placetype": "venue"
  },
  "geometry": {"coordinates":[-84.375635,39.122403],"type":"Point"}
}
