{
  "type": "Feature",
  "properties": {
    "addr:full":"4416 Tiffin Ave Sandusky OH 44870",
    "addr:housenumber":"4416",
    "addr:postcode":"44870",
    "addr:street":"Tiffin Ave",
    "iso:country":"US",
    "sg:address":"4416 Tiffin Ave",
    "sg:city":"Sandusky",
    "sg:classifiers":[
        {
            "category":"Autos & Motor Vehicles",
            "subcategory":"Motorcycle Sales",
            "type":"Retail Goods"
        }
    ],
    "sg:phone":"+1 419 624 8739",
    "sg:postcode":"44870",
    "sg:province":"OH",
    "wof:name":"M & M Cycle",
    "wof:placetype":"venue"
},
  "geometry": {"coordinates":[-82.76709700000001,41.4114],"type":"Point"}
}