{
  "type": "Feature",
  "properties": {
    "iso:country":"US",
    "sg:address":"9871 Waterstone Blvd",
    "sg:city":"Cincinnati",
    "sg:classifiers":[
        {
            "category":"Home & Garden",
            "subcategory":"Furniture",
            "type":"Retail Goods"
        }
    ],
    "sg:phone":"+1 513 683 0700",
    "sg:postcode":"45249",
    "sg:province":"OH",
    "sg:tags":[
        "accessory"
    ],
    "wof:name":"Bassett Furniture Direct",
    "wof:placetype":"venue"
},
  "geometry": {"coordinates":[-84.3056,39.292762],"type":"Point"}
}