{
  "type": "Feature",
  "properties": {
    "addr:full":"3651 Salem Ave Dayton OH 45406",
    "addr:housenumber":"3651",
    "addr:postcode":"45406",
    "addr:street":"Salem Ave",
    "iso:country":"US",
    "sg:address":"3651 Salem Ave",
    "sg:city":"Dayton",
    "sg:classifiers":[
        {
            "category":"Education",
            "subcategory":"School",
            "type":"Public Place"
        }
    ],
    "sg:phone":"+1 937 276 4552",
    "sg:postcode":"45406",
    "sg:province":"OH",
    "wof:name":"C Js Cntry Morning Pancake Hs",
    "wof:placetype":"venue"
},
  "geometry": {"coordinates":[-84.247231,39.79457],"type":"Point"}
}