{
  "type": "Feature",
  "properties": {
    "iso:country":"US",
    "sg:address":"701 Congress Park Dr",
    "sg:city":"Dayton",
    "sg:classifiers":[
        {
            "category":"Wholesale",
            "subcategory":"Construction Materials",
            "type":"Manufacturing & Wholesale Goods"
        }
    ],
    "sg:phone":"+1 937 435 7900",
    "sg:postcode":"45459",
    "sg:province":"OH",
    "sg:tags":[
        "marble"
    ],
    "wof:name":"Marble Dimensions Worldwide",
    "wof:placetype":"venue"
},
  "geometry": {"coordinates":[-84.179006,39.634489],"type":"Point"}
}