{
  "type": "Feature",
  "properties": {
    "iso:country":"US",
    "sg:address":"7 Willipie St",
    "sg:city":"Wapakoneta",
    "sg:classifiers":[
        {
            "category":"Travel",
            "subcategory":"Travel Agent",
            "type":"Entertainment"
        }
    ],
    "sg:phone":"+1 419 738 7337",
    "sg:postcode":"45895",
    "sg:province":"OH",
    "sg:tags":[
        "agency",
        "bureau"
    ],
    "wof:name":"Apollo Travel Agency",
    "wof:placetype":"venue"
},
  "geometry": {"coordinates":[-84.194057,40.570499],"type":"Point"}
}