{
  "type": "Feature",
  "properties": {
    "iso:country":"US",
    "sg:address":"40 Southmoor Cir NE",
    "sg:city":"Dayton",
    "sg:classifiers":[
        {
            "category":"Insurance",
            "subcategory":"Insurance Agent",
            "type":"Services"
        }
    ],
    "sg:phone":"+1 937 299 1001",
    "sg:postcode":"45429",
    "sg:province":"OH",
    "wof:name":"State Farm Insurance",
    "wof:placetype":"venue"
},
  "geometry": {"coordinates":[-84.168476,39.690464],"type":"Point"}
}