{
  "type": "Feature",
  "properties": {
    "addr:full":"409 Applegrove St NW Canton OH 44720",
    "addr:housenumber":"409",
    "addr:postcode":"44720",
    "addr:street":"Applegrove St Nw",
    "iso:country":"US",
    "sg:address":"409 Applegrove St NW",
    "sg:city":"Canton",
    "sg:classifiers":[
        {
            "category":"Freight",
            "type":"Transportation"
        }
    ],
    "sg:phone":"+1 330 494 8710",
    "sg:postcode":"44720",
    "sg:province":"OH",
    "sg:tags":[
        "storage",
        "household",
        "good",
        "moving",
        "local"
    ],
    "wof:name":"Wackerlys Moving & Storage",
    "wof:placetype":"venue"
},
  "geometry": {"coordinates":[-81.409671,40.890758],"type":"Point"}
}