{
  "type": "Feature",
  "properties": {
    "addr:full": "322 W Main St Montpelier OH 43543",
    "addr:housenumber": "322",
    "addr:postcode": "43543",
    "addr:street": "W Main St",
    "iso:country": "US",
    "sg:address": "322 W Main St",
    "sg:city": "Montpelier",
    "sg:classifiers": [
      {
        "category": "Personal",
        "subcategory": "Beauty Salon",
        "type": "Services"
      }
    ],
    "sg:phone": "+1 419 485 4968",
    "sg:postcode": "43543",
    "sg:province": "OH",
    "wof:name": "Hair Fashions",
    "wof:placetype": "venue"
  },
  "geometry": {"coordinates":[-84.610517,41.586388],"type":"Point"}
}
