{
  "type": "Feature",
  "properties": {
    "addr:full":"14550 Lorain Ave Cleveland OH 44111",
    "addr:housenumber":"14550",
    "addr:postcode":"44111",
    "addr:street":"Lorain Ave",
    "iso:country":"US",
    "sg:address":"14550 Lorain Ave",
    "sg:city":"Cleveland",
    "sg:classifiers":[
        {
            "category":"Autos & Motor Vehicles",
            "subcategory":"Automobile Sales",
            "type":"Retail Goods"
        }
    ],
    "sg:phone":"+1 216 251 4900",
    "sg:postcode":"44111",
    "sg:province":"OH",
    "sg:tags":[
        "car",
        "used",
        "dealer",
        "lot"
    ],
    "sg:website":"www.thedodgeboyz.com",
    "wof:name":"Ganley Dodge West Inc",
    "wof:placetype":"venue"
},
  "geometry": {"coordinates":[-81.795058,41.454214],"type":"Point"}
}