{
  "type": "Feature",
  "properties": {
    "addr:full": "1963 Easton St NW North Canton OH 44720",
    "addr:housenumber": "1963",
    "addr:postcode": "44720",
    "addr:street": "Easton St Nw",
    "iso:country": "US",
    "sg:address": "1963 Easton St NW",
    "sg:city": "North Canton",
    "sg:classifiers": [
      {
        "category": "Personal",
        "subcategory": "Beauty Salon",
        "type": "Services"
      }
    ],
    "sg:phone": "+1 330 244 8928",
    "sg:postcode": "44720",
    "sg:province": "OH",
    "wof:name": "Famous Hair",
    "wof:placetype": "venue"
  },
  "geometry": {"coordinates":[-81.367962,40.875139],"type":"Point"}
}
