{
  "type": "Feature",
  "properties": {
    "iso:country":"US",
    "sg:address":"7410 Defiance Pike",
    "sg:city":"Wayne",
    "sg:classifiers":[
        {
            "category":"Farming",
            "subcategory":"Farm",
            "type":"Manufacturing & Wholesale Goods"
        }
    ],
    "sg:phone":"+1 419 288 2220",
    "sg:postcode":"43466",
    "sg:province":"OH",
    "sg:tags":[
        "crop",
        "general"
    ],
    "wof:name":"Aurands Colonial Acres",
    "wof:placetype":"venue"
},
  "geometry": {"coordinates":[-83.542058,41.282527],"type":"Point"}
}