{
  "type": "Feature",
  "properties": {
    "iso:country":"US",
    "sg:address":"2840 Ebenezer Rd",
    "sg:city":"Cincinnati",
    "sg:classifiers":[
        {
            "category":"Building & Trades",
            "subcategory":"Plumbing",
            "type":"Services"
        }
    ],
    "sg:phone":"+1 513 451 6593",
    "sg:postcode":"45233",
    "sg:province":"OH",
    "sg:tags":[
        "contractor"
    ],
    "wof:name":"Jt Hathaway & Sons",
    "wof:placetype":"venue"
},
  "geometry": {"coordinates":[-84.65063000000001,39.140789],"type":"Point"}
}