{
  "type": "Feature",
  "properties": {
    "addr:full": "2840 Ebenezer Rd Cincinnati OH 45233",
    "addr:housenumber": "2840",
    "addr:postcode": "45233",
    "addr:street": "Ebenezer Rd",
    "iso:country": "US",
    "sg:address": "2840 Ebenezer Rd",
    "sg:city": "Cincinnati",
    "sg:classifiers": [
      {
        "category": "Building \u0026 Trades",
        "subcategory": "Plumbing",
        "type": "Services"
      }
    ],
    "sg:phone": "+1 513 451 6593",
    "sg:postcode": "45233",
    "sg:province": "OH",
    "sg:tags": [
      "contractor"
    ],
    "wof:name": "Jt Hathaway \u0026 Sons",
    "wof:placetype": "venue"
  },
  "geometry": {"coordinates":[-84.65063,39.140789],"type":"Point"}
}
