{
  "type": "Feature",
  "properties": {
    "addr:full":"6 Jupiter Ct Fairfield OH 45014",
    "addr:housenumber":"6",
    "addr:postcode":"45014",
    "addr:street":"Jupiter Ct",
    "iso:country":"US",
    "sg:address":"6 Jupiter Ct",
    "sg:city":"Fairfield",
    "sg:classifiers":[
        {
            "category":"Building & Trades",
            "subcategory":"Plumbing",
            "type":"Services"
        }
    ],
    "sg:phone":"+1 513 870 0702",
    "sg:postcode":"45014",
    "sg:province":"OH",
    "sg:tags":[
        "contractor"
    ],
    "wof:name":"Mikes Fire & Ice Hvac LLC",
    "wof:placetype":"venue"
},
  "geometry": {"coordinates":[-84.532403,39.324521],"type":"Point"}
}