{
  "type": "Feature",
  "properties": {
    "addr:full": "6016 N Summit St Toledo OH 43611",
    "addr:housenumber": "6016",
    "addr:postcode": "43611",
    "addr:street": "N Summit St",
    "iso:country": "US",
    "sg:address": "6016 N Summit St",
    "sg:city": "Toledo",
    "sg:classifiers": [
      {
        "category": "Professional",
        "type": "Services"
      }
    ],
    "sg:phone": "+1 419 729 1903",
    "sg:postcode": "43611",
    "sg:province": "OH",
    "sg:tags": [
      "establishment"
    ],
    "wof:name": "U Di It",
    "wof:placetype": "venue"
  },
  "geometry": {"coordinates":[-83.479474,41.727317],"type":"Point"}
}
