{
  "type": "Feature",
  "properties": {
    "addr:full": "1079 S Main St Centerville OH 45458",
    "addr:housenumber": "1079",
    "addr:postcode": "45458",
    "addr:street": "S Main St",
    "iso:country": "US",
    "sg:address": "1079 S Main St",
    "sg:city": "Centerville",
    "sg:classifiers": [
      {
        "category": "Shopping",
        "subcategory": "Gifts \u0026 Souvenirs",
        "type": "Retail Goods"
      }
    ],
    "sg:phone": "+1 937 432 9308",
    "sg:postcode": "45458",
    "sg:province": "OH",
    "sg:tags": [
      "shop"
    ],
    "wof:name": "Tuesday Morning Inc",
    "wof:placetype": "venue"
  },
  "geometry": {"coordinates":[-84.16051,39.610474],"type":"Point"}
}
