{
  "type": "Feature",
  "properties": {
    "iso:country":"US",
    "sg:address":"1430 Goodyear Blvd",
    "sg:city":"Akron",
    "sg:classifiers":[
        {
            "category":"Organizations",
            "subcategory":"Religious Organization",
            "type":"Services"
        }
    ],
    "sg:phone":"+1 330 784 7633",
    "sg:postcode":"44305",
    "sg:province":"OH",
    "sg:tags":[
        "church"
    ],
    "sg:website":"www.ghpcakron.org",
    "wof:name":"Goodyear Heights Presbyterian",
    "wof:placetype":"venue"
},
  "geometry": {"coordinates":[-81.471264,41.070351],"type":"Point"}
}