{
  "type": "Feature",
  "properties": {
    "addr:full": "1430 Goodyear Blvd Akron OH 44305",
    "addr:housenumber": "1430",
    "addr:postcode": "44305",
    "addr:street": "Goodyear Blvd",
    "iso:country": "US",
    "sg:address": "1430 Goodyear Blvd",
    "sg:city": "Akron",
    "sg:classifiers": [
      {
        "category": "Organizations",
        "subcategory": "Religious Organization",
        "type": "Services"
      }
    ],
    "sg:phone": "+1 330 784 7633",
    "sg:postcode": "44305",
    "sg:province": "OH",
    "sg:tags": [
      "church"
    ],
    "sg:website": "www.ghpcakron.org",
    "wof:name": "Goodyear Heights Presbyterian",
    "wof:placetype": "venue"
  },
  "geometry": {"coordinates":[-81.471264,41.070351],"type":"Point"}
}
