{
  "type": "Feature",
  "properties": {
    "addr:full":"8860 Aspenwood Ct Mentor OH 44060",
    "addr:housenumber":"8860",
    "addr:postcode":"44060",
    "addr:street":"Aspenwood Ct",
    "iso:country":"US",
    "sg:address":"8860 Aspenwood Ct",
    "sg:city":"Mentor",
    "sg:classifiers":[
        {
            "category":"Manufacturing",
            "subcategory":"Printing",
            "type":"Manufacturing & Wholesale Goods"
        }
    ],
    "sg:phone":"+1 440 255 7579",
    "sg:postcode":"44060",
    "sg:province":"OH",
    "sg:tags":[
        "printer"
    ],
    "wof:name":"D & L Printing",
    "wof:placetype":"venue"
},
  "geometry": {"coordinates":[-81.320761,41.704067],"type":"Point"}
}