{
  "type": "Feature",
  "properties": {
    "iso:country":"US",
    "sg:address":"4673 Mc Cormick Ln",
    "sg:city":"Fairfield",
    "sg:classifiers":[
        {
            "category":"Shopping",
            "type":"Retail Goods"
        }
    ],
    "sg:phone":"+1 513 856 9427",
    "sg:postcode":"45014",
    "sg:province":"OH",
    "sg:tags":[
        "hanging",
        "merchandise",
        "contractor"
    ],
    "wof:name":"W J Painting",
    "wof:placetype":"venue"
},
  "geometry": {"coordinates":[-84.570324,39.352219],"type":"Point"}
}