{
  "type": "Feature",
  "properties": {
    "addr:full": "8227 Brecksville Rd Brecksville OH 44141",
    "addr:housenumber": "8227",
    "addr:postcode": "44141",
    "addr:street": "Brecksville Rd",
    "iso:country": "US",
    "sg:address": "8227 Brecksville Rd",
    "sg:city": "Brecksville",
    "sg:classifiers": [
      {
        "category": "Insurance",
        "subcategory": "Insurance Agent",
        "type": "Services"
      }
    ],
    "sg:phone": "+1 440 838 1870",
    "sg:postcode": "44141",
    "sg:province": "OH",
    "sg:tags": [
      "broker"
    ],
    "wof:name": "Jacobs \u0026 Associates Agcy",
    "wof:placetype": "venue"
  },
  "geometry": {"coordinates":[-81.627535,41.339365],"type":"Point"}
}
