{
  "type": "Feature",
  "properties": {
    "addr:full":"320 W Exchange St Akron OH 44302",
    "addr:housenumber":"320",
    "addr:postcode":"44302",
    "addr:street":"W Exchange St",
    "iso:country":"US",
    "sg:address":"320 W Exchange St",
    "sg:city":"Akron",
    "sg:classifiers":[
        {
            "category":"Health Services",
            "subcategory":"Doctor",
            "type":"Services"
        }
    ],
    "sg:phone":"+1 330 535 4428",
    "sg:postcode":"44302",
    "sg:province":"OH",
    "sg:tags":[
        "physician",
        "surgeon"
    ],
    "wof:name":"Center For Urologic Health LLC",
    "wof:placetype":"venue"
},
  "geometry": {"coordinates":[-81.53107199999999,41.081059],"type":"Point"}
}