{
  "type": "Feature",
  "properties": {
    "iso:country":"US",
    "sg:address":"2636 Cambria Mill Rd",
    "sg:city":"Granville",
    "sg:classifiers":[
        {
            "category":"Banks & Credit Unions",
            "subcategory":"Investment Brokerage",
            "type":"Services"
        }
    ],
    "sg:phone":"+1 740 587 4884",
    "sg:postcode":"43023",
    "sg:province":"OH",
    "sg:tags":[
        "consultant",
        "planning",
        "financial"
    ],
    "wof:name":"Welsh Hills Financial Svc",
    "wof:placetype":"venue"
},
  "geometry": {"coordinates":[-82.48745700000001,40.107425],"type":"Point"}
}