{
  "type": "Feature",
  "properties": {
    "addr:full": "4409 Far Hills Ave Dayton OH 45429",
    "addr:housenumber": "4409",
    "addr:postcode": "45429",
    "addr:street": "Far Hills Ave",
    "iso:country": "US",
    "sg:address": "4409 Far Hills Ave",
    "sg:city": "Dayton",
    "sg:classifiers": [
      {
        "category": "Personal",
        "subcategory": "Beauty Salon",
        "type": "Services"
      }
    ],
    "sg:phone": "+1 937 643 0861",
    "sg:postcode": "45429",
    "sg:province": "OH",
    "wof:name": "Dimitri Salon",
    "wof:placetype": "venue"
  },
  "geometry": {"coordinates":[-84.167271,39.683056],"type":"Point"}
}
