{
  "type": "Feature",
  "properties": {
    "iso:country":"US",
    "sg:address":"300 West Ave",
    "sg:city":"Tallmadge",
    "sg:classifiers":[
        {
            "category":"Autos & Motor Vehicles",
            "subcategory":"Automobile Sales",
            "type":"Retail Goods"
        }
    ],
    "sg:phone":"+1 330 633 3234",
    "sg:postcode":"44278",
    "sg:province":"OH",
    "sg:tags":[
        "car",
        "dealer"
    ],
    "sg:website":"www.tricitynissan.com",
    "wof:name":"Tri City Nissan",
    "wof:placetype":"venue"
},
  "geometry": {"coordinates":[-81.454526,41.101733],"type":"Point"}
}