{
  "type": "Feature",
  "properties": {
    "addr:full": "300 West Ave Tallmadge OH 44278",
    "addr:housenumber": "300",
    "addr:postcode": "44278",
    "addr:street": "West Ave",
    "iso:country": "US",
    "sg:address": "300 West Ave",
    "sg:city": "Tallmadge",
    "sg:classifiers": [
      {
        "category": "Autos \u0026 Motor Vehicles",
        "subcategory": "Automobile Sales",
        "type": "Retail Goods"
      }
    ],
    "sg:phone": "+1 330 633 3234",
    "sg:postcode": "44278",
    "sg:province": "OH",
    "sg:tags": [
      "car",
      "dealer"
    ],
    "sg:website": "www.tricitynissan.com",
    "wof:name": "Tri City Nissan",
    "wof:placetype": "venue"
  },
  "geometry": {"coordinates":[-81.454526,41.101733],"type":"Point"}
}
