{
  "type": "Feature",
  "properties": {
    "iso:country":"US",
    "sg:address":"81 Essex Ct",
    "sg:city":"Hamilton",
    "sg:classifiers":[
        {
            "category":"Building & Trades",
            "subcategory":"Construction",
            "type":"Services"
        }
    ],
    "sg:phone":"+1 513 896 1102",
    "sg:postcode":"45013",
    "sg:province":"IN",
    "sg:tags":[
        "house"
    ],
    "wof:name":"Construction Technology",
    "wof:placetype":"venue"
},
  "geometry": {"coordinates":[-84.61117,39.409488],"type":"Point"}
}