{
  "type": "Feature",
  "properties": {
    "addr:full": "81 Essex Ct Hamilton IN 45013",
    "addr:housenumber": "81",
    "addr:postcode": "45013",
    "addr:street": "Essex Ct",
    "iso:country": "US",
    "sg:address": "81 Essex Ct",
    "sg:city": "Hamilton",
    "sg:classifiers": [
      {
        "category": "Building \u0026 Trades",
        "subcategory": "Construction",
        "type": "Services"
      }
    ],
    "sg:phone": "+1 513 896 1102",
    "sg:postcode": "45013",
    "sg:province": "IN",
    "sg:tags": [
      "house"
    ],
    "wof:name": "Construction Technology",
    "wof:placetype": "venue"
  },
  "geometry": {"coordinates":[-84.61117,39.409488],"type":"Point"}
}
