{
  "type": "Feature",
  "properties": {
    "iso:country":"US",
    "sg:address":"2240 Richard St",
    "sg:city":"Dayton",
    "sg:classifiers":[
        {
            "category":"Manufacturing",
            "subcategory":"Metals",
            "type":"Manufacturing & Wholesale Goods"
        }
    ],
    "sg:phone":"+1 937 252 6143",
    "sg:postcode":"45403",
    "sg:province":"OH",
    "sg:tags":[
        "product",
        "mfg",
        "plastic"
    ],
    "wof:name":"PSI",
    "wof:placetype":"venue"
},
  "geometry": {"coordinates":[-84.154768,39.755004],"type":"Point"}
}