{
  "type": "Feature",
  "properties": {
    "iso:country":"US",
    "sg:address":"8465 Tyler Blvd",
    "sg:city":"Mentor",
    "sg:classifiers":[
        {
            "category":"Autos & Motor Vehicles",
            "subcategory":"Automobile Sales",
            "type":"Retail Goods"
        }
    ],
    "sg:phone":"+1 440 205 6500",
    "sg:postcode":"44060",
    "sg:province":"OH",
    "sg:tags":[
        "car",
        "dealer"
    ],
    "sg:website":"www.driveclassic.com",
    "wof:name":"Classic Mazda",
    "wof:placetype":"venue"
},
  "geometry": {"coordinates":[-81.333806,41.685468],"type":"Point"}
}