{
  "type": "Feature",
  "properties": {
    "addr:full": "766 Parsons Ave Columbus OH 43206",
    "addr:housenumber": "766",
    "addr:postcode": "43206",
    "addr:street": "Parsons Ave",
    "iso:country": "US",
    "sg:address": "766 Parsons Ave",
    "sg:city": "Columbus",
    "sg:classifiers": [
      {
        "category": "Food \u0026 Beverages",
        "subcategory": "Liquor \u0026 Beverages",
        "type": "Retail Goods"
      }
    ],
    "sg:phone": "+1 614 449 9615",
    "sg:postcode": "43206",
    "sg:province": "OH",
    "sg:tags": [
      "alcoholic"
    ],
    "wof:name": "Elza Inc",
    "wof:placetype": "venue"
  },
  "geometry": {"coordinates":[-82.98262,39.948654],"type":"Point"}
}
