{
  "type": "Feature",
  "properties": {
    "iso:country":"US",
    "sg:address":"766 Parsons Ave",
    "sg:city":"Columbus",
    "sg:classifiers":[
        {
            "category":"Food & Beverages",
            "subcategory":"Liquor & Beverages",
            "type":"Retail Goods"
        }
    ],
    "sg:phone":"+1 614 449 9615",
    "sg:postcode":"43206",
    "sg:province":"OH",
    "sg:tags":[
        "alcoholic"
    ],
    "wof:name":"Elza Inc",
    "wof:placetype":"venue"
},
  "geometry": {"coordinates":[-82.98262,39.948654],"type":"Point"}
}