{
  "type": "Feature",
  "properties": {
    "addr:full":"729 E Main St Trotwood OH 45426",
    "addr:housenumber":"729",
    "addr:postcode":"45426",
    "addr:street":"E Main St",
    "iso:country":"US",
    "sg:address":"729 E Main St",
    "sg:city":"Trotwood",
    "sg:classifiers":[
        {
            "category":"Personal",
            "subcategory":"Barber",
            "type":"Services"
        }
    ],
    "sg:phone":"+1 937 837 3131",
    "sg:postcode":"45426",
    "sg:province":"OH",
    "wof:name":"Headliners Barbershop",
    "wof:placetype":"venue"
},
  "geometry": {"coordinates":[-84.296278,39.797564],"type":"Point"}
}