{
  "type": "Feature",
  "properties": {
    "addr:full":"124 1st Ave Tiffin OH 44883",
    "addr:housenumber":"124",
    "addr:postcode":"44883",
    "addr:street":"1St Ave",
    "iso:country":"US",
    "sg:address":"124 1st Ave",
    "sg:city":"Tiffin",
    "sg:classifiers":[
        {
            "category":"Shopping",
            "subcategory":"Gifts & Souvenirs",
            "type":"Retail Goods"
        }
    ],
    "sg:phone":"+1 419 447 9244",
    "sg:postcode":"44883",
    "sg:province":"OH",
    "wof:name":"Green Room",
    "wof:placetype":"venue"
},
  "geometry": {"coordinates":[-83.181567,41.127976],"type":"Point"}
}