{
  "type": "Feature",
  "properties": {
    "addr:full":"2611 Kemper Ln Cincinnati OH 45206",
    "addr:housenumber":"2611",
    "addr:postcode":"45206",
    "addr:street":"Kemper Ln",
    "iso:country":"US",
    "sg:address":"2611 Kemper Ln",
    "sg:city":"Cincinnati",
    "sg:classifiers":[
        {
            "category":"Wholesale",
            "subcategory":"Electrical",
            "type":"Manufacturing & Wholesale Goods"
        }
    ],
    "sg:phone":"+1 513 221 7111",
    "sg:postcode":"45206",
    "sg:province":"OH",
    "sg:tags":[
        "fire",
        "alarm",
        "system"
    ],
    "wof:name":"Rice Electrical Sales Inc",
    "wof:placetype":"venue"
},
  "geometry": {"coordinates":[-84.487652,39.128813],"type":"Point"}
}