{
  "type": "Feature",
  "properties": {
    "addr:full":"6106 Forest Ave Cleveland OH 44129",
    "addr:housenumber":"6106",
    "addr:postcode":"44129",
    "addr:street":"Forest Ave",
    "iso:country":"US",
    "sg:address":"6106 Forest Ave",
    "sg:city":"Cleveland",
    "sg:classifiers":[
        {
            "category":"Insurance",
            "subcategory":"Insurance Agent",
            "type":"Services"
        }
    ],
    "sg:phone":"+1 440 884 0427",
    "sg:postcode":"44129",
    "sg:province":"OH",
    "wof:name":"Auping Insurance",
    "wof:placetype":"venue"
},
  "geometry": {"coordinates":[-81.73008900000001,41.408157],"type":"Point"}
}