{
  "type": "Feature",
  "properties": {
    "iso:country":"US",
    "sg:address":"9075 Boundaries Rd",
    "sg:city":"Thornville",
    "sg:classifiers":[
        {
            "category":"Manufacturing",
            "subcategory":"Signs",
            "type":"Manufacturing & Wholesale Goods"
        }
    ],
    "sg:phone":"+1 740 246 4843",
    "sg:postcode":"43076",
    "sg:province":"OH",
    "wof:name":"Lakes End",
    "wof:placetype":"venue"
},
  "geometry": {"coordinates":[-82.40808800000001,39.921833],"type":"Point"}
}