{
  "type": "Feature",
  "properties": {
    "addr:full": "15408 Triskett Rd Cleveland OH 44111",
    "addr:housenumber": "15408",
    "addr:postcode": "44111",
    "addr:street": "Triskett Rd",
    "iso:country": "US",
    "sg:address": "15408 Triskett Rd",
    "sg:city": "Cleveland",
    "sg:classifiers": [
      {
        "category": "Retail",
        "subcategory": "Funeral Services",
        "type": "Services"
      }
    ],
    "sg:phone": "+1 216 251 7300",
    "sg:postcode": "44111",
    "sg:province": "OH",
    "sg:tags": [
      "director"
    ],
    "wof:name": "Donlon Funeral Home",
    "wof:placetype": "venue"
  },
  "geometry": {"coordinates":[-81.804476,41.453765],"type":"Point"}
}
