{
  "type": "Feature",
  "properties": {
    "iso:country":"US",
    "sg:address":"15408 Triskett Rd",
    "sg:city":"Cleveland",
    "sg:classifiers":[
        {
            "category":"Retail",
            "subcategory":"Funeral Services",
            "type":"Services"
        }
    ],
    "sg:phone":"+1 216 251 7300",
    "sg:postcode":"44111",
    "sg:province":"OH",
    "sg:tags":[
        "director"
    ],
    "wof:name":"Donlon Funeral Home",
    "wof:placetype":"venue"
},
  "geometry": {"coordinates":[-81.80447599999999,41.453765],"type":"Point"}
}