{
  "type": "Feature",
  "properties": {
    "addr:full": "248 McKinley Ave Campbell OH 44405",
    "addr:housenumber": "248",
    "addr:postcode": "44405",
    "addr:street": "Mckinley Ave",
    "iso:country": "US",
    "sg:address": "248 McKinley Ave",
    "sg:city": "Campbell",
    "sg:classifiers": [
      {
        "category": "Autos \u0026 Motor Vehicles",
        "subcategory": "Automobile Sales",
        "type": "Retail Goods"
      }
    ],
    "sg:phone": "+1 330 746 5015",
    "sg:postcode": "44405",
    "sg:province": "OH",
    "sg:tags": [
      "used"
    ],
    "wof:name": "L \u0026 T Auto Sales",
    "wof:placetype": "venue"
  },
  "geometry": {"coordinates":[-80.607056,41.089907],"type":"Point"}
}
