{
  "type": "Feature",
  "properties": {
    "addr:full":"1265 N Stange Rd Graytown OH 43432",
    "addr:housenumber":"1265",
    "addr:postcode":"43432",
    "addr:street":"N Stange Rd",
    "iso:country":"US",
    "sg:address":"1265 N Stange Rd",
    "sg:city":"Graytown",
    "sg:classifiers":[
        {
            "category":"Building & Trades",
            "subcategory":"Construction",
            "type":"Services"
        }
    ],
    "sg:phone":"+1 419 862 2000",
    "sg:postcode":"43432",
    "sg:province":"OH",
    "sg:tags":[
        "hanging",
        "floor",
        "laying",
        "contract",
        "contractor"
    ],
    "wof:name":"Knieriem Painting and Dctg",
    "wof:placetype":"venue"
},
  "geometry": {"coordinates":[-83.241326,41.534362],"type":"Point"}
}