{
  "type": "Feature",
  "properties": {
    "addr:full":"86 N Main St Chagrin Falls OH 44022",
    "addr:housenumber":"86",
    "addr:postcode":"44022",
    "addr:street":"N Main St",
    "iso:country":"US",
    "sg:address":"86 N Main St",
    "sg:city":"Chagrin Falls",
    "sg:classifiers":[
        {
            "category":"Travel",
            "subcategory":"Travel Agent",
            "type":"Entertainment"
        }
    ],
    "sg:phone":"+1 440 247 1570",
    "sg:postcode":"44022",
    "sg:province":"OH",
    "sg:tags":[
        "agency",
        "bureau"
    ],
    "wof:name":"Travel Mgmt",
    "wof:placetype":"venue"
},
  "geometry": {"coordinates":[-81.391801,41.431145],"type":"Point"}
}