{
  "type": "Feature",
  "properties": {
    "addr:full":"1539 Johnson Plank Rd Cortland OH 44410",
    "addr:housenumber":"1539",
    "addr:postcode":"44410",
    "addr:street":"Johnson Plank Rd",
    "iso:country":"US",
    "sg:address":"1539 Johnson Plank Rd",
    "sg:city":"Cortland",
    "sg:classifiers":[
        {
            "category":"Shopping",
            "type":"Retail Goods"
        }
    ],
    "sg:phone":"+1 330 637 5002",
    "sg:postcode":"44410",
    "sg:province":"OH",
    "sg:tags":[
        "awning",
        "canopy"
    ],
    "wof:name":"Eric's Custom Awnings",
    "wof:placetype":"venue"
},
  "geometry": {"coordinates":[-80.77277100000001,41.293674],"type":"Point"}
}