{
  "type": "Feature",
  "properties": {
    "addr:full":"4217 Rocky River Dr Cleveland OH 44135",
    "addr:housenumber":"4217",
    "addr:postcode":"44135",
    "addr:street":"Rocky River Dr",
    "iso:country":"US",
    "sg:address":"4217 Rocky River Dr",
    "sg:city":"Cleveland",
    "sg:classifiers":[
        {
            "category":"Retail",
            "subcategory":"Auto Rental",
            "type":"Services"
        }
    ],
    "sg:phone":"+1 216 251 4045",
    "sg:postcode":"44135",
    "sg:province":"OH",
    "sg:tags":[
        "renting",
        "truck",
        "leasing"
    ],
    "wof:name":"U-Haul Co",
    "wof:placetype":"venue"
},
  "geometry": {"coordinates":[-81.81995999999999,41.439197],"type":"Point"}
}