{
  "type": "Feature",
  "properties": {
    "addr:full": "3051 Rodenbeck Dr Dayton OH 45432",
    "addr:housenumber": "3051",
    "addr:postcode": "45432",
    "addr:street": "Rodenbeck Dr",
    "iso:country": "US",
    "sg:address": "3051 Rodenbeck Dr",
    "sg:city": "Dayton",
    "sg:classifiers": [
      {
        "category": "Education",
        "subcategory": "Special Training",
        "type": "Public Place"
      }
    ],
    "sg:phone": "+1 937 429 5010",
    "sg:postcode": "45432",
    "sg:province": "OH",
    "sg:tags": [
      "instruction",
      "driving"
    ],
    "wof:name": "Wheeler Driving School",
    "wof:placetype": "venue"
  },
  "geometry": {"coordinates":[-84.052157,39.727082],"type":"Point"}
}
