{
  "type": "Feature",
  "properties": {
    "addr:full": "4526 Torrington Ave Cleveland OH 44134",
    "addr:housenumber": "4526",
    "addr:postcode": "44134",
    "addr:street": "Torrington Ave",
    "iso:country": "US",
    "sg:address": "4526 Torrington Ave",
    "sg:city": "Cleveland",
    "sg:classifiers": [
      {
        "category": "Manufacturing",
        "subcategory": "Printing",
        "type": "Manufacturing \u0026 Wholesale Goods"
      }
    ],
    "sg:phone": "+1 216 335 9980",
    "sg:postcode": "44134",
    "sg:province": "OH",
    "sg:tags": [
      "engraving"
    ],
    "wof:name": "M \u0026 M Engraving",
    "wof:placetype": "venue"
  },
  "geometry": {"coordinates":[-81.716332,41.410495],"type":"Point"}
}
