{
  "type": "Feature",
  "properties": {
    "iso:country":"US",
    "sg:address":"4526 Torrington Ave",
    "sg:city":"Cleveland",
    "sg:classifiers":[
        {
            "category":"Manufacturing",
            "subcategory":"Printing",
            "type":"Manufacturing & Wholesale Goods"
        }
    ],
    "sg:phone":"+1 216 335 9980",
    "sg:postcode":"44134",
    "sg:province":"OH",
    "sg:tags":[
        "engraving"
    ],
    "wof:name":"M & M Engraving",
    "wof:placetype":"venue"
},
  "geometry": {"coordinates":[-81.71633199999999,41.410495],"type":"Point"}
}