{
  "type": "Feature",
  "properties": {
    "addr:full": "8389 Mayfield Rd Chesterland OH 44026",
    "addr:housenumber": "8389",
    "addr:postcode": "44026",
    "addr:street": "Mayfield Rd",
    "iso:country": "US",
    "sg:address": "8389 Mayfield Rd",
    "sg:city": "Chesterland",
    "sg:classifiers": [
      {
        "category": "Sports \u0026 Exercise",
        "subcategory": "Gym",
        "type": "Entertainment"
      }
    ],
    "sg:phone": "+1 440 729 3355",
    "sg:postcode": "44026",
    "sg:province": "OH",
    "sg:tags": [
      "club",
      "health",
      "studio",
      "gymnasium"
    ],
    "wof:name": "Curves",
    "wof:placetype": "venue"
  },
  "geometry": {"coordinates":[-81.342975,41.522136],"type":"Point"}
}
