{
  "type": "Feature",
  "properties": {
    "addr:full": "228 S Scranton St Ravenna OH 44266",
    "addr:housenumber": "228",
    "addr:postcode": "44266",
    "addr:street": "S Scranton St",
    "iso:country": "US",
    "sg:address": "228 S Scranton St",
    "sg:city": "Ravenna",
    "sg:classifiers": [
      {
        "category": "Education",
        "subcategory": "School",
        "type": "Public Place"
      }
    ],
    "sg:phone": "+1 330 296 3849",
    "sg:postcode": "44266",
    "sg:province": "OH",
    "sg:tags": [
      "middle"
    ],
    "wof:name": "Brown Middle School",
    "wof:placetype": "venue"
  },
  "geometry": {"coordinates":[-81.263677,41.156471],"type":"Point"}
}
