{
  "type": "Feature",
  "properties": {
    "iso:country":"US",
    "sg:address":"35010 Chardon Rd",
    "sg:city":"Willoughby",
    "sg:classifiers":[
        {
            "category":"Mining & Drilling",
            "type":"Manufacturing & Wholesale Goods"
        }
    ],
    "sg:phone":"+1 440 954 5022",
    "sg:postcode":"44094",
    "sg:province":"OH",
    "sg:tags":[
        "development",
        "gas",
        "oil",
        "exploration"
    ],
    "wof:name":"Quantum Energy LLC",
    "wof:placetype":"venue"
},
  "geometry": {"coordinates":[-81.432472,41.588452],"type":"Point"}
}