{
  "type": "Feature",
  "properties": {
    "addr:full":"848 Rogers St Toledo OH 43605",
    "addr:housenumber":"848",
    "addr:postcode":"43605",
    "addr:street":"Rogers St",
    "iso:country":"US",
    "sg:address":"848 Rogers St",
    "sg:city":"Toledo",
    "sg:classifiers":[
        {
            "category":"Freight",
            "type":"Transportation"
        }
    ],
    "sg:phone":"+1 419 698 0494",
    "sg:postcode":"43605",
    "sg:province":"OH",
    "sg:tags":[
        "operator",
        "local",
        "trucking"
    ],
    "wof:name":"Micks Delivery & Light Hauling",
    "wof:placetype":"venue"
},
  "geometry": {"coordinates":[-83.519246,41.632966],"type":"Point"}
}