{
  "type": "Feature",
  "properties": {
    "iso:country":"US",
    "sg:address":"945 S Main St",
    "sg:city":"Celina",
    "sg:classifiers":[
        {
            "category":"Freight",
            "type":"Transportation"
        }
    ],
    "sg:phone":"+1 419 586 4862",
    "sg:postcode":"45822",
    "sg:province":"OH",
    "sg:tags":[
        "warehouse"
    ],
    "wof:name":"Star Warehousing",
    "wof:placetype":"venue"
},
  "geometry": {"coordinates":[-84.573809,40.540577],"type":"Point"}
}