{
  "type": "Feature",
  "properties": {
    "addr:full": "9111 Sharrott Rd Youngstown OH 44514",
    "addr:housenumber": "9111",
    "addr:postcode": "44514",
    "addr:street": "Sharrott Rd",
    "iso:country": "US",
    "sg:address": "9111 Sharrott Rd",
    "sg:city": "Youngstown",
    "sg:classifiers": [
      {
        "category": "Health Services",
        "subcategory": "Nursing And Care Facility",
        "type": "Services"
      }
    ],
    "sg:phone": "+1 330 726 7110",
    "sg:postcode": "44514",
    "sg:province": "OH",
    "sg:tags": [
      "home",
      "retirement",
      "community"
    ],
    "wof:name": "Shepherd Of The Valley-Poland",
    "wof:placetype": "venue"
  },
  "geometry": {"coordinates":[-80.669115,40.986303],"type":"Point"}
}
