{
  "type": "Feature",
  "properties": {
    "iso:country":"US",
    "sg:address":"4148 W 56th St",
    "sg:city":"Cleveland",
    "sg:classifiers":[
        {
            "category":"Organizations",
            "subcategory":"Religious Organization",
            "type":"Services"
        }
    ],
    "sg:phone":"+1 216 651 8744",
    "sg:postcode":"44144",
    "sg:province":"OH",
    "sg:tags":[
        "church"
    ],
    "wof:name":"Holy Resurrection Orthodox Chr",
    "wof:placetype":"venue"
},
  "geometry": {"coordinates":[-81.72462899999999,41.445215],"type":"Point"}
}