{
  "type": "Feature",
  "properties": {
    "iso:country":"US",
    "sg:address":"89 Morgan Sisters Rd",
    "sg:city":"Patriot",
    "sg:classifiers":[
        {
            "category":"Freight",
            "type":"Transportation"
        }
    ],
    "sg:phone":"+1 740 379 2643",
    "sg:postcode":"45658",
    "sg:province":"OH",
    "sg:tags":[
        "operator",
        "local",
        "trucking"
    ],
    "wof:name":"William J Lester",
    "wof:placetype":"venue"
},
  "geometry": {"coordinates":[-82.484116,38.802229],"type":"Point"}
}