{
  "type": "Feature",
  "properties": {
    "iso:country":"US",
    "sg:address":"3582 Denlinger Rd",
    "sg:city":"Dayton",
    "sg:classifiers":[
        {
            "category":"Real Estate",
            "subcategory":"Real Estate Agent",
            "type":"Services"
        }
    ],
    "sg:phone":"+1 937 837 3779",
    "sg:postcode":"45426",
    "sg:province":"OH",
    "wof:name":"Joseph Baldwin Jr",
    "wof:placetype":"venue"
},
  "geometry": {"coordinates":[-84.273354,39.800061],"type":"Point"}
}