{
  "type": "Feature",
  "properties": {
    "iso:country":"US",
    "sg:address":"2186 Clifton Way",
    "sg:city":"Avon",
    "sg:classifiers":[
        {
            "category":"Building & Trades",
            "subcategory":"Construction",
            "type":"Services"
        }
    ],
    "sg:phone":"+1 440 934 6262",
    "sg:postcode":"44011",
    "sg:province":"OH",
    "sg:tags":[
        "contractor"
    ],
    "wof:name":"Lake Pointe Construction",
    "wof:placetype":"venue"
},
  "geometry": {"coordinates":[-82.028857,41.457094],"type":"Point"}
}