{
  "type": "Feature",
  "properties": {
    "iso:country":"US",
    "sg:address":"36 W Gay St",
    "sg:city":"Columbus",
    "sg:classifiers":[
        {
            "category":"Professional",
            "subcategory":"Management & Consulting",
            "type":"Services"
        }
    ],
    "sg:phone":"+1 614 228 7146",
    "sg:postcode":"43215",
    "sg:province":"OH",
    "sg:tags":[
        "consultant",
        "resource",
        "human"
    ],
    "wof:name":"Mercer Human Resource Cnsltng",
    "wof:placetype":"venue"
},
  "geometry": {"coordinates":[-83.00251299999999,39.963506],"type":"Point"}
}