{
  "type": "Feature",
  "properties": {
    "addr:full": "36 W Gay St Columbus OH 43215",
    "addr:housenumber": "36",
    "addr:postcode": "43215",
    "addr:street": "W Gay St",
    "iso:country": "US",
    "sg:address": "36 W Gay St",
    "sg:city": "Columbus",
    "sg:classifiers": [
      {
        "category": "Professional",
        "subcategory": "Management \u0026 Consulting",
        "type": "Services"
      }
    ],
    "sg:phone": "+1 614 228 7146",
    "sg:postcode": "43215",
    "sg:province": "OH",
    "sg:tags": [
      "consultant",
      "resource",
      "human"
    ],
    "wof:name": "Mercer Human Resource Cnsltng",
    "wof:placetype": "venue"
  },
  "geometry": {"coordinates":[-83.002513,39.963506],"type":"Point"}
}
