{
  "type": "Feature",
  "properties": {
    "addr:full": "1710 Cooper Foster Park Rd W Lorain OH 44053",
    "addr:housenumber": "1710",
    "addr:postcode": "44053",
    "addr:street": "Cooper Foster Park Rd W",
    "iso:country": "US",
    "sg:address": "1710 Cooper Foster Park Rd W",
    "sg:city": "Lorain",
    "sg:classifiers": [
      {
        "category": "Health Services",
        "subcategory": "Optometrist",
        "type": "Services"
      }
    ],
    "sg:phone": "+1 440 960 2020",
    "sg:postcode": "44053",
    "sg:province": "OH",
    "wof:name": "David J Sterna OD",
    "wof:placetype": "venue"
  },
  "geometry": {"coordinates":[-82.2596,41.407067],"type":"Point"}
}
