{
  "type": "Feature",
  "properties": {
    "addr:full": "3001 Goda Ave Cincinnati OH 45211",
    "addr:housenumber": "3001",
    "addr:postcode": "45211",
    "addr:street": "Goda Ave",
    "iso:country": "US",
    "sg:address": "3001 Goda Ave",
    "sg:city": "Cincinnati",
    "sg:classifiers": [
      {
        "category": "Building \u0026 Trades",
        "subcategory": "Construction",
        "type": "Services"
      }
    ],
    "sg:phone": "+1 513 481 0054",
    "sg:postcode": "45211",
    "sg:province": "OH",
    "sg:tags": [
      "new",
      "remodeling",
      "commercial"
    ],
    "wof:name": "Middendorf-Niehoff Contractors",
    "wof:placetype": "venue"
  },
  "geometry": {"coordinates":[-84.596502,39.166213],"type":"Point"}
}
