{
  "type": "Feature",
  "properties": {
    "addr:full":"5720 Westbourne Ave Columbus OH 43213",
    "addr:housenumber":"5720",
    "addr:postcode":"43213",
    "addr:street":"Westbourne Ave",
    "iso:country":"US",
    "sg:address":"5720 Westbourne Ave",
    "sg:city":"Columbus",
    "sg:classifiers":[
        {
            "category":"Building & Trades",
            "subcategory":"Construction",
            "type":"Services"
        }
    ],
    "sg:phone":"+1 614 856 9850",
    "sg:postcode":"43213",
    "sg:province":"OH",
    "sg:tags":[
        "general",
        "contractor"
    ],
    "wof:name":"Mid Ohio Contracting & Mntnc",
    "wof:placetype":"venue"
},
  "geometry": {"coordinates":[-82.849434,39.984446],"type":"Point"}
}