{
  "type": "Feature",
  "properties": {
    "addr:full": "1400 E Main St Greenville OH 45331",
    "addr:housenumber": "1400",
    "addr:postcode": "45331",
    "addr:street": "E Main St",
    "iso:country": "US",
    "sg:address": "1400 E Main St",
    "sg:city": "Greenville",
    "sg:classifiers": [
      {
        "category": "Organizations",
        "subcategory": "Religious Organization",
        "type": "Services"
      }
    ],
    "sg:phone": "+1 937 547 0337",
    "sg:postcode": "45331",
    "sg:province": "OH",
    "sg:tags": [
      "church"
    ],
    "sg:website": "www.greenvilletwc.com",
    "wof:name": "Trinity Wesleyan Church",
    "wof:placetype": "venue"
  },
  "geometry": {"coordinates":[-84.61356,40.111739],"type":"Point"}
}
