{
  "type": "Feature",
  "properties": {
    "iso:country":"US",
    "sg:address":"1400 E Main St",
    "sg:city":"Greenville",
    "sg:classifiers":[
        {
            "category":"Organizations",
            "subcategory":"Religious Organization",
            "type":"Services"
        }
    ],
    "sg:phone":"+1 937 547 0337",
    "sg:postcode":"45331",
    "sg:province":"OH",
    "sg:tags":[
        "church"
    ],
    "sg:website":"www.greenvilletwc.com",
    "wof:name":"Trinity Wesleyan Church",
    "wof:placetype":"venue"
},
  "geometry": {"coordinates":[-84.61356000000001,40.111739],"type":"Point"}
}