{
  "type": "Feature",
  "properties": {
    "addr:full": "3 Summit Park Dr Cleveland OH 44131",
    "addr:housenumber": "3",
    "addr:postcode": "44131",
    "addr:street": "Summit Park Dr",
    "iso:country": "US",
    "sg:address": "3 Summit Park Dr",
    "sg:city": "Cleveland",
    "sg:classifiers": [
      {
        "category": "Shopping",
        "subcategory": "Computers \u0026 Home Electronics",
        "type": "Retail Goods"
      }
    ],
    "sg:phone": "+1 216 606 3000",
    "sg:postcode": "44131",
    "sg:province": "OH",
    "sg:tags": [
      "software"
    ],
    "wof:name": "Siebel Systems Inc",
    "wof:placetype": "venue"
  },
  "geometry": {"coordinates":[-81.655851,41.39571],"type":"Point"}
}
