{
  "type": "Feature",
  "properties": {
    "addr:full": "421 E Miami St De Graff OH 43318",
    "addr:housenumber": "421",
    "addr:postcode": "43318",
    "addr:street": "E Miami St",
    "iso:country": "US",
    "sg:address": "421 E Miami St",
    "sg:city": "De Graff",
    "sg:phone": "+1 937 585 4890",
    "sg:postcode": "43318",
    "sg:province": "OH",
    "sg:tags": [
      "hog",
      "farm",
      "cash",
      "grain",
      "or",
      "feedlot"
    ],
    "wof:name": "Ray Vondenhuevel",
    "wof:placetype": "venue"
  },
  "geometry": {"coordinates":[-83.908923,40.311442],"type":"Point"}
}
