{
  "type": "Feature",
  "properties": {
    "addr:full": "717 Huron Ave Dayton OH 45402",
    "addr:housenumber": "717",
    "addr:postcode": "45402",
    "addr:street": "Huron Ave",
    "iso:country": "US",
    "sg:address": "717 Huron Ave",
    "sg:city": "Dayton",
    "sg:classifiers": [
      {
        "category": "Organizations",
        "subcategory": "Religious Organization",
        "type": "Services"
      }
    ],
    "sg:phone": "+1 937 268 0323",
    "sg:postcode": "45402",
    "sg:province": "OH",
    "sg:tags": [
      "church"
    ],
    "wof:name": "Mt Carmel United Holy Church",
    "wof:placetype": "venue"
  },
  "geometry": {"coordinates":[-84.242706,39.763506],"type":"Point"}
}
