{
  "type": "Feature",
  "properties": {
    "addr:full":"9188 E Berrysville Rd Hillsboro OH 45133",
    "addr:housenumber":"9188",
    "addr:postcode":"45133",
    "addr:street":"E Berrysville Rd",
    "iso:country":"US",
    "sg:address":"9188 E Berrysville Rd",
    "sg:city":"Hillsboro",
    "sg:classifiers":[
        {
            "category":"Real Estate",
            "subcategory":"Real Estate Operator",
            "type":"Services"
        }
    ],
    "sg:phone":"+1 740 393 9783",
    "sg:postcode":"45133",
    "sg:province":"OH",
    "sg:tags":[
        "property",
        "lessor"
    ],
    "wof:name":"Gary B Reno Farm",
    "wof:placetype":"venue"
},
  "geometry": {"coordinates":[-83.552128,39.12802],"type":"Point"}
}