{
  "type": "Feature",
  "properties": {
    "iso:country":"US",
    "sg:address":"91 Old Rainer Rd",
    "sg:city":"Roseville",
    "sg:classifiers":[
        {
            "category":"Personal",
            "subcategory":"Beauty Salon",
            "type":"Services"
        }
    ],
    "sg:phone":"+1 740 697 7590",
    "sg:postcode":"43777",
    "sg:province":"OH",
    "wof:name":"Pearl's Beauty Shop",
    "wof:placetype":"venue"
},
  "geometry": {"coordinates":[-82.092615,39.801027],"type":"Point"}
}