{
  "type": "Feature",
  "properties": {
    "iso:country":"US",
    "sg:address":"650 Porter Ave",
    "sg:city":"Campbell",
    "sg:classifiers":[
        {
            "category":"Retail",
            "subcategory":"Portrait Studio",
            "type":"Services"
        }
    ],
    "sg:phone":"+1 330 755 0618",
    "sg:postcode":"44405",
    "sg:province":"OH",
    "sg:tags":[
        "photographer"
    ],
    "wof:name":"Reflections Studio",
    "wof:placetype":"venue"
},
  "geometry": {"coordinates":[-80.585219,41.08144],"type":"Point"}
}