{
  "type": "Feature",
  "properties": {
    "addr:full": "20 W Grace St Cleveland OH 44146",
    "addr:housenumber": "20",
    "addr:postcode": "44146",
    "addr:street": "W Grace St",
    "iso:country": "US",
    "sg:address": "20 W Grace St",
    "sg:city": "Cleveland",
    "sg:classifiers": [
      {
        "category": "Social Services",
        "subcategory": "Child Care",
        "type": "Services"
      }
    ],
    "sg:phone": "+1 440 439 6667",
    "sg:postcode": "44146",
    "sg:province": "OH",
    "wof:name": "All My Children Daycare Inc",
    "wof:placetype": "venue"
  },
  "geometry": {"coordinates":[-81.54053,41.394942],"type":"Point"}
}
