{
  "type": "Feature",
  "properties": {
    "addr:full": "340 Washington St Washingtonville OH 44490",
    "addr:housenumber": "340",
    "addr:postcode": "44490",
    "addr:street": "Washington St",
    "iso:country": "US",
    "sg:address": "340 Washington St",
    "sg:city": "Washingtonville",
    "sg:classifiers": [
      {
        "category": "Home \u0026 Garden",
        "subcategory": "Furniture",
        "type": "Retail Goods"
      }
    ],
    "sg:phone": "+1 330 427 0401",
    "sg:postcode": "44490",
    "sg:province": "OH",
    "wof:name": "Ww Moving \u0026 Furniture Inc",
    "wof:placetype": "venue"
  },
  "geometry": {"coordinates":[-80.760646,40.898154],"type":"Point"}
}
