{
  "type": "Feature",
  "properties": {
    "iso:country":"US",
    "sg:address":"340 Washington St",
    "sg:city":"Washingtonville",
    "sg:classifiers":[
        {
            "category":"Home & Garden",
            "subcategory":"Furniture",
            "type":"Retail Goods"
        }
    ],
    "sg:phone":"+1 330 427 0401",
    "sg:postcode":"44490",
    "sg:province":"OH",
    "wof:name":"Ww Moving & Furniture Inc",
    "wof:placetype":"venue"
},
  "geometry": {"coordinates":[-80.76064599999999,40.898154],"type":"Point"}
}