{
  "type": "Feature",
  "properties": {
    "iso:country":"US",
    "sg:address":"3917 Colerain Ave",
    "sg:city":"Cincinnati",
    "sg:classifiers":[
        {
            "category":"Wholesale",
            "subcategory":"Electrical",
            "type":"Manufacturing & Wholesale Goods"
        }
    ],
    "sg:phone":"+1 513 591 0290",
    "sg:postcode":"45223",
    "sg:province":"OH",
    "sg:tags":[
        "lighting",
        "fixture",
        "electric",
        "equipment"
    ],
    "wof:name":"Havco Lighting",
    "wof:placetype":"venue"
},
  "geometry": {"coordinates":[-84.54411,39.157622],"type":"Point"}
}