{
  "type": "Feature",
  "properties": {
    "addr:full": "3917 Colerain Ave Cincinnati OH 45223",
    "addr:housenumber": "3917",
    "addr:postcode": "45223",
    "addr:street": "Colerain Ave",
    "iso:country": "US",
    "sg:address": "3917 Colerain Ave",
    "sg:city": "Cincinnati",
    "sg:classifiers": [
      {
        "category": "Wholesale",
        "subcategory": "Electrical",
        "type": "Manufacturing \u0026 Wholesale Goods"
      }
    ],
    "sg:phone": "+1 513 591 0290",
    "sg:postcode": "45223",
    "sg:province": "OH",
    "sg:tags": [
      "lighting",
      "fixture",
      "electric",
      "equipment"
    ],
    "wof:name": "Havco Lighting",
    "wof:placetype": "venue"
  },
  "geometry": {"coordinates":[-84.54411,39.157622],"type":"Point"}
}
