{
  "type": "Feature",
  "properties": {
    "addr:full":"1627 Claremont Ave Ashland OH 44805",
    "addr:housenumber":"1627",
    "addr:postcode":"44805",
    "addr:street":"Claremont Ave",
    "iso:country":"US",
    "sg:address":"1627 Claremont Ave",
    "sg:city":"Ashland",
    "sg:classifiers":[
        {
            "category":"Shopping",
            "type":"Retail Goods"
        }
    ],
    "sg:phone":"+1 419 289 0076",
    "sg:postcode":"44805",
    "sg:province":"OH",
    "sg:tags":[
        "telephone",
        "cellular"
    ],
    "wof:name":"Radio Shack",
    "wof:placetype":"venue"
},
  "geometry": {"coordinates":[-82.339298,40.852553],"type":"Point"}
}