{
  "type": "Feature",
  "properties": {
    "iso:country":"US",
    "sg:address":"3722 Jessup Rd",
    "sg:city":"Cincinnati",
    "sg:classifiers":[
        {
            "category":"Wholesale",
            "subcategory":"Vending Machines",
            "type":"Manufacturing & Wholesale Goods"
        }
    ],
    "sg:phone":"+1 513 741 9202",
    "sg:postcode":"45247",
    "sg:province":"OH",
    "sg:tags":[
        "operator"
    ],
    "wof:name":"Top Gun Vending LLC",
    "wof:placetype":"venue"
},
  "geometry": {"coordinates":[-84.605324,39.199013],"type":"Point"}
}