{
  "type": "Feature",
  "properties": {
    "addr:full":"1313 Ridge Rd NE Lancaster OH 43130",
    "addr:housenumber":"1313",
    "addr:postcode":"43130",
    "addr:street":"Ridge Rd Ne",
    "iso:country":"US",
    "sg:address":"1313 Ridge Rd NE",
    "sg:city":"Lancaster",
    "sg:classifiers":[
        {
            "category":"Manufacturing",
            "subcategory":"Metals",
            "type":"Manufacturing & Wholesale Goods"
        }
    ],
    "sg:phone":"+1 740 687 0944",
    "sg:postcode":"43130",
    "sg:province":"OH",
    "sg:tags":[
        "product",
        "fabricated",
        "mfg"
    ],
    "wof:name":"Heath Company",
    "wof:placetype":"venue"
},
  "geometry": {"coordinates":[-82.573143,39.739134],"type":"Point"}
}