{
  "type": "Feature",
  "properties": {
    "addr:full":"6390 Erie Ave N Canal Fulton OH 44614",
    "addr:housenumber":"6390",
    "addr:postcode":"44614",
    "addr:street":"Erie Ave N",
    "iso:country":"US",
    "sg:address":"6390 Erie Ave N",
    "sg:city":"Canal Fulton",
    "sg:classifiers":[
        {
            "category":"Farming",
            "subcategory":"Nursery",
            "type":"Manufacturing & Wholesale Goods"
        }
    ],
    "sg:phone":"+1 330 854 2637",
    "sg:postcode":"44614",
    "sg:province":"OH",
    "sg:tags":[
        "greenhouse"
    ],
    "wof:name":"Manda's Plant Farm",
    "wof:placetype":"venue"
},
  "geometry": {"coordinates":[-81.58206800000001,40.877862],"type":"Point"}
}