{
  "type": "Feature",
  "properties": {
    "iso:country":"US",
    "sg:address":"5323 Foley Rd",
    "sg:city":"Cincinnati",
    "sg:classifiers":[
        {
            "category":"Insurance",
            "subcategory":"Insurance Agent",
            "type":"Services"
        }
    ],
    "sg:phone":"+1 513 922 7100",
    "sg:postcode":"45238",
    "sg:province":"OH",
    "wof:name":"Bob Schaefer Insurance",
    "wof:placetype":"venue"
},
  "geometry": {"coordinates":[-84.61905400000001,39.104133],"type":"Point"}
}