{
  "type": "Feature",
  "properties": {
    "addr:full": "2405 N Columbus St Lancaster OH 43130",
    "addr:housenumber": "2405",
    "addr:postcode": "43130",
    "addr:street": "N Columbus St",
    "iso:country": "US",
    "sg:address": "2405 N Columbus St",
    "sg:city": "Lancaster",
    "sg:classifiers": [
      {
        "category": "Health Services",
        "subcategory": "Clinic",
        "type": "Services"
      }
    ],
    "sg:phone": "+1 740 689 9770",
    "sg:postcode": "43130",
    "sg:province": "OH",
    "sg:tags": [
      "specialty",
      "outpatient"
    ],
    "wof:name": "Pain Care Center The",
    "wof:placetype": "venue"
  },
  "geometry": {"coordinates":[-82.631824,39.740598],"type":"Point"}
}
