{
  "type": "Feature",
  "properties": {
    "addr:full": "4756 Elliott Rd Hilliard OH 43002",
    "addr:housenumber": "4756",
    "addr:postcode": "43002",
    "addr:street": "Elliott Rd",
    "iso:country": "US",
    "sg:address": "4756 Elliott Rd",
    "sg:city": "Hilliard",
    "sg:classifiers": [
      {
        "category": "Building \u0026 Trades",
        "subcategory": "Construction",
        "type": "Services"
      }
    ],
    "sg:phone": "+1 614 771 2709",
    "sg:postcode": "43002",
    "sg:province": "OH",
    "sg:tags": [
      "planning",
      "remodeling",
      "kitchen"
    ],
    "wof:name": "Kitchen Tune-Up",
    "wof:placetype": "venue"
  },
  "geometry": {"coordinates":[-83.200667,40.051322],"type":"Point"}
}
