{
  "type": "Feature",
  "properties": {
    "addr:full": "605 E Montford Ave Ada OH 45810",
    "addr:housenumber": "605",
    "addr:postcode": "45810",
    "addr:street": "E Montford Ave",
    "iso:country": "US",
    "sg:address": "605 E Montford Ave",
    "sg:city": "Ada",
    "sg:classifiers": [
      {
        "category": "Manufacturing",
        "subcategory": "Metals",
        "type": "Manufacturing \u0026 Wholesale Goods"
      }
    ],
    "sg:phone": "+1 419 634 3125",
    "sg:postcode": "45810",
    "sg:province": "OH",
    "sg:tags": [
      "stamping"
    ],
    "sg:website": "www.adastampings.com",
    "wof:name": "Ohio Stampings LLC",
    "wof:placetype": "venue"
  },
  "geometry": {"coordinates":[-83.813081,40.773316],"type":"Point"}
}
