{
  "type": "Feature",
  "properties": {
    "iso:country":"US",
    "sg:address":"402 S Main St",
    "sg:city":"Franklin",
    "sg:classifiers":[
        {
            "category":"Retail",
            "subcategory":"Repair Shop",
            "type":"Services"
        }
    ],
    "sg:phone":"+1 937 743 0713",
    "sg:postcode":"45005",
    "sg:province":"OH",
    "sg:tags":[
        "equipment",
        "electronic",
        "supply"
    ],
    "wof:name":"Active Electronics-Dane Billig",
    "wof:placetype":"venue"
},
  "geometry": {"coordinates":[-84.30463,39.55925],"type":"Point"}
}