{
  "type": "Feature",
  "properties": {
    "iso:country":"US",
    "sg:address":"1214 Pinnacle Dr",
    "sg:city":"Columbus",
    "sg:classifiers":[
        {
            "category":"Building & Trades",
            "subcategory":"Plumbing",
            "type":"Services"
        }
    ],
    "sg:phone":"+1 614 235 6655",
    "sg:postcode":"43204",
    "sg:province":"OH",
    "sg:tags":[
        "plumbing",
        "contractor"
    ],
    "wof:name":"Guaranteed Plumbing",
    "wof:placetype":"venue"
},
  "geometry": {"coordinates":[-83.08629999999999,39.928639],"type":"Point"}
}