{
  "type": "Feature",
  "properties": {
    "addr:full": "101 S Main St Clyde OH 43410",
    "addr:housenumber": "101",
    "addr:postcode": "43410",
    "addr:street": "S Main St",
    "iso:country": "US",
    "sg:address": "101 S Main St",
    "sg:city": "Clyde",
    "sg:classifiers": [
      {
        "category": "Shopping",
        "subcategory": "Hobbies, Toys, \u0026 Games",
        "type": "Retail Goods"
      }
    ],
    "sg:phone": "+1 419 547 1441",
    "sg:postcode": "43410",
    "sg:province": "OH",
    "sg:tags": [
      "craft",
      "supply"
    ],
    "wof:name": "Scrap'n Tree",
    "wof:placetype": "venue"
  },
  "geometry": {"coordinates":[-82.974853,41.305312],"type":"Point"}
}
