{
  "type": "Feature",
  "properties": {
    "iso:country":"US",
    "sg:address":"13812 Othello Ave",
    "sg:city":"Cleveland",
    "sg:classifiers":[
        {
            "category":"Shopping",
            "subcategory":"Hobbies, Toys, & Games",
            "type":"Retail Goods"
        }
    ],
    "sg:phone":"+1 216 268 0237",
    "sg:postcode":"44110",
    "sg:province":"OH",
    "wof:name":"B J Catering & Craft",
    "wof:placetype":"venue"
},
  "geometry": {"coordinates":[-81.58651999999999,41.56599],"type":"Point"}
}