{
  "type": "Feature",
  "properties": {
    "addr:full": "293 Hopewell Dr Powell OH 43065",
    "addr:housenumber": "293",
    "addr:postcode": "43065",
    "addr:street": "Hopewell Dr",
    "iso:country": "US",
    "sg:address": "293 Hopewell Dr",
    "sg:city": "Powell",
    "sg:classifiers": [
      {
        "category": "Manufacturing",
        "subcategory": "Printing",
        "type": "Manufacturing \u0026 Wholesale Goods"
      }
    ],
    "sg:phone": "+1 614 848 3232",
    "sg:postcode": "43065",
    "sg:province": "OH",
    "sg:tags": [
      "journal",
      "publication"
    ],
    "wof:name": "North American Fastener Inst",
    "wof:placetype": "venue"
  },
  "geometry": {"coordinates":[-83.065904,40.162864],"type":"Point"}
}
