{
  "type": "Feature",
  "properties": {
    "addr:full":"1006 Summit Dr Middletown OH 45042",
    "addr:housenumber":"1006",
    "addr:postcode":"45042",
    "addr:street":"Summit Dr",
    "iso:country":"US",
    "sg:address":"1006 Summit Dr",
    "sg:city":"Middletown",
    "sg:classifiers":[
        {
            "category":"Insurance",
            "subcategory":"Insurance Agent",
            "type":"Services"
        }
    ],
    "sg:phone":"+1 513 422 5914",
    "sg:postcode":"45042",
    "sg:province":"OH",
    "wof:name":"Nlh Insurance",
    "wof:placetype":"venue"
},
  "geometry": {"coordinates":[-84.351798,39.52411],"type":"Point"}
}