{
  "type": "Feature",
  "properties": {
    "addr:full":"3830 Kelley Ave Cleveland OH 44114",
    "addr:housenumber":"3830",
    "addr:postcode":"44114",
    "addr:street":"Kelley Ave",
    "iso:country":"US",
    "sg:address":"3830 Kelley Ave",
    "sg:city":"Cleveland",
    "sg:classifiers":[
        {
            "category":"Manufacturing",
            "subcategory":"Printing",
            "type":"Manufacturing & Wholesale Goods"
        }
    ],
    "sg:phone":"+1 216 881 5300",
    "sg:postcode":"44114",
    "sg:province":"OH",
    "wof:name":"Pubco Corp",
    "wof:placetype":"venue"
},
  "geometry": {"coordinates":[-81.66045099999999,41.508398],"type":"Point"}
}