{
  "type": "Feature",
  "properties": {
    "iso:country":"US",
    "sg:address":"4921 N Arbor Woods Ct",
    "sg:city":"Cincinnati",
    "sg:classifiers":[
        {
            "category":"Real Estate",
            "subcategory":"Real Estate Services",
            "type":"Services"
        }
    ],
    "sg:phone":"+1 513 598 5968",
    "sg:postcode":"45248",
    "sg:province":"OH",
    "sg:tags":[
        "management",
        "condominium"
    ],
    "wof:name":"Arbor Woods Condminium Sales",
    "wof:placetype":"venue"
},
  "geometry": {"coordinates":[-84.641265,39.178217],"type":"Point"}
}