{
  "type": "Feature",
  "properties": {
    "addr:full":"7875 Montgomery Rd Cincinnati OH 45236",
    "addr:housenumber":"7875",
    "addr:postcode":"45236",
    "addr:street":"Montgomery Rd",
    "iso:country":"US",
    "sg:address":"7875 Montgomery Rd",
    "sg:city":"Cincinnati",
    "sg:classifiers":[
        {
            "category":"Home & Garden",
            "subcategory":"Home Furnishings",
            "type":"Retail Goods"
        }
    ],
    "sg:phone":"+1 513 793 1131",
    "sg:postcode":"45236",
    "sg:province":"OH",
    "wof:name":"Pottery Barn",
    "wof:placetype":"venue"
},
  "geometry": {"coordinates":[-84.37692199999999,39.200242],"type":"Point"}
}