{
  "type": "Feature",
  "properties": {
    "addr:full": "1115 Portage Lakes Dr Akron OH 44319",
    "addr:housenumber": "1115",
    "addr:postcode": "44319",
    "addr:street": "Portage Lakes Dr",
    "iso:country": "US",
    "sg:address": "1115 Portage Lakes Dr",
    "sg:city": "Akron",
    "sg:classifiers": [
      {
        "category": "Restaurant",
        "type": "Food \u0026 Drink"
      }
    ],
    "sg:phone": "+1 330 245 1911",
    "sg:postcode": "44319",
    "sg:province": "OH",
    "sg:tags": [
      "parlor",
      "ice",
      "cream"
    ],
    "wof:name": "Ice Cream Park",
    "wof:placetype": "venue"
  },
  "geometry": {"coordinates":[-81.555562,41.005788],"type":"Point"}
}
