{
  "type": "Feature",
  "properties": {
    "iso:country":"US",
    "sg:address":"80 W Bowery St",
    "sg:city":"Akron",
    "sg:classifiers":[
        {
            "category":"Professional",
            "subcategory":"Secretarial Services",
            "type":"Services"
        }
    ],
    "sg:phone":"+1 330 374 0761",
    "sg:postcode":"44308",
    "sg:province":"OH",
    "sg:tags":[
        "transcription",
        "medical"
    ],
    "wof:name":"Logical Medical Services",
    "wof:placetype":"venue"
},
  "geometry": {"coordinates":[-81.52142000000001,41.081167],"type":"Point"}
}