{
  "type": "Feature",
  "properties": {
    "iso:country":"US",
    "sg:address":"10235 Spartan Dr",
    "sg:city":"Cincinnati",
    "sg:classifiers":[
        {
            "category":"Retail",
            "subcategory":"Laundry & Dry Cleaning",
            "type":"Services"
        }
    ],
    "sg:phone":"+1 513 772 0030",
    "sg:postcode":"45215",
    "sg:province":"OH",
    "sg:tags":[
        "cleaners",
        "rug",
        "carpet"
    ],
    "wof:name":"Weickert's Carpet Dry Cleaning",
    "wof:placetype":"venue"
},
  "geometry": {"coordinates":[-84.449837,39.254361],"type":"Point"}
}