{
  "type": "Feature",
  "properties": {
    "addr:full": "4928 Eastern Ave Cincinnati OH 45208",
    "addr:housenumber": "4928",
    "addr:postcode": "45208",
    "addr:street": "Eastern Ave",
    "iso:country": "US",
    "sg:address": "4928 Eastern Ave",
    "sg:city": "Cincinnati",
    "sg:classifiers": [
      {
        "category": "Organizations",
        "subcategory": "Religious Organization",
        "type": "Services"
      }
    ],
    "sg:phone": "+1 513 321 5117",
    "sg:postcode": "45208",
    "sg:province": "OH",
    "sg:tags": [
      "church"
    ],
    "wof:name": "Ark By The River",
    "wof:placetype": "venue"
  },
  "geometry": {"coordinates":[-84.413345,39.124987],"type":"Point"}
}
