{
  "type": "Feature",
  "properties": {
    "addr:full": "10665 Co Rd C Bryan OH 43506",
    "addr:housenumber": "10665",
    "addr:postcode": "43506",
    "addr:street": "Co Rd",
    "iso:country": "US",
    "sg:address": "10665 Co Rd C",
    "sg:city": "Bryan",
    "sg:classifiers": [
      {
        "category": "Farming",
        "subcategory": "Livestock Farm",
        "type": "Manufacturing \u0026 Wholesale Goods"
      }
    ],
    "sg:phone": "+1 419 636 5473",
    "sg:postcode": "43506",
    "sg:province": "OH",
    "sg:tags": [
      "hog",
      "wheat",
      "corn",
      "soybean",
      "or",
      "feedlot"
    ],
    "wof:name": "Wirth Farms",
    "wof:placetype": "venue"
  },
  "geometry": {"coordinates":[-84.619077,41.456002],"type":"Point"}
}
