{
  "type": "Feature",
  "properties": {
    "iso:country":"US",
    "sg:address":"15882 Chardon-Windsor Rd",
    "sg:city":"Huntsburg",
    "sg:classifiers":[
        {
            "category":"Manufacturing",
            "subcategory":"Printing",
            "type":"Manufacturing & Wholesale Goods"
        }
    ],
    "sg:phone":"+1 440 636 5369",
    "sg:postcode":"44046",
    "sg:province":"OH",
    "sg:tags":[
        "commercial",
        "lithographic"
    ],
    "wof:name":"Huntsburg Printing Company",
    "wof:placetype":"venue"
},
  "geometry": {"coordinates":[-81.071606,41.562559],"type":"Point"}
}