{
  "type": "Feature",
  "properties": {
    "iso:country":"US",
    "sg:address":"30184 Euclid Ave",
    "sg:city":"Wickliffe",
    "sg:classifiers":[
        {
            "category":"Health Services",
            "subcategory":"Optometrist",
            "type":"Services"
        }
    ],
    "sg:phone":"+1 440 943 3663",
    "sg:postcode":"44092",
    "sg:province":"OH",
    "wof:name":"Harris & Marsh Inc",
    "wof:placetype":"venue"
},
  "geometry": {"coordinates":[-81.460245,41.616487],"type":"Point"}
}