{
  "type": "Feature",
  "properties": {
    "iso:country":"US",
    "sg:address":"53 S Miami St",
    "sg:city":"West Milton",
    "sg:classifiers":[
        {
            "category":"Home & Garden",
            "subcategory":"Furniture",
            "type":"Retail Goods"
        }
    ],
    "sg:phone":"+1 937 698 0137",
    "sg:postcode":"45383",
    "sg:province":"OH",
    "sg:tags":[
        "cabinet"
    ],
    "wof:name":"Creative Cabinet Concepts",
    "wof:placetype":"venue"
},
  "geometry": {"coordinates":[-84.327735,39.961966],"type":"Point"}
}