{
  "type": "Feature",
  "properties": {
    "addr:full": "130 W Columbus Ave Bellefontaine OH 43311",
    "addr:housenumber": "130",
    "addr:postcode": "43311",
    "addr:street": "W Columbus Ave",
    "iso:country": "US",
    "sg:address": "130 W Columbus Ave",
    "sg:city": "Bellefontaine",
    "sg:classifiers": [
      {
        "category": "Shopping",
        "subcategory": "Bicycles \u0026 Sporting Goods",
        "type": "Retail Goods"
      }
    ],
    "sg:phone": "+1 937 593 4420",
    "sg:postcode": "43311",
    "sg:province": "OH",
    "wof:name": "Sports Plus Inc",
    "wof:placetype": "venue"
  },
  "geometry": {"coordinates":[-83.761587,40.361345],"type":"Point"}
}
