{
  "type": "Feature",
  "properties": {
    "addr:full":"13311 Shady Ln Chesterland OH 44026",
    "addr:housenumber":"13311",
    "addr:postcode":"44026",
    "addr:street":"Shady Ln",
    "iso:country":"US",
    "sg:address":"13311 Shady Ln",
    "sg:city":"Chesterland",
    "sg:classifiers":[
        {
            "category":"Shopping",
            "subcategory":"Computers & Home Electronics",
            "type":"Retail Goods"
        }
    ],
    "sg:phone":"+1 440 729 2843",
    "sg:postcode":"44026",
    "sg:province":"OH",
    "wof:name":"Tulip Tree Creative & Computer",
    "wof:placetype":"venue"
},
  "geometry": {"coordinates":[-81.34967899999999,41.50313],"type":"Point"}
}