{
  "type": "Feature",
  "properties": {
    "addr:full":"17 W Main St Tipp City OH 45371",
    "addr:housenumber":"17",
    "addr:postcode":"45371",
    "addr:street":"W Main St",
    "iso:country":"US",
    "sg:address":"17 W Main St",
    "sg:city":"Tipp City",
    "sg:classifiers":[
        {
            "category":"Professional",
            "subcategory":"Lawyer & Legal Services",
            "type":"Services"
        }
    ],
    "sg:phone":"+1 937 667 6684",
    "sg:postcode":"45371",
    "sg:province":"OH",
    "sg:tags":[
        "attorney"
    ],
    "wof:name":"Thomas R Cochran",
    "wof:placetype":"venue"
},
  "geometry": {"coordinates":[-84.171492,39.961301],"type":"Point"}
}