{
  "type": "Feature",
  "properties": {
    "iso:country":"US",
    "sg:address":"38 W Main St",
    "sg:city":"Madison",
    "sg:classifiers":[
        {
            "category":"Professional",
            "subcategory":"Accounting & Tax Preparation",
            "type":"Services"
        }
    ],
    "sg:phone":"+1 440 428 1801",
    "sg:postcode":"44057",
    "sg:province":"OH",
    "sg:tags":[
        "accountant"
    ],
    "wof:name":"Knapp Ransom & Assoc",
    "wof:placetype":"venue"
},
  "geometry": {"coordinates":[-81.04768799999999,41.771655],"type":"Point"}
}