{
  "type": "Feature",
  "properties": {
    "addr:full":"4580 Columbus-Lancaster Rd NW Carroll OH 43112",
    "addr:housenumber":"4580",
    "addr:postcode":"43112",
    "addr:street":"Columbus-Lancaster Rd Nw",
    "iso:country":"US",
    "sg:address":"4580 Columbus-Lancaster Rd NW",
    "sg:city":"Carroll",
    "sg:classifiers":[
        {
            "category":"Professional",
            "type":"Services"
        }
    ],
    "sg:phone":"+1 740 756 4699",
    "sg:postcode":"43112",
    "sg:province":"OH",
    "wof:name":"Kokosing Materials Inc 514",
    "wof:placetype":"venue"
},
  "geometry": {"coordinates":[-82.686432,39.776675],"type":"Point"}
}