{
  "type": "Feature",
  "properties": {
    "addr:full": "525 W Riverview Ave Dayton OH 45405",
    "addr:housenumber": "525",
    "addr:postcode": "45405",
    "addr:street": "W Riverview Ave",
    "iso:country": "US",
    "sg:address": "525 W Riverview Ave",
    "sg:city": "Dayton",
    "sg:classifiers": [
      {
        "category": "Restaurant",
        "type": "Food \u0026 Drink"
      }
    ],
    "sg:phone": "+1 937 224 3080",
    "sg:postcode": "45405",
    "sg:province": "OH",
    "sg:tags": [
      "banquet",
      "rooms"
    ],
    "wof:name": "Belmont Park Hospitality Corp",
    "wof:placetype": "venue"
  },
  "geometry": {"coordinates":[-84.202982,39.764052],"type":"Point"}
}
