{
  "type": "Feature",
  "properties": {
    "addr:full": "1045 Dearbaugh Ave Wapakoneta OH 45895",
    "addr:housenumber": "1045",
    "addr:postcode": "45895",
    "addr:street": "Dearbaugh Ave",
    "iso:country": "US",
    "sg:address": "1045 Dearbaugh Ave",
    "sg:city": "Wapakoneta",
    "sg:classifiers": [
      {
        "category": "Education",
        "subcategory": "School",
        "type": "Public Place"
      }
    ],
    "sg:phone": "+1 419 738 9224",
    "sg:postcode": "45895",
    "sg:province": "OH",
    "sg:tags": [
      "educational",
      "administrative"
    ],
    "wof:name": "West Cntl Ohio Special Educatn",
    "wof:placetype": "venue"
  },
  "geometry": {"coordinates":[-84.207552,40.559367],"type":"Point"}
}
