{
  "type": "Feature",
  "properties": {
    "addr:full":"1494 S Arlington St Akron OH 44306",
    "addr:housenumber":"1494",
    "addr:postcode":"44306",
    "addr:street":"S Arlington St",
    "iso:country":"US",
    "sg:address":"1494 S Arlington St",
    "sg:city":"Akron",
    "sg:classifiers":[
        {
            "category":"Banks & Credit Unions",
            "subcategory":"Bank",
            "type":"Services"
        }
    ],
    "sg:phone":"+1 330 785 4640",
    "sg:postcode":"44306",
    "sg:province":"OH",
    "sg:tags":[
        "depository",
        "banking",
        "check",
        "cashing"
    ],
    "wof:name":"Check Into Cash",
    "wof:placetype":"venue"
},
  "geometry": {"coordinates":[-81.49149199999999,41.030518],"type":"Point"}
}