{
  "type": "Feature",
  "properties": {
    "addr:full": "3477 Co Rd 605 Sunbury OH 43074",
    "addr:housenumber": "3477;605",
    "addr:postcode": "sunbury;43074",
    "addr:street": "Co Rd",
    "iso:country": "US",
    "sg:address": "3477 Co Rd 605",
    "sg:city": "Sunbury",
    "sg:classifiers": [
      {
        "category": "Freight",
        "type": "Transportation"
      },
      {
        "category": "Professional",
        "subcategory": "Advertising",
        "type": "Services"
      }
    ],
    "sg:phone": "+1 740 965 3600",
    "sg:postcode": "43074",
    "sg:province": "OH",
    "sg:tags": [
      "plumbing",
      "distribution",
      "special"
    ],
    "wof:name": "Carter Distribution Center",
    "wof:placetype": "venue"
  },
  "geometry": {"coordinates":[-82.788794,40.249925],"type":"Point"}
}
