{
  "type": "Feature",
  "properties": {
    "addr:full": "26 S Railroad St New London OH 44851",
    "addr:housenumber": "26",
    "addr:postcode": "44851",
    "addr:street": "S Railroad St",
    "iso:country": "US",
    "sg:address": "26 S Railroad St",
    "sg:city": "New London",
    "sg:classifiers": [
      {
        "category": "Autos \u0026 Motor Vehicles",
        "subcategory": "Auto Supplies",
        "type": "Retail Goods"
      }
    ],
    "sg:phone": "+1 419 929 3931",
    "sg:postcode": "44851",
    "sg:province": "OH",
    "sg:tags": [
      "tire"
    ],
    "wof:name": "KIDD Tire \u0026 Auto LLC",
    "wof:placetype": "venue"
  },
  "geometry": {"coordinates":[-82.398453,41.086037],"type":"Point"}
}
