{
  "type": "Feature",
  "properties": {
    "iso:country":"US",
    "sg:address":"12062 Marwood Ln",
    "sg:city":"Cincinnati",
    "sg:classifiers":[
        {
            "category":"Local Transit",
            "type":"Transportation"
        }
    ],
    "sg:phone":"+1 513 671 4403",
    "sg:postcode":"45246",
    "sg:province":"OH",
    "sg:tags":[
        "passenger"
    ],
    "wof:name":"RAS Limousine",
    "wof:placetype":"venue"
},
  "geometry": {"coordinates":[-84.449524,39.296576],"type":"Point"}
}