{
  "type": "Feature",
  "properties": {
    "addr:full":"1400 Polaris Pkwy Columbus OH 43240",
    "addr:housenumber":"1400",
    "addr:postcode":"43240",
    "addr:street":"Polaris Pkwy",
    "iso:country":"US",
    "sg:address":"1400 Polaris Pkwy",
    "sg:city":"Columbus",
    "sg:classifiers":[
        {
            "category":"Real Estate",
            "subcategory":"Real Estate Operator",
            "type":"Services"
        }
    ],
    "sg:phone":"+1 614 797 2054",
    "sg:postcode":"43240",
    "sg:province":"OH",
    "sg:tags":[
        "building",
        "optical",
        "good",
        "nonresidential"
    ],
    "wof:name":"Sears Roebock and Company",
    "wof:placetype":"venue"
},
  "geometry": {"coordinates":[-82.982022,40.141132],"type":"Point"}
}