{
  "type": "Feature",
  "properties": {
    "iso:country":"US",
    "sg:address":"935 Walnut St",
    "sg:city":"Hamilton",
    "sg:classifiers":[
        {
            "category":"Cinema",
            "subcategory":"Movie Rental",
            "type":"Entertainment"
        }
    ],
    "sg:phone":"+1 513 896 7779",
    "sg:postcode":"45011",
    "sg:province":"OH",
    "sg:tags":[
        "leasing",
        "video",
        "disc",
        "tape"
    ],
    "wof:name":"VIP Video Sales",
    "wof:placetype":"venue"
},
  "geometry": {"coordinates":[-84.553384,39.391348],"type":"Point"}
}