{
  "type": "Feature",
  "properties": {
    "addr:full":"7350 Gracely Dr Cincinnati OH 45233",
    "addr:housenumber":"7350",
    "addr:postcode":"45233",
    "addr:street":"Gracely Dr",
    "iso:country":"US",
    "sg:address":"7350 Gracely Dr",
    "sg:city":"Cincinnati",
    "sg:classifiers":[
        {
            "category":"Professional",
            "subcategory":"Art Services",
            "type":"Services"
        }
    ],
    "sg:phone":"+1 513 941 2447",
    "sg:postcode":"45233",
    "sg:province":"OH",
    "sg:tags":[
        "photographer"
    ],
    "wof:name":"Robert Cushman Hayes Stock",
    "wof:placetype":"venue"
},
  "geometry": {"coordinates":[-84.703926,39.126361],"type":"Point"}
}