{
  "type": "Feature",
  "properties": {
    "addr:full": "30185 Overlook Dr Wickliffe OH 44092",
    "addr:housenumber": "30185",
    "addr:postcode": "44092",
    "addr:street": "Overlook Dr",
    "iso:country": "US",
    "sg:address": "30185 Overlook Dr",
    "sg:city": "Wickliffe",
    "sg:classifiers": [
      {
        "category": "Wholesale",
        "subcategory": "Machinery \u0026 Supplies",
        "type": "Manufacturing \u0026 Wholesale Goods"
      }
    ],
    "sg:phone": "+1 440 585 4224",
    "sg:postcode": "44092",
    "sg:province": "OH",
    "sg:tags": [
      "repairing"
    ],
    "wof:name": "Jmrr Co All Machinery",
    "wof:placetype": "venue"
  },
  "geometry": {"coordinates":[-81.456668,41.607069],"type":"Point"}
}
