{
  "type": "Feature",
  "properties": {
    "iso:country":"US",
    "sg:address":"30185 Overlook Dr",
    "sg:city":"Wickliffe",
    "sg:classifiers":[
        {
            "category":"Wholesale",
            "subcategory":"Machinery & Supplies",
            "type":"Manufacturing & Wholesale Goods"
        }
    ],
    "sg:phone":"+1 440 585 4224",
    "sg:postcode":"44092",
    "sg:province":"OH",
    "sg:tags":[
        "repairing"
    ],
    "wof:name":"Jmrr Co All Machinery",
    "wof:placetype":"venue"
},
  "geometry": {"coordinates":[-81.45666799999999,41.607069],"type":"Point"}
}