{
  "type": "Feature",
  "properties": {
    "iso:country":"US",
    "sg:address":"5218 State Rte 235",
    "sg:city":"Conover",
    "sg:phone":"+1 937 362 4146",
    "sg:postcode":"45317",
    "sg:province":"OH",
    "sg:tags":[
        "beef",
        "farm",
        "corn",
        "soybean",
        "cattle",
        "feedlot"
    ],
    "wof:name":"Robert Ray Evans",
    "wof:placetype":"venue"
},
  "geometry": {"coordinates":[-83.98137199999999,40.201602],"type":"Point"}
}