{
  "type": "Feature",
  "properties": {
    "addr:full": "5218 State Rte 235 Conover OH 45317",
    "addr:housenumber": "5218",
    "addr:postcode": "45317",
    "addr:street": "State Rte 235",
    "iso:country": "US",
    "sg:address": "5218 State Rte 235",
    "sg:city": "Conover",
    "sg:phone": "+1 937 362 4146",
    "sg:postcode": "45317",
    "sg:province": "OH",
    "sg:tags": [
      "beef",
      "farm",
      "corn",
      "soybean",
      "cattle",
      "feedlot"
    ],
    "wof:name": "Robert Ray Evans",
    "wof:placetype": "venue"
  },
  "geometry": {"coordinates":[-83.981372,40.201602],"type":"Point"}
}
