{
  "type": "Feature",
  "properties": {
    "addr:full":"60310 S 26th Rd Bethesda OH 43719",
    "addr:housenumber":"60310",
    "addr:postcode":"43719",
    "addr:street":"S 26Th Rd",
    "iso:country":"US",
    "sg:address":"60310 S 26th Rd",
    "sg:city":"Bethesda",
    "sg:classifiers":[
        {
            "category":"Farming",
            "subcategory":"Farm",
            "type":"Manufacturing & Wholesale Goods"
        }
    ],
    "sg:phone":"+1 740 484 1350",
    "sg:postcode":"43719",
    "sg:province":"OH",
    "sg:tags":[
        "crop",
        "general"
    ],
    "wof:name":"Robert Martin",
    "wof:placetype":"venue"
},
  "geometry": {"coordinates":[-81.08223099999999,39.962864],"type":"Point"}
}