{
  "type": "Feature",
  "properties": {
    "iso:country":"US",
    "sg:address":"16085 State Rte 39",
    "sg:city":"Loudonville",
    "sg:classifiers":[
        {
            "category":"Farming",
            "subcategory":"Livestock Farm",
            "type":"Manufacturing & Wholesale Goods"
        }
    ],
    "sg:phone":"+1 419 994 3432",
    "sg:postcode":"44842",
    "sg:province":"OH",
    "sg:tags":[
        "beef",
        "feedlot",
        "cattle"
    ],
    "wof:name":"Elmer Dezort",
    "wof:placetype":"venue"
},
  "geometry": {"coordinates":[-82.19894,40.626514],"type":"Point"}
}