{
  "type": "Feature",
  "properties": {
    "addr:full": "16085 State Rte 39 Loudonville OH 44842",
    "addr:housenumber": "16085",
    "addr:postcode": "44842",
    "addr:street": "State Rte 39",
    "iso:country": "US",
    "sg:address": "16085 State Rte 39",
    "sg:city": "Loudonville",
    "sg:classifiers": [
      {
        "category": "Farming",
        "subcategory": "Livestock Farm",
        "type": "Manufacturing \u0026 Wholesale Goods"
      }
    ],
    "sg:phone": "+1 419 994 3432",
    "sg:postcode": "44842",
    "sg:province": "OH",
    "sg:tags": [
      "beef",
      "feedlot",
      "cattle"
    ],
    "wof:name": "Elmer Dezort",
    "wof:placetype": "venue"
  },
  "geometry": {"coordinates":[-82.19894,40.626514],"type":"Point"}
}
