{
  "type": "Feature",
  "properties": {
    "addr:full": "9119 Brookpark Rd Cleveland OH 44129",
    "addr:housenumber": "9119",
    "addr:postcode": "44129",
    "addr:street": "Brookpark Rd",
    "iso:country": "US",
    "sg:address": "9119 Brookpark Rd",
    "sg:city": "Cleveland",
    "sg:classifiers": [
      {
        "category": "Autos \u0026 Motor Vehicles",
        "subcategory": "Automobile Sales",
        "type": "Retail Goods"
      },
      {
        "category": "Retail",
        "subcategory": "Auto Repair",
        "type": "Services"
      }
    ],
    "sg:phone": "+1 216 661 6368",
    "sg:postcode": "44129",
    "sg:province": "OH",
    "sg:tags": [
      "body",
      "repairing",
      "used",
      "painting",
      "dealers-used",
      "car",
      "new",
      "cars-wholesale"
    ],
    "wof:name": "Sliva Bros Auto Repair Inc",
    "wof:placetype": "venue"
  },
  "geometry": {"coordinates":[-81.748741,41.418527],"type":"Point"}
}
