{
  "type": "Feature",
  "properties": {
    "addr:full": "301 Palmwood St Delta OH 43515",
    "addr:housenumber": "301",
    "addr:postcode": "43515",
    "addr:street": "Palmwood St",
    "iso:country": "US",
    "sg:address": "301 Palmwood St",
    "sg:city": "Delta",
    "sg:classifiers": [
      {
        "category": "Retail",
        "subcategory": "Auto Repair",
        "type": "Services"
      }
    ],
    "sg:phone": "+1 419 822 5370",
    "sg:postcode": "43515",
    "sg:province": "OH",
    "sg:tags": [
      "repairing",
      "automobile"
    ],
    "wof:name": "Schultz Automotive Repair",
    "wof:placetype": "venue"
  },
  "geometry": {"coordinates":[-84.007296,41.574754],"type":"Point"}
}
