{
  "type": "Feature",
  "properties": {
    "addr:full":"1075 Ashland Rd Mansfield OH 44905",
    "addr:housenumber":"1075",
    "addr:postcode":"44905",
    "addr:street":"Ashland Rd",
    "iso:country":"US",
    "sg:address":"1075 Ashland Rd",
    "sg:city":"Mansfield",
    "sg:classifiers":[
        {
            "category":"Restaurant",
            "type":"Food & Drink"
        }
    ],
    "sg:phone":"+1 419 589 2807",
    "sg:postcode":"44905",
    "sg:province":"OH",
    "sg:tags":[
        "eating"
    ],
    "wof:name":"Ponderosa Steakhouse",
    "wof:placetype":"venue"
},
  "geometry": {"coordinates":[-82.474813,40.776871],"type":"Point"}
}