{
  "type": "Feature",
  "properties": {
    "addr:full": "1712 Wayne Ave Dayton OH 45410",
    "addr:housenumber": "1712",
    "addr:postcode": "45410",
    "addr:street": "Wayne Ave",
    "iso:country": "US",
    "sg:address": "1712 Wayne Ave",
    "sg:city": "Dayton",
    "sg:classifiers": [
      {
        "category": "Retail",
        "subcategory": "Funeral Services",
        "type": "Services"
      }
    ],
    "sg:phone": "+1 937 253 6161",
    "sg:postcode": "45410",
    "sg:province": "OH",
    "sg:tags": [
      "director"
    ],
    "wof:name": "Westbrock Funeral Home Inc",
    "wof:placetype": "venue"
  },
  "geometry": {"coordinates":[-84.168813,39.744493],"type":"Point"}
}
