{
  "type": "Feature",
  "properties": {
    "iso:country":"US",
    "sg:address":"3312 W 105th St",
    "sg:city":"Cleveland",
    "sg:classifiers":[
        {
            "category":"Restaurant",
            "type":"Food & Drink"
        }
    ],
    "sg:phone":"+1 216 252 0560",
    "sg:postcode":"44111",
    "sg:province":"OH",
    "sg:tags":[
        "beverage"
    ],
    "wof:name":"Almira Beverage Drive-In",
    "wof:placetype":"venue"
},
  "geometry": {"coordinates":[-81.758686,41.463058],"type":"Point"}
}