{
  "type": "Feature",
  "properties": {
    "addr:full": "132 S Oxford St Troy OH 45373",
    "addr:housenumber": "132",
    "addr:postcode": "45373",
    "addr:street": "S Oxford St",
    "iso:country": "US",
    "sg:address": "132 S Oxford St",
    "sg:city": "Troy",
    "sg:classifiers": [
      {
        "category": "Real Estate",
        "subcategory": "Real Estate Operator",
        "type": "Services"
      }
    ],
    "sg:phone": "+1 937 335 1628",
    "sg:postcode": "45373",
    "sg:province": "OH",
    "sg:tags": [
      "building",
      "nonresidential"
    ],
    "wof:name": "Blk Diamond Properties LLC",
    "wof:placetype": "venue"
  },
  "geometry": {"coordinates":[-84.208107,40.040005],"type":"Point"}
}
