{
  "type": "Feature",
  "properties": {
    "addr:full": "3470 Clover Rd Bethel OH 45106",
    "addr:housenumber": "3470",
    "addr:postcode": "45106",
    "addr:street": "Clover Rd",
    "iso:country": "US",
    "sg:address": "3470 Clover Rd",
    "sg:city": "Bethel",
    "sg:classifiers": [
      {
        "category": "Professional",
        "type": "Services"
      }
    ],
    "sg:phone": "+1 513 734 6184",
    "sg:postcode": "45106",
    "sg:province": "OH",
    "wof:name": "D D Wilson LLC",
    "wof:placetype": "venue"
  },
  "geometry": {"coordinates":[-84.069792,39.005875],"type":"Point"}
}
