{
  "type": "Feature",
  "properties": {
    "addr:full":"5736 Deerfield Rd Milford OH 45150",
    "addr:housenumber":"5736",
    "addr:postcode":"45150",
    "addr:street":"Deerfield Rd",
    "iso:country":"US",
    "sg:address":"5736 Deerfield Rd",
    "sg:city":"Milford",
    "sg:classifiers":[
        {
            "category":"Autos & Motor Vehicles",
            "subcategory":"Automobile Sales",
            "type":"Retail Goods"
        }
    ],
    "sg:phone":"+1 513 575 4460",
    "sg:postcode":"45150",
    "sg:province":"OH",
    "sg:tags":[
        "car",
        "used",
        "dealer"
    ],
    "wof:name":"Deerfield Truck & Auto Sales",
    "wof:placetype":"venue"
},
  "geometry": {"coordinates":[-84.172549,39.177353],"type":"Point"}
}