{
  "type": "Feature",
  "properties": {
    "addr:full":"14101 Euclid Ave Cleveland OH 44112",
    "addr:housenumber":"14101",
    "addr:postcode":"44112",
    "addr:street":"Euclid Ave",
    "iso:country":"US",
    "sg:address":"14101 Euclid Ave",
    "sg:city":"Cleveland",
    "sg:classifiers":[
        {
            "category":"Education",
            "subcategory":"Library",
            "type":"Public Place"
        }
    ],
    "sg:phone":"+1 216 451 1596",
    "sg:postcode":"44112",
    "sg:province":"OH",
    "sg:website":"www.ecpl.lib.oh.us",
    "wof:name":"East Cleveland Public Library",
    "wof:placetype":"venue"
},
  "geometry": {"coordinates":[-81.584129,41.528389],"type":"Point"}
}