{
  "type": "Feature",
  "properties": {
    "addr:full":"104 Middle Post Pointe Chardon OH 44024",
    "addr:housenumber":"104",
    "addr:postcode":"44024",
    "addr:street":"Middle Post Pointe",
    "iso:country":"US",
    "sg:address":"104 Middle Post Pointe",
    "sg:city":"Chardon",
    "sg:classifiers":[
        {
            "category":"Wholesale",
            "subcategory":"Electrical",
            "type":"Manufacturing & Wholesale Goods"
        }
    ],
    "sg:phone":"+1 440 285 5591",
    "sg:postcode":"44024",
    "sg:province":"OH",
    "sg:tags":[
        "electronic"
    ],
    "wof:name":"Lisa Orlandi",
    "wof:placetype":"venue"
},
  "geometry": {"coordinates":[-81.19635700000001,41.561924],"type":"Point"}
}