{
  "type": "Feature",
  "properties": {
    "addr:full":"510 18th Ave Middletown OH 45044",
    "addr:housenumber":"510",
    "addr:postcode":"45044",
    "addr:street":"18Th Ave",
    "iso:country":"US",
    "sg:address":"510 18th Ave",
    "sg:city":"Middletown",
    "sg:classifiers":[
        {
            "category":"Organizations",
            "subcategory":"Religious Organization",
            "type":"Services"
        }
    ],
    "sg:phone":"+1 513 423 6322",
    "sg:postcode":"45044",
    "sg:province":"OH",
    "sg:tags":[
        "church"
    ],
    "wof:name":"Pentecostal Holiness Church",
    "wof:placetype":"venue"
},
  "geometry": {"coordinates":[-84.41535500000001,39.497932],"type":"Point"}
}