{
  "type": "Feature",
  "properties": {
    "addr:full": "11503 Springfield Pike Cincinnati OH 45246",
    "addr:housenumber": "11503",
    "addr:postcode": "45246",
    "addr:street": "Springfield Pike",
    "iso:country": "US",
    "sg:address": "11503 Springfield Pike",
    "sg:city": "Cincinnati",
    "sg:classifiers": [
      {
        "category": "Manufacturing",
        "subcategory": "Printing",
        "type": "Manufacturing \u0026 Wholesale Goods"
      }
    ],
    "sg:phone": "+1 513 772 3369",
    "sg:postcode": "45246",
    "sg:province": "OH",
    "sg:tags": [
      "periodical"
    ],
    "wof:name": "One Accord Christian Magazine",
    "wof:placetype": "venue"
  },
  "geometry": {"coordinates":[-84.485489,39.284346],"type":"Point"}
}
