{
  "type": "Feature",
  "properties": {
    "addr:full":"20325 Center Ridge Rd Cleveland OH 44116",
    "addr:housenumber":"20325",
    "addr:postcode":"44116",
    "addr:street":"Center Ridge Rd",
    "iso:country":"US",
    "sg:address":"20325 Center Ridge Rd",
    "sg:city":"Cleveland",
    "sg:classifiers":[
        {
            "category":"Banks & Credit Unions",
            "subcategory":"Bank",
            "type":"Services"
        }
    ],
    "sg:phone":"+1 440 333 6630",
    "sg:postcode":"44116",
    "sg:province":"OH",
    "sg:tags":[
        "mortgage",
        "loan",
        "broker",
        "real estate"
    ],
    "wof:name":"Mid America Mortgage Corp",
    "wof:placetype":"venue"
},
  "geometry": {"coordinates":[-81.844165,41.464431],"type":"Point"}
}