{
  "type": "Feature",
  "properties": {
    "addr:full": "9787 US Rte 40 W New Paris OH 45347",
    "addr:housenumber": "9787",
    "addr:postcode": "45347",
    "addr:street": "Us Rte 40 W",
    "iso:country": "US",
    "sg:address": "9787 US Rte 40 W",
    "sg:city": "New Paris",
    "sg:classifiers": [
      {
        "category": "Retail",
        "subcategory": "Repair Shop",
        "type": "Services"
      },
      {
        "category": "Shopping",
        "subcategory": "Computers \u0026 Home Electronics",
        "type": "Retail Goods"
      }
    ],
    "sg:phone": "+1 937 437 2929",
    "sg:postcode": "45347",
    "sg:province": "OH",
    "sg:tags": [
      "equipment",
      "electronic",
      "supply"
    ],
    "wof:name": "Cat CB Of Ohio Inc",
    "wof:placetype": "venue"
  },
  "geometry": {"coordinates":[-84.813748,39.833707],"type":"Point"}
}
