{
  "type": "Feature",
  "properties": {
    "iso:country":"US",
    "sg:address":"154 Bavarian Dr",
    "sg:city":"Middletown",
    "sg:classifiers":[
        {
            "category":"Real Estate",
            "subcategory":"Real Estate Agent",
            "type":"Services"
        }
    ],
    "sg:phone":"+1 513 423 5796",
    "sg:postcode":"45044",
    "sg:province":"OH",
    "wof:name":"Bavarian Woods Apartments",
    "wof:placetype":"venue"
},
  "geometry": {"coordinates":[-84.335948,39.506026],"type":"Point"}
}