{
  "type": "Feature",
  "properties": {
    "iso:country":"US",
    "sg:address":"8060 Frank Ave NW",
    "sg:city":"North Canton",
    "sg:classifiers":[
        {
            "category":"Building & Trades",
            "subcategory":"Construction",
            "type":"Services"
        }
    ],
    "sg:phone":"+1 330 497 0946",
    "sg:postcode":"44720",
    "sg:province":"OH",
    "sg:tags":[
        "painter"
    ],
    "wof:name":"Northwest Decorating & Paint",
    "wof:placetype":"venue"
},
  "geometry": {"coordinates":[-81.439141,40.90255],"type":"Point"}
}