{
  "type": "Feature",
  "properties": {
    "addr:full": "8060 Frank Ave NW North Canton OH 44720",
    "addr:housenumber": "8060",
    "addr:postcode": "44720",
    "addr:street": "Frank Ave Nw",
    "iso:country": "US",
    "sg:address": "8060 Frank Ave NW",
    "sg:city": "North Canton",
    "sg:classifiers": [
      {
        "category": "Building \u0026 Trades",
        "subcategory": "Construction",
        "type": "Services"
      }
    ],
    "sg:phone": "+1 330 497 0946",
    "sg:postcode": "44720",
    "sg:province": "OH",
    "sg:tags": [
      "painter"
    ],
    "wof:name": "Northwest Decorating \u0026 Paint",
    "wof:placetype": "venue"
  },
  "geometry": {"coordinates":[-81.439141,40.90255],"type":"Point"}
}
