{
  "type": "Feature",
  "properties": {
    "addr:full": "12653 Madison Rd Middlefield OH 44062",
    "addr:housenumber": "12653",
    "addr:postcode": "44062",
    "addr:street": "Madison Rd",
    "iso:country": "US",
    "sg:address": "12653 Madison Rd",
    "sg:city": "Middlefield",
    "sg:classifiers": [
      {
        "category": "Manufacturing",
        "subcategory": "Metals",
        "type": "Manufacturing \u0026 Wholesale Goods"
      }
    ],
    "sg:phone": "+1 440 636 5493",
    "sg:postcode": "44062",
    "sg:province": "OH",
    "sg:tags": [
      "product",
      "wood",
      "fabricated",
      "mfg"
    ],
    "wof:name": "Company Front Award",
    "wof:placetype": "venue"
  },
  "geometry": {"coordinates":[-81.051721,41.521414],"type":"Point"}
}
