{
  "type": "Feature",
  "properties": {
    "iso:country":"US",
    "sg:address":"12653 Madison Rd",
    "sg:city":"Middlefield",
    "sg:classifiers":[
        {
            "category":"Manufacturing",
            "subcategory":"Metals",
            "type":"Manufacturing & Wholesale Goods"
        }
    ],
    "sg:phone":"+1 440 636 5493",
    "sg:postcode":"44062",
    "sg:province":"OH",
    "sg:tags":[
        "product",
        "wood",
        "fabricated",
        "mfg"
    ],
    "wof:name":"Company Front Award",
    "wof:placetype":"venue"
},
  "geometry": {"coordinates":[-81.051721,41.521414],"type":"Point"}
}