{
  "type": "Feature",
  "properties": {
    "addr:full": "5551 Wheatmore Ct Mason OH 45040",
    "addr:postcode": "5551;45040",
    "addr:street": "Wheatmore Ct",
    "iso:country": "US",
    "sg:address": "5551 Wheatmore Ct",
    "sg:city": "Mason",
    "sg:classifiers": [
      {
        "category": "Building \u0026 Trades",
        "subcategory": "Construction",
        "type": "Services"
      }
    ],
    "sg:phone": "+1 513 398 8933",
    "sg:postcode": "45040",
    "sg:province": "OH",
    "sg:tags": [
      "contractor"
    ],
    "wof:name": "Youngs Masonry Inc",
    "wof:placetype": "venue"
  },
  "geometry": {"coordinates":[-84.326223,39.356552],"type":"Point"}
}
