{
  "type": "Feature",
  "properties": {
    "iso:country":"US",
    "sg:address":"4305 E Galbraith Rd",
    "sg:city":"Cincinnati",
    "sg:classifiers":[
        {
            "category":"Real Estate",
            "subcategory":"Real Estate Services",
            "type":"Services"
        },
        {
            "category":"Building & Trades",
            "subcategory":"Cleaning & Sanitation",
            "type":"Services"
        }
    ],
    "sg:phone":"+1 513 631 2756",
    "sg:postcode":"45236",
    "sg:province":"OH",
    "sg:tags":[
        "maintenance",
        "cleaners-interior"
    ],
    "wof:name":"T Q C",
    "wof:placetype":"venue"
},
  "geometry": {"coordinates":[-84.393556,39.207965],"type":"Point"}
}