{
  "type": "Feature",
  "properties": {
    "addr:full":"506 N Main St North Canton OH 44720",
    "addr:housenumber":"506",
    "addr:postcode":"44720",
    "addr:street":"N Main St",
    "iso:country":"US",
    "sg:address":"506 N Main St",
    "sg:city":"North Canton",
    "sg:classifiers":[
        {
            "category":"Health Services",
            "subcategory":"Doctor",
            "type":"Services"
        }
    ],
    "sg:phone":"+1 330 499 4403",
    "sg:postcode":"44720",
    "sg:province":"OH",
    "sg:tags":[
        "dentist"
    ],
    "wof:name":"John D Suglio Inc",
    "wof:placetype":"venue"
},
  "geometry": {"coordinates":[-81.402895,40.880407],"type":"Point"}
}