{
  "type": "Feature",
  "properties": {
    "iso:country":"US",
    "sg:address":"31 E Main St",
    "sg:city":"Norwalk",
    "sg:classifiers":[
        {
            "category":"Shopping",
            "subcategory":"Books",
            "type":"Retail Goods"
        }
    ],
    "sg:phone":"+1 419 668 6775",
    "sg:postcode":"44857",
    "sg:province":"OH",
    "sg:tags":[
        "dealer"
    ],
    "wof:name":"Book Express",
    "wof:placetype":"venue"
},
  "geometry": {"coordinates":[-82.61388700000001,41.243222],"type":"Point"}
}