{
  "type": "Feature",
  "properties": {
    "addr:full": "1037 Vance St Toledo OH 43607",
    "addr:housenumber": "1037",
    "addr:postcode": "43607",
    "addr:street": "Vance St",
    "iso:country": "US",
    "sg:address": "1037 Vance St",
    "sg:city": "Toledo",
    "sg:classifiers": [
      {
        "category": "Professional",
        "type": "Services"
      }
    ],
    "sg:phone": "+1 419 241 4024",
    "sg:postcode": "43607",
    "sg:province": "OH",
    "wof:name": "Edward Dotson Rev",
    "wof:placetype": "venue"
  },
  "geometry": {"coordinates":[-83.569118,41.647241],"type":"Point"}
}
