{
  "type": "Feature",
  "properties": {
    "addr:full":"1450 Waterbury Rd Lakewood OH 44107",
    "addr:housenumber":"1450",
    "addr:postcode":"44107",
    "addr:street":"Waterbury Rd",
    "iso:country":"US",
    "sg:address":"1450 Waterbury Rd",
    "sg:city":"Lakewood",
    "sg:classifiers":[
        {
            "category":"Manufacturing",
            "subcategory":"Signs",
            "type":"Manufacturing & Wholesale Goods"
        }
    ],
    "sg:phone":"+1 216 521 3946",
    "sg:postcode":"44107",
    "sg:province":"OH",
    "sg:tags":[
        "specialty",
        "mfg"
    ],
    "wof:name":"Crossfire Studio",
    "wof:placetype":"venue"
},
  "geometry": {"coordinates":[-81.783012,41.481698],"type":"Point"}
}