{
  "type": "Feature",
  "properties": {
    "addr:full": "1991 Crocker Rd Cleveland OH 44145",
    "addr:housenumber": "1991",
    "addr:postcode": "44145",
    "addr:street": "Crocker Rd",
    "iso:country": "US",
    "sg:address": "1991 Crocker Rd",
    "sg:city": "Cleveland",
    "sg:classifiers": [
      {
        "category": "Real Estate",
        "subcategory": "Real Estate Agent",
        "type": "Services"
      }
    ],
    "sg:phone": "+1 440 892 3387",
    "sg:postcode": "44145",
    "sg:province": "OH",
    "sg:tags": [
      "desk",
      "space"
    ],
    "sg:website": "www.psoffices.com",
    "wof:name": "Access Workplaces By PS Exec",
    "wof:placetype": "venue"
  },
  "geometry": {"coordinates":[-81.950408,41.460615],"type":"Point"}
}
