{
  "type": "Feature",
  "properties": {
    "iso:country":"US",
    "sg:address":"19020 White Stone Rd",
    "sg:city":"Marysville",
    "sg:classifiers":[
        {
            "category":"Building & Trades",
            "subcategory":"Landscaping Services",
            "type":"Services"
        }
    ],
    "sg:phone":"+1 937 642 6937",
    "sg:postcode":"43040",
    "sg:province":"OH",
    "wof:name":"LLC White Rock",
    "wof:placetype":"venue"
},
  "geometry": {"coordinates":[-83.296982,40.276771],"type":"Point"}
}