{
  "type": "Feature",
  "properties": {
    "addr:full":"601 Adams St Toledo OH 43604",
    "addr:housenumber":"601",
    "addr:postcode":"43604",
    "addr:street":"Adams St",
    "iso:country":"US",
    "sg:address":"601 Adams St",
    "sg:city":"Toledo",
    "sg:classifiers":[
        {
            "category":"Restaurant",
            "type":"Food & Drink"
        }
    ],
    "sg:phone":"+1 419 241 6965",
    "sg:postcode":"43604",
    "sg:province":"OH",
    "wof:name":"Magic Wok",
    "wof:placetype":"venue"
},
  "geometry": {"coordinates":[-83.536776,41.654053],"type":"Point"}
}