{
  "type": "Feature",
  "properties": {
    "addr:full":"24650 Center Ridge Rd Cleveland OH 44145",
    "addr:housenumber":"24650",
    "addr:postcode":"44145",
    "addr:street":"Center Ridge Rd",
    "iso:country":"US",
    "sg:address":"24650 Center Ridge Rd",
    "sg:city":"Cleveland",
    "sg:classifiers":[
        {
            "category":"Professional",
            "subcategory":"Accounting & Tax Preparation",
            "type":"Services"
        }
    ],
    "sg:phone":"+1 440 617 0100",
    "sg:postcode":"44145",
    "sg:province":"OH",
    "sg:tags":[
        "return",
        "filing"
    ],
    "wof:name":"H & R Block Tax Svc",
    "wof:placetype":"venue"
},
  "geometry": {"coordinates":[-81.89702,41.457228],"type":"Point"}
}