{
  "type": "Feature",
  "properties": {
    "iso:country":"US",
    "sg:address":"9145 N Dixie Dr",
    "sg:city":"Dayton",
    "sg:classifiers":[
        {
            "category":"Sports & Exercise",
            "subcategory":"Gym",
            "type":"Entertainment"
        }
    ],
    "sg:phone":"+1 937 264 1188",
    "sg:postcode":"45414",
    "sg:province":"OH",
    "sg:tags":[
        "club",
        "health",
        "studio",
        "gymnasium"
    ],
    "wof:name":"Curves",
    "wof:placetype":"venue"
},
  "geometry": {"coordinates":[-84.199144,39.862706],"type":"Point"}
}