{
  "type": "Feature",
  "properties": {
    "addr:full": "5907 Ridge Rd Cleveland OH 44129",
    "addr:housenumber": "5907",
    "addr:postcode": "44129",
    "addr:street": "Ridge Rd",
    "iso:country": "US",
    "sg:address": "5907 Ridge Rd",
    "sg:city": "Cleveland",
    "sg:classifiers": [
      {
        "category": "Banks \u0026 Credit Unions",
        "subcategory": "Bank",
        "type": "Services"
      },
      {
        "category": "Banks \u0026 Credit Unions",
        "subcategory": "Financial Services",
        "type": "Services"
      }
    ],
    "sg:phone": "+1 440 888 0330",
    "sg:postcode": "44129",
    "sg:province": "OH",
    "sg:tags": [
      "loan",
      "saving"
    ],
    "wof:name": "Charter One",
    "wof:placetype": "venue"
  },
  "geometry": {"coordinates":[-81.734573,41.402111],"type":"Point"}
}
