{
  "type": "Feature",
  "properties": {
    "addr:full":"330 Decourcey Rd Rittman OH 44270",
    "addr:housenumber":"330",
    "addr:postcode":"44270",
    "addr:street":"Decourcey Rd",
    "iso:country":"US",
    "sg:address":"330 Decourcey Rd",
    "sg:city":"Rittman",
    "sg:classifiers":[
        {
            "category":"Building & Trades",
            "subcategory":"Plumbing",
            "type":"Services"
        }
    ],
    "sg:phone":"+1 330 925 1448",
    "sg:postcode":"44270",
    "sg:province":"OH",
    "sg:tags":[
        "repair",
        "contractor"
    ],
    "wof:name":"Buckingham Plumbing & Heating",
    "wof:placetype":"venue"
},
  "geometry": {"coordinates":[-81.799982,40.980269],"type":"Point"}
}