{
  "type": "Feature",
  "properties": {
    "addr:full": "58 N Meridian Rd Youngstown OH 44509",
    "addr:housenumber": "58",
    "addr:postcode": "44509",
    "addr:street": "N Meridian Rd",
    "iso:country": "US",
    "sg:address": "58 N Meridian Rd",
    "sg:city": "Youngstown",
    "sg:classifiers": [
      {
        "category": "Autos \u0026 Motor Vehicles",
        "subcategory": "Auto Supplies",
        "type": "Retail Goods"
      },
      {
        "category": "Retail",
        "subcategory": "Auto Repair",
        "type": "Services"
      }
    ],
    "sg:phone": "+1 330 799 0976",
    "sg:postcode": "44509",
    "sg:province": "OH",
    "sg:tags": [
      "automobile",
      "part",
      "truck"
    ],
    "sg:website": "http://clickserve.dartsearch.net/link/click?lid=43000000313871401\u0026ds_s_kwgid=58000000006820725\u0026ds_e_matchtype={MatchType}\u0026ds_e_kwdid={OrderItemId}\u0026ds_e_adid={AdId}\u0026ds_url_v=2",
    "wof:name": "Patrick's Service",
    "wof:placetype": "venue"
  },
  "geometry": {"coordinates":[-80.711082,41.104184],"type":"Point"}
}
