{
  "type": "Feature",
  "properties": {
    "iso:country":"US",
    "sg:address":"1894 Hackleshin Rd",
    "sg:city":"Peebles",
    "sg:classifiers":[
        {
            "category":"Building & Trades",
            "subcategory":"Construction",
            "type":"Services"
        }
    ],
    "sg:phone":"+1 937 587 3383",
    "sg:postcode":"45660",
    "sg:province":"OH",
    "sg:tags":[
        "concrete",
        "contractor"
    ],
    "wof:name":"Ronald Porter",
    "wof:placetype":"venue"
},
  "geometry": {"coordinates":[-83.31777599999999,38.989802],"type":"Point"}
}