{
  "type": "Feature",
  "properties": {
    "addr:full": "1894 Hackleshin Rd Peebles OH 45660",
    "addr:housenumber": "1894",
    "addr:postcode": "45660",
    "addr:street": "Hackleshin Rd",
    "iso:country": "US",
    "sg:address": "1894 Hackleshin Rd",
    "sg:city": "Peebles",
    "sg:classifiers": [
      {
        "category": "Building \u0026 Trades",
        "subcategory": "Construction",
        "type": "Services"
      }
    ],
    "sg:phone": "+1 937 587 3383",
    "sg:postcode": "45660",
    "sg:province": "OH",
    "sg:tags": [
      "concrete",
      "contractor"
    ],
    "wof:name": "Ronald Porter",
    "wof:placetype": "venue"
  },
  "geometry": {"coordinates":[-83.317776,38.989802],"type":"Point"}
}
