{
  "type": "Feature",
  "properties": {
    "addr:full": "5601 Opengate Ct Cincinnati OH 45247",
    "addr:housenumber": "5601",
    "addr:postcode": "45247",
    "addr:street": "Opengate Ct",
    "iso:country": "US",
    "sg:address": "5601 Opengate Ct",
    "sg:city": "Cincinnati",
    "sg:classifiers": [
      {
        "category": "Health Services",
        "subcategory": "Nursing And Care Facility",
        "type": "Services"
      }
    ],
    "sg:phone": "+1 513 662 0005",
    "sg:postcode": "45247",
    "sg:province": "OH",
    "sg:tags": [
      "home",
      "retirement",
      "community"
    ],
    "wof:name": "Pro Visions Supported Living",
    "wof:placetype": "venue"
  },
  "geometry": {"coordinates":[-84.625876,39.195137],"type":"Point"}
}
