{
  "type": "Feature",
  "properties": {
    "iso:country":"US",
    "sg:address":"5601 Opengate Ct",
    "sg:city":"Cincinnati",
    "sg:classifiers":[
        {
            "category":"Health Services",
            "subcategory":"Nursing And Care Facility",
            "type":"Services"
        }
    ],
    "sg:phone":"+1 513 662 0005",
    "sg:postcode":"45247",
    "sg:province":"OH",
    "sg:tags":[
        "home",
        "retirement",
        "community"
    ],
    "wof:name":"Pro Visions Supported Living",
    "wof:placetype":"venue"
},
  "geometry": {"coordinates":[-84.62587600000001,39.195137],"type":"Point"}
}