{
  "type": "Feature",
  "properties": {
    "addr:full": "23 E Main St Shelby OH 44875",
    "addr:housenumber": "23",
    "addr:postcode": "44875",
    "addr:street": "E Main St",
    "iso:country": "US",
    "sg:address": "23 E Main St",
    "sg:city": "Shelby",
    "sg:classifiers": [
      {
        "category": "Utilities",
        "subcategory": "Water",
        "type": "Services"
      }
    ],
    "sg:phone": "+1 419 342 4085",
    "sg:postcode": "44875",
    "sg:province": "OH",
    "sg:tags": [
      "company",
      "sewage"
    ],
    "wof:name": "Shelby Water Dept",
    "wof:placetype": "venue"
  },
  "geometry": {"coordinates":[-82.657619,40.881453],"type":"Point"}
}
