{
  "type": "Feature",
  "properties": {
    "iso:country":"US",
    "sg:address":"60 Sterling Ave",
    "sg:city":"Rittman",
    "sg:classifiers":[
        {
            "category":"Shopping",
            "subcategory":"Discount & Variety Stores",
            "type":"Retail Goods"
        }
    ],
    "sg:phone":"+1 330 927 2262",
    "sg:postcode":"44270",
    "sg:province":"OH",
    "wof:name":"M D M Resale",
    "wof:placetype":"venue"
},
  "geometry": {"coordinates":[-81.782766,40.967146],"type":"Point"}
}