{
  "type": "Feature",
  "properties": {
    "addr:full":"6055 W Chester Rd West Chester OH 45069",
    "addr:housenumber":"6055",
    "addr:postcode":"45069",
    "addr:street":"W Chester Rd",
    "iso:country":"US",
    "sg:address":"6055 W Chester Rd",
    "sg:city":"West Chester",
    "sg:classifiers":[
        {
            "category":"Building & Trades",
            "subcategory":"Construction",
            "type":"Services"
        }
    ],
    "sg:phone":"+1 513 777 1777",
    "sg:postcode":"45069",
    "sg:province":"OH",
    "sg:tags":[
        "general",
        "contractor"
    ],
    "wof:name":"Pae & Assoc Inc",
    "wof:placetype":"venue"
},
  "geometry": {"coordinates":[-84.43394000000001,39.329349],"type":"Point"}
}