{
  "type": "Feature",
  "properties": {
    "addr:full":"2110 Saint Clair Ave NE Cleveland OH 44114",
    "addr:housenumber":"2110",
    "addr:postcode":"44114",
    "addr:street":"Saint Clair Ave Ne",
    "iso:country":"US",
    "sg:address":"2110 Saint Clair Ave NE",
    "sg:city":"Cleveland",
    "sg:classifiers":[
        {
            "category":"Retail",
            "subcategory":"Auto Repair",
            "type":"Services"
        }
    ],
    "sg:phone":"+1 216 566 9550",
    "sg:postcode":"44114",
    "sg:province":"OH",
    "sg:tags":[
        "repairing",
        "automobile"
    ],
    "wof:name":"Auto Shop",
    "wof:placetype":"venue"
},
  "geometry": {"coordinates":[-81.677496,41.510033],"type":"Point"}
}