{
  "type": "Feature",
  "properties": {
    "addr:full": "3900 Riverside Dr Columbus OH 43220",
    "addr:housenumber": "3900",
    "addr:postcode": "43220",
    "addr:street": "Riverside Dr",
    "iso:country": "US",
    "sg:address": "3900 Riverside Dr",
    "sg:city": "Columbus",
    "sg:classifiers": [
      {
        "category": "Restaurant",
        "type": "Food \u0026 Drink"
      }
    ],
    "sg:phone": "+1 614 451 5146",
    "sg:postcode": "43220",
    "sg:province": "OH",
    "sg:tags": [
      "eating"
    ],
    "wof:name": "Tastefully Yours",
    "wof:placetype": "venue"
  },
  "geometry": {"coordinates":[-83.092778,40.033988],"type":"Point"}
}
