{
  "type": "Feature",
  "properties": {
    "iso:country":"US",
    "sg:address":"7480 Young Dr",
    "sg:city":"Cleveland",
    "sg:classifiers":[
        {
            "category":"Freight",
            "type":"Transportation"
        }
    ],
    "sg:phone":"+1 440 232 7281",
    "sg:postcode":"44146",
    "sg:province":"OH",
    "sg:tags":[
        "hauling",
        "trucking"
    ],
    "wof:name":"Hazen Transportation",
    "wof:placetype":"venue"
},
  "geometry": {"coordinates":[-81.530063,41.362223],"type":"Point"}
}