{
  "type": "Feature",
  "properties": {
    "iso:country":"US",
    "sg:address":"18740 Auburn Glenn Dr",
    "sg:city":"Mantua",
    "sg:classifiers":[
        {
            "category":"Building & Trades",
            "subcategory":"Construction",
            "type":"Services"
        }
    ],
    "sg:phone":"+1 330 422 1200",
    "sg:postcode":"44255",
    "sg:province":"OH",
    "sg:tags":[
        "bathroom",
        "remodeling"
    ],
    "wof:name":"Custom Interior Design Inc",
    "wof:placetype":"venue"
},
  "geometry": {"coordinates":[-81.25531700000001,41.360925],"type":"Point"}
}