{
  "type": "Feature",
  "properties": {
    "iso:country":"US",
    "sg:address":"18040 Roettger Rd",
    "sg:city":"Botkins",
    "sg:classifiers":[
        {
            "category":"Retail",
            "subcategory":"Portrait Studio",
            "type":"Services"
        }
    ],
    "sg:phone":"+1 419 753 2004",
    "sg:postcode":"45306",
    "sg:province":"OH",
    "sg:tags":[
        "photography"
    ],
    "wof:name":"MAK Photography",
    "wof:placetype":"venue"
},
  "geometry": {"coordinates":[-84.298126,40.463027],"type":"Point"}
}