{
  "type": "Feature",
  "properties": {
    "addr:full":"2810 Bobmeyer Rd Hamilton OH 45015",
    "addr:housenumber":"2810",
    "addr:postcode":"45015",
    "addr:street":"Bobmeyer Rd",
    "iso:country":"US",
    "sg:address":"2810 Bobmeyer Rd",
    "sg:city":"Hamilton",
    "sg:classifiers":[
        {
            "category":"Airline",
            "type":"Transportation"
        }
    ],
    "sg:phone":"+1 513 863 3999",
    "sg:postcode":"45015",
    "sg:province":"OH",
    "sg:tags":[
        "company"
    ],
    "wof:name":"Airway Air Charter",
    "wof:placetype":"venue"
},
  "geometry": {"coordinates":[-84.525847,39.362818],"type":"Point"}
}