{
  "type": "Feature",
  "properties": {
    "addr:full":"815 W Grand Ave Dayton OH 45402",
    "addr:housenumber":"815",
    "addr:postcode":"45402",
    "addr:street":"W Grand Ave",
    "iso:country":"US",
    "sg:address":"815 W Grand Ave",
    "sg:city":"Dayton",
    "sg:classifiers":[
        {
            "category":"Real Estate",
            "subcategory":"Real Estate Agent",
            "type":"Services"
        }
    ],
    "sg:phone":"+1 937 278 5734",
    "sg:postcode":"45402",
    "sg:province":"OH",
    "wof:name":"Hawes Realty Inc",
    "wof:placetype":"venue"
},
  "geometry": {"coordinates":[-84.210798,39.767258],"type":"Point"}
}