{
  "type": "Feature",
  "properties": {
    "addr:full": "7001 W Cross Creek Trl Brecksville OH 44141",
    "addr:housenumber": "7001",
    "addr:postcode": "44141",
    "addr:street": "W Cross Creek Trl",
    "iso:country": "US",
    "sg:address": "7001 W Cross Creek Trl",
    "sg:city": "Brecksville",
    "sg:classifiers": [
      {
        "category": "Real Estate",
        "subcategory": "Real Estate Operator",
        "type": "Services"
      }
    ],
    "sg:phone": "+1 440 526 5440",
    "sg:postcode": "44141",
    "sg:province": "OH",
    "sg:tags": [
      "building",
      "apartment"
    ],
    "wof:name": "Grand Bay of Brecksville",
    "wof:placetype": "venue"
  },
  "geometry": {"coordinates":[-81.646248,41.292676],"type":"Point"}
}
