{
  "type": "Feature",
  "properties": {
    "addr:full":"5255 State Rd Ashtabula OH 44004",
    "addr:housenumber":"5255",
    "addr:postcode":"44004",
    "addr:street":"State Rd",
    "iso:country":"US",
    "sg:address":"5255 State Rd",
    "sg:city":"Ashtabula",
    "sg:classifiers":[
        {
            "category":"Utilities",
            "subcategory":"Telephone",
            "type":"Services"
        }
    ],
    "sg:phone":"+1 440 997 5309",
    "sg:postcode":"44004",
    "sg:province":"OH",
    "sg:tags":[
        "communications"
    ],
    "wof:name":"Burt Brown",
    "wof:placetype":"venue"
},
  "geometry": {"coordinates":[-80.76927999999999,41.859112],"type":"Point"}
}