{
  "type": "Feature",
  "properties": {
    "iso:country":"US",
    "sg:address":"56253 Beaver Valley Rd",
    "sg:city":"Quaker City",
    "sg:classifiers":[
        {
            "category":"Professional",
            "type":"Services"
        }
    ],
    "sg:phone":"+1 740 679 3621",
    "sg:postcode":"43773",
    "sg:province":"OH",
    "wof:name":"Dr Angelo J Magistro Inc",
    "wof:placetype":"venue"
},
  "geometry": {"coordinates":[-81.24963099999999,39.919483],"type":"Point"}
}