{
  "type": "Feature",
  "properties": {
    "iso:country":"US",
    "sg:address":"13917 State Rte 64",
    "sg:city":"Swanton",
    "sg:classifiers":[
        {
            "category":"Wholesale",
            "subcategory":"Meat",
            "type":"Manufacturing & Wholesale Goods"
        }
    ],
    "sg:phone":"+1 419 644 3461",
    "sg:postcode":"43558",
    "sg:province":"OH",
    "sg:tags":[
        "packer"
    ],
    "wof:name":"St Mary's Meats LLC",
    "wof:placetype":"venue"
},
  "geometry": {"coordinates":[-83.912055,41.669923],"type":"Point"}
}