{
  "type": "Feature",
  "properties": {
    "iso:country":"US",
    "sg:address":"150 Kimberwick Rd",
    "sg:city":"Lexington",
    "sg:classifiers":[
        {
            "category":"Communications",
            "subcategory":"Film & Video Production",
            "type":"Services"
        },
        {
            "category":"Professional",
            "type":"Services"
        }
    ],
    "sg:phone":"+1 419 884 3938",
    "sg:postcode":"44904",
    "sg:province":"OH",
    "sg:tags":[
        "taping"
    ],
    "wof:name":"Captured Digital Memories",
    "wof:placetype":"venue"
},
  "geometry": {"coordinates":[-82.603241,40.67966],"type":"Point"}
}