{
  "type": "Feature",
  "properties": {
    "addr:full":"1334 Phillips Ave Dayton OH 45410",
    "addr:housenumber":"1334",
    "addr:postcode":"45410",
    "addr:street":"Phillips Ave",
    "iso:country":"US",
    "sg:address":"1334 Phillips Ave",
    "sg:city":"Dayton",
    "sg:classifiers":[
        {
            "category":"Freight",
            "type":"Transportation"
        }
    ],
    "sg:phone":"+1 937 252 4617",
    "sg:postcode":"45410",
    "sg:province":"OH",
    "sg:tags":[
        "operator",
        "trucking"
    ],
    "wof:name":"Dallas Wood Trucking",
    "wof:placetype":"venue"
},
  "geometry": {"coordinates":[-84.15594299999999,39.741027],"type":"Point"}
}