{
  "type": "Feature",
  "properties": {
    "addr:full":"975 Chestnut St Nelsonville OH 45764",
    "addr:housenumber":"975",
    "addr:postcode":"45764",
    "addr:street":"Chestnut St",
    "iso:country":"US",
    "sg:address":"975 Chestnut St",
    "sg:city":"Nelsonville",
    "sg:classifiers":[
        {
            "category":"Autos & Motor Vehicles",
            "subcategory":"Fuel & Gas Station",
            "type":"Retail Goods"
        }
    ],
    "sg:phone":"+1 740 753 2871",
    "sg:postcode":"45764",
    "sg:province":"OH",
    "sg:tags":[
        "station",
        "gasoline"
    ],
    "wof:name":"BP",
    "wof:placetype":"venue"
},
  "geometry": {"coordinates":[-82.22107699999999,39.451048],"type":"Point"}
}