{
  "type": "Feature",
  "properties": {
    "addr:full":"1549 S Breiel Blvd Middletown OH 45044",
    "addr:housenumber":"1549",
    "addr:postcode":"45044",
    "addr:street":"S Breiel Blvd",
    "iso:country":"US",
    "sg:address":"1549 S Breiel Blvd",
    "sg:city":"Middletown",
    "sg:classifiers":[
        {
            "category":"Building & Trades",
            "subcategory":"Cleaning & Sanitation",
            "type":"Services"
        }
    ],
    "sg:phone":"+1 513 423 8999",
    "sg:postcode":"45044",
    "sg:province":"OH",
    "sg:tags":[
        "janitor"
    ],
    "wof:name":"Super Shine Inc",
    "wof:placetype":"venue"
},
  "geometry": {"coordinates":[-84.35563999999999,39.497661],"type":"Point"}
}