{
  "type": "Feature",
  "properties": {
    "addr:full": "1060 Derby Downs Dr Akron OH 44306",
    "addr:housenumber": "1060",
    "addr:postcode": "44306",
    "addr:street": "Derby Downs Dr",
    "iso:country": "US",
    "sg:address": "1060 Derby Downs Dr",
    "sg:city": "Akron",
    "sg:classifiers": [
      {
        "category": "Home \u0026 Garden",
        "subcategory": "Carpets \u0026 Floor Coverings",
        "type": "Retail Goods"
      }
    ],
    "sg:phone": "+1 330 733 4710",
    "sg:postcode": "44306",
    "sg:province": "OH",
    "sg:tags": [
      "hardwood",
      "material"
    ],
    "sg:website": "http://www.buckeyefloorsupply.com",
    "wof:name": "Buckeye Hardwood Floor Supply Inc",
    "wof:placetype": "venue"
  },
  "geometry": {"coordinates":[-81.463242,41.031089],"type":"Point"}
}
