{
  "type": "Feature",
  "properties": {
    "iso:country":"US",
    "sg:address":"3739 Glenmore Ave",
    "sg:city":"Cincinnati",
    "sg:classifiers":[
        {
            "category":"Shopping",
            "subcategory":"Clothing, Apparel, & Fashions",
            "type":"Retail Goods"
        }
    ],
    "sg:phone":"+1 513 662 5400",
    "sg:postcode":"45211",
    "sg:province":"OH",
    "sg:tags":[
        "t"
    ],
    "sg:website":"www.anythingairbrushed.com",
    "wof:name":"Anything Airbrushed Plus",
    "wof:placetype":"venue"
},
  "geometry": {"coordinates":[-84.611216,39.156153],"type":"Point"}
}