{
  "type": "Feature",
  "properties": {
    "iso:country":"US",
    "sg:address":"1440 Passport Ln",
    "sg:city":"Dayton",
    "sg:classifiers":[
        {
            "category":"Real Estate",
            "subcategory":"Real Estate Agent",
            "type":"Services"
        }
    ],
    "sg:phone":"+1 937 264 9200",
    "sg:postcode":"45414",
    "sg:province":"OH",
    "wof:name":"Realty Source Inc",
    "wof:placetype":"venue"
},
  "geometry": {"coordinates":[-84.24105900000001,39.845347],"type":"Point"}
}