{
  "type": "Feature",
  "properties": {
    "addr:full":"1400 S Arlington St Akron OH 44306",
    "addr:housenumber":"1400",
    "addr:postcode":"44306",
    "addr:street":"S Arlington St",
    "iso:country":"US",
    "sg:address":"1400 S Arlington St",
    "sg:city":"Akron",
    "sg:classifiers":[
        {
            "category":"Insurance",
            "subcategory":"Insurance Agent",
            "type":"Services"
        }
    ],
    "sg:phone":"+1 330 724 4994",
    "sg:postcode":"44306",
    "sg:province":"OH",
    "wof:name":"Acceptance Insurance Agency",
    "wof:placetype":"venue"
},
  "geometry": {"coordinates":[-81.49135699999999,41.035419],"type":"Point"}
}