{
  "type": "Feature",
  "properties": {
    "iso:country":"US",
    "sg:address":"4113 Mogadore Rd",
    "sg:city":"Kent",
    "sg:classifiers":[
        {
            "category":"Retail",
            "subcategory":"Auto Repair",
            "type":"Services"
        }
    ],
    "sg:phone":"+1 330 678 0709",
    "sg:postcode":"44240",
    "sg:province":"OH",
    "sg:tags":[
        "muffler",
        "exhaust",
        "system"
    ],
    "wof:name":"Brimfield Muffler",
    "wof:placetype":"venue"
},
  "geometry": {"coordinates":[-81.376874,41.101344],"type":"Point"}
}