{
  "type": "Feature",
  "properties": {
    "addr:full":"1801 Race St Cincinnati OH 45202",
    "addr:housenumber":"1801",
    "addr:postcode":"45202",
    "addr:street":"Race St",
    "iso:country":"US",
    "sg:address":"1801 Race St",
    "sg:city":"Cincinnati",
    "sg:classifiers":[
        {
            "category":"Food & Beverages",
            "subcategory":"Fruits & Vegetables",
            "type":"Retail Goods"
        }
    ],
    "sg:phone":"+1 513 721 2154",
    "sg:postcode":"45202",
    "sg:province":"OH",
    "sg:tags":[
        "produce"
    ],
    "wof:name":"Gaudio Produce",
    "wof:placetype":"venue"
},
  "geometry": {"coordinates":[-84.51835199999999,39.115854],"type":"Point"}
}