{
  "type": "Feature",
  "properties": {
    "addr:full":"212 Blakely St East Liverpool OH 43920",
    "addr:housenumber":"212",
    "addr:postcode":"43920",
    "addr:street":"Blakely St",
    "iso:country":"US",
    "sg:address":"212 Blakely St",
    "sg:city":"East Liverpool",
    "sg:classifiers":[
        {
            "category":"Organizations",
            "subcategory":"Community Association",
            "type":"Services"
        }
    ],
    "sg:phone":"+1 330 385 6632",
    "sg:postcode":"43920",
    "sg:province":"OH",
    "sg:tags":[
        "military"
    ],
    "sg:website":"www.vfw.org",
    "wof:name":"Veterans Of Foreign Wars",
    "wof:placetype":"venue"
},
  "geometry": {"coordinates":[-80.573116,40.618897],"type":"Point"}
}