{
  "type": "Feature",
  "properties": {
    "iso:country":"US",
    "sg:address":"21771 Northwest Pkwy",
    "sg:city":"Marysville",
    "sg:classifiers":[
        {
            "category":"Freight",
            "type":"Transportation"
        }
    ],
    "sg:phone":"+1 937 642 4393",
    "sg:postcode":"43040",
    "sg:province":"OH",
    "sg:tags":[
        "trucking"
    ],
    "wof:name":"Transport International Pool",
    "wof:placetype":"venue"
},
  "geometry": {"coordinates":[-83.468327,40.263013],"type":"Point"}
}