{
  "type": "Feature",
  "properties": {
    "addr:full": "8621 Winton Rd Cincinnati OH 45231",
    "addr:housenumber": "8621",
    "addr:postcode": "45231",
    "addr:street": "Winton Rd",
    "iso:country": "US",
    "sg:address": "8621 Winton Rd",
    "sg:city": "Cincinnati",
    "sg:classifiers": [
      {
        "category": "Food \u0026 Beverages",
        "subcategory": "Meat \u0026 Fish",
        "type": "Retail Goods"
      },
      {
        "category": "Restaurant",
        "type": "Food \u0026 Drink"
      }
    ],
    "sg:phone": "+1 513 522 4443",
    "sg:postcode": "45231",
    "sg:province": "OH",
    "sg:tags": [
      "eating",
      "caterer"
    ],
    "sg:website": "www.schmidtsmeats.com",
    "wof:name": "Schmidt Meats \u0026 Catering Inc",
    "wof:placetype": "venue"
  },
  "geometry": {"coordinates":[-84.516307,39.224703],"type":"Point"}
}
