{
  "type": "Feature",
  "properties": {
    "iso:country":"US",
    "sg:address":"8621 Winton Rd",
    "sg:city":"Cincinnati",
    "sg:classifiers":[
        {
            "category":"Food & Beverages",
            "subcategory":"Meat & Fish",
            "type":"Retail Goods"
        },
        {
            "category":"Restaurant",
            "type":"Food & Drink"
        }
    ],
    "sg:phone":"+1 513 522 4443",
    "sg:postcode":"45231",
    "sg:province":"OH",
    "sg:tags":[
        "eating",
        "caterer"
    ],
    "sg:website":"www.schmidtsmeats.com",
    "wof:name":"Schmidt Meats & Catering Inc",
    "wof:placetype":"venue"
},
  "geometry": {"coordinates":[-84.516307,39.224703],"type":"Point"}
}