{
  "type": "Feature",
  "properties": {
    "addr:full":"421 Industry Dr Columbus OH 43204",
    "addr:housenumber":"421",
    "addr:postcode":"43204",
    "addr:street":"Industry Dr",
    "iso:country":"US",
    "sg:address":"421 Industry Dr",
    "sg:city":"Columbus",
    "sg:classifiers":[
        {
            "category":"Building & Trades",
            "subcategory":"Cleaning & Sanitation",
            "type":"Services"
        }
    ],
    "sg:phone":"+1 614 443 4446",
    "sg:postcode":"43204",
    "sg:province":"OH",
    "sg:tags":[
        "ceiling"
    ],
    "wof:name":"Acousti Care",
    "wof:placetype":"venue"
},
  "geometry": {"coordinates":[-83.08975599999999,39.963476],"type":"Point"}
}