{
  "type": "Feature",
  "properties": {
    "addr:full": "421 Industry Dr Columbus OH 43204",
    "addr:housenumber": "421",
    "addr:postcode": "43204",
    "addr:street": "Industry Dr",
    "iso:country": "US",
    "sg:address": "421 Industry Dr",
    "sg:city": "Columbus",
    "sg:classifiers": [
      {
        "category": "Building \u0026 Trades",
        "subcategory": "Cleaning \u0026 Sanitation",
        "type": "Services"
      }
    ],
    "sg:phone": "+1 614 443 4446",
    "sg:postcode": "43204",
    "sg:province": "OH",
    "sg:tags": [
      "ceiling"
    ],
    "wof:name": "Acousti Care",
    "wof:placetype": "venue"
  },
  "geometry": {"coordinates":[-83.089756,39.963476],"type":"Point"}
}
