{
  "type": "Feature",
  "properties": {
    "addr:full":"419 W Main St Troy OH 45373",
    "addr:housenumber":"419",
    "addr:postcode":"45373",
    "addr:street":"W Main St",
    "iso:country":"US",
    "sg:address":"419 W Main St",
    "sg:city":"Troy",
    "sg:classifiers":[
        {
            "category":"Education",
            "subcategory":"Library",
            "type":"Public Place"
        }
    ],
    "sg:phone":"+1 937 339 0502",
    "sg:postcode":"45373",
    "sg:province":"OH",
    "wof:name":"Troy-Miami Co Public Library",
    "wof:placetype":"venue"
},
  "geometry": {"coordinates":[-84.207194,40.04141],"type":"Point"}
}