{
  "type": "Feature",
  "properties": {
    "iso:country":"US",
    "sg:address":"2000 47th St NE",
    "sg:city":"Canton",
    "sg:classifiers":[
        {
            "category":"Education",
            "subcategory":"School",
            "type":"Public Place"
        }
    ],
    "sg:phone":"+1 330 493 5555",
    "sg:postcode":"44705",
    "sg:province":"OH",
    "sg:tags":[
        "elementary"
    ],
    "wof:name":"Ransom H Barr Elementary Schl",
    "wof:placetype":"venue"
},
  "geometry": {"coordinates":[-81.345001,40.849101],"type":"Point"}
}