{
  "type": "Feature",
  "properties": {
    "addr:full":"4489 Cemetery Rd Hilliard OH 43026",
    "addr:housenumber":"4489",
    "addr:postcode":"43026",
    "addr:street":"Cemetery Rd",
    "iso:country":"US",
    "sg:address":"4489 Cemetery Rd",
    "sg:city":"Hilliard",
    "sg:classifiers":[
        {
            "category":"Food & Beverages",
            "subcategory":"Groceries & Convenience Stores",
            "type":"Retail Goods"
        }
    ],
    "sg:phone":"+1 614 000 1111",
    "sg:postcode":"43026",
    "sg:province":"OH",
    "sg:tags":[
        "grocer"
    ],
    "wof:name":"Aldi",
    "wof:placetype":"venue"
},
  "geometry": {"coordinates":[-83.13577600000001,40.032019],"type":"Point"}
}