{
  "type": "Feature",
  "properties": {
    "addr:full": "4 Wiltshire Blvd Dayton OH 45419",
    "addr:housenumber": "4",
    "addr:postcode": "45419",
    "addr:street": "Wiltshire Blvd",
    "iso:country": "US",
    "sg:address": "4 Wiltshire Blvd",
    "sg:city": "Dayton",
    "sg:classifiers": [
      {
        "category": "Building \u0026 Trades",
        "subcategory": "Construction",
        "type": "Services"
      }
    ],
    "sg:phone": "+1 937 313 3334",
    "sg:postcode": "45419",
    "sg:province": "OH",
    "wof:name": "Water Quality Systems Inc",
    "wof:placetype": "venue"
  },
  "geometry": {"coordinates":[-84.171039,39.714116],"type":"Point"}
}
