{
  "type": "Feature",
  "properties": {
    "addr:full": "630 Oak St Mansfield OH 44907",
    "addr:housenumber": "630",
    "addr:postcode": "44907",
    "addr:street": "Oak St",
    "iso:country": "US",
    "sg:address": "630 Oak St",
    "sg:city": "Mansfield",
    "sg:classifiers": [
      {
        "category": "Real Estate",
        "subcategory": "Real Estate Operator",
        "type": "Services"
      }
    ],
    "sg:phone": "+1 419 526 4591",
    "sg:postcode": "44907",
    "sg:province": "OH",
    "sg:tags": [
      "mobile",
      "home",
      "park"
    ],
    "wof:name": "Greenfield Estates MBL HM Pk",
    "wof:placetype": "venue"
  },
  "geometry": {"coordinates":[-82.48983,40.748177],"type":"Point"}
}
