{
  "type": "Feature",
  "properties": {
    "addr:full": "86 E Elm St Sabina OH 45169",
    "addr:housenumber": "86",
    "addr:postcode": "45169",
    "addr:street": "E Elm St",
    "iso:country": "US",
    "sg:address": "86 E Elm St",
    "sg:city": "Sabina",
    "sg:classifiers": [
      {
        "category": "Personal",
        "subcategory": "Beauty Salon",
        "type": "Services"
      }
    ],
    "sg:phone": "+1 937 584 4085",
    "sg:postcode": "45169",
    "sg:province": "OH",
    "wof:name": "Helene's Hair Salon",
    "wof:placetype": "venue"
  },
  "geometry": {"coordinates":[-83.635084,39.48995],"type":"Point"}
}
