{
  "type": "Feature",
  "properties": {
    "iso:country":"US",
    "sg:address":"86 E Elm St",
    "sg:city":"Sabina",
    "sg:classifiers":[
        {
            "category":"Personal",
            "subcategory":"Beauty Salon",
            "type":"Services"
        }
    ],
    "sg:phone":"+1 937 584 4085",
    "sg:postcode":"45169",
    "sg:province":"OH",
    "wof:name":"Helene's Hair Salon",
    "wof:placetype":"venue"
},
  "geometry": {"coordinates":[-83.63508400000001,39.48995],"type":"Point"}
}