{
  "type": "Feature",
  "properties": {
    "iso:country":"US",
    "sg:address":"2880 N Star Rd",
    "sg:city":"Columbus",
    "sg:classifiers":[
        {
            "category":"Wholesale",
            "subcategory":"Chemicals & Plastics",
            "type":"Manufacturing & Wholesale Goods"
        }
    ],
    "sg:phone":"+1 614 582 6222",
    "sg:postcode":"43221",
    "sg:province":"OH",
    "sg:tags":[
        "blended",
        "product",
        "broker"
    ],
    "wof:name":"Blending Technologies LLC",
    "wof:placetype":"venue"
},
  "geometry": {"coordinates":[-83.048002,40.01595],"type":"Point"}
}