{
  "type": "Feature",
  "properties": {
    "iso:country":"US",
    "sg:address":"2787 Parlin Dr",
    "sg:city":"Grove City",
    "sg:classifiers":[
        {
            "category":"Building & Trades",
            "subcategory":"Electrical",
            "type":"Services"
        }
    ],
    "sg:phone":"+1 614 804 2509",
    "sg:postcode":"43123",
    "sg:province":"OH",
    "sg:tags":[
        "electric",
        "contractor"
    ],
    "wof:name":"A-Bear Electric",
    "wof:placetype":"venue"
},
  "geometry": {"coordinates":[-83.07562799999999,39.895278],"type":"Point"}
}