{
  "type": "Feature",
  "properties": {
    "addr:full": "2787 Parlin Dr Grove City OH 43123",
    "addr:housenumber": "2787",
    "addr:postcode": "43123",
    "addr:street": "Parlin Dr",
    "iso:country": "US",
    "sg:address": "2787 Parlin Dr",
    "sg:city": "Grove City",
    "sg:classifiers": [
      {
        "category": "Building \u0026 Trades",
        "subcategory": "Electrical",
        "type": "Services"
      }
    ],
    "sg:phone": "+1 614 804 2509",
    "sg:postcode": "43123",
    "sg:province": "OH",
    "sg:tags": [
      "electric",
      "contractor"
    ],
    "wof:name": "A-Bear Electric",
    "wof:placetype": "venue"
  },
  "geometry": {"coordinates":[-83.075628,39.895278],"type":"Point"}
}
