{
  "type": "Feature",
  "properties": {
    "iso:country":"US",
    "sg:address":"2460 Wimpole St",
    "sg:city":"Wooster",
    "sg:classifiers":[
        {
            "category":"Banks & Credit Unions",
            "subcategory":"Investment Brokerage",
            "type":"Services"
        }
    ],
    "sg:phone":"+1 330 345 8886",
    "sg:postcode":"44691",
    "sg:province":"OH",
    "sg:tags":[
        "security"
    ],
    "wof:name":"Robert Jaffray Col",
    "wof:placetype":"venue"
},
  "geometry": {"coordinates":[-81.92594200000001,40.828609],"type":"Point"}
}