{
  "type": "Feature",
  "properties": {
    "addr:full": "123 Woodrow Ave St Clairsville OH 43950",
    "addr:housenumber": "123",
    "addr:postcode": "43950",
    "addr:street": "Woodrow Ave",
    "iso:country": "US",
    "sg:address": "123 Woodrow Ave",
    "sg:city": "St Clairsville",
    "sg:classifiers": [
      {
        "category": "Organizations",
        "subcategory": "Religious Organization",
        "type": "Services"
      }
    ],
    "sg:phone": "+1 740 695 2195",
    "sg:postcode": "43950",
    "sg:province": "OH",
    "sg:tags": [
      "church"
    ],
    "wof:name": "First Christian Church",
    "wof:placetype": "venue"
  },
  "geometry": {"coordinates":[-80.903387,40.078812],"type":"Point"}
}
