{
  "type": "Feature",
  "properties": {
    "iso:country":"US",
    "sg:address":"2515 Shiloh Springs Rd",
    "sg:city":"Trotwood",
    "sg:classifiers":[
        {
            "category":"Banks & Credit Unions",
            "subcategory":"Bank",
            "type":"Services"
        }
    ],
    "sg:phone":"+1 937 837 9797",
    "sg:postcode":"45426",
    "sg:province":"OH",
    "sg:tags":[
        "loan"
    ],
    "wof:name":"A Loan Co",
    "wof:placetype":"venue"
},
  "geometry": {"coordinates":[-84.281842,39.818963],"type":"Point"}
}