{
  "type": "Feature",
  "properties": {
    "addr:full": "2515 Shiloh Springs Rd Trotwood OH 45426",
    "addr:housenumber": "2515",
    "addr:postcode": "45426",
    "addr:street": "Shiloh Springs Rd",
    "iso:country": "US",
    "sg:address": "2515 Shiloh Springs Rd",
    "sg:city": "Trotwood",
    "sg:classifiers": [
      {
        "category": "Banks \u0026 Credit Unions",
        "subcategory": "Bank",
        "type": "Services"
      }
    ],
    "sg:phone": "+1 937 837 9797",
    "sg:postcode": "45426",
    "sg:province": "OH",
    "sg:tags": [
      "loan"
    ],
    "wof:name": "A Loan Co",
    "wof:placetype": "venue"
  },
  "geometry": {"coordinates":[-84.281842,39.818963],"type":"Point"}
}
