{
  "type": "Feature",
  "properties": {
    "iso:country":"US",
    "sg:address":"158 S Main St",
    "sg:city":"Chagrin Falls",
    "sg:classifiers":[
        {
            "category":"Professional",
            "subcategory":"Business Services",
            "type":"Services"
        }
    ],
    "sg:phone":"+1 440 247 2822",
    "sg:postcode":"44022",
    "sg:province":"OH",
    "sg:tags":[
        "disposal",
        "reduction",
        "waste"
    ],
    "wof:name":"Waste Organizer",
    "wof:placetype":"venue"
},
  "geometry": {"coordinates":[-81.38888,41.426395],"type":"Point"}
}