{
  "type": "Feature",
  "properties": {
    "addr:full": "1381 W 3rd Ave Columbus OH 43212",
    "addr:housenumber": "1381",
    "addr:postcode": "43212",
    "addr:street": "W 3Rd Ave",
    "iso:country": "US",
    "sg:address": "1381 W 3rd Ave",
    "sg:city": "Columbus",
    "sg:classifiers": [
      {
        "category": "Autos \u0026 Motor Vehicles",
        "subcategory": "Automobile Sales",
        "type": "Retail Goods"
      }
    ],
    "sg:phone": "+1 614 488 4510",
    "sg:postcode": "43212",
    "sg:province": "OH",
    "sg:tags": [
      "car",
      "dealer"
    ],
    "wof:name": "Third Avenue Auto Svc",
    "wof:placetype": "venue"
  },
  "geometry": {"coordinates":[-83.042002,39.984911],"type":"Point"}
}
