{
  "type": "Feature",
  "properties": {
    "addr:full":"1619 Burney Ln Cincinnati OH 45230",
    "addr:housenumber":"1619",
    "addr:postcode":"45230",
    "addr:street":"Burney Ln",
    "iso:country":"US",
    "sg:address":"1619 Burney Ln",
    "sg:city":"Cincinnati",
    "sg:classifiers":[
        {
            "category":"Health Services",
            "subcategory":"Clinic",
            "type":"Services"
        }
    ],
    "sg:phone":"+1 513 509 4463",
    "sg:postcode":"45230",
    "sg:province":"OH",
    "wof:name":"Jack Daniel & Assoc",
    "wof:placetype":"venue"
},
  "geometry": {"coordinates":[-84.374639,39.083038],"type":"Point"}
}