{
  "type": "Feature",
  "properties": {
    "addr:full": "2320 S High St Columbus OH 43207",
    "addr:housenumber": "2320",
    "addr:postcode": "43207",
    "addr:street": "S High St",
    "iso:country": "US",
    "sg:address": "2320 S High St",
    "sg:city": "Columbus",
    "sg:classifiers": [
      {
        "category": "Autos \u0026 Motor Vehicles",
        "subcategory": "Automobile Sales",
        "type": "Retail Goods"
      }
    ],
    "sg:phone": "+1 614 445 6886",
    "sg:postcode": "43207",
    "sg:province": "OH",
    "sg:tags": [
      "car",
      "dealer"
    ],
    "wof:name": "Buy For Less Motors",
    "wof:placetype": "venue"
  },
  "geometry": {"coordinates":[-82.99528,39.913199],"type":"Point"}
}
