{
  "type": "Feature",
  "properties": {
    "iso:country":"US",
    "sg:address":"51 Public Sq",
    "sg:city":"Mt Vernon",
    "sg:classifiers":[
        {
            "category":"Real Estate",
            "subcategory":"Real Estate Services",
            "type":"Services"
        }
    ],
    "sg:phone":"+1 740 393 2900",
    "sg:postcode":"43050",
    "sg:province":"OH",
    "sg:tags":[
        "company",
        "title"
    ],
    "wof:name":"Land America Lawyers Title",
    "wof:placetype":"venue"
},
  "geometry": {"coordinates":[-82.48539100000001,40.394031],"type":"Point"}
}