{
  "type": "Feature",
  "properties": {
    "addr:full": "51 Public Sq Mt Vernon OH 43050",
    "addr:housenumber": "51",
    "addr:postcode": "43050",
    "addr:street": "Public Sq",
    "iso:country": "US",
    "sg:address": "51 Public Sq",
    "sg:city": "Mt Vernon",
    "sg:classifiers": [
      {
        "category": "Real Estate",
        "subcategory": "Real Estate Services",
        "type": "Services"
      }
    ],
    "sg:phone": "+1 740 393 2900",
    "sg:postcode": "43050",
    "sg:province": "OH",
    "sg:tags": [
      "company",
      "title"
    ],
    "wof:name": "Land America Lawyers Title",
    "wof:placetype": "venue"
  },
  "geometry": {"coordinates":[-82.485391,40.394031],"type":"Point"}
}
