{
  "type": "Feature",
  "properties": {
    "iso:country":"US",
    "sg:address":"4400 Columbus-Sandusky Rd N",
    "sg:city":"Marion",
    "sg:classifiers":[
        {
            "category":"Farming",
            "subcategory":"Farm",
            "type":"Manufacturing & Wholesale Goods"
        }
    ],
    "sg:phone":"+1 740 726 2519",
    "sg:postcode":"43302",
    "sg:province":"OH",
    "sg:tags":[
        "crop",
        "general"
    ],
    "wof:name":"Leo Lawson",
    "wof:placetype":"venue"
},
  "geometry": {"coordinates":[-83.011314,40.678725],"type":"Point"}
}