{
  "type": "Feature",
  "properties": {
    "addr:full": "645 Lafayette Rd Medina OH 44256",
    "addr:housenumber": "645",
    "addr:postcode": "44256",
    "addr:street": "Rd",
    "iso:country": "US",
    "sg:address": "645 Lafayette Rd",
    "sg:city": "Medina",
    "sg:classifiers": [
      {
        "category": "Building \u0026 Trades",
        "subcategory": "Plumbing",
        "type": "Services"
      }
    ],
    "sg:phone": "+1 330 723 4840",
    "sg:postcode": "44256",
    "sg:province": "OH",
    "sg:tags": [
      "plumbing",
      "heating",
      "contractor"
    ],
    "wof:name": "Swingle Mechanical Contractors",
    "wof:placetype": "venue"
  },
  "geometry": {"coordinates":[-81.87617,41.130329],"type":"Point"}
}
