{
  "type": "Feature",
  "properties": {
    "addr:full": "145 N Glenellen Ave Youngstown OH 44509",
    "addr:housenumber": "145",
    "addr:postcode": "44509",
    "addr:street": "N Glenellen Ave",
    "iso:country": "US",
    "sg:address": "145 N Glenellen Ave",
    "sg:city": "Youngstown",
    "sg:classifiers": [
      {
        "category": "Social Services",
        "subcategory": "Job Training",
        "type": "Services"
      },
      {
        "category": "Autos \u0026 Motor Vehicles",
        "subcategory": "Auto Supplies",
        "type": "Retail Goods"
      }
    ],
    "sg:phone": "+1 330 799 4594",
    "sg:postcode": "44509",
    "sg:province": "OH",
    "sg:tags": [
      "wheel",
      "cover"
    ],
    "wof:name": "Potter's Wheel",
    "wof:placetype": "venue"
  },
  "geometry": {"coordinates":[-80.701069,41.107005],"type":"Point"}
}
