{
  "type": "Feature",
  "properties": {
    "iso:country":"US",
    "sg:address":"145 N Glenellen Ave",
    "sg:city":"Youngstown",
    "sg:classifiers":[
        {
            "category":"Social Services",
            "subcategory":"Job Training",
            "type":"Services"
        },
        {
            "category":"Autos & Motor Vehicles",
            "subcategory":"Auto Supplies",
            "type":"Retail Goods"
        }
    ],
    "sg:phone":"+1 330 799 4594",
    "sg:postcode":"44509",
    "sg:province":"OH",
    "sg:tags":[
        "wheel",
        "cover"
    ],
    "wof:name":"Potter's Wheel",
    "wof:placetype":"venue"
},
  "geometry": {"coordinates":[-80.701069,41.107005],"type":"Point"}
}