{
  "type": "Feature",
  "properties": {
    "iso:country":"US",
    "sg:address":"2725 New Washington Rd",
    "sg:city":"Bloomville",
    "sg:phone":"+1 419 284 3737",
    "sg:postcode":"44818",
    "sg:province":"OH",
    "sg:tags":[
        "farm",
        "corn",
        "soybean"
    ],
    "wof:name":"Harer Brothers Farms",
    "wof:placetype":"venue"
},
  "geometry": {"coordinates":[-82.982562,40.964779],"type":"Point"}
}