{
  "type": "Feature",
  "properties": {
    "iso:country":"US",
    "sg:address":"1480 Zettler Rd",
    "sg:city":"Columbus",
    "sg:classifiers":[
        {
            "category":"Organizations",
            "subcategory":"Religious Organization",
            "type":"Services"
        }
    ],
    "sg:phone":"+1 614 231 4568",
    "sg:postcode":"43227",
    "sg:province":"OH",
    "sg:website":"www.christumccol.org",
    "wof:name":"Christ United Methodist Church",
    "wof:placetype":"venue"
},
  "geometry": {"coordinates":[-82.91098,39.941176],"type":"Point"}
}