{
  "type": "Feature",
  "properties": {
    "addr:full": "407 E 5th St Dover OH 44622",
    "addr:housenumber": "407",
    "addr:postcode": "44622",
    "addr:street": "E 5Th St",
    "iso:country": "US",
    "sg:address": "407 E 5th St",
    "sg:city": "Dover",
    "sg:classifiers": [
      {
        "category": "Retail",
        "subcategory": "Auto Repair",
        "type": "Services"
      }
    ],
    "sg:phone": "+1 330 602 4323",
    "sg:postcode": "44622",
    "sg:province": "OH",
    "sg:tags": [
      "repairing",
      "automobile"
    ],
    "wof:name": "Mike Walters Garage",
    "wof:placetype": "venue"
  },
  "geometry": {"coordinates":[-81.474699,40.527485],"type":"Point"}
}
