{
  "type": "Feature",
  "properties": {
    "addr:full":"4300 Duck Creek Rd Apt 8 Cincinnati OH 45227",
    "addr:housenumber":"4300;8",
    "addr:postcode":"45227",
    "addr:street":"Duck Creek Rd Apt",
    "iso:country":"US",
    "sg:address":"4300 Duck Creek Rd Apt 8",
    "sg:city":"Cincinnati",
    "sg:classifiers":[
        {
            "category":"Real Estate",
            "subcategory":"Real Estate Operator",
            "type":"Services"
        }
    ],
    "sg:phone":"+1 513 731 8915",
    "sg:postcode":"45227",
    "sg:province":"OH",
    "sg:tags":[
        "apartment"
    ],
    "sg:website":"http://www.fathproperties.com",
    "wof:name":"Lindsay Lane Apartments",
    "wof:placetype":"venue"
},
  "geometry": {"coordinates":[-84.415175,39.165211],"type":"Point"}
}