{
  "type": "Feature",
  "properties": {
    "addr:full":"131 N Ludlow St Dayton OH 45402",
    "addr:housenumber":"131",
    "addr:postcode":"45402",
    "addr:street":"N Ludlow St",
    "iso:country":"US",
    "sg:address":"131 N Ludlow St",
    "sg:city":"Dayton",
    "sg:classifiers":[
        {
            "category":"Professional",
            "subcategory":"Employment Agencies",
            "type":"Services"
        }
    ],
    "sg:phone":"+1 937 228 3954",
    "sg:postcode":"45402",
    "sg:province":"OH",
    "sg:tags":[
        "opportunity"
    ],
    "wof:name":"Adecco",
    "wof:placetype":"venue"
},
  "geometry": {"coordinates":[-84.19419000000001,39.760903],"type":"Point"}
}