{
  "type": "Feature",
  "properties": {
    "addr:full":"904 Tod Ave Youngstown OH 44502",
    "addr:housenumber":"904",
    "addr:postcode":"44502",
    "addr:street":"Tod Ave",
    "iso:country":"US",
    "sg:address":"904 Tod Ave",
    "sg:city":"Youngstown",
    "sg:classifiers":[
        {
            "category":"Manufacturing",
            "subcategory":"Furniture",
            "type":"Manufacturing & Wholesale Goods"
        }
    ],
    "sg:phone":"+1 330 747 0181",
    "sg:postcode":"44502",
    "sg:province":"OH",
    "sg:tags":[
        "building",
        "public",
        "mfg"
    ],
    "wof:name":"Quality Seating",
    "wof:placetype":"venue"
},
  "geometry": {"coordinates":[-80.66886100000001,41.102904],"type":"Point"}
}