{
  "type": "Feature",
  "properties": {
    "iso:country":"US",
    "sg:address":"2104 Jennifer St",
    "sg:city":"Akron",
    "sg:classifiers":[
        {
            "category":"Real Estate",
            "subcategory":"Real Estate Agent",
            "type":"Services"
        }
    ],
    "sg:phone":"+1 330 865 9235",
    "sg:postcode":"44313",
    "sg:province":"OH",
    "wof:name":"Cew Real Estate",
    "wof:placetype":"venue"
},
  "geometry": {"coordinates":[-81.585691,41.139158],"type":"Point"}
}