{
  "type": "Feature",
  "properties": {
    "addr:full": "9 Plato Ln Akron OH 44301",
    "addr:housenumber": "9",
    "addr:postcode": "44301",
    "addr:street": "Plato Ln",
    "iso:country": "US",
    "sg:address": "9 Plato Ln",
    "sg:city": "Akron",
    "sg:classifiers": [
      {
        "category": "Social Services",
        "subcategory": "Child Care",
        "type": "Services"
      }
    ],
    "sg:phone": "+1 330 535 8144",
    "sg:postcode": "44301",
    "sg:province": "OH",
    "wof:name": "Akron Summit Community Action",
    "wof:placetype": "venue"
  },
  "geometry": {"coordinates":[-81.543392,41.054808],"type":"Point"}
}
