{
  "type": "Feature",
  "properties": {
    "addr:full": "3070 Riverside Dr Columbus OH 43221",
    "addr:housenumber": "3070",
    "addr:postcode": "43221",
    "addr:street": "Riverside Dr",
    "iso:country": "US",
    "sg:address": "3070 Riverside Dr",
    "sg:city": "Columbus",
    "sg:classifiers": [
      {
        "category": "Organizations",
        "subcategory": "Professional Association",
        "type": "Services"
      }
    ],
    "sg:phone": "+1 614 481 8558",
    "sg:postcode": "43221",
    "sg:province": "OH",
    "sg:tags": [
      "business",
      "trade"
    ],
    "wof:name": "Central Ohio Chapter",
    "wof:placetype": "venue"
  },
  "geometry": {"coordinates":[-83.090764,40.016262],"type":"Point"}
}
