{
  "type": "Feature",
  "properties": {
    "iso:country":"US",
    "sg:address":"25 S Mulberry St",
    "sg:city":"Mansfield",
    "sg:classifiers":[
        {
            "category":"Personal",
            "subcategory":"Beauty Salon",
            "type":"Services"
        }
    ],
    "sg:phone":"+1 419 522 0623",
    "sg:postcode":"44902",
    "sg:province":"OH",
    "wof:name":"Jaimes Hair Suppies",
    "wof:placetype":"venue"
},
  "geometry": {"coordinates":[-82.517973,40.757708],"type":"Point"}
}