{
  "type": "Feature",
  "properties": {
    "addr:full":"8589 Columbus Pike Lewis Center OH 43035",
    "addr:housenumber":"8589",
    "addr:postcode":"43035",
    "addr:street":"Columbus Pike",
    "iso:country":"US",
    "sg:address":"8589 Columbus Pike",
    "sg:city":"Lewis Center",
    "sg:classifiers":[
        {
            "category":"Retail",
            "subcategory":"Laundry & Dry Cleaning",
            "type":"Services"
        }
    ],
    "sg:phone":"+1 740 657 1997",
    "sg:postcode":"43035",
    "sg:province":"OH",
    "sg:tags":[
        "cleaners"
    ],
    "wof:name":"Swan Cleaners",
    "wof:placetype":"venue"
},
  "geometry": {"coordinates":[-83.01986599999999,40.165561],"type":"Point"}
}