{
  "type": "Feature",
  "properties": {
    "iso:country":"US",
    "sg:address":"101 2nd Ave",
    "sg:city":"Chesapeake",
    "sg:classifiers":[
        {
            "category":"Professional",
            "subcategory":"Computer Services",
            "type":"Services"
        }
    ],
    "sg:phone":"+1 740 867 0461",
    "sg:postcode":"45619",
    "sg:province":"OH",
    "sg:tags":[
        "repair"
    ],
    "wof:name":"OCR Computers",
    "wof:placetype":"venue"
},
  "geometry": {"coordinates":[-82.45075199999999,38.428303],"type":"Point"}
}