{
  "type": "Feature",
  "properties": {
    "addr:full": "5100 Friendsville Rd Wooster OH 44691",
    "addr:housenumber": "5100",
    "addr:postcode": "44691",
    "addr:street": "Friendsville Rd",
    "iso:country": "US",
    "sg:address": "5100 Friendsville Rd",
    "sg:city": "Wooster",
    "sg:phone": "+1 330 345 6121",
    "sg:postcode": "44691",
    "sg:province": "OH",
    "sg:tags": [
      "farm",
      "corn",
      "soybean"
    ],
    "wof:name": "Stewart J Mc Coy",
    "wof:placetype": "venue"
  },
  "geometry": {"coordinates":[-81.944045,40.861396],"type":"Point"}
}
