{
  "type": "Feature",
  "properties": {
    "addr:full": "2721 Shawnee Rd Lima OH 45806",
    "addr:housenumber": "2721",
    "addr:postcode": "45806",
    "addr:street": "Shawnee Rd",
    "iso:country": "US",
    "sg:address": "2721 Shawnee Rd",
    "sg:city": "Lima",
    "sg:classifiers": [
      {
        "category": "Health Services",
        "subcategory": "Doctor",
        "type": "Services"
      }
    ],
    "sg:phone": "+1 419 225 4751",
    "sg:postcode": "45806",
    "sg:province": "OH",
    "sg:tags": [
      "dentist"
    ],
    "wof:name": "Charles L Butts II Inc",
    "wof:placetype": "venue"
  },
  "geometry": {"coordinates":[-84.151317,40.70081],"type":"Point"}
}
