{
  "type": "Feature",
  "properties": {
    "addr:full": "28926 Euclid Ave Wickliffe OH 44092",
    "addr:housenumber": "28926",
    "addr:postcode": "44092",
    "addr:street": "Euclid Ave",
    "iso:country": "US",
    "sg:address": "28926 Euclid Ave",
    "sg:city": "Wickliffe",
    "sg:classifiers": [
      {
        "category": "Food \u0026 Beverages",
        "subcategory": "Groceries \u0026 Convenience Stores",
        "type": "Retail Goods"
      }
    ],
    "sg:phone": "+1 440 516 1985",
    "sg:postcode": "44092",
    "sg:province": "OH",
    "wof:name": "Wickliffe Food Mart",
    "wof:placetype": "venue"
  },
  "geometry": {"coordinates":[-81.479728,41.601928],"type":"Point"}
}
