{
  "type": "Feature",
  "properties": {
    "addr:full":"414 Broad View Ct Pataskala OH 43062",
    "addr:housenumber":"414",
    "addr:postcode":"43062",
    "addr:street":"Broad View Ct",
    "iso:country":"US",
    "sg:address":"414 Broad View Ct",
    "sg:city":"Pataskala",
    "sg:classifiers":[
        {
            "category":"Building & Trades",
            "subcategory":"Cleaning & Sanitation",
            "type":"Services"
        }
    ],
    "sg:phone":"+1 740 964 9697",
    "sg:postcode":"43062",
    "sg:province":"OH",
    "sg:tags":[
        "janitor"
    ],
    "wof:name":"Excel Cleaning Svc",
    "wof:placetype":"venue"
},
  "geometry": {"coordinates":[-82.681521,40.012412],"type":"Point"}
}