{
  "type": "Feature",
  "properties": {
    "iso:country":"US",
    "sg:address":"8658 Tyler Blvd",
    "sg:city":"Mentor",
    "sg:classifiers":[
        {
            "category":"Manufacturing",
            "subcategory":"Tools & Machinery",
            "type":"Manufacturing & Wholesale Goods"
        }
    ],
    "sg:phone":"+1 440 205 1600",
    "sg:postcode":"44060",
    "sg:province":"OH",
    "sg:tags":[
        "industrial",
        "mfg"
    ],
    "wof:name":"SSC Controls Company",
    "wof:placetype":"venue"
},
  "geometry": {"coordinates":[-81.327755,41.689513],"type":"Point"}
}