{
  "type": "Feature",
  "properties": {
    "addr:full":"120 W Jackson St West Unity OH 43570",
    "addr:housenumber":"120",
    "addr:postcode":"43570",
    "addr:street":"W Jackson St",
    "iso:country":"US",
    "sg:address":"120 W Jackson St",
    "sg:city":"West Unity",
    "sg:classifiers":[
        {
            "category":"Organizations",
            "subcategory":"Community Association",
            "type":"Services"
        }
    ],
    "sg:phone":"+1 419 924 2375",
    "sg:postcode":"43570",
    "sg:province":"OH",
    "sg:tags":[
        "military"
    ],
    "wof:name":"American Legion",
    "wof:placetype":"venue"
},
  "geometry": {"coordinates":[-84.43459199999999,41.58657],"type":"Point"}
}