{
  "type": "Feature",
  "properties": {
    "addr:full":"2901 Parklane St NW Canton OH 44709",
    "addr:housenumber":"2901",
    "addr:postcode":"44709",
    "addr:street":"Parklane St Nw",
    "iso:country":"US",
    "sg:address":"2901 Parklane St NW",
    "sg:city":"Canton",
    "sg:classifiers":[
        {
            "category":"Real Estate",
            "subcategory":"Real Estate Operator",
            "type":"Services"
        }
    ],
    "sg:phone":"+1 330 499 7241",
    "sg:postcode":"44709",
    "sg:province":"OH",
    "sg:tags":[
        "building",
        "apartment"
    ],
    "wof:name":"Woodside Terrace Apartments",
    "wof:placetype":"venue"
},
  "geometry": {"coordinates":[-81.40456399999999,40.850066],"type":"Point"}
}