{
  "type": "Feature",
  "properties": {
    "iso:country":"US",
    "sg:address":"480 Main St",
    "sg:city":"Groveport",
    "sg:classifiers":[
        {
            "category":"Retail",
            "subcategory":"Portrait Studio",
            "type":"Services"
        }
    ],
    "sg:phone":"+1 614 836 3786",
    "sg:postcode":"43125",
    "sg:province":"OH",
    "sg:tags":[
        "photographer"
    ],
    "wof:name":"Gray's Image Gallery",
    "wof:placetype":"venue"
},
  "geometry": {"coordinates":[-82.887225,39.852132],"type":"Point"}
}