{
  "type": "Feature",
  "properties": {
    "iso:country":"US",
    "sg:address":"8215 Cornell Rd",
    "sg:city":"Cincinnati",
    "sg:classifiers":[
        {
            "category":"Professional",
            "subcategory":"Computer Services",
            "type":"Services"
        }
    ],
    "sg:phone":"+1 513 489 4678",
    "sg:postcode":"45249",
    "sg:province":"OH",
    "sg:tags":[
        "website",
        "design"
    ],
    "wof:name":"Missions Communication",
    "wof:placetype":"venue"
},
  "geometry": {"coordinates":[-84.337296,39.264708],"type":"Point"}
}