{
  "type": "Feature",
  "properties": {
    "addr:full": "12909 Westchester Rd Pickerington OH 43147",
    "addr:housenumber": "12909",
    "addr:postcode": "43147",
    "addr:street": "Westchester Rd",
    "iso:country": "US",
    "sg:address": "12909 Westchester Rd",
    "sg:city": "Pickerington",
    "sg:classifiers": [
      {
        "category": "Professional",
        "type": "Services"
      }
    ],
    "sg:phone": "+1 614 861 0622",
    "sg:postcode": "43147",
    "sg:province": "OH",
    "wof:name": "AG Perspectives Co",
    "wof:placetype": "venue"
  },
  "geometry": {"coordinates":[-82.763304,39.920448],"type":"Point"}
}
