{
  "type": "Feature",
  "properties": {
    "iso:country":"US",
    "sg:address":"14090 Ridge Rd",
    "sg:city":"Cleveland",
    "sg:classifiers":[
        {
            "category":"Organizations",
            "subcategory":"Religious Organization",
            "type":"Services"
        }
    ],
    "sg:phone":"+1 440 230 2789",
    "sg:postcode":"44133",
    "sg:province":"OH",
    "sg:tags":[
        "church"
    ],
    "wof:name":"Church On The Summit",
    "wof:placetype":"venue"
},
  "geometry": {"coordinates":[-81.734739,41.311737],"type":"Point"}
}