{
  "type": "Feature",
  "properties": {
    "addr:full":"12511 Detroit Ave Lakewood OH 44107",
    "addr:housenumber":"12511",
    "addr:postcode":"44107",
    "addr:street":"Detroit Ave",
    "iso:country":"US",
    "sg:address":"12511 Detroit Ave",
    "sg:city":"Lakewood",
    "sg:classifiers":[
        {
            "category":"Autos & Motor Vehicles",
            "subcategory":"Fuel & Gas Station",
            "type":"Retail Goods"
        }
    ],
    "sg:phone":"+1 216 227 9863",
    "sg:postcode":"44107",
    "sg:province":"OH",
    "sg:tags":[
        "station",
        "gasoline"
    ],
    "wof:name":"U-Haul",
    "wof:placetype":"venue"
},
  "geometry": {"coordinates":[-81.775941,41.484173],"type":"Point"}
}