{
  "type": "Feature",
  "properties": {
    "addr:full":"601 W Main St Batavia OH 45103",
    "addr:housenumber":"601",
    "addr:postcode":"45103",
    "addr:street":"W Main St",
    "iso:country":"US",
    "sg:address":"601 W Main St",
    "sg:city":"Batavia",
    "sg:classifiers":[
        {
            "category":"Bars & Pubs",
            "type":"Food & Drink"
        }
    ],
    "sg:phone":"+1 513 732 6427",
    "sg:postcode":"45103",
    "sg:province":"OH",
    "sg:tags":[
        "drinking"
    ],
    "wof:name":"Short Stop Drive Thru",
    "wof:placetype":"venue"
},
  "geometry": {"coordinates":[-84.18753599999999,39.082108],"type":"Point"}
}