{
  "type": "Feature",
  "properties": {
    "addr:full": "601 W Main St Batavia OH 45103",
    "addr:housenumber": "601",
    "addr:postcode": "45103",
    "addr:street": "W Main St",
    "iso:country": "US",
    "sg:address": "601 W Main St",
    "sg:city": "Batavia",
    "sg:classifiers": [
      {
        "category": "Bars \u0026 Pubs",
        "type": "Food \u0026 Drink"
      }
    ],
    "sg:phone": "+1 513 732 6427",
    "sg:postcode": "45103",
    "sg:province": "OH",
    "sg:tags": [
      "drinking"
    ],
    "wof:name": "Short Stop Drive Thru",
    "wof:placetype": "venue"
  },
  "geometry": {"coordinates":[-84.187536,39.082108],"type":"Point"}
}
