{
  "type": "Feature",
  "properties": {
    "addr:full":"2936 Lagrange St Toledo OH 43608",
    "addr:housenumber":"2936",
    "addr:postcode":"43608",
    "addr:street":"Lagrange St",
    "iso:country":"US",
    "sg:address":"2936 Lagrange St",
    "sg:city":"Toledo",
    "sg:classifiers":[
        {
            "category":"Professional",
            "subcategory":"Accounting & Tax Preparation",
            "type":"Services"
        }
    ],
    "sg:phone":"+1 419 727 1222",
    "sg:postcode":"43608",
    "sg:province":"OH",
    "sg:tags":[
        "return",
        "filing"
    ],
    "wof:name":"Jackson Hewitt Tax Svc",
    "wof:placetype":"venue"
},
  "geometry": {"coordinates":[-83.540183,41.678177],"type":"Point"}
}