{
  "type": "Feature",
  "properties": {
    "iso:country":"US",
    "sg:address":"3265 W Market St",
    "sg:city":"Fairlawn",
    "sg:classifiers":[
        {
            "category":"Utilities",
            "subcategory":"Mobile Phone",
            "type":"Services"
        }
    ],
    "sg:phone":"+1 330 867 4911",
    "sg:postcode":"44333",
    "sg:province":"OH",
    "sg:tags":[
        "telephone",
        "cellular"
    ],
    "wof:name":"Wireless 4U Inc",
    "wof:placetype":"venue"
},
  "geometry": {"coordinates":[-81.618917,41.132495],"type":"Point"}
}