{
  "type": "Feature",
  "properties": {
    "iso:country":"US",
    "sg:address":"43 Northwood Dr",
    "sg:city":"Delaware",
    "sg:classifiers":[
        {
            "category":"Health Services",
            "subcategory":"Medical Lab",
            "type":"Services"
        }
    ],
    "sg:phone":"+1 740 369 3542",
    "sg:postcode":"43015",
    "sg:province":"OH",
    "sg:tags":[
        "laboratory"
    ],
    "wof:name":"Laboratory Corp Of America",
    "wof:placetype":"venue"
},
  "geometry": {"coordinates":[-83.086304,40.307173],"type":"Point"}
}