{
  "type": "Feature",
  "properties": {
    "addr:full": "715 N Mantua St Kent OH 44240",
    "addr:housenumber": "715",
    "addr:postcode": "44240",
    "addr:street": "N Mantua St",
    "iso:country": "US",
    "sg:address": "715 N Mantua St",
    "sg:city": "Kent",
    "sg:classifiers": [
      {
        "category": "Personal",
        "subcategory": "Beauty Salon",
        "type": "Services"
      }
    ],
    "sg:phone": "+1 330 676 9663",
    "sg:postcode": "44240",
    "sg:province": "OH",
    "wof:name": "Trend Zone",
    "wof:placetype": "venue"
  },
  "geometry": {"coordinates":[-81.359458,41.159212],"type":"Point"}
}
