{
  "type": "Feature",
  "properties": {
    "addr:full":"56 Milford Dr Hudson OH 44236",
    "addr:housenumber":"56",
    "addr:postcode":"44236",
    "addr:street":"Milford Dr",
    "iso:country":"US",
    "sg:address":"56 Milford Dr",
    "sg:city":"Hudson",
    "sg:classifiers":[
        {
            "category":"Banks & Credit Unions",
            "subcategory":"Investment Brokerage",
            "type":"Services"
        }
    ],
    "sg:phone":"+1 330 342 8435",
    "sg:postcode":"44236",
    "sg:province":"OH",
    "sg:tags":[
        "security"
    ],
    "wof:name":"Charles Schwab",
    "wof:placetype":"venue"
},
  "geometry": {"coordinates":[-81.447992,41.237755],"type":"Point"}
}