{
  "type": "Feature",
  "properties": {
    "iso:country":"US",
    "sg:address":"1461 Summit St",
    "sg:city":"Columbus",
    "sg:classifiers":[
        {
            "category":"Wholesale",
            "subcategory":"Electrical",
            "type":"Manufacturing & Wholesale Goods"
        }
    ],
    "sg:phone":"+1 614 424 6730",
    "sg:postcode":"43201",
    "sg:province":"OH",
    "sg:tags":[
        "control",
        "security",
        "system"
    ],
    "wof:name":"All Secured Security Svc",
    "wof:placetype":"venue"
},
  "geometry": {"coordinates":[-83.001723,39.992603],"type":"Point"}
}