{
  "type": "Feature",
  "properties": {
    "addr:full": "1461 Summit St Columbus OH 43201",
    "addr:housenumber": "1461",
    "addr:postcode": "43201",
    "addr:street": "Summit St",
    "iso:country": "US",
    "sg:address": "1461 Summit St",
    "sg:city": "Columbus",
    "sg:classifiers": [
      {
        "category": "Wholesale",
        "subcategory": "Electrical",
        "type": "Manufacturing \u0026 Wholesale Goods"
      }
    ],
    "sg:phone": "+1 614 424 6730",
    "sg:postcode": "43201",
    "sg:province": "OH",
    "sg:tags": [
      "control",
      "security",
      "system"
    ],
    "wof:name": "All Secured Security Svc",
    "wof:placetype": "venue"
  },
  "geometry": {"coordinates":[-83.001723,39.992603],"type":"Point"}
}
