{
  "type": "Feature",
  "properties": {
    "addr:full": "622 W 58th St Ashtabula OH 44004",
    "addr:housenumber": "622",
    "addr:postcode": "44004",
    "addr:street": "W 58Th St",
    "iso:country": "US",
    "sg:address": "622 W 58th St",
    "sg:city": "Ashtabula",
    "sg:classifiers": [
      {
        "category": "Organizations",
        "subcategory": "Religious Organization",
        "type": "Services"
      }
    ],
    "sg:phone": "+1 440 992 4417",
    "sg:postcode": "44004",
    "sg:province": "OH",
    "sg:tags": [
      "church"
    ],
    "wof:name": "Child Evangelism Fellowship",
    "wof:placetype": "venue"
  },
  "geometry": {"coordinates":[-80.789628,41.855146],"type":"Point"}
}
