{
  "type": "Feature",
  "properties": {
    "iso:country":"US",
    "sg:address":"3946 E Harbor Rd",
    "sg:city":"Port Clinton",
    "sg:classifiers":[
        {
            "category":"Restaurant",
            "type":"Food & Drink"
        }
    ],
    "sg:phone":"+1 419 732 6443",
    "sg:postcode":"43452",
    "sg:province":"OH",
    "sg:tags":[
        "eating"
    ],
    "wof:name":"Hanzels Ice Cream",
    "wof:placetype":"venue"
},
  "geometry": {"coordinates":[-82.856317,41.524489],"type":"Point"}
}