{
  "type": "Feature",
  "properties": {
    "iso:country":"US",
    "sg:address":"17383 Foltz Industrial Pkwy",
    "sg:city":"Strongsville",
    "sg:classifiers":[
        {
            "category":"Manufacturing",
            "subcategory":"Tools & Machinery",
            "type":"Manufacturing & Wholesale Goods"
        }
    ],
    "sg:phone":"+1 440 572 5130",
    "sg:postcode":"44149",
    "sg:province":"OH",
    "sg:tags":[
        "shop",
        "repair",
        "industrial",
        "mfg",
        "machine",
        "welding"
    ],
    "wof:name":"K & M Tool & Machine Co",
    "wof:placetype":"venue"
},
  "geometry": {"coordinates":[-81.869654,41.293728],"type":"Point"}
}