{
  "type": "Feature",
  "properties": {
    "addr:full": "17383 Foltz Industrial Pkwy Strongsville OH 44149",
    "addr:housenumber": "17383",
    "addr:postcode": "44149",
    "addr:street": "Foltz Industrial Pkwy",
    "iso:country": "US",
    "sg:address": "17383 Foltz Industrial Pkwy",
    "sg:city": "Strongsville",
    "sg:classifiers": [
      {
        "category": "Manufacturing",
        "subcategory": "Tools \u0026 Machinery",
        "type": "Manufacturing \u0026 Wholesale Goods"
      }
    ],
    "sg:phone": "+1 440 572 5130",
    "sg:postcode": "44149",
    "sg:province": "OH",
    "sg:tags": [
      "shop",
      "repair",
      "industrial",
      "mfg",
      "machine",
      "welding"
    ],
    "wof:name": "K \u0026 M Tool \u0026 Machine Co",
    "wof:placetype": "venue"
  },
  "geometry": {"coordinates":[-81.869654,41.293728],"type":"Point"}
}
