{
  "type": "Feature",
  "properties": {
    "addr:full":"2141 Gilbert Ave Cincinnati OH 45206",
    "addr:housenumber":"2141",
    "addr:postcode":"45206",
    "addr:street":"Gilbert Ave",
    "iso:country":"US",
    "sg:address":"2141 Gilbert Ave",
    "sg:city":"Cincinnati",
    "sg:classifiers":[
        {
            "category":"Manufacturing",
            "subcategory":"Printing",
            "type":"Manufacturing & Wholesale Goods"
        }
    ],
    "sg:phone":"+1 513 281 0999",
    "sg:postcode":"45206",
    "sg:province":"OH",
    "sg:tags":[
        "printer"
    ],
    "sg:website":"www.phototype.com",
    "wof:name":"Phototype",
    "wof:placetype":"venue"
},
  "geometry": {"coordinates":[-84.494224,39.120669],"type":"Point"}
}