{
  "type": "Feature",
  "properties": {
    "addr:full": "10231 Woodlawn Ave Miamisburg OH 45342",
    "addr:housenumber": "10231",
    "addr:postcode": "45342",
    "addr:street": "Woodlawn Ave",
    "iso:country": "US",
    "sg:address": "10231 Woodlawn Ave",
    "sg:city": "Miamisburg",
    "sg:classifiers": [
      {
        "category": "Building \u0026 Trades",
        "subcategory": "Construction",
        "type": "Services"
      }
    ],
    "sg:phone": "+1 937 743 3832",
    "sg:postcode": "45342",
    "sg:province": "OH",
    "sg:tags": [
      "roofing",
      "contractor"
    ],
    "wof:name": "Tirey Contractors",
    "wof:placetype": "venue"
  },
  "geometry": {"coordinates":[-84.292953,39.595399],"type":"Point"}
}
