{
  "type": "Feature",
  "properties": {
    "addr:full": "6202 Fairfield Dr Northwood OH 43619",
    "addr:housenumber": "6202",
    "addr:postcode": "43619",
    "addr:street": "Fairfield Dr",
    "iso:country": "US",
    "sg:address": "6202 Fairfield Dr",
    "sg:city": "Northwood",
    "sg:classifiers": [
      {
        "category": "Autos \u0026 Motor Vehicles",
        "subcategory": "Auto Supplies",
        "type": "Retail Goods"
      }
    ],
    "sg:phone": "+1 419 661 1800",
    "sg:postcode": "43619",
    "sg:province": "OH",
    "sg:tags": [
      "tire"
    ],
    "wof:name": "Jam Tire Inc",
    "wof:placetype": "venue"
  },
  "geometry": {"coordinates":[-83.552141,41.604378],"type":"Point"}
}
