{
  "type": "Feature",
  "properties": {
    "iso:country":"US",
    "sg:address":"6202 Fairfield Dr",
    "sg:city":"Northwood",
    "sg:classifiers":[
        {
            "category":"Autos & Motor Vehicles",
            "subcategory":"Auto Supplies",
            "type":"Retail Goods"
        }
    ],
    "sg:phone":"+1 419 661 1800",
    "sg:postcode":"43619",
    "sg:province":"OH",
    "sg:tags":[
        "tire"
    ],
    "wof:name":"Jam Tire Inc",
    "wof:placetype":"venue"
},
  "geometry": {"coordinates":[-83.55214100000001,41.604378],"type":"Point"}
}