{
  "type": "Feature",
  "properties": {
    "addr:full": "4470 Coopermill Rd Zanesville OH 43701",
    "addr:housenumber": "4470",
    "addr:postcode": "43701",
    "addr:street": "Coopermill Rd",
    "iso:country": "US",
    "sg:address": "4470 Coopermill Rd",
    "sg:city": "Zanesville",
    "sg:classifiers": [
      {
        "category": "Professional",
        "type": "Services"
      }
    ],
    "sg:phone": "+1 740 453 2168",
    "sg:postcode": "43701",
    "sg:province": "OH",
    "wof:name": "Anthony Landers",
    "wof:placetype": "venue"
  },
  "geometry": {"coordinates":[-82.082916,39.911415],"type":"Point"}
}
