{
  "type": "Feature",
  "properties": {
    "addr:full":"2012 W 25th St Ste 810 Cleveland OH 44113",
    "addr:housenumber":"2012",
    "addr:postcode":"44113",
    "addr:street":"W 25Th St Ste 810",
    "iso:country":"US",
    "sg:address":"2012 W 25th St Ste 810",
    "sg:city":"Cleveland",
    "sg:phone":"+1 216 664 1919",
    "sg:postcode":"44113",
    "sg:province":"OH",
    "wof:name":"Continental Management",
    "wof:placetype":"venue"
},
  "geometry": {"coordinates":[-81.70320700000001,41.484008],"type":"Point"}
}