{
  "type": "Feature",
  "properties": {
    "addr:full":"1185 N Court St Circleville OH 43113",
    "addr:housenumber":"1185",
    "addr:postcode":"43113",
    "addr:street":"N Court St",
    "iso:country":"US",
    "sg:address":"1185 N Court St",
    "sg:city":"Circleville",
    "sg:classifiers":[
        {
            "category":"Retail",
            "subcategory":"Laundry & Dry Cleaning",
            "type":"Services"
        }
    ],
    "sg:phone":"+1 740 474 2206",
    "sg:postcode":"43113",
    "sg:province":"OH",
    "sg:tags":[
        "cleaners"
    ],
    "wof:name":"Porters Laundry & Dry Cleaning",
    "wof:placetype":"venue"
},
  "geometry": {"coordinates":[-82.94051,39.620973],"type":"Point"}
}