{
  "type": "Feature",
  "properties": {
    "iso:country":"US",
    "sg:address":"108 Kenilworth Dr",
    "sg:city":"Akron",
    "sg:classifiers":[
        {
            "category":"Building & Trades",
            "subcategory":"Construction",
            "type":"Services"
        }
    ],
    "sg:phone":"+1 330 867 5426",
    "sg:postcode":"44313",
    "sg:province":"OH",
    "sg:tags":[
        "concrete",
        "contractor"
    ],
    "wof:name":"Ohio Concrete Raising Inc",
    "wof:placetype":"venue"
},
  "geometry": {"coordinates":[-81.560384,41.105667],"type":"Point"}
}