{
  "type": "Feature",
  "properties": {
    "iso:country":"US",
    "sg:address":"164 S Mulberry St",
    "sg:city":"Wilmington",
    "sg:classifiers":[
        {
            "category":"Freight",
            "type":"Transportation"
        }
    ],
    "sg:phone":"+1 937 382 0547",
    "sg:postcode":"45177",
    "sg:province":"OH",
    "sg:tags":[
        "special"
    ],
    "wof:name":"Sewell Store & Lock",
    "wof:placetype":"venue"
},
  "geometry": {"coordinates":[-83.830226,39.443646],"type":"Point"}
}