{
  "type": "Feature",
  "properties": {
    "iso:country":"US",
    "sg:address":"2765 Fairmount Blvd",
    "sg:city":"Cleveland",
    "sg:classifiers":[
        {
            "category":"Social Services",
            "type":"Services"
        }
    ],
    "sg:phone":"+1 216 321 2582",
    "sg:postcode":"44118",
    "sg:province":"OH",
    "sg:tags":[
        "youth",
        "organization",
        "center"
    ],
    "wof:name":"Heights Youth Club",
    "wof:placetype":"venue"
},
  "geometry": {"coordinates":[-81.58056500000001,41.492616],"type":"Point"}
}