{
  "type": "Feature",
  "properties": {
    "addr:full": "2515 Lakewood Ave Lima OH 45805",
    "addr:housenumber": "2515",
    "addr:postcode": "45805",
    "addr:street": "Lakewood Ave",
    "iso:country": "US",
    "sg:address": "2515 Lakewood Ave",
    "sg:city": "Lima",
    "sg:classifiers": [
      {
        "category": "Home \u0026 Garden",
        "subcategory": "Garden Supply",
        "type": "Retail Goods"
      }
    ],
    "sg:phone": "+1 419 222 8451",
    "sg:postcode": "45805",
    "sg:province": "OH",
    "sg:tags": [
      "lawn",
      "mower"
    ],
    "wof:name": "Cut Right Equipment",
    "wof:placetype": "venue"
  },
  "geometry": {"coordinates":[-84.148891,40.733674],"type":"Point"}
}
