{
  "type": "Feature",
  "properties": {
    "iso:country":"US",
    "sg:address":"2515 Lakewood Ave",
    "sg:city":"Lima",
    "sg:classifiers":[
        {
            "category":"Home & Garden",
            "subcategory":"Garden Supply",
            "type":"Retail Goods"
        }
    ],
    "sg:phone":"+1 419 222 8451",
    "sg:postcode":"45805",
    "sg:province":"OH",
    "sg:tags":[
        "lawn",
        "mower"
    ],
    "wof:name":"Cut Right Equipment",
    "wof:placetype":"venue"
},
  "geometry": {"coordinates":[-84.14889100000001,40.733674],"type":"Point"}
}