{
  "type": "Feature",
  "properties": {
    "iso:country":"US",
    "sg:address":"580 Broadway Ave",
    "sg:city":"Cleveland",
    "sg:classifiers":[
        {
            "category":"Autos & Motor Vehicles",
            "subcategory":"Automobile Sales",
            "type":"Retail Goods"
        }
    ],
    "sg:phone":"+1 440 439 5318",
    "sg:postcode":"44146",
    "sg:province":"OH",
    "sg:tags":[
        "car",
        "dealer"
    ],
    "wof:name":"Northeast Auto Finance Inc",
    "wof:placetype":"venue"
},
  "geometry": {"coordinates":[-81.538082,41.393849],"type":"Point"}
}