{
  "type": "Feature",
  "properties": {
    "addr:full": "8920 Basil Rd NW Baltimore OH 43105",
    "addr:housenumber": "8920",
    "addr:postcode": "43105",
    "addr:street": "Basil Rd Nw",
    "iso:country": "US",
    "sg:address": "8920 Basil Rd NW",
    "sg:city": "Baltimore",
    "sg:classifiers": [
      {
        "category": "Freight",
        "type": "Transportation"
      }
    ],
    "sg:phone": "+1 740 862 4951",
    "sg:postcode": "43105",
    "sg:province": "OH",
    "sg:tags": [
      "operator",
      "trucking"
    ],
    "wof:name": "David Kimberly Stilwell",
    "wof:placetype": "venue"
  },
  "geometry": {"coordinates":[-82.615377,39.856062],"type":"Point"}
}
