{
  "type": "Feature",
  "properties": {
    "iso:country":"US",
    "sg:address":"131 E Main St",
    "sg:city":"Mason",
    "sg:classifiers":[
        {
            "category":"Food & Beverages",
            "subcategory":"Groceries & Convenience Stores",
            "type":"Retail Goods"
        }
    ],
    "sg:phone":"+1 513 398 4435",
    "sg:postcode":"45040",
    "sg:province":"OH",
    "wof:name":"Mason Kwikmart",
    "wof:placetype":"venue"
},
  "geometry": {"coordinates":[-84.308184,39.360423],"type":"Point"}
}