{
  "type": "Feature",
  "properties": {
    "addr:full":"1580 Chestnut Rd Cleveland OH 44131",
    "addr:housenumber":"1580",
    "addr:postcode":"44131",
    "addr:street":"Chestnut Rd",
    "iso:country":"US",
    "sg:address":"1580 Chestnut Rd",
    "sg:city":"Cleveland",
    "sg:classifiers":[
        {
            "category":"Home & Garden",
            "subcategory":"Home Furnishings",
            "type":"Retail Goods"
        }
    ],
    "sg:phone":"+1 216 529 1056",
    "sg:postcode":"44131",
    "sg:province":"OH",
    "wof:name":"Hubbell Incorporated",
    "wof:placetype":"venue"
},
  "geometry": {"coordinates":[-81.67998900000001,41.384305],"type":"Point"}
}