{
  "type": "Feature",
  "properties": {
    "iso:country":"US",
    "sg:address":"10228 Pottenger Rd",
    "sg:city":"Camden",
    "sg:classifiers":[
        {
            "category":"Building & Trades",
            "subcategory":"Construction",
            "type":"Services"
        }
    ],
    "sg:phone":"+1 513 796 3338",
    "sg:postcode":"45311",
    "sg:province":"OH",
    "sg:tags":[
        "residential"
    ],
    "wof:name":"Jim Baugh Inc",
    "wof:placetype":"venue"
},
  "geometry": {"coordinates":[-84.695054,39.603598],"type":"Point"}
}