{
  "type": "Feature",
  "properties": {
    "addr:full":"46545 Y and O Rd East Liverpool OH 43920",
    "addr:housenumber":"46545",
    "addr:postcode":"43920",
    "addr:street":"Y And O Rd",
    "iso:country":"US",
    "sg:address":"46545 Y and O Rd",
    "sg:city":"East Liverpool",
    "sg:classifiers":[
        {
            "category":"Organizations",
            "subcategory":"Religious Organization",
            "type":"Services"
        }
    ],
    "sg:phone":"+1 330 386 5211",
    "sg:postcode":"43920",
    "sg:province":"OH",
    "sg:tags":[
        "church"
    ],
    "wof:name":"Tri State Christian Church",
    "wof:placetype":"venue"
},
  "geometry": {"coordinates":[-80.622231,40.664332],"type":"Point"}
}