{
  "type": "Feature",
  "properties": {
    "addr:full": "4242 Tuller Rd Dublin OH 43017",
    "addr:housenumber": "4242",
    "addr:postcode": "43017",
    "addr:street": "Tuller Rd",
    "iso:country": "US",
    "sg:address": "4242 Tuller Rd",
    "sg:city": "Dublin",
    "sg:classifiers": [
      {
        "category": "Real Estate",
        "subcategory": "Architect",
        "type": "Services"
      }
    ],
    "sg:phone": "+1 614 798 0900",
    "sg:postcode": "43017",
    "sg:province": "OH",
    "wof:name": "Robert L Fiorita Architects",
    "wof:placetype": "venue"
  },
  "geometry": {"coordinates":[-83.106784,40.107805],"type":"Point"}
}
