{
  "type": "Feature",
  "properties": {
    "iso:country":"US",
    "sg:address":"5503 Cheviot Rd",
    "sg:city":"Cincinnati",
    "sg:classifiers":[
        {
            "category":"Organizations",
            "subcategory":"Community Association",
            "type":"Services"
        }
    ],
    "sg:phone":"+1 513 662 1988",
    "sg:postcode":"45247",
    "sg:province":"OH",
    "sg:tags":[
        "club"
    ],
    "wof:name":"Amvets",
    "wof:placetype":"venue"
},
  "geometry": {"coordinates":[-84.599327,39.191226],"type":"Point"}
}