{
  "type": "Feature",
  "properties": {
    "addr:full": "196 S Chillicothe Rd Aurora OH 44202",
    "addr:housenumber": "196",
    "addr:postcode": "44202",
    "addr:street": "S Chillicothe Rd",
    "iso:country": "US",
    "sg:address": "196 S Chillicothe Rd",
    "sg:city": "Aurora",
    "sg:classifiers": [
      {
        "category": "Shopping",
        "subcategory": "Clothing, Apparel, \u0026 Fashions",
        "type": "Retail Goods"
      }
    ],
    "sg:phone": "+1 330 995 0547",
    "sg:postcode": "44202",
    "sg:province": "OH",
    "sg:tags": [
      "baby",
      "accessory"
    ],
    "wof:name": "Three Elysabethe's",
    "wof:placetype": "venue"
  },
  "geometry": {"coordinates":[-81.345592,41.312485],"type":"Point"}
}
