{
  "type": "Feature",
  "properties": {
    "iso:country":"US",
    "sg:address":"196 S Chillicothe Rd",
    "sg:city":"Aurora",
    "sg:classifiers":[
        {
            "category":"Shopping",
            "subcategory":"Clothing, Apparel, & Fashions",
            "type":"Retail Goods"
        }
    ],
    "sg:phone":"+1 330 995 0547",
    "sg:postcode":"44202",
    "sg:province":"OH",
    "sg:tags":[
        "baby",
        "accessory"
    ],
    "wof:name":"Three Elysabethe's",
    "wof:placetype":"venue"
},
  "geometry": {"coordinates":[-81.345592,41.312485],"type":"Point"}
}