{
  "type": "Feature",
  "properties": {
    "addr:full":"4346 Greenville Rd NE Farmdale OH 44417",
    "addr:housenumber":"4346",
    "addr:postcode":"44417",
    "addr:street":"Greenville Rd Ne",
    "iso:country":"US",
    "sg:address":"4346 Greenville Rd NE",
    "sg:city":"Farmdale",
    "sg:classifiers":[
        {
            "category":"Shopping",
            "subcategory":"Clothing, Apparel, & Fashions",
            "type":"Retail Goods"
        }
    ],
    "sg:phone":"+1 330 924 2865",
    "sg:postcode":"44417",
    "sg:province":"OH",
    "wof:name":"Wagner Wedding Accessories",
    "wof:placetype":"venue"
},
  "geometry": {"coordinates":[-80.65893,41.388727],"type":"Point"}
}