{
  "type": "Feature",
  "properties": {
    "addr:full": "21641 Buena Vista Rd Rockbridge OH 43149",
    "addr:housenumber": "21641",
    "addr:postcode": "43149",
    "addr:street": "Buena Vista Rd",
    "iso:country": "US",
    "sg:address": "21641 Buena Vista Rd",
    "sg:city": "Rockbridge",
    "sg:classifiers": [
      {
        "category": "Building \u0026 Trades",
        "subcategory": "Plumbing",
        "type": "Services"
      }
    ],
    "sg:phone": "+1 740 969 0010",
    "sg:postcode": "43149",
    "sg:province": "OH",
    "sg:tags": [
      "conditioning",
      "air",
      "system",
      "contractor"
    ],
    "wof:name": "Trutemp Heating \u0026 Cooling",
    "wof:placetype": "venue"
  },
  "geometry": {"coordinates":[-82.632219,39.549569],"type":"Point"}
}
