{
  "type": "Feature",
  "properties": {
    "iso:country":"US",
    "sg:address":"21641 Buena Vista Rd",
    "sg:city":"Rockbridge",
    "sg:classifiers":[
        {
            "category":"Building & Trades",
            "subcategory":"Plumbing",
            "type":"Services"
        }
    ],
    "sg:phone":"+1 740 969 0010",
    "sg:postcode":"43149",
    "sg:province":"OH",
    "sg:tags":[
        "conditioning",
        "air",
        "system",
        "contractor"
    ],
    "wof:name":"Trutemp Heating & Cooling",
    "wof:placetype":"venue"
},
  "geometry": {"coordinates":[-82.632219,39.549569],"type":"Point"}
}