{
  "type": "Feature",
  "properties": {
    "addr:full": "5201 Grant Ave Cleveland OH 44125",
    "addr:housenumber": "5201",
    "addr:postcode": "44125",
    "addr:street": "Grant Ave",
    "iso:country": "US",
    "sg:address": "5201 Grant Ave",
    "sg:city": "Cleveland",
    "sg:classifiers": [
      {
        "category": "Building \u0026 Trades",
        "subcategory": "Construction",
        "type": "Services"
      }
    ],
    "sg:phone": "+1 216 429 2400",
    "sg:postcode": "44125",
    "sg:province": "OH",
    "sg:tags": [
      "concrete",
      "cutting",
      "breaking",
      "sawing"
    ],
    "wof:name": "Precision Pro Cut Inc",
    "wof:placetype": "venue"
  },
  "geometry": {"coordinates":[-81.651483,41.43953],"type":"Point"}
}
