{
  "type": "Feature",
  "properties": {
    "iso:country":"US",
    "sg:address":"315 E Main St",
    "sg:city":"Russells Point",
    "sg:classifiers":[
        {
            "category":"Restaurant",
            "type":"Food & Drink"
        }
    ],
    "sg:phone":"+1 937 843 3420",
    "sg:postcode":"43348",
    "sg:province":"OH",
    "wof:name":"B J Pizza",
    "wof:placetype":"venue"
},
  "geometry": {"coordinates":[-83.893252,40.471259],"type":"Point"}
}