{
  "type": "Feature",
  "properties": {
    "addr:full": "315 E Main St Russells Point OH 43348",
    "addr:housenumber": "315",
    "addr:postcode": "43348",
    "addr:street": "E Main St",
    "iso:country": "US",
    "sg:address": "315 E Main St",
    "sg:city": "Russells Point",
    "sg:classifiers": [
      {
        "category": "Restaurant",
        "type": "Food \u0026 Drink"
      }
    ],
    "sg:phone": "+1 937 843 3420",
    "sg:postcode": "43348",
    "sg:province": "OH",
    "wof:name": "B J Pizza",
    "wof:placetype": "venue"
  },
  "geometry": {"coordinates":[-83.893252,40.471259],"type":"Point"}
}
