{
  "type": "Feature",
  "properties": {
    "addr:full":"26011 Lake Shore Blvd Cleveland OH 44132",
    "addr:housenumber":"26011",
    "addr:postcode":"44132",
    "addr:street":"Lake Shore Blvd",
    "iso:country":"US",
    "sg:address":"26011 Lake Shore Blvd",
    "sg:city":"Cleveland",
    "sg:classifiers":[
        {
            "category":"Real Estate",
            "subcategory":"Real Estate Operator",
            "type":"Services"
        }
    ],
    "sg:phone":"+1 216 261 5077",
    "sg:postcode":"44132",
    "sg:province":"OH",
    "sg:tags":[
        "building",
        "apartment"
    ],
    "wof:name":"Riviera Apartments",
    "wof:placetype":"venue"
},
  "geometry": {"coordinates":[-81.502436,41.620958],"type":"Point"}
}