{
  "type": "Feature",
  "properties": {
    "addr:full": "2361 W Bancroft St Toledo OH 43607",
    "addr:housenumber": "2361",
    "addr:postcode": "43607",
    "addr:street": "W Bancroft St",
    "iso:country": "US",
    "sg:address": "2361 W Bancroft St",
    "sg:city": "Toledo",
    "sg:classifiers": [
      {
        "category": "Health Services",
        "subcategory": "Doctor",
        "type": "Services"
      }
    ],
    "sg:phone": "+1 419 539 4114",
    "sg:postcode": "43607",
    "sg:province": "OH",
    "sg:tags": [
      "physician",
      "surgeon"
    ],
    "wof:name": "Bancroft West",
    "wof:placetype": "venue"
  },
  "geometry": {"coordinates":[-83.596917,41.663217],"type":"Point"}
}
