{
  "type": "Feature",
  "properties": {
    "addr:full":"2305 Concord St Cincinnati OH 45206",
    "addr:housenumber":"2305",
    "addr:postcode":"45206",
    "addr:street":"Concord St",
    "iso:country":"US",
    "sg:address":"2305 Concord St",
    "sg:city":"Cincinnati",
    "sg:classifiers":[
        {
            "category":"Retail",
            "subcategory":"Auto Repair",
            "type":"Services"
        }
    ],
    "sg:phone":"+1 513 961 0612",
    "sg:postcode":"45206",
    "sg:province":"OH",
    "sg:tags":[
        "repairing",
        "automobile"
    ],
    "wof:name":"Integrity Auto Repair LLC",
    "wof:placetype":"venue"
},
  "geometry": {"coordinates":[-84.49360799999999,39.122976],"type":"Point"}
}