{
  "type": "Feature",
  "properties": {
    "addr:full": "1380 Hartford Ave Akron OH 44320",
    "addr:housenumber": "1380",
    "addr:postcode": "44320",
    "addr:street": "Hartford Ave",
    "iso:country": "US",
    "sg:address": "1380 Hartford Ave",
    "sg:city": "Akron",
    "sg:classifiers": [
      {
        "category": "Organizations",
        "subcategory": "Religious Organization",
        "type": "Services"
      }
    ],
    "sg:phone": "+1 330 836 2030",
    "sg:postcode": "44320",
    "sg:province": "OH",
    "sg:tags": [
      "church"
    ],
    "wof:name": "New Trinity Missionary Baptist",
    "wof:placetype": "venue"
  },
  "geometry": {"coordinates":[-81.564505,41.069963],"type":"Point"}
}
