{
  "type": "Feature",
  "properties": {
    "addr:full":"6855 Warren Sharon Rd Brookfield OH 44403",
    "addr:housenumber":"6855",
    "addr:postcode":"44403",
    "addr:street":"Warren Sharon Rd",
    "iso:country":"US",
    "sg:address":"6855 Warren Sharon Rd",
    "sg:city":"Brookfield",
    "sg:classifiers":[
        {
            "category":"Insurance",
            "subcategory":"Hazard Insurance",
            "type":"Services"
        }
    ],
    "sg:phone":"+1 330 448 6030",
    "sg:postcode":"44403",
    "sg:province":"OH",
    "sg:tags":[
        "commercial",
        "business"
    ],
    "wof:name":"Wayne Brookfield Finacial Svcs",
    "wof:placetype":"venue"
},
  "geometry": {"coordinates":[-80.56906499999999,41.23417],"type":"Point"}
}