{
  "type": "Feature",
  "properties": {
    "iso:country":"US",
    "sg:address":"6455 Case Rd",
    "sg:city":"North Ridgeville",
    "sg:classifiers":[
        {
            "category":"Building & Trades",
            "subcategory":"Landscaping Services",
            "type":"Services"
        }
    ],
    "sg:phone":"+1 440 353 9501",
    "sg:postcode":"44039",
    "sg:province":"OH",
    "sg:tags":[
        "landscape",
        "contractor"
    ],
    "wof:name":"Creative Annuals",
    "wof:placetype":"venue"
},
  "geometry": {"coordinates":[-82.05862500000001,41.39553],"type":"Point"}
}