{
  "type": "Feature",
  "properties": {
    "addr:full": "6455 Case Rd North Ridgeville OH 44039",
    "addr:housenumber": "6455",
    "addr:postcode": "44039",
    "addr:street": "Case Rd",
    "iso:country": "US",
    "sg:address": "6455 Case Rd",
    "sg:city": "North Ridgeville",
    "sg:classifiers": [
      {
        "category": "Building \u0026 Trades",
        "subcategory": "Landscaping Services",
        "type": "Services"
      }
    ],
    "sg:phone": "+1 440 353 9501",
    "sg:postcode": "44039",
    "sg:province": "OH",
    "sg:tags": [
      "landscape",
      "contractor"
    ],
    "wof:name": "Creative Annuals",
    "wof:placetype": "venue"
  },
  "geometry": {"coordinates":[-82.058625,41.39553],"type":"Point"}
}
