{
  "type": "Feature",
  "properties": {
    "iso:country":"US",
    "sg:address":"103 S Walnut St",
    "sg:city":"Harrison",
    "sg:classifiers":[
        {
            "category":"Building & Trades",
            "subcategory":"Construction",
            "type":"Services"
        }
    ],
    "sg:phone":"+1 513 367 5548",
    "sg:postcode":"45030",
    "sg:province":"IN",
    "sg:tags":[
        "restoration",
        "preservation"
    ],
    "sg:website":"www.shopharrison.org",
    "wof:name":"Main Street Harrison Inc",
    "wof:placetype":"venue"
},
  "geometry": {"coordinates":[-84.81862700000001,39.26095],"type":"Point"}
}