{
  "type": "Feature",
  "properties": {
    "addr:full":"14216 State Rte 113 Wakeman OH 44889",
    "addr:housenumber":"14216",
    "addr:postcode":"44889",
    "addr:street":"State Rte 113",
    "iso:country":"US",
    "sg:address":"14216 State Rte 113",
    "sg:city":"Wakeman",
    "sg:classifiers":[
        {
            "category":"Autos & Motor Vehicles",
            "subcategory":"Automobile Sales",
            "type":"Retail Goods"
        }
    ],
    "sg:phone":"+1 440 965 4520",
    "sg:postcode":"44889",
    "sg:province":"OH",
    "sg:tags":[
        "used"
    ],
    "wof:name":"Clark Auto",
    "wof:placetype":"venue"
},
  "geometry": {"coordinates":[-82.360867,41.330178],"type":"Point"}
}