{
  "type": "Feature",
  "properties": {
    "iso:country":"US",
    "sg:address":"1663 Main St",
    "sg:city":"Peninsula",
    "sg:classifiers":[
        {
            "category":"Food & Beverages",
            "subcategory":"Specialty",
            "type":"Retail Goods"
        }
    ],
    "sg:phone":"+1 330 657 2332",
    "sg:postcode":"44264",
    "sg:province":"OH",
    "sg:tags":[
        "herb"
    ],
    "wof:name":"Crooked River Herb Farm Shop",
    "wof:placetype":"venue"
},
  "geometry": {"coordinates":[-81.550045,41.241362],"type":"Point"}
}