{
  "type": "Feature",
  "properties": {
    "addr:full": "1663 Main St Peninsula OH 44264",
    "addr:housenumber": "1663",
    "addr:postcode": "44264",
    "addr:street": "Main St",
    "iso:country": "US",
    "sg:address": "1663 Main St",
    "sg:city": "Peninsula",
    "sg:classifiers": [
      {
        "category": "Food \u0026 Beverages",
        "subcategory": "Specialty",
        "type": "Retail Goods"
      }
    ],
    "sg:phone": "+1 330 657 2332",
    "sg:postcode": "44264",
    "sg:province": "OH",
    "sg:tags": [
      "herb"
    ],
    "wof:name": "Crooked River Herb Farm Shop",
    "wof:placetype": "venue"
  },
  "geometry": {"coordinates":[-81.550045,41.241362],"type":"Point"}
}
