{
  "type": "Feature",
  "properties": {
    "addr:full":"540 Water St Chardon OH 44024",
    "addr:housenumber":"540",
    "addr:postcode":"44024",
    "addr:street":"Water St",
    "iso:country":"US",
    "sg:address":"540 Water St",
    "sg:city":"Chardon",
    "sg:classifiers":[
        {
            "category":"Professional",
            "subcategory":"Employment Agencies",
            "type":"Services"
        }
    ],
    "sg:phone":"+1 440 286 8600",
    "sg:postcode":"44024",
    "sg:province":"OH",
    "sg:tags":[
        "temporary",
        "opportunity"
    ],
    "wof:name":"Randstad",
    "wof:placetype":"venue"
},
  "geometry": {"coordinates":[-81.212627,41.580877],"type":"Point"}
}