{
  "type": "Feature",
  "properties": {
    "addr:full": "901 W Jefferson St New Carlisle OH 45344",
    "addr:housenumber": "901",
    "addr:postcode": "45344",
    "addr:street": "W Jefferson St",
    "iso:country": "US",
    "sg:address": "901 W Jefferson St",
    "sg:city": "New Carlisle",
    "sg:classifiers": [
      {
        "category": "Retail",
        "subcategory": "Auto Repair",
        "type": "Services"
      }
    ],
    "sg:phone": "+1 937 845 1815",
    "sg:postcode": "45344",
    "sg:province": "OH",
    "sg:tags": [
      "repairing",
      "automobile"
    ],
    "wof:name": "Jenkins Automotive",
    "wof:placetype": "venue"
  },
  "geometry": {"coordinates":[-84.035815,39.935218],"type":"Point"}
}
