{
  "type": "Feature",
  "properties": {
    "addr:full":"6515 Mason Rd Berlin Heights OH 44814",
    "addr:housenumber":"6515",
    "addr:postcode":"44814",
    "addr:street":"Mason Rd",
    "iso:country":"US",
    "sg:address":"6515 Mason Rd",
    "sg:city":"Berlin Heights",
    "sg:phone":"+1 419 588 2347",
    "sg:postcode":"44814",
    "sg:province":"OH",
    "sg:tags":[
        "farm"
    ],
    "wof:name":"Cedar Grove Farm",
    "wof:placetype":"venue"
},
  "geometry": {"coordinates":[-82.511758,41.330708],"type":"Point"}
}