{
  "type": "Feature",
  "properties": {
    "addr:full":"3221 W Siebenthaler Ave Dayton OH 45406",
    "addr:housenumber":"3221",
    "addr:postcode":"45406",
    "addr:street":"W Siebenthaler Ave",
    "iso:country":"US",
    "sg:address":"3221 W Siebenthaler Ave",
    "sg:city":"Dayton",
    "sg:classifiers":[
        {
            "category":"Shopping",
            "subcategory":"Shoes",
            "type":"Retail Goods"
        }
    ],
    "sg:phone":"+1 937 276 3266",
    "sg:postcode":"45406",
    "sg:province":"OH",
    "wof:name":"Jocelyn's & Teef's Fresh Kickz",
    "wof:placetype":"venue"
},
  "geometry": {"coordinates":[-84.244786,39.798201],"type":"Point"}
}