{
  "type": "Feature",
  "properties": {
    "addr:full": "1400 Myrtle Ave Columbus OH 43211",
    "addr:housenumber": "1400",
    "addr:postcode": "43211",
    "addr:street": "Myrtle Ave",
    "iso:country": "US",
    "sg:address": "1400 Myrtle Ave",
    "sg:city": "Columbus",
    "sg:classifiers": [
      {
        "category": "Education",
        "subcategory": "School",
        "type": "Public Place"
      }
    ],
    "sg:phone": "+1 614 365 6037",
    "sg:postcode": "43211",
    "sg:province": "OH",
    "wof:name": "Linden Park Elementary School",
    "wof:placetype": "venue"
  },
  "geometry": {"coordinates":[-82.972433,40.017471],"type":"Point"}
}
