{
  "type": "Feature",
  "properties": {
    "addr:full": "5994 W Elkton Rd Somerville OH 45064",
    "addr:housenumber": "5994",
    "addr:postcode": "45064",
    "addr:street": "W Elkton Rd",
    "iso:country": "US",
    "sg:address": "5994 W Elkton Rd",
    "sg:city": "Somerville",
    "sg:classifiers": [
      {
        "category": "Manufacturing",
        "subcategory": "Glass \u0026 Minerals",
        "type": "Manufacturing \u0026 Wholesale Goods"
      }
    ],
    "sg:phone": "+1 513 726 1200",
    "sg:postcode": "45064",
    "sg:province": "OH",
    "sg:tags": [
      "art"
    ],
    "wof:name": "Wingate Arts \u0026 Crafts",
    "wof:placetype": "venue"
  },
  "geometry": {"coordinates":[-84.552973,39.537974],"type":"Point"}
}
