{
  "type": "Feature",
  "properties": {
    "iso:country":"US",
    "sg:address":"5994 W Elkton Rd",
    "sg:city":"Somerville",
    "sg:classifiers":[
        {
            "category":"Manufacturing",
            "subcategory":"Glass & Minerals",
            "type":"Manufacturing & Wholesale Goods"
        }
    ],
    "sg:phone":"+1 513 726 1200",
    "sg:postcode":"45064",
    "sg:province":"OH",
    "sg:tags":[
        "art"
    ],
    "wof:name":"Wingate Arts & Crafts",
    "wof:placetype":"venue"
},
  "geometry": {"coordinates":[-84.55297299999999,39.537974],"type":"Point"}
}