{
  "type": "Feature",
  "properties": {
    "iso:country":"US",
    "sg:address":"7975 W Chester Rd",
    "sg:city":"West Chester",
    "sg:classifiers":[
        {
            "category":"Shopping",
            "type":"Retail Goods"
        }
    ],
    "sg:phone":"+1 513 759 0178",
    "sg:postcode":"45069",
    "sg:province":"OH",
    "sg:tags":[
        "telephone",
        "cellular"
    ],
    "wof:name":"Citel Wireless",
    "wof:placetype":"venue"
},
  "geometry": {"coordinates":[-84.362991,39.317758],"type":"Point"}
}