{
  "type": "Feature",
  "properties": {
    "addr:full":"28921 Wayside Ln Cleveland OH 44140",
    "addr:housenumber":"28921",
    "addr:postcode":"44140",
    "addr:street":"Wayside Ln",
    "iso:country":"US",
    "sg:address":"28921 Wayside Ln",
    "sg:city":"Cleveland",
    "sg:classifiers":[
        {
            "category":"Wholesale",
            "subcategory":"Hardware",
            "type":"Manufacturing & Wholesale Goods"
        }
    ],
    "sg:phone":"+1 440 899 1574",
    "sg:postcode":"44140",
    "sg:province":"OH",
    "sg:tags":[
        "equipment",
        "heating",
        "system"
    ],
    "wof:name":"Edgewood Supply LTD",
    "wof:placetype":"venue"
},
  "geometry": {"coordinates":[-81.940268,41.486418],"type":"Point"}
}