{
  "type": "Feature",
  "properties": {
    "addr:full": "3200 Belmont Ave Youngstown OH 44505",
    "addr:housenumber": "3200",
    "addr:postcode": "44505",
    "addr:street": "Belmont Ave",
    "iso:country": "US",
    "sg:address": "3200 Belmont Ave",
    "sg:city": "Youngstown",
    "sg:classifiers": [
      {
        "category": "Home \u0026 Garden",
        "subcategory": "Household Appliances",
        "type": "Retail Goods"
      }
    ],
    "sg:phone": "+1 330 759 7694",
    "sg:postcode": "44505",
    "sg:province": "OH",
    "sg:tags": [
      "pump"
    ],
    "wof:name": "Premier Pump",
    "wof:placetype": "venue"
  },
  "geometry": {"coordinates":[-80.665506,41.141101],"type":"Point"}
}
