{
  "type": "Feature",
  "properties": {
    "iso:country":"US",
    "sg:address":"240 Eastholm Ave",
    "sg:city":"Akron",
    "sg:classifiers":[
        {
            "category":"Building & Trades",
            "subcategory":"Plumbing",
            "type":"Services"
        }
    ],
    "sg:phone":"+1 330 784 4700",
    "sg:postcode":"44312",
    "sg:province":"OH",
    "sg:tags":[
        "conditioning",
        "air",
        "system",
        "contractor"
    ],
    "wof:name":"Holland Furnace Co",
    "wof:placetype":"venue"
},
  "geometry": {"coordinates":[-81.448149,41.056546],"type":"Point"}
}