{
  "type": "Feature",
  "properties": {
    "addr:full": "230 Howe Ave Cuyahoga Falls OH 44221",
    "addr:housenumber": "230",
    "addr:postcode": "44221",
    "addr:street": "Howe Ave",
    "iso:country": "US",
    "sg:address": "230 Howe Ave",
    "sg:city": "Cuyahoga Falls",
    "sg:classifiers": [
      {
        "category": "Food \u0026 Beverages",
        "subcategory": "Groceries \u0026 Convenience Stores",
        "type": "Retail Goods"
      }
    ],
    "sg:phone": "+1 330 922 0131",
    "sg:postcode": "44221",
    "sg:province": "OH",
    "sg:tags": [
      "florist",
      "grocer"
    ],
    "sg:website": "www.topsmarkets.com",
    "wof:name": "Tops Friendly Markets",
    "wof:placetype": "venue"
  },
  "geometry": {"coordinates":[-81.481962,41.119145],"type":"Point"}
}
