{
  "type": "Feature",
  "properties": {
    "addr:full":"180 S Stanfield Rd Troy OH 45373",
    "addr:housenumber":"180",
    "addr:postcode":"45373",
    "addr:street":"S Stanfield Rd",
    "iso:country":"US",
    "sg:address":"180 S Stanfield Rd",
    "sg:city":"Troy",
    "sg:classifiers":[
        {
            "category":"Health Services",
            "subcategory":"Doctor",
            "type":"Services"
        }
    ],
    "sg:phone":"+1 937 440 9758",
    "sg:postcode":"45373",
    "sg:province":"OH",
    "sg:tags":[
        "physician",
        "surgeon"
    ],
    "wof:name":"Upper Valley Pain Clinic",
    "wof:placetype":"venue"
},
  "geometry": {"coordinates":[-84.240613,40.051466],"type":"Point"}
}