{
  "type": "Feature",
  "properties": {
    "addr:full": "2200 Victory Pkwy Cincinnati OH 45206",
    "addr:housenumber": "2200",
    "addr:postcode": "45206",
    "addr:street": "Victory Pkwy",
    "iso:country": "US",
    "sg:address": "2200 Victory Pkwy",
    "sg:city": "Cincinnati",
    "sg:classifiers": [
      {
        "category": "Restaurant",
        "type": "Food \u0026 Drink"
      }
    ],
    "sg:phone": "+1 513 751 0933",
    "sg:postcode": "45206",
    "sg:province": "OH",
    "sg:tags": [
      "eating"
    ],
    "wof:name": "Edgecliff Room",
    "wof:placetype": "venue"
  },
  "geometry": {"coordinates":[-84.48528,39.12105],"type":"Point"}
}
