{
  "type": "Feature",
  "properties": {
    "addr:full":"254 W Main St Hillsboro OH 45133",
    "addr:housenumber":"254",
    "addr:postcode":"45133",
    "addr:street":"W Main St",
    "iso:country":"US",
    "sg:address":"254 W Main St",
    "sg:city":"Hillsboro",
    "sg:classifiers":[
        {
            "category":"Wholesale",
            "subcategory":"Farm Supplies",
            "type":"Manufacturing & Wholesale Goods"
        }
    ],
    "sg:phone":"+1 937 393 1958",
    "sg:postcode":"45133",
    "sg:province":"OH",
    "sg:tags":[
        "auction",
        "livestock",
        "market"
    ],
    "wof:name":"Union Stock Yards Co",
    "wof:placetype":"venue"
},
  "geometry": {"coordinates":[-83.61400399999999,39.202559],"type":"Point"}
}