{
  "type": "Feature",
  "properties": {
    "addr:full": "10216 Adelaide Ave Cleveland OH 44111",
    "addr:housenumber": "10216",
    "addr:postcode": "44111",
    "addr:street": "Adelaide Ave",
    "iso:country": "US",
    "sg:address": "10216 Adelaide Ave",
    "sg:city": "Cleveland",
    "sg:classifiers": [
      {
        "category": "Wholesale",
        "subcategory": "Scrap",
        "type": "Manufacturing \u0026 Wholesale Goods"
      }
    ],
    "sg:phone": "+1 216 631 0477",
    "sg:postcode": "44111",
    "sg:province": "OH",
    "sg:tags": [
      "material"
    ],
    "wof:name": "Homan Oil Service",
    "wof:placetype": "venue"
  },
  "geometry": {"coordinates":[-81.756016,41.459586],"type":"Point"}
}
