{
  "type": "Feature",
  "properties": {
    "iso:country":"US",
    "sg:address":"370 E Mark St",
    "sg:city":"Marion",
    "sg:classifiers":[
        {
            "category":"Social Services",
            "type":"Services"
        }
    ],
    "sg:phone":"+1 740 387 3462",
    "sg:postcode":"43302",
    "sg:province":"OH",
    "sg:tags":[
        "organization",
        "welfare"
    ],
    "wof:name":"Boys & Girls Club-Marion Cnty",
    "wof:placetype":"venue"
},
  "geometry": {"coordinates":[-83.121889,40.595106],"type":"Point"}
}