{
  "type": "Feature",
  "properties": {
    "iso:country":"US",
    "sg:address":"19 W 8th St",
    "sg:city":"Dresden",
    "sg:classifiers":[
        {
            "category":"Shopping",
            "subcategory":"Gifts & Souvenirs",
            "type":"Retail Goods"
        }
    ],
    "sg:phone":"+1 740 754 2470",
    "sg:postcode":"43821",
    "sg:province":"OH",
    "sg:tags":[
        "shop"
    ],
    "wof:name":"Heart Of The Home",
    "wof:placetype":"venue"
},
  "geometry": {"coordinates":[-82.011686,40.121191],"type":"Point"}
}