{
  "type": "Feature",
  "properties": {
    "addr:full": "20140 Lake Rd Cleveland OH 44116",
    "addr:housenumber": "20140",
    "addr:postcode": "44116",
    "addr:street": "Lake Rd",
    "iso:country": "US",
    "sg:address": "20140 Lake Rd",
    "sg:city": "Cleveland",
    "sg:classifiers": [
      {
        "category": "Education",
        "subcategory": "School",
        "type": "Public Place"
      }
    ],
    "sg:phone": "+1 440 356 6770",
    "sg:postcode": "44116",
    "sg:province": "OH",
    "sg:website": "www.rockyriverschools.com",
    "wof:name": "Kensington Intermediate School",
    "wof:placetype": "venue"
  },
  "geometry": {"coordinates":[-81.844977,41.483811],"type":"Point"}
}
