{
  "type": "Feature",
  "properties": {
    "iso:country":"US",
    "sg:address":"1560 S Byrne Rd",
    "sg:city":"Toledo",
    "sg:classifiers":[
        {
            "category":"Retail",
            "subcategory":"Laundry & Dry Cleaning",
            "type":"Services"
        }
    ],
    "sg:phone":"+1 419 536 3615",
    "sg:postcode":"43614",
    "sg:province":"OH",
    "sg:tags":[
        "cleaners"
    ],
    "wof:name":"Strater Cleaners",
    "wof:placetype":"venue"
},
  "geometry": {"coordinates":[-83.62583600000001,41.609908],"type":"Point"}
}