{
  "type": "Feature",
  "properties": {
    "addr:full":"6950 Grace Ave Cincinnati OH 45239",
    "addr:housenumber":"6950",
    "addr:postcode":"45239",
    "addr:street":"Grace Ave",
    "iso:country":"US",
    "sg:address":"6950 Grace Ave",
    "sg:city":"Cincinnati",
    "sg:classifiers":[
        {
            "category":"Recreation",
            "type":"Entertainment"
        }
    ],
    "sg:phone":"+1 513 522 5488",
    "sg:postcode":"45239",
    "sg:province":"OH",
    "sg:tags":[
        "pool",
        "swimming"
    ],
    "wof:name":"North College Hill Swim Pool",
    "wof:placetype":"venue"
},
  "geometry": {"coordinates":[-84.554383,39.218685],"type":"Point"}
}