{
  "type": "Feature",
  "properties": {
    "addr:full":"777 W State St Columbus OH 43222",
    "addr:housenumber":"777",
    "addr:postcode":"43222",
    "addr:street":"W State St",
    "iso:country":"US",
    "sg:address":"777 W State St",
    "sg:city":"Columbus",
    "sg:classifiers":[
        {
            "category":"Professional",
            "type":"Services"
        }
    ],
    "sg:phone":"+1 614 221 2024",
    "sg:postcode":"43222",
    "sg:province":"OH",
    "sg:tags":[
        "bureau"
    ],
    "wof:name":"Ohio EKG Svc",
    "wof:placetype":"venue"
},
  "geometry": {"coordinates":[-83.020413,39.957757],"type":"Point"}
}