{
  "type": "Feature",
  "properties": {
    "addr:full": "5770 Liberty Ave Vermilion OH 44089",
    "addr:housenumber": "5770",
    "addr:postcode": "44089",
    "addr:street": "Liberty Ave",
    "iso:country": "US",
    "sg:address": "5770 Liberty Ave",
    "sg:city": "Vermilion",
    "sg:classifiers": [
      {
        "category": "Professional",
        "type": "Services"
      }
    ],
    "sg:phone": "+1 440 967 2040",
    "sg:postcode": "44089",
    "sg:province": "OH",
    "wof:name": "Promac International Inc",
    "wof:placetype": "venue"
  },
  "geometry": {"coordinates":[-82.36915,41.422117],"type":"Point"}
}
