{
  "type": "Feature",
  "properties": {
    "addr:full":"1669 Fishinger Rd Columbus OH 43221",
    "addr:housenumber":"1669",
    "addr:postcode":"43221",
    "addr:street":"Fishinger Rd",
    "iso:country":"US",
    "sg:address":"1669 Fishinger Rd",
    "sg:city":"Columbus",
    "sg:classifiers":[
        {
            "category":"Banks & Credit Unions",
            "subcategory":"Bank",
            "type":"Services"
        }
    ],
    "sg:phone":"+1 614 451 8530",
    "sg:postcode":"43221",
    "sg:province":"OH",
    "sg:tags":[
        "state",
        "commercial"
    ],
    "sg:website":"www.53.com",
    "wof:name":"Fifth Third Bank",
    "wof:placetype":"venue"
},
  "geometry": {"coordinates":[-83.05897899999999,40.025995],"type":"Point"}
}