{
  "type": "Feature",
  "properties": {
    "addr:full": "7301 West Blvd Youngstown OH 44512",
    "addr:housenumber": "7301",
    "addr:postcode": "44512",
    "addr:street": "West Blvd",
    "iso:country": "US",
    "sg:address": "7301 West Blvd",
    "sg:city": "Youngstown",
    "sg:classifiers": [
      {
        "category": "Professional",
        "subcategory": "Lawyer \u0026 Legal Services",
        "type": "Services"
      }
    ],
    "sg:phone": "+1 330 758 2445",
    "sg:postcode": "44512",
    "sg:province": "OH",
    "sg:tags": [
      "attorney"
    ],
    "wof:name": "John F Petrony Law Offices",
    "wof:placetype": "venue"
  },
  "geometry": {"coordinates":[-80.682004,41.022506],"type":"Point"}
}
