{
  "type": "Feature",
  "properties": {
    "iso:country":"US",
    "sg:address":"7301 West Blvd",
    "sg:city":"Youngstown",
    "sg:classifiers":[
        {
            "category":"Professional",
            "subcategory":"Lawyer & Legal Services",
            "type":"Services"
        }
    ],
    "sg:phone":"+1 330 758 2445",
    "sg:postcode":"44512",
    "sg:province":"OH",
    "sg:tags":[
        "attorney"
    ],
    "wof:name":"John F Petrony Law Offices",
    "wof:placetype":"venue"
},
  "geometry": {"coordinates":[-80.68200400000001,41.022506],"type":"Point"}
}