{
  "type": "Feature",
  "properties": {
    "iso:country":"US",
    "sg:address":"11142 Kenwood Rd",
    "sg:city":"Cincinnati",
    "sg:classifiers":[
        {
            "category":"Personal",
            "type":"Services"
        }
    ],
    "sg:phone":"+1 513 469 7151",
    "sg:postcode":"45242",
    "sg:province":"OH",
    "sg:tags":[
        "hair",
        "replacement"
    ],
    "wof:name":"Apollo Hair Systems",
    "wof:placetype":"venue"
},
  "geometry": {"coordinates":[-84.373245,39.268413],"type":"Point"}
}