{
  "type": "Feature",
  "properties": {
    "addr:full": "27684 Royalton Rd Columbia Station OH 44028",
    "addr:housenumber": "27684",
    "addr:postcode": "44028",
    "addr:street": "Royalton Rd",
    "iso:country": "US",
    "sg:address": "27684 Royalton Rd",
    "sg:city": "Columbia Station",
    "sg:classifiers": [
      {
        "category": "Manufacturing",
        "subcategory": "Tools \u0026 Machinery",
        "type": "Manufacturing \u0026 Wholesale Goods"
      }
    ],
    "sg:phone": "+1 440 236 9600",
    "sg:postcode": "44028",
    "sg:province": "OH",
    "sg:tags": [
      "machine",
      "shop"
    ],
    "wof:name": "Modern Mold and Tool",
    "wof:placetype": "venue"
  },
  "geometry": {"coordinates":[-81.939228,41.31298],"type":"Point"}
}
