{
  "type": "Feature",
  "properties": {
    "iso:country":"US",
    "sg:address":"27684 Royalton Rd",
    "sg:city":"Columbia Station",
    "sg:classifiers":[
        {
            "category":"Manufacturing",
            "subcategory":"Tools & Machinery",
            "type":"Manufacturing & Wholesale Goods"
        }
    ],
    "sg:phone":"+1 440 236 9600",
    "sg:postcode":"44028",
    "sg:province":"OH",
    "sg:tags":[
        "machine",
        "shop"
    ],
    "wof:name":"Modern Mold and Tool",
    "wof:placetype":"venue"
},
  "geometry": {"coordinates":[-81.939228,41.31298],"type":"Point"}
}