{
  "type": "Feature",
  "properties": {
    "addr:full": "1222 Buck Run Rd Seaman OH 45679",
    "addr:housenumber": "1222",
    "addr:postcode": "45679",
    "addr:street": "Buck Run Rd",
    "iso:country": "US",
    "sg:address": "1222 Buck Run Rd",
    "sg:city": "Seaman",
    "sg:classifiers": [
      {
        "category": "Professional",
        "type": "Services"
      }
    ],
    "sg:phone": "+1 937 695 0968",
    "sg:postcode": "45679",
    "sg:province": "OH",
    "wof:name": "Kindle",
    "wof:placetype": "venue"
  },
  "geometry": {"coordinates":[-83.615436,38.973948],"type":"Point"}
}
