{
  "type": "Feature",
  "properties": {
    "addr:full":"3820 Zane Trace Dr Columbus OH 43228",
    "addr:housenumber":"3820",
    "addr:postcode":"43228",
    "addr:street":"Zane Trace Dr",
    "iso:country":"US",
    "sg:address":"3820 Zane Trace Dr",
    "sg:city":"Columbus",
    "sg:classifiers":[
        {
            "category":"Professional",
            "subcategory":"Business Services",
            "type":"Services"
        }
    ],
    "sg:phone":"+1 614 577 9088",
    "sg:postcode":"43228",
    "sg:province":"OH",
    "sg:tags":[
        "warehousing",
        "private",
        "air",
        "delivery",
        "field",
        "letter"
    ],
    "wof:name":"Accurate Logistics",
    "wof:placetype":"venue"
},
  "geometry": {"coordinates":[-83.110164,40.004406],"type":"Point"}
}