{
  "type": "Feature",
  "properties": {
    "addr:full": "1061 S Main St Centerville OH 45458",
    "addr:housenumber": "1061",
    "addr:postcode": "45458",
    "addr:street": "S Main St",
    "iso:country": "US",
    "sg:address": "1061 S Main St",
    "sg:city": "Centerville",
    "sg:classifiers": [
      {
        "category": "Shopping",
        "subcategory": "Discount \u0026 Variety Stores",
        "type": "Retail Goods"
      }
    ],
    "sg:phone": "+1 937 428 0641",
    "sg:postcode": "45458",
    "sg:province": "OH",
    "wof:name": "One Dollar Store",
    "wof:placetype": "venue"
  },
  "geometry": {"coordinates":[-84.160375,39.611868],"type":"Point"}
}
