{
  "type": "Feature",
  "properties": {
    "addr:full": "9401 Denison Ave Cleveland OH 44102",
    "addr:housenumber": "9401",
    "addr:postcode": "44102",
    "addr:street": "Denison Ave",
    "iso:country": "US",
    "sg:address": "9401 Denison Ave",
    "sg:city": "Cleveland",
    "sg:classifiers": [
      {
        "category": "Bars \u0026 Pubs",
        "type": "Food \u0026 Drink"
      }
    ],
    "sg:phone": "+1 216 961 8710",
    "sg:postcode": "44102",
    "sg:province": "OH",
    "wof:name": "Bonkers Cafe",
    "wof:placetype": "venue"
  },
  "geometry": {"coordinates":[-81.747774,41.46507],"type":"Point"}
}
