{
  "type": "Feature",
  "properties": {
    "addr:full": "2902 Jewett Rd Powell OH 43065",
    "addr:housenumber": "2902",
    "addr:postcode": "43065",
    "addr:street": "Jewett Rd",
    "iso:country": "US",
    "sg:address": "2902 Jewett Rd",
    "sg:city": "Powell",
    "sg:classifiers": [
      {
        "category": "Manufacturing",
        "subcategory": "Textiles",
        "type": "Manufacturing \u0026 Wholesale Goods"
      }
    ],
    "sg:phone": "+1 614 888 1019",
    "sg:postcode": "43065",
    "sg:province": "OH",
    "sg:tags": [
      "mfg"
    ],
    "wof:name": "Quality Products \u0026 Service",
    "wof:placetype": "venue"
  },
  "geometry": {"coordinates":[-83.061905,40.143966],"type":"Point"}
}
