{
  "type": "Feature",
  "properties": {
    "iso:country":"US",
    "sg:address":"589 Calvary Rd",
    "sg:city":"Seaman",
    "sg:phone":"+1 937 386 2460",
    "sg:postcode":"45679",
    "sg:province":"OH",
    "sg:tags":[
        "farm",
        "tobacco"
    ],
    "wof:name":"David Edenfield",
    "wof:placetype":"venue"
},
  "geometry": {"coordinates":[-83.58468499999999,38.986093],"type":"Point"}
}