{
  "type": "Feature",
  "properties": {
    "iso:country":"US",
    "sg:address":"11435 Hamilton Ave",
    "sg:city":"Cincinnati",
    "sg:classifiers":[
        {
            "category":"Food & Beverages",
            "subcategory":"Groceries & Convenience Stores",
            "type":"Retail Goods"
        }
    ],
    "sg:phone":"+1 513 825 6170",
    "sg:postcode":"45231",
    "sg:province":"OH",
    "wof:name":"Mac's",
    "wof:placetype":"venue"
},
  "geometry": {"coordinates":[-84.564142,39.289683],"type":"Point"}
}