{
  "type": "Feature",
  "properties": {
    "addr:full":"2520 Monroe St Toledo OH 43620",
    "addr:housenumber":"2520",
    "addr:postcode":"43620",
    "addr:street":"Monroe St",
    "iso:country":"US",
    "sg:address":"2520 Monroe St",
    "sg:city":"Toledo",
    "sg:classifiers":[
        {
            "category":"Real Estate",
            "subcategory":"Real Estate Operator",
            "type":"Services"
        }
    ],
    "sg:phone":"+1 419 244 1881",
    "sg:postcode":"43620",
    "sg:province":"OH",
    "sg:tags":[
        "apartment"
    ],
    "wof:name":"Plaza Apartments",
    "wof:placetype":"venue"
},
  "geometry": {"coordinates":[-83.559969,41.659686],"type":"Point"}
}