{
  "type": "Feature",
  "properties": {
    "addr:full":"72 N Lake St Madison OH 44057",
    "addr:housenumber":"72",
    "addr:postcode":"44057",
    "addr:street":"N Lake St",
    "iso:country":"US",
    "sg:address":"72 N Lake St",
    "sg:city":"Madison",
    "sg:classifiers":[
        {
            "category":"Autos & Motor Vehicles",
            "subcategory":"Fuel & Gas Station",
            "type":"Retail Goods"
        }
    ],
    "sg:phone":"+1 440 417 0616",
    "sg:postcode":"44057",
    "sg:province":"OH",
    "sg:tags":[
        "station",
        "gasoline"
    ],
    "wof:name":"True North 209",
    "wof:placetype":"venue"
},
  "geometry": {"coordinates":[-81.04709699999999,41.772749],"type":"Point"}
}