{
  "type": "Feature",
  "properties": {
    "addr:full": "1410 Motor Ave Fremont OH 43420",
    "addr:housenumber": "1410",
    "addr:postcode": "43420",
    "addr:street": "Motor Ave",
    "iso:country": "US",
    "sg:address": "1410 Motor Ave",
    "sg:city": "Fremont",
    "sg:classifiers": [
      {
        "category": "Manufacturing",
        "subcategory": "Rubber \u0026 Plastics",
        "type": "Manufacturing \u0026 Wholesale Goods"
      }
    ],
    "sg:phone": "+1 419 334 8951",
    "sg:postcode": "43420",
    "sg:province": "OH",
    "sg:tags": [
      "profile",
      "shape",
      "vehicle",
      "motor",
      "mfg"
    ],
    "sg:website": "www.eaton.com",
    "wof:name": "Eaton Inoac Company",
    "wof:placetype": "venue"
  },
  "geometry": {"coordinates":[-83.152194,41.364027],"type":"Point"}
}
