{
  "type": "Feature",
  "properties": {
    "iso:country":"US",
    "sg:address":"3031 Elm Rd NE",
    "sg:city":"Warren",
    "sg:classifiers":[
        {
            "category":"Banks & Credit Unions",
            "subcategory":"Bank",
            "type":"Services"
        }
    ],
    "sg:phone":"+1 330 372 7529",
    "sg:postcode":"44483",
    "sg:province":"OH",
    "sg:tags":[
        "personal",
        "institution"
    ],
    "wof:name":"Advance America",
    "wof:placetype":"venue"
},
  "geometry": {"coordinates":[-80.78358299999999,41.262911],"type":"Point"}
}