{
  "type": "Feature",
  "properties": {
    "addr:full": "3031 Elm Rd NE Warren OH 44483",
    "addr:housenumber": "3031",
    "addr:postcode": "44483",
    "addr:street": "Elm Rd Ne",
    "iso:country": "US",
    "sg:address": "3031 Elm Rd NE",
    "sg:city": "Warren",
    "sg:classifiers": [
      {
        "category": "Banks \u0026 Credit Unions",
        "subcategory": "Bank",
        "type": "Services"
      }
    ],
    "sg:phone": "+1 330 372 7529",
    "sg:postcode": "44483",
    "sg:province": "OH",
    "sg:tags": [
      "personal",
      "institution"
    ],
    "wof:name": "Advance America",
    "wof:placetype": "venue"
  },
  "geometry": {"coordinates":[-80.783583,41.262911],"type":"Point"}
}
