{
  "type": "Feature",
  "properties": {
    "iso:country":"US",
    "sg:address":"826 Busch Ct",
    "sg:city":"Columbus",
    "sg:classifiers":[
        {
            "category":"Wholesale",
            "subcategory":"Construction Materials",
            "type":"Manufacturing & Wholesale Goods"
        }
    ],
    "sg:phone":"+1 614 888 4695",
    "sg:postcode":"43229",
    "sg:province":"OH",
    "sg:tags":[
        "fence"
    ],
    "wof:name":"Around The House Fencing LTD",
    "wof:placetype":"venue"
},
  "geometry": {"coordinates":[-82.994597,40.096066],"type":"Point"}
}