{
  "type": "Feature",
  "properties": {
    "addr:full":"134 Merz Blvd Akron OH 44333",
    "addr:housenumber":"134",
    "addr:postcode":"44333",
    "addr:street":"Merz Blvd",
    "iso:country":"US",
    "sg:address":"134 Merz Blvd",
    "sg:city":"Akron",
    "sg:classifiers":[
        {
            "category":"Real Estate",
            "subcategory":"Real Estate Agent",
            "type":"Services"
        }
    ],
    "sg:phone":"+1 330 864 5011",
    "sg:postcode":"44333",
    "sg:province":"OH",
    "wof:name":"Howard W Myers",
    "wof:placetype":"venue"
},
  "geometry": {"coordinates":[-81.613051,41.133206],"type":"Point"}
}