{
  "type": "Feature",
  "properties": {
    "iso:country":"US",
    "sg:address":"6969 Industrial Pkwy",
    "sg:city":"Plain City",
    "sg:classifiers":[
        {
            "category":"Building & Trades",
            "subcategory":"Construction",
            "type":"Services"
        }
    ],
    "sg:phone":"+1 740 717 0604",
    "sg:postcode":"43064",
    "sg:province":"OH",
    "sg:tags":[
        "home",
        "builder"
    ],
    "wof:name":"Miriello & Assoc",
    "wof:placetype":"venue"
},
  "geometry": {"coordinates":[-83.18669,40.113437],"type":"Point"}
}