{
  "type": "Feature",
  "properties": {
    "addr:full":"213 W 4th St Delphos OH 45833",
    "addr:housenumber":"213",
    "addr:postcode":"45833",
    "addr:street":"W 4Th St",
    "iso:country":"US",
    "sg:address":"213 W 4th St",
    "sg:city":"Delphos",
    "sg:classifiers":[
        {
            "category":"Organizations",
            "subcategory":"Community Association",
            "type":"Services"
        }
    ],
    "sg:phone":"+1 419 692 8816",
    "sg:postcode":"45833",
    "sg:province":"OH",
    "sg:tags":[
        "military"
    ],
    "sg:website":"www.vfw.org",
    "wof:name":"Veterans Of Foreign Wars",
    "wof:placetype":"venue"
},
  "geometry": {"coordinates":[-84.341713,40.845804],"type":"Point"}
}