{
  "type": "Feature",
  "properties": {
    "addr:full":"37710 Rogers Rd Willoughby OH 44094",
    "addr:housenumber":"37710",
    "addr:postcode":"44094",
    "addr:street":"Rogers Rd",
    "iso:country":"US",
    "sg:address":"37710 Rogers Rd",
    "sg:city":"Willoughby",
    "sg:classifiers":[
        {
            "category":"Building & Trades",
            "subcategory":"Landscaping Services",
            "type":"Services"
        }
    ],
    "sg:phone":"+1 440 951 6257",
    "sg:postcode":"44094",
    "sg:province":"OH",
    "sg:tags":[
        "landscape"
    ],
    "wof:name":"J S Landscape",
    "wof:placetype":"venue"
},
  "geometry": {"coordinates":[-81.404943,41.57222],"type":"Point"}
}