{
  "type": "Feature",
  "properties": {
    "addr:full": "930 Grieves Ln Zanesville OH 43701",
    "addr:housenumber": "930",
    "addr:postcode": "43701",
    "addr:street": "Grieves Ln",
    "iso:country": "US",
    "sg:address": "930 Grieves Ln",
    "sg:city": "Zanesville",
    "sg:classifiers": [
      {
        "category": "Building \u0026 Trades",
        "subcategory": "Construction",
        "type": "Services"
      }
    ],
    "sg:phone": "+1 740 452 9251",
    "sg:postcode": "43701",
    "sg:province": "OH",
    "sg:tags": [
      "excavating",
      "contractor"
    ],
    "wof:name": "J \u0026 J Excavating \u0026 Landscaping",
    "wof:placetype": "venue"
  },
  "geometry": {"coordinates":[-81.942659,39.925916],"type":"Point"}
}
