{
  "type": "Feature",
  "properties": {
    "addr:full":"248 Main St Luckey OH 43443",
    "addr:housenumber":"248",
    "addr:postcode":"43443",
    "addr:street":"Main St",
    "iso:country":"US",
    "sg:address":"248 Main St",
    "sg:city":"Luckey",
    "sg:classifiers":[
        {
            "category":"Government",
            "subcategory":"Post Office",
            "type":"Public Place"
        }
    ],
    "sg:phone":"+1 419 833 4031",
    "sg:postcode":"43443",
    "sg:province":"OH",
    "wof:name":"US Post Office",
    "wof:placetype":"venue"
},
  "geometry": {"coordinates":[-83.484567,41.450659],"type":"Point"}
}