{
  "type": "Feature",
  "properties": {
    "addr:full": "655 Metro Pl S Dublin OH 43017",
    "addr:housenumber": "655",
    "addr:postcode": "43017",
    "addr:street": "Metro Pl",
    "iso:country": "US",
    "sg:address": "655 Metro Pl S",
    "sg:city": "Dublin",
    "sg:classifiers": [
      {
        "category": "Banks \u0026 Credit Unions",
        "subcategory": "Investment Brokerage",
        "type": "Services"
      }
    ],
    "sg:phone": "+1 614 761 2900",
    "sg:postcode": "43017",
    "sg:province": "OH",
    "sg:tags": [
      "security"
    ],
    "wof:name": "Cornerstone International Inc",
    "wof:placetype": "venue"
  },
  "geometry": {"coordinates":[-83.126202,40.093382],"type":"Point"}
}
