{
  "type": "Feature",
  "properties": {
    "addr:full":"38683 Taylor Pkwy Elyria OH 44035",
    "addr:housenumber":"38683",
    "addr:postcode":"44035",
    "addr:street":"Taylor Pkwy",
    "iso:country":"US",
    "sg:address":"38683 Taylor Pkwy",
    "sg:city":"Elyria",
    "sg:classifiers":[
        {
            "category":"Retail",
            "subcategory":"Repair Shop",
            "type":"Services"
        }
    ],
    "sg:phone":"+1 440 353 2000",
    "sg:postcode":"44035",
    "sg:province":"OH",
    "sg:tags":[
        "telecommunication"
    ],
    "wof:name":"Allen-Bradley",
    "wof:placetype":"venue"
},
  "geometry": {"coordinates":[-82.058933,41.371643],"type":"Point"}
}