{
  "type": "Feature",
  "properties": {
    "addr:full":"2455 Dutch Hollow Rd Lima OH 45807",
    "addr:housenumber":"2455",
    "addr:postcode":"45807",
    "addr:street":"Dutch Hollow Rd",
    "iso:country":"US",
    "sg:address":"2455 Dutch Hollow Rd",
    "sg:city":"Lima",
    "sg:classifiers":[
        {
            "category":"Professional",
            "type":"Services"
        }
    ],
    "sg:phone":"+1 419 339 6161",
    "sg:postcode":"45807",
    "sg:province":"OH",
    "wof:name":"Tc Company",
    "wof:placetype":"venue"
},
  "geometry": {"coordinates":[-84.20356,40.771836],"type":"Point"}
}