{
  "type": "Feature",
  "properties": {
    "iso:country":"US",
    "sg:address":"1894 Creeks Crossing Ct",
    "sg:city":"Grove City",
    "sg:classifiers":[
        {
            "category":"Building & Trades",
            "subcategory":"Construction",
            "type":"Services"
        }
    ],
    "sg:phone":"+1 614 801 9191",
    "sg:postcode":"43123",
    "sg:province":"OH",
    "sg:tags":[
        "home",
        "builder"
    ],
    "sg:website":"www.mihomes.com",
    "wof:name":"M/I Homes",
    "wof:placetype":"venue"
},
  "geometry": {"coordinates":[-83.05485299999999,39.856406],"type":"Point"}
}