{
  "type": "Feature",
  "properties": {
    "addr:full": "1894 Creeks Crossing Ct Grove City OH 43123",
    "addr:housenumber": "1894",
    "addr:postcode": "43123",
    "addr:street": "Creeks Crossing Ct",
    "iso:country": "US",
    "sg:address": "1894 Creeks Crossing Ct",
    "sg:city": "Grove City",
    "sg:classifiers": [
      {
        "category": "Building \u0026 Trades",
        "subcategory": "Construction",
        "type": "Services"
      }
    ],
    "sg:phone": "+1 614 801 9191",
    "sg:postcode": "43123",
    "sg:province": "OH",
    "sg:tags": [
      "home",
      "builder"
    ],
    "sg:website": "www.mihomes.com",
    "wof:name": "M/I Homes",
    "wof:placetype": "venue"
  },
  "geometry": {"coordinates":[-83.054853,39.856406],"type":"Point"}
}
