{
  "type": "Feature",
  "properties": {
    "addr:full":"2716 Sherman Rd Portsmouth OH 45662",
    "addr:housenumber":"2716",
    "addr:postcode":"45662",
    "addr:street":"Sherman Rd",
    "iso:country":"US",
    "sg:address":"2716 Sherman Rd",
    "sg:city":"Portsmouth",
    "sg:classifiers":[
        {
            "category":"Health Services",
            "subcategory":"Clinic",
            "type":"Services"
        }
    ],
    "sg:phone":"+1 740 354 4828",
    "sg:postcode":"45662",
    "sg:province":"OH",
    "sg:tags":[
        "home",
        "care"
    ],
    "wof:name":"Kendra Tener",
    "wof:placetype":"venue"
},
  "geometry": {"coordinates":[-82.981037,38.756487],"type":"Point"}
}