{
  "type": "Feature",
  "properties": {
    "addr:full": "4398 Midway Mall Elyria OH 44035",
    "addr:housenumber": "4398",
    "addr:postcode": "44035",
    "addr:street": "Midway Mall",
    "iso:country": "US",
    "sg:address": "4398 Midway Mall",
    "sg:city": "Elyria",
    "sg:classifiers": [
      {
        "category": "Shopping",
        "subcategory": "Gifts \u0026 Souvenirs",
        "type": "Retail Goods"
      }
    ],
    "sg:phone": "+1 440 324 5780",
    "sg:postcode": "44035",
    "sg:province": "OH",
    "sg:tags": [
      "shop"
    ],
    "wof:name": "Spencer Gifts LLC",
    "wof:placetype": "venue"
  },
  "geometry": {"coordinates":[-82.11351,41.398763],"type":"Point"}
}
