{
  "type": "Feature",
  "properties": {
    "iso:country":"US",
    "sg:address":"2229 Koehler Ave",
    "sg:city":"Dayton",
    "sg:classifiers":[
        {
            "category":"Shopping",
            "subcategory":"Gifts & Souvenirs",
            "type":"Retail Goods"
        }
    ],
    "sg:phone":"+1 937 274 5132",
    "sg:postcode":"45414",
    "sg:province":"OH",
    "wof:name":"Watering Cans R US",
    "wof:placetype":"venue"
},
  "geometry": {"coordinates":[-84.191135,39.809218],"type":"Point"}
}