{
  "type": "Feature",
  "properties": {
    "addr:full": "2229 Koehler Ave Dayton OH 45414",
    "addr:housenumber": "2229",
    "addr:postcode": "45414",
    "addr:street": "Koehler Ave",
    "iso:country": "US",
    "sg:address": "2229 Koehler Ave",
    "sg:city": "Dayton",
    "sg:classifiers": [
      {
        "category": "Shopping",
        "subcategory": "Gifts \u0026 Souvenirs",
        "type": "Retail Goods"
      }
    ],
    "sg:phone": "+1 937 274 5132",
    "sg:postcode": "45414",
    "sg:province": "OH",
    "wof:name": "Watering Cans R US",
    "wof:placetype": "venue"
  },
  "geometry": {"coordinates":[-84.191135,39.809218],"type":"Point"}
}
