{
  "type": "Feature",
  "properties": {
    "addr:full": "410 Kaler Ave Bucyrus OH 44820",
    "addr:housenumber": "410",
    "addr:postcode": "44820",
    "addr:street": "Kaler Ave",
    "iso:country": "US",
    "sg:address": "410 Kaler Ave",
    "sg:city": "Bucyrus",
    "sg:classifiers": [
      {
        "category": "Recreation",
        "type": "Entertainment"
      }
    ],
    "sg:phone": "+1 419 562 8899",
    "sg:postcode": "44820",
    "sg:province": "OH",
    "sg:tags": [
      "diving",
      "instruction"
    ],
    "wof:name": "Zen Scuba Diving",
    "wof:placetype": "venue"
  },
  "geometry": {"coordinates":[-82.979201,40.80531],"type":"Point"}
}
