{
  "type": "Feature",
  "properties": {
    "addr:full": "124 N Valley St Akron OH 44303",
    "addr:housenumber": "124",
    "addr:postcode": "44303",
    "addr:street": "N Valley St",
    "iso:country": "US",
    "sg:address": "124 N Valley St",
    "sg:city": "Akron",
    "sg:classifiers": [
      {
        "category": "Professional",
        "type": "Services"
      }
    ],
    "sg:phone": "+1 330 762 4853",
    "sg:postcode": "44303",
    "sg:province": "OH",
    "wof:name": "Anthony A Drevniak",
    "wof:placetype": "venue"
  },
  "geometry": {"coordinates":[-81.528981,41.093309],"type":"Point"}
}
