{
  "type": "Feature",
  "properties": {
    "iso:country":"US",
    "sg:address":"124 N Valley St",
    "sg:city":"Akron",
    "sg:classifiers":[
        {
            "category":"Professional",
            "type":"Services"
        }
    ],
    "sg:phone":"+1 330 762 4853",
    "sg:postcode":"44303",
    "sg:province":"OH",
    "wof:name":"Anthony A Drevniak",
    "wof:placetype":"venue"
},
  "geometry": {"coordinates":[-81.528981,41.093309],"type":"Point"}
}