{
  "type": "Feature",
  "properties": {
    "iso:country":"US",
    "sg:address":"4691 Turney Rd",
    "sg:city":"Cleveland",
    "sg:classifiers":[
        {
            "category":"Food & Beverages",
            "subcategory":"Specialty",
            "type":"Retail Goods"
        }
    ],
    "sg:phone":"+1 216 883 2211",
    "sg:postcode":"44125",
    "sg:province":"OH",
    "wof:name":"Town & Country Beverage",
    "wof:placetype":"venue"
},
  "geometry": {"coordinates":[-81.617182,41.432226],"type":"Point"}
}