{
  "type": "Feature",
  "properties": {
    "addr:full": "4691 Turney Rd Cleveland OH 44125",
    "addr:housenumber": "4691",
    "addr:postcode": "44125",
    "addr:street": "Turney Rd",
    "iso:country": "US",
    "sg:address": "4691 Turney Rd",
    "sg:city": "Cleveland",
    "sg:classifiers": [
      {
        "category": "Food \u0026 Beverages",
        "subcategory": "Specialty",
        "type": "Retail Goods"
      }
    ],
    "sg:phone": "+1 216 883 2211",
    "sg:postcode": "44125",
    "sg:province": "OH",
    "wof:name": "Town \u0026 Country Beverage",
    "wof:placetype": "venue"
  },
  "geometry": {"coordinates":[-81.617182,41.432226],"type":"Point"}
}
