{
  "type": "Feature",
  "properties": {
    "iso:country":"US",
    "sg:address":"18039 Neff Rd",
    "sg:city":"Cleveland",
    "sg:classifiers":[
        {
            "category":"Building & Trades",
            "subcategory":"Construction",
            "type":"Services"
        }
    ],
    "sg:phone":"+1 216 481 6912",
    "sg:postcode":"44119",
    "sg:province":"OH",
    "sg:tags":[
        "house"
    ],
    "wof:name":"Fine Home Improvement Inc",
    "wof:placetype":"venue"
},
  "geometry": {"coordinates":[-81.552424,41.584265],"type":"Point"}
}