{
  "type": "Feature",
  "properties": {
    "addr:full": "207 W High St Melmore OH 44830",
    "addr:housenumber": "207",
    "addr:postcode": "44830",
    "addr:street": "W High St",
    "iso:country": "US",
    "sg:address": "207 W High St",
    "sg:city": "Melmore",
    "sg:classifiers": [
      {
        "category": "Utilities",
        "subcategory": "Natural Gas",
        "type": "Services"
      }
    ],
    "sg:phone": "+1 419 397 6251",
    "sg:postcode": "44830",
    "sg:province": "OH",
    "sg:tags": [
      "transmission"
    ],
    "wof:name": "Columbia Gas Of Ohio Inc",
    "wof:placetype": "venue"
  },
  "geometry": {"coordinates":[-83.416622,41.16174],"type":"Point"}
}
