{
  "type": "Feature",
  "properties": {
    "addr:full":"401 Main St Zanesville OH 43701",
    "addr:housenumber":"401",
    "addr:postcode":"43701",
    "addr:street":"Main St",
    "iso:country":"US",
    "sg:address":"401 Main St",
    "sg:city":"Zanesville",
    "sg:classifiers":[
        {
            "category":"Government",
            "subcategory":"Office",
            "type":"Public Place"
        }
    ],
    "sg:phone":"+1 740 455 7193",
    "sg:postcode":"43701",
    "sg:province":"OH",
    "wof:name":"Muskingum County Fair Housing",
    "wof:placetype":"venue"
},
  "geometry": {"coordinates":[-82.007785,39.940146],"type":"Point"}
}