{
  "type": "Feature",
  "properties": {
    "iso:country":"US",
    "sg:address":"5001 Monroe St",
    "sg:city":"Toledo",
    "sg:classifiers":[
        {
            "category":"Shopping",
            "subcategory":"Department Store",
            "type":"Retail Goods"
        }
    ],
    "sg:phone":"+1 419 473 3317",
    "sg:postcode":"43606",
    "sg:province":"OH",
    "wof:name":"Spectramagic",
    "wof:placetype":"venue"
},
  "geometry": {"coordinates":[-83.642016,41.697742],"type":"Point"}
}