{
  "type": "Feature",
  "properties": {
    "iso:country":"US",
    "sg:address":"3211 Westgate",
    "sg:city":"Cleveland",
    "sg:classifiers":[
        {
            "category":"Shopping",
            "subcategory":"Clothing, Apparel, & Fashions",
            "type":"Retail Goods"
        }
    ],
    "sg:phone":"+1 440 779 8164",
    "sg:postcode":"44126",
    "sg:province":"OH",
    "wof:name":"Lener Shops",
    "wof:placetype":"venue"
},
  "geometry": {"coordinates":[-81.852795,41.458355],"type":"Point"}
}