{
  "type": "Feature",
  "properties": {
    "addr:full": "634 N 7th St Marietta OH 45750",
    "addr:housenumber": "634",
    "addr:postcode": "45750",
    "addr:street": "N 7Th St",
    "iso:country": "US",
    "sg:address": "634 N 7th St",
    "sg:city": "Marietta",
    "sg:classifiers": [
      {
        "category": "Recreation",
        "type": "Entertainment"
      }
    ],
    "sg:phone": "+1 740 373 2068",
    "sg:postcode": "45750",
    "sg:province": "OH",
    "sg:tags": [
      "amusement"
    ],
    "wof:name": "Coast To Coast Softball Inc",
    "wof:placetype": "venue"
  },
  "geometry": {"coordinates":[-81.455671,39.426584],"type":"Point"}
}
