{
  "type": "Feature",
  "properties": {
    "addr:full": "5294 Tamarack Cir E Columbus OH 43229",
    "addr:housenumber": "5294",
    "addr:postcode": "43229",
    "addr:street": "Tamarack Cir E",
    "iso:country": "US",
    "sg:address": "5294 Tamarack Cir E",
    "sg:city": "Columbus",
    "sg:classifiers": [
      {
        "category": "Food \u0026 Beverages",
        "subcategory": "Liquor \u0026 Beverages",
        "type": "Retail Goods"
      }
    ],
    "sg:phone": "+1 614 891 5929",
    "sg:postcode": "43229",
    "sg:province": "OH",
    "sg:tags": [
      "alcoholic"
    ],
    "wof:name": "Smart Bottle Inc",
    "wof:placetype": "venue"
  },
  "geometry": {"coordinates":[-82.964966,40.076534],"type":"Point"}
}
