{
  "type": "Feature",
  "properties": {
    "addr:full": "1745 W Market St Akron OH 44313",
    "addr:housenumber": "1745",
    "addr:postcode": "44313",
    "addr:street": "W Market St",
    "iso:country": "US",
    "sg:address": "1745 W Market St",
    "sg:city": "Akron",
    "sg:classifiers": [
      {
        "category": "Personal",
        "subcategory": "Beauty Salon",
        "type": "Services"
      }
    ],
    "sg:phone": "+1 330 836 9604",
    "sg:postcode": "44313",
    "sg:province": "OH",
    "sg:tags": [
      "treatment",
      "skin"
    ],
    "wof:name": "Here's Looking At You",
    "wof:placetype": "venue"
  },
  "geometry": {"coordinates":[-81.57262,41.111142],"type":"Point"}
}
