{
  "type": "Feature",
  "properties": {
    "addr:full":"1 Riverside Plz Columbus OH 43215",
    "addr:housenumber":"1",
    "addr:postcode":"43215",
    "addr:street":"Riverside Plz",
    "iso:country":"US",
    "sg:address":"1 Riverside Plz",
    "sg:city":"Columbus",
    "sg:classifiers":[
        {
            "category":"Shopping",
            "subcategory":"Computers & Home Electronics",
            "type":"Retail Goods"
        }
    ],
    "sg:phone":"+1 614 228 0662",
    "sg:postcode":"43215",
    "sg:province":"OH",
    "sg:tags":[
        "equipment",
        "satellite",
        "system"
    ],
    "sg:website":"www.xmradio.net",
    "wof:name":"XM Satellite Radio",
    "wof:placetype":"venue"
},
  "geometry": {"coordinates":[-83.005077,39.965077],"type":"Point"}
}