{
  "type": "Feature",
  "properties": {
    "addr:full": "1248 Coon Hollow Rd Lucasville OH 45648",
    "addr:housenumber": "1248",
    "addr:postcode": "45648",
    "addr:street": "Coon Hollow Rd",
    "iso:country": "US",
    "sg:address": "1248 Coon Hollow Rd",
    "sg:city": "Lucasville",
    "sg:classifiers": [
      {
        "category": "Real Estate",
        "subcategory": "Real Estate Operator",
        "type": "Services"
      }
    ],
    "sg:phone": "+1 740 259 5366",
    "sg:postcode": "45648",
    "sg:province": "OH",
    "sg:tags": [
      "building",
      "nonresidential"
    ],
    "wof:name": "Sisler John",
    "wof:placetype": "venue"
  },
  "geometry": {"coordinates":[-82.957631,38.930622],"type":"Point"}
}
