{
  "type": "Feature",
  "properties": {
    "iso:country":"US",
    "sg:address":"246 E 4th St",
    "sg:city":"Mansfield",
    "sg:classifiers":[
        {
            "category":"Wholesale",
            "subcategory":"Durable Goods & Equipment",
            "type":"Manufacturing & Wholesale Goods"
        }
    ],
    "sg:phone":"+1 419 521 5018",
    "sg:postcode":"44902",
    "sg:province":"OH",
    "wof:name":"Bbs Supply",
    "wof:placetype":"venue"
},
  "geometry": {"coordinates":[-82.506512,40.760612],"type":"Point"}
}