{
  "type": "Feature",
  "properties": {
    "iso:country":"US",
    "sg:address":"3205 W Central Ave",
    "sg:city":"Toledo",
    "sg:classifiers":[
        {
            "category":"Shopping",
            "subcategory":"Music",
            "type":"Retail Goods"
        }
    ],
    "sg:phone":"+1 419 537 7017",
    "sg:postcode":"43606",
    "sg:province":"OH",
    "sg:tags":[
        "record",
        "stereo",
        "tape",
        "equipment"
    ],
    "wof:name":"Coconuts",
    "wof:placetype":"venue"
},
  "geometry": {"coordinates":[-83.622606,41.677307],"type":"Point"}
}