{
  "type": "Feature",
  "properties": {
    "iso:country":"US",
    "sg:address":"1798 State Rte 534",
    "sg:city":"Southington",
    "sg:classifiers":[
        {
            "category":"Banks & Credit Unions",
            "subcategory":"Investment Brokerage",
            "type":"Services"
        }
    ],
    "sg:phone":"+1 330 898 8740",
    "sg:postcode":"44470",
    "sg:province":"OH",
    "sg:tags":[
        "security"
    ],
    "wof:name":"Simon Pj Consultants",
    "wof:placetype":"venue"
},
  "geometry": {"coordinates":[-80.97828,41.2676],"type":"Point"}
}