{
  "type": "Feature",
  "properties": {
    "iso:country":"US",
    "sg:address":"3401 Enterprise Pkwy",
    "sg:city":"Cleveland",
    "sg:classifiers":[
        {
            "category":"Organizations",
            "subcategory":"Non-profit Organization",
            "type":"Services"
        }
    ],
    "sg:phone":"+1 216 766 5730",
    "sg:postcode":"44122",
    "sg:province":"OH",
    "sg:tags":[
        "fund",
        "counselor",
        "raising"
    ],
    "wof:name":"Campbell & Co Inc",
    "wof:placetype":"venue"
},
  "geometry": {"coordinates":[-81.494602,41.466431],"type":"Point"}
}