{
  "type": "Feature",
  "properties": {
    "iso:country":"US",
    "sg:address":"775 US Hwy 42 NE",
    "sg:city":"London",
    "sg:classifiers":[
        {
            "category":"Restaurant",
            "type":"Food & Drink"
        }
    ],
    "sg:phone":"+1 740 852 4403",
    "sg:postcode":"43140",
    "sg:province":"OH",
    "sg:tags":[
        "eating"
    ],
    "wof:name":"Taco Bell",
    "wof:placetype":"venue"
},
  "geometry": {"coordinates":[-83.382541,39.949329],"type":"Point"}
}