{
  "type": "Feature",
  "properties": {
    "addr:full": "775 US Hwy 42 NE London OH 43140",
    "addr:housenumber": "775",
    "addr:postcode": "43140",
    "addr:street": "Us Hwy 42 Ne",
    "iso:country": "US",
    "sg:address": "775 US Hwy 42 NE",
    "sg:city": "London",
    "sg:classifiers": [
      {
        "category": "Restaurant",
        "type": "Food \u0026 Drink"
      }
    ],
    "sg:phone": "+1 740 852 4403",
    "sg:postcode": "43140",
    "sg:province": "OH",
    "sg:tags": [
      "eating"
    ],
    "wof:name": "Taco Bell",
    "wof:placetype": "venue"
  },
  "geometry": {"coordinates":[-83.382541,39.949329],"type":"Point"}
}
