{
  "type": "Feature",
  "properties": {
    "iso:country":"US",
    "sg:address":"904 E Broad St",
    "sg:city":"Columbus",
    "sg:classifiers":[
        {
            "category":"Organizations",
            "subcategory":"Religious Organization",
            "type":"Services"
        }
    ],
    "sg:phone":"+1 614 253 8865",
    "sg:postcode":"43205",
    "sg:province":"OH",
    "sg:tags":[
        "church"
    ],
    "wof:name":"Church Shiloh Full Gospel Chr",
    "wof:placetype":"venue"
},
  "geometry": {"coordinates":[-82.976833,39.965009],"type":"Point"}
}