{
  "type": "Feature",
  "properties": {
    "iso:country":"US",
    "sg:address":"10936 Shadow Glen Dr",
    "sg:city":"Loveland",
    "sg:classifiers":[
        {
            "category":"Building & Trades",
            "subcategory":"Construction",
            "type":"Services"
        }
    ],
    "sg:phone":"+1 513 774 8349",
    "sg:postcode":"45140",
    "sg:province":"OH",
    "sg:tags":[
        "contractor"
    ],
    "wof:name":"Contractors Register",
    "wof:placetype":"venue"
},
  "geometry": {"coordinates":[-84.286701,39.258723],"type":"Point"}
}