{
  "type": "Feature",
  "properties": {
    "iso:country":"US",
    "sg:address":"2265 Delaware Dr",
    "sg:city":"Cleveland",
    "sg:classifiers":[
        {
            "category":"Organizations",
            "subcategory":"Non-profit Organization",
            "type":"Services"
        }
    ],
    "sg:phone":"+1 216 229 2413",
    "sg:postcode":"44106",
    "sg:province":"OH",
    "wof:name":"CUSP",
    "wof:placetype":"venue"
},
  "geometry": {"coordinates":[-81.595716,41.498211],"type":"Point"}
}