{
  "type": "Feature",
  "properties": {
    "addr:full":"3437 Baronwood Blvd Dayton OH 45440",
    "addr:housenumber":"3437",
    "addr:postcode":"45440",
    "addr:street":"Baronwood Blvd",
    "iso:country":"US",
    "sg:address":"3437 Baronwood Blvd",
    "sg:city":"Dayton",
    "sg:classifiers":[
        {
            "category":"Professional",
            "type":"Services"
        }
    ],
    "sg:phone":"+1 937 429 3590",
    "sg:postcode":"45440",
    "sg:province":"OH",
    "wof:name":"Paper Recovry Inc",
    "wof:placetype":"venue"
},
  "geometry": {"coordinates":[-84.063383,39.69159],"type":"Point"}
}