{
  "type": "Feature",
  "properties": {
    "iso:country":"US",
    "sg:address":"715 Moorefield Rd",
    "sg:city":"Springfield",
    "sg:classifiers":[
        {
            "category":"Banks & Credit Unions",
            "subcategory":"Bank",
            "type":"Services"
        }
    ],
    "sg:phone":"+1 937 342 8979",
    "sg:postcode":"45502",
    "sg:province":"OH",
    "sg:tags":[
        "financing"
    ],
    "wof:name":"John Deere Credit Co",
    "wof:placetype":"venue"
},
  "geometry": {"coordinates":[-83.790001,39.996496],"type":"Point"}
}