{
  "type": "Feature",
  "properties": {
    "addr:full": "715 Moorefield Rd Springfield OH 45502",
    "addr:housenumber": "715",
    "addr:postcode": "45502",
    "addr:street": "Moorefield Rd",
    "iso:country": "US",
    "sg:address": "715 Moorefield Rd",
    "sg:city": "Springfield",
    "sg:classifiers": [
      {
        "category": "Banks \u0026 Credit Unions",
        "subcategory": "Bank",
        "type": "Services"
      }
    ],
    "sg:phone": "+1 937 342 8979",
    "sg:postcode": "45502",
    "sg:province": "OH",
    "sg:tags": [
      "financing"
    ],
    "wof:name": "John Deere Credit Co",
    "wof:placetype": "venue"
  },
  "geometry": {"coordinates":[-83.790001,39.996496],"type":"Point"}
}
