{
  "type": "Feature",
  "properties": {
    "addr:full":"1308 Wilson Ave Columbus OH 43206",
    "addr:housenumber":"1308",
    "addr:postcode":"43206",
    "addr:street":"Wilson Ave",
    "iso:country":"US",
    "sg:address":"1308 Wilson Ave",
    "sg:city":"Columbus",
    "sg:classifiers":[
        {
            "category":"Organizations",
            "subcategory":"Religious Organization",
            "type":"Services"
        }
    ],
    "sg:phone":"+1 614 444 5308",
    "sg:postcode":"43206",
    "sg:province":"OH",
    "sg:tags":[
        "church"
    ],
    "wof:name":"Independent True Crk Ukrainian",
    "wof:placetype":"venue"
},
  "geometry": {"coordinates":[-82.96807,39.939619],"type":"Point"}
}