{
  "type": "Feature",
  "properties": {
    "addr:full":"2225 Westlawn Dr Dayton OH 45440",
    "addr:housenumber":"2225",
    "addr:postcode":"45440",
    "addr:street":"Westlawn Dr",
    "iso:country":"US",
    "sg:address":"2225 Westlawn Dr",
    "sg:city":"Dayton",
    "sg:classifiers":[
        {
            "category":"Communications",
            "subcategory":"Film & Video Production",
            "type":"Services"
        }
    ],
    "sg:phone":"+1 937 436 4740",
    "sg:postcode":"45440",
    "sg:province":"OH",
    "sg:tags":[
        "duplication",
        "tape"
    ],
    "wof:name":"Filmworks Limited",
    "wof:placetype":"venue"
},
  "geometry": {"coordinates":[-84.12340500000001,39.672821],"type":"Point"}
}