{
  "type": "Feature",
  "properties": {
    "iso:country":"US",
    "sg:address":"4117 Whipple Ave NW",
    "sg:city":"Canton",
    "sg:classifiers":[
        {
            "category":"Personal",
            "subcategory":"Barber",
            "type":"Services"
        }
    ],
    "sg:phone":"+1 330 492 6971",
    "sg:postcode":"44718",
    "sg:province":"OH",
    "sg:tags":[
        "shop",
        "accessory"
    ],
    "wof:name":"Phils Hair Design",
    "wof:placetype":"venue"
},
  "geometry": {"coordinates":[-81.423979,40.843956],"type":"Point"}
}