{
  "type": "Feature",
  "properties": {
    "addr:full": "424 Middle Ave Elyria OH 44035",
    "addr:housenumber": "424",
    "addr:postcode": "44035",
    "addr:street": "Middle Ave",
    "iso:country": "US",
    "sg:address": "424 Middle Ave",
    "sg:city": "Elyria",
    "sg:classifiers": [
      {
        "category": "Professional",
        "subcategory": "Engineering",
        "type": "Services"
      }
    ],
    "sg:phone": "+1 440 322 6317",
    "sg:postcode": "44035",
    "sg:province": "OH",
    "sg:tags": [
      "engineer"
    ],
    "wof:name": "K S Assoc",
    "wof:placetype": "venue"
  },
  "geometry": {"coordinates":[-82.107066,41.363089],"type":"Point"}
}
