{
  "type": "Feature",
  "properties": {
    "addr:full":"9517 State Rte 14 Streetsboro OH 44241",
    "addr:housenumber":"9517",
    "addr:postcode":"44241",
    "addr:street":"State Rte 14",
    "iso:country":"US",
    "sg:address":"9517 State Rte 14",
    "sg:city":"Streetsboro",
    "sg:classifiers":[
        {
            "category":"Restaurant",
            "type":"Food & Drink"
        }
    ],
    "sg:phone":"+1 330 422 1420",
    "sg:postcode":"44241",
    "sg:province":"OH",
    "wof:name":"Quiznos Sub",
    "wof:placetype":"venue"
},
  "geometry": {"coordinates":[-81.355971,41.244153],"type":"Point"}
}