{
  "type": "Feature",
  "properties": {
    "iso:country":"US",
    "sg:address":"8149 Newcomb Rd",
    "sg:city":"Celina",
    "sg:classifiers":[
        {
            "category":"Building & Trades",
            "subcategory":"Landscaping Services",
            "type":"Services"
        }
    ],
    "sg:phone":"+1 419 584 1810",
    "sg:postcode":"45822",
    "sg:province":"OH",
    "sg:tags":[
        "tree",
        "care"
    ],
    "wof:name":"McKissack Certified Tree Care",
    "wof:placetype":"venue"
},
  "geometry": {"coordinates":[-84.532893,40.586753],"type":"Point"}
}