{
  "type": "Feature",
  "properties": {
    "addr:full": "248 E Main St Alliance OH 44601",
    "addr:housenumber": "248",
    "addr:postcode": "44601",
    "addr:street": "E Main St",
    "iso:country": "US",
    "sg:address": "248 E Main St",
    "sg:city": "Alliance",
    "sg:classifiers": [
      {
        "category": "Shopping",
        "subcategory": "Used Merchandise",
        "type": "Retail Goods"
      }
    ],
    "sg:phone": "+1 330 823 8920",
    "sg:postcode": "44601",
    "sg:province": "OH",
    "sg:tags": [
      "antique"
    ],
    "wof:name": "Attic Treasures Antiques",
    "wof:placetype": "venue"
  },
  "geometry": {"coordinates":[-81.101804,40.921862],"type":"Point"}
}
