{
  "type": "Feature",
  "properties": {
    "addr:full":"1114 Bowers Ave NW New Philadelphia OH 44663",
    "addr:housenumber":"1114",
    "addr:postcode":"44663",
    "addr:street":"Bowers Ave Nw New Philadelphia",
    "iso:country":"US",
    "sg:address":"1114 Bowers Ave NW",
    "sg:city":"New Philadelphia",
    "sg:classifiers":[
        {
            "category":"Personal",
            "subcategory":"Beauty Salon",
            "type":"Services"
        }
    ],
    "sg:phone":"+1 330 364 5759",
    "sg:postcode":"44663",
    "sg:province":"OH",
    "sg:tags":[
        "shop"
    ],
    "wof:name":"Hair Graphics Inc",
    "wof:placetype":"venue"
},
  "geometry": {"coordinates":[-81.46146299999999,40.505245],"type":"Point"}
}