{
  "type": "Feature",
  "properties": {
    "addr:full": "458 S Main St Pataskala OH 43062",
    "addr:housenumber": "458",
    "addr:postcode": "43062",
    "addr:street": "S Main St",
    "iso:country": "US",
    "sg:address": "458 S Main St",
    "sg:city": "Pataskala",
    "sg:classifiers": [
      {
        "category": "Social Services",
        "subcategory": "Child Care",
        "type": "Services"
      }
    ],
    "sg:phone": "+1 740 927 9795",
    "sg:postcode": "43062",
    "sg:province": "OH",
    "wof:name": "Learn Grow Play Child Dev Ctr",
    "wof:placetype": "venue"
  },
  "geometry": {"coordinates":[-82.675351,39.993517],"type":"Point"}
}
