{
  "type": "Feature",
  "properties": {
    "addr:full": "10856 Liberty-Union Rd Van Wert OH 45891",
    "addr:housenumber": "10856",
    "addr:postcode": "45891",
    "addr:street": "Liberty-Union Rd",
    "iso:country": "US",
    "sg:address": "10856 Liberty-Union Rd",
    "sg:city": "Van Wert",
    "sg:classifiers": [
      {
        "category": "Building \u0026 Trades",
        "subcategory": "Construction",
        "type": "Services"
      }
    ],
    "sg:phone": "+1 419 232 4786",
    "sg:postcode": "45891",
    "sg:province": "OH",
    "sg:tags": [
      "excavation",
      "operator",
      "contractor",
      "local",
      "trucking"
    ],
    "wof:name": "Mengerink Gtshell Excvtg Trckg",
    "wof:placetype": "venue"
  },
  "geometry": {"coordinates":[-84.629379,40.846763],"type":"Point"}
}
