{
  "type": "Feature",
  "properties": {
    "addr:full": "3485 E Broad St Columbus OH 43213",
    "addr:housenumber": "3485",
    "addr:postcode": "43213",
    "addr:street": "E Broad St",
    "iso:country": "US",
    "sg:address": "3485 E Broad St",
    "sg:city": "Columbus",
    "sg:classifiers": [
      {
        "category": "Banks \u0026 Credit Unions",
        "subcategory": "Bank",
        "type": "Services"
      }
    ],
    "sg:phone": "+1 614 766 1848",
    "sg:postcode": "43213",
    "sg:province": "OH",
    "sg:tags": [
      "cashing",
      "check"
    ],
    "wof:name": "United Check Cashing Co",
    "wof:placetype": "venue"
  },
  "geometry": {"coordinates":[-82.906969,39.972618],"type":"Point"}
}
