{
  "type": "Feature",
  "properties": {
    "iso:country":"US",
    "sg:address":"3485 E Broad St",
    "sg:city":"Columbus",
    "sg:classifiers":[
        {
            "category":"Banks & Credit Unions",
            "subcategory":"Bank",
            "type":"Services"
        }
    ],
    "sg:phone":"+1 614 766 1848",
    "sg:postcode":"43213",
    "sg:province":"OH",
    "sg:tags":[
        "cashing",
        "check"
    ],
    "wof:name":"United Check Cashing Co",
    "wof:placetype":"venue"
},
  "geometry": {"coordinates":[-82.906969,39.972618],"type":"Point"}
}