{
  "type": "Feature",
  "properties": {
    "addr:full":"415 E Mound St Columbus OH 43215",
    "addr:housenumber":"415",
    "addr:postcode":"43215",
    "addr:street":"E Mound St",
    "iso:country":"US",
    "sg:address":"415 E Mound St",
    "sg:city":"Columbus",
    "sg:classifiers":[
        {
            "category":"Health Services",
            "subcategory":"Doctor",
            "type":"Services"
        }
    ],
    "sg:phone":"+1 614 228 1773",
    "sg:postcode":"43215",
    "sg:province":"OH",
    "sg:tags":[
        "clinic"
    ],
    "sg:website":"www.davita.com",
    "wof:name":"Da Vita Inc",
    "wof:placetype":"venue"
},
  "geometry": {"coordinates":[-82.98835699999999,39.955951],"type":"Point"}
}