{
  "type": "Feature",
  "properties": {
    "iso:country":"US",
    "sg:address":"16615 US Hwy 68",
    "sg:city":"Mount Orab",
    "sg:classifiers":[
        {
            "category":"Building & Trades",
            "subcategory":"Construction",
            "type":"Services"
        }
    ],
    "sg:phone":"+1 937 444 2540",
    "sg:postcode":"45154",
    "sg:province":"OH",
    "sg:tags":[
        "house"
    ],
    "wof:name":"Ellis Bryant",
    "wof:placetype":"venue"
},
  "geometry": {"coordinates":[-83.930513,39.094878],"type":"Point"}
}