{
  "type": "Feature",
  "properties": {
    "addr:full": "16615 US Hwy 68 Mount Orab OH 45154",
    "addr:postcode": "16615;45154",
    "addr:street": "Us Hwy 68 Mount",
    "iso:country": "US",
    "sg:address": "16615 US Hwy 68",
    "sg:city": "Mount Orab",
    "sg:classifiers": [
      {
        "category": "Building \u0026 Trades",
        "subcategory": "Construction",
        "type": "Services"
      }
    ],
    "sg:phone": "+1 937 444 2540",
    "sg:postcode": "45154",
    "sg:province": "OH",
    "sg:tags": [
      "house"
    ],
    "wof:name": "Ellis Bryant",
    "wof:placetype": "venue"
  },
  "geometry": {"coordinates":[-83.930513,39.094878],"type":"Point"}
}
