{
  "type": "Feature",
  "properties": {
    "iso:country":"US",
    "sg:address":"7908 Hamilton Ave",
    "sg:city":"Cincinnati",
    "sg:classifiers":[
        {
            "category":"Manufacturing",
            "subcategory":"Printing",
            "type":"Manufacturing & Wholesale Goods"
        }
    ],
    "sg:phone":"+1 513 522 1822",
    "sg:postcode":"45231",
    "sg:province":"OH",
    "sg:tags":[
        "printer"
    ],
    "wof:name":"Gruber Printing",
    "wof:placetype":"venue"
},
  "geometry": {"coordinates":[-84.54724299999999,39.242456],"type":"Point"}
}