{
  "type": "Feature",
  "properties": {
    "addr:full":"199 N Main St Mansfield OH 44902",
    "addr:housenumber":"199",
    "addr:postcode":"44902",
    "addr:street":"N Main St",
    "iso:country":"US",
    "sg:address":"199 N Main St",
    "sg:city":"Mansfield",
    "sg:classifiers":[
        {
            "category":"Organizations",
            "subcategory":"Non-profit Organization",
            "type":"Services"
        }
    ],
    "sg:phone":"+1 419 522 1875",
    "sg:postcode":"44902",
    "sg:province":"OH",
    "wof:name":"Central City Economic Devmnt",
    "wof:placetype":"venue"
},
  "geometry": {"coordinates":[-82.515277,40.764201],"type":"Point"}
}