{
  "type": "Feature",
  "properties": {
    "iso:country":"US",
    "sg:address":"2323 W 5th Ave",
    "sg:city":"Columbus",
    "sg:classifiers":[
        {
            "category":"Communications",
            "subcategory":"Radio Station",
            "type":"Services"
        }
    ],
    "sg:phone":"+1 614 821 1230",
    "sg:postcode":"43204",
    "sg:province":"OH",
    "sg:tags":[
        "company",
        "broadcasting"
    ],
    "wof:name":"WCOL",
    "wof:placetype":"venue"
},
  "geometry": {"coordinates":[-83.069276,39.988504],"type":"Point"}
}