{
  "type": "Feature",
  "properties": {
    "iso:country":"US",
    "sg:address":"2130 S Union Ave",
    "sg:city":"Alliance",
    "sg:classifiers":[
        {
            "category":"Professional",
            "subcategory":"Management & Consulting",
            "type":"Services"
        }
    ],
    "sg:phone":"+1 330 829 9900",
    "sg:postcode":"44601",
    "sg:province":"OH",
    "sg:tags":[
        "consultant",
        "training"
    ],
    "wof:name":"Alliance Training Group LLC",
    "wof:placetype":"venue"
},
  "geometry": {"coordinates":[-81.105816,40.900235],"type":"Point"}
}