{
  "type": "Feature",
  "properties": {
    "addr:full": "3000 Culver Dr Hilliard OH 43026",
    "addr:housenumber": "3000",
    "addr:postcode": "43026",
    "addr:street": "Culver Dr",
    "iso:country": "US",
    "sg:address": "3000 Culver Dr",
    "sg:city": "Hilliard",
    "sg:classifiers": [
      {
        "category": "Building \u0026 Trades",
        "subcategory": "Construction",
        "type": "Services"
      }
    ],
    "sg:phone": "+1 614 850 9363",
    "sg:postcode": "43026",
    "sg:province": "OH",
    "sg:tags": [
      "roads",
      "contracting",
      "general"
    ],
    "wof:name": "North Atlantic Construction Co",
    "wof:placetype": "venue"
  },
  "geometry": {"coordinates":[-83.14204,40.012559],"type":"Point"}
}
