{
  "type": "Feature",
  "properties": {
    "addr:full": "730 Colvin St Belpre OH 45714",
    "addr:housenumber": "730",
    "addr:postcode": "45714",
    "addr:street": "Colvin St",
    "iso:country": "US",
    "sg:address": "730 Colvin St",
    "sg:city": "Belpre",
    "sg:classifiers": [
      {
        "category": "Building \u0026 Trades",
        "subcategory": "Construction",
        "type": "Services"
      }
    ],
    "sg:phone": "+1 740 423 1444",
    "sg:postcode": "45714",
    "sg:province": "OH",
    "sg:tags": [
      "house"
    ],
    "wof:name": "River City Construction",
    "wof:placetype": "venue"
  },
  "geometry": {"coordinates":[-81.602128,39.280141],"type":"Point"}
}
