{
  "type": "Feature",
  "properties": {
    "iso:country":"US",
    "sg:address":"2101 W Breese Rd",
    "sg:city":"Lima",
    "sg:classifiers":[
        {
            "category":"Organizations",
            "subcategory":"Religious Organization",
            "type":"Services"
        }
    ],
    "sg:phone":"+1 419 999 1936",
    "sg:postcode":"45806",
    "sg:province":"OH",
    "sg:tags":[
        "church"
    ],
    "wof:name":"Meadowbrook Baptist Church",
    "wof:placetype":"venue"
},
  "geometry": {"coordinates":[-84.142472,40.686488],"type":"Point"}
}