{
  "type": "Feature",
  "properties": {
    "addr:full":"7413 Wahl Rd Vickery OH 43464",
    "addr:housenumber":"7413",
    "addr:postcode":"43464",
    "addr:street":"Wahl Rd",
    "iso:country":"US",
    "sg:address":"7413 Wahl Rd",
    "sg:city":"Vickery",
    "sg:classifiers":[
        {
            "category":"Bars & Pubs",
            "type":"Food & Drink"
        }
    ],
    "sg:postcode":"43464",
    "sg:province":"OH",
    "wof:name":"2 Cans Tiki Bar",
    "wof:placetype":"venue"
},
  "geometry": {"coordinates":[-82.895781,41.431474],"type":"Point"}
}