{
  "type": "Feature",
  "properties": {
    "addr:full":"3359 Carey St Harrod OH 45850",
    "addr:housenumber":"3359",
    "addr:postcode":"45850",
    "addr:street":"Carey St",
    "iso:country":"US",
    "sg:address":"3359 Carey St",
    "sg:city":"Harrod",
    "sg:classifiers":[
        {
            "category":"Building & Trades",
            "subcategory":"Construction",
            "type":"Services"
        }
    ],
    "sg:phone":"+1 419 648 6703",
    "sg:postcode":"45850",
    "sg:province":"OH",
    "sg:tags":[
        "house"
    ],
    "wof:name":"Custom Home Improvements",
    "wof:placetype":"venue"
},
  "geometry": {"coordinates":[-83.97843899999999,40.693412],"type":"Point"}
}