{
  "type": "Feature",
  "properties": {
    "addr:full":"22 S Miami St West Milton OH 45383",
    "addr:housenumber":"22",
    "addr:postcode":"45383",
    "addr:street":"S Miami St West",
    "iso:country":"US",
    "sg:address":"22 S Miami St",
    "sg:city":"West Milton",
    "sg:classifiers":[
        {
            "category":"Personal",
            "subcategory":"Barber",
            "type":"Services"
        }
    ],
    "sg:phone":"+1 937 698 3400",
    "sg:postcode":"45383",
    "sg:province":"OH",
    "wof:name":"Hair Liners Stylists & Barber",
    "wof:placetype":"venue"
},
  "geometry": {"coordinates":[-84.32768,39.962311],"type":"Point"}
}