{
  "type": "Feature",
  "properties": {
    "iso:country":"US",
    "sg:address":"912 Lydian Cir",
    "sg:city":"Brunswick",
    "sg:classifiers":[
        {
            "category":"Building & Trades",
            "subcategory":"Construction",
            "type":"Services"
        }
    ],
    "sg:phone":"+1 330 273 4308",
    "sg:postcode":"44212",
    "sg:province":"OH",
    "sg:tags":[
        "excavation",
        "contractor"
    ],
    "wof:name":"Berndt Schneider",
    "wof:placetype":"venue"
},
  "geometry": {"coordinates":[-81.810312,41.250765],"type":"Point"}
}