{
  "type": "Feature",
  "properties": {
    "addr:full": "4597 Ridge Rd Cleveland OH 44144",
    "addr:housenumber": "4597",
    "addr:postcode": "44144",
    "addr:street": "Ridge Rd",
    "iso:country": "US",
    "sg:address": "4597 Ridge Rd",
    "sg:city": "Cleveland",
    "sg:classifiers": [
      {
        "category": "Health Services",
        "subcategory": "Doctor",
        "type": "Services"
      }
    ],
    "sg:phone": "+1 216 398 7285",
    "sg:postcode": "44144",
    "sg:province": "OH",
    "sg:tags": [
      "dentist"
    ],
    "wof:name": "William M Beegan DDS",
    "wof:placetype": "venue"
  },
  "geometry": {"coordinates":[-81.735233,41.431749],"type":"Point"}
}
