{
  "type": "Feature",
  "properties": {
    "addr:full": "2209 N High St Columbus OH 43201",
    "addr:housenumber": "2209",
    "addr:postcode": "43201",
    "addr:street": "N High St",
    "iso:country": "US",
    "sg:address": "2209 N High St",
    "sg:city": "Columbus",
    "sg:classifiers": [
      {
        "category": "Shopping",
        "subcategory": "Gifts \u0026 Souvenirs",
        "type": "Retail Goods"
      }
    ],
    "sg:phone": "+1 614 299 5498",
    "sg:postcode": "43201",
    "sg:province": "OH",
    "sg:tags": [
      "shop"
    ],
    "wof:name": "Contra Culture",
    "wof:placetype": "venue"
  },
  "geometry": {"coordinates":[-83.009702,40.007973],"type":"Point"}
}
