{
  "type": "Feature",
  "properties": {
    "iso:country":"US",
    "sg:address":"98 Glendale Milford Rd",
    "sg:city":"Cincinnati",
    "sg:classifiers":[
        {
            "category":"Freight",
            "type":"Transportation"
        }
    ],
    "sg:phone":"+1 513 771 4782",
    "sg:postcode":"45215",
    "sg:province":"OH",
    "sg:tags":[
        "warehousing"
    ],
    "wof:name":"World Super Svc Inc",
    "wof:placetype":"venue"
},
  "geometry": {"coordinates":[-84.468221,39.257773],"type":"Point"}
}