{
  "type": "Feature",
  "properties": {
    "addr:full": "439 Brucehills Dr Cincinnati OH 45224",
    "addr:housenumber": "439",
    "addr:postcode": "45224",
    "addr:street": "Brucehills Dr",
    "iso:country": "US",
    "sg:address": "439 Brucehills Dr",
    "sg:city": "Cincinnati",
    "sg:classifiers": [
      {
        "category": "Wholesale",
        "subcategory": "Non-durable Goods",
        "type": "Manufacturing \u0026 Wholesale Goods"
      }
    ],
    "sg:phone": "+1 513 761 7645",
    "sg:postcode": "45224",
    "sg:province": "OH",
    "wof:name": "Cat Equipment Co Ltd",
    "wof:placetype": "venue"
  },
  "geometry": {"coordinates":[-84.496169,39.214337],"type":"Point"}
}
