{
  "type": "Feature",
  "properties": {
    "iso:country":"US",
    "sg:address":"7441 N US Hwy 68",
    "sg:city":"Wilmington",
    "sg:classifiers":[
        {
            "category":"Retail",
            "subcategory":"Animal Services",
            "type":"Services"
        }
    ],
    "sg:phone":"+1 937 486 1314",
    "sg:postcode":"45177",
    "sg:province":"OH",
    "wof:name":"Ceasarscreek Brding Kennel LLC",
    "wof:placetype":"venue"
},
  "geometry": {"coordinates":[-83.850114,39.542115],"type":"Point"}
}