{
  "type": "Feature",
  "properties": {
    "iso:country":"US",
    "sg:address":"16500 Louisville St NE",
    "sg:city":"Homeworth",
    "sg:classifiers":[
        {
            "category":"Shopping",
            "subcategory":"Hobbies, Toys, & Games",
            "type":"Retail Goods"
        },
        {
            "category":"Shopping",
            "subcategory":"Gifts & Souvenirs",
            "type":"Retail Goods"
        }
    ],
    "sg:phone":"+1 330 823 8075",
    "sg:postcode":"44634",
    "sg:province":"OH",
    "sg:tags":[
        "florist",
        "craft",
        "supply"
    ],
    "wof:name":"Earth's Garden",
    "wof:placetype":"venue"
},
  "geometry": {"coordinates":[-81.09529499999999,40.834445],"type":"Point"}
}