{
  "type": "Feature",
  "properties": {
    "addr:full": "16500 Louisville St NE Homeworth OH 44634",
    "addr:housenumber": "16500",
    "addr:postcode": "44634",
    "addr:street": "Louisville St Ne",
    "iso:country": "US",
    "sg:address": "16500 Louisville St NE",
    "sg:city": "Homeworth",
    "sg:classifiers": [
      {
        "category": "Shopping",
        "subcategory": "Hobbies, Toys, \u0026 Games",
        "type": "Retail Goods"
      },
      {
        "category": "Shopping",
        "subcategory": "Gifts \u0026 Souvenirs",
        "type": "Retail Goods"
      }
    ],
    "sg:phone": "+1 330 823 8075",
    "sg:postcode": "44634",
    "sg:province": "OH",
    "sg:tags": [
      "florist",
      "craft",
      "supply"
    ],
    "wof:name": "Earth's Garden",
    "wof:placetype": "venue"
  },
  "geometry": {"coordinates":[-81.095295,40.834445],"type":"Point"}
}
