{
  "type": "Feature",
  "properties": {
    "addr:full":"105 S Market St Lisbon OH 44432",
    "addr:housenumber":"105",
    "addr:postcode":"44432",
    "addr:street":"S Market St",
    "iso:country":"US",
    "sg:address":"105 S Market St",
    "sg:city":"Lisbon",
    "sg:classifiers":[
        {
            "category":"Government",
            "subcategory":"Office",
            "type":"Public Place"
        }
    ],
    "sg:phone":"+1 330 424 9515",
    "sg:postcode":"44432",
    "sg:province":"OH",
    "sg:tags":[
        "county"
    ],
    "sg:website":"www.columbianacntyauditor.org",
    "wof:name":"Columbiana County Auditor",
    "wof:placetype":"venue"
},
  "geometry": {"coordinates":[-80.768091,40.772077],"type":"Point"}
}