{
  "type": "Feature",
  "properties": {
    "addr:full":"107 Main St Corning OH 43730",
    "addr:housenumber":"107",
    "addr:postcode":"43730",
    "addr:street":"Main St",
    "iso:country":"US",
    "sg:address":"107 Main St",
    "sg:city":"Corning",
    "sg:classifiers":[
        {
            "category":"Government",
            "subcategory":"Fire Station",
            "type":"Public Place"
        }
    ],
    "sg:phone":"+1 740 347 4511",
    "sg:postcode":"43730",
    "sg:province":"OH",
    "sg:tags":[
        "department"
    ],
    "wof:name":"Corning Fire Dept",
    "wof:placetype":"venue"
},
  "geometry": {"coordinates":[-82.08927799999999,39.602747],"type":"Point"}
}