{
  "type": "Feature",
  "properties": {
    "iso:country":"US",
    "sg:address":"1155 Newark Rd",
    "sg:city":"Zanesville",
    "sg:classifiers":[
        {
            "category":"Building & Trades",
            "subcategory":"Pest Control",
            "type":"Services"
        }
    ],
    "sg:phone":"+1 740 452 6757",
    "sg:postcode":"43701",
    "sg:province":"OH",
    "wof:name":"Terminix International Co",
    "wof:placetype":"venue"
},
  "geometry": {"coordinates":[-82.02435199999999,39.956514],"type":"Point"}
}