{
  "type": "Feature",
  "properties": {
    "addr:full": "1155 Newark Rd Zanesville OH 43701",
    "addr:housenumber": "1155",
    "addr:postcode": "43701",
    "addr:street": "Newark Rd",
    "iso:country": "US",
    "sg:address": "1155 Newark Rd",
    "sg:city": "Zanesville",
    "sg:classifiers": [
      {
        "category": "Building \u0026 Trades",
        "subcategory": "Pest Control",
        "type": "Services"
      }
    ],
    "sg:phone": "+1 740 452 6757",
    "sg:postcode": "43701",
    "sg:province": "OH",
    "wof:name": "Terminix International Co",
    "wof:placetype": "venue"
  },
  "geometry": {"coordinates":[-82.024352,39.956514],"type":"Point"}
}
