{
  "type": "Feature",
  "properties": {
    "iso:country":"US",
    "sg:address":"2980 Maine Ave",
    "sg:city":"Perry",
    "sg:classifiers":[
        {
            "category":"Wholesale",
            "subcategory":"Construction Materials",
            "type":"Manufacturing & Wholesale Goods"
        }
    ],
    "sg:phone":"+1 440 796 4717",
    "sg:postcode":"44081",
    "sg:province":"OH",
    "wof:name":"Cooper Concrete Design",
    "wof:placetype":"venue"
},
  "geometry": {"coordinates":[-81.173239,41.751401],"type":"Point"}
}