{
  "type": "Feature",
  "properties": {
    "addr:full":"960 Brocklesby Rd Caledonia OH 43314",
    "addr:housenumber":"960",
    "addr:postcode":"43314",
    "addr:street":"Brocklesby Rd",
    "iso:country":"US",
    "sg:address":"960 Brocklesby Rd",
    "sg:city":"Caledonia",
    "sg:classifiers":[
        {
            "category":"Manufacturing",
            "subcategory":"Printing",
            "type":"Manufacturing & Wholesale Goods"
        }
    ],
    "sg:phone":"+1 419 845 3218",
    "sg:postcode":"43314",
    "sg:province":"OH",
    "sg:tags":[
        "book"
    ],
    "wof:name":"JB Computer Services",
    "wof:placetype":"venue"
},
  "geometry": {"coordinates":[-83.005101,40.614296],"type":"Point"}
}