{
  "type": "Feature",
  "properties": {
    "addr:full":"750 Main St Milford OH 45150",
    "addr:housenumber":"750",
    "addr:postcode":"45150",
    "addr:street":"Main St",
    "iso:country":"US",
    "sg:address":"750 Main St",
    "sg:city":"Milford",
    "sg:classifiers":[
        {
            "category":"Autos & Motor Vehicles",
            "subcategory":"Auto Supplies",
            "type":"Retail Goods"
        }
    ],
    "sg:phone":"+1 513 576 1349",
    "sg:postcode":"45150",
    "sg:province":"OH",
    "sg:tags":[
        "automobile",
        "stereo",
        "radio"
    ],
    "wof:name":"G V Designs",
    "wof:placetype":"venue"
},
  "geometry": {"coordinates":[-84.28054,39.177847],"type":"Point"}
}