{
  "type": "Feature",
  "properties": {
    "addr:full": "77 S Franklin St Chagrin Falls OH 44022",
    "addr:housenumber": "77",
    "addr:postcode": "44022",
    "addr:street": "S Franklin St",
    "iso:country": "US",
    "sg:address": "77 S Franklin St",
    "sg:city": "Chagrin Falls",
    "sg:classifiers": [
      {
        "category": "Shopping",
        "subcategory": "Books",
        "type": "Retail Goods"
      }
    ],
    "sg:phone": "+1 440 247 3616",
    "sg:postcode": "44022",
    "sg:province": "OH",
    "sg:tags": [
      "bookstore"
    ],
    "wof:name": "Jupiter Press",
    "wof:placetype": "venue"
  },
  "geometry": {"coordinates":[-81.391602,41.4277],"type":"Point"}
}
