{
  "type": "Feature",
  "properties": {
    "addr:full": "1429 King Ave Columbus OH 43212",
    "addr:housenumber": "1429",
    "addr:postcode": "43212",
    "addr:street": "King Ave",
    "iso:country": "US",
    "sg:address": "1429 King Ave",
    "sg:city": "Columbus",
    "sg:classifiers": [
      {
        "category": "Professional",
        "subcategory": "Business Services",
        "type": "Services"
      },
      {
        "category": "Insurance",
        "subcategory": "Insurance Agent",
        "type": "Services"
      }
    ],
    "sg:phone": "+1 614 486 0691",
    "sg:postcode": "43212",
    "sg:province": "OH",
    "sg:tags": [
      "planning",
      "financial"
    ],
    "wof:name": "First Ohio Planning Corp",
    "wof:placetype": "venue"
  },
  "geometry": {"coordinates":[-83.045065,39.991526],"type":"Point"}
}
