{
  "type": "Feature",
  "properties": {
    "iso:country":"US",
    "sg:address":"8131 Edison St NE",
    "sg:city":"Louisville",
    "sg:classifiers":[
        {
            "category":"Education",
            "subcategory":"School",
            "type":"Public Place"
        }
    ],
    "sg:phone":"+1 330 935 8309",
    "sg:postcode":"44641",
    "sg:province":"OH",
    "wof:name":"Marlington Local Sch Dist",
    "wof:placetype":"venue"
},
  "geometry": {"coordinates":[-81.243137,40.951933],"type":"Point"}
}