{
  "type": "Feature",
  "properties": {
    "iso:country":"US",
    "sg:address":"1989 W 5th Ave",
    "sg:city":"Columbus",
    "sg:classifiers":[
        {
            "category":"Professional",
            "subcategory":"Advertising",
            "type":"Services"
        }
    ],
    "sg:phone":"+1 614 485 9913",
    "sg:postcode":"43212",
    "sg:province":"OH",
    "sg:tags":[
        "counselor"
    ],
    "wof:name":"Meyer Bennett Creative",
    "wof:placetype":"venue"
},
  "geometry": {"coordinates":[-83.059634,39.989345],"type":"Point"}
}