{
  "type": "Feature",
  "properties": {
    "addr:full":"31 W Main St Seville OH 44273",
    "addr:housenumber":"31",
    "addr:postcode":"44273",
    "addr:street":"W Main St",
    "iso:country":"US",
    "sg:address":"31 W Main St",
    "sg:city":"Seville",
    "sg:classifiers":[
        {
            "category":"Restaurant",
            "type":"Food & Drink"
        }
    ],
    "sg:phone":"+1 330 769 9900",
    "sg:postcode":"44273",
    "sg:province":"OH",
    "wof:name":"American Heritage Restaurant",
    "wof:placetype":"venue"
},
  "geometry": {"coordinates":[-81.86260900000001,41.010022],"type":"Point"}
}