{
  "type": "Feature",
  "properties": {
    "addr:full": "112 N Main St Mt Vernon OH 43050",
    "addr:housenumber": "112",
    "addr:postcode": "43050",
    "addr:street": "N Main St",
    "iso:country": "US",
    "sg:address": "112 N Main St",
    "sg:city": "Mt Vernon",
    "sg:classifiers": [
      {
        "category": "Professional",
        "subcategory": "Lawyer \u0026 Legal Services",
        "type": "Services"
      }
    ],
    "sg:phone": "+1 740 393 2718",
    "sg:postcode": "43050",
    "sg:province": "OH",
    "sg:tags": [
      "attorney"
    ],
    "wof:name": "Folland \u0026 Drown",
    "wof:placetype": "venue"
  },
  "geometry": {"coordinates":[-82.485229,40.395186],"type":"Point"}
}
