{
  "type": "Feature",
  "properties": {
    "addr:full":"3870 Oxford Millville Rd Oxford IN 45056",
    "addr:housenumber":"3870",
    "addr:postcode":"45056",
    "addr:street":"Oxford Millville Rd",
    "iso:country":"US",
    "sg:address":"3870 Oxford Millville Rd",
    "sg:city":"Oxford",
    "sg:classifiers":[
        {
            "category":"Organizations",
            "subcategory":"Religious Organization",
            "type":"Services"
        }
    ],
    "sg:phone":"+1 513 523 4500",
    "sg:postcode":"45056",
    "sg:province":"IN",
    "sg:tags":[
        "church"
    ],
    "wof:name":"Hopedale Unitarian Unvrslst",
    "wof:placetype":"venue"
},
  "geometry": {"coordinates":[-84.71638900000001,39.484413],"type":"Point"}
}