{
  "type": "Feature",
  "properties": {
    "addr:full": "4325 E Bluelick Rd Lima OH 45801",
    "addr:housenumber": "4325",
    "addr:postcode": "45801",
    "addr:street": "E Bluelick Rd",
    "iso:country": "US",
    "sg:address": "4325 E Bluelick Rd",
    "sg:city": "Lima",
    "sg:classifiers": [
      {
        "category": "Wholesale",
        "subcategory": "Chemicals \u0026 Plastics",
        "type": "Manufacturing \u0026 Wholesale Goods"
      }
    ],
    "sg:phone": "+1 419 221 0926",
    "sg:postcode": "45801",
    "sg:province": "OH",
    "sg:tags": [
      "cleaning",
      "compound"
    ],
    "wof:name": "Orange TKO Midwest LTD",
    "wof:placetype": "venue"
  },
  "geometry": {"coordinates":[-84.015548,40.789258],"type":"Point"}
}
