{
  "type": "Feature",
  "properties": {
    "iso:country":"US",
    "sg:address":"4325 E Bluelick Rd",
    "sg:city":"Lima",
    "sg:classifiers":[
        {
            "category":"Wholesale",
            "subcategory":"Chemicals & Plastics",
            "type":"Manufacturing & Wholesale Goods"
        }
    ],
    "sg:phone":"+1 419 221 0926",
    "sg:postcode":"45801",
    "sg:province":"OH",
    "sg:tags":[
        "cleaning",
        "compound"
    ],
    "wof:name":"Orange TKO Midwest LTD",
    "wof:placetype":"venue"
},
  "geometry": {"coordinates":[-84.015548,40.789258],"type":"Point"}
}