{
  "type": "Feature",
  "properties": {
    "addr:full":"11049 Twp Rd 506 Shreve OH 44676",
    "addr:housenumber":"11049;506",
    "addr:postcode":"44676",
    "addr:street":"Twp Rd",
    "iso:country":"US",
    "sg:address":"11049 Twp Rd 506",
    "sg:city":"Shreve",
    "sg:classifiers":[
        {
            "category":"Retail",
            "subcategory":"Animal Services",
            "type":"Services"
        }
    ],
    "sg:phone":"+1 330 567 2119",
    "sg:postcode":"44676",
    "sg:province":"OH",
    "wof:name":"Leon Troyer",
    "wof:placetype":"venue"
},
  "geometry": {"coordinates":[-82.02146399999999,40.605653],"type":"Point"}
}