{
  "type": "Feature",
  "properties": {
    "addr:full":"3540 Ridge Rd Cleveland OH 44102",
    "addr:housenumber":"3540",
    "addr:postcode":"44102",
    "addr:street":"Ridge Rd",
    "iso:country":"US",
    "sg:address":"3540 Ridge Rd",
    "sg:city":"Cleveland",
    "sg:classifiers":[
        {
            "category":"Real Estate",
            "subcategory":"Real Estate Operator",
            "type":"Services"
        }
    ],
    "sg:phone":"+1 216 961 9100",
    "sg:postcode":"44102",
    "sg:province":"OH",
    "sg:tags":[
        "building",
        "commercial",
        "stenographic"
    ],
    "wof:name":"Ridge Secretarial Service",
    "wof:placetype":"venue"
},
  "geometry": {"coordinates":[-81.73833500000001,41.459593],"type":"Point"}
}