{
  "type": "Feature",
  "properties": {
    "addr:full":"227 Crestview Dr Hillsboro OH 45133",
    "addr:housenumber":"227",
    "addr:postcode":"45133",
    "addr:street":"Crestview Dr",
    "iso:country":"US",
    "sg:address":"227 Crestview Dr",
    "sg:city":"Hillsboro",
    "sg:classifiers":[
        {
            "category":"Farming",
            "subcategory":"Livestock Farm",
            "type":"Manufacturing & Wholesale Goods"
        }
    ],
    "sg:phone":"+1 937 393 1464",
    "sg:postcode":"45133",
    "sg:province":"OH",
    "sg:tags":[
        "beef",
        "feedlot",
        "cattle"
    ],
    "wof:name":"C & C Farms",
    "wof:placetype":"venue"
},
  "geometry": {"coordinates":[-83.615903,39.196062],"type":"Point"}
}