{
  "type": "Feature",
  "properties": {
    "addr:full": "1301 E 9th St Cleveland OH 44114",
    "addr:housenumber": "1301",
    "addr:postcode": "44114",
    "addr:street": "E 9Th St",
    "iso:country": "US",
    "sg:address": "1301 E 9th St",
    "sg:city": "Cleveland",
    "sg:classifiers": [
      {
        "category": "Restaurant",
        "type": "Food \u0026 Drink"
      }
    ],
    "sg:phone": "+1 216 687 0599",
    "sg:postcode": "44114",
    "sg:province": "OH",
    "wof:name": "Mc Donald's",
    "wof:placetype": "venue"
  },
  "geometry": {"coordinates":[-81.689572,41.503429],"type":"Point"}
}
