{
  "type": "Feature",
  "properties": {
    "addr:full": "466 Catalina Ave Youngstown OH 44504",
    "addr:housenumber": "466",
    "addr:postcode": "44504",
    "addr:street": "Catalina Ave",
    "iso:country": "US",
    "sg:address": "466 Catalina Ave",
    "sg:city": "Youngstown",
    "sg:classifiers": [
      {
        "category": "Shopping",
        "subcategory": "Books",
        "type": "Retail Goods"
      }
    ],
    "sg:phone": "+1 330 744 4897",
    "sg:postcode": "44504",
    "sg:province": "OH",
    "wof:name": "Siver Company",
    "wof:placetype": "venue"
  },
  "geometry": {"coordinates":[-80.65797,41.1239],"type":"Point"}
}
