{
  "type": "Feature",
  "properties": {
    "iso:country":"US",
    "sg:address":"5338 Meadow Lane Ct",
    "sg:city":"Elyria",
    "sg:classifiers":[
        {
            "category":"Professional",
            "subcategory":"Lawyer & Legal Services",
            "type":"Services"
        }
    ],
    "sg:phone":"+1 440 934 7000",
    "sg:postcode":"44035",
    "sg:province":"OH",
    "wof:name":"Zagrans Law Firm Co LPA",
    "wof:placetype":"venue"
},
  "geometry": {"coordinates":[-82.074932,41.420778],"type":"Point"}
}