{
  "type": "Feature",
  "properties": {
    "addr:full": "5314 Trillium Ct Columbus OH 43230",
    "addr:housenumber": "5314",
    "addr:postcode": "43230",
    "addr:street": "Trillium Ct",
    "iso:country": "US",
    "sg:address": "5314 Trillium Ct",
    "sg:city": "Columbus",
    "sg:classifiers": [
      {
        "category": "Restaurant",
        "type": "Food \u0026 Drink"
      }
    ],
    "sg:phone": "+1 614 794 3269",
    "sg:postcode": "43230",
    "sg:province": "OH",
    "sg:tags": [
      "eating"
    ],
    "wof:name": "Mystery Diner",
    "wof:placetype": "venue"
  },
  "geometry": {"coordinates":[-82.912083,40.08145],"type":"Point"}
}
