{
  "type": "Feature",
  "properties": {
    "iso:country":"US",
    "sg:address":"3575 E Livingston Ave",
    "sg:city":"Columbus",
    "sg:classifiers":[
        {
            "category":"Shopping",
            "subcategory":"Clothing, Apparel, & Fashions",
            "type":"Retail Goods"
        }
    ],
    "sg:phone":"+1 614 236 2300",
    "sg:postcode":"43227",
    "sg:province":"OH",
    "wof:name":"Lois Lace",
    "wof:placetype":"venue"
},
  "geometry": {"coordinates":[-82.899381,39.945918],"type":"Point"}
}