{
  "type": "Feature",
  "properties": {
    "addr:full": "3575 E Livingston Ave Columbus OH 43227",
    "addr:housenumber": "3575",
    "addr:postcode": "43227",
    "addr:street": "E Livingston Ave",
    "iso:country": "US",
    "sg:address": "3575 E Livingston Ave",
    "sg:city": "Columbus",
    "sg:classifiers": [
      {
        "category": "Shopping",
        "subcategory": "Clothing, Apparel, \u0026 Fashions",
        "type": "Retail Goods"
      }
    ],
    "sg:phone": "+1 614 236 2300",
    "sg:postcode": "43227",
    "sg:province": "OH",
    "wof:name": "Lois Lace",
    "wof:placetype": "venue"
  },
  "geometry": {"coordinates":[-82.899381,39.945918],"type":"Point"}
}
