{
  "type": "Feature",
  "properties": {
    "addr:full": "510 W Main St Batavia OH 45103",
    "addr:housenumber": "510",
    "addr:postcode": "45103",
    "addr:street": "W Main St",
    "iso:country": "US",
    "sg:address": "510 W Main St",
    "sg:city": "Batavia",
    "sg:classifiers": [
      {
        "category": "Freight",
        "type": "Transportation"
      }
    ],
    "sg:phone": "+1 513 732 3335",
    "sg:postcode": "45103",
    "sg:province": "OH",
    "sg:tags": [
      "special",
      "general"
    ],
    "wof:name": "Batavia Mini Storage",
    "wof:placetype": "venue"
  },
  "geometry": {"coordinates":[-84.185683,39.081716],"type":"Point"}
}
