{
  "type": "Feature",
  "properties": {
    "addr:full": "2126 Nichols Ridge Rd Seaman OH 45679",
    "addr:housenumber": "2126",
    "addr:postcode": "45679",
    "addr:street": "Nichols Ridge Rd",
    "iso:country": "US",
    "sg:address": "2126 Nichols Ridge Rd",
    "sg:city": "Seaman",
    "sg:classifiers": [
      {
        "category": "Farming",
        "subcategory": "Livestock Farm",
        "type": "Manufacturing \u0026 Wholesale Goods"
      }
    ],
    "sg:phone": "+1 937 386 2962",
    "sg:postcode": "45679",
    "sg:province": "OH",
    "sg:tags": [
      "beef",
      "feedlot",
      "cattle"
    ],
    "wof:name": "David Newman Farm",
    "wof:placetype": "venue"
  },
  "geometry": {"coordinates":[-83.510859,38.939187],"type":"Point"}
}
