{
  "type": "Feature",
  "properties": {
    "addr:full": "2032 W 105th St Cleveland OH 44102",
    "addr:housenumber": "2032",
    "addr:postcode": "44102",
    "addr:street": "W 105Th St",
    "iso:country": "US",
    "sg:address": "2032 W 105th St",
    "sg:city": "Cleveland",
    "sg:classifiers": [
      {
        "category": "Manufacturing",
        "subcategory": "Tools \u0026 Machinery",
        "type": "Manufacturing \u0026 Wholesale Goods"
      }
    ],
    "sg:phone": "+1 216 651 3383",
    "sg:postcode": "44102",
    "sg:province": "OH",
    "sg:tags": [
      "mfg"
    ],
    "wof:name": "Tiburzi Machine \u0026 Tool Co",
    "wof:placetype": "venue"
  },
  "geometry": {"coordinates":[-81.758829,41.470634],"type":"Point"}
}
