{
  "type": "Feature",
  "properties": {
    "iso:country":"US",
    "sg:address":"11314 Montgomery Rd",
    "sg:city":"Cincinnati",
    "sg:classifiers":[
        {
            "category":"Shopping",
            "type":"Retail Goods"
        }
    ],
    "sg:phone":"+1 513 489 9484",
    "sg:postcode":"45249",
    "sg:province":"OH",
    "sg:tags":[
        "floral",
        "home",
        "design",
        "accent",
        "custom"
    ],
    "wof:name":"Botanica Inc",
    "wof:placetype":"venue"
},
  "geometry": {"coordinates":[-84.32792499999999,39.27131],"type":"Point"}
}