{
  "type": "Feature",
  "properties": {
    "addr:full": "140 Industrial Dr Mansfield OH 44904",
    "addr:housenumber": "140",
    "addr:postcode": "44904",
    "addr:street": "Industrial Dr",
    "iso:country": "US",
    "sg:address": "140 Industrial Dr",
    "sg:city": "Mansfield",
    "sg:classifiers": [
      {
        "category": "Manufacturing",
        "subcategory": "Metals",
        "type": "Manufacturing \u0026 Wholesale Goods"
      }
    ],
    "sg:phone": "+1 419 522 0091",
    "sg:postcode": "44904",
    "sg:province": "OH",
    "sg:tags": [
      "stampings"
    ],
    "wof:name": "Enman",
    "wof:placetype": "venue"
  },
  "geometry": {"coordinates":[-82.565785,40.67884],"type":"Point"}
}
