{
  "type": "Feature",
  "properties": {
    "iso:country":"US",
    "sg:address":"140 Industrial Dr",
    "sg:city":"Mansfield",
    "sg:classifiers":[
        {
            "category":"Manufacturing",
            "subcategory":"Metals",
            "type":"Manufacturing & Wholesale Goods"
        }
    ],
    "sg:phone":"+1 419 522 0091",
    "sg:postcode":"44904",
    "sg:province":"OH",
    "sg:tags":[
        "stampings"
    ],
    "wof:name":"Enman",
    "wof:placetype":"venue"
},
  "geometry": {"coordinates":[-82.565785,40.67884],"type":"Point"}
}