{
  "type": "Feature",
  "properties": {
    "iso:country":"US",
    "sg:address":"2275 Harding Rd",
    "sg:city":"Cuyahoga Falls",
    "sg:classifiers":[
        {
            "category":"Building & Trades",
            "subcategory":"Landscaping Services",
            "type":"Services"
        }
    ],
    "sg:phone":"+1 330 923 2649",
    "sg:postcode":"44223",
    "sg:province":"OH",
    "sg:tags":[
        "lawn",
        "garden"
    ],
    "wof:name":"Jims Lawn Service",
    "wof:placetype":"venue"
},
  "geometry": {"coordinates":[-81.51565600000001,41.138728],"type":"Point"}
}