{
  "type": "Feature",
  "properties": {
    "iso:country":"US",
    "sg:address":"1225 N Home Rd",
    "sg:city":"Mansfield",
    "sg:classifiers":[
        {
            "category":"Insurance",
            "subcategory":"Insurance Agent",
            "type":"Services"
        }
    ],
    "sg:phone":"+1 419 747 2288",
    "sg:postcode":"44906",
    "sg:province":"OH",
    "wof:name":"American Family Insurance",
    "wof:placetype":"venue"
},
  "geometry": {"coordinates":[-82.570908,40.785757],"type":"Point"}
}