{
  "type": "Feature",
  "properties": {
    "addr:full":"450 Greenlawn Ave Columbus OH 43223",
    "addr:housenumber":"450",
    "addr:postcode":"43223",
    "addr:street":"Greenlawn Ave",
    "iso:country":"US",
    "sg:address":"450 Greenlawn Ave",
    "sg:city":"Columbus",
    "sg:classifiers":[
        {
            "category":"Manufacturing",
            "subcategory":"Chemicals & Compounds",
            "type":"Manufacturing & Wholesale Goods"
        }
    ],
    "sg:phone":"+1 614 443 7487",
    "sg:postcode":"43223",
    "sg:province":"OH",
    "sg:tags":[
        "gas"
    ],
    "sg:website":"www.uslindegas.com",
    "wof:name":"Linde Gas",
    "wof:placetype":"venue"
},
  "geometry": {"coordinates":[-83.009923,39.939555],"type":"Point"}
}