{
  "type": "Feature",
  "properties": {
    "iso:country":"US",
    "sg:address":"4536 Main Ave",
    "sg:city":"Ashtabula",
    "sg:classifiers":[
        {
            "category":"Professional",
            "type":"Services"
        }
    ],
    "sg:phone":"+1 440 998 6564",
    "sg:postcode":"44004",
    "sg:province":"OH",
    "sg:tags":[
        "establishment"
    ],
    "wof:name":"Junior Achievement-Ashtabula",
    "wof:placetype":"venue"
},
  "geometry": {"coordinates":[-80.781935,41.865874],"type":"Point"}
}