{
  "type": "Feature",
  "properties": {
    "addr:full": "14040 Weaver Rd Marysville OH 43040",
    "addr:housenumber": "14040",
    "addr:postcode": "43040",
    "addr:street": "Weaver Rd",
    "iso:country": "US",
    "sg:address": "14040 Weaver Rd",
    "sg:city": "Marysville",
    "sg:classifiers": [
      {
        "category": "Freight",
        "type": "Transportation"
      }
    ],
    "sg:phone": "+1 937 644 1304",
    "sg:postcode": "43040",
    "sg:province": "OH",
    "sg:tags": [
      "operator",
      "local",
      "trucking"
    ],
    "wof:name": "Aquasource Water Hauling Co",
    "wof:placetype": "venue"
  },
  "geometry": {"coordinates":[-83.352416,40.207024],"type":"Point"}
}
