{
  "type": "Feature",
  "properties": {
    "iso:country":"US",
    "sg:address":"121 W Caroline St",
    "sg:city":"Paulding",
    "sg:classifiers":[
        {
            "category":"Professional",
            "type":"Services"
        }
    ],
    "sg:phone":"+1 419 399 2925",
    "sg:postcode":"45879",
    "sg:province":"OH",
    "wof:name":"Free & Accepted Masons of",
    "wof:placetype":"venue"
},
  "geometry": {"coordinates":[-84.581857,41.139168],"type":"Point"}
}