{
  "type": "Feature",
  "properties": {
    "addr:full": "121 W Caroline St Paulding OH 45879",
    "addr:housenumber": "121",
    "addr:postcode": "45879",
    "addr:street": "W Caroline St",
    "iso:country": "US",
    "sg:address": "121 W Caroline St",
    "sg:city": "Paulding",
    "sg:classifiers": [
      {
        "category": "Professional",
        "type": "Services"
      }
    ],
    "sg:phone": "+1 419 399 2925",
    "sg:postcode": "45879",
    "sg:province": "OH",
    "wof:name": "Free \u0026 Accepted Masons of",
    "wof:placetype": "venue"
  },
  "geometry": {"coordinates":[-84.581857,41.139168],"type":"Point"}
}
