{
  "type": "Feature",
  "properties": {
    "addr:full": "691 Richmond Rd Cleveland OH 44143",
    "addr:housenumber": "691",
    "addr:postcode": "44143",
    "addr:street": "Richmond Rd",
    "iso:country": "US",
    "sg:address": "691 Richmond Rd",
    "sg:city": "Cleveland",
    "sg:classifiers": [
      {
        "category": "Personal",
        "subcategory": "Beauty Salon",
        "type": "Services"
      }
    ],
    "sg:phone": "+1 440 684 1223",
    "sg:postcode": "44143",
    "sg:province": "OH",
    "sg:tags": [
      "shop",
      "manicuring"
    ],
    "wof:name": "Nail City",
    "wof:placetype": "venue"
  },
  "geometry": {"coordinates":[-81.497099,41.54074],"type":"Point"}
}
