{
  "type": "Feature",
  "properties": {
    "iso:country":"US",
    "sg:address":"1302 Canterbury Dr",
    "sg:city":"Celina",
    "sg:classifiers":[
        {
            "category":"Organizations",
            "subcategory":"Community Association",
            "type":"Services"
        }
    ],
    "sg:phone":"+1 419 586 8718",
    "sg:postcode":"45822",
    "sg:province":"OH",
    "wof:name":"Interntnal Assn of Lions Clubs",
    "wof:placetype":"venue"
},
  "geometry": {"coordinates":[-84.560337,40.564163],"type":"Point"}
}