{
  "type": "Feature",
  "properties": {
    "iso:country":"US",
    "sg:address":"9920 Newberry-Washington North Rd",
    "sg:city":"Piqua",
    "sg:classifiers":[
        {
            "category":"Wholesale",
            "subcategory":"Machinery & Supplies",
            "type":"Manufacturing & Wholesale Goods"
        },
        {
            "category":"Manufacturing",
            "subcategory":"Tools & Machinery",
            "type":"Manufacturing & Wholesale Goods"
        }
    ],
    "sg:phone":"+1 937 773 8842",
    "sg:postcode":"45356",
    "sg:province":"OH",
    "sg:tags":[
        "farm",
        "repair",
        "equipment"
    ],
    "wof:name":"Wenrick Equipment Sales",
    "wof:placetype":"venue"
},
  "geometry": {"coordinates":[-84.31788299999999,40.179666],"type":"Point"}
}