{
  "type": "Feature",
  "properties": {
    "addr:full": "3698 Harry Truman Dr Beavercreek OH 45432",
    "addr:housenumber": "3698",
    "addr:postcode": "45432",
    "addr:street": "Harry Truman Dr",
    "iso:country": "US",
    "sg:address": "3698 Harry Truman Dr",
    "sg:city": "Beavercreek",
    "sg:classifiers": [
      {
        "category": "Building \u0026 Trades",
        "subcategory": "Landscaping Services",
        "type": "Services"
      }
    ],
    "sg:phone": "+1 937 372 5921",
    "sg:postcode": "45432",
    "sg:province": "OH",
    "sg:tags": [
      "landscape",
      "contractor"
    ],
    "wof:name": "Landscape Innovations Inc",
    "wof:placetype": "venue"
  },
  "geometry": {"coordinates":[-84.070259,39.743824],"type":"Point"}
}
