{
  "type": "Feature",
  "properties": {
    "addr:full": "586 Co Rd 50 Helena OH 43435",
    "addr:housenumber": "586;50",
    "addr:postcode": "43435",
    "addr:street": "Co Rd",
    "iso:country": "US",
    "sg:address": "586 Co Rd 50",
    "sg:city": "Helena",
    "sg:classifiers": [
      {
        "category": "Real Estate",
        "subcategory": "Real Estate Operator",
        "type": "Services"
      }
    ],
    "sg:phone": "+1 419 638 4104",
    "sg:postcode": "43435",
    "sg:province": "OH",
    "sg:tags": [
      "property",
      "lessor"
    ],
    "wof:name": "Phillip Hammer",
    "wof:placetype": "venue"
  },
  "geometry": {"coordinates":[-83.330079,41.327074],"type":"Point"}
}
