{
  "type": "Feature",
  "properties": {
    "addr:full":"1514 Plaza Dr Hamilton IN 45013",
    "addr:housenumber":"1514",
    "addr:postcode":"45013",
    "addr:street":"Plaza Dr",
    "iso:country":"US",
    "sg:address":"1514 Plaza Dr",
    "sg:city":"Hamilton",
    "sg:classifiers":[
        {
            "category":"Personal",
            "subcategory":"Beauty Salon",
            "type":"Services"
        }
    ],
    "sg:phone":"+1 513 844 2216",
    "sg:postcode":"45013",
    "sg:province":"IN",
    "sg:tags":[
        "shop"
    ],
    "wof:name":"Family Styling",
    "wof:placetype":"venue"
},
  "geometry": {"coordinates":[-84.611205,39.406586],"type":"Point"}
}