{
  "type": "Feature",
  "properties": {
    "addr:full": "6100 Rockside Woods Blvd Cleveland OH 44131",
    "addr:housenumber": "6100",
    "addr:postcode": "44131",
    "addr:street": "Rockside Woods Blvd",
    "iso:country": "US",
    "sg:address": "6100 Rockside Woods Blvd",
    "sg:city": "Cleveland",
    "sg:classifiers": [
      {
        "category": "Real Estate",
        "subcategory": "Real Estate Services",
        "type": "Services"
      }
    ],
    "sg:phone": "+1 216 520 3624",
    "sg:postcode": "44131",
    "sg:province": "OH",
    "sg:tags": [
      "company",
      "title"
    ],
    "wof:name": "American Title Resolutions Inc",
    "wof:placetype": "venue"
  },
  "geometry": {"coordinates":[-81.645622,41.399277],"type":"Point"}
}
