{
  "type": "Feature",
  "properties": {
    "addr:full":"3100 McHenry Ave Cincinnati OH 45211",
    "addr:housenumber":"3100",
    "addr:postcode":"45211",
    "addr:street":"Mchenry Ave",
    "iso:country":"US",
    "sg:address":"3100 McHenry Ave",
    "sg:city":"Cincinnati",
    "sg:classifiers":[
        {
            "category":"Shopping",
            "subcategory":"Musical Instruments",
            "type":"Retail Goods"
        }
    ],
    "sg:phone":"+1 513 481 4180",
    "sg:postcode":"45211",
    "sg:province":"OH",
    "wof:name":"Walt N Kellsha",
    "wof:placetype":"venue"
},
  "geometry": {"coordinates":[-84.580536,39.140829],"type":"Point"}
}