{
  "type": "Feature",
  "properties": {
    "iso:country":"US",
    "sg:address":"160 Bryn Mawr St",
    "sg:city":"Ravenna",
    "sg:classifiers":[
        {
            "category":"Wholesale",
            "subcategory":"Machinery & Supplies",
            "type":"Manufacturing & Wholesale Goods"
        }
    ],
    "sg:phone":"+1 330 296 9676",
    "sg:postcode":"44266",
    "sg:province":"OH",
    "sg:tags":[
        "engine"
    ],
    "wof:name":"D & D Truck Parts",
    "wof:placetype":"venue"
},
  "geometry": {"coordinates":[-81.22192,41.157011],"type":"Point"}
}