{
  "type": "Feature",
  "properties": {
    "addr:full": "160 Bryn Mawr St Ravenna OH 44266",
    "addr:housenumber": "160",
    "addr:postcode": "44266",
    "addr:street": "Bryn Mawr St",
    "iso:country": "US",
    "sg:address": "160 Bryn Mawr St",
    "sg:city": "Ravenna",
    "sg:classifiers": [
      {
        "category": "Wholesale",
        "subcategory": "Machinery \u0026 Supplies",
        "type": "Manufacturing \u0026 Wholesale Goods"
      }
    ],
    "sg:phone": "+1 330 296 9676",
    "sg:postcode": "44266",
    "sg:province": "OH",
    "sg:tags": [
      "engine"
    ],
    "wof:name": "D \u0026 D Truck Parts",
    "wof:placetype": "venue"
  },
  "geometry": {"coordinates":[-81.22192,41.157011],"type":"Point"}
}
