{
  "type": "Feature",
  "properties": {
    "addr:full":"3637 Werk Rd Cincinnati OH 45248",
    "addr:housenumber":"3637",
    "addr:postcode":"45248",
    "addr:street":"Werk Rd",
    "iso:country":"US",
    "sg:address":"3637 Werk Rd",
    "sg:city":"Cincinnati",
    "sg:classifiers":[
        {
            "category":"Restaurant",
            "type":"Food & Drink"
        }
    ],
    "sg:menulink":"http://www.allmenus.com/oh/bridgetown-north/18963-mios-pizzeria/menu/",
    "sg:phone":"+1 513 451 9911",
    "sg:postcode":"45248",
    "sg:province":"OH",
    "sg:tags":[
        "italian"
    ],
    "wof:name":"Mio's Pizzeria",
    "wof:placetype":"venue"
},
  "geometry": {"coordinates":[-84.625122,39.14177],"type":"Point"}
}