{
  "type": "Feature",
  "properties": {
    "addr:full": "1277 Turner Dr Sidney OH 45365",
    "addr:housenumber": "1277",
    "addr:postcode": "45365",
    "addr:street": "Turner Dr",
    "iso:country": "US",
    "sg:address": "1277 Turner Dr",
    "sg:city": "Sidney",
    "sg:classifiers": [
      {
        "category": "Building \u0026 Trades",
        "subcategory": "Cleaning \u0026 Sanitation",
        "type": "Services"
      }
    ],
    "sg:phone": "+1 937 497 9496",
    "sg:postcode": "45365",
    "sg:province": "OH",
    "sg:tags": [
      "janitor",
      "maintenance"
    ],
    "wof:name": "Absolute Cleaning Service",
    "wof:placetype": "venue"
  },
  "geometry": {"coordinates":[-84.173092,40.282353],"type":"Point"}
}
