{
  "type": "Feature",
  "properties": {
    "addr:full":"9882 Colerain Ave Cincinnati OH 45251",
    "addr:housenumber":"9882",
    "addr:postcode":"45251",
    "addr:street":"Colerain Ave",
    "iso:country":"US",
    "sg:address":"9882 Colerain Ave",
    "sg:city":"Cincinnati",
    "sg:classifiers":[
        {
            "category":"Banks & Credit Unions",
            "subcategory":"Bank",
            "type":"Services"
        }
    ],
    "sg:phone":"+1 513 385 9150",
    "sg:postcode":"45251",
    "sg:province":"OH",
    "sg:tags":[
        "personal",
        "loan",
        "real estate",
        "institution"
    ],
    "wof:name":"Associates Financial Svc",
    "wof:placetype":"venue"
},
  "geometry": {"coordinates":[-84.59867800000001,39.252671],"type":"Point"}
}