{
  "type": "Feature",
  "properties": {
    "addr:full": "18563 Royalton Rd Strongsville OH 44136",
    "addr:housenumber": "18563",
    "addr:postcode": "44136",
    "addr:street": "Royalton Rd",
    "iso:country": "US",
    "sg:address": "18563 Royalton Rd",
    "sg:city": "Strongsville",
    "sg:classifiers": [
      {
        "category": "Insurance",
        "subcategory": "Insurance Agent",
        "type": "Services"
      }
    ],
    "sg:phone": "+1 440 234 8333",
    "sg:postcode": "44136",
    "sg:province": "OH",
    "wof:name": "John Graff Agency",
    "wof:placetype": "venue"
  },
  "geometry": {"coordinates":[-81.831261,41.314178],"type":"Point"}
}
