{
  "type": "Feature",
  "properties": {
    "iso:country":"US",
    "sg:address":"2500 Ohio Ave",
    "sg:city":"Gallipolis",
    "sg:classifiers":[
        {
            "category":"Organizations",
            "subcategory":"Labor Organization",
            "type":"Services"
        }
    ],
    "sg:phone":"+1 740 446 9544",
    "sg:postcode":"45631",
    "sg:province":"OH",
    "wof:name":"Ocsea-Afscme Local",
    "wof:placetype":"venue"
},
  "geometry": {"coordinates":[-82.188492,38.822765],"type":"Point"}
}