{
  "type": "Feature",
  "properties": {
    "iso:country":"US",
    "sg:address":"6727 Denison Ave",
    "sg:city":"Cleveland",
    "sg:classifiers":[
        {
            "category":"Restaurant",
            "type":"Food & Drink"
        }
    ],
    "sg:menulink":"http://www.allmenus.com/oh/cleveland/86311-little-caesars-pizza/menu/",
    "sg:phone":"+1 216 651 9000",
    "sg:postcode":"44102",
    "sg:province":"OH",
    "sg:tags":[
        "american",
        "pizza"
    ],
    "wof:name":"Little Caesar's Pizza",
    "wof:placetype":"venue"
},
  "geometry": {"coordinates":[-81.73403500000001,41.460767],"type":"Point"}
}