{
  "type": "Feature",
  "properties": {
    "iso:country":"US",
    "sg:address":"8340 Colerain Ave",
    "sg:city":"Cincinnati",
    "sg:classifiers":[
        {
            "category":"Restaurant",
            "type":"Food & Drink"
        }
    ],
    "sg:phone":"+1 513 385 5659",
    "sg:postcode":"45239",
    "sg:province":"OH",
    "sg:tags":[
        "eating"
    ],
    "wof:name":"Dynasty Buffet",
    "wof:placetype":"venue"
},
  "geometry": {"coordinates":[-84.58725099999999,39.223103],"type":"Point"}
}