{
  "type": "Feature",
  "properties": {
    "addr:full": "8340 Colerain Ave Cincinnati OH 45239",
    "addr:postcode": "8340;45239",
    "addr:street": "Colerain Ave",
    "iso:country": "US",
    "sg:address": "8340 Colerain Ave",
    "sg:city": "Cincinnati",
    "sg:classifiers": [
      {
        "category": "Restaurant",
        "type": "Food \u0026 Drink"
      }
    ],
    "sg:phone": "+1 513 385 5659",
    "sg:postcode": "45239",
    "sg:province": "OH",
    "sg:tags": [
      "eating"
    ],
    "wof:name": "Dynasty Buffet",
    "wof:placetype": "venue"
  },
  "geometry": {"coordinates":[-84.587251,39.223103],"type":"Point"}
}
