{
  "type": "Feature",
  "properties": {
    "addr:full":"10620 Mayfield Rd Chesterland OH 44026",
    "addr:housenumber":"10620",
    "addr:postcode":"44026",
    "addr:street":"Mayfield Rd",
    "iso:country":"US",
    "sg:address":"10620 Mayfield Rd",
    "sg:city":"Chesterland",
    "sg:classifiers":[
        {
            "category":"Travel",
            "subcategory":"Hotels & Motels",
            "type":"Entertainment"
        }
    ],
    "sg:phone":"+1 440 285 2211",
    "sg:postcode":"44026",
    "sg:province":"OH",
    "sg:tags":[
        "lodge",
        "ski",
        "caterer"
    ],
    "wof:name":"Alpine Valley",
    "wof:placetype":"venue"
},
  "geometry": {"coordinates":[-81.26058399999999,41.525656],"type":"Point"}
}