{
  "type": "Feature",
  "properties": {
    "iso:country":"US",
    "sg:address":"2444 E High St",
    "sg:city":"Springfield",
    "sg:classifiers":[
        {
            "category":"Retail",
            "subcategory":"Veterinary Services",
            "type":"Services"
        }
    ],
    "sg:phone":"+1 937 323 9000",
    "sg:postcode":"45505",
    "sg:province":"OH",
    "sg:tags":[
        "veterinarian"
    ],
    "wof:name":"East High Veterinary Clinic",
    "wof:placetype":"venue"
},
  "geometry": {"coordinates":[-83.772187,39.921572],"type":"Point"}
}