{
  "type": "Feature",
  "properties": {
    "addr:full":"716 Portage Trl Cuyahoga Falls OH 44221",
    "addr:housenumber":"716",
    "addr:postcode":"44221",
    "addr:street":"Portage Trl",
    "iso:country":"US",
    "sg:address":"716 Portage Trl",
    "sg:city":"Cuyahoga Falls",
    "sg:classifiers":[
        {
            "category":"Building & Trades",
            "subcategory":"Plumbing",
            "type":"Services"
        }
    ],
    "sg:phone":"+1 330 929 4024",
    "sg:postcode":"44221",
    "sg:province":"OH",
    "wof:name":"K&M Service",
    "wof:placetype":"venue"
},
  "geometry": {"coordinates":[-81.49300100000001,41.140168],"type":"Point"}
}