{
  "type": "Feature",
  "properties": {
    "iso:country":"US",
    "sg:address":"140 W Broadway St",
    "sg:city":"Dover",
    "sg:classifiers":[
        {
            "category":"Retail",
            "subcategory":"Auto Repair",
            "type":"Services"
        }
    ],
    "sg:phone":"+1 330 343 1311",
    "sg:postcode":"44622",
    "sg:province":"OH",
    "sg:tags":[
        "body"
    ],
    "sg:website":"www.haasbodyshop.com",
    "wof:name":"Haas Body Shop",
    "wof:placetype":"venue"
},
  "geometry": {"coordinates":[-81.472842,40.518664],"type":"Point"}
}