{
  "type": "Feature",
  "properties": {
    "iso:country":"US",
    "sg:address":"7195 Singer Rd",
    "sg:city":"Dayton",
    "sg:classifiers":[
        {
            "category":"Recreation",
            "type":"Entertainment"
        }
    ],
    "sg:phone":"+1 937 845 9599",
    "sg:postcode":"45424",
    "sg:province":"OH",
    "sg:tags":[
        "stable"
    ],
    "wof:name":"Shady Glen Farms & Feed Pantry",
    "wof:placetype":"venue"
},
  "geometry": {"coordinates":[-84.079306,39.888792],"type":"Point"}
}