{
  "type": "Feature",
  "properties": {
    "addr:full":"2230 Bluebell Ln Grove City OH 43123",
    "addr:housenumber":"2230",
    "addr:postcode":"43123",
    "addr:street":"Bluebell Ln",
    "iso:country":"US",
    "sg:address":"2230 Bluebell Ln",
    "sg:city":"Grove City",
    "sg:classifiers":[
        {
            "category":"Building & Trades",
            "subcategory":"Construction",
            "type":"Services"
        }
    ],
    "sg:phone":"+1 614 871 3895",
    "sg:postcode":"43123",
    "sg:province":"OH",
    "sg:tags":[
        "house"
    ],
    "wof:name":"Walker & Sons Const",
    "wof:placetype":"venue"
},
  "geometry": {"coordinates":[-83.065219,39.853309],"type":"Point"}
}