{
  "type": "Feature",
  "properties": {
    "addr:full": "129 Executive Ct Westerville OH 43081",
    "addr:housenumber": "129",
    "addr:postcode": "43081",
    "addr:street": "Executive Ct",
    "iso:country": "US",
    "sg:address": "129 Executive Ct",
    "sg:city": "Westerville",
    "sg:classifiers": [
      {
        "category": "Professional",
        "subcategory": "Engineering",
        "type": "Services"
      }
    ],
    "sg:phone": "+1 614 890 2171",
    "sg:postcode": "43081",
    "sg:province": "OH",
    "sg:tags": [
      "engineer"
    ],
    "wof:name": "Frank Solutions LTD",
    "wof:placetype": "venue"
  },
  "geometry": {"coordinates":[-82.935795,40.132873],"type":"Point"}
}
