{
  "type": "Feature",
  "properties": {
    "addr:full": "242 E State St Athens OH 45701",
    "addr:housenumber": "242",
    "addr:postcode": "45701",
    "addr:street": "E State St",
    "iso:country": "US",
    "sg:address": "242 E State St",
    "sg:city": "Athens",
    "sg:classifiers": [
      {
        "category": "Wholesale",
        "subcategory": "Durable Goods \u0026 Equipment",
        "type": "Manufacturing \u0026 Wholesale Goods"
      }
    ],
    "sg:phone": "+1 740 592 3810",
    "sg:postcode": "45701",
    "sg:province": "OH",
    "sg:tags": [
      "importer"
    ],
    "wof:name": "Russkaya Traders",
    "wof:placetype": "venue"
  },
  "geometry": {"coordinates":[-82.093742,39.33743],"type":"Point"}
}
