{
  "type": "Feature",
  "properties": {
    "iso:country":"US",
    "sg:address":"242 E State St",
    "sg:city":"Athens",
    "sg:classifiers":[
        {
            "category":"Wholesale",
            "subcategory":"Durable Goods & Equipment",
            "type":"Manufacturing & Wholesale Goods"
        }
    ],
    "sg:phone":"+1 740 592 3810",
    "sg:postcode":"45701",
    "sg:province":"OH",
    "sg:tags":[
        "importer"
    ],
    "wof:name":"Russkaya Traders",
    "wof:placetype":"venue"
},
  "geometry": {"coordinates":[-82.09374200000001,39.33743],"type":"Point"}
}