{
  "type": "Feature",
  "properties": {
    "iso:country":"US",
    "sg:address":"7550 Lydia Ln",
    "sg:city":"Canfield",
    "sg:classifiers":[
        {
            "category":"Building & Trades",
            "subcategory":"Cleaning & Sanitation",
            "type":"Services"
        }
    ],
    "sg:phone":"+1 330 755 6196",
    "sg:postcode":"44406",
    "sg:province":"OH",
    "sg:tags":[
        "maintenance"
    ],
    "wof:name":"Sadie Sadie Cleaning Lady",
    "wof:placetype":"venue"
},
  "geometry": {"coordinates":[-80.794406,40.999032],"type":"Point"}
}