{
  "type": "Feature",
  "properties": {
    "iso:country":"US",
    "sg:address":"490 E 200th St",
    "sg:city":"Cleveland",
    "sg:classifiers":[
        {
            "category":"Shopping",
            "type":"Retail Goods"
        }
    ],
    "sg:phone":"+1 216 486 1112",
    "sg:postcode":"44119",
    "sg:province":"OH",
    "sg:tags":[
        "awning",
        "windows",
        "door",
        "storm"
    ],
    "wof:name":"Euclid Jalousies Inc",
    "wof:placetype":"venue"
},
  "geometry": {"coordinates":[-81.540234,41.593036],"type":"Point"}
}