{
  "type": "Feature",
  "properties": {
    "addr:full": "1745 Stine Rd Peninsula OH 44264",
    "addr:housenumber": "1745",
    "addr:postcode": "44264",
    "addr:street": "Stine Rd",
    "iso:country": "US",
    "sg:address": "1745 Stine Rd",
    "sg:city": "Peninsula",
    "sg:classifiers": [
      {
        "category": "Manufacturing",
        "subcategory": "Tools \u0026 Machinery",
        "type": "Manufacturing \u0026 Wholesale Goods"
      }
    ],
    "sg:phone": "+1 330 657 2134",
    "sg:postcode": "44264",
    "sg:province": "OH",
    "sg:tags": [
      "water"
    ],
    "wof:name": "Summit Engineering Co",
    "wof:placetype": "venue"
  },
  "geometry": {"coordinates":[-81.563377,41.248602],"type":"Point"}
}
