{
  "type": "Feature",
  "properties": {
    "addr:full": "29313 Clemens Rd Cleveland OH 44145",
    "addr:housenumber": "29313",
    "addr:postcode": "44145",
    "addr:street": "Clemens Rd",
    "iso:country": "US",
    "sg:address": "29313 Clemens Rd",
    "sg:city": "Cleveland",
    "sg:classifiers": [
      {
        "category": "Wholesale",
        "subcategory": "Medical Equipment \u0026 Supplies",
        "type": "Manufacturing \u0026 Wholesale Goods"
      },
      {
        "category": "Manufacturing",
        "subcategory": "Tools \u0026 Machinery",
        "type": "Manufacturing \u0026 Wholesale Goods"
      }
    ],
    "sg:phone": "+1 440 617 2200",
    "sg:postcode": "44145",
    "sg:province": "OH",
    "sg:tags": [
      "dental"
    ],
    "sg:website": "www.drrobertwolf.com",
    "wof:name": "Perfect Smile Corporation",
    "wof:placetype": "venue"
  },
  "geometry": {"coordinates":[-81.950659,41.470476],"type":"Point"}
}
