{
  "type": "Feature",
  "properties": {
    "addr:full":"5766 Richland Cir Milford OH 45150",
    "addr:housenumber":"5766",
    "addr:postcode":"45150",
    "addr:street":"Richland Cir",
    "iso:country":"US",
    "sg:address":"5766 Richland Cir",
    "sg:city":"Milford",
    "sg:classifiers":[
        {
            "category":"Communications",
            "subcategory":"Radio Station",
            "type":"Services"
        }
    ],
    "sg:phone":"+1 513 831 6546",
    "sg:postcode":"45150",
    "sg:province":"OH",
    "sg:tags":[
        "broadcast"
    ],
    "wof:name":"Oldies But Goodies",
    "wof:placetype":"venue"
},
  "geometry": {"coordinates":[-84.232207,39.182839],"type":"Point"}
}