{
  "type": "Feature",
  "properties": {
    "addr:full": "3402 Dahlgreen Dr Westerville OH 43081",
    "addr:housenumber": "3402",
    "addr:postcode": "43081",
    "addr:street": "Dahlgreen Dr",
    "iso:country": "US",
    "sg:address": "3402 Dahlgreen Dr",
    "sg:city": "Westerville",
    "sg:classifiers": [
      {
        "category": "Retail",
        "subcategory": "Repair Shop",
        "type": "Services"
      }
    ],
    "sg:phone": "+1 614 890 5296",
    "sg:postcode": "43081",
    "sg:province": "OH",
    "sg:tags": [
      "machine",
      "sewing"
    ],
    "wof:name": "Buckeye Sewing Svc",
    "wof:placetype": "venue"
  },
  "geometry": {"coordinates":[-82.915984,40.095726],"type":"Point"}
}
