{
  "type": "Feature",
  "properties": {
    "iso:country":"US",
    "sg:address":"3402 Dahlgreen Dr",
    "sg:city":"Westerville",
    "sg:classifiers":[
        {
            "category":"Retail",
            "subcategory":"Repair Shop",
            "type":"Services"
        }
    ],
    "sg:phone":"+1 614 890 5296",
    "sg:postcode":"43081",
    "sg:province":"OH",
    "sg:tags":[
        "machine",
        "sewing"
    ],
    "wof:name":"Buckeye Sewing Svc",
    "wof:placetype":"venue"
},
  "geometry": {"coordinates":[-82.91598399999999,40.095726],"type":"Point"}
}