{
  "type": "Feature",
  "properties": {
    "iso:country":"US",
    "sg:address":"140 Public Sq",
    "sg:city":"Cleveland",
    "sg:classifiers":[
        {
            "category":"Professional",
            "subcategory":"Advertising",
            "type":"Services"
        }
    ],
    "sg:phone":"+1 216 344 9800",
    "sg:postcode":"44114",
    "sg:province":"OH",
    "sg:tags":[
        "designer",
        "display",
        "producer"
    ],
    "wof:name":"Panel Vision",
    "wof:placetype":"venue"
},
  "geometry": {"coordinates":[-81.693012,41.500179],"type":"Point"}
}