{
  "type": "Feature",
  "properties": {
    "addr:full": "92 W 5th Ave Columbus OH 43201",
    "addr:housenumber": "92",
    "addr:postcode": "43201",
    "addr:street": "W 5Th Ave",
    "iso:country": "US",
    "sg:address": "92 W 5th Ave",
    "sg:city": "Columbus",
    "sg:classifiers": [
      {
        "category": "Building \u0026 Trades",
        "subcategory": "Construction",
        "type": "Services"
      }
    ],
    "sg:phone": "+1 614 294 0025",
    "sg:postcode": "43201",
    "sg:province": "OH",
    "sg:tags": [
      "windows"
    ],
    "wof:name": "Homestead Glass Co",
    "wof:placetype": "venue"
  },
  "geometry": {"coordinates":[-83.005513,39.9871],"type":"Point"}
}
