{
  "type": "Feature",
  "properties": {
    "iso:country":"US",
    "sg:address":"92 W 5th Ave",
    "sg:city":"Columbus",
    "sg:classifiers":[
        {
            "category":"Building & Trades",
            "subcategory":"Construction",
            "type":"Services"
        }
    ],
    "sg:phone":"+1 614 294 0025",
    "sg:postcode":"43201",
    "sg:province":"OH",
    "sg:tags":[
        "windows"
    ],
    "wof:name":"Homestead Glass Co",
    "wof:placetype":"venue"
},
  "geometry": {"coordinates":[-83.00551299999999,39.9871],"type":"Point"}
}