{
  "type": "Feature",
  "properties": {
    "addr:full":"1300 W 9th St Cleveland OH 44113",
    "addr:housenumber":"1300",
    "addr:postcode":"44113",
    "addr:street":"W 9Th St",
    "iso:country":"US",
    "sg:address":"1300 W 9th St",
    "sg:city":"Cleveland",
    "sg:classifiers":[
        {
            "category":"Professional",
            "subcategory":"Computer Services",
            "type":"Services"
        }
    ],
    "sg:phone":"+1 216 344 1232",
    "sg:postcode":"44113",
    "sg:province":"OH",
    "sg:tags":[
        "internet"
    ],
    "wof:name":"Northern Ohio Broadband",
    "wof:placetype":"venue"
},
  "geometry": {"coordinates":[-81.70027899999999,41.498718],"type":"Point"}
}