{
  "type": "Feature",
  "properties": {
    "iso:country":"US",
    "sg:address":"317 Geneva Rd",
    "sg:city":"Dayton",
    "sg:classifiers":[
        {
            "category":"Organizations",
            "subcategory":"Religious Organization",
            "type":"Services"
        }
    ],
    "sg:phone":"+1 937 268 4344",
    "sg:postcode":"45417",
    "sg:province":"OH",
    "sg:tags":[
        "clergy"
    ],
    "wof:name":"Benjamin F Shockley",
    "wof:placetype":"venue"
},
  "geometry": {"coordinates":[-84.260363,39.751946],"type":"Point"}
}