{
  "type": "Feature",
  "properties": {
    "addr:full":"9380 Saint Clair Ave Cleveland OH 44108",
    "addr:housenumber":"9380",
    "addr:postcode":"44108",
    "addr:street":"Saint Clair Ave",
    "iso:country":"US",
    "sg:address":"9380 Saint Clair Ave",
    "sg:city":"Cleveland",
    "sg:classifiers":[
        {
            "category":"Real Estate",
            "subcategory":"Real Estate Operator",
            "type":"Services"
        }
    ],
    "sg:phone":"+1 216 249 9400",
    "sg:postcode":"44108",
    "sg:province":"OH",
    "sg:tags":[
        "building",
        "apartment"
    ],
    "wof:name":"Glen Haven Apartments",
    "wof:placetype":"venue"
},
  "geometry": {"coordinates":[-81.62205299999999,41.53569],"type":"Point"}
}