{
  "type": "Feature",
  "properties": {
    "addr:full":"436 W River St S Elyria OH 44035",
    "addr:housenumber":"436",
    "addr:postcode":"44035",
    "addr:street":"W River St S",
    "iso:country":"US",
    "sg:address":"436 W River St S",
    "sg:city":"Elyria",
    "sg:classifiers":[
        {
            "category":"Health Services",
            "subcategory":"Health Practitioner",
            "type":"Services"
        }
    ],
    "sg:phone":"+1 440 322 1667",
    "sg:postcode":"44035",
    "sg:province":"OH",
    "sg:tags":[
        "therapist",
        "physical"
    ],
    "wof:name":"Integrity PT",
    "wof:placetype":"venue"
},
  "geometry": {"coordinates":[-82.11631800000001,41.36031],"type":"Point"}
}