{
  "type": "Feature",
  "properties": {
    "iso:country":"US",
    "sg:address":"2477 Mogadore Rd",
    "sg:city":"Akron",
    "sg:classifiers":[
        {
            "category":"Retail",
            "subcategory":"Animal Services",
            "type":"Services"
        }
    ],
    "sg:phone":"+1 330 733 9590",
    "sg:postcode":"44312",
    "sg:province":"OH",
    "sg:tags":[
        "pet",
        "training"
    ],
    "wof:name":"Papp's Dog Svc",
    "wof:placetype":"venue"
},
  "geometry": {"coordinates":[-81.439571,41.063557],"type":"Point"}
}