{
  "type": "Feature",
  "properties": {
    "iso:country":"US",
    "sg:address":"760 N Market St",
    "sg:city":"Minerva",
    "sg:classifiers":[
        {
            "category":"Real Estate",
            "subcategory":"Real Estate Agent",
            "type":"Services"
        }
    ],
    "sg:phone":"+1 330 868 4106",
    "sg:postcode":"44657",
    "sg:province":"OH",
    "wof:name":"Nantodd LLC",
    "wof:placetype":"venue"
},
  "geometry": {"coordinates":[-81.098973,40.736761],"type":"Point"}
}