{
  "type": "Feature",
  "properties": {
    "addr:full":"690 Euclaire Ave Columbus OH 43209",
    "addr:housenumber":"690",
    "addr:postcode":"43209",
    "addr:street":"Euclaire Ave",
    "iso:country":"US",
    "sg:address":"690 Euclaire Ave",
    "sg:city":"Columbus",
    "sg:classifiers":[
        {
            "category":"Building & Trades",
            "subcategory":"Construction",
            "type":"Services"
        }
    ],
    "sg:phone":"+1 614 235 0749",
    "sg:postcode":"43209",
    "sg:province":"OH",
    "sg:tags":[
        "hanging",
        "contractor"
    ],
    "wof:name":"G List Inc",
    "wof:placetype":"venue"
},
  "geometry": {"coordinates":[-82.93340000000001,39.957065],"type":"Point"}
}