{
  "type": "Feature",
  "properties": {
    "addr:full":"9945 N Co Rd 25A Piqua OH 45356",
    "addr:housenumber":"9945;25a",
    "addr:postcode":"45356",
    "addr:street":"N Co Rd",
    "iso:country":"US",
    "sg:address":"9945 N Co Rd 25A",
    "sg:city":"Piqua",
    "sg:classifiers":[
        {
            "category":"Wholesale",
            "subcategory":"Scrap",
            "type":"Manufacturing & Wholesale Goods"
        }
    ],
    "sg:phone":"+1 937 773 3989",
    "sg:postcode":"45356",
    "sg:province":"OH",
    "sg:tags":[
        "waste"
    ],
    "wof:name":"Pence Containerized Refuse Svc",
    "wof:placetype":"venue"
},
  "geometry": {"coordinates":[-84.195061,40.175415],"type":"Point"}
}