{
  "type": "Feature",
  "properties": {
    "addr:full": "17324 Broadway Ave Cleveland OH 44137",
    "addr:housenumber": "17324",
    "addr:postcode": "ave;44137",
    "addr:street": "Broadway",
    "iso:country": "US",
    "sg:address": "17324 Broadway Ave",
    "sg:city": "Cleveland",
    "sg:classifiers": [
      {
        "category": "Personal",
        "subcategory": "Beauty Salon",
        "type": "Services"
      }
    ],
    "sg:phone": "+1 216 662 8949",
    "sg:postcode": "44137",
    "sg:province": "OH",
    "wof:name": "Fran's Beauty Salon",
    "wof:placetype": "venue"
  },
  "geometry": {"coordinates":[-81.557214,41.406056],"type":"Point"}
}
