{
  "type": "Feature",
  "properties": {
    "addr:full":"328 Bank St Lodi OH 44254",
    "addr:housenumber":"328",
    "addr:postcode":"44254",
    "addr:street":"Bank St",
    "iso:country":"US",
    "sg:address":"328 Bank St",
    "sg:city":"Lodi",
    "sg:classifiers":[
        {
            "category":"Manufacturing",
            "subcategory":"Tools & Machinery",
            "type":"Manufacturing & Wholesale Goods"
        }
    ],
    "sg:phone":"+1 330 948 2353",
    "sg:postcode":"44254",
    "sg:province":"OH",
    "sg:tags":[
        "machine",
        "shop"
    ],
    "wof:name":"Marcum Machine Shop",
    "wof:placetype":"venue"
},
  "geometry": {"coordinates":[-82.01672000000001,41.032767],"type":"Point"}
}