{
  "type": "Feature",
  "properties": {
    "addr:full":"435 Boardman Canfield Rd Youngstown OH 44512",
    "addr:housenumber":"435",
    "addr:postcode":"44512",
    "addr:street":"Boardman Canfield Rd",
    "iso:country":"US",
    "sg:address":"435 Boardman Canfield Rd",
    "sg:city":"Youngstown",
    "sg:classifiers":[
        {
            "category":"Banks & Credit Unions",
            "subcategory":"Bank",
            "type":"Services"
        }
    ],
    "sg:phone":"+1 330 965 9776",
    "sg:postcode":"44512",
    "sg:province":"OH",
    "sg:tags":[
        "loan"
    ],
    "wof:name":"Check Into Cash",
    "wof:placetype":"venue"
},
  "geometry": {"coordinates":[-80.676408,41.024385],"type":"Point"}
}