{
  "type": "Feature",
  "properties": {
    "addr:full":"100 E Broad St Elyria OH 44035",
    "addr:housenumber":"100",
    "addr:postcode":"44035",
    "addr:street":"E Broad St",
    "iso:country":"US",
    "sg:address":"100 E Broad St",
    "sg:city":"Elyria",
    "sg:classifiers":[
        {
            "category":"Retail",
            "subcategory":"Auto Repair",
            "type":"Services"
        }
    ],
    "sg:phone":"+1 440 322 1508",
    "sg:postcode":"44035",
    "sg:province":"OH",
    "sg:tags":[
        "general"
    ],
    "wof:name":"John Pais Auto Service Inc",
    "wof:placetype":"venue"
},
  "geometry": {"coordinates":[-82.09536300000001,41.367529],"type":"Point"}
}