{
  "type": "Feature",
  "properties": {
    "addr:full":"6572 Butler Warren Rd Mason OH 45040",
    "addr:housenumber":"6572",
    "addr:postcode":"45040",
    "addr:street":"Butler Warren Rd",
    "iso:country":"US",
    "sg:address":"6572 Butler Warren Rd",
    "sg:city":"Mason",
    "sg:classifiers":[
        {
            "category":"Building & Trades",
            "subcategory":"Landscaping Services",
            "type":"Services"
        }
    ],
    "sg:phone":"+1 513 459 1330",
    "sg:postcode":"45040",
    "sg:province":"OH",
    "wof:name":"Approved Lawn Care",
    "wof:placetype":"venue"
},
  "geometry": {"coordinates":[-84.348699,39.342039],"type":"Point"}
}