{
  "type": "Feature",
  "properties": {
    "addr:full":"3170 Wasson Rd Cincinnati OH 45209",
    "addr:postcode":"3170;45209",
    "addr:street":"Wasson Rd",
    "iso:country":"US",
    "sg:address":"3170 Wasson Rd",
    "sg:city":"Cincinnati",
    "sg:classifiers":[
        {
            "category":"Manufacturing",
            "subcategory":"Metals",
            "type":"Manufacturing & Wholesale Goods"
        }
    ],
    "sg:phone":"+1 513 533 7340",
    "sg:postcode":"45209",
    "sg:province":"OH",
    "sg:tags":[
        "valve"
    ],
    "sg:website":"www.marwinvalve.com",
    "wof:name":"Marwin Ball Valves",
    "wof:placetype":"venue"
},
  "geometry": {"coordinates":[-84.42667400000001,39.144049],"type":"Point"}
}