{
  "type": "Feature",
  "properties": {
    "iso:country":"US",
    "sg:address":"1515 W 3rd Ave",
    "sg:city":"Columbus",
    "sg:classifiers":[
        {
            "category":"Professional",
            "subcategory":"Lawyer & Legal Services",
            "type":"Services"
        }
    ],
    "sg:phone":"+1 614 486 0052",
    "sg:postcode":"43212",
    "sg:province":"OH",
    "sg:tags":[
        "attorney"
    ],
    "wof:name":"Lorelei M Lanier",
    "wof:placetype":"venue"
},
  "geometry": {"coordinates":[-83.045174,39.985053],"type":"Point"}
}