{
  "type": "Feature",
  "properties": {
    "addr:full": "419 A St Hamilton IN 45013",
    "addr:housenumber": "419",
    "addr:postcode": "45013",
    "addr:street": "A St",
    "iso:country": "US",
    "sg:address": "419 A St",
    "sg:city": "Hamilton",
    "sg:classifiers": [
      {
        "category": "Retail",
        "subcategory": "Auto Repair",
        "type": "Services"
      }
    ],
    "sg:phone": "+1 513 887 7333",
    "sg:postcode": "45013",
    "sg:province": "IN",
    "sg:tags": [
      "body",
      "automobile",
      "painting"
    ],
    "wof:name": "Lewis Collision \u0026 Refinishing",
    "wof:placetype": "venue"
  },
  "geometry": {"coordinates":[-84.572764,39.395144],"type":"Point"}
}
