{
  "type": "Feature",
  "properties": {
    "iso:country":"US",
    "sg:address":"1624 Marion Mount Gilead Rd",
    "sg:city":"Marion",
    "sg:classifiers":[
        {
            "category":"Restaurant",
            "type":"Food & Drink"
        }
    ],
    "sg:menulink":"http://www.allmenus.com/oh/marion/192962-bellacinos/menu/",
    "sg:phone":"+1 740 389 4732",
    "sg:postcode":"43302",
    "sg:province":"OH",
    "sg:tags":[
        "american"
    ],
    "wof:name":"Bellacino's",
    "wof:placetype":"venue"
},
  "geometry": {"coordinates":[-83.08540000000001,40.581137],"type":"Point"}
}