{
  "type": "Feature",
  "properties": {
    "addr:full": "1624 Marion Mount Gilead Rd Marion OH 43302",
    "addr:housenumber": "1624",
    "addr:postcode": "43302",
    "addr:street": "Marion Mount Gilead Rd",
    "iso:country": "US",
    "sg:address": "1624 Marion Mount Gilead Rd",
    "sg:city": "Marion",
    "sg:classifiers": [
      {
        "category": "Restaurant",
        "type": "Food \u0026 Drink"
      }
    ],
    "sg:menulink": "http://www.allmenus.com/oh/marion/192962-bellacinos/menu/",
    "sg:phone": "+1 740 389 4732",
    "sg:postcode": "43302",
    "sg:province": "OH",
    "sg:tags": [
      "american"
    ],
    "wof:name": "Bellacino's",
    "wof:placetype": "venue"
  },
  "geometry": {"coordinates":[-83.0854,40.581137],"type":"Point"}
}
