{
  "type": "Feature",
  "properties": {
    "addr:full":"305 Lennox Ave NW Massillon OH 44646",
    "addr:housenumber":"305",
    "addr:postcode":"44646",
    "addr:street":"Lennox Ave Nw",
    "iso:country":"US",
    "sg:address":"305 Lennox Ave NW",
    "sg:city":"Massillon",
    "sg:classifiers":[
        {
            "category":"Building & Trades",
            "subcategory":"Construction",
            "type":"Services"
        }
    ],
    "sg:phone":"+1 330 830 5034",
    "sg:postcode":"44646",
    "sg:province":"OH",
    "sg:tags":[
        "house"
    ],
    "wof:name":"Kerestes Construction",
    "wof:placetype":"venue"
},
  "geometry": {"coordinates":[-81.47281,40.795942],"type":"Point"}
}