{
  "type": "Feature",
  "properties": {
    "addr:full": "468 Cleveland St Elyria OH 44035",
    "addr:housenumber": "468",
    "addr:postcode": "44035",
    "addr:street": "Cleveland St",
    "iso:country": "US",
    "sg:address": "468 Cleveland St",
    "sg:city": "Elyria",
    "sg:classifiers": [
      {
        "category": "Home \u0026 Garden",
        "subcategory": "Household Appliances",
        "type": "Retail Goods"
      }
    ],
    "sg:phone": "+1 440 365 7321",
    "sg:postcode": "44035",
    "sg:province": "OH",
    "sg:website": "www.stewartappliance.com",
    "wof:name": "Stewart's TV \u0026 Appliance",
    "wof:placetype": "venue"
  },
  "geometry": {"coordinates":[-82.084229,41.375426],"type":"Point"}
}
