{
  "type": "Feature",
  "properties": {
    "iso:country":"US",
    "sg:address":"468 Cleveland St",
    "sg:city":"Elyria",
    "sg:classifiers":[
        {
            "category":"Home & Garden",
            "subcategory":"Household Appliances",
            "type":"Retail Goods"
        }
    ],
    "sg:phone":"+1 440 365 7321",
    "sg:postcode":"44035",
    "sg:province":"OH",
    "sg:website":"www.stewartappliance.com",
    "wof:name":"Stewart's TV & Appliance",
    "wof:placetype":"venue"
},
  "geometry": {"coordinates":[-82.084229,41.375426],"type":"Point"}
}