{
  "type": "Feature",
  "properties": {
    "iso:country":"US",
    "sg:address":"215 Commerce Way",
    "sg:city":"Upper Sandusky",
    "sg:classifiers":[
        {
            "category":"Wholesale",
            "subcategory":"Auto Parts",
            "type":"Manufacturing & Wholesale Goods"
        }
    ],
    "sg:phone":"+1 419 294 2432",
    "sg:postcode":"43351",
    "sg:province":"OH",
    "sg:tags":[
        "vehicle",
        "recreational",
        "truck",
        "accessory"
    ],
    "wof:name":"Mc Guire Automotive Wholesale",
    "wof:placetype":"venue"
},
  "geometry": {"coordinates":[-83.273792,40.855806],"type":"Point"}
}