{
  "type": "Feature",
  "properties": {
    "addr:full": "862 Hoover Dr Ashland OH 44805",
    "addr:housenumber": "862",
    "addr:postcode": "44805",
    "addr:street": "Hoover Dr",
    "iso:country": "US",
    "sg:address": "862 Hoover Dr",
    "sg:city": "Ashland",
    "sg:classifiers": [
      {
        "category": "Communications",
        "subcategory": "Film \u0026 Video Production",
        "type": "Services"
      }
    ],
    "sg:phone": "+1 419 281 4566",
    "sg:postcode": "44805",
    "sg:province": "OH",
    "sg:tags": [
      "taping"
    ],
    "wof:name": "Joe Denbow \u0026 Assoc",
    "wof:placetype": "venue"
  },
  "geometry": {"coordinates":[-82.300394,40.859543],"type":"Point"}
}
