{
  "type": "Feature",
  "properties": {
    "iso:country":"US",
    "sg:address":"862 Hoover Dr",
    "sg:city":"Ashland",
    "sg:classifiers":[
        {
            "category":"Communications",
            "subcategory":"Film & Video Production",
            "type":"Services"
        }
    ],
    "sg:phone":"+1 419 281 4566",
    "sg:postcode":"44805",
    "sg:province":"OH",
    "sg:tags":[
        "taping"
    ],
    "wof:name":"Joe Denbow & Assoc",
    "wof:placetype":"venue"
},
  "geometry": {"coordinates":[-82.300394,40.859543],"type":"Point"}
}