{
  "type": "Feature",
  "properties": {
    "iso:country":"US",
    "sg:address":"7099 Leibel Rd",
    "sg:city":"Cincinnati",
    "sg:classifiers":[
        {
            "category":"Real Estate",
            "subcategory":"Real Estate Agent",
            "type":"Services"
        }
    ],
    "sg:phone":"+1 513 574 6467",
    "sg:postcode":"45248",
    "sg:province":"OH",
    "wof:name":"Bickel Realtor",
    "wof:placetype":"venue"
},
  "geometry": {"coordinates":[-84.682664,39.150601],"type":"Point"}
}