{
  "type": "Feature",
  "properties": {
    "addr:full":"2400 Highpoint Rd Cleveland OH 44124",
    "addr:housenumber":"2400",
    "addr:postcode":"44124",
    "addr:street":"Highpoint Rd",
    "iso:country":"US",
    "sg:address":"2400 Highpoint Rd",
    "sg:city":"Cleveland",
    "sg:classifiers":[
        {
            "category":"Health Services",
            "subcategory":"Doctor",
            "type":"Services"
        }
    ],
    "sg:phone":"+1 216 831 6550",
    "sg:postcode":"44124",
    "sg:province":"OH",
    "sg:tags":[
        "psychiatrist"
    ],
    "wof:name":"Comprehensive Psychiatric Servs Inc",
    "wof:placetype":"venue"
},
  "geometry": {"coordinates":[-81.46520200000001,41.5116],"type":"Point"}
}