{
  "type": "Feature",
  "properties": {
    "addr:full":"142 N Main St Waynesville OH 45068",
    "addr:housenumber":"142",
    "addr:postcode":"45068",
    "addr:street":"N Main St",
    "iso:country":"US",
    "sg:address":"142 N Main St",
    "sg:city":"Waynesville",
    "sg:classifiers":[
        {
            "category":"Real Estate",
            "subcategory":"Architect",
            "type":"Services"
        }
    ],
    "sg:phone":"+1 513 897 3111",
    "sg:postcode":"45068",
    "sg:province":"OH",
    "sg:website":"www.stanrussellarchitect.com",
    "wof:name":"Design Works",
    "wof:placetype":"venue"
},
  "geometry": {"coordinates":[-84.084632,39.531784],"type":"Point"}
}