{
  "type": "Feature",
  "properties": {
    "addr:full":"201 S Main St Cadiz OH 43907",
    "addr:housenumber":"201",
    "addr:postcode":"43907",
    "addr:street":"S Main St",
    "iso:country":"US",
    "sg:address":"201 S Main St",
    "sg:city":"Cadiz",
    "sg:classifiers":[
        {
            "category":"Organizations",
            "subcategory":"Religious Organization",
            "type":"Services"
        }
    ],
    "sg:phone":"+1 740 942 1177",
    "sg:postcode":"43907",
    "sg:province":"OH",
    "sg:tags":[
        "church"
    ],
    "wof:name":"Hillside Baptist Church",
    "wof:placetype":"venue"
},
  "geometry": {"coordinates":[-80.998205,40.271875],"type":"Point"}
}