{
  "type": "Feature",
  "properties": {
    "addr:full":"34501 Aurora Rd Cleveland OH 44139",
    "addr:housenumber":"34501",
    "addr:postcode":"44139",
    "addr:street":"Aurora Rd",
    "iso:country":"US",
    "sg:address":"34501 Aurora Rd",
    "sg:city":"Cleveland",
    "sg:classifiers":[
        {
            "category":"Health Services",
            "subcategory":"Doctor",
            "type":"Services"
        }
    ],
    "sg:phone":"+1 440 349 2999",
    "sg:postcode":"44139",
    "sg:province":"OH",
    "sg:tags":[
        "physician",
        "surgeon"
    ],
    "wof:name":"J Jin El-Mallawany MD",
    "wof:placetype":"venue"
},
  "geometry": {"coordinates":[-81.428631,41.380846],"type":"Point"}
}