{
  "type": "Feature",
  "properties": {
    "addr:full":"28720 Tracy Rd Walbridge OH 43465",
    "addr:housenumber":"28720",
    "addr:postcode":"43465",
    "addr:street":"Tracy Rd",
    "iso:country":"US",
    "sg:address":"28720 Tracy Rd",
    "sg:city":"Walbridge",
    "sg:classifiers":[
        {
            "category":"Professional",
            "subcategory":"Research",
            "type":"Services"
        }
    ],
    "sg:phone":"+1 419 666 5310",
    "sg:postcode":"43465",
    "sg:province":"OH",
    "sg:tags":[
        "environmental",
        "ecological"
    ],
    "wof:name":"MWC Ohio",
    "wof:placetype":"venue"
},
  "geometry": {"coordinates":[-83.527608,41.5657],"type":"Point"}
}