{
  "type": "Feature",
  "properties": {
    "iso:country":"US",
    "sg:address":"8216 W Chester Rd",
    "sg:city":"West Chester",
    "sg:classifiers":[
        {
            "category":"Insurance",
            "subcategory":"Insurance Agent",
            "type":"Services"
        }
    ],
    "sg:phone":"+1 513 779 4003",
    "sg:postcode":"45069",
    "sg:province":"OH",
    "wof:name":"Reserve Financial Agency",
    "wof:placetype":"venue"
},
  "geometry": {"coordinates":[-84.356033,39.317762],"type":"Point"}
}