{
  "type": "Feature",
  "properties": {
    "iso:country":"US",
    "sg:address":"1922 Randall Ave",
    "sg:city":"Dayton",
    "sg:classifiers":[
        {
            "category":"Building & Trades",
            "subcategory":"Construction",
            "type":"Services"
        }
    ],
    "sg:phone":"+1 937 256 4963",
    "sg:postcode":"45420",
    "sg:province":"OH",
    "sg:tags":[
        "hanging",
        "contractor"
    ],
    "wof:name":"Sharon S Painter",
    "wof:placetype":"venue"
},
  "geometry": {"coordinates":[-84.138806,39.737932],"type":"Point"}
}