{
  "type": "Feature",
  "properties": {
    "addr:full":"104 High St Wadsworth OH 44281",
    "addr:housenumber":"104",
    "addr:postcode":"44281",
    "addr:street":"High St",
    "iso:country":"US",
    "sg:address":"104 High St",
    "sg:city":"Wadsworth",
    "sg:classifiers":[
        {
            "category":"Shopping",
            "subcategory":"Stationery & Office Supplies",
            "type":"Retail Goods"
        },
        {
            "category":"Shopping",
            "type":"Retail Goods"
        }
    ],
    "sg:phone":"+1 330 334 1079",
    "sg:postcode":"44281",
    "sg:province":"OH",
    "sg:tags":[
        "machine"
    ],
    "wof:name":"Accurate Office Equipment Inc",
    "wof:placetype":"venue"
},
  "geometry": {"coordinates":[-81.72969500000001,41.025599],"type":"Point"}
}