{
  "type": "Feature",
  "properties": {
    "addr:full": "8090 Cedar Rd Chesterland OH 44026",
    "addr:housenumber": "8090",
    "addr:postcode": "44026",
    "addr:street": "Cedar Rd",
    "iso:country": "US",
    "sg:address": "8090 Cedar Rd",
    "sg:city": "Chesterland",
    "sg:classifiers": [
      {
        "category": "Professional",
        "subcategory": "Business Services",
        "type": "Services"
      }
    ],
    "sg:phone": "+1 440 729 1919",
    "sg:postcode": "44026",
    "sg:province": "OH",
    "sg:tags": [
      "packaging"
    ],
    "wof:name": "Metzenbaum Adult Svc",
    "wof:placetype": "venue"
  },
  "geometry": {"coordinates":[-81.356256,41.507914],"type":"Point"}
}
