{
  "type": "Feature",
  "properties": {
    "iso:country":"US",
    "sg:address":"3884 N Dayton Xenia Rd",
    "sg:city":"Beavercreek",
    "sg:classifiers":[
        {
            "category":"Building & Trades",
            "subcategory":"Plumbing",
            "type":"Services"
        }
    ],
    "sg:phone":"+1 937 426 7399",
    "sg:postcode":"45432",
    "sg:province":"OH",
    "sg:tags":[
        "air",
        "conditioning",
        "contractor",
        "system",
        "heating"
    ],
    "wof:name":"Extreme Heating & Cooling",
    "wof:placetype":"venue"
},
  "geometry": {"coordinates":[-84.07799199999999,39.736161],"type":"Point"}
}