{
  "type": "Feature",
  "properties": {
    "iso:country":"US",
    "sg:address":"1045 Mackenzie Dr",
    "sg:city":"Lima",
    "sg:classifiers":[
        {
            "category":"Professional",
            "subcategory":"Lawyer & Legal Services",
            "type":"Services"
        }
    ],
    "sg:phone":"+1 419 224 0075",
    "sg:postcode":"45805",
    "sg:province":"OH",
    "sg:tags":[
        "attorney"
    ],
    "wof:name":"Allotta & Farley Co",
    "wof:placetype":"venue"
},
  "geometry": {"coordinates":[-84.145675,40.752927],"type":"Point"}
}