{
  "type": "Feature",
  "properties": {
    "iso:country":"US",
    "sg:address":"2987 46th St SW",
    "sg:city":"Canton",
    "sg:classifiers":[
        {
            "category":"Building & Trades",
            "subcategory":"Construction",
            "type":"Services"
        }
    ],
    "sg:phone":"+1 330 484 3670",
    "sg:postcode":"44706",
    "sg:province":"OH",
    "sg:tags":[
        "contractor"
    ],
    "wof:name":"Singlesource Roofing",
    "wof:placetype":"venue"
},
  "geometry": {"coordinates":[-81.41129599999999,40.745765],"type":"Point"}
}