{
  "type": "Feature",
  "properties": {
    "addr:full": "2987 46th St SW Canton OH 44706",
    "addr:housenumber": "2987",
    "addr:postcode": "44706",
    "addr:street": "46Th St Sw",
    "iso:country": "US",
    "sg:address": "2987 46th St SW",
    "sg:city": "Canton",
    "sg:classifiers": [
      {
        "category": "Building \u0026 Trades",
        "subcategory": "Construction",
        "type": "Services"
      }
    ],
    "sg:phone": "+1 330 484 3670",
    "sg:postcode": "44706",
    "sg:province": "OH",
    "sg:tags": [
      "contractor"
    ],
    "wof:name": "Singlesource Roofing",
    "wof:placetype": "venue"
  },
  "geometry": {"coordinates":[-81.411296,40.745765],"type":"Point"}
}
