{
  "type": "Feature",
  "properties": {
    "iso:country":"US",
    "sg:address":"660 Dover Center Rd",
    "sg:city":"Bay Village",
    "sg:classifiers":[
        {
            "category":"Health Services",
            "subcategory":"Doctor",
            "type":"Services"
        }
    ],
    "sg:phone":"+1 440 899 7950",
    "sg:postcode":"44140",
    "sg:province":"OH",
    "sg:tags":[
        "dentist"
    ],
    "wof:name":"Bay Dental Offices",
    "wof:placetype":"venue"
},
  "geometry": {"coordinates":[-81.92121299999999,41.477194],"type":"Point"}
}