{
  "type": "Feature",
  "properties": {
    "addr:full":"4915 Lower Valley Pike Springfield OH 45506",
    "addr:housenumber":"4915",
    "addr:postcode":"45506",
    "addr:street":"Lower Valley Pike",
    "iso:country":"US",
    "sg:address":"4915 Lower Valley Pike",
    "sg:city":"Springfield",
    "sg:classifiers":[
        {
            "category":"Wholesale",
            "subcategory":"Machinery & Supplies",
            "type":"Manufacturing & Wholesale Goods"
        }
    ],
    "sg:phone":"+1 937 322 7242",
    "sg:postcode":"45506",
    "sg:province":"OH",
    "sg:tags":[
        "pump"
    ],
    "wof:name":"Gothard Pump & Supply Co",
    "wof:placetype":"venue"
},
  "geometry": {"coordinates":[-83.904933,39.907842],"type":"Point"}
}