{
  "type": "Feature",
  "properties": {
    "iso:country":"US",
    "sg:address":"10700 Robstone Ct",
    "sg:city":"Powell",
    "sg:classifiers":[
        {
            "category":"Professional",
            "subcategory":"Computer Services",
            "type":"Services"
        }
    ],
    "sg:phone":"+1 614 764 4616",
    "sg:postcode":"43065",
    "sg:province":"OH",
    "sg:tags":[
        "consultant",
        "designer"
    ],
    "wof:name":"Decisive Systems Technology",
    "wof:placetype":"venue"
},
  "geometry": {"coordinates":[-83.086029,40.140081],"type":"Point"}
}