{
  "type": "Feature",
  "properties": {
    "addr:full": "309 W Loveland Ave Loveland OH 45140",
    "addr:housenumber": "309",
    "addr:postcode": "45140",
    "addr:street": "W Loveland Ave",
    "iso:country": "US",
    "sg:address": "309 W Loveland Ave",
    "sg:city": "Loveland",
    "sg:classifiers": [
      {
        "category": "Food \u0026 Beverages",
        "subcategory": "Liquor \u0026 Beverages",
        "type": "Retail Goods"
      }
    ],
    "sg:phone": "+1 513 677 2599",
    "sg:postcode": "45140",
    "sg:province": "OH",
    "sg:tags": [
      "beer",
      "ale",
      "alcoholic"
    ],
    "wof:name": "Butch's Deli \u0026 Carry Out",
    "wof:placetype": "venue"
  },
  "geometry": {"coordinates":[-84.26166,39.268728],"type":"Point"}
}
