{
  "type": "Feature",
  "properties": {
    "iso:country":"US",
    "sg:address":"309 W Loveland Ave",
    "sg:city":"Loveland",
    "sg:classifiers":[
        {
            "category":"Food & Beverages",
            "subcategory":"Liquor & Beverages",
            "type":"Retail Goods"
        }
    ],
    "sg:phone":"+1 513 677 2599",
    "sg:postcode":"45140",
    "sg:province":"OH",
    "sg:tags":[
        "beer",
        "ale",
        "alcoholic"
    ],
    "wof:name":"Butch's Deli & Carry Out",
    "wof:placetype":"venue"
},
  "geometry": {"coordinates":[-84.26166000000001,39.268728],"type":"Point"}
}