{
  "type": "Feature",
  "properties": {
    "addr:full":"810 Dodgeville Rd Jefferson OH 44047",
    "addr:housenumber":"810",
    "addr:postcode":"44047",
    "addr:street":"Dodgeville Rd",
    "iso:country":"US",
    "sg:address":"810 Dodgeville Rd",
    "sg:city":"Jefferson",
    "sg:classifiers":[
        {
            "category":"Government",
            "subcategory":"Office",
            "type":"Public Place"
        }
    ],
    "sg:phone":"+1 440 294 3632",
    "sg:postcode":"44047",
    "sg:province":"OH",
    "sg:tags":[
        "village"
    ],
    "wof:name":"New Lyme Twp Garage",
    "wof:placetype":"venue"
},
  "geometry": {"coordinates":[-80.754949,41.58784],"type":"Point"}
}