{
  "type": "Feature",
  "properties": {
    "addr:full": "508 Sherwood St Piqua OH 45356",
    "addr:housenumber": "508",
    "addr:postcode": "45356",
    "addr:street": "Sherwood St",
    "iso:country": "US",
    "sg:address": "508 Sherwood St",
    "sg:city": "Piqua",
    "sg:classifiers": [
      {
        "category": "Building \u0026 Trades",
        "subcategory": "Landscaping Services",
        "type": "Services"
      }
    ],
    "sg:phone": "+1 937 773 3673",
    "sg:postcode": "45356",
    "sg:province": "OH",
    "wof:name": "Dawn Lewis",
    "wof:placetype": "venue"
  },
  "geometry": {"coordinates":[-84.264056,40.137558],"type":"Point"}
}
