{
  "type": "Feature",
  "properties": {
    "addr:full": "16504 Pearldale Ave Cleveland OH 44135",
    "addr:postcode": "16504;44135",
    "addr:street": "Pearldale Ave",
    "iso:country": "US",
    "sg:address": "16504 Pearldale Ave",
    "sg:city": "Cleveland",
    "sg:classifiers": [
      {
        "category": "Building \u0026 Trades",
        "subcategory": "Pest Control",
        "type": "Services"
      }
    ],
    "sg:phone": "+1 216 251 7770",
    "sg:postcode": "44135",
    "sg:province": "OH",
    "wof:name": "Aggressive Termite \u0026 Pest Co",
    "wof:placetype": "venue"
  },
  "geometry": {"coordinates":[-81.813529,41.44179],"type":"Point"}
}
