{
  "type": "Feature",
  "properties": {
    "iso:country":"US",
    "sg:address":"16504 Pearldale Ave",
    "sg:city":"Cleveland",
    "sg:classifiers":[
        {
            "category":"Building & Trades",
            "subcategory":"Pest Control",
            "type":"Services"
        }
    ],
    "sg:phone":"+1 216 251 7770",
    "sg:postcode":"44135",
    "sg:province":"OH",
    "wof:name":"Aggressive Termite & Pest Co",
    "wof:placetype":"venue"
},
  "geometry": {"coordinates":[-81.813529,41.44179],"type":"Point"}
}