{
  "type": "Feature",
  "properties": {
    "addr:full": "10094 Bolingbroke Dr Cincinnati OH 45241",
    "addr:housenumber": "10094",
    "addr:postcode": "45241",
    "addr:street": "Bolingbroke Dr",
    "iso:country": "US",
    "sg:address": "10094 Bolingbroke Dr",
    "sg:city": "Cincinnati",
    "sg:classifiers": [
      {
        "category": "Professional",
        "type": "Services"
      }
    ],
    "sg:phone": "+1 513 777 3141",
    "sg:postcode": "45241",
    "sg:province": "OH",
    "sg:tags": [
      "hospital"
    ],
    "wof:name": "Mitzi Shomler",
    "wof:placetype": "venue"
  },
  "geometry": {"coordinates":[-84.381604,39.298099],"type":"Point"}
}
