{
  "type": "Feature",
  "properties": {
    "addr:full": "39 W Winter St Delaware OH 43015",
    "addr:housenumber": "39",
    "addr:postcode": "43015",
    "addr:street": "W Winter St",
    "iso:country": "US",
    "sg:address": "39 W Winter St",
    "sg:city": "Delaware",
    "sg:classifiers": [
      {
        "category": "Health Services",
        "subcategory": "Clinic",
        "type": "Services"
      }
    ],
    "sg:phone": "+1 740 363 5720",
    "sg:postcode": "43015",
    "sg:province": "OH",
    "sg:tags": [
      "home"
    ],
    "sg:website": "www.homeinstead.com",
    "wof:name": "Home Instead Senior Care",
    "wof:placetype": "venue"
  },
  "geometry": {"coordinates":[-83.071008,40.300269],"type":"Point"}
}
