{
  "type": "Feature",
  "properties": {
    "iso:country":"US",
    "sg:address":"24 W Main St",
    "sg:city":"Springfield",
    "sg:classifiers":[
        {
            "category":"Insurance",
            "subcategory":"Hazard Insurance",
            "type":"Services"
        }
    ],
    "sg:phone":"+1 937 323 2050",
    "sg:postcode":"45504",
    "sg:province":"OH",
    "sg:tags":[
        "bond"
    ],
    "wof:name":"Castle Bail Bonds Inc",
    "wof:placetype":"venue"
},
  "geometry": {"coordinates":[-83.81062300000001,39.924676],"type":"Point"}
}