{
  "type": "Feature",
  "properties": {
    "addr:full": "867 S Detroit Ave Toledo OH 43609",
    "addr:housenumber": "867",
    "addr:postcode": "43609",
    "addr:street": "S Detroit Ave",
    "iso:country": "US",
    "sg:address": "867 S Detroit Ave",
    "sg:city": "Toledo",
    "sg:classifiers": [
      {
        "category": "Arts \u0026 Performance",
        "subcategory": "Theater",
        "type": "Entertainment"
      }
    ],
    "sg:phone": "+1 419 389 5893",
    "sg:postcode": "43609",
    "sg:province": "OH",
    "sg:tags": [
      "clown"
    ],
    "wof:name": "Balloons \u0026 Laughs",
    "wof:placetype": "venue"
  },
  "geometry": {"coordinates":[-83.596013,41.62482],"type":"Point"}
}
