{
  "type": "Feature",
  "properties": {
    "iso:country":"US",
    "sg:address":"867 S Detroit Ave",
    "sg:city":"Toledo",
    "sg:classifiers":[
        {
            "category":"Arts & Performance",
            "subcategory":"Theater",
            "type":"Entertainment"
        }
    ],
    "sg:phone":"+1 419 389 5893",
    "sg:postcode":"43609",
    "sg:province":"OH",
    "sg:tags":[
        "clown"
    ],
    "wof:name":"Balloons & Laughs",
    "wof:placetype":"venue"
},
  "geometry": {"coordinates":[-83.596013,41.62482],"type":"Point"}
}