{
  "type": "Feature",
  "properties": {
    "addr:full": "131 S Cherry St Germantown OH 45327",
    "addr:housenumber": "131",
    "addr:postcode": "45327",
    "addr:street": "S Cherry St",
    "iso:country": "US",
    "sg:address": "131 S Cherry St",
    "sg:city": "Germantown",
    "sg:classifiers": [
      {
        "category": "Building \u0026 Trades",
        "subcategory": "Electrical",
        "type": "Services"
      }
    ],
    "sg:phone": "+1 513 320 1303",
    "sg:postcode": "45327",
    "sg:province": "OH",
    "sg:tags": [
      "electric",
      "contractor"
    ],
    "wof:name": "Leach Electrical Construction",
    "wof:placetype": "venue"
  },
  "geometry": {"coordinates":[-84.369022,39.623067],"type":"Point"}
}
