{
  "type": "Feature",
  "properties": {
    "addr:full":"405 Public Sq Troy OH 45373",
    "addr:housenumber":"405",
    "addr:postcode":"45373",
    "addr:street":"Public Sq",
    "iso:country":"US",
    "sg:address":"405 Public Sq",
    "sg:city":"Troy",
    "sg:classifiers":[
        {
            "category":"Social Services",
            "type":"Services"
        }
    ],
    "sg:phone":"+1 937 335 0209",
    "sg:postcode":"45373",
    "sg:province":"OH",
    "sg:tags":[
        "organization",
        "welfare"
    ],
    "wof:name":"CASA Gal Of Miami Cty Inc",
    "wof:placetype":"venue"
},
  "geometry": {"coordinates":[-84.20307099999999,40.039437],"type":"Point"}
}