{
  "type": "Feature",
  "properties": {
    "iso:country":"US",
    "sg:address":"6112 Acoma Dr",
    "sg:city":"Toledo",
    "sg:classifiers":[
        {
            "category":"Building & Trades",
            "subcategory":"Construction",
            "type":"Services"
        }
    ],
    "sg:phone":"+1 419 475 1900",
    "sg:postcode":"43623",
    "sg:province":"OH",
    "sg:tags":[
        "house"
    ],
    "wof:name":"Owens Remodeling Company",
    "wof:placetype":"venue"
},
  "geometry": {"coordinates":[-83.630617,41.725674],"type":"Point"}
}