{
  "type": "Feature",
  "properties": {
    "addr:full": "628 Payne Ave Akron OH 44302",
    "addr:housenumber": "628",
    "addr:postcode": "44302",
    "addr:street": "Payne Ave",
    "iso:country": "US",
    "sg:address": "628 Payne Ave",
    "sg:city": "Akron",
    "sg:classifiers": [
      {
        "category": "Professional",
        "type": "Services"
      }
    ],
    "sg:phone": "+1 330 379 9813",
    "sg:postcode": "44302",
    "sg:province": "OH",
    "wof:name": "Dcore Professional Inc",
    "wof:placetype": "venue"
  },
  "geometry": {"coordinates":[-81.53988,41.092009],"type":"Point"}
}
