{
  "type": "Feature",
  "properties": {
    "iso:country":"US",
    "sg:address":"111 W Main St",
    "sg:city":"Van Wert",
    "sg:classifiers":[
        {
            "category":"Restaurant",
            "type":"Food & Drink"
        }
    ],
    "sg:phone":"+1 419 238 0380",
    "sg:postcode":"45891",
    "sg:province":"OH",
    "sg:tags":[
        "eating"
    ],
    "wof:name":"Midtown Cafe",
    "wof:placetype":"venue"
},
  "geometry": {"coordinates":[-84.584149,40.869694],"type":"Point"}
}