{
  "type": "Feature",
  "properties": {
    "addr:full": "111 W Main St Van Wert OH 45891",
    "addr:housenumber": "111",
    "addr:postcode": "45891",
    "addr:street": "W Main St",
    "iso:country": "US",
    "sg:address": "111 W Main St",
    "sg:city": "Van Wert",
    "sg:classifiers": [
      {
        "category": "Restaurant",
        "type": "Food \u0026 Drink"
      }
    ],
    "sg:phone": "+1 419 238 0380",
    "sg:postcode": "45891",
    "sg:province": "OH",
    "sg:tags": [
      "eating"
    ],
    "wof:name": "Midtown Cafe",
    "wof:placetype": "venue"
  },
  "geometry": {"coordinates":[-84.584149,40.869694],"type":"Point"}
}
