{
  "type": "Feature",
  "properties": {
    "addr:full": "2140 Pogue Ave Cincinnati OH 45208",
    "addr:housenumber": "2140",
    "addr:postcode": "45208",
    "addr:street": "Pogue Ave",
    "iso:country": "US",
    "sg:address": "2140 Pogue Ave",
    "sg:city": "Cincinnati",
    "sg:classifiers": [
      {
        "category": "Health Services",
        "subcategory": "Nursing And Care Facility",
        "type": "Services"
      }
    ],
    "sg:phone": "+1 513 321 9294",
    "sg:postcode": "45208",
    "sg:province": "OH",
    "sg:tags": [
      "skilled"
    ],
    "wof:name": "Beechwood Home",
    "wof:placetype": "venue"
  },
  "geometry": {"coordinates":[-84.458597,39.136147],"type":"Point"}
}
