{
  "type": "Feature",
  "properties": {
    "iso:country":"US",
    "sg:address":"1363 Edison St NW",
    "sg:city":"Hartville",
    "sg:classifiers":[
        {
            "category":"Building & Trades",
            "subcategory":"Plumbing",
            "type":"Services"
        }
    ],
    "sg:phone":"+1 330 877 6511",
    "sg:postcode":"44632",
    "sg:province":"OH",
    "sg:tags":[
        "contractor"
    ],
    "wof:name":"Leroy Wagler",
    "wof:placetype":"venue"
},
  "geometry": {"coordinates":[-81.36845599999999,40.972681],"type":"Point"}
}