{
  "type": "Feature",
  "properties": {
    "addr:full": "1363 Edison St NW Hartville OH 44632",
    "addr:housenumber": "1363",
    "addr:postcode": "hartville;44632",
    "addr:street": "Edison St Nw",
    "iso:country": "US",
    "sg:address": "1363 Edison St NW",
    "sg:city": "Hartville",
    "sg:classifiers": [
      {
        "category": "Building \u0026 Trades",
        "subcategory": "Plumbing",
        "type": "Services"
      }
    ],
    "sg:phone": "+1 330 877 6511",
    "sg:postcode": "44632",
    "sg:province": "OH",
    "sg:tags": [
      "contractor"
    ],
    "wof:name": "Leroy Wagler",
    "wof:placetype": "venue"
  },
  "geometry": {"coordinates":[-81.368456,40.972681],"type":"Point"}
}
