{
  "type": "Feature",
  "properties": {
    "addr:full":"125 Schoolhouse St Wayne OH 43466",
    "addr:housenumber":"125",
    "addr:postcode":"43466",
    "addr:street":"Schoolhouse St",
    "iso:country":"US",
    "sg:address":"125 Schoolhouse St",
    "sg:city":"Wayne",
    "sg:classifiers":[
        {
            "category":"Government",
            "subcategory":"Police Station",
            "type":"Public Place"
        }
    ],
    "sg:phone":"+1 419 288 2777",
    "sg:postcode":"43466",
    "sg:province":"OH",
    "sg:tags":[
        "department"
    ],
    "wof:name":"Wayne Police Dept",
    "wof:placetype":"venue"
},
  "geometry": {"coordinates":[-83.47717900000001,41.301478],"type":"Point"}
}