{
  "type": "Feature",
  "properties": {
    "addr:full": "3075 Smith Rd Akron OH 44333",
    "addr:housenumber": "3075",
    "addr:postcode": "44333",
    "addr:street": "Smith Rd",
    "iso:country": "US",
    "sg:address": "3075 Smith Rd",
    "sg:city": "Akron",
    "sg:classifiers": [
      {
        "category": "Banks \u0026 Credit Unions",
        "subcategory": "Bank",
        "type": "Services"
      }
    ],
    "sg:phone": "+1 330 864 1640",
    "sg:postcode": "44333",
    "sg:province": "OH",
    "sg:tags": [
      "mortgage",
      "loan",
      "broker",
      "real estate"
    ],
    "wof:name": "Union National Mortgage Co",
    "wof:placetype": "venue"
  },
  "geometry": {"coordinates":[-81.620443,41.135928],"type":"Point"}
}
