{
  "type": "Feature",
  "properties": {
    "iso:country":"US",
    "sg:address":"1405 Timken Pl SW",
    "sg:city":"Canton",
    "sg:classifiers":[
        {
            "category":"Wholesale",
            "subcategory":"Machinery & Supplies",
            "type":"Manufacturing & Wholesale Goods"
        }
    ],
    "sg:phone":"+1 330 455 8925",
    "sg:postcode":"44706",
    "sg:province":"OH",
    "sg:tags":[
        "equipment",
        "industrial",
        "m",
        "mfg"
    ],
    "sg:website":"www.airpowerofohio.com",
    "wof:name":"Air Power Of Ohio",
    "wof:placetype":"venue"
},
  "geometry": {"coordinates":[-81.39026800000001,40.774681],"type":"Point"}
}