{
  "type": "Feature",
  "properties": {
    "addr:full": "1405 Timken Pl SW Canton OH 44706",
    "addr:housenumber": "1405",
    "addr:postcode": "44706",
    "addr:street": "Timken Pl Sw",
    "iso:country": "US",
    "sg:address": "1405 Timken Pl SW",
    "sg:city": "Canton",
    "sg:classifiers": [
      {
        "category": "Wholesale",
        "subcategory": "Machinery \u0026 Supplies",
        "type": "Manufacturing \u0026 Wholesale Goods"
      }
    ],
    "sg:phone": "+1 330 455 8925",
    "sg:postcode": "44706",
    "sg:province": "OH",
    "sg:tags": [
      "equipment",
      "industrial",
      "m",
      "mfg"
    ],
    "sg:website": "www.airpowerofohio.com",
    "wof:name": "Air Power Of Ohio",
    "wof:placetype": "venue"
  },
  "geometry": {"coordinates":[-81.390268,40.774681],"type":"Point"}
}
