{
  "type": "Feature",
  "properties": {
    "iso:country":"US",
    "sg:address":"2 S Main St",
    "sg:city":"Niles",
    "sg:classifiers":[
        {
            "category":"Professional",
            "subcategory":"Accounting & Tax Preparation",
            "type":"Services"
        }
    ],
    "sg:phone":"+1 330 652 2483",
    "sg:postcode":"44446",
    "sg:province":"OH",
    "sg:tags":[
        "return",
        "filing"
    ],
    "wof:name":"Vinions Tax & Books",
    "wof:placetype":"venue"
},
  "geometry": {"coordinates":[-80.765245,41.179102],"type":"Point"}
}