{
  "type": "Feature",
  "properties": {
    "addr:full": "8479 Co Rd 153 East Liberty OH 43319",
    "addr:housenumber": "8479",
    "addr:postcode": "43319",
    "addr:street": "Co Rd 153",
    "iso:country": "US",
    "sg:address": "8479 Co Rd 153",
    "sg:city": "East Liberty",
    "sg:classifiers": [
      {
        "category": "Real Estate",
        "subcategory": "Developer",
        "type": "Services"
      },
      {
        "category": "Real Estate",
        "subcategory": "Real Estate Agent",
        "type": "Services"
      }
    ],
    "sg:phone": "+1 937 666 5545",
    "sg:postcode": "43319",
    "sg:province": "OH",
    "sg:tags": [
      "consultant"
    ],
    "wof:name": "Jeffrey J Hall Co",
    "wof:placetype": "venue"
  },
  "geometry": {"coordinates":[-83.616415,40.3081],"type":"Point"}
}
