{
  "type": "Feature",
  "properties": {
    "iso:country":"US",
    "sg:address":"8560 Canter St NW",
    "sg:city":"Massillon",
    "sg:classifiers":[
        {
            "category":"Building & Trades",
            "subcategory":"Construction",
            "type":"Services"
        }
    ],
    "sg:phone":"+1 330 834 0800",
    "sg:postcode":"44646",
    "sg:province":"OH",
    "sg:tags":[
        "home",
        "builder"
    ],
    "wof:name":"Render Construction",
    "wof:placetype":"venue"
},
  "geometry": {"coordinates":[-81.508844,40.857081],"type":"Point"}
}