{
  "type": "Feature",
  "properties": {
    "iso:country":"US",
    "sg:address":"8603 Chardon Rd",
    "sg:city":"Kirtland",
    "sg:classifiers":[
        {
            "category":"Building & Trades",
            "subcategory":"Construction",
            "type":"Services"
        }
    ],
    "sg:phone":"+1 440 256 1486",
    "sg:postcode":"44094",
    "sg:province":"OH",
    "sg:tags":[
        "house",
        "general",
        "contractor"
    ],
    "wof:name":"Aristotile Demarco Constr",
    "wof:placetype":"venue"
},
  "geometry": {"coordinates":[-81.344598,41.583816],"type":"Point"}
}