{
  "type": "Feature",
  "properties": {
    "iso:country":"US",
    "sg:address":"1702 Empire Rd",
    "sg:city":"Wickliffe",
    "sg:classifiers":[
        {
            "category":"Building & Trades",
            "subcategory":"Plumbing",
            "type":"Services"
        }
    ],
    "sg:phone":"+1 440 951 0442",
    "sg:postcode":"44092",
    "sg:province":"OH",
    "sg:tags":[
        "air",
        "heating",
        "conditioning",
        "contractor"
    ],
    "wof:name":"Overholt Heating & Air Cond",
    "wof:placetype":"venue"
},
  "geometry": {"coordinates":[-81.45324100000001,41.609345],"type":"Point"}
}