{
  "type": "Feature",
  "properties": {
    "addr:full": "1702 Empire Rd Wickliffe OH 44092",
    "addr:housenumber": "1702",
    "addr:postcode": "44092",
    "addr:street": "Empire Rd",
    "iso:country": "US",
    "sg:address": "1702 Empire Rd",
    "sg:city": "Wickliffe",
    "sg:classifiers": [
      {
        "category": "Building \u0026 Trades",
        "subcategory": "Plumbing",
        "type": "Services"
      }
    ],
    "sg:phone": "+1 440 951 0442",
    "sg:postcode": "44092",
    "sg:province": "OH",
    "sg:tags": [
      "air",
      "heating",
      "conditioning",
      "contractor"
    ],
    "wof:name": "Overholt Heating \u0026 Air Cond",
    "wof:placetype": "venue"
  },
  "geometry": {"coordinates":[-81.453241,41.609345],"type":"Point"}
}
