{
  "type": "Feature",
  "properties": {
    "addr:full": "8384 Twp Rd 56 Lexington OH 44904",
    "addr:housenumber": "56",
    "addr:postcode": "8384;44904",
    "addr:street": "Twp Rd",
    "iso:country": "US",
    "sg:address": "8384 Twp Rd 56",
    "sg:city": "Lexington",
    "sg:classifiers": [
      {
        "category": "Building \u0026 Trades",
        "subcategory": "Construction",
        "type": "Services"
      }
    ],
    "sg:phone": "+1 419 362 1303",
    "sg:postcode": "44904",
    "sg:province": "OH",
    "sg:tags": [
      "excavating",
      "contractor"
    ],
    "wof:name": "Dirt Works",
    "wof:placetype": "venue"
  },
  "geometry": {"coordinates":[-82.708882,40.656424],"type":"Point"}
}
