{
  "type": "Feature",
  "properties": {
    "iso:country":"US",
    "sg:address":"8384 Twp Rd 56",
    "sg:city":"Lexington",
    "sg:classifiers":[
        {
            "category":"Building & Trades",
            "subcategory":"Construction",
            "type":"Services"
        }
    ],
    "sg:phone":"+1 419 362 1303",
    "sg:postcode":"44904",
    "sg:province":"OH",
    "sg:tags":[
        "excavating",
        "contractor"
    ],
    "wof:name":"Dirt Works",
    "wof:placetype":"venue"
},
  "geometry": {"coordinates":[-82.708882,40.656424],"type":"Point"}
}