{
  "type": "Feature",
  "properties": {
    "addr:full":"2430 Youngstown Rd SE Warren OH 44484",
    "addr:housenumber":"2430",
    "addr:postcode":"44484",
    "addr:street":"Youngstown Rd Se",
    "iso:country":"US",
    "sg:address":"2430 Youngstown Rd SE",
    "sg:city":"Warren",
    "sg:classifiers":[
        {
            "category":"Food & Beverages",
            "subcategory":"Groceries & Convenience Stores",
            "type":"Retail Goods"
        }
    ],
    "sg:phone":"+1 330 369 4635",
    "sg:postcode":"44484",
    "sg:province":"OH",
    "sg:tags":[
        "grocer"
    ],
    "wof:name":"J & B Bi-Rite",
    "wof:placetype":"venue"
},
  "geometry": {"coordinates":[-80.789873,41.225099],"type":"Point"}
}