{
  "type": "Feature",
  "properties": {
    "addr:full": "2836 US Hwy 52 Felicity OH 45120",
    "addr:housenumber": "2836",
    "addr:postcode": "45120",
    "addr:street": "Us Hwy 52",
    "iso:country": "US",
    "sg:address": "2836 US Hwy 52",
    "sg:city": "Felicity",
    "sg:classifiers": [
      {
        "category": "Food \u0026 Beverages",
        "subcategory": "Groceries \u0026 Convenience Stores",
        "type": "Retail Goods"
      }
    ],
    "sg:phone": "+1 513 876 2886",
    "sg:postcode": "45120",
    "sg:province": "OH",
    "wof:name": "M \u0026 M Discount Grocery",
    "wof:placetype": "venue"
  },
  "geometry": {"coordinates":[-84.133013,38.794026],"type":"Point"}
}
