{
  "type": "Feature",
  "properties": {
    "addr:full":"6021 Madison Rd Cincinnati OH 45227",
    "addr:housenumber":"6021",
    "addr:postcode":"45227",
    "addr:street":"Madison Rd",
    "iso:country":"US",
    "sg:address":"6021 Madison Rd",
    "sg:city":"Cincinnati",
    "sg:classifiers":[
        {
            "category":"Retail",
            "subcategory":"Auto Repair",
            "type":"Services"
        }
    ],
    "sg:phone":"+1 513 272 0777",
    "sg:postcode":"45227",
    "sg:province":"OH",
    "sg:tags":[
        "repairing",
        "automobile"
    ],
    "wof:name":"Spectrum Automotive Svc",
    "wof:placetype":"venue"
},
  "geometry": {"coordinates":[-84.390913,39.160383],"type":"Point"}
}