{
  "type": "Feature",
  "properties": {
    "addr:full":"8006 Newton Falls Rd Ravenna OH 44266",
    "addr:housenumber":"8006",
    "addr:postcode":"44266",
    "addr:street":"Newton Falls Rd",
    "iso:country":"US",
    "sg:address":"8006 Newton Falls Rd",
    "sg:city":"Ravenna",
    "sg:classifiers":[
        {
            "category":"Retail",
            "subcategory":"Animal Services",
            "type":"Services"
        }
    ],
    "sg:phone":"+1 330 297 7545",
    "sg:postcode":"44266",
    "sg:province":"OH",
    "sg:tags":[
        "pet",
        "grooming",
        "washing"
    ],
    "wof:name":"Shaggy Doo Dog Grooming",
    "wof:placetype":"venue"
},
  "geometry": {"coordinates":[-81.104004,41.162796],"type":"Point"}
}