{
  "type": "Feature",
  "properties": {
    "addr:full":"9290 Lake Shore Blvd Mentor OH 44060",
    "addr:housenumber":"9290",
    "addr:postcode":"44060",
    "addr:street":"Lake Shore Blvd",
    "iso:country":"US",
    "sg:address":"9290 Lake Shore Blvd",
    "sg:city":"Mentor",
    "sg:classifiers":[
        {
            "category":"Organizations",
            "subcategory":"Religious Organization",
            "type":"Services"
        }
    ],
    "sg:phone":"+1 440 257 6419",
    "sg:postcode":"44060",
    "sg:province":"OH",
    "sg:tags":[
        "church"
    ],
    "wof:name":"North Mentor Centenary United",
    "wof:placetype":"venue"
},
  "geometry": {"coordinates":[-81.302432,41.727044],"type":"Point"}
}