{
  "type": "Feature",
  "properties": {
    "addr:full":"101 Front St Portsmouth OH 45662",
    "addr:housenumber":"101",
    "addr:postcode":"45662",
    "addr:street":"Front St",
    "iso:country":"US",
    "sg:address":"101 Front St",
    "sg:city":"Portsmouth",
    "sg:classifiers":[
        {
            "category":"Recreation",
            "type":"Entertainment"
        }
    ],
    "sg:phone":"+1 740 353 0972",
    "sg:postcode":"45662",
    "sg:province":"OH",
    "sg:tags":[
        "club",
        "membership"
    ],
    "wof:name":"Ports Mtr Cycle Club",
    "wof:placetype":"venue"
},
  "geometry": {"coordinates":[-83.010837,38.730903],"type":"Point"}
}