{
  "type": "Feature",
  "properties": {
    "iso:country":"US",
    "sg:address":"468 Geiger St",
    "sg:city":"Berea",
    "sg:classifiers":[
        {
            "category":"Manufacturing",
            "subcategory":"Rubber & Plastics",
            "type":"Manufacturing & Wholesale Goods"
        }
    ],
    "sg:phone":"+1 440 234 4000",
    "sg:postcode":"44017",
    "sg:province":"OH",
    "sg:website":"www.jacomfg.com",
    "wof:name":"Jaco Manufacturing",
    "wof:placetype":"venue"
},
  "geometry": {"coordinates":[-81.869658,41.373138],"type":"Point"}
}