{
  "type": "Feature",
  "properties": {
    "iso:country":"US",
    "sg:address":"517 W Exchange St",
    "sg:city":"Akron",
    "sg:classifiers":[
        {
            "category":"Social Services",
            "type":"Services"
        }
    ],
    "sg:phone":"+1 330 253 0011",
    "sg:postcode":"44302",
    "sg:province":"OH",
    "sg:tags":[
        "organization",
        "welfare"
    ],
    "wof:name":"Gennesaret Inc",
    "wof:placetype":"venue"
},
  "geometry": {"coordinates":[-81.536351,41.085216],"type":"Point"}
}