{
  "type": "Feature",
  "properties": {
    "iso:country":"US",
    "sg:address":"688 E Center St",
    "sg:city":"Marion",
    "sg:classifiers":[
        {
            "category":"Shopping",
            "type":"Retail Goods"
        }
    ],
    "sg:phone":"+1 740 382 3600",
    "sg:postcode":"43302",
    "sg:province":"OH",
    "sg:tags":[
        "candle"
    ],
    "wof:name":"Candle Shop",
    "wof:placetype":"venue"
},
  "geometry": {"coordinates":[-83.113687,40.589297],"type":"Point"}
}