{
  "type": "Feature",
  "properties": {
    "iso:country":"US",
    "sg:address":"6354 Sour Run Rd",
    "sg:city":"Wellston",
    "sg:classifiers":[
        {
            "category":"Retail",
            "subcategory":"Auto Repair",
            "type":"Services"
        }
    ],
    "sg:phone":"+1 740 286 2213",
    "sg:postcode":"45692",
    "sg:province":"OH",
    "sg:tags":[
        "repairing",
        "automobile"
    ],
    "wof:name":"Larry Baker's Automotive",
    "wof:placetype":"venue"
},
  "geometry": {"coordinates":[-82.619996,39.121914],"type":"Point"}
}