{
  "type": "Feature",
  "properties": {
    "addr:full": "1951 Bellefontaine Rd Lima OH 45804",
    "addr:housenumber": "1951",
    "addr:postcode": "45804",
    "addr:street": "Bellefontaine Rd",
    "iso:country": "US",
    "sg:address": "1951 Bellefontaine Rd",
    "sg:city": "Lima",
    "sg:classifiers": [
      {
        "category": "Health Services",
        "subcategory": "Medical Lab",
        "type": "Services"
      }
    ],
    "sg:phone": "+1 419 228 6680",
    "sg:postcode": "45804",
    "sg:province": "OH",
    "sg:tags": [
      "laboratory",
      "dental"
    ],
    "wof:name": "Affordble Dntres Dntl Labs Inc",
    "wof:placetype": "venue"
  },
  "geometry": {"coordinates":[-84.066744,40.727232],"type":"Point"}
}
