{
  "type": "Feature",
  "properties": {
    "addr:full":"834 Huron Rd E Cleveland OH 44115",
    "addr:housenumber":"834",
    "addr:postcode":"44115",
    "addr:street":"Huron Rd E",
    "iso:country":"US",
    "sg:address":"834 Huron Rd E",
    "sg:city":"Cleveland",
    "sg:classifiers":[
        {
            "category":"Bars & Pubs",
            "type":"Food & Drink"
        }
    ],
    "sg:phone":"+1 216 771 3723",
    "sg:postcode":"44115",
    "sg:province":"OH",
    "sg:tags":[
        "drinking"
    ],
    "wof:name":"Clevelander Bar & Grill",
    "wof:placetype":"venue"
},
  "geometry": {"coordinates":[-81.686324,41.49849],"type":"Point"}
}