{
  "type": "Feature",
  "properties": {
    "addr:full":"3519 Eyrich Rd Cincinnati OH 45248",
    "addr:housenumber":"3519",
    "addr:postcode":"45248",
    "addr:street":"Eyrich Rd",
    "iso:country":"US",
    "sg:address":"3519 Eyrich Rd",
    "sg:city":"Cincinnati",
    "sg:classifiers":[
        {
            "category":"Building & Trades",
            "subcategory":"Electrical",
            "type":"Services"
        }
    ],
    "sg:phone":"+1 513 574 2134",
    "sg:postcode":"45248",
    "sg:province":"OH",
    "sg:tags":[
        "electrical",
        "contractor"
    ],
    "wof:name":"Brian Kist Electric",
    "wof:placetype":"venue"
},
  "geometry": {"coordinates":[-84.642686,39.15335],"type":"Point"}
}