{
  "type": "Feature",
  "properties": {
    "addr:full": "8375 Davis Rd Celina OH 45822",
    "addr:housenumber": "8375",
    "addr:postcode": "45822",
    "addr:street": "Davis Rd",
    "iso:country": "US",
    "sg:address": "8375 Davis Rd",
    "sg:city": "Celina",
    "sg:classifiers": [
      {
        "category": "Building \u0026 Trades",
        "subcategory": "Construction",
        "type": "Services"
      }
    ],
    "sg:phone": "+1 419 586 3193",
    "sg:postcode": "45822",
    "sg:province": "OH",
    "sg:tags": [
      "house"
    ],
    "wof:name": "Carter Construction",
    "wof:placetype": "venue"
  },
  "geometry": {"coordinates":[-84.479655,40.618944],"type":"Point"}
}
