{
  "type": "Feature",
  "properties": {
    "addr:full": "644 N Union St Lima OH 45801",
    "addr:housenumber": "644",
    "addr:postcode": "45801",
    "addr:street": "N Union St",
    "iso:country": "US",
    "sg:address": "644 N Union St",
    "sg:city": "Lima",
    "sg:classifiers": [
      {
        "category": "Retail",
        "subcategory": "Auto Repair",
        "type": "Services"
      }
    ],
    "sg:phone": "+1 419 229 2313",
    "sg:postcode": "45801",
    "sg:province": "OH",
    "sg:tags": [
      "body",
      "automobile",
      "painting"
    ],
    "wof:name": "H \u0026 H Auto Body",
    "wof:placetype": "venue"
  },
  "geometry": {"coordinates":[-84.103164,40.748138],"type":"Point"}
}
