{
  "type": "Feature",
  "properties": {
    "iso:country":"US",
    "sg:address":"644 N Union St",
    "sg:city":"Lima",
    "sg:classifiers":[
        {
            "category":"Retail",
            "subcategory":"Auto Repair",
            "type":"Services"
        }
    ],
    "sg:phone":"+1 419 229 2313",
    "sg:postcode":"45801",
    "sg:province":"OH",
    "sg:tags":[
        "body",
        "automobile",
        "painting"
    ],
    "wof:name":"H & H Auto Body",
    "wof:placetype":"venue"
},
  "geometry": {"coordinates":[-84.10316400000001,40.748138],"type":"Point"}
}