{
  "type": "Feature",
  "properties": {
    "iso:country":"US",
    "sg:address":"360 W Prospect St",
    "sg:city":"Painesville",
    "sg:classifiers":[
        {
            "category":"Wholesale",
            "subcategory":"Construction Materials",
            "type":"Manufacturing & Wholesale Goods"
        }
    ],
    "sg:phone":"+1 440 639 2514",
    "sg:postcode":"44077",
    "sg:province":"OH",
    "wof:name":"Bomark Supply Inc",
    "wof:placetype":"venue"
},
  "geometry": {"coordinates":[-81.254477,41.725593],"type":"Point"}
}