{
  "type": "Feature",
  "properties": {
    "addr:full": "360 W Prospect St Painesville OH 44077",
    "addr:housenumber": "360",
    "addr:postcode": "44077",
    "addr:street": "W Prospect St",
    "iso:country": "US",
    "sg:address": "360 W Prospect St",
    "sg:city": "Painesville",
    "sg:classifiers": [
      {
        "category": "Wholesale",
        "subcategory": "Construction Materials",
        "type": "Manufacturing \u0026 Wholesale Goods"
      }
    ],
    "sg:phone": "+1 440 639 2514",
    "sg:postcode": "44077",
    "sg:province": "OH",
    "wof:name": "Bomark Supply Inc",
    "wof:placetype": "venue"
  },
  "geometry": {"coordinates":[-81.254477,41.725593],"type":"Point"}
}
