{
  "type": "Feature",
  "properties": {
    "addr:full":"1785 S Lincoln Ave Salem OH 44460",
    "addr:housenumber":"1785",
    "addr:postcode":"44460",
    "addr:street":"S Lincoln Ave",
    "iso:country":"US",
    "sg:address":"1785 S Lincoln Ave",
    "sg:city":"Salem",
    "sg:classifiers":[
        {
            "category":"Home & Garden",
            "subcategory":"Household Appliances",
            "type":"Retail Goods"
        }
    ],
    "sg:phone":"+1 330 332 1137",
    "sg:postcode":"44460",
    "sg:province":"OH",
    "wof:name":"B & L Electronics",
    "wof:placetype":"venue"
},
  "geometry": {"coordinates":[-80.842465,40.880413],"type":"Point"}
}