{
  "type": "Feature",
  "properties": {
    "addr:full":"3749 Crescent Hill Rd Springfield OH 45502",
    "addr:housenumber":"3749",
    "addr:postcode":"45502",
    "addr:street":"Crescent Hill Rd",
    "iso:country":"US",
    "sg:address":"3749 Crescent Hill Rd",
    "sg:city":"Springfield",
    "sg:classifiers":[
        {
            "category":"Building & Trades",
            "subcategory":"Construction",
            "type":"Services"
        }
    ],
    "sg:phone":"+1 937 964 0113",
    "sg:postcode":"45502",
    "sg:province":"OH",
    "sg:tags":[
        "repairing",
        "remodeling",
        "contractor"
    ],
    "wof:name":"GSI Inc",
    "wof:placetype":"venue"
},
  "geometry": {"coordinates":[-83.87222199999999,40.008337],"type":"Point"}
}