{
  "type": "Feature",
  "properties": {
    "addr:full":"193 E Main St Chillicothe OH 45601",
    "addr:housenumber":"193",
    "addr:postcode":"45601",
    "addr:street":"E Main St",
    "iso:country":"US",
    "sg:address":"193 E Main St",
    "sg:city":"Chillicothe",
    "sg:classifiers":[
        {
            "category":"Shopping",
            "subcategory":"Bicycles & Sporting Goods",
            "type":"Retail Goods"
        }
    ],
    "sg:phone":"+1 740 775 0606",
    "sg:postcode":"45601",
    "sg:province":"OH",
    "wof:name":"Sonnie Sports Plus",
    "wof:placetype":"venue"
},
  "geometry": {"coordinates":[-82.979007,39.33366],"type":"Point"}
}