{
  "type": "Feature",
  "properties": {
    "addr:full":"38721 Mentor Ave Willoughby OH 44094",
    "addr:postcode":"38721;44094",
    "addr:street":"Mentor Ave",
    "iso:country":"US",
    "sg:address":"38721 Mentor Ave",
    "sg:city":"Willoughby",
    "sg:classifiers":[
        {
            "category":"Utilities",
            "subcategory":"Telephone",
            "type":"Services"
        }
    ],
    "sg:phone":"+1 440 942 1555",
    "sg:postcode":"44094",
    "sg:province":"OH",
    "sg:tags":[
        "telecommunication"
    ],
    "sg:website":"www.intermessage.com",
    "wof:name":"Intermessage Communications",
    "wof:placetype":"venue"
},
  "geometry": {"coordinates":[-81.39255,41.645076],"type":"Point"}
}