{
  "type": "Feature",
  "properties": {
    "iso:country":"US",
    "sg:address":"14150 Mangen Rd",
    "sg:city":"Yorkshire",
    "sg:classifiers":[
        {
            "category":"Shopping",
            "subcategory":"Gifts & Souvenirs",
            "type":"Retail Goods"
        }
    ],
    "sg:phone":"+1 419 336 7292",
    "sg:postcode":"45388",
    "sg:province":"OH",
    "wof:name":"Celtic Cross",
    "wof:placetype":"venue"
},
  "geometry": {"coordinates":[-84.534342,40.32626],"type":"Point"}
}