{
  "type": "Feature",
  "properties": {
    "addr:full": "14150 Mangen Rd Yorkshire OH 45388",
    "addr:postcode": "14150;45388",
    "addr:street": "Mangen Rd",
    "iso:country": "US",
    "sg:address": "14150 Mangen Rd",
    "sg:city": "Yorkshire",
    "sg:classifiers": [
      {
        "category": "Shopping",
        "subcategory": "Gifts \u0026 Souvenirs",
        "type": "Retail Goods"
      }
    ],
    "sg:phone": "+1 419 336 7292",
    "sg:postcode": "45388",
    "sg:province": "OH",
    "wof:name": "Celtic Cross",
    "wof:placetype": "venue"
  },
  "geometry": {"coordinates":[-84.534342,40.32626],"type":"Point"}
}
