{
  "type": "Feature",
  "properties": {
    "iso:country":"US",
    "sg:address":"3694 Troon Dr",
    "sg:city":"Uniontown",
    "sg:classifiers":[
        {
            "category":"Building & Trades",
            "subcategory":"Construction",
            "type":"Services"
        }
    ],
    "sg:phone":"+1 330 699 0227",
    "sg:postcode":"44685",
    "sg:province":"OH",
    "sg:tags":[
        "house",
        "concrete",
        "contractor"
    ],
    "wof:name":"Frank Kramanak Building Contr",
    "wof:placetype":"venue"
},
  "geometry": {"coordinates":[-81.452491,40.963807],"type":"Point"}
}