{
  "type": "Feature",
  "properties": {
    "iso:country":"US",
    "sg:address":"5294 Sebring Warner Rd",
    "sg:city":"Greenville",
    "sg:classifiers":[
        {
            "category":"Building & Trades",
            "subcategory":"Construction",
            "type":"Services"
        }
    ],
    "sg:phone":"+1 937 548 4345",
    "sg:postcode":"45331",
    "sg:province":"OH",
    "sg:tags":[
        "farm",
        "general",
        "commercial",
        "contractor"
    ],
    "wof:name":"Nu Way Builders",
    "wof:placetype":"venue"
},
  "geometry": {"coordinates":[-84.60720999999999,40.077832],"type":"Point"}
}