{
  "type": "Feature",
  "properties": {
    "addr:full":"2301 13th St NW Canton OH 44708",
    "addr:housenumber":"2301",
    "addr:postcode":"44708",
    "addr:street":"13Th St Nw",
    "iso:country":"US",
    "sg:address":"2301 13th St NW",
    "sg:city":"Canton",
    "sg:classifiers":[
        {
            "category":"Organizations",
            "subcategory":"Community Association",
            "type":"Services"
        }
    ],
    "sg:phone":"+1 330 580 4272",
    "sg:postcode":"44708",
    "sg:province":"OH",
    "sg:website":"www.scouting.org",
    "wof:name":"Boy Scouts Of America",
    "wof:placetype":"venue"
},
  "geometry": {"coordinates":[-81.399869,40.811586],"type":"Point"}
}