{
  "type": "Feature",
  "properties": {
    "iso:country":"US",
    "sg:address":"4565 Dressler Rd NW",
    "sg:city":"Canton",
    "sg:classifiers":[
        {
            "category":"Professional",
            "subcategory":"Computer Services",
            "type":"Services"
        }
    ],
    "sg:phone":"+1 330 499 0692",
    "sg:postcode":"44720",
    "sg:province":"OH",
    "sg:tags":[
        "application",
        "hosting",
        "internet"
    ],
    "wof:name":"Mapstrategies",
    "wof:placetype":"venue"
},
  "geometry": {"coordinates":[-81.434518,40.847448],"type":"Point"}
}