{
  "type": "Feature",
  "properties": {
    "addr:full":"815 Greenler St Defiance OH 43512",
    "addr:housenumber":"815",
    "addr:postcode":"43512",
    "addr:street":"Greenler St",
    "iso:country":"US",
    "sg:address":"815 Greenler St",
    "sg:city":"Defiance",
    "sg:classifiers":[
        {
            "category":"Real Estate",
            "subcategory":"Real Estate Operator",
            "type":"Services"
        }
    ],
    "sg:phone":"+1 419 782 7421",
    "sg:postcode":"43512",
    "sg:province":"OH",
    "sg:tags":[
        "building",
        "nonresidential"
    ],
    "wof:name":"Lankenau Properties I Ltd",
    "wof:placetype":"venue"
},
  "geometry": {"coordinates":[-84.35001699999999,41.27748],"type":"Point"}
}