{
  "type": "Feature",
  "properties": {
    "addr:full":"904 Swann Beatty Rd Camden OH 45311",
    "addr:housenumber":"904",
    "addr:postcode":"45311",
    "addr:street":"Swann Beatty Rd",
    "iso:country":"US",
    "sg:address":"904 Swann Beatty Rd",
    "sg:city":"Camden",
    "sg:classifiers":[
        {
            "category":"Food & Beverages",
            "subcategory":"Specialty",
            "type":"Retail Goods"
        },
        {
            "category":"Wholesale",
            "subcategory":"Groceries",
            "type":"Manufacturing & Wholesale Goods"
        }
    ],
    "sg:phone":"+1 937 452 7452",
    "sg:postcode":"45311",
    "sg:province":"OH",
    "sg:tags":[
        "health",
        "diet"
    ],
    "wof:name":"Shaklee Distributors",
    "wof:placetype":"venue"
},
  "geometry": {"coordinates":[-84.66175,39.599757],"type":"Point"}
}