{
  "type": "Feature",
  "properties": {
    "iso:country":"US",
    "sg:address":"8195 Tyler Blvd",
    "sg:city":"Mentor",
    "sg:classifiers":[
        {
            "category":"Retail",
            "subcategory":"Auto Repair",
            "type":"Services"
        }
    ],
    "sg:phone":"+1 440 974 0670",
    "sg:postcode":"44060",
    "sg:province":"OH",
    "sg:tags":[
        "body",
        "automobile",
        "painting"
    ],
    "wof:name":"American Collision & Custom",
    "wof:placetype":"venue"
},
  "geometry": {"coordinates":[-81.345427,41.682929],"type":"Point"}
}