{
  "type": "Feature",
  "properties": {
    "addr:full":"5618 US Hwy 20A Delta OH 43515",
    "addr:housenumber":"5618;20a",
    "addr:postcode":"43515",
    "addr:street":"Us Hwy",
    "iso:country":"US",
    "sg:address":"5618 US Hwy 20A",
    "sg:city":"Delta",
    "sg:classifiers":[
        {
            "category":"Home & Garden",
            "subcategory":"Mobile Homes",
            "type":"Retail Goods"
        }
    ],
    "sg:phone":"+1 419 822 4930",
    "sg:postcode":"43515",
    "sg:province":"OH",
    "wof:name":"Countryside Homes Inc",
    "wof:placetype":"venue"
},
  "geometry": {"coordinates":[-83.96959699999999,41.574214],"type":"Point"}
}