{
  "type": "Feature",
  "properties": {
    "addr:full": "5333 Monroe St Ste 31 Toledo OH 43623",
    "addr:housenumber": "5333",
    "addr:postcode": "43623",
    "addr:street": "Monroe St Ste 31",
    "iso:country": "US",
    "sg:address": "5333 Monroe St Ste 31",
    "sg:city": "Toledo",
    "sg:classifiers": [
      {
        "category": "Bars \u0026 Pubs",
        "type": "Food \u0026 Drink"
      }
    ],
    "sg:phone": "+1 419 841 7999",
    "sg:postcode": "43623",
    "sg:province": "OH",
    "wof:name": "Bier Stube",
    "wof:placetype": "venue"
  },
  "geometry": {"coordinates":[-83.656779,41.703337],"type":"Point"}
}
