{
  "type": "Feature",
  "properties": {
    "addr:full": "2800 Hayes Ave Bldg A Sandusky OH 44870",
    "addr:housenumber": "2800",
    "addr:postcode": "44870",
    "addr:street": "Hayes Ave Bldg A",
    "iso:country": "US",
    "sg:address": "2800 Hayes Ave Bldg A",
    "sg:city": "Sandusky",
    "sg:classifiers": [
      {
        "category": "Health Services",
        "subcategory": "Doctor",
        "type": "Services"
      }
    ],
    "sg:phone": "+1 419 626 7246",
    "sg:postcode": "44870",
    "sg:province": "OH",
    "wof:name": "Key Pain Treatment Center",
    "wof:placetype": "venue"
  },
  "geometry": {"coordinates":[-82.718102,41.425999],"type":"Point"}
}
