{
  "type": "Feature",
  "properties": {
    "iso:country":"US",
    "sg:address":"5410 Dixie Hwy",
    "sg:city":"Fairfield",
    "sg:classifiers":[
        {
            "category":"Autos & Motor Vehicles",
            "subcategory":"Automobile Sales",
            "type":"Retail Goods"
        }
    ],
    "sg:phone":"+1 513 939 3320",
    "sg:postcode":"45014",
    "sg:province":"OH",
    "sg:tags":[
        "used"
    ],
    "wof:name":"Hertz",
    "wof:placetype":"venue"
},
  "geometry": {"coordinates":[-84.524001,39.333931],"type":"Point"}
}