{
  "type": "Feature",
  "properties": {
    "addr:full": "8060 Montgomery Rd Cincinnati OH 45236",
    "addr:housenumber": "8060",
    "addr:postcode": "45236",
    "addr:street": "Montgomery Rd",
    "iso:country": "US",
    "sg:address": "8060 Montgomery Rd",
    "sg:city": "Cincinnati",
    "sg:classifiers": [
      {
        "category": "Health Services",
        "subcategory": "Doctor",
        "type": "Services"
      }
    ],
    "sg:phone": "+1 513 891 3664",
    "sg:postcode": "45236",
    "sg:province": "OH",
    "sg:tags": [
      "medical"
    ],
    "wof:name": "Primary Care Physicians",
    "wof:placetype": "venue"
  },
  "geometry": {"coordinates":[-84.371242,39.202328],"type":"Point"}
}
