{
  "type": "Feature",
  "properties": {
    "addr:full": "6601 Huntley Rd Columbus OH 43229",
    "addr:housenumber": "6601",
    "addr:postcode": "43229",
    "addr:street": "Huntley Rd",
    "iso:country": "US",
    "sg:address": "6601 Huntley Rd",
    "sg:city": "Columbus",
    "sg:classifiers": [
      {
        "category": "Wholesale",
        "subcategory": "Machinery \u0026 Supplies",
        "type": "Manufacturing \u0026 Wholesale Goods"
      }
    ],
    "sg:phone": "+1 614 847 0042",
    "sg:postcode": "43229",
    "sg:province": "OH",
    "sg:tags": [
      "equipment",
      "layer",
      "carpet"
    ],
    "wof:name": "Tri-State Carpet Supplies Inc",
    "wof:placetype": "venue"
  },
  "geometry": {"coordinates":[-82.998423,40.089915],"type":"Point"}
}
