{
  "type": "Feature",
  "properties": {
    "addr:full":"2450 Kipling Ave Cincinnati OH 45239",
    "addr:housenumber":"2450",
    "addr:postcode":"45239",
    "addr:street":"Kipling Ave",
    "iso:country":"US",
    "sg:address":"2450 Kipling Ave",
    "sg:city":"Cincinnati",
    "sg:classifiers":[
        {
            "category":"Health Services",
            "subcategory":"Doctor",
            "type":"Services"
        }
    ],
    "sg:phone":"+1 513 541 5522",
    "sg:postcode":"45239",
    "sg:province":"OH",
    "sg:tags":[
        "medical"
    ],
    "wof:name":"McTighe Martin L",
    "wof:placetype":"venue"
},
  "geometry": {"coordinates":[-84.573294,39.201661],"type":"Point"}
}