{
  "type": "Feature",
  "properties": {
    "addr:full":"916 Trenton St Toronto OH 43964",
    "addr:housenumber":"916",
    "addr:postcode":"43964",
    "addr:street":"Trenton St",
    "iso:country":"US",
    "sg:address":"916 Trenton St",
    "sg:city":"Toronto",
    "sg:classifiers":[
        {
            "category":"Professional",
            "type":"Services"
        }
    ],
    "sg:phone":"+1 740 537 3146",
    "sg:postcode":"43964",
    "sg:province":"OH",
    "wof:name":"Terra Paris",
    "wof:placetype":"venue"
},
  "geometry": {"coordinates":[-80.61090799999999,40.459904],"type":"Point"}
}