{
  "type": "Feature",
  "properties": {
    "iso:country":"US",
    "sg:address":"1134 Partridge Dr",
    "sg:city":"Wadsworth",
    "sg:classifiers":[
        {
            "category":"Shopping",
            "subcategory":"Computers & Home Electronics",
            "type":"Retail Goods"
        }
    ],
    "sg:phone":"+1 330 335 7228",
    "sg:postcode":"44281",
    "sg:province":"OH",
    "wof:name":"V S Strategies",
    "wof:placetype":"venue"
},
  "geometry": {"coordinates":[-81.740578,41.052733],"type":"Point"}
}