{
  "type": "Feature",
  "properties": {
    "addr:full": "1134 Partridge Dr Wadsworth OH 44281",
    "addr:housenumber": "1134",
    "addr:postcode": "44281",
    "addr:street": "Partridge Dr",
    "iso:country": "US",
    "sg:address": "1134 Partridge Dr",
    "sg:city": "Wadsworth",
    "sg:classifiers": [
      {
        "category": "Shopping",
        "subcategory": "Computers \u0026 Home Electronics",
        "type": "Retail Goods"
      }
    ],
    "sg:phone": "+1 330 335 7228",
    "sg:postcode": "44281",
    "sg:province": "OH",
    "wof:name": "V S Strategies",
    "wof:placetype": "venue"
  },
  "geometry": {"coordinates":[-81.740578,41.052733],"type":"Point"}
}
