{
  "type": "Feature",
  "properties": {
    "addr:full":"7777 Washington Park Dr Dayton OH 45459",
    "addr:housenumber":"7777",
    "addr:postcode":"45459",
    "addr:street":"Washington Park Dr",
    "iso:country":"US",
    "sg:address":"7777 Washington Park Dr",
    "sg:city":"Dayton",
    "sg:classifiers":[
        {
            "category":"Professional",
            "subcategory":"Employment Agencies",
            "type":"Services"
        }
    ],
    "sg:phone":"+1 937 434 2707",
    "sg:postcode":"45459",
    "sg:province":"OH",
    "wof:name":"Right Associates",
    "wof:placetype":"venue"
},
  "geometry": {"coordinates":[-84.20799100000001,39.637355],"type":"Point"}
}