{
  "type": "Feature",
  "properties": {
    "addr:full": "3666 Carnegie Ave Cleveland OH 44115",
    "addr:housenumber": "3666",
    "addr:postcode": "44115",
    "addr:street": "Carnegie Ave",
    "iso:country": "US",
    "sg:address": "3666 Carnegie Ave",
    "sg:city": "Cleveland",
    "sg:classifiers": [
      {
        "category": "Organizations",
        "subcategory": "Labor Organization",
        "type": "Services"
      }
    ],
    "sg:phone": "+1 216 391 1645",
    "sg:postcode": "44115",
    "sg:province": "OH",
    "sg:tags": [
      "union"
    ],
    "wof:name": "Sheet Metal Workers Internatio",
    "wof:placetype": "venue"
  },
  "geometry": {"coordinates":[-81.658784,41.500737],"type":"Point"}
}
