{
  "type": "Feature",
  "properties": {
    "iso:country":"US",
    "sg:address":"5917 US Hwy 322",
    "sg:city":"Williamsfield",
    "sg:classifiers":[
        {
            "category":"Banks & Credit Unions",
            "subcategory":"Bank",
            "type":"Services"
        }
    ],
    "sg:phone":"+1 440 293 7502",
    "sg:postcode":"44093",
    "sg:province":"OH",
    "wof:name":"Cortland Savings & Banking Co",
    "wof:placetype":"venue"
},
  "geometry": {"coordinates":[-80.571544,41.533238],"type":"Point"}
}