{
  "type": "Feature",
  "properties": {
    "addr:full": "5917 US Hwy 322 Williamsfield OH 44093",
    "addr:housenumber": "5917",
    "addr:postcode": "44093",
    "addr:street": "Us Hwy 322",
    "iso:country": "US",
    "sg:address": "5917 US Hwy 322",
    "sg:city": "Williamsfield",
    "sg:classifiers": [
      {
        "category": "Banks \u0026 Credit Unions",
        "subcategory": "Bank",
        "type": "Services"
      }
    ],
    "sg:phone": "+1 440 293 7502",
    "sg:postcode": "44093",
    "sg:province": "OH",
    "wof:name": "Cortland Savings \u0026 Banking Co",
    "wof:placetype": "venue"
  },
  "geometry": {"coordinates":[-80.571544,41.533238],"type":"Point"}
}
