{
  "type": "Feature",
  "properties": {
    "addr:full": "2075 Big Tree Dr Columbus OH 43223",
    "addr:housenumber": "2075",
    "addr:postcode": "43223",
    "addr:street": "Big Tree Dr",
    "iso:country": "US",
    "sg:address": "2075 Big Tree Dr",
    "sg:city": "Columbus",
    "sg:classifiers": [
      {
        "category": "Organizations",
        "subcategory": "Religious Organization",
        "type": "Services"
      }
    ],
    "sg:phone": "+1 614 275 1877",
    "sg:postcode": "43223",
    "sg:province": "OH",
    "sg:tags": [
      "church"
    ],
    "wof:name": "New Breed Fellowship Church",
    "wof:placetype": "venue"
  },
  "geometry": {"coordinates":[-83.051096,39.926143],"type":"Point"}
}
