{
  "type": "Feature",
  "properties": {
    "iso:country":"US",
    "sg:address":"6540 Reynoldsburg Baltimore Rd NW",
    "sg:city":"Pickerington",
    "sg:classifiers":[
        {
            "category":"Banks & Credit Unions",
            "subcategory":"Financial Services",
            "type":"Services"
        }
    ],
    "sg:phone":"+1 614 837 4455",
    "sg:postcode":"43147",
    "sg:province":"OH",
    "sg:tags":[
        "investor"
    ],
    "wof:name":"Sj Investments LLC",
    "wof:placetype":"venue"
},
  "geometry": {"coordinates":[-82.716791,39.877178],"type":"Point"}
}