{
  "type": "Feature",
  "properties": {
    "addr:full": "27830 Gilchrist Dr Euclid OH 44132",
    "addr:postcode": "27830;44132",
    "addr:street": "Gilchrist Dr",
    "iso:country": "US",
    "sg:address": "27830 Gilchrist Dr",
    "sg:city": "Euclid",
    "sg:classifiers": [
      {
        "category": "Banks \u0026 Credit Unions",
        "subcategory": "Financial Services",
        "type": "Services"
      }
    ],
    "sg:phone": "+1 216 731 5959",
    "sg:postcode": "44132",
    "sg:province": "OH",
    "sg:tags": [
      "investor"
    ],
    "wof:name": "Yurch Investments Inc",
    "wof:placetype": "venue"
  },
  "geometry": {"coordinates":[-81.491927,41.628099],"type":"Point"}
}
