{
  "type": "Feature",
  "properties": {
    "addr:full":"45905 Middle Ridge Rd Amherst OH 44001",
    "addr:housenumber":"45905",
    "addr:postcode":"44001",
    "addr:street":"Middle Ridge Rd",
    "iso:country":"US",
    "sg:address":"45905 Middle Ridge Rd",
    "sg:city":"Amherst",
    "sg:classifiers":[
        {
            "category":"Retail",
            "subcategory":"Auto Repair",
            "type":"Services"
        }
    ],
    "sg:phone":"+1 440 988 3161",
    "sg:postcode":"44001",
    "sg:province":"OH",
    "sg:tags":[
        "repairing",
        "automobile"
    ],
    "wof:name":"Cuenin's Auto Svc",
    "wof:placetype":"venue"
},
  "geometry": {"coordinates":[-82.212025,41.388851],"type":"Point"}
}