{
  "type": "Feature",
  "properties": {
    "addr:full":"706 Oakwood St Ravenna OH 44266",
    "addr:housenumber":"706",
    "addr:postcode":"44266",
    "addr:street":"Oakwood St",
    "iso:country":"US",
    "sg:address":"706 Oakwood St",
    "sg:city":"Ravenna",
    "sg:classifiers":[
        {
            "category":"Manufacturing",
            "subcategory":"Rubber & Plastics",
            "type":"Manufacturing & Wholesale Goods"
        }
    ],
    "sg:phone":"+1 330 296 2831",
    "sg:postcode":"44266",
    "sg:province":"OH",
    "sg:tags":[
        "supply"
    ],
    "wof:name":"Colonial Rubber Co",
    "wof:placetype":"venue"
},
  "geometry": {"coordinates":[-81.25563,41.165269],"type":"Point"}
}