{
  "type": "Feature",
  "properties": {
    "iso:country":"US",
    "sg:address":"7344 Mentor Ave",
    "sg:city":"Mentor",
    "sg:classifiers":[
        {
            "category":"Home & Garden",
            "subcategory":"Furniture",
            "type":"Retail Goods"
        }
    ],
    "sg:phone":"+1 440 946 7014",
    "sg:postcode":"44060",
    "sg:province":"OH",
    "wof:name":"Wood Manor Furniture Outlet",
    "wof:placetype":"venue"
},
  "geometry": {"coordinates":[-81.377568,41.652669],"type":"Point"}
}