{
  "type": "Feature",
  "properties": {
    "addr:full": "7344 Mentor Ave Mentor OH 44060",
    "addr:housenumber": "7344",
    "addr:postcode": "44060",
    "addr:street": "Mentor Ave",
    "iso:country": "US",
    "sg:address": "7344 Mentor Ave",
    "sg:city": "Mentor",
    "sg:classifiers": [
      {
        "category": "Home \u0026 Garden",
        "subcategory": "Furniture",
        "type": "Retail Goods"
      }
    ],
    "sg:phone": "+1 440 946 7014",
    "sg:postcode": "44060",
    "sg:province": "OH",
    "wof:name": "Wood Manor Furniture Outlet",
    "wof:placetype": "venue"
  },
  "geometry": {"coordinates":[-81.377568,41.652669],"type":"Point"}
}
