{
  "type": "Feature",
  "properties": {
    "addr:full": "8261 Jakaro Dr Cincinnati OH 45255",
    "addr:housenumber": "8261",
    "addr:postcode": "45255",
    "addr:street": "Jakaro Dr",
    "iso:country": "US",
    "sg:address": "8261 Jakaro Dr",
    "sg:city": "Cincinnati",
    "sg:classifiers": [
      {
        "category": "Communications",
        "type": "Services"
      }
    ],
    "sg:phone": "+1 513 474 3102",
    "sg:postcode": "45255",
    "sg:province": "OH",
    "sg:tags": [
      "communication"
    ],
    "wof:name": "Riehle Communications LLC",
    "wof:placetype": "venue"
  },
  "geometry": {"coordinates":[-84.329248,39.066758],"type":"Point"}
}
