{
  "type": "Feature",
  "properties": {
    "iso:country":"US",
    "sg:address":"950 Lake Rd",
    "sg:city":"Medina",
    "sg:classifiers":[
        {
            "category":"Wholesale",
            "subcategory":"Machinery & Supplies",
            "type":"Manufacturing & Wholesale Goods"
        }
    ],
    "sg:phone":"+1 330 665 2039",
    "sg:postcode":"44256",
    "sg:province":"OH",
    "sg:tags":[
        "industrial",
        "miscellaneous"
    ],
    "wof:name":"SME Equipment",
    "wof:placetype":"venue"
},
  "geometry": {"coordinates":[-81.89466,41.122064],"type":"Point"}
}