{
  "type": "Feature",
  "properties": {
    "iso:country":"US",
    "sg:address":"365 Northland Blvd",
    "sg:city":"Cincinnati",
    "sg:classifiers":[
        {
            "category":"Professional",
            "subcategory":"Accounting & Tax Preparation",
            "type":"Services"
        }
    ],
    "sg:phone":"+1 513 772 7591",
    "sg:postcode":"45246",
    "sg:province":"OH",
    "sg:tags":[
        "accountant"
    ],
    "wof:name":"Geo R Lewis",
    "wof:placetype":"venue"
},
  "geometry": {"coordinates":[-84.494179,39.281654],"type":"Point"}
}