{
  "type": "Feature",
  "properties": {
    "iso:country":"US",
    "sg:address":"1969 S Main St",
    "sg:city":"Akron",
    "sg:classifiers":[
        {
            "category":"Autos & Motor Vehicles",
            "subcategory":"Auto Supplies",
            "type":"Retail Goods"
        }
    ],
    "sg:phone":"+1 330 745 3300",
    "sg:postcode":"44301",
    "sg:province":"OH",
    "sg:tags":[
        "automobile",
        "parts"
    ],
    "wof:name":"SUR & R",
    "wof:placetype":"venue"
},
  "geometry": {"coordinates":[-81.526842,41.032691],"type":"Point"}
}