{
  "type": "Feature",
  "properties": {
    "iso:country":"US",
    "sg:address":"319 Fairway Ave",
    "sg:city":"Chillicothe",
    "sg:classifiers":[
        {
            "category":"Professional",
            "subcategory":"Employment Agencies",
            "type":"Services"
        }
    ],
    "sg:phone":"+1 740 775 5999",
    "sg:postcode":"45601",
    "sg:province":"OH",
    "sg:tags":[
        "leasing"
    ],
    "wof:name":"Work Force LTD",
    "wof:placetype":"venue"
},
  "geometry": {"coordinates":[-83.004538,39.339272],"type":"Point"}
}