{
  "type": "Feature",
  "properties": {
    "addr:full":"8659 Co Hwy 95 Wharton OH 43359",
    "addr:housenumber":"8659",
    "addr:postcode":"43359",
    "addr:street":"Co Hwy 95",
    "iso:country":"US",
    "sg:address":"8659 Co Hwy 95",
    "sg:city":"Wharton",
    "sg:phone":"+1 419 458 2301",
    "sg:postcode":"43359",
    "sg:province":"OH",
    "sg:tags":[
        "farm",
        "corn"
    ],
    "wof:name":"Vincent Derr",
    "wof:placetype":"venue"
},
  "geometry": {"coordinates":[-83.419067,40.867298],"type":"Point"}
}