{
  "type": "Feature",
  "properties": {
    "addr:full": "3663 Ridge Mill Dr Hilliard OH 43026",
    "addr:housenumber": "3663",
    "addr:postcode": "43026",
    "addr:street": "Ridge Mill Dr",
    "iso:country": "US",
    "sg:address": "3663 Ridge Mill Dr",
    "sg:city": "Hilliard",
    "sg:classifiers": [
      {
        "category": "Social Services",
        "subcategory": "Job Training",
        "type": "Services"
      }
    ],
    "sg:phone": "+1 614 293 6384",
    "sg:postcode": "43026",
    "sg:province": "OH",
    "sg:tags": [
      "rehabilitation"
    ],
    "wof:name": "Hilliard Rehab",
    "wof:placetype": "venue"
  },
  "geometry": {"coordinates":[-83.111996,40.028639],"type":"Point"}
}
