{
  "type": "Feature",
  "properties": {
    "addr:full": "479 Parsons Ave Columbus OH 43215",
    "addr:housenumber": "479",
    "addr:postcode": "43215",
    "addr:street": "Parsons Ave",
    "iso:country": "US",
    "sg:address": "479 Parsons Ave",
    "sg:city": "Columbus",
    "sg:classifiers": [
      {
        "category": "Health Services",
        "subcategory": "Doctor",
        "type": "Services"
      }
    ],
    "sg:phone": "+1 614 461 7972",
    "sg:postcode": "43215",
    "sg:province": "OH",
    "sg:tags": [
      "physician",
      "surgeon"
    ],
    "sg:website": "www.childrenshospital.com",
    "wof:name": "Cardinal Orthopaedic Institute",
    "wof:placetype": "venue"
  },
  "geometry": {"coordinates":[-82.982358,39.954436],"type":"Point"}
}
