{
  "type": "Feature",
  "properties": {
    "addr:full": "19211 State Rte 219 Botkins OH 45306",
    "addr:housenumber": "19211",
    "addr:postcode": "45306",
    "addr:street": "State Rte 219",
    "iso:country": "US",
    "sg:address": "19211 State Rte 219",
    "sg:city": "Botkins",
    "sg:classifiers": [
      {
        "category": "Personal",
        "type": "Services"
      }
    ],
    "sg:phone": "+1 937 693 3149",
    "sg:postcode": "45306",
    "sg:province": "OH",
    "sg:tags": [
      "therapist",
      "massage"
    ],
    "wof:name": "Nurturing Hands",
    "wof:placetype": "venue"
  },
  "geometry": {"coordinates":[-84.183965,40.48153],"type":"Point"}
}
