{
  "type": "Feature",
  "properties": {
    "addr:full": "1870 E Main St Columbus OH 43205",
    "addr:housenumber": "1870",
    "addr:postcode": "43205",
    "addr:street": "E Main St",
    "iso:country": "US",
    "sg:address": "1870 E Main St",
    "sg:city": "Columbus",
    "sg:classifiers": [
      {
        "category": "Retail",
        "subcategory": "Auto Repair",
        "type": "Services"
      }
    ],
    "sg:phone": "+1 614 251 0691",
    "sg:postcode": "43205",
    "sg:province": "OH",
    "sg:tags": [
      "repairing",
      "automobile"
    ],
    "wof:name": "Sticks Auto",
    "wof:placetype": "venue"
  },
  "geometry": {"coordinates":[-82.947989,39.957409],"type":"Point"}
}
