{
  "type": "Feature",
  "properties": {
    "iso:country":"US",
    "sg:address":"1064 Center Rd",
    "sg:city":"Clinton",
    "sg:classifiers":[
        {
            "category":"Building & Trades",
            "subcategory":"Construction",
            "type":"Services"
        }
    ],
    "sg:phone":"+1 330 882 4671",
    "sg:postcode":"44216",
    "sg:province":"OH",
    "sg:tags":[
        "house"
    ],
    "wof:name":"Southern Eagle Construction",
    "wof:placetype":"venue"
},
  "geometry": {"coordinates":[-81.579025,40.952356],"type":"Point"}
}