{
  "type": "Feature",
  "properties": {
    "addr:full": "1064 Center Rd Clinton OH 44216",
    "addr:housenumber": "1064",
    "addr:postcode": "44216",
    "addr:street": "Center Rd",
    "iso:country": "US",
    "sg:address": "1064 Center Rd",
    "sg:city": "Clinton",
    "sg:classifiers": [
      {
        "category": "Building \u0026 Trades",
        "subcategory": "Construction",
        "type": "Services"
      }
    ],
    "sg:phone": "+1 330 882 4671",
    "sg:postcode": "44216",
    "sg:province": "OH",
    "sg:tags": [
      "house"
    ],
    "wof:name": "Southern Eagle Construction",
    "wof:placetype": "venue"
  },
  "geometry": {"coordinates":[-81.579025,40.952356],"type":"Point"}
}
