{
  "type": "Feature",
  "properties": {
    "iso:country":"US",
    "sg:address":"9015 London Groveport Rd",
    "sg:city":"Grove City",
    "sg:classifiers":[
        {
            "category":"Food & Beverages",
            "subcategory":"Fruits & Vegetables",
            "type":"Retail Goods"
        }
    ],
    "sg:phone":"+1 614 878 9462",
    "sg:postcode":"43123",
    "sg:province":"OH",
    "sg:tags":[
        "market"
    ],
    "sg:website":"www.circlesfarm.com",
    "wof:name":"Circle S Farm",
    "wof:placetype":"venue"
},
  "geometry": {"coordinates":[-83.246036,39.860438],"type":"Point"}
}