{
  "type": "Feature",
  "properties": {
    "addr:full": "9015 London Groveport Rd Grove City OH 43123",
    "addr:housenumber": "9015",
    "addr:postcode": "43123",
    "addr:street": "London Groveport Rd",
    "iso:country": "US",
    "sg:address": "9015 London Groveport Rd",
    "sg:city": "Grove City",
    "sg:classifiers": [
      {
        "category": "Food \u0026 Beverages",
        "subcategory": "Fruits \u0026 Vegetables",
        "type": "Retail Goods"
      }
    ],
    "sg:phone": "+1 614 878 9462",
    "sg:postcode": "43123",
    "sg:province": "OH",
    "sg:tags": [
      "market"
    ],
    "sg:website": "www.circlesfarm.com",
    "wof:name": "Circle S Farm",
    "wof:placetype": "venue"
  },
  "geometry": {"coordinates":[-83.246036,39.860438],"type":"Point"}
}
