{
  "type": "Feature",
  "properties": {
    "iso:country":"US",
    "sg:address":"1114 Hazel St",
    "sg:city":"Akron",
    "sg:classifiers":[
        {
            "category":"Manufacturing",
            "subcategory":"Metals",
            "type":"Manufacturing & Wholesale Goods"
        }
    ],
    "sg:phone":"+1 330 733 8818",
    "sg:postcode":"44305",
    "sg:province":"OH",
    "sg:tags":[
        "production",
        "grinding"
    ],
    "wof:name":"Rodgers Micro Grinding Inc",
    "wof:placetype":"venue"
},
  "geometry": {"coordinates":[-81.479314,41.083379],"type":"Point"}
}