{
  "type": "Feature",
  "properties": {
    "iso:country":"US",
    "sg:address":"444 Youngstown Poland Rd",
    "sg:city":"Struthers",
    "sg:classifiers":[
        {
            "category":"Shopping",
            "subcategory":"Discount & Variety Stores",
            "type":"Retail Goods"
        },
        {
            "category":"Shopping",
            "subcategory":"Department Store",
            "type":"Retail Goods"
        }
    ],
    "sg:phone":"+1 330 755 7005",
    "sg:postcode":"44471",
    "sg:province":"OH",
    "wof:name":"Family Dollar Stores",
    "wof:placetype":"venue"
},
  "geometry": {"coordinates":[-80.615784,41.058976],"type":"Point"}
}