{
  "type": "Feature",
  "properties": {
    "addr:full": "26241 State Rte 281 Defiance OH 43512",
    "addr:housenumber": "26241",
    "addr:postcode": "43512",
    "addr:street": "State Rte 281",
    "iso:country": "US",
    "sg:address": "26241 State Rte 281",
    "sg:city": "Defiance",
    "sg:classifiers": [
      {
        "category": "Manufacturing",
        "subcategory": "Metals",
        "type": "Manufacturing \u0026 Wholesale Goods"
      }
    ],
    "sg:phone": "+1 419 782 2363",
    "sg:postcode": "43512",
    "sg:province": "OH",
    "sg:tags": [
      "coating",
      "powder"
    ],
    "wof:name": "Advantage Powder Coating Inc",
    "wof:placetype": "venue"
  },
  "geometry": {"coordinates":[-84.316273,41.282604],"type":"Point"}
}
