{
  "type": "Feature",
  "properties": {
    "addr:full": "200 W Monroe St Zanesville OH 43701",
    "addr:housenumber": "200",
    "addr:postcode": "43701",
    "addr:street": "W Monroe St",
    "iso:country": "US",
    "sg:address": "200 W Monroe St",
    "sg:city": "Zanesville",
    "sg:classifiers": [
      {
        "category": "Wholesale",
        "subcategory": "Machinery \u0026 Supplies",
        "type": "Manufacturing \u0026 Wholesale Goods"
      }
    ],
    "sg:phone": "+1 740 454 1289",
    "sg:postcode": "43701",
    "sg:province": "OH",
    "sg:tags": [
      "farm",
      "equipment"
    ],
    "wof:name": "Muskingum Tractor \u0026 Equipment",
    "wof:placetype": "venue"
  },
  "geometry": {"coordinates":[-82.005657,39.953841],"type":"Point"}
}
