{
  "type": "Feature",
  "properties": {
    "iso:country":"US",
    "sg:address":"6469 Genevieve Rd",
    "sg:city":"Ravenna",
    "sg:classifiers":[
        {
            "category":"Retail",
            "subcategory":"Animal Services",
            "type":"Services"
        }
    ],
    "sg:phone":"+1 330 296 6335",
    "sg:postcode":"44266",
    "sg:province":"OH",
    "wof:name":"Hugh Mahan Racing Stable",
    "wof:placetype":"venue"
},
  "geometry": {"coordinates":[-81.278931,41.165636],"type":"Point"}
}