{
  "type": "Feature",
  "properties": {
    "iso:country":"US",
    "sg:address":"5001 Monroe St",
    "sg:city":"Toledo",
    "sg:classifiers":[
        {
            "category":"Building & Trades",
            "subcategory":"Landscaping Services",
            "type":"Services"
        }
    ],
    "sg:phone":"+1 419 472 5235",
    "sg:postcode":"43606",
    "sg:province":"OH",
    "sg:tags":[
        "tree"
    ],
    "wof:name":"Almond Tree Nut Co",
    "wof:placetype":"venue"
},
  "geometry": {"coordinates":[-83.642016,41.697742],"type":"Point"}
}