{
  "type": "Feature",
  "properties": {
    "iso:country":"US",
    "sg:address":"636 Northland Blvd",
    "sg:city":"Cincinnati",
    "sg:classifiers":[
        {
            "category":"Professional",
            "subcategory":"Advertising",
            "type":"Services"
        }
    ],
    "sg:phone":"+1 513 674 1414",
    "sg:postcode":"45240",
    "sg:province":"OH",
    "wof:name":"M J Promotions",
    "wof:placetype":"venue"
},
  "geometry": {"coordinates":[-84.497297,39.281457],"type":"Point"}
}