{
  "type": "Feature",
  "properties": {
    "iso:country":"US",
    "sg:address":"6611 Marcy Rd",
    "sg:city":"Pierpont",
    "sg:classifiers":[
        {
            "category":"Shopping",
            "type":"Retail Goods"
        }
    ],
    "sg:phone":"+1 440 577 1129",
    "sg:postcode":"44082",
    "sg:province":"OH",
    "sg:tags":[
        "farm",
        "equipment",
        "lawn",
        "garden"
    ],
    "wof:name":"Marcy Equipment",
    "wof:placetype":"venue"
},
  "geometry": {"coordinates":[-80.54326,41.75274],"type":"Point"}
}