{
  "type": "Feature",
  "properties": {
    "iso:country":"US",
    "sg:address":"1340 Hird Ave",
    "sg:city":"Cleveland",
    "sg:classifiers":[
        {
            "category":"Real Estate",
            "subcategory":"Real Estate Operator",
            "type":"Services"
        }
    ],
    "sg:phone":"+1 216 226 3300",
    "sg:postcode":"44107",
    "sg:province":"OH",
    "sg:tags":[
        "apartment"
    ],
    "wof:name":"Lakewood Club Apartments",
    "wof:placetype":"venue"
},
  "geometry": {"coordinates":[-81.77027200000001,41.483791],"type":"Point"}
}