{
  "type": "Feature",
  "properties": {
    "addr:full":"1827 Coventry Rd Cleveland OH 44118",
    "addr:housenumber":"1827",
    "addr:postcode":"44118",
    "addr:street":"Coventry Rd",
    "iso:country":"US",
    "sg:address":"1827 Coventry Rd",
    "sg:city":"Cleveland",
    "sg:classifiers":[
        {
            "category":"Shopping",
            "subcategory":"Hobbies, Toys, & Games",
            "type":"Retail Goods"
        }
    ],
    "sg:phone":"+1 216 371 4386",
    "sg:postcode":"44118",
    "sg:province":"OH",
    "wof:name":"Big Fun",
    "wof:placetype":"venue"
},
  "geometry": {"coordinates":[-81.57991,41.51005],"type":"Point"}
}