{
  "type": "Feature",
  "properties": {
    "addr:full": "7231 State Rte 43 East Springfield OH 43908",
    "addr:housenumber": "7231",
    "addr:postcode": "43908",
    "addr:street": "State Rte 43",
    "iso:country": "US",
    "sg:address": "7231 State Rte 43",
    "sg:city": "East Springfield",
    "sg:classifiers": [
      {
        "category": "Sports \u0026 Exercise",
        "subcategory": "Golf",
        "type": "Entertainment"
      }
    ],
    "sg:phone": "+1 740 543 3270",
    "sg:postcode": "43908",
    "sg:province": "OH",
    "sg:tags": [
      "course"
    ],
    "wof:name": "Spring Hills Golf Club",
    "wof:placetype": "venue"
  },
  "geometry": {"coordinates":[-80.844736,40.44968],"type":"Point"}
}
