{
  "type": "Feature",
  "properties": {
    "iso:country":"US",
    "sg:address":"5170 Belmont Ave",
    "sg:city":"Youngstown",
    "sg:classifiers":[
        {
            "category":"Health Services",
            "subcategory":"Doctor",
            "type":"Services"
        }
    ],
    "sg:phone":"+1 330 759 2511",
    "sg:postcode":"44505",
    "sg:province":"OH",
    "sg:tags":[
        "physician",
        "surgeon"
    ],
    "wof:name":"Paul A Rich MD",
    "wof:placetype":"venue"
},
  "geometry": {"coordinates":[-80.664742,41.173852],"type":"Point"}
}