{
  "type": "Feature",
  "properties": {
    "addr:full":"273 S Main St Waynesville OH 45068",
    "addr:housenumber":"273",
    "addr:postcode":"45068",
    "addr:street":"S Main St",
    "iso:country":"US",
    "sg:address":"273 S Main St",
    "sg:city":"Waynesville",
    "sg:classifiers":[
        {
            "category":"Shopping",
            "subcategory":"Used Merchandise",
            "type":"Retail Goods"
        }
    ],
    "sg:phone":"+1 513 897 3447",
    "sg:postcode":"45068",
    "sg:province":"OH",
    "sg:tags":[
        "antique"
    ],
    "wof:name":"Fresh Eggs",
    "wof:placetype":"venue"
},
  "geometry": {"coordinates":[-84.088148,39.528201],"type":"Point"}
}