{
  "type": "Feature",
  "properties": {
    "addr:full": "1119 Robin Rd St Marys OH 45885",
    "addr:housenumber": "1119",
    "addr:postcode": "45885",
    "addr:street": "Robin Rd",
    "iso:country": "US",
    "sg:address": "1119 Robin Rd",
    "sg:city": "St Marys",
    "sg:classifiers": [
      {
        "category": "Restaurant",
        "type": "Food \u0026 Drink"
      }
    ],
    "sg:phone": "+1 419 394 5744",
    "sg:postcode": "45885",
    "sg:province": "OH",
    "sg:tags": [
      "caterer"
    ],
    "wof:name": "MJM Catering",
    "wof:placetype": "venue"
  },
  "geometry": {"coordinates":[-84.404016,40.549207],"type":"Point"}
}
