{
  "type": "Feature",
  "properties": {
    "addr:full": "950 Ford Ave Conneaut OH 44030",
    "addr:housenumber": "950",
    "addr:postcode": "44030",
    "addr:street": "Ford Ave",
    "iso:country": "US",
    "sg:address": "950 Ford Ave",
    "sg:city": "Conneaut",
    "sg:classifiers": [
      {
        "category": "Freight",
        "type": "Transportation"
      }
    ],
    "sg:phone": "+1 440 593 1102",
    "sg:postcode": "44030",
    "sg:province": "OH",
    "sg:tags": [
      "dock"
    ],
    "wof:name": "Pittsburgh \u0026 Conneaut Dock Co",
    "wof:placetype": "venue"
  },
  "geometry": {"coordinates":[-80.549607,41.963152],"type":"Point"}
}
