{
  "type": "Feature",
  "properties": {
    "addr:full":"1676 Lancaster Ave Reynoldsburg OH 43068",
    "addr:housenumber":"1676",
    "addr:postcode":"43068",
    "addr:street":"Lancaster Ave",
    "iso:country":"US",
    "sg:address":"1676 Lancaster Ave",
    "sg:city":"Reynoldsburg",
    "sg:classifiers":[
        {
            "category":"Farming",
            "subcategory":"Nursery",
            "type":"Manufacturing & Wholesale Goods"
        }
    ],
    "sg:phone":"+1 614 866 0142",
    "sg:postcode":"43068",
    "sg:province":"OH",
    "sg:tags":[
        "ornamental"
    ],
    "wof:name":"Pioneer Nursery",
    "wof:placetype":"venue"
},
  "geometry": {"coordinates":[-82.79862300000001,39.949198],"type":"Point"}
}