{
  "type": "Feature",
  "properties": {
    "addr:full": "148 Crofton Dr South Vienna OH 45369",
    "addr:housenumber": "148",
    "addr:postcode": "45369",
    "addr:street": "Crofton Dr South",
    "iso:country": "US",
    "sg:address": "148 Crofton Dr",
    "sg:city": "South Vienna",
    "sg:classifiers": [
      {
        "category": "Building \u0026 Trades",
        "subcategory": "Construction",
        "type": "Services"
      }
    ],
    "sg:phone": "+1 937 568 9462",
    "sg:postcode": "45369",
    "sg:province": "OH",
    "sg:tags": [
      "steel",
      "erection",
      "erectors",
      "structural"
    ],
    "wof:name": "Tuttle Erectors LLC",
    "wof:placetype": "venue"
  },
  "geometry": {"coordinates":[-83.680906,39.952206],"type":"Point"}
}
