{
  "type": "Feature",
  "properties": {
    "iso:country":"US",
    "sg:address":"7574 Atwell Ct",
    "sg:city":"Canal Winchester",
    "sg:classifiers":[
        {
            "category":"Building & Trades",
            "subcategory":"Plumbing",
            "type":"Services"
        }
    ],
    "sg:phone":"+1 614 834 9304",
    "sg:postcode":"43110",
    "sg:province":"OH",
    "sg:tags":[
        "contractor"
    ],
    "wof:name":"Blaze Guard",
    "wof:placetype":"venue"
},
  "geometry": {"coordinates":[-82.81604400000001,39.827698],"type":"Point"}
}