{
  "type": "Feature",
  "properties": {
    "addr:full": "7574 Atwell Ct Canal Winchester OH 43110",
    "addr:housenumber": "7574",
    "addr:postcode": "43110",
    "addr:street": "Atwell Ct",
    "iso:country": "US",
    "sg:address": "7574 Atwell Ct",
    "sg:city": "Canal Winchester",
    "sg:classifiers": [
      {
        "category": "Building \u0026 Trades",
        "subcategory": "Plumbing",
        "type": "Services"
      }
    ],
    "sg:phone": "+1 614 834 9304",
    "sg:postcode": "43110",
    "sg:province": "OH",
    "sg:tags": [
      "contractor"
    ],
    "wof:name": "Blaze Guard",
    "wof:placetype": "venue"
  },
  "geometry": {"coordinates":[-82.816044,39.827698],"type":"Point"}
}
