{
  "type": "Feature",
  "properties": {
    "addr:full": "9368 Twp Rd 50 Dola OH 45835",
    "addr:housenumber": "9368;50",
    "addr:postcode": "45835",
    "addr:street": "Twp Rd",
    "iso:country": "US",
    "sg:address": "9368 Twp Rd 50",
    "sg:city": "Dola",
    "sg:phone": "+1 419 759 2075",
    "sg:postcode": "45835",
    "sg:province": "OH",
    "sg:tags": [
      "farm",
      "corn",
      "soybean"
    ],
    "wof:name": "Mike Dilts",
    "wof:placetype": "venue"
  },
  "geometry": {"coordinates":[-83.703088,40.761537],"type":"Point"}
}
