{
  "type": "Feature",
  "properties": {
    "addr:full": "7406 Lauren J Dr Mentor OH 44060",
    "addr:housenumber": "7406",
    "addr:postcode": "44060",
    "addr:street": "Lauren J Dr",
    "iso:country": "US",
    "sg:address": "7406 Lauren J Dr",
    "sg:city": "Mentor",
    "sg:classifiers": [
      {
        "category": "Manufacturing",
        "subcategory": "Building Materials",
        "type": "Manufacturing \u0026 Wholesale Goods"
      }
    ],
    "sg:phone": "+1 440 478 6785",
    "sg:postcode": "44060",
    "sg:province": "OH",
    "sg:tags": [
      "interior",
      "woodworking",
      "design",
      "custom"
    ],
    "wof:name": "Collins Woodworking",
    "wof:placetype": "venue"
  },
  "geometry": {"coordinates":[-81.347333,41.666168],"type":"Point"}
}
