{
  "type": "Feature",
  "properties": {
    "iso:country":"US",
    "sg:address":"7406 Lauren J Dr",
    "sg:city":"Mentor",
    "sg:classifiers":[
        {
            "category":"Manufacturing",
            "subcategory":"Building Materials",
            "type":"Manufacturing & Wholesale Goods"
        }
    ],
    "sg:phone":"+1 440 478 6785",
    "sg:postcode":"44060",
    "sg:province":"OH",
    "sg:tags":[
        "interior",
        "woodworking",
        "design",
        "custom"
    ],
    "wof:name":"Collins Woodworking",
    "wof:placetype":"venue"
},
  "geometry": {"coordinates":[-81.34733300000001,41.666168],"type":"Point"}
}