{
  "type": "Feature",
  "properties": {
    "addr:full":"2525 34th St NE Canton OH 44705",
    "addr:housenumber":"2525",
    "addr:postcode":"44705",
    "addr:street":"34Th St Ne",
    "iso:country":"US",
    "sg:address":"2525 34th St NE",
    "sg:city":"Canton",
    "sg:classifiers":[
        {
            "category":"Home & Garden",
            "subcategory":"Building Materials",
            "type":"Retail Goods"
        }
    ],
    "sg:phone":"+1 330 453 5255",
    "sg:postcode":"44705",
    "sg:province":"OH",
    "sg:tags":[
        "windows",
        "installs",
        "siding",
        "door"
    ],
    "wof:name":"Windows & More Inc",
    "wof:placetype":"venue"
},
  "geometry": {"coordinates":[-81.33978999999999,40.833664],"type":"Point"}
}