{
  "type": "Feature",
  "properties": {
    "addr:full": "5141 Norris Dr Dayton OH 45414",
    "addr:housenumber": "5141",
    "addr:postcode": "45414",
    "addr:street": "Norris Dr",
    "iso:country": "US",
    "sg:address": "5141 Norris Dr",
    "sg:city": "Dayton",
    "sg:classifiers": [
      {
        "category": "Real Estate",
        "subcategory": "Real Estate Operator",
        "type": "Services"
      }
    ],
    "sg:phone": "+1 937 264 8760",
    "sg:postcode": "45414",
    "sg:province": "OH",
    "sg:tags": [
      "apartment"
    ],
    "wof:name": "Northcrest Garden Apartments",
    "wof:placetype": "venue"
  },
  "geometry": {"coordinates":[-84.2053,39.819683],"type":"Point"}
}
