{
  "type": "Feature",
  "properties": {
    "addr:full": "15623 US Hwy 23 Waverly OH 45690",
    "addr:postcode": "15623;45690",
    "addr:street": "Us Hwy 23",
    "iso:country": "US",
    "sg:address": "15623 US Hwy 23",
    "sg:city": "Waverly",
    "sg:classifiers": [
      {
        "category": "Building \u0026 Trades",
        "subcategory": "Construction",
        "type": "Services"
      }
    ],
    "sg:phone": "+1 740 947 6077",
    "sg:postcode": "45690",
    "sg:province": "OH",
    "sg:tags": [
      "downspouts",
      "gutter"
    ],
    "wof:name": "Gragg's Gutters",
    "wof:placetype": "venue"
  },
  "geometry": {"coordinates":[-82.975547,39.174187],"type":"Point"}
}
