{
  "type": "Feature",
  "properties": {
    "iso:country":"US",
    "sg:address":"6 Mount Vernon Ave",
    "sg:city":"Mt Vernon",
    "sg:classifiers":[
        {
            "category":"Retail",
            "subcategory":"Auto Repair",
            "type":"Services"
        }
    ],
    "sg:phone":"+1 740 397 7501",
    "sg:postcode":"43050",
    "sg:province":"OH",
    "sg:tags":[
        "repairing",
        "automobile"
    ],
    "wof:name":"Dick's Complete Auto & Muffler",
    "wof:placetype":"venue"
},
  "geometry": {"coordinates":[-82.48516600000001,40.384738],"type":"Point"}
}