{
  "type": "Feature",
  "properties": {
    "addr:full": "51 N Elm St Farmersville OH 45325",
    "addr:housenumber": "51",
    "addr:postcode": "45325",
    "addr:street": "N Elm St",
    "iso:country": "US",
    "sg:address": "51 N Elm St",
    "sg:city": "Farmersville",
    "sg:classifiers": [
      {
        "category": "Retail",
        "subcategory": "Auto Repair",
        "type": "Services"
      }
    ],
    "sg:phone": "+1 937 696 2168",
    "sg:postcode": "45325",
    "sg:province": "OH",
    "sg:tags": [
      "repairing",
      "automobile"
    ],
    "wof:name": "Adkins Automotive",
    "wof:placetype": "venue"
  },
  "geometry": {"coordinates":[-84.423993,39.679966],"type":"Point"}
}
