{
  "type": "Feature",
  "properties": {
    "iso:country":"US",
    "sg:address":"51 N Elm St",
    "sg:city":"Farmersville",
    "sg:classifiers":[
        {
            "category":"Retail",
            "subcategory":"Auto Repair",
            "type":"Services"
        }
    ],
    "sg:phone":"+1 937 696 2168",
    "sg:postcode":"45325",
    "sg:province":"OH",
    "sg:tags":[
        "repairing",
        "automobile"
    ],
    "wof:name":"Adkins Automotive",
    "wof:placetype":"venue"
},
  "geometry": {"coordinates":[-84.423993,39.679966],"type":"Point"}
}