{
  "type": "Feature",
  "properties": {
    "addr:full": "318 W 2nd St Wellston OH 45692",
    "addr:housenumber": "318",
    "addr:postcode": "45692",
    "addr:street": "W 2Nd St",
    "iso:country": "US",
    "sg:address": "318 W 2nd St",
    "sg:city": "Wellston",
    "sg:classifiers": [
      {
        "category": "Travel",
        "subcategory": "Bed \u0026 Breakfast",
        "type": "Entertainment"
      }
    ],
    "sg:phone": "+1 740 384 3125",
    "sg:postcode": "45692",
    "sg:province": "OH",
    "sg:tags": [
      "house",
      "real estate"
    ],
    "wof:name": "Carolyn Martindill",
    "wof:placetype": "venue"
  },
  "geometry": {"coordinates":[-82.540571,39.122075],"type":"Point"}
}
