{
  "type": "Feature",
  "properties": {
    "addr:full": "10683 Ravenna Rd Twinsburg OH 44087",
    "addr:housenumber": "10683",
    "addr:postcode": "44087",
    "addr:street": "Ravenna Rd",
    "iso:country": "US",
    "sg:address": "10683 Ravenna Rd",
    "sg:city": "Twinsburg",
    "sg:classifiers": [
      {
        "category": "Personal",
        "subcategory": "Barber",
        "type": "Services"
      }
    ],
    "sg:phone": "+1 330 425 9313",
    "sg:postcode": "44087",
    "sg:province": "OH",
    "wof:name": "Haircut House Inc",
    "wof:placetype": "venue"
  },
  "geometry": {"coordinates":[-81.462441,41.328503],"type":"Point"}
}
