{
  "type": "Feature",
  "properties": {
    "addr:full":"5020 Lewis Ave Toledo OH 43612",
    "addr:housenumber":"5020",
    "addr:postcode":"43612",
    "addr:street":"Lewis Ave",
    "iso:country":"US",
    "sg:address":"5020 Lewis Ave",
    "sg:city":"Toledo",
    "sg:classifiers":[
        {
            "category":"Shopping",
            "subcategory":"Department Store",
            "type":"Retail Goods"
        }
    ],
    "sg:phone":"+1 419 478 6947",
    "sg:postcode":"43612",
    "sg:province":"OH",
    "wof:name":"Family Dollar Store",
    "wof:placetype":"venue"
},
  "geometry": {"coordinates":[-83.56604,41.707811],"type":"Point"}
}