{
  "type": "Feature",
  "properties": {
    "iso:country":"US",
    "sg:address":"3347 Central Ave",
    "sg:city":"Cleveland",
    "sg:classifiers":[
        {
            "category":"Professional",
            "subcategory":"Lawyer & Legal Services",
            "type":"Services"
        }
    ],
    "sg:phone":"+1 216 771 0000",
    "sg:postcode":"44115",
    "sg:province":"OH",
    "sg:tags":[
        "attorney"
    ],
    "wof:name":"Chisara S Nwabara Co Lpa",
    "wof:placetype":"venue"
},
  "geometry": {"coordinates":[-81.663217,41.496846],"type":"Point"}
}