{
  "type": "Feature",
  "properties": {
    "addr:full": "3347 Central Ave Cleveland OH 44115",
    "addr:housenumber": "3347",
    "addr:postcode": "44115",
    "addr:street": "Central Ave",
    "iso:country": "US",
    "sg:address": "3347 Central Ave",
    "sg:city": "Cleveland",
    "sg:classifiers": [
      {
        "category": "Professional",
        "subcategory": "Lawyer \u0026 Legal Services",
        "type": "Services"
      }
    ],
    "sg:phone": "+1 216 771 0000",
    "sg:postcode": "44115",
    "sg:province": "OH",
    "sg:tags": [
      "attorney"
    ],
    "wof:name": "Chisara S Nwabara Co Lpa",
    "wof:placetype": "venue"
  },
  "geometry": {"coordinates":[-81.663217,41.496846],"type":"Point"}
}
