{
  "type": "Feature",
  "properties": {
    "addr:full":"6521 Beecher Rd Granville OH 43023",
    "addr:housenumber":"6521",
    "addr:postcode":"43023",
    "addr:street":"Beecher Rd",
    "iso:country":"US",
    "sg:address":"6521 Beecher Rd",
    "sg:city":"Granville",
    "sg:classifiers":[
        {
            "category":"Manufacturing",
            "subcategory":"Wood Products",
            "type":"Manufacturing & Wholesale Goods"
        }
    ],
    "sg:phone":"+1 740 927 0656",
    "sg:postcode":"43023",
    "sg:province":"OH",
    "sg:tags":[
        "mfg"
    ],
    "wof:name":"Sherri Daley Crafts",
    "wof:placetype":"venue"
},
  "geometry": {"coordinates":[-82.61406700000001,40.01348],"type":"Point"}
}