{
  "type": "Feature",
  "properties": {
    "addr:full": "5140 State Rte 4 Fairfield OH 45014",
    "addr:housenumber": "5140",
    "addr:postcode": "45014",
    "addr:street": "State Rte 4",
    "iso:country": "US",
    "sg:address": "5140 State Rte 4",
    "sg:city": "Fairfield",
    "sg:classifiers": [
      {
        "category": "Wholesale",
        "subcategory": "Auto Parts",
        "type": "Manufacturing \u0026 Wholesale Goods"
      }
    ],
    "sg:phone": "+1 513 829 6633",
    "sg:postcode": "45014",
    "sg:province": "OH",
    "sg:tags": [
      "supply"
    ],
    "wof:name": "Phalen Imported Parts",
    "wof:placetype": "venue"
  },
  "geometry": {"coordinates":[-84.528964,39.336604],"type":"Point"}
}
