{
  "type": "Feature",
  "properties": {
    "addr:full":"18579 Pearl Rd Cleveland OH 44136",
    "addr:housenumber":"18579",
    "addr:postcode":"44136",
    "addr:street":"Pearl Rd",
    "iso:country":"US",
    "sg:address":"18579 Pearl Rd",
    "sg:city":"Cleveland",
    "sg:classifiers":[
        {
            "category":"Building & Trades",
            "subcategory":"Construction",
            "type":"Services"
        }
    ],
    "sg:phone":"+1 440 846 9891",
    "sg:postcode":"44136",
    "sg:province":"OH",
    "sg:tags":[
        "insulation",
        "heat",
        "contractor"
    ],
    "sg:website":"www.davcorinternational.com",
    "wof:name":"Davcor International Inc",
    "wof:placetype":"venue"
},
  "geometry": {"coordinates":[-81.83566,41.276002],"type":"Point"}
}