{
  "type": "Feature",
  "properties": {
    "addr:full": "4430 Carver Woods Dr Cincinnati OH 45242",
    "addr:housenumber": "4430",
    "addr:postcode": "45242",
    "addr:street": "Carver Woods Dr",
    "iso:country": "US",
    "sg:address": "4430 Carver Woods Dr",
    "sg:city": "Cincinnati",
    "sg:classifiers": [
      {
        "category": "Professional",
        "type": "Services"
      }
    ],
    "sg:phone": "+1 513 792 2021",
    "sg:postcode": "45242",
    "sg:province": "OH",
    "sg:tags": [
      "establishment"
    ],
    "wof:name": "G E Co",
    "wof:placetype": "venue"
  },
  "geometry": {"coordinates":[-84.386504,39.245385],"type":"Point"}
}
