{
  "type": "Feature",
  "properties": {
    "addr:full": "1805 E Manhattan Blvd Toledo OH 43608",
    "addr:housenumber": "1805",
    "addr:postcode": "43608",
    "addr:street": "E Manhattan Blvd",
    "iso:country": "US",
    "sg:address": "1805 E Manhattan Blvd",
    "sg:city": "Toledo",
    "sg:classifiers": [
      {
        "category": "Retail",
        "subcategory": "Auto Repair",
        "type": "Services"
      }
    ],
    "sg:phone": "+1 419 726 2432",
    "sg:postcode": "43608",
    "sg:province": "OH",
    "sg:tags": [
      "repairing",
      "automobile"
    ],
    "wof:name": "S \u0026 I Auto",
    "wof:placetype": "venue"
  },
  "geometry": {"coordinates":[-83.508859,41.688064],"type":"Point"}
}
