{
  "type": "Feature",
  "properties": {
    "addr:full":"11517 Snow Rd Cleveland OH 44130",
    "addr:housenumber":"11517",
    "addr:postcode":"44130",
    "addr:street":"Snow Rd",
    "iso:country":"US",
    "sg:address":"11517 Snow Rd",
    "sg:city":"Cleveland",
    "sg:classifiers":[
        {
            "category":"Insurance",
            "subcategory":"Insurance Agent",
            "type":"Services"
        }
    ],
    "sg:phone":"+1 440 888 8838",
    "sg:postcode":"44130",
    "sg:province":"OH",
    "wof:name":"State Farm Insurance",
    "wof:placetype":"venue"
},
  "geometry": {"coordinates":[-81.768647,41.40496],"type":"Point"}
}