{
  "type": "Feature",
  "properties": {
    "iso:country":"US",
    "sg:address":"20 Troy Town Dr",
    "sg:city":"Troy",
    "sg:classifiers":[
        {
            "category":"Restaurant",
            "type":"Food & Drink"
        }
    ],
    "sg:phone":"+1 937 339 1889",
    "sg:postcode":"45373",
    "sg:province":"OH",
    "wof:name":"Frisch's Big Boy Restaurant",
    "wof:placetype":"venue"
},
  "geometry": {"coordinates":[-84.237549,40.051352],"type":"Point"}
}