{
  "type": "Feature",
  "properties": {
    "addr:full":"6386 Bridgetown Rd Cincinnati OH 45248",
    "addr:housenumber":"6386",
    "addr:postcode":"45248",
    "addr:street":"Bridgetown Rd",
    "iso:country":"US",
    "sg:address":"6386 Bridgetown Rd",
    "sg:city":"Cincinnati",
    "sg:classifiers":[
        {
            "category":"Personal",
            "subcategory":"Beauty Salon",
            "type":"Services"
        }
    ],
    "sg:phone":"+1 513 574 3508",
    "sg:postcode":"45248",
    "sg:province":"OH",
    "sg:tags":[
        "shop"
    ],
    "wof:name":"Studio C Hair & Nails",
    "wof:placetype":"venue"
},
  "geometry": {"coordinates":[-84.659256,39.153125],"type":"Point"}
}