{
  "type": "Feature",
  "properties": {
    "addr:full": "320 S Chestnut St Barnesville OH 43713",
    "addr:housenumber": "320",
    "addr:postcode": "43713",
    "addr:street": "S Chestnut St",
    "iso:country": "US",
    "sg:address": "320 S Chestnut St",
    "sg:city": "Barnesville",
    "sg:classifiers": [
      {
        "category": "Food \u0026 Beverages",
        "subcategory": "Liquor \u0026 Beverages",
        "type": "Retail Goods"
      }
    ],
    "sg:phone": "+1 740 425 1047",
    "sg:postcode": "43713",
    "sg:province": "OH",
    "sg:tags": [
      "beer"
    ],
    "wof:name": "Chestnut Package Store Inc",
    "wof:placetype": "venue"
  },
  "geometry": {"coordinates":[-81.178075,39.98614],"type":"Point"}
}
