{
  "type": "Feature",
  "properties": {
    "iso:country":"US",
    "sg:address":"37 N High St",
    "sg:city":"Columbus",
    "sg:classifiers":[
        {
            "category":"Organizations",
            "subcategory":"Professional Association",
            "type":"Services"
        }
    ],
    "sg:phone":"+1 614 221 1321",
    "sg:postcode":"43215",
    "sg:province":"OH",
    "sg:tags":[
        "chamber",
        "commerce"
    ],
    "wof:name":"Greater Clmbus Chmber Commerce",
    "wof:placetype":"venue"
},
  "geometry": {"coordinates":[-83.000963,39.963441],"type":"Point"}
}