{
  "type": "Feature",
  "properties": {
    "iso:country":"US",
    "sg:address":"12607 Chillicothe Rd",
    "sg:city":"Chesterland",
    "sg:classifiers":[
        {
            "category":"Cinema",
            "subcategory":"Movie Rental",
            "type":"Entertainment"
        }
    ],
    "sg:phone":"+1 440 729 9177",
    "sg:postcode":"44026",
    "sg:province":"OH",
    "sg:tags":[
        "video"
    ],
    "wof:name":"Movie Mart",
    "wof:placetype":"venue"
},
  "geometry": {"coordinates":[-81.337839,41.526464],"type":"Point"}
}