{
  "type": "Feature",
  "properties": {
    "addr:full": "519 E 11th Ave Columbus OH 43211",
    "addr:housenumber": "519",
    "addr:postcode": "43211",
    "addr:street": "E 11Th Ave",
    "iso:country": "US",
    "sg:address": "519 E 11th Ave",
    "sg:city": "Columbus",
    "sg:classifiers": [
      {
        "category": "Building \u0026 Trades",
        "subcategory": "Construction",
        "type": "Services"
      }
    ],
    "sg:phone": "+1 614 299 2990",
    "sg:postcode": "43211",
    "sg:province": "OH",
    "sg:tags": [
      "commercial"
    ],
    "sg:website": "www.arlingtonconstruction.com",
    "wof:name": "Arlington Construction Inc",
    "wof:placetype": "venue"
  },
  "geometry": {"coordinates":[-82.991832,39.994055],"type":"Point"}
}
