{
  "type": "Feature",
  "properties": {
    "addr:full":"5232 Beechgrove Ave NE Canton OH 44705",
    "addr:postcode":"5232;44705",
    "addr:street":"Beechgrove Ave Ne",
    "iso:country":"US",
    "sg:address":"5232 Beechgrove Ave NE",
    "sg:city":"Canton",
    "sg:classifiers":[
        {
            "category":"Retail",
            "subcategory":"Car Wash",
            "type":"Services"
        }
    ],
    "sg:phone":"+1 330 494 6770",
    "sg:postcode":"44705",
    "sg:province":"OH",
    "sg:tags":[
        "polishing",
        "washing"
    ],
    "wof:name":"Camelot Car Wash",
    "wof:placetype":"venue"
},
  "geometry": {"coordinates":[-81.339962,40.855191],"type":"Point"}
}