{
  "type": "Feature",
  "properties": {
    "addr:full": "1092 Anderson Ferry Rd Cincinnati OH 45238",
    "addr:housenumber": "1092",
    "addr:postcode": "45238",
    "addr:street": "Anderson Ferry Rd",
    "iso:country": "US",
    "sg:address": "1092 Anderson Ferry Rd",
    "sg:city": "Cincinnati",
    "sg:classifiers": [
      {
        "category": "Building \u0026 Trades",
        "subcategory": "Construction",
        "type": "Services"
      }
    ],
    "sg:phone": "+1 513 921 9229",
    "sg:postcode": "45238",
    "sg:province": "OH",
    "sg:tags": [
      "repairing",
      "remodeling",
      "contractor"
    ],
    "wof:name": "Vaughn Construction-Remodeling",
    "wof:placetype": "venue"
  },
  "geometry": {"coordinates":[-84.616361,39.114232],"type":"Point"}
}
