{
  "type": "Feature",
  "properties": {
    "iso:country":"US",
    "sg:address":"4121 Lake Vista Rd",
    "sg:city":"Akron",
    "sg:classifiers":[
        {
            "category":"Real Estate",
            "subcategory":"Real Estate Operator",
            "type":"Services"
        }
    ],
    "sg:phone":"+1 330 645 6576",
    "sg:postcode":"44319",
    "sg:province":"OH",
    "sg:tags":[
        "property",
        "lessor"
    ],
    "wof:name":"Major Properties",
    "wof:placetype":"venue"
},
  "geometry": {"coordinates":[-81.560362,40.989345],"type":"Point"}
}