{
  "type": "Feature",
  "properties": {
    "addr:full": "4288 Miamitrail Ln Cincinnati OH 45252",
    "addr:housenumber": "4288",
    "addr:postcode": "45252",
    "addr:street": "Miamitrail Ln",
    "iso:country": "US",
    "sg:address": "4288 Miamitrail Ln",
    "sg:city": "Cincinnati",
    "sg:classifiers": [
      {
        "category": "Building \u0026 Trades",
        "subcategory": "Pest Control",
        "type": "Services"
      }
    ],
    "sg:phone": "+1 513 741 0122",
    "sg:postcode": "45252",
    "sg:province": "OH",
    "wof:name": "All Pest Control Co",
    "wof:placetype": "venue"
  },
  "geometry": {"coordinates":[-84.631235,39.301085],"type":"Point"}
}
