{
  "type": "Feature",
  "properties": {
    "addr:full":"1422 Woodville Pike Loveland OH 45140",
    "addr:housenumber":"1422",
    "addr:postcode":"45140",
    "addr:street":"Woodville Pike",
    "iso:country":"US",
    "sg:address":"1422 Woodville Pike",
    "sg:city":"Loveland",
    "sg:classifiers":[
        {
            "category":"Real Estate",
            "subcategory":"Real Estate Agent",
            "type":"Services"
        }
    ],
    "sg:phone":"+1 513 722 0842",
    "sg:postcode":"45140",
    "sg:province":"OH",
    "sg:tags":[
        "inspection"
    ],
    "wof:name":"Hawk Home Inspectors LLC",
    "wof:placetype":"venue"
},
  "geometry": {"coordinates":[-84.204707,39.202458],"type":"Point"}
}