{
  "type": "Feature",
  "properties": {
    "addr:full": "744 Huffman Ave Dayton OH 45403",
    "addr:housenumber": "744",
    "addr:postcode": "45403",
    "addr:street": "Huffman Ave",
    "iso:country": "US",
    "sg:address": "744 Huffman Ave",
    "sg:city": "Dayton",
    "sg:classifiers": [
      {
        "category": "Professional",
        "subcategory": "Business Services",
        "type": "Services"
      }
    ],
    "sg:phone": "+1 937 608 1105",
    "sg:postcode": "45403",
    "sg:province": "OH",
    "wof:name": "Emergncy Response Training Ctr",
    "wof:placetype": "venue"
  },
  "geometry": {"coordinates":[-84.155517,39.758531],"type":"Point"}
}
