{
  "type": "Feature",
  "properties": {
    "addr:full":"972 Youngstown Kingsville Rd Vienna OH 44473",
    "addr:housenumber":"972",
    "addr:postcode":"44473",
    "addr:street":"Youngstown Kingsville Rd",
    "iso:country":"US",
    "sg:address":"972 Youngstown Kingsville Rd",
    "sg:city":"Vienna",
    "sg:classifiers":[
        {
            "category":"Professional",
            "type":"Services"
        }
    ],
    "sg:phone":"+1 330 539 9333",
    "sg:postcode":"44473",
    "sg:province":"OH",
    "sg:tags":[
        "establishment"
    ],
    "wof:name":"Liberty Design Corp",
    "wof:placetype":"venue"
},
  "geometry": {"coordinates":[-80.66371100000001,41.246281],"type":"Point"}
}