{
  "type": "Feature",
  "properties": {
    "iso:country":"US",
    "sg:address":"8924 Angola Rd",
    "sg:city":"Holland",
    "sg:classifiers":[
        {
            "category":"Wholesale",
            "subcategory":"Plants",
            "type":"Manufacturing & Wholesale Goods"
        }
    ],
    "sg:phone":"+1 419 866 1518",
    "sg:postcode":"43528",
    "sg:province":"OH",
    "sg:tags":[
        "supply"
    ],
    "wof:name":"Traceys Terrariums",
    "wof:placetype":"venue"
},
  "geometry": {"coordinates":[-83.75491100000001,41.62491],"type":"Point"}
}