{
  "type": "Feature",
  "properties": {
    "addr:full": "8924 Angola Rd Holland OH 43528",
    "addr:housenumber": "8924",
    "addr:postcode": "43528",
    "addr:street": "Angola Rd",
    "iso:country": "US",
    "sg:address": "8924 Angola Rd",
    "sg:city": "Holland",
    "sg:classifiers": [
      {
        "category": "Wholesale",
        "subcategory": "Plants",
        "type": "Manufacturing \u0026 Wholesale Goods"
      }
    ],
    "sg:phone": "+1 419 866 1518",
    "sg:postcode": "43528",
    "sg:province": "OH",
    "sg:tags": [
      "supply"
    ],
    "wof:name": "Traceys Terrariums",
    "wof:placetype": "venue"
  },
  "geometry": {"coordinates":[-83.754911,41.62491],"type":"Point"}
}
