{
  "type": "Feature",
  "properties": {
    "addr:full": "5766 Westbourne Ave Columbus OH 43213",
    "addr:housenumber": "5766",
    "addr:postcode": "43213",
    "addr:street": "Westbourne Ave",
    "iso:country": "US",
    "sg:address": "5766 Westbourne Ave",
    "sg:city": "Columbus",
    "sg:classifiers": [
      {
        "category": "Building \u0026 Trades",
        "subcategory": "Construction",
        "type": "Services"
      }
    ],
    "sg:phone": "+1 614 751 8244",
    "sg:postcode": "43213",
    "sg:province": "OH",
    "sg:tags": [
      "concrete",
      "contractor"
    ],
    "wof:name": "A \u0026 D Concrete Corp",
    "wof:placetype": "venue"
  },
  "geometry": {"coordinates":[-82.843249,39.984062],"type":"Point"}
}
