{
  "type": "Feature",
  "properties": {
    "iso:country":"US",
    "sg:address":"22376 Lorain Rd",
    "sg:city":"Cleveland",
    "sg:classifiers":[
        {
            "category":"Professional",
            "subcategory":"Business Services",
            "type":"Services"
        }
    ],
    "sg:phone":"+1 440 777 4434",
    "sg:postcode":"44126",
    "sg:province":"OH",
    "sg:tags":[
        "interior",
        "consultant",
        "design",
        "decorator"
    ],
    "wof:name":"Pegasus Interiors",
    "wof:placetype":"venue"
},
  "geometry": {"coordinates":[-81.86795499999999,41.440344],"type":"Point"}
}