{
  "type": "Feature",
  "properties": {
    "addr:full": "8900 Evergreen Dr Cleveland OH 44129",
    "addr:housenumber": "8900",
    "addr:postcode": "44129",
    "addr:street": "Evergreen Dr",
    "iso:country": "US",
    "sg:address": "8900 Evergreen Dr",
    "sg:city": "Cleveland",
    "sg:classifiers": [
      {
        "category": "Health Services",
        "subcategory": "Health Practitioner",
        "type": "Services"
      }
    ],
    "sg:phone": "+1 440 886 2670",
    "sg:postcode": "44129",
    "sg:province": "OH",
    "sg:tags": [
      "psychologist"
    ],
    "wof:name": "Herbert S Caron",
    "wof:placetype": "venue"
  },
  "geometry": {"coordinates":[-81.746121,41.407886],"type":"Point"}
}
