{
  "type": "Feature",
  "properties": {
    "iso:country":"US",
    "sg:address":"311 E 6th St",
    "sg:city":"Marysville",
    "sg:classifiers":[
        {
            "category":"Organizations",
            "subcategory":"Religious Organization",
            "type":"Services"
        }
    ],
    "sg:phone":"+1 937 642 1616",
    "sg:postcode":"43040",
    "sg:province":"OH",
    "sg:tags":[
        "church"
    ],
    "sg:website":"www.trinitymarysville.org",
    "wof:name":"Trinity Lutheran Church",
    "wof:placetype":"venue"
},
  "geometry": {"coordinates":[-83.364467,40.235067],"type":"Point"}
}