{
  "type": "Feature",
  "properties": {
    "addr:full": "203 E Main St Bradford OH 45308",
    "addr:housenumber": "203",
    "addr:postcode": "45308",
    "addr:street": "E Main St",
    "iso:country": "US",
    "sg:address": "203 E Main St",
    "sg:city": "Bradford",
    "sg:classifiers": [
      {
        "category": "Manufacturing",
        "subcategory": "Apparel",
        "type": "Manufacturing \u0026 Wholesale Goods"
      }
    ],
    "sg:phone": "+1 937 448 2615",
    "sg:postcode": "45308",
    "sg:province": "OH",
    "sg:tags": [
      "emblem"
    ],
    "sg:website": "www.delong-sportswear.com",
    "wof:name": "De Long Sportswear",
    "wof:placetype": "venue"
  },
  "geometry": {"coordinates":[-84.429065,40.13183],"type":"Point"}
}
