{
  "type": "Feature",
  "properties": {
    "addr:full":"6632 S State Rte 48 Maineville OH 45039",
    "addr:housenumber":"6632",
    "addr:postcode":"45039",
    "addr:street":"S State Rte 48",
    "iso:country":"US",
    "sg:address":"6632 S State Rte 48",
    "sg:city":"Maineville",
    "sg:classifiers":[
        {
            "category":"Shopping",
            "subcategory":"Pharmacy",
            "type":"Retail Goods"
        }
    ],
    "sg:phone":"+1 513 697 4881",
    "sg:postcode":"45039",
    "sg:province":"OH",
    "sg:website":"www.cvs.com",
    "wof:name":"CVS Pharmacy",
    "wof:placetype":"venue"
},
  "geometry": {"coordinates":[-84.219414,39.337493],"type":"Point"}
}