{
  "type": "Feature",
  "properties": {
    "iso:country":"US",
    "sg:address":"3966 Warren-Sharon Rd",
    "sg:city":"Vienna",
    "sg:classifiers":[
        {
            "category":"Retail",
            "subcategory":"Funeral Services",
            "type":"Services"
        }
    ],
    "sg:phone":"+1 330 856 4695",
    "sg:postcode":"44473",
    "sg:province":"OH",
    "sg:tags":[
        "director"
    ],
    "wof:name":"Selby-Cole Funeral Home",
    "wof:placetype":"venue"
},
  "geometry": {"coordinates":[-80.681983,41.238009],"type":"Point"}
}