{
  "type": "Feature",
  "properties": {
    "addr:full":"291 E Market St Akron OH 44308",
    "addr:housenumber":"291",
    "addr:postcode":"44308",
    "addr:street":"E Market St",
    "iso:country":"US",
    "sg:address":"291 E Market St",
    "sg:city":"Akron",
    "sg:classifiers":[
        {
            "category":"Retail",
            "subcategory":"Self-service Laundry",
            "type":"Services"
        }
    ],
    "sg:phone":"+1 330 535 3002",
    "sg:postcode":"44308",
    "sg:province":"OH",
    "wof:name":"University Laundry & Dry Clean",
    "wof:placetype":"venue"
},
  "geometry": {"coordinates":[-81.50907599999999,41.082334],"type":"Point"}
}