{
  "type": "Feature",
  "properties": {
    "iso:country":"US",
    "sg:address":"412 Rosewood Ave",
    "sg:city":"Findlay",
    "sg:classifiers":[
        {
            "category":"Wholesale",
            "subcategory":"Vending Machines",
            "type":"Manufacturing & Wholesale Goods"
        }
    ],
    "sg:phone":"+1 419 422 7013",
    "sg:postcode":"45840",
    "sg:province":"OH",
    "sg:tags":[
        "operator"
    ],
    "wof:name":"Candy Man Vending",
    "wof:placetype":"venue"
},
  "geometry": {"coordinates":[-83.656369,41.069259],"type":"Point"}
}