{
  "type": "Feature",
  "properties": {
    "addr:full":"20615 Sterling Way Strongsville OH 44149",
    "addr:housenumber":"20615",
    "addr:postcode":"44149",
    "addr:street":"Sterling Way",
    "iso:country":"US",
    "sg:address":"20615 Sterling Way",
    "sg:city":"Strongsville",
    "sg:classifiers":[
        {
            "category":"Real Estate",
            "subcategory":"Real Estate Agent",
            "type":"Services"
        }
    ],
    "sg:phone":"+1 440 846 1658",
    "sg:postcode":"44149",
    "sg:province":"OH",
    "wof:name":"21st Century Sales & Marketing",
    "wof:placetype":"venue"
},
  "geometry": {"coordinates":[-81.853278,41.306204],"type":"Point"}
}