{
  "type": "Feature",
  "properties": {
    "addr:full": "5880 Mahoning Ave Youngstown OH 44515",
    "addr:housenumber": "5880",
    "addr:postcode": "44515",
    "addr:street": "Mahoning Ave",
    "iso:country": "US",
    "sg:address": "5880 Mahoning Ave",
    "sg:city": "Youngstown",
    "sg:classifiers": [
      {
        "category": "Wholesale",
        "subcategory": "Sporting Goods",
        "type": "Manufacturing \u0026 Wholesale Goods"
      }
    ],
    "sg:phone": "+1 330 793 2222",
    "sg:postcode": "44515",
    "sg:province": "OH",
    "sg:tags": [
      "equipment",
      "pool",
      "swimming"
    ],
    "wof:name": "R-Ski Pools \u0026 Golf",
    "wof:placetype": "venue"
  },
  "geometry": {"coordinates":[-80.776919,41.099664],"type":"Point"}
}
