{
  "type": "Feature",
  "properties": {
    "iso:country":"US",
    "sg:address":"5880 Mahoning Ave",
    "sg:city":"Youngstown",
    "sg:classifiers":[
        {
            "category":"Wholesale",
            "subcategory":"Sporting Goods",
            "type":"Manufacturing & Wholesale Goods"
        }
    ],
    "sg:phone":"+1 330 793 2222",
    "sg:postcode":"44515",
    "sg:province":"OH",
    "sg:tags":[
        "equipment",
        "pool",
        "swimming"
    ],
    "wof:name":"R-Ski Pools & Golf",
    "wof:placetype":"venue"
},
  "geometry": {"coordinates":[-80.77691900000001,41.099664],"type":"Point"}
}