{
  "type": "Feature",
  "properties": {
    "addr:full": "2427 Portage Path Bellbrook OH 45305",
    "addr:housenumber": "2427",
    "addr:postcode": "45305",
    "addr:street": "Portage Path",
    "iso:country": "US",
    "sg:address": "2427 Portage Path",
    "sg:city": "Bellbrook",
    "sg:classifiers": [
      {
        "category": "Organizations",
        "subcategory": "Religious Organization",
        "type": "Services"
      }
    ],
    "sg:phone": "+1 937 848 2733",
    "sg:postcode": "45305",
    "sg:province": "OH",
    "sg:tags": [
      "clergy"
    ],
    "wof:name": "Ronald A Mueller",
    "wof:placetype": "venue"
  },
  "geometry": {"coordinates":[-84.093965,39.628418],"type":"Point"}
}
