{
  "type": "Feature",
  "properties": {
    "addr:full":"1607 State Rte 28 Loveland OH 45140",
    "addr:housenumber":"1607",
    "addr:postcode":"45140",
    "addr:street":"State Rte 28",
    "iso:country":"US",
    "sg:address":"1607 State Rte 28",
    "sg:city":"Loveland",
    "sg:classifiers":[
        {
            "category":"Building & Trades",
            "subcategory":"Construction",
            "type":"Services"
        }
    ],
    "sg:phone":"+1 513 722 1964",
    "sg:postcode":"45140",
    "sg:province":"OH",
    "sg:tags":[
        "carpentry",
        "contractor"
    ],
    "wof:name":"Patricia S Ross",
    "wof:placetype":"venue"
},
  "geometry": {"coordinates":[-84.18898299999999,39.221517],"type":"Point"}
}