{
  "type": "Feature",
  "properties": {
    "addr:full": "250 E 5th St Cincinnati OH 45202",
    "addr:housenumber": "250",
    "addr:postcode": "45202",
    "addr:street": "E 5Th St",
    "iso:country": "US",
    "sg:address": "250 E 5th St",
    "sg:city": "Cincinnati",
    "sg:classifiers": [
      {
        "category": "Food \u0026 Beverages",
        "subcategory": "Groceries \u0026 Convenience Stores",
        "type": "Retail Goods"
      }
    ],
    "sg:phone": "+1 513 723 0999",
    "sg:postcode": "45202",
    "sg:province": "OH",
    "sg:tags": [
      "grocer"
    ],
    "wof:name": "Alliance Rock Tenn",
    "wof:placetype": "venue"
  },
  "geometry": {"coordinates":[-84.508324,39.101923],"type":"Point"}
}
