{
  "type": "Feature",
  "properties": {
    "iso:country":"US",
    "sg:address":"250 E 5th St",
    "sg:city":"Cincinnati",
    "sg:classifiers":[
        {
            "category":"Food & Beverages",
            "subcategory":"Groceries & Convenience Stores",
            "type":"Retail Goods"
        }
    ],
    "sg:phone":"+1 513 723 0999",
    "sg:postcode":"45202",
    "sg:province":"OH",
    "sg:tags":[
        "grocer"
    ],
    "wof:name":"Alliance Rock Tenn",
    "wof:placetype":"venue"
},
  "geometry": {"coordinates":[-84.508324,39.101923],"type":"Point"}
}