{
  "type": "Feature",
  "properties": {
    "addr:full":"4807 Chalet Dr Cincinnati OH 45217",
    "addr:housenumber":"4807",
    "addr:postcode":"45217",
    "addr:street":"Chalet Dr",
    "iso:country":"US",
    "sg:address":"4807 Chalet Dr",
    "sg:city":"Cincinnati",
    "sg:classifiers":[
        {
            "category":"Building & Trades",
            "subcategory":"Construction",
            "type":"Services"
        }
    ],
    "sg:phone":"+1 513 242 2000",
    "sg:postcode":"45217",
    "sg:province":"OH",
    "sg:tags":[
        "handyman"
    ],
    "wof:name":"Home Repair Solutions Inc",
    "wof:placetype":"venue"
},
  "geometry": {"coordinates":[-84.48433799999999,39.166187],"type":"Point"}
}