{
  "type": "Feature",
  "properties": {
    "iso:country":"US",
    "sg:address":"5904 E Walnut St",
    "sg:city":"Westerville",
    "sg:classifiers":[
        {
            "category":"Real Estate",
            "subcategory":"Real Estate Agent",
            "type":"Services"
        }
    ],
    "sg:phone":"+1 614 855 5111",
    "sg:postcode":"43081",
    "sg:province":"OH",
    "wof:name":"Taylor Property Investments",
    "wof:placetype":"venue"
},
  "geometry": {"coordinates":[-82.830304,40.113721],"type":"Point"}
}