{
  "type": "Feature",
  "properties": {
    "iso:country":"US",
    "sg:address":"24383 Yearsley Rd",
    "sg:city":"Marysville",
    "sg:classifiers":[
        {
            "category":"Building & Trades",
            "subcategory":"Cleaning & Sanitation",
            "type":"Services"
        }
    ],
    "sg:phone":"+1 937 246 3271",
    "sg:postcode":"43040",
    "sg:province":"OH",
    "sg:tags":[
        "janitor"
    ],
    "wof:name":"Rausch Maintenance Inc",
    "wof:placetype":"venue"
},
  "geometry": {"coordinates":[-83.41770200000001,40.355508],"type":"Point"}
}