{
  "type": "Feature",
  "properties": {
    "addr:full": "24383 Yearsley Rd Marysville OH 43040",
    "addr:housenumber": "24383",
    "addr:postcode": "43040",
    "addr:street": "Yearsley Rd",
    "iso:country": "US",
    "sg:address": "24383 Yearsley Rd",
    "sg:city": "Marysville",
    "sg:classifiers": [
      {
        "category": "Building \u0026 Trades",
        "subcategory": "Cleaning \u0026 Sanitation",
        "type": "Services"
      }
    ],
    "sg:phone": "+1 937 246 3271",
    "sg:postcode": "43040",
    "sg:province": "OH",
    "sg:tags": [
      "janitor"
    ],
    "wof:name": "Rausch Maintenance Inc",
    "wof:placetype": "venue"
  },
  "geometry": {"coordinates":[-83.417702,40.355508],"type":"Point"}
}
