{
  "type": "Feature",
  "properties": {
    "addr:full":"892 Neville Penn Schoolhou Rd Felicity OH 45120",
    "addr:housenumber":"892",
    "addr:postcode":"45120",
    "addr:street":"Neville Penn Schoolhou Rd",
    "iso:country":"US",
    "sg:address":"892 Neville Penn Schoolhou Rd",
    "sg:city":"Felicity",
    "sg:classifiers":[
        {
            "category":"Manufacturing",
            "subcategory":"Rubber & Plastics",
            "type":"Manufacturing & Wholesale Goods"
        }
    ],
    "sg:phone":"+1 513 876 2376",
    "sg:postcode":"45120",
    "sg:province":"OH",
    "wof:name":"Rigdon Electric & Molding",
    "wof:placetype":"venue"
},
  "geometry": {"coordinates":[-84.145878,38.844168],"type":"Point"}
}