{
  "type": "Feature",
  "properties": {
    "addr:full":"4631 Linden Ave Dayton OH 45432",
    "addr:housenumber":"4631",
    "addr:postcode":"45432",
    "addr:street":"Linden Ave",
    "iso:country":"US",
    "sg:address":"4631 Linden Ave",
    "sg:city":"Dayton",
    "sg:classifiers":[
        {
            "category":"Retail",
            "subcategory":"Auto Repair",
            "type":"Services"
        }
    ],
    "sg:phone":"+1 937 256 4163",
    "sg:postcode":"45432",
    "sg:province":"OH",
    "sg:tags":[
        "repairing",
        "automobile"
    ],
    "wof:name":"Hudson's Automotive Svc",
    "wof:placetype":"venue"
},
  "geometry": {"coordinates":[-84.110528,39.74207],"type":"Point"}
}