{
  "type": "Feature",
  "properties": {
    "iso:country":"US",
    "sg:address":"9733 Brown Ave NW",
    "sg:city":"Greentown",
    "sg:classifiers":[
        {
            "category":"Retail",
            "subcategory":"Auto Repair",
            "type":"Services"
        }
    ],
    "sg:phone":"+1 330 494 2165",
    "sg:postcode":"44685",
    "sg:province":"OH",
    "sg:tags":[
        "repairing",
        "automobile"
    ],
    "wof:name":"Engine Co No 9 Inc",
    "wof:placetype":"venue"
},
  "geometry": {"coordinates":[-81.40113599999999,40.928288],"type":"Point"}
}