{
  "type": "Feature",
  "properties": {
    "addr:full":"864 Cove Ct Willoughby OH 44095",
    "addr:housenumber":"864",
    "addr:postcode":"44095",
    "addr:street":"Cove Ct",
    "iso:country":"US",
    "sg:address":"864 Cove Ct",
    "sg:city":"Willoughby",
    "sg:classifiers":[
        {
            "category":"Building & Trades",
            "subcategory":"Construction",
            "type":"Services"
        }
    ],
    "sg:phone":"+1 440 951 4585",
    "sg:postcode":"44095",
    "sg:province":"OH",
    "sg:tags":[
        "concrete",
        "contractor"
    ],
    "wof:name":"Finomore Concrete Contractors",
    "wof:placetype":"venue"
},
  "geometry": {"coordinates":[-81.424879,41.655642],"type":"Point"}
}