{
  "type": "Feature",
  "properties": {
    "addr:full": "853 Continental Dr Waterville OH 43566",
    "addr:housenumber": "853",
    "addr:postcode": "43566",
    "addr:street": "Continental Dr",
    "iso:country": "US",
    "sg:address": "853 Continental Dr",
    "sg:city": "Waterville",
    "sg:classifiers": [
      {
        "category": "Shopping",
        "type": "Retail Goods"
      }
    ],
    "sg:phone": "+1 419 878 8654",
    "sg:postcode": "43566",
    "sg:province": "OH",
    "sg:tags": [
      "merchandise"
    ],
    "wof:name": "Macs Woodworking \u0026 Crafts",
    "wof:placetype": "venue"
  },
  "geometry": {"coordinates":[-83.72709,41.507269],"type":"Point"}
}
