{
  "type": "Feature",
  "properties": {
    "addr:full": "303 E Main St Port Washington OH 43837",
    "addr:housenumber": "303",
    "addr:postcode": "43837",
    "addr:street": "E Main St",
    "iso:country": "US",
    "sg:address": "303 E Main St",
    "sg:city": "Port Washington",
    "sg:classifiers": [
      {
        "category": "Wholesale",
        "subcategory": "Machinery \u0026 Supplies",
        "type": "Manufacturing \u0026 Wholesale Goods"
      }
    ],
    "sg:phone": "+1 740 498 4695",
    "sg:postcode": "43837",
    "sg:province": "OH",
    "sg:tags": [
      "field",
      "oil"
    ],
    "wof:name": "Ridge Pump \u0026 Supply",
    "wof:placetype": "venue"
  },
  "geometry": {"coordinates":[-81.517748,40.329349],"type":"Point"}
}
