{
  "type": "Feature",
  "properties": {
    "addr:full": "7981 Hills and Dales Rd NW Massillon OH 44646",
    "addr:housenumber": "7981",
    "addr:postcode": "44646",
    "addr:street": "Hills And Dales Rd Nw",
    "iso:country": "US",
    "sg:address": "7981 Hills and Dales Rd NW",
    "sg:city": "Massillon",
    "sg:classifiers": [
      {
        "category": "Health Services",
        "subcategory": "Chiropractor",
        "type": "Services"
      }
    ],
    "sg:phone": "+1 330 832 9200",
    "sg:postcode": "44646",
    "sg:province": "OH",
    "wof:name": "Thompson Gary A DC",
    "wof:placetype": "venue"
  },
  "geometry": {"coordinates":[-81.500861,40.820685],"type":"Point"}
}
