{
  "type": "Feature",
  "properties": {
    "addr:full": "2461 Nill Ave Dayton OH 45420",
    "addr:housenumber": "2461",
    "addr:postcode": "45420",
    "addr:street": "Nill Ave",
    "iso:country": "US",
    "sg:address": "2461 Nill Ave",
    "sg:city": "Dayton",
    "sg:classifiers": [
      {
        "category": "Shopping",
        "subcategory": "Gifts \u0026 Souvenirs",
        "type": "Retail Goods"
      }
    ],
    "sg:phone": "+1 937 252 8233",
    "sg:postcode": "45420",
    "sg:province": "OH",
    "wof:name": "Waterbury Arts \u0026 Gifts LLC",
    "wof:placetype": "venue"
  },
  "geometry": {"coordinates":[-84.147857,39.731991],"type":"Point"}
}
