{
  "type": "Feature",
  "properties": {
    "iso:country":"US",
    "sg:address":"29042 W Brockway Dr",
    "sg:city":"Cleveland",
    "sg:classifiers":[
        {
            "category":"Shopping",
            "subcategory":"Computers & Home Electronics",
            "type":"Retail Goods"
        }
    ],
    "sg:phone":"+1 440 808 0566",
    "sg:postcode":"44145",
    "sg:province":"OH",
    "wof:name":"Directech Solutions Inc",
    "wof:placetype":"venue"
},
  "geometry": {"coordinates":[-81.937347,41.434571],"type":"Point"}
}