{
  "type": "Feature",
  "properties": {
    "iso:country":"US",
    "sg:address":"18 Westville-Lake Rd",
    "sg:city":"Beloit",
    "sg:classifiers":[
        {
            "category":"Autos & Motor Vehicles",
            "subcategory":"Fuel & Gas Station",
            "type":"Retail Goods"
        }
    ],
    "sg:phone":"+1 330 938 6882",
    "sg:postcode":"44609",
    "sg:province":"OH",
    "sg:tags":[
        "oil"
    ],
    "wof:name":"Westville Marathon",
    "wof:placetype":"venue"
},
  "geometry": {"coordinates":[-80.994147,40.897467],"type":"Point"}
}