{
  "type": "Feature",
  "properties": {
    "addr:full":"125 Pelret Industrial Pkwy Berea OH 44017",
    "addr:housenumber":"125",
    "addr:postcode":"44017",
    "addr:street":"Pelret Industrial Pkwy",
    "iso:country":"US",
    "sg:address":"125 Pelret Industrial Pkwy",
    "sg:city":"Berea",
    "sg:classifiers":[
        {
            "category":"Building & Trades",
            "subcategory":"Electrical",
            "type":"Services"
        },
        {
            "category":"Building & Trades",
            "subcategory":"Construction",
            "type":"Services"
        }
    ],
    "sg:phone":"+1 440 891 0465",
    "sg:postcode":"44017",
    "sg:province":"OH",
    "sg:tags":[
        "cable",
        "phone",
        "system",
        "contractor",
        "equipment",
        "computer",
        "rooms",
        "line"
    ],
    "sg:website":"www.icns-interconnect.com",
    "wof:name":"Interconnect Cabling Inc",
    "wof:placetype":"venue"
},
  "geometry": {"coordinates":[-81.886465,41.373167],"type":"Point"}
}