{
  "type": "Feature",
  "properties": {
    "addr:full":"6708 Loop Rd Dayton OH 45459",
    "addr:housenumber":"6708",
    "addr:postcode":"45459",
    "addr:street":"Loop Rd",
    "iso:country":"US",
    "sg:address":"6708 Loop Rd",
    "sg:city":"Dayton",
    "sg:classifiers":[
        {
            "category":"Shopping",
            "subcategory":"Computers & Home Electronics",
            "type":"Retail Goods"
        }
    ],
    "sg:phone":"+1 937 439 7925",
    "sg:postcode":"45459",
    "sg:province":"OH",
    "sg:tags":[
        "software"
    ],
    "wof:name":"Profound Logic Software Inc",
    "wof:placetype":"venue"
},
  "geometry": {"coordinates":[-84.148207,39.643775],"type":"Point"}
}