{
  "type": "Feature",
  "properties": {
    "addr:full": "5775 Perimeter Dr Dublin OH 43017",
    "addr:housenumber": "5775",
    "addr:postcode": "43017",
    "addr:street": "Perimeter Dr",
    "iso:country": "US",
    "sg:address": "5775 Perimeter Dr",
    "sg:city": "Dublin",
    "sg:classifiers": [
      {
        "category": "Professional",
        "subcategory": "Lawyer \u0026 Legal Services",
        "type": "Services"
      }
    ],
    "sg:phone": "+1 614 799 2800",
    "sg:postcode": "43017",
    "sg:province": "OH",
    "sg:tags": [
      "attorney"
    ],
    "sg:website": "www.zandhlpa.com",
    "wof:name": "Zaino \u0026 Humphrey",
    "wof:placetype": "venue"
  },
  "geometry": {"coordinates":[-83.141861,40.102482],"type":"Point"}
}
