{
  "type": "Feature",
  "properties": {
    "iso:country":"US",
    "sg:address":"5775 Perimeter Dr",
    "sg:city":"Dublin",
    "sg:classifiers":[
        {
            "category":"Professional",
            "subcategory":"Lawyer & Legal Services",
            "type":"Services"
        }
    ],
    "sg:phone":"+1 614 799 2800",
    "sg:postcode":"43017",
    "sg:province":"OH",
    "sg:tags":[
        "attorney"
    ],
    "sg:website":"www.zandhlpa.com",
    "wof:name":"Zaino & Humphrey",
    "wof:placetype":"venue"
},
  "geometry": {"coordinates":[-83.14186100000001,40.102482],"type":"Point"}
}