{
  "type": "Feature",
  "properties": {
    "iso:country":"US",
    "sg:address":"1108 Fett Ave",
    "sg:city":"Lima",
    "sg:classifiers":[
        {
            "category":"Professional",
            "subcategory":"Accounting & Tax Preparation",
            "type":"Services"
        }
    ],
    "sg:phone":"+1 419 225 6805",
    "sg:postcode":"45801",
    "sg:province":"OH",
    "sg:tags":[
        "bookkeeping",
        "general"
    ],
    "wof:name":"Affordable Accounting",
    "wof:placetype":"venue"
},
  "geometry": {"coordinates":[-84.06674599999999,40.75576],"type":"Point"}
}