{
  "type": "Feature",
  "properties": {
    "addr:full": "1108 Fett Ave Lima OH 45801",
    "addr:housenumber": "1108",
    "addr:postcode": "45801",
    "addr:street": "Fett Ave",
    "iso:country": "US",
    "sg:address": "1108 Fett Ave",
    "sg:city": "Lima",
    "sg:classifiers": [
      {
        "category": "Professional",
        "subcategory": "Accounting \u0026 Tax Preparation",
        "type": "Services"
      }
    ],
    "sg:phone": "+1 419 225 6805",
    "sg:postcode": "45801",
    "sg:province": "OH",
    "sg:tags": [
      "bookkeeping",
      "general"
    ],
    "wof:name": "Affordable Accounting",
    "wof:placetype": "venue"
  },
  "geometry": {"coordinates":[-84.066746,40.75576],"type":"Point"}
}
