{
  "type": "Feature",
  "properties": {
    "iso:country":"US",
    "sg:address":"805 W Main St",
    "sg:city":"Leipsic",
    "sg:classifiers":[
        {
            "category":"Food & Beverages",
            "subcategory":"Groceries & Convenience Stores",
            "type":"Retail Goods"
        }
    ],
    "sg:phone":"+1 419 943 3920",
    "sg:postcode":"45856",
    "sg:province":"OH",
    "wof:name":"A J's Carry Out",
    "wof:placetype":"venue"
},
  "geometry": {"coordinates":[-83.99730099999999,41.101623],"type":"Point"}
}