{
  "type": "Feature",
  "properties": {
    "addr:full": "805 W Main St Leipsic OH 45856",
    "addr:housenumber": "805",
    "addr:postcode": "45856",
    "addr:street": "W Main St",
    "iso:country": "US",
    "sg:address": "805 W Main St",
    "sg:city": "Leipsic",
    "sg:classifiers": [
      {
        "category": "Food \u0026 Beverages",
        "subcategory": "Groceries \u0026 Convenience Stores",
        "type": "Retail Goods"
      }
    ],
    "sg:phone": "+1 419 943 3920",
    "sg:postcode": "45856",
    "sg:province": "OH",
    "wof:name": "A J's Carry Out",
    "wof:placetype": "venue"
  },
  "geometry": {"coordinates":[-83.997301,41.101623],"type":"Point"}
}
