{
  "type": "Feature",
  "properties": {
    "addr:full": "1125 Ellen Kay Dr Marion OH 43302",
    "addr:housenumber": "1125",
    "addr:postcode": "43302",
    "addr:street": "Ellen Kay Dr",
    "iso:country": "US",
    "sg:address": "1125 Ellen Kay Dr",
    "sg:city": "Marion",
    "sg:classifiers": [
      {
        "category": "Health Services",
        "subcategory": "Clinic",
        "type": "Services"
      }
    ],
    "sg:phone": "+1 740 382 4171",
    "sg:postcode": "43302",
    "sg:province": "OH",
    "sg:tags": [
      "home"
    ],
    "sg:website": "www.americannursingcare.com",
    "wof:name": "American Nursing Care",
    "wof:placetype": "venue"
  },
  "geometry": {"coordinates":[-83.124198,40.568827],"type":"Point"}
}
