{
  "type": "Feature",
  "properties": {
    "addr:full": "12061 Federal Rd Orient OH 43146",
    "addr:housenumber": "12061",
    "addr:postcode": "43146",
    "addr:street": "Federal Rd",
    "iso:country": "US",
    "sg:address": "12061 Federal Rd",
    "sg:city": "Orient",
    "sg:classifiers": [
      {
        "category": "Wholesale",
        "subcategory": "Construction Materials",
        "type": "Manufacturing \u0026 Wholesale Goods"
      }
    ],
    "sg:phone": "+1 740 869 7676",
    "sg:postcode": "43146",
    "sg:province": "OH",
    "sg:tags": [
      "greenhouse"
    ],
    "wof:name": "Cuthbert Greenhouse Inc",
    "wof:placetype": "venue"
  },
  "geometry": {"coordinates":[-83.159416,39.731655],"type":"Point"}
}
