{
  "type": "Feature",
  "properties": {
    "iso:country":"US",
    "sg:address":"12061 Federal Rd",
    "sg:city":"Orient",
    "sg:classifiers":[
        {
            "category":"Wholesale",
            "subcategory":"Construction Materials",
            "type":"Manufacturing & Wholesale Goods"
        }
    ],
    "sg:phone":"+1 740 869 7676",
    "sg:postcode":"43146",
    "sg:province":"OH",
    "sg:tags":[
        "greenhouse"
    ],
    "wof:name":"Cuthbert Greenhouse Inc",
    "wof:placetype":"venue"
},
  "geometry": {"coordinates":[-83.15941599999999,39.731655],"type":"Point"}
}