{
  "type": "Feature",
  "properties": {
    "iso:country":"US",
    "sg:address":"13008 Woodworth Rd",
    "sg:city":"New Springfield",
    "sg:classifiers":[
        {
            "category":"Autos & Motor Vehicles",
            "subcategory":"Auto Supplies",
            "type":"Retail Goods"
        },
        {
            "category":"Wholesale",
            "subcategory":"Auto Parts",
            "type":"Manufacturing & Wholesale Goods"
        }
    ],
    "sg:phone":"+1 330 549 1980",
    "sg:postcode":"44443",
    "sg:province":"OH",
    "sg:tags":[
        "equipment",
        "truck"
    ],
    "wof:name":"Truck Parts Specialists",
    "wof:placetype":"venue"
},
  "geometry": {"coordinates":[-80.62398,40.928909],"type":"Point"}
}