{
  "type": "Feature",
  "properties": {
    "addr:full": "240 2nd St Portsmouth OH 45662",
    "addr:housenumber": "240",
    "addr:postcode": "45662",
    "addr:street": "2Nd St",
    "iso:country": "US",
    "sg:address": "240 2nd St",
    "sg:city": "Portsmouth",
    "sg:classifiers": [
      {
        "category": "Home \u0026 Garden",
        "subcategory": "Garden Supply",
        "type": "Retail Goods"
      }
    ],
    "sg:phone": "+1 740 354 4025",
    "sg:postcode": "45662",
    "sg:province": "OH",
    "wof:name": "Portsmouth Feed \u0026 Supply",
    "wof:placetype": "venue"
  },
  "geometry": {"coordinates":[-83.008563,38.731733],"type":"Point"}
}
