{
  "type": "Feature",
  "properties": {
    "iso:country":"US",
    "sg:address":"240 2nd St",
    "sg:city":"Portsmouth",
    "sg:classifiers":[
        {
            "category":"Home & Garden",
            "subcategory":"Garden Supply",
            "type":"Retail Goods"
        }
    ],
    "sg:phone":"+1 740 354 4025",
    "sg:postcode":"45662",
    "sg:province":"OH",
    "wof:name":"Portsmouth Feed & Supply",
    "wof:placetype":"venue"
},
  "geometry": {"coordinates":[-83.008563,38.731733],"type":"Point"}
}