{
  "type": "Feature",
  "properties": {
    "iso:country":"US",
    "sg:address":"1028 Stevens Blvd",
    "sg:city":"Willoughby",
    "sg:classifiers":[
        {
            "category":"Building & Trades",
            "subcategory":"Construction",
            "type":"Services"
        }
    ],
    "sg:phone":"+1 216 287 7070",
    "sg:postcode":"44095",
    "sg:province":"OH",
    "sg:tags":[
        "house"
    ],
    "wof:name":"Flawless Builders",
    "wof:placetype":"venue"
},
  "geometry": {"coordinates":[-81.449168,41.651849],"type":"Point"}
}