{
  "type": "Feature",
  "properties": {
    "iso:country":"US",
    "sg:address":"21480 Sheldon Rd",
    "sg:city":"Cleveland",
    "sg:classifiers":[
        {
            "category":"Real Estate",
            "subcategory":"Real Estate Operator",
            "type":"Services"
        }
    ],
    "sg:phone":"+1 440 243 8086",
    "sg:postcode":"44142",
    "sg:province":"OH",
    "sg:tags":[
        "building",
        "apartment"
    ],
    "wof:name":"Acadian Apartments",
    "wof:placetype":"venue"
},
  "geometry": {"coordinates":[-81.85990700000001,41.389832],"type":"Point"}
}