{
  "type": "Feature",
  "properties": {
    "iso:country":"US",
    "sg:address":"1630 E Main St",
    "sg:city":"Ottawa",
    "sg:classifiers":[
        {
            "category":"Retail",
            "subcategory":"Auto Repair",
            "type":"Services"
        }
    ],
    "sg:phone":"+1 419 523 3655",
    "sg:postcode":"45875",
    "sg:province":"OH",
    "sg:tags":[
        "wheel",
        "axle",
        "alignment"
    ],
    "wof:name":"Nordhaus Garage",
    "wof:placetype":"venue"
},
  "geometry": {"coordinates":[-84.027801,41.020158],"type":"Point"}
}