{
  "type": "Feature",
  "properties": {
    "addr:full": "284 W Main St Cortland OH 44410",
    "addr:housenumber": "284",
    "addr:postcode": "44410",
    "addr:street": "W Main St",
    "iso:country": "US",
    "sg:address": "284 W Main St",
    "sg:city": "Cortland",
    "sg:classifiers": [
      {
        "category": "Education",
        "subcategory": "Special Training",
        "type": "Public Place"
      }
    ],
    "sg:phone": "+1 330 637 3541",
    "sg:postcode": "44410",
    "sg:province": "OH",
    "sg:tags": [
      "instruction",
      "driving"
    ],
    "wof:name": "Cortland Driving Academy",
    "wof:placetype": "venue"
  },
  "geometry": {"coordinates":[-80.730001,41.330173],"type":"Point"}
}
