{
  "type": "Feature",
  "properties": {
    "iso:country":"US",
    "sg:address":"1881 Swailes Rd",
    "sg:city":"Troy",
    "sg:classifiers":[
        {
            "category":"Building & Trades",
            "subcategory":"Landscaping Services",
            "type":"Services"
        }
    ],
    "sg:phone":"+1 937 335 7526",
    "sg:postcode":"45373",
    "sg:province":"OH",
    "sg:tags":[
        "landscape",
        "contractor"
    ],
    "wof:name":"Fairs Landscpe Svc",
    "wof:placetype":"venue"
},
  "geometry": {"coordinates":[-84.238223,40.010023],"type":"Point"}
}