{
  "type": "Feature",
  "properties": {
    "iso:country":"US",
    "sg:address":"4747 Interstate Dr",
    "sg:city":"Cincinnati",
    "sg:classifiers":[
        {
            "category":"Wholesale",
            "subcategory":"Auto Parts",
            "type":"Manufacturing & Wholesale Goods"
        }
    ],
    "sg:phone":"+1 513 874 0100",
    "sg:postcode":"45246",
    "sg:province":"OH",
    "sg:tags":[
        "automobile",
        "supply"
    ],
    "wof:name":"Wilcox Autoparts",
    "wof:placetype":"venue"
},
  "geometry": {"coordinates":[-84.468029,39.308619],"type":"Point"}
}