{
  "type": "Feature",
  "properties": {
    "addr:full": "931 S Front St Columbus OH 43206",
    "addr:housenumber": "931",
    "addr:postcode": "43206",
    "addr:street": "S Front St",
    "iso:country": "US",
    "sg:address": "931 S Front St",
    "sg:city": "Columbus",
    "sg:classifiers": [
      {
        "category": "Professional",
        "subcategory": "Lawyer \u0026 Legal Services",
        "type": "Services"
      }
    ],
    "sg:phone": "+1 614 449 8282",
    "sg:postcode": "43206",
    "sg:province": "OH",
    "sg:tags": [
      "attorney"
    ],
    "wof:name": "Joseph \u0026 Joseph PA",
    "wof:placetype": "venue"
  },
  "geometry": {"coordinates":[-82.998041,39.940987],"type":"Point"}
}
