{
  "type": "Feature",
  "properties": {
    "addr:full": "1502 S Raccoon Rd Youngstown OH 44515",
    "addr:housenumber": "1502",
    "addr:postcode": "44515",
    "addr:street": "S Raccoon Rd",
    "iso:country": "US",
    "sg:address": "1502 S Raccoon Rd",
    "sg:city": "Youngstown",
    "sg:classifiers": [
      {
        "category": "Restaurant",
        "type": "Food \u0026 Drink"
      }
    ],
    "sg:menulink": "http://www.allmenus.com/oh/austintown/84404-papa-johns-pizza/menu/",
    "sg:phone": "+1 330 793 3400",
    "sg:postcode": "44515",
    "sg:province": "OH",
    "sg:tags": [
      "american",
      "pizza"
    ],
    "wof:name": "Papa John's Pizza",
    "wof:placetype": "venue"
  },
  "geometry": {"coordinates":[-80.732309,41.085543],"type":"Point"}
}
