{
  "type": "Feature",
  "properties": {
    "iso:country":"US",
    "sg:address":"509 N Park St",
    "sg:city":"Bellefontaine",
    "sg:classifiers":[
        {
            "category":"Education",
            "subcategory":"School",
            "type":"Public Place"
        }
    ],
    "sg:phone":"+1 937 593 9010",
    "sg:postcode":"43311",
    "sg:province":"OH",
    "sg:website":"www.bellefontaine.k12.oh.us",
    "wof:name":"Bellefontaine Middle School",
    "wof:placetype":"venue"
},
  "geometry": {"coordinates":[-83.755216,40.367991],"type":"Point"}
}