{
  "type": "Feature",
  "properties": {
    "iso:country":"US",
    "sg:address":"2355 Andover Rd",
    "sg:city":"Columbus",
    "sg:classifiers":[
        {
            "category":"Real Estate",
            "subcategory":"Real Estate Operator",
            "type":"Services"
        }
    ],
    "sg:phone":"+1 614 488 5128",
    "sg:postcode":"43221",
    "sg:province":"OH",
    "sg:tags":[
        "building",
        "apartment"
    ],
    "wof:name":"Robert Owens Co",
    "wof:placetype":"venue"
},
  "geometry": {"coordinates":[-83.06063899999999,40.004475],"type":"Point"}
}