{
  "type": "Feature",
  "properties": {
    "addr:full": "2355 Andover Rd Columbus OH 43221",
    "addr:housenumber": "2355",
    "addr:postcode": "43221",
    "addr:street": "Andover Rd",
    "iso:country": "US",
    "sg:address": "2355 Andover Rd",
    "sg:city": "Columbus",
    "sg:classifiers": [
      {
        "category": "Real Estate",
        "subcategory": "Real Estate Operator",
        "type": "Services"
      }
    ],
    "sg:phone": "+1 614 488 5128",
    "sg:postcode": "43221",
    "sg:province": "OH",
    "sg:tags": [
      "building",
      "apartment"
    ],
    "wof:name": "Robert Owens Co",
    "wof:placetype": "venue"
  },
  "geometry": {"coordinates":[-83.060639,40.004475],"type":"Point"}
}
