{
  "type": "Feature",
  "properties": {
    "iso:country":"US",
    "sg:address":"700 S 3rd St",
    "sg:city":"Tipp City",
    "sg:classifiers":[
        {
            "category":"Sports & Exercise",
            "subcategory":"Gym",
            "type":"Entertainment"
        }
    ],
    "sg:phone":"+1 937 667 7772",
    "sg:postcode":"45371",
    "sg:province":"OH",
    "sg:tags":[
        "club",
        "health",
        "studio",
        "gymnasium"
    ],
    "wof:name":"Curves",
    "wof:placetype":"venue"
},
  "geometry": {"coordinates":[-84.171042,39.952306],"type":"Point"}
}