{
  "type": "Feature",
  "properties": {
    "addr:full": "700 S 3rd St Tipp City OH 45371",
    "addr:housenumber": "700",
    "addr:postcode": "45371",
    "addr:street": "S 3Rd St",
    "iso:country": "US",
    "sg:address": "700 S 3rd St",
    "sg:city": "Tipp City",
    "sg:classifiers": [
      {
        "category": "Sports \u0026 Exercise",
        "subcategory": "Gym",
        "type": "Entertainment"
      }
    ],
    "sg:phone": "+1 937 667 7772",
    "sg:postcode": "45371",
    "sg:province": "OH",
    "sg:tags": [
      "club",
      "health",
      "studio",
      "gymnasium"
    ],
    "wof:name": "Curves",
    "wof:placetype": "venue"
  },
  "geometry": {"coordinates":[-84.171042,39.952306],"type":"Point"}
}
