{
  "type": "Feature",
  "properties": {
    "addr:full":"1041 Findlay Rd Lima OH 45801",
    "addr:housenumber":"1041",
    "addr:postcode":"45801",
    "addr:street":"Findlay Rd",
    "iso:country":"US",
    "sg:address":"1041 Findlay Rd",
    "sg:city":"Lima",
    "sg:classifiers":[
        {
            "category":"Restaurant",
            "type":"Food & Drink"
        }
    ],
    "sg:menulink":"http://www.allmenus.com/oh/bath/134020-subway/menu/",
    "sg:phone":"+1 419 229 4782",
    "sg:postcode":"45801",
    "sg:province":"OH",
    "sg:tags":[
        "american",
        "sandwich"
    ],
    "wof:name":"Subway",
    "wof:placetype":"venue"
},
  "geometry": {"coordinates":[-84.09079,40.753208],"type":"Point"}
}