{
  "type": "Feature",
  "properties": {
    "addr:full": "7581 Broadview Rd Independence OH 44131",
    "addr:housenumber": "7581",
    "addr:postcode": "44131",
    "addr:street": "Broadview Rd",
    "iso:country": "US",
    "sg:address": "7581 Broadview Rd",
    "sg:city": "Independence",
    "sg:classifiers": [
      {
        "category": "Restaurant",
        "type": "Food \u0026 Drink"
      }
    ],
    "sg:menulink": "http://www.allmenus.com/oh/seven-hills/79219-pizza-hut/menu/",
    "sg:phone": "+1 216 524 4444",
    "sg:postcode": "44131",
    "sg:province": "OH",
    "sg:tags": [
      "american",
      "pizza"
    ],
    "wof:name": "Pizza Hut",
    "wof:placetype": "venue"
  },
  "geometry": {"coordinates":[-81.683778,41.359331],"type":"Point"}
}
