{
  "type": "Feature",
  "properties": {
    "iso:country":"US",
    "sg:address":"303 W Rayen Ave",
    "sg:city":"Youngstown",
    "sg:classifiers":[
        {
            "category":"Building & Trades",
            "subcategory":"Construction",
            "type":"Services"
        }
    ],
    "sg:phone":"+1 330 744 4500",
    "sg:postcode":"44502",
    "sg:province":"OH",
    "sg:tags":[
        "general",
        "contractor"
    ],
    "wof:name":"Phase One",
    "wof:placetype":"venue"
},
  "geometry": {"coordinates":[-80.655615,41.106531],"type":"Point"}
}