{
  "type": "Feature",
  "properties": {
    "addr:full":"4990 Wilmington Pike Dayton OH 45440",
    "addr:housenumber":"4990",
    "addr:postcode":"45440",
    "addr:street":"Wilmington Pike",
    "iso:country":"US",
    "sg:address":"4990 Wilmington Pike",
    "sg:city":"Dayton",
    "sg:classifiers":[
        {
            "category":"Recreation",
            "subcategory":"Amusement Park",
            "type":"Entertainment"
        }
    ],
    "sg:phone":"+1 937 434 4911",
    "sg:postcode":"45440",
    "sg:province":"OH",
    "sg:website":"www.gorollandia.com",
    "wof:name":"Magic Castle At Rollandia",
    "wof:placetype":"venue"
},
  "geometry": {"coordinates":[-84.10867399999999,39.667089],"type":"Point"}
}