{
  "type": "Feature",
  "properties": {
    "addr:full":"6114 Madison Rd Cincinnati OH 45227",
    "addr:housenumber":"6114",
    "addr:postcode":"45227",
    "addr:street":"Madison Rd",
    "iso:country":"US",
    "sg:address":"6114 Madison Rd",
    "sg:city":"Cincinnati",
    "sg:classifiers":[
        {
            "category":"Building & Trades",
            "subcategory":"Electrical",
            "type":"Services"
        }
    ],
    "sg:phone":"+1 513 527 4400",
    "sg:postcode":"45227",
    "sg:province":"OH",
    "sg:tags":[
        "security",
        "electrical",
        "system",
        "contractor"
    ],
    "wof:name":"Dial One Gen Electronic SEC",
    "wof:placetype":"venue"
},
  "geometry": {"coordinates":[-84.388077,39.160333],"type":"Point"}
}