{
  "type": "Feature",
  "properties": {
    "addr:full": "72 Indianola Rd Youngstown OH 44512",
    "addr:housenumber": "72",
    "addr:postcode": "44512",
    "addr:street": "Indianola Rd",
    "iso:country": "US",
    "sg:address": "72 Indianola Rd",
    "sg:city": "Youngstown",
    "sg:classifiers": [
      {
        "category": "Personal",
        "subcategory": "Beauty Salon",
        "type": "Services"
      }
    ],
    "sg:phone": "+1 330 782 8350",
    "sg:postcode": "44512",
    "sg:province": "OH",
    "wof:name": "Frank Charles Hairdressers",
    "wof:placetype": "venue"
  },
  "geometry": {"coordinates":[-80.660614,41.046552],"type":"Point"}
}
