{
  "type": "Feature",
  "properties": {
    "iso:country":"US",
    "sg:address":"8271 Fenner Rd",
    "sg:city":"Plymouth",
    "sg:classifiers":[
        {
            "category":"Farming",
            "subcategory":"Livestock Farm",
            "type":"Manufacturing & Wholesale Goods"
        }
    ],
    "sg:phone":"+1 419 687 7011",
    "sg:postcode":"44865",
    "sg:province":"OH",
    "sg:tags":[
        "hog",
        "beef",
        "cattle",
        "chicken",
        "or",
        "feedlot"
    ],
    "wof:name":"Paul Zimmerman",
    "wof:placetype":"venue"
},
  "geometry": {"coordinates":[-82.695798,40.978942],"type":"Point"}
}