{
  "type": "Feature",
  "properties": {
    "addr:full": "8271 Fenner Rd Plymouth OH 44865",
    "addr:housenumber": "8271",
    "addr:postcode": "44865",
    "addr:street": "Fenner Rd",
    "iso:country": "US",
    "sg:address": "8271 Fenner Rd",
    "sg:city": "Plymouth",
    "sg:classifiers": [
      {
        "category": "Farming",
        "subcategory": "Livestock Farm",
        "type": "Manufacturing \u0026 Wholesale Goods"
      }
    ],
    "sg:phone": "+1 419 687 7011",
    "sg:postcode": "44865",
    "sg:province": "OH",
    "sg:tags": [
      "hog",
      "beef",
      "cattle",
      "chicken",
      "or",
      "feedlot"
    ],
    "wof:name": "Paul Zimmerman",
    "wof:placetype": "venue"
  },
  "geometry": {"coordinates":[-82.695798,40.978942],"type":"Point"}
}
