{
  "type": "Feature",
  "properties": {
    "iso:country":"US",
    "sg:address":"573 Wilkes Ln",
    "sg:city":"Cleveland",
    "sg:classifiers":[
        {
            "category":"Health Services",
            "subcategory":"Clinic",
            "type":"Services"
        }
    ],
    "sg:phone":"+1 216 383 5198",
    "sg:postcode":"44143",
    "sg:province":"OH",
    "wof:name":"Health Testing",
    "wof:placetype":"venue"
},
  "geometry": {"coordinates":[-81.519758,41.548034],"type":"Point"}
}