{
  "type": "Feature",
  "properties": {
    "iso:country":"US",
    "sg:address":"725 N Hamilton Rd",
    "sg:city":"Columbus",
    "sg:classifiers":[
        {
            "category":"Government",
            "subcategory":"Office",
            "type":"Public Place"
        }
    ],
    "sg:phone":"+1 614 235 5394",
    "sg:postcode":"43230",
    "sg:province":"OH",
    "sg:tags":[
        "army",
        "reserve"
    ],
    "wof:name":"US Army Reserve",
    "wof:placetype":"venue"
},
  "geometry": {"coordinates":[-82.865178,40.036098],"type":"Point"}
}