{
  "type": "Feature",
  "properties": {
    "iso:country":"US",
    "sg:address":"2047 W 25th St",
    "sg:city":"Cleveland",
    "sg:classifiers":[
        {
            "category":"Banks & Credit Unions",
            "subcategory":"Bank",
            "type":"Services"
        }
    ],
    "sg:phone":"+1 216 574 6112",
    "sg:postcode":"44113",
    "sg:province":"OH",
    "wof:name":"Keybank National Association",
    "wof:placetype":"venue"
},
  "geometry": {"coordinates":[-81.70269399999999,41.483326],"type":"Point"}
}