{
  "type": "Feature",
  "properties": {
    "addr:full":"318 Cleveland Ave NW Canton OH 44702",
    "addr:housenumber":"318",
    "addr:postcode":"44702",
    "addr:street":"Cleveland Ave Nw",
    "iso:country":"US",
    "sg:address":"318 Cleveland Ave NW",
    "sg:city":"Canton",
    "sg:classifiers":[
        {
            "category":"Organizations",
            "subcategory":"Community Association",
            "type":"Services"
        }
    ],
    "sg:phone":"+1 330 454 3111",
    "sg:postcode":"44702",
    "sg:province":"OH",
    "sg:tags":[
        "environmental",
        "org"
    ],
    "wof:name":"Earth Action Parternership Inc",
    "wof:placetype":"venue"
},
  "geometry": {"coordinates":[-81.37576799999999,40.800763],"type":"Point"}
}