{
  "type": "Feature",
  "properties": {
    "iso:country":"US",
    "sg:address":"2775 S Moreland Blvd",
    "sg:city":"Cleveland",
    "sg:classifiers":[
        {
            "category":"Real Estate",
            "subcategory":"Architect",
            "type":"Services"
        }
    ],
    "sg:phone":"+1 216 752 8750",
    "sg:postcode":"44120",
    "sg:province":"OH",
    "sg:website":"www.bialosky.com",
    "wof:name":"Bialosky & Partners Architects",
    "wof:placetype":"venue"
},
  "geometry": {"coordinates":[-81.59036,41.48308],"type":"Point"}
}