{
  "type": "Feature",
  "properties": {
    "iso:country":"US",
    "sg:address":"38642 Maysville-Greendale Rd",
    "sg:city":"Logan",
    "sg:classifiers":[
        {
            "category":"Building & Trades",
            "subcategory":"Construction",
            "type":"Services"
        }
    ],
    "sg:phone":"+1 740 380 1396",
    "sg:postcode":"43138",
    "sg:province":"OH",
    "sg:tags":[
        "excavation",
        "excavating",
        "contractor"
    ],
    "wof:name":"Bryan Kearns Trucking & Excvtg",
    "wof:placetype":"venue"
},
  "geometry": {"coordinates":[-82.30520799999999,39.539295],"type":"Point"}
}