{
  "type": "Feature",
  "properties": {
    "addr:full": "38642 Maysville-Greendale Rd Logan OH 43138",
    "addr:postcode": "38642;43138",
    "addr:street": "Maysville-Greendale Rd",
    "iso:country": "US",
    "sg:address": "38642 Maysville-Greendale Rd",
    "sg:city": "Logan",
    "sg:classifiers": [
      {
        "category": "Building \u0026 Trades",
        "subcategory": "Construction",
        "type": "Services"
      }
    ],
    "sg:phone": "+1 740 380 1396",
    "sg:postcode": "43138",
    "sg:province": "OH",
    "sg:tags": [
      "excavation",
      "excavating",
      "contractor"
    ],
    "wof:name": "Bryan Kearns Trucking \u0026 Excvtg",
    "wof:placetype": "venue"
  },
  "geometry": {"coordinates":[-82.305208,39.539295],"type":"Point"}
}
