{
  "type": "Feature",
  "properties": {
    "addr:full":"775 Saint Andrews Ct Pickerington OH 43147",
    "addr:housenumber":"775",
    "addr:postcode":"43147",
    "addr:street":"Saint Andrews Ct",
    "iso:country":"US",
    "sg:address":"775 Saint Andrews Ct",
    "sg:city":"Pickerington",
    "sg:classifiers":[
        {
            "category":"Recreation",
            "type":"Entertainment"
        }
    ],
    "sg:phone":"+1 614 864 3483",
    "sg:postcode":"43147",
    "sg:province":"OH",
    "sg:tags":[
        "pool",
        "swimming"
    ],
    "wof:name":"Swim Club",
    "wof:placetype":"venue"
},
  "geometry": {"coordinates":[-82.76519500000001,39.901365],"type":"Point"}
}