{
  "type": "Feature",
  "properties": {
    "addr:full":"216 E Main St Sugarcreek OH 44681",
    "addr:housenumber":"216",
    "addr:postcode":"44681",
    "addr:street":"E Main St",
    "iso:country":"US",
    "sg:address":"216 E Main St",
    "sg:city":"Sugarcreek",
    "sg:classifiers":[
        {
            "category":"Home & Garden",
            "subcategory":"Hardware",
            "type":"Retail Goods"
        }
    ],
    "sg:phone":"+1 330 852 4611",
    "sg:postcode":"44681",
    "sg:province":"OH",
    "wof:name":"Sugarcreek Lumber & Hardware",
    "wof:placetype":"venue"
},
  "geometry": {"coordinates":[-81.63923699999999,40.501929],"type":"Point"}
}