{
  "type": "Feature",
  "properties": {
    "addr:full":"218 E Herrick Ave Wellington OH 44090",
    "addr:housenumber":"218",
    "addr:postcode":"44090",
    "addr:street":"E Herrick Ave",
    "iso:country":"US",
    "sg:address":"218 E Herrick Ave",
    "sg:city":"Wellington",
    "sg:classifiers":[
        {
            "category":"Retail",
            "subcategory":"Funeral Services",
            "type":"Services"
        }
    ],
    "sg:phone":"+1 440 647 2626",
    "sg:postcode":"44090",
    "sg:province":"OH",
    "sg:tags":[
        "director"
    ],
    "wof:name":"Cowling Truman Funeral Home",
    "wof:placetype":"venue"
},
  "geometry": {"coordinates":[-82.21380499999999,41.168453],"type":"Point"}
}