{
  "type": "Feature",
  "properties": {
    "iso:country":"US",
    "sg:address":"131 N Mercer Ave",
    "sg:city":"Sharpsville",
    "sg:classifiers":[
        {
            "category":"Organizations",
            "subcategory":"Religious Organization",
            "type":"Services"
        }
    ],
    "sg:phone":"+1 724 962 4441",
    "sg:postcode":"16150",
    "sg:province":"OH",
    "sg:tags":[
        "church"
    ],
    "wof:name":"Sharpsville Historical Society",
    "wof:placetype":"venue"
},
  "geometry": {"coordinates":[-80.47547,41.26642],"type":"Point"}
}