{
  "type": "Feature",
  "properties": {
    "iso:country":"US",
    "sg:address":"3575 E Livingston Ave",
    "sg:city":"Columbus",
    "sg:classifiers":[
        {
            "category":"Retail",
            "subcategory":"Repair Shop",
            "type":"Services"
        }
    ],
    "sg:phone":"+1 614 235 9151",
    "sg:postcode":"43227",
    "sg:province":"OH",
    "sg:tags":[
        "jewelry"
    ],
    "wof:name":"Gold Rush Jewelers",
    "wof:placetype":"venue"
},
  "geometry": {"coordinates":[-82.899381,39.945918],"type":"Point"}
}