{
  "type": "Feature",
  "properties": {
    "addr:full": "31201 Claypool Hollow Rd Mc Arthur OH 45651",
    "addr:postcode": "31201;45651",
    "addr:street": "Claypool Hollow Rd",
    "iso:country": "US",
    "sg:address": "31201 Claypool Hollow Rd",
    "sg:city": "Mc Arthur",
    "sg:classifiers": [
      {
        "category": "Professional",
        "type": "Services"
      }
    ],
    "sg:phone": "+1 740 596 4042",
    "sg:postcode": "45651",
    "sg:province": "OH",
    "sg:tags": [
      "establishment"
    ],
    "wof:name": "Mayerle \u0026 Mayerle",
    "wof:placetype": "venue"
  },
  "geometry": {"coordinates":[-82.626757,39.285316],"type":"Point"}
}
