{
  "type": "Feature",
  "properties": {
    "iso:country":"US",
    "sg:address":"990 Bergholz Rd NE",
    "sg:city":"Mechanicstown",
    "sg:classifiers":[
        {
            "category":"Professional",
            "type":"Services"
        }
    ],
    "sg:phone":"+1 330 738 2423",
    "sg:postcode":"44651",
    "sg:province":"OH",
    "wof:name":"Matthew J Pincura",
    "wof:placetype":"venue"
},
  "geometry": {"coordinates":[-80.95358,40.596581],"type":"Point"}
}