{
  "type": "Feature",
  "properties": {
    "iso:country":"US",
    "sg:address":"3550 Lander Rd",
    "sg:city":"Cleveland",
    "sg:classifiers":[
        {
            "category":"Professional",
            "subcategory":"Management & Consulting",
            "type":"Services"
        }
    ],
    "sg:phone":"+1 216 831 1795",
    "sg:postcode":"44124",
    "sg:province":"OH",
    "sg:tags":[
        "consultant",
        "business"
    ],
    "sg:website":"www.curtiss.com",
    "wof:name":"Loveman Curtiss Inc",
    "wof:placetype":"venue"
},
  "geometry": {"coordinates":[-81.463373,41.463824],"type":"Point"}
}