{
  "type": "Feature",
  "properties": {
    "addr:full": "5955 N Ridge Rd Madison OH 44057",
    "addr:housenumber": "5955",
    "addr:postcode": "44057",
    "addr:street": "N Ridge Rd",
    "iso:country": "US",
    "sg:address": "5955 N Ridge Rd",
    "sg:city": "Madison",
    "sg:classifiers": [
      {
        "category": "Building \u0026 Trades",
        "subcategory": "Construction",
        "type": "Services"
      }
    ],
    "sg:phone": "+1 440 428 3794",
    "sg:postcode": "44057",
    "sg:province": "OH",
    "sg:tags": [
      "home",
      "improvement"
    ],
    "wof:name": "Rich Reynolds Aluminum",
    "wof:placetype": "venue"
  },
  "geometry": {"coordinates":[-81.075672,41.80049],"type":"Point"}
}
