{
  "type": "Feature",
  "properties": {
    "addr:full": "720 Cedar Bark Dr Aurora OH 44202",
    "addr:housenumber": "720",
    "addr:postcode": "44202",
    "addr:street": "Cedar Bark Dr",
    "iso:country": "US",
    "sg:address": "720 Cedar Bark Dr",
    "sg:city": "Aurora",
    "sg:classifiers": [
      {
        "category": "Professional",
        "type": "Services"
      }
    ],
    "sg:phone": "+1 330 995 8700",
    "sg:postcode": "44202",
    "sg:province": "OH",
    "sg:tags": [
      "establishment"
    ],
    "wof:name": "Valentie Inc",
    "wof:placetype": "venue"
  },
  "geometry": {"coordinates":[-81.322876,41.337391],"type":"Point"}
}
