{
  "type": "Feature",
  "properties": {
    "addr:full":"6749 Ottawa Ave Madison OH 44057",
    "addr:housenumber":"6749",
    "addr:postcode":"44057",
    "addr:street":"Ottawa Ave",
    "iso:country":"US",
    "sg:address":"6749 Ottawa Ave",
    "sg:city":"Madison",
    "sg:classifiers":[
        {
            "category":"Building & Trades",
            "subcategory":"Construction",
            "type":"Services"
        }
    ],
    "sg:phone":"+1 440 298 9817",
    "sg:postcode":"44057",
    "sg:province":"OH",
    "sg:tags":[
        "contractor"
    ],
    "wof:name":"Alexander The Great Inc",
    "wof:placetype":"venue"
},
  "geometry": {"coordinates":[-81.046961,41.834058],"type":"Point"}
}