{
  "type": "Feature",
  "properties": {
    "iso:country":"US",
    "sg:address":"15 E Main St",
    "sg:city":"New Concord",
    "sg:classifiers":[
        {
            "category":"Shopping",
            "type":"Retail Goods"
        }
    ],
    "sg:phone":"+1 740 826 0222",
    "sg:postcode":"43762",
    "sg:province":"OH",
    "sg:tags":[
        "telephone",
        "cellular"
    ],
    "wof:name":"Gig-A-Bytes II",
    "wof:placetype":"venue"
},
  "geometry": {"coordinates":[-81.73089299999999,39.993891],"type":"Point"}
}