{
  "type": "Feature",
  "properties": {
    "iso:country":"US",
    "sg:address":"121 N Arch St",
    "sg:city":"Fremont",
    "sg:classifiers":[
        {
            "category":"Professional",
            "subcategory":"Lawyer & Legal Services",
            "type":"Services"
        }
    ],
    "sg:phone":"+1 419 334 8899",
    "sg:postcode":"43420",
    "sg:province":"OH",
    "wof:name":"L S N O-Legal Svcs NW Ohio",
    "wof:placetype":"venue"
},
  "geometry": {"coordinates":[-83.114374,41.347351],"type":"Point"}
}