{
  "type": "Feature",
  "properties": {
    "iso:country":"US",
    "sg:address":"454 Ramsgate Dr",
    "sg:city":"Dayton",
    "sg:classifiers":[
        {
            "category":"Professional",
            "subcategory":"Engineering",
            "type":"Services"
        }
    ],
    "sg:phone":"+1 937 431 1446",
    "sg:postcode":"45430",
    "sg:province":"OH",
    "sg:tags":[
        "engineer"
    ],
    "sg:website":"www.mixtech.com",
    "wof:name":"Mix Tech",
    "wof:placetype":"venue"
},
  "geometry": {"coordinates":[-84.089265,39.704311],"type":"Point"}
}