{
  "type": "Feature",
  "properties": {
    "addr:full":"5899 Mahoning Ave NW Warren OH 44483",
    "addr:housenumber":"5899",
    "addr:postcode":"44483",
    "addr:street":"Mahoning Ave Nw",
    "iso:country":"US",
    "sg:address":"5899 Mahoning Ave NW",
    "sg:city":"Warren",
    "sg:classifiers":[
        {
            "category":"Wholesale",
            "subcategory":"Construction Materials",
            "type":"Manufacturing & Wholesale Goods"
        }
    ],
    "sg:phone":"+1 330 847 7430",
    "sg:postcode":"44483",
    "sg:province":"OH",
    "sg:tags":[
        "fence"
    ],
    "wof:name":"Eagle Fence Co",
    "wof:placetype":"venue"
},
  "geometry": {"coordinates":[-80.85095,41.313547],"type":"Point"}
}