{
  "type": "Feature",
  "properties": {
    "addr:full": "30 N Main St Chagrin Falls OH 44022",
    "addr:housenumber": "30",
    "addr:postcode": "44022",
    "addr:street": "N Main St",
    "iso:country": "US",
    "sg:address": "30 N Main St",
    "sg:city": "Chagrin Falls",
    "sg:classifiers": [
      {
        "category": "Restaurant",
        "type": "Food \u0026 Drink"
      }
    ],
    "sg:phone": "+1 440 247 3232",
    "sg:postcode": "44022",
    "sg:province": "OH",
    "sg:website": "www.ytr.com",
    "wof:name": "Yours Truly Restaurants",
    "wof:placetype": "venue"
  },
  "geometry": {"coordinates":[-81.391502,41.430698],"type":"Point"}
}
