{
  "type": "Feature",
  "properties": {
    "iso:country":"US",
    "sg:address":"702 Fairwood Blvd",
    "sg:city":"Elyria",
    "sg:classifiers":[
        {
            "category":"Professional",
            "type":"Services"
        }
    ],
    "sg:phone":"+1 440 365 3867",
    "sg:postcode":"44035",
    "sg:province":"OH",
    "wof:name":"Your Budget Inc",
    "wof:placetype":"venue"
},
  "geometry": {"coordinates":[-82.075171,41.398473],"type":"Point"}
}