{
  "type": "Feature",
  "properties": {
    "iso:country":"US",
    "sg:address":"4427 Talmadge Rd",
    "sg:city":"Toledo",
    "sg:classifiers":[
        {
            "category":"Personal",
            "type":"Services"
        }
    ],
    "sg:phone":"+1 419 473 2639",
    "sg:postcode":"43623",
    "sg:province":"OH",
    "sg:tags":[
        "therapist",
        "massage"
    ],
    "wof:name":"Body Care Ctr",
    "wof:placetype":"venue"
},
  "geometry": {"coordinates":[-83.644874,41.695377],"type":"Point"}
}