{
  "type": "Feature",
  "properties": {
    "addr:full":"6350 Lake O Springs Ave NW Canton OH 44718",
    "addr:housenumber":"6350",
    "addr:postcode":"44718",
    "addr:street":"Lake O Springs Ave Nw",
    "iso:country":"US",
    "sg:address":"6350 Lake O Springs Ave NW",
    "sg:city":"Canton",
    "sg:classifiers":[
        {
            "category":"Wholesale",
            "subcategory":"Hardware",
            "type":"Manufacturing & Wholesale Goods"
        },
        {
            "category":"Professional",
            "subcategory":"Business Services",
            "type":"Services"
        }
    ],
    "sg:phone":"+1 330 499 3726",
    "sg:postcode":"44718",
    "sg:province":"OH",
    "sg:tags":[
        "plumbing",
        "water",
        "treatment"
    ],
    "wof:name":"Softee Inc",
    "wof:placetype":"venue"
},
  "geometry": {"coordinates":[-81.460674,40.868986],"type":"Point"}
}