{
  "type": "Feature",
  "properties": {
    "addr:full": "9507 US Hwy 250 Milan OH 44846",
    "addr:housenumber": "9507",
    "addr:postcode": "44846",
    "addr:street": "Us Hwy 250",
    "iso:country": "US",
    "sg:address": "9507 US Hwy 250",
    "sg:city": "Milan",
    "sg:classifiers": [
      {
        "category": "Wholesale",
        "subcategory": "Machinery \u0026 Supplies",
        "type": "Manufacturing \u0026 Wholesale Goods"
      }
    ],
    "sg:phone": "+1 419 626 3810",
    "sg:postcode": "44846",
    "sg:province": "OH",
    "sg:tags": [
      "equipment",
      "welding"
    ],
    "sg:website": "www.praxair.com",
    "wof:name": "Praxair",
    "wof:placetype": "venue"
  },
  "geometry": {"coordinates":[-82.628471,41.341336],"type":"Point"}
}
