{
  "type": "Feature",
  "properties": {
    "addr:full":"400 E Erie St Painesville OH 44077",
    "addr:housenumber":"400",
    "addr:postcode":"44077",
    "addr:street":"E Erie St",
    "iso:country":"US",
    "sg:address":"400 E Erie St",
    "sg:city":"Painesville",
    "sg:classifiers":[
        {
            "category":"Building & Trades",
            "subcategory":"Construction",
            "type":"Services"
        }
    ],
    "sg:phone":"+1 440 354 8838",
    "sg:postcode":"44077",
    "sg:province":"OH",
    "sg:tags":[
        "residential"
    ],
    "wof:name":"Graywood Manor LLC",
    "wof:placetype":"venue"
},
  "geometry": {"coordinates":[-81.24281000000001,41.730328],"type":"Point"}
}