{
  "type": "Feature",
  "properties": {
    "iso:country":"US",
    "sg:address":"3476 Fulton Rd",
    "sg:city":"Cleveland",
    "sg:classifiers":[
        {
            "category":"Recreation",
            "type":"Entertainment"
        }
    ],
    "sg:phone":"+1 216 661 2300",
    "sg:postcode":"44109",
    "sg:province":"OH",
    "sg:tags":[
        "parlor",
        "billiard"
    ],
    "wof:name":"Bud-Light Pool League",
    "wof:placetype":"venue"
},
  "geometry": {"coordinates":[-81.71239,41.45918],"type":"Point"}
}