{
  "type": "Feature",
  "properties": {
    "iso:country":"US",
    "sg:address":"415 W Saffell Ave",
    "sg:city":"Sycamore",
    "sg:classifiers":[
        {
            "category":"Building & Trades",
            "subcategory":"Electrical",
            "type":"Services"
        }
    ],
    "sg:phone":"+1 419 927 2442",
    "sg:postcode":"44882",
    "sg:province":"OH",
    "sg:tags":[
        "contractor",
        "electrical",
        "electric",
        "general"
    ],
    "wof:name":"Sauber S A Electrical Contrs",
    "wof:placetype":"venue"
},
  "geometry": {"coordinates":[-83.175145,40.949782],"type":"Point"}
}