{
  "type": "Feature",
  "properties": {
    "addr:full":"5830 Darrow Rd Hudson OH 44236",
    "addr:housenumber":"5830",
    "addr:postcode":"44236",
    "addr:street":"Darrow Rd",
    "iso:country":"US",
    "sg:address":"5830 Darrow Rd",
    "sg:city":"Hudson",
    "sg:classifiers":[
        {
            "category":"Retail",
            "subcategory":"Laundry & Dry Cleaning",
            "type":"Services"
        }
    ],
    "sg:phone":"+1 330 650 2789",
    "sg:postcode":"44236",
    "sg:province":"OH",
    "sg:tags":[
        "cleaners"
    ],
    "wof:name":"Best Cleaners",
    "wof:placetype":"venue"
},
  "geometry": {"coordinates":[-81.440473,41.227701],"type":"Point"}
}