{
  "type": "Feature",
  "properties": {
    "addr:full": "516 E High St Bryan OH 43506",
    "addr:housenumber": "516",
    "addr:postcode": "43506",
    "addr:street": "E High St",
    "iso:country": "US",
    "sg:address": "516 E High St",
    "sg:city": "Bryan",
    "sg:classifiers": [
      {
        "category": "Government",
        "subcategory": "Court House",
        "type": "Public Place"
      }
    ],
    "sg:phone": "+1 419 636 6939",
    "sg:postcode": "43506",
    "sg:province": "OH",
    "sg:tags": [
      "city"
    ],
    "wof:name": "Bryan City Municipal Court",
    "wof:placetype": "venue"
  },
  "geometry": {"coordinates":[-84.544758,41.474555],"type":"Point"}
}
