{
  "type": "Feature",
  "properties": {
    "iso:country":"US",
    "sg:address":"2888 Station Rd",
    "sg:city":"Medina",
    "sg:classifiers":[
        {
            "category":"Building & Trades",
            "subcategory":"Cleaning & Sanitation",
            "type":"Services"
        }
    ],
    "sg:phone":"+1 330 722 1725",
    "sg:postcode":"44256",
    "sg:province":"OH",
    "sg:tags":[
        "fireplace",
        "chimney"
    ],
    "wof:name":"Dave's Clean Sweep Chimney Svc",
    "wof:placetype":"venue"
},
  "geometry": {"coordinates":[-81.95869,41.197953],"type":"Point"}
}