{
  "type": "Feature",
  "properties": {
    "iso:country":"US",
    "sg:address":"9624 Cincinnati Columbus Rd",
    "sg:city":"Cincinnati",
    "sg:classifiers":[
        {
            "category":"Banks & Credit Unions",
            "subcategory":"Bank",
            "type":"Services"
        }
    ],
    "sg:phone":"+1 513 755 6677",
    "sg:postcode":"45241",
    "sg:province":"OH",
    "sg:tags":[
        "mortgage"
    ],
    "wof:name":"A & H Mortgage Services Inc",
    "wof:placetype":"venue"
},
  "geometry": {"coordinates":[-84.380749,39.310227],"type":"Point"}
}