{
  "type": "Feature",
  "properties": {
    "addr:full": "9624 Cincinnati Columbus Rd Cincinnati OH 45241",
    "addr:housenumber": "9624",
    "addr:postcode": "45241",
    "addr:street": "Cincinnati Columbus Rd",
    "iso:country": "US",
    "sg:address": "9624 Cincinnati Columbus Rd",
    "sg:city": "Cincinnati",
    "sg:classifiers": [
      {
        "category": "Banks \u0026 Credit Unions",
        "subcategory": "Bank",
        "type": "Services"
      }
    ],
    "sg:phone": "+1 513 755 6677",
    "sg:postcode": "45241",
    "sg:province": "OH",
    "sg:tags": [
      "mortgage"
    ],
    "wof:name": "A \u0026 H Mortgage Services Inc",
    "wof:placetype": "venue"
  },
  "geometry": {"coordinates":[-84.380749,39.310227],"type":"Point"}
}
