{
  "type": "Feature",
  "properties": {
    "addr:full":"815 Crocker Rd Westlake OH 44145",
    "addr:housenumber":"815",
    "addr:postcode":"44145",
    "addr:street":"Crocker Rd",
    "iso:country":"US",
    "sg:address":"815 Crocker Rd",
    "sg:city":"Westlake",
    "sg:classifiers":[
        {
            "category":"Manufacturing",
            "subcategory":"Rubber & Plastics",
            "type":"Manufacturing & Wholesale Goods"
        }
    ],
    "sg:phone":"+1 440 808 0578",
    "sg:postcode":"44145",
    "sg:province":"OH",
    "sg:tags":[
        "extrusion",
        "molding"
    ],
    "wof:name":"Universal Import/Export LLC",
    "wof:placetype":"venue"
},
  "geometry": {"coordinates":[-81.95077499999999,41.470828],"type":"Point"}
}