{
  "type": "Feature",
  "properties": {
    "addr:full":"1404 E 9th St Cleveland OH 44114",
    "addr:housenumber":"1404",
    "addr:postcode":"44114",
    "addr:street":"E 9Th St",
    "iso:country":"US",
    "sg:address":"1404 E 9th St",
    "sg:city":"Cleveland",
    "sg:classifiers":[
        {
            "category":"Wholesale",
            "subcategory":"Hardware",
            "type":"Manufacturing & Wholesale Goods"
        }
    ],
    "sg:phone":"+1 216 623 1610",
    "sg:postcode":"44114",
    "sg:province":"OH",
    "sg:tags":[
        "representative",
        "precision"
    ],
    "wof:name":"Comvac Inc",
    "wof:placetype":"venue"
},
  "geometry": {"coordinates":[-81.689244,41.502947],"type":"Point"}
}