{
  "type": "Feature",
  "properties": {
    "addr:full": "5717 Bromley Ave Worthington OH 43085",
    "addr:housenumber": "5717",
    "addr:postcode": "43085",
    "addr:street": "Bromley Ave",
    "iso:country": "US",
    "sg:address": "5717 Bromley Ave",
    "sg:city": "Worthington",
    "sg:classifiers": [
      {
        "category": "Building \u0026 Trades",
        "subcategory": "Construction",
        "type": "Services"
      }
    ],
    "sg:phone": "+1 614 436 1872",
    "sg:postcode": "43085",
    "sg:province": "OH",
    "sg:tags": [
      "caulking",
      "contractor"
    ],
    "sg:website": "www.caulku.com",
    "wof:name": "Spal-Tech",
    "wof:placetype": "venue"
  },
  "geometry": {"coordinates":[-83.01714,40.08029],"type":"Point"}
}
