{
  "type": "Feature",
  "properties": {
    "addr:full":"5108 Darrow Rd Hudson OH 44236",
    "addr:housenumber":"5108",
    "addr:postcode":"44236",
    "addr:street":"Darrow Rd",
    "iso:country":"US",
    "sg:address":"5108 Darrow Rd",
    "sg:city":"Hudson",
    "sg:classifiers":[
        {
            "category":"Health Services",
            "subcategory":"Chiropractor",
            "type":"Services"
        }
    ],
    "sg:phone":"+1 330 656 1977",
    "sg:postcode":"44236",
    "sg:province":"OH",
    "wof:name":"Chiropractic Wellness Ctr",
    "wof:placetype":"venue"
},
  "geometry": {"coordinates":[-81.440489,41.205953],"type":"Point"}
}