{
  "type": "Feature",
  "properties": {
    "addr:full": "1777 Mc Kinley Ave Columbus OH 43222",
    "addr:housenumber": "1777",
    "addr:postcode": "43222",
    "addr:street": "Mc Kinley Ave",
    "iso:country": "US",
    "sg:address": "1777 Mc Kinley Ave",
    "sg:city": "Columbus",
    "sg:classifiers": [
      {
        "category": "Manufacturing",
        "subcategory": "Metals",
        "type": "Manufacturing \u0026 Wholesale Goods"
      }
    ],
    "sg:phone": "+1 614 274 7015",
    "sg:postcode": "43222",
    "sg:province": "OH",
    "sg:tags": [
      "steel"
    ],
    "sg:website": "www.edwardssteel.com",
    "wof:name": "Edwards Steel",
    "wof:placetype": "venue"
  },
  "geometry": {"coordinates":[-83.047416,39.964013],"type":"Point"}
}
