{
  "type": "Feature",
  "properties": {
    "iso:country":"US",
    "sg:address":"1777 Mc Kinley Ave",
    "sg:city":"Columbus",
    "sg:classifiers":[
        {
            "category":"Manufacturing",
            "subcategory":"Metals",
            "type":"Manufacturing & Wholesale Goods"
        }
    ],
    "sg:phone":"+1 614 274 7015",
    "sg:postcode":"43222",
    "sg:province":"OH",
    "sg:tags":[
        "steel"
    ],
    "sg:website":"www.edwardssteel.com",
    "wof:name":"Edwards Steel",
    "wof:placetype":"venue"
},
  "geometry": {"coordinates":[-83.047416,39.964013],"type":"Point"}
}