{
  "type": "Feature",
  "properties": {
    "iso:country":"US",
    "sg:address":"300 W 13th St",
    "sg:city":"Lorain",
    "sg:classifiers":[
        {
            "category":"Organizations",
            "subcategory":"Religious Organization",
            "type":"Services"
        }
    ],
    "sg:phone":"+1 440 244 1530",
    "sg:postcode":"44052",
    "sg:province":"OH",
    "wof:name":"Second Baptist Church",
    "wof:placetype":"venue"
},
  "geometry": {"coordinates":[-82.17325599999999,41.457905],"type":"Point"}
}