{
  "type": "Feature",
  "properties": {
    "addr:full":"960 Kenton Ave Marion OH 43302",
    "addr:housenumber":"960",
    "addr:postcode":"43302",
    "addr:street":"Kenton Ave",
    "iso:country":"US",
    "sg:address":"960 Kenton Ave",
    "sg:city":"Marion",
    "sg:classifiers":[
        {
            "category":"Autos & Motor Vehicles",
            "subcategory":"Auto Supplies",
            "type":"Retail Goods"
        }
    ],
    "sg:phone":"+1 740 383 1814",
    "sg:postcode":"43302",
    "sg:province":"OH",
    "sg:tags":[
        "tire"
    ],
    "wof:name":"Logan Tire Sales & Svc",
    "wof:placetype":"venue"
},
  "geometry": {"coordinates":[-83.150211,40.592679],"type":"Point"}
}