{
  "type": "Feature",
  "properties": {
    "addr:full": "19405 Nitra Ave Maple Heights OH 44137",
    "addr:postcode": "19405;44137",
    "addr:street": "Nitra Ave",
    "iso:country": "US",
    "sg:address": "19405 Nitra Ave",
    "sg:city": "Maple Heights",
    "sg:classifiers": [
      {
        "category": "Professional",
        "type": "Services"
      }
    ],
    "sg:phone": "+1 216 581 8629",
    "sg:postcode": "44137",
    "sg:province": "OH",
    "wof:name": "At Your Door Video",
    "wof:placetype": "venue"
  },
  "geometry": {"coordinates":[-81.541878,41.421118],"type":"Point"}
}
