{
  "type": "Feature",
  "properties": {
    "iso:country":"US",
    "sg:address":"754 Neil Ave",
    "sg:city":"Columbus",
    "sg:classifiers":[
        {
            "category":"Building & Trades",
            "subcategory":"Landscaping Services",
            "type":"Services"
        }
    ],
    "sg:phone":"+1 614 221 0580",
    "sg:postcode":"43215",
    "sg:province":"OH",
    "sg:tags":[
        "designer",
        "landscape"
    ],
    "wof:name":"Edsall & Assoc LLC",
    "wof:placetype":"venue"
},
  "geometry": {"coordinates":[-83.010954,39.976721],"type":"Point"}
}