{
  "type": "Feature",
  "properties": {
    "iso:country":"US",
    "sg:address":"22 W Stroop Rd",
    "sg:city":"Dayton",
    "sg:classifiers":[
        {
            "category":"Insurance",
            "subcategory":"Insurance Agent",
            "type":"Services"
        }
    ],
    "sg:phone":"+1 937 298 5443",
    "sg:postcode":"45429",
    "sg:province":"OH",
    "wof:name":"Janelle Sicard Agency",
    "wof:placetype":"venue"
},
  "geometry": {"coordinates":[-84.16968799999999,39.68953],"type":"Point"}
}