{
  "type": "Feature",
  "properties": {
    "addr:full": "75 Public Sq Cleveland OH 44113",
    "addr:housenumber": "75",
    "addr:postcode": "44113",
    "addr:street": "Public Sq",
    "iso:country": "US",
    "sg:address": "75 Public Sq",
    "sg:city": "Cleveland",
    "sg:classifiers": [
      {
        "category": "Professional",
        "subcategory": "Lawyer \u0026 Legal Services",
        "type": "Services"
      }
    ],
    "sg:phone": "+1 216 566 8188",
    "sg:postcode": "44113",
    "sg:province": "OH",
    "sg:tags": [
      "attorney"
    ],
    "wof:name": "Pasalis \u0026 Assoc",
    "wof:placetype": "venue"
  },
  "geometry": {"coordinates":[-81.694492,41.500271],"type":"Point"}
}
