{
  "type": "Feature",
  "properties": {
    "addr:full":"81 Brookwood Ave Hamilton IN 45013",
    "addr:housenumber":"81",
    "addr:postcode":"45013",
    "addr:street":"Brookwood Ave",
    "iso:country":"US",
    "sg:address":"81 Brookwood Ave",
    "sg:city":"Hamilton",
    "sg:classifiers":[
        {
            "category":"Restaurant",
            "type":"Food & Drink"
        }
    ],
    "sg:phone":"+1 513 863 4992",
    "sg:postcode":"45013",
    "sg:province":"IN",
    "wof:name":"Cafe' Ole'",
    "wof:placetype":"venue"
},
  "geometry": {"coordinates":[-84.58971699999999,39.419816],"type":"Point"}
}