{
  "type": "Feature",
  "properties": {
    "addr:full": "21343 State Rte 2 Archbold OH 43502",
    "addr:housenumber": "21343",
    "addr:postcode": "43502",
    "addr:street": "State Rte 2",
    "iso:country": "US",
    "sg:address": "21343 State Rte 2",
    "sg:city": "Archbold",
    "sg:classifiers": [
      {
        "category": "Wholesale",
        "subcategory": "Electrical",
        "type": "Manufacturing \u0026 Wholesale Goods"
      }
    ],
    "sg:phone": "+1 419 445 1800",
    "sg:postcode": "43502",
    "sg:province": "OH",
    "sg:tags": [
      "r",
      "electronic",
      "contractor"
    ],
    "wof:name": "Flex Com",
    "wof:placetype": "venue"
  },
  "geometry": {"coordinates":[-84.268801,41.543221],"type":"Point"}
}
