{
  "type": "Feature",
  "properties": {
    "iso:country":"US",
    "sg:address":"13840 Puritas Ave",
    "sg:city":"Cleveland",
    "sg:classifiers":[
        {
            "category":"Autos & Motor Vehicles",
            "subcategory":"Auto Supplies",
            "type":"Retail Goods"
        }
    ],
    "sg:phone":"+1 216 252 1994",
    "sg:postcode":"44135",
    "sg:province":"OH",
    "sg:tags":[
        "automobile",
        "cap",
        "hub"
    ],
    "wof:name":"Hubcap Heaven & Wheels",
    "wof:placetype":"venue"
},
  "geometry": {"coordinates":[-81.788757,41.433554],"type":"Point"}
}