{
  "type": "Feature",
  "properties": {
    "addr:full": "13840 Puritas Ave Cleveland OH 44135",
    "addr:postcode": "13840;44135",
    "addr:street": "Puritas Ave",
    "iso:country": "US",
    "sg:address": "13840 Puritas Ave",
    "sg:city": "Cleveland",
    "sg:classifiers": [
      {
        "category": "Autos \u0026 Motor Vehicles",
        "subcategory": "Auto Supplies",
        "type": "Retail Goods"
      }
    ],
    "sg:phone": "+1 216 252 1994",
    "sg:postcode": "44135",
    "sg:province": "OH",
    "sg:tags": [
      "automobile",
      "cap",
      "hub"
    ],
    "wof:name": "Hubcap Heaven \u0026 Wheels",
    "wof:placetype": "venue"
  },
  "geometry": {"coordinates":[-81.788757,41.433554],"type":"Point"}
}
