{
  "type": "Feature",
  "properties": {
    "addr:full": "2250 Innis Rd Columbus OH 43224",
    "addr:housenumber": "2250",
    "addr:postcode": "43224",
    "addr:street": "Innis Rd",
    "iso:country": "US",
    "sg:address": "2250 Innis Rd",
    "sg:city": "Columbus",
    "sg:classifiers": [
      {
        "category": "Retail",
        "subcategory": "Auto Repair",
        "type": "Services"
      }
    ],
    "sg:phone": "+1 614 428 4881",
    "sg:postcode": "43224",
    "sg:province": "OH",
    "sg:tags": [
      "body",
      "automobile",
      "painting"
    ],
    "wof:name": "Northern Lights Collision Ctr",
    "wof:placetype": "venue"
  },
  "geometry": {"coordinates":[-82.952922,40.037276],"type":"Point"}
}
