{
  "type": "Feature",
  "properties": {
    "addr:full": "139 Auto Club Dr Dayton OH 45402",
    "addr:housenumber": "139",
    "addr:postcode": "45402",
    "addr:street": "Auto Club Dr",
    "iso:country": "US",
    "sg:address": "139 Auto Club Dr",
    "sg:city": "Dayton",
    "sg:classifiers": [
      {
        "category": "Manufacturing",
        "subcategory": "Motor Vehicles \u0026 Parts",
        "type": "Manufacturing \u0026 Wholesale Goods"
      }
    ],
    "sg:phone": "+1 937 293 2223",
    "sg:postcode": "45402",
    "sg:province": "OH",
    "sg:tags": [
      "automotive"
    ],
    "wof:name": "Miller Industries Inc",
    "wof:placetype": "venue"
  },
  "geometry": {"coordinates":[-84.192225,39.74953],"type":"Point"}
}
