{
  "type": "Feature",
  "properties": {
    "iso:country":"US",
    "sg:address":"139 Auto Club Dr",
    "sg:city":"Dayton",
    "sg:classifiers":[
        {
            "category":"Manufacturing",
            "subcategory":"Motor Vehicles & Parts",
            "type":"Manufacturing & Wholesale Goods"
        }
    ],
    "sg:phone":"+1 937 293 2223",
    "sg:postcode":"45402",
    "sg:province":"OH",
    "sg:tags":[
        "automotive"
    ],
    "wof:name":"Miller Industries Inc",
    "wof:placetype":"venue"
},
  "geometry": {"coordinates":[-84.192225,39.74953],"type":"Point"}
}