{
  "type": "Feature",
  "properties": {
    "addr:full":"106 E Moler St Columbus OH 43207",
    "addr:housenumber":"106",
    "addr:postcode":"43207",
    "addr:street":"E Moler St",
    "iso:country":"US",
    "sg:address":"106 E Moler St",
    "sg:city":"Columbus",
    "sg:classifiers":[
        {
            "category":"Wholesale",
            "subcategory":"Machinery & Supplies",
            "type":"Manufacturing & Wholesale Goods"
        }
    ],
    "sg:phone":"+1 614 449 9040",
    "sg:postcode":"43207",
    "sg:province":"OH",
    "sg:tags":[
        "industrial",
        "equipment",
        "work",
        "clothing",
        "mfg"
    ],
    "sg:website":"www.racequip.com",
    "wof:name":"Racequip Safety Systems",
    "wof:placetype":"venue"
},
  "geometry": {"coordinates":[-82.993414,39.935191],"type":"Point"}
}