{
  "type": "Feature",
  "properties": {
    "addr:full": "104 Liberty St Columbus Grove OH 45830",
    "addr:housenumber": "104",
    "addr:postcode": "45830",
    "addr:street": "Liberty St",
    "iso:country": "US",
    "sg:address": "104 Liberty St",
    "sg:city": "Columbus Grove",
    "sg:classifiers": [
      {
        "category": "Food \u0026 Beverages",
        "subcategory": "Liquor \u0026 Beverages",
        "type": "Retail Goods"
      }
    ],
    "sg:phone": "+1 419 659 2644",
    "sg:postcode": "45830",
    "sg:province": "OH",
    "sg:tags": [
      "alcoholic"
    ],
    "wof:name": "L \u0026 J Party Shop",
    "wof:placetype": "venue"
  },
  "geometry": {"coordinates":[-84.057161,40.920608],"type":"Point"}
}
