{
  "type": "Feature",
  "properties": {
    "iso:country":"US",
    "sg:address":"104 Liberty St",
    "sg:city":"Columbus Grove",
    "sg:classifiers":[
        {
            "category":"Food & Beverages",
            "subcategory":"Liquor & Beverages",
            "type":"Retail Goods"
        }
    ],
    "sg:phone":"+1 419 659 2644",
    "sg:postcode":"45830",
    "sg:province":"OH",
    "sg:tags":[
        "alcoholic"
    ],
    "wof:name":"L & J Party Shop",
    "wof:placetype":"venue"
},
  "geometry": {"coordinates":[-84.05716099999999,40.920608],"type":"Point"}
}