{
  "type": "Feature",
  "properties": {
    "addr:full":"800 Braceville Robinson Rd SW Newton Falls OH 44444",
    "addr:housenumber":"800",
    "addr:postcode":"44444",
    "addr:street":"Braceville Robinson Rd Sw Newton",
    "iso:country":"US",
    "sg:address":"800 Braceville Robinson Rd SW",
    "sg:city":"Newton Falls",
    "sg:classifiers":[
        {
            "category":"Government",
            "subcategory":"Office",
            "type":"Public Place"
        }
    ],
    "sg:phone":"+1 330 872 5502",
    "sg:postcode":"44444",
    "sg:province":"OH",
    "sg:tags":[
        "village"
    ],
    "wof:name":"Braceville Twp Garage",
    "wof:placetype":"venue"
},
  "geometry": {"coordinates":[-80.95807000000001,41.21517],"type":"Point"}
}