{
  "type": "Feature",
  "properties": {
    "addr:full":"1155 Diana Ave Miamisburg OH 45342",
    "addr:housenumber":"1155",
    "addr:postcode":"45342",
    "addr:street":"Diana Ave",
    "iso:country":"US",
    "sg:address":"1155 Diana Ave",
    "sg:city":"Miamisburg",
    "sg:classifiers":[
        {
            "category":"Wholesale",
            "subcategory":"Electrical",
            "type":"Manufacturing & Wholesale Goods"
        }
    ],
    "sg:phone":"+1 937 847 8100",
    "sg:postcode":"45342",
    "sg:province":"OH",
    "sg:tags":[
        "television"
    ],
    "wof:name":"Wavelink",
    "wof:placetype":"venue"
},
  "geometry": {"coordinates":[-84.271441,39.65372],"type":"Point"}
}