{
  "type": "Feature",
  "properties": {
    "addr:full":"135 Ohio Blvd Marietta OH 45750",
    "addr:housenumber":"135",
    "addr:postcode":"45750",
    "addr:street":"Ohio Blvd",
    "iso:country":"US",
    "sg:address":"135 Ohio Blvd",
    "sg:city":"Marietta",
    "sg:classifiers":[
        {
            "category":"Professional",
            "subcategory":"Business Services",
            "type":"Services"
        }
    ],
    "sg:phone":"+1 740 373 3556",
    "sg:postcode":"45750",
    "sg:province":"OH",
    "sg:tags":[
        "sign"
    ],
    "wof:name":"Signs and Mores Inc 24",
    "wof:placetype":"venue"
},
  "geometry": {"coordinates":[-81.48092699999999,39.477015],"type":"Point"}
}