{
  "type": "Feature",
  "properties": {
    "addr:full": "3263 E Pitchin Rd Springfield OH 45502",
    "addr:housenumber": "3263",
    "addr:postcode": "45502",
    "addr:street": "E Pitchin Rd",
    "iso:country": "US",
    "sg:address": "3263 E Pitchin Rd",
    "sg:city": "Springfield",
    "sg:classifiers": [
      {
        "category": "Real Estate",
        "subcategory": "Real Estate Operator",
        "type": "Services"
      }
    ],
    "sg:phone": "+1 937 265 5123",
    "sg:postcode": "45502",
    "sg:province": "OH",
    "sg:tags": [
      "building",
      "nonresidential"
    ],
    "wof:name": "Grimm Properties",
    "wof:placetype": "venue"
  },
  "geometry": {"coordinates":[-83.747641,39.859082],"type":"Point"}
}
