{
  "type": "Feature",
  "properties": {
    "iso:country":"US",
    "sg:address":"8668 Troy Pike",
    "sg:city":"Dayton",
    "sg:classifiers":[
        {
            "category":"Retail",
            "subcategory":"Veterinary Services",
            "type":"Services"
        }
    ],
    "sg:phone":"+1 937 236 8070",
    "sg:postcode":"45424",
    "sg:province":"OH",
    "wof:name":"Linda Adkins Dvm",
    "wof:placetype":"venue"
},
  "geometry": {"coordinates":[-84.136719,39.877544],"type":"Point"}
}