{
  "type": "Feature",
  "properties": {
    "iso:country":"US",
    "sg:address":"1104 N Countyline St",
    "sg:city":"Fostoria",
    "sg:classifiers":[
        {
            "category":"Restaurant",
            "type":"Food & Drink"
        }
    ],
    "sg:menulink":"http://www.allmenus.com/oh/fostoria/164616-wendys/menu/",
    "sg:phone":"+1 419 435 6485",
    "sg:postcode":"44830",
    "sg:province":"OH",
    "sg:tags":[
        "burger",
        "american",
        "soup"
    ],
    "wof:name":"Wendy's",
    "wof:placetype":"venue"
},
  "geometry": {"coordinates":[-83.42096600000001,41.170461],"type":"Point"}
}