{
  "type": "Feature",
  "properties": {
    "addr:full": "1104 N Countyline St Fostoria OH 44830",
    "addr:housenumber": "1104",
    "addr:postcode": "44830",
    "addr:street": "N Countyline St",
    "iso:country": "US",
    "sg:address": "1104 N Countyline St",
    "sg:city": "Fostoria",
    "sg:classifiers": [
      {
        "category": "Restaurant",
        "type": "Food \u0026 Drink"
      }
    ],
    "sg:menulink": "http://www.allmenus.com/oh/fostoria/164616-wendys/menu/",
    "sg:phone": "+1 419 435 6485",
    "sg:postcode": "44830",
    "sg:province": "OH",
    "sg:tags": [
      "burger",
      "american",
      "soup"
    ],
    "wof:name": "Wendy's",
    "wof:placetype": "venue"
  },
  "geometry": {"coordinates":[-83.420966,41.170461],"type":"Point"}
}
