{
  "type": "Feature",
  "properties": {
    "addr:full":"1104 Winchester Rd Galion OH 44833",
    "addr:housenumber":"1104",
    "addr:postcode":"44833",
    "addr:street":"Winchester Rd",
    "iso:country":"US",
    "sg:address":"1104 Winchester Rd",
    "sg:city":"Galion",
    "sg:classifiers":[
        {
            "category":"Building & Trades",
            "subcategory":"Landscaping Services",
            "type":"Services"
        }
    ],
    "sg:phone":"+1 419 468 2795",
    "sg:postcode":"44833",
    "sg:province":"OH",
    "sg:tags":[
        "tree"
    ],
    "wof:name":"Robison Tree Svc",
    "wof:placetype":"venue"
},
  "geometry": {"coordinates":[-82.814981,40.734208],"type":"Point"}
}