{
  "type": "Feature",
  "properties": {
    "addr:full": "302 E Main St Columbus OH 43215",
    "addr:housenumber": "302",
    "addr:postcode": "43215",
    "addr:street": "E Main St",
    "iso:country": "US",
    "sg:address": "302 E Main St",
    "sg:city": "Columbus",
    "sg:classifiers": [
      {
        "category": "Banks \u0026 Credit Unions",
        "subcategory": "Financial Services",
        "type": "Services"
      }
    ],
    "sg:phone": "+1 877 607 8600",
    "sg:postcode": "43215",
    "sg:province": "OH",
    "sg:tags": [
      "loan"
    ],
    "wof:name": "PaymentQuote.com",
    "wof:placetype": "venue"
  },
  "geometry": {"coordinates":[-82.991348,39.957099],"type":"Point"}
}
