{
  "type": "Feature",
  "properties": {
    "iso:country":"US",
    "sg:address":"1650 Gelhot Dr",
    "sg:city":"Fairfield",
    "sg:classifiers":[
        {
            "category":"Building & Trades",
            "subcategory":"Electrical",
            "type":"Services"
        }
    ],
    "sg:phone":"+1 513 772 5123",
    "sg:postcode":"45014",
    "sg:province":"OH",
    "sg:tags":[
        "electric",
        "contractor"
    ],
    "wof:name":"Frebis Electric Co",
    "wof:placetype":"venue"
},
  "geometry": {"coordinates":[-84.564539,39.314251],"type":"Point"}
}