{
  "type": "Feature",
  "properties": {
    "addr:full": "3160 Fulmer Dr Lorain OH 44053",
    "addr:postcode": "3160;44053",
    "addr:street": "Fulmer Dr",
    "iso:country": "US",
    "sg:address": "3160 Fulmer Dr",
    "sg:city": "Lorain",
    "sg:classifiers": [
      {
        "category": "Professional",
        "type": "Services"
      }
    ],
    "sg:phone": "+1 440 989 2731",
    "sg:postcode": "44053",
    "sg:province": "OH",
    "wof:name": "Kimberly Weigl",
    "wof:placetype": "venue"
  },
  "geometry": {"coordinates":[-82.228065,41.441926],"type":"Point"}
}
