{
  "type": "Feature",
  "properties": {
    "iso:country":"US",
    "sg:address":"1170 Carrousel Dr E",
    "sg:city":"Reynoldsburg",
    "sg:classifiers":[
        {
            "category":"Shopping",
            "subcategory":"Florist",
            "type":"Retail Goods"
        }
    ],
    "sg:phone":"+1 614 866 5980",
    "sg:postcode":"43068",
    "sg:province":"OH",
    "wof:name":"Flowers By Fox",
    "wof:placetype":"venue"
},
  "geometry": {"coordinates":[-82.810322,39.959933],"type":"Point"}
}