{
  "type": "Feature",
  "properties": {
    "addr:full": "270 Southern Ave Cincinnati OH 45219",
    "addr:housenumber": "270",
    "addr:postcode": "45219",
    "addr:street": "Southern Ave",
    "iso:country": "US",
    "sg:address": "270 Southern Ave",
    "sg:city": "Cincinnati",
    "sg:classifiers": [
      {
        "category": "Education",
        "subcategory": "School",
        "type": "Public Place"
      }
    ],
    "sg:phone": "+1 513 363 5600",
    "sg:postcode": "45219",
    "sg:province": "OH",
    "sg:tags": [
      "elementary"
    ],
    "sg:website": "http://www.walnuthillseagles.com",
    "wof:name": "Taft Elementary School",
    "wof:placetype": "venue"
  },
  "geometry": {"coordinates":[-84.50589,39.120076],"type":"Point"}
}
