{
  "type": "Feature",
  "properties": {
    "iso:country":"US",
    "sg:address":"270 Southern Ave",
    "sg:city":"Cincinnati",
    "sg:classifiers":[
        {
            "category":"Education",
            "subcategory":"School",
            "type":"Public Place"
        }
    ],
    "sg:phone":"+1 513 363 5600",
    "sg:postcode":"45219",
    "sg:province":"OH",
    "sg:tags":[
        "elementary"
    ],
    "sg:website":"http://www.walnuthillseagles.com",
    "wof:name":"Taft Elementary School",
    "wof:placetype":"venue"
},
  "geometry": {"coordinates":[-84.50588999999999,39.120076],"type":"Point"}
}