{
  "type": "Feature",
  "properties": {
    "addr:full":"1616 Claremont Ave Ashland OH 44805",
    "addr:housenumber":"1616",
    "addr:postcode":"44805",
    "addr:street":"Claremont Ave",
    "iso:country":"US",
    "sg:address":"1616 Claremont Ave",
    "sg:city":"Ashland",
    "sg:classifiers":[
        {
            "category":"Restaurant",
            "type":"Food & Drink"
        }
    ],
    "sg:phone":"+1 419 282 9988",
    "sg:postcode":"44805",
    "sg:province":"OH",
    "sg:tags":[
        "eating"
    ],
    "wof:name":"Ocean Buffet Chinese Rest",
    "wof:placetype":"venue"
},
  "geometry": {"coordinates":[-82.33908,40.852652],"type":"Point"}
}