{
  "type": "Feature",
  "properties": {
    "addr:full": "13246 Doylestown Rd Rittman OH 44270",
    "addr:housenumber": "13246",
    "addr:postcode": "44270",
    "addr:street": "Doylestown Rd",
    "iso:country": "US",
    "sg:address": "13246 Doylestown Rd",
    "sg:city": "Rittman",
    "sg:classifiers": [
      {
        "category": "Building \u0026 Trades",
        "subcategory": "Landscaping Services",
        "type": "Services"
      }
    ],
    "sg:phone": "+1 330 925 1411",
    "sg:postcode": "44270",
    "sg:province": "OH",
    "sg:tags": [
      "lawn",
      "maintenance",
      "grounds"
    ],
    "wof:name": "Forrer Lawn Svc",
    "wof:placetype": "venue"
  },
  "geometry": {"coordinates":[-81.736933,40.97157],"type":"Point"}
}
