{
  "type": "Feature",
  "properties": {
    "addr:full":"8118 Euclid Ave Cleveland OH 44103",
    "addr:housenumber":"8118",
    "addr:postcode":"44103",
    "addr:street":"Euclid Ave",
    "iso:country":"US",
    "sg:address":"8118 Euclid Ave",
    "sg:city":"Cleveland",
    "sg:classifiers":[
        {
            "category":"Restaurant",
            "type":"Food & Drink"
        }
    ],
    "sg:menulink":"http://www.allmenus.com/oh/cleveland/211058-kfc---kentucky-fried-chicken/menu/",
    "sg:phone":"+1 216 791 2600",
    "sg:postcode":"44103",
    "sg:province":"OH",
    "sg:tags":[
        "american",
        "chicken"
    ],
    "wof:name":"KFC - Kentucky Fried Chicken",
    "wof:placetype":"venue"
},
  "geometry": {"coordinates":[-81.631326,41.503705],"type":"Point"}
}