{
  "type": "Feature",
  "properties": {
    "iso:country":"US",
    "sg:address":"17309 Madison Ave",
    "sg:city":"Cleveland",
    "sg:classifiers":[
        {
            "category":"Personal",
            "subcategory":"Beauty Salon",
            "type":"Services"
        }
    ],
    "sg:phone":"+1 216 228 8796",
    "sg:postcode":"44107",
    "sg:province":"OH",
    "wof:name":"Shearly Unique",
    "wof:placetype":"venue"
},
  "geometry": {"coordinates":[-81.818696,41.477506],"type":"Point"}
}