{
  "type": "Feature",
  "properties": {
    "addr:full":"916 E Lincoln Way Minerva OH 44657",
    "addr:housenumber":"916",
    "addr:postcode":"44657",
    "addr:street":"E Lincoln Way",
    "iso:country":"US",
    "sg:address":"916 E Lincoln Way",
    "sg:city":"Minerva",
    "sg:classifiers":[
        {
            "category":"Personal",
            "subcategory":"Beauty Salon",
            "type":"Services"
        }
    ],
    "sg:phone":"+1 330 868 9871",
    "sg:postcode":"44657",
    "sg:province":"OH",
    "wof:name":"Hair By Angie",
    "wof:placetype":"venue"
},
  "geometry": {"coordinates":[-81.090125,40.737055],"type":"Point"}
}