{
  "type": "Feature",
  "properties": {
    "addr:full":"3031 Center Rd Brunswick OH 44212",
    "addr:housenumber":"3031",
    "addr:postcode":"44212",
    "addr:street":"Center Rd",
    "iso:country":"US",
    "sg:address":"3031 Center Rd",
    "sg:city":"Brunswick",
    "sg:classifiers":[
        {
            "category":"Autos & Motor Vehicles",
            "subcategory":"Automobile Sales",
            "type":"Retail Goods"
        }
    ],
    "sg:phone":"+1 330 273 3300",
    "sg:postcode":"44212",
    "sg:province":"OH",
    "sg:tags":[
        "car",
        "dealer"
    ],
    "sg:website":"www.brunswickautomart.com",
    "wof:name":"Brunswick Auto Mart",
    "wof:placetype":"venue"
},
  "geometry": {"coordinates":[-81.795044,41.238454],"type":"Point"}
}