{
  "type": "Feature",
  "properties": {
    "iso:country":"US",
    "sg:address":"610 E Lima St",
    "sg:city":"Forest",
    "sg:classifiers":[
        {
            "category":"Manufacturing",
            "subcategory":"Tools & Machinery",
            "type":"Manufacturing & Wholesale Goods"
        }
    ],
    "sg:phone":"+1 419 423 9434",
    "sg:postcode":"45843",
    "sg:province":"OH",
    "sg:tags":[
        "milling",
        "mfg",
        "industry",
        "custom",
        "machine",
        "special"
    ],
    "sg:website":"www.buckeyemachine.com",
    "wof:name":"Buckeye Machine & Fabricators",
    "wof:placetype":"venue"
},
  "geometry": {"coordinates":[-83.504774,40.801843],"type":"Point"}
}