{
  "type": "Feature",
  "properties": {
    "iso:country":"US",
    "sg:address":"1619 N Main St",
    "sg:city":"North Canton",
    "sg:classifiers":[
        {
            "category":"Health Services",
            "subcategory":"Doctor",
            "type":"Services"
        }
    ],
    "sg:phone":"+1 330 497 4000",
    "sg:postcode":"44720",
    "sg:province":"OH",
    "sg:tags":[
        "dentist"
    ],
    "wof:name":"Larry J Brandau LLC",
    "wof:placetype":"venue"
},
  "geometry": {"coordinates":[-81.406288,40.897858],"type":"Point"}
}