{
  "type": "Feature",
  "properties": {
    "iso:country":"US",
    "sg:address":"4259 Kirk Rd",
    "sg:city":"Columbiana",
    "sg:classifiers":[
        {
            "category":"Building & Trades",
            "subcategory":"Construction",
            "type":"Services"
        }
    ],
    "sg:phone":"+1 330 482 4072",
    "sg:postcode":"44408",
    "sg:province":"OH",
    "sg:tags":[
        "excavation",
        "contractor"
    ],
    "wof:name":"Hawkins Excavating",
    "wof:placetype":"venue"
},
  "geometry": {"coordinates":[-80.66275,40.837595],"type":"Point"}
}