{
  "type": "Feature",
  "properties": {
    "iso:country":"US",
    "sg:address":"3166 Co Hwy 35",
    "sg:city":"Sycamore",
    "sg:classifiers":[
        {
            "category":"Travel",
            "subcategory":"Campground",
            "type":"Entertainment"
        }
    ],
    "sg:phone":"+1 419 927 4266",
    "sg:postcode":"44882",
    "sg:province":"OH",
    "sg:tags":[
        "camp"
    ],
    "wof:name":"Natures Classroom",
    "wof:placetype":"venue"
},
  "geometry": {"coordinates":[-83.218156,40.946861],"type":"Point"}
}