{
  "type": "Feature",
  "properties": {
    "addr:full":"1400 Raff Rd SW Canton OH 44710",
    "addr:housenumber":"1400",
    "addr:postcode":"44710",
    "addr:street":"Raff Rd Sw",
    "iso:country":"US",
    "sg:address":"1400 Raff Rd SW",
    "sg:city":"Canton",
    "sg:classifiers":[
        {
            "category":"Professional",
            "type":"Services"
        }
    ],
    "sg:phone":"+1 330 478 1419",
    "sg:postcode":"44710",
    "sg:province":"OH",
    "sg:tags":[
        "establishment"
    ],
    "wof:name":"Step Lively",
    "wof:placetype":"venue"
},
  "geometry": {"coordinates":[-81.419742,40.783856],"type":"Point"}
}