{
  "type": "Feature",
  "properties": {
    "iso:country":"US",
    "sg:address":"121 Belair Cir",
    "sg:city":"Bellbrook",
    "sg:classifiers":[
        {
            "category":"Building & Trades",
            "subcategory":"Construction",
            "type":"Services"
        }
    ],
    "sg:phone":"+1 937 848 3266",
    "sg:postcode":"45305",
    "sg:province":"OH",
    "sg:tags":[
        "contractor"
    ],
    "wof:name":"Lindseys Roofing & Siding",
    "wof:placetype":"venue"
},
  "geometry": {"coordinates":[-84.061966,39.641536],"type":"Point"}
}