{
  "type": "Feature",
  "properties": {
    "iso:country":"US",
    "sg:address":"2904 Shilling Dr",
    "sg:city":"Columbus",
    "sg:classifiers":[
        {
            "category":"Real Estate",
            "subcategory":"Real Estate Operator",
            "type":"Services"
        }
    ],
    "sg:phone":"+1 614 236 8624",
    "sg:postcode":"43232",
    "sg:province":"OH",
    "sg:tags":[
        "apartment",
        "complex"
    ],
    "wof:name":"Darmouth Place Apartments",
    "wof:placetype":"venue"
},
  "geometry": {"coordinates":[-82.908009,39.912534],"type":"Point"}
}