{
  "type": "Feature",
  "properties": {
    "iso:country":"US",
    "sg:address":"754 Evergreen Pl",
    "sg:city":"Loveland",
    "sg:classifiers":[
        {
            "category":"Manufacturing",
            "subcategory":"Retail Goods",
            "type":"Manufacturing & Wholesale Goods"
        }
    ],
    "sg:phone":"+1 513 831 1005",
    "sg:postcode":"45140",
    "sg:province":"OH",
    "sg:tags":[
        "manufacturer"
    ],
    "wof:name":"Morad",
    "wof:placetype":"venue"
},
  "geometry": {"coordinates":[-84.26952900000001,39.212171],"type":"Point"}
}