{
  "type": "Feature",
  "properties": {
    "addr:full": "754 Evergreen Pl Loveland OH 45140",
    "addr:housenumber": "754",
    "addr:postcode": "45140",
    "addr:street": "Evergreen Pl",
    "iso:country": "US",
    "sg:address": "754 Evergreen Pl",
    "sg:city": "Loveland",
    "sg:classifiers": [
      {
        "category": "Manufacturing",
        "subcategory": "Retail Goods",
        "type": "Manufacturing \u0026 Wholesale Goods"
      }
    ],
    "sg:phone": "+1 513 831 1005",
    "sg:postcode": "45140",
    "sg:province": "OH",
    "sg:tags": [
      "manufacturer"
    ],
    "wof:name": "Morad",
    "wof:placetype": "venue"
  },
  "geometry": {"coordinates":[-84.269529,39.212171],"type":"Point"}
}
