{
  "type": "Feature",
  "properties": {
    "addr:full": "17550 Rosbough Blvd Cleveland OH 44130",
    "addr:housenumber": "17550",
    "addr:postcode": "44130",
    "addr:street": "Rosbough Blvd",
    "iso:country": "US",
    "sg:address": "17550 Rosbough Blvd",
    "sg:city": "Cleveland",
    "sg:classifiers": [
      {
        "category": "Travel",
        "subcategory": "Hotels \u0026 Motels",
        "type": "Entertainment"
      }
    ],
    "sg:phone": "+1 440 234 3131",
    "sg:postcode": "44130",
    "sg:province": "OH",
    "sg:website": "www.choicehotels.com",
    "wof:name": "Comfort Inn Cleveland Airport",
    "wof:placetype": "venue"
  },
  "geometry": {"coordinates":[-81.823056,41.374776],"type":"Point"}
}
