{
  "type": "Feature",
  "properties": {
    "iso:country":"US",
    "sg:address":"17550 Rosbough Blvd",
    "sg:city":"Cleveland",
    "sg:classifiers":[
        {
            "category":"Travel",
            "subcategory":"Hotels & Motels",
            "type":"Entertainment"
        }
    ],
    "sg:phone":"+1 440 234 3131",
    "sg:postcode":"44130",
    "sg:province":"OH",
    "sg:website":"www.choicehotels.com",
    "wof:name":"Comfort Inn Cleveland Airport",
    "wof:placetype":"venue"
},
  "geometry": {"coordinates":[-81.82305599999999,41.374776],"type":"Point"}
}