{
  "type": "Feature",
  "properties": {
    "addr:full": "4103 Tonya Trl Hamilton OH 45011",
    "addr:housenumber": "4103",
    "addr:postcode": "45011",
    "addr:street": "Tonya Trl",
    "iso:country": "US",
    "sg:address": "4103 Tonya Trl",
    "sg:city": "Hamilton",
    "sg:classifiers": [
      {
        "category": "Retail",
        "subcategory": "Auto Repair",
        "type": "Services"
      }
    ],
    "sg:phone": "+1 513 892 9500",
    "sg:postcode": "45011",
    "sg:province": "OH",
    "sg:tags": [
      "body",
      "automobile",
      "painting"
    ],
    "wof:name": "Liberty Collision",
    "wof:placetype": "venue"
  },
  "geometry": {"coordinates":[-84.478941,39.417601],"type":"Point"}
}
