{
  "type": "Feature",
  "properties": {
    "addr:full": "801 W Cherry St Sunbury OH 43074",
    "addr:housenumber": "801",
    "addr:postcode": "43074",
    "addr:street": "W Cherry St",
    "iso:country": "US",
    "sg:address": "801 W Cherry St",
    "sg:city": "Sunbury",
    "sg:classifiers": [
      {
        "category": "Banks \u0026 Credit Unions",
        "subcategory": "Bank",
        "type": "Services"
      }
    ],
    "sg:phone": "+1 740 965 1010",
    "sg:postcode": "43074",
    "sg:province": "OH",
    "sg:tags": [
      "loan",
      "mortgage",
      "real estate"
    ],
    "wof:name": "American Mortgage Express",
    "wof:placetype": "venue"
  },
  "geometry": {"coordinates":[-82.869436,40.249065],"type":"Point"}
}
