{
  "type": "Feature",
  "properties": {
    "addr:full": "47217 State Rte 303 Wellington OH 44090",
    "addr:housenumber": "47217",
    "addr:postcode": "44090",
    "addr:street": "State Rte 303",
    "iso:country": "US",
    "sg:address": "47217 State Rte 303",
    "sg:city": "Wellington",
    "sg:phone": "+1 440 775 7817",
    "sg:postcode": "44090",
    "sg:province": "OH",
    "sg:tags": [
      "farm",
      "corn",
      "wheat",
      "soybean"
    ],
    "wof:name": "Lloyd Mull",
    "wof:placetype": "venue"
  },
  "geometry": {"coordinates":[-82.239844,41.23698],"type":"Point"}
}
