{
  "type": "Feature",
  "properties": {
    "addr:full": "709 N Main St Hubbard OH 44425",
    "addr:housenumber": "709",
    "addr:postcode": "44425",
    "addr:street": "N Main St",
    "iso:country": "US",
    "sg:address": "709 N Main St",
    "sg:city": "Hubbard",
    "sg:classifiers": [
      {
        "category": "Organizations",
        "subcategory": "Professional Association",
        "type": "Services"
      }
    ],
    "sg:phone": "+1 330 534 4472",
    "sg:postcode": "44425",
    "sg:province": "OH",
    "wof:name": "Hubbard Alumni Assoc",
    "wof:placetype": "venue"
  },
  "geometry": {"coordinates":[-80.568884,41.164249],"type":"Point"}
}
