{
  "type": "Feature",
  "properties": {
    "iso:country":"US",
    "sg:address":"2019 W Sylvania Ave",
    "sg:city":"Toledo",
    "sg:classifiers":[
        {
            "category":"Restaurant",
            "type":"Food & Drink"
        }
    ],
    "sg:phone":"+1 419 474 2009",
    "sg:postcode":"43613",
    "sg:province":"OH",
    "sg:tags":[
        "eating",
        "caterer"
    ],
    "wof:name":"Licia's Creative Catering Inc",
    "wof:placetype":"venue"
},
  "geometry": {"coordinates":[-83.593178,41.692178],"type":"Point"}
}