{
  "type": "Feature",
  "properties": {
    "iso:country":"US",
    "sg:address":"127 Bayview Ave",
    "sg:city":"Brookville",
    "sg:classifiers":[
        {
            "category":"Home & Garden",
            "subcategory":"Building Materials",
            "type":"Retail Goods"
        }
    ],
    "sg:phone":"+1 937 833 2710",
    "sg:postcode":"45309",
    "sg:province":"OH",
    "sg:tags":[
        "door"
    ],
    "wof:name":"BBS Home Improvements",
    "wof:placetype":"venue"
},
  "geometry": {"coordinates":[-84.415155,39.827765],"type":"Point"}
}