{
  "type": "Feature",
  "properties": {
    "iso:country":"US",
    "sg:address":"115 S Locust St",
    "sg:city":"Oxford",
    "sg:classifiers":[
        {
            "category":"Retail",
            "subcategory":"Self-service Laundry",
            "type":"Services"
        }
    ],
    "sg:phone":"+1 513 523 0917",
    "sg:postcode":"45056",
    "sg:province":"OH",
    "wof:name":"Locust Car Wash & Laundry",
    "wof:placetype":"venue"
},
  "geometry": {"coordinates":[-84.749208,39.508955],"type":"Point"}
}