{
  "type": "Feature",
  "properties": {
    "addr:full": "115 S Locust St Oxford OH 45056",
    "addr:housenumber": "115",
    "addr:postcode": "45056",
    "addr:street": "S Locust St",
    "iso:country": "US",
    "sg:address": "115 S Locust St",
    "sg:city": "Oxford",
    "sg:classifiers": [
      {
        "category": "Retail",
        "subcategory": "Self-service Laundry",
        "type": "Services"
      }
    ],
    "sg:phone": "+1 513 523 0917",
    "sg:postcode": "45056",
    "sg:province": "OH",
    "wof:name": "Locust Car Wash \u0026 Laundry",
    "wof:placetype": "venue"
  },
  "geometry": {"coordinates":[-84.749208,39.508955],"type":"Point"}
}
