{
  "type": "Feature",
  "properties": {
    "iso:country":"US",
    "sg:address":"576 W Park Ave",
    "sg:city":"Barberton",
    "sg:classifiers":[
        {
            "category":"Government",
            "subcategory":"Office",
            "type":"Public Place"
        }
    ],
    "sg:phone":"+1 330 753 6611",
    "sg:postcode":"44203",
    "sg:province":"OH",
    "sg:tags":[
        "city"
    ],
    "wof:name":"Utilities Dept",
    "wof:placetype":"venue"
},
  "geometry": {"coordinates":[-81.610703,41.013667],"type":"Point"}
}