{
  "type": "Feature",
  "properties": {
    "iso:country":"US",
    "sg:address":"450 Eldridge St",
    "sg:city":"Wauseon",
    "sg:classifiers":[
        {
            "category":"Building & Trades",
            "subcategory":"Landscaping Services",
            "type":"Services"
        }
    ],
    "sg:phone":"+1 419 335 8335",
    "sg:postcode":"43567",
    "sg:province":"OH",
    "sg:tags":[
        "tree"
    ],
    "wof:name":"Randolph Tree Svc",
    "wof:placetype":"venue"
},
  "geometry": {"coordinates":[-84.20208,41.604695],"type":"Point"}
}