{
  "type": "Feature",
  "properties": {
    "addr:full": "718 S Dixie Dr Vandalia OH 45377",
    "addr:housenumber": "718",
    "addr:postcode": "45377",
    "addr:street": "S Dixie Dr",
    "iso:country": "US",
    "sg:address": "718 S Dixie Dr",
    "sg:city": "Vandalia",
    "sg:classifiers": [
      {
        "category": "Real Estate",
        "subcategory": "Real Estate Agent",
        "type": "Services"
      }
    ],
    "sg:phone": "+1 937 890 1580",
    "sg:postcode": "45377",
    "sg:province": "OH",
    "wof:name": "Geoffrey Smith",
    "wof:placetype": "venue"
  },
  "geometry": {"coordinates":[-84.199226,39.884427],"type":"Point"}
}
