{
  "type": "Feature",
  "properties": {
    "iso:country":"US",
    "sg:address":"45 Cresswell Ave",
    "sg:city":"Bedford",
    "sg:classifiers":[
        {
            "category":"Organizations",
            "subcategory":"Membership Organization",
            "type":"Services"
        }
    ],
    "sg:phone":"+1 440 232 0922",
    "sg:postcode":"44146",
    "sg:province":"OH",
    "wof:name":"Pearl Harbor Survivor Assn",
    "wof:placetype":"venue"
},
  "geometry": {"coordinates":[-81.548858,41.40838],"type":"Point"}
}