{
  "type": "Feature",
  "properties": {
    "addr:full": "5042 Cardington Green Cir NW Canton OH 44718",
    "addr:housenumber": "5042",
    "addr:postcode": "44718",
    "addr:street": "Cardington Green Cir Nw",
    "iso:country": "US",
    "sg:address": "5042 Cardington Green Cir NW",
    "sg:city": "Canton",
    "sg:classifiers": [
      {
        "category": "Retail",
        "subcategory": "Portrait Studio",
        "type": "Services"
      }
    ],
    "sg:phone": "+1 330 833 7990",
    "sg:postcode": "44718",
    "sg:province": "OH",
    "sg:tags": [
      "photographer"
    ],
    "wof:name": "Chris Rowley Photography",
    "wof:placetype": "venue"
  },
  "geometry": {"coordinates":[-81.486945,40.853172],"type":"Point"}
}
