{
  "type": "Feature",
  "properties": {
    "addr:full": "5393 Larue-Prospect Rd W New Bloomington OH 43341",
    "addr:housenumber": "5393",
    "addr:postcode": "43341",
    "addr:street": "Larue-Prospect Rd W New",
    "iso:country": "US",
    "sg:address": "5393 Larue-Prospect Rd W",
    "sg:city": "New Bloomington",
    "sg:classifiers": [
      {
        "category": "Government",
        "subcategory": "Office",
        "type": "Public Place"
      }
    ],
    "sg:phone": "+1 740 499 3019",
    "sg:postcode": "43341",
    "sg:province": "OH",
    "wof:name": "Big Island Wildlife Area",
    "wof:placetype": "venue"
  },
  "geometry": {"coordinates":[-83.278376,40.569744],"type":"Point"}
}
