{
  "type": "Feature",
  "properties": {
    "addr:full":"205 Aldrich Rd Columbus OH 43214",
    "addr:housenumber":"205",
    "addr:postcode":"43214",
    "addr:street":"Aldrich Rd",
    "iso:country":"US",
    "sg:address":"205 Aldrich Rd",
    "sg:city":"Columbus",
    "sg:classifiers":[
        {
            "category":"Shopping",
            "subcategory":"Books",
            "type":"Retail Goods"
        }
    ],
    "sg:phone":"+1 614 262 9332",
    "sg:postcode":"43214",
    "sg:province":"OH",
    "sg:tags":[
        "store"
    ],
    "wof:name":"Discovering Books",
    "wof:placetype":"venue"
},
  "geometry": {"coordinates":[-83.025083,40.050443],"type":"Point"}
}