{
  "type": "Feature",
  "properties": {
    "addr:full":"3657 Yoakam Rd Lima OH 45806",
    "addr:housenumber":"3657",
    "addr:postcode":"45806",
    "addr:street":"Yoakam Rd",
    "iso:country":"US",
    "sg:address":"3657 Yoakam Rd",
    "sg:city":"Lima",
    "sg:classifiers":[
        {
            "category":"Building & Trades",
            "subcategory":"Landscaping Services",
            "type":"Services"
        }
    ],
    "sg:phone":"+1 419 991 2140",
    "sg:postcode":"45806",
    "sg:province":"OH",
    "wof:name":"Professional Edge Lawn Mowing",
    "wof:placetype":"venue"
},
  "geometry": {"coordinates":[-84.175004,40.689035],"type":"Point"}
}