{
  "type": "Feature",
  "properties": {
    "addr:full":"391 Kline Ave Akron OH 44305",
    "addr:housenumber":"391",
    "addr:postcode":"44305",
    "addr:street":"Kline Ave",
    "iso:country":"US",
    "sg:address":"391 Kline Ave",
    "sg:city":"Akron",
    "sg:classifiers":[
        {
            "category":"Manufacturing",
            "subcategory":"Printing",
            "type":"Manufacturing & Wholesale Goods"
        }
    ],
    "sg:phone":"+1 330 798 7515",
    "sg:postcode":"44305",
    "sg:province":"OH",
    "sg:tags":[
        "publishing"
    ],
    "wof:name":"Zamar Publishing",
    "wof:placetype":"venue"
},
  "geometry": {"coordinates":[-81.47877800000001,41.074994],"type":"Point"}
}