{
  "type": "Feature",
  "properties": {
    "addr:full": "1782 N High St Columbus OH 43201",
    "addr:housenumber": "1782",
    "addr:postcode": "43201",
    "addr:street": "N High St",
    "iso:country": "US",
    "sg:address": "1782 N High St",
    "sg:city": "Columbus",
    "sg:classifiers": [
      {
        "category": "Shopping",
        "subcategory": "Clothing, Apparel, \u0026 Fashions",
        "type": "Retail Goods"
      }
    ],
    "sg:phone": "+1 614 298 8809",
    "sg:postcode": "43201",
    "sg:province": "OH",
    "sg:website": "www.urbanoutfitters.com",
    "wof:name": "Urban Outfitters Inc",
    "wof:placetype": "venue"
  },
  "geometry": {"coordinates":[-83.007435,39.996826],"type":"Point"}
}
