{
  "type": "Feature",
  "properties": {
    "iso:country":"US",
    "sg:address":"1100 W Bagley Rd",
    "sg:city":"Berea",
    "sg:classifiers":[
        {
            "category":"Wholesale",
            "subcategory":"Electrical",
            "type":"Manufacturing & Wholesale Goods"
        }
    ],
    "sg:phone":"+1 440 243 4500",
    "sg:postcode":"44017",
    "sg:province":"OH",
    "sg:tags":[
        "control",
        "security",
        "system"
    ],
    "wof:name":"Complete Security Solutions",
    "wof:placetype":"venue"
},
  "geometry": {"coordinates":[-81.891909,41.372639],"type":"Point"}
}