{
  "type": "Feature",
  "properties": {
    "addr:full":"606 N Main St Mansfield OH 44902",
    "addr:housenumber":"606",
    "addr:postcode":"44902",
    "addr:street":"N Main St",
    "iso:country":"US",
    "sg:address":"606 N Main St",
    "sg:city":"Mansfield",
    "sg:classifiers":[
        {
            "category":"Building & Trades",
            "subcategory":"Construction",
            "type":"Services"
        }
    ],
    "sg:phone":"+1 419 524 5656",
    "sg:postcode":"44902",
    "sg:province":"OH",
    "sg:tags":[
        "general",
        "contractor"
    ],
    "sg:website":"www.kokosing-inc.com",
    "wof:name":"Kokosing Construction Co",
    "wof:placetype":"venue"
},
  "geometry": {"coordinates":[-82.514235,40.774898],"type":"Point"}
}