{
  "type": "Feature",
  "properties": {
    "addr:full": "458 Caskey Dr Oberlin OH 44074",
    "addr:housenumber": "458",
    "addr:postcode": "44074",
    "addr:street": "Caskey Dr",
    "iso:country": "US",
    "sg:address": "458 Caskey Dr",
    "sg:city": "Oberlin",
    "sg:classifiers": [
      {
        "category": "Building \u0026 Trades",
        "subcategory": "Construction",
        "type": "Services"
      }
    ],
    "sg:phone": "+1 440 774 3440",
    "sg:postcode": "44074",
    "sg:province": "OH",
    "sg:tags": [
      "hanging",
      "contractor"
    ],
    "wof:name": "Melvin Painter PH D Inc",
    "wof:placetype": "venue"
  },
  "geometry": {"coordinates":[-82.200153,41.290304],"type":"Point"}
}
