{
  "type": "Feature",
  "properties": {
    "addr:full":"165 Smokerise Dr Wadsworth OH 44281",
    "addr:housenumber":"165",
    "addr:postcode":"44281",
    "addr:street":"Smokerise Dr",
    "iso:country":"US",
    "sg:address":"165 Smokerise Dr",
    "sg:city":"Wadsworth",
    "sg:classifiers":[
        {
            "category":"Professional",
            "subcategory":"Engineering",
            "type":"Services"
        }
    ],
    "sg:phone":"+1 330 334 1585",
    "sg:postcode":"44281",
    "sg:province":"OH",
    "wof:name":"Louis Perry & Associates",
    "wof:placetype":"venue"
},
  "geometry": {"coordinates":[-81.730262,41.051799],"type":"Point"}
}