{
  "type": "Feature",
  "properties": {
    "iso:country":"US",
    "sg:address":"54 Woodland Chase Blvd",
    "sg:city":"Niles",
    "sg:classifiers":[
        {
            "category":"Personal",
            "type":"Services"
        }
    ],
    "sg:phone":"+1 330 544 0165",
    "sg:postcode":"44446",
    "sg:province":"OH",
    "sg:tags":[
        "program",
        "physical",
        "exercise",
        "fitness"
    ],
    "wof:name":"World Of Fitness",
    "wof:placetype":"venue"
},
  "geometry": {"coordinates":[-80.752444,41.195253],"type":"Point"}
}