{
  "type": "Feature",
  "properties": {
    "iso:country":"US",
    "sg:address":"143 N Market St",
    "sg:city":"Wooster",
    "sg:classifiers":[
        {
            "category":"Real Estate",
            "subcategory":"Real Estate Services",
            "type":"Services"
        }
    ],
    "sg:phone":"+1 330 263 6075",
    "sg:postcode":"44691",
    "sg:province":"OH",
    "sg:tags":[
        "company",
        "title"
    ],
    "wof:name":"Oak Tree Title LTD",
    "wof:placetype":"venue"
},
  "geometry": {"coordinates":[-81.940068,40.798927],"type":"Point"}
}