{
  "type": "Feature",
  "properties": {
    "addr:full": "3265 W Market St Fairlawn OH 44333",
    "addr:housenumber": "3265",
    "addr:postcode": "44333",
    "addr:street": "W Market St",
    "iso:country": "US",
    "sg:address": "3265 W Market St",
    "sg:city": "Fairlawn",
    "sg:classifiers": [
      {
        "category": "Shopping",
        "subcategory": "Clothing, Apparel, \u0026 Fashions",
        "type": "Retail Goods"
      }
    ],
    "sg:phone": "+1 330 867 5815",
    "sg:postcode": "44333",
    "sg:province": "OH",
    "sg:website": "www.cache.com",
    "wof:name": "Cache",
    "wof:placetype": "venue"
  },
  "geometry": {"coordinates":[-81.618917,41.132495],"type":"Point"}
}
