{
  "type": "Feature",
  "properties": {
    "addr:full": "3430 Shady Ln North Bend OH 45052",
    "addr:housenumber": "3430",
    "addr:postcode": "45052",
    "addr:street": "Shady Ln",
    "iso:country": "US",
    "sg:address": "3430 Shady Ln",
    "sg:city": "North Bend",
    "sg:classifiers": [
      {
        "category": "Building \u0026 Trades",
        "subcategory": "Landscaping Services",
        "type": "Services"
      }
    ],
    "sg:phone": "+1 513 941 1166",
    "sg:postcode": "45052",
    "sg:province": "OH",
    "wof:name": "Mc Michael Landscape Service",
    "wof:placetype": "venue"
  },
  "geometry": {"coordinates":[-84.704455,39.154369],"type":"Point"}
}
