{
  "type": "Feature",
  "properties": {
    "addr:full": "2550 Corporate Exchange Dr Columbus OH 43231",
    "addr:housenumber": "2550",
    "addr:postcode": "43231",
    "addr:street": "Corporate Exchange Dr",
    "iso:country": "US",
    "sg:address": "2550 Corporate Exchange Dr",
    "sg:city": "Columbus",
    "sg:classifiers": [
      {
        "category": "Professional",
        "subcategory": "Engineering",
        "type": "Services"
      }
    ],
    "sg:phone": "+1 614 901 2235",
    "sg:postcode": "43231",
    "sg:province": "OH",
    "wof:name": "American Consulting Inc",
    "wof:placetype": "venue"
  },
  "geometry": {"coordinates":[-82.943491,40.101917],"type":"Point"}
}
