{
  "type": "Feature",
  "properties": {
    "iso:country":"US",
    "sg:address":"6081 Central Park Dr",
    "sg:city":"Columbus",
    "sg:classifiers":[
        {
            "category":"Wholesale",
            "subcategory":"Durable Goods & Equipment",
            "type":"Manufacturing & Wholesale Goods"
        }
    ],
    "sg:phone":"+1 614 797 2265",
    "sg:postcode":"43231",
    "sg:province":"OH",
    "sg:tags":[
        "representative",
        "manufacturer"
    ],
    "wof:name":"Industrial Diamond Assn",
    "wof:placetype":"venue"
},
  "geometry": {"coordinates":[-82.94605799999999,40.095384],"type":"Point"}
}