{
  "type": "Feature",
  "properties": {
    "addr:full": "13240 Shanley Rd Quincy OH 43343",
    "addr:postcode": "13240;43343",
    "addr:street": "Shanley Rd",
    "iso:country": "US",
    "sg:address": "13240 Shanley Rd",
    "sg:city": "Quincy",
    "sg:phone": "+1 937 362 4311",
    "sg:postcode": "43343",
    "sg:province": "OH",
    "sg:tags": [
      "farm",
      "grain",
      "cash"
    ],
    "wof:name": "Baker John",
    "wof:placetype": "venue"
  },
  "geometry": {"coordinates":[-83.997191,40.243229],"type":"Point"}
}
