{
  "type": "Feature",
  "properties": {
    "iso:country":"US",
    "sg:address":"10052 Klipstine Rd",
    "sg:city":"Versailles",
    "sg:classifiers":[
        {
            "category":"Building & Trades",
            "subcategory":"Plumbing",
            "type":"Services"
        }
    ],
    "sg:phone":"+1 937 526 5253",
    "sg:postcode":"45380",
    "sg:province":"OH",
    "sg:tags":[
        "contractor"
    ],
    "wof:name":"S Condon Heating Cooling",
    "wof:placetype":"venue"
},
  "geometry": {"coordinates":[-84.474525,40.215311],"type":"Point"}
}