{
  "type": "Feature",
  "properties": {
    "addr:full": "37225 Euclid Ave Willoughby OH 44094",
    "addr:housenumber": "37225",
    "addr:postcode": "44094",
    "addr:street": "Euclid Ave",
    "iso:country": "US",
    "sg:address": "37225 Euclid Ave",
    "sg:city": "Willoughby",
    "sg:classifiers": [
      {
        "category": "Building \u0026 Trades",
        "subcategory": "Construction",
        "type": "Services"
      }
    ],
    "sg:phone": "+1 440 975 1901",
    "sg:postcode": "44094",
    "sg:province": "OH",
    "sg:tags": [
      "home",
      "improvement"
    ],
    "wof:name": "F \u0026 D Home Improvement",
    "wof:placetype": "venue"
  },
  "geometry": {"coordinates":[-81.416437,41.630068],"type":"Point"}
}
