{
  "type": "Feature",
  "properties": {
    "iso:country":"US",
    "sg:address":"37225 Euclid Ave",
    "sg:city":"Willoughby",
    "sg:classifiers":[
        {
            "category":"Building & Trades",
            "subcategory":"Construction",
            "type":"Services"
        }
    ],
    "sg:phone":"+1 440 975 1901",
    "sg:postcode":"44094",
    "sg:province":"OH",
    "sg:tags":[
        "home",
        "improvement"
    ],
    "wof:name":"F & D Home Improvement",
    "wof:placetype":"venue"
},
  "geometry": {"coordinates":[-81.416437,41.630068],"type":"Point"}
}