{
  "type": "Feature",
  "properties": {
    "iso:country":"US",
    "sg:address":"5981 Edgewater Dr",
    "sg:city":"Toledo",
    "sg:classifiers":[
        {
            "category":"Restaurant",
            "type":"Food & Drink"
        }
    ],
    "sg:phone":"+1 419 727 0331",
    "sg:postcode":"43611",
    "sg:province":"OH",
    "sg:tags":[
        "eating"
    ],
    "wof:name":"Wesleys On Water",
    "wof:placetype":"venue"
},
  "geometry": {"coordinates":[-83.466383,41.726866],"type":"Point"}
}