{
  "type": "Feature",
  "properties": {
    "addr:full": "5981 Edgewater Dr Toledo OH 43611",
    "addr:housenumber": "5981",
    "addr:postcode": "43611",
    "addr:street": "Edgewater Dr",
    "iso:country": "US",
    "sg:address": "5981 Edgewater Dr",
    "sg:city": "Toledo",
    "sg:classifiers": [
      {
        "category": "Restaurant",
        "type": "Food \u0026 Drink"
      }
    ],
    "sg:phone": "+1 419 727 0331",
    "sg:postcode": "43611",
    "sg:province": "OH",
    "sg:tags": [
      "eating"
    ],
    "wof:name": "Wesleys On Water",
    "wof:placetype": "venue"
  },
  "geometry": {"coordinates":[-83.466383,41.726866],"type":"Point"}
}
