{
  "type": "Feature",
  "properties": {
    "iso:country":"US",
    "sg:address":"1141 N Monroe Dr",
    "sg:city":"Xenia",
    "sg:classifiers":[
        {
            "category":"Banks & Credit Unions",
            "subcategory":"Investment Brokerage",
            "type":"Services"
        }
    ],
    "sg:phone":"+1 937 376 7387",
    "sg:postcode":"45385",
    "sg:province":"OH",
    "sg:tags":[
        "consultant",
        "planning",
        "financial"
    ],
    "wof:name":"Greene Foundation",
    "wof:placetype":"venue"
},
  "geometry": {"coordinates":[-83.928555,39.699673],"type":"Point"}
}