{
  "type": "Feature",
  "properties": {
    "addr:full": "1141 N Monroe Dr Xenia OH 45385",
    "addr:housenumber": "1141",
    "addr:postcode": "45385",
    "addr:street": "N Monroe Dr",
    "iso:country": "US",
    "sg:address": "1141 N Monroe Dr",
    "sg:city": "Xenia",
    "sg:classifiers": [
      {
        "category": "Banks \u0026 Credit Unions",
        "subcategory": "Investment Brokerage",
        "type": "Services"
      }
    ],
    "sg:phone": "+1 937 376 7387",
    "sg:postcode": "45385",
    "sg:province": "OH",
    "sg:tags": [
      "consultant",
      "planning",
      "financial"
    ],
    "wof:name": "Greene Foundation",
    "wof:placetype": "venue"
  },
  "geometry": {"coordinates":[-83.928555,39.699673],"type":"Point"}
}
