{
  "type": "Feature",
  "properties": {
    "addr:full": "775 Adams Rd Loveland OH 45140",
    "addr:housenumber": "775",
    "addr:postcode": "45140",
    "addr:street": "Adams Rd",
    "iso:country": "US",
    "sg:address": "775 Adams Rd",
    "sg:city": "Loveland",
    "sg:classifiers": [
      {
        "category": "Building \u0026 Trades",
        "subcategory": "Landscaping Services",
        "type": "Services"
      }
    ],
    "sg:phone": "+1 513 683 7444",
    "sg:postcode": "45140",
    "sg:province": "OH",
    "sg:tags": [
      "landscape",
      "contractor"
    ],
    "wof:name": "Gehler Grounds Care",
    "wof:placetype": "venue"
  },
  "geometry": {"coordinates":[-84.239324,39.286568],"type":"Point"}
}
