{
  "type": "Feature",
  "properties": {
    "addr:full":"61 2nd Ave SE London OH 43140",
    "addr:housenumber":"61",
    "addr:postcode":"43140",
    "addr:street":"2Nd Ave Se",
    "iso:country":"US",
    "sg:address":"61 2nd Ave SE",
    "sg:city":"London",
    "sg:classifiers":[
        {
            "category":"Organizations",
            "subcategory":"Religious Organization",
            "type":"Services"
        }
    ],
    "sg:phone":"+1 740 857 1114",
    "sg:postcode":"43140",
    "sg:province":"OH",
    "sg:tags":[
        "church"
    ],
    "wof:name":"Plumwood United Methodist Chr",
    "wof:placetype":"venue"
},
  "geometry": {"coordinates":[-83.409109,39.93633],"type":"Point"}
}