{
  "type": "Feature",
  "properties": {
    "iso:country":"US",
    "sg:address":"181 Humphries Dr",
    "sg:city":"Etna",
    "sg:classifiers":[
        {
            "category":"Building & Trades",
            "subcategory":"Construction",
            "type":"Services"
        },
        {
            "category":"Home & Garden",
            "subcategory":"Carpets & Floor Coverings",
            "type":"Retail Goods"
        }
    ],
    "sg:phone":"+1 740 927 3460",
    "sg:postcode":"43068",
    "sg:province":"OH",
    "sg:tags":[
        "dealer",
        "resurfacing",
        "laying",
        "refinishing",
        "rug"
    ],
    "wof:name":"A & A Commercial Flooring Spec",
    "wof:placetype":"venue"
},
  "geometry": {"coordinates":[-82.739891,39.955914],"type":"Point"}
}