{
  "type": "Feature",
  "properties": {
    "addr:full": "181 Humphries Dr Etna OH 43068",
    "addr:housenumber": "181",
    "addr:postcode": "43068",
    "addr:street": "Humphries Dr",
    "iso:country": "US",
    "sg:address": "181 Humphries Dr",
    "sg:city": "Etna",
    "sg:classifiers": [
      {
        "category": "Building \u0026 Trades",
        "subcategory": "Construction",
        "type": "Services"
      },
      {
        "category": "Home \u0026 Garden",
        "subcategory": "Carpets \u0026 Floor Coverings",
        "type": "Retail Goods"
      }
    ],
    "sg:phone": "+1 740 927 3460",
    "sg:postcode": "43068",
    "sg:province": "OH",
    "sg:tags": [
      "dealer",
      "resurfacing",
      "laying",
      "refinishing",
      "rug"
    ],
    "wof:name": "A \u0026 A Commercial Flooring Spec",
    "wof:placetype": "venue"
  },
  "geometry": {"coordinates":[-82.739891,39.955914],"type":"Point"}
}
