{
  "type": "Feature",
  "properties": {
    "addr:full": "9597 Mentor Ave Mentor OH 44060",
    "addr:housenumber": "9597",
    "addr:postcode": "44060",
    "addr:street": "Mentor Ave",
    "iso:country": "US",
    "sg:address": "9597 Mentor Ave",
    "sg:city": "Mentor",
    "sg:classifiers": [
      {
        "category": "Shopping",
        "subcategory": "Gifts \u0026 Souvenirs",
        "type": "Retail Goods"
      }
    ],
    "sg:phone": "+1 440 350 9816",
    "sg:postcode": "44060",
    "sg:province": "OH",
    "sg:tags": [
      "party",
      "supply"
    ],
    "sg:website": "www.factorycard.com",
    "wof:name": "Factory Card Outlet 175",
    "wof:placetype": "venue"
  },
  "geometry": {"coordinates":[-81.293771,41.684324],"type":"Point"}
}
