{
  "type": "Feature",
  "properties": {
    "addr:full":"4065 Hillman Way Youngstown OH 44512",
    "addr:housenumber":"4065",
    "addr:postcode":"44512",
    "addr:street":"Hillman Way",
    "iso:country":"US",
    "sg:address":"4065 Hillman Way",
    "sg:city":"Youngstown",
    "sg:classifiers":[
        {
            "category":"Insurance",
            "subcategory":"Insurance Agent",
            "type":"Services"
        }
    ],
    "sg:phone":"+1 330 788 7283",
    "sg:postcode":"44512",
    "sg:province":"OH",
    "wof:name":"All Drivers Insurance Agency",
    "wof:placetype":"venue"
},
  "geometry": {"coordinates":[-80.663889,41.059627],"type":"Point"}
}