{
  "type": "Feature",
  "properties": {
    "iso:country":"US",
    "sg:address":"1662 Mars Ave",
    "sg:city":"Lakewood",
    "sg:classifiers":[
        {
            "category":"Professional",
            "subcategory":"Computer Services",
            "type":"Services"
        }
    ],
    "sg:phone":"+1 216 521 9027",
    "sg:postcode":"44107",
    "sg:province":"OH",
    "sg:tags":[
        "programing",
        "custom"
    ],
    "wof:name":"D C Hubbell & Associates Inc",
    "wof:placetype":"venue"
},
  "geometry": {"coordinates":[-81.803822,41.477838],"type":"Point"}
}