{
  "type": "Feature",
  "properties": {
    "addr:full":"861 W Maple St Hartville OH 44632",
    "addr:housenumber":"861",
    "addr:postcode":"44632",
    "addr:street":"W Maple St",
    "iso:country":"US",
    "sg:address":"861 W Maple St",
    "sg:city":"Hartville",
    "sg:classifiers":[
        {
            "category":"Government",
            "subcategory":"Post Office",
            "type":"Public Place"
        }
    ],
    "sg:phone":"+1 330 877 9296",
    "sg:postcode":"44632",
    "sg:province":"OH",
    "wof:name":"US Post Office",
    "wof:placetype":"venue"
},
  "geometry": {"coordinates":[-81.345601,40.967716],"type":"Point"}
}