{
  "type": "Feature",
  "properties": {
    "addr:full":"790 Ken Mar Ind Pkwy Cleveland OH 44147",
    "addr:housenumber":"790",
    "addr:postcode":"44147",
    "addr:street":"Ken Mar Ind Pkwy",
    "iso:country":"US",
    "sg:address":"790 Ken Mar Ind Pkwy",
    "sg:city":"Cleveland",
    "sg:classifiers":[
        {
            "category":"Shopping",
            "subcategory":"Computers & Home Electronics",
            "type":"Retail Goods"
        }
    ],
    "sg:phone":"+1 440 740 0630",
    "sg:postcode":"44147",
    "sg:province":"OH",
    "sg:tags":[
        "audio"
    ],
    "wof:name":"Audio Visual Innovations",
    "wof:placetype":"venue"
},
  "geometry": {"coordinates":[-81.65704599999999,41.317125],"type":"Point"}
}