{
  "type": "Feature",
  "properties": {
    "iso:country":"US",
    "sg:address":"9615 Diamond Centre Dr",
    "sg:city":"Mentor",
    "sg:classifiers":[
        {
            "category":"Professional",
            "type":"Services"
        }
    ],
    "sg:phone":"+1 440 350 0692",
    "sg:postcode":"44060",
    "sg:province":"OH",
    "sg:tags":[
        "establishment"
    ],
    "wof:name":"Behr Process Corp",
    "wof:placetype":"venue"
},
  "geometry": {"coordinates":[-81.29485200000001,41.714834],"type":"Point"}
}