{
  "type": "Feature",
  "properties": {
    "iso:country":"US",
    "sg:address":"601 Manor Park Dr",
    "sg:city":"Columbus",
    "sg:classifiers":[
        {
            "category":"Wholesale",
            "subcategory":"Machinery & Supplies",
            "type":"Manufacturing & Wholesale Goods"
        }
    ],
    "sg:phone":"+1 614 922 0400",
    "sg:postcode":"43228",
    "sg:province":"OH",
    "sg:tags":[
        "equipment",
        "construction",
        "rent"
    ],
    "sg:website":"www.wacoscaf.com",
    "wof:name":"WACO Scaffolding & Equipment",
    "wof:placetype":"venue"
},
  "geometry": {"coordinates":[-83.142926,39.963667],"type":"Point"}
}