{
  "type": "Feature",
  "properties": {
    "addr:full": "601 Manor Park Dr Columbus OH 43228",
    "addr:housenumber": "601",
    "addr:postcode": "43228",
    "addr:street": "Manor Park Dr",
    "iso:country": "US",
    "sg:address": "601 Manor Park Dr",
    "sg:city": "Columbus",
    "sg:classifiers": [
      {
        "category": "Wholesale",
        "subcategory": "Machinery \u0026 Supplies",
        "type": "Manufacturing \u0026 Wholesale Goods"
      }
    ],
    "sg:phone": "+1 614 922 0400",
    "sg:postcode": "43228",
    "sg:province": "OH",
    "sg:tags": [
      "equipment",
      "construction",
      "rent"
    ],
    "sg:website": "www.wacoscaf.com",
    "wof:name": "WACO Scaffolding \u0026 Equipment",
    "wof:placetype": "venue"
  },
  "geometry": {"coordinates":[-83.142926,39.963667],"type":"Point"}
}
