{
  "type": "Feature",
  "properties": {
    "iso:country":"US",
    "sg:address":"308 W Washington St",
    "sg:city":"Dayton",
    "sg:classifiers":[
        {
            "category":"Home & Garden",
            "subcategory":"Household Appliances",
            "type":"Retail Goods"
        }
    ],
    "sg:phone":"+1 937 461 4766",
    "sg:postcode":"45402",
    "sg:province":"OH",
    "sg:tags":[
        "irons"
    ],
    "sg:website":"www.elegantiron.com",
    "wof:name":"Elegant Iron Inc",
    "wof:placetype":"venue"
},
  "geometry": {"coordinates":[-84.195527,39.751375],"type":"Point"}
}