{
  "type": "Feature",
  "properties": {
    "addr:full": "4977 Delhi Ave Cincinnati OH 45238",
    "addr:housenumber": "4977",
    "addr:postcode": "45238",
    "addr:street": "Delhi Ave",
    "iso:country": "US",
    "sg:address": "4977 Delhi Ave",
    "sg:city": "Cincinnati",
    "sg:classifiers": [
      {
        "category": "Building \u0026 Trades",
        "subcategory": "Electrical",
        "type": "Services"
      }
    ],
    "sg:phone": "+1 513 347 0404",
    "sg:postcode": "45238",
    "sg:province": "OH",
    "sg:tags": [
      "electric",
      "contractor"
    ],
    "wof:name": "Bonomini Electric Co Inc",
    "wof:placetype": "venue"
  },
  "geometry": {"coordinates":[-84.61258,39.09486],"type":"Point"}
}
