{
  "type": "Feature",
  "properties": {
    "addr:full":"19111 Detroit Rd Cleveland OH 44116",
    "addr:housenumber":"19111",
    "addr:postcode":"44116",
    "addr:street":"Detroit Rd",
    "iso:country":"US",
    "sg:address":"19111 Detroit Rd",
    "sg:city":"Cleveland",
    "sg:classifiers":[
        {
            "category":"Banks & Credit Unions",
            "subcategory":"Investment Brokerage",
            "type":"Services"
        }
    ],
    "sg:phone":"+1 440 333 3300",
    "sg:postcode":"44116",
    "sg:province":"OH",
    "sg:tags":[
        "advisory",
        "financial"
    ],
    "wof:name":"O'Dennell Asset Management",
    "wof:placetype":"venue"
},
  "geometry": {"coordinates":[-81.833952,41.482946],"type":"Point"}
}