{
  "type": "Feature",
  "properties": {
    "addr:full":"1086 Concord Church Rd Chillicothe OH 45601",
    "addr:housenumber":"1086",
    "addr:postcode":"45601",
    "addr:street":"Concord Church Rd",
    "iso:country":"US",
    "sg:address":"1086 Concord Church Rd",
    "sg:city":"Chillicothe",
    "sg:phone":"+1 740 775 7668",
    "sg:postcode":"45601",
    "sg:province":"OH",
    "sg:tags":[
        "beef",
        "farm",
        "corn",
        "soybean",
        "cattle",
        "feedlot"
    ],
    "wof:name":"Timothy Corcoran",
    "wof:placetype":"venue"
},
  "geometry": {"coordinates":[-82.885046,39.303284],"type":"Point"}
}