{
  "type": "Feature",
  "properties": {
    "iso:country":"US",
    "sg:address":"4823 Brookpark Rd",
    "sg:city":"Cleveland",
    "sg:classifiers":[
        {
            "category":"Retail",
            "subcategory":"Auto Repair",
            "type":"Services"
        }
    ],
    "sg:phone":"+1 216 661 5930",
    "sg:postcode":"44134",
    "sg:province":"OH",
    "sg:tags":[
        "repairing",
        "automobile",
        "body"
    ],
    "wof:name":"Todd's Automotive",
    "wof:placetype":"venue"
},
  "geometry": {"coordinates":[-81.719312,41.418693],"type":"Point"}
}