{
  "type": "Feature",
  "properties": {
    "iso:country":"US",
    "sg:address":"43 W Lincoln St",
    "sg:city":"Westerville",
    "sg:classifiers":[
        {
            "category":"Organizations",
            "subcategory":"Religious Organization",
            "type":"Services"
        }
    ],
    "sg:phone":"+1 614 899 7879",
    "sg:postcode":"43081",
    "sg:province":"OH",
    "sg:tags":[
        "clergy"
    ],
    "wof:name":"H Sonntag",
    "wof:placetype":"venue"
},
  "geometry": {"coordinates":[-82.933961,40.128802],"type":"Point"}
}