{
  "type": "Feature",
  "properties": {
    "addr:full": "43 W Lincoln St Westerville OH 43081",
    "addr:housenumber": "43",
    "addr:postcode": "43081",
    "addr:street": "W Lincoln St",
    "iso:country": "US",
    "sg:address": "43 W Lincoln St",
    "sg:city": "Westerville",
    "sg:classifiers": [
      {
        "category": "Organizations",
        "subcategory": "Religious Organization",
        "type": "Services"
      }
    ],
    "sg:phone": "+1 614 899 7879",
    "sg:postcode": "43081",
    "sg:province": "OH",
    "sg:tags": [
      "clergy"
    ],
    "wof:name": "H Sonntag",
    "wof:placetype": "venue"
  },
  "geometry": {"coordinates":[-82.933961,40.128802],"type":"Point"}
}
