{
  "type": "Feature",
  "properties": {
    "iso:country":"US",
    "sg:address":"40889 Carlisle Ave",
    "sg:city":"Elyria",
    "sg:classifiers":[
        {
            "category":"Professional",
            "subcategory":"Accounting & Tax Preparation",
            "type":"Services"
        }
    ],
    "sg:phone":"+1 440 458 8148",
    "sg:postcode":"44035",
    "sg:province":"OH",
    "sg:tags":[
        "accountant"
    ],
    "wof:name":"Carlisle Bookkeeping Svc",
    "wof:placetype":"venue"
},
  "geometry": {"coordinates":[-82.11707699999999,41.331323],"type":"Point"}
}