{
  "type": "Feature",
  "properties": {
    "iso:country":"US",
    "sg:address":"689 Sugar Ln",
    "sg:city":"Elyria",
    "sg:classifiers":[
        {
            "category":"Wholesale",
            "subcategory":"Auto Parts",
            "type":"Manufacturing & Wholesale Goods"
        }
    ],
    "sg:phone":"+1 440 366 5400",
    "sg:postcode":"44035",
    "sg:province":"OH",
    "sg:tags":[
        "foundry",
        "replacement"
    ],
    "wof:name":"CA Picard Surface Engrg Inc",
    "wof:placetype":"venue"
},
  "geometry": {"coordinates":[-82.073044,41.362789],"type":"Point"}
}