{
  "type": "Feature",
  "properties": {
    "addr:full": "689 Sugar Ln Elyria OH 44035",
    "addr:housenumber": "689",
    "addr:postcode": "44035",
    "addr:street": "Sugar Ln",
    "iso:country": "US",
    "sg:address": "689 Sugar Ln",
    "sg:city": "Elyria",
    "sg:classifiers": [
      {
        "category": "Wholesale",
        "subcategory": "Auto Parts",
        "type": "Manufacturing \u0026 Wholesale Goods"
      }
    ],
    "sg:phone": "+1 440 366 5400",
    "sg:postcode": "44035",
    "sg:province": "OH",
    "sg:tags": [
      "foundry",
      "replacement"
    ],
    "wof:name": "CA Picard Surface Engrg Inc",
    "wof:placetype": "venue"
  },
  "geometry": {"coordinates":[-82.073044,41.362789],"type":"Point"}
}
