{
  "type": "Feature",
  "properties": {
    "addr:full":"322 Wyoming Ave Cincinnati OH 45215",
    "addr:housenumber":"322",
    "addr:postcode":"45215",
    "addr:street":"Wyoming Ave",
    "iso:country":"US",
    "sg:address":"322 Wyoming Ave",
    "sg:city":"Cincinnati",
    "sg:classifiers":[
        {
            "category":"Education",
            "subcategory":"Special Training",
            "type":"Public Place"
        },
        {
            "category":"Shopping",
            "subcategory":"Crafts & Fabrics",
            "type":"Retail Goods"
        }
    ],
    "sg:phone":"+1 513 948 9480",
    "sg:postcode":"45215",
    "sg:province":"OH",
    "sg:tags":[
        "school",
        "instruction",
        "art"
    ],
    "sg:website":"http://www.theartworkshopinc.org",
    "wof:name":"The Art Workshop Inc",
    "wof:placetype":"venue"
},
  "geometry": {"coordinates":[-84.467781,39.227236],"type":"Point"}
}