{
  "type": "Feature",
  "properties": {
    "iso:country":"US",
    "sg:address":"2575 Parkman Rd NW",
    "sg:city":"Warren",
    "sg:classifiers":[
        {
            "category":"Professional",
            "type":"Services"
        }
    ],
    "sg:phone":"+1 330 898 5333",
    "sg:postcode":"44485",
    "sg:province":"OH",
    "wof:name":"Cures For Warren",
    "wof:placetype":"venue"
},
  "geometry": {"coordinates":[-80.862082,41.255852],"type":"Point"}
}