{
  "type": "Feature",
  "properties": {
    "addr:full":"3678 Winchell Rd Cleveland OH 44122",
    "addr:housenumber":"3678",
    "addr:postcode":"44122",
    "addr:street":"Winchell Rd",
    "iso:country":"US",
    "sg:address":"3678 Winchell Rd",
    "sg:city":"Cleveland",
    "sg:classifiers":[
        {
            "category":"Local Transit",
            "type":"Transportation"
        }
    ],
    "sg:phone":"+1 216 921 8039",
    "sg:postcode":"44122",
    "sg:province":"OH",
    "sg:tags":[
        "suburban"
    ],
    "wof:name":"Maxs Airport Transportation",
    "wof:placetype":"venue"
},
  "geometry": {"coordinates":[-81.548185,41.459897],"type":"Point"}
}