{
  "type": "Feature",
  "properties": {
    "addr:full":"3201 Croydon Dr NW Canton OH 44718",
    "addr:housenumber":"3201",
    "addr:postcode":"44718",
    "addr:street":"Croydon Dr Nw",
    "iso:country":"US",
    "sg:address":"3201 Croydon Dr NW",
    "sg:city":"Canton",
    "sg:classifiers":[
        {
            "category":"Local Transit",
            "type":"Transportation"
        }
    ],
    "sg:phone":"+1 330 492 2552",
    "sg:postcode":"44718",
    "sg:province":"OH",
    "sg:tags":[
        "passenger"
    ],
    "wof:name":"Woodhall Leasing",
    "wof:placetype":"venue"
},
  "geometry": {"coordinates":[-81.41000699999999,40.831538],"type":"Point"}
}