{
  "type": "Feature",
  "properties": {
    "addr:full":"7010 South Ave Boardman OH 44512",
    "addr:housenumber":"7010",
    "addr:postcode":"44512",
    "addr:street":"South Ave",
    "iso:country":"US",
    "sg:address":"7010 South Ave",
    "sg:city":"Boardman",
    "sg:classifiers":[
        {
            "category":"Government",
            "subcategory":"Office",
            "type":"Public Place"
        }
    ],
    "sg:phone":"+1 330 629 9475",
    "sg:postcode":"44512",
    "sg:province":"OH",
    "sg:tags":[
        "armed",
        "force",
        "recruiting"
    ],
    "wof:name":"US Army Recruiting",
    "wof:placetype":"venue"
},
  "geometry": {"coordinates":[-80.634556,41.027982],"type":"Point"}
}