{
  "type": "Feature",
  "properties": {
    "addr:full": "6555 Corporate Dr Cincinnati OH 45242",
    "addr:housenumber": "6555",
    "addr:postcode": "45242",
    "addr:street": "Corporate Dr",
    "iso:country": "US",
    "sg:address": "6555 Corporate Dr",
    "sg:city": "Cincinnati",
    "sg:classifiers": [
      {
        "category": "Manufacturing",
        "subcategory": "Tools \u0026 Machinery",
        "type": "Manufacturing \u0026 Wholesale Goods"
      },
      {
        "category": "Manufacturing",
        "subcategory": "Electronics",
        "type": "Manufacturing \u0026 Wholesale Goods"
      },
      {
        "category": "Shopping",
        "subcategory": "Computers \u0026 Home Electronics",
        "type": "Retail Goods"
      }
    ],
    "sg:phone": "+1 513 489 2060",
    "sg:postcode": "45242",
    "sg:province": "OH",
    "sg:tags": [
      "electric",
      "consumer",
      "equipment-testing",
      "equipment",
      "supplies-wholesale",
      "manufacturer"
    ],
    "wof:name": "The Midwest Equipment Co Inc",
    "wof:placetype": "venue"
  },
  "geometry": {"coordinates":[-84.360771,39.273241],"type":"Point"}
}
