{
  "type": "Feature",
  "properties": {
    "iso:country":"US",
    "sg:address":"101 W Main St",
    "sg:city":"Lima",
    "sg:classifiers":[
        {
            "category":"Shopping",
            "subcategory":"Gifts & Souvenirs",
            "type":"Retail Goods"
        }
    ],
    "sg:phone":"+1 419 339 2771",
    "sg:postcode":"45807",
    "sg:province":"OH",
    "wof:name":"K S M Management",
    "wof:placetype":"venue"
},
  "geometry": {"coordinates":[-84.204802,40.788592],"type":"Point"}
}