{
  "type": "Feature",
  "properties": {
    "addr:full": "101 W Main St Lima OH 45807",
    "addr:housenumber": "101",
    "addr:postcode": "45807",
    "addr:street": "W Main St",
    "iso:country": "US",
    "sg:address": "101 W Main St",
    "sg:city": "Lima",
    "sg:classifiers": [
      {
        "category": "Shopping",
        "subcategory": "Gifts \u0026 Souvenirs",
        "type": "Retail Goods"
      }
    ],
    "sg:phone": "+1 419 339 2771",
    "sg:postcode": "45807",
    "sg:province": "OH",
    "wof:name": "K S M Management",
    "wof:placetype": "venue"
  },
  "geometry": {"coordinates":[-84.204802,40.788592],"type":"Point"}
}
