{
  "type": "Feature",
  "properties": {
    "addr:full":"4230 State Rte 306 Willoughby OH 44094",
    "addr:housenumber":"4230",
    "addr:postcode":"44094",
    "addr:street":"State Rte 306",
    "iso:country":"US",
    "sg:address":"4230 State Rte 306",
    "sg:city":"Willoughby",
    "sg:classifiers":[
        {
            "category":"Professional",
            "subcategory":"Lawyer & Legal Services",
            "type":"Services"
        }
    ],
    "sg:phone":"+1 440 951 2303",
    "sg:postcode":"44094",
    "sg:province":"OH",
    "sg:tags":[
        "attorney"
    ],
    "wof:name":"Byron & Byron",
    "wof:placetype":"venue"
},
  "geometry": {"coordinates":[-81.373279,41.639606],"type":"Point"}
}