{
  "type": "Feature",
  "properties": {
    "iso:country":"US",
    "sg:address":"5210 Duff Dr",
    "sg:city":"Cincinnati",
    "sg:classifiers":[
        {
            "category":"Manufacturing",
            "subcategory":"Rubber & Plastics",
            "type":"Manufacturing & Wholesale Goods"
        }
    ],
    "sg:phone":"+1 513 870 6400",
    "sg:postcode":"45246",
    "sg:province":"OH",
    "sg:tags":[
        "gasket"
    ],
    "wof:name":"Ohio Valley Gasket Inc",
    "wof:placetype":"venue"
},
  "geometry": {"coordinates":[-84.456048,39.309161],"type":"Point"}
}