{
  "type": "Feature",
  "properties": {
    "addr:full": "4200 Kirby Ave Cincinnati OH 45223",
    "addr:housenumber": "4200",
    "addr:postcode": "45223",
    "addr:street": "Kirby Ave",
    "iso:country": "US",
    "sg:address": "4200 Kirby Ave",
    "sg:city": "Cincinnati",
    "sg:classifiers": [
      {
        "category": "Autos \u0026 Motor Vehicles",
        "subcategory": "Fuel \u0026 Gas Station",
        "type": "Retail Goods"
      }
    ],
    "sg:phone": "+1 513 681 3812",
    "sg:postcode": "45223",
    "sg:province": "OH",
    "sg:tags": [
      "oil"
    ],
    "wof:name": "S \u0026 J Petroleum LTD",
    "wof:placetype": "venue"
  },
  "geometry": {"coordinates":[-84.546703,39.166273],"type":"Point"}
}
