{
  "type": "Feature",
  "properties": {
    "iso:country":"US",
    "sg:address":"4200 Kirby Ave",
    "sg:city":"Cincinnati",
    "sg:classifiers":[
        {
            "category":"Autos & Motor Vehicles",
            "subcategory":"Fuel & Gas Station",
            "type":"Retail Goods"
        }
    ],
    "sg:phone":"+1 513 681 3812",
    "sg:postcode":"45223",
    "sg:province":"OH",
    "sg:tags":[
        "oil"
    ],
    "wof:name":"S & J Petroleum LTD",
    "wof:placetype":"venue"
},
  "geometry": {"coordinates":[-84.546703,39.166273],"type":"Point"}
}