{
  "type": "Feature",
  "properties": {
    "addr:full": "37 W Broad St Columbus OH 43215",
    "addr:housenumber": "37",
    "addr:postcode": "43215",
    "addr:street": "W Broad St",
    "iso:country": "US",
    "sg:address": "37 W Broad St",
    "sg:city": "Columbus",
    "sg:classifiers": [
      {
        "category": "Professional",
        "subcategory": "Accounting \u0026 Tax Preparation",
        "type": "Services"
      }
    ],
    "sg:phone": "+1 614 224 2164",
    "sg:postcode": "43215",
    "sg:province": "OH",
    "sg:tags": [
      "firm",
      "accountant",
      "public"
    ],
    "sg:website": "www.johngerlach.com",
    "wof:name": "John Gerlach \u0026 Company",
    "wof:placetype": "venue"
  },
  "geometry": {"coordinates":[-83.002217,39.961974],"type":"Point"}
}
