{
  "type": "Feature",
  "properties": {
    "iso:country":"US",
    "sg:address":"110 Boggs Ln",
    "sg:city":"Cincinnati",
    "sg:classifiers":[
        {
            "category":"Professional",
            "type":"Services"
        }
    ],
    "sg:phone":"+1 513 721 5588",
    "sg:postcode":"45246",
    "sg:province":"OH",
    "wof:name":"CBC Credit Svc Inc",
    "wof:placetype":"venue"
},
  "geometry": {"coordinates":[-84.470384,39.284629],"type":"Point"}
}