{
  "type": "Feature",
  "properties": {
    "addr:full": "3780 Eakins Rd Cuyahoga Falls OH 44223",
    "addr:housenumber": "3780",
    "addr:postcode": "44223",
    "addr:street": "Eakins Rd",
    "iso:country": "US",
    "sg:address": "3780 Eakins Rd",
    "sg:city": "Cuyahoga Falls",
    "sg:classifiers": [
      {
        "category": "Building \u0026 Trades",
        "subcategory": "Construction",
        "type": "Services"
      }
    ],
    "sg:phone": "+1 330 920 1521",
    "sg:postcode": "44223",
    "sg:province": "OH",
    "sg:tags": [
      "house"
    ],
    "wof:name": "Biro Construction",
    "wof:placetype": "venue"
  },
  "geometry": {"coordinates":[-81.516008,41.18628],"type":"Point"}
}
