{
  "type": "Feature",
  "properties": {
    "iso:country":"US",
    "sg:address":"3780 Eakins Rd",
    "sg:city":"Cuyahoga Falls",
    "sg:classifiers":[
        {
            "category":"Building & Trades",
            "subcategory":"Construction",
            "type":"Services"
        }
    ],
    "sg:phone":"+1 330 920 1521",
    "sg:postcode":"44223",
    "sg:province":"OH",
    "sg:tags":[
        "house"
    ],
    "wof:name":"Biro Construction",
    "wof:placetype":"venue"
},
  "geometry": {"coordinates":[-81.516008,41.18628],"type":"Point"}
}