{
  "type": "Feature",
  "properties": {
    "iso:country":"US",
    "sg:address":"6887 Brandywine Rd",
    "sg:city":"Cleveland",
    "sg:classifiers":[
        {
            "category":"Building & Trades",
            "subcategory":"Construction",
            "type":"Services"
        }
    ],
    "sg:phone":"+1 440 843 6010",
    "sg:postcode":"44130",
    "sg:province":"OH",
    "sg:tags":[
        "glass",
        "glazing",
        "contractor"
    ],
    "wof:name":"Glass Services of Ne Ohio",
    "wof:placetype":"venue"
},
  "geometry": {"coordinates":[-81.75349300000001,41.377505],"type":"Point"}
}