{
  "type": "Feature",
  "properties": {
    "addr:full": "801 Havens Corners Rd Gahanna OH 43230",
    "addr:housenumber": "801",
    "addr:postcode": "43230",
    "addr:street": "Havens Corners Rd",
    "iso:country": "US",
    "sg:address": "801 Havens Corners Rd",
    "sg:city": "Gahanna",
    "sg:classifiers": [
      {
        "category": "Social Services",
        "subcategory": "Child Care",
        "type": "Services"
      }
    ],
    "sg:phone": "+1 614 471 6693",
    "sg:postcode": "43230",
    "sg:province": "OH",
    "wof:name": "St Matthew Child Care",
    "wof:placetype": "venue"
  },
  "geometry": {"coordinates":[-82.85466,40.017664],"type":"Point"}
}
