{
  "type": "Feature",
  "properties": {
    "addr:full": "11443 Twin Mills Ln Chardon OH 44024",
    "addr:housenumber": "11443",
    "addr:postcode": "44024",
    "addr:street": "Twin Mills Ln",
    "iso:country": "US",
    "sg:address": "11443 Twin Mills Ln",
    "sg:city": "Chardon",
    "sg:classifiers": [
      {
        "category": "Professional",
        "subcategory": "Computer Services",
        "type": "Services"
      }
    ],
    "sg:phone": "+1 440 286 9101",
    "sg:postcode": "44024",
    "sg:province": "OH",
    "sg:tags": [
      "internet"
    ],
    "sg:website": "www.edissnet.com",
    "wof:name": "EDI Support Svc",
    "wof:placetype": "venue"
  },
  "geometry": {"coordinates":[-81.260852,41.557669],"type":"Point"}
}
