{
  "type": "Feature",
  "properties": {
    "addr:full": "10501 Columbus Expressway Park Pataskala OH 43062",
    "addr:housenumber": "10501",
    "addr:postcode": "43062",
    "addr:street": "Columbus Expressway Park",
    "iso:country": "US",
    "sg:address": "10501 Columbus Expressway Park",
    "sg:city": "Pataskala",
    "sg:classifiers": [
      {
        "category": "Shopping",
        "subcategory": "Used Merchandise",
        "type": "Retail Goods"
      }
    ],
    "sg:phone": "+1 740 927 2276",
    "sg:postcode": "43062",
    "sg:province": "OH",
    "sg:tags": [
      "flea",
      "market"
    ],
    "wof:name": "Red Barn Flea Market \u0026 Auto",
    "wof:placetype": "venue"
  },
  "geometry": {"coordinates":[-82.689149,39.948569],"type":"Point"}
}
