{
  "type": "Feature",
  "properties": {
    "addr:full": "5531 Canal Rd Cleveland OH 44125",
    "addr:housenumber": "5531",
    "addr:postcode": "44125",
    "addr:street": "Canal Rd",
    "iso:country": "US",
    "sg:address": "5531 Canal Rd",
    "sg:city": "Cleveland",
    "sg:classifiers": [
      {
        "category": "Mining \u0026 Drilling",
        "type": "Manufacturing \u0026 Wholesale Goods"
      }
    ],
    "sg:phone": "+1 216 524 0999",
    "sg:postcode": "44125",
    "sg:province": "OH",
    "sg:tags": [
      "stone"
    ],
    "sg:website": "www.indrec.com",
    "wof:name": "Independence Recycling",
    "wof:placetype": "venue"
  },
  "geometry": {"coordinates":[-81.628239,41.409764],"type":"Point"}
}
