{
  "type": "Feature",
  "properties": {
    "iso:country":"US",
    "sg:address":"5531 Canal Rd",
    "sg:city":"Cleveland",
    "sg:classifiers":[
        {
            "category":"Mining & Drilling",
            "type":"Manufacturing & Wholesale Goods"
        }
    ],
    "sg:phone":"+1 216 524 0999",
    "sg:postcode":"44125",
    "sg:province":"OH",
    "sg:tags":[
        "stone"
    ],
    "sg:website":"www.indrec.com",
    "wof:name":"Independence Recycling",
    "wof:placetype":"venue"
},
  "geometry": {"coordinates":[-81.62823899999999,41.409764],"type":"Point"}
}