{
  "type": "Feature",
  "properties": {
    "iso:country":"US",
    "sg:address":"6550 Camden Row Rd",
    "sg:city":"Dublin",
    "sg:classifiers":[
        {
            "category":"Building & Trades",
            "subcategory":"Construction",
            "type":"Services"
        }
    ],
    "sg:phone":"+1 614 799 0339",
    "sg:postcode":"43016",
    "sg:province":"OH",
    "sg:tags":[
        "home",
        "builder"
    ],
    "wof:name":"Trinity Homes",
    "wof:placetype":"venue"
},
  "geometry": {"coordinates":[-83.164422,40.131083],"type":"Point"}
}