{
  "type": "Feature",
  "properties": {
    "addr:full":"10600 Springfield Pike Cincinnati OH 45215",
    "addr:housenumber":"10600",
    "addr:postcode":"45215",
    "addr:street":"Springfield Pike",
    "iso:country":"US",
    "sg:address":"10600 Springfield Pike",
    "sg:city":"Cincinnati",
    "sg:classifiers":[
        {
            "category":"Social Services",
            "type":"Services"
        },
        {
            "category":"Shopping",
            "subcategory":"Used Merchandise",
            "type":"Retail Goods"
        },
        {
            "category":"Banks & Credit Unions",
            "subcategory":"Bank",
            "type":"Services"
        },
        {
            "category":"Shopping",
            "subcategory":"Thrift Store",
            "type":"Retail Goods"
        },
        {
            "category":"Organizations",
            "subcategory":"Non-profit Organization",
            "type":"Services"
        }
    ],
    "sg:phone":"+1 513 771 4800",
    "sg:postcode":"45215",
    "sg:province":"OH",
    "sg:tags":[
        "shop",
        "foundations-educational",
        "philanthropic",
        "research",
        "resale",
        "second",
        "hand",
        "furniture",
        "charity"
    ],
    "sg:website":"http://www.ypad.com/business-profile.cfm/state/OH/city/Woodlawn/ppid/7894",
    "wof:name":"Goodwill Industries",
    "wof:placetype":"venue"
},
  "geometry": {"coordinates":[-84.469318,39.262837],"type":"Point"}
}