{
  "type": "Feature",
  "properties": {
    "addr:full": "5828 Zarley St New Albany OH 43054",
    "addr:housenumber": "5828",
    "addr:postcode": "43054",
    "addr:street": "Zarley St",
    "iso:country": "US",
    "sg:address": "5828 Zarley St",
    "sg:city": "New Albany",
    "sg:classifiers": [
      {
        "category": "Banks \u0026 Credit Unions",
        "subcategory": "Investment Brokerage",
        "type": "Services"
      }
    ],
    "sg:phone": "+1 614 775 0856",
    "sg:postcode": "43054",
    "sg:province": "OH",
    "sg:tags": [
      "advisory",
      "financial"
    ],
    "wof:name": "Donald Walsh \u0026 Assoc",
    "wof:placetype": "venue"
  },
  "geometry": {"coordinates":[-82.79472,40.087853],"type":"Point"}
}
