{
  "type": "Feature",
  "properties": {
    "addr:full": "806 Crestview Ave Wilmington OH 45177",
    "addr:housenumber": "806",
    "addr:postcode": "45177",
    "addr:street": "Crestview Ave",
    "iso:country": "US",
    "sg:address": "806 Crestview Ave",
    "sg:city": "Wilmington",
    "sg:classifiers": [
      {
        "category": "Professional",
        "type": "Services"
      }
    ],
    "sg:phone": "+1 937 655 9099",
    "sg:postcode": "45177",
    "sg:province": "OH",
    "wof:name": "Planning With Purpose Inc",
    "wof:placetype": "venue"
  },
  "geometry": {"coordinates":[-83.846803,39.434717],"type":"Point"}
}
