{
  "type": "Feature",
  "properties": {
    "addr:full":"1923 Bailey Rd Cuyahoga Falls OH 44221",
    "addr:housenumber":"1923",
    "addr:postcode":"44221",
    "addr:street":"Bailey Rd",
    "iso:country":"US",
    "sg:address":"1923 Bailey Rd",
    "sg:city":"Cuyahoga Falls",
    "sg:classifiers":[
        {
            "category":"Real Estate",
            "subcategory":"Surveying",
            "type":"Services"
        }
    ],
    "sg:phone":"+1 330 945 4117",
    "sg:postcode":"44221",
    "sg:province":"OH",
    "sg:tags":[
        "surveyor"
    ],
    "sg:website":"www.campbellsurvey.com",
    "wof:name":"Campbell & Assoc Inc",
    "wof:placetype":"venue"
},
  "geometry": {"coordinates":[-81.46610699999999,41.133007],"type":"Point"}
}