{
  "type": "Feature",
  "properties": {
    "addr:full": "15545 W High St Middlefield OH 44062",
    "addr:housenumber": "15545",
    "addr:postcode": "44062",
    "addr:street": "W High St",
    "iso:country": "US",
    "sg:address": "15545 W High St",
    "sg:city": "Middlefield",
    "sg:classifiers": [
      {
        "category": "Banks \u0026 Credit Unions",
        "subcategory": "Bank",
        "type": "Services"
      }
    ],
    "sg:phone": "+1 440 632 1666",
    "sg:postcode": "44062",
    "sg:province": "OH",
    "sg:website": "www.middlefieldbank.com",
    "wof:name": "Middlefield Banking Co",
    "wof:placetype": "venue"
  },
  "geometry": {"coordinates":[-81.091499,41.463224],"type":"Point"}
}
