{
  "type": "Feature",
  "properties": {
    "iso:country":"US",
    "sg:address":"2531 N Park Blvd",
    "sg:city":"Cleveland",
    "sg:classifiers":[
        {
            "category":"Professional",
            "type":"Services"
        }
    ],
    "sg:phone":"+1 216 321 3301",
    "sg:postcode":"44106",
    "sg:province":"OH",
    "wof:name":"Banbury Jullian",
    "wof:placetype":"venue"
},
  "geometry": {"coordinates":[-81.588817,41.492058],"type":"Point"}
}