{
  "type": "Feature",
  "properties": {
    "iso:country":"US",
    "sg:address":"42841 Carbon Hill Buchtel Rd",
    "sg:city":"Nelsonville",
    "sg:classifiers":[
        {
            "category":"Retail",
            "subcategory":"Auto Repair",
            "type":"Services"
        }
    ],
    "sg:phone":"+1 740 753 4113",
    "sg:postcode":"45764",
    "sg:province":"OH",
    "sg:tags":[
        "repairing",
        "automobile"
    ],
    "wof:name":"Baden's I Care Auto Repair",
    "wof:placetype":"venue"
},
  "geometry": {"coordinates":[-82.220123,39.49824],"type":"Point"}
}