{
  "type": "Feature",
  "properties": {
    "iso:country":"US",
    "sg:address":"726 E Wilbeth Rd",
    "sg:city":"Akron",
    "sg:classifiers":[
        {
            "category":"Food & Beverages",
            "subcategory":"Groceries & Convenience Stores",
            "type":"Retail Goods"
        }
    ],
    "sg:phone":"+1 330 724 4425",
    "sg:postcode":"44306",
    "sg:province":"OH",
    "wof:name":"Total Convenience Mart",
    "wof:placetype":"venue"
},
  "geometry": {"coordinates":[-81.501053,41.039728],"type":"Point"}
}