{
  "type": "Feature",
  "properties": {
    "addr:full": "726 E Wilbeth Rd Akron OH 44306",
    "addr:housenumber": "726",
    "addr:postcode": "44306",
    "addr:street": "E Wilbeth Rd",
    "iso:country": "US",
    "sg:address": "726 E Wilbeth Rd",
    "sg:city": "Akron",
    "sg:classifiers": [
      {
        "category": "Food \u0026 Beverages",
        "subcategory": "Groceries \u0026 Convenience Stores",
        "type": "Retail Goods"
      }
    ],
    "sg:phone": "+1 330 724 4425",
    "sg:postcode": "44306",
    "sg:province": "OH",
    "wof:name": "Total Convenience Mart",
    "wof:placetype": "venue"
  },
  "geometry": {"coordinates":[-81.501053,41.039728],"type":"Point"}
}
