{
  "type": "Feature",
  "properties": {
    "addr:full":"2733 Mc Kinley Ave Cincinnati OH 45211",
    "addr:housenumber":"2733",
    "addr:postcode":"45211",
    "addr:street":"Mc Kinley Ave",
    "iso:country":"US",
    "sg:address":"2733 Mc Kinley Ave",
    "sg:city":"Cincinnati",
    "sg:classifiers":[
        {
            "category":"Professional",
            "subcategory":"Art Services",
            "type":"Services"
        }
    ],
    "sg:phone":"+1 513 481 5836",
    "sg:postcode":"45211",
    "sg:province":"OH",
    "sg:tags":[
        "graphic",
        "designer"
    ],
    "wof:name":"Kelby & Teresa Bowers Graphics",
    "wof:placetype":"venue"
},
  "geometry": {"coordinates":[-84.592624,39.143273],"type":"Point"}
}