{
  "type": "Feature",
  "properties": {
    "iso:country":"US",
    "sg:address":"3501 Monroe St",
    "sg:city":"Bellaire",
    "sg:classifiers":[
        {
            "category":"Organizations",
            "subcategory":"Religious Organization",
            "type":"Services"
        }
    ],
    "sg:phone":"+1 740 676 1678",
    "sg:postcode":"43906",
    "sg:province":"OH",
    "sg:tags":[
        "church"
    ],
    "wof:name":"Pilgrim Rest Baptist Church",
    "wof:placetype":"venue"
},
  "geometry": {"coordinates":[-80.74548900000001,40.018343],"type":"Point"}
}