{
  "type": "Feature",
  "properties": {
    "addr:full": "3501 Monroe St Bellaire OH 43906",
    "addr:housenumber": "3501",
    "addr:postcode": "43906",
    "addr:street": "Monroe St",
    "iso:country": "US",
    "sg:address": "3501 Monroe St",
    "sg:city": "Bellaire",
    "sg:classifiers": [
      {
        "category": "Organizations",
        "subcategory": "Religious Organization",
        "type": "Services"
      }
    ],
    "sg:phone": "+1 740 676 1678",
    "sg:postcode": "43906",
    "sg:province": "OH",
    "sg:tags": [
      "church"
    ],
    "wof:name": "Pilgrim Rest Baptist Church",
    "wof:placetype": "venue"
  },
  "geometry": {"coordinates":[-80.745489,40.018343],"type":"Point"}
}
