{
  "type": "Feature",
  "properties": {
    "addr:full":"14689 E Twp Rd 58 Attica OH 44807",
    "addr:housenumber":"14689;58",
    "addr:postcode":"44807",
    "addr:street":"E Twp Rd",
    "iso:country":"US",
    "sg:address":"14689 E Twp Rd 58",
    "sg:city":"Attica",
    "sg:classifiers":[
        {
            "category":"Building & Trades",
            "subcategory":"Construction",
            "type":"Services"
        }
    ],
    "sg:phone":"+1 419 426 3445",
    "sg:postcode":"44807",
    "sg:province":"OH",
    "sg:tags":[
        "carpentry",
        "contractor"
    ],
    "wof:name":"Dave Stallings Builder",
    "wof:placetype":"venue"
},
  "geometry": {"coordinates":[-82.886572,41.037363],"type":"Point"}
}