{
  "type": "Feature",
  "properties": {
    "addr:full":"7537 Mentor Ave Mentor OH 44060",
    "addr:housenumber":"7537",
    "addr:postcode":"44060",
    "addr:street":"Mentor Ave",
    "iso:country":"US",
    "sg:address":"7537 Mentor Ave",
    "sg:city":"Mentor",
    "sg:classifiers":[
        {
            "category":"Banks & Credit Unions",
            "subcategory":"Bank",
            "type":"Services"
        }
    ],
    "sg:phone":"+1 440 951 9702",
    "sg:postcode":"44060",
    "sg:province":"OH",
    "sg:tags":[
        "loan",
        "real estate"
    ],
    "wof:name":"First Ohio Banc & Lending Inc",
    "wof:placetype":"venue"
},
  "geometry": {"coordinates":[-81.37150699999999,41.656443],"type":"Point"}
}