{
  "type": "Feature",
  "properties": {
    "addr:full": "8929 Freeway Dr Macedonia OH 44056",
    "addr:housenumber": "8929",
    "addr:postcode": "44056",
    "addr:street": "Freeway Dr",
    "iso:country": "US",
    "sg:address": "8929 Freeway Dr",
    "sg:city": "Macedonia",
    "sg:classifiers": [
      {
        "category": "Building \u0026 Trades",
        "subcategory": "Electrical",
        "type": "Services"
      },
      {
        "category": "Wholesale",
        "subcategory": "Electrical",
        "type": "Manufacturing \u0026 Wholesale Goods"
      }
    ],
    "sg:phone": "+1 330 883 9800",
    "sg:postcode": "44056",
    "sg:province": "OH",
    "sg:tags": [
      "drive",
      "electric",
      "motor",
      "contractor"
    ],
    "sg:website": "www.baldor.com",
    "wof:name": "Baldor Electric Company",
    "wof:placetype": "venue"
  },
  "geometry": {"coordinates":[-81.511259,41.313857],"type":"Point"}
}
