{
  "type": "Feature",
  "properties": {
    "iso:country":"US",
    "sg:address":"113 Louisiana Ave",
    "sg:city":"Perrysburg",
    "sg:classifiers":[
        {
            "category":"Retail",
            "subcategory":"Animal Services",
            "type":"Services"
        }
    ],
    "sg:phone":"+1 419 874 3836",
    "sg:postcode":"43551",
    "sg:province":"OH",
    "wof:name":"Pet Spa",
    "wof:placetype":"venue"
},
  "geometry": {"coordinates":[-83.629318,41.559503],"type":"Point"}
}