{
  "type": "Feature",
  "properties": {
    "iso:country":"US",
    "sg:address":"560 Forestview Rd",
    "sg:city":"Bay Village",
    "sg:classifiers":[
        {
            "category":"Building & Trades",
            "subcategory":"Construction",
            "type":"Services"
        }
    ],
    "sg:phone":"+1 440 892 9562",
    "sg:postcode":"44140",
    "sg:province":"OH",
    "sg:tags":[
        "house"
    ],
    "wof:name":"Topshelf Builders",
    "wof:placetype":"venue"
},
  "geometry": {"coordinates":[-81.89634599999999,41.47943],"type":"Point"}
}