{
  "type": "Feature",
  "properties": {
    "addr:full": "560 Forestview Rd Bay Village OH 44140",
    "addr:housenumber": "560",
    "addr:postcode": "44140",
    "addr:street": "Forestview Rd",
    "iso:country": "US",
    "sg:address": "560 Forestview Rd",
    "sg:city": "Bay Village",
    "sg:classifiers": [
      {
        "category": "Building \u0026 Trades",
        "subcategory": "Construction",
        "type": "Services"
      }
    ],
    "sg:phone": "+1 440 892 9562",
    "sg:postcode": "44140",
    "sg:province": "OH",
    "sg:tags": [
      "house"
    ],
    "wof:name": "Topshelf Builders",
    "wof:placetype": "venue"
  },
  "geometry": {"coordinates":[-81.896346,41.47943],"type":"Point"}
}
