{
  "type": "Feature",
  "properties": {
    "addr:full": "7799 Kate Brown Dr Dublin OH 43017",
    "addr:housenumber": "7799",
    "addr:postcode": "43017",
    "addr:street": "Kate Brown Dr",
    "iso:country": "US",
    "sg:address": "7799 Kate Brown Dr",
    "sg:city": "Dublin",
    "sg:classifiers": [
      {
        "category": "Professional",
        "type": "Services"
      }
    ],
    "sg:phone": "+1 614 734 0070",
    "sg:postcode": "43017",
    "sg:province": "OH",
    "sg:tags": [
      "establishment"
    ],
    "wof:name": "Strategic Moves",
    "wof:placetype": "venue"
  },
  "geometry": {"coordinates":[-83.129033,40.126321],"type":"Point"}
}
