{
  "type": "Feature",
  "properties": {
    "addr:full":"126 S Main St Dayton OH 45402",
    "addr:housenumber":"126",
    "addr:postcode":"45402",
    "addr:street":"S Main St",
    "iso:country":"US",
    "sg:address":"126 S Main St",
    "sg:city":"Dayton",
    "sg:classifiers":[
        {
            "category":"Communications",
            "subcategory":"Radio Station",
            "type":"Services"
        }
    ],
    "sg:phone":"+1 937 222 8950",
    "sg:postcode":"45402",
    "sg:province":"OH",
    "sg:tags":[
        "company",
        "broadcasting"
    ],
    "wof:name":"WDPR",
    "wof:placetype":"venue"
},
  "geometry": {"coordinates":[-84.191025,39.757285],"type":"Point"}
}