{
  "type": "Feature",
  "properties": {
    "addr:full":"5422 E 96th St Cleveland OH 44125",
    "addr:housenumber":"5422",
    "addr:postcode":"44125",
    "addr:street":"E 96Th St",
    "iso:country":"US",
    "sg:address":"5422 E 96th St",
    "sg:city":"Cleveland",
    "sg:classifiers":[
        {
            "category":"Professional",
            "subcategory":"Art Services",
            "type":"Services"
        }
    ],
    "sg:phone":"+1 216 581 3178",
    "sg:postcode":"44125",
    "sg:province":"OH",
    "sg:tags":[
        "artist"
    ],
    "wof:name":"Ron Kurtz Illustrator",
    "wof:placetype":"venue"
},
  "geometry": {"coordinates":[-81.61787099999999,41.414029],"type":"Point"}
}