{
  "type": "Feature",
  "properties": {
    "addr:full": "200 Harding Ave Kenton OH 43326",
    "addr:housenumber": "200",
    "addr:postcode": "43326",
    "addr:street": "Harding Ave",
    "iso:country": "US",
    "sg:address": "200 Harding Ave",
    "sg:city": "Kenton",
    "sg:classifiers": [
      {
        "category": "Education",
        "subcategory": "School",
        "type": "Public Place"
      }
    ],
    "sg:phone": "+1 419 673 1286",
    "sg:postcode": "43326",
    "sg:province": "OH",
    "sg:website": "www.kenton.k12.oh.us",
    "wof:name": "Kenton Senior High School",
    "wof:placetype": "venue"
  },
  "geometry": {"coordinates":[-83.597553,40.654041],"type":"Point"}
}
