{
  "type": "Feature",
  "properties": {
    "addr:full": "6264 Eaton Lewisburg Rd Lewisburg OH 45338",
    "addr:housenumber": "6264",
    "addr:postcode": "45338",
    "addr:street": "Eaton Lewisburg Rd",
    "iso:country": "US",
    "sg:address": "6264 Eaton Lewisburg Rd",
    "sg:city": "Lewisburg",
    "sg:classifiers": [
      {
        "category": "Farming",
        "subcategory": "Farm",
        "type": "Manufacturing \u0026 Wholesale Goods"
      }
    ],
    "sg:phone": "+1 937 962 4634",
    "sg:postcode": "45338",
    "sg:province": "OH",
    "sg:tags": [
      "crop",
      "general"
    ],
    "wof:name": "David W Arnett",
    "wof:placetype": "venue"
  },
  "geometry": {"coordinates":[-84.553694,39.814403],"type":"Point"}
}
