{
  "type": "Feature",
  "properties": {
    "addr:full": "9871 Waterstone Blvd Cincinnati OH 45249",
    "addr:housenumber": "9871",
    "addr:postcode": "45249",
    "addr:street": "Waterstone Blvd",
    "iso:country": "US",
    "sg:address": "9871 Waterstone Blvd",
    "sg:city": "Cincinnati",
    "sg:classifiers": [
      {
        "category": "Home \u0026 Garden",
        "subcategory": "Household Appliances",
        "type": "Retail Goods"
      }
    ],
    "sg:phone": "+1 513 683 7777",
    "sg:postcode": "45249",
    "sg:province": "OH",
    "sg:tags": [
      "electronics",
      "consumer"
    ],
    "wof:name": "Best Buy Co Inc",
    "wof:placetype": "venue"
  },
  "geometry": {"coordinates":[-84.3056,39.292762],"type":"Point"}
}
