{
  "type": "Feature",
  "properties": {
    "addr:full": "2971 Saddleback Dr Cincinnati OH 45244",
    "addr:housenumber": "2971",
    "addr:postcode": "45244",
    "addr:street": "Saddleback Dr",
    "iso:country": "US",
    "sg:address": "2971 Saddleback Dr",
    "sg:city": "Cincinnati",
    "sg:classifiers": [
      {
        "category": "Wholesale",
        "subcategory": "Sporting Goods",
        "type": "Manufacturing \u0026 Wholesale Goods"
      }
    ],
    "sg:phone": "+1 513 232 5355",
    "sg:postcode": "45244",
    "sg:province": "OH",
    "sg:tags": [
      "tackle",
      "fishing"
    ],
    "wof:name": "Queen City Tackle",
    "wof:placetype": "venue"
  },
  "geometry": {"coordinates":[-84.382345,39.114192],"type":"Point"}
}
