{
  "type": "Feature",
  "properties": {
    "iso:country":"US",
    "sg:address":"2971 Saddleback Dr",
    "sg:city":"Cincinnati",
    "sg:classifiers":[
        {
            "category":"Wholesale",
            "subcategory":"Sporting Goods",
            "type":"Manufacturing & Wholesale Goods"
        }
    ],
    "sg:phone":"+1 513 232 5355",
    "sg:postcode":"45244",
    "sg:province":"OH",
    "sg:tags":[
        "tackle",
        "fishing"
    ],
    "wof:name":"Queen City Tackle",
    "wof:placetype":"venue"
},
  "geometry": {"coordinates":[-84.382345,39.114192],"type":"Point"}
}