{
  "type": "Feature",
  "properties": {
    "addr:full": "6000 W Creek Rd Cleveland OH 44131",
    "addr:housenumber": "6000",
    "addr:postcode": "44131",
    "addr:street": "W Creek Rd",
    "iso:country": "US",
    "sg:address": "6000 W Creek Rd",
    "sg:city": "Cleveland",
    "sg:classifiers": [
      {
        "category": "Wholesale",
        "subcategory": "Electrical",
        "type": "Manufacturing \u0026 Wholesale Goods"
      }
    ],
    "sg:phone": "+1 216 524 5930",
    "sg:postcode": "44131",
    "sg:province": "OH",
    "sg:tags": [
      "instrument",
      "electronic"
    ],
    "wof:name": "WKM Assoc",
    "wof:placetype": "venue"
  },
  "geometry": {"coordinates":[-81.652968,41.404676],"type":"Point"}
}
