{
  "type": "Feature",
  "properties": {
    "iso:country":"US",
    "sg:address":"6000 W Creek Rd",
    "sg:city":"Cleveland",
    "sg:classifiers":[
        {
            "category":"Wholesale",
            "subcategory":"Electrical",
            "type":"Manufacturing & Wholesale Goods"
        }
    ],
    "sg:phone":"+1 216 524 5930",
    "sg:postcode":"44131",
    "sg:province":"OH",
    "sg:tags":[
        "instrument",
        "electronic"
    ],
    "wof:name":"WKM Assoc",
    "wof:placetype":"venue"
},
  "geometry": {"coordinates":[-81.652968,41.404676],"type":"Point"}
}