{
  "type": "Feature",
  "properties": {
    "addr:full": "8800 Lyra Dr Ste 690 Columbus OH 43240",
    "addr:housenumber": "8800",
    "addr:postcode": "43240",
    "addr:street": "Lyra Dr Ste 690",
    "iso:country": "US",
    "sg:address": "8800 Lyra Dr Ste 690",
    "sg:city": "Columbus",
    "sg:classifiers": [
      {
        "category": "Banks \u0026 Credit Unions",
        "subcategory": "Investment Brokerage",
        "type": "Services"
      },
      {
        "category": "Banks \u0026 Credit Unions",
        "subcategory": "Bank",
        "type": "Services"
      },
      {
        "category": "Banks \u0026 Credit Unions",
        "subcategory": "Financial Services",
        "type": "Services"
      }
    ],
    "sg:phone": "+1 614 430 8412",
    "sg:postcode": "43240",
    "sg:province": "OH",
    "sg:tags": [
      "bond",
      "advisory",
      "management",
      "broker",
      "stock"
    ],
    "sg:website": "http://www.ameritas.com",
    "wof:name": "Ameritas Life Insurance Corp",
    "wof:placetype": "venue"
  },
  "geometry": {"coordinates":[-82.97538,40.14489],"type":"Point"}
}
