{
  "type": "Feature",
  "properties": {
    "iso:country":"US",
    "sg:address":"8800 Lyra Dr Ste 690",
    "sg:city":"Columbus",
    "sg:classifiers":[
        {
            "category":"Banks & Credit Unions",
            "subcategory":"Investment Brokerage",
            "type":"Services"
        },
        {
            "category":"Banks & Credit Unions",
            "subcategory":"Bank",
            "type":"Services"
        },
        {
            "category":"Banks & Credit Unions",
            "subcategory":"Financial Services",
            "type":"Services"
        }
    ],
    "sg:phone":"+1 614 430 8412",
    "sg:postcode":"43240",
    "sg:province":"OH",
    "sg:tags":[
        "bond",
        "advisory",
        "management",
        "broker",
        "stock"
    ],
    "sg:website":"http://www.ameritas.com",
    "wof:name":"Ameritas Life Insurance Corp",
    "wof:placetype":"venue"
},
  "geometry": {"coordinates":[-82.97538,40.14489],"type":"Point"}
}