{
  "type": "Feature",
  "properties": {
    "iso:country":"US",
    "sg:address":"10738 Kenwood Rd",
    "sg:city":"Cincinnati",
    "sg:classifiers":[
        {
            "category":"Restaurant",
            "type":"Food & Drink"
        }
    ],
    "sg:phone":"+1 513 791 2199",
    "sg:postcode":"45242",
    "sg:province":"OH",
    "sg:website":"www.throughthegarden.com",
    "wof:name":"Through The Garden Ltd",
    "wof:placetype":"venue"
},
  "geometry": {"coordinates":[-84.373751,39.263685],"type":"Point"}
}