{
  "type": "Feature",
  "properties": {
    "addr:full": "10738 Kenwood Rd Cincinnati OH 45242",
    "addr:housenumber": "10738",
    "addr:postcode": "45242",
    "addr:street": "Kenwood Rd",
    "iso:country": "US",
    "sg:address": "10738 Kenwood Rd",
    "sg:city": "Cincinnati",
    "sg:classifiers": [
      {
        "category": "Restaurant",
        "type": "Food \u0026 Drink"
      }
    ],
    "sg:phone": "+1 513 791 2199",
    "sg:postcode": "45242",
    "sg:province": "OH",
    "sg:website": "www.throughthegarden.com",
    "wof:name": "Through The Garden Ltd",
    "wof:placetype": "venue"
  },
  "geometry": {"coordinates":[-84.373751,39.263685],"type":"Point"}
}
