{
  "type": "Feature",
  "properties": {
    "addr:full": "40 Shoshone Trl Malvern OH 44644",
    "addr:housenumber": "40",
    "addr:postcode": "44644",
    "addr:street": "Shoshone Trl",
    "iso:country": "US",
    "sg:address": "40 Shoshone Trl",
    "sg:city": "Malvern",
    "sg:classifiers": [
      {
        "category": "Professional",
        "type": "Services"
      }
    ],
    "sg:phone": "+1 330 863 1960",
    "sg:postcode": "44644",
    "sg:province": "OH",
    "wof:name": "Sherman \u0026 Son Inc",
    "wof:placetype": "venue"
  },
  "geometry": {"coordinates":[-81.18412,40.670517],"type":"Point"}
}
