{
  "type": "Feature",
  "properties": {
    "iso:country":"US",
    "sg:address":"40 Shoshone Trl",
    "sg:city":"Malvern",
    "sg:classifiers":[
        {
            "category":"Professional",
            "type":"Services"
        }
    ],
    "sg:phone":"+1 330 863 1960",
    "sg:postcode":"44644",
    "sg:province":"OH",
    "wof:name":"Sherman & Son Inc",
    "wof:placetype":"venue"
},
  "geometry": {"coordinates":[-81.18411999999999,40.670517],"type":"Point"}
}