{
  "type": "Feature",
  "properties": {
    "addr:full":"7198 Industrial Park Blvd Mentor OH 44060",
    "addr:housenumber":"7198",
    "addr:postcode":"44060",
    "addr:street":"Industrial Park Blvd",
    "iso:country":"US",
    "sg:address":"7198 Industrial Park Blvd",
    "sg:city":"Mentor",
    "sg:classifiers":[
        {
            "category":"Manufacturing",
            "subcategory":"Building Materials",
            "type":"Manufacturing & Wholesale Goods"
        }
    ],
    "sg:phone":"+1 440 942 0205",
    "sg:postcode":"44060",
    "sg:province":"OH",
    "sg:tags":[
        "mfg",
        "fine",
        "architectural",
        "cabinetry",
        "furniture"
    ],
    "sg:website":"www.merrittwoodwork.com",
    "wof:name":"Merritt Woodwork",
    "wof:placetype":"venue"
},
  "geometry": {"coordinates":[-81.382605,41.658767],"type":"Point"}
}