{
  "type": "Feature",
  "properties": {
    "addr:full":"2175 Stiving Rd Mansfield OH 44903",
    "addr:housenumber":"2175",
    "addr:postcode":"44903",
    "addr:street":"Stiving Rd",
    "iso:country":"US",
    "sg:address":"2175 Stiving Rd",
    "sg:city":"Mansfield",
    "sg:classifiers":[
        {
            "category":"Utilities",
            "subcategory":"Refuse",
            "type":"Services"
        }
    ],
    "sg:phone":"+1 800 686 4085",
    "sg:postcode":"44903",
    "sg:province":"OH",
    "sg:tags":[
        "operator",
        "local",
        "system",
        "trucking"
    ],
    "wof:name":"Site 226a",
    "wof:placetype":"venue"
},
  "geometry": {"coordinates":[-82.600342,40.814589],"type":"Point"}
}