{
  "type": "Feature",
  "properties": {
    "iso:country":"US",
    "sg:address":"7462 State Rd",
    "sg:city":"Cleveland",
    "sg:classifiers":[
        {
            "category":"Retail",
            "subcategory":"Funeral Services",
            "type":"Services"
        }
    ],
    "sg:phone":"+1 440 842 4080",
    "sg:postcode":"44134",
    "sg:province":"OH",
    "sg:tags":[
        "director"
    ],
    "wof:name":"Riczo Funeral Homes Inc",
    "wof:placetype":"venue"
},
  "geometry": {"coordinates":[-81.717651,41.363215],"type":"Point"}
}