{
  "type": "Feature",
  "properties": {
    "addr:full": "1080 Nimitzview Dr Cincinnati OH 45230",
    "addr:housenumber": "1080",
    "addr:postcode": "45230",
    "addr:street": "Nimitzview Dr",
    "iso:country": "US",
    "sg:address": "1080 Nimitzview Dr",
    "sg:city": "Cincinnati",
    "sg:classifiers": [
      {
        "category": "Professional",
        "subcategory": "Management \u0026 Consulting",
        "type": "Services"
      }
    ],
    "sg:phone": "+1 513 624 2836",
    "sg:postcode": "45230",
    "sg:province": "OH",
    "sg:tags": [
      "consultant",
      "safety"
    ],
    "wof:name": "ABCO Safety Co",
    "wof:placetype": "venue"
  },
  "geometry": {"coordinates":[-84.352525,39.069472],"type":"Point"}
}
