{
  "type": "Feature",
  "properties": {
    "iso:country":"US",
    "sg:address":"2216 Quail Lake Rd",
    "sg:city":"Findlay",
    "sg:classifiers":[
        {
            "category":"Organizations",
            "subcategory":"Religious Organization",
            "type":"Services"
        }
    ],
    "sg:phone":"+1 419 425 9104",
    "sg:postcode":"45840",
    "sg:province":"OH",
    "sg:tags":[
        "clergy"
    ],
    "wof:name":"Don R Bridinger",
    "wof:placetype":"venue"
},
  "geometry": {"coordinates":[-83.600076,41.046263],"type":"Point"}
}