{
  "type": "Feature",
  "properties": {
    "addr:full":"215 N High St Hillsboro OH 45133",
    "addr:housenumber":"215",
    "addr:postcode":"45133",
    "addr:street":"N High St",
    "iso:country":"US",
    "sg:address":"215 N High St",
    "sg:city":"Hillsboro",
    "sg:classifiers":[
        {
            "category":"Shopping",
            "type":"Retail Goods"
        }
    ],
    "sg:phone":"+1 937 393 4558",
    "sg:postcode":"45133",
    "sg:province":"OH",
    "sg:tags":[
        "hearing",
        "equipment",
        "supply",
        "merchandise",
        "impaired"
    ],
    "wof:name":"Highland Cnty Hearing Aid Ctr",
    "wof:placetype":"venue"
},
  "geometry": {"coordinates":[-83.61116800000001,39.204011],"type":"Point"}
}