{
  "type": "Feature",
  "properties": {
    "addr:full":"138 S Sugar St St Clairsville OH 43950",
    "addr:housenumber":"138",
    "addr:postcode":"43950",
    "addr:street":"S Sugar St",
    "iso:country":"US",
    "sg:address":"138 S Sugar St",
    "sg:city":"St Clairsville",
    "sg:classifiers":[
        {
            "category":"Personal",
            "type":"Services"
        }
    ],
    "sg:phone":"+1 740 695 0362",
    "sg:postcode":"43950",
    "sg:province":"OH",
    "sg:tags":[
        "therapist",
        "massage"
    ],
    "wof:name":"Facello's Medical Massage",
    "wof:placetype":"venue"
},
  "geometry": {"coordinates":[-80.897424,40.077999],"type":"Point"}
}