{
  "type": "Feature",
  "properties": {
    "addr:full":"333 Decatur St Kenton OH 43326",
    "addr:housenumber":"333",
    "addr:postcode":"43326",
    "addr:street":"Decatur St",
    "iso:country":"US",
    "sg:address":"333 Decatur St",
    "sg:city":"Kenton",
    "sg:classifiers":[
        {
            "category":"Restaurant",
            "type":"Food & Drink"
        }
    ],
    "sg:phone":"+1 419 674 4674",
    "sg:postcode":"43326",
    "sg:province":"OH",
    "sg:tags":[
        "eating"
    ],
    "wof:name":"Friends Coffee Cafe",
    "wof:placetype":"venue"
},
  "geometry": {"coordinates":[-83.606048,40.643805],"type":"Point"}
}