{
  "type": "Feature",
  "properties": {
    "addr:full": "119 Paw Paw St Dayton OH 45404",
    "addr:housenumber": "119",
    "addr:postcode": "45404",
    "addr:street": "Paw Paw St",
    "iso:country": "US",
    "sg:address": "119 Paw Paw St",
    "sg:city": "Dayton",
    "sg:classifiers": [
      {
        "category": "Real Estate",
        "subcategory": "Real Estate Agent",
        "type": "Services"
      }
    ],
    "sg:phone": "+1 937 610 0606",
    "sg:postcode": "45404",
    "sg:province": "OH",
    "wof:name": "Glad Enterprises LLC",
    "wof:placetype": "venue"
  },
  "geometry": {"coordinates":[-84.160134,39.785288],"type":"Point"}
}
