{
  "type": "Feature",
  "properties": {
    "iso:country":"US",
    "sg:address":"4665 Cornell Rd",
    "sg:city":"Cincinnati",
    "sg:classifiers":[
        {
            "category":"Shopping",
            "subcategory":"Computers & Home Electronics",
            "type":"Retail Goods"
        }
    ],
    "sg:phone":"+1 513 985 9900",
    "sg:postcode":"45241",
    "sg:province":"OH",
    "sg:tags":[
        "software"
    ],
    "sg:website":"www.shoptech.com",
    "wof:name":"Shop Tech",
    "wof:placetype":"venue"
},
  "geometry": {"coordinates":[-84.377527,39.270406],"type":"Point"}
}