{
  "type": "Feature",
  "properties": {
    "addr:full":"10104 Rd 13 Ottawa OH 45875",
    "addr:housenumber":"10104",
    "addr:postcode":"45875",
    "addr:street":"Rd 13",
    "iso:country":"US",
    "sg:address":"10104 Rd 13",
    "sg:city":"Ottawa",
    "sg:phone":"+1 419 538 6978",
    "sg:postcode":"45875",
    "sg:province":"OH",
    "sg:tags":[
        "farm",
        "wheat"
    ],
    "wof:name":"Mike Verhoff",
    "wof:placetype":"venue"
},
  "geometry": {"coordinates":[-84.111622,41.034117],"type":"Point"}
}