{
  "type": "Feature",
  "properties": {
    "iso:country":"US",
    "sg:address":"492 W 2nd St",
    "sg:city":"Xenia",
    "sg:classifiers":[
        {
            "category":"Health Services",
            "subcategory":"Chiropractor",
            "type":"Services"
        }
    ],
    "sg:phone":"+1 937 376 1234",
    "sg:postcode":"45385",
    "sg:province":"OH",
    "wof:name":"Labig Chiropractic Inc",
    "wof:placetype":"venue"
},
  "geometry": {"coordinates":[-83.936098,39.683238],"type":"Point"}
}