{
  "type": "Feature",
  "properties": {
    "iso:country":"US",
    "sg:address":"32858 Walker Rd",
    "sg:city":"Avon Lake",
    "sg:classifiers":[
        {
            "category":"Restaurant",
            "type":"Food & Drink"
        }
    ],
    "sg:phone":"+1 440 930 7144",
    "sg:postcode":"44012",
    "sg:province":"OH",
    "sg:tags":[
        "eating"
    ],
    "wof:name":"Atlanta Bread Co",
    "wof:placetype":"venue"
},
  "geometry": {"coordinates":[-82.023912,41.49311],"type":"Point"}
}