{
  "type": "Feature",
  "properties": {
    "addr:full": "122 3rd St NW New Philadelphia OH 44663",
    "addr:housenumber": "122",
    "addr:postcode": "44663",
    "addr:street": "3Rd St Nw New Philadelphia",
    "iso:country": "US",
    "sg:address": "122 3rd St NW",
    "sg:city": "New Philadelphia",
    "sg:classifiers": [
      {
        "category": "Organizations",
        "subcategory": "Religious Organization",
        "type": "Services"
      }
    ],
    "sg:phone": "+1 330 339 6439",
    "sg:postcode": "44663",
    "sg:province": "OH",
    "sg:tags": [
      "church"
    ],
    "wof:name": "Trinity Episcopal Church",
    "wof:placetype": "venue"
  },
  "geometry": {"coordinates":[-81.449958,40.49052],"type":"Point"}
}
