{
  "type": "Feature",
  "properties": {
    "addr:full": "4303 Cleveland Ave Columbus OH 43224",
    "addr:housenumber": "4303",
    "addr:postcode": "43224",
    "addr:street": "Cleveland Ave",
    "iso:country": "US",
    "sg:address": "4303 Cleveland Ave",
    "sg:city": "Columbus",
    "sg:classifiers": [
      {
        "category": "Professional",
        "subcategory": "Accounting \u0026 Tax Preparation",
        "type": "Services"
      }
    ],
    "sg:phone": "+1 614 476 5225",
    "sg:postcode": "43224",
    "sg:province": "OH",
    "sg:tags": [
      "return",
      "filing"
    ],
    "wof:name": "Jackson Hewitt Tax Service",
    "wof:placetype": "venue"
  },
  "geometry": {"coordinates":[-82.953122,40.059053],"type":"Point"}
}
