{
  "type": "Feature",
  "properties": {
    "addr:full":"231 Aqua Blvd Akron OH 44319",
    "addr:housenumber":"231",
    "addr:postcode":"44319",
    "addr:street":"Aqua Blvd",
    "iso:country":"US",
    "sg:address":"231 Aqua Blvd",
    "sg:city":"Akron",
    "sg:classifiers":[
        {
            "category":"Banks & Credit Unions",
            "subcategory":"Financial Services",
            "type":"Services"
        }
    ],
    "sg:phone":"+1 330 645 0912",
    "sg:postcode":"44319",
    "sg:province":"OH",
    "sg:tags":[
        "company",
        "holding"
    ],
    "wof:name":"Just Us Enterprises",
    "wof:placetype":"venue"
},
  "geometry": {"coordinates":[-81.531192,40.997392],"type":"Point"}
}