{
  "type": "Feature",
  "properties": {
    "iso:country":"US",
    "sg:address":"704 W Main St",
    "sg:city":"Louisville",
    "sg:classifiers":[
        {
            "category":"Restaurant",
            "type":"Food & Drink"
        }
    ],
    "sg:phone":"+1 330 875 7101",
    "sg:postcode":"44641",
    "sg:province":"OH",
    "sg:tags":[
        "eating"
    ],
    "wof:name":"Dominos Pizza",
    "wof:placetype":"venue"
},
  "geometry": {"coordinates":[-81.265852,40.836853],"type":"Point"}
}