{
  "type": "Feature",
  "properties": {
    "addr:full": "704 W Main St Louisville OH 44641",
    "addr:housenumber": "704",
    "addr:postcode": "44641",
    "addr:street": "W Main St",
    "iso:country": "US",
    "sg:address": "704 W Main St",
    "sg:city": "Louisville",
    "sg:classifiers": [
      {
        "category": "Restaurant",
        "type": "Food \u0026 Drink"
      }
    ],
    "sg:phone": "+1 330 875 7101",
    "sg:postcode": "44641",
    "sg:province": "OH",
    "sg:tags": [
      "eating"
    ],
    "wof:name": "Dominos Pizza",
    "wof:placetype": "venue"
  },
  "geometry": {"coordinates":[-81.265852,40.836853],"type":"Point"}
}
