{
  "type": "Feature",
  "properties": {
    "addr:full": "706 Center Ridge Rd Bryan OH 43506",
    "addr:housenumber": "706",
    "addr:postcode": "43506",
    "addr:street": "Center Ridge Rd",
    "iso:country": "US",
    "sg:address": "706 Center Ridge Rd",
    "sg:city": "Bryan",
    "sg:classifiers": [
      {
        "category": "Travel",
        "subcategory": "Travel Agent",
        "type": "Entertainment"
      }
    ],
    "sg:phone": "+1 419 636 5504",
    "sg:postcode": "43506",
    "sg:province": "OH",
    "sg:tags": [
      "agency"
    ],
    "wof:name": "Adventure Travel Inc",
    "wof:placetype": "venue"
  },
  "geometry": {"coordinates":[-84.561575,41.465397],"type":"Point"}
}
