{
  "type": "Feature",
  "properties": {
    "addr:full":"5080 Sinclair Rd Columbus OH 43229",
    "addr:housenumber":"5080",
    "addr:postcode":"43229",
    "addr:street":"Sinclair Rd",
    "iso:country":"US",
    "sg:address":"5080 Sinclair Rd",
    "sg:city":"Columbus",
    "sg:classifiers":[
        {
            "category":"Wholesale",
            "subcategory":"Non-durable Goods",
            "type":"Manufacturing & Wholesale Goods"
        }
    ],
    "sg:phone":"+1 614 436 9964",
    "sg:postcode":"43229",
    "sg:province":"OH",
    "sg:tags":[
        "p",
        "consulting",
        "commercial",
        "advertising"
    ],
    "sg:website":"www.recognitionlink.com",
    "wof:name":"Rathburn & Associates",
    "wof:placetype":"venue"
},
  "geometry": {"coordinates":[-82.998113,40.070335],"type":"Point"}
}