{
  "type": "Feature",
  "properties": {
    "iso:country":"US",
    "sg:address":"345 Ludlow Ave",
    "sg:city":"Cincinnati",
    "sg:classifiers":[
        {
            "category":"Restaurant",
            "type":"Food & Drink"
        }
    ],
    "sg:phone":"+1 513 281 4965",
    "sg:postcode":"45220",
    "sg:province":"OH",
    "wof:name":"Proud Rooster Restaurant",
    "wof:placetype":"venue"
},
  "geometry": {"coordinates":[-84.521111,39.143785],"type":"Point"}
}