{
  "type": "Feature",
  "properties": {
    "addr:full":"770 E Main St Jackson OH 45640",
    "addr:housenumber":"770",
    "addr:postcode":"45640",
    "addr:street":"E Main St",
    "iso:country":"US",
    "sg:address":"770 E Main St",
    "sg:city":"Jackson",
    "sg:classifiers":[
        {
            "category":"Restaurant",
            "type":"Food & Drink"
        }
    ],
    "sg:menulink":"http://www.allmenus.com/oh/jackson/41844-bob-evans/menu/",
    "sg:phone":"+1 740 288 1001",
    "sg:postcode":"45640",
    "sg:province":"OH",
    "sg:tags":[
        "american"
    ],
    "wof:name":"Bob Evans",
    "wof:placetype":"venue"
},
  "geometry": {"coordinates":[-82.6288,39.042145],"type":"Point"}
}