{
  "type": "Feature",
  "properties": {
    "iso:country":"US",
    "sg:address":"420 Madison Ave",
    "sg:city":"Toledo",
    "sg:classifiers":[
        {
            "category":"Government",
            "subcategory":"Office",
            "type":"Public Place"
        }
    ],
    "sg:phone":"+1 419 259 3895",
    "sg:postcode":"43604",
    "sg:province":"OH",
    "sg:tags":[
        "executive"
    ],
    "wof:name":"Senator Voinovichs Office",
    "wof:placetype":"venue"
},
  "geometry": {"coordinates":[-83.534878,41.651461],"type":"Point"}
}