{
  "type": "Feature",
  "properties": {
    "iso:country":"US",
    "sg:address":"520 Meadow Dr",
    "sg:city":"Wadsworth",
    "sg:classifiers":[
        {
            "category":"Personal",
            "type":"Services"
        }
    ],
    "sg:phone":"+1 330 524 1459",
    "sg:postcode":"44281",
    "sg:province":"OH",
    "sg:tags":[
        "therapist",
        "massage"
    ],
    "wof:name":"Associates Massotherapy Inc",
    "wof:placetype":"venue"
},
  "geometry": {"coordinates":[-81.705904,41.014655],"type":"Point"}
}