{
  "type": "Feature",
  "properties": {
    "addr:full": "2775 Barber Rd Norton OH 44203",
    "addr:housenumber": "2775",
    "addr:postcode": "44203",
    "addr:street": "Barber Rd",
    "iso:country": "US",
    "sg:address": "2775 Barber Rd",
    "sg:city": "Norton",
    "sg:classifiers": [
      {
        "category": "Manufacturing",
        "subcategory": "Rubber \u0026 Plastics",
        "type": "Manufacturing \u0026 Wholesale Goods"
      }
    ],
    "sg:phone": "+1 330 753 4585",
    "sg:postcode": "44203",
    "sg:province": "OH",
    "sg:website": "www.fomo.com",
    "wof:name": "Fomo Products Inc",
    "wof:placetype": "venue"
  },
  "geometry": {"coordinates":[-81.608606,41.045559],"type":"Point"}
}
