{
  "type": "Feature",
  "properties": {
    "addr:full": "6499 E US Hwy 22 Wilmington OH 45177",
    "addr:housenumber": "6499",
    "addr:postcode": "45177",
    "addr:street": "E Us Hwy 22",
    "iso:country": "US",
    "sg:address": "6499 E US Hwy 22",
    "sg:city": "Wilmington",
    "sg:phone": "+1 937 584 4096",
    "sg:postcode": "45177",
    "sg:province": "OH",
    "sg:tags": [
      "farm",
      "corn",
      "soybean"
    ],
    "wof:name": "James Ellis",
    "wof:placetype": "venue"
  },
  "geometry": {"coordinates":[-83.725713,39.466916],"type":"Point"}
}
