{
  "type": "Feature",
  "properties": {
    "iso:country":"US",
    "sg:address":"8145 Detroit Ave",
    "sg:city":"Cleveland",
    "sg:classifiers":[
        {
            "category":"Freight",
            "type":"Transportation"
        }
    ],
    "sg:phone":"+1 216 631 4021",
    "sg:postcode":"44102",
    "sg:province":"OH",
    "sg:tags":[
        "operator",
        "local",
        "trucking"
    ],
    "wof:name":"Cristesch Mihai",
    "wof:placetype":"venue"
},
  "geometry": {"coordinates":[-81.741351,41.481094],"type":"Point"}
}