{
  "type": "Feature",
  "properties": {
    "addr:full": "3408 S River Rd Zanesville OH 43701",
    "addr:housenumber": "3408",
    "addr:postcode": "43701",
    "addr:street": "S River Rd",
    "iso:country": "US",
    "sg:address": "3408 S River Rd",
    "sg:city": "Zanesville",
    "sg:classifiers": [
      {
        "category": "Farming",
        "subcategory": "Farm",
        "type": "Manufacturing \u0026 Wholesale Goods"
      }
    ],
    "sg:phone": "+1 740 452 1869",
    "sg:postcode": "43701",
    "sg:province": "OH",
    "sg:tags": [
      "food",
      "covered",
      "crop"
    ],
    "wof:name": "Riverview",
    "wof:placetype": "venue"
  },
  "geometry": {"coordinates":[-81.976453,39.879944],"type":"Point"}
}
