{
  "type": "Feature",
  "properties": {
    "iso:country":"US",
    "sg:address":"3408 S River Rd",
    "sg:city":"Zanesville",
    "sg:classifiers":[
        {
            "category":"Farming",
            "subcategory":"Farm",
            "type":"Manufacturing & Wholesale Goods"
        }
    ],
    "sg:phone":"+1 740 452 1869",
    "sg:postcode":"43701",
    "sg:province":"OH",
    "sg:tags":[
        "food",
        "covered",
        "crop"
    ],
    "wof:name":"Riverview",
    "wof:placetype":"venue"
},
  "geometry": {"coordinates":[-81.97645300000001,39.879944],"type":"Point"}
}