{
  "type": "Feature",
  "properties": {
    "iso:country":"US",
    "sg:address":"24100 Chagrin Blvd",
    "sg:city":"Cleveland",
    "sg:classifiers":[
        {
            "category":"Education",
            "subcategory":"Vocational School",
            "type":"Public Place"
        }
    ],
    "sg:phone":"+1 216 650 2291",
    "sg:postcode":"44122",
    "sg:province":"OH",
    "wof:name":"Dental Assistant Training Schl",
    "wof:placetype":"venue"
},
  "geometry": {"coordinates":[-81.510464,41.464401],"type":"Point"}
}