{
  "type": "Feature",
  "properties": {
    "addr:full": "120 Market St Youngstown OH 44503",
    "addr:housenumber": "120",
    "addr:postcode": "44503",
    "addr:street": "Market St",
    "iso:country": "US",
    "sg:address": "120 Market St",
    "sg:city": "Youngstown",
    "sg:classifiers": [
      {
        "category": "Government",
        "subcategory": "Office",
        "type": "Public Place"
      }
    ],
    "sg:phone": "+1 330 740 2303",
    "sg:postcode": "44503",
    "sg:province": "OH",
    "wof:name": "Mahoning County Microfilm Dept",
    "wof:placetype": "venue"
  },
  "geometry": {"coordinates":[-80.650621,41.098517],"type":"Point"}
}
