{
  "type": "Feature",
  "properties": {
    "addr:full":"69 New Burlington Rd Waynesville OH 45068",
    "addr:housenumber":"69",
    "addr:postcode":"45068",
    "addr:street":"New Burlington Rd",
    "iso:country":"US",
    "sg:address":"69 New Burlington Rd",
    "sg:city":"Waynesville",
    "sg:classifiers":[
        {
            "category":"Recreation",
            "type":"Entertainment"
        }
    ],
    "sg:phone":"+1 513 897 3536",
    "sg:postcode":"45068",
    "sg:province":"OH",
    "sg:tags":[
        "bicycle"
    ],
    "wof:name":"Corwin Peddler",
    "wof:placetype":"venue"
},
  "geometry": {"coordinates":[-84.07620300000001,39.526351],"type":"Point"}
}