{
  "type": "Feature",
  "properties": {
    "addr:full": "631 State Rte 309 Alger OH 45812",
    "addr:housenumber": "631",
    "addr:postcode": "45812",
    "addr:street": "State Rte 309",
    "iso:country": "US",
    "sg:address": "631 State Rte 309",
    "sg:city": "Alger",
    "sg:phone": "+1 419 634 2164",
    "sg:postcode": "45812",
    "sg:province": "OH",
    "sg:tags": [
      "farm",
      "wheat",
      "soybean"
    ],
    "wof:name": "Willis Nelson",
    "wof:placetype": "venue"
  },
  "geometry": {"coordinates":[-83.869657,40.732592],"type":"Point"}
}
