{
  "type": "Feature",
  "properties": {
    "addr:full": "11374 Montgomery Rd Cincinnati OH 45249",
    "addr:housenumber": "11374",
    "addr:postcode": "45249",
    "addr:street": "Montgomery Rd",
    "iso:country": "US",
    "sg:address": "11374 Montgomery Rd",
    "sg:city": "Cincinnati",
    "sg:classifiers": [
      {
        "category": "Travel",
        "subcategory": "Travel Agent",
        "type": "Entertainment"
      }
    ],
    "sg:phone": "+1 513 489 1199",
    "sg:postcode": "45249",
    "sg:province": "OH",
    "sg:tags": [
      "agency"
    ],
    "wof:name": "Majestic Travel Inc",
    "wof:placetype": "venue"
  },
  "geometry": {"coordinates":[-84.328449,39.270369],"type":"Point"}
}
