{
  "type": "Feature",
  "properties": {
    "iso:country":"US",
    "sg:address":"231 Davids St",
    "sg:city":"Marion",
    "sg:classifiers":[
        {
            "category":"Freight",
            "type":"Transportation"
        }
    ],
    "sg:phone":"+1 740 387 1505",
    "sg:postcode":"43302",
    "sg:province":"OH",
    "sg:tags":[
        "commercial",
        "storage"
    ],
    "wof:name":"Westside Storage",
    "wof:placetype":"venue"
},
  "geometry": {"coordinates":[-83.14343100000001,40.585965],"type":"Point"}
}