{
  "type": "Feature",
  "properties": {
    "addr:full":"1510 7th St Portsmouth OH 45662",
    "addr:housenumber":"1510",
    "addr:postcode":"45662",
    "addr:street":"7Th St",
    "iso:country":"US",
    "sg:address":"1510 7th St",
    "sg:city":"Portsmouth",
    "sg:classifiers":[
        {
            "category":"Retail",
            "subcategory":"Auto Rental",
            "type":"Services"
        }
    ],
    "sg:phone":"+1 740 354 6097",
    "sg:postcode":"45662",
    "sg:province":"OH",
    "sg:tags":[
        "renting",
        "truck",
        "leasing"
    ],
    "wof:name":"U-Haul Co",
    "wof:placetype":"venue"
},
  "geometry": {"coordinates":[-82.985277,38.735332],"type":"Point"}
}