{
  "type": "Feature",
  "properties": {
    "iso:country":"US",
    "sg:address":"8280 Forestdale Dr",
    "sg:city":"Willoughby",
    "sg:phone":"+1 440 256 3411",
    "sg:postcode":"44094",
    "sg:province":"OH",
    "sg:tags":[
        "equipment",
        "supply"
    ],
    "wof:name":"GOURMET.COM",
    "wof:placetype":"venue"
},
  "geometry": {"coordinates":[-81.345585,41.622811],"type":"Point"}
}