{
  "type": "Feature",
  "properties": {
    "addr:full": "3411 Michigan Ave Cincinnati OH 45208",
    "addr:housenumber": "3411",
    "addr:postcode": "45208",
    "addr:street": "Michigan Ave",
    "iso:country": "US",
    "sg:address": "3411 Michigan Ave",
    "sg:city": "Cincinnati",
    "sg:classifiers": [
      {
        "category": "Real Estate",
        "subcategory": "Real Estate Agent",
        "type": "Services"
      }
    ],
    "sg:phone": "+1 513 924 9200",
    "sg:postcode": "45208",
    "sg:province": "OH",
    "sg:website": "www.strietmann-realty.com",
    "wof:name": "Strietmann Realty Inc",
    "wof:placetype": "venue"
  },
  "geometry": {"coordinates":[-84.441818,39.139198],"type":"Point"}
}
