{
  "type": "Feature",
  "properties": {
    "iso:country":"US",
    "sg:address":"34050 Solon Rd",
    "sg:city":"Solon",
    "sg:classifiers":[
        {
            "category":"Travel",
            "subcategory":"Travel Agent",
            "type":"Entertainment"
        }
    ],
    "sg:phone":"+1 440 248 1808",
    "sg:postcode":"44139",
    "sg:province":"OH",
    "sg:tags":[
        "agency"
    ],
    "wof:name":"A A A Travel",
    "wof:placetype":"venue"
},
  "geometry": {"coordinates":[-81.435385,41.39311],"type":"Point"}
}