{
  "type": "Feature",
  "properties": {
    "addr:full":"8881 State Rte 110 Napoleon OH 43545",
    "addr:housenumber":"8881",
    "addr:postcode":"43545",
    "addr:street":"State Rte 110",
    "iso:country":"US",
    "sg:address":"8881 State Rte 110",
    "sg:city":"Napoleon",
    "sg:phone":"+1 419 533 2105",
    "sg:postcode":"43545",
    "sg:province":"OH",
    "sg:tags":[
        "hog",
        "farm",
        "corn",
        "soybean",
        "or",
        "feedlot"
    ],
    "wof:name":"Bauman Farms",
    "wof:placetype":"venue"
},
  "geometry": {"coordinates":[-84.03583999999999,41.406601],"type":"Point"}
}