{
  "type": "Feature",
  "properties": {
    "addr:full": "5434 Teakwood Ct Columbus OH 43229",
    "addr:housenumber": "5434",
    "addr:postcode": "43229",
    "addr:street": "Teakwood Ct",
    "iso:country": "US",
    "sg:address": "5434 Teakwood Ct",
    "sg:city": "Columbus",
    "sg:classifiers": [
      {
        "category": "Building \u0026 Trades",
        "subcategory": "Construction",
        "type": "Services"
      }
    ],
    "sg:phone": "+1 614 882 9702",
    "sg:postcode": "43229",
    "sg:province": "OH",
    "sg:tags": [
      "contractor"
    ],
    "wof:name": "Pat Valentine Masonry",
    "wof:placetype": "venue"
  },
  "geometry": {"coordinates":[-82.959651,40.078647],"type":"Point"}
}
