{
  "type": "Feature",
  "properties": {
    "iso:country":"US",
    "sg:address":"5434 Teakwood Ct",
    "sg:city":"Columbus",
    "sg:classifiers":[
        {
            "category":"Building & Trades",
            "subcategory":"Construction",
            "type":"Services"
        }
    ],
    "sg:phone":"+1 614 882 9702",
    "sg:postcode":"43229",
    "sg:province":"OH",
    "sg:tags":[
        "contractor"
    ],
    "wof:name":"Pat Valentine Masonry",
    "wof:placetype":"venue"
},
  "geometry": {"coordinates":[-82.95965099999999,40.078647],"type":"Point"}
}