{
  "type": "Feature",
  "properties": {
    "addr:full":"118 E Hall St Kent OH 44240",
    "addr:housenumber":"118",
    "addr:postcode":"44240",
    "addr:street":"E Hall St",
    "iso:country":"US",
    "sg:address":"118 E Hall St",
    "sg:city":"Kent",
    "sg:classifiers":[
        {
            "category":"Health Services",
            "subcategory":"Health Practitioner",
            "type":"Services"
        }
    ],
    "sg:phone":"+1 330 672 2018",
    "sg:postcode":"44240",
    "sg:province":"OH",
    "wof:name":"Kent State Psychology Dept",
    "wof:placetype":"venue"
},
  "geometry": {"coordinates":[-81.356781,41.14674],"type":"Point"}
}