{
  "type": "Feature",
  "properties": {
    "iso:country":"US",
    "sg:address":"395 Osage Dr",
    "sg:city":"Maumee",
    "sg:classifiers":[
        {
            "category":"Home & Garden",
            "subcategory":"Building Materials",
            "type":"Retail Goods"
        },
        {
            "category":"Manufacturing",
            "subcategory":"Chemicals & Compounds",
            "type":"Manufacturing & Wholesale Goods"
        }
    ],
    "sg:phone":"+1 419 893 5755",
    "sg:postcode":"43537",
    "sg:province":"OH",
    "sg:tags":[
        "paint",
        "floor",
        "covering"
    ],
    "wof:name":"Sherwin-Williams Paints",
    "wof:placetype":"venue"
},
  "geometry": {"coordinates":[-83.675268,41.582411],"type":"Point"}
}