{
  "type": "Feature",
  "properties": {
    "iso:country":"US",
    "sg:address":"6424 Chambersburg Rd",
    "sg:city":"Dayton",
    "sg:classifiers":[
        {
            "category":"Home & Garden",
            "subcategory":"Carpets & Floor Coverings",
            "type":"Retail Goods"
        }
    ],
    "sg:phone":"+1 937 233 4004",
    "sg:postcode":"45424",
    "sg:province":"OH",
    "wof:name":"Huber Carpet",
    "wof:placetype":"venue"
},
  "geometry": {"coordinates":[-84.11041,39.846616],"type":"Point"}
}