{
  "type": "Feature",
  "properties": {
    "addr:full":"245 W Main St Xenia OH 45385",
    "addr:housenumber":"245",
    "addr:postcode":"45385",
    "addr:street":"W Main St",
    "iso:country":"US",
    "sg:address":"245 W Main St",
    "sg:city":"Xenia",
    "sg:classifiers":[
        {
            "category":"Restaurant",
            "type":"Food & Drink"
        }
    ],
    "sg:menulink":"http://www.allmenus.com/oh/xenia/86363-little-caesars-pizza/menu/",
    "sg:phone":"+1 937 376 5422",
    "sg:postcode":"45385",
    "sg:province":"OH",
    "sg:tags":[
        "american",
        "pizza"
    ],
    "wof:name":"Little Caesar's Pizza",
    "wof:placetype":"venue"
},
  "geometry": {"coordinates":[-83.933984,39.684485],"type":"Point"}
}