{
  "type": "Feature",
  "properties": {
    "iso:country":"US",
    "sg:address":"302 N Detroit Ave",
    "sg:city":"Toledo",
    "sg:classifiers":[
        {
            "category":"Bars & Pubs",
            "type":"Food & Drink"
        }
    ],
    "sg:phone":"+1 419 244 0652",
    "sg:postcode":"43607",
    "sg:province":"OH",
    "wof:name":"Mary's Bar & Grill",
    "wof:placetype":"venue"
},
  "geometry": {"coordinates":[-83.58354,41.643758],"type":"Point"}
}