{
  "type": "Feature",
  "properties": {
    "addr:full": "302 N Detroit Ave Toledo OH 43607",
    "addr:housenumber": "302",
    "addr:postcode": "43607",
    "addr:street": "N Detroit Ave",
    "iso:country": "US",
    "sg:address": "302 N Detroit Ave",
    "sg:city": "Toledo",
    "sg:classifiers": [
      {
        "category": "Bars \u0026 Pubs",
        "type": "Food \u0026 Drink"
      }
    ],
    "sg:phone": "+1 419 244 0652",
    "sg:postcode": "43607",
    "sg:province": "OH",
    "wof:name": "Mary's Bar \u0026 Grill",
    "wof:placetype": "venue"
  },
  "geometry": {"coordinates":[-83.58354,41.643758],"type":"Point"}
}
