{
  "type": "Feature",
  "properties": {
    "addr:full": "805 N Limestone St Springfield OH 45503",
    "addr:housenumber": "805",
    "addr:postcode": "45503",
    "addr:street": "N Limestone St",
    "iso:country": "US",
    "sg:address": "805 N Limestone St",
    "sg:city": "Springfield",
    "sg:classifiers": [
      {
        "category": "Insurance",
        "subcategory": "Insurance Agent",
        "type": "Services"
      }
    ],
    "sg:phone": "+1 937 325 7625",
    "sg:postcode": "45503",
    "sg:province": "OH",
    "wof:name": "Nationwide",
    "wof:placetype": "venue"
  },
  "geometry": {"coordinates":[-83.805858,39.935071],"type":"Point"}
}
