{
  "type": "Feature",
  "properties": {
    "addr:full":"2315 Lincoln Way E Massillon OH 44646",
    "addr:housenumber":"2315",
    "addr:postcode":"44646",
    "addr:street":"Lincoln Way E",
    "iso:country":"US",
    "sg:address":"2315 Lincoln Way E",
    "sg:city":"Massillon",
    "sg:classifiers":[
        {
            "category":"Health Services",
            "subcategory":"Chiropractor",
            "type":"Services"
        }
    ],
    "sg:phone":"+1 330 833 7007",
    "sg:postcode":"44646",
    "sg:province":"OH",
    "wof:name":"Cheatle Chiropractic & Rehab",
    "wof:placetype":"venue"
},
  "geometry": {"coordinates":[-81.491663,40.798309],"type":"Point"}
}