{
  "type": "Feature",
  "properties": {
    "addr:full":"607 N Meridian Rd Youngstown OH 44509",
    "addr:housenumber":"607",
    "addr:postcode":"44509",
    "addr:street":"N Meridian Rd",
    "iso:country":"US",
    "sg:address":"607 N Meridian Rd",
    "sg:city":"Youngstown",
    "sg:classifiers":[
        {
            "category":"Wholesale",
            "subcategory":"Hardware",
            "type":"Manufacturing & Wholesale Goods"
        }
    ],
    "sg:phone":"+1 330 270 1745",
    "sg:postcode":"44509",
    "sg:province":"OH",
    "sg:tags":[
        "fastener"
    ],
    "sg:website":"www.fastenal.com",
    "wof:name":"Fastenal Co",
    "wof:placetype":"venue"
},
  "geometry": {"coordinates":[-80.711084,41.1162],"type":"Point"}
}