{
  "type": "Feature",
  "properties": {
    "addr:full": "165 E Tiffin St Fostoria OH 44830",
    "addr:housenumber": "165",
    "addr:postcode": "44830",
    "addr:street": "E Tiffin St",
    "iso:country": "US",
    "sg:address": "165 E Tiffin St",
    "sg:city": "Fostoria",
    "sg:classifiers": [
      {
        "category": "Autos \u0026 Motor Vehicles",
        "subcategory": "Fuel \u0026 Gas Station",
        "type": "Retail Goods"
      }
    ],
    "sg:phone": "+1 419 435 8622",
    "sg:postcode": "44830",
    "sg:province": "OH",
    "sg:tags": [
      "oil"
    ],
    "wof:name": "Jack's Garage",
    "wof:placetype": "venue"
  },
  "geometry": {"coordinates":[-83.412471,41.156536],"type":"Point"}
}
