{
  "type": "Feature",
  "properties": {
    "addr:full": "1521 E Home Rd Springfield OH 45503",
    "addr:housenumber": "1521",
    "addr:postcode": "45503",
    "addr:street": "E Home Rd",
    "iso:country": "US",
    "sg:address": "1521 E Home Rd",
    "sg:city": "Springfield",
    "sg:classifiers": [
      {
        "category": "Organizations",
        "subcategory": "Religious Organization",
        "type": "Services"
      }
    ],
    "sg:phone": "+1 937 399 6878",
    "sg:postcode": "45503",
    "sg:province": "OH",
    "sg:tags": [
      "church"
    ],
    "sg:website": "www.alcassembly.org",
    "wof:name": "Abundant Life Church",
    "wof:placetype": "venue"
  },
  "geometry": {"coordinates":[-83.781211,39.951876],"type":"Point"}
}
