{
  "type": "Feature",
  "properties": {
    "addr:full":"504 Jerusalem Rd SE Bremen OH 43107",
    "addr:housenumber":"504",
    "addr:postcode":"43107",
    "addr:street":"Jerusalem Rd Se",
    "iso:country":"US",
    "sg:address":"504 Jerusalem Rd SE",
    "sg:city":"Bremen",
    "sg:classifiers":[
        {
            "category":"Restaurant",
            "type":"Food & Drink"
        }
    ],
    "sg:phone":"+1 740 569 6223",
    "sg:postcode":"43107",
    "sg:province":"OH",
    "wof:name":"Pizza Station",
    "wof:placetype":"venue"
},
  "geometry": {"coordinates":[-82.390351,39.707275],"type":"Point"}
}