{
  "type": "Feature",
  "properties": {
    "iso:country":"US",
    "sg:address":"5745 Willnean Dr",
    "sg:city":"Milford",
    "sg:classifiers":[
        {
            "category":"Wholesale",
            "subcategory":"Machinery & Supplies",
            "type":"Manufacturing & Wholesale Goods"
        }
    ],
    "sg:phone":"+1 513 831 0688",
    "sg:postcode":"45150",
    "sg:province":"OH",
    "sg:tags":[
        "equipment",
        "industrial"
    ],
    "wof:name":"Kemper Automation",
    "wof:placetype":"venue"
},
  "geometry": {"coordinates":[-84.246578,39.184189],"type":"Point"}
}