{
  "type": "Feature",
  "properties": {
    "addr:full": "5745 Willnean Dr Milford OH 45150",
    "addr:housenumber": "5745",
    "addr:postcode": "45150",
    "addr:street": "Willnean Dr",
    "iso:country": "US",
    "sg:address": "5745 Willnean Dr",
    "sg:city": "Milford",
    "sg:classifiers": [
      {
        "category": "Wholesale",
        "subcategory": "Machinery \u0026 Supplies",
        "type": "Manufacturing \u0026 Wholesale Goods"
      }
    ],
    "sg:phone": "+1 513 831 0688",
    "sg:postcode": "45150",
    "sg:province": "OH",
    "sg:tags": [
      "equipment",
      "industrial"
    ],
    "wof:name": "Kemper Automation",
    "wof:placetype": "venue"
  },
  "geometry": {"coordinates":[-84.246578,39.184189],"type":"Point"}
}
