{
  "type": "Feature",
  "properties": {
    "addr:full": "5925 Karl Rd Columbus OH 43229",
    "addr:housenumber": "5925",
    "addr:postcode": "43229",
    "addr:street": "Karl Rd",
    "iso:country": "US",
    "sg:address": "5925 Karl Rd",
    "sg:city": "Columbus",
    "sg:classifiers": [
      {
        "category": "Organizations",
        "subcategory": "Community Association",
        "type": "Services"
      }
    ],
    "sg:phone": "+1 614 468 0160",
    "sg:postcode": "43229",
    "sg:province": "OH",
    "sg:tags": [
      "military"
    ],
    "wof:name": "Paralyzed Veterans Of America",
    "wof:placetype": "venue"
  },
  "geometry": {"coordinates":[-82.975399,40.092313],"type":"Point"}
}
