{
  "type": "Feature",
  "properties": {
    "addr:full": "308 E Statler Rd Piqua OH 45356",
    "addr:housenumber": "308",
    "addr:postcode": "45356",
    "addr:street": "E Statler Rd",
    "iso:country": "US",
    "sg:address": "308 E Statler Rd",
    "sg:city": "Piqua",
    "sg:classifiers": [
      {
        "category": "Manufacturing",
        "subcategory": "Metals",
        "type": "Manufacturing \u0026 Wholesale Goods"
      }
    ],
    "sg:phone": "+1 937 773 7601",
    "sg:postcode": "45356",
    "sg:province": "OH",
    "sg:tags": [
      "machine",
      "screw",
      "product"
    ],
    "wof:name": "General Industrial Supply Co",
    "wof:placetype": "venue"
  },
  "geometry": {"coordinates":[-84.185809,40.134616],"type":"Point"}
}
