{
  "type": "Feature",
  "properties": {
    "iso:country":"US",
    "sg:address":"1155 Delaware Ave",
    "sg:city":"Marion",
    "sg:classifiers":[
        {
            "category":"Autos & Motor Vehicles",
            "subcategory":"Automobile Sales",
            "type":"Retail Goods"
        }
    ],
    "sg:phone":"+1 740 387 3673",
    "sg:postcode":"43302",
    "sg:province":"OH",
    "sg:tags":[
        "body",
        "repair",
        "general"
    ],
    "wof:name":"Mathews Mitsubishi",
    "wof:placetype":"venue"
},
  "geometry": {"coordinates":[-83.121908,40.56853],"type":"Point"}
}