{
  "type": "Feature",
  "properties": {
    "addr:full":"829 Union Ave Dover OH 44622",
    "addr:housenumber":"829",
    "addr:postcode":"44622",
    "addr:street":"Union Ave",
    "iso:country":"US",
    "sg:address":"829 Union Ave",
    "sg:city":"Dover",
    "sg:classifiers":[
        {
            "category":"Organizations",
            "subcategory":"Membership Organization",
            "type":"Services"
        }
    ],
    "sg:phone":"+1 330 602 6762",
    "sg:postcode":"44622",
    "sg:province":"OH",
    "wof:name":"Cats N Us",
    "wof:placetype":"venue"
},
  "geometry": {"coordinates":[-81.465141,40.506815],"type":"Point"}
}