{
  "type": "Feature",
  "properties": {
    "addr:full": "1124 True St Toledo OH 43607",
    "addr:housenumber": "1124",
    "addr:postcode": "43607",
    "addr:street": "True St",
    "iso:country": "US",
    "sg:address": "1124 True St",
    "sg:city": "Toledo",
    "sg:classifiers": [
      {
        "category": "Autos \u0026 Motor Vehicles",
        "subcategory": "Auto Supplies",
        "type": "Retail Goods"
      }
    ],
    "sg:phone": "+1 419 244 7110",
    "sg:postcode": "43607",
    "sg:province": "OH",
    "sg:tags": [
      "tire"
    ],
    "wof:name": "K \u0026 M Tire",
    "wof:placetype": "venue"
  },
  "geometry": {"coordinates":[-83.573633,41.651807],"type":"Point"}
}
