{
  "type": "Feature",
  "properties": {
    "iso:country":"US",
    "sg:address":"1124 True St",
    "sg:city":"Toledo",
    "sg:classifiers":[
        {
            "category":"Autos & Motor Vehicles",
            "subcategory":"Auto Supplies",
            "type":"Retail Goods"
        }
    ],
    "sg:phone":"+1 419 244 7110",
    "sg:postcode":"43607",
    "sg:province":"OH",
    "sg:tags":[
        "tire"
    ],
    "wof:name":"K & M Tire",
    "wof:placetype":"venue"
},
  "geometry": {"coordinates":[-83.573633,41.651807],"type":"Point"}
}