{
  "type": "Feature",
  "properties": {
    "addr:full": "2311 Hayes Ave Fremont OH 43420",
    "addr:housenumber": "2311",
    "addr:postcode": "43420",
    "addr:street": "Hayes Ave",
    "iso:country": "US",
    "sg:address": "2311 Hayes Ave",
    "sg:city": "Fremont",
    "sg:classifiers": [
      {
        "category": "Health Services",
        "subcategory": "Doctor",
        "type": "Services"
      }
    ],
    "sg:phone": "+1 419 334 8121",
    "sg:postcode": "43420",
    "sg:province": "OH",
    "sg:tags": [
      "physician",
      "surgeon"
    ],
    "wof:name": "Eye Centers Of Northwest Ohio",
    "wof:placetype": "venue"
  },
  "geometry": {"coordinates":[-83.139051,41.342044],"type":"Point"}
}
