{
  "type": "Feature",
  "properties": {
    "iso:country":"US",
    "sg:address":"1624 Demaret Ln",
    "sg:city":"Columbus",
    "sg:classifiers":[
        {
            "category":"Wholesale",
            "subcategory":"Sporting Goods",
            "type":"Manufacturing & Wholesale Goods"
        }
    ],
    "sg:phone":"+1 614 275 0565",
    "sg:postcode":"43228",
    "sg:province":"OH",
    "wof:name":"Knochel Enterprises Inc",
    "wof:placetype":"venue"
},
  "geometry": {"coordinates":[-83.104094,39.987436],"type":"Point"}
}