{
  "type": "Feature",
  "properties": {
    "iso:country":"US",
    "sg:address":"5902 Country View Dr",
    "sg:city":"Hamilton",
    "sg:classifiers":[
        {
            "category":"Building & Trades",
            "subcategory":"Construction",
            "type":"Services"
        }
    ],
    "sg:phone":"+1 513 895 3920",
    "sg:postcode":"45011",
    "sg:province":"OH",
    "sg:tags":[
        "contractor"
    ],
    "wof:name":"Carlos Jackson Remodeling",
    "wof:placetype":"venue"
},
  "geometry": {"coordinates":[-84.46619099999999,39.4055],"type":"Point"}
}