{
  "type": "Feature",
  "properties": {
    "addr:full": "5902 Country View Dr Hamilton OH 45011",
    "addr:housenumber": "5902",
    "addr:postcode": "45011",
    "addr:street": "Country View Dr",
    "iso:country": "US",
    "sg:address": "5902 Country View Dr",
    "sg:city": "Hamilton",
    "sg:classifiers": [
      {
        "category": "Building \u0026 Trades",
        "subcategory": "Construction",
        "type": "Services"
      }
    ],
    "sg:phone": "+1 513 895 3920",
    "sg:postcode": "45011",
    "sg:province": "OH",
    "sg:tags": [
      "contractor"
    ],
    "wof:name": "Carlos Jackson Remodeling",
    "wof:placetype": "venue"
  },
  "geometry": {"coordinates":[-84.466191,39.4055],"type":"Point"}
}
