{
  "type": "Feature",
  "properties": {
    "iso:country":"US",
    "sg:address":"14524 Polo Club Dr",
    "sg:city":"Cleveland",
    "sg:classifiers":[
        {
            "category":"Organizations",
            "subcategory":"Community Association",
            "type":"Services"
        }
    ],
    "sg:phone":"+1 440 238 4517",
    "sg:postcode":"44136",
    "sg:province":"OH",
    "sg:tags":[
        "club"
    ],
    "wof:name":"Polo Club",
    "wof:placetype":"venue"
},
  "geometry": {"coordinates":[-81.81268799999999,41.309464],"type":"Point"}
}