{
  "type": "Feature",
  "properties": {
    "addr:full": "4351 Herr Rd Lima OH 45801",
    "addr:housenumber": "4351",
    "addr:postcode": "45801",
    "addr:street": "Herr Rd",
    "iso:country": "US",
    "sg:address": "4351 Herr Rd",
    "sg:city": "Lima",
    "sg:phone": "+1 419 643 6385",
    "sg:postcode": "45801",
    "sg:province": "OH",
    "sg:tags": [
      "livestock",
      "beef",
      "farm",
      "corn",
      "feedlot",
      "soybean",
      "cattle",
      "se"
    ],
    "wof:name": "Rodney Geiger",
    "wof:placetype": "venue"
  },
  "geometry": {"coordinates":[-83.956575,40.802141],"type":"Point"}
}
