{
  "type": "Feature",
  "properties": {
    "iso:country":"US",
    "sg:address":"7666 Production Dr",
    "sg:city":"Cincinnati",
    "sg:classifiers":[
        {
            "category":"Manufacturing",
            "subcategory":"Printing",
            "type":"Manufacturing & Wholesale Goods"
        }
    ],
    "sg:phone":"+1 513 821 3150",
    "sg:postcode":"45237",
    "sg:province":"OH",
    "sg:tags":[
        "screen",
        "graphic",
        "designer"
    ],
    "wof:name":"Hey Graphics Inc",
    "wof:placetype":"venue"
},
  "geometry": {"coordinates":[-84.454911,39.199059],"type":"Point"}
}