{
  "type": "Feature",
  "properties": {
    "addr:full":"1661 Kenny Rd Columbus OH 43212",
    "addr:housenumber":"1661",
    "addr:postcode":"43212",
    "addr:street":"Kenny Rd",
    "iso:country":"US",
    "sg:address":"1661 Kenny Rd",
    "sg:city":"Columbus",
    "sg:classifiers":[
        {
            "category":"Building & Trades",
            "subcategory":"Plumbing",
            "type":"Services"
        }
    ],
    "sg:phone":"+1 614 299 7700",
    "sg:postcode":"43212",
    "sg:province":"OH",
    "sg:tags":[
        "plumbing",
        "contractor"
    ],
    "sg:website":"www.muetzel.com",
    "wof:name":"Muetzel Plumbing & Heating Co",
    "wof:placetype":"venue"
},
  "geometry": {"coordinates":[-83.035248,39.992686],"type":"Point"}
}