{
  "type": "Feature",
  "properties": {
    "addr:full":"3118 Gardenia Dr Dayton OH 45449",
    "addr:housenumber":"3118",
    "addr:postcode":"45449",
    "addr:street":"Gardenia Dr",
    "iso:country":"US",
    "sg:address":"3118 Gardenia Dr",
    "sg:city":"Dayton",
    "sg:classifiers":[
        {
            "category":"Restaurant",
            "type":"Food & Drink"
        }
    ],
    "sg:phone":"+1 937 436 1496",
    "sg:postcode":"45449",
    "sg:province":"OH",
    "sg:tags":[
        "eating"
    ],
    "wof:name":"Tastefully Done",
    "wof:placetype":"venue"
},
  "geometry": {"coordinates":[-84.2274,39.667886],"type":"Point"}
}