{
  "type": "Feature",
  "properties": {
    "addr:full":"2781 E Lytle-Five Points Rd Waynesville OH 45068",
    "addr:housenumber":"2781",
    "addr:postcode":"45068",
    "addr:street":"E Lytle-Five Points Rd",
    "iso:country":"US",
    "sg:address":"2781 E Lytle-Five Points Rd",
    "sg:city":"Waynesville",
    "sg:classifiers":[
        {
            "category":"Building & Trades",
            "subcategory":"Construction",
            "type":"Services"
        }
    ],
    "sg:phone":"+1 513 897 9715",
    "sg:postcode":"45068",
    "sg:province":"OH",
    "sg:tags":[
        "house"
    ],
    "wof:name":"P H & Sons Inc",
    "wof:placetype":"venue"
},
  "geometry": {"coordinates":[-84.13488,39.568456],"type":"Point"}
}