{
  "type": "Feature",
  "properties": {
    "addr:full":"16515 Square Dr Marysville OH 43040",
    "addr:housenumber":"16515",
    "addr:postcode":"43040",
    "addr:street":"Square Dr",
    "iso:country":"US",
    "sg:address":"16515 Square Dr",
    "sg:city":"Marysville",
    "sg:classifiers":[
        {
            "category":"Health Services",
            "subcategory":"Clinic",
            "type":"Services"
        }
    ],
    "sg:phone":"+1 937 642 6848",
    "sg:postcode":"43040",
    "sg:province":"OH",
    "sg:tags":[
        "specialty",
        "outpatient"
    ],
    "wof:name":"Comprehensive Services",
    "wof:placetype":"venue"
},
  "geometry": {"coordinates":[-83.34754700000001,40.24274],"type":"Point"}
}