{
  "type": "Feature",
  "properties": {
    "addr:full": "1009 N Memorial Dr Lancaster OH 43130",
    "addr:housenumber": "1009",
    "addr:postcode": "43130",
    "addr:street": "N Memorial Dr",
    "iso:country": "US",
    "sg:address": "1009 N Memorial Dr",
    "sg:city": "Lancaster",
    "sg:classifiers": [
      {
        "category": "Restaurant",
        "type": "Food \u0026 Drink"
      }
    ],
    "sg:menulink": "http://www.allmenus.com/oh/lancaster/19468-roosters/menu/",
    "sg:phone": "+1 740 653 1444",
    "sg:postcode": "43130",
    "sg:province": "OH",
    "sg:tags": [
      "american"
    ],
    "wof:name": "Rooster's",
    "wof:placetype": "venue"
  },
  "geometry": {"coordinates":[-82.608893,39.725112],"type":"Point"}
}
