{
  "type": "Feature",
  "properties": {
    "iso:country":"US",
    "sg:address":"530 Dow Ave",
    "sg:city":"Columbus",
    "sg:classifiers":[
        {
            "category":"Manufacturing",
            "subcategory":"Tools & Machinery",
            "type":"Manufacturing & Wholesale Goods"
        }
    ],
    "sg:phone":"+1 614 294 2694",
    "sg:postcode":"43211",
    "sg:province":"OH",
    "sg:tags":[
        "equipment",
        "die",
        "cutting",
        "supply"
    ],
    "wof:name":"Grandon Manufacturing Co",
    "wof:placetype":"venue"
},
  "geometry": {"coordinates":[-82.992549,39.99245],"type":"Point"}
}