{
  "type": "Feature",
  "properties": {
    "addr:full":"6723 State Rte 132 Goshen OH 45122",
    "addr:housenumber":"6723",
    "addr:postcode":"45122",
    "addr:street":"State Rte 132",
    "iso:country":"US",
    "sg:address":"6723 State Rte 132",
    "sg:city":"Goshen",
    "sg:classifiers":[
        {
            "category":"Banks & Credit Unions",
            "subcategory":"Bank",
            "type":"Services"
        }
    ],
    "sg:phone":"+1 513 722 3901",
    "sg:postcode":"45122",
    "sg:province":"OH",
    "wof:name":"Lebanon Citizens National Bank",
    "wof:placetype":"venue"
},
  "geometry": {"coordinates":[-84.16391299999999,39.227068],"type":"Point"}
}