{
  "type": "Feature",
  "properties": {
    "iso:country":"US",
    "sg:address":"1739 N High St",
    "sg:city":"Columbus",
    "sg:classifiers":[
        {
            "category":"Organizations",
            "subcategory":"Community Association",
            "type":"Services"
        }
    ],
    "sg:phone":"+1 614 292 9369",
    "sg:postcode":"43210",
    "sg:province":"OH",
    "wof:name":"O Block",
    "wof:placetype":"venue"
},
  "geometry": {"coordinates":[-83.007831,39.99886],"type":"Point"}
}