{
  "type": "Feature",
  "properties": {
    "addr:full": "130 N Wayne St St Marys OH 45885",
    "addr:housenumber": "130",
    "addr:postcode": "45885",
    "addr:street": "N Wayne St",
    "iso:country": "US",
    "sg:address": "130 N Wayne St",
    "sg:city": "St Marys",
    "sg:classifiers": [
      {
        "category": "Organizations",
        "subcategory": "Religious Organization",
        "type": "Services"
      }
    ],
    "sg:phone": "+1 419 394 3615",
    "sg:postcode": "45885",
    "sg:province": "OH",
    "sg:tags": [
      "church"
    ],
    "wof:name": "Wayne St United Methodist Chr",
    "wof:placetype": "venue"
  },
  "geometry": {"coordinates":[-84.391778,40.541969],"type":"Point"}
}
