{
  "type": "Feature",
  "properties": {
    "addr:full": "9634 Tallmadge Rd Diamond OH 44412",
    "addr:housenumber": "9634",
    "addr:postcode": "44412",
    "addr:street": "Tallmadge Rd",
    "iso:country": "US",
    "sg:address": "9634 Tallmadge Rd",
    "sg:city": "Diamond",
    "sg:classifiers": [
      {
        "category": "Government",
        "subcategory": "Office",
        "type": "Public Place"
      }
    ],
    "sg:phone": "+1 330 654 2279",
    "sg:postcode": "44412",
    "sg:province": "OH",
    "sg:tags": [
      "village"
    ],
    "wof:name": "Palmyra Twp Trustee",
    "wof:placetype": "venue"
  },
  "geometry": {"coordinates":[-81.048253,41.098792],"type":"Point"}
}
