{
  "type": "Feature",
  "properties": {
    "addr:full": "6178 Bane Rd NE Mechanicstown OH 44651",
    "addr:housenumber": "6178",
    "addr:postcode": "44651",
    "addr:street": "Bane Rd Ne",
    "iso:country": "US",
    "sg:address": "6178 Bane Rd NE",
    "sg:city": "Mechanicstown",
    "sg:classifiers": [
      {
        "category": "Organizations",
        "subcategory": "Religious Organization",
        "type": "Services"
      }
    ],
    "sg:phone": "+1 330 738 4090",
    "sg:postcode": "44651",
    "sg:province": "OH",
    "sg:tags": [
      "church"
    ],
    "wof:name": "Church Of Christ At Glade Run",
    "wof:placetype": "venue"
  },
  "geometry": {"coordinates":[-80.965212,40.659255],"type":"Point"}
}
