{
  "type": "Feature",
  "properties": {
    "addr:full":"4460 Heatherdowns Blvd Toledo OH 43614",
    "addr:housenumber":"4460",
    "addr:postcode":"43614",
    "addr:street":"Heatherdowns Blvd",
    "iso:country":"US",
    "sg:address":"4460 Heatherdowns Blvd",
    "sg:city":"Toledo",
    "sg:classifiers":[
        {
            "category":"Government",
            "subcategory":"Office",
            "type":"Public Place"
        }
    ],
    "sg:phone":"+1 419 385 6479",
    "sg:postcode":"43614",
    "sg:province":"OH",
    "sg:tags":[
        "transportation"
    ],
    "wof:name":"Pate Highway Patrol",
    "wof:placetype":"venue"
},
  "geometry": {"coordinates":[-83.648212,41.594388],"type":"Point"}
}