{
  "type": "Feature",
  "properties": {
    "addr:full":"1675 Ansel Rd Cleveland OH 44106",
    "addr:housenumber":"1675",
    "addr:postcode":"44106",
    "addr:street":"Ansel Rd",
    "iso:country":"US",
    "sg:address":"1675 Ansel Rd",
    "sg:city":"Cleveland",
    "sg:classifiers":[
        {
            "category":"Government",
            "subcategory":"Office",
            "type":"Public Place"
        }
    ],
    "sg:phone":"+1 216 795 9065",
    "sg:postcode":"44106",
    "sg:province":"OH",
    "sg:tags":[
        "agency"
    ],
    "sg:website":"www.cmha.net",
    "wof:name":"Cuyahoga Metro Housing",
    "wof:placetype":"venue"
},
  "geometry": {"coordinates":[-81.61912,41.510949],"type":"Point"}
}