{
  "type": "Feature",
  "properties": {
    "addr:full": "2204 S Taylor Rd Cleveland OH 44118",
    "addr:housenumber": "2204",
    "addr:postcode": "44118",
    "addr:street": "S Taylor Rd",
    "iso:country": "US",
    "sg:address": "2204 S Taylor Rd",
    "sg:city": "Cleveland",
    "sg:classifiers": [
      {
        "category": "Health Services",
        "subcategory": "Doctor",
        "type": "Services"
      }
    ],
    "sg:phone": "+1 216 321 3552",
    "sg:postcode": "44118",
    "sg:province": "OH",
    "sg:tags": [
      "dentist"
    ],
    "wof:name": "A United Dental Assoc",
    "wof:placetype": "venue"
  },
  "geometry": {"coordinates":[-81.556165,41.498634],"type":"Point"}
}
