{
  "type": "Feature",
  "properties": {
    "iso:country":"US",
    "sg:address":"13320 State Rte 7",
    "sg:city":"Lisbon",
    "sg:classifiers":[
        {
            "category":"Organizations",
            "subcategory":"Religious Organization",
            "type":"Services"
        }
    ],
    "sg:phone":"+1 330 385 4673",
    "sg:postcode":"44432",
    "sg:province":"OH",
    "sg:tags":[
        "church"
    ],
    "wof:name":"Hope Chrisitian Fellowship",
    "wof:placetype":"venue"
},
  "geometry": {"coordinates":[-80.635124,40.708429],"type":"Point"}
}