{
  "type": "Feature",
  "properties": {
    "iso:country":"US",
    "sg:address":"3801 Gantz Rd",
    "sg:city":"Grove City",
    "sg:classifiers":[
        {
            "category":"Freight",
            "type":"Transportation"
        }
    ],
    "sg:phone":"+1 614 539 5527",
    "sg:postcode":"43123",
    "sg:province":"OH",
    "sg:tags":[
        "print",
        "lithographic",
        "commercial",
        "general"
    ],
    "wof:name":"Wallace",
    "wof:placetype":"venue"
},
  "geometry": {"coordinates":[-83.056011,39.881133],"type":"Point"}
}