{
  "type": "Feature",
  "properties": {
    "iso:country":"US",
    "sg:address":"25 E Dayton St",
    "sg:city":"West Alexandria",
    "sg:classifiers":[
        {
            "category":"Food & Beverages",
            "subcategory":"Specialty",
            "type":"Retail Goods"
        }
    ],
    "sg:phone":"+1 937 839 4668",
    "sg:postcode":"45381",
    "sg:province":"OH",
    "wof:name":"West Alexandria Fire Station",
    "wof:placetype":"venue"
},
  "geometry": {"coordinates":[-84.530811,39.744534],"type":"Point"}
}