{
  "type": "Feature",
  "properties": {
    "addr:full": "7513 Leavitt Rd Amherst OH 44001",
    "addr:housenumber": "7513",
    "addr:postcode": "44001",
    "addr:street": "Leavitt Rd",
    "iso:country": "US",
    "sg:address": "7513 Leavitt Rd",
    "sg:city": "Amherst",
    "sg:classifiers": [
      {
        "category": "Autos \u0026 Motor Vehicles",
        "subcategory": "Automobile Sales",
        "type": "Retail Goods"
      }
    ],
    "sg:phone": "+1 440 988 8200",
    "sg:postcode": "44001",
    "sg:province": "OH",
    "sg:tags": [
      "car",
      "dealer"
    ],
    "wof:name": "Arch Abraham Suzuki",
    "wof:placetype": "venue"
  },
  "geometry": {"coordinates":[-82.209935,41.38853],"type":"Point"}
}
