{
  "type": "Feature",
  "properties": {
    "addr:full": "2207 Oak Harbor Rd Fremont OH 43420",
    "addr:housenumber": "2207",
    "addr:postcode": "43420",
    "addr:street": "Oak Harbor Rd",
    "iso:country": "US",
    "sg:address": "2207 Oak Harbor Rd",
    "sg:city": "Fremont",
    "sg:classifiers": [
      {
        "category": "Government",
        "subcategory": "Office",
        "type": "Public Place"
      }
    ],
    "sg:phone": "+1 419 332 3810",
    "sg:postcode": "43420",
    "sg:province": "OH",
    "sg:tags": [
      "executive"
    ],
    "wof:name": "Sandusky Township Trustees",
    "wof:placetype": "venue"
  },
  "geometry": {"coordinates":[-83.134808,41.377188],"type":"Point"}
}
