{
  "type": "Feature",
  "properties": {
    "iso:country":"US",
    "sg:address":"4501 Bridgetown Rd",
    "sg:city":"Cincinnati",
    "sg:classifiers":[
        {
            "category":"Professional",
            "subcategory":"Research",
            "type":"Services"
        }
    ],
    "sg:phone":"+1 513 574 6280",
    "sg:postcode":"45211",
    "sg:province":"OH",
    "sg:tags":[
        "environmental",
        "ecological"
    ],
    "sg:website":"www.etenv.com",
    "wof:name":"E T Environmental Corp",
    "wof:placetype":"venue"
},
  "geometry": {"coordinates":[-84.628221,39.157609],"type":"Point"}
}