{
  "type": "Feature",
  "properties": {
    "iso:country":"US",
    "sg:address":"600 Weber Dr",
    "sg:city":"Wadsworth",
    "sg:classifiers":[
        {
            "category":"Professional",
            "subcategory":"Computer Services",
            "type":"Services"
        }
    ],
    "sg:phone":"+1 330 352 7460",
    "sg:postcode":"44281",
    "sg:province":"OH",
    "sg:tags":[
        "repair"
    ],
    "wof:name":"Computer Surgeon Inc",
    "wof:placetype":"venue"
},
  "geometry": {"coordinates":[-81.76364,41.004701],"type":"Point"}
}