{
  "type": "Feature",
  "properties": {
    "iso:country":"US",
    "sg:address":"7701 W Salem Rd",
    "sg:city":"West Salem",
    "sg:phone":"+1 419 846 3340",
    "sg:postcode":"44287",
    "sg:province":"OH",
    "sg:tags":[
        "farm",
        "corn"
    ],
    "wof:name":"Koch Brothers",
    "wof:placetype":"venue"
},
  "geometry": {"coordinates":[-82.063621,40.990848],"type":"Point"}
}