{
  "type": "Feature",
  "properties": {
    "addr:full":"5205 New Albany Rd New Albany OH 43054",
    "addr:housenumber":"5205",
    "addr:postcode":"43054",
    "addr:street":"New Albany Rd",
    "iso:country":"US",
    "sg:address":"5205 New Albany Rd",
    "sg:city":"New Albany",
    "sg:classifiers":[
        {
            "category":"Restaurant",
            "type":"Food & Drink"
        }
    ],
    "sg:menulink":"http://www.allmenus.com/oh/columbus/44155-bob-evans/menu/",
    "sg:phone":"+1 614 939 4518",
    "sg:postcode":"43054",
    "sg:province":"OH",
    "sg:tags":[
        "american"
    ],
    "wof:name":"Bob Evans",
    "wof:placetype":"venue"
},
  "geometry": {"coordinates":[-82.823279,40.089191],"type":"Point"}
}