{
  "type": "Feature",
  "properties": {
    "addr:full": "209 E Britton Rd Burbank OH 44214",
    "addr:housenumber": "209",
    "addr:postcode": "44214",
    "addr:street": "E Britton Rd",
    "iso:country": "US",
    "sg:address": "209 E Britton Rd",
    "sg:city": "Burbank",
    "sg:classifiers": [
      {
        "category": "Freight",
        "type": "Transportation"
      }
    ],
    "sg:phone": "+1 330 435 6657",
    "sg:postcode": "44214",
    "sg:province": "OH",
    "sg:tags": [
      "operator",
      "trucking"
    ],
    "wof:name": "Winebrenner Enterprises",
    "wof:placetype": "venue"
  },
  "geometry": {"coordinates":[-81.951776,40.973917],"type":"Point"}
}
