{
  "type": "Feature",
  "properties": {
    "iso:country":"US",
    "sg:address":"1459 Hamilton Ave",
    "sg:city":"Cleveland",
    "sg:classifiers":[
        {
            "category":"Parking",
            "type":"Transportation"
        }
    ],
    "sg:phone":"+1 216 621 6600",
    "sg:postcode":"44114",
    "sg:province":"OH",
    "sg:tags":[
        "automobile",
        "facility"
    ],
    "wof:name":"Ampco System Parking Inc",
    "wof:placetype":"venue"
},
  "geometry": {"coordinates":[-81.686426,41.50705],"type":"Point"}
}