{
  "type": "Feature",
  "properties": {
    "addr:full": "851 Galaxy Ct Cincinnati OH 45224",
    "addr:housenumber": "851",
    "addr:postcode": "45224",
    "addr:street": "Galaxy Ct",
    "iso:country": "US",
    "sg:address": "851 Galaxy Ct",
    "sg:city": "Cincinnati",
    "sg:classifiers": [
      {
        "category": "Shopping",
        "subcategory": "Gifts \u0026 Souvenirs",
        "type": "Retail Goods"
      }
    ],
    "sg:phone": "+1 513 522 0914",
    "sg:postcode": "45224",
    "sg:province": "OH",
    "wof:name": "Q\u0026C Consulting",
    "wof:placetype": "venue"
  },
  "geometry": {"coordinates":[-84.516139,39.214126],"type":"Point"}
}
