{
  "type": "Feature",
  "properties": {
    "addr:full":"11351 E Pike Rd Cambridge OH 43725",
    "addr:housenumber":"11351",
    "addr:postcode":"43725",
    "addr:street":"E Pike Rd",
    "iso:country":"US",
    "sg:address":"11351 E Pike Rd",
    "sg:city":"Cambridge",
    "sg:classifiers":[
        {
            "category":"Organizations",
            "subcategory":"Community Association",
            "type":"Services"
        }
    ],
    "sg:phone":"+1 740 439 7751",
    "sg:postcode":"43725",
    "sg:province":"OH",
    "wof:name":"O E A",
    "wof:placetype":"venue"
},
  "geometry": {"coordinates":[-81.536179,40.024549],"type":"Point"}
}