{
  "type": "Feature",
  "properties": {
    "addr:full":"323 Orange St Jackson OH 45640",
    "addr:housenumber":"323",
    "addr:postcode":"45640",
    "addr:street":"Orange St",
    "iso:country":"US",
    "sg:address":"323 Orange St",
    "sg:city":"Jackson",
    "sg:classifiers":[
        {
            "category":"Professional",
            "type":"Services"
        }
    ],
    "sg:phone":"+1 740 286 8721",
    "sg:postcode":"45640",
    "sg:province":"OH",
    "wof:name":"David R Chisholm",
    "wof:placetype":"venue"
},
  "geometry": {"coordinates":[-82.650353,39.047981],"type":"Point"}
}