{
  "type": "Feature",
  "properties": {
    "iso:country":"US",
    "sg:address":"333 S Main St",
    "sg:city":"Akron",
    "sg:classifiers":[
        {
            "category":"Building & Trades",
            "subcategory":"Construction",
            "type":"Services"
        }
    ],
    "sg:phone":"+1 330 237 7300",
    "sg:postcode":"44308",
    "sg:province":"OH",
    "sg:tags":[
        "house"
    ],
    "wof:name":"Americas 1 Remodeler Inc",
    "wof:placetype":"venue"
},
  "geometry": {"coordinates":[-81.52186,41.076796],"type":"Point"}
}