{
  "type": "Feature",
  "properties": {
    "addr:full": "117 S Main St Marysville OH 43040",
    "addr:housenumber": "117",
    "addr:postcode": "43040",
    "addr:street": "S Main St",
    "iso:country": "US",
    "sg:address": "117 S Main St",
    "sg:city": "Marysville",
    "sg:classifiers": [
      {
        "category": "Shopping",
        "subcategory": "Used Merchandise",
        "type": "Retail Goods"
      }
    ],
    "sg:phone": "+1 937 642 9393",
    "sg:postcode": "43040",
    "sg:province": "OH",
    "sg:tags": [
      "antique"
    ],
    "wof:name": "Marysville Antique Mall",
    "wof:placetype": "venue"
  },
  "geometry": {"coordinates":[-83.367015,40.23624],"type":"Point"}
}
