{
  "type": "Feature",
  "properties": {
    "iso:country":"US",
    "sg:address":"235 Evergreen Dr",
    "sg:city":"Youngstown",
    "sg:classifiers":[
        {
            "category":"Building & Trades",
            "subcategory":"Construction",
            "type":"Services"
        }
    ],
    "sg:phone":"+1 330 402 3463",
    "sg:postcode":"44514",
    "sg:province":"OH",
    "sg:tags":[
        "downspouts",
        "gutter"
    ],
    "wof:name":"Dan's Gutter Cleaning & Repair",
    "wof:placetype":"venue"
},
  "geometry": {"coordinates":[-80.60225,41.021049],"type":"Point"}
}