{
  "type": "Feature",
  "properties": {
    "addr:full": "3461 S Canfield Niles Rd Canfield OH 44406",
    "addr:housenumber": "3461",
    "addr:postcode": "44406",
    "addr:street": "S Canfield Niles Rd",
    "iso:country": "US",
    "sg:address": "3461 S Canfield Niles Rd",
    "sg:city": "Canfield",
    "sg:classifiers": [
      {
        "category": "Freight",
        "type": "Transportation"
      }
    ],
    "sg:phone": "+1 330 533 0995",
    "sg:postcode": "44406",
    "sg:province": "OH",
    "sg:tags": [
      "operator",
      "local",
      "trucking"
    ],
    "wof:name": "Evans ME Trucking",
    "wof:placetype": "venue"
  },
  "geometry": {"coordinates":[-80.760537,41.063303],"type":"Point"}
}
