{
  "type": "Feature",
  "properties": {
    "addr:full": "3569 Newark Rd Zanesville OH 43701",
    "addr:housenumber": "3569",
    "addr:postcode": "43701",
    "addr:street": "Newark Rd",
    "iso:country": "US",
    "sg:address": "3569 Newark Rd",
    "sg:city": "Zanesville",
    "sg:classifiers": [
      {
        "category": "Freight",
        "type": "Transportation"
      }
    ],
    "sg:phone": "+1 740 452 2092",
    "sg:postcode": "43701",
    "sg:province": "OH",
    "sg:tags": [
      "special"
    ],
    "wof:name": "High N Dry Mini Storage Inc",
    "wof:placetype": "venue"
  },
  "geometry": {"coordinates":[-82.053621,39.984449],"type":"Point"}
}
