{
  "type": "Feature",
  "properties": {
    "addr:full": "5755 Granger Rd Cleveland OH 44131",
    "addr:housenumber": "5755",
    "addr:postcode": "44131",
    "addr:street": "Granger Rd",
    "iso:country": "US",
    "sg:address": "5755 Granger Rd",
    "sg:city": "Cleveland",
    "sg:classifiers": [
      {
        "category": "Shopping",
        "subcategory": "Computers \u0026 Home Electronics",
        "type": "Retail Goods"
      }
    ],
    "sg:phone": "+1 216 749 7180",
    "sg:postcode": "44131",
    "sg:province": "OH",
    "sg:tags": [
      "software"
    ],
    "wof:name": "Affiliated Resource Group",
    "wof:placetype": "venue"
  },
  "geometry": {"coordinates":[-81.652902,41.41507],"type":"Point"}
}
