{
  "type": "Feature",
  "properties": {
    "iso:country":"US",
    "sg:address":"5755 Granger Rd",
    "sg:city":"Cleveland",
    "sg:classifiers":[
        {
            "category":"Shopping",
            "subcategory":"Computers & Home Electronics",
            "type":"Retail Goods"
        }
    ],
    "sg:phone":"+1 216 749 7180",
    "sg:postcode":"44131",
    "sg:province":"OH",
    "sg:tags":[
        "software"
    ],
    "wof:name":"Affiliated Resource Group",
    "wof:placetype":"venue"
},
  "geometry": {"coordinates":[-81.652902,41.41507],"type":"Point"}
}