{
  "type": "Feature",
  "properties": {
    "iso:country":"US",
    "sg:address":"4124 Munson St NW",
    "sg:city":"Canton",
    "sg:classifiers":[
        {
            "category":"Health Services",
            "subcategory":"Doctor",
            "type":"Services"
        }
    ],
    "sg:phone":"+1 330 649 9323",
    "sg:postcode":"44718",
    "sg:province":"OH",
    "sg:tags":[
        "physician",
        "surgeon"
    ],
    "wof:name":"Ohio Vascular Care & Co",
    "wof:placetype":"venue"
},
  "geometry": {"coordinates":[-81.427559,40.84606],"type":"Point"}
}