{
  "type": "Feature",
  "properties": {
    "addr:full":"301 W Columbus Ave Bellefontaine OH 43311",
    "addr:housenumber":"301",
    "addr:postcode":"43311",
    "addr:street":"W Columbus Ave",
    "iso:country":"US",
    "sg:address":"301 W Columbus Ave",
    "sg:city":"Bellefontaine",
    "sg:classifiers":[
        {
            "category":"Manufacturing",
            "subcategory":"Chemicals & Compounds",
            "type":"Manufacturing & Wholesale Goods"
        },
        {
            "category":"Retail",
            "subcategory":"Auto Repair",
            "type":"Services"
        }
    ],
    "sg:phone":"+1 937 592 7836",
    "sg:postcode":"43311",
    "sg:province":"OH",
    "sg:tags":[
        "welding",
        "gas",
        "alignment",
        "supply"
    ],
    "wof:name":"Groves Alignment and Radiator",
    "wof:placetype":"venue"
},
  "geometry": {"coordinates":[-83.764048,40.361421],"type":"Point"}
}