{
  "type": "Feature",
  "properties": {
    "iso:country":"US",
    "sg:address":"8040 Co Rd 139",
    "sg:city":"Findlay",
    "sg:phone":"+1 419 423 0680",
    "sg:postcode":"45840",
    "sg:province":"OH",
    "sg:tags":[
        "farm",
        "corn",
        "soybean"
    ],
    "wof:name":"Doyle Tuttle",
    "wof:placetype":"venue"
},
  "geometry": {"coordinates":[-83.708065,41.046311],"type":"Point"}
}