{
  "type": "Feature",
  "properties": {
    "addr:full": "16213 E Liverpool Rd East Liverpool OH 43920",
    "addr:housenumber": "16213",
    "addr:postcode": "43920",
    "addr:street": "E Liverpool Rd",
    "iso:country": "US",
    "sg:address": "16213 E Liverpool Rd",
    "sg:city": "East Liverpool",
    "sg:classifiers": [
      {
        "category": "Retail",
        "subcategory": "Animal Services",
        "type": "Services"
      }
    ],
    "sg:phone": "+1 330 385 7387",
    "sg:postcode": "43920",
    "sg:province": "OH",
    "sg:tags": [
      "pet",
      "boarding",
      "sitting"
    ],
    "wof:name": "Golden Pond Pet Camp",
    "wof:placetype": "venue"
  },
  "geometry": {"coordinates":[-80.598054,40.666983],"type":"Point"}
}
