{
  "type": "Feature",
  "properties": {
    "addr:full": "2103 Harrison Ave SW Canton OH 44706",
    "addr:housenumber": "2103",
    "addr:postcode": "44706",
    "addr:street": "Harrison Ave Sw",
    "iso:country": "US",
    "sg:address": "2103 Harrison Ave SW",
    "sg:city": "Canton",
    "sg:classifiers": [
      {
        "category": "Bars \u0026 Pubs",
        "type": "Food \u0026 Drink"
      }
    ],
    "sg:phone": "+1 330 454 0152",
    "sg:postcode": "44706",
    "sg:province": "OH",
    "sg:tags": [
      "drinking"
    ],
    "wof:name": "Smitty's Pub",
    "wof:placetype": "venue"
  },
  "geometry": {"coordinates":[-81.399057,40.77496],"type":"Point"}
}
