{
  "type": "Feature",
  "properties": {
    "addr:full": "8101 N High St Columbus OH 43235",
    "addr:housenumber": "8101",
    "addr:postcode": "43235",
    "addr:street": "N High St",
    "iso:country": "US",
    "sg:address": "8101 N High St",
    "sg:city": "Columbus",
    "sg:classifiers": [
      {
        "category": "Banks \u0026 Credit Unions",
        "subcategory": "Investment Brokerage",
        "type": "Services"
      }
    ],
    "sg:phone": "+1 614 846 7193",
    "sg:postcode": "43235",
    "sg:province": "OH",
    "sg:tags": [
      "consultant",
      "planning",
      "financial"
    ],
    "wof:name": "American Express Financial Adv",
    "wof:placetype": "venue"
  },
  "geometry": {"coordinates":[-83.016306,40.126895],"type":"Point"}
}
