{
  "type": "Feature",
  "properties": {
    "addr:full": "164 Sylvia Ln Cincinnati OH 45215",
    "addr:housenumber": "164",
    "addr:postcode": "45215",
    "addr:street": "Sylvia Ln",
    "iso:country": "US",
    "sg:address": "164 Sylvia Ln",
    "sg:city": "Cincinnati",
    "sg:classifiers": [
      {
        "category": "Building \u0026 Trades",
        "subcategory": "Construction",
        "type": "Services"
      }
    ],
    "sg:phone": "+1 513 733 5338",
    "sg:postcode": "45215",
    "sg:province": "OH",
    "sg:tags": [
      "general",
      "contractor"
    ],
    "wof:name": "Fricke \u0026 Wells LLC",
    "wof:placetype": "venue"
  },
  "geometry": {"coordinates":[-84.417601,39.230692],"type":"Point"}
}
