{
  "type": "Feature",
  "properties": {
    "iso:country":"US",
    "sg:address":"164 Sylvia Ln",
    "sg:city":"Cincinnati",
    "sg:classifiers":[
        {
            "category":"Building & Trades",
            "subcategory":"Construction",
            "type":"Services"
        }
    ],
    "sg:phone":"+1 513 733 5338",
    "sg:postcode":"45215",
    "sg:province":"OH",
    "sg:tags":[
        "general",
        "contractor"
    ],
    "wof:name":"Fricke & Wells LLC",
    "wof:placetype":"venue"
},
  "geometry": {"coordinates":[-84.417601,39.230692],"type":"Point"}
}