{
  "type": "Feature",
  "properties": {
    "addr:full": "119 E Main St Eaton OH 45320",
    "addr:housenumber": "119",
    "addr:postcode": "45320",
    "addr:street": "E Main St",
    "iso:country": "US",
    "sg:address": "119 E Main St",
    "sg:city": "Eaton",
    "sg:classifiers": [
      {
        "category": "Home \u0026 Garden",
        "subcategory": "Hardware",
        "type": "Retail Goods"
      }
    ],
    "sg:phone": "+1 937 456 3939",
    "sg:postcode": "45320",
    "sg:province": "OH",
    "wof:name": "Wilson Hardware Co",
    "wof:placetype": "venue"
  },
  "geometry": {"coordinates":[-84.635001,39.743878],"type":"Point"}
}
