{
  "type": "Feature",
  "properties": {
    "addr:full": "13550 Old Lincoln Way Dalton OH 44618",
    "addr:housenumber": "13550",
    "addr:postcode": "44618",
    "addr:street": "Old Lincoln Way",
    "iso:country": "US",
    "sg:address": "13550 Old Lincoln Way",
    "sg:city": "Dalton",
    "sg:classifiers": [
      {
        "category": "Building \u0026 Trades",
        "subcategory": "Construction",
        "type": "Services"
      }
    ],
    "sg:phone": "+1 330 683 5809",
    "sg:postcode": "44618",
    "sg:province": "OH",
    "sg:tags": [
      "contractor"
    ],
    "wof:name": "Raff Insulation",
    "wof:placetype": "venue"
  },
  "geometry": {"coordinates":[-81.73972,40.799215],"type":"Point"}
}
