{
  "type": "Feature",
  "properties": {
    "addr:full": "7700 New Carlisle Rd Dayton OH 45424",
    "addr:housenumber": "7700",
    "addr:postcode": "45424",
    "addr:street": "New Carlisle Rd",
    "iso:country": "US",
    "sg:address": "7700 New Carlisle Rd",
    "sg:city": "Dayton",
    "sg:classifiers": [
      {
        "category": "Manufacturing",
        "subcategory": "Aerospace",
        "type": "Manufacturing \u0026 Wholesale Goods"
      }
    ],
    "sg:phone": "+1 937 878 3800",
    "sg:postcode": "45424",
    "sg:province": "OH",
    "sg:tags": [
      "aircraft",
      "s",
      "mfg"
    ],
    "wof:name": "Enginetics Corporation",
    "wof:placetype": "venue"
  },
  "geometry": {"coordinates":[-84.060926,39.86454],"type":"Point"}
}
