{
  "type": "Feature",
  "properties": {
    "iso:country":"US",
    "sg:address":"5374 Co Rd 60",
    "sg:city":"Ada",
    "sg:classifiers":[
        {
            "category":"Building & Trades",
            "subcategory":"Construction",
            "type":"Services"
        }
    ],
    "sg:phone":"+1 419 634 0111",
    "sg:postcode":"45810",
    "sg:province":"OH",
    "sg:tags":[
        "excavating",
        "contractor"
    ],
    "wof:name":"Country Excavating Inc",
    "wof:placetype":"venue"
},
  "geometry": {"coordinates":[-83.777331,40.747348],"type":"Point"}
}