{
  "type": "Feature",
  "properties": {
    "addr:full":"75 N Main St Rittman OH 44270",
    "addr:housenumber":"75",
    "addr:postcode":"44270",
    "addr:street":"N Main St",
    "iso:country":"US",
    "sg:address":"75 N Main St",
    "sg:city":"Rittman",
    "sg:classifiers":[
        {
            "category":"Education",
            "subcategory":"School",
            "type":"Public Place"
        }
    ],
    "sg:phone":"+1 330 927 3145",
    "sg:postcode":"44270",
    "sg:province":"OH",
    "sg:website":"www.tccsa.net",
    "wof:name":"Rittman Middle School",
    "wof:placetype":"venue"
},
  "geometry": {"coordinates":[-81.78161,40.973855],"type":"Point"}
}