{
  "type": "Feature",
  "properties": {
    "addr:full":"1180 Wingwood Dr Batavia OH 45103",
    "addr:housenumber":"1180",
    "addr:postcode":"45103",
    "addr:street":"Wingwood Dr",
    "iso:country":"US",
    "sg:address":"1180 Wingwood Dr",
    "sg:city":"Batavia",
    "sg:classifiers":[
        {
            "category":"Travel",
            "subcategory":"Travel Agent",
            "type":"Entertainment"
        }
    ],
    "sg:phone":"+1 513 947 8739",
    "sg:postcode":"45103",
    "sg:province":"OH",
    "sg:tags":[
        "operator",
        "tour"
    ],
    "wof:name":"Johnson Tours Inc",
    "wof:placetype":"venue"
},
  "geometry": {"coordinates":[-84.241283,39.077468],"type":"Point"}
}