{
  "type": "Feature",
  "properties": {
    "addr:full":"13240 Indian Hollow Rd Grafton OH 44044",
    "addr:housenumber":"13240",
    "addr:postcode":"44044",
    "addr:street":"Indian Hollow Rd",
    "iso:country":"US",
    "sg:address":"13240 Indian Hollow Rd",
    "sg:city":"Grafton",
    "sg:classifiers":[
        {
            "category":"Home & Garden",
            "subcategory":"Hardware",
            "type":"Retail Goods"
        }
    ],
    "sg:phone":"+1 440 458 4374",
    "sg:postcode":"44044",
    "sg:province":"OH",
    "wof:name":"Ladd Tool Co Inc",
    "wof:placetype":"venue"
},
  "geometry": {"coordinates":[-82.08573800000001,41.297301],"type":"Point"}
}