{
  "type": "Feature",
  "properties": {
    "addr:full": "726 E Main St Lebanon OH 45036",
    "addr:housenumber": "726",
    "addr:postcode": "45036",
    "addr:street": "E Main St",
    "iso:country": "US",
    "sg:address": "726 E Main St",
    "sg:city": "Lebanon",
    "sg:classifiers": [
      {
        "category": "Home \u0026 Garden",
        "subcategory": "Carpets \u0026 Floor Coverings",
        "type": "Retail Goods"
      }
    ],
    "sg:phone": "+1 513 932 5898",
    "sg:postcode": "45036",
    "sg:province": "OH",
    "sg:tags": [
      "rug",
      "dealer"
    ],
    "wof:name": "Carroll's Carpets",
    "wof:placetype": "venue"
  },
  "geometry": {"coordinates":[-84.192018,39.432307],"type":"Point"}
}
