{
  "type": "Feature",
  "properties": {
    "addr:full": "6216 Rogers Park Pl Cincinnati OH 45213",
    "addr:housenumber": "6216",
    "addr:postcode": "45213",
    "addr:street": "Rogers Park Pl",
    "iso:country": "US",
    "sg:address": "6216 Rogers Park Pl",
    "sg:city": "Cincinnati",
    "sg:classifiers": [
      {
        "category": "Farming",
        "subcategory": "Fish \u0026 Marine Products",
        "type": "Manufacturing \u0026 Wholesale Goods"
      }
    ],
    "sg:phone": "+1 513 731 7827",
    "sg:postcode": "45213",
    "sg:province": "OH",
    "sg:tags": [
      "actuary"
    ],
    "wof:name": "Star Consltg. Group",
    "wof:placetype": "venue"
  },
  "geometry": {"coordinates":[-84.416786,39.185371],"type":"Point"}
}
