{
  "type": "Feature",
  "properties": {
    "iso:country":"US",
    "sg:address":"6216 Rogers Park Pl",
    "sg:city":"Cincinnati",
    "sg:classifiers":[
        {
            "category":"Farming",
            "subcategory":"Fish & Marine Products",
            "type":"Manufacturing & Wholesale Goods"
        }
    ],
    "sg:phone":"+1 513 731 7827",
    "sg:postcode":"45213",
    "sg:province":"OH",
    "sg:tags":[
        "actuary"
    ],
    "wof:name":"Star Consltg. Group",
    "wof:placetype":"venue"
},
  "geometry": {"coordinates":[-84.416786,39.185371],"type":"Point"}
}