{
  "type": "Feature",
  "properties": {
    "addr:full": "8115 Factory Shops Blvd Jeffersonville OH 43128",
    "addr:housenumber": "8115",
    "addr:postcode": "43128",
    "addr:street": "Factory Shops Blvd",
    "iso:country": "US",
    "sg:address": "8115 Factory Shops Blvd",
    "sg:city": "Jeffersonville",
    "sg:classifiers": [
      {
        "category": "Shopping",
        "subcategory": "Clothing, Apparel, \u0026 Fashions",
        "type": "Retail Goods"
      }
    ],
    "sg:phone": "+1 740 948 2068",
    "sg:postcode": "43128",
    "sg:province": "OH",
    "sg:tags": [
      "furnishing"
    ],
    "wof:name": "Casual Male Big \u0026 Tall",
    "wof:placetype": "venue"
  },
  "geometry": {"coordinates":[-83.601258,39.618126],"type":"Point"}
}
