{
  "type": "Feature",
  "properties": {
    "iso:country":"US",
    "sg:address":"1820 E Market St",
    "sg:city":"Warren",
    "sg:classifiers":[
        {
            "category":"Health Services",
            "subcategory":"Doctor",
            "type":"Services"
        }
    ],
    "sg:phone":"+1 330 394 6660",
    "sg:postcode":"44483",
    "sg:province":"OH",
    "sg:tags":[
        "dentist"
    ],
    "wof:name":"Anthony P Antolini DDS",
    "wof:placetype":"venue"
},
  "geometry": {"coordinates":[-80.793803,41.236464],"type":"Point"}
}