{
  "type": "Feature",
  "properties": {
    "addr:full": "414 Hyder Dr Madison OH 44057",
    "addr:housenumber": "414",
    "addr:postcode": "44057",
    "addr:street": "Hyder Dr",
    "iso:country": "US",
    "sg:address": "414 Hyder Dr",
    "sg:city": "Madison",
    "sg:classifiers": [
      {
        "category": "Banks \u0026 Credit Unions",
        "subcategory": "Investment Brokerage",
        "type": "Services"
      }
    ],
    "sg:phone": "+1 440 428 1212",
    "sg:postcode": "44057",
    "sg:province": "OH",
    "sg:tags": [
      "advisory",
      "financial"
    ],
    "wof:name": "Amenity Financial Advisors",
    "wof:placetype": "venue"
  },
  "geometry": {"coordinates":[-81.037911,41.766422],"type":"Point"}
}
