{
  "type": "Feature",
  "properties": {
    "iso:country":"US",
    "sg:address":"2238 E River Rd",
    "sg:city":"Dayton",
    "sg:classifiers":[
        {
            "category":"Building & Trades",
            "subcategory":"Plumbing",
            "type":"Services"
        }
    ],
    "sg:phone":"+1 937 299 2500",
    "sg:postcode":"45439",
    "sg:province":"OH",
    "sg:tags":[
        "air",
        "ventilation",
        "warm",
        "heating",
        "conditioning"
    ],
    "wof:name":"Tanner Heating & AC",
    "wof:placetype":"venue"
},
  "geometry": {"coordinates":[-84.21914,39.723503],"type":"Point"}
}