{
  "type": "Feature",
  "properties": {
    "iso:country":"US",
    "sg:address":"507 Whites Rd",
    "sg:city":"Marietta",
    "sg:classifiers":[
        {
            "category":"Real Estate",
            "subcategory":"Real Estate Agent",
            "type":"Services"
        }
    ],
    "sg:phone":"+1 740 374 6331",
    "sg:postcode":"45750",
    "sg:province":"OH",
    "wof:name":"C & J Property Management Ltd",
    "wof:placetype":"venue"
},
  "geometry": {"coordinates":[-81.45130899999999,39.41836],"type":"Point"}
}