{
  "type": "Feature",
  "properties": {
    "iso:country":"US",
    "sg:address":"14235 Madison Ave",
    "sg:city":"Cleveland",
    "sg:classifiers":[
        {
            "category":"Autos & Motor Vehicles",
            "subcategory":"Fuel & Gas Station",
            "type":"Retail Goods"
        }
    ],
    "sg:phone":"+1 216 529 1638",
    "sg:postcode":"44107",
    "sg:province":"OH",
    "sg:tags":[
        "oil"
    ],
    "wof:name":"Upm",
    "wof:placetype":"venue"
},
  "geometry": {"coordinates":[-81.793343,41.477057],"type":"Point"}
}