{
  "type": "Feature",
  "properties": {
    "addr:full": "14235 Madison Ave Cleveland OH 44107",
    "addr:housenumber": "14235",
    "addr:postcode": "44107",
    "addr:street": "Madison Ave",
    "iso:country": "US",
    "sg:address": "14235 Madison Ave",
    "sg:city": "Cleveland",
    "sg:classifiers": [
      {
        "category": "Autos \u0026 Motor Vehicles",
        "subcategory": "Fuel \u0026 Gas Station",
        "type": "Retail Goods"
      }
    ],
    "sg:phone": "+1 216 529 1638",
    "sg:postcode": "44107",
    "sg:province": "OH",
    "sg:tags": [
      "oil"
    ],
    "wof:name": "Upm",
    "wof:placetype": "venue"
  },
  "geometry": {"coordinates":[-81.793343,41.477057],"type":"Point"}
}
