{
  "type": "Feature",
  "properties": {
    "addr:full": "4500 Cemetery Rd Hilliard OH 43026",
    "addr:housenumber": "4500",
    "addr:postcode": "43026",
    "addr:street": "Cemetery Rd",
    "iso:country": "US",
    "sg:address": "4500 Cemetery Rd",
    "sg:city": "Hilliard",
    "sg:classifiers": [
      {
        "category": "Arts \u0026 Performance",
        "subcategory": "Theater",
        "type": "Entertainment"
      }
    ],
    "sg:phone": "+1 614 777 7632",
    "sg:postcode": "43026",
    "sg:province": "OH",
    "sg:tags": [
      "magician"
    ],
    "wof:name": "Joe Lyon's Magic Enterprises",
    "wof:placetype": "venue"
  },
  "geometry": {"coordinates":[-83.135925,40.032153],"type":"Point"}
}
