{
  "type": "Feature",
  "properties": {
    "iso:country":"US",
    "sg:address":"1060 W Alexis Rd",
    "sg:city":"Toledo",
    "sg:classifiers":[
        {
            "category":"Banks & Credit Unions",
            "subcategory":"Bank",
            "type":"Services"
        }
    ],
    "sg:phone":"+1 419 269 0792",
    "sg:postcode":"43612",
    "sg:province":"OH",
    "sg:tags":[
        "financing"
    ],
    "wof:name":"American General Finance Inc",
    "wof:placetype":"venue"
},
  "geometry": {"coordinates":[-83.569492,41.721601],"type":"Point"}
}