{
  "type": "Feature",
  "properties": {
    "iso:country":"US",
    "sg:address":"618 E Weisheimer Rd",
    "sg:city":"Columbus",
    "sg:classifiers":[
        {
            "category":"Professional",
            "subcategory":"Art Services",
            "type":"Services"
        }
    ],
    "sg:phone":"+1 614 246 6068",
    "sg:postcode":"43214",
    "sg:province":"OH",
    "sg:tags":[
        "graphic",
        "designer"
    ],
    "wof:name":"Written Expressions",
    "wof:placetype":"venue"
},
  "geometry": {"coordinates":[-83.00371800000001,40.054582],"type":"Point"}
}