{
  "type": "Feature",
  "properties": {
    "addr:full": "1800 Lyn Grove Dr Cridersville OH 45806",
    "addr:housenumber": "1800",
    "addr:postcode": "45806",
    "addr:street": "Lyn Grove Dr",
    "iso:country": "US",
    "sg:address": "1800 Lyn Grove Dr",
    "sg:city": "Cridersville",
    "sg:classifiers": [
      {
        "category": "Building \u0026 Trades",
        "subcategory": "Construction",
        "type": "Services"
      }
    ],
    "sg:phone": "+1 419 645 5128",
    "sg:postcode": "45806",
    "sg:province": "OH",
    "sg:tags": [
      "maintenance",
      "contractor"
    ],
    "wof:name": "Master Maintenance",
    "wof:placetype": "venue"
  },
  "geometry": {"coordinates":[-84.1358,40.659616],"type":"Point"}
}
