{
  "type": "Feature",
  "properties": {
    "addr:full":"655 Central Ave Franklin OH 45005",
    "addr:housenumber":"655",
    "addr:postcode":"45005",
    "addr:street":"Central Ave",
    "iso:country":"US",
    "sg:address":"655 Central Ave",
    "sg:city":"Franklin",
    "sg:classifiers":[
        {
            "category":"Banks & Credit Unions",
            "subcategory":"Bank",
            "type":"Services"
        }
    ],
    "sg:phone":"+1 937 746 9077",
    "sg:postcode":"45005",
    "sg:province":"OH",
    "wof:name":"First National Bank-Carlisle",
    "wof:placetype":"venue"
},
  "geometry": {"coordinates":[-84.31966199999999,39.581895],"type":"Point"}
}