{
  "type": "Feature",
  "properties": {
    "iso:country":"US",
    "sg:address":"18605 May Rd",
    "sg:city":"Botkins",
    "sg:classifiers":[
        {
            "category":"Wholesale",
            "subcategory":"Machinery & Supplies",
            "type":"Manufacturing & Wholesale Goods"
        }
    ],
    "sg:phone":"+1 937 693 2382",
    "sg:postcode":"45306",
    "sg:province":"OH",
    "sg:tags":[
        "machine",
        "tool"
    ],
    "wof:name":"May Custom Mfg Inc",
    "wof:placetype":"venue"
},
  "geometry": {"coordinates":[-84.240533,40.468023],"type":"Point"}
}