{
  "type": "Feature",
  "properties": {
    "addr:full": "16300 Saranac Rd Cleveland OH 44110",
    "addr:housenumber": "16300",
    "addr:postcode": "44110",
    "addr:street": "Saranac Rd",
    "iso:country": "US",
    "sg:address": "16300 Saranac Rd",
    "sg:city": "Cleveland",
    "sg:classifiers": [
      {
        "category": "Real Estate",
        "subcategory": "Real Estate Agent",
        "type": "Services"
      }
    ],
    "sg:phone": "+1 216 531 7010",
    "sg:postcode": "44110",
    "sg:province": "OH",
    "sg:tags": [
      "management"
    ],
    "wof:name": "R \u0026 K Terminal Management",
    "wof:placetype": "venue"
  },
  "geometry": {"coordinates":[-81.56431,41.565503],"type":"Point"}
}
