{
  "type": "Feature",
  "properties": {
    "iso:country":"US",
    "sg:address":"16300 Saranac Rd",
    "sg:city":"Cleveland",
    "sg:classifiers":[
        {
            "category":"Real Estate",
            "subcategory":"Real Estate Agent",
            "type":"Services"
        }
    ],
    "sg:phone":"+1 216 531 7010",
    "sg:postcode":"44110",
    "sg:province":"OH",
    "sg:tags":[
        "management"
    ],
    "wof:name":"R & K Terminal Management",
    "wof:placetype":"venue"
},
  "geometry": {"coordinates":[-81.56431000000001,41.565503],"type":"Point"}
}