{
  "type": "Feature",
  "properties": {
    "addr:full":"1100 Broad Ave Findlay OH 45840",
    "addr:housenumber":"1100",
    "addr:postcode":"45840",
    "addr:street":"Broad Ave",
    "iso:country":"US",
    "sg:address":"1100 Broad Ave",
    "sg:city":"Findlay",
    "sg:classifiers":[
        {
            "category":"Social Services",
            "subcategory":"Job Training",
            "type":"Services"
        }
    ],
    "sg:phone":"+1 419 420 7012",
    "sg:postcode":"45840",
    "sg:province":"OH",
    "sg:tags":[
        "employment"
    ],
    "sg:website":"www.findlaycityschools.org",
    "wof:name":"Millstream Career & Technology",
    "wof:placetype":"venue"
},
  "geometry": {"coordinates":[-83.664565,41.053435],"type":"Point"}
}