{
  "type": "Feature",
  "properties": {
    "addr:full": "7605 Washington Park Dr Dayton OH 45459",
    "addr:housenumber": "7605",
    "addr:postcode": "45459",
    "addr:street": "Washington Park Dr",
    "iso:country": "US",
    "sg:address": "7605 Washington Park Dr",
    "sg:city": "Dayton",
    "sg:classifiers": [
      {
        "category": "Real Estate",
        "subcategory": "Real Estate Operator",
        "type": "Services"
      }
    ],
    "sg:phone": "+1 937 428 7750",
    "sg:postcode": "45459",
    "sg:province": "OH",
    "sg:tags": [
      "building",
      "apartment"
    ],
    "wof:name": "Washington Park Apartments",
    "wof:placetype": "venue"
  },
  "geometry": {"coordinates":[-84.208066,39.639055],"type":"Point"}
}
