{
  "type": "Feature",
  "properties": {
    "addr:full":"5131 Glencrossing Way Cincinnati OH 45238",
    "addr:housenumber":"5131",
    "addr:postcode":"45238",
    "addr:street":"Glencrossing Way",
    "iso:country":"US",
    "sg:address":"5131 Glencrossing Way",
    "sg:city":"Cincinnati",
    "sg:classifiers":[
        {
            "category":"Sports & Exercise",
            "subcategory":"Gym",
            "type":"Entertainment"
        }
    ],
    "sg:phone":"+1 513 347 4653",
    "sg:postcode":"45238",
    "sg:province":"OH",
    "sg:tags":[
        "club",
        "health",
        "studio",
        "gymnasium"
    ],
    "wof:name":"Gold's Gym",
    "wof:placetype":"venue"
},
  "geometry": {"coordinates":[-84.616112,39.130383],"type":"Point"}
}