{
  "type": "Feature",
  "properties": {
    "addr:full": "28569 Glenwood Rd Perrysburg OH 43551",
    "addr:housenumber": "28569",
    "addr:postcode": "43551",
    "addr:street": "Glenwood Rd",
    "iso:country": "US",
    "sg:address": "28569 Glenwood Rd",
    "sg:city": "Perrysburg",
    "sg:classifiers": [
      {
        "category": "Freight",
        "type": "Transportation"
      }
    ],
    "sg:phone": "+1 419 666 1498",
    "sg:postcode": "43551",
    "sg:province": "OH",
    "sg:tags": [
      "trucking"
    ],
    "wof:name": "Falcon Transport",
    "wof:placetype": "venue"
  },
  "geometry": {"coordinates":[-83.557748,41.569151],"type":"Point"}
}
