{
  "type": "Feature",
  "properties": {
    "iso:country":"US",
    "sg:address":"7733 Pleasant Valley Rd",
    "sg:city":"Camden",
    "sg:classifiers":[
        {
            "category":"Real Estate",
            "subcategory":"Real Estate Operator",
            "type":"Services"
        }
    ],
    "sg:phone":"+1 937 787 4563",
    "sg:postcode":"45311",
    "sg:province":"OH",
    "sg:tags":[
        "property",
        "lessor"
    ],
    "wof:name":"Jeffery A Faulkner",
    "wof:placetype":"venue"
},
  "geometry": {"coordinates":[-84.498636,39.627375],"type":"Point"}
}