{
  "type": "Feature",
  "properties": {
    "addr:full":"76 Spring Creek Rd Northfield OH 44067",
    "addr:housenumber":"76",
    "addr:postcode":"44067",
    "addr:street":"Spring Creek Rd",
    "iso:country":"US",
    "sg:address":"76 Spring Creek Rd",
    "sg:city":"Northfield",
    "sg:classifiers":[
        {
            "category":"Building & Trades",
            "subcategory":"Plumbing",
            "type":"Services"
        }
    ],
    "sg:phone":"+1 330 467 8770",
    "sg:postcode":"44067",
    "sg:province":"OH",
    "sg:tags":[
        "contractor"
    ],
    "wof:name":"Shagrin Valley Plumbing",
    "wof:placetype":"venue"
},
  "geometry": {"coordinates":[-81.54241500000001,41.317462],"type":"Point"}
}