{
  "type": "Feature",
  "properties": {
    "addr:full": "515 W Broadway St New Lexington OH 43764",
    "addr:housenumber": "515",
    "addr:postcode": "43764",
    "addr:street": "W Broadway St",
    "iso:country": "US",
    "sg:address": "515 W Broadway St",
    "sg:city": "New Lexington",
    "sg:classifiers": [
      {
        "category": "Autos \u0026 Motor Vehicles",
        "subcategory": "Automobile Sales",
        "type": "Retail Goods"
      }
    ],
    "sg:phone": "+1 740 342 1407",
    "sg:postcode": "43764",
    "sg:province": "OH",
    "sg:tags": [
      "body",
      "car",
      "used",
      "dealer"
    ],
    "wof:name": "Fair Deal Used Cars Inc",
    "wof:placetype": "venue"
  },
  "geometry": {"coordinates":[-82.217928,39.720423],"type":"Point"}
}
