{
  "type": "Feature",
  "properties": {
    "iso:country":"US",
    "sg:address":"3814 West St",
    "sg:city":"Cincinnati",
    "sg:classifiers":[
        {
            "category":"Banks & Credit Unions",
            "subcategory":"Bank",
            "type":"Services"
        }
    ],
    "sg:phone":"+1 513 272 8989",
    "sg:postcode":"45227",
    "sg:province":"OH",
    "sg:tags":[
        "loan"
    ],
    "wof:name":"Concord Business Assoc",
    "wof:placetype":"venue"
},
  "geometry": {"coordinates":[-84.376481,39.146399],"type":"Point"}
}