{
  "type": "Feature",
  "properties": {
    "addr:full": "3093 E Pleasant Home Rd Creston OH 44217",
    "addr:housenumber": "3093",
    "addr:postcode": "44217",
    "addr:street": "E Pleasant Home Rd",
    "iso:country": "US",
    "sg:address": "3093 E Pleasant Home Rd",
    "sg:city": "Creston",
    "sg:phone": "+1 330 435 4357",
    "sg:postcode": "44217",
    "sg:province": "OH",
    "sg:tags": [
      "farm",
      "corn",
      "dairy",
      "soybean"
    ],
    "wof:name": "Virgil Gasser",
    "wof:placetype": "venue"
  },
  "geometry": {"coordinates":[-81.907111,40.915791],"type":"Point"}
}
