{
  "type": "Feature",
  "properties": {
    "iso:country":"US",
    "sg:address":"5012 Glenway Ave",
    "sg:city":"Cincinnati",
    "sg:classifiers":[
        {
            "category":"Professional",
            "type":"Services"
        }
    ],
    "sg:phone":"+1 513 921 0796",
    "sg:postcode":"45238",
    "sg:province":"OH",
    "sg:tags":[
        "establishment"
    ],
    "wof:name":"Rumors",
    "wof:placetype":"venue"
},
  "geometry": {"coordinates":[-84.601789,39.122321],"type":"Point"}
}