{
  "type": "Feature",
  "properties": {
    "iso:country":"US",
    "sg:address":"7790 N Central Dr",
    "sg:city":"Lewis Center",
    "sg:classifiers":[
        {
            "category":"Professional",
            "type":"Services"
        }
    ],
    "sg:phone":"+1 740 223 7777",
    "sg:postcode":"43035",
    "sg:province":"OH",
    "sg:tags":[
        "establishment"
    ],
    "wof:name":"Sakamura USA",
    "wof:placetype":"venue"
},
  "geometry": {"coordinates":[-83.01281,40.17703],"type":"Point"}
}