{
  "type": "Feature",
  "properties": {
    "addr:full":"11700 E Washington St Burton OH 44021",
    "addr:housenumber":"11700",
    "addr:postcode":"44021",
    "addr:street":"E Washington St",
    "iso:country":"US",
    "sg:address":"11700 E Washington St",
    "sg:city":"Burton",
    "sg:classifiers":[
        {
            "category":"Banks & Credit Unions",
            "subcategory":"Bank",
            "type":"Services"
        }
    ],
    "sg:phone":"+1 440 708 0902",
    "sg:postcode":"44021",
    "sg:province":"OH",
    "wof:name":"Charter One Bank",
    "wof:placetype":"venue"
},
  "geometry": {"coordinates":[-81.225267,41.387208],"type":"Point"}
}