{
  "type": "Feature",
  "properties": {
    "addr:full": "500 2nd Ave Stratton OH 43961",
    "addr:housenumber": "500",
    "addr:postcode": "43961",
    "addr:street": "2Nd Ave",
    "iso:country": "US",
    "sg:address": "500 2nd Ave",
    "sg:city": "Stratton",
    "sg:classifiers": [
      {
        "category": "Building \u0026 Trades",
        "subcategory": "Cleaning \u0026 Sanitation",
        "type": "Services"
      }
    ],
    "sg:phone": "+1 740 282 3690",
    "sg:postcode": "43961",
    "sg:province": "OH",
    "wof:name": "Hydrochem Industrial Svc",
    "wof:placetype": "venue"
  },
  "geometry": {"coordinates":[-80.627918,40.523697],"type":"Point"}
}
