{
  "type": "Feature",
  "properties": {
    "addr:full": "2400 Elida Rd Lima OH 45805",
    "addr:postcode": "2400;45805",
    "addr:street": "Elida Rd",
    "iso:country": "US",
    "sg:address": "2400 Elida Rd",
    "sg:city": "Lima",
    "sg:classifiers": [
      {
        "category": "Shopping",
        "subcategory": "Jewelry",
        "type": "Retail Goods"
      }
    ],
    "sg:phone": "+1 419 331 1155",
    "sg:postcode": "45805",
    "sg:province": "OH",
    "wof:name": "Piercing Pagoda",
    "wof:placetype": "venue"
  },
  "geometry": {"coordinates":[-84.148983,40.762762],"type":"Point"}
}
