{
  "type": "Feature",
  "properties": {
    "addr:full": "3879 Rhodes Ave New Boston OH 45662",
    "addr:housenumber": "3879",
    "addr:postcode": "45662",
    "addr:street": "Rhodes Ave",
    "iso:country": "US",
    "sg:address": "3879 Rhodes Ave",
    "sg:city": "New Boston",
    "sg:classifiers": [
      {
        "category": "Shopping",
        "subcategory": "Computers \u0026 Home Electronics",
        "type": "Retail Goods"
      },
      {
        "category": "Professional",
        "subcategory": "Computer Services",
        "type": "Services"
      }
    ],
    "sg:phone": "+1 740 456 3333",
    "sg:postcode": "45662",
    "sg:province": "OH",
    "sg:tags": [
      "repair"
    ],
    "sg:website": "www.ccspecialties.com",
    "wof:name": "C \u0026 C Specialties",
    "wof:placetype": "venue"
  },
  "geometry": {"coordinates":[-82.938971,38.749906],"type":"Point"}
}
