{
  "type": "Feature",
  "properties": {
    "addr:full":"1030 N Fountain Ave Springfield OH 45504",
    "addr:housenumber":"1030",
    "addr:postcode":"45504",
    "addr:street":"N Fountain Ave",
    "iso:country":"US",
    "sg:address":"1030 N Fountain Ave",
    "sg:city":"Springfield",
    "sg:classifiers":[
        {
            "category":"Health Services",
            "subcategory":"Doctor",
            "type":"Services"
        }
    ],
    "sg:phone":"+1 937 323 8874",
    "sg:postcode":"45504",
    "sg:province":"OH",
    "sg:tags":[
        "physician",
        "surgeon"
    ],
    "wof:name":"Charles J Townsend MD",
    "wof:placetype":"venue"
},
  "geometry": {"coordinates":[-83.80912600000001,39.936728],"type":"Point"}
}