{
  "type": "Feature",
  "properties": {
    "iso:country":"US",
    "sg:address":"512 Bidwell Ave",
    "sg:city":"Fremont",
    "sg:classifiers":[
        {
            "category":"Bars & Pubs",
            "type":"Food & Drink"
        }
    ],
    "sg:phone":"+1 419 332 0590",
    "sg:postcode":"43420",
    "sg:province":"OH",
    "sg:tags":[
        "drinking"
    ],
    "wof:name":"Lillie Mae McKinstry",
    "wof:placetype":"venue"
},
  "geometry": {"coordinates":[-83.11259699999999,41.341999],"type":"Point"}
}