{
  "type": "Feature",
  "properties": {
    "addr:full": "512 Bidwell Ave Fremont OH 43420",
    "addr:housenumber": "512",
    "addr:postcode": "43420",
    "addr:street": "Bidwell Ave",
    "iso:country": "US",
    "sg:address": "512 Bidwell Ave",
    "sg:city": "Fremont",
    "sg:classifiers": [
      {
        "category": "Bars \u0026 Pubs",
        "type": "Food \u0026 Drink"
      }
    ],
    "sg:phone": "+1 419 332 0590",
    "sg:postcode": "43420",
    "sg:province": "OH",
    "sg:tags": [
      "drinking"
    ],
    "wof:name": "Lillie Mae McKinstry",
    "wof:placetype": "venue"
  },
  "geometry": {"coordinates":[-83.112597,41.341999],"type":"Point"}
}
