{
  "type": "Feature",
  "properties": {
    "addr:full":"3760 Boudinot Ave Cincinnati OH 45211",
    "addr:housenumber":"3760",
    "addr:postcode":"45211",
    "addr:street":"Boudinot Ave",
    "iso:country":"US",
    "sg:address":"3760 Boudinot Ave",
    "sg:city":"Cincinnati",
    "sg:classifiers":[
        {
            "category":"Professional",
            "subcategory":"Computer Services",
            "type":"Services"
        }
    ],
    "sg:phone":"+1 513 662 1666",
    "sg:postcode":"45211",
    "sg:province":"OH",
    "sg:tags":[
        "graphics"
    ],
    "sg:website":"www.madmacsgraphics.com",
    "wof:name":"Mad Macs",
    "wof:placetype":"venue"
},
  "geometry": {"coordinates":[-84.602468,39.157429],"type":"Point"}
}