{
  "type": "Feature",
  "properties": {
    "iso:country":"US",
    "sg:address":"415 N Walnut St",
    "sg:city":"Bucyrus",
    "sg:classifiers":[
        {
            "category":"Building & Trades",
            "subcategory":"Landscaping Services",
            "type":"Services"
        }
    ],
    "sg:phone":"+1 419 562 8418",
    "sg:postcode":"44820",
    "sg:province":"OH",
    "wof:name":"Asplundh Tree Expert Co",
    "wof:placetype":"venue"
},
  "geometry": {"coordinates":[-82.974244,40.812521],"type":"Point"}
}