{
  "type": "Feature",
  "properties": {
    "addr:full":"6545 Perimeter Dr Dublin OH 43016",
    "addr:housenumber":"6545",
    "addr:postcode":"43016",
    "addr:street":"Perimeter Dr",
    "iso:country":"US",
    "sg:address":"6545 Perimeter Dr",
    "sg:city":"Dublin",
    "sg:classifiers":[
        {
            "category":"Shopping",
            "subcategory":"Gifts & Souvenirs",
            "type":"Retail Goods"
        }
    ],
    "sg:phone":"+1 614 791 0060",
    "sg:postcode":"43016",
    "sg:province":"OH",
    "sg:tags":[
        "shop"
    ],
    "wof:name":"Tuesday Morning",
    "wof:placetype":"venue"
},
  "geometry": {"coordinates":[-83.16001199999999,40.10494],"type":"Point"}
}