{
  "type": "Feature",
  "properties": {
    "addr:full": "2546 Lorain Ave Cleveland OH 44113",
    "addr:housenumber": "2546",
    "addr:postcode": "44113",
    "addr:street": "Lorain Ave",
    "iso:country": "US",
    "sg:address": "2546 Lorain Ave",
    "sg:city": "Cleveland",
    "sg:classifiers": [
      {
        "category": "Government",
        "subcategory": "Police Station",
        "type": "Public Place"
      }
    ],
    "sg:phone": "+1 216 348 7114",
    "sg:postcode": "44113",
    "sg:province": "OH",
    "sg:tags": [
      "department"
    ],
    "wof:name": "Cleveland Police Dept",
    "wof:placetype": "venue"
  },
  "geometry": {"coordinates":[-81.704032,41.484014],"type":"Point"}
}
