{
  "type": "Feature",
  "properties": {
    "addr:full":"225 Lookout Dr Dayton OH 45419",
    "addr:housenumber":"225",
    "addr:postcode":"45419",
    "addr:street":"Lookout Dr",
    "iso:country":"US",
    "sg:address":"225 Lookout Dr",
    "sg:city":"Dayton",
    "sg:classifiers":[
        {
            "category":"Real Estate",
            "subcategory":"Real Estate Agent",
            "type":"Services"
        }
    ],
    "sg:phone":"+1 937 298 6853",
    "sg:postcode":"45419",
    "sg:province":"OH",
    "wof:name":"Alo Family Limited Partnership",
    "wof:placetype":"venue"
},
  "geometry": {"coordinates":[-84.170131,39.730245],"type":"Point"}
}