{
  "type": "Feature",
  "properties": {
    "iso:country":"US",
    "sg:address":"4400 N High St",
    "sg:city":"Columbus",
    "sg:classifiers":[
        {
            "category":"Building & Trades",
            "subcategory":"Construction",
            "type":"Services"
        }
    ],
    "sg:phone":"+1 614 784 4411",
    "sg:postcode":"43214",
    "sg:province":"OH",
    "sg:tags":[
        "paving",
        "surfacing",
        "contractor"
    ],
    "wof:name":"Big Daddys Paving",
    "wof:placetype":"venue"
},
  "geometry": {"coordinates":[-83.020019,40.05175],"type":"Point"}
}