{
  "type": "Feature",
  "properties": {
    "iso:country":"US",
    "sg:address":"1405 Cedar Point Rd",
    "sg:city":"Sandusky",
    "sg:classifiers":[
        {
            "category":"Real Estate",
            "subcategory":"Developer",
            "type":"Services"
        }
    ],
    "sg:phone":"+1 419 625 3754",
    "sg:postcode":"44870",
    "sg:province":"OH",
    "wof:name":"J S M Development",
    "wof:placetype":"venue"
},
  "geometry": {"coordinates":[-82.649237,41.452931],"type":"Point"}
}