{
  "type": "Feature",
  "properties": {
    "addr:full": "4225 Malsbary Rd Cincinnati OH 45242",
    "addr:housenumber": "4225",
    "addr:postcode": "45242",
    "addr:street": "Malsbary Rd",
    "iso:country": "US",
    "sg:address": "4225 Malsbary Rd",
    "sg:city": "Cincinnati",
    "sg:classifiers": [
      {
        "category": "Insurance",
        "subcategory": "Insurance Agent",
        "type": "Services"
      }
    ],
    "sg:phone": "+1 513 984 3100",
    "sg:postcode": "45242",
    "sg:province": "OH",
    "sg:tags": [
      "consultant",
      "financial",
      "investment"
    ],
    "sg:website": "http://www.langgroup.com",
    "wof:name": "Lang Financial Group Inc",
    "wof:placetype": "venue"
  },
  "geometry": {"coordinates":[-84.391167,39.240501],"type":"Point"}
}
