{
  "type": "Feature",
  "properties": {
    "addr:full": "5891 Red Winesap Way Dublin OH 43016",
    "addr:housenumber": "5891",
    "addr:postcode": "43016",
    "addr:street": "Red Winesap Way",
    "iso:country": "US",
    "sg:address": "5891 Red Winesap Way",
    "sg:city": "Dublin",
    "sg:classifiers": [
      {
        "category": "Professional",
        "type": "Services"
      }
    ],
    "sg:phone": "+1 614 876 8569",
    "sg:postcode": "43016",
    "sg:province": "OH",
    "sg:tags": [
      "establishment"
    ],
    "wof:name": "American Heartland Inc",
    "wof:placetype": "venue"
  },
  "geometry": {"coordinates":[-83.152317,40.072478],"type":"Point"}
}
