{
  "type": "Feature",
  "properties": {
    "addr:full": "105 2nd Ave Chesapeake OH 45619",
    "addr:housenumber": "105",
    "addr:postcode": "45619",
    "addr:street": "2Nd Ave",
    "iso:country": "US",
    "sg:address": "105 2nd Ave",
    "sg:city": "Chesapeake",
    "sg:classifiers": [
      {
        "category": "Shopping",
        "subcategory": "Bicycles \u0026 Sporting Goods",
        "type": "Retail Goods"
      }
    ],
    "sg:phone": "+1 740 867 3010",
    "sg:postcode": "45619",
    "sg:province": "OH",
    "wof:name": "Henson's Rod \u0026 Bow Shop",
    "wof:placetype": "venue"
  },
  "geometry": {"coordinates":[-82.451208,38.428106],"type":"Point"}
}
