{
  "type": "Feature",
  "properties": {
    "addr:full":"295 E State St Alliance OH 44601",
    "addr:housenumber":"295",
    "addr:postcode":"44601",
    "addr:street":"E State St",
    "iso:country":"US",
    "sg:address":"295 E State St",
    "sg:city":"Alliance",
    "sg:classifiers":[
        {
            "category":"Real Estate",
            "subcategory":"Real Estate Agent",
            "type":"Services"
        }
    ],
    "sg:phone":"+1 330 823 7733",
    "sg:postcode":"44601",
    "sg:province":"OH",
    "wof:name":"Courtney RE & Auctn Sls",
    "wof:placetype":"venue"
},
  "geometry": {"coordinates":[-81.102132,40.901614],"type":"Point"}
}