{
  "type": "Feature",
  "properties": {
    "iso:country":"US",
    "sg:address":"10280 Alliance Rd",
    "sg:city":"Cincinnati",
    "sg:classifiers":[
        {
            "category":"Manufacturing",
            "subcategory":"Tools & Machinery",
            "type":"Manufacturing & Wholesale Goods"
        }
    ],
    "sg:phone":"+1 513 984 8900",
    "sg:postcode":"45242",
    "sg:province":"OH",
    "sg:tags":[
        "detection",
        "radar",
        "mfg",
        "system",
        "equipment"
    ],
    "sg:website":"www.valentine1.com",
    "wof:name":"Valentine Research Inc",
    "wof:placetype":"venue"
},
  "geometry": {"coordinates":[-84.380477,39.245399],"type":"Point"}
}