{
  "type": "Feature",
  "properties": {
    "addr:full":"116 W Sawmill Rd Findlay OH 45840",
    "addr:housenumber":"116",
    "addr:postcode":"45840",
    "addr:street":"W Sawmill Rd",
    "iso:country":"US",
    "sg:address":"116 W Sawmill Rd",
    "sg:city":"Findlay",
    "sg:classifiers":[
        {
            "category":"Professional",
            "type":"Services"
        }
    ],
    "sg:phone":"+1 419 424 4065",
    "sg:postcode":"45840",
    "sg:province":"OH",
    "wof:name":"Michelle R McComas",
    "wof:placetype":"venue"
},
  "geometry": {"coordinates":[-83.624928,41.038049],"type":"Point"}
}