{
  "type": "Feature",
  "properties": {
    "addr:full":"2209 Richland Mall Mansfield OH 44906",
    "addr:housenumber":"2209",
    "addr:postcode":"44906",
    "addr:street":"Richland Mall",
    "iso:country":"US",
    "sg:address":"2209 Richland Mall",
    "sg:city":"Mansfield",
    "sg:classifiers":[
        {
            "category":"Shopping",
            "type":"Retail Goods"
        }
    ],
    "sg:phone":"+1 419 528 0067",
    "sg:postcode":"44906",
    "sg:province":"OH",
    "sg:tags":[
        "merchandise"
    ],
    "wof:name":"Cherry Hill Photo",
    "wof:placetype":"venue"
},
  "geometry": {"coordinates":[-82.593734,40.772532],"type":"Point"}
}