{
  "type": "Feature",
  "properties": {
    "addr:full": "9730 Montgomery Rd Cincinnati OH 45242",
    "addr:housenumber": "9730",
    "addr:postcode": "45242",
    "addr:street": "Montgomery Rd",
    "iso:country": "US",
    "sg:address": "9730 Montgomery Rd",
    "sg:city": "Cincinnati",
    "sg:classifiers": [
      {
        "category": "Professional",
        "subcategory": "Management \u0026 Consulting",
        "type": "Services"
      }
    ],
    "sg:phone": "+1 513 984 9333",
    "sg:postcode": "45242",
    "sg:province": "OH",
    "sg:tags": [
      "european"
    ],
    "wof:name": "GTC Bake House",
    "wof:placetype": "venue"
  },
  "geometry": {"coordinates":[-84.352243,39.231544],"type":"Point"}
}
