{
  "type": "Feature",
  "properties": {
    "addr:full": "2488 Shoup Dr Orrville OH 44667",
    "addr:housenumber": "2488",
    "addr:postcode": "44667",
    "addr:street": "Shoup Dr",
    "iso:country": "US",
    "sg:address": "2488 Shoup Dr",
    "sg:city": "Orrville",
    "sg:classifiers": [
      {
        "category": "Wholesale",
        "subcategory": "Groceries",
        "type": "Manufacturing \u0026 Wholesale Goods"
      }
    ],
    "sg:phone": "+1 330 683 6701",
    "sg:postcode": "44667",
    "sg:province": "OH",
    "sg:tags": [
      "confectionery"
    ],
    "wof:name": "Thomas A Androsac",
    "wof:placetype": "venue"
  },
  "geometry": {"coordinates":[-81.78956,40.830359],"type":"Point"}
}
