{
  "type": "Feature",
  "properties": {
    "addr:full": "1685 E Cherry St Youngstown OH 44506",
    "addr:housenumber": "1685",
    "addr:postcode": "44506",
    "addr:street": "E Cherry St",
    "iso:country": "US",
    "sg:address": "1685 E Cherry St",
    "sg:city": "Youngstown",
    "sg:classifiers": [
      {
        "category": "Autos \u0026 Motor Vehicles",
        "subcategory": "Automobile Sales",
        "type": "Retail Goods"
      }
    ],
    "sg:phone": "+1 330 744 2518",
    "sg:postcode": "44506",
    "sg:province": "OH",
    "sg:tags": [
      "used",
      "supply"
    ],
    "wof:name": "Tippers-Tipron Auto Used Cars",
    "wof:placetype": "venue"
  },
  "geometry": {"coordinates":[-80.620273,41.083127],"type":"Point"}
}
