{
  "type": "Feature",
  "properties": {
    "iso:country":"US",
    "sg:address":"1685 E Cherry St",
    "sg:city":"Youngstown",
    "sg:classifiers":[
        {
            "category":"Autos & Motor Vehicles",
            "subcategory":"Automobile Sales",
            "type":"Retail Goods"
        }
    ],
    "sg:phone":"+1 330 744 2518",
    "sg:postcode":"44506",
    "sg:province":"OH",
    "sg:tags":[
        "used",
        "supply"
    ],
    "wof:name":"Tippers-Tipron Auto Used Cars",
    "wof:placetype":"venue"
},
  "geometry": {"coordinates":[-80.620273,41.083127],"type":"Point"}
}