{
  "type": "Feature",
  "properties": {
    "iso:country":"US",
    "sg:address":"373 S High St",
    "sg:city":"Columbus",
    "sg:classifiers":[
        {
            "category":"Government",
            "subcategory":"Office",
            "type":"Public Place"
        }
    ],
    "sg:phone":"+1 614 462 4023",
    "sg:postcode":"43215",
    "sg:province":"OH",
    "wof:name":"10th Appellate District",
    "wof:placetype":"venue"
},
  "geometry": {"coordinates":[-82.99908000000001,39.953836],"type":"Point"}
}