{
  "type": "Feature",
  "properties": {
    "addr:full": "5156 State Rte 122 Franklin OH 45005",
    "addr:housenumber": "5156",
    "addr:postcode": "45005",
    "addr:street": "State Rte 122",
    "iso:country": "US",
    "sg:address": "5156 State Rte 122",
    "sg:city": "Franklin",
    "sg:classifiers": [
      {
        "category": "Building \u0026 Trades",
        "subcategory": "Construction",
        "type": "Services"
      }
    ],
    "sg:phone": "+1 513 422 5815",
    "sg:postcode": "45005",
    "sg:province": "OH",
    "sg:tags": [
      "house"
    ],
    "wof:name": "James A Wilson",
    "wof:placetype": "venue"
  },
  "geometry": {"coordinates":[-84.30194,39.493736],"type":"Point"}
}
