{
  "type": "Feature",
  "properties": {
    "addr:full":"3236 Ormond Rd Cleveland OH 44118",
    "addr:housenumber":"3236",
    "addr:postcode":"44118",
    "addr:street":"Ormond Rd",
    "iso:country":"US",
    "sg:address":"3236 Ormond Rd",
    "sg:city":"Cleveland",
    "sg:classifiers":[
        {
            "category":"Organizations",
            "subcategory":"Religious Organization",
            "type":"Services"
        }
    ],
    "sg:phone":"+1 216 321 8283",
    "sg:postcode":"44118",
    "sg:province":"OH",
    "sg:tags":[
        "clergy"
    ],
    "wof:name":"Robert W Haring",
    "wof:placetype":"venue"
},
  "geometry": {"coordinates":[-81.55707099999999,41.495101],"type":"Point"}
}