{
  "type": "Feature",
  "properties": {
    "addr:full":"1277 Maple Ave Zanesville OH 43701",
    "addr:housenumber":"1277",
    "addr:postcode":"43701",
    "addr:street":"Maple Ave",
    "iso:country":"US",
    "sg:address":"1277 Maple Ave",
    "sg:city":"Zanesville",
    "sg:classifiers":[
        {
            "category":"Insurance",
            "subcategory":"Insurance Agent",
            "type":"Services"
        }
    ],
    "sg:phone":"+1 740 455 2126",
    "sg:postcode":"43701",
    "sg:province":"OH",
    "wof:name":"Allstate Insurance Co",
    "wof:placetype":"venue"
},
  "geometry": {"coordinates":[-82.010666,39.954602],"type":"Point"}
}