{
  "type": "Feature",
  "properties": {
    "iso:country":"US",
    "sg:address":"126 N Main Ave",
    "sg:city":"Sidney",
    "sg:classifiers":[
        {
            "category":"Local Transit",
            "type":"Transportation"
        }
    ],
    "sg:phone":"+1 937 492 9858",
    "sg:postcode":"45365",
    "sg:province":"OH",
    "sg:tags":[
        "passenger"
    ],
    "wof:name":"Tk2 Limousine",
    "wof:placetype":"venue"
},
  "geometry": {"coordinates":[-84.15504199999999,40.286535],"type":"Point"}
}