{
  "type": "Feature",
  "properties": {
    "addr:full":"112 Koneta St Wapakoneta OH 45895",
    "addr:housenumber":"112",
    "addr:postcode":"45895",
    "addr:street":"Koneta St",
    "iso:country":"US",
    "sg:address":"112 Koneta St",
    "sg:city":"Wapakoneta",
    "sg:classifiers":[
        {
            "category":"Freight",
            "type":"Transportation"
        }
    ],
    "sg:phone":"+1 419 738 2706",
    "sg:postcode":"45895",
    "sg:province":"OH",
    "sg:tags":[
        "commercial",
        "storage"
    ],
    "wof:name":"Koneta Stor & More",
    "wof:placetype":"venue"
},
  "geometry": {"coordinates":[-84.195352,40.556622],"type":"Point"}
}