{
  "type": "Feature",
  "properties": {
    "iso:country":"US",
    "sg:address":"455 W Main St",
    "sg:city":"Conneaut",
    "sg:classifiers":[
        {
            "category":"Real Estate",
            "subcategory":"Real Estate Operator",
            "type":"Services"
        }
    ],
    "sg:phone":"+1 440 593 6200",
    "sg:postcode":"44030",
    "sg:province":"OH",
    "sg:tags":[
        "apartment"
    ],
    "wof:name":"Sunset West Apartments",
    "wof:placetype":"venue"
},
  "geometry": {"coordinates":[-80.609266,41.92835],"type":"Point"}
}