{
  "type": "Feature",
  "properties": {
    "addr:full":"18100 Jefferson Park Rd Cleveland OH 44130",
    "addr:housenumber":"18100",
    "addr:postcode":"44130",
    "addr:street":"Jefferson Park Rd",
    "iso:country":"US",
    "sg:address":"18100 Jefferson Park Rd",
    "sg:city":"Cleveland",
    "sg:classifiers":[
        {
            "category":"Professional",
            "subcategory":"Management & Consulting",
            "type":"Services"
        }
    ],
    "sg:phone":"+1 440 239 0847",
    "sg:postcode":"44130",
    "sg:province":"OH",
    "sg:tags":[
        "retail",
        "direct",
        "sales"
    ],
    "wof:name":"Colorado Prime Foods",
    "wof:placetype":"venue"
},
  "geometry": {"coordinates":[-81.825683,41.376158],"type":"Point"}
}