{
  "type": "Feature",
  "properties": {
    "addr:full": "233 Witte St Lancaster OH 43130",
    "addr:housenumber": "233",
    "addr:postcode": "43130",
    "addr:street": "Witte St",
    "iso:country": "US",
    "sg:address": "233 Witte St",
    "sg:city": "Lancaster",
    "sg:classifiers": [
      {
        "category": "Autos \u0026 Motor Vehicles",
        "subcategory": "Auto Supplies",
        "type": "Retail Goods"
      }
    ],
    "sg:phone": "+1 740 654 2035",
    "sg:postcode": "43130",
    "sg:province": "OH",
    "wof:name": "B \u0026 S Auto Parts Inc",
    "wof:placetype": "venue"
  },
  "geometry": {"coordinates":[-82.614128,39.709632],"type":"Point"}
}
