{
  "type": "Feature",
  "properties": {
    "iso:country":"US",
    "sg:address":"233 Witte St",
    "sg:city":"Lancaster",
    "sg:classifiers":[
        {
            "category":"Autos & Motor Vehicles",
            "subcategory":"Auto Supplies",
            "type":"Retail Goods"
        }
    ],
    "sg:phone":"+1 740 654 2035",
    "sg:postcode":"43130",
    "sg:province":"OH",
    "wof:name":"B & S Auto Parts Inc",
    "wof:placetype":"venue"
},
  "geometry": {"coordinates":[-82.61412799999999,39.709632],"type":"Point"}
}