{
  "type": "Feature",
  "properties": {
    "addr:full":"6625 Reflections Dr Dublin OH 43017",
    "addr:postcode":"6625;43017",
    "addr:street":"Reflections Dr",
    "iso:country":"US",
    "sg:address":"6625 Reflections Dr",
    "sg:city":"Dublin",
    "sg:classifiers":[
        {
            "category":"Professional",
            "subcategory":"Art Services",
            "type":"Services"
        }
    ],
    "sg:phone":"+1 614 652 2025",
    "sg:postcode":"43017",
    "sg:province":"OH",
    "sg:tags":[
        "photography",
        "printing",
        "commercial"
    ],
    "sg:website":"www.eclipse-studio.com",
    "wof:name":"Eclipse Studios Inc",
    "wof:placetype":"venue"
},
  "geometry": {"coordinates":[-83.088202,40.090994],"type":"Point"}
}