{
  "type": "Feature",
  "properties": {
    "addr:full":"49035 Old Hopedale Rd Hopedale OH 43976",
    "addr:housenumber":"49035",
    "addr:postcode":"43976",
    "addr:street":"Old Hopedale Rd",
    "iso:country":"US",
    "sg:address":"49035 Old Hopedale Rd",
    "sg:city":"Hopedale",
    "sg:classifiers":[
        {
            "category":"Building & Trades",
            "subcategory":"Construction",
            "type":"Services"
        }
    ],
    "sg:phone":"+1 740 937 2324",
    "sg:postcode":"43976",
    "sg:province":"OH",
    "sg:tags":[
        "excavating",
        "contractor"
    ],
    "wof:name":"Hare Excavating & Blacktopping",
    "wof:placetype":"venue"
},
  "geometry": {"coordinates":[-80.89255199999999,40.325714],"type":"Point"}
}