{
  "type": "Feature",
  "properties": {
    "iso:country":"US",
    "sg:address":"1600 Market Place Dr",
    "sg:city":"Maumee",
    "sg:classifiers":[
        {
            "category":"Recreation",
            "type":"Entertainment"
        }
    ],
    "sg:phone":"+1 419 897 9464",
    "sg:postcode":"43537",
    "sg:province":"OH",
    "sg:tags":[
        "sporting"
    ],
    "sg:website":"www.maumeesportsmall.com",
    "wof:name":"Maumee Sports Mall",
    "wof:placetype":"venue"
},
  "geometry": {"coordinates":[-83.661009,41.588024],"type":"Point"}
}