{
  "type": "Feature",
  "properties": {
    "iso:country":"US",
    "sg:address":"2479 S Green Rd",
    "sg:city":"Cleveland",
    "sg:classifiers":[
        {
            "category":"Organizations",
            "subcategory":"Religious Organization",
            "type":"Services"
        }
    ],
    "sg:phone":"+1 216 381 1922",
    "sg:postcode":"44122",
    "sg:province":"OH",
    "sg:tags":[
        "clergy"
    ],
    "wof:name":"Leib Alesvsky",
    "wof:placetype":"venue"
},
  "geometry": {"coordinates":[-81.516976,41.491158],"type":"Point"}
}