{
  "type": "Feature",
  "properties": {
    "addr:full": "9278 Arena Dr Rossford OH 43460",
    "addr:housenumber": "9278",
    "addr:postcode": "43460",
    "addr:street": "Arena Dr",
    "iso:country": "US",
    "sg:address": "9278 Arena Dr",
    "sg:city": "Rossford",
    "sg:classifiers": [
      {
        "category": "Organizations",
        "subcategory": "Labor Organization",
        "type": "Services"
      }
    ],
    "sg:phone": "+1 419 893 3089",
    "sg:postcode": "43460",
    "sg:province": "OH",
    "wof:name": "Council of Carpenters",
    "wof:placetype": "venue"
  },
  "geometry": {"coordinates":[-83.573726,41.557514],"type":"Point"}
}
