{
  "type": "Feature",
  "properties": {
    "addr:full":"2888 Bixby Rd Groveport OH 43125",
    "addr:housenumber":"2888",
    "addr:postcode":"43125",
    "addr:street":"Bixby Rd",
    "iso:country":"US",
    "sg:address":"2888 Bixby Rd",
    "sg:city":"Groveport",
    "sg:classifiers":[
        {
            "category":"Bars & Pubs",
            "type":"Food & Drink"
        }
    ],
    "sg:phone":"+1 614 497 9039",
    "sg:postcode":"43125",
    "sg:province":"OH",
    "sg:tags":[
        "drinking"
    ],
    "wof:name":"Mavericks Bar & Grill",
    "wof:placetype":"venue"
},
  "geometry": {"coordinates":[-82.927004,39.862038],"type":"Point"}
}