{
  "type": "Feature",
  "properties": {
    "addr:full": "28 E Liberty St Girard OH 44420",
    "addr:housenumber": "28",
    "addr:postcode": "44420",
    "addr:street": "E Liberty St",
    "iso:country": "US",
    "sg:address": "28 E Liberty St",
    "sg:city": "Girard",
    "sg:classifiers": [
      {
        "category": "Manufacturing",
        "subcategory": "Printing",
        "type": "Manufacturing \u0026 Wholesale Goods"
      }
    ],
    "sg:phone": "+1 330 545 5533",
    "sg:postcode": "44420",
    "sg:province": "OH",
    "sg:tags": [
      "commercial"
    ],
    "wof:name": "Girard Printing Co",
    "wof:placetype": "venue"
  },
  "geometry": {"coordinates":[-80.698994,41.154118],"type":"Point"}
}
