{
  "type": "Feature",
  "properties": {
    "iso:country":"US",
    "sg:address":"4460 Mayfield Rd",
    "sg:city":"Cleveland",
    "sg:classifiers":[
        {
            "category":"Shopping",
            "subcategory":"Pharmacy",
            "type":"Retail Goods"
        }
    ],
    "sg:phone":"+1 216 382 6780",
    "sg:postcode":"44121",
    "sg:province":"OH",
    "sg:website":"www.cvs.com",
    "wof:name":"CVS Pharmacy",
    "wof:placetype":"venue"
},
  "geometry": {"coordinates":[-81.517499,41.519843],"type":"Point"}
}