{
  "type": "Feature",
  "properties": {
    "iso:country":"US",
    "sg:address":"808 E Cooke Rd",
    "sg:city":"Columbus",
    "sg:classifiers":[
        {
            "category":"Freight",
            "type":"Transportation"
        }
    ],
    "sg:phone":"+1 614 268 9400",
    "sg:postcode":"43214",
    "sg:province":"OH",
    "sg:tags":[
        "commercial",
        "storage",
        "special",
        "general"
    ],
    "wof:name":"Storage USA",
    "wof:placetype":"venue"
},
  "geometry": {"coordinates":[-82.99839900000001,40.048344],"type":"Point"}
}