{
  "type": "Feature",
  "properties": {
    "iso:country":"US",
    "sg:address":"4272 Armstrong Blvd",
    "sg:city":"Batavia",
    "sg:classifiers":[
        {
            "category":"Wholesale",
            "subcategory":"Medical Equipment & Supplies",
            "type":"Manufacturing & Wholesale Goods"
        }
    ],
    "sg:phone":"+1 513 732 3400",
    "sg:postcode":"45103",
    "sg:province":"OH",
    "sg:tags":[
        "optical"
    ],
    "wof:name":"Edward H Schmidt & Sons Of Oh",
    "wof:placetype":"venue"
},
  "geometry": {"coordinates":[-84.217315,39.084697],"type":"Point"}
}