{
  "type": "Feature",
  "properties": {
    "addr:full": "4272 Armstrong Blvd Batavia OH 45103",
    "addr:housenumber": "4272",
    "addr:postcode": "45103",
    "addr:street": "Armstrong Blvd",
    "iso:country": "US",
    "sg:address": "4272 Armstrong Blvd",
    "sg:city": "Batavia",
    "sg:classifiers": [
      {
        "category": "Wholesale",
        "subcategory": "Medical Equipment \u0026 Supplies",
        "type": "Manufacturing \u0026 Wholesale Goods"
      }
    ],
    "sg:phone": "+1 513 732 3400",
    "sg:postcode": "45103",
    "sg:province": "OH",
    "sg:tags": [
      "optical"
    ],
    "wof:name": "Edward H Schmidt \u0026 Sons Of Oh",
    "wof:placetype": "venue"
  },
  "geometry": {"coordinates":[-84.217315,39.084697],"type":"Point"}
}
