{
  "type": "Feature",
  "properties": {
    "iso:country":"US",
    "sg:address":"9387 S Old State Rd",
    "sg:city":"Lewis Center",
    "sg:classifiers":[
        {
            "category":"Banks & Credit Unions",
            "subcategory":"Bank",
            "type":"Services"
        }
    ],
    "sg:phone":"+1 614 880 5464",
    "sg:postcode":"43081",
    "sg:province":"OH",
    "sg:tags":[
        "loan",
        "real estate"
    ],
    "wof:name":"King Capital",
    "wof:placetype":"venue"
},
  "geometry": {"coordinates":[-82.999201,40.14629],"type":"Point"}
}