{
  "type": "Feature",
  "properties": {
    "addr:full": "7780 Northfield Rd Cleveland OH 44146",
    "addr:housenumber": "7780",
    "addr:postcode": "44146",
    "addr:street": "Northfield Rd",
    "iso:country": "US",
    "sg:address": "7780 Northfield Rd",
    "sg:city": "Cleveland",
    "sg:classifiers": [
      {
        "category": "Professional",
        "subcategory": "Business Services",
        "type": "Services"
      }
    ],
    "sg:phone": "+1 440 439 8353",
    "sg:postcode": "44146",
    "sg:province": "OH",
    "sg:tags": [
      "record",
      "document"
    ],
    "wof:name": "Medical Records Management",
    "wof:placetype": "venue"
  },
  "geometry": {"coordinates":[-81.526747,41.355034],"type":"Point"}
}
