{
  "type": "Feature",
  "properties": {
    "addr:full":"2031 Eckard Rd Centerburg OH 43011",
    "addr:housenumber":"2031",
    "addr:postcode":"43011",
    "addr:street":"Eckard Rd",
    "iso:country":"US",
    "sg:address":"2031 Eckard Rd",
    "sg:city":"Centerburg",
    "sg:classifiers":[
        {
            "category":"Professional",
            "subcategory":"Management & Consulting",
            "type":"Services"
        }
    ],
    "sg:phone":"+1 740 625 9930",
    "sg:postcode":"43011",
    "sg:province":"OH",
    "sg:tags":[
        "construction"
    ],
    "wof:name":"Amberika Mgt",
    "wof:placetype":"venue"
},
  "geometry": {"coordinates":[-82.726848,40.306202],"type":"Point"}
}