{
  "type": "Feature",
  "properties": {
    "iso:country":"US",
    "sg:address":"624 Harrisburg Pike",
    "sg:city":"Columbus",
    "sg:classifiers":[
        {
            "category":"Government",
            "subcategory":"Post Office",
            "type":"Public Place"
        }
    ],
    "sg:phone":"+1 614 228 1570",
    "sg:postcode":"43223",
    "sg:province":"OH",
    "sg:tags":[
        "postal",
        "us"
    ],
    "wof:name":"Central Point Station",
    "wof:placetype":"venue"
},
  "geometry": {"coordinates":[-83.036824,39.944349],"type":"Point"}
}