{
  "type": "Feature",
  "properties": {
    "iso:country":"US",
    "sg:address":"320 N Main St",
    "sg:city":"Cedarville",
    "sg:classifiers":[
        {
            "category":"Restaurant",
            "type":"Food & Drink"
        }
    ],
    "sg:phone":"+1 937 766 2046",
    "sg:postcode":"45314",
    "sg:province":"OH",
    "sg:tags":[
        "eating"
    ],
    "wof:name":"Mom & Dad's Dairy Bar",
    "wof:placetype":"venue"
},
  "geometry": {"coordinates":[-83.809085,39.748756],"type":"Point"}
}