{
  "type": "Feature",
  "properties": {
    "addr:full": "2470 Dunsworth Dr Columbus OH 43235",
    "addr:housenumber": "2470",
    "addr:postcode": "43235",
    "addr:street": "Dunsworth Dr",
    "iso:country": "US",
    "sg:address": "2470 Dunsworth Dr",
    "sg:city": "Columbus",
    "sg:classifiers": [
      {
        "category": "Retail",
        "subcategory": "Animal Services",
        "type": "Services"
      }
    ],
    "sg:phone": "+1 614 791 9392",
    "sg:postcode": "43235",
    "sg:province": "OH",
    "sg:tags": [
      "pet",
      "boarding",
      "sitting"
    ],
    "wof:name": "A \u0026 P Pet Sitting Service",
    "wof:placetype": "venue"
  },
  "geometry": {"coordinates":[-83.079571,40.112827],"type":"Point"}
}
