{
  "type": "Feature",
  "properties": {
    "addr:full": "9501 Colerain Ave Cincinnati OH 45251",
    "addr:housenumber": "9501",
    "addr:postcode": "45251",
    "addr:street": "Colerain Ave",
    "iso:country": "US",
    "sg:address": "9501 Colerain Ave",
    "sg:city": "Cincinnati",
    "sg:classifiers": [
      {
        "category": "Shopping",
        "subcategory": "Clothing, Apparel, \u0026 Fashions",
        "type": "Retail Goods"
      }
    ],
    "sg:phone": "+1 513 923 9323",
    "sg:postcode": "45251",
    "sg:province": "OH",
    "sg:website": "www.aeropostale.com",
    "wof:name": "Aeropostale Inc",
    "wof:placetype": "venue"
  },
  "geometry": {"coordinates":[-84.595047,39.243543],"type":"Point"}
}
