{
  "type": "Feature",
  "properties": {
    "iso:country":"US",
    "sg:address":"720 Wolf Ledges Pkwy",
    "sg:city":"Akron",
    "sg:classifiers":[
        {
            "category":"Organizations",
            "subcategory":"Labor Organization",
            "type":"Services"
        }
    ],
    "sg:phone":"+1 330 535 6913",
    "sg:postcode":"44311",
    "sg:province":"OH",
    "wof:name":"International Association-Brdg",
    "wof:placetype":"venue"
},
  "geometry": {"coordinates":[-81.520556,41.065318],"type":"Point"}
}