{
  "type": "Feature",
  "properties": {
    "iso:country":"US",
    "sg:address":"3374 Schneiders Crossing Rd NW",
    "sg:city":"Dover",
    "sg:classifiers":[
        {
            "category":"Organizations",
            "subcategory":"Religious Organization",
            "type":"Services"
        }
    ],
    "sg:phone":"+1 330 343 7980",
    "sg:postcode":"44622",
    "sg:province":"OH",
    "sg:tags":[
        "church"
    ],
    "wof:name":"Church Of New Hope",
    "wof:placetype":"venue"
},
  "geometry": {"coordinates":[-81.52032,40.5496],"type":"Point"}
}