{
  "type": "Feature",
  "properties": {
    "iso:country":"US",
    "sg:address":"7917 State Rte 60",
    "sg:city":"Wakeman",
    "sg:classifiers":[
        {
            "category":"Shopping",
            "subcategory":"Gifts & Souvenirs",
            "type":"Retail Goods"
        }
    ],
    "sg:phone":"+1 440 965 8858",
    "sg:postcode":"44889",
    "sg:province":"OH",
    "wof:name":"Gathered Gifts",
    "wof:placetype":"venue"
},
  "geometry": {"coordinates":[-82.364069,41.319148],"type":"Point"}
}