{
  "type": "Feature",
  "properties": {
    "addr:full": "7917 State Rte 60 Wakeman OH 44889",
    "addr:housenumber": "7917",
    "addr:postcode": "44889",
    "addr:street": "State Rte 60",
    "iso:country": "US",
    "sg:address": "7917 State Rte 60",
    "sg:city": "Wakeman",
    "sg:classifiers": [
      {
        "category": "Shopping",
        "subcategory": "Gifts \u0026 Souvenirs",
        "type": "Retail Goods"
      }
    ],
    "sg:phone": "+1 440 965 8858",
    "sg:postcode": "44889",
    "sg:province": "OH",
    "wof:name": "Gathered Gifts",
    "wof:placetype": "venue"
  },
  "geometry": {"coordinates":[-82.364069,41.319148],"type":"Point"}
}
