{
  "type": "Feature",
  "properties": {
    "addr:full": "4931 Lauderdale Dr Dayton OH 45439",
    "addr:housenumber": "4931",
    "addr:postcode": "45439",
    "addr:street": "Lauderdale Dr",
    "iso:country": "US",
    "sg:address": "4931 Lauderdale Dr",
    "sg:city": "Dayton",
    "sg:classifiers": [
      {
        "category": "Building \u0026 Trades",
        "subcategory": "Construction",
        "type": "Services"
      }
    ],
    "sg:phone": "+1 937 672 8910",
    "sg:postcode": "45439",
    "sg:province": "OH",
    "sg:tags": [
      "painting"
    ],
    "wof:name": "Stomoff Painting Company",
    "wof:placetype": "venue"
  },
  "geometry": {"coordinates":[-84.218753,39.685278],"type":"Point"}
}
