{
  "type": "Feature",
  "properties": {
    "addr:full": "8262 Columbia Rd Cleveland OH 44138",
    "addr:housenumber": "8262",
    "addr:postcode": "44138",
    "addr:street": "Columbia Rd",
    "iso:country": "US",
    "sg:address": "8262 Columbia Rd",
    "sg:city": "Cleveland",
    "sg:classifiers": [
      {
        "category": "Education",
        "subcategory": "School",
        "type": "Public Place"
      }
    ],
    "sg:phone": "+1 440 235 4580",
    "sg:postcode": "44138",
    "sg:province": "OH",
    "wof:name": "St Mary of The Falls School",
    "wof:placetype": "venue"
  },
  "geometry": {"coordinates":[-81.902244,41.37056],"type":"Point"}
}
