{
  "type": "Feature",
  "properties": {
    "addr:full": "2565 State Rte 46 N Jefferson OH 44047",
    "addr:housenumber": "2565",
    "addr:postcode": "44047",
    "addr:street": "State Rte 46 N",
    "iso:country": "US",
    "sg:address": "2565 State Rte 46 N",
    "sg:city": "Jefferson",
    "sg:classifiers": [
      {
        "category": "Building \u0026 Trades",
        "subcategory": "Electrical",
        "type": "Services"
      }
    ],
    "sg:phone": "+1 440 998 2641",
    "sg:postcode": "44047",
    "sg:province": "OH",
    "sg:tags": [
      "electric",
      "contractor"
    ],
    "wof:name": "Cole's Electric Svc",
    "wof:placetype": "venue"
  },
  "geometry": {"coordinates":[-80.764092,41.800226],"type":"Point"}
}
