{
  "type": "Feature",
  "properties": {
    "addr:full":"4753 Camden College Corner Rd Camden OH 45311",
    "addr:housenumber":"4753",
    "addr:postcode":"45311",
    "addr:street":"Camden College Corner Rd",
    "iso:country":"US",
    "sg:address":"4753 Camden College Corner Rd",
    "sg:city":"Camden",
    "sg:classifiers":[
        {
            "category":"Farming",
            "subcategory":"Farm",
            "type":"Manufacturing & Wholesale Goods"
        }
    ],
    "sg:phone":"+1 513 796 2034",
    "sg:postcode":"45311",
    "sg:province":"OH",
    "sg:tags":[
        "crop",
        "general"
    ],
    "wof:name":"Larry G Black",
    "wof:placetype":"venue"
},
  "geometry": {"coordinates":[-84.723429,39.603891],"type":"Point"}
}