{
  "type": "Feature",
  "properties": {
    "addr:full": "2900 Columbus Ave Sandusky OH 44870",
    "addr:housenumber": "2900",
    "addr:postcode": "44870",
    "addr:street": "Columbus Ave",
    "iso:country": "US",
    "sg:address": "2900 Columbus Ave",
    "sg:city": "Sandusky",
    "sg:classifiers": [
      {
        "category": "Government",
        "subcategory": "Office",
        "type": "Public Place"
      }
    ],
    "sg:phone": "+1 419 627 7682",
    "sg:postcode": "44870",
    "sg:province": "OH",
    "wof:name": "County Of Erie",
    "wof:placetype": "venue"
  },
  "geometry": {"coordinates":[-82.694407,41.426797],"type":"Point"}
}
