{
  "type": "Feature",
  "properties": {
    "addr:full": "5480 Creek Rd Cincinnati OH 45242",
    "addr:housenumber": "5480",
    "addr:postcode": "45242",
    "addr:street": "Creek Rd",
    "iso:country": "US",
    "sg:address": "5480 Creek Rd",
    "sg:city": "Cincinnati",
    "sg:classifiers": [
      {
        "category": "Manufacturing",
        "subcategory": "Printing",
        "type": "Manufacturing \u0026 Wholesale Goods"
      }
    ],
    "sg:phone": "+1 513 459 0059",
    "sg:postcode": "45242",
    "sg:province": "OH",
    "sg:tags": [
      "printer"
    ],
    "wof:name": "Quality Press",
    "wof:placetype": "venue"
  },
  "geometry": {"coordinates":[-84.372718,39.258443],"type":"Point"}
}
