{
  "type": "Feature",
  "properties": {
    "addr:full":"351 Darst Rd Dayton OH 45440",
    "addr:housenumber":"351",
    "addr:postcode":"45440",
    "addr:street":"Darst Rd",
    "iso:country":"US",
    "sg:address":"351 Darst Rd",
    "sg:city":"Dayton",
    "sg:classifiers":[
        {
            "category":"Building & Trades",
            "subcategory":"Construction",
            "type":"Services"
        }
    ],
    "sg:phone":"+1 937 426 7229",
    "sg:postcode":"45440",
    "sg:province":"OH",
    "sg:tags":[
        "floor",
        "laying",
        "contractor"
    ],
    "wof:name":"Abrams Tile and Flooring",
    "wof:placetype":"venue"
},
  "geometry": {"coordinates":[-84.08576600000001,39.68707],"type":"Point"}
}