{
  "type": "Feature",
  "properties": {
    "iso:country":"US",
    "sg:address":"469 Albion Ave",
    "sg:city":"Cincinnati",
    "sg:classifiers":[
        {
            "category":"Health Services",
            "subcategory":"Nursing And Care Facility",
            "type":"Services"
        },
        {
            "category":"Social Services",
            "subcategory":"Adult Care",
            "type":"Services"
        }
    ],
    "sg:phone":"+1 513 771 2170",
    "sg:postcode":"45246",
    "sg:province":"OH",
    "sg:tags":[
        "home",
        "rest",
        "residential"
    ],
    "wof:name":"St Mary's Memorial Home",
    "wof:placetype":"venue"
},
  "geometry": {"coordinates":[-84.45325200000001,39.267503],"type":"Point"}
}