{
  "type": "Feature",
  "properties": {
    "addr:full":"243 S Prospect St Ravenna OH 44266",
    "addr:housenumber":"243",
    "addr:postcode":"44266",
    "addr:street":"S Prospect St",
    "iso:country":"US",
    "sg:address":"243 S Prospect St",
    "sg:city":"Ravenna",
    "sg:classifiers":[
        {
            "category":"Social Services",
            "subcategory":"Child Care",
            "type":"Services"
        }
    ],
    "sg:phone":"+1 330 297 2257",
    "sg:postcode":"44266",
    "sg:province":"OH",
    "sg:tags":[
        "kindergarten",
        "academic",
        "school"
    ],
    "wof:name":"Even Start",
    "wof:placetype":"venue"
},
  "geometry": {"coordinates":[-81.24153699999999,41.155958],"type":"Point"}
}