{
  "type": "Feature",
  "properties": {
    "iso:country":"US",
    "sg:address":"2470 Powell Rd",
    "sg:city":"Powell",
    "sg:phone":"+1 614 846 3396",
    "sg:postcode":"43065",
    "sg:province":"OH",
    "sg:website":"http://www.powderrm.com",
    "wof:name":"Powder Room Gun Shop & Target Range",
    "wof:placetype":"venue"
},
  "geometry": {"coordinates":[-83.120998,40.159529],"type":"Point"}
}