{
  "type": "Feature",
  "properties": {
    "addr:full": "6448 Gano Rd West Chester OH 45069",
    "addr:housenumber": "6448",
    "addr:postcode": "45069",
    "addr:street": "Gano Rd",
    "iso:country": "US",
    "sg:address": "6448 Gano Rd",
    "sg:city": "West Chester",
    "sg:phone": "+1 513 755 2111",
    "sg:postcode": "45069",
    "sg:province": "OH",
    "sg:tags": [
      "machine",
      "parts",
      "vending",
      "supply"
    ],
    "wof:name": "Vendor's Supply Of Ohio Inc",
    "wof:placetype": "venue"
  },
  "geometry": {"coordinates":[-84.411419,39.303242],"type":"Point"}
}
