{
  "type": "Feature",
  "properties": {
    "iso:country":"US",
    "sg:address":"6448 Gano Rd",
    "sg:city":"West Chester",
    "sg:phone":"+1 513 755 2111",
    "sg:postcode":"45069",
    "sg:province":"OH",
    "sg:tags":[
        "machine",
        "parts",
        "vending",
        "supply"
    ],
    "wof:name":"Vendor's Supply Of Ohio Inc",
    "wof:placetype":"venue"
},
  "geometry": {"coordinates":[-84.411419,39.303242],"type":"Point"}
}