{
  "type": "Feature",
  "properties": {
    "addr:full":"3740 Eastport Rd SE Dennison OH 44621",
    "addr:housenumber":"3740",
    "addr:postcode":"44621",
    "addr:street":"Eastport Rd Se",
    "iso:country":"US",
    "sg:address":"3740 Eastport Rd SE",
    "sg:city":"Dennison",
    "sg:classifiers":[
        {
            "category":"Retail",
            "subcategory":"Auto Repair",
            "type":"Services"
        }
    ],
    "sg:phone":"+1 740 922 3294",
    "sg:postcode":"44621",
    "sg:province":"OH",
    "sg:tags":[
        "repairing",
        "automobile"
    ],
    "wof:name":"L A Smart Alignment",
    "wof:placetype":"venue"
},
  "geometry": {"coordinates":[-81.3446,40.41329],"type":"Point"}
}