{
  "type": "Feature",
  "properties": {
    "iso:country":"US",
    "sg:address":"19 W Market St",
    "sg:city":"Tiffin",
    "sg:classifiers":[
        {
            "category":"Insurance",
            "subcategory":"Insurance Agent",
            "type":"Services"
        }
    ],
    "sg:phone":"+1 419 447 9853",
    "sg:postcode":"44883",
    "sg:province":"OH",
    "wof:name":"Barbara Smith Agency",
    "wof:placetype":"venue"
},
  "geometry": {"coordinates":[-83.18124,41.11406],"type":"Point"}
}