{
  "type": "Feature",
  "properties": {
    "iso:country":"US",
    "sg:address":"519 N Broad St",
    "sg:city":"Canfield",
    "sg:classifiers":[
        {
            "category":"Building & Trades",
            "subcategory":"Construction",
            "type":"Services"
        }
    ],
    "sg:phone":"+1 330 533 3315",
    "sg:postcode":"44406",
    "sg:province":"OH",
    "sg:tags":[
        "marking",
        "maintenance",
        "parking"
    ],
    "wof:name":"Canfield Street Dept",
    "wof:placetype":"venue"
},
  "geometry": {"coordinates":[-80.76056800000001,41.039891],"type":"Point"}
}