{
  "type": "Feature",
  "properties": {
    "iso:country":"US",
    "sg:address":"7444 Jager Ct",
    "sg:city":"Cincinnati",
    "sg:phone":"+1 513 271 1460",
    "sg:postcode":"45230",
    "sg:province":"OH",
    "sg:tags":[
        "wholesale",
        "gas",
        "natural",
        "liquid"
    ],
    "wof:name":"Rich Energy Inc",
    "wof:placetype":"venue"
},
  "geometry": {"coordinates":[-84.35144699999999,39.066597],"type":"Point"}
}