{
  "type": "Feature",
  "properties": {
    "iso:country":"US",
    "sg:address":"8075 Reading Rd",
    "sg:city":"Cincinnati",
    "sg:classifiers":[
        {
            "category":"Building & Trades",
            "subcategory":"Cleaning & Sanitation",
            "type":"Services"
        }
    ],
    "sg:phone":"+1 513 761 5615",
    "sg:postcode":"45237",
    "sg:province":"OH",
    "sg:tags":[
        "janitor"
    ],
    "sg:website":"www.callmapp.com",
    "wof:name":"Mapp Building Svc Inc",
    "wof:placetype":"venue"
},
  "geometry": {"coordinates":[-84.451672,39.206461],"type":"Point"}
}