{
  "type": "Feature",
  "properties": {
    "iso:country":"US",
    "sg:address":"664 Ridgeway Dr",
    "sg:city":"Sidney",
    "sg:classifiers":[
        {
            "category":"Professional",
            "subcategory":"Art Services",
            "type":"Services"
        }
    ],
    "sg:phone":"+1 937 497 1507",
    "sg:postcode":"45365",
    "sg:province":"OH",
    "sg:tags":[
        "photographer"
    ],
    "wof:name":"Russ Moore Photography",
    "wof:placetype":"venue"
},
  "geometry": {"coordinates":[-84.163839,40.271037],"type":"Point"}
}