{
  "type": "Feature",
  "properties": {
    "addr:full": "41 N Main St Chagrin Falls OH 44022",
    "addr:housenumber": "41",
    "addr:postcode": "44022",
    "addr:street": "N Main St",
    "iso:country": "US",
    "sg:address": "41 N Main St",
    "sg:city": "Chagrin Falls",
    "sg:classifiers": [
      {
        "category": "Food \u0026 Beverages",
        "subcategory": "Candy",
        "type": "Retail Goods"
      }
    ],
    "sg:phone": "+1 440 247 0624",
    "sg:postcode": "44022",
    "sg:province": "OH",
    "sg:tags": [
      "confectionery"
    ],
    "wof:name": "T C Wolf Chocolate",
    "wof:placetype": "venue"
  },
  "geometry": {"coordinates":[-81.391852,41.430917],"type":"Point"}
}
