{
  "type": "Feature",
  "properties": {
    "iso:country":"US",
    "sg:address":"230 W Huron Rd",
    "sg:city":"Cleveland",
    "sg:classifiers":[
        {
            "category":"Shopping",
            "subcategory":"Beauty & Cosmetics",
            "type":"Retail Goods"
        },
        {
            "category":"Personal",
            "subcategory":"Beauty Salon",
            "type":"Services"
        }
    ],
    "sg:phone":"+1 216 696 0285",
    "sg:postcode":"44113",
    "sg:province":"OH",
    "sg:tags":[
        "miscellaneous",
        "store"
    ],
    "wof:name":"Trade Secret",
    "wof:placetype":"venue"
},
  "geometry": {"coordinates":[-81.694536,41.496868],"type":"Point"}
}