{
  "type": "Feature",
  "properties": {
    "addr:full": "2731 Apple Creek Rd Wooster OH 44691",
    "addr:housenumber": "2731",
    "addr:postcode": "44691",
    "addr:street": "Apple Creek Rd",
    "iso:country": "US",
    "sg:address": "2731 Apple Creek Rd",
    "sg:city": "Wooster",
    "sg:classifiers": [
      {
        "category": "Retail",
        "subcategory": "Repair Shop",
        "type": "Services"
      }
    ],
    "sg:phone": "+1 330 669 2814",
    "sg:postcode": "44691",
    "sg:province": "OH",
    "sg:tags": [
      "water",
      "equipment",
      "softening"
    ],
    "wof:name": "Aquatek Water Conditioning",
    "wof:placetype": "venue"
  },
  "geometry": {"coordinates":[-81.84232,40.834632],"type":"Point"}
}
