{
  "type": "Feature",
  "properties": {
    "addr:full": "830 Delaware Ave Marysville OH 43040",
    "addr:housenumber": "830",
    "addr:postcode": "43040",
    "addr:street": "Delaware Ave",
    "iso:country": "US",
    "sg:address": "830 Delaware Ave",
    "sg:city": "Marysville",
    "sg:classifiers": [
      {
        "category": "Utilities",
        "subcategory": "Mobile Phone",
        "type": "Services"
      }
    ],
    "sg:phone": "+1 937 644 1990",
    "sg:postcode": "43040",
    "sg:province": "OH",
    "sg:tags": [
      "telephone",
      "cellular"
    ],
    "wof:name": "Phone Store",
    "wof:placetype": "venue"
  },
  "geometry": {"coordinates":[-83.354962,40.236334],"type":"Point"}
}
