{
  "type": "Feature",
  "properties": {
    "iso:country":"US",
    "sg:address":"830 Delaware Ave",
    "sg:city":"Marysville",
    "sg:classifiers":[
        {
            "category":"Utilities",
            "subcategory":"Mobile Phone",
            "type":"Services"
        }
    ],
    "sg:phone":"+1 937 644 1990",
    "sg:postcode":"43040",
    "sg:province":"OH",
    "sg:tags":[
        "telephone",
        "cellular"
    ],
    "wof:name":"Phone Store",
    "wof:placetype":"venue"
},
  "geometry": {"coordinates":[-83.354962,40.236334],"type":"Point"}
}