{
  "type": "Feature",
  "properties": {
    "addr:full":"438 Patterson Rd Dayton OH 45419",
    "addr:housenumber":"438",
    "addr:postcode":"45419",
    "addr:street":"Patterson Rd",
    "iso:country":"US",
    "sg:address":"438 Patterson Rd",
    "sg:city":"Dayton",
    "sg:classifiers":[
        {
            "category":"Professional",
            "subcategory":"Lawyer & Legal Services",
            "type":"Services"
        }
    ],
    "sg:phone":"+1 937 298 0067",
    "sg:postcode":"45419",
    "sg:province":"OH",
    "sg:tags":[
        "attorney"
    ],
    "wof:name":"Suarez & Assoc",
    "wof:placetype":"venue"
},
  "geometry": {"coordinates":[-84.161008,39.724613],"type":"Point"}
}