{
  "type": "Feature",
  "properties": {
    "addr:full": "1017 Wooster Rd W Barberton OH 44203",
    "addr:housenumber": "1017",
    "addr:postcode": "44203",
    "addr:street": "Wooster Rd W",
    "iso:country": "US",
    "sg:address": "1017 Wooster Rd W",
    "sg:city": "Barberton",
    "sg:classifiers": [
      {
        "category": "Cinema",
        "subcategory": "Movie Theater",
        "type": "Entertainment"
      }
    ],
    "sg:phone": "+1 330 825 6912",
    "sg:postcode": "44203",
    "sg:province": "OH",
    "wof:name": "West Theatre",
    "wof:placetype": "venue"
  },
  "geometry": {"coordinates":[-81.626264,41.009924],"type":"Point"}
}
