{
  "type": "Feature",
  "properties": {
    "iso:country":"US",
    "sg:address":"1017 Wooster Rd W",
    "sg:city":"Barberton",
    "sg:classifiers":[
        {
            "category":"Cinema",
            "subcategory":"Movie Theater",
            "type":"Entertainment"
        }
    ],
    "sg:phone":"+1 330 825 6912",
    "sg:postcode":"44203",
    "sg:province":"OH",
    "wof:name":"West Theatre",
    "wof:placetype":"venue"
},
  "geometry": {"coordinates":[-81.62626400000001,41.009924],"type":"Point"}
}