{
  "type": "Feature",
  "properties": {
    "iso:country":"US",
    "sg:address":"2435 S Main St",
    "sg:city":"Findlay",
    "sg:classifiers":[
        {
            "category":"Cinema",
            "subcategory":"Movie Rental",
            "type":"Entertainment"
        }
    ],
    "sg:phone":"+1 419 422 9642",
    "sg:postcode":"45840",
    "sg:province":"OH",
    "sg:tags":[
        "video",
        "tape"
    ],
    "wof:name":"Blockbuster",
    "wof:placetype":"venue"
},
  "geometry": {"coordinates":[-83.650393,41.008502],"type":"Point"}
}