{
  "type": "Feature",
  "properties": {
    "addr:full": "2435 S Main St Findlay OH 45840",
    "addr:housenumber": "2435",
    "addr:postcode": "45840",
    "addr:street": "S Main St",
    "iso:country": "US",
    "sg:address": "2435 S Main St",
    "sg:city": "Findlay",
    "sg:classifiers": [
      {
        "category": "Cinema",
        "subcategory": "Movie Rental",
        "type": "Entertainment"
      }
    ],
    "sg:phone": "+1 419 422 9642",
    "sg:postcode": "45840",
    "sg:province": "OH",
    "sg:tags": [
      "video",
      "tape"
    ],
    "wof:name": "Blockbuster",
    "wof:placetype": "venue"
  },
  "geometry": {"coordinates":[-83.650393,41.008502],"type":"Point"}
}
