{
  "type": "Feature",
  "properties": {
    "addr:full":"1244 S Main St Bellefontaine OH 43311",
    "addr:housenumber":"1244",
    "addr:postcode":"43311",
    "addr:street":"S Main St",
    "iso:country":"US",
    "sg:address":"1244 S Main St",
    "sg:city":"Bellefontaine",
    "sg:classifiers":[
        {
            "category":"Wholesale",
            "subcategory":"Farm Supplies",
            "type":"Manufacturing & Wholesale Goods"
        },
        {
            "category":"Shopping",
            "type":"Retail Goods"
        }
    ],
    "sg:phone":"+1 937 592 1307",
    "sg:postcode":"43311",
    "sg:province":"OH",
    "sg:tags":[
        "feed"
    ],
    "wof:name":"King Feed Drive Thru",
    "wof:placetype":"venue"
},
  "geometry": {"coordinates":[-83.76159699999999,40.34339],"type":"Point"}
}