{
  "type": "Feature",
  "properties": {
    "iso:country":"US",
    "sg:address":"14 N 5th St",
    "sg:city":"Zanesville",
    "sg:classifiers":[
        {
            "category":"Shopping",
            "subcategory":"Computers & Home Electronics",
            "type":"Retail Goods"
        }
    ],
    "sg:phone":"+1 740 455 8955",
    "sg:postcode":"43701",
    "sg:province":"OH",
    "sg:tags":[
        "parts",
        "supply"
    ],
    "wof:name":"GBS Corp",
    "wof:placetype":"venue"
},
  "geometry": {"coordinates":[-82.006377,39.940749],"type":"Point"}
}