{
  "type": "Feature",
  "properties": {
    "addr:full": "14 N 5th St Zanesville OH 43701",
    "addr:housenumber": "14",
    "addr:postcode": "43701",
    "addr:street": "N 5Th St",
    "iso:country": "US",
    "sg:address": "14 N 5th St",
    "sg:city": "Zanesville",
    "sg:classifiers": [
      {
        "category": "Shopping",
        "subcategory": "Computers \u0026 Home Electronics",
        "type": "Retail Goods"
      }
    ],
    "sg:phone": "+1 740 455 8955",
    "sg:postcode": "43701",
    "sg:province": "OH",
    "sg:tags": [
      "parts",
      "supply"
    ],
    "wof:name": "GBS Corp",
    "wof:placetype": "venue"
  },
  "geometry": {"coordinates":[-82.006377,39.940749],"type":"Point"}
}
