{
  "type": "Feature",
  "properties": {
    "addr:full": "7408 Suzi Cir West Chester OH 45069",
    "addr:housenumber": "7408",
    "addr:postcode": "45069",
    "addr:street": "Suzi Cir",
    "iso:country": "US",
    "sg:address": "7408 Suzi Cir",
    "sg:city": "West Chester",
    "sg:classifiers": [
      {
        "category": "Shopping",
        "type": "Retail Goods"
      }
    ],
    "sg:phone": "+1 513 759 2618",
    "sg:postcode": "45069",
    "sg:province": "OH",
    "sg:tags": [
      "merchandise"
    ],
    "wof:name": "Buckeye Shop",
    "wof:placetype": "venue"
  },
  "geometry": {"coordinates":[-84.408878,39.368455],"type":"Point"}
}
