{
  "type": "Feature",
  "properties": {
    "iso:country":"US",
    "sg:address":"1023 N Main St",
    "sg:city":"Lewisburg",
    "sg:classifiers":[
        {
            "category":"Shopping",
            "subcategory":"Gifts & Souvenirs",
            "type":"Retail Goods"
        }
    ],
    "sg:phone":"+1 937 962 2584",
    "sg:postcode":"45338",
    "sg:province":"OH",
    "sg:tags":[
        "shop"
    ],
    "wof:name":"Iris Gift Shop",
    "wof:placetype":"venue"
},
  "geometry": {"coordinates":[-84.540486,39.854996],"type":"Point"}
}