{
  "type": "Feature",
  "properties": {
    "addr:full": "409 Ohio St Wapakoneta OH 45895",
    "addr:housenumber": "409",
    "addr:postcode": "45895",
    "addr:street": "Ohio St",
    "iso:country": "US",
    "sg:address": "409 Ohio St",
    "sg:city": "Wapakoneta",
    "sg:classifiers": [
      {
        "category": "Building \u0026 Trades",
        "subcategory": "Electrical",
        "type": "Services"
      }
    ],
    "sg:phone": "+1 419 738 2884",
    "sg:postcode": "45895",
    "sg:province": "OH",
    "sg:tags": [
      "electrical",
      "contractor"
    ],
    "wof:name": "Nagel Electric",
    "wof:placetype": "venue"
  },
  "geometry": {"coordinates":[-84.200538,40.56691],"type":"Point"}
}
