{
  "type": "Feature",
  "properties": {
    "iso:country":"US",
    "sg:address":"5130 Youngstown Warren Rd",
    "sg:city":"Niles",
    "sg:classifiers":[
        {
            "category":"Shopping",
            "subcategory":"Discount & Variety Stores",
            "type":"Retail Goods"
        }
    ],
    "sg:phone":"+1 330 544 3501",
    "sg:postcode":"44446",
    "sg:province":"OH",
    "wof:name":"Dollar General",
    "wof:placetype":"venue"
},
  "geometry": {"coordinates":[-80.761758,41.212864],"type":"Point"}
}