{
  "type": "Feature",
  "properties": {
    "addr:full":"101 W 3rd St Dayton OH 45402",
    "addr:housenumber":"101",
    "addr:postcode":"45402",
    "addr:street":"W 3Rd St",
    "iso:country":"US",
    "sg:address":"101 W 3rd St",
    "sg:city":"Dayton",
    "sg:classifiers":[
        {
            "category":"Utilities",
            "subcategory":"Water",
            "type":"Services"
        }
    ],
    "sg:phone":"+1 937 333 3550",
    "sg:postcode":"45402",
    "sg:province":"OH",
    "sg:tags":[
        "company",
        "sewage"
    ],
    "wof:name":"Dayton Water Dept",
    "wof:placetype":"venue"
},
  "geometry": {"coordinates":[-84.195268,39.758965],"type":"Point"}
}