{
  "type": "Feature",
  "properties": {
    "iso:country":"US",
    "sg:address":"1129 State Ave NE",
    "sg:city":"Massillon",
    "sg:classifiers":[
        {
            "category":"Personal",
            "type":"Services"
        }
    ],
    "sg:phone":"+1 330 833 6270",
    "sg:postcode":"44646",
    "sg:province":"OH",
    "sg:tags":[
        "therapist",
        "massage"
    ],
    "wof:name":"Karen Campbell",
    "wof:placetype":"venue"
},
  "geometry": {"coordinates":[-81.50970599999999,40.804032],"type":"Point"}
}