{
  "type": "Feature",
  "properties": {
    "addr:full": "2899 Center Rd Poland OH 44514",
    "addr:housenumber": "2899",
    "addr:postcode": "44514",
    "addr:street": "Center Rd",
    "iso:country": "US",
    "sg:address": "2899 Center Rd",
    "sg:city": "Poland",
    "sg:classifiers": [
      {
        "category": "Building \u0026 Trades",
        "subcategory": "Plumbing",
        "type": "Services"
      }
    ],
    "sg:phone": "+1 330 707 9126",
    "sg:postcode": "44514",
    "sg:province": "OH",
    "sg:tags": [
      "plumbing",
      "contractor"
    ],
    "wof:name": "Dan's Plumbing Svc",
    "wof:placetype": "venue"
  },
  "geometry": {"coordinates":[-80.600382,41.023699],"type":"Point"}
}
