{
  "type": "Feature",
  "properties": {
    "iso:country":"US",
    "sg:address":"362 State Rte 250",
    "sg:city":"Jeromesville",
    "sg:classifiers":[
        {
            "category":"Wholesale",
            "subcategory":"Construction Materials",
            "type":"Manufacturing & Wholesale Goods"
        }
    ],
    "sg:phone":"+1 419 869 7509",
    "sg:postcode":"44840",
    "sg:province":"OH",
    "wof:name":"Regg S Rader",
    "wof:placetype":"venue"
},
  "geometry": {"coordinates":[-82.20046000000001,40.856608],"type":"Point"}
}