{
  "type": "Feature",
  "properties": {
    "addr:full": "41 Loganwood Dr Dayton OH 45458",
    "addr:housenumber": "41",
    "addr:postcode": "45458",
    "addr:street": "Loganwood Dr",
    "iso:country": "US",
    "sg:address": "41 Loganwood Dr",
    "sg:city": "Dayton",
    "sg:classifiers": [
      {
        "category": "Real Estate",
        "subcategory": "Real Estate Operator",
        "type": "Services"
      }
    ],
    "sg:phone": "+1 937 433 8148",
    "sg:postcode": "45458",
    "sg:province": "OH",
    "sg:tags": [
      "building",
      "apartment"
    ],
    "wof:name": "Chevy Chase Park Apartments",
    "wof:placetype": "venue"
  },
  "geometry": {"coordinates":[-84.158415,39.619396],"type":"Point"}
}
