{
  "type": "Feature",
  "properties": {
    "addr:full": "2615 E High St Springfield OH 45505",
    "addr:housenumber": "2615",
    "addr:postcode": "45505",
    "addr:street": "E High St",
    "iso:country": "US",
    "sg:address": "2615 E High St",
    "sg:city": "Springfield",
    "sg:classifiers": [
      {
        "category": "Health Services",
        "subcategory": "Hospital",
        "type": "Services"
      }
    ],
    "sg:phone": "+1 937 328 9236",
    "sg:postcode": "45505",
    "sg:province": "OH",
    "sg:tags": [
      "general"
    ],
    "wof:name": "Birthing Center At Cmnty Hosp",
    "wof:placetype": "venue"
  },
  "geometry": {"coordinates":[-83.768674,39.920122],"type":"Point"}
}
