{
  "type": "Feature",
  "properties": {
    "iso:country":"US",
    "sg:address":"2615 E High St",
    "sg:city":"Springfield",
    "sg:classifiers":[
        {
            "category":"Health Services",
            "subcategory":"Hospital",
            "type":"Services"
        }
    ],
    "sg:phone":"+1 937 328 9236",
    "sg:postcode":"45505",
    "sg:province":"OH",
    "sg:tags":[
        "general"
    ],
    "wof:name":"Birthing Center At Cmnty Hosp",
    "wof:placetype":"venue"
},
  "geometry": {"coordinates":[-83.768674,39.920122],"type":"Point"}
}