{
  "type": "Feature",
  "properties": {
    "iso:country":"US",
    "sg:address":"6750 Hamilton Ave",
    "sg:city":"Cincinnati",
    "sg:classifiers":[
        {
            "category":"Autos & Motor Vehicles",
            "subcategory":"Auto Supplies",
            "type":"Retail Goods"
        }
    ],
    "sg:phone":"+1 513 522 4858",
    "sg:postcode":"45224",
    "sg:province":"OH",
    "sg:tags":[
        "parts",
        "accessory"
    ],
    "sg:website":"www.autozone.com",
    "wof:name":"Autozone",
    "wof:placetype":"venue"
},
  "geometry": {"coordinates":[-84.54928099999999,39.21578],"type":"Point"}
}