{
  "type": "Feature",
  "properties": {
    "addr:full": "6750 Hamilton Ave Cincinnati OH 45224",
    "addr:housenumber": "6750",
    "addr:postcode": "45224",
    "addr:street": "Hamilton Ave",
    "iso:country": "US",
    "sg:address": "6750 Hamilton Ave",
    "sg:city": "Cincinnati",
    "sg:classifiers": [
      {
        "category": "Autos \u0026 Motor Vehicles",
        "subcategory": "Auto Supplies",
        "type": "Retail Goods"
      }
    ],
    "sg:phone": "+1 513 522 4858",
    "sg:postcode": "45224",
    "sg:province": "OH",
    "sg:tags": [
      "parts",
      "accessory"
    ],
    "sg:website": "www.autozone.com",
    "wof:name": "Autozone",
    "wof:placetype": "venue"
  },
  "geometry": {"coordinates":[-84.549281,39.21578],"type":"Point"}
}
