{
  "type": "Feature",
  "properties": {
    "iso:country":"US",
    "sg:address":"11320 Springfield Pike",
    "sg:city":"Cincinnati",
    "sg:classifiers":[
        {
            "category":"Social Services",
            "subcategory":"Adult Care",
            "type":"Services"
        }
    ],
    "sg:phone":"+1 513 772 7878",
    "sg:postcode":"45246",
    "sg:province":"OH",
    "sg:tags":[
        "home",
        "residential"
    ],
    "sg:website":"www.assisted.com",
    "wof:name":"Alterra Sterling House",
    "wof:placetype":"venue"
},
  "geometry": {"coordinates":[-84.484101,39.280083],"type":"Point"}
}