{
  "type": "Feature",
  "properties": {
    "addr:full": "403 Hamilton St New Richmond OH 45157",
    "addr:housenumber": "403",
    "addr:postcode": "45157",
    "addr:street": "Hamilton St",
    "iso:country": "US",
    "sg:address": "403 Hamilton St",
    "sg:city": "New Richmond",
    "sg:classifiers": [
      {
        "category": "Home \u0026 Garden",
        "subcategory": "Building Materials",
        "type": "Retail Goods"
      }
    ],
    "sg:phone": "+1 513 553 6358",
    "sg:postcode": "45157",
    "sg:province": "OH",
    "sg:tags": [
      "paint"
    ],
    "wof:name": "Cincinnati Paint Equipment",
    "wof:placetype": "venue"
  },
  "geometry": {"coordinates":[-84.276898,38.947686],"type":"Point"}
}
