{
  "type": "Feature",
  "properties": {
    "addr:full":"2619 Glendora Ave Cincinnati OH 45219",
    "addr:housenumber":"2619",
    "addr:postcode":"45219",
    "addr:street":"Glendora Ave",
    "iso:country":"US",
    "sg:address":"2619 Glendora Ave",
    "sg:city":"Cincinnati",
    "sg:classifiers":[
        {
            "category":"Professional",
            "type":"Services"
        }
    ],
    "sg:phone":"+1 513 751 1969",
    "sg:postcode":"45219",
    "sg:province":"OH",
    "wof:name":"Kauffman Jacobs Co",
    "wof:placetype":"venue"
},
  "geometry": {"coordinates":[-84.510465,39.130203],"type":"Point"}
}