{
  "type": "Feature",
  "properties": {
    "iso:country":"US",
    "sg:address":"4366 Ridge Rd SW",
    "sg:city":"Baltic",
    "sg:classifiers":[
        {
            "category":"Manufacturing",
            "subcategory":"Apparel",
            "type":"Manufacturing & Wholesale Goods"
        }
    ],
    "sg:phone":"+1 330 897 6205",
    "sg:postcode":"43804",
    "sg:province":"OH",
    "sg:tags":[
        "contractor",
        "product",
        "sewing",
        "mfg"
    ],
    "wof:name":"Valley View Sewing LLC",
    "wof:placetype":"venue"
},
  "geometry": {"coordinates":[-81.68491899999999,40.422766],"type":"Point"}
}