{
  "type": "Feature",
  "properties": {
    "addr:full": "4366 Ridge Rd SW Baltic OH 43804",
    "addr:housenumber": "4366",
    "addr:postcode": "43804",
    "addr:street": "Ridge Rd Sw",
    "iso:country": "US",
    "sg:address": "4366 Ridge Rd SW",
    "sg:city": "Baltic",
    "sg:classifiers": [
      {
        "category": "Manufacturing",
        "subcategory": "Apparel",
        "type": "Manufacturing \u0026 Wholesale Goods"
      }
    ],
    "sg:phone": "+1 330 897 6205",
    "sg:postcode": "43804",
    "sg:province": "OH",
    "sg:tags": [
      "contractor",
      "product",
      "sewing",
      "mfg"
    ],
    "wof:name": "Valley View Sewing LLC",
    "wof:placetype": "venue"
  },
  "geometry": {"coordinates":[-81.684919,40.422766],"type":"Point"}
}
