{
  "type": "Feature",
  "properties": {
    "iso:country":"US",
    "sg:address":"2181 Victory Pkwy",
    "sg:city":"Cincinnati",
    "sg:classifiers":[
        {
            "category":"Health Services",
            "subcategory":"Health Practitioner",
            "type":"Services"
        }
    ],
    "sg:phone":"+1 513 961 3344",
    "sg:postcode":"45206",
    "sg:province":"OH",
    "sg:tags":[
        "psychologist"
    ],
    "wof:name":"Abundant Living Psychological",
    "wof:placetype":"venue"
},
  "geometry": {"coordinates":[-84.48665,39.120278],"type":"Point"}
}