{
  "type": "Feature",
  "properties": {
    "addr:full":"3223 Belmont Ave Youngstown OH 44505",
    "addr:housenumber":"3223",
    "addr:postcode":"44505",
    "addr:street":"Belmont Ave",
    "iso:country":"US",
    "sg:address":"3223 Belmont Ave",
    "sg:city":"Youngstown",
    "sg:classifiers":[
        {
            "category":"Shopping",
            "subcategory":"Jewelry",
            "type":"Retail Goods"
        }
    ],
    "sg:phone":"+1 330 759 8181",
    "sg:postcode":"44505",
    "sg:province":"OH",
    "sg:tags":[
        "used",
        "merchandise",
        "business",
        "jeweler"
    ],
    "wof:name":"Marvin Schwartz Co",
    "wof:placetype":"venue"
},
  "geometry": {"coordinates":[-80.66543,41.14144],"type":"Point"}
}