{
  "type": "Feature",
  "properties": {
    "addr:full": "1134 Schwilk Rd SE Lancaster OH 43130",
    "addr:housenumber": "1134",
    "addr:postcode": "43130",
    "addr:street": "Schwilk Rd Se",
    "iso:country": "US",
    "sg:address": "1134 Schwilk Rd SE",
    "sg:city": "Lancaster",
    "sg:classifiers": [
      {
        "category": "Wholesale",
        "subcategory": "Auto Parts",
        "type": "Manufacturing \u0026 Wholesale Goods"
      }
    ],
    "sg:phone": "+1 740 654 8608",
    "sg:postcode": "43130",
    "sg:province": "OH",
    "sg:tags": [
      "battery",
      "industrial"
    ],
    "wof:name": "Davis Battery Sales Inc",
    "wof:placetype": "venue"
  },
  "geometry": {"coordinates":[-82.525278,39.704135],"type":"Point"}
}
