{
  "type": "Feature",
  "properties": {
    "iso:country":"US",
    "sg:address":"1134 Schwilk Rd SE",
    "sg:city":"Lancaster",
    "sg:classifiers":[
        {
            "category":"Wholesale",
            "subcategory":"Auto Parts",
            "type":"Manufacturing & Wholesale Goods"
        }
    ],
    "sg:phone":"+1 740 654 8608",
    "sg:postcode":"43130",
    "sg:province":"OH",
    "sg:tags":[
        "battery",
        "industrial"
    ],
    "wof:name":"Davis Battery Sales Inc",
    "wof:placetype":"venue"
},
  "geometry": {"coordinates":[-82.525278,39.704135],"type":"Point"}
}