{
  "type": "Feature",
  "properties": {
    "iso:country":"US",
    "sg:address":"20115 Harvard Ave",
    "sg:city":"Cleveland",
    "sg:classifiers":[
        {
            "category":"Personal",
            "subcategory":"Beauty Salon",
            "type":"Services"
        }
    ],
    "sg:phone":"+1 216 752 0477",
    "sg:postcode":"44122",
    "sg:province":"OH",
    "sg:tags":[
        "manicuring"
    ],
    "wof:name":"Nail Creations",
    "wof:placetype":"venue"
},
  "geometry": {"coordinates":[-81.537522,41.449935],"type":"Point"}
}