{
  "type": "Feature",
  "properties": {
    "addr:full": "86 N Hanover St Minster OH 45865",
    "addr:housenumber": "86",
    "addr:postcode": "45865",
    "addr:street": "N Hanover St",
    "iso:country": "US",
    "sg:address": "86 N Hanover St",
    "sg:city": "Minster",
    "sg:classifiers": [
      {
        "category": "Education",
        "subcategory": "School",
        "type": "Public Place"
      }
    ],
    "sg:phone": "+1 419 628 2214",
    "sg:postcode": "45865",
    "sg:province": "OH",
    "sg:website": "www.minster.k12.oh.us",
    "wof:name": "Minster Elementary School",
    "wof:placetype": "venue"
  },
  "geometry": {"coordinates":[-84.380353,40.39498],"type":"Point"}
}
