{
  "type": "Feature",
  "properties": {
    "iso:country":"US",
    "sg:address":"2205 Beckler Rd",
    "sg:city":"New Marshfield",
    "sg:classifiers":[
        {
            "category":"Wholesale",
            "subcategory":"Auto Parts",
            "type":"Manufacturing & Wholesale Goods"
        }
    ],
    "sg:phone":"+1 740 753 1100",
    "sg:postcode":"45766",
    "sg:province":"OH",
    "sg:tags":[
        "recycle",
        "automobile",
        "rebuilt",
        "used"
    ],
    "wof:name":"Mc Kee Auto Parts",
    "wof:placetype":"venue"
},
  "geometry": {"coordinates":[-82.24309100000001,39.37634],"type":"Point"}
}