{
  "type": "Feature",
  "properties": {
    "addr:full": "2205 Beckler Rd New Marshfield OH 45766",
    "addr:housenumber": "2205",
    "addr:postcode": "45766",
    "addr:street": "Beckler Rd",
    "iso:country": "US",
    "sg:address": "2205 Beckler Rd",
    "sg:city": "New Marshfield",
    "sg:classifiers": [
      {
        "category": "Wholesale",
        "subcategory": "Auto Parts",
        "type": "Manufacturing \u0026 Wholesale Goods"
      }
    ],
    "sg:phone": "+1 740 753 1100",
    "sg:postcode": "45766",
    "sg:province": "OH",
    "sg:tags": [
      "recycle",
      "automobile",
      "rebuilt",
      "used"
    ],
    "wof:name": "Mc Kee Auto Parts",
    "wof:placetype": "venue"
  },
  "geometry": {"coordinates":[-82.243091,39.37634],"type":"Point"}
}
