{
  "type": "Feature",
  "properties": {
    "addr:full": "16568 Twp Rd 60 Attica OH 44807",
    "addr:housenumber": "16568;60",
    "addr:postcode": "44807",
    "addr:street": "Twp Rd",
    "iso:country": "US",
    "sg:address": "16568 Twp Rd 60",
    "sg:city": "Attica",
    "sg:phone": "+1 419 426 5095",
    "sg:postcode": "44807",
    "sg:province": "OH",
    "sg:tags": [
      "farm",
      "corn"
    ],
    "wof:name": "Thomas Weaver",
    "wof:placetype": "venue"
  },
  "geometry": {"coordinates":[-82.851416,41.029757],"type":"Point"}
}
