{
  "type": "Feature",
  "properties": {
    "addr:full": "115 Sophia's Ln Ottawa OH 45875",
    "addr:housenumber": "115",
    "addr:postcode": "45875",
    "addr:street": "Sophia'S Ln",
    "iso:country": "US",
    "sg:address": "115 Sophia's Ln",
    "sg:city": "Ottawa",
    "sg:classifiers": [
      {
        "category": "Real Estate",
        "subcategory": "Developer",
        "type": "Services"
      }
    ],
    "sg:phone": "+1 419 538 7374",
    "sg:postcode": "45875",
    "sg:province": "OH",
    "wof:name": "Giesken Outdoor Advertising",
    "wof:placetype": "venue"
  },
  "geometry": {"coordinates":[-84.073733,41.023947],"type":"Point"}
}
