{
  "type": "Feature",
  "properties": {
    "addr:full": "7280 Bohemian Rd SE Corning OH 43730",
    "addr:postcode": "7280;43730",
    "addr:street": "Bohemian Rd Se",
    "iso:country": "US",
    "sg:address": "7280 Bohemian Rd SE",
    "sg:city": "Corning",
    "sg:classifiers": [
      {
        "category": "Freight",
        "type": "Transportation"
      }
    ],
    "sg:phone": "+1 740 394 2088",
    "sg:postcode": "43730",
    "sg:province": "OH",
    "sg:tags": [
      "operator",
      "trucking"
    ],
    "wof:name": "Rolo Enterprises Inc",
    "wof:placetype": "venue"
  },
  "geometry": {"coordinates":[-82.159831,39.610428],"type":"Point"}
}
