{
  "type": "Feature",
  "properties": {
    "addr:full":"325 Co Rd 406 South Point OH 45680",
    "addr:housenumber":"325",
    "addr:postcode":"45680",
    "addr:street":"Co Rd 406",
    "iso:country":"US",
    "sg:address":"325 Co Rd 406",
    "sg:city":"South Point",
    "sg:classifiers":[
        {
            "category":"Restaurant",
            "type":"Food & Drink"
        }
    ],
    "sg:phone":"+1 740 894 5417",
    "sg:postcode":"45680",
    "sg:province":"OH",
    "sg:tags":[
        "eating"
    ],
    "wof:name":"Taco Bell",
    "wof:placetype":"venue"
},
  "geometry": {"coordinates":[-82.51106799999999,38.417444],"type":"Point"}
}