{
  "type": "Feature",
  "properties": {
    "addr:full": "1125 Hubbard Rd Galloway OH 43119",
    "addr:housenumber": "1125",
    "addr:postcode": "43119",
    "addr:street": "Hubbard Rd",
    "iso:country": "US",
    "sg:address": "1125 Hubbard Rd",
    "sg:city": "Galloway",
    "sg:classifiers": [
      {
        "category": "Social Services",
        "type": "Services"
      }
    ],
    "sg:phone": "+1 614 878 5203",
    "sg:postcode": "43119",
    "sg:province": "OH",
    "sg:tags": [
      "youth",
      "organization",
      "center"
    ],
    "wof:name": "Girl Scout Seal-Ohio Council",
    "wof:placetype": "venue"
  },
  "geometry": {"coordinates":[-83.238611,39.969471],"type":"Point"}
}
