{
  "type": "Feature",
  "properties": {
    "addr:full": "347 W Spring St Cadiz OH 43907",
    "addr:housenumber": "347",
    "addr:postcode": "43907",
    "addr:street": "W Spring St",
    "iso:country": "US",
    "sg:address": "347 W Spring St",
    "sg:city": "Cadiz",
    "sg:classifiers": [
      {
        "category": "Health Services",
        "subcategory": "Doctor",
        "type": "Services"
      }
    ],
    "sg:phone": "+1 740 942 3311",
    "sg:postcode": "43907",
    "sg:province": "OH",
    "sg:tags": [
      "dentist"
    ],
    "wof:name": "Gary A Barker DDS",
    "wof:placetype": "venue"
  },
  "geometry": {"coordinates":[-80.999342,40.276211],"type":"Point"}
}
