{
  "type": "Feature",
  "properties": {
    "iso:country":"US",
    "sg:address":"755 Stelzer Rd",
    "sg:city":"Columbus",
    "sg:classifiers":[
        {
            "category":"Food & Beverages",
            "subcategory":"Groceries & Convenience Stores",
            "type":"Retail Goods"
        }
    ],
    "sg:phone":"+1 614 235 3027",
    "sg:postcode":"43219",
    "sg:province":"OH",
    "wof:name":"Stelzer Food Market",
    "wof:placetype":"venue"
},
  "geometry": {"coordinates":[-82.91414,39.98715],"type":"Point"}
}