{
  "type": "Feature",
  "properties": {
    "addr:full":"7098 Old Prose Ct Dublin OH 43017",
    "addr:housenumber":"7098",
    "addr:postcode":"43017",
    "addr:street":"Old Prose Ct",
    "iso:country":"US",
    "sg:address":"7098 Old Prose Ct",
    "sg:city":"Dublin",
    "sg:classifiers":[
        {
            "category":"Professional",
            "type":"Services"
        }
    ],
    "sg:phone":"+1 614 764 0045",
    "sg:postcode":"43017",
    "sg:province":"OH",
    "wof:name":"Cellar Dweller",
    "wof:placetype":"venue"
},
  "geometry": {"coordinates":[-83.135007,40.112452],"type":"Point"}
}