{
  "type": "Feature",
  "properties": {
    "addr:full":"3591 W 56th St Cleveland OH 44102",
    "addr:housenumber":"3591",
    "addr:postcode":"44102",
    "addr:street":"W 56Th St",
    "iso:country":"US",
    "sg:address":"3591 W 56th St",
    "sg:city":"Cleveland",
    "sg:classifiers":[
        {
            "category":"Manufacturing",
            "subcategory":"Petroleum Products",
            "type":"Manufacturing & Wholesale Goods"
        }
    ],
    "sg:phone":"+1 216 961 6900",
    "sg:postcode":"44102",
    "sg:province":"OH",
    "sg:tags":[
        "lubricant",
        "industrial",
        "based",
        "mfg"
    ],
    "sg:website":"www.acmerefining.com",
    "wof:name":"Acme Refining",
    "wof:placetype":"venue"
},
  "geometry": {"coordinates":[-81.725846,41.460214],"type":"Point"}
}