{
  "type": "Feature",
  "properties": {
    "iso:country":"US",
    "sg:address":"1115 Portage Lakes Dr",
    "sg:city":"Akron",
    "sg:classifiers":[
        {
            "category":"Autos & Motor Vehicles",
            "subcategory":"Boat Sales",
            "type":"Retail Goods"
        }
    ],
    "sg:phone":"+1 330 644 8080",
    "sg:postcode":"44319",
    "sg:province":"OH",
    "sg:tags":[
        "equipment",
        "marine",
        "supply"
    ],
    "wof:name":"Marine Engine Controls Inc",
    "wof:placetype":"venue"
},
  "geometry": {"coordinates":[-81.555562,41.005788],"type":"Point"}
}