{
  "type": "Feature",
  "properties": {
    "iso:country":"US",
    "sg:address":"263 E Broadway St",
    "sg:city":"Loveland",
    "sg:classifiers":[
        {
            "category":"Building & Trades",
            "subcategory":"Electrical",
            "type":"Services"
        }
    ],
    "sg:phone":"+1 513 683 5257",
    "sg:postcode":"45140",
    "sg:province":"OH",
    "sg:tags":[
        "electrical",
        "contractor"
    ],
    "wof:name":"Ellis Electric Co",
    "wof:placetype":"venue"
},
  "geometry": {"coordinates":[-84.25335800000001,39.263607],"type":"Point"}
}