{
  "type": "Feature",
  "properties": {
    "addr:full": "263 E Broadway St Loveland OH 45140",
    "addr:housenumber": "263",
    "addr:postcode": "45140",
    "addr:street": "E Broadway St",
    "iso:country": "US",
    "sg:address": "263 E Broadway St",
    "sg:city": "Loveland",
    "sg:classifiers": [
      {
        "category": "Building \u0026 Trades",
        "subcategory": "Electrical",
        "type": "Services"
      }
    ],
    "sg:phone": "+1 513 683 5257",
    "sg:postcode": "45140",
    "sg:province": "OH",
    "sg:tags": [
      "electrical",
      "contractor"
    ],
    "wof:name": "Ellis Electric Co",
    "wof:placetype": "venue"
  },
  "geometry": {"coordinates":[-84.253358,39.263607],"type":"Point"}
}
