{
  "type": "Feature",
  "properties": {
    "iso:country":"US",
    "sg:address":"7097 Allyn Rd",
    "sg:city":"Hiram",
    "sg:classifiers":[
        {
            "category":"Professional",
            "subcategory":"Research",
            "type":"Services"
        }
    ],
    "sg:phone":"+1 330 569 3487",
    "sg:postcode":"44231",
    "sg:province":"OH",
    "sg:tags":[
        "development",
        "laboratory"
    ],
    "wof:name":"Small Farm Research & Educatn",
    "wof:placetype":"venue"
},
  "geometry": {"coordinates":[-81.14313799999999,41.345399],"type":"Point"}
}