{
  "type": "Feature",
  "properties": {
    "iso:country":"US",
    "sg:address":"13405 Graham Rd",
    "sg:city":"Cleveland",
    "sg:classifiers":[
        {
            "category":"Wholesale",
            "subcategory":"Non-durable Goods",
            "type":"Manufacturing & Wholesale Goods"
        }
    ],
    "sg:phone":"+1 216 851 1911",
    "sg:postcode":"44112",
    "sg:province":"OH",
    "sg:tags":[
        "leather"
    ],
    "sg:website":"www.whipappeal.com",
    "wof:name":"Whipappeal Leather Inc",
    "wof:placetype":"venue"
},
  "geometry": {"coordinates":[-81.587253,41.535728],"type":"Point"}
}