{
  "type": "Feature",
  "properties": {
    "iso:country":"US",
    "sg:address":"3805 Shady Ln",
    "sg:city":"North Bend",
    "sg:classifiers":[
        {
            "category":"Food & Beverages",
            "subcategory":"Bakery",
            "type":"Retail Goods"
        }
    ],
    "sg:phone":"+1 513 941 1585",
    "sg:postcode":"45052",
    "sg:province":"OH",
    "wof:name":"Regina Bakery",
    "wof:placetype":"venue"
},
  "geometry": {"coordinates":[-84.699679,39.164542],"type":"Point"}
}