{
  "type": "Feature",
  "properties": {
    "addr:full": "3805 Shady Ln North Bend OH 45052",
    "addr:housenumber": "3805",
    "addr:postcode": "45052",
    "addr:street": "Shady Ln",
    "iso:country": "US",
    "sg:address": "3805 Shady Ln",
    "sg:city": "North Bend",
    "sg:classifiers": [
      {
        "category": "Food \u0026 Beverages",
        "subcategory": "Bakery",
        "type": "Retail Goods"
      }
    ],
    "sg:phone": "+1 513 941 1585",
    "sg:postcode": "45052",
    "sg:province": "OH",
    "wof:name": "Regina Bakery",
    "wof:placetype": "venue"
  },
  "geometry": {"coordinates":[-84.699679,39.164542],"type":"Point"}
}
