{
  "type": "Feature",
  "properties": {
    "addr:full": "3527 Edson Dr Columbus OH 43228",
    "addr:housenumber": "3527",
    "addr:postcode": "43228",
    "addr:street": "Edson Dr",
    "iso:country": "US",
    "sg:address": "3527 Edson Dr",
    "sg:city": "Columbus",
    "sg:classifiers": [
      {
        "category": "Professional",
        "subcategory": "Computer Services",
        "type": "Services"
      }
    ],
    "sg:phone": "+1 614 272 8770",
    "sg:postcode": "43228",
    "sg:province": "OH",
    "sg:tags": [
      "repair"
    ],
    "wof:name": "Hobbs Computer Repair",
    "wof:placetype": "venue"
  },
  "geometry": {"coordinates":[-83.095597,39.958366],"type":"Point"}
}
