{
  "type": "Feature",
  "properties": {
    "addr:full": "107 E College Ave Westerville OH 43081",
    "addr:housenumber": "107",
    "addr:postcode": "43081",
    "addr:street": "E College Ave",
    "iso:country": "US",
    "sg:address": "107 E College Ave",
    "sg:city": "Westerville",
    "sg:classifiers": [
      {
        "category": "Professional",
        "type": "Services"
      }
    ],
    "sg:phone": "+1 614 440 1934",
    "sg:postcode": "43081",
    "sg:province": "OH",
    "wof:name": "ISB Svc",
    "wof:placetype": "venue"
  },
  "geometry": {"coordinates":[-82.927607,40.126286],"type":"Point"}
}
