{
  "type": "Feature",
  "properties": {
    "iso:country":"US",
    "sg:address":"1934 Fairmount Ave",
    "sg:city":"Cincinnati",
    "sg:classifiers":[
        {
            "category":"Shopping",
            "subcategory":"Catalog Store",
            "type":"Retail Goods"
        }
    ],
    "sg:phone":"+1 513 251 4129",
    "sg:postcode":"45214",
    "sg:province":"OH",
    "sg:tags":[
        "mail",
        "order"
    ],
    "wof:name":"A D Jones Enterprises",
    "wof:placetype":"venue"
},
  "geometry": {"coordinates":[-84.55852899999999,39.130353],"type":"Point"}
}