{
  "type": "Feature",
  "properties": {
    "addr:full": "313 W Lincoln Way Minerva OH 44657",
    "addr:housenumber": "313",
    "addr:postcode": "44657",
    "addr:street": "W Lincoln Way",
    "iso:country": "US",
    "sg:address": "313 W Lincoln Way",
    "sg:city": "Minerva",
    "sg:classifiers": [
      {
        "category": "Freight",
        "type": "Transportation"
      }
    ],
    "sg:phone": "+1 330 868 4380",
    "sg:postcode": "44657",
    "sg:province": "OH",
    "sg:tags": [
      "general"
    ],
    "wof:name": "Jnm Storage",
    "wof:placetype": "venue"
  },
  "geometry": {"coordinates":[-81.106603,40.72972],"type":"Point"}
}
