{
  "type": "Feature",
  "properties": {
    "addr:full": "2600 6th St SW Canton OH 44710",
    "addr:housenumber": "2600",
    "addr:postcode": "44710",
    "addr:street": "6Th St Sw",
    "iso:country": "US",
    "sg:address": "2600 6th St SW",
    "sg:city": "Canton",
    "sg:classifiers": [
      {
        "category": "Professional",
        "subcategory": "Business Services",
        "type": "Services"
      }
    ],
    "sg:phone": "+1 330 452 8152",
    "sg:postcode": "44710",
    "sg:province": "OH",
    "sg:tags": [
      "paging",
      "answering"
    ],
    "wof:name": "Aultman Physicians Answering",
    "wof:placetype": "venue"
  },
  "geometry": {"coordinates":[-81.402901,40.796753],"type":"Point"}
}
