{
  "type": "Feature",
  "properties": {
    "addr:full":"215 W 2nd St Dayton OH 45402",
    "addr:housenumber":"215",
    "addr:postcode":"45402",
    "addr:street":"W 2Nd St",
    "iso:country":"US",
    "sg:address":"215 W 2nd St",
    "sg:city":"Dayton",
    "sg:classifiers":[
        {
            "category":"Shopping",
            "subcategory":"Computers & Home Electronics",
            "type":"Retail Goods"
        }
    ],
    "sg:phone":"+1 937 226 1703",
    "sg:postcode":"45402",
    "sg:province":"OH",
    "sg:tags":[
        "equipment",
        "satellite",
        "system"
    ],
    "wof:name":"Siroius Satellite Radio Inc",
    "wof:placetype":"venue"
},
  "geometry": {"coordinates":[-84.196372,39.76037],"type":"Point"}
}