{
  "type": "Feature",
  "properties": {
    "addr:full":"2949 Fair Ave Columbus OH 43209",
    "addr:housenumber":"2949",
    "addr:postcode":"43209",
    "addr:street":"Fair Ave",
    "iso:country":"US",
    "sg:address":"2949 Fair Ave",
    "sg:city":"Columbus",
    "sg:classifiers":[
        {
            "category":"Real Estate",
            "subcategory":"Real Estate Operator",
            "type":"Services"
        }
    ],
    "sg:phone":"+1 614 237 6677",
    "sg:postcode":"43209",
    "sg:province":"OH",
    "sg:tags":[
        "building",
        "nonresidential"
    ],
    "wof:name":"Kur-Bur Inc",
    "wof:placetype":"venue"
},
  "geometry": {"coordinates":[-82.920762,39.961479],"type":"Point"}
}