{
  "type": "Feature",
  "properties": {
    "addr:full": "12178 E Co Rd 6 Attica OH 44807",
    "addr:housenumber": "12178",
    "addr:postcode": "44807",
    "addr:street": "E Co Rd 6",
    "iso:country": "US",
    "sg:address": "12178 E Co Rd 6",
    "sg:city": "Attica",
    "sg:phone": "+1 419 426 7771",
    "sg:postcode": "44807",
    "sg:province": "OH",
    "sg:tags": [
      "farm",
      "corn",
      "wheat",
      "soybean"
    ],
    "wof:name": "Jim-DOT Farms",
    "wof:placetype": "venue"
  },
  "geometry": {"coordinates":[-82.935646,41.022772],"type":"Point"}
}
