{
  "type": "Feature",
  "properties": {
    "iso:country":"US",
    "sg:address":"12178 E Co Rd 6",
    "sg:city":"Attica",
    "sg:phone":"+1 419 426 7771",
    "sg:postcode":"44807",
    "sg:province":"OH",
    "sg:tags":[
        "farm",
        "corn",
        "wheat",
        "soybean"
    ],
    "wof:name":"Jim-DOT Farms",
    "wof:placetype":"venue"
},
  "geometry": {"coordinates":[-82.93564600000001,41.022772],"type":"Point"}
}