{
  "type": "Feature",
  "properties": {
    "iso:country":"US",
    "sg:address":"6466 Stover Ave",
    "sg:city":"Cincinnati",
    "sg:classifiers":[
        {
            "category":"Health Services",
            "subcategory":"Medical Lab",
            "type":"Services"
        }
    ],
    "sg:phone":"+1 513 631 9944",
    "sg:postcode":"45237",
    "sg:province":"OH",
    "sg:tags":[
        "laboratory"
    ],
    "wof:name":"Larry B Selker Dental Labs Inc",
    "wof:placetype":"venue"
},
  "geometry": {"coordinates":[-84.45076,39.189328],"type":"Point"}
}