{
  "type": "Feature",
  "properties": {
    "addr:full": "9681 Whippoorwill Dr Mason OH 45040",
    "addr:housenumber": "9681",
    "addr:postcode": "45040",
    "addr:street": "Whippoorwill Dr",
    "iso:country": "US",
    "sg:address": "9681 Whippoorwill Dr",
    "sg:city": "Mason",
    "sg:classifiers": [
      {
        "category": "Freight",
        "type": "Transportation"
      }
    ],
    "sg:phone": "+1 513 398 7509",
    "sg:postcode": "45040",
    "sg:province": "OH",
    "sg:tags": [
      "operator",
      "local",
      "trucking"
    ],
    "wof:name": "Billups Trucking LLC",
    "wof:placetype": "venue"
  },
  "geometry": {"coordinates":[-84.339755,39.296542],"type":"Point"}
}
