{
  "type": "Feature",
  "properties": {
    "addr:full": "357 Leatherman Rd Wadsworth OH 44281",
    "addr:housenumber": "357",
    "addr:postcode": "44281",
    "addr:street": "Leatherman Rd",
    "iso:country": "US",
    "sg:address": "357 Leatherman Rd",
    "sg:city": "Wadsworth",
    "sg:classifiers": [
      {
        "category": "Building \u0026 Trades",
        "subcategory": "Construction",
        "type": "Services"
      }
    ],
    "sg:phone": "+1 330 334 1470",
    "sg:postcode": "44281",
    "sg:province": "OH",
    "sg:tags": [
      "excavating",
      "contractor"
    ],
    "wof:name": "Thompson Excavating",
    "wof:placetype": "venue"
  },
  "geometry": {"coordinates":[-81.749509,41.03217],"type":"Point"}
}
