{
  "type": "Feature",
  "properties": {
    "iso:country":"US",
    "sg:address":"3637 State Rte 167",
    "sg:city":"Jefferson",
    "sg:classifiers":[
        {
            "category":"Farming",
            "subcategory":"Nursery",
            "type":"Manufacturing & Wholesale Goods"
        },
        {
            "category":"Home & Garden",
            "subcategory":"Garden Supply",
            "type":"Retail Goods"
        }
    ],
    "sg:phone":"+1 440 858 9660",
    "sg:postcode":"44047",
    "sg:province":"OH",
    "sg:tags":[
        "nurseryman",
        "perennial"
    ],
    "sg:website":"www.sunnyborderohio.com",
    "wof:name":"Sunny Border-Ohio Inc",
    "wof:placetype":"venue"
},
  "geometry": {"coordinates":[-80.658237,41.751814],"type":"Point"}
}