{
  "type": "Feature",
  "properties": {
    "iso:country":"US",
    "sg:address":"4680 Douglas Cir NW",
    "sg:city":"Canton",
    "sg:classifiers":[
        {
            "category":"Health Services",
            "subcategory":"Chiropractor",
            "type":"Services"
        }
    ],
    "sg:phone":"+1 330 498 9446",
    "sg:postcode":"44718",
    "sg:province":"OH",
    "sg:website":"www.chiropracticradiology.com",
    "wof:name":"Professional Imaging Conslnts",
    "wof:placetype":"venue"
},
  "geometry": {"coordinates":[-81.439464,40.848808],"type":"Point"}
}