{
  "type": "Feature",
  "properties": {
    "iso:country":"US",
    "sg:address":"1550 Peck Blvd",
    "sg:city":"Hamilton",
    "sg:classifiers":[
        {
            "category":"Building & Trades",
            "subcategory":"Construction",
            "type":"Services"
        }
    ],
    "sg:phone":"+1 513 737 0405",
    "sg:postcode":"45011",
    "sg:province":"OH",
    "sg:tags":[
        "dry wall",
        "contractor"
    ],
    "wof:name":"Classic General Contractor",
    "wof:placetype":"venue"
},
  "geometry": {"coordinates":[-84.561438,39.383683],"type":"Point"}
}