{
  "type": "Feature",
  "properties": {
    "addr:full": "10430 Airport Hwy Swanton OH 43558",
    "addr:housenumber": "10430",
    "addr:postcode": "43558",
    "addr:street": "Airport Hwy",
    "iso:country": "US",
    "sg:address": "10430 Airport Hwy",
    "sg:city": "Swanton",
    "sg:classifiers": [
      {
        "category": "Building \u0026 Trades",
        "subcategory": "Construction",
        "type": "Services"
      }
    ],
    "sg:phone": "+1 419 343 3826",
    "sg:postcode": "43558",
    "sg:province": "OH",
    "sg:tags": [
      "painter"
    ],
    "wof:name": "Wray's Quality Painting",
    "wof:placetype": "venue"
  },
  "geometry": {"coordinates":[-83.789504,41.601963],"type":"Point"}
}
