{
  "type": "Feature",
  "properties": {
    "iso:country":"US",
    "sg:address":"10430 Airport Hwy",
    "sg:city":"Swanton",
    "sg:classifiers":[
        {
            "category":"Building & Trades",
            "subcategory":"Construction",
            "type":"Services"
        }
    ],
    "sg:phone":"+1 419 343 3826",
    "sg:postcode":"43558",
    "sg:province":"OH",
    "sg:tags":[
        "painter"
    ],
    "wof:name":"Wray's Quality Painting",
    "wof:placetype":"venue"
},
  "geometry": {"coordinates":[-83.78950399999999,41.601963],"type":"Point"}
}