{
  "type": "Feature",
  "properties": {
    "addr:full":"1814 Portage Trl Cuyahoga Falls OH 44223",
    "addr:housenumber":"1814",
    "addr:postcode":"44223",
    "addr:street":"Portage Trl",
    "iso:country":"US",
    "sg:address":"1814 Portage Trl",
    "sg:city":"Cuyahoga Falls",
    "sg:classifiers":[
        {
            "category":"Retail",
            "subcategory":"Self-service Laundry",
            "type":"Services"
        }
    ],
    "sg:phone":"+1 330 928 6678",
    "sg:postcode":"44223",
    "sg:province":"OH",
    "wof:name":"Fall's Wash N Dry",
    "wof:placetype":"venue"
},
  "geometry": {"coordinates":[-81.50577199999999,41.147937],"type":"Point"}
}