{
  "type": "Feature",
  "properties": {
    "addr:full": "341 Lake Ave Ashtabula OH 44004",
    "addr:housenumber": "341",
    "addr:postcode": "44004",
    "addr:street": "Lake Ave",
    "iso:country": "US",
    "sg:address": "341 Lake Ave",
    "sg:city": "Ashtabula",
    "sg:classifiers": [
      {
        "category": "Organizations",
        "subcategory": "Religious Organization",
        "type": "Services"
      }
    ],
    "sg:phone": "+1 440 964 8089",
    "sg:postcode": "44004",
    "sg:province": "OH",
    "sg:tags": [
      "church"
    ],
    "wof:name": "Holy Cross Charismatic",
    "wof:placetype": "venue"
  },
  "geometry": {"coordinates":[-80.804637,41.898336],"type":"Point"}
}
