{
  "type": "Feature",
  "properties": {
    "iso:country":"US",
    "sg:address":"6334 Wellington Pl",
    "sg:city":"Dayton",
    "sg:classifiers":[
        {
            "category":"Building & Trades",
            "subcategory":"Equipment Rental",
            "type":"Services"
        }
    ],
    "sg:phone":"+1 937 278 2000",
    "sg:postcode":"45424",
    "sg:province":"OH",
    "sg:tags":[
        "furniture"
    ],
    "wof:name":"Srkinnear  Inc",
    "wof:placetype":"venue"
},
  "geometry": {"coordinates":[-84.10906,39.827038],"type":"Point"}
}