{
  "type": "Feature",
  "properties": {
    "addr:full":"5120 Warrensville Center Rd Cleveland OH 44137",
    "addr:housenumber":"5120",
    "addr:postcode":"44137",
    "addr:street":"Warrensville Center Rd",
    "iso:country":"US",
    "sg:address":"5120 Warrensville Center Rd",
    "sg:city":"Cleveland",
    "sg:classifiers":[
        {
            "category":"Bars & Pubs",
            "type":"Food & Drink"
        }
    ],
    "sg:phone":"+1 216 332 1760",
    "sg:postcode":"44137",
    "sg:province":"OH",
    "sg:tags":[
        "club",
        "night"
    ],
    "wof:name":"Club Mapletree",
    "wof:placetype":"venue"
},
  "geometry": {"coordinates":[-81.53744,41.421753],"type":"Point"}
}