{
  "type": "Feature",
  "properties": {
    "addr:full": "3455 Granger Rd Akron OH 44333",
    "addr:housenumber": "3455",
    "addr:postcode": "44333",
    "addr:street": "Granger Rd",
    "iso:country": "US",
    "sg:address": "3455 Granger Rd",
    "sg:city": "Akron",
    "sg:classifiers": [
      {
        "category": "Health Services",
        "subcategory": "Doctor",
        "type": "Services"
      }
    ],
    "sg:phone": "+1 330 666 0035",
    "sg:postcode": "44333",
    "sg:province": "OH",
    "sg:tags": [
      "dentist"
    ],
    "wof:name": "Michael Van Der Kuyp DDS",
    "wof:placetype": "venue"
  },
  "geometry": {"coordinates":[-81.639843,41.158522],"type":"Point"}
}
