{
  "type": "Feature",
  "properties": {
    "addr:full":"1290 Co Rd 11 Bellefontaine OH 43311",
    "addr:housenumber":"1290;11",
    "addr:postcode":"43311",
    "addr:street":"Co Rd",
    "iso:country":"US",
    "sg:address":"1290 Co Rd 11",
    "sg:city":"Bellefontaine",
    "sg:classifiers":[
        {
            "category":"Building & Trades",
            "subcategory":"Landscaping Services",
            "type":"Services"
        }
    ],
    "sg:phone":"+1 937 592 5296",
    "sg:postcode":"43311",
    "sg:province":"OH",
    "sg:tags":[
        "landscape",
        "contractor"
    ],
    "wof:name":"Lyons Pro Lawn Care",
    "wof:placetype":"venue"
},
  "geometry": {"coordinates":[-83.784631,40.34813],"type":"Point"}
}