{
  "type": "Feature",
  "properties": {
    "addr:full": "2 Spring Knoll Dr Cincinnati OH 45227",
    "addr:housenumber": "2",
    "addr:postcode": "45227",
    "addr:street": "Spring Knoll Dr",
    "iso:country": "US",
    "sg:address": "2 Spring Knoll Dr",
    "sg:city": "Cincinnati",
    "sg:classifiers": [
      {
        "category": "Wholesale",
        "subcategory": "Stationery",
        "type": "Manufacturing \u0026 Wholesale Goods"
      }
    ],
    "sg:phone": "+1 513 321 4517",
    "sg:postcode": "45227",
    "sg:province": "OH",
    "sg:tags": [
      "room",
      "shipping",
      "supply"
    ],
    "wof:name": "Product \u0026 Packaging Design",
    "wof:placetype": "venue"
  },
  "geometry": {"coordinates":[-84.36066,39.144324],"type":"Point"}
}
