{
  "type": "Feature",
  "properties": {
    "addr:full":"77 S Cleveland Ave Mogadore OH 44260",
    "addr:housenumber":"77",
    "addr:postcode":"44260",
    "addr:street":"S Cleveland Ave",
    "iso:country":"US",
    "sg:address":"77 S Cleveland Ave",
    "sg:city":"Mogadore",
    "sg:classifiers":[
        {
            "category":"Food & Beverages",
            "subcategory":"Bakery",
            "type":"Retail Goods"
        }
    ],
    "sg:phone":"+1 330 628 0651",
    "sg:postcode":"44260",
    "sg:province":"OH",
    "wof:name":"Vincents Bakery",
    "wof:placetype":"venue"
},
  "geometry": {"coordinates":[-81.393203,41.050292],"type":"Point"}
}