{
  "type": "Feature",
  "properties": {
    "iso:country":"US",
    "sg:address":"7 Liberty St",
    "sg:city":"Berea",
    "sg:classifiers":[
        {
            "category":"Social Services",
            "subcategory":"Child Care",
            "type":"Services"
        }
    ],
    "sg:phone":"+1 440 234 3762",
    "sg:postcode":"44017",
    "sg:province":"OH",
    "wof:name":"Mary Hart Nursery School Inc",
    "wof:placetype":"venue"
},
  "geometry": {"coordinates":[-81.851816,41.371853],"type":"Point"}
}