{
  "type": "Feature",
  "properties": {
    "addr:full": "413 W Main St Crestline OH 44827",
    "addr:housenumber": "413",
    "addr:postcode": "44827",
    "addr:street": "W Main St",
    "iso:country": "US",
    "sg:address": "413 W Main St",
    "sg:city": "Crestline",
    "sg:classifiers": [
      {
        "category": "Insurance",
        "subcategory": "Insurance Agent",
        "type": "Services"
      }
    ],
    "sg:phone": "+1 419 683 1142",
    "sg:postcode": "44827",
    "sg:province": "OH",
    "wof:name": "New York Life",
    "wof:placetype": "venue"
  },
  "geometry": {"coordinates":[-82.740927,40.789094],"type":"Point"}
}
