{
  "type": "Feature",
  "properties": {
    "iso:country":"US",
    "sg:address":"2254 Scott St",
    "sg:city":"Napoleon",
    "sg:classifiers":[
        {
            "category":"Freight",
            "type":"Transportation"
        }
    ],
    "sg:phone":"+1 419 592 9030",
    "sg:postcode":"43545",
    "sg:province":"OH",
    "sg:tags":[
        "trucking"
    ],
    "wof:name":"Siebert Trucking LLC",
    "wof:placetype":"venue"
},
  "geometry": {"coordinates":[-84.13193800000001,41.405258],"type":"Point"}
}