{
  "type": "Feature",
  "properties": {
    "addr:full":"9 Mount Vernon Ave Mt Vernon OH 43050",
    "addr:housenumber":"9",
    "addr:postcode":"43050",
    "addr:street":"Mount Vernon Ave",
    "iso:country":"US",
    "sg:address":"9 Mount Vernon Ave",
    "sg:city":"Mt Vernon",
    "sg:classifiers":[
        {
            "category":"Professional",
            "subcategory":"Art Services",
            "type":"Services"
        }
    ],
    "sg:phone":"+1 740 392 3064",
    "sg:postcode":"43050",
    "sg:province":"OH",
    "sg:tags":[
        "graphic",
        "designer"
    ],
    "wof:name":"Malone Creative",
    "wof:placetype":"venue"
},
  "geometry": {"coordinates":[-82.484841,40.384807],"type":"Point"}
}