{
  "type": "Feature",
  "properties": {
    "iso:country":"US",
    "sg:address":"1441 King Ave",
    "sg:city":"Columbus",
    "sg:classifiers":[
        {
            "category":"Building & Trades",
            "subcategory":"Construction",
            "type":"Services"
        }
    ],
    "sg:phone":"+1 614 451 1194",
    "sg:postcode":"43212",
    "sg:province":"OH",
    "sg:tags":[
        "concrete",
        "contractor"
    ],
    "wof:name":"Tarini Cement",
    "wof:placetype":"venue"
},
  "geometry": {"coordinates":[-83.044595,39.991513],"type":"Point"}
}