{
  "type": "Feature",
  "properties": {
    "addr:full": "3848 Erie Ave SW Massillon OH 44646",
    "addr:housenumber": "3848",
    "addr:postcode": "44646",
    "addr:street": "Erie Ave Sw",
    "iso:country": "US",
    "sg:address": "3848 Erie Ave SW",
    "sg:city": "Massillon",
    "sg:classifiers": [
      {
        "category": "Manufacturing",
        "subcategory": "Petroleum Products",
        "type": "Manufacturing \u0026 Wholesale Goods"
      }
    ],
    "sg:phone": "+1 330 425 7861",
    "sg:postcode": "44646",
    "sg:province": "OH",
    "sg:tags": [
      "construction",
      "asphalt",
      "mfg"
    ],
    "wof:name": "Allied Corporation Inc",
    "wof:placetype": "venue"
  },
  "geometry": {"coordinates":[-81.516449,40.755417],"type":"Point"}
}
