{
  "type": "Feature",
  "properties": {
    "iso:country":"US",
    "sg:address":"3848 Erie Ave SW",
    "sg:city":"Massillon",
    "sg:classifiers":[
        {
            "category":"Manufacturing",
            "subcategory":"Petroleum Products",
            "type":"Manufacturing & Wholesale Goods"
        }
    ],
    "sg:phone":"+1 330 425 7861",
    "sg:postcode":"44646",
    "sg:province":"OH",
    "sg:tags":[
        "construction",
        "asphalt",
        "mfg"
    ],
    "wof:name":"Allied Corporation Inc",
    "wof:placetype":"venue"
},
  "geometry": {"coordinates":[-81.51644899999999,40.755417],"type":"Point"}
}