{
  "type": "Feature",
  "properties": {
    "addr:full": "690 Lakeview Plaza Blvd Columbus OH 43085",
    "addr:housenumber": "690",
    "addr:postcode": "43085",
    "addr:street": "Lakeview Plaza Blvd",
    "iso:country": "US",
    "sg:address": "690 Lakeview Plaza Blvd",
    "sg:city": "Columbus",
    "sg:classifiers": [
      {
        "category": "Professional",
        "subcategory": "Business Services",
        "type": "Services"
      }
    ],
    "sg:phone": "+1 614 847 7731",
    "sg:postcode": "43085",
    "sg:province": "OH",
    "sg:tags": [
      "process",
      "loan",
      "manages",
      "real estate",
      "payment"
    ],
    "wof:name": "Household Credit Services",
    "wof:placetype": "venue"
  },
  "geometry": {"coordinates":[-82.997623,40.11313],"type":"Point"}
}
