{
  "type": "Feature",
  "properties": {
    "iso:country":"US",
    "sg:address":"8837 Old Airport Hwy",
    "sg:city":"Holland",
    "sg:classifiers":[
        {
            "category":"Building & Trades",
            "subcategory":"Landscaping Services",
            "type":"Services"
        }
    ],
    "sg:phone":"+1 419 867 8823",
    "sg:postcode":"43528",
    "sg:province":"OH",
    "sg:tags":[
        "landscape",
        "contractor"
    ],
    "wof:name":"PJM Landscaping",
    "wof:placetype":"venue"
},
  "geometry": {"coordinates":[-83.75247299999999,41.610156],"type":"Point"}
}