{
  "type": "Feature",
  "properties": {
    "addr:full": "8837 Old Airport Hwy Holland OH 43528",
    "addr:housenumber": "8837",
    "addr:postcode": "43528",
    "addr:street": "Old Airport Hwy",
    "iso:country": "US",
    "sg:address": "8837 Old Airport Hwy",
    "sg:city": "Holland",
    "sg:classifiers": [
      {
        "category": "Building \u0026 Trades",
        "subcategory": "Landscaping Services",
        "type": "Services"
      }
    ],
    "sg:phone": "+1 419 867 8823",
    "sg:postcode": "43528",
    "sg:province": "OH",
    "sg:tags": [
      "landscape",
      "contractor"
    ],
    "wof:name": "PJM Landscaping",
    "wof:placetype": "venue"
  },
  "geometry": {"coordinates":[-83.752473,41.610156],"type":"Point"}
}
