{
  "type": "Feature",
  "properties": {
    "addr:full":"1482 John Gray Rd Fairfield OH 45014",
    "addr:housenumber":"1482",
    "addr:postcode":"45014",
    "addr:street":"John Gray Rd",
    "iso:country":"US",
    "sg:address":"1482 John Gray Rd",
    "sg:city":"Fairfield",
    "sg:classifiers":[
        {
            "category":"Building & Trades",
            "subcategory":"Plumbing",
            "type":"Services"
        }
    ],
    "sg:phone":"+1 513 602 3764",
    "sg:postcode":"45014",
    "sg:province":"OH",
    "sg:tags":[
        "contractor"
    ],
    "wof:name":"Mobiel Automotive AC",
    "wof:placetype":"venue"
},
  "geometry": {"coordinates":[-84.568208,39.308068],"type":"Point"}
}