{
  "type": "Feature",
  "properties": {
    "iso:country":"US",
    "sg:address":"2295 Lexington Ave",
    "sg:city":"Mansfield",
    "sg:classifiers":[
        {
            "category":"Recreation",
            "subcategory":"Amusement Park",
            "type":"Entertainment"
        },
        {
            "category":"Government",
            "subcategory":"Office",
            "type":"Public Place"
        }
    ],
    "sg:phone":"+1 419 884 3764",
    "sg:postcode":"44907",
    "sg:province":"OH",
    "sg:tags":[
        "executive",
        "park"
    ],
    "wof:name":"Gorman Nature Center",
    "wof:placetype":"venue"
},
  "geometry": {"coordinates":[-82.559628,40.699661],"type":"Point"}
}