{
  "type": "Feature",
  "properties": {
    "addr:full":"4400 Shakertown Rd Dayton OH 45430",
    "addr:housenumber":"4400",
    "addr:postcode":"45430",
    "addr:street":"Shakertown Rd",
    "iso:country":"US",
    "sg:address":"4400 Shakertown Rd",
    "sg:city":"Dayton",
    "sg:classifiers":[
        {
            "category":"Organizations",
            "subcategory":"Religious Organization",
            "type":"Services"
        }
    ],
    "sg:phone":"+1 937 429 0510",
    "sg:postcode":"45430",
    "sg:province":"OH",
    "sg:tags":[
        "church"
    ],
    "sg:website":"www.qac-ohio.org",
    "wof:name":"Queen Of Apostles Catholic Ch",
    "wof:placetype":"venue"
},
  "geometry": {"coordinates":[-84.10442999999999,39.717114],"type":"Point"}
}