{
  "type": "Feature",
  "properties": {
    "addr:full": "16771 Twp Rd 178 Bellevue OH 44811",
    "addr:housenumber": "178",
    "addr:postcode": "16771;44811",
    "addr:street": "Twp Rd",
    "iso:country": "US",
    "sg:address": "16771 Twp Rd 178",
    "sg:city": "Bellevue",
    "sg:classifiers": [
      {
        "category": "Freight",
        "type": "Transportation"
      }
    ],
    "sg:phone": "+1 419 483 3135",
    "sg:postcode": "44811",
    "sg:province": "OH",
    "sg:tags": [
      "operator",
      "local",
      "trucking"
    ],
    "wof:name": "S M Swartz Trucking \u0026 Excvtg",
    "wof:placetype": "venue"
  },
  "geometry": {"coordinates":[-82.844157,41.226016],"type":"Point"}
}
