{
  "type": "Feature",
  "properties": {
    "iso:country":"US",
    "sg:address":"16771 Twp Rd 178",
    "sg:city":"Bellevue",
    "sg:classifiers":[
        {
            "category":"Freight",
            "type":"Transportation"
        }
    ],
    "sg:phone":"+1 419 483 3135",
    "sg:postcode":"44811",
    "sg:province":"OH",
    "sg:tags":[
        "operator",
        "local",
        "trucking"
    ],
    "wof:name":"S M Swartz Trucking & Excvtg",
    "wof:placetype":"venue"
},
  "geometry": {"coordinates":[-82.844157,41.226016],"type":"Point"}
}