{
  "type": "Feature",
  "properties": {
    "addr:full": "168 Brookfield Rd Avon Lake OH 44012",
    "addr:housenumber": "168",
    "addr:postcode": "44012",
    "addr:street": "Brookfield Rd",
    "iso:country": "US",
    "sg:address": "168 Brookfield Rd",
    "sg:city": "Avon Lake",
    "sg:classifiers": [
      {
        "category": "Insurance",
        "subcategory": "Life Insurance",
        "type": "Services"
      }
    ],
    "sg:phone": "+1 440 933 3975",
    "sg:postcode": "44012",
    "sg:province": "OH",
    "sg:tags": [
      "carrier",
      "carrie"
    ],
    "wof:name": "Kathleen A Terrell",
    "wof:placetype": "venue"
  },
  "geometry": {"coordinates":[-82.023622,41.507738],"type":"Point"}
}
