{
  "type": "Feature",
  "properties": {
    "addr:full": "8673 S Cadet Dr Galloway OH 43119",
    "addr:housenumber": "8673",
    "addr:postcode": "43119",
    "addr:street": "S Cadet Dr",
    "iso:country": "US",
    "sg:address": "8673 S Cadet Dr",
    "sg:city": "Galloway",
    "sg:classifiers": [
      {
        "category": "Professional",
        "subcategory": "Art Services",
        "type": "Services"
      }
    ],
    "sg:phone": "+1 614 878 9782",
    "sg:postcode": "43119",
    "sg:province": "OH",
    "sg:tags": [
      "commercial",
      "design",
      "publishing"
    ],
    "wof:name": "Probe Publishing",
    "wof:placetype": "venue"
  },
  "geometry": {"coordinates":[-83.233264,39.96379],"type":"Point"}
}
