{
  "type": "Feature",
  "properties": {
    "addr:full":"5580 Moser Rd Defiance OH 43512",
    "addr:housenumber":"5580",
    "addr:postcode":"43512",
    "addr:street":"Moser Rd",
    "iso:country":"US",
    "sg:address":"5580 Moser Rd",
    "sg:city":"Defiance",
    "sg:classifiers":[
        {
            "category":"Organizations",
            "subcategory":"Religious Organization",
            "type":"Services"
        }
    ],
    "sg:phone":"+1 419 497 3122",
    "sg:postcode":"43512",
    "sg:province":"OH",
    "wof:name":"St Michaels Church",
    "wof:placetype":"venue"
},
  "geometry": {"coordinates":[-84.304661,41.360498],"type":"Point"}
}