{
  "type": "Feature",
  "properties": {
    "addr:full":"107 Seminary Ave Dayton OH 45403",
    "addr:housenumber":"107",
    "addr:postcode":"45403",
    "addr:street":"Seminary Ave",
    "iso:country":"US",
    "sg:address":"107 Seminary Ave",
    "sg:city":"Dayton",
    "sg:classifiers":[
        {
            "category":"Retail",
            "subcategory":"Auto Repair",
            "type":"Services"
        }
    ],
    "sg:phone":"+1 937 252 3356",
    "sg:postcode":"45403",
    "sg:province":"OH",
    "sg:tags":[
        "wrecker"
    ],
    "wof:name":"Hollis Towing",
    "wof:placetype":"venue"
},
  "geometry": {"coordinates":[-84.14635,39.754755],"type":"Point"}
}