{
  "type": "Feature",
  "properties": {
    "addr:full": "4062 Belden Village St NW Canton OH 44718",
    "addr:housenumber": "4062",
    "addr:postcode": "44718",
    "addr:street": "Belden Village St Nw",
    "iso:country": "US",
    "sg:address": "4062 Belden Village St NW",
    "sg:city": "Canton",
    "sg:classifiers": [
      {
        "category": "Utilities",
        "subcategory": "Mobile Phone",
        "type": "Services"
      }
    ],
    "sg:phone": "+1 330 493 2969",
    "sg:postcode": "44718",
    "sg:province": "OH",
    "sg:tags": [
      "telephone",
      "cellular"
    ],
    "wof:name": "Cingular Wireless",
    "wof:placetype": "venue"
  },
  "geometry": {"coordinates":[-81.426481,40.855173],"type":"Point"}
}
