{
  "type": "Feature",
  "properties": {
    "addr:full":"18370 S Miles Rd Cleveland OH 44128",
    "addr:housenumber":"18370",
    "addr:postcode":"44128",
    "addr:street":"S Miles Rd",
    "iso:country":"US",
    "sg:address":"18370 S Miles Rd",
    "sg:city":"Cleveland",
    "sg:classifiers":[
        {
            "category":"Wholesale",
            "subcategory":"Durable Goods & Equipment",
            "type":"Manufacturing & Wholesale Goods"
        }
    ],
    "sg:phone":"+1 216 475 5511",
    "sg:postcode":"44128",
    "sg:province":"OH",
    "sg:tags":[
        "professional"
    ],
    "sg:website":"www.future-light.com",
    "wof:name":"Future Light Inc",
    "wof:placetype":"venue"
},
  "geometry": {"coordinates":[-81.54805899999999,41.430422],"type":"Point"}
}