{
  "type": "Feature",
  "properties": {
    "addr:full": "227 N Market St East Palestine OH 44413",
    "addr:housenumber": "227",
    "addr:postcode": "44413",
    "addr:street": "N Market St",
    "iso:country": "US",
    "sg:address": "227 N Market St",
    "sg:city": "East Palestine",
    "sg:classifiers": [
      {
        "category": "Restaurant",
        "type": "Food \u0026 Drink"
      }
    ],
    "sg:phone": "+1 330 426 3354",
    "sg:postcode": "44413",
    "sg:province": "OH",
    "sg:tags": [
      "eating"
    ],
    "wof:name": "Napoli Pizza",
    "wof:placetype": "venue"
  },
  "geometry": {"coordinates":[-80.539945,40.836036],"type":"Point"}
}
