{
  "type": "Feature",
  "properties": {
    "addr:full":"1246 Nilles Rd Fairfield OH 45014",
    "addr:housenumber":"1246",
    "addr:postcode":"45014",
    "addr:street":"Nilles Rd",
    "iso:country":"US",
    "sg:address":"1246 Nilles Rd",
    "sg:city":"Fairfield",
    "sg:classifiers":[
        {
            "category":"Freight",
            "type":"Transportation"
        }
    ],
    "sg:phone":"+1 513 542 5225",
    "sg:postcode":"45014",
    "sg:province":"OH",
    "wof:name":"Justice Traffic Svc",
    "wof:placetype":"venue"
},
  "geometry": {"coordinates":[-84.538752,39.337558],"type":"Point"}
}