{
  "type": "Feature",
  "properties": {
    "iso:country":"US",
    "sg:address":"6837 Hogpath Rd",
    "sg:city":"Greenville",
    "sg:phone":"+1 937 548 8588",
    "sg:postcode":"45331",
    "sg:province":"OH",
    "sg:tags":[
        "farm",
        "soybean"
    ],
    "wof:name":"Wayne Shafer",
    "wof:placetype":"venue"
},
  "geometry": {"coordinates":[-84.55143700000001,40.048988],"type":"Point"}
}