{
  "type": "Feature",
  "properties": {
    "addr:full": "6837 Hogpath Rd Greenville OH 45331",
    "addr:housenumber": "6837",
    "addr:postcode": "45331",
    "addr:street": "Hogpath Rd",
    "iso:country": "US",
    "sg:address": "6837 Hogpath Rd",
    "sg:city": "Greenville",
    "sg:phone": "+1 937 548 8588",
    "sg:postcode": "45331",
    "sg:province": "OH",
    "sg:tags": [
      "farm",
      "soybean"
    ],
    "wof:name": "Wayne Shafer",
    "wof:placetype": "venue"
  },
  "geometry": {"coordinates":[-84.551437,40.048988],"type":"Point"}
}
