{
  "type": "Feature",
  "properties": {
    "addr:full": "7450 S Mason Montgomery Rd Mason OH 45040",
    "addr:housenumber": "7450",
    "addr:postcode": "45040",
    "addr:street": "S Mason Montgomery Rd",
    "iso:country": "US",
    "sg:address": "7450 S Mason Montgomery Rd",
    "sg:city": "Mason",
    "sg:classifiers": [
      {
        "category": "Health Services",
        "subcategory": "Doctor",
        "type": "Services"
      }
    ],
    "sg:phone": "+1 513 229 8010",
    "sg:postcode": "45040",
    "sg:province": "OH",
    "sg:tags": [
      "physician",
      "surgeon"
    ],
    "wof:name": "David Aichholz MD",
    "wof:placetype": "venue"
  },
  "geometry": {"coordinates":[-84.311914,39.329485],"type":"Point"}
}
