{
  "type": "Feature",
  "properties": {
    "iso:country":"US",
    "sg:address":"13520 Shirley Dr",
    "sg:city":"Painesville",
    "sg:classifiers":[
        {
            "category":"Freight",
            "type":"Transportation"
        }
    ],
    "sg:phone":"+1 440 254 0506",
    "sg:postcode":"44077",
    "sg:province":"OH",
    "sg:tags":[
        "commercial",
        "storage"
    ],
    "wof:name":"Fairport Mini Storage LTD",
    "wof:placetype":"venue"
},
  "geometry": {"coordinates":[-81.152224,41.698398],"type":"Point"}
}