{
  "type": "Feature",
  "properties": {
    "addr:full": "602 Robinson Ave Piqua OH 45356",
    "addr:housenumber": "602",
    "addr:postcode": "45356",
    "addr:street": "Robinson Ave",
    "iso:country": "US",
    "sg:address": "602 Robinson Ave",
    "sg:city": "Piqua",
    "sg:classifiers": [
      {
        "category": "Home \u0026 Garden",
        "subcategory": "Garden Supply",
        "type": "Retail Goods"
      }
    ],
    "sg:phone": "+1 937 773 2147",
    "sg:postcode": "45356",
    "sg:province": "OH",
    "sg:tags": [
      "center"
    ],
    "wof:name": "Piqua's Garden Place",
    "wof:placetype": "venue"
  },
  "geometry": {"coordinates":[-84.250322,40.158971],"type":"Point"}
}
