{
  "type": "Feature",
  "properties": {
    "iso:country":"US",
    "sg:address":"12112 Village Woods Dr",
    "sg:city":"Cincinnati",
    "sg:classifiers":[
        {
            "category":"Bars & Pubs",
            "type":"Food & Drink"
        }
    ],
    "sg:phone":"+1 513 793 2440",
    "sg:postcode":"45241",
    "sg:province":"OH",
    "wof:name":"Old Saloon",
    "wof:placetype":"venue"
},
  "geometry": {"coordinates":[-84.38663200000001,39.294072],"type":"Point"}
}