{
  "type": "Feature",
  "properties": {
    "addr:full": "12112 Village Woods Dr Cincinnati OH 45241",
    "addr:housenumber": "12112",
    "addr:postcode": "45241",
    "addr:street": "Village Woods Dr",
    "iso:country": "US",
    "sg:address": "12112 Village Woods Dr",
    "sg:city": "Cincinnati",
    "sg:classifiers": [
      {
        "category": "Bars \u0026 Pubs",
        "type": "Food \u0026 Drink"
      }
    ],
    "sg:phone": "+1 513 793 2440",
    "sg:postcode": "45241",
    "sg:province": "OH",
    "wof:name": "Old Saloon",
    "wof:placetype": "venue"
  },
  "geometry": {"coordinates":[-84.386632,39.294072],"type":"Point"}
}
