{
  "type": "Feature",
  "properties": {
    "iso:country":"US",
    "sg:address":"1099 Ferris Rd",
    "sg:city":"Amelia",
    "sg:classifiers":[
        {
            "category":"Building & Trades",
            "subcategory":"Construction",
            "type":"Services"
        }
    ],
    "sg:phone":"+1 513 752 4947",
    "sg:postcode":"45102",
    "sg:province":"OH",
    "sg:tags":[
        "house",
        "carpentry",
        "r",
        "contractor"
    ],
    "wof:name":"Beavers & Thomas Construction",
    "wof:placetype":"venue"
},
  "geometry": {"coordinates":[-84.2575,39.055057],"type":"Point"}
}