{
  "type": "Feature",
  "properties": {
    "addr:full":"111 S Downing St Piqua OH 45356",
    "addr:housenumber":"111",
    "addr:postcode":"45356",
    "addr:street":"S Downing St",
    "iso:country":"US",
    "sg:address":"111 S Downing St",
    "sg:city":"Piqua",
    "sg:classifiers":[
        {
            "category":"Retail",
            "subcategory":"Laundry & Dry Cleaning",
            "type":"Services"
        }
    ],
    "sg:phone":"+1 937 773 9034",
    "sg:postcode":"45356",
    "sg:province":"OH",
    "sg:tags":[
        "cleaners"
    ],
    "wof:name":"Sunset Cleaners",
    "wof:placetype":"venue"
},
  "geometry": {"coordinates":[-84.242482,40.145219],"type":"Point"}
}