{
  "type": "Feature",
  "properties": {
    "iso:country":"US",
    "sg:address":"1026 King St",
    "sg:city":"Lancaster",
    "sg:classifiers":[
        {
            "category":"Building & Trades",
            "subcategory":"Construction",
            "type":"Services"
        }
    ],
    "sg:phone":"+1 740 653 7240",
    "sg:postcode":"43130",
    "sg:province":"OH",
    "sg:tags":[
        "hanging",
        "painter",
        "contractor"
    ],
    "wof:name":"Yates Service Company",
    "wof:placetype":"venue"
},
  "geometry": {"coordinates":[-82.582049,39.716914],"type":"Point"}
}