{
  "type": "Feature",
  "properties": {
    "addr:full":"216 E State St Trenton OH 45067",
    "addr:housenumber":"216",
    "addr:postcode":"45067",
    "addr:street":"E State St",
    "iso:country":"US",
    "sg:address":"216 E State St",
    "sg:city":"Trenton",
    "sg:classifiers":[
        {
            "category":"Shopping",
            "subcategory":"Florist",
            "type":"Retail Goods"
        }
    ],
    "sg:phone":"+1 513 988 0228",
    "sg:postcode":"45067",
    "sg:province":"OH",
    "wof:name":"Country Corner",
    "wof:placetype":"venue"
},
  "geometry": {"coordinates":[-84.45509300000001,39.481141],"type":"Point"}
}