{
  "type": "Feature",
  "properties": {
    "addr:full":"6718 N Ridge Rd Madison OH 44057",
    "addr:housenumber":"6718",
    "addr:postcode":"44057",
    "addr:street":"N Ridge Rd",
    "iso:country":"US",
    "sg:address":"6718 N Ridge Rd",
    "sg:city":"Madison",
    "sg:classifiers":[
        {
            "category":"Sports & Exercise",
            "subcategory":"Gym",
            "type":"Entertainment"
        }
    ],
    "sg:phone":"+1 440 428 5730",
    "sg:postcode":"44057",
    "sg:province":"OH",
    "sg:tags":[
        "club",
        "health",
        "studio",
        "gymnasium"
    ],
    "wof:name":"Curves",
    "wof:placetype":"venue"
},
  "geometry": {"coordinates":[-81.047168,41.8019],"type":"Point"}
}