{
  "type": "Feature",
  "properties": {
    "addr:full":"3155 Canfield Rd Youngstown OH 44511",
    "addr:housenumber":"3155",
    "addr:postcode":"44511",
    "addr:street":"Canfield Rd",
    "iso:country":"US",
    "sg:address":"3155 Canfield Rd",
    "sg:city":"Youngstown",
    "sg:classifiers":[
        {
            "category":"Professional",
            "subcategory":"Research",
            "type":"Services"
        },
        {
            "category":"Professional",
            "subcategory":"Management & Consulting",
            "type":"Services"
        }
    ],
    "sg:phone":"+1 330 793 8018",
    "sg:postcode":"44511",
    "sg:province":"OH",
    "sg:tags":[
        "environmental",
        "ecological",
        "consultant"
    ],
    "wof:name":"J L T Research Inc",
    "wof:placetype":"venue"
},
  "geometry": {"coordinates":[-80.703502,41.064038],"type":"Point"}
}