{
  "type": "Feature",
  "properties": {
    "iso:country":"US",
    "sg:address":"6630 Ridge Rd",
    "sg:city":"Cleveland",
    "sg:classifiers":[
        {
            "category":"Autos & Motor Vehicles",
            "subcategory":"Fuel & Gas Station",
            "type":"Retail Goods"
        }
    ],
    "sg:phone":"+1 440 886 4298",
    "sg:postcode":"44129",
    "sg:province":"OH",
    "sg:tags":[
        "oil"
    ],
    "wof:name":"Ridge & Ridgewood Shell Food",
    "wof:placetype":"venue"
},
  "geometry": {"coordinates":[-81.734757,41.383375],"type":"Point"}
}