{
  "type": "Feature",
  "properties": {
    "addr:full": "6630 Ridge Rd Cleveland OH 44129",
    "addr:housenumber": "6630",
    "addr:postcode": "44129",
    "addr:street": "Ridge Rd",
    "iso:country": "US",
    "sg:address": "6630 Ridge Rd",
    "sg:city": "Cleveland",
    "sg:classifiers": [
      {
        "category": "Autos \u0026 Motor Vehicles",
        "subcategory": "Fuel \u0026 Gas Station",
        "type": "Retail Goods"
      }
    ],
    "sg:phone": "+1 440 886 4298",
    "sg:postcode": "44129",
    "sg:province": "OH",
    "sg:tags": [
      "oil"
    ],
    "wof:name": "Ridge \u0026 Ridgewood Shell Food",
    "wof:placetype": "venue"
  },
  "geometry": {"coordinates":[-81.734757,41.383375],"type":"Point"}
}
