{
  "type": "Feature",
  "properties": {
    "addr:full": "303 Oak St Continental OH 45831",
    "addr:housenumber": "303",
    "addr:postcode": "45831",
    "addr:street": "Oak St",
    "iso:country": "US",
    "sg:address": "303 Oak St",
    "sg:city": "Continental",
    "sg:classifiers": [
      {
        "category": "Shopping",
        "subcategory": "Discount \u0026 Variety Stores",
        "type": "Retail Goods"
      }
    ],
    "sg:phone": "+1 419 596 3752",
    "sg:postcode": "45831",
    "sg:province": "OH",
    "sg:tags": [
      "merchandise",
      "general"
    ],
    "wof:name": "Trading Post Inc",
    "wof:placetype": "venue"
  },
  "geometry": {"coordinates":[-84.270861,41.097139],"type":"Point"}
}
