{
  "type": "Feature",
  "properties": {
    "iso:country":"US",
    "sg:address":"2411 Commercial Ave",
    "sg:city":"Mingo Junction",
    "sg:classifiers":[
        {
            "category":"Personal",
            "subcategory":"Barber",
            "type":"Services"
        }
    ],
    "sg:phone":"+1 740 535 0201",
    "sg:postcode":"43938",
    "sg:province":"OH",
    "wof:name":"Sunset Barber Shop",
    "wof:placetype":"venue"
},
  "geometry": {"coordinates":[-80.618072,40.302637],"type":"Point"}
}