{
  "type": "Feature",
  "properties": {
    "addr:full":"1300 Flagship Dr Perrysburg OH 43551",
    "addr:housenumber":"1300",
    "addr:postcode":"43551",
    "addr:street":"Flagship Dr",
    "iso:country":"US",
    "sg:address":"1300 Flagship Dr",
    "sg:city":"Perrysburg",
    "sg:classifiers":[
        {
            "category":"Home & Garden",
            "subcategory":"Furniture",
            "type":"Retail Goods"
        }
    ],
    "sg:phone":"+1 419 873 9500",
    "sg:postcode":"43551",
    "sg:province":"OH",
    "sg:tags":[
        "top",
        "counter"
    ],
    "wof:name":"Cutting Edge Countertops Inc",
    "wof:placetype":"venue"
},
  "geometry": {"coordinates":[-83.644586,41.536345],"type":"Point"}
}