{
  "type": "Feature",
  "properties": {
    "iso:country":"US",
    "sg:address":"100 Public Sq",
    "sg:city":"Greenville",
    "sg:classifiers":[
        {
            "category":"Government",
            "subcategory":"Office",
            "type":"Public Place"
        }
    ],
    "sg:phone":"+1 937 548 1103",
    "sg:postcode":"45331",
    "sg:province":"OH",
    "sg:tags":[
        "village"
    ],
    "wof:name":"Greenville Safety Director",
    "wof:placetype":"venue"
},
  "geometry": {"coordinates":[-84.63399,40.102042],"type":"Point"}
}