{
  "type": "Feature",
  "properties": {
    "addr:full": "128 E US Hwy 22 and 3 Maineville OH 45039",
    "addr:housenumber": "128",
    "addr:postcode": "45039",
    "addr:street": "E Us Hwy 22 And 3",
    "iso:country": "US",
    "sg:address": "128 E US Hwy 22 and 3",
    "sg:city": "Maineville",
    "sg:classifiers": [
      {
        "category": "Autos \u0026 Motor Vehicles",
        "subcategory": "Automobile Sales",
        "type": "Retail Goods"
      }
    ],
    "sg:phone": "+1 513 774 8702",
    "sg:postcode": "45039",
    "sg:province": "OH",
    "sg:tags": [
      "car",
      "dealer"
    ],
    "wof:name": "Landen Motors North",
    "wof:placetype": "venue"
  },
  "geometry": {"coordinates":[-84.214582,39.341532],"type":"Point"}
}
