{
  "type": "Feature",
  "properties": {
    "addr:full": "3055 Arlington Ave Toledo OH 43614",
    "addr:housenumber": "3055",
    "addr:postcode": "43614",
    "addr:street": "Arlington Ave",
    "iso:country": "US",
    "sg:address": "3055 Arlington Ave",
    "sg:city": "Toledo",
    "sg:classifiers": [
      {
        "category": "Shopping",
        "subcategory": "Books",
        "type": "Retail Goods"
      }
    ],
    "sg:phone": "+1 419 383 4216",
    "sg:postcode": "43614",
    "sg:province": "OH",
    "sg:tags": [
      "dealer"
    ],
    "wof:name": "Medical College Of Ohio Book",
    "wof:placetype": "venue"
  },
  "geometry": {"coordinates":[-83.618697,41.620869],"type":"Point"}
}
