{
  "type": "Feature",
  "properties": {
    "addr:full": "2035 Barrows St Toledo OH 43613",
    "addr:housenumber": "2035",
    "addr:postcode": "43613",
    "addr:street": "Barrows St",
    "iso:country": "US",
    "sg:address": "2035 Barrows St",
    "sg:city": "Toledo",
    "sg:classifiers": [
      {
        "category": "Home \u0026 Garden",
        "subcategory": "Building Materials",
        "type": "Retail Goods"
      },
      {
        "category": "Building \u0026 Trades",
        "subcategory": "Construction",
        "type": "Services"
      }
    ],
    "sg:phone": "+1 419 472 0055",
    "sg:postcode": "43613",
    "sg:province": "OH",
    "sg:tags": [
      "painter"
    ],
    "wof:name": "Ken's Wallpaper \u0026 Paint",
    "wof:placetype": "venue"
  },
  "geometry": {"coordinates":[-83.593602,41.689276],"type":"Point"}
}
