{
  "type": "Feature",
  "properties": {
    "addr:full": "9800 E Washington St Chagrin Falls OH 44023",
    "addr:housenumber": "9800",
    "addr:postcode": "44023",
    "addr:street": "E Washington St",
    "iso:country": "US",
    "sg:address": "9800 E Washington St",
    "sg:city": "Chagrin Falls",
    "sg:classifiers": [
      {
        "category": "Restaurant",
        "type": "Food \u0026 Drink"
      }
    ],
    "sg:phone": "+1 440 543 8191",
    "sg:postcode": "44023",
    "sg:province": "OH",
    "sg:tags": [
      "pizza"
    ],
    "wof:name": "Angie's Restaurant \u0026 Pizzeria",
    "wof:placetype": "venue"
  },
  "geometry": {"coordinates":[-81.296204,41.395199],"type":"Point"}
}
