{
  "type": "Feature",
  "properties": {
    "addr:full":"132 N Elmwood Ave Medina OH 44256",
    "addr:housenumber":"132",
    "addr:postcode":"44256",
    "addr:street":"N Elmwood Ave",
    "iso:country":"US",
    "sg:address":"132 N Elmwood Ave",
    "sg:city":"Medina",
    "sg:classifiers":[
        {
            "category":"Government",
            "subcategory":"Office",
            "type":"Public Place"
        }
    ],
    "sg:phone":"+1 330 722 9026",
    "sg:postcode":"44256",
    "sg:province":"OH",
    "sg:tags":[
        "city",
        "program"
    ],
    "wof:name":"City Of Medina Sanitation Dept",
    "wof:placetype":"venue"
},
  "geometry": {"coordinates":[-81.86595699999999,41.139622],"type":"Point"}
}