{
  "type": "Feature",
  "properties": {
    "addr:full":"351 Highland Ave Cambridge OH 43725",
    "addr:housenumber":"351",
    "addr:postcode":"43725",
    "addr:street":"Highland Ave",
    "iso:country":"US",
    "sg:address":"351 Highland Ave",
    "sg:city":"Cambridge",
    "sg:classifiers":[
        {
            "category":"Manufacturing",
            "subcategory":"Printing",
            "type":"Manufacturing & Wholesale Goods"
        }
    ],
    "sg:phone":"+1 740 432 2133",
    "sg:postcode":"43725",
    "sg:province":"OH",
    "sg:tags":[
        "multimedia"
    ],
    "wof:name":"Adelphia",
    "wof:placetype":"venue"
},
  "geometry": {"coordinates":[-81.577432,40.028688],"type":"Point"}
}