{
  "type": "Feature",
  "properties": {
    "addr:full":"361 W 3rd St Dayton OH 45402",
    "addr:housenumber":"361",
    "addr:postcode":"45402",
    "addr:street":"W 3Rd St",
    "iso:country":"US",
    "sg:address":"361 W 3rd St",
    "sg:city":"Dayton",
    "sg:classifiers":[
        {
            "category":"Government",
            "subcategory":"Office",
            "type":"Public Place"
        }
    ],
    "sg:phone":"+1 937 225 4156",
    "sg:postcode":"45402",
    "sg:province":"OH",
    "wof:name":"Montgomery Cnty Coroner Office",
    "wof:placetype":"venue"
},
  "geometry": {"coordinates":[-84.197712,39.758642],"type":"Point"}
}