{
  "type": "Feature",
  "properties": {
    "addr:full": "6371 River Styx Rd Medina OH 44256",
    "addr:housenumber": "6371",
    "addr:postcode": "44256",
    "addr:street": "River Styx Rd",
    "iso:country": "US",
    "sg:address": "6371 River Styx Rd",
    "sg:city": "Medina",
    "sg:classifiers": [
      {
        "category": "Utilities",
        "type": "Services"
      }
    ],
    "sg:phone": "+1 330 723 7663",
    "sg:postcode": "44256",
    "sg:province": "OH",
    "sg:tags": [
      "sanitary",
      "business"
    ],
    "wof:name": "Ponds Beautiful",
    "wof:placetype": "venue"
  },
  "geometry": {"coordinates":[-81.803828,41.100279],"type":"Point"}
}
