{
  "type": "Feature",
  "properties": {
    "iso:country":"US",
    "sg:address":"226 Fulton St",
    "sg:city":"Port Clinton",
    "sg:classifiers":[
        {
            "category":"Personal",
            "subcategory":"Barber",
            "type":"Services"
        }
    ],
    "sg:phone":"+1 419 734 4242",
    "sg:postcode":"43452",
    "sg:province":"OH",
    "wof:name":"Hair Doc",
    "wof:placetype":"venue"
},
  "geometry": {"coordinates":[-82.933898,41.510997],"type":"Point"}
}