{
  "type": "Feature",
  "properties": {
    "addr:full": "2130 Cleveland Ave NW Canton OH 44709",
    "addr:housenumber": "2130",
    "addr:postcode": "44709",
    "addr:street": "Cleveland Ave Nw",
    "iso:country": "US",
    "sg:address": "2130 Cleveland Ave NW",
    "sg:city": "Canton",
    "sg:classifiers": [
      {
        "category": "Autos \u0026 Motor Vehicles",
        "subcategory": "Fuel \u0026 Gas Station",
        "type": "Retail Goods"
      }
    ],
    "sg:phone": "+1 330 452 7415",
    "sg:postcode": "44709",
    "sg:province": "OH",
    "sg:tags": [
      "oil"
    ],
    "wof:name": "Northcoast Oil",
    "wof:placetype": "venue"
  },
  "geometry": {"coordinates":[-81.382459,40.821565],"type":"Point"}
}
