{
  "type": "Feature",
  "properties": {
    "iso:country":"US",
    "sg:address":"102 Shady Ln",
    "sg:city":"Marietta",
    "sg:classifiers":[
        {
            "category":"Shopping",
            "type":"Retail Goods"
        }
    ],
    "sg:phone":"+1 740 373 1005",
    "sg:postcode":"45750",
    "sg:province":"OH",
    "sg:tags":[
        "cosmetic",
        "perfume"
    ],
    "wof:name":"Mary Kay Cosmetics",
    "wof:placetype":"venue"
},
  "geometry": {"coordinates":[-81.382558,39.384955],"type":"Point"}
}