{
  "type": "Feature",
  "properties": {
    "addr:full": "102 Shady Ln Marietta OH 45750",
    "addr:housenumber": "102",
    "addr:postcode": "45750",
    "addr:street": "Shady Ln",
    "iso:country": "US",
    "sg:address": "102 Shady Ln",
    "sg:city": "Marietta",
    "sg:classifiers": [
      {
        "category": "Shopping",
        "type": "Retail Goods"
      }
    ],
    "sg:phone": "+1 740 373 1005",
    "sg:postcode": "45750",
    "sg:province": "OH",
    "sg:tags": [
      "cosmetic",
      "perfume"
    ],
    "wof:name": "Mary Kay Cosmetics",
    "wof:placetype": "venue"
  },
  "geometry": {"coordinates":[-81.382558,39.384955],"type":"Point"}
}
