{
  "type": "Feature",
  "properties": {
    "addr:full":"9501 Colerain Ave Cincinnati OH 45251",
    "addr:housenumber":"9501",
    "addr:postcode":"45251",
    "addr:street":"Colerain Ave",
    "iso:country":"US",
    "sg:address":"9501 Colerain Ave",
    "sg:city":"Cincinnati",
    "sg:classifiers":[
        {
            "category":"Shopping",
            "subcategory":"Jewelry",
            "type":"Retail Goods"
        }
    ],
    "sg:phone":"+1 513 923 1600",
    "sg:postcode":"45251",
    "sg:province":"OH",
    "sg:tags":[
        "jeweler"
    ],
    "wof:name":"Austin 925",
    "wof:placetype":"venue"
},
  "geometry": {"coordinates":[-84.59504699999999,39.243543],"type":"Point"}
}