{
  "type": "Feature",
  "properties": {
    "iso:country":"US",
    "sg:address":"110 Poland Ave",
    "sg:city":"Struthers",
    "sg:classifiers":[
        {
            "category":"Social Services",
            "subcategory":"Child Care",
            "type":"Services"
        }
    ],
    "sg:phone":"+1 330 755 6519",
    "sg:postcode":"44471",
    "sg:province":"OH",
    "wof:name":"Bear Hugs Child Care & Nursery",
    "wof:placetype":"venue"
},
  "geometry": {"coordinates":[-80.591692,41.053972],"type":"Point"}
}