{
  "type": "Feature",
  "properties": {
    "iso:country":"US",
    "sg:address":"122 S Main St",
    "sg:city":"Celina",
    "sg:classifiers":[
        {
            "category":"Manufacturing",
            "subcategory":"Apparel",
            "type":"Manufacturing & Wholesale Goods"
        }
    ],
    "sg:phone":"+1 419 584 1500",
    "sg:postcode":"45822",
    "sg:province":"OH",
    "wof:name":"Corporate Image",
    "wof:placetype":"venue"
},
  "geometry": {"coordinates":[-84.570723,40.548784],"type":"Point"}
}