{
  "type": "Feature",
  "properties": {
    "addr:full":"9556 Hoose Rd Mentor OH 44060",
    "addr:housenumber":"9556",
    "addr:postcode":"44060",
    "addr:street":"Hoose Rd",
    "iso:country":"US",
    "sg:address":"9556 Hoose Rd",
    "sg:city":"Mentor",
    "sg:classifiers":[
        {
            "category":"Building & Trades",
            "subcategory":"Construction",
            "type":"Services"
        }
    ],
    "sg:phone":"+1 440 205 8615",
    "sg:postcode":"44060",
    "sg:province":"OH",
    "sg:tags":[
        "house"
    ],
    "wof:name":"Chesterfield Const",
    "wof:placetype":"venue"
},
  "geometry": {"coordinates":[-81.297704,41.655317],"type":"Point"}
}