{
  "type": "Feature",
  "properties": {
    "iso:country":"US",
    "sg:address":"4330 Colby Ave",
    "sg:city":"Columbus",
    "sg:classifiers":[
        {
            "category":"Taxi",
            "type":"Transportation"
        }
    ],
    "sg:phone":"+1 614 236 4444",
    "sg:postcode":"43227",
    "sg:province":"OH",
    "sg:tags":[
        "taxicab"
    ],
    "wof:name":"Blue Cab",
    "wof:placetype":"venue"
},
  "geometry": {"coordinates":[-82.880978,39.946041],"type":"Point"}
}