{
  "type": "Feature",
  "properties": {
    "iso:country":"US",
    "sg:address":"2692 Saville Row",
    "sg:city":"Columbus",
    "sg:classifiers":[
        {
            "category":"Professional",
            "type":"Services"
        }
    ],
    "sg:phone":"+1 614 476 4904",
    "sg:postcode":"43224",
    "sg:province":"OH",
    "sg:tags":[
        "establishment"
    ],
    "wof:name":"Carter & Carter",
    "wof:placetype":"venue"
},
  "geometry": {"coordinates":[-82.944373,40.053656],"type":"Point"}
}