{
  "type": "Feature",
  "properties": {
    "addr:full": "4300 Elida Rd Lima OH 45807",
    "addr:postcode": "4300;45807",
    "addr:street": "Elida Rd",
    "iso:country": "US",
    "sg:address": "4300 Elida Rd",
    "sg:city": "Lima",
    "sg:classifiers": [
      {
        "category": "Retail",
        "subcategory": "Portrait Studio",
        "type": "Services"
      }
    ],
    "sg:phone": "+1 419 222 0077",
    "sg:postcode": "45807",
    "sg:province": "OH",
    "sg:tags": [
      "photographer"
    ],
    "wof:name": "Fisher Photography",
    "wof:placetype": "venue"
  },
  "geometry": {"coordinates":[-84.181493,40.778251],"type":"Point"}
}
