{
  "type": "Feature",
  "properties": {
    "iso:country":"US",
    "sg:address":"615 Liverpool Dr",
    "sg:city":"Valley City",
    "sg:classifiers":[
        {
            "category":"Manufacturing",
            "subcategory":"Metals",
            "type":"Manufacturing & Wholesale Goods"
        }
    ],
    "sg:phone":"+1 330 225 7741",
    "sg:postcode":"44280",
    "sg:province":"OH",
    "sg:tags":[
        "steel"
    ],
    "sg:website":"www.independentsteel.com",
    "wof:name":"Independent Steel Co",
    "wof:placetype":"venue"
},
  "geometry": {"coordinates":[-81.891665,41.257509],"type":"Point"}
}