{
  "type": "Feature",
  "properties": {
    "addr:full": "8192 Salineville Rd NE Salineville OH 43945",
    "addr:housenumber": "8192",
    "addr:postcode": "43945",
    "addr:street": "Salineville Rd Ne",
    "iso:country": "US",
    "sg:address": "8192 Salineville Rd NE",
    "sg:city": "Salineville",
    "sg:classifiers": [
      {
        "category": "Farming",
        "subcategory": "Dairy Farm",
        "type": "Manufacturing \u0026 Wholesale Goods"
      }
    ],
    "sg:phone": "+1 330 738 5175",
    "sg:postcode": "43945",
    "sg:province": "OH",
    "wof:name": "Stevens Farm",
    "wof:placetype": "venue"
  },
  "geometry": {"coordinates":[-80.926966,40.619247],"type":"Point"}
}
