{
  "type": "Feature",
  "properties": {
    "addr:full": "8052 State St Garrettsville OH 44231",
    "addr:housenumber": "8052",
    "addr:postcode": "44231",
    "addr:street": "State St",
    "iso:country": "US",
    "sg:address": "8052 State St",
    "sg:city": "Garrettsville",
    "sg:classifiers": [
      {
        "category": "Wholesale",
        "subcategory": "Metals \u0026 Minerals",
        "type": "Manufacturing \u0026 Wholesale Goods"
      }
    ],
    "sg:phone": "+1 330 527 2568",
    "sg:postcode": "44231",
    "sg:province": "OH",
    "sg:tags": [
      "copper",
      "product"
    ],
    "sg:website": "www.wmwa.net",
    "wof:name": "Williams Metals \u0026 Welding",
    "wof:placetype": "venue"
  },
  "geometry": {"coordinates":[-81.099156,41.28546],"type":"Point"}
}
