{
  "type": "Feature",
  "properties": {
    "addr:full":"8052 State St Garrettsville OH 44231",
    "addr:housenumber":"8052",
    "addr:postcode":"44231",
    "addr:street":"State St",
    "iso:country":"US",
    "sg:address":"8052 State St",
    "sg:city":"Garrettsville",
    "sg:classifiers":[
        {
            "category":"Wholesale",
            "subcategory":"Metals & Minerals",
            "type":"Manufacturing & Wholesale Goods"
        }
    ],
    "sg:phone":"+1 330 527 2568",
    "sg:postcode":"44231",
    "sg:province":"OH",
    "sg:tags":[
        "copper",
        "product"
    ],
    "sg:website":"www.wmwa.net",
    "wof:name":"Williams Metals & Welding",
    "wof:placetype":"venue"
},
  "geometry": {"coordinates":[-81.09915599999999,41.28546],"type":"Point"}
}