{
  "type": "Feature",
  "properties": {
    "iso:country":"US",
    "sg:address":"125 Clark Ave",
    "sg:city":"Piqua",
    "sg:classifiers":[
        {
            "category":"Manufacturing",
            "subcategory":"Tools & Machinery",
            "type":"Manufacturing & Wholesale Goods"
        }
    ],
    "sg:phone":"+1 937 615 9243",
    "sg:postcode":"45356",
    "sg:province":"OH",
    "sg:tags":[
        "machine",
        "shop"
    ],
    "wof:name":"Axis Machine & Tool",
    "wof:placetype":"venue"
},
  "geometry": {"coordinates":[-84.240184,40.135317],"type":"Point"}
}