{
  "type": "Feature",
  "properties": {
    "addr:full": "125 Clark Ave Piqua OH 45356",
    "addr:housenumber": "125",
    "addr:postcode": "45356",
    "addr:street": "Clark Ave",
    "iso:country": "US",
    "sg:address": "125 Clark Ave",
    "sg:city": "Piqua",
    "sg:classifiers": [
      {
        "category": "Manufacturing",
        "subcategory": "Tools \u0026 Machinery",
        "type": "Manufacturing \u0026 Wholesale Goods"
      }
    ],
    "sg:phone": "+1 937 615 9243",
    "sg:postcode": "45356",
    "sg:province": "OH",
    "sg:tags": [
      "machine",
      "shop"
    ],
    "wof:name": "Axis Machine \u0026 Tool",
    "wof:placetype": "venue"
  },
  "geometry": {"coordinates":[-84.240184,40.135317],"type":"Point"}
}
