{
  "type": "Feature",
  "properties": {
    "iso:country":"US",
    "sg:address":"200 E Campus View Blvd",
    "sg:city":"Columbus",
    "sg:classifiers":[
        {
            "category":"Professional",
            "subcategory":"Management & Consulting",
            "type":"Services"
        }
    ],
    "sg:phone":"+1 614 842 9285",
    "sg:postcode":"43235",
    "sg:province":"OH",
    "wof:name":"Infocision Management",
    "wof:placetype":"venue"
},
  "geometry": {"coordinates":[-83.01340999999999,40.118272],"type":"Point"}
}