{
  "type": "Feature",
  "properties": {
    "addr:full": "1162 Heyl Rd Wooster OH 44691",
    "addr:housenumber": "1162",
    "addr:postcode": "44691",
    "addr:street": "Heyl Rd",
    "iso:country": "US",
    "sg:address": "1162 Heyl Rd",
    "sg:city": "Wooster",
    "sg:phone": "+1 330 264 5853",
    "sg:postcode": "44691",
    "sg:province": "OH",
    "sg:tags": [
      "farm",
      "field",
      "crop",
      "soybean"
    ],
    "wof:name": "Donald J Varns",
    "wof:placetype": "venue"
  },
  "geometry": {"coordinates":[-81.96149,40.784617],"type":"Point"}
}
