{
  "type": "Feature",
  "properties": {
    "iso:country":"US",
    "sg:address":"2099 Temple Rd",
    "sg:city":"Bucyrus",
    "sg:classifiers":[
        {
            "category":"Farming",
            "subcategory":"Livestock Farm",
            "type":"Manufacturing & Wholesale Goods"
        }
    ],
    "sg:phone":"+1 419 562 2947",
    "sg:postcode":"44820",
    "sg:province":"OH",
    "sg:tags":[
        "beef",
        "f",
        "corn",
        "soybean",
        "cattle",
        "feedlot"
    ],
    "wof:name":"Stahl John",
    "wof:placetype":"venue"
},
  "geometry": {"coordinates":[-83.008864,40.877548],"type":"Point"}
}