{
  "type": "Feature",
  "properties": {
    "iso:country":"US",
    "sg:address":"184 Brush Rd",
    "sg:city":"Cleveland",
    "sg:classifiers":[
        {
            "category":"Building & Trades",
            "subcategory":"Plumbing",
            "type":"Services"
        }
    ],
    "sg:phone":"+1 216 731 1828",
    "sg:postcode":"44143",
    "sg:province":"OH",
    "sg:tags":[
        "contractor"
    ],
    "wof:name":"Tonys Heating",
    "wof:placetype":"venue"
},
  "geometry": {"coordinates":[-81.495057,41.579642],"type":"Point"}
}