{
  "type": "Feature",
  "properties": {
    "iso:country":"US",
    "sg:address":"2744 State Rte 669",
    "sg:city":"Somerset",
    "sg:classifiers":[
        {
            "category":"Real Estate",
            "subcategory":"Real Estate Agent",
            "type":"Services"
        }
    ],
    "sg:phone":"+1 740 743 2304",
    "sg:postcode":"43783",
    "sg:province":"OH",
    "wof:name":"GE Hankison & Assocs",
    "wof:placetype":"venue"
},
  "geometry": {"coordinates":[-82.270179,39.796502],"type":"Point"}
}