{
  "type": "Feature",
  "properties": {
    "iso:country":"US",
    "sg:address":"5025 Monroe St",
    "sg:city":"Toledo",
    "sg:classifiers":[
        {
            "category":"Food & Beverages",
            "subcategory":"Specialty",
            "type":"Retail Goods"
        }
    ],
    "sg:phone":"+1 419 475 1186",
    "sg:postcode":"43606",
    "sg:province":"OH",
    "sg:tags":[
        "vitamin"
    ],
    "sg:website":"www.vitaminshoppe.com",
    "wof:name":"Vitamin Shoppe",
    "wof:placetype":"venue"
},
  "geometry": {"coordinates":[-83.64131,41.697409],"type":"Point"}
}