{
  "type": "Feature",
  "properties": {
    "addr:full": "1325 Mabert Rd Portsmouth OH 45662",
    "addr:housenumber": "1325",
    "addr:postcode": "45662",
    "addr:street": "Mabert Rd",
    "iso:country": "US",
    "sg:address": "1325 Mabert Rd",
    "sg:city": "Portsmouth",
    "sg:classifiers": [
      {
        "category": "Organizations",
        "subcategory": "Religious Organization",
        "type": "Services"
      }
    ],
    "sg:phone": "+1 740 354 4711",
    "sg:postcode": "45662",
    "sg:province": "OH",
    "sg:tags": [
      "church"
    ],
    "wof:name": "Mabert Road Baptist Church",
    "wof:placetype": "venue"
  },
  "geometry": {"coordinates":[-82.964924,38.741708],"type":"Point"}
}
