{
  "type": "Feature",
  "properties": {
    "addr:full": "403 Broadway Ave Bedford OH 44146",
    "addr:housenumber": "403",
    "addr:postcode": "44146",
    "addr:street": "Broadway Ave",
    "iso:country": "US",
    "sg:address": "403 Broadway Ave",
    "sg:city": "Bedford",
    "sg:classifiers": [
      {
        "category": "Insurance",
        "subcategory": "Insurance Agent",
        "type": "Services"
      }
    ],
    "sg:phone": "+1 440 232 4127",
    "sg:postcode": "44146",
    "sg:province": "OH",
    "wof:name": "State Farm Insurance",
    "wof:placetype": "venue"
  },
  "geometry": {"coordinates":[-81.543632,41.398258],"type":"Point"}
}
