{
  "type": "Feature",
  "properties": {
    "addr:full": "174 Marsden Ave SW Canton OH 44710",
    "addr:housenumber": "174",
    "addr:postcode": "44710",
    "addr:street": "Marsden Ave Sw",
    "iso:country": "US",
    "sg:address": "174 Marsden Ave SW",
    "sg:city": "Canton",
    "sg:classifiers": [
      {
        "category": "Building \u0026 Trades",
        "subcategory": "Construction",
        "type": "Services"
      }
    ],
    "sg:phone": "+1 330 479 1809",
    "sg:postcode": "44710",
    "sg:province": "OH",
    "sg:tags": [
      "contractor"
    ],
    "wof:name": "M\u0026D Drywall",
    "wof:placetype": "venue"
  },
  "geometry": {"coordinates":[-81.435813,40.793313],"type":"Point"}
}
