{
  "type": "Feature",
  "properties": {
    "iso:country":"US",
    "sg:address":"174 Marsden Ave SW",
    "sg:city":"Canton",
    "sg:classifiers":[
        {
            "category":"Building & Trades",
            "subcategory":"Construction",
            "type":"Services"
        }
    ],
    "sg:phone":"+1 330 479 1809",
    "sg:postcode":"44710",
    "sg:province":"OH",
    "sg:tags":[
        "contractor"
    ],
    "wof:name":"M&D Drywall",
    "wof:placetype":"venue"
},
  "geometry": {"coordinates":[-81.435813,40.793313],"type":"Point"}
}