{
  "type": "Feature",
  "properties": {
    "addr:full":"2020 Sherman Ave Cincinnati OH 45212",
    "addr:housenumber":"2020",
    "addr:postcode":"45212",
    "addr:street":"Sherman Ave",
    "iso:country":"US",
    "sg:address":"2020 Sherman Ave",
    "sg:city":"Cincinnati",
    "sg:classifiers":[
        {
            "category":"Education",
            "subcategory":"School",
            "type":"Public Place"
        }
    ],
    "sg:phone":"+1 513 924 2885",
    "sg:postcode":"45212",
    "sg:province":"OH",
    "wof:name":"Norwood City Schools Cafeteria",
    "wof:placetype":"venue"
},
  "geometry": {"coordinates":[-84.460989,39.160865],"type":"Point"}
}