{
  "type": "Feature",
  "properties": {
    "iso:country":"US",
    "sg:address":"2925 Kenlo Woods Dr",
    "sg:city":"Nashport",
    "sg:classifiers":[
        {
            "category":"Real Estate",
            "subcategory":"Surveying",
            "type":"Services"
        }
    ],
    "sg:phone":"+1 740 454 1029",
    "sg:postcode":"43830",
    "sg:province":"OH",
    "sg:tags":[
        "surveyor"
    ],
    "wof:name":"Richard M Graves Co",
    "wof:placetype":"venue"
},
  "geometry": {"coordinates":[-82.042012,40.045307],"type":"Point"}
}