{
  "type": "Feature",
  "properties": {
    "iso:country":"US",
    "sg:address":"921 N Main St",
    "sg:city":"Bowling Green",
    "sg:classifiers":[
        {
            "category":"Autos & Motor Vehicles",
            "subcategory":"Automobile Sales",
            "type":"Retail Goods"
        }
    ],
    "sg:phone":"+1 419 352 5151",
    "sg:postcode":"43402",
    "sg:province":"OH",
    "sg:tags":[
        "new",
        "used"
    ],
    "wof:name":"Al Smith Plymouth",
    "wof:placetype":"venue"
},
  "geometry": {"coordinates":[-83.650525,41.384436],"type":"Point"}
}