{
  "type": "Feature",
  "properties": {
    "iso:country":"US",
    "sg:address":"6517 E Livingston Ave",
    "sg:city":"Reynoldsburg",
    "sg:classifiers":[
        {
            "category":"Restaurant",
            "type":"Food & Drink"
        }
    ],
    "sg:phone":"+1 614 863 2828",
    "sg:postcode":"43068",
    "sg:province":"OH",
    "sg:tags":[
        "specializing",
        "eating",
        "chinese"
    ],
    "wof:name":"Sun Tong Luck Tea Hse Restrnt",
    "wof:placetype":"venue"
},
  "geometry": {"coordinates":[-82.821325,39.942768],"type":"Point"}
}