{
  "type": "Feature",
  "properties": {
    "addr:full": "825 Scholz Dr Vandalia OH 45377",
    "addr:housenumber": "825",
    "addr:postcode": "45377",
    "addr:street": "Scholz Dr",
    "iso:country": "US",
    "sg:address": "825 Scholz Dr",
    "sg:city": "Vandalia",
    "sg:classifiers": [
      {
        "category": "Manufacturing",
        "subcategory": "Metals",
        "type": "Manufacturing \u0026 Wholesale Goods"
      },
      {
        "category": "Manufacturing",
        "subcategory": "Tools \u0026 Machinery",
        "type": "Manufacturing \u0026 Wholesale Goods"
      }
    ],
    "sg:phone": "+1 937 898 5786",
    "sg:postcode": "45377",
    "sg:province": "OH",
    "sg:tags": [
      "machine",
      "product",
      "production",
      "grinding",
      "mfg"
    ],
    "sg:website": "www.valmacind.com",
    "wof:name": "Valmac Industries Inc",
    "wof:placetype": "venue"
  },
  "geometry": {"coordinates":[-84.181229,39.882116],"type":"Point"}
}
