{
  "type": "Feature",
  "properties": {
    "iso:country":"US",
    "sg:address":"825 Scholz Dr",
    "sg:city":"Vandalia",
    "sg:classifiers":[
        {
            "category":"Manufacturing",
            "subcategory":"Metals",
            "type":"Manufacturing & Wholesale Goods"
        },
        {
            "category":"Manufacturing",
            "subcategory":"Tools & Machinery",
            "type":"Manufacturing & Wholesale Goods"
        }
    ],
    "sg:phone":"+1 937 898 5786",
    "sg:postcode":"45377",
    "sg:province":"OH",
    "sg:tags":[
        "machine",
        "product",
        "production",
        "grinding",
        "mfg"
    ],
    "sg:website":"www.valmacind.com",
    "wof:name":"Valmac Industries Inc",
    "wof:placetype":"venue"
},
  "geometry": {"coordinates":[-84.181229,39.882116],"type":"Point"}
}