{
  "type": "Feature",
  "properties": {
    "addr:full":"1740 Cooper Foster Park Rd W Lorain OH 44053",
    "addr:housenumber":"1740",
    "addr:postcode":"44053",
    "addr:street":"Cooper Foster Park Rd W",
    "iso:country":"US",
    "sg:address":"1740 Cooper Foster Park Rd W",
    "sg:city":"Lorain",
    "sg:classifiers":[
        {
            "category":"Health Services",
            "subcategory":"Chiropractor",
            "type":"Services"
        }
    ],
    "sg:phone":"+1 440 960 0100",
    "sg:postcode":"44053",
    "sg:province":"OH",
    "wof:name":"Salas Chiropractic",
    "wof:placetype":"venue"
},
  "geometry": {"coordinates":[-82.258793,41.407503],"type":"Point"}
}