{
  "type": "Feature",
  "properties": {
    "iso:country":"US",
    "sg:address":"38 N Broadway St",
    "sg:city":"Farmersville",
    "sg:classifiers":[
        {
            "category":"Banks & Credit Unions",
            "subcategory":"Bank",
            "type":"Services"
        }
    ],
    "sg:phone":"+1 937 696 2303",
    "sg:postcode":"45325",
    "sg:province":"OH",
    "sg:tags":[
        "national"
    ],
    "wof:name":"Firstar Bank",
    "wof:placetype":"venue"
},
  "geometry": {"coordinates":[-84.425349,39.680042],"type":"Point"}
}