{
  "type": "Feature",
  "properties": {
    "addr:full": "38 N Broadway St Farmersville OH 45325",
    "addr:housenumber": "38",
    "addr:postcode": "45325",
    "addr:street": "N Broadway St",
    "iso:country": "US",
    "sg:address": "38 N Broadway St",
    "sg:city": "Farmersville",
    "sg:classifiers": [
      {
        "category": "Banks \u0026 Credit Unions",
        "subcategory": "Bank",
        "type": "Services"
      }
    ],
    "sg:phone": "+1 937 696 2303",
    "sg:postcode": "45325",
    "sg:province": "OH",
    "sg:tags": [
      "national"
    ],
    "wof:name": "Firstar Bank",
    "wof:placetype": "venue"
  },
  "geometry": {"coordinates":[-84.425349,39.680042],"type":"Point"}
}
