{
  "type": "Feature",
  "properties": {
    "addr:full": "2858 W Sylvania Ave Toledo OH 43613",
    "addr:housenumber": "2858",
    "addr:postcode": "43613",
    "addr:street": "W Sylvania Ave",
    "iso:country": "US",
    "sg:address": "2858 W Sylvania Ave",
    "sg:city": "Toledo",
    "sg:classifiers": [
      {
        "category": "Shopping",
        "type": "Retail Goods"
      }
    ],
    "sg:phone": "+1 419 472 4959",
    "sg:postcode": "43613",
    "sg:province": "OH",
    "sg:tags": [
      "eating",
      "merchandise"
    ],
    "wof:name": "Cake Arts Supplies \u0026 Bakery",
    "wof:placetype": "venue"
  },
  "geometry": {"coordinates":[-83.612902,41.692066],"type":"Point"}
}
