{
  "type": "Feature",
  "properties": {
    "iso:country":"US",
    "sg:address":"4265 Pennyroyal Rd",
    "sg:city":"Franklin",
    "sg:classifiers":[
        {
            "category":"Retail",
            "subcategory":"Animal Services",
            "type":"Services"
        }
    ],
    "sg:phone":"+1 937 743 9956",
    "sg:postcode":"45005",
    "sg:province":"OH",
    "sg:tags":[
        "pet",
        "boarding",
        "sitting"
    ],
    "wof:name":"Dog Lady's Pet Camp",
    "wof:placetype":"venue"
},
  "geometry": {"coordinates":[-84.257655,39.580072],"type":"Point"}
}