{
  "type": "Feature",
  "properties": {
    "iso:country":"US",
    "sg:address":"820 Ludlow Rd",
    "sg:city":"Bellefontaine",
    "sg:classifiers":[
        {
            "category":"Education",
            "subcategory":"School",
            "type":"Public Place"
        }
    ],
    "sg:phone":"+1 937 593 9060",
    "sg:postcode":"43311",
    "sg:province":"OH",
    "sg:website":"www.bellefontaine.k12.oh.us",
    "wof:name":"Bellefontaine School District",
    "wof:placetype":"venue"
},
  "geometry": {"coordinates":[-83.750173,40.350012],"type":"Point"}
}