{
  "type": "Feature",
  "properties": {
    "iso:country":"US",
    "sg:address":"3544 Brookside Rd",
    "sg:city":"Ottawa Hills",
    "sg:classifiers":[
        {
            "category":"Health Services",
            "subcategory":"Optometrist",
            "type":"Services"
        }
    ],
    "sg:phone":"+1 419 893 6841",
    "sg:postcode":"43606",
    "sg:province":"OH",
    "wof:name":"Lifetime Vision Care Ctr",
    "wof:placetype":"venue"
},
  "geometry": {"coordinates":[-83.63091799999999,41.66609],"type":"Point"}
}