{
  "type": "Feature",
  "properties": {
    "addr:full": "3544 Brookside Rd Ottawa Hills OH 43606",
    "addr:housenumber": "3544",
    "addr:postcode": "43606",
    "addr:street": "Brookside Rd",
    "iso:country": "US",
    "sg:address": "3544 Brookside Rd",
    "sg:city": "Ottawa Hills",
    "sg:classifiers": [
      {
        "category": "Health Services",
        "subcategory": "Optometrist",
        "type": "Services"
      }
    ],
    "sg:phone": "+1 419 893 6841",
    "sg:postcode": "43606",
    "sg:province": "OH",
    "wof:name": "Lifetime Vision Care Ctr",
    "wof:placetype": "venue"
  },
  "geometry": {"coordinates":[-83.630918,41.66609],"type":"Point"}
}
