{
  "type": "Feature",
  "properties": {
    "addr:full": "4110 Bridlegate Way Dayton OH 45424",
    "addr:postcode": "4110;45424",
    "addr:street": "Bridlegate Way",
    "iso:country": "US",
    "sg:address": "4110 Bridlegate Way",
    "sg:city": "Dayton",
    "sg:classifiers": [
      {
        "category": "Building \u0026 Trades",
        "subcategory": "Landscaping Services",
        "type": "Services"
      }
    ],
    "sg:phone": "+1 937 684 3190",
    "sg:postcode": "45424",
    "sg:province": "OH",
    "sg:tags": [
      "landscape"
    ],
    "wof:name": "Whispering Creek",
    "wof:placetype": "venue"
  },
  "geometry": {"coordinates":[-84.110663,39.806656],"type":"Point"}
}
