{
  "type": "Feature",
  "properties": {
    "addr:full": "85 N Columbus St Sunbury OH 43074",
    "addr:housenumber": "85",
    "addr:postcode": "43074",
    "addr:street": "N Columbus St",
    "iso:country": "US",
    "sg:address": "85 N Columbus St",
    "sg:city": "Sunbury",
    "sg:classifiers": [
      {
        "category": "Organizations",
        "subcategory": "Religious Organization",
        "type": "Services"
      }
    ],
    "sg:phone": "+1 740 965 6237",
    "sg:postcode": "43074",
    "sg:province": "OH",
    "sg:tags": [
      "church"
    ],
    "wof:name": "Kicks Club Church",
    "wof:placetype": "venue"
  },
  "geometry": {"coordinates":[-82.85957,40.244903],"type":"Point"}
}
