{
  "type": "Feature",
  "properties": {
    "addr:full":"7940 Springledge Rd Northfield OH 44067",
    "addr:housenumber":"7940",
    "addr:postcode":"44067",
    "addr:street":"Springledge Rd",
    "iso:country":"US",
    "sg:address":"7940 Springledge Rd",
    "sg:city":"Northfield",
    "sg:classifiers":[
        {
            "category":"Organizations",
            "subcategory":"Religious Organization",
            "type":"Services"
        }
    ],
    "sg:phone":"+1 330 468 2390",
    "sg:postcode":"44067",
    "sg:province":"OH",
    "sg:tags":[
        "church"
    ],
    "wof:name":"St Andrews Eastrn Orthodox Chr",
    "wof:placetype":"venue"
},
  "geometry": {"coordinates":[-81.549564,41.320596],"type":"Point"}
}