{
  "type": "Feature",
  "properties": {
    "addr:full":"1410 Newark Rd Zanesville OH 43701",
    "addr:housenumber":"1410",
    "addr:postcode":"43701",
    "addr:street":"Newark Rd",
    "iso:country":"US",
    "sg:address":"1410 Newark Rd",
    "sg:city":"Zanesville",
    "sg:classifiers":[
        {
            "category":"Government",
            "subcategory":"Office",
            "type":"Public Place"
        }
    ],
    "sg:phone":"+1 740 452 4940",
    "sg:postcode":"43701",
    "sg:province":"OH",
    "wof:name":"Muskingum County Sewage Dept",
    "wof:placetype":"venue"
},
  "geometry": {"coordinates":[-82.032053,39.959721],"type":"Point"}
}